{
  "type": "Feature",
  "properties": {
    "addr:full":"53 Haig Mactier ON P0C 1H0",
    "addr:housenumber":"53",
    "addr:postcode":"p0c 1h0",
    "addr:street":"Haig Mactier",
    "iso:country":"CA",
    "sg:address":"53 Haig",
    "sg:city":"Mactier",
    "sg:classifiers":[
        {
            "category":"Organizations",
            "subcategory":"Professional Association",
            "type":"Services"
        }
    ],
    "sg:phone":"+1 705 375 0755",
    "sg:postcode":"P0C 1H0",
    "sg:province":"ON",
    "wof:name":"Mac Tier Lions Club",
    "wof:placetype":"venue"
},
  "geometry": {"coordinates":[-79.7719573975,45.1343383789],"type":"Point"}
}