{
  "type": "Feature",
  "properties": {
    "addr:full":"Porcupine Plain SK S0E 1H0",
    "addr:postcode":"s0e 1h0",
    "addr:street":"Porcupine Plain",
    "iso:country":"CA",
    "sg:city":"Porcupine Plain",
    "sg:classifiers":[
        {
            "category":"Food & Beverages",
            "subcategory":"Groceries & Convenience Stores",
            "type":"Retail Goods"
        }
    ],
    "sg:phone":"+1 306 278 2066",
    "sg:postcode":"S0E 1H0",
    "sg:province":"SK",
    "sg:tags":[
        "grocer"
    ],
    "wof:name":"Parkland CO-OP Assoc Ltd",
    "wof:placetype":"venue"
},
  "geometry": {"coordinates":[-103.254333496,52.5980644226],"type":"Point"}
}