{
  "type": "Feature",
  "properties": {
    "addr:full":"3720 Saint Bernard Blossom Pk Ottawa ON K1T 1K8",
    "addr:housenumber":"3720",
    "addr:postcode":"k1t 1k8",
    "addr:street":"Saint Bernard Blossom Pk",
    "iso:country":"CA",
    "sg:address":"3720 Saint Bernard Blossom Pk",
    "sg:city":"Ottawa",
    "sg:classifiers":[
        {
            "category":"Organizations",
            "subcategory":"Religious Organization",
            "type":"Services"
        }
    ],
    "sg:phone":"+1 613 521 0097",
    "sg:postcode":"K1T 1K8",
    "sg:province":"ON",
    "sg:tags":[
        "church"
    ],
    "wof:name":"St Bernards Catholic Church",
    "wof:placetype":"venue"
},
  "geometry": {"coordinates":[-75.69189453120001,45.4215011597],"type":"Point"}
}