{
  "type": "Feature",
  "properties": {
    "addr:full":"68 Carson Dr Hamilton ON L8T 4M4",
    "addr:housenumber":"68",
    "addr:postcode":"l8t 4m4",
    "addr:street":"Carson Dr",
    "iso:country":"CA",
    "sg:address":"68 Carson Dr",
    "sg:city":"Hamilton",
    "sg:classifiers":[
        {
            "category":"Building & Trades",
            "subcategory":"Cleaning & Sanitation",
            "type":"Services"
        }
    ],
    "sg:phone":"+1 905 383 2516",
    "sg:postcode":"L8T 4M4",
    "sg:province":"ON",
    "sg:tags":[
        "window"
    ],
    "wof:name":"Ideal Window Cleaning",
    "wof:placetype":"venue"
},
  "geometry": {"coordinates":[-79.832733,43.209759],"type":"Point"}
}