{
  "type": "Feature",
  "properties": {
    "addr:full":"690 Muskoka Rd S # 1 Gravenhurst ON P1P 1K2",
    "addr:housenumber":"690",
    "addr:postcode":"p1p 1k2",
    "addr:street":"Muskoka Rd S # 1",
    "iso:country":"CA",
    "sg:address":"690 Muskoka Rd S # 1",
    "sg:city":"Gravenhurst",
    "sg:classifiers":[
        {
            "category":"Insurance",
            "subcategory":"Insurance Agent",
            "type":"Services"
        }
    ],
    "sg:phone":"+1 705 687 3451",
    "sg:postcode":"P1P 1K2",
    "sg:province":"ON",
    "wof:name":"Johnston & Assoc Insurance Ltd",
    "wof:placetype":"venue"
},
  "geometry": {"coordinates":[-79.37153625489999,44.9148750305],"type":"Point"}
}