{
  "type": "Feature",
  "properties": {
    "addr:full":"24 Rue Du Firmament Hull QC J9A 3H9",
    "addr:housenumber":"24",
    "addr:postcode":"j9a 3h9",
    "addr:street":"Rue Du Firmament",
    "iso:country":"CA",
    "sg:address":"24 Rue Du Firmament",
    "sg:city":"Hull",
    "sg:classifiers":[
        {
            "category":"Professional",
            "subcategory":"Computer Services",
            "type":"Services"
        }
    ],
    "sg:phone":"+1 819 595 0974",
    "sg:postcode":"J9A 3H9",
    "sg:province":"QC",
    "sg:tags":[
        "internet"
    ],
    "wof:name":"Tds Communications",
    "wof:placetype":"venue"
},
  "geometry": {"coordinates":[-75.7849731445,45.4398231506],"type":"Point"}
}