{
  "type": "Feature",
  "properties": {
    "addr:full":"1450 Birchmount Rd Scarborough ON M1P 2E3",
    "addr:housenumber":"1450",
    "addr:postcode":"m1p 2e3",
    "addr:street":"Birchmount Rd",
    "iso:country":"CA",
    "sg:address":"1450 Birchmount Rd",
    "sg:city":"Scarborough",
    "sg:classifiers":[
        {
            "category":"Manufacturing",
            "subcategory":"Furniture",
            "type":"Manufacturing & Wholesale Goods"
        }
    ],
    "sg:phone":"+1 416 759 5665",
    "sg:postcode":"M1P 2E3",
    "sg:province":"ON",
    "wof:name":"Keilhauer",
    "wof:placetype":"venue"
},
  "geometry": {"coordinates":[-79.287491,43.753586],"type":"Point"}
}