{
  "type": "Feature",
  "properties": {
    "addr:full":"138 Rue Principale Saint-Andre-Avellin QC J0V 1W0",
    "addr:housenumber":"138",
    "addr:postcode":"j0v 1w0",
    "addr:street":"Rue Principale",
    "iso:country":"CA",
    "sg:address":"138 Rue Principale",
    "sg:city":"Saint-Andre-Avellin",
    "sg:classifiers":[
        {
            "category":"Professional",
            "subcategory":"Business Services",
            "type":"Services"
        }
    ],
    "sg:phone":"+1 819 983 2721",
    "sg:postcode":"J0V 1W0",
    "sg:province":"QC",
    "sg:tags":[
        "notary"
    ],
    "wof:name":"Robert Louis Philippe",
    "wof:placetype":"venue"
},
  "geometry": {"coordinates":[-75.05326843260001,45.7262268066],"type":"Point"}
}