{
  "type": "Feature",
  "properties": {
    "addr:full":"69 Ch Kichi Mikan Maniwaki QC J9E 3C3",
    "addr:housenumber":"69",
    "addr:postcode":"j9e 3c3",
    "addr:street":"Ch Kichi Mikan",
    "iso:country":"CA",
    "sg:address":"69 Ch Kichi Mikan",
    "sg:city":"Maniwaki",
    "sg:classifiers":[
        {
            "category":"Taxi",
            "type":"Transportation"
        }
    ],
    "sg:phone":"+1 819 449 3737",
    "sg:postcode":"J9E 3C3",
    "sg:province":"QC",
    "sg:tags":[
        "taxicab"
    ],
    "wof:name":"Chalifoux Hubert Taxi",
    "wof:placetype":"venue"
},
  "geometry": {"coordinates":[-75.9815979004,46.3746795654],"type":"Point"}
}