{
  "type": "Feature",
  "properties": {
    "addr:full":"1345 Morningside Ave #3 Scarborough ON M1B 5K3",
    "addr:housenumber":"1345",
    "addr:postcode":"m1b 5k3",
    "addr:street":"Morningside Ave # 3",
    "iso:country":"CA",
    "sg:address":"1345 Morningside Ave #3",
    "sg:city":"Scarborough",
    "sg:classifiers":[
        {
            "category":"Professional",
            "type":"Services"
        }
    ],
    "sg:phone":"+1 416 282 4756",
    "sg:postcode":"M1B 5K3",
    "sg:province":"ON",
    "sg:tags":[
        "cleaners",
        "establishment",
        "vacuum"
    ],
    "wof:name":"Alpine Installation Svc Ltd",
    "wof:placetype":"venue"
},
  "geometry": {"coordinates":[-79.20146942140001,43.8069915771],"type":"Point"}
}