{
  "type": "Feature",
  "properties": {
    "addr:full":"2605 Alta Vista Dr Ottawa ON K1V 7T3",
    "addr:housenumber":"2605",
    "addr:postcode":"k1v 7t3",
    "addr:street":"Alta Vista Dr",
    "iso:country":"CA",
    "sg:address":"2605 Alta Vista Dr",
    "sg:city":"Ottawa",
    "sg:classifiers":[
        {
            "category":"Social Services",
            "subcategory":"Child Care",
            "type":"Services"
        }
    ],
    "sg:phone":"+1 613 733 0868",
    "sg:postcode":"K1V 7T3",
    "sg:province":"ON",
    "wof:name":"Vista Kindergarten School Age",
    "wof:placetype":"venue"
},
  "geometry": {"coordinates":[-75.66059112550001,45.3759841919],"type":"Point"}
}