{
  "type": "Feature",
  "properties": {
    "addr:full":"Montreal QC H2H 2S6",
    "addr:postcode":"h2h 2s6",
    "iso:country":"CA",
    "sg:city":"Montreal",
    "sg:classifiers":[
        {
            "category":"Wholesale",
            "subcategory":"Machinery & Supplies",
            "type":"Manufacturing & Wholesale Goods"
        }
    ],
    "sg:phone":"+1 514 284 5018",
    "sg:postcode":"H2H 2S6",
    "sg:province":"QC",
    "sg:tags":[
        "salon",
        "beauty"
    ],
    "wof:name":"Pivot Point Coiffure DE Paris",
    "wof:placetype":"venue"
},
  "geometry": {"coordinates":[-73.217377,45.281342],"type":"Point"}
}