{
  "type": "Feature",
  "properties": {
    "addr:full":"3823 Albert St # A Regina SK S4S 3R4",
    "addr:housenumber":"3823",
    "addr:postcode":"s4s 3r4",
    "addr:street":"Albert St # A",
    "iso:country":"CA",
    "sg:address":"3823 Albert St # A",
    "sg:city":"Regina",
    "sg:classifiers":[
        {
            "category":"Home & Garden",
            "subcategory":"Home Furnishings",
            "type":"Retail Goods"
        }
    ],
    "sg:phone":"+1 306 586 7799",
    "sg:postcode":"S4S 3R4",
    "sg:province":"SK",
    "sg:tags":[
        "curtain",
        "made",
        "drapery",
        "cleaners"
    ],
    "wof:name":"Able Venetian Blind & Drapery",
    "wof:placetype":"venue"
},
  "geometry": {"coordinates":[-104.617783,50.418274],"type":"Point"}
}