{
  "type": "Feature",
  "properties": {
    "addr:full":"Bond Head ON L0G 1B0",
    "addr:postcode":"l0g 1b0",
    "addr:street":"Bond",
    "iso:country":"CA",
    "sg:city":"Bond Head",
    "sg:classifiers":[
        {
            "category":"Home & Garden",
            "subcategory":"Furniture",
            "type":"Retail Goods"
        }
    ],
    "sg:phone":"+1 905 775 7144",
    "sg:postcode":"L0G 1B0",
    "sg:province":"ON",
    "sg:tags":[
        "builder",
        "custom"
    ],
    "wof:name":"Bruce Chambers Period Furn Ltd",
    "wof:placetype":"venue"
},
  "geometry": {"coordinates":[-79.67794799799999,44.0895004272],"type":"Point"}
}