{
  "type": "Feature",
  "properties": {
    "addr:full":"99 Park St Chatham ON N7M 3R5",
    "addr:housenumber":"99",
    "addr:postcode":"n7m 3r5",
    "addr:street":"Park St",
    "iso:country":"CA",
    "sg:address":"99 Park St",
    "sg:city":"Chatham",
    "sg:classifiers":[
        {
            "category":"Health Services",
            "subcategory":"Nursing And Care Facility",
            "type":"Services"
        }
    ],
    "sg:phone":"+1 519 354 8103",
    "sg:postcode":"N7M 3R5",
    "sg:province":"ON",
    "sg:tags":[
        "home",
        "retirement",
        "community"
    ],
    "wof:name":"St Andrew's Residence",
    "wof:placetype":"venue"
},
  "geometry": {"coordinates":[-82.1788864136,42.4025650024],"type":"Point"}
}