{
  "type": "Feature",
  "properties": {
    "iso:country":"CA",
    "sg:address":"4020 Boul Saint-Jean",
    "sg:city":"Dollard-Des-Ormeaux",
    "sg:classifiers":[
        {
            "category":"Real Estate",
            "subcategory":"Real Estate Operator",
            "type":"Services"
        }
    ],
    "sg:phone":"+1 514 620 1311",
    "sg:postcode":"H9G 2L6",
    "sg:province":"QC",
    "sg:tags":[
        "apartment"
    ],
    "wof:name":"Summit House",
    "wof:placetype":"venue"
},
  "geometry": {"coordinates":[-73.838417,45.476372],"type":"Point"}
}