{
  "type": "Feature",
  "properties": {
    "addr:full":"20 Main St N Waterdown ON L0R 2H0",
    "addr:housenumber":"20",
    "addr:postcode":"l0r 2h0",
    "addr:street":"Main St N",
    "iso:country":"CA",
    "sg:address":"20 Main St N",
    "sg:city":"Waterdown",
    "sg:classifiers":[
        {
            "category":"Health Services",
            "subcategory":"Doctor",
            "type":"Services"
        }
    ],
    "sg:phone":"+1 905 689 9090",
    "sg:postcode":"L0R 2H0",
    "sg:province":"ON",
    "sg:tags":[
        "dentist"
    ],
    "wof:name":"Despond, Frank T DDS",
    "wof:placetype":"venue"
},
  "geometry": {"coordinates":[-79.89343261720001,43.3339424133],"type":"Point"}
}