{
  "type": "Feature",
  "properties": {
    "addr:full":"490 Longman Cres N Regina SK S4N 6J4",
    "addr:housenumber":"490",
    "addr:postcode":"s4n 6j4",
    "addr:street":"Longman Cres N",
    "iso:country":"CA",
    "sg:address":"490 Longman Cres N",
    "sg:city":"Regina",
    "sg:classifiers":[
        {
            "category":"Manufacturing",
            "subcategory":"Tools & Machinery",
            "type":"Manufacturing & Wholesale Goods"
        }
    ],
    "sg:phone":"+1 306 721 2497",
    "sg:postcode":"S4N 6J4",
    "sg:province":"SK",
    "sg:tags":[
        "equipment",
        "hydraulic",
        "supply"
    ],
    "wof:name":"Park Hydraulic & Machine",
    "wof:placetype":"venue"
},
  "geometry": {"coordinates":[-104.563087,50.482895],"type":"Point"}
}