{
  "type": "Feature",
  "properties": {
    "addr:full":"81 Boul Greber Gatineau QC J8T 3P9",
    "addr:housenumber":"81",
    "addr:postcode":"j8t 3p9",
    "addr:street":"Boul Greber",
    "iso:country":"CA",
    "sg:address":"81 Boul Greber",
    "sg:city":"Gatineau",
    "sg:classifiers":[
        {
            "category":"Retail",
            "subcategory":"Auto Repair",
            "type":"Services"
        }
    ],
    "sg:phone":"+1 819 568 0880",
    "sg:postcode":"J8T 3P9",
    "sg:province":"QC",
    "sg:tags":[
        "repairing",
        "automobile",
        "muffler",
        "system",
        "exhaust"
    ],
    "wof:name":"Mister Muffler",
    "wof:placetype":"venue"
},
  "geometry": {"coordinates":[-75.6998672485,45.4643630981],"type":"Point"}
}