{
  "type": "Feature",
  "properties": {
    "addr:full":"6125 101 Ave NW Edmonton AB T6A 0G9",
    "addr:housenumber":"6125",
    "addr:postcode":"t6a 0g9",
    "addr:street":"101 Ave Nw",
    "iso:country":"CA",
    "sg:address":"6125 101 Ave NW",
    "sg:city":"Edmonton",
    "sg:classifiers":[
        {
            "category":"Autos & Motor Vehicles",
            "subcategory":"Fuel & Gas Station",
            "type":"Retail Goods"
        }
    ],
    "sg:phone":"+1 780 468 7659",
    "sg:postcode":"T6A 0G9",
    "sg:province":"AB",
    "sg:tags":[
        "oil"
    ],
    "wof:name":"Capilano Mohawk",
    "wof:placetype":"venue"
},
  "geometry": {"coordinates":[-113.42649078399999,53.5410766602],"type":"Point"}
}