{
  "type": "Feature",
  "properties": {
    "addr:full":"16 King St St Stephen NB E3L 2B9",
    "addr:housenumber":"16",
    "addr:postcode":"nb e3l 2b9",
    "addr:street":"King St",
    "iso:country":"CA",
    "sg:address":"16 King St",
    "sg:city":"St Stephen",
    "sg:classifiers":[
        {
            "category":"Autos & Motor Vehicles",
            "subcategory":"Auto Supplies",
            "type":"Retail Goods"
        }
    ],
    "sg:phone":"+1 506 466 2333",
    "sg:postcode":"E3L 2B9",
    "sg:province":"NB",
    "sg:tags":[
        "automobile",
        "parts"
    ],
    "wof:name":"Uap Napa Auto Parts",
    "wof:placetype":"venue"
},
  "geometry": {"coordinates":[-67.27597799999999,45.19305],"type":"Point"}
}