{
  "type": "Feature",
  "properties": {
    "addr:full":"3630 16th Ave W Vancouver BC V6R 3C4",
    "addr:housenumber":"3630",
    "addr:postcode":"v6r 3c4",
    "addr:street":"16Th Ave W",
    "iso:country":"CA",
    "sg:address":"3630 16th Ave W",
    "sg:city":"Vancouver",
    "sg:classifiers":[
        {
            "category":"Restaurant",
            "type":"Food & Drink"
        }
    ],
    "sg:phone":"+1 604 707 0770",
    "sg:postcode":"V6R 3C4",
    "sg:province":"BC",
    "sg:tags":[
        "out"
    ],
    "wof:name":"York Fresh Pizza",
    "wof:placetype":"venue"
},
  "geometry": {"coordinates":[-123.185699,49.257702],"type":"Point"}
}