{
  "type": "Feature",
  "properties": {
    "addr:full":"4573 Rue Sherbrooke O Westmount QC H3Z 1E9",
    "addr:housenumber":"4573",
    "addr:postcode":"h3z 1e9",
    "addr:street":"Rue Sherbrooke O",
    "iso:country":"CA",
    "sg:address":"4573 Rue Sherbrooke O",
    "sg:city":"Westmount",
    "sg:classifiers":[
        {
            "category":"Health Services",
            "subcategory":"Doctor",
            "type":"Services"
        }
    ],
    "sg:phone":"+1 514 933 4336",
    "sg:postcode":"H3Z 1E9",
    "sg:province":"QC",
    "sg:tags":[
        "physician",
        "surgeon"
    ],
    "wof:name":"Calles, J F MD",
    "wof:placetype":"venue"
},
  "geometry": {"coordinates":[-73.6000289917,45.4821853638],"type":"Point"}
}