{
  "type": "Feature",
  "properties": {
    "iso:country":"CA",
    "sg:address":"966 Ghislain St",
    "sg:city":"Hawkesbury",
    "sg:classifiers":[
        {
            "category":"Building & Trades",
            "subcategory":"Construction",
            "type":"Services"
        }
    ],
    "sg:phone":"+1 613 632 8122",
    "sg:postcode":"K6A 3B2",
    "sg:province":"ON",
    "sg:tags":[
        "roofing",
        "contractor"
    ],
    "wof:name":"J Sylvain Roofing & Plastering",
    "wof:placetype":"venue"
},
  "geometry": {"coordinates":[-74.6117095947,45.5999641418],"type":"Point"}
}