{
  "type": "Feature",
  "properties": {
    "addr:full":"1110 Cotton Dr Vancouver BC V5L 3T5",
    "addr:housenumber":"1110",
    "addr:postcode":"v5l 3t5",
    "addr:street":"Cotton Dr",
    "iso:country":"CA",
    "sg:address":"1110 Cotton Dr",
    "sg:city":"Vancouver",
    "sg:classifiers":[
        {
            "category":"Education",
            "subcategory":"School",
            "type":"Public Place"
        }
    ],
    "sg:phone":"+1 604 713 4497",
    "sg:postcode":"V5L 3T5",
    "sg:province":"BC",
    "wof:name":"Britannia Elementary School",
    "wof:placetype":"venue"
},
  "geometry": {"coordinates":[-123.071404,49.2743],"type":"Point"}
}