{
  "type": "Feature",
  "properties": {
    "addr:full":"118 1E Av E Saint-Martin QC G0M 1B0",
    "addr:housenumber":"118",
    "addr:postcode":"g0m 1b0",
    "addr:street":"1E Av E Saint-Martin",
    "iso:country":"CA",
    "sg:address":"118 1E Av E",
    "sg:city":"Saint-Martin",
    "sg:classifiers":[
        {
            "category":"Shopping",
            "subcategory":"Clothing, Apparel, & Fashions",
            "type":"Retail Goods"
        }
    ],
    "sg:phone":"+1 418 382 3040",
    "sg:postcode":"G0M 1B0",
    "sg:province":"QC",
    "wof:name":"Chez Francoise Enr",
    "wof:placetype":"venue"
},
  "geometry": {"coordinates":[-70.6564331055,45.9592018127],"type":"Point"}
}