{
  "type": "Feature",
  "properties": {
    "iso:country":"CA",
    "sg:address":"3300 Boul DE Portland",
    "sg:city":"Sherbrooke",
    "sg:classifiers":[
        {
            "category":"Home & Garden",
            "subcategory":"Home Furnishings",
            "type":"Retail Goods"
        }
    ],
    "sg:phone":"+1 819 569 5989",
    "sg:postcode":"J1L 2A6",
    "sg:province":"QC",
    "sg:tags":[
        "shop",
        "made",
        "fabric",
        "drapery"
    ],
    "wof:name":"Bou Clair Maison DE Tissus",
    "wof:placetype":"venue"
},
  "geometry": {"coordinates":[-71.9566040039,45.4030075073],"type":"Point"}
}