{
  "type": "Feature",
  "properties": {
    "addr:full":"20267 Menzies Rd Pitt Meadows BC V3Y 2T9",
    "addr:housenumber":"20267",
    "addr:postcode":"v3y 2t9",
    "addr:street":"Menzies Rd",
    "iso:country":"CA",
    "sg:address":"20267 Menzies Rd",
    "sg:city":"Pitt Meadows",
    "sg:classifiers":[
        {
            "category":"Building & Trades",
            "subcategory":"Construction",
            "type":"Services"
        }
    ],
    "sg:phone":"+1 604 465 4649",
    "sg:postcode":"V3Y 2T9",
    "sg:province":"BC",
    "sg:tags":[
        "excavating",
        "contractor"
    ],
    "wof:name":"Nol Griffioen Enterprises",
    "wof:placetype":"venue"
},
  "geometry": {"coordinates":[-122.658829,49.27861],"type":"Point"}
}