{
  "type": "Feature",
  "properties": {
    "addr:full":"Humboldt SK S0K 2A0",
    "addr:postcode":"s0k 2a0",
    "addr:street":"Humboldt",
    "iso:country":"CA",
    "sg:city":"Humboldt",
    "sg:classifiers":[
        {
            "category":"Retail",
            "subcategory":"Auto Repair",
            "type":"Services"
        }
    ],
    "sg:phone":"+1 306 231 7477",
    "sg:postcode":"S0K 2A0",
    "sg:province":"SK",
    "sg:tags":[
        "wrecker"
    ],
    "wof:name":"Select Towing",
    "wof:placetype":"venue"
},
  "geometry": {"coordinates":[-105.12429,52.199184],"type":"Point"}
}