{
  "type": "Feature",
  "properties": {
    "addr:full":"60 Centennial Pky N Hamilton ON L8E 1H6",
    "addr:housenumber":"60",
    "addr:postcode":"l8e 1h6",
    "addr:street":"Centennial Pky N",
    "iso:country":"CA",
    "sg:address":"60 Centennial Pky N",
    "sg:city":"Hamilton",
    "sg:classifiers":[
        {
            "category":"Government",
            "subcategory":"Office",
            "type":"Public Place"
        }
    ],
    "sg:phone":"+1 905 546 3750",
    "sg:postcode":"L8E 1H6",
    "sg:province":"ON",
    "sg:tags":[
        "village"
    ],
    "wof:name":"Stoney Creek Sexual Health Svc",
    "wof:placetype":"venue"
},
  "geometry": {"coordinates":[-79.76335899999999,43.229736],"type":"Point"}
}