{
  "type": "Feature",
  "properties": {
    "addr:full":"147 Rue Principale N Saint-Pamphile QC G0R 3X0",
    "addr:housenumber":"147",
    "addr:postcode":"g0r 3x0",
    "addr:street":"Rue Principale N",
    "iso:country":"CA",
    "sg:address":"147 Rue Principale N",
    "sg:city":"Saint-Pamphile",
    "sg:classifiers":[
        {
            "category":"Retail",
            "subcategory":"Repair Shop",
            "type":"Services"
        }
    ],
    "sg:phone":"+1 418 356 5811",
    "sg:postcode":"G0R 3X0",
    "sg:province":"QC",
    "sg:tags":[
        "repairing",
        "boot",
        "shoe",
        "upholsterer"
    ],
    "wof:name":"Lebel Vallier",
    "wof:placetype":"venue"
},
  "geometry": {"coordinates":[-69.78175354,46.9626426697],"type":"Point"}
}