{
  "type": "Feature",
  "properties": {
    "addr:full":"1144 Narrow Locks Rd Portland ON K0G 1V0",
    "addr:housenumber":"1144",
    "addr:postcode":"k0g 1v0",
    "addr:street":"Narrow Locks Rd",
    "iso:country":"CA",
    "sg:address":"1144 Narrow Locks Rd",
    "sg:city":"Portland",
    "sg:classifiers":[
        {
            "category":"Travel",
            "subcategory":"Campground",
            "type":"Entertainment"
        }
    ],
    "sg:phone":"+1 613 272 3401",
    "sg:postcode":"K0G 1V0",
    "sg:province":"ON",
    "sg:tags":[
        "camp"
    ],
    "wof:name":"Narrows Lock Campground",
    "wof:placetype":"venue"
},
  "geometry": {"coordinates":[-76.1882095337,44.698425293],"type":"Point"}
}