{
  "type": "Feature",
  "properties": {
    "addr:full":"Beauport QC G1C 1A4",
    "addr:postcode":"qc g1c 1a4",
    "iso:country":"CA",
    "sg:city":"Beauport",
    "sg:classifiers":[
        {
            "category":"Personal",
            "subcategory":"Beauty Salon",
            "type":"Services"
        }
    ],
    "sg:phone":"+1 418 660 0059",
    "sg:postcode":"G1C 1A4",
    "sg:province":"QC",
    "wof:name":"Coiffure Image Innee",
    "wof:placetype":"venue"
},
  "geometry": {"coordinates":[-71.2170715332,46.8900108337],"type":"Point"}
}