{
  "type": "Feature",
  "properties": {
    "addr:full":"308 Catherine St Victoria BC V9A 3S8",
    "addr:housenumber":"308",
    "addr:postcode":"v9a 3s8",
    "addr:street":"Catherine St",
    "iso:country":"CA",
    "sg:address":"308 Catherine St",
    "sg:city":"Victoria",
    "sg:classifiers":[
        {
            "category":"Manufacturing",
            "subcategory":"Food",
            "type":"Manufacturing & Wholesale Goods"
        }
    ],
    "sg:phone":"+1 250 386 2739",
    "sg:postcode":"V9A 3S8",
    "sg:province":"BC",
    "sg:tags":[
        "brewer"
    ],
    "wof:name":"Spinnakers Brewpub & Guest Hse",
    "wof:placetype":"venue"
},
  "geometry": {"coordinates":[-123.384803772,48.4294509888],"type":"Point"}
}