{
  "type": "Feature",
  "properties": {
    "iso:country":"CA",
    "sg:city":"North Vancouver",
    "sg:classifiers":[
        {
            "category":"Bars & Pubs",
            "type":"Food & Drink"
        }
    ],
    "sg:phone":"+1 604 986 7333",
    "sg:postcode":"V7M 2H9",
    "sg:province":"BC",
    "wof:name":"Jack Lonsdale's Pub",
    "wof:placetype":"venue"
},
  "geometry": {"coordinates":[-123.07254,49.321419],"type":"Point"}
}