{
  "type": "Feature",
  "properties": {
    "addr:full":"4320 17 Ave SE Calgary AB T2A 0T4",
    "addr:housenumber":"4320",
    "addr:postcode":"t2a 0t4",
    "addr:street":"17 Ave Se",
    "iso:country":"CA",
    "sg:address":"4320 17 Ave SE",
    "sg:city":"Calgary",
    "sg:classifiers":[
        {
            "category":"Retail",
            "subcategory":"Auto Repair",
            "type":"Services"
        }
    ],
    "sg:phone":"+1 403 248 0400",
    "sg:postcode":"T2A 0T4",
    "sg:province":"AB",
    "sg:tags":[
        "automobile",
        "lubrication"
    ],
    "wof:name":"Minit Lube",
    "wof:placetype":"venue"
},
  "geometry": {"coordinates":[-113.972443,51.038063],"type":"Point"}
}