{
  "type": "Feature",
  "properties": {
    "addr:full":"525 128E Rue Shawinigan-Sud QC G9P 4A5",
    "addr:housenumber":"525",
    "addr:postcode":"g9p 4a5",
    "addr:street":"128E Rue Shawinigan-Sud",
    "iso:country":"CA",
    "sg:address":"525 128E Rue",
    "sg:city":"Shawinigan-Sud",
    "sg:classifiers":[
        {
            "category":"Health Services",
            "subcategory":"Nursing And Care Facility",
            "type":"Services"
        }
    ],
    "sg:phone":"+1 819 536 2262",
    "sg:postcode":"G9P 4A5",
    "sg:province":"QC",
    "sg:tags":[
        "home",
        "retirement",
        "community"
    ],
    "wof:name":"Residence Le Reflet Du Sud Enr",
    "wof:placetype":"venue"
},
  "geometry": {"coordinates":[-72.741219,46.516758],"type":"Point"}
}