{
  "type": "Feature",
  "properties": {
    "addr:full":"Compressor Hill Rd Bell Island NL A0A 4H0",
    "addr:postcode":"a0a 4h0",
    "addr:street":"Compressor Hill Rd",
    "iso:country":"CA",
    "sg:address":"Compressor Hill Rd",
    "sg:city":"Bell Island",
    "sg:classifiers":[
        {
            "category":"Food & Beverages",
            "subcategory":"Bakery",
            "type":"Retail Goods"
        }
    ],
    "sg:phone":"+1 709 488 2250",
    "sg:postcode":"A0A 4H0",
    "sg:province":"NL",
    "sg:tags":[
        "baker"
    ],
    "wof:name":"Bell Island CO-OP Bakery",
    "wof:placetype":"venue"
},
  "geometry": {"coordinates":[-52.94907,47.622978],"type":"Point"}
}