{
  "type": "Feature",
  "properties": {
    "addr:full":"3120 Edgemont Blvd North Vancouver BC V7R 2N6",
    "addr:housenumber":"3120",
    "addr:postcode":"v7r 2n6",
    "addr:street":"Edgemont Blvd",
    "iso:country":"CA",
    "sg:address":"3120 Edgemont Blvd",
    "sg:city":"North Vancouver",
    "sg:classifiers":[
        {
            "category":"Food & Beverages",
            "subcategory":"Specialty",
            "type":"Retail Goods"
        }
    ],
    "sg:phone":"+1 604 987 0104",
    "sg:postcode":"V7R 2N6",
    "sg:province":"BC",
    "sg:tags":[
        "health",
        "diet"
    ],
    "wof:name":"Health Works",
    "wof:placetype":"venue"
},
  "geometry": {"coordinates":[-123.102058,49.337833],"type":"Point"}
}