{
  "type": "Feature",
  "properties": {
    "iso:country":"CA",
    "sg:city":"Warwick",
    "sg:classifiers":[
        {
            "category":"Shopping",
            "subcategory":"Clothing, Apparel, & Fashions",
            "type":"Retail Goods"
        }
    ],
    "sg:phone":"+1 819 358 5660",
    "sg:postcode":"J0A 1M0",
    "sg:province":"QC",
    "wof:name":"Confection-Christine Enr",
    "wof:placetype":"venue"
},
  "geometry": {"coordinates":[-71.984009,45.93877],"type":"Point"}
}