{
  "type": "Feature",
  "properties": {
    "addr:full":"3630 Lawrence Ave E Scarborough ON M1G 1P6",
    "addr:housenumber":"3630",
    "addr:postcode":"m1g 1p6",
    "addr:street":"Lawrence Ave E",
    "iso:country":"CA",
    "sg:address":"3630 Lawrence Ave E",
    "sg:city":"Scarborough",
    "sg:classifiers":[
        {
            "category":"Restaurant",
            "type":"Food & Drink"
        }
    ],
    "sg:phone":"+1 416 438 5649",
    "sg:postcode":"M1G 1P6",
    "sg:province":"ON",
    "wof:name":"Pasupathy Villasa",
    "wof:placetype":"venue"
},
  "geometry": {"coordinates":[-79.22263336180001,43.7605133057],"type":"Point"}
}