{
  "type": "Feature",
  "properties": {
    "iso:country":"CA",
    "sg:city":"Belleville",
    "sg:classifiers":[
        {
            "category":"Restaurant",
            "type":"Food & Drink"
        }
    ],
    "sg:phone":"+1 613 968 5731",
    "sg:postcode":"K8P 3B9",
    "sg:province":"ON",
    "wof:name":"Mariner's Fish & Chips",
    "wof:placetype":"venue"
},
  "geometry": {"coordinates":[-77.39166259770001,44.1783103943],"type":"Point"}
}