{
  "type": "Feature",
  "properties": {
    "iso:country":"CA",
    "sg:address":"884 Mcgillivray St",
    "sg:city":"Kamloops",
    "sg:classifiers":[
        {
            "category":"Building & Trades",
            "subcategory":"Construction",
            "type":"Services"
        }
    ],
    "sg:phone":"+1 250 554 3307",
    "sg:postcode":"V2B 5R6",
    "sg:province":"BC",
    "sg:tags":[
        "dry wall",
        "contractor"
    ],
    "wof:name":"Pittman Construction Ltd",
    "wof:placetype":"venue"
},
  "geometry": {"coordinates":[-120.406593,50.701839],"type":"Point"}
}