{
  "type": "Feature",
  "properties": {
    "addr:full":"43 Rue DE Buade Quebec QC G1R 4A2",
    "addr:housenumber":"43",
    "addr:postcode":"g1r 4a2",
    "addr:street":"Rue De Buade",
    "iso:country":"CA",
    "sg:address":"43 Rue DE Buade",
    "sg:city":"Quebec",
    "sg:classifiers":[
        {
            "category":"Shopping",
            "type":"Retail Goods"
        }
    ],
    "sg:phone":"+1 418 692 1367",
    "sg:postcode":"G1R 4A2",
    "sg:province":"QC",
    "sg:tags":[
        "item",
        "boutique",
        "cosmetic"
    ],
    "wof:name":"Parfumerie Jolicoeur",
    "wof:placetype":"venue"
},
  "geometry": {"coordinates":[-71.20663500000001,46.813538],"type":"Point"}
}