{
  "type": "Feature",
  "properties": {
    "iso:country":"CA",
    "sg:address":"1788 Drew Rd # A",
    "sg:city":"Mississauga",
    "sg:classifiers":[
        {
            "category":"Wholesale",
            "subcategory":"Machinery & Supplies",
            "type":"Manufacturing & Wholesale Goods"
        }
    ],
    "sg:phone":"+1 905 671 8665",
    "sg:postcode":"L5S 1L7",
    "sg:province":"ON",
    "sg:tags":[
        "tool"
    ],
    "wof:name":"Tool Sales",
    "wof:placetype":"venue"
},
  "geometry": {"coordinates":[-79.6742324829,43.6860313416],"type":"Point"}
}