{
  "type": "Feature",
  "properties": {
    "addr:full":"223 Centre St Meadow Lake SK S9X 1L5",
    "addr:housenumber":"223",
    "addr:postcode":"s9x 1l5",
    "addr:street":"Centre St",
    "iso:country":"CA",
    "sg:address":"223 Centre St",
    "sg:city":"Meadow Lake",
    "sg:classifiers":[
        {
            "category":"Personal",
            "type":"Services"
        }
    ],
    "sg:phone":"+1 306 236 6153",
    "sg:postcode":"S9X 1L5",
    "sg:province":"SK",
    "sg:tags":[
        "clothing",
        "furnishing",
        "formal"
    ],
    "wof:name":"Albert's Mens Wear Ltd",
    "wof:placetype":"venue"
},
  "geometry": {"coordinates":[-108.432198,54.119946],"type":"Point"}
}