{
  "type": "Feature",
  "properties": {
    "iso:country":"CA",
    "sg:city":"Mississauga",
    "sg:classifiers":[
        {
            "category":"Building & Trades",
            "subcategory":"Plumbing",
            "type":"Services"
        }
    ],
    "sg:phone":"+1 905 502 7006",
    "sg:postcode":"L4Z 1Y6",
    "sg:province":"ON",
    "sg:tags":[
        "conditioning",
        "air",
        "system",
        "contractor"
    ],
    "wof:name":"Islandaire Canada Inc",
    "wof:placetype":"venue"
},
  "geometry": {"coordinates":[-79.66877746580001,43.6206703186],"type":"Point"}
}