{
  "type": "Feature",
  "properties": {
    "addr:full":"3 Albert St Dartmouth NS B2Y 3M1",
    "addr:housenumber":"3",
    "addr:postcode":"b2y 3m1",
    "addr:street":"Albert St",
    "iso:country":"CA",
    "sg:address":"3 Albert St",
    "sg:city":"Dartmouth",
    "sg:classifiers":[
        {
            "category":"Shopping",
            "type":"Retail Goods"
        }
    ],
    "sg:phone":"+1 902 469 7454",
    "sg:postcode":"B2Y 3M1",
    "sg:province":"NS",
    "sg:tags":[
        "art",
        "gallery",
        "dealer"
    ],
    "wof:name":"Forrestall Fine Arts Ltd",
    "wof:placetype":"venue"
},
  "geometry": {"coordinates":[-63.5601348877,44.666973114],"type":"Point"}
}