{
  "type": "Feature",
  "properties": {
    "addr:full":"Vancouver BC V6G 2B4",
    "addr:postcode":"v6g 2b4",
    "iso:country":"CA",
    "sg:city":"Vancouver",
    "sg:classifiers":[
        {
            "category":"Real Estate",
            "subcategory":"Real Estate Operator",
            "type":"Services"
        }
    ],
    "sg:phone":"+1 604 684 7811",
    "sg:postcode":"V6G 2B4",
    "sg:province":"BC",
    "sg:tags":[
        "apartment"
    ],
    "wof:name":"Empire Towers Inn",
    "wof:placetype":"venue"
},
  "geometry": {"coordinates":[-123.13674899999999,49.283627],"type":"Point"}
}