{
  "type": "Feature",
  "properties": {
    "addr:full":"120 Erie St N Leamington ON N8H 3A2",
    "addr:housenumber":"120",
    "addr:postcode":"n8h 3a2",
    "addr:street":"Erie St N",
    "iso:country":"CA",
    "sg:address":"120 Erie St N",
    "sg:city":"Leamington",
    "sg:classifiers":[
        {
            "category":"Building & Trades",
            "subcategory":"Construction",
            "type":"Services"
        }
    ],
    "sg:phone":"+1 519 326 1221",
    "sg:postcode":"N8H 3A2",
    "sg:province":"ON",
    "sg:tags":[
        "painter"
    ],
    "wof:name":"Peter Milec Painting Ltd",
    "wof:placetype":"venue"
},
  "geometry": {"coordinates":[-82.5992889404,42.0577812195],"type":"Point"}
}