{
  "type": "Feature",
  "properties": {
    "iso:country":"CA",
    "sg:city":"Vancouver",
    "sg:classifiers":[
        {
            "category":"Real Estate",
            "subcategory":"Real Estate Agent",
            "type":"Services"
        }
    ],
    "sg:phone":"+1 604 737 9808",
    "sg:postcode":"V6J 5E7",
    "sg:province":"BC",
    "sg:tags":[
        "management"
    ],
    "wof:name":"Point Grey Properties Inc",
    "wof:placetype":"venue"
},
  "geometry": {"coordinates":[-123.14339447,49.2661857605],"type":"Point"}
}