{
  "type": "Feature",
  "properties": {
    "addr:full":"148 Peel St New Hamburg ON N3A 1E3",
    "addr:housenumber":"148",
    "addr:postcode":"n3a 1e3",
    "addr:street":"Peel St",
    "iso:country":"CA",
    "sg:address":"148 Peel St",
    "sg:city":"New Hamburg",
    "sg:classifiers":[
        {
            "category":"Personal",
            "subcategory":"Beauty Salon",
            "type":"Services"
        }
    ],
    "sg:phone":"+1 519 662 9799",
    "sg:postcode":"N3A 1E3",
    "sg:province":"ON",
    "wof:name":"Clip & Style",
    "wof:placetype":"venue"
},
  "geometry": {"coordinates":[-80.7089691162,43.3775405884],"type":"Point"}
}