{
  "type": "Feature",
  "properties": {
    "iso:country":"CA",
    "sg:address":"95 Boul Greber",
    "sg:city":"Gatineau",
    "sg:classifiers":[
        {
            "category":"Autos & Motor Vehicles",
            "subcategory":"Auto Supplies",
            "type":"Retail Goods"
        }
    ],
    "sg:phone":"+1 819 568 0044",
    "sg:postcode":"J8T 3P9",
    "sg:province":"QC",
    "sg:tags":[
        "automobile",
        "parts"
    ],
    "wof:name":"Pieces D'Autos Poulin Ltee",
    "wof:placetype":"venue"
},
  "geometry": {"coordinates":[-75.699982,45.465157],"type":"Point"}
}