{
  "type": "Feature",
  "properties": {
    "iso:country":"CA",
    "sg:address":"1146 Depot Rd",
    "sg:city":"Brackendale",
    "sg:classifiers":[
        {
            "category":"Building & Trades",
            "subcategory":"Construction",
            "type":"Services"
        }
    ],
    "sg:phone":"+1 604 898 4427",
    "sg:postcode":"V0N 1H0",
    "sg:province":"BC",
    "sg:tags":[
        "dry wall",
        "contractor"
    ],
    "wof:name":"Blueline Drywall",
    "wof:placetype":"venue"
},
  "geometry": {"coordinates":[-123.154563904,49.7660140991],"type":"Point"}
}