{
  "type": "Feature",
  "properties": {
    "addr:full":"765 Mcphee Ave Courtenay BC V9N 2Z7",
    "addr:housenumber":"765",
    "addr:postcode":"v9n 2z7",
    "addr:street":"Mcphee Ave",
    "iso:country":"CA",
    "sg:address":"765 Mcphee Ave",
    "sg:city":"Courtenay",
    "sg:classifiers":[
        {
            "category":"Manufacturing",
            "subcategory":"Printing",
            "type":"Manufacturing & Wholesale Goods"
        }
    ],
    "sg:phone":"+1 250 338 5811",
    "sg:postcode":"V9N 2Z7",
    "sg:province":"BC",
    "sg:tags":[
        "newspaper"
    ],
    "wof:name":"Comox Valley Record",
    "wof:placetype":"venue"
},
  "geometry": {"coordinates":[-125.00425,49.686058],"type":"Point"}
}