{
  "type": "Feature",
  "properties": {
    "addr:full":"2140 Walkley Rd Ottawa ON K1G 3V3",
    "addr:housenumber":"2140",
    "addr:postcode":"k1g 3v3",
    "addr:street":"Walkley Rd",
    "iso:country":"CA",
    "sg:address":"2140 Walkley Rd",
    "sg:city":"Ottawa",
    "sg:classifiers":[
        {
            "category":"Recreation",
            "type":"Entertainment"
        }
    ],
    "sg:phone":"+1 613 521 8636",
    "sg:postcode":"K1G 3V3",
    "sg:province":"ON",
    "sg:tags":[
        "hall",
        "auditorium"
    ],
    "wof:name":"Ottawa Masonic Ctr",
    "wof:placetype":"venue"
},
  "geometry": {"coordinates":[-75.623901,45.386124],"type":"Point"}
}