{
  "type": "Feature",
  "properties": {
    "addr:full":"43 Cosentino Dr Scarborough ON M1P 3A3",
    "addr:housenumber":"43",
    "addr:postcode":"m1p 3a3",
    "addr:street":"Cosentino Dr",
    "iso:country":"CA",
    "sg:address":"43 Cosentino Dr",
    "sg:city":"Scarborough",
    "sg:classifiers":[
        {
            "category":"Building & Trades",
            "subcategory":"Construction",
            "type":"Services"
        }
    ],
    "sg:phone":"+1 416 332 3770",
    "sg:postcode":"M1P 3A3",
    "sg:province":"ON",
    "sg:tags":[
        "concrete",
        "contractor"
    ],
    "wof:name":"Colonial Building Restoration",
    "wof:placetype":"venue"
},
  "geometry": {"coordinates":[-79.269974,43.771667],"type":"Point"}
}