{
  "type": "Feature",
  "properties": {
    "iso:country":"CA",
    "sg:address":"285 Gray Rd",
    "sg:city":"Kelowna",
    "sg:classifiers":[
        {
            "category":"Utilities",
            "subcategory":"Water",
            "type":"Services"
        }
    ],
    "sg:phone":"+1 250 765 5169",
    "sg:postcode":"V1X 1W8",
    "sg:province":"BC",
    "sg:tags":[
        "company",
        "sewage"
    ],
    "wof:name":"Black Mountain Irrigatn Dist",
    "wof:placetype":"venue"
},
  "geometry": {"coordinates":[-119.390694,49.887897],"type":"Point"}
}