{
  "type": "Feature",
  "properties": {
    "iso:country":"CA",
    "sg:address":"505 Old King George Hwy",
    "sg:city":"Miramichi",
    "sg:classifiers":[
        {
            "category":"Professional",
            "subcategory":"Management & Consulting",
            "type":"Services"
        }
    ],
    "sg:phone":"+1 506 778 6646",
    "sg:postcode":"E1V 1J8",
    "sg:province":"NB",
    "sg:tags":[
        "waste"
    ],
    "wof:name":"Northumberland Solid Waste Com",
    "wof:placetype":"venue"
},
  "geometry": {"coordinates":[-65.563148,47.011116],"type":"Point"}
}