{
  "type": "Feature",
  "properties": {
    "addr:full":"3 Roydon Pl Nepean ON K2E 1A3",
    "addr:housenumber":"3",
    "addr:postcode":"k2e 1a3",
    "addr:street":"Roydon Pl",
    "iso:country":"CA",
    "sg:address":"3 Roydon Pl",
    "sg:city":"Nepean",
    "sg:classifiers":[
        {
            "category":"Professional",
            "type":"Services"
        }
    ],
    "sg:phone":"+1 613 228 4570",
    "sg:postcode":"K2E 1A3",
    "sg:province":"ON",
    "sg:tags":[
        "computer",
        "establishment",
        "software"
    ],
    "wof:name":"Compus Smart",
    "wof:placetype":"venue"
},
  "geometry": {"coordinates":[-75.725112915,45.3386116028],"type":"Point"}
}