{
  "type": "Feature",
  "properties": {
    "addr:full":"4873 46 St Lacombe AB T4L 2B2",
    "addr:housenumber":"4873",
    "addr:postcode":"t4l 2b2",
    "addr:street":"46 St",
    "iso:country":"CA",
    "sg:address":"4873 46 St",
    "sg:city":"Lacombe",
    "sg:classifiers":[
        {
            "category":"Retail",
            "subcategory":"Repair Shop",
            "type":"Services"
        }
    ],
    "sg:phone":"+1 403 346 7444",
    "sg:postcode":"T4L 2B2",
    "sg:province":"AB",
    "sg:tags":[
        "field",
        "oil",
        "related"
    ],
    "wof:name":"Decoking Descaling Tchnlgy Inc",
    "wof:placetype":"venue"
},
  "geometry": {"coordinates":[-113.729537964,52.4611816406],"type":"Point"}
}