{
  "type": "Feature",
  "properties": {
    "addr:full":"9457 47 St NW Edmonton AB T6B 2R7",
    "addr:housenumber":"9457",
    "addr:postcode":"t6b 2r7",
    "addr:street":"47 St Nw",
    "iso:country":"CA",
    "sg:address":"9457 47 St NW",
    "sg:city":"Edmonton",
    "sg:classifiers":[
        {
            "category":"Building & Trades",
            "subcategory":"Construction",
            "type":"Services"
        }
    ],
    "sg:phone":"+1 780 440 0066",
    "sg:postcode":"T6B 2R7",
    "sg:province":"AB",
    "sg:tags":[
        "asbestos",
        "removal"
    ],
    "wof:name":"Dmi Svc Ltd",
    "wof:placetype":"venue"
},
  "geometry": {"coordinates":[-113.40778350799999,53.5316200256],"type":"Point"}
}