{
  "type": "Feature",
  "properties": {
    "addr:full":"Calgary AB T2V 0E4",
    "addr:postcode":"t2v 0e4",
    "iso:country":"CA",
    "sg:city":"Calgary",
    "sg:classifiers":[
        {
            "category":"Health Services",
            "subcategory":"Doctor",
            "type":"Services"
        }
    ],
    "sg:phone":"+1 403 255 4833",
    "sg:postcode":"T2V 0E4",
    "sg:province":"AB",
    "sg:tags":[
        "physician",
        "surgeon"
    ],
    "wof:name":"Adamiak, E J MD",
    "wof:placetype":"venue"
},
  "geometry": {"coordinates":[-114.0832901,50.9931526184],"type":"Point"}
}