{
  "type": "Feature",
  "properties": {
    "iso:country":"CA",
    "sg:address":"45 Rue DE L'Hotel DE Ville",
    "sg:city":"Warwick",
    "sg:classifiers":[
        {
            "category":"Retail",
            "subcategory":"Auto Repair",
            "type":"Services"
        }
    ],
    "sg:phone":"+1 819 358 5959",
    "sg:postcode":"J0A 1M0",
    "sg:province":"QC",
    "sg:tags":[
        "repairing",
        "automobile"
    ],
    "wof:name":"Garage Jean-Yves Martel Inc",
    "wof:placetype":"venue"
},
  "geometry": {"coordinates":[-71.9925003052,45.9468803406],"type":"Point"}
}