{
  "type": "Feature",
  "properties": {
    "addr:full":"1201 Broadway Ave Saskatoon SK S7H 2A4",
    "addr:housenumber":"1201",
    "addr:postcode":"s7h 2a4",
    "addr:street":"Broadway Ave",
    "iso:country":"CA",
    "sg:address":"1201 Broadway Ave",
    "sg:city":"Saskatoon",
    "sg:classifiers":[
        {
            "category":"Organizations",
            "subcategory":"Religious Organization",
            "type":"Services"
        }
    ],
    "sg:phone":"+1 306 242 9553",
    "sg:postcode":"S7H 2A4",
    "sg:province":"SK",
    "sg:tags":[
        "church"
    ],
    "wof:name":"Augustana Lutheran Church",
    "wof:placetype":"venue"
},
  "geometry": {"coordinates":[-106.65654000000001,52.113544],"type":"Point"}
}