{
  "type": "Feature",
  "properties": {
    "iso:country":"CA",
    "sg:address":"79 Fernlea Cres",
    "sg:city":"Oakville",
    "sg:classifiers":[
        {
            "category":"Freight",
            "type":"Transportation"
        }
    ],
    "sg:phone":"+1 905 337 3880",
    "sg:postcode":"L6H 6B2",
    "sg:province":"ON",
    "sg:tags":[
        "consultant"
    ],
    "wof:name":"Transportation Concepts",
    "wof:placetype":"venue"
},
  "geometry": {"coordinates":[-79.7181625366,43.4736595154],"type":"Point"}
}