{
  "type": "Feature",
  "properties": {
    "addr:full":"Surrey BC V3W 1A2",
    "addr:postcode":"v3w 1a2",
    "iso:country":"CA",
    "sg:city":"Surrey",
    "sg:classifiers":[
        {
            "category":"Manufacturing",
            "subcategory":"Signs",
            "type":"Manufacturing & Wholesale Goods"
        }
    ],
    "sg:phone":"+1 604 572 5000",
    "sg:postcode":"V3W 1A2",
    "sg:province":"BC",
    "wof:name":"Abstract Industries Ltd",
    "wof:placetype":"venue"
},
  "geometry": {"coordinates":[-122.830215454,49.105178833],"type":"Point"}
}