{
  "type": "Feature",
  "properties": {
    "iso:country":"CA",
    "sg:address":"418 Boul Des Promenades",
    "sg:city":"Saint-Bruno",
    "sg:classifiers":[
        {
            "category":"Shopping",
            "subcategory":"Clothing, Apparel, & Fashions",
            "type":"Retail Goods"
        }
    ],
    "sg:phone":"+1 450 441 7944",
    "sg:postcode":"J3V 6A8",
    "sg:province":"QC",
    "sg:tags":[
        "item",
        "boutique"
    ],
    "wof:name":"Bikini Village Inc",
    "wof:placetype":"venue"
},
  "geometry": {"coordinates":[-71.675522,48.471771],"type":"Point"}
}