{
  "type": "Feature",
  "properties": {
    "addr:full":"1930 Maynard Rd SE # 28 Calgary AB T2E 6J8",
    "addr:housenumber":"1930",
    "addr:postcode":"t2e 6j8",
    "addr:street":"Maynard Rd Se # 28",
    "iso:country":"CA",
    "sg:address":"1930 Maynard Rd SE # 28",
    "sg:city":"Calgary",
    "sg:classifiers":[
        {
            "category":"Building & Trades",
            "subcategory":"Construction",
            "type":"Services"
        }
    ],
    "sg:phone":"+1 403 264 9155",
    "sg:postcode":"T2E 6J8",
    "sg:province":"AB",
    "sg:tags":[
        "general",
        "contractor"
    ],
    "wof:name":"Ledcor Construction Ltd",
    "wof:placetype":"venue"
},
  "geometry": {"coordinates":[-114.01018500000001,51.047447],"type":"Point"}
}