{
  "type": "Feature",
  "properties": {
    "addr:full":"3600 Boul Casavant O Saint-Hyacinthe QC J2S 8E3",
    "addr:housenumber":"3600",
    "addr:postcode":"j2s 8e3",
    "addr:street":"Boul Casavant O",
    "iso:country":"CA",
    "sg:address":"3600 Boul Casavant O",
    "sg:city":"Saint-Hyacinthe",
    "sg:classifiers":[
        {
            "category":"Government",
            "subcategory":"Office",
            "type":"Public Place"
        }
    ],
    "sg:phone":"+1 450 773 1105",
    "sg:postcode":"J2S 8E3",
    "sg:province":"QC",
    "wof:name":"Canada Agriculture Dept",
    "wof:placetype":"venue"
},
  "geometry": {"coordinates":[-72.987449646,45.6237754822],"type":"Point"}
}