{
  "type": "Feature",
  "properties": {
    "addr:full":"847 Norwest Rd Kingston ON K7P 2N3",
    "addr:housenumber":"847",
    "addr:postcode":"k7p 2n3",
    "addr:street":"Norwest Rd",
    "iso:country":"CA",
    "sg:address":"847 Norwest Rd",
    "sg:city":"Kingston",
    "sg:classifiers":[
        {
            "category":"Personal",
            "type":"Services"
        }
    ],
    "sg:phone":"+1 613 384 2218",
    "sg:postcode":"K7P 2N3",
    "sg:province":"ON",
    "sg:tags":[
        "control",
        "weight"
    ],
    "wof:name":"Beverly Hills Weight Mgmt Clnc",
    "wof:placetype":"venue"
},
  "geometry": {"coordinates":[-76.575546,44.25716],"type":"Point"}
}