{
  "type": "Feature",
  "properties": {
    "iso:country":"CA",
    "sg:address":"8025 Boul Taschereau",
    "sg:city":"Brossard",
    "sg:classifiers":[
        {
            "category":"Home & Garden",
            "subcategory":"Furniture",
            "type":"Retail Goods"
        }
    ],
    "sg:phone":"+1 450 445 4420",
    "sg:postcode":"J4Y 1A4",
    "sg:province":"QC",
    "sg:tags":[
        "hardware",
        "kitchen",
        "cabinet"
    ],
    "wof:name":"Cuisi Boutique Ed",
    "wof:placetype":"venue"
},
  "geometry": {"coordinates":[-73.467628479,45.450214386],"type":"Point"}
}