{
  "type": "Feature",
  "properties": {
    "addr:full":"28 Torlake Cres Etobicoke ON M8Z 1B3",
    "addr:housenumber":"28",
    "addr:postcode":"m8z 1b3",
    "addr:street":"Torlake Cres",
    "iso:country":"CA",
    "sg:address":"28 Torlake Cres",
    "sg:city":"Etobicoke",
    "sg:classifiers":[
        {
            "category":"Manufacturing",
            "subcategory":"Tools & Machinery",
            "type":"Manufacturing & Wholesale Goods"
        }
    ],
    "sg:phone":"+1 416 259 7601",
    "sg:postcode":"M8Z 1B3",
    "sg:province":"ON",
    "sg:tags":[
        "machine",
        "die",
        "maker",
        "shop"
    ],
    "wof:name":"Quality Tool & Die CO",
    "wof:placetype":"venue"
},
  "geometry": {"coordinates":[-79.52441399999999,43.610977],"type":"Point"}
}