{
  "type": "Feature",
  "properties": {
    "addr:full":"45 Milner Ave Scarborough ON M1S 3P6",
    "addr:housenumber":"45",
    "addr:postcode":"m1s 3p6",
    "addr:street":"Milner Ave",
    "iso:country":"CA",
    "sg:address":"45 Milner Ave",
    "sg:city":"Scarborough",
    "sg:classifiers":[
        {
            "category":"Shopping",
            "subcategory":"Shoes",
            "type":"Retail Goods"
        }
    ],
    "sg:phone":"+1 416 298 9970",
    "sg:postcode":"M1S 3P6",
    "sg:province":"ON",
    "wof:name":"Mondo Milano",
    "wof:placetype":"venue"
},
  "geometry": {"coordinates":[-79.2529373169,43.7839851379],"type":"Point"}
}