{
  "type": "Feature",
  "properties": {
    "addr:full":"17360 108 Ave NW Edmonton AB T5S 1E8",
    "addr:housenumber":"17360",
    "addr:postcode":"t5s 1e8",
    "addr:street":"108 Ave Nw",
    "iso:country":"CA",
    "sg:address":"17360 108 Ave NW",
    "sg:city":"Edmonton",
    "sg:classifiers":[
        {
            "category":"Wholesale",
            "subcategory":"Durable Goods & Equipment",
            "type":"Manufacturing & Wholesale Goods"
        }
    ],
    "sg:phone":"+1 780 484 1849",
    "sg:postcode":"T5S 1E8",
    "sg:province":"AB",
    "sg:tags":[
        "laboratory",
        "instrument",
        "scientific",
        "apparatus",
        "supply"
    ],
    "wof:name":"Parkes Scientific Canada Inc",
    "wof:placetype":"venue"
},
  "geometry": {"coordinates":[-113.62061300000001,53.554699],"type":"Point"}
}