{
  "type": "Feature",
  "properties": {
    "addr:full":"Chicoutimi QC G7H 2R3",
    "addr:postcode":"g7h 2r3",
    "iso:country":"CA",
    "sg:city":"Chicoutimi",
    "sg:classifiers":[
        {
            "category":"Shopping",
            "type":"Retail Goods"
        }
    ],
    "sg:phone":"+1 418 696 3449",
    "sg:postcode":"G7H 2R3",
    "sg:province":"QC",
    "sg:tags":[
        "hearing",
        "equipment",
        "supply",
        "impaired"
    ],
    "wof:name":"Malentendex",
    "wof:placetype":"venue"
},
  "geometry": {"coordinates":[-71.04898834230001,48.4168891907],"type":"Point"}
}