{
  "type": "Feature",
  "properties": {
    "iso:country":"CA",
    "sg:address":"8 Saskatoon Ave",
    "sg:city":"Halifax",
    "sg:classifiers":[
        {
            "category":"Building & Trades",
            "subcategory":"Construction",
            "type":"Services"
        }
    ],
    "sg:phone":"+1 902 443 2139",
    "sg:postcode":"B3M 3H7",
    "sg:province":"NS",
    "sg:tags":[
        "roofing",
        "contractor",
        "general"
    ],
    "wof:name":"J L Dufour Construction Svc",
    "wof:placetype":"venue"
},
  "geometry": {"coordinates":[-63.686580658,44.687461853],"type":"Point"}
}