{
  "type": "Feature",
  "properties": {
    "addr:full":"Sherbrooke QC J1H 1S6",
    "addr:postcode":"j1h 1s6",
    "iso:country":"CA",
    "sg:city":"Sherbrooke",
    "sg:classifiers":[
        {
            "category":"Health Services",
            "subcategory":"Health Practitioner",
            "type":"Services"
        }
    ],
    "sg:phone":"+1 819 823 1477",
    "sg:postcode":"J1H 1S6",
    "sg:province":"QC",
    "sg:tags":[
        "physician"
    ],
    "wof:name":"Centre DE Sante Integrale",
    "wof:placetype":"venue"
},
  "geometry": {"coordinates":[-71.862915,45.408466],"type":"Point"}
}