{
  "type": "Feature",
  "properties": {
    "iso:country":"CA",
    "sg:address":"32 Bayfield St",
    "sg:city":"Barrie",
    "sg:classifiers":[
        {
            "category":"Shopping",
            "subcategory":"Jewelry",
            "type":"Retail Goods"
        }
    ],
    "sg:phone":"+1 705 728 4201",
    "sg:postcode":"L4M 3A5",
    "sg:province":"ON",
    "sg:tags":[
        "jeweler"
    ],
    "wof:name":"Stephenson's Jewellers",
    "wof:placetype":"venue"
},
  "geometry": {"coordinates":[-79.690559,44.389549],"type":"Point"}
}