{
  "type": "Feature",
  "properties": {
    "addr:full":"2 Pleasant St E Amherst NS B4H 1M4",
    "addr:housenumber":"2",
    "addr:postcode":"b4h 1m4",
    "addr:street":"Pleasant St E",
    "iso:country":"CA",
    "sg:address":"2 Pleasant St E",
    "sg:city":"Amherst",
    "sg:classifiers":[
        {
            "category":"Home & Garden",
            "subcategory":"Furniture",
            "type":"Retail Goods"
        }
    ],
    "sg:phone":"+1 902 661 4478",
    "sg:postcode":"B4H 1M4",
    "sg:province":"NS",
    "sg:tags":[
        "appliance"
    ],
    "wof:name":"Nibs Top Quality Used Furn",
    "wof:placetype":"venue"
},
  "geometry": {"coordinates":[-64.2074584961,45.8258323669],"type":"Point"}
}