{
  "type": "Feature",
  "properties": {
    "addr:full":"9542 87 St NW Edmonton AB T6C 3J1",
    "addr:housenumber":"9542",
    "addr:postcode":"t6c 3j1",
    "addr:street":"87 St Nw",
    "iso:country":"CA",
    "sg:address":"9542 87 St NW",
    "sg:city":"Edmonton",
    "sg:classifiers":[
        {
            "category":"Restaurant",
            "type":"Food & Drink"
        }
    ],
    "sg:phone":"+1 780 462 6379",
    "sg:postcode":"T6C 3J1",
    "sg:province":"AB",
    "wof:name":"A Hollywood Pizza & Donair",
    "wof:placetype":"venue"
},
  "geometry": {"coordinates":[-113.46107499999999,53.532772],"type":"Point"}
}