{
  "type": "Feature",
  "properties": {
    "addr:full":"5639 Rue DE Verdun Verdun QC H4H 1L3",
    "addr:housenumber":"5639",
    "addr:postcode":"h4h 1l3",
    "addr:street":"Rue De Verdun",
    "iso:country":"CA",
    "sg:address":"5639 Rue DE Verdun",
    "sg:city":"Verdun",
    "sg:classifiers":[
        {
            "category":"Wholesale",
            "subcategory":"Machinery & Supplies",
            "type":"Manufacturing & Wholesale Goods"
        }
    ],
    "sg:phone":"+1 514 769 3341",
    "sg:postcode":"H4H 1L3",
    "sg:province":"QC",
    "sg:tags":[
        "child",
        "care"
    ],
    "wof:name":"Abc Day Nursery",
    "wof:placetype":"venue"
},
  "geometry": {"coordinates":[-73.572624,45.450947],"type":"Point"}
}