{
  "type": "Feature",
  "properties": {
    "addr:full":"222 Tims Cres Swift Current SK S9H 4K8",
    "addr:housenumber":"222",
    "addr:postcode":"s9h 4k8",
    "addr:street":"Tims Cres",
    "iso:country":"CA",
    "sg:address":"222 Tims Cres",
    "sg:city":"Swift Current",
    "sg:classifiers":[
        {
            "category":"Professional",
            "subcategory":"Business Services",
            "type":"Services"
        }
    ],
    "sg:phone":"+1 306 773 8180",
    "sg:postcode":"S9H 4K8",
    "sg:province":"SK",
    "sg:tags":[
        "process",
        "server"
    ],
    "wof:name":"Lormit Process Svc",
    "wof:placetype":"venue"
},
  "geometry": {"coordinates":[-107.80556488000001,50.2983856201],"type":"Point"}
}