{
  "type": "Feature",
  "properties": {
    "iso:country":"CA",
    "sg:address":"304 Slater Rd NW",
    "sg:city":"Cranbrook",
    "sg:classifiers":[
        {
            "category":"Wholesale",
            "subcategory":"Scrap",
            "type":"Manufacturing & Wholesale Goods"
        }
    ],
    "sg:phone":"+1 250 426 7268",
    "sg:postcode":"V1C 4K5",
    "sg:province":"BC",
    "sg:tags":[
        "recycling",
        "center"
    ],
    "wof:name":"Skyway Distributors Ltd",
    "wof:placetype":"venue"
},
  "geometry": {"coordinates":[-115.766784668,49.5167770386],"type":"Point"}
}