{
  "type": "Feature",
  "properties": {
    "addr:full":"1075 Boul Firestone # 6 Joliette QC J6E 6X6",
    "addr:housenumber":"1075;# 6",
    "addr:postcode":"j6e 6x6",
    "addr:street":"Boul Firestone",
    "iso:country":"CA",
    "sg:address":"1075 Boul Firestone # 6",
    "sg:city":"Joliette",
    "sg:classifiers":[
        {
            "category":"Home & Garden",
            "subcategory":"Home Furnishings",
            "type":"Retail Goods"
        }
    ],
    "sg:phone":"+1 450 753 1144",
    "sg:postcode":"J6E 6X6",
    "sg:province":"QC",
    "sg:tags":[
        "shop",
        "venetian",
        "fabric"
    ],
    "wof:name":"Bou Clair Inc",
    "wof:placetype":"venue"
},
  "geometry": {"coordinates":[-73.426109314,46.0338401794],"type":"Point"}
}