{
  "type": "Feature",
  "properties": {
    "addr:full":"325 Lambton St Kincardine ON N2Z 2Y1",
    "addr:housenumber":"325",
    "addr:postcode":"n2z 2y1",
    "addr:street":"Lambton St",
    "iso:country":"CA",
    "sg:address":"325 Lambton St",
    "sg:city":"Kincardine",
    "sg:classifiers":[
        {
            "category":"Government",
            "subcategory":"Office",
            "type":"Public Place"
        }
    ],
    "sg:phone":"+1 519 396 3439",
    "sg:postcode":"N2Z 2Y1",
    "sg:province":"ON",
    "sg:tags":[
        "housing",
        "assistance",
        "village"
    ],
    "wof:name":"Bruce County Nonprofit Housing",
    "wof:placetype":"venue"
},
  "geometry": {"coordinates":[-81.6338806152,44.1774139404],"type":"Point"}
}