{
  "type": "Feature",
  "properties": {
    "addr:full":"8228 Granville St Vancouver BC V6P 4Z4",
    "addr:housenumber":"8228",
    "addr:postcode":"v6p 4z4",
    "addr:street":"Granville St",
    "iso:country":"CA",
    "sg:address":"8228 Granville St",
    "sg:city":"Vancouver",
    "sg:classifiers":[
        {
            "category":"Travel",
            "subcategory":"Travel Agent",
            "type":"Entertainment"
        }
    ],
    "sg:phone":"+1 604 263 8985",
    "sg:postcode":"V6P 4Z4",
    "sg:province":"BC",
    "sg:tags":[
        "agency",
        "bureau"
    ],
    "wof:name":"Grandfair Travel Ltd",
    "wof:placetype":"venue"
},
  "geometry": {"coordinates":[-123.14019,49.211678],"type":"Point"}
}