{
  "type": "Feature",
  "properties": {
    "addr:full":"Cannington ON L0E 1E0",
    "addr:postcode":"l0e 1e0",
    "iso:country":"CA",
    "sg:city":"Cannington",
    "sg:classifiers":[
        {
            "category":"Shopping",
            "subcategory":"Computers & Home Electronics",
            "type":"Retail Goods"
        }
    ],
    "sg:phone":"+1 705 432 3391",
    "sg:postcode":"L0E 1E0",
    "sg:province":"ON",
    "sg:tags":[
        "equipment",
        "dealer"
    ],
    "wof:name":"Your Computer & Signs",
    "wof:placetype":"venue"
},
  "geometry": {"coordinates":[-79.03926800000001,44.350201],"type":"Point"}
}