{
  "type": "Feature",
  "properties": {
    "addr:full":"421 Main St Bengough SK S0C 0K0",
    "addr:housenumber":"421",
    "addr:postcode":"s0c 0k0",
    "addr:street":"Main St",
    "iso:country":"CA",
    "sg:address":"421 Main St",
    "sg:city":"Bengough",
    "sg:classifiers":[
        {
            "category":"Recreation",
            "type":"Entertainment"
        }
    ],
    "sg:phone":"+1 306 268 2870",
    "sg:postcode":"S0C 0K0",
    "sg:province":"SK",
    "sg:tags":[
        "skating",
        "rink"
    ],
    "wof:name":"Bengough Skating Rink",
    "wof:placetype":"venue"
},
  "geometry": {"coordinates":[-105.12273399999999,49.397285],"type":"Point"}
}