{
  "type": "Feature",
  "properties": {
    "addr:full":"291 Rte Du Nord Brownsburg-Chatham QC J8G 1L7",
    "addr:housenumber":"291",
    "addr:postcode":"j8g 1l7",
    "addr:street":"Rte Du Nord",
    "iso:country":"CA",
    "sg:address":"291 Rte Du Nord",
    "sg:city":"Brownsburg-Chatham",
    "sg:classifiers":[
        {
            "category":"Wholesale",
            "subcategory":"Construction Materials",
            "type":"Manufacturing & Wholesale Goods"
        }
    ],
    "sg:phone":"+1 450 562 8471",
    "sg:postcode":"J8G 1L7",
    "sg:province":"QC",
    "sg:tags":[
        "concrete",
        "form"
    ],
    "wof:name":"Materiaux Inventifs Inc",
    "wof:placetype":"venue"
},
  "geometry": {"coordinates":[-74.368095,45.670319],"type":"Point"}
}