{
  "type": "Feature",
  "properties": {
    "addr:full":"4907 52nd Ave Whitecourt AB T7S 1P6",
    "addr:housenumber":"4907",
    "addr:postcode":"t7s 1p6",
    "addr:street":"52Nd Ave",
    "iso:country":"CA",
    "sg:address":"4907 52nd Ave",
    "sg:city":"Whitecourt",
    "sg:classifiers":[
        {
            "category":"Professional",
            "subcategory":"Accounting & Tax Preparation",
            "type":"Services"
        }
    ],
    "sg:phone":"+1 780 778 2612",
    "sg:postcode":"T7S 1P6",
    "sg:province":"AB",
    "sg:tags":[
        "consultant",
        "return",
        "filing"
    ],
    "wof:name":"H & R Block Canada Inc",
    "wof:placetype":"venue"
},
  "geometry": {"coordinates":[-115.68235799999999,54.142139],"type":"Point"}
}