{
  "type": "Feature",
  "properties": {
    "addr:full":"401 Salter St New Westminster BC V3M 5Y1",
    "addr:housenumber":"401",
    "addr:postcode":"v3m 5y1",
    "addr:street":"Salter St",
    "iso:country":"CA",
    "sg:address":"401 Salter St",
    "sg:city":"New Westminster",
    "sg:classifiers":[
        {
            "category":"Manufacturing",
            "subcategory":"Metals",
            "type":"Manufacturing & Wholesale Goods"
        }
    ],
    "sg:phone":"+1 604 521 3322",
    "sg:postcode":"V3M 5Y1",
    "sg:province":"BC",
    "sg:tags":[
        "pipe",
        "bending",
        "boiler",
        "fabricating"
    ],
    "wof:name":"Lockerbie & Holes Ind Corp",
    "wof:placetype":"venue"
},
  "geometry": {"coordinates":[-122.932312,49.188931],"type":"Point"}
}