{
  "type": "Feature",
  "properties": {
    "addr:full":"Hwy 601 Alix AB T0C 0B0",
    "addr:postcode":"t0c 0b0",
    "addr:street":"Hwy 601",
    "iso:country":"CA",
    "sg:address":"Hwy 601",
    "sg:city":"Alix",
    "sg:classifiers":[
        {
            "category":"Sports & Exercise",
            "subcategory":"Golf",
            "type":"Entertainment"
        }
    ],
    "sg:phone":"+1 403 747 2330",
    "sg:postcode":"T0C 0B0",
    "sg:province":"AB",
    "sg:tags":[
        "course"
    ],
    "wof:name":"Haunted Lakes Golf Club",
    "wof:placetype":"venue"
},
  "geometry": {"coordinates":[-113.189651,52.384346],"type":"Point"}
}