{
  "type": "Feature",
  "properties": {
    "addr:full":"1309 Rte Marie-Victorin O Deschaillons-Sur-Saint-Laurent QC G0S 1G0",
    "addr:housenumber":"1309",
    "addr:postcode":"g0s 1g0",
    "addr:street":"Rte Marie-Victorin O",
    "iso:country":"CA",
    "sg:address":"1309 Rte Marie-Victorin O",
    "sg:city":"Deschaillons-Sur-Saint-Laurent",
    "sg:classifiers":[
        {
            "category":"Autos & Motor Vehicles",
            "subcategory":"Automobile Sales",
            "type":"Retail Goods"
        }
    ],
    "sg:phone":"+1 819 292 2440",
    "sg:postcode":"G0S 1G0",
    "sg:province":"QC",
    "sg:tags":[
        "body",
        "car"
    ],
    "wof:name":"Auto Perfection",
    "wof:placetype":"venue"
},
  "geometry": {"coordinates":[-72.12039900000001,46.554615],"type":"Point"}
}