{
  "type": "Feature",
  "properties": {
    "addr:full":"Quebec QC G2K 2E3",
    "addr:postcode":"g2k 2e3",
    "iso:country":"CA",
    "sg:city":"Quebec",
    "sg:classifiers":[
        {
            "category":"Retail",
            "subcategory":"Laundry & Dry Cleaning",
            "type":"Services"
        }
    ],
    "sg:phone":"+1 418 627 2697",
    "sg:postcode":"G2K 2E3",
    "sg:province":"QC",
    "sg:tags":[
        "cleaners"
    ],
    "wof:name":"Nettoyeurs DE LA Capitale Ltee",
    "wof:placetype":"venue"
},
  "geometry": {"coordinates":[-71.29394499999999,46.836075],"type":"Point"}
}