{
  "type": "Feature",
  "properties": {
    "addr:full":"240 St-Nicolas Roxton Falls QC J0H 1E0",
    "addr:housenumber":"240",
    "addr:postcode":"j0h 1e0",
    "addr:street":"St-Nicolas",
    "iso:country":"CA",
    "sg:address":"240 St-Nicolas",
    "sg:city":"Roxton Falls",
    "sg:classifiers":[
        {
            "category":"Organizations",
            "subcategory":"Professional Association",
            "type":"Services"
        }
    ],
    "sg:phone":"+1 450 548 5832",
    "sg:postcode":"J0H 1E0",
    "sg:province":"QC",
    "wof:name":"Loisirs Roxton Falls",
    "wof:placetype":"venue"
},
  "geometry": {"coordinates":[-72.5207443237,45.570854187],"type":"Point"}
}