{
  "type": "Feature",
  "properties": {
    "iso:country":"CA",
    "sg:address":"3111 2nd Conc Line",
    "sg:city":"Wheatley",
    "sg:classifiers":[
        {
            "category":"Manufacturing",
            "subcategory":"Tools & Machinery",
            "type":"Manufacturing & Wholesale Goods"
        }
    ],
    "sg:phone":"+1 519 825 7354",
    "sg:postcode":"N0P 2P0",
    "sg:province":"ON",
    "sg:tags":[
        "farm",
        "equipment"
    ],
    "wof:name":"Manufarm Specialties Ltd",
    "wof:placetype":"venue"
},
  "geometry": {"coordinates":[-82.3834075928,42.1413612366],"type":"Point"}
}