{
  "type": "Feature",
  "properties": {
    "addr:full":"Saint-Robert QC J0G 1S0",
    "addr:postcode":"j0g 1s0",
    "iso:country":"CA",
    "sg:city":"Saint-Robert",
    "sg:classifiers":[
        {
            "category":"Bus Charters",
            "type":"Transportation"
        }
    ],
    "sg:phone":"+1 450 782 2755",
    "sg:postcode":"J0G 1S0",
    "sg:province":"QC",
    "sg:tags":[
        "rental"
    ],
    "wof:name":"Autobus Gaetan Jutras Ltee",
    "wof:placetype":"venue"
},
  "geometry": {"coordinates":[-73.00659899999999,45.973663],"type":"Point"}
}