{
  "type": "Feature",
  "properties": {
    "addr:full":"351 Kerr St Oakville ON L6K 3B7",
    "addr:housenumber":"351",
    "addr:postcode":"l6k 3b7",
    "addr:street":"Kerr St",
    "iso:country":"CA",
    "sg:address":"351 Kerr St",
    "sg:city":"Oakville",
    "sg:classifiers":[
        {
            "category":"Food & Beverages",
            "subcategory":"Meat & Fish",
            "type":"Retail Goods"
        }
    ],
    "sg:phone":"+1 905 849 0870",
    "sg:postcode":"L6K 3B7",
    "sg:province":"ON",
    "sg:tags":[
        "seafood"
    ],
    "wof:name":"Mermaid & the Oyster",
    "wof:placetype":"venue"
},
  "geometry": {"coordinates":[-79.6820983887,43.4440612793],"type":"Point"}
}