{
  "type": "Feature",
  "properties": {
    "addr:full":"1215 Oxford St White Rock BC V4B 3P7",
    "addr:housenumber":"1215",
    "addr:postcode":"v4b 3p7",
    "addr:street":"Oxford St",
    "iso:country":"CA",
    "sg:address":"1215 Oxford St",
    "sg:city":"White Rock",
    "sg:classifiers":[
        {
            "category":"Building & Trades",
            "subcategory":"Construction",
            "type":"Services"
        }
    ],
    "sg:phone":"+1 604 536 9242",
    "sg:postcode":"V4B 3P7",
    "sg:province":"BC",
    "sg:tags":[
        "siding",
        "contractor"
    ],
    "wof:name":"Finn Custom Aluminum",
    "wof:placetype":"venue"
},
  "geometry": {"coordinates":[-122.812210083,49.0244255066],"type":"Point"}
}