{
  "type": "Feature",
  "properties": {
    "addr:full":"1681 Clearbrook Rd Abbotsford BC V2T 5X5",
    "addr:housenumber":"1681",
    "addr:postcode":"v2t 5x5",
    "addr:street":"Clearbrook Rd",
    "iso:country":"CA",
    "sg:address":"1681 Clearbrook Rd",
    "sg:city":"Abbotsford",
    "sg:classifiers":[
        {
            "category":"Farming",
            "subcategory":"Poultry Farm",
            "type":"Manufacturing & Wholesale Goods"
        }
    ],
    "sg:phone":"+1 604 864 0555",
    "sg:postcode":"V2T 5X5",
    "sg:province":"BC",
    "wof:name":"Fraser Valley Chick Sales",
    "wof:placetype":"venue"
},
  "geometry": {"coordinates":[-122.337898254,49.0329246521],"type":"Point"}
}