{
  "type": "Feature",
  "properties": {
    "addr:full":"2274 South Main St Westville NS B0K 2A0",
    "addr:housenumber":"2274",
    "addr:postcode":"b0k 2a0",
    "addr:street":"South Main St",
    "iso:country":"CA",
    "sg:address":"2274 South Main St",
    "sg:city":"Westville",
    "sg:classifiers":[
        {
            "category":"Home & Garden",
            "subcategory":"Garden Supply",
            "type":"Retail Goods"
        }
    ],
    "sg:phone":"+1 902 396 3134",
    "sg:postcode":"B0K 2A0",
    "sg:province":"NS",
    "sg:tags":[
        "center"
    ],
    "wof:name":"Lamey's Greenhouse",
    "wof:placetype":"venue"
},
  "geometry": {"coordinates":[-62.71912,45.553326],"type":"Point"}
}