{
  "type": "Feature",
  "properties": {
    "iso:country":"CA",
    "sg:address":"6928 51 Ave NW",
    "sg:city":"Edmonton",
    "sg:classifiers":[
        {
            "category":"Freight",
            "type":"Transportation"
        }
    ],
    "sg:phone":"+1 780 461 6684",
    "sg:postcode":"T6B 2P4",
    "sg:province":"AB",
    "sg:tags":[
        "commercial",
        "storage"
    ],
    "wof:name":"Instant Storage Inc",
    "wof:placetype":"venue"
},
  "geometry": {"coordinates":[-113.435783,53.488121],"type":"Point"}
}