{
  "type": "Feature",
  "properties": {
    "addr:full":"21 Main St Springhill NS B0M 1X0",
    "addr:housenumber":"21",
    "addr:postcode":"b0m 1x0",
    "addr:street":"Main St",
    "iso:country":"CA",
    "sg:address":"21 Main St",
    "sg:city":"Springhill",
    "sg:classifiers":[
        {
            "category":"Food & Beverages",
            "subcategory":"Bakery",
            "type":"Retail Goods"
        }
    ],
    "sg:phone":"+1 902 597 8777",
    "sg:postcode":"B0M 1X0",
    "sg:province":"NS",
    "sg:tags":[
        "grocer"
    ],
    "wof:name":"Foodland",
    "wof:placetype":"venue"
},
  "geometry": {"coordinates":[-64.05693817140001,45.6506500244],"type":"Point"}
}