{
  "type": "Feature",
  "properties": {
    "addr:full":"3819 Bloor St W Etobicoke ON M9B 1K7",
    "addr:housenumber":"3819",
    "addr:postcode":"m9b 1k7",
    "addr:street":"Bloor St W",
    "iso:country":"CA",
    "sg:address":"3819 Bloor St W",
    "sg:city":"Etobicoke",
    "sg:classifiers":[
        {
            "category":"Organizations",
            "subcategory":"Religious Organization",
            "type":"Services"
        }
    ],
    "sg:phone":"+1 416 233 9800",
    "sg:postcode":"M9B 1K7",
    "sg:province":"ON",
    "sg:tags":[
        "church"
    ],
    "wof:name":"St Andrews Presbyterian Church",
    "wof:placetype":"venue"
},
  "geometry": {"coordinates":[-79.536888,43.641357],"type":"Point"}
}