{
  "type": "Feature",
  "properties": {
    "addr:full":"500 May St N Thunder Bay ON P7C 3R6",
    "addr:housenumber":"500",
    "addr:postcode":"p7c 3r6",
    "addr:street":"May St N",
    "iso:country":"CA",
    "sg:address":"500 May St N",
    "sg:city":"Thunder Bay",
    "sg:classifiers":[
        {
            "category":"Shopping",
            "subcategory":"Tobacco",
            "type":"Retail Goods"
        }
    ],
    "sg:phone":"+1 807 626 9816",
    "sg:postcode":"P7C 3R6",
    "sg:province":"ON",
    "sg:tags":[
        "cigarette",
        "cigar",
        "dealer"
    ],
    "wof:name":"Rollies the Discount Tobacco",
    "wof:placetype":"venue"
},
  "geometry": {"coordinates":[-89.2453918457,48.3922843933],"type":"Point"}
}