{
  "type": "Feature",
  "properties": {
    "iso:country":"CA",
    "sg:address":"4410 43 St N",
    "sg:city":"Lethbridge",
    "sg:classifiers":[
        {
            "category":"Organizations",
            "subcategory":"Professional Association",
            "type":"Services"
        }
    ],
    "sg:phone":"+1 403 380 4591",
    "sg:postcode":"T1H 6P3",
    "sg:province":"AB",
    "sg:tags":[
        "club"
    ],
    "wof:name":"Croatian Centre",
    "wof:placetype":"venue"
},
  "geometry": {"coordinates":[-112.778839111,49.727268219],"type":"Point"}
}