{
  "type": "Feature",
  "properties": {
    "addr:full":"Saint-Leonard QC H1R 2B6",
    "addr:postcode":"h1r 2b6",
    "iso:country":"CA",
    "sg:city":"Saint-Leonard",
    "sg:classifiers":[
        {
            "category":"Recreation",
            "type":"Entertainment"
        }
    ],
    "sg:phone":"+1 514 322 9919",
    "sg:postcode":"H1R 2B6",
    "sg:province":"QC",
    "sg:tags":[
        "martial",
        "arts",
        "instruction"
    ],
    "wof:name":"Zen Arts Martiaux Enr",
    "wof:placetype":"venue"
},
  "geometry": {"coordinates":[-73.610832,45.59819],"type":"Point"}
}