{
  "type": "Feature",
  "properties": {
    "addr:full":"1100 Pembroke St E #320 Pembroke ON K8A 6Y7",
    "addr:housenumber":"1100",
    "addr:postcode":"k8a 6y7",
    "addr:street":"Pembroke St E # 320",
    "iso:country":"CA",
    "sg:address":"1100 Pembroke St E #320",
    "sg:city":"Pembroke",
    "sg:classifiers":[
        {
            "category":"Shopping",
            "subcategory":"Clothing, Apparel, & Fashions",
            "type":"Retail Goods"
        }
    ],
    "sg:phone":"+1 613 735 8377",
    "sg:postcode":"K8A 6Y7",
    "sg:province":"ON",
    "wof:name":"Alia",
    "wof:placetype":"venue"
},
  "geometry": {"coordinates":[-77.085526,45.824032],"type":"Point"}
}