{
  "type": "Feature",
  "properties": {
    "iso:country":"CA",
    "sg:address":"2920 Boul Monseigneur-Gauthier",
    "sg:city":"Beauport",
    "sg:classifiers":[
        {
            "category":"Freight",
            "type":"Transportation"
        }
    ],
    "sg:phone":"+1 418 666 7201",
    "sg:postcode":"G1E 2V2",
    "sg:province":"QC",
    "sg:tags":[
        "commercial",
        "storage"
    ],
    "wof:name":"Entrepotheque Beauport Inc",
    "wof:placetype":"venue"
},
  "geometry": {"coordinates":[-71.213638,46.84676],"type":"Point"}
}