{
  "type": "Feature",
  "properties": {
    "addr:full":"18 Marena Ave Sauble Beach ON N0H 2G0",
    "addr:housenumber":"18",
    "addr:postcode":"n0h 2g0",
    "addr:street":"Marena Ave",
    "iso:country":"CA",
    "sg:address":"18 Marena Ave",
    "sg:city":"Sauble Beach",
    "sg:classifiers":[
        {
            "category":"Recreation",
            "subcategory":"Marina",
            "type":"Entertainment"
        }
    ],
    "sg:phone":"+1 519 422 1762",
    "sg:postcode":"N0H 2G0",
    "sg:province":"ON",
    "wof:name":"Sauble Beach Marina & Lodge",
    "wof:placetype":"venue"
},
  "geometry": {"coordinates":[-81.27215576170001,44.6631851196],"type":"Point"}
}