{
  "type": "Feature",
  "properties": {
    "addr:full":"21 Rue Notre-Dame-DE-Lourdes Ville-Marie QC J9V 1X8",
    "addr:housenumber":"21",
    "addr:postcode":"j9v 1x8",
    "addr:street":"Rue Notre-Dame-De-Lourdes",
    "iso:country":"CA",
    "sg:address":"21 Rue Notre-Dame-DE-Lourdes",
    "sg:city":"Ville-Marie",
    "sg:classifiers":[
        {
            "category":"Social Services",
            "type":"Services"
        }
    ],
    "sg:phone":"+1 819 629 2676",
    "sg:postcode":"J9V 1X8",
    "sg:province":"QC",
    "sg:tags":[
        "organization",
        "welfare"
    ],
    "wof:name":"Centre DE Svc Sociaux-Abitibi",
    "wof:placetype":"venue"
},
  "geometry": {"coordinates":[-79.440178,47.332764],"type":"Point"}
}