{
  "type": "Feature",
  "properties": {
    "addr:full":"17790 56 Ave Surrey BC V3S 1C7",
    "addr:housenumber":"17790",
    "addr:postcode":"v3s 1c7",
    "addr:street":"56 Ave",
    "iso:country":"CA",
    "sg:address":"17790 56 Ave",
    "sg:city":"Surrey",
    "sg:classifiers":[
        {
            "category":"Building & Trades",
            "subcategory":"Construction",
            "type":"Services"
        }
    ],
    "sg:phone":"+1 604 576 2226",
    "sg:postcode":"V3S 1C7",
    "sg:province":"BC",
    "sg:tags":[
        "contractor"
    ],
    "wof:name":"South Ridge Developments Ltd",
    "wof:placetype":"venue"
},
  "geometry": {"coordinates":[-122.729523,49.103935],"type":"Point"}
}