{
  "type": "Feature",
  "properties": {
    "iso:country":"CA",
    "sg:city":"London",
    "sg:classifiers":[
        {
            "category":"Wholesale",
            "subcategory":"Farm Supplies",
            "type":"Manufacturing & Wholesale Goods"
        }
    ],
    "sg:phone":"+1 519 473 9333",
    "sg:postcode":"N6H 5L6",
    "sg:province":"ON",
    "sg:tags":[
        "grain"
    ],
    "wof:name":"London Agricultural Commoditie",
    "wof:placetype":"venue"
},
  "geometry": {"coordinates":[-81.33609,42.999371],"type":"Point"}
}