{
  "type": "Feature",
  "properties": {
    "addr:full":"5680 Oak St Vancouver BC V6M 2V6",
    "addr:housenumber":"5680",
    "addr:postcode":"v6m 2v6",
    "addr:street":"Oak St",
    "iso:country":"CA",
    "sg:address":"5680 Oak St",
    "sg:city":"Vancouver",
    "sg:classifiers":[
        {
            "category":"Autos & Motor Vehicles",
            "subcategory":"Fuel & Gas Station",
            "type":"Retail Goods"
        }
    ],
    "sg:phone":"+1 604 266 0314",
    "sg:postcode":"V6M 2V6",
    "sg:province":"BC",
    "sg:tags":[
        "oil"
    ],
    "wof:name":"41st & Oak Petro-Canada",
    "wof:placetype":"venue"
},
  "geometry": {"coordinates":[-123.12784600000001,49.234421],"type":"Point"}
}