{
  "type": "Feature",
  "properties": {
    "addr:full":"1 Saskatchewan Ave W Portage LA Prairie MB R1N 0P4",
    "addr:housenumber":"1",
    "addr:postcode":"r1n 0p4",
    "addr:street":"Saskatchewan Ave W",
    "iso:country":"CA",
    "sg:address":"1 Saskatchewan Ave W",
    "sg:city":"Portage LA Prairie",
    "sg:classifiers":[
        {
            "category":"Banks & Credit Unions",
            "subcategory":"Bank",
            "type":"Services"
        }
    ],
    "sg:phone":"+1 204 239 8600",
    "sg:postcode":"R1N 0P4",
    "sg:province":"MB",
    "wof:name":"Bank of Montreal",
    "wof:placetype":"venue"
},
  "geometry": {"coordinates":[-98.2913284302,49.9730606079],"type":"Point"}
}