{
  "type": "Feature",
  "properties": {
    "addr:full":"1445 Rue Antonio Laval QC H7V 3N5",
    "addr:housenumber":"1445",
    "addr:postcode":"h7v 3n5",
    "addr:street":"Rue Antonio",
    "iso:country":"CA",
    "sg:address":"1445 Rue Antonio",
    "sg:city":"Laval",
    "sg:classifiers":[
        {
            "category":"Building & Trades",
            "subcategory":"Landscaping Services",
            "type":"Services"
        }
    ],
    "sg:phone":"+1 450 681 2947",
    "sg:postcode":"H7V 3N5",
    "sg:province":"QC",
    "sg:tags":[
        "tree"
    ],
    "wof:name":"Paysarbres Enr",
    "wof:placetype":"venue"
},
  "geometry": {"coordinates":[-73.7548980713,45.5487937927],"type":"Point"}
}