{
  "type": "Feature",
  "properties": {
    "iso:country":"CA",
    "sg:address":"4504 14 St NE",
    "sg:city":"Calgary",
    "sg:classifiers":[
        {
            "category":"Autos & Motor Vehicles",
            "subcategory":"Auto Supplies",
            "type":"Retail Goods"
        }
    ],
    "sg:phone":"+1 403 248 7898",
    "sg:postcode":"T2E 6T7",
    "sg:province":"AB",
    "sg:tags":[
        "automobile",
        "parts"
    ],
    "wof:name":"Fender & Body Parts",
    "wof:placetype":"venue"
},
  "geometry": {"coordinates":[-114.028762817,51.0922470093],"type":"Point"}
}