{
  "type": "Feature",
  "properties": {
    "addr:full":"319 Rue Arbic Saint-Eustache QC J7R 6N8",
    "addr:housenumber":"319",
    "addr:postcode":"j7r 6n8",
    "addr:street":"Rue Arbic",
    "iso:country":"CA",
    "sg:address":"319 Rue Arbic",
    "sg:city":"Saint-Eustache",
    "sg:classifiers":[
        {
            "category":"Professional",
            "subcategory":"Accounting & Tax Preparation",
            "type":"Services"
        }
    ],
    "sg:phone":"+1 450 974 3043",
    "sg:postcode":"J7R 6N8",
    "sg:province":"QC",
    "sg:tags":[
        "accountant"
    ],
    "wof:name":"Legault, Marc CA",
    "wof:placetype":"venue"
},
  "geometry": {"coordinates":[-73.93353999999999,45.578976],"type":"Point"}
}