{
  "type": "Feature",
  "properties": {
    "addr:full":"273 Rue Tache N Saint-Pascal QC G0L 3Y0",
    "addr:housenumber":"273",
    "addr:postcode":"g0l 3y0",
    "addr:street":"Rue Tache N",
    "iso:country":"CA",
    "sg:address":"273 Rue Tache N",
    "sg:city":"Saint-Pascal",
    "sg:classifiers":[
        {
            "category":"Retail",
            "subcategory":"Repair Shop",
            "type":"Services"
        }
    ],
    "sg:phone":"+1 418 492 9605",
    "sg:postcode":"G0L 3Y0",
    "sg:province":"QC",
    "sg:tags":[
        "equipment",
        "electronic",
        "supply"
    ],
    "wof:name":"Erictronique Enr",
    "wof:placetype":"venue"
},
  "geometry": {"coordinates":[-69.81146240229999,47.5304374695],"type":"Point"}
}