{
  "type": "Feature",
  "properties": {
    "addr:full":"1210 Rue Lachaine Laval QC H7C 2N7",
    "addr:housenumber":"1210",
    "addr:postcode":"h7c 2n7",
    "addr:street":"Rue Lachaine",
    "iso:country":"CA",
    "sg:address":"1210 Rue Lachaine",
    "sg:city":"Laval",
    "sg:classifiers":[
        {
            "category":"Retail",
            "subcategory":"Auto Repair",
            "type":"Services"
        }
    ],
    "sg:phone":"+1 450 661 7114",
    "sg:postcode":"H7C 2N7",
    "sg:province":"QC",
    "sg:tags":[
        "repairing",
        "tire"
    ],
    "wof:name":"Pneus Parent",
    "wof:placetype":"venue"
},
  "geometry": {"coordinates":[-73.65785217289999,45.6166381836],"type":"Point"}
}