{
  "type": "Feature",
  "properties": {
    "addr:full":"370 Markham St Toronto ON M6G 2K9",
    "addr:housenumber":"370",
    "addr:postcode":"m6g 2k9",
    "addr:street":"Markham St",
    "iso:country":"CA",
    "sg:address":"370 Markham St",
    "sg:city":"Toronto",
    "sg:classifiers":[
        {
            "category":"Real Estate",
            "subcategory":"Architect",
            "type":"Services"
        }
    ],
    "sg:phone":"+1 416 515 1082",
    "sg:postcode":"M6G 2K9",
    "sg:province":"ON",
    "wof:name":"Wink Architect Inc",
    "wof:placetype":"venue"
},
  "geometry": {"coordinates":[-79.40989685060001,43.6580886841],"type":"Point"}
}