{
  "type": "Feature",
  "properties": {
    "addr:full":"54 Whyte Ave Stratford ON N5A 2S2",
    "addr:housenumber":"54",
    "addr:postcode":"n5a 2s2",
    "addr:street":"Whyte Ave",
    "iso:country":"CA",
    "sg:address":"54 Whyte Ave",
    "sg:city":"Stratford",
    "sg:classifiers":[
        {
            "category":"Manufacturing",
            "subcategory":"Tools & Machinery",
            "type":"Manufacturing & Wholesale Goods"
        }
    ],
    "sg:phone":"+1 519 271 9981",
    "sg:postcode":"N5A 2S2",
    "sg:province":"ON",
    "sg:tags":[
        "machine",
        "shop"
    ],
    "wof:name":"O'Hara Machine & Tool",
    "wof:placetype":"venue"
},
  "geometry": {"coordinates":[-80.99380499999999,43.36031],"type":"Point"}
}