{
  "type": "Feature",
  "properties": {
    "addr:full":"1286 Conception Bay Hwy Conception Bay South NL A1X 4G5",
    "addr:housenumber":"1286",
    "addr:postcode":"a1x 4g5",
    "addr:street":"Conception Bay Hwy",
    "iso:country":"CA",
    "sg:address":"1286 Conception Bay Hwy",
    "sg:city":"Conception Bay South",
    "sg:classifiers":[
        {
            "category":"Shopping",
            "subcategory":"Discount & Variety Stores",
            "type":"Retail Goods"
        }
    ],
    "sg:phone":"+1 709 744 3022",
    "sg:postcode":"A1X 4G5",
    "sg:province":"NL",
    "wof:name":"Smith's Shoe & Variety Store",
    "wof:placetype":"venue"
},
  "geometry": {"coordinates":[-53.056129,47.477211],"type":"Point"}
}