{
  "type": "Feature",
  "properties": {
    "addr:full":"London ON N5V 2C7",
    "addr:postcode":"n5v 2c7",
    "iso:country":"CA",
    "sg:city":"London",
    "sg:classifiers":[
        {
            "category":"Professional",
            "subcategory":"Business Services",
            "type":"Services"
        }
    ],
    "sg:phone":"+1 519 453 7052",
    "sg:postcode":"N5V 2C7",
    "sg:province":"ON",
    "sg:tags":[
        "water",
        "company",
        "treatment"
    ],
    "wof:name":"Fountain Water Products",
    "wof:placetype":"venue"
},
  "geometry": {"coordinates":[-81.17817700000001,43.009766],"type":"Point"}
}