{
  "type": "Feature",
  "properties": {
    "addr:full":"2204 4 St SW Calgary AB T2S 1W9",
    "addr:housenumber":"2204 4",
    "addr:postcode":"t2s 1w9",
    "addr:street":"St Sw",
    "iso:country":"CA",
    "sg:address":"2204 4 St SW",
    "sg:city":"Calgary",
    "sg:classifiers":[
        {
            "category":"Restaurant",
            "type":"Food & Drink"
        }
    ],
    "sg:phone":"+1 403 802 0058",
    "sg:postcode":"T2S 1W9",
    "sg:province":"AB",
    "wof:name":"Sushi Kawa Japanese Rstrnt",
    "wof:placetype":"venue"
},
  "geometry": {"coordinates":[-114.071403503,51.0332489014],"type":"Point"}
}