{
  "type": "Feature",
  "properties": {
    "addr:full":"942 Brant St Burlington ON L7R 2J7",
    "addr:housenumber":"942",
    "addr:postcode":"l7r 2j7",
    "addr:street":"Brant St",
    "iso:country":"CA",
    "sg:address":"942 Brant St",
    "sg:city":"Burlington",
    "sg:classifiers":[
        {
            "category":"Wholesale",
            "subcategory":"Chemicals & Plastics",
            "type":"Manufacturing & Wholesale Goods"
        }
    ],
    "sg:phone":"+1 905 632 7861",
    "sg:postcode":"L7R 2J7",
    "sg:province":"ON",
    "wof:name":"Hercules Canada Inc",
    "wof:placetype":"venue"
},
  "geometry": {"coordinates":[-79.8152389526,43.337310791],"type":"Point"}
}