{
  "type": "Feature",
  "properties": {
    "addr:full":"Saint-Simon-DE-Rimouski QC G0L 4C0",
    "addr:postcode":"g0l 4c0",
    "iso:country":"CA",
    "sg:city":"Saint-Simon-DE-Rimouski",
    "sg:classifiers":[
        {
            "category":"Education",
            "subcategory":"School",
            "type":"Public Place"
        }
    ],
    "sg:phone":"+1 418 738 2870",
    "sg:postcode":"G0L 4C0",
    "sg:province":"QC",
    "wof:name":"Ecole DE LA Joie",
    "wof:placetype":"venue"
},
  "geometry": {"coordinates":[-69.037453,48.207069],"type":"Point"}
}