{
  "type": "Feature",
  "properties": {
    "addr:full":"1622 10th Ave Fernie BC V0B 1M0",
    "addr:housenumber":"1622",
    "addr:postcode":"bc v0b 1m0",
    "addr:street":"10Th Ave",
    "iso:country":"CA",
    "sg:address":"1622 10th Ave",
    "sg:city":"Fernie",
    "sg:classifiers":[
        {
            "category":"Organizations",
            "subcategory":"Religious Organization",
            "type":"Services"
        }
    ],
    "sg:phone":"+1 250 423 4112",
    "sg:postcode":"V0B 1M0",
    "sg:province":"BC",
    "sg:tags":[
        "church"
    ],
    "wof:name":"Fellowship Baptist Church",
    "wof:placetype":"venue"
},
  "geometry": {"coordinates":[-115.061172485,49.5161743164],"type":"Point"}
}