{
  "type": "Feature",
  "properties": {
    "addr:full":"General Delivery Ware BC V0J 3B0",
    "addr:postcode":"v0j 3b0",
    "iso:country":"CA",
    "sg:address":"General Delivery",
    "sg:city":"Ware",
    "sg:classifiers":[
        {
            "category":"Organizations",
            "subcategory":"Professional Association",
            "type":"Services"
        }
    ],
    "sg:phone":"+1 250 471 2302",
    "sg:postcode":"V0J 3B0",
    "sg:province":"BC",
    "sg:tags":[
        "native"
    ],
    "wof:name":"Kwadacha Band",
    "wof:placetype":"venue"
},
  "geometry": {"coordinates":[-125.633331,57.416672],"type":"Point"}
}