{
  "type": "Feature",
  "properties": {
    "iso:country":"CA",
    "sg:address":"10400 Av Merritt",
    "sg:city":"Montreal",
    "sg:classifiers":[
        {
            "category":"Health Services",
            "subcategory":"Doctor",
            "type":"Services"
        }
    ],
    "sg:phone":"+1 514 384 1437",
    "sg:postcode":"H2B 2K4",
    "sg:province":"QC",
    "sg:tags":[
        "physician",
        "surgeon"
    ],
    "wof:name":"Bardagi, Victor MD",
    "wof:placetype":"venue"
},
  "geometry": {"coordinates":[-73.651985,45.572041],"type":"Point"}
}