{
  "type": "Feature",
  "properties": {
    "addr:full":"22 Cottonwood Cres London ON N6G 2Y8",
    "addr:housenumber":"22",
    "addr:postcode":"n6g 2y8",
    "addr:street":"Cottonwood Cres",
    "iso:country":"CA",
    "sg:address":"22 Cottonwood Cres",
    "sg:city":"London",
    "sg:classifiers":[
        {
            "category":"Professional",
            "subcategory":"Management & Consulting",
            "type":"Services"
        }
    ],
    "sg:phone":"+1 519 657 3000",
    "sg:postcode":"N6G 2Y8",
    "sg:province":"ON",
    "sg:tags":[
        "career",
        "counseling",
        "employment",
        "screening",
        "vocational"
    ],
    "wof:name":"Human Achievement Assoc",
    "wof:placetype":"venue"
},
  "geometry": {"coordinates":[-81.3140640259,43.0074882507],"type":"Point"}
}