{
  "type": "Feature",
  "properties": {
    "addr:full":"RR 3 STN Main Antigonish NS B2G 2L1",
    "addr:postcode":"b2g 2l1",
    "addr:street":"Rr 3 Stn Main",
    "iso:country":"CA",
    "sg:address":"RR 3 STN Main",
    "sg:city":"Antigonish",
    "sg:classifiers":[
        {
            "category":"Manufacturing",
            "subcategory":"Food",
            "type":"Manufacturing & Wholesale Goods"
        }
    ],
    "sg:phone":"+1 902 926 2423",
    "sg:postcode":"B2G 2L1",
    "sg:province":"NS",
    "sg:tags":[
        "packer",
        "fish"
    ],
    "wof:name":"Lismore Sea Products Ltd",
    "wof:placetype":"venue"
},
  "geometry": {"coordinates":[-61.99427,45.622189],"type":"Point"}
}