{
  "type": "Feature",
  "properties": {
    "addr:full":"540 Admiral Dr London ON N5V 4L5",
    "addr:housenumber":"540",
    "addr:postcode":"n5v 4l5",
    "addr:street":"Admiral Dr",
    "iso:country":"CA",
    "sg:address":"540 Admiral Dr",
    "sg:city":"London",
    "sg:classifiers":[
        {
            "category":"Wholesale",
            "subcategory":"Chemicals & Plastics",
            "type":"Manufacturing & Wholesale Goods"
        }
    ],
    "sg:phone":"+1 519 659 2101",
    "sg:postcode":"N5V 4L5",
    "sg:province":"ON",
    "sg:tags":[
        "cleaning",
        "compound"
    ],
    "wof:name":"Swish Maintenance Ltd",
    "wof:placetype":"venue"
},
  "geometry": {"coordinates":[-81.15004730219999,43.0042457581],"type":"Point"}
}