{
  "type": "Feature",
  "properties": {
    "addr:full":"213 Rue Christophe-Colomb #1 Cowansville QC J2K 1G6",
    "addr:housenumber":"213",
    "addr:postcode":"j2k 1g6",
    "addr:street":"Rue Christophe-Colomb # 1",
    "iso:country":"CA",
    "sg:address":"213 Rue Christophe-Colomb #1",
    "sg:city":"Cowansville",
    "sg:classifiers":[
        {
            "category":"Building & Trades",
            "subcategory":"Electrical",
            "type":"Services"
        }
    ],
    "sg:phone":"+1 450 266 5426",
    "sg:postcode":"J2K 1G6",
    "sg:province":"QC",
    "sg:tags":[
        "electric",
        "contractor"
    ],
    "wof:name":"Roger Turgeon Electrique Inc",
    "wof:placetype":"venue"
},
  "geometry": {"coordinates":[-72.74745900000001,45.21048],"type":"Point"}
}