{
  "type": "Feature",
  "properties": {
    "iso:country":"CA",
    "sg:address":"1451 Yonge St",
    "sg:city":"Toronto",
    "sg:classifiers":[
        {
            "category":"Shopping",
            "subcategory":"Shoes",
            "type":"Retail Goods"
        }
    ],
    "sg:phone":"+1 416 967 4131",
    "sg:postcode":"M4T 1Y5",
    "sg:province":"ON",
    "wof:name":"Town Shoes",
    "wof:placetype":"venue"
},
  "geometry": {"coordinates":[-79.39402771,43.6883354187],"type":"Point"}
}