{
  "type": "Feature",
  "properties": {
    "addr:full":"124 Clarke St Treherne MB R0G 2V0",
    "addr:housenumber":"124",
    "addr:postcode":"r0g 2v0",
    "addr:street":"Clarke St",
    "iso:country":"CA",
    "sg:address":"124 Clarke St",
    "sg:city":"Treherne",
    "sg:classifiers":[
        {
            "category":"Freight",
            "type":"Transportation"
        }
    ],
    "sg:phone":"+1 204 723 2535",
    "sg:postcode":"R0G 2V0",
    "sg:province":"MB",
    "sg:tags":[
        "car",
        "pilot"
    ],
    "wof:name":"Ape Pilot Escort",
    "wof:placetype":"venue"
},
  "geometry": {"coordinates":[-98.69813499999999,49.634331],"type":"Point"}
}