{
  "type": "Feature",
  "properties": {
    "addr:full":"3220 Eby St Terrace BC V8G 5H4",
    "addr:housenumber":"3220",
    "addr:postcode":"v8g 5h4",
    "addr:street":"Eby St Terrace",
    "iso:country":"CA",
    "sg:address":"3220 Eby St",
    "sg:city":"Terrace",
    "sg:classifiers":[
        {
            "category":"Government",
            "subcategory":"Office",
            "type":"Public Place"
        }
    ],
    "sg:phone":"+1 250 638 6560",
    "sg:postcode":"V8G 5H4",
    "sg:province":"BC",
    "wof:name":"BC Govt Agents-Associated Ofc",
    "wof:placetype":"venue"
},
  "geometry": {"coordinates":[-128.59881591800001,54.5174255371],"type":"Point"}
}