{
  "type": "Feature",
  "properties": {
    "addr:full":"33 Vernon Keats Dr St Clements MB R2C 2Z2",
    "addr:housenumber":"33",
    "addr:postcode":"r2c 2z2",
    "addr:street":"Vernon Keats Dr St Clements",
    "iso:country":"CA",
    "sg:address":"33 Vernon Keats Dr",
    "sg:city":"St Clements",
    "sg:classifiers":[
        {
            "category":"Retail",
            "subcategory":"Repair Shop",
            "type":"Services"
        }
    ],
    "sg:phone":"+1 204 222 6893",
    "sg:postcode":"R2C 2Z2",
    "sg:province":"MB",
    "sg:tags":[
        "upholsterer"
    ],
    "wof:name":"Triple M Upholstery",
    "wof:placetype":"venue"
},
  "geometry": {"coordinates":[-96.8221588135,50.1318588257],"type":"Point"}
}