{
  "type": "Feature",
  "properties": {
    "addr:full":"3717 Roblin Blvd Winnipeg MB R3R 0E3",
    "addr:postcode":"3717;r3r 0e3",
    "addr:street":"Roblin Blvd",
    "iso:country":"CA",
    "sg:address":"3717 Roblin Blvd",
    "sg:city":"Winnipeg",
    "sg:classifiers":[
        {
            "category":"Retail",
            "subcategory":"Veterinary Services",
            "type":"Services"
        }
    ],
    "sg:phone":"+1 204 889 3110",
    "sg:postcode":"R3R 0E3",
    "sg:province":"MB",
    "sg:tags":[
        "veterinarian"
    ],
    "wof:name":"Charleswood Veterinary Clinic",
    "wof:placetype":"venue"
},
  "geometry": {"coordinates":[-97.26264999999999,49.868282],"type":"Point"}
}