{
  "type": "Feature",
  "properties": {
    "addr:full":"180 Dundurn St S Hamilton ON L8P 4K3",
    "addr:housenumber":"180",
    "addr:postcode":"l8p 4k3",
    "addr:street":"Dundurn St S",
    "iso:country":"CA",
    "sg:address":"180 Dundurn St S",
    "sg:city":"Hamilton",
    "sg:classifiers":[
        {
            "category":"Wholesale",
            "subcategory":"Office Equipment",
            "type":"Manufacturing & Wholesale Goods"
        }
    ],
    "sg:phone":"+1 905 528 5903",
    "sg:postcode":"L8P 4K3",
    "sg:province":"ON",
    "sg:tags":[
        "register",
        "cash",
        "supply"
    ],
    "wof:name":"Armagh Cash Register Ltd",
    "wof:placetype":"venue"
},
  "geometry": {"coordinates":[-79.89046500000001,43.256729],"type":"Point"}
}