{
  "type": "Feature",
  "properties": {
    "addr:full":"650 Rue Maurice-Bois Vanier QC G1M 3G3",
    "addr:housenumber":"650",
    "addr:postcode":"g1m 3g3",
    "addr:street":"Rue Maurice-Bois",
    "iso:country":"CA",
    "sg:address":"650 Rue Maurice-Bois",
    "sg:city":"Vanier",
    "sg:classifiers":[
        {
            "category":"Manufacturing",
            "subcategory":"Tools & Machinery",
            "type":"Manufacturing & Wholesale Goods"
        }
    ],
    "sg:phone":"+1 418 683 0767",
    "sg:postcode":"G1M 3G3",
    "sg:province":"QC",
    "sg:tags":[
        "fire",
        "equipment",
        "protection",
        "sprinkler"
    ],
    "wof:name":"Gicleurs Vanier Inc",
    "wof:placetype":"venue"
},
  "geometry": {"coordinates":[-71.279068,46.820141],"type":"Point"}
}