{
  "type": "Feature",
  "properties": {
    "addr:full":"307 Rue Notre-Dame Repentigny QC J6A 2R9",
    "addr:housenumber":"307",
    "addr:postcode":"j6a 2r9",
    "addr:street":"Rue Notre-Dame",
    "iso:country":"CA",
    "sg:address":"307 Rue Notre-Dame",
    "sg:city":"Repentigny",
    "sg:classifiers":[
        {
            "category":"Health Services",
            "subcategory":"Doctor",
            "type":"Services"
        }
    ],
    "sg:phone":"+1 450 581 9614",
    "sg:postcode":"J6A 2R9",
    "sg:province":"QC",
    "sg:tags":[
        "physiotherapist",
        "clinic"
    ],
    "wof:name":"Physiotherapie Rene Joyal",
    "wof:placetype":"venue"
},
  "geometry": {"coordinates":[-73.45665700000001,45.729301],"type":"Point"}
}