{
  "type": "Feature",
  "properties": {
    "addr:full":"1195 Fir St #B Campbell River BC V9W 3B7",
    "addr:housenumber":"1195",
    "addr:postcode":"v9w 3b7",
    "addr:street":"Fir St # B",
    "iso:country":"CA",
    "sg:address":"1195 Fir St #B",
    "sg:city":"Campbell River",
    "sg:classifiers":[
        {
            "category":"Wholesale",
            "subcategory":"Medical Equipment & Supplies",
            "type":"Manufacturing & Wholesale Goods"
        }
    ],
    "sg:phone":"+1 250 286 4888",
    "sg:postcode":"V9W 3B7",
    "sg:province":"BC",
    "sg:tags":[
        "alarm"
    ],
    "wof:name":"Campbell River Life Line",
    "wof:placetype":"venue"
},
  "geometry": {"coordinates":[-125.250664,50.02673],"type":"Point"}
}