{
  "type": "Feature",
  "properties": {
    "addr:full":"Edmonton AB T5M 2P6",
    "addr:postcode":"t5m 2p6",
    "iso:country":"CA",
    "sg:city":"Edmonton",
    "sg:classifiers":[
        {
            "category":"Banks & Credit Unions",
            "subcategory":"Investment Brokerage",
            "type":"Services"
        }
    ],
    "sg:phone":"+1 780 484 4132",
    "sg:postcode":"T5M 2P6",
    "sg:province":"AB",
    "wof:name":"Guertin Consulting",
    "wof:placetype":"venue"
},
  "geometry": {"coordinates":[-113.579155,53.55867],"type":"Point"}
}