{
  "type": "Feature",
  "properties": {
    "iso:country":"CA",
    "sg:address":"115 DE Baets St",
    "sg:city":"Winnipeg",
    "sg:classifiers":[
        {
            "category":"Restaurant",
            "type":"Food & Drink"
        }
    ],
    "sg:phone":"+1 204 661 2851",
    "sg:postcode":"R2J 3R9",
    "sg:province":"MB",
    "sg:tags":[
        "pizza"
    ],
    "wof:name":"Gondola Pizza Restaurants",
    "wof:placetype":"venue"
},
  "geometry": {"coordinates":[-97.042678833,49.8834266663],"type":"Point"}
}