{
  "type": "Feature",
  "properties": {
    "addr:full":"10970 124 St Surrey BC V3V 4T9",
    "addr:housenumber":"10970",
    "addr:postcode":"v3v 4t9",
    "addr:street":"124 St",
    "iso:country":"CA",
    "sg:address":"10970 124 St",
    "sg:city":"Surrey",
    "sg:classifiers":[
        {
            "category":"Retail",
            "subcategory":"Auto Repair",
            "type":"Services"
        }
    ],
    "sg:phone":"+1 604 580 3388",
    "sg:postcode":"V3V 4T9",
    "sg:province":"BC",
    "sg:tags":[
        "automobile",
        "wrecker"
    ],
    "wof:name":"Scott Road Automotive & Towing",
    "wof:placetype":"venue"
},
  "geometry": {"coordinates":[-122.878440857,49.2020301819],"type":"Point"}
}