{
  "type": "Feature",
  "properties": {
    "iso:country":"CA",
    "sg:address":"60 Rue Cloutier",
    "sg:city":"Val-D'Or",
    "sg:classifiers":[
        {
            "category":"Organizations",
            "subcategory":"Professional Association",
            "type":"Services"
        }
    ],
    "sg:phone":"+1 819 874 7915",
    "sg:postcode":"J9P 4K7",
    "sg:province":"QC",
    "wof:name":"Societe DE LA Sclerose En",
    "wof:placetype":"venue"
},
  "geometry": {"coordinates":[-71.197281,46.778751],"type":"Point"}
}