{
  "type": "Feature",
  "properties": {
    "addr:full":"351 Christie St Pembroke ON K8A 4R6",
    "addr:housenumber":"351",
    "addr:postcode":"k8a 4r6",
    "addr:street":"Christie St",
    "iso:country":"CA",
    "sg:address":"351 Christie St",
    "sg:city":"Pembroke",
    "sg:classifiers":[
        {
            "category":"Organizations",
            "subcategory":"Professional Association",
            "type":"Services"
        }
    ],
    "sg:phone":"+1 613 735 0869",
    "sg:postcode":"K8A 4R6",
    "sg:province":"ON",
    "wof:name":"Oecta Refrew Unit",
    "wof:placetype":"venue"
},
  "geometry": {"coordinates":[-77.122658,45.821068],"type":"Point"}
}