{
  "type": "Feature",
  "properties": {
    "addr:full":"Winnipeg MB R3C 3T1",
    "addr:postcode":"r3c 3t1",
    "iso:country":"CA",
    "sg:city":"Winnipeg",
    "sg:classifiers":[
        {
            "category":"Shopping",
            "subcategory":"Gifts & Souvenirs",
            "type":"Retail Goods"
        }
    ],
    "sg:phone":"+1 204 943 4991",
    "sg:postcode":"R3C 3T1",
    "sg:province":"MB",
    "sg:tags":[
        "novelty"
    ],
    "wof:name":"S R Novelties",
    "wof:placetype":"venue"
},
  "geometry": {"coordinates":[-97.1490325928,49.8888511658],"type":"Point"}
}