{
  "type": "Feature",
  "properties": {
    "addr:full":"4240 Av Girouard Montreal QC H4A 3C9",
    "addr:housenumber":"4240",
    "addr:postcode":"h4a 3c9",
    "addr:street":"Av Girouard",
    "iso:country":"CA",
    "sg:address":"4240 Av Girouard",
    "sg:city":"Montreal",
    "sg:classifiers":[
        {
            "category":"Education",
            "subcategory":"School",
            "type":"Public Place"
        }
    ],
    "sg:phone":"+1 514 485 3859",
    "sg:postcode":"H4A 3C9",
    "sg:province":"QC",
    "sg:tags":[
        "academic",
        "special"
    ],
    "wof:name":"Natural Health Consultants",
    "wof:placetype":"venue"
},
  "geometry": {"coordinates":[-73.62111663819999,45.4764823914],"type":"Point"}
}