{
  "type": "Feature",
  "properties": {
    "addr:full":"9111 River Dr Richmond BC V6X 1Z1",
    "addr:housenumber":"9111",
    "addr:postcode":"v6x 1z1",
    "addr:street":"River Dr",
    "iso:country":"CA",
    "sg:address":"9111 River Dr",
    "sg:city":"Richmond",
    "sg:classifiers":[
        {
            "category":"Manufacturing",
            "subcategory":"Tools & Machinery",
            "type":"Manufacturing & Wholesale Goods"
        }
    ],
    "sg:phone":"+1 604 273 9401",
    "sg:postcode":"V6X 1Z1",
    "sg:province":"BC",
    "sg:tags":[
        "scale"
    ],
    "wof:name":"Pacific Industrial Scale CO",
    "wof:placetype":"venue"
},
  "geometry": {"coordinates":[-123.1251297,49.1979141235],"type":"Point"}
}