{
  "type": "Feature",
  "properties": {
    "iso:country":"CA",
    "sg:city":"Chateauguay",
    "sg:classifiers":[
        {
            "category":"Shopping",
            "subcategory":"Clothing, Apparel, & Fashions",
            "type":"Retail Goods"
        }
    ],
    "sg:phone":"+1 450 691 9733",
    "sg:postcode":"J6K 1C5",
    "sg:province":"QC",
    "sg:tags":[
        "furnishing"
    ],
    "wof:name":"Tisseur Mercerie",
    "wof:placetype":"venue"
},
  "geometry": {"coordinates":[-73.74011230470001,45.3614845276],"type":"Point"}
}