{
  "type": "Feature",
  "properties": {
    "iso:country":"CA",
    "sg:address":"965 Brookdale Ave",
    "sg:city":"Cornwall",
    "sg:classifiers":[
        {
            "category":"Shopping",
            "subcategory":"Clothing, Apparel, & Fashions",
            "type":"Retail Goods"
        }
    ],
    "sg:phone":"+1 613 936 8099",
    "sg:postcode":"K6J 4P5",
    "sg:province":"ON",
    "wof:name":"Winners 323",
    "wof:placetype":"venue"
},
  "geometry": {"coordinates":[-74.749893,45.025124],"type":"Point"}
}