{
  "type": "Feature",
  "properties": {
    "addr:full":"201 Broadway Ave E Redcliff AB T0J 2P0",
    "addr:housenumber":"201",
    "addr:postcode":"t0j 2p0",
    "addr:street":"Broadway Ave E",
    "iso:country":"CA",
    "sg:address":"201 Broadway Ave E",
    "sg:city":"Redcliff",
    "sg:classifiers":[
        {
            "category":"Personal",
            "subcategory":"Beauty Salon",
            "type":"Services"
        }
    ],
    "sg:phone":"+1 403 548 3030",
    "sg:postcode":"T0J 2P0",
    "sg:province":"AB",
    "wof:name":"Broadway Beauty & Tanning Slns",
    "wof:placetype":"venue"
},
  "geometry": {"coordinates":[-110.786117554,50.0772895813],"type":"Point"}
}