{
  "type": "Feature",
  "properties": {
    "addr:full":"1215 Rue Kitchener Sherbrooke QC J1H 3L1",
    "addr:housenumber":"1215",
    "addr:postcode":"j1h 3l1",
    "addr:street":"Rue Kitchener",
    "iso:country":"CA",
    "sg:address":"1215 Rue Kitchener",
    "sg:city":"Sherbrooke",
    "sg:classifiers":[
        {
            "category":"Cinema",
            "subcategory":"Movie Theater",
            "type":"Entertainment"
        }
    ],
    "sg:phone":"+1 819 565 5536",
    "sg:postcode":"J1H 3L1",
    "sg:province":"QC",
    "wof:name":"Theatre Du Double Signe",
    "wof:placetype":"venue"
},
  "geometry": {"coordinates":[-71.90581512449999,45.3891296387],"type":"Point"}
}