{
  "type": "Feature",
  "properties": {
    "addr:full":"4355 Boul Poirier Saint-Laurent QC H4R 2A4",
    "addr:housenumber":"4355",
    "addr:postcode":"h4r 2a4",
    "addr:street":"Boul Poirier",
    "iso:country":"CA",
    "sg:address":"4355 Boul Poirier",
    "sg:city":"Saint-Laurent",
    "sg:classifiers":[
        {
            "category":"Wholesale",
            "subcategory":"Groceries",
            "type":"Manufacturing & Wholesale Goods"
        }
    ],
    "sg:phone":"+1 514 333 7726",
    "sg:postcode":"H4R 2A4",
    "sg:province":"QC",
    "sg:tags":[
        "food",
        "product"
    ],
    "wof:name":"Rip Corp",
    "wof:placetype":"venue"
},
  "geometry": {"coordinates":[-73.72472399999999,45.493408],"type":"Point"}
}