{
  "type": "Feature",
  "properties": {
    "addr:full":"5510 Rue Saint-Jacques Montreal QC H4A 2E2",
    "addr:housenumber":"5510",
    "addr:postcode":"h4a 2e2",
    "addr:street":"Rue Saint-Jacques",
    "iso:country":"CA",
    "sg:address":"5510 Rue Saint-Jacques",
    "sg:city":"Montreal",
    "sg:classifiers":[
        {
            "category":"Wholesale",
            "subcategory":"Hardware",
            "type":"Manufacturing & Wholesale Goods"
        }
    ],
    "sg:phone":"+1 514 481 5614",
    "sg:postcode":"H4A 2E2",
    "sg:province":"QC",
    "sg:tags":[
        "plumbing",
        "fixture",
        "supply"
    ],
    "wof:name":"Nelco Inc",
    "wof:placetype":"venue"
},
  "geometry": {"coordinates":[-73.60459899999999,45.468872],"type":"Point"}
}