{
  "type": "Feature",
  "properties": {
    "addr:full":"4615 Av Bergeron Becancour QC G9H 2E7",
    "addr:housenumber":"4615",
    "addr:postcode":"g9h 2e7",
    "addr:street":"Av Bergeron Becancour",
    "iso:country":"CA",
    "sg:address":"4615 Av Bergeron",
    "sg:city":"Becancour",
    "sg:classifiers":[
        {
            "category":"Building & Trades",
            "subcategory":"Electrical",
            "type":"Services"
        }
    ],
    "sg:phone":"+1 819 233 2571",
    "sg:postcode":"G9H 2E7",
    "sg:province":"QC",
    "sg:tags":[
        "electric",
        "contractor"
    ],
    "wof:name":"T Rouleau & Fils Inc",
    "wof:placetype":"venue"
},
  "geometry": {"coordinates":[-72.512794,46.269871],"type":"Point"}
}