{
  "type": "Feature",
  "properties": {
    "addr:full":"193 Guertin Rd Brighton ON K0K 1H0",
    "addr:housenumber":"193",
    "addr:postcode":"k0k 1h0",
    "addr:street":"Guertin Rd",
    "iso:country":"CA",
    "sg:address":"193 Guertin Rd",
    "sg:city":"Brighton",
    "sg:classifiers":[
        {
            "category":"Shopping",
            "subcategory":"Used Merchandise",
            "type":"Retail Goods"
        }
    ],
    "sg:phone":"+1 613 475 2671",
    "sg:postcode":"K0K 1H0",
    "sg:province":"ON",
    "sg:tags":[
        "antique"
    ],
    "wof:name":"Breakaway Antiques",
    "wof:placetype":"venue"
},
  "geometry": {"coordinates":[-77.78626300000001,44.1073],"type":"Point"}
}