{
  "type": "Feature",
  "properties": {
    "addr:full":"Hines Creek AB T0H 2A0",
    "addr:postcode":"t0h 2a0",
    "iso:country":"CA",
    "sg:city":"Hines Creek",
    "sg:classifiers":[
        {
            "category":"Personal",
            "subcategory":"Beauty Salon",
            "type":"Services"
        }
    ],
    "sg:phone":"+1 780 494 3576",
    "sg:postcode":"T0H 2A0",
    "sg:province":"AB",
    "wof:name":"Natural Flaire",
    "wof:placetype":"venue"
},
  "geometry": {"coordinates":[-118.604073,56.247128],"type":"Point"}
}