{
  "type": "Feature",
  "properties": {
    "addr:full":"1035 Boul Auger O Alma QC G8B 2C2",
    "addr:housenumber":"1035",
    "addr:postcode":"g8b 2c2",
    "addr:street":"Boul Auger O",
    "iso:country":"CA",
    "sg:address":"1035 Boul Auger O",
    "sg:city":"Alma",
    "sg:classifiers":[
        {
            "category":"Professional",
            "subcategory":"Accounting & Tax Preparation",
            "type":"Services"
        }
    ],
    "sg:phone":"+1 418 662 6464",
    "sg:postcode":"G8B 2C2",
    "sg:province":"QC",
    "sg:tags":[
        "accountant"
    ],
    "wof:name":"Brisson, Anthony CA",
    "wof:placetype":"venue"
},
  "geometry": {"coordinates":[-71.61800384519999,48.5351142883],"type":"Point"}
}