{
  "type": "Feature",
  "properties": {
    "addr:full":"West Guilford ON K0M 2S0",
    "addr:postcode":"k0m 2s0",
    "addr:street":"West",
    "iso:country":"CA",
    "sg:city":"West Guilford",
    "sg:classifiers":[
        {
            "category":"Food & Beverages",
            "subcategory":"Groceries & Convenience Stores",
            "type":"Retail Goods"
        }
    ],
    "sg:phone":"+1 705 754 2162",
    "sg:postcode":"K0M 2S0",
    "sg:province":"ON",
    "sg:tags":[
        "grocer"
    ],
    "wof:name":"West Guilford Shopping Ctr",
    "wof:placetype":"venue"
},
  "geometry": {"coordinates":[-78.600525,45.109039],"type":"Point"}
}