{
  "type": "Feature",
  "properties": {
    "iso:country":"CA",
    "sg:address":"1110 Boul Moody",
    "sg:city":"Terrebonne",
    "sg:classifiers":[
        {
            "category":"Restaurant",
            "type":"Food & Drink"
        }
    ],
    "sg:phone":"+1 450 961 1363",
    "sg:postcode":"J6W 3K9",
    "sg:province":"QC",
    "wof:name":"Burger King",
    "wof:placetype":"venue"
},
  "geometry": {"coordinates":[-73.648109,45.701488],"type":"Point"}
}