{
  "type": "Feature",
  "properties": {
    "addr:full":"500 Boul Des Laurentides Saint-Jerome QC J7Z 4M2",
    "addr:housenumber":"500",
    "addr:postcode":"j7z 4m2",
    "addr:street":"Boul Des Laurentides",
    "iso:country":"CA",
    "sg:address":"500 Boul Des Laurentides",
    "sg:city":"Saint-Jerome",
    "sg:classifiers":[
        {
            "category":"Home & Garden",
            "subcategory":"Household Appliances",
            "type":"Retail Goods"
        }
    ],
    "sg:phone":"+1 450 569 0002",
    "sg:postcode":"J7Z 4M2",
    "sg:province":"QC",
    "sg:tags":[
        "cleaners",
        "vacuum"
    ],
    "wof:name":"Aspirateur 2000 Plus",
    "wof:placetype":"venue"
},
  "geometry": {"coordinates":[-73.99303399999999,45.762627],"type":"Point"}
}