{
  "type": "Feature",
  "properties": {
    "addr:full":"Black Lake QC G6H 2J8",
    "addr:postcode":"g6h 2j8",
    "addr:street":"Black Lake",
    "iso:country":"CA",
    "sg:city":"Black Lake",
    "sg:classifiers":[
        {
            "category":"Health Services",
            "subcategory":"Doctor",
            "type":"Services"
        }
    ],
    "sg:phone":"+1 418 423 5582",
    "sg:postcode":"G6H 2J8",
    "sg:province":"QC",
    "sg:tags":[
        "physician",
        "surgeon"
    ],
    "wof:name":"Centre Medical DE Black Lake",
    "wof:placetype":"venue"
},
  "geometry": {"coordinates":[-71.3666687012,46.0529747009],"type":"Point"}
}