{
  "type": "Feature",
  "properties": {
    "addr:full":"225 Rue Principale Saint-Gervais QC G0R 3C0",
    "addr:housenumber":"225",
    "addr:postcode":"g0r 3c0",
    "addr:street":"Rue Principale",
    "iso:country":"CA",
    "sg:address":"225 Rue Principale",
    "sg:city":"Saint-Gervais",
    "sg:classifiers":[
        {
            "category":"Organizations",
            "subcategory":"Religious Organization",
            "type":"Services"
        }
    ],
    "sg:phone":"+1 418 887 3248",
    "sg:postcode":"G0R 3C0",
    "sg:province":"QC",
    "sg:tags":[
        "church"
    ],
    "wof:name":"Presbytere DE St-Gervais",
    "wof:placetype":"venue"
},
  "geometry": {"coordinates":[-70.887978,46.714314],"type":"Point"}
}