{
  "type": "Feature",
  "properties": {
    "addr:full":"109 Rte Du President-Kennedy Levis QC G6V 6C8",
    "addr:housenumber":"109",
    "addr:postcode":"g6v 6c8",
    "addr:street":"Rte Du President-Kennedy",
    "iso:country":"CA",
    "sg:address":"109 Rte Du President-Kennedy",
    "sg:city":"Levis",
    "sg:classifiers":[
        {
            "category":"Home & Garden",
            "subcategory":"Building Materials",
            "type":"Retail Goods"
        }
    ],
    "sg:phone":"+1 418 833 7777",
    "sg:postcode":"G6V 6C8",
    "sg:province":"QC",
    "sg:tags":[
        "glass",
        "window",
        "plate"
    ],
    "wof:name":"Lebeau Vitres D'Autos",
    "wof:placetype":"venue"
},
  "geometry": {"coordinates":[-71.16748046879999,46.7892723083],"type":"Point"}
}