{
  "type": "Feature",
  "properties": {
    "addr:full":"Emsdale ON P0A 1J0",
    "addr:postcode":"p0a 1j0",
    "iso:country":"CA",
    "sg:city":"Emsdale",
    "sg:classifiers":[
        {
            "category":"Travel",
            "subcategory":"Hotels & Motels",
            "type":"Entertainment"
        }
    ],
    "sg:phone":"+1 705 636 5390",
    "sg:postcode":"P0A 1J0",
    "sg:province":"ON",
    "sg:tags":[
        "cottage",
        "cabin"
    ],
    "wof:name":"Maple Brae Cottages",
    "wof:placetype":"venue"
},
  "geometry": {"coordinates":[-79.3152084351,45.5264701843],"type":"Point"}
}