{
  "type": "Feature",
  "properties": {
    "addr:full":"640 Grande Allee E Quebec QC G1R 2K5",
    "addr:housenumber":"640",
    "addr:postcode":"g1r 2k5",
    "addr:street":"Grande Allee E",
    "iso:country":"CA",
    "sg:address":"640 Grande Allee E",
    "sg:city":"Quebec",
    "sg:classifiers":[
        {
            "category":"Restaurant",
            "type":"Food & Drink"
        }
    ],
    "sg:phone":"+1 418 522 3449",
    "sg:postcode":"G1R 2K5",
    "sg:province":"QC",
    "wof:name":"Chez Ashton",
    "wof:placetype":"venue"
},
  "geometry": {"coordinates":[-71.216461,46.806557],"type":"Point"}
}