{
  "type": "Feature",
  "properties": {
    "addr:full":"5043 50A St Sylvan Lake AB T4S 1R1",
    "addr:housenumber":"5043",
    "addr:postcode":"t4s 1r1",
    "addr:street":"50A St",
    "iso:country":"CA",
    "sg:address":"5043 50A St",
    "sg:city":"Sylvan Lake",
    "sg:classifiers":[
        {
            "category":"Shopping",
            "subcategory":"Pharmacy",
            "type":"Retail Goods"
        }
    ],
    "sg:phone":"+1 403 887 3772",
    "sg:postcode":"T4S 1R1",
    "sg:province":"AB",
    "sg:tags":[
        "photo",
        "finishing"
    ],
    "wof:name":"Sylvan Lake Value Drug Mart",
    "wof:placetype":"venue"
},
  "geometry": {"coordinates":[-114.09850311300001,52.3091850281],"type":"Point"}
}