{
  "type": "Feature",
  "properties": {
    "iso:country":"CA",
    "sg:address":"1492 Boul Shevchenko",
    "sg:city":"Lasalle",
    "sg:classifiers":[
        {
            "category":"Bars & Pubs",
            "type":"Food & Drink"
        }
    ],
    "sg:phone":"+1 514 363 3111",
    "sg:postcode":"H8N 1P1",
    "sg:province":"QC",
    "sg:tags":[
        "lounge",
        "cocktail"
    ],
    "wof:name":"Haraiki Cocktail Lounge",
    "wof:placetype":"venue"
},
  "geometry": {"coordinates":[-73.62358093260001,45.4309082031],"type":"Point"}
}