{
  "type": "Feature",
  "properties": {
    "addr:full":"4103 Macdonald St Vancouver BC V6L 2P1",
    "addr:housenumber":"4103",
    "addr:postcode":"v6l 2p1",
    "addr:street":"Macdonald St",
    "iso:country":"CA",
    "sg:address":"4103 Macdonald St",
    "sg:city":"Vancouver",
    "sg:classifiers":[
        {
            "category":"Retail",
            "subcategory":"Laundry & Dry Cleaning",
            "type":"Services"
        }
    ],
    "sg:phone":"+1 604 732 6866",
    "sg:postcode":"V6L 2P1",
    "sg:province":"BC",
    "sg:tags":[
        "cleaners"
    ],
    "wof:name":"Mac Donald Dry Cleaning",
    "wof:placetype":"venue"
},
  "geometry": {"coordinates":[-123.16795349100001,49.2500648499],"type":"Point"}
}