{
  "type": "Feature",
  "properties": {
    "addr:full":"1000 Weston Rd York ON M6N 3S1",
    "addr:housenumber":"1000",
    "addr:postcode":"m6n 3s1",
    "addr:street":"Weston Rd",
    "iso:country":"CA",
    "sg:address":"1000 Weston Rd",
    "sg:city":"York",
    "sg:classifiers":[
        {
            "category":"Autos & Motor Vehicles",
            "subcategory":"Auto Supplies",
            "type":"Retail Goods"
        }
    ],
    "sg:phone":"+1 416 763 3566",
    "sg:postcode":"M6N 3S1",
    "sg:province":"ON",
    "sg:tags":[
        "automobile",
        "parts"
    ],
    "wof:name":"West Toronto Spring Svc Ltd",
    "wof:placetype":"venue"
},
  "geometry": {"coordinates":[-79.48432200000001,43.684227],"type":"Point"}
}