{
  "type": "Feature",
  "properties": {
    "addr:full":"1567 Rue DE Touraine Laval QC H7N 5W2",
    "addr:housenumber":"1567",
    "addr:postcode":"h7n 5w2",
    "addr:street":"Rue De Touraine",
    "iso:country":"CA",
    "sg:address":"1567 Rue DE Touraine",
    "sg:city":"Laval",
    "sg:classifiers":[
        {
            "category":"Building & Trades",
            "subcategory":"Plumbing",
            "type":"Services"
        }
    ],
    "sg:phone":"+1 450 662 3225",
    "sg:postcode":"H7N 5W2",
    "sg:province":"QC",
    "sg:tags":[
        "conditioning",
        "air",
        "system",
        "contractor"
    ],
    "wof:name":"Ventilation S & S Bergeron",
    "wof:placetype":"venue"
},
  "geometry": {"coordinates":[-73.70858,45.574696],"type":"Point"}
}