{
  "type": "Feature",
  "properties": {
    "iso:country":"CA",
    "sg:address":"NW 27 17 15",
    "sg:city":"Riding Mountain",
    "sg:classifiers":[
        {
            "category":"Building & Trades",
            "subcategory":"Construction",
            "type":"Services"
        }
    ],
    "sg:phone":"+1 204 966 3890",
    "sg:postcode":"R0J 1T0",
    "sg:province":"MB",
    "sg:tags":[
        "home",
        "builder"
    ],
    "wof:name":"G Friesen Enterprises",
    "wof:placetype":"venue"
},
  "geometry": {"coordinates":[-101.086395264,52.3841896057],"type":"Point"}
}