{
  "type": "Feature",
  "properties": {
    "addr:full":"Etobicoke ON M9W 6B2",
    "addr:postcode":"m9w 6b2",
    "iso:country":"CA",
    "sg:city":"Etobicoke",
    "sg:classifiers":[
        {
            "category":"Manufacturing",
            "subcategory":"Food",
            "type":"Manufacturing & Wholesale Goods"
        }
    ],
    "sg:phone":"+1 416 744 3986",
    "sg:postcode":"M9W 6B2",
    "sg:province":"ON",
    "sg:tags":[
        "bakery",
        "prod",
        "cookie"
    ],
    "wof:name":"Mom's Best Gourmet Foods Inc",
    "wof:placetype":"venue"
},
  "geometry": {"coordinates":[-79.5790939331,43.7166404724],"type":"Point"}
}