{
  "type": "Feature",
  "properties": {
    "addr:full":"Kenora ON P9N 1M2",
    "addr:postcode":"p9n 1m2",
    "iso:country":"CA",
    "sg:city":"Kenora",
    "sg:classifiers":[
        {
            "category":"Food & Beverages",
            "subcategory":"Bakery",
            "type":"Retail Goods"
        }
    ],
    "sg:phone":"+1 807 467 8667",
    "sg:postcode":"P9N 1M2",
    "sg:province":"ON",
    "sg:tags":[
        "doughnut"
    ],
    "wof:name":"Tim Hortons",
    "wof:placetype":"venue"
},
  "geometry": {"coordinates":[-94.469246,49.759949],"type":"Point"}
}