{
  "type": "Feature",
  "properties": {
    "iso:country":"CA",
    "sg:address":"3950 Boul Harvey",
    "sg:city":"Jonquiere",
    "sg:classifiers":[
        {
            "category":"Government",
            "subcategory":"Office",
            "type":"Public Place"
        }
    ],
    "sg:phone":"+1 418 695 7970",
    "sg:postcode":"G7X 8L6",
    "sg:province":"QC",
    "wof:name":"Quebec Ministere Des Regions",
    "wof:placetype":"venue"
},
  "geometry": {"coordinates":[-71.2561798096,48.4141311646],"type":"Point"}
}