{
  "type": "Feature",
  "properties": {
    "addr:full":"Guelph ON N1H 3M3",
    "addr:postcode":"n1h 3m3",
    "iso:country":"CA",
    "sg:city":"Guelph",
    "sg:classifiers":[
        {
            "category":"Manufacturing",
            "subcategory":"Printing",
            "type":"Manufacturing & Wholesale Goods"
        }
    ],
    "sg:phone":"+1 519 821 4576",
    "sg:postcode":"N1H 3M3",
    "sg:province":"ON",
    "sg:tags":[
        "newspaper"
    ],
    "wof:name":"Guida Italian Newspaper",
    "wof:placetype":"venue"
},
  "geometry": {"coordinates":[-80.25636299999999,43.533676],"type":"Point"}
}