{
  "type": "Feature",
  "properties": {
    "addr:full":"1821 Grant Ave Winnipeg MB R3N 0N1",
    "addr:housenumber":"1821",
    "addr:postcode":"r3n 0n1",
    "addr:street":"Grant Ave",
    "iso:country":"CA",
    "sg:address":"1821 Grant Ave",
    "sg:city":"Winnipeg",
    "sg:classifiers":[
        {
            "category":"Organizations",
            "subcategory":"Religious Organization",
            "type":"Services"
        }
    ],
    "sg:phone":"+1 204 489 7301",
    "sg:postcode":"R3N 0N1",
    "sg:province":"MB",
    "sg:tags":[
        "synagogue"
    ],
    "wof:name":"Lubavtich Centre",
    "wof:placetype":"venue"
},
  "geometry": {"coordinates":[-97.200844,49.857193],"type":"Point"}
}