{
  "type": "Feature",
  "properties": {
    "addr:full":"4441 50 Ave St Paul AB T0A 3A3",
    "addr:housenumber":"4441",
    "addr:postcode":"t0a 3a3",
    "addr:street":"50 Ave",
    "iso:country":"CA",
    "sg:address":"4441 50 Ave",
    "sg:city":"St Paul",
    "sg:classifiers":[
        {
            "category":"Personal",
            "subcategory":"Beauty Salon",
            "type":"Services"
        }
    ],
    "sg:phone":"+1 780 645 2964",
    "sg:postcode":"T0A 3A3",
    "sg:province":"AB",
    "wof:name":"Magic Fingers Design Team",
    "wof:placetype":"venue"
},
  "geometry": {"coordinates":[-111.279930115,53.9912109375],"type":"Point"}
}