{
  "type": "Feature",
  "properties": {
    "addr:full":"820 8E Rang Mont-Tremblant QC J8E 1X2",
    "addr:housenumber":"820",
    "addr:postcode":"j8e 1x2",
    "addr:street":"8E Rang",
    "iso:country":"CA",
    "sg:address":"820 8E Rang",
    "sg:city":"Mont-Tremblant",
    "sg:classifiers":[
        {
            "category":"Retail",
            "subcategory":"Animal Services",
            "type":"Services"
        }
    ],
    "sg:phone":"+1 819 425 8484",
    "sg:postcode":"J8E 1X2",
    "sg:province":"QC",
    "sg:tags":[
        "cat",
        "dog",
        "kennel"
    ],
    "wof:name":"Chenil DE LA Foret",
    "wof:placetype":"venue"
},
  "geometry": {"coordinates":[-74.533241272,46.148891449],"type":"Point"}
}