{
  "type": "Feature",
  "properties": {
    "addr:full":"2865 Boul Masson Quebec QC G1P 1J7",
    "addr:housenumber":"2865",
    "addr:postcode":"g1p 1j7",
    "addr:street":"Boul Masson",
    "iso:country":"CA",
    "sg:address":"2865 Boul Masson",
    "sg:city":"Quebec",
    "sg:classifiers":[
        {
            "category":"Food & Beverages",
            "subcategory":"Groceries & Convenience Stores",
            "type":"Retail Goods"
        }
    ],
    "sg:phone":"+1 418 872 3003",
    "sg:postcode":"G1P 1J7",
    "sg:province":"QC",
    "sg:tags":[
        "grocer"
    ],
    "wof:name":"Delicatesse Europeenne",
    "wof:placetype":"venue"
},
  "geometry": {"coordinates":[-71.3214416504,46.8112373352],"type":"Point"}
}