{
  "type": "Feature",
  "properties": {
    "addr:full":"275 Bernard Ave Kelowna BC V1Y 6N2",
    "addr:housenumber":"275",
    "addr:postcode":"v1y 6n2",
    "addr:street":"Bernard Ave",
    "iso:country":"CA",
    "sg:address":"275 Bernard Ave",
    "sg:city":"Kelowna",
    "sg:classifiers":[
        {
            "category":"Restaurant",
            "type":"Food & Drink"
        }
    ],
    "sg:phone":"+1 250 763 5020",
    "sg:postcode":"V1Y 6N2",
    "sg:province":"BC",
    "wof:name":"Seven Seas Restaurant",
    "wof:placetype":"venue"
},
  "geometry": {"coordinates":[-119.497276306,49.8861694336],"type":"Point"}
}