{
  "type": "Feature",
  "properties": {
    "addr:full":"2373 Beacon Ave Sidney BC V8L 1W9",
    "addr:housenumber":"2373",
    "addr:postcode":"v8l 1w9",
    "addr:street":"Beacon Ave",
    "iso:country":"CA",
    "sg:address":"2373 Beacon Ave",
    "sg:city":"Sidney",
    "sg:classifiers":[
        {
            "category":"Personal",
            "subcategory":"Beauty Salon",
            "type":"Services"
        }
    ],
    "sg:phone":"+1 250 656 1713",
    "sg:postcode":"V8L 1W9",
    "sg:province":"BC",
    "wof:name":"Cameo Beauty Salon",
    "wof:placetype":"venue"
},
  "geometry": {"coordinates":[-123.401253,48.648815],"type":"Point"}
}