{
  "type": "Feature",
  "properties": {
    "addr:full":"134 Talbot St W Leamington ON N8H 1N3",
    "addr:housenumber":"134",
    "addr:postcode":"n8h 1n3",
    "addr:street":"Talbot St W",
    "iso:country":"CA",
    "sg:address":"134 Talbot St W",
    "sg:city":"Leamington",
    "sg:classifiers":[
        {
            "category":"Restaurant",
            "type":"Food & Drink"
        }
    ],
    "sg:phone":"+1 519 326 5738",
    "sg:postcode":"N8H 1N3",
    "sg:province":"ON",
    "wof:name":"Kfc",
    "wof:placetype":"venue"
},
  "geometry": {"coordinates":[-82.60906199999999,42.05072],"type":"Point"}
}