{
  "type": "Feature",
  "properties": {
    "addr:full":"406 Hornby St Vancouver BC V6C 3J1",
    "addr:housenumber":"406",
    "addr:postcode":"bc v6c 3j1",
    "addr:street":"Hornby St",
    "iso:country":"CA",
    "sg:address":"406 Hornby St",
    "sg:city":"Vancouver",
    "sg:classifiers":[
        {
            "category":"Restaurant",
            "type":"Food & Drink"
        }
    ],
    "sg:phone":"+1 604 688 3354",
    "sg:postcode":"V6C 3J1",
    "sg:province":"BC",
    "wof:name":"Edelweiss Delicatessen",
    "wof:placetype":"venue"
},
  "geometry": {"coordinates":[-123.11573,49.286407],"type":"Point"}
}