{
  "type": "Feature",
  "properties": {
    "iso:country":"CA",
    "sg:address":"8 Bayside Dr",
    "sg:city":"Saint John",
    "sg:classifiers":[
        {
            "category":"Wholesale",
            "subcategory":"Office Equipment",
            "type":"Manufacturing & Wholesale Goods"
        }
    ],
    "sg:phone":"+1 506 657 2319",
    "sg:postcode":"E2J 1A2",
    "sg:province":"NB",
    "sg:tags":[
        "machine",
        "duplicating",
        "copying"
    ],
    "wof:name":"Southern New Brunswick Office",
    "wof:placetype":"venue"
},
  "geometry": {"coordinates":[-66.0425109863,45.2865524292],"type":"Point"}
}