{
  "type": "Feature",
  "properties": {
    "addr:full":"267 Boul Brien Repentigny QC J6A 6S4",
    "addr:housenumber":"267",
    "addr:postcode":"j6a 6s4",
    "addr:street":"Boul Brien",
    "iso:country":"CA",
    "sg:address":"267 Boul Brien",
    "sg:city":"Repentigny",
    "sg:classifiers":[
        {
            "category":"Personal",
            "subcategory":"Beauty Salon",
            "type":"Services"
        }
    ],
    "sg:phone":"+1 450 581 2272",
    "sg:postcode":"J6A 6S4",
    "sg:province":"QC",
    "wof:name":"Complexe LA Fine Pointe Enr",
    "wof:placetype":"venue"
},
  "geometry": {"coordinates":[-73.465416,45.749825],"type":"Point"}
}