{
  "type": "Feature",
  "properties": {
    "iso:country":"CA",
    "sg:address":"3845 Bathurst St",
    "sg:city":"North York",
    "sg:classifiers":[
        {
            "category":"Real Estate",
            "subcategory":"Real Estate Agent",
            "type":"Services"
        }
    ],
    "sg:phone":"+1 416 665 9810",
    "sg:postcode":"M3H 3N2",
    "sg:province":"ON",
    "sg:tags":[
        "management"
    ],
    "wof:name":"W A Construction CO Ltd",
    "wof:placetype":"venue"
},
  "geometry": {"coordinates":[-79.4345550537,43.7403831482],"type":"Point"}
}