{
  "type": "Feature",
  "properties": {
    "addr:full":"470 Cecelia Rd Victoria BC V8T 4T5",
    "addr:housenumber":"470",
    "addr:postcode":"v8t 4t5",
    "addr:street":"Cecelia Rd",
    "iso:country":"CA",
    "sg:address":"470 Cecelia Rd",
    "sg:city":"Victoria",
    "sg:classifiers":[
        {
            "category":"Organizations",
            "subcategory":"Religious Organization",
            "type":"Services"
        }
    ],
    "sg:phone":"+1 250 475 2280",
    "sg:postcode":"V8T 4T5",
    "sg:province":"BC",
    "sg:tags":[
        "church"
    ],
    "wof:name":"Gurdwara Singh Sabha",
    "wof:placetype":"venue"
},
  "geometry": {"coordinates":[-123.376801,48.444],"type":"Point"}
}