{
  "type": "Feature",
  "properties": {
    "addr:full":"Saskatoon SK S7L 6H5",
    "addr:postcode":"s7l 6h5",
    "iso:country":"CA",
    "sg:city":"Saskatoon",
    "sg:classifiers":[
        {
            "category":"Professional",
            "subcategory":"Engineering",
            "type":"Services"
        }
    ],
    "sg:phone":"+1 306 652 1800",
    "sg:postcode":"S7L 6H5",
    "sg:province":"SK",
    "sg:tags":[
        "engineer"
    ],
    "wof:name":"Loken Engineering Svc",
    "wof:placetype":"venue"
},
  "geometry": {"coordinates":[-106.685783,52.15453],"type":"Point"}
}