{
  "type": "Feature",
  "properties": {
    "addr:full":"241 Columbia Ave Castlegar BC V1N 1G3",
    "addr:housenumber":"241",
    "addr:postcode":"v1n 1g3",
    "addr:street":"Columbia Ave",
    "iso:country":"CA",
    "sg:address":"241 Columbia Ave",
    "sg:city":"Castlegar",
    "sg:classifiers":[
        {
            "category":"Professional",
            "subcategory":"Accounting & Tax Preparation",
            "type":"Services"
        }
    ],
    "sg:phone":"+1 250 365 7287",
    "sg:postcode":"V1N 1G3",
    "sg:province":"BC",
    "sg:tags":[
        "accountant"
    ],
    "wof:name":"Moroso Markin & Blain",
    "wof:placetype":"venue"
},
  "geometry": {"coordinates":[-117.665145874,49.3270683289],"type":"Point"}
}