{
  "type": "Feature",
  "properties": {
    "addr:full":"155 Elm St Sudbury ON P3C 1T9",
    "addr:housenumber":"155",
    "addr:postcode":"p3c 1t9",
    "addr:street":"Elm St",
    "iso:country":"CA",
    "sg:address":"155 Elm St",
    "sg:city":"Sudbury",
    "sg:classifiers":[
        {
            "category":"Government",
            "subcategory":"Office",
            "type":"Public Place"
        }
    ],
    "sg:phone":"+1 705 564 7600",
    "sg:postcode":"P3C 1T9",
    "sg:province":"ON",
    "wof:name":"Bureaux DE L'Execution DE LA",
    "wof:placetype":"venue"
},
  "geometry": {"coordinates":[-81.00145721440001,46.4929733276],"type":"Point"}
}