{
  "type": "Feature",
  "properties": {
    "addr:full":"Dummer Rd Warsaw ON K0L 3A0",
    "addr:postcode":"k0l 3a0",
    "addr:street":"Dummer Rd",
    "iso:country":"CA",
    "sg:address":"Dummer Rd",
    "sg:city":"Warsaw",
    "sg:classifiers":[
        {
            "category":"Government",
            "subcategory":"Office",
            "type":"Public Place"
        }
    ],
    "sg:phone":"+1 705 652 8402",
    "sg:postcode":"K0L 3A0",
    "sg:province":"ON",
    "sg:tags":[
        "village"
    ],
    "wof:name":"Dummer Road Department",
    "wof:placetype":"venue"
},
  "geometry": {"coordinates":[-78.13716100000001,44.428085],"type":"Point"}
}