{
  "type": "Feature",
  "properties": {
    "addr:full":"143 2nd St E North Vancouver BC V7L 1C2",
    "addr:housenumber":"143",
    "addr:postcode":"v7l 1c2",
    "addr:street":"2Nd St E",
    "iso:country":"CA",
    "sg:address":"143 2nd St E",
    "sg:city":"North Vancouver",
    "sg:classifiers":[
        {
            "category":"Shopping",
            "subcategory":"Hobbies, Toys, & Games",
            "type":"Retail Goods"
        }
    ],
    "sg:phone":"+1 604 904 8686",
    "sg:postcode":"V7L 1C2",
    "sg:province":"BC",
    "sg:tags":[
        "supply"
    ],
    "wof:name":"Checkpoint Charlie's Games",
    "wof:placetype":"venue"
},
  "geometry": {"coordinates":[-123.076553,49.31197],"type":"Point"}
}