{
  "type": "Feature",
  "properties": {
    "iso:country":"CA",
    "sg:address":"6852 Rue Jean-Talon E # A",
    "sg:city":"Saint-Leonard",
    "sg:classifiers":[
        {
            "category":"Food & Beverages",
            "subcategory":"Groceries & Convenience Stores",
            "type":"Retail Goods"
        }
    ],
    "sg:phone":"+1 514 252 8277",
    "sg:postcode":"H1S 1N1",
    "sg:province":"QC",
    "sg:tags":[
        "grocer"
    ],
    "wof:name":"Marches Bonanza",
    "wof:placetype":"venue"
},
  "geometry": {"coordinates":[-73.57178497309999,45.5955200195],"type":"Point"}
}