{
  "type": "Feature",
  "properties": {
    "addr:full":"33324 South Fraser Way # 5 Abbotsford BC V2S 2B4",
    "addr:housenumber":"33324",
    "addr:postcode":"v2s 2b4",
    "addr:street":"South Fraser Way # 5",
    "iso:country":"CA",
    "sg:address":"33324 South Fraser Way # 5",
    "sg:city":"Abbotsford",
    "sg:classifiers":[
        {
            "category":"Health Services",
            "subcategory":"Doctor",
            "type":"Services"
        }
    ],
    "sg:phone":"+1 604 852 2171",
    "sg:postcode":"V2S 2B4",
    "sg:province":"BC",
    "sg:tags":[
        "dentist"
    ],
    "wof:name":"Edworthy, Samuel DDS",
    "wof:placetype":"venue"
},
  "geometry": {"coordinates":[-122.30101000000001,49.049854],"type":"Point"}
}