{
  "type": "Feature",
  "properties": {
    "addr:full":"850 Av Tecumseh Pointe-Claire QC H9R 4B2",
    "addr:housenumber":"850",
    "addr:postcode":"h9r 4b2",
    "addr:street":"Av Tecumseh",
    "iso:country":"CA",
    "sg:address":"850 Av Tecumseh",
    "sg:city":"Pointe-Claire",
    "sg:classifiers":[
        {
            "category":"Building & Trades",
            "subcategory":"Construction",
            "type":"Services"
        }
    ],
    "sg:phone":"+1 514 630 0099",
    "sg:postcode":"H9R 4B2",
    "sg:province":"QC",
    "sg:tags":[
        "pavement",
        "sealing"
    ],
    "wof:name":"Aqua Force",
    "wof:placetype":"venue"
},
  "geometry": {"coordinates":[-73.814201,45.476406],"type":"Point"}
}