{
  "type": "Feature",
  "properties": {
    "addr:full":"Calgary AB T2E 6V6",
    "addr:postcode":"t2e 6v6",
    "iso:country":"CA",
    "sg:city":"Calgary",
    "sg:classifiers":[
        {
            "category":"Home & Garden",
            "subcategory":"Building Materials",
            "type":"Retail Goods"
        }
    ],
    "sg:phone":"+1 403 250 9770",
    "sg:postcode":"T2E 6V6",
    "sg:province":"AB",
    "sg:tags":[
        "door"
    ],
    "wof:name":"Module Interior Ltd",
    "wof:placetype":"venue"
},
  "geometry": {"coordinates":[-114.00842299999999,51.084381],"type":"Point"}
}