{
  "type": "Feature",
  "properties": {
    "addr:full":"216 18E Av Deux-Montagnes QC J7R 4B1",
    "addr:housenumber":"216",
    "addr:postcode":"j7r 4b1",
    "addr:street":"18E Av Deux-Montagnes",
    "iso:country":"CA",
    "sg:address":"216 18E Av",
    "sg:city":"Deux-Montagnes",
    "sg:classifiers":[
        {
            "category":"Building & Trades",
            "subcategory":"Construction",
            "type":"Services"
        }
    ],
    "sg:phone":"+1 450 472 6239",
    "sg:postcode":"J7R 4B1",
    "sg:province":"QC",
    "sg:tags":[
        "repairing",
        "remodeling",
        "contractor"
    ],
    "wof:name":"Renovation Asp Inc",
    "wof:placetype":"venue"
},
  "geometry": {"coordinates":[-73.9011,45.536491],"type":"Point"}
}