{
  "type": "Feature",
  "properties": {
    "addr:full":"Etobicoke ON M8Y 1K9",
    "addr:postcode":"m8y 1k9",
    "iso:country":"CA",
    "sg:city":"Etobicoke",
    "sg:classifiers":[
        {
            "category":"Professional",
            "subcategory":"Computer Services",
            "type":"Services"
        }
    ],
    "sg:phone":"+1 416 255 2022",
    "sg:postcode":"M8Y 1K9",
    "sg:province":"ON",
    "sg:tags":[
        "internet"
    ],
    "wof:name":"Define.ca",
    "wof:placetype":"venue"
},
  "geometry": {"coordinates":[-79.499718,43.627102],"type":"Point"}
}