{
  "type": "Feature",
  "properties": {
    "addr:full":"4875 Rue Bourg Saint-Laurent QC H4T 1H9",
    "addr:housenumber":"4875",
    "addr:postcode":"h4t 1h9",
    "addr:street":"Rue Bourg",
    "iso:country":"CA",
    "sg:address":"4875 Rue Bourg",
    "sg:city":"Saint-Laurent",
    "sg:classifiers":[
        {
            "category":"Wholesale",
            "subcategory":"Machinery & Supplies",
            "type":"Manufacturing & Wholesale Goods"
        }
    ],
    "sg:phone":"+1 514 341 3432",
    "sg:postcode":"H4T 1H9",
    "sg:province":"QC",
    "sg:tags":[
        "compressor",
        "gas"
    ],
    "wof:name":"Compair Canada Inc",
    "wof:placetype":"venue"
},
  "geometry": {"coordinates":[-73.701065,45.473129],"type":"Point"}
}