{
  "type": "Feature",
  "properties": {
    "addr:full":"Toronto ON M4V 2Y7",
    "addr:postcode":"m4v 2y7",
    "iso:country":"CA",
    "sg:city":"Toronto",
    "sg:classifiers":[
        {
            "category":"Organizations",
            "subcategory":"Professional Association",
            "type":"Services"
        }
    ],
    "sg:phone":"+1 416 944 9727",
    "sg:postcode":"M4V 2Y7",
    "sg:province":"ON",
    "wof:name":"Inst Chartered Secretaries",
    "wof:placetype":"venue"
},
  "geometry": {"coordinates":[-79.398697,43.687016],"type":"Point"}
}