{
  "type": "Feature",
  "properties": {
    "addr:full":"London ON N6A 5N6",
    "addr:postcode":"n6a 5n6",
    "iso:country":"CA",
    "sg:city":"London",
    "sg:classifiers":[
        {
            "category":"Professional",
            "subcategory":"Employment Agencies",
            "type":"Services"
        }
    ],
    "sg:phone":"+1 519 672 2795",
    "sg:postcode":"N6A 5N6",
    "sg:province":"ON",
    "sg:tags":[
        "consultant",
        "search",
        "executive"
    ],
    "wof:name":"Express Professional Staffing",
    "wof:placetype":"venue"
},
  "geometry": {"coordinates":[-81.25202899999999,42.986542],"type":"Point"}
}