{
  "type": "Feature",
  "properties": {
    "addr:full":"Calgary AB T2E 6X8",
    "addr:postcode":"t2e 6x8",
    "iso:country":"CA",
    "sg:city":"Calgary",
    "sg:classifiers":[
        {
            "category":"Manufacturing",
            "subcategory":"Printing",
            "type":"Manufacturing & Wholesale Goods"
        }
    ],
    "sg:phone":"+1 403 250 8933",
    "sg:postcode":"T2E 6X8",
    "sg:province":"AB",
    "sg:tags":[
        "printer"
    ],
    "wof:name":"Emerson Clarke Printing",
    "wof:placetype":"venue"
},
  "geometry": {"coordinates":[-114.011993408,51.0884933472],"type":"Point"}
}