{
  "type": "Feature",
  "properties": {
    "iso:country":"CA",
    "sg:city":"Vaudreuil-Dorion",
    "sg:classifiers":[
        {
            "category":"Professional",
            "subcategory":"Business Services",
            "type":"Services"
        }
    ],
    "sg:phone":"+1 450 455 6534",
    "sg:postcode":"J7V 7W1",
    "sg:province":"QC",
    "sg:tags":[
        "interior",
        "consultant",
        "design",
        "decorator"
    ],
    "wof:name":"P E Felx & Fils Inc",
    "wof:placetype":"venue"
},
  "geometry": {"coordinates":[-74.018867,45.379829],"type":"Point"}
}