{
  "type": "Feature",
  "properties": {
    "addr:full":"21 Morrow Ave Toronto ON M6R 2H9",
    "addr:housenumber":"21",
    "addr:postcode":"m6r 2h9",
    "addr:street":"Morrow Ave",
    "iso:country":"CA",
    "sg:address":"21 Morrow Ave",
    "sg:city":"Toronto",
    "sg:classifiers":[
        {
            "category":"Shopping",
            "type":"Retail Goods"
        }
    ],
    "sg:phone":"+1 416 532 5566",
    "sg:postcode":"M6R 2H9",
    "sg:province":"ON",
    "sg:tags":[
        "art",
        "gallery",
        "dealer"
    ],
    "wof:name":"Christopher Cutts Gallery",
    "wof:placetype":"venue"
},
  "geometry": {"coordinates":[-79.4469070435,43.6526145935],"type":"Point"}
}