{
  "type": "Feature",
  "properties": {
    "addr:full":"23 Graham Ave St Catharines ON L2N 5L3",
    "addr:housenumber":"23",
    "addr:postcode":"l2n 5l3",
    "addr:street":"Graham Ave",
    "iso:country":"CA",
    "sg:address":"23 Graham Ave",
    "sg:city":"St Catharines",
    "sg:classifiers":[
        {
            "category":"Professional",
            "subcategory":"Business Services",
            "type":"Services"
        }
    ],
    "sg:phone":"+1 905 935 7617",
    "sg:postcode":"L2N 5L3",
    "sg:province":"ON",
    "sg:tags":[
        "interior",
        "consultant",
        "design",
        "decorator"
    ],
    "wof:name":"Catherine Campbell Interior",
    "wof:placetype":"venue"
},
  "geometry": {"coordinates":[-79.28022799999999,43.19902],"type":"Point"}
}