{
  "type": "Feature",
  "properties": {
    "addr:full":"97 Ohio Rd Shelburne NS B0T 1W0",
    "addr:housenumber":"97",
    "addr:postcode":"b0t 1w0",
    "addr:street":"Ohio Rd",
    "iso:country":"CA",
    "sg:address":"97 Ohio Rd",
    "sg:city":"Shelburne",
    "sg:classifiers":[
        {
            "category":"Shopping",
            "type":"Retail Goods"
        }
    ],
    "sg:phone":"+1 902 875 3379",
    "sg:postcode":"B0T 1W0",
    "sg:province":"NS",
    "sg:tags":[
        "monument"
    ],
    "wof:name":"Nelson Monuments Ltd",
    "wof:placetype":"venue"
},
  "geometry": {"coordinates":[-65.31564331049999,43.7656593323],"type":"Point"}
}