{
  "type": "Feature",
  "properties": {
    "addr:full":"2110 Henry Ave Sidney BC V8L 4L9",
    "addr:housenumber":"2110",
    "addr:postcode":"v8l 4l9",
    "addr:street":"Henry Ave",
    "iso:country":"CA",
    "sg:address":"2110 Henry Ave",
    "sg:city":"Sidney",
    "sg:classifiers":[
        {
            "category":"Manufacturing",
            "subcategory":"Buildings",
            "type":"Manufacturing & Wholesale Goods"
        }
    ],
    "sg:phone":"+1 250 656 0915",
    "sg:postcode":"V8L 4L9",
    "sg:province":"BC",
    "sg:tags":[
        "prefab"
    ],
    "wof:name":"Dean Development Ltd",
    "wof:placetype":"venue"
},
  "geometry": {"coordinates":[-123.409401,48.653294],"type":"Point"}
}