{
  "type": "Feature",
  "properties": {
    "addr:full":"48 Church St Orangeville ON L9W 1N8",
    "addr:housenumber":"48",
    "addr:postcode":"l9w 1n8",
    "addr:street":"Church St",
    "iso:country":"CA",
    "sg:address":"48 Church St",
    "sg:city":"Orangeville",
    "sg:classifiers":[
        {
            "category":"Health Services",
            "subcategory":"Doctor",
            "type":"Services"
        }
    ],
    "sg:phone":"+1 519 942 8022",
    "sg:postcode":"L9W 1N8",
    "sg:province":"ON",
    "sg:tags":[
        "physician",
        "surgeon"
    ],
    "wof:name":"Riddell, D Alex MD",
    "wof:placetype":"venue"
},
  "geometry": {"coordinates":[-80.0981140137,43.9154205322],"type":"Point"}
}