{
  "type": "Feature",
  "properties": {
    "addr:full":"1407 Dugald Rd Winnipeg MB R2J 0H3",
    "addr:housenumber":"1407",
    "addr:postcode":"r2j 0h3",
    "addr:street":"Dugald Rd",
    "iso:country":"CA",
    "sg:address":"1407 Dugald Rd",
    "sg:city":"Winnipeg",
    "sg:classifiers":[
        {
            "category":"Building & Trades",
            "subcategory":"Landscaping Services",
            "type":"Services"
        }
    ],
    "sg:phone":"+1 204 233 9337",
    "sg:postcode":"R2J 0H3",
    "sg:province":"MB",
    "sg:tags":[
        "tree"
    ],
    "wof:name":"Kildonan Tree Svc Ltd",
    "wof:placetype":"venue"
},
  "geometry": {"coordinates":[-97.054688,49.886074],"type":"Point"}
}