{
  "type": "Feature",
  "properties": {
    "addr:full":"16 Woodgate Bay SW Calgary AB T2W 4B8",
    "addr:housenumber":"16",
    "addr:postcode":"t2w 4b8",
    "addr:street":"Woodgate Bay Sw",
    "iso:country":"CA",
    "sg:address":"16 Woodgate Bay SW",
    "sg:city":"Calgary",
    "sg:classifiers":[
        {
            "category":"Professional",
            "subcategory":"Accounting & Tax Preparation",
            "type":"Services"
        }
    ],
    "sg:phone":"+1 403 238 3266",
    "sg:postcode":"T2W 4B8",
    "sg:province":"AB",
    "sg:tags":[
        "accountant"
    ],
    "wof:name":"Entrepreneurial Cas-Calgary",
    "wof:placetype":"venue"
},
  "geometry": {"coordinates":[-114.10154,50.937576],"type":"Point"}
}