{
  "type": "Feature",
  "properties": {
    "addr:full":"2695 Macdonald Dr Victoria BC V8N 1Y1",
    "addr:housenumber":"2695",
    "addr:postcode":"v8n 1y1",
    "addr:street":"Macdonald Dr",
    "iso:country":"CA",
    "sg:address":"2695 Macdonald Dr",
    "sg:city":"Victoria",
    "sg:classifiers":[
        {
            "category":"Real Estate",
            "subcategory":"Surveying",
            "type":"Services"
        }
    ],
    "sg:phone":"+1 250 721 1352",
    "sg:postcode":"V8N 1Y1",
    "sg:province":"BC",
    "sg:tags":[
        "surveyor"
    ],
    "wof:name":"A C Consulting",
    "wof:placetype":"venue"
},
  "geometry": {"coordinates":[-123.36451700000001,48.428314],"type":"Point"}
}