{
  "type": "Feature",
  "properties": {
    "addr:full":"100 Rue Moreau Saint-Luc QC J2W 2M4",
    "addr:housenumber":"100",
    "addr:postcode":"j2w 2m4",
    "addr:street":"Rue Moreau",
    "iso:country":"CA",
    "sg:address":"100 Rue Moreau",
    "sg:city":"Saint-Luc",
    "sg:classifiers":[
        {
            "category":"Home & Garden",
            "subcategory":"Household Appliances",
            "type":"Retail Goods"
        }
    ],
    "sg:phone":"+1 450 349 0066",
    "sg:postcode":"J2W 2M4",
    "sg:province":"QC",
    "wof:name":"Corbeil Electromenagers",
    "wof:placetype":"venue"
},
  "geometry": {"coordinates":[-73.28877300000001,45.341961],"type":"Point"}
}