{
  "type": "Feature",
  "properties": {
    "addr:full":"Montreal QC H3H 2N4",
    "addr:postcode":"h3h 2n4",
    "iso:country":"CA",
    "sg:city":"Montreal",
    "sg:classifiers":[
        {
            "category":"Personal",
            "type":"Services"
        }
    ],
    "sg:phone":"+1 514 273 5434",
    "sg:postcode":"H3H 2N4",
    "sg:province":"QC",
    "sg:tags":[
        "dating"
    ],
    "wof:name":"Agence L'Eden",
    "wof:placetype":"venue"
},
  "geometry": {"coordinates":[-73.554672,45.522472],"type":"Point"}
}