{
  "type": "Feature",
  "properties": {
    "iso:country":"CA",
    "sg:address":"2 College St",
    "sg:city":"Toronto",
    "sg:classifiers":[
        {
            "category":"Restaurant",
            "type":"Food & Drink"
        }
    ],
    "sg:phone":"+1 416 964 1313",
    "sg:postcode":"M5G 1K3",
    "sg:province":"ON",
    "sg:tags":[
        "caterer"
    ],
    "wof:name":"Greek Island Catering",
    "wof:placetype":"venue"
},
  "geometry": {"coordinates":[-79.3831787109,43.6613769531],"type":"Point"}
}