{
  "type": "Feature",
  "properties": {
    "iso:country":"CA",
    "sg:city":"Ottawa",
    "sg:classifiers":[
        {
            "category":"Real Estate",
            "subcategory":"Real Estate Agent",
            "type":"Services"
        }
    ],
    "sg:phone":"+1 613 234 4416",
    "sg:postcode":"K1P 5V9",
    "sg:province":"ON",
    "sg:tags":[
        "management"
    ],
    "wof:name":"Dundee Realty Management Corp",
    "wof:placetype":"venue"
},
  "geometry": {"coordinates":[-75.7013015747,45.4201927185],"type":"Point"}
}