{
  "type": "Feature",
  "properties": {
    "addr:full":"125 Rue Beaudry N Joliette QC J6E 6A7",
    "addr:housenumber":"125",
    "addr:postcode":"j6e 6a7",
    "addr:street":"Rue Beaudry N",
    "iso:country":"CA",
    "sg:address":"125 Rue Beaudry N",
    "sg:city":"Joliette",
    "sg:classifiers":[
        {
            "category":"Professional",
            "subcategory":"Lawyer & Legal Services",
            "type":"Services"
        }
    ],
    "sg:phone":"+1 450 759 3958",
    "sg:postcode":"J6E 6A7",
    "sg:province":"QC",
    "sg:tags":[
        "attorney"
    ],
    "wof:name":"Vincelette, Claudette",
    "wof:placetype":"venue"
},
  "geometry": {"coordinates":[-73.45086669920001,46.0196037292],"type":"Point"}
}