{
  "type": "Feature",
  "properties": {
    "addr:full":"1450 Rebecca St Oakville ON L6L 1Z7",
    "addr:housenumber":"1450",
    "addr:postcode":"l6l 1z7",
    "addr:street":"Rebecca St",
    "iso:country":"CA",
    "sg:address":"1450 Rebecca St",
    "sg:city":"Oakville",
    "sg:classifiers":[
        {
            "category":"Organizations",
            "subcategory":"Religious Organization",
            "type":"Services"
        }
    ],
    "sg:phone":"+1 905 827 0251",
    "sg:postcode":"L6L 1Z7",
    "sg:province":"ON",
    "sg:tags":[
        "church"
    ],
    "wof:name":"Evangel Pentecostal Church",
    "wof:placetype":"venue"
},
  "geometry": {"coordinates":[-79.70375799999999,43.412586],"type":"Point"}
}