{
  "type": "Feature",
  "properties": {
    "addr:full":"205 Main St Elrose SK S0L 0Z0",
    "addr:housenumber":"205",
    "addr:postcode":"s0l 0z0",
    "addr:street":"Main St",
    "iso:country":"CA",
    "sg:address":"205 Main St",
    "sg:city":"Elrose",
    "sg:classifiers":[
        {
            "category":"Food & Beverages",
            "subcategory":"Groceries & Convenience Stores",
            "type":"Retail Goods"
        }
    ],
    "sg:phone":"+1 306 378 2514",
    "sg:postcode":"S0L 0Z0",
    "sg:province":"SK",
    "sg:tags":[
        "grocer"
    ],
    "wof:name":"Torrance Brothers Locker",
    "wof:placetype":"venue"
},
  "geometry": {"coordinates":[-108.033157,51.201462],"type":"Point"}
}