{
  "type": "Feature",
  "properties": {
    "addr:full":"2900 14 Ave NE Calgary AB T2A 6J4",
    "addr:housenumber":"2900",
    "addr:postcode":"t2a 6j4",
    "addr:street":"14 Ave Ne",
    "iso:country":"CA",
    "sg:address":"2900 14 Ave NE",
    "sg:city":"Calgary",
    "sg:classifiers":[
        {
            "category":"Organizations",
            "subcategory":"Religious Organization",
            "type":"Services"
        }
    ],
    "sg:phone":"+1 403 569 8258",
    "sg:postcode":"T2A 6J4",
    "sg:province":"AB",
    "sg:tags":[
        "church"
    ],
    "wof:name":"Jehovah's Witnesses El Reino",
    "wof:placetype":"venue"
},
  "geometry": {"coordinates":[-113.992591858,51.0652084351],"type":"Point"}
}