{
  "type": "Feature",
  "properties": {
    "addr:full":"1730 Guildford Town Ctr Surrey BC V3R 7B8",
    "addr:housenumber":"1730",
    "addr:postcode":"v3r 7b8",
    "addr:street":"Guildford Town Ctr",
    "iso:country":"CA",
    "sg:address":"1730 Guildford Town Ctr",
    "sg:city":"Surrey",
    "sg:classifiers":[
        {
            "category":"Professional",
            "subcategory":"Accounting & Tax Preparation",
            "type":"Services"
        }
    ],
    "sg:phone":"+1 604 584 4149",
    "sg:postcode":"V3R 7B8",
    "sg:province":"BC",
    "sg:tags":[
        "consultant",
        "return",
        "filing"
    ],
    "wof:name":"H & R Block Canada Inc",
    "wof:placetype":"venue"
},
  "geometry": {"coordinates":[-122.802894592,49.1889343262],"type":"Point"}
}