{
  "type": "Feature",
  "properties": {
    "iso:country":"CA",
    "sg:address":"143 Fairway Dr",
    "sg:city":"Coaldale",
    "sg:classifiers":[
        {
            "category":"Manufacturing",
            "subcategory":"Tools & Machinery",
            "type":"Manufacturing & Wholesale Goods"
        }
    ],
    "sg:phone":"+1 403 345 2222",
    "sg:postcode":"T1M 1H2",
    "sg:province":"AB",
    "sg:tags":[
        "feed",
        "electric",
        "supply",
        "contractor",
        "equipment",
        "mill"
    ],
    "wof:name":"Kenner Electric",
    "wof:placetype":"venue"
},
  "geometry": {"coordinates":[-112.63621521,49.7171058655],"type":"Point"}
}