{
  "type": "Feature",
  "properties": {
    "iso:country":"CA",
    "sg:city":"Saint-Jerome",
    "sg:classifiers":[
        {
            "category":"Building & Trades",
            "subcategory":"Cleaning & Sanitation",
            "type":"Services"
        }
    ],
    "sg:phone":"+1 450 569 9262",
    "sg:postcode":"J7Y 4J1",
    "sg:province":"QC",
    "sg:tags":[
        "house",
        "janitor"
    ],
    "wof:name":"Kaivac Canada Inc",
    "wof:placetype":"venue"
},
  "geometry": {"coordinates":[-74.00350952150001,45.7750091553],"type":"Point"}
}