{
  "type": "Feature",
  "properties": {
    "addr:full":"1229 Main St Geraldton ON P0T 1M0",
    "addr:housenumber":"1229",
    "addr:postcode":"p0t 1m0",
    "addr:street":"Main St",
    "iso:country":"CA",
    "sg:address":"1229 Main St",
    "sg:city":"Geraldton",
    "sg:classifiers":[
        {
            "category":"Retail",
            "subcategory":"Laundry & Dry Cleaning",
            "type":"Services"
        }
    ],
    "sg:phone":"+1 807 854 0211",
    "sg:postcode":"P0T 1M0",
    "sg:province":"ON",
    "sg:tags":[
        "cleaners"
    ],
    "wof:name":"Bestway Dry Cleaners",
    "wof:placetype":"venue"
},
  "geometry": {"coordinates":[-86.952538,49.709702],"type":"Point"}
}