{
  "type": "Feature",
  "properties": {
    "addr:full":"180 Cree Cres Winnipeg MB R3J 3W1",
    "addr:housenumber":"180",
    "addr:postcode":"r3j 3w1",
    "addr:street":"Cree Cres",
    "iso:country":"CA",
    "sg:address":"180 Cree Cres",
    "sg:city":"Winnipeg",
    "sg:classifiers":[
        {
            "category":"Manufacturing",
            "subcategory":"Tools & Machinery",
            "type":"Manufacturing & Wholesale Goods"
        }
    ],
    "sg:phone":"+1 204 832 2828",
    "sg:postcode":"R3J 3W1",
    "sg:province":"MB",
    "sg:tags":[
        "machine",
        "shop"
    ],
    "wof:name":"Dimatec Inc",
    "wof:placetype":"venue"
},
  "geometry": {"coordinates":[-97.263863,49.892555],"type":"Point"}
}