{
  "type": "Feature",
  "properties": {
    "addr:full":"Richmond BC V6V 1Z1",
    "addr:postcode":"v6v 1z1",
    "iso:country":"CA",
    "sg:city":"Richmond",
    "sg:classifiers":[
        {
            "category":"Wholesale",
            "subcategory":"Machinery & Supplies",
            "type":"Manufacturing & Wholesale Goods"
        }
    ],
    "sg:phone":"+1 604 276 9557",
    "sg:postcode":"V6V 1Z1",
    "sg:province":"BC",
    "sg:tags":[
        "rope"
    ],
    "wof:name":"Mcm Rope & Rigging Ltd",
    "wof:placetype":"venue"
},
  "geometry": {"coordinates":[-123.06905365,49.1719398499],"type":"Point"}
}