{
  "type": "Feature",
  "properties": {
    "addr:full":"1112 Franklin St Vancouver BC V6A 1J6",
    "addr:housenumber":"1112",
    "addr:postcode":"v6a 1j6",
    "addr:street":"Franklin St",
    "iso:country":"CA",
    "sg:address":"1112 Franklin St",
    "sg:city":"Vancouver",
    "sg:classifiers":[
        {
            "category":"Autos & Motor Vehicles",
            "subcategory":"Auto Supplies",
            "type":"Retail Goods"
        }
    ],
    "sg:phone":"+1 604 255 7696",
    "sg:postcode":"V6A 1J6",
    "sg:province":"BC",
    "sg:tags":[
        "tire"
    ],
    "wof:name":"Pacific Tire Ltd",
    "wof:placetype":"venue"
},
  "geometry": {"coordinates":[-123.080833435,49.282207489],"type":"Point"}
}