{
  "type": "Feature",
  "properties": {
    "addr:full":"6960 Quesnel St Powell River BC V8A 1J2",
    "addr:postcode":"6960;v8a 1j2",
    "addr:street":"Quesnel St",
    "iso:country":"CA",
    "sg:address":"6960 Quesnel St",
    "sg:city":"Powell River",
    "sg:classifiers":[
        {
            "category":"Education",
            "subcategory":"School",
            "type":"Public Place"
        }
    ],
    "sg:phone":"+1 604 485 5660",
    "sg:postcode":"V8A 1J2",
    "sg:province":"BC",
    "wof:name":"Grief Point Elementary School",
    "wof:placetype":"venue"
},
  "geometry": {"coordinates":[-124.522018,49.812977],"type":"Point"}
}