{
  "type": "Feature",
  "properties": {
    "addr:full":"4012 Millar Cres Burlington ON L7R 3X4",
    "addr:housenumber":"4012",
    "addr:postcode":"l7r 3x4",
    "addr:street":"Millar Cres",
    "iso:country":"CA",
    "sg:address":"4012 Millar Cres",
    "sg:city":"Burlington",
    "sg:classifiers":[
        {
            "category":"Building & Trades",
            "subcategory":"Construction",
            "type":"Services"
        }
    ],
    "sg:phone":"+1 905 315 9730",
    "sg:postcode":"L7R 3X4",
    "sg:province":"ON",
    "sg:tags":[
        "roofing",
        "contractor",
        "general"
    ],
    "wof:name":"Grange Roofing Ltd",
    "wof:placetype":"venue"
},
  "geometry": {"coordinates":[-79.85882599999999,43.390705],"type":"Point"}
}