{
  "type": "Feature",
  "properties": {
    "addr:full":"4424 Dundas St E Thorndale ON N0M 2P0",
    "addr:housenumber":"4424",
    "addr:postcode":"n0m 2p0",
    "addr:street":"Dundas St",
    "iso:country":"CA",
    "sg:address":"4424 Dundas St E",
    "sg:city":"Thorndale",
    "sg:classifiers":[
        {
            "category":"Autos & Motor Vehicles",
            "subcategory":"Motorcycle Sales",
            "type":"Retail Goods"
        }
    ],
    "sg:phone":"+1 519 268 3550",
    "sg:postcode":"N0M 2P0",
    "sg:province":"ON",
    "sg:tags":[
        "golf",
        "car",
        "cart",
        "accessory",
        "parts",
        "snowmobile"
    ],
    "wof:name":"Snow Line Sports",
    "wof:placetype":"venue"
},
  "geometry": {"coordinates":[-81.1411819458,43.1051330566],"type":"Point"}
}