{
  "type": "Feature",
  "properties": {
    "addr:full":"4550 Rue Hochelaga Montreal QC H1V 1C5",
    "addr:housenumber":"4550",
    "addr:postcode":"h1v 1c5",
    "addr:street":"Rue Hochelaga",
    "iso:country":"CA",
    "sg:address":"4550 Rue Hochelaga",
    "sg:city":"Montreal",
    "sg:classifiers":[
        {
            "category":"Manufacturing",
            "subcategory":"Jewelry",
            "type":"Manufacturing & Wholesale Goods"
        }
    ],
    "sg:phone":"+1 514 254 9899",
    "sg:postcode":"H1V 1C5",
    "sg:province":"QC",
    "wof:name":"Fusiotronik Inc",
    "wof:placetype":"venue"
},
  "geometry": {"coordinates":[-73.545029,45.557224],"type":"Point"}
}