{
  "type": "Feature",
  "properties": {
    "addr:full":"Fisher Branch MB R0C 0Z0",
    "addr:postcode":"r0c 0z0",
    "iso:country":"CA",
    "sg:city":"Fisher Branch",
    "sg:classifiers":[
        {
            "category":"Travel",
            "subcategory":"Hotels & Motels",
            "type":"Entertainment"
        }
    ],
    "sg:phone":"+1 204 372 6351",
    "sg:postcode":"R0C 0Z0",
    "sg:province":"MB",
    "wof:name":"Fisher Branch Motor Hotel",
    "wof:placetype":"venue"
},
  "geometry": {"coordinates":[-97.618454,51.082603],"type":"Point"}
}