{
  "type": "Feature",
  "properties": {
    "addr:full":"44 Ingram Dr North York ON M6M 2L6",
    "addr:housenumber":"44",
    "addr:postcode":"m6m 2l6",
    "addr:street":"Ingram Dr",
    "iso:country":"CA",
    "sg:address":"44 Ingram Dr",
    "sg:city":"North York",
    "sg:classifiers":[
        {
            "category":"Autos & Motor Vehicles",
            "subcategory":"Automobile Sales",
            "type":"Retail Goods"
        }
    ],
    "sg:phone":"+1 416 247 8999",
    "sg:postcode":"M6M 2L6",
    "sg:province":"ON",
    "sg:tags":[
        "car",
        "dealer"
    ],
    "wof:name":"Legacy Motors",
    "wof:placetype":"venue"
},
  "geometry": {"coordinates":[-79.47086334230001,43.7006759644],"type":"Point"}
}