{
  "type": "Feature",
  "properties": {
    "addr:full":"560 Av Du Phare E Matane QC G4W 1A7",
    "addr:housenumber":"560",
    "addr:postcode":"g4w 1a7",
    "addr:street":"Av Du Phare E",
    "iso:country":"CA",
    "sg:address":"560 Av Du Phare E",
    "sg:city":"Matane",
    "sg:classifiers":[
        {
            "category":"Shopping",
            "subcategory":"Computers & Home Electronics",
            "type":"Retail Goods"
        }
    ],
    "sg:phone":"+1 418 562 3359",
    "sg:postcode":"G4W 1A7",
    "sg:province":"QC",
    "sg:tags":[
        "equipment",
        "dealer"
    ],
    "wof:name":"Informidata Inc",
    "wof:placetype":"venue"
},
  "geometry": {"coordinates":[-67.512688,48.852604],"type":"Point"}
}