{
  "type": "Feature",
  "properties": {
    "addr:full":"12228 113 Ave NW Edmonton AB T5M 2W2",
    "addr:housenumber":"12228",
    "addr:postcode":"t5m 2w2",
    "addr:street":"113 Ave Nw",
    "iso:country":"CA",
    "sg:address":"12228 113 Ave NW",
    "sg:city":"Edmonton",
    "sg:classifiers":[
        {
            "category":"Professional",
            "subcategory":"Art Services",
            "type":"Services"
        }
    ],
    "sg:phone":"+1 780 451 6160",
    "sg:postcode":"T5M 2W2",
    "sg:province":"AB",
    "sg:tags":[
        "graphic",
        "designer"
    ],
    "wof:name":"Halkier & Dutton Design",
    "wof:placetype":"venue"
},
  "geometry": {"coordinates":[-113.53301999999999,53.562305],"type":"Point"}
}