{
  "type": "Feature",
  "properties": {
    "iso:country":"CA",
    "sg:city":"Belleville",
    "sg:classifiers":[
        {
            "category":"Shopping",
            "subcategory":"Department Store",
            "type":"Retail Goods"
        }
    ],
    "sg:phone":"+1 613 966 6486",
    "sg:postcode":"K8N 1G1",
    "sg:province":"ON",
    "sg:tags":[
        "shop"
    ],
    "wof:name":"A Buck or Two",
    "wof:placetype":"venue"
},
  "geometry": {"coordinates":[-77.35340118409999,44.1675300598],"type":"Point"}
}