{
  "type": "Feature",
  "properties": {
    "addr:full":"93 Gerrish St Windsor NS B0N 2T0",
    "addr:housenumber":"93",
    "addr:postcode":"b0n 2t0",
    "addr:street":"Gerrish St",
    "iso:country":"CA",
    "sg:address":"93 Gerrish St",
    "sg:city":"Windsor",
    "sg:classifiers":[
        {
            "category":"Banks & Credit Unions",
            "subcategory":"Investment Brokerage",
            "type":"Services"
        }
    ],
    "sg:phone":"+1 902 798 0164",
    "sg:postcode":"B0N 2T0",
    "sg:province":"NS",
    "wof:name":"Acadian Securities",
    "wof:placetype":"venue"
},
  "geometry": {"coordinates":[-64.1326751709,44.9923667908],"type":"Point"}
}