{
  "type": "Feature",
  "properties": {
    "addr:full":"100 Railway Ave E Outlook SK S0L 2N0",
    "addr:housenumber":"100",
    "addr:postcode":"s0l 2n0",
    "addr:street":"Railway Ave E Outlook",
    "iso:country":"CA",
    "sg:address":"100 Railway Ave E",
    "sg:city":"Outlook",
    "sg:classifiers":[
        {
            "category":"Museum",
            "type":"Entertainment"
        }
    ],
    "sg:phone":"+1 306 867 8285",
    "sg:postcode":"S0L 2N0",
    "sg:province":"SK",
    "wof:name":"Outlook & District Heritage",
    "wof:placetype":"venue"
},
  "geometry": {"coordinates":[-107.049004,51.489155],"type":"Point"}
}