{
  "type": "Feature",
  "properties": {
    "addr:full":"11873 Rue Notre-Dame E Pointe-Aux-Trembles QC H1B 2Y2",
    "addr:housenumber":"11873",
    "addr:postcode":"h1b 2y2",
    "addr:street":"Rue Notre-Dame E Pointe-Aux-Trembles",
    "iso:country":"CA",
    "sg:address":"11873 Rue Notre-Dame E",
    "sg:city":"Pointe-Aux-Trembles",
    "sg:classifiers":[
        {
            "category":"Shopping",
            "subcategory":"Computers & Home Electronics",
            "type":"Retail Goods"
        }
    ],
    "sg:phone":"+1 514 528 4922",
    "sg:postcode":"H1B 2Y2",
    "sg:province":"QC",
    "sg:tags":[
        "equipment",
        "dealer"
    ],
    "wof:name":"Melrond Informatique",
    "wof:placetype":"venue"
},
  "geometry": {"coordinates":[-73.491348,45.63802],"type":"Point"}
}