{
  "type": "Feature",
  "properties": {
    "iso:country":"CA",
    "sg:address":"8540 Keele St",
    "sg:city":"Concord",
    "sg:classifiers":[
        {
            "category":"Building & Trades",
            "subcategory":"Electrical",
            "type":"Services"
        }
    ],
    "sg:phone":"+1 905 660 3770",
    "sg:postcode":"L4K 2N2",
    "sg:province":"ON",
    "sg:tags":[
        "electric",
        "contractor"
    ],
    "wof:name":"Antra Electric Ltd",
    "wof:placetype":"venue"
},
  "geometry": {"coordinates":[-79.504654,43.820801],"type":"Point"}
}