{
  "type": "Feature",
  "properties": {
    "addr:full":"5700 Av Einstein Cote Saint-Luc QC H4W 1V3",
    "addr:housenumber":"5700",
    "addr:postcode":"h4w 1v3",
    "addr:street":"Av Einstein Cote",
    "iso:country":"CA",
    "sg:address":"5700 Av Einstein",
    "sg:city":"Cote Saint-Luc",
    "sg:classifiers":[
        {
            "category":"Organizations",
            "subcategory":"Religious Organization",
            "type":"Services"
        }
    ],
    "sg:phone":"+1 514 489 1301",
    "sg:postcode":"H4W 1V3",
    "sg:province":"QC",
    "sg:tags":[
        "synagogue"
    ],
    "wof:name":"Congregation Sepharade",
    "wof:placetype":"venue"
},
  "geometry": {"coordinates":[-73.66256,45.470181],"type":"Point"}
}