{
  "type": "Feature",
  "properties": {
    "addr:full":"1861 Portage Ave Winnipeg MB R3J 0G8",
    "addr:housenumber":"1861",
    "addr:postcode":"r3j 0g8",
    "addr:street":"Portage Ave",
    "iso:country":"CA",
    "sg:address":"1861 Portage Ave",
    "sg:city":"Winnipeg",
    "sg:classifiers":[
        {
            "category":"Health Services",
            "subcategory":"Chiropractor",
            "type":"Services"
        }
    ],
    "sg:phone":"+1 204 888 1202",
    "sg:postcode":"R3J 0G8",
    "sg:province":"MB",
    "wof:name":"Assiniboine Chiropractic Ctr",
    "wof:placetype":"venue"
},
  "geometry": {"coordinates":[-97.2175064087,49.8788108826],"type":"Point"}
}