{
  "type": "Feature",
  "properties": {
    "iso:country":"CA",
    "sg:address":"1158 Russell St # B",
    "sg:city":"Thunder Bay",
    "sg:classifiers":[
        {
            "category":"Building & Trades",
            "subcategory":"Construction",
            "type":"Services"
        }
    ],
    "sg:phone":"+1 807 623 6424",
    "sg:postcode":"P7B 5N2",
    "sg:province":"ON",
    "sg:tags":[
        "maker",
        "cabinet"
    ],
    "wof:name":"Distinctive Woodwork & Design",
    "wof:placetype":"venue"
},
  "geometry": {"coordinates":[-89.2539367676,48.4026603699],"type":"Point"}
}