{
  "type": "Feature",
  "properties": {
    "addr:full":"1583 Rue Fleury E Montreal QC H2C 1S7",
    "addr:housenumber":"1583",
    "addr:postcode":"h2c 1s7",
    "addr:street":"Rue Fleury E",
    "iso:country":"CA",
    "sg:address":"1583 Rue Fleury E",
    "sg:city":"Montreal",
    "sg:classifiers":[
        {
            "category":"Professional",
            "subcategory":"Art Services",
            "type":"Services"
        }
    ],
    "sg:phone":"+1 514 814 0156",
    "sg:postcode":"H2C 1S7",
    "sg:province":"QC",
    "sg:tags":[
        "graphic",
        "designer"
    ],
    "wof:name":"Dauphigraphie Comms Graphiques",
    "wof:placetype":"venue"
},
  "geometry": {"coordinates":[-73.65608978269999,45.5636825562],"type":"Point"}
}