{
  "type": "Feature",
  "properties": {
    "iso:country":"CA",
    "sg:address":"116 Browning Ave",
    "sg:city":"Toronto",
    "sg:classifiers":[
        {
            "category":"Social Services",
            "type":"Services"
        }
    ],
    "sg:phone":"+1 416 778 7200",
    "sg:postcode":"M4K 1W3",
    "sg:province":"ON",
    "sg:tags":[
        "organization",
        "welfare"
    ],
    "wof:name":"Koster Consulting & Assoc",
    "wof:placetype":"venue"
},
  "geometry": {"coordinates":[-79.351890564,43.6822433472],"type":"Point"}
}