{
  "type": "Feature",
  "properties": {
    "addr:full":"Thetford Mines QC G6G 5V9",
    "addr:postcode":"g6g 5v9",
    "iso:country":"CA",
    "sg:city":"Thetford Mines",
    "sg:classifiers":[
        {
            "category":"Shopping",
            "subcategory":"Gifts & Souvenirs",
            "type":"Retail Goods"
        }
    ],
    "sg:phone":"+1 418 334 0065",
    "sg:postcode":"G6G 5V9",
    "sg:province":"QC",
    "sg:tags":[
        "shop"
    ],
    "wof:name":"Mille & Un Cadeaux",
    "wof:placetype":"venue"
},
  "geometry": {"coordinates":[-71.299263,46.090576],"type":"Point"}
}