{
  "type": "Feature",
  "properties": {
    "addr:full":"Nepean ON K2G 0G2",
    "addr:postcode":"k2g 0g2",
    "iso:country":"CA",
    "sg:city":"Nepean",
    "sg:classifiers":[
        {
            "category":"Wholesale",
            "subcategory":"Hardware",
            "type":"Manufacturing & Wholesale Goods"
        }
    ],
    "sg:phone":"+1 613 224 8410",
    "sg:postcode":"K2G 0G2",
    "sg:province":"ON",
    "sg:tags":[
        "beer",
        "cooling",
        "dispensing"
    ],
    "wof:name":"Diageo Canada",
    "wof:placetype":"venue"
},
  "geometry": {"coordinates":[-75.7213897705,45.3213729858],"type":"Point"}
}