{
  "type": "Feature",
  "properties": {
    "addr:full":"Thessalon ON P0R 1L0",
    "addr:postcode":"p0r 1l0",
    "iso:country":"CA",
    "sg:city":"Thessalon",
    "sg:classifiers":[
        {
            "category":"Social Services",
            "subcategory":"Child Care",
            "type":"Services"
        }
    ],
    "sg:phone":"+1 705 842 0117",
    "sg:postcode":"P0R 1L0",
    "sg:province":"ON",
    "wof:name":"Thessalon Child Care Ctr",
    "wof:placetype":"venue"
},
  "geometry": {"coordinates":[-83.556938,46.262058],"type":"Point"}
}