{
  "type": "Feature",
  "properties": {
    "iso:country":"CA",
    "sg:address":"19 Market St W",
    "sg:city":"Port Dover",
    "sg:classifiers":[
        {
            "category":"Organizations",
            "subcategory":"Professional Association",
            "type":"Services"
        }
    ],
    "sg:phone":"+1 519 583 1314",
    "sg:postcode":"N0A 1N0",
    "sg:province":"ON",
    "wof:name":"Port Dover Board of Trade",
    "wof:placetype":"venue"
},
  "geometry": {"coordinates":[-80.203125,42.785987854],"type":"Point"}
}