{
  "type": "Feature",
  "properties": {
    "iso:country":"CA",
    "sg:address":"45 Rue Des Sables",
    "sg:city":"Victoriaville",
    "sg:classifiers":[
        {
            "category":"Building & Trades",
            "subcategory":"Construction",
            "type":"Services"
        }
    ],
    "sg:phone":"+1 819 758 5585",
    "sg:postcode":"G6P 9R3",
    "sg:province":"QC",
    "sg:tags":[
        "excavating",
        "contractor"
    ],
    "wof:name":"Shervic Enr",
    "wof:placetype":"venue"
},
  "geometry": {"coordinates":[-72.0067443848,46.0424079895],"type":"Point"}
}