{
  "type": "Feature",
  "properties": {
    "addr:full":"3350 Yonge St Toronto ON M4N 2M7",
    "addr:housenumber":"3350",
    "addr:postcode":"m4n 2m7",
    "addr:street":"Yonge St",
    "iso:country":"CA",
    "sg:address":"3350 Yonge St",
    "sg:city":"Toronto",
    "sg:classifiers":[
        {
            "category":"Shopping",
            "subcategory":"Books",
            "type":"Retail Goods"
        }
    ],
    "sg:phone":"+1 416 487 7177",
    "sg:postcode":"M4N 2M7",
    "sg:province":"ON",
    "sg:tags":[
        "dealer"
    ],
    "wof:name":"Mastermind Educational",
    "wof:placetype":"venue"
},
  "geometry": {"coordinates":[-79.404152,43.732059],"type":"Point"}
}