{
  "type": "Feature",
  "properties": {
    "addr:full":"Langley BC V3A 5E8",
    "addr:postcode":"v3a 5e8",
    "iso:country":"CA",
    "sg:city":"Langley",
    "sg:classifiers":[
        {
            "category":"Food & Beverages",
            "subcategory":"Meat & Fish",
            "type":"Retail Goods"
        }
    ],
    "sg:phone":"+1 604 530 1551",
    "sg:postcode":"V3A 5E8",
    "sg:province":"BC",
    "sg:tags":[
        "delicatessen"
    ],
    "wof:name":"Don's Deli Supply Ltd",
    "wof:placetype":"venue"
},
  "geometry": {"coordinates":[-122.649055,49.113216],"type":"Point"}
}