{
  "type": "Feature",
  "properties": {
    "addr:full":"430 Hespeler Rd Cambridge ON N1R 6J7",
    "addr:housenumber":"430",
    "addr:postcode":"n1r 6j7",
    "addr:street":"Hespeler Rd",
    "iso:country":"CA",
    "sg:address":"430 Hespeler Rd",
    "sg:city":"Cambridge",
    "sg:classifiers":[
        {
            "category":"Restaurant",
            "type":"Food & Drink"
        }
    ],
    "sg:phone":"+1 519 623 4700",
    "sg:postcode":"N1R 6J7",
    "sg:province":"ON",
    "wof:name":"Wendy's",
    "wof:placetype":"venue"
},
  "geometry": {"coordinates":[-80.3245773315,43.3963012695],"type":"Point"}
}