{
  "type": "Feature",
  "properties": {
    "addr:full":"178 St-Joseph Gracefield QC J0X 1W0",
    "addr:housenumber":"178",
    "addr:postcode":"j0x 1w0",
    "addr:street":"St-Joseph",
    "iso:country":"CA",
    "sg:address":"178 St-Joseph",
    "sg:city":"Gracefield",
    "sg:classifiers":[
        {
            "category":"Manufacturing",
            "subcategory":"Glass & Minerals",
            "type":"Manufacturing & Wholesale Goods"
        }
    ],
    "sg:phone":"+1 819 463 3506",
    "sg:postcode":"J0X 1W0",
    "sg:province":"QC",
    "sg:tags":[
        "concrete",
        "brick",
        "block",
        "form"
    ],
    "wof:name":"Constructions Marc Martin",
    "wof:placetype":"venue"
},
  "geometry": {"coordinates":[-76.044037,46.101025],"type":"Point"}
}