{
  "type": "Feature",
  "properties": {
    "iso:country":"CA",
    "sg:city":"Vancouver",
    "sg:classifiers":[
        {
            "category":"Shopping",
            "type":"Retail Goods"
        }
    ],
    "sg:phone":"+1 604 681 5442",
    "sg:postcode":"V6B 4M3",
    "sg:province":"BC",
    "sg:tags":[
        "product",
        "ethnic"
    ],
    "wof:name":"House of Mc Laren",
    "wof:placetype":"venue"
},
  "geometry": {"coordinates":[-123.107200623,49.2841796875],"type":"Point"}
}