{
  "type": "Feature",
  "properties": {
    "addr:full":"73 Craven Pl SE Medicine Hat AB T1A 7T1",
    "addr:housenumber":"73",
    "addr:postcode":"t1a 7t1",
    "addr:street":"Craven Pl Se",
    "iso:country":"CA",
    "sg:address":"73 Craven Pl SE",
    "sg:city":"Medicine Hat",
    "sg:classifiers":[
        {
            "category":"Professional",
            "subcategory":"Management & Consulting",
            "type":"Services"
        }
    ],
    "sg:phone":"+1 403 526 1616",
    "sg:postcode":"T1A 7T1",
    "sg:province":"AB",
    "sg:tags":[
        "consultant",
        "business"
    ],
    "wof:name":"Positive Culture CO",
    "wof:placetype":"venue"
},
  "geometry": {"coordinates":[-110.663230896,50.0237846375],"type":"Point"}
}