{
  "type": "Feature",
  "properties": {
    "addr:full":"2802 Dundas St W Toronto ON M6P 1Y5",
    "addr:housenumber":"2802",
    "addr:postcode":"m6p 1y5",
    "addr:street":"Dundas St W",
    "iso:country":"CA",
    "sg:address":"2802 Dundas St W",
    "sg:city":"Toronto",
    "sg:classifiers":[
        {
            "category":"Wholesale",
            "subcategory":"Meat",
            "type":"Manufacturing & Wholesale Goods"
        }
    ],
    "sg:phone":"+1 416 767 5003",
    "sg:postcode":"M6P 1Y5",
    "sg:province":"ON",
    "sg:tags":[
        "butchering"
    ],
    "wof:name":"Junction Meats",
    "wof:placetype":"venue"
},
  "geometry": {"coordinates":[-79.46268463129999,43.6655235291],"type":"Point"}
}