{
  "type": "Feature",
  "properties": {
    "iso:country":"CA",
    "sg:city":"Burlington",
    "sg:classifiers":[
        {
            "category":"Wholesale",
            "subcategory":"Electrical",
            "type":"Manufacturing & Wholesale Goods"
        }
    ],
    "sg:phone":"+1 905 315 9509",
    "sg:postcode":"L7N 3P5",
    "sg:province":"ON",
    "sg:tags":[
        "equipment",
        "electronic",
        "supply"
    ],
    "wof:name":"Stratuscom Manufacturing Syst",
    "wof:placetype":"venue"
},
  "geometry": {"coordinates":[-79.78347,43.338245],"type":"Point"}
}