{
  "type": "Feature",
  "properties": {
    "addr:full":"64 Des Sports Sainte-Hedwidge-DE-Roberval QC G0W 2R0",
    "addr:housenumber":"64",
    "addr:postcode":"g0w 2r0",
    "addr:street":"Des Sports",
    "iso:country":"CA",
    "sg:address":"64 Des Sports",
    "sg:city":"Sainte-Hedwidge-DE-Roberval",
    "sg:classifiers":[
        {
            "category":"Recreation",
            "type":"Entertainment"
        }
    ],
    "sg:phone":"+1 418 275 3968",
    "sg:postcode":"G0W 2R0",
    "sg:province":"QC",
    "sg:tags":[
        "attraction",
        "tourist"
    ],
    "wof:name":"Defi Du Lac St-Jean",
    "wof:placetype":"venue"
},
  "geometry": {"coordinates":[-72.224457,48.515263],"type":"Point"}
}