{
  "type": "Feature",
  "properties": {
    "addr:full":"Nepean ON K2G 6E8",
    "addr:postcode":"k2g 6e8",
    "iso:country":"CA",
    "sg:city":"Nepean",
    "sg:classifiers":[
        {
            "category":"Banks & Credit Unions",
            "subcategory":"Investment Brokerage",
            "type":"Services"
        }
    ],
    "sg:phone":"+1 613 224 5055",
    "sg:postcode":"K2G 6E8",
    "sg:province":"ON",
    "wof:name":"Edward Jones",
    "wof:placetype":"venue"
},
  "geometry": {"coordinates":[-75.7705612183,45.3387641907],"type":"Point"}
}