{
  "type": "Feature",
  "properties": {
    "addr:full":"61 Rue Principale Saint-Aime-Des-Lacs QC G0T 1S0",
    "addr:housenumber":"61",
    "addr:postcode":"g0t 1s0",
    "addr:street":"Rue Principale",
    "iso:country":"CA",
    "sg:address":"61 Rue Principale",
    "sg:city":"Saint-Aime-Des-Lacs",
    "sg:classifiers":[
        {
            "category":"Building & Trades",
            "subcategory":"Construction",
            "type":"Services"
        }
    ],
    "sg:phone":"+1 418 439 3715",
    "sg:postcode":"G0T 1S0",
    "sg:province":"QC",
    "sg:tags":[
        "maker",
        "cabinet"
    ],
    "wof:name":"Menuiserie Du Lac Inc",
    "wof:placetype":"venue"
},
  "geometry": {"coordinates":[-70.29232,47.6791],"type":"Point"}
}