{
  "type": "Feature",
  "properties": {
    "iso:country":"CA",
    "sg:city":"Cap-DE-LA-Madeleine",
    "sg:classifiers":[
        {
            "category":"Manufacturing",
            "subcategory":"Metals",
            "type":"Manufacturing & Wholesale Goods"
        }
    ],
    "sg:phone":"+1 819 374 2313",
    "sg:postcode":"G8V 2R9",
    "sg:province":"QC",
    "sg:tags":[
        "steel"
    ],
    "wof:name":"Metalite Inc",
    "wof:placetype":"venue"
},
  "geometry": {"coordinates":[-72.5002441406,46.3747215271],"type":"Point"}
}