{
  "type": "Feature",
  "properties": {
    "addr:full":"1633 Kingsway Vancouver BC V5N 2S2",
    "addr:housenumber":"1633",
    "addr:postcode":"v5n 2s2",
    "addr:street":"Kingsway",
    "iso:country":"CA",
    "sg:address":"1633 Kingsway",
    "sg:city":"Vancouver",
    "sg:classifiers":[
        {
            "category":"Insurance",
            "subcategory":"Insurance Agent",
            "type":"Services"
        }
    ],
    "sg:phone":"+1 604 879 6238",
    "sg:postcode":"V5N 2S2",
    "sg:province":"BC",
    "wof:name":"Dason Insurance",
    "wof:placetype":"venue"
},
  "geometry": {"coordinates":[-123.070595,49.247833],"type":"Point"}
}