{
  "type": "Feature",
  "properties": {
    "addr:full":"243 Rue Sharron Otterburn Park QC J3H 1Y7",
    "addr:housenumber":"243",
    "addr:postcode":"j3h 1y7",
    "addr:street":"Rue Sharron;Park",
    "iso:country":"CA",
    "sg:address":"243 Rue Sharron",
    "sg:city":"Otterburn Park",
    "sg:classifiers":[
        {
            "category":"Building & Trades",
            "subcategory":"Construction",
            "type":"Services"
        }
    ],
    "sg:phone":"+1 450 446 6227",
    "sg:postcode":"J3H 1Y7",
    "sg:province":"QC",
    "sg:tags":[
        "plastering",
        "stone",
        "contractor"
    ],
    "wof:name":"Finitions Mp",
    "wof:placetype":"venue"
},
  "geometry": {"coordinates":[-73.195221,45.54644],"type":"Point"}
}