{
  "type": "Feature",
  "properties": {
    "addr:full":"265 King George Rd Brantford ON N3R 6Y1",
    "addr:housenumber":"265",
    "addr:postcode":"n3r 6y1",
    "addr:street":"King George Rd",
    "iso:country":"CA",
    "sg:address":"265 King George Rd",
    "sg:city":"Brantford",
    "sg:classifiers":[
        {
            "category":"Food & Beverages",
            "subcategory":"Bakery",
            "type":"Retail Goods"
        }
    ],
    "sg:phone":"+1 519 759 8920",
    "sg:postcode":"N3R 6Y1",
    "sg:province":"ON",
    "sg:tags":[
        "doughnut"
    ],
    "wof:name":"Tim Hortons",
    "wof:placetype":"venue"
},
  "geometry": {"coordinates":[-80.279991,43.178257],"type":"Point"}
}