{
  "type": "Feature",
  "properties": {
    "addr:full":"5600 Rue Hochelaga Montreal QC H1N 3L7",
    "addr:housenumber":"5600",
    "addr:postcode":"h1n 3l7",
    "addr:street":"Rue Hochelaga",
    "iso:country":"CA",
    "sg:address":"5600 Rue Hochelaga",
    "sg:city":"Montreal",
    "sg:classifiers":[
        {
            "category":"Professional",
            "subcategory":"Art Services",
            "type":"Services"
        }
    ],
    "sg:phone":"+1 514 255 0077",
    "sg:postcode":"H1N 3L7",
    "sg:province":"QC",
    "sg:tags":[
        "graphic",
        "designer"
    ],
    "wof:name":"Groupe Duck Communications Inc",
    "wof:placetype":"venue"
},
  "geometry": {"coordinates":[-73.538712,45.568275],"type":"Point"}
}