{
  "type": "Feature",
  "properties": {
    "addr:full":"Medicine Hat AB T1A 0H2",
    "addr:postcode":"t1a 0h2",
    "iso:country":"CA",
    "sg:city":"Medicine Hat",
    "sg:classifiers":[
        {
            "category":"Travel",
            "subcategory":"Travel Agent",
            "type":"Entertainment"
        }
    ],
    "sg:phone":"+1 403 526 6931",
    "sg:postcode":"T1A 0H2",
    "sg:province":"AB",
    "sg:tags":[
        "agency",
        "bureau"
    ],
    "wof:name":"Carlson Wagonlit/Kabet Travel",
    "wof:placetype":"venue"
},
  "geometry": {"coordinates":[-110.673530579,50.0405197144],"type":"Point"}
}