{
  "type": "Feature",
  "properties": {
    "addr:full":"Paspebiac QC G0C 2K0",
    "addr:postcode":"g0c 2k0",
    "iso:country":"CA",
    "sg:city":"Paspebiac",
    "sg:classifiers":[
        {
            "category":"Retail",
            "subcategory":"Auto Repair",
            "type":"Services"
        }
    ],
    "sg:phone":"+1 418 752 5151",
    "sg:postcode":"G0C 2K0",
    "sg:province":"QC",
    "sg:tags":[
        "muffler",
        "exhaust",
        "system"
    ],
    "wof:name":"Garage Joseph Phedor",
    "wof:placetype":"venue"
},
  "geometry": {"coordinates":[-65.239357,48.030212],"type":"Point"}
}