{
  "type": "Feature",
  "properties": {
    "addr:full":"Saskatoon SK S7H 0V1",
    "addr:postcode":"s7h 0v1",
    "iso:country":"CA",
    "sg:city":"Saskatoon",
    "sg:classifiers":[
        {
            "category":"Shopping",
            "subcategory":"Bicycles & Sporting Goods",
            "type":"Retail Goods"
        }
    ],
    "sg:phone":"+1 306 955 2381",
    "sg:postcode":"S7H 0V1",
    "sg:province":"SK",
    "sg:tags":[
        "clothing"
    ],
    "wof:name":"Momentum Equipment & Clothing",
    "wof:placetype":"venue"
},
  "geometry": {"coordinates":[-106.624146,52.114609],"type":"Point"}
}