{
  "type": "Feature",
  "properties": {
    "addr:full":"189 Patricia Rd Windsor ON N9B 3B8",
    "addr:housenumber":"189",
    "addr:postcode":"n9b 3b8",
    "addr:street":"Patricia Rd",
    "iso:country":"CA",
    "sg:address":"189 Patricia Rd",
    "sg:city":"Windsor",
    "sg:classifiers":[
        {
            "category":"Organizations",
            "subcategory":"Religious Organization",
            "type":"Services"
        }
    ],
    "sg:phone":"+1 519 253 1077",
    "sg:postcode":"N9B 3B8",
    "sg:province":"ON",
    "sg:tags":[
        "church"
    ],
    "wof:name":"Windsor Full Gospel Msn Church",
    "wof:placetype":"venue"
},
  "geometry": {"coordinates":[-83.06931299999999,42.309425],"type":"Point"}
}