{
  "type": "Feature",
  "properties": {
    "addr:full":"Cowansville QC J2K 3Y9",
    "addr:postcode":"j2k 3y9",
    "iso:country":"CA",
    "sg:city":"Cowansville",
    "sg:classifiers":[
        {
            "category":"Building & Trades",
            "subcategory":"Plumbing",
            "type":"Services"
        }
    ],
    "sg:phone":"+1 450 263 2226",
    "sg:postcode":"J2K 3Y9",
    "sg:province":"QC",
    "sg:tags":[
        "contractor"
    ],
    "wof:name":"Plomberie Goyer Inc",
    "wof:placetype":"venue"
},
  "geometry": {"coordinates":[-72.75677490229999,45.1917686462],"type":"Point"}
}