{
  "type": "Feature",
  "properties": {
    "addr:full":"197 Acacia Dr SE Airdrie AB T4B 1G6",
    "addr:housenumber":"197",
    "addr:postcode":"t4b 1g6",
    "addr:street":"Acacia Dr Se",
    "iso:country":"CA",
    "sg:address":"197 Acacia Dr SE",
    "sg:city":"Airdrie",
    "sg:classifiers":[
        {
            "category":"Building & Trades",
            "subcategory":"Plumbing",
            "type":"Services"
        }
    ],
    "sg:phone":"+1 403 948 7798",
    "sg:postcode":"T4B 1G6",
    "sg:province":"AB",
    "sg:tags":[
        "refrigeration",
        "contractor"
    ],
    "wof:name":"Heritage Refrigeration & Ac",
    "wof:placetype":"venue"
},
  "geometry": {"coordinates":[-114.011292,51.286606],"type":"Point"}
}