{
  "type": "Feature",
  "properties": {
    "iso:country":"CA",
    "sg:address":"4400 Ch DE LA Cote-DE-Liesse",
    "sg:city":"Mont-Royal",
    "sg:classifiers":[
        {
            "category":"Real Estate",
            "subcategory":"Real Estate Agent",
            "type":"Services"
        }
    ],
    "sg:phone":"+1 514 744 0799",
    "sg:postcode":"H4N 2P7",
    "sg:province":"QC",
    "wof:name":"Ice Intl Consultant Experts",
    "wof:placetype":"venue"
},
  "geometry": {"coordinates":[-73.664108,45.505196],"type":"Point"}
}