{
  "type": "Feature",
  "properties": {
    "iso:country":"CA",
    "sg:city":"Toronto",
    "sg:classifiers":[
        {
            "category":"Building & Trades",
            "subcategory":"Plumbing",
            "type":"Services"
        }
    ],
    "sg:phone":"+1 416 364 5569",
    "sg:postcode":"M5H 1T1",
    "sg:province":"ON",
    "sg:tags":[
        "product",
        "management",
        "consultant",
        "energy",
        "system",
        "conservation"
    ],
    "wof:name":"Cgx Energy Inc",
    "wof:placetype":"venue"
},
  "geometry": {"coordinates":[-79.3833999634,43.6494598389],"type":"Point"}
}