{
  "type": "Feature",
  "properties": {
    "addr:full":"1179 Kapelus Dr West St Paul MB R4A 5A8",
    "addr:housenumber":"1179",
    "addr:postcode":"r4a 5a8",
    "addr:street":"Kapelus Dr",
    "iso:country":"CA",
    "sg:address":"1179 Kapelus Dr",
    "sg:city":"West St Paul",
    "sg:classifiers":[
        {
            "category":"Manufacturing",
            "subcategory":"Retail Goods",
            "type":"Manufacturing & Wholesale Goods"
        }
    ],
    "sg:phone":"+1 204 632 6223",
    "sg:postcode":"R4A 5A8",
    "sg:province":"MB",
    "sg:tags":[
        "grain",
        "elevator",
        "manufacturer"
    ],
    "wof:name":"Minic Industries Ltd",
    "wof:placetype":"venue"
},
  "geometry": {"coordinates":[-97.1022109985,49.9896316528],"type":"Point"}
}