{
  "type": "Feature",
  "properties": {
    "addr:full":"55 Rue Du Bruant Hull QC J9A 2X9",
    "addr:housenumber":"55",
    "addr:postcode":"j9a 2x9",
    "addr:street":"Rue Du Bruant",
    "iso:country":"CA",
    "sg:address":"55 Rue Du Bruant",
    "sg:city":"Hull",
    "sg:classifiers":[
        {
            "category":"Professional",
            "subcategory":"Business Services",
            "type":"Services"
        }
    ],
    "sg:phone":"+1 819 770 7676",
    "sg:postcode":"J9A 2X9",
    "sg:province":"QC",
    "sg:tags":[
        "translator",
        "interpreter"
    ],
    "wof:name":"Hispanet Inc",
    "wof:placetype":"venue"
},
  "geometry": {"coordinates":[-75.768028,45.427902],"type":"Point"}
}