{
  "type": "Feature",
  "properties": {
    "addr:full":"279 Yonge St Barrie ON L4N 7T9",
    "addr:housenumber":"279",
    "addr:postcode":"l4n 7t9",
    "addr:street":"Yonge St",
    "iso:country":"CA",
    "sg:address":"279 Yonge St",
    "sg:city":"Barrie",
    "sg:classifiers":[
        {
            "category":"Restaurant",
            "type":"Food & Drink"
        }
    ],
    "sg:phone":"+1 705 725 9535",
    "sg:postcode":"L4N 7T9",
    "sg:province":"ON",
    "wof:name":"Wimpy's Diner",
    "wof:placetype":"venue"
},
  "geometry": {"coordinates":[-79.670937,44.370602],"type":"Point"}
}