{
  "type": "Feature",
  "properties": {
    "addr:full":"903 Boul Decarie # 201 Saint-Laurent QC H4L 3M3",
    "addr:housenumber":"903",
    "addr:postcode":"h4l 3m3",
    "addr:street":"Boul Decarie # 201",
    "iso:country":"CA",
    "sg:address":"903 Boul Decarie # 201",
    "sg:city":"Saint-Laurent",
    "sg:classifiers":[
        {
            "category":"Real Estate",
            "subcategory":"Architect",
            "type":"Services"
        }
    ],
    "sg:phone":"+1 514 748 2770",
    "sg:postcode":"H4L 3M3",
    "sg:province":"QC",
    "wof:name":"Janson Wong",
    "wof:placetype":"venue"
},
  "geometry": {"coordinates":[-73.68045806879999,45.5130310059],"type":"Point"}
}