{
  "type": "Feature",
  "properties": {
    "addr:full":"603 King Ave Bathurst NB E2A 1P9",
    "addr:housenumber":"603",
    "addr:postcode":"e2a 1p9",
    "addr:street":"King Ave",
    "iso:country":"CA",
    "sg:address":"603 King Ave",
    "sg:city":"Bathurst",
    "sg:classifiers":[
        {
            "category":"Organizations",
            "subcategory":"Religious Organization",
            "type":"Services"
        }
    ],
    "sg:phone":"+1 506 546 8782",
    "sg:postcode":"E2A 1P9",
    "sg:province":"NB",
    "sg:tags":[
        "church"
    ],
    "wof:name":"Bathurst Christian Fellowship",
    "wof:placetype":"venue"
},
  "geometry": {"coordinates":[-65.651443,47.615482],"type":"Point"}
}