{
  "type": "Feature",
  "properties": {
    "addr:full":"1803 35 St SE Calgary AB T2B 0W6",
    "addr:housenumber":"1803",
    "addr:postcode":"t2b 0w6",
    "addr:street":"35 St Se",
    "iso:country":"CA",
    "sg:address":"1803 35 St SE",
    "sg:city":"Calgary",
    "sg:classifiers":[
        {
            "category":"Health Services",
            "subcategory":"Health Practitioner",
            "type":"Services"
        }
    ],
    "sg:phone":"+1 403 272 2351",
    "sg:postcode":"T2B 0W6",
    "sg:province":"AB",
    "sg:tags":[
        "therapist",
        "physical"
    ],
    "wof:name":"Forest Lawn Physiotherapy",
    "wof:placetype":"venue"
},
  "geometry": {"coordinates":[-113.983306885,51.0374412537],"type":"Point"}
}