{
  "type": "Feature",
  "properties": {
    "addr:full":"1295 Rue Hodge Saint-Laurent QC H4N 2B1",
    "addr:housenumber":"1295",
    "addr:postcode":"h4n 2b1",
    "addr:street":"Rue Hodge",
    "iso:country":"CA",
    "sg:address":"1295 Rue Hodge",
    "sg:city":"Saint-Laurent",
    "sg:classifiers":[
        {
            "category":"Building & Trades",
            "subcategory":"Construction",
            "type":"Services"
        }
    ],
    "sg:phone":"+1 514 744 0000",
    "sg:postcode":"H4N 2B1",
    "sg:province":"QC",
    "sg:tags":[
        "masonry",
        "contractor"
    ],
    "wof:name":"C Ricci & Son Construction Inc",
    "wof:placetype":"venue"
},
  "geometry": {"coordinates":[-73.66731299999999,45.509666],"type":"Point"}
}