{
  "type": "Feature",
  "properties": {
    "addr:full":"1529 71st Ave W Vancouver BC V6P 3B9",
    "addr:housenumber":"1529",
    "addr:postcode":"v6p 3b9",
    "addr:street":"71St Ave W",
    "iso:country":"CA",
    "sg:address":"1529 71st Ave W",
    "sg:city":"Vancouver",
    "sg:classifiers":[
        {
            "category":"Real Estate",
            "subcategory":"Real Estate Agent",
            "type":"Services"
        }
    ],
    "sg:phone":"+1 604 264 0850",
    "sg:postcode":"V6P 3B9",
    "sg:province":"BC",
    "sg:tags":[
        "cooperative"
    ],
    "wof:name":"David Wetherow Housing CO-OP",
    "wof:placetype":"venue"
},
  "geometry": {"coordinates":[-123.141479,49.207275],"type":"Point"}
}