{
  "type": "Feature",
  "properties": {
    "iso:country":"CA",
    "sg:address":"100 Rue Veteran",
    "sg:city":"Grand Falls",
    "sg:classifiers":[
        {
            "category":"Sports & Exercise",
            "subcategory":"Bowling",
            "type":"Entertainment"
        }
    ],
    "sg:phone":"+1 506 473 5531",
    "sg:postcode":"E3Y 1A9",
    "sg:province":"NB",
    "sg:tags":[
        "center"
    ],
    "wof:name":"Complexe Sportif",
    "wof:placetype":"venue"
},
  "geometry": {"coordinates":[-67.7255706787,47.0564804077],"type":"Point"}
}