{
  "type": "Feature",
  "properties": {
    "addr:full":"Saint-Urbain-Premier QC J0S 1Y0",
    "addr:postcode":"j0s 1y0",
    "iso:country":"CA",
    "sg:city":"Saint-Urbain-Premier",
    "sg:classifiers":[
        {
            "category":"Retail",
            "subcategory":"Repair Shop",
            "type":"Services"
        }
    ],
    "sg:phone":"+1 450 427 1440",
    "sg:postcode":"J0S 1Y0",
    "sg:province":"QC",
    "sg:tags":[
        "welding"
    ],
    "wof:name":"Soudure Industrielle Yves Cote",
    "wof:placetype":"venue"
},
  "geometry": {"coordinates":[-73.737297,45.218777],"type":"Point"}
}