{
  "type": "Feature",
  "properties": {
    "addr:full":"Mulhurst Bay AB T0C 2C0",
    "addr:postcode":"t0c 2c0",
    "iso:country":"CA",
    "sg:city":"Mulhurst Bay",
    "sg:classifiers":[
        {
            "category":"Organizations",
            "subcategory":"Religious Organization",
            "type":"Services"
        }
    ],
    "sg:phone":"+1 780 389 4242",
    "sg:postcode":"T0C 2C0",
    "sg:province":"AB",
    "sg:tags":[
        "church"
    ],
    "wof:name":"Jehovah's Witnesses Bonnie Gln",
    "wof:placetype":"venue"
},
  "geometry": {"coordinates":[-114.00106,53.05426],"type":"Point"}
}