{
  "type": "Feature",
  "properties": {
    "addr:full":"2720 Hastings St E Vancouver BC V5K 1Z9",
    "addr:housenumber":"2720",
    "addr:postcode":"v5k 1z9",
    "addr:street":"Hastings St E",
    "iso:country":"CA",
    "sg:address":"2720 Hastings St E",
    "sg:city":"Vancouver",
    "sg:classifiers":[
        {
            "category":"Personal",
            "subcategory":"Beauty Salon",
            "type":"Services"
        }
    ],
    "sg:phone":"+1 604 216 6715",
    "sg:postcode":"V5K 1Z9",
    "sg:province":"BC",
    "sg:tags":[
        "manicuring"
    ],
    "wof:name":"Fantasy Nails",
    "wof:placetype":"venue"
},
  "geometry": {"coordinates":[-123.04856100000001,49.280926],"type":"Point"}
}