{
  "type": "Feature",
  "properties": {
    "iso:country":"CA",
    "sg:address":"2430 South Service Rd W",
    "sg:city":"Oakville",
    "sg:classifiers":[
        {
            "category":"Autos & Motor Vehicles",
            "subcategory":"Automobile Sales",
            "type":"Retail Goods"
        }
    ],
    "sg:phone":"+1 905 845 1443",
    "sg:postcode":"L6L 5M9",
    "sg:province":"ON",
    "sg:tags":[
        "car",
        "dealer"
    ],
    "wof:name":"Budds' Imported Cars",
    "wof:placetype":"venue"
},
  "geometry": {"coordinates":[-79.73783874510001,43.4118041992],"type":"Point"}
}