{
  "type": "Feature",
  "properties": {
    "addr:full":"483 Eastchester Ave E St Catharines ON L2M 6S2",
    "addr:housenumber":"483",
    "addr:postcode":"l2m 6s2",
    "addr:street":"Eastchester Ave E",
    "iso:country":"CA",
    "sg:address":"483 Eastchester Ave E",
    "sg:city":"St Catharines",
    "sg:classifiers":[
        {
            "category":"Shopping",
            "type":"Retail Goods"
        }
    ],
    "sg:phone":"+1 905 984 6884",
    "sg:postcode":"L2M 6S2",
    "sg:province":"ON",
    "sg:tags":[
        "awning",
        "canopy"
    ],
    "wof:name":"Alexander Awnings",
    "wof:placetype":"venue"
},
  "geometry": {"coordinates":[-79.201561,43.17025],"type":"Point"}
}