{
  "type": "Feature",
  "properties": {
    "iso:country":"CA",
    "sg:address":"34 Blair Rd",
    "sg:city":"Cambridge",
    "sg:classifiers":[
        {
            "category":"Health Services",
            "subcategory":"Doctor",
            "type":"Services"
        }
    ],
    "sg:phone":"+1 519 623 0535",
    "sg:postcode":"N1S 2H9",
    "sg:province":"ON",
    "sg:tags":[
        "x",
        "surgeon",
        "physician"
    ],
    "wof:name":"Radiology Associates",
    "wof:placetype":"venue"
},
  "geometry": {"coordinates":[-80.3188858032,43.3609733582],"type":"Point"}
}