{
  "type": "Feature",
  "properties": {
    "addr:full":"550 Ontario St S #19 Milton ON L9T 5E4",
    "addr:housenumber":"550",
    "addr:postcode":"l9t 5e4",
    "addr:street":"Ontario St S # 19",
    "iso:country":"CA",
    "sg:address":"550 Ontario St S #19",
    "sg:city":"Milton",
    "sg:classifiers":[
        {
            "category":"Restaurant",
            "type":"Food & Drink"
        }
    ],
    "sg:phone":"+1 905 876 0499",
    "sg:postcode":"L9T 5E4",
    "sg:province":"ON",
    "wof:name":"Trattoria Domenico II",
    "wof:placetype":"venue"
},
  "geometry": {"coordinates":[-79.8628921509,43.5072937012],"type":"Point"}
}