{
  "type": "Feature",
  "properties": {
    "addr:full":"212 Oak Ave S Grunthal MB R0A 0R0",
    "addr:housenumber":"212",
    "addr:postcode":"r0a 0r0",
    "addr:street":"Oak Ave S Grunthal",
    "iso:country":"CA",
    "sg:address":"212 Oak Ave S",
    "sg:city":"Grunthal",
    "sg:classifiers":[
        {
            "category":"Education",
            "subcategory":"School",
            "type":"Public Place"
        }
    ],
    "sg:phone":"+1 204 434 6415",
    "sg:postcode":"R0A 0R0",
    "sg:province":"MB",
    "wof:name":"Green Valley School",
    "wof:placetype":"venue"
},
  "geometry": {"coordinates":[-96.85130310060001,49.4066886902],"type":"Point"}
}