{
  "type": "Feature",
  "properties": {
    "addr:full":"139 Rue Principale Cowansville QC J2K 1J3",
    "addr:housenumber":"139",
    "addr:postcode":"j2k 1j3",
    "addr:street":"Rue Principale",
    "iso:country":"CA",
    "sg:address":"139 Rue Principale",
    "sg:city":"Cowansville",
    "sg:classifiers":[
        {
            "category":"Cinema",
            "subcategory":"Movie Theater",
            "type":"Entertainment"
        }
    ],
    "sg:phone":"+1 450 263 5900",
    "sg:postcode":"J2K 1J3",
    "sg:province":"QC",
    "wof:name":"Cinema Princesse",
    "wof:placetype":"venue"
},
  "geometry": {"coordinates":[-72.74638400000001,45.207863],"type":"Point"}
}