{
  "type": "Feature",
  "properties": {
    "iso:country":"CA",
    "sg:city":"Picton",
    "sg:classifiers":[
        {
            "category":"Wholesale",
            "subcategory":"Meat",
            "type":"Manufacturing & Wholesale Goods"
        }
    ],
    "sg:phone":"+1 613 476 6955",
    "sg:postcode":"K0K 2T0",
    "sg:province":"ON",
    "sg:tags":[
        "butchering"
    ],
    "wof:name":"Cole Brothers Meat Processing",
    "wof:placetype":"venue"
},
  "geometry": {"coordinates":[-77.1089553833,43.9980316162],"type":"Point"}
}