{
  "type": "Feature",
  "properties": {
    "addr:full":"794 Rue Principale Granby QC J2G 2Y7",
    "addr:housenumber":"794",
    "addr:postcode":"j2g 2y7",
    "addr:street":"Rue Principale",
    "iso:country":"CA",
    "sg:address":"794 Rue Principale",
    "sg:city":"Granby",
    "sg:classifiers":[
        {
            "category":"Food & Beverages",
            "subcategory":"Meat & Fish",
            "type":"Retail Goods"
        }
    ],
    "sg:phone":"+1 450 405 4056",
    "sg:postcode":"J2G 2Y7",
    "sg:province":"QC",
    "sg:tags":[
        "seafood"
    ],
    "wof:name":"Poissonnerie L'Elgefin",
    "wof:placetype":"venue"
},
  "geometry": {"coordinates":[-72.749146,45.41151],"type":"Point"}
}