{
  "type": "Feature",
  "properties": {
    "addr:full":"130 Paris St Sudbury ON P3E 3E1",
    "addr:housenumber":"130",
    "addr:postcode":"p3e 3e1",
    "addr:street":"Paris St",
    "iso:country":"CA",
    "sg:address":"130 Paris St",
    "sg:city":"Sudbury",
    "sg:classifiers":[
        {
            "category":"Insurance",
            "subcategory":"Insurance Agent",
            "type":"Services"
        }
    ],
    "sg:phone":"+1 705 673 5000",
    "sg:postcode":"P3E 3E1",
    "sg:province":"ON",
    "wof:name":"Navarro, Julio",
    "wof:placetype":"venue"
},
  "geometry": {"coordinates":[-80.988846,46.490276],"type":"Point"}
}