{
  "type": "Feature",
  "properties": {
    "addr:full":"314 3 St S Lethbridge AB T1J 1Y9",
    "addr:housenumber":"314 3",
    "addr:postcode":"t1j 1y9",
    "addr:street":"St S",
    "iso:country":"CA",
    "sg:address":"314 3 St S",
    "sg:city":"Lethbridge",
    "sg:classifiers":[
        {
            "category":"Professional",
            "subcategory":"Lawyer & Legal Services",
            "type":"Services"
        }
    ],
    "sg:phone":"+1 403 328 5577",
    "sg:postcode":"T1J 1Y9",
    "sg:province":"AB",
    "sg:tags":[
        "attorney"
    ],
    "wof:name":"Evans, John D",
    "wof:placetype":"venue"
},
  "geometry": {"coordinates":[-112.843605041,49.6953086853],"type":"Point"}
}