{
  "type": "Feature",
  "properties": {
    "addr:full":"898 Broadway W Vancouver BC V5Z 1J8",
    "addr:housenumber":"898",
    "addr:postcode":"v5z 1j8",
    "addr:street":"Broadway W",
    "iso:country":"CA",
    "sg:address":"898 Broadway W",
    "sg:city":"Vancouver",
    "sg:classifiers":[
        {
            "category":"Travel",
            "subcategory":"Hotels & Motels",
            "type":"Entertainment"
        }
    ],
    "sg:phone":"+1 604 872 1262",
    "sg:postcode":"V5Z 1J8",
    "sg:province":"BC",
    "sg:tags":[
        "club",
        "night"
    ],
    "wof:name":"Fairview Pub",
    "wof:placetype":"venue"
},
  "geometry": {"coordinates":[-123.123955,49.263245],"type":"Point"}
}