{
  "type": "Feature",
  "properties": {
    "addr:full":"359 Kent St Ottawa ON K2P 0R6",
    "addr:housenumber":"359",
    "addr:postcode":"k2p 0r6",
    "addr:street":"Kent St",
    "iso:country":"CA",
    "sg:address":"359 Kent St",
    "sg:city":"Ottawa",
    "sg:classifiers":[
        {
            "category":"Shopping",
            "subcategory":"Computers & Home Electronics",
            "type":"Retail Goods"
        }
    ],
    "sg:phone":"+1 613 231 6623",
    "sg:postcode":"K2P 0R6",
    "sg:province":"ON",
    "sg:tags":[
        "software"
    ],
    "wof:name":"Once Corp",
    "wof:placetype":"venue"
},
  "geometry": {"coordinates":[-75.697441,45.413296],"type":"Point"}
}