{
  "type": "Feature",
  "properties": {
    "addr:full":"50 Oliphant Way Wiarton ON N0H 2T0",
    "addr:housenumber":"50",
    "addr:postcode":"n0h 2t0",
    "addr:street":"Oliphant Way",
    "iso:country":"CA",
    "sg:address":"50 Oliphant Way",
    "sg:city":"Wiarton",
    "sg:classifiers":[
        {
            "category":"Travel",
            "subcategory":"Hotels & Motels",
            "type":"Entertainment"
        }
    ],
    "sg:phone":"+1 519 534 0405",
    "sg:postcode":"N0H 2T0",
    "sg:province":"ON",
    "sg:tags":[
        "cottage",
        "campground",
        "cabin"
    ],
    "wof:name":"Fiddlehead Resort",
    "wof:placetype":"venue"
},
  "geometry": {"coordinates":[-81.1397857666,44.7401351929],"type":"Point"}
}