{
  "type": "Feature",
  "properties": {
    "iso:country":"CA",
    "sg:address":"1142 304th St",
    "sg:city":"Marysville",
    "sg:classifiers":[
        {
            "category":"Autos & Motor Vehicles",
            "subcategory":"Automobile Sales",
            "type":"Retail Goods"
        }
    ],
    "sg:phone":"+1 250 427 4895",
    "sg:postcode":"V1A 3H6",
    "sg:province":"BC",
    "sg:tags":[
        "car",
        "dealer"
    ],
    "wof:name":"Chalet Chevrolet Oldsmobile",
    "wof:placetype":"venue"
},
  "geometry": {"coordinates":[-115.88213348399999,49.606174469],"type":"Point"}
}