{
  "type": "Feature",
  "properties": {
    "addr:full":"13162 159 St NW Edmonton AB T5V 1H7",
    "addr:housenumber":"13162",
    "addr:postcode":"t5v 1h7",
    "addr:street":"159 St Nw",
    "iso:country":"CA",
    "sg:address":"13162 159 St NW",
    "sg:city":"Edmonton",
    "sg:classifiers":[
        {
            "category":"Building & Trades",
            "subcategory":"Electrical",
            "type":"Services"
        }
    ],
    "sg:phone":"+1 780 447 1234",
    "sg:postcode":"T5V 1H7",
    "sg:province":"AB",
    "sg:tags":[
        "electric",
        "contractor"
    ],
    "wof:name":"Blouin Electrical Systems CO",
    "wof:placetype":"venue"
},
  "geometry": {"coordinates":[-113.596947,53.591415],"type":"Point"}
}