{
  "type": "Feature",
  "properties": {
    "iso:country":"CA",
    "sg:address":"5051 Elliott Ave",
    "sg:city":"Peachland",
    "sg:classifiers":[
        {
            "category":"Retail",
            "subcategory":"Repair Shop",
            "type":"Services"
        }
    ],
    "sg:phone":"+1 250 767 3492",
    "sg:postcode":"V0H 1X8",
    "sg:province":"BC",
    "sg:tags":[
        "appliance"
    ],
    "wof:name":"Appliance Doctors",
    "wof:placetype":"venue"
},
  "geometry": {"coordinates":[-119.77348327599999,49.7526664734],"type":"Point"}
}