{
  "type": "Feature",
  "properties": {
    "addr:full":"749 Base Line Rd E London ON N6C 2R6",
    "addr:housenumber":"749",
    "addr:postcode":"n6c 2r6",
    "addr:street":"Base Line Rd E",
    "iso:country":"CA",
    "sg:address":"749 Base Line Rd E",
    "sg:city":"London",
    "sg:classifiers":[
        {
            "category":"Social Services",
            "type":"Services"
        }
    ],
    "sg:phone":"+1 519 685 8420",
    "sg:postcode":"N6C 2R6",
    "sg:province":"ON",
    "sg:tags":[
        "organization",
        "welfare"
    ],
    "wof:name":"Canadian National Institute",
    "wof:placetype":"venue"
},
  "geometry": {"coordinates":[-81.22723388670001,42.961933136],"type":"Point"}
}