{
  "type": "Feature",
  "properties": {
    "addr:full":"13 Commercial Crt Fox Creek AB T0H 1P0",
    "addr:housenumber":"13",
    "addr:postcode":"t0h 1p0",
    "addr:street":"Commercial Crt Fox",
    "iso:country":"CA",
    "sg:address":"13 Commercial Crt",
    "sg:city":"Fox Creek",
    "sg:classifiers":[
        {
            "category":"Food & Beverages",
            "subcategory":"Groceries & Convenience Stores",
            "type":"Retail Goods"
        }
    ],
    "sg:phone":"+1 780 622 3779",
    "sg:postcode":"T0H 1P0",
    "sg:province":"AB",
    "sg:tags":[
        "grocer"
    ],
    "wof:name":"Fox Creek Iga",
    "wof:placetype":"venue"
},
  "geometry": {"coordinates":[-116.804946899,54.3941078186],"type":"Point"}
}