{
  "type": "Feature",
  "properties": {
    "addr:full":"9904 98 St Fort St John BC V1J 3T8",
    "addr:housenumber":"9904",
    "addr:postcode":"v1j 3t8",
    "addr:street":"98 St",
    "iso:country":"CA",
    "sg:address":"9904 98 St",
    "sg:city":"Fort St John",
    "sg:classifiers":[
        {
            "category":"Organizations",
            "subcategory":"Religious Organization",
            "type":"Services"
        }
    ],
    "sg:phone":"+1 250 785 4644",
    "sg:postcode":"V1J 3T8",
    "sg:province":"BC",
    "sg:tags":[
        "church"
    ],
    "wof:name":"Christian & Missionary Church",
    "wof:placetype":"venue"
},
  "geometry": {"coordinates":[-120.844177246,56.2455291748],"type":"Point"}
}