{
  "type": "Feature",
  "properties": {
    "addr:full":"500 Errol Rd W Sarnia ON N7V 1X7",
    "addr:housenumber":"500",
    "addr:postcode":"n7v 1x7",
    "addr:street":"Errol Rd W",
    "iso:country":"CA",
    "sg:address":"500 Errol Rd W",
    "sg:city":"Sarnia",
    "sg:classifiers":[
        {
            "category":"Recreation",
            "type":"Entertainment"
        }
    ],
    "sg:phone":"+1 519 336 2201",
    "sg:postcode":"N7V 1X7",
    "sg:province":"ON",
    "sg:tags":[
        "course",
        "golf"
    ],
    "wof:name":"Sarnia Golf & Curling Club Ltd",
    "wof:placetype":"venue"
},
  "geometry": {"coordinates":[-82.393372,42.992195],"type":"Point"}
}