{
  "type": "Feature",
  "properties": {
    "addr:full":"21 Weber St N Waterloo ON N2J 3G5",
    "addr:housenumber":"21",
    "addr:postcode":"n2j 3g5",
    "addr:street":"Weber St N",
    "iso:country":"CA",
    "sg:address":"21 Weber St N",
    "sg:city":"Waterloo",
    "sg:classifiers":[
        {
            "category":"Shopping",
            "subcategory":"Optical Goods",
            "type":"Retail Goods"
        }
    ],
    "sg:phone":"+1 519 884 2828",
    "sg:postcode":"N2J 3G5",
    "sg:province":"ON",
    "sg:tags":[
        "optician"
    ],
    "wof:name":"Hakim Optical Factory Outlet",
    "wof:placetype":"venue"
},
  "geometry": {"coordinates":[-80.51174163819999,43.4691314697],"type":"Point"}
}