{
  "type": "Feature",
  "properties": {
    "iso:country":"CA",
    "sg:city":"Pemberton",
    "sg:classifiers":[
        {
            "category":"Retail",
            "subcategory":"Laundry & Dry Cleaning",
            "type":"Services"
        }
    ],
    "sg:phone":"+1 604 894 9479",
    "sg:postcode":"V0N 2L1",
    "sg:province":"BC",
    "sg:tags":[
        "cleaners",
        "janitor",
        "rug",
        "carpet"
    ],
    "wof:name":"Eagle Springs Carpet",
    "wof:placetype":"venue"
},
  "geometry": {"coordinates":[-122.80381011999999,50.3197898865],"type":"Point"}
}