{
  "type": "Feature",
  "properties": {
    "addr:full":"46 Kingswood Dr Fredericton NB E3B 6Z8",
    "addr:housenumber":"46",
    "addr:postcode":"e3b 6z8",
    "addr:street":"Kingswood Dr",
    "iso:country":"CA",
    "sg:address":"46 Kingswood Dr",
    "sg:city":"Fredericton",
    "sg:classifiers":[
        {
            "category":"Professional",
            "subcategory":"Research",
            "type":"Services"
        }
    ],
    "sg:phone":"+1 506 450 2820",
    "sg:postcode":"E3B 6Z8",
    "sg:province":"NB",
    "sg:tags":[
        "environmental",
        "ecological",
        "engineer"
    ],
    "wof:name":"Touchie Engineering Ltd",
    "wof:placetype":"venue"
},
  "geometry": {"coordinates":[-66.701561,45.963913],"type":"Point"}
}