{
  "type": "Feature",
  "properties": {
    "addr:full":"Scarborough ON M1X 1N4",
    "addr:postcode":"m1x 1n4",
    "iso:country":"CA",
    "sg:city":"Scarborough",
    "sg:classifiers":[
        {
            "category":"Manufacturing",
            "subcategory":"Apparel",
            "type":"Manufacturing & Wholesale Goods"
        }
    ],
    "sg:phone":"+1 416 299 1833",
    "sg:postcode":"M1X 1N4",
    "sg:province":"ON",
    "sg:tags":[
        "flag",
        "sign"
    ],
    "wof:name":"Signs 2 Go",
    "wof:placetype":"venue"
},
  "geometry": {"coordinates":[-79.2418746948,43.8225364685],"type":"Point"}
}