{
  "type": "Feature",
  "properties": {
    "addr:full":"8 Church St E Brampton ON L6V 1E9",
    "addr:housenumber":"8",
    "addr:postcode":"l6v 1e9",
    "addr:street":"Church St E",
    "iso:country":"CA",
    "sg:address":"8 Church St E",
    "sg:city":"Brampton",
    "sg:classifiers":[
        {
            "category":"Personal",
            "subcategory":"Beauty Salon",
            "type":"Services"
        }
    ],
    "sg:phone":"+1 905 459 4525",
    "sg:postcode":"L6V 1E9",
    "sg:province":"ON",
    "wof:name":"Hans Hair Stylist",
    "wof:placetype":"venue"
},
  "geometry": {"coordinates":[-79.76264999999999,43.688541],"type":"Point"}
}