{
  "type": "Feature",
  "properties": {
    "addr:full":"3460 Boul Dagenais O Laval QC H7P 1V6",
    "addr:housenumber":"3460",
    "addr:postcode":"h7p 1v6",
    "addr:street":"Boul Dagenais O",
    "iso:country":"CA",
    "sg:address":"3460 Boul Dagenais O",
    "sg:city":"Laval",
    "sg:classifiers":[
        {
            "category":"Restaurant",
            "type":"Food & Drink"
        }
    ],
    "sg:phone":"+1 450 622 9641",
    "sg:postcode":"H7P 1V6",
    "sg:province":"QC",
    "wof:name":"Calimero Restaurant",
    "wof:placetype":"venue"
},
  "geometry": {"coordinates":[-73.80847900000001,45.577488],"type":"Point"}
}