{
  "type": "Feature",
  "properties": {
    "addr:full":"85 King St E Bowmanville ON L1C 1N4",
    "addr:housenumber":"85",
    "addr:postcode":"l1c 1n4",
    "addr:street":"King St",
    "iso:country":"CA",
    "sg:address":"85 King St E",
    "sg:city":"Bowmanville",
    "sg:classifiers":[
        {
            "category":"Food & Beverages",
            "subcategory":"Groceries & Convenience Stores",
            "type":"Retail Goods"
        }
    ],
    "sg:phone":"+1 905 623 1350",
    "sg:postcode":"L1C 1N4",
    "sg:province":"ON",
    "sg:tags":[
        "grocer"
    ],
    "wof:name":"Puffins Variety",
    "wof:placetype":"venue"
},
  "geometry": {"coordinates":[-78.6866226196,43.9114112854],"type":"Point"}
}