{
  "type": "Feature",
  "properties": {
    "addr:full":"Saint-Alexis-Des-Monts QC J0K 1V0",
    "addr:postcode":"j0k 1v0",
    "iso:country":"CA",
    "sg:city":"Saint-Alexis-Des-Monts",
    "sg:classifiers":[
        {
            "category":"Building & Trades",
            "subcategory":"Construction",
            "type":"Services"
        }
    ],
    "sg:phone":"+1 819 265 2431",
    "sg:postcode":"J0K 1V0",
    "sg:province":"QC",
    "sg:tags":[
        "painter"
    ],
    "wof:name":"Peinture Jacques Elliott Inc",
    "wof:placetype":"venue"
},
  "geometry": {"coordinates":[-73.1486587524,46.4675559998],"type":"Point"}
}