{
  "type": "Feature",
  "properties": {
    "addr:full":"19 Sheldon Ave N Kitchener ON N2H 3M1",
    "addr:housenumber":"19",
    "addr:postcode":"n2h 3m1",
    "addr:street":"Sheldon Ave N",
    "iso:country":"CA",
    "sg:address":"19 Sheldon Ave N",
    "sg:city":"Kitchener",
    "sg:classifiers":[
        {
            "category":"Shopping",
            "subcategory":"Clothing, Apparel, & Fashions",
            "type":"Retail Goods"
        }
    ],
    "sg:phone":"+1 519 579 4122",
    "sg:postcode":"N2H 3M1",
    "sg:province":"ON",
    "sg:tags":[
        "dressmaker"
    ],
    "wof:name":"Rias Alterations",
    "wof:placetype":"venue"
},
  "geometry": {"coordinates":[-80.467957,43.440926],"type":"Point"}
}