{
  "type": "Feature",
  "properties": {
    "addr:full":"2144 King St N St Jacobs ON N0B 2N0",
    "addr:housenumber":"2144",
    "addr:postcode":"n0b 2n0",
    "addr:street":"King St N St",
    "iso:country":"CA",
    "sg:address":"2144 King St N",
    "sg:city":"St Jacobs",
    "sg:classifiers":[
        {
            "category":"Home & Garden",
            "subcategory":"Furniture",
            "type":"Retail Goods"
        }
    ],
    "sg:phone":"+1 519 664 3365",
    "sg:postcode":"N0B 2N0",
    "sg:province":"ON",
    "wof:name":"Frey, Levi M",
    "wof:placetype":"venue"
},
  "geometry": {"coordinates":[-80.582352,43.555153],"type":"Point"}
}