{
  "type": "Feature",
  "properties": {
    "addr:full":"Dorval QC H4Y 1J6",
    "addr:postcode":"h4y 1j6",
    "iso:country":"CA",
    "sg:city":"Dorval",
    "sg:classifiers":[
        {
            "category":"Freight",
            "type":"Transportation"
        }
    ],
    "sg:phone":"+1 514 420 0651",
    "sg:postcode":"H4Y 1J6",
    "sg:province":"QC",
    "sg:tags":[
        "broker",
        "customs"
    ],
    "wof:name":"Arrival Custom Brokers Ltd",
    "wof:placetype":"venue"
},
  "geometry": {"coordinates":[-73.76113100000001,45.457432],"type":"Point"}
}