{
  "type": "Feature",
  "properties": {
    "iso:country":"CA",
    "sg:address":"1425 Rue Du Sud",
    "sg:city":"Cowansville",
    "sg:classifiers":[
        {
            "category":"Retail",
            "subcategory":"Auto Repair",
            "type":"Services"
        }
    ],
    "sg:phone":"+1 450 263 3396",
    "sg:postcode":"J2K 2Z3",
    "sg:province":"QC",
    "sg:tags":[
        "body",
        "automobile",
        "painting"
    ],
    "wof:name":"Garage Johnny Mc Dermott Inc",
    "wof:placetype":"venue"
},
  "geometry": {"coordinates":[-72.751648,45.194321],"type":"Point"}
}