{
  "type": "Feature",
  "properties": {
    "addr:full":"12 Bell St Carleton Place ON K7C 1V9",
    "addr:housenumber":"12",
    "addr:postcode":"k7c 1v9",
    "addr:street":"Bell St",
    "iso:country":"CA",
    "sg:address":"12 Bell St",
    "sg:city":"Carleton Place",
    "sg:classifiers":[
        {
            "category":"Restaurant",
            "type":"Food & Drink"
        }
    ],
    "sg:phone":"+1 613 257 5755",
    "sg:postcode":"K7C 1V9",
    "sg:province":"ON",
    "wof:name":"Leather Works Pub & Restaurant",
    "wof:placetype":"venue"
},
  "geometry": {"coordinates":[-76.147605896,45.1414833069],"type":"Point"}
}