{
  "type": "Feature",
  "properties": {
    "addr:full":"37 Spadina Rd Toronto ON M5R 2S9",
    "addr:housenumber":"37",
    "addr:postcode":"m5r 2s9",
    "addr:street":"Spadina Rd",
    "iso:country":"CA",
    "sg:address":"37 Spadina Rd",
    "sg:city":"Toronto",
    "sg:classifiers":[
        {
            "category":"Health Services",
            "subcategory":"Health Practitioner",
            "type":"Services"
        }
    ],
    "sg:phone":"+1 416 925 5854",
    "sg:postcode":"M5R 2S9",
    "sg:province":"ON",
    "sg:tags":[
        "psychotherapist"
    ],
    "wof:name":"DE Graaff, Arnold",
    "wof:placetype":"venue"
},
  "geometry": {"coordinates":[-79.40431976319999,43.668346405],"type":"Point"}
}