{
  "type": "Feature",
  "properties": {
    "addr:full":"Calgary AB T2G 4X7",
    "addr:postcode":"t2g 4x7",
    "iso:country":"CA",
    "sg:city":"Calgary",
    "sg:classifiers":[
        {
            "category":"Organizations",
            "subcategory":"Non-profit Organization",
            "type":"Services"
        }
    ],
    "sg:phone":"+1 403 777 1212",
    "sg:postcode":"T2G 4X7",
    "sg:province":"AB",
    "sg:tags":[
        "information",
        "alcoholism",
        "treatment"
    ],
    "wof:name":"Alcoholics Anonymous",
    "wof:placetype":"venue"
},
  "geometry": {"coordinates":[-114.05923461899999,51.0173187256],"type":"Point"}
}