{
  "type": "Feature",
  "properties": {
    "iso:country":"CA",
    "sg:city":"London",
    "sg:classifiers":[
        {
            "category":"Shopping",
            "subcategory":"Computers & Home Electronics",
            "type":"Retail Goods"
        }
    ],
    "sg:phone":"+1 519 679 8750",
    "sg:postcode":"N6G 3Y9",
    "sg:province":"ON",
    "sg:tags":[
        "television",
        "radio"
    ],
    "wof:name":"Sony Store",
    "wof:placetype":"venue"
},
  "geometry": {"coordinates":[-81.2817077637,43.0252723694],"type":"Point"}
}