{
  "type": "Feature",
  "properties": {
    "addr:full":"173 Kenmount Rd St. John's NL A1B 3P9",
    "addr:housenumber":"173",
    "addr:postcode":"a1b 3p9",
    "addr:street":"Kenmount Rd",
    "iso:country":"CA",
    "sg:address":"173 Kenmount Rd",
    "sg:city":"St. John's",
    "sg:classifiers":[
        {
            "category":"Building & Trades",
            "subcategory":"Construction",
            "type":"Services"
        }
    ],
    "sg:phone":"+1 709 753 8957",
    "sg:postcode":"A1B 3P9",
    "sg:province":"NL",
    "sg:tags":[
        "woodworker"
    ],
    "wof:name":"Scaplen Woodworking",
    "wof:placetype":"venue"
},
  "geometry": {"coordinates":[-52.765648,47.55537],"type":"Point"}
}