{
  "type": "Feature",
  "properties": {
    "addr:full":"155 Rue DE Port-Royal O Montreal QC H3L 2B3",
    "addr:housenumber":"155",
    "addr:postcode":"h3l 2b3",
    "addr:street":"Rue De Port-Royal O",
    "iso:country":"CA",
    "sg:address":"155 Rue DE Port-Royal O",
    "sg:city":"Montreal",
    "sg:classifiers":[
        {
            "category":"Wholesale",
            "subcategory":"Durable Goods & Equipment",
            "type":"Manufacturing & Wholesale Goods"
        }
    ],
    "sg:phone":"+1 514 385 0813",
    "sg:postcode":"H3L 2B3",
    "sg:province":"QC",
    "sg:tags":[
        "importer"
    ],
    "wof:name":"Newport Pagnell Investments",
    "wof:placetype":"venue"
},
  "geometry": {"coordinates":[-73.65664700000001,45.547523],"type":"Point"}
}