{
  "type": "Feature",
  "properties": {
    "addr:full":"91 Caldari Rd Concord ON L4K 3Z9",
    "addr:housenumber":"91",
    "addr:postcode":"l4k 3z9",
    "addr:street":"Caldari Rd",
    "iso:country":"CA",
    "sg:address":"91 Caldari Rd",
    "sg:city":"Concord",
    "sg:classifiers":[
        {
            "category":"Freight",
            "type":"Transportation"
        }
    ],
    "sg:phone":"+1 416 667 1803",
    "sg:postcode":"L4K 3Z9",
    "sg:province":"ON",
    "wof:name":"Cavalier Transportation Svc",
    "wof:placetype":"venue"
},
  "geometry": {"coordinates":[-79.527939,43.819485],"type":"Point"}
}