{
  "type": "Feature",
  "properties": {
    "addr:full":"100 Ash Ave # 52V Kaleden BC V0H 1K0",
    "addr:housenumber":"100",
    "addr:postcode":"v0h 1k0",
    "addr:street":"Ash Ave # 52V",
    "iso:country":"CA",
    "sg:address":"100 Ash Ave # 52V",
    "sg:city":"Kaleden",
    "sg:classifiers":[
        {
            "category":"Travel",
            "subcategory":"Campground",
            "type":"Entertainment"
        }
    ],
    "sg:phone":"+1 250 497 5584",
    "sg:postcode":"V0H 1K0",
    "sg:province":"BC",
    "wof:name":"Camp-Along Resort",
    "wof:placetype":"venue"
},
  "geometry": {"coordinates":[-119.602142,49.392677],"type":"Point"}
}