{
  "type": "Feature",
  "properties": {
    "addr:full":"975 Logan Ave Winnipeg MB R3E 1P3",
    "addr:housenumber":"975",
    "addr:postcode":"r3e 1p3",
    "addr:street":"Logan Ave",
    "iso:country":"CA",
    "sg:address":"975 Logan Ave",
    "sg:city":"Winnipeg",
    "sg:classifiers":[
        {
            "category":"Manufacturing",
            "subcategory":"Building Materials",
            "type":"Manufacturing & Wholesale Goods"
        }
    ],
    "sg:phone":"+1 204 774 4533",
    "sg:postcode":"R3E 1P3",
    "sg:province":"MB",
    "sg:tags":[
        "frame",
        "door"
    ],
    "wof:name":"Greensteel Industries",
    "wof:placetype":"venue"
},
  "geometry": {"coordinates":[-97.164169,49.911762],"type":"Point"}
}