{
  "type": "Feature",
  "properties": {
    "addr:full":"1603 Rue Saint-Regis Dollard-Des-Ormeaux QC H9B 3H7",
    "addr:housenumber":"1603",
    "addr:postcode":"h9b 3h7",
    "addr:street":"Rue Saint-Regis",
    "iso:country":"CA",
    "sg:address":"1603 Rue Saint-Regis",
    "sg:city":"Dollard-Des-Ormeaux",
    "sg:classifiers":[
        {
            "category":"Professional",
            "subcategory":"Management & Consulting",
            "type":"Services"
        }
    ],
    "sg:phone":"+1 514 684 4554",
    "sg:postcode":"H9B 3H7",
    "sg:province":"QC",
    "sg:tags":[
        "consultant",
        "telecommunication"
    ],
    "wof:name":"Focus Microwaves Inc",
    "wof:placetype":"venue"
},
  "geometry": {"coordinates":[-73.778793335,45.4895935059],"type":"Point"}
}