{
  "type": "Feature",
  "properties": {
    "addr:full":"Concord ON L4K 4H3",
    "addr:postcode":"l4k 4h3",
    "iso:country":"CA",
    "sg:city":"Concord",
    "sg:classifiers":[
        {
            "category":"Building & Trades",
            "subcategory":"Electrical",
            "type":"Services"
        }
    ],
    "sg:phone":"+1 905 660 9956",
    "sg:postcode":"L4K 4H3",
    "sg:province":"ON",
    "sg:tags":[
        "electric",
        "contractor"
    ],
    "wof:name":"Proto Electric Contracting Inc",
    "wof:placetype":"venue"
},
  "geometry": {"coordinates":[-79.53552999999999,43.805725],"type":"Point"}
}