{
  "type": "Feature",
  "properties": {
    "addr:full":"North York ON M3C 1J4",
    "addr:postcode":"m3c 1j4",
    "iso:country":"CA",
    "sg:city":"North York",
    "sg:classifiers":[
        {
            "category":"Health Services",
            "subcategory":"Doctor",
            "type":"Services"
        }
    ],
    "sg:phone":"+1 416 441 1060",
    "sg:postcode":"M3C 1J4",
    "sg:province":"ON",
    "sg:tags":[
        "physician",
        "surgeon"
    ],
    "wof:name":"Barrington, T W MD",
    "wof:placetype":"venue"
},
  "geometry": {"coordinates":[-79.336029,43.723732],"type":"Point"}
}