{
  "type": "Feature",
  "properties": {
    "addr:full":"40 Golden Ave South Porcupine ON P0N 1H0",
    "addr:housenumber":"40",
    "addr:postcode":"p0n 1h0",
    "addr:street":"Golden Ave South",
    "iso:country":"CA",
    "sg:address":"40 Golden Ave",
    "sg:city":"South Porcupine",
    "sg:classifiers":[
        {
            "category":"Building & Trades",
            "subcategory":"Electrical",
            "type":"Services"
        }
    ],
    "sg:phone":"+1 705 235 4045",
    "sg:postcode":"P0N 1H0",
    "sg:province":"ON",
    "sg:tags":[
        "plumbing",
        "electric",
        "contractor"
    ],
    "wof:name":"Tisdale Plumbing & Heating Ltd",
    "wof:placetype":"venue"
},
  "geometry": {"coordinates":[-81.213486,48.477451],"type":"Point"}
}