{
  "type": "Feature",
  "properties": {
    "addr:full":"1350 Polson Dr Vernon BC V1T 8H2",
    "addr:housenumber":"1350",
    "addr:postcode":"v1t 8h2",
    "addr:street":"Polson Dr",
    "iso:country":"CA",
    "sg:address":"1350 Polson Dr",
    "sg:city":"Vernon",
    "sg:classifiers":[
        {
            "category":"Building & Trades",
            "subcategory":"Plumbing",
            "type":"Services"
        }
    ],
    "sg:phone":"+1 250 503 2533",
    "sg:postcode":"V1T 8H2",
    "sg:province":"BC",
    "sg:tags":[
        "sheet",
        "work",
        "metal",
        "contractor"
    ],
    "wof:name":"Allied Blower & Sheet Metal",
    "wof:placetype":"venue"
},
  "geometry": {"coordinates":[-119.265586853,50.2515716553],"type":"Point"}
}