{
  "type": "Feature",
  "properties": {
    "addr:full":"Saint-Zacharie QC G0M 2C0",
    "addr:postcode":"g0m 2c0",
    "iso:country":"CA",
    "sg:city":"Saint-Zacharie",
    "sg:classifiers":[
        {
            "category":"Professional",
            "subcategory":"Accounting & Tax Preparation",
            "type":"Services"
        }
    ],
    "sg:phone":"+1 418 593 5353",
    "sg:postcode":"G0M 2C0",
    "sg:province":"QC",
    "sg:tags":[
        "accountant"
    ],
    "wof:name":"Poirier, Germaine",
    "wof:placetype":"venue"
},
  "geometry": {"coordinates":[-70.363983,46.126015],"type":"Point"}
}