{
  "type": "Feature",
  "properties": {
    "addr:full":"105 Athabasca Ave Hinton AB T7V 2A4",
    "addr:housenumber":"105",
    "addr:postcode":"t7v 2a4",
    "addr:street":"Athabasca Ave",
    "iso:country":"CA",
    "sg:address":"105 Athabasca Ave",
    "sg:city":"Hinton",
    "sg:classifiers":[
        {
            "category":"Food & Beverages",
            "subcategory":"Liquor & Beverages",
            "type":"Retail Goods"
        }
    ],
    "sg:phone":"+1 780 865 3633",
    "sg:postcode":"T7V 2A4",
    "sg:province":"AB",
    "sg:tags":[
        "store"
    ],
    "wof:name":"Imperial Liquor",
    "wof:placetype":"venue"
},
  "geometry": {"coordinates":[-117.542511,53.425022],"type":"Point"}
}