{
  "type": "Feature",
  "properties": {
    "addr:full":"London ON N6J 3T4",
    "addr:postcode":"n6j 3t4",
    "iso:country":"CA",
    "sg:city":"London",
    "sg:classifiers":[
        {
            "category":"Professional",
            "subcategory":"Business Services",
            "type":"Services"
        }
    ],
    "sg:phone":"+1 519 668 2375",
    "sg:postcode":"N6J 3T4",
    "sg:province":"ON",
    "sg:tags":[
        "process",
        "server"
    ],
    "wof:name":"Morgan Financial Svc",
    "wof:placetype":"venue"
},
  "geometry": {"coordinates":[-81.2618942261,42.9470329285],"type":"Point"}
}