{
  "type": "Feature",
  "properties": {
    "iso:country":"CA",
    "sg:address":"1702 23 St N",
    "sg:city":"Lethbridge",
    "sg:classifiers":[
        {
            "category":"Restaurant",
            "type":"Food & Drink"
        }
    ],
    "sg:phone":"+1 403 329 0132",
    "sg:postcode":"T1H 5B3",
    "sg:province":"AB",
    "wof:name":"Onion Bar & Grill",
    "wof:placetype":"venue"
},
  "geometry": {"coordinates":[-112.810516357,49.7200965881],"type":"Point"}
}