{
  "type": "Feature",
  "properties": {
    "addr:full":"357 Boul Du Seminaire N Saint-Jean-Sur-Richelieu QC J3B 8C5",
    "addr:housenumber":"357",
    "addr:postcode":"j3b 8c5",
    "addr:street":"Boul Du Seminaire N",
    "iso:country":"CA",
    "sg:address":"357 Boul Du Seminaire N",
    "sg:city":"Saint-Jean-Sur-Richelieu",
    "sg:classifiers":[
        {
            "category":"Professional",
            "subcategory":"Accounting & Tax Preparation",
            "type":"Services"
        }
    ],
    "sg:phone":"+1 450 348 6886",
    "sg:postcode":"J3B 8C5",
    "sg:province":"QC",
    "sg:tags":[
        "accountant"
    ],
    "wof:name":"Raymond Chabot Grant Thornton",
    "wof:placetype":"venue"
},
  "geometry": {"coordinates":[-73.264877,45.311481],"type":"Point"}
}