{
  "type": "Feature",
  "properties": {
    "addr:full":"286 Rue Jacques-Cartier Salaberry-DE-Valleyfield QC J6T 4T1",
    "addr:housenumber":"286",
    "addr:postcode":"j6t 4t1",
    "addr:street":"Rue Jacques-Cartier",
    "iso:country":"CA",
    "sg:address":"286 Rue Jacques-Cartier",
    "sg:city":"Salaberry-DE-Valleyfield",
    "sg:classifiers":[
        {
            "category":"Wholesale",
            "subcategory":"Electrical",
            "type":"Manufacturing & Wholesale Goods"
        }
    ],
    "sg:phone":"+1 450 373 1294",
    "sg:postcode":"J6T 4T1",
    "sg:province":"QC",
    "sg:tags":[
        "sound",
        "equipment",
        "television",
        "radio",
        "system"
    ],
    "wof:name":"Martel Electronique",
    "wof:placetype":"venue"
},
  "geometry": {"coordinates":[-74.121109,45.244469],"type":"Point"}
}