{
  "type": "Feature",
  "properties": {
    "addr:full":"598 Gould St Wiarton ON N0H 2T0",
    "addr:housenumber":"598",
    "addr:postcode":"n0h 2t0",
    "addr:street":"Gould St",
    "iso:country":"CA",
    "sg:address":"598 Gould St",
    "sg:city":"Wiarton",
    "sg:classifiers":[
        {
            "category":"Health Services",
            "subcategory":"Nursing And Care Facility",
            "type":"Services"
        }
    ],
    "sg:phone":"+1 519 534 3357",
    "sg:postcode":"N0H 2T0",
    "sg:province":"ON",
    "sg:tags":[
        "home",
        "retirement",
        "community"
    ],
    "wof:name":"New Horizons Retirement Home",
    "wof:placetype":"venue"
},
  "geometry": {"coordinates":[-81.142754,44.743073],"type":"Point"}
}