{
  "type": "Feature",
  "properties": {
    "iso:country":"CA",
    "sg:address":"RR 1 Lcd 1",
    "sg:city":"Red Deer",
    "sg:classifiers":[
        {
            "category":"Autos & Motor Vehicles",
            "subcategory":"Auto Supplies",
            "type":"Retail Goods"
        }
    ],
    "sg:phone":"+1 403 347 0332",
    "sg:postcode":"T4N 5E1",
    "sg:province":"AB",
    "sg:tags":[
        "automobile",
        "parts"
    ],
    "wof:name":"Western Rose 1996 Ltd",
    "wof:placetype":"venue"
},
  "geometry": {"coordinates":[-113.817436218,52.2623023987],"type":"Point"}
}