{
  "type": "Feature",
  "properties": {
    "addr:full":"3595 Boul DE LA Rive-Sud Levis QC G6W 6P5",
    "addr:housenumber":"3595",
    "addr:postcode":"g6w 6p5",
    "addr:street":"Boul De La Rive-Sud",
    "iso:country":"CA",
    "sg:address":"3595 Boul DE LA Rive-Sud",
    "sg:city":"Levis",
    "sg:classifiers":[
        {
            "category":"Government",
            "subcategory":"Office",
            "type":"Public Place"
        }
    ],
    "sg:phone":"+1 418 833 0850",
    "sg:postcode":"G6W 6P5",
    "sg:province":"QC",
    "wof:name":"Canada Agriculture",
    "wof:placetype":"venue"
},
  "geometry": {"coordinates":[-71.200943,46.769367],"type":"Point"}
}