{
  "type": "Feature",
  "properties": {
    "addr:full":"Woodstock NB E7M 2N9",
    "addr:postcode":"e7m 2n9",
    "iso:country":"CA",
    "sg:city":"Woodstock",
    "sg:classifiers":[
        {
            "category":"Social Services",
            "type":"Services"
        }
    ],
    "sg:phone":"+1 506 328 8881",
    "sg:postcode":"E7M 2N9",
    "sg:province":"NB",
    "sg:tags":[
        "organization",
        "welfare"
    ],
    "wof:name":"Canadian Red Cross Society",
    "wof:placetype":"venue"
},
  "geometry": {"coordinates":[-67.571487,46.153301],"type":"Point"}
}