{
  "type": "Feature",
  "properties": {
    "addr:full":"30 Norfolk St S Simcoe ON N3Y 2V9",
    "addr:housenumber":"30",
    "addr:postcode":"n3y 2v9",
    "addr:street":"Norfolk St S",
    "iso:country":"CA",
    "sg:address":"30 Norfolk St S",
    "sg:city":"Simcoe",
    "sg:classifiers":[
        {
            "category":"Shopping",
            "subcategory":"Jewelry",
            "type":"Retail Goods"
        }
    ],
    "sg:phone":"+1 519 426 3948",
    "sg:postcode":"N3Y 2V9",
    "sg:province":"ON",
    "sg:tags":[
        "jeweler"
    ],
    "wof:name":"Halmo Jewellers Ltd",
    "wof:placetype":"venue"
},
  "geometry": {"coordinates":[-80.3039474487,42.8367500305],"type":"Point"}
}