{
  "type": "Feature",
  "properties": {
    "addr:full":"896 Mcpherson Dr Corbeil ON P0H 1K0",
    "addr:housenumber":"896",
    "addr:postcode":"p0h 1k0",
    "addr:street":"Mcpherson Dr Corbeil",
    "iso:country":"CA",
    "sg:address":"896 Mcpherson Dr",
    "sg:city":"Corbeil",
    "sg:classifiers":[
        {
            "category":"Shopping",
            "subcategory":"Computers & Home Electronics",
            "type":"Retail Goods"
        }
    ],
    "sg:phone":"+1 705 752 3413",
    "sg:postcode":"P0H 1K0",
    "sg:province":"ON",
    "sg:tags":[
        "parts",
        "supply"
    ],
    "wof:name":"Toner Cartridge Svc",
    "wof:placetype":"venue"
},
  "geometry": {"coordinates":[-79.29141235349999,46.2617683411],"type":"Point"}
}