{
  "type": "Feature",
  "properties": {
    "iso:country":"CA",
    "sg:address":"167 Main St E # 1",
    "sg:city":"Grimsby",
    "sg:classifiers":[
        {
            "category":"Health Services",
            "subcategory":"Hospital",
            "type":"Services"
        }
    ],
    "sg:phone":"+1 905 309 3336",
    "sg:postcode":"L3M 1P2",
    "sg:province":"ON",
    "sg:tags":[
        "mental"
    ],
    "wof:name":"West Niagara Mental Health",
    "wof:placetype":"venue"
},
  "geometry": {"coordinates":[-79.5422286987,43.1876678467],"type":"Point"}
}