{
  "type": "Feature",
  "properties": {
    "iso:country":"CA",
    "sg:city":"Red Deer County",
    "sg:classifiers":[
        {
            "category":"Organizations",
            "subcategory":"Professional Association",
            "type":"Services"
        }
    ],
    "sg:phone":"+1 403 347 1505",
    "sg:postcode":"T4E 1B4",
    "sg:province":"AB",
    "wof:name":"Moose Hall",
    "wof:placetype":"venue"
},
  "geometry": {"coordinates":[-113.93549346899999,52.0221366882],"type":"Point"}
}