{
  "type": "Feature",
  "properties": {
    "addr:full":"Charlottetown PE C1A 7M4",
    "addr:postcode":"c1a 7m4",
    "iso:country":"CA",
    "sg:city":"Charlottetown",
    "sg:classifiers":[
        {
            "category":"Organizations",
            "subcategory":"Religious Organization",
            "type":"Services"
        }
    ],
    "sg:phone":"+1 902 368 1226",
    "sg:postcode":"C1A 7M4",
    "sg:province":"PE",
    "sg:tags":[
        "church"
    ],
    "wof:name":"Calvary Temple Paoc",
    "wof:placetype":"venue"
},
  "geometry": {"coordinates":[-63.1281700134,46.2365913391],"type":"Point"}
}