{
  "type": "Feature",
  "properties": {
    "iso:country":"CA",
    "sg:address":"171 Rue Choquette",
    "sg:city":"Dollard-Des-Ormeaux",
    "sg:classifiers":[
        {
            "category":"Wholesale",
            "subcategory":"Machinery & Supplies",
            "type":"Manufacturing & Wholesale Goods"
        }
    ],
    "sg:phone":"+1 514 624 1263",
    "sg:postcode":"H9A 3H2",
    "sg:province":"QC",
    "sg:tags":[
        "equipment",
        "video",
        "system",
        "vacuum"
    ],
    "wof:name":"Amberhill Distribution Inc",
    "wof:placetype":"venue"
},
  "geometry": {"coordinates":[-73.8414077759,45.4890594482],"type":"Point"}
}