{
  "type": "Feature",
  "properties": {
    "addr:full":"122 Boul Saint-Martin O Laval QC H7M 3Y8",
    "addr:housenumber":"122",
    "addr:postcode":"h7m 3y8",
    "addr:street":"Boul Saint-Martin O",
    "iso:country":"CA",
    "sg:address":"122 Boul Saint-Martin O",
    "sg:city":"Laval",
    "sg:classifiers":[
        {
            "category":"Restaurant",
            "type":"Food & Drink"
        }
    ],
    "sg:phone":"+1 450 669 4384",
    "sg:postcode":"H7M 3Y8",
    "sg:province":"QC",
    "wof:name":"Wendy's",
    "wof:placetype":"venue"
},
  "geometry": {"coordinates":[-73.70710800000001,45.580776],"type":"Point"}
}