{
  "type": "Feature",
  "properties": {
    "addr:full":"2055 Ch Dewey Stanstead QC J0B 3E1",
    "addr:postcode":"2055;j0b 3e1",
    "addr:street":"Ch Dewey",
    "iso:country":"CA",
    "sg:address":"2055 Ch Dewey",
    "sg:city":"Stanstead",
    "sg:classifiers":[
        {
            "category":"Wholesale",
            "subcategory":"Fruits & Vegetables",
            "type":"Manufacturing & Wholesale Goods"
        }
    ],
    "sg:phone":"+1 819 876 7300",
    "sg:postcode":"J0B 3E1",
    "sg:province":"QC",
    "sg:tags":[
        "shipper"
    ],
    "wof:name":"Verger Stevens Orchard",
    "wof:placetype":"venue"
},
  "geometry": {"coordinates":[-72.0642776489,45.0228691101],"type":"Point"}
}