{
  "type": "Feature",
  "properties": {
    "addr:full":"130 Gerstmar Rd Kelowna BC V1X 4A7",
    "addr:housenumber":"130",
    "addr:postcode":"v1x 4a7",
    "addr:street":"Gerstmar Rd",
    "iso:country":"CA",
    "sg:address":"130 Gerstmar Rd",
    "sg:city":"Kelowna",
    "sg:classifiers":[
        {
            "category":"Organizations",
            "subcategory":"Religious Organization",
            "type":"Services"
        }
    ],
    "sg:phone":"+1 250 860 5096",
    "sg:postcode":"V1X 4A7",
    "sg:province":"BC",
    "sg:tags":[
        "church"
    ],
    "wof:name":"Seventh Day Adventist Church",
    "wof:placetype":"venue"
},
  "geometry": {"coordinates":[-119.409599304,49.8885116577],"type":"Point"}
}