{
  "type": "Feature",
  "properties": {
    "addr:full":"32203 South Fraser Way Abbotsford BC V2T 1W6",
    "addr:housenumber":"32203",
    "addr:postcode":"v2t 1w6",
    "addr:street":"South Fraser Way",
    "iso:country":"CA",
    "sg:address":"32203 South Fraser Way",
    "sg:city":"Abbotsford",
    "sg:classifiers":[
        {
            "category":"Government",
            "subcategory":"Office",
            "type":"Public Place"
        }
    ],
    "sg:phone":"+1 604 855 3200",
    "sg:postcode":"V2T 1W6",
    "sg:province":"BC",
    "wof:name":"BC Provincial Court",
    "wof:placetype":"venue"
},
  "geometry": {"coordinates":[-122.338066,49.049358],"type":"Point"}
}