{
  "type": "Feature",
  "properties": {
    "iso:country":"CA",
    "sg:address":"308 King St",
    "sg:city":"Midland",
    "sg:classifiers":[
        {
            "category":"Social Services",
            "subcategory":"Child Care",
            "type":"Services"
        }
    ],
    "sg:phone":"+1 705 526 7513",
    "sg:postcode":"L4R 3M6",
    "sg:province":"ON",
    "wof:name":"Midland Nursery School",
    "wof:placetype":"venue"
},
  "geometry": {"coordinates":[-79.8849029541,44.7490692139],"type":"Point"}
}