{
  "type": "Feature",
  "properties": {
    "addr:full":"12 Allee Mcintyre Baie-Sainte-Anne NB E9A 1C2",
    "addr:housenumber":"12",
    "addr:postcode":"e9a 1c2",
    "addr:street":"Allee Mcintyre Baie-Sainte-Anne",
    "iso:country":"CA",
    "sg:address":"12 Allee Mcintyre",
    "sg:city":"Baie-Sainte-Anne",
    "sg:classifiers":[
        {
            "category":"Wholesale",
            "subcategory":"Seafood",
            "type":"Manufacturing & Wholesale Goods"
        }
    ],
    "sg:phone":"+1 506 228 1180",
    "sg:postcode":"E9A 1C2",
    "sg:province":"NB",
    "wof:name":"Manuel's Seafoods Ltd",
    "wof:placetype":"venue"
},
  "geometry": {"coordinates":[-64.9677886963,47.0468902588],"type":"Point"}
}