{
  "type": "Feature",
  "properties": {
    "addr:full":"1198 Rue William Montreal QC H3C 1R1",
    "addr:housenumber":"1198",
    "addr:postcode":"h3c 1r1",
    "addr:street":"Rue William",
    "iso:country":"CA",
    "sg:address":"1198 Rue William",
    "sg:city":"Montreal",
    "sg:classifiers":[
        {
            "category":"Building & Trades",
            "subcategory":"Electrical",
            "type":"Services"
        }
    ],
    "sg:phone":"+1 514 935 1131",
    "sg:postcode":"H3C 1R1",
    "sg:province":"QC",
    "sg:tags":[
        "electric",
        "contractor"
    ],
    "wof:name":"Bremer Electric CO",
    "wof:placetype":"venue"
},
  "geometry": {"coordinates":[-73.56231699999999,45.493134],"type":"Point"}
}