{
  "type": "Feature",
  "properties": {
    "addr:full":"6947 Av Wilderton Montreal QC H3S 2M4",
    "addr:housenumber":"6947",
    "addr:postcode":"h3s 2m4",
    "addr:street":"Av Wilderton",
    "iso:country":"CA",
    "sg:address":"6947 Av Wilderton",
    "sg:city":"Montreal",
    "sg:classifiers":[
        {
            "category":"Wholesale",
            "subcategory":"Meat",
            "type":"Manufacturing & Wholesale Goods"
        }
    ],
    "sg:phone":"+1 514 735 3001",
    "sg:postcode":"H3S 2M4",
    "sg:province":"QC",
    "sg:tags":[
        "butchering"
    ],
    "wof:name":"Boucherie Cachere Shapiro",
    "wof:placetype":"venue"
},
  "geometry": {"coordinates":[-73.6307067871,45.5131988525],"type":"Point"}
}