{
  "type": "Feature",
  "properties": {
    "addr:full":"1633 Parker Ave Regina SK S4S 4R9",
    "addr:housenumber":"1633",
    "addr:postcode":"s4s 4r9",
    "addr:street":"Parker Ave",
    "iso:country":"CA",
    "sg:address":"1633 Parker Ave",
    "sg:city":"Regina",
    "sg:classifiers":[
        {
            "category":"Banks & Credit Unions",
            "subcategory":"Investment Brokerage",
            "type":"Services"
        }
    ],
    "sg:phone":"+1 306 586 4729",
    "sg:postcode":"S4S 4R9",
    "sg:province":"SK",
    "sg:tags":[
        "consultant",
        "planning",
        "financial"
    ],
    "wof:name":"Crystal Financial Consultants",
    "wof:placetype":"venue"
},
  "geometry": {"coordinates":[-104.60534699999999,50.411716],"type":"Point"}
}