{
  "type": "Feature",
  "properties": {
    "addr:full":"PO Box 106 New Norway AB T0B 3L0",
    "addr:housenumber":"po;106",
    "addr:postcode":"t0b 3l0",
    "addr:street":"Box;New",
    "iso:country":"CA",
    "sg:address":"PO Box 106",
    "sg:city":"New Norway",
    "sg:classifiers":[
        {
            "category":"Wholesale",
            "subcategory":"Electrical",
            "type":"Manufacturing & Wholesale Goods"
        }
    ],
    "sg:phone":"+1 780 855 3779",
    "sg:postcode":"T0B 3L0",
    "sg:province":"AB",
    "sg:tags":[
        "generator"
    ],
    "wof:name":"Huolt Electric Ltd",
    "wof:placetype":"venue"
},
  "geometry": {"coordinates":[-112.95079,52.869144],"type":"Point"}
}