{
  "type": "Feature",
  "properties": {
    "addr:full":"645 Rue Pierre-Caisse Saint-Jean-Sur-Richelieu QC J3A 1P1",
    "addr:housenumber":"645",
    "addr:postcode":"j3a 1p1",
    "addr:street":"Rue Pierre-Caisse",
    "iso:country":"CA",
    "sg:address":"645 Rue Pierre-Caisse",
    "sg:city":"Saint-Jean-Sur-Richelieu",
    "sg:classifiers":[
        {
            "category":"Shopping",
            "subcategory":"Department Store",
            "type":"Retail Goods"
        }
    ],
    "sg:phone":"+1 450 348 1001",
    "sg:postcode":"J3A 1P1",
    "sg:province":"QC",
    "wof:name":"Aubainerie",
    "wof:placetype":"venue"
},
  "geometry": {"coordinates":[-73.28198999999999,45.331959],"type":"Point"}
}