{
  "type": "Feature",
  "properties": {
    "iso:country":"CA",
    "sg:address":"1000 Rue DE LA Gauchetiere O",
    "sg:city":"Montreal",
    "sg:classifiers":[
        {
            "category":"Shopping",
            "subcategory":"Tobacco",
            "type":"Retail Goods"
        }
    ],
    "sg:phone":"+1 514 786 6106",
    "sg:postcode":"H3B 4W5",
    "sg:province":"QC",
    "sg:tags":[
        "cigarette",
        "cigar",
        "dealer"
    ],
    "wof:name":"Drugstore",
    "wof:placetype":"venue"
},
  "geometry": {"coordinates":[-73.553764,45.515373],"type":"Point"}
}