{
  "type": "Feature",
  "properties": {
    "addr:full":"2736 Fernwood Rd Victoria BC V8T 3A4",
    "addr:housenumber":"2736",
    "addr:postcode":"v8t 3a4",
    "addr:street":"Fernwood Rd",
    "iso:country":"CA",
    "sg:address":"2736 Fernwood Rd",
    "sg:city":"Victoria",
    "sg:classifiers":[
        {
            "category":"Organizations",
            "subcategory":"Religious Organization",
            "type":"Services"
        }
    ],
    "sg:phone":"+1 250 595 1411",
    "sg:postcode":"V8T 3A4",
    "sg:province":"BC",
    "sg:tags":[
        "church"
    ],
    "wof:name":"Oaklands Gospel Chapel",
    "wof:placetype":"venue"
},
  "geometry": {"coordinates":[-123.34506225600001,48.4388618469],"type":"Point"}
}