{
  "type": "Feature",
  "properties": {
    "addr:full":"777 Forest Glade Rd Margaretsville NS B0S 1N0",
    "addr:housenumber":"777",
    "addr:postcode":"b0s 1n0",
    "addr:street":"Forest Glade Rd",
    "iso:country":"CA",
    "sg:address":"777 Forest Glade Rd",
    "sg:city":"Margaretsville",
    "sg:classifiers":[
        {
            "category":"Building & Trades",
            "subcategory":"Construction",
            "type":"Services"
        }
    ],
    "sg:phone":"+1 902 765 4679",
    "sg:postcode":"B0S 1N0",
    "sg:province":"NS",
    "sg:tags":[
        "roofing",
        "contractor",
        "general"
    ],
    "wof:name":"Mc Laughlin Roofing & Siding",
    "wof:placetype":"venue"
},
  "geometry": {"coordinates":[-65.0650558472,45.0467224121],"type":"Point"}
}