{
  "type": "Feature",
  "properties": {
    "addr:full":"2449 Rue Guenette Saint-Laurent QC H4R 2E9",
    "addr:housenumber":"2449",
    "addr:postcode":"h4r 2e9",
    "addr:street":"Rue Guenette",
    "iso:country":"CA",
    "sg:address":"2449 Rue Guenette",
    "sg:city":"Saint-Laurent",
    "sg:classifiers":[
        {
            "category":"Building & Trades",
            "subcategory":"Cleaning & Sanitation",
            "type":"Services"
        }
    ],
    "sg:phone":"+1 514 332 4522",
    "sg:postcode":"H4R 2E9",
    "sg:province":"QC",
    "sg:tags":[
        "janitor"
    ],
    "wof:name":"Entretien D'Edifice Pinkham",
    "wof:placetype":"venue"
},
  "geometry": {"coordinates":[-73.728897,45.500565],"type":"Point"}
}