{
  "type": "Feature",
  "properties": {
    "addr:full":"Rigaud QC J0P 1P0",
    "addr:postcode":"j0p 1p0",
    "iso:country":"CA",
    "sg:city":"Rigaud",
    "sg:classifiers":[
        {
            "category":"Personal",
            "subcategory":"Beauty Salon",
            "type":"Services"
        }
    ],
    "sg:phone":"+1 450 451 4088",
    "sg:postcode":"J0P 1P0",
    "sg:province":"QC",
    "wof:name":"Salon Ja-Dy",
    "wof:placetype":"venue"
},
  "geometry": {"coordinates":[-74.29956799999999,45.477329],"type":"Point"}
}