{
  "type": "Feature",
  "properties": {
    "addr:full":"45 Ch Du Tour-Du-Lac Mont-Tremblant QC J8E 2A8",
    "addr:housenumber":"45",
    "addr:postcode":"j8e 2a8",
    "addr:street":"Ch Du Tour-Du-Lac",
    "iso:country":"CA",
    "sg:address":"45 Ch Du Tour-Du-Lac",
    "sg:city":"Mont-Tremblant",
    "sg:classifiers":[
        {
            "category":"Restaurant",
            "type":"Food & Drink"
        }
    ],
    "sg:phone":"+1 819 425 5557",
    "sg:postcode":"J8E 2A8",
    "sg:province":"QC",
    "wof:name":"Trattoria Di Lago",
    "wof:placetype":"venue"
},
  "geometry": {"coordinates":[-74.60781860349999,46.0868606567],"type":"Point"}
}