{
  "type": "Feature",
  "properties": {
    "iso:country":"CA",
    "sg:city":"Langley",
    "sg:classifiers":[
        {
            "category":"Restaurant",
            "type":"Food & Drink"
        }
    ],
    "sg:phone":"+1 604 534 4317",
    "sg:postcode":"V3A 7E9",
    "sg:province":"BC",
    "sg:tags":[
        "juice",
        "bars"
    ],
    "wof:name":"Orange Julius",
    "wof:placetype":"venue"
},
  "geometry": {"coordinates":[-122.677361,49.113033],"type":"Point"}
}