{
  "type": "Feature",
  "properties": {
    "addr:full":"7123 101 Ave NW Edmonton AB T6A 0H9",
    "addr:housenumber":"7123",
    "addr:postcode":"t6a 0h9",
    "addr:street":"101 Ave Nw",
    "iso:country":"CA",
    "sg:address":"7123 101 Ave NW",
    "sg:city":"Edmonton",
    "sg:classifiers":[
        {
            "category":"Personal",
            "subcategory":"Shoe Repair & Shine",
            "type":"Services"
        }
    ],
    "sg:phone":"+1 780 469 6667",
    "sg:postcode":"T6A 0H9",
    "sg:province":"AB",
    "sg:tags":[
        "repairing",
        "boot",
        "shoes"
    ],
    "wof:name":"Thiel's Shoes",
    "wof:placetype":"venue"
},
  "geometry": {"coordinates":[-113.437325,53.541084],"type":"Point"}
}