{
  "type": "Feature",
  "properties": {
    "addr:full":"496 Queen St E Toronto ON M5A 4G8",
    "addr:housenumber":"496",
    "addr:postcode":"m5a 4g8",
    "addr:street":"Queen St E",
    "iso:country":"CA",
    "sg:address":"496 Queen St E",
    "sg:city":"Toronto",
    "sg:classifiers":[
        {
            "category":"Shopping",
            "subcategory":"Computers & Home Electronics",
            "type":"Retail Goods"
        }
    ],
    "sg:phone":"+1 416 365 1777",
    "sg:postcode":"M5A 4G8",
    "sg:province":"ON",
    "sg:tags":[
        "equipment",
        "dealer"
    ],
    "wof:name":"Vistek",
    "wof:placetype":"venue"
},
  "geometry": {"coordinates":[-79.359436,43.656807],"type":"Point"}
}