{
  "type": "Feature",
  "properties": {
    "addr:full":"North York ON M6B 3B4",
    "addr:postcode":"m6b 3b4",
    "iso:country":"CA",
    "sg:city":"North York",
    "sg:classifiers":[
        {
            "category":"Education",
            "subcategory":"Special Training",
            "type":"Public Place"
        }
    ],
    "sg:phone":"+1 416 782 2071",
    "sg:postcode":"M6B 3B4",
    "sg:province":"ON",
    "sg:tags":[
        "tutoring"
    ],
    "wof:name":"Tutoring Works",
    "wof:placetype":"venue"
},
  "geometry": {"coordinates":[-79.42948199999999,43.717312],"type":"Point"}
}