{
  "type": "Feature",
  "properties": {
    "addr:full":"PO Box 665 Hines Creek AB T0H 2A0",
    "addr:housenumber":"po;665",
    "addr:postcode":"ab t0h 2a0",
    "addr:street":"Box;Creek",
    "iso:country":"CA",
    "sg:address":"PO Box 665",
    "sg:city":"Hines Creek",
    "sg:classifiers":[
        {
            "category":"Sports & Exercise",
            "subcategory":"Golf",
            "type":"Entertainment"
        }
    ],
    "sg:phone":"+1 780 494 2217",
    "sg:postcode":"T0H 2A0",
    "sg:province":"AB",
    "sg:tags":[
        "course"
    ],
    "wof:name":"Hines Creek Golf Course",
    "wof:placetype":"venue"
},
  "geometry": {"coordinates":[-118.602264404,56.2473716736],"type":"Point"}
}