{
  "type": "Feature",
  "properties": {
    "addr:full":"750 9 Ave SE Calgary AB T2G 5E1",
    "addr:housenumber":"750",
    "addr:postcode":"t2g 5e1",
    "addr:street":"9 Ave Se",
    "iso:country":"CA",
    "sg:address":"750 9 Ave SE",
    "sg:city":"Calgary",
    "sg:classifiers":[
        {
            "category":"Museum",
            "type":"Entertainment"
        }
    ],
    "sg:phone":"+1 403 290 1875",
    "sg:postcode":"T2G 5E1",
    "sg:province":"AB",
    "sg:tags":[
        "government"
    ],
    "wof:name":"Fort Calgary Historic Park",
    "wof:placetype":"venue"
},
  "geometry": {"coordinates":[-114.045860291,51.0440444946],"type":"Point"}
}