{
  "type": "Feature",
  "properties": {
    "addr:full":"35 Railway Ave Brunkild MB R0G 0E0",
    "addr:housenumber":"35",
    "addr:postcode":"r0g 0e0",
    "addr:street":"Railway Ave",
    "iso:country":"CA",
    "sg:address":"35 Railway Ave",
    "sg:city":"Brunkild",
    "sg:classifiers":[
        {
            "category":"Travel",
            "subcategory":"Hotels & Motels",
            "type":"Entertainment"
        }
    ],
    "sg:phone":"+1 204 736 4705",
    "sg:postcode":"R0G 0E0",
    "sg:province":"MB",
    "wof:name":"Brunkild Bar & Grill",
    "wof:placetype":"venue"
},
  "geometry": {"coordinates":[-97.5743103027,49.5927886963],"type":"Point"}
}