{
  "type": "Feature",
  "properties": {
    "addr:full":"3980 Railway Ave # B Smithers BC V0J 2N0",
    "addr:housenumber":"3980",
    "addr:postcode":"v0j 2n0",
    "addr:street":"Railway Ave # B",
    "iso:country":"CA",
    "sg:address":"3980 Railway Ave # B",
    "sg:city":"Smithers",
    "sg:classifiers":[
        {
            "category":"Building & Trades",
            "subcategory":"Electrical",
            "type":"Services"
        }
    ],
    "sg:phone":"+1 250 847 3451",
    "sg:postcode":"V0J 2N0",
    "sg:province":"BC",
    "sg:tags":[
        "electric",
        "contractor"
    ],
    "wof:name":"Glacier Electric Ltd",
    "wof:placetype":"venue"
},
  "geometry": {"coordinates":[-127.17924499999999,54.780724],"type":"Point"}
}