{
  "type": "Feature",
  "properties": {
    "addr:full":"Toronto ON M5G 2K8",
    "addr:postcode":"m5g 2k8",
    "iso:country":"CA",
    "sg:city":"Toronto",
    "sg:classifiers":[
        {
            "category":"Health Services",
            "subcategory":"Doctor",
            "type":"Services"
        }
    ],
    "sg:phone":"+1 416 977 8877",
    "sg:postcode":"M5G 2K8",
    "sg:province":"ON",
    "sg:tags":[
        "dentist"
    ],
    "wof:name":"Downtown Dentistry",
    "wof:placetype":"venue"
},
  "geometry": {"coordinates":[-79.3884811401,43.6543617249],"type":"Point"}
}