{
  "type": "Feature",
  "properties": {
    "iso:country":"CA",
    "sg:city":"Seldom Come By",
    "sg:classifiers":[
        {
            "category":"Building & Trades",
            "subcategory":"Electrical",
            "type":"Services"
        }
    ],
    "sg:phone":"+1 709 627 3223",
    "sg:postcode":"A0G 3Z0",
    "sg:province":"NL",
    "sg:tags":[
        "electric",
        "contractor"
    ],
    "wof:name":"Lgr Electrical Inc",
    "wof:placetype":"venue"
},
  "geometry": {"coordinates":[-54.1720237732,49.6157455444],"type":"Point"}
}