{
  "type": "Feature",
  "properties": {
    "addr:full":"836 5th Ave W Owen Sound ON N4K 5A4",
    "addr:housenumber":"836",
    "addr:postcode":"n4k 5a4",
    "addr:street":"5Th Ave W",
    "iso:country":"CA",
    "sg:address":"836 5th Ave W",
    "sg:city":"Owen Sound",
    "sg:classifiers":[
        {
            "category":"Shopping",
            "subcategory":"Discount & Variety Stores",
            "type":"Retail Goods"
        }
    ],
    "sg:phone":"+1 519 371 6339",
    "sg:postcode":"N4K 5A4",
    "sg:province":"ON",
    "wof:name":"Westview Variety",
    "wof:placetype":"venue"
},
  "geometry": {"coordinates":[-80.950974,44.563622],"type":"Point"}
}