{
  "type": "Feature",
  "properties": {
    "addr:full":"Sooke BC V0S 1N0",
    "addr:postcode":"v0s 1n0",
    "iso:country":"CA",
    "sg:city":"Sooke",
    "sg:classifiers":[
        {
            "category":"Home & Garden",
            "subcategory":"Furniture",
            "type":"Retail Goods"
        }
    ],
    "sg:phone":"+1 250 642 2755",
    "sg:postcode":"V0S 1N0",
    "sg:province":"BC",
    "wof:name":"Country Craft Furniture",
    "wof:placetype":"venue"
},
  "geometry": {"coordinates":[-123.717781067,48.379283905],"type":"Point"}
}