{
  "type": "Feature",
  "properties": {
    "addr:full":"830 Grande Ligne Saint-Raymond QC G3L 2Z2",
    "addr:housenumber":"830",
    "addr:postcode":"g3l 2z2",
    "addr:street":"Grande Ligne",
    "iso:country":"CA",
    "sg:address":"830 Grande Ligne",
    "sg:city":"Saint-Raymond",
    "sg:classifiers":[
        {
            "category":"Recreation",
            "type":"Entertainment"
        }
    ],
    "sg:phone":"+1 418 337 2744",
    "sg:postcode":"G3L 2Z2",
    "sg:province":"QC",
    "sg:tags":[
        "campground",
        "swimming"
    ],
    "wof:name":"Piscine Claire Fontaine",
    "wof:placetype":"venue"
},
  "geometry": {"coordinates":[-71.776672,46.898209],"type":"Point"}
}