{
  "type": "Feature",
  "properties": {
    "addr:full":"101 Boul DE LA Marine Varennes QC J3X 1Y2",
    "addr:housenumber":"101",
    "addr:postcode":"j3x 1y2",
    "addr:street":"Boul De La Marine",
    "iso:country":"CA",
    "sg:address":"101 Boul DE LA Marine",
    "sg:city":"Varennes",
    "sg:classifiers":[
        {
            "category":"Social Services",
            "subcategory":"Child Care",
            "type":"Services"
        }
    ],
    "sg:phone":"+1 450 652 1923",
    "sg:postcode":"J3X 1Y2",
    "sg:province":"QC",
    "wof:name":"Garderie Educative Mimi-Pinson",
    "wof:placetype":"venue"
},
  "geometry": {"coordinates":[-73.43193817140001,45.6643333435],"type":"Point"}
}