{
  "type": "Feature",
  "properties": {
    "iso:country":"CA",
    "sg:address":"100 James St S",
    "sg:city":"Hamilton",
    "sg:classifiers":[
        {
            "category":"Health Services",
            "subcategory":"Health Practitioner",
            "type":"Services"
        }
    ],
    "sg:phone":"+1 905 528 5847",
    "sg:postcode":"L8P 2Z2",
    "sg:province":"ON",
    "sg:tags":[
        "physiotherapist"
    ],
    "wof:name":"Go Physiotherapy",
    "wof:placetype":"venue"
},
  "geometry": {"coordinates":[-79.8704833984,43.2540435791],"type":"Point"}
}