{
  "type": "Feature",
  "properties": {
    "addr:full":"1334 Main St North Vancouver BC V7J 1C3",
    "addr:housenumber":"1334",
    "addr:postcode":"v7j 1c3",
    "addr:street":"Main St",
    "iso:country":"CA",
    "sg:address":"1334 Main St",
    "sg:city":"North Vancouver",
    "sg:classifiers":[
        {
            "category":"Professional",
            "subcategory":"Management & Consulting",
            "type":"Services"
        }
    ],
    "sg:phone":"+1 604 983 3550",
    "sg:postcode":"V7J 1C3",
    "sg:province":"BC",
    "sg:tags":[
        "consultant",
        "product",
        "drafting"
    ],
    "wof:name":"Westcad Services Ltd",
    "wof:placetype":"venue"
},
  "geometry": {"coordinates":[-123.099876404,49.2730751038],"type":"Point"}
}