{
  "type": "Feature",
  "properties": {
    "addr:full":"20 Duncan St Welland ON L3B 2C6",
    "addr:housenumber":"20",
    "addr:postcode":"l3b 2c6",
    "addr:street":"Duncan St",
    "iso:country":"CA",
    "sg:address":"20 Duncan St",
    "sg:city":"Welland",
    "sg:classifiers":[
        {
            "category":"Education",
            "subcategory":"School",
            "type":"Public Place"
        }
    ],
    "sg:phone":"+1 905 735 5764",
    "sg:postcode":"L3B 2C6",
    "sg:province":"ON",
    "wof:name":"Empire Elementary School",
    "wof:placetype":"venue"
},
  "geometry": {"coordinates":[-79.237953,42.992725],"type":"Point"}
}