{
  "type": "Feature",
  "properties": {
    "iso:country":"CA",
    "sg:address":"175 Rue Ellen",
    "sg:city":"Salaberry-DE-Valleyfield",
    "sg:classifiers":[
        {
            "category":"Organizations",
            "subcategory":"Religious Organization",
            "type":"Services"
        }
    ],
    "sg:phone":"+1 514 373 7633",
    "sg:postcode":"J6S 3A8",
    "sg:province":"QC",
    "sg:tags":[
        "church"
    ],
    "wof:name":"Assemblee Chretienne St Timoth",
    "wof:placetype":"venue"
},
  "geometry": {"coordinates":[-74.144791,45.265762],"type":"Point"}
}