{
  "type": "Feature",
  "properties": {
    "addr:full":"2815 Highway Dr Trail BC V1R 2T1",
    "addr:housenumber":"2815",
    "addr:postcode":"bc v1r 2t1",
    "addr:street":"Highway Dr Trail",
    "iso:country":"CA",
    "sg:address":"2815 Highway Dr",
    "sg:city":"Trail",
    "sg:classifiers":[
        {
            "category":"Retail",
            "subcategory":"Auto Repair",
            "type":"Services"
        }
    ],
    "sg:phone":"+1 250 368 9151",
    "sg:postcode":"V1R 2T1",
    "sg:province":"BC",
    "sg:tags":[
        "repairing",
        "automobile"
    ],
    "wof:name":"Bella Tire Svc Ctr",
    "wof:placetype":"venue"
},
  "geometry": {"coordinates":[-117.682411,49.098087],"type":"Point"}
}