{
  "type": "Feature",
  "properties": {
    "addr:full":"65 Pacific Ave Moncton NB E1E 2G2",
    "addr:housenumber":"65",
    "addr:postcode":"e1e 2g2",
    "addr:street":"Pacific Ave",
    "iso:country":"CA",
    "sg:address":"65 Pacific Ave",
    "sg:city":"Moncton",
    "sg:classifiers":[
        {
            "category":"Retail",
            "subcategory":"Auto Repair",
            "type":"Services"
        }
    ],
    "sg:phone":"+1 506 853 0934",
    "sg:postcode":"E1E 2G2",
    "sg:province":"NB",
    "sg:tags":[
        "repairing",
        "automobile"
    ],
    "wof:name":"Robert K Buzzell Ltd",
    "wof:placetype":"venue"
},
  "geometry": {"coordinates":[-64.7984390259,46.088924408],"type":"Point"}
}