{
  "type": "Feature",
  "properties": {
    "addr:full":"119 Rue St-Joseph Gracefield QC J0X 1W0",
    "addr:housenumber":"119",
    "addr:postcode":"j0x 1w0",
    "addr:street":"Rue St-Joseph",
    "iso:country":"CA",
    "sg:address":"119 Rue St-Joseph",
    "sg:city":"Gracefield",
    "sg:classifiers":[
        {
            "category":"Social Services",
            "type":"Services"
        }
    ],
    "sg:phone":"+1 819 463 4030",
    "sg:postcode":"J0X 1W0",
    "sg:province":"QC",
    "sg:tags":[
        "youth",
        "organization",
        "center"
    ],
    "wof:name":"Maison Des Jeunes-Gracefield",
    "wof:placetype":"venue"
},
  "geometry": {"coordinates":[-76.0517730713,46.0958747864],"type":"Point"}
}