{
  "type": "Feature",
  "properties": {
    "addr:full":"165 Tanbark Rd St Davids ON L0S 1P0",
    "addr:housenumber":"165",
    "addr:postcode":"l0s 1p0",
    "addr:street":"Tanbark Rd St",
    "iso:country":"CA",
    "sg:address":"165 Tanbark Rd",
    "sg:city":"St Davids",
    "sg:classifiers":[
        {
            "category":"Wholesale",
            "subcategory":"Plants",
            "type":"Manufacturing & Wholesale Goods"
        }
    ],
    "sg:phone":"+1 905 262 4979",
    "sg:postcode":"L0S 1P0",
    "sg:province":"ON",
    "sg:tags":[
        "florist"
    ],
    "wof:name":"Scott St Greenhouses Ltd",
    "wof:placetype":"venue"
},
  "geometry": {"coordinates":[-79.10835299999999,43.154888],"type":"Point"}
}