{
  "type": "Feature",
  "properties": {
    "addr:full":"1537 9 Ave SE Calgary AB T2G 5N4",
    "addr:housenumber":"1537",
    "addr:postcode":"t2g 5n4",
    "addr:street":"9 Ave Se",
    "iso:country":"CA",
    "sg:address":"1537 9 Ave SE",
    "sg:city":"Calgary",
    "sg:classifiers":[
        {
            "category":"Building & Trades",
            "subcategory":"Construction",
            "type":"Services"
        }
    ],
    "sg:phone":"+1 403 253 8661",
    "sg:postcode":"T2G 5N4",
    "sg:province":"AB",
    "sg:tags":[
        "concrete",
        "contractor"
    ],
    "wof:name":"Renaissance Concrete Ltd",
    "wof:placetype":"venue"
},
  "geometry": {"coordinates":[-114.027046204,51.0382461548],"type":"Point"}
}