{
  "type": "Feature",
  "properties": {
    "addr:full":"St Albert AB T8N 1B4",
    "addr:postcode":"t8n 1b4",
    "iso:country":"CA",
    "sg:city":"St Albert",
    "sg:classifiers":[
        {
            "category":"Health Services",
            "subcategory":"Health Practitioner",
            "type":"Services"
        }
    ],
    "sg:phone":"+1 780 458 9383",
    "sg:postcode":"T8N 1B4",
    "sg:province":"AB",
    "sg:tags":[
        "psychologist"
    ],
    "wof:name":"Monson, Joan",
    "wof:placetype":"venue"
},
  "geometry": {"coordinates":[-113.628693,53.629749],"type":"Point"}
}