{
  "type": "Feature",
  "properties": {
    "iso:country":"CA",
    "sg:address":"456 Windmill Rd",
    "sg:city":"Dartmouth",
    "sg:classifiers":[
        {
            "category":"Travel",
            "subcategory":"Hotels & Motels",
            "type":"Entertainment"
        }
    ],
    "sg:phone":"+1 902 463 9900",
    "sg:postcode":"B3A 1J7",
    "sg:province":"NS",
    "wof:name":"Comfort Inn",
    "wof:placetype":"venue"
},
  "geometry": {"coordinates":[-63.598553,44.685734],"type":"Point"}
}