{
  "type": "Feature",
  "properties": {
    "iso:country":"CA",
    "sg:address":"3908 Boul Taschereau",
    "sg:city":"Greenfield Park",
    "sg:classifiers":[
        {
            "category":"Wholesale",
            "subcategory":"Apparel",
            "type":"Manufacturing & Wholesale Goods"
        }
    ],
    "sg:phone":"+1 450 465 9189",
    "sg:postcode":"J4V 2H9",
    "sg:province":"QC",
    "sg:tags":[
        "clothing"
    ],
    "wof:name":"Centre Du Manteau",
    "wof:placetype":"venue"
},
  "geometry": {"coordinates":[-73.468529,45.486012],"type":"Point"}
}