{
  "type": "Feature",
  "properties": {
    "addr:full":"Rimouski QC G5L 1A2",
    "addr:postcode":"g5l 1a2",
    "iso:country":"CA",
    "sg:city":"Rimouski",
    "sg:classifiers":[
        {
            "category":"Real Estate",
            "subcategory":"Surveying",
            "type":"Services"
        }
    ],
    "sg:phone":"+1 418 724 2414",
    "sg:postcode":"G5L 1A2",
    "sg:province":"QC",
    "sg:tags":[
        "surveyor"
    ],
    "wof:name":"Pelletier & Couillard",
    "wof:placetype":"venue"
},
  "geometry": {"coordinates":[-68.52720600000001,48.451683],"type":"Point"}
}