{
  "type": "Feature",
  "properties": {
    "addr:full":"Mississauga ON L4T 3W4",
    "addr:postcode":"l4t 3w4",
    "iso:country":"CA",
    "sg:city":"Mississauga",
    "sg:classifiers":[
        {
            "category":"Manufacturing",
            "subcategory":"Tools & Machinery",
            "type":"Manufacturing & Wholesale Goods"
        }
    ],
    "sg:phone":"+1 905 405 1057",
    "sg:postcode":"L4T 3W4",
    "sg:province":"ON",
    "sg:tags":[
        "filter"
    ],
    "wof:name":"Gkn Filters Ltd",
    "wof:placetype":"venue"
},
  "geometry": {"coordinates":[-79.6576766968,43.6981277466],"type":"Point"}
}