{
  "type": "Feature",
  "properties": {
    "addr:full":"Corner Brook NL A2H 4B5",
    "addr:postcode":"a2h 4b5",
    "iso:country":"CA",
    "sg:city":"Corner Brook",
    "sg:classifiers":[
        {
            "category":"Health Services",
            "subcategory":"Doctor",
            "type":"Services"
        }
    ],
    "sg:phone":"+1 709 639 9181",
    "sg:postcode":"A2H 4B5",
    "sg:province":"NL",
    "sg:tags":[
        "physician",
        "surgeon"
    ],
    "wof:name":"Graham, Jamie D MD",
    "wof:placetype":"venue"
},
  "geometry": {"coordinates":[-57.954945,48.951473],"type":"Point"}
}