{
  "type": "Feature",
  "properties": {
    "addr:full":"210 Main St Sussex NB E4E 1P9",
    "addr:housenumber":"210",
    "addr:postcode":"e4e 1p9",
    "addr:street":"Main St",
    "iso:country":"CA",
    "sg:address":"210 Main St",
    "sg:city":"Sussex",
    "sg:classifiers":[
        {
            "category":"Home & Garden",
            "subcategory":"Household Appliances",
            "type":"Retail Goods"
        }
    ],
    "sg:phone":"+1 506 433 1270",
    "sg:postcode":"E4E 1P9",
    "sg:province":"NB",
    "wof:name":"Sears Canada Inc",
    "wof:placetype":"venue"
},
  "geometry": {"coordinates":[-65.52478000000001,45.724533],"type":"Point"}
}