{
  "type": "Feature",
  "properties": {
    "iso:country":"CA",
    "sg:address":"3 Sutherland Ave",
    "sg:city":"Sudbury",
    "sg:classifiers":[
        {
            "category":"Wholesale",
            "subcategory":"Auto Parts",
            "type":"Manufacturing & Wholesale Goods"
        }
    ],
    "sg:phone":"+1 705 671 4455",
    "sg:postcode":"P3C 3A7",
    "sg:province":"ON",
    "sg:tags":[
        "automobile",
        "rebuilt",
        "electric"
    ],
    "wof:name":"Herold Supply",
    "wof:placetype":"venue"
},
  "geometry": {"coordinates":[-81.032143,46.471264],"type":"Point"}
}