{
  "type": "Feature",
  "properties": {
    "addr:full":"22339 48 Ave Langley BC V3A 3N4",
    "addr:housenumber":"22339",
    "addr:postcode":"v3a 3n4",
    "addr:street":"48 Ave",
    "iso:country":"CA",
    "sg:address":"22339 48 Ave",
    "sg:city":"Langley",
    "sg:classifiers":[
        {
            "category":"Retail",
            "subcategory":"Auto Repair",
            "type":"Services"
        }
    ],
    "sg:phone":"+1 604 533 9291",
    "sg:postcode":"V3A 3N4",
    "sg:province":"BC",
    "sg:tags":[
        "repairing",
        "automobile"
    ],
    "wof:name":"Fernridge Automotive",
    "wof:placetype":"venue"
},
  "geometry": {"coordinates":[-122.605003,49.089584],"type":"Point"}
}