{
  "type": "Feature",
  "properties": {
    "addr:full":"Winnipeg MB R2M 3L4",
    "addr:postcode":"r2m 3l4",
    "iso:country":"CA",
    "sg:city":"Winnipeg",
    "sg:classifiers":[
        {
            "category":"Health Services",
            "subcategory":"Doctor",
            "type":"Services"
        }
    ],
    "sg:phone":"+1 204 233 1615",
    "sg:postcode":"R2M 3L4",
    "sg:province":"MB",
    "sg:tags":[
        "physician",
        "surgeon"
    ],
    "wof:name":"Kerr, Lorraine MD",
    "wof:placetype":"venue"
},
  "geometry": {"coordinates":[-97.15321400000001,49.889393],"type":"Point"}
}