{
  "type": "Feature",
  "properties": {
    "addr:full":"16 Guelph St Georgetown ON L7G 3Z2",
    "addr:housenumber":"16",
    "addr:postcode":"l7g 3z2",
    "addr:street":"Guelph St",
    "iso:country":"CA",
    "sg:address":"16 Guelph St",
    "sg:city":"Georgetown",
    "sg:classifiers":[
        {
            "category":"Retail",
            "subcategory":"Animal Services",
            "type":"Services"
        }
    ],
    "sg:phone":"+1 905 702 9333",
    "sg:postcode":"L7G 3Z2",
    "sg:province":"ON",
    "sg:tags":[
        "pet",
        "grooming",
        "washing"
    ],
    "wof:name":"Beautiful Pets",
    "wof:placetype":"venue"
},
  "geometry": {"coordinates":[-79.92630800000001,43.651272],"type":"Point"}
}