{
  "type": "Feature",
  "properties": {
    "addr:full":"331 Ch DE LA Canardiere Quebec QC G1L 2V1",
    "addr:housenumber":"331",
    "addr:postcode":"g1l 2v1",
    "addr:street":"Ch De La Canardiere",
    "iso:country":"CA",
    "sg:address":"331 Ch DE LA Canardiere",
    "sg:city":"Quebec",
    "sg:classifiers":[
        {
            "category":"Personal",
            "subcategory":"Shoe Repair & Shine",
            "type":"Services"
        }
    ],
    "sg:phone":"+1 418 522 8768",
    "sg:postcode":"G1L 2V1",
    "sg:province":"QC",
    "sg:tags":[
        "repairing",
        "boot"
    ],
    "wof:name":"Cordonnerie M Vermette",
    "wof:placetype":"venue"
},
  "geometry": {"coordinates":[-71.227402,46.824547],"type":"Point"}
}