{
  "type": "Feature",
  "properties": {
    "addr:full":"Summerside PE C1N 4K5",
    "addr:postcode":"c1n 4k5",
    "iso:country":"CA",
    "sg:city":"Summerside",
    "sg:classifiers":[
        {
            "category":"Manufacturing",
            "subcategory":"Printing",
            "type":"Manufacturing & Wholesale Goods"
        }
    ],
    "sg:phone":"+1 902 436 2121",
    "sg:postcode":"C1N 4K5",
    "sg:province":"PE",
    "sg:tags":[
        "newspaper"
    ],
    "wof:name":"Journal Pioneer News",
    "wof:placetype":"venue"
},
  "geometry": {"coordinates":[-63.7930831909,46.391002655],"type":"Point"}
}