{
  "type": "Feature",
  "properties": {
    "addr:full":"25 5th Ave E Vancouver BC V5T 1G7",
    "addr:housenumber":"25",
    "addr:postcode":"v5t 1g7",
    "addr:street":"5Th Ave E",
    "iso:country":"CA",
    "sg:address":"25 5th Ave E",
    "sg:city":"Vancouver",
    "sg:classifiers":[
        {
            "category":"Professional",
            "subcategory":"Business Services",
            "type":"Services"
        }
    ],
    "sg:phone":"+1 604 873 3991",
    "sg:postcode":"V5T 1G7",
    "sg:province":"BC",
    "sg:tags":[
        "broker",
        "merchandise"
    ],
    "wof:name":"Seaboard Development Ltd",
    "wof:placetype":"venue"
},
  "geometry": {"coordinates":[-123.104187012,49.2666168213],"type":"Point"}
}