{
  "type": "Feature",
  "properties": {
    "iso:country":"CA",
    "sg:address":"1680 Kingston Rd",
    "sg:city":"Pickering",
    "sg:classifiers":[
        {
            "category":"Restaurant",
            "type":"Food & Drink"
        }
    ],
    "sg:phone":"+1 905 428 2200",
    "sg:postcode":"L1V 5R1",
    "sg:province":"ON",
    "wof:name":"Swiss Chalet Rotisserie/Grill",
    "wof:placetype":"venue"
},
  "geometry": {"coordinates":[-79.0752944946,43.8472328186],"type":"Point"}
}