{
  "type": "Feature",
  "properties": {
    "addr:full":"3711 Boul Laviolette Trois-Rivieres QC G8Y 1E8",
    "addr:housenumber":"3711",
    "addr:postcode":"g8y 1e8",
    "addr:street":"Boul Laviolette",
    "iso:country":"CA",
    "sg:address":"3711 Boul Laviolette",
    "sg:city":"Trois-Rivieres",
    "sg:classifiers":[
        {
            "category":"Health Services",
            "subcategory":"Nursing And Care Facility",
            "type":"Services"
        }
    ],
    "sg:phone":"+1 819 374 5941",
    "sg:postcode":"G8Y 1E8",
    "sg:province":"QC",
    "sg:tags":[
        "house",
        "retirement",
        "retreat",
        "community",
        "home"
    ],
    "wof:name":"Residence St-Pie X",
    "wof:placetype":"venue"
},
  "geometry": {"coordinates":[-72.572052,46.360977],"type":"Point"}
}