{
  "type": "Feature",
  "properties": {
    "addr:full":"80 Birmingham St Etobicoke ON M8V 3W6",
    "addr:housenumber":"80",
    "addr:postcode":"m8v 3w6",
    "addr:street":"Birmingham St",
    "iso:country":"CA",
    "sg:address":"80 Birmingham St",
    "sg:city":"Etobicoke",
    "sg:classifiers":[
        {
            "category":"Professional",
            "subcategory":"Engineering",
            "type":"Services"
        }
    ],
    "sg:phone":"+1 416 622 6470",
    "sg:postcode":"M8V 3W6",
    "sg:province":"ON",
    "sg:tags":[
        "engineer"
    ],
    "wof:name":"Vandesco & Assoc Ltd",
    "wof:placetype":"venue"
},
  "geometry": {"coordinates":[-79.504349,43.603802],"type":"Point"}
}