{
  "type": "Feature",
  "properties": {
    "addr:full":"16715 Yonge St Newmarket ON L3X 1X4",
    "addr:housenumber":"16715",
    "addr:postcode":"l3x 1x4",
    "addr:street":"Yonge St",
    "iso:country":"CA",
    "sg:address":"16715 Yonge St",
    "sg:city":"Newmarket",
    "sg:classifiers":[
        {
            "category":"Retail",
            "subcategory":"Laundry & Dry Cleaning",
            "type":"Services"
        }
    ],
    "sg:phone":"+1 905 895 7710",
    "sg:postcode":"L3X 1X4",
    "sg:province":"ON",
    "sg:tags":[
        "cleaners"
    ],
    "wof:name":"Dry Cleaners Plus",
    "wof:placetype":"venue"
},
  "geometry": {"coordinates":[-79.47556304930001,44.0349807739],"type":"Point"}
}