{
  "type": "Feature",
  "properties": {
    "addr:full":"151 Frobisher Dr #C109 Waterloo ON N2V 2C9",
    "addr:housenumber":"151",
    "addr:postcode":"n2v 2c9",
    "addr:street":"Frobisher Dr # C109",
    "iso:country":"CA",
    "sg:address":"151 Frobisher Dr #C109",
    "sg:city":"Waterloo",
    "sg:classifiers":[
        {
            "category":"Wholesale",
            "subcategory":"Non-durable Goods",
            "type":"Manufacturing & Wholesale Goods"
        }
    ],
    "sg:phone":"+1 519 885 6060",
    "sg:postcode":"N2V 2C9",
    "sg:province":"ON",
    "sg:tags":[
        "printer"
    ],
    "wof:name":"Ricoh Canada Inc",
    "wof:placetype":"venue"
},
  "geometry": {"coordinates":[-80.52690124510001,43.5064125061],"type":"Point"}
}