{
  "type": "Feature",
  "properties": {
    "iso:country":"CA",
    "sg:address":"29 33E Av",
    "sg:city":"Edmundston",
    "sg:classifiers":[
        {
            "category":"Building & Trades",
            "subcategory":"Plumbing",
            "type":"Services"
        }
    ],
    "sg:phone":"+1 506 735 6476",
    "sg:postcode":"E3V 2S3",
    "sg:province":"NB",
    "sg:tags":[
        "contractor"
    ],
    "wof:name":"Andre Bouchard Plomberie",
    "wof:placetype":"venue"
},
  "geometry": {"coordinates":[-68.3216171265,47.3692817688],"type":"Point"}
}