{
  "type": "Feature",
  "properties": {
    "addr:full":"5932 Thornton Rd NW Calgary AB T2K 3C2",
    "addr:housenumber":"5932",
    "addr:postcode":"t2k 3c2",
    "addr:street":"Thornton Rd Nw",
    "iso:country":"CA",
    "sg:address":"5932 Thornton Rd NW",
    "sg:city":"Calgary",
    "sg:classifiers":[
        {
            "category":"Professional",
            "subcategory":"Research",
            "type":"Services"
        }
    ],
    "sg:phone":"+1 403 274 0100",
    "sg:postcode":"T2K 3C2",
    "sg:province":"AB",
    "sg:tags":[
        "pressure",
        "testing"
    ],
    "wof:name":"Triple T Pressure Testing",
    "wof:placetype":"venue"
},
  "geometry": {"coordinates":[-114.06861114500001,51.1040802002],"type":"Point"}
}