{
  "type": "Feature",
  "properties": {
    "iso:country":"CA",
    "sg:address":"1218 Millcrest Rise SW",
    "sg:city":"Calgary",
    "sg:classifiers":[
        {
            "category":"Building & Trades",
            "subcategory":"Construction",
            "type":"Services"
        }
    ],
    "sg:phone":"+1 403 256 6617",
    "sg:postcode":"T2Y 2L9",
    "sg:province":"AB",
    "sg:tags":[
        "general",
        "contractor"
    ],
    "wof:name":"C M Interiors Ltd",
    "wof:placetype":"venue"
},
  "geometry": {"coordinates":[-114.09022521999999,50.917301178],"type":"Point"}
}