{
  "type": "Feature",
  "properties": {
    "addr:full":"13 High St Vankleek Hill ON K0B 1R0",
    "addr:housenumber":"13",
    "addr:postcode":"k0b 1r0",
    "addr:street":"High St",
    "iso:country":"CA",
    "sg:address":"13 High St",
    "sg:city":"Vankleek Hill",
    "sg:classifiers":[
        {
            "category":"Shopping",
            "subcategory":"Florist",
            "type":"Retail Goods"
        }
    ],
    "sg:phone":"+1 613 678 6008",
    "sg:postcode":"K0B 1R0",
    "sg:province":"ON",
    "wof:name":"Jardin Jade Garden",
    "wof:placetype":"venue"
},
  "geometry": {"coordinates":[-74.65220600000001,45.519268],"type":"Point"}
}