{
  "type": "Feature",
  "properties": {
    "addr:full":"264 Townsend St Sydney NS B1P 5E9",
    "addr:housenumber":"264",
    "addr:postcode":"b1p 5e9",
    "addr:street":"Townsend St",
    "iso:country":"CA",
    "sg:address":"264 Townsend St",
    "sg:city":"Sydney",
    "sg:classifiers":[
        {
            "category":"Restaurant",
            "type":"Food & Drink"
        }
    ],
    "sg:phone":"+1 902 567 1414",
    "sg:postcode":"B1P 5E9",
    "sg:province":"NS",
    "wof:name":"Kay's Kozy Korner Restaurant",
    "wof:placetype":"venue"
},
  "geometry": {"coordinates":[-60.186214447,46.1356201172],"type":"Point"}
}