{
  "type": "Feature",
  "properties": {
    "addr:full":"Everett ON L0M 1J0",
    "addr:postcode":"l0m 1j0",
    "iso:country":"CA",
    "sg:city":"Everett",
    "sg:classifiers":[
        {
            "category":"Shopping",
            "subcategory":"Discount & Variety Stores",
            "type":"Retail Goods"
        }
    ],
    "sg:phone":"+1 705 435 9616",
    "sg:postcode":"L0M 1J0",
    "sg:province":"ON",
    "wof:name":"Everett Variety",
    "wof:placetype":"venue"
},
  "geometry": {"coordinates":[-79.9388809204,44.1912345886],"type":"Point"}
}