{
  "type": "Feature",
  "properties": {
    "addr:full":"Calgary AB T2P 2R9",
    "addr:postcode":"t2p 2r9",
    "iso:country":"CA",
    "sg:city":"Calgary",
    "sg:classifiers":[
        {
            "category":"Restaurant",
            "type":"Food & Drink"
        }
    ],
    "sg:phone":"+1 403 266 1450",
    "sg:postcode":"T2P 2R9",
    "sg:province":"AB",
    "wof:name":"Counter Offer",
    "wof:placetype":"venue"
},
  "geometry": {"coordinates":[-114.065613,51.047634],"type":"Point"}
}