{
  "type": "Feature",
  "properties": {
    "addr:full":"250 Welton St Sydney NS B1P 5S2",
    "addr:housenumber":"250",
    "addr:postcode":"b1p 5s2",
    "addr:street":"Welton St",
    "iso:country":"CA",
    "sg:address":"250 Welton St",
    "sg:city":"Sydney",
    "sg:classifiers":[
        {
            "category":"Personal",
            "subcategory":"Beauty Salon",
            "type":"Services"
        }
    ],
    "sg:phone":"+1 902 564 0716",
    "sg:postcode":"B1P 5S2",
    "sg:province":"NS",
    "wof:name":"Cindy's Esthetics",
    "wof:placetype":"venue"
},
  "geometry": {"coordinates":[-60.166,46.143261],"type":"Point"}
}