{
  "type": "Feature",
  "properties": {
    "addr:full":"600 Clayson Rd North York ON M9M 2H2",
    "addr:housenumber":"600",
    "addr:postcode":"m9m 2h2",
    "addr:street":"Clayson Rd",
    "iso:country":"CA",
    "sg:address":"600 Clayson Rd",
    "sg:city":"North York",
    "sg:classifiers":[
        {
            "category":"Manufacturing",
            "subcategory":"Furniture",
            "type":"Manufacturing & Wholesale Goods"
        }
    ],
    "sg:phone":"+1 416 740 7773",
    "sg:postcode":"M9M 2H2",
    "sg:province":"ON",
    "wof:name":"Distinctive Designs Furniture",
    "wof:placetype":"venue"
},
  "geometry": {"coordinates":[-79.528809,43.728039],"type":"Point"}
}