{
  "type": "Feature",
  "properties": {
    "addr:full":"2001 Sheppard Ave E # 200 North York ON M2J 4Z8",
    "addr:housenumber":"2001",
    "addr:postcode":"m2j 4z8",
    "addr:street":"Sheppard Ave E # 200",
    "iso:country":"CA",
    "sg:address":"2001 Sheppard Ave E # 200",
    "sg:city":"North York",
    "sg:classifiers":[
        {
            "category":"Professional",
            "subcategory":"Computer Services",
            "type":"Services"
        }
    ],
    "sg:phone":"+1 416 495 0515",
    "sg:postcode":"M2J 4Z8",
    "sg:province":"ON",
    "sg:tags":[
        "equipment",
        "establishment",
        "dealer",
        "consultant"
    ],
    "wof:name":"Unisys Canada Inc",
    "wof:placetype":"venue"
},
  "geometry": {"coordinates":[-79.338989,43.775883],"type":"Point"}
}