{
  "type": "Feature",
  "properties": {
    "addr:full":"Richmond BC V6X 3M7",
    "addr:postcode":"v6x 3m7",
    "iso:country":"CA",
    "sg:city":"Richmond",
    "sg:classifiers":[
        {
            "category":"Retail",
            "subcategory":"Auto Repair",
            "type":"Services"
        }
    ],
    "sg:phone":"+1 604 273 6666",
    "sg:postcode":"V6X 3M7",
    "sg:province":"BC",
    "sg:tags":[
        "repairing",
        "automobile",
        "dealer"
    ],
    "wof:name":"Abs Auto Ltd",
    "wof:placetype":"venue"
},
  "geometry": {"coordinates":[-123.12487,49.178577],"type":"Point"}
}