{
  "type": "Feature",
  "properties": {
    "iso:country":"CA",
    "sg:address":"339 Westminster Ave",
    "sg:city":"London",
    "sg:classifiers":[
        {
            "category":"Health Services",
            "subcategory":"Health Practitioner",
            "type":"Services"
        }
    ],
    "sg:phone":"+1 519 439 0103",
    "sg:postcode":"N6C 4V3",
    "sg:province":"ON",
    "sg:tags":[
        "physiotherapist"
    ],
    "wof:name":"Cbi Physiotherapy",
    "wof:placetype":"venue"
},
  "geometry": {"coordinates":[-81.2250137329,42.9636154175],"type":"Point"}
}