{
  "type": "Feature",
  "properties": {
    "iso:country":"CA",
    "sg:address":"9543 Hwy 8",
    "sg:city":"Annapolis Royal",
    "sg:classifiers":[
        {
            "category":"Food & Beverages",
            "subcategory":"Groceries & Convenience Stores",
            "type":"Retail Goods"
        }
    ],
    "sg:phone":"+1 902 532 5362",
    "sg:postcode":"B0S 1A0",
    "sg:province":"NS",
    "sg:tags":[
        "grocer"
    ],
    "wof:name":"Lequille Country Store",
    "wof:placetype":"venue"
},
  "geometry": {"coordinates":[-65.50635528559999,44.7396392822],"type":"Point"}
}