{
  "type": "Feature",
  "properties": {
    "addr:full":"1490 Bank St Ottawa ON K1H 7Z2",
    "addr:housenumber":"1490",
    "addr:postcode":"k1h 7z2",
    "addr:street":"Bank St",
    "iso:country":"CA",
    "sg:address":"1490 Bank St",
    "sg:city":"Ottawa",
    "sg:classifiers":[
        {
            "category":"Cinema",
            "subcategory":"Movie Rental",
            "type":"Entertainment"
        }
    ],
    "sg:phone":"+1 613 737 3718",
    "sg:postcode":"K1H 7Z2",
    "sg:province":"ON",
    "sg:tags":[
        "leasing",
        "video",
        "disc",
        "tape"
    ],
    "wof:name":"Blockbuster Video",
    "wof:placetype":"venue"
},
  "geometry": {"coordinates":[-75.6707000732,45.3822441101],"type":"Point"}
}