{
  "type": "Feature",
  "properties": {
    "addr:full":"215 Dalhousie St Ottawa ON K1N 7C9",
    "addr:housenumber":"215",
    "addr:postcode":"k1n 7c9",
    "addr:street":"Dalhousie St",
    "iso:country":"CA",
    "sg:address":"215 Dalhousie St",
    "sg:city":"Ottawa",
    "sg:classifiers":[
        {
            "category":"Personal",
            "type":"Services"
        }
    ],
    "sg:phone":"+1 613 789 7875",
    "sg:postcode":"K1N 7C9",
    "sg:province":"ON",
    "sg:tags":[
        "electrolysis"
    ],
    "wof:name":"Gina's School of Aesthetics",
    "wof:placetype":"venue"
},
  "geometry": {"coordinates":[-75.693459,45.43174],"type":"Point"}
}