{
  "type": "Feature",
  "properties": {
    "addr:full":"1000 Gerrard St E # D6 Toronto ON M4M 3G6",
    "addr:housenumber":"1000",
    "addr:postcode":"m4m 3g6",
    "addr:street":"Gerrard St E # D6",
    "iso:country":"CA",
    "sg:address":"1000 Gerrard St E # D6",
    "sg:city":"Toronto",
    "sg:classifiers":[
        {
            "category":"Food & Beverages",
            "subcategory":"Specialty",
            "type":"Retail Goods"
        }
    ],
    "sg:phone":"+1 416 406 3999",
    "sg:postcode":"M4M 3G6",
    "sg:province":"ON",
    "sg:tags":[
        "health",
        "diet"
    ],
    "wof:name":"Nature's Health Food",
    "wof:placetype":"venue"
},
  "geometry": {"coordinates":[-79.338463,43.668732],"type":"Point"}
}