{
  "type": "Feature",
  "properties": {
    "addr:full":"367 Ridge Rd N Ridgeway ON L0S 1N0",
    "addr:housenumber":"367",
    "addr:postcode":"l0s 1n0",
    "addr:street":"Ridge Rd N",
    "iso:country":"CA",
    "sg:address":"367 Ridge Rd N",
    "sg:city":"Ridgeway",
    "sg:classifiers":[
        {
            "category":"Travel",
            "subcategory":"Travel Agent",
            "type":"Entertainment"
        }
    ],
    "sg:phone":"+1 905 894 5995",
    "sg:postcode":"L0S 1N0",
    "sg:province":"ON",
    "sg:tags":[
        "agency",
        "bureau"
    ],
    "wof:name":"Pbb Travel Svc",
    "wof:placetype":"venue"
},
  "geometry": {"coordinates":[-79.052193,42.884739],"type":"Point"}
}