{
  "type": "Feature",
  "properties": {
    "addr:full":"10699 Salisbury Dr Surrey BC V4N 1N1",
    "addr:housenumber":"10699",
    "addr:postcode":"v4n 1n1",
    "addr:street":"Salisbury Dr",
    "iso:country":"CA",
    "sg:address":"10699 Salisbury Dr",
    "sg:city":"Surrey",
    "sg:classifiers":[
        {
            "category":"Professional",
            "subcategory":"Testing Lab",
            "type":"Services"
        }
    ],
    "sg:phone":"+1 604 583 7325",
    "sg:postcode":"V4N 1N1",
    "sg:province":"BC",
    "sg:tags":[
        "laboratory"
    ],
    "wof:name":"Rebl Refractories Evaluate",
    "wof:placetype":"venue"
},
  "geometry": {"coordinates":[-122.751029968,49.1957893372],"type":"Point"}
}