{
  "type": "Feature",
  "properties": {
    "addr:full":"1030 Rue Notre-Dame Saint-Remi QC J0L 2L0",
    "addr:housenumber":"1030",
    "addr:postcode":"j0l 2l0",
    "addr:street":"Rue Notre-Dame Saint-Remi",
    "iso:country":"CA",
    "sg:address":"1030 Rue Notre-Dame",
    "sg:city":"Saint-Remi",
    "sg:classifiers":[
        {
            "category":"Organizations",
            "subcategory":"Professional Association",
            "type":"Services"
        }
    ],
    "sg:phone":"+1 450 454 6567",
    "sg:postcode":"J0L 2L0",
    "sg:province":"QC",
    "wof:name":"Service D'Action Benevole",
    "wof:placetype":"venue"
},
  "geometry": {"coordinates":[-73.6224060059,45.2582855225],"type":"Point"}
}