{
  "type": "Feature",
  "properties": {
    "iso:country":"CA",
    "sg:city":"Wetaskiwin",
    "sg:classifiers":[
        {
            "category":"Health Services",
            "subcategory":"Clinic",
            "type":"Services"
        }
    ],
    "sg:phone":"+1 780 361 0233",
    "sg:postcode":"T9A 0S7",
    "sg:province":"AB",
    "sg:tags":[
        "equipment",
        "therapy",
        "oxygen"
    ],
    "wof:name":"Cairco Respiratory Svc",
    "wof:placetype":"venue"
},
  "geometry": {"coordinates":[-113.37892150899999,52.9699211121],"type":"Point"}
}