{
  "type": "Feature",
  "properties": {
    "addr:full":"2325 Boul Des Recollets Trois-Rivieres QC G8Z 3X6",
    "addr:housenumber":"2325",
    "addr:postcode":"g8z 3x6",
    "addr:street":"Boul Des Recollets Trois-Rivieres",
    "iso:country":"CA",
    "sg:address":"2325 Boul Des Recollets",
    "sg:city":"Trois-Rivieres",
    "sg:classifiers":[
        {
            "category":"Shopping",
            "subcategory":"Department Store",
            "type":"Retail Goods"
        }
    ],
    "sg:phone":"+1 819 374 4625",
    "sg:postcode":"G8Z 3X6",
    "sg:province":"QC",
    "wof:name":"Korvette Les Magasins Ltee",
    "wof:placetype":"venue"
},
  "geometry": {"coordinates":[-72.580101,46.338734],"type":"Point"}
}