{
  "type": "Feature",
  "properties": {
    "addr:full":"2925 Boul Industriel Laval QC H7L 3W9",
    "addr:housenumber":"2925",
    "addr:postcode":"h7l 3w9",
    "addr:street":"Boul Industriel",
    "iso:country":"CA",
    "sg:address":"2925 Boul Industriel",
    "sg:city":"Laval",
    "sg:classifiers":[
        {
            "category":"Wholesale",
            "subcategory":"Drugs",
            "type":"Manufacturing & Wholesale Goods"
        }
    ],
    "sg:phone":"+1 450 668 9750",
    "sg:postcode":"H7L 3W9",
    "sg:province":"QC",
    "sg:tags":[
        "pharmaceutical",
        "product"
    ],
    "wof:name":"Laboratoires Pro Doc Ltee",
    "wof:placetype":"venue"
},
  "geometry": {"coordinates":[-73.739906311,45.5885925293],"type":"Point"}
}