{
  "type": "Feature",
  "properties": {
    "iso:country":"CA",
    "sg:address":"1101 Arthur St W",
    "sg:city":"Thunder Bay",
    "sg:classifiers":[
        {
            "category":"Food & Beverages",
            "subcategory":"Groceries & Convenience Stores",
            "type":"Retail Goods"
        }
    ],
    "sg:phone":"+1 807 577 3910",
    "sg:postcode":"P7E 5S2",
    "sg:province":"ON",
    "sg:tags":[
        "grocer"
    ],
    "wof:name":"A & P Food Stores Ltd",
    "wof:placetype":"venue"
},
  "geometry": {"coordinates":[-89.30609893800001,48.3809776306],"type":"Point"}
}