{
  "type": "Feature",
  "properties": {
    "addr:full":"786 Dufferin Ave Wallaceburg ON N8A 2V3",
    "addr:housenumber":"786",
    "addr:postcode":"n8a 2v3",
    "addr:street":"Dufferin Ave",
    "iso:country":"CA",
    "sg:address":"786 Dufferin Ave",
    "sg:city":"Wallaceburg",
    "sg:classifiers":[
        {
            "category":"Government",
            "subcategory":"Office",
            "type":"Public Place"
        }
    ],
    "sg:phone":"+1 519 627 1603",
    "sg:postcode":"N8A 2V3",
    "sg:province":"ON",
    "sg:tags":[
        "village"
    ],
    "wof:name":"Wallaceburg Municipal Offices",
    "wof:placetype":"venue"
},
  "geometry": {"coordinates":[-82.389687,42.592957],"type":"Point"}
}