{
  "type": "Feature",
  "properties": {
    "addr:full":"328 Fischer Ave The Pas MB R9A 1K4",
    "addr:housenumber":"328",
    "addr:postcode":"r9a 1k4",
    "addr:street":"Fischer Ave",
    "iso:country":"CA",
    "sg:address":"328 Fischer Ave",
    "sg:city":"The Pas",
    "sg:classifiers":[
        {
            "category":"Shopping",
            "subcategory":"Pharmacy",
            "type":"Retail Goods"
        }
    ],
    "sg:phone":"+1 204 623 5331",
    "sg:postcode":"R9A 1K4",
    "sg:province":"MB",
    "wof:name":"Nordic Pharmacy",
    "wof:placetype":"venue"
},
  "geometry": {"coordinates":[-101.2526474,53.8233184814],"type":"Point"}
}