{
  "type": "Feature",
  "properties": {
    "iso:country":"CA",
    "sg:address":"259 Loop 4",
    "sg:city":"Truro",
    "sg:classifiers":[
        {
            "category":"Food & Beverages",
            "subcategory":"Bakery",
            "type":"Retail Goods"
        }
    ],
    "sg:phone":"+1 902 895 8290",
    "sg:postcode":"B2N 5B1",
    "sg:province":"NS",
    "sg:tags":[
        "baker"
    ],
    "wof:name":"Scott's Bakery & Variety",
    "wof:placetype":"venue"
},
  "geometry": {"coordinates":[-63.2890396118,45.3660202026],"type":"Point"}
}