{
  "type": "Feature",
  "properties": {
    "addr:full":"80 Rue Morin Sainte-Adele QC J8B 2P7",
    "addr:housenumber":"80",
    "addr:postcode":"j8b 2p7",
    "addr:street":"Rue Morin",
    "iso:country":"CA",
    "sg:address":"80 Rue Morin",
    "sg:city":"Sainte-Adele",
    "sg:classifiers":[
        {
            "category":"Shopping",
            "type":"Retail Goods"
        }
    ],
    "sg:phone":"+1 514 229 4341",
    "sg:postcode":"J8B 2P7",
    "sg:province":"QC",
    "sg:tags":[
        "art",
        "gallery",
        "dealer"
    ],
    "wof:name":"Galerie D'Art Richard Harvey",
    "wof:placetype":"venue"
},
  "geometry": {"coordinates":[-74.136955,45.950893],"type":"Point"}
}