{
  "type": "Feature",
  "properties": {
    "iso:country":"CA",
    "sg:city":"Huntsville",
    "sg:classifiers":[
        {
            "category":"Personal",
            "type":"Services"
        }
    ],
    "sg:phone":"+1 705 788 1480",
    "sg:postcode":"P1H 1K6",
    "sg:province":"ON",
    "sg:tags":[
        "therapist",
        "massage"
    ],
    "wof:name":"Pro Active Rehab & Sport Injry",
    "wof:placetype":"venue"
},
  "geometry": {"coordinates":[-79.2134475708,45.3281593323],"type":"Point"}
}