{
  "type": "Feature",
  "properties": {
    "addr:full":"246 Rue Saint-Pierre Matane QC G4W 2B5",
    "addr:housenumber":"246",
    "addr:postcode":"g4w 2b5",
    "addr:street":"Rue Saint-Pierre",
    "iso:country":"CA",
    "sg:address":"246 Rue Saint-Pierre",
    "sg:city":"Matane",
    "sg:classifiers":[
        {
            "category":"Home & Garden",
            "subcategory":"Household Appliances",
            "type":"Retail Goods"
        }
    ],
    "sg:phone":"+1 418 562 3987",
    "sg:postcode":"G4W 2B5",
    "sg:province":"QC",
    "wof:name":"Matane Service DE Pieces Enr",
    "wof:placetype":"venue"
},
  "geometry": {"coordinates":[-67.53454600000001,48.845894],"type":"Point"}
}