{
  "type": "Feature",
  "properties": {
    "iso:country":"CA",
    "sg:address":"3547 Skaha Lake Rd",
    "sg:city":"Penticton",
    "sg:classifiers":[
        {
            "category":"Government",
            "subcategory":"Office",
            "type":"Public Place"
        }
    ],
    "sg:phone":"+1 250 490 8200",
    "sg:postcode":"V2A 7K2",
    "sg:province":"BC",
    "wof:name":"BC Conservation",
    "wof:placetype":"venue"
},
  "geometry": {"coordinates":[-119.587387085,49.4559822083],"type":"Point"}
}