{
  "type": "Feature",
  "properties": {
    "addr:full":"1059 Selkirk Ave Winnipeg MB R2X 0C2",
    "addr:housenumber":"1059",
    "addr:postcode":"r2x 0c2",
    "addr:street":"Selkirk Ave",
    "iso:country":"CA",
    "sg:address":"1059 Selkirk Ave",
    "sg:city":"Winnipeg",
    "sg:classifiers":[
        {
            "category":"Building & Trades",
            "subcategory":"Equipment Rental",
            "type":"Services"
        }
    ],
    "sg:phone":"+1 204 586 6238",
    "sg:postcode":"R2X 0C2",
    "sg:province":"MB",
    "sg:tags":[
        "yard"
    ],
    "wof:name":"Coin-Trol Wash",
    "wof:placetype":"venue"
},
  "geometry": {"coordinates":[-97.16673299999999,49.922783],"type":"Point"}
}