{
  "type": "Feature",
  "properties": {
    "addr:full":"5405 129 Ave NW Edmonton AB T5A 0A3",
    "addr:housenumber":"5405",
    "addr:postcode":"t5a 0a3",
    "addr:street":"129 Ave Nw",
    "iso:country":"CA",
    "sg:address":"5405 129 Ave NW",
    "sg:city":"Edmonton",
    "sg:classifiers":[
        {
            "category":"Building & Trades",
            "subcategory":"Construction",
            "type":"Services"
        }
    ],
    "sg:phone":"+1 780 475 6835",
    "sg:postcode":"T5A 0A3",
    "sg:province":"AB",
    "sg:tags":[
        "sewer",
        "contractor"
    ],
    "wof:name":"Nikiforuk Construction Ltd",
    "wof:placetype":"venue"
},
  "geometry": {"coordinates":[-113.424728,53.587505],"type":"Point"}
}