{
  "type": "Feature",
  "properties": {
    "addr:full":"32 Jasper St Jasper ON K0G 1G0",
    "addr:housenumber":"32",
    "addr:postcode":"k0g 1g0",
    "addr:street":"Jasper St",
    "iso:country":"CA",
    "sg:address":"32 Jasper St",
    "sg:city":"Jasper",
    "sg:classifiers":[
        {
            "category":"Shopping",
            "subcategory":"Bicycles & Sporting Goods",
            "type":"Retail Goods"
        }
    ],
    "sg:phone":"+1 613 283 8738",
    "sg:postcode":"K0G 1G0",
    "sg:province":"ON",
    "sg:tags":[
        "recreation",
        "center"
    ],
    "wof:name":"Jasper Fitness Ctr",
    "wof:placetype":"venue"
},
  "geometry": {"coordinates":[-75.9413604736,44.8259162903],"type":"Point"}
}