{
  "type": "Feature",
  "properties": {
    "addr:full":"323 Evans Ave Etobicoke ON M8Z 1K2",
    "addr:housenumber":"323",
    "addr:postcode":"m8z 1k2",
    "addr:street":"Evans Ave",
    "iso:country":"CA",
    "sg:address":"323 Evans Ave",
    "sg:city":"Etobicoke",
    "sg:classifiers":[
        {
            "category":"Freight",
            "type":"Transportation"
        }
    ],
    "sg:phone":"+1 416 251 2100",
    "sg:postcode":"M8Z 1K2",
    "sg:province":"ON",
    "sg:tags":[
        "trucking"
    ],
    "wof:name":"Longbow Freight Systems",
    "wof:placetype":"venue"
},
  "geometry": {"coordinates":[-79.5210723877,43.6163444519],"type":"Point"}
}