{
  "type": "Feature",
  "properties": {
    "addr:full":"Calgary AB T2C 2C5",
    "addr:postcode":"t2c 2c5",
    "iso:country":"CA",
    "sg:city":"Calgary",
    "sg:classifiers":[
        {
            "category":"Food & Beverages",
            "subcategory":"Groceries & Convenience Stores",
            "type":"Retail Goods"
        }
    ],
    "sg:phone":"+1 403 279 1711",
    "sg:postcode":"T2C 2C5",
    "sg:province":"AB",
    "sg:tags":[
        "grocer"
    ],
    "wof:name":"Rick's Grocery",
    "wof:placetype":"venue"
},
  "geometry": {"coordinates":[-114.0206604,50.9976196289],"type":"Point"}
}