{
  "type": "Feature",
  "properties": {
    "addr:full":"1 Nelson Hollow Dr Doaktown NB E9C 1X7",
    "addr:housenumber":"1",
    "addr:postcode":"e9c 1x7",
    "addr:street":"Nelson Hollow Dr",
    "iso:country":"CA",
    "sg:address":"1 Nelson Hollow Dr",
    "sg:city":"Doaktown",
    "sg:classifiers":[
        {
            "category":"Wholesale",
            "subcategory":"Scrap",
            "type":"Manufacturing & Wholesale Goods"
        }
    ],
    "sg:phone":"+1 506 365 7326",
    "sg:postcode":"E9C 1X7",
    "sg:province":"NB",
    "sg:tags":[
        "recycling",
        "can",
        "bottle",
        "depot"
    ],
    "wof:name":"Porters Bottle Exchange",
    "wof:placetype":"venue"
},
  "geometry": {"coordinates":[-66.17478199999999,46.542976],"type":"Point"}
}