{
  "type": "Feature",
  "properties": {
    "addr:full":"11 Rue DE LA Nicolet Victoriaville QC G6P 7H2",
    "addr:housenumber":"11",
    "addr:postcode":"g6p 7h2",
    "addr:street":"Rue De La Nicolet",
    "iso:country":"CA",
    "sg:address":"11 Rue DE LA Nicolet",
    "sg:city":"Victoriaville",
    "sg:classifiers":[
        {
            "category":"Home & Garden",
            "subcategory":"Furniture",
            "type":"Retail Goods"
        }
    ],
    "sg:phone":"+1 819 758 1594",
    "sg:postcode":"G6P 7H2",
    "sg:province":"QC",
    "sg:tags":[
        "equipment",
        "kitchen",
        "cabinet"
    ],
    "wof:name":"Cuisines Mrs Inc",
    "wof:placetype":"venue"
},
  "geometry": {"coordinates":[-71.9607391357,46.0695915222],"type":"Point"}
}