{
  "type": "Feature",
  "properties": {
    "iso:country":"CA",
    "sg:address":"2239 Prospect Rd",
    "sg:city":"Hatchet Lake",
    "sg:classifiers":[
        {
            "category":"Education",
            "subcategory":"School",
            "type":"Public Place"
        }
    ],
    "sg:phone":"+1 902 852 2062",
    "sg:postcode":"B3T 1R8",
    "sg:province":"NS",
    "wof:name":"Brookside Jr High School",
    "wof:placetype":"venue"
},
  "geometry": {"coordinates":[-63.7136192322,44.5680236816],"type":"Point"}
}