{
  "type": "Feature",
  "properties": {
    "addr:full":"2061 Lawrence Ave W York ON M9N 1H7",
    "addr:housenumber":"2061",
    "addr:postcode":"m9n 1h7",
    "addr:street":"Lawrence Ave W",
    "iso:country":"CA",
    "sg:address":"2061 Lawrence Ave W",
    "sg:city":"York",
    "sg:classifiers":[
        {
            "category":"Health Services",
            "subcategory":"Doctor",
            "type":"Services"
        }
    ],
    "sg:phone":"+1 416 249 7768",
    "sg:postcode":"M9N 1H7",
    "sg:province":"ON",
    "sg:tags":[
        "dentist"
    ],
    "wof:name":"Dumitru Jr, George S DDS",
    "wof:placetype":"venue"
},
  "geometry": {"coordinates":[-79.51660200000001,43.699913],"type":"Point"}
}