{
  "type": "Feature",
  "properties": {
    "addr:full":"422 Parliament St Toronto ON M5A 3A2",
    "addr:housenumber":"422",
    "addr:postcode":"m5a 3a2",
    "addr:street":"Parliament St",
    "iso:country":"CA",
    "sg:address":"422 Parliament St",
    "sg:city":"Toronto",
    "sg:classifiers":[
        {
            "category":"Shopping",
            "subcategory":"Catalog Store",
            "type":"Retail Goods"
        }
    ],
    "sg:phone":"+1 416 967 2720",
    "sg:postcode":"M5A 3A2",
    "sg:province":"ON",
    "sg:tags":[
        "mail",
        "order",
        "internet"
    ],
    "wof:name":"Sears Canada Inc",
    "wof:placetype":"venue"
},
  "geometry": {"coordinates":[-79.36748504640001,43.6626243591],"type":"Point"}
}