{
  "type": "Feature",
  "properties": {
    "addr:full":"60 Av Saint-Jacques Louiseville QC J5V 1C2",
    "addr:postcode":"j5v 1c2",
    "addr:street":"60 Av Saint-Jacques",
    "iso:country":"CA",
    "sg:address":"60 Av Saint-Jacques",
    "sg:city":"Louiseville",
    "sg:classifiers":[
        {
            "category":"Organizations",
            "subcategory":"Professional Association",
            "type":"Services"
        }
    ],
    "sg:phone":"+1 819 228 4889",
    "sg:postcode":"J5V 1C2",
    "sg:province":"QC",
    "wof:name":"Cadets Richelieu-Louiseville",
    "wof:placetype":"venue"
},
  "geometry": {"coordinates":[-72.940697,46.257664],"type":"Point"}
}