{
  "type": "Feature",
  "properties": {
    "iso:country":"CA",
    "sg:city":"St-Marcel-DE-L'Islet",
    "sg:classifiers":[
        {
            "category":"Building & Trades",
            "subcategory":"Construction",
            "type":"Services"
        }
    ],
    "sg:phone":"+1 418 356 5250",
    "sg:postcode":"G0R 3R0",
    "sg:province":"QC",
    "sg:tags":[
        "refinishing",
        "floor",
        "consultant",
        "laying",
        "resurfacing",
        "design",
        "interior",
        "decorator"
    ],
    "wof:name":"Prodecor Sv Inc",
    "wof:placetype":"venue"
},
  "geometry": {"coordinates":[-70.33153533940001,47.0898017883],"type":"Point"}
}