{
  "type": "Feature",
  "properties": {
    "addr:full":"52 Cote DE LA Fabrique Quebec QC G1R 3V7",
    "addr:housenumber":"52",
    "addr:postcode":"g1r 3v7",
    "addr:street":"Cote De La Fabrique",
    "iso:country":"CA",
    "sg:address":"52 Cote DE LA Fabrique",
    "sg:city":"Quebec",
    "sg:classifiers":[
        {
            "category":"Shopping",
            "subcategory":"Gifts & Souvenirs",
            "type":"Retail Goods"
        }
    ],
    "sg:phone":"+1 418 692 5312",
    "sg:postcode":"G1R 3V7",
    "sg:province":"QC",
    "sg:tags":[
        "shop"
    ],
    "wof:name":"Boutique Les Sentiers",
    "wof:placetype":"venue"
},
  "geometry": {"coordinates":[-71.207825,46.814445],"type":"Point"}
}