{
  "type": "Feature",
  "properties": {
    "addr:full":"80 Marine Dr Edwardsville NS B2A 4S6",
    "addr:housenumber":"80",
    "addr:postcode":"b2a 4s6",
    "addr:street":"Marine Dr",
    "iso:country":"CA",
    "sg:address":"80 Marine Dr",
    "sg:city":"Edwardsville",
    "sg:classifiers":[
        {
            "category":"Building & Trades",
            "subcategory":"Plumbing",
            "type":"Services"
        }
    ],
    "sg:phone":"+1 902 567 6100",
    "sg:postcode":"B2A 4S6",
    "sg:province":"NS",
    "sg:tags":[
        "refrigeration",
        "contractor"
    ],
    "wof:name":"J R Mahoney Contracting Ltd",
    "wof:placetype":"venue"
},
  "geometry": {"coordinates":[-60.221478,46.156784],"type":"Point"}
}