{
  "type": "Feature",
  "properties": {
    "addr:full":"75 Alma St Moncton NB E1C 4Y3",
    "addr:housenumber":"75",
    "addr:postcode":"e1c 4y3",
    "addr:street":"Alma St",
    "iso:country":"CA",
    "sg:address":"75 Alma St",
    "sg:city":"Moncton",
    "sg:classifiers":[
        {
            "category":"Organizations",
            "subcategory":"Religious Organization",
            "type":"Services"
        }
    ],
    "sg:phone":"+1 506 858 8289",
    "sg:postcode":"E1C 4Y3",
    "sg:province":"NB",
    "sg:tags":[
        "church"
    ],
    "wof:name":"St John's United Church",
    "wof:placetype":"venue"
},
  "geometry": {"coordinates":[-64.77752700000001,46.090595],"type":"Point"}
}