{
  "type": "Feature",
  "properties": {
    "addr:full":"154 Rue Saint-Charles Saint-Jean-Sur-Richelieu QC J3B 2C6",
    "addr:housenumber":"154",
    "addr:postcode":"j3b 2c6",
    "addr:street":"Rue Saint-Charles",
    "iso:country":"CA",
    "sg:address":"154 Rue Saint-Charles",
    "sg:city":"Saint-Jean-Sur-Richelieu",
    "sg:classifiers":[
        {
            "category":"Education",
            "subcategory":"School",
            "type":"Public Place"
        }
    ],
    "sg:phone":"+1 450 347 5113",
    "sg:postcode":"J3B 2C6",
    "sg:province":"QC",
    "wof:name":"Ecole Secondaire Marguerite",
    "wof:placetype":"venue"
},
  "geometry": {"coordinates":[-73.2564315796,45.3075141907],"type":"Point"}
}