{
  "type": "Feature",
  "properties": {
    "addr:full":"341 Johnson Rd Brantford ON N3T 5M1",
    "addr:housenumber":"341",
    "addr:postcode":"n3t 5m1",
    "addr:street":"Johnson Rd",
    "iso:country":"CA",
    "sg:address":"341 Johnson Rd",
    "sg:city":"Brantford",
    "sg:classifiers":[
        {
            "category":"Building & Trades",
            "subcategory":"Electrical",
            "type":"Services"
        }
    ],
    "sg:phone":"+1 519 753 7112",
    "sg:postcode":"N3T 5M1",
    "sg:province":"ON",
    "sg:tags":[
        "electric",
        "contractor"
    ],
    "wof:name":"Iec Group",
    "wof:placetype":"venue"
},
  "geometry": {"coordinates":[-80.200401,43.151711],"type":"Point"}
}