{
  "type": "Feature",
  "properties": {
    "addr:full":"733 Rue Saint-Jean Longueuil QC J4H 2Y8",
    "addr:housenumber":"733",
    "addr:postcode":"j4h 2y8",
    "addr:street":"Rue Saint-Jean",
    "iso:country":"CA",
    "sg:address":"733 Rue Saint-Jean",
    "sg:city":"Longueuil",
    "sg:classifiers":[
        {
            "category":"Education",
            "subcategory":"Dance Studio",
            "type":"Public Place"
        }
    ],
    "sg:phone":"+1 450 679 3620",
    "sg:postcode":"J4H 2Y8",
    "sg:province":"QC",
    "sg:tags":[
        "instruction",
        "dancing"
    ],
    "wof:name":"Mutins DE Longueuil",
    "wof:placetype":"venue"
},
  "geometry": {"coordinates":[-73.500488,45.533211],"type":"Point"}
}