{
  "type": "Feature",
  "properties": {
    "addr:full":"34505 89th St Oliver BC V0H 1T0",
    "addr:housenumber":"34505",
    "addr:postcode":"bc v0h 1t0",
    "addr:street":"89Th St",
    "iso:country":"CA",
    "sg:address":"34505 89th St",
    "sg:city":"Oliver",
    "sg:classifiers":[
        {
            "category":"Building & Trades",
            "subcategory":"Construction",
            "type":"Services"
        }
    ],
    "sg:phone":"+1 250 498 2250",
    "sg:postcode":"V0H 1T0",
    "sg:province":"BC",
    "sg:tags":[
        "fire",
        "restoration",
        "damage"
    ],
    "wof:name":"Sunrise Restorations",
    "wof:placetype":"venue"
},
  "geometry": {"coordinates":[-119.541984558,49.1757164001],"type":"Point"}
}