{
  "type": "Feature",
  "properties": {
    "iso:country":"CA",
    "sg:address":"1443 16 St NE",
    "sg:city":"Calgary",
    "sg:classifiers":[
        {
            "category":"Building & Trades",
            "subcategory":"Construction",
            "type":"Services"
        }
    ],
    "sg:phone":"+1 403 277 6090",
    "sg:postcode":"T2E 4S7",
    "sg:province":"AB",
    "sg:tags":[
        "carpenter"
    ],
    "wof:name":"Rds Construction",
    "wof:placetype":"venue"
},
  "geometry": {"coordinates":[-114.021507,51.064732],"type":"Point"}
}