{
  "type": "Feature",
  "properties": {
    "addr:full":"985 Rue Notre-Dame Lachine QC H8S 2C1",
    "addr:housenumber":"985",
    "addr:postcode":"h8s 2c1",
    "addr:street":"Rue Notre-Dame",
    "iso:country":"CA",
    "sg:address":"985 Rue Notre-Dame",
    "sg:city":"Lachine",
    "sg:classifiers":[
        {
            "category":"Recreation",
            "type":"Entertainment"
        }
    ],
    "sg:phone":"+1 514 637 5341",
    "sg:postcode":"H8S 2C1",
    "sg:province":"QC",
    "sg:tags":[
        "parlor",
        "billiard"
    ],
    "wof:name":"Billard Lachine",
    "wof:placetype":"venue"
},
  "geometry": {"coordinates":[-73.6724243164,45.434803009],"type":"Point"}
}