{
  "type": "Feature",
  "properties": {
    "addr:full":"1020 Av Des Erables Quebec QC G1R 2M9",
    "addr:housenumber":"1020",
    "addr:postcode":"g1r 2m9",
    "addr:street":"Av Des Erables",
    "iso:country":"CA",
    "sg:address":"1020 Av Des Erables",
    "sg:city":"Quebec",
    "sg:classifiers":[
        {
            "category":"Travel",
            "subcategory":"Travel Agent",
            "type":"Entertainment"
        }
    ],
    "sg:phone":"+1 418 684 0662",
    "sg:postcode":"G1R 2M9",
    "sg:province":"QC",
    "sg:tags":[
        "agency",
        "bureau"
    ],
    "wof:name":"Global Tourisme Intl Inc",
    "wof:placetype":"venue"
},
  "geometry": {"coordinates":[-71.229584,46.802185],"type":"Point"}
}