{
  "type": "Feature",
  "properties": {
    "addr:full":"Repentigny QC J6A 1L2",
    "addr:postcode":"j6a 1l2",
    "iso:country":"CA",
    "sg:city":"Repentigny",
    "sg:classifiers":[
        {
            "category":"Personal",
            "type":"Services"
        }
    ],
    "sg:phone":"+1 450 654 2100",
    "sg:postcode":"J6A 1L2",
    "sg:province":"QC",
    "sg:tags":[
        "therapist",
        "massage"
    ],
    "wof:name":"Massotherapie Genevieve",
    "wof:placetype":"venue"
},
  "geometry": {"coordinates":[-73.4685592651,45.7325439453],"type":"Point"}
}