{
  "type": "Feature",
  "properties": {
    "iso:country":"CA",
    "sg:city":"Scarborough",
    "sg:classifiers":[
        {
            "category":"Personal",
            "subcategory":"Beauty Salon",
            "type":"Services"
        }
    ],
    "sg:phone":"+1 416 298 2925",
    "sg:postcode":"M1V 5E6",
    "sg:province":"ON",
    "wof:name":"Top Stylist Salon",
    "wof:placetype":"venue"
},
  "geometry": {"coordinates":[-79.2890930176,43.8072967529],"type":"Point"}
}