{
  "type": "Feature",
  "properties": {
    "addr:full":"11160 River Valley Rd Edmonton AB T5J 2G7",
    "addr:housenumber":"11160",
    "addr:postcode":"t5j 2g7",
    "addr:street":"River Valley Rd",
    "iso:country":"CA",
    "sg:address":"11160 River Valley Rd",
    "sg:city":"Edmonton",
    "sg:classifiers":[
        {
            "category":"Organizations",
            "subcategory":"Community Association",
            "type":"Services"
        }
    ],
    "sg:phone":"+1 780 482 2371",
    "sg:postcode":"T5J 2G7",
    "sg:province":"AB",
    "sg:tags":[
        "club"
    ],
    "wof:name":"Royal Glenora Club",
    "wof:placetype":"venue"
},
  "geometry": {"coordinates":[-113.51432800000001,53.532166],"type":"Point"}
}