{
  "type": "Feature",
  "properties": {
    "addr:full":"7721 40 St NE Calgary AB T3J 4H2",
    "addr:housenumber":"7721",
    "addr:postcode":"t3j 4h2",
    "addr:street":"40 St Ne",
    "iso:country":"CA",
    "sg:address":"7721 40 St NE",
    "sg:city":"Calgary",
    "sg:classifiers":[
        {
            "category":"Wholesale",
            "subcategory":"Construction Materials",
            "type":"Manufacturing & Wholesale Goods"
        }
    ],
    "sg:phone":"+1 403 280 1166",
    "sg:postcode":"T3J 4H2",
    "sg:province":"AB",
    "sg:tags":[
        "concrete",
        "fence"
    ],
    "wof:name":"Yards Plus Outdoor Depot",
    "wof:placetype":"venue"
},
  "geometry": {"coordinates":[-113.976547,51.121632],"type":"Point"}
}