{
  "type": "Feature",
  "properties": {
    "addr:full":"129 Rowntree Dairy Rd # 14 Woodbridge ON L4L 6C9",
    "addr:housenumber":"129",
    "addr:postcode":"l4l 6c9",
    "addr:street":"Rowntree Dairy Rd # 14",
    "iso:country":"CA",
    "sg:address":"129 Rowntree Dairy Rd # 14",
    "sg:city":"Woodbridge",
    "sg:classifiers":[
        {
            "category":"Building & Trades",
            "subcategory":"Plumbing",
            "type":"Services"
        }
    ],
    "sg:phone":"+1 905 850 3761",
    "sg:postcode":"L4L 6C9",
    "sg:province":"ON",
    "sg:tags":[
        "heating",
        "contractor"
    ],
    "wof:name":"Gastech Hvac Systems",
    "wof:placetype":"venue"
},
  "geometry": {"coordinates":[-79.5523986816,43.7850990295],"type":"Point"}
}