{
  "type": "Feature",
  "properties": {
    "addr:full":"33 Madison Cres Saskatoon SK S7L 3V7",
    "addr:housenumber":"33",
    "addr:postcode":"s7l 3v7",
    "addr:street":"Madison Cres",
    "iso:country":"CA",
    "sg:address":"33 Madison Cres",
    "sg:city":"Saskatoon",
    "sg:classifiers":[
        {
            "category":"Building & Trades",
            "subcategory":"Construction",
            "type":"Services"
        }
    ],
    "sg:phone":"+1 306 955 2624",
    "sg:postcode":"S7L 3V7",
    "sg:province":"SK",
    "sg:tags":[
        "marking",
        "maintenance",
        "parking"
    ],
    "wof:name":"Northern Blacktop Ltd",
    "wof:placetype":"venue"
},
  "geometry": {"coordinates":[-106.71304321300001,52.1415519714],"type":"Point"}
}