{
  "type": "Feature",
  "properties": {
    "addr:full":"219 Notre Dame Belle River ON N0R 1A0",
    "addr:housenumber":"219",
    "addr:postcode":"n0r 1a0",
    "addr:street":"Notre Dame",
    "iso:country":"CA",
    "sg:address":"219 Notre Dame",
    "sg:city":"Belle River",
    "sg:classifiers":[
        {
            "category":"Wholesale",
            "subcategory":"Machinery & Supplies",
            "type":"Manufacturing & Wholesale Goods"
        }
    ],
    "sg:phone":"+1 519 728 4683",
    "sg:postcode":"N0R 1A0",
    "sg:province":"ON",
    "sg:tags":[
        "equipment",
        "industrial"
    ],
    "wof:name":"C H Henze CO Ltd Ind Supplies",
    "wof:placetype":"venue"
},
  "geometry": {"coordinates":[-82.692368,42.292725],"type":"Point"}
}