{
  "type": "Feature",
  "properties": {
    "addr:full":"11390 55E Av Montreal QC H1E 2K1",
    "addr:housenumber":"11390",
    "addr:postcode":"h1e 2k1",
    "addr:street":"55E Av",
    "iso:country":"CA",
    "sg:address":"11390 55E Av",
    "sg:city":"Montreal",
    "sg:classifiers":[
        {
            "category":"Building & Trades",
            "subcategory":"Construction",
            "type":"Services"
        }
    ],
    "sg:phone":"+1 514 494 4981",
    "sg:postcode":"H1E 2K1",
    "sg:province":"QC",
    "sg:tags":[
        "paving",
        "contractor"
    ],
    "wof:name":"Pavages Spinelli Enr",
    "wof:placetype":"venue"
},
  "geometry": {"coordinates":[-73.55815887449999,45.6427536011],"type":"Point"}
}