{
  "type": "Feature",
  "properties": {
    "addr:full":"7145 West Credit Ave Mississauga ON L5N 6J7",
    "addr:housenumber":"7145",
    "addr:postcode":"l5n 6j7",
    "addr:street":"West Credit Ave",
    "iso:country":"CA",
    "sg:address":"7145 West Credit Ave",
    "sg:city":"Mississauga",
    "sg:classifiers":[
        {
            "category":"Wholesale",
            "subcategory":"Groceries",
            "type":"Manufacturing & Wholesale Goods"
        }
    ],
    "sg:phone":"+1 905 567 1755",
    "sg:postcode":"L5N 6J7",
    "sg:province":"ON",
    "sg:tags":[
        "food",
        "broker"
    ],
    "wof:name":"Tri R Foods Intl Inc",
    "wof:placetype":"venue"
},
  "geometry": {"coordinates":[-79.7559967041,43.608707428],"type":"Point"}
}