{
  "type": "Feature",
  "properties": {
    "addr:full":"840 Main St Melville SK S0A 2P0",
    "addr:housenumber":"840",
    "addr:postcode":"s0a 2p0",
    "addr:street":"Main St",
    "iso:country":"CA",
    "sg:address":"840 Main St",
    "sg:city":"Melville",
    "sg:classifiers":[
        {
            "category":"Education",
            "subcategory":"School",
            "type":"Public Place"
        }
    ],
    "sg:phone":"+1 306 728 4758",
    "sg:postcode":"S0A 2P0",
    "sg:province":"SK",
    "wof:name":"St Henry's Junior School",
    "wof:placetype":"venue"
},
  "geometry": {"coordinates":[-102.80231475799999,50.9335250854],"type":"Point"}
}