{
  "type": "Feature",
  "properties": {
    "addr:full":"8607 Main St Alma NB E4H 1N6",
    "addr:housenumber":"8607",
    "addr:postcode":"e4h 1n6",
    "addr:street":"Main St",
    "iso:country":"CA",
    "sg:address":"8607 Main St",
    "sg:city":"Alma",
    "sg:classifiers":[
        {
            "category":"Wholesale",
            "subcategory":"Seafood",
            "type":"Manufacturing & Wholesale Goods"
        }
    ],
    "sg:phone":"+1 506 887 2190",
    "sg:postcode":"E4H 1N6",
    "sg:province":"NB",
    "wof:name":"Butland's Seafood",
    "wof:placetype":"venue"
},
  "geometry": {"coordinates":[-64.942848,45.602058],"type":"Point"}
}