{
  "type": "Feature",
  "properties": {
    "addr:full":"8064 Buscombe St Vancouver BC V5X 3S1",
    "addr:housenumber":"8064",
    "addr:postcode":"v5x 3s1",
    "addr:street":"Buscombe St",
    "iso:country":"CA",
    "sg:address":"8064 Buscombe St",
    "sg:city":"Vancouver",
    "sg:classifiers":[
        {
            "category":"Social Services",
            "subcategory":"Child Care",
            "type":"Services"
        }
    ],
    "sg:phone":"+1 604 325 3817",
    "sg:postcode":"V5X 3S1",
    "sg:province":"BC",
    "wof:name":"Sunset Area Day Care Ctr",
    "wof:placetype":"venue"
},
  "geometry": {"coordinates":[-123.09504699999999,49.211731],"type":"Point"}
}