{
  "type": "Feature",
  "properties": {
    "addr:full":"330 University Park Dr Regina SK S4V 0Y8",
    "addr:housenumber":"330",
    "addr:postcode":"s4v 0y8",
    "addr:street":"University Park Dr",
    "iso:country":"CA",
    "sg:address":"330 University Park Dr",
    "sg:city":"Regina",
    "sg:classifiers":[
        {
            "category":"Health Services",
            "subcategory":"Health Practitioner",
            "type":"Services"
        }
    ],
    "sg:phone":"+1 306 789 2484",
    "sg:postcode":"S4V 0Y8",
    "sg:province":"SK",
    "sg:tags":[
        "therapist",
        "physical"
    ],
    "wof:name":"Arcola Physiotherapy-Acpnctr",
    "wof:placetype":"venue"
},
  "geometry": {"coordinates":[-104.555305,50.43441],"type":"Point"}
}