{
  "type": "Feature",
  "properties": {
    "addr:full":"252 132 Rte E Val-Brillant QC G0J 3L0",
    "addr:housenumber":"132",
    "addr:postcode":"g0j 3l0",
    "addr:street":"Rte E Val-Brillant",
    "iso:country":"CA",
    "sg:address":"252 132 Rte E",
    "sg:city":"Val-Brillant",
    "sg:classifiers":[
        {
            "category":"Freight",
            "type":"Transportation"
        }
    ],
    "sg:phone":"+1 418 742 3656",
    "sg:postcode":"G0J 3L0",
    "sg:province":"QC",
    "sg:tags":[
        "repairing",
        "automobile",
        "trucking"
    ],
    "wof:name":"Transport Mario Asselin",
    "wof:placetype":"venue"
},
  "geometry": {"coordinates":[-67.54908,48.531906],"type":"Point"}
}