{
  "type": "Feature",
  "properties": {
    "addr:full":"Fenelon Falls ON K0M 1N0",
    "addr:postcode":"k0m 1n0",
    "iso:country":"CA",
    "sg:city":"Fenelon Falls",
    "sg:classifiers":[
        {
            "category":"Building & Trades",
            "subcategory":"Construction",
            "type":"Services"
        }
    ],
    "sg:phone":"+1 705 887 3331",
    "sg:postcode":"K0M 1N0",
    "sg:province":"ON",
    "sg:tags":[
        "water",
        "well",
        "drilling"
    ],
    "wof:name":"G Hart & Sons Well Drilling",
    "wof:placetype":"venue"
},
  "geometry": {"coordinates":[-78.73584747309999,44.5375785828],"type":"Point"}
}