{
  "type": "Feature",
  "properties": {
    "addr:full":"151 Bentley St # 7 Markham ON L3R 3X9",
    "addr:housenumber":"151",
    "addr:postcode":"l3r 3x9",
    "addr:street":"Bentley St # 7",
    "iso:country":"CA",
    "sg:address":"151 Bentley St # 7",
    "sg:city":"Markham",
    "sg:classifiers":[
        {
            "category":"Retail",
            "subcategory":"Repair Shop",
            "type":"Services"
        }
    ],
    "sg:phone":"+1 905 475 1499",
    "sg:postcode":"L3R 3X9",
    "sg:province":"ON",
    "sg:tags":[
        "equipment"
    ],
    "wof:name":"Action Restaurant Equipment",
    "wof:placetype":"venue"
},
  "geometry": {"coordinates":[-79.3324050903,43.8297119141],"type":"Point"}
}