{
  "type": "Feature",
  "properties": {
    "iso:country":"CA",
    "sg:address":"231 2nd Ave W",
    "sg:city":"Hanna",
    "sg:classifiers":[
        {
            "category":"Shopping",
            "subcategory":"Pharmacy",
            "type":"Retail Goods"
        }
    ],
    "sg:phone":"+1 403 854 4081",
    "sg:postcode":"T0J 1P0",
    "sg:province":"AB",
    "wof:name":"Hanna Value Drug Mart",
    "wof:placetype":"venue"
},
  "geometry": {"coordinates":[-111.929244995,51.6426925659],"type":"Point"}
}