{
  "type": "Feature",
  "properties": {
    "addr:full":"221 Wilson St Thunder Bay ON P7B 1M7",
    "addr:housenumber":"221",
    "addr:postcode":"p7b 1m7",
    "addr:street":"Wilson St",
    "iso:country":"CA",
    "sg:address":"221 Wilson St",
    "sg:city":"Thunder Bay",
    "sg:classifiers":[
        {
            "category":"Banks & Credit Unions",
            "subcategory":"Investment Brokerage",
            "type":"Services"
        }
    ],
    "sg:phone":"+1 807 343 4788",
    "sg:postcode":"P7B 1M7",
    "sg:province":"ON",
    "sg:tags":[
        "consultant",
        "planning",
        "financial"
    ],
    "wof:name":"Freedom 55 Financial",
    "wof:placetype":"venue"
},
  "geometry": {"coordinates":[-89.2235488892,48.4321060181],"type":"Point"}
}