{
  "type": "Feature",
  "properties": {
    "addr:full":"L'Annonciation QC J0T 1T0",
    "addr:postcode":"j0t 1t0",
    "iso:country":"CA",
    "sg:city":"L'Annonciation",
    "sg:classifiers":[
        {
            "category":"Food & Beverages",
            "subcategory":"Groceries & Convenience Stores",
            "type":"Retail Goods"
        }
    ],
    "sg:phone":"+1 819 275 1223",
    "sg:postcode":"J0T 1T0",
    "sg:province":"QC",
    "wof:name":"Depanneur Bonisoir",
    "wof:placetype":"venue"
},
  "geometry": {"coordinates":[-74.869011,46.408436],"type":"Point"}
}