{
  "type": "Feature",
  "properties": {
    "addr:full":"5781 Rue DE Verdun Verdun QC H4H 1L7",
    "addr:housenumber":"5781",
    "addr:postcode":"h4h 1l7",
    "addr:street":"Rue De Verdun",
    "iso:country":"CA",
    "sg:address":"5781 Rue DE Verdun",
    "sg:city":"Verdun",
    "sg:classifiers":[
        {
            "category":"Restaurant",
            "type":"Food & Drink"
        }
    ],
    "sg:phone":"+1 514 761 5533",
    "sg:postcode":"H4H 1L7",
    "sg:province":"QC",
    "sg:tags":[
        "caterer"
    ],
    "wof:name":"Silencee on Bouffe Inc",
    "wof:placetype":"venue"
},
  "geometry": {"coordinates":[-73.572762,45.449551],"type":"Point"}
}