{
  "type": "Feature",
  "properties": {
    "iso:country":"CA",
    "sg:address":"555 Mapleview Dr W #8",
    "sg:city":"Barrie",
    "sg:classifiers":[
        {
            "category":"Personal",
            "subcategory":"Beauty Salon",
            "type":"Services"
        }
    ],
    "sg:phone":"+1 705 735 4240",
    "sg:postcode":"L4N 8G5",
    "sg:province":"ON",
    "wof:name":"Caralee's Pure Bliss Salon",
    "wof:placetype":"venue"
},
  "geometry": {"coordinates":[-79.7280044556,44.3255882263],"type":"Point"}
}