{
  "type": "Feature",
  "properties": {
    "iso:country":"CA",
    "sg:address":"1105 Ch Beauvoir O",
    "sg:city":"Fleurimont",
    "sg:classifiers":[
        {
            "category":"Manufacturing",
            "subcategory":"Lumber",
            "type":"Manufacturing & Wholesale Goods"
        }
    ],
    "sg:phone":"+1 819 563 7455",
    "sg:postcode":"J1H 5H3",
    "sg:province":"QC",
    "sg:tags":[
        "syrup",
        "maple",
        "sugar"
    ],
    "wof:name":"Erabliere Patoine",
    "wof:placetype":"venue"
},
  "geometry": {"coordinates":[-71.8397521973,45.4066848755],"type":"Point"}
}