{
  "type": "Feature",
  "properties": {
    "addr:full":"703 King St E Cambridge ON N3H 3N8",
    "addr:housenumber":"703",
    "addr:postcode":"n3h 3n8",
    "addr:street":"King St E",
    "iso:country":"CA",
    "sg:address":"703 King St E",
    "sg:city":"Cambridge",
    "sg:classifiers":[
        {
            "category":"Shopping",
            "subcategory":"Used Merchandise",
            "type":"Retail Goods"
        }
    ],
    "sg:phone":"+1 519 653 1227",
    "sg:postcode":"N3H 3N8",
    "sg:province":"ON",
    "sg:tags":[
        "pawnbroker"
    ],
    "wof:name":"Cambridge Pawn Shop",
    "wof:placetype":"venue"
},
  "geometry": {"coordinates":[-80.358093,43.39587],"type":"Point"}
}