{
  "type": "Feature",
  "properties": {
    "addr:full":"441 Dundas St Woodstock ON N4S 1C2",
    "addr:housenumber":"441",
    "addr:postcode":"n4s 1c2",
    "addr:street":"Dundas St",
    "iso:country":"CA",
    "sg:address":"441 Dundas St",
    "sg:city":"Woodstock",
    "sg:classifiers":[
        {
            "category":"Banks & Credit Unions",
            "subcategory":"Bank",
            "type":"Services"
        }
    ],
    "sg:phone":"+1 519 537 6221",
    "sg:postcode":"N4S 1C2",
    "sg:province":"ON",
    "wof:name":"Cibc",
    "wof:placetype":"venue"
},
  "geometry": {"coordinates":[-80.7585067749,43.1298980713],"type":"Point"}
}