{
  "type": "Feature",
  "properties": {
    "addr:full":"Winnipeg MB R3T 3Y6",
    "addr:postcode":"r3t 3y6",
    "iso:country":"CA",
    "sg:city":"Winnipeg",
    "sg:classifiers":[
        {
            "category":"Education",
            "subcategory":"College",
            "type":"Public Place"
        }
    ],
    "sg:phone":"+1 204 478 8884",
    "sg:postcode":"R3T 3Y6",
    "sg:province":"MB",
    "sg:tags":[
        "academic",
        "school"
    ],
    "wof:name":"Academy of Learning",
    "wof:placetype":"venue"
},
  "geometry": {"coordinates":[-97.15158099999999,49.831123],"type":"Point"}
}