{
  "type": "Feature",
  "properties": {
    "addr:full":"2306 Mississauga Rd Mississauga ON L5H 2L1",
    "addr:housenumber":"2306",
    "addr:postcode":"l5h 2l1",
    "addr:street":"Mississauga Rd",
    "iso:country":"CA",
    "sg:address":"2306 Mississauga Rd",
    "sg:city":"Mississauga",
    "sg:classifiers":[
        {
            "category":"Professional",
            "subcategory":"Business Services",
            "type":"Services"
        }
    ],
    "sg:phone":"+1 905 891 9885",
    "sg:postcode":"L5H 2L1",
    "sg:province":"ON",
    "sg:tags":[
        "interior",
        "consultant",
        "design",
        "decorator"
    ],
    "wof:name":"Sylvia Camilleri Int Decrtng",
    "wof:placetype":"venue"
},
  "geometry": {"coordinates":[-79.639297,43.540173],"type":"Point"}
}