{
  "type": "Feature",
  "properties": {
    "addr:full":"PO Box 235 Ferryland NL A0A 2H0",
    "addr:housenumber":"po",
    "addr:postcode":"a0a 2h0",
    "addr:street":"Box 235",
    "iso:country":"CA",
    "sg:address":"PO Box 235",
    "sg:city":"Ferryland",
    "sg:classifiers":[
        {
            "category":"Restaurant",
            "type":"Food & Drink"
        }
    ],
    "sg:phone":"+1 709 432 2052",
    "sg:postcode":"A0A 2H0",
    "sg:province":"NL",
    "wof:name":"Southern Shore Folk Arts Cncl",
    "wof:placetype":"venue"
},
  "geometry": {"coordinates":[-52.8899,47.02203],"type":"Point"}
}