{
  "type": "Feature",
  "properties": {
    "iso:country":"CA",
    "sg:address":"2384 Route 102",
    "sg:city":"Lincoln",
    "sg:classifiers":[
        {
            "category":"Professional",
            "subcategory":"Advertising",
            "type":"Services"
        }
    ],
    "sg:phone":"+1 506 446 4400",
    "sg:postcode":"E3B 7G1",
    "sg:province":"NB",
    "wof:name":"Auto Seller Magazine Ltd",
    "wof:placetype":"venue"
},
  "geometry": {"coordinates":[-66.548317,45.884518],"type":"Point"}
}