{
  "type": "Feature",
  "properties": {
    "addr:full":"2250 Av Vallee Plessisville QC G6L 3N2",
    "addr:housenumber":"2250",
    "addr:postcode":"g6l 3n2",
    "addr:street":"Av Vallee",
    "iso:country":"CA",
    "sg:address":"2250 Av Vallee",
    "sg:city":"Plessisville",
    "sg:classifiers":[
        {
            "category":"Manufacturing",
            "subcategory":"Tools & Machinery",
            "type":"Manufacturing & Wholesale Goods"
        }
    ],
    "sg:phone":"+1 819 362 6315",
    "sg:postcode":"G6L 3N2",
    "sg:province":"QC",
    "sg:tags":[
        "machine",
        "shop"
    ],
    "wof:name":"Plessitech Inc",
    "wof:placetype":"venue"
},
  "geometry": {"coordinates":[-71.77608499999999,46.228905],"type":"Point"}
}