{
  "type": "Feature",
  "properties": {
    "addr:full":"79 Parkhurst Dr Grafton NB E7N 1P2",
    "addr:housenumber":"79",
    "addr:postcode":"e7n 1p2",
    "addr:street":"Parkhurst Dr",
    "iso:country":"CA",
    "sg:address":"79 Parkhurst Dr",
    "sg:city":"Grafton",
    "sg:classifiers":[
        {
            "category":"Building & Trades",
            "subcategory":"Construction",
            "type":"Services"
        }
    ],
    "sg:phone":"+1 506 328 4722",
    "sg:postcode":"E7N 1P2",
    "sg:province":"NB",
    "sg:tags":[
        "home",
        "general",
        "improvement",
        "contractor"
    ],
    "wof:name":"Riverview Installations Ltd",
    "wof:placetype":"venue"
},
  "geometry": {"coordinates":[-67.565781,46.139099],"type":"Point"}
}