{
  "type": "Feature",
  "properties": {
    "iso:country":"CA",
    "sg:address":"412 Birchs Rd",
    "sg:city":"North Bay",
    "sg:classifiers":[
        {
            "category":"Retail",
            "subcategory":"Auto Repair",
            "type":"Services"
        }
    ],
    "sg:phone":"+1 705 474 7130",
    "sg:postcode":"P1A 4A9",
    "sg:province":"ON",
    "sg:tags":[
        "body",
        "automobile",
        "wrecker"
    ],
    "wof:name":"Central Auto Svc",
    "wof:placetype":"venue"
},
  "geometry": {"coordinates":[-79.4022979736,46.2715988159],"type":"Point"}
}