{
  "type": "Feature",
  "properties": {
    "addr:full":"310 Cote DE L'Artiste Saint-Denis-DE-Brompton QC J0B 2P0",
    "addr:housenumber":"310",
    "addr:postcode":"j0b 2p0",
    "addr:street":"Cote De L'Artiste",
    "iso:country":"CA",
    "sg:address":"310 Cote DE L'Artiste",
    "sg:city":"Saint-Denis-DE-Brompton",
    "sg:classifiers":[
        {
            "category":"Restaurant",
            "type":"Food & Drink"
        }
    ],
    "sg:phone":"+1 819 846 6226",
    "sg:postcode":"J0B 2P0",
    "sg:province":"QC",
    "sg:tags":[
        "pub"
    ],
    "wof:name":"Resto-Bar Lac Brompton",
    "wof:placetype":"venue"
},
  "geometry": {"coordinates":[-72.22968299999999,45.151981],"type":"Point"}
}