{
  "type": "Feature",
  "properties": {
    "iso:country":"CA",
    "sg:city":"Apsley",
    "sg:classifiers":[
        {
            "category":"Wholesale",
            "subcategory":"Construction Materials",
            "type":"Manufacturing & Wholesale Goods"
        }
    ],
    "sg:phone":"+1 705 656 4022",
    "sg:postcode":"K0L 1A0",
    "sg:province":"ON",
    "sg:tags":[
        "sand",
        "gravel"
    ],
    "wof:name":"Lippert's Carpentry & Contract",
    "wof:placetype":"venue"
},
  "geometry": {"coordinates":[-78.0853729248,44.7530212402],"type":"Point"}
}