{
  "type": "Feature",
  "properties": {
    "addr:full":"Edmonton AB T5J 4A1",
    "addr:postcode":"t5j 4a1",
    "iso:country":"CA",
    "sg:city":"Edmonton",
    "sg:classifiers":[
        {
            "category":"Shopping",
            "subcategory":"Tobacco",
            "type":"Retail Goods"
        }
    ],
    "sg:phone":"+1 780 429 9988",
    "sg:postcode":"T5J 4A1",
    "sg:province":"AB",
    "sg:tags":[
        "cigarette",
        "cigar",
        "dealer"
    ],
    "wof:name":"Boardwalk Smoke Shop",
    "wof:placetype":"venue"
},
  "geometry": {"coordinates":[-113.497902,53.54314],"type":"Point"}
}