{
  "type": "Feature",
  "properties": {
    "addr:full":"103 Manville Rd Scarborough ON M1L 4H9",
    "addr:housenumber":"103",
    "addr:postcode":"m1l 4h9",
    "addr:street":"Manville Rd",
    "iso:country":"CA",
    "sg:address":"103 Manville Rd",
    "sg:city":"Scarborough",
    "sg:classifiers":[
        {
            "category":"Restaurant",
            "type":"Food & Drink"
        }
    ],
    "sg:phone":"+1 416 759 3341",
    "sg:postcode":"M1L 4H9",
    "sg:province":"ON",
    "sg:tags":[
        "caterer"
    ],
    "wof:name":"Choice Children's Catering Ltd",
    "wof:placetype":"venue"
},
  "geometry": {"coordinates":[-79.281128,43.721222],"type":"Point"}
}