{
  "type": "Feature",
  "properties": {
    "addr:full":"4858 Rue Nancy Pierrefonds QC H8Z 1Z8",
    "addr:housenumber":"4858",
    "addr:postcode":"h8z 1z8",
    "addr:street":"Rue Nancy",
    "iso:country":"CA",
    "sg:address":"4858 Rue Nancy",
    "sg:city":"Pierrefonds",
    "sg:classifiers":[
        {
            "category":"Professional",
            "subcategory":"Accounting & Tax Preparation",
            "type":"Services"
        }
    ],
    "sg:phone":"+1 514 683 4222",
    "sg:postcode":"H8Z 1Z8",
    "sg:province":"QC",
    "sg:tags":[
        "bookkeeping",
        "general"
    ],
    "wof:name":"Busy Bee Bookkeeping Svc",
    "wof:placetype":"venue"
},
  "geometry": {"coordinates":[-73.83075714109999,45.5047569275],"type":"Point"}
}