{
  "type": "Feature",
  "properties": {
    "addr:full":"244 Mary St Hamilton ON L8L 4W1",
    "addr:housenumber":"244",
    "addr:postcode":"l8l 4w1",
    "addr:street":"Mary St",
    "iso:country":"CA",
    "sg:address":"244 Mary St",
    "sg:city":"Hamilton",
    "sg:classifiers":[
        {
            "category":"Retail",
            "subcategory":"Auto Repair",
            "type":"Services"
        }
    ],
    "sg:phone":"+1 905 543 8710",
    "sg:postcode":"L8L 4W1",
    "sg:province":"ON",
    "sg:tags":[
        "repairing",
        "automobile"
    ],
    "wof:name":"Quality Automotive",
    "wof:placetype":"venue"
},
  "geometry": {"coordinates":[-79.86088562010001,43.2620162964],"type":"Point"}
}