{
  "type": "Feature",
  "properties": {
    "addr:full":"Winnipeg MB R3B 0S5",
    "addr:postcode":"r3b 0s5",
    "iso:country":"CA",
    "sg:city":"Winnipeg",
    "sg:classifiers":[
        {
            "category":"Education",
            "subcategory":"Special Training",
            "type":"Public Place"
        }
    ],
    "sg:phone":"+1 204 946 5100",
    "sg:postcode":"R3B 0S5",
    "sg:province":"MB",
    "sg:tags":[
        "aid",
        "instruction",
        "first"
    ],
    "wof:name":"Emergency Rescue Response Svc",
    "wof:placetype":"venue"
},
  "geometry": {"coordinates":[-97.1404876709,49.8969764709],"type":"Point"}
}