{
  "type": "Feature",
  "properties": {
    "addr:full":"Mckenzie Hwy 3 Rae Edzo NT X0E 0Y0",
    "addr:postcode":"x0e 0y0",
    "addr:street":"Mckenzie Hwy 3 Rae Edzo",
    "iso:country":"CA",
    "sg:address":"Mckenzie Hwy 3",
    "sg:city":"Rae Edzo",
    "sg:classifiers":[
        {
            "category":"Professional",
            "subcategory":"Management & Consulting",
            "type":"Services"
        }
    ],
    "sg:phone":"+1 867 371 3144",
    "sg:postcode":"X0E 0Y0",
    "sg:province":"NT",
    "sg:tags":[
        "consultant",
        "business"
    ],
    "wof:name":"Rabesca's Resources Ltd",
    "wof:placetype":"venue"
},
  "geometry": {"coordinates":[-115.994919,62.78421],"type":"Point"}
}