{
  "type": "Feature",
  "properties": {
    "iso:country":"CA",
    "sg:address":"142 Main St",
    "sg:city":"Unionville",
    "sg:classifiers":[
        {
            "category":"Personal",
            "subcategory":"Beauty Salon",
            "type":"Services"
        }
    ],
    "sg:phone":"+1 905 477 1899",
    "sg:postcode":"L3R 2G5",
    "sg:province":"ON",
    "wof:name":"Carelli Hair Studio",
    "wof:placetype":"venue"
},
  "geometry": {"coordinates":[-79.310883,43.865505],"type":"Point"}
}