{
  "type": "Feature",
  "properties": {
    "iso:country":"CA",
    "sg:city":"Woodbridge",
    "sg:classifiers":[
        {
            "category":"Shopping",
            "subcategory":"Clothing, Apparel, & Fashions",
            "type":"Retail Goods"
        }
    ],
    "sg:phone":"+1 905 265 0166",
    "sg:postcode":"L4L 9G7",
    "sg:province":"ON",
    "wof:name":"Cherie",
    "wof:placetype":"venue"
},
  "geometry": {"coordinates":[-79.5495834351,43.8063850403],"type":"Point"}
}