{
  "type": "Feature",
  "properties": {
    "addr:full":"5813 Byrne Rd Burnaby BC V5J 3J1",
    "addr:housenumber":"5813",
    "addr:postcode":"v5j 3j1",
    "addr:street":"Byrne Rd",
    "iso:country":"CA",
    "sg:address":"5813 Byrne Rd",
    "sg:city":"Burnaby",
    "sg:classifiers":[
        {
            "category":"Retail",
            "subcategory":"Auto Repair",
            "type":"Services"
        }
    ],
    "sg:phone":"+1 604 435 5549",
    "sg:postcode":"V5J 3J1",
    "sg:province":"BC",
    "sg:tags":[
        "truck"
    ],
    "wof:name":"B C Truck & Welding Repairs",
    "wof:placetype":"venue"
},
  "geometry": {"coordinates":[-122.979606628,49.2034225464],"type":"Point"}
}