{
  "type": "Feature",
  "properties": {
    "iso:country":"CA",
    "sg:address":"2619 Derbyshire Way",
    "sg:city":"North Vancouver",
    "sg:classifiers":[
        {
            "category":"Building & Trades",
            "subcategory":"Plumbing",
            "type":"Services"
        }
    ],
    "sg:phone":"+1 604 929 2225",
    "sg:postcode":"V7H 1P9",
    "sg:province":"BC",
    "sg:tags":[
        "heat",
        "heating",
        "pump",
        "contractor"
    ],
    "wof:name":"Enertech Sales Ltd",
    "wof:placetype":"venue"
},
  "geometry": {"coordinates":[-123.001029968,49.3277015686],"type":"Point"}
}