{
  "type": "Feature",
  "properties": {
    "addr:full":"23 Westside Dr Cochrane AB T4C 1M1",
    "addr:housenumber":"23",
    "addr:postcode":"t4c 1m1",
    "addr:street":"Westside Dr",
    "iso:country":"CA",
    "sg:address":"23 Westside Dr",
    "sg:city":"Cochrane",
    "sg:classifiers":[
        {
            "category":"Restaurant",
            "type":"Food & Drink"
        }
    ],
    "sg:phone":"+1 403 932 9552",
    "sg:postcode":"T4C 1M1",
    "sg:province":"AB",
    "wof:name":"A & W Family Restaurant",
    "wof:placetype":"venue"
},
  "geometry": {"coordinates":[-114.48902893099999,51.1900215149],"type":"Point"}
}