{
  "type": "Feature",
  "properties": {
    "iso:country":"CA",
    "sg:address":"140 Concession St W",
    "sg:city":"Tillsonburg",
    "sg:classifiers":[
        {
            "category":"Home & Garden",
            "subcategory":"Home Furnishings",
            "type":"Retail Goods"
        }
    ],
    "sg:phone":"+1 519 842 7138",
    "sg:postcode":"N4G 1R7",
    "sg:province":"ON",
    "sg:tags":[
        "made",
        "consultant",
        "design",
        "decorator",
        "interior",
        "drapery"
    ],
    "wof:name":"Ask Anna Ltd",
    "wof:placetype":"venue"
},
  "geometry": {"coordinates":[-80.7487411499,42.8638114929],"type":"Point"}
}