{
  "type": "Feature",
  "properties": {
    "iso:country":"CA",
    "sg:city":"Innisfail",
    "sg:classifiers":[
        {
            "category":"Home & Garden",
            "subcategory":"Household Appliances",
            "type":"Retail Goods"
        }
    ],
    "sg:phone":"+1 403 227 4664",
    "sg:postcode":"T4G 1C2",
    "sg:province":"AB",
    "sg:tags":[
        "cleaners",
        "vacuum"
    ],
    "wof:name":"All-Vac Sales Svc & Repair",
    "wof:placetype":"venue"
},
  "geometry": {"coordinates":[-113.944877624,52.0274505615],"type":"Point"}
}