{
  "type": "Feature",
  "properties": {
    "addr:full":"150 Ch Saint-Louis Beauharnois QC J6N 2H9",
    "addr:housenumber":"150",
    "addr:postcode":"j6n 2h9",
    "addr:street":"Ch Saint-Louis",
    "iso:country":"CA",
    "sg:address":"150 Ch Saint-Louis",
    "sg:city":"Beauharnois",
    "sg:classifiers":[
        {
            "category":"Professional",
            "subcategory":"Business Services",
            "type":"Services"
        }
    ],
    "sg:phone":"+1 450 429 4633",
    "sg:postcode":"J6N 2H9",
    "sg:province":"QC",
    "sg:tags":[
        "notary"
    ],
    "wof:name":"Philie & Morrisseau",
    "wof:placetype":"venue"
},
  "geometry": {"coordinates":[-73.87844800000001,45.313213],"type":"Point"}
}