{
  "type": "Feature",
  "properties": {
    "addr:full":"416 Davis Dr Newmarket ON L3Y 2N9",
    "addr:housenumber":"416",
    "addr:postcode":"l3y 2n9",
    "addr:street":"Davis Dr",
    "iso:country":"CA",
    "sg:address":"416 Davis Dr",
    "sg:city":"Newmarket",
    "sg:classifiers":[
        {
            "category":"Restaurant",
            "type":"Food & Drink"
        }
    ],
    "sg:phone":"+1 905 853 5222",
    "sg:postcode":"L3Y 2N9",
    "sg:province":"ON",
    "wof:name":"Wimpy's Diner",
    "wof:placetype":"venue"
},
  "geometry": {"coordinates":[-79.461876,44.058842],"type":"Point"}
}