{
  "type": "Feature",
  "properties": {
    "iso:country":"CA",
    "sg:address":"30 Rue Saint-Dominique",
    "sg:city":"Victoriaville",
    "sg:classifiers":[
        {
            "category":"Shopping",
            "subcategory":"Used Merchandise",
            "type":"Retail Goods"
        }
    ],
    "sg:phone":"+1 819 752 9306",
    "sg:postcode":"G6P 5B6",
    "sg:province":"QC",
    "sg:tags":[
        "book",
        "rare",
        "dealer"
    ],
    "wof:name":"Recyclo-Livres",
    "wof:placetype":"venue"
},
  "geometry": {"coordinates":[-71.9566650391,46.0558509827],"type":"Point"}
}