{
  "type": "Feature",
  "properties": {
    "addr:full":"1012 Av Du Mont-Royal E Montreal QC H2J 1X6",
    "addr:housenumber":"1012",
    "addr:postcode":"h2j 1x6",
    "addr:street":"Av Du Mont-Royal E",
    "iso:country":"CA",
    "sg:address":"1012 Av Du Mont-Royal E",
    "sg:city":"Montreal",
    "sg:classifiers":[
        {
            "category":"Organizations",
            "subcategory":"Professional Association",
            "type":"Services"
        }
    ],
    "sg:phone":"+1 514 522 3797",
    "sg:postcode":"H2J 1X6",
    "sg:province":"QC",
    "wof:name":"Societe DE Dev DE L'Avenue",
    "wof:placetype":"venue"
},
  "geometry": {"coordinates":[-73.5795135498,45.5274429321],"type":"Point"}
}