{
  "type": "Feature",
  "properties": {
    "addr:full":"Halifax NS B3J 3K3",
    "addr:postcode":"ns b3j 3k3",
    "iso:country":"CA",
    "sg:city":"Halifax",
    "sg:classifiers":[
        {
            "category":"Education",
            "subcategory":"College",
            "type":"Public Place"
        }
    ],
    "sg:phone":"+1 902 491 1526",
    "sg:postcode":"B3J 3K3",
    "sg:province":"NS",
    "sg:tags":[
        "academic",
        "school",
        "language"
    ],
    "wof:name":"East Coast School-Languages",
    "wof:placetype":"venue"
},
  "geometry": {"coordinates":[-63.578194,44.643093],"type":"Point"}
}