{
  "type": "Feature",
  "properties": {
    "iso:country":"CA",
    "sg:address":"7000 Gold River Rd",
    "sg:city":"Campbell River",
    "sg:classifiers":[
        {
            "category":"Professional",
            "subcategory":"Engineering",
            "type":"Services"
        }
    ],
    "sg:phone":"+1 250 286 4080",
    "sg:postcode":"V9H 1P1",
    "sg:province":"BC",
    "sg:tags":[
        "engineer"
    ],
    "wof:name":"Brian Gunn Consulting",
    "wof:placetype":"venue"
},
  "geometry": {"coordinates":[-125.354377747,50.0174789429],"type":"Point"}
}