{
  "type": "Feature",
  "properties": {
    "addr:full":"935 Spring Pl Nanaimo BC V9R 6C3",
    "addr:housenumber":"935",
    "addr:postcode":"v9r 6c3",
    "addr:street":"Spring Pl",
    "iso:country":"CA",
    "sg:address":"935 Spring Pl",
    "sg:city":"Nanaimo",
    "sg:classifiers":[
        {
            "category":"Food & Beverages",
            "subcategory":"Bakery",
            "type":"Retail Goods"
        }
    ],
    "sg:phone":"+1 250 753 1273",
    "sg:postcode":"V9R 6C3",
    "sg:province":"BC",
    "sg:tags":[
        "baker"
    ],
    "wof:name":"Buns Master Bakery",
    "wof:placetype":"venue"
},
  "geometry": {"coordinates":[-123.954353333,49.1404190063],"type":"Point"}
}