{
  "type": "Feature",
  "properties": {
    "iso:country":"CA",
    "sg:address":"5743 Thorold Stone Rd",
    "sg:city":"Niagara Falls",
    "sg:classifiers":[
        {
            "category":"Health Services",
            "subcategory":"Chiropractor",
            "type":"Services"
        }
    ],
    "sg:phone":"+1 905 356 0005",
    "sg:postcode":"L2J 1A1",
    "sg:province":"ON",
    "wof:name":"DE Fazio, Christine DC",
    "wof:placetype":"venue"
},
  "geometry": {"coordinates":[-79.0907211304,43.1155891418],"type":"Point"}
}