{
  "type": "Feature",
  "properties": {
    "addr:full":"55 Main St S Georgetown ON L7G 3G2",
    "addr:housenumber":"55",
    "addr:postcode":"l7g 3g2",
    "addr:street":"Main St S",
    "iso:country":"CA",
    "sg:address":"55 Main St S",
    "sg:city":"Georgetown",
    "sg:classifiers":[
        {
            "category":"Retail",
            "subcategory":"Laundry & Dry Cleaning",
            "type":"Services"
        }
    ],
    "sg:phone":"+1 905 877 0469",
    "sg:postcode":"L7G 3G2",
    "sg:province":"ON",
    "sg:tags":[
        "cleaners"
    ],
    "wof:name":"North Star Dry Cleaners",
    "wof:placetype":"venue"
},
  "geometry": {"coordinates":[-79.92671199999999,43.65004],"type":"Point"}
}