{
  "type": "Feature",
  "properties": {
    "addr:full":"505 Boul Lebeau Saint-Laurent QC H4N 1S2",
    "addr:housenumber":"505",
    "addr:postcode":"h4n 1s2",
    "addr:street":"Boul Lebeau",
    "iso:country":"CA",
    "sg:address":"505 Boul Lebeau",
    "sg:city":"Saint-Laurent",
    "sg:classifiers":[
        {
            "category":"Wholesale",
            "subcategory":"Apparel",
            "type":"Manufacturing & Wholesale Goods"
        }
    ],
    "sg:phone":"+1 514 856 0056",
    "sg:postcode":"H4N 1S2",
    "sg:province":"QC",
    "sg:tags":[
        "cotton"
    ],
    "wof:name":"Delfeb Enterprises Inc",
    "wof:placetype":"venue"
},
  "geometry": {"coordinates":[-73.661072,45.526779],"type":"Point"}
}