{
  "type": "Feature",
  "properties": {
    "addr:full":"Stoney Creek ON L8E 3R9",
    "addr:postcode":"l8e 3r9",
    "iso:country":"CA",
    "sg:city":"Stoney Creek",
    "sg:classifiers":[
        {
            "category":"Manufacturing",
            "subcategory":"Metals",
            "type":"Manufacturing & Wholesale Goods"
        }
    ],
    "sg:phone":"+1 905 664 2574",
    "sg:postcode":"L8E 3R9",
    "sg:province":"ON",
    "sg:tags":[
        "steel"
    ],
    "wof:name":"Pro Art Metals",
    "wof:placetype":"venue"
},
  "geometry": {"coordinates":[-79.71769,43.23613],"type":"Point"}
}