{
  "type": "Feature",
  "properties": {
    "addr:full":"Monetville ON P0M 2K0",
    "addr:postcode":"p0m 2k0",
    "iso:country":"CA",
    "sg:city":"Monetville",
    "sg:classifiers":[
        {
            "category":"Organizations",
            "subcategory":"Professional Association",
            "type":"Services"
        }
    ],
    "sg:phone":"+1 705 763 2778",
    "sg:postcode":"P0M 2K0",
    "sg:province":"ON",
    "wof:name":"Dokis Band Contact North Site",
    "wof:placetype":"venue"
},
  "geometry": {"coordinates":[-80.35855865480001,46.1621894836],"type":"Point"}
}