{
  "type": "Feature",
  "properties": {
    "addr:full":"Sainte-Rose QC H7L 3A1",
    "addr:postcode":"h7l 3a1",
    "iso:country":"CA",
    "sg:city":"Sainte-Rose",
    "sg:classifiers":[
        {
            "category":"Professional",
            "subcategory":"Business Services",
            "type":"Services"
        }
    ],
    "sg:phone":"+1 450 628 2137",
    "sg:postcode":"H7L 3A1",
    "sg:province":"QC",
    "sg:tags":[
        "drafting"
    ],
    "wof:name":"Cla Concept",
    "wof:placetype":"venue"
},
  "geometry": {"coordinates":[-73.7899856567,45.6044425964],"type":"Point"}
}