{
  "type": "Feature",
  "properties": {
    "addr:full":"3480 Boul Decarie Montreal QC H4A 3J5",
    "addr:housenumber":"3480",
    "addr:postcode":"h4a 3j5",
    "addr:street":"Boul Decarie",
    "iso:country":"CA",
    "sg:address":"3480 Boul Decarie",
    "sg:city":"Montreal",
    "sg:classifiers":[
        {
            "category":"Organizations",
            "subcategory":"Professional Association",
            "type":"Services"
        }
    ],
    "sg:phone":"+1 514 481 6661",
    "sg:postcode":"H4A 3J5",
    "sg:province":"QC",
    "wof:name":"Korean Community-Greater Mntrl",
    "wof:placetype":"venue"
},
  "geometry": {"coordinates":[-73.610344,45.474827],"type":"Point"}
}