{
  "type": "Feature",
  "properties": {
    "addr:full":"Spruce Grove AB T7X 4G3",
    "addr:postcode":"t7x 4g3",
    "iso:country":"CA",
    "sg:city":"Spruce Grove",
    "sg:classifiers":[
        {
            "category":"Wholesale",
            "subcategory":"Construction Materials",
            "type":"Manufacturing & Wholesale Goods"
        }
    ],
    "sg:phone":"+1 780 962 4824",
    "sg:postcode":"T7X 4G3",
    "sg:province":"AB",
    "sg:tags":[
        "limestone",
        "lime"
    ],
    "wof:name":"Mountain Lime & Marble Inc",
    "wof:placetype":"venue"
},
  "geometry": {"coordinates":[-113.903648,53.538826],"type":"Point"}
}