{
  "type": "Feature",
  "properties": {
    "iso:country":"CA",
    "sg:city":"Calgary",
    "sg:classifiers":[
        {
            "category":"Home & Garden",
            "subcategory":"Household Appliances",
            "type":"Retail Goods"
        }
    ],
    "sg:phone":"+1 403 282 9618",
    "sg:postcode":"T2L 1V9",
    "sg:province":"AB",
    "sg:tags":[
        "cleaners",
        "vacuum"
    ],
    "wof:name":"Vacuum Experts Inc",
    "wof:placetype":"venue"
},
  "geometry": {"coordinates":[-114.13908386200001,51.1010894775],"type":"Point"}
}