{
  "type": "Feature",
  "properties": {
    "addr:full":"315 7 St S Lethbridge AB T1J 2G4",
    "addr:housenumber":"315 7",
    "addr:postcode":"t1j 2g4",
    "addr:street":"St S",
    "iso:country":"CA",
    "sg:address":"315 7 St S",
    "sg:city":"Lethbridge",
    "sg:classifiers":[
        {
            "category":"Shopping",
            "subcategory":"Bicycles & Sporting Goods",
            "type":"Retail Goods"
        }
    ],
    "sg:phone":"+1 403 327 5751",
    "sg:postcode":"T1J 2G4",
    "sg:province":"AB",
    "wof:name":"Doug's Sports Ltd",
    "wof:placetype":"venue"
},
  "geometry": {"coordinates":[-112.836929321,49.6956939697],"type":"Point"}
}