{
  "type": "Feature",
  "properties": {
    "iso:country":"CA",
    "sg:city":"Etobicoke",
    "sg:classifiers":[
        {
            "category":"Manufacturing",
            "subcategory":"Printing",
            "type":"Manufacturing & Wholesale Goods"
        }
    ],
    "sg:phone":"+1 416 251 8163",
    "sg:postcode":"M8Z 1R7",
    "sg:province":"ON",
    "sg:tags":[
        "printer"
    ],
    "wof:name":"Premier Quality Printing",
    "wof:placetype":"venue"
},
  "geometry": {"coordinates":[-79.52252197270001,43.6217346191],"type":"Point"}
}