{
  "type": "Feature",
  "properties": {
    "addr:full":"4000 Yonge St North York ON M4N 2N9",
    "addr:housenumber":"4000",
    "addr:postcode":"m4n 2n9",
    "addr:street":"Yonge St",
    "iso:country":"CA",
    "sg:address":"4000 Yonge St",
    "sg:city":"North York",
    "sg:classifiers":[
        {
            "category":"Personal",
            "subcategory":"Beauty Salon",
            "type":"Services"
        }
    ],
    "sg:phone":"+1 416 481 5935",
    "sg:postcode":"M4N 2N9",
    "sg:province":"ON",
    "wof:name":"Leo & Mike Coiffures",
    "wof:placetype":"venue"
},
  "geometry": {"coordinates":[-79.406639,43.742905],"type":"Point"}
}