{
  "type": "Feature",
  "properties": {
    "addr:full":"2446 Main St Vancouver BC V5T 3E2",
    "addr:housenumber":"2446",
    "addr:postcode":"v5t 3e2",
    "addr:street":"Main St",
    "iso:country":"CA",
    "sg:address":"2446 Main St",
    "sg:city":"Vancouver",
    "sg:classifiers":[
        {
            "category":"Personal",
            "subcategory":"Beauty Salon",
            "type":"Services"
        }
    ],
    "sg:phone":"+1 604 873 2311",
    "sg:postcode":"V5T 3E2",
    "sg:province":"BC",
    "wof:name":"Mabel's Beauty Salon",
    "wof:placetype":"venue"
},
  "geometry": {"coordinates":[-123.100738525,49.2633094788],"type":"Point"}
}