{
  "type": "Feature",
  "properties": {
    "addr:full":"231 Boul Rene-A.-Robert Sainte-Therese QC J7E 4L1",
    "addr:housenumber":"231",
    "addr:postcode":"j7e 4l1",
    "addr:street":"Boul Rene-A.-Robert Sainte-Therese",
    "iso:country":"CA",
    "sg:address":"231 Boul Rene-A.-Robert",
    "sg:city":"Sainte-Therese",
    "sg:classifiers":[
        {
            "category":"Manufacturing",
            "subcategory":"Chemicals & Compounds",
            "type":"Manufacturing & Wholesale Goods"
        }
    ],
    "sg:phone":"+1 450 435 1227",
    "sg:postcode":"J7E 4L1",
    "sg:province":"QC",
    "sg:tags":[
        "paint"
    ],
    "wof:name":"Gotham Industries Inc",
    "wof:placetype":"venue"
},
  "geometry": {"coordinates":[-73.817047,45.642399],"type":"Point"}
}