{
  "type": "Feature",
  "properties": {
    "addr:full":"Guelph ON N1H 3V8",
    "addr:postcode":"n1h 3v8",
    "iso:country":"CA",
    "sg:city":"Guelph",
    "sg:classifiers":[
        {
            "category":"Shopping",
            "subcategory":"Clothing, Apparel, & Fashions",
            "type":"Retail Goods"
        }
    ],
    "sg:phone":"+1 519 824 6798",
    "sg:postcode":"N1H 3V8",
    "sg:province":"ON",
    "sg:tags":[
        "dressmaker"
    ],
    "wof:name":"Wardrobe Designer",
    "wof:placetype":"venue"
},
  "geometry": {"coordinates":[-80.2478713989,43.5445632935],"type":"Point"}
}