{
  "type": "Feature",
  "properties": {
    "addr:full":"270 153 Rte E Grand-Mere QC G9T 3B7",
    "addr:housenumber":"153",
    "addr:postcode":"g9t 3b7",
    "addr:street":"Rte E Grand-Mere",
    "iso:country":"CA",
    "sg:address":"270 153 Rte E",
    "sg:city":"Grand-Mere",
    "sg:classifiers":[
        {
            "category":"Building & Trades",
            "subcategory":"Construction",
            "type":"Services"
        }
    ],
    "sg:phone":"+1 819 538 4315",
    "sg:postcode":"G9T 3B7",
    "sg:province":"QC",
    "sg:tags":[
        "door",
        "contractor"
    ],
    "wof:name":"Allaire Georges Aluminium Inc",
    "wof:placetype":"venue"
},
  "geometry": {"coordinates":[-72.69319900000001,46.620956],"type":"Point"}
}