{
  "type": "Feature",
  "properties": {
    "addr:full":"Val-Belair QC G3J 1R3",
    "addr:postcode":"g3j 1r3",
    "iso:country":"CA",
    "sg:city":"Val-Belair",
    "sg:classifiers":[
        {
            "category":"Mining & Drilling",
            "type":"Manufacturing & Wholesale Goods"
        }
    ],
    "sg:phone":"+1 418 843 7753",
    "sg:postcode":"G3J 1R3",
    "sg:province":"QC",
    "sg:tags":[
        "stone",
        "quarry"
    ],
    "wof:name":"Sabliere Drapeau Inc",
    "wof:placetype":"venue"
},
  "geometry": {"coordinates":[-71.45169799999999,46.87804],"type":"Point"}
}