{
  "type": "Feature",
  "properties": {
    "addr:full":"111 Sherwood Dr # 7 Brantford ON N3T 6J9",
    "addr:housenumber":"111",
    "addr:postcode":"n3t 6j9",
    "addr:street":"Sherwood Dr # 7",
    "iso:country":"CA",
    "sg:address":"111 Sherwood Dr # 7",
    "sg:city":"Brantford",
    "sg:classifiers":[
        {
            "category":"Retail",
            "subcategory":"Repair Shop",
            "type":"Services"
        }
    ],
    "sg:phone":"+1 519 753 6297",
    "sg:postcode":"N3T 6J9",
    "sg:province":"ON",
    "sg:tags":[
        "refinishing",
        "furniture"
    ],
    "wof:name":"Strippers the Brantford",
    "wof:placetype":"venue"
},
  "geometry": {"coordinates":[-80.27900699999999,43.133152],"type":"Point"}
}