{
  "type": "Feature",
  "properties": {
    "addr:full":"398 Av Oakville Dorval QC H9S 2R5",
    "addr:postcode":"h9s 2r5",
    "addr:street":"398 Av Oakville",
    "iso:country":"CA",
    "sg:address":"398 Av Oakville",
    "sg:city":"Dorval",
    "sg:classifiers":[
        {
            "category":"Health Services",
            "subcategory":"Doctor",
            "type":"Services"
        }
    ],
    "sg:phone":"+1 514 636 2502",
    "sg:postcode":"H9S 2R5",
    "sg:province":"QC",
    "sg:tags":[
        "dentist"
    ],
    "wof:name":"Collet, J C DDS",
    "wof:placetype":"venue"
},
  "geometry": {"coordinates":[-73.7675476074,45.4477996826],"type":"Point"}
}