{
  "type": "Feature",
  "properties": {
    "addr:full":"New Lowell ON L0M 1N0",
    "addr:postcode":"l0m 1n0",
    "addr:street":"New",
    "iso:country":"CA",
    "sg:city":"New Lowell",
    "sg:classifiers":[
        {
            "category":"Autos & Motor Vehicles",
            "subcategory":"Automobile Sales",
            "type":"Retail Goods"
        }
    ],
    "sg:phone":"+1 705 424 1691",
    "sg:postcode":"L0M 1N0",
    "sg:province":"ON",
    "sg:tags":[
        "parts",
        "snowmobile",
        "accessory"
    ],
    "wof:name":"J T's Snowmobile Repair",
    "wof:placetype":"venue"
},
  "geometry": {"coordinates":[-79.9740982056,44.3577842712],"type":"Point"}
}