{
  "type": "Feature",
  "properties": {
    "addr:full":"35 Rue Saint-Etienne Saint-Gervais QC G0R 3C0",
    "addr:housenumber":"35",
    "addr:postcode":"g0r 3c0",
    "addr:street":"Rue Saint-Etienne",
    "iso:country":"CA",
    "sg:address":"35 Rue Saint-Etienne",
    "sg:city":"Saint-Gervais",
    "sg:classifiers":[
        {
            "category":"Shopping",
            "subcategory":"Computers & Home Electronics",
            "type":"Retail Goods"
        }
    ],
    "sg:phone":"+1 418 887 3237",
    "sg:postcode":"G0R 3C0",
    "sg:province":"QC",
    "sg:tags":[
        "equipment",
        "dealer"
    ],
    "wof:name":"Allo Micro Informatique Enr",
    "wof:placetype":"venue"
},
  "geometry": {"coordinates":[-70.8897476196,46.71459198],"type":"Point"}
}