{
  "type": "Feature",
  "properties": {
    "iso:country":"CA",
    "sg:address":"775 Main St E",
    "sg:city":"North Bay",
    "sg:classifiers":[
        {
            "category":"Wholesale",
            "subcategory":"Auto Parts",
            "type":"Manufacturing & Wholesale Goods"
        }
    ],
    "sg:phone":"+1 705 474 9006",
    "sg:postcode":"P1B 1C2",
    "sg:province":"ON",
    "sg:tags":[
        "equipment",
        "truck"
    ],
    "wof:name":"Carter's Custom Caps",
    "wof:placetype":"venue"
},
  "geometry": {"coordinates":[-79.45622253419999,46.3013153076],"type":"Point"}
}