{
  "type": "Feature",
  "properties": {
    "addr:full":"11762 106 St NW Edmonton AB T5G 2R1",
    "addr:housenumber":"11762",
    "addr:postcode":"t5g 2r1",
    "addr:street":"106 St Nw",
    "iso:country":"CA",
    "sg:address":"11762 106 St NW",
    "sg:city":"Edmonton",
    "sg:classifiers":[
        {
            "category":"Education",
            "subcategory":"College",
            "type":"Public Place"
        }
    ],
    "sg:phone":"+1 780 471 7400",
    "sg:postcode":"T5G 2R1",
    "sg:province":"AB",
    "sg:tags":[
        "academic",
        "school"
    ],
    "wof:name":"Northern Alberta Institute",
    "wof:placetype":"venue"
},
  "geometry": {"coordinates":[-113.503242,53.56818],"type":"Point"}
}