{
  "type": "Feature",
  "properties": {
    "addr:full":"Vancouver BC V5S 1J9",
    "addr:postcode":"v5s 1j9",
    "iso:country":"CA",
    "sg:city":"Vancouver",
    "sg:classifiers":[
        {
            "category":"Retail",
            "subcategory":"Photofinishing",
            "type":"Services"
        }
    ],
    "sg:phone":"+1 604 438 1742",
    "sg:postcode":"V5S 1J9",
    "sg:province":"BC",
    "sg:tags":[
        "photo",
        "finishing"
    ],
    "wof:name":"Qualimax Photo",
    "wof:placetype":"venue"
},
  "geometry": {"coordinates":[-123.05437499999999,49.224998],"type":"Point"}
}