{
  "type": "Feature",
  "properties": {
    "addr:full":"91 Geneva St St Catharines ON L2R 4M9",
    "addr:housenumber":"91",
    "addr:postcode":"l2r 4m9",
    "addr:street":"Geneva St",
    "iso:country":"CA",
    "sg:address":"91 Geneva St",
    "sg:city":"St Catharines",
    "sg:classifiers":[
        {
            "category":"Professional",
            "subcategory":"Credit Reporting & Collection",
            "type":"Services"
        }
    ],
    "sg:phone":"+1 905 684 1324",
    "sg:postcode":"L2R 4M9",
    "sg:province":"ON",
    "sg:tags":[
        "agency"
    ],
    "wof:name":"Credit Network Inc",
    "wof:placetype":"venue"
},
  "geometry": {"coordinates":[-79.24039459230001,43.1646308899],"type":"Point"}
}