{
  "type": "Feature",
  "properties": {
    "iso:country":"CA",
    "sg:address":"146 Simcoe St N",
    "sg:city":"Oshawa",
    "sg:classifiers":[
        {
            "category":"Professional",
            "subcategory":"Lawyer & Legal Services",
            "type":"Services"
        }
    ],
    "sg:phone":"+1 905 571 1400",
    "sg:postcode":"L1G 4S7",
    "sg:province":"ON",
    "sg:tags":[
        "attorney"
    ],
    "wof:name":"Mack, Paul D",
    "wof:placetype":"venue"
},
  "geometry": {"coordinates":[-78.865524,43.901363],"type":"Point"}
}