{
  "type": "Feature",
  "properties": {
    "addr:full":"1965 Boul DE Comporte LA Malbaie QC G5A 1N9",
    "addr:housenumber":"1965",
    "addr:postcode":"g5a 1n9",
    "addr:street":"Boul De Comporte",
    "iso:country":"CA",
    "sg:address":"1965 Boul DE Comporte",
    "sg:city":"LA Malbaie",
    "sg:classifiers":[
        {
            "category":"Wholesale",
            "subcategory":"Electrical",
            "type":"Manufacturing & Wholesale Goods"
        }
    ],
    "sg:phone":"+1 418 665 7835",
    "sg:postcode":"G5A 1N9",
    "sg:province":"QC",
    "sg:tags":[
        "battery"
    ],
    "wof:name":"Batteries Expert Charlevoix",
    "wof:placetype":"venue"
},
  "geometry": {"coordinates":[-70.1794662476,47.6745071411],"type":"Point"}
}