{
  "type": "Feature",
  "properties": {
    "addr:full":"5964 Bow Cres NW Calgary AB T3B 2B9",
    "addr:housenumber":"5964",
    "addr:postcode":"t3b 2b9",
    "addr:street":"Bow Cres Nw",
    "iso:country":"CA",
    "sg:address":"5964 Bow Cres NW",
    "sg:city":"Calgary",
    "sg:classifiers":[
        {
            "category":"Home & Garden",
            "subcategory":"Home Furnishings",
            "type":"Retail Goods"
        }
    ],
    "sg:phone":"+1 403 813 8398",
    "sg:postcode":"T3B 2B9",
    "sg:province":"AB",
    "sg:tags":[
        "fireplace",
        "cleaning",
        "chimney"
    ],
    "wof:name":"Heatsafe Industries",
    "wof:placetype":"venue"
},
  "geometry": {"coordinates":[-114.169022,51.083515],"type":"Point"}
}