{
  "type": "Feature",
  "properties": {
    "iso:country":"CA",
    "sg:city":"Vancouver",
    "sg:classifiers":[
        {
            "category":"Shopping",
            "subcategory":"Shoes",
            "type":"Retail Goods"
        }
    ],
    "sg:phone":"+1 604 689 8378",
    "sg:postcode":"V6E 3P3",
    "sg:province":"BC",
    "wof:name":"Valentini Shoes",
    "wof:placetype":"venue"
},
  "geometry": {"coordinates":[-123.122123718,49.2852706909],"type":"Point"}
}