{
  "type": "Feature",
  "properties": {
    "addr:full":"St Ambroise MB R0H 1G0",
    "addr:postcode":"r0h 1g0",
    "addr:street":"St Ambroise",
    "iso:country":"CA",
    "sg:city":"St Ambroise",
    "sg:classifiers":[
        {
            "category":"Food & Beverages",
            "subcategory":"Groceries & Convenience Stores",
            "type":"Retail Goods"
        }
    ],
    "sg:phone":"+1 204 243 2631",
    "sg:postcode":"R0H 1G0",
    "sg:province":"MB",
    "sg:tags":[
        "grocer"
    ],
    "wof:name":"Ducharme's General Store",
    "wof:placetype":"venue"
},
  "geometry": {"coordinates":[-98.043739,50.2603],"type":"Point"}
}