{
  "type": "Feature",
  "properties": {
    "iso:country":"CA",
    "sg:address":"126 Gore Ave",
    "sg:city":"Vancouver",
    "sg:classifiers":[
        {
            "category":"Manufacturing",
            "subcategory":"Pet Food",
            "type":"Manufacturing & Wholesale Goods"
        }
    ],
    "sg:phone":"+1 604 687 4204",
    "sg:postcode":"V6A 2Y9",
    "sg:province":"BC",
    "sg:tags":[
        "rice",
        "mills"
    ],
    "wof:name":"China Cereals & Oils Corp Ltd",
    "wof:placetype":"venue"
},
  "geometry": {"coordinates":[-123.097564697,49.28383255],"type":"Point"}
}