{
  "type": "Feature",
  "properties": {
    "addr:full":"19 Ottawa St N Kitchener ON N2H 3K2",
    "addr:housenumber":"19",
    "addr:postcode":"n2h 3k2",
    "addr:street":"Ottawa St N",
    "iso:country":"CA",
    "sg:address":"19 Ottawa St N",
    "sg:city":"Kitchener",
    "sg:classifiers":[
        {
            "category":"Organizations",
            "subcategory":"Religious Organization",
            "type":"Services"
        }
    ],
    "sg:phone":"+1 519 745 5144",
    "sg:postcode":"N2H 3K2",
    "sg:province":"ON",
    "sg:tags":[
        "church"
    ],
    "wof:name":"Kitchener Mennonite Brethern",
    "wof:placetype":"venue"
},
  "geometry": {"coordinates":[-80.47026062010001,43.4424972534],"type":"Point"}
}