{
  "type": "Feature",
  "properties": {
    "addr:full":"Montreal QC H4P 2S8",
    "addr:postcode":"h4p 2s8",
    "iso:country":"CA",
    "sg:city":"Montreal",
    "sg:classifiers":[
        {
            "category":"Wholesale",
            "subcategory":"Construction Materials",
            "type":"Manufacturing & Wholesale Goods"
        }
    ],
    "sg:phone":"+1 514 344 4531",
    "sg:postcode":"H4P 2S8",
    "sg:province":"QC",
    "sg:tags":[
        "granite"
    ],
    "wof:name":"Summum Granit Inc",
    "wof:placetype":"venue"
},
  "geometry": {"coordinates":[-73.65991200000001,45.498131],"type":"Point"}
}