{
  "type": "Feature",
  "properties": {
    "iso:country":"CA",
    "sg:address":"998 Mckinnon Rd",
    "sg:city":"Williams Lake",
    "sg:classifiers":[
        {
            "category":"Food & Beverages",
            "subcategory":"Groceries & Convenience Stores",
            "type":"Retail Goods"
        }
    ],
    "sg:phone":"+1 250 398 7892",
    "sg:postcode":"V2G 2L3",
    "sg:province":"BC",
    "sg:tags":[
        "grocer"
    ],
    "wof:name":"Handi-Mart",
    "wof:placetype":"venue"
},
  "geometry": {"coordinates":[-122.13609314,52.1394844055],"type":"Point"}
}