{
  "type": "Feature",
  "properties": {
    "addr:full":"6640 3E Av O Charlesbourg QC G1H 6H4",
    "addr:housenumber":"6640",
    "addr:postcode":"g1h 6h4",
    "addr:street":"3E Av O",
    "iso:country":"CA",
    "sg:address":"6640 3E Av O",
    "sg:city":"Charlesbourg",
    "sg:classifiers":[
        {
            "category":"Organizations",
            "subcategory":"Religious Organization",
            "type":"Services"
        }
    ],
    "sg:phone":"+1 418 623 7077",
    "sg:postcode":"G1H 6H4",
    "sg:province":"QC",
    "sg:tags":[
        "church"
    ],
    "wof:name":"Aujourd'Hui L'Espoir",
    "wof:placetype":"venue"
},
  "geometry": {"coordinates":[-71.2565536499,46.8560409546],"type":"Point"}
}