{
  "type": "Feature",
  "properties": {
    "addr:full":"424 W 4th St Vanderhoof BC V0J 3A0",
    "addr:housenumber":"424",
    "addr:postcode":"v0j 3a0",
    "addr:street":"W 4Th St",
    "iso:country":"CA",
    "sg:address":"424 W 4th St",
    "sg:city":"Vanderhoof",
    "sg:classifiers":[
        {
            "category":"Professional",
            "subcategory":"Business Services",
            "type":"Services"
        }
    ],
    "sg:phone":"+1 250 567 9479",
    "sg:postcode":"V0J 3A0",
    "sg:province":"BC",
    "sg:tags":[
        "process",
        "server"
    ],
    "wof:name":"Nechako Valley Legal Document",
    "wof:placetype":"venue"
},
  "geometry": {"coordinates":[-124.016357422,54.0113067627],"type":"Point"}
}