{
  "type": "Feature",
  "properties": {
    "addr:full":"21 Kenneth St Duncan BC V9L 1N3",
    "addr:housenumber":"21",
    "addr:postcode":"v9l 1n3",
    "addr:street":"Kenneth St",
    "iso:country":"CA",
    "sg:address":"21 Kenneth St",
    "sg:city":"Duncan",
    "sg:classifiers":[
        {
            "category":"Restaurant",
            "type":"Food & Drink"
        }
    ],
    "sg:phone":"+1 250 748 0144",
    "sg:postcode":"V9L 1N3",
    "sg:province":"BC",
    "sg:tags":[
        "delicatessen"
    ],
    "wof:name":"Tulip Imports & Delicatessen",
    "wof:placetype":"venue"
},
  "geometry": {"coordinates":[-123.707489014,48.7786941528],"type":"Point"}
}