{
  "type": "Feature",
  "properties": {
    "addr:full":"Prince George BC V2L 1N2",
    "addr:postcode":"v2l 1n2",
    "iso:country":"CA",
    "sg:city":"Prince George",
    "sg:classifiers":[
        {
            "category":"Organizations",
            "subcategory":"Labor Organization",
            "type":"Services"
        }
    ],
    "sg:phone":"+1 250 563 5346",
    "sg:postcode":"V2L 1N2",
    "sg:province":"BC",
    "wof:name":"Teamsters Local 31",
    "wof:placetype":"venue"
},
  "geometry": {"coordinates":[-122.743095,53.894341],"type":"Point"}
}