{
  "type": "Feature",
  "properties": {
    "addr:full":"451 Rue Des Faconniers Rimouski QC G5M 1X2",
    "addr:housenumber":"451",
    "addr:postcode":"g5m 1x2",
    "addr:street":"Rue Des Faconniers",
    "iso:country":"CA",
    "sg:address":"451 Rue Des Faconniers",
    "sg:city":"Rimouski",
    "sg:classifiers":[
        {
            "category":"Wholesale",
            "subcategory":"Hardware",
            "type":"Manufacturing & Wholesale Goods"
        }
    ],
    "sg:phone":"+1 418 723 6515",
    "sg:postcode":"G5M 1X2",
    "sg:province":"QC",
    "sg:tags":[
        "plumbing",
        "fixture",
        "supply"
    ],
    "wof:name":"Deschenes & Fils Ltee",
    "wof:placetype":"venue"
},
  "geometry": {"coordinates":[-68.52467300000001,48.449295],"type":"Point"}
}