{
  "type": "Feature",
  "properties": {
    "addr:full":"Hwy 16 Russell MB R0J 1W0",
    "addr:postcode":"r0j 1w0",
    "addr:street":"Hwy 16",
    "iso:country":"CA",
    "sg:address":"Hwy 16",
    "sg:city":"Russell",
    "sg:classifiers":[
        {
            "category":"Manufacturing",
            "subcategory":"Tools & Machinery",
            "type":"Manufacturing & Wholesale Goods"
        }
    ],
    "sg:phone":"+1 204 773 3265",
    "sg:postcode":"R0J 1W0",
    "sg:province":"MB",
    "sg:tags":[
        "machine",
        "shop"
    ],
    "wof:name":"Tremaine Services",
    "wof:placetype":"venue"
},
  "geometry": {"coordinates":[-101.280151,50.771774],"type":"Point"}
}