{
  "type": "Feature",
  "properties": {
    "addr:full":"3369 Portage Ave Winnipeg MB R3K 0W9",
    "addr:housenumber":"3369",
    "addr:postcode":"r3k 0w9",
    "addr:street":"Portage Ave",
    "iso:country":"CA",
    "sg:address":"3369 Portage Ave",
    "sg:city":"Winnipeg",
    "sg:classifiers":[
        {
            "category":"Banks & Credit Unions",
            "subcategory":"Bank",
            "type":"Services"
        }
    ],
    "sg:phone":"+1 204 944 6029",
    "sg:postcode":"R3K 0W9",
    "sg:province":"MB",
    "wof:name":"Cibc",
    "wof:placetype":"venue"
},
  "geometry": {"coordinates":[-97.297432,49.882595],"type":"Point"}
}