{
  "type": "Feature",
  "properties": {
    "addr:full":"1615 Orleans Blvd Orleans ON K1C 7E2",
    "addr:housenumber":"1615",
    "addr:postcode":"k1c 7e2",
    "addr:street":"Orleans Blvd",
    "iso:country":"CA",
    "sg:address":"1615 Orleans Blvd",
    "sg:city":"Orleans",
    "sg:classifiers":[
        {
            "category":"Restaurant",
            "type":"Food & Drink"
        }
    ],
    "sg:phone":"+1 613 830 3314",
    "sg:postcode":"K1C 7E2",
    "sg:province":"ON",
    "wof:name":"Broadway Bar & Grill",
    "wof:placetype":"venue"
},
  "geometry": {"coordinates":[-75.525093,45.459766],"type":"Point"}
}