{
  "type": "Feature",
  "properties": {
    "addr:full":"Toronto ON M5V 1P9",
    "addr:postcode":"m5v 1p9",
    "iso:country":"CA",
    "sg:city":"Toronto",
    "sg:classifiers":[
        {
            "category":"Shopping",
            "subcategory":"Computers & Home Electronics",
            "type":"Retail Goods"
        }
    ],
    "sg:phone":"+1 416 217 0381",
    "sg:postcode":"M5V 1P9",
    "sg:province":"ON",
    "sg:tags":[
        "equipment",
        "dealer"
    ],
    "wof:name":"Mac Library Technology Inc",
    "wof:placetype":"venue"
},
  "geometry": {"coordinates":[-79.39221999999999,43.647293],"type":"Point"}
}