{
  "type": "Feature",
  "properties": {
    "addr:full":"York ON M6M 1S6",
    "addr:postcode":"m6m 1s6",
    "iso:country":"CA",
    "sg:city":"York",
    "sg:classifiers":[
        {
            "category":"Education",
            "subcategory":"Special Training",
            "type":"Public Place"
        }
    ],
    "sg:phone":"+1 416 757 6523",
    "sg:postcode":"M6M 1S6",
    "sg:province":"ON",
    "sg:tags":[
        "instruction",
        "music"
    ],
    "wof:name":"Music Masters Education Ctr",
    "wof:placetype":"venue"
},
  "geometry": {"coordinates":[-79.4661407471,43.6919784546],"type":"Point"}
}