{
  "type": "Feature",
  "properties": {
    "addr:full":"Calgary AB T3C 0K1",
    "addr:postcode":"t3c 0k1",
    "iso:country":"CA",
    "sg:city":"Calgary",
    "sg:classifiers":[
        {
            "category":"Banks & Credit Unions",
            "subcategory":"Investment Brokerage",
            "type":"Services"
        }
    ],
    "sg:phone":"+1 403 277 0065",
    "sg:postcode":"T3C 0K1",
    "sg:province":"AB",
    "sg:tags":[
        "advisory",
        "financial"
    ],
    "wof:name":"Westcana Management & Realty",
    "wof:placetype":"venue"
},
  "geometry": {"coordinates":[-114.099915,51.044216],"type":"Point"}
}