{
  "type": "Feature",
  "properties": {
    "addr:full":"4484 97 St NW Edmonton AB T6E 5R9",
    "addr:housenumber":"4484",
    "addr:postcode":"t6e 5r9",
    "addr:street":"97 St Nw",
    "iso:country":"CA",
    "sg:address":"4484 97 St NW",
    "sg:city":"Edmonton",
    "sg:classifiers":[
        {
            "category":"Wholesale",
            "subcategory":"Hardware",
            "type":"Manufacturing & Wholesale Goods"
        }
    ],
    "sg:phone":"+1 780 434 3666",
    "sg:postcode":"T6E 5R9",
    "sg:province":"AB",
    "sg:tags":[
        "nut",
        "bolt"
    ],
    "wof:name":"Edmonton Fasteners & Tools Ltd",
    "wof:placetype":"venue"
},
  "geometry": {"coordinates":[-113.47959136999999,53.4825172424],"type":"Point"}
}