{
  "type": "Feature",
  "properties": {
    "addr:full":"100 Emmett Ave York ON M6M 2E6",
    "addr:housenumber":"100",
    "addr:postcode":"m6m 2e6",
    "addr:street":"Emmett Ave",
    "iso:country":"CA",
    "sg:address":"100 Emmett Ave",
    "sg:city":"York",
    "sg:classifiers":[
        {
            "category":"Education",
            "subcategory":"School",
            "type":"Public Place"
        }
    ],
    "sg:phone":"+1 416 394 3280",
    "sg:postcode":"M6M 2E6",
    "sg:province":"ON",
    "wof:name":"York Humber High School",
    "wof:placetype":"venue"
},
  "geometry": {"coordinates":[-79.507408,43.687355],"type":"Point"}
}