{
  "type": "Feature",
  "properties": {
    "addr:full":"7229 Pacific Cir Mississauga ON L5T 1S9",
    "addr:housenumber":"7229",
    "addr:postcode":"l5t 1s9",
    "addr:street":"Pacific Cir",
    "iso:country":"CA",
    "sg:address":"7229 Pacific Cir",
    "sg:city":"Mississauga",
    "sg:classifiers":[
        {
            "category":"Professional",
            "subcategory":"Lawyer & Legal Services",
            "type":"Services"
        }
    ],
    "sg:phone":"+1 905 795 4040",
    "sg:postcode":"L5T 1S9",
    "sg:province":"ON",
    "sg:tags":[
        "attorney"
    ],
    "wof:name":"Eades Law Office",
    "wof:placetype":"venue"
},
  "geometry": {"coordinates":[-79.681541,43.657928],"type":"Point"}
}