{
  "type": "Feature",
  "properties": {
    "addr:full":"Hudson QC J0P 1H0",
    "addr:postcode":"j0p 1h0",
    "iso:country":"CA",
    "sg:city":"Hudson",
    "sg:classifiers":[
        {
            "category":"Wholesale",
            "subcategory":"Electrical",
            "type":"Manufacturing & Wholesale Goods"
        }
    ],
    "sg:phone":"+1 450 458 8826",
    "sg:postcode":"J0P 1H0",
    "sg:province":"QC",
    "sg:tags":[
        "control"
    ],
    "wof:name":"Kesseltronics Systems Corp",
    "wof:placetype":"venue"
},
  "geometry": {"coordinates":[-74.1396484375,45.45936203],"type":"Point"}
}