{
  "type": "Feature",
  "properties": {
    "addr:full":"1447 Ch Royal Saint-Pierre-Ile-D'Orleans QC G0A 4E0",
    "addr:postcode":"1447;g0a 4e0",
    "addr:street":"Ch Royal Saint-Pierre-Ile-D'Orleans",
    "iso:country":"CA",
    "sg:address":"1447 Ch Royal",
    "sg:city":"Saint-Pierre-Ile-D'Orleans",
    "sg:classifiers":[
        {
            "category":"Recreation",
            "type":"Entertainment"
        }
    ],
    "sg:phone":"+1 418 828 1269",
    "sg:postcode":"G0A 4E0",
    "sg:province":"QC",
    "sg:tags":[
        "sugar",
        "syrup",
        "hall",
        "maple",
        "auditorium"
    ],
    "wof:name":"Entailleur Inc",
    "wof:placetype":"venue"
},
  "geometry": {"coordinates":[-70.903893,46.913807],"type":"Point"}
}