{
  "type": "Feature",
  "properties": {
    "iso:country":"CA",
    "sg:address":"131 Morin St",
    "sg:city":"St Joseph",
    "sg:classifiers":[
        {
            "category":"Retail",
            "subcategory":"Repair Shop",
            "type":"Services"
        }
    ],
    "sg:phone":"+1 204 737 2234",
    "sg:postcode":"R0G 2C0",
    "sg:province":"MB",
    "sg:tags":[
        "welding"
    ],
    "wof:name":"Bonin Welding Ltd",
    "wof:placetype":"venue"
},
  "geometry": {"coordinates":[-97.3921203613,49.1426582336],"type":"Point"}
}