{
  "type": "Feature",
  "properties": {
    "addr:full":"774 Rue Berlinguet Cap-DE-LA-Madeleine QC G8T 2H2",
    "addr:housenumber":"774",
    "addr:postcode":"g8t 2h2",
    "addr:street":"Rue Berlinguet",
    "iso:country":"CA",
    "sg:address":"774 Rue Berlinguet",
    "sg:city":"Cap-DE-LA-Madeleine",
    "sg:classifiers":[
        {
            "category":"Building & Trades",
            "subcategory":"Construction",
            "type":"Services"
        }
    ],
    "sg:phone":"+1 819 375 8477",
    "sg:postcode":"G8T 2H2",
    "sg:province":"QC",
    "sg:tags":[
        "general",
        "contractor"
    ],
    "wof:name":"L A Brouillette Ltee",
    "wof:placetype":"venue"
},
  "geometry": {"coordinates":[-72.535904,46.378979],"type":"Point"}
}