{
  "type": "Feature",
  "properties": {
    "addr:full":"Campbellville ON L0P 1B0",
    "addr:postcode":"l0p 1b0",
    "iso:country":"CA",
    "sg:city":"Campbellville",
    "sg:classifiers":[
        {
            "category":"Professional",
            "subcategory":"Business Services",
            "type":"Services"
        }
    ],
    "sg:phone":"+1 905 854 4451",
    "sg:postcode":"L0P 1B0",
    "sg:province":"ON",
    "sg:tags":[
        "interior",
        "consultant",
        "design",
        "decorator"
    ],
    "wof:name":"Carriage Hill Interiors Ltd",
    "wof:placetype":"venue"
},
  "geometry": {"coordinates":[-79.9798965454,43.4890708923],"type":"Point"}
}