{
  "type": "Feature",
  "properties": {
    "addr:full":"PO Box 10 Charlottetown NL A0C 1L0",
    "addr:housenumber":"po box 10",
    "addr:postcode":"a0c 1l0",
    "iso:country":"CA",
    "sg:address":"PO Box 10",
    "sg:city":"Charlottetown",
    "sg:classifiers":[
        {
            "category":"Food & Beverages",
            "subcategory":"Groceries & Convenience Stores",
            "type":"Retail Goods"
        }
    ],
    "sg:phone":"+1 709 664 3411",
    "sg:postcode":"A0C 1L0",
    "sg:province":"NL",
    "sg:tags":[
        "merchandise",
        "general"
    ],
    "wof:name":"Spracklins Enterprises Ltd",
    "wof:placetype":"venue"
},
  "geometry": {"coordinates":[-56.1393585205,52.769733429],"type":"Point"}
}