{
  "type": "Feature",
  "properties": {
    "addr:full":"868 Rue DE Puyjalon Baie-Comeau QC G5C 1N1",
    "addr:housenumber":"868",
    "addr:postcode":"g5c 1n1",
    "addr:street":"Rue De Puyjalon",
    "iso:country":"CA",
    "sg:address":"868 Rue DE Puyjalon",
    "sg:city":"Baie-Comeau",
    "sg:classifiers":[
        {
            "category":"Personal",
            "subcategory":"Beauty Salon",
            "type":"Services"
        }
    ],
    "sg:phone":"+1 418 589 2792",
    "sg:postcode":"G5C 1N1",
    "sg:province":"QC",
    "wof:name":"Salon DE Coiffure Maxim'Homme",
    "wof:placetype":"venue"
},
  "geometry": {"coordinates":[-68.25858306879999,49.1918716431],"type":"Point"}
}