{
  "type": "Feature",
  "properties": {
    "addr:full":"10106 Main St Summerland BC V0H 1Z0",
    "addr:housenumber":"10106",
    "addr:postcode":"v0h 1z0",
    "addr:street":"Main St",
    "iso:country":"CA",
    "sg:address":"10106 Main St",
    "sg:city":"Summerland",
    "sg:classifiers":[
        {
            "category":"Shopping",
            "subcategory":"Used Merchandise",
            "type":"Retail Goods"
        }
    ],
    "sg:phone":"+1 250 494 3214",
    "sg:postcode":"V0H 1Z0",
    "sg:province":"BC",
    "sg:tags":[
        "antique"
    ],
    "wof:name":"Carousel",
    "wof:placetype":"venue"
},
  "geometry": {"coordinates":[-119.682922,49.601559],"type":"Point"}
}