{
  "type": "Feature",
  "properties": {
    "addr:full":"207 Hurontario St Collingwood ON L9Y 2M1",
    "addr:housenumber":"207",
    "addr:postcode":"l9y 2m1",
    "addr:street":"Hurontario St",
    "iso:country":"CA",
    "sg:address":"207 Hurontario St",
    "sg:city":"Collingwood",
    "sg:classifiers":[
        {
            "category":"Shopping",
            "subcategory":"Florist",
            "type":"Retail Goods"
        }
    ],
    "sg:phone":"+1 705 444 0614",
    "sg:postcode":"L9Y 2M1",
    "sg:province":"ON",
    "wof:name":"Blue Mountain Flowers",
    "wof:placetype":"venue"
},
  "geometry": {"coordinates":[-80.21623200000001,44.497807],"type":"Point"}
}