{
  "type": "Feature",
  "properties": {
    "iso:country":"CA",
    "sg:address":"52 Scott St W # 4",
    "sg:city":"St Catharines",
    "sg:classifiers":[
        {
            "category":"Retail",
            "subcategory":"Auto Repair",
            "type":"Services"
        }
    ],
    "sg:phone":"+1 905 687 4044",
    "sg:postcode":"L2R 1C9",
    "sg:province":"ON",
    "sg:tags":[
        "repairing",
        "automobile"
    ],
    "wof:name":"Lincoln Valley Automotive Ltd",
    "wof:placetype":"venue"
},
  "geometry": {"coordinates":[-79.26261901860001,43.1767463684],"type":"Point"}
}