{
  "type": "Feature",
  "properties": {
    "iso:country":"CA",
    "sg:address":"340 Gerrard St E",
    "sg:city":"Toronto",
    "sg:classifiers":[
        {
            "category":"Communications",
            "subcategory":"Film & Video Production",
            "type":"Services"
        }
    ],
    "sg:phone":"+1 416 921 4166",
    "sg:postcode":"M5A 2G7",
    "sg:province":"ON",
    "sg:tags":[
        "consultant",
        "taping"
    ],
    "wof:name":"Galaviz & Hauver Productions",
    "wof:placetype":"venue"
},
  "geometry": {"coordinates":[-79.3651809692,43.6624717712],"type":"Point"}
}