{
  "type": "Feature",
  "properties": {
    "addr:full":"Kingston ON K7M 4Y2",
    "addr:postcode":"k7m 4y2",
    "iso:country":"CA",
    "sg:city":"Kingston",
    "sg:classifiers":[
        {
            "category":"Organizations",
            "subcategory":"Labor Organization",
            "type":"Services"
        }
    ],
    "sg:phone":"+1 613 384 2269",
    "sg:postcode":"K7M 4Y2",
    "sg:province":"ON",
    "wof:name":"Sheet Metal Workers Intl",
    "wof:placetype":"venue"
},
  "geometry": {"coordinates":[-76.54108428959999,44.2381515503],"type":"Point"}
}