{
  "type": "Feature",
  "properties": {
    "addr:full":"8 Portage St St George NB E5C 3L4",
    "addr:housenumber":"8",
    "addr:postcode":"e5c 3l4",
    "addr:street":"Portage St",
    "iso:country":"CA",
    "sg:address":"8 Portage St",
    "sg:city":"St George",
    "sg:classifiers":[
        {
            "category":"Shopping",
            "subcategory":"Clothing, Apparel, & Fashions",
            "type":"Retail Goods"
        }
    ],
    "sg:phone":"+1 506 755 2751",
    "sg:postcode":"E5C 3L4",
    "sg:province":"NB",
    "sg:tags":[
        "shop",
        "boutique",
        "gift"
    ],
    "wof:name":"Charlotte's Webb",
    "wof:placetype":"venue"
},
  "geometry": {"coordinates":[-66.824471,45.128963],"type":"Point"}
}