{
  "type": "Feature",
  "properties": {
    "addr:full":"1405 Hwy 9 Mildmay ON N0G 2J0",
    "addr:housenumber":"1405",
    "addr:postcode":"n0g 2j0",
    "addr:street":"Hwy 9 Mildmay",
    "iso:country":"CA",
    "sg:address":"1405 Hwy 9",
    "sg:city":"Mildmay",
    "sg:classifiers":[
        {
            "category":"Wholesale",
            "subcategory":"Machinery & Supplies",
            "type":"Manufacturing & Wholesale Goods"
        }
    ],
    "sg:phone":"+1 519 367 2672",
    "sg:postcode":"N0G 2J0",
    "sg:province":"ON",
    "sg:tags":[
        "farm",
        "equipment"
    ],
    "wof:name":"Stolz Sales & Svc",
    "wof:placetype":"venue"
},
  "geometry": {"coordinates":[-81.1149215698,44.0401916504],"type":"Point"}
}