{
  "type": "Feature",
  "properties": {
    "addr:full":"1005 Lansdowne Ave Toronto ON M6H 4E9",
    "addr:housenumber":"1005",
    "addr:postcode":"m6h 4e9",
    "addr:street":"Lansdowne Ave",
    "iso:country":"CA",
    "sg:address":"1005 Lansdowne Ave",
    "sg:city":"Toronto",
    "sg:classifiers":[
        {
            "category":"Food & Beverages",
            "subcategory":"Bakery",
            "type":"Retail Goods"
        }
    ],
    "sg:phone":"+1 416 588 2760",
    "sg:postcode":"M6H 4E9",
    "sg:province":"ON",
    "sg:tags":[
        "doughnut"
    ],
    "wof:name":"Coffee Time Donuts",
    "wof:placetype":"venue"
},
  "geometry": {"coordinates":[-79.4463729858,43.667049408],"type":"Point"}
}