{
  "type": "Feature",
  "properties": {
    "addr:full":"111 Ave B W Wynyard SK S0A 4T0",
    "addr:postcode":"s0a 4t0",
    "addr:street":"111 Ave B W Wynyard",
    "iso:country":"CA",
    "sg:address":"111 Ave B W",
    "sg:city":"Wynyard",
    "sg:classifiers":[
        {
            "category":"Home & Garden",
            "subcategory":"Building Materials",
            "type":"Retail Goods"
        }
    ],
    "sg:phone":"+1 306 554 2233",
    "sg:postcode":"S0A 4T0",
    "sg:province":"SK",
    "wof:name":"Home Building Ctr",
    "wof:placetype":"venue"
},
  "geometry": {"coordinates":[-104.18665313699999,51.7705459595],"type":"Point"}
}