{
  "type": "Feature",
  "properties": {
    "addr:full":"511 3rd St SW Black Diamond AB T0L 0H0",
    "addr:housenumber":"511",
    "addr:postcode":"t0l 0h0",
    "addr:street":"3Rd St Sw",
    "iso:country":"CA",
    "sg:address":"511 3rd St SW",
    "sg:city":"Black Diamond",
    "sg:classifiers":[
        {
            "category":"Education",
            "subcategory":"School",
            "type":"Public Place"
        }
    ],
    "sg:phone":"+1 403 933 4373",
    "sg:postcode":"T0L 0H0",
    "sg:province":"AB",
    "wof:name":"Oilfields High School",
    "wof:placetype":"venue"
},
  "geometry": {"coordinates":[-114.238510132,50.68359375],"type":"Point"}
}