{
  "type": "Feature",
  "properties": {
    "addr:full":"22 Wentworth St Dartmouth NS B2Y 2S6",
    "addr:housenumber":"22",
    "addr:postcode":"b2y 2s6",
    "addr:street":"Wentworth St",
    "iso:country":"CA",
    "sg:address":"22 Wentworth St",
    "sg:city":"Dartmouth",
    "sg:classifiers":[
        {
            "category":"Retail",
            "subcategory":"Animal Services",
            "type":"Services"
        }
    ],
    "sg:phone":"+1 902 463 6287",
    "sg:postcode":"B2Y 2S6",
    "sg:province":"NS",
    "sg:tags":[
        "pet",
        "grooming",
        "washing"
    ],
    "wof:name":"Debbie's Dog Boutique",
    "wof:placetype":"venue"
},
  "geometry": {"coordinates":[-63.566185,44.666519],"type":"Point"}
}