{
  "type": "Feature",
  "properties": {
    "iso:country":"CA",
    "sg:address":"4928 49 St",
    "sg:city":"Rocky Mountain House",
    "sg:classifiers":[
        {
            "category":"Social Services",
            "type":"Services"
        }
    ],
    "sg:phone":"+1 403 845 5609",
    "sg:postcode":"T4T 1C2",
    "sg:province":"AB",
    "sg:tags":[
        "youth",
        "organization",
        "center"
    ],
    "wof:name":"Clearwater Boys & Girls Club",
    "wof:placetype":"venue"
},
  "geometry": {"coordinates":[-114.91795349100001,52.3731842041],"type":"Point"}
}