{
  "type": "Feature",
  "properties": {
    "addr:full":"227 Rue Larochelle Asbestos QC J1T 3M7",
    "addr:housenumber":"227",
    "addr:postcode":"j1t 3m7",
    "addr:street":"Rue Larochelle",
    "iso:country":"CA",
    "sg:address":"227 Rue Larochelle",
    "sg:city":"Asbestos",
    "sg:classifiers":[
        {
            "category":"Travel",
            "subcategory":"Campground",
            "type":"Entertainment"
        }
    ],
    "sg:phone":"+1 819 879 5000",
    "sg:postcode":"J1T 3M7",
    "sg:province":"QC",
    "wof:name":"Villa Du Campeur Des Trois Lac",
    "wof:placetype":"venue"
},
  "geometry": {"coordinates":[-71.8844070435,45.7998847961],"type":"Point"}
}