{
  "type": "Feature",
  "properties": {
    "addr:full":"83 Sufian Rd Pembroke ON K8A 6W6",
    "addr:housenumber":"83",
    "addr:postcode":"k8a 6w6",
    "addr:street":"Sufian Rd",
    "iso:country":"CA",
    "sg:address":"83 Sufian Rd",
    "sg:city":"Pembroke",
    "sg:classifiers":[
        {
            "category":"Education",
            "subcategory":"Dance Studio",
            "type":"Public Place"
        }
    ],
    "sg:phone":"+1 613 732 8721",
    "sg:postcode":"K8A 6W6",
    "sg:province":"ON",
    "sg:tags":[
        "instruction",
        "dancing"
    ],
    "wof:name":"Croy School of Ballet",
    "wof:placetype":"venue"
},
  "geometry": {"coordinates":[-77.112213,45.826481],"type":"Point"}
}