{
  "type": "Feature",
  "properties": {
    "iso:country":"CA",
    "sg:address":"784 Whitney Dr",
    "sg:city":"Mississauga",
    "sg:classifiers":[
        {
            "category":"Professional",
            "subcategory":"Art Services",
            "type":"Services"
        }
    ],
    "sg:phone":"+1 905 848 4632",
    "sg:postcode":"L4Y 1E3",
    "sg:province":"ON",
    "sg:tags":[
        "artist"
    ],
    "wof:name":"Lightfoot Art & Design Inc",
    "wof:placetype":"venue"
},
  "geometry": {"coordinates":[-79.584091,43.586437],"type":"Point"}
}