{
  "type": "Feature",
  "properties": {
    "addr:full":"1000 Rue Woodland Verdun QC H4H 1V9",
    "addr:housenumber":"1000",
    "addr:postcode":"h4h 1v9",
    "addr:street":"Rue Woodland",
    "iso:country":"CA",
    "sg:address":"1000 Rue Woodland",
    "sg:city":"Verdun",
    "sg:classifiers":[
        {
            "category":"Autos & Motor Vehicles",
            "subcategory":"Automobile Sales",
            "type":"Retail Goods"
        }
    ],
    "sg:phone":"+1 514 761 3444",
    "sg:postcode":"H4H 1V9",
    "sg:province":"QC",
    "sg:tags":[
        "car",
        "dealer"
    ],
    "wof:name":"Woodland Toyota",
    "wof:placetype":"venue"
},
  "geometry": {"coordinates":[-73.577629,45.452579],"type":"Point"}
}