{
  "type": "Feature",
  "properties": {
    "iso:country":"CA",
    "sg:city":"Medicine Hat",
    "sg:classifiers":[
        {
            "category":"Building & Trades",
            "subcategory":"Construction",
            "type":"Services"
        }
    ],
    "sg:phone":"+1 403 529 1688",
    "sg:postcode":"T1B 3M6",
    "sg:province":"AB",
    "sg:tags":[
        "concrete",
        "contractor"
    ],
    "wof:name":"Eckes Concrete",
    "wof:placetype":"venue"
},
  "geometry": {"coordinates":[-110.647575378,50.0060348511],"type":"Point"}
}