{
  "type": "Feature",
  "properties": {
    "addr:full":"13648 105A Ave Surrey BC V3T 2B3",
    "addr:housenumber":"13648",
    "addr:postcode":"v3t 2b3",
    "addr:street":"105A Ave",
    "iso:country":"CA",
    "sg:address":"13648 105A Ave",
    "sg:city":"Surrey",
    "sg:classifiers":[
        {
            "category":"Restaurant",
            "type":"Food & Drink"
        }
    ],
    "sg:phone":"+1 604 585 2288",
    "sg:postcode":"V3T 2B3",
    "sg:province":"BC",
    "wof:name":"New King DO Szechuan Seafood",
    "wof:placetype":"venue"
},
  "geometry": {"coordinates":[-122.830215,49.105179],"type":"Point"}
}