{
  "type": "Feature",
  "properties": {
    "addr:full":"3057 Grandview Hwy Vancouver BC V5M 2E4",
    "addr:housenumber":"3057",
    "addr:postcode":"v5m 2e4",
    "addr:street":"Grandview Hwy",
    "iso:country":"CA",
    "sg:address":"3057 Grandview Hwy",
    "sg:city":"Vancouver",
    "sg:classifiers":[
        {
            "category":"Home & Garden",
            "subcategory":"Furniture",
            "type":"Retail Goods"
        }
    ],
    "sg:phone":"+1 604 430 8899",
    "sg:postcode":"V5M 2E4",
    "sg:province":"BC",
    "wof:name":"United Furniture Warehouse",
    "wof:placetype":"venue"
},
  "geometry": {"coordinates":[-123.040176,49.258385],"type":"Point"}
}