{
  "type": "Feature",
  "properties": {
    "iso:country":"CA",
    "sg:address":"1670 Commercial Dr",
    "sg:city":"Vancouver",
    "sg:classifiers":[
        {
            "category":"Restaurant",
            "type":"Food & Drink"
        }
    ],
    "sg:phone":"+1 604 253 8224",
    "sg:postcode":"V5L 3Y4",
    "sg:province":"BC",
    "sg:tags":[
        "shop",
        "coffee"
    ],
    "wof:name":"Caffe Bella Napoli",
    "wof:placetype":"venue"
},
  "geometry": {"coordinates":[-123.069488525,49.2698822021],"type":"Point"}
}