{
  "type": "Feature",
  "properties": {
    "addr:full":"Montreal QC H1K 2V8",
    "addr:postcode":"h1k 2v8",
    "iso:country":"CA",
    "sg:city":"Montreal",
    "sg:classifiers":[
        {
            "category":"Education",
            "subcategory":"School",
            "type":"Public Place"
        }
    ],
    "sg:phone":"+1 514 596 5040",
    "sg:postcode":"H1K 2V8",
    "sg:province":"QC",
    "wof:name":"Ecole St-Justin",
    "wof:placetype":"venue"
},
  "geometry": {"coordinates":[-73.55438995359999,45.5122871399],"type":"Point"}
}