{
  "type": "Feature",
  "properties": {
    "addr:full":"3704 32E Av Pointe-Aux-Trembles QC H1A 3M2",
    "addr:housenumber":"3704",
    "addr:postcode":"h1a 3m2",
    "addr:street":"32E Av Pointe-Aux-Trembles",
    "iso:country":"CA",
    "sg:address":"3704 32E Av",
    "sg:city":"Pointe-Aux-Trembles",
    "sg:classifiers":[
        {
            "category":"Building & Trades",
            "subcategory":"Construction",
            "type":"Services"
        }
    ],
    "sg:phone":"+1 514 644 8824",
    "sg:postcode":"H1A 3M2",
    "sg:province":"QC",
    "sg:tags":[
        "roofing",
        "contractor"
    ],
    "wof:name":"Cnf Couvreur",
    "wof:placetype":"venue"
},
  "geometry": {"coordinates":[-73.5149230957,45.6592674255],"type":"Point"}
}