{
  "type": "Feature",
  "properties": {
    "addr:full":"102 Christina St S Sarnia ON N7T 2M6",
    "addr:housenumber":"102",
    "addr:postcode":"n7t 2m6",
    "addr:street":"Christina St S",
    "iso:country":"CA",
    "sg:address":"102 Christina St S",
    "sg:city":"Sarnia",
    "sg:classifiers":[
        {
            "category":"Wholesale",
            "subcategory":"Vending Machines",
            "type":"Manufacturing & Wholesale Goods"
        }
    ],
    "sg:phone":"+1 519 332 4591",
    "sg:postcode":"N7T 2M6",
    "sg:province":"ON",
    "wof:name":"D & J's Vending",
    "wof:placetype":"venue"
},
  "geometry": {"coordinates":[-82.407715,42.970581],"type":"Point"}
}