{
  "type": "Feature",
  "properties": {
    "iso:country":"CA",
    "sg:address":"4020 Dundas St W",
    "sg:city":"York",
    "sg:classifiers":[
        {
            "category":"Social Services",
            "subcategory":"Child Care",
            "type":"Services"
        }
    ],
    "sg:phone":"+1 416 762 1295",
    "sg:postcode":"M6S 4W6",
    "sg:province":"ON",
    "wof:name":"Copper Mills Day Care Ctr",
    "wof:placetype":"venue"
},
  "geometry": {"coordinates":[-79.505661,43.66275],"type":"Point"}
}