{
  "type": "Feature",
  "properties": {
    "addr:full":"731 Ch Riverside Wakefield QC J0X 3G0",
    "addr:housenumber":"731",
    "addr:postcode":"j0x 3g0",
    "addr:street":"Ch Riverside",
    "iso:country":"CA",
    "sg:address":"731 Ch Riverside",
    "sg:city":"Wakefield",
    "sg:classifiers":[
        {
            "category":"Real Estate",
            "subcategory":"Real Estate Agent",
            "type":"Services"
        }
    ],
    "sg:phone":"+1 819 459 2387",
    "sg:postcode":"J0X 3G0",
    "sg:province":"QC",
    "wof:name":"Re/Max Outaouais Ctr Inc",
    "wof:placetype":"venue"
},
  "geometry": {"coordinates":[-75.92845153810001,45.6337051392],"type":"Point"}
}