{
  "type": "Feature",
  "properties": {
    "addr:full":"911 Rue Notre-Dame S Louiseville QC J5V 2L4",
    "addr:housenumber":"911",
    "addr:postcode":"j5v 2l4",
    "addr:street":"Rue Notre-Dame S",
    "iso:country":"CA",
    "sg:address":"911 Rue Notre-Dame S",
    "sg:city":"Louiseville",
    "sg:classifiers":[
        {
            "category":"Real Estate",
            "subcategory":"Real Estate Agent",
            "type":"Services"
        }
    ],
    "sg:phone":"+1 819 228 4430",
    "sg:postcode":"J5V 2L4",
    "sg:province":"QC",
    "sg:tags":[
        "cooperative"
    ],
    "wof:name":"Cooperative DE Solidarite",
    "wof:placetype":"venue"
},
  "geometry": {"coordinates":[-72.923294,46.236588],"type":"Point"}
}