{
  "type": "Feature",
  "properties": {
    "addr:full":"14 Abacus Rd Brampton ON L6T 5B7",
    "addr:housenumber":"14",
    "addr:postcode":"l6t 5b7",
    "addr:street":"Abacus Rd",
    "iso:country":"CA",
    "sg:address":"14 Abacus Rd",
    "sg:city":"Brampton",
    "sg:classifiers":[
        {
            "category":"Professional",
            "subcategory":"Research",
            "type":"Services"
        }
    ],
    "sg:phone":"+1 905 794 2367",
    "sg:postcode":"L6T 5B7",
    "sg:province":"ON",
    "sg:tags":[
        "environmental",
        "ecological",
        "engineer"
    ],
    "wof:name":"Aquafor Beech Ltd",
    "wof:placetype":"venue"
},
  "geometry": {"coordinates":[-79.661293,43.763725],"type":"Point"}
}