{
  "type": "Feature",
  "properties": {
    "iso:country":"CA",
    "sg:address":"3999 Locust Ln",
    "sg:city":"Beamsville",
    "sg:classifiers":[
        {
            "category":"Building & Trades",
            "subcategory":"Construction",
            "type":"Services"
        }
    ],
    "sg:phone":"+1 905 563 8437",
    "sg:postcode":"L0R 1B2",
    "sg:province":"ON",
    "sg:tags":[
        "excavating",
        "contractor"
    ],
    "wof:name":"Earl Walters & Custom Works",
    "wof:placetype":"venue"
},
  "geometry": {"coordinates":[-79.49704742430001,43.1538085938],"type":"Point"}
}