{
  "type": "Feature",
  "properties": {
    "addr:full":"1309 Island Hwy Campbell River BC V9W 8C2",
    "addr:housenumber":"1309",
    "addr:postcode":"v9w 8c2",
    "addr:street":"Island Hwy",
    "iso:country":"CA",
    "sg:address":"1309 Island Hwy",
    "sg:city":"Campbell River",
    "sg:classifiers":[
        {
            "category":"Restaurant",
            "type":"Food & Drink"
        }
    ],
    "sg:phone":"+1 250 286 6120",
    "sg:postcode":"V9W 8C2",
    "sg:province":"BC",
    "wof:name":"Boston Pizza",
    "wof:placetype":"venue"
},
  "geometry": {"coordinates":[-125.245300293,50.0303916931],"type":"Point"}
}