{
  "type": "Feature",
  "properties": {
    "addr:full":"7224 76 Ave NW Edmonton AB T6B 0B2",
    "addr:housenumber":"7224",
    "addr:postcode":"t6b 0b2",
    "addr:street":"76 Ave Nw",
    "iso:country":"CA",
    "sg:address":"7224 76 Ave NW",
    "sg:city":"Edmonton",
    "sg:classifiers":[
        {
            "category":"Wholesale",
            "subcategory":"Hardware",
            "type":"Manufacturing & Wholesale Goods"
        }
    ],
    "sg:phone":"+1 780 466 6611",
    "sg:postcode":"T6B 0B2",
    "sg:province":"AB",
    "sg:tags":[
        "equipment",
        "heating",
        "system"
    ],
    "wof:name":"Qualitec Distributors Inc",
    "wof:placetype":"venue"
},
  "geometry": {"coordinates":[-113.438911,53.512501],"type":"Point"}
}