{
  "type": "Feature",
  "properties": {
    "addr:full":"1688 Water St Miramichi NB E1N 1B1",
    "addr:housenumber":"1688",
    "addr:postcode":"e1n 1b1",
    "addr:street":"Water St",
    "iso:country":"CA",
    "sg:address":"1688 Water St",
    "sg:city":"Miramichi",
    "sg:classifiers":[
        {
            "category":"Restaurant",
            "type":"Food & Drink"
        }
    ],
    "sg:phone":"+1 506 773 3207",
    "sg:postcode":"E1N 1B1",
    "sg:province":"NB",
    "wof:name":"Ben's Lunch Room",
    "wof:placetype":"venue"
},
  "geometry": {"coordinates":[-65.47063446040001,47.0283813477],"type":"Point"}
}