{
  "type": "Feature",
  "properties": {
    "addr:full":"8000 Boul Henri-Bourassa Charlesbourg QC G1G 4C7",
    "addr:housenumber":"8000",
    "addr:postcode":"g1g 4c7",
    "addr:street":"Boul Henri-Bourassa",
    "iso:country":"CA",
    "sg:address":"8000 Boul Henri-Bourassa",
    "sg:city":"Charlesbourg",
    "sg:classifiers":[
        {
            "category":"Restaurant",
            "type":"Food & Drink"
        }
    ],
    "sg:phone":"+1 418 624 9000",
    "sg:postcode":"G1G 4C7",
    "sg:province":"QC",
    "wof:name":"Cage Aux Sports",
    "wof:placetype":"venue"
},
  "geometry": {"coordinates":[-71.268021,46.862724],"type":"Point"}
}