{
  "type": "Feature",
  "properties": {
    "addr:full":"Toronto ON M5C 1W6",
    "addr:postcode":"m5c 1w6",
    "iso:country":"CA",
    "sg:city":"Toronto",
    "sg:classifiers":[
        {
            "category":"Retail",
            "subcategory":"Repair Shop",
            "type":"Services"
        }
    ],
    "sg:phone":"+1 416 366 6182",
    "sg:postcode":"M5C 1W6",
    "sg:province":"ON",
    "sg:tags":[
        "watch"
    ],
    "wof:name":"Prestige Time",
    "wof:placetype":"venue"
},
  "geometry": {"coordinates":[-79.3785934448,43.6512794495],"type":"Point"}
}