{
  "type": "Feature",
  "properties": {
    "iso:country":"CA",
    "sg:address":"620 Railway Ave",
    "sg:city":"Rocanville",
    "sg:classifiers":[
        {
            "category":"Banks & Credit Unions",
            "subcategory":"Investment Brokerage",
            "type":"Services"
        }
    ],
    "sg:phone":"+1 306 645 2777",
    "sg:postcode":"S0A 3L0",
    "sg:province":"SK",
    "sg:tags":[
        "consultant",
        "planning",
        "financial"
    ],
    "wof:name":"Rathgeber Associates",
    "wof:placetype":"venue"
},
  "geometry": {"coordinates":[-101.699920654,50.3824424744],"type":"Point"}
}