{
  "type": "Feature",
  "properties": {
    "addr:full":"Fork River MB R0L 0V0",
    "addr:postcode":"r0l 0v0",
    "iso:country":"CA",
    "sg:city":"Fork River",
    "sg:classifiers":[
        {
            "category":"Professional",
            "subcategory":"Accounting & Tax Preparation",
            "type":"Services"
        }
    ],
    "sg:phone":"+1 204 657 2381",
    "sg:postcode":"R0L 0V0",
    "sg:province":"MB",
    "sg:tags":[
        "return",
        "filing"
    ],
    "wof:name":"C J's Income Tax Svc",
    "wof:placetype":"venue"
},
  "geometry": {"coordinates":[-100.01811981199999,51.5120544434],"type":"Point"}
}