{
  "type": "Feature",
  "properties": {
    "addr:full":"RR 3 Alexandria ON K0C 1A0",
    "addr:postcode":"k0c 1a0",
    "addr:street":"Rr 3",
    "iso:country":"CA",
    "sg:address":"RR 3",
    "sg:city":"Alexandria",
    "sg:classifiers":[
        {
            "category":"Building & Trades",
            "subcategory":"Cleaning & Sanitation",
            "type":"Services"
        }
    ],
    "sg:phone":"+1 613 525 3249",
    "sg:postcode":"K0C 1A0",
    "sg:province":"ON",
    "sg:tags":[
        "janitor"
    ],
    "wof:name":"Stay Net Reg'd",
    "wof:placetype":"venue"
},
  "geometry": {"coordinates":[-74.6369476318,45.3115501404],"type":"Point"}
}