{
  "type": "Feature",
  "properties": {
    "addr:full":"1000 the Rapids Pky Sarnia ON N7S 6K3",
    "addr:housenumber":"1000",
    "addr:postcode":"n7s 6k3",
    "addr:street":"The Rapids Pky",
    "iso:country":"CA",
    "sg:address":"1000 the Rapids Pky",
    "sg:city":"Sarnia",
    "sg:classifiers":[
        {
            "category":"Social Services",
            "subcategory":"Child Care",
            "type":"Services"
        }
    ],
    "sg:phone":"+1 519 542 8846",
    "sg:postcode":"N7S 6K3",
    "sg:province":"ON",
    "wof:name":"St Annes Day Care",
    "wof:placetype":"venue"
},
  "geometry": {"coordinates":[-82.350815,42.99649],"type":"Point"}
}