{
  "type": "Feature",
  "properties": {
    "addr:full":"9907 108 Ave NW Edmonton AB T5H 1A5",
    "addr:housenumber":"9907",
    "addr:postcode":"t5h 1a5",
    "addr:street":"108 Ave Nw",
    "iso:country":"CA",
    "sg:address":"9907 108 Ave NW",
    "sg:city":"Edmonton",
    "sg:classifiers":[
        {
            "category":"Professional",
            "subcategory":"Employment Agencies",
            "type":"Services"
        }
    ],
    "sg:phone":"+1 780 944 0317",
    "sg:postcode":"T5H 1A5",
    "sg:province":"AB",
    "sg:tags":[
        "opportunity"
    ],
    "wof:name":"Labour Ready Temporary Svc Ltd",
    "wof:placetype":"venue"
},
  "geometry": {"coordinates":[-113.492363,53.553284],"type":"Point"}
}