{
  "type": "Feature",
  "properties": {
    "addr:full":"929 Church Rd Parksville BC V9P 2B8",
    "addr:housenumber":"929",
    "addr:postcode":"v9p 2b8",
    "addr:street":"Church Rd",
    "iso:country":"CA",
    "sg:address":"929 Church Rd",
    "sg:city":"Parksville",
    "sg:classifiers":[
        {
            "category":"Wholesale",
            "subcategory":"Construction Materials",
            "type":"Manufacturing & Wholesale Goods"
        }
    ],
    "sg:phone":"+1 250 248 3122",
    "sg:postcode":"V9P 2B8",
    "sg:province":"BC",
    "sg:tags":[
        "fence"
    ],
    "wof:name":"Fenceline Products Ltd",
    "wof:placetype":"venue"
},
  "geometry": {"coordinates":[-124.31364440900001,49.3196907043],"type":"Point"}
}