{
  "type": "Feature",
  "properties": {
    "iso:country":"CA",
    "sg:address":"4200 Boul Saint-Laurent",
    "sg:city":"Montreal",
    "sg:classifiers":[
        {
            "category":"Professional",
            "subcategory":"Business Services",
            "type":"Services"
        }
    ],
    "sg:phone":"+1 514 844 2886",
    "sg:postcode":"H2W 2R2",
    "sg:province":"QC",
    "wof:name":"Association Sectorielle Svc",
    "wof:placetype":"venue"
},
  "geometry": {"coordinates":[-73.5821838379,45.5181083679],"type":"Point"}
}