{
  "type": "Feature",
  "properties": {
    "addr:full":"6209 Skyway Rd Smithville ON L0R 2A0",
    "addr:housenumber":"6209",
    "addr:postcode":"l0r 2a0",
    "addr:street":"Skyway Rd",
    "iso:country":"CA",
    "sg:address":"6209 Skyway Rd",
    "sg:city":"Smithville",
    "sg:classifiers":[
        {
            "category":"Wholesale",
            "subcategory":"Metals & Minerals",
            "type":"Manufacturing & Wholesale Goods"
        }
    ],
    "sg:phone":"+1 905 957 7000",
    "sg:postcode":"L0R 2A0",
    "sg:province":"ON",
    "sg:tags":[
        "pipe"
    ],
    "wof:name":"Cappco Tubular Products",
    "wof:placetype":"venue"
},
  "geometry": {"coordinates":[-79.53619384770001,43.1000556946],"type":"Point"}
}