{
  "type": "Feature",
  "properties": {
    "addr:full":"1125 Boul Saint-Joseph Drummondville QC J2C 2C8",
    "addr:housenumber":"1125",
    "addr:postcode":"j2c 2c8",
    "addr:street":"Boul Saint-Joseph",
    "iso:country":"CA",
    "sg:address":"1125 Boul Saint-Joseph",
    "sg:city":"Drummondville",
    "sg:classifiers":[
        {
            "category":"Professional",
            "subcategory":"Accounting & Tax Preparation",
            "type":"Services"
        }
    ],
    "sg:phone":"+1 819 479 8980",
    "sg:postcode":"J2C 2C8",
    "sg:province":"QC",
    "sg:tags":[
        "accountant"
    ],
    "wof:name":"Samson Belair Deloitte-Touche",
    "wof:placetype":"venue"
},
  "geometry": {"coordinates":[-72.50533299999999,45.887608],"type":"Point"}
}