{
  "type": "Feature",
  "properties": {
    "iso:country":"CA",
    "sg:address":"1284 Main St E",
    "sg:city":"Hamilton",
    "sg:classifiers":[
        {
            "category":"Education",
            "subcategory":"School",
            "type":"Public Place"
        }
    ],
    "sg:phone":"+1 905 549 3031",
    "sg:postcode":"L8K 1B2",
    "sg:province":"ON",
    "wof:name":"Delta School",
    "wof:placetype":"venue"
},
  "geometry": {"coordinates":[-79.8137435913,43.2411003113],"type":"Point"}
}