{
  "type": "Feature",
  "properties": {
    "addr:full":"3874 Victoria Ave Vineland ON L0R 2C0",
    "addr:housenumber":"3874",
    "addr:postcode":"l0r 2c0",
    "addr:street":"Victoria Ave",
    "iso:country":"CA",
    "sg:address":"3874 Victoria Ave",
    "sg:city":"Vineland",
    "sg:classifiers":[
        {
            "category":"Organizations",
            "subcategory":"Religious Organization",
            "type":"Services"
        }
    ],
    "sg:phone":"+1 905 562 7141",
    "sg:postcode":"L0R 2C0",
    "sg:province":"ON",
    "sg:tags":[
        "church"
    ],
    "wof:name":"Vineland Missionary Church",
    "wof:placetype":"venue"
},
  "geometry": {"coordinates":[-79.39287567140001,43.1491966248],"type":"Point"}
}