{
  "type": "Feature",
  "properties": {
    "iso:country":"CA",
    "sg:address":"314 Souris Ave",
    "sg:city":"Weyburn",
    "sg:classifiers":[
        {
            "category":"Health Services",
            "subcategory":"Medical Lab",
            "type":"Services"
        }
    ],
    "sg:phone":"+1 306 842 2500",
    "sg:postcode":"S4H 0C7",
    "sg:province":"SK",
    "wof:name":"South East Denture Clinic",
    "wof:placetype":"venue"
},
  "geometry": {"coordinates":[-103.853584,49.661606],"type":"Point"}
}