{
  "type": "Feature",
  "properties": {
    "addr:full":"5014 3 Ave Edson AB T7E 1V4",
    "addr:housenumber":"5014",
    "addr:postcode":"t7e 1v4",
    "addr:street":"3 Ave",
    "iso:country":"CA",
    "sg:address":"5014 3 Ave",
    "sg:city":"Edson",
    "sg:classifiers":[
        {
            "category":"Retail",
            "subcategory":"Self-service Laundry",
            "type":"Services"
        }
    ],
    "sg:phone":"+1 780 723 4722",
    "sg:postcode":"T7E 1V4",
    "sg:province":"AB",
    "wof:name":"Sea Spray Coin Laundry",
    "wof:placetype":"venue"
},
  "geometry": {"coordinates":[-116.431763,53.582104],"type":"Point"}
}