{
  "type": "Feature",
  "properties": {
    "addr:full":"16504 95 St NW Edmonton AB T5Z 3L7",
    "addr:housenumber":"16504",
    "addr:postcode":"t5z 3l7",
    "addr:street":"95 St Nw",
    "iso:country":"CA",
    "sg:address":"16504 95 St NW",
    "sg:city":"Edmonton",
    "sg:classifiers":[
        {
            "category":"Shopping",
            "subcategory":"Pharmacy",
            "type":"Retail Goods"
        }
    ],
    "sg:phone":"+1 780 456 5557",
    "sg:postcode":"T5Z 3L7",
    "sg:province":"AB",
    "wof:name":"Shoppers Drug Mart",
    "wof:placetype":"venue"
},
  "geometry": {"coordinates":[-113.487236,53.627125],"type":"Point"}
}