{
  "type": "Feature",
  "properties": {
    "addr:full":"610 Albert St Regina SK S4R 2P3",
    "addr:housenumber":"610",
    "addr:postcode":"s4r 2p3",
    "addr:street":"Albert St",
    "iso:country":"CA",
    "sg:address":"610 Albert St",
    "sg:city":"Regina",
    "sg:classifiers":[
        {
            "category":"Retail",
            "subcategory":"Auto Rental",
            "type":"Services"
        }
    ],
    "sg:phone":"+1 306 757 7014",
    "sg:postcode":"S4R 2P3",
    "sg:province":"SK",
    "sg:tags":[
        "renting",
        "automobile"
    ],
    "wof:name":"AAA Cheap Car Rentals",
    "wof:placetype":"venue"
},
  "geometry": {"coordinates":[-104.61843109100001,50.4690513611],"type":"Point"}
}