{
  "type": "Feature",
  "properties": {
    "addr:full":"Ignace ON P0T 1T0",
    "addr:postcode":"p0t 1t0",
    "iso:country":"CA",
    "sg:city":"Ignace",
    "sg:classifiers":[
        {
            "category":"Travel",
            "subcategory":"Hotels & Motels",
            "type":"Entertainment"
        }
    ],
    "sg:phone":"+1 807 934 2239",
    "sg:postcode":"P0T 1T0",
    "sg:province":"ON",
    "wof:name":"Lone Pine Motel",
    "wof:placetype":"venue"
},
  "geometry": {"coordinates":[-91.6723480225,49.417678833],"type":"Point"}
}