{
  "type": "Feature",
  "properties": {
    "addr:full":"901 Kingsway Ave SE # A Medicine Hat AB T1A 2X6",
    "addr:housenumber":"901",
    "addr:postcode":"t1a 2x6",
    "addr:street":"Kingsway Ave Se # A",
    "iso:country":"CA",
    "sg:address":"901 Kingsway Ave SE # A",
    "sg:city":"Medicine Hat",
    "sg:classifiers":[
        {
            "category":"Retail",
            "subcategory":"Auto Repair",
            "type":"Services"
        }
    ],
    "sg:phone":"+1 403 527 7975",
    "sg:postcode":"T1A 2X6",
    "sg:province":"AB",
    "sg:tags":[
        "automobile",
        "lubrication"
    ],
    "wof:name":"Mr Lube",
    "wof:placetype":"venue"
},
  "geometry": {"coordinates":[-110.669021606,50.0301017761],"type":"Point"}
}