{
  "type": "Feature",
  "properties": {
    "addr:full":"RR 4 Shelburne ON L0N 1S8",
    "addr:postcode":"l0n 1s8",
    "addr:street":"Rr 4",
    "iso:country":"CA",
    "sg:address":"RR 4",
    "sg:city":"Shelburne",
    "sg:classifiers":[
        {
            "category":"Building & Trades",
            "subcategory":"Construction",
            "type":"Services"
        }
    ],
    "sg:phone":"+1 519 925 6332",
    "sg:postcode":"L0N 1S8",
    "sg:province":"ON",
    "sg:tags":[
        "concrete",
        "contractor"
    ],
    "wof:name":"Complete Concrete Finishing",
    "wof:placetype":"venue"
},
  "geometry": {"coordinates":[-80.20208700000001,44.078785],"type":"Point"}
}