{
  "type": "Feature",
  "properties": {
    "addr:full":"Richmond BC V6V 1Z4",
    "addr:postcode":"v6v 1z4",
    "iso:country":"CA",
    "sg:city":"Richmond",
    "sg:classifiers":[
        {
            "category":"Building & Trades",
            "subcategory":"Electrical",
            "type":"Services"
        }
    ],
    "sg:phone":"+1 604 279 9398",
    "sg:postcode":"V6V 1Z4",
    "sg:province":"BC",
    "sg:tags":[
        "electric",
        "contractor"
    ],
    "wof:name":"Makle Electric Ltd",
    "wof:placetype":"venue"
},
  "geometry": {"coordinates":[-123.08190918,49.1890144348],"type":"Point"}
}