{
  "type": "Feature",
  "properties": {
    "addr:full":"410 Rue Notre-Dame O Victoriaville QC G6P 1S6",
    "addr:housenumber":"410",
    "addr:postcode":"g6p 1s6",
    "addr:street":"Rue Notre-Dame O",
    "iso:country":"CA",
    "sg:address":"410 Rue Notre-Dame O",
    "sg:city":"Victoriaville",
    "sg:classifiers":[
        {
            "category":"Restaurant",
            "type":"Food & Drink"
        }
    ],
    "sg:phone":"+1 819 795 4747",
    "sg:postcode":"G6P 1S6",
    "sg:province":"QC",
    "wof:name":"Resto LA Vigne",
    "wof:placetype":"venue"
},
  "geometry": {"coordinates":[-71.946579,46.059494],"type":"Point"}
}