{
  "type": "Feature",
  "properties": {
    "addr:full":"Toronto ON M5J 2N3",
    "addr:postcode":"m5j 2n3",
    "iso:country":"CA",
    "sg:city":"Toronto",
    "sg:classifiers":[
        {
            "category":"Personal",
            "type":"Services"
        }
    ],
    "sg:phone":"+1 416 260 5678",
    "sg:postcode":"M5J 2N3",
    "sg:province":"ON",
    "sg:tags":[
        "control",
        "weight"
    ],
    "wof:name":"Herbalife Distributor",
    "wof:placetype":"venue"
},
  "geometry": {"coordinates":[-79.3857269287,43.6391563416],"type":"Point"}
}