{
  "type": "Feature",
  "properties": {
    "addr:full":"979 Rue Des Forges L'Ancienne-Lorette QC G2E 1L2",
    "addr:housenumber":"979",
    "addr:postcode":"g2e 1l2",
    "addr:street":"Rue Des Forges",
    "iso:country":"CA",
    "sg:address":"979 Rue Des Forges",
    "sg:city":"L'Ancienne-Lorette",
    "sg:classifiers":[
        {
            "category":"Building & Trades",
            "subcategory":"Cleaning & Sanitation",
            "type":"Services"
        }
    ],
    "sg:phone":"+1 418 871 2548",
    "sg:postcode":"G2E 1L2",
    "sg:province":"QC",
    "sg:tags":[
        "janitor",
        "steam"
    ],
    "wof:name":"Entreprises Bule",
    "wof:placetype":"venue"
},
  "geometry": {"coordinates":[-71.350418,46.811966],"type":"Point"}
}