{
  "type": "Feature",
  "properties": {
    "addr:full":"1260 Rue Notre-Dame O Champlain QC G0X 1C0",
    "addr:housenumber":"1260",
    "addr:postcode":"g0x 1c0",
    "addr:street":"Rue Notre-Dame O",
    "iso:country":"CA",
    "sg:address":"1260 Rue Notre-Dame O",
    "sg:city":"Champlain",
    "sg:classifiers":[
        {
            "category":"Home & Garden",
            "subcategory":"Garden Supply",
            "type":"Retail Goods"
        }
    ],
    "sg:phone":"+1 819 295 3787",
    "sg:postcode":"G0X 1C0",
    "sg:province":"QC",
    "sg:tags":[
        "nurseryman"
    ],
    "wof:name":"Pepiniere Champlain Enr",
    "wof:placetype":"venue"
},
  "geometry": {"coordinates":[-72.3152542114,46.4434089661],"type":"Point"}
}