{
  "type": "Feature",
  "properties": {
    "addr:full":"666 Bloor St W Toronto ON M6G 1L2",
    "addr:housenumber":"666",
    "addr:postcode":"m6g 1l2",
    "addr:street":"Bloor St W",
    "iso:country":"CA",
    "sg:address":"666 Bloor St W",
    "sg:city":"Toronto",
    "sg:classifiers":[
        {
            "category":"Restaurant",
            "type":"Food & Drink"
        }
    ],
    "sg:phone":"+1 416 536 8666",
    "sg:postcode":"M6G 1L2",
    "sg:province":"ON",
    "wof:name":"Korea House",
    "wof:placetype":"venue"
},
  "geometry": {"coordinates":[-79.416343689,43.6641273499],"type":"Point"}
}