{
  "type": "Feature",
  "properties": {
    "addr:full":"517 Sixth Ave N Williams Lake BC V2G 2G8",
    "addr:housenumber":"517",
    "addr:postcode":"v2g 2g8",
    "addr:street":"Sixth Ave N",
    "iso:country":"CA",
    "sg:address":"517 Sixth Ave N",
    "sg:city":"Williams Lake",
    "sg:classifiers":[
        {
            "category":"Government",
            "subcategory":"Office",
            "type":"Public Place"
        }
    ],
    "sg:phone":"+1 250 398 4625",
    "sg:postcode":"V2G 2G8",
    "sg:province":"BC",
    "wof:name":"BC Health Unit",
    "wof:placetype":"venue"
},
  "geometry": {"coordinates":[-122.14205200000001,52.137405],"type":"Point"}
}