{
  "type": "Feature",
  "properties": {
    "iso:country":"CA",
    "sg:city":"Toronto",
    "sg:classifiers":[
        {
            "category":"Professional",
            "subcategory":"Lawyer & Legal Services",
            "type":"Services"
        }
    ],
    "sg:phone":"+1 416 777 2270",
    "sg:postcode":"M5H 2A4",
    "sg:province":"ON",
    "sg:tags":[
        "attorney"
    ],
    "wof:name":"Hitchman & Sprigings",
    "wof:placetype":"venue"
},
  "geometry": {"coordinates":[-79.38250732420001,43.651008606],"type":"Point"}
}