{
  "type": "Feature",
  "properties": {
    "addr:full":"Saint-Cuthbert QC J0K 2C0",
    "addr:postcode":"j0k 2c0",
    "iso:country":"CA",
    "sg:city":"Saint-Cuthbert",
    "sg:classifiers":[
        {
            "category":"Manufacturing",
            "subcategory":"Printing",
            "type":"Manufacturing & Wholesale Goods"
        }
    ],
    "sg:phone":"+1 450 836 3519",
    "sg:postcode":"J0K 2C0",
    "sg:province":"QC",
    "sg:tags":[
        "publisher",
        "music"
    ],
    "wof:name":"Chorus Plus",
    "wof:placetype":"venue"
},
  "geometry": {"coordinates":[-73.22602844239999,46.15417099],"type":"Point"}
}