{
  "type": "Feature",
  "properties": {
    "addr:full":"740 Boul DE LA Cote-Vertu Saint-Laurent QC H4L 5C8",
    "addr:housenumber":"740",
    "addr:postcode":"h4l 5c8",
    "addr:street":"Boul De La Cote-Vertu",
    "iso:country":"CA",
    "sg:address":"740 Boul DE LA Cote-Vertu",
    "sg:city":"Saint-Laurent",
    "sg:classifiers":[
        {
            "category":"Airline",
            "type":"Transportation"
        }
    ],
    "sg:phone":"+1 514 748 2769",
    "sg:postcode":"H4L 5C8",
    "sg:province":"QC",
    "sg:tags":[
        "company"
    ],
    "wof:name":"Singapore Airlines",
    "wof:placetype":"venue"
},
  "geometry": {"coordinates":[-73.6745376587,45.5202407837],"type":"Point"}
}