{
  "type": "Feature",
  "properties": {
    "addr:full":"805 Boul Talbot Chicoutimi QC G7H 4B3",
    "addr:housenumber":"805",
    "addr:postcode":"g7h 4b3",
    "addr:street":"Boul Talbot",
    "iso:country":"CA",
    "sg:address":"805 Boul Talbot",
    "sg:city":"Chicoutimi",
    "sg:classifiers":[
        {
            "category":"Restaurant",
            "type":"Food & Drink"
        }
    ],
    "sg:phone":"+1 418 698 8877",
    "sg:postcode":"G7H 4B3",
    "sg:province":"QC",
    "wof:name":"Coq Roti Pizza Delight",
    "wof:placetype":"venue"
},
  "geometry": {"coordinates":[-71.0464553833,48.4164237976],"type":"Point"}
}