{
  "type": "Feature",
  "properties": {
    "iso:country":"CA",
    "sg:address":"126 2 Ave SW",
    "sg:city":"Calgary",
    "sg:classifiers":[
        {
            "category":"Education",
            "subcategory":"School",
            "type":"Public Place"
        }
    ],
    "sg:phone":"+1 403 264 4941",
    "sg:postcode":"T2P 0B9",
    "sg:province":"AB",
    "wof:name":"Chinese Public School",
    "wof:placetype":"venue"
},
  "geometry": {"coordinates":[-114.06340789799999,51.0513648987],"type":"Point"}
}