{
  "type": "Feature",
  "properties": {
    "addr:full":"Victoria BC V9B 6B2",
    "addr:postcode":"v9b 6b2",
    "iso:country":"CA",
    "sg:city":"Victoria",
    "sg:classifiers":[
        {
            "category":"Wholesale",
            "subcategory":"Auto Parts",
            "type":"Manufacturing & Wholesale Goods"
        }
    ],
    "sg:phone":"+1 250 391 1332",
    "sg:postcode":"V9B 6B2",
    "sg:province":"BC",
    "sg:tags":[
        "equipment",
        "truck",
        "trailer"
    ],
    "wof:name":"Traction",
    "wof:placetype":"venue"
},
  "geometry": {"coordinates":[-123.514977,48.444695],"type":"Point"}
}