{
  "type": "Feature",
  "properties": {
    "addr:full":"110 Bearbrook Rd # 200 Gloucester ON K1B 5R2",
    "addr:housenumber":"110",
    "addr:postcode":"k1b 5r2",
    "addr:street":"Bearbrook Rd # 200",
    "iso:country":"CA",
    "sg:address":"110 Bearbrook Rd # 200",
    "sg:city":"Gloucester",
    "sg:classifiers":[
        {
            "category":"Health Services",
            "subcategory":"Doctor",
            "type":"Services"
        }
    ],
    "sg:phone":"+1 613 824 6318",
    "sg:postcode":"K1B 5R2",
    "sg:province":"ON",
    "sg:tags":[
        "physician",
        "surgeon"
    ],
    "wof:name":"Linney, Louise MD",
    "wof:placetype":"venue"
},
  "geometry": {"coordinates":[-75.565361,45.432835],"type":"Point"}
}