{
  "type": "Feature",
  "properties": {
    "addr:full":"227 Rue Dufferin Stanstead QC J0B 3E2",
    "addr:housenumber":"227",
    "addr:postcode":"j0b 3e2",
    "addr:street":"Rue Dufferin",
    "iso:country":"CA",
    "sg:address":"227 Rue Dufferin",
    "sg:city":"Stanstead",
    "sg:classifiers":[
        {
            "category":"Health Services",
            "subcategory":"Medical Lab",
            "type":"Services"
        }
    ],
    "sg:phone":"+1 819 876 5298",
    "sg:postcode":"J0B 3E2",
    "sg:province":"QC",
    "sg:tags":[
        "clinic"
    ],
    "wof:name":"Clinique DE Denturologie",
    "wof:placetype":"venue"
},
  "geometry": {"coordinates":[-72.0988235474,45.0070114136],"type":"Point"}
}