{
  "type": "Feature",
  "properties": {
    "addr:full":"413 Norfolk St N Simcoe ON N3Y 3P4",
    "addr:housenumber":"413",
    "addr:postcode":"n3y 3p4",
    "addr:street":"Norfolk St N",
    "iso:country":"CA",
    "sg:address":"413 Norfolk St N",
    "sg:city":"Simcoe",
    "sg:classifiers":[
        {
            "category":"Restaurant",
            "type":"Food & Drink"
        }
    ],
    "sg:phone":"+1 519 426 4800",
    "sg:postcode":"N3Y 3P4",
    "sg:province":"ON",
    "wof:name":"Wendy's",
    "wof:placetype":"venue"
},
  "geometry": {"coordinates":[-80.306831,42.845909],"type":"Point"}
}