{
  "type": "Feature",
  "properties": {
    "addr:full":"Fossambault-Sur-Le-Lac QC G0A 3M0",
    "addr:postcode":"g0a 3m0",
    "iso:country":"CA",
    "sg:city":"Fossambault-Sur-Le-Lac",
    "sg:classifiers":[
        {
            "category":"Food & Beverages",
            "subcategory":"Groceries & Convenience Stores",
            "type":"Retail Goods"
        }
    ],
    "sg:phone":"+1 418 875 3725",
    "sg:postcode":"G0A 3M0",
    "sg:province":"QC",
    "sg:tags":[
        "grocer"
    ],
    "wof:name":"Epicerie Du Lac St-Joseph Enr",
    "wof:placetype":"venue"
},
  "geometry": {"coordinates":[-71.61908699999999,46.866726],"type":"Point"}
}