{
  "type": "Feature",
  "properties": {
    "addr:full":"520 Sovereign Rd London ON N5V 4K4",
    "addr:housenumber":"520",
    "addr:postcode":"n5v 4k4",
    "addr:street":"Sovereign Rd",
    "iso:country":"CA",
    "sg:address":"520 Sovereign Rd",
    "sg:city":"London",
    "sg:classifiers":[
        {
            "category":"Professional",
            "subcategory":"Management & Consulting",
            "type":"Services"
        }
    ],
    "sg:phone":"+1 519 452 7306",
    "sg:postcode":"N5V 4K4",
    "sg:province":"ON",
    "sg:tags":[
        "employee",
        "consultant",
        "benefit"
    ],
    "wof:name":"Simply Benefits Inc",
    "wof:placetype":"venue"
},
  "geometry": {"coordinates":[-81.144981,42.999783],"type":"Point"}
}