{
  "type": "Feature",
  "properties": {
    "addr:full":"11303 143 St NW Edmonton AB T5M 3P8",
    "addr:housenumber":"11303",
    "addr:postcode":"t5m 3p8",
    "addr:street":"143 St Nw",
    "iso:country":"CA",
    "sg:address":"11303 143 St NW",
    "sg:city":"Edmonton",
    "sg:classifiers":[
        {
            "category":"Professional",
            "subcategory":"Research",
            "type":"Services"
        }
    ],
    "sg:phone":"+1 780 448 9366",
    "sg:postcode":"T5M 3P8",
    "sg:province":"AB",
    "sg:tags":[
        "environmental",
        "ecological"
    ],
    "wof:name":"B P Resources",
    "wof:placetype":"venue"
},
  "geometry": {"coordinates":[-113.567238,53.561687],"type":"Point"}
}