{
  "type": "Feature",
  "properties": {
    "iso:country":"CA",
    "sg:address":"15 Maple Ave E",
    "sg:city":"Hamiota",
    "sg:classifiers":[
        {
            "category":"Shopping",
            "subcategory":"Computers & Home Electronics",
            "type":"Retail Goods"
        }
    ],
    "sg:phone":"+1 204 412 0017",
    "sg:postcode":"R0M 0T0",
    "sg:province":"MB",
    "sg:tags":[
        "equipment",
        "dealer",
        "software"
    ],
    "wof:name":"Kirk Computer Svc",
    "wof:placetype":"venue"
},
  "geometry": {"coordinates":[-100.599845886,50.182510376],"type":"Point"}
}