{
  "type": "Feature",
  "properties": {
    "addr:full":"510 Av Principale Sainte-Foy QC G2G 2T9",
    "addr:housenumber":"510",
    "addr:postcode":"g2g 2t9",
    "addr:street":"Av Principale",
    "iso:country":"CA",
    "sg:address":"510 Av Principale",
    "sg:city":"Sainte-Foy",
    "sg:classifiers":[
        {
            "category":"Organizations",
            "subcategory":"Professional Association",
            "type":"Services"
        }
    ],
    "sg:phone":"+1 418 871 7266",
    "sg:postcode":"G2G 2T9",
    "sg:province":"QC",
    "wof:name":"Assn Intl Des Machinistes",
    "wof:placetype":"venue"
},
  "geometry": {"coordinates":[-71.383675,46.791519],"type":"Point"}
}