{
  "type": "Feature",
  "properties": {
    "addr:full":"6375 Rue D'Iberville Montreal QC H2G 2C5",
    "addr:housenumber":"6375",
    "addr:postcode":"h2g 2c5",
    "addr:street":"Rue D'Iberville",
    "iso:country":"CA",
    "sg:address":"6375 Rue D'Iberville",
    "sg:city":"Montreal",
    "sg:classifiers":[
        {
            "category":"Professional",
            "subcategory":"Management & Consulting",
            "type":"Services"
        }
    ],
    "sg:phone":"+1 514 282 1669",
    "sg:postcode":"H2G 2C5",
    "sg:province":"QC",
    "sg:tags":[
        "marketing",
        "consultant"
    ],
    "wof:name":"Communications Dsa Inc",
    "wof:placetype":"venue"
},
  "geometry": {"coordinates":[-73.217377,45.281342],"type":"Point"}
}