{
  "type": "Feature",
  "properties": {
    "iso:country":"CA",
    "sg:address":"700 Montreal Rd",
    "sg:city":"Cornwall",
    "sg:classifiers":[
        {
            "category":"Professional",
            "subcategory":"Lawyer & Legal Services",
            "type":"Services"
        }
    ],
    "sg:phone":"+1 613 933 6443",
    "sg:postcode":"K6H 1C4",
    "sg:province":"ON",
    "sg:tags":[
        "attorney"
    ],
    "wof:name":"White, Donald J",
    "wof:placetype":"venue"
},
  "geometry": {"coordinates":[-74.7066421509,45.0185012817],"type":"Point"}
}