{
  "type": "Feature",
  "properties": {
    "addr:full":"3406 Kingston Rd Scarborough ON M1M 1R2",
    "addr:housenumber":"3406",
    "addr:postcode":"m1m 1r2",
    "addr:street":"Kingston Rd",
    "iso:country":"CA",
    "sg:address":"3406 Kingston Rd",
    "sg:city":"Scarborough",
    "sg:classifiers":[
        {
            "category":"Restaurant",
            "type":"Food & Drink"
        }
    ],
    "sg:phone":"+1 416 267 9230",
    "sg:postcode":"M1M 1R2",
    "sg:province":"ON",
    "wof:name":"Big Pete's Restaurant & Bar",
    "wof:placetype":"venue"
},
  "geometry": {"coordinates":[-79.2198257446,43.7366523743],"type":"Point"}
}