{
  "type": "Feature",
  "properties": {
    "addr:full":"4 E Arbutus St Lake Cowichan BC V0R 2G0",
    "addr:housenumber":"4",
    "addr:postcode":"v0r 2g0",
    "addr:street":"E Arbutus St",
    "iso:country":"CA",
    "sg:address":"4 E Arbutus St",
    "sg:city":"Lake Cowichan",
    "sg:classifiers":[
        {
            "category":"Personal",
            "subcategory":"Beauty Salon",
            "type":"Services"
        }
    ],
    "sg:phone":"+1 250 749 6559",
    "sg:postcode":"V0R 2G0",
    "sg:province":"BC",
    "wof:name":"Robin's",
    "wof:placetype":"venue"
},
  "geometry": {"coordinates":[-124.053284,48.81889],"type":"Point"}
}