{
  "type": "Feature",
  "properties": {
    "addr:full":"14209 Atkinson Rd Summerland BC V0H 1Z0",
    "addr:housenumber":"14209",
    "addr:postcode":"v0h 1z0",
    "addr:street":"Atkinson Rd",
    "iso:country":"CA",
    "sg:address":"14209 Atkinson Rd",
    "sg:city":"Summerland",
    "sg:classifiers":[
        {
            "category":"Wholesale",
            "subcategory":"Machinery & Supplies",
            "type":"Manufacturing & Wholesale Goods"
        }
    ],
    "sg:phone":"+1 250 494 8922",
    "sg:postcode":"V0H 1Z0",
    "sg:province":"BC",
    "sg:tags":[
        "equipment",
        "bottler"
    ],
    "wof:name":"Mission Bottlewashing Ltd",
    "wof:placetype":"venue"
},
  "geometry": {"coordinates":[-119.668556,49.604874],"type":"Point"}
}