{
  "type": "Feature",
  "properties": {
    "addr:full":"154 Rue Boulerice Thurso QC J0X 3B0",
    "addr:housenumber":"154",
    "addr:postcode":"j0x 3b0",
    "addr:street":"Rue Boulerice",
    "iso:country":"CA",
    "sg:address":"154 Rue Boulerice",
    "sg:city":"Thurso",
    "sg:classifiers":[
        {
            "category":"Personal",
            "subcategory":"Beauty Salon",
            "type":"Services"
        }
    ],
    "sg:phone":"+1 819 985 1777",
    "sg:postcode":"J0X 3B0",
    "sg:province":"QC",
    "wof:name":"Salon DE Coiffure Studio Tech",
    "wof:placetype":"venue"
},
  "geometry": {"coordinates":[-75.242515564,45.599861145],"type":"Point"}
}