{
  "type": "Feature",
  "properties": {
    "addr:full":"25 John St Shannonville ON K0K 3A0",
    "addr:housenumber":"25",
    "addr:postcode":"k0k 3a0",
    "addr:street":"John St",
    "iso:country":"CA",
    "sg:address":"25 John St",
    "sg:city":"Shannonville",
    "sg:classifiers":[
        {
            "category":"Wholesale",
            "subcategory":"Auto Parts",
            "type":"Manufacturing & Wholesale Goods"
        }
    ],
    "sg:phone":"+1 613 968 7952",
    "sg:postcode":"K0K 3A0",
    "sg:province":"ON",
    "sg:tags":[
        "automobile",
        "supply"
    ],
    "wof:name":"Red Stallion Svc Station",
    "wof:placetype":"venue"
},
  "geometry": {"coordinates":[-77.2300109863,44.1973266602],"type":"Point"}
}