{
  "type": "Feature",
  "properties": {
    "addr:full":"Dartmouth NS B3B 1S8",
    "addr:postcode":"b3b 1s8",
    "iso:country":"CA",
    "sg:city":"Dartmouth",
    "sg:classifiers":[
        {
            "category":"Wholesale",
            "subcategory":"Machinery & Supplies",
            "type":"Manufacturing & Wholesale Goods"
        }
    ],
    "sg:phone":"+1 902 468 2368",
    "sg:postcode":"B3B 1S8",
    "sg:province":"NS",
    "sg:tags":[
        "equipment",
        "salon",
        "barber",
        "beauty"
    ],
    "wof:name":"Obsco",
    "wof:placetype":"venue"
},
  "geometry": {"coordinates":[-63.587433,44.700459],"type":"Point"}
}