{
  "type": "Feature",
  "properties": {
    "addr:full":"1113 Route 875 Searsville NB E5P 3S9",
    "addr:housenumber":"1113",
    "addr:postcode":"e5p 3s9",
    "addr:street":"Route 875",
    "iso:country":"CA",
    "sg:address":"1113 Route 875",
    "sg:city":"Searsville",
    "sg:classifiers":[
        {
            "category":"Building & Trades",
            "subcategory":"Construction",
            "type":"Services"
        }
    ],
    "sg:phone":"+1 506 433 5608",
    "sg:postcode":"E5P 3S9",
    "sg:province":"NB",
    "sg:tags":[
        "contractor",
        "landscape",
        "general"
    ],
    "wof:name":"T A Raymond Landscaping Ltd",
    "wof:placetype":"venue"
},
  "geometry": {"coordinates":[-65.69309199999999,45.714741],"type":"Point"}
}