{
  "type": "Feature",
  "properties": {
    "iso:country":"CA",
    "sg:address":"1441 Berko Crt",
    "sg:city":"Burlington",
    "sg:classifiers":[
        {
            "category":"Building & Trades",
            "subcategory":"Construction",
            "type":"Services"
        }
    ],
    "sg:phone":"+1 905 332 7727",
    "sg:postcode":"L7P 4W4",
    "sg:province":"ON",
    "sg:tags":[
        "general",
        "contractor"
    ],
    "wof:name":"Trigiani Construction Ltd",
    "wof:placetype":"venue"
},
  "geometry": {"coordinates":[-79.8444976807,43.3403091431],"type":"Point"}
}