{
  "type": "Feature",
  "properties": {
    "addr:full":"10 Knowlton Dr Brandon MB R7A 6N7",
    "addr:housenumber":"10",
    "addr:postcode":"r7a 6n7",
    "addr:street":"Knowlton Dr",
    "iso:country":"CA",
    "sg:address":"10 Knowlton Dr",
    "sg:city":"Brandon",
    "sg:classifiers":[
        {
            "category":"Social Services",
            "subcategory":"Child Care",
            "type":"Services"
        }
    ],
    "sg:phone":"+1 204 726 5321",
    "sg:postcode":"R7A 6N7",
    "sg:province":"MB",
    "wof:name":"Fuzzy Bears' Inc",
    "wof:placetype":"venue"
},
  "geometry": {"coordinates":[-99.94715118409999,49.8659858704],"type":"Point"}
}