{
  "type": "Feature",
  "properties": {
    "addr:full":"7250 Boul Maurice-Duplessis Montreal QC H1E 4A7",
    "addr:housenumber":"7250",
    "addr:postcode":"h1e 4a7",
    "addr:street":"Boul Maurice-Duplessis",
    "iso:country":"CA",
    "sg:address":"7250 Boul Maurice-Duplessis",
    "sg:city":"Montreal",
    "sg:classifiers":[
        {
            "category":"Shopping",
            "subcategory":"Clothing, Apparel, & Fashions",
            "type":"Retail Goods"
        }
    ],
    "sg:phone":"+1 514 494 1854",
    "sg:postcode":"H1E 4A7",
    "sg:province":"QC",
    "sg:tags":[
        "shop",
        "bridal"
    ],
    "wof:name":"Luisa Sposina Inc",
    "wof:placetype":"venue"
},
  "geometry": {"coordinates":[-73.6021728516,45.6236076355],"type":"Point"}
}