{
  "type": "Feature",
  "properties": {
    "addr:full":"1600 Rue Principale Sainte-Julie QC J3E 1W6",
    "addr:housenumber":"1600",
    "addr:postcode":"j3e 1w6",
    "addr:street":"Rue Principale",
    "iso:country":"CA",
    "sg:address":"1600 Rue Principale",
    "sg:city":"Sainte-Julie",
    "sg:classifiers":[
        {
            "category":"Bars & Pubs",
            "type":"Food & Drink"
        }
    ],
    "sg:phone":"+1 450 649 0734",
    "sg:postcode":"J3E 1W6",
    "sg:province":"QC",
    "sg:tags":[
        "lounge",
        "cocktail"
    ],
    "wof:name":"Bar L'Etoile D'Or Enr",
    "wof:placetype":"venue"
},
  "geometry": {"coordinates":[-73.337532,45.594696],"type":"Point"}
}