{
  "type": "Feature",
  "properties": {
    "addr:full":"Irricana AB T0M 1B0",
    "addr:postcode":"t0m 1b0",
    "iso:country":"CA",
    "sg:city":"Irricana",
    "sg:classifiers":[
        {
            "category":"Wholesale",
            "subcategory":"Durable Goods & Equipment",
            "type":"Manufacturing & Wholesale Goods"
        }
    ],
    "sg:phone":"+1 403 935 5595",
    "sg:postcode":"T0M 1B0",
    "sg:province":"AB",
    "sg:tags":[
        "representative",
        "manufacturer"
    ],
    "wof:name":"T A Ferguson & Assoc",
    "wof:placetype":"venue"
},
  "geometry": {"coordinates":[-113.59141540500001,51.3250465393],"type":"Point"}
}