{
  "type": "Feature",
  "properties": {
    "addr:full":"North York ON M2J 1V1",
    "addr:postcode":"m2j 1v1",
    "iso:country":"CA",
    "sg:city":"North York",
    "sg:classifiers":[
        {
            "category":"Health Services",
            "subcategory":"Doctor",
            "type":"Services"
        }
    ],
    "sg:phone":"+1 416 491 2117",
    "sg:postcode":"M2J 1V1",
    "sg:province":"ON",
    "sg:tags":[
        "dentist"
    ],
    "wof:name":"Milanovic, Jovan DDS",
    "wof:placetype":"venue"
},
  "geometry": {"coordinates":[-79.3622894287,43.7717437744],"type":"Point"}
}