{
  "type": "Feature",
  "properties": {
    "addr:full":"250 Mark St Sault Ste Marie ON P6A 3M7",
    "addr:housenumber":"250",
    "addr:postcode":"p6a 3m7",
    "addr:street":"Mark St",
    "iso:country":"CA",
    "sg:address":"250 Mark St",
    "sg:city":"Sault Ste Marie",
    "sg:classifiers":[
        {
            "category":"Education",
            "subcategory":"School",
            "type":"Public Place"
        }
    ],
    "sg:phone":"+1 705 945 7106",
    "sg:postcode":"P6A 3M7",
    "sg:province":"ON",
    "wof:name":"Anna Mc Crea School",
    "wof:placetype":"venue"
},
  "geometry": {"coordinates":[-84.28847500000001,46.505573],"type":"Point"}
}