{
  "type": "Feature",
  "properties": {
    "iso:country":"CA",
    "sg:address":"4750 Rue Bourg",
    "sg:city":"Saint-Laurent",
    "sg:classifiers":[
        {
            "category":"Wholesale",
            "subcategory":"Machinery & Supplies",
            "type":"Manufacturing & Wholesale Goods"
        }
    ],
    "sg:phone":"+1 514 735 3627",
    "sg:postcode":"H4T 1J2",
    "sg:province":"QC",
    "sg:tags":[
        "equipment",
        "ice"
    ],
    "wof:name":"Bazinet Taylor Ltee",
    "wof:placetype":"venue"
},
  "geometry": {"coordinates":[-73.699875,45.473621],"type":"Point"}
}