{
  "type": "Feature",
  "properties": {
    "addr:full":"4750 Rue Bourg Saint-Laurent QC H4T 1J2",
    "addr:housenumber":"4750",
    "addr:postcode":"h4t 1j2",
    "addr:street":"Rue Bourg",
    "iso:country":"CA",
    "sg:address":"4750 Rue Bourg",
    "sg:city":"Saint-Laurent",
    "sg:classifiers":[
        {
            "category":"Wholesale",
            "subcategory":"Machinery & Supplies",
            "type":"Manufacturing & Wholesale Goods"
        }
    ],
    "sg:phone":"+1 514 735 3627",
    "sg:postcode":"H4T 1J2",
    "sg:province":"QC",
    "sg:tags":[
        "equipment",
        "ice"
    ],
    "wof:name":"Bazinet Taylor Ltee",
    "wof:placetype":"venue"
},
  "geometry": {"coordinates":[-73.69987500000001,45.473621],"type":"Point"}
}