{
  "type": "Feature",
  "properties": {
    "addr:full":"145 Gloucester Grove York ON M6C 2A9",
    "addr:housenumber":"145",
    "addr:postcode":"m6c 2a9",
    "addr:street":"Gloucester Grove",
    "iso:country":"CA",
    "sg:address":"145 Gloucester Grove",
    "sg:city":"York",
    "sg:classifiers":[
        {
            "category":"Building & Trades",
            "subcategory":"Construction",
            "type":"Services"
        }
    ],
    "sg:phone":"+1 416 783 7705",
    "sg:postcode":"M6C 2A9",
    "sg:province":"ON",
    "sg:tags":[
        "general",
        "contractor"
    ],
    "wof:name":"Canadian Star Construction Ltd",
    "wof:placetype":"venue"
},
  "geometry": {"coordinates":[-79.44060500000001,43.695953],"type":"Point"}
}