{
  "type": "Feature",
  "properties": {
    "iso:country":"CA",
    "sg:city":"Pincher Creek",
    "sg:classifiers":[
        {
            "category":"Government",
            "subcategory":"Office",
            "type":"Public Place"
        }
    ],
    "sg:phone":"+1 403 627 3156",
    "sg:postcode":"T0K 1W0",
    "sg:province":"AB",
    "sg:tags":[
        "village"
    ],
    "wof:name":"Pincher Creek Town Office",
    "wof:placetype":"venue"
},
  "geometry": {"coordinates":[-113.947822571,49.4850120544],"type":"Point"}
}