{
  "type": "Feature",
  "properties": {
    "addr:full":"1720 John Brebeuf Pl Winnipeg MB R3N 0M1",
    "addr:housenumber":"1720",
    "addr:postcode":"r3n 0m1",
    "addr:street":"John Brebeuf Pl",
    "iso:country":"CA",
    "sg:address":"1720 John Brebeuf Pl",
    "sg:city":"Winnipeg",
    "sg:classifiers":[
        {
            "category":"Education",
            "subcategory":"School",
            "type":"Public Place"
        }
    ],
    "sg:phone":"+1 204 488 4517",
    "sg:postcode":"R3N 0M1",
    "sg:province":"MB",
    "wof:name":"J B Mitchell School",
    "wof:placetype":"venue"
},
  "geometry": {"coordinates":[-97.198784,49.860348],"type":"Point"}
}