{
  "type": "Feature",
  "properties": {
    "iso:country":"CA",
    "sg:address":"3358 Salsbury Way",
    "sg:city":"Victoria",
    "sg:classifiers":[
        {
            "category":"Professional",
            "type":"Services"
        }
    ],
    "sg:phone":"+1 250 385 5398",
    "sg:postcode":"V8P 3K3",
    "sg:province":"BC",
    "sg:tags":[
        "home",
        "planning"
    ],
    "wof:name":"Mc Mullan, Tricia",
    "wof:placetype":"venue"
},
  "geometry": {"coordinates":[-123.364517,48.428314],"type":"Point"}
}