{
  "type": "Feature",
  "properties": {
    "addr:full":"310 Matheson Blvd E Mississauga ON L4Z 1P5",
    "addr:housenumber":"310",
    "addr:postcode":"l4z 1p5",
    "addr:street":"Matheson Blvd E",
    "iso:country":"CA",
    "sg:address":"310 Matheson Blvd E",
    "sg:city":"Mississauga",
    "sg:classifiers":[
        {
            "category":"Manufacturing",
            "subcategory":"Rubber & Plastics",
            "type":"Manufacturing & Wholesale Goods"
        }
    ],
    "sg:phone":"+1 905 890 1788",
    "sg:postcode":"L4Z 1P5",
    "sg:province":"ON",
    "sg:tags":[
        "mold",
        "maker"
    ],
    "wof:name":"Plastic Packaging & Components",
    "wof:placetype":"venue"
},
  "geometry": {"coordinates":[-79.66222399999999,43.622974],"type":"Point"}
}