{
  "type": "Feature",
  "properties": {
    "addr:full":"2512 Eglinton Ave W York ON M6M 1T1",
    "addr:housenumber":"2512",
    "addr:postcode":"m6m 1t1",
    "addr:street":"Eglinton Ave W",
    "iso:country":"CA",
    "sg:address":"2512 Eglinton Ave W",
    "sg:city":"York",
    "sg:classifiers":[
        {
            "category":"Manufacturing",
            "subcategory":"Food",
            "type":"Manufacturing & Wholesale Goods"
        }
    ],
    "sg:phone":"+1 416 658 2846",
    "sg:postcode":"M6M 1T1",
    "sg:province":"ON",
    "sg:tags":[
        "baker",
        "product",
        "manufacturer"
    ],
    "wof:name":"Sunlight Bakery",
    "wof:placetype":"venue"
},
  "geometry": {"coordinates":[-79.47023799999999,43.691387],"type":"Point"}
}