{
  "type": "Feature",
  "properties": {
    "addr:full":"4440 Stark St Richmond BC V7B 1A1",
    "addr:housenumber":"4440",
    "addr:postcode":"bc v7b 1a1",
    "addr:street":"Stark St",
    "iso:country":"CA",
    "sg:address":"4440 Stark St",
    "sg:city":"Richmond",
    "sg:classifiers":[
        {
            "category":"Health Services",
            "subcategory":"Doctor",
            "type":"Services"
        }
    ],
    "sg:phone":"+1 604 270 1370",
    "sg:postcode":"V7B 1A1",
    "sg:province":"BC",
    "sg:tags":[
        "physician",
        "surgeon"
    ],
    "wof:name":"Ultima Yvr South",
    "wof:placetype":"venue"
},
  "geometry": {"coordinates":[-123.170082092,49.1779785156],"type":"Point"}
}