{
  "type": "Feature",
  "properties": {
    "addr:full":"Trois-Rivieres QC G8Y 1V7",
    "addr:postcode":"g8y 1v7",
    "iso:country":"CA",
    "sg:city":"Trois-Rivieres",
    "sg:classifiers":[
        {
            "category":"Banks & Credit Unions",
            "subcategory":"Financial Services",
            "type":"Services"
        }
    ],
    "sg:phone":"+1 819 370 2020",
    "sg:postcode":"G8Y 1V7",
    "sg:province":"QC",
    "sg:tags":[
        "bankruptcy",
        "trustee"
    ],
    "wof:name":"Jean Fortin & Assoc",
    "wof:placetype":"venue"
},
  "geometry": {"coordinates":[-72.584274292,46.3553085327],"type":"Point"}
}