{
  "type": "Feature",
  "properties": {
    "addr:full":"1067 Ridgeway Ave Coquitlam BC V3J 1S6",
    "addr:housenumber":"1067",
    "addr:postcode":"v3j 1s6",
    "addr:street":"Ridgeway Ave",
    "iso:country":"CA",
    "sg:address":"1067 Ridgeway Ave",
    "sg:city":"Coquitlam",
    "sg:classifiers":[
        {
            "category":"Food & Beverages",
            "subcategory":"Groceries & Convenience Stores",
            "type":"Retail Goods"
        }
    ],
    "sg:phone":"+1 604 936 3337",
    "sg:postcode":"V3J 1S6",
    "sg:province":"BC",
    "sg:tags":[
        "grocer"
    ],
    "wof:name":"Ridgemont Foods",
    "wof:placetype":"venue"
},
  "geometry": {"coordinates":[-122.863747,49.249878],"type":"Point"}
}