{
  "type": "Feature",
  "properties": {
    "addr:full":"70 Wade Ave # 3 Toronto ON M6H 1P6",
    "addr:housenumber":"70",
    "addr:postcode":"m6h 1p6",
    "addr:street":"Wade Ave # 3",
    "iso:country":"CA",
    "sg:address":"70 Wade Ave # 3",
    "sg:city":"Toronto",
    "sg:classifiers":[
        {
            "category":"Food & Beverages",
            "subcategory":"Specialty",
            "type":"Retail Goods"
        }
    ],
    "sg:phone":"+1 416 285 5300",
    "sg:postcode":"M6H 1P6",
    "sg:province":"ON",
    "sg:tags":[
        "health",
        "diet"
    ],
    "wof:name":"Green Earth Organics",
    "wof:placetype":"venue"
},
  "geometry": {"coordinates":[-79.44516,43.659847],"type":"Point"}
}