{
  "type": "Feature",
  "properties": {
    "addr:full":"1886 University Ave W Windsor ON N9B 1C6",
    "addr:housenumber":"1886",
    "addr:postcode":"n9b 1c6",
    "addr:street":"University Ave W",
    "iso:country":"CA",
    "sg:address":"1886 University Ave W",
    "sg:city":"Windsor",
    "sg:classifiers":[
        {
            "category":"Bars & Pubs",
            "type":"Food & Drink"
        }
    ],
    "sg:phone":"+1 519 252 1075",
    "sg:postcode":"N9B 1C6",
    "sg:province":"ON",
    "wof:name":"Bridge Tavern",
    "wof:placetype":"venue"
},
  "geometry": {"coordinates":[-83.0608215332,42.3112564087],"type":"Point"}
}