{
  "type": "Feature",
  "properties": {
    "addr:full":"800 Prince St Truro NS B2N 1H1",
    "addr:housenumber":"800",
    "addr:postcode":"b2n 1h1",
    "addr:street":"Prince St",
    "iso:country":"CA",
    "sg:address":"800 Prince St",
    "sg:city":"Truro",
    "sg:classifiers":[
        {
            "category":"Professional",
            "subcategory":"Accounting & Tax Preparation",
            "type":"Services"
        }
    ],
    "sg:phone":"+1 902 893 4200",
    "sg:postcode":"B2N 1H1",
    "sg:province":"NS",
    "sg:tags":[
        "bookkeeping",
        "general"
    ],
    "wof:name":"Tuttle Accounting Svc Ltd",
    "wof:placetype":"venue"
},
  "geometry": {"coordinates":[-63.277527,45.364616],"type":"Point"}
}