{
  "type": "Feature",
  "properties": {
    "addr:full":"London ON N6H 1T6",
    "addr:postcode":"n6h 1t6",
    "iso:country":"CA",
    "sg:city":"London",
    "sg:classifiers":[
        {
            "category":"Professional",
            "subcategory":"Accounting & Tax Preparation",
            "type":"Services"
        }
    ],
    "sg:phone":"+1 519 473 4405",
    "sg:postcode":"N6H 1T6",
    "sg:province":"ON",
    "sg:tags":[
        "return",
        "filing"
    ],
    "wof:name":"H & R Block Canada Inc",
    "wof:placetype":"venue"
},
  "geometry": {"coordinates":[-81.28996276860001,42.9844589233],"type":"Point"}
}