{
  "type": "Feature",
  "properties": {
    "addr:full":"North York ON M2R 2Z2",
    "addr:postcode":"m2r 2z2",
    "iso:country":"CA",
    "sg:city":"North York",
    "sg:classifiers":[
        {
            "category":"Professional",
            "subcategory":"Research",
            "type":"Services"
        }
    ],
    "sg:phone":"+1 416 665 1016",
    "sg:postcode":"M2R 2Z2",
    "sg:province":"ON",
    "sg:tags":[
        "market",
        "analysis"
    ],
    "wof:name":"June Connection",
    "wof:placetype":"venue"
},
  "geometry": {"coordinates":[-79.4472122192,43.7837028503],"type":"Point"}
}