{
  "type": "Feature",
  "properties": {
    "addr:full":"10866 Av Moisan Montreal-Nord QC H1G 4N7",
    "addr:housenumber":"10866",
    "addr:postcode":"h1g 4n7",
    "addr:street":"Av Moisan",
    "iso:country":"CA",
    "sg:address":"10866 Av Moisan",
    "sg:city":"Montreal-Nord",
    "sg:classifiers":[
        {
            "category":"Retail",
            "subcategory":"Auto Repair",
            "type":"Services"
        }
    ],
    "sg:phone":"+1 514 323 0270",
    "sg:postcode":"H1G 4N7",
    "sg:province":"QC",
    "sg:tags":[
        "wheel",
        "automobile",
        "painting",
        "alignment"
    ],
    "wof:name":"Chassis D'Auto Carrefour Inc",
    "wof:placetype":"venue"
},
  "geometry": {"coordinates":[-73.6160354614,45.6019363403],"type":"Point"}
}