{
  "type": "Feature",
  "properties": {
    "addr:full":"PO Box 63 Tulita NT X0E 0K0",
    "addr:housenumber":"po box 63",
    "addr:postcode":"x0e 0k0",
    "iso:country":"CA",
    "sg:address":"PO Box 63",
    "sg:city":"Tulita",
    "sg:classifiers":[
        {
            "category":"Real Estate",
            "subcategory":"Developer",
            "type":"Services"
        }
    ],
    "sg:phone":"+1 867 588 3734",
    "sg:postcode":"X0E 0K0",
    "sg:province":"NT",
    "sg:tags":[
        "consultant",
        "company",
        "land"
    ],
    "wof:name":"Tulita Land & Financial Corp",
    "wof:placetype":"venue"
},
  "geometry": {"coordinates":[-125.842033386,64.9491119385],"type":"Point"}
}