{
  "type": "Feature",
  "properties": {
    "addr:full":"9902 20th Ave North Battleford SK S9A 3M4",
    "addr:housenumber":"9902",
    "addr:postcode":"s9a 3m4",
    "addr:street":"20Th Ave",
    "iso:country":"CA",
    "sg:address":"9902 20th Ave",
    "sg:city":"North Battleford",
    "sg:classifiers":[
        {
            "category":"Shopping",
            "subcategory":"Musical Instruments",
            "type":"Retail Goods"
        }
    ],
    "sg:phone":"+1 306 445 7788",
    "sg:postcode":"S9A 3M4",
    "sg:province":"SK",
    "sg:tags":[
        "pawnbroker"
    ],
    "wof:name":"Classic Trading",
    "wof:placetype":"venue"
},
  "geometry": {"coordinates":[-108.301231,52.787006],"type":"Point"}
}