{
  "type": "Feature",
  "properties": {
    "addr:full":"103015 Grey Rd 18 Owen Sound ON N4K 5N6",
    "addr:housenumber":"103015;18",
    "addr:postcode":"n4k 5n6",
    "addr:street":"Grey Rd",
    "iso:country":"CA",
    "sg:address":"103015 Grey Rd 18",
    "sg:city":"Owen Sound",
    "sg:classifiers":[
        {
            "category":"Manufacturing",
            "subcategory":"Pet Food",
            "type":"Manufacturing & Wholesale Goods"
        }
    ],
    "sg:phone":"+1 519 372 1818",
    "sg:postcode":"N4K 5N6",
    "sg:province":"ON",
    "sg:tags":[
        "dog",
        "cat"
    ],
    "wof:name":"Pets 4 Life",
    "wof:placetype":"venue"
},
  "geometry": {"coordinates":[-80.942604,44.564877],"type":"Point"}
}