{
  "type": "Feature",
  "properties": {
    "addr:full":"1295 St Clair Ave W Toronto ON M6E 1C2",
    "addr:housenumber":"1295",
    "addr:postcode":"m6e 1c2",
    "addr:street":"St Clair Ave W",
    "iso:country":"CA",
    "sg:address":"1295 St Clair Ave W",
    "sg:city":"Toronto",
    "sg:classifiers":[
        {
            "category":"Banks & Credit Unions",
            "subcategory":"Bank",
            "type":"Services"
        }
    ],
    "sg:phone":"+1 416 654 8890",
    "sg:postcode":"M6E 1C2",
    "sg:province":"ON",
    "wof:name":"National Bank of Canada",
    "wof:placetype":"venue"
},
  "geometry": {"coordinates":[-79.4481964111,43.6767654419],"type":"Point"}
}