{
  "type": "Feature",
  "properties": {
    "addr:full":"40 Rue Evangeline Granby QC J2G 8K1",
    "addr:housenumber":"40",
    "addr:postcode":"j2g 8k1",
    "addr:street":"Rue Evangeline",
    "iso:country":"CA",
    "sg:address":"40 Rue Evangeline",
    "sg:city":"Granby",
    "sg:classifiers":[
        {
            "category":"Shopping",
            "subcategory":"Luggage & Leather Goods",
            "type":"Retail Goods"
        }
    ],
    "sg:phone":"+1 450 375 3626",
    "sg:postcode":"J2G 8K1",
    "sg:province":"QC",
    "wof:name":"Access",
    "wof:placetype":"venue"
},
  "geometry": {"coordinates":[-72.7486190796,45.4135284424],"type":"Point"}
}