{
  "type": "Feature",
  "properties": {
    "addr:full":"900 Boul Grignon # 59 Saint-Jerome QC J7Y 3S7",
    "addr:housenumber":"900;# 59",
    "addr:postcode":"j7y 3s7",
    "addr:street":"Boul Grignon;Saint-Jerome",
    "iso:country":"CA",
    "sg:address":"900 Boul Grignon # 59",
    "sg:city":"Saint-Jerome",
    "sg:classifiers":[
        {
            "category":"Shopping",
            "subcategory":"Jewelry",
            "type":"Retail Goods"
        }
    ],
    "sg:phone":"+1 450 432 2888",
    "sg:postcode":"J7Y 3S7",
    "sg:province":"QC",
    "sg:tags":[
        "jeweler"
    ],
    "wof:name":"Bijouterie Doucet",
    "wof:placetype":"venue"
},
  "geometry": {"coordinates":[-74.015625,45.79472],"type":"Point"}
}