{
  "type": "Feature",
  "properties": {
    "addr:full":"57 Madawaska St Arnprior ON K7S 1R8",
    "addr:housenumber":"57",
    "addr:postcode":"k7s 1r8",
    "addr:street":"Madawaska St",
    "iso:country":"CA",
    "sg:address":"57 Madawaska St",
    "sg:city":"Arnprior",
    "sg:classifiers":[
        {
            "category":"Personal",
            "subcategory":"Beauty Salon",
            "type":"Services"
        }
    ],
    "sg:phone":"+1 613 623 3987",
    "sg:postcode":"K7S 1R8",
    "sg:province":"ON",
    "wof:name":"A'Head of Style",
    "wof:placetype":"venue"
},
  "geometry": {"coordinates":[-76.35420999999999,45.435043],"type":"Point"}
}