{
  "type": "Feature",
  "properties": {
    "iso:country":"CA",
    "sg:address":"950 Gladstone Ave",
    "sg:city":"Ottawa",
    "sg:classifiers":[
        {
            "category":"Manufacturing",
            "subcategory":"Printing",
            "type":"Manufacturing & Wholesale Goods"
        }
    ],
    "sg:phone":"+1 613 729 4200",
    "sg:postcode":"K1Y 3E6",
    "sg:province":"ON",
    "sg:tags":[
        "newspaper",
        "advertising"
    ],
    "wof:name":"Auto Trader",
    "wof:placetype":"venue"
},
  "geometry": {"coordinates":[-75.71505,45.403439],"type":"Point"}
}