{
  "type": "Feature",
  "properties": {
    "addr:full":"Houston BC V0J 1Z0",
    "addr:postcode":"v0j 1z0",
    "iso:country":"CA",
    "sg:city":"Houston",
    "sg:classifiers":[
        {
            "category":"Autos & Motor Vehicles",
            "subcategory":"Auto Supplies",
            "type":"Retail Goods"
        }
    ],
    "sg:phone":"+1 250 845 7341",
    "sg:postcode":"V0J 1Z0",
    "sg:province":"BC",
    "sg:tags":[
        "tire"
    ],
    "wof:name":"Kal Tire",
    "wof:placetype":"venue"
},
  "geometry": {"coordinates":[-126.656998,54.39732],"type":"Point"}
}