{
  "type": "Feature",
  "properties": {
    "iso:country":"CA",
    "sg:address":"7110 Bulyea Ave",
    "sg:city":"Fort Mcmurray",
    "sg:classifiers":[
        {
            "category":"Freight",
            "type":"Transportation"
        }
    ],
    "sg:phone":"+1 780 743 4487",
    "sg:postcode":"T9H 1B1",
    "sg:province":"AB",
    "sg:tags":[
        "sand",
        "gravel",
        "trucking"
    ],
    "wof:name":"Metro Gordey Trucking Ltd",
    "wof:placetype":"venue"
},
  "geometry": {"coordinates":[-111.336181641,56.6982460022],"type":"Point"}
}