{
  "type": "Feature",
  "properties": {
    "iso:country":"CA",
    "sg:city":"Rankin Inlet",
    "sg:classifiers":[
        {
            "category":"Travel",
            "subcategory":"Travel Agent",
            "type":"Entertainment"
        }
    ],
    "sg:phone":"+1 867 645 2650",
    "sg:postcode":"X0C 0G0",
    "sg:province":"NU",
    "sg:tags":[
        "information",
        "tourist"
    ],
    "wof:name":"Nanuk Enterprises Ltd",
    "wof:placetype":"venue"
},
  "geometry": {"coordinates":[-92.08335113530001,62.807144165],"type":"Point"}
}