{
  "type": "Feature",
  "properties": {
    "addr:full":"6448 Quinpool Rd Halifax NS B3L 1A8",
    "addr:housenumber":"6448",
    "addr:postcode":"b3l 1a8",
    "addr:street":"Quinpool Rd",
    "iso:country":"CA",
    "sg:address":"6448 Quinpool Rd",
    "sg:city":"Halifax",
    "sg:classifiers":[
        {
            "category":"Retail",
            "subcategory":"Repair Shop",
            "type":"Services"
        }
    ],
    "sg:phone":"+1 902 499 3647",
    "sg:postcode":"B3L 1A8",
    "sg:province":"NS",
    "sg:tags":[
        "sharpening"
    ],
    "wof:name":"Blade Runner",
    "wof:placetype":"venue"
},
  "geometry": {"coordinates":[-63.6014671326,44.6440238953],"type":"Point"}
}