{
  "type": "Feature",
  "properties": {
    "addr:full":"2580 Birchmount Rd Scarborough ON M1T 2M5",
    "addr:housenumber":"2580",
    "addr:postcode":"m1t 2m5",
    "addr:street":"Birchmount Rd",
    "iso:country":"CA",
    "sg:address":"2580 Birchmount Rd",
    "sg:city":"Scarborough",
    "sg:classifiers":[
        {
            "category":"Personal",
            "subcategory":"Beauty Salon",
            "type":"Services"
        }
    ],
    "sg:phone":"+1 416 291 2119",
    "sg:postcode":"M1T 2M5",
    "sg:province":"ON",
    "wof:name":"Gondola Hair Design",
    "wof:placetype":"venue"
},
  "geometry": {"coordinates":[-79.3017654419,43.7887573242],"type":"Point"}
}