{
  "type": "Feature",
  "properties": {
    "addr:full":"5051 Yonge St North York ON M2N 5P2",
    "addr:housenumber":"5051",
    "addr:postcode":"m2n 5p2",
    "addr:street":"Yonge St",
    "iso:country":"CA",
    "sg:address":"5051 Yonge St",
    "sg:city":"North York",
    "sg:classifiers":[
        {
            "category":"Home & Garden",
            "subcategory":"Furniture",
            "type":"Retail Goods"
        }
    ],
    "sg:phone":"+1 416 226 3730",
    "sg:postcode":"M2N 5P2",
    "sg:province":"ON",
    "wof:name":"DE Boer's",
    "wof:placetype":"venue"
},
  "geometry": {"coordinates":[-79.412148,43.767094],"type":"Point"}
}