{
  "type": "Feature",
  "properties": {
    "addr:full":"55 Rutherford Rd S # 205 Brampton ON L6W 3J3",
    "addr:housenumber":"55",
    "addr:postcode":"l6w 3j3",
    "addr:street":"Rutherford Rd S # 205",
    "iso:country":"CA",
    "sg:address":"55 Rutherford Rd S # 205",
    "sg:city":"Brampton",
    "sg:classifiers":[
        {
            "category":"Freight",
            "type":"Transportation"
        }
    ],
    "sg:phone":"+1 905 453 3817",
    "sg:postcode":"L6W 3J3",
    "sg:province":"ON",
    "sg:tags":[
        "trucking"
    ],
    "wof:name":"Flagship Transportation Svc",
    "wof:placetype":"venue"
},
  "geometry": {"coordinates":[-79.7356338501,43.6965103149],"type":"Point"}
}