{
  "type": "Feature",
  "properties": {
    "addr:full":"425 Phipps St Fort Erie ON L2A 2W1",
    "addr:housenumber":"425",
    "addr:postcode":"l2a 2w1",
    "addr:street":"Phipps St",
    "iso:country":"CA",
    "sg:address":"425 Phipps St",
    "sg:city":"Fort Erie",
    "sg:classifiers":[
        {
            "category":"Manufacturing",
            "subcategory":"Metals",
            "type":"Manufacturing & Wholesale Goods"
        }
    ],
    "sg:phone":"+1 905 871 6191",
    "sg:postcode":"L2A 2W1",
    "sg:province":"ON",
    "sg:tags":[
        "treating",
        "heat"
    ],
    "wof:name":"Metcor Inc",
    "wof:placetype":"venue"
},
  "geometry": {"coordinates":[-78.930992,42.931129],"type":"Point"}
}