{
  "type": "Feature",
  "properties": {
    "addr:full":"RR 5 Wiarton ON N0H 2T0",
    "addr:postcode":"n0h 2t0",
    "addr:street":"Rr 5 Wiarton",
    "iso:country":"CA",
    "sg:address":"RR 5",
    "sg:city":"Wiarton",
    "sg:classifiers":[
        {
            "category":"Recreation",
            "type":"Entertainment"
        }
    ],
    "sg:phone":"+1 519 534 3266",
    "sg:postcode":"N0H 2T0",
    "sg:province":"ON",
    "sg:tags":[
        "center"
    ],
    "wof:name":"Nawash First Nation Rec Dept",
    "wof:placetype":"venue"
},
  "geometry": {"coordinates":[-81.1397857666,44.7401351929],"type":"Point"}
}