{
  "type": "Feature",
  "properties": {
    "addr:full":"2010A Queen St E Toronto ON M4L 1J3",
    "addr:housenumber":"2010a",
    "addr:postcode":"m4l 1j3",
    "addr:street":"Queen St E",
    "iso:country":"CA",
    "sg:address":"2010A Queen St E",
    "sg:city":"Toronto",
    "sg:classifiers":[
        {
            "category":"Home & Garden",
            "subcategory":"Garden Supply",
            "type":"Retail Goods"
        }
    ],
    "sg:phone":"+1 416 698 5339",
    "sg:postcode":"M4L 1J3",
    "sg:province":"ON",
    "sg:tags":[
        "lawn"
    ],
    "wof:name":"Gardenscape Tools",
    "wof:placetype":"venue"
},
  "geometry": {"coordinates":[-79.299408,43.670315],"type":"Point"}
}