{
  "type": "Feature",
  "properties": {
    "addr:full":"2569 Rue DE Miniac Saint-Laurent QC H4S 1E5",
    "addr:housenumber":"2569",
    "addr:postcode":"h4s 1e5",
    "addr:street":"Rue De Miniac",
    "iso:country":"CA",
    "sg:address":"2569 Rue DE Miniac",
    "sg:city":"Saint-Laurent",
    "sg:classifiers":[
        {
            "category":"Wholesale",
            "subcategory":"Machinery & Supplies",
            "type":"Manufacturing & Wholesale Goods"
        }
    ],
    "sg:phone":"+1 514 332 4824",
    "sg:postcode":"H4S 1E5",
    "sg:province":"QC",
    "sg:tags":[
        "pump"
    ],
    "wof:name":"Viking Pump of Canada Inc",
    "wof:placetype":"venue"
},
  "geometry": {"coordinates":[-73.7460098267,45.4925003052],"type":"Point"}
}