{
  "type": "Feature",
  "properties": {
    "addr:full":"769 Gladstone Ave Ottawa ON K1R 6X4",
    "addr:housenumber":"769",
    "addr:postcode":"k1r 6x4",
    "addr:street":"Gladstone Ave",
    "iso:country":"CA",
    "sg:address":"769 Gladstone Ave",
    "sg:city":"Ottawa",
    "sg:classifiers":[
        {
            "category":"Restaurant",
            "type":"Food & Drink"
        }
    ],
    "sg:phone":"+1 613 234 9379",
    "sg:postcode":"K1R 6X4",
    "sg:province":"ON",
    "wof:name":"Brothers Restaurant",
    "wof:placetype":"venue"
},
  "geometry": {"coordinates":[-75.706131,45.40696],"type":"Point"}
}