{
  "type": "Feature",
  "properties": {
    "addr:full":"6442 Quinpool Rd Halifax NS B3L 1A8",
    "addr:housenumber":"6442",
    "addr:postcode":"b3l 1a8",
    "addr:street":"Quinpool Rd",
    "iso:country":"CA",
    "sg:address":"6442 Quinpool Rd",
    "sg:city":"Halifax",
    "sg:classifiers":[
        {
            "category":"Retail",
            "subcategory":"Laundry & Dry Cleaning",
            "type":"Services"
        }
    ],
    "sg:phone":"+1 902 429 2976",
    "sg:postcode":"B3L 1A8",
    "sg:province":"NS",
    "sg:tags":[
        "cleaners"
    ],
    "wof:name":"Koolex Kleaners",
    "wof:placetype":"venue"
},
  "geometry": {"coordinates":[-63.601372,44.644073],"type":"Point"}
}