{
  "type": "Feature",
  "properties": {
    "addr:full":"Niagara on the Lake ON L0S 1J0",
    "addr:postcode":"l0s 1j0",
    "iso:country":"CA",
    "sg:city":"Niagara on the Lake",
    "sg:classifiers":[
        {
            "category":"Manufacturing",
            "subcategory":"Glass & Minerals",
            "type":"Manufacturing & Wholesale Goods"
        }
    ],
    "sg:phone":"+1 905 468 0500",
    "sg:postcode":"L0S 1J0",
    "sg:province":"ON",
    "sg:tags":[
        "stone",
        "product"
    ],
    "wof:name":"Upper Canada Stone CO Ltd",
    "wof:placetype":"venue"
},
  "geometry": {"coordinates":[-79.0921325684,43.2499656677],"type":"Point"}
}