{
  "type": "Feature",
  "properties": {
    "addr:full":"147 Euclid Ave Scarborough ON M1C 1K2",
    "addr:housenumber":"147",
    "addr:postcode":"m1c 1k2",
    "addr:street":"Euclid Ave",
    "iso:country":"CA",
    "sg:address":"147 Euclid Ave",
    "sg:city":"Scarborough",
    "sg:classifiers":[
        {
            "category":"Professional",
            "subcategory":"Accounting & Tax Preparation",
            "type":"Services"
        }
    ],
    "sg:phone":"+1 416 282 6202",
    "sg:postcode":"M1C 1K2",
    "sg:province":"ON",
    "sg:tags":[
        "accountant"
    ],
    "wof:name":"D Woods & Assoc",
    "wof:placetype":"venue"
},
  "geometry": {"coordinates":[-79.16683999999999,43.795418],"type":"Point"}
}