{
  "type": "Feature",
  "properties": {
    "addr:full":"55 Keays St Dauphin MB R7N 3B3",
    "addr:housenumber":"55",
    "addr:postcode":"r7n 3b3",
    "addr:street":"Keays St",
    "iso:country":"CA",
    "sg:address":"55 Keays St",
    "sg:city":"Dauphin",
    "sg:classifiers":[
        {
            "category":"Building & Trades",
            "subcategory":"Equipment Rental",
            "type":"Services"
        }
    ],
    "sg:phone":"+1 204 622 5505",
    "sg:postcode":"R7N 3B3",
    "sg:province":"MB",
    "sg:tags":[
        "contractor"
    ],
    "wof:name":"T R Rentals",
    "wof:placetype":"venue"
},
  "geometry": {"coordinates":[-100.063545,51.159107],"type":"Point"}
}