{
  "type": "Feature",
  "properties": {
    "addr:full":"285 Rue Gaspard N Joliette QC J6E 5T8",
    "addr:housenumber":"285",
    "addr:postcode":"j6e 5t8",
    "addr:street":"Rue Gaspard N",
    "iso:country":"CA",
    "sg:address":"285 Rue Gaspard N",
    "sg:city":"Joliette",
    "sg:classifiers":[
        {
            "category":"Building & Trades",
            "subcategory":"Cleaning & Sanitation",
            "type":"Services"
        }
    ],
    "sg:phone":"+1 450 759 4368",
    "sg:postcode":"J6E 5T8",
    "sg:province":"QC",
    "sg:tags":[
        "janitor"
    ],
    "wof:name":"Entretien Mira-Sol Inc",
    "wof:placetype":"venue"
},
  "geometry": {"coordinates":[-73.44976800000001,46.024719],"type":"Point"}
}