{
  "type": "Feature",
  "properties": {
    "addr:full":"30 Albert St Clinton ON N0M 1L0",
    "addr:housenumber":"30",
    "addr:postcode":"n0m 1l0",
    "addr:street":"Albert St",
    "iso:country":"CA",
    "sg:address":"30 Albert St",
    "sg:city":"Clinton",
    "sg:classifiers":[
        {
            "category":"Building & Trades",
            "subcategory":"Construction",
            "type":"Services"
        }
    ],
    "sg:phone":"+1 519 482 1234",
    "sg:postcode":"N0M 1L0",
    "sg:province":"ON",
    "sg:tags":[
        "painter"
    ],
    "wof:name":"Rick's Painting",
    "wof:placetype":"venue"
},
  "geometry": {"coordinates":[-81.539894,43.61845],"type":"Point"}
}