{
  "type": "Feature",
  "properties": {
    "addr:full":"31 Rue DE L'Ermitage Blainville QC J7B 1K3",
    "addr:housenumber":"31",
    "addr:postcode":"j7b 1k3",
    "addr:street":"Rue De L'Ermitage",
    "iso:country":"CA",
    "sg:address":"31 Rue DE L'Ermitage",
    "sg:city":"Blainville",
    "sg:classifiers":[
        {
            "category":"Building & Trades",
            "subcategory":"Construction",
            "type":"Services"
        }
    ],
    "sg:phone":"+1 450 979 2665",
    "sg:postcode":"J7B 1K3",
    "sg:province":"QC",
    "sg:tags":[
        "detection",
        "splicing",
        "installation",
        "cable"
    ],
    "wof:name":"Systemes DE Cablage Gemini",
    "wof:placetype":"venue"
},
  "geometry": {"coordinates":[-73.804253,45.660892],"type":"Point"}
}