{
  "type": "Feature",
  "properties": {
    "addr:full":"Montreal QC H2S 3C7",
    "addr:postcode":"h2s 3c7",
    "iso:country":"CA",
    "sg:city":"Montreal",
    "sg:classifiers":[
        {
            "category":"Professional",
            "subcategory":"Business Services",
            "type":"Services"
        }
    ],
    "sg:phone":"+1 514 279 8421",
    "sg:postcode":"H2S 3C7",
    "sg:province":"QC",
    "sg:tags":[
        "notary"
    ],
    "wof:name":"Esposito & Assoc",
    "wof:placetype":"venue"
},
  "geometry": {"coordinates":[-73.61450958250001,45.5328063965],"type":"Point"}
}