{
  "type": "Feature",
  "properties": {
    "addr:full":"12287 84 Ave Surrey BC V3W 3G7",
    "addr:housenumber":"12287",
    "addr:postcode":"v3w 3g7",
    "addr:street":"84 Ave",
    "iso:country":"CA",
    "sg:address":"12287 84 Ave",
    "sg:city":"Surrey",
    "sg:classifiers":[
        {
            "category":"Professional",
            "subcategory":"Computer Services",
            "type":"Services"
        }
    ],
    "sg:phone":"+1 604 501 0369",
    "sg:postcode":"V3W 3G7",
    "sg:province":"BC",
    "sg:tags":[
        "consultant",
        "designer"
    ],
    "wof:name":"Bbr Technologies Inc",
    "wof:placetype":"venue"
},
  "geometry": {"coordinates":[-122.882835,49.155991],"type":"Point"}
}