{
  "type": "Feature",
  "properties": {
    "addr:full":"200 Dundas St Cambridge ON N1R 5P4",
    "addr:housenumber":"200",
    "addr:postcode":"n1r 5p4",
    "addr:street":"Dundas St",
    "iso:country":"CA",
    "sg:address":"200 Dundas St",
    "sg:city":"Cambridge",
    "sg:classifiers":[
        {
            "category":"Autos & Motor Vehicles",
            "subcategory":"Automobile Sales",
            "type":"Retail Goods"
        }
    ],
    "sg:phone":"+1 519 621 9991",
    "sg:postcode":"N1R 5P4",
    "sg:province":"ON",
    "sg:tags":[
        "car",
        "dealer"
    ],
    "wof:name":"Regency Auto Sales & Leasing",
    "wof:placetype":"venue"
},
  "geometry": {"coordinates":[-80.30085,43.362572],"type":"Point"}
}