{
  "type": "Feature",
  "properties": {
    "iso:country":"CA",
    "sg:address":"301 Cordova St W",
    "sg:city":"Vancouver",
    "sg:classifiers":[
        {
            "category":"Restaurant",
            "type":"Food & Drink"
        }
    ],
    "sg:phone":"+1 604 681 4323",
    "sg:postcode":"V6B 1E5",
    "sg:province":"BC",
    "wof:name":"Bambo Cafe",
    "wof:placetype":"venue"
},
  "geometry": {"coordinates":[-123.109130859,49.2835998535],"type":"Point"}
}