{
  "type": "Feature",
  "properties": {
    "addr:full":"4986 Dundas St W Etobicoke ON M9A 1B7",
    "addr:housenumber":"4986",
    "addr:postcode":"m9a 1b7",
    "addr:street":"Dundas St W",
    "iso:country":"CA",
    "sg:address":"4986 Dundas St W",
    "sg:city":"Etobicoke",
    "sg:classifiers":[
        {
            "category":"Health Services",
            "subcategory":"Chiropractor",
            "type":"Services"
        }
    ],
    "sg:phone":"+1 416 233 5673",
    "sg:postcode":"M9A 1B7",
    "sg:province":"ON",
    "wof:name":"Mac Gillivray, Charles J DC",
    "wof:placetype":"venue"
},
  "geometry": {"coordinates":[-79.5303039551,43.6472625732],"type":"Point"}
}