{
  "type": "Feature",
  "properties": {
    "addr:full":"938 Rue Saint-Thomas Laval QC H7W 1A4",
    "addr:housenumber":"938",
    "addr:postcode":"h7w 1a4",
    "addr:street":"Rue Saint-Thomas",
    "iso:country":"CA",
    "sg:address":"938 Rue Saint-Thomas",
    "sg:city":"Laval",
    "sg:classifiers":[
        {
            "category":"Building & Trades",
            "subcategory":"Construction",
            "type":"Services"
        }
    ],
    "sg:phone":"+1 450 681 7048",
    "sg:postcode":"H7W 1A4",
    "sg:province":"QC",
    "sg:tags":[
        "designer",
        "dealer",
        "pool",
        "swimming"
    ],
    "wof:name":"Piscines Bonaventure Inc",
    "wof:placetype":"venue"
},
  "geometry": {"coordinates":[-73.75915500000001,45.549381],"type":"Point"}
}