{
  "type": "Feature",
  "properties": {
    "addr:full":"Langley BC V1M 3C7",
    "addr:postcode":"v1m 3c7",
    "iso:country":"CA",
    "sg:city":"Langley",
    "sg:classifiers":[
        {
            "category":"Retail",
            "subcategory":"Auto Repair",
            "type":"Services"
        }
    ],
    "sg:phone":"+1 604 513 9200",
    "sg:postcode":"V1M 3C7",
    "sg:province":"BC",
    "sg:tags":[
        "repairing",
        "automobile"
    ],
    "wof:name":"Minit-Tune & Brake Auto Ctr",
    "wof:placetype":"venue"
},
  "geometry": {"coordinates":[-122.670806885,49.1771965027],"type":"Point"}
}