{
  "type": "Feature",
  "properties": {
    "addr:full":"Saanichton BC V8M 2A5",
    "addr:postcode":"v8m 2a5",
    "iso:country":"CA",
    "sg:city":"Saanichton",
    "sg:classifiers":[
        {
            "category":"Home & Garden",
            "subcategory":"Home Furnishings",
            "type":"Retail Goods"
        }
    ],
    "sg:phone":"+1 250 544 6769",
    "sg:postcode":"V8M 2A5",
    "sg:province":"BC",
    "sg:tags":[
        "fireplace"
    ],
    "wof:name":"Pacific Fireplaces",
    "wof:placetype":"venue"
},
  "geometry": {"coordinates":[-123.409187317,48.5650177002],"type":"Point"}
}