{
  "type": "Feature",
  "properties": {
    "addr:full":"Grand-Sault/Grand Falls NB E3Z 2K3",
    "addr:postcode":"e3z 2k3",
    "iso:country":"CA",
    "sg:city":"Grand-Sault/Grand Falls",
    "sg:classifiers":[
        {
            "category":"Personal",
            "subcategory":"Barber",
            "type":"Services"
        }
    ],
    "sg:phone":"+1 506 473 4103",
    "sg:postcode":"E3Z 2K3",
    "sg:province":"NB",
    "sg:tags":[
        "salon",
        "beauty"
    ],
    "wof:name":"Miche Barber Shop",
    "wof:placetype":"venue"
},
  "geometry": {"coordinates":[-67.7423782349,47.0464744568],"type":"Point"}
}