{
  "type": "Feature",
  "properties": {
    "addr:full":"4376 Boul Bourque Rock Forest QC J1N 1S3",
    "addr:housenumber":"4376",
    "addr:postcode":"j1n 1s3",
    "addr:street":"Boul Bourque",
    "iso:country":"CA",
    "sg:address":"4376 Boul Bourque",
    "sg:city":"Rock Forest",
    "sg:classifiers":[
        {
            "category":"Retail",
            "subcategory":"Auto Repair",
            "type":"Services"
        }
    ],
    "sg:phone":"+1 819 821 4788",
    "sg:postcode":"J1N 1S3",
    "sg:province":"QC",
    "sg:tags":[
        "body",
        "automobile",
        "painting"
    ],
    "wof:name":"Carrosserie Real Blouin",
    "wof:placetype":"venue"
},
  "geometry": {"coordinates":[-71.97479199999999,45.378609],"type":"Point"}
}