{
  "type": "Feature",
  "properties": {
    "iso:country":"CA",
    "sg:address":"4376 Boul Bourque",
    "sg:city":"Rock Forest",
    "sg:classifiers":[
        {
            "category":"Retail",
            "subcategory":"Auto Repair",
            "type":"Services"
        }
    ],
    "sg:phone":"+1 819 821 4788",
    "sg:postcode":"J1N 1S3",
    "sg:province":"QC",
    "sg:tags":[
        "body",
        "automobile",
        "painting"
    ],
    "wof:name":"Carrosserie Real Blouin",
    "wof:placetype":"venue"
},
  "geometry": {"coordinates":[-71.974792,45.378609],"type":"Point"}
}