{
  "type": "Feature",
  "properties": {
    "addr:full":"3849 Rue Colbert Jonquiere QC G7X 0E6",
    "addr:housenumber":"3849",
    "addr:postcode":"g7x 0e6",
    "addr:street":"Rue Colbert",
    "iso:country":"CA",
    "sg:address":"3849 Rue Colbert",
    "sg:city":"Jonquiere",
    "sg:classifiers":[
        {
            "category":"Organizations",
            "subcategory":"Community Association",
            "type":"Services"
        }
    ],
    "sg:phone":"+1 418 546 0055",
    "sg:postcode":"G7X 0E6",
    "sg:province":"QC",
    "sg:tags":[
        "club"
    ],
    "wof:name":"Club DE Gymnastique Jako Inc",
    "wof:placetype":"venue"
},
  "geometry": {"coordinates":[-71.25248000000001,48.41132],"type":"Point"}
}