{
  "type": "Feature",
  "properties": {
    "addr:full":"8292 Av Sous-Le-Vent Charny QC G6X 1K3",
    "addr:housenumber":"8292",
    "addr:postcode":"g6x 1k3",
    "addr:street":"Av Sous-Le-Vent",
    "iso:country":"CA",
    "sg:address":"8292 Av Sous-Le-Vent",
    "sg:city":"Charny",
    "sg:classifiers":[
        {
            "category":"Professional",
            "subcategory":"Business Services",
            "type":"Services"
        }
    ],
    "sg:phone":"+1 418 832 5852",
    "sg:postcode":"G6X 1K3",
    "sg:province":"QC",
    "sg:tags":[
        "painter",
        "sign"
    ],
    "wof:name":"Enseignes Stenaco Enr",
    "wof:placetype":"venue"
},
  "geometry": {"coordinates":[-71.26861599999999,46.722256],"type":"Point"}
}