{
  "type": "Feature",
  "properties": {
    "addr:full":"12 Colborne St S Walkerton ON N0G 2V0",
    "addr:housenumber":"12",
    "addr:postcode":"n0g 2v0",
    "addr:street":"Colborne St S Walkerton",
    "iso:country":"CA",
    "sg:address":"12 Colborne St S",
    "sg:city":"Walkerton",
    "sg:classifiers":[
        {
            "category":"Personal",
            "subcategory":"Beauty Salon",
            "type":"Services"
        }
    ],
    "sg:phone":"+1 519 881 1847",
    "sg:postcode":"N0G 2V0",
    "sg:province":"ON",
    "wof:name":"Styles By Elaine",
    "wof:placetype":"venue"
},
  "geometry": {"coordinates":[-81.1484375,44.1328926086],"type":"Point"}
}