{
  "type": "Feature",
  "properties": {
    "addr:full":"2 Ch DE L'Equerre Baie-Saint-Paul QC G3Z 2Y5",
    "addr:housenumber":"2",
    "addr:postcode":"g3z 2y5",
    "addr:street":"Ch De L'Equerre",
    "iso:country":"CA",
    "sg:address":"2 Ch DE L'Equerre",
    "sg:city":"Baie-Saint-Paul",
    "sg:classifiers":[
        {
            "category":"Shopping",
            "subcategory":"Shoes",
            "type":"Retail Goods"
        }
    ],
    "sg:phone":"+1 418 435 5491",
    "sg:postcode":"G3Z 2Y5",
    "sg:province":"QC",
    "wof:name":"Chaussure Helen Inc",
    "wof:placetype":"venue"
},
  "geometry": {"coordinates":[-70.5255203247,47.4457359314],"type":"Point"}
}