{
  "type": "Feature",
  "properties": {
    "addr:full":"Main St Inverness NS B0E 1N0",
    "addr:postcode":"b0e 1n0",
    "addr:street":"Main St",
    "iso:country":"CA",
    "sg:address":"Main St",
    "sg:city":"Inverness",
    "sg:classifiers":[
        {
            "category":"Insurance",
            "subcategory":"Insurance Agent",
            "type":"Services"
        }
    ],
    "sg:phone":"+1 902 258 2484",
    "sg:postcode":"B0E 1N0",
    "sg:province":"NS",
    "wof:name":"A A Munro Insurance Ltd",
    "wof:placetype":"venue"
},
  "geometry": {"coordinates":[-61.304523468,46.2312049866],"type":"Point"}
}