{
  "type": "Feature",
  "properties": {
    "iso:country":"CA",
    "sg:address":"11422 Boul Albert-Hudon",
    "sg:city":"Montreal-Nord",
    "sg:classifiers":[
        {
            "category":"Professional",
            "type":"Services"
        }
    ],
    "sg:phone":"+1 514 325 4633",
    "sg:postcode":"H1G 3J6",
    "sg:province":"QC",
    "sg:tags":[
        "automobile",
        "parts",
        "establishment",
        "supply"
    ],
    "wof:name":"Atlas Auto Accessories CO Inc",
    "wof:placetype":"venue"
},
  "geometry": {"coordinates":[-73.60791778559999,45.6139068604],"type":"Point"}
}