{
  "type": "Feature",
  "properties": {
    "addr:full":"3100 Ridgeway Dr #1 Mississauga ON L5L 5M5",
    "addr:housenumber":"3100",
    "addr:postcode":"l5l 5m5",
    "addr:street":"Ridgeway Dr # 1",
    "iso:country":"CA",
    "sg:address":"3100 Ridgeway Dr #1",
    "sg:city":"Mississauga",
    "sg:classifiers":[
        {
            "category":"Retail",
            "subcategory":"Repair Shop",
            "type":"Services"
        }
    ],
    "sg:phone":"+1 905 858 3477",
    "sg:postcode":"L5L 5M5",
    "sg:province":"ON",
    "sg:tags":[
        "door"
    ],
    "wof:name":"Rekeys Lock Stock & Barrel",
    "wof:placetype":"venue"
},
  "geometry": {"coordinates":[-79.691002,43.518375],"type":"Point"}
}