{
  "type": "Feature",
  "properties": {
    "addr:full":"360 Rte 308 N Tusket NS B0W 3M0",
    "addr:housenumber":"360",
    "addr:postcode":"b0w 3m0",
    "addr:street":"Rte 308 N",
    "iso:country":"CA",
    "sg:address":"360 Rte 308 N",
    "sg:city":"Tusket",
    "sg:classifiers":[
        {
            "category":"Education",
            "subcategory":"School",
            "type":"Public Place"
        }
    ],
    "sg:phone":"+1 902 648 5900",
    "sg:postcode":"B0W 3M0",
    "sg:province":"NS",
    "wof:name":"Ecole Secondaire DE Par-En-Bas",
    "wof:placetype":"venue"
},
  "geometry": {"coordinates":[-65.976753,43.859447],"type":"Point"}
}