{
  "type": "Feature",
  "properties": {
    "addr:full":"5 King St Kingsville ON N9Y 1H9",
    "addr:housenumber":"5",
    "addr:postcode":"n9y 1h9",
    "addr:street":"King St",
    "iso:country":"CA",
    "sg:address":"5 King St",
    "sg:city":"Kingsville",
    "sg:classifiers":[
        {
            "category":"Insurance",
            "subcategory":"Insurance Agent",
            "type":"Services"
        }
    ],
    "sg:phone":"+1 519 733 2349",
    "sg:postcode":"N9Y 1H9",
    "sg:province":"ON",
    "wof:name":"Wilson, Bonnie",
    "wof:placetype":"venue"
},
  "geometry": {"coordinates":[-82.739746,42.038715],"type":"Point"}
}