{
  "type": "Feature",
  "properties": {
    "addr:full":"950 Islington Ave Etobicoke ON M8Z 4P6",
    "addr:housenumber":"950",
    "addr:postcode":"m8z 4p6",
    "addr:street":"Islington Ave",
    "iso:country":"CA",
    "sg:address":"950 Islington Ave",
    "sg:city":"Etobicoke",
    "sg:classifiers":[
        {
            "category":"Organizations",
            "subcategory":"Religious Organization",
            "type":"Services"
        }
    ],
    "sg:phone":"+1 416 251 6121",
    "sg:postcode":"M8Z 4P6",
    "sg:province":"ON",
    "sg:tags":[
        "church"
    ],
    "wof:name":"Queensway Baptist Church",
    "wof:placetype":"venue"
},
  "geometry": {"coordinates":[-79.51655599999999,43.627438],"type":"Point"}
}