{
  "type": "Feature",
  "properties": {
    "addr:full":"59 Rue Principale # 68 Lachute QC J8H 3A7",
    "addr:housenumber":"59",
    "addr:postcode":"j8h 3a7",
    "addr:street":"Rue Principale # 68",
    "iso:country":"CA",
    "sg:address":"59 Rue Principale # 68",
    "sg:city":"Lachute",
    "sg:classifiers":[
        {
            "category":"Home & Garden",
            "subcategory":"Garden Supply",
            "type":"Retail Goods"
        }
    ],
    "sg:phone":"+1 450 562 3434",
    "sg:postcode":"J8H 3A7",
    "sg:province":"QC",
    "sg:tags":[
        "engine",
        "lawn",
        "mower"
    ],
    "wof:name":"Au Petit Moteur DE Lachute",
    "wof:placetype":"venue"
},
  "geometry": {"coordinates":[-74.361794,45.652847],"type":"Point"}
}