{
  "type": "Feature",
  "properties": {
    "addr:full":"5 Omingmak St Cambridge Bay NU X0B 0C0",
    "addr:housenumber":"5",
    "addr:postcode":"x0b 0c0",
    "addr:street":"Omingmak St",
    "iso:country":"CA",
    "sg:address":"5 Omingmak St",
    "sg:city":"Cambridge Bay",
    "sg:classifiers":[
        {
            "category":"Organizations",
            "subcategory":"Religious Organization",
            "type":"Services"
        }
    ],
    "sg:phone":"+1 867 983 2387",
    "sg:postcode":"X0B 0C0",
    "sg:province":"NU",
    "sg:tags":[
        "church"
    ],
    "wof:name":"Glad Tidings Church",
    "wof:placetype":"venue"
},
  "geometry": {"coordinates":[-105.05755600000001,69.11428100000001],"type":"Point"}
}