{
  "type": "Feature",
  "properties": {
    "addr:full":"2135 Rue Saint-Louis Saint-Laurent QC H4M 1P1",
    "addr:housenumber":"2135",
    "addr:postcode":"h4m 1p1",
    "addr:street":"Rue Saint-Louis",
    "iso:country":"CA",
    "sg:address":"2135 Rue Saint-Louis",
    "sg:city":"Saint-Laurent",
    "sg:classifiers":[
        {
            "category":"Food & Beverages",
            "subcategory":"Bakery",
            "type":"Retail Goods"
        }
    ],
    "sg:phone":"+1 514 747 5116",
    "sg:postcode":"H4M 1P1",
    "sg:province":"QC",
    "sg:tags":[
        "baker"
    ],
    "wof:name":"Montreal Kosher Bakery Ltd",
    "wof:placetype":"venue"
},
  "geometry": {"coordinates":[-73.68138885499999,45.5013160706],"type":"Point"}
}