{
  "type": "Feature",
  "properties": {
    "iso:country":"CA",
    "sg:city":"Concord",
    "sg:classifiers":[
        {
            "category":"Building & Trades",
            "subcategory":"Construction",
            "type":"Services"
        }
    ],
    "sg:phone":"+1 905 738 1652",
    "sg:postcode":"L4K 1X5",
    "sg:province":"ON",
    "sg:tags":[
        "carpenter"
    ],
    "wof:name":"Concord Trimming Inc",
    "wof:placetype":"venue"
},
  "geometry": {"coordinates":[-79.493546,43.795696],"type":"Point"}
}