{
  "type": "Feature",
  "properties": {
    "iso:country":"CA",
    "sg:address":"141 Hudson Ave NW",
    "sg:city":"Salmon Arm",
    "sg:classifiers":[
        {
            "category":"Organizations",
            "subcategory":"Community Association",
            "type":"Services"
        }
    ],
    "sg:phone":"+1 250 832 3118",
    "sg:postcode":"V1E 4M2",
    "sg:province":"BC",
    "sg:tags":[
        "fraternal"
    ],
    "wof:name":"Royal Canadian Legion",
    "wof:placetype":"venue"
},
  "geometry": {"coordinates":[-119.286674499,50.7006225586],"type":"Point"}
}