{
  "type": "Feature",
  "properties": {
    "addr:full":"670 Wilson Ave North York ON M3K 1E1",
    "addr:housenumber":"670",
    "addr:postcode":"m3k 1e1",
    "addr:street":"Wilson Ave",
    "iso:country":"CA",
    "sg:address":"670 Wilson Ave",
    "sg:city":"North York",
    "sg:classifiers":[
        {
            "category":"Travel",
            "subcategory":"Travel Agent",
            "type":"Entertainment"
        }
    ],
    "sg:phone":"+1 416 638 2950",
    "sg:postcode":"M3K 1E1",
    "sg:province":"ON",
    "sg:tags":[
        "agency",
        "bureau"
    ],
    "wof:name":"Downsview Travel Agency",
    "wof:placetype":"venue"
},
  "geometry": {"coordinates":[-79.461609,43.731934],"type":"Point"}
}