{
  "type": "Feature",
  "properties": {
    "addr:full":"Brampton ON L6W 2A4",
    "addr:postcode":"l6w 2a4",
    "iso:country":"CA",
    "sg:city":"Brampton",
    "sg:classifiers":[
        {
            "category":"Health Services",
            "subcategory":"Medical Lab",
            "type":"Services"
        }
    ],
    "sg:phone":"+1 905 455 4414",
    "sg:postcode":"L6W 2A4",
    "sg:province":"ON",
    "sg:tags":[
        "laboratory"
    ],
    "wof:name":"Brampton Vascular Institute",
    "wof:placetype":"venue"
},
  "geometry": {"coordinates":[-79.75262499999999,43.691669],"type":"Point"}
}