{
  "type": "Feature",
  "properties": {
    "iso:country":"CA",
    "sg:address":"38 Payzant Ave",
    "sg:city":"Dartmouth",
    "sg:classifiers":[
        {
            "category":"Wholesale",
            "subcategory":"Machinery & Supplies",
            "type":"Manufacturing & Wholesale Goods"
        }
    ],
    "sg:phone":"+1 902 481 1661",
    "sg:postcode":"B3B 1Z6",
    "sg:province":"NS",
    "sg:tags":[
        "ship",
        "chandler"
    ],
    "wof:name":"Seagulf Maritimes Ltd",
    "wof:placetype":"venue"
},
  "geometry": {"coordinates":[-63.583988,44.715672],"type":"Point"}
}