{
  "type": "Feature",
  "properties": {
    "addr:full":"1090 Talbot Rd Windsor ON N9H 1A3",
    "addr:housenumber":"1090",
    "addr:postcode":"n9h 1a3",
    "addr:street":"Talbot Rd",
    "iso:country":"CA",
    "sg:address":"1090 Talbot Rd",
    "sg:city":"Windsor",
    "sg:classifiers":[
        {
            "category":"Retail",
            "subcategory":"Portrait Studio",
            "type":"Services"
        }
    ],
    "sg:phone":"+1 519 969 2550",
    "sg:postcode":"N9H 1A3",
    "sg:province":"ON",
    "sg:tags":[
        "photographer"
    ],
    "wof:name":"Mainstreet Photography",
    "wof:placetype":"venue"
},
  "geometry": {"coordinates":[-83.003922,42.238369],"type":"Point"}
}