{
  "type": "Feature",
  "properties": {
    "addr:full":"675 Rang DE LA Riviere-Bayonne Berthierville QC J0K 1A0",
    "addr:housenumber":"675",
    "addr:postcode":"j0k 1a0",
    "addr:street":"Rang De La Riviere-Bayonne",
    "iso:country":"CA",
    "sg:address":"675 Rang DE LA Riviere-Bayonne",
    "sg:city":"Berthierville",
    "sg:classifiers":[
        {
            "category":"Restaurant",
            "type":"Food & Drink"
        }
    ],
    "sg:phone":"+1 450 836 1935",
    "sg:postcode":"J0K 1A0",
    "sg:province":"QC",
    "wof:name":"Casse-Croute L'Oasis Enr",
    "wof:placetype":"venue"
},
  "geometry": {"coordinates":[-73.18367000000001,46.096001],"type":"Point"}
}