{
  "type": "Feature",
  "properties": {
    "iso:country":"CA",
    "sg:city":"Trois-Rivieres-Ouest",
    "sg:classifiers":[
        {
            "category":"Home & Garden",
            "subcategory":"Building Materials",
            "type":"Retail Goods"
        }
    ],
    "sg:phone":"+1 819 378 2791",
    "sg:postcode":"G9A 4N4",
    "sg:province":"QC",
    "sg:tags":[
        "glass",
        "window",
        "plate"
    ],
    "wof:name":"Lebeau Vitres D'Autos",
    "wof:placetype":"venue"
},
  "geometry": {"coordinates":[-72.59326934809999,46.3322525024],"type":"Point"}
}