{
  "type": "Feature",
  "properties": {
    "addr:full":"Saint-Severin-DE-Beauce QC G0N 1V0",
    "addr:postcode":"g0n 1v0",
    "iso:country":"CA",
    "sg:city":"Saint-Severin-DE-Beauce",
    "sg:classifiers":[
        {
            "category":"Banks & Credit Unions",
            "subcategory":"Bank",
            "type":"Services"
        }
    ],
    "sg:phone":"+1 418 426 2221",
    "sg:postcode":"G0N 1V0",
    "sg:province":"QC",
    "wof:name":"Caisses Desjardins",
    "wof:placetype":"venue"
},
  "geometry": {"coordinates":[-71.05587005620001,46.3275413513],"type":"Point"}
}