{
  "type": "Feature",
  "properties": {
    "addr:full":"North Vancouver BC V7J 3T6",
    "addr:postcode":"v7j 3t6",
    "iso:country":"CA",
    "sg:city":"North Vancouver",
    "sg:classifiers":[
        {
            "category":"Retail",
            "subcategory":"Repair Shop",
            "type":"Services"
        }
    ],
    "sg:phone":"+1 604 980 7799",
    "sg:postcode":"V7J 3T6",
    "sg:province":"BC",
    "sg:tags":[
        "television",
        "radio"
    ],
    "wof:name":"Lions Gate Tv Repair",
    "wof:placetype":"venue"
},
  "geometry": {"coordinates":[-123.032234192,49.3067398071],"type":"Point"}
}