{
  "type": "Feature",
  "properties": {
    "iso:country":"CA",
    "sg:address":"155 Somerset Cres",
    "sg:city":"London",
    "sg:classifiers":[
        {
            "category":"Personal",
            "type":"Services"
        }
    ],
    "sg:phone":"+1 519 657 2207",
    "sg:postcode":"N6K 3S1",
    "sg:province":"ON",
    "sg:tags":[
        "electrolysis"
    ],
    "wof:name":"Byron Electrolysis",
    "wof:placetype":"venue"
},
  "geometry": {"coordinates":[-81.32184599999999,42.944382],"type":"Point"}
}