{
  "type": "Feature",
  "properties": {
    "addr:full":"3821 Cedar Hill Cross Rd Victoria BC V8P 2M6",
    "addr:housenumber":"3821",
    "addr:postcode":"v8p 2m6",
    "addr:street":"Cedar Hill Cross Rd",
    "iso:country":"CA",
    "sg:address":"3821 Cedar Hill Cross Rd",
    "sg:city":"Victoria",
    "sg:classifiers":[
        {
            "category":"Social Services",
            "subcategory":"Child Care",
            "type":"Services"
        }
    ],
    "sg:phone":"+1 250 477 4141",
    "sg:postcode":"V8P 2M6",
    "sg:province":"BC",
    "wof:name":"Lakehill Pre-School",
    "wof:placetype":"venue"
},
  "geometry": {"coordinates":[-123.36451700000001,48.428314],"type":"Point"}
}