{
  "type": "Feature",
  "properties": {
    "iso:country":"CA",
    "sg:city":"Vancouver",
    "sg:classifiers":[
        {
            "category":"Building & Trades",
            "subcategory":"Pest Control",
            "type":"Services"
        }
    ],
    "sg:phone":"+1 604 434 8296",
    "sg:postcode":"V5R 5H4",
    "sg:province":"BC",
    "wof:name":"A-Aaron's Pest Control",
    "wof:placetype":"venue"
},
  "geometry": {"coordinates":[-123.051940918,49.2392044067],"type":"Point"}
}