{
  "type": "Feature",
  "properties": {
    "iso:country":"CA",
    "sg:city":"Edmonton",
    "sg:classifiers":[
        {
            "category":"Health Services",
            "subcategory":"Doctor",
            "type":"Services"
        }
    ],
    "sg:phone":"+1 780 454 1114",
    "sg:postcode":"T5M 3L7",
    "sg:province":"AB",
    "sg:tags":[
        "dentist"
    ],
    "wof:name":"Bieniak, K DDS",
    "wof:placetype":"venue"
},
  "geometry": {"coordinates":[-113.550682068,53.5532684326],"type":"Point"}
}