{
  "type": "Feature",
  "properties": {
    "addr:full":"1750 Huron Church Rd Windsor ON N9C 2L4",
    "addr:housenumber":"1750",
    "addr:postcode":"n9c 2l4",
    "addr:street":"Huron Church Rd",
    "iso:country":"CA",
    "sg:address":"1750 Huron Church Rd",
    "sg:city":"Windsor",
    "sg:classifiers":[
        {
            "category":"Restaurant",
            "type":"Food & Drink"
        }
    ],
    "sg:phone":"+1 519 254 7113",
    "sg:postcode":"N9C 2L4",
    "sg:province":"ON",
    "wof:name":"Arby's",
    "wof:placetype":"venue"
},
  "geometry": {"coordinates":[-83.055809,42.284195],"type":"Point"}
}