{
  "type": "Feature",
  "properties": {
    "addr:full":"63 Rue Lambton Ormstown QC J0S 1K0",
    "addr:housenumber":"63",
    "addr:postcode":"j0s 1k0",
    "addr:street":"Rue Lambton",
    "iso:country":"CA",
    "sg:address":"63 Rue Lambton",
    "sg:city":"Ormstown",
    "sg:classifiers":[
        {
            "category":"Banks & Credit Unions",
            "subcategory":"Bank",
            "type":"Services"
        }
    ],
    "sg:phone":"+1 450 829 2365",
    "sg:postcode":"J0S 1K0",
    "sg:province":"QC",
    "wof:name":"Cibc",
    "wof:placetype":"venue"
},
  "geometry": {"coordinates":[-73.99202728269999,45.1257896423],"type":"Point"}
}