{
  "type": "Feature",
  "properties": {
    "addr:full":"24 St. Peters Rd Charlottetown PE C1A 5N4",
    "addr:housenumber":"24",
    "addr:postcode":"c1a 5n4",
    "addr:street":"St. Peters Rd",
    "iso:country":"CA",
    "sg:address":"24 St. Peters Rd",
    "sg:city":"Charlottetown",
    "sg:classifiers":[
        {
            "category":"Shopping",
            "subcategory":"Pharmacy",
            "type":"Retail Goods"
        }
    ],
    "sg:phone":"+1 902 894 8553",
    "sg:postcode":"C1A 5N4",
    "sg:province":"PE",
    "wof:name":"Murphy's Pharmacies",
    "wof:placetype":"venue"
},
  "geometry": {"coordinates":[-63.122635,46.248066],"type":"Point"}
}