{
  "type": "Feature",
  "properties": {
    "addr:full":"Vancouver BC V6E 3P1",
    "addr:postcode":"v6e 3p1",
    "iso:country":"CA",
    "sg:city":"Vancouver",
    "sg:classifiers":[
        {
            "category":"Shopping",
            "subcategory":"Shoes",
            "type":"Retail Goods"
        }
    ],
    "sg:phone":"+1 604 682 2228",
    "sg:postcode":"V6E 3P1",
    "sg:province":"BC",
    "sg:tags":[
        "clothing",
        "furnishing"
    ],
    "wof:name":"Giorgio's Men's Wear Ltd",
    "wof:placetype":"venue"
},
  "geometry": {"coordinates":[-123.122124,49.285271],"type":"Point"}
}