{
  "type": "Feature",
  "properties": {
    "addr:full":"566 Main St E North Bay ON P1B 1B8",
    "addr:housenumber":"566",
    "addr:postcode":"p1b 1b8",
    "addr:street":"Main St E",
    "iso:country":"CA",
    "sg:address":"566 Main St E",
    "sg:city":"North Bay",
    "sg:classifiers":[
        {
            "category":"Recreation",
            "type":"Entertainment"
        }
    ],
    "sg:phone":"+1 705 476 5424",
    "sg:postcode":"P1B 1B8",
    "sg:province":"ON",
    "sg:tags":[
        "astrologer"
    ],
    "wof:name":"Norah of the North",
    "wof:placetype":"venue"
},
  "geometry": {"coordinates":[-79.458366394,46.3043746948],"type":"Point"}
}