{
  "type": "Feature",
  "properties": {
    "iso:country":"CA",
    "sg:address":"5024 50th St",
    "sg:city":"Irma",
    "sg:classifiers":[
        {
            "category":"Insurance",
            "subcategory":"Insurance Agent",
            "type":"Services"
        }
    ],
    "sg:phone":"+1 780 754 2121",
    "sg:postcode":"T0B 2H0",
    "sg:province":"AB",
    "wof:name":"Irma Insurance Svc",
    "wof:placetype":"venue"
},
  "geometry": {"coordinates":[-111.230141,52.913956],"type":"Point"}
}