{
  "type": "Feature",
  "properties": {
    "addr:full":"139 Main St Lafleche SK S0H 2K0",
    "addr:housenumber":"139",
    "addr:postcode":"s0h 2k0",
    "addr:street":"Main St",
    "iso:country":"CA",
    "sg:address":"139 Main St",
    "sg:city":"Lafleche",
    "sg:classifiers":[
        {
            "category":"Restaurant",
            "type":"Food & Drink"
        }
    ],
    "sg:phone":"+1 306 472 5900",
    "sg:postcode":"S0H 2K0",
    "sg:province":"SK",
    "sg:tags":[
        "caterer"
    ],
    "wof:name":"Lafleche Cafe",
    "wof:placetype":"venue"
},
  "geometry": {"coordinates":[-106.57157135,49.6989746094],"type":"Point"}
}