{
  "type": "Feature",
  "properties": {
    "addr:full":"4820 50 Ave Leduc AB T9E 6X9",
    "addr:housenumber":"4820",
    "addr:postcode":"t9e 6x9",
    "addr:street":"50 Ave",
    "iso:country":"CA",
    "sg:address":"4820 50 Ave",
    "sg:city":"Leduc",
    "sg:classifiers":[
        {
            "category":"Travel",
            "subcategory":"Hotels & Motels",
            "type":"Entertainment"
        }
    ],
    "sg:phone":"+1 780 986 3259",
    "sg:postcode":"T9E 6X9",
    "sg:province":"AB",
    "wof:name":"Waldorf Hotel",
    "wof:placetype":"venue"
},
  "geometry": {"coordinates":[-113.54921,53.264889],"type":"Point"}
}