{
  "type": "Feature",
  "properties": {
    "addr:full":"Riviere-Du-Loup QC G5R 4C2",
    "addr:postcode":"g5r 4c2",
    "iso:country":"CA",
    "sg:city":"Riviere-Du-Loup",
    "sg:classifiers":[
        {
            "category":"Shopping",
            "subcategory":"Clothing, Apparel, & Fashions",
            "type":"Retail Goods"
        }
    ],
    "sg:phone":"+1 418 867 3477",
    "sg:postcode":"G5R 4C2",
    "sg:province":"QC",
    "sg:tags":[
        "item",
        "boutique"
    ],
    "wof:name":"Boutique Pentagone Inc",
    "wof:placetype":"venue"
},
  "geometry": {"coordinates":[-69.53703299999999,47.835041],"type":"Point"}
}