{
  "type": "Feature",
  "properties": {
    "addr:full":"6 Jacob St Neustadt ON N0G 2M0",
    "addr:housenumber":"6",
    "addr:postcode":"n0g 2m0",
    "addr:street":"Jacob St",
    "iso:country":"CA",
    "sg:address":"6 Jacob St",
    "sg:city":"Neustadt",
    "sg:classifiers":[
        {
            "category":"Organizations",
            "subcategory":"Religious Organization",
            "type":"Services"
        }
    ],
    "sg:phone":"+1 519 799 5506",
    "sg:postcode":"N0G 2M0",
    "sg:province":"ON",
    "sg:tags":[
        "church"
    ],
    "wof:name":"St Peter's Lutheran Church",
    "wof:placetype":"venue"
},
  "geometry": {"coordinates":[-81.00267028810001,44.0758781433],"type":"Point"}
}