{
  "type": "Feature",
  "properties": {
    "iso:country":"CA",
    "sg:address":"5224 48 Ave",
    "sg:city":"Taber",
    "sg:classifiers":[
        {
            "category":"Personal",
            "subcategory":"Beauty Salon",
            "type":"Services"
        }
    ],
    "sg:phone":"+1 403 223 1660",
    "sg:postcode":"T1G 1S1",
    "sg:province":"AB",
    "wof:name":"Coco's Loft",
    "wof:placetype":"venue"
},
  "geometry": {"coordinates":[-112.146125794,49.7842636108],"type":"Point"}
}