{
  "type": "Feature",
  "properties": {
    "addr:full":"8112 120 St Surrey BC V3W 3N3",
    "addr:housenumber":"8112",
    "addr:postcode":"v3w 3n3",
    "addr:street":"120 St",
    "iso:country":"CA",
    "sg:address":"8112 120 St",
    "sg:city":"Surrey",
    "sg:classifiers":[
        {
            "category":"Cinema",
            "subcategory":"Movie Rental",
            "type":"Entertainment"
        }
    ],
    "sg:phone":"+1 604 599 0099",
    "sg:postcode":"V3W 3N3",
    "sg:province":"BC",
    "sg:tags":[
        "leasing",
        "video",
        "disc",
        "tape"
    ],
    "wof:name":"Rogers Video",
    "wof:placetype":"venue"
},
  "geometry": {"coordinates":[-122.890236,49.150654],"type":"Point"}
}