{
  "type": "Feature",
  "properties": {
    "addr:full":"4963 Angus St Port Alberni BC V9Y 7Z4",
    "addr:housenumber":"4963",
    "addr:postcode":"v9y 7z4",
    "addr:street":"Angus St",
    "iso:country":"CA",
    "sg:address":"4963 Angus St",
    "sg:city":"Port Alberni",
    "sg:classifiers":[
        {
            "category":"Recreation",
            "type":"Entertainment"
        }
    ],
    "sg:phone":"+1 250 723 1212",
    "sg:postcode":"V9Y 7Z4",
    "sg:province":"BC",
    "sg:tags":[
        "parlor",
        "billiard"
    ],
    "wof:name":"Alberni Valley Billiard Club",
    "wof:placetype":"venue"
},
  "geometry": {"coordinates":[-124.806983948,49.2335548401],"type":"Point"}
}