{
  "type": "Feature",
  "properties": {
    "addr:full":"PO Box 598 Vulcan AB T0L 2B0",
    "addr:housenumber":"po",
    "addr:postcode":"t0l 2b0",
    "addr:street":"Box 598 Vulcan",
    "iso:country":"CA",
    "sg:address":"PO Box 598",
    "sg:city":"Vulcan",
    "sg:classifiers":[
        {
            "category":"Travel",
            "subcategory":"Hotels & Motels",
            "type":"Entertainment"
        }
    ],
    "sg:phone":"+1 403 485 6116",
    "sg:postcode":"T0L 2B0",
    "sg:province":"AB",
    "sg:tags":[
        "resort"
    ],
    "wof:name":"Lake Mc Gregor Resort Corp",
    "wof:placetype":"venue"
},
  "geometry": {"coordinates":[-113.258179,50.397339],"type":"Point"}
}