{
  "type": "Feature",
  "properties": {
    "addr:full":"1240 4th Ave E Owen Sound ON N4K 2P6",
    "addr:housenumber":"1240",
    "addr:postcode":"n4k 2p6",
    "addr:street":"4Th Ave E",
    "iso:country":"CA",
    "sg:address":"1240 4th Ave E",
    "sg:city":"Owen Sound",
    "sg:classifiers":[
        {
            "category":"Manufacturing",
            "subcategory":"Printing",
            "type":"Manufacturing & Wholesale Goods"
        }
    ],
    "sg:phone":"+1 519 376 2899",
    "sg:postcode":"N4K 2P6",
    "sg:province":"ON",
    "sg:tags":[
        "printer"
    ],
    "wof:name":"Stan Brown Printers Ltd",
    "wof:placetype":"venue"
},
  "geometry": {"coordinates":[-80.9374160767,44.5717163086],"type":"Point"}
}