{
  "type": "Feature",
  "properties": {
    "addr:full":"Charlottetown PE C1A 7J7",
    "addr:postcode":"c1a 7j7",
    "iso:country":"CA",
    "sg:city":"Charlottetown",
    "sg:classifiers":[
        {
            "category":"Building & Trades",
            "subcategory":"Electrical",
            "type":"Services"
        }
    ],
    "sg:phone":"+1 902 629 1344",
    "sg:postcode":"C1A 7J7",
    "sg:province":"PE",
    "sg:tags":[
        "electric",
        "contractor"
    ],
    "wof:name":"Mc Nally Electric",
    "wof:placetype":"venue"
},
  "geometry": {"coordinates":[-63.1243667603,46.2639503479],"type":"Point"}
}