{
  "type": "Feature",
  "properties": {
    "iso:country":"CA",
    "sg:address":"53 Parkhurst Sq",
    "sg:city":"Brampton",
    "sg:classifiers":[
        {
            "category":"Shopping",
            "subcategory":"Jewelry",
            "type":"Retail Goods"
        }
    ],
    "sg:phone":"+1 905 789 0686",
    "sg:postcode":"L6T 5H5",
    "sg:province":"ON",
    "sg:tags":[
        "jeweler"
    ],
    "wof:name":"Morning Star Jewellery",
    "wof:placetype":"venue"
},
  "geometry": {"coordinates":[-79.66836547849999,43.7266082764],"type":"Point"}
}