{
  "type": "Feature",
  "properties": {
    "addr:full":"550 Boul Wilfrid-Hamel # 2 Quebec QC G1M 2S6",
    "addr:housenumber":"550",
    "addr:postcode":"g1m 2s6",
    "addr:street":"Boul Wilfrid-Hamel # 2",
    "iso:country":"CA",
    "sg:address":"550 Boul Wilfrid-Hamel # 2",
    "sg:city":"Quebec",
    "sg:classifiers":[
        {
            "category":"Restaurant",
            "type":"Food & Drink"
        }
    ],
    "sg:phone":"+1 418 648 9444",
    "sg:postcode":"G1M 2S6",
    "sg:province":"QC",
    "wof:name":"Saignon Tokyo",
    "wof:placetype":"venue"
},
  "geometry": {"coordinates":[-71.2489395142,46.8203735352],"type":"Point"}
}