{
  "type": "Feature",
  "properties": {
    "addr:full":"Calgary AB T2E 1K2",
    "addr:postcode":"t2e 1k2",
    "iso:country":"CA",
    "sg:city":"Calgary",
    "sg:classifiers":[
        {
            "category":"Food & Beverages",
            "subcategory":"Liquor & Beverages",
            "type":"Retail Goods"
        }
    ],
    "sg:phone":"+1 403 230 8522",
    "sg:postcode":"T2E 1K2",
    "sg:province":"AB",
    "sg:tags":[
        "store"
    ],
    "wof:name":"Transcanada Liquor",
    "wof:placetype":"venue"
},
  "geometry": {"coordinates":[-114.054359436,51.0671195984],"type":"Point"}
}