{
  "type": "Feature",
  "properties": {
    "iso:country":"CA",
    "sg:address":"374 Clarkson Pl",
    "sg:city":"Parksville",
    "sg:classifiers":[
        {
            "category":"Building & Trades",
            "subcategory":"Construction",
            "type":"Services"
        }
    ],
    "sg:phone":"+1 250 248 2904",
    "sg:postcode":"V9P 2V8",
    "sg:province":"BC",
    "sg:tags":[
        "roofing",
        "contractor"
    ],
    "wof:name":"Low Cost Roofing",
    "wof:placetype":"venue"
},
  "geometry": {"coordinates":[-124.340218,49.326817],"type":"Point"}
}