{
  "type": "Feature",
  "properties": {
    "addr:full":"1455 Av Cardinal Dorval QC H9P 2N8",
    "addr:housenumber":"1455",
    "addr:postcode":"h9p 2n8",
    "addr:street":"Av Cardinal",
    "iso:country":"CA",
    "sg:address":"1455 Av Cardinal",
    "sg:city":"Dorval",
    "sg:classifiers":[
        {
            "category":"Recreation",
            "type":"Entertainment"
        }
    ],
    "sg:phone":"+1 514 631 4711",
    "sg:postcode":"H9P 2N8",
    "sg:province":"QC",
    "sg:tags":[
        "course",
        "golf"
    ],
    "wof:name":"Dorval Municipal Golf Club",
    "wof:placetype":"venue"
},
  "geometry": {"coordinates":[-73.759911,45.450012],"type":"Point"}
}