{
  "type": "Feature",
  "properties": {
    "iso:country":"CA",
    "sg:address":"1246 Rue DE Fenouillet",
    "sg:city":"Cap-Rouge",
    "sg:classifiers":[
        {
            "category":"Professional",
            "subcategory":"Credit Reporting & Collection",
            "type":"Services"
        }
    ],
    "sg:phone":"+1 418 652 7700",
    "sg:postcode":"G1Y 2Y5",
    "sg:province":"QC",
    "sg:tags":[
        "agency"
    ],
    "wof:name":"Services En Credit Commercial",
    "wof:placetype":"venue"
},
  "geometry": {"coordinates":[-71.3651809692,46.7493476868],"type":"Point"}
}