{
  "type": "Feature",
  "properties": {
    "addr:full":"3666 Edinburgh St Vancouver BC V5K 1B7",
    "addr:housenumber":"3666",
    "addr:postcode":"v5k 1b7",
    "addr:street":"Edinburgh St",
    "iso:country":"CA",
    "sg:address":"3666 Edinburgh St",
    "sg:city":"Vancouver",
    "sg:classifiers":[
        {
            "category":"Real Estate",
            "subcategory":"Architect",
            "type":"Services"
        }
    ],
    "sg:phone":"+1 604 684 1531",
    "sg:postcode":"V5K 1B7",
    "sg:province":"BC",
    "wof:name":"Cairns Architect Planner",
    "wof:placetype":"venue"
},
  "geometry": {"coordinates":[-123.023834228,49.2915306091],"type":"Point"}
}