{
  "type": "Feature",
  "properties": {
    "addr:full":"512 Seventh Ave New Westminster BC V3L 1W9",
    "addr:housenumber":"512",
    "addr:postcode":"v3l 1w9",
    "addr:street":"Seventh Ave",
    "iso:country":"CA",
    "sg:address":"512 Seventh Ave",
    "sg:city":"New Westminster",
    "sg:classifiers":[
        {
            "category":"Shopping",
            "subcategory":"Florist",
            "type":"Retail Goods"
        }
    ],
    "sg:phone":"+1 604 522 5121",
    "sg:postcode":"V3L 1W9",
    "sg:province":"BC",
    "wof:name":"Kitty's-Butterfield Flrst Ltd",
    "wof:placetype":"venue"
},
  "geometry": {"coordinates":[-122.920807,49.214909],"type":"Point"}
}