{
  "type": "Feature",
  "properties": {
    "addr:full":"North York ON M2N 6K1",
    "addr:postcode":"m2n 6k1",
    "iso:country":"CA",
    "sg:city":"North York",
    "sg:classifiers":[
        {
            "category":"Banks & Credit Unions",
            "subcategory":"Investment Brokerage",
            "type":"Services"
        }
    ],
    "sg:phone":"+1 416 733 4722",
    "sg:postcode":"M2N 6K1",
    "sg:province":"ON",
    "sg:tags":[
        "funds",
        "mutual"
    ],
    "wof:name":"Investors Group Financial Svc",
    "wof:placetype":"venue"
},
  "geometry": {"coordinates":[-79.4120025635,43.7649803162],"type":"Point"}
}