{
  "type": "Feature",
  "properties": {
    "iso:country":"CA",
    "sg:address":"NW 3 3 5W",
    "sg:city":"Morden",
    "sg:classifiers":[
        {
            "category":"Manufacturing",
            "subcategory":"Furniture",
            "type":"Manufacturing & Wholesale Goods"
        }
    ],
    "sg:phone":"+1 204 822 6760",
    "sg:postcode":"R6M 1B1",
    "sg:province":"MB",
    "wof:name":"Braman Furniture Intl Ltd",
    "wof:placetype":"venue"
},
  "geometry": {"coordinates":[-98.11302185060001,49.1922836304],"type":"Point"}
}