{
  "type": "Feature",
  "properties": {
    "addr:full":"3622 Kingsway Vancouver BC V5R 5M2",
    "addr:housenumber":"3622",
    "addr:postcode":"v5r 5m2",
    "addr:street":"Kingsway",
    "iso:country":"CA",
    "sg:address":"3622 Kingsway",
    "sg:city":"Vancouver",
    "sg:classifiers":[
        {
            "category":"Shopping",
            "type":"Retail Goods"
        }
    ],
    "sg:phone":"+1 604 733 1888",
    "sg:postcode":"V5R 5M2",
    "sg:province":"BC",
    "sg:tags":[
        "pet",
        "shop"
    ],
    "wof:name":"Coral Ocean Aquarium Inc",
    "wof:placetype":"venue"
},
  "geometry": {"coordinates":[-123.02623699999999,49.232044],"type":"Point"}
}