{
  "type": "Feature",
  "properties": {
    "addr:full":"Blanc-Sablon QC G0G 1C0",
    "addr:postcode":"g0g 1c0",
    "iso:country":"CA",
    "sg:city":"Blanc-Sablon",
    "sg:classifiers":[
        {
            "category":"Restaurant",
            "type":"Food & Drink"
        }
    ],
    "sg:phone":"+1 418 461 2614",
    "sg:postcode":"G0G 1C0",
    "sg:province":"QC",
    "wof:name":"A & S Take Out",
    "wof:placetype":"venue"
},
  "geometry": {"coordinates":[-57.1352081299,51.4286155701],"type":"Point"}
}