{
  "type": "Feature",
  "properties": {
    "addr:full":"30 Downie St Stratford ON N5A 1W5",
    "addr:housenumber":"30",
    "addr:postcode":"n5a 1w5",
    "addr:street":"Downie St",
    "iso:country":"CA",
    "sg:address":"30 Downie St",
    "sg:city":"Stratford",
    "sg:classifiers":[
        {
            "category":"Banks & Credit Unions",
            "subcategory":"Bank",
            "type":"Services"
        }
    ],
    "sg:phone":"+1 519 271 0920",
    "sg:postcode":"N5A 1W5",
    "sg:province":"ON",
    "wof:name":"Cibc",
    "wof:placetype":"venue"
},
  "geometry": {"coordinates":[-80.98248291020001,43.3708076477],"type":"Point"}
}