{
  "type": "Feature",
  "properties": {
    "addr:full":"2569 Shaughnessy St Port Coquitlam BC V3C 3G3",
    "addr:housenumber":"2569",
    "addr:postcode":"v3c 3g3",
    "addr:street":"Shaughnessy St",
    "iso:country":"CA",
    "sg:address":"2569 Shaughnessy St",
    "sg:city":"Port Coquitlam",
    "sg:classifiers":[
        {
            "category":"Professional",
            "subcategory":"Accounting & Tax Preparation",
            "type":"Services"
        }
    ],
    "sg:phone":"+1 604 941 5734",
    "sg:postcode":"V3C 3G3",
    "sg:province":"BC",
    "sg:tags":[
        "consultant",
        "return",
        "filing"
    ],
    "wof:name":"H & R Block Canada Inc",
    "wof:placetype":"venue"
},
  "geometry": {"coordinates":[-122.78176879900001,49.2624397278],"type":"Point"}
}