{
  "type": "Feature",
  "properties": {
    "addr:full":"105 Ontario Rd Mitchell ON N0K 1N0",
    "addr:housenumber":"105",
    "addr:postcode":"n0k 1n0",
    "addr:street":"Ontario Rd",
    "iso:country":"CA",
    "sg:address":"105 Ontario Rd",
    "sg:city":"Mitchell",
    "sg:classifiers":[
        {
            "category":"Banks & Credit Unions",
            "subcategory":"Bank",
            "type":"Services"
        }
    ],
    "sg:phone":"+1 519 348 8448",
    "sg:postcode":"N0K 1N0",
    "sg:province":"ON",
    "wof:name":"Mitchell & District Cu",
    "wof:placetype":"venue"
},
  "geometry": {"coordinates":[-81.1955871582,43.4672088623],"type":"Point"}
}