{
  "type": "Feature",
  "properties": {
    "addr:full":"555 Ch Du Fer-A-Cheval Sainte-Julie QC J3E 1Y2",
    "addr:housenumber":"555",
    "addr:postcode":"j3e 1y2",
    "addr:street":"Ch Du Fer-A-Cheval",
    "iso:country":"CA",
    "sg:address":"555 Ch Du Fer-A-Cheval",
    "sg:city":"Sainte-Julie",
    "sg:classifiers":[
        {
            "category":"Home & Garden",
            "subcategory":"Building Materials",
            "type":"Retail Goods"
        }
    ],
    "sg:phone":"+1 514 990 2359",
    "sg:postcode":"J3E 1Y2",
    "sg:province":"QC",
    "sg:tags":[
        "sod",
        "sodding"
    ],
    "wof:name":"Gazon Groupe Richer",
    "wof:placetype":"venue"
},
  "geometry": {"coordinates":[-73.3314361572,45.6160697937],"type":"Point"}
}