{
  "type": "Feature",
  "properties": {
    "addr:full":"Calgary AB T2L 2J8",
    "addr:postcode":"t2l 2j8",
    "iso:country":"CA",
    "sg:city":"Calgary",
    "sg:classifiers":[
        {
            "category":"Shopping",
            "subcategory":"Music",
            "type":"Retail Goods"
        }
    ],
    "sg:phone":"+1 403 288 6845",
    "sg:postcode":"T2L 2J8",
    "sg:province":"AB",
    "sg:tags":[
        "compact",
        "record",
        "disc",
        "tape"
    ],
    "wof:name":"Music World",
    "wof:placetype":"venue"
},
  "geometry": {"coordinates":[-114.141571,51.098434],"type":"Point"}
}