{
  "type": "Feature",
  "properties": {
    "addr:full":"1055 Rue D'Hibernia Montreal QC H3K 2V3",
    "addr:housenumber":"1055",
    "addr:postcode":"h3k 2v3",
    "addr:street":"Rue D'Hibernia",
    "iso:country":"CA",
    "sg:address":"1055 Rue D'Hibernia",
    "sg:city":"Montreal",
    "sg:classifiers":[
        {
            "category":"Recreation",
            "type":"Entertainment"
        }
    ],
    "sg:phone":"+1 514 872 2501",
    "sg:postcode":"H3K 2V3",
    "sg:province":"QC",
    "sg:tags":[
        "pool",
        "swimming"
    ],
    "wof:name":"Montreal Piscines Interieures",
    "wof:placetype":"venue"
},
  "geometry": {"coordinates":[-73.56295799999999,45.478634],"type":"Point"}
}