{
  "type": "Feature",
  "properties": {
    "addr:full":"Stettler AB T0C 2L2",
    "addr:postcode":"t0c 2l2",
    "iso:country":"CA",
    "sg:city":"Stettler",
    "sg:classifiers":[
        {
            "category":"Shopping",
            "subcategory":"Florist",
            "type":"Retail Goods"
        }
    ],
    "sg:phone":"+1 403 742 2725",
    "sg:postcode":"T0C 2L2",
    "sg:province":"AB",
    "wof:name":"Panda Flowers",
    "wof:placetype":"venue"
},
  "geometry": {"coordinates":[-112.705299377,52.3232727051],"type":"Point"}
}