{
  "type": "Feature",
  "properties": {
    "addr:full":"776 Queen St Kincardine ON N2Z 2Y2",
    "addr:housenumber":"776",
    "addr:postcode":"n2z 2y2",
    "addr:street":"Queen St",
    "iso:country":"CA",
    "sg:address":"776 Queen St",
    "sg:city":"Kincardine",
    "sg:classifiers":[
        {
            "category":"Personal",
            "type":"Services"
        }
    ],
    "sg:phone":"+1 519 396 2882",
    "sg:postcode":"N2Z 2Y2",
    "sg:province":"ON",
    "sg:tags":[
        "program",
        "physical",
        "exercise",
        "fitness"
    ],
    "wof:name":"Curves For Women",
    "wof:placetype":"venue"
},
  "geometry": {"coordinates":[-81.6355133057,44.176940918],"type":"Point"}
}