{
  "type": "Feature",
  "properties": {
    "addr:full":"27 Amikook St Wikwemikong ON P0P 2J0",
    "addr:housenumber":"27",
    "addr:postcode":"p0p 2j0",
    "addr:street":"Amikook St",
    "iso:country":"CA",
    "sg:address":"27 Amikook St",
    "sg:city":"Wikwemikong",
    "sg:classifiers":[
        {
            "category":"Education",
            "subcategory":"School",
            "type":"Public Place"
        }
    ],
    "sg:phone":"+1 705 859 3797",
    "sg:postcode":"P0P 2J0",
    "sg:province":"ON",
    "sg:tags":[
        "child",
        "care"
    ],
    "wof:name":"Wikwemikong Hub Ctr",
    "wof:placetype":"venue"
},
  "geometry": {"coordinates":[-81.726433,45.797588],"type":"Point"}
}