{
  "type": "Feature",
  "properties": {
    "addr:full":"1079 Boul Sainte-Foy Longueuil QC J4K 1W5",
    "addr:housenumber":"1079",
    "addr:postcode":"j4k 1w5",
    "addr:street":"Boul Sainte-Foy",
    "iso:country":"CA",
    "sg:address":"1079 Boul Sainte-Foy",
    "sg:city":"Longueuil",
    "sg:classifiers":[
        {
            "category":"Home & Garden",
            "subcategory":"Building Materials",
            "type":"Retail Goods"
        }
    ],
    "sg:phone":"+1 450 651 2223",
    "sg:postcode":"J4K 1W5",
    "sg:province":"QC",
    "sg:tags":[
        "paint"
    ],
    "wof:name":"Betonel Limitee",
    "wof:placetype":"venue"
},
  "geometry": {"coordinates":[-73.4973983765,45.519077301],"type":"Point"}
}