{
  "type": "Feature",
  "properties": {
    "addr:full":"4814 Centre St NE Calgary AB T2E 2Z7",
    "addr:housenumber":"4814",
    "addr:postcode":"t2e 2z7",
    "addr:street":"Centre St Ne",
    "iso:country":"CA",
    "sg:address":"4814 Centre St NE",
    "sg:city":"Calgary",
    "sg:classifiers":[
        {
            "category":"Food & Beverages",
            "subcategory":"Liquor & Beverages",
            "type":"Retail Goods"
        }
    ],
    "sg:phone":"+1 403 276 5500",
    "sg:postcode":"T2E 2Z7",
    "sg:province":"AB",
    "sg:tags":[
        "store"
    ],
    "wof:name":"B K Liquor Store",
    "wof:placetype":"venue"
},
  "geometry": {"coordinates":[-114.062202,51.094898],"type":"Point"}
}