{
  "type": "Feature",
  "properties": {
    "iso:country":"CA",
    "sg:address":"498 Horner Ave",
    "sg:city":"Etobicoke",
    "sg:classifiers":[
        {
            "category":"Restaurant",
            "type":"Food & Drink"
        }
    ],
    "sg:phone":"+1 416 521 9119",
    "sg:postcode":"M8W 2B8",
    "sg:province":"ON",
    "wof:name":"Harley's Roadhouse",
    "wof:placetype":"venue"
},
  "geometry": {"coordinates":[-79.5445022583,43.601978302],"type":"Point"}
}