{
  "type": "Feature",
  "properties": {
    "addr:full":"Castor AB T0C 0X0",
    "addr:postcode":"t0c 0x0",
    "iso:country":"CA",
    "sg:city":"Castor",
    "sg:classifiers":[
        {
            "category":"Sports & Exercise",
            "subcategory":"Golf",
            "type":"Entertainment"
        }
    ],
    "sg:phone":"+1 403 882 2112",
    "sg:postcode":"T0C 0X0",
    "sg:province":"AB",
    "sg:tags":[
        "course"
    ],
    "wof:name":"Castor Golf Club",
    "wof:placetype":"venue"
},
  "geometry": {"coordinates":[-111.90719604500001,52.2172317505],"type":"Point"}
}