{
  "type": "Feature",
  "properties": {
    "iso:country":"CA",
    "sg:address":"100 City Centre Dr",
    "sg:city":"Mississauga",
    "sg:classifiers":[
        {
            "category":"Professional",
            "subcategory":"Business Services",
            "type":"Services"
        }
    ],
    "sg:phone":"+1 905 270 0049",
    "sg:postcode":"L5B 2C9",
    "sg:province":"ON",
    "sg:tags":[
        "wine"
    ],
    "wof:name":"Wine Rack",
    "wof:placetype":"venue"
},
  "geometry": {"coordinates":[-79.6395111084,43.5920944214],"type":"Point"}
}