{
  "type": "Feature",
  "properties": {
    "addr:full":"46 Overlea Blvd Toronto ON M4H 1B6",
    "addr:housenumber":"46",
    "addr:postcode":"m4h 1b6",
    "addr:street":"Overlea Blvd",
    "iso:country":"CA",
    "sg:address":"46 Overlea Blvd",
    "sg:city":"Toronto",
    "sg:classifiers":[
        {
            "category":"Organizations",
            "subcategory":"Professional Association",
            "type":"Services"
        }
    ],
    "sg:phone":"+1 416 423 6630",
    "sg:postcode":"M4H 1B6",
    "sg:province":"ON",
    "wof:name":"Caw Local 385",
    "wof:placetype":"venue"
},
  "geometry": {"coordinates":[-79.346733,43.706944],"type":"Point"}
}