{
  "type": "Feature",
  "properties": {
    "addr:full":"580 Fanshawe Park Rd E London ON N5X 1L1",
    "addr:housenumber":"580",
    "addr:postcode":"n5x 1l1",
    "addr:street":"Fanshawe Park Rd E",
    "iso:country":"CA",
    "sg:address":"580 Fanshawe Park Rd E",
    "sg:city":"London",
    "sg:classifiers":[
        {
            "category":"Autos & Motor Vehicles",
            "subcategory":"Fuel & Gas Station",
            "type":"Retail Goods"
        }
    ],
    "sg:phone":"+1 519 660 6003",
    "sg:postcode":"N5X 1L1",
    "sg:province":"ON",
    "sg:tags":[
        "repairing",
        "automobile",
        "oil"
    ],
    "wof:name":"Stoneybrook Sunoco",
    "wof:placetype":"venue"
},
  "geometry": {"coordinates":[-81.256393,43.034519],"type":"Point"}
}