{
  "type": "Feature",
  "properties": {
    "iso:country":"CA",
    "sg:address":"15 Locke Hts",
    "sg:city":"Strathroy",
    "sg:classifiers":[
        {
            "category":"Building & Trades",
            "subcategory":"Cleaning & Sanitation",
            "type":"Services"
        }
    ],
    "sg:phone":"+1 519 245 3480",
    "sg:postcode":"N7G 3X1",
    "sg:province":"ON",
    "sg:tags":[
        "janitor"
    ],
    "wof:name":"Superior Cleaning & Mntnc",
    "wof:placetype":"venue"
},
  "geometry": {"coordinates":[-81.6265335083,42.9652671814],"type":"Point"}
}