{
  "type": "Feature",
  "properties": {
    "iso:country":"CA",
    "sg:address":"2097 Rue Barbeau",
    "sg:city":"Longueuil",
    "sg:classifiers":[
        {
            "category":"Building & Trades",
            "subcategory":"Construction",
            "type":"Services"
        }
    ],
    "sg:phone":"+1 450 468 7166",
    "sg:postcode":"J4M 2T3",
    "sg:province":"QC",
    "sg:tags":[
        "masonry",
        "contractor"
    ],
    "wof:name":"Leon Murray Maconnerie Inc",
    "wof:placetype":"venue"
},
  "geometry": {"coordinates":[-73.4455413818,45.5450744629],"type":"Point"}
}