{
  "type": "Feature",
  "properties": {
    "iso:country":"CA",
    "sg:address":"472 Danforth Ave",
    "sg:city":"Toronto",
    "sg:classifiers":[
        {
            "category":"Bars & Pubs",
            "type":"Food & Drink"
        }
    ],
    "sg:phone":"+1 416 267 8406",
    "sg:postcode":"M4K 1P4",
    "sg:province":"ON",
    "wof:name":"Newfoundlander Restaurant",
    "wof:placetype":"venue"
},
  "geometry": {"coordinates":[-79.349937439,43.6780548096],"type":"Point"}
}