{
  "type": "Feature",
  "properties": {
    "addr:full":"St Paul AB T0A 3A2",
    "addr:postcode":"t0a 3a2",
    "iso:country":"CA",
    "sg:city":"St Paul",
    "sg:classifiers":[
        {
            "category":"Shopping",
            "subcategory":"Clothing, Apparel, & Fashions",
            "type":"Retail Goods"
        }
    ],
    "sg:phone":"+1 780 645 5000",
    "sg:postcode":"T0A 3A2",
    "sg:province":"AB",
    "wof:name":"Red Bird Clothing CO",
    "wof:placetype":"venue"
},
  "geometry": {"coordinates":[-111.273186,53.992325],"type":"Point"}
}