{
  "type": "Feature",
  "properties": {
    "addr:full":"Etobicoke ON M9W 4L6",
    "addr:postcode":"m9w 4l6",
    "iso:country":"CA",
    "sg:city":"Etobicoke",
    "sg:classifiers":[
        {
            "category":"Food & Beverages",
            "subcategory":"Specialty",
            "type":"Retail Goods"
        }
    ],
    "sg:phone":"+1 416 740 1344",
    "sg:postcode":"M9W 4L6",
    "sg:province":"ON",
    "sg:tags":[
        "health",
        "diet"
    ],
    "wof:name":"Living Healthy",
    "wof:placetype":"venue"
},
  "geometry": {"coordinates":[-79.57511901860001,43.7294578552],"type":"Point"}
}