{
  "type": "Feature",
  "properties": {
    "addr:full":"1985 Rue Lucien-Thimens Saint-Laurent QC H4R 1K8",
    "addr:housenumber":"1985",
    "addr:postcode":"h4r 1k8",
    "addr:street":"Rue Lucien-Thimens",
    "iso:country":"CA",
    "sg:address":"1985 Rue Lucien-Thimens",
    "sg:city":"Saint-Laurent",
    "sg:classifiers":[
        {
            "category":"Shopping",
            "subcategory":"Computers & Home Electronics",
            "type":"Retail Goods"
        }
    ],
    "sg:phone":"+1 514 336 7088",
    "sg:postcode":"H4R 1K8",
    "sg:province":"QC",
    "sg:tags":[
        "parts",
        "supply"
    ],
    "wof:name":"Rubans Micro Ribbons",
    "wof:placetype":"venue"
},
  "geometry": {"coordinates":[-73.69302399999999,45.511395],"type":"Point"}
}