{
  "type": "Feature",
  "properties": {
    "iso:country":"CA",
    "sg:address":"1985 Rue Lucien-Thimens",
    "sg:city":"Saint-Laurent",
    "sg:classifiers":[
        {
            "category":"Shopping",
            "subcategory":"Computers & Home Electronics",
            "type":"Retail Goods"
        }
    ],
    "sg:phone":"+1 514 336 7088",
    "sg:postcode":"H4R 1K8",
    "sg:province":"QC",
    "sg:tags":[
        "parts",
        "supply"
    ],
    "wof:name":"Rubans Micro Ribbons",
    "wof:placetype":"venue"
},
  "geometry": {"coordinates":[-73.693024,45.511395],"type":"Point"}
}