{
  "type": "Feature",
  "properties": {
    "addr:full":"817 Rte Des Campagnards Val-Senneville QC J0Y 2P0",
    "addr:housenumber":"817",
    "addr:postcode":"j0y 2p0",
    "addr:street":"Rte Des Campagnards",
    "iso:country":"CA",
    "sg:address":"817 Rte Des Campagnards",
    "sg:city":"Val-Senneville",
    "sg:classifiers":[
        {
            "category":"Travel",
            "subcategory":"Campground",
            "type":"Entertainment"
        }
    ],
    "sg:phone":"+1 819 824 9222",
    "sg:postcode":"J0Y 2P0",
    "sg:province":"QC",
    "sg:tags":[
        "camp"
    ],
    "wof:name":"Camp Familial Abitibi",
    "wof:placetype":"venue"
},
  "geometry": {"coordinates":[-77.627174,48.254135],"type":"Point"}
}