{
  "type": "Feature",
  "properties": {
    "addr:full":"1707 Sismet Rd # 4 Mississauga ON L4W 2K8",
    "addr:housenumber":"1707",
    "addr:postcode":"l4w 2k8",
    "addr:street":"Sismet Rd # 4",
    "iso:country":"CA",
    "sg:address":"1707 Sismet Rd # 4",
    "sg:city":"Mississauga",
    "sg:classifiers":[
        {
            "category":"Wholesale",
            "subcategory":"Meat",
            "type":"Manufacturing & Wholesale Goods"
        }
    ],
    "sg:phone":"+1 905 238 3188",
    "sg:postcode":"L4W 2K8",
    "sg:province":"ON",
    "sg:tags":[
        "product"
    ],
    "wof:name":"Dixie Trading CO Ltd",
    "wof:placetype":"venue"
},
  "geometry": {"coordinates":[-79.62190246580001,43.6454162598],"type":"Point"}
}