{
  "type": "Feature",
  "properties": {
    "addr:full":"204 King St W Oshawa ON L1J 2J2",
    "addr:housenumber":"204",
    "addr:postcode":"l1j 2j2",
    "addr:street":"King St W",
    "iso:country":"CA",
    "sg:address":"204 King St W",
    "sg:city":"Oshawa",
    "sg:classifiers":[
        {
            "category":"Retail",
            "subcategory":"Auto Repair",
            "type":"Services"
        }
    ],
    "sg:phone":"+1 905 728 6268",
    "sg:postcode":"L1J 2J2",
    "sg:province":"ON",
    "sg:tags":[
        "repairing",
        "automobile"
    ],
    "wof:name":"Speedy Auto Svc",
    "wof:placetype":"venue"
},
  "geometry": {"coordinates":[-78.8712463379,43.8960075378],"type":"Point"}
}