{
  "type": "Feature",
  "properties": {
    "addr:full":"1620 Johnston St Vancouver BC V6H 3S2",
    "addr:housenumber":"1620",
    "addr:postcode":"v6h 3s2",
    "addr:street":"Johnston St",
    "iso:country":"CA",
    "sg:address":"1620 Johnston St",
    "sg:city":"Vancouver",
    "sg:classifiers":[
        {
            "category":"Home & Garden",
            "subcategory":"Home Furnishings",
            "type":"Retail Goods"
        }
    ],
    "sg:phone":"+1 604 682 6575",
    "sg:postcode":"V6H 3S2",
    "sg:province":"BC",
    "sg:tags":[
        "pottery"
    ],
    "wof:name":"Kingsmill Studio Pottery",
    "wof:placetype":"venue"
},
  "geometry": {"coordinates":[-123.135169983,49.2719993591],"type":"Point"}
}