{
  "type": "Feature",
  "properties": {
    "iso:country":"CA",
    "sg:address":"360 Niagara St",
    "sg:city":"St Catharines",
    "sg:classifiers":[
        {
            "category":"Museum",
            "type":"Entertainment"
        }
    ],
    "sg:phone":"+1 905 646 4365",
    "sg:postcode":"L2M 4W1",
    "sg:province":"ON",
    "wof:name":"Children's Discovery Ctr",
    "wof:placetype":"venue"
},
  "geometry": {"coordinates":[-79.225402832,43.1836967468],"type":"Point"}
}