{
  "type": "Feature",
  "properties": {
    "addr:full":"860 Pleasant Dr Minto NB E4B 2V5",
    "addr:housenumber":"860",
    "addr:postcode":"e4b 2v5",
    "addr:street":"Pleasant Dr",
    "iso:country":"CA",
    "sg:address":"860 Pleasant Dr",
    "sg:city":"Minto",
    "sg:classifiers":[
        {
            "category":"Manufacturing",
            "subcategory":"Tools & Machinery",
            "type":"Manufacturing & Wholesale Goods"
        }
    ],
    "sg:phone":"+1 506 327 3361",
    "sg:postcode":"E4B 2V5",
    "sg:province":"NB",
    "sg:tags":[
        "machine",
        "shop"
    ],
    "wof:name":"Minto Machine & Welding Ltd",
    "wof:placetype":"venue"
},
  "geometry": {"coordinates":[-66.05020141599999,46.0772094727],"type":"Point"}
}