{
  "type": "Feature",
  "properties": {
    "addr:full":"849 Henderson Hwy Winnipeg MB R2K 2L4",
    "addr:housenumber":"849",
    "addr:postcode":"r2k 2l4",
    "addr:street":"Henderson Hwy",
    "iso:country":"CA",
    "sg:address":"849 Henderson Hwy",
    "sg:city":"Winnipeg",
    "sg:classifiers":[
        {
            "category":"Restaurant",
            "type":"Food & Drink"
        }
    ],
    "sg:phone":"+1 204 982 5557",
    "sg:postcode":"R2K 2L4",
    "sg:province":"MB",
    "sg:tags":[
        "pizza"
    ],
    "wof:name":"Big Time Pizza",
    "wof:placetype":"venue"
},
  "geometry": {"coordinates":[-97.1007156372,49.9306983948],"type":"Point"}
}