{
  "type": "Feature",
  "properties": {
    "addr:full":"2494 125 Rte S Saint-Donat-DE-Montcalm QC J0T 2C0",
    "addr:housenumber":"2494",
    "addr:postcode":"j0t 2c0",
    "addr:street":"125 Rte S",
    "iso:country":"CA",
    "sg:address":"2494 125 Rte S",
    "sg:city":"Saint-Donat-DE-Montcalm",
    "sg:classifiers":[
        {
            "category":"Travel",
            "subcategory":"Campground",
            "type":"Entertainment"
        }
    ],
    "sg:phone":"+1 819 424 2662",
    "sg:postcode":"J0T 2C0",
    "sg:province":"QC",
    "sg:tags":[
        "camp"
    ],
    "wof:name":"Camp Ouareau",
    "wof:placetype":"venue"
},
  "geometry": {"coordinates":[-74.54745483400001,45.9447593689],"type":"Point"}
}