{
  "type": "Feature",
  "properties": {
    "addr:full":"29 William Kitchen Rd Scarborough ON M1P 5B7",
    "addr:housenumber":"29",
    "addr:postcode":"m1p 5b7",
    "addr:street":"William Kitchen Rd",
    "iso:country":"CA",
    "sg:address":"29 William Kitchen Rd",
    "sg:city":"Scarborough",
    "sg:classifiers":[
        {
            "category":"Home & Garden",
            "subcategory":"Home Furnishings",
            "type":"Retail Goods"
        }
    ],
    "sg:phone":"+1 416 299 6176",
    "sg:postcode":"M1P 5B7",
    "sg:province":"ON",
    "sg:tags":[
        "housewares"
    ],
    "wof:name":"Benix & CO",
    "wof:placetype":"venue"
},
  "geometry": {"coordinates":[-79.279167,43.771996],"type":"Point"}
}