{
  "type": "Feature",
  "properties": {
    "iso:country":"CA",
    "sg:address":"1475 Ch Sainte-Foy",
    "sg:city":"Quebec",
    "sg:classifiers":[
        {
            "category":"Retail",
            "subcategory":"Laundry & Dry Cleaning",
            "type":"Services"
        }
    ],
    "sg:phone":"+1 418 681 4000",
    "sg:postcode":"G1S 2N7",
    "sg:province":"QC",
    "sg:tags":[
        "cleaners"
    ],
    "wof:name":"Lavoir St-Sacrement",
    "wof:placetype":"venue"
},
  "geometry": {"coordinates":[-71.257286,46.793243],"type":"Point"}
}