{
  "type": "Feature",
  "properties": {
    "addr:full":"Levis QC G6V 6L1",
    "addr:postcode":"g6v 6l1",
    "iso:country":"CA",
    "sg:city":"Levis",
    "sg:classifiers":[
        {
            "category":"Retail",
            "subcategory":"Car Wash",
            "type":"Services"
        }
    ],
    "sg:phone":"+1 418 835 8484",
    "sg:postcode":"G6V 6L1",
    "sg:province":"QC",
    "sg:tags":[
        "polishing",
        "washing"
    ],
    "wof:name":"Lave-Auto A LA Main Bel Air",
    "wof:placetype":"venue"
},
  "geometry": {"coordinates":[-71.1837463379,46.7928085327],"type":"Point"}
}