{
  "type": "Feature",
  "properties": {
    "iso:country":"CA",
    "sg:address":"1077 Crois Albanel",
    "sg:city":"Laval",
    "sg:classifiers":[
        {
            "category":"Professional",
            "subcategory":"Accounting & Tax Preparation",
            "type":"Services"
        }
    ],
    "sg:phone":"+1 450 629 1572",
    "sg:postcode":"H7G 4K9",
    "sg:province":"QC",
    "sg:tags":[
        "datum",
        "processing",
        "return",
        "filing"
    ],
    "wof:name":"Infogenie Inc",
    "wof:placetype":"venue"
},
  "geometry": {"coordinates":[-73.680031,45.583813],"type":"Point"}
}