{
  "type": "Feature",
  "properties": {
    "addr:full":"866 Rue Leon-Martel Terrebonne QC J6W 2K3",
    "addr:housenumber":"866",
    "addr:postcode":"j6w 2k3",
    "addr:street":"Rue Leon-Martel",
    "iso:country":"CA",
    "sg:address":"866 Rue Leon-Martel",
    "sg:city":"Terrebonne",
    "sg:classifiers":[
        {
            "category":"Travel",
            "subcategory":"Travel Agent",
            "type":"Entertainment"
        }
    ],
    "sg:phone":"+1 450 492 0896",
    "sg:postcode":"J6W 2K3",
    "sg:province":"QC",
    "sg:tags":[
        "agency",
        "bureau"
    ],
    "wof:name":"Voyages Ter & Mer",
    "wof:placetype":"venue"
},
  "geometry": {"coordinates":[-73.6311264038,45.7024688721],"type":"Point"}
}