{
  "type": "Feature",
  "properties": {
    "addr:full":"8538 Granville St Vancouver BC V6P 4Z7",
    "addr:housenumber":"8538",
    "addr:postcode":"v6p 4z7",
    "addr:street":"Granville St",
    "iso:country":"CA",
    "sg:address":"8538 Granville St",
    "sg:city":"Vancouver",
    "sg:classifiers":[
        {
            "category":"Personal",
            "subcategory":"Beauty Salon",
            "type":"Services"
        }
    ],
    "sg:phone":"+1 604 266 5810",
    "sg:postcode":"V6P 4Z7",
    "sg:province":"BC",
    "wof:name":"Nelly's Studio",
    "wof:placetype":"venue"
},
  "geometry": {"coordinates":[-123.14032,49.209076],"type":"Point"}
}