{
  "type": "Feature",
  "properties": {
    "iso:country":"CA",
    "sg:address":"653 Bishop St N",
    "sg:city":"Cambridge",
    "sg:classifiers":[
        {
            "category":"Shopping",
            "subcategory":"Jewelry",
            "type":"Retail Goods"
        }
    ],
    "sg:phone":"+1 519 653 0070",
    "sg:postcode":"N3H 2K8",
    "sg:province":"ON",
    "sg:tags":[
        "jeweler"
    ],
    "wof:name":"Kaieteur Gold",
    "wof:placetype":"venue"
},
  "geometry": {"coordinates":[-80.33795166020001,43.3928489685],"type":"Point"}
}