{
  "type": "Feature",
  "properties": {
    "addr:full":"644 Ireland Rd Simcoe ON N3Y 4K2",
    "addr:housenumber":"644",
    "addr:postcode":"n3y 4k2",
    "addr:street":"Ireland Rd",
    "iso:country":"CA",
    "sg:address":"644 Ireland Rd",
    "sg:city":"Simcoe",
    "sg:classifiers":[
        {
            "category":"Retail",
            "subcategory":"Car Wash",
            "type":"Services"
        }
    ],
    "sg:phone":"+1 519 426 5000",
    "sg:postcode":"N3Y 4K2",
    "sg:province":"ON",
    "sg:tags":[
        "polishing",
        "washing",
        "caterer"
    ],
    "wof:name":"Venture Cafe & Catering",
    "wof:placetype":"venue"
},
  "geometry": {"coordinates":[-80.280762,42.835705],"type":"Point"}
}