{
  "type": "Feature",
  "properties": {
    "addr:full":"21 Primrose Ave Toronto ON M6H 3V1",
    "addr:housenumber":"21",
    "addr:postcode":"m6h 3v1",
    "addr:street":"Primrose Ave",
    "iso:country":"CA",
    "sg:address":"21 Primrose Ave",
    "sg:city":"Toronto",
    "sg:classifiers":[
        {
            "category":"Manufacturing",
            "subcategory":"Chemicals & Compounds",
            "type":"Manufacturing & Wholesale Goods"
        }
    ],
    "sg:phone":"+1 416 531 4669",
    "sg:postcode":"M6H 3V1",
    "sg:province":"ON",
    "sg:tags":[
        "paint",
        "lacquer"
    ],
    "wof:name":"John E Goudey Mfg Ltd",
    "wof:placetype":"venue"
},
  "geometry": {"coordinates":[-79.444565,43.668674],"type":"Point"}
}