{
  "type": "Feature",
  "properties": {
    "addr:full":"313 Hayes Dr Swift Current SK S9H 4H2",
    "addr:housenumber":"313",
    "addr:postcode":"s9h 4h2",
    "addr:street":"Hayes Dr",
    "iso:country":"CA",
    "sg:address":"313 Hayes Dr",
    "sg:city":"Swift Current",
    "sg:classifiers":[
        {
            "category":"Building & Trades",
            "subcategory":"Construction",
            "type":"Services"
        }
    ],
    "sg:phone":"+1 306 773 0482",
    "sg:postcode":"S9H 4H2",
    "sg:province":"SK",
    "sg:tags":[
        "general",
        "contractor"
    ],
    "wof:name":"Pisiak Custom Framing Ltd",
    "wof:placetype":"venue"
},
  "geometry": {"coordinates":[-107.80744900000001,50.269501],"type":"Point"}
}