{
  "type": "Feature",
  "properties": {
    "addr:full":"201 3rd St Craik SK S0G 0V0",
    "addr:housenumber":"201",
    "addr:postcode":"s0g 0v0",
    "addr:street":"3Rd St",
    "iso:country":"CA",
    "sg:address":"201 3rd St",
    "sg:city":"Craik",
    "sg:classifiers":[
        {
            "category":"Banks & Credit Unions",
            "subcategory":"Bank",
            "type":"Services"
        }
    ],
    "sg:phone":"+1 306 734 2672",
    "sg:postcode":"S0G 0V0",
    "sg:province":"SK",
    "wof:name":"Royal Bank Financial Group",
    "wof:placetype":"venue"
},
  "geometry": {"coordinates":[-105.817504883,51.0488052368],"type":"Point"}
}