{
  "type": "Feature",
  "properties": {
    "addr:full":"143 Industrial Park Rd Shoal Lake MB R0J 1Z0",
    "addr:housenumber":"143",
    "addr:postcode":"r0j 1z0",
    "addr:street":"Industrial Park Rd",
    "iso:country":"CA",
    "sg:address":"143 Industrial Park Rd",
    "sg:city":"Shoal Lake",
    "sg:classifiers":[
        {
            "category":"Freight",
            "type":"Transportation"
        }
    ],
    "sg:phone":"+1 204 759 3045",
    "sg:postcode":"R0J 1Z0",
    "sg:province":"MB",
    "sg:tags":[
        "product",
        "protection",
        "grain",
        "crop",
        "elevator"
    ],
    "wof:name":"Agricore United",
    "wof:placetype":"venue"
},
  "geometry": {"coordinates":[-100.590721,50.43692],"type":"Point"}
}