{
  "type": "Feature",
  "properties": {
    "addr:full":"Vancouver BC V5T 4G5",
    "addr:postcode":"v5t 4g5",
    "iso:country":"CA",
    "sg:city":"Vancouver",
    "sg:classifiers":[
        {
            "category":"Shopping",
            "type":"Retail Goods"
        }
    ],
    "sg:phone":"+1 604 877 1198",
    "sg:postcode":"V5T 4G5",
    "sg:province":"BC",
    "sg:tags":[
        "cards",
        "sport",
        "baseball",
        "memorabilia"
    ],
    "wof:name":"Gem Mint Collectibles Ltd",
    "wof:placetype":"venue"
},
  "geometry": {"coordinates":[-123.097206116,49.262714386],"type":"Point"}
}