{
  "type": "Feature",
  "properties": {
    "addr:full":"13 Jutland Rd Etobicoke ON M8Z 2G6",
    "addr:housenumber":"13",
    "addr:postcode":"m8z 2g6",
    "addr:street":"Jutland Rd",
    "iso:country":"CA",
    "sg:address":"13 Jutland Rd",
    "sg:city":"Etobicoke",
    "sg:classifiers":[
        {
            "category":"Building & Trades",
            "subcategory":"Cleaning & Sanitation",
            "type":"Services"
        }
    ],
    "sg:phone":"+1 416 253 9722",
    "sg:postcode":"M8Z 2G6",
    "sg:province":"ON",
    "sg:tags":[
        "maintenance"
    ],
    "wof:name":"Macdero Construction Ltd",
    "wof:placetype":"venue"
},
  "geometry": {"coordinates":[-79.52713799999999,43.626575],"type":"Point"}
}