{
  "type": "Feature",
  "properties": {
    "addr:full":"Vancouver BC V6E 3P3",
    "addr:postcode":"v6e 3p3",
    "iso:country":"CA",
    "sg:city":"Vancouver",
    "sg:classifiers":[
        {
            "category":"Professional",
            "subcategory":"Lawyer & Legal Services",
            "type":"Services"
        }
    ],
    "sg:phone":"+1 604 682 6821",
    "sg:postcode":"V6E 3P3",
    "sg:province":"BC",
    "sg:tags":[
        "attorney"
    ],
    "wof:name":"Lando & CO",
    "wof:placetype":"venue"
},
  "geometry": {"coordinates":[-123.122124,49.285271],"type":"Point"}
}