{
  "type": "Feature",
  "properties": {
    "addr:full":"1050 South Service Rd W Oakville ON L6L 5T7",
    "addr:housenumber":"1050",
    "addr:postcode":"l6l 5t7",
    "addr:street":"South Service Rd W",
    "iso:country":"CA",
    "sg:address":"1050 South Service Rd W",
    "sg:city":"Oakville",
    "sg:classifiers":[
        {
            "category":"Retail",
            "subcategory":"Auto Repair",
            "type":"Services"
        }
    ],
    "sg:phone":"+1 905 847 6000",
    "sg:postcode":"L6L 5T7",
    "sg:province":"ON",
    "sg:tags":[
        "repairing",
        "automobile"
    ],
    "wof:name":"Oakville Tire Svc Ltd & Auto",
    "wof:placetype":"venue"
},
  "geometry": {"coordinates":[-79.7082061768,43.4352493286],"type":"Point"}
}