{
  "type": "Feature",
  "properties": {
    "addr:full":"1064 Ch Staynerville O Brownsburg-Chatham QC J8G 1S1",
    "addr:housenumber":"1064",
    "addr:postcode":"j8g 1s1",
    "addr:street":"Ch Staynerville O",
    "iso:country":"CA",
    "sg:address":"1064 Ch Staynerville O",
    "sg:city":"Brownsburg-Chatham",
    "sg:classifiers":[
        {
            "category":"Building & Trades",
            "subcategory":"Construction",
            "type":"Services"
        }
    ],
    "sg:phone":"+1 450 533 4211",
    "sg:postcode":"J8G 1S1",
    "sg:province":"QC",
    "sg:tags":[
        "excavating",
        "contractor"
    ],
    "wof:name":"Excavation Don Heatlie & Fils",
    "wof:placetype":"venue"
},
  "geometry": {"coordinates":[-74.5156326294,45.6596603394],"type":"Point"}
}