{
  "type": "Feature",
  "properties": {
    "addr:full":"1190 1E Av Lac-Saint-Charles QC G3G 2S9",
    "addr:housenumber":"1190",
    "addr:postcode":"g3g 2s9",
    "addr:street":"1E Av Lac-Saint-Charles",
    "iso:country":"CA",
    "sg:address":"1190 1E Av",
    "sg:city":"Lac-Saint-Charles",
    "sg:classifiers":[
        {
            "category":"Building & Trades",
            "subcategory":"Construction",
            "type":"Services"
        }
    ],
    "sg:phone":"+1 418 849 2841",
    "sg:postcode":"G3G 2S9",
    "sg:province":"QC",
    "sg:tags":[
        "general",
        "contractor"
    ],
    "wof:name":"Entreprises Peb Ltee",
    "wof:placetype":"venue"
},
  "geometry": {"coordinates":[-71.375916,46.908199],"type":"Point"}
}