{
  "type": "Feature",
  "properties": {
    "addr:full":"42 Arthur St S Elmira ON N3B 2M7",
    "addr:housenumber":"42",
    "addr:postcode":"n3b 2m7",
    "addr:street":"Arthur St S",
    "iso:country":"CA",
    "sg:address":"42 Arthur St S",
    "sg:city":"Elmira",
    "sg:classifiers":[
        {
            "category":"Wholesale",
            "subcategory":"Machinery & Supplies",
            "type":"Manufacturing & Wholesale Goods"
        }
    ],
    "sg:phone":"+1 519 669 1664",
    "sg:postcode":"N3B 2M7",
    "sg:province":"ON",
    "sg:tags":[
        "equipment",
        "industrial"
    ],
    "wof:name":"William Knell & CO Ltd",
    "wof:placetype":"venue"
},
  "geometry": {"coordinates":[-80.5588302612,43.5987815857],"type":"Point"}
}