{
  "type": "Feature",
  "properties": {
    "addr:full":"516 Portage Ave Fort Frances ON P9A 2A3",
    "addr:housenumber":"516",
    "addr:postcode":"p9a 2a3",
    "addr:street":"Portage Ave",
    "iso:country":"CA",
    "sg:address":"516 Portage Ave",
    "sg:city":"Fort Frances",
    "sg:classifiers":[
        {
            "category":"Social Services",
            "type":"Services"
        }
    ],
    "sg:phone":"+1 807 274 8541",
    "sg:postcode":"P9A 2A3",
    "sg:province":"ON",
    "sg:tags":[
        "organization",
        "welfare"
    ],
    "wof:name":"United Native Friendship Ctr",
    "wof:placetype":"venue"
},
  "geometry": {"coordinates":[-93.395409,48.610241],"type":"Point"}
}