{
  "type": "Feature",
  "properties": {
    "addr:full":"310 Smith St Arthur ON N0G 1A0",
    "addr:housenumber":"310",
    "addr:postcode":"n0g 1a0",
    "addr:street":"Smith St",
    "iso:country":"CA",
    "sg:address":"310 Smith St",
    "sg:city":"Arthur",
    "sg:classifiers":[
        {
            "category":"Professional",
            "subcategory":"Accounting & Tax Preparation",
            "type":"Services"
        }
    ],
    "sg:phone":"+1 905 669 1337",
    "sg:postcode":"N0G 1A0",
    "sg:province":"ON",
    "sg:tags":[
        "accountant"
    ],
    "wof:name":"Deacur Worthington & Assoc Ltd",
    "wof:placetype":"venue"
},
  "geometry": {"coordinates":[-80.5439300537,43.8337898254],"type":"Point"}
}