{
  "type": "Feature",
  "properties": {
    "addr:full":"365 Wellington St Miramichi NB E1N 1P6",
    "addr:housenumber":"365",
    "addr:postcode":"e1n 1p6",
    "addr:street":"Wellington St",
    "iso:country":"CA",
    "sg:address":"365 Wellington St",
    "sg:city":"Miramichi",
    "sg:classifiers":[
        {
            "category":"Building & Trades",
            "subcategory":"Construction",
            "type":"Services"
        }
    ],
    "sg:phone":"+1 506 778 8100",
    "sg:postcode":"E1N 1P6",
    "sg:province":"NB",
    "sg:tags":[
        "general",
        "contractor"
    ],
    "wof:name":"William J Kerr Ltd",
    "wof:placetype":"venue"
},
  "geometry": {"coordinates":[-65.4422988892,47.0443878174],"type":"Point"}
}