{
  "type": "Feature",
  "properties": {
    "addr:full":"30 Gore St E Perth ON K7H 1H5",
    "addr:housenumber":"30",
    "addr:postcode":"k7h 1h5",
    "addr:street":"Gore St E",
    "iso:country":"CA",
    "sg:address":"30 Gore St E",
    "sg:city":"Perth",
    "sg:classifiers":[
        {
            "category":"Banks & Credit Unions",
            "subcategory":"Bank",
            "type":"Services"
        }
    ],
    "sg:phone":"+1 613 267 3220",
    "sg:postcode":"K7H 1H5",
    "sg:province":"ON",
    "wof:name":"Bank of Montreal",
    "wof:placetype":"venue"
},
  "geometry": {"coordinates":[-76.250443,44.900513],"type":"Point"}
}