{
  "type": "Feature",
  "properties": {
    "addr:full":"891 Boul Sainte-Foy Longueuil QC J4K 1V6",
    "addr:housenumber":"891",
    "addr:postcode":"j4k 1v6",
    "addr:street":"Boul Sainte-Foy",
    "iso:country":"CA",
    "sg:address":"891 Boul Sainte-Foy",
    "sg:city":"Longueuil",
    "sg:classifiers":[
        {
            "category":"Building & Trades",
            "subcategory":"Construction",
            "type":"Services"
        }
    ],
    "sg:phone":"+1 514 527 1466",
    "sg:postcode":"J4K 1V6",
    "sg:province":"QC",
    "sg:tags":[
        "designer",
        "dealer",
        "pool",
        "swimming"
    ],
    "wof:name":"Piscines Perrin Inc",
    "wof:placetype":"venue"
},
  "geometry": {"coordinates":[-73.497536,45.521935],"type":"Point"}
}