{
  "type": "Feature",
  "properties": {
    "addr:full":"1181 Rue DE LA Montagne Montreal QC H3G 1Z2",
    "addr:housenumber":"1181",
    "addr:postcode":"h3g 1z2",
    "addr:street":"Rue De La Montagne",
    "iso:country":"CA",
    "sg:address":"1181 Rue DE LA Montagne",
    "sg:city":"Montreal",
    "sg:classifiers":[
        {
            "category":"Organizations",
            "subcategory":"Professional Association",
            "type":"Services"
        }
    ],
    "sg:phone":"+1 514 393 1417",
    "sg:postcode":"H3G 1Z2",
    "sg:province":"QC",
    "wof:name":"Canadian Heritage of Quebec",
    "wof:placetype":"venue"
},
  "geometry": {"coordinates":[-73.57338,45.497288],"type":"Point"}
}