{
  "type": "Feature",
  "properties": {
    "iso:country":"CA",
    "sg:address":"2585 Rue Masson",
    "sg:city":"Montreal",
    "sg:classifiers":[
        {
            "category":"Restaurant",
            "type":"Food & Drink"
        }
    ],
    "sg:phone":"+1 514 721 7721",
    "sg:postcode":"H1Y 1V7",
    "sg:province":"QC",
    "wof:name":"Pizza Masson Enr",
    "wof:placetype":"venue"
},
  "geometry": {"coordinates":[-73.576965332,45.5449676514],"type":"Point"}
}