{
  "type": "Feature",
  "properties": {
    "addr:full":"83 Nuggett Crt # 4 Brampton ON L6T 5H2",
    "addr:housenumber":"83",
    "addr:postcode":"l6t 5h2",
    "addr:street":"Nuggett Crt # 4",
    "iso:country":"CA",
    "sg:address":"83 Nuggett Crt # 4",
    "sg:city":"Brampton",
    "sg:classifiers":[
        {
            "category":"Professional",
            "subcategory":"Research",
            "type":"Services"
        }
    ],
    "sg:phone":"+1 905 799 3403",
    "sg:postcode":"L6T 5H2",
    "sg:province":"ON",
    "sg:tags":[
        "environmental",
        "ecological"
    ],
    "wof:name":"Wtp Equipment",
    "wof:placetype":"venue"
},
  "geometry": {"coordinates":[-79.6873703003,43.7219963074],"type":"Point"}
}