{
  "type": "Feature",
  "properties": {
    "iso:country":"CA",
    "sg:address":"66 Edward Ave",
    "sg:city":"Fort Erie",
    "sg:classifiers":[
        {
            "category":"Building & Trades",
            "subcategory":"Landscaping Services",
            "type":"Services"
        }
    ],
    "sg:phone":"+1 905 871 3074",
    "sg:postcode":"L2A 5K3",
    "sg:province":"ON",
    "sg:tags":[
        "lawn",
        "contractor",
        "landscape",
        "maintenance",
        "grounds"
    ],
    "wof:name":"Grass Groomers",
    "wof:placetype":"venue"
},
  "geometry": {"coordinates":[-78.9302139282,42.8940505981],"type":"Point"}
}