{
  "type": "Feature",
  "properties": {
    "iso:country":"CA",
    "sg:address":"6100 Young St",
    "sg:city":"Halifax",
    "sg:classifiers":[
        {
            "category":"Retail",
            "subcategory":"Laundry & Dry Cleaning",
            "type":"Services"
        }
    ],
    "sg:phone":"+1 902 454 6459",
    "sg:postcode":"B3K 2A4",
    "sg:province":"NS",
    "sg:tags":[
        "cleaners"
    ],
    "wof:name":"Same Day Dry Cleaners",
    "wof:placetype":"venue"
},
  "geometry": {"coordinates":[-63.60408,44.658134],"type":"Point"}
}