{
  "type": "Feature",
  "properties": {
    "addr:full":"4251 Village Stroll Whistler BC V0N 1B4",
    "addr:housenumber":"4251",
    "addr:postcode":"v0n 1b4",
    "addr:street":"Village Stroll",
    "iso:country":"CA",
    "sg:address":"4251 Village Stroll",
    "sg:city":"Whistler",
    "sg:classifiers":[
        {
            "category":"Shopping",
            "subcategory":"Bicycles & Sporting Goods",
            "type":"Retail Goods"
        }
    ],
    "sg:phone":"+1 604 932 6409",
    "sg:postcode":"V0N 1B4",
    "sg:province":"BC",
    "wof:name":"Sport Style Outdoor",
    "wof:placetype":"venue"
},
  "geometry": {"coordinates":[-122.955848694,50.1141624451],"type":"Point"}
}