{
  "type": "Feature",
  "properties": {
    "addr:full":"2 Edvac Dr Brampton ON L6S 5P2",
    "addr:housenumber":"2",
    "addr:postcode":"l6s 5p2",
    "addr:street":"Edvac Dr",
    "iso:country":"CA",
    "sg:address":"2 Edvac Dr",
    "sg:city":"Brampton",
    "sg:classifiers":[
        {
            "category":"Manufacturing",
            "subcategory":"Tools & Machinery",
            "type":"Manufacturing & Wholesale Goods"
        }
    ],
    "sg:phone":"+1 905 799 8555",
    "sg:postcode":"L6S 5P2",
    "sg:province":"ON",
    "sg:tags":[
        "machine",
        "screw",
        "product",
        "equipment"
    ],
    "wof:name":"Jobal Industries Ltd",
    "wof:placetype":"venue"
},
  "geometry": {"coordinates":[-79.70141599999999,43.760967],"type":"Point"}
}