{
  "type": "Feature",
  "properties": {
    "addr:full":"495 King St E Gananoque ON K7G 1G9",
    "addr:housenumber":"495",
    "addr:postcode":"k7g 1g9",
    "addr:street":"King St E",
    "iso:country":"CA",
    "sg:address":"495 King St E",
    "sg:city":"Gananoque",
    "sg:classifiers":[
        {
            "category":"Food & Beverages",
            "subcategory":"Groceries & Convenience Stores",
            "type":"Retail Goods"
        }
    ],
    "sg:phone":"+1 613 382 1830",
    "sg:postcode":"K7G 1G9",
    "sg:province":"ON",
    "sg:tags":[
        "grocer"
    ],
    "wof:name":"M & M Meat Shops",
    "wof:placetype":"venue"
},
  "geometry": {"coordinates":[-76.155045,44.334244],"type":"Point"}
}