{
  "type": "Feature",
  "properties": {
    "iso:country":"CA",
    "sg:address":"183 Preston St",
    "sg:city":"Ottawa",
    "sg:classifiers":[
        {
            "category":"Food & Beverages",
            "subcategory":"Specialty",
            "type":"Retail Goods"
        }
    ],
    "sg:phone":"+1 613 569 0456",
    "sg:postcode":"K1R 7P8",
    "sg:province":"ON",
    "sg:tags":[
        "health",
        "diet"
    ],
    "wof:name":"Muscle Madness",
    "wof:placetype":"venue"
},
  "geometry": {"coordinates":[-75.712929,45.406578],"type":"Point"}
}