{
  "type": "Feature",
  "properties": {
    "iso:country":"CA",
    "sg:address":"226 Rue Saint-Georges",
    "sg:city":"Matane",
    "sg:classifiers":[
        {
            "category":"Personal",
            "subcategory":"Beauty Salon",
            "type":"Services"
        }
    ],
    "sg:phone":"+1 418 562 8525",
    "sg:postcode":"G4W 2B4",
    "sg:province":"QC",
    "wof:name":"Coiffure Multicoupe",
    "wof:placetype":"venue"
},
  "geometry": {"coordinates":[-67.53378295900001,48.846534729],"type":"Point"}
}