{
  "type": "Feature",
  "properties": {
    "addr:full":"Toronto ON M5R 2E2",
    "addr:postcode":"m5r 2e2",
    "iso:country":"CA",
    "sg:city":"Toronto",
    "sg:classifiers":[
        {
            "category":"Shopping",
            "type":"Retail Goods"
        }
    ],
    "sg:phone":"+1 416 925 2461",
    "sg:postcode":"M5R 2E2",
    "sg:province":"ON",
    "sg:tags":[
        "art",
        "gallery",
        "dealer"
    ],
    "wof:name":"Miriam Shiell Fine Art Ltd",
    "wof:placetype":"venue"
},
  "geometry": {"coordinates":[-79.39343261720001,43.6712722778],"type":"Point"}
}