{
  "type": "Feature",
  "properties": {
    "iso:country":"CA",
    "sg:address":"1572 Dublin Ave",
    "sg:city":"Winnipeg",
    "sg:classifiers":[
        {
            "category":"Building & Trades",
            "subcategory":"Plumbing",
            "type":"Services"
        }
    ],
    "sg:phone":"+1 204 775 7237",
    "sg:postcode":"R3E 0L4",
    "sg:province":"MB",
    "sg:tags":[
        "product",
        "management",
        "energy",
        "system"
    ],
    "wof:name":"Siemens Building Technologies",
    "wof:placetype":"venue"
},
  "geometry": {"coordinates":[-97.1978149414,49.911277771],"type":"Point"}
}