{
  "type": "Feature",
  "properties": {
    "iso:country":"CA",
    "sg:address":"2611 3 Ave SE",
    "sg:city":"Calgary",
    "sg:classifiers":[
        {
            "category":"Social Services",
            "subcategory":"Child Care",
            "type":"Services"
        }
    ],
    "sg:phone":"+1 403 204 5633",
    "sg:postcode":"T2A 7W7",
    "sg:province":"AB",
    "wof:name":"Franklin Childrens' Ctr",
    "wof:placetype":"venue"
},
  "geometry": {"coordinates":[-113.99971771200001,51.0472412109],"type":"Point"}
}