{
  "type": "Feature",
  "properties": {
    "addr:full":"Whistler BC V0N 1B1",
    "addr:postcode":"v0n 1b1",
    "iso:country":"CA",
    "sg:city":"Whistler",
    "sg:classifiers":[
        {
            "category":"Professional",
            "subcategory":"Art Services",
            "type":"Services"
        }
    ],
    "sg:phone":"+1 604 932 8482",
    "sg:postcode":"V0N 1B1",
    "sg:province":"BC",
    "sg:tags":[
        "graphic",
        "designer"
    ],
    "wof:name":"Origin Design & Comms Ltd",
    "wof:placetype":"venue"
},
  "geometry": {"coordinates":[-123.03997,50.087666],"type":"Point"}
}