{
  "type": "Feature",
  "properties": {
    "addr:full":"1130 Boul DE L'Escale Havre-Saint-Pierre QC G0G 1P0",
    "addr:housenumber":"1130",
    "addr:postcode":"g0g 1p0",
    "addr:street":"Boul De",
    "iso:country":"CA",
    "sg:address":"1130 Boul DE L'Escale",
    "sg:city":"Havre-Saint-Pierre",
    "sg:classifiers":[
        {
            "category":"Insurance",
            "subcategory":"Insurance Agent",
            "type":"Services"
        }
    ],
    "sg:phone":"+1 418 538 3676",
    "sg:postcode":"G0G 1P0",
    "sg:province":"QC",
    "wof:name":"Assurance Promutuel",
    "wof:placetype":"venue"
},
  "geometry": {"coordinates":[-63.60453,50.244751],"type":"Point"}
}