{
  "type": "Feature",
  "properties": {
    "addr:full":"34 Rue DE LA Reserve Les Escoumins QC G0T 1K0",
    "addr:housenumber":"34",
    "addr:postcode":"g0t 1k0",
    "addr:street":"Rue De La Reserve",
    "iso:country":"CA",
    "sg:address":"34 Rue DE LA Reserve",
    "sg:city":"Les Escoumins",
    "sg:classifiers":[
        {
            "category":"Communications",
            "subcategory":"Radio Station",
            "type":"Services"
        }
    ],
    "sg:phone":"+1 418 233 2700",
    "sg:postcode":"G0T 1K0",
    "sg:province":"QC",
    "sg:tags":[
        "company",
        "broadcasting"
    ],
    "wof:name":"Radio Chme-FM",
    "wof:placetype":"venue"
},
  "geometry": {"coordinates":[-69.40119934080001,48.344127655],"type":"Point"}
}