{
  "type": "Feature",
  "properties": {
    "iso:country":"CA",
    "sg:address":"1103 3 Ave S",
    "sg:city":"Lethbridge",
    "sg:classifiers":[
        {
            "category":"Restaurant",
            "type":"Food & Drink"
        }
    ],
    "sg:phone":"+1 403 328 5503",
    "sg:postcode":"T1J 0J5",
    "sg:province":"AB",
    "wof:name":"Peking Gardens Restaurant",
    "wof:placetype":"venue"
},
  "geometry": {"coordinates":[-112.830627441,49.696308136],"type":"Point"}
}