{
  "type": "Feature",
  "properties": {
    "addr:full":"1110 12 Ave N Lethbridge AB T1H 1P8",
    "addr:housenumber":"1110",
    "addr:postcode":"t1h 1p8",
    "addr:street":"12 Ave N",
    "iso:country":"CA",
    "sg:address":"1110 12 Ave N",
    "sg:city":"Lethbridge",
    "sg:classifiers":[
        {
            "category":"Wholesale",
            "subcategory":"Photographic Equipment",
            "type":"Manufacturing & Wholesale Goods"
        }
    ],
    "sg:phone":"+1 403 328 0445",
    "sg:postcode":"T1H 1P8",
    "sg:province":"AB",
    "sg:tags":[
        "manufacturer"
    ],
    "wof:name":"Gibson Audio Visual Svc",
    "wof:placetype":"venue"
},
  "geometry": {"coordinates":[-112.830681,49.715473],"type":"Point"}
}