{
  "type": "Feature",
  "properties": {
    "addr:full":"10837 Rue Saint-Hubert Montreal QC H2C 2J3",
    "addr:housenumber":"10837",
    "addr:postcode":"h2c 2j3",
    "addr:street":"Rue Saint-Hubert",
    "iso:country":"CA",
    "sg:address":"10837 Rue Saint-Hubert",
    "sg:city":"Montreal",
    "sg:classifiers":[
        {
            "category":"Shopping",
            "subcategory":"Books",
            "type":"Retail Goods"
        }
    ],
    "sg:phone":"+1 514 388 8115",
    "sg:postcode":"H2C 2J3",
    "sg:province":"QC",
    "sg:tags":[
        "dealer"
    ],
    "wof:name":"Pontius Livres Books",
    "wof:placetype":"venue"
},
  "geometry": {"coordinates":[-73.66980743409999,45.5592422485],"type":"Point"}
}