{
  "type": "Feature",
  "properties": {
    "addr:full":"5372 10E Av Montreal QC H1Y 2G6",
    "addr:housenumber":"5372",
    "addr:postcode":"h1y 2g6",
    "addr:street":"10E Av",
    "iso:country":"CA",
    "sg:address":"5372 10E Av",
    "sg:city":"Montreal",
    "sg:classifiers":[
        {
            "category":"Wholesale",
            "subcategory":"Electrical",
            "type":"Manufacturing & Wholesale Goods"
        }
    ],
    "sg:phone":"+1 514 374 8695",
    "sg:postcode":"H1Y 2G6",
    "sg:province":"QC",
    "sg:tags":[
        "sound",
        "equipment",
        "system"
    ],
    "wof:name":"Integration Plus 4 Inc",
    "wof:placetype":"venue"
},
  "geometry": {"coordinates":[-73.572937,45.550037],"type":"Point"}
}