{
  "type": "Feature",
  "properties": {
    "addr:full":"603 N 8th Ave Golden BC V0A 1H0",
    "addr:housenumber":"603",
    "addr:postcode":"v0a 1h0",
    "addr:street":"N 8Th Ave",
    "iso:country":"CA",
    "sg:address":"603 N 8th Ave",
    "sg:city":"Golden",
    "sg:classifiers":[
        {
            "category":"Travel",
            "subcategory":"Hotels & Motels",
            "type":"Entertainment"
        }
    ],
    "sg:phone":"+1 250 344 7111",
    "sg:postcode":"V0A 1H0",
    "sg:province":"BC",
    "wof:name":"Mary's Motel",
    "wof:placetype":"venue"
},
  "geometry": {"coordinates":[-116.969246,51.300945],"type":"Point"}
}