{
  "type": "Feature",
  "properties": {
    "addr:full":"1625 Av Ampere Quebec QC G1P 4B8",
    "addr:housenumber":"1625",
    "addr:postcode":"g1p 4b8",
    "addr:street":"Av Ampere",
    "iso:country":"CA",
    "sg:address":"1625 Av Ampere",
    "sg:city":"Quebec",
    "sg:classifiers":[
        {
            "category":"Wholesale",
            "subcategory":"Machinery & Supplies",
            "type":"Manufacturing & Wholesale Goods"
        }
    ],
    "sg:phone":"+1 418 687 4106",
    "sg:postcode":"G1P 4B8",
    "sg:province":"QC",
    "sg:tags":[
        "equipment",
        "industrial"
    ],
    "wof:name":"Acklands Grainger Inc",
    "wof:placetype":"venue"
},
  "geometry": {"coordinates":[-71.2987976074,46.8056602478],"type":"Point"}
}