{
  "type": "Feature",
  "properties": {
    "addr:full":"20 1st Ave SW Weyburn SK S4H 2H8",
    "addr:housenumber":"20",
    "addr:postcode":"s4h 2h8",
    "addr:street":"1St Ave Sw",
    "iso:country":"CA",
    "sg:address":"20 1st Ave SW",
    "sg:city":"Weyburn",
    "sg:classifiers":[
        {
            "category":"Restaurant",
            "type":"Food & Drink"
        }
    ],
    "sg:phone":"+1 306 842 4555",
    "sg:postcode":"S4H 2H8",
    "sg:province":"SK",
    "wof:name":"A & W Family Restaurant",
    "wof:placetype":"venue"
},
  "geometry": {"coordinates":[-103.858543,49.658051],"type":"Point"}
}