{
  "type": "Feature",
  "properties": {
    "addr:full":"Valemount BC V0E 2Z0",
    "addr:postcode":"v0e 2z0",
    "iso:country":"CA",
    "sg:city":"Valemount",
    "sg:classifiers":[
        {
            "category":"Shopping",
            "subcategory":"Gifts & Souvenirs",
            "type":"Retail Goods"
        }
    ],
    "sg:phone":"+1 250 566 9197",
    "sg:postcode":"V0E 2Z0",
    "sg:province":"BC",
    "sg:tags":[
        "shop"
    ],
    "wof:name":"Essentials",
    "wof:placetype":"venue"
},
  "geometry": {"coordinates":[-119.278503418,52.8314399719],"type":"Point"}
}