{
  "type": "Feature",
  "properties": {
    "addr:full":"133 Hwy 10 N Balcarres SK S0G 0C0",
    "addr:housenumber":"133",
    "addr:postcode":"s0g 0c0",
    "addr:street":"Hwy 10 N",
    "iso:country":"CA",
    "sg:address":"133 Hwy 10 N",
    "sg:city":"Balcarres",
    "sg:classifiers":[
        {
            "category":"Retail",
            "subcategory":"Veterinary Services",
            "type":"Services"
        }
    ],
    "sg:phone":"+1 306 334 2598",
    "sg:postcode":"S0G 0C0",
    "sg:province":"SK",
    "sg:tags":[
        "veterinarian"
    ],
    "wof:name":"Balcarres Animal Clinic",
    "wof:placetype":"venue"
},
  "geometry": {"coordinates":[-103.538177,50.798374],"type":"Point"}
}