{
  "type": "Feature",
  "properties": {
    "addr:full":"35 Saffron Cres Etobicoke ON M9C 3T8",
    "addr:housenumber":"35",
    "addr:postcode":"m9c 3t8",
    "addr:street":"Saffron Cres",
    "iso:country":"CA",
    "sg:address":"35 Saffron Cres",
    "sg:city":"Etobicoke",
    "sg:classifiers":[
        {
            "category":"Education",
            "subcategory":"School",
            "type":"Public Place"
        }
    ],
    "sg:phone":"+1 416 393 5288",
    "sg:postcode":"M9C 3T8",
    "sg:province":"ON",
    "wof:name":"Nativity of Our Lord",
    "wof:placetype":"venue"
},
  "geometry": {"coordinates":[-79.575912,43.653744],"type":"Point"}
}