{
  "type": "Feature",
  "properties": {
    "addr:full":"4073 34E Av Shawinigan QC G9N 7J1",
    "addr:housenumber":"4073",
    "addr:postcode":"g9n 7j1",
    "addr:street":"34E Av",
    "iso:country":"CA",
    "sg:address":"4073 34E Av",
    "sg:city":"Shawinigan",
    "sg:classifiers":[
        {
            "category":"Professional",
            "subcategory":"Accounting & Tax Preparation",
            "type":"Services"
        }
    ],
    "sg:phone":"+1 819 539 2117",
    "sg:postcode":"G9N 7J1",
    "sg:province":"QC",
    "sg:tags":[
        "accountant"
    ],
    "wof:name":"Grenier, Pierre CA",
    "wof:placetype":"venue"
},
  "geometry": {"coordinates":[-72.746933,46.575829],"type":"Point"}
}