{
  "type": "Feature",
  "properties": {
    "addr:full":"7205 Portage Pl Burnaby BC V5A 3S9",
    "addr:housenumber":"7205",
    "addr:postcode":"v5a 3s9",
    "addr:street":"Portage Pl",
    "iso:country":"CA",
    "sg:address":"7205 Portage Pl",
    "sg:city":"Burnaby",
    "sg:classifiers":[
        {
            "category":"Professional",
            "type":"Services"
        }
    ],
    "sg:phone":"+1 604 420 4416",
    "sg:postcode":"V5A 3S9",
    "sg:province":"BC",
    "sg:tags":[
        "art",
        "restoring"
    ],
    "wof:name":"27 Fine Arts & Restoration",
    "wof:placetype":"venue"
},
  "geometry": {"coordinates":[-122.952072,49.252609],"type":"Point"}
}