{
  "type": "Feature",
  "properties": {
    "addr:full":"Ingleside ON K0C 1M0",
    "addr:postcode":"k0c 1m0",
    "iso:country":"CA",
    "sg:city":"Ingleside",
    "sg:classifiers":[
        {
            "category":"Health Services",
            "subcategory":"Doctor",
            "type":"Services"
        }
    ],
    "sg:phone":"+1 613 537 2044",
    "sg:postcode":"K0C 1M0",
    "sg:province":"ON",
    "sg:tags":[
        "physician",
        "clinic",
        "surgeon"
    ],
    "wof:name":"St Lawrence Medical Clinic",
    "wof:placetype":"venue"
},
  "geometry": {"coordinates":[-74.987793,44.996742],"type":"Point"}
}