{
  "type": "Feature",
  "properties": {
    "addr:full":"1311 Gemmell St Sudbury ON P3A 1G3",
    "addr:housenumber":"1311",
    "addr:postcode":"p3a 1g3",
    "addr:street":"Gemmell St",
    "iso:country":"CA",
    "sg:address":"1311 Gemmell St",
    "sg:city":"Sudbury",
    "sg:classifiers":[
        {
            "category":"Education",
            "subcategory":"School",
            "type":"Public Place"
        }
    ],
    "sg:phone":"+1 705 524 1150",
    "sg:postcode":"P3A 1G3",
    "sg:province":"ON",
    "wof:name":"Fare",
    "wof:placetype":"venue"
},
  "geometry": {"coordinates":[-80.94699900000001,46.512798],"type":"Point"}
}