{
  "type": "Feature",
  "properties": {
    "addr:full":"6100 Av Pierre-DE Coubertin Montreal QC H1N 1S4",
    "addr:housenumber":"6100",
    "addr:postcode":"h1n 1s4",
    "addr:street":"Av Pierre-De Coubertin",
    "iso:country":"CA",
    "sg:address":"6100 Av Pierre-DE Coubertin",
    "sg:city":"Montreal",
    "sg:classifiers":[
        {
            "category":"Recreation",
            "type":"Entertainment"
        }
    ],
    "sg:phone":"+1 514 872 6171",
    "sg:postcode":"H1N 1S4",
    "sg:province":"QC",
    "sg:tags":[
        "pool",
        "swimming"
    ],
    "wof:name":"Montreal Piscines Interieures",
    "wof:placetype":"venue"
},
  "geometry": {"coordinates":[-73.53866577150001,45.574672699],"type":"Point"}
}