{
  "type": "Feature",
  "properties": {
    "addr:full":"414 Main St Grandview MB R0L 0Y0",
    "addr:housenumber":"414",
    "addr:postcode":"r0l 0y0",
    "addr:street":"Main St",
    "iso:country":"CA",
    "sg:address":"414 Main St",
    "sg:city":"Grandview",
    "sg:classifiers":[
        {
            "category":"Professional",
            "subcategory":"Accounting & Tax Preparation",
            "type":"Services"
        }
    ],
    "sg:phone":"+1 204 546 2677",
    "sg:postcode":"R0L 0Y0",
    "sg:province":"MB",
    "sg:tags":[
        "accountant"
    ],
    "wof:name":"Shumka, Donald W CA",
    "wof:placetype":"venue"
},
  "geometry": {"coordinates":[-100.69960021999999,51.1684112549],"type":"Point"}
}