{
  "type": "Feature",
  "properties": {
    "addr:full":"92 Nithview Dr New Hamburg ON N3A 2H3",
    "addr:housenumber":"92",
    "addr:postcode":"n3a 2h3",
    "addr:street":"Nithview Dr",
    "iso:country":"CA",
    "sg:address":"92 Nithview Dr",
    "sg:city":"New Hamburg",
    "sg:classifiers":[
        {
            "category":"Professional",
            "subcategory":"Lawyer & Legal Services",
            "type":"Services"
        }
    ],
    "sg:phone":"+1 519 662 9520",
    "sg:postcode":"N3A 2H3",
    "sg:province":"ON",
    "sg:tags":[
        "attorney"
    ],
    "wof:name":"Thomson, Randell K",
    "wof:placetype":"venue"
},
  "geometry": {"coordinates":[-80.703064,43.381947],"type":"Point"}
}