{
  "type": "Feature",
  "properties": {
    "iso:country":"CA",
    "sg:address":"155 Rue Notre-Dame",
    "sg:city":"Repentigny",
    "sg:classifiers":[
        {
            "category":"Professional",
            "subcategory":"Advertising",
            "type":"Services"
        }
    ],
    "sg:phone":"+1 450 581 0214",
    "sg:postcode":"J6A 5L3",
    "sg:province":"QC",
    "sg:tags":[
        "grocer",
        "distribution"
    ],
    "wof:name":"Provigo Distribution Inc",
    "wof:placetype":"venue"
},
  "geometry": {"coordinates":[-73.47016906739999,45.7174835205],"type":"Point"}
}