{
  "type": "Feature",
  "properties": {
    "iso:country":"CA",
    "sg:city":"Spirit River",
    "sg:classifiers":[
        {
            "category":"Travel",
            "subcategory":"Travel Agent",
            "type":"Entertainment"
        }
    ],
    "sg:phone":"+1 780 864 4080",
    "sg:postcode":"T0H 3G0",
    "sg:province":"AB",
    "sg:tags":[
        "agency",
        "bureau"
    ],
    "wof:name":"Traveller's Agency",
    "wof:placetype":"venue"
},
  "geometry": {"coordinates":[-118.83657100000001,55.779785],"type":"Point"}
}