{
  "type": "Feature",
  "properties": {
    "addr:full":"Vancouver BC V5X 4P3",
    "addr:postcode":"v5x 4p3",
    "iso:country":"CA",
    "sg:city":"Vancouver",
    "sg:classifiers":[
        {
            "category":"Autos & Motor Vehicles",
            "subcategory":"Auto Supplies",
            "type":"Retail Goods"
        }
    ],
    "sg:phone":"+1 604 323 8369",
    "sg:postcode":"V5X 4P3",
    "sg:province":"BC",
    "sg:tags":[
        "equipment",
        "car",
        "racing",
        "tire",
        "automobile"
    ],
    "wof:name":"Trend Motoring Accessories Ltd",
    "wof:placetype":"venue"
},
  "geometry": {"coordinates":[-123.094223023,49.2083320618],"type":"Point"}
}