{
  "type": "Feature",
  "properties": {
    "addr:full":"2857 Derry Rd E Mississauga ON L4T 1A6",
    "addr:housenumber":"2857",
    "addr:postcode":"l4t 1a6",
    "addr:street":"Derry Rd E",
    "iso:country":"CA",
    "sg:address":"2857 Derry Rd E",
    "sg:city":"Mississauga",
    "sg:classifiers":[
        {
            "category":"Home & Garden",
            "subcategory":"Household Appliances",
            "type":"Retail Goods"
        }
    ],
    "sg:phone":"+1 905 677 0210",
    "sg:postcode":"L4T 1A6",
    "sg:province":"ON",
    "wof:name":"Atri Appliance Svc Inc",
    "wof:placetype":"venue"
},
  "geometry": {"coordinates":[-79.6446380615,43.7021903992],"type":"Point"}
}