{
  "type": "Feature",
  "properties": {
    "addr:full":"574 Watt St Winnipeg MB R2K 4K1",
    "addr:housenumber":"574",
    "addr:postcode":"r2k 4k1",
    "addr:street":"Watt St",
    "iso:country":"CA",
    "sg:address":"574 Watt St",
    "sg:city":"Winnipeg",
    "sg:classifiers":[
        {
            "category":"Wholesale",
            "subcategory":"Machinery & Supplies",
            "type":"Manufacturing & Wholesale Goods"
        }
    ],
    "sg:phone":"+1 204 668 7316",
    "sg:postcode":"R2K 4K1",
    "sg:province":"MB",
    "sg:tags":[
        "abrasive"
    ],
    "wof:name":"Convoy Industrial Supplies Ltd",
    "wof:placetype":"venue"
},
  "geometry": {"coordinates":[-97.0977935791,49.9181022644],"type":"Point"}
}