{
  "type": "Feature",
  "properties": {
    "iso:country":"CA",
    "sg:address":"263 Waterloo St",
    "sg:city":"London",
    "sg:classifiers":[
        {
            "category":"Manufacturing",
            "subcategory":"Metals",
            "type":"Manufacturing & Wholesale Goods"
        }
    ],
    "sg:phone":"+1 519 645 2799",
    "sg:postcode":"N6B 2N5",
    "sg:province":"ON",
    "sg:tags":[
        "plating"
    ],
    "wof:name":"Precision Plating",
    "wof:placetype":"venue"
},
  "geometry": {"coordinates":[-81.2404098511,42.9812278748],"type":"Point"}
}