{
  "type": "Feature",
  "properties": {
    "iso:country":"CA",
    "sg:address":"1008 41st Ave W",
    "sg:city":"Vancouver",
    "sg:classifiers":[
        {
            "category":"Autos & Motor Vehicles",
            "subcategory":"Fuel & Gas Station",
            "type":"Retail Goods"
        }
    ],
    "sg:phone":"+1 604 261 7283",
    "sg:postcode":"V6M 1W8",
    "sg:province":"BC",
    "sg:tags":[
        "oil"
    ],
    "wof:name":"41st & Oak Chevron Svc",
    "wof:placetype":"venue"
},
  "geometry": {"coordinates":[-123.128433227,49.2338752747],"type":"Point"}
}