{
  "type": "Feature",
  "properties": {
    "addr:full":"2110 Boul Saint-Jean-Baptiste Chicoutimi QC G7H 7W1",
    "addr:housenumber":"2110",
    "addr:postcode":"g7h 7w1",
    "addr:street":"Boul Saint-Jean-Baptiste",
    "iso:country":"CA",
    "sg:address":"2110 Boul Saint-Jean-Baptiste",
    "sg:city":"Chicoutimi",
    "sg:classifiers":[
        {
            "category":"Building & Trades",
            "subcategory":"Construction",
            "type":"Services"
        }
    ],
    "sg:phone":"+1 418 549 7107",
    "sg:postcode":"G7H 7W1",
    "sg:province":"QC",
    "sg:tags":[
        "sandblasting",
        "painter"
    ],
    "wof:name":"Sablage Industriel Sagu Ltee",
    "wof:placetype":"venue"
},
  "geometry": {"coordinates":[-71.0085525513,48.4033126831],"type":"Point"}
}