{
  "type": "Feature",
  "properties": {
    "addr:full":"Edmonton AB T5J 3N6",
    "addr:postcode":"t5j 3n6",
    "iso:country":"CA",
    "sg:city":"Edmonton",
    "sg:classifiers":[
        {
            "category":"Shopping",
            "subcategory":"Gifts & Souvenirs",
            "type":"Retail Goods"
        }
    ],
    "sg:phone":"+1 780 425 1063",
    "sg:postcode":"T5J 3N6",
    "sg:province":"AB",
    "sg:tags":[
        "shop"
    ],
    "wof:name":"Payless Snacks & Novelties",
    "wof:placetype":"venue"
},
  "geometry": {"coordinates":[-113.497581,53.540829],"type":"Point"}
}