{
  "type": "Feature",
  "properties": {
    "addr:full":"200 Av DE Merton Saint-Lambert QC J4P 2W3",
    "addr:housenumber":"200",
    "addr:postcode":"j4p 2w3",
    "addr:street":"Av De Merton",
    "iso:country":"CA",
    "sg:address":"200 Av DE Merton",
    "sg:city":"Saint-Lambert",
    "sg:classifiers":[
        {
            "category":"Real Estate",
            "subcategory":"Architect",
            "type":"Services"
        }
    ],
    "sg:phone":"+1 450 465 9470",
    "sg:postcode":"J4P 2W3",
    "sg:province":"QC",
    "wof:name":"Michon, Gilles",
    "wof:placetype":"venue"
},
  "geometry": {"coordinates":[-73.5143280029,45.5100135803],"type":"Point"}
}