{
  "type": "Feature",
  "properties": {
    "iso:country":"CA",
    "sg:city":"Saint-Hubert",
    "sg:classifiers":[
        {
            "category":"Shopping",
            "subcategory":"Florist",
            "type":"Retail Goods"
        }
    ],
    "sg:phone":"+1 450 656 7673",
    "sg:postcode":"J3Y 8X9",
    "sg:province":"QC",
    "wof:name":"Jardin Des Roses",
    "wof:placetype":"venue"
},
  "geometry": {"coordinates":[-73.406799,45.494141],"type":"Point"}
}