{
  "type": "Feature",
  "properties": {
    "addr:full":"4700 Vanguard Rd Richmond BC V6X 2P8",
    "addr:housenumber":"4700",
    "addr:postcode":"v6x 2p8",
    "addr:street":"Vanguard Rd",
    "iso:country":"CA",
    "sg:address":"4700 Vanguard Rd",
    "sg:city":"Richmond",
    "sg:classifiers":[
        {
            "category":"Home & Garden",
            "subcategory":"Building Materials",
            "type":"Retail Goods"
        }
    ],
    "sg:phone":"+1 604 273 8595",
    "sg:postcode":"V6X 2P8",
    "sg:province":"BC",
    "sg:tags":[
        "door"
    ],
    "wof:name":"Acme Prehung Doors Ltd",
    "wof:placetype":"venue"
},
  "geometry": {"coordinates":[-123.100601,49.17915],"type":"Point"}
}