{
  "type": "Feature",
  "properties": {
    "addr:full":"7300 Boul DE LA Rive-Sud Levis QC G6V 6Z4",
    "addr:housenumber":"7300",
    "addr:postcode":"g6v 6z4",
    "addr:street":"Boul De La Rive-Sud",
    "iso:country":"CA",
    "sg:address":"7300 Boul DE LA Rive-Sud",
    "sg:city":"Levis",
    "sg:classifiers":[
        {
            "category":"Arena",
            "subcategory":"Sports Club",
            "type":"Entertainment"
        }
    ],
    "sg:phone":"+1 418 838 4129",
    "sg:postcode":"G6V 6Z4",
    "sg:province":"QC",
    "sg:tags":[
        "athletic",
        "fields",
        "stadium",
        "government"
    ],
    "wof:name":"Arena Andre Lacroix",
    "wof:placetype":"venue"
},
  "geometry": {"coordinates":[-71.153793335,46.813457489],"type":"Point"}
}