{
  "type": "Feature",
  "properties": {
    "iso:country":"CA",
    "sg:address":"4187 Cote DE Cap-Rouge",
    "sg:city":"Cap-Rouge",
    "sg:classifiers":[
        {
            "category":"Shopping",
            "type":"Retail Goods"
        }
    ],
    "sg:phone":"+1 418 652 8363",
    "sg:postcode":"G1Y 1V2",
    "sg:province":"QC",
    "sg:tags":[
        "art",
        "gallery",
        "dealer"
    ],
    "wof:name":"Maison Blanchette",
    "wof:placetype":"venue"
},
  "geometry": {"coordinates":[-71.341796875,46.7490386963],"type":"Point"}
}