{
  "type": "Feature",
  "properties": {
    "addr:full":"7331 Rue Notre-Dame Ouest Trois-Rivieres-Ouest QC G9B 1L7",
    "addr:housenumber":"7331",
    "addr:postcode":"g9b 1l7",
    "addr:street":"Rue Notre-Dame Ouest",
    "iso:country":"CA",
    "sg:address":"7331 Rue Notre-Dame Ouest",
    "sg:city":"Trois-Rivieres-Ouest",
    "sg:classifiers":[
        {
            "category":"Health Services",
            "subcategory":"Nursing And Care Facility",
            "type":"Services"
        }
    ],
    "sg:phone":"+1 819 377 0277",
    "sg:postcode":"G9B 1L7",
    "sg:province":"QC",
    "sg:tags":[
        "home",
        "retirement",
        "community"
    ],
    "wof:name":"Villa Du Jardin Fleuri",
    "wof:placetype":"venue"
},
  "geometry": {"coordinates":[-72.5770187378,46.3123092651],"type":"Point"}
}