{
  "type": "Feature",
  "properties": {
    "addr:full":"18 Court House Sq Goderich ON N7A 3Y7",
    "addr:housenumber":"18",
    "addr:postcode":"n7a 3y7",
    "addr:street":"Court House Sq",
    "iso:country":"CA",
    "sg:address":"18 Court House Sq",
    "sg:city":"Goderich",
    "sg:classifiers":[
        {
            "category":"Professional",
            "subcategory":"Lawyer & Legal Services",
            "type":"Services"
        }
    ],
    "sg:phone":"+1 519 524 2154",
    "sg:postcode":"N7A 3Y7",
    "sg:province":"ON",
    "sg:tags":[
        "attorney"
    ],
    "wof:name":"Donnelly & Murphy",
    "wof:placetype":"venue"
},
  "geometry": {"coordinates":[-81.7118148804,43.7438087463],"type":"Point"}
}