{
  "type": "Feature",
  "properties": {
    "addr:full":"19 Duncan St Lancaster ON K0C 1N0",
    "addr:housenumber":"19",
    "addr:postcode":"k0c 1n0",
    "addr:street":"Duncan St",
    "iso:country":"CA",
    "sg:address":"19 Duncan St",
    "sg:city":"Lancaster",
    "sg:classifiers":[
        {
            "category":"Retail",
            "subcategory":"Auto Repair",
            "type":"Services"
        }
    ],
    "sg:phone":"+1 613 347 2067",
    "sg:postcode":"K0C 1N0",
    "sg:province":"ON",
    "sg:tags":[
        "repairing",
        "automobile"
    ],
    "wof:name":"Roger Menard Garage Ltd",
    "wof:placetype":"venue"
},
  "geometry": {"coordinates":[-74.49861900000001,45.1413],"type":"Point"}
}