{
  "type": "Feature",
  "properties": {
    "iso:country":"CA",
    "sg:city":"Parksville",
    "sg:classifiers":[
        {
            "category":"Shopping",
            "type":"Retail Goods"
        }
    ],
    "sg:phone":"+1 250 248 9833",
    "sg:postcode":"V9P 1W3",
    "sg:province":"BC",
    "sg:tags":[
        "upholstery",
        "top",
        "cover",
        "awning",
        "canopy",
        "boat"
    ],
    "wof:name":"Fawcett Boat Covers",
    "wof:placetype":"venue"
},
  "geometry": {"coordinates":[-124.26473999,49.3072547913],"type":"Point"}
}