{
  "type": "Feature",
  "properties": {
    "addr:full":"2481 Kaladar Ave Ottawa ON K1V 8B9",
    "addr:housenumber":"2481",
    "addr:postcode":"k1v 8b9",
    "addr:street":"Kaladar Ave",
    "iso:country":"CA",
    "sg:address":"2481 Kaladar Ave",
    "sg:city":"Ottawa",
    "sg:classifiers":[
        {
            "category":"Manufacturing",
            "subcategory":"Tools & Machinery",
            "type":"Manufacturing & Wholesale Goods"
        }
    ],
    "sg:phone":"+1 613 731 5935",
    "sg:postcode":"K1V 8B9",
    "sg:province":"ON",
    "sg:tags":[
        "equipment",
        "hospital",
        "supply"
    ],
    "wof:name":"Vms Rehab Systems",
    "wof:placetype":"venue"
},
  "geometry": {"coordinates":[-75.67099,45.375484],"type":"Point"}
}