{
  "type": "Feature",
  "properties": {
    "addr:full":"55 Rue DE L'Eglise Verdun QC H4G 3E7",
    "addr:housenumber":"55",
    "addr:postcode":"h4g 3e7",
    "addr:street":"Rue De L'Eglise",
    "iso:country":"CA",
    "sg:address":"55 Rue DE L'Eglise",
    "sg:city":"Verdun",
    "sg:classifiers":[
        {
            "category":"Shopping",
            "subcategory":"Pharmacy",
            "type":"Retail Goods"
        }
    ],
    "sg:phone":"+1 514 768 1119",
    "sg:postcode":"H4G 3E7",
    "sg:province":"QC",
    "wof:name":"Pharmacie Michel Lapalme",
    "wof:placetype":"venue"
},
  "geometry": {"coordinates":[-73.5642776489,45.4628410339],"type":"Point"}
}