{
  "type": "Feature",
  "properties": {
    "addr:full":"312 5 St S Lethbridge AB T1J 2B5",
    "addr:housenumber":"312 5",
    "addr:postcode":"t1j 2b5",
    "addr:street":"St S",
    "iso:country":"CA",
    "sg:address":"312 5 St S",
    "sg:city":"Lethbridge",
    "sg:classifiers":[
        {
            "category":"Travel",
            "subcategory":"Hotels & Motels",
            "type":"Entertainment"
        }
    ],
    "sg:phone":"+1 403 327 5754",
    "sg:postcode":"T1J 2B5",
    "sg:province":"AB",
    "wof:name":"Coal Banks Inn",
    "wof:placetype":"venue"
},
  "geometry": {"coordinates":[-112.840492,49.695469],"type":"Point"}
}