{
  "type": "Feature",
  "properties": {
    "addr:full":"364 Simcoe St Beaverton ON L0K 1A0",
    "addr:housenumber":"364",
    "addr:postcode":"l0k 1a0",
    "addr:street":"Simcoe St",
    "iso:country":"CA",
    "sg:address":"364 Simcoe St",
    "sg:city":"Beaverton",
    "sg:classifiers":[
        {
            "category":"Personal",
            "type":"Services"
        }
    ],
    "sg:phone":"+1 705 426 9554",
    "sg:postcode":"L0K 1A0",
    "sg:province":"ON",
    "sg:tags":[
        "program",
        "physical",
        "exercise",
        "fitness"
    ],
    "wof:name":"Bodyfirm",
    "wof:placetype":"venue"
},
  "geometry": {"coordinates":[-79.153671,44.429695],"type":"Point"}
}