{
  "type": "Feature",
  "properties": {
    "iso:country":"CA",
    "sg:city":"Lachine",
    "sg:classifiers":[
        {
            "category":"Shopping",
            "subcategory":"Clothing, Apparel, & Fashions",
            "type":"Retail Goods"
        }
    ],
    "sg:phone":"+1 514 639 5198",
    "sg:postcode":"H8S 1X8",
    "sg:province":"QC",
    "sg:tags":[
        "item",
        "boutique"
    ],
    "wof:name":"Dada Mode",
    "wof:placetype":"venue"
},
  "geometry": {"coordinates":[-73.689774,45.437798],"type":"Point"}
}