{
  "type": "Feature",
  "properties": {
    "addr:full":"8 Director Crt Woodbridge ON L4L 3Z5",
    "addr:housenumber":"8",
    "addr:postcode":"l4l 3z5",
    "addr:street":"Director Crt",
    "iso:country":"CA",
    "sg:address":"8 Director Crt",
    "sg:city":"Woodbridge",
    "sg:classifiers":[
        {
            "category":"Professional",
            "subcategory":"Detective & Security Services",
            "type":"Services"
        }
    ],
    "sg:phone":"+1 905 850 8888",
    "sg:postcode":"L4L 3Z5",
    "sg:province":"ON",
    "sg:tags":[
        "investigator"
    ],
    "wof:name":"Mc Nulty & Assoc Investigation",
    "wof:placetype":"venue"
},
  "geometry": {"coordinates":[-79.5411,43.772022],"type":"Point"}
}