{
  "type": "Feature",
  "properties": {
    "addr:full":"752 Rue Saint-Jean Quebec QC G1R 1P9",
    "addr:housenumber":"752",
    "addr:postcode":"g1r 1p9",
    "addr:street":"Rue Saint-Jean",
    "iso:country":"CA",
    "sg:address":"752 Rue Saint-Jean",
    "sg:city":"Quebec",
    "sg:classifiers":[
        {
            "category":"Shopping",
            "subcategory":"Clothing, Apparel, & Fashions",
            "type":"Retail Goods"
        }
    ],
    "sg:phone":"+1 418 525 5600",
    "sg:postcode":"G1R 1P9",
    "sg:province":"QC",
    "sg:tags":[
        "item",
        "boutique"
    ],
    "wof:name":"Boutique Mec",
    "wof:placetype":"venue"
},
  "geometry": {"coordinates":[-71.2180404663,46.8111114502],"type":"Point"}
}