{
  "type": "Feature",
  "properties": {
    "addr:full":"258 Wallace Ave #206 Toronto ON M6P 3M9",
    "addr:housenumber":"258",
    "addr:postcode":"m6p 3m9",
    "addr:street":"Wallace Ave # 206",
    "iso:country":"CA",
    "sg:address":"258 Wallace Ave #206",
    "sg:city":"Toronto",
    "sg:classifiers":[
        {
            "category":"Manufacturing",
            "subcategory":"Printing",
            "type":"Manufacturing & Wholesale Goods"
        }
    ],
    "sg:phone":"+1 416 537 2103",
    "sg:postcode":"M6P 3M9",
    "sg:province":"ON",
    "sg:tags":[
        "newspaper"
    ],
    "wof:name":"Teach Magazine",
    "wof:placetype":"venue"
},
  "geometry": {"coordinates":[-79.447182,43.661915],"type":"Point"}
}