{
  "type": "Feature",
  "properties": {
    "addr:full":"504 Knutsen Crt Yellowknife NT X1A 2Y5",
    "addr:housenumber":"504",
    "addr:postcode":"x1a 2y5",
    "addr:street":"Knutsen Crt",
    "iso:country":"CA",
    "sg:address":"504 Knutsen Crt",
    "sg:city":"Yellowknife",
    "sg:classifiers":[
        {
            "category":"Arts & Performance",
            "subcategory":"Theater",
            "type":"Entertainment"
        }
    ],
    "sg:phone":"+1 867 873 8144",
    "sg:postcode":"X1A 2Y5",
    "sg:province":"NT",
    "sg:tags":[
        "live",
        "music"
    ],
    "wof:name":"Danceaway Music Svc",
    "wof:placetype":"venue"
},
  "geometry": {"coordinates":[-114.406639,62.442825],"type":"Point"}
}