{
  "type": "Feature",
  "properties": {
    "iso:country":"CA",
    "sg:city":"Waubaushene",
    "sg:classifiers":[
        {
            "category":"Autos & Motor Vehicles",
            "subcategory":"Automobile Sales",
            "type":"Retail Goods"
        }
    ],
    "sg:phone":"+1 705 538 9978",
    "sg:postcode":"L0K 2C0",
    "sg:province":"ON",
    "sg:tags":[
        "car",
        "dealer"
    ],
    "wof:name":"Bay Street Auto Sales Ltd",
    "wof:placetype":"venue"
},
  "geometry": {"coordinates":[-79.71072387700001,44.754119873],"type":"Point"}
}