{
  "type": "Feature",
  "properties": {
    "addr:full":"8 Art St Powerview MB R0E 1P0",
    "addr:housenumber":"8",
    "addr:postcode":"r0e 1p0",
    "addr:street":"Art St",
    "iso:country":"CA",
    "sg:address":"8 Art St",
    "sg:city":"Powerview",
    "sg:classifiers":[
        {
            "category":"Shopping",
            "subcategory":"Used Merchandise",
            "type":"Retail Goods"
        }
    ],
    "sg:phone":"+1 204 367 4537",
    "sg:postcode":"R0E 1P0",
    "sg:province":"MB",
    "sg:tags":[
        "second",
        "pawnbroker",
        "store",
        "hand"
    ],
    "wof:name":"Cash in A Flash Pawn Shop",
    "wof:placetype":"venue"
},
  "geometry": {"coordinates":[-96.198257,50.567291],"type":"Point"}
}