{
  "type": "Feature",
  "properties": {
    "iso:country":"CA",
    "sg:city":"Kanata",
    "sg:classifiers":[
        {
            "category":"Health Services",
            "subcategory":"Doctor",
            "type":"Services"
        }
    ],
    "sg:phone":"+1 613 592 5105",
    "sg:postcode":"K2K 1L1",
    "sg:province":"ON",
    "sg:tags":[
        "dentist"
    ],
    "wof:name":"Beaverbrook Dental Health Clnc",
    "wof:placetype":"venue"
},
  "geometry": {"coordinates":[-75.90139,45.329918],"type":"Point"}
}