{
  "type": "Feature",
  "properties": {
    "addr:full":"680 Ch Du Lac Boucherville QC J4B 6W7",
    "addr:housenumber":"680",
    "addr:postcode":"j4b 6w7",
    "addr:street":"Ch Du Lac",
    "iso:country":"CA",
    "sg:address":"680 Ch Du Lac",
    "sg:city":"Boucherville",
    "sg:classifiers":[
        {
            "category":"Retail",
            "subcategory":"Auto Repair",
            "type":"Services"
        }
    ],
    "sg:phone":"+1 450 655 5004",
    "sg:postcode":"J4B 6W7",
    "sg:province":"QC",
    "sg:tags":[
        "repairing",
        "automobile",
        "radiator"
    ],
    "wof:name":"Radiateur D'Auto Boucherville",
    "wof:placetype":"venue"
},
  "geometry": {"coordinates":[-73.4418792725,45.611541748],"type":"Point"}
}