{
  "type": "Feature",
  "properties": {
    "addr:full":"200 Station Rd Glovertown NL A0G 2L0",
    "addr:housenumber":"200",
    "addr:postcode":"a0g 2l0",
    "addr:street":"Station Rd",
    "iso:country":"CA",
    "sg:address":"200 Station Rd",
    "sg:city":"Glovertown",
    "sg:classifiers":[
        {
            "category":"Health Services",
            "subcategory":"Nursing And Care Facility",
            "type":"Services"
        }
    ],
    "sg:phone":"+1 709 533 2600",
    "sg:postcode":"A0G 2L0",
    "sg:province":"NL",
    "sg:tags":[
        "home",
        "rest"
    ],
    "wof:name":"Orams Birchview Manor",
    "wof:placetype":"venue"
},
  "geometry": {"coordinates":[-54.0351257324,48.6735153198],"type":"Point"}
}