{
  "type": "Feature",
  "properties": {
    "addr:full":"2100 Bloor St W # 1 Toronto ON M6S 1M7",
    "addr:housenumber":"2100",
    "addr:postcode":"m6s 1m7",
    "addr:street":"Bloor St W # 1",
    "iso:country":"CA",
    "sg:address":"2100 Bloor St W # 1",
    "sg:city":"Toronto",
    "sg:classifiers":[
        {
            "category":"Restaurant",
            "type":"Food & Drink"
        }
    ],
    "sg:phone":"+1 416 763 5555",
    "sg:postcode":"M6S 1M7",
    "sg:province":"ON",
    "wof:name":"Pizza Hut",
    "wof:placetype":"venue"
},
  "geometry": {"coordinates":[-79.47065000000001,43.652512],"type":"Point"}
}