{
  "type": "Feature",
  "properties": {
    "addr:full":"10 Mcewan Dr W Bolton ON L7E 1H1",
    "addr:housenumber":"10",
    "addr:postcode":"l7e 1h1",
    "addr:street":"Mcewan Dr W",
    "iso:country":"CA",
    "sg:address":"10 Mcewan Dr W",
    "sg:city":"Bolton",
    "sg:classifiers":[
        {
            "category":"Home & Garden",
            "subcategory":"Furniture",
            "type":"Retail Goods"
        }
    ],
    "sg:phone":"+1 905 951 9669",
    "sg:postcode":"L7E 1H1",
    "sg:province":"ON",
    "sg:tags":[
        "top",
        "counter",
        "kitchen",
        "cabinet"
    ],
    "wof:name":"Bolton Counter Top Inc",
    "wof:placetype":"venue"
},
  "geometry": {"coordinates":[-79.712509,43.862061],"type":"Point"}
}