{
  "type": "Feature",
  "properties": {
    "addr:full":"1908 6 Ave S Lethbridge AB T1J 1B9",
    "addr:housenumber":"1908",
    "addr:postcode":"t1j 1b9",
    "addr:street":"6 Ave S",
    "iso:country":"CA",
    "sg:address":"1908 6 Ave S",
    "sg:city":"Lethbridge",
    "sg:classifiers":[
        {
            "category":"Shopping",
            "subcategory":"Florist",
            "type":"Retail Goods"
        }
    ],
    "sg:phone":"+1 403 320 0697",
    "sg:postcode":"T1J 1B9",
    "sg:province":"AB",
    "sg:tags":[
        "plant"
    ],
    "wof:name":"Touch of Green",
    "wof:placetype":"venue"
},
  "geometry": {"coordinates":[-112.81436920199999,49.6914138794],"type":"Point"}
}