{
  "type": "Feature",
  "properties": {
    "addr:full":"Churchill MB R0B 0E0",
    "addr:postcode":"r0b 0e0",
    "iso:country":"CA",
    "sg:city":"Churchill",
    "sg:classifiers":[
        {
            "category":"Building & Trades",
            "subcategory":"Construction",
            "type":"Services"
        }
    ],
    "sg:phone":"+1 204 675 2717",
    "sg:postcode":"R0B 0E0",
    "sg:province":"MB",
    "sg:tags":[
        "demolition",
        "contractor"
    ],
    "wof:name":"Button Bay Blasting CO",
    "wof:placetype":"venue"
},
  "geometry": {"coordinates":[-94.1679534912,58.7691192627],"type":"Point"}
}