{
  "type": "Feature",
  "properties": {
    "addr:full":"80 Rue Beaudin Saint-Remi QC J0L 2L0",
    "addr:housenumber":"80",
    "addr:postcode":"j0l 2l0",
    "addr:street":"Rue Beaudin Saint-Remi",
    "iso:country":"CA",
    "sg:address":"80 Rue Beaudin",
    "sg:city":"Saint-Remi",
    "sg:classifiers":[
        {
            "category":"Building & Trades",
            "subcategory":"Electrical",
            "type":"Services"
        }
    ],
    "sg:phone":"+1 450 454 6492",
    "sg:postcode":"J0L 2L0",
    "sg:province":"QC",
    "sg:tags":[
        "electric",
        "contractor"
    ],
    "wof:name":"Mjm Electrique Inc",
    "wof:placetype":"venue"
},
  "geometry": {"coordinates":[-73.622253,45.256699],"type":"Point"}
}