{
  "type": "Feature",
  "properties": {
    "addr:full":"6604 Rama Rd RR 6 Orillia ON L3V 6H6",
    "addr:housenumber":"6604",
    "addr:postcode":"l3v 6h6",
    "addr:street":"Rama Rd;6",
    "iso:country":"CA",
    "sg:address":"6604 Rama Rd RR 6",
    "sg:city":"Orillia",
    "sg:classifiers":[
        {
            "category":"Professional",
            "subcategory":"Business Services",
            "type":"Services"
        }
    ],
    "sg:phone":"+1 416 350 2370",
    "sg:postcode":"L3V 6H6",
    "sg:province":"ON",
    "sg:tags":[
        "resort",
        "convention",
        "meeting",
        "facility"
    ],
    "wof:name":"Geneva Park Conference Ctr",
    "wof:placetype":"venue"
},
  "geometry": {"coordinates":[-79.418228,44.60659],"type":"Point"}
}