{
  "type": "Feature",
  "properties": {
    "addr:full":"88 Main St Grand Falls-Windsor NL A2B 1J6",
    "addr:housenumber":"88",
    "addr:postcode":"a2b 1j6",
    "addr:street":"Main St",
    "iso:country":"CA",
    "sg:address":"88 Main St",
    "sg:city":"Grand Falls-Windsor",
    "sg:classifiers":[
        {
            "category":"Professional",
            "subcategory":"Business Services",
            "type":"Services"
        }
    ],
    "sg:phone":"+1 709 489 8000",
    "sg:postcode":"A2B 1J6",
    "sg:province":"NL",
    "sg:tags":[
        "embroidery"
    ],
    "wof:name":"Atlantex Imaged Wear",
    "wof:placetype":"venue"
},
  "geometry": {"coordinates":[-55.6604232788,48.9499588013],"type":"Point"}
}