{
  "type": "Feature",
  "properties": {
    "addr:full":"67 Route 230 O Saint-Pascal QC G0L 3Y0",
    "addr:housenumber":"67",
    "addr:postcode":"g0l 3y0",
    "addr:street":"Route 230 O",
    "iso:country":"CA",
    "sg:address":"67 Route 230 O",
    "sg:city":"Saint-Pascal",
    "sg:classifiers":[
        {
            "category":"Farming",
            "subcategory":"Farm & Veterinary Services",
            "type":"Manufacturing & Wholesale Goods"
        }
    ],
    "sg:phone":"+1 418 492 2727",
    "sg:postcode":"G0L 3Y0",
    "sg:province":"QC",
    "sg:tags":[
        "insemination"
    ],
    "wof:name":"Pelletier, Denis",
    "wof:placetype":"venue"
},
  "geometry": {"coordinates":[-69.84214799999999,47.501965],"type":"Point"}
}