{
  "type": "Feature",
  "properties": {
    "addr:full":"425 University Ave E # K Waterloo ON N2K 4C9",
    "addr:housenumber":"425",
    "addr:postcode":"n2k 4c9",
    "addr:street":"University Ave E # K",
    "iso:country":"CA",
    "sg:address":"425 University Ave E # K",
    "sg:city":"Waterloo",
    "sg:classifiers":[
        {
            "category":"Health Services",
            "subcategory":"Optometrist",
            "type":"Services"
        }
    ],
    "sg:phone":"+1 519 744 4157",
    "sg:postcode":"N2K 4C9",
    "sg:province":"ON",
    "wof:name":"Sarvas, Carmen OD",
    "wof:placetype":"venue"
},
  "geometry": {"coordinates":[-80.49176,43.490829],"type":"Point"}
}