{
  "type": "Feature",
  "properties": {
    "iso:country":"CA",
    "sg:city":"Mont-Tremblant",
    "sg:classifiers":[
        {
            "category":"Real Estate",
            "subcategory":"Real Estate Agent",
            "type":"Services"
        }
    ],
    "sg:phone":"+1 819 425 3777",
    "sg:postcode":"J8E 3J8",
    "sg:province":"QC",
    "wof:name":"Region Mont Tremblant",
    "wof:placetype":"venue"
},
  "geometry": {"coordinates":[-74.595703125,46.1183586121],"type":"Point"}
}