{
  "type": "Feature",
  "properties": {
    "addr:full":"8097 134 St Surrey BC V3W 4T7",
    "addr:housenumber":"8097",
    "addr:postcode":"v3w 4t7",
    "addr:street":"134 St",
    "iso:country":"CA",
    "sg:address":"8097 134 St",
    "sg:city":"Surrey",
    "sg:classifiers":[
        {
            "category":"Social Services",
            "subcategory":"Child Care",
            "type":"Services"
        }
    ],
    "sg:phone":"+1 604 572 5758",
    "sg:postcode":"V3W 4T7",
    "sg:province":"BC",
    "wof:name":"Little Newton Daycare Ctr",
    "wof:placetype":"venue"
},
  "geometry": {"coordinates":[-122.851471,49.14983],"type":"Point"}
}