{
  "type": "Feature",
  "properties": {
    "addr:full":"60 Rue Saint-Jean Longueuil QC J4H 2W9",
    "addr:housenumber":"60",
    "addr:postcode":"j4h 2w9",
    "addr:street":"Rue Saint-Jean",
    "iso:country":"CA",
    "sg:address":"60 Rue Saint-Jean",
    "sg:city":"Longueuil",
    "sg:classifiers":[
        {
            "category":"Personal",
            "subcategory":"Barber",
            "type":"Services"
        }
    ],
    "sg:phone":"+1 450 670 4440",
    "sg:postcode":"J4H 2W9",
    "sg:province":"QC",
    "wof:name":"Salon Sylvie Dubois",
    "wof:placetype":"venue"
},
  "geometry": {"coordinates":[-73.512924,45.53738],"type":"Point"}
}