{
  "type": "Feature",
  "properties": {
    "addr:full":"PO Box 62 Schuler AB T0J 3B0",
    "addr:housenumber":"po box 62;ab",
    "addr:postcode":"t0j 3b0",
    "addr:street":"Schuler",
    "iso:country":"CA",
    "sg:address":"PO Box 62",
    "sg:city":"Schuler",
    "sg:classifiers":[
        {
            "category":"Recreation",
            "type":"Entertainment"
        }
    ],
    "sg:phone":"+1 403 839 3788",
    "sg:postcode":"T0J 3B0",
    "sg:province":"AB",
    "sg:tags":[
        "club",
        "curling"
    ],
    "wof:name":"Schuler Community Curling Club",
    "wof:placetype":"venue"
},
  "geometry": {"coordinates":[-110.094245911,50.3681755066],"type":"Point"}
}