{
  "type": "Feature",
  "properties": {
    "iso:country":"CA",
    "sg:address":"234 Stewart Green SW",
    "sg:city":"Calgary",
    "sg:classifiers":[
        {
            "category":"Personal",
            "subcategory":"Beauty Salon",
            "type":"Services"
        }
    ],
    "sg:phone":"+1 403 246 8880",
    "sg:postcode":"T3H 3C8",
    "sg:province":"AB",
    "wof:name":"Styling CO",
    "wof:placetype":"venue"
},
  "geometry": {"coordinates":[-114.168938,51.015362],"type":"Point"}
}