{
  "type": "Feature",
  "properties": {
    "addr:full":"12 Durham St Brockville ON K6V 7A4",
    "addr:housenumber":"12",
    "addr:postcode":"k6v 7a4",
    "addr:street":"Durham St",
    "iso:country":"CA",
    "sg:address":"12 Durham St",
    "sg:city":"Brockville",
    "sg:classifiers":[
        {
            "category":"Social Services",
            "subcategory":"Child Care",
            "type":"Services"
        }
    ],
    "sg:phone":"+1 613 342 1479",
    "sg:postcode":"K6V 7A4",
    "sg:province":"ON",
    "wof:name":"St John Bosco Children's Ctr",
    "wof:placetype":"venue"
},
  "geometry": {"coordinates":[-75.708893,44.608723],"type":"Point"}
}