{
  "type": "Feature",
  "properties": {
    "addr:full":"Red Deer AB T4N 4R7",
    "addr:postcode":"t4n 4r7",
    "iso:country":"CA",
    "sg:city":"Red Deer",
    "sg:classifiers":[
        {
            "category":"Restaurant",
            "type":"Food & Drink"
        }
    ],
    "sg:phone":"+1 403 340 3795",
    "sg:postcode":"T4N 4R7",
    "sg:province":"AB",
    "wof:name":"Hubie's 1955 Diner",
    "wof:placetype":"venue"
},
  "geometry": {"coordinates":[-113.829742,52.257809],"type":"Point"}
}