{
  "type": "Feature",
  "properties": {
    "addr:full":"9889 Pinnacles Rd Vernon BC V1B 3M1",
    "addr:housenumber":"9889",
    "addr:postcode":"bc v1b 3m1",
    "addr:street":"Pinnacles Rd",
    "iso:country":"CA",
    "sg:address":"9889 Pinnacles Rd",
    "sg:city":"Vernon",
    "sg:classifiers":[
        {
            "category":"Travel",
            "subcategory":"Hotels & Motels",
            "type":"Entertainment"
        }
    ],
    "sg:phone":"+1 250 542 4548",
    "sg:postcode":"V1B 3M1",
    "sg:province":"BC",
    "wof:name":"Pinnacles Suite Hotels",
    "wof:placetype":"venue"
},
  "geometry": {"coordinates":[-119.273803711,50.2656860352],"type":"Point"}
}