{
  "type": "Feature",
  "properties": {
    "addr:full":"Huntingdon QC J0S 1H0",
    "addr:postcode":"j0s 1h0",
    "iso:country":"CA",
    "sg:city":"Huntingdon",
    "sg:classifiers":[
        {
            "category":"Farming",
            "subcategory":"Farm",
            "type":"Manufacturing & Wholesale Goods"
        }
    ],
    "sg:phone":"+1 450 264 2979",
    "sg:postcode":"J0S 1H0",
    "sg:province":"QC",
    "wof:name":"Buermans Fermes",
    "wof:placetype":"venue"
},
  "geometry": {"coordinates":[-74.169212,45.091461],"type":"Point"}
}