{
  "type": "Feature",
  "properties": {
    "addr:full":"1806 Rue Des Herons Chicoutimi QC G7H 7M6",
    "addr:housenumber":"1806",
    "addr:postcode":"g7h 7m6",
    "addr:street":"Rue Des Herons",
    "iso:country":"CA",
    "sg:address":"1806 Rue Des Herons",
    "sg:city":"Chicoutimi",
    "sg:classifiers":[
        {
            "category":"Professional",
            "subcategory":"Management & Consulting",
            "type":"Services"
        }
    ],
    "sg:phone":"+1 418 693 5151",
    "sg:postcode":"G7H 7M6",
    "sg:province":"QC",
    "sg:tags":[
        "consultant",
        "welding"
    ],
    "wof:name":"Groupe Conseil En Soudage Inc",
    "wof:placetype":"venue"
},
  "geometry": {"coordinates":[-71.0559310913,48.3954429626],"type":"Point"}
}