{
  "type": "Feature",
  "properties": {
    "addr:full":"186 Ontario St Burks Falls ON P0A 1C0",
    "addr:housenumber":"186",
    "addr:postcode":"p0a 1c0",
    "addr:street":"Ontario St",
    "iso:country":"CA",
    "sg:address":"186 Ontario St",
    "sg:city":"Burks Falls",
    "sg:classifiers":[
        {
            "category":"Banks & Credit Unions",
            "subcategory":"Bank",
            "type":"Services"
        }
    ],
    "sg:phone":"+1 705 382 2364",
    "sg:postcode":"P0A 1C0",
    "sg:province":"ON",
    "wof:name":"Kawartha Credit Union",
    "wof:placetype":"venue"
},
  "geometry": {"coordinates":[-83.563789,46.256714],"type":"Point"}
}