{
  "type": "Feature",
  "properties": {
    "addr:full":"North Bay ON P1B 9S9",
    "addr:postcode":"p1b 9s9",
    "iso:country":"CA",
    "sg:city":"North Bay",
    "sg:classifiers":[
        {
            "category":"Government",
            "subcategory":"Office",
            "type":"Public Place"
        }
    ],
    "sg:phone":"+1 705 494 4130",
    "sg:postcode":"P1B 9S9",
    "sg:province":"ON",
    "wof:name":"Ontario Health Insurance Plan",
    "wof:placetype":"venue"
},
  "geometry": {"coordinates":[-79.4853820801,46.3336181641],"type":"Point"}
}