{
  "type": "Feature",
  "properties": {
    "iso:country":"CA",
    "sg:address":"405 18 St S",
    "sg:city":"Lethbridge",
    "sg:classifiers":[
        {
            "category":"Education",
            "subcategory":"School",
            "type":"Public Place"
        }
    ],
    "sg:phone":"+1 403 327 4596",
    "sg:postcode":"T1J 3E5",
    "sg:province":"AB",
    "wof:name":"Catholic Central High School",
    "wof:placetype":"venue"
},
  "geometry": {"coordinates":[-112.816001892,49.6947135925],"type":"Point"}
}