{
  "type": "Feature",
  "properties": {
    "addr:full":"80 Richmond St Amherstburg ON N9V 1E9",
    "addr:housenumber":"80",
    "addr:postcode":"n9v 1e9",
    "addr:street":"Richmond St",
    "iso:country":"CA",
    "sg:address":"80 Richmond St",
    "sg:city":"Amherstburg",
    "sg:classifiers":[
        {
            "category":"Health Services",
            "subcategory":"Optometrist",
            "type":"Services"
        }
    ],
    "sg:phone":"+1 519 736 2406",
    "sg:postcode":"N9V 1E9",
    "sg:province":"ON",
    "wof:name":"DE Pinto, Giuseppe OD",
    "wof:placetype":"venue"
},
  "geometry": {"coordinates":[-83.11112199999999,42.102955],"type":"Point"}
}