{
  "type": "Feature",
  "properties": {
    "addr:full":"4698 Kingston Rd Scarborough ON M1E 2P9",
    "addr:housenumber":"4698",
    "addr:postcode":"m1e 2p9",
    "addr:street":"Kingston Rd",
    "iso:country":"CA",
    "sg:address":"4698 Kingston Rd",
    "sg:city":"Scarborough",
    "sg:classifiers":[
        {
            "category":"Organizations",
            "subcategory":"Religious Organization",
            "type":"Services"
        }
    ],
    "sg:phone":"+1 416 208 9276",
    "sg:postcode":"M1E 2P9",
    "sg:province":"ON",
    "wof:name":"Buddhist Centre Toronto",
    "wof:placetype":"venue"
},
  "geometry": {"coordinates":[-79.1721878052,43.7784538269],"type":"Point"}
}