{
  "type": "Feature",
  "properties": {
    "addr:full":"RR 1 Wellington Station PE C0B 2E0",
    "addr:postcode":"c0b 2e0",
    "addr:street":"Rr 1 Wellington",
    "iso:country":"CA",
    "sg:address":"RR 1",
    "sg:city":"Wellington Station",
    "sg:classifiers":[
        {
            "category":"Building & Trades",
            "subcategory":"Construction",
            "type":"Services"
        }
    ],
    "sg:phone":"+1 902 854 2405",
    "sg:postcode":"C0B 2E0",
    "sg:province":"PE",
    "sg:tags":[
        "painter"
    ],
    "wof:name":"Arsenault Painters Ltd",
    "wof:placetype":"venue"
},
  "geometry": {"coordinates":[-64.00045,46.449951],"type":"Point"}
}