{
  "type": "Feature",
  "properties": {
    "addr:full":"682 Granderson Rd Victoria BC V9B 2R8",
    "addr:housenumber":"682",
    "addr:postcode":"v9b 2r8",
    "addr:street":"Granderson Rd",
    "iso:country":"CA",
    "sg:address":"682 Granderson Rd",
    "sg:city":"Victoria",
    "sg:classifiers":[
        {
            "category":"Personal",
            "subcategory":"Barber",
            "type":"Services"
        }
    ],
    "sg:phone":"+1 250 478 8065",
    "sg:postcode":"V9B 2R8",
    "sg:province":"BC",
    "wof:name":"Gaby the Barber",
    "wof:placetype":"venue"
},
  "geometry": {"coordinates":[-123.36451700000001,48.428314],"type":"Point"}
}