{
  "type": "Feature",
  "properties": {
    "addr:full":"663 Av Mceachran Outremont QC H2V 3C6",
    "addr:postcode":"h2v 3c6",
    "addr:street":"663 Av Mceachran",
    "iso:country":"CA",
    "sg:address":"663 Av Mceachran",
    "sg:city":"Outremont",
    "sg:classifiers":[
        {
            "category":"Manufacturing",
            "subcategory":"Tools & Machinery",
            "type":"Manufacturing & Wholesale Goods"
        }
    ],
    "sg:phone":"+1 514 274 4244",
    "sg:postcode":"H2V 3C6",
    "sg:province":"QC",
    "sg:tags":[
        "windmill",
        "engineer"
    ],
    "wof:name":"Dermond Experts-Conseil Inc",
    "wof:placetype":"venue"
},
  "geometry": {"coordinates":[-73.6131820679,45.5168914795],"type":"Point"}
}