{
  "type": "Feature",
  "properties": {
    "addr:full":"155 Rue Martineau # 105 Saint-Gilles QC G0S 2P0",
    "addr:housenumber":"155",
    "addr:postcode":"g0s 2p0",
    "addr:street":"Rue Martineau # 105",
    "iso:country":"CA",
    "sg:address":"155 Rue Martineau # 105",
    "sg:city":"Saint-Gilles",
    "sg:classifiers":[
        {
            "category":"Home & Garden",
            "subcategory":"Building Materials",
            "type":"Retail Goods"
        }
    ],
    "sg:phone":"+1 418 888 1322",
    "sg:postcode":"G0S 2P0",
    "sg:province":"QC",
    "sg:tags":[
        "door"
    ],
    "wof:name":"Ultra-Fab Inc",
    "wof:placetype":"venue"
},
  "geometry": {"coordinates":[-71.369141,46.512215],"type":"Point"}
}