{
  "type": "Feature",
  "properties": {
    "addr:full":"321 Main St S Morris MB R0G 1K0",
    "addr:housenumber":"321",
    "addr:postcode":"r0g 1k0",
    "addr:street":"Main St S Morris",
    "iso:country":"CA",
    "sg:address":"321 Main St S",
    "sg:city":"Morris",
    "sg:classifiers":[
        {
            "category":"Manufacturing",
            "subcategory":"Metals",
            "type":"Manufacturing & Wholesale Goods"
        }
    ],
    "sg:phone":"+1 204 746 8770",
    "sg:postcode":"R0G 1K0",
    "sg:province":"MB",
    "sg:tags":[
        "fence"
    ],
    "wof:name":"Ed's Carpentry",
    "wof:placetype":"venue"
},
  "geometry": {"coordinates":[-97.3648605347,49.3506088257],"type":"Point"}
}