{
  "type": "Feature",
  "properties": {
    "addr:full":"338 Waterloo St New Hamburg ON N3A 1T6",
    "addr:housenumber":"338",
    "addr:postcode":"n3a 1t6",
    "addr:street":"Waterloo St",
    "iso:country":"CA",
    "sg:address":"338 Waterloo St",
    "sg:city":"New Hamburg",
    "sg:classifiers":[
        {
            "category":"Restaurant",
            "type":"Food & Drink"
        }
    ],
    "sg:phone":"+1 519 662 1314",
    "sg:postcode":"N3A 1T6",
    "sg:province":"ON",
    "wof:name":"Kfc",
    "wof:placetype":"venue"
},
  "geometry": {"coordinates":[-80.712334,43.385941],"type":"Point"}
}