{
  "type": "Feature",
  "properties": {
    "addr:full":"1010 3E Av Val-D'Or QC J9P 1T3",
    "addr:housenumber":"1010",
    "addr:postcode":"j9p 1t3",
    "addr:street":"3E Av Val-D'Or",
    "iso:country":"CA",
    "sg:address":"1010 3E Av",
    "sg:city":"Val-D'Or",
    "sg:classifiers":[
        {
            "category":"Mining & Drilling",
            "type":"Manufacturing & Wholesale Goods"
        }
    ],
    "sg:phone":"+1 819 874 4511",
    "sg:postcode":"J9P 1T3",
    "sg:province":"QC",
    "sg:tags":[
        "company",
        "mine"
    ],
    "wof:name":"Aurizon Mines Ltd",
    "wof:placetype":"venue"
},
  "geometry": {"coordinates":[-71.8759231567,48.4230728149],"type":"Point"}
}