{
  "type": "Feature",
  "properties": {
    "iso:country":"CA",
    "sg:address":"423 Enfield Rd",
    "sg:city":"Burlington",
    "sg:classifiers":[
        {
            "category":"Manufacturing",
            "subcategory":"Tools & Machinery",
            "type":"Manufacturing & Wholesale Goods"
        }
    ],
    "sg:phone":"+1 905 631 1919",
    "sg:postcode":"L7T 2X5",
    "sg:province":"ON",
    "sg:tags":[
        "chemical",
        "plant"
    ],
    "wof:name":"Syscan Technologies",
    "wof:placetype":"venue"
},
  "geometry": {"coordinates":[-79.84272,43.319656],"type":"Point"}
}