{
  "type": "Feature",
  "properties": {
    "addr:full":"20460 Langley Bypass Langley BC V3A 5E7",
    "addr:housenumber":"20460",
    "addr:postcode":"v3a 5e7",
    "addr:street":"Langley Bypass",
    "iso:country":"CA",
    "sg:address":"20460 Langley Bypass",
    "sg:city":"Langley",
    "sg:classifiers":[
        {
            "category":"Restaurant",
            "type":"Food & Drink"
        }
    ],
    "sg:phone":"+1 604 534 1442",
    "sg:postcode":"V3A 5E7",
    "sg:province":"BC",
    "sg:tags":[
        "sandwich"
    ],
    "wof:name":"Subway Sandwiches & Salads",
    "wof:placetype":"venue"
},
  "geometry": {"coordinates":[-122.655021667,49.1130905151],"type":"Point"}
}