{
  "type": "Feature",
  "properties": {
    "addr:full":"Onanole MB R0J 1N0",
    "addr:postcode":"r0j 1n0",
    "iso:country":"CA",
    "sg:city":"Onanole",
    "sg:classifiers":[
        {
            "category":"Education",
            "subcategory":"School",
            "type":"Public Place"
        }
    ],
    "sg:phone":"+1 204 848 2402",
    "sg:postcode":"R0J 1N0",
    "sg:province":"MB",
    "wof:name":"Onanole School",
    "wof:placetype":"venue"
},
  "geometry": {"coordinates":[-99.9686050415,50.6227912903],"type":"Point"}
}