{
  "type": "Feature",
  "properties": {
    "addr:full":"4869 Boul Taschereau Greenfield Park QC J4V 3K3",
    "addr:housenumber":"4869",
    "addr:postcode":"j4v 3k3",
    "addr:street":"Boul Taschereau",
    "iso:country":"CA",
    "sg:address":"4869 Boul Taschereau",
    "sg:city":"Greenfield Park",
    "sg:classifiers":[
        {
            "category":"Travel",
            "subcategory":"Hotels & Motels",
            "type":"Entertainment"
        }
    ],
    "sg:phone":"+1 450 676 0285",
    "sg:postcode":"J4V 3K3",
    "sg:province":"QC",
    "wof:name":"Canada Motel",
    "wof:placetype":"venue"
},
  "geometry": {"coordinates":[-73.465133667,45.4838676453],"type":"Point"}
}