{
  "type": "Feature",
  "properties": {
    "addr:full":"1221 Canyon Meadows Dr SE #11 Calgary AB T2J 6G2",
    "addr:housenumber":"1221",
    "addr:postcode":"t2j 6g2",
    "addr:street":"Canyon Meadows Dr Se # 11",
    "iso:country":"CA",
    "sg:address":"1221 Canyon Meadows Dr SE #11",
    "sg:city":"Calgary",
    "sg:classifiers":[
        {
            "category":"Shopping",
            "subcategory":"Florist",
            "type":"Retail Goods"
        }
    ],
    "sg:phone":"+1 403 278 0214",
    "sg:postcode":"T2J 6G2",
    "sg:province":"AB",
    "wof:name":"Deer Valley Florist",
    "wof:placetype":"venue"
},
  "geometry": {"coordinates":[-114.03048699999999,50.931244],"type":"Point"}
}