{
  "type": "Feature",
  "properties": {
    "addr:full":"450 Av Kensington Westmount QC H3Y 3A2",
    "addr:housenumber":"450",
    "addr:postcode":"h3y 3a2",
    "addr:street":"Av Kensington",
    "iso:country":"CA",
    "sg:address":"450 Av Kensington",
    "sg:city":"Westmount",
    "sg:classifiers":[
        {
            "category":"Education",
            "subcategory":"College",
            "type":"Public Place"
        }
    ],
    "sg:phone":"+1 514 939 2430",
    "sg:postcode":"H3Y 3A2",
    "sg:province":"QC",
    "sg:tags":[
        "academic",
        "school"
    ],
    "wof:name":"Akiva School",
    "wof:placetype":"venue"
},
  "geometry": {"coordinates":[-73.59761,45.485027],"type":"Point"}
}