{
  "type": "Feature",
  "properties": {
    "addr:full":"591 Main St W Grimsby ON L3M 1V1",
    "addr:housenumber":"591",
    "addr:postcode":"l3m 1v1",
    "addr:street":"Main St W",
    "iso:country":"CA",
    "sg:address":"591 Main St W",
    "sg:city":"Grimsby",
    "sg:classifiers":[
        {
            "category":"Retail",
            "subcategory":"Auto Repair",
            "type":"Services"
        }
    ],
    "sg:phone":"+1 905 643 3965",
    "sg:postcode":"L3M 1V1",
    "sg:province":"ON",
    "sg:tags":[
        "machine",
        "automobile",
        "shop"
    ],
    "wof:name":"Steven's Auto Electric & Mach",
    "wof:placetype":"venue"
},
  "geometry": {"coordinates":[-79.62994399999999,43.205872],"type":"Point"}
}