{
  "type": "Feature",
  "properties": {
    "addr:full":"Jerseyside NL A0B 2G0",
    "addr:postcode":"a0b 2g0",
    "iso:country":"CA",
    "sg:city":"Jerseyside",
    "sg:classifiers":[
        {
            "category":"Organizations",
            "subcategory":"Professional Association",
            "type":"Services"
        }
    ],
    "sg:phone":"+1 709 227 5142",
    "sg:postcode":"A0B 2G0",
    "sg:province":"NL",
    "wof:name":"Waterfront Club Citizens",
    "wof:placetype":"venue"
},
  "geometry": {"coordinates":[-53.99308,47.276569],"type":"Point"}
}