{
  "type": "Feature",
  "properties": {
    "addr:full":"55 Trillium Park Pl Kitchener ON N2E 1X1",
    "addr:housenumber":"55",
    "addr:postcode":"n2e 1x1",
    "addr:street":"Trillium Park Pl",
    "iso:country":"CA",
    "sg:address":"55 Trillium Park Pl",
    "sg:city":"Kitchener",
    "sg:classifiers":[
        {
            "category":"Professional",
            "subcategory":"Detective & Security Services",
            "type":"Services"
        }
    ],
    "sg:phone":"+1 519 748 5358",
    "sg:postcode":"N2E 1X1",
    "sg:province":"ON",
    "sg:tags":[
        "car",
        "armored"
    ],
    "wof:name":"Brink's Armoured Car Svc",
    "wof:placetype":"venue"
},
  "geometry": {"coordinates":[-80.46049499999999,43.399853],"type":"Point"}
}