{
  "type": "Feature",
  "properties": {
    "addr:full":"1067 Broadway W Vancouver BC V6H 1E2",
    "addr:housenumber":"1067",
    "addr:postcode":"v6h 1e2",
    "addr:street":"Broadway W",
    "iso:country":"CA",
    "sg:address":"1067 Broadway W",
    "sg:city":"Vancouver",
    "sg:classifiers":[
        {
            "category":"Manufacturing",
            "subcategory":"Printing",
            "type":"Manufacturing & Wholesale Goods"
        }
    ],
    "sg:phone":"+1 604 734 4908",
    "sg:postcode":"V6H 1E2",
    "sg:province":"BC",
    "sg:tags":[
        "printer"
    ],
    "wof:name":"Prompt Printers Ltd",
    "wof:placetype":"venue"
},
  "geometry": {"coordinates":[-123.128128,49.263577],"type":"Point"}
}