{
  "type": "Feature",
  "properties": {
    "addr:full":"80 Main St Sackville NB E4L 4A7",
    "addr:housenumber":"80",
    "addr:postcode":"e4l 4a7",
    "addr:street":"Main St",
    "iso:country":"CA",
    "sg:address":"80 Main St",
    "sg:city":"Sackville",
    "sg:classifiers":[
        {
            "category":"Manufacturing",
            "subcategory":"Printing",
            "type":"Manufacturing & Wholesale Goods"
        }
    ],
    "sg:phone":"+1 506 536 2500",
    "sg:postcode":"E4L 4A7",
    "sg:province":"NB",
    "sg:tags":[
        "newspaper"
    ],
    "wof:name":"Sackville Tribune Post Ltd",
    "wof:placetype":"venue"
},
  "geometry": {"coordinates":[-64.3689651489,45.8970527649],"type":"Point"}
}