{
  "type": "Feature",
  "properties": {
    "addr:full":"1301 Lakewood Dr Sudbury ON P3E 6H9",
    "addr:housenumber":"1301",
    "addr:postcode":"p3e 6h9",
    "addr:street":"Lakewood Dr",
    "iso:country":"CA",
    "sg:address":"1301 Lakewood Dr",
    "sg:city":"Sudbury",
    "sg:classifiers":[
        {
            "category":"Manufacturing",
            "subcategory":"Tools & Machinery",
            "type":"Manufacturing & Wholesale Goods"
        }
    ],
    "sg:phone":"+1 705 670 8652",
    "sg:postcode":"P3E 6H9",
    "sg:province":"ON",
    "sg:tags":[
        "fan"
    ],
    "wof:name":"Garner Sales Inc ma",
    "wof:placetype":"venue"
},
  "geometry": {"coordinates":[-80.958664,46.469269],"type":"Point"}
}