{
  "type": "Feature",
  "properties": {
    "addr:full":"555 Parkdale Ave Ottawa ON K1Y 1H9",
    "addr:housenumber":"555",
    "addr:postcode":"k1y 1h9",
    "addr:street":"Parkdale Ave",
    "iso:country":"CA",
    "sg:address":"555 Parkdale Ave",
    "sg:city":"Ottawa",
    "sg:classifiers":[
        {
            "category":"Organizations",
            "subcategory":"Religious Organization",
            "type":"Services"
        }
    ],
    "sg:phone":"+1 613 728 3996",
    "sg:postcode":"K1Y 1H9",
    "sg:province":"ON",
    "sg:tags":[
        "church"
    ],
    "wof:name":"St Matthias' Anglican Church",
    "wof:placetype":"venue"
},
  "geometry": {"coordinates":[-75.7261505127,45.3962059021],"type":"Point"}
}