{
  "type": "Feature",
  "properties": {
    "addr:full":"Banff AB T1L 1B3",
    "addr:postcode":"t1l 1b3",
    "iso:country":"CA",
    "sg:city":"Banff",
    "sg:classifiers":[
        {
            "category":"Recreation",
            "type":"Entertainment"
        }
    ],
    "sg:phone":"+1 403 762 4226",
    "sg:postcode":"T1L 1B3",
    "sg:province":"AB",
    "sg:tags":[
        "tours",
        "sightseeing"
    ],
    "wof:name":"Banff Executive Tours Inc",
    "wof:placetype":"venue"
},
  "geometry": {"coordinates":[-115.570709228,51.1790313721],"type":"Point"}
}