{
  "type": "Feature",
  "properties": {
    "addr:full":"114 Rue DE LA Reine Gaspe QC G4X 1T4",
    "addr:housenumber":"114",
    "addr:postcode":"g4x 1t4",
    "addr:street":"Rue De La Reine Gaspe",
    "iso:country":"CA",
    "sg:address":"114 Rue DE LA Reine",
    "sg:city":"Gaspe",
    "sg:classifiers":[
        {
            "category":"Bars & Pubs",
            "type":"Food & Drink"
        }
    ],
    "sg:phone":"+1 418 368 1219",
    "sg:postcode":"G4X 1T4",
    "sg:province":"QC",
    "sg:tags":[
        "lounge",
        "cocktail"
    ],
    "wof:name":"Bar LA Voute",
    "wof:placetype":"venue"
},
  "geometry": {"coordinates":[-64.484138,48.829559],"type":"Point"}
}