{
  "type": "Feature",
  "properties": {
    "iso:country":"CA",
    "sg:city":"Roslin",
    "sg:classifiers":[
        {
            "category":"Building & Trades",
            "subcategory":"Plumbing",
            "type":"Services"
        }
    ],
    "sg:phone":"+1 613 477 3250",
    "sg:postcode":"K0K 2Y0",
    "sg:province":"ON",
    "sg:tags":[
        "air",
        "conditioning",
        "contractor",
        "system",
        "heating"
    ],
    "wof:name":"Strong Brothers Heating & Air",
    "wof:placetype":"venue"
},
  "geometry": {"coordinates":[-77.37395477290001,44.3657341003],"type":"Point"}
}