{
  "type": "Feature",
  "properties": {
    "addr:full":"360 Rue Duhamel Lasalle QC H8P 3S8",
    "addr:housenumber":"360",
    "addr:postcode":"h8p 3s8",
    "addr:street":"Rue Duhamel",
    "iso:country":"CA",
    "sg:address":"360 Rue Duhamel",
    "sg:city":"Lasalle",
    "sg:classifiers":[
        {
            "category":"Building & Trades",
            "subcategory":"Construction",
            "type":"Services"
        }
    ],
    "sg:phone":"+1 514 366 7839",
    "sg:postcode":"H8P 3S8",
    "sg:province":"QC",
    "sg:tags":[
        "masonry",
        "contractor"
    ],
    "wof:name":"Ddm Construction Inc",
    "wof:placetype":"venue"
},
  "geometry": {"coordinates":[-73.61014556879999,45.4187698364],"type":"Point"}
}