{
  "type": "Feature",
  "properties": {
    "addr:full":"Sault Ste Marie ON P6A 2J8",
    "addr:postcode":"p6a 2j8",
    "iso:country":"CA",
    "sg:city":"Sault Ste Marie",
    "sg:classifiers":[
        {
            "category":"Banks & Credit Unions",
            "subcategory":"Bank",
            "type":"Services"
        }
    ],
    "sg:phone":"+1 705 949 8220",
    "sg:postcode":"P6A 2J8",
    "sg:province":"ON",
    "sg:tags":[
        "loan"
    ],
    "wof:name":"Omaa Development Corp",
    "wof:placetype":"venue"
},
  "geometry": {"coordinates":[-84.3311080933,46.5122451782],"type":"Point"}
}