{
  "type": "Feature",
  "properties": {
    "addr:full":"NE 8-26-28W Roblin MB R0L 1P0",
    "addr:postcode":"r0l 1p0",
    "addr:street":"Ne 8-26-28W",
    "iso:country":"CA",
    "sg:address":"NE 8-26-28W",
    "sg:city":"Roblin",
    "sg:classifiers":[
        {
            "category":"Building & Trades",
            "subcategory":"Construction",
            "type":"Services"
        }
    ],
    "sg:phone":"+1 204 937 4239",
    "sg:postcode":"R0L 1P0",
    "sg:province":"MB",
    "sg:tags":[
        "excavating",
        "handling",
        "contractor",
        "equipment",
        "sand",
        "gravel"
    ],
    "wof:name":"Murray's Hauling",
    "wof:placetype":"venue"
},
  "geometry": {"coordinates":[-101.352851868,51.2281532288],"type":"Point"}
}