{
  "type": "Feature",
  "properties": {
    "addr:full":"Chase BC V0E 1M0",
    "addr:postcode":"v0e 1m0",
    "iso:country":"CA",
    "sg:city":"Chase",
    "sg:classifiers":[
        {
            "category":"Real Estate",
            "subcategory":"Real Estate Operator",
            "type":"Services"
        }
    ],
    "sg:phone":"+1 250 679 8059",
    "sg:postcode":"V0E 1M0",
    "sg:province":"BC",
    "sg:tags":[
        "condominium"
    ],
    "wof:name":"Sun Valley Housing Society",
    "wof:placetype":"venue"
},
  "geometry": {"coordinates":[-119.69177999999999,50.81274],"type":"Point"}
}