{
  "type": "Feature",
  "properties": {
    "addr:full":"4738 Riverside Dr Red Deer AB T4N 2N7",
    "addr:housenumber":"4738",
    "addr:postcode":"t4n 2n7",
    "addr:street":"Riverside Dr",
    "iso:country":"CA",
    "sg:address":"4738 Riverside Dr",
    "sg:city":"Red Deer",
    "sg:classifiers":[
        {
            "category":"Home & Garden",
            "subcategory":"Building Materials",
            "type":"Retail Goods"
        }
    ],
    "sg:phone":"+1 403 341 5600",
    "sg:postcode":"T4N 2N7",
    "sg:province":"AB",
    "sg:tags":[
        "lumber"
    ],
    "wof:name":"Red Deer CO-OP Ltd",
    "wof:placetype":"venue"
},
  "geometry": {"coordinates":[-113.809387,52.279045],"type":"Point"}
}