{
  "type": "Feature",
  "properties": {
    "iso:country":"CA",
    "sg:address":"139 Montee Masson",
    "sg:city":"Mascouche",
    "sg:classifiers":[
        {
            "category":"Shopping",
            "subcategory":"Clothing, Apparel, & Fashions",
            "type":"Retail Goods"
        }
    ],
    "sg:phone":"+1 450 474 1140",
    "sg:postcode":"J7K 3B4",
    "sg:province":"QC",
    "sg:tags":[
        "work"
    ],
    "wof:name":"L'Equipeur",
    "wof:placetype":"venue"
},
  "geometry": {"coordinates":[-73.6189880371,45.7245521545],"type":"Point"}
}