{
  "type": "Feature",
  "properties": {
    "addr:full":"73 Centre St Espanola ON P5E 1S4",
    "addr:housenumber":"73",
    "addr:postcode":"p5e 1s4",
    "addr:street":"Centre St",
    "iso:country":"CA",
    "sg:address":"73 Centre St",
    "sg:city":"Espanola",
    "sg:classifiers":[
        {
            "category":"Health Services",
            "subcategory":"Medical Lab",
            "type":"Services"
        }
    ],
    "sg:phone":"+1 705 869 4544",
    "sg:postcode":"P5E 1S4",
    "sg:province":"ON",
    "wof:name":"Denture Clinic Espanola",
    "wof:placetype":"venue"
},
  "geometry": {"coordinates":[-81.770737,46.265045],"type":"Point"}
}