{
  "type": "Feature",
  "properties": {
    "addr:full":"5384 Kitchener St Niagara Falls ON L2G 1B7",
    "addr:housenumber":"5384",
    "addr:postcode":"l2g 1b7",
    "addr:street":"Kitchener St",
    "iso:country":"CA",
    "sg:address":"5384 Kitchener St",
    "sg:city":"Niagara Falls",
    "sg:classifiers":[
        {
            "category":"Travel",
            "subcategory":"Hotels & Motels",
            "type":"Entertainment"
        }
    ],
    "sg:phone":"+1 905 358 9714",
    "sg:postcode":"L2G 1B7",
    "sg:province":"ON",
    "wof:name":"Waldorf Motel",
    "wof:placetype":"venue"
},
  "geometry": {"coordinates":[-79.08335113530001,43.0952186584],"type":"Point"}
}