{
  "type": "Feature",
  "properties": {
    "addr:full":"640 5 Ave Wainwright AB T9W 1B6",
    "addr:housenumber":"640",
    "addr:postcode":"t9w 1b6",
    "addr:street":"5 Ave",
    "iso:country":"CA",
    "sg:address":"640 5 Ave",
    "sg:city":"Wainwright",
    "sg:classifiers":[
        {
            "category":"Personal",
            "subcategory":"Beauty Salon",
            "type":"Services"
        }
    ],
    "sg:phone":"+1 780 842 4100",
    "sg:postcode":"T9W 1B6",
    "sg:province":"AB",
    "wof:name":"Ron's Clip & Curl Beauty Salon",
    "wof:placetype":"venue"
},
  "geometry": {"coordinates":[-110.865814,52.839249],"type":"Point"}
}