{
  "type": "Feature",
  "properties": {
    "iso:country":"CA",
    "sg:city":"Regina",
    "sg:classifiers":[
        {
            "category":"Organizations",
            "subcategory":"Political Organization",
            "type":"Services"
        }
    ],
    "sg:phone":"+1 306 585 7777",
    "sg:postcode":"S4P 4H8",
    "sg:province":"SK",
    "wof:name":"Tony Merchant Political Office",
    "wof:placetype":"venue"
},
  "geometry": {"coordinates":[-104.615257263,50.451335907],"type":"Point"}
}