{
  "type": "Feature",
  "properties": {
    "addr:full":"Toronto ON M5V 1E7",
    "addr:postcode":"m5v 1e7",
    "iso:country":"CA",
    "sg:city":"Toronto",
    "sg:classifiers":[
        {
            "category":"Recreation",
            "type":"Entertainment"
        }
    ],
    "sg:phone":"+1 416 935 0037",
    "sg:postcode":"M5V 1E7",
    "sg:province":"ON",
    "sg:tags":[
        "company",
        "circus"
    ],
    "wof:name":"Toronto School of Circus Arts",
    "wof:placetype":"venue"
},
  "geometry": {"coordinates":[-79.39576721189999,43.6436042786],"type":"Point"}
}