{
  "type": "Feature",
  "properties": {
    "iso:country":"CA",
    "sg:address":"90 Advance Rd",
    "sg:city":"Etobicoke",
    "sg:classifiers":[
        {
            "category":"Professional",
            "type":"Services"
        }
    ],
    "sg:phone":"+1 416 246 0037",
    "sg:postcode":"M8Z 2T7",
    "sg:province":"ON",
    "sg:tags":[
        "establishment",
        "heating",
        "contractor"
    ],
    "wof:name":"Commercial Equipment Svc CO",
    "wof:placetype":"venue"
},
  "geometry": {"coordinates":[-79.5249862671,43.6348266602],"type":"Point"}
}