{
  "type": "Feature",
  "properties": {
    "addr:full":"1391 Johnston Rd White Rock BC V4B 3Z3",
    "addr:housenumber":"1391",
    "addr:postcode":"v4b 3z3",
    "addr:street":"Johnston Rd",
    "iso:country":"CA",
    "sg:address":"1391 Johnston Rd",
    "sg:city":"White Rock",
    "sg:classifiers":[
        {
            "category":"Home & Garden",
            "subcategory":"Home Furnishings",
            "type":"Retail Goods"
        }
    ],
    "sg:phone":"+1 604 541 3112",
    "sg:postcode":"V4B 3Z3",
    "sg:province":"BC",
    "sg:tags":[
        "equipment",
        "fireplace"
    ],
    "wof:name":"Cascade Fireplaces Inc",
    "wof:placetype":"venue"
},
  "geometry": {"coordinates":[-122.801361,49.027187],"type":"Point"}
}