{
  "type": "Feature",
  "properties": {
    "addr:full":"1600 Bayly St Pickering ON L1W 3N2",
    "addr:housenumber":"1600",
    "addr:postcode":"l1w 3n2",
    "addr:street":"Bayly St",
    "iso:country":"CA",
    "sg:address":"1600 Bayly St",
    "sg:city":"Pickering",
    "sg:classifiers":[
        {
            "category":"Retail",
            "subcategory":"Auto Rental",
            "type":"Services"
        }
    ],
    "sg:phone":"+1 416 698 7538",
    "sg:postcode":"L1W 3N2",
    "sg:province":"ON",
    "sg:tags":[
        "renting",
        "automobile",
        "leasing"
    ],
    "wof:name":"Clark Leasing",
    "wof:placetype":"venue"
},
  "geometry": {"coordinates":[-79.0724639893,43.8321151733],"type":"Point"}
}