{
  "type": "Feature",
  "properties": {
    "iso:country":"CA",
    "sg:address":"8048 Boul Saint-Michel",
    "sg:city":"Montreal",
    "sg:classifiers":[
        {
            "category":"Shopping",
            "subcategory":"Pharmacy",
            "type":"Retail Goods"
        }
    ],
    "sg:phone":"+1 514 725 7874",
    "sg:postcode":"H1Z 3E1",
    "sg:province":"QC",
    "wof:name":"Pharmacie N Le Dinh",
    "wof:placetype":"venue"
},
  "geometry": {"coordinates":[-73.60894,45.563301],"type":"Point"}
}