{
  "type": "Feature",
  "properties": {
    "addr:full":"1643 Venables St Vancouver BC V5L 2H1",
    "addr:housenumber":"1643",
    "addr:postcode":"v5l 2h1",
    "addr:street":"Venables St",
    "iso:country":"CA",
    "sg:address":"1643 Venables St",
    "sg:city":"Vancouver",
    "sg:classifiers":[
        {
            "category":"Professional",
            "subcategory":"Research",
            "type":"Services"
        }
    ],
    "sg:phone":"+1 604 253 5264",
    "sg:postcode":"V5L 2H1",
    "sg:province":"BC",
    "sg:tags":[
        "environmental",
        "ecological"
    ],
    "wof:name":"Nova Pacific Environmental",
    "wof:placetype":"venue"
},
  "geometry": {"coordinates":[-123.071861267,49.2768592834],"type":"Point"}
}