{
  "type": "Feature",
  "properties": {
    "addr:full":"Burnaby BC V5H 1Z5",
    "addr:postcode":"v5h 1z5",
    "iso:country":"CA",
    "sg:city":"Burnaby",
    "sg:classifiers":[
        {
            "category":"Banks & Credit Unions",
            "subcategory":"Bank",
            "type":"Services"
        }
    ],
    "sg:phone":"+1 604 668 3741",
    "sg:postcode":"V5H 1Z5",
    "sg:province":"BC",
    "wof:name":"Scotiabank",
    "wof:placetype":"venue"
},
  "geometry": {"coordinates":[-123.008698,49.231621],"type":"Point"}
}