{
  "type": "Feature",
  "properties": {
    "addr:full":"3044 Bloor St W Etobicoke ON M8X 1C4",
    "addr:housenumber":"3044",
    "addr:postcode":"m8x 1c4",
    "addr:street":"Bloor St W",
    "iso:country":"CA",
    "sg:address":"3044 Bloor St W",
    "sg:city":"Etobicoke",
    "sg:classifiers":[
        {
            "category":"Professional",
            "subcategory":"Detective & Security Services",
            "type":"Services"
        }
    ],
    "sg:phone":"+1 416 231 8247",
    "sg:postcode":"M8X 1C4",
    "sg:province":"ON",
    "sg:tags":[
        "guard",
        "patrol"
    ],
    "wof:name":"Authorized Parking Only Ltd",
    "wof:placetype":"venue"
},
  "geometry": {"coordinates":[-79.51269499999999,43.647194],"type":"Point"}
}