{
  "type": "Feature",
  "properties": {
    "addr:full":"6203 28 Ave NW Edmonton AB T6L 6K3",
    "addr:housenumber":"6203",
    "addr:postcode":"t6l 6k3",
    "addr:street":"28 Ave Nw",
    "iso:country":"CA",
    "sg:address":"6203 28 Ave NW",
    "sg:city":"Edmonton",
    "sg:classifiers":[
        {
            "category":"Health Services",
            "subcategory":"Doctor",
            "type":"Services"
        }
    ],
    "sg:phone":"+1 780 462 9306",
    "sg:postcode":"T6L 6K3",
    "sg:province":"AB",
    "sg:tags":[
        "physician",
        "surgeon"
    ],
    "wof:name":"Mediclinic",
    "wof:placetype":"venue"
},
  "geometry": {"coordinates":[-113.428718567,53.4585838318],"type":"Point"}
}