{
  "type": "Feature",
  "properties": {
    "addr:full":"Vancouver BC V6B 5T2",
    "addr:postcode":"v6b 5t2",
    "iso:country":"CA",
    "sg:city":"Vancouver",
    "sg:classifiers":[
        {
            "category":"Professional",
            "subcategory":"Lawyer & Legal Services",
            "type":"Services"
        }
    ],
    "sg:phone":"+1 604 669 3544",
    "sg:postcode":"V6B 5T2",
    "sg:province":"BC",
    "sg:tags":[
        "attorney",
        "bureau"
    ],
    "wof:name":"Continuing Legal Education",
    "wof:placetype":"venue"
},
  "geometry": {"coordinates":[-123.115821838,49.2778053284],"type":"Point"}
}