{
  "type": "Feature",
  "properties": {
    "addr:full":"3082 Av Francis-Hughes Laval QC H7L 5A7",
    "addr:housenumber":"3082",
    "addr:postcode":"h7l 5a7",
    "addr:street":"Av Francis-Hughes",
    "iso:country":"CA",
    "sg:address":"3082 Av Francis-Hughes",
    "sg:city":"Laval",
    "sg:classifiers":[
        {
            "category":"Wholesale",
            "subcategory":"Hardware",
            "type":"Manufacturing & Wholesale Goods"
        }
    ],
    "sg:phone":"+1 450 663 8370",
    "sg:postcode":"H7L 5A7",
    "sg:province":"QC",
    "sg:tags":[
        "ventilating",
        "equipment"
    ],
    "wof:name":"Ventimetal Limitee",
    "wof:placetype":"venue"
},
  "geometry": {"coordinates":[-73.7367477417,45.5922584534],"type":"Point"}
}