{
  "type": "Feature",
  "properties": {
    "addr:full":"5555 Boul Des Laurentides Laval QC H7K 2K4",
    "addr:housenumber":"5555",
    "addr:postcode":"qc h7k 2k4",
    "addr:street":"Boul Des Laurentides",
    "iso:country":"CA",
    "sg:address":"5555 Boul Des Laurentides",
    "sg:city":"Laval",
    "sg:classifiers":[
        {
            "category":"Wholesale",
            "subcategory":"Non-durable Goods",
            "type":"Manufacturing & Wholesale Goods"
        }
    ],
    "sg:phone":"+1 450 963 2121",
    "sg:postcode":"H7K 2K4",
    "sg:province":"QC",
    "sg:tags":[
        "water"
    ],
    "wof:name":"Vaporel",
    "wof:placetype":"venue"
},
  "geometry": {"coordinates":[-73.751266,45.626568],"type":"Point"}
}