{
  "type": "Feature",
  "properties": {
    "addr:full":"Hwy 11 N Gravenhurst ON P1P 1R1",
    "addr:postcode":"p1p 1r1",
    "addr:street":"Hwy 11 N",
    "iso:country":"CA",
    "sg:address":"Hwy 11 N",
    "sg:city":"Gravenhurst",
    "sg:classifiers":[
        {
            "category":"Restaurant",
            "type":"Food & Drink"
        }
    ],
    "sg:phone":"+1 705 687 3150",
    "sg:postcode":"P1P 1R1",
    "sg:province":"ON",
    "wof:name":"Granite Restaurant",
    "wof:placetype":"venue"
},
  "geometry": {"coordinates":[-79.3573,44.89257],"type":"Point"}
}