{
  "type": "Feature",
  "properties": {
    "addr:full":"1189 Lawrence Ave W North York ON M6A 1E2",
    "addr:housenumber":"1189",
    "addr:postcode":"m6a 1e2",
    "addr:street":"Lawrence Ave W",
    "iso:country":"CA",
    "sg:address":"1189 Lawrence Ave W",
    "sg:city":"North York",
    "sg:classifiers":[
        {
            "category":"Home & Garden",
            "subcategory":"Building Materials",
            "type":"Retail Goods"
        }
    ],
    "sg:phone":"+1 416 785 1676",
    "sg:postcode":"M6A 1E2",
    "sg:province":"ON",
    "sg:tags":[
        "glass",
        "window",
        "plate"
    ],
    "wof:name":"Belmont Glass Mirror & Alum",
    "wof:placetype":"venue"
},
  "geometry": {"coordinates":[-79.4673461914,43.7111701965],"type":"Point"}
}