{
  "type": "Feature",
  "properties": {
    "addr:full":"28 Murphy Sq Corner Brook NL A2H 1R4",
    "addr:housenumber":"28",
    "addr:postcode":"a2h 1r4",
    "addr:street":"Murphy Sq",
    "iso:country":"CA",
    "sg:address":"28 Murphy Sq",
    "sg:city":"Corner Brook",
    "sg:classifiers":[
        {
            "category":"Food & Beverages",
            "subcategory":"Bakery",
            "type":"Retail Goods"
        }
    ],
    "sg:phone":"+1 709 634 8115",
    "sg:postcode":"A2H 1R4",
    "sg:province":"NL",
    "sg:tags":[
        "tea",
        "coffee",
        "doughnut"
    ],
    "wof:name":"Tim Hortons",
    "wof:placetype":"venue"
},
  "geometry": {"coordinates":[-57.94947052,48.9501991272],"type":"Point"}
}