{
  "type": "Feature",
  "properties": {
    "iso:country":"CA",
    "sg:address":"12 Main St",
    "sg:city":"Shellbrook",
    "sg:classifiers":[
        {
            "category":"Restaurant",
            "type":"Food & Drink"
        }
    ],
    "sg:phone":"+1 306 747 3633",
    "sg:postcode":"S0J 2E0",
    "sg:province":"SK",
    "wof:name":"Between Friends Family Rstrnt",
    "wof:placetype":"venue"
},
  "geometry": {"coordinates":[-106.38822937,53.2190475464],"type":"Point"}
}