{
  "type": "Feature",
  "properties": {
    "addr:full":"1340 Boul Shevchenko Lasalle QC H8N 1P1",
    "addr:housenumber":"1340",
    "addr:postcode":"h8n 1p1",
    "addr:street":"Boul Shevchenko",
    "iso:country":"CA",
    "sg:address":"1340 Boul Shevchenko",
    "sg:city":"Lasalle",
    "sg:classifiers":[
        {
            "category":"Retail",
            "subcategory":"Auto Repair",
            "type":"Services"
        }
    ],
    "sg:phone":"+1 514 363 2840",
    "sg:postcode":"H8N 1P1",
    "sg:province":"QC",
    "sg:tags":[
        "repairing",
        "automobile"
    ],
    "wof:name":"Pompeo Pneus & Mecanique Inc",
    "wof:placetype":"venue"
},
  "geometry": {"coordinates":[-73.620018,45.430962],"type":"Point"}
}