{
  "type": "Feature",
  "properties": {
    "iso:country":"CA",
    "sg:city":"Anahim Lake",
    "sg:classifiers":[
        {
            "category":"Education",
            "subcategory":"School",
            "type":"Public Place"
        }
    ],
    "sg:phone":"+1 250 742 3235",
    "sg:postcode":"V0L 1C0",
    "sg:province":"BC",
    "wof:name":"Anahim Lake School",
    "wof:placetype":"venue"
},
  "geometry": {"coordinates":[-125.306930542,52.4617042542],"type":"Point"}
}