{
  "type": "Feature",
  "properties": {
    "addr:full":"5556 LA Grande-Allee Saint-Hubert QC J3Y 1A8",
    "addr:housenumber":"5556",
    "addr:postcode":"j3y 1a8",
    "addr:street":"La Grande-Allee",
    "iso:country":"CA",
    "sg:address":"5556 LA Grande-Allee",
    "sg:city":"Saint-Hubert",
    "sg:classifiers":[
        {
            "category":"Recreation",
            "type":"Entertainment"
        }
    ],
    "sg:phone":"+1 450 445 7141",
    "sg:postcode":"J3Y 1A8",
    "sg:province":"QC",
    "sg:tags":[
        "auditorium",
        "rooms",
        "banquet",
        "hall"
    ],
    "wof:name":"Salle DE Reception LA Ka-Danse",
    "wof:placetype":"venue"
},
  "geometry": {"coordinates":[-73.444405,45.475796],"type":"Point"}
}