{
  "type": "Feature",
  "properties": {
    "addr:full":"234 Rue Des Pionniers Sept-Iles QC G4R 4K2",
    "addr:housenumber":"234",
    "addr:postcode":"g4r 4k2",
    "addr:street":"Rue Des Pionniers Sept-Iles",
    "iso:country":"CA",
    "sg:address":"234 Rue Des Pionniers",
    "sg:city":"Sept-Iles",
    "sg:classifiers":[
        {
            "category":"Wholesale",
            "subcategory":"Metals & Minerals",
            "type":"Manufacturing & Wholesale Goods"
        }
    ],
    "sg:phone":"+1 418 962 7744",
    "sg:postcode":"G4R 4K2",
    "sg:province":"QC",
    "sg:tags":[
        "steel",
        "warehouse"
    ],
    "wof:name":"Acier Du Nord Ltee-Norsteel",
    "wof:placetype":"venue"
},
  "geometry": {"coordinates":[-66.30645,50.207584],"type":"Point"}
}