{
  "type": "Feature",
  "properties": {
    "iso:country":"CA",
    "sg:address":"1126 Rue Saint-Cyrille",
    "sg:city":"Thetford Mines",
    "sg:classifiers":[
        {
            "category":"Organizations",
            "subcategory":"Labor Organization",
            "type":"Services"
        }
    ],
    "sg:phone":"+1 418 335 7593",
    "sg:postcode":"G6G 7K5",
    "sg:province":"QC",
    "wof:name":"Syndicat L'Amiante",
    "wof:placetype":"venue"
},
  "geometry": {"coordinates":[-71.3150939941,46.1028785706],"type":"Point"}
}