{
  "type": "Feature",
  "properties": {
    "addr:full":"1105 111th Ave Tisdale SK S0E 1T0",
    "addr:housenumber":"1105",
    "addr:postcode":"s0e 1t0",
    "addr:street":"111Th Ave",
    "iso:country":"CA",
    "sg:address":"1105 111th Ave",
    "sg:city":"Tisdale",
    "sg:classifiers":[
        {
            "category":"Building & Trades",
            "subcategory":"Plumbing",
            "type":"Services"
        }
    ],
    "sg:phone":"+1 306 873 2967",
    "sg:postcode":"S0E 1T0",
    "sg:province":"SK",
    "sg:tags":[
        "heating",
        "contractor"
    ],
    "wof:name":"Gary's Plumbing & Heating Ltd",
    "wof:placetype":"venue"
},
  "geometry": {"coordinates":[-104.05291748,52.8418045044],"type":"Point"}
}