{
  "type": "Feature",
  "properties": {
    "addr:full":"98 Island Rd Scarborough ON M1C 2P5",
    "addr:housenumber":"98",
    "addr:postcode":"m1c 2p5",
    "addr:street":"Island Rd",
    "iso:country":"CA",
    "sg:address":"98 Island Rd",
    "sg:city":"Scarborough",
    "sg:classifiers":[
        {
            "category":"Retail",
            "subcategory":"Auto Repair",
            "type":"Services"
        }
    ],
    "sg:phone":"+1 416 284 9918",
    "sg:postcode":"M1C 2P5",
    "sg:province":"ON",
    "sg:tags":[
        "repairing",
        "automobile"
    ],
    "wof:name":"Total Auto Svc",
    "wof:placetype":"venue"
},
  "geometry": {"coordinates":[-79.139267,43.798134],"type":"Point"}
}