{
  "type": "Feature",
  "properties": {
    "addr:full":"1654 St Clair Ave W Toronto ON M6N 1H8",
    "addr:housenumber":"1654",
    "addr:postcode":"m6n 1h8",
    "addr:street":"St Clair Ave W",
    "iso:country":"CA",
    "sg:address":"1654 St Clair Ave W",
    "sg:city":"Toronto",
    "sg:classifiers":[
        {
            "category":"Wholesale",
            "subcategory":"Meat",
            "type":"Manufacturing & Wholesale Goods"
        }
    ],
    "sg:phone":"+1 416 656 7045",
    "sg:postcode":"M6N 1H8",
    "sg:province":"ON",
    "sg:tags":[
        "butchering"
    ],
    "wof:name":"Macelleria Del Baby Beef",
    "wof:placetype":"venue"
},
  "geometry": {"coordinates":[-79.45755,43.674854],"type":"Point"}
}