{
  "type": "Feature",
  "properties": {
    "addr:full":"2780 Skymark Ave Mississauga ON L4W 5A7",
    "addr:housenumber":"2780",
    "addr:postcode":"l4w 5a7",
    "addr:street":"Skymark Ave",
    "iso:country":"CA",
    "sg:address":"2780 Skymark Ave",
    "sg:city":"Mississauga",
    "sg:classifiers":[
        {
            "category":"Wholesale",
            "subcategory":"Sporting Goods",
            "type":"Manufacturing & Wholesale Goods"
        }
    ],
    "sg:phone":"+1 905 602 9988",
    "sg:postcode":"L4W 5A7",
    "sg:province":"ON",
    "wof:name":"Ryeka Sport",
    "wof:placetype":"venue"
},
  "geometry": {"coordinates":[-79.59446,43.662048],"type":"Point"}
}