{
  "type": "Feature",
  "properties": {
    "addr:full":"29170 Fraser Hwy Abbotsford BC V4X 1G8",
    "addr:housenumber":"29170",
    "addr:postcode":"v4x 1g8",
    "addr:street":"Fraser Hwy",
    "iso:country":"CA",
    "sg:address":"29170 Fraser Hwy",
    "sg:city":"Abbotsford",
    "sg:classifiers":[
        {
            "category":"Wholesale",
            "subcategory":"Machinery & Supplies",
            "type":"Manufacturing & Wholesale Goods"
        }
    ],
    "sg:phone":"+1 604 856 3490",
    "sg:postcode":"V4X 1G8",
    "sg:province":"BC",
    "wof:name":"Redel Holdings Ltd",
    "wof:placetype":"venue"
},
  "geometry": {"coordinates":[-122.415558,49.057144],"type":"Point"}
}