{
  "type": "Feature",
  "properties": {
    "addr:full":"107 Avenue Rd Cambridge ON N1R 1C2",
    "addr:housenumber":"107",
    "addr:postcode":"n1r 1c2",
    "addr:street":"Avenue Rd",
    "iso:country":"CA",
    "sg:address":"107 Avenue Rd",
    "sg:city":"Cambridge",
    "sg:classifiers":[
        {
            "category":"Autos & Motor Vehicles",
            "subcategory":"Automobile Sales",
            "type":"Retail Goods"
        }
    ],
    "sg:phone":"+1 519 622 3030",
    "sg:postcode":"N1R 1C2",
    "sg:province":"ON",
    "sg:tags":[
        "car",
        "dealer"
    ],
    "wof:name":"Cambridge Auto Sales & Leasing",
    "wof:placetype":"venue"
},
  "geometry": {"coordinates":[-80.30986799999999,43.378712],"type":"Point"}
}