{
  "type": "Feature",
  "properties": {
    "addr:full":"6817 Headquarters Rd Courtenay BC V9J 1N2",
    "addr:housenumber":"6817",
    "addr:postcode":"v9j 1n2",
    "addr:street":"Headquarters Rd",
    "iso:country":"CA",
    "sg:address":"6817 Headquarters Rd",
    "sg:city":"Courtenay",
    "sg:classifiers":[
        {
            "category":"Organizations",
            "subcategory":"Community Association",
            "type":"Services"
        }
    ],
    "sg:phone":"+1 250 337 2021",
    "sg:postcode":"V9J 1N2",
    "sg:province":"BC",
    "sg:tags":[
        "environmental",
        "org",
        "internet"
    ],
    "wof:name":"Mountainaire Avian Rescue Soc",
    "wof:placetype":"venue"
},
  "geometry": {"coordinates":[-124.99375915500001,49.7025718689],"type":"Point"}
}