{
  "type": "Feature",
  "properties": {
    "iso:country":"CA",
    "sg:address":"1041 Boul Talbot",
    "sg:city":"Chicoutimi",
    "sg:classifiers":[
        {
            "category":"Shopping",
            "subcategory":"Clothing, Apparel, & Fashions",
            "type":"Retail Goods"
        }
    ],
    "sg:phone":"+1 418 545 2843",
    "sg:postcode":"G7H 4B5",
    "sg:province":"QC",
    "sg:tags":[
        "sportswear"
    ],
    "wof:name":"Boutique Ouragan Inc",
    "wof:placetype":"venue"
},
  "geometry": {"coordinates":[-71.051612854,48.4112548828],"type":"Point"}
}