{
  "type": "Feature",
  "properties": {
    "iso:country":"CA",
    "sg:address":"1470 Clark Ave",
    "sg:city":"Penticton",
    "sg:classifiers":[
        {
            "category":"Building & Trades",
            "subcategory":"Construction",
            "type":"Services"
        }
    ],
    "sg:phone":"+1 250 492 1002",
    "sg:postcode":"V2A 7B4",
    "sg:province":"BC",
    "sg:tags":[
        "hardwood",
        "resurfacing",
        "laying",
        "refinishing",
        "floor"
    ],
    "wof:name":"Signature Wood Flooring Inc",
    "wof:placetype":"venue"
},
  "geometry": {"coordinates":[-119.56056213399999,49.4815673828],"type":"Point"}
}