{
  "type": "Feature",
  "properties": {
    "iso:country":"CA",
    "sg:address":"1134 Av Saint-Antoine",
    "sg:city":"Vaudreuil-Dorion",
    "sg:classifiers":[
        {
            "category":"Recreation",
            "type":"Entertainment"
        }
    ],
    "sg:phone":"+1 450 455 0288",
    "sg:postcode":"J7V 8P2",
    "sg:province":"QC",
    "sg:tags":[
        "range",
        "practice",
        "golf"
    ],
    "wof:name":"Champ DE Pratique DE Golf",
    "wof:placetype":"venue"
},
  "geometry": {"coordinates":[-74.0274963379,45.3488845825],"type":"Point"}
}