{
  "type": "Feature",
  "properties": {
    "addr:full":"3511 Witt Pl Peachland BC V0H 1X2",
    "addr:housenumber":"3511",
    "addr:postcode":"v0h 1x2",
    "addr:street":"Witt Pl",
    "iso:country":"CA",
    "sg:address":"3511 Witt Pl",
    "sg:city":"Peachland",
    "sg:classifiers":[
        {
            "category":"Real Estate",
            "subcategory":"Architect",
            "type":"Services"
        }
    ],
    "sg:phone":"+1 250 767 3345",
    "sg:postcode":"V0H 1X2",
    "sg:province":"BC",
    "sg:tags":[
        "home",
        "specification",
        "planning",
        "architectural"
    ],
    "wof:name":"Innovative Home Design",
    "wof:placetype":"venue"
},
  "geometry": {"coordinates":[-119.71376800500001,49.7886924744],"type":"Point"}
}