{
  "type": "Feature",
  "properties": {
    "addr:full":"1055 116E Rue Saint-Georges QC G5Y 3G1",
    "addr:housenumber":"1055",
    "addr:postcode":"g5y 3g1",
    "addr:street":"116E Rue",
    "iso:country":"CA",
    "sg:address":"1055 116E Rue",
    "sg:city":"Saint-Georges",
    "sg:classifiers":[
        {
            "category":"Education",
            "subcategory":"College",
            "type":"Public Place"
        }
    ],
    "sg:phone":"+1 418 228 8896",
    "sg:postcode":"G5Y 3G1",
    "sg:province":"QC",
    "sg:tags":[
        "academic",
        "school"
    ],
    "wof:name":"Cegep Beauce-Appalaches",
    "wof:placetype":"venue"
},
  "geometry": {"coordinates":[-70.6694717407,46.1257400513],"type":"Point"}
}