{
  "type": "Feature",
  "properties": {
    "addr:full":"1234 Boul Wallberg Dolbeau-Mistassini QC G8L 1H1",
    "addr:housenumber":"1234",
    "addr:postcode":"g8l 1h1",
    "addr:street":"Boul Wallberg",
    "iso:country":"CA",
    "sg:address":"1234 Boul Wallberg",
    "sg:city":"Dolbeau-Mistassini",
    "sg:classifiers":[
        {
            "category":"Shopping",
            "subcategory":"Clothing, Apparel, & Fashions",
            "type":"Retail Goods"
        }
    ],
    "sg:phone":"+1 418 276 8615",
    "sg:postcode":"G8L 1H1",
    "sg:province":"QC",
    "sg:tags":[
        "boutique",
        "lingerie"
    ],
    "wof:name":"Boutique Valentine Enr",
    "wof:placetype":"venue"
},
  "geometry": {"coordinates":[-72.2275009155,48.8774681091],"type":"Point"}
}