{
  "type": "Feature",
  "properties": {
    "addr:full":"Ottawa ON K1S 2E1",
    "addr:postcode":"k1s 2e1",
    "iso:country":"CA",
    "sg:city":"Ottawa",
    "sg:classifiers":[
        {
            "category":"Shopping",
            "subcategory":"Computers & Home Electronics",
            "type":"Retail Goods"
        }
    ],
    "sg:phone":"+1 613 234 6512",
    "sg:postcode":"K1S 2E1",
    "sg:province":"ON",
    "sg:tags":[
        "equipment",
        "dealer"
    ],
    "wof:name":"Shoshin Systems Inc",
    "wof:placetype":"venue"
},
  "geometry": {"coordinates":[-75.7009506226,45.4007949829],"type":"Point"}
}