{
  "type": "Feature",
  "properties": {
    "iso:country":"CA",
    "sg:address":"5701 Av DE Monkland",
    "sg:city":"Montreal",
    "sg:classifiers":[
        {
            "category":"Banks & Credit Unions",
            "subcategory":"Bank",
            "type":"Services"
        }
    ],
    "sg:phone":"+1 514 874 3433",
    "sg:postcode":"H4A 1E7",
    "sg:province":"QC",
    "wof:name":"Banque Royale",
    "wof:placetype":"venue"
},
  "geometry": {"coordinates":[-73.623962,45.474457],"type":"Point"}
}