{
  "type": "Feature",
  "properties": {
    "addr:full":"5701 Av DE Monkland Montreal QC H4A 1E7",
    "addr:housenumber":"5701",
    "addr:postcode":"h4a 1e7",
    "addr:street":"Av De Monkland",
    "iso:country":"CA",
    "sg:address":"5701 Av DE Monkland",
    "sg:city":"Montreal",
    "sg:classifiers":[
        {
            "category":"Banks & Credit Unions",
            "subcategory":"Bank",
            "type":"Services"
        }
    ],
    "sg:phone":"+1 514 874 3433",
    "sg:postcode":"H4A 1E7",
    "sg:province":"QC",
    "wof:name":"Banque Royale",
    "wof:placetype":"venue"
},
  "geometry": {"coordinates":[-73.62396200000001,45.474457],"type":"Point"}
}