{
  "type": "Feature",
  "properties": {
    "iso:country":"CA",
    "sg:city":"Toronto",
    "sg:classifiers":[
        {
            "category":"Professional",
            "subcategory":"Management & Consulting",
            "type":"Services"
        }
    ],
    "sg:phone":"+1 416 424 2999",
    "sg:postcode":"M5A 3X9",
    "sg:province":"ON",
    "sg:tags":[
        "training",
        "sales"
    ],
    "wof:name":"Fusion Learning",
    "wof:placetype":"venue"
},
  "geometry": {"coordinates":[-79.3683013916,43.6523513794],"type":"Point"}
}