{
  "type": "Feature",
  "properties": {
    "addr:full":"10512 Islington Ave Kleinburg ON L0J 1C0",
    "addr:housenumber":"10512",
    "addr:postcode":"l0j 1c0",
    "addr:street":"Islington Ave",
    "iso:country":"CA",
    "sg:address":"10512 Islington Ave",
    "sg:city":"Kleinburg",
    "sg:classifiers":[
        {
            "category":"Restaurant",
            "type":"Food & Drink"
        }
    ],
    "sg:phone":"+1 905 224 6031",
    "sg:postcode":"L0J 1C0",
    "sg:province":"ON",
    "wof:name":"Chartreuse Restaurant",
    "wof:placetype":"venue"
},
  "geometry": {"coordinates":[-79.62847137449999,43.8439445496],"type":"Point"}
}