{
  "type": "Feature",
  "properties": {
    "addr:full":"Courtenay BC V9N 3P8",
    "addr:postcode":"v9n 3p8",
    "iso:country":"CA",
    "sg:city":"Courtenay",
    "sg:classifiers":[
        {
            "category":"Recreation",
            "subcategory":"Marina",
            "type":"Entertainment"
        }
    ],
    "sg:phone":"+1 250 339 4422",
    "sg:postcode":"V9N 3P8",
    "sg:province":"BC",
    "sg:tags":[
        "repair",
        "marine",
        "dealer",
        "boat",
        "sales"
    ],
    "wof:name":"A & E Marine Ltd",
    "wof:placetype":"venue"
},
  "geometry": {"coordinates":[-124.98818199999999,49.686562],"type":"Point"}
}