{
  "type": "Feature",
  "properties": {
    "addr:full":"5 Rue Arnault Notre-Dame-Des-Prairies QC J6E 6W1",
    "addr:housenumber":"5",
    "addr:postcode":"j6e 6w1",
    "addr:street":"Rue Arnault",
    "iso:country":"CA",
    "sg:address":"5 Rue Arnault",
    "sg:city":"Notre-Dame-Des-Prairies",
    "sg:classifiers":[
        {
            "category":"Personal",
            "subcategory":"Beauty Salon",
            "type":"Services"
        }
    ],
    "sg:phone":"+1 450 756 6416",
    "sg:postcode":"J6E 6W1",
    "sg:province":"QC",
    "wof:name":"Salon DE Coiffure L'Unique Enr",
    "wof:placetype":"venue"
},
  "geometry": {"coordinates":[-73.42530059809999,46.0411567688],"type":"Point"}
}