{
  "type": "Feature",
  "properties": {
    "addr:full":"316 1st Ave E Nipawin SK S0E 1E0",
    "addr:housenumber":"316",
    "addr:postcode":"s0e 1e0",
    "addr:street":"1St Ave E Nipawin",
    "iso:country":"CA",
    "sg:address":"316 1st Ave E",
    "sg:city":"Nipawin",
    "sg:classifiers":[
        {
            "category":"Home & Garden",
            "subcategory":"Building Materials",
            "type":"Retail Goods"
        }
    ],
    "sg:phone":"+1 306 862 5838",
    "sg:postcode":"S0E 1E0",
    "sg:province":"SK",
    "sg:tags":[
        "glass",
        "window",
        "plate"
    ],
    "wof:name":"Paul's Custom Glass",
    "wof:placetype":"venue"
},
  "geometry": {"coordinates":[-104.01399231000001,53.3639678955],"type":"Point"}
}