{
  "type": "Feature",
  "properties": {
    "addr:full":"725 Highway 16 Burns Lake BC V0J 1E0",
    "addr:housenumber":"725",
    "addr:postcode":"v0j 1e0",
    "addr:street":"Highway 16 Burns",
    "iso:country":"CA",
    "sg:address":"725 Highway 16",
    "sg:city":"Burns Lake",
    "sg:classifiers":[
        {
            "category":"Retail",
            "subcategory":"Car Wash",
            "type":"Services"
        }
    ],
    "sg:phone":"+1 250 692 9121",
    "sg:postcode":"V0J 1E0",
    "sg:province":"BC",
    "sg:tags":[
        "polishing",
        "washing"
    ],
    "wof:name":"Twisters Car & Truck Wash",
    "wof:placetype":"venue"
},
  "geometry": {"coordinates":[-125.758537,54.2267],"type":"Point"}
}