{
  "type": "Feature",
  "properties": {
    "addr:full":"10 Dolman St Breslau ON N0B 1M0",
    "addr:housenumber":"10",
    "addr:postcode":"n0b 1m0",
    "addr:street":"Dolman St",
    "iso:country":"CA",
    "sg:address":"10 Dolman St",
    "sg:city":"Breslau",
    "sg:classifiers":[
        {
            "category":"Government",
            "subcategory":"Post Office",
            "type":"Public Place"
        }
    ],
    "sg:phone":"+1 519 648 2580",
    "sg:postcode":"N0B 1M0",
    "sg:province":"ON",
    "wof:name":"Breslau Express",
    "wof:placetype":"venue"
},
  "geometry": {"coordinates":[-80.415359,43.478535],"type":"Point"}
}