{
  "type": "Feature",
  "properties": {
    "addr:full":"1 Thirtieth St Etobicoke ON M8W 3B5",
    "addr:housenumber":"1",
    "addr:postcode":"m8w 3b5",
    "addr:street":"Thirtieth St",
    "iso:country":"CA",
    "sg:address":"1 Thirtieth St",
    "sg:city":"Etobicoke",
    "sg:classifiers":[
        {
            "category":"Building & Trades",
            "subcategory":"Plumbing",
            "type":"Services"
        }
    ],
    "sg:phone":"+1 416 251 4470",
    "sg:postcode":"M8W 3B5",
    "sg:province":"ON",
    "sg:tags":[
        "waterproofing",
        "contractor"
    ],
    "wof:name":"Denver Drain Svc Ltd",
    "wof:placetype":"venue"
},
  "geometry": {"coordinates":[-79.5296707153,43.5955543518],"type":"Point"}
}