{
  "type": "Feature",
  "properties": {
    "addr:full":"143 Rue Principale Aylmer QC J9H 3M6",
    "addr:housenumber":"143",
    "addr:postcode":"j9h 3m6",
    "addr:street":"Rue Principale",
    "iso:country":"CA",
    "sg:address":"143 Rue Principale",
    "sg:city":"Aylmer",
    "sg:classifiers":[
        {
            "category":"Retail",
            "subcategory":"Auto Repair",
            "type":"Services"
        }
    ],
    "sg:phone":"+1 819 682 4807",
    "sg:postcode":"J9H 3M6",
    "sg:province":"QC",
    "sg:tags":[
        "repairing",
        "automobile"
    ],
    "wof:name":"Garage Hugo Caumartin",
    "wof:placetype":"venue"
},
  "geometry": {"coordinates":[-75.841888,45.395199],"type":"Point"}
}