{
  "type": "Feature",
  "properties": {
    "addr:full":"Montreal QC H1N 1E9",
    "addr:postcode":"h1n 1e9",
    "iso:country":"CA",
    "sg:city":"Montreal",
    "sg:classifiers":[
        {
            "category":"Wholesale",
            "subcategory":"Drugs",
            "type":"Manufacturing & Wholesale Goods"
        }
    ],
    "sg:phone":"+1 514 354 9588",
    "sg:postcode":"H1N 1E9",
    "sg:province":"QC",
    "sg:tags":[
        "preparation",
        "toilet"
    ],
    "wof:name":"Clair DE Lune",
    "wof:placetype":"venue"
},
  "geometry": {"coordinates":[-73.53909299999999,45.590172],"type":"Point"}
}