{
  "type": "Feature",
  "properties": {
    "iso:country":"CA",
    "sg:address":"337 Rue Moreault",
    "sg:city":"Rimouski",
    "sg:classifiers":[
        {
            "category":"Government",
            "subcategory":"Office",
            "type":"Public Place"
        }
    ],
    "sg:phone":"+1 418 727 3566",
    "sg:postcode":"G5L 1P4",
    "sg:province":"QC",
    "wof:name":"Quebec Affaires Regionales",
    "wof:placetype":"venue"
},
  "geometry": {"coordinates":[-68.51654052729999,48.4620323181],"type":"Point"}
}