{
  "type": "Feature",
  "properties": {
    "iso:country":"CA",
    "sg:address":"1071 Canada Ave",
    "sg:city":"Duncan",
    "sg:classifiers":[
        {
            "category":"Organizations",
            "subcategory":"Religious Organization",
            "type":"Services"
        }
    ],
    "sg:phone":"+1 250 746 5822",
    "sg:postcode":"V9L 1V2",
    "sg:province":"BC",
    "sg:tags":[
        "church"
    ],
    "wof:name":"Jehovah's Witnesses",
    "wof:placetype":"venue"
},
  "geometry": {"coordinates":[-123.709091,48.785488],"type":"Point"}
}