{
  "type": "Feature",
  "properties": {
    "addr:full":"Lunenburg NS B0J 2C0",
    "addr:postcode":"b0j 2c0",
    "iso:country":"CA",
    "sg:city":"Lunenburg",
    "sg:classifiers":[
        {
            "category":"Personal",
            "subcategory":"Beauty Salon",
            "type":"Services"
        }
    ],
    "sg:phone":"+1 902 634 4322",
    "sg:postcode":"B0J 2C0",
    "sg:province":"NS",
    "wof:name":"Studio 177 Hair Design",
    "wof:placetype":"venue"
},
  "geometry": {"coordinates":[-64.312454,44.377449],"type":"Point"}
}