{
  "type": "Feature",
  "properties": {
    "addr:full":"83 Manitowaning Rd Little Current ON P0P 1K0",
    "addr:housenumber":"83",
    "addr:postcode":"p0p 1k0",
    "addr:street":"Manitowaning Rd",
    "iso:country":"CA",
    "sg:address":"83 Manitowaning Rd",
    "sg:city":"Little Current",
    "sg:classifiers":[
        {
            "category":"Retail",
            "subcategory":"Auto Repair",
            "type":"Services"
        }
    ],
    "sg:phone":"+1 705 368 3111",
    "sg:postcode":"P0P 1K0",
    "sg:province":"ON",
    "sg:tags":[
        "repairing",
        "automobile"
    ],
    "wof:name":"Highway 6 Svc Ctr Ltd",
    "wof:placetype":"venue"
},
  "geometry": {"coordinates":[-81.92212677000001,45.9726486206],"type":"Point"}
}