{
  "type": "Feature",
  "properties": {
    "addr:full":"2700 Rue Leger Lasalle QC H8N 1A3",
    "addr:housenumber":"2700",
    "addr:postcode":"h8n 1a3",
    "addr:street":"Rue Leger",
    "iso:country":"CA",
    "sg:address":"2700 Rue Leger",
    "sg:city":"Lasalle",
    "sg:classifiers":[
        {
            "category":"Wholesale",
            "subcategory":"Stationery",
            "type":"Manufacturing & Wholesale Goods"
        }
    ],
    "sg:phone":"+1 514 364 6444",
    "sg:postcode":"H8N 1A3",
    "sg:province":"QC",
    "sg:tags":[
        "cardboard"
    ],
    "wof:name":"Blue Star Paper Inc",
    "wof:placetype":"venue"
},
  "geometry": {"coordinates":[-73.63056899999999,45.446491],"type":"Point"}
}