{
  "type": "Feature",
  "properties": {
    "addr:full":"2190 King Albert Ave Coquitlam BC V3J 1Z5",
    "addr:housenumber":"2190",
    "addr:postcode":"v3j 1z5",
    "addr:street":"King Albert Ave",
    "iso:country":"CA",
    "sg:address":"2190 King Albert Ave",
    "sg:city":"Coquitlam",
    "sg:classifiers":[
        {
            "category":"Wholesale",
            "subcategory":"Durable Goods & Equipment",
            "type":"Manufacturing & Wholesale Goods"
        }
    ],
    "sg:phone":"+1 604 937 3614",
    "sg:postcode":"V3J 1Z5",
    "sg:province":"BC",
    "sg:tags":[
        "importer"
    ],
    "wof:name":"Intal Trade Ventures Ltd",
    "wof:placetype":"venue"
},
  "geometry": {"coordinates":[-122.83438099999999,49.250679],"type":"Point"}
}