{
  "type": "Feature",
  "properties": {
    "addr:full":"19 Rue Saint-Paul Otterburn Park QC J3H 5R1",
    "addr:housenumber":"19",
    "addr:postcode":"j3h 5r1",
    "addr:street":"Rue Saint-Paul",
    "iso:country":"CA",
    "sg:address":"19 Rue Saint-Paul",
    "sg:city":"Otterburn Park",
    "sg:classifiers":[
        {
            "category":"Building & Trades",
            "subcategory":"Construction",
            "type":"Services"
        }
    ],
    "sg:phone":"+1 450 464 9438",
    "sg:postcode":"J3H 5R1",
    "sg:province":"QC",
    "sg:tags":[
        "contractor"
    ],
    "wof:name":"Construction Rejean Boies",
    "wof:placetype":"venue"
},
  "geometry": {"coordinates":[-73.20459,45.539345],"type":"Point"}
}