{
  "type": "Feature",
  "properties": {
    "iso:country":"CA",
    "sg:address":"1305 Rue Des Cascades O",
    "sg:city":"Saint-Hyacinthe",
    "sg:classifiers":[
        {
            "category":"Shopping",
            "type":"Retail Goods"
        }
    ],
    "sg:phone":"+1 450 774 2618",
    "sg:postcode":"J2S 3H3",
    "sg:province":"QC",
    "sg:tags":[
        "shop",
        "art",
        "gallery",
        "gift",
        "dealer"
    ],
    "wof:name":"Galerie D'Amandine",
    "wof:placetype":"venue"
},
  "geometry": {"coordinates":[-72.94445,45.625381],"type":"Point"}
}