{
  "type": "Feature",
  "properties": {
    "addr:full":"981 Foxbrook Rd Westville NS B0K 2A0",
    "addr:housenumber":"981",
    "addr:postcode":"b0k 2a0",
    "addr:street":"Foxbrook Rd",
    "iso:country":"CA",
    "sg:address":"981 Foxbrook Rd",
    "sg:city":"Westville",
    "sg:classifiers":[
        {
            "category":"Building & Trades",
            "subcategory":"Construction",
            "type":"Services"
        }
    ],
    "sg:phone":"+1 902 396 4808",
    "sg:postcode":"B0K 2A0",
    "sg:province":"NS",
    "sg:tags":[
        "contractor",
        "dry wall",
        "general"
    ],
    "wof:name":"D & B Spears Drywall Ltd",
    "wof:placetype":"venue"
},
  "geometry": {"coordinates":[-62.7093048096,45.5301361084],"type":"Point"}
}