{
  "type": "Feature",
  "properties": {
    "addr:full":"2049 Boul Marcel-Laurin Saint-Laurent QC H4R 1K4",
    "addr:housenumber":"2049",
    "addr:postcode":"h4r 1k4",
    "addr:street":"Boul Marcel-Laurin",
    "iso:country":"CA",
    "sg:address":"2049 Boul Marcel-Laurin",
    "sg:city":"Saint-Laurent",
    "sg:classifiers":[
        {
            "category":"Shopping",
            "type":"Retail Goods"
        }
    ],
    "sg:phone":"+1 514 337 2582",
    "sg:postcode":"H4R 1K4",
    "sg:province":"QC",
    "sg:tags":[
        "equipment",
        "wine",
        "supply"
    ],
    "wof:name":"Cellier St Laurent",
    "wof:placetype":"venue"
},
  "geometry": {"coordinates":[-73.70171356199999,45.5187759399],"type":"Point"}
}