{
  "type": "Feature",
  "properties": {
    "addr:full":"37 King William St Hamilton ON L8R 1A1",
    "addr:housenumber":"37",
    "addr:postcode":"l8r 1a1",
    "addr:street":"King William St",
    "iso:country":"CA",
    "sg:address":"37 King William St",
    "sg:city":"Hamilton",
    "sg:classifiers":[
        {
            "category":"Restaurant",
            "type":"Food & Drink"
        }
    ],
    "sg:phone":"+1 905 522 3354",
    "sg:postcode":"L8R 1A1",
    "sg:province":"ON",
    "sg:tags":[
        "butchering",
        "caterer"
    ],
    "wof:name":"Reardon's Deli Counter",
    "wof:placetype":"venue"
},
  "geometry": {"coordinates":[-79.86756099999999,43.257385],"type":"Point"}
}