{
  "type": "Feature",
  "properties": {
    "addr:full":"495 Boul Saint-Martin O Laval QC H7M 1Y9",
    "addr:housenumber":"495",
    "addr:postcode":"h7m 1y9",
    "addr:street":"Boul Saint-Martin O",
    "iso:country":"CA",
    "sg:address":"495 Boul Saint-Martin O",
    "sg:city":"Laval",
    "sg:classifiers":[
        {
            "category":"Professional",
            "subcategory":"Engineering",
            "type":"Services"
        }
    ],
    "sg:phone":"+1 450 662 8318",
    "sg:postcode":"H7M 1Y9",
    "sg:province":"QC",
    "sg:tags":[
        "engineer"
    ],
    "wof:name":"Filiatrault Mc Neil & Assoc",
    "wof:placetype":"venue"
},
  "geometry": {"coordinates":[-73.712433,45.576908],"type":"Point"}
}