{
  "type": "Feature",
  "properties": {
    "iso:country":"CA",
    "sg:address":"RR 3",
    "sg:city":"Belfast",
    "sg:classifiers":[
        {
            "category":"Recreation",
            "type":"Entertainment"
        }
    ],
    "sg:phone":"+1 902 659 2277",
    "sg:postcode":"C0A 1A0",
    "sg:province":"PE",
    "sg:tags":[
        "center"
    ],
    "wof:name":"Belfast Rec Ctr",
    "wof:placetype":"venue"
},
  "geometry": {"coordinates":[-62.878937,46.089355],"type":"Point"}
}