{
  "type": "Feature",
  "properties": {
    "addr:full":"336 Pine St Sudbury ON P3C 1X8",
    "addr:housenumber":"336",
    "addr:postcode":"p3c 1x8",
    "addr:street":"Pine St",
    "iso:country":"CA",
    "sg:address":"336 Pine St",
    "sg:city":"Sudbury",
    "sg:classifiers":[
        {
            "category":"Organizations",
            "subcategory":"Non-profit Organization",
            "type":"Services"
        }
    ],
    "sg:phone":"+1 705 688 9929",
    "sg:postcode":"P3C 1X8",
    "sg:province":"ON",
    "sg:tags":[
        "addiction",
        "treatment",
        "center"
    ],
    "wof:name":"Narcotics Anonymous",
    "wof:placetype":"venue"
},
  "geometry": {"coordinates":[-81.007492,46.493988],"type":"Point"}
}