{
  "type": "Feature",
  "properties": {
    "addr:full":"6022 48 Ave Camrose AB T4V 0K3",
    "addr:housenumber":"6022",
    "addr:postcode":"t4v 0k3",
    "addr:street":"48 Ave",
    "iso:country":"CA",
    "sg:address":"6022 48 Ave",
    "sg:city":"Camrose",
    "sg:classifiers":[
        {
            "category":"Real Estate",
            "subcategory":"Real Estate Agent",
            "type":"Services"
        }
    ],
    "sg:phone":"+1 780 672 7474",
    "sg:postcode":"T4V 0K3",
    "sg:province":"AB",
    "wof:name":"Re Max Real Estate",
    "wof:placetype":"venue"
},
  "geometry": {"coordinates":[-112.84303300000001,53.018162],"type":"Point"}
}