{
  "type": "Feature",
  "properties": {
    "addr:full":"Calgary AB T2J 0S5",
    "addr:postcode":"t2j 0s5",
    "iso:country":"CA",
    "sg:city":"Calgary",
    "sg:classifiers":[
        {
            "category":"Real Estate",
            "subcategory":"Real Estate Operator",
            "type":"Services"
        }
    ],
    "sg:phone":"+1 403 278 5231",
    "sg:postcode":"T2J 0S5",
    "sg:province":"AB",
    "sg:tags":[
        "apartment"
    ],
    "wof:name":"Willow Green Estates",
    "wof:placetype":"venue"
},
  "geometry": {"coordinates":[-114.058441,50.96294],"type":"Point"}
}