{
  "type": "Feature",
  "properties": {
    "iso:country":"CA",
    "sg:city":"Halifax",
    "sg:classifiers":[
        {
            "category":"Health Services",
            "subcategory":"Doctor",
            "type":"Services"
        }
    ],
    "sg:phone":"+1 902 422 5454",
    "sg:postcode":"B3J 1G9",
    "sg:province":"NS",
    "sg:tags":[
        "dentist"
    ],
    "wof:name":"Davies, Ben DDS",
    "wof:placetype":"venue"
},
  "geometry": {"coordinates":[-63.5786514282,44.6426620483],"type":"Point"}
}