{
  "type": "Feature",
  "properties": {
    "addr:full":"8 Rue Gale Ormstown QC J0S 1K0",
    "addr:housenumber":"8",
    "addr:postcode":"j0s 1k0",
    "addr:street":"Rue Gale",
    "iso:country":"CA",
    "sg:address":"8 Rue Gale",
    "sg:city":"Ormstown",
    "sg:classifiers":[
        {
            "category":"Manufacturing",
            "subcategory":"Tools & Machinery",
            "type":"Manufacturing & Wholesale Goods"
        }
    ],
    "sg:phone":"+1 450 829 3130",
    "sg:postcode":"J0S 1K0",
    "sg:province":"QC",
    "sg:tags":[
        "electric",
        "motor"
    ],
    "wof:name":"Entreprises Mc",
    "wof:placetype":"venue"
},
  "geometry": {"coordinates":[-73.99683400000001,45.127224],"type":"Point"}
}