{
  "type": "Feature",
  "properties": {
    "addr:full":"615 Rue Craig Richmond QC J0B 2H0",
    "addr:housenumber":"615",
    "addr:postcode":"j0b 2h0",
    "addr:street":"Rue Craig",
    "iso:country":"CA",
    "sg:address":"615 Rue Craig",
    "sg:city":"Richmond",
    "sg:classifiers":[
        {
            "category":"Shopping",
            "subcategory":"Used Merchandise",
            "type":"Retail Goods"
        }
    ],
    "sg:phone":"+1 819 826 6764",
    "sg:postcode":"J0B 2H0",
    "sg:province":"QC",
    "sg:tags":[
        "antique"
    ],
    "wof:name":"Antiquites Du Carre",
    "wof:placetype":"venue"
},
  "geometry": {"coordinates":[-72.13385772709999,45.6640853882],"type":"Point"}
}