{
  "type": "Feature",
  "properties": {
    "addr:full":"380 Bovaird Dr #26 Brampton ON L6Z 2S8",
    "addr:housenumber":"380",
    "addr:postcode":"l6z 2s8",
    "addr:street":"Bovaird Dr # 26",
    "iso:country":"CA",
    "sg:address":"380 Bovaird Dr #26",
    "sg:city":"Brampton",
    "sg:classifiers":[
        {
            "category":"Shopping",
            "subcategory":"Pharmacy",
            "type":"Retail Goods"
        }
    ],
    "sg:phone":"+1 905 840 0660",
    "sg:postcode":"L6Z 2S8",
    "sg:province":"ON",
    "wof:name":"Pharma Plus Drugmart",
    "wof:placetype":"venue"
},
  "geometry": {"coordinates":[-79.77861,43.714252],"type":"Point"}
}