{
  "type": "Feature",
  "properties": {
    "addr:full":"1914 Meredith Rd Nanaimo BC V9S 2M7",
    "addr:housenumber":"1914",
    "addr:postcode":"v9s 2m7",
    "addr:street":"Meredith Rd",
    "iso:country":"CA",
    "sg:address":"1914 Meredith Rd",
    "sg:city":"Nanaimo",
    "sg:classifiers":[
        {
            "category":"Insurance",
            "subcategory":"Insurance Agent",
            "type":"Services"
        }
    ],
    "sg:phone":"+1 250 758 3131",
    "sg:postcode":"V9S 2M7",
    "sg:province":"BC",
    "wof:name":"Transamerica Life Insurance CO",
    "wof:placetype":"venue"
},
  "geometry": {"coordinates":[-123.985039,49.18832],"type":"Point"}
}