{
  "type": "Feature",
  "properties": {
    "addr:full":"6630 Ch DE LA Cote-Saint-Luc Montreal QC H4V 1G8",
    "addr:postcode":"6630;h4v 1g8",
    "addr:street":"Ch De La Cote-Saint-Luc",
    "iso:country":"CA",
    "sg:address":"6630 Ch DE LA Cote-Saint-Luc",
    "sg:city":"Montreal",
    "sg:classifiers":[
        {
            "category":"Restaurant",
            "type":"Food & Drink"
        }
    ],
    "sg:phone":"+1 514 488 4111",
    "sg:postcode":"H4V 1G8",
    "sg:province":"QC",
    "sg:tags":[
        "caterer"
    ],
    "wof:name":"Marguerite",
    "wof:placetype":"venue"
},
  "geometry": {"coordinates":[-73.649147,45.470486],"type":"Point"}
}