{
  "type": "Feature",
  "properties": {
    "iso:country":"CA",
    "sg:address":"365 Trans Canada Hwy",
    "sg:city":"Lytton",
    "sg:classifiers":[
        {
            "category":"Education",
            "subcategory":"School",
            "type":"Public Place"
        }
    ],
    "sg:phone":"+1 250 455 2328",
    "sg:postcode":"V0K 1Z0",
    "sg:province":"BC",
    "wof:name":"Kumsheen Secondary School",
    "wof:placetype":"venue"
},
  "geometry": {"coordinates":[-121.573829651,50.2398338318],"type":"Point"}
}