{
  "type": "Feature",
  "properties": {
    "addr:full":"9810 Seventh St Sidney BC V8L 4W6",
    "addr:housenumber":"9810",
    "addr:postcode":"v8l 4w6",
    "addr:street":"Seventh St",
    "iso:country":"CA",
    "sg:address":"9810 Seventh St",
    "sg:city":"Sidney",
    "sg:classifiers":[
        {
            "category":"Shopping",
            "subcategory":"Pharmacy",
            "type":"Retail Goods"
        }
    ],
    "sg:phone":"+1 250 656 1148",
    "sg:postcode":"V8L 4W6",
    "sg:province":"BC",
    "wof:name":"Pharmasave Drugs",
    "wof:placetype":"venue"
},
  "geometry": {"coordinates":[-123.40381600000001,48.649277],"type":"Point"}
}