{
  "type": "Feature",
  "properties": {
    "addr:full":"369 Park St Regina SK S4N 5B2",
    "addr:housenumber":"369",
    "addr:postcode":"s4n 5b2",
    "addr:street":"Park St",
    "iso:country":"CA",
    "sg:address":"369 Park St",
    "sg:city":"Regina",
    "sg:classifiers":[
        {
            "category":"Organizations",
            "subcategory":"Professional Association",
            "type":"Services"
        }
    ],
    "sg:phone":"+1 306 721 2767",
    "sg:postcode":"S4N 5B2",
    "sg:province":"SK",
    "wof:name":"Multicultural Council-Sask",
    "wof:placetype":"venue"
},
  "geometry": {"coordinates":[-104.579002,50.472801],"type":"Point"}
}