{
  "type": "Feature",
  "properties": {
    "addr:full":"Victoria BC V8W 1L8",
    "addr:postcode":"v8w 1l8",
    "iso:country":"CA",
    "sg:city":"Victoria",
    "sg:classifiers":[
        {
            "category":"Government",
            "subcategory":"Office",
            "type":"Public Place"
        }
    ],
    "sg:phone":"+1 250 953 3471",
    "sg:postcode":"V8W 1L8",
    "sg:province":"BC",
    "wof:name":"B C Landscape & Watershed",
    "wof:placetype":"venue"
},
  "geometry": {"coordinates":[-123.36090850799999,48.4260025024],"type":"Point"}
}