{
  "type": "Feature",
  "properties": {
    "iso:country":"CA",
    "sg:address":"5016 48 Ave",
    "sg:city":"Taber",
    "sg:classifiers":[
        {
            "category":"Health Services",
            "subcategory":"Doctor",
            "type":"Services"
        }
    ],
    "sg:phone":"+1 403 223 3525",
    "sg:postcode":"T1G 1R8",
    "sg:province":"AB",
    "sg:tags":[
        "physician",
        "surgeon"
    ],
    "wof:name":"Medical Centre Assoc",
    "wof:placetype":"venue"
},
  "geometry": {"coordinates":[-112.14928436300001,49.7836723328],"type":"Point"}
}