{
  "type": "Feature",
  "properties": {
    "addr:full":"652 Corbeil Astorville Rd Corbeil ON P0H 1K0",
    "addr:housenumber":"652",
    "addr:postcode":"p0h 1k0",
    "addr:street":"Corbeil Astorville Rd",
    "iso:country":"CA",
    "sg:address":"652 Corbeil Astorville Rd",
    "sg:city":"Corbeil",
    "sg:classifiers":[
        {
            "category":"Travel",
            "subcategory":"Hotels & Motels",
            "type":"Entertainment"
        }
    ],
    "sg:phone":"+1 705 752 3105",
    "sg:postcode":"P0H 1K0",
    "sg:province":"ON",
    "sg:tags":[
        "cottage",
        "tourist",
        "cabin",
        "accommodation"
    ],
    "wof:name":"Happy Holiday Cabins",
    "wof:placetype":"venue"
},
  "geometry": {"coordinates":[-79.29196929930001,46.2616081238],"type":"Point"}
}