{
  "type": "Feature",
  "properties": {
    "addr:full":"Tofino BC V0R 2Z0",
    "addr:postcode":"v0r 2z0",
    "iso:country":"CA",
    "sg:city":"Tofino",
    "sg:classifiers":[
        {
            "category":"Farming",
            "subcategory":"Fish & Marine Products",
            "type":"Manufacturing & Wholesale Goods"
        }
    ],
    "sg:phone":"+1 250 725 2700",
    "sg:postcode":"V0R 2Z0",
    "sg:province":"BC",
    "sg:tags":[
        "fisherman"
    ],
    "wof:name":"Clayoquot Ventures Guide Svc",
    "wof:placetype":"venue"
},
  "geometry": {"coordinates":[-125.900841,49.152084],"type":"Point"}
}