{
  "type": "Feature",
  "properties": {
    "iso:country":"CA",
    "sg:address":"1110 Bloor St",
    "sg:city":"Mississauga",
    "sg:classifiers":[
        {
            "category":"Health Services",
            "subcategory":"Doctor",
            "type":"Services"
        }
    ],
    "sg:phone":"+1 905 277 1783",
    "sg:postcode":"L4Y 2N7",
    "sg:province":"ON",
    "sg:tags":[
        "physician",
        "surgeon"
    ],
    "wof:name":"Lo, Eddie MD",
    "wof:placetype":"venue"
},
  "geometry": {"coordinates":[-79.600189,43.610596],"type":"Point"}
}