{
  "type": "Feature",
  "properties": {
    "addr:full":"24 Gale Ave Sherwood Park AB T8A 2K8",
    "addr:housenumber":"24",
    "addr:postcode":"t8a 2k8",
    "addr:street":"Gale Ave",
    "iso:country":"CA",
    "sg:address":"24 Gale Ave",
    "sg:city":"Sherwood Park",
    "sg:classifiers":[
        {
            "category":"Food & Beverages",
            "subcategory":"Specialty",
            "type":"Retail Goods"
        }
    ],
    "sg:phone":"+1 780 467 0523",
    "sg:postcode":"T8A 2K8",
    "sg:province":"AB",
    "sg:tags":[
        "health",
        "diet"
    ],
    "wof:name":"Shaklee Products Distributor",
    "wof:placetype":"venue"
},
  "geometry": {"coordinates":[-113.291252136,53.5372085571],"type":"Point"}
}