{
  "type": "Feature",
  "properties": {
    "addr:full":"3257 Boul Henri-Bourassa E Montreal-Nord QC H1H 1H3",
    "addr:housenumber":"3257",
    "addr:postcode":"h1h 1h3",
    "addr:street":"Boul Henri-Bourassa E",
    "iso:country":"CA",
    "sg:address":"3257 Boul Henri-Bourassa E",
    "sg:city":"Montreal-Nord",
    "sg:classifiers":[
        {
            "category":"Shopping",
            "type":"Retail Goods"
        }
    ],
    "sg:phone":"+1 514 321 8424",
    "sg:postcode":"H1H 1H3",
    "sg:province":"QC",
    "sg:tags":[
        "orthopedic",
        "appliance"
    ],
    "wof:name":"Laboratoire Bergeron",
    "wof:placetype":"venue"
},
  "geometry": {"coordinates":[-73.65046691889999,45.5843925476],"type":"Point"}
}