{
  "type": "Feature",
  "properties": {
    "addr:full":"Woodbridge ON L4L 6E3",
    "addr:postcode":"l4l 6e3",
    "iso:country":"CA",
    "sg:city":"Woodbridge",
    "sg:classifiers":[
        {
            "category":"Education",
            "subcategory":"Special Training",
            "type":"Public Place"
        }
    ],
    "sg:phone":"+1 905 850 0552",
    "sg:postcode":"L4L 6E3",
    "sg:province":"ON",
    "sg:tags":[
        "instruction",
        "music"
    ],
    "wof:name":"Canadian School of Performing",
    "wof:placetype":"venue"
},
  "geometry": {"coordinates":[-79.5554656982,43.785572052],"type":"Point"}
}