{
  "type": "Feature",
  "properties": {
    "addr:full":"Calgary AB T2H 0S6",
    "addr:postcode":"t2h 0s6",
    "iso:country":"CA",
    "sg:city":"Calgary",
    "sg:classifiers":[
        {
            "category":"Professional",
            "subcategory":"Engineering",
            "type":"Services"
        }
    ],
    "sg:phone":"+1 403 259 5944",
    "sg:postcode":"T2H 0S6",
    "sg:province":"AB",
    "sg:tags":[
        "engineer"
    ],
    "wof:name":"Techcord Consulting Group Ltd",
    "wof:placetype":"venue"
},
  "geometry": {"coordinates":[-114.04939299999999,50.98893],"type":"Point"}
}