{
  "type": "Feature",
  "properties": {
    "addr:full":"18 Tutshi Rd Whitehorse YT Y1A 3R3",
    "addr:housenumber":"18",
    "addr:postcode":"y1a 3r3",
    "addr:street":"Tutshi Rd",
    "iso:country":"CA",
    "sg:address":"18 Tutshi Rd",
    "sg:city":"Whitehorse",
    "sg:classifiers":[
        {
            "category":"Professional",
            "subcategory":"Engineering",
            "type":"Services"
        }
    ],
    "sg:phone":"+1 867 633 6755",
    "sg:postcode":"Y1A 3R3",
    "sg:province":"YT",
    "sg:tags":[
        "sprinkler",
        "engineer"
    ],
    "wof:name":"Fireguard Automatic Sprinkler",
    "wof:placetype":"venue"
},
  "geometry": {"coordinates":[-135.026398,60.709057],"type":"Point"}
}