{
  "type": "Feature",
  "properties": {
    "addr:full":"299 King St Port Colborne ON L3K 4H2",
    "addr:housenumber":"299",
    "addr:postcode":"l3k 4h2",
    "addr:street":"King St",
    "iso:country":"CA",
    "sg:address":"299 King St",
    "sg:city":"Port Colborne",
    "sg:classifiers":[
        {
            "category":"Personal",
            "subcategory":"Beauty Salon",
            "type":"Services"
        }
    ],
    "sg:phone":"+1 905 834 0990",
    "sg:postcode":"L3K 4H2",
    "sg:province":"ON",
    "wof:name":"Style Majestic Design",
    "wof:placetype":"venue"
},
  "geometry": {"coordinates":[-79.251366,42.88826],"type":"Point"}
}