{
  "type": "Feature",
  "properties": {
    "addr:full":"1891 Wellington Cres Richmond BC V7B 1G6",
    "addr:housenumber":"1891",
    "addr:postcode":"v7b 1g6",
    "addr:street":"Wellington Cres",
    "iso:country":"CA",
    "sg:address":"1891 Wellington Cres",
    "sg:city":"Richmond",
    "sg:classifiers":[
        {
            "category":"Education",
            "subcategory":"School",
            "type":"Public Place"
        }
    ],
    "sg:phone":"+1 604 668 6468",
    "sg:postcode":"V7B 1G6",
    "sg:province":"BC",
    "wof:name":"Sea Island Elementary School",
    "wof:placetype":"venue"
},
  "geometry": {"coordinates":[-123.149047852,49.1906013489],"type":"Point"}
}