{
  "type": "Feature",
  "properties": {
    "addr:full":"1509 Centre St SW #350 Calgary AB T2G 2E6",
    "addr:housenumber":"1509",
    "addr:postcode":"t2g 2e6",
    "addr:street":"Centre St Sw # 350",
    "iso:country":"CA",
    "sg:address":"1509 Centre St SW #350",
    "sg:city":"Calgary",
    "sg:classifiers":[
        {
            "category":"Professional",
            "subcategory":"Lawyer & Legal Services",
            "type":"Services"
        }
    ],
    "sg:phone":"+1 403 261 9048",
    "sg:postcode":"T2G 2E6",
    "sg:province":"AB",
    "sg:tags":[
        "attorney"
    ],
    "wof:name":"Darwent, Charles R",
    "wof:placetype":"venue"
},
  "geometry": {"coordinates":[-114.06368999999999,51.038437],"type":"Point"}
}