{
  "type": "Feature",
  "properties": {
    "iso:country":"CA",
    "sg:address":"3524 Rue Griffith",
    "sg:city":"Saint-Laurent",
    "sg:classifiers":[
        {
            "category":"Wholesale",
            "subcategory":"Hardware",
            "type":"Manufacturing & Wholesale Goods"
        }
    ],
    "sg:phone":"+1 514 735 6555",
    "sg:postcode":"H4T 1A7",
    "sg:province":"QC",
    "wof:name":"Mkc Inc",
    "wof:placetype":"venue"
},
  "geometry": {"coordinates":[-73.69503,45.487541],"type":"Point"}
}