{
  "type": "Feature",
  "properties": {
    "addr:full":"Waterloo ON N2V 1Y8",
    "addr:postcode":"n2v 1y8",
    "iso:country":"CA",
    "sg:city":"Waterloo",
    "sg:classifiers":[
        {
            "category":"Home & Garden",
            "subcategory":"Carpets & Floor Coverings",
            "type":"Retail Goods"
        }
    ],
    "sg:phone":"+1 519 888 7338",
    "sg:postcode":"N2V 1Y8",
    "sg:province":"ON",
    "sg:tags":[
        "material"
    ],
    "wof:name":"Rushton Contract Flooring Inc",
    "wof:placetype":"venue"
},
  "geometry": {"coordinates":[-80.532387,43.507454],"type":"Point"}
}