{
  "type": "Feature",
  "properties": {
    "addr:full":"901 Rue D'Acton Acton Vale QC J0H 1A0",
    "addr:housenumber":"901",
    "addr:postcode":"j0h 1a0",
    "addr:street":"Rue D'Acton",
    "iso:country":"CA",
    "sg:address":"901 Rue D'Acton",
    "sg:city":"Acton Vale",
    "sg:classifiers":[
        {
            "category":"Education",
            "subcategory":"School",
            "type":"Public Place"
        }
    ],
    "sg:phone":"+1 450 546 2712",
    "sg:postcode":"J0H 1A0",
    "sg:province":"QC",
    "wof:name":"Ecole Roger Labreque",
    "wof:placetype":"venue"
},
  "geometry": {"coordinates":[-72.5658569336,45.6469955444],"type":"Point"}
}