{
  "type": "Feature",
  "properties": {
    "addr:full":"5314 50th St Castor AB T0C 0X0",
    "addr:housenumber":"5314",
    "addr:postcode":"t0c 0x0",
    "addr:street":"50Th St",
    "iso:country":"CA",
    "sg:address":"5314 50th St",
    "sg:city":"Castor",
    "sg:classifiers":[
        {
            "category":"Organizations",
            "subcategory":"Religious Organization",
            "type":"Services"
        }
    ],
    "sg:phone":"+1 403 882 4041",
    "sg:postcode":"T0C 0X0",
    "sg:province":"AB",
    "sg:tags":[
        "church"
    ],
    "wof:name":"Missionary Church",
    "wof:placetype":"venue"
},
  "geometry": {"coordinates":[-111.901412964,52.2222938538],"type":"Point"}
}