{
  "type": "Feature",
  "properties": {
    "iso:country":"CA",
    "sg:address":"40th St E",
    "sg:city":"Prince Albert",
    "sg:classifiers":[
        {
            "category":"Building & Trades",
            "subcategory":"Construction",
            "type":"Services"
        }
    ],
    "sg:phone":"+1 306 961 4041",
    "sg:postcode":"S6V 8C3",
    "sg:province":"SK",
    "sg:tags":[
        "siding",
        "stucco",
        "contractor"
    ],
    "wof:name":"Harasyn Brothers Stucco Ltd",
    "wof:placetype":"venue"
},
  "geometry": {"coordinates":[-105.752952576,53.1767883301],"type":"Point"}
}