{
  "type": "Feature",
  "properties": {
    "addr:full":"1281 Rue Du Pont Saint-Lambert-DE-Lauzon QC G0S 2W0",
    "addr:housenumber":"1281",
    "addr:postcode":"g0s 2w0",
    "addr:street":"Rue Du Pont",
    "iso:country":"CA",
    "sg:address":"1281 Rue Du Pont",
    "sg:city":"Saint-Lambert-DE-Lauzon",
    "sg:classifiers":[
        {
            "category":"Health Services",
            "subcategory":"Doctor",
            "type":"Services"
        }
    ],
    "sg:phone":"+1 418 889 0430",
    "sg:postcode":"G0S 2W0",
    "sg:province":"QC",
    "sg:tags":[
        "clinic"
    ],
    "wof:name":"Clinique Medicale Du Rivage",
    "wof:placetype":"venue"
},
  "geometry": {"coordinates":[-71.202225,46.593628],"type":"Point"}
}