{
  "type": "Feature",
  "properties": {
    "addr:full":"11511 King Rd Richmond BC V7A 3B5",
    "addr:housenumber":"11511",
    "addr:postcode":"v7a 3b5",
    "addr:street":"King Rd",
    "iso:country":"CA",
    "sg:address":"11511 King Rd",
    "sg:city":"Richmond",
    "sg:classifiers":[
        {
            "category":"Education",
            "subcategory":"School",
            "type":"Public Place"
        }
    ],
    "sg:phone":"+1 604 668 6280",
    "sg:postcode":"V7A 3B5",
    "sg:province":"BC",
    "wof:name":"Kingswood Elementary School",
    "wof:placetype":"venue"
},
  "geometry": {"coordinates":[-123.095688,49.144527],"type":"Point"}
}