{
  "type": "Feature",
  "properties": {
    "addr:full":"Saint-Charles-DE-Mandeville QC J0K 1L0",
    "addr:postcode":"j0k 1l0",
    "iso:country":"CA",
    "sg:city":"Saint-Charles-DE-Mandeville",
    "sg:classifiers":[
        {
            "category":"Bars & Pubs",
            "type":"Food & Drink"
        }
    ],
    "sg:phone":"+1 450 835 3444",
    "sg:postcode":"J0K 1L0",
    "sg:province":"QC",
    "sg:tags":[
        "lounge",
        "cocktail"
    ],
    "wof:name":"Restaurant Hotel St-Charles",
    "wof:placetype":"venue"
},
  "geometry": {"coordinates":[-73.35283660890001,46.3594512939],"type":"Point"}
}