{
  "type": "Feature",
  "properties": {
    "addr:full":"101 Amber St # 5 Markham ON L3R 3B2",
    "addr:housenumber":"101",
    "addr:postcode":"l3r 3b2",
    "addr:street":"Amber St # 5",
    "iso:country":"CA",
    "sg:address":"101 Amber St # 5",
    "sg:city":"Markham",
    "sg:classifiers":[
        {
            "category":"Wholesale",
            "subcategory":"Machinery & Supplies",
            "type":"Manufacturing & Wholesale Goods"
        }
    ],
    "sg:phone":"+1 905 475 9955",
    "sg:postcode":"L3R 3B2",
    "sg:province":"ON",
    "sg:tags":[
        "jig",
        "fixture"
    ],
    "wof:name":"Northview Industries Ltd",
    "wof:placetype":"venue"
},
  "geometry": {"coordinates":[-79.331337,43.828079],"type":"Point"}
}