{
  "type": "Feature",
  "properties": {
    "addr:full":"514 Yonge St Toronto ON M4Y 1X9",
    "addr:housenumber":"514",
    "addr:postcode":"m4y 1x9",
    "addr:street":"Yonge St",
    "iso:country":"CA",
    "sg:address":"514 Yonge St",
    "sg:city":"Toronto",
    "sg:classifiers":[
        {
            "category":"Professional",
            "subcategory":"Business Services",
            "type":"Services"
        }
    ],
    "sg:phone":"+1 416 922 5842",
    "sg:postcode":"M4Y 1X9",
    "sg:province":"ON",
    "sg:tags":[
        "liquidator",
        "auctioneer"
    ],
    "wof:name":"Joseph Hollander & Sons Ltd",
    "wof:placetype":"venue"
},
  "geometry": {"coordinates":[-79.38413238530001,43.6634407043],"type":"Point"}
}