{
  "type": "Feature",
  "properties": {
    "addr:full":"140 Rue Des Erables Stratford QC G0Y 1P0",
    "addr:housenumber":"140",
    "addr:postcode":"g0y 1p0",
    "addr:street":"Rue Des Erables",
    "iso:country":"CA",
    "sg:address":"140 Rue Des Erables",
    "sg:city":"Stratford",
    "sg:classifiers":[
        {
            "category":"Building & Trades",
            "subcategory":"Construction",
            "type":"Services"
        }
    ],
    "sg:phone":"+1 418 443 2055",
    "sg:postcode":"G0Y 1P0",
    "sg:province":"QC",
    "sg:tags":[
        "excavating",
        "contractor"
    ],
    "wof:name":"Excavation Gagnon & Freres Inc",
    "wof:placetype":"venue"
},
  "geometry": {"coordinates":[-71.278496,45.782799],"type":"Point"}
}