{
  "type": "Feature",
  "properties": {
    "addr:full":"Richmond BC V6V 3B2",
    "addr:postcode":"v6v 3b2",
    "iso:country":"CA",
    "sg:city":"Richmond",
    "sg:classifiers":[
        {
            "category":"Manufacturing",
            "subcategory":"Tools & Machinery",
            "type":"Manufacturing & Wholesale Goods"
        }
    ],
    "sg:phone":"+1 604 691 6340",
    "sg:postcode":"V6V 3B2",
    "sg:province":"BC",
    "sg:tags":[
        "engine"
    ],
    "wof:name":"Finning Power Systems",
    "wof:placetype":"venue"
},
  "geometry": {"coordinates":[-123.05592300000001,49.202579],"type":"Point"}
}