{
  "type": "Feature",
  "properties": {
    "iso:country":"CA",
    "sg:city":"Mississauga",
    "sg:classifiers":[
        {
            "category":"Shopping",
            "subcategory":"Music",
            "type":"Retail Goods"
        }
    ],
    "sg:phone":"+1 905 813 9544",
    "sg:postcode":"L5M 6G4",
    "sg:province":"ON",
    "sg:tags":[
        "compact",
        "record",
        "disc",
        "tape"
    ],
    "wof:name":"Continental Records CO Ltd",
    "wof:placetype":"venue"
},
  "geometry": {"coordinates":[-79.72686004640001,43.5671157837],"type":"Point"}
}