{
  "type": "Feature",
  "properties": {
    "addr:full":"Didsbury AB T0M 0W0",
    "addr:postcode":"t0m 0w0",
    "iso:country":"CA",
    "sg:city":"Didsbury",
    "sg:classifiers":[
        {
            "category":"Wholesale",
            "subcategory":"Scrap",
            "type":"Manufacturing & Wholesale Goods"
        }
    ],
    "sg:phone":"+1 403 335 9525",
    "sg:postcode":"T0M 0W0",
    "sg:province":"AB",
    "sg:tags":[
        "automobile",
        "crushing"
    ],
    "wof:name":"Waymore Service & Auto Rcyclrs",
    "wof:placetype":"venue"
},
  "geometry": {"coordinates":[-114.14054107699999,51.6662712097],"type":"Point"}
}