{
  "type": "Feature",
  "properties": {
    "addr:full":"2260 4th Ave E Vancouver BC V5N 1K8",
    "addr:housenumber":"2260",
    "addr:postcode":"v5n 1k8",
    "addr:street":"4Th Ave E",
    "iso:country":"CA",
    "sg:address":"2260 4th Ave E",
    "sg:city":"Vancouver",
    "sg:classifiers":[
        {
            "category":"Building & Trades",
            "subcategory":"Cleaning & Sanitation",
            "type":"Services"
        }
    ],
    "sg:phone":"+1 604 255 4115",
    "sg:postcode":"V5N 1K8",
    "sg:province":"BC",
    "sg:tags":[
        "janitor"
    ],
    "wof:name":"Blackman Window Cleaners",
    "wof:placetype":"venue"
},
  "geometry": {"coordinates":[-123.058853149,49.2666549683],"type":"Point"}
}