{
  "type": "Feature",
  "properties": {
    "addr:full":"1021 Woodbine Rd Kingston ON K7P 2V9",
    "addr:housenumber":"1021",
    "addr:postcode":"k7p 2v9",
    "addr:street":"Woodbine Rd",
    "iso:country":"CA",
    "sg:address":"1021 Woodbine Rd",
    "sg:city":"Kingston",
    "sg:classifiers":[
        {
            "category":"Organizations",
            "subcategory":"Religious Organization",
            "type":"Services"
        }
    ],
    "sg:phone":"+1 613 384 7306",
    "sg:postcode":"K7P 2V9",
    "sg:province":"ON",
    "sg:tags":[
        "church"
    ],
    "wof:name":"Westside Fellowship Church",
    "wof:placetype":"venue"
},
  "geometry": {"coordinates":[-76.5932006836,44.2584915161],"type":"Point"}
}