{
  "type": "Feature",
  "properties": {
    "addr:full":"80 Industrial Rd Leamington ON N8H 4W4",
    "addr:housenumber":"80",
    "addr:postcode":"n8h 4w4",
    "addr:street":"Industrial Rd",
    "iso:country":"CA",
    "sg:address":"80 Industrial Rd",
    "sg:city":"Leamington",
    "sg:classifiers":[
        {
            "category":"Retail",
            "subcategory":"Auto Repair",
            "type":"Services"
        }
    ],
    "sg:phone":"+1 519 326 4510",
    "sg:postcode":"N8H 4W4",
    "sg:province":"ON",
    "sg:tags":[
        "repairing",
        "automobile"
    ],
    "wof:name":"Oakway Automotive Repair",
    "wof:placetype":"venue"
},
  "geometry": {"coordinates":[-82.608643,42.048355],"type":"Point"}
}