{
  "type": "Feature",
  "properties": {
    "addr:full":"161 Kingston St Prince George BC V2L 1C4",
    "addr:housenumber":"161",
    "addr:postcode":"v2l 1c4",
    "addr:street":"Kingston St",
    "iso:country":"CA",
    "sg:address":"161 Kingston St",
    "sg:city":"Prince George",
    "sg:classifiers":[
        {
            "category":"Home & Garden",
            "subcategory":"Furniture",
            "type":"Retail Goods"
        }
    ],
    "sg:phone":"+1 250 563 9193",
    "sg:postcode":"V2L 1C4",
    "sg:province":"BC",
    "sg:tags":[
        "top",
        "counter"
    ],
    "wof:name":"Modern Countertop Shoppe",
    "wof:placetype":"venue"
},
  "geometry": {"coordinates":[-122.732536,53.914776],"type":"Point"}
}