{
  "type": "Feature",
  "properties": {
    "addr:full":"680 Adams Crt Kelowna BC V1X 7S2",
    "addr:housenumber":"680",
    "addr:postcode":"v1x 7s2",
    "addr:street":"Adams",
    "iso:country":"CA",
    "sg:address":"680 Adams Crt",
    "sg:city":"Kelowna",
    "sg:classifiers":[
        {
            "category":"Wholesale",
            "subcategory":"Metals & Minerals",
            "type":"Manufacturing & Wholesale Goods"
        }
    ],
    "sg:phone":"+1 250 765 2077",
    "sg:postcode":"V1X 7S2",
    "sg:province":"BC",
    "sg:tags":[
        "steel",
        "warehouse"
    ],
    "wof:name":"R & R Reinforcing",
    "wof:placetype":"venue"
},
  "geometry": {"coordinates":[-119.388397,49.929756],"type":"Point"}
}