{
  "type": "Feature",
  "properties": {
    "iso:country":"CA",
    "sg:address":"49 Queensway W",
    "sg:city":"Simcoe",
    "sg:classifiers":[
        {
            "category":"Autos & Motor Vehicles",
            "subcategory":"Auto Supplies",
            "type":"Retail Goods"
        }
    ],
    "sg:phone":"+1 519 426 5280",
    "sg:postcode":"N3Y 2M7",
    "sg:province":"ON",
    "sg:tags":[
        "tire"
    ],
    "wof:name":"Queensway Tire Svc Ltd",
    "wof:placetype":"venue"
},
  "geometry": {"coordinates":[-80.3092803955,42.8459777832],"type":"Point"}
}