{
  "type": "Feature",
  "properties": {
    "addr:full":"18435 Rue Charles Mirabel QC J7J 1H8",
    "addr:housenumber":"18435",
    "addr:postcode":"j7j 1h8",
    "addr:street":"Rue Charles",
    "iso:country":"CA",
    "sg:address":"18435 Rue Charles",
    "sg:city":"Mirabel",
    "sg:classifiers":[
        {
            "category":"Building & Trades",
            "subcategory":"Electrical",
            "type":"Services"
        }
    ],
    "sg:phone":"+1 450 437 7214",
    "sg:postcode":"J7J 1H8",
    "sg:province":"QC",
    "sg:tags":[
        "electric",
        "contractor"
    ],
    "wof:name":"Entreprises Electriques Daniel",
    "wof:placetype":"venue"
},
  "geometry": {"coordinates":[-73.917282,45.707462],"type":"Point"}
}