{
  "type": "Feature",
  "properties": {
    "addr:full":"Burnaby BC V5J 5E3",
    "addr:postcode":"v5j 5e3",
    "iso:country":"CA",
    "sg:city":"Burnaby",
    "sg:classifiers":[
        {
            "category":"Wholesale",
            "subcategory":"Home Furnishings",
            "type":"Manufacturing & Wholesale Goods"
        }
    ],
    "sg:phone":"+1 604 439 0094",
    "sg:postcode":"V5J 5E3",
    "sg:province":"BC",
    "sg:tags":[
        "pottery"
    ],
    "wof:name":"Arbutus Landscape Pottery",
    "wof:placetype":"venue"
},
  "geometry": {"coordinates":[-123.015854,49.205647],"type":"Point"}
}