{
  "type": "Feature",
  "properties": {
    "iso:country":"CA",
    "sg:address":"400-601 West Broadway",
    "sg:city":"Vancouver",
    "sg:classifiers":[
        {
            "category":"Professional",
            "subcategory":"Advertising",
            "type":"Services"
        }
    ],
    "sg:postcode":"V5Z 4C2",
    "sg:tags":[
        "web-design--internet-marketing",
        "google-analytics",
        "cms"
    ],
    "sg:website":"http://www.isl.ca",
    "wof:name":"ISL web marketing & development",
    "wof:placetype":"venue"
},
  "geometry": {"coordinates":[-123.1175437,49.2632504],"type":"Point"}
}