{
  "type": "Feature",
  "properties": {
    "iso:country":"CA",
    "sg:address":"5619 Colonel Talbot Rd",
    "sg:city":"London",
    "sg:classifiers":[
        {
            "category":"Food & Beverages",
            "subcategory":"Fruits & Vegetables",
            "type":"Retail Goods"
        }
    ],
    "sg:phone":"+1 519 652 5697",
    "sg:postcode":"N6P 1H8",
    "sg:province":"ON",
    "sg:tags":[
        "produce"
    ],
    "wof:name":"Farmer Jack's Orchards-Fruit",
    "wof:placetype":"venue"
},
  "geometry": {"coordinates":[-81.2860488892,42.8769378662],"type":"Point"}
}