{
  "type": "Feature",
  "properties": {
    "iso:country":"CA",
    "sg:address":"370 Albert St",
    "sg:city":"Regina",
    "sg:classifiers":[
        {
            "category":"Restaurant",
            "type":"Food & Drink"
        }
    ],
    "sg:phone":"+1 306 545 8333",
    "sg:postcode":"S4R 2N7",
    "sg:province":"SK",
    "wof:name":"Mr Sub",
    "wof:placetype":"venue"
},
  "geometry": {"coordinates":[-104.618347168,50.4729194641],"type":"Point"}
}