{
  "type": "Feature",
  "properties": {
    "addr:full":"Saint-Jerome QC J7Z 2B8",
    "addr:postcode":"j7z 2b8",
    "iso:country":"CA",
    "sg:city":"Saint-Jerome",
    "sg:classifiers":[
        {
            "category":"Health Services",
            "subcategory":"Health Practitioner",
            "type":"Services"
        }
    ],
    "sg:phone":"+1 450 569 1113",
    "sg:postcode":"J7Z 2B8",
    "sg:province":"QC",
    "sg:tags":[
        "psychologist"
    ],
    "wof:name":"Bachand, Gilles PhD",
    "wof:placetype":"venue"
},
  "geometry": {"coordinates":[-74.00295300000001,45.775803],"type":"Point"}
}