{
  "type": "Feature",
  "properties": {
    "iso:country":"CA",
    "sg:address":"60 Rue Savard",
    "sg:city":"Dolbeau-Mistassini",
    "sg:classifiers":[
        {
            "category":"Recreation",
            "type":"Entertainment"
        }
    ],
    "sg:phone":"+1 418 276 6886",
    "sg:postcode":"G8L 4L3",
    "sg:province":"QC",
    "sg:tags":[
        "center"
    ],
    "wof:name":"Centre Sportif Vallee Secteur",
    "wof:placetype":"venue"
},
  "geometry": {"coordinates":[-72.2035064697,48.8892822266],"type":"Point"}
}