{
  "type": "Feature",
  "properties": {
    "addr:full":"511 Ch DE LA Grande-Carriere Louiseville QC J5V 2L4",
    "addr:housenumber":"511",
    "addr:postcode":"j5v 2l4",
    "addr:street":"Ch De La Grande-Carriere",
    "iso:country":"CA",
    "sg:address":"511 Ch DE LA Grande-Carriere",
    "sg:city":"Louiseville",
    "sg:classifiers":[
        {
            "category":"Retail",
            "subcategory":"Animal Services",
            "type":"Services"
        }
    ],
    "sg:phone":"+1 819 228 5649",
    "sg:postcode":"J5V 2L4",
    "sg:province":"QC",
    "sg:tags":[
        "pet",
        "grooming",
        "washing"
    ],
    "wof:name":"Studio Elegance Canine",
    "wof:placetype":"venue"
},
  "geometry": {"coordinates":[-72.97627300000001,46.264999],"type":"Point"}
}