{
  "type": "Feature",
  "properties": {
    "addr:full":"4880 No. 6 Rd Richmond BC V6V 1P7",
    "addr:postcode":"4880;v6v 1p7",
    "addr:street":"6 Rd",
    "iso:country":"CA",
    "sg:address":"4880 No. 6 Rd",
    "sg:city":"Richmond",
    "sg:classifiers":[
        {
            "category":"Restaurant",
            "type":"Food & Drink"
        }
    ],
    "sg:phone":"+1 604 821 2969",
    "sg:postcode":"V6V 1P7",
    "sg:province":"BC",
    "wof:name":"Sumo Express Cafe",
    "wof:placetype":"venue"
},
  "geometry": {"coordinates":[-123.069015503,49.1788291931],"type":"Point"}
}