{
  "type": "Feature",
  "properties": {
    "addr:full":"874 Rue DE Gentilly E Longueuil QC J4J 5B6",
    "addr:housenumber":"874",
    "addr:postcode":"j4j 5b6",
    "addr:street":"Rue De Gentilly E",
    "iso:country":"CA",
    "sg:address":"874 Rue DE Gentilly E",
    "sg:city":"Longueuil",
    "sg:classifiers":[
        {
            "category":"Food & Beverages",
            "subcategory":"Groceries & Convenience Stores",
            "type":"Retail Goods"
        }
    ],
    "sg:phone":"+1 450 674 1671",
    "sg:postcode":"J4J 5B6",
    "sg:province":"QC",
    "wof:name":"Depanneur Bellerive Enr",
    "wof:placetype":"venue"
},
  "geometry": {"coordinates":[-73.488953,45.541069],"type":"Point"}
}