{
  "type": "Feature",
  "properties": {
    "addr:full":"9 Pine St N Thorold ON L2V 3Z9",
    "addr:housenumber":"9",
    "addr:postcode":"l2v 3z9",
    "addr:street":"Pine St N",
    "iso:country":"CA",
    "sg:address":"9 Pine St N",
    "sg:city":"Thorold",
    "sg:classifiers":[
        {
            "category":"Shopping",
            "subcategory":"Gifts & Souvenirs",
            "type":"Retail Goods"
        }
    ],
    "sg:phone":"+1 905 227 5687",
    "sg:postcode":"L2V 3Z9",
    "sg:province":"ON",
    "sg:tags":[
        "shop"
    ],
    "wof:name":"You Send me",
    "wof:placetype":"venue"
},
  "geometry": {"coordinates":[-79.20343017579999,43.1254844666],"type":"Point"}
}