{
  "type": "Feature",
  "properties": {
    "addr:full":"2 Pinto Pl Fort Macleod AB T0L 0Z0",
    "addr:housenumber":"2",
    "addr:postcode":"t0l 0z0",
    "addr:street":"Pinto Pl Fort",
    "iso:country":"CA",
    "sg:address":"2 Pinto Pl",
    "sg:city":"Fort Macleod",
    "sg:classifiers":[
        {
            "category":"Real Estate",
            "subcategory":"Developer",
            "type":"Services"
        }
    ],
    "sg:phone":"+1 403 553 2188",
    "sg:postcode":"T0L 0Z0",
    "sg:province":"AB",
    "sg:tags":[
        "mobile",
        "home"
    ],
    "wof:name":"Mac Leod Meadows",
    "wof:placetype":"venue"
},
  "geometry": {"coordinates":[-113.395584106,49.7260742188],"type":"Point"}
}