{
  "type": "Feature",
  "properties": {
    "addr:full":"2315 Patterson Ave Armstrong BC V0E 1B0",
    "addr:housenumber":"2315",
    "addr:postcode":"v0e 1b0",
    "addr:street":"Patterson Ave",
    "iso:country":"CA",
    "sg:address":"2315 Patterson Ave",
    "sg:city":"Armstrong",
    "sg:classifiers":[
        {
            "category":"Organizations",
            "subcategory":"Religious Organization",
            "type":"Services"
        }
    ],
    "sg:phone":"+1 250 546 9366",
    "sg:postcode":"V0E 1B0",
    "sg:province":"BC",
    "sg:tags":[
        "church"
    ],
    "wof:name":"Anglican Church of St James",
    "wof:placetype":"venue"
},
  "geometry": {"coordinates":[-119.189323,50.447388],"type":"Point"}
}