{
  "type": "Feature",
  "properties": {
    "addr:full":"8331 River Rd # 10 Richmond BC V6X 1Y1",
    "addr:housenumber":"8331;10",
    "addr:postcode":"v6x 1y1",
    "addr:street":"River Rd #",
    "iso:country":"CA",
    "sg:address":"8331 River Rd # 10",
    "sg:city":"Richmond",
    "sg:classifiers":[
        {
            "category":"Wholesale",
            "subcategory":"Groceries",
            "type":"Manufacturing & Wholesale Goods"
        }
    ],
    "sg:phone":"+1 604 244 0964",
    "sg:postcode":"V6X 1Y1",
    "sg:province":"BC",
    "sg:tags":[
        "food",
        "grocer",
        "health"
    ],
    "wof:name":"Northern Seas Shark Cartilage",
    "wof:placetype":"venue"
},
  "geometry": {"coordinates":[-123.13388824499999,49.1915435791],"type":"Point"}
}