{
  "type": "Feature",
  "properties": {
    "addr:full":"Saint John NB E2L 2X6",
    "addr:postcode":"e2l 2x6",
    "iso:country":"CA",
    "sg:city":"Saint John",
    "sg:classifiers":[
        {
            "category":"Insurance",
            "subcategory":"Insurance Agent",
            "type":"Services"
        }
    ],
    "sg:phone":"+1 506 642 7065",
    "sg:postcode":"E2L 2X6",
    "sg:province":"NB",
    "wof:name":"Moir Insurance Inc",
    "wof:placetype":"venue"
},
  "geometry": {"coordinates":[-66.051514,45.281166],"type":"Point"}
}