{
  "type": "Feature",
  "properties": {
    "iso:country":"CA",
    "sg:address":"76 St Lawrence Ave E",
    "sg:city":"Madoc",
    "sg:classifiers":[
        {
            "category":"Organizations",
            "subcategory":"Religious Organization",
            "type":"Services"
        }
    ],
    "sg:phone":"+1 613 473 2968",
    "sg:postcode":"K0K 2K0",
    "sg:province":"ON",
    "sg:tags":[
        "church"
    ],
    "wof:name":"Trinity United Church",
    "wof:placetype":"venue"
},
  "geometry": {"coordinates":[-77.4714889526,44.5056037903],"type":"Point"}
}