{
  "type": "Feature",
  "properties": {
    "iso:country":"CA",
    "sg:address":"1430 Henderson Hwy",
    "sg:city":"Winnipeg",
    "sg:classifiers":[
        {
            "category":"Health Services",
            "subcategory":"Doctor",
            "type":"Services"
        }
    ],
    "sg:phone":"+1 204 338 4618",
    "sg:postcode":"R2G 1N4",
    "sg:province":"MB",
    "sg:tags":[
        "dentist"
    ],
    "wof:name":"Nickel, R J DDS",
    "wof:placetype":"venue"
},
  "geometry": {"coordinates":[-97.0866394043,49.9453620911],"type":"Point"}
}