{
  "type": "Feature",
  "properties": {
    "addr:full":"6515 Bonsor Ave Burnaby BC V5H 3E8",
    "addr:housenumber":"6515",
    "addr:postcode":"v5h 3e8",
    "addr:street":"Bonsor Ave",
    "iso:country":"CA",
    "sg:address":"6515 Bonsor Ave",
    "sg:city":"Burnaby",
    "sg:classifiers":[
        {
            "category":"Restaurant",
            "type":"Food & Drink"
        }
    ],
    "sg:phone":"+1 604 437 6338",
    "sg:postcode":"V5H 3E8",
    "sg:province":"BC",
    "sg:tags":[
        "auditorium",
        "rooms",
        "banquet",
        "hall"
    ],
    "wof:name":"Firefighters Banquet Hall",
    "wof:placetype":"venue"
},
  "geometry": {"coordinates":[-122.997421265,49.2246856689],"type":"Point"}
}