{
  "type": "Feature",
  "properties": {
    "addr:full":"160 St Anne's Rd Winnipeg MB R2M 2Z6",
    "addr:housenumber":"160",
    "addr:postcode":"r2m 2z6",
    "addr:street":"St Anne'S Rd",
    "iso:country":"CA",
    "sg:address":"160 St Anne's Rd",
    "sg:city":"Winnipeg",
    "sg:classifiers":[
        {
            "category":"Restaurant",
            "type":"Food & Drink"
        }
    ],
    "sg:phone":"+1 204 987 5553",
    "sg:postcode":"R2M 2Z6",
    "sg:province":"MB",
    "sg:tags":[
        "pizza"
    ],
    "wof:name":"Domino's Pizza",
    "wof:placetype":"venue"
},
  "geometry": {"coordinates":[-97.106621,49.858429],"type":"Point"}
}