{
  "type": "Feature",
  "properties": {
    "addr:full":"Orangeville ON L9W 1H8",
    "addr:postcode":"l9w 1h8",
    "iso:country":"CA",
    "sg:city":"Orangeville",
    "sg:classifiers":[
        {
            "category":"Health Services",
            "subcategory":"Doctor",
            "type":"Services"
        }
    ],
    "sg:phone":"+1 519 938 8000",
    "sg:postcode":"L9W 1H8",
    "sg:province":"ON",
    "sg:tags":[
        "clinic"
    ],
    "wof:name":"Orangeville Family Medical Ctr",
    "wof:placetype":"venue"
},
  "geometry": {"coordinates":[-80.0951156616,43.9206771851],"type":"Point"}
}