{
  "type": "Feature",
  "properties": {
    "addr:full":"55 Boul Sainte-Rose Laval QC H7L 3J9",
    "addr:housenumber":"55",
    "addr:postcode":"h7l 3j9",
    "addr:street":"Boul Sainte-Rose",
    "iso:country":"CA",
    "sg:address":"55 Boul Sainte-Rose",
    "sg:city":"Laval",
    "sg:classifiers":[
        {
            "category":"Professional",
            "subcategory":"Business Services",
            "type":"Services"
        }
    ],
    "sg:phone":"+1 450 624 1414",
    "sg:postcode":"H7L 3J9",
    "sg:province":"QC",
    "sg:tags":[
        "fire",
        "protection"
    ],
    "wof:name":"Giclocept",
    "wof:placetype":"venue"
},
  "geometry": {"coordinates":[-73.744637,45.551567],"type":"Point"}
}