{
  "type": "Feature",
  "properties": {
    "addr:full":"4470 Av Thibault Saint-Hubert QC J3Y 7T9",
    "addr:housenumber":"4470",
    "addr:postcode":"j3y 7t9",
    "addr:street":"Av Thibault",
    "iso:country":"CA",
    "sg:address":"4470 Av Thibault",
    "sg:city":"Saint-Hubert",
    "sg:classifiers":[
        {
            "category":"Wholesale",
            "subcategory":"Electrical",
            "type":"Manufacturing & Wholesale Goods"
        }
    ],
    "sg:phone":"+1 450 656 2759",
    "sg:postcode":"J3Y 7T9",
    "sg:province":"QC",
    "sg:tags":[
        "equipment",
        "electronic",
        "supply"
    ],
    "wof:name":"Solen Electronique Inc",
    "wof:placetype":"venue"
},
  "geometry": {"coordinates":[-73.442565918,45.5044021606],"type":"Point"}
}