{
  "type": "Feature",
  "properties": {
    "addr:full":"877 Rte 116 O Acton Vale QC J0H 1A0",
    "addr:housenumber":"877",
    "addr:postcode":"j0h 1a0",
    "addr:street":"Rte 116 O",
    "iso:country":"CA",
    "sg:address":"877 Rte 116 O",
    "sg:city":"Acton Vale",
    "sg:classifiers":[
        {
            "category":"Retail",
            "subcategory":"Auto Repair",
            "type":"Services"
        }
    ],
    "sg:phone":"+1 450 549 5858",
    "sg:postcode":"J0H 1A0",
    "sg:province":"QC",
    "sg:tags":[
        "repairing",
        "automobile"
    ],
    "wof:name":"B L Auto Electrique & Associe",
    "wof:placetype":"venue"
},
  "geometry": {"coordinates":[-72.5832824707,45.6440925598],"type":"Point"}
}