{
  "type": "Feature",
  "properties": {
    "addr:full":"7 Harvest Park Terr NE Calgary AB T3K 4V9",
    "addr:housenumber":"7",
    "addr:postcode":"t3k 4v9",
    "addr:street":"Harvest Park Terr Ne",
    "iso:country":"CA",
    "sg:address":"7 Harvest Park Terr NE",
    "sg:city":"Calgary",
    "sg:classifiers":[
        {
            "category":"Wholesale",
            "subcategory":"Non-durable Goods",
            "type":"Manufacturing & Wholesale Goods"
        }
    ],
    "sg:phone":"+1 403 226 5925",
    "sg:postcode":"T3K 4V9",
    "sg:province":"AB",
    "sg:tags":[
        "advertising"
    ],
    "wof:name":"Calgary Specialty Advertising",
    "wof:placetype":"venue"
},
  "geometry": {"coordinates":[-114.057579,51.144047],"type":"Point"}
}