{
  "type": "Feature",
  "properties": {
    "addr:full":"1054 Coxwell Ave East York ON M4C 3G5",
    "addr:housenumber":"1054",
    "addr:postcode":"m4c 3g5",
    "addr:street":"Coxwell Ave",
    "iso:country":"CA",
    "sg:address":"1054 Coxwell Ave",
    "sg:city":"East York",
    "sg:classifiers":[
        {
            "category":"Food & Beverages",
            "subcategory":"Groceries & Convenience Stores",
            "type":"Retail Goods"
        }
    ],
    "sg:phone":"+1 416 429 8208",
    "sg:postcode":"M4C 3G5",
    "sg:province":"ON",
    "sg:tags":[
        "grocer"
    ],
    "wof:name":"Wayne's Supermarket",
    "wof:placetype":"venue"
},
  "geometry": {"coordinates":[-79.3293685913,43.6969947815],"type":"Point"}
}