{
  "type": "Feature",
  "properties": {
    "addr:full":"175 School St Liverpool NS B0T 1K0",
    "addr:housenumber":"175",
    "addr:postcode":"b0t 1k0",
    "addr:street":"School St",
    "iso:country":"CA",
    "sg:address":"175 School St",
    "sg:city":"Liverpool",
    "sg:classifiers":[
        {
            "category":"Health Services",
            "subcategory":"Hospital",
            "type":"Services"
        }
    ],
    "sg:phone":"+1 902 354 3436",
    "sg:postcode":"B0T 1K0",
    "sg:province":"NS",
    "wof:name":"Queens General Hospital",
    "wof:placetype":"venue"
},
  "geometry": {"coordinates":[-64.706993,44.037415],"type":"Point"}
}