{
  "type": "Feature",
  "properties": {
    "iso:country":"CA",
    "sg:city":"Lloydminster",
    "sg:classifiers":[
        {
            "category":"Health Services",
            "subcategory":"Nursing And Care Facility",
            "type":"Services"
        }
    ],
    "sg:phone":"+1 306 820 5950",
    "sg:postcode":"S9V 1Z2",
    "sg:province":"SK",
    "sg:tags":[
        "home",
        "convalescent"
    ],
    "wof:name":"Jubilee Home",
    "wof:placetype":"venue"
},
  "geometry": {"coordinates":[-109.991691589,53.2759246826],"type":"Point"}
}