{
  "type": "Feature",
  "properties": {
    "addr:full":"770 Mckay Rd Pickering ON L1W 2Y4",
    "addr:housenumber":"770",
    "addr:postcode":"l1w 2y4",
    "addr:street":"Mckay Rd",
    "iso:country":"CA",
    "sg:address":"770 Mckay Rd",
    "sg:city":"Pickering",
    "sg:classifiers":[
        {
            "category":"Manufacturing",
            "subcategory":"Paper Products",
            "type":"Manufacturing & Wholesale Goods"
        }
    ],
    "sg:phone":"+1 905 683 8235",
    "sg:postcode":"L1W 2Y4",
    "sg:province":"ON",
    "sg:tags":[
        "corrugated",
        "solid",
        "fiber",
        "box"
    ],
    "wof:name":"Cardinal Corrugated Containers",
    "wof:placetype":"venue"
},
  "geometry": {"coordinates":[-79.05661773680001,43.8205680847],"type":"Point"}
}