{
  "type": "Feature",
  "properties": {
    "addr:full":"140 2E Rue Batiscan QC G0X 1A0",
    "addr:housenumber":"140",
    "addr:postcode":"g0x 1a0",
    "addr:street":"2E Rue Batiscan",
    "iso:country":"CA",
    "sg:address":"140 2E Rue",
    "sg:city":"Batiscan",
    "sg:classifiers":[
        {
            "category":"Insurance",
            "subcategory":"Insurance Agent",
            "type":"Services"
        }
    ],
    "sg:phone":"+1 418 362 3108",
    "sg:postcode":"G0X 1A0",
    "sg:province":"QC",
    "wof:name":"Assurances Sylvie Chandonnet",
    "wof:placetype":"venue"
},
  "geometry": {"coordinates":[-72.2525177002,46.4895935059],"type":"Point"}
}