{
  "type": "Feature",
  "properties": {
    "addr:full":"1150 Sanford St Winnipeg MB R3E 2Z9",
    "addr:housenumber":"1150",
    "addr:postcode":"r3e 2z9",
    "addr:street":"Sanford St",
    "iso:country":"CA",
    "sg:address":"1150 Sanford St",
    "sg:city":"Winnipeg",
    "sg:classifiers":[
        {
            "category":"Manufacturing",
            "subcategory":"Building Materials",
            "type":"Manufacturing & Wholesale Goods"
        }
    ],
    "sg:phone":"+1 204 786 1411",
    "sg:postcode":"R3E 2Z9",
    "sg:province":"MB",
    "sg:tags":[
        "door",
        "plywood"
    ],
    "wof:name":"Dormond Industries Ltd",
    "wof:placetype":"venue"
},
  "geometry": {"coordinates":[-97.1937713623,49.8993644714],"type":"Point"}
}