{
  "type": "Feature",
  "properties": {
    "iso:country":"CA",
    "sg:city":"Burnaby",
    "sg:classifiers":[
        {
            "category":"Shopping",
            "subcategory":"Florist",
            "type":"Retail Goods"
        }
    ],
    "sg:phone":"+1 604 439 0272",
    "sg:postcode":"V5H 4L7",
    "sg:province":"BC",
    "wof:name":"A Flower's Touch",
    "wof:placetype":"venue"
},
  "geometry": {"coordinates":[-123.004394531,49.2278442383],"type":"Point"}
}