{
  "type": "Feature",
  "properties": {
    "addr:full":"1625 Kenaston Blvd Winnipeg MB R3P 2M4",
    "addr:housenumber":"1625",
    "addr:postcode":"r3p 2m4",
    "addr:street":"Kenaston Blvd",
    "iso:country":"CA",
    "sg:address":"1625 Kenaston Blvd",
    "sg:city":"Winnipeg",
    "sg:classifiers":[
        {
            "category":"Food & Beverages",
            "subcategory":"Groceries & Convenience Stores",
            "type":"Retail Goods"
        }
    ],
    "sg:phone":"+1 204 488 9404",
    "sg:postcode":"R3P 2M4",
    "sg:province":"MB",
    "sg:tags":[
        "florist"
    ],
    "wof:name":"Canada Safeway Ltd",
    "wof:placetype":"venue"
},
  "geometry": {"coordinates":[-97.2033920288,49.824546814],"type":"Point"}
}