{
  "type": "Feature",
  "properties": {
    "addr:full":"150 Leroux St Alexandria ON K0C 1A0",
    "addr:housenumber":"150",
    "addr:postcode":"k0c 1a0",
    "addr:street":"Leroux St",
    "iso:country":"CA",
    "sg:address":"150 Leroux St",
    "sg:city":"Alexandria",
    "sg:phone":"+1 613 525 5050",
    "sg:postcode":"K0C 1A0",
    "sg:province":"ON",
    "sg:tags":[
        "material",
        "fixture",
        "display",
        "store"
    ],
    "wof:name":"Premier Wire Ltd",
    "wof:placetype":"venue"
},
  "geometry": {"coordinates":[-74.648804,45.316971],"type":"Point"}
}