{
  "type": "Feature",
  "properties": {
    "addr:full":"125 8th Ave NW Milk River AB T0K 1M0",
    "addr:housenumber":"125",
    "addr:postcode":"t0k 1m0",
    "addr:street":"8Th Ave Nw Milk",
    "iso:country":"CA",
    "sg:address":"125 8th Ave NW",
    "sg:city":"Milk River",
    "sg:classifiers":[
        {
            "category":"Utilities",
            "subcategory":"Natural Gas",
            "type":"Services"
        }
    ],
    "sg:phone":"+1 403 647 3588",
    "sg:postcode":"T0K 1M0",
    "sg:province":"AB",
    "sg:tags":[
        "company"
    ],
    "wof:name":"Chinook Gas CO-OP Ltd",
    "wof:placetype":"venue"
},
  "geometry": {"coordinates":[-112.08782959,49.1564254761],"type":"Point"}
}