{
  "type": "Feature",
  "properties": {
    "addr:full":"5299 Dorchester Rd Harrietsville ON N0L 1N0",
    "addr:housenumber":"5299",
    "addr:postcode":"n0l 1n0",
    "addr:street":"Dorchester Rd",
    "iso:country":"CA",
    "sg:address":"5299 Dorchester Rd",
    "sg:city":"Harrietsville",
    "sg:classifiers":[
        {
            "category":"Autos & Motor Vehicles",
            "subcategory":"Automobile Sales",
            "type":"Retail Goods"
        }
    ],
    "sg:phone":"+1 519 269 3256",
    "sg:postcode":"N0L 1N0",
    "sg:province":"ON",
    "sg:tags":[
        "car",
        "dealer"
    ],
    "wof:name":"Inter Trader Auto Sales",
    "wof:placetype":"venue"
},
  "geometry": {"coordinates":[-81.0477523804,42.9070701599],"type":"Point"}
}