{
  "type": "Feature",
  "properties": {
    "addr:full":"153 112 Rte W Marbleton QC J0B 2L0",
    "addr:housenumber":"112",
    "addr:postcode":"j0b 2l0",
    "addr:street":"Rte W Marbleton",
    "iso:country":"CA",
    "sg:address":"153 112 Rte W",
    "sg:city":"Marbleton",
    "sg:classifiers":[
        {
            "category":"Manufacturing",
            "subcategory":"Lumber",
            "type":"Manufacturing & Wholesale Goods"
        }
    ],
    "sg:phone":"+1 819 887 6621",
    "sg:postcode":"J0B 2L0",
    "sg:province":"QC",
    "sg:tags":[
        "syrup",
        "maple",
        "sugar"
    ],
    "wof:name":"Erabliere Pare",
    "wof:placetype":"venue"
},
  "geometry": {"coordinates":[-71.591415,45.634167],"type":"Point"}
}