{
  "type": "Feature",
  "properties": {
    "addr:full":"4809 50 Ave Vegreville AB T9C 1K9",
    "addr:housenumber":"4809",
    "addr:postcode":"t9c 1k9",
    "addr:street":"50 Ave",
    "iso:country":"CA",
    "sg:address":"4809 50 Ave",
    "sg:city":"Vegreville",
    "sg:classifiers":[
        {
            "category":"Government",
            "subcategory":"Office",
            "type":"Public Place"
        }
    ],
    "sg:phone":"+1 780 632 5415",
    "sg:postcode":"T9C 1K9",
    "sg:province":"AB",
    "wof:name":"Alberta Provincial Court Dept",
    "wof:placetype":"venue"
},
  "geometry": {"coordinates":[-112.048202515,53.4927215576],"type":"Point"}
}