{
  "type": "Feature",
  "properties": {
    "iso:country":"CA",
    "sg:address":"4231 Boul Notre-Dame",
    "sg:city":"Laval",
    "sg:classifiers":[
        {
            "category":"Retail",
            "subcategory":"Laundry & Dry Cleaning",
            "type":"Services"
        }
    ],
    "sg:phone":"+1 450 681 6668",
    "sg:postcode":"H7W 1T3",
    "sg:province":"QC",
    "wof:name":"Buanderie Le Pelican",
    "wof:placetype":"venue"
},
  "geometry": {"coordinates":[-73.756226,45.538364],"type":"Point"}
}