{
  "type": "Feature",
  "properties": {
    "addr:full":"1435 Mountain Rd Moncton NB E1G 1A3",
    "addr:housenumber":"1435",
    "addr:postcode":"e1g 1a3",
    "addr:street":"Mountain Rd",
    "iso:country":"CA",
    "sg:address":"1435 Mountain Rd",
    "sg:city":"Moncton",
    "sg:classifiers":[
        {
            "category":"Health Services",
            "subcategory":"Doctor",
            "type":"Services"
        }
    ],
    "sg:phone":"+1 506 857 2187",
    "sg:postcode":"E1G 1A3",
    "sg:province":"NB",
    "sg:tags":[
        "dentist"
    ],
    "wof:name":"Mountain Road Pro Dental Ctr",
    "wof:placetype":"venue"
},
  "geometry": {"coordinates":[-64.8361663818,46.1137313843],"type":"Point"}
}