{
  "type": "Feature",
  "properties": {
    "addr:full":"14799 Highway 4 St Peters NS B0E 3B0",
    "addr:housenumber":"14799",
    "addr:postcode":"b0e 3b0",
    "addr:street":"Highway 4",
    "iso:country":"CA",
    "sg:address":"14799 Highway 4",
    "sg:city":"St Peters",
    "sg:classifiers":[
        {
            "category":"Professional",
            "subcategory":"Business Services",
            "type":"Services"
        }
    ],
    "sg:phone":"+1 902 535 3375",
    "sg:postcode":"B0E 3B0",
    "sg:province":"NS",
    "sg:tags":[
        "fire",
        "protection"
    ],
    "wof:name":"Red Islands Fire Dept",
    "wof:placetype":"venue"
},
  "geometry": {"coordinates":[-60.1825561523,46.1308250427],"type":"Point"}
}