{
  "type": "Feature",
  "properties": {
    "addr:full":"3115 Harriet Rd Victoria BC V9A 1T7",
    "addr:housenumber":"3115",
    "addr:postcode":"v9a 1t7",
    "addr:street":"Harriet Rd",
    "iso:country":"CA",
    "sg:address":"3115 Harriet Rd",
    "sg:city":"Victoria",
    "sg:classifiers":[
        {
            "category":"Building & Trades",
            "subcategory":"Plumbing",
            "type":"Services"
        }
    ],
    "sg:phone":"+1 250 381 2622",
    "sg:postcode":"V9A 1T7",
    "sg:province":"BC",
    "sg:tags":[
        "contractor"
    ],
    "wof:name":"Aquarian Plumbing Svc",
    "wof:placetype":"venue"
},
  "geometry": {"coordinates":[-123.386101,48.447777],"type":"Point"}
}