{
  "type": "Feature",
  "properties": {
    "iso:country":"CA",
    "sg:city":"Nepean",
    "sg:classifiers":[
        {
            "category":"Shopping",
            "subcategory":"Computers & Home Electronics",
            "type":"Retail Goods"
        }
    ],
    "sg:phone":"+1 613 224 4045",
    "sg:postcode":"K2E 8A5",
    "sg:province":"ON",
    "sg:tags":[
        "equipment",
        "dealer"
    ],
    "wof:name":"Onward Computer Systems",
    "wof:placetype":"venue"
},
  "geometry": {"coordinates":[-75.7052536011,45.3309593201],"type":"Point"}
}