{
  "type": "Feature",
  "properties": {
    "addr:full":"235 Wellington St W Sault Ste Marie ON P6A 1H6",
    "addr:housenumber":"235",
    "addr:postcode":"p6a 1h6",
    "addr:street":"Wellington St W",
    "iso:country":"CA",
    "sg:address":"235 Wellington St W",
    "sg:city":"Sault Ste Marie",
    "sg:classifiers":[
        {
            "category":"Government",
            "subcategory":"Office",
            "type":"Public Place"
        }
    ],
    "sg:phone":"+1 705 759 5377",
    "sg:postcode":"P6A 1H6",
    "sg:province":"ON",
    "sg:tags":[
        "village"
    ],
    "wof:name":"Sault Ste Marie Steelton Sr",
    "wof:placetype":"venue"
},
  "geometry": {"coordinates":[-84.345253,46.524506],"type":"Point"}
}