{
  "type": "Feature",
  "properties": {
    "addr:full":"2470 Dixon Rd Powell River BC V8A 5C1",
    "addr:housenumber":"2470",
    "addr:postcode":"v8a 5c1",
    "addr:street":"Dixon Rd",
    "iso:country":"CA",
    "sg:address":"2470 Dixon Rd",
    "sg:city":"Powell River",
    "sg:classifiers":[
        {
            "category":"Manufacturing",
            "subcategory":"Lumber",
            "type":"Manufacturing & Wholesale Goods"
        }
    ],
    "sg:phone":"+1 604 487 1982",
    "sg:postcode":"V8A 5C1",
    "sg:province":"BC",
    "sg:tags":[
        "company",
        "logging"
    ],
    "wof:name":"Jepson Log Sorting Ltd",
    "wof:placetype":"venue"
},
  "geometry": {"coordinates":[-124.344666,49.782841],"type":"Point"}
}