{
  "type": "Feature",
  "properties": {
    "iso:country":"CA",
    "sg:address":"410 Sunset Dr",
    "sg:city":"St Thomas",
    "sg:classifiers":[
        {
            "category":"Social Services",
            "type":"Services"
        }
    ],
    "sg:phone":"+1 519 631 1492",
    "sg:postcode":"N5R 3C7",
    "sg:province":"ON",
    "sg:tags":[
        "organization",
        "welfare"
    ],
    "wof:name":"Family & Children's Svc",
    "wof:placetype":"venue"
},
  "geometry": {"coordinates":[-81.21231079099999,42.7784690857],"type":"Point"}
}