{
  "type": "Feature",
  "properties": {
    "addr:full":"Grande Prairie AB T8V 7G2",
    "addr:postcode":"t8v 7g2",
    "iso:country":"CA",
    "sg:city":"Grande Prairie",
    "sg:classifiers":[
        {
            "category":"Mining & Drilling",
            "type":"Manufacturing & Wholesale Goods"
        }
    ],
    "sg:phone":"+1 780 538 1141",
    "sg:postcode":"T8V 7G2",
    "sg:province":"AB",
    "sg:tags":[
        "field",
        "oil"
    ],
    "wof:name":"Brenntag Canada",
    "wof:placetype":"venue"
},
  "geometry": {"coordinates":[-118.792389,55.206921],"type":"Point"}
}