{
  "type": "Feature",
  "properties": {
    "addr:full":"379 Boul Bourque Omerville QC J1X 4E9",
    "addr:housenumber":"379",
    "addr:postcode":"j1x 4e9",
    "addr:street":"Boul Bourque",
    "iso:country":"CA",
    "sg:address":"379 Boul Bourque",
    "sg:city":"Omerville",
    "sg:classifiers":[
        {
            "category":"Restaurant",
            "type":"Food & Drink"
        }
    ],
    "sg:phone":"+1 819 843 7113",
    "sg:postcode":"J1X 4E9",
    "sg:province":"QC",
    "wof:name":"Restaurant LA Falaise D'Orford",
    "wof:placetype":"venue"
},
  "geometry": {"coordinates":[-72.112579,45.290115],"type":"Point"}
}