{
  "type": "Feature",
  "properties": {
    "addr:full":"90 Rue Des Grands-Lacs Saint-Augustin-DE-Desmaures QC G3A 2K1",
    "addr:housenumber":"90",
    "addr:postcode":"g3a 2k1",
    "addr:street":"Rue Des Grands-Lacs",
    "iso:country":"CA",
    "sg:address":"90 Rue Des Grands-Lacs",
    "sg:city":"Saint-Augustin-DE-Desmaures",
    "sg:classifiers":[
        {
            "category":"Wholesale",
            "subcategory":"Construction Materials",
            "type":"Manufacturing & Wholesale Goods"
        }
    ],
    "sg:phone":"+1 418 878 4252",
    "sg:postcode":"G3A 2K1",
    "sg:province":"QC",
    "sg:tags":[
        "lumber"
    ],
    "wof:name":"Materiaux DE Construction",
    "wof:placetype":"venue"
},
  "geometry": {"coordinates":[-71.44700622560001,46.7499656677],"type":"Point"}
}