{
  "type": "Feature",
  "properties": {
    "iso:country":"CA",
    "sg:address":"571 Welham Rd",
    "sg:city":"Barrie",
    "sg:classifiers":[
        {
            "category":"Manufacturing",
            "subcategory":"Glass & Minerals",
            "type":"Manufacturing & Wholesale Goods"
        }
    ],
    "sg:phone":"+1 705 725 1176",
    "sg:postcode":"L4N 8Z6",
    "sg:province":"ON",
    "sg:tags":[
        "granite",
        "monument"
    ],
    "wof:name":"Regal Monuments Inc",
    "wof:placetype":"venue"
},
  "geometry": {"coordinates":[-79.67003631590001,44.3411254883],"type":"Point"}
}