{
  "type": "Feature",
  "properties": {
    "addr:full":"215 Walmer Rd Toronto ON M5R 3P7",
    "addr:housenumber":"215",
    "addr:postcode":"m5r 3p7",
    "addr:street":"Walmer Rd",
    "iso:country":"CA",
    "sg:address":"215 Walmer Rd",
    "sg:city":"Toronto",
    "sg:classifiers":[
        {
            "category":"Banks & Credit Unions",
            "subcategory":"Investment Brokerage",
            "type":"Services"
        }
    ],
    "sg:phone":"+1 416 924 9260",
    "sg:postcode":"M5R 3P7",
    "sg:province":"ON",
    "sg:tags":[
        "consultant",
        "financing"
    ],
    "wof:name":"Four Line Corp",
    "wof:placetype":"venue"
},
  "geometry": {"coordinates":[-79.4086685181,43.6761398315],"type":"Point"}
}