{
  "type": "Feature",
  "properties": {
    "addr:full":"Quispamsis NB E2E 4R2",
    "addr:postcode":"e2e 4r2",
    "iso:country":"CA",
    "sg:city":"Quispamsis",
    "sg:classifiers":[
        {
            "category":"Health Services",
            "subcategory":"Optometrist",
            "type":"Services"
        }
    ],
    "sg:phone":"+1 506 849 3937",
    "sg:postcode":"E2E 4R2",
    "sg:province":"NB",
    "wof:name":"Professional Corp Landing Clnc",
    "wof:placetype":"venue"
},
  "geometry": {"coordinates":[-65.9578170776,45.413269043],"type":"Point"}
}