{
  "type": "Feature",
  "properties": {
    "addr:full":"845 Rte Marie-Victorin # 4 Saint-Nicolas QC G7A 3S8",
    "addr:housenumber":"845;# 4",
    "addr:postcode":"g7a 3s8",
    "addr:street":"Rte Marie-Victorin;Saint-Nicolas",
    "iso:country":"CA",
    "sg:address":"845 Rte Marie-Victorin # 4",
    "sg:city":"Saint-Nicolas",
    "sg:classifiers":[
        {
            "category":"Personal",
            "subcategory":"Beauty Salon",
            "type":"Services"
        }
    ],
    "sg:phone":"+1 418 831 2754",
    "sg:postcode":"G7A 3S8",
    "sg:province":"QC",
    "wof:name":"Institut Renaissance",
    "wof:placetype":"venue"
},
  "geometry": {"coordinates":[-71.34831200000001,46.715527],"type":"Point"}
}