{
  "type": "Feature",
  "properties": {
    "addr:full":"Sussex NB E4E 2P1",
    "addr:postcode":"e4e 2p1",
    "iso:country":"CA",
    "sg:city":"Sussex",
    "sg:classifiers":[
        {
            "category":"Health Services",
            "subcategory":"Doctor",
            "type":"Services"
        }
    ],
    "sg:phone":"+1 506 433 4672",
    "sg:postcode":"E4E 2P1",
    "sg:province":"NB",
    "sg:tags":[
        "physician",
        "surgeon"
    ],
    "wof:name":"Phillips, M Elizabeth MD",
    "wof:placetype":"venue"
},
  "geometry": {"coordinates":[-65.4896621704,45.7249069214],"type":"Point"}
}