{
  "type": "Feature",
  "properties": {
    "addr:full":"107 King St W Dundas ON L9H 1V1",
    "addr:housenumber":"107",
    "addr:postcode":"l9h 1v1",
    "addr:street":"King St W",
    "iso:country":"CA",
    "sg:address":"107 King St W",
    "sg:city":"Dundas",
    "sg:classifiers":[
        {
            "category":"Health Services",
            "subcategory":"Doctor",
            "type":"Services"
        }
    ],
    "sg:phone":"+1 905 628 0054",
    "sg:postcode":"L9H 1V1",
    "sg:province":"ON",
    "sg:tags":[
        "physician",
        "surgeon"
    ],
    "wof:name":"Seigel, S A MD",
    "wof:placetype":"venue"
},
  "geometry": {"coordinates":[-79.95822099999999,43.266811],"type":"Point"}
}