{
  "type": "Feature",
  "properties": {
    "addr:full":"6685 Rue Hochelaga Montreal QC H1N 1Y1",
    "addr:housenumber":"6685",
    "addr:postcode":"h1n 1y1",
    "addr:street":"Rue Hochelaga",
    "iso:country":"CA",
    "sg:address":"6685 Rue Hochelaga",
    "sg:city":"Montreal",
    "sg:classifiers":[
        {
            "category":"Retail",
            "subcategory":"Auto Repair",
            "type":"Services"
        }
    ],
    "sg:phone":"+1 514 252 9765",
    "sg:postcode":"H1N 1Y1",
    "sg:province":"QC",
    "sg:tags":[
        "repairing",
        "automobile"
    ],
    "wof:name":"Station Service Robert Gagnon",
    "wof:placetype":"venue"
},
  "geometry": {"coordinates":[-73.5319900513,45.580039978],"type":"Point"}
}