{
  "type": "Feature",
  "properties": {
    "addr:full":"Port Coquitlam BC V3C 4K9",
    "addr:postcode":"v3c 4k9",
    "iso:country":"CA",
    "sg:city":"Port Coquitlam",
    "sg:classifiers":[
        {
            "category":"Building & Trades",
            "subcategory":"Construction",
            "type":"Services"
        }
    ],
    "sg:phone":"+1 604 552 6120",
    "sg:postcode":"V3C 4K9",
    "sg:province":"BC",
    "sg:tags":[
        "maker",
        "cabinet"
    ],
    "wof:name":"Sunny Custom Cabinets",
    "wof:placetype":"venue"
},
  "geometry": {"coordinates":[-122.765693665,49.2531585693],"type":"Point"}
}