{
  "type": "Feature",
  "properties": {
    "addr:full":"Hwy 17 W Dryden ON P8N 2Y7",
    "addr:postcode":"p8n 2y7",
    "addr:street":"Hwy 17 W",
    "iso:country":"CA",
    "sg:address":"Hwy 17 W",
    "sg:city":"Dryden",
    "sg:classifiers":[
        {
            "category":"Home & Garden",
            "subcategory":"Carpets & Floor Coverings",
            "type":"Retail Goods"
        }
    ],
    "sg:phone":"+1 807 223 2909",
    "sg:postcode":"P8N 2Y7",
    "sg:province":"ON",
    "sg:tags":[
        "material",
        "rug"
    ],
    "wof:name":"Guenther's Flooring & Window",
    "wof:placetype":"venue"
},
  "geometry": {"coordinates":[-92.71369199999999,49.785564],"type":"Point"}
}