{
  "type": "Feature",
  "properties": {
    "iso:country":"CA",
    "sg:address":"3539 Boul Saint-Charles",
    "sg:city":"Kirkland",
    "sg:classifiers":[
        {
            "category":"Professional",
            "subcategory":"Management & Consulting",
            "type":"Services"
        }
    ],
    "sg:phone":"+1 514 694 9420",
    "sg:postcode":"H9H 3C4",
    "sg:province":"QC",
    "sg:tags":[
        "consultant",
        "business"
    ],
    "wof:name":"Bids Quebec",
    "wof:placetype":"venue"
},
  "geometry": {"coordinates":[-73.862366,45.456474],"type":"Point"}
}