{
  "type": "Feature",
  "properties": {
    "iso:country":"CA",
    "sg:address":"14 Bay Road Dr",
    "sg:city":"Nelson House",
    "sg:classifiers":[
        {
            "category":"Organizations",
            "subcategory":"Community Association",
            "type":"Services"
        }
    ],
    "sg:phone":"+1 204 484 2341",
    "sg:postcode":"R0B 1A0",
    "sg:province":"MB",
    "sg:tags":[
        "native"
    ],
    "wof:name":"Ncn Family & Comm Wellness",
    "wof:placetype":"venue"
},
  "geometry": {"coordinates":[-98.86893463129999,55.7969436646],"type":"Point"}
}