{
  "type": "Feature",
  "properties": {
    "addr:full":"9550 Boul DE L'Ormiere # 507 Quebec QC G2B 3Z6",
    "addr:housenumber":"9550",
    "addr:postcode":"g2b 3z6",
    "addr:street":"Boul De L'Ormiere # 507",
    "iso:country":"CA",
    "sg:address":"9550 Boul DE L'Ormiere # 507",
    "sg:city":"Quebec",
    "sg:classifiers":[
        {
            "category":"Shopping",
            "subcategory":"Pharmacy",
            "type":"Retail Goods"
        }
    ],
    "sg:phone":"+1 418 842 9221",
    "sg:postcode":"G2B 3Z6",
    "sg:province":"QC",
    "wof:name":"Brunet",
    "wof:placetype":"venue"
},
  "geometry": {"coordinates":[-71.339935,46.824921],"type":"Point"}
}