{
  "type": "Feature",
  "properties": {
    "addr:full":"1 Cross St Dundas ON L9H 2R3",
    "addr:housenumber":"1",
    "addr:postcode":"l9h 2r3",
    "addr:street":"Cross St",
    "iso:country":"CA",
    "sg:address":"1 Cross St",
    "sg:city":"Dundas",
    "sg:classifiers":[
        {
            "category":"Real Estate",
            "subcategory":"Real Estate Agent",
            "type":"Services"
        }
    ],
    "sg:phone":"+1 905 389 7777",
    "sg:postcode":"L9H 2R3",
    "sg:province":"ON",
    "wof:name":"Coldwell Banker Amalfi Realty",
    "wof:placetype":"venue"
},
  "geometry": {"coordinates":[-79.95360599999999,43.26622],"type":"Point"}
}