{
  "type": "Feature",
  "properties": {
    "addr:full":"30 Ruth Ave Mount Pearl NL A1N 1H7",
    "addr:housenumber":"30",
    "addr:postcode":"a1n 1h7",
    "addr:street":"Ruth Ave",
    "iso:country":"CA",
    "sg:address":"30 Ruth Ave",
    "sg:city":"Mount Pearl",
    "sg:classifiers":[
        {
            "category":"Building & Trades",
            "subcategory":"Cleaning & Sanitation",
            "type":"Services"
        }
    ],
    "sg:phone":"+1 709 368 7663",
    "sg:postcode":"A1N 1H7",
    "sg:province":"NL",
    "sg:tags":[
        "janitor"
    ],
    "wof:name":"Walsh's Cleaning & Janitorial",
    "wof:placetype":"venue"
},
  "geometry": {"coordinates":[-52.812984,47.520031],"type":"Point"}
}