{
  "type": "Feature",
  "properties": {
    "iso:country":"CA",
    "sg:address":"2499 Nanaimo St",
    "sg:city":"Vancouver",
    "sg:classifiers":[
        {
            "category":"Travel",
            "subcategory":"Travel Agent",
            "type":"Entertainment"
        }
    ],
    "sg:phone":"+1 604 254 4433",
    "sg:postcode":"V5N 5E5",
    "sg:province":"BC",
    "sg:tags":[
        "agency",
        "bureau"
    ],
    "wof:name":"Sena Travel",
    "wof:placetype":"venue"
},
  "geometry": {"coordinates":[-123.05668640099999,49.2622451782],"type":"Point"}
}