{
  "type": "Feature",
  "properties": {
    "iso:country":"CA",
    "sg:address":"85 Rue Drummond",
    "sg:city":"Granby",
    "sg:classifiers":[
        {
            "category":"Personal",
            "subcategory":"Beauty Salon",
            "type":"Services"
        }
    ],
    "sg:phone":"+1 450 372 3062",
    "sg:postcode":"J2G 2S7",
    "sg:province":"QC",
    "wof:name":"Salon Sevigny Madeleine",
    "wof:placetype":"venue"
},
  "geometry": {"coordinates":[-72.71547698969999,45.398235321],"type":"Point"}
}