{
  "type": "Feature",
  "properties": {
    "addr:full":"654 Mcgee St Winnipeg MB R3E 1W8",
    "addr:housenumber":"654",
    "addr:postcode":"r3e 1w8",
    "addr:street":"Mcgee St",
    "iso:country":"CA",
    "sg:address":"654 Mcgee St",
    "sg:city":"Winnipeg",
    "sg:classifiers":[
        {
            "category":"Manufacturing",
            "subcategory":"Printing",
            "type":"Manufacturing & Wholesale Goods"
        }
    ],
    "sg:phone":"+1 204 775 9986",
    "sg:postcode":"R3E 1W8",
    "sg:province":"MB",
    "sg:tags":[
        "printer"
    ],
    "wof:name":"Econo Job Printers Ltd",
    "wof:placetype":"venue"
},
  "geometry": {"coordinates":[-97.1606063843,49.8983917236],"type":"Point"}
}