{
  "type": "Feature",
  "properties": {
    "addr:full":"Vancouver BC V5Z 2M9",
    "addr:postcode":"v5z 2m9",
    "iso:country":"CA",
    "sg:city":"Vancouver",
    "sg:classifiers":[
        {
            "category":"Shopping",
            "subcategory":"Department Store",
            "type":"Retail Goods"
        }
    ],
    "sg:phone":"+1 604 261 6234",
    "sg:postcode":"V5Z 2M9",
    "sg:province":"BC",
    "wof:name":"Zellers",
    "wof:placetype":"venue"
},
  "geometry": {"coordinates":[-123.117676,49.233551],"type":"Point"}
}