{
  "type": "Feature",
  "properties": {
    "addr:full":"345 White Lake Rd Arnprior ON K7S 3G9",
    "addr:housenumber":"345",
    "addr:postcode":"k7s 3g9",
    "addr:street":"White Lake Rd",
    "iso:country":"CA",
    "sg:address":"345 White Lake Rd",
    "sg:city":"Arnprior",
    "sg:classifiers":[
        {
            "category":"Restaurant",
            "type":"Food & Drink"
        }
    ],
    "sg:phone":"+1 613 623 9508",
    "sg:postcode":"K7S 3G9",
    "sg:province":"ON",
    "sg:tags":[
        "sandwich"
    ],
    "wof:name":"Subway Sandwiches & Salads",
    "wof:placetype":"venue"
},
  "geometry": {"coordinates":[-76.368752,45.423733],"type":"Point"}
}