{
  "type": "Feature",
  "properties": {
    "addr:full":"324 Ch DE LA Rabastaliere O Saint-Bruno QC J3V 1Z7",
    "addr:housenumber":"324",
    "addr:postcode":"j3v 1z7",
    "addr:street":"Ch De La Rabastaliere O",
    "iso:country":"CA",
    "sg:address":"324 Ch DE LA Rabastaliere O",
    "sg:city":"Saint-Bruno",
    "sg:classifiers":[
        {
            "category":"Building & Trades",
            "subcategory":"Electrical",
            "type":"Services"
        }
    ],
    "sg:phone":"+1 450 653 4290",
    "sg:postcode":"J3V 1Z7",
    "sg:province":"QC",
    "sg:tags":[
        "electric",
        "contractor"
    ],
    "wof:name":"Bcp Electrique Inc",
    "wof:placetype":"venue"
},
  "geometry": {"coordinates":[-71.675522,48.471771],"type":"Point"}
}