{
  "type": "Feature",
  "properties": {
    "iso:country":"CA",
    "sg:address":"380 Main St",
    "sg:city":"Mattawa",
    "sg:classifiers":[
        {
            "category":"Health Services",
            "subcategory":"Chiropractor",
            "type":"Services"
        }
    ],
    "sg:phone":"+1 705 744 4440",
    "sg:postcode":"P0H 1V0",
    "sg:province":"ON",
    "wof:name":"Ethier Chiropractic Wellness",
    "wof:placetype":"venue"
},
  "geometry": {"coordinates":[-78.70397949220001,46.317779541],"type":"Point"}
}