{
  "type": "Feature",
  "properties": {
    "iso:country":"CA",
    "sg:city":"Toronto",
    "sg:classifiers":[
        {
            "category":"Health Services",
            "subcategory":"Doctor",
            "type":"Services"
        }
    ],
    "sg:phone":"+1 416 652 3226",
    "sg:postcode":"M6H 4H4",
    "sg:province":"ON",
    "sg:tags":[
        "physician",
        "surgeon"
    ],
    "wof:name":"Papini, O F MD",
    "wof:placetype":"venue"
},
  "geometry": {"coordinates":[-79.442329,43.676456],"type":"Point"}
}