{
  "type": "Feature",
  "properties": {
    "addr:full":"4234 Rue Jean-Talon E Saint-Leonard QC H1S 1J7",
    "addr:housenumber":"4234",
    "addr:postcode":"h1s 1j7",
    "addr:street":"Rue Jean-Talon E",
    "iso:country":"CA",
    "sg:address":"4234 Rue Jean-Talon E",
    "sg:city":"Saint-Leonard",
    "sg:classifiers":[
        {
            "category":"Home & Garden",
            "subcategory":"Household Appliances",
            "type":"Retail Goods"
        }
    ],
    "sg:phone":"+1 514 729 1809",
    "sg:postcode":"H1S 1J7",
    "sg:province":"QC",
    "sg:tags":[
        "machine",
        "sewing"
    ],
    "wof:name":"Centre DE Couture Metro Inc",
    "wof:placetype":"venue"
},
  "geometry": {"coordinates":[-73.59024047849999,45.567779541],"type":"Point"}
}