{
  "type": "Feature",
  "properties": {
    "addr:full":"3509 35 St Whitecourt AB T7S 1N3",
    "addr:housenumber":"3509",
    "addr:postcode":"t7s 1n3",
    "addr:street":"35 St",
    "iso:country":"CA",
    "sg:address":"3509 35 St",
    "sg:city":"Whitecourt",
    "sg:classifiers":[
        {
            "category":"Building & Trades",
            "subcategory":"Electrical",
            "type":"Services"
        }
    ],
    "sg:phone":"+1 780 706 3226",
    "sg:postcode":"T7S 1N3",
    "sg:province":"AB",
    "sg:tags":[
        "electric",
        "contractor"
    ],
    "wof:name":"Tschigerl Electrical Contract",
    "wof:placetype":"venue"
},
  "geometry": {"coordinates":[-115.651641846,54.1223678589],"type":"Point"}
}