{
  "type": "Feature",
  "properties": {
    "addr:full":"235 Rue Valois Vaudreuil-Dorion QC J7V 1T2",
    "addr:housenumber":"235",
    "addr:postcode":"j7v 1t2",
    "addr:street":"Rue Valois",
    "iso:country":"CA",
    "sg:address":"235 Rue Valois",
    "sg:city":"Vaudreuil-Dorion",
    "sg:classifiers":[
        {
            "category":"Government",
            "subcategory":"Office",
            "type":"Public Place"
        }
    ],
    "sg:phone":"+1 450 424 7250",
    "sg:postcode":"J7V 1T2",
    "sg:province":"QC",
    "sg:tags":[
        "village"
    ],
    "wof:name":"Dorion Centre Age D'Or",
    "wof:placetype":"venue"
},
  "geometry": {"coordinates":[-74.016655,45.384579],"type":"Point"}
}