{
  "type": "Feature",
  "properties": {
    "addr:full":"Saint-Pie-DE-Guire QC J0G 1R0",
    "addr:postcode":"j0g 1r0",
    "iso:country":"CA",
    "sg:city":"Saint-Pie-DE-Guire",
    "sg:classifiers":[
        {
            "category":"Retail",
            "subcategory":"Auto Repair",
            "type":"Services"
        }
    ],
    "sg:phone":"+1 450 784 2222",
    "sg:postcode":"J0G 1R0",
    "sg:province":"QC",
    "sg:tags":[
        "repairing",
        "automobile"
    ],
    "wof:name":"Garage Deragon & Freres",
    "wof:placetype":"venue"
},
  "geometry": {"coordinates":[-72.750038147,46.0012245178],"type":"Point"}
}