{
  "type": "Feature",
  "properties": {
    "addr:full":"6440 Rue DE Terrebonne Montreal QC H4B 1B1",
    "addr:housenumber":"6440",
    "addr:postcode":"h4b 1b1",
    "addr:street":"Rue De Terrebonne",
    "iso:country":"CA",
    "sg:address":"6440 Rue DE Terrebonne",
    "sg:city":"Montreal",
    "sg:classifiers":[
        {
            "category":"Education",
            "subcategory":"School",
            "type":"Public Place"
        }
    ],
    "sg:phone":"+1 514 369 0070",
    "sg:postcode":"H4B 1B1",
    "sg:province":"QC",
    "wof:name":"St Monica Ecoles",
    "wof:placetype":"venue"
},
  "geometry": {"coordinates":[-73.63439200000001,45.467396],"type":"Point"}
}