{
  "type": "Feature",
  "properties": {
    "addr:full":"14 Glenwood Dr Truro NS B2N 6V9",
    "addr:housenumber":"14",
    "addr:postcode":"b2n 6v9",
    "addr:street":"Glenwood Dr",
    "iso:country":"CA",
    "sg:address":"14 Glenwood Dr",
    "sg:city":"Truro",
    "sg:classifiers":[
        {
            "category":"Shopping",
            "type":"Retail Goods"
        }
    ],
    "sg:phone":"+1 902 893 1161",
    "sg:postcode":"B2N 6V9",
    "sg:province":"NS",
    "sg:tags":[
        "trophy",
        "medal",
        "award"
    ],
    "wof:name":"A1 Trophies & Promotional Prod",
    "wof:placetype":"venue"
},
  "geometry": {"coordinates":[-63.2928733826,45.3506317139],"type":"Point"}
}