{
  "type": "Feature",
  "properties": {
    "iso:country":"CA",
    "sg:address":"PO Box 4728 STN Main",
    "sg:city":"Ponoka",
    "sg:classifiers":[
        {
            "category":"Shopping",
            "type":"Retail Goods"
        }
    ],
    "sg:phone":"+1 780 372 9120",
    "sg:postcode":"T4J 1S5",
    "sg:province":"AB",
    "sg:tags":[
        "chemical",
        "agricultural"
    ],
    "wof:name":"Cashchem Limited",
    "wof:placetype":"venue"
},
  "geometry": {"coordinates":[-113.5909729,52.6760749817],"type":"Point"}
}