{
  "type": "Feature",
  "properties": {
    "addr:full":"12727 50 St NW Edmonton AB T5A 4L8",
    "addr:housenumber":"12727",
    "addr:postcode":"t5a 4l8",
    "addr:street":"50 St Nw",
    "iso:country":"CA",
    "sg:address":"12727 50 St NW",
    "sg:city":"Edmonton",
    "sg:classifiers":[
        {
            "category":"Food & Beverages",
            "subcategory":"Liquor & Beverages",
            "type":"Retail Goods"
        }
    ],
    "sg:phone":"+1 780 473 0957",
    "sg:postcode":"T5A 4L8",
    "sg:province":"AB",
    "sg:tags":[
        "store"
    ],
    "wof:name":"Hermitage Liquor Express",
    "wof:placetype":"venue"
},
  "geometry": {"coordinates":[-113.418121,53.586189],"type":"Point"}
}