{
  "type": "Feature",
  "properties": {
    "addr:full":"3880 Boul Harvey # 61 Jonquiere QC G7X 8R6",
    "addr:housenumber":"3880",
    "addr:postcode":"g7x 8r6",
    "addr:street":"Boul Harvey # 61",
    "iso:country":"CA",
    "sg:address":"3880 Boul Harvey # 61",
    "sg:city":"Jonquiere",
    "sg:classifiers":[
        {
            "category":"Shopping",
            "subcategory":"Clothing, Apparel, & Fashions",
            "type":"Retail Goods"
        }
    ],
    "sg:phone":"+1 418 695 0061",
    "sg:postcode":"G7X 8R6",
    "sg:province":"QC",
    "wof:name":"Boutique Signal Inc",
    "wof:placetype":"venue"
},
  "geometry": {"coordinates":[-71.251869,48.413246],"type":"Point"}
}