{
  "type": "Feature",
  "properties": {
    "addr:full":"Ottawa ON K1Y 3B8",
    "addr:postcode":"k1y 3b8",
    "iso:country":"CA",
    "sg:city":"Ottawa",
    "sg:classifiers":[
        {
            "category":"Retail",
            "subcategory":"Repair Shop",
            "type":"Services"
        }
    ],
    "sg:phone":"+1 613 715 9786",
    "sg:postcode":"K1Y 3B8",
    "sg:province":"ON",
    "sg:tags":[
        "equipment"
    ],
    "wof:name":"Quality Restaurant Svc",
    "wof:placetype":"venue"
},
  "geometry": {"coordinates":[-75.73767100000001,45.398624],"type":"Point"}
}