{
  "type": "Feature",
  "properties": {
    "iso:country":"CA",
    "sg:address":"County Rd 14",
    "sg:city":"Haliburton",
    "sg:classifiers":[
        {
            "category":"Travel",
            "subcategory":"Campground",
            "type":"Entertainment"
        }
    ],
    "sg:phone":"+1 705 754 2374",
    "sg:postcode":"K0M 1S0",
    "sg:province":"ON",
    "sg:tags":[
        "camp"
    ],
    "wof:name":"Camp Northland",
    "wof:placetype":"venue"
},
  "geometry": {"coordinates":[-78.508804,45.0467],"type":"Point"}
}