{
  "type": "Feature",
  "properties": {
    "addr:full":"15 Main St N Markham ON L3P 1X3",
    "addr:housenumber":"15",
    "addr:postcode":"l3p 1x3",
    "addr:street":"Main St N",
    "iso:country":"CA",
    "sg:address":"15 Main St N",
    "sg:city":"Markham",
    "sg:classifiers":[
        {
            "category":"Shopping",
            "subcategory":"Clothing, Apparel, & Fashions",
            "type":"Retail Goods"
        }
    ],
    "sg:phone":"+1 905 294 7244",
    "sg:postcode":"L3P 1X3",
    "sg:province":"ON",
    "sg:tags":[
        "fur",
        "business"
    ],
    "wof:name":"C M Furs",
    "wof:placetype":"venue"
},
  "geometry": {"coordinates":[-79.2598114014,43.8745079041],"type":"Point"}
}