{
  "type": "Feature",
  "properties": {
    "addr:full":"Vancouver BC V5N 2T6",
    "addr:postcode":"v5n 2t6",
    "iso:country":"CA",
    "sg:city":"Vancouver",
    "sg:classifiers":[
        {
            "category":"Organizations",
            "subcategory":"Community Association",
            "type":"Services"
        }
    ],
    "sg:phone":"+1 604 435 5770",
    "sg:postcode":"V5N 2T6",
    "sg:province":"BC",
    "sg:tags":[
        "fraternal"
    ],
    "wof:name":"Army Navy & Air Force Veterans",
    "wof:placetype":"venue"
},
  "geometry": {"coordinates":[-123.06107299999999,49.243404],"type":"Point"}
}