{
  "type": "Feature",
  "properties": {
    "addr:full":"1405 Boul-Parc Technologique Quebec QC G1P 4P5",
    "addr:housenumber":"1405",
    "addr:postcode":"g1p 4p5",
    "addr:street":"Boul-Parc Technologique",
    "iso:country":"CA",
    "sg:address":"1405 Boul-Parc Technologique",
    "sg:city":"Quebec",
    "sg:classifiers":[
        {
            "category":"Wholesale",
            "subcategory":"Groceries",
            "type":"Manufacturing & Wholesale Goods"
        }
    ],
    "sg:phone":"+1 418 652 1116",
    "sg:postcode":"G1P 4P5",
    "sg:province":"QC",
    "sg:tags":[
        "food",
        "product",
        "natural"
    ],
    "wof:name":"Atrium Biotechnologies Inc",
    "wof:placetype":"venue"
},
  "geometry": {"coordinates":[-71.3231964111,46.8014678955],"type":"Point"}
}