{
  "type": "Feature",
  "properties": {
    "iso:country":"CA",
    "sg:city":"Richmond",
    "sg:classifiers":[
        {
            "category":"Retail",
            "subcategory":"Auto Repair",
            "type":"Services"
        }
    ],
    "sg:phone":"+1 604 273 2871",
    "sg:postcode":"V6X 2C2",
    "sg:province":"BC",
    "sg:tags":[
        "repairing",
        "automobile"
    ],
    "wof:name":"Minit-Tune Brake & Auto Ctr",
    "wof:placetype":"venue"
},
  "geometry": {"coordinates":[-123.136253357,49.1824111938],"type":"Point"}
}