{
  "type": "Feature",
  "properties": {
    "addr:full":"Fort-Coulonge QC J0X 1V0",
    "addr:postcode":"j0x 1v0",
    "iso:country":"CA",
    "sg:city":"Fort-Coulonge",
    "sg:classifiers":[
        {
            "category":"Autos & Motor Vehicles",
            "subcategory":"Auto Supplies",
            "type":"Retail Goods"
        }
    ],
    "sg:phone":"+1 819 683 2371",
    "sg:postcode":"J0X 1V0",
    "sg:province":"QC",
    "sg:tags":[
        "tire"
    ],
    "wof:name":"Pontiac Tire Svc",
    "wof:placetype":"venue"
},
  "geometry": {"coordinates":[-76.74354599999999,45.84544],"type":"Point"}
}