{
  "type": "Feature",
  "properties": {
    "addr:full":"891 99th St North Battleford SK S9A 0N8",
    "addr:housenumber":"891",
    "addr:postcode":"s9a 0n8",
    "addr:street":"99Th St",
    "iso:country":"CA",
    "sg:address":"891 99th St",
    "sg:city":"North Battleford",
    "sg:classifiers":[
        {
            "category":"Organizations",
            "subcategory":"Professional Association",
            "type":"Services"
        }
    ],
    "sg:phone":"+1 306 446 3393",
    "sg:postcode":"S9A 0N8",
    "sg:province":"SK",
    "wof:name":"Battlefords Minor Hockey Assn",
    "wof:placetype":"venue"
},
  "geometry": {"coordinates":[-108.300735,52.769081],"type":"Point"}
}