{
  "type": "Feature",
  "properties": {
    "iso:country":"CA",
    "sg:address":"2320 Fischer-Hallman Rd",
    "sg:city":"New Dundee",
    "sg:classifiers":[
        {
            "category":"Retail",
            "subcategory":"Veterinary Services",
            "type":"Services"
        }
    ],
    "sg:phone":"+1 519 696 3130",
    "sg:postcode":"N0B 2E0",
    "sg:province":"ON",
    "sg:tags":[
        "veterinarian"
    ],
    "wof:name":"Westmount Animal Hospital",
    "wof:placetype":"venue"
},
  "geometry": {"coordinates":[-80.537193,43.34985],"type":"Point"}
}