{
  "type": "Feature",
  "properties": {
    "addr:full":"788 St Clair Ave W Toronto ON M6C 1B6",
    "addr:housenumber":"788",
    "addr:postcode":"m6c 1b6",
    "addr:street":"St Clair Ave W",
    "iso:country":"CA",
    "sg:address":"788 St Clair Ave W",
    "sg:city":"Toronto",
    "sg:classifiers":[
        {
            "category":"Restaurant",
            "type":"Food & Drink"
        }
    ],
    "sg:phone":"+1 416 658 5950",
    "sg:postcode":"M6C 1B6",
    "sg:province":"ON",
    "wof:name":"Pyrgos Coffee Shop",
    "wof:placetype":"venue"
},
  "geometry": {"coordinates":[-79.4294509888,43.6810798645],"type":"Point"}
}