{
  "type": "Feature",
  "properties": {
    "addr:full":"306 Watson Rd Echo Bay ON P0S 1C0",
    "addr:housenumber":"306",
    "addr:postcode":"p0s 1c0",
    "addr:street":"Watson Rd",
    "iso:country":"CA",
    "sg:address":"306 Watson Rd",
    "sg:city":"Echo Bay",
    "sg:classifiers":[
        {
            "category":"Government",
            "subcategory":"Office",
            "type":"Public Place"
        }
    ],
    "sg:phone":"+1 705 248 2220",
    "sg:postcode":"P0S 1C0",
    "sg:province":"ON",
    "wof:name":"Municipal Field Office",
    "wof:placetype":"venue"
},
  "geometry": {"coordinates":[-84.0700454712,46.4849357605],"type":"Point"}
}