{
  "type": "Feature",
  "properties": {
    "addr:full":"724 Rue Ardouin Beauport QC G1C 7J8",
    "addr:housenumber":"724",
    "addr:postcode":"qc g1c 7j8",
    "addr:street":"Rue Ardouin",
    "iso:country":"CA",
    "sg:address":"724 Rue Ardouin",
    "sg:city":"Beauport",
    "sg:classifiers":[
        {
            "category":"Shopping",
            "type":"Retail Goods"
        }
    ],
    "sg:phone":"+1 418 660 4995",
    "sg:postcode":"G1C 7J8",
    "sg:province":"QC",
    "sg:tags":[
        "awning",
        "canopy"
    ],
    "wof:name":"Auvents St Laurent Inc",
    "wof:placetype":"venue"
},
  "geometry": {"coordinates":[-71.19249725340001,46.8822860718],"type":"Point"}
}