{
  "type": "Feature",
  "properties": {
    "addr:full":"6013 44 Ave Drayton Valley AB T7A 1R3",
    "addr:housenumber":"6013",
    "addr:postcode":"t7a 1r3",
    "addr:street":"44 Ave",
    "iso:country":"CA",
    "sg:address":"6013 44 Ave",
    "sg:city":"Drayton Valley",
    "sg:classifiers":[
        {
            "category":"Museum",
            "type":"Entertainment"
        }
    ],
    "sg:phone":"+1 780 542 5482",
    "sg:postcode":"T7A 1R3",
    "sg:province":"AB",
    "wof:name":"Drayton Valley Museum",
    "wof:placetype":"venue"
},
  "geometry": {"coordinates":[-114.982261658,53.2155303955],"type":"Point"}
}