{
  "type": "Feature",
  "properties": {
    "addr:full":"5117 52 St Yellowknife NT X1A 1T7",
    "addr:housenumber":"5117",
    "addr:postcode":"x1a 1t7",
    "addr:street":"52 St",
    "iso:country":"CA",
    "sg:address":"5117 52 St",
    "sg:city":"Yellowknife",
    "sg:classifiers":[
        {
            "category":"Organizations",
            "subcategory":"Religious Organization",
            "type":"Services"
        }
    ],
    "sg:phone":"+1 867 920 2129",
    "sg:postcode":"X1A 1T7",
    "sg:province":"NT",
    "sg:tags":[
        "church"
    ],
    "wof:name":"Roman Catholic Diocese",
    "wof:placetype":"venue"
},
  "geometry": {"coordinates":[-114.370407,62.45145],"type":"Point"}
}