{
  "type": "Feature",
  "properties": {
    "iso:country":"CA",
    "sg:address":"3620 Cedarille Dr SW",
    "sg:city":"Calgary",
    "sg:classifiers":[
        {
            "category":"Social Services",
            "subcategory":"Child Care",
            "type":"Services"
        }
    ],
    "sg:phone":"+1 403 281 1418",
    "sg:postcode":"T2W 5B2",
    "sg:province":"AB",
    "wof:name":"Sunshine Creative Childcare",
    "wof:placetype":"venue"
},
  "geometry": {"coordinates":[-114.134506226,50.9525222778],"type":"Point"}
}