{
  "type": "Feature",
  "properties": {
    "iso:country":"CA",
    "sg:city":"Vancouver",
    "sg:classifiers":[
        {
            "category":"Shopping",
            "subcategory":"Gifts & Souvenirs",
            "type":"Retail Goods"
        }
    ],
    "sg:phone":"+1 604 684 9999",
    "sg:postcode":"V6C 3B5",
    "sg:province":"BC",
    "sg:tags":[
        "shop"
    ],
    "wof:name":"Discovery House Trading Ltd",
    "wof:placetype":"venue"
},
  "geometry": {"coordinates":[-123.114899,49.288002],"type":"Point"}
}