{
  "type": "Feature",
  "properties": {
    "addr:full":"27 Milliken Blvd Scarborough ON M1V 5H9",
    "addr:housenumber":"27",
    "addr:postcode":"m1v 5h9",
    "addr:street":"Milliken Blvd",
    "iso:country":"CA",
    "sg:address":"27 Milliken Blvd",
    "sg:city":"Scarborough",
    "sg:classifiers":[
        {
            "category":"Wholesale",
            "subcategory":"Fruits & Vegetables",
            "type":"Manufacturing & Wholesale Goods"
        }
    ],
    "sg:phone":"+1 416 293 8123",
    "sg:postcode":"M1V 5H9",
    "sg:province":"ON",
    "wof:name":"Pie Farm Produce",
    "wof:placetype":"venue"
},
  "geometry": {"coordinates":[-79.294884,43.803528],"type":"Point"}
}