{
  "type": "Feature",
  "properties": {
    "addr:full":"7398 Yonge St # 11D Thornhill ON L4J 8J2",
    "addr:housenumber":"7398",
    "addr:postcode":"l4j 8j2",
    "addr:street":"Yonge St # 11D",
    "iso:country":"CA",
    "sg:address":"7398 Yonge St # 11D",
    "sg:city":"Thornhill",
    "sg:classifiers":[
        {
            "category":"Personal",
            "subcategory":"Beauty Salon",
            "type":"Services"
        }
    ],
    "sg:phone":"+1 905 889 4923",
    "sg:postcode":"L4J 8J2",
    "sg:province":"ON",
    "wof:name":"Pink Nail Salon",
    "wof:placetype":"venue"
},
  "geometry": {"coordinates":[-79.42287399999999,43.8083],"type":"Point"}
}