{
  "type": "Feature",
  "properties": {
    "iso:country":"CA",
    "sg:address":"12960 Rue Notre-Dame E",
    "sg:city":"Pointe-Aux-Trembles",
    "sg:classifiers":[
        {
            "category":"Personal",
            "subcategory":"Beauty Salon",
            "type":"Services"
        }
    ],
    "sg:phone":"+1 514 645 0981",
    "sg:postcode":"H1A 1R9",
    "sg:province":"QC",
    "wof:name":"Salon Nycol",
    "wof:placetype":"venue"
},
  "geometry": {"coordinates":[-73.489746,45.653214],"type":"Point"}
}