{
  "type": "Feature",
  "properties": {
    "addr:full":"Oxbow SK S0C 2B0",
    "addr:postcode":"s0c 2b0",
    "addr:street":"Oxbow",
    "iso:country":"CA",
    "sg:city":"Oxbow",
    "sg:classifiers":[
        {
            "category":"Mining & Drilling",
            "type":"Manufacturing & Wholesale Goods"
        }
    ],
    "sg:phone":"+1 306 483 2411",
    "sg:postcode":"S0C 2B0",
    "sg:province":"SK",
    "sg:tags":[
        "oil",
        "well"
    ],
    "wof:name":"A 1 Anchor Specialties Ltd",
    "wof:placetype":"venue"
},
  "geometry": {"coordinates":[-102.17251586899999,49.2280731201],"type":"Point"}
}