{
  "type": "Feature",
  "properties": {
    "iso:country":"CA",
    "sg:city":"Saint John",
    "sg:classifiers":[
        {
            "category":"Food & Beverages",
            "subcategory":"Groceries & Convenience Stores",
            "type":"Retail Goods"
        }
    ],
    "sg:phone":"+1 506 696 2510",
    "sg:postcode":"E2H 2G5",
    "sg:province":"NB",
    "wof:name":"Little John's Variety",
    "wof:placetype":"venue"
},
  "geometry": {"coordinates":[-66.01082599999999,45.32164],"type":"Point"}
}