{
  "type": "Feature",
  "properties": {
    "addr:full":"2132 Rue Crescent #200 Montreal QC H3G 2B8",
    "addr:housenumber":"2132",
    "addr:postcode":"h3g 2b8",
    "addr:street":"Rue Crescent # 200",
    "iso:country":"CA",
    "sg:address":"2132 Rue Crescent #200",
    "sg:city":"Montreal",
    "sg:classifiers":[
        {
            "category":"Personal",
            "subcategory":"Beauty Salon",
            "type":"Services"
        }
    ],
    "sg:phone":"+1 514 845 8426",
    "sg:postcode":"H3G 2B8",
    "sg:province":"QC",
    "wof:name":"Institut Marie-France Nantel",
    "wof:placetype":"venue"
},
  "geometry": {"coordinates":[-73.578453064,45.4983825684],"type":"Point"}
}