{
  "type": "Feature",
  "properties": {
    "addr:full":"1104 Fennell Ave E # 213 Hamilton ON L8T 1R9",
    "addr:housenumber":"1104;213",
    "addr:postcode":"l8t 1r9",
    "addr:street":"Fennell Ave E #",
    "iso:country":"CA",
    "sg:address":"1104 Fennell Ave E # 213",
    "sg:city":"Hamilton",
    "sg:classifiers":[
        {
            "category":"Organizations",
            "subcategory":"Labor Organization",
            "type":"Services"
        }
    ],
    "sg:phone":"+1 905 389 1574",
    "sg:postcode":"L8T 1R9",
    "sg:province":"ON",
    "wof:name":"Hamilton Brantford Ontario",
    "wof:placetype":"venue"
},
  "geometry": {"coordinates":[-79.8304901123,43.2256660461],"type":"Point"}
}