{
  "type": "Feature",
  "properties": {
    "addr:full":"5610 97 St NW Edmonton AB T6E 3J1",
    "addr:housenumber":"5610",
    "addr:postcode":"t6e 3j1",
    "addr:street":"97 St Nw",
    "iso:country":"CA",
    "sg:address":"5610 97 St NW",
    "sg:city":"Edmonton",
    "sg:classifiers":[
        {
            "category":"Manufacturing",
            "subcategory":"Metals",
            "type":"Manufacturing & Wholesale Goods"
        }
    ],
    "sg:phone":"+1 780 437 7970",
    "sg:postcode":"T6E 3J1",
    "sg:province":"AB",
    "sg:tags":[
        "building"
    ],
    "wof:name":"Brytex Building Systems Inc",
    "wof:placetype":"venue"
},
  "geometry": {"coordinates":[-113.479530334,53.4920425415],"type":"Point"}
}