{
  "type": "Feature",
  "properties": {
    "iso:country":"CA",
    "sg:address":"1234 Merivale Rd",
    "sg:city":"Ottawa",
    "sg:classifiers":[
        {
            "category":"Health Services",
            "subcategory":"Doctor",
            "type":"Services"
        }
    ],
    "sg:phone":"+1 613 722 4442",
    "sg:postcode":"K2C 4C3",
    "sg:province":"ON",
    "sg:tags":[
        "dentist"
    ],
    "wof:name":"Central Park Dental Ctr",
    "wof:placetype":"venue"
},
  "geometry": {"coordinates":[-75.732544,45.371891],"type":"Point"}
}