{
  "type": "Feature",
  "properties": {
    "addr:full":"2350 Trans Canada Hwy NE Salmon Arm BC V1E 4P6",
    "addr:housenumber":"2350",
    "addr:postcode":"v1e 4p6",
    "addr:street":"Trans Canada Hwy Ne",
    "iso:country":"CA",
    "sg:address":"2350 Trans Canada Hwy NE",
    "sg:city":"Salmon Arm",
    "sg:classifiers":[
        {
            "category":"Autos & Motor Vehicles",
            "subcategory":"Automobile Sales",
            "type":"Retail Goods"
        }
    ],
    "sg:phone":"+1 250 832 9433",
    "sg:postcode":"V1E 4P6",
    "sg:province":"BC",
    "sg:tags":[
        "car",
        "dealer"
    ],
    "wof:name":"Hilltop Toyota Ltd",
    "wof:placetype":"venue"
},
  "geometry": {"coordinates":[-119.277618408,50.7022285461],"type":"Point"}
}