{
  "type": "Feature",
  "properties": {
    "addr:full":"1450 Rue Cunard Laval QC H7S 2B7",
    "addr:housenumber":"1450",
    "addr:postcode":"h7s 2b7",
    "addr:street":"Rue Cunard",
    "iso:country":"CA",
    "sg:address":"1450 Rue Cunard",
    "sg:city":"Laval",
    "sg:classifiers":[
        {
            "category":"Building & Trades",
            "subcategory":"Plumbing",
            "type":"Services"
        }
    ],
    "sg:phone":"+1 450 662 1210",
    "sg:postcode":"H7S 2B7",
    "sg:province":"QC",
    "sg:tags":[
        "conditioning",
        "air",
        "system",
        "contractor"
    ],
    "wof:name":"Engineered Air",
    "wof:placetype":"venue"
},
  "geometry": {"coordinates":[-73.73410800000001,45.580948],"type":"Point"}
}