{
  "type": "Feature",
  "properties": {
    "addr:full":"135 12E Av Iberville QC J2X 1C7",
    "addr:housenumber":"135",
    "addr:postcode":"j2x 1c7",
    "addr:street":"12E Av",
    "iso:country":"CA",
    "sg:address":"135 12E Av",
    "sg:city":"Iberville",
    "sg:classifiers":[
        {
            "category":"Health Services",
            "subcategory":"Health Practitioner",
            "type":"Services"
        }
    ],
    "sg:phone":"+1 450 347 5988",
    "sg:postcode":"J2X 1C7",
    "sg:province":"QC",
    "sg:tags":[
        "speech",
        "therapy",
        "hearing"
    ],
    "wof:name":"Neveu, Mireille",
    "wof:placetype":"venue"
},
  "geometry": {"coordinates":[-73.245178,45.312965],"type":"Point"}
}