{
  "type": "Feature",
  "properties": {
    "addr:full":"152 Strathnairn Ave York ON M6M 2G1",
    "addr:housenumber":"152",
    "addr:postcode":"m6m 2g1",
    "addr:street":"Strathnairn Ave",
    "iso:country":"CA",
    "sg:address":"152 Strathnairn Ave",
    "sg:city":"York",
    "sg:classifiers":[
        {
            "category":"Building & Trades",
            "subcategory":"Construction",
            "type":"Services"
        }
    ],
    "sg:phone":"+1 416 201 8000",
    "sg:postcode":"M6M 2G1",
    "sg:province":"ON",
    "sg:tags":[
        "home",
        "general",
        "improvement",
        "contractor"
    ],
    "wof:name":"Chum Construction",
    "wof:placetype":"venue"
},
  "geometry": {"coordinates":[-79.47146606450001,43.6967735291],"type":"Point"}
}