{
  "type": "Feature",
  "properties": {
    "addr:full":"515 Centennial Dr S Martensville SK S0K 2T0",
    "addr:housenumber":"515",
    "addr:postcode":"s0k 2t0",
    "addr:street":"Centennial Dr S",
    "iso:country":"CA",
    "sg:address":"515 Centennial Dr S",
    "sg:city":"Martensville",
    "sg:classifiers":[
        {
            "category":"Government",
            "subcategory":"Fire Station",
            "type":"Public Place"
        }
    ],
    "sg:phone":"+1 ",
    "sg:postcode":"S0K 2T0",
    "sg:province":"SK",
    "sg:tags":[
        "department"
    ],
    "wof:name":"Martensville Fire Dept Hall",
    "wof:placetype":"venue"
},
  "geometry": {"coordinates":[-106.670242,52.281471],"type":"Point"}
}