{
  "type": "Feature",
  "properties": {
    "addr:full":"Lethbridge AB T1J 0G9",
    "addr:postcode":"t1j 0g9",
    "iso:country":"CA",
    "sg:city":"Lethbridge",
    "sg:classifiers":[
        {
            "category":"Banks & Credit Unions",
            "subcategory":"Bank",
            "type":"Services"
        }
    ],
    "sg:phone":"+1 403 382 3137",
    "sg:postcode":"T1J 0G9",
    "sg:province":"AB",
    "sg:tags":[
        "financing"
    ],
    "wof:name":"Canada Farm Credit Corp Canada",
    "wof:placetype":"venue"
},
  "geometry": {"coordinates":[-112.84353637700001,49.6955757141],"type":"Point"}
}