{
  "type": "Feature",
  "properties": {
    "addr:full":"9382 Boul Saint-Michel Montreal QC H1Z 3H2",
    "addr:housenumber":"9382",
    "addr:postcode":"h1z 3h2",
    "addr:street":"Boul Saint-Michel",
    "iso:country":"CA",
    "sg:address":"9382 Boul Saint-Michel",
    "sg:city":"Montreal",
    "sg:classifiers":[
        {
            "category":"Retail",
            "subcategory":"Auto Repair",
            "type":"Services"
        }
    ],
    "sg:phone":"+1 514 388 1300",
    "sg:postcode":"H1Z 3H2",
    "sg:province":"QC",
    "sg:tags":[
        "body",
        "automobile",
        "painting"
    ],
    "wof:name":"Toto Garage Auto Repair",
    "wof:placetype":"venue"
},
  "geometry": {"coordinates":[-73.63372,45.574249],"type":"Point"}
}