{
  "type": "Feature",
  "properties": {
    "addr:full":"2075 34th St Brandon MB R7A 5Y1",
    "addr:housenumber":"2075",
    "addr:postcode":"r7a 5y1",
    "addr:street":"34Th St",
    "iso:country":"CA",
    "sg:address":"2075 34th St",
    "sg:city":"Brandon",
    "sg:classifiers":[
        {
            "category":"Professional",
            "subcategory":"Accounting & Tax Preparation",
            "type":"Services"
        }
    ],
    "sg:phone":"+1 204 728 6838",
    "sg:postcode":"R7A 5Y1",
    "sg:province":"MB",
    "sg:tags":[
        "accountant"
    ],
    "wof:name":"Nightingale, Brett",
    "wof:placetype":"venue"
},
  "geometry": {"coordinates":[-99.961952,49.847698],"type":"Point"}
}