{
  "type": "Feature",
  "properties": {
    "addr:full":"1200 Boul Rome Brossard QC J4W 3H3",
    "addr:housenumber":"1200",
    "addr:postcode":"j4w 3h3",
    "addr:street":"Boul Rome",
    "iso:country":"CA",
    "sg:address":"1200 Boul Rome",
    "sg:city":"Brossard",
    "sg:classifiers":[
        {
            "category":"Building & Trades",
            "subcategory":"Construction",
            "type":"Services"
        }
    ],
    "sg:phone":"+1 450 671 5541",
    "sg:postcode":"J4W 3H3",
    "sg:province":"QC",
    "sg:tags":[
        "contractor"
    ],
    "wof:name":"Claude Legault Constrn Ltee",
    "wof:placetype":"venue"
},
  "geometry": {"coordinates":[-73.492142,45.457199],"type":"Point"}
}