{
  "type": "Feature",
  "properties": {
    "addr:full":"103 Toronto St S Markdale ON N0C 1H0",
    "addr:housenumber":"103",
    "addr:postcode":"n0c 1h0",
    "addr:street":"Toronto St S",
    "iso:country":"CA",
    "sg:address":"103 Toronto St S",
    "sg:city":"Markdale",
    "sg:classifiers":[
        {
            "category":"Restaurant",
            "type":"Food & Drink"
        }
    ],
    "sg:phone":"+1 519 986 2527",
    "sg:postcode":"N0C 1H0",
    "sg:province":"ON",
    "wof:name":"Dairy Daughter Gas Station",
    "wof:placetype":"venue"
},
  "geometry": {"coordinates":[-80.6448516846,44.3169136047],"type":"Point"}
}