{
  "type": "Feature",
  "properties": {
    "addr:full":"Drayton Valley AB T7A 1S1",
    "addr:postcode":"t7a 1s1",
    "addr:street":"Drayton",
    "iso:country":"CA",
    "sg:city":"Drayton Valley",
    "sg:classifiers":[
        {
            "category":"Mining & Drilling",
            "type":"Manufacturing & Wholesale Goods"
        }
    ],
    "sg:phone":"+1 780 542 6946",
    "sg:postcode":"T7A 1S1",
    "sg:province":"AB",
    "sg:tags":[
        "field",
        "oil"
    ],
    "wof:name":"Ariant Holdings Ltd",
    "wof:placetype":"venue"
},
  "geometry": {"coordinates":[-114.9868927,53.2279968262],"type":"Point"}
}