{
  "type": "Feature",
  "properties": {
    "addr:full":"176 Catharine St Port Colborne ON L3K 4K6",
    "addr:housenumber":"176",
    "addr:postcode":"l3k 4k6",
    "addr:street":"Catharine St",
    "iso:country":"CA",
    "sg:address":"176 Catharine St",
    "sg:city":"Port Colborne",
    "sg:classifiers":[
        {
            "category":"Professional",
            "subcategory":"Accounting & Tax Preparation",
            "type":"Services"
        }
    ],
    "sg:phone":"+1 905 834 6688",
    "sg:postcode":"L3K 4K6",
    "sg:province":"ON",
    "sg:tags":[
        "accountant"
    ],
    "wof:name":"Van Viegen, Conrad CA",
    "wof:placetype":"venue"
},
  "geometry": {"coordinates":[-79.2528305054,42.8842086792],"type":"Point"}
}