{
  "type": "Feature",
  "properties": {
    "iso:country":"CA",
    "sg:address":"450 Rue Wright",
    "sg:city":"Saint-Laurent",
    "sg:classifiers":[
        {
            "category":"Wholesale",
            "subcategory":"Office Equipment",
            "type":"Manufacturing & Wholesale Goods"
        }
    ],
    "sg:phone":"+1 514 333 5260",
    "sg:postcode":"H4N 1M6",
    "sg:province":"QC",
    "sg:tags":[
        "machine",
        "duplicating",
        "copying"
    ],
    "wof:name":"Copidata Inc",
    "wof:placetype":"venue"
},
  "geometry": {"coordinates":[-73.6829299927,45.5069618225],"type":"Point"}
}