{
  "type": "Feature",
  "properties": {
    "addr:full":"332 Kettleby Rd Kettleby ON L0G 1J0",
    "addr:housenumber":"332",
    "addr:postcode":"l0g 1j0",
    "addr:street":"Kettleby Rd",
    "iso:country":"CA",
    "sg:address":"332 Kettleby Rd",
    "sg:city":"Kettleby",
    "sg:classifiers":[
        {
            "category":"Professional",
            "subcategory":"Management & Consulting",
            "type":"Services"
        }
    ],
    "sg:phone":"+1 905 727 4111",
    "sg:postcode":"L0G 1J0",
    "sg:province":"ON",
    "sg:tags":[
        "consultant",
        "business"
    ],
    "wof:name":"G Vogan Enterprises",
    "wof:placetype":"venue"
},
  "geometry": {"coordinates":[-79.5606384277,44.0100440979],"type":"Point"}
}