{
  "type": "Feature",
  "properties": {
    "iso:country":"CA",
    "sg:city":"Nanaimo",
    "sg:classifiers":[
        {
            "category":"Education",
            "subcategory":"Special Training",
            "type":"Public Place"
        }
    ],
    "sg:phone":"+1 250 753 2888",
    "sg:postcode":"V9R 5C8",
    "sg:province":"BC",
    "sg:tags":[
        "aid",
        "instruction",
        "first"
    ],
    "wof:name":"Abcb First Aid Training",
    "wof:placetype":"venue"
},
  "geometry": {"coordinates":[-123.938270569,49.1658782959],"type":"Point"}
}