{
  "type": "Feature",
  "properties": {
    "addr:full":"Langley BC V3A 3Y8",
    "addr:postcode":"v3a 3y8",
    "iso:country":"CA",
    "sg:city":"Langley",
    "sg:classifiers":[
        {
            "category":"Shopping",
            "subcategory":"Bicycles & Sporting Goods",
            "type":"Retail Goods"
        }
    ],
    "sg:phone":"+1 604 530 7899",
    "sg:postcode":"V3A 3Y8",
    "sg:province":"BC",
    "sg:tags":[
        "gun",
        "gunsmith"
    ],
    "wof:name":"Langley Guns & Tackle",
    "wof:placetype":"venue"
},
  "geometry": {"coordinates":[-122.652832,49.104683],"type":"Point"}
}