{
  "type": "Feature",
  "properties": {
    "addr:full":"4515 Lobsinger Line St Clements ON N0B 2M0",
    "addr:housenumber":"4515",
    "addr:postcode":"n0b 2m0",
    "addr:street":"Lobsinger Line St Clements",
    "iso:country":"CA",
    "sg:address":"4515 Lobsinger Line",
    "sg:city":"St Clements",
    "sg:classifiers":[
        {
            "category":"Building & Trades",
            "subcategory":"Landscaping Services",
            "type":"Services"
        }
    ],
    "sg:phone":"+1 519 699 5666",
    "sg:postcode":"N0B 2M0",
    "sg:province":"ON",
    "sg:tags":[
        "landscape",
        "contractor"
    ],
    "wof:name":"A A Landscaping",
    "wof:placetype":"venue"
},
  "geometry": {"coordinates":[-80.72556304930001,43.52602005],"type":"Point"}
}