{
  "type": "Feature",
  "properties": {
    "addr:full":"390 Rothesay Ave Saint John NB E2J 2C4",
    "addr:housenumber":"390",
    "addr:postcode":"e2j 2c4",
    "addr:street":"Rothesay Ave",
    "iso:country":"CA",
    "sg:address":"390 Rothesay Ave",
    "sg:city":"Saint John",
    "sg:classifiers":[
        {
            "category":"Manufacturing",
            "subcategory":"Metals",
            "type":"Manufacturing & Wholesale Goods"
        }
    ],
    "sg:phone":"+1 506 658 1959",
    "sg:postcode":"E2J 2C4",
    "sg:province":"NB",
    "sg:tags":[
        "steel"
    ],
    "wof:name":"Harris Rebar",
    "wof:placetype":"venue"
},
  "geometry": {"coordinates":[-66.0368423462,45.3003807068],"type":"Point"}
}