{
  "type": "Feature",
  "properties": {
    "iso:country":"CA",
    "sg:address":"388 Rue Hebert",
    "sg:city":"Mont-Laurier",
    "sg:classifiers":[
        {
            "category":"Professional",
            "type":"Services"
        }
    ],
    "sg:phone":"+1 819 623 6623",
    "sg:postcode":"J9L 2X2",
    "sg:province":"QC",
    "sg:tags":[
        "equipment",
        "hydroponics",
        "supply"
    ],
    "wof:name":"Hydromax",
    "wof:placetype":"venue"
},
  "geometry": {"coordinates":[-75.49113464360001,46.5521278381],"type":"Point"}
}