{
  "type": "Feature",
  "properties": {
    "addr:full":"1154 St Clair Ave W Toronto ON M6E 1B3",
    "addr:housenumber":"1154",
    "addr:postcode":"m6e 1b3",
    "addr:street":"St Clair Ave W",
    "iso:country":"CA",
    "sg:address":"1154 St Clair Ave W",
    "sg:city":"Toronto",
    "sg:classifiers":[
        {
            "category":"Personal",
            "type":"Services"
        }
    ],
    "sg:phone":"+1 416 656 0616",
    "sg:postcode":"M6E 1B3",
    "sg:province":"ON",
    "sg:tags":[
        "program",
        "physical",
        "exercise",
        "fitness"
    ],
    "wof:name":"Pro Active Fitness",
    "wof:placetype":"venue"
},
  "geometry": {"coordinates":[-79.442802,43.67815],"type":"Point"}
}