{
  "type": "Feature",
  "properties": {
    "addr:full":"64 Alphonse Sainte-Hedwidge-DE-Roberval QC G0W 2R0",
    "addr:housenumber":"64",
    "addr:postcode":"g0w 2r0",
    "addr:street":"Alphonse Sainte-Hedwidge-De-Roberval",
    "iso:country":"CA",
    "sg:address":"64 Alphonse",
    "sg:city":"Sainte-Hedwidge-DE-Roberval",
    "sg:classifiers":[
        {
            "category":"Recreation",
            "type":"Entertainment"
        }
    ],
    "sg:phone":"+1 418 275 5093",
    "sg:postcode":"G0W 2R0",
    "sg:province":"QC",
    "sg:tags":[
        "center",
        "government"
    ],
    "wof:name":"Ste Hedwidge Comite-Loisirs",
    "wof:placetype":"venue"
},
  "geometry": {"coordinates":[-72.366196,48.480679],"type":"Point"}
}