{
  "type": "Feature",
  "properties": {
    "iso:country":"CA",
    "sg:address":"1202 Ch D'Oka",
    "sg:city":"Deux-Montagnes",
    "sg:classifiers":[
        {
            "category":"Personal",
            "subcategory":"Beauty Salon",
            "type":"Services"
        }
    ],
    "sg:phone":"+1 450 473 3512",
    "sg:postcode":"J7R 1M3",
    "sg:province":"QC",
    "wof:name":"Salon Mirelle",
    "wof:placetype":"venue"
},
  "geometry": {"coordinates":[-73.892868042,45.5414924622],"type":"Point"}
}