{
  "type": "Feature",
  "properties": {
    "addr:full":"874 Rue Commerciale Saint-Jean-Chrysostome QC G6Z 2E2",
    "addr:housenumber":"874",
    "addr:postcode":"g6z 2e2",
    "addr:street":"Rue Commerciale Saint-Jean-Chrysostome",
    "iso:country":"CA",
    "sg:address":"874 Rue Commerciale",
    "sg:city":"Saint-Jean-Chrysostome",
    "sg:classifiers":[
        {
            "category":"Retail",
            "subcategory":"Auto Repair",
            "type":"Services"
        }
    ],
    "sg:phone":"+1 418 839 5037",
    "sg:postcode":"G6Z 2E2",
    "sg:province":"QC",
    "sg:tags":[
        "repairing",
        "automobile"
    ],
    "wof:name":"Garage Real Morin",
    "wof:placetype":"venue"
},
  "geometry": {"coordinates":[-71.2035446167,46.7260856628],"type":"Point"}
}