{
  "type": "Feature",
  "properties": {
    "iso:country":"CA",
    "sg:address":"Main Hwy",
    "sg:city":"Ferryland",
    "sg:classifiers":[
        {
            "category":"Shopping",
            "subcategory":"Pharmacy",
            "type":"Retail Goods"
        }
    ],
    "sg:phone":"+1 709 432 2797",
    "sg:postcode":"A0A 2H0",
    "sg:province":"NL",
    "wof:name":"Baltimore Pharmacy Ltd",
    "wof:placetype":"venue"
},
  "geometry": {"coordinates":[-52.8899002075,47.0220298767],"type":"Point"}
}