{
  "type": "Feature",
  "properties": {
    "addr:full":"476 Bloor St W Toronto ON M5S 1X8",
    "addr:housenumber":"476",
    "addr:postcode":"m5s 1x8",
    "addr:street":"Bloor St W",
    "iso:country":"CA",
    "sg:address":"476 Bloor St W",
    "sg:city":"Toronto",
    "sg:classifiers":[
        {
            "category":"Shopping",
            "subcategory":"Clothing, Apparel, & Fashions",
            "type":"Retail Goods"
        }
    ],
    "sg:phone":"+1 416 538 1234",
    "sg:postcode":"M5S 1X8",
    "sg:province":"ON",
    "sg:tags":[
        "lingerie"
    ],
    "wof:name":"Secrets From Your Sister",
    "wof:placetype":"venue"
},
  "geometry": {"coordinates":[-79.409691,43.665573],"type":"Point"}
}