{
  "type": "Feature",
  "properties": {
    "addr:full":"130 1st Ave W Souris MB R0K 2C0",
    "addr:housenumber":"130",
    "addr:postcode":"r0k 2c0",
    "addr:street":"1St Ave W",
    "iso:country":"CA",
    "sg:address":"130 1st Ave W",
    "sg:city":"Souris",
    "sg:classifiers":[
        {
            "category":"Government",
            "subcategory":"Office",
            "type":"Public Place"
        }
    ],
    "sg:phone":"+1 204 483 4050",
    "sg:postcode":"R0K 2C0",
    "sg:province":"MB",
    "wof:name":"Manitoba Education & Training",
    "wof:placetype":"venue"
},
  "geometry": {"coordinates":[-100.258865,49.620834],"type":"Point"}
}