{
  "type": "Feature",
  "properties": {
    "addr:full":"500 Dutton Dr Waterloo ON N2L 4C6",
    "addr:housenumber":"500",
    "addr:postcode":"n2l 4c6",
    "addr:street":"Dutton Dr",
    "iso:country":"CA",
    "sg:address":"500 Dutton Dr",
    "sg:city":"Waterloo",
    "sg:classifiers":[
        {
            "category":"Restaurant",
            "type":"Food & Drink"
        }
    ],
    "sg:phone":"+1 519 747 0055",
    "sg:postcode":"N2L 4C6",
    "sg:province":"ON",
    "sg:tags":[
        "caterer"
    ],
    "wof:name":"Country Kettle Classics",
    "wof:placetype":"venue"
},
  "geometry": {"coordinates":[-80.538635,43.494022],"type":"Point"}
}