{
  "type": "Feature",
  "properties": {
    "addr:full":"2345 Keele St North York ON M6M 4A2",
    "addr:housenumber":"2345",
    "addr:postcode":"m6m 4a2",
    "addr:street":"Keele St",
    "iso:country":"CA",
    "sg:address":"2345 Keele St",
    "sg:city":"North York",
    "sg:classifiers":[
        {
            "category":"Shopping",
            "subcategory":"Department Store",
            "type":"Retail Goods"
        }
    ],
    "sg:phone":"+1 416 247 7372",
    "sg:postcode":"M6M 4A2",
    "sg:province":"ON",
    "wof:name":"Value Village Stores Ltd",
    "wof:placetype":"venue"
},
  "geometry": {"coordinates":[-79.477425,43.70673],"type":"Point"}
}