{
  "type": "Feature",
  "properties": {
    "iso:country":"CA",
    "sg:address":"8710 152B Ave NW",
    "sg:city":"Edmonton",
    "sg:classifiers":[
        {
            "category":"Professional",
            "subcategory":"Research",
            "type":"Services"
        }
    ],
    "sg:phone":"+1 780 457 0799",
    "sg:postcode":"T5E 6H2",
    "sg:province":"AB",
    "sg:tags":[
        "market",
        "analysis"
    ],
    "wof:name":"Goldfire Distributor",
    "wof:placetype":"venue"
},
  "geometry": {"coordinates":[-113.47515106199999,53.6147613525],"type":"Point"}
}