{
  "type": "Feature",
  "properties": {
    "addr:full":"3460 Boul Des Sources Dollard-Des-Ormeaux QC H9B 1Z9",
    "addr:housenumber":"3460",
    "addr:postcode":"h9b 1z9",
    "addr:street":"Boul Des Sources",
    "iso:country":"CA",
    "sg:address":"3460 Boul Des Sources",
    "sg:city":"Dollard-Des-Ormeaux",
    "sg:classifiers":[
        {
            "category":"Home & Garden",
            "subcategory":"Building Materials",
            "type":"Retail Goods"
        }
    ],
    "sg:phone":"+1 514 421 1454",
    "sg:postcode":"H9B 1Z9",
    "sg:province":"QC",
    "sg:tags":[
        "paint"
    ],
    "wof:name":"Peintures Montreal Metro Inc",
    "wof:placetype":"venue"
},
  "geometry": {"coordinates":[-73.797867,45.484753],"type":"Point"}
}