{
  "type": "Feature",
  "properties": {
    "addr:full":"2820 Danforth Ave Toronto ON M4C 1M1",
    "addr:housenumber":"2820",
    "addr:postcode":"m4c 1m1",
    "addr:street":"Danforth Ave",
    "iso:country":"CA",
    "sg:address":"2820 Danforth Ave",
    "sg:city":"Toronto",
    "sg:classifiers":[
        {
            "category":"Recreation",
            "type":"Entertainment"
        }
    ],
    "sg:phone":"+1 416 699 5078",
    "sg:postcode":"M4C 1M1",
    "sg:province":"ON",
    "sg:tags":[
        "martial",
        "arts",
        "instruction"
    ],
    "wof:name":"DE Santos Martial Arts Studio",
    "wof:placetype":"venue"
},
  "geometry": {"coordinates":[-79.295715332,43.6896591187],"type":"Point"}
}