{
  "type": "Feature",
  "properties": {
    "addr:full":"382 Wilson Ave North York ON M3H 1S9",
    "addr:housenumber":"382",
    "addr:postcode":"m3h 1s9",
    "addr:street":"Wilson Ave",
    "iso:country":"CA",
    "sg:address":"382 Wilson Ave",
    "sg:city":"North York",
    "sg:classifiers":[
        {
            "category":"Personal",
            "subcategory":"Shoe Repair & Shine",
            "type":"Services"
        }
    ],
    "sg:phone":"+1 416 638 3360",
    "sg:postcode":"M3H 1S9",
    "sg:province":"ON",
    "sg:tags":[
        "repairing",
        "boot",
        "shoes"
    ],
    "wof:name":"Elio's Shoes",
    "wof:placetype":"venue"
},
  "geometry": {"coordinates":[-79.439323,43.736427],"type":"Point"}
}