{
  "type": "Feature",
  "properties": {
    "addr:full":"406 Oxford St E London ON N5Y 3H4",
    "addr:housenumber":"406",
    "addr:postcode":"n5y 3h4",
    "addr:street":"Oxford St E",
    "iso:country":"CA",
    "sg:address":"406 Oxford St E",
    "sg:city":"London",
    "sg:classifiers":[
        {
            "category":"Social Services",
            "type":"Services"
        }
    ],
    "sg:phone":"+1 519 438 7065",
    "sg:postcode":"N5Y 3H4",
    "sg:province":"ON",
    "sg:tags":[
        "organization",
        "welfare"
    ],
    "wof:name":"Big Sisters",
    "wof:placetype":"venue"
},
  "geometry": {"coordinates":[-81.2453613281,42.9979248047],"type":"Point"}
}