{
  "type": "Feature",
  "properties": {
    "addr:full":"4702 51 St Whitecourt AB T7S 1R9",
    "addr:housenumber":"4702",
    "addr:postcode":"t7s 1r9",
    "addr:street":"51 St",
    "iso:country":"CA",
    "sg:address":"4702 51 St",
    "sg:city":"Whitecourt",
    "sg:classifiers":[
        {
            "category":"Shopping",
            "subcategory":"Pharmacy",
            "type":"Retail Goods"
        }
    ],
    "sg:phone":"+1 780 778 3676",
    "sg:postcode":"T7S 1R9",
    "sg:province":"AB",
    "wof:name":"Medi-Save Drugs Rexall",
    "wof:placetype":"venue"
},
  "geometry": {"coordinates":[-115.687301636,54.1383705139],"type":"Point"}
}