{
  "type": "Feature",
  "properties": {
    "iso:country":"CA",
    "sg:address":"558 Av Notre-Dame",
    "sg:city":"Saint-Lambert",
    "sg:classifiers":[
        {
            "category":"Health Services",
            "subcategory":"Health Practitioner",
            "type":"Services"
        }
    ],
    "sg:phone":"+1 450 671 0159",
    "sg:postcode":"J4P 2K7",
    "sg:province":"QC",
    "sg:tags":[
        "psychologist"
    ],
    "wof:name":"Le Toullec, Pierre PhD",
    "wof:placetype":"venue"
},
  "geometry": {"coordinates":[-73.509361,45.501766],"type":"Point"}
}