{
  "type": "Feature",
  "properties": {
    "addr:full":"252 River Ave Cochrane AB T4C 2C1",
    "addr:housenumber":"252",
    "addr:postcode":"t4c 2c1",
    "addr:street":"River Ave",
    "iso:country":"CA",
    "sg:address":"252 River Ave",
    "sg:city":"Cochrane",
    "sg:classifiers":[
        {
            "category":"Autos & Motor Vehicles",
            "subcategory":"Motorcycle Sales",
            "type":"Retail Goods"
        }
    ],
    "sg:phone":"+1 403 932 2019",
    "sg:postcode":"T4C 2C1",
    "sg:province":"AB",
    "sg:tags":[
        "all",
        "terrain"
    ],
    "wof:name":"Bow Ridge Sports",
    "wof:placetype":"venue"
},
  "geometry": {"coordinates":[-114.465744,51.184265],"type":"Point"}
}