{
  "type": "Feature",
  "properties": {
    "addr:full":"Moosonee ON P0L 1Y0",
    "addr:postcode":"p0l 1y0",
    "iso:country":"CA",
    "sg:city":"Moosonee",
    "sg:classifiers":[
        {
            "category":"Organizations",
            "subcategory":"Religious Organization",
            "type":"Services"
        }
    ],
    "sg:phone":"+1 705 336 2361",
    "sg:postcode":"P0L 1Y0",
    "sg:province":"ON",
    "sg:tags":[
        "church"
    ],
    "wof:name":"Northern Missionary Fellowship",
    "wof:placetype":"venue"
},
  "geometry": {"coordinates":[-80.640625,51.273418],"type":"Point"}
}