{
  "type": "Feature",
  "properties": {
    "iso:country":"CA",
    "sg:city":"Kitchener",
    "sg:classifiers":[
        {
            "category":"Wholesale",
            "subcategory":"Machinery & Supplies",
            "type":"Manufacturing & Wholesale Goods"
        }
    ],
    "sg:phone":"+1 519 742 0171",
    "sg:postcode":"N2M 1N6",
    "sg:province":"ON",
    "sg:tags":[
        "fan",
        "commercial"
    ],
    "wof:name":"Ironross Inc",
    "wof:placetype":"venue"
},
  "geometry": {"coordinates":[-80.51738,43.452881],"type":"Point"}
}