{
  "type": "Feature",
  "properties": {
    "addr:full":"2575 Av Watt # 2 Sainte-Foy QC G1P 3T2",
    "addr:housenumber":"2575;# 2",
    "addr:postcode":"g1p 3t2",
    "addr:street":"Av Watt;Sainte-Foy",
    "iso:country":"CA",
    "sg:address":"2575 Av Watt # 2",
    "sg:city":"Sainte-Foy",
    "sg:classifiers":[
        {
            "category":"Wholesale",
            "subcategory":"Construction Materials",
            "type":"Manufacturing & Wholesale Goods"
        }
    ],
    "sg:phone":"+1 418 653 6807",
    "sg:postcode":"G1P 3T2",
    "sg:province":"QC",
    "sg:tags":[
        "building",
        "contractor"
    ],
    "wof:name":"Dryvit Quebec Distributions",
    "wof:placetype":"venue"
},
  "geometry": {"coordinates":[-71.30168151860001,46.7886161804],"type":"Point"}
}