{
  "type": "Feature",
  "properties": {
    "addr:full":"2579 Victoria St Prince George BC V2L 2M3",
    "addr:housenumber":"2579",
    "addr:postcode":"v2l 2m3",
    "addr:street":"Victoria St",
    "iso:country":"CA",
    "sg:address":"2579 Victoria St",
    "sg:city":"Prince George",
    "sg:classifiers":[
        {
            "category":"Social Services",
            "subcategory":"Child Care",
            "type":"Services"
        }
    ],
    "sg:phone":"+1 250 563 8827",
    "sg:postcode":"V2L 2M3",
    "sg:province":"BC",
    "sg:tags":[
        "kindergarten",
        "academic"
    ],
    "wof:name":"Kidsity",
    "wof:placetype":"venue"
},
  "geometry": {"coordinates":[-122.755402,53.898884],"type":"Point"}
}