{
  "type": "Feature",
  "properties": {
    "addr:full":"9916 100 Ave High Level AB T0H 1Z0",
    "addr:housenumber":"9916",
    "addr:postcode":"t0h 1z0",
    "addr:street":"100 Ave",
    "iso:country":"CA",
    "sg:address":"9916 100 Ave",
    "sg:city":"High Level",
    "sg:classifiers":[
        {
            "category":"Health Services",
            "subcategory":"Doctor",
            "type":"Services"
        }
    ],
    "sg:phone":"+1 780 926 2660",
    "sg:postcode":"T0H 1Z0",
    "sg:province":"AB",
    "sg:tags":[
        "dentist"
    ],
    "wof:name":"Blue Sky Dental Clinic",
    "wof:placetype":"venue"
},
  "geometry": {"coordinates":[-117.130569458,58.5182266235],"type":"Point"}
}