{
  "type": "Feature",
  "properties": {
    "addr:full":"Simcoe ON N3Y 4S9",
    "addr:postcode":"n3y 4s9",
    "iso:country":"CA",
    "sg:city":"Simcoe",
    "sg:classifiers":[
        {
            "category":"Real Estate",
            "subcategory":"Real Estate Operator",
            "type":"Services"
        }
    ],
    "sg:phone":"+1 519 428 2271",
    "sg:postcode":"N3Y 4S9",
    "sg:province":"ON",
    "sg:tags":[
        "apartment"
    ],
    "wof:name":"Oakdale Apartments",
    "wof:placetype":"venue"
},
  "geometry": {"coordinates":[-80.293587,42.833576],"type":"Point"}
}