{
  "type": "Feature",
  "properties": {
    "iso:country":"CA",
    "sg:address":"982 Albion Rd",
    "sg:city":"Etobicoke",
    "sg:classifiers":[
        {
            "category":"Restaurant",
            "type":"Food & Drink"
        }
    ],
    "sg:phone":"+1 416 310 2121",
    "sg:postcode":"M9V 1A7",
    "sg:province":"ON",
    "sg:tags":[
        "chicken",
        "dinner"
    ],
    "wof:name":"Kalifornia Rotisserie Chicken",
    "wof:placetype":"venue"
},
  "geometry": {"coordinates":[-79.5625152588,43.7361030579],"type":"Point"}
}