{
  "type": "Feature",
  "properties": {
    "addr:full":"Le Gardeur QC J5Z 2P7",
    "addr:postcode":"j5z 2p7",
    "addr:street":"Le Gardeur",
    "iso:country":"CA",
    "sg:city":"Le Gardeur",
    "sg:classifiers":[
        {
            "category":"Building & Trades",
            "subcategory":"Electrical",
            "type":"Services"
        }
    ],
    "sg:phone":"+1 450 654 7811",
    "sg:postcode":"J5Z 2P7",
    "sg:province":"QC",
    "sg:tags":[
        "electric",
        "contractor"
    ],
    "wof:name":"Mkg Demers Entrepreneur",
    "wof:placetype":"venue"
},
  "geometry": {"coordinates":[-73.4554138184,45.7656097412],"type":"Point"}
}