{
  "type": "Feature",
  "properties": {
    "addr:full":"1165 Attlee Ave Sudbury ON P3A 3J5",
    "addr:housenumber":"1165",
    "addr:postcode":"p3a 3j5",
    "addr:street":"Attlee Ave",
    "iso:country":"CA",
    "sg:address":"1165 Attlee Ave",
    "sg:city":"Sudbury",
    "sg:classifiers":[
        {
            "category":"Personal",
            "type":"Services"
        }
    ],
    "sg:phone":"+1 705 524 2864",
    "sg:postcode":"P3A 3J5",
    "sg:province":"ON",
    "sg:tags":[
        "therapist",
        "massage"
    ],
    "wof:name":"NU Wave Aromatix",
    "wof:placetype":"venue"
},
  "geometry": {"coordinates":[-80.9530410767,46.5222167969],"type":"Point"}
}