{
  "type": "Feature",
  "properties": {
    "addr:full":"250 161 Rte Saint-Valere QC G0P 1M0",
    "addr:housenumber":"161",
    "addr:postcode":"g0p 1m0",
    "addr:street":"Rte Saint-Valere",
    "iso:country":"CA",
    "sg:address":"250 161 Rte",
    "sg:city":"Saint-Valere",
    "sg:classifiers":[
        {
            "category":"Wholesale",
            "subcategory":"Fruits & Vegetables",
            "type":"Manufacturing & Wholesale Goods"
        }
    ],
    "sg:phone":"+1 819 353 1901",
    "sg:postcode":"G0P 1M0",
    "sg:province":"QC",
    "sg:tags":[
        "shipper"
    ],
    "wof:name":"Fraisiere Normand",
    "wof:placetype":"venue"
},
  "geometry": {"coordinates":[-72.030083,46.066216],"type":"Point"}
}