{
  "type": "Feature",
  "properties": {
    "iso:country":"CA",
    "sg:city":"Boucherville",
    "sg:classifiers":[
        {
            "category":"Manufacturing",
            "subcategory":"Tools & Machinery",
            "type":"Manufacturing & Wholesale Goods"
        }
    ],
    "sg:phone":"+1 450 641 7900",
    "sg:postcode":"J4B 5H3",
    "sg:province":"QC",
    "sg:tags":[
        "equipment",
        "printing"
    ],
    "wof:name":"Eti",
    "wof:placetype":"venue"
},
  "geometry": {"coordinates":[-73.42180633540001,45.5684165955],"type":"Point"}
}