{
  "type": "Feature",
  "properties": {
    "addr:full":"314 Rubidge St Peterborough ON K9J 3P4",
    "addr:housenumber":"314",
    "addr:postcode":"k9j 3p4",
    "addr:street":"Rubidge St",
    "iso:country":"CA",
    "sg:address":"314 Rubidge St",
    "sg:city":"Peterborough",
    "sg:classifiers":[
        {
            "category":"Professional",
            "subcategory":"Lawyer & Legal Services",
            "type":"Services"
        }
    ],
    "sg:phone":"+1 705 748 2211",
    "sg:postcode":"K9J 3P4",
    "sg:province":"ON",
    "sg:tags":[
        "attorney"
    ],
    "wof:name":"Mc Vicar, Jack",
    "wof:placetype":"venue"
},
  "geometry": {"coordinates":[-78.3264007568,44.302696228],"type":"Point"}
}