{
  "type": "Feature",
  "properties": {
    "addr:full":"513 Main St Esterhazy SK S0A 0X0",
    "addr:housenumber":"513",
    "addr:postcode":"s0a 0x0",
    "addr:street":"Main St",
    "iso:country":"CA",
    "sg:address":"513 Main St",
    "sg:city":"Esterhazy",
    "sg:classifiers":[
        {
            "category":"Professional",
            "subcategory":"Accounting & Tax Preparation",
            "type":"Services"
        }
    ],
    "sg:phone":"+1 306 745 6450",
    "sg:postcode":"S0A 0X0",
    "sg:province":"SK",
    "sg:tags":[
        "return",
        "filing"
    ],
    "wof:name":"H & R Block Canada Inc",
    "wof:placetype":"venue"
},
  "geometry": {"coordinates":[-102.07811,50.655663],"type":"Point"}
}