{
  "type": "Feature",
  "properties": {
    "addr:full":"225 Mcleod St Parkhill ON N0M 2K0",
    "addr:housenumber":"225",
    "addr:postcode":"n0m 2k0",
    "addr:street":"Mcleod St",
    "iso:country":"CA",
    "sg:address":"225 Mcleod St",
    "sg:city":"Parkhill",
    "sg:classifiers":[
        {
            "category":"Recreation",
            "type":"Entertainment"
        }
    ],
    "sg:phone":"+1 519 294 6134",
    "sg:postcode":"N0M 2K0",
    "sg:province":"ON",
    "sg:tags":[
        "center"
    ],
    "wof:name":"North Middlesex District Comm",
    "wof:placetype":"venue"
},
  "geometry": {"coordinates":[-81.6852798462,43.1564407349],"type":"Point"}
}