{
  "type": "Feature",
  "properties": {
    "addr:full":"1454 Gilford Rd Gilford ON L0L 1R0",
    "addr:housenumber":"1454",
    "addr:postcode":"l0l 1r0",
    "addr:street":"Gilford Rd",
    "iso:country":"CA",
    "sg:address":"1454 Gilford Rd",
    "sg:city":"Gilford",
    "sg:classifiers":[
        {
            "category":"Food & Beverages",
            "subcategory":"Groceries & Convenience Stores",
            "type":"Retail Goods"
        }
    ],
    "sg:phone":"+1 705 456 2101",
    "sg:postcode":"L0L 1R0",
    "sg:province":"ON",
    "sg:tags":[
        "grocer"
    ],
    "wof:name":"Gilford Plaza General Store",
    "wof:placetype":"venue"
},
  "geometry": {"coordinates":[-79.549103,44.221687],"type":"Point"}
}