{
  "type": "Feature",
  "properties": {
    "addr:full":"239 117 Rte Lac-Saguay QC J0W 1L0",
    "addr:housenumber":"117",
    "addr:postcode":"j0w 1l0",
    "addr:street":"Rte Lac-Saguay",
    "iso:country":"CA",
    "sg:address":"239 117 Rte",
    "sg:city":"Lac-Saguay",
    "sg:classifiers":[
        {
            "category":"Food & Beverages",
            "subcategory":"Groceries & Convenience Stores",
            "type":"Retail Goods"
        }
    ],
    "sg:phone":"+1 819 278 3646",
    "sg:postcode":"J0W 1L0",
    "sg:province":"QC",
    "sg:tags":[
        "grocer"
    ],
    "wof:name":"Marche Rouleau",
    "wof:placetype":"venue"
},
  "geometry": {"coordinates":[-75.142174,46.496342],"type":"Point"}
}