{
  "type": "Feature",
  "properties": {
    "iso:country":"CA",
    "sg:city":"London",
    "sg:classifiers":[
        {
            "category":"Restaurant",
            "type":"Food & Drink"
        }
    ],
    "sg:phone":"+1 519 472 4168",
    "sg:postcode":"N6H 5L4",
    "sg:province":"ON",
    "wof:name":"Gainsborough Restaurant",
    "wof:placetype":"venue"
},
  "geometry": {"coordinates":[-81.3316574097,42.9982795715],"type":"Point"}
}