{
  "type": "Feature",
  "properties": {
    "addr:full":"Toronto ON M5B 2H1",
    "addr:postcode":"m5b 2h1",
    "iso:country":"CA",
    "sg:city":"Toronto",
    "sg:classifiers":[
        {
            "category":"Shopping",
            "type":"Retail Goods"
        }
    ],
    "sg:phone":"+1 416 351 1522",
    "sg:postcode":"M5B 2H1",
    "sg:province":"ON",
    "sg:tags":[
        "telephone",
        "cellular"
    ],
    "wof:name":"Rogers At & T Wireless",
    "wof:placetype":"venue"
},
  "geometry": {"coordinates":[-79.379807,43.653202],"type":"Point"}
}