{
  "type": "Feature",
  "properties": {
    "addr:full":"Westbank BC V4T 2E9",
    "addr:postcode":"v4t 2e9",
    "iso:country":"CA",
    "sg:city":"Westbank",
    "sg:classifiers":[
        {
            "category":"Food & Beverages",
            "subcategory":"Liquor & Beverages",
            "type":"Retail Goods"
        }
    ],
    "sg:phone":"+1 250 768 7394",
    "sg:postcode":"V4T 2E9",
    "sg:province":"BC",
    "sg:tags":[
        "store"
    ],
    "wof:name":"Liquor Stores-Government",
    "wof:placetype":"venue"
},
  "geometry": {"coordinates":[-119.62958500000001,49.828381],"type":"Point"}
}