{
  "type": "Feature",
  "properties": {
    "addr:full":"56 Rue DE Quen Dolbeau-Mistassini QC G8L 4J8",
    "addr:housenumber":"56",
    "addr:postcode":"g8l 4j8",
    "addr:street":"Rue De Quen",
    "iso:country":"CA",
    "sg:address":"56 Rue DE Quen",
    "sg:city":"Dolbeau-Mistassini",
    "sg:classifiers":[
        {
            "category":"Shopping",
            "subcategory":"Bicycles & Sporting Goods",
            "type":"Retail Goods"
        }
    ],
    "sg:phone":"+1 418 276 7890",
    "sg:postcode":"G8L 4J8",
    "sg:province":"QC",
    "wof:name":"Sports Ben Inc",
    "wof:placetype":"venue"
},
  "geometry": {"coordinates":[-72.20573400000001,48.889046],"type":"Point"}
}