{
  "type": "Feature",
  "properties": {
    "addr:full":"Wembley Trail Wembley AB T0H 3S0",
    "addr:postcode":"t0h 3s0",
    "addr:street":"Wembley Trail",
    "iso:country":"CA",
    "sg:address":"Wembley Trail",
    "sg:city":"Wembley",
    "sg:classifiers":[
        {
            "category":"Mining & Drilling",
            "type":"Manufacturing & Wholesale Goods"
        }
    ],
    "sg:phone":"+1 780 538 9875",
    "sg:postcode":"T0H 3S0",
    "sg:province":"AB",
    "sg:tags":[
        "field",
        "oil",
        "piling"
    ],
    "wof:name":"Peace Land Piling Ltd",
    "wof:placetype":"venue"
},
  "geometry": {"coordinates":[-119.13919799999999,55.164795],"type":"Point"}
}