{
  "type": "Feature",
  "properties": {
    "addr:full":"Broadway Rd Rainy River ON P0W 1L0",
    "addr:postcode":"p0w 1l0",
    "addr:street":"Broadway Rd",
    "iso:country":"CA",
    "sg:address":"Broadway Rd",
    "sg:city":"Rainy River",
    "sg:classifiers":[
        {
            "category":"Government",
            "subcategory":"Office",
            "type":"Public Place"
        }
    ],
    "sg:phone":"+1 807 852 3970",
    "sg:postcode":"P0W 1L0",
    "sg:province":"ON",
    "sg:tags":[
        "village"
    ],
    "wof:name":"Rainy River Public Works Gar",
    "wof:placetype":"venue"
},
  "geometry": {"coordinates":[-94.5704650879,48.7206001282],"type":"Point"}
}