{
  "type": "Feature",
  "properties": {
    "addr:full":"Huntsville ON P1H 2J3",
    "addr:postcode":"p1h 2j3",
    "iso:country":"CA",
    "sg:city":"Huntsville",
    "sg:classifiers":[
        {
            "category":"Building & Trades",
            "subcategory":"Construction",
            "type":"Services"
        }
    ],
    "sg:phone":"+1 705 789 9290",
    "sg:postcode":"P1H 2J3",
    "sg:province":"ON",
    "sg:tags":[
        "excavating",
        "contractor",
        "general"
    ],
    "wof:name":"Lovegrove Haulage & Contr",
    "wof:placetype":"venue"
},
  "geometry": {"coordinates":[-79.2180023193,45.3265647888],"type":"Point"}
}