{
  "type": "Feature",
  "properties": {
    "addr:full":"449 Carlaw Ave Toronto ON M4K 3H9",
    "addr:housenumber":"449",
    "addr:postcode":"m4k 3h9",
    "addr:street":"Carlaw Ave",
    "iso:country":"CA",
    "sg:address":"449 Carlaw Ave",
    "sg:city":"Toronto",
    "sg:classifiers":[
        {
            "category":"Shopping",
            "subcategory":"Pharmacy",
            "type":"Retail Goods"
        }
    ],
    "sg:phone":"+1 416 462 0651",
    "sg:postcode":"M4K 3H9",
    "sg:province":"ON",
    "wof:name":"Drug Store Pharmacy",
    "wof:placetype":"venue"
},
  "geometry": {"coordinates":[-79.34277299999999,43.668125],"type":"Point"}
}