{
  "type": "Feature",
  "properties": {
    "addr:full":"Kingston ON K7K 6W6",
    "addr:postcode":"k7k 6w6",
    "iso:country":"CA",
    "sg:city":"Kingston",
    "sg:classifiers":[
        {
            "category":"Insurance",
            "subcategory":"Insurance Agent",
            "type":"Services"
        }
    ],
    "sg:phone":"+1 613 544 9771",
    "sg:postcode":"K7K 6W6",
    "sg:province":"ON",
    "sg:tags":[
        "adjuster"
    ],
    "wof:name":"Pca Adjusters Ltd",
    "wof:placetype":"venue"
},
  "geometry": {"coordinates":[-76.5071716309,44.2410202026],"type":"Point"}
}