{
  "type": "Feature",
  "properties": {
    "iso:country":"CA",
    "sg:address":"219 Colonnade Rd",
    "sg:city":"Nepean",
    "sg:classifiers":[
        {
            "category":"Insurance",
            "subcategory":"Insurance Agent",
            "type":"Services"
        }
    ],
    "sg:phone":"+1 613 225 4333",
    "sg:postcode":"K2E 7K3",
    "sg:province":"ON",
    "wof:name":"Canada Life Ind Reprsentatives",
    "wof:placetype":"venue"
},
  "geometry": {"coordinates":[-75.712624,45.34177],"type":"Point"}
}