{
  "type": "Feature",
  "properties": {
    "addr:full":"219 Colonnade Rd Nepean ON K2E 7K3",
    "addr:housenumber":"219",
    "addr:postcode":"k2e 7k3",
    "addr:street":"Colonnade Rd",
    "iso:country":"CA",
    "sg:address":"219 Colonnade Rd",
    "sg:city":"Nepean",
    "sg:classifiers":[
        {
            "category":"Insurance",
            "subcategory":"Insurance Agent",
            "type":"Services"
        }
    ],
    "sg:phone":"+1 613 225 4333",
    "sg:postcode":"K2E 7K3",
    "sg:province":"ON",
    "wof:name":"Canada Life Ind Reprsentatives",
    "wof:placetype":"venue"
},
  "geometry": {"coordinates":[-75.71262400000001,45.34177],"type":"Point"}
}