{
  "type": "Feature",
  "properties": {
    "iso:country":"CA",
    "sg:address":"11425 26E Av",
    "sg:city":"Montreal",
    "sg:classifiers":[
        {
            "category":"Manufacturing",
            "subcategory":"Tools & Machinery",
            "type":"Manufacturing & Wholesale Goods"
        }
    ],
    "sg:phone":"+1 514 648 4410",
    "sg:postcode":"H1E 3K3",
    "sg:province":"QC",
    "sg:tags":[
        "machine",
        "shop"
    ],
    "wof:name":"Atelier D'Usinage L & F Inc",
    "wof:placetype":"venue"
},
  "geometry": {"coordinates":[-73.58070373539999,45.6287155151],"type":"Point"}
}