{
  "type": "Feature",
  "properties": {
    "addr:full":"6455 Vipond Dr Mississauga ON L5T 1J9",
    "addr:housenumber":"6455",
    "addr:postcode":"l5t 1j9",
    "addr:street":"Vipond Dr",
    "iso:country":"CA",
    "sg:address":"6455 Vipond Dr",
    "sg:city":"Mississauga",
    "sg:classifiers":[
        {
            "category":"Freight",
            "type":"Transportation"
        }
    ],
    "sg:phone":"+1 905 678 7777",
    "sg:postcode":"L5T 1J9",
    "sg:province":"ON",
    "wof:name":"Beacon International Ltd",
    "wof:placetype":"venue"
},
  "geometry": {"coordinates":[-79.6644744873,43.6606826782],"type":"Point"}
}