{
  "type": "Feature",
  "properties": {
    "addr:full":"2 King George Rd Brantford ON N3R 5J7",
    "addr:housenumber":"2",
    "addr:postcode":"n3r 5j7",
    "addr:street":"King George Rd",
    "iso:country":"CA",
    "sg:address":"2 King George Rd",
    "sg:city":"Brantford",
    "sg:classifiers":[
        {
            "category":"Banks & Credit Unions",
            "subcategory":"Bank",
            "type":"Services"
        }
    ],
    "sg:phone":"+1 519 756 2330",
    "sg:postcode":"N3R 5J7",
    "sg:province":"ON",
    "wof:name":"Cibc",
    "wof:placetype":"venue"
},
  "geometry": {"coordinates":[-80.272446,43.15966],"type":"Point"}
}