{
  "type": "Feature",
  "properties": {
    "iso:country":"CA",
    "sg:address":"1270 Tower Rd",
    "sg:city":"Halifax",
    "sg:classifiers":[
        {
            "category":"Organizations",
            "subcategory":"Non-profit Organization",
            "type":"Services"
        }
    ],
    "sg:phone":"+1 902 473 7301",
    "sg:postcode":"B3K 5M4",
    "sg:province":"NS",
    "sg:tags":[
        "charitable",
        "institution"
    ],
    "wof:name":"Brain Injury Association",
    "wof:placetype":"venue"
},
  "geometry": {"coordinates":[-63.579120636,44.6377067566],"type":"Point"}
}