{
  "type": "Feature",
  "properties": {
    "addr:full":"3 Birgitta Cres Etobicoke ON M9C 3W1",
    "addr:housenumber":"3",
    "addr:postcode":"m9c 3w1",
    "addr:street":"Birgitta Cres",
    "iso:country":"CA",
    "sg:address":"3 Birgitta Cres",
    "sg:city":"Etobicoke",
    "sg:classifiers":[
        {
            "category":"Building & Trades",
            "subcategory":"Cleaning & Sanitation",
            "type":"Services"
        }
    ],
    "sg:phone":"+1 416 621 6390",
    "sg:postcode":"M9C 3W1",
    "sg:province":"ON",
    "sg:tags":[
        "butler",
        "maid"
    ],
    "wof:name":"King Service",
    "wof:placetype":"venue"
},
  "geometry": {"coordinates":[-79.573151,43.657097],"type":"Point"}
}