{
  "type": "Feature",
  "properties": {
    "addr:full":"168 Wellington St Kingston ON K7L 3E4",
    "addr:housenumber":"168",
    "addr:postcode":"k7l 3e4",
    "addr:street":"Wellington St",
    "iso:country":"CA",
    "sg:address":"168 Wellington St",
    "sg:city":"Kingston",
    "sg:classifiers":[
        {
            "category":"Professional",
            "subcategory":"Advertising",
            "type":"Services"
        }
    ],
    "sg:phone":"+1 613 544 1380",
    "sg:postcode":"K7L 3E4",
    "sg:province":"ON",
    "sg:tags":[
        "counselor"
    ],
    "wof:name":"Bermingham Marketing",
    "wof:placetype":"venue"
},
  "geometry": {"coordinates":[-76.482872,44.230949],"type":"Point"}
}