{
  "type": "Feature",
  "properties": {
    "addr:full":"50 Hudson Bay Ave Kirkland Lake ON P2N 2J2",
    "addr:housenumber":"50",
    "addr:postcode":"p2n 2j2",
    "addr:street":"Hudson Bay Ave",
    "iso:country":"CA",
    "sg:address":"50 Hudson Bay Ave",
    "sg:city":"Kirkland Lake",
    "sg:classifiers":[
        {
            "category":"Building & Trades",
            "subcategory":"Construction",
            "type":"Services"
        }
    ],
    "sg:phone":"+1 705 567 4698",
    "sg:postcode":"P2N 2J2",
    "sg:province":"ON",
    "sg:tags":[
        "general",
        "contractor"
    ],
    "wof:name":"Sauriol Haulage",
    "wof:placetype":"venue"
},
  "geometry": {"coordinates":[-80.0352554321,48.1475753784],"type":"Point"}
}