{
  "type": "Feature",
  "properties": {
    "addr:full":"10834 97 St NW Edmonton AB T5H 2M3",
    "addr:housenumber":"10834",
    "addr:postcode":"t5h 2m3",
    "addr:street":"97 St Nw",
    "iso:country":"CA",
    "sg:address":"10834 97 St NW",
    "sg:city":"Edmonton",
    "sg:classifiers":[
        {
            "category":"Wholesale",
            "subcategory":"Durable Goods & Equipment",
            "type":"Manufacturing & Wholesale Goods"
        }
    ],
    "sg:phone":"+1 780 424 1777",
    "sg:postcode":"T5H 2M3",
    "sg:province":"AB",
    "sg:tags":[
        "exporter"
    ],
    "wof:name":"Meest Alberta Ltd",
    "wof:placetype":"venue"
},
  "geometry": {"coordinates":[-113.490784,53.554386],"type":"Point"}
}