{
  "type": "Feature",
  "properties": {
    "addr:full":"115 Rue Principale Aylmer QC J9H 3M2",
    "addr:housenumber":"115",
    "addr:postcode":"j9h 3m2",
    "addr:street":"Rue Principale",
    "iso:country":"CA",
    "sg:address":"115 Rue Principale",
    "sg:city":"Aylmer",
    "sg:classifiers":[
        {
            "category":"Government",
            "subcategory":"Office",
            "type":"Public Place"
        }
    ],
    "sg:phone":"+1 819 685 5005",
    "sg:postcode":"J9H 3M2",
    "sg:province":"QC",
    "sg:tags":[
        "village"
    ],
    "wof:name":"Aylmer Hotel DE Ville",
    "wof:placetype":"venue"
},
  "geometry": {"coordinates":[-75.84507751460001,45.3950309753],"type":"Point"}
}