{
  "type": "Feature",
  "properties": {
    "addr:full":"871 Erie St E Windsor ON N9A 3Y7",
    "addr:housenumber":"871",
    "addr:postcode":"n9a 3y7",
    "addr:street":"Erie St E",
    "iso:country":"CA",
    "sg:address":"871 Erie St E",
    "sg:city":"Windsor",
    "sg:classifiers":[
        {
            "category":"Shopping",
            "subcategory":"Gifts & Souvenirs",
            "type":"Retail Goods"
        }
    ],
    "sg:phone":"+1 519 253 4016",
    "sg:postcode":"N9A 3Y7",
    "sg:province":"ON",
    "sg:tags":[
        "housewares",
        "shop"
    ],
    "wof:name":"Giuliana Housewares & Gifts",
    "wof:placetype":"venue"
},
  "geometry": {"coordinates":[-83.02117919920001,42.3132324219],"type":"Point"}
}