{
  "type": "Feature",
  "properties": {
    "addr:full":"459 Banff Ave Banff AB T1L 1H1",
    "addr:housenumber":"459",
    "addr:postcode":"t1l 1h1",
    "addr:street":"Banff Ave",
    "iso:country":"CA",
    "sg:address":"459 Banff Ave",
    "sg:city":"Banff",
    "sg:classifiers":[
        {
            "category":"Personal",
            "type":"Services"
        }
    ],
    "sg:phone":"+1 403 762 3307",
    "sg:postcode":"T1L 1H1",
    "sg:province":"AB",
    "sg:tags":[
        "therapist",
        "massage"
    ],
    "wof:name":"Grotto Spa",
    "wof:placetype":"venue"
},
  "geometry": {"coordinates":[-115.56414032000001,51.1828422546],"type":"Point"}
}