{
  "type": "Feature",
  "properties": {
    "iso:country":"CA",
    "sg:address":"355 Rue Collard O",
    "sg:city":"Alma",
    "sg:classifiers":[
        {
            "category":"Personal",
            "subcategory":"Shoe Repair & Shine",
            "type":"Services"
        }
    ],
    "sg:phone":"+1 418 668 0430",
    "sg:postcode":"G8B 1M8",
    "sg:province":"QC",
    "sg:tags":[
        "repairing",
        "boot"
    ],
    "wof:name":"Cordonnerie Alma Centre-Ville",
    "wof:placetype":"venue"
},
  "geometry": {"coordinates":[-71.647567749,48.5474357605],"type":"Point"}
}