{
  "type": "Feature",
  "properties": {
    "addr:full":"3835 Broadway Ave Smithers BC V0J 2N0",
    "addr:housenumber":"3835",
    "addr:postcode":"v0j 2n0",
    "addr:street":"Broadway Ave",
    "iso:country":"CA",
    "sg:address":"3835 Broadway Ave",
    "sg:city":"Smithers",
    "sg:classifiers":[
        {
            "category":"Building & Trades",
            "subcategory":"Plumbing",
            "type":"Services"
        }
    ],
    "sg:phone":"+1 250 847 3060",
    "sg:postcode":"V0J 2N0",
    "sg:province":"BC",
    "sg:tags":[
        "contractor"
    ],
    "wof:name":"North Central Plumbing & Htg",
    "wof:placetype":"venue"
},
  "geometry": {"coordinates":[-127.17440000000001,54.779728],"type":"Point"}
}