{
  "type": "Feature",
  "properties": {
    "addr:full":"Toronto ON M5V 1Z8",
    "addr:postcode":"m5v 1z8",
    "iso:country":"CA",
    "sg:city":"Toronto",
    "sg:classifiers":[
        {
            "category":"Banks & Credit Unions",
            "subcategory":"Investment Brokerage",
            "type":"Services"
        }
    ],
    "sg:phone":"+1 416 364 5311",
    "sg:postcode":"M5V 1Z8",
    "sg:province":"ON",
    "wof:name":"Granite Venture Partners Inc",
    "wof:placetype":"venue"
},
  "geometry": {"coordinates":[-79.3916473389,43.6499176025],"type":"Point"}
}