{
  "type": "Feature",
  "properties": {
    "iso:country":"CA",
    "sg:address":"1493 Centre Rd",
    "sg:city":"Carlisle",
    "sg:classifiers":[
        {
            "category":"Health Services",
            "subcategory":"Doctor",
            "type":"Services"
        }
    ],
    "sg:phone":"+1 905 689 0733",
    "sg:postcode":"L0R 1H2",
    "sg:province":"ON",
    "sg:tags":[
        "dentist"
    ],
    "wof:name":"Rodgers, Kelly D DDS",
    "wof:placetype":"venue"
},
  "geometry": {"coordinates":[-79.982109,43.395081],"type":"Point"}
}