{
  "type": "Feature",
  "properties": {
    "iso:country":"CA",
    "sg:address":"47 Glencairn Ave",
    "sg:city":"Toronto",
    "sg:classifiers":[
        {
            "category":"Wholesale",
            "subcategory":"Photographic Equipment",
            "type":"Manufacturing & Wholesale Goods"
        }
    ],
    "sg:phone":"+1 416 483 9700",
    "sg:postcode":"M4R 1M6",
    "sg:province":"ON",
    "sg:tags":[
        "motion",
        "picture",
        "supply"
    ],
    "wof:name":"Moto Cam",
    "wof:placetype":"venue"
},
  "geometry": {"coordinates":[-79.40315246580001,43.7177238464],"type":"Point"}
}