{
  "type": "Feature",
  "properties": {
    "addr:full":"2605 49 St NW Edmonton AB T6L 3W8",
    "addr:housenumber":"2605",
    "addr:postcode":"t6l 3w8",
    "addr:street":"49 St Nw",
    "iso:country":"CA",
    "sg:address":"2605 49 St NW",
    "sg:city":"Edmonton",
    "sg:classifiers":[
        {
            "category":"Building & Trades",
            "subcategory":"Cleaning & Sanitation",
            "type":"Services"
        }
    ],
    "sg:phone":"+1 780 461 8276",
    "sg:postcode":"T6L 3W8",
    "sg:province":"AB",
    "sg:tags":[
        "janitor"
    ],
    "wof:name":"United Cleanco",
    "wof:placetype":"venue"
},
  "geometry": {"coordinates":[-113.41817500000001,53.45752],"type":"Point"}
}