{
  "type": "Feature",
  "properties": {
    "iso:country":"CA",
    "sg:city":"Revelstoke",
    "sg:classifiers":[
        {
            "category":"Organizations",
            "subcategory":"Community Association",
            "type":"Services"
        }
    ],
    "sg:phone":"+1 250 837 9311",
    "sg:postcode":"V0E 2S0",
    "sg:province":"BC",
    "sg:tags":[
        "environmental",
        "org"
    ],
    "wof:name":"Columbia Mountains Institute",
    "wof:placetype":"venue"
},
  "geometry": {"coordinates":[-118.19546508800001,51.0000343323],"type":"Point"}
}