{
  "type": "Feature",
  "properties": {
    "iso:country":"CA",
    "sg:address":"4989 Victoria Dr",
    "sg:city":"Vancouver",
    "sg:classifiers":[
        {
            "category":"Restaurant",
            "type":"Food & Drink"
        }
    ],
    "sg:phone":"+1 604 321 6862",
    "sg:postcode":"V5P 3T7",
    "sg:province":"BC",
    "wof:name":"Wong Gok Restaurant",
    "wof:placetype":"venue"
},
  "geometry": {"coordinates":[-123.06549835200001,49.2393836975],"type":"Point"}
}