{
  "type": "Feature",
  "properties": {
    "addr:full":"222 Boul St-Pierre E Caraquet NB E1W 1B1",
    "addr:housenumber":"222",
    "addr:postcode":"e1w 1b1",
    "addr:street":"Boul St-Pierre E Caraquet",
    "iso:country":"CA",
    "sg:address":"222 Boul St-Pierre E",
    "sg:city":"Caraquet",
    "sg:classifiers":[
        {
            "category":"Social Services",
            "type":"Services"
        }
    ],
    "sg:phone":"+1 506 727 6183",
    "sg:postcode":"E1W 1B1",
    "sg:province":"NB",
    "sg:tags":[
        "youth",
        "organization",
        "center"
    ],
    "wof:name":"Maison Des Jeunes DE Caraquet",
    "wof:placetype":"venue"
},
  "geometry": {"coordinates":[-64.908585,47.795834],"type":"Point"}
}