{
  "type": "Feature",
  "properties": {
    "addr:full":"17 Lakevista Ave Markham ON L3P 1H4",
    "addr:housenumber":"17",
    "addr:postcode":"l3p 1h4",
    "addr:street":"Lakevista Ave",
    "iso:country":"CA",
    "sg:address":"17 Lakevista Ave",
    "sg:city":"Markham",
    "sg:classifiers":[
        {
            "category":"Social Services",
            "type":"Services"
        }
    ],
    "sg:phone":"+1 905 201 9052",
    "sg:postcode":"L3P 1H4",
    "sg:province":"ON",
    "sg:tags":[
        "instruction",
        "health",
        "care"
    ],
    "wof:name":"Coram Health Care",
    "wof:placetype":"venue"
},
  "geometry": {"coordinates":[-79.2779998779,43.8668708801],"type":"Point"}
}