{
  "type": "Feature",
  "properties": {
    "iso:country":"CA",
    "sg:city":"North Vancouver",
    "sg:classifiers":[
        {
            "category":"Restaurant",
            "type":"Food & Drink"
        }
    ],
    "sg:phone":"+1 604 986 3733",
    "sg:postcode":"V7J 3S8",
    "sg:province":"BC",
    "wof:name":"Golden Pearl Restaurant",
    "wof:placetype":"venue"
},
  "geometry": {"coordinates":[-123.04066467299999,49.3087806702],"type":"Point"}
}