{
  "type": "Feature",
  "properties": {
    "addr:full":"1100 Finch Ave W #11D North York ON M3J 2E2",
    "addr:housenumber":"1100",
    "addr:postcode":"m3j 2e2",
    "addr:street":"Finch Ave W # 11D",
    "iso:country":"CA",
    "sg:address":"1100 Finch Ave W #11D",
    "sg:city":"North York",
    "sg:classifiers":[
        {
            "category":"Manufacturing",
            "subcategory":"Motor Vehicles & Parts",
            "type":"Manufacturing & Wholesale Goods"
        }
    ],
    "sg:phone":"+1 416 667 8884",
    "sg:postcode":"M3J 2E2",
    "sg:province":"ON",
    "sg:tags":[
        "automobile",
        "wrecking"
    ],
    "wof:name":"Auto Parts By Jk",
    "wof:placetype":"venue"
},
  "geometry": {"coordinates":[-79.475441,43.76709],"type":"Point"}
}