{
  "type": "Feature",
  "properties": {
    "addr:full":"Pikangikum ON P0V 2L0",
    "addr:postcode":"p0v 2l0",
    "iso:country":"CA",
    "sg:city":"Pikangikum",
    "sg:classifiers":[
        {
            "category":"Social Services",
            "type":"Services"
        }
    ],
    "sg:phone":"+1 807 773 1103",
    "sg:postcode":"P0V 2L0",
    "sg:province":"ON",
    "sg:tags":[
        "organization",
        "welfare"
    ],
    "wof:name":"Tikinagan Child & Family Svc",
    "wof:placetype":"venue"
},
  "geometry": {"coordinates":[-93.6466827393,51.7360725403],"type":"Point"}
}