{
  "type": "Feature",
  "properties": {
    "addr:full":"RR 1 Niton Junction AB T0E 1S0",
    "addr:postcode":"t0e 1s0",
    "addr:street":"Rr 1 Niton Junction",
    "iso:country":"CA",
    "sg:address":"RR 1",
    "sg:city":"Niton Junction",
    "sg:classifiers":[
        {
            "category":"Organizations",
            "subcategory":"Professional Association",
            "type":"Services"
        }
    ],
    "sg:phone":"+1 780 795 2439",
    "sg:postcode":"T0E 1S0",
    "sg:province":"AB",
    "wof:name":"Mackay Community Ctr",
    "wof:placetype":"venue"
},
  "geometry": {"coordinates":[-115.770782471,53.6356887817],"type":"Point"}
}