{
  "type": "Feature",
  "properties": {
    "addr:full":"10434 Mayfield Rd NW Edmonton AB T5P 4P4",
    "addr:housenumber":"10434",
    "addr:postcode":"t5p 4p4",
    "addr:street":"Mayfield Rd Nw",
    "iso:country":"CA",
    "sg:address":"10434 Mayfield Rd NW",
    "sg:city":"Edmonton",
    "sg:classifiers":[
        {
            "category":"Home & Garden",
            "subcategory":"Furniture",
            "type":"Retail Goods"
        }
    ],
    "sg:phone":"+1 780 483 5949",
    "sg:postcode":"T5P 4P4",
    "sg:province":"AB",
    "sg:tags":[
        "builder",
        "custom"
    ],
    "wof:name":"Leather Elite",
    "wof:placetype":"venue"
},
  "geometry": {"coordinates":[-113.612968,53.547127],"type":"Point"}
}