{
  "type": "Feature",
  "properties": {
    "addr:full":"Maple Ridge BC V2X 0Y6",
    "addr:postcode":"v2x 0y6",
    "iso:country":"CA",
    "sg:city":"Maple Ridge",
    "sg:classifiers":[
        {
            "category":"Retail",
            "subcategory":"Repair Shop",
            "type":"Services"
        }
    ],
    "sg:phone":"+1 604 465 9465",
    "sg:postcode":"V2X 0Y6",
    "sg:province":"BC",
    "sg:tags":[
        "equipment",
        "electronic",
        "supply"
    ],
    "wof:name":"Mei Monitor Enterprises Ltd",
    "wof:placetype":"venue"
},
  "geometry": {"coordinates":[-122.665871,49.210285],"type":"Point"}
}