{
  "type": "Feature",
  "properties": {
    "addr:full":"Vancouver BC V5M 4V8",
    "addr:postcode":"v5m 4v8",
    "iso:country":"CA",
    "sg:city":"Vancouver",
    "sg:classifiers":[
        {
            "category":"Wholesale",
            "subcategory":"Furniture",
            "type":"Manufacturing & Wholesale Goods"
        }
    ],
    "sg:phone":"+1 604 299 4899",
    "sg:postcode":"V5M 4V8",
    "sg:province":"BC",
    "wof:name":"Alexander Furniture Agencies",
    "wof:placetype":"venue"
},
  "geometry": {"coordinates":[-123.023926,49.263245],"type":"Point"}
}