{
  "type": "Feature",
  "properties": {
    "iso:country":"CA",
    "sg:address":"18 3rd Ave S",
    "sg:city":"Niverville",
    "sg:classifiers":[
        {
            "category":"Shopping",
            "subcategory":"Florist",
            "type":"Retail Goods"
        }
    ],
    "sg:phone":"+1 204 388 4057",
    "sg:postcode":"R0A 1E0",
    "sg:province":"MB",
    "wof:name":"Country Blossoms Florists",
    "wof:placetype":"venue"
},
  "geometry": {"coordinates":[-97.0414428711,49.6059188843],"type":"Point"}
}