{
  "type": "Feature",
  "properties": {
    "addr:full":"2146 Queen St E Toronto ON M4E 1E3",
    "addr:housenumber":"2146",
    "addr:postcode":"m4e 1e3",
    "addr:street":"Queen St E",
    "iso:country":"CA",
    "sg:address":"2146 Queen St E",
    "sg:city":"Toronto",
    "sg:classifiers":[
        {
            "category":"Food & Beverages",
            "subcategory":"Specialty",
            "type":"Retail Goods"
        }
    ],
    "sg:phone":"+1 416 693 5328",
    "sg:postcode":"M4E 1E3",
    "sg:province":"ON",
    "sg:tags":[
        "health",
        "diet"
    ],
    "wof:name":"Optimum Natural Foods",
    "wof:placetype":"venue"
},
  "geometry": {"coordinates":[-79.2930221558,43.671672821],"type":"Point"}
}