{
  "type": "Feature",
  "properties": {
    "addr:full":"455 Boul Sainte-Anne Pointe-Au-Pere QC G5M 1E9",
    "addr:housenumber":"455",
    "addr:postcode":"g5m 1e9",
    "addr:street":"Boul Sainte-Anne Pointe-Au-Pere",
    "iso:country":"CA",
    "sg:address":"455 Boul Sainte-Anne",
    "sg:city":"Pointe-Au-Pere",
    "sg:classifiers":[
        {
            "category":"Autos & Motor Vehicles",
            "subcategory":"Automobile Sales",
            "type":"Retail Goods"
        }
    ],
    "sg:phone":"+1 418 724 7888",
    "sg:postcode":"G5M 1E9",
    "sg:province":"QC",
    "sg:tags":[
        "repairing",
        "car"
    ],
    "wof:name":"Automobiles Rp Inc",
    "wof:placetype":"venue"
},
  "geometry": {"coordinates":[-68.48168200000001,48.498295],"type":"Point"}
}