{
  "type": "Feature",
  "properties": {
    "iso:country":"CA",
    "sg:city":"Port Carling",
    "sg:classifiers":[
        {
            "category":"Building & Trades",
            "subcategory":"Construction",
            "type":"Services"
        }
    ],
    "sg:phone":"+1 705 765 3212",
    "sg:postcode":"P0B 1J0",
    "sg:province":"ON",
    "sg:tags":[
        "excavating",
        "contractor"
    ],
    "wof:name":"Mc Dermott & Sons Construction",
    "wof:placetype":"venue"
},
  "geometry": {"coordinates":[-79.5775680542,45.1204833984],"type":"Point"}
}