{
  "type": "Feature",
  "properties": {
    "iso:country":"CA",
    "sg:address":"62 Swayne St",
    "sg:city":"Cobourg",
    "sg:classifiers":[
        {
            "category":"Shopping",
            "subcategory":"Musical Instruments",
            "type":"Retail Goods"
        }
    ],
    "sg:phone":"+1 905 373 1991",
    "sg:postcode":"K9A 1K5",
    "sg:province":"ON",
    "wof:name":"George's Guitars & Music",
    "wof:placetype":"venue"
},
  "geometry": {"coordinates":[-78.163567,43.961094],"type":"Point"}
}