{
  "type": "Feature",
  "properties": {
    "iso:country":"CA",
    "sg:address":"163 Henderson Hwy",
    "sg:city":"Winnipeg",
    "sg:classifiers":[
        {
            "category":"Shopping",
            "subcategory":"Bicycles & Sporting Goods",
            "type":"Retail Goods"
        }
    ],
    "sg:phone":"+1 204 668 2816",
    "sg:postcode":"R2L 1L5",
    "sg:province":"MB",
    "sg:tags":[
        "equipment",
        "diver",
        "supply"
    ],
    "wof:name":"3 Fathoms Scuba Ltd",
    "wof:placetype":"venue"
},
  "geometry": {"coordinates":[-97.116028,49.912422],"type":"Point"}
}