{
  "type": "Feature",
  "properties": {
    "addr:full":"289 Main St Wellington ON K0K 3L0",
    "addr:housenumber":"289",
    "addr:postcode":"k0k 3l0",
    "addr:street":"Main St",
    "iso:country":"CA",
    "sg:address":"289 Main St",
    "sg:city":"Wellington",
    "sg:classifiers":[
        {
            "category":"Home & Garden",
            "subcategory":"Household Appliances",
            "type":"Retail Goods"
        }
    ],
    "sg:phone":"+1 613 399 3203",
    "sg:postcode":"K0K 3L0",
    "sg:province":"ON",
    "sg:tags":[
        "hardware"
    ],
    "wof:name":"Wellington Home Hardware",
    "wof:placetype":"venue"
},
  "geometry": {"coordinates":[-77.35020400000001,43.951569],"type":"Point"}
}