{
  "type": "Feature",
  "properties": {
    "addr:full":"Mississauga ON L5T 2A9",
    "addr:postcode":"l5t 2a9",
    "iso:country":"CA",
    "sg:city":"Mississauga",
    "sg:classifiers":[
        {
            "category":"Home & Garden",
            "subcategory":"Household Appliances",
            "type":"Retail Goods"
        }
    ],
    "sg:phone":"+1 905 670 0773",
    "sg:postcode":"L5T 2A9",
    "sg:province":"ON",
    "sg:tags":[
        "machine",
        "sewing"
    ],
    "wof:name":"Sewing Machine Svc",
    "wof:placetype":"venue"
},
  "geometry": {"coordinates":[-79.6816329956,43.6625061035],"type":"Point"}
}