{
  "type": "Feature",
  "properties": {
    "iso:country":"CA",
    "sg:city":"North York",
    "sg:classifiers":[
        {
            "category":"Retail",
            "subcategory":"Auto Repair",
            "type":"Services"
        }
    ],
    "sg:phone":"+1 416 746 1166",
    "sg:postcode":"M9M 2Y3",
    "sg:province":"ON",
    "sg:tags":[
        "repairing",
        "automobile"
    ],
    "wof:name":"Naser Auto Repairs & Svc Ltd",
    "wof:placetype":"venue"
},
  "geometry": {"coordinates":[-79.540459,43.75251],"type":"Point"}
}