{
  "type": "Feature",
  "properties": {
    "addr:full":"9841 Av Du Parc-Georges Montreal-Nord QC H1H 4X6",
    "addr:housenumber":"9841",
    "addr:postcode":"h1h 4x6",
    "addr:street":"Av Du Parc-Georges",
    "iso:country":"CA",
    "sg:address":"9841 Av Du Parc-Georges",
    "sg:city":"Montreal-Nord",
    "sg:classifiers":[
        {
            "category":"Autos & Motor Vehicles",
            "subcategory":"Automobile Sales",
            "type":"Retail Goods"
        }
    ],
    "sg:phone":"+1 514 325 3244",
    "sg:postcode":"H1H 4X6",
    "sg:province":"QC",
    "sg:tags":[
        "car",
        "dealer"
    ],
    "wof:name":"J C Auto",
    "wof:placetype":"venue"
},
  "geometry": {"coordinates":[-73.6362533569,45.5778694153],"type":"Point"}
}