{
  "type": "Feature",
  "properties": {
    "addr:full":"1145 Pembroke St E Pembroke ON K8A 7R4",
    "addr:housenumber":"1145",
    "addr:postcode":"k8a 7r4",
    "addr:street":"Pembroke St E",
    "iso:country":"CA",
    "sg:address":"1145 Pembroke St E",
    "sg:city":"Pembroke",
    "sg:classifiers":[
        {
            "category":"Building & Trades",
            "subcategory":"Construction",
            "type":"Services"
        }
    ],
    "sg:phone":"+1 613 732 7311",
    "sg:postcode":"K8A 7R4",
    "sg:province":"ON",
    "sg:tags":[
        "roofing",
        "contractor"
    ],
    "wof:name":"Irvcon Limited",
    "wof:placetype":"venue"
},
  "geometry": {"coordinates":[-77.0855255127,45.8240318298],"type":"Point"}
}