{
  "type": "Feature",
  "properties": {
    "iso:country":"CA",
    "sg:address":"RR 6 STN Main",
    "sg:city":"Kingston",
    "sg:classifiers":[
        {
            "category":"Social Services",
            "subcategory":"Child Care",
            "type":"Services"
        }
    ],
    "sg:phone":"+1 613 542 8931",
    "sg:postcode":"K7L 4V3",
    "sg:province":"ON",
    "wof:name":"Meadowcrest Community Ctr",
    "wof:placetype":"venue"
},
  "geometry": {"coordinates":[-76.47933197019999,44.2315368652],"type":"Point"}
}