{
  "type": "Feature",
  "properties": {
    "iso:country":"CA",
    "sg:address":"335 Rue Benjamin-Hudon",
    "sg:city":"Saint-Laurent",
    "sg:classifiers":[
        {
            "category":"Wholesale",
            "subcategory":"Fruits & Vegetables",
            "type":"Manufacturing & Wholesale Goods"
        }
    ],
    "sg:phone":"+1 514 337 9251",
    "sg:postcode":"H4N 1J1",
    "sg:province":"QC",
    "wof:name":"Robert Charbonneau Frts & Lgms",
    "wof:placetype":"venue"
},
  "geometry": {"coordinates":[-73.6588439941,45.5238609314],"type":"Point"}
}