{
  "type": "Feature",
  "properties": {
    "addr:full":"233 Cross Ave Oakville ON L6J 2W9",
    "addr:housenumber":"233",
    "addr:postcode":"l6j 2w9",
    "addr:street":"Cross Ave",
    "iso:country":"CA",
    "sg:address":"233 Cross Ave",
    "sg:city":"Oakville",
    "sg:classifiers":[
        {
            "category":"Retail",
            "subcategory":"Laundry & Dry Cleaning",
            "type":"Services"
        }
    ],
    "sg:phone":"+1 905 815 0797",
    "sg:postcode":"L6J 2W9",
    "sg:province":"ON",
    "sg:tags":[
        "cleaners"
    ],
    "wof:name":"Top Hat Cleaners",
    "wof:placetype":"venue"
},
  "geometry": {"coordinates":[-79.6830291748,43.4568710327],"type":"Point"}
}