{
  "type": "Feature",
  "properties": {
    "addr:full":"561 Josephine St Nelson BC V1L 1W5",
    "addr:housenumber":"561",
    "addr:postcode":"bc v1l 1w5",
    "addr:street":"Josephine St",
    "iso:country":"CA",
    "sg:address":"561 Josephine St",
    "sg:city":"Nelson",
    "sg:classifiers":[
        {
            "category":"Home & Garden",
            "subcategory":"Furniture",
            "type":"Retail Goods"
        }
    ],
    "sg:phone":"+1 250 352 6432",
    "sg:postcode":"V1L 1W5",
    "sg:province":"BC",
    "wof:name":"Nelson Home Furn & Appl Ltd",
    "wof:placetype":"venue"
},
  "geometry": {"coordinates":[-117.292068,49.492069],"type":"Point"}
}