{
  "type": "Feature",
  "properties": {
    "iso:country":"CA",
    "sg:address":"1450 Pearson Pl",
    "sg:city":"Kamloops",
    "sg:classifiers":[
        {
            "category":"Government",
            "subcategory":"Office",
            "type":"Public Place"
        }
    ],
    "sg:phone":"+1 250 614 4105",
    "sg:postcode":"V1S 1J9",
    "sg:province":"BC",
    "wof:name":"British Columbia Buildings",
    "wof:placetype":"venue"
},
  "geometry": {"coordinates":[-120.378647,50.649982],"type":"Point"}
}