{
  "type": "Feature",
  "properties": {
    "addr:full":"1789 Bath Rd Kingston ON K7M 4Y3",
    "addr:housenumber":"1789",
    "addr:postcode":"k7m 4y3",
    "addr:street":"Bath Rd",
    "iso:country":"CA",
    "sg:address":"1789 Bath Rd",
    "sg:city":"Kingston",
    "sg:classifiers":[
        {
            "category":"Education",
            "subcategory":"School",
            "type":"Public Place"
        }
    ],
    "sg:phone":"+1 613 389 2130",
    "sg:postcode":"K7M 4Y3",
    "sg:province":"ON",
    "wof:name":"Frontenac Secondary School",
    "wof:placetype":"venue"
},
  "geometry": {"coordinates":[-76.5412979126,44.2384033203],"type":"Point"}
}