{
  "type": "Feature",
  "properties": {
    "addr:full":"5212 51 St Eckville AB T0M 0X0",
    "addr:housenumber":"5212",
    "addr:postcode":"t0m 0x0",
    "addr:street":"51 St",
    "iso:country":"CA",
    "sg:address":"5212 51 St",
    "sg:city":"Eckville",
    "sg:classifiers":[
        {
            "category":"Recreation",
            "type":"Entertainment"
        }
    ],
    "sg:phone":"+1 403 746 2442",
    "sg:postcode":"T0M 0X0",
    "sg:province":"AB",
    "sg:tags":[
        "club",
        "curling"
    ],
    "wof:name":"Eckville Curling Club",
    "wof:placetype":"venue"
},
  "geometry": {"coordinates":[-114.370598,52.363079],"type":"Point"}
}