{
  "type": "Feature",
  "properties": {
    "addr:full":"3200 Stanley Ave Niagara Falls ON L2E 6S4",
    "addr:housenumber":"3200",
    "addr:postcode":"l2e 6s4",
    "addr:street":"Stanley Ave",
    "iso:country":"CA",
    "sg:address":"3200 Stanley Ave",
    "sg:city":"Niagara Falls",
    "sg:classifiers":[
        {
            "category":"Government",
            "subcategory":"Office",
            "type":"Public Place"
        }
    ],
    "sg:phone":"+1 905 356 1355",
    "sg:postcode":"L2E 6S4",
    "sg:province":"ON",
    "sg:tags":[
        "municipality"
    ],
    "wof:name":"Niagara Falls Municipal Works",
    "wof:placetype":"venue"
},
  "geometry": {"coordinates":[-79.0869216919,43.1303215027],"type":"Point"}
}