{
  "type": "Feature",
  "properties": {
    "addr:full":"Calgary AB T2J 7G9",
    "addr:postcode":"t2j 7g9",
    "iso:country":"CA",
    "sg:city":"Calgary",
    "sg:classifiers":[
        {
            "category":"Shopping",
            "subcategory":"Bicycles & Sporting Goods",
            "type":"Retail Goods"
        }
    ],
    "sg:phone":"+1 403 640 1273",
    "sg:postcode":"T2J 7G9",
    "sg:province":"AB",
    "sg:tags":[
        "tackle",
        "fishing"
    ],
    "wof:name":"Fish Tales Fly Shop Ltd",
    "wof:placetype":"venue"
},
  "geometry": {"coordinates":[-114.06999969500001,50.9439048767],"type":"Point"}
}