{
  "type": "Feature",
  "properties": {
    "addr:full":"480 Ravineview Way Oakville ON L6H 6S8",
    "addr:housenumber":"480",
    "addr:postcode":"l6h 6s8",
    "addr:street":"Ravineview Way",
    "iso:country":"CA",
    "sg:address":"480 Ravineview Way",
    "sg:city":"Oakville",
    "sg:classifiers":[
        {
            "category":"Building & Trades",
            "subcategory":"Construction",
            "type":"Services"
        }
    ],
    "sg:phone":"+1 905 257 9310",
    "sg:postcode":"L6H 6S8",
    "sg:province":"ON",
    "sg:tags":[
        "painter"
    ],
    "wof:name":"Indigo Painting Inc",
    "wof:placetype":"venue"
},
  "geometry": {"coordinates":[-79.709114,43.487968],"type":"Point"}
}