{
  "type": "Feature",
  "properties": {
    "addr:full":"800 Manitoba Ave Selkirk MB R1A 2C9",
    "addr:housenumber":"800",
    "addr:postcode":"r1a 2c9",
    "addr:street":"Manitoba Ave",
    "iso:country":"CA",
    "sg:address":"800 Manitoba Ave",
    "sg:city":"Selkirk",
    "sg:classifiers":[
        {
            "category":"Health Services",
            "subcategory":"Nursing And Care Facility",
            "type":"Services"
        }
    ],
    "sg:phone":"+1 204 482 6601",
    "sg:postcode":"R1A 2C9",
    "sg:province":"MB",
    "sg:tags":[
        "personal",
        "home"
    ],
    "wof:name":"Tudor House Personal Care Home",
    "wof:placetype":"venue"
},
  "geometry": {"coordinates":[-96.88785552980001,50.1514968872],"type":"Point"}
}