{
  "type": "Feature",
  "properties": {
    "addr:full":"313 5th Ave Stewart BC V0T 1W0",
    "addr:housenumber":"313",
    "addr:postcode":"v0t 1w0",
    "addr:street":"5Th Ave",
    "iso:country":"CA",
    "sg:address":"313 5th Ave",
    "sg:city":"Stewart",
    "sg:classifiers":[
        {
            "category":"Restaurant",
            "type":"Food & Drink"
        }
    ],
    "sg:phone":"+1 250 636 2166",
    "sg:postcode":"V0T 1W0",
    "sg:province":"BC",
    "wof:name":"Bitter Creek Cafe",
    "wof:placetype":"venue"
},
  "geometry": {"coordinates":[-129.98503099999999,55.935856],"type":"Point"}
}