{
  "type": "Feature",
  "properties": {
    "addr:full":"216 Boul Brunswick Pointe-Claire QC H9R 1A6",
    "addr:housenumber":"216",
    "addr:postcode":"h9r 1a6",
    "addr:street":"Boul Brunswick",
    "iso:country":"CA",
    "sg:address":"216 Boul Brunswick",
    "sg:city":"Pointe-Claire",
    "sg:classifiers":[
        {
            "category":"Autos & Motor Vehicles",
            "subcategory":"Automobile Sales",
            "type":"Retail Goods"
        }
    ],
    "sg:phone":"+1 514 697 7655",
    "sg:postcode":"H9R 1A6",
    "sg:province":"QC",
    "sg:tags":[
        "equipment",
        "aircraft",
        "parts",
        "supply"
    ],
    "wof:name":"Simex Equipment Inc",
    "wof:placetype":"venue"
},
  "geometry": {"coordinates":[-73.82347900000001,45.470345],"type":"Point"}
}