{
  "type": "Feature",
  "properties": {
    "addr:full":"23 Main St Seaforth ON N0K 1W0",
    "addr:housenumber":"23",
    "addr:postcode":"n0k 1w0",
    "addr:street":"Main St",
    "iso:country":"CA",
    "sg:address":"23 Main St",
    "sg:city":"Seaforth",
    "sg:classifiers":[
        {
            "category":"Food & Beverages",
            "subcategory":"Bakery",
            "type":"Retail Goods"
        }
    ],
    "sg:phone":"+1 519 527 1803",
    "sg:postcode":"N0K 1W0",
    "sg:province":"ON",
    "sg:tags":[
        "baker"
    ],
    "wof:name":"Seaforth Bakery",
    "wof:placetype":"venue"
},
  "geometry": {"coordinates":[-81.3926849365,43.5539741516],"type":"Point"}
}