{
  "type": "Feature",
  "properties": {
    "iso:country":"CA",
    "sg:address":"PO Box 329",
    "sg:city":"Fort Chipewyan",
    "sg:classifiers":[
        {
            "category":"Restaurant",
            "type":"Food & Drink"
        }
    ],
    "sg:phone":"+1 780 697 3737",
    "sg:postcode":"T0P 1B0",
    "sg:province":"AB",
    "wof:name":"Athabasca Cafe & Dining Lounge",
    "wof:placetype":"venue"
},
  "geometry": {"coordinates":[-111.15284699999999,58.713268],"type":"Point"}
}