{
  "type": "Feature",
  "properties": {
    "addr:full":"Cardston AB T0K 0K0",
    "addr:postcode":"t0k 0k0",
    "iso:country":"CA",
    "sg:city":"Cardston",
    "sg:classifiers":[
        {
            "category":"Shopping",
            "type":"Retail Goods"
        }
    ],
    "sg:phone":"+1 403 653 4757",
    "sg:postcode":"T0K 0K0",
    "sg:province":"AB",
    "sg:tags":[
        "picture",
        "frame"
    ],
    "wof:name":"Line Upon Line Studio",
    "wof:placetype":"venue"
},
  "geometry": {"coordinates":[-113.327667236,49.2003822327],"type":"Point"}
}