{
  "type": "Feature",
  "properties": {
    "addr:full":"5329 Imperial St Burnaby BC V5J 1E5",
    "addr:housenumber":"5329",
    "addr:postcode":"v5j 1e5",
    "addr:street":"Imperial St",
    "iso:country":"CA",
    "sg:address":"5329 Imperial St",
    "sg:city":"Burnaby",
    "sg:classifiers":[
        {
            "category":"Retail",
            "subcategory":"Auto Repair",
            "type":"Services"
        }
    ],
    "sg:phone":"+1 604 436 2998",
    "sg:postcode":"V5J 1E5",
    "sg:province":"BC",
    "sg:tags":[
        "body",
        "automobile",
        "painting"
    ],
    "wof:name":"Chariot Auto Svc Inc",
    "wof:placetype":"venue"
},
  "geometry": {"coordinates":[-122.986434937,49.222114563],"type":"Point"}
}