{
  "type": "Feature",
  "properties": {
    "addr:full":"166 Saunders Rd Barrie ON L4N 9A4",
    "addr:housenumber":"166",
    "addr:postcode":"l4n 9a4",
    "addr:street":"Saunders Rd",
    "iso:country":"CA",
    "sg:address":"166 Saunders Rd",
    "sg:city":"Barrie",
    "sg:classifiers":[
        {
            "category":"Home & Garden",
            "subcategory":"Furniture",
            "type":"Retail Goods"
        }
    ],
    "sg:phone":"+1 705 739 1889",
    "sg:postcode":"L4N 9A4",
    "sg:province":"ON",
    "sg:tags":[
        "equipment",
        "kitchen",
        "cabinet"
    ],
    "wof:name":"Raywall Kitchens",
    "wof:placetype":"venue"
},
  "geometry": {"coordinates":[-79.67601000000001,44.332664],"type":"Point"}
}