{
  "type": "Feature",
  "properties": {
    "addr:full":"705 Princess Ave Brandon MB R7A 0P4",
    "addr:housenumber":"705",
    "addr:postcode":"r7a 0p4",
    "addr:street":"Princess Ave",
    "iso:country":"CA",
    "sg:address":"705 Princess Ave",
    "sg:city":"Brandon",
    "sg:classifiers":[
        {
            "category":"Government",
            "subcategory":"Office",
            "type":"Public Place"
        }
    ],
    "sg:phone":"+1 204 726 6279",
    "sg:postcode":"R7A 0P4",
    "sg:province":"MB",
    "wof:name":"Manitoba Consumer & Corporate",
    "wof:placetype":"venue"
},
  "geometry": {"coordinates":[-99.9475784302,49.8470153809],"type":"Point"}
}