{
  "type": "Feature",
  "properties": {
    "addr:full":"Advocate Harbour NS B0M 1A0",
    "addr:postcode":"b0m 1a0",
    "iso:country":"CA",
    "sg:city":"Advocate Harbour",
    "sg:classifiers":[
        {
            "category":"Organizations",
            "subcategory":"Religious Organization",
            "type":"Services"
        }
    ],
    "sg:phone":"+1 902 392 2078",
    "sg:postcode":"B0M 1A0",
    "sg:province":"NS",
    "sg:tags":[
        "church"
    ],
    "wof:name":"United Church",
    "wof:placetype":"venue"
},
  "geometry": {"coordinates":[-64.77971599999999,45.334534],"type":"Point"}
}