{
  "type": "Feature",
  "properties": {
    "iso:country":"CA",
    "sg:city":"Woodbridge",
    "sg:classifiers":[
        {
            "category":"Manufacturing",
            "subcategory":"Metals",
            "type":"Manufacturing & Wholesale Goods"
        }
    ],
    "sg:phone":"+1 905 851 2574",
    "sg:postcode":"L4L 5Z5",
    "sg:province":"ON",
    "sg:tags":[
        "spinning"
    ],
    "wof:name":"Kenspin Limited",
    "wof:placetype":"venue"
},
  "geometry": {"coordinates":[-79.562538,43.784756],"type":"Point"}
}