{
  "type": "Feature",
  "properties": {
    "addr:full":"325 Rue Du Roi Asbestos QC J1T 1S7",
    "addr:housenumber":"325",
    "addr:postcode":"j1t 1s7",
    "addr:street":"Rue Du Roi",
    "iso:country":"CA",
    "sg:address":"325 Rue Du Roi",
    "sg:city":"Asbestos",
    "sg:classifiers":[
        {
            "category":"Home & Garden",
            "subcategory":"Household Appliances",
            "type":"Retail Goods"
        }
    ],
    "sg:phone":"+1 819 879 7759",
    "sg:postcode":"J1T 1S7",
    "sg:province":"QC",
    "wof:name":"Appareils Electro-Menagers J-M",
    "wof:placetype":"venue"
},
  "geometry": {"coordinates":[-71.93103000000001,45.779282],"type":"Point"}
}