{
  "type": "Feature",
  "properties": {
    "addr:full":"115 Dundas St E Mississauga ON L5A 1W7",
    "addr:housenumber":"115",
    "addr:postcode":"l5a 1w7",
    "addr:street":"Dundas St E",
    "iso:country":"CA",
    "sg:address":"115 Dundas St E",
    "sg:city":"Mississauga",
    "sg:classifiers":[
        {
            "category":"Food & Beverages",
            "subcategory":"Specialty",
            "type":"Retail Goods"
        }
    ],
    "sg:phone":"+1 905 270 5299",
    "sg:postcode":"L5A 1W7",
    "sg:province":"ON",
    "sg:tags":[
        "herb"
    ],
    "wof:name":"Vanxuan Inc",
    "wof:placetype":"venue"
},
  "geometry": {"coordinates":[-79.61364,43.582855],"type":"Point"}
}