{
  "type": "Feature",
  "properties": {
    "addr:full":"Farm Star City SK S0E 1P0",
    "addr:postcode":"s0e 1p0",
    "iso:country":"CA",
    "sg:address":"Farm",
    "sg:city":"Star City",
    "sg:classifiers":[
        {
            "category":"Farming",
            "subcategory":"Nursery",
            "type":"Manufacturing & Wholesale Goods"
        }
    ],
    "sg:phone":"+1 306 863 2681",
    "sg:postcode":"S0E 1P0",
    "sg:province":"SK",
    "sg:tags":[
        "seed"
    ],
    "wof:name":"Birch Rose Acres Ltd",
    "wof:placetype":"venue"
},
  "geometry": {"coordinates":[-104.332069397,52.8635902405],"type":"Point"}
}