{
  "type": "Feature",
  "properties": {
    "iso:country":"CA",
    "sg:address":"666 Wonderland Rd N",
    "sg:city":"London",
    "sg:classifiers":[
        {
            "category":"Restaurant",
            "type":"Food & Drink"
        }
    ],
    "sg:phone":"+1 519 473 5702",
    "sg:postcode":"N6H 4K9",
    "sg:province":"ON",
    "wof:name":"Oar House Sports Bar & Grill",
    "wof:placetype":"venue"
},
  "geometry": {"coordinates":[-81.29332,42.984814],"type":"Point"}
}