{
  "type": "Feature",
  "properties": {
    "addr:full":"10120 Elbow Dr SW Calgary AB T2W 1E7",
    "addr:housenumber":"10120",
    "addr:postcode":"t2w 1e7",
    "addr:street":"Elbow Dr Sw",
    "iso:country":"CA",
    "sg:address":"10120 Elbow Dr SW",
    "sg:city":"Calgary",
    "sg:classifiers":[
        {
            "category":"Autos & Motor Vehicles",
            "subcategory":"Fuel & Gas Station",
            "type":"Retail Goods"
        }
    ],
    "sg:phone":"+1 403 255 3775",
    "sg:postcode":"T2W 1E7",
    "sg:province":"AB",
    "sg:tags":[
        "oil"
    ],
    "wof:name":"Neighbours Convenience Store",
    "wof:placetype":"venue"
},
  "geometry": {"coordinates":[-114.084602356,50.9633026123],"type":"Point"}
}