{
  "type": "Feature",
  "properties": {
    "addr:full":"100 Cardevco Rd Carp ON K0A 1L0",
    "addr:housenumber":"100",
    "addr:postcode":"k0a 1l0",
    "addr:street":"Cardevco Rd",
    "iso:country":"CA",
    "sg:address":"100 Cardevco Rd",
    "sg:city":"Carp",
    "sg:classifiers":[
        {
            "category":"Bus Charters",
            "type":"Transportation"
        }
    ],
    "sg:phone":"+1 613 836 7725",
    "sg:postcode":"K0A 1L0",
    "sg:province":"ON",
    "sg:tags":[
        "rental"
    ],
    "wof:name":"Laidlaw Transit Ltd",
    "wof:placetype":"venue"
},
  "geometry": {"coordinates":[-75.97566999999999,45.291176],"type":"Point"}
}