{
  "type": "Feature",
  "properties": {
    "addr:full":"15214 North Bluff Rd White Rock BC V4B 3E6",
    "addr:housenumber":"15214",
    "addr:postcode":"v4b 3e6",
    "addr:street":"North Bluff Rd",
    "iso:country":"CA",
    "sg:address":"15214 North Bluff Rd",
    "sg:city":"White Rock",
    "sg:classifiers":[
        {
            "category":"Restaurant",
            "type":"Food & Drink"
        }
    ],
    "sg:phone":"+1 604 531 5030",
    "sg:postcode":"V4B 3E6",
    "sg:province":"BC",
    "sg:tags":[
        "delicatessen"
    ],
    "wof:name":"Wolf's Deli",
    "wof:placetype":"venue"
},
  "geometry": {"coordinates":[-122.80072,49.031063],"type":"Point"}
}