{
  "type": "Feature",
  "properties": {
    "addr:full":"Barrie ON L4N 5R7",
    "addr:postcode":"l4n 5r7",
    "iso:country":"CA",
    "sg:city":"Barrie",
    "sg:classifiers":[
        {
            "category":"Shopping",
            "subcategory":"Clothing, Apparel, & Fashions",
            "type":"Retail Goods"
        }
    ],
    "sg:phone":"+1 705 734 0555",
    "sg:postcode":"L4N 5R7",
    "sg:province":"ON",
    "sg:tags":[
        "swimwear",
        "accessory"
    ],
    "wof:name":"Swimwear Beach Resort",
    "wof:placetype":"venue"
},
  "geometry": {"coordinates":[-79.7124862671,44.3808860779],"type":"Point"}
}