{
  "type": "Feature",
  "properties": {
    "addr:full":"1211 9 Ave SE #B Calgary AB T2G 0S9",
    "addr:housenumber":"1211",
    "addr:postcode":"t2g 0s9",
    "addr:street":"9 Ave Se # B",
    "iso:country":"CA",
    "sg:address":"1211 9 Ave SE #B",
    "sg:city":"Calgary",
    "sg:classifiers":[
        {
            "category":"Shopping",
            "subcategory":"Used Merchandise",
            "type":"Retail Goods"
        }
    ],
    "sg:phone":"+1 403 263 0011",
    "sg:postcode":"T2G 0S9",
    "sg:province":"AB",
    "sg:tags":[
        "furniture"
    ],
    "wof:name":"Bud's Place",
    "wof:placetype":"venue"
},
  "geometry": {"coordinates":[-114.03649900000001,51.041965],"type":"Point"}
}