{
  "type": "Feature",
  "properties": {
    "addr:full":"580 Park St Winkler MB R6W 1B4",
    "addr:housenumber":"580",
    "addr:postcode":"r6w 1b4",
    "addr:street":"Park St",
    "iso:country":"CA",
    "sg:address":"580 Park St",
    "sg:city":"Winkler",
    "sg:classifiers":[
        {
            "category":"Recreation",
            "type":"Entertainment"
        }
    ],
    "sg:phone":"+1 204 325 8212",
    "sg:postcode":"R6W 1B4",
    "sg:province":"MB",
    "sg:tags":[
        "pool",
        "swimming"
    ],
    "wof:name":"Winkler Aquatic Ctr",
    "wof:placetype":"venue"
},
  "geometry": {"coordinates":[-97.94476299999999,49.18681],"type":"Point"}
}