{
  "type": "Feature",
  "properties": {
    "addr:full":"Point May Lamaline NL A0E 2C0",
    "addr:postcode":"a0e 2c0",
    "addr:street":"Point",
    "iso:country":"CA",
    "sg:address":"Point May",
    "sg:city":"Lamaline",
    "sg:classifiers":[
        {
            "category":"Government",
            "subcategory":"Office",
            "type":"Public Place"
        }
    ],
    "sg:phone":"+1 709 857 2640",
    "sg:postcode":"A0E 2C0",
    "sg:province":"NL",
    "sg:tags":[
        "village"
    ],
    "wof:name":"Community Council Point May",
    "wof:placetype":"venue"
},
  "geometry": {"coordinates":[-55.787178,46.869202],"type":"Point"}
}