{
  "type": "Feature",
  "properties": {
    "addr:full":"4111 Wood Ave Port Alberni BC V9Y 5E8",
    "addr:housenumber":"4111",
    "addr:postcode":"v9y 5e8",
    "addr:street":"Wood Ave",
    "iso:country":"CA",
    "sg:address":"4111 Wood Ave",
    "sg:city":"Port Alberni",
    "sg:classifiers":[
        {
            "category":"Education",
            "subcategory":"School",
            "type":"Public Place"
        }
    ],
    "sg:phone":"+1 250 724 1132",
    "sg:postcode":"V9Y 5E8",
    "sg:province":"BC",
    "wof:name":"Wood Elementary",
    "wof:placetype":"venue"
},
  "geometry": {"coordinates":[-124.79142,49.250999],"type":"Point"}
}