{
  "type": "Feature",
  "properties": {
    "addr:full":"12 Parade St Yarmouth NS B5A 3A4",
    "addr:housenumber":"12",
    "addr:postcode":"b5a 3a4",
    "addr:street":"Parade St",
    "iso:country":"CA",
    "sg:address":"12 Parade St",
    "sg:city":"Yarmouth",
    "sg:classifiers":[
        {
            "category":"Health Services",
            "subcategory":"Doctor",
            "type":"Services"
        }
    ],
    "sg:phone":"+1 902 749 1655",
    "sg:postcode":"B5A 3A4",
    "sg:province":"NS",
    "sg:tags":[
        "physician",
        "surgeon"
    ],
    "wof:name":"Webster, David M MD",
    "wof:placetype":"venue"
},
  "geometry": {"coordinates":[-66.118850708,43.8378334045],"type":"Point"}
}