{
  "type": "Feature",
  "properties": {
    "iso:country":"CA",
    "sg:address":"119 1/2 King George Rd",
    "sg:city":"Brantford",
    "sg:classifiers":[
        {
            "category":"Personal",
            "subcategory":"Beauty Salon",
            "type":"Services"
        }
    ],
    "sg:phone":"+1 519 753 6316",
    "sg:postcode":"N3R 5K7",
    "sg:province":"ON",
    "wof:name":"Wally's Barber Shop",
    "wof:placetype":"venue"
},
  "geometry": {"coordinates":[-80.27666473390001,43.1696052551],"type":"Point"}
}