{
  "type": "Feature",
  "properties": {
    "iso:country":"CA",
    "sg:address":"60 Government Rd W",
    "sg:city":"Kirkland Lake",
    "sg:classifiers":[
        {
            "category":"Bars & Pubs",
            "type":"Food & Drink"
        }
    ],
    "sg:phone":"+1 705 567 4834",
    "sg:postcode":"P2N 2E4",
    "sg:province":"ON",
    "wof:name":"Franklin Tavern",
    "wof:placetype":"venue"
},
  "geometry": {"coordinates":[-80.0372467041,48.1496276855],"type":"Point"}
}