{
  "type": "Feature",
  "properties": {
    "addr:full":"630 Rue King E Sherbrooke QC J1G 1B8",
    "addr:housenumber":"630",
    "addr:postcode":"j1g 1b8",
    "addr:street":"Rue King E",
    "iso:country":"CA",
    "sg:address":"630 Rue King E",
    "sg:city":"Sherbrooke",
    "sg:classifiers":[
        {
            "category":"Insurance",
            "subcategory":"Insurance Agent",
            "type":"Services"
        }
    ],
    "sg:phone":"+1 819 566 0050",
    "sg:postcode":"J1G 1B8",
    "sg:province":"QC",
    "wof:name":"Assurances Generales-Caisses",
    "wof:placetype":"venue"
},
  "geometry": {"coordinates":[-71.87515999999999,45.407944],"type":"Point"}
}