{
  "type": "Feature",
  "properties": {
    "addr:full":"4898 Boul Gouin E Montreal-Nord QC H1G 1A2",
    "addr:housenumber":"4898",
    "addr:postcode":"h1g 1a2",
    "addr:street":"Boul Gouin E",
    "iso:country":"CA",
    "sg:address":"4898 Boul Gouin E",
    "sg:city":"Montreal-Nord",
    "sg:classifiers":[
        {
            "category":"Organizations",
            "subcategory":"Community Association",
            "type":"Services"
        }
    ],
    "sg:phone":"+1 514 321 2750",
    "sg:postcode":"H1G 1A2",
    "sg:province":"QC",
    "sg:tags":[
        "club"
    ],
    "wof:name":"Club Social Montreal Nord Inc",
    "wof:placetype":"venue"
},
  "geometry": {"coordinates":[-73.6384887695,45.6063575745],"type":"Point"}
}