{
  "type": "Feature",
  "properties": {
    "iso:country":"CA",
    "sg:address":"90 Creditstone Rd",
    "sg:city":"Concord",
    "sg:classifiers":[
        {
            "category":"Autos & Motor Vehicles",
            "subcategory":"Auto Supplies",
            "type":"Retail Goods"
        }
    ],
    "sg:phone":"+1 905 738 0825",
    "sg:postcode":"L4K 1P2",
    "sg:province":"ON",
    "sg:tags":[
        "spring",
        "absorber",
        "shock"
    ],
    "wof:name":"Thomasos Spring Svc Ltd",
    "wof:placetype":"venue"
},
  "geometry": {"coordinates":[-79.51676940919999,43.7906455994],"type":"Point"}
}