{
  "type": "Feature",
  "properties": {
    "addr:full":"6009 Ch Saint-Francois Saint-Laurent QC H4S 1B6",
    "addr:postcode":"6009;h4s 1b6",
    "addr:street":"Ch Saint-Francois",
    "iso:country":"CA",
    "sg:address":"6009 Ch Saint-Francois",
    "sg:city":"Saint-Laurent",
    "sg:classifiers":[
        {
            "category":"Wholesale",
            "subcategory":"Durable Goods & Equipment",
            "type":"Manufacturing & Wholesale Goods"
        }
    ],
    "sg:phone":"+1 514 333 3426",
    "sg:postcode":"H4S 1B6",
    "sg:province":"QC",
    "sg:tags":[
        "importer"
    ],
    "wof:name":"Aroc Electronics Intl Inc",
    "wof:placetype":"venue"
},
  "geometry": {"coordinates":[-73.7409744263,45.4857711792],"type":"Point"}
}