{
  "type": "Feature",
  "properties": {
    "addr:full":"656 Rue Gauthier Larouche QC G0W 1Z0",
    "addr:housenumber":"656",
    "addr:postcode":"g0w 1z0",
    "addr:street":"Rue Gauthier",
    "iso:country":"CA",
    "sg:address":"656 Rue Gauthier",
    "sg:city":"Larouche",
    "sg:classifiers":[
        {
            "category":"Organizations",
            "subcategory":"Religious Organization",
            "type":"Services"
        }
    ],
    "sg:phone":"+1 418 547 0857",
    "sg:postcode":"G0W 1Z0",
    "sg:province":"QC",
    "sg:tags":[
        "church"
    ],
    "wof:name":"Presbytere St-Gerard Magella",
    "wof:placetype":"venue"
},
  "geometry": {"coordinates":[-71.5239028931,48.4478530884],"type":"Point"}
}