{
  "type": "Feature",
  "properties": {
    "addr:full":"20 Poplar Heights Dr Etobicoke ON M9A 5A2",
    "addr:housenumber":"20",
    "addr:postcode":"m9a 5a2",
    "addr:street":"Poplar Heights Dr",
    "iso:country":"CA",
    "sg:address":"20 Poplar Heights Dr",
    "sg:city":"Etobicoke",
    "sg:classifiers":[
        {
            "category":"Professional",
            "subcategory":"Management & Consulting",
            "type":"Services"
        }
    ],
    "sg:phone":"+1 416 249 8696",
    "sg:postcode":"M9A 5A2",
    "sg:province":"ON",
    "sg:tags":[
        "control",
        "consultant",
        "quality"
    ],
    "wof:name":"Performance Plus Consultants",
    "wof:placetype":"venue"
},
  "geometry": {"coordinates":[-79.534843,43.676487],"type":"Point"}
}