{
  "type": "Feature",
  "properties": {
    "iso:country":"CA",
    "sg:city":"Montreal",
    "sg:classifiers":[
        {
            "category":"Wholesale",
            "subcategory":"Stationery",
            "type":"Manufacturing & Wholesale Goods"
        }
    ],
    "sg:phone":"+1 514 529 8696",
    "sg:postcode":"H2H 1E9",
    "sg:province":"QC",
    "sg:tags":[
        "mapping"
    ],
    "wof:name":"Geomatique Sigisco Inc",
    "wof:placetype":"venue"
},
  "geometry": {"coordinates":[-73.57646942140001,45.5386352539],"type":"Point"}
}