{
  "type": "Feature",
  "properties": {
    "addr:full":"400 Spence St Winnipeg MB R3B 2R6",
    "addr:housenumber":"400",
    "addr:postcode":"r3b 2r6",
    "addr:street":"Spence St",
    "iso:country":"CA",
    "sg:address":"400 Spence St",
    "sg:city":"Winnipeg",
    "sg:classifiers":[
        {
            "category":"Health Services",
            "subcategory":"Doctor",
            "type":"Services"
        }
    ],
    "sg:phone":"+1 204 786 9418",
    "sg:postcode":"R3B 2R6",
    "sg:province":"MB",
    "sg:tags":[
        "medicine",
        "injury",
        "sport"
    ],
    "wof:name":"University-Winnipeg Athletic",
    "wof:placetype":"venue"
},
  "geometry": {"coordinates":[-97.154083,49.892143],"type":"Point"}
}