{
  "type": "Feature",
  "properties": {
    "iso:country":"CA",
    "sg:address":"272 Innisfil St",
    "sg:city":"Barrie",
    "sg:classifiers":[
        {
            "category":"Building & Trades",
            "subcategory":"Construction",
            "type":"Services"
        }
    ],
    "sg:phone":"+1 705 725 0605",
    "sg:postcode":"L4N 3G1",
    "sg:province":"ON",
    "sg:tags":[
        "tile",
        "dealer"
    ],
    "wof:name":"Gianni's Tile Gallery Ltd",
    "wof:placetype":"venue"
},
  "geometry": {"coordinates":[-79.693878,44.372337],"type":"Point"}
}