{
  "type": "Feature",
  "properties": {
    "addr:full":"Bayfield ON N0M 1G0",
    "addr:postcode":"n0m 1g0",
    "iso:country":"CA",
    "sg:city":"Bayfield",
    "sg:classifiers":[
        {
            "category":"Real Estate",
            "subcategory":"Real Estate Agent",
            "type":"Services"
        }
    ],
    "sg:phone":"+1 519 565 5951",
    "sg:postcode":"N0M 1G0",
    "sg:province":"ON",
    "wof:name":"Peak Four Seasons Realty Ltd",
    "wof:placetype":"venue"
},
  "geometry": {"coordinates":[-81.6968841553,43.5616493225],"type":"Point"}
}