{
  "type": "Feature",
  "properties": {
    "addr:full":"1410 Rue Principale Labrecque QC G0W 2S0",
    "addr:housenumber":"1410",
    "addr:postcode":"g0w 2s0",
    "addr:street":"Rue Principale",
    "iso:country":"CA",
    "sg:address":"1410 Rue Principale",
    "sg:city":"Labrecque",
    "sg:classifiers":[
        {
            "category":"Health Services",
            "subcategory":"Nursing And Care Facility",
            "type":"Services"
        }
    ],
    "sg:phone":"+1 418 481 1654",
    "sg:postcode":"G0W 2S0",
    "sg:province":"QC",
    "sg:tags":[
        "home",
        "retirement",
        "community"
    ],
    "wof:name":"Residence DE Labrecque",
    "wof:placetype":"venue"
},
  "geometry": {"coordinates":[-71.523735,48.673489],"type":"Point"}
}