{
  "type": "Feature",
  "properties": {
    "iso:country":"CA",
    "sg:address":"48 Keewatin St N",
    "sg:city":"Oshawa",
    "sg:classifiers":[
        {
            "category":"Professional",
            "subcategory":"Advertising",
            "type":"Services"
        }
    ],
    "sg:phone":"+1 905 723 3760",
    "sg:postcode":"L1G 6M8",
    "sg:province":"ON",
    "sg:tags":[
        "distribution",
        "oil"
    ],
    "wof:name":"Petrocor Distributors Inc",
    "wof:placetype":"venue"
},
  "geometry": {"coordinates":[-78.826996,43.906654],"type":"Point"}
}