{
  "type": "Feature",
  "properties": {
    "addr:full":"Delta BC V4C 6R8",
    "addr:postcode":"v4c 6r8",
    "iso:country":"CA",
    "sg:city":"Delta",
    "sg:classifiers":[
        {
            "category":"Health Services",
            "subcategory":"Doctor",
            "type":"Services"
        }
    ],
    "sg:phone":"+1 604 588 7451",
    "sg:postcode":"V4C 6R8",
    "sg:province":"BC",
    "sg:tags":[
        "dentist"
    ],
    "wof:name":"Andersson, Paul J DDS",
    "wof:placetype":"venue"
},
  "geometry": {"coordinates":[-122.890449524,49.1732406616],"type":"Point"}
}