{
  "type": "Feature",
  "properties": {
    "addr:full":"Grandes-Bergeronnes QC G0T 1G0",
    "addr:postcode":"g0t 1g0",
    "iso:country":"CA",
    "sg:city":"Grandes-Bergeronnes",
    "sg:classifiers":[
        {
            "category":"Government",
            "subcategory":"Office",
            "type":"Public Place"
        }
    ],
    "sg:phone":"+1 418 232 6273",
    "sg:postcode":"G0T 1G0",
    "sg:province":"QC",
    "wof:name":"Quebec Agriculture Pecheries",
    "wof:placetype":"venue"
},
  "geometry": {"coordinates":[-69.5410461426,48.2469482422],"type":"Point"}
}