{
  "type": "Feature",
  "properties": {
    "addr:full":"107 Second Ave S Cranberry Portage MB R0B 0H0",
    "addr:housenumber":"107",
    "addr:postcode":"r0b 0h0",
    "addr:street":"Second Ave S Cranberry",
    "iso:country":"CA",
    "sg:address":"107 Second Ave S",
    "sg:city":"Cranberry Portage",
    "sg:classifiers":[
        {
            "category":"Social Services",
            "subcategory":"Child Care",
            "type":"Services"
        }
    ],
    "sg:phone":"+1 204 472 3430",
    "sg:postcode":"R0B 0H0",
    "sg:province":"MB",
    "wof:name":"Cranberry Portage Child Devmnt",
    "wof:placetype":"venue"
},
  "geometry": {"coordinates":[-101.371201,54.581146],"type":"Point"}
}