{
  "type": "Feature",
  "properties": {
    "addr:full":"Quebec QC G1P 4R7",
    "addr:postcode":"g1p 4r7",
    "iso:country":"CA",
    "sg:city":"Quebec",
    "sg:classifiers":[
        {
            "category":"Professional",
            "subcategory":"Management & Consulting",
            "type":"Services"
        }
    ],
    "sg:phone":"+1 418 688 0334",
    "sg:postcode":"G1P 4R7",
    "sg:province":"QC",
    "sg:tags":[
        "instrumentation",
        "indicating"
    ],
    "wof:name":"Optel Technologies Inc",
    "wof:placetype":"venue"
},
  "geometry": {"coordinates":[-71.3227157593,46.8018951416],"type":"Point"}
}