{
  "type": "Feature",
  "properties": {
    "addr:full":"663 Industrial Ave Ottawa ON K1G 0Z1",
    "addr:housenumber":"663",
    "addr:postcode":"k1g 0z1",
    "addr:street":"Industrial Ave",
    "iso:country":"CA",
    "sg:address":"663 Industrial Ave",
    "sg:city":"Ottawa",
    "sg:phone":"+1 613 733 0555",
    "sg:postcode":"K1G 0Z1",
    "sg:province":"ON",
    "sg:tags":[
        "equipment",
        "supply"
    ],
    "wof:name":"Jordash CO Ltd",
    "wof:placetype":"venue"
},
  "geometry": {"coordinates":[-75.639061,45.410469],"type":"Point"}
}