{
  "type": "Feature",
  "properties": {
    "addr:full":"6618 20A St SE Calgary AB T2C 0R3",
    "addr:housenumber":"6618",
    "addr:postcode":"t2c 0r3",
    "addr:street":"20A St Se",
    "iso:country":"CA",
    "sg:address":"6618 20A St SE",
    "sg:city":"Calgary",
    "sg:classifiers":[
        {
            "category":"Shopping",
            "subcategory":"Pharmacy",
            "type":"Retail Goods"
        }
    ],
    "sg:phone":"+1 403 279 3731",
    "sg:postcode":"T2C 0R3",
    "sg:province":"AB",
    "wof:name":"Lynnwood Drugs",
    "wof:placetype":"venue"
},
  "geometry": {"coordinates":[-114.009933,50.993896],"type":"Point"}
}