{
  "type": "Feature",
  "properties": {
    "addr:full":"415 2nd Ave E Rapid City MB R0K 1W0",
    "addr:housenumber":"415",
    "addr:postcode":"r0k 1w0",
    "addr:street":"2Nd Ave E",
    "iso:country":"CA",
    "sg:address":"415 2nd Ave E",
    "sg:city":"Rapid City",
    "sg:classifiers":[
        {
            "category":"Wholesale",
            "subcategory":"Machinery & Supplies",
            "type":"Manufacturing & Wholesale Goods"
        }
    ],
    "sg:phone":"+1 204 826 2072",
    "sg:postcode":"R0K 1W0",
    "sg:province":"MB",
    "sg:tags":[
        "farm",
        "equipment"
    ],
    "wof:name":"Belcher's Service",
    "wof:placetype":"venue"
},
  "geometry": {"coordinates":[-100.037285,50.119984],"type":"Point"}
}