{
  "type": "Feature",
  "properties": {
    "addr:full":"9426 111 Ave NW Edmonton AB T5G 0A4",
    "addr:housenumber":"9426",
    "addr:postcode":"t5g 0a4",
    "addr:street":"111 Ave Nw",
    "iso:country":"CA",
    "sg:address":"9426 111 Ave NW",
    "sg:city":"Edmonton",
    "sg:classifiers":[
        {
            "category":"Banks & Credit Unions",
            "subcategory":"Bank",
            "type":"Services"
        }
    ],
    "sg:phone":"+1 780 471 3215",
    "sg:postcode":"T5G 0A4",
    "sg:province":"AB",
    "sg:tags":[
        "exchange",
        "cashing",
        "dealer",
        "broker",
        "foreign",
        "check"
    ],
    "wof:name":"Money Mart",
    "wof:placetype":"venue"
},
  "geometry": {"coordinates":[-113.486228943,53.5603637695],"type":"Point"}
}