{
  "type": "Feature",
  "properties": {
    "addr:full":"317 Foxtrap Access Rd Conception Bay South NL A1X 7E9",
    "addr:housenumber":"317",
    "addr:postcode":"a1x 7e9",
    "addr:street":"Foxtrap Access Rd",
    "iso:country":"CA",
    "sg:address":"317 Foxtrap Access Rd",
    "sg:city":"Conception Bay South",
    "sg:classifiers":[
        {
            "category":"Freight",
            "type":"Transportation"
        }
    ],
    "sg:phone":"+1 709 834 5592",
    "sg:postcode":"A1X 7E9",
    "sg:province":"NL",
    "sg:tags":[
        "trucking"
    ],
    "wof:name":"Walt Rideout Trucking",
    "wof:placetype":"venue"
},
  "geometry": {"coordinates":[-52.968876,47.512619],"type":"Point"}
}