{
  "type": "Feature",
  "properties": {
    "iso:country":"CA",
    "sg:address":"PO Box 542 STN Main",
    "sg:city":"Barrie",
    "sg:classifiers":[
        {
            "category":"Organizations",
            "subcategory":"Religious Organization",
            "type":"Services"
        }
    ],
    "sg:phone":"+1 705 726 9875",
    "sg:postcode":"L4M 4T7",
    "sg:province":"ON",
    "sg:tags":[
        "church"
    ],
    "wof:name":"Holy Cross St Nektarios Ch",
    "wof:placetype":"venue"
},
  "geometry": {"coordinates":[-79.686325,44.389301],"type":"Point"}
}