{
  "type": "Feature",
  "properties": {
    "addr:full":"130 Rue Bayard Chicoutimi QC G7G 3V7",
    "addr:housenumber":"130",
    "addr:postcode":"g7g 3v7",
    "addr:street":"Rue Bayard",
    "iso:country":"CA",
    "sg:address":"130 Rue Bayard",
    "sg:city":"Chicoutimi",
    "sg:classifiers":[
        {
            "category":"Building & Trades",
            "subcategory":"Construction",
            "type":"Services"
        }
    ],
    "sg:phone":"+1 418 693 1110",
    "sg:postcode":"G7G 3V7",
    "sg:province":"QC",
    "sg:tags":[
        "roofing",
        "contractor"
    ],
    "wof:name":"Aluminium Jr Enr",
    "wof:placetype":"venue"
},
  "geometry": {"coordinates":[-71.09494018549999,48.4511489868],"type":"Point"}
}