{
  "type": "Feature",
  "properties": {
    "addr:full":"3131 Boul DE LA Cote-Vertu # 22M22 Saint-Laurent QC H4R 1Y8",
    "addr:housenumber":"3131",
    "addr:postcode":"h4r 1y8",
    "addr:street":"Boul De La Cote-Vertu # 22M22",
    "iso:country":"CA",
    "sg:address":"3131 Boul DE LA Cote-Vertu # 22M22",
    "sg:city":"Saint-Laurent",
    "sg:classifiers":[
        {
            "category":"Shopping",
            "subcategory":"Clothing, Apparel, & Fashions",
            "type":"Retail Goods"
        }
    ],
    "sg:phone":"+1 514 336 5410",
    "sg:postcode":"H4R 1Y8",
    "sg:province":"QC",
    "wof:name":"LA Senza",
    "wof:placetype":"venue"
},
  "geometry": {"coordinates":[-73.70355987550001,45.4979896545],"type":"Point"}
}