{
  "type": "Feature",
  "properties": {
    "addr:full":"2108 18 St SW Calgary AB T2T 4T4",
    "addr:housenumber":"2108",
    "addr:postcode":"t2t 4t4",
    "addr:street":"18 St Sw",
    "iso:country":"CA",
    "sg:address":"2108 18 St SW",
    "sg:city":"Calgary",
    "sg:classifiers":[
        {
            "category":"Shopping",
            "type":"Retail Goods"
        }
    ],
    "sg:phone":"+1 403 244 5466",
    "sg:postcode":"T2T 4T4",
    "sg:province":"AB",
    "sg:tags":[
        "cosmetic",
        "perfume"
    ],
    "wof:name":"Mary Kay Cosmetics",
    "wof:placetype":"venue"
},
  "geometry": {"coordinates":[-114.103928,51.035614],"type":"Point"}
}