{
  "type": "Feature",
  "properties": {
    "addr:full":"Calgary AB T2C 2C9",
    "addr:postcode":"t2c 2c9",
    "iso:country":"CA",
    "sg:city":"Calgary",
    "sg:classifiers":[
        {
            "category":"Freight",
            "type":"Transportation"
        }
    ],
    "sg:phone":"+1 403 236 4748",
    "sg:postcode":"T2C 2C9",
    "sg:province":"AB",
    "sg:tags":[
        "trucking"
    ],
    "wof:name":"Dick Klepper Trucking",
    "wof:placetype":"venue"
},
  "geometry": {"coordinates":[-113.970276,50.995819],"type":"Point"}
}