{
  "type": "Feature",
  "properties": {
    "addr:full":"327 Harbour Rd Victoria BC V9A 3S2",
    "addr:housenumber":"327",
    "addr:postcode":"v9a 3s2",
    "addr:street":"Harbour Rd",
    "iso:country":"CA",
    "sg:address":"327 Harbour Rd",
    "sg:city":"Victoria",
    "sg:classifiers":[
        {
            "category":"Building & Trades",
            "subcategory":"Construction",
            "type":"Services"
        }
    ],
    "sg:phone":"+1 250 382 5885",
    "sg:postcode":"V9A 3S2",
    "sg:province":"BC",
    "sg:tags":[
        "downspouts",
        "gutter"
    ],
    "wof:name":"Pro-Tech Exterior Products",
    "wof:placetype":"venue"
},
  "geometry": {"coordinates":[-123.376281738,48.4306793213],"type":"Point"}
}