{
  "type": "Feature",
  "properties": {
    "addr:full":"327 Kaska Rd Sherwood Park AB T8A 4E9",
    "addr:housenumber":"327",
    "addr:postcode":"t8a 4e9",
    "addr:street":"Kaska Rd",
    "iso:country":"CA",
    "sg:address":"327 Kaska Rd",
    "sg:city":"Sherwood Park",
    "sg:classifiers":[
        {
            "category":"Restaurant",
            "type":"Food & Drink"
        }
    ],
    "sg:phone":"+1 780 467 7493",
    "sg:postcode":"T8A 4E9",
    "sg:province":"AB",
    "sg:tags":[
        "caterer"
    ],
    "wof:name":"Mushrooms & More Quality Food",
    "wof:placetype":"venue"
},
  "geometry": {"coordinates":[-113.32979583700001,53.5388221741],"type":"Point"}
}