{
  "type": "Feature",
  "properties": {
    "addr:full":"3615 18 Ave NW Edmonton AB T6L 3C1",
    "addr:housenumber":"3615",
    "addr:postcode":"t6l 3c1",
    "addr:street":"18 Ave Nw",
    "iso:country":"CA",
    "sg:address":"3615 18 Ave NW",
    "sg:city":"Edmonton",
    "sg:classifiers":[
        {
            "category":"Organizations",
            "subcategory":"Professional Association",
            "type":"Services"
        }
    ],
    "sg:phone":"+1 780 462 6229",
    "sg:postcode":"T6L 3C1",
    "sg:province":"AB",
    "wof:name":"Southside Safe House",
    "wof:placetype":"venue"
},
  "geometry": {"coordinates":[-113.396690369,53.4475975037],"type":"Point"}
}