{
  "type": "Feature",
  "properties": {
    "addr:full":"Vancouver BC V6J 5B3",
    "addr:postcode":"v6j 5b3",
    "iso:country":"CA",
    "sg:city":"Vancouver",
    "sg:classifiers":[
        {
            "category":"Communications",
            "subcategory":"Film & Video Production",
            "type":"Services"
        }
    ],
    "sg:phone":"+1 604 731 9194",
    "sg:postcode":"V6J 5B3",
    "sg:province":"BC",
    "sg:tags":[
        "motion",
        "picture",
        "studio",
        "producer"
    ],
    "wof:name":"Mvp Entertainment",
    "wof:placetype":"venue"
},
  "geometry": {"coordinates":[-123.140404,49.273174],"type":"Point"}
}