{
  "type": "Feature",
  "properties": {
    "iso:country":"CA",
    "sg:city":"Nipawin",
    "sg:classifiers":[
        {
            "category":"Health Services",
            "subcategory":"Clinic",
            "type":"Services"
        }
    ],
    "sg:phone":"+1 306 862 2230",
    "sg:postcode":"S0E 1E0",
    "sg:province":"SK",
    "sg:tags":[
        "home"
    ],
    "wof:name":"Handi-Works Home",
    "wof:placetype":"venue"
},
  "geometry": {"coordinates":[-104.026283264,53.3567428589],"type":"Point"}
}