{
  "type": "Feature",
  "properties": {
    "addr:full":"Arden ON K0H 1B0",
    "addr:postcode":"k0h 1b0",
    "iso:country":"CA",
    "sg:city":"Arden",
    "sg:classifiers":[
        {
            "category":"Autos & Motor Vehicles",
            "subcategory":"Fuel & Gas Station",
            "type":"Retail Goods"
        }
    ],
    "sg:phone":"+1 613 335 5433",
    "sg:postcode":"K0H 1B0",
    "sg:province":"ON",
    "sg:tags":[
        "oil"
    ],
    "wof:name":"Scott's Gas & Variety",
    "wof:placetype":"venue"
},
  "geometry": {"coordinates":[-76.924057,44.720909],"type":"Point"}
}