{
  "type": "Feature",
  "properties": {
    "addr:full":"Frelighsburg QC J0J 1C0",
    "addr:postcode":"j0j 1c0",
    "iso:country":"CA",
    "sg:city":"Frelighsburg",
    "sg:classifiers":[
        {
            "category":"Government",
            "subcategory":"Office",
            "type":"Public Place"
        }
    ],
    "sg:phone":"+1 450 298 5133",
    "sg:postcode":"J0J 1C0",
    "sg:province":"QC",
    "sg:tags":[
        "village"
    ],
    "wof:name":"Frelighsburg Hotel DE Ville",
    "wof:placetype":"venue"
},
  "geometry": {"coordinates":[-72.838257,45.055519],"type":"Point"}
}