{
  "type": "Feature",
  "properties": {
    "addr:full":"4355 Mathissi Pl Burnaby BC V5G 4S8",
    "addr:housenumber":"4355",
    "addr:postcode":"v5g 4s8",
    "addr:street":"Mathissi Pl",
    "iso:country":"CA",
    "sg:address":"4355 Mathissi Pl",
    "sg:city":"Burnaby",
    "sg:classifiers":[
        {
            "category":"Education",
            "subcategory":"College",
            "type":"Public Place"
        }
    ],
    "sg:phone":"+1 604 431 3000",
    "sg:postcode":"V5G 4S8",
    "sg:province":"BC",
    "sg:tags":[
        "academic",
        "school"
    ],
    "wof:name":"Open Learning Agency",
    "wof:placetype":"venue"
},
  "geometry": {"coordinates":[-123.005622864,49.2460632324],"type":"Point"}
}