{
  "type": "Feature",
  "properties": {
    "addr:full":"2651 Douglas St Victoria BC V8T 4M2",
    "addr:housenumber":"2651",
    "addr:postcode":"v8t 4m2",
    "addr:street":"Douglas St",
    "iso:country":"CA",
    "sg:address":"2651 Douglas St",
    "sg:city":"Victoria",
    "sg:classifiers":[
        {
            "category":"Shopping",
            "type":"Retail Goods"
        }
    ],
    "sg:phone":"+1 250 381 4022",
    "sg:postcode":"V8T 4M2",
    "sg:province":"BC",
    "sg:tags":[
        "picture",
        "frame"
    ],
    "wof:name":"Options Picture Framing",
    "wof:placetype":"venue"
},
  "geometry": {"coordinates":[-123.366142,48.437389],"type":"Point"}
}