{
  "type": "Feature",
  "properties": {
    "addr:full":"2600 Rue William-Tremblay Montreal QC H1Y 3J2",
    "addr:housenumber":"2600",
    "addr:postcode":"h1y 3j2",
    "addr:street":"Rue William-Tremblay",
    "iso:country":"CA",
    "sg:address":"2600 Rue William-Tremblay",
    "sg:city":"Montreal",
    "sg:classifiers":[
        {
            "category":"Building & Trades",
            "subcategory":"Construction",
            "type":"Services"
        }
    ],
    "sg:phone":"+1 514 278 3050",
    "sg:postcode":"H1Y 3J2",
    "sg:province":"QC",
    "sg:tags":[
        "designer"
    ],
    "wof:name":"Alto Design Inc",
    "wof:placetype":"venue"
},
  "geometry": {"coordinates":[-73.56450700000001,45.542633],"type":"Point"}
}