{
  "type": "Feature",
  "properties": {
    "addr:full":"759 1st St Brandon MB R7A 2X5",
    "addr:housenumber":"759",
    "addr:postcode":"r7a 2x5",
    "addr:street":"1St St",
    "iso:country":"CA",
    "sg:address":"759 1st St",
    "sg:city":"Brandon",
    "sg:classifiers":[
        {
            "category":"Retail",
            "subcategory":"Auto Rental",
            "type":"Services"
        }
    ],
    "sg:phone":"+1 204 725 1300",
    "sg:postcode":"R7A 2X5",
    "sg:province":"MB",
    "sg:tags":[
        "renting",
        "automobile"
    ],
    "wof:name":"Enterprise Rent A Car",
    "wof:placetype":"venue"
},
  "geometry": {"coordinates":[-99.938835144,49.8383712769],"type":"Point"}
}