{
  "type": "Feature",
  "properties": {
    "addr:full":"211 Clare Ave Winnipeg MB R3L 1R8",
    "addr:housenumber":"211",
    "addr:postcode":"r3l 1r8",
    "addr:street":"Clare Ave",
    "iso:country":"CA",
    "sg:address":"211 Clare Ave",
    "sg:city":"Winnipeg",
    "sg:classifiers":[
        {
            "category":"Professional",
            "subcategory":"Business Services",
            "type":"Services"
        }
    ],
    "sg:phone":"+1 204 284 2015",
    "sg:postcode":"R3L 1R8",
    "sg:province":"MB",
    "sg:tags":[
        "pool",
        "swimming"
    ],
    "wof:name":"Mark's Home & Pool Svc",
    "wof:placetype":"venue"
},
  "geometry": {"coordinates":[-97.12305499999999,49.861725],"type":"Point"}
}