{
  "type": "Feature",
  "properties": {
    "addr:full":"1759 King St E Hamilton ON L8K 1V6",
    "addr:housenumber":"1759",
    "addr:postcode":"l8k 1v6",
    "addr:street":"King St E",
    "iso:country":"CA",
    "sg:address":"1759 King St E",
    "sg:city":"Hamilton",
    "sg:classifiers":[
        {
            "category":"Organizations",
            "subcategory":"Membership Organization",
            "type":"Services"
        }
    ],
    "sg:phone":"+1 905 544 4444",
    "sg:postcode":"L8K 1V6",
    "sg:province":"ON",
    "wof:name":"Parents Without Partners Inc",
    "wof:placetype":"venue"
},
  "geometry": {"coordinates":[-79.812065,43.232704],"type":"Point"}
}