{
  "type": "Feature",
  "properties": {
    "addr:full":"Lundar MB R0C 1Y0",
    "addr:postcode":"r0c 1y0",
    "iso:country":"CA",
    "sg:city":"Lundar",
    "sg:classifiers":[
        {
            "category":"Restaurant",
            "type":"Food & Drink"
        }
    ],
    "sg:phone":"+1 204 762 5100",
    "sg:postcode":"R0C 1Y0",
    "sg:province":"MB",
    "wof:name":"Chicken Chef",
    "wof:placetype":"venue"
},
  "geometry": {"coordinates":[-98.03052520750001,50.6976089478],"type":"Point"}
}