{
  "type": "Feature",
  "properties": {
    "addr:full":"1610 Johnston St Vancouver BC V6H 3S2",
    "addr:housenumber":"1610",
    "addr:postcode":"v6h 3s2",
    "addr:street":"Johnston St",
    "iso:country":"CA",
    "sg:address":"1610 Johnston St",
    "sg:city":"Vancouver",
    "sg:classifiers":[
        {
            "category":"Shopping",
            "type":"Retail Goods"
        }
    ],
    "sg:phone":"+1 604 688 3047",
    "sg:postcode":"V6H 3S2",
    "sg:province":"BC",
    "sg:tags":[
        "art",
        "gallery",
        "dealer"
    ],
    "wof:name":"Fibre Arts Studio",
    "wof:placetype":"venue"
},
  "geometry": {"coordinates":[-123.13520813,49.2719078064],"type":"Point"}
}