{
  "type": "Feature",
  "properties": {
    "iso:country":"CA",
    "sg:city":"Ravenna",
    "sg:classifiers":[
        {
            "category":"Freight",
            "type":"Transportation"
        }
    ],
    "sg:phone":"+1 705 444 0211",
    "sg:postcode":"N0H 2E0",
    "sg:province":"ON",
    "sg:tags":[
        "trucking"
    ],
    "wof:name":"Fairfield Distributing CO",
    "wof:placetype":"venue"
},
  "geometry": {"coordinates":[-80.41924285890001,44.4775733948],"type":"Point"}
}