{
  "type": "Feature",
  "properties": {
    "addr:full":"1926 Broadway W Vancouver BC V6J 1Z2",
    "addr:housenumber":"1926",
    "addr:postcode":"v6j 1z2",
    "addr:street":"Broadway W",
    "iso:country":"CA",
    "sg:address":"1926 Broadway W",
    "sg:city":"Vancouver",
    "sg:classifiers":[
        {
            "category":"Restaurant",
            "type":"Food & Drink"
        }
    ],
    "sg:phone":"+1 604 733 5862",
    "sg:postcode":"V6J 1Z2",
    "sg:province":"BC",
    "wof:name":"Mesaluna",
    "wof:placetype":"venue"
},
  "geometry": {"coordinates":[-123.148796,49.263641],"type":"Point"}
}