{
  "type": "Feature",
  "properties": {
    "iso:country":"CA",
    "sg:address":"6091 Goldsmith Dr",
    "sg:city":"Richmond",
    "sg:classifiers":[
        {
            "category":"Building & Trades",
            "subcategory":"Landscaping Services",
            "type":"Services"
        }
    ],
    "sg:phone":"+1 604 277 9096",
    "sg:postcode":"V7E 4G4",
    "sg:province":"BC",
    "sg:tags":[
        "landscape",
        "contractor"
    ],
    "wof:name":"Matsumura Landscaping",
    "wof:placetype":"venue"
},
  "geometry": {"coordinates":[-123.15782928500001,49.138874054],"type":"Point"}
}