{
  "type": "Feature",
  "properties": {
    "addr:full":"429 Talbot St St Thomas ON N5P 1C1",
    "addr:housenumber":"429",
    "addr:postcode":"n5p 1c1",
    "addr:street":"Talbot St",
    "iso:country":"CA",
    "sg:address":"429 Talbot St",
    "sg:city":"St Thomas",
    "sg:classifiers":[
        {
            "category":"Shopping",
            "subcategory":"Shoes",
            "type":"Retail Goods"
        }
    ],
    "sg:phone":"+1 519 631 0755",
    "sg:postcode":"N5P 1C1",
    "sg:province":"ON",
    "wof:name":"Mugford Shoes",
    "wof:placetype":"venue"
},
  "geometry": {"coordinates":[-81.19615899999999,42.779175],"type":"Point"}
}