{
  "type": "Feature",
  "properties": {
    "iso:country":"CA",
    "sg:address":"3108 33 Ave",
    "sg:city":"Vernon",
    "sg:classifiers":[
        {
            "category":"Banks & Credit Unions",
            "subcategory":"Bank",
            "type":"Services"
        }
    ],
    "sg:phone":"+1 250 545 9251",
    "sg:postcode":"V1T 2N7",
    "sg:province":"BC",
    "wof:name":"Vernon & District Credit Union",
    "wof:placetype":"venue"
},
  "geometry": {"coordinates":[-119.27252960200001,50.265914917],"type":"Point"}
}