{
  "type": "Feature",
  "properties": {
    "addr:full":"Winnipeg MB R2G 3G6",
    "addr:postcode":"r2g 3g6",
    "iso:country":"CA",
    "sg:city":"Winnipeg",
    "sg:classifiers":[
        {
            "category":"Real Estate",
            "subcategory":"Real Estate Operator",
            "type":"Services"
        }
    ],
    "sg:phone":"+1 204 940 3484",
    "sg:postcode":"R2G 3G6",
    "sg:province":"MB",
    "sg:tags":[
        "apartment"
    ],
    "wof:name":"Oakland Gardens",
    "wof:placetype":"venue"
},
  "geometry": {"coordinates":[-97.09243011469999,49.9371948242],"type":"Point"}
}