{
  "type": "Feature",
  "properties": {
    "addr:full":"315 Brock St S Whitby ON L1N 4K3",
    "addr:housenumber":"315",
    "addr:postcode":"l1n 4k3",
    "addr:street":"Brock St S",
    "iso:country":"CA",
    "sg:address":"315 Brock St S",
    "sg:city":"Whitby",
    "sg:classifiers":[
        {
            "category":"Restaurant",
            "type":"Food & Drink"
        }
    ],
    "sg:phone":"+1 905 668 7151",
    "sg:postcode":"L1N 4K3",
    "sg:province":"ON",
    "wof:name":"P J's Restaurant",
    "wof:placetype":"venue"
},
  "geometry": {"coordinates":[-78.9410858154,43.8775672913],"type":"Point"}
}