{
  "type": "Feature",
  "properties": {
    "iso:country":"CA",
    "sg:address":"2595 Inkster Blvd",
    "sg:city":"Winnipeg",
    "sg:classifiers":[
        {
            "category":"Freight",
            "type":"Transportation"
        }
    ],
    "sg:phone":"+1 204 633 1200",
    "sg:postcode":"R3C 2E6",
    "sg:province":"MB",
    "sg:tags":[
        "broker",
        "customs"
    ],
    "wof:name":"Expert Customs Brokers",
    "wof:placetype":"venue"
},
  "geometry": {"coordinates":[-97.228477478,49.946018219],"type":"Point"}
}