{
  "type": "Feature",
  "properties": {
    "addr:full":"Langley BC V3A 7R3",
    "addr:postcode":"v3a 7r3",
    "iso:country":"CA",
    "sg:city":"Langley",
    "sg:classifiers":[
        {
            "category":"Utilities",
            "subcategory":"Refuse",
            "type":"Services"
        }
    ],
    "sg:phone":"+1 604 534 0071",
    "sg:postcode":"V3A 7R3",
    "sg:province":"BC",
    "sg:tags":[
        "equipment",
        "recycling",
        "waste",
        "system"
    ],
    "wof:name":"Waste Less Environmental Svc",
    "wof:placetype":"venue"
},
  "geometry": {"coordinates":[-122.652206421,49.1056747437],"type":"Point"}
}