{
  "type": "Feature",
  "properties": {
    "addr:full":"Williamsburg ON K0C 2H0",
    "addr:postcode":"k0c 2h0",
    "iso:country":"CA",
    "sg:city":"Williamsburg",
    "sg:classifiers":[
        {
            "category":"Building & Trades",
            "subcategory":"Construction",
            "type":"Services"
        }
    ],
    "sg:phone":"+1 613 535 2079",
    "sg:postcode":"K0C 2H0",
    "sg:province":"ON",
    "sg:tags":[
        "masonry",
        "contractor"
    ],
    "wof:name":"B & H Masonry",
    "wof:placetype":"venue"
},
  "geometry": {"coordinates":[-75.244591,44.974403],"type":"Point"}
}