{
  "type": "Feature",
  "properties": {
    "addr:full":"201 Rue Du Manoir Montmagny QC G5V 1G1",
    "addr:housenumber":"201",
    "addr:postcode":"g5v 1g1",
    "addr:street":"Rue Du Manoir",
    "iso:country":"CA",
    "sg:address":"201 Rue Du Manoir",
    "sg:city":"Montmagny",
    "sg:classifiers":[
        {
            "category":"Building & Trades",
            "subcategory":"Construction",
            "type":"Services"
        }
    ],
    "sg:phone":"+1 418 628 6010",
    "sg:postcode":"G5V 1G1",
    "sg:province":"QC",
    "sg:tags":[
        "resurfacing",
        "laying",
        "refinishing",
        "floor"
    ],
    "wof:name":"Roch Tessier Inc",
    "wof:placetype":"venue"
},
  "geometry": {"coordinates":[-70.5540237427,46.9840278625],"type":"Point"}
}