{
  "type": "Feature",
  "properties": {
    "addr:full":"291 Boul Montcalm Granby QC J2G 5C4",
    "addr:housenumber":"291",
    "addr:postcode":"j2g 5c4",
    "addr:street":"Boul Montcalm",
    "iso:country":"CA",
    "sg:address":"291 Boul Montcalm",
    "sg:city":"Granby",
    "sg:classifiers":[
        {
            "category":"Personal",
            "subcategory":"Beauty Salon",
            "type":"Services"
        }
    ],
    "sg:phone":"+1 450 372 4334",
    "sg:postcode":"J2G 5C4",
    "sg:province":"QC",
    "sg:tags":[
        "electrolysis"
    ],
    "wof:name":"Gynecee",
    "wof:placetype":"venue"
},
  "geometry": {"coordinates":[-72.722977,45.409237],"type":"Point"}
}