{
  "type": "Feature",
  "properties": {
    "addr:full":"Roblin ON K0K 2W0",
    "addr:postcode":"k0k 2w0",
    "iso:country":"CA",
    "sg:city":"Roblin",
    "sg:classifiers":[
        {
            "category":"Organizations",
            "subcategory":"Religious Organization",
            "type":"Services"
        }
    ],
    "sg:phone":"+1 613 388 2518",
    "sg:postcode":"K0K 2W0",
    "sg:province":"ON",
    "sg:tags":[
        "church"
    ],
    "wof:name":"Wesleyan Church",
    "wof:placetype":"venue"
},
  "geometry": {"coordinates":[-77.027168,44.388977],"type":"Point"}
}