{
  "type": "Feature",
  "properties": {
    "iso:country":"CA",
    "sg:city":"Thetford Mines",
    "sg:classifiers":[
        {
            "category":"Autos & Motor Vehicles",
            "subcategory":"Auto Supplies",
            "type":"Retail Goods"
        }
    ],
    "sg:phone":"+1 418 335 6381",
    "sg:postcode":"G6G 1N3",
    "sg:province":"QC",
    "sg:tags":[
        "automobile",
        "stereo",
        "radio"
    ],
    "wof:name":"Carrier Electronique Inc",
    "wof:placetype":"venue"
},
  "geometry": {"coordinates":[-71.3057098389,46.0868034363],"type":"Point"}
}