{
  "type": "Feature",
  "properties": {
    "addr:full":"Pond Inlet NU X0A 0S0",
    "addr:postcode":"x0a 0s0",
    "iso:country":"CA",
    "sg:city":"Pond Inlet",
    "sg:classifiers":[
        {
            "category":"Building & Trades",
            "subcategory":"Construction",
            "type":"Services"
        }
    ],
    "sg:phone":"+1 867 899 8462",
    "sg:postcode":"X0A 0S0",
    "sg:province":"NU",
    "sg:tags":[
        "general",
        "contractor"
    ],
    "wof:name":"Nunavut Construction Corp",
    "wof:placetype":"venue"
},
  "geometry": {"coordinates":[-77.953941,72.698143],"type":"Point"}
}