{
  "type": "Feature",
  "properties": {
    "addr:full":"1735 Trans Canada Hwy E Kamloops BC V2C 3Z6",
    "addr:housenumber":"1735",
    "addr:postcode":"bc v2c 3z6",
    "addr:street":"Trans Canada Hwy E",
    "iso:country":"CA",
    "sg:address":"1735 Trans Canada Hwy E",
    "sg:city":"Kamloops",
    "sg:classifiers":[
        {
            "category":"Restaurant",
            "type":"Food & Drink"
        }
    ],
    "sg:phone":"+1 250 374 2744",
    "sg:postcode":"V2C 3Z6",
    "sg:province":"BC",
    "wof:name":"Wendy's",
    "wof:placetype":"venue"
},
  "geometry": {"coordinates":[-120.28868900000001,50.676777],"type":"Point"}
}