{
  "type": "Feature",
  "properties": {
    "addr:full":"Victoria BC V8R 2S6",
    "addr:postcode":"v8r 2s6",
    "iso:country":"CA",
    "sg:city":"Victoria",
    "sg:classifiers":[
        {
            "category":"Shopping",
            "subcategory":"Hobbies, Toys, & Games",
            "type":"Retail Goods"
        }
    ],
    "sg:phone":"+1 250 595 6501",
    "sg:postcode":"V8R 2S6",
    "sg:province":"BC",
    "wof:name":"Buddies Toy Store",
    "wof:placetype":"venue"
},
  "geometry": {"coordinates":[-123.307762146,48.4373664856],"type":"Point"}
}