{
  "type": "Feature",
  "properties": {
    "addr:full":"1873 Rue Principale Pohenegamook QC G0L 1J0",
    "addr:housenumber":"1873",
    "addr:postcode":"g0l 1j0",
    "addr:street":"Rue Principale",
    "iso:country":"CA",
    "sg:address":"1873 Rue Principale",
    "sg:city":"Pohenegamook",
    "sg:classifiers":[
        {
            "category":"Bars & Pubs",
            "type":"Food & Drink"
        }
    ],
    "sg:phone":"+1 418 859 2441",
    "sg:postcode":"G0L 1J0",
    "sg:province":"QC",
    "sg:tags":[
        "lounge",
        "cocktail"
    ],
    "wof:name":"Bar L'Eden",
    "wof:placetype":"venue"
},
  "geometry": {"coordinates":[-69.28014400000001,47.486214],"type":"Point"}
}