{
  "type": "Feature",
  "properties": {
    "addr:full":"25 Rogate Pl Scarborough ON M1M 3C4",
    "addr:housenumber":"25",
    "addr:postcode":"m1m 3c4",
    "addr:street":"Rogate Pl",
    "iso:country":"CA",
    "sg:address":"25 Rogate Pl",
    "sg:city":"Scarborough",
    "sg:classifiers":[
        {
            "category":"Professional",
            "subcategory":"Computer Services",
            "type":"Services"
        }
    ],
    "sg:phone":"+1 416 267 8399",
    "sg:postcode":"M1M 3C4",
    "sg:province":"ON",
    "sg:tags":[
        "consultant"
    ],
    "wof:name":"Netrus",
    "wof:placetype":"venue"
},
  "geometry": {"coordinates":[-79.205513,43.737255],"type":"Point"}
}