{
  "type": "Feature",
  "properties": {
    "iso:country":"CA",
    "sg:address":"2413 6th Ave",
    "sg:city":"Regina",
    "sg:classifiers":[
        {
            "category":"Manufacturing",
            "subcategory":"Building Materials",
            "type":"Manufacturing & Wholesale Goods"
        }
    ],
    "sg:phone":"+1 306 565 0033",
    "sg:postcode":"S4R 1B5",
    "sg:province":"SK",
    "wof:name":"Lancashire Distribution",
    "wof:placetype":"venue"
},
  "geometry": {"coordinates":[-104.615470886,50.4597244263],"type":"Point"}
}