{
  "type": "Feature",
  "properties": {
    "addr:full":"3215 Dunmore Rd SE Medicine Hat AB T1B 2H2",
    "addr:housenumber":"3215",
    "addr:postcode":"t1b 2h2",
    "addr:street":"Dunmore Rd Se",
    "iso:country":"CA",
    "sg:address":"3215 Dunmore Rd SE",
    "sg:city":"Medicine Hat",
    "sg:classifiers":[
        {
            "category":"Manufacturing",
            "subcategory":"Jewelry",
            "type":"Manufacturing & Wholesale Goods"
        }
    ],
    "sg:phone":"+1 403 527 0620",
    "sg:postcode":"T1B 2H2",
    "sg:province":"AB",
    "sg:tags":[
        "jeweler",
        "supply"
    ],
    "wof:name":"Galaxie",
    "wof:placetype":"venue"
},
  "geometry": {"coordinates":[-110.646873474,50.0082550049],"type":"Point"}
}