{
  "type": "Feature",
  "properties": {
    "iso:country":"CA",
    "sg:address":"325 Munro St",
    "sg:city":"Thunder Bay",
    "sg:classifiers":[
        {
            "category":"Travel",
            "subcategory":"Hotels & Motels",
            "type":"Entertainment"
        }
    ],
    "sg:phone":"+1 807 345 5342",
    "sg:postcode":"P7A 2N4",
    "sg:province":"ON",
    "wof:name":"Munro Motel",
    "wof:placetype":"venue"
},
  "geometry": {"coordinates":[-89.2071762085,48.4501876831],"type":"Point"}
}