{
  "type": "Feature",
  "properties": {
    "addr:full":"15750 128 Ave NW Edmonton AB T5V 1G1",
    "addr:housenumber":"15750",
    "addr:postcode":"t5v 1g1",
    "addr:street":"128 Ave Nw",
    "iso:country":"CA",
    "sg:address":"15750 128 Ave NW",
    "sg:city":"Edmonton",
    "sg:classifiers":[
        {
            "category":"Wholesale",
            "subcategory":"Motor Vehicles",
            "type":"Manufacturing & Wholesale Goods"
        }
    ],
    "sg:phone":"+1 780 447 2237",
    "sg:postcode":"T5V 1G1",
    "sg:province":"AB",
    "sg:tags":[
        "trailer"
    ],
    "wof:name":"Gerry's Trailer Sales Ltd",
    "wof:placetype":"venue"
},
  "geometry": {"coordinates":[-113.59346771200001,53.5850601196],"type":"Point"}
}