{
  "type": "Feature",
  "properties": {
    "addr:full":"Richmond BC V7A 4S5",
    "addr:postcode":"v7a 4s5",
    "iso:country":"CA",
    "sg:city":"Richmond",
    "sg:classifiers":[
        {
            "category":"Wholesale",
            "subcategory":"Machinery & Supplies",
            "type":"Manufacturing & Wholesale Goods"
        }
    ],
    "sg:phone":"+1 604 271 2200",
    "sg:postcode":"V7A 4S5",
    "sg:province":"BC",
    "sg:tags":[
        "machine",
        "sewing"
    ],
    "wof:name":"Janome Sewing Machine CO Ltd",
    "wof:placetype":"venue"
},
  "geometry": {"coordinates":[-123.09607696499999,49.1303863525],"type":"Point"}
}