{
  "type": "Feature",
  "properties": {
    "addr:full":"1526 Woods Dr North Vancouver BC V7R 1A9",
    "addr:housenumber":"1526",
    "addr:postcode":"v7r 1a9",
    "addr:street":"Woods Dr",
    "iso:country":"CA",
    "sg:address":"1526 Woods Dr",
    "sg:city":"North Vancouver",
    "sg:classifiers":[
        {
            "category":"Shopping",
            "subcategory":"Computers & Home Electronics",
            "type":"Retail Goods"
        }
    ],
    "sg:phone":"+1 604 980 7663",
    "sg:postcode":"V7R 1A9",
    "sg:province":"BC",
    "sg:tags":[
        "software"
    ],
    "wof:name":"Maplewood Computing",
    "wof:placetype":"venue"
},
  "geometry": {"coordinates":[-123.115669,49.334839],"type":"Point"}
}