{
  "type": "Feature",
  "properties": {
    "addr:full":"10 Dunlop Dr St Catharines ON L2R 1A2",
    "addr:housenumber":"10",
    "addr:postcode":"l2r 1a2",
    "addr:street":"Dunlop Dr",
    "iso:country":"CA",
    "sg:address":"10 Dunlop Dr",
    "sg:city":"St Catharines",
    "sg:classifiers":[
        {
            "category":"Food & Beverages",
            "subcategory":"Bakery",
            "type":"Retail Goods"
        }
    ],
    "sg:phone":"+1 905 984 5225",
    "sg:postcode":"L2R 1A2",
    "sg:province":"ON",
    "sg:tags":[
        "doughnut"
    ],
    "wof:name":"Donut Diners",
    "wof:placetype":"venue"
},
  "geometry": {"coordinates":[-79.244072,43.175304],"type":"Point"}
}