{
  "type": "Feature",
  "properties": {
    "addr:full":"26 Braemar Cres London ON N6H 2X1",
    "addr:housenumber":"26",
    "addr:postcode":"n6h 2x1",
    "addr:street":"Braemar Cres",
    "iso:country":"CA",
    "sg:address":"26 Braemar Cres",
    "sg:city":"London",
    "sg:classifiers":[
        {
            "category":"Professional",
            "subcategory":"Management & Consulting",
            "type":"Services"
        }
    ],
    "sg:phone":"+1 519 472 5065",
    "sg:postcode":"N6H 2X1",
    "sg:province":"ON",
    "sg:tags":[
        "marketing",
        "consultant"
    ],
    "wof:name":"Don Park Marketing",
    "wof:placetype":"venue"
},
  "geometry": {"coordinates":[-81.28703308110001,42.9787559509],"type":"Point"}
}