{
  "type": "Feature",
  "properties": {
    "addr:full":"6432 Route 101 Hoyt NB E5L 2A7",
    "addr:housenumber":"6432",
    "addr:postcode":"e5l 2a7",
    "addr:street":"Route 101",
    "iso:country":"CA",
    "sg:address":"6432 Route 101",
    "sg:city":"Hoyt",
    "sg:classifiers":[
        {
            "category":"Shopping",
            "subcategory":"Discount & Variety Stores",
            "type":"Retail Goods"
        }
    ],
    "sg:phone":"+1 506 687 4202",
    "sg:postcode":"E5L 2A7",
    "sg:province":"NB",
    "sg:tags":[
        "merchandise",
        "general"
    ],
    "wof:name":"Kirkpatrick's Mercantile",
    "wof:placetype":"venue"
},
  "geometry": {"coordinates":[-66.547928,45.580212],"type":"Point"}
}