{
  "type": "Feature",
  "properties": {
    "addr:full":"Moisie QC G0G 2B0",
    "addr:postcode":"g0g 2b0",
    "iso:country":"CA",
    "sg:city":"Moisie",
    "sg:classifiers":[
        {
            "category":"Restaurant",
            "type":"Food & Drink"
        }
    ],
    "sg:phone":"+1 418 927 2066",
    "sg:postcode":"G0G 2B0",
    "sg:province":"QC",
    "wof:name":"Casse-Croute LA Petite Bouffe",
    "wof:placetype":"venue"
},
  "geometry": {"coordinates":[-66.206436,50.220779],"type":"Point"}
}