{
  "type": "Feature",
  "properties": {
    "addr:full":"Saint-Jerome QC J5L 1G2",
    "addr:postcode":"j5l 1g2",
    "iso:country":"CA",
    "sg:city":"Saint-Jerome",
    "sg:classifiers":[
        {
            "category":"Wholesale",
            "subcategory":"Meat",
            "type":"Manufacturing & Wholesale Goods"
        }
    ],
    "sg:phone":"+1 450 438 3842",
    "sg:postcode":"J5L 1G2",
    "sg:province":"QC",
    "sg:tags":[
        "butchering"
    ],
    "wof:name":"Salaison Legare",
    "wof:placetype":"venue"
},
  "geometry": {"coordinates":[-74.027771,45.750065],"type":"Point"}
}