{
  "type": "Feature",
  "properties": {
    "addr:full":"2045 Midland Ave Scarborough ON M1P 3E2",
    "addr:housenumber":"2045",
    "addr:postcode":"m1p 3e2",
    "addr:street":"Midland Ave",
    "iso:country":"CA",
    "sg:address":"2045 Midland Ave",
    "sg:city":"Scarborough",
    "sg:classifiers":[
        {
            "category":"Wholesale",
            "subcategory":"Machinery & Supplies",
            "type":"Manufacturing & Wholesale Goods"
        }
    ],
    "sg:phone":"+1 416 291 8085",
    "sg:postcode":"M1P 3E2",
    "sg:province":"ON",
    "sg:tags":[
        "packaging"
    ],
    "wof:name":"Emplex Systems Inc",
    "wof:placetype":"venue"
},
  "geometry": {"coordinates":[-79.271378,43.769402],"type":"Point"}
}