{
  "type": "Feature",
  "properties": {
    "addr:full":"301 2nd Ave S Cranbrook BC V1C 2B2",
    "addr:housenumber":"301",
    "addr:postcode":"bc v1c 2b2",
    "addr:street":"2Nd Ave S",
    "iso:country":"CA",
    "sg:address":"301 2nd Ave S",
    "sg:city":"Cranbrook",
    "sg:classifiers":[
        {
            "category":"Building & Trades",
            "subcategory":"Plumbing",
            "type":"Services"
        }
    ],
    "sg:phone":"+1 250 489 1803",
    "sg:postcode":"V1C 2B2",
    "sg:province":"BC",
    "sg:tags":[
        "conditioning",
        "contractor",
        "system",
        "air"
    ],
    "wof:name":"Dean's Plumbing & Heating",
    "wof:placetype":"venue"
},
  "geometry": {"coordinates":[-115.778931,49.506516],"type":"Point"}
}