{
  "type": "Feature",
  "properties": {
    "iso:country":"CA",
    "sg:address":"16635 Yonge St",
    "sg:city":"Newmarket",
    "sg:classifiers":[
        {
            "category":"Autos & Motor Vehicles",
            "subcategory":"Fuel & Gas Station",
            "type":"Retail Goods"
        }
    ],
    "sg:phone":"+1 905 898 0430",
    "sg:postcode":"L3X 1V6",
    "sg:province":"ON",
    "sg:tags":[
        "oil"
    ],
    "wof:name":"Shell Canada Products Ltd",
    "wof:placetype":"venue"
},
  "geometry": {"coordinates":[-79.475258,44.033672],"type":"Point"}
}