{
  "type": "Feature",
  "properties": {
    "addr:full":"44 Steinway Blvd #4 Etobicoke ON M9W 6Y7",
    "addr:housenumber":"44",
    "addr:postcode":"m9w 6y7",
    "addr:street":"Steinway Blvd # 4",
    "iso:country":"CA",
    "sg:address":"44 Steinway Blvd #4",
    "sg:city":"Etobicoke",
    "sg:classifiers":[
        {
            "category":"Building & Trades",
            "subcategory":"Construction",
            "type":"Services"
        }
    ],
    "sg:phone":"+1 416 798 8422",
    "sg:postcode":"M9W 6Y7",
    "sg:province":"ON",
    "sg:tags":[
        "general",
        "contractor"
    ],
    "wof:name":"Tartu Inc",
    "wof:placetype":"venue"
},
  "geometry": {"coordinates":[-79.6234054565,43.7508354187],"type":"Point"}
}