{
  "type": "Feature",
  "properties": {
    "iso:country":"CA",
    "sg:address":"General Delivery",
    "sg:city":"Beaver Creek",
    "sg:classifiers":[
        {
            "category":"Government",
            "subcategory":"Office",
            "type":"Public Place"
        }
    ],
    "sg:phone":"+1 867 862 7230",
    "sg:postcode":"Y0B 1A0",
    "sg:province":"YT",
    "wof:name":"Canada Customs",
    "wof:placetype":"venue"
},
  "geometry": {"coordinates":[-140.87725830100001,62.3790016174],"type":"Point"}
}