{
  "type": "Feature",
  "properties": {
    "addr:full":"751 Lorne St W Swift Current SK S9H 0J7",
    "addr:housenumber":"751",
    "addr:postcode":"s9h 0j7",
    "addr:street":"Lorne St W",
    "iso:country":"CA",
    "sg:address":"751 Lorne St W",
    "sg:city":"Swift Current",
    "sg:classifiers":[
        {
            "category":"Education",
            "subcategory":"School",
            "type":"Public Place"
        }
    ],
    "sg:phone":"+1 306 778 4645",
    "sg:postcode":"S9H 0J7",
    "sg:province":"SK",
    "wof:name":"St Patrick's Separate School",
    "wof:placetype":"venue"
},
  "geometry": {"coordinates":[-107.809577942,50.2895545959],"type":"Point"}
}