{
  "type": "Feature",
  "properties": {
    "addr:full":"Edmonton AB T5J 1V9",
    "addr:postcode":"t5j 1v9",
    "iso:country":"CA",
    "sg:city":"Edmonton",
    "sg:classifiers":[
        {
            "category":"Professional",
            "subcategory":"Business Services",
            "type":"Services"
        }
    ],
    "sg:phone":"+1 780 421 8557",
    "sg:postcode":"T5J 1V9",
    "sg:province":"AB",
    "sg:tags":[
        "credit",
        "other",
        "paralegal",
        "plan",
        "card"
    ],
    "wof:name":"Arvic Search Svc Ltd",
    "wof:placetype":"venue"
},
  "geometry": {"coordinates":[-113.493118286,53.54114151],"type":"Point"}
}