{
  "type": "Feature",
  "properties": {
    "addr:full":"70 St David St Mitchell ON N0K 1N0",
    "addr:housenumber":"70",
    "addr:postcode":"n0k 1n0",
    "addr:street":"St David St",
    "iso:country":"CA",
    "sg:address":"70 St David St",
    "sg:city":"Mitchell",
    "sg:classifiers":[
        {
            "category":"Building & Trades",
            "subcategory":"Construction",
            "type":"Services"
        }
    ],
    "sg:phone":"+1 519 348 9568",
    "sg:postcode":"N0K 1N0",
    "sg:province":"ON",
    "sg:tags":[
        "painter"
    ],
    "wof:name":"Mike Uniac Painting & Dcrtng",
    "wof:placetype":"venue"
},
  "geometry": {"coordinates":[-81.19673899999999,43.463448],"type":"Point"}
}