{
  "type": "Feature",
  "properties": {
    "addr:full":"19 Cambridge St Cambridge ON N1R 3R8",
    "addr:housenumber":"19",
    "addr:postcode":"n1r 3r8",
    "addr:street":"Cambridge St",
    "iso:country":"CA",
    "sg:address":"19 Cambridge St",
    "sg:city":"Cambridge",
    "sg:classifiers":[
        {
            "category":"Professional",
            "subcategory":"Lawyer & Legal Services",
            "type":"Services"
        }
    ],
    "sg:phone":"+1 519 621 7260",
    "sg:postcode":"N1R 3R8",
    "sg:province":"ON",
    "sg:tags":[
        "attorney"
    ],
    "wof:name":"Whitteveen, Stephen F",
    "wof:placetype":"venue"
},
  "geometry": {"coordinates":[-80.3124923706,43.3614196777],"type":"Point"}
}