{
  "type": "Feature",
  "properties": {
    "iso:country":"CA",
    "sg:address":"813 Parkinson Rd",
    "sg:city":"Woodstock",
    "sg:classifiers":[
        {
            "category":"Health Services",
            "subcategory":"Doctor",
            "type":"Services"
        }
    ],
    "sg:phone":"+1 519 539 7049",
    "sg:postcode":"N4S 8L1",
    "sg:province":"ON",
    "sg:tags":[
        "dentist"
    ],
    "wof:name":"Rutherdale, Thanh DDS",
    "wof:placetype":"venue"
},
  "geometry": {"coordinates":[-80.7382888794,43.1205215454],"type":"Point"}
}