{
  "type": "Feature",
  "properties": {
    "addr:full":"180 Adelaide St S London ON N5Z 3L1",
    "addr:housenumber":"180",
    "addr:postcode":"n5z 3l1",
    "addr:street":"Adelaide St S",
    "iso:country":"CA",
    "sg:address":"180 Adelaide St S",
    "sg:city":"London",
    "sg:classifiers":[
        {
            "category":"Real Estate",
            "subcategory":"Real Estate Agent",
            "type":"Services"
        }
    ],
    "sg:phone":"+1 519 680 1872",
    "sg:postcode":"N5Z 3L1",
    "sg:province":"ON",
    "sg:tags":[
        "management"
    ],
    "wof:name":"Niwri Management",
    "wof:placetype":"venue"
},
  "geometry": {"coordinates":[-81.22146606450001,42.9657745361],"type":"Point"}
}