{
  "type": "Feature",
  "properties": {
    "iso:country":"CA",
    "sg:address":"1231 King's Hwy",
    "sg:city":"Fort Frances",
    "sg:classifiers":[
        {
            "category":"Real Estate",
            "subcategory":"Real Estate Operator",
            "type":"Services"
        }
    ],
    "sg:phone":"+1 807 274 6456",
    "sg:postcode":"P9A 2X8",
    "sg:province":"ON",
    "sg:tags":[
        "mobile",
        "home",
        "community"
    ],
    "wof:name":"Walleye Trailer Park Ltd",
    "wof:placetype":"venue"
},
  "geometry": {"coordinates":[-93.4358291626,48.6071434021],"type":"Point"}
}