{
  "type": "Feature",
  "properties": {
    "addr:full":"9 Sir Winston Churchill Sq NW Edmonton AB T5J 5B5",
    "addr:housenumber":"9",
    "addr:postcode":"t5j 5b5",
    "addr:street":"Sir Winston Churchill Sq Nw",
    "iso:country":"CA",
    "sg:address":"9 Sir Winston Churchill Sq NW",
    "sg:city":"Edmonton",
    "sg:classifiers":[
        {
            "category":"Banks & Credit Unions",
            "subcategory":"Bank",
            "type":"Services"
        }
    ],
    "sg:phone":"+1 780 424 4771",
    "sg:postcode":"T5J 5B5",
    "sg:province":"AB",
    "wof:name":"National Bank of Canada",
    "wof:placetype":"venue"
},
  "geometry": {"coordinates":[-113.490623474,53.5446014404],"type":"Point"}
}