{
  "type": "Feature",
  "properties": {
    "addr:full":"125 Wilson Ave Timmins ON P4N 2S8",
    "addr:housenumber":"125",
    "addr:postcode":"p4n 2s8",
    "addr:street":"Wilson Ave",
    "iso:country":"CA",
    "sg:address":"125 Wilson Ave",
    "sg:city":"Timmins",
    "sg:classifiers":[
        {
            "category":"Wholesale",
            "subcategory":"Meat",
            "type":"Manufacturing & Wholesale Goods"
        }
    ],
    "sg:phone":"+1 705 268 1955",
    "sg:postcode":"P4N 2S8",
    "sg:province":"ON",
    "sg:tags":[
        "butchering"
    ],
    "wof:name":"Dabrowski's Smoked Meats Ltd",
    "wof:placetype":"venue"
},
  "geometry": {"coordinates":[-81.338638,48.475224],"type":"Point"}
}