{
  "type": "Feature",
  "properties": {
    "addr:full":"15018 12th Ave Blairmore AB T0K 0E0",
    "addr:housenumber":"15018",
    "addr:postcode":"t0k 0e0",
    "addr:street":"12Th Ave",
    "iso:country":"CA",
    "sg:address":"15018 12th Ave",
    "sg:city":"Blairmore",
    "sg:classifiers":[
        {
            "category":"Home & Garden",
            "subcategory":"Building Materials",
            "type":"Retail Goods"
        }
    ],
    "sg:phone":"+1 403 562 8658",
    "sg:postcode":"T0K 0E0",
    "sg:province":"AB",
    "wof:name":"Border Building Materials",
    "wof:placetype":"venue"
},
  "geometry": {"coordinates":[-114.436981,49.607658],"type":"Point"}
}