{
  "type": "Feature",
  "properties": {
    "addr:full":"1330 Portage Ave Winnipeg MB R3G 0V6",
    "addr:housenumber":"1330",
    "addr:postcode":"r3g 0v6",
    "addr:street":"Portage Ave",
    "iso:country":"CA",
    "sg:address":"1330 Portage Ave",
    "sg:city":"Winnipeg",
    "sg:classifiers":[
        {
            "category":"Education",
            "subcategory":"Special Training",
            "type":"Public Place"
        }
    ],
    "sg:phone":"+1 204 786 1199",
    "sg:postcode":"R3G 0V6",
    "sg:province":"MB",
    "sg:tags":[
        "instruction",
        "music"
    ],
    "wof:name":"Yamaha Music Schools",
    "wof:placetype":"venue"
},
  "geometry": {"coordinates":[-97.189697,49.882328],"type":"Point"}
}