{
  "type": "Feature",
  "properties": {
    "addr:full":"4680 Ch Georgeville Stanstead QC J0B 3E0",
    "addr:postcode":"4680;j0b 3e0",
    "addr:street":"Ch Georgeville",
    "iso:country":"CA",
    "sg:address":"4680 Ch Georgeville",
    "sg:city":"Stanstead",
    "sg:classifiers":[
        {
            "category":"Recreation",
            "type":"Entertainment"
        }
    ],
    "sg:phone":"+1 819 847 0612",
    "sg:postcode":"J0B 3E0",
    "sg:province":"QC",
    "sg:tags":[
        "center"
    ],
    "wof:name":"Community Assn of Georgeville",
    "wof:placetype":"venue"
},
  "geometry": {"coordinates":[-72.25243377690001,45.1400947571],"type":"Point"}
}