{
  "type": "Feature",
  "properties": {
    "addr:full":"627 Oxford St Peterborough ON K9H 2A9",
    "addr:housenumber":"627",
    "addr:postcode":"k9h 2a9",
    "addr:street":"Oxford St",
    "iso:country":"CA",
    "sg:address":"627 Oxford St",
    "sg:city":"Peterborough",
    "sg:classifiers":[
        {
            "category":"Professional",
            "subcategory":"Business Services",
            "type":"Services"
        }
    ],
    "sg:phone":"+1 705 876 7670",
    "sg:postcode":"K9H 2A9",
    "sg:province":"ON",
    "sg:tags":[
        "fund",
        "promotion",
        "raising"
    ],
    "wof:name":"Ron Hawkins Campaign",
    "wof:placetype":"venue"
},
  "geometry": {"coordinates":[-78.310631,44.312893],"type":"Point"}
}