{
  "type": "Feature",
  "properties": {
    "addr:full":"214 Quappelle St W Mcauley MB R0M 1H0",
    "addr:housenumber":"214",
    "addr:postcode":"r0m 1h0",
    "addr:street":"Quappelle St W Mcauley",
    "iso:country":"CA",
    "sg:address":"214 Quappelle St W",
    "sg:city":"Mcauley",
    "sg:classifiers":[
        {
            "category":"Social Services",
            "type":"Services"
        }
    ],
    "sg:phone":"+1 204 722 2313",
    "sg:postcode":"R0M 1H0",
    "sg:province":"MB",
    "sg:tags":[
        "organization",
        "welfare"
    ],
    "wof:name":"Mc Auley Fun Club",
    "wof:placetype":"venue"
},
  "geometry": {"coordinates":[-101.38427,50.263226],"type":"Point"}
}