{
  "type": "Feature",
  "properties": {
    "addr:full":"3866 Charlton Dr Qualicum Beach BC V9K 1Z3",
    "addr:housenumber":"3866",
    "addr:postcode":"v9k 1z3",
    "addr:street":"Charlton Dr",
    "iso:country":"CA",
    "sg:address":"3866 Charlton Dr",
    "sg:city":"Qualicum Beach",
    "sg:classifiers":[
        {
            "category":"Building & Trades",
            "subcategory":"Plumbing",
            "type":"Services"
        }
    ],
    "sg:phone":"+1 250 757 8496",
    "sg:postcode":"V9K 1Z3",
    "sg:province":"BC",
    "sg:tags":[
        "contractor"
    ],
    "wof:name":"Qualicum Bay Plumbing",
    "wof:placetype":"venue"
},
  "geometry": {"coordinates":[-124.441704,49.346706],"type":"Point"}
}