{
  "type": "Feature",
  "properties": {
    "addr:full":"7077 Rue Beaubien E Anjou QC H1M 2Y2",
    "addr:housenumber":"7077",
    "addr:postcode":"h1m 2y2",
    "addr:street":"Rue Beaubien E",
    "iso:country":"CA",
    "sg:address":"7077 Rue Beaubien E",
    "sg:city":"Anjou",
    "sg:classifiers":[
        {
            "category":"Wholesale",
            "subcategory":"Fruits & Vegetables",
            "type":"Manufacturing & Wholesale Goods"
        }
    ],
    "sg:phone":"+1 514 354 8181",
    "sg:postcode":"H1M 2Y2",
    "sg:province":"QC",
    "wof:name":"Sunkist Growers",
    "wof:placetype":"venue"
},
  "geometry": {"coordinates":[-73.557648,45.593681],"type":"Point"}
}