{
  "type": "Feature",
  "properties": {
    "addr:full":"255 Metcalf St #4 Tweed ON K0K 3J0",
    "addr:housenumber":"255",
    "addr:postcode":"k0k 3j0",
    "addr:street":"Metcalf St # 4",
    "iso:country":"CA",
    "sg:address":"255 Metcalf St #4",
    "sg:city":"Tweed",
    "sg:classifiers":[
        {
            "category":"Travel",
            "subcategory":"Travel Agent",
            "type":"Entertainment"
        }
    ],
    "sg:phone":"+1 613 478 1444",
    "sg:postcode":"K0K 3J0",
    "sg:province":"ON",
    "sg:tags":[
        "information",
        "tourist"
    ],
    "wof:name":"Eastern Ontario Trails Allnce",
    "wof:placetype":"venue"
},
  "geometry": {"coordinates":[-77.314171,44.477169],"type":"Point"}
}