{
  "type": "Feature",
  "properties": {
    "iso:country":"CA",
    "sg:address":"365 Rue Main",
    "sg:city":"Gatineau",
    "sg:classifiers":[
        {
            "category":"Bars & Pubs",
            "type":"Food & Drink"
        }
    ],
    "sg:phone":"+1 819 663 0614",
    "sg:postcode":"J8P 5K6",
    "sg:province":"QC",
    "sg:tags":[
        "club",
        "night"
    ],
    "wof:name":"Club 77",
    "wof:placetype":"venue"
},
  "geometry": {"coordinates":[-75.6520690918,45.4909439087],"type":"Point"}
}