{
  "type": "Feature",
  "properties": {
    "iso:country":"CA",
    "sg:address":"135 Av DE LA Graviere",
    "sg:city":"Coaticook",
    "sg:classifiers":[
        {
            "category":"Home & Garden",
            "subcategory":"Furniture",
            "type":"Retail Goods"
        }
    ],
    "sg:phone":"+1 819 849 4161",
    "sg:postcode":"J1A 3E5",
    "sg:province":"QC",
    "sg:tags":[
        "equipment",
        "kitchen",
        "cabinet"
    ],
    "wof:name":"Cuisines Modernes DE L'Estrie",
    "wof:placetype":"venue"
},
  "geometry": {"coordinates":[-71.81299591059999,45.1269874573],"type":"Point"}
}