{
  "type": "Feature",
  "properties": {
    "addr:full":"Easterville MB R0C 0V0",
    "addr:postcode":"r0c 0v0",
    "iso:country":"CA",
    "sg:city":"Easterville",
    "sg:classifiers":[
        {
            "category":"Social Services",
            "type":"Services"
        }
    ],
    "sg:phone":"+1 204 329 2035",
    "sg:postcode":"R0C 0V0",
    "sg:province":"MB",
    "sg:tags":[
        "youth",
        "organization",
        "center"
    ],
    "wof:name":"Chemawawin Youth Ctr",
    "wof:placetype":"venue"
},
  "geometry": {"coordinates":[-99.81971,53.106041],"type":"Point"}
}