{
  "type": "Feature",
  "properties": {
    "addr:full":"520 Main St N Montague PE C0A 1R0",
    "addr:housenumber":"520",
    "addr:postcode":"c0a 1r0",
    "addr:street":"Main St N",
    "iso:country":"CA",
    "sg:address":"520 Main St N",
    "sg:city":"Montague",
    "sg:classifiers":[
        {
            "category":"Manufacturing",
            "subcategory":"Food",
            "type":"Manufacturing & Wholesale Goods"
        }
    ],
    "sg:phone":"+1 902 838 4170",
    "sg:postcode":"C0A 1R0",
    "sg:province":"PE",
    "sg:tags":[
        "baker",
        "cookie",
        "bakery"
    ],
    "wof:name":"Montague Bakery Ltd",
    "wof:placetype":"venue"
},
  "geometry": {"coordinates":[-62.6500968933,46.168636322],"type":"Point"}
}