{
  "type": "Feature",
  "properties": {
    "addr:full":"59 Toms Rd Barrington NS B0W 1E0",
    "addr:housenumber":"59",
    "addr:postcode":"b0w 1e0",
    "addr:street":"Toms Rd",
    "iso:country":"CA",
    "sg:address":"59 Toms Rd",
    "sg:city":"Barrington",
    "sg:classifiers":[
        {
            "category":"Home & Garden",
            "subcategory":"Building Materials",
            "type":"Retail Goods"
        }
    ],
    "sg:phone":"+1 902 637 2101",
    "sg:postcode":"B0W 1E0",
    "sg:province":"NS",
    "sg:tags":[
        "lumber"
    ],
    "wof:name":"Thomas Scott Lumber Ltd",
    "wof:placetype":"venue"
},
  "geometry": {"coordinates":[-65.583405,43.571178],"type":"Point"}
}