{
  "type": "Feature",
  "properties": {
    "addr:full":"85 Rosedale Ave W Brampton ON L6X 4H5",
    "addr:housenumber":"85",
    "addr:postcode":"l6x 4h5",
    "addr:street":"Rosedale Ave W",
    "iso:country":"CA",
    "sg:address":"85 Rosedale Ave W",
    "sg:city":"Brampton",
    "sg:classifiers":[
        {
            "category":"Personal",
            "type":"Services"
        }
    ],
    "sg:phone":"+1 905 452 2558",
    "sg:postcode":"L6X 4H5",
    "sg:province":"ON",
    "sg:tags":[
        "therapist",
        "massage"
    ],
    "wof:name":"Mc Phee, Loriann",
    "wof:placetype":"venue"
},
  "geometry": {"coordinates":[-79.77066802980001,43.6874656677],"type":"Point"}
}