{
  "type": "Feature",
  "properties": {
    "iso:country":"CA",
    "sg:address":"53 Victoria St",
    "sg:city":"Elora",
    "sg:classifiers":[
        {
            "category":"Travel",
            "subcategory":"Hotels & Motels",
            "type":"Entertainment"
        }
    ],
    "sg:phone":"+1 519 846 0703",
    "sg:postcode":"N0B 1S0",
    "sg:province":"ON",
    "sg:tags":[
        "breakfast",
        "accommodation",
        "bed"
    ],
    "wof:name":"Blinkers Bed & Breakfast",
    "wof:placetype":"venue"
},
  "geometry": {"coordinates":[-80.43022918699999,43.67943573],"type":"Point"}
}