{
  "type": "Feature",
  "properties": {
    "addr:full":"1100 Barnett Dr Cumberland ON K4C 1C7",
    "addr:housenumber":"1100",
    "addr:postcode":"k4c 1c7",
    "addr:street":"Barnett Dr",
    "iso:country":"CA",
    "sg:address":"1100 Barnett Dr",
    "sg:city":"Cumberland",
    "sg:classifiers":[
        {
            "category":"Social Services",
            "type":"Services"
        }
    ],
    "sg:phone":"+1 613 833 1608",
    "sg:postcode":"K4C 1C7",
    "sg:province":"ON",
    "sg:tags":[
        "organization",
        "welfare"
    ],
    "wof:name":"Family Tree Youth Svc",
    "wof:placetype":"venue"
},
  "geometry": {"coordinates":[-75.397659,45.515633],"type":"Point"}
}