{
  "type": "Feature",
  "properties": {
    "addr:full":"Georgetown ON L7G 3H3",
    "addr:postcode":"l7g 3h3",
    "iso:country":"CA",
    "sg:city":"Georgetown",
    "sg:classifiers":[
        {
            "category":"Restaurant",
            "type":"Food & Drink"
        }
    ],
    "sg:phone":"+1 905 877 3000",
    "sg:postcode":"L7G 3H3",
    "sg:province":"ON",
    "sg:tags":[
        "pizza"
    ],
    "wof:name":"A Joe's Great 2 For 1 Pizza",
    "wof:placetype":"venue"
},
  "geometry": {"coordinates":[-79.9335479736,43.6548271179],"type":"Point"}
}