{
  "type": "Feature",
  "properties": {
    "iso:country":"CA",
    "sg:address":"4673 Ontario St",
    "sg:city":"Beamsville",
    "sg:classifiers":[
        {
            "category":"Freight",
            "type":"Transportation"
        }
    ],
    "sg:phone":"+1 905 563 8816",
    "sg:postcode":"L0R 1B3",
    "sg:province":"ON",
    "sg:tags":[
        "truck",
        "plaza",
        "commercial",
        "stops"
    ],
    "wof:name":"Beamsville Relay Station",
    "wof:placetype":"venue"
},
  "geometry": {"coordinates":[-79.4766616821,43.1833076477],"type":"Point"}
}