{
  "type": "Feature",
  "properties": {
    "iso:country":"CA",
    "sg:address":"379 Bonaventure Dr",
    "sg:city":"Timmins",
    "sg:classifiers":[
        {
            "category":"Personal",
            "subcategory":"Beauty Salon",
            "type":"Services"
        }
    ],
    "sg:phone":"+1 705 267 3232",
    "sg:postcode":"P4R 1M6",
    "sg:province":"ON",
    "sg:tags":[
        "school"
    ],
    "wof:name":"Esthetics By Lisa Chopp",
    "wof:placetype":"venue"
},
  "geometry": {"coordinates":[-81.3824768066,48.4691200256],"type":"Point"}
}