{
  "type": "Feature",
  "properties": {
    "addr:full":"Edmonton AB T5H 0L3",
    "addr:postcode":"t5h 0l3",
    "iso:country":"CA",
    "sg:city":"Edmonton",
    "sg:classifiers":[
        {
            "category":"Health Services",
            "subcategory":"Doctor",
            "type":"Services"
        }
    ],
    "sg:phone":"+1 780 420 1510",
    "sg:postcode":"T5H 0L3",
    "sg:province":"AB",
    "sg:tags":[
        "dentist"
    ],
    "wof:name":"Fialka-Eshenko, Christine DDS",
    "wof:placetype":"venue"
},
  "geometry": {"coordinates":[-113.50870500000001,53.548401],"type":"Point"}
}