{
  "type": "Feature",
  "properties": {
    "addr:full":"571 3E Rue Chibougamau QC G8P 1N8",
    "addr:housenumber":"571",
    "addr:postcode":"g8p 1n8",
    "addr:street":"3E Rue",
    "iso:country":"CA",
    "sg:address":"571 3E Rue",
    "sg:city":"Chibougamau",
    "sg:classifiers":[
        {
            "category":"Restaurant",
            "type":"Food & Drink"
        }
    ],
    "sg:phone":"+1 418 748 4818",
    "sg:postcode":"G8P 1N8",
    "sg:province":"QC",
    "wof:name":"Restaurant LA Chaumiere",
    "wof:placetype":"venue"
},
  "geometry": {"coordinates":[-74.365005,49.91378],"type":"Point"}
}