{
  "type": "Feature",
  "properties": {
    "addr:full":"22673 132 Ave Maple Ridge BC V4R 2R2",
    "addr:housenumber":"22673",
    "addr:postcode":"bc v4r 2r2",
    "addr:street":"132 Ave",
    "iso:country":"CA",
    "sg:address":"22673 132 Ave",
    "sg:city":"Maple Ridge",
    "sg:classifiers":[
        {
            "category":"Wholesale",
            "subcategory":"Plants",
            "type":"Manufacturing & Wholesale Goods"
        }
    ],
    "sg:phone":"+1 604 463 3408",
    "sg:postcode":"V4R 2R2",
    "sg:province":"BC",
    "sg:tags":[
        "nursery",
        "tree"
    ],
    "wof:name":"Alouette Nursery",
    "wof:placetype":"venue"
},
  "geometry": {"coordinates":[-122.592391968,49.2422485352],"type":"Point"}
}