{
  "type": "Feature",
  "properties": {
    "addr:full":"1238 5th Ave Prince George BC V2L 3L2",
    "addr:housenumber":"1238",
    "addr:postcode":"v2l 3l2",
    "addr:street":"5Th Ave",
    "iso:country":"CA",
    "sg:address":"1238 5th Ave",
    "sg:city":"Prince George",
    "sg:classifiers":[
        {
            "category":"Restaurant",
            "type":"Food & Drink"
        }
    ],
    "sg:phone":"+1 250 564 3005",
    "sg:postcode":"V2L 3L2",
    "sg:province":"BC",
    "sg:tags":[
        "greek",
        "product"
    ],
    "wof:name":"Meteora Taverna",
    "wof:placetype":"venue"
},
  "geometry": {"coordinates":[-122.74630000000001,53.915325],"type":"Point"}
}