{
  "type": "Feature",
  "properties": {
    "addr:full":"Toronto ON M5A 3S5",
    "addr:postcode":"m5a 3s5",
    "iso:country":"CA",
    "sg:city":"Toronto",
    "sg:classifiers":[
        {
            "category":"Manufacturing",
            "subcategory":"Printing",
            "type":"Manufacturing & Wholesale Goods"
        }
    ],
    "sg:phone":"+1 416 947 2154",
    "sg:postcode":"M5A 3S5",
    "sg:province":"ON",
    "sg:tags":[
        "newspaper",
        "internet"
    ],
    "wof:name":"Canadian Online Explorer Lp",
    "wof:placetype":"venue"
},
  "geometry": {"coordinates":[-79.367149,43.653652],"type":"Point"}
}