{
  "type": "Feature",
  "properties": {
    "iso:country":"CA",
    "sg:address":"48 Av Begin",
    "sg:city":"Levis",
    "sg:classifiers":[
        {
            "category":"Shopping",
            "subcategory":"Florist",
            "type":"Retail Goods"
        }
    ],
    "sg:phone":"+1 418 837 2404",
    "sg:postcode":"G6V 4C2",
    "sg:province":"QC",
    "wof:name":"Mc Neil Fleuriste Inc",
    "wof:placetype":"venue"
},
  "geometry": {"coordinates":[-71.181282,46.808121],"type":"Point"}
}