{
  "type": "Feature",
  "properties": {
    "addr:full":"20570 56 Ave Langley BC V3A 3Z1",
    "addr:housenumber":"20570",
    "addr:postcode":"v3a 3z1",
    "addr:street":"56 Ave",
    "iso:country":"CA",
    "sg:address":"20570 56 Ave",
    "sg:city":"Langley",
    "sg:classifiers":[
        {
            "category":"Professional",
            "subcategory":"Lawyer & Legal Services",
            "type":"Services"
        }
    ],
    "sg:phone":"+1 604 530 2191",
    "sg:postcode":"V3A 3Z1",
    "sg:province":"BC",
    "sg:tags":[
        "attorney"
    ],
    "wof:name":"Minten, Peter V",
    "wof:placetype":"venue"
},
  "geometry": {"coordinates":[-122.652748108,49.1046562195],"type":"Point"}
}