{
  "type": "Feature",
  "properties": {
    "iso:country":"CA",
    "sg:address":"568 Rue Saint-Paul",
    "sg:city":"Trois-Rivieres",
    "sg:classifiers":[
        {
            "category":"Organizations",
            "subcategory":"Religious Organization",
            "type":"Services"
        }
    ],
    "sg:phone":"+1 819 376 2581",
    "sg:postcode":"G9A 1H8",
    "sg:province":"QC",
    "sg:tags":[
        "church"
    ],
    "wof:name":"Ste-Cecile Eglise",
    "wof:placetype":"venue"
},
  "geometry": {"coordinates":[-72.538658,46.348869],"type":"Point"}
}