{
  "type": "Feature",
  "properties": {
    "addr:full":"6510 39 Ave Ponoka AB T4J 1J8",
    "addr:housenumber":"6510",
    "addr:postcode":"t4j 1j8",
    "addr:street":"39 Ave",
    "iso:country":"CA",
    "sg:address":"6510 39 Ave",
    "sg:city":"Ponoka",
    "sg:classifiers":[
        {
            "category":"Autos & Motor Vehicles",
            "subcategory":"Automobile Sales",
            "type":"Retail Goods"
        }
    ],
    "sg:phone":"+1 403 783 3366",
    "sg:postcode":"T4J 1J8",
    "sg:province":"AB",
    "sg:tags":[
        "car",
        "dealer"
    ],
    "wof:name":"Ponoka Chrysler Jeep",
    "wof:placetype":"venue"
},
  "geometry": {"coordinates":[-113.604004,52.667931],"type":"Point"}
}