{
  "type": "Feature",
  "properties": {
    "addr:full":"3310 Victoria Ave # C Brandon MB R7B 0N2",
    "addr:housenumber":"3310",
    "addr:postcode":"r7b 0n2",
    "addr:street":"Victoria Ave # C",
    "iso:country":"CA",
    "sg:address":"3310 Victoria Ave # C",
    "sg:city":"Brandon",
    "sg:classifiers":[
        {
            "category":"Personal",
            "subcategory":"Beauty Salon",
            "type":"Services"
        }
    ],
    "sg:phone":"+1 204 727 7773",
    "sg:postcode":"R7B 0N2",
    "sg:province":"MB",
    "wof:name":"Hair Haven",
    "wof:placetype":"venue"
},
  "geometry": {"coordinates":[-99.9830627441,49.8420562744],"type":"Point"}
}