{
  "type": "Feature",
  "properties": {
    "iso:country":"CA",
    "sg:city":"Burnaby",
    "sg:classifiers":[
        {
            "category":"Food & Beverages",
            "subcategory":"Specialty",
            "type":"Retail Goods"
        }
    ],
    "sg:phone":"+1 604 451 0030",
    "sg:postcode":"V5H 4M1",
    "sg:province":"BC",
    "sg:tags":[
        "health",
        "diet"
    ],
    "wof:name":"Vitamin Store",
    "wof:placetype":"venue"
},
  "geometry": {"coordinates":[-122.999435,49.228325],"type":"Point"}
}