{
  "type": "Feature",
  "properties": {
    "addr:full":"971 Boul Des Ruisseaux Mont-Laurier QC J9L 3G6",
    "addr:housenumber":"971",
    "addr:postcode":"j9l 3g6",
    "addr:street":"Boul Des Ruisseaux",
    "iso:country":"CA",
    "sg:address":"971 Boul Des Ruisseaux",
    "sg:city":"Mont-Laurier",
    "sg:classifiers":[
        {
            "category":"Manufacturing",
            "subcategory":"Food",
            "type":"Manufacturing & Wholesale Goods"
        }
    ],
    "sg:phone":"+1 819 623 1286",
    "sg:postcode":"J9L 3G6",
    "sg:province":"QC",
    "sg:tags":[
        "establishment",
        "product",
        "chips",
        "manufacturer"
    ],
    "wof:name":"Falardeau Distribution Inc",
    "wof:placetype":"venue"
},
  "geometry": {"coordinates":[-75.55950164790001,46.5629272461],"type":"Point"}
}