{
  "type": "Feature",
  "properties": {
    "iso:country":"CA",
    "sg:address":"8330 Kennedy Rd",
    "sg:city":"Markham",
    "sg:classifiers":[
        {
            "category":"Local Transit",
            "type":"Transportation"
        }
    ],
    "sg:phone":"+1 905 477 4444",
    "sg:postcode":"L3R 0P5",
    "sg:province":"ON",
    "sg:tags":[
        "limousine"
    ],
    "wof:name":"First Choice Limousine",
    "wof:placetype":"venue"
},
  "geometry": {"coordinates":[-79.3042602539,43.8573379517],"type":"Point"}
}