{
  "type": "Feature",
  "properties": {
    "iso:country":"CA",
    "sg:address":"978 Boul L'Assomption",
    "sg:city":"Repentigny",
    "sg:classifiers":[
        {
            "category":"Building & Trades",
            "subcategory":"Construction",
            "type":"Services"
        }
    ],
    "sg:phone":"+1 450 582 4848",
    "sg:postcode":"J6A 5H5",
    "sg:province":"QC",
    "sg:tags":[
        "roofing",
        "contractor"
    ],
    "wof:name":"Toitures Rive-Nord Inc",
    "wof:placetype":"venue"
},
  "geometry": {"coordinates":[-73.444061,45.75544],"type":"Point"}
}