{
  "type": "Feature",
  "properties": {
    "addr:full":"14807 Marine Dr White Rock BC V4B 1C1",
    "addr:housenumber":"14807",
    "addr:postcode":"v4b 1c1",
    "addr:street":"Marine Dr",
    "iso:country":"CA",
    "sg:address":"14807 Marine Dr",
    "sg:city":"White Rock",
    "sg:classifiers":[
        {
            "category":"Retail",
            "subcategory":"Auto Repair",
            "type":"Services"
        }
    ],
    "sg:phone":"+1 604 531 9022",
    "sg:postcode":"V4B 1C1",
    "sg:province":"BC",
    "sg:tags":[
        "muffler",
        "exhaust",
        "system"
    ],
    "wof:name":"White Rock Mufflers",
    "wof:placetype":"venue"
},
  "geometry": {"coordinates":[-122.81186700000001,49.023312],"type":"Point"}
}