{
  "type": "Feature",
  "properties": {
    "addr:full":"865 Rue Hodge Saint-Laurent QC H4N 2B1",
    "addr:housenumber":"865",
    "addr:postcode":"h4n 2b1",
    "addr:street":"Rue Hodge",
    "iso:country":"CA",
    "sg:address":"865 Rue Hodge",
    "sg:city":"Saint-Laurent",
    "sg:classifiers":[
        {
            "category":"Wholesale",
            "subcategory":"Machinery & Supplies",
            "type":"Manufacturing & Wholesale Goods"
        }
    ],
    "sg:phone":"+1 514 747 7771",
    "sg:postcode":"H4N 2B1",
    "sg:province":"QC",
    "sg:tags":[
        "machine",
        "cleaners",
        "pressing",
        "dyer",
        "equipment"
    ],
    "wof:name":"Metromec Equipment Inc",
    "wof:placetype":"venue"
},
  "geometry": {"coordinates":[-73.6640167236,45.5154418945],"type":"Point"}
}