{
  "type": "Feature",
  "properties": {
    "addr:full":"Pointe-Claire QC H9R 5J2",
    "addr:postcode":"h9r 5j2",
    "iso:country":"CA",
    "sg:city":"Pointe-Claire",
    "sg:classifiers":[
        {
            "category":"Shopping",
            "subcategory":"Shoes",
            "type":"Retail Goods"
        }
    ],
    "sg:phone":"+1 514 697 5448",
    "sg:postcode":"H9R 5J2",
    "sg:province":"QC",
    "wof:name":"Super Monde Des Athletes",
    "wof:placetype":"venue"
},
  "geometry": {"coordinates":[-73.838218689,45.4578323364],"type":"Point"}
}