{
  "type": "Feature",
  "properties": {
    "addr:full":"2315 Rue Mcgill Longueuil QC J4J 3M3",
    "addr:housenumber":"2315",
    "addr:postcode":"j4j 3m3",
    "addr:street":"Rue Mcgill",
    "iso:country":"CA",
    "sg:address":"2315 Rue Mcgill",
    "sg:city":"Longueuil",
    "sg:classifiers":[
        {
            "category":"Real Estate",
            "subcategory":"Real Estate Agent",
            "type":"Services"
        }
    ],
    "sg:phone":"+1 450 677 1414",
    "sg:postcode":"J4J 3M3",
    "sg:province":"QC",
    "sg:tags":[
        "appraiser"
    ],
    "wof:name":"Evaluation Florent & Assoc",
    "wof:placetype":"venue"
},
  "geometry": {"coordinates":[-73.47595200000001,45.522942],"type":"Point"}
}