{
  "type": "Feature",
  "properties": {
    "addr:full":"53 Main St Elgin ON K0G 1E0",
    "addr:housenumber":"53",
    "addr:postcode":"k0g 1e0",
    "addr:street":"Main St",
    "iso:country":"CA",
    "sg:address":"53 Main St",
    "sg:city":"Elgin",
    "sg:classifiers":[
        {
            "category":"Home & Garden",
            "subcategory":"Household Appliances",
            "type":"Retail Goods"
        }
    ],
    "sg:phone":"+1 613 359 5660",
    "sg:postcode":"K0G 1E0",
    "sg:province":"ON",
    "wof:name":"Duncan's Radio & Television",
    "wof:placetype":"venue"
},
  "geometry": {"coordinates":[-76.2194900513,44.6093254089],"type":"Point"}
}