{
  "type": "Feature",
  "properties": {
    "addr:full":"2626 E Dewdney Ave Regina SK S4N 5E3",
    "addr:housenumber":"2626",
    "addr:postcode":"s4n 5e3",
    "addr:street":"E Dewdney Ave",
    "iso:country":"CA",
    "sg:address":"2626 E Dewdney Ave",
    "sg:city":"Regina",
    "sg:classifiers":[
        {
            "category":"Recreation",
            "type":"Entertainment"
        }
    ],
    "sg:phone":"+1 306 777 7747",
    "sg:postcode":"S4N 5E3",
    "sg:province":"SK",
    "sg:tags":[
        "center",
        "hall",
        "auditorium"
    ],
    "wof:name":"Glencairn Neighbourhood Rec",
    "wof:placetype":"venue"
},
  "geometry": {"coordinates":[-104.54444100000001,50.455292],"type":"Point"}
}