{
  "type": "Feature",
  "properties": {
    "addr:full":"151 Dundas St E Belleville ON K8N 1C3",
    "addr:housenumber":"151",
    "addr:postcode":"k8n 1c3",
    "addr:street":"Dundas St E",
    "iso:country":"CA",
    "sg:address":"151 Dundas St E",
    "sg:city":"Belleville",
    "sg:classifiers":[
        {
            "category":"Recreation",
            "type":"Entertainment"
        }
    ],
    "sg:phone":"+1 613 969 1669",
    "sg:postcode":"K8N 1C3",
    "sg:province":"ON",
    "sg:tags":[
        "pool",
        "swimming"
    ],
    "wof:name":"Kinsmen Swimming Pool",
    "wof:placetype":"venue"
},
  "geometry": {"coordinates":[-77.373367,44.162189],"type":"Point"}
}