{
  "type": "Feature",
  "properties": {
    "iso:country":"CA",
    "sg:address":"3058 Hurontario St",
    "sg:city":"Mississauga",
    "sg:classifiers":[
        {
            "category":"Health Services",
            "subcategory":"Doctor",
            "type":"Services"
        }
    ],
    "sg:phone":"+1 905 848 6212",
    "sg:postcode":"L5B 1N7",
    "sg:province":"ON",
    "sg:tags":[
        "dentist"
    ],
    "wof:name":"Kannan Dental Ctr",
    "wof:placetype":"venue"
},
  "geometry": {"coordinates":[-79.6184005737,43.5815582275],"type":"Point"}
}