{
  "type": "Feature",
  "properties": {
    "addr:full":"8210 Victoria St Metcalfe ON K0A 2P0",
    "addr:housenumber":"8210",
    "addr:postcode":"k0a 2p0",
    "addr:street":"Victoria St",
    "iso:country":"CA",
    "sg:address":"8210 Victoria St",
    "sg:city":"Metcalfe",
    "sg:classifiers":[
        {
            "category":"Restaurant",
            "type":"Food & Drink"
        }
    ],
    "sg:phone":"+1 613 821 5557",
    "sg:postcode":"K0A 2P0",
    "sg:province":"ON",
    "wof:name":"Main Bar & Grill",
    "wof:placetype":"venue"
},
  "geometry": {"coordinates":[-75.4733886719,45.2354316711],"type":"Point"}
}