{
  "type": "Feature",
  "properties": {
    "addr:full":"4040 Brandon St SE Calgary AB T2G 4A8",
    "addr:housenumber":"4040",
    "addr:postcode":"t2g 4a8",
    "addr:street":"Brandon St Se",
    "iso:country":"CA",
    "sg:address":"4040 Brandon St SE",
    "sg:city":"Calgary",
    "sg:classifiers":[
        {
            "category":"Wholesale",
            "subcategory":"Motor Vehicles",
            "type":"Manufacturing & Wholesale Goods"
        }
    ],
    "sg:phone":"+1 403 287 3730",
    "sg:postcode":"T2G 4A8",
    "sg:province":"AB",
    "sg:tags":[
        "body",
        "equipment",
        "truck"
    ],
    "wof:name":"Raytel Equipment Ltd",
    "wof:placetype":"venue"
},
  "geometry": {"coordinates":[-114.054344,51.01786],"type":"Point"}
}