{
  "type": "Feature",
  "properties": {
    "iso:country":"CA",
    "sg:address":"807 Av Du Mont-Royal E",
    "sg:city":"Montreal",
    "sg:classifiers":[
        {
            "category":"Shopping",
            "subcategory":"Clothing, Apparel, & Fashions",
            "type":"Retail Goods"
        }
    ],
    "sg:phone":"+1 514 521 1631",
    "sg:postcode":"H2J 1W9",
    "sg:province":"QC",
    "sg:tags":[
        "hosiery"
    ],
    "wof:name":"Au Coin Des Bas",
    "wof:placetype":"venue"
},
  "geometry": {"coordinates":[-73.58107757569999,45.5261268616],"type":"Point"}
}