{
  "type": "Feature",
  "properties": {
    "addr:full":"Railway Ave Edam SK S0M 0V0",
    "addr:postcode":"s0m 0v0",
    "addr:street":"Railway Ave",
    "iso:country":"CA",
    "sg:address":"Railway Ave",
    "sg:city":"Edam",
    "sg:classifiers":[
        {
            "category":"Autos & Motor Vehicles",
            "subcategory":"Auto Supplies",
            "type":"Retail Goods"
        }
    ],
    "sg:phone":"+1 306 397 2321",
    "sg:postcode":"S0M 0V0",
    "sg:province":"SK",
    "sg:tags":[
        "automobile",
        "parts"
    ],
    "wof:name":"Levasseur Sales & Svc Ltd",
    "wof:placetype":"venue"
},
  "geometry": {"coordinates":[-108.767837524,53.1907157898],"type":"Point"}
}