{
  "type": "Feature",
  "properties": {
    "addr:full":"2215 41 St N Lethbridge AB T1H 5W3",
    "addr:housenumber":"2215",
    "addr:postcode":"t1h 5w3",
    "addr:street":"41 St N",
    "iso:country":"CA",
    "sg:address":"2215 41 St N",
    "sg:city":"Lethbridge",
    "sg:classifiers":[
        {
            "category":"Building & Trades",
            "subcategory":"Construction",
            "type":"Services"
        }
    ],
    "sg:phone":"+1 403 320 5647",
    "sg:postcode":"T1H 5W3",
    "sg:province":"AB",
    "sg:tags":[
        "excavating",
        "contractor",
        "general"
    ],
    "wof:name":"DE Graaf Excavating Ltd",
    "wof:placetype":"venue"
},
  "geometry": {"coordinates":[-112.780822754,49.7230110168],"type":"Point"}
}