{
  "type": "Feature",
  "properties": {
    "addr:full":"1810 Fir St Vancouver BC V6J 3B1",
    "addr:housenumber":"1810",
    "addr:postcode":"v6j 3b1",
    "addr:street":"Fir St",
    "iso:country":"CA",
    "sg:address":"1810 Fir St",
    "sg:city":"Vancouver",
    "sg:classifiers":[
        {
            "category":"Shopping",
            "subcategory":"Bicycles & Sporting Goods",
            "type":"Retail Goods"
        }
    ],
    "sg:phone":"+1 604 731 2420",
    "sg:postcode":"V6J 3B1",
    "sg:province":"BC",
    "wof:name":"Reckless the Bike Store Inc",
    "wof:placetype":"venue"
},
  "geometry": {"coordinates":[-123.140617371,49.2695426941],"type":"Point"}
}