{
  "type": "Feature",
  "properties": {
    "iso:country":"CA",
    "sg:address":"21 Hale Rd",
    "sg:city":"Brampton",
    "sg:classifiers":[
        {
            "category":"Retail",
            "subcategory":"Auto Repair",
            "type":"Services"
        }
    ],
    "sg:phone":"+1 905 459 4041",
    "sg:postcode":"L6W 3J9",
    "sg:province":"ON",
    "sg:tags":[
        "repairing",
        "automobile"
    ],
    "wof:name":"J M Automotive",
    "wof:placetype":"venue"
},
  "geometry": {"coordinates":[-79.7197113037,43.6847877502],"type":"Point"}
}