{
  "type": "Feature",
  "properties": {
    "iso:country":"CA",
    "sg:address":"1600 Gerrard St E",
    "sg:city":"Toronto",
    "sg:classifiers":[
        {
            "category":"Shopping",
            "subcategory":"Discount & Variety Stores",
            "type":"Retail Goods"
        }
    ],
    "sg:phone":"+1 416 406 2479",
    "sg:postcode":"M4L 2A5",
    "sg:province":"ON",
    "wof:name":"8 11 Variety Store",
    "wof:placetype":"venue"
},
  "geometry": {"coordinates":[-79.31967926030001,43.6729507446],"type":"Point"}
}