{
  "type": "Feature",
  "properties": {
    "iso:country":"CA",
    "sg:address":"75 Devon Rd",
    "sg:city":"Brampton",
    "sg:classifiers":[
        {
            "category":"Wholesale",
            "subcategory":"Hardware",
            "type":"Manufacturing & Wholesale Goods"
        }
    ],
    "sg:phone":"+1 905 458 0400",
    "sg:postcode":"L6T 5A4",
    "sg:province":"ON",
    "sg:tags":[
        "control",
        "collecting",
        "system",
        "air",
        "dust",
        "pollution"
    ],
    "wof:name":"Kraemer Tool & Mfg CO Ltd",
    "wof:placetype":"venue"
},
  "geometry": {"coordinates":[-79.6800613403,43.733833313],"type":"Point"}
}