{
  "type": "Feature",
  "properties": {
    "addr:full":"2160 Sussex Lane Prince George BC V2K 3K9",
    "addr:housenumber":"2160",
    "addr:postcode":"v2k 3k9",
    "addr:street":"Sussex Lane",
    "iso:country":"CA",
    "sg:address":"2160 Sussex Lane",
    "sg:city":"Prince George",
    "sg:classifiers":[
        {
            "category":"Communications",
            "subcategory":"Radio Station",
            "type":"Services"
        }
    ],
    "sg:phone":"+1 250 962 2331",
    "sg:postcode":"V2K 3K9",
    "sg:province":"BC",
    "sg:tags":[
        "company",
        "broadcasting"
    ],
    "wof:name":"Lprf Broadcast Maintenance",
    "wof:placetype":"venue"
},
  "geometry": {"coordinates":[-122.79067999999999,53.975121],"type":"Point"}
}