{
  "type": "Feature",
  "properties": {
    "iso:country":"CA",
    "sg:address":"157 Mitton St S",
    "sg:city":"Sarnia",
    "sg:classifiers":[
        {
            "category":"Restaurant",
            "type":"Food & Drink"
        }
    ],
    "sg:phone":"+1 519 332 0081",
    "sg:postcode":"N7T 3C5",
    "sg:province":"ON",
    "sg:tags":[
        "pizza"
    ],
    "wof:name":"Italia Pizzeria",
    "wof:placetype":"venue"
},
  "geometry": {"coordinates":[-82.398575,42.96875],"type":"Point"}
}