{
  "type": "Feature",
  "properties": {
    "addr:full":"11330 54 Ave NW Edmonton AB T6H 0V7",
    "addr:housenumber":"11330",
    "addr:postcode":"t6h 0v7",
    "addr:street":"54 Ave Nw",
    "iso:country":"CA",
    "sg:address":"11330 54 Ave NW",
    "sg:city":"Edmonton",
    "sg:classifiers":[
        {
            "category":"Social Services",
            "subcategory":"Child Care",
            "type":"Services"
        }
    ],
    "sg:phone":"+1 780 437 4308",
    "sg:postcode":"T6H 0V7",
    "sg:province":"AB",
    "wof:name":"Greenfield School Age Day Care",
    "wof:placetype":"venue"
},
  "geometry": {"coordinates":[-113.522308,53.490845],"type":"Point"}
}