{
  "type": "Feature",
  "properties": {
    "addr:full":"9613 96 Ave NW Edmonton AB T6C 2B3",
    "addr:housenumber":"9613",
    "addr:postcode":"t6c 2b3",
    "addr:street":"96 Ave Nw",
    "iso:country":"CA",
    "sg:address":"9613 96 Ave NW",
    "sg:city":"Edmonton",
    "sg:classifiers":[
        {
            "category":"Travel",
            "subcategory":"Hotels & Motels",
            "type":"Entertainment"
        }
    ],
    "sg:phone":"+1 780 465 0852",
    "sg:postcode":"T6C 2B3",
    "sg:province":"AB",
    "sg:tags":[
        "resort"
    ],
    "wof:name":"Edmonton Ski Club",
    "wof:placetype":"venue"
},
  "geometry": {"coordinates":[-113.475074768,53.5344734192],"type":"Point"}
}