{
  "type": "Feature",
  "properties": {
    "iso:country":"CA",
    "sg:address":"1672 Barrington St",
    "sg:city":"Halifax",
    "sg:classifiers":[
        {
            "category":"Real Estate",
            "subcategory":"Architect",
            "type":"Services"
        }
    ],
    "sg:phone":"+1 902 422 9599",
    "sg:postcode":"B3J 2A2",
    "sg:province":"NS",
    "wof:name":"Grunsky, G Michael",
    "wof:placetype":"venue"
},
  "geometry": {"coordinates":[-63.5739898682,44.6467285156],"type":"Point"}
}