{
  "type": "Feature",
  "properties": {
    "addr:full":"London ON N6J 4Y2",
    "addr:postcode":"n6j 4y2",
    "iso:country":"CA",
    "sg:city":"London",
    "sg:classifiers":[
        {
            "category":"Real Estate",
            "subcategory":"Real Estate Operator",
            "type":"Services"
        }
    ],
    "sg:phone":"+1 519 474 0567",
    "sg:postcode":"N6J 4Y2",
    "sg:province":"ON",
    "sg:tags":[
        "apartment"
    ],
    "wof:name":"William Mercer Wilson Ctr",
    "wof:placetype":"venue"
},
  "geometry": {"coordinates":[-81.2779083252,42.9561157227],"type":"Point"}
}