{
  "type": "Feature",
  "properties": {
    "addr:full":"501 3rd Ave St Brieux SK S0K 3V0",
    "addr:housenumber":"501",
    "addr:postcode":"s0k 3v0",
    "addr:street":"3Rd Ave St",
    "iso:country":"CA",
    "sg:address":"501 3rd Ave",
    "sg:city":"St Brieux",
    "sg:classifiers":[
        {
            "category":"Education",
            "subcategory":"School",
            "type":"Public Place"
        }
    ],
    "sg:phone":"+1 306 275 2133",
    "sg:postcode":"S0K 3V0",
    "sg:province":"SK",
    "wof:name":"St Brieux High School",
    "wof:placetype":"venue"
},
  "geometry": {"coordinates":[-104.88899231000001,52.6353607178],"type":"Point"}
}