{
  "type": "Feature",
  "properties": {
    "addr:full":"Maple Ridge BC V2X 9E7",
    "addr:postcode":"v2x 9e7",
    "iso:country":"CA",
    "sg:city":"Maple Ridge",
    "sg:classifiers":[
        {
            "category":"Wholesale",
            "subcategory":"Machinery & Supplies",
            "type":"Manufacturing & Wholesale Goods"
        }
    ],
    "sg:phone":"+1 604 465 4639",
    "sg:postcode":"V2X 9E7",
    "sg:province":"BC",
    "sg:tags":[
        "equipment",
        "marine"
    ],
    "wof:name":"Klein Maritime Group",
    "wof:placetype":"venue"
},
  "geometry": {"coordinates":[-122.66791499999999,49.21487],"type":"Point"}
}