{
  "type": "Feature",
  "properties": {
    "addr:full":"Red Deer AB T4N 6V9",
    "addr:postcode":"t4n 6v9",
    "iso:country":"CA",
    "sg:city":"Red Deer",
    "sg:classifiers":[
        {
            "category":"Personal",
            "subcategory":"Beauty Salon",
            "type":"Services"
        }
    ],
    "sg:phone":"+1 403 341 3333",
    "sg:postcode":"T4N 6V9",
    "sg:province":"AB",
    "wof:name":"Off the Top Family Hair Shop",
    "wof:placetype":"venue"
},
  "geometry": {"coordinates":[-113.837257385,52.2819786072],"type":"Point"}
}