{
  "type": "Feature",
  "properties": {
    "addr:full":"371 Rue St-Laurent Saint-Simeon QC G0T 1X0",
    "addr:housenumber":"371",
    "addr:postcode":"g0t 1x0",
    "addr:street":"Rue St-Laurent",
    "iso:country":"CA",
    "sg:address":"371 Rue St-Laurent",
    "sg:city":"Saint-Simeon",
    "sg:classifiers":[
        {
            "category":"Health Services",
            "subcategory":"Hospital",
            "type":"Services"
        }
    ],
    "sg:phone":"+1 418 638 2414",
    "sg:postcode":"G0T 1X0",
    "sg:province":"QC",
    "sg:tags":[
        "home",
        "rest"
    ],
    "wof:name":"Foyer Notre-Dame-Du-Sacre-Coeu",
    "wof:placetype":"venue"
},
  "geometry": {"coordinates":[-69.87944793699999,47.8426132202],"type":"Point"}
}