{
  "type": "Feature",
  "properties": {
    "addr:full":"47 Walden Cres St Albert AB T8N 3N5",
    "addr:housenumber":"47",
    "addr:postcode":"t8n 3n5",
    "addr:street":"Walden Cres",
    "iso:country":"CA",
    "sg:address":"47 Walden Cres",
    "sg:city":"St Albert",
    "sg:classifiers":[
        {
            "category":"Professional",
            "subcategory":"Business Services",
            "type":"Services"
        }
    ],
    "sg:phone":"+1 780 460 9774",
    "sg:postcode":"T8N 3N5",
    "sg:province":"AB",
    "sg:tags":[
        "lecture",
        "bureau",
        "seminar"
    ],
    "wof:name":"Barbara May Productions",
    "wof:placetype":"venue"
},
  "geometry": {"coordinates":[-113.59639,53.650265],"type":"Point"}
}