{
  "type": "Feature",
  "properties": {
    "iso:country":"CA",
    "sg:address":"3590 Mountain Hwy",
    "sg:city":"North Vancouver",
    "sg:classifiers":[
        {
            "category":"Social Services",
            "subcategory":"Child Care",
            "type":"Services"
        }
    ],
    "sg:phone":"+1 604 987 7529",
    "sg:postcode":"V7K 2H5",
    "sg:province":"BC",
    "wof:name":"Sandpiper Pre School",
    "wof:placetype":"venue"
},
  "geometry": {"coordinates":[-123.037827,49.341438],"type":"Point"}
}