{
  "type": "Feature",
  "properties": {
    "iso:country":"CA",
    "sg:address":"3443 Drummond Rd",
    "sg:city":"Mississauga",
    "sg:classifiers":[
        {
            "category":"Education",
            "subcategory":"Library",
            "type":"Public Place"
        }
    ],
    "sg:phone":"+1 905 828 8522",
    "sg:postcode":"L5L 4H3",
    "sg:province":"ON",
    "sg:tags":[
        "research"
    ],
    "wof:name":"Cdn Research Assoc",
    "wof:placetype":"venue"
},
  "geometry": {"coordinates":[-79.7128372192,43.5283851624],"type":"Point"}
}