{
  "type": "Feature",
  "properties": {
    "addr:full":"1412 Sandhill Dr Ancaster ON L9G 4V5",
    "addr:housenumber":"1412",
    "addr:postcode":"l9g 4v5",
    "addr:street":"Sandhill Dr",
    "iso:country":"CA",
    "sg:address":"1412 Sandhill Dr",
    "sg:city":"Ancaster",
    "sg:classifiers":[
        {
            "category":"Education",
            "subcategory":"School",
            "type":"Public Place"
        }
    ],
    "sg:phone":"+1 905 648 6555",
    "sg:postcode":"L9G 4V5",
    "sg:province":"ON",
    "wof:name":"Dancesations",
    "wof:placetype":"venue"
},
  "geometry": {"coordinates":[-80.0317153931,43.1903800964],"type":"Point"}
}