{
  "type": "Feature",
  "properties": {
    "addr:full":"85 Kingston Rd E Ajax ON L1S 7J4",
    "addr:housenumber":"85",
    "addr:postcode":"l1s 7j4",
    "addr:street":"Kingston Rd E",
    "iso:country":"CA",
    "sg:address":"85 Kingston Rd E",
    "sg:city":"Ajax",
    "sg:classifiers":[
        {
            "category":"Shopping",
            "subcategory":"Clothing, Apparel, & Fashions",
            "type":"Retail Goods"
        }
    ],
    "sg:phone":"+1 905 683 2598",
    "sg:postcode":"L1S 7J4",
    "sg:province":"ON",
    "sg:tags":[
        "tuxedo",
        "wear",
        "formal"
    ],
    "wof:name":"Tuxedo Junction",
    "wof:placetype":"venue"
},
  "geometry": {"coordinates":[-79.0212020874,43.8620491028],"type":"Point"}
}