{
  "type": "Feature",
  "properties": {
    "iso:country":"CA",
    "sg:address":"1980 Rue DE Flandre",
    "sg:city":"Saint-Hyacinthe",
    "sg:classifiers":[
        {
            "category":"Building & Trades",
            "subcategory":"Construction",
            "type":"Services"
        }
    ],
    "sg:phone":"+1 450 799 4559",
    "sg:postcode":"J2T 4N5",
    "sg:province":"QC",
    "sg:tags":[
        "repairing",
        "remodeling",
        "contractor"
    ],
    "wof:name":"Batiments Monteregiens Inc",
    "wof:placetype":"venue"
},
  "geometry": {"coordinates":[-72.93402862550001,45.6414985657],"type":"Point"}
}