{
  "type": "Feature",
  "properties": {
    "addr:full":"133 the West Mall Etobicoke ON M9C 1C2",
    "addr:housenumber":"133",
    "addr:postcode":"m9c 1c2",
    "addr:street":"The West Mall",
    "iso:country":"CA",
    "sg:address":"133 the West Mall",
    "sg:city":"Etobicoke",
    "sg:classifiers":[
        {
            "category":"Freight",
            "type":"Transportation"
        }
    ],
    "sg:phone":"+1 416 695 9558",
    "sg:postcode":"M9C 1C2",
    "sg:province":"ON",
    "sg:tags":[
        "warehouse",
        "storage"
    ],
    "wof:name":"Opoint Cold Storage",
    "wof:placetype":"venue"
},
  "geometry": {"coordinates":[-79.562363,43.619556],"type":"Point"}
}