{
  "type": "Feature",
  "properties": {
    "addr:full":"Taber AB T1G 2A4",
    "addr:postcode":"t1g 2a4",
    "iso:country":"CA",
    "sg:city":"Taber",
    "sg:classifiers":[
        {
            "category":"Autos & Motor Vehicles",
            "subcategory":"Automobile Sales",
            "type":"Retail Goods"
        }
    ],
    "sg:phone":"+1 403 223 3556",
    "sg:postcode":"T1G 2A4",
    "sg:province":"AB",
    "sg:tags":[
        "car",
        "dealer"
    ],
    "wof:name":"Ken Mc Donald Chev Olds Ltd",
    "wof:placetype":"venue"
},
  "geometry": {"coordinates":[-112.151344299,49.7817420959],"type":"Point"}
}