{
  "type": "Feature",
  "properties": {
    "addr:full":"1200 St Laurent Blvd Ottawa ON K1K 3B8",
    "addr:housenumber":"1200",
    "addr:postcode":"k1k 3b8",
    "addr:street":"St Laurent Blvd",
    "iso:country":"CA",
    "sg:address":"1200 St Laurent Blvd",
    "sg:city":"Ottawa",
    "sg:classifiers":[
        {
            "category":"Retail",
            "subcategory":"Photofinishing",
            "type":"Services"
        }
    ],
    "sg:phone":"+1 613 745 9710",
    "sg:postcode":"K1K 3B8",
    "sg:province":"ON",
    "sg:tags":[
        "photo",
        "photographic",
        "supply"
    ],
    "wof:name":"Black's Photography",
    "wof:placetype":"venue"
},
  "geometry": {"coordinates":[-75.63735198969999,45.4237518311],"type":"Point"}
}