{
  "type": "Feature",
  "properties": {
    "iso:country":"CA",
    "sg:address":"46 Brydon Dr",
    "sg:city":"Etobicoke",
    "sg:classifiers":[
        {
            "category":"Manufacturing",
            "subcategory":"Tools & Machinery",
            "type":"Manufacturing & Wholesale Goods"
        }
    ],
    "sg:phone":"+1 416 741 9615",
    "sg:postcode":"M9W 4N5",
    "sg:province":"ON",
    "sg:tags":[
        "machine",
        "shop",
        "supply",
        "automobile"
    ],
    "wof:name":"Rotem Industrial Products Inc",
    "wof:placetype":"venue"
},
  "geometry": {"coordinates":[-79.57270812989999,43.7172470093],"type":"Point"}
}