{
  "type": "Feature",
  "properties": {
    "addr:full":"220 Av Sainte-Brigitte Sainte-Brigitte-DE-Laval QC G0A 3K0",
    "addr:housenumber":"220",
    "addr:postcode":"g0a 3k0",
    "addr:street":"Av Sainte-Brigitte",
    "iso:country":"CA",
    "sg:address":"220 Av Sainte-Brigitte",
    "sg:city":"Sainte-Brigitte-DE-Laval",
    "sg:classifiers":[
        {
            "category":"Home & Garden",
            "subcategory":"Furniture",
            "type":"Retail Goods"
        }
    ],
    "sg:phone":"+1 418 825 3048",
    "sg:postcode":"G0A 3K0",
    "sg:province":"QC",
    "sg:tags":[
        "equipment",
        "kitchen",
        "cabinet"
    ],
    "wof:name":"Industries Amco Inc",
    "wof:placetype":"venue"
},
  "geometry": {"coordinates":[-71.20024100000001,46.979153],"type":"Point"}
}