{
  "type": "Feature",
  "properties": {
    "addr:full":"11 Lakeshore Rd W Oakville ON L6K 1C6",
    "addr:housenumber":"11",
    "addr:postcode":"l6k 1c6",
    "addr:street":"Lakeshore Rd W",
    "iso:country":"CA",
    "sg:address":"11 Lakeshore Rd W",
    "sg:city":"Oakville",
    "sg:classifiers":[
        {
            "category":"Personal",
            "type":"Services"
        }
    ],
    "sg:phone":"+1 905 844 1610",
    "sg:postcode":"L6K 1C6",
    "sg:province":"ON",
    "sg:tags":[
        "physiotherapist",
        "program",
        "physical",
        "exercise",
        "fitness"
    ],
    "wof:name":"Gym Nautilus Sports Medical",
    "wof:placetype":"venue"
},
  "geometry": {"coordinates":[-79.672417,43.442059],"type":"Point"}
}