{
  "type": "Feature",
  "properties": {
    "addr:full":"225 1 Ave S Lethbridge AB T1J 4P2",
    "addr:housenumber":"225",
    "addr:postcode":"t1j 4p2",
    "addr:street":"1 Ave S",
    "iso:country":"CA",
    "sg:address":"225 1 Ave S",
    "sg:city":"Lethbridge",
    "sg:classifiers":[
        {
            "category":"Shopping",
            "subcategory":"Hobbies, Toys, & Games",
            "type":"Retail Goods"
        }
    ],
    "sg:phone":"+1 403 329 4869",
    "sg:postcode":"T1J 4P2",
    "sg:province":"AB",
    "wof:name":"Toys R US Ltd",
    "wof:placetype":"venue"
},
  "geometry": {"coordinates":[-112.843887,49.697872],"type":"Point"}
}