{
  "type": "Feature",
  "properties": {
    "addr:full":"7800 Macleod Trail SE Calgary AB T2H 0L9",
    "addr:housenumber":"7800",
    "addr:postcode":"t2h 0l9",
    "addr:street":"Macleod Trail Se",
    "iso:country":"CA",
    "sg:address":"7800 Macleod Trail SE",
    "sg:city":"Calgary",
    "sg:classifiers":[
        {
            "category":"Building & Trades",
            "subcategory":"Plumbing",
            "type":"Services"
        }
    ],
    "sg:phone":"+1 403 271 5411",
    "sg:postcode":"T2H 0L9",
    "sg:province":"AB",
    "sg:tags":[
        "conditioning",
        "air",
        "system",
        "contractor"
    ],
    "wof:name":"NU-Air Mechanical Svc Ltd",
    "wof:placetype":"venue"
},
  "geometry": {"coordinates":[-114.070869,50.983685],"type":"Point"}
}