{
  "type": "Feature",
  "properties": {
    "addr:full":"926 Wedgewood Ave Sarnia ON N7V 3E7",
    "addr:housenumber":"926",
    "addr:postcode":"n7v 3e7",
    "addr:street":"Wedgewood Ave",
    "iso:country":"CA",
    "sg:address":"926 Wedgewood Ave",
    "sg:city":"Sarnia",
    "sg:classifiers":[
        {
            "category":"Professional",
            "subcategory":"Accounting & Tax Preparation",
            "type":"Services"
        }
    ],
    "sg:phone":"+1 519 339 8836",
    "sg:postcode":"N7V 3E7",
    "sg:province":"ON",
    "sg:tags":[
        "consultant"
    ],
    "wof:name":"D B Burnard & Assoc",
    "wof:placetype":"venue"
},
  "geometry": {"coordinates":[-82.3908081055,42.9891433716],"type":"Point"}
}