{
  "type": "Feature",
  "properties": {
    "addr:full":"3904 20 St SW Calgary AB T2T 4Z9",
    "addr:housenumber":"3904",
    "addr:postcode":"t2t 4z9",
    "addr:street":"20 St Sw",
    "iso:country":"CA",
    "sg:address":"3904 20 St SW",
    "sg:city":"Calgary",
    "sg:classifiers":[
        {
            "category":"Education",
            "subcategory":"School",
            "type":"Public Place"
        }
    ],
    "sg:phone":"+1 403 777 8300",
    "sg:postcode":"T2T 4Z9",
    "sg:province":"AB",
    "wof:name":"Dr Oakley School",
    "wof:placetype":"venue"
},
  "geometry": {"coordinates":[-114.10906199999999,51.019428],"type":"Point"}
}