{
  "type": "Feature",
  "properties": {
    "addr:full":"3277 Bloor St W Etobicoke ON M8X 1E2",
    "addr:housenumber":"3277",
    "addr:postcode":"m8x 1e2",
    "addr:street":"Bloor St W",
    "iso:country":"CA",
    "sg:address":"3277 Bloor St W",
    "sg:city":"Etobicoke",
    "sg:classifiers":[
        {
            "category":"Restaurant",
            "type":"Food & Drink"
        }
    ],
    "sg:phone":"+1 416 233 7406",
    "sg:postcode":"M8X 1E2",
    "sg:province":"ON",
    "wof:name":"Black Angus Steak House",
    "wof:placetype":"venue"
},
  "geometry": {"coordinates":[-79.518699646,43.6456031799],"type":"Point"}
}