{
  "type": "Feature",
  "properties": {
    "addr:full":"28 Arlington Ave Ottawa ON K2P 1C2",
    "addr:housenumber":"28",
    "addr:postcode":"k2p 1c2",
    "addr:street":"Arlington Ave",
    "iso:country":"CA",
    "sg:address":"28 Arlington Ave",
    "sg:city":"Ottawa",
    "sg:classifiers":[
        {
            "category":"Education",
            "subcategory":"School",
            "type":"Public Place"
        }
    ],
    "sg:phone":"+1 613 239 2264",
    "sg:postcode":"K2P 1C2",
    "sg:province":"ON",
    "wof:name":"Glashan Public School",
    "wof:placetype":"venue"
},
  "geometry": {"coordinates":[-75.69338226319999,45.4096603394],"type":"Point"}
}