{
  "type": "Feature",
  "properties": {
    "addr:full":"2430 Bank St Ottawa ON K1V 0T7",
    "addr:housenumber":"2430",
    "addr:postcode":"k1v 0t7",
    "addr:street":"Bank St",
    "iso:country":"CA",
    "sg:address":"2430 Bank St",
    "sg:city":"Ottawa",
    "sg:classifiers":[
        {
            "category":"Food & Beverages",
            "subcategory":"Groceries & Convenience Stores",
            "type":"Retail Goods"
        }
    ],
    "sg:phone":"+1 613 738 2438",
    "sg:postcode":"K1V 0T7",
    "sg:province":"ON",
    "wof:name":"Quickie Convenience Stores",
    "wof:placetype":"venue"
},
  "geometry": {"coordinates":[-75.64877300000001,45.35387],"type":"Point"}
}