{
  "type": "Feature",
  "properties": {
    "addr:full":"Saskatoon SK S7K 1P1",
    "addr:postcode":"s7k 1p1",
    "iso:country":"CA",
    "sg:city":"Saskatoon",
    "sg:classifiers":[
        {
            "category":"Manufacturing",
            "subcategory":"Printing",
            "type":"Manufacturing & Wholesale Goods"
        }
    ],
    "sg:phone":"+1 306 244 8973",
    "sg:postcode":"S7K 1P1",
    "sg:province":"SK",
    "sg:tags":[
        "printer"
    ],
    "wof:name":"Distinctive Imagesetting Inc",
    "wof:placetype":"venue"
},
  "geometry": {"coordinates":[-106.667198181,52.1325073242],"type":"Point"}
}