{
  "type": "Feature",
  "properties": {
    "addr:full":"Cambridge ON N1R 7S7",
    "addr:postcode":"n1r 7s7",
    "iso:country":"CA",
    "sg:city":"Cambridge",
    "sg:classifiers":[
        {
            "category":"Wholesale",
            "subcategory":"Electrical",
            "type":"Manufacturing & Wholesale Goods"
        }
    ],
    "sg:phone":"+1 519 622 4070",
    "sg:postcode":"N1R 7S7",
    "sg:province":"ON",
    "sg:tags":[
        "control"
    ],
    "wof:name":"Systems Drives Controls Inc",
    "wof:placetype":"venue"
},
  "geometry": {"coordinates":[-80.31884002690001,43.403087616],"type":"Point"}
}