{
  "type": "Feature",
  "properties": {
    "addr:full":"Victoria BC V8T 4E8",
    "addr:postcode":"v8t 4e8",
    "iso:country":"CA",
    "sg:city":"Victoria",
    "sg:classifiers":[
        {
            "category":"Professional",
            "subcategory":"Engineering",
            "type":"Services"
        }
    ],
    "sg:phone":"+1 250 388 6919",
    "sg:postcode":"V8T 4E8",
    "sg:province":"BC",
    "sg:tags":[
        "engineer"
    ],
    "wof:name":"Gary Carrothers Consulting",
    "wof:placetype":"venue"
},
  "geometry": {"coordinates":[-123.359673,48.440586],"type":"Point"}
}