{
  "type": "Feature",
  "properties": {
    "addr:full":"4001 Knight St Vancouver BC V5N 3L9",
    "addr:housenumber":"4001",
    "addr:postcode":"v5n 3l9",
    "addr:street":"Knight St",
    "iso:country":"CA",
    "sg:address":"4001 Knight St",
    "sg:city":"Vancouver",
    "sg:classifiers":[
        {
            "category":"Retail",
            "subcategory":"Laundry & Dry Cleaning",
            "type":"Services"
        }
    ],
    "sg:phone":"+1 604 876 7412",
    "sg:postcode":"V5N 3L9",
    "sg:province":"BC",
    "sg:tags":[
        "cleaners"
    ],
    "wof:name":"Checkmate Dry Cleaning",
    "wof:placetype":"venue"
},
  "geometry": {"coordinates":[-123.07620199999999,49.249016],"type":"Point"}
}