{
  "type": "Feature",
  "properties": {
    "addr:full":"18 Rockford Rd North York ON M2R 3V9",
    "addr:housenumber":"18",
    "addr:postcode":"m2r 3v9",
    "addr:street":"Rockford Rd",
    "iso:country":"CA",
    "sg:address":"18 Rockford Rd",
    "sg:city":"North York",
    "sg:classifiers":[
        {
            "category":"Organizations",
            "subcategory":"Religious Organization",
            "type":"Services"
        }
    ],
    "sg:phone":"+1 416 222 7105",
    "sg:postcode":"M2R 3V9",
    "sg:province":"ON",
    "sg:tags":[
        "synagogue"
    ],
    "wof:name":"Jewish Russian Community Ctr",
    "wof:placetype":"venue"
},
  "geometry": {"coordinates":[-79.448318,43.785622],"type":"Point"}
}