{
  "type": "Feature",
  "properties": {
    "addr:full":"12 Heritage Rd Markham ON L3P 1M4",
    "addr:housenumber":"12",
    "addr:postcode":"l3p 1m4",
    "addr:street":"Heritage Rd",
    "iso:country":"CA",
    "sg:address":"12 Heritage Rd",
    "sg:city":"Markham",
    "sg:classifiers":[
        {
            "category":"Retail",
            "subcategory":"Auto Repair",
            "type":"Services"
        }
    ],
    "sg:phone":"+1 905 472 0748",
    "sg:postcode":"L3P 1M4",
    "sg:province":"ON",
    "sg:tags":[
        "repairing",
        "automobile"
    ],
    "wof:name":"Bubby Automotive",
    "wof:placetype":"venue"
},
  "geometry": {"coordinates":[-79.279411,43.871357],"type":"Point"}
}