{
  "type": "Feature",
  "properties": {
    "addr:full":"86 John St Brockville ON K6V 5B2",
    "addr:housenumber":"86",
    "addr:postcode":"k6v 5b2",
    "addr:street":"John St",
    "iso:country":"CA",
    "sg:address":"86 John St",
    "sg:city":"Brockville",
    "sg:classifiers":[
        {
            "category":"Shopping",
            "subcategory":"Clothing, Apparel, & Fashions",
            "type":"Retail Goods"
        }
    ],
    "sg:phone":"+1 613 342 4603",
    "sg:postcode":"K6V 5B2",
    "sg:province":"ON",
    "sg:tags":[
        "fur",
        "business"
    ],
    "wof:name":"Edward Reilly & CO",
    "wof:placetype":"venue"
},
  "geometry": {"coordinates":[-75.690361,44.589485],"type":"Point"}
}