{
  "type": "Feature",
  "properties": {
    "iso:country":"CA",
    "sg:city":"Vancouver",
    "sg:classifiers":[
        {
            "category":"Banks & Credit Unions",
            "subcategory":"Investment Brokerage",
            "type":"Services"
        }
    ],
    "sg:phone":"+1 604 876 2529",
    "sg:postcode":"V5Z 4J7",
    "sg:province":"BC",
    "wof:name":"Invis Financial Group",
    "wof:placetype":"venue"
},
  "geometry": {"coordinates":[-123.121292114,49.263469696],"type":"Point"}
}