{
  "type": "Feature",
  "properties": {
    "addr:full":"3759 Boul Levesque O Laval QC H7V 1G4",
    "addr:housenumber":"3759",
    "addr:postcode":"h7v 1g4",
    "addr:street":"Boul Levesque O",
    "iso:country":"CA",
    "sg:address":"3759 Boul Levesque O",
    "sg:city":"Laval",
    "sg:classifiers":[
        {
            "category":"Manufacturing",
            "subcategory":"Jewelry",
            "type":"Manufacturing & Wholesale Goods"
        }
    ],
    "sg:phone":"+1 450 681 4902",
    "sg:postcode":"H7V 1G4",
    "sg:province":"QC",
    "sg:tags":[
        "diamond",
        "cutting",
        "jeweler"
    ],
    "wof:name":"Andre & Jean Marchand Joailli",
    "wof:placetype":"venue"
},
  "geometry": {"coordinates":[-73.73767100000001,45.535053],"type":"Point"}
}