{
  "type": "Feature",
  "properties": {
    "addr:full":"5 Rue Mercier Dollard-Des-Ormeaux QC H9A 1H4",
    "addr:housenumber":"5",
    "addr:postcode":"h9a 1h4",
    "addr:street":"Rue Mercier",
    "iso:country":"CA",
    "sg:address":"5 Rue Mercier",
    "sg:city":"Dollard-Des-Ormeaux",
    "sg:classifiers":[
        {
            "category":"Restaurant",
            "type":"Food & Drink"
        }
    ],
    "sg:phone":"+1 514 685 2171",
    "sg:postcode":"H9A 1H4",
    "sg:province":"QC",
    "sg:tags":[
        "caterer"
    ],
    "wof:name":"Moulin Bleu 2000",
    "wof:placetype":"venue"
},
  "geometry": {"coordinates":[-73.823143,45.503677],"type":"Point"}
}