{
  "type": "Feature",
  "properties": {
    "addr:full":"765 Boul Saint-Luc Saint-Luc QC J2W 2G6",
    "addr:housenumber":"765",
    "addr:postcode":"j2w 2g6",
    "addr:street":"Boul Saint-Luc",
    "iso:country":"CA",
    "sg:address":"765 Boul Saint-Luc",
    "sg:city":"Saint-Luc",
    "sg:classifiers":[
        {
            "category":"Building & Trades",
            "subcategory":"Cleaning & Sanitation",
            "type":"Services"
        }
    ],
    "sg:phone":"+1 450 349 2551",
    "sg:postcode":"J2W 2G6",
    "sg:province":"QC",
    "sg:tags":[
        "snow",
        "removal"
    ],
    "wof:name":"Deneigement Alix & Freres",
    "wof:placetype":"venue"
},
  "geometry": {"coordinates":[-73.32865905760001,45.3668746948],"type":"Point"}
}