{
  "type": "Feature",
  "properties": {
    "iso:country":"CA",
    "sg:address":"2536 Harper-Ranch Rd",
    "sg:city":"Pinantan Lake",
    "sg:classifiers":[
        {
            "category":"Food & Beverages",
            "subcategory":"Groceries & Convenience Stores",
            "type":"Retail Goods"
        }
    ],
    "sg:phone":"+1 250 573 4446",
    "sg:postcode":"V0E 3E1",
    "sg:province":"BC",
    "sg:tags":[
        "grocer"
    ],
    "wof:name":"Pinantan General Store",
    "wof:placetype":"venue"
},
  "geometry": {"coordinates":[-120.026390076,50.7319717407],"type":"Point"}
}