{
  "type": "Feature",
  "properties": {
    "addr:full":"363 David St Victoria BC V8T 5C1",
    "addr:housenumber":"363",
    "addr:postcode":"v8t 5c1",
    "addr:street":"David St",
    "iso:country":"CA",
    "sg:address":"363 David St",
    "sg:city":"Victoria",
    "sg:classifiers":[
        {
            "category":"Building & Trades",
            "subcategory":"Construction",
            "type":"Services"
        }
    ],
    "sg:phone":"+1 250 381 1989",
    "sg:postcode":"V8T 5C1",
    "sg:province":"BC",
    "sg:tags":[
        "painter"
    ],
    "wof:name":"Tri City Finishing",
    "wof:placetype":"venue"
},
  "geometry": {"coordinates":[-123.37541961700001,48.4374008179],"type":"Point"}
}