{
  "type": "Feature",
  "properties": {
    "iso:country":"CA",
    "sg:address":"64 Rue Bridge",
    "sg:city":"Ormstown",
    "sg:classifiers":[
        {
            "category":"Health Services",
            "subcategory":"Chiropractor",
            "type":"Services"
        }
    ],
    "sg:phone":"+1 450 829 2352",
    "sg:postcode":"J0S 1K0",
    "sg:province":"QC",
    "wof:name":"Brodeur, Gerard G DC",
    "wof:placetype":"venue"
},
  "geometry": {"coordinates":[-73.9935531616,45.1239738464],"type":"Point"}
}