{
  "type": "Feature",
  "properties": {
    "addr:full":"19 Alpaca Dr Scarborough ON M1J 2Z8",
    "addr:housenumber":"19",
    "addr:postcode":"m1j 2z8",
    "addr:street":"Alpaca Dr",
    "iso:country":"CA",
    "sg:address":"19 Alpaca Dr",
    "sg:city":"Scarborough",
    "sg:classifiers":[
        {
            "category":"Real Estate",
            "subcategory":"Real Estate Agent",
            "type":"Services"
        }
    ],
    "sg:phone":"+1 416 439 5155",
    "sg:postcode":"M1J 2Z8",
    "sg:province":"ON",
    "wof:name":"Family Realty Crocker Ltd",
    "wof:placetype":"venue"
},
  "geometry": {"coordinates":[-79.23027,43.750439],"type":"Point"}
}