{
  "type": "Feature",
  "properties": {
    "addr:full":"12009 Rue Notre-Dame E Pointe-Aux-Trembles QC H1B 2Y8",
    "addr:housenumber":"12009",
    "addr:postcode":"h1b 2y8",
    "addr:street":"Rue Notre-Dame E Pointe-Aux-Trembles",
    "iso:country":"CA",
    "sg:address":"12009 Rue Notre-Dame E",
    "sg:city":"Pointe-Aux-Trembles",
    "sg:classifiers":[
        {
            "category":"Shopping",
            "subcategory":"Bicycles & Sporting Goods",
            "type":"Retail Goods"
        }
    ],
    "sg:phone":"+1 514 645 5301",
    "sg:postcode":"H1B 2Y8",
    "sg:province":"QC",
    "wof:name":"Sports A Roy Inc",
    "wof:placetype":"venue"
},
  "geometry": {"coordinates":[-73.490517,45.639683],"type":"Point"}
}