{
  "type": "Feature",
  "properties": {
    "addr:full":"269 Highway 214 # 12 Elmsdale NS B2S 1K1",
    "addr:housenumber":"269",
    "addr:postcode":"b2s 1k1",
    "addr:street":"Highway 214 # 12",
    "iso:country":"CA",
    "sg:address":"269 Highway 214 # 12",
    "sg:city":"Elmsdale",
    "sg:classifiers":[
        {
            "category":"Retail",
            "subcategory":"Self-service Laundry",
            "type":"Services"
        }
    ],
    "sg:phone":"+1 902 883 7121",
    "sg:postcode":"B2S 1K1",
    "sg:province":"NS",
    "wof:name":"Just Like Home Laundromat",
    "wof:placetype":"venue"
},
  "geometry": {"coordinates":[-63.5046348572,44.9673805237],"type":"Point"}
}