{
  "type": "Feature",
  "properties": {
    "addr:full":"13245 Ilderton Rd Ilderton ON N0M 2A0",
    "addr:housenumber":"13245",
    "addr:postcode":"n0m 2a0",
    "addr:street":"Ilderton Rd",
    "iso:country":"CA",
    "sg:address":"13245 Ilderton Rd",
    "sg:city":"Ilderton",
    "sg:classifiers":[
        {
            "category":"Health Services",
            "subcategory":"Chiropractor",
            "type":"Services"
        }
    ],
    "sg:phone":"+1 519 666 3993",
    "sg:postcode":"N0M 2A0",
    "sg:province":"ON",
    "wof:name":"Active Chiropractic",
    "wof:placetype":"venue"
},
  "geometry": {"coordinates":[-81.3819351196,43.0790290833],"type":"Point"}
}