{
  "type": "Feature",
  "properties": {
    "addr:full":"11 Rue Saint-Edouard Levis QC G6V 6E5",
    "addr:housenumber":"11",
    "addr:postcode":"g6v 6e5",
    "addr:street":"Rue Saint-Edouard",
    "iso:country":"CA",
    "sg:address":"11 Rue Saint-Edouard",
    "sg:city":"Levis",
    "sg:classifiers":[
        {
            "category":"Organizations",
            "subcategory":"Professional Association",
            "type":"Services"
        }
    ],
    "sg:phone":"+1 418 789 3417",
    "sg:postcode":"G6V 6E5",
    "sg:province":"QC",
    "wof:name":"Adds Rive-Sud Inc",
    "wof:placetype":"venue"
},
  "geometry": {"coordinates":[-71.186874,46.799732],"type":"Point"}
}