{
  "type": "Feature",
  "properties": {
    "addr:full":"150 Cumberland St Toronto ON M5R 1A8",
    "addr:housenumber":"150",
    "addr:postcode":"m5r 1a8",
    "addr:street":"Cumberland St",
    "iso:country":"CA",
    "sg:address":"150 Cumberland St",
    "sg:city":"Toronto",
    "sg:classifiers":[
        {
            "category":"Retail",
            "subcategory":"Auto Rental",
            "type":"Services"
        }
    ],
    "sg:phone":"+1 416 927 8300",
    "sg:postcode":"M5R 1A8",
    "sg:province":"ON",
    "sg:tags":[
        "renting",
        "automobile"
    ],
    "wof:name":"Budget Car & Truck Rental",
    "wof:placetype":"venue"
},
  "geometry": {"coordinates":[-79.3928146362,43.6700782776],"type":"Point"}
}