{
  "type": "Feature",
  "properties": {
    "addr:full":"754 Brighton Ave Hamilton ON L8H 6H7",
    "addr:housenumber":"754",
    "addr:postcode":"l8h 6h7",
    "addr:street":"Brighton Ave",
    "iso:country":"CA",
    "sg:address":"754 Brighton Ave",
    "sg:city":"Hamilton",
    "sg:classifiers":[
        {
            "category":"Manufacturing",
            "subcategory":"Signs",
            "type":"Manufacturing & Wholesale Goods"
        }
    ],
    "sg:phone":"+1 905 312 9641",
    "sg:postcode":"L8H 6H7",
    "sg:province":"ON",
    "wof:name":"Ultra Graphic Detail",
    "wof:placetype":"venue"
},
  "geometry": {"coordinates":[-79.779976,43.255962],"type":"Point"}
}