{
  "type": "Feature",
  "properties": {
    "addr:full":"520 Centre St Assiniboia SK S0H 0B0",
    "addr:housenumber":"520",
    "addr:postcode":"s0h 0b0",
    "addr:street":"Centre St",
    "iso:country":"CA",
    "sg:address":"520 Centre St",
    "sg:city":"Assiniboia",
    "sg:classifiers":[
        {
            "category":"Health Services",
            "subcategory":"Optometrist",
            "type":"Services"
        }
    ],
    "sg:phone":"+1 306 642 4632",
    "sg:postcode":"S0H 0B0",
    "sg:province":"SK",
    "wof:name":"Turriff, Richard OD",
    "wof:placetype":"venue"
},
  "geometry": {"coordinates":[-105.993088,49.629929],"type":"Point"}
}