{
  "type": "Feature",
  "properties": {
    "addr:full":"2861 Granville St Vancouver BC V6H 3J4",
    "addr:housenumber":"2861",
    "addr:postcode":"v6h 3j4",
    "addr:street":"Granville St",
    "iso:country":"CA",
    "sg:address":"2861 Granville St",
    "sg:city":"Vancouver",
    "sg:classifiers":[
        {
            "category":"Restaurant",
            "type":"Food & Drink"
        }
    ],
    "sg:phone":"+1 604 488 1326",
    "sg:postcode":"V6H 3J4",
    "sg:province":"BC",
    "wof:name":"Cafe Crepe",
    "wof:placetype":"venue"
},
  "geometry": {"coordinates":[-123.138900757,49.2602539062],"type":"Point"}
}