{
  "type": "Feature",
  "properties": {
    "addr:full":"42 Beaudoin St Cookshire QC J0B 1M0",
    "addr:housenumber":"42",
    "addr:postcode":"j0b 1m0",
    "addr:street":"Beaudoin St",
    "iso:country":"CA",
    "sg:address":"42 Beaudoin St",
    "sg:city":"Cookshire",
    "sg:classifiers":[
        {
            "category":"Building & Trades",
            "subcategory":"Electrical",
            "type":"Services"
        }
    ],
    "sg:phone":"+1 819 875 3309",
    "sg:postcode":"J0B 1M0",
    "sg:province":"QC",
    "sg:tags":[
        "equipment",
        "electric",
        "contractor",
        "system",
        "automation"
    ],
    "wof:name":"Cjs Electrique",
    "wof:placetype":"venue"
},
  "geometry": {"coordinates":[-71.624573,45.412773],"type":"Point"}
}