{
  "type": "Feature",
  "properties": {
    "addr:full":"6446 Fraser St Vancouver BC V5W 3A4",
    "addr:housenumber":"6446",
    "addr:postcode":"v5w 3a4",
    "addr:street":"Fraser St",
    "iso:country":"CA",
    "sg:address":"6446 Fraser St",
    "sg:city":"Vancouver",
    "sg:classifiers":[
        {
            "category":"Personal",
            "subcategory":"Beauty Salon",
            "type":"Services"
        }
    ],
    "sg:phone":"+1 604 324 6462",
    "sg:postcode":"V5W 3A4",
    "sg:province":"BC",
    "wof:name":"Nima's Spa & Cafe on Fraser",
    "wof:placetype":"venue"
},
  "geometry": {"coordinates":[-123.09050000000001,49.22607],"type":"Point"}
}