{
  "type": "Feature",
  "properties": {
    "iso:country":"CA",
    "sg:address":"36 Provincial Rd 205E",
    "sg:city":"Rosenort",
    "sg:classifiers":[
        {
            "category":"Manufacturing",
            "subcategory":"Motor Vehicles & Parts",
            "type":"Manufacturing & Wholesale Goods"
        }
    ],
    "sg:phone":"+1 204 746 2348",
    "sg:postcode":"R0G 1W0",
    "sg:province":"MB",
    "sg:tags":[
        "trailer"
    ],
    "wof:name":"Midland Manufacturing Ltd",
    "wof:placetype":"venue"
},
  "geometry": {"coordinates":[-97.4346160889,49.464805603],"type":"Point"}
}