{
  "type": "Feature",
  "properties": {
    "iso:country":"CA",
    "sg:city":"Hanover",
    "sg:classifiers":[
        {
            "category":"Building & Trades",
            "subcategory":"Construction",
            "type":"Services"
        }
    ],
    "sg:phone":"+1 519 364 3518",
    "sg:postcode":"N4N 3B8",
    "sg:province":"ON",
    "sg:tags":[
        "excavating",
        "contractor"
    ],
    "wof:name":"Jerry Seip Construction",
    "wof:placetype":"venue"
},
  "geometry": {"coordinates":[-81.02582550050001,44.1523742676],"type":"Point"}
}