{
  "type": "Feature",
  "properties": {
    "addr:full":"3 Place DE Mailly Lorraine QC J6Z 4L5",
    "addr:housenumber":"3",
    "addr:postcode":"j6z 4l5",
    "addr:street":"Place De Mailly",
    "iso:country":"CA",
    "sg:address":"3 Place DE Mailly",
    "sg:city":"Lorraine",
    "sg:classifiers":[
        {
            "category":"Freight",
            "type":"Transportation"
        }
    ],
    "sg:phone":"+1 450 621 6767",
    "sg:postcode":"J6Z 4L5",
    "sg:province":"QC",
    "sg:tags":[
        "shipping",
        "agent"
    ],
    "wof:name":"Aqua-Jet Cargo Inc",
    "wof:placetype":"venue"
},
  "geometry": {"coordinates":[-73.77806854249999,45.6748275757],"type":"Point"}
}