{
  "type": "Feature",
  "properties": {
    "addr:full":"Richmond BC V6X 3E1",
    "addr:postcode":"v6x 3e1",
    "iso:country":"CA",
    "sg:city":"Richmond",
    "sg:classifiers":[
        {
            "category":"Retail",
            "subcategory":"Auto Repair",
            "type":"Services"
        }
    ],
    "sg:phone":"+1 604 278 4566",
    "sg:postcode":"V6X 3E1",
    "sg:province":"BC",
    "sg:tags":[
        "repairing",
        "automobile"
    ],
    "wof:name":"Bill's Automotive",
    "wof:placetype":"venue"
},
  "geometry": {"coordinates":[-123.09967041,49.1912193298],"type":"Point"}
}