{
  "type": "Feature",
  "properties": {
    "addr:full":"95 Corriveau Ave St Albert AB T8N 5A3",
    "addr:housenumber":"95",
    "addr:postcode":"t8n 5a3",
    "addr:street":"Corriveau Ave",
    "iso:country":"CA",
    "sg:address":"95 Corriveau Ave",
    "sg:city":"St Albert",
    "sg:classifiers":[
        {
            "category":"Building & Trades",
            "subcategory":"Cleaning & Sanitation",
            "type":"Services"
        }
    ],
    "sg:phone":"+1 780 458 6040",
    "sg:postcode":"T8N 5A3",
    "sg:province":"AB",
    "sg:tags":[
        "fireplace",
        "chimney"
    ],
    "wof:name":"St Albert Chimney Sweep Svc",
    "wof:placetype":"venue"
},
  "geometry": {"coordinates":[-113.566833,53.642529],"type":"Point"}
}