{
  "type": "Feature",
  "properties": {
    "addr:full":"Wikwemikong ON P0P 2J0",
    "addr:postcode":"p0p 2j0",
    "iso:country":"CA",
    "sg:city":"Wikwemikong",
    "sg:classifiers":[
        {
            "category":"Professional",
            "subcategory":"Engineering",
            "type":"Services"
        }
    ],
    "sg:phone":"+1 705 859 2803",
    "sg:postcode":"P0P 2J0",
    "sg:province":"ON",
    "sg:tags":[
        "engineer"
    ],
    "wof:name":"First Nations Engineering",
    "wof:placetype":"venue"
},
  "geometry": {"coordinates":[-81.709496,45.806664],"type":"Point"}
}