{
  "type": "Feature",
  "properties": {
    "addr:full":"11033 101 St # B Grande Prairie AB T8V 2R7",
    "addr:housenumber":"11033",
    "addr:postcode":"t8v 2r7",
    "addr:street":"101 St # B",
    "iso:country":"CA",
    "sg:address":"11033 101 St # B",
    "sg:city":"Grande Prairie",
    "sg:classifiers":[
        {
            "category":"Retail",
            "subcategory":"Auto Repair",
            "type":"Services"
        }
    ],
    "sg:phone":"+1 780 532 4051",
    "sg:postcode":"T8V 2R7",
    "sg:province":"AB",
    "sg:tags":[
        "repairing",
        "automobile",
        "engine"
    ],
    "wof:name":"Precision Automotive Mach Shop",
    "wof:placetype":"venue"
},
  "geometry": {"coordinates":[-118.797585,55.180077],"type":"Point"}
}