{
  "type": "Feature",
  "properties": {
    "addr:full":"6 Rue Paul Saint-Majorique QC J2B 8A8",
    "addr:housenumber":"6",
    "addr:postcode":"j2b 8a8",
    "addr:street":"Rue Paul Saint-Majorique",
    "iso:country":"CA",
    "sg:address":"6 Rue Paul",
    "sg:city":"Saint-Majorique",
    "sg:classifiers":[
        {
            "category":"Retail",
            "subcategory":"Auto Repair",
            "type":"Services"
        }
    ],
    "sg:phone":"+1 819 475 1330",
    "sg:postcode":"J2B 8A8",
    "sg:province":"QC",
    "sg:tags":[
        "body",
        "automobile",
        "painting"
    ],
    "wof:name":"Garage Luc Favreau",
    "wof:placetype":"venue"
},
  "geometry": {"coordinates":[-72.578918,45.930977],"type":"Point"}
}