{
  "type": "Feature",
  "properties": {
    "iso:country":"CA",
    "sg:address":"107 Rue DE Berne",
    "sg:city":"Kirkland",
    "sg:classifiers":[
        {
            "category":"Personal",
            "type":"Services"
        }
    ],
    "sg:phone":"+1 514 630 6553",
    "sg:postcode":"H9J 2J5",
    "sg:province":"QC",
    "sg:tags":[
        "buyer",
        "importer"
    ],
    "wof:name":"Global Fashions Intl",
    "wof:placetype":"venue"
},
  "geometry": {"coordinates":[-73.87125396730001,45.4497528076],"type":"Point"}
}