{
  "type": "Feature",
  "properties": {
    "addr:full":"99 Centre St Campbellford ON K0L 1L0",
    "addr:housenumber":"99",
    "addr:postcode":"k0l 1l0",
    "addr:street":"Centre St",
    "iso:country":"CA",
    "sg:address":"99 Centre St",
    "sg:city":"Campbellford",
    "sg:classifiers":[
        {
            "category":"Social Services",
            "type":"Services"
        }
    ],
    "sg:phone":"+1 705 653 1821",
    "sg:postcode":"K0L 1L0",
    "sg:province":"ON",
    "sg:tags":[
        "organization",
        "welfare"
    ],
    "wof:name":"Campbellford & District Assn",
    "wof:placetype":"venue"
},
  "geometry": {"coordinates":[-77.791595,44.304363],"type":"Point"}
}