{
  "type": "Feature",
  "properties": {
    "iso:country":"CA",
    "sg:address":"5 Maplehurst Rd",
    "sg:city":"Winnipeg",
    "sg:classifiers":[
        {
            "category":"Wholesale",
            "subcategory":"Machinery & Supplies",
            "type":"Manufacturing & Wholesale Goods"
        }
    ],
    "sg:phone":"+1 204 256 3324",
    "sg:postcode":"R2J 1W7",
    "sg:province":"MB",
    "sg:tags":[
        "sandblasting"
    ],
    "wof:name":"Manus Abrasive Systems Inc",
    "wof:placetype":"venue"
},
  "geometry": {"coordinates":[-97.07112121580001,49.8608169556],"type":"Point"}
}