{
  "type": "Feature",
  "properties": {
    "iso:country":"CA",
    "sg:address":"834 Rue Simard",
    "sg:city":"Saint-Ambroise",
    "sg:classifiers":[
        {
            "category":"Freight",
            "type":"Transportation"
        }
    ],
    "sg:phone":"+1 418 672 6301",
    "sg:postcode":"G7P 2T6",
    "sg:province":"QC",
    "sg:tags":[
        "trucking"
    ],
    "wof:name":"Transport St-Ambroise Inc",
    "wof:placetype":"venue"
},
  "geometry": {"coordinates":[-71.32274627690001,48.5633277893],"type":"Point"}
}