{
  "type": "Feature",
  "properties": {
    "addr:full":"70 Main St S Minnedosa MB R0J 1E0",
    "addr:housenumber":"70",
    "addr:postcode":"r0j 1e0",
    "addr:street":"Main St S Minnedosa",
    "iso:country":"CA",
    "sg:address":"70 Main St S",
    "sg:city":"Minnedosa",
    "sg:classifiers":[
        {
            "category":"Professional",
            "subcategory":"Accounting & Tax Preparation",
            "type":"Services"
        }
    ],
    "sg:phone":"+1 204 867 5124",
    "sg:postcode":"R0J 1E0",
    "sg:province":"MB",
    "sg:tags":[
        "return",
        "filing"
    ],
    "wof:name":"H & R Block Canada Inc",
    "wof:placetype":"venue"
},
  "geometry": {"coordinates":[-99.8386230469,50.2470207214],"type":"Point"}
}