{
  "type": "Feature",
  "properties": {
    "iso:country":"CA",
    "sg:address":"29 Anne St S",
    "sg:city":"Barrie",
    "sg:classifiers":[
        {
            "category":"Restaurant",
            "type":"Food & Drink"
        }
    ],
    "sg:phone":"+1 705 727 9060",
    "sg:postcode":"L4N 2C5",
    "sg:province":"ON",
    "wof:name":"Players Cookhouse & Beverage",
    "wof:placetype":"venue"
},
  "geometry": {"coordinates":[-79.7038345337,44.3810997009],"type":"Point"}
}