{
  "type": "Feature",
  "properties": {
    "addr:full":"32785 Lougheed Hwy Mission BC V2V 1A8",
    "addr:housenumber":"32785",
    "addr:postcode":"v2v 1a8",
    "addr:street":"Lougheed Hwy",
    "iso:country":"CA",
    "sg:address":"32785 Lougheed Hwy",
    "sg:city":"Mission",
    "sg:classifiers":[
        {
            "category":"Retail",
            "subcategory":"Auto Repair",
            "type":"Services"
        }
    ],
    "sg:phone":"+1 604 820 0708",
    "sg:postcode":"V2V 1A8",
    "sg:province":"BC",
    "sg:tags":[
        "repairing",
        "automobile"
    ],
    "wof:name":"Penzoil 10 Minute Oil Change",
    "wof:placetype":"venue"
},
  "geometry": {"coordinates":[-122.317123,49.133137],"type":"Point"}
}