{
  "type": "Feature",
  "properties": {
    "addr:full":"16648 95 St NW Edmonton AB T5Z 3L2",
    "addr:housenumber":"16648",
    "addr:postcode":"t5z 3l2",
    "addr:street":"95 St Nw",
    "iso:country":"CA",
    "sg:address":"16648 95 St NW",
    "sg:city":"Edmonton",
    "sg:classifiers":[
        {
            "category":"Shopping",
            "subcategory":"Florist",
            "type":"Retail Goods"
        }
    ],
    "sg:phone":"+1 780 475 6306",
    "sg:postcode":"T5Z 3L2",
    "sg:province":"AB",
    "wof:name":"Bunches Flower CO",
    "wof:placetype":"venue"
},
  "geometry": {"coordinates":[-113.487267,53.628166],"type":"Point"}
}