{
  "type": "Feature",
  "properties": {
    "addr:full":"111 Davis Dr Newmarket ON L3Y 2M9",
    "addr:housenumber":"111",
    "addr:postcode":"l3y 2m9",
    "addr:street":"Davis Dr",
    "iso:country":"CA",
    "sg:address":"111 Davis Dr",
    "sg:city":"Newmarket",
    "sg:classifiers":[
        {
            "category":"Food & Beverages",
            "subcategory":"Groceries & Convenience Stores",
            "type":"Retail Goods"
        }
    ],
    "sg:phone":"+1 905 898 0136",
    "sg:postcode":"L3Y 2M9",
    "sg:province":"ON",
    "sg:tags":[
        "grocer"
    ],
    "wof:name":"Town Centre News & Convenience",
    "wof:placetype":"venue"
},
  "geometry": {"coordinates":[-79.475571,44.056034],"type":"Point"}
}