{
  "type": "Feature",
  "properties": {
    "iso:country":"CA",
    "sg:address":"215 Niagara Street Suite 200",
    "sg:city":"Toronto",
    "sg:classifiers":[
        {
            "category":"Professional",
            "subcategory":"Computer Services",
            "type":"Services"
        }
    ],
    "sg:postcode":"M6J 2L2",
    "sg:tags":[
        "blogging",
        "liveblogging",
        "live-cms",
        "journalism",
        "live-journalism",
        "real-time",
        "web-now",
        "media"
    ],
    "sg:website":"http://www.scribblelive.com/",
    "wof:name":"ScribbleLive",
    "wof:placetype":"venue"
},
  "geometry": {"coordinates":[-79.406775,43.64308],"type":"Point"}
}