{
  "type": "Feature",
  "properties": {
    "addr:full":"612 Rte DE Mansonville Mansonville QC J0E 1X0",
    "addr:housenumber":"612",
    "addr:postcode":"j0e 1x0",
    "addr:street":"Rte De Mansonville",
    "iso:country":"CA",
    "sg:address":"612 Rte DE Mansonville",
    "sg:city":"Mansonville",
    "sg:classifiers":[
        {
            "category":"Manufacturing",
            "subcategory":"Lumber",
            "type":"Manufacturing & Wholesale Goods"
        }
    ],
    "sg:phone":"+1 450 292 3490",
    "sg:postcode":"J0E 1X0",
    "sg:province":"QC",
    "sg:tags":[
        "sawmill"
    ],
    "wof:name":"Bois Champigny Inc",
    "wof:placetype":"venue"
},
  "geometry": {"coordinates":[-72.3921966553,45.0488700867],"type":"Point"}
}