{
  "type": "Feature",
  "properties": {
    "addr:full":"375 Nimpkish Gold River BC V0P 1G0",
    "addr:housenumber":"375",
    "addr:postcode":"v0p 1g0",
    "addr:street":"Nimpkish",
    "iso:country":"CA",
    "sg:address":"375 Nimpkish",
    "sg:city":"Gold River",
    "sg:classifiers":[
        {
            "category":"Professional",
            "subcategory":"Accounting & Tax Preparation",
            "type":"Services"
        }
    ],
    "sg:phone":"+1 250 283 7353",
    "sg:postcode":"V0P 1G0",
    "sg:province":"BC",
    "sg:tags":[
        "bookkeeping",
        "general"
    ],
    "wof:name":"Gold River Business Ctr",
    "wof:placetype":"venue"
},
  "geometry": {"coordinates":[-126.054985,49.781273],"type":"Point"}
}