{
  "type": "Feature",
  "properties": {
    "addr:full":"2098 Rue Jean-Talon E Montreal QC H2E 1V3",
    "addr:housenumber":"2098",
    "addr:postcode":"h2e 1v3",
    "addr:street":"Rue Jean-Talon E",
    "iso:country":"CA",
    "sg:address":"2098 Rue Jean-Talon E",
    "sg:city":"Montreal",
    "sg:classifiers":[
        {
            "category":"Restaurant",
            "type":"Food & Drink"
        }
    ],
    "sg:phone":"+1 514 725 9077",
    "sg:postcode":"H2E 1V3",
    "sg:province":"QC",
    "wof:name":"Restaurant Le Gavroche Inc",
    "wof:placetype":"venue"
},
  "geometry": {"coordinates":[-73.6048812866,45.5502891541],"type":"Point"}
}