{
  "type": "Feature",
  "properties": {
    "addr:full":"2093 Jetstream Rd London ON N5V 4M7",
    "addr:housenumber":"2093",
    "addr:postcode":"n5v 4m7",
    "addr:street":"Jetstream Rd",
    "iso:country":"CA",
    "sg:address":"2093 Jetstream Rd",
    "sg:city":"London",
    "sg:classifiers":[
        {
            "category":"Building & Trades",
            "subcategory":"Construction",
            "type":"Services"
        }
    ],
    "sg:phone":"+1 519 457 7979",
    "sg:postcode":"N5V 4M7",
    "sg:province":"ON",
    "sg:tags":[
        "general",
        "contractor"
    ],
    "wof:name":"Autoform Contracting London",
    "wof:placetype":"venue"
},
  "geometry": {"coordinates":[-81.166054,43.025791],"type":"Point"}
}