{
  "type": "Feature",
  "properties": {
    "iso:country":"CA",
    "sg:address":"1458 Broadway E",
    "sg:city":"Vancouver",
    "sg:classifiers":[
        {
            "category":"Shopping",
            "subcategory":"Clothing, Apparel, & Fashions",
            "type":"Retail Goods"
        }
    ],
    "sg:phone":"+1 604 873 2522",
    "sg:postcode":"V5N 1V6",
    "sg:province":"BC",
    "sg:tags":[
        "salvage",
        "surplus",
        "merchandise"
    ],
    "wof:name":"Gorilla Surplus",
    "wof:placetype":"venue"
},
  "geometry": {"coordinates":[-123.07434845,49.2622146606],"type":"Point"}
}