{
  "type": "Feature",
  "properties": {
    "addr:full":"1010 Rue Saint-Joseph Valcourt QC J0E 2L0",
    "addr:housenumber":"1010",
    "addr:postcode":"j0e 2l0",
    "addr:street":"Rue Saint-Joseph",
    "iso:country":"CA",
    "sg:address":"1010 Rue Saint-Joseph",
    "sg:city":"Valcourt",
    "sg:classifiers":[
        {
            "category":"Shopping",
            "subcategory":"Pharmacy",
            "type":"Retail Goods"
        }
    ],
    "sg:phone":"+1 450 532 3130",
    "sg:postcode":"J0E 2L0",
    "sg:province":"QC",
    "wof:name":"Guy Rouillard Pharmacien",
    "wof:placetype":"venue"
},
  "geometry": {"coordinates":[-72.31521606450001,45.4943466187],"type":"Point"}
}