{
  "type": "Feature",
  "properties": {
    "addr:full":"1940 9 Ave SE Calgary AB T2G 0V2",
    "addr:housenumber":"1940",
    "addr:postcode":"t2g 0v2",
    "addr:street":"9 Ave Se",
    "iso:country":"CA",
    "sg:address":"1940 9 Ave SE",
    "sg:city":"Calgary",
    "sg:classifiers":[
        {
            "category":"Retail",
            "subcategory":"Auto Repair",
            "type":"Services"
        }
    ],
    "sg:phone":"+1 403 263 6339",
    "sg:postcode":"T2G 0V2",
    "sg:province":"AB",
    "sg:tags":[
        "repairing",
        "engine"
    ],
    "wof:name":"Performance Plus",
    "wof:placetype":"venue"
},
  "geometry": {"coordinates":[-114.018974,51.035168],"type":"Point"}
}