{
  "type": "Feature",
  "properties": {
    "addr:full":"8515 148 St Surrey BC V3S 3G5",
    "addr:housenumber":"8515",
    "addr:postcode":"v3s 3g5",
    "addr:street":"148 St",
    "iso:country":"CA",
    "sg:address":"8515 148 St",
    "sg:city":"Surrey",
    "sg:classifiers":[
        {
            "category":"Wholesale",
            "subcategory":"Construction Materials",
            "type":"Manufacturing & Wholesale Goods"
        }
    ],
    "sg:phone":"+1 604 591 5141",
    "sg:postcode":"V3S 3G5",
    "sg:province":"BC",
    "sg:tags":[
        "building",
        "contractor"
    ],
    "wof:name":"Dryco Building Supplies Ltd",
    "wof:placetype":"venue"
},
  "geometry": {"coordinates":[-122.812767029,49.1576385498],"type":"Point"}
}