{
  "type": "Feature",
  "properties": {
    "addr:full":"16 Rue Sebastien Chateauguay QC J6K 1N7",
    "addr:housenumber":"16",
    "addr:postcode":"j6k 1n7",
    "addr:street":"Rue Sebastien Chateauguay",
    "iso:country":"CA",
    "sg:address":"16 Rue Sebastien",
    "sg:city":"Chateauguay",
    "sg:classifiers":[
        {
            "category":"Personal",
            "subcategory":"Beauty Salon",
            "type":"Services"
        }
    ],
    "sg:phone":"+1 450 692 4722",
    "sg:postcode":"J6K 1N7",
    "sg:province":"QC",
    "wof:name":"L'Equipe DE LA Coiffure Enr",
    "wof:placetype":"venue"
},
  "geometry": {"coordinates":[-73.745468,45.358173],"type":"Point"}
}