{
  "type": "Feature",
  "properties": {
    "iso:country":"CA",
    "sg:city":"Hamilton",
    "sg:classifiers":[
        {
            "category":"Professional",
            "subcategory":"Employment Agencies",
            "type":"Services"
        }
    ],
    "sg:phone":"+1 905 527 0631",
    "sg:postcode":"L8N 2C3",
    "sg:province":"ON",
    "sg:tags":[
        "opportunity",
        "franchising"
    ],
    "wof:name":"D C Harrison & Assoc Ltd",
    "wof:placetype":"venue"
},
  "geometry": {"coordinates":[-79.86797300000001,43.252426],"type":"Point"}
}