{
  "type": "Feature",
  "properties": {
    "addr:full":"144 Ferrie St E Hamilton ON L8L 3T3",
    "addr:housenumber":"144",
    "addr:postcode":"l8l 3t3",
    "addr:street":"Ferrie St E",
    "iso:country":"CA",
    "sg:address":"144 Ferrie St E",
    "sg:city":"Hamilton",
    "sg:classifiers":[
        {
            "category":"Building & Trades",
            "subcategory":"Cleaning & Sanitation",
            "type":"Services"
        }
    ],
    "sg:phone":"+1 905 527 2828",
    "sg:postcode":"L8L 3T3",
    "sg:province":"ON",
    "sg:tags":[
        "janitor"
    ],
    "wof:name":"Atlas Building Cleaning",
    "wof:placetype":"venue"
},
  "geometry": {"coordinates":[-79.85766599999999,43.267204],"type":"Point"}
}