{
  "type": "Feature",
  "properties": {
    "addr:full":"927 Highway 19 Troy NS B9A 1E9",
    "addr:housenumber":"927",
    "addr:postcode":"b9a 1e9",
    "addr:street":"Highway 19",
    "iso:country":"CA",
    "sg:address":"927 Highway 19",
    "sg:city":"Troy",
    "sg:classifiers":[
        {
            "category":"Travel",
            "subcategory":"Hotels & Motels",
            "type":"Entertainment"
        }
    ],
    "sg:phone":"+1 902 625 3033",
    "sg:postcode":"B9A 1E9",
    "sg:province":"NS",
    "sg:tags":[
        "cottage",
        "tourist",
        "cabin",
        "accommodation"
    ],
    "wof:name":"Paul Bunyan's Cottages",
    "wof:placetype":"venue"
},
  "geometry": {"coordinates":[-61.4390563965,45.6896514893],"type":"Point"}
}