{
  "type": "Feature",
  "properties": {
    "iso:country":"CA",
    "sg:address":"11637 Rue Notre-Dame E",
    "sg:city":"Pointe-Aux-Trembles",
    "sg:classifiers":[
        {
            "category":"Personal",
            "subcategory":"Beauty Salon",
            "type":"Services"
        }
    ],
    "sg:phone":"+1 514 640 6222",
    "sg:postcode":"H1B 2X6",
    "sg:province":"QC",
    "sg:tags":[
        "manicuring"
    ],
    "wof:name":"Grifferie",
    "wof:placetype":"venue"
},
  "geometry": {"coordinates":[-73.4929885864,45.6349411011],"type":"Point"}
}