{
  "type": "Feature",
  "properties": {
    "addr:full":"Grande Prairie AB T8V 0R3",
    "addr:postcode":"t8v 0r3",
    "iso:country":"CA",
    "sg:city":"Grande Prairie",
    "sg:classifiers":[
        {
            "category":"Shopping",
            "subcategory":"Used Merchandise",
            "type":"Retail Goods"
        }
    ],
    "sg:phone":"+1 780 402 6398",
    "sg:postcode":"T8V 0R3",
    "sg:province":"AB",
    "sg:tags":[
        "clothing"
    ],
    "wof:name":"Goodwill Industries of Alberta",
    "wof:placetype":"venue"
},
  "geometry": {"coordinates":[-118.789978,55.169544],"type":"Point"}
}