{
  "type": "Feature",
  "properties": {
    "iso:country":"CA",
    "sg:city":"Vancouver",
    "sg:classifiers":[
        {
            "category":"Restaurant",
            "type":"Food & Drink"
        }
    ],
    "sg:phone":"+1 604 222 2922",
    "sg:postcode":"V6T 1K6",
    "sg:province":"BC",
    "sg:tags":[
        "pizza"
    ],
    "wof:name":"University Plaza Pizza",
    "wof:placetype":"venue"
},
  "geometry": {"coordinates":[-123.242912292,49.2666053772],"type":"Point"}
}