{
  "type": "Feature",
  "properties": {
    "iso:country":"CA",
    "sg:address":"1795 Danforth Ave",
    "sg:city":"Toronto",
    "sg:classifiers":[
        {
            "category":"Bars & Pubs",
            "type":"Food & Drink"
        }
    ],
    "sg:phone":"+1 416 698 9191",
    "sg:postcode":"M4C 1J2",
    "sg:province":"ON",
    "wof:name":"Cheers",
    "wof:placetype":"venue"
},
  "geometry": {"coordinates":[-79.318764,43.68425],"type":"Point"}
}