{
  "type": "Feature",
  "properties": {
    "addr:full":"764 Division St Cobourg ON K9A 5V2",
    "addr:housenumber":"764",
    "addr:postcode":"k9a 5v2",
    "addr:street":"Division St",
    "iso:country":"CA",
    "sg:address":"764 Division St",
    "sg:city":"Cobourg",
    "sg:classifiers":[
        {
            "category":"Home & Garden",
            "subcategory":"Hardware",
            "type":"Retail Goods"
        }
    ],
    "sg:phone":"+1 905 372 3381",
    "sg:postcode":"K9A 5V2",
    "sg:province":"ON",
    "sg:tags":[
        "paint"
    ],
    "wof:name":"Cobourg Home Hardware",
    "wof:placetype":"venue"
},
  "geometry": {"coordinates":[-78.17083,43.972237],"type":"Point"}
}