{
  "type": "Feature",
  "properties": {
    "addr:full":"Beaverlodge AB T0H 0C0",
    "addr:postcode":"t0h 0c0",
    "iso:country":"CA",
    "sg:city":"Beaverlodge",
    "sg:classifiers":[
        {
            "category":"Health Services",
            "subcategory":"Doctor",
            "type":"Services"
        }
    ],
    "sg:phone":"+1 780 354 2646",
    "sg:postcode":"T0H 0C0",
    "sg:province":"AB",
    "sg:tags":[
        "physician",
        "surgeon"
    ],
    "wof:name":"Beaverlodge Medical Clinic",
    "wof:placetype":"venue"
},
  "geometry": {"coordinates":[-119.42691803,55.208770752],"type":"Point"}
}