{
  "type": "Feature",
  "properties": {
    "addr:full":"14 Lakeport Rd St Catharines ON L2N 4P5",
    "addr:housenumber":"14",
    "addr:postcode":"l2n 4p5",
    "addr:street":"Lakeport Rd",
    "iso:country":"CA",
    "sg:address":"14 Lakeport Rd",
    "sg:city":"St Catharines",
    "sg:classifiers":[
        {
            "category":"Restaurant",
            "type":"Food & Drink"
        }
    ],
    "sg:phone":"+1 905 646 7777",
    "sg:postcode":"L2N 4P5",
    "sg:province":"ON",
    "sg:tags":[
        "pizza"
    ],
    "wof:name":"Da Pizza Joint Ltd",
    "wof:placetype":"venue"
},
  "geometry": {"coordinates":[-79.26546500000001,43.202507],"type":"Point"}
}