{
  "type": "Feature",
  "properties": {
    "iso:country":"CA",
    "sg:address":"16 Edvac Dr",
    "sg:city":"Brampton",
    "sg:classifiers":[
        {
            "category":"Manufacturing",
            "subcategory":"Metals",
            "type":"Manufacturing & Wholesale Goods"
        }
    ],
    "sg:phone":"+1 905 458 8850",
    "sg:postcode":"L6S 5P2",
    "sg:province":"ON",
    "sg:tags":[
        "steel"
    ],
    "wof:name":"Lorvin Steel Ltd",
    "wof:placetype":"venue"
},
  "geometry": {"coordinates":[-79.705399,43.762184],"type":"Point"}
}