{
  "type": "Feature",
  "properties": {
    "addr:full":"1825 Rue Principale E Abbotsford QC J0E 1A0",
    "addr:housenumber":"1825",
    "addr:postcode":"j0e 1a0",
    "addr:street":"Rue Principale E",
    "iso:country":"CA",
    "sg:address":"1825 Rue Principale E",
    "sg:city":"Abbotsford",
    "sg:classifiers":[
        {
            "category":"Building & Trades",
            "subcategory":"Construction",
            "type":"Services"
        }
    ],
    "sg:phone":"+1 450 379 5251",
    "sg:postcode":"J0E 1A0",
    "sg:province":"QC",
    "sg:tags":[
        "paving",
        "road",
        "contractor"
    ],
    "wof:name":"Sintra Inc",
    "wof:placetype":"venue"
},
  "geometry": {"coordinates":[-72.863281,45.434124],"type":"Point"}
}