{
  "type": "Feature",
  "properties": {
    "addr:full":"1548 the Queensway Etobicoke ON M8Z 1T5",
    "addr:housenumber":"1548",
    "addr:postcode":"m8z 1t5",
    "addr:street":"The Queensway",
    "iso:country":"CA",
    "sg:address":"1548 the Queensway",
    "sg:city":"Etobicoke",
    "sg:classifiers":[
        {
            "category":"Manufacturing",
            "subcategory":"Tools & Machinery",
            "type":"Manufacturing & Wholesale Goods"
        }
    ],
    "sg:phone":"+1 416 252 2293",
    "sg:postcode":"M8Z 1T5",
    "sg:province":"ON",
    "sg:tags":[
        "stamp",
        "recorder",
        "time"
    ],
    "wof:name":"Cincinnati Time",
    "wof:placetype":"venue"
},
  "geometry": {"coordinates":[-79.53801,43.618576],"type":"Point"}
}