{
  "type": "Feature",
  "properties": {
    "addr:full":"295 King St W Toronto ON M5V 1J5",
    "addr:housenumber":"295",
    "addr:postcode":"m5v 1j5",
    "addr:street":"King St W",
    "iso:country":"CA",
    "sg:address":"295 King St W",
    "sg:city":"Toronto",
    "sg:classifiers":[
        {
            "category":"Restaurant",
            "type":"Food & Drink"
        }
    ],
    "sg:phone":"+1 416 408 3633",
    "sg:postcode":"M5V 1J5",
    "sg:province":"ON",
    "wof:name":"Hey Lucy Cafe",
    "wof:placetype":"venue"
},
  "geometry": {"coordinates":[-79.390198,43.646355],"type":"Point"}
}