{
  "type": "Feature",
  "properties": {
    "addr:full":"2525 Dougall Ave Windsor ON N8X 5A7",
    "addr:housenumber":"2525",
    "addr:postcode":"n8x 5a7",
    "addr:street":"Dougall Ave",
    "iso:country":"CA",
    "sg:address":"2525 Dougall Ave",
    "sg:city":"Windsor",
    "sg:classifiers":[
        {
            "category":"Professional",
            "subcategory":"Computer Services",
            "type":"Services"
        }
    ],
    "sg:phone":"+1 519 972 6677",
    "sg:postcode":"N8X 5A7",
    "sg:province":"ON",
    "sg:tags":[
        "internet"
    ],
    "wof:name":"Cogeco Cable Solutions",
    "wof:placetype":"venue"
},
  "geometry": {"coordinates":[-83.0222167969,42.2855377197],"type":"Point"}
}