{
  "type": "Feature",
  "properties": {
    "addr:full":"3770 Rue Marian Laval QC H7P 1M5",
    "addr:housenumber":"3770",
    "addr:postcode":"h7p 1m5",
    "addr:street":"Rue Marian",
    "iso:country":"CA",
    "sg:address":"3770 Rue Marian",
    "sg:city":"Laval",
    "sg:classifiers":[
        {
            "category":"Building & Trades",
            "subcategory":"Electrical",
            "type":"Services"
        }
    ],
    "sg:phone":"+1 450 622 2020",
    "sg:postcode":"H7P 1M5",
    "sg:province":"QC",
    "sg:tags":[
        "electric",
        "contractor"
    ],
    "wof:name":"A Neron Electrique Inc",
    "wof:placetype":"venue"
},
  "geometry": {"coordinates":[-73.8207168579,45.5762443542],"type":"Point"}
}