{
  "type": "Feature",
  "properties": {
    "addr:full":"1168 125 Rte Sainte-Julienne QC J0K 2T0",
    "addr:housenumber":"1168",
    "addr:postcode":"j0k 2t0",
    "addr:street":"125 Rte",
    "iso:country":"CA",
    "sg:address":"1168 125 Rte",
    "sg:city":"Sainte-Julienne",
    "sg:classifiers":[
        {
            "category":"Restaurant",
            "type":"Food & Drink"
        }
    ],
    "sg:phone":"+1 450 831 4011",
    "sg:postcode":"J0K 2T0",
    "sg:province":"QC",
    "sg:tags":[
        "cafe"
    ],
    "wof:name":"Bistro L'Empire",
    "wof:placetype":"venue"
},
  "geometry": {"coordinates":[-73.70792400000001,45.962708],"type":"Point"}
}