{
  "type": "Feature",
  "properties": {
    "iso:country":"CA",
    "sg:address":"1500 Arbour Lake Rd NW",
    "sg:city":"Calgary",
    "sg:classifiers":[
        {
            "category":"Organizations",
            "subcategory":"Religious Organization",
            "type":"Services"
        }
    ],
    "sg:phone":"+1 403 693 5555",
    "sg:postcode":"T3G 4X9",
    "sg:province":"AB",
    "sg:tags":[
        "church"
    ],
    "wof:name":"Hillside Community Church",
    "wof:placetype":"venue"
},
  "geometry": {"coordinates":[-114.207893,51.133862],"type":"Point"}
}