{
  "type": "Feature",
  "properties": {
    "addr:full":"Grande Prairie AB T8V 3Y2",
    "addr:postcode":"t8v 3y2",
    "iso:country":"CA",
    "sg:city":"Grande Prairie",
    "sg:classifiers":[
        {
            "category":"Shopping",
            "subcategory":"Jewelry",
            "type":"Retail Goods"
        }
    ],
    "sg:phone":"+1 780 532 3523",
    "sg:postcode":"T8V 3Y2",
    "sg:province":"AB",
    "sg:tags":[
        "jeweler"
    ],
    "wof:name":"Warrington's Jewellers",
    "wof:placetype":"venue"
},
  "geometry": {"coordinates":[-118.794456,55.186874],"type":"Point"}
}