{
  "type": "Feature",
  "properties": {
    "addr:full":"314 Harwood Ave S Ajax ON L1S 2J1",
    "addr:housenumber":"314",
    "addr:postcode":"l1s 2j1",
    "addr:street":"Harwood Ave S",
    "iso:country":"CA",
    "sg:address":"314 Harwood Ave S",
    "sg:city":"Ajax",
    "sg:classifiers":[
        {
            "category":"Shopping",
            "subcategory":"Pharmacy",
            "type":"Retail Goods"
        }
    ],
    "sg:phone":"+1 905 683 5222",
    "sg:postcode":"L1S 2J1",
    "sg:province":"ON",
    "wof:name":"Shoppers Drug Mart",
    "wof:placetype":"venue"
},
  "geometry": {"coordinates":[-79.0195846558,43.846206665],"type":"Point"}
}