{
  "type": "Feature",
  "properties": {
    "iso:country":"CA",
    "sg:city":"Henryville",
    "sg:classifiers":[
        {
            "category":"Home & Garden",
            "subcategory":"Hardware",
            "type":"Retail Goods"
        }
    ],
    "sg:phone":"+1 450 299 2856",
    "sg:postcode":"J0J 1E0",
    "sg:province":"QC",
    "wof:name":"Coopexcel Cooperative Agricole",
    "wof:placetype":"venue"
},
  "geometry": {"coordinates":[-73.18520355219999,45.1367492676],"type":"Point"}
}