{
  "type": "Feature",
  "properties": {
    "addr:full":"255 Rte Du Pont Saint-Nicolas QC G7A 2V1",
    "addr:housenumber":"255",
    "addr:postcode":"g7a 2v1",
    "addr:street":"Rte Du Pont",
    "iso:country":"CA",
    "sg:address":"255 Rte Du Pont",
    "sg:city":"Saint-Nicolas",
    "sg:classifiers":[
        {
            "category":"Wholesale",
            "subcategory":"Sporting Goods",
            "type":"Manufacturing & Wholesale Goods"
        }
    ],
    "sg:phone":"+1 418 836 7383",
    "sg:postcode":"G7A 2V1",
    "sg:province":"QC",
    "wof:name":"Agence Andre Emond Enr",
    "wof:placetype":"venue"
},
  "geometry": {"coordinates":[-71.295174,46.730503],"type":"Point"}
}