{
  "type": "Feature",
  "properties": {
    "addr:full":"48 Rue Boivin Ville-Marie QC J9V 1B5",
    "addr:housenumber":"48",
    "addr:postcode":"j9v 1b5",
    "addr:street":"Rue Boivin",
    "iso:country":"CA",
    "sg:address":"48 Rue Boivin",
    "sg:city":"Ville-Marie",
    "sg:classifiers":[
        {
            "category":"Organizations",
            "subcategory":"Labor Organization",
            "type":"Services"
        }
    ],
    "sg:phone":"+1 819 629 3120",
    "sg:postcode":"J9V 1B5",
    "sg:province":"QC",
    "wof:name":"Confederation Des Syndicats",
    "wof:placetype":"venue"
},
  "geometry": {"coordinates":[-79.4289855957,47.3286094666],"type":"Point"}
}