{
  "type": "Feature",
  "properties": {
    "addr:full":"1800 Logan Ave Winnipeg MB R2R 0H3",
    "addr:housenumber":"1800",
    "addr:postcode":"r2r 0h3",
    "addr:street":"Logan Ave",
    "iso:country":"CA",
    "sg:address":"1800 Logan Ave",
    "sg:city":"Winnipeg",
    "sg:classifiers":[
        {
            "category":"Health Services",
            "subcategory":"Doctor",
            "type":"Services"
        }
    ],
    "sg:phone":"+1 204 633 7281",
    "sg:postcode":"R2R 0H3",
    "sg:province":"MB",
    "sg:tags":[
        "physician",
        "surgeon"
    ],
    "wof:name":"Westbrook Medical Ctr",
    "wof:placetype":"venue"
},
  "geometry": {"coordinates":[-97.19573200000001,49.921619],"type":"Point"}
}