{
  "type": "Feature",
  "properties": {
    "addr:full":"21 Moffatt's Rd Mount Pearl NL A1N 5B9",
    "addr:housenumber":"21",
    "addr:postcode":"a1n 5b9",
    "addr:street":"Moffatt'S Rd",
    "iso:country":"CA",
    "sg:address":"21 Moffatt's Rd",
    "sg:city":"Mount Pearl",
    "sg:classifiers":[
        {
            "category":"Freight",
            "type":"Transportation"
        }
    ],
    "sg:phone":"+1 709 364 4255",
    "sg:postcode":"A1N 5B9",
    "sg:province":"NL",
    "sg:tags":[
        "mover"
    ],
    "wof:name":"Amj Campbell",
    "wof:placetype":"venue"
},
  "geometry": {"coordinates":[-52.819721,47.516399],"type":"Point"}
}