{
  "type": "Feature",
  "properties": {
    "addr:full":"605 Nicola St Kamloops BC V2C 2R3",
    "addr:housenumber":"605",
    "addr:postcode":"bc v2c 2r3",
    "addr:street":"Nicola St",
    "iso:country":"CA",
    "sg:address":"605 Nicola St",
    "sg:city":"Kamloops",
    "sg:classifiers":[
        {
            "category":"Real Estate",
            "subcategory":"Real Estate Services",
            "type":"Services"
        }
    ],
    "sg:phone":"+1 250 372 3514",
    "sg:postcode":"V2C 2R3",
    "sg:province":"BC",
    "sg:tags":[
        "company",
        "title"
    ],
    "wof:name":"Central Sten-Ad Ltd",
    "wof:placetype":"venue"
},
  "geometry": {"coordinates":[-120.326729,50.672131],"type":"Point"}
}