{
  "type": "Feature",
  "properties": {
    "addr:full":"640 Rte Begin Saint-Anselme QC G0R 2N0",
    "addr:housenumber":"640",
    "addr:postcode":"g0r 2n0",
    "addr:street":"Rte Begin",
    "iso:country":"CA",
    "sg:address":"640 Rte Begin",
    "sg:city":"Saint-Anselme",
    "sg:classifiers":[
        {
            "category":"Restaurant",
            "type":"Food & Drink"
        }
    ],
    "sg:phone":"+1 418 885 9412",
    "sg:postcode":"G0R 2N0",
    "sg:province":"QC",
    "wof:name":"Restaurant Chez Doc Inc",
    "wof:placetype":"venue"
},
  "geometry": {"coordinates":[-70.97937,46.633595],"type":"Point"}
}