{
  "type": "Feature",
  "properties": {
    "addr:full":"3355 Kingsway Vancouver BC V5R 5K6",
    "addr:housenumber":"3355",
    "addr:postcode":"v5r 5k6",
    "addr:street":"Kingsway",
    "iso:country":"CA",
    "sg:address":"3355 Kingsway",
    "sg:city":"Vancouver",
    "sg:classifiers":[
        {
            "category":"Insurance",
            "subcategory":"Insurance Agent",
            "type":"Services"
        }
    ],
    "sg:phone":"+1 604 434 3177",
    "sg:postcode":"V5R 5K6",
    "sg:province":"BC",
    "wof:name":"Apex Insurance Svc",
    "wof:placetype":"venue"
},
  "geometry": {"coordinates":[-123.03426399999999,49.233486],"type":"Point"}
}