{
  "type": "Feature",
  "properties": {
    "iso:country":"CA",
    "sg:city":"Burnaby",
    "sg:classifiers":[
        {
            "category":"Wholesale",
            "subcategory":"Groceries",
            "type":"Manufacturing & Wholesale Goods"
        }
    ],
    "sg:phone":"+1 604 435 1255",
    "sg:postcode":"V5H 4M1",
    "sg:province":"BC",
    "sg:tags":[
        "optical"
    ],
    "wof:name":"Eye Star Optical",
    "wof:placetype":"venue"
},
  "geometry": {"coordinates":[-122.999435425,49.2283248901],"type":"Point"}
}