{
  "type": "Feature",
  "properties": {
    "addr:full":"Victoria BC V8V 4Y9",
    "addr:postcode":"v8v 4y9",
    "iso:country":"CA",
    "sg:city":"Victoria",
    "sg:classifiers":[
        {
            "category":"Professional",
            "subcategory":"Management & Consulting",
            "type":"Services"
        }
    ],
    "sg:phone":"+1 250 370 7617",
    "sg:postcode":"V8V 4Y9",
    "sg:province":"BC",
    "sg:tags":[
        "arbitration",
        "consultant",
        "business"
    ],
    "wof:name":"Diamond Management Consulting",
    "wof:placetype":"venue"
},
  "geometry": {"coordinates":[-123.358772,48.425507],"type":"Point"}
}