{
  "type": "Feature",
  "properties": {
    "addr:full":"41 Hudson Bay Ave Kirkland Lake ON P2N 2H8",
    "addr:housenumber":"41",
    "addr:postcode":"p2n 2h8",
    "addr:street":"Hudson Bay Ave",
    "iso:country":"CA",
    "sg:address":"41 Hudson Bay Ave",
    "sg:city":"Kirkland Lake",
    "sg:classifiers":[
        {
            "category":"Wholesale",
            "subcategory":"Meat",
            "type":"Manufacturing & Wholesale Goods"
        }
    ],
    "sg:phone":"+1 705 568 8435",
    "sg:postcode":"P2N 2H8",
    "sg:province":"ON",
    "sg:tags":[
        "butchering"
    ],
    "wof:name":"Claude's Meat Market",
    "wof:placetype":"venue"
},
  "geometry": {"coordinates":[-80.03447723390001,48.1479072571],"type":"Point"}
}