{
  "type": "Feature",
  "properties": {
    "iso:country":"CA",
    "sg:city":"Chateauguay",
    "sg:classifiers":[
        {
            "category":"Health Services",
            "subcategory":"Doctor",
            "type":"Services"
        }
    ],
    "sg:phone":"+1 450 692 4000",
    "sg:postcode":"J6K 3B1",
    "sg:province":"QC",
    "sg:tags":[
        "clinic"
    ],
    "wof:name":"Clinique Dentaire N Socque",
    "wof:placetype":"venue"
},
  "geometry": {"coordinates":[-73.71812438960001,45.3552284241],"type":"Point"}
}