{
  "type": "Feature",
  "properties": {
    "addr:full":"7355 Bayview Ave # 3 Thornhill ON L3T 5Z2",
    "addr:housenumber":"7355",
    "addr:postcode":"l3t 5z2",
    "addr:street":"Bayview Ave # 3",
    "iso:country":"CA",
    "sg:address":"7355 Bayview Ave # 3",
    "sg:city":"Thornhill",
    "sg:classifiers":[
        {
            "category":"Personal",
            "subcategory":"Beauty Salon",
            "type":"Services"
        }
    ],
    "sg:phone":"+1 905 731 6567",
    "sg:postcode":"L3T 5Z2",
    "sg:province":"ON",
    "wof:name":"Ferro Hair Art",
    "wof:placetype":"venue"
},
  "geometry": {"coordinates":[-79.39957427980001,43.8128166199],"type":"Point"}
}