{
  "type": "Feature",
  "properties": {
    "addr:full":"400 Midpark Way SE Calgary AB T2X 3S4",
    "addr:housenumber":"400",
    "addr:postcode":"t2x 3s4",
    "addr:street":"Midpark Way Se",
    "iso:country":"CA",
    "sg:address":"400 Midpark Way SE",
    "sg:city":"Calgary",
    "sg:classifiers":[
        {
            "category":"Retail",
            "subcategory":"Auto Rental",
            "type":"Services"
        }
    ],
    "sg:phone":"+1 403 873 2580",
    "sg:postcode":"T2X 3S4",
    "sg:province":"AB",
    "sg:tags":[
        "renting",
        "automobile"
    ],
    "wof:name":"Avis Rent A Car",
    "wof:placetype":"venue"
},
  "geometry": {"coordinates":[-114.060776,50.906715],"type":"Point"}
}