{
  "type": "Feature",
  "properties": {
    "iso:country":"CA",
    "sg:city":"Mississauga",
    "sg:classifiers":[
        {
            "category":"Manufacturing",
            "subcategory":"Tools & Machinery",
            "type":"Manufacturing & Wholesale Goods"
        }
    ],
    "sg:phone":"+1 905 542 2300",
    "sg:postcode":"L5N 2M2",
    "sg:province":"ON",
    "sg:tags":[
        "body",
        "automobile",
        "shop",
        "equipment"
    ],
    "wof:name":"Carsystem Canada Inc",
    "wof:placetype":"venue"
},
  "geometry": {"coordinates":[-79.7456665039,43.5923118591],"type":"Point"}
}