{
  "type": "Feature",
  "properties": {
    "addr:full":"201 Main St Punnichy SK S0A 3C0",
    "addr:housenumber":"201",
    "addr:postcode":"s0a 3c0",
    "addr:street":"Main St",
    "iso:country":"CA",
    "sg:address":"201 Main St",
    "sg:city":"Punnichy",
    "sg:classifiers":[
        {
            "category":"Autos & Motor Vehicles",
            "subcategory":"Auto Supplies",
            "type":"Retail Goods"
        }
    ],
    "sg:phone":"+1 306 835 2102",
    "sg:postcode":"S0A 3C0",
    "sg:province":"SK",
    "sg:tags":[
        "automobile",
        "parts"
    ],
    "wof:name":"Punnichy Auto Supply",
    "wof:placetype":"venue"
},
  "geometry": {"coordinates":[-104.293823242,51.3744850159],"type":"Point"}
}