{
  "type": "Feature",
  "properties": {
    "addr:full":"1790 Rue Couvrette Saint-Laurent QC H4L 4T8",
    "addr:housenumber":"1790",
    "addr:postcode":"h4l 4t8",
    "addr:street":"Rue Couvrette",
    "iso:country":"CA",
    "sg:address":"1790 Rue Couvrette",
    "sg:city":"Saint-Laurent",
    "sg:classifiers":[
        {
            "category":"Professional",
            "subcategory":"Computer Services",
            "type":"Services"
        }
    ],
    "sg:phone":"+1 514 747 7577",
    "sg:postcode":"H4L 4T8",
    "sg:province":"QC",
    "sg:tags":[
        "information",
        "system",
        "consultant"
    ],
    "wof:name":"Cogiq Inc",
    "wof:placetype":"venue"
},
  "geometry": {"coordinates":[-73.683685,45.527493],"type":"Point"}
}