{
  "type": "Feature",
  "properties": {
    "addr:full":"153 Mississaga St E Orillia ON L3V 1V6",
    "addr:housenumber":"153",
    "addr:postcode":"l3v 1v6",
    "addr:street":"Mississaga St E",
    "iso:country":"CA",
    "sg:address":"153 Mississaga St E",
    "sg:city":"Orillia",
    "sg:classifiers":[
        {
            "category":"Personal",
            "subcategory":"Beauty Salon",
            "type":"Services"
        }
    ],
    "sg:phone":"+1 705 326 2381",
    "sg:postcode":"L3V 1V6",
    "sg:province":"ON",
    "wof:name":"Details Hair Care",
    "wof:placetype":"venue"
},
  "geometry": {"coordinates":[-79.41596199999999,44.609669],"type":"Point"}
}