{
  "type": "Feature",
  "properties": {
    "iso:country":"CA",
    "sg:address":"126 Main St N",
    "sg:city":"Markham",
    "sg:classifiers":[
        {
            "category":"Manufacturing",
            "subcategory":"Leather Goods",
            "type":"Manufacturing & Wholesale Goods"
        }
    ],
    "sg:phone":"+1 905 294 9515",
    "sg:postcode":"L3P 1Y1",
    "sg:province":"ON",
    "sg:tags":[
        "fur",
        "business"
    ],
    "wof:name":"Elizabeth Furs Ltd",
    "wof:placetype":"venue"
},
  "geometry": {"coordinates":[-79.2611083984,43.8784370422],"type":"Point"}
}