{
  "type": "Feature",
  "properties": {
    "addr:full":"459 E Island Hwy Parksville BC V9P 2G5",
    "addr:housenumber":"459",
    "addr:postcode":"v9p 2g5",
    "addr:street":"E Island Hwy",
    "iso:country":"CA",
    "sg:address":"459 E Island Hwy",
    "sg:city":"Parksville",
    "sg:classifiers":[
        {
            "category":"Travel",
            "subcategory":"Hotels & Motels",
            "type":"Entertainment"
        }
    ],
    "sg:phone":"+1 250 248 4271",
    "sg:postcode":"V9P 2G5",
    "sg:province":"BC",
    "wof:name":"Skylite Motel",
    "wof:placetype":"venue"
},
  "geometry": {"coordinates":[-124.297989,49.318325],"type":"Point"}
}