{
  "type": "Feature",
  "properties": {
    "addr:full":"Espanola ON P5E 1S3",
    "addr:postcode":"p5e 1s3",
    "iso:country":"CA",
    "sg:city":"Espanola",
    "sg:classifiers":[
        {
            "category":"Bus Charters",
            "type":"Transportation"
        }
    ],
    "sg:phone":"+1 705 869 2250",
    "sg:postcode":"P5E 1S3",
    "sg:province":"ON",
    "sg:tags":[
        "rental"
    ],
    "wof:name":"Veterans Transportation",
    "wof:placetype":"venue"
},
  "geometry": {"coordinates":[-81.7642364502,46.2567710876],"type":"Point"}
}