{
  "type": "Feature",
  "properties": {
    "addr:full":"219 3rd Ave W Prince Rupert BC V8J 1L2",
    "addr:housenumber":"219",
    "addr:postcode":"v8j 1l2",
    "addr:street":"3Rd Ave W",
    "iso:country":"CA",
    "sg:address":"219 3rd Ave W",
    "sg:city":"Prince Rupert",
    "sg:classifiers":[
        {
            "category":"Shopping",
            "subcategory":"Computers & Home Electronics",
            "type":"Retail Goods"
        }
    ],
    "sg:phone":"+1 250 627 7960",
    "sg:postcode":"V8J 1L2",
    "sg:province":"BC",
    "sg:tags":[
        "high",
        "television",
        "stereophonic",
        "fidelity"
    ],
    "wof:name":"East Wind Emporium",
    "wof:placetype":"venue"
},
  "geometry": {"coordinates":[-130.32238799999999,54.314018],"type":"Point"}
}