{
  "type": "Feature",
  "properties": {
    "addr:full":"249 Erie St Stratford ON N5A 2M9",
    "addr:housenumber":"249",
    "addr:postcode":"n5a 2m9",
    "addr:street":"Erie St",
    "iso:country":"CA",
    "sg:address":"249 Erie St",
    "sg:city":"Stratford",
    "sg:classifiers":[
        {
            "category":"Personal",
            "subcategory":"Beauty Salon",
            "type":"Services"
        }
    ],
    "sg:phone":"+1 519 271 6936",
    "sg:postcode":"N5A 2M9",
    "sg:province":"ON",
    "wof:name":"Vickie's Hair Styling",
    "wof:placetype":"venue"
},
  "geometry": {"coordinates":[-80.98723602290001,43.3659515381],"type":"Point"}
}