{
  "type": "Feature",
  "properties": {
    "iso:country":"CA",
    "sg:address":"322 Rue King-George",
    "sg:city":"Longueuil",
    "sg:classifiers":[
        {
            "category":"Health Services",
            "subcategory":"Doctor",
            "type":"Services"
        }
    ],
    "sg:phone":"+1 450 647 1441",
    "sg:postcode":"J4J 2V5",
    "sg:province":"QC",
    "sg:tags":[
        "dentist"
    ],
    "wof:name":"Clinique Dentaire & Medicale",
    "wof:placetype":"venue"
},
  "geometry": {"coordinates":[-73.4720840454,45.5311088562],"type":"Point"}
}