{
  "type": "Feature",
  "properties": {
    "addr:full":"Joliette QC J6E 3R4",
    "addr:postcode":"j6e 3r4",
    "iso:country":"CA",
    "sg:city":"Joliette",
    "sg:classifiers":[
        {
            "category":"Shopping",
            "subcategory":"Florist",
            "type":"Retail Goods"
        }
    ],
    "sg:phone":"+1 450 759 2081",
    "sg:postcode":"J6E 3R4",
    "sg:province":"QC",
    "wof:name":"Fleuriste Au Langage Des Fleur",
    "wof:placetype":"venue"
},
  "geometry": {"coordinates":[-73.43163300000001,46.025944],"type":"Point"}
}