{
  "type": "Feature",
  "properties": {
    "addr:full":"1149 Boul Saint-Antoine Saint-Jerome QC J7Z 7M1",
    "addr:housenumber":"1149",
    "addr:postcode":"j7z 7m1",
    "addr:street":"Boul Saint-Antoine",
    "iso:country":"CA",
    "sg:address":"1149 Boul Saint-Antoine",
    "sg:city":"Saint-Jerome",
    "sg:classifiers":[
        {
            "category":"Autos & Motor Vehicles",
            "subcategory":"Fuel & Gas Station",
            "type":"Retail Goods"
        }
    ],
    "sg:phone":"+1 450 438 4307",
    "sg:postcode":"J7Z 7M1",
    "sg:province":"QC",
    "sg:tags":[
        "oil"
    ],
    "wof:name":"Depanneur Voisin Au Bon Svc",
    "wof:placetype":"venue"
},
  "geometry": {"coordinates":[-73.977585,45.767284],"type":"Point"}
}