{
  "type": "Feature",
  "properties": {
    "iso:country":"CA",
    "sg:address":"560 Boul Cremazie E",
    "sg:city":"Montreal",
    "sg:classifiers":[
        {
            "category":"Organizations",
            "subcategory":"Religious Organization",
            "type":"Services"
        }
    ],
    "sg:phone":"+1 514 388 1161",
    "sg:postcode":"H2P 1E8",
    "sg:province":"QC",
    "sg:tags":[
        "church"
    ],
    "wof:name":"St Alphonse Paroisse",
    "wof:placetype":"venue"
},
  "geometry": {"coordinates":[-73.6371002197,45.5468482971],"type":"Point"}
}