{
  "type": "Feature",
  "properties": {
    "addr:full":"1520 Lynn Valley Rd North Vancouver BC V7J 2B2",
    "addr:housenumber":"1520",
    "addr:postcode":"v7j 2b2",
    "addr:street":"Lynn Valley Rd",
    "iso:country":"CA",
    "sg:address":"1520 Lynn Valley Rd",
    "sg:city":"North Vancouver",
    "sg:classifiers":[
        {
            "category":"Professional",
            "type":"Services"
        }
    ],
    "sg:phone":"+1 604 983 2525",
    "sg:postcode":"V7J 2B2",
    "sg:province":"BC",
    "sg:tags":[
        "editorial"
    ],
    "wof:name":"Word Works Editorial Svc",
    "wof:placetype":"venue"
},
  "geometry": {"coordinates":[-123.03205871599999,49.3405265808],"type":"Point"}
}