{
  "type": "Feature",
  "properties": {
    "iso:country":"CA",
    "sg:address":"65 Lakeshore Rd",
    "sg:city":"Selkirk",
    "sg:classifiers":[
        {
            "category":"Manufacturing",
            "subcategory":"Food",
            "type":"Manufacturing & Wholesale Goods"
        }
    ],
    "sg:phone":"+1 905 776 2108",
    "sg:postcode":"N0A 1P0",
    "sg:province":"ON",
    "sg:tags":[
        "seafood",
        "product",
        "fish",
        "prepared"
    ],
    "wof:name":"Cooper Bay Fishery Ltd",
    "wof:placetype":"venue"
},
  "geometry": {"coordinates":[-79.91938781739999,42.8197288513],"type":"Point"}
}