{
  "type": "Feature",
  "properties": {
    "addr:full":"3400 Highway 35 115 Newcastle ON L1B 1L9",
    "addr:housenumber":"3400;115",
    "addr:postcode":"l1b 1l9",
    "addr:street":"Highway 35",
    "iso:country":"CA",
    "sg:address":"3400 Highway 35 115",
    "sg:city":"Newcastle",
    "sg:classifiers":[
        {
            "category":"Retail",
            "subcategory":"Auto Repair",
            "type":"Services"
        }
    ],
    "sg:phone":"+1 905 987 5153",
    "sg:postcode":"L1B 1L9",
    "sg:province":"ON",
    "sg:tags":[
        "repairing",
        "automobile"
    ],
    "wof:name":"Hometown Tire & Auto Ctr",
    "wof:placetype":"venue"
},
  "geometry": {"coordinates":[-78.60311900000001,43.941895],"type":"Point"}
}