{
  "type": "Feature",
  "properties": {
    "addr:full":"5002 50 Ave Millet AB T0C 1Z0",
    "addr:housenumber":"5002",
    "addr:postcode":"t0c 1z0",
    "addr:street":"50 Ave",
    "iso:country":"CA",
    "sg:address":"5002 50 Ave",
    "sg:city":"Millet",
    "sg:classifiers":[
        {
            "category":"Shopping",
            "subcategory":"Gifts & Souvenirs",
            "type":"Retail Goods"
        }
    ],
    "sg:phone":"+1 780 387 5866",
    "sg:postcode":"T0C 1Z0",
    "sg:province":"AB",
    "sg:tags":[
        "shop"
    ],
    "wof:name":"Old Bank Stopping House Ltd",
    "wof:placetype":"venue"
},
  "geometry": {"coordinates":[-113.472359,53.095654],"type":"Point"}
}