{
  "type": "Feature",
  "properties": {
    "addr:full":"70 Dunlop Rd Newport NS B0N 2A0",
    "addr:housenumber":"70",
    "addr:postcode":"b0n 2a0",
    "addr:street":"Dunlop Rd",
    "iso:country":"CA",
    "sg:address":"70 Dunlop Rd",
    "sg:city":"Newport",
    "sg:classifiers":[
        {
            "category":"Wholesale",
            "subcategory":"Farm Supplies",
            "type":"Manufacturing & Wholesale Goods"
        }
    ],
    "sg:phone":"+1 902 757 3232",
    "sg:postcode":"B0N 2A0",
    "sg:province":"NS",
    "sg:tags":[
        "feed"
    ],
    "wof:name":"CO-OP Atlantic Feed Plant",
    "wof:placetype":"venue"
},
  "geometry": {"coordinates":[-63.9783287048,44.9654884338],"type":"Point"}
}