{
  "type": "Feature",
  "properties": {
    "iso:country":"CA",
    "sg:address":"3760 Tecumseh Rd E",
    "sg:city":"Windsor",
    "sg:classifiers":[
        {
            "category":"Personal",
            "subcategory":"Beauty Salon",
            "type":"Services"
        }
    ],
    "sg:phone":"+1 519 948 4442",
    "sg:postcode":"N8W 1H9",
    "sg:province":"ON",
    "wof:name":"Marco's Hair Design",
    "wof:placetype":"venue"
},
  "geometry": {"coordinates":[-82.97891235349999,42.3054504395],"type":"Point"}
}