{
  "type": "Feature",
  "properties": {
    "addr:full":"740 Rue Notre-Dame O # 1490 Montreal QC H3C 3X6",
    "addr:housenumber":"740",
    "addr:postcode":"h3c 3x6",
    "addr:street":"Rue Notre-Dame O # 1490",
    "iso:country":"CA",
    "sg:address":"740 Rue Notre-Dame O # 1490",
    "sg:city":"Montreal",
    "sg:classifiers":[
        {
            "category":"Professional",
            "subcategory":"Accounting & Tax Preparation",
            "type":"Services"
        }
    ],
    "sg:phone":"+1 514 849 2238",
    "sg:postcode":"H3C 3X6",
    "sg:province":"QC",
    "sg:tags":[
        "accountant"
    ],
    "wof:name":"Boily Handfield",
    "wof:placetype":"venue"
},
  "geometry": {"coordinates":[-73.5507888794,45.5127220154],"type":"Point"}
}