{
  "type": "Feature",
  "properties": {
    "addr:full":"5 MI W 1 MI N of Fairview Fairview AB T0H 1L0",
    "addr:housenumber":"1",
    "addr:postcode":"t0h 1l0",
    "addr:street":"5 Mi W;Mi N",
    "iso:country":"CA",
    "sg:address":"5 MI W 1 MI N of Fairview",
    "sg:city":"Fairview",
    "sg:classifiers":[
        {
            "category":"Farming",
            "subcategory":"Nursery",
            "type":"Manufacturing & Wholesale Goods"
        }
    ],
    "sg:phone":"+1 780 835 3352",
    "sg:postcode":"T0H 1L0",
    "sg:province":"AB",
    "sg:tags":[
        "greenhouse"
    ],
    "wof:name":"Peace Pedigreed Seed",
    "wof:placetype":"venue"
},
  "geometry": {"coordinates":[-118.392051697,56.0686187744],"type":"Point"}
}