{
  "type": "Feature",
  "properties": {
    "addr:full":"704 Major Mackenzie Dr E Richmond Hill ON L4C 1J9",
    "addr:housenumber":"704",
    "addr:postcode":"l4c 1j9",
    "addr:street":"Major Mackenzie Dr E",
    "iso:country":"CA",
    "sg:address":"704 Major Mackenzie Dr E",
    "sg:city":"Richmond Hill",
    "sg:classifiers":[
        {
            "category":"Food & Beverages",
            "subcategory":"Bakery",
            "type":"Retail Goods"
        }
    ],
    "sg:phone":"+1 905 780 2368",
    "sg:postcode":"L4C 1J9",
    "sg:province":"ON",
    "sg:tags":[
        "doughnut"
    ],
    "wof:name":"Coffee Time Donuts",
    "wof:placetype":"venue"
},
  "geometry": {"coordinates":[-79.416962,43.875839],"type":"Point"}
}