{
  "type": "Feature",
  "properties": {
    "addr:full":"1866 Triumph St Vancouver BC V5L 1K3",
    "addr:housenumber":"1866",
    "addr:postcode":"v5l 1k3",
    "addr:street":"Triumph St",
    "iso:country":"CA",
    "sg:address":"1866 Triumph St",
    "sg:city":"Vancouver",
    "sg:classifiers":[
        {
            "category":"Manufacturing",
            "subcategory":"Tools & Machinery",
            "type":"Manufacturing & Wholesale Goods"
        }
    ],
    "sg:phone":"+1 604 253 2221",
    "sg:postcode":"V5L 1K3",
    "sg:province":"BC",
    "sg:tags":[
        "pattern",
        "maker"
    ],
    "wof:name":"North American Pattern Works",
    "wof:placetype":"venue"
},
  "geometry": {"coordinates":[-123.066413879,49.2837715149],"type":"Point"}
}