{
  "type": "Feature",
  "properties": {
    "iso:country":"CA",
    "sg:address":"42 8th Ave S",
    "sg:city":"Cranbrook",
    "sg:classifiers":[
        {
            "category":"Manufacturing",
            "subcategory":"Printing",
            "type":"Manufacturing & Wholesale Goods"
        }
    ],
    "sg:phone":"+1 250 426 3032",
    "sg:postcode":"V1C 2K3",
    "sg:province":"BC",
    "sg:tags":[
        "printer"
    ],
    "wof:name":"Rocky Mountain Printers Ltd",
    "wof:placetype":"venue"
},
  "geometry": {"coordinates":[-115.770126343,49.5113449097],"type":"Point"}
}