{
  "type": "Feature",
  "properties": {
    "addr:full":"42 8th Ave S Cranbrook BC V1C 2K3",
    "addr:housenumber":"42",
    "addr:postcode":"bc v1c 2k3",
    "addr:street":"8Th Ave S",
    "iso:country":"CA",
    "sg:address":"42 8th Ave S",
    "sg:city":"Cranbrook",
    "sg:classifiers":[
        {
            "category":"Manufacturing",
            "subcategory":"Printing",
            "type":"Manufacturing & Wholesale Goods"
        }
    ],
    "sg:phone":"+1 250 426 3032",
    "sg:postcode":"V1C 2K3",
    "sg:province":"BC",
    "sg:tags":[
        "printer"
    ],
    "wof:name":"Rocky Mountain Printers Ltd",
    "wof:placetype":"venue"
},
  "geometry": {"coordinates":[-115.770126343,49.5113449097],"type":"Point"}
}