{
  "type": "Feature",
  "properties": {
    "addr:full":"21111 108 Ave NW Edmonton AB T5S 1X3",
    "addr:housenumber":"21111",
    "addr:postcode":"t5s 1x3",
    "addr:street":"108 Ave Nw",
    "iso:country":"CA",
    "sg:address":"21111 108 Ave NW",
    "sg:city":"Edmonton",
    "sg:classifiers":[
        {
            "category":"Insurance",
            "subcategory":"Insurance Agent",
            "type":"Services"
        }
    ],
    "sg:phone":"+1 780 454 4994",
    "sg:postcode":"T5S 1X3",
    "sg:province":"AB",
    "sg:tags":[
        "consultant",
        "planning",
        "financial"
    ],
    "wof:name":"Abovebaord Financial",
    "wof:placetype":"venue"
},
  "geometry": {"coordinates":[-113.682755,53.553265],"type":"Point"}
}