{
  "type": "Feature",
  "properties": {
    "addr:full":"6205 Boul Grande-Allee Brossard QC J4Z 3K1",
    "addr:housenumber":"6205",
    "addr:postcode":"j4z 3k1",
    "addr:street":"Boul Grande-Allee",
    "iso:country":"CA",
    "sg:address":"6205 Boul Grande-Allee",
    "sg:city":"Brossard",
    "sg:classifiers":[
        {
            "category":"Education",
            "subcategory":"School",
            "type":"Public Place"
        }
    ],
    "sg:phone":"+1 450 445 5463",
    "sg:postcode":"J4Z 3K1",
    "sg:province":"QC",
    "wof:name":"Ecole Privee Kinderville",
    "wof:placetype":"venue"
},
  "geometry": {"coordinates":[-73.43414300000001,45.468346],"type":"Point"}
}