{
  "type": "Feature",
  "properties": {
    "iso:country":"CA",
    "sg:city":"Victoria",
    "sg:classifiers":[
        {
            "category":"Organizations",
            "subcategory":"Religious Organization",
            "type":"Services"
        }
    ],
    "sg:phone":"+1 250 381 6866",
    "sg:postcode":"V8T 1W4",
    "sg:province":"BC",
    "sg:tags":[
        "church"
    ],
    "wof:name":"Victoria Foursquare Gospel Chr",
    "wof:placetype":"venue"
},
  "geometry": {"coordinates":[-123.364372253,48.4365081787],"type":"Point"}
}