{
  "type": "Feature",
  "properties": {
    "addr:full":"8811 Beckwith Rd Richmond BC V6X 1V4",
    "addr:housenumber":"8811",
    "addr:postcode":"v6x 1v4",
    "addr:street":"Beckwith Rd",
    "iso:country":"CA",
    "sg:address":"8811 Beckwith Rd",
    "sg:city":"Richmond",
    "sg:classifiers":[
        {
            "category":"Wholesale",
            "subcategory":"Toys & Hobbies",
            "type":"Manufacturing & Wholesale Goods"
        }
    ],
    "sg:phone":"+1 604 270 7537",
    "sg:postcode":"V6X 1V4",
    "sg:province":"BC",
    "sg:tags":[
        "wholesaler",
        "textile"
    ],
    "wof:name":"International Textiles Ltd",
    "wof:placetype":"venue"
},
  "geometry": {"coordinates":[-123.12702899999999,49.193958],"type":"Point"}
}