{
  "type": "Feature",
  "properties": {
    "addr:full":"Etobicoke ON M9W 6T7",
    "addr:postcode":"m9w 6t7",
    "iso:country":"CA",
    "sg:city":"Etobicoke",
    "sg:classifiers":[
        {
            "category":"Manufacturing",
            "subcategory":"Food",
            "type":"Manufacturing & Wholesale Goods"
        }
    ],
    "sg:phone":"+1 416 748 7611",
    "sg:postcode":"M9W 6T7",
    "sg:province":"ON",
    "sg:tags":[
        "grocer",
        "product",
        "manufacturer"
    ],
    "wof:name":"Royal Delight Foods Ltd",
    "wof:placetype":"venue"
},
  "geometry": {"coordinates":[-79.620811,43.751961],"type":"Point"}
}