{
  "type": "Feature",
  "properties": {
    "addr:full":"St Catharines ON L2R 7K8",
    "addr:postcode":"l2r 7k8",
    "iso:country":"CA",
    "sg:city":"St Catharines",
    "sg:classifiers":[
        {
            "category":"Retail",
            "subcategory":"Auto Repair",
            "type":"Services"
        }
    ],
    "sg:phone":"+1 905 687 4116",
    "sg:postcode":"L2R 7K8",
    "sg:province":"ON",
    "sg:tags":[
        "body",
        "automobile",
        "painting"
    ],
    "wof:name":"Mason's Collision & Refinish",
    "wof:placetype":"venue"
},
  "geometry": {"coordinates":[-79.229782,43.168457],"type":"Point"}
}