{
  "type": "Feature",
  "properties": {
    "iso:country":"CA",
    "sg:address":"329 Waverley St",
    "sg:city":"Ottawa",
    "sg:classifiers":[
        {
            "category":"Banks & Credit Unions",
            "subcategory":"Investment Brokerage",
            "type":"Services"
        }
    ],
    "sg:phone":"+1 613 234 8023",
    "sg:postcode":"K2P 0V9",
    "sg:province":"ON",
    "sg:tags":[
        "consultant",
        "planning",
        "financial",
        "advisory"
    ],
    "wof:name":"David Ingram & Assoc",
    "wof:placetype":"venue"
},
  "geometry": {"coordinates":[-75.69208526609999,45.4142913818],"type":"Point"}
}