{
  "type": "Feature",
  "properties": {
    "addr:full":"London ON N6H 5J9",
    "addr:postcode":"n6h 5j9",
    "iso:country":"CA",
    "sg:city":"London",
    "sg:classifiers":[
        {
            "category":"Recreation",
            "type":"Entertainment"
        }
    ],
    "sg:phone":"+1 519 474 2358",
    "sg:postcode":"N6H 5J9",
    "sg:province":"ON",
    "sg:tags":[
        "martial",
        "arts",
        "instruction"
    ],
    "wof:name":"Northern Black Dragon Martial",
    "wof:placetype":"venue"
},
  "geometry": {"coordinates":[-81.3221359253,42.9888687134],"type":"Point"}
}