{
  "type": "Feature",
  "properties": {
    "addr:full":"649 Queensland Dr SE Calgary AB T2J 4S8",
    "addr:housenumber":"649",
    "addr:postcode":"t2j 4s8",
    "addr:street":"Queensland Dr Se",
    "iso:country":"CA",
    "sg:address":"649 Queensland Dr SE",
    "sg:city":"Calgary",
    "sg:classifiers":[
        {
            "category":"Education",
            "subcategory":"School",
            "type":"Public Place"
        }
    ],
    "sg:phone":"+1 403 225 2419",
    "sg:postcode":"T2J 4S8",
    "sg:province":"AB",
    "wof:name":"Great Beginnings Preschool",
    "wof:placetype":"venue"
},
  "geometry": {"coordinates":[-114.022903,50.939796],"type":"Point"}
}