{
  "type": "Feature",
  "properties": {
    "addr:full":"Barrie ON L4M 3A5",
    "addr:postcode":"l4m 3a5",
    "iso:country":"CA",
    "sg:city":"Barrie",
    "sg:classifiers":[
        {
            "category":"Restaurant",
            "type":"Food & Drink"
        }
    ],
    "sg:phone":"+1 705 737 0522",
    "sg:postcode":"L4M 3A5",
    "sg:province":"ON",
    "wof:name":"Oscar's Restaurant",
    "wof:placetype":"venue"
},
  "geometry": {"coordinates":[-79.691078186,44.3901977539],"type":"Point"}
}