{
  "type": "Feature",
  "properties": {
    "addr:full":"303 Rang Saint-Amable Saint-Barnabe-Sud QC J0H 1G0",
    "addr:housenumber":"303",
    "addr:postcode":"j0h 1g0",
    "addr:street":"Rang Saint-Amable Saint-Barnabe-Sud",
    "iso:country":"CA",
    "sg:address":"303 Rang Saint-Amable",
    "sg:city":"Saint-Barnabe-Sud",
    "sg:classifiers":[
        {
            "category":"Manufacturing",
            "subcategory":"Tools & Machinery",
            "type":"Manufacturing & Wholesale Goods"
        }
    ],
    "sg:phone":"+1 450 792 6291",
    "sg:postcode":"J0H 1G0",
    "sg:province":"QC",
    "sg:tags":[
        "farm",
        "refrigeration",
        "contractor"
    ],
    "wof:name":"Entreprises Leblanc & Fils Inc",
    "wof:placetype":"venue"
},
  "geometry": {"coordinates":[-72.908897,45.740555],"type":"Point"}
}