{
  "type": "Feature",
  "properties": {
    "addr:full":"888 Callander Bay Dr Callander ON P0H 1H0",
    "addr:housenumber":"888",
    "addr:postcode":"p0h 1h0",
    "addr:street":"Callander Bay Dr",
    "iso:country":"CA",
    "sg:address":"888 Callander Bay Dr",
    "sg:city":"Callander",
    "sg:classifiers":[
        {
            "category":"Organizations",
            "subcategory":"Religious Organization",
            "type":"Services"
        }
    ],
    "sg:phone":"+1 705 752 1649",
    "sg:postcode":"P0H 1H0",
    "sg:province":"ON",
    "sg:tags":[
        "church"
    ],
    "wof:name":"Callander Bay Evangelical",
    "wof:placetype":"venue"
},
  "geometry": {"coordinates":[-79.36992600000001,46.234966],"type":"Point"}
}