{
  "type": "Feature",
  "properties": {
    "iso:country":"CA",
    "sg:address":"500 Willow Rd",
    "sg:city":"Guelph",
    "sg:classifiers":[
        {
            "category":"Personal",
            "subcategory":"Beauty Salon",
            "type":"Services"
        }
    ],
    "sg:phone":"+1 519 821 4040",
    "sg:postcode":"N1H 7G4",
    "sg:province":"ON",
    "sg:tags":[
        "barber"
    ],
    "wof:name":"R Moretti Barbering",
    "wof:placetype":"venue"
},
  "geometry": {"coordinates":[-80.287727356,43.5333366394],"type":"Point"}
}