{
  "type": "Feature",
  "properties": {
    "addr:full":"85 Rue Notre-Dame #201 Nicolet QC J3T 1V8",
    "addr:housenumber":"85",
    "addr:postcode":"j3t 1v8",
    "addr:street":"Rue Notre-Dame # 201",
    "iso:country":"CA",
    "sg:address":"85 Rue Notre-Dame #201",
    "sg:city":"Nicolet",
    "sg:classifiers":[
        {
            "category":"Wholesale",
            "subcategory":"Office Equipment",
            "type":"Manufacturing & Wholesale Goods"
        }
    ],
    "sg:phone":"+1 819 293 4525",
    "sg:postcode":"J3T 1V8",
    "sg:province":"QC",
    "sg:tags":[
        "accounting",
        "bookkeeping",
        "system"
    ],
    "wof:name":"Frechette Lionel & Assoc",
    "wof:placetype":"venue"
},
  "geometry": {"coordinates":[-72.61842300000001,46.226635],"type":"Point"}
}