{
  "type": "Feature",
  "properties": {
    "addr:full":"Unity SK S0K 4L0",
    "addr:postcode":"s0k 4l0",
    "iso:country":"CA",
    "sg:city":"Unity",
    "sg:classifiers":[
        {
            "category":"Personal",
            "subcategory":"Beauty Salon",
            "type":"Services"
        }
    ],
    "sg:phone":"+1 306 228 4288",
    "sg:postcode":"S0K 4L0",
    "sg:province":"SK",
    "wof:name":"Cuts'n Things",
    "wof:placetype":"venue"
},
  "geometry": {"coordinates":[-109.148056,52.442764],"type":"Point"}
}