{
  "type": "Feature",
  "properties": {
    "addr:full":"1776 Albion Rd Etobicoke ON M9V 1C1",
    "addr:housenumber":"1776",
    "addr:postcode":"m9v 1c1",
    "addr:street":"Albion Rd",
    "iso:country":"CA",
    "sg:address":"1776 Albion Rd",
    "sg:city":"Etobicoke",
    "sg:classifiers":[
        {
            "category":"Manufacturing",
            "subcategory":"Apparel",
            "type":"Manufacturing & Wholesale Goods"
        }
    ],
    "sg:phone":"+1 416 746 6200",
    "sg:postcode":"M9V 1C1",
    "sg:province":"ON",
    "sg:tags":[
        "clothing"
    ],
    "wof:name":"Canadian Garment Exporters Ltd",
    "wof:placetype":"venue"
},
  "geometry": {"coordinates":[-79.604454,43.743877],"type":"Point"}
}