{
  "type": "Feature",
  "properties": {
    "addr:full":"706 Rte Begin # 1 Saint-Anselme QC G0R 2N0",
    "addr:housenumber":"706",
    "addr:postcode":"g0r 2n0",
    "addr:street":"Rte Begin # 1",
    "iso:country":"CA",
    "sg:address":"706 Rte Begin # 1",
    "sg:city":"Saint-Anselme",
    "sg:classifiers":[
        {
            "category":"Health Services",
            "subcategory":"Doctor",
            "type":"Services"
        }
    ],
    "sg:phone":"+1 418 885 9625",
    "sg:postcode":"G0R 2N0",
    "sg:province":"QC",
    "sg:tags":[
        "clinic"
    ],
    "wof:name":"Clinique Medicale St-Anselme",
    "wof:placetype":"venue"
},
  "geometry": {"coordinates":[-70.975159,46.631676],"type":"Point"}
}