{
  "type": "Feature",
  "properties": {
    "addr:full":"1205 Nine Mile Lake Rd Torrance ON P0C 1M0",
    "addr:housenumber":"1205",
    "addr:postcode":"p0c 1m0",
    "addr:street":"Nine Mile Lake Rd",
    "iso:country":"CA",
    "sg:address":"1205 Nine Mile Lake Rd",
    "sg:city":"Torrance",
    "sg:classifiers":[
        {
            "category":"Recreation",
            "subcategory":"Marina",
            "type":"Entertainment"
        }
    ],
    "sg:phone":"+1 705 762 5303",
    "sg:postcode":"P0C 1M0",
    "sg:province":"ON",
    "wof:name":"Nine Mile Marina",
    "wof:placetype":"venue"
},
  "geometry": {"coordinates":[-79.5664978027,44.9922332764],"type":"Point"}
}