{
  "type": "Feature",
  "properties": {
    "addr:full":"1327 Rue Laviolette Trois-Rivieres QC G9A 1W5",
    "addr:housenumber":"1327",
    "addr:postcode":"g9a 1w5",
    "addr:street":"Rue Laviolette",
    "iso:country":"CA",
    "sg:address":"1327 Rue Laviolette",
    "sg:city":"Trois-Rivieres",
    "sg:classifiers":[
        {
            "category":"Personal",
            "subcategory":"Barber",
            "type":"Services"
        }
    ],
    "sg:phone":"+1 819 374 7873",
    "sg:postcode":"G9A 1W5",
    "sg:province":"QC",
    "wof:name":"Salon Pepito",
    "wof:placetype":"venue"
},
  "geometry": {"coordinates":[-72.5493392944,46.3518180847],"type":"Point"}
}