{
  "type": "Feature",
  "properties": {
    "addr:full":"Airdrie AB T4B 2X7",
    "addr:postcode":"t4b 2x7",
    "iso:country":"CA",
    "sg:city":"Airdrie",
    "sg:classifiers":[
        {
            "category":"Food & Beverages",
            "subcategory":"Groceries & Convenience Stores",
            "type":"Retail Goods"
        }
    ],
    "sg:phone":"+1 403 948 9750",
    "sg:postcode":"T4B 2X7",
    "sg:province":"AB",
    "sg:tags":[
        "grocer"
    ],
    "wof:name":"Mac's Convenience Stores Ltd",
    "wof:placetype":"venue"
},
  "geometry": {"coordinates":[-114.025115967,51.2927284241],"type":"Point"}
}