{
  "type": "Feature",
  "properties": {
    "addr:full":"464 Pembroke St W Pembroke ON K8A 5N9",
    "addr:housenumber":"464",
    "addr:postcode":"k8a 5n9",
    "addr:street":"Pembroke St W",
    "iso:country":"CA",
    "sg:address":"464 Pembroke St W",
    "sg:city":"Pembroke",
    "sg:classifiers":[
        {
            "category":"Shopping",
            "type":"Retail Goods"
        }
    ],
    "sg:phone":"+1 613 735 0389",
    "sg:postcode":"K8A 5N9",
    "sg:province":"ON",
    "sg:tags":[
        "designer",
        "hot",
        "spa",
        "tub",
        "dealer",
        "pool",
        "swimming"
    ],
    "wof:name":"Kutschke Pools Hot Tubs Spas",
    "wof:placetype":"venue"
},
  "geometry": {"coordinates":[-77.1245346069,45.8239364624],"type":"Point"}
}