{
  "type": "Feature",
  "properties": {
    "iso:country":"CA",
    "sg:city":"Calgary",
    "sg:classifiers":[
        {
            "category":"Banks & Credit Unions",
            "subcategory":"Investment Brokerage",
            "type":"Services"
        }
    ],
    "sg:phone":"+1 403 292 2875",
    "sg:postcode":"T2P 2Z2",
    "sg:province":"AB",
    "wof:name":"Td Waterhouse",
    "wof:placetype":"venue"
},
  "geometry": {"coordinates":[-114.068665,51.045837],"type":"Point"}
}