{
  "type": "Feature",
  "properties": {
    "addr:full":"950 Boul Long Clair NB E7A 2C6",
    "addr:housenumber":"950",
    "addr:postcode":"e7a 2c6",
    "addr:street":"Boul Long",
    "iso:country":"CA",
    "sg:address":"950 Boul Long",
    "sg:city":"Clair",
    "sg:classifiers":[
        {
            "category":"Freight",
            "type":"Transportation"
        }
    ],
    "sg:phone":"+1 506 992 2075",
    "sg:postcode":"E7A 2C6",
    "sg:province":"NB",
    "sg:tags":[
        "trucking"
    ],
    "wof:name":"Soucy Brothers Ltd",
    "wof:placetype":"venue"
},
  "geometry": {"coordinates":[-68.6078872681,47.2559890747],"type":"Point"}
}