{
  "type": "Feature",
  "properties": {
    "addr:full":"104 Yorkville Ave Toronto ON M5R 1B9",
    "addr:housenumber":"104",
    "addr:postcode":"m5r 1b9",
    "addr:street":"Yorkville Ave",
    "iso:country":"CA",
    "sg:address":"104 Yorkville Ave",
    "sg:city":"Toronto",
    "sg:classifiers":[
        {
            "category":"Shopping",
            "subcategory":"Optical Goods",
            "type":"Retail Goods"
        }
    ],
    "sg:phone":"+1 416 961 9589",
    "sg:postcode":"M5R 1B9",
    "sg:province":"ON",
    "sg:tags":[
        "optician"
    ],
    "wof:name":"Optical Outlook Ltd",
    "wof:placetype":"venue"
},
  "geometry": {"coordinates":[-79.39250183110001,43.6709976196],"type":"Point"}
}