{
  "type": "Feature",
  "properties": {
    "addr:full":"Sundre AB T0M 1X0",
    "addr:postcode":"t0m 1x0",
    "iso:country":"CA",
    "sg:city":"Sundre",
    "sg:classifiers":[
        {
            "category":"Building & Trades",
            "subcategory":"Cleaning & Sanitation",
            "type":"Services"
        }
    ],
    "sg:phone":"+1 403 638 4074",
    "sg:postcode":"T0M 1X0",
    "sg:province":"AB",
    "sg:tags":[
        "janitor"
    ],
    "wof:name":"Mr Mom's Cleaning Svc",
    "wof:placetype":"venue"
},
  "geometry": {"coordinates":[-114.641212,51.797192],"type":"Point"}
}