{
  "type": "Feature",
  "properties": {
    "iso:country":"CA",
    "sg:city":"Vancouver",
    "sg:classifiers":[
        {
            "category":"Personal",
            "type":"Services"
        }
    ],
    "sg:phone":"+1 604 737 4900",
    "sg:postcode":"V6H 3V1",
    "sg:province":"BC",
    "sg:tags":[
        "shopping",
        "community"
    ],
    "wof:name":"Greater Vancouver Community",
    "wof:placetype":"venue"
},
  "geometry": {"coordinates":[-123.131859,49.263363],"type":"Point"}
}