{
  "type": "Feature",
  "properties": {
    "addr:full":"Altona MB R0G 0B0",
    "addr:postcode":"r0g 0b0",
    "iso:country":"CA",
    "sg:city":"Altona",
    "sg:classifiers":[
        {
            "category":"Professional",
            "subcategory":"Accounting & Tax Preparation",
            "type":"Services"
        }
    ],
    "sg:phone":"+1 204 324 6966",
    "sg:postcode":"R0G 0B0",
    "sg:province":"MB",
    "sg:tags":[
        "return",
        "filing"
    ],
    "wof:name":"Red River Tax Svc",
    "wof:placetype":"venue"
},
  "geometry": {"coordinates":[-97.55544999999999,49.103951],"type":"Point"}
}