{
  "type": "Feature",
  "properties": {
    "addr:full":"345 Main St E Port Dover ON N0A 1N0",
    "addr:housenumber":"345",
    "addr:postcode":"n0a 1n0",
    "addr:street":"Main St E Port Dover",
    "iso:country":"CA",
    "sg:address":"345 Main St E",
    "sg:city":"Port Dover",
    "sg:classifiers":[
        {
            "category":"Shopping",
            "subcategory":"Gifts & Souvenirs",
            "type":"Retail Goods"
        }
    ],
    "sg:phone":"+1 519 583 2522",
    "sg:postcode":"N0A 1N0",
    "sg:province":"ON",
    "sg:tags":[
        "shop"
    ],
    "wof:name":"Oriental Shop",
    "wof:placetype":"venue"
},
  "geometry": {"coordinates":[-80.204407,42.787094],"type":"Point"}
}