{
  "type": "Feature",
  "properties": {
    "addr:full":"Calgary AB T1Y 5T4",
    "addr:postcode":"t1y 5t4",
    "iso:country":"CA",
    "sg:city":"Calgary",
    "sg:classifiers":[
        {
            "category":"Shopping",
            "subcategory":"Shoes",
            "type":"Retail Goods"
        }
    ],
    "sg:phone":"+1 403 280 1735",
    "sg:postcode":"T1Y 5T4",
    "sg:province":"AB",
    "wof:name":"Aldo Shoes Inc",
    "wof:placetype":"venue"
},
  "geometry": {"coordinates":[-113.982178,51.074127],"type":"Point"}
}