{
  "type": "Feature",
  "properties": {
    "addr:full":"Edmonton AB T5L 0M3",
    "addr:postcode":"t5l 0m3",
    "iso:country":"CA",
    "sg:city":"Edmonton",
    "sg:classifiers":[
        {
            "category":"Health Services",
            "subcategory":"Doctor",
            "type":"Services"
        }
    ],
    "sg:phone":"+1 780 455 8141",
    "sg:postcode":"T5L 0M3",
    "sg:province":"AB",
    "sg:tags":[
        "dentist"
    ],
    "wof:name":"Robertson, Donald J DDS",
    "wof:placetype":"venue"
},
  "geometry": {"coordinates":[-113.536140442,53.5706825256],"type":"Point"}
}