{
  "type": "Feature",
  "properties": {
    "iso:country":"CA",
    "sg:city":"Port Coquitlam",
    "sg:classifiers":[
        {
            "category":"Health Services",
            "subcategory":"Medical Lab",
            "type":"Services"
        }
    ],
    "sg:phone":"+1 604 944 7754",
    "sg:postcode":"V3C 6C1",
    "sg:province":"BC",
    "sg:tags":[
        "laboratory"
    ],
    "wof:name":"B C Bio-Medical Labs Ltd",
    "wof:placetype":"venue"
},
  "geometry": {"coordinates":[-122.77782440199999,49.2609786987],"type":"Point"}
}