{
  "type": "Feature",
  "properties": {
    "addr:full":"22 Rue DE Terrebonne Mercier QC J6R 1C4",
    "addr:housenumber":"22",
    "addr:postcode":"j6r 1c4",
    "addr:street":"Rue De Terrebonne",
    "iso:country":"CA",
    "sg:address":"22 Rue DE Terrebonne",
    "sg:city":"Mercier",
    "sg:classifiers":[
        {
            "category":"Manufacturing",
            "subcategory":"Tools & Machinery",
            "type":"Manufacturing & Wholesale Goods"
        }
    ],
    "sg:phone":"+1 450 699 6919",
    "sg:postcode":"J6R 1C4",
    "sg:province":"QC",
    "sg:tags":[
        "equipment",
        "system",
        "automation"
    ],
    "wof:name":"Autogest Controle Ltee",
    "wof:placetype":"venue"
},
  "geometry": {"coordinates":[-73.75013,45.307205],"type":"Point"}
}