{
  "type": "Feature",
  "properties": {
    "addr:full":"6 Albert St Hastings ON K0L 1Y0",
    "addr:housenumber":"6",
    "addr:postcode":"k0l 1y0",
    "addr:street":"Albert St",
    "iso:country":"CA",
    "sg:address":"6 Albert St",
    "sg:city":"Hastings",
    "sg:classifiers":[
        {
            "category":"Education",
            "subcategory":"Library",
            "type":"Public Place"
        }
    ],
    "sg:phone":"+1 705 696 2111",
    "sg:postcode":"K0L 1Y0",
    "sg:province":"ON",
    "wof:name":"Hastings Branch Library",
    "wof:placetype":"venue"
},
  "geometry": {"coordinates":[-77.957909,44.311089],"type":"Point"}
}