{
  "type": "Feature",
  "properties": {
    "addr:full":"704 Main St E Swan River MB R0L 1Z0",
    "addr:housenumber":"704",
    "addr:postcode":"r0l 1z0",
    "addr:street":"Main St E Swan",
    "iso:country":"CA",
    "sg:address":"704 Main St E",
    "sg:city":"Swan River",
    "sg:classifiers":[
        {
            "category":"Manufacturing",
            "subcategory":"Printing",
            "type":"Manufacturing & Wholesale Goods"
        }
    ],
    "sg:phone":"+1 204 734 3858",
    "sg:postcode":"R0L 1Z0",
    "sg:province":"MB",
    "sg:tags":[
        "newspaper"
    ],
    "wof:name":"Star & Times",
    "wof:placetype":"venue"
},
  "geometry": {"coordinates":[-101.26594543500001,52.1059799194],"type":"Point"}
}