{
  "type": "Feature",
  "properties": {
    "addr:full":"Vancouver BC V5N 5N8",
    "addr:postcode":"v5n 5n8",
    "iso:country":"CA",
    "sg:city":"Vancouver",
    "sg:classifiers":[
        {
            "category":"Professional",
            "subcategory":"Business Services",
            "type":"Services"
        }
    ],
    "sg:phone":"+1 604 431 6468",
    "sg:postcode":"V5N 5N8",
    "sg:province":"BC",
    "sg:tags":[
        "drafting"
    ],
    "wof:name":"Edward Palad & Assoc",
    "wof:placetype":"venue"
},
  "geometry": {"coordinates":[-123.06379699999999,49.244236],"type":"Point"}
}