{
  "type": "Feature",
  "properties": {
    "addr:full":"1342 Dundas St E Whitby ON L1N 2K5",
    "addr:housenumber":"1342",
    "addr:postcode":"l1n 2k5",
    "addr:street":"Dundas St E",
    "iso:country":"CA",
    "sg:address":"1342 Dundas St E",
    "sg:city":"Whitby",
    "sg:classifiers":[
        {
            "category":"Autos & Motor Vehicles",
            "subcategory":"Fuel & Gas Station",
            "type":"Retail Goods"
        }
    ],
    "sg:phone":"+1 905 430 7473",
    "sg:postcode":"L1N 2K5",
    "sg:province":"ON",
    "sg:tags":[
        "oil"
    ],
    "wof:name":"Canadian Tire Gas Bar",
    "wof:placetype":"venue"
},
  "geometry": {"coordinates":[-78.919571,43.885128],"type":"Point"}
}