{
  "type": "Feature",
  "properties": {
    "addr:full":"212 Main St Whitehorse YT Y1A 2B1",
    "addr:housenumber":"212",
    "addr:postcode":"y1a 2b1",
    "addr:street":"Main St",
    "iso:country":"CA",
    "sg:address":"212 Main St",
    "sg:city":"Whitehorse",
    "sg:classifiers":[
        {
            "category":"Restaurant",
            "type":"Food & Drink"
        }
    ],
    "sg:phone":"+1 867 393 5000",
    "sg:postcode":"Y1A 2B1",
    "sg:province":"YT",
    "wof:name":"Subway Sandwiches & Salads",
    "wof:placetype":"venue"
},
  "geometry": {"coordinates":[-135.05279540999999,60.7197418213],"type":"Point"}
}