{
  "type": "Feature",
  "properties": {
    "iso:country":"CA",
    "sg:city":"Bouctouche",
    "sg:classifiers":[
        {
            "category":"Shopping",
            "subcategory":"Department Store",
            "type":"Retail Goods"
        }
    ],
    "sg:phone":"+1 506 743 8586",
    "sg:postcode":"E4S 3K4",
    "sg:province":"NB",
    "wof:name":"Magasins Saan Ltee",
    "wof:placetype":"venue"
},
  "geometry": {"coordinates":[-64.733299,46.464741],"type":"Point"}
}