{
  "type": "Feature",
  "properties": {
    "addr:full":"21 Perini Rd Elliot Lake ON P5A 2T1",
    "addr:housenumber":"21",
    "addr:postcode":"p5a 2t1",
    "addr:street":"Perini Rd",
    "iso:country":"CA",
    "sg:address":"21 Perini Rd",
    "sg:city":"Elliot Lake",
    "sg:classifiers":[
        {
            "category":"Building & Trades",
            "subcategory":"Plumbing",
            "type":"Services"
        }
    ],
    "sg:phone":"+1 705 461 1793",
    "sg:postcode":"P5A 2T1",
    "sg:province":"ON",
    "sg:tags":[
        "conditioning",
        "air",
        "appliance",
        "system",
        "contractor"
    ],
    "wof:name":"Appliance Busters Ltd",
    "wof:placetype":"venue"
},
  "geometry": {"coordinates":[-82.638367,46.377312],"type":"Point"}
}