{
  "type": "Feature",
  "properties": {
    "iso:country":"CA",
    "sg:address":"7300 11 St SE",
    "sg:city":"Calgary",
    "sg:classifiers":[
        {
            "category":"Home & Garden",
            "subcategory":"Furniture",
            "type":"Retail Goods"
        }
    ],
    "sg:phone":"+1 403 253 1000",
    "sg:postcode":"T2H 2S9",
    "sg:province":"AB",
    "wof:name":"LA-Z-Boy Furniture Galleries",
    "wof:placetype":"venue"
},
  "geometry": {"coordinates":[-114.039337158,50.9883460999],"type":"Point"}
}