{
  "type": "Feature",
  "properties": {
    "iso:country":"CA",
    "sg:address":"460 Forestlawn Rd",
    "sg:city":"Waterloo",
    "sg:classifiers":[
        {
            "category":"Professional",
            "subcategory":"Computer Services",
            "type":"Services"
        }
    ],
    "sg:phone":"+1 519 746 7925",
    "sg:postcode":"N2K 2J6",
    "sg:province":"ON",
    "sg:tags":[
        "consultant"
    ],
    "wof:name":"Archelon Inc",
    "wof:placetype":"venue"
},
  "geometry": {"coordinates":[-80.4952468872,43.5015411377],"type":"Point"}
}