{
  "type": "Feature",
  "properties": {
    "addr:full":"Dutton ON N0L 1J0",
    "addr:postcode":"n0l 1j0",
    "iso:country":"CA",
    "sg:city":"Dutton",
    "sg:classifiers":[
        {
            "category":"Professional",
            "subcategory":"Advertising",
            "type":"Services"
        }
    ],
    "sg:phone":"+1 519 762 3993",
    "sg:postcode":"N0L 1J0",
    "sg:province":"ON",
    "sg:tags":[
        "publisher"
    ],
    "wof:name":"Horsetrader",
    "wof:placetype":"venue"
},
  "geometry": {"coordinates":[-81.51499938960001,42.6516685486],"type":"Point"}
}