{
  "type": "Feature",
  "properties": {
    "addr:full":"Scarborough ON M1L 4J5",
    "addr:postcode":"m1l 4j5",
    "iso:country":"CA",
    "sg:city":"Scarborough",
    "sg:classifiers":[
        {
            "category":"Retail",
            "subcategory":"Auto Repair",
            "type":"Services"
        }
    ],
    "sg:phone":"+1 416 751 6186",
    "sg:postcode":"M1L 4J5",
    "sg:province":"ON",
    "sg:tags":[
        "body",
        "automobile",
        "painting"
    ],
    "wof:name":"Mc Kenzie Auto Body Repair Ltd",
    "wof:placetype":"venue"
},
  "geometry": {"coordinates":[-79.28289794920001,43.7246513367],"type":"Point"}
}