{
  "type": "Feature",
  "properties": {
    "iso:country":"CA",
    "sg:address":"7125 Boul Newman",
    "sg:city":"Lasalle",
    "sg:classifiers":[
        {
            "category":"Shopping",
            "subcategory":"Hobbies, Toys, & Games",
            "type":"Retail Goods"
        }
    ],
    "sg:phone":"+1 514 366 4532",
    "sg:postcode":"H8N 2K3",
    "sg:province":"QC",
    "wof:name":"Toys R US",
    "wof:placetype":"venue"
},
  "geometry": {"coordinates":[-73.614906311,45.4439964294],"type":"Point"}
}