{
  "type": "Feature",
  "properties": {
    "addr:full":"2385 Rue DE LA Metropole Longueuil QC J4G 1E5",
    "addr:housenumber":"2385",
    "addr:postcode":"j4g 1e5",
    "addr:street":"Rue De La Metropole",
    "iso:country":"CA",
    "sg:address":"2385 Rue DE LA Metropole",
    "sg:city":"Longueuil",
    "sg:classifiers":[
        {
            "category":"Building & Trades",
            "subcategory":"Construction",
            "type":"Services"
        }
    ],
    "sg:phone":"+1 450 670 4949",
    "sg:postcode":"J4G 1E5",
    "sg:province":"QC",
    "sg:tags":[
        "painter"
    ],
    "wof:name":"Peintures Pro-Spec",
    "wof:placetype":"venue"
},
  "geometry": {"coordinates":[-73.47146606450001,45.5730056763],"type":"Point"}
}