{
  "type": "Feature",
  "properties": {
    "iso:country":"CA",
    "sg:city":"Kugaaruk",
    "sg:classifiers":[
        {
            "category":"Government",
            "subcategory":"Office",
            "type":"Public Place"
        }
    ],
    "sg:phone":"+1 867 769 7900",
    "sg:postcode":"X0B 1K0",
    "sg:province":"NU",
    "wof:name":"NT Social Svc Comm Social Wrk",
    "wof:placetype":"venue"
},
  "geometry": {"coordinates":[-89.8267211914,68.5329818726],"type":"Point"}
}