{
  "type": "Feature",
  "properties": {
    "iso:country":"CA",
    "sg:city":"Mont-Saint-Hilaire",
    "sg:classifiers":[
        {
            "category":"Manufacturing",
            "subcategory":"Jewelry",
            "type":"Manufacturing & Wholesale Goods"
        }
    ],
    "sg:phone":"+1 450 464 2512",
    "sg:postcode":"J3H 5V3",
    "sg:province":"QC",
    "sg:tags":[
        "diamond",
        "cutting",
        "jeweler"
    ],
    "wof:name":"Almanzor Bijouterie",
    "wof:placetype":"venue"
},
  "geometry": {"coordinates":[-73.18483,45.564388],"type":"Point"}
}