{
  "type": "Feature",
  "properties": {
    "addr:full":"6218 London Rd Smithville ON L0R 2A0",
    "addr:housenumber":"6218",
    "addr:postcode":"l0r 2a0",
    "addr:street":"London Rd",
    "iso:country":"CA",
    "sg:address":"6218 London Rd",
    "sg:city":"Smithville",
    "sg:classifiers":[
        {
            "category":"Government",
            "subcategory":"Office",
            "type":"Public Place"
        }
    ],
    "sg:phone":"+1 905 957 3396",
    "sg:postcode":"L0R 2A0",
    "sg:province":"ON",
    "sg:tags":[
        "village"
    ],
    "wof:name":"West Lincoln Road Supt Ofc",
    "wof:placetype":"venue"
},
  "geometry": {"coordinates":[-79.53634599999999,43.102604],"type":"Point"}
}