{
  "type": "Feature",
  "properties": {
    "iso:country":"CA",
    "sg:address":"8624 Boul Saint-Laurent",
    "sg:city":"Montreal",
    "sg:classifiers":[
        {
            "category":"Personal",
            "subcategory":"Tanning Parlor",
            "type":"Services"
        }
    ],
    "sg:phone":"+1 514 382 7641",
    "sg:postcode":"H2P 2N4",
    "sg:province":"QC",
    "sg:tags":[
        "salon"
    ],
    "wof:name":"Extoica Bronzage",
    "wof:placetype":"venue"
},
  "geometry": {"coordinates":[-73.639664,45.541245],"type":"Point"}
}