{
  "type": "Feature",
  "properties": {
    "addr:full":"6206 Rue Sherbrooke O Montreal QC H4B 1M2",
    "addr:housenumber":"6206",
    "addr:postcode":"h4b 1m2",
    "addr:street":"Rue Sherbrooke O",
    "iso:country":"CA",
    "sg:address":"6206 Rue Sherbrooke O",
    "sg:city":"Montreal",
    "sg:classifiers":[
        {
            "category":"Shopping",
            "subcategory":"Florist",
            "type":"Retail Goods"
        }
    ],
    "sg:phone":"+1 514 488 1147",
    "sg:postcode":"H4B 1M2",
    "sg:province":"QC",
    "wof:name":"Jardin DE Melissa",
    "wof:placetype":"venue"
},
  "geometry": {"coordinates":[-73.544921875,45.5792274475],"type":"Point"}
}