{
  "type": "Feature",
  "properties": {
    "addr:full":"445 Norton Ave Miami MB R0G 1H0",
    "addr:housenumber":"445",
    "addr:postcode":"r0g 1h0",
    "addr:street":"Norton Ave",
    "iso:country":"CA",
    "sg:address":"445 Norton Ave",
    "sg:city":"Miami",
    "sg:classifiers":[
        {
            "category":"Personal",
            "subcategory":"Beauty Salon",
            "type":"Services"
        }
    ],
    "sg:phone":"+1 204 435 2399",
    "sg:postcode":"R0G 1H0",
    "sg:province":"MB",
    "wof:name":"Shear Magic",
    "wof:placetype":"venue"
},
  "geometry": {"coordinates":[-98.243416,49.371086],"type":"Point"}
}