{
  "type": "Feature",
  "properties": {
    "addr:full":"Scarborough ON M1C 1L5",
    "addr:postcode":"m1c 1l5",
    "iso:country":"CA",
    "sg:city":"Scarborough",
    "sg:classifiers":[
        {
            "category":"Retail",
            "subcategory":"Auto Repair",
            "type":"Services"
        }
    ],
    "sg:phone":"+1 416 283 1843",
    "sg:postcode":"M1C 1L5",
    "sg:province":"ON",
    "sg:tags":[
        "repairing",
        "automobile"
    ],
    "wof:name":"Mosher's Auto Svc",
    "wof:placetype":"venue"
},
  "geometry": {"coordinates":[-79.15537999999999,43.792919],"type":"Point"}
}