{
  "type": "Feature",
  "properties": {
    "iso:country":"CA",
    "sg:address":"15 Main St N",
    "sg:city":"Preeceville",
    "sg:classifiers":[
        {
            "category":"Restaurant",
            "type":"Food & Drink"
        }
    ],
    "sg:phone":"+1 306 547 3338",
    "sg:postcode":"S0A 3B0",
    "sg:province":"SK",
    "wof:name":"One's Cafe",
    "wof:placetype":"venue"
},
  "geometry": {"coordinates":[-102.668121,51.95631],"type":"Point"}
}