{
  "type": "Feature",
  "properties": {
    "addr:full":"7 Parnell Ave Scarborough ON M1K 1B1",
    "addr:housenumber":"7",
    "addr:postcode":"m1k 1b1",
    "addr:street":"Parnell Ave",
    "iso:country":"CA",
    "sg:address":"7 Parnell Ave",
    "sg:city":"Scarborough",
    "sg:classifiers":[
        {
            "category":"Manufacturing",
            "subcategory":"Food",
            "type":"Manufacturing & Wholesale Goods"
        }
    ],
    "sg:phone":"+1 416 266 5544",
    "sg:postcode":"M1K 1B1",
    "sg:province":"ON",
    "sg:tags":[
        "bakery",
        "prod",
        "product",
        "manufacturer"
    ],
    "wof:name":"Honeycrust Pie CO Ltd",
    "wof:placetype":"venue"
},
  "geometry": {"coordinates":[-79.2660827637,43.7056121826],"type":"Point"}
}