{
  "type": "Feature",
  "properties": {
    "iso:country":"CA",
    "sg:address":"378 King St W",
    "sg:city":"Oshawa",
    "sg:classifiers":[
        {
            "category":"Building & Trades",
            "subcategory":"Construction",
            "type":"Services"
        }
    ],
    "sg:phone":"+1 905 728 9471",
    "sg:postcode":"L1J 2J9",
    "sg:province":"ON",
    "sg:tags":[
        "contractor"
    ],
    "wof:name":"Michael Zygocki Ltd",
    "wof:placetype":"venue"
},
  "geometry": {"coordinates":[-78.87738800050001,43.8945655823],"type":"Point"}
}