{
  "type": "Feature",
  "properties": {
    "addr:full":"1301 Rue Principale Canton-DE-Granby QC J2G 8C8",
    "addr:housenumber":"1301",
    "addr:postcode":"j2g 8c8",
    "addr:street":"Rue Principale",
    "iso:country":"CA",
    "sg:address":"1301 Rue Principale",
    "sg:city":"Canton-DE-Granby",
    "sg:classifiers":[
        {
            "category":"Shopping",
            "type":"Retail Goods"
        }
    ],
    "sg:phone":"+1 450 776 1687",
    "sg:postcode":"J2G 8C8",
    "sg:province":"QC",
    "sg:tags":[
        "miscellaneous",
        "store"
    ],
    "wof:name":"Reises Lamontagne Real Inc",
    "wof:placetype":"venue"
},
  "geometry": {"coordinates":[-72.784119,45.421726],"type":"Point"}
}