{
  "type": "Feature",
  "properties": {
    "iso:country":"CA",
    "sg:address":"1341 Rue Provinciale",
    "sg:city":"Quebec",
    "sg:classifiers":[
        {
            "category":"Building & Trades",
            "subcategory":"Electrical",
            "type":"Services"
        }
    ],
    "sg:phone":"+1 418 681 7787",
    "sg:postcode":"G1N 4A1",
    "sg:province":"QC",
    "sg:tags":[
        "electric",
        "contractor"
    ],
    "wof:name":"Prl Electrique Inc",
    "wof:placetype":"venue"
},
  "geometry": {"coordinates":[-71.263985,46.802433],"type":"Point"}
}