{
  "type": "Feature",
  "properties": {
    "iso:country":"CA",
    "sg:city":"North Vancouver",
    "sg:classifiers":[
        {
            "category":"Restaurant",
            "type":"Food & Drink"
        }
    ],
    "sg:phone":"+1 604 988 2888",
    "sg:postcode":"V7P 1S3",
    "sg:province":"BC",
    "sg:tags":[
        "parlor",
        "ice",
        "cream"
    ],
    "wof:name":"Dairy Queen",
    "wof:placetype":"venue"
},
  "geometry": {"coordinates":[-123.09912872300001,49.3225708008],"type":"Point"}
}