{
  "type": "Feature",
  "properties": {
    "addr:full":"62 Douglas Rd Richmond Hill ON L4E 3G9",
    "addr:housenumber":"62",
    "addr:postcode":"l4e 3g9",
    "addr:street":"Douglas Rd",
    "iso:country":"CA",
    "sg:address":"62 Douglas Rd",
    "sg:city":"Richmond Hill",
    "sg:classifiers":[
        {
            "category":"Building & Trades",
            "subcategory":"Construction",
            "type":"Services"
        }
    ],
    "sg:phone":"+1 905 773 7491",
    "sg:postcode":"L4E 3G9",
    "sg:province":"ON",
    "sg:tags":[
        "general",
        "contractor"
    ],
    "wof:name":"Kitte Construction Inc",
    "wof:placetype":"venue"
},
  "geometry": {"coordinates":[-79.44998168950001,43.9438858032],"type":"Point"}
}