{
  "type": "Feature",
  "properties": {
    "addr:full":"1 Centrepointe Dr # 407 Nepean ON K2G 6E2",
    "addr:housenumber":"1;407",
    "addr:postcode":"k2g 6e2",
    "addr:street":"Centrepointe Dr #",
    "iso:country":"CA",
    "sg:address":"1 Centrepointe Dr # 407",
    "sg:city":"Nepean",
    "sg:classifiers":[
        {
            "category":"Health Services",
            "subcategory":"Doctor",
            "type":"Services"
        }
    ],
    "sg:phone":"+1 613 224 1223",
    "sg:postcode":"K2G 6E2",
    "sg:province":"ON",
    "sg:tags":[
        "physician",
        "surgeon"
    ],
    "wof:name":"Ottawa Headache Ctr Research",
    "wof:placetype":"venue"
},
  "geometry": {"coordinates":[-75.7688903809,45.3483963013],"type":"Point"}
}