{
  "type": "Feature",
  "properties": {
    "addr:full":"70 Acorn Way Cambridge ON N1R 8M5",
    "addr:housenumber":"70",
    "addr:postcode":"n1r 8m5",
    "addr:street":"Acorn Way",
    "iso:country":"CA",
    "sg:address":"70 Acorn Way",
    "sg:city":"Cambridge",
    "sg:classifiers":[
        {
            "category":"Education",
            "subcategory":"School",
            "type":"Public Place"
        }
    ],
    "sg:phone":"+1 519 621 6680",
    "sg:postcode":"N1R 8M5",
    "sg:province":"ON",
    "wof:name":"Christ the King School",
    "wof:placetype":"venue"
},
  "geometry": {"coordinates":[-80.307327,43.388168],"type":"Point"}
}