{
  "type": "Feature",
  "properties": {
    "addr:full":"1251 Prince St Truro NS B2N 1J5",
    "addr:housenumber":"1251",
    "addr:postcode":"b2n 1j5",
    "addr:street":"Prince St",
    "iso:country":"CA",
    "sg:address":"1251 Prince St",
    "sg:city":"Truro",
    "sg:classifiers":[
        {
            "category":"Food & Beverages",
            "subcategory":"Groceries & Convenience Stores",
            "type":"Retail Goods"
        }
    ],
    "sg:phone":"+1 902 893 0383",
    "sg:postcode":"B2N 1J5",
    "sg:province":"NS",
    "sg:tags":[
        "grocer"
    ],
    "wof:name":"Needs Convenience Store",
    "wof:placetype":"venue"
},
  "geometry": {"coordinates":[-63.257389,45.364693],"type":"Point"}
}