{
  "type": "Feature",
  "properties": {
    "addr:full":"240 Brock St Kingston ON K7L 1S4",
    "addr:housenumber":"240",
    "addr:postcode":"k7l 1s4",
    "addr:street":"Brock St",
    "iso:country":"CA",
    "sg:address":"240 Brock St",
    "sg:city":"Kingston",
    "sg:classifiers":[
        {
            "category":"Organizations",
            "subcategory":"Non-profit Organization",
            "type":"Services"
        }
    ],
    "sg:phone":"+1 613 549 6461",
    "sg:postcode":"K7L 1S4",
    "sg:province":"ON",
    "sg:tags":[
        "addiction",
        "treatment",
        "center"
    ],
    "wof:name":"Detox Centre",
    "wof:placetype":"venue"
},
  "geometry": {"coordinates":[-76.4886398315,44.231388092],"type":"Point"}
}