{
  "type": "Feature",
  "properties": {
    "addr:full":"1550 Rue DE LA Pointe-Aux-Liev Quebec QC G1L 4M8",
    "addr:housenumber":"1550",
    "addr:postcode":"g1l 4m8",
    "addr:street":"Rue De La Pointe-Aux-Liev",
    "iso:country":"CA",
    "sg:address":"1550 Rue DE LA Pointe-Aux-Liev",
    "sg:city":"Quebec",
    "sg:classifiers":[
        {
            "category":"Health Services",
            "subcategory":"Nursing And Care Facility",
            "type":"Services"
        }
    ],
    "sg:phone":"+1 418 529 5511",
    "sg:postcode":"G1L 4M8",
    "sg:province":"QC",
    "sg:tags":[
        "social",
        "home",
        "welfare",
        "rest",
        "organization"
    ],
    "wof:name":"Residence Louis Hebert",
    "wof:placetype":"venue"
},
  "geometry": {"coordinates":[-71.244362,46.824337],"type":"Point"}
}