{
  "type": "Feature",
  "properties": {
    "iso:country":"CA",
    "sg:address":"14 O'Connor Cres",
    "sg:city":"Kindersley",
    "sg:classifiers":[
        {
            "category":"Personal",
            "subcategory":"Beauty Salon",
            "type":"Services"
        }
    ],
    "sg:phone":"+1 306 463 6254",
    "sg:postcode":"S0L 1S1",
    "sg:province":"SK",
    "wof:name":"Sandy's Hair Salon",
    "wof:placetype":"venue"
},
  "geometry": {"coordinates":[-109.13746643099999,51.463218689],"type":"Point"}
}