{
  "type": "Feature",
  "properties": {
    "addr:full":"1847 Boul Perrot Notre-Dame-DE-L'Ile-Perrot QC J7V 8P4",
    "addr:housenumber":"1847",
    "addr:postcode":"j7v 8p4",
    "addr:street":"Boul Perrot Notre-Dame-De-L'Ile-Perrot",
    "iso:country":"CA",
    "sg:address":"1847 Boul Perrot",
    "sg:city":"Notre-Dame-DE-L'Ile-Perrot",
    "sg:classifiers":[
        {
            "category":"Food & Beverages",
            "subcategory":"Groceries & Convenience Stores",
            "type":"Retail Goods"
        }
    ],
    "sg:phone":"+1 514 425 3650",
    "sg:postcode":"J7V 8P4",
    "sg:province":"QC",
    "wof:name":"Depanneur Atlantide",
    "wof:placetype":"venue"
},
  "geometry": {"coordinates":[-73.95536800000001,45.393764],"type":"Point"}
}