{
  "type": "Feature",
  "properties": {
    "iso:country":"CA",
    "sg:address":"1847 Boul Perrot",
    "sg:city":"Notre-Dame-DE-L'Ile-Perrot",
    "sg:classifiers":[
        {
            "category":"Food & Beverages",
            "subcategory":"Groceries & Convenience Stores",
            "type":"Retail Goods"
        }
    ],
    "sg:phone":"+1 514 425 3650",
    "sg:postcode":"J7V 8P4",
    "sg:province":"QC",
    "wof:name":"Depanneur Atlantide",
    "wof:placetype":"venue"
},
  "geometry": {"coordinates":[-73.955368,45.393764],"type":"Point"}
}