{
  "type": "Feature",
  "properties": {
    "addr:full":"160 116 Rte Saint-Agapit QC G0S 1Z0",
    "addr:housenumber":"116",
    "addr:postcode":"g0s 1z0",
    "addr:street":"Rte Saint-Agapit",
    "iso:country":"CA",
    "sg:address":"160 116 Rte",
    "sg:city":"Saint-Agapit",
    "sg:classifiers":[
        {
            "category":"Wholesale",
            "subcategory":"Stationery",
            "type":"Manufacturing & Wholesale Goods"
        }
    ],
    "sg:phone":"+1 418 888 4453",
    "sg:postcode":"G0S 1Z0",
    "sg:province":"QC",
    "sg:tags":[
        "sanitary",
        "product",
        "supply"
    ],
    "wof:name":"Produits Debout Inc",
    "wof:placetype":"venue"
},
  "geometry": {"coordinates":[-71.40387699999999,46.576576],"type":"Point"}
}