{
  "type": "Feature",
  "properties": {
    "addr:full":"400 Boul Saint-Joseph E Montreal QC H2J 1J5",
    "addr:housenumber":"400",
    "addr:postcode":"h2j 1j5",
    "addr:street":"Boul Saint-Joseph E",
    "iso:country":"CA",
    "sg:address":"400 Boul Saint-Joseph E",
    "sg:city":"Montreal",
    "sg:classifiers":[
        {
            "category":"Health Services",
            "subcategory":"Doctor",
            "type":"Services"
        }
    ],
    "sg:phone":"+1 514 288 3421",
    "sg:postcode":"H2J 1J5",
    "sg:province":"QC",
    "sg:tags":[
        "clinic",
        "chiropractor"
    ],
    "wof:name":"Clinique Chiropratique St Jose",
    "wof:placetype":"venue"
},
  "geometry": {"coordinates":[-73.5876998901,45.5262298584],"type":"Point"}
}