{
  "type": "Feature",
  "properties": {
    "addr:full":"Mayfield Hunter River PE C0A 1N0",
    "addr:postcode":"c0a 1n0",
    "iso:country":"CA",
    "sg:address":"Mayfield",
    "sg:city":"Hunter River",
    "sg:classifiers":[
        {
            "category":"Real Estate",
            "subcategory":"Architect",
            "type":"Services"
        }
    ],
    "sg:phone":"+1 902 963 3221",
    "sg:postcode":"C0A 1N0",
    "sg:province":"PE",
    "wof:name":"W D Lawrence Architecture Inc",
    "wof:placetype":"venue"
},
  "geometry": {"coordinates":[-63.343147,46.351761],"type":"Point"}
}