{
  "type": "Feature",
  "properties": {
    "addr:full":"1232 Yonge St Toronto ON M4T 1W3",
    "addr:housenumber":"1232",
    "addr:postcode":"m4t 1w3",
    "addr:street":"Yonge St",
    "iso:country":"CA",
    "sg:address":"1232 Yonge St",
    "sg:city":"Toronto",
    "sg:classifiers":[
        {
            "category":"Personal",
            "type":"Services"
        }
    ],
    "sg:phone":"+1 416 413 0020",
    "sg:postcode":"M4T 1W3",
    "sg:province":"ON",
    "sg:tags":[
        "therapist",
        "massage"
    ],
    "wof:name":"Summerhill Massage Therapy",
    "wof:placetype":"venue"
},
  "geometry": {"coordinates":[-79.391975,43.682514],"type":"Point"}
}