{
  "type": "Feature",
  "properties": {
    "addr:full":"350 Government Rd E Kapuskasing ON P5N 2X7",
    "addr:housenumber":"350",
    "addr:postcode":"p5n 2x7",
    "addr:street":"Government Rd E",
    "iso:country":"CA",
    "sg:address":"350 Government Rd E",
    "sg:city":"Kapuskasing",
    "sg:classifiers":[
        {
            "category":"Restaurant",
            "type":"Food & Drink"
        }
    ],
    "sg:phone":"+1 705 337 5221",
    "sg:postcode":"P5N 2X7",
    "sg:province":"ON",
    "wof:name":"Mc Donald's",
    "wof:placetype":"venue"
},
  "geometry": {"coordinates":[-82.3770065308,49.3997535706],"type":"Point"}
}