{
  "type": "Feature",
  "properties": {
    "addr:full":"63451 Flood Hope Rd Hope BC V0X 1L2",
    "addr:postcode":"63451;v0x 1l2",
    "addr:street":"Flood Hope Rd",
    "iso:country":"CA",
    "sg:address":"63451 Flood Hope Rd",
    "sg:city":"Hope",
    "sg:classifiers":[
        {
            "category":"Manufacturing",
            "subcategory":"Building Materials",
            "type":"Manufacturing & Wholesale Goods"
        }
    ],
    "sg:phone":"+1 604 869 3376",
    "sg:postcode":"V0X 1L2",
    "sg:province":"BC",
    "wof:name":"Tradesman Millworks",
    "wof:placetype":"venue"
},
  "geometry": {"coordinates":[-121.482338,49.36586],"type":"Point"}
}