{
  "type": "Feature",
  "properties": {
    "addr:full":"20717 Downie Line Rodney ON N0L 2C0",
    "addr:housenumber":"20717",
    "addr:postcode":"n0l 2c0",
    "addr:street":"Downie Line",
    "iso:country":"CA",
    "sg:address":"20717 Downie Line",
    "sg:city":"Rodney",
    "sg:classifiers":[
        {
            "category":"Building & Trades",
            "subcategory":"Construction",
            "type":"Services"
        }
    ],
    "sg:phone":"+1 519 785 2087",
    "sg:postcode":"N0L 2C0",
    "sg:province":"ON",
    "sg:tags":[
        "excavating",
        "tank",
        "septic",
        "contractor"
    ],
    "wof:name":"Mc Coll Excavating & Concrete",
    "wof:placetype":"venue"
},
  "geometry": {"coordinates":[-81.727531,42.554798],"type":"Point"}
}