{
  "type": "Feature",
  "properties": {
    "iso:country":"CA",
    "sg:city":"Winnipeg",
    "sg:classifiers":[
        {
            "category":"Professional",
            "subcategory":"Lawyer & Legal Services",
            "type":"Services"
        }
    ],
    "sg:phone":"+1 204 885 5980",
    "sg:postcode":"R3R 0G7",
    "sg:province":"MB",
    "sg:tags":[
        "attorney"
    ],
    "wof:name":"Winters, Edward N",
    "wof:placetype":"venue"
},
  "geometry": {"coordinates":[-97.283073,49.857498],"type":"Point"}
}