{
  "type": "Feature",
  "properties": {
    "addr:full":"4 Rue Du College Saint-Hubert-Riviere-Du-Loup QC G0L 3L0",
    "addr:housenumber":"4",
    "addr:postcode":"g0l 3l0",
    "addr:street":"Rue Du College Saint-Hubert-Riviere-Du-Loup",
    "iso:country":"CA",
    "sg:address":"4 Rue Du College",
    "sg:city":"Saint-Hubert-Riviere-Du-Loup",
    "sg:classifiers":[
        {
            "category":"Recreation",
            "type":"Entertainment"
        }
    ],
    "sg:phone":"+1 418 497 2223",
    "sg:postcode":"G0L 3L0",
    "sg:province":"QC",
    "sg:tags":[
        "center",
        "government"
    ],
    "wof:name":"St-Hubert Comite Des Loisirs",
    "wof:placetype":"venue"
},
  "geometry": {"coordinates":[-69.53703308110001,47.8350410461],"type":"Point"}
}