{
  "type": "Feature",
  "properties": {
    "addr:full":"2057 Mills Rd Sidney BC V8L 5X2",
    "addr:housenumber":"2057",
    "addr:postcode":"v8l 5x2",
    "addr:street":"Mills Rd",
    "iso:country":"CA",
    "sg:address":"2057 Mills Rd",
    "sg:city":"Sidney",
    "sg:classifiers":[
        {
            "category":"Autos & Motor Vehicles",
            "subcategory":"Motorcycle Sales",
            "type":"Retail Goods"
        }
    ],
    "sg:phone":"+1 250 656 7714",
    "sg:postcode":"V8L 5X2",
    "sg:province":"BC",
    "sg:tags":[
        "engine"
    ],
    "wof:name":"Grant's Small Motors",
    "wof:placetype":"venue"
},
  "geometry": {"coordinates":[-123.414665222,48.6551704407],"type":"Point"}
}