{
  "type": "Feature",
  "properties": {
    "addr:full":"7710 Boul Lasalle Lasalle QC H8P 1X6",
    "addr:housenumber":"7710",
    "addr:postcode":"h8p 1x6",
    "addr:street":"Boul Lasalle",
    "iso:country":"CA",
    "sg:address":"7710 Boul Lasalle",
    "sg:city":"Lasalle",
    "sg:classifiers":[
        {
            "category":"Organizations",
            "subcategory":"Professional Association",
            "type":"Services"
        }
    ],
    "sg:phone":"+1 514 366 6580",
    "sg:postcode":"H8P 1X6",
    "sg:province":"QC",
    "wof:name":"Chevaliers DE Colomb",
    "wof:placetype":"venue"
},
  "geometry": {"coordinates":[-73.59365099999999,45.428932],"type":"Point"}
}