{
  "type": "Feature",
  "properties": {
    "addr:full":"598 Norris Crt Kingston ON K7P 2R9",
    "addr:housenumber":"598",
    "addr:postcode":"k7p 2r9",
    "addr:street":"Norris Crt",
    "iso:country":"CA",
    "sg:address":"598 Norris Crt",
    "sg:city":"Kingston",
    "sg:classifiers":[
        {
            "category":"Manufacturing",
            "subcategory":"Apparel",
            "type":"Manufacturing & Wholesale Goods"
        }
    ],
    "sg:phone":"+1 613 384 3930",
    "sg:postcode":"K7P 2R9",
    "sg:province":"ON",
    "sg:tags":[
        "embroidery"
    ],
    "wof:name":"Villager Custom Screenprinting",
    "wof:placetype":"venue"
},
  "geometry": {"coordinates":[-76.567268,44.263519],"type":"Point"}
}