{
  "type": "Feature",
  "properties": {
    "addr:full":"Plamondon AB T0A 2T0",
    "addr:postcode":"t0a 2t0",
    "iso:country":"CA",
    "sg:city":"Plamondon",
    "sg:classifiers":[
        {
            "category":"Government",
            "subcategory":"Office",
            "type":"Public Place"
        }
    ],
    "sg:phone":"+1 780 798 3881",
    "sg:postcode":"T0A 2T0",
    "sg:province":"AB",
    "sg:tags":[
        "village"
    ],
    "wof:name":"Plamondon Water Treatment Plnt",
    "wof:placetype":"venue"
},
  "geometry": {"coordinates":[-112.344475,54.849781],"type":"Point"}
}