{
  "type": "Feature",
  "properties": {
    "addr:full":"Sutton QC J0E 2K0",
    "addr:postcode":"j0e 2k0",
    "iso:country":"CA",
    "sg:city":"Sutton",
    "sg:classifiers":[
        {
            "category":"Shopping",
            "subcategory":"Computers & Home Electronics",
            "type":"Retail Goods"
        }
    ],
    "sg:phone":"+1 450 538 0446",
    "sg:postcode":"J0E 2K0",
    "sg:province":"QC",
    "sg:tags":[
        "equipment",
        "dealer"
    ],
    "wof:name":"Reproduction Rs Enr",
    "wof:placetype":"venue"
},
  "geometry": {"coordinates":[-72.61507400000001,45.10585],"type":"Point"}
}