{
  "type": "Feature",
  "properties": {
    "iso:country":"CA",
    "sg:address":"5107 53 St",
    "sg:city":"Yellowknife",
    "sg:classifiers":[
        {
            "category":"Professional",
            "subcategory":"Lawyer & Legal Services",
            "type":"Services"
        }
    ],
    "sg:phone":"+1 867 920 4151",
    "sg:postcode":"X1A 1V7",
    "sg:province":"NT",
    "sg:tags":[
        "attorney"
    ],
    "wof:name":"Walsh, Louis M",
    "wof:placetype":"venue"
},
  "geometry": {"coordinates":[-114.37216949499999,62.4511108398],"type":"Point"}
}