{
  "type": "Feature",
  "properties": {
    "addr:full":"Newmarket ON L3Y 6P5",
    "addr:postcode":"l3y 6p5",
    "iso:country":"CA",
    "sg:city":"Newmarket",
    "sg:classifiers":[
        {
            "category":"Health Services",
            "subcategory":"Podiatrist",
            "type":"Services"
        }
    ],
    "sg:phone":"+1 905 853 6466",
    "sg:postcode":"L3Y 6P5",
    "sg:province":"ON",
    "wof:name":"Haber, Stephen A DPM",
    "wof:placetype":"venue"
},
  "geometry": {"coordinates":[-79.4559707642,44.0604171753],"type":"Point"}
}