{
  "type": "Feature",
  "properties": {
    "addr:full":"3575 Lake Shore Blvd W Etobicoke ON M8W 1P5",
    "addr:housenumber":"3575",
    "addr:postcode":"m8w 1p5",
    "addr:street":"Lake Shore Blvd W",
    "iso:country":"CA",
    "sg:address":"3575 Lake Shore Blvd W",
    "sg:city":"Etobicoke",
    "sg:classifiers":[
        {
            "category":"Restaurant",
            "type":"Food & Drink"
        }
    ],
    "sg:phone":"+1 416 503 1201",
    "sg:postcode":"M8W 1P5",
    "sg:province":"ON",
    "wof:name":"George the Greek",
    "wof:placetype":"venue"
},
  "geometry": {"coordinates":[-79.534142,43.594231],"type":"Point"}
}