{
  "type": "Feature",
  "properties": {
    "addr:full":"Tavistock ON N0B 2R0",
    "addr:postcode":"n0b 2r0",
    "iso:country":"CA",
    "sg:city":"Tavistock",
    "sg:classifiers":[
        {
            "category":"Professional",
            "subcategory":"Accounting & Tax Preparation",
            "type":"Services"
        }
    ],
    "sg:phone":"+1 519 655 3490",
    "sg:postcode":"N0B 2R0",
    "sg:province":"ON",
    "sg:tags":[
        "accountant"
    ],
    "wof:name":"Clive A Lawry Certified Mgmt",
    "wof:placetype":"venue"
},
  "geometry": {"coordinates":[-80.83689099999999,43.320511],"type":"Point"}
}