{
  "type": "Feature",
  "properties": {
    "addr:full":"48 Hollywood Ave Smooth Rock Falls ON P0L 2B0",
    "addr:housenumber":"48",
    "addr:postcode":"p0l 2b0",
    "addr:street":"Hollywood Ave",
    "iso:country":"CA",
    "sg:address":"48 Hollywood Ave",
    "sg:city":"Smooth Rock Falls",
    "sg:classifiers":[
        {
            "category":"Organizations",
            "subcategory":"Religious Organization",
            "type":"Services"
        }
    ],
    "sg:phone":"+1 705 338 2716",
    "sg:postcode":"P0L 2B0",
    "sg:province":"ON",
    "sg:tags":[
        "church"
    ],
    "wof:name":"St Gertrude Catholic Church",
    "wof:placetype":"venue"
},
  "geometry": {"coordinates":[-81.63030999999999,49.280575],"type":"Point"}
}