{
  "type": "Feature",
  "properties": {
    "addr:full":"498 Rue Rachel Charlesbourg QC G2L 1S6",
    "addr:housenumber":"498",
    "addr:postcode":"g2l 1s6",
    "addr:street":"Rue Rachel",
    "iso:country":"CA",
    "sg:address":"498 Rue Rachel",
    "sg:city":"Charlesbourg",
    "sg:classifiers":[
        {
            "category":"Professional",
            "subcategory":"Accounting & Tax Preparation",
            "type":"Services"
        }
    ],
    "sg:phone":"+1 418 622 2404",
    "sg:postcode":"G2L 1S6",
    "sg:province":"QC",
    "sg:tags":[
        "accountant"
    ],
    "wof:name":"Turmel, Roger",
    "wof:placetype":"venue"
},
  "geometry": {"coordinates":[-71.23226200000001,46.880215],"type":"Point"}
}