{
  "type": "Feature",
  "properties": {
    "addr:full":"15 Industrial Dr #2 Sylvan Lake AB T4S 1P4",
    "addr:housenumber":"15",
    "addr:postcode":"t4s 1p4",
    "addr:street":"Industrial Dr # 2",
    "iso:country":"CA",
    "sg:address":"15 Industrial Dr #2",
    "sg:city":"Sylvan Lake",
    "sg:classifiers":[
        {
            "category":"Manufacturing",
            "subcategory":"Printing",
            "type":"Manufacturing & Wholesale Goods"
        }
    ],
    "sg:phone":"+1 403 887 5600",
    "sg:postcode":"T4S 1P4",
    "sg:province":"AB",
    "sg:tags":[
        "printer"
    ],
    "wof:name":"Cat Tail Publishing Ltd",
    "wof:placetype":"venue"
},
  "geometry": {"coordinates":[-114.06899300000001,52.315533],"type":"Point"}
}