{
  "type": "Feature",
  "properties": {
    "addr:full":"4808 30 St SE Calgary AB T2B 2Z1",
    "addr:housenumber":"4808",
    "addr:postcode":"t2b 2z1",
    "addr:street":"30 St Se",
    "iso:country":"CA",
    "sg:address":"4808 30 St SE",
    "sg:city":"Calgary",
    "sg:classifiers":[
        {
            "category":"Building & Trades",
            "subcategory":"Construction",
            "type":"Services"
        }
    ],
    "sg:phone":"+1 403 235 1592",
    "sg:postcode":"T2B 2Z1",
    "sg:province":"AB",
    "sg:tags":[
        "masonry",
        "contractor"
    ],
    "wof:name":"G & A Masonry Ltd",
    "wof:placetype":"venue"
},
  "geometry": {"coordinates":[-113.988685608,51.0111541748],"type":"Point"}
}