{
  "type": "Feature",
  "properties": {
    "addr:full":"5161 Boul DE LA Rive-Sud Levis QC G6V 4Z5",
    "addr:housenumber":"5161",
    "addr:postcode":"g6v 4z5",
    "addr:street":"Boul De La Rive-Sud",
    "iso:country":"CA",
    "sg:address":"5161 Boul DE LA Rive-Sud",
    "sg:city":"Levis",
    "sg:classifiers":[
        {
            "category":"Shopping",
            "type":"Retail Goods"
        }
    ],
    "sg:phone":"+1 418 833 8931",
    "sg:postcode":"G6V 4Z5",
    "sg:province":"QC",
    "sg:tags":[
        "awning",
        "canopy"
    ],
    "wof:name":"Auvents W Lecours Inc",
    "wof:placetype":"venue"
},
  "geometry": {"coordinates":[-71.18311300000001,46.791077],"type":"Point"}
}