{
  "type": "Feature",
  "properties": {
    "addr:full":"314 4E Av Iberville QC J2X 1W9",
    "addr:housenumber":"314",
    "addr:postcode":"j2x 1w9",
    "addr:street":"4E Av",
    "iso:country":"CA",
    "sg:address":"314 4E Av",
    "sg:city":"Iberville",
    "sg:classifiers":[
        {
            "category":"Manufacturing",
            "subcategory":"Textiles",
            "type":"Manufacturing & Wholesale Goods"
        }
    ],
    "sg:phone":"+1 450 347 5396",
    "sg:postcode":"J2X 1W9",
    "sg:province":"QC",
    "sg:tags":[
        "rug",
        "carpet"
    ],
    "wof:name":"Tapis Ibe Inc",
    "wof:placetype":"venue"
},
  "geometry": {"coordinates":[-73.23498499999999,45.306641],"type":"Point"}
}