{
  "type": "Feature",
  "properties": {
    "addr:full":"275 First St Collingwood ON L9Y 1A8",
    "addr:housenumber":"275",
    "addr:postcode":"l9y 1a8",
    "addr:street":"First St",
    "iso:country":"CA",
    "sg:address":"275 First St",
    "sg:city":"Collingwood",
    "sg:classifiers":[
        {
            "category":"Food & Beverages",
            "subcategory":"Specialty",
            "type":"Retail Goods"
        }
    ],
    "sg:phone":"+1 705 445 6006",
    "sg:postcode":"L9Y 1A8",
    "sg:province":"ON",
    "sg:tags":[
        "control",
        "herb",
        "weight"
    ],
    "wof:name":"Herbal Magic Systems",
    "wof:placetype":"venue"
},
  "geometry": {"coordinates":[-80.224785,44.502239],"type":"Point"}
}