{
  "type": "Feature",
  "properties": {
    "addr:full":"108 Juanita St Carp ON K0A 1L0",
    "addr:housenumber":"108",
    "addr:postcode":"k0a 1l0",
    "addr:street":"Juanita St",
    "iso:country":"CA",
    "sg:address":"108 Juanita St",
    "sg:city":"Carp",
    "sg:classifiers":[
        {
            "category":"Recreation",
            "type":"Entertainment"
        }
    ],
    "sg:phone":"+1 613 839 2959",
    "sg:postcode":"K0A 1L0",
    "sg:province":"ON",
    "sg:tags":[
        "government",
        "social",
        "welfare",
        "organization",
        "hall",
        "auditorium"
    ],
    "wof:name":"Huntley Community Ctr",
    "wof:placetype":"venue"
},
  "geometry": {"coordinates":[-76.0396728516,45.3499450684],"type":"Point"}
}