{
  "type": "Feature",
  "properties": {
    "iso:country":"CA",
    "sg:address":"645 Lakeshore Rd",
    "sg:city":"Sarnia",
    "sg:classifiers":[
        {
            "category":"Shopping",
            "type":"Retail Goods"
        }
    ],
    "sg:phone":"+1 519 337 0303",
    "sg:postcode":"N7V 2T1",
    "sg:province":"ON",
    "sg:tags":[
        "equipment",
        "wine",
        "supply"
    ],
    "wof:name":"Wine Kitz",
    "wof:placetype":"venue"
},
  "geometry": {"coordinates":[-82.3871078491,43.0105476379],"type":"Point"}
}