{
  "type": "Feature",
  "properties": {
    "addr:full":"3 Reenders Dr # 7 Winnipeg MB R2C 5K5",
    "addr:housenumber":"3",
    "addr:postcode":"r2c 5k5",
    "addr:street":"Reenders Dr # 7",
    "iso:country":"CA",
    "sg:address":"3 Reenders Dr # 7",
    "sg:city":"Winnipeg",
    "sg:classifiers":[
        {
            "category":"Restaurant",
            "type":"Food & Drink"
        }
    ],
    "sg:phone":"+1 204 949 0001",
    "sg:postcode":"R2C 5K5",
    "sg:province":"MB",
    "sg:tags":[
        "out"
    ],
    "wof:name":"Panago Pizza",
    "wof:placetype":"venue"
},
  "geometry": {"coordinates":[-97.057022,49.897305],"type":"Point"}
}