{
  "type": "Feature",
  "properties": {
    "addr:full":"75 Erie St S Leamington ON N8H 3B2",
    "addr:housenumber":"75",
    "addr:postcode":"n8h 3b2",
    "addr:street":"Erie St S",
    "iso:country":"CA",
    "sg:address":"75 Erie St S",
    "sg:city":"Leamington",
    "sg:classifiers":[
        {
            "category":"Social Services",
            "type":"Services"
        }
    ],
    "sg:phone":"+1 519 733 8982",
    "sg:postcode":"N8H 3B2",
    "sg:province":"ON",
    "sg:tags":[
        "counselor",
        "marriage",
        "family"
    ],
    "wof:name":"Gero Counselling Svc",
    "wof:placetype":"venue"
},
  "geometry": {"coordinates":[-82.60013600000001,42.050743],"type":"Point"}
}