{
  "type": "Feature",
  "properties": {
    "addr:full":"63 Main St W # 7 Grimsby ON L3M 4H1",
    "addr:housenumber":"63",
    "addr:postcode":"l3m 4h1",
    "addr:street":"Main St W # 7",
    "iso:country":"CA",
    "sg:address":"63 Main St W # 7",
    "sg:city":"Grimsby",
    "sg:classifiers":[
        {
            "category":"Health Services",
            "subcategory":"Doctor",
            "type":"Services"
        }
    ],
    "sg:phone":"+1 905 945 4975",
    "sg:postcode":"L3M 4H1",
    "sg:province":"ON",
    "sg:tags":[
        "dentist"
    ],
    "wof:name":"Mac Neil, Cheslea P DDS",
    "wof:placetype":"venue"
},
  "geometry": {"coordinates":[-79.56317138670001,43.1943969727],"type":"Point"}
}