{
  "type": "Feature",
  "properties": {
    "addr:full":"640 Dublin Ch Inverness QC G0S 1K0",
    "addr:housenumber":"640",
    "addr:postcode":"g0s 1k0",
    "iso:country":"CA",
    "sg:address":"640 Dublin Ch",
    "sg:city":"Inverness",
    "sg:classifiers":[
        {
            "category":"Recreation",
            "type":"Entertainment"
        }
    ],
    "sg:phone":"+1 418 453 7750",
    "sg:postcode":"G0S 1K0",
    "sg:province":"QC",
    "sg:tags":[
        "sugar",
        "syrup",
        "hall",
        "maple",
        "auditorium"
    ],
    "wof:name":"L'Invernois",
    "wof:placetype":"venue"
},
  "geometry": {"coordinates":[-71.5910644531,46.2905654907],"type":"Point"}
}