{
  "type": "Feature",
  "properties": {
    "addr:full":"Surrey BC V3S 6C8",
    "addr:postcode":"v3s 6c8",
    "iso:country":"CA",
    "sg:city":"Surrey",
    "sg:classifiers":[
        {
            "category":"Shopping",
            "type":"Retail Goods"
        }
    ],
    "sg:phone":"+1 604 576 8855",
    "sg:postcode":"V3S 6C8",
    "sg:province":"BC",
    "sg:tags":[
        "equipment",
        "beer",
        "supply"
    ],
    "wof:name":"West Coast Fermenters Inc",
    "wof:placetype":"venue"
},
  "geometry": {"coordinates":[-122.72457900000001,49.102161],"type":"Point"}
}