{
  "type": "Feature",
  "properties": {
    "addr:full":"10804 81 Ave NW Edmonton AB T6E 1Y4",
    "addr:housenumber":"10804",
    "addr:postcode":"t6e 1y4",
    "addr:street":"81 Ave Nw",
    "iso:country":"CA",
    "sg:address":"10804 81 Ave NW",
    "sg:city":"Edmonton",
    "sg:classifiers":[
        {
            "category":"Real Estate",
            "subcategory":"Architect",
            "type":"Services"
        }
    ],
    "sg:phone":"+1 780 433 0854",
    "sg:postcode":"T6E 1Y4",
    "sg:province":"AB",
    "wof:name":"Wilson Architects Ltd",
    "wof:placetype":"venue"
},
  "geometry": {"coordinates":[-113.50971221899999,53.5172271729],"type":"Point"}
}