{
  "type": "Feature",
  "properties": {
    "addr:full":"1341 Grand Marais Rd W Windsor ON N9E 1E2",
    "addr:housenumber":"1341",
    "addr:postcode":"n9e 1e2",
    "addr:street":"Grand Marais Rd W",
    "iso:country":"CA",
    "sg:address":"1341 Grand Marais Rd W",
    "sg:city":"Windsor",
    "sg:classifiers":[
        {
            "category":"Real Estate",
            "subcategory":"Real Estate Agent",
            "type":"Services"
        }
    ],
    "sg:phone":"+1 519 969 4680",
    "sg:postcode":"N9E 1E2",
    "sg:province":"ON",
    "sg:tags":[
        "management"
    ],
    "wof:name":"N & D Supermarkets Ltd",
    "wof:placetype":"venue"
},
  "geometry": {"coordinates":[-83.0264129639,42.267868042],"type":"Point"}
}