{
  "type": "Feature",
  "properties": {
    "addr:full":"Sidney BC V8L 3C4",
    "addr:postcode":"v8l 3c4",
    "iso:country":"CA",
    "sg:city":"Sidney",
    "sg:classifiers":[
        {
            "category":"Professional",
            "subcategory":"Lawyer & Legal Services",
            "type":"Services"
        }
    ],
    "sg:phone":"+1 250 656 0981",
    "sg:postcode":"V8L 3C4",
    "sg:province":"BC",
    "sg:tags":[
        "attorney"
    ],
    "wof:name":"Scott-Moncrieff & CO",
    "wof:placetype":"venue"
},
  "geometry": {"coordinates":[-123.396789551,48.6469917297],"type":"Point"}
}