{
  "type": "Feature",
  "properties": {
    "addr:full":"152 Rte Du Fleuve Beaumont QC G0R 1C0",
    "addr:housenumber":"152",
    "addr:postcode":"g0r 1c0",
    "addr:street":"Rte Du Fleuve",
    "iso:country":"CA",
    "sg:address":"152 Rte Du Fleuve",
    "sg:city":"Beaumont",
    "sg:classifiers":[
        {
            "category":"Building & Trades",
            "subcategory":"Construction",
            "type":"Services"
        }
    ],
    "sg:phone":"+1 418 837 2300",
    "sg:postcode":"G0R 1C0",
    "sg:province":"QC",
    "sg:tags":[
        "water",
        "well",
        "drilling"
    ],
    "wof:name":"Forages Denis Proulx Inc",
    "wof:placetype":"venue"
},
  "geometry": {"coordinates":[-70.97970599999999,46.835812],"type":"Point"}
}