{
  "type": "Feature",
  "properties": {
    "iso:country":"CA",
    "sg:address":"12 Rue Blainville O",
    "sg:city":"Sainte-Therese",
    "sg:classifiers":[
        {
            "category":"Restaurant",
            "type":"Food & Drink"
        }
    ],
    "sg:phone":"+1 450 979 9979",
    "sg:postcode":"J7E 1W9",
    "sg:province":"QC",
    "sg:tags":[
        "pizza"
    ],
    "wof:name":"Pizza Welat",
    "wof:placetype":"venue"
},
  "geometry": {"coordinates":[-73.839607,45.6394],"type":"Point"}
}