{
  "type": "Feature",
  "properties": {
    "addr:full":"Calgary AB T2P 1N3",
    "addr:postcode":"t2p 1n3",
    "iso:country":"CA",
    "sg:city":"Calgary",
    "sg:classifiers":[
        {
            "category":"Building & Trades",
            "subcategory":"Landscaping Services",
            "type":"Services"
        }
    ],
    "sg:phone":"+1 403 262 9744",
    "sg:postcode":"T2P 1N3",
    "sg:province":"AB",
    "sg:tags":[
        "designer",
        "landscape"
    ],
    "wof:name":"Scatliff Miller Murray Land",
    "wof:placetype":"venue"
},
  "geometry": {"coordinates":[-114.065711975,51.0453987122],"type":"Point"}
}