{
  "type": "Feature",
  "properties": {
    "addr:full":"1063 Rue Du Phare Pointe-Au-Pere QC G5M 1L9",
    "addr:housenumber":"1063",
    "addr:postcode":"g5m 1l9",
    "addr:street":"Rue Du Phare",
    "iso:country":"CA",
    "sg:address":"1063 Rue Du Phare",
    "sg:city":"Pointe-Au-Pere",
    "sg:classifiers":[
        {
            "category":"Building & Trades",
            "subcategory":"Equipment Rental",
            "type":"Services"
        }
    ],
    "sg:phone":"+1 418 722 8224",
    "sg:postcode":"G5M 1L9",
    "sg:province":"QC",
    "sg:tags":[
        "renting",
        "leasing",
        "moving",
        "truck",
        "supply"
    ],
    "wof:name":"U-Haul Cie Ltee",
    "wof:placetype":"venue"
},
  "geometry": {"coordinates":[-68.46687300000001,48.517159],"type":"Point"}
}