{
  "type": "Feature",
  "properties": {
    "iso:country":"CA",
    "sg:address":"147 Brookfield Ave",
    "sg:city":"Sault Ste Marie",
    "sg:classifiers":[
        {
            "category":"Education",
            "subcategory":"School",
            "type":"Public Place"
        }
    ],
    "sg:phone":"+1 705 945 5525",
    "sg:postcode":"P6C 5P2",
    "sg:province":"ON",
    "wof:name":"St Francis Elementary School",
    "wof:placetype":"venue"
},
  "geometry": {"coordinates":[-84.3971710205,46.5327796936],"type":"Point"}
}