{
  "type": "Feature",
  "properties": {
    "addr:full":"73 Hargrave St Winnipeg MB R3C 1N3",
    "addr:housenumber":"73",
    "addr:postcode":"r3c 1n3",
    "addr:street":"Hargrave St",
    "iso:country":"CA",
    "sg:address":"73 Hargrave St",
    "sg:city":"Winnipeg",
    "sg:classifiers":[
        {
            "category":"Personal",
            "subcategory":"Beauty Salon",
            "type":"Services"
        }
    ],
    "sg:phone":"+1 204 942 3351",
    "sg:postcode":"R3C 1N3",
    "sg:province":"MB",
    "wof:name":"Rouge",
    "wof:placetype":"venue"
},
  "geometry": {"coordinates":[-97.1408615112,49.8865737915],"type":"Point"}
}