{
  "type": "Feature",
  "properties": {
    "addr:full":"614 Cliff St Bella Coola BC V0T 1C0",
    "addr:housenumber":"614",
    "addr:postcode":"v0t 1c0",
    "addr:street":"Cliff St",
    "iso:country":"CA",
    "sg:address":"614 Cliff St",
    "sg:city":"Bella Coola",
    "sg:classifiers":[
        {
            "category":"Restaurant",
            "type":"Food & Drink"
        }
    ],
    "sg:phone":"+1 250 799 5989",
    "sg:postcode":"V0T 1C0",
    "sg:province":"BC",
    "wof:name":"Palm Garden Restaurant",
    "wof:placetype":"venue"
},
  "geometry": {"coordinates":[-126.74625399999999,52.372021],"type":"Point"}
}