{
  "type": "Feature",
  "properties": {
    "addr:full":"1148 Third Ave Trail BC V1R 1N9",
    "addr:housenumber":"1148",
    "addr:postcode":"bc v1r 1n9",
    "addr:street":"Third Ave Trail",
    "iso:country":"CA",
    "sg:address":"1148 Third Ave",
    "sg:city":"Trail",
    "sg:classifiers":[
        {
            "category":"Professional",
            "subcategory":"Management & Consulting",
            "type":"Services"
        }
    ],
    "sg:phone":"+1 250 364 0195",
    "sg:postcode":"V1R 1N9",
    "sg:province":"BC",
    "sg:tags":[
        "consultant",
        "safety"
    ],
    "wof:name":"Kootenay Kidsafe",
    "wof:placetype":"venue"
},
  "geometry": {"coordinates":[-117.70482635499999,49.1035423279],"type":"Point"}
}