{
  "type": "Feature",
  "properties": {
    "addr:full":"7670 Tecumseh Rd E Windsor ON N8T 1E9",
    "addr:housenumber":"7670",
    "addr:postcode":"n8t 1e9",
    "addr:street":"Tecumseh Rd E",
    "iso:country":"CA",
    "sg:address":"7670 Tecumseh Rd E",
    "sg:city":"Windsor",
    "sg:classifiers":[
        {
            "category":"Shopping",
            "subcategory":"Clothing, Apparel, & Fashions",
            "type":"Retail Goods"
        }
    ],
    "sg:phone":"+1 519 945 2796",
    "sg:postcode":"N8T 1E9",
    "sg:province":"ON",
    "wof:name":"Penningtons Superstore",
    "wof:placetype":"venue"
},
  "geometry": {"coordinates":[-82.934792,42.31382],"type":"Point"}
}