{
  "type": "Feature",
  "properties": {
    "addr:full":"474 Davis Dr Newmarket ON L3Y 2P3",
    "addr:housenumber":"474",
    "addr:postcode":"l3y 2p3",
    "addr:street":"Davis Dr",
    "iso:country":"CA",
    "sg:address":"474 Davis Dr",
    "sg:city":"Newmarket",
    "sg:classifiers":[
        {
            "category":"Government",
            "subcategory":"Office",
            "type":"Public Place"
        }
    ],
    "sg:phone":"+1 905 953 5325",
    "sg:postcode":"L3Y 2P3",
    "sg:province":"ON",
    "sg:tags":[
        "village"
    ],
    "wof:name":"Newmarket Senior's Meeting Plc",
    "wof:placetype":"venue"
},
  "geometry": {"coordinates":[-79.458969,44.05949],"type":"Point"}
}