{
  "type": "Feature",
  "properties": {
    "addr:full":"White Rock BC V4B 1P8",
    "addr:postcode":"v4b 1p8",
    "iso:country":"CA",
    "sg:city":"White Rock",
    "sg:classifiers":[
        {
            "category":"Personal",
            "subcategory":"Beauty Salon",
            "type":"Services"
        }
    ],
    "sg:phone":"+1 604 538 9202",
    "sg:postcode":"V4B 1P8",
    "sg:province":"BC",
    "wof:name":"Impressions & Images",
    "wof:placetype":"venue"
},
  "geometry": {"coordinates":[-122.80033899999999,49.023705],"type":"Point"}
}