{
  "type": "Feature",
  "properties": {
    "addr:full":"19 Glen Agar Dr Etobicoke ON M9B 5L5",
    "addr:housenumber":"19",
    "addr:postcode":"m9b 5l5",
    "addr:street":"Glen Agar Dr",
    "iso:country":"CA",
    "sg:address":"19 Glen Agar Dr",
    "sg:city":"Etobicoke",
    "sg:classifiers":[
        {
            "category":"Social Services",
            "subcategory":"Child Care",
            "type":"Services"
        }
    ],
    "sg:phone":"+1 416 695 1212",
    "sg:postcode":"M9B 5L5",
    "sg:province":"ON",
    "sg:tags":[
        "kindergarten",
        "academic"
    ],
    "wof:name":"Phoenix Montessori School",
    "wof:placetype":"venue"
},
  "geometry": {"coordinates":[-79.55182600000001,43.662037],"type":"Point"}
}