{
  "type": "Feature",
  "properties": {
    "addr:full":"653 Hwy 1 Mount Uniacke NS B0N 1Z0",
    "addr:housenumber":"653",
    "addr:postcode":"b0n 1z0",
    "addr:street":"Hwy 1",
    "iso:country":"CA",
    "sg:address":"653 Hwy 1",
    "sg:city":"Mount Uniacke",
    "sg:classifiers":[
        {
            "category":"Shopping",
            "subcategory":"Pharmacy",
            "type":"Retail Goods"
        }
    ],
    "sg:phone":"+1 902 866 3848",
    "sg:postcode":"B0N 1Z0",
    "sg:province":"NS",
    "wof:name":"Mount Uniacke Pharmacy",
    "wof:placetype":"venue"
},
  "geometry": {"coordinates":[-63.8340301514,44.8959693909],"type":"Point"}
}