{
  "type": "Feature",
  "properties": {
    "addr:full":"83 Bigwin Rd Hamilton ON L8W 3R3",
    "addr:housenumber":"83",
    "addr:postcode":"l8w 3r3",
    "addr:street":"Bigwin Rd",
    "iso:country":"CA",
    "sg:address":"83 Bigwin Rd",
    "sg:city":"Hamilton",
    "sg:classifiers":[
        {
            "category":"Shopping",
            "subcategory":"Bicycles & Sporting Goods",
            "type":"Retail Goods"
        }
    ],
    "sg:phone":"+1 905 575 4840",
    "sg:postcode":"L8W 3R3",
    "sg:province":"ON",
    "sg:tags":[
        "skating",
        "equipment",
        "supply"
    ],
    "wof:name":"A Skaters Wish",
    "wof:placetype":"venue"
},
  "geometry": {"coordinates":[-79.82051849370001,43.1929359436],"type":"Point"}
}