{
  "type": "Feature",
  "properties": {
    "addr:full":"Lloydminster AB T9V 0M3",
    "addr:postcode":"t9v 0m3",
    "iso:country":"CA",
    "sg:city":"Lloydminster",
    "sg:classifiers":[
        {
            "category":"Personal",
            "subcategory":"Beauty Salon",
            "type":"Services"
        }
    ],
    "sg:phone":"+1 780 875 6673",
    "sg:postcode":"T9V 0M3",
    "sg:province":"AB",
    "wof:name":"New Look Electrolysis Studio",
    "wof:placetype":"venue"
},
  "geometry": {"coordinates":[-110.008537,53.283676],"type":"Point"}
}