{
  "type": "Feature",
  "properties": {
    "addr:full":"401 Rue Principale Saint-Pierre-Montmagny QC G0R 4B0",
    "addr:housenumber":"401",
    "addr:postcode":"g0r 4b0",
    "addr:street":"Rue Principale",
    "iso:country":"CA",
    "sg:address":"401 Rue Principale",
    "sg:city":"Saint-Pierre-Montmagny",
    "sg:classifiers":[
        {
            "category":"Retail",
            "subcategory":"Auto Repair",
            "type":"Services"
        }
    ],
    "sg:phone":"+1 418 248 1284",
    "sg:postcode":"G0R 4B0",
    "sg:province":"QC",
    "sg:tags":[
        "repairing",
        "automobile"
    ],
    "wof:name":"Garage Fernand Cloutier Enr",
    "wof:placetype":"venue"
},
  "geometry": {"coordinates":[-70.62696800000001,46.914959],"type":"Point"}
}