{
  "type": "Feature",
  "properties": {
    "iso:country":"CA",
    "sg:city":"Brossard",
    "sg:classifiers":[
        {
            "category":"Professional",
            "subcategory":"Lawyer & Legal Services",
            "type":"Services"
        }
    ],
    "sg:phone":"+1 450 445 1662",
    "sg:postcode":"J4Z 2X5",
    "sg:province":"QC",
    "sg:tags":[
        "attorney"
    ],
    "wof:name":"Arbitrage Jp Lussier",
    "wof:placetype":"venue"
},
  "geometry": {"coordinates":[-73.4448013306,45.4665565491],"type":"Point"}
}