{
  "type": "Feature",
  "properties": {
    "addr:full":"2230 Lake Shore Blvd W Etobicoke ON M8V 1A5",
    "addr:housenumber":"2230",
    "addr:postcode":"m8v 1a5",
    "addr:street":"Lake Shore Blvd W",
    "iso:country":"CA",
    "sg:address":"2230 Lake Shore Blvd W",
    "sg:city":"Etobicoke",
    "sg:classifiers":[
        {
            "category":"Food & Beverages",
            "subcategory":"Groceries & Convenience Stores",
            "type":"Retail Goods"
        }
    ],
    "sg:phone":"+1 416 255 3663",
    "sg:postcode":"M8V 1A5",
    "sg:province":"ON",
    "sg:tags":[
        "grocer"
    ],
    "wof:name":"Rabba Fine Foods",
    "wof:placetype":"venue"
},
  "geometry": {"coordinates":[-79.48258209230001,43.6213531494],"type":"Point"}
}