{
  "type": "Feature",
  "properties": {
    "iso:country":"CA",
    "sg:address":"575 River Glen Blvd # 8",
    "sg:city":"Oakville",
    "sg:classifiers":[
        {
            "category":"Health Services",
            "subcategory":"Doctor",
            "type":"Services"
        }
    ],
    "sg:phone":"+1 905 257 3400",
    "sg:postcode":"L6H 6X6",
    "sg:province":"ON",
    "sg:tags":[
        "dentist"
    ],
    "wof:name":"Woods, Charles A DDS",
    "wof:placetype":"venue"
},
  "geometry": {"coordinates":[-79.73709106450001,43.4610214233],"type":"Point"}
}