{
  "type": "Feature",
  "properties": {
    "addr:full":"830 Bernard Ave Kelowna BC V1Y 6P5",
    "addr:housenumber":"830",
    "addr:postcode":"v1y 6p5",
    "addr:street":"Bernard Ave",
    "iso:country":"CA",
    "sg:address":"830 Bernard Ave",
    "sg:city":"Kelowna",
    "sg:classifiers":[
        {
            "category":"Professional",
            "subcategory":"Lawyer & Legal Services",
            "type":"Services"
        }
    ],
    "sg:phone":"+1 250 868 2848",
    "sg:postcode":"V1Y 6P5",
    "sg:province":"BC",
    "sg:tags":[
        "attorney"
    ],
    "wof:name":"Heritage Law Group",
    "wof:placetype":"venue"
},
  "geometry": {"coordinates":[-119.48493999999999,49.886433],"type":"Point"}
}