{
  "type": "Feature",
  "properties": {
    "addr:full":"1575 Dundas St W Toronto ON M6K 1T9",
    "addr:housenumber":"1575",
    "addr:postcode":"m6k 1t9",
    "addr:street":"Dundas St W",
    "iso:country":"CA",
    "sg:address":"1575 Dundas St W",
    "sg:city":"Toronto",
    "sg:classifiers":[
        {
            "category":"Manufacturing",
            "subcategory":"Metals",
            "type":"Manufacturing & Wholesale Goods"
        }
    ],
    "sg:phone":"+1 416 532 4049",
    "sg:postcode":"M6K 1T9",
    "sg:province":"ON",
    "sg:tags":[
        "work",
        "sheet",
        "contractor"
    ],
    "wof:name":"Star Sheet Metal Mfg CO",
    "wof:placetype":"venue"
},
  "geometry": {"coordinates":[-79.43445587159999,43.6496772766],"type":"Point"}
}