{
  "type": "Feature",
  "properties": {
    "addr:full":"543 Richmond St W Toronto ON M5V 1Y6",
    "addr:housenumber":"543",
    "addr:postcode":"m5v 1y6",
    "addr:street":"Richmond St W",
    "iso:country":"CA",
    "sg:address":"543 Richmond St W",
    "sg:city":"Toronto",
    "sg:classifiers":[
        {
            "category":"Communications",
            "subcategory":"Film & Video Production",
            "type":"Services"
        }
    ],
    "sg:phone":"+1 416 362 3330",
    "sg:postcode":"M5V 1Y6",
    "sg:province":"ON",
    "sg:tags":[
        "motion",
        "picture",
        "studio",
        "producer"
    ],
    "wof:name":"Buck Productions",
    "wof:placetype":"venue"
},
  "geometry": {"coordinates":[-79.40142822270001,43.6467590332],"type":"Point"}
}