{
  "type": "Feature",
  "properties": {
    "addr:full":"144 Main St Atwood ON N0G 1B0",
    "addr:housenumber":"144",
    "addr:postcode":"n0g 1b0",
    "addr:street":"Main St",
    "iso:country":"CA",
    "sg:address":"144 Main St",
    "sg:city":"Atwood",
    "sg:classifiers":[
        {
            "category":"Retail",
            "subcategory":"Auto Repair",
            "type":"Services"
        }
    ],
    "sg:phone":"+1 519 356 2291",
    "sg:postcode":"N0G 1B0",
    "sg:province":"ON",
    "sg:tags":[
        "repairing",
        "automobile"
    ],
    "wof:name":"Corner Auto Repair",
    "wof:placetype":"venue"
},
  "geometry": {"coordinates":[-81.016563,43.671352],"type":"Point"}
}