{
  "type": "Feature",
  "properties": {
    "iso:country":"CA",
    "sg:city":"Vancouver",
    "sg:classifiers":[
        {
            "category":"Government",
            "subcategory":"Office",
            "type":"Public Place"
        }
    ],
    "sg:phone":"+1 604 736 9844",
    "sg:postcode":"V6Z 1W2",
    "sg:province":"BC",
    "wof:name":"Vancouver Health Unit",
    "wof:placetype":"venue"
},
  "geometry": {"coordinates":[-123.129333496,49.2774353027],"type":"Point"}
}