{
  "type": "Feature",
  "properties": {
    "addr:full":"4733 Elbow Dr SW Calgary AB T2S 2K9",
    "addr:housenumber":"4733",
    "addr:postcode":"t2s 2k9",
    "addr:street":"Elbow Dr Sw",
    "iso:country":"CA",
    "sg:address":"4733 Elbow Dr SW",
    "sg:city":"Calgary",
    "sg:classifiers":[
        {
            "category":"Building & Trades",
            "subcategory":"Plumbing",
            "type":"Services"
        }
    ],
    "sg:phone":"+1 403 287 1550",
    "sg:postcode":"T2S 2K9",
    "sg:province":"AB",
    "sg:tags":[
        "leak",
        "detecting"
    ],
    "wof:name":"Gutermann Leak Detection",
    "wof:placetype":"venue"
},
  "geometry": {"coordinates":[-114.080704,51.012165],"type":"Point"}
}