{
  "type": "Feature",
  "properties": {
    "iso:country":"CA",
    "sg:address":"4360 Ch DE LA Cote-DE-Liesse",
    "sg:city":"Mont-Royal",
    "sg:classifiers":[
        {
            "category":"Wholesale",
            "subcategory":"Apparel",
            "type":"Manufacturing & Wholesale Goods"
        }
    ],
    "sg:phone":"+1 514 343 5252",
    "sg:postcode":"H4N 2P7",
    "sg:province":"QC",
    "sg:tags":[
        "textile"
    ],
    "wof:name":"Ern-Tex Inc",
    "wof:placetype":"venue"
},
  "geometry": {"coordinates":[-73.663696,45.505585],"type":"Point"}
}