{
  "type": "Feature",
  "properties": {
    "iso:country":"CA",
    "sg:address":"220 Main St",
    "sg:city":"Minto",
    "sg:classifiers":[
        {
            "category":"Restaurant",
            "type":"Food & Drink"
        }
    ],
    "sg:phone":"+1 506 327 4477",
    "sg:postcode":"E4B 3R3",
    "sg:province":"NB",
    "sg:tags":[
        "pizza"
    ],
    "wof:name":"Twins Pizza",
    "wof:placetype":"venue"
},
  "geometry": {"coordinates":[-66.06405639650001,46.0719833374],"type":"Point"}
}