{
  "type": "Feature",
  "properties": {
    "addr:full":"Montreal QC H3A 1M8",
    "addr:postcode":"h3a 1m8",
    "iso:country":"CA",
    "sg:city":"Montreal",
    "sg:classifiers":[
        {
            "category":"Shopping",
            "subcategory":"Jewelry",
            "type":"Retail Goods"
        }
    ],
    "sg:phone":"+1 514 849 9252",
    "sg:postcode":"H3A 1M8",
    "sg:province":"QC",
    "sg:tags":[
        "jeweler"
    ],
    "wof:name":"Bijouterie Nora",
    "wof:placetype":"venue"
},
  "geometry": {"coordinates":[-73.5749282837,45.5005226135],"type":"Point"}
}