{
  "type": "Feature",
  "properties": {
    "addr:full":"69 Centre St N Huntsville ON P1H 1T4",
    "addr:housenumber":"69",
    "addr:postcode":"p1h 1t4",
    "addr:street":"Centre St N",
    "iso:country":"CA",
    "sg:address":"69 Centre St N",
    "sg:city":"Huntsville",
    "sg:classifiers":[
        {
            "category":"Autos & Motor Vehicles",
            "subcategory":"Automobile Sales",
            "type":"Retail Goods"
        }
    ],
    "sg:phone":"+1 705 789 8818",
    "sg:postcode":"P1H 1T4",
    "sg:province":"ON",
    "sg:tags":[
        "car",
        "dealer"
    ],
    "wof:name":"Festing Toyota Inc",
    "wof:placetype":"venue"
},
  "geometry": {"coordinates":[-79.22380800000001,45.332214],"type":"Point"}
}