{
  "type": "Feature",
  "properties": {
    "addr:full":"105 North Cayuga St W Dunnville ON N1A 1P3",
    "addr:housenumber":"105",
    "addr:postcode":"n1a 1p3",
    "addr:street":"North Cayuga St W",
    "iso:country":"CA",
    "sg:address":"105 North Cayuga St W",
    "sg:city":"Dunnville",
    "sg:classifiers":[
        {
            "category":"Retail",
            "subcategory":"Auto Rental",
            "type":"Services"
        }
    ],
    "sg:phone":"+1 905 701 7222",
    "sg:postcode":"N1A 1P3",
    "sg:province":"ON",
    "sg:tags":[
        "renting",
        "automobile"
    ],
    "wof:name":"Bolcan Leasing & Daily Rentals",
    "wof:placetype":"venue"
},
  "geometry": {"coordinates":[-79.617569,42.906765],"type":"Point"}
}