{
  "type": "Feature",
  "properties": {
    "addr:full":"Calgary AB T3H 4R5",
    "addr:postcode":"t3h 4r5",
    "iso:country":"CA",
    "sg:city":"Calgary",
    "sg:classifiers":[
        {
            "category":"Restaurant",
            "type":"Food & Drink"
        }
    ],
    "sg:phone":"+1 403 217 3000",
    "sg:postcode":"T3H 4R5",
    "sg:province":"AB",
    "wof:name":"Misato Japanese Restaurant",
    "wof:placetype":"venue"
},
  "geometry": {"coordinates":[-114.168670654,51.0367546082],"type":"Point"}
}