{
  "type": "Feature",
  "properties": {
    "addr:full":"175 Lawndale Ave Winnipeg MB R2H 1T4",
    "addr:housenumber":"175",
    "addr:postcode":"r2h 1t4",
    "addr:street":"Lawndale Ave",
    "iso:country":"CA",
    "sg:address":"175 Lawndale Ave",
    "sg:city":"Winnipeg",
    "sg:classifiers":[
        {
            "category":"Wholesale",
            "subcategory":"Hardware",
            "type":"Manufacturing & Wholesale Goods"
        }
    ],
    "sg:phone":"+1 204 233 1310",
    "sg:postcode":"R2H 1T4",
    "sg:province":"MB",
    "sg:tags":[
        "conditioning",
        "air",
        "system",
        "contractor"
    ],
    "wof:name":"Bel Air-Conditioning & Heating",
    "wof:placetype":"venue"
},
  "geometry": {"coordinates":[-97.128685,49.877357],"type":"Point"}
}