{
  "type": "Feature",
  "properties": {
    "addr:full":"102 Ottawa St E Havelock ON K0L 1Z0",
    "addr:housenumber":"102",
    "addr:postcode":"k0l 1z0",
    "addr:street":"Ottawa St E",
    "iso:country":"CA",
    "sg:address":"102 Ottawa St E",
    "sg:city":"Havelock",
    "sg:classifiers":[
        {
            "category":"Restaurant",
            "type":"Food & Drink"
        }
    ],
    "sg:phone":"+1 705 778 2511",
    "sg:postcode":"K0L 1Z0",
    "sg:province":"ON",
    "wof:name":"Park Seven Restaurant",
    "wof:placetype":"venue"
},
  "geometry": {"coordinates":[-77.872238,44.433571],"type":"Point"}
}