{
  "type": "Feature",
  "properties": {
    "addr:full":"Tehkummah ON P0P 2C0",
    "addr:postcode":"p0p 2c0",
    "iso:country":"CA",
    "sg:city":"Tehkummah",
    "sg:classifiers":[
        {
            "category":"Retail",
            "subcategory":"Repair Shop",
            "type":"Services"
        }
    ],
    "sg:phone":"+1 705 859 2180",
    "sg:postcode":"P0P 2C0",
    "sg:province":"ON",
    "sg:tags":[
        "water",
        "equipment",
        "softening"
    ],
    "wof:name":"Wahl Water & Air Treatment",
    "wof:placetype":"venue"
},
  "geometry": {"coordinates":[-82.00348700000001,45.649551],"type":"Point"}
}