{
  "type": "Feature",
  "properties": {
    "addr:full":"3480 Rue Windsor Saint-Hubert QC J4T 2Y7",
    "addr:housenumber":"3480",
    "addr:postcode":"j4t 2y7",
    "addr:street":"Rue Windsor",
    "iso:country":"CA",
    "sg:address":"3480 Rue Windsor",
    "sg:city":"Saint-Hubert",
    "sg:classifiers":[
        {
            "category":"Professional",
            "subcategory":"Management & Consulting",
            "type":"Services"
        }
    ],
    "sg:phone":"+1 450 443 0632",
    "sg:postcode":"J4T 2Y7",
    "sg:province":"QC",
    "sg:tags":[
        "facility",
        "consultant",
        "planning",
        "space"
    ],
    "wof:name":"Francois Ouellet Designer",
    "wof:placetype":"venue"
},
  "geometry": {"coordinates":[-73.4688034058,45.4966087341],"type":"Point"}
}