{
  "type": "Feature",
  "properties": {
    "addr:full":"940 Belfast Rd Ottawa ON K1G 4A2",
    "addr:housenumber":"940",
    "addr:postcode":"k1g 4a2",
    "addr:street":"Belfast Rd",
    "iso:country":"CA",
    "sg:address":"940 Belfast Rd",
    "sg:city":"Ottawa",
    "sg:classifiers":[
        {
            "category":"Freight",
            "type":"Transportation"
        }
    ],
    "sg:phone":"+1 613 244 7347",
    "sg:postcode":"K1G 4A2",
    "sg:province":"ON",
    "sg:tags":[
        "shipping"
    ],
    "wof:name":"Rogers Worldwide Canada Inc",
    "wof:placetype":"venue"
},
  "geometry": {"coordinates":[-75.6343612671,45.4117622375],"type":"Point"}
}