{
  "type": "Feature",
  "properties": {
    "addr:full":"61 Clipper St Coquitlam BC V3K 6X2",
    "addr:housenumber":"61",
    "addr:postcode":"v3k 6x2",
    "addr:street":"Clipper St",
    "iso:country":"CA",
    "sg:address":"61 Clipper St",
    "sg:city":"Coquitlam",
    "sg:classifiers":[
        {
            "category":"Manufacturing",
            "subcategory":"Paper Products",
            "type":"Manufacturing & Wholesale Goods"
        }
    ],
    "sg:phone":"+1 604 525 4764",
    "sg:postcode":"V3K 6X2",
    "sg:province":"BC",
    "sg:tags":[
        "label"
    ],
    "wof:name":"Associated Labels",
    "wof:placetype":"venue"
},
  "geometry": {"coordinates":[-122.852615,49.227715],"type":"Point"}
}