{
  "type": "Feature",
  "properties": {
    "iso:country":"CA",
    "sg:city":"Parksville",
    "sg:classifiers":[
        {
            "category":"Health Services",
            "subcategory":"Doctor",
            "type":"Services"
        }
    ],
    "sg:phone":"+1 250 248 5049",
    "sg:postcode":"V9P 2H7",
    "sg:province":"BC",
    "sg:tags":[
        "clinic"
    ],
    "wof:name":"Parksville Acupuncture Clinic",
    "wof:placetype":"venue"
},
  "geometry": {"coordinates":[-124.308761597,49.3203849792],"type":"Point"}
}