{
  "type": "Feature",
  "properties": {
    "iso:country":"CA",
    "sg:address":"737 Ouellette Ave",
    "sg:city":"Windsor",
    "sg:classifiers":[
        {
            "category":"Real Estate",
            "subcategory":"Real Estate Operator",
            "type":"Services"
        }
    ],
    "sg:phone":"+1 519 254 9259",
    "sg:postcode":"N9A 4J4",
    "sg:province":"ON",
    "sg:tags":[
        "apartment"
    ],
    "wof:name":"Ouellette Tower's Apartments",
    "wof:placetype":"venue"
},
  "geometry": {"coordinates":[-83.035934,42.312344],"type":"Point"}
}