{
  "type": "Feature",
  "properties": {
    "addr:full":"Lennoxville QC J1M 1L8",
    "addr:postcode":"j1m 1l8",
    "iso:country":"CA",
    "sg:city":"Lennoxville",
    "sg:classifiers":[
        {
            "category":"Manufacturing",
            "subcategory":"Furniture",
            "type":"Manufacturing & Wholesale Goods"
        }
    ],
    "sg:phone":"+1 819 569 5976",
    "sg:postcode":"J1M 1L8",
    "sg:province":"QC",
    "sg:tags":[
        "maker",
        "cabinet"
    ],
    "wof:name":"Wright, Mark",
    "wof:placetype":"venue"
},
  "geometry": {"coordinates":[-71.85437011720001,45.3677139282],"type":"Point"}
}