{
  "type": "Feature",
  "properties": {
    "iso:country":"CA",
    "sg:address":"1864 Rue Sainte-Catherine O",
    "sg:city":"Montreal",
    "sg:classifiers":[
        {
            "category":"Personal",
            "subcategory":"Barber",
            "type":"Services"
        }
    ],
    "sg:phone":"+1 514 932 1378",
    "sg:postcode":"H3H 1M1",
    "sg:province":"QC",
    "wof:name":"Albanese Barber Shop",
    "wof:placetype":"venue"
},
  "geometry": {"coordinates":[-73.5517196655,45.5231208801],"type":"Point"}
}