{
  "type": "Feature",
  "properties": {
    "addr:full":"PO Box 122 Mine Centre ON P0W 1H0",
    "addr:housenumber":"po",
    "addr:postcode":"p0w 1h0",
    "addr:street":"Box 122 Mine",
    "iso:country":"CA",
    "sg:address":"PO Box 122",
    "sg:city":"Mine Centre",
    "sg:classifiers":[
        {
            "category":"Travel",
            "subcategory":"Campground",
            "type":"Entertainment"
        }
    ],
    "sg:phone":"+1 807 599 2713",
    "sg:postcode":"P0W 1H0",
    "sg:province":"ON",
    "sg:tags":[
        "camp"
    ],
    "wof:name":"Mudge's Camp",
    "wof:placetype":"venue"
},
  "geometry": {"coordinates":[-92.640602,48.760971],"type":"Point"}
}