{
  "type": "Feature",
  "properties": {
    "iso:country":"CA",
    "sg:address":"1667 Boul Saint-Joseph",
    "sg:city":"Drummondville",
    "sg:classifiers":[
        {
            "category":"Professional",
            "subcategory":"Lawyer & Legal Services",
            "type":"Services"
        }
    ],
    "sg:phone":"+1 819 474 2770",
    "sg:postcode":"J2C 2G5",
    "sg:province":"QC",
    "sg:tags":[
        "attorney"
    ],
    "wof:name":"Rheaume, Gilles",
    "wof:placetype":"venue"
},
  "geometry": {"coordinates":[-72.493233,45.88081],"type":"Point"}
}