{
  "type": "Feature",
  "properties": {
    "addr:full":"Winnipeg MB R3J 0R2",
    "addr:postcode":"r3j 0r2",
    "iso:country":"CA",
    "sg:city":"Winnipeg",
    "sg:classifiers":[
        {
            "category":"Real Estate",
            "subcategory":"Real Estate Agent",
            "type":"Services"
        }
    ],
    "sg:phone":"+1 204 925 2900",
    "sg:postcode":"R3J 0R2",
    "sg:province":"MB",
    "wof:name":"Judy Lindsay Team Realty",
    "wof:placetype":"venue"
},
  "geometry": {"coordinates":[-97.27322387700001,49.8782958984],"type":"Point"}
}