{
  "type": "Feature",
  "properties": {
    "iso:country":"CA",
    "sg:address":"2252 Hwy 24",
    "sg:city":"Simcoe",
    "sg:classifiers":[
        {
            "category":"Retail",
            "subcategory":"Car Wash",
            "type":"Services"
        }
    ],
    "sg:phone":"+1 519 426 5522",
    "sg:postcode":"N3Y 4K2",
    "sg:province":"ON",
    "sg:tags":[
        "automobile",
        "rustproofing",
        "undercoating",
        "detail"
    ],
    "wof:name":"Rct Car Care Ctr",
    "wof:placetype":"venue"
},
  "geometry": {"coordinates":[-80.3152313232,42.8685302734],"type":"Point"}
}