{
  "type": "Feature",
  "properties": {
    "addr:full":"Surrey BC V3S 4C8",
    "addr:postcode":"v3s 4c8",
    "iso:country":"CA",
    "sg:city":"Surrey",
    "sg:classifiers":[
        {
            "category":"Professional",
            "subcategory":"Research",
            "type":"Services"
        }
    ],
    "sg:phone":"+1 604 574 3100",
    "sg:postcode":"V3S 4C8",
    "sg:province":"BC",
    "sg:tags":[
        "environmental",
        "ecological"
    ],
    "wof:name":"Carr Environmental Consultants",
    "wof:placetype":"venue"
},
  "geometry": {"coordinates":[-122.734909,49.10397],"type":"Point"}
}