{
  "type": "Feature",
  "properties": {
    "addr:full":"8975 Rue Pascal-Gagnon Saint-Leonard QC H1P 1Z4",
    "addr:housenumber":"8975",
    "addr:postcode":"h1p 1z4",
    "addr:street":"Rue Pascal-Gagnon",
    "iso:country":"CA",
    "sg:address":"8975 Rue Pascal-Gagnon",
    "sg:city":"Saint-Leonard",
    "sg:classifiers":[
        {
            "category":"Shopping",
            "type":"Retail Goods"
        }
    ],
    "sg:phone":"+1 514 327 6110",
    "sg:postcode":"H1P 1Z4",
    "sg:province":"QC",
    "sg:tags":[
        "awning",
        "canopy",
        "railing"
    ],
    "wof:name":"Mondi Les Produits D'Aluminium",
    "wof:placetype":"venue"
},
  "geometry": {"coordinates":[-73.5953826904,45.6054801941],"type":"Point"}
}