{
  "type": "Feature",
  "properties": {
    "iso:country":"CA",
    "sg:city":"Montreal",
    "sg:classifiers":[
        {
            "category":"Shopping",
            "type":"Retail Goods"
        }
    ],
    "sg:phone":"+1 514 721 4616",
    "sg:postcode":"H2E 1V7",
    "sg:province":"QC",
    "sg:tags":[
        "hearing",
        "equipment",
        "supply",
        "impaired"
    ],
    "wof:name":"Audioprothesiste Beauchesne",
    "wof:placetype":"venue"
},
  "geometry": {"coordinates":[-73.60305,45.552345],"type":"Point"}
}