{
  "type": "Feature",
  "properties": {
    "addr:full":"440 Rue Sainte-Helene Montreal QC H2Y 2K7",
    "addr:housenumber":"440",
    "addr:postcode":"h2y 2k7",
    "addr:street":"Rue Sainte-Helene",
    "iso:country":"CA",
    "sg:address":"440 Rue Sainte-Helene",
    "sg:city":"Montreal",
    "sg:classifiers":[
        {
            "category":"Freight",
            "type":"Transportation"
        }
    ],
    "sg:phone":"+1 514 288 8844",
    "sg:postcode":"H2Y 2K7",
    "sg:province":"QC",
    "sg:tags":[
        "shipping",
        "agent"
    ],
    "wof:name":"All Seas Shipping Corp",
    "wof:placetype":"venue"
},
  "geometry": {"coordinates":[-73.55836499999999,45.50119],"type":"Point"}
}