{
  "type": "Feature",
  "properties": {
    "addr:full":"NE 19 11 15E Rennie MB R0E 1R0",
    "addr:housenumber":"11 15e",
    "addr:postcode":"r0e 1r0",
    "addr:street":"Ne 19;Rennie",
    "iso:country":"CA",
    "sg:address":"NE 19 11 15E",
    "sg:city":"Rennie",
    "sg:classifiers":[
        {
            "category":"Travel",
            "subcategory":"Hotels & Motels",
            "type":"Entertainment"
        }
    ],
    "sg:phone":"+1 204 369 5336",
    "sg:postcode":"R0E 1R0",
    "sg:province":"MB",
    "sg:tags":[
        "resort"
    ],
    "wof:name":"Inverness Falls Resort",
    "wof:placetype":"venue"
},
  "geometry": {"coordinates":[-95.5551071167,49.8531303406],"type":"Point"}
}