{
  "type": "Feature",
  "properties": {
    "addr:full":"235 Brock St Kingston ON K7L 1S3",
    "addr:housenumber":"235",
    "addr:postcode":"k7l 1s3",
    "addr:street":"Brock St",
    "iso:country":"CA",
    "sg:address":"235 Brock St",
    "sg:city":"Kingston",
    "sg:classifiers":[
        {
            "category":"Manufacturing",
            "subcategory":"Printing",
            "type":"Manufacturing & Wholesale Goods"
        }
    ],
    "sg:phone":"+1 613 547 9229",
    "sg:postcode":"K7L 1S3",
    "sg:province":"ON",
    "sg:tags":[
        "multimedia"
    ],
    "wof:name":"Softlight Inc",
    "wof:placetype":"venue"
},
  "geometry": {"coordinates":[-76.4884109497,44.231628418],"type":"Point"}
}