{
  "type": "Feature",
  "properties": {
    "addr:full":"165 St David St N Fergus ON N1M 2J5",
    "addr:housenumber":"165",
    "addr:postcode":"n1m 2j5",
    "addr:street":"St David St N",
    "iso:country":"CA",
    "sg:address":"165 St David St N",
    "sg:city":"Fergus",
    "sg:classifiers":[
        {
            "category":"Personal",
            "subcategory":"Beauty Salon",
            "type":"Services"
        }
    ],
    "sg:phone":"+1 519 787 2703",
    "sg:postcode":"N1M 2J5",
    "sg:province":"ON",
    "wof:name":"Village Hairstyling",
    "wof:placetype":"venue"
},
  "geometry": {"coordinates":[-80.37861599999999,43.706005],"type":"Point"}
}