{
  "type": "Feature",
  "properties": {
    "addr:full":"47 Maple Ave E Hamiota MB R0M 0T0",
    "addr:housenumber":"47",
    "addr:postcode":"r0m 0t0",
    "addr:street":"Maple Ave E Hamiota",
    "iso:country":"CA",
    "sg:address":"47 Maple Ave E",
    "sg:city":"Hamiota",
    "sg:classifiers":[
        {
            "category":"Shopping",
            "subcategory":"Jewelry",
            "type":"Retail Goods"
        }
    ],
    "sg:phone":"+1 204 764 2565",
    "sg:postcode":"R0M 0T0",
    "sg:province":"MB",
    "sg:tags":[
        "jeweler"
    ],
    "wof:name":"Oakden's Jewellery",
    "wof:placetype":"venue"
},
  "geometry": {"coordinates":[-100.599846,50.18251],"type":"Point"}
}