{
  "type": "Feature",
  "properties": {
    "addr:full":"7886 Boul Champlain Lasalle QC H8P 1B3",
    "addr:housenumber":"7886",
    "addr:postcode":"h8p 1b3",
    "addr:street":"Boul Champlain",
    "iso:country":"CA",
    "sg:address":"7886 Boul Champlain",
    "sg:city":"Lasalle",
    "sg:classifiers":[
        {
            "category":"Personal",
            "subcategory":"Beauty Salon",
            "type":"Services"
        }
    ],
    "sg:phone":"+1 514 365 1010",
    "sg:postcode":"H8P 1B3",
    "sg:province":"QC",
    "wof:name":"Carisme Coiffure Elle Et Lui",
    "wof:placetype":"venue"
},
  "geometry": {"coordinates":[-73.6097946167,45.4282569885],"type":"Point"}
}