{
  "type": "Feature",
  "properties": {
    "iso:country":"CA",
    "sg:city":"Hunter River",
    "sg:classifiers":[
        {
            "category":"Travel",
            "subcategory":"Hotels & Motels",
            "type":"Entertainment"
        }
    ],
    "sg:phone":"+1 902 963 3324",
    "sg:postcode":"C0A 1N0",
    "sg:province":"PE",
    "sg:tags":[
        "breakfast",
        "accommodation",
        "bed"
    ],
    "wof:name":"Cavendish Wild Rose Country",
    "wof:placetype":"venue"
},
  "geometry": {"coordinates":[-63.3431472778,46.3517608643],"type":"Point"}
}