{
  "type": "Feature",
  "properties": {
    "addr:full":"Castlegar BC V1N 2X1",
    "addr:postcode":"v1n 2x1",
    "iso:country":"CA",
    "sg:city":"Castlegar",
    "sg:classifiers":[
        {
            "category":"Organizations",
            "subcategory":"Labor Organization",
            "type":"Services"
        }
    ],
    "sg:phone":"+1 250 365 2813",
    "sg:postcode":"V1N 2X1",
    "sg:province":"BC",
    "wof:name":"United Brotherhood-Carpenters",
    "wof:placetype":"venue"
},
  "geometry": {"coordinates":[-117.650993347,49.287399292],"type":"Point"}
}