{
  "type": "Feature",
  "properties": {
    "addr:full":"186 Barrette St Vanier ON K1L 8A1",
    "addr:housenumber":"186",
    "addr:postcode":"k1l 8a1",
    "addr:street":"Barrette St",
    "iso:country":"CA",
    "sg:address":"186 Barrette St",
    "sg:city":"Vanier",
    "sg:classifiers":[
        {
            "category":"Restaurant",
            "type":"Food & Drink"
        }
    ],
    "sg:phone":"+1 613 749 4877",
    "sg:postcode":"K1L 8A1",
    "sg:province":"ON",
    "wof:name":"IL Vagabondo Restaurant",
    "wof:placetype":"venue"
},
  "geometry": {"coordinates":[-75.671654,45.441505],"type":"Point"}
}