{
  "type": "Feature",
  "properties": {
    "addr:full":"1005 Ch DE Saint-Jean LA Prairie QC J5R 2L6",
    "addr:housenumber":"1005",
    "addr:postcode":"j5r 2l6",
    "addr:street":"Ch De Saint-Jean",
    "iso:country":"CA",
    "sg:address":"1005 Ch DE Saint-Jean",
    "sg:city":"LA Prairie",
    "sg:classifiers":[
        {
            "category":"Restaurant",
            "type":"Food & Drink"
        }
    ],
    "sg:phone":"+1 450 444 3333",
    "sg:postcode":"J5R 2L6",
    "sg:province":"QC",
    "sg:tags":[
        "pizza"
    ],
    "wof:name":"Jacques Cartier Pizza",
    "wof:placetype":"venue"
},
  "geometry": {"coordinates":[-73.47814200000001,45.411671],"type":"Point"}
}