{
  "type": "Feature",
  "properties": {
    "addr:full":"2360 Ch Lucerne Mont-Royal QC H3R 2K2",
    "addr:postcode":"2360;h3r 2k2",
    "addr:street":"Ch Lucerne",
    "iso:country":"CA",
    "sg:address":"2360 Ch Lucerne",
    "sg:city":"Mont-Royal",
    "sg:classifiers":[
        {
            "category":"Professional",
            "subcategory":"Computer Services",
            "type":"Services"
        }
    ],
    "sg:phone":"+1 514 344 4007",
    "sg:postcode":"H3R 2K2",
    "sg:province":"QC",
    "sg:tags":[
        "internet"
    ],
    "wof:name":"Microware Net",
    "wof:placetype":"venue"
},
  "geometry": {"coordinates":[-73.6615219116,45.5072784424],"type":"Point"}
}