{
  "type": "Feature",
  "properties": {
    "addr:full":"Brandon MB R7A 4R8",
    "addr:postcode":"r7a 4r8",
    "iso:country":"CA",
    "sg:city":"Brandon",
    "sg:classifiers":[
        {
            "category":"Building & Trades",
            "subcategory":"Electrical",
            "type":"Services"
        }
    ],
    "sg:phone":"+1 204 727 2722",
    "sg:postcode":"R7A 4R8",
    "sg:province":"MB",
    "sg:tags":[
        "electric",
        "elevator",
        "contractor"
    ],
    "wof:name":"Brandon Elevator & Electric",
    "wof:placetype":"venue"
},
  "geometry": {"coordinates":[-99.955406,49.837242],"type":"Point"}
}