{
  "type": "Feature",
  "properties": {
    "addr:full":"13471 Mitchell Rd Richmond BC V6V 1M7",
    "addr:housenumber":"13471",
    "addr:postcode":"v6v 1m7",
    "addr:street":"Mitchell Rd",
    "iso:country":"CA",
    "sg:address":"13471 Mitchell Rd",
    "sg:city":"Richmond",
    "sg:classifiers":[
        {
            "category":"Wholesale",
            "subcategory":"Auto Parts",
            "type":"Manufacturing & Wholesale Goods"
        }
    ],
    "sg:phone":"+1 604 321 0888",
    "sg:postcode":"V6V 1M7",
    "sg:province":"BC",
    "sg:tags":[
        "automobile",
        "wrecking"
    ],
    "wof:name":"Ceegee's Auto Wrecking",
    "wof:placetype":"venue"
},
  "geometry": {"coordinates":[-123.073326111,49.2058944702],"type":"Point"}
}