{
  "type": "Feature",
  "properties": {
    "iso:country":"CA",
    "sg:address":"49 Hwy 289",
    "sg:city":"Brookfield",
    "sg:classifiers":[
        {
            "category":"Organizations",
            "subcategory":"Religious Organization",
            "type":"Services"
        }
    ],
    "sg:phone":"+1 902 673 3363",
    "sg:postcode":"B0N 1C0",
    "sg:province":"NS",
    "sg:tags":[
        "church"
    ],
    "wof:name":"United Church of Canada",
    "wof:placetype":"venue"
},
  "geometry": {"coordinates":[-63.285538,45.252285],"type":"Point"}
}