{
  "type": "Feature",
  "properties": {
    "addr:full":"7299 East Danbro Cres Mississauga ON L5N 6P8",
    "addr:housenumber":"7299",
    "addr:postcode":"l5n 6p8",
    "addr:street":"East Danbro Cres",
    "iso:country":"CA",
    "sg:address":"7299 East Danbro Cres",
    "sg:city":"Mississauga",
    "sg:classifiers":[
        {
            "category":"Manufacturing",
            "subcategory":"Motor Vehicles & Parts",
            "type":"Manufacturing & Wholesale Goods"
        }
    ],
    "sg:phone":"+1 905 819 9900",
    "sg:postcode":"L5N 6P8",
    "sg:province":"ON",
    "sg:tags":[
        "automobile"
    ],
    "wof:name":"Matsu Manufacturing Inc",
    "wof:placetype":"venue"
},
  "geometry": {"coordinates":[-79.77551269529999,43.6053009033],"type":"Point"}
}