{
  "type": "Feature",
  "properties": {
    "iso:country":"CA",
    "sg:address":"1903 9 Ave S",
    "sg:city":"Lethbridge",
    "sg:classifiers":[
        {
            "category":"Health Services",
            "subcategory":"Doctor",
            "type":"Services"
        }
    ],
    "sg:phone":"+1 403 320 0633",
    "sg:postcode":"T1J 1W8",
    "sg:province":"AB",
    "sg:tags":[
        "physician",
        "surgeon"
    ],
    "wof:name":"Schuld, R MD",
    "wof:placetype":"venue"
},
  "geometry": {"coordinates":[-112.814491272,49.6867752075],"type":"Point"}
}