{
  "type": "Feature",
  "properties": {
    "iso:country":"CA",
    "sg:city":"Saint-Adolphe-D'Howard",
    "sg:classifiers":[
        {
            "category":"Building & Trades",
            "subcategory":"Electrical",
            "type":"Services"
        }
    ],
    "sg:phone":"+1 819 327 2211",
    "sg:postcode":"J0T 2B0",
    "sg:province":"QC",
    "sg:tags":[
        "electric",
        "contractor"
    ],
    "wof:name":"Marcel Gaudet Electrique Inc",
    "wof:placetype":"venue"
},
  "geometry": {"coordinates":[-71.029296875,48.5650138855],"type":"Point"}
}