{
  "type": "Feature",
  "properties": {
    "addr:full":"61 Mcbrine Pl Kitchener ON N2R 1H5",
    "addr:housenumber":"61",
    "addr:postcode":"n2r 1h5",
    "addr:street":"Mcbrine Pl",
    "iso:country":"CA",
    "sg:address":"61 Mcbrine Pl",
    "sg:city":"Kitchener",
    "sg:classifiers":[
        {
            "category":"Home & Garden",
            "subcategory":"Home Furnishings",
            "type":"Retail Goods"
        }
    ],
    "sg:phone":"+1 519 748 2211",
    "sg:postcode":"N2R 1H5",
    "sg:province":"ON",
    "sg:tags":[
        "cutlery"
    ],
    "wof:name":"Minit of Canada Ltd",
    "wof:placetype":"venue"
},
  "geometry": {"coordinates":[-80.47592899999999,43.401146],"type":"Point"}
}