{
  "type": "Feature",
  "properties": {
    "addr:full":"Thornhill ON L4J 8J1",
    "addr:postcode":"l4j 8j1",
    "iso:country":"CA",
    "sg:city":"Thornhill",
    "sg:classifiers":[
        {
            "category":"Personal",
            "subcategory":"Beauty Salon",
            "type":"Services"
        }
    ],
    "sg:phone":"+1 905 882 9614",
    "sg:postcode":"L4J 8J1",
    "sg:province":"ON",
    "wof:name":"Hair Salon Your Style",
    "wof:placetype":"venue"
},
  "geometry": {"coordinates":[-79.422737,43.807755],"type":"Point"}
}