{
  "type": "Feature",
  "properties": {
    "addr:full":"6 Ch Guilbault Saint-Paul QC J0K 3E0",
    "addr:housenumber":"6",
    "addr:postcode":"j0k 3e0",
    "addr:street":"Ch Guilbault",
    "iso:country":"CA",
    "sg:address":"6 Ch Guilbault",
    "sg:city":"Saint-Paul",
    "sg:classifiers":[
        {
            "category":"Building & Trades",
            "subcategory":"Electrical",
            "type":"Services"
        }
    ],
    "sg:phone":"+1 450 754 4419",
    "sg:postcode":"J0K 3E0",
    "sg:province":"QC",
    "sg:tags":[
        "electric",
        "contractor"
    ],
    "wof:name":"Multi-Maitre Electrique Inc",
    "wof:placetype":"venue"
},
  "geometry": {"coordinates":[-73.412567,45.953941],"type":"Point"}
}