{
  "type": "Feature",
  "properties": {
    "addr:full":"Markham ON L3R 9Y7",
    "addr:postcode":"l3r 9y7",
    "iso:country":"CA",
    "sg:city":"Markham",
    "sg:classifiers":[
        {
            "category":"Insurance",
            "subcategory":"Insurance Agent",
            "type":"Services"
        }
    ],
    "sg:phone":"+1 905 513 8466",
    "sg:postcode":"L3R 9Y7",
    "sg:province":"ON",
    "wof:name":"Safety Insurance Svc Ltd",
    "wof:placetype":"venue"
},
  "geometry": {"coordinates":[-79.356995,43.844994],"type":"Point"}
}