{
  "type": "Feature",
  "properties": {
    "addr:full":"377 Kearney Lake Rd Bedford NS B4B 1H6",
    "addr:housenumber":"377",
    "addr:postcode":"b4b 1h6",
    "addr:street":"Kearney Lake Rd",
    "iso:country":"CA",
    "sg:address":"377 Kearney Lake Rd",
    "sg:city":"Bedford",
    "sg:classifiers":[
        {
            "category":"Building & Trades",
            "subcategory":"Construction",
            "type":"Services"
        }
    ],
    "sg:phone":"+1 902 443 0431",
    "sg:postcode":"B4B 1H6",
    "sg:province":"NS",
    "sg:tags":[
        "general",
        "contractor"
    ],
    "wof:name":"Largo Contracting Ltd",
    "wof:placetype":"venue"
},
  "geometry": {"coordinates":[-63.6954040527,44.6966094971],"type":"Point"}
}