{
  "type": "Feature",
  "properties": {
    "iso:country":"CA",
    "sg:address":"640 North St",
    "sg:city":"Dresden",
    "sg:classifiers":[
        {
            "category":"Health Services",
            "subcategory":"Doctor",
            "type":"Services"
        }
    ],
    "sg:phone":"+1 519 683 2082",
    "sg:postcode":"N0P 1M0",
    "sg:province":"ON",
    "sg:tags":[
        "physician",
        "surgeon"
    ],
    "wof:name":"Thompson, D MD",
    "wof:placetype":"venue"
},
  "geometry": {"coordinates":[-82.179901,42.584332],"type":"Point"}
}