{
  "type": "Feature",
  "properties": {
    "addr:full":"135 Coldwater Rd W Orillia ON L3V 3L5",
    "addr:housenumber":"135",
    "addr:postcode":"l3v 3l5",
    "addr:street":"Coldwater Rd W",
    "iso:country":"CA",
    "sg:address":"135 Coldwater Rd W",
    "sg:city":"Orillia",
    "sg:classifiers":[
        {
            "category":"Shopping",
            "subcategory":"Shoes",
            "type":"Retail Goods"
        }
    ],
    "sg:phone":"+1 705 326 5808",
    "sg:postcode":"L3V 3L5",
    "sg:province":"ON",
    "sg:tags":[
        "orthopedic",
        "appliance"
    ],
    "wof:name":"Thomas Wood Pedorthic Clinic",
    "wof:placetype":"venue"
},
  "geometry": {"coordinates":[-79.427986,44.609123],"type":"Point"}
}