{
  "type": "Feature",
  "properties": {
    "addr:full":"Riverton MB R0C 2R0",
    "addr:postcode":"r0c 2r0",
    "iso:country":"CA",
    "sg:city":"Riverton",
    "sg:classifiers":[
        {
            "category":"Food & Beverages",
            "subcategory":"Groceries & Convenience Stores",
            "type":"Retail Goods"
        }
    ],
    "sg:phone":"+1 204 378 2999",
    "sg:postcode":"R0C 2R0",
    "sg:province":"MB",
    "sg:tags":[
        "grocer"
    ],
    "wof:name":"Grindstone General Store",
    "wof:placetype":"venue"
},
  "geometry": {"coordinates":[-96.99645200000001,50.998409],"type":"Point"}
}