{
  "type": "Feature",
  "properties": {
    "addr:full":"Shippagan NB E8S 1B9",
    "addr:postcode":"e8s 1b9",
    "iso:country":"CA",
    "sg:city":"Shippagan",
    "sg:classifiers":[
        {
            "category":"Personal",
            "subcategory":"Shoe Repair & Shine",
            "type":"Services"
        }
    ],
    "sg:phone":"+1 506 336 8956",
    "sg:postcode":"E8S 1B9",
    "sg:province":"NB",
    "sg:tags":[
        "repairing",
        "boot",
        "shoes"
    ],
    "wof:name":"Chaussures & Uniformes Hache",
    "wof:placetype":"venue"
},
  "geometry": {"coordinates":[-64.7087631226,47.7438468933],"type":"Point"}
}