{
  "type": "Feature",
  "properties": {
    "addr:full":"2493 Lake Shore Blvd W #814 Etobicoke ON M8V 1C7",
    "addr:housenumber":"2493",
    "addr:postcode":"m8v 1c7",
    "addr:street":"Lake Shore Blvd W # 814",
    "iso:country":"CA",
    "sg:address":"2493 Lake Shore Blvd W #814",
    "sg:city":"Etobicoke",
    "sg:classifiers":[
        {
            "category":"Shopping",
            "subcategory":"Gifts & Souvenirs",
            "type":"Retail Goods"
        }
    ],
    "sg:phone":"+1 416 253 5881",
    "sg:postcode":"M8V 1C7",
    "sg:province":"ON",
    "sg:tags":[
        "shop"
    ],
    "wof:name":"Salt Crystal Rock Creations",
    "wof:placetype":"venue"
},
  "geometry": {"coordinates":[-79.48967,43.612598],"type":"Point"}
}