{
  "type": "Feature",
  "properties": {
    "iso:country":"CA",
    "sg:address":"1196 Torbay Rd",
    "sg:city":"Torbay",
    "sg:classifiers":[
        {
            "category":"Building & Trades",
            "subcategory":"Landscaping Services",
            "type":"Services"
        }
    ],
    "sg:phone":"+1 709 673 5898",
    "sg:postcode":"A1K 1A4",
    "sg:province":"NL",
    "sg:tags":[
        "control",
        "equipment",
        "pest",
        "tree",
        "supply"
    ],
    "wof:name":"Newfoundland Vegetation Cntrl",
    "wof:placetype":"venue"
},
  "geometry": {"coordinates":[-52.7252426147,47.6514816284],"type":"Point"}
}