{
  "type": "Feature",
  "properties": {
    "iso:country":"CA",
    "sg:address":"48 Rue Du Petit-Champlain",
    "sg:city":"Quebec",
    "sg:classifiers":[
        {
            "category":"Manufacturing",
            "subcategory":"Jewelry",
            "type":"Manufacturing & Wholesale Goods"
        }
    ],
    "sg:phone":"+1 418 692 4633",
    "sg:postcode":"G1K 4H4",
    "sg:province":"QC",
    "sg:tags":[
        "craftsman"
    ],
    "wof:name":"Louis Perrier Joaillier",
    "wof:placetype":"venue"
},
  "geometry": {"coordinates":[-71.203728,46.811993],"type":"Point"}
}