{
  "type": "Feature",
  "properties": {
    "addr:full":"309 Main St Foam Lake SK S0A 1A0",
    "addr:housenumber":"309",
    "addr:postcode":"s0a 1a0",
    "addr:street":"Main St",
    "iso:country":"CA",
    "sg:address":"309 Main St",
    "sg:city":"Foam Lake",
    "sg:classifiers":[
        {
            "category":"Recreation",
            "type":"Entertainment"
        }
    ],
    "sg:phone":"+1 306 272 4188",
    "sg:postcode":"S0A 1A0",
    "sg:province":"SK",
    "sg:tags":[
        "hall",
        "auditorium"
    ],
    "wof:name":"Sunset Parish Hall",
    "wof:placetype":"venue"
},
  "geometry": {"coordinates":[-103.53357699999999,51.641315],"type":"Point"}
}