{
  "type": "Feature",
  "properties": {
    "addr:full":"PO Box 2086 STN Main Strathmore AB T1P 1K1",
    "addr:housenumber":"po",
    "addr:postcode":"t1p 1k1",
    "addr:street":"Box 2086 Stn Main",
    "iso:country":"CA",
    "sg:address":"PO Box 2086 STN Main",
    "sg:city":"Strathmore",
    "sg:classifiers":[
        {
            "category":"Wholesale",
            "subcategory":"Farm Supplies",
            "type":"Manufacturing & Wholesale Goods"
        }
    ],
    "sg:phone":"+1 403 934 2885",
    "sg:postcode":"T1P 1K1",
    "sg:province":"AB",
    "sg:tags":[
        "chemical",
        "agricultural"
    ],
    "wof:name":"Wheatland Agro Ctr",
    "wof:placetype":"venue"
},
  "geometry": {"coordinates":[-113.400291,51.041306],"type":"Point"}
}