{
  "type": "Feature",
  "properties": {
    "addr:full":"634 7th St Gretna MB R0G 0V0",
    "addr:housenumber":"634",
    "addr:postcode":"r0g 0v0",
    "addr:street":"7Th St",
    "iso:country":"CA",
    "sg:address":"634 7th St",
    "sg:city":"Gretna",
    "sg:classifiers":[
        {
            "category":"Retail",
            "subcategory":"Auto Repair",
            "type":"Services"
        }
    ],
    "sg:phone":"+1 204 327 5577",
    "sg:postcode":"R0G 0V0",
    "sg:province":"MB",
    "sg:tags":[
        "repairing",
        "automobile"
    ],
    "wof:name":"Albert's Service Ctr",
    "wof:placetype":"venue"
},
  "geometry": {"coordinates":[-97.5609970093,49.0079307556],"type":"Point"}
}