{
  "type": "Feature",
  "properties": {
    "iso:country":"CA",
    "sg:address":"126 Rue Bennett O",
    "sg:city":"Thetford Mines",
    "sg:classifiers":[
        {
            "category":"Manufacturing",
            "subcategory":"Printing",
            "type":"Manufacturing & Wholesale Goods"
        }
    ],
    "sg:phone":"+1 418 335 5707",
    "sg:postcode":"G6G 2R4",
    "sg:province":"QC",
    "sg:tags":[
        "printer"
    ],
    "wof:name":"Imprimerie Roy & Laliberte Inc",
    "wof:placetype":"venue"
},
  "geometry": {"coordinates":[-71.2998123169,46.0889282227],"type":"Point"}
}