{
  "type": "Feature",
  "properties": {
    "iso:country":"CA",
    "sg:city":"Waterloo",
    "sg:classifiers":[
        {
            "category":"Shopping",
            "subcategory":"Discount & Variety Stores",
            "type":"Retail Goods"
        }
    ],
    "sg:phone":"+1 519 884 5555",
    "sg:postcode":"N2J 4K8",
    "sg:province":"ON",
    "wof:name":"Erb Variety",
    "wof:placetype":"venue"
},
  "geometry": {"coordinates":[-80.518738,43.465603],"type":"Point"}
}