{
  "type": "Feature",
  "properties": {
    "iso:country":"CA",
    "sg:address":"899 Water St",
    "sg:city":"Peterborough",
    "sg:classifiers":[
        {
            "category":"Retail",
            "subcategory":"Auto Repair",
            "type":"Services"
        }
    ],
    "sg:phone":"+1 705 745 3603",
    "sg:postcode":"K9H 3P2",
    "sg:province":"ON",
    "sg:tags":[
        "repairing",
        "automobile",
        "rustproofing",
        "undercoating"
    ],
    "wof:name":"Ruffo's Automotive Pro",
    "wof:placetype":"venue"
},
  "geometry": {"coordinates":[-78.31591796879999,44.3225135803],"type":"Point"}
}