{
  "type": "Feature",
  "properties": {
    "iso:country":"CA",
    "sg:address":"716 Industrial Road No 1",
    "sg:city":"Cranbrook",
    "sg:classifiers":[
        {
            "category":"Manufacturing",
            "subcategory":"Tools & Machinery",
            "type":"Manufacturing & Wholesale Goods"
        }
    ],
    "sg:phone":"+1 250 426 2267",
    "sg:postcode":"V1C 4C6",
    "sg:province":"BC",
    "sg:tags":[
        "control",
        "fire",
        "extinguisher"
    ],
    "wof:name":"Guillevin International Inc",
    "wof:placetype":"venue"
},
  "geometry": {"coordinates":[-115.76282501199999,49.5204734802],"type":"Point"}
}