{
  "type": "Feature",
  "properties": {
    "addr:full":"112 Rue Principale Notre-Dame-Du-Laus QC J0X 2M0",
    "addr:housenumber":"112",
    "addr:postcode":"j0x 2m0",
    "addr:street":"Rue Principale",
    "iso:country":"CA",
    "sg:address":"112 Rue Principale",
    "sg:city":"Notre-Dame-Du-Laus",
    "sg:classifiers":[
        {
            "category":"Food & Beverages",
            "subcategory":"Groceries & Convenience Stores",
            "type":"Retail Goods"
        }
    ],
    "sg:phone":"+1 819 767 2243",
    "sg:postcode":"J0X 2M0",
    "sg:province":"QC",
    "sg:tags":[
        "grocer"
    ],
    "wof:name":"Epicerie Charbonneau",
    "wof:placetype":"venue"
},
  "geometry": {"coordinates":[-75.62481699999999,46.089752],"type":"Point"}
}