{
  "type": "Feature",
  "properties": {
    "addr:full":"300 Rochester St # 218 Ottawa ON K1R 7N4",
    "addr:housenumber":"300",
    "addr:postcode":"k1r 7n4",
    "addr:street":"Rochester St # 218",
    "iso:country":"CA",
    "sg:address":"300 Rochester St # 218",
    "sg:city":"Ottawa",
    "sg:classifiers":[
        {
            "category":"Education",
            "subcategory":"Special Training",
            "type":"Public Place"
        }
    ],
    "sg:phone":"+1 613 563 3776",
    "sg:postcode":"K1R 7N4",
    "sg:province":"ON",
    "sg:tags":[
        "school",
        "language"
    ],
    "wof:name":"Ottawa Chinese Language School",
    "wof:placetype":"venue"
},
  "geometry": {"coordinates":[-75.70977000000001,45.404896],"type":"Point"}
}