{
  "type": "Feature",
  "properties": {
    "addr:full":"2025 Ottawa St Windsor ON N8Y 1R6",
    "addr:housenumber":"2025",
    "addr:postcode":"n8y 1r6",
    "addr:street":"Ottawa St",
    "iso:country":"CA",
    "sg:address":"2025 Ottawa St",
    "sg:city":"Windsor",
    "sg:classifiers":[
        {
            "category":"Shopping",
            "subcategory":"Clothing, Apparel, & Fashions",
            "type":"Retail Goods"
        }
    ],
    "sg:phone":"+1 519 252 7684",
    "sg:postcode":"N8Y 1R6",
    "sg:province":"ON",
    "wof:name":"Chatty Collection",
    "wof:placetype":"venue"
},
  "geometry": {"coordinates":[-83.0049133301,42.3123054504],"type":"Point"}
}