{
  "type": "Feature",
  "properties": {
    "addr:full":"9620 Rue Saint-Patrick Lasalle QC H8R 1R8",
    "addr:housenumber":"9620",
    "addr:postcode":"h8r 1r8",
    "addr:street":"Rue Saint-Patrick",
    "iso:country":"CA",
    "sg:address":"9620 Rue Saint-Patrick",
    "sg:city":"Lasalle",
    "sg:classifiers":[
        {
            "category":"Professional",
            "subcategory":"Engineering",
            "type":"Services"
        }
    ],
    "sg:phone":"+1 514 366 2970",
    "sg:postcode":"H8R 1R8",
    "sg:province":"QC",
    "sg:tags":[
        "engineer"
    ],
    "wof:name":"Groupe-Conseil LA Salle Inc",
    "wof:placetype":"venue"
},
  "geometry": {"coordinates":[-73.653648,45.435841],"type":"Point"}
}