{
  "type": "Feature",
  "properties": {
    "addr:full":"7653 Rte Marie-Victorin Lotbiniere QC G0S 1S0",
    "addr:housenumber":"7653",
    "addr:postcode":"g0s 1s0",
    "addr:street":"Rte Marie-Victorin",
    "iso:country":"CA",
    "sg:address":"7653 Rte Marie-Victorin",
    "sg:city":"Lotbiniere",
    "sg:classifiers":[
        {
            "category":"Wholesale",
            "subcategory":"Fruits & Vegetables",
            "type":"Manufacturing & Wholesale Goods"
        }
    ],
    "sg:phone":"+1 418 796 2471",
    "sg:postcode":"G0S 1S0",
    "sg:province":"QC",
    "sg:tags":[
        "shipper"
    ],
    "wof:name":"Centre DE Parage P Plaisance",
    "wof:placetype":"venue"
},
  "geometry": {"coordinates":[-71.95494100000001,46.609558],"type":"Point"}
}