{
  "type": "Feature",
  "properties": {
    "addr:full":"6620 28 Ave NW Edmonton AB T6K 2R1",
    "addr:housenumber":"6620",
    "addr:postcode":"t6k 2r1",
    "addr:street":"28 Ave Nw",
    "iso:country":"CA",
    "sg:address":"6620 28 Ave NW",
    "sg:city":"Edmonton",
    "sg:classifiers":[
        {
            "category":"Health Services",
            "subcategory":"Nursing And Care Facility",
            "type":"Services"
        }
    ],
    "sg:phone":"+1 780 463 9810",
    "sg:postcode":"T6K 2R1",
    "sg:province":"AB",
    "sg:tags":[
        "home",
        "convalescent"
    ],
    "wof:name":"Millwoods Shepherd's Care Ctr",
    "wof:placetype":"venue"
},
  "geometry": {"coordinates":[-113.43601200000001,53.458534],"type":"Point"}
}