{
  "type": "Feature",
  "properties": {
    "addr:full":"42 Centre St Gimli MB R0C 1B0",
    "addr:housenumber":"42",
    "addr:postcode":"r0c 1b0",
    "addr:street":"Centre St",
    "iso:country":"CA",
    "sg:address":"42 Centre St",
    "sg:city":"Gimli",
    "sg:classifiers":[
        {
            "category":"Shopping",
            "subcategory":"Jewelry",
            "type":"Retail Goods"
        }
    ],
    "sg:phone":"+1 204 642 5039",
    "sg:postcode":"R0C 1B0",
    "sg:province":"MB",
    "sg:tags":[
        "jeweler"
    ],
    "wof:name":"Cronshaw Jewellers",
    "wof:placetype":"venue"
},
  "geometry": {"coordinates":[-96.9855270386,50.6319847107],"type":"Point"}
}