{
  "type": "Feature",
  "properties": {
    "addr:full":"39 Thome Cres Toronto ON M6H 2S6",
    "addr:housenumber":"39",
    "addr:postcode":"m6h 2s6",
    "addr:street":"Thome Cres",
    "iso:country":"CA",
    "sg:address":"39 Thome Cres",
    "sg:city":"Toronto",
    "sg:classifiers":[
        {
            "category":"Professional",
            "type":"Services"
        }
    ],
    "sg:phone":"+1 416 654 6356",
    "sg:postcode":"M6H 2S6",
    "sg:province":"ON",
    "sg:tags":[
        "arranger",
        "music",
        "composer"
    ],
    "wof:name":"Air in Motion Music Production",
    "wof:placetype":"venue"
},
  "geometry": {"coordinates":[-79.4334564209,43.6766357422],"type":"Point"}
}