{
  "type": "Feature",
  "properties": {
    "addr:full":"31499 Southern Dr Abbotsford BC V2T 5P1",
    "addr:housenumber":"31499",
    "addr:postcode":"v2t 5p1",
    "addr:street":"Southern Dr",
    "iso:country":"CA",
    "sg:address":"31499 Southern Dr",
    "sg:city":"Abbotsford",
    "sg:classifiers":[
        {
            "category":"Organizations",
            "subcategory":"Religious Organization",
            "type":"Services"
        }
    ],
    "sg:phone":"+1 604 556 7889",
    "sg:postcode":"V2T 5P1",
    "sg:province":"BC",
    "sg:tags":[
        "church"
    ],
    "wof:name":"Global Outreach Foundation",
    "wof:placetype":"venue"
},
  "geometry": {"coordinates":[-122.35193599999999,49.058975],"type":"Point"}
}