{
  "type": "Feature",
  "properties": {
    "addr:full":"1260 Rue Sainte-Helene Longueuil QC J4K 3S6",
    "addr:housenumber":"1260",
    "addr:postcode":"j4k 3s6",
    "addr:street":"Rue Sainte-Helene",
    "iso:country":"CA",
    "sg:address":"1260 Rue Sainte-Helene",
    "sg:city":"Longueuil",
    "sg:classifiers":[
        {
            "category":"Shopping",
            "subcategory":"Pharmacy",
            "type":"Retail Goods"
        }
    ],
    "sg:phone":"+1 450 674 6219",
    "sg:postcode":"J4K 3S6",
    "sg:province":"QC",
    "wof:name":"Hohuu Q Anh Pharmacy",
    "wof:placetype":"venue"
},
  "geometry": {"coordinates":[-73.499275,45.517899],"type":"Point"}
}