{
  "type": "Feature",
  "properties": {
    "addr:full":"9019 Rue Descartes # A Saint-Leonard QC H1R 3M3",
    "addr:housenumber":"9019",
    "addr:postcode":"h1r 3m3",
    "addr:street":"Rue Descartes # A",
    "iso:country":"CA",
    "sg:address":"9019 Rue Descartes # A",
    "sg:city":"Saint-Leonard",
    "sg:classifiers":[
        {
            "category":"Building & Trades",
            "subcategory":"Construction",
            "type":"Services"
        }
    ],
    "sg:phone":"+1 514 322 5607",
    "sg:postcode":"H1R 3M3",
    "sg:province":"QC",
    "sg:tags":[
        "masonry",
        "contractor"
    ],
    "wof:name":"Maconnerie Rosemont Inc",
    "wof:placetype":"venue"
},
  "geometry": {"coordinates":[-73.616859436,45.5824317932],"type":"Point"}
}