{
  "type": "Feature",
  "properties": {
    "addr:full":"156 Rue Beaubien E Montreal QC H2S 1R2",
    "addr:housenumber":"156",
    "addr:postcode":"h2s 1r2",
    "addr:street":"Rue Beaubien E",
    "iso:country":"CA",
    "sg:address":"156 Rue Beaubien E",
    "sg:city":"Montreal",
    "sg:classifiers":[
        {
            "category":"Autos & Motor Vehicles",
            "subcategory":"Automobile Sales",
            "type":"Retail Goods"
        }
    ],
    "sg:phone":"+1 514 272 8456",
    "sg:postcode":"H2S 1R2",
    "sg:province":"QC",
    "sg:tags":[
        "parts",
        "snowmobile",
        "accessory"
    ],
    "wof:name":"Entreprises Lucien Goyette Inc",
    "wof:placetype":"venue"
},
  "geometry": {"coordinates":[-73.60694122309999,45.5316352844],"type":"Point"}
}