{
  "type": "Feature",
  "properties": {
    "iso:country":"CA",
    "sg:address":"2095 Linmouth Terr",
    "sg:city":"Burlington",
    "sg:classifiers":[
        {
            "category":"Wholesale",
            "subcategory":"Hardware",
            "type":"Manufacturing & Wholesale Goods"
        }
    ],
    "sg:phone":"+1 905 639 7340",
    "sg:postcode":"L7P 1Y5",
    "sg:province":"ON",
    "sg:tags":[
        "furnace"
    ],
    "wof:name":"Gosley Heating Svc",
    "wof:placetype":"venue"
},
  "geometry": {"coordinates":[-79.8366012573,43.3544960022],"type":"Point"}
}