{
  "type": "Feature",
  "properties": {
    "addr:full":"25 Highway 17 W Deep River ON K0J 1P0",
    "addr:housenumber":"25",
    "addr:postcode":"k0j 1p0",
    "addr:street":"Highway 17 W",
    "iso:country":"CA",
    "sg:address":"25 Highway 17 W",
    "sg:city":"Deep River",
    "sg:classifiers":[
        {
            "category":"Autos & Motor Vehicles",
            "subcategory":"Automobile Sales",
            "type":"Retail Goods"
        }
    ],
    "sg:phone":"+1 613 584 3666",
    "sg:postcode":"K0J 1P0",
    "sg:province":"ON",
    "sg:tags":[
        "car",
        "dealer"
    ],
    "wof:name":"Esilman Auto",
    "wof:placetype":"venue"
},
  "geometry": {"coordinates":[-77.4926528931,46.0980758667],"type":"Point"}
}