{
  "type": "Feature",
  "properties": {
    "addr:full":"4 Lakeshore Rd W Oakville ON L6K 1C5",
    "addr:housenumber":"4",
    "addr:postcode":"l6k 1c5",
    "addr:street":"Lakeshore Rd W",
    "iso:country":"CA",
    "sg:address":"4 Lakeshore Rd W",
    "sg:city":"Oakville",
    "sg:classifiers":[
        {
            "category":"Restaurant",
            "type":"Food & Drink"
        }
    ],
    "sg:phone":"+1 905 849 8229",
    "sg:postcode":"L6K 1C5",
    "sg:province":"ON",
    "wof:name":"Subway Sandwiches & Salads",
    "wof:placetype":"venue"
},
  "geometry": {"coordinates":[-79.671982,43.442066],"type":"Point"}
}