{
  "type": "Feature",
  "properties": {
    "iso:country":"CA",
    "sg:city":"Chertsey",
    "sg:classifiers":[
        {
            "category":"Food & Beverages",
            "subcategory":"Groceries & Convenience Stores",
            "type":"Retail Goods"
        }
    ],
    "sg:phone":"+1 450 882 2054",
    "sg:postcode":"J0K 3K0",
    "sg:province":"QC",
    "wof:name":"Marche Chertsey Enr",
    "wof:placetype":"venue"
},
  "geometry": {"coordinates":[-73.89222717289999,46.0730705261],"type":"Point"}
}