{
  "type": "Feature",
  "properties": {
    "addr:full":"Stoney Creek ON L8G 1A7",
    "addr:postcode":"l8g 1a7",
    "iso:country":"CA",
    "sg:city":"Stoney Creek",
    "sg:classifiers":[
        {
            "category":"Health Services",
            "subcategory":"Doctor",
            "type":"Services"
        }
    ],
    "sg:phone":"+1 905 664 3236",
    "sg:postcode":"L8G 1A7",
    "sg:province":"ON",
    "sg:tags":[
        "dentist"
    ],
    "wof:name":"Kutcher, Victor DDS",
    "wof:placetype":"venue"
},
  "geometry": {"coordinates":[-79.76494598390001,43.2281455994],"type":"Point"}
}