{
  "type": "Feature",
  "properties": {
    "addr:full":"281 Fern Rd E Qualicum Beach BC V9K 1R1",
    "addr:housenumber":"281",
    "addr:postcode":"v9k 1r1",
    "addr:street":"Fern Rd E",
    "iso:country":"CA",
    "sg:address":"281 Fern Rd E",
    "sg:city":"Qualicum Beach",
    "sg:classifiers":[
        {
            "category":"Freight",
            "type":"Transportation"
        }
    ],
    "sg:phone":"+1 250 752 3606",
    "sg:postcode":"V9K 1R1",
    "sg:province":"BC",
    "sg:tags":[
        "commercial",
        "storage"
    ],
    "wof:name":"Eagle Mini Warehousing",
    "wof:placetype":"venue"
},
  "geometry": {"coordinates":[-124.430893,49.34613],"type":"Point"}
}