{
  "type": "Feature",
  "properties": {
    "addr:full":"574 Bloor St W Toronto ON M6G 1K1",
    "addr:housenumber":"574",
    "addr:postcode":"m6g 1k1",
    "addr:street":"Bloor St W",
    "iso:country":"CA",
    "sg:address":"574 Bloor St W",
    "sg:city":"Toronto",
    "sg:classifiers":[
        {
            "category":"Banks & Credit Unions",
            "subcategory":"Bank",
            "type":"Services"
        }
    ],
    "sg:phone":"+1 416 534 9211",
    "sg:postcode":"M6G 1K1",
    "sg:province":"ON",
    "wof:name":"Td Canada Trust",
    "wof:placetype":"venue"
},
  "geometry": {"coordinates":[-79.412125,43.665062],"type":"Point"}
}