{
  "type": "Feature",
  "properties": {
    "addr:full":"243 Seymour St Kamloops BC V2C 2E7",
    "addr:housenumber":"243",
    "addr:postcode":"bc v2c 2e7",
    "addr:street":"Seymour St",
    "iso:country":"CA",
    "sg:address":"243 Seymour St",
    "sg:city":"Kamloops",
    "sg:classifiers":[
        {
            "category":"Professional",
            "subcategory":"Lawyer & Legal Services",
            "type":"Services"
        }
    ],
    "sg:phone":"+1 250 374 3337",
    "sg:postcode":"V2C 2E7",
    "sg:province":"BC",
    "sg:tags":[
        "attorney"
    ],
    "wof:name":"Gary Woitas & Assoc",
    "wof:placetype":"venue"
},
  "geometry": {"coordinates":[-120.335663,50.674812],"type":"Point"}
}