{
  "type": "Feature",
  "properties": {
    "addr:full":"15706 Boul DE Pierrefonds Pierrefonds QC H9H 3P6",
    "addr:housenumber":"15706",
    "addr:postcode":"h9h 3p6",
    "addr:street":"Boul De Pierrefonds",
    "iso:country":"CA",
    "sg:address":"15706 Boul DE Pierrefonds",
    "sg:city":"Pierrefonds",
    "sg:classifiers":[
        {
            "category":"Home & Garden",
            "subcategory":"Building Materials",
            "type":"Retail Goods"
        }
    ],
    "sg:phone":"+1 514 620 3125",
    "sg:postcode":"H9H 3P6",
    "sg:province":"QC",
    "sg:tags":[
        "plumbing",
        "fixture",
        "supply"
    ],
    "wof:name":"Plomberium Pierrefonds",
    "wof:placetype":"venue"
},
  "geometry": {"coordinates":[-73.86554,45.479687],"type":"Point"}
}