{
  "type": "Feature",
  "properties": {
    "addr:full":"625 2E Rue E LA Sarre QC J9Z 2S7",
    "addr:housenumber":"625",
    "addr:postcode":"j9z 2s7",
    "addr:street":"2E Rue E La Sarre",
    "iso:country":"CA",
    "sg:address":"625 2E Rue E",
    "sg:city":"LA Sarre",
    "sg:classifiers":[
        {
            "category":"Wholesale",
            "subcategory":"Durable Goods & Equipment",
            "type":"Manufacturing & Wholesale Goods"
        }
    ],
    "sg:phone":"+1 819 333 2351",
    "sg:postcode":"J9Z 2S7",
    "sg:province":"QC",
    "sg:tags":[
        "fire",
        "extinguisher",
        "parts",
        "automobile",
        "supply"
    ],
    "wof:name":"Jgr Ltee",
    "wof:placetype":"venue"
},
  "geometry": {"coordinates":[-79.200485,48.815582],"type":"Point"}
}