{
  "type": "Feature",
  "properties": {
    "addr:full":"RR 1 Wembley AB T0H 3S0",
    "addr:postcode":"t0h 3s0",
    "addr:street":"Rr 1",
    "iso:country":"CA",
    "sg:address":"RR 1",
    "sg:city":"Wembley",
    "sg:classifiers":[
        {
            "category":"Retail",
            "subcategory":"Animal Services",
            "type":"Services"
        }
    ],
    "sg:phone":"+1 780 766 3044",
    "sg:postcode":"T0H 3S0",
    "sg:province":"AB",
    "sg:tags":[
        "pet",
        "boarding",
        "sitting"
    ],
    "wof:name":"Saskatoon Mountain Kennels",
    "wof:placetype":"venue"
},
  "geometry": {"coordinates":[-119.139198303,55.1647949219],"type":"Point"}
}