{
  "type": "Feature",
  "properties": {
    "addr:full":"739 Av Meloche Dorval QC H9P 2S4",
    "addr:postcode":"h9p 2s4",
    "addr:street":"739 Av Meloche",
    "iso:country":"CA",
    "sg:address":"739 Av Meloche",
    "sg:city":"Dorval",
    "sg:classifiers":[
        {
            "category":"Wholesale",
            "subcategory":"Machinery & Supplies",
            "type":"Manufacturing & Wholesale Goods"
        }
    ],
    "sg:phone":"+1 514 639 0700",
    "sg:postcode":"H9P 2S4",
    "sg:province":"QC",
    "sg:tags":[
        "gage",
        "valve"
    ],
    "wof:name":"Royal Valve Inc",
    "wof:placetype":"venue"
},
  "geometry": {"coordinates":[-73.7278137207,45.4567604065],"type":"Point"}
}