{
  "type": "Feature",
  "properties": {
    "addr:full":"5613 Ch DE L'Eglise Laterriere QC G7N 1P1",
    "addr:housenumber":"5613",
    "addr:postcode":"g7n 1p1",
    "addr:street":"Ch De L'Eglise Laterriere",
    "iso:country":"CA",
    "sg:address":"5613 Ch DE L'Eglise",
    "sg:city":"Laterriere",
    "sg:classifiers":[
        {
            "category":"Professional",
            "subcategory":"Testing Lab",
            "type":"Services"
        }
    ],
    "sg:phone":"+1 418 678 3392",
    "sg:postcode":"G7N 1P1",
    "sg:province":"QC",
    "sg:tags":[
        "environmental",
        "ecological"
    ],
    "wof:name":"Gve Consultants",
    "wof:placetype":"venue"
},
  "geometry": {"coordinates":[-71.093788147,48.3176116943],"type":"Point"}
}