{
  "type": "Feature",
  "properties": {
    "addr:full":"571 Kingston Rd W Ajax ON L1S 6M1",
    "addr:housenumber":"571",
    "addr:postcode":"l1s 6m1",
    "addr:street":"Kingston Rd W",
    "iso:country":"CA",
    "sg:address":"571 Kingston Rd W",
    "sg:city":"Ajax",
    "sg:classifiers":[
        {
            "category":"Insurance",
            "subcategory":"Insurance Agent",
            "type":"Services"
        }
    ],
    "sg:phone":"+1 905 619 0611",
    "sg:postcode":"L1S 6M1",
    "sg:province":"ON",
    "wof:name":"Jane Cameron Insurance Inc",
    "wof:placetype":"venue"
},
  "geometry": {"coordinates":[-79.0539398193,43.8547325134],"type":"Point"}
}