{
  "type": "Feature",
  "properties": {
    "addr:full":"St Catharines ON L2P 3H6",
    "addr:postcode":"l2p 3h6",
    "iso:country":"CA",
    "sg:city":"St Catharines",
    "sg:classifiers":[
        {
            "category":"Autos & Motor Vehicles",
            "subcategory":"Automobile Sales",
            "type":"Retail Goods"
        }
    ],
    "sg:phone":"+1 905 641 8779",
    "sg:postcode":"L2P 3H6",
    "sg:province":"ON",
    "sg:tags":[
        "car",
        "leasing"
    ],
    "wof:name":"Cmh Leasing",
    "wof:placetype":"venue"
},
  "geometry": {"coordinates":[-79.214111,43.168579],"type":"Point"}
}