{
  "type": "Feature",
  "properties": {
    "iso:country":"CA",
    "sg:address":"969 Eglinton Ave W",
    "sg:city":"York",
    "sg:classifiers":[
        {
            "category":"Personal",
            "subcategory":"Tanning Parlor",
            "type":"Services"
        }
    ],
    "sg:phone":"+1 416 787 2226",
    "sg:postcode":"M6C 2C4",
    "sg:province":"ON",
    "sg:tags":[
        "salon"
    ],
    "wof:name":"Moda Tanning Inc",
    "wof:placetype":"venue"
},
  "geometry": {"coordinates":[-79.4292678833,43.700050354],"type":"Point"}
}