{
  "type": "Feature",
  "properties": {
    "addr:full":"538 Bevel Line Rd Leamington ON N8H 3V4",
    "addr:housenumber":"538",
    "addr:postcode":"n8h 3v4",
    "addr:street":"Bevel Line Rd",
    "iso:country":"CA",
    "sg:address":"538 Bevel Line Rd",
    "sg:city":"Leamington",
    "sg:classifiers":[
        {
            "category":"Recreation",
            "type":"Entertainment"
        }
    ],
    "sg:phone":"+1 519 326 0991",
    "sg:postcode":"N8H 3V4",
    "sg:province":"ON",
    "sg:tags":[
        "amusement"
    ],
    "wof:name":"Point Pelee Karting",
    "wof:placetype":"venue"
},
  "geometry": {"coordinates":[-82.57624800000001,42.024029],"type":"Point"}
}