{
  "type": "Feature",
  "properties": {
    "addr:full":"Saskatoon SK S7H 0V1",
    "addr:postcode":"s7h 0v1",
    "iso:country":"CA",
    "sg:city":"Saskatoon",
    "sg:classifiers":[
        {
            "category":"Professional",
            "subcategory":"Lawyer & Legal Services",
            "type":"Services"
        }
    ],
    "sg:phone":"+1 306 955 8890",
    "sg:postcode":"S7H 0V1",
    "sg:province":"SK",
    "sg:tags":[
        "attorney"
    ],
    "wof:name":"Steponchev, Richard J",
    "wof:placetype":"venue"
},
  "geometry": {"coordinates":[-106.624145508,52.1146087646],"type":"Point"}
}