{
  "type": "Feature",
  "properties": {
    "iso:country":"CA",
    "sg:city":"Strathmore",
    "sg:classifiers":[
        {
            "category":"Farming",
            "subcategory":"Livestock Farm",
            "type":"Manufacturing & Wholesale Goods"
        }
    ],
    "sg:phone":"+1 403 934 3341",
    "sg:postcode":"T1P 1K3",
    "sg:province":"AB",
    "sg:tags":[
        "feeding"
    ],
    "wof:name":"Western Feedlots Ltd",
    "wof:placetype":"venue"
},
  "geometry": {"coordinates":[-113.400291,51.041306],"type":"Point"}
}