{
  "type": "Feature",
  "properties": {
    "addr:full":"876 Wellington Rd London ON N6E 1L9",
    "addr:housenumber":"876",
    "addr:postcode":"n6e 1l9",
    "addr:street":"Wellington Rd",
    "iso:country":"CA",
    "sg:address":"876 Wellington Rd",
    "sg:city":"London",
    "sg:classifiers":[
        {
            "category":"Home & Garden",
            "subcategory":"Household Appliances",
            "type":"Retail Goods"
        }
    ],
    "sg:phone":"+1 519 681 0060",
    "sg:postcode":"N6E 1L9",
    "sg:province":"ON",
    "wof:name":"Don Brown Appliances Ltd",
    "wof:placetype":"venue"
},
  "geometry": {"coordinates":[-81.225235,42.941929],"type":"Point"}
}