{
  "type": "Feature",
  "properties": {
    "addr:full":"988 Pembroke St W Pembroke ON K8A 5P9",
    "addr:housenumber":"988",
    "addr:postcode":"k8a 5p9",
    "addr:street":"Pembroke St W",
    "iso:country":"CA",
    "sg:address":"988 Pembroke St W",
    "sg:city":"Pembroke",
    "sg:classifiers":[
        {
            "category":"Retail",
            "subcategory":"Repair Shop",
            "type":"Services"
        }
    ],
    "sg:phone":"+1 613 735 3365",
    "sg:postcode":"K8A 5P9",
    "sg:province":"ON",
    "sg:tags":[
        "appliance"
    ],
    "wof:name":"Mac Donald Appliance & Refrig",
    "wof:placetype":"venue"
},
  "geometry": {"coordinates":[-77.13812299999999,45.829086],"type":"Point"}
}