{
  "type": "Feature",
  "properties": {
    "iso:country":"CA",
    "sg:address":"344 Rue Strathmore",
    "sg:city":"Verdun",
    "sg:classifiers":[
        {
            "category":"Shopping",
            "subcategory":"Computers & Home Electronics",
            "type":"Retail Goods"
        }
    ],
    "sg:phone":"+1 514 768 3414",
    "sg:postcode":"H4G 2E4",
    "sg:province":"QC",
    "sg:tags":[
        "television",
        "radio"
    ],
    "wof:name":"LA Salle Television Ltee",
    "wof:placetype":"venue"
},
  "geometry": {"coordinates":[-73.5681,45.468597],"type":"Point"}
}