{
  "type": "Feature",
  "properties": {
    "addr:full":"2nd & Princess Dawson YT Y0B 1G0",
    "addr:postcode":"y0b 1g0",
    "addr:street":"Dawson",
    "iso:country":"CA",
    "sg:address":"2nd & Princess",
    "sg:city":"Dawson",
    "sg:classifiers":[
        {
            "category":"Retail",
            "subcategory":"Portrait Studio",
            "type":"Services"
        }
    ],
    "sg:phone":"+1 867 993 5209",
    "sg:postcode":"Y0B 1G0",
    "sg:province":"YT",
    "sg:tags":[
        "photo",
        "finishing"
    ],
    "wof:name":"Peabody's Photo Parlor",
    "wof:placetype":"venue"
},
  "geometry": {"coordinates":[-139.435776,64.060997],"type":"Point"}
}