{
  "type": "Feature",
  "properties": {
    "iso:country":"CA",
    "sg:address":"2200 Dundas St",
    "sg:city":"London",
    "sg:classifiers":[
        {
            "category":"Autos & Motor Vehicles",
            "subcategory":"Fuel & Gas Station",
            "type":"Retail Goods"
        }
    ],
    "sg:phone":"+1 519 455 0700",
    "sg:postcode":"N5V 1R5",
    "sg:province":"ON",
    "sg:tags":[
        "oil"
    ],
    "wof:name":"Ken's Sunoco Svc",
    "wof:placetype":"venue"
},
  "geometry": {"coordinates":[-81.1585388184,43.0096244812],"type":"Point"}
}