{
  "type": "Feature",
  "properties": {
    "addr:full":"62 Queen St Miramichi NB E1N 2M8",
    "addr:housenumber":"62",
    "addr:postcode":"e1n 2m8",
    "addr:street":"Queen St",
    "iso:country":"CA",
    "sg:address":"62 Queen St",
    "sg:city":"Miramichi",
    "sg:classifiers":[
        {
            "category":"Shopping",
            "subcategory":"Computers & Home Electronics",
            "type":"Retail Goods"
        }
    ],
    "sg:phone":"+1 506 773 7534",
    "sg:postcode":"E1N 2M8",
    "sg:province":"NB",
    "sg:tags":[
        "television",
        "radio"
    ],
    "wof:name":"Bryan's Tv & Vcr Repair",
    "wof:placetype":"venue"
},
  "geometry": {"coordinates":[-65.463066,47.030643],"type":"Point"}
}