{
  "type": "Feature",
  "properties": {
    "addr:full":"PO Box 280 Saint-Pamphile QC G0R 3X0",
    "addr:housenumber":"po",
    "addr:postcode":"g0r 3x0",
    "addr:street":"Box 280",
    "iso:country":"CA",
    "sg:address":"PO Box 280",
    "sg:city":"Saint-Pamphile",
    "sg:classifiers":[
        {
            "category":"Manufacturing",
            "subcategory":"Lumber",
            "type":"Manufacturing & Wholesale Goods"
        }
    ],
    "sg:phone":"+1 418 356 3177",
    "sg:postcode":"G0R 3X0",
    "sg:province":"QC",
    "sg:tags":[
        "company",
        "logging"
    ],
    "wof:name":"Robinson Lumber CO",
    "wof:placetype":"venue"
},
  "geometry": {"coordinates":[-69.77864099999999,46.960812],"type":"Point"}
}