{
  "type": "Feature",
  "properties": {
    "iso:country":"CA",
    "sg:address":"250 Mill St S",
    "sg:city":"Newcastle",
    "sg:classifiers":[
        {
            "category":"Organizations",
            "subcategory":"Religious Organization",
            "type":"Services"
        }
    ],
    "sg:phone":"+1 905 987 5044",
    "sg:postcode":"L1B 1C5",
    "sg:province":"ON",
    "sg:tags":[
        "church"
    ],
    "wof:name":"St George Anglican Church",
    "wof:placetype":"venue"
},
  "geometry": {"coordinates":[-78.5874252319,43.9139976501],"type":"Point"}
}