{
  "type": "Feature",
  "properties": {
    "addr:full":"2464 South River Rd Kemptville ON K0G 1J0",
    "addr:housenumber":"2464",
    "addr:postcode":"k0g 1j0",
    "addr:street":"South River Rd",
    "iso:country":"CA",
    "sg:address":"2464 South River Rd",
    "sg:city":"Kemptville",
    "sg:classifiers":[
        {
            "category":"Home & Garden",
            "subcategory":"Furniture",
            "type":"Retail Goods"
        }
    ],
    "sg:phone":"+1 613 258 7851",
    "sg:postcode":"K0G 1J0",
    "sg:province":"ON",
    "sg:tags":[
        "kitchen",
        "maker",
        "cabinet"
    ],
    "wof:name":"Pine Ridge Cabinets",
    "wof:placetype":"venue"
},
  "geometry": {"coordinates":[-75.6886978149,45.0361328125],"type":"Point"}
}