{
  "type": "Feature",
  "properties": {
    "addr:full":"Okanagan Falls BC V0H 1R0",
    "addr:postcode":"v0h 1r0",
    "iso:country":"CA",
    "sg:city":"Okanagan Falls",
    "sg:classifiers":[
        {
            "category":"Shopping",
            "subcategory":"Department Store",
            "type":"Retail Goods"
        }
    ],
    "sg:phone":"+1 250 497 8037",
    "sg:postcode":"V0H 1R0",
    "sg:province":"BC",
    "sg:tags":[
        "shop",
        "variety"
    ],
    "wof:name":"Dollar Store",
    "wof:placetype":"venue"
},
  "geometry": {"coordinates":[-119.57674408,49.3451156616],"type":"Point"}
}