{
  "type": "Feature",
  "properties": {
    "addr:full":"2515 6E Av Saint-Georges QC G5Y 3X9",
    "addr:housenumber":"2515",
    "addr:postcode":"g5y 3x9",
    "addr:street":"6E Av",
    "iso:country":"CA",
    "sg:address":"2515 6E Av",
    "sg:city":"Saint-Georges",
    "sg:classifiers":[
        {
            "category":"Building & Trades",
            "subcategory":"Construction",
            "type":"Services"
        }
    ],
    "sg:phone":"+1 418 228 1053",
    "sg:postcode":"G5Y 3X9",
    "sg:province":"QC",
    "sg:tags":[
        "builder",
        "burning",
        "stove",
        "wood",
        "repairer",
        "chimney"
    ],
    "wof:name":"Poeles & Cheminees Rock Inc",
    "wof:placetype":"venue"
},
  "geometry": {"coordinates":[-70.67115,46.123348],"type":"Point"}
}