{
  "type": "Feature",
  "properties": {
    "addr:full":"444 Dundas St Woodstock ON N4S 1C1",
    "addr:housenumber":"444",
    "addr:postcode":"n4s 1c1",
    "addr:street":"Dundas St",
    "iso:country":"CA",
    "sg:address":"444 Dundas St",
    "sg:city":"Woodstock",
    "sg:classifiers":[
        {
            "category":"Restaurant",
            "type":"Food & Drink"
        }
    ],
    "sg:phone":"+1 519 539 0000",
    "sg:postcode":"N4S 1C1",
    "sg:province":"ON",
    "wof:name":"Let's Eat Pizza",
    "wof:placetype":"venue"
},
  "geometry": {"coordinates":[-80.758415,43.129761],"type":"Point"}
}