{
  "type": "Feature",
  "properties": {
    "addr:full":"Scarborough ON M1C 3B2",
    "addr:postcode":"m1c 3b2",
    "iso:country":"CA",
    "sg:city":"Scarborough",
    "sg:classifiers":[
        {
            "category":"Cinema",
            "subcategory":"Movie Rental",
            "type":"Entertainment"
        }
    ],
    "sg:phone":"+1 416 284 0094",
    "sg:postcode":"M1C 3B2",
    "sg:province":"ON",
    "sg:tags":[
        "leasing",
        "video",
        "disc",
        "tape"
    ],
    "wof:name":"Markville Video",
    "wof:placetype":"venue"
},
  "geometry": {"coordinates":[-79.13880899999999,43.779247],"type":"Point"}
}