{
  "type": "Feature",
  "properties": {
    "addr:full":"850 Av Munck Laval QC H7S 1B1",
    "addr:housenumber":"850",
    "addr:postcode":"h7s 1b1",
    "addr:street":"Av Munck",
    "iso:country":"CA",
    "sg:address":"850 Av Munck",
    "sg:city":"Laval",
    "sg:classifiers":[
        {
            "category":"Manufacturing",
            "subcategory":"Paper Products",
            "type":"Manufacturing & Wholesale Goods"
        }
    ],
    "sg:phone":"+1 514 384 5060",
    "sg:postcode":"H7S 1B1",
    "sg:province":"QC",
    "sg:tags":[
        "packaging",
        "material"
    ],
    "wof:name":"Poly Expert Inc",
    "wof:placetype":"venue"
},
  "geometry": {"coordinates":[-73.725639,45.581356],"type":"Point"}
}