{
  "type": "Feature",
  "properties": {
    "addr:full":"London ON N6H 5L9",
    "addr:postcode":"n6h 5l9",
    "iso:country":"CA",
    "sg:city":"London",
    "sg:classifiers":[
        {
            "category":"Building & Trades",
            "subcategory":"Construction",
            "type":"Services"
        }
    ],
    "sg:phone":"+1 519 471 1089",
    "sg:postcode":"N6H 5L9",
    "sg:province":"ON",
    "sg:tags":[
        "resurfacing",
        "laying",
        "refinishing",
        "floor"
    ],
    "wof:name":"R G Gibson & Sons Ltd",
    "wof:placetype":"venue"
},
  "geometry": {"coordinates":[-81.33833300000001,43.006584],"type":"Point"}
}