{
  "type": "Feature",
  "properties": {
    "addr:full":"Montreal QC H3A 3H3",
    "addr:postcode":"h3a 3h3",
    "iso:country":"CA",
    "sg:city":"Montreal",
    "sg:classifiers":[
        {
            "category":"Insurance",
            "subcategory":"Insurance Agent",
            "type":"Services"
        }
    ],
    "sg:phone":"+1 514 842 0603",
    "sg:postcode":"H3A 3H3",
    "sg:province":"QC",
    "wof:name":"Compagnies American Intl",
    "wof:placetype":"venue"
},
  "geometry": {"coordinates":[-73.573296,45.502785],"type":"Point"}
}