{
  "type": "Feature",
  "properties": {
    "iso:country":"CA",
    "sg:address":"1330 Ritson Rd N",
    "sg:city":"Oshawa",
    "sg:classifiers":[
        {
            "category":"Retail",
            "subcategory":"Laundry & Dry Cleaning",
            "type":"Services"
        }
    ],
    "sg:phone":"+1 905 433 1636",
    "sg:postcode":"L1G 6Z6",
    "sg:province":"ON",
    "sg:tags":[
        "cleaners"
    ],
    "wof:name":"Ted's Dry Cleaners",
    "wof:placetype":"venue"
},
  "geometry": {"coordinates":[-78.8689575195,43.9342346191],"type":"Point"}
}