{
  "type": "Feature",
  "properties": {
    "addr:full":"48 Ave & 116 St NE Calgary AB T2M 4L5",
    "addr:postcode":"t2m 4l5",
    "addr:street":"48 Ave & 116 St Ne",
    "iso:country":"CA",
    "sg:address":"48 Ave & 116 St NE",
    "sg:city":"Calgary",
    "sg:classifiers":[
        {
            "category":"Autos & Motor Vehicles",
            "subcategory":"Fuel & Gas Station",
            "type":"Retail Goods"
        }
    ],
    "sg:phone":"+1 403 285 8080",
    "sg:postcode":"T2M 4L5",
    "sg:province":"AB",
    "sg:tags":[
        "oil"
    ],
    "wof:name":"Gas Plus Inc",
    "wof:placetype":"venue"
},
  "geometry": {"coordinates":[-113.531761,53.485729],"type":"Point"}
}