{
  "type": "Feature",
  "properties": {
    "addr:full":"3177 Lakefield Rd Peterborough ON K9J 6X5",
    "addr:housenumber":"3177",
    "addr:postcode":"k9j 6x5",
    "addr:street":"Lakefield Rd",
    "iso:country":"CA",
    "sg:address":"3177 Lakefield Rd",
    "sg:city":"Peterborough",
    "sg:classifiers":[
        {
            "category":"Professional",
            "subcategory":"Business Services",
            "type":"Services"
        }
    ],
    "sg:phone":"+1 705 652 3864",
    "sg:postcode":"K9J 6X5",
    "sg:province":"ON",
    "sg:tags":[
        "water",
        "treatment"
    ],
    "wof:name":"Alternative Water Treatment",
    "wof:placetype":"venue"
},
  "geometry": {"coordinates":[-78.32131200000001,44.300732],"type":"Point"}
}