{
  "type": "Feature",
  "properties": {
    "addr:full":"279 Danforth Ave Toronto ON M4K 1N2",
    "addr:housenumber":"279",
    "addr:postcode":"m4k 1n2",
    "addr:street":"Danforth Ave",
    "iso:country":"CA",
    "sg:address":"279 Danforth Ave",
    "sg:city":"Toronto",
    "sg:classifiers":[
        {
            "category":"Shopping",
            "subcategory":"Hobbies, Toys, & Games",
            "type":"Retail Goods"
        }
    ],
    "sg:phone":"+1 416 466 8474",
    "sg:postcode":"M4K 1N2",
    "sg:province":"ON",
    "sg:tags":[
        "product",
        "ceramic"
    ],
    "wof:name":"Clay Room",
    "wof:placetype":"venue"
},
  "geometry": {"coordinates":[-79.35443100000001,43.676907],"type":"Point"}
}