{
  "type": "Feature",
  "properties": {
    "addr:full":"67 Barron St Stratford ON N4Z 1G9",
    "addr:housenumber":"67",
    "addr:postcode":"n4z 1g9",
    "addr:street":"Barron St",
    "iso:country":"CA",
    "sg:address":"67 Barron St",
    "sg:city":"Stratford",
    "sg:classifiers":[
        {
            "category":"Social Services",
            "type":"Services"
        }
    ],
    "sg:phone":"+1 519 273 7350",
    "sg:postcode":"N4Z 1G9",
    "sg:province":"ON",
    "sg:tags":[
        "organization",
        "welfare"
    ],
    "wof:name":"Emily Murphy Ctr Second Stage",
    "wof:placetype":"venue"
},
  "geometry": {"coordinates":[-81.00649261469999,43.3618164062],"type":"Point"}
}