{
  "type": "Feature",
  "properties": {
    "addr:full":"Edmonton AB T5H 2X6",
    "addr:postcode":"t5h 2x6",
    "iso:country":"CA",
    "sg:city":"Edmonton",
    "sg:classifiers":[
        {
            "category":"Professional",
            "subcategory":"Research",
            "type":"Services"
        }
    ],
    "sg:phone":"+1 780 423 5840",
    "sg:postcode":"T5H 2X6",
    "sg:province":"AB",
    "sg:tags":[
        "archaeologist"
    ],
    "wof:name":"Altamira Consulting Ltd",
    "wof:placetype":"venue"
},
  "geometry": {"coordinates":[-113.503044128,53.54870224],"type":"Point"}
}