{
  "type": "Feature",
  "properties": {
    "addr:full":"47 Elmont Rise SW Calgary AB T3H 4X9",
    "addr:housenumber":"47",
    "addr:postcode":"t3h 4x9",
    "addr:street":"Elmont Rise Sw",
    "iso:country":"CA",
    "sg:address":"47 Elmont Rise SW",
    "sg:city":"Calgary",
    "sg:classifiers":[
        {
            "category":"Professional",
            "subcategory":"Computer Services",
            "type":"Services"
        }
    ],
    "sg:phone":"+1 403 242 8184",
    "sg:postcode":"T3H 4X9",
    "sg:province":"AB",
    "sg:tags":[
        "consultant"
    ],
    "wof:name":"Anira Systems Consultants Inc",
    "wof:placetype":"venue"
},
  "geometry": {"coordinates":[-114.189414978,51.0269012451],"type":"Point"}
}