{
  "type": "Feature",
  "properties": {
    "addr:full":"1711 Main St N Moose Jaw SK S6J 1L6",
    "addr:housenumber":"1711",
    "addr:postcode":"s6j 1l6",
    "addr:street":"Main St N",
    "iso:country":"CA",
    "sg:address":"1711 Main St N",
    "sg:city":"Moose Jaw",
    "sg:classifiers":[
        {
            "category":"Restaurant",
            "type":"Food & Drink"
        }
    ],
    "sg:phone":"+1 306 692 8999",
    "sg:postcode":"S6J 1L6",
    "sg:province":"SK",
    "wof:name":"Joey's Only Seafood Restaurant",
    "wof:placetype":"venue"
},
  "geometry": {"coordinates":[-105.53428599999999,50.415451],"type":"Point"}
}