{
  "type": "Feature",
  "properties": {
    "addr:full":"Barrett Hat Rd Houston BC V0J 1Z0",
    "addr:postcode":"v0j 1z0",
    "addr:street":"Hat Rd",
    "iso:country":"CA",
    "sg:address":"Barrett Hat Rd",
    "sg:city":"Houston",
    "sg:classifiers":[
        {
            "category":"Travel",
            "subcategory":"Campground",
            "type":"Entertainment"
        }
    ],
    "sg:phone":"+1 250 845 2179",
    "sg:postcode":"V0J 1Z0",
    "sg:province":"BC",
    "sg:tags":[
        "camp"
    ],
    "wof:name":"Rock Nest Ranch",
    "wof:placetype":"venue"
},
  "geometry": {"coordinates":[-126.647041321,54.4006347656],"type":"Point"}
}