{
  "type": "Feature",
  "properties": {
    "addr:full":"Surrey BC V4N 3R1",
    "addr:postcode":"v4n 3r1",
    "iso:country":"CA",
    "sg:city":"Surrey",
    "sg:classifiers":[
        {
            "category":"Wholesale",
            "subcategory":"Non-durable Goods",
            "type":"Manufacturing & Wholesale Goods"
        }
    ],
    "sg:phone":"+1 604 882 0022",
    "sg:postcode":"V4N 3R1",
    "sg:province":"BC",
    "sg:tags":[
        "pet",
        "supply"
    ],
    "wof:name":"Excalibur Sharpening & Supply",
    "wof:placetype":"venue"
},
  "geometry": {"coordinates":[-122.70056200000001,49.176857],"type":"Point"}
}