{
  "type": "Feature",
  "properties": {
    "addr:full":"435 Brookside Dr Fredericton NB E3A 8V4",
    "addr:housenumber":"435",
    "addr:postcode":"e3a 8v4",
    "addr:street":"Brookside Dr",
    "iso:country":"CA",
    "sg:address":"435 Brookside Dr",
    "sg:city":"Fredericton",
    "sg:classifiers":[
        {
            "category":"Real Estate",
            "subcategory":"Real Estate Operator",
            "type":"Services"
        }
    ],
    "sg:phone":"+1 506 458 9038",
    "sg:postcode":"E3A 8V4",
    "sg:province":"NB",
    "sg:tags":[
        "mall",
        "shopping",
        "center"
    ],
    "wof:name":"Brookside Mall",
    "wof:placetype":"venue"
},
  "geometry": {"coordinates":[-66.65032958979999,45.9922142029],"type":"Point"}
}