{
  "type": "Feature",
  "properties": {
    "addr:full":"18325 Stony Plain Rd NW Edmonton AB T5S 1C6",
    "addr:housenumber":"18325",
    "addr:postcode":"t5s 1c6",
    "addr:street":"Stony Plain Rd Nw",
    "iso:country":"CA",
    "sg:address":"18325 Stony Plain Rd NW",
    "sg:city":"Edmonton",
    "sg:classifiers":[
        {
            "category":"Wholesale",
            "subcategory":"Painting Supplies",
            "type":"Manufacturing & Wholesale Goods"
        }
    ],
    "sg:phone":"+1 780 444 5595",
    "sg:postcode":"T5S 1C6",
    "sg:province":"AB",
    "sg:tags":[
        "equipment",
        "painter",
        "paint"
    ],
    "wof:name":"Western Paint Supply",
    "wof:placetype":"venue"
},
  "geometry": {"coordinates":[-113.63799285899999,53.5408554077],"type":"Point"}
}