{
  "type": "Feature",
  "properties": {
    "iso:country":"CA",
    "sg:address":"95 West Beaver Creek Rd",
    "sg:city":"Richmond Hill",
    "sg:classifiers":[
        {
            "category":"Building & Trades",
            "subcategory":"Plumbing",
            "type":"Services"
        }
    ],
    "sg:phone":"+1 905 763 7365",
    "sg:postcode":"L4B 1H2",
    "sg:province":"ON",
    "sg:tags":[
        "contractor"
    ],
    "wof:name":"Bruce Clark & Son Plumbing",
    "wof:placetype":"venue"
},
  "geometry": {"coordinates":[-79.39292144780001,43.8529129028],"type":"Point"}
}