{
  "type": "Feature",
  "properties": {
    "addr:full":"15 Brackley Point Rd Charlottetown PE C1A 6Y1",
    "addr:housenumber":"15",
    "addr:postcode":"c1a 6y1",
    "addr:street":"Brackley Point Rd",
    "iso:country":"CA",
    "sg:address":"15 Brackley Point Rd",
    "sg:city":"Charlottetown",
    "sg:classifiers":[
        {
            "category":"Health Services",
            "subcategory":"Doctor",
            "type":"Services"
        }
    ],
    "sg:phone":"+1 902 566 4734",
    "sg:postcode":"C1A 6Y1",
    "sg:province":"PE",
    "sg:tags":[
        "physician",
        "surgeon"
    ],
    "wof:name":"Slysz, G W MD",
    "wof:placetype":"venue"
},
  "geometry": {"coordinates":[-63.1203765869,46.2595863342],"type":"Point"}
}