{
  "type": "Feature",
  "properties": {
    "addr:full":"Maberly ON K0H 2B0",
    "addr:postcode":"k0h 2b0",
    "addr:street":"Maberly",
    "iso:country":"CA",
    "sg:city":"Maberly",
    "sg:classifiers":[
        {
            "category":"Building & Trades",
            "subcategory":"Construction",
            "type":"Services"
        }
    ],
    "sg:phone":"+1 613 268 2308",
    "sg:postcode":"K0H 2B0",
    "sg:province":"ON",
    "sg:tags":[
        "contractor",
        "road",
        "general"
    ],
    "wof:name":"Crain's Construction Ltd",
    "wof:placetype":"venue"
},
  "geometry": {"coordinates":[-76.54206848139999,44.8355140686],"type":"Point"}
}