{
  "type": "Feature",
  "properties": {
    "addr:full":"2660 Kingsway Ave Port Coquitlam BC V3C 1T8",
    "addr:housenumber":"2660",
    "addr:postcode":"v3c 1t8",
    "addr:street":"Kingsway Ave",
    "iso:country":"CA",
    "sg:address":"2660 Kingsway Ave",
    "sg:city":"Port Coquitlam",
    "sg:classifiers":[
        {
            "category":"Manufacturing",
            "subcategory":"Printing",
            "type":"Manufacturing & Wholesale Goods"
        }
    ],
    "sg:phone":"+1 604 468 9855",
    "sg:postcode":"V3C 1T8",
    "sg:province":"BC",
    "sg:tags":[
        "screen"
    ],
    "wof:name":"Flashpoint Screenworks",
    "wof:placetype":"venue"
},
  "geometry": {"coordinates":[-122.78958129900001,49.2650337219],"type":"Point"}
}