{
  "type": "Feature",
  "properties": {
    "addr:full":"Bldg 101 St Theresa Point MB R0B 1J0",
    "addr:postcode":"r0b 1j0",
    "addr:street":"St",
    "iso:country":"CA",
    "sg:address":"Bldg 101",
    "sg:city":"St Theresa Point",
    "sg:classifiers":[
        {
            "category":"Organizations",
            "subcategory":"Religious Organization",
            "type":"Services"
        }
    ],
    "sg:phone":"+1 204 462 2475",
    "sg:postcode":"R0B 1J0",
    "sg:province":"MB",
    "sg:tags":[
        "church"
    ],
    "wof:name":"St Theresa Rc Church",
    "wof:placetype":"venue"
},
  "geometry": {"coordinates":[-94.844055,53.821236],"type":"Point"}
}