{
  "type": "Feature",
  "properties": {
    "iso:country":"CA",
    "sg:address":"300 Rue Valmont",
    "sg:city":"Repentigny",
    "sg:classifiers":[
        {
            "category":"Health Services",
            "subcategory":"Doctor",
            "type":"Services"
        }
    ],
    "sg:phone":"+1 450 581 8014",
    "sg:postcode":"J5Y 3X6",
    "sg:province":"QC",
    "sg:tags":[
        "clinic",
        "dentist"
    ],
    "wof:name":"Centre Dentaire C Lepage",
    "wof:placetype":"venue"
},
  "geometry": {"coordinates":[-73.4457778931,45.7675018311],"type":"Point"}
}