{
  "type": "Feature",
  "properties": {
    "iso:country":"CA",
    "sg:address":"216 Rectory St",
    "sg:city":"London",
    "sg:classifiers":[
        {
            "category":"Retail",
            "subcategory":"Auto Repair",
            "type":"Services"
        }
    ],
    "sg:phone":"+1 519 963 1985",
    "sg:postcode":"N5Z 2A7",
    "sg:province":"ON",
    "sg:tags":[
        "body",
        "automobile",
        "painting"
    ],
    "wof:name":"Maaco Auto Painting & Bodywork",
    "wof:placetype":"venue"
},
  "geometry": {"coordinates":[-81.22175598139999,42.984287262],"type":"Point"}
}