{
  "type": "Feature",
  "properties": {
    "addr:full":"2952 Willamstown Rd Route 560 Centreville NB E7K 3G4",
    "addr:housenumber":"2952",
    "addr:postcode":"e7k 3g4",
    "addr:street":"Willamstown Rd;560",
    "iso:country":"CA",
    "sg:address":"2952 Willamstown Rd Route 560",
    "sg:city":"Centreville",
    "sg:classifiers":[
        {
            "category":"Building & Trades",
            "subcategory":"Construction",
            "type":"Services"
        }
    ],
    "sg:phone":"+1 506 276 4478",
    "sg:postcode":"E7K 3G4",
    "sg:province":"NB",
    "sg:tags":[
        "concrete",
        "contractor"
    ],
    "wof:name":"Mac Leod General Construction",
    "wof:placetype":"venue"
},
  "geometry": {"coordinates":[-67.71118199999999,46.429733],"type":"Point"}
}