{
  "type": "Feature",
  "properties": {
    "addr:full":"6085 Creditview Rd Mississauga ON L5V 2A8",
    "addr:housenumber":"6085",
    "addr:postcode":"l5v 2a8",
    "addr:street":"Creditview Rd",
    "iso:country":"CA",
    "sg:address":"6085 Creditview Rd",
    "sg:city":"Mississauga",
    "sg:classifiers":[
        {
            "category":"Banks & Credit Unions",
            "subcategory":"Bank",
            "type":"Services"
        }
    ],
    "sg:phone":"+1 905 567 6953",
    "sg:postcode":"L5V 2A8",
    "sg:province":"ON",
    "wof:name":"Cibc",
    "wof:placetype":"venue"
},
  "geometry": {"coordinates":[-79.71423299999999,43.59943],"type":"Point"}
}