{
  "type": "Feature",
  "properties": {
    "addr:full":"Ottawa ON K2C 3T2",
    "addr:postcode":"k2c 3t2",
    "iso:country":"CA",
    "sg:city":"Ottawa",
    "sg:classifiers":[
        {
            "category":"Government",
            "subcategory":"Office",
            "type":"Public Place"
        }
    ],
    "sg:phone":"+1 613 946 2800",
    "sg:postcode":"K2C 3T2",
    "sg:province":"ON",
    "wof:name":"Human Resources Development",
    "wof:placetype":"venue"
},
  "geometry": {"coordinates":[-75.70611572270001,45.3770561218],"type":"Point"}
}