{
  "type": "Feature",
  "properties": {
    "addr:full":"700 Av Du Phare E Matane QC G4W 1B1",
    "addr:housenumber":"700",
    "addr:postcode":"g4w 1b1",
    "addr:street":"Av Du Phare E",
    "iso:country":"CA",
    "sg:address":"700 Av Du Phare E",
    "sg:city":"Matane",
    "sg:classifiers":[
        {
            "category":"Retail",
            "subcategory":"Repair Shop",
            "type":"Services"
        }
    ],
    "sg:phone":"+1 418 562 7701",
    "sg:postcode":"G4W 1B1",
    "sg:province":"QC",
    "sg:tags":[
        "equipment",
        "electronic",
        "supply"
    ],
    "wof:name":"Atelier Electronique Enr",
    "wof:placetype":"venue"
},
  "geometry": {"coordinates":[-67.50351000000001,48.852566],"type":"Point"}
}