{
  "type": "Feature",
  "properties": {
    "addr:full":"313 Front St Belleville ON K8N 2Z9",
    "addr:housenumber":"313",
    "addr:postcode":"k8n 2z9",
    "addr:street":"Front St",
    "iso:country":"CA",
    "sg:address":"313 Front St",
    "sg:city":"Belleville",
    "sg:classifiers":[
        {
            "category":"Manufacturing",
            "subcategory":"Printing",
            "type":"Manufacturing & Wholesale Goods"
        }
    ],
    "sg:phone":"+1 613 962 3663",
    "sg:postcode":"K8N 2Z9",
    "sg:province":"ON",
    "sg:tags":[
        "trophy",
        "screen",
        "medal",
        "award"
    ],
    "wof:name":"Ray & Jim's Signs & Trophies",
    "wof:placetype":"venue"
},
  "geometry": {"coordinates":[-77.3853683472,44.1668243408],"type":"Point"}
}