{
  "type": "Feature",
  "properties": {
    "addr:full":"2577 Eglinton Ave W York ON M6M 1T3",
    "addr:housenumber":"2577",
    "addr:postcode":"m6m 1t3",
    "addr:street":"Eglinton Ave W",
    "iso:country":"CA",
    "sg:address":"2577 Eglinton Ave W",
    "sg:city":"York",
    "sg:classifiers":[
        {
            "category":"Personal",
            "subcategory":"Beauty Salon",
            "type":"Services"
        }
    ],
    "sg:phone":"+1 416 653 7116",
    "sg:postcode":"M6M 1T3",
    "sg:province":"ON",
    "wof:name":"Beauty Queen Hair Styles",
    "wof:placetype":"venue"
},
  "geometry": {"coordinates":[-79.4733581543,43.6903877258],"type":"Point"}
}