{
  "type": "Feature",
  "properties": {
    "iso:country":"CA",
    "sg:address":"6071 Rue Laurendeau",
    "sg:city":"Montreal",
    "sg:classifiers":[
        {
            "category":"Recreation",
            "type":"Entertainment"
        }
    ],
    "sg:phone":"+1 514 872 2585",
    "sg:postcode":"H4E 3X6",
    "sg:province":"QC",
    "sg:tags":[
        "pool",
        "swimming"
    ],
    "wof:name":"Montreal Piscines Interieures",
    "wof:placetype":"venue"
},
  "geometry": {"coordinates":[-73.58844,45.457893],"type":"Point"}
}