{
  "type": "Feature",
  "properties": {
    "addr:full":"2580 Yonge St Toronto ON M4P 2J3",
    "addr:housenumber":"2580",
    "addr:postcode":"m4p 2j3",
    "addr:street":"Yonge St",
    "iso:country":"CA",
    "sg:address":"2580 Yonge St",
    "sg:city":"Toronto",
    "sg:classifiers":[
        {
            "category":"Shopping",
            "subcategory":"Clothing, Apparel, & Fashions",
            "type":"Retail Goods"
        }
    ],
    "sg:phone":"+1 416 839 3706",
    "sg:postcode":"M4P 2J3",
    "sg:province":"ON",
    "sg:tags":[
        "item",
        "boutique"
    ],
    "wof:name":"Excalibor Inc",
    "wof:placetype":"venue"
},
  "geometry": {"coordinates":[-79.4001159668,43.7141304016],"type":"Point"}
}