{
  "type": "Feature",
  "properties": {
    "addr:full":"79 Marlborough St W Leamington ON N8H 1W2",
    "addr:housenumber":"79",
    "addr:postcode":"n8h 1w2",
    "addr:street":"Marlborough St W",
    "iso:country":"CA",
    "sg:address":"79 Marlborough St W",
    "sg:city":"Leamington",
    "sg:classifiers":[
        {
            "category":"Personal",
            "subcategory":"Beauty Salon",
            "type":"Services"
        }
    ],
    "sg:phone":"+1 519 326 8885",
    "sg:postcode":"N8H 1W2",
    "sg:province":"ON",
    "wof:name":"Heidi's Hair Studio",
    "wof:placetype":"venue"
},
  "geometry": {"coordinates":[-82.60572814939999,42.0506362915],"type":"Point"}
}