{
  "type": "Feature",
  "properties": {
    "addr:full":"543 Trunk Rd Sault Ste Marie ON P6A 3T1",
    "addr:housenumber":"543",
    "addr:postcode":"p6a 3t1",
    "addr:street":"Trunk Rd",
    "iso:country":"CA",
    "sg:address":"543 Trunk Rd",
    "sg:city":"Sault Ste Marie",
    "sg:classifiers":[
        {
            "category":"Organizations",
            "subcategory":"Professional Association",
            "type":"Services"
        }
    ],
    "sg:phone":"+1 705 759 8623",
    "sg:postcode":"P6A 3T1",
    "sg:province":"ON",
    "wof:name":"Loyal Order of Moose",
    "wof:placetype":"venue"
},
  "geometry": {"coordinates":[-84.278099,46.519814],"type":"Point"}
}