{
  "type": "Feature",
  "properties": {
    "addr:full":"367 Rue Legare Repentigny QC J6A 5V4",
    "addr:housenumber":"367",
    "addr:postcode":"j6a 5v4",
    "addr:street":"Rue Legare",
    "iso:country":"CA",
    "sg:address":"367 Rue Legare",
    "sg:city":"Repentigny",
    "sg:classifiers":[
        {
            "category":"Building & Trades",
            "subcategory":"Construction",
            "type":"Services"
        }
    ],
    "sg:phone":"+1 514 591 4693",
    "sg:postcode":"J6A 5V4",
    "sg:province":"QC",
    "sg:tags":[
        "general",
        "contractor"
    ],
    "wof:name":"Construction Gerald Grandmsn",
    "wof:placetype":"venue"
},
  "geometry": {"coordinates":[-73.4736785889,45.7436943054],"type":"Point"}
}