{
  "type": "Feature",
  "properties": {
    "addr:full":"6915 Rue DE Marseille Montreal QC H1N 1N2",
    "addr:housenumber":"6915",
    "addr:postcode":"h1n 1n2",
    "addr:street":"Rue De Marseille",
    "iso:country":"CA",
    "sg:address":"6915 Rue DE Marseille",
    "sg:city":"Montreal",
    "sg:classifiers":[
        {
            "category":"Shopping",
            "subcategory":"Bicycles & Sporting Goods",
            "type":"Retail Goods"
        }
    ],
    "sg:phone":"+1 514 254 0581",
    "sg:postcode":"H1N 1N2",
    "sg:province":"QC",
    "wof:name":"Marseille Bicycle & Sport Enr",
    "wof:placetype":"venue"
},
  "geometry": {"coordinates":[-73.537308,45.584976],"type":"Point"}
}