{
  "type": "Feature",
  "properties": {
    "addr:full":"604 Queen St Fredericton NB E3B 1C2",
    "addr:housenumber":"604",
    "addr:postcode":"e3b 1c2",
    "addr:street":"Queen St",
    "iso:country":"CA",
    "sg:address":"604 Queen St",
    "sg:city":"Fredericton",
    "sg:classifiers":[
        {
            "category":"Personal",
            "subcategory":"Beauty Salon",
            "type":"Services"
        }
    ],
    "sg:phone":"+1 506 459 5027",
    "sg:postcode":"E3B 1C2",
    "sg:province":"NB",
    "sg:tags":[
        "barber"
    ],
    "wof:name":"Fox's Barber Shop",
    "wof:placetype":"venue"
},
  "geometry": {"coordinates":[-66.63861799999999,45.961018],"type":"Point"}
}