{
  "type": "Feature",
  "properties": {
    "iso:country":"CA",
    "sg:city":"Richmond",
    "sg:classifiers":[
        {
            "category":"Building & Trades",
            "subcategory":"Construction",
            "type":"Services"
        }
    ],
    "sg:phone":"+1 604 270 2256",
    "sg:postcode":"V6V 1Z5",
    "sg:province":"BC",
    "sg:tags":[
        "general",
        "contractor"
    ],
    "wof:name":"Darby Construction Ltd",
    "wof:placetype":"venue"
},
  "geometry": {"coordinates":[-123.08482360799999,49.1955108643],"type":"Point"}
}