{
  "type": "Feature",
  "properties": {
    "addr:full":"124 Burnstown Rd White Lake ON K0A 3L0",
    "addr:housenumber":"124",
    "addr:postcode":"k0a 3l0",
    "addr:street":"Burnstown Rd",
    "iso:country":"CA",
    "sg:address":"124 Burnstown Rd",
    "sg:city":"White Lake",
    "sg:classifiers":[
        {
            "category":"Freight",
            "type":"Transportation"
        }
    ],
    "sg:phone":"+1 613 623 8264",
    "sg:postcode":"K0A 3L0",
    "sg:province":"ON",
    "sg:tags":[
        "courier"
    ],
    "wof:name":"Madawaska Express Courier",
    "wof:placetype":"venue"
},
  "geometry": {"coordinates":[-76.503265,45.363312],"type":"Point"}
}