{
  "type": "Feature",
  "properties": {
    "addr:full":"West Vancouver BC V7T 1B9",
    "addr:postcode":"v7t 1b9",
    "iso:country":"CA",
    "sg:city":"West Vancouver",
    "sg:classifiers":[
        {
            "category":"Professional",
            "subcategory":"Business Services",
            "type":"Services"
        }
    ],
    "sg:phone":"+1 604 926 1985",
    "sg:postcode":"V7T 1B9",
    "sg:province":"BC",
    "sg:tags":[
        "paging",
        "answering"
    ],
    "wof:name":"Accutype Secretarial Svc",
    "wof:placetype":"venue"
},
  "geometry": {"coordinates":[-123.155029,49.328175],"type":"Point"}
}