{
  "type": "Feature",
  "properties": {
    "addr:full":"Saskatoon SK S7L 6A3",
    "addr:postcode":"s7l 6a3",
    "iso:country":"CA",
    "sg:city":"Saskatoon",
    "sg:classifiers":[
        {
            "category":"Freight",
            "type":"Transportation"
        }
    ],
    "sg:phone":"+1 306 653 8500",
    "sg:postcode":"S7L 6A3",
    "sg:province":"SK",
    "sg:tags":[
        "courier",
        "trucking"
    ],
    "wof:name":"Custom Courier Svc",
    "wof:placetype":"venue"
},
  "geometry": {"coordinates":[-106.67215,52.162815],"type":"Point"}
}