{
  "type": "Feature",
  "properties": {
    "addr:full":"4220 Norland Ave Burnaby BC V5G 3X2",
    "addr:housenumber":"4220",
    "addr:postcode":"v5g 3x2",
    "addr:street":"Norland Ave",
    "iso:country":"CA",
    "sg:address":"4220 Norland Ave",
    "sg:city":"Burnaby",
    "sg:classifiers":[
        {
            "category":"Organizations",
            "subcategory":"Labor Organization",
            "type":"Services"
        }
    ],
    "sg:phone":"+1 604 571 6540",
    "sg:postcode":"V5G 3X2",
    "sg:province":"BC",
    "wof:name":"Ibew Apprenticeship Training",
    "wof:placetype":"venue"
},
  "geometry": {"coordinates":[-122.974502563,49.2464294434],"type":"Point"}
}