{
  "type": "Feature",
  "properties": {
    "addr:full":"55 Lansdowne St N Souris MB R0K 2C0",
    "addr:housenumber":"55",
    "addr:postcode":"r0k 2c0",
    "addr:street":"Lansdowne St N",
    "iso:country":"CA",
    "sg:address":"55 Lansdowne St N",
    "sg:city":"Souris",
    "sg:classifiers":[
        {
            "category":"Education",
            "subcategory":"School",
            "type":"Public Place"
        }
    ],
    "sg:phone":"+1 204 483 2161",
    "sg:postcode":"R0K 2C0",
    "sg:province":"MB",
    "wof:name":"Souris School",
    "wof:placetype":"venue"
},
  "geometry": {"coordinates":[-100.258865,49.620834],"type":"Point"}
}