{
  "type": "Feature",
  "properties": {
    "addr:full":"12 Donald Dr Port Carling ON P0B 1J0",
    "addr:housenumber":"12",
    "addr:postcode":"p0b 1j0",
    "addr:street":"Donald Dr",
    "iso:country":"CA",
    "sg:address":"12 Donald Dr",
    "sg:city":"Port Carling",
    "sg:classifiers":[
        {
            "category":"Sports & Exercise",
            "subcategory":"Golf",
            "type":"Entertainment"
        }
    ],
    "sg:phone":"+1 705 765 6600",
    "sg:postcode":"P0B 1J0",
    "sg:province":"ON",
    "sg:tags":[
        "course"
    ],
    "wof:name":"Port Carling Golf & Country",
    "wof:placetype":"venue"
},
  "geometry": {"coordinates":[-79.588973999,45.1167564392],"type":"Point"}
}