{
  "type": "Feature",
  "properties": {
    "iso:country":"CA",
    "sg:address":"2135 Pegasus Rd NE",
    "sg:city":"Calgary",
    "sg:classifiers":[
        {
            "category":"Freight",
            "type":"Transportation"
        }
    ],
    "sg:phone":"+1 403 250 3894",
    "sg:postcode":"T2E 8C3",
    "sg:province":"AB",
    "sg:tags":[
        "commercial",
        "storage"
    ],
    "wof:name":"Sentinel Self-Storage",
    "wof:placetype":"venue"
},
  "geometry": {"coordinates":[-114.007881165,51.0938110352],"type":"Point"}
}