{
  "type": "Feature",
  "properties": {
    "addr:full":"1380 Matheson Blvd E # 5 Mississauga ON L4W 4P8",
    "addr:housenumber":"1380",
    "addr:postcode":"l4w 4p8",
    "addr:street":"Matheson Blvd E # 5",
    "iso:country":"CA",
    "sg:address":"1380 Matheson Blvd E # 5",
    "sg:city":"Mississauga",
    "sg:classifiers":[
        {
            "category":"Retail",
            "subcategory":"Auto Repair",
            "type":"Services"
        }
    ],
    "sg:phone":"+1 905 212 1266",
    "sg:postcode":"L4W 4P8",
    "sg:province":"ON",
    "sg:tags":[
        "body",
        "automobile",
        "painting"
    ],
    "wof:name":"Dent Clinic Ontario",
    "wof:placetype":"venue"
},
  "geometry": {"coordinates":[-79.63111114500001,43.6419410706],"type":"Point"}
}