{
  "type": "Feature",
  "properties": {
    "addr:full":"7080 West Saanich Rd Brentwood Bay BC V8M 1P9",
    "addr:housenumber":"7080",
    "addr:postcode":"v8m 1p9",
    "addr:street":"West Saanich Rd",
    "iso:country":"CA",
    "sg:address":"7080 West Saanich Rd",
    "sg:city":"Brentwood Bay",
    "sg:classifiers":[
        {
            "category":"Autos & Motor Vehicles",
            "subcategory":"Fuel & Gas Station",
            "type":"Retail Goods"
        }
    ],
    "sg:phone":"+1 250 652 4143",
    "sg:postcode":"V8M 1P9",
    "sg:province":"BC",
    "sg:tags":[
        "oil"
    ],
    "wof:name":"Brentwood Chevron Svc",
    "wof:placetype":"venue"
},
  "geometry": {"coordinates":[-123.444489,48.574543],"type":"Point"}
}