{
  "type": "Feature",
  "properties": {
    "addr:full":"1807 42 St SE Calgary AB T2B 1G1",
    "addr:housenumber":"1807",
    "addr:postcode":"t2b 1g1",
    "addr:street":"42 St Se",
    "iso:country":"CA",
    "sg:address":"1807 42 St SE",
    "sg:city":"Calgary",
    "sg:classifiers":[
        {
            "category":"Manufacturing",
            "subcategory":"Chemicals & Compounds",
            "type":"Manufacturing & Wholesale Goods"
        }
    ],
    "sg:phone":"+1 403 272 5074",
    "sg:postcode":"T2B 1G1",
    "sg:province":"AB",
    "sg:tags":[
        "paint"
    ],
    "wof:name":"Mills Paint & Wallcoverings",
    "wof:placetype":"venue"
},
  "geometry": {"coordinates":[-113.97302999999999,51.037605],"type":"Point"}
}