{
  "type": "Feature",
  "properties": {
    "iso:country":"CA",
    "sg:address":"494 Jarvis Ave",
    "sg:city":"Winnipeg",
    "sg:classifiers":[
        {
            "category":"Manufacturing",
            "subcategory":"Building Materials",
            "type":"Manufacturing & Wholesale Goods"
        }
    ],
    "sg:phone":"+1 204 589 9200",
    "sg:postcode":"R2W 3A9",
    "sg:province":"MB",
    "wof:name":"Display Fixtures",
    "wof:placetype":"venue"
},
  "geometry": {"coordinates":[-97.1471481323,49.9116210938],"type":"Point"}
}