{
  "type": "Feature",
  "properties": {
    "addr:full":"280 Bernard Ave Kelowna BC V1Y 6N4",
    "addr:housenumber":"280",
    "addr:postcode":"v1y 6n4",
    "addr:street":"Bernard Ave",
    "iso:country":"CA",
    "sg:address":"280 Bernard Ave",
    "sg:city":"Kelowna",
    "sg:classifiers":[
        {
            "category":"Restaurant",
            "type":"Food & Drink"
        }
    ],
    "sg:phone":"+1 250 861 1305",
    "sg:postcode":"V1Y 6N4",
    "sg:province":"BC",
    "wof:name":"Dragon King Restaurant",
    "wof:placetype":"venue"
},
  "geometry": {"coordinates":[-119.49715399999999,49.88644],"type":"Point"}
}