{
  "type": "Feature",
  "properties": {
    "addr:full":"1562 100th St North Battleford SK S9A 0W4",
    "addr:housenumber":"1562",
    "addr:postcode":"s9a 0w4",
    "addr:street":"100Th St",
    "iso:country":"CA",
    "sg:address":"1562 100th St",
    "sg:city":"North Battleford",
    "sg:classifiers":[
        {
            "category":"Health Services",
            "subcategory":"Doctor",
            "type":"Services"
        }
    ],
    "sg:phone":"+1 306 445 3317",
    "sg:postcode":"S9A 0W4",
    "sg:province":"SK",
    "sg:tags":[
        "dentist"
    ],
    "wof:name":"Williams Dental Clinic",
    "wof:placetype":"venue"
},
  "geometry": {"coordinates":[-108.29881286600001,52.7805595398],"type":"Point"}
}