{
  "type": "Feature",
  "properties": {
    "addr:full":"York ON M9N 1J2",
    "addr:postcode":"m9n 1j2",
    "iso:country":"CA",
    "sg:city":"York",
    "sg:classifiers":[
        {
            "category":"Professional",
            "subcategory":"Lawyer & Legal Services",
            "type":"Services"
        }
    ],
    "sg:phone":"+1 416 241 0111",
    "sg:postcode":"M9N 1J2",
    "sg:province":"ON",
    "sg:tags":[
        "attorney"
    ],
    "wof:name":"Fraser Simms & Reid",
    "wof:placetype":"venue"
},
  "geometry": {"coordinates":[-79.886353,43.022453],"type":"Point"}
}