{
  "type": "Feature",
  "properties": {
    "iso:country":"CA",
    "sg:address":"224262 Ostrander Rd",
    "sg:city":"Tillsonburg",
    "sg:classifiers":[
        {
            "category":"Retail",
            "subcategory":"Veterinary Services",
            "type":"Services"
        }
    ],
    "sg:phone":"+1 519 842 7845",
    "sg:postcode":"N4G 4H1",
    "sg:province":"ON",
    "sg:tags":[
        "veterinarian"
    ],
    "wof:name":"Mac Donald, Allyson DVM",
    "wof:placetype":"venue"
},
  "geometry": {"coordinates":[-80.7278671265,42.8606758118],"type":"Point"}
}