{
  "type": "Feature",
  "properties": {
    "addr:full":"1590 Griffin Terr Kamloops BC V2B 7R6",
    "addr:housenumber":"1590",
    "addr:postcode":"bc v2b 7r6",
    "addr:street":"Griffin Terr",
    "iso:country":"CA",
    "sg:address":"1590 Griffin Terr",
    "sg:city":"Kamloops",
    "sg:classifiers":[
        {
            "category":"Insurance",
            "subcategory":"Insurance Agent",
            "type":"Services"
        }
    ],
    "sg:phone":"+1 250 376 4400",
    "sg:postcode":"V2B 7R6",
    "sg:province":"BC",
    "wof:name":"Morris Insurance Svc",
    "wof:placetype":"venue"
},
  "geometry": {"coordinates":[-120.373451,50.713821],"type":"Point"}
}