{
  "type": "Feature",
  "properties": {
    "iso:country":"CA",
    "sg:address":"3912 44th St",
    "sg:city":"Lloydminster",
    "sg:classifiers":[
        {
            "category":"Retail",
            "subcategory":"Auto Repair",
            "type":"Services"
        }
    ],
    "sg:phone":"+1 306 825 4454",
    "sg:postcode":"S9V 0Y1",
    "sg:province":"SK",
    "sg:tags":[
        "repairing",
        "automobile"
    ],
    "wof:name":"All-O-Matic Transmission Clnc",
    "wof:placetype":"venue"
},
  "geometry": {"coordinates":[-109.992027283,53.2620506287],"type":"Point"}
}