{
  "type": "Feature",
  "properties": {
    "addr:full":"320 Durham St E Walkerton ON N0G 2V0",
    "addr:housenumber":"320",
    "addr:postcode":"n0g 2v0",
    "addr:street":"Durham St E Walkerton",
    "iso:country":"CA",
    "sg:address":"320 Durham St E",
    "sg:city":"Walkerton",
    "sg:classifiers":[
        {
            "category":"Professional",
            "subcategory":"Accounting & Tax Preparation",
            "type":"Services"
        }
    ],
    "sg:phone":"+1 519 881 0620",
    "sg:postcode":"N0G 2V0",
    "sg:province":"ON",
    "sg:tags":[
        "return",
        "filing"
    ],
    "wof:name":"Bruce Grey Bookkeeping Svc",
    "wof:placetype":"venue"
},
  "geometry": {"coordinates":[-81.1481170654,44.1331825256],"type":"Point"}
}