{
  "type": "Feature",
  "properties": {
    "addr:full":"59 Carden St Guelph ON N1H 2Z9",
    "addr:housenumber":"59",
    "addr:postcode":"n1h 2z9",
    "addr:street":"Carden St",
    "iso:country":"CA",
    "sg:address":"59 Carden St",
    "sg:city":"Guelph",
    "sg:classifiers":[
        {
            "category":"Government",
            "subcategory":"Office",
            "type":"Public Place"
        }
    ],
    "sg:phone":"+1 519 837 5603",
    "sg:postcode":"N1H 2Z9",
    "sg:province":"ON",
    "sg:tags":[
        "village"
    ],
    "wof:name":"Guelph City Information Svc",
    "wof:placetype":"venue"
},
  "geometry": {"coordinates":[-80.24797058110001,43.5440444946],"type":"Point"}
}