{
  "type": "Feature",
  "properties": {
    "addr:full":"680 Great Northern Rd Sault Ste Marie ON P6B 5A2",
    "addr:housenumber":"680",
    "addr:postcode":"p6b 5a2",
    "addr:street":"Great Northern Rd",
    "iso:country":"CA",
    "sg:address":"680 Great Northern Rd",
    "sg:city":"Sault Ste Marie",
    "sg:classifiers":[
        {
            "category":"Autos & Motor Vehicles",
            "subcategory":"Automobile Sales",
            "type":"Retail Goods"
        }
    ],
    "sg:phone":"+1 705 256 5326",
    "sg:postcode":"P6B 5A2",
    "sg:province":"ON",
    "sg:tags":[
        "car",
        "dealer"
    ],
    "wof:name":"Bud Robinson Used Cars",
    "wof:placetype":"venue"
},
  "geometry": {"coordinates":[-84.319115,46.545906],"type":"Point"}
}