{
  "type": "Feature",
  "properties": {
    "addr:full":"968 Redonda St Winnipeg MB R2C 2Z2",
    "addr:housenumber":"968",
    "addr:postcode":"r2c 2z2",
    "addr:street":"Redonda St",
    "iso:country":"CA",
    "sg:address":"968 Redonda St",
    "sg:city":"Winnipeg",
    "sg:classifiers":[
        {
            "category":"Building & Trades",
            "subcategory":"Construction",
            "type":"Services"
        }
    ],
    "sg:phone":"+1 204 777 0342",
    "sg:postcode":"R2C 2Z2",
    "sg:province":"MB",
    "sg:tags":[
        "maker",
        "cabinet"
    ],
    "wof:name":"Bwi Woodworking Ltd",
    "wof:placetype":"venue"
},
  "geometry": {"coordinates":[-96.979523,49.915531],"type":"Point"}
}