{
  "type": "Feature",
  "properties": {
    "addr:full":"2300 Finch Ave W North York ON M9M 2Y3",
    "addr:housenumber":"2300",
    "addr:postcode":"m9m 2y3",
    "addr:street":"Finch Ave W",
    "iso:country":"CA",
    "sg:address":"2300 Finch Ave W",
    "sg:city":"North York",
    "sg:classifiers":[
        {
            "category":"Government",
            "subcategory":"Office",
            "type":"Public Place"
        }
    ],
    "sg:phone":"+1 416 743 7272",
    "sg:postcode":"M9M 2Y3",
    "sg:province":"ON",
    "wof:name":"Ontario Provincial Parliament",
    "wof:placetype":"venue"
},
  "geometry": {"coordinates":[-79.540459,43.75251],"type":"Point"}
}