{
  "type": "Feature",
  "properties": {
    "iso:country":"CA",
    "sg:city":"Boucherville",
    "sg:classifiers":[
        {
            "category":"Building & Trades",
            "subcategory":"Plumbing",
            "type":"Services"
        }
    ],
    "sg:phone":"+1 450 449 3544",
    "sg:postcode":"J4B 5Z5",
    "sg:province":"QC",
    "sg:tags":[
        "conditioning",
        "air",
        "system",
        "contractor"
    ],
    "wof:name":"Blm Refrigeration Inc",
    "wof:placetype":"venue"
},
  "geometry": {"coordinates":[-73.4155654907,45.5706748962],"type":"Point"}
}