{
  "type": "Feature",
  "properties": {
    "addr:full":"Alliston ON L9R 1E7",
    "addr:postcode":"l9r 1e7",
    "addr:street":"Alliston",
    "iso:country":"CA",
    "sg:city":"Alliston",
    "sg:classifiers":[
        {
            "category":"Recreation",
            "type":"Entertainment"
        }
    ],
    "sg:phone":"+1 705 435 4300",
    "sg:postcode":"L9R 1E7",
    "sg:province":"ON",
    "sg:tags":[
        "parachute",
        "skydiving",
        "jumping"
    ],
    "wof:name":"Highline Ropes",
    "wof:placetype":"venue"
},
  "geometry": {"coordinates":[-79.86219024659999,44.1478843689],"type":"Point"}
}