{
  "type": "Feature",
  "properties": {
    "iso:country":"CA",
    "sg:address":"103 Warwick St",
    "sg:city":"Digby",
    "sg:classifiers":[
        {
            "category":"Home & Garden",
            "subcategory":"Building Materials",
            "type":"Retail Goods"
        }
    ],
    "sg:phone":"+1 902 245 4731",
    "sg:postcode":"B0V 1A0",
    "sg:province":"NS",
    "wof:name":"Wilson's Hardware Ltd",
    "wof:placetype":"venue"
},
  "geometry": {"coordinates":[-65.7618484497,44.6169319153],"type":"Point"}
}