{
  "type": "Feature",
  "properties": {
    "addr:full":"Dartmouth NS B3B 1M2",
    "addr:postcode":"b3b 1m2",
    "iso:country":"CA",
    "sg:city":"Dartmouth",
    "sg:classifiers":[
        {
            "category":"Building & Trades",
            "subcategory":"Construction",
            "type":"Services"
        }
    ],
    "sg:phone":"+1 902 468 7471",
    "sg:postcode":"B3B 1M2",
    "sg:province":"NS",
    "sg:tags":[
        "general",
        "contractor"
    ],
    "wof:name":"Maxim Construction Inc",
    "wof:placetype":"venue"
},
  "geometry": {"coordinates":[-63.611061,44.705479],"type":"Point"}
}