{
  "type": "Feature",
  "properties": {
    "iso:country":"CA",
    "sg:address":"1595 Bedford Hwy # 24",
    "sg:city":"Bedford",
    "sg:classifiers":[
        {
            "category":"Shopping",
            "subcategory":"Clothing, Apparel, & Fashions",
            "type":"Retail Goods"
        }
    ],
    "sg:phone":"+1 902 832 3664",
    "sg:postcode":"B4A 3Y4",
    "sg:province":"NS",
    "sg:tags":[
        "sportswear"
    ],
    "wof:name":"Roots Canada Ltd",
    "wof:placetype":"venue"
},
  "geometry": {"coordinates":[-63.6559715271,44.7327804565],"type":"Point"}
}