{
  "type": "Feature",
  "properties": {
    "addr:full":"430 Graham Ave Fort Erie ON L2A 4K6",
    "addr:housenumber":"430",
    "addr:postcode":"l2a 4k6",
    "addr:street":"Graham Ave",
    "iso:country":"CA",
    "sg:address":"430 Graham Ave",
    "sg:city":"Fort Erie",
    "sg:classifiers":[
        {
            "category":"Wholesale",
            "subcategory":"Machinery & Supplies",
            "type":"Manufacturing & Wholesale Goods"
        }
    ],
    "sg:phone":"+1 905 871 3560",
    "sg:postcode":"L2A 4K6",
    "sg:province":"ON",
    "sg:tags":[
        "engine"
    ],
    "wof:name":"Jack's Small Engines Repair",
    "wof:placetype":"venue"
},
  "geometry": {"coordinates":[-78.937645,42.887661],"type":"Point"}
}