{
  "type": "Feature",
  "properties": {
    "addr:full":"10 Old York Mills Rd North York ON M2P 2G9",
    "addr:housenumber":"10",
    "addr:postcode":"m2p 2g9",
    "addr:street":"Old York Mills Rd",
    "iso:country":"CA",
    "sg:address":"10 Old York Mills Rd",
    "sg:city":"North York",
    "sg:classifiers":[
        {
            "category":"Real Estate",
            "subcategory":"Real Estate Operator",
            "type":"Services"
        }
    ],
    "sg:phone":"+1 416 512 0867",
    "sg:postcode":"M2P 2G9",
    "sg:province":"ON",
    "sg:tags":[
        "management",
        "apartment"
    ],
    "wof:name":"Del Property Management",
    "wof:placetype":"venue"
},
  "geometry": {"coordinates":[-79.4057312012,43.7436065674],"type":"Point"}
}