{
  "type": "Feature",
  "properties": {
    "addr:full":"78 Boulder Blvd Stony Plain AB T7Z 1V7",
    "addr:housenumber":"78",
    "addr:postcode":"t7z 1v7",
    "addr:street":"Boulder Blvd",
    "iso:country":"CA",
    "sg:address":"78 Boulder Blvd",
    "sg:city":"Stony Plain",
    "sg:classifiers":[
        {
            "category":"Restaurant",
            "type":"Food & Drink"
        }
    ],
    "sg:phone":"+1 780 968 5595",
    "sg:postcode":"T7Z 1V7",
    "sg:province":"AB",
    "wof:name":"Abc Country Restaurant",
    "wof:placetype":"venue"
},
  "geometry": {"coordinates":[-113.977242,53.542278],"type":"Point"}
}