{
  "type": "Feature",
  "properties": {
    "iso:country":"CA",
    "sg:address":"2158 Broadway W",
    "sg:city":"Vancouver",
    "sg:classifiers":[
        {
            "category":"Health Services",
            "subcategory":"Chiropractor",
            "type":"Services"
        }
    ],
    "sg:phone":"+1 604 737 0706",
    "sg:postcode":"V6K 2C8",
    "sg:province":"BC",
    "wof:name":"Broadway Corridor Chiropractic",
    "wof:placetype":"venue"
},
  "geometry": {"coordinates":[-123.15424346899999,49.2637329102],"type":"Point"}
}