{
  "type": "Feature",
  "properties": {
    "addr:full":"7540 Bell Mckinnon Rd Duncan BC V9L 6B1",
    "addr:housenumber":"7540",
    "addr:postcode":"v9l 6b1",
    "addr:street":"Bell Mckinnon Rd",
    "iso:country":"CA",
    "sg:address":"7540 Bell Mckinnon Rd",
    "sg:city":"Duncan",
    "sg:classifiers":[
        {
            "category":"Wholesale",
            "subcategory":"Plants",
            "type":"Manufacturing & Wholesale Goods"
        }
    ],
    "sg:phone":"+1 250 715 1447",
    "sg:postcode":"V9L 6B1",
    "sg:province":"BC",
    "sg:tags":[
        "greenhouse"
    ],
    "wof:name":"Tilladown Greenhouse Growers",
    "wof:placetype":"venue"
},
  "geometry": {"coordinates":[-123.707382,48.779095],"type":"Point"}
}