{
  "type": "Feature",
  "properties": {
    "addr:full":"St Isidore ON K0C 2B0",
    "addr:postcode":"k0c 2b0",
    "addr:street":"St Isidore",
    "iso:country":"CA",
    "sg:city":"St Isidore",
    "sg:classifiers":[
        {
            "category":"Home & Garden",
            "subcategory":"Furniture",
            "type":"Retail Goods"
        }
    ],
    "sg:phone":"+1 613 524 3333",
    "sg:postcode":"K0C 2B0",
    "sg:province":"ON",
    "wof:name":"Meuble Home Furniture",
    "wof:placetype":"venue"
},
  "geometry": {"coordinates":[-74.906769,45.387691],"type":"Point"}
}