{
  "type": "Feature",
  "properties": {
    "addr:full":"Calgary AB T1Y 5E4",
    "addr:postcode":"t1y 5e4",
    "iso:country":"CA",
    "sg:city":"Calgary",
    "sg:classifiers":[
        {
            "category":"Manufacturing",
            "subcategory":"Tools & Machinery",
            "type":"Manufacturing & Wholesale Goods"
        }
    ],
    "sg:phone":"+1 403 250 2685",
    "sg:postcode":"T1Y 5E4",
    "sg:province":"AB",
    "sg:tags":[
        "irrigation",
        "system",
        "sprinkler"
    ],
    "wof:name":"Regency Irrigation Ltd",
    "wof:placetype":"venue"
},
  "geometry": {"coordinates":[-113.995018,51.08461],"type":"Point"}
}