{
  "type": "Feature",
  "properties": {
    "addr:full":"4946 Lake Kathlyn Junction Rd Smithers BC V0J 2N2",
    "addr:housenumber":"4946",
    "addr:postcode":"v0j 2n2",
    "addr:street":"Lake Kathlyn Junction Rd",
    "iso:country":"CA",
    "sg:address":"4946 Lake Kathlyn Junction Rd",
    "sg:city":"Smithers",
    "sg:classifiers":[
        {
            "category":"Wholesale",
            "subcategory":"Meat",
            "type":"Manufacturing & Wholesale Goods"
        }
    ],
    "sg:phone":"+1 250 847 3361",
    "sg:postcode":"V0J 2N2",
    "sg:province":"BC",
    "sg:tags":[
        "butchering"
    ],
    "wof:name":"Hammings Butcher Shop",
    "wof:placetype":"venue"
},
  "geometry": {"coordinates":[-127.16812899999999,54.782803],"type":"Point"}
}