{
  "type": "Feature",
  "properties": {
    "addr:full":"1227 Rue DE LA Montagne Montreal QC H3G 1Z2",
    "addr:housenumber":"1227",
    "addr:postcode":"h3g 1z2",
    "addr:street":"Rue De La Montagne",
    "iso:country":"CA",
    "sg:address":"1227 Rue DE LA Montagne",
    "sg:city":"Montreal",
    "sg:classifiers":[
        {
            "category":"Restaurant",
            "type":"Food & Drink"
        }
    ],
    "sg:phone":"+1 514 398 9229",
    "sg:postcode":"H3G 1Z2",
    "sg:province":"QC",
    "wof:name":"Europea Restaurant",
    "wof:placetype":"venue"
},
  "geometry": {"coordinates":[-73.573868,45.497517],"type":"Point"}
}