{
  "type": "Feature",
  "properties": {
    "addr:full":"7156 Duncan St Powell River BC V8A 5J4",
    "addr:housenumber":"7156",
    "addr:postcode":"v8a 5j4",
    "addr:street":"Duncan St",
    "iso:country":"CA",
    "sg:address":"7156 Duncan St",
    "sg:city":"Powell River",
    "sg:classifiers":[
        {
            "category":"Government",
            "subcategory":"Office",
            "type":"Public Place"
        }
    ],
    "sg:phone":"+1 604 485 4606",
    "sg:postcode":"V8A 5J4",
    "sg:province":"BC",
    "sg:tags":[
        "village"
    ],
    "wof:name":"Powell River Dog Pound",
    "wof:placetype":"venue"
},
  "geometry": {"coordinates":[-124.51461792000001,49.8365440369],"type":"Point"}
}