{
  "type": "Feature",
  "properties": {
    "addr:full":"61 Lewis Rd Guelph ON N1H 1E9",
    "addr:housenumber":"61",
    "addr:postcode":"n1h 1e9",
    "addr:street":"Lewis Rd",
    "iso:country":"CA",
    "sg:address":"61 Lewis Rd",
    "sg:city":"Guelph",
    "sg:classifiers":[
        {
            "category":"Manufacturing",
            "subcategory":"Printing",
            "type":"Manufacturing & Wholesale Goods"
        }
    ],
    "sg:phone":"+1 519 836 3780",
    "sg:postcode":"N1H 1E9",
    "sg:province":"ON",
    "sg:tags":[
        "printer"
    ],
    "wof:name":"Fast Printing By Complete Svc",
    "wof:placetype":"venue"
},
  "geometry": {"coordinates":[-80.29461669920001,43.5463485718],"type":"Point"}
}