{
  "type": "Feature",
  "properties": {
    "addr:full":"Fernie BC V0B 1M1",
    "addr:postcode":"bc v0b 1m1",
    "iso:country":"CA",
    "sg:city":"Fernie",
    "sg:classifiers":[
        {
            "category":"Autos & Motor Vehicles",
            "subcategory":"Fuel & Gas Station",
            "type":"Retail Goods"
        }
    ],
    "sg:phone":"+1 250 423 3613",
    "sg:postcode":"V0B 1M1",
    "sg:province":"BC",
    "sg:tags":[
        "oil"
    ],
    "wof:name":"West Fernie Turbo",
    "wof:placetype":"venue"
},
  "geometry": {"coordinates":[-115.06295,49.509483],"type":"Point"}
}