{
  "type": "Feature",
  "properties": {
    "addr:full":"Trans-Canada Hwy Lytton BC V0K 1Z0",
    "addr:postcode":"v0k 1z0",
    "addr:street":"Trans-Canada Hwy",
    "iso:country":"CA",
    "sg:address":"Trans-Canada Hwy",
    "sg:city":"Lytton",
    "sg:classifiers":[
        {
            "category":"Manufacturing",
            "subcategory":"Lumber",
            "type":"Manufacturing & Wholesale Goods"
        }
    ],
    "sg:phone":"+1 250 455 2605",
    "sg:postcode":"V0K 1Z0",
    "sg:province":"BC",
    "wof:name":"Kam-Pac Forest Products Ltd",
    "wof:placetype":"venue"
},
  "geometry": {"coordinates":[-121.57383,50.239834],"type":"Point"}
}