{
  "type": "Feature",
  "properties": {
    "addr:full":"PO Box 5620 STN Main Bonnyville AB T9N 2G6",
    "addr:housenumber":"po",
    "addr:postcode":"5620;t9n 2g6",
    "addr:street":"Box;Stn Main",
    "iso:country":"CA",
    "sg:address":"PO Box 5620 STN Main",
    "sg:city":"Bonnyville",
    "sg:classifiers":[
        {
            "category":"Building & Trades",
            "subcategory":"Construction",
            "type":"Services"
        }
    ],
    "sg:phone":"+1 780 812 0047",
    "sg:postcode":"T9N 2G6",
    "sg:province":"AB",
    "sg:tags":[
        "concrete",
        "cutting",
        "breaking",
        "sawing"
    ],
    "wof:name":"Lakeland Reinforcing Ltd",
    "wof:placetype":"venue"
},
  "geometry": {"coordinates":[-110.753662109,54.26795578],"type":"Point"}
}