{
  "type": "Feature",
  "properties": {
    "iso:country":"CA",
    "sg:city":"Milden",
    "sg:classifiers":[
        {
            "category":"Wholesale",
            "subcategory":"Petroleum",
            "type":"Manufacturing & Wholesale Goods"
        }
    ],
    "sg:phone":"+1 306 935 2027",
    "sg:postcode":"S0L 2L0",
    "sg:province":"SK",
    "sg:tags":[
        "pipe",
        "line",
        "company"
    ],
    "wof:name":"Enbridge Pipelines Inc",
    "wof:placetype":"venue"
},
  "geometry": {"coordinates":[-107.527252197,51.4861297607],"type":"Point"}
}