{
  "type": "Feature",
  "properties": {
    "addr:full":"417 Smith St New Waterford NS B1H 3R3",
    "addr:housenumber":"417",
    "addr:postcode":"b1h 3r3",
    "addr:street":"Smith St",
    "iso:country":"CA",
    "sg:address":"417 Smith St",
    "sg:city":"New Waterford",
    "sg:classifiers":[
        {
            "category":"Organizations",
            "subcategory":"Religious Organization",
            "type":"Services"
        }
    ],
    "sg:phone":"+1 902 862 2436",
    "sg:postcode":"B1H 3R3",
    "sg:province":"NS",
    "sg:tags":[
        "church"
    ],
    "wof:name":"Calvin United Church",
    "wof:placetype":"venue"
},
  "geometry": {"coordinates":[-60.086624,46.249985],"type":"Point"}
}