{
  "type": "Feature",
  "properties": {
    "addr:full":"7620 101 Hwy Powell River BC V8A 4Z2",
    "addr:housenumber":"7620",
    "addr:postcode":"v8a 4z2",
    "addr:street":"101 Hwy Powell",
    "iso:country":"CA",
    "sg:address":"7620 101 Hwy",
    "sg:city":"Powell River",
    "sg:classifiers":[
        {
            "category":"Building & Trades",
            "subcategory":"Construction",
            "type":"Services"
        }
    ],
    "sg:phone":"+1 604 485 9666",
    "sg:postcode":"V8A 4Z2",
    "sg:province":"BC",
    "sg:tags":[
        "material",
        "culvert"
    ],
    "wof:name":"Les's Lumber",
    "wof:placetype":"venue"
},
  "geometry": {"coordinates":[-124.585548,49.895519],"type":"Point"}
}