{
  "type": "Feature",
  "properties": {
    "iso:country":"CA",
    "sg:address":"202 3rd St",
    "sg:city":"Hague",
    "sg:classifiers":[
        {
            "category":"Organizations",
            "subcategory":"Religious Organization",
            "type":"Services"
        }
    ],
    "sg:phone":"+1 306 225 2211",
    "sg:postcode":"S0K 1X0",
    "sg:province":"SK",
    "sg:tags":[
        "church"
    ],
    "wof:name":"Hague Mennonite Church",
    "wof:placetype":"venue"
},
  "geometry": {"coordinates":[-106.41189575200001,52.5121803284],"type":"Point"}
}