{
  "type": "Feature",
  "properties": {
    "iso:country":"CA",
    "sg:address":"22190 48 Ave",
    "sg:city":"Langley",
    "sg:classifiers":[
        {
            "category":"Health Services",
            "subcategory":"Doctor",
            "type":"Services"
        }
    ],
    "sg:phone":"+1 604 534 8151",
    "sg:postcode":"V3A 3N5",
    "sg:province":"BC",
    "sg:tags":[
        "physician",
        "surgeon"
    ],
    "wof:name":"Nmhs Holdings",
    "wof:placetype":"venue"
},
  "geometry": {"coordinates":[-122.608749,49.089184],"type":"Point"}
}