{
  "type": "Feature",
  "properties": {
    "iso:country":"CA",
    "sg:address":"461 St Catherines Rd",
    "sg:city":"Souris",
    "sg:classifiers":[
        {
            "category":"Wholesale",
            "subcategory":"Farm Supplies",
            "type":"Manufacturing & Wholesale Goods"
        }
    ],
    "sg:phone":"+1 902 687 3620",
    "sg:postcode":"C0A 2B0",
    "sg:province":"PE",
    "sg:tags":[
        "feed"
    ],
    "wof:name":"Eastern Feed & Seed Svc",
    "wof:placetype":"venue"
},
  "geometry": {"coordinates":[-62.24173,46.364319],"type":"Point"}
}