{
  "type": "Feature",
  "properties": {
    "addr:full":"81 Rue Saint-Georges Beauharnois QC J6N 1Y9",
    "addr:housenumber":"81",
    "addr:postcode":"j6n 1y9",
    "addr:street":"Rue Saint-Georges",
    "iso:country":"CA",
    "sg:address":"81 Rue Saint-Georges",
    "sg:city":"Beauharnois",
    "sg:classifiers":[
        {
            "category":"Wholesale",
            "subcategory":"Durable Goods & Equipment",
            "type":"Manufacturing & Wholesale Goods"
        }
    ],
    "sg:phone":"+1 450 225 1186",
    "sg:postcode":"J6N 1Y9",
    "sg:province":"QC",
    "sg:tags":[
        "fire",
        "extinguisher"
    ],
    "wof:name":"Securite Incendie Sos Enr",
    "wof:placetype":"venue"
},
  "geometry": {"coordinates":[-73.8741,45.312717],"type":"Point"}
}