{
  "type": "Feature",
  "properties": {
    "addr:full":"Neepawa MB R0J 1H0",
    "addr:postcode":"r0j 1h0",
    "iso:country":"CA",
    "sg:city":"Neepawa",
    "sg:classifiers":[
        {
            "category":"Health Services",
            "subcategory":"Chiropractor",
            "type":"Services"
        }
    ],
    "sg:phone":"+1 204 476 3984",
    "sg:postcode":"R0J 1H0",
    "sg:province":"MB",
    "wof:name":"Neepawa Chiropractic Ctr",
    "wof:placetype":"venue"
},
  "geometry": {"coordinates":[-99.466324,50.227119],"type":"Point"}
}