{
  "type": "Feature",
  "properties": {
    "addr:full":"North Vancouver BC V7J 3H2",
    "addr:postcode":"v7j 3h2",
    "iso:country":"CA",
    "sg:city":"North Vancouver",
    "sg:classifiers":[
        {
            "category":"Health Services",
            "subcategory":"Doctor",
            "type":"Services"
        }
    ],
    "sg:phone":"+1 604 984 4356",
    "sg:postcode":"V7J 3H2",
    "sg:province":"BC",
    "sg:tags":[
        "dentist"
    ],
    "wof:name":"Brody, I DDS",
    "wof:placetype":"venue"
},
  "geometry": {"coordinates":[-123.040817261,49.3354415894],"type":"Point"}
}