{
  "type": "Feature",
  "properties": {
    "iso:country":"CA",
    "sg:address":"221 Herring Cove Rd",
    "sg:city":"Halifax",
    "sg:classifiers":[
        {
            "category":"Arts & Performance",
            "subcategory":"Theater",
            "type":"Entertainment"
        }
    ],
    "sg:phone":"+1 902 479 3200",
    "sg:postcode":"B3P 1L3",
    "sg:province":"NS",
    "sg:tags":[
        "musician",
        "bureau"
    ],
    "wof:name":"Atlantic Federation-Musicians",
    "wof:placetype":"venue"
},
  "geometry": {"coordinates":[-63.6179008484,44.6221885681],"type":"Point"}
}