{
  "type": "Feature",
  "properties": {
    "addr:full":"462 Ch Central Saint-Francois-D'Assise QC G0J 2N0",
    "addr:housenumber":"462",
    "addr:postcode":"g0j 2n0",
    "addr:street":"Ch Central Saint-Francois-D'Assise",
    "iso:country":"CA",
    "sg:address":"462 Ch Central",
    "sg:city":"Saint-Francois-D'Assise",
    "sg:classifiers":[
        {
            "category":"Home & Garden",
            "subcategory":"Hardware",
            "type":"Retail Goods"
        }
    ],
    "sg:phone":"+1 418 299 2744",
    "sg:postcode":"G0J 2N0",
    "sg:province":"QC",
    "sg:tags":[
        "building",
        "material"
    ],
    "wof:name":"Materiaux St-Francois",
    "wof:placetype":"venue"
},
  "geometry": {"coordinates":[-67.166183,47.982582],"type":"Point"}
}