{
  "type": "Feature",
  "properties": {
    "addr:full":"434 Salmo Ski Hill Rd Salmo BC V0G 1Z0",
    "addr:housenumber":"434",
    "addr:postcode":"v0g 1z0",
    "addr:street":"Salmo Ski Hill Rd",
    "iso:country":"CA",
    "sg:address":"434 Salmo Ski Hill Rd",
    "sg:city":"Salmo",
    "sg:classifiers":[
        {
            "category":"Travel",
            "subcategory":"Hotels & Motels",
            "type":"Entertainment"
        }
    ],
    "sg:phone":"+1 250 357 2323",
    "sg:postcode":"V0G 1Z0",
    "sg:province":"BC",
    "sg:tags":[
        "resort"
    ],
    "wof:name":"Salmo Ski Club",
    "wof:placetype":"venue"
},
  "geometry": {"coordinates":[-117.281273,49.180344],"type":"Point"}
}