{
  "type": "Feature",
  "properties": {
    "addr:full":"488 Dominion Ave Midland ON L4R 1P6",
    "addr:housenumber":"488",
    "addr:postcode":"l4r 1p6",
    "addr:street":"Dominion Ave",
    "iso:country":"CA",
    "sg:address":"488 Dominion Ave",
    "sg:city":"Midland",
    "sg:classifiers":[
        {
            "category":"Professional",
            "subcategory":"Lawyer & Legal Services",
            "type":"Services"
        }
    ],
    "sg:phone":"+1 705 527 0007",
    "sg:postcode":"L4R 1P6",
    "sg:province":"ON",
    "sg:tags":[
        "attorney"
    ],
    "wof:name":"Northcott, David",
    "wof:placetype":"venue"
},
  "geometry": {"coordinates":[-79.885086,44.75156],"type":"Point"}
}