{
  "type": "Feature",
  "properties": {
    "addr:full":"34 Rue Eddy Hull QC J8X 2V6",
    "addr:housenumber":"34",
    "addr:postcode":"j8x 2v6",
    "addr:street":"Rue Eddy",
    "iso:country":"CA",
    "sg:address":"34 Rue Eddy",
    "sg:city":"Hull",
    "sg:classifiers":[
        {
            "category":"Taxi",
            "type":"Transportation"
        }
    ],
    "sg:phone":"+1 819 777 1645",
    "sg:postcode":"J8X 2V6",
    "sg:province":"QC",
    "sg:tags":[
        "taxicab"
    ],
    "wof:name":"Crown Taxi",
    "wof:placetype":"venue"
},
  "geometry": {"coordinates":[-75.719666,45.425846],"type":"Point"}
}