{
  "type": "Feature",
  "properties": {
    "iso:country":"CA",
    "sg:address":"3648 Main Rd",
    "sg:city":"Petit DE Grat",
    "sg:classifiers":[
        {
            "category":"Food & Beverages",
            "subcategory":"Groceries & Convenience Stores",
            "type":"Retail Goods"
        }
    ],
    "sg:phone":"+1 902 226 3225",
    "sg:postcode":"B0E 2L0",
    "sg:province":"NS",
    "wof:name":"Corner Bridge Store Ltd",
    "wof:placetype":"venue"
},
  "geometry": {"coordinates":[-60.9570388794,45.5050888062],"type":"Point"}
}