{
  "type": "Feature",
  "properties": {
    "addr:full":"500 Highway 118 W Bracebridge ON P1L 1T4",
    "addr:housenumber":"500",
    "addr:postcode":"p1l 1t4",
    "addr:street":"Highway 118 W",
    "iso:country":"CA",
    "sg:address":"500 Highway 118 W",
    "sg:city":"Bracebridge",
    "sg:classifiers":[
        {
            "category":"Shopping",
            "subcategory":"Crafts & Fabrics",
            "type":"Retail Goods"
        }
    ],
    "sg:phone":"+1 705 645 3361",
    "sg:postcode":"P1L 1T4",
    "sg:province":"ON",
    "sg:tags":[
        "shop"
    ],
    "wof:name":"Fabricland Distributors",
    "wof:placetype":"venue"
},
  "geometry": {"coordinates":[-79.329857,45.043484],"type":"Point"}
}