{
  "type": "Feature",
  "properties": {
    "addr:full":"487 East St N Sarnia ON N7T 6Y7",
    "addr:housenumber":"487",
    "addr:postcode":"n7t 6y7",
    "addr:street":"East St N",
    "iso:country":"CA",
    "sg:address":"487 East St N",
    "sg:city":"Sarnia",
    "sg:classifiers":[
        {
            "category":"Personal",
            "subcategory":"Tanning Parlor",
            "type":"Services"
        }
    ],
    "sg:phone":"+1 519 332 1199",
    "sg:postcode":"N7T 6Y7",
    "sg:province":"ON",
    "sg:tags":[
        "salon"
    ],
    "wof:name":"Sun City Tanning Studios",
    "wof:placetype":"venue"
},
  "geometry": {"coordinates":[-82.3863830566,42.9844207764],"type":"Point"}
}