{
  "type": "Feature",
  "properties": {
    "addr:full":"355 New York Central Ave Embrun ON K0A 1W1",
    "addr:housenumber":"355",
    "addr:postcode":"k0a 1w1",
    "addr:street":"New York Central Ave",
    "iso:country":"CA",
    "sg:address":"355 New York Central Ave",
    "sg:city":"Embrun",
    "sg:classifiers":[
        {
            "category":"Retail",
            "subcategory":"Auto Repair",
            "type":"Services"
        }
    ],
    "sg:phone":"+1 613 443 2350",
    "sg:postcode":"K0A 1W1",
    "sg:province":"ON",
    "sg:tags":[
        "body",
        "automobile",
        "painting"
    ],
    "wof:name":"Embrun Collision",
    "wof:placetype":"venue"
},
  "geometry": {"coordinates":[-75.30497699999999,45.270493],"type":"Point"}
}