{
  "type": "Feature",
  "properties": {
    "addr:full":"Saint-Mathias-Sur-Richelieu QC J3L 6E6",
    "addr:postcode":"j3l 6e6",
    "iso:country":"CA",
    "sg:city":"Saint-Mathias-Sur-Richelieu",
    "sg:classifiers":[
        {
            "category":"Home & Garden",
            "subcategory":"Building Materials",
            "type":"Retail Goods"
        }
    ],
    "sg:phone":"+1 450 658 3787",
    "sg:postcode":"J3L 6E6",
    "sg:province":"QC",
    "sg:tags":[
        "firewood"
    ],
    "wof:name":"Brosseau, Andre",
    "wof:placetype":"venue"
},
  "geometry": {"coordinates":[-73.2528762817,45.5017204285],"type":"Point"}
}