{
  "type": "Feature",
  "properties": {
    "addr:full":"13234 137 Ave NW Edmonton AB T5L 4Z6",
    "addr:housenumber":"13234",
    "addr:postcode":"t5l 4z6",
    "addr:street":"137 Ave Nw",
    "iso:country":"CA",
    "sg:address":"13234 137 Ave NW",
    "sg:city":"Edmonton",
    "sg:classifiers":[
        {
            "category":"Restaurant",
            "type":"Food & Drink"
        }
    ],
    "sg:phone":"+1 780 456 6074",
    "sg:postcode":"T5L 4Z6",
    "sg:province":"AB",
    "wof:name":"Albert's Family Restaurant",
    "wof:placetype":"venue"
},
  "geometry": {"coordinates":[-113.549713,53.599697],"type":"Point"}
}