{
  "type": "Feature",
  "properties": {
    "iso:country":"CA",
    "sg:address":"163 King St",
    "sg:city":"Liverpool",
    "sg:classifiers":[
        {
            "category":"Building & Trades",
            "subcategory":"Construction",
            "type":"Services"
        }
    ],
    "sg:phone":"+1 902 354 5055",
    "sg:postcode":"B0T 1K0",
    "sg:province":"NS",
    "sg:tags":[
        "general",
        "contractor"
    ],
    "wof:name":"C Eugene Ingram Constr Ltd",
    "wof:placetype":"venue"
},
  "geometry": {"coordinates":[-64.73114013670001,44.0355834961],"type":"Point"}
}