{
  "type": "Feature",
  "properties": {
    "addr:full":"2095 Av Madison Montreal QC H4B 2T2",
    "addr:housenumber":"2095",
    "addr:postcode":"h4b 2t2",
    "addr:street":"Av Madison",
    "iso:country":"CA",
    "sg:address":"2095 Av Madison",
    "sg:city":"Montreal",
    "sg:classifiers":[
        {
            "category":"Wholesale",
            "subcategory":"Hardware",
            "type":"Manufacturing & Wholesale Goods"
        }
    ],
    "sg:phone":"+1 514 482 9770",
    "sg:postcode":"H4B 2T2",
    "sg:province":"QC",
    "sg:tags":[
        "equipment",
        "heating",
        "system"
    ],
    "wof:name":"Eclipse Combustion",
    "wof:placetype":"venue"
},
  "geometry": {"coordinates":[-73.6194763184,45.4638214111],"type":"Point"}
}