{
  "type": "Feature",
  "properties": {
    "addr:full":"21211 100 Ave NW Edmonton AB T5T 5X8",
    "addr:housenumber":"21211",
    "addr:postcode":"t5t 5x8",
    "addr:street":"100 Ave Nw",
    "iso:country":"CA",
    "sg:address":"21211 100 Ave NW",
    "sg:city":"Edmonton",
    "sg:classifiers":[
        {
            "category":"Freight",
            "type":"Transportation"
        }
    ],
    "sg:phone":"+1 780 452 2508",
    "sg:postcode":"T5T 5X8",
    "sg:province":"AB",
    "sg:tags":[
        "commercial",
        "storage"
    ],
    "wof:name":"Access Mini Storage",
    "wof:placetype":"venue"
},
  "geometry": {"coordinates":[-113.68425000000001,53.539448],"type":"Point"}
}