{
  "type": "Feature",
  "properties": {
    "addr:full":"317 Main St Mattawa ON P0H 1V0",
    "addr:housenumber":"317",
    "addr:postcode":"p0h 1v0",
    "addr:street":"Main St",
    "iso:country":"CA",
    "sg:address":"317 Main St",
    "sg:city":"Mattawa",
    "sg:classifiers":[
        {
            "category":"Autos & Motor Vehicles",
            "subcategory":"Auto Supplies",
            "type":"Retail Goods"
        }
    ],
    "sg:phone":"+1 705 744 5546",
    "sg:postcode":"P0H 1V0",
    "sg:province":"ON",
    "sg:tags":[
        "automobile",
        "parts"
    ],
    "wof:name":"Car Quest Auto Parts",
    "wof:placetype":"venue"
},
  "geometry": {"coordinates":[-78.705368042,46.3183784485],"type":"Point"}
}