{
  "type": "Feature",
  "properties": {
    "iso:country":"CA",
    "sg:address":"5023 Tiger Moth Lane",
    "sg:city":"Regina",
    "sg:classifiers":[
        {
            "category":"Airport",
            "type":"Transportation"
        }
    ],
    "sg:phone":"+1 306 352 5252",
    "sg:postcode":"S4W 1B4",
    "sg:province":"SK",
    "sg:tags":[
        "rental",
        "aircraft",
        "leasing",
        "charter",
        "maintenance"
    ],
    "wof:name":"Southern Aviation Ltd",
    "wof:placetype":"venue"
},
  "geometry": {"coordinates":[-104.652351379,50.4397010803],"type":"Point"}
}