{
  "type": "Feature",
  "properties": {
    "iso:country":"CA",
    "sg:address":"14464 County Road 2",
    "sg:city":"Brighton",
    "sg:classifiers":[
        {
            "category":"Freight",
            "type":"Transportation"
        }
    ],
    "sg:phone":"+1 613 475 6148",
    "sg:postcode":"K0K 1H0",
    "sg:province":"ON",
    "sg:tags":[
        "mover"
    ],
    "wof:name":"Borchert's Moving Svc",
    "wof:placetype":"venue"
},
  "geometry": {"coordinates":[-77.73780059809999,44.0420188904],"type":"Point"}
}