{
  "type": "Feature",
  "properties": {
    "iso:country":"CA",
    "sg:address":"303 Dunlop St W",
    "sg:city":"Barrie",
    "sg:classifiers":[
        {
            "category":"Retail",
            "subcategory":"Auto Repair",
            "type":"Services"
        }
    ],
    "sg:phone":"+1 705 735 0084",
    "sg:postcode":"L4N 1C1",
    "sg:province":"ON",
    "sg:tags":[
        "van",
        "conversion",
        "truck",
        "accessory"
    ],
    "wof:name":"Action Van & Truck World",
    "wof:placetype":"venue"
},
  "geometry": {"coordinates":[-79.706902,44.381931],"type":"Point"}
}