{
  "type": "Feature",
  "properties": {
    "addr:full":"Kelowna BC V1X 7S1",
    "addr:postcode":"v1x 7s1",
    "iso:country":"CA",
    "sg:city":"Kelowna",
    "sg:classifiers":[
        {
            "category":"Building & Trades",
            "subcategory":"Pest Control",
            "type":"Services"
        }
    ],
    "sg:phone":"+1 250 765 8784",
    "sg:postcode":"V1X 7S1",
    "sg:province":"BC",
    "wof:name":"Okanagan Tree & Lawn Care",
    "wof:placetype":"venue"
},
  "geometry": {"coordinates":[-119.388908386,49.9275016785],"type":"Point"}
}