{
  "type": "Feature",
  "properties": {
    "iso:country":"CA",
    "sg:city":"Burnaby",
    "sg:classifiers":[
        {
            "category":"Restaurant",
            "type":"Food & Drink"
        }
    ],
    "sg:phone":"+1 604 294 1919",
    "sg:postcode":"V5G 4E1",
    "sg:province":"BC",
    "wof:name":"Ace Cafe",
    "wof:placetype":"venue"
},
  "geometry": {"coordinates":[-122.97032165500001,49.244178772],"type":"Point"}
}