{
  "type": "Feature",
  "properties": {
    "addr:full":"8208 Bayview Ave Thornhill ON L3T 2S2",
    "addr:housenumber":"8208",
    "addr:postcode":"l3t 2s2",
    "addr:street":"Bayview Ave",
    "iso:country":"CA",
    "sg:address":"8208 Bayview Ave",
    "sg:city":"Thornhill",
    "sg:classifiers":[
        {
            "category":"Personal",
            "subcategory":"Beauty Salon",
            "type":"Services"
        }
    ],
    "sg:phone":"+1 905 881 2781",
    "sg:postcode":"L3T 2S2",
    "sg:province":"ON",
    "wof:name":"L'Equipe 21",
    "wof:placetype":"venue"
},
  "geometry": {"coordinates":[-79.4046325684,43.8318786621],"type":"Point"}
}