{
  "type": "Feature",
  "properties": {
    "addr:full":"500 1st Ave NW Moose Jaw SK S6H 3M5",
    "addr:housenumber":"500",
    "addr:postcode":"s6h 3m5",
    "addr:street":"1St Ave Nw",
    "iso:country":"CA",
    "sg:address":"500 1st Ave NW",
    "sg:city":"Moose Jaw",
    "sg:classifiers":[
        {
            "category":"Restaurant",
            "type":"Food & Drink"
        }
    ],
    "sg:phone":"+1 306 692 2351",
    "sg:postcode":"S6H 3M5",
    "sg:province":"SK",
    "sg:tags":[
        "mall",
        "shopping",
        "center",
        "caterer"
    ],
    "wof:name":"Moose Jaw CO-OP Assn Ltd",
    "wof:placetype":"venue"
},
  "geometry": {"coordinates":[-105.537491,50.394508],"type":"Point"}
}