{
  "type": "Feature",
  "properties": {
    "addr:full":"7220 76 Ave NW Edmonton AB T6B 0B2",
    "addr:housenumber":"7220",
    "addr:postcode":"t6b 0b2",
    "addr:street":"76 Ave Nw",
    "iso:country":"CA",
    "sg:address":"7220 76 Ave NW",
    "sg:city":"Edmonton",
    "sg:classifiers":[
        {
            "category":"Retail",
            "subcategory":"Auto Repair",
            "type":"Services"
        }
    ],
    "sg:phone":"+1 780 465 2783",
    "sg:postcode":"T6B 0B2",
    "sg:province":"AB",
    "sg:tags":[
        "repairing",
        "automobile"
    ],
    "wof:name":"Bruce Stewart Auto Repair Ctr",
    "wof:placetype":"venue"
},
  "geometry": {"coordinates":[-113.438850403,53.5125274658],"type":"Point"}
}