{
  "type": "Feature",
  "properties": {
    "addr:full":"851 Westminster Ave W Penticton BC V2A 1L1",
    "addr:housenumber":"851",
    "addr:postcode":"v2a 1l1",
    "addr:street":"Westminster Ave W",
    "iso:country":"CA",
    "sg:address":"851 Westminster Ave W",
    "sg:city":"Penticton",
    "sg:classifiers":[
        {
            "category":"Personal",
            "subcategory":"Beauty Salon",
            "type":"Services"
        }
    ],
    "sg:phone":"+1 250 770 1041",
    "sg:postcode":"V2A 1L1",
    "sg:province":"BC",
    "wof:name":"Generation Hair Care By Teresa",
    "wof:placetype":"venue"
},
  "geometry": {"coordinates":[-119.606628,49.49754],"type":"Point"}
}