{
  "type": "Feature",
  "properties": {
    "addr:full":"17 Ashwood Crt Stoney Creek ON L8E 3C9",
    "addr:housenumber":"17",
    "addr:postcode":"l8e 3c9",
    "addr:street":"Ashwood Crt",
    "iso:country":"CA",
    "sg:address":"17 Ashwood Crt",
    "sg:city":"Stoney Creek",
    "sg:classifiers":[
        {
            "category":"Building & Trades",
            "subcategory":"Cleaning & Sanitation",
            "type":"Services"
        }
    ],
    "sg:phone":"+1 905 664 6333",
    "sg:postcode":"L8E 3C9",
    "sg:province":"ON",
    "sg:tags":[
        "janitor"
    ],
    "wof:name":"Aldo Bracco Janitorial Svc",
    "wof:placetype":"venue"
},
  "geometry": {"coordinates":[-79.7324371338,43.2298126221],"type":"Point"}
}