{
  "type": "Feature",
  "properties": {
    "addr:full":"4701 Boul Bourque Rock Forest QC J1N 2G6",
    "addr:housenumber":"4701",
    "addr:postcode":"j1n 2g6",
    "addr:street":"Boul Bourque",
    "iso:country":"CA",
    "sg:address":"4701 Boul Bourque",
    "sg:city":"Rock Forest",
    "sg:classifiers":[
        {
            "category":"Home & Garden",
            "subcategory":"Hardware",
            "type":"Retail Goods"
        }
    ],
    "sg:phone":"+1 819 564 2257",
    "sg:postcode":"J1N 2G6",
    "sg:province":"QC",
    "wof:name":"Centre DE Renovation Gaudette",
    "wof:placetype":"venue"
},
  "geometry": {"coordinates":[-71.9829483032,45.37449646],"type":"Point"}
}