{
  "type": "Feature",
  "properties": {
    "addr:full":"1474 Fairburn St Sudbury ON P3A 1N7",
    "addr:housenumber":"1474",
    "addr:postcode":"p3a 1n7",
    "addr:street":"Fairburn St",
    "iso:country":"CA",
    "sg:address":"1474 Fairburn St",
    "sg:city":"Sudbury",
    "sg:classifiers":[
        {
            "category":"Wholesale",
            "subcategory":"Machinery & Supplies",
            "type":"Manufacturing & Wholesale Goods"
        }
    ],
    "sg:phone":"+1 705 688 2106",
    "sg:postcode":"P3A 1N7",
    "sg:province":"ON",
    "sg:tags":[
        "equipment",
        "material",
        "handling",
        "contractor"
    ],
    "wof:name":"Renfor Lift Truck Sales & Rntl",
    "wof:placetype":"venue"
},
  "geometry": {"coordinates":[-80.9424743652,46.5175056458],"type":"Point"}
}