{
  "type": "Feature",
  "properties": {
    "iso:country":"CA",
    "sg:address":"80 King St E",
    "sg:city":"Harrow",
    "sg:classifiers":[
        {
            "category":"Food & Beverages",
            "subcategory":"Groceries & Convenience Stores",
            "type":"Retail Goods"
        }
    ],
    "sg:phone":"+1 519 738 2342",
    "sg:postcode":"N0R 1G0",
    "sg:province":"ON",
    "wof:name":"Stop N Go",
    "wof:placetype":"venue"
},
  "geometry": {"coordinates":[-82.9160232544,42.0355873108],"type":"Point"}
}