{
  "type": "Feature",
  "properties": {
    "addr:full":"337 16 St N Lethbridge AB T1H 3A2",
    "addr:housenumber":"16",
    "addr:postcode":"t1h 3a2",
    "addr:street":"337;St N",
    "iso:country":"CA",
    "sg:address":"337 16 St N",
    "sg:city":"Lethbridge",
    "sg:classifiers":[
        {
            "category":"Building & Trades",
            "subcategory":"Construction",
            "type":"Services"
        }
    ],
    "sg:phone":"+1 403 328 6904",
    "sg:postcode":"T1H 3A2",
    "sg:province":"AB",
    "sg:tags":[
        "roofing",
        "contractor"
    ],
    "wof:name":"Kolk's Roofing",
    "wof:placetype":"venue"
},
  "geometry": {"coordinates":[-112.819717407,49.7036437988],"type":"Point"}
}