{
  "type": "Feature",
  "properties": {
    "addr:full":"Taloyoak NU X0B 1B0",
    "addr:postcode":"x0b 1b0",
    "iso:country":"CA",
    "sg:city":"Taloyoak",
    "sg:classifiers":[
        {
            "category":"Government",
            "subcategory":"Office",
            "type":"Public Place"
        }
    ],
    "sg:phone":"+1 867 561 6111",
    "sg:postcode":"X0B 1B0",
    "sg:province":"NU",
    "sg:tags":[
        "village"
    ],
    "wof:name":"Taloyoak Director of Mntnce",
    "wof:placetype":"venue"
},
  "geometry": {"coordinates":[-93.53401947019999,69.5377120972],"type":"Point"}
}