{
  "type": "Feature",
  "properties": {
    "addr:full":"Prescott ON K0E 1T0",
    "addr:postcode":"k0e 1t0",
    "iso:country":"CA",
    "sg:city":"Prescott",
    "sg:classifiers":[
        {
            "category":"Recreation",
            "type":"Entertainment"
        }
    ],
    "sg:phone":"+1 613 925 2896",
    "sg:postcode":"K0E 1T0",
    "sg:province":"ON",
    "sg:tags":[
        "historical",
        "government"
    ],
    "wof:name":"Fort Wellington National",
    "wof:placetype":"venue"
},
  "geometry": {"coordinates":[-75.508415,44.712162],"type":"Point"}
}