{
  "type": "Feature",
  "properties": {
    "addr:full":"1771 Cuba Ave Ottawa ON K1G 1L7",
    "addr:housenumber":"1771",
    "addr:postcode":"k1g 1l7",
    "addr:street":"Cuba Ave",
    "iso:country":"CA",
    "sg:address":"1771 Cuba Ave",
    "sg:city":"Ottawa",
    "sg:classifiers":[
        {
            "category":"Organizations",
            "subcategory":"Religious Organization",
            "type":"Services"
        }
    ],
    "sg:phone":"+1 613 526 9192",
    "sg:postcode":"K1G 1L7",
    "sg:province":"ON",
    "sg:tags":[
        "synagogue"
    ],
    "wof:name":"Ottawa Chevra Kadisha",
    "wof:placetype":"venue"
},
  "geometry": {"coordinates":[-75.628868,45.40131],"type":"Point"}
}