{
  "type": "Feature",
  "properties": {
    "addr:full":"905 Brookfield Pl Nanaimo BC V9R 6P4",
    "addr:housenumber":"905",
    "addr:postcode":"v9r 6p4",
    "addr:street":"Brookfield Pl",
    "iso:country":"CA",
    "sg:address":"905 Brookfield Pl",
    "sg:city":"Nanaimo",
    "sg:classifiers":[
        {
            "category":"Professional",
            "subcategory":"Business Services",
            "type":"Services"
        }
    ],
    "sg:phone":"+1 250 754 8942",
    "sg:postcode":"V9R 6P4",
    "sg:province":"BC",
    "sg:tags":[
        "inspection"
    ],
    "wof:name":"Barker Building & Consulting",
    "wof:placetype":"venue"
},
  "geometry": {"coordinates":[-123.963684082,49.1438446045],"type":"Point"}
}