{
  "type": "Feature",
  "properties": {
    "addr:full":"360 Rue Argyll Sherbrooke QC J1J 3H6",
    "addr:housenumber":"360",
    "addr:postcode":"j1j 3h6",
    "addr:street":"Rue Argyll",
    "iso:country":"CA",
    "sg:address":"360 Rue Argyll",
    "sg:city":"Sherbrooke",
    "sg:classifiers":[
        {
            "category":"Education",
            "subcategory":"School",
            "type":"Public Place"
        }
    ],
    "sg:phone":"+1 819 822 2663",
    "sg:postcode":"J1J 3H6",
    "sg:province":"QC",
    "sg:tags":[
        "academic",
        "special"
    ],
    "wof:name":"Centre Effi",
    "wof:placetype":"venue"
},
  "geometry": {"coordinates":[-71.913094,45.403969],"type":"Point"}
}