{
  "type": "Feature",
  "properties": {
    "addr:full":"Calgary AB T2E 7E1",
    "addr:postcode":"t2e 7e1",
    "iso:country":"CA",
    "sg:city":"Calgary",
    "sg:classifiers":[
        {
            "category":"Home & Garden",
            "subcategory":"Carpets & Floor Coverings",
            "type":"Retail Goods"
        }
    ],
    "sg:phone":"+1 403 292 9400",
    "sg:postcode":"T2E 7E1",
    "sg:province":"AB",
    "sg:tags":[
        "dealer",
        "rug"
    ],
    "wof:name":"Simco Furnishings & Carpet",
    "wof:placetype":"venue"
},
  "geometry": {"coordinates":[-114.016464,51.076767],"type":"Point"}
}