{
  "type": "Feature",
  "properties": {
    "addr:full":"Winnipeg MB R3C 4M6",
    "addr:postcode":"r3c 4m6",
    "iso:country":"CA",
    "sg:city":"Winnipeg",
    "sg:classifiers":[
        {
            "category":"Organizations",
            "subcategory":"Labor Organization",
            "type":"Services"
        }
    ],
    "sg:phone":"+1 204 947 1400",
    "sg:postcode":"R3C 4M6",
    "sg:province":"MB",
    "wof:name":"Manitoba Federation of Labour",
    "wof:placetype":"venue"
},
  "geometry": {"coordinates":[-97.13858,49.888241],"type":"Point"}
}