{
  "type": "Feature",
  "properties": {
    "addr:full":"5641 Duncan Bay Rd Campbell River BC V9H 1N6",
    "addr:housenumber":"5641",
    "addr:postcode":"v9h 1n6",
    "addr:street":"Duncan Bay Rd",
    "iso:country":"CA",
    "sg:address":"5641 Duncan Bay Rd",
    "sg:city":"Campbell River",
    "sg:classifiers":[
        {
            "category":"Freight",
            "type":"Transportation"
        }
    ],
    "sg:phone":"+1 250 287 4699",
    "sg:postcode":"V9H 1N6",
    "sg:province":"BC",
    "sg:tags":[
        "booming",
        "log"
    ],
    "wof:name":"Heatley Boom Svc",
    "wof:placetype":"venue"
},
  "geometry": {"coordinates":[-125.31391143800001,50.0802192688],"type":"Point"}
}