{
  "type": "Feature",
  "properties": {
    "addr:full":"1980 Yonge St Toronto ON M4S 1Z7",
    "addr:housenumber":"1980",
    "addr:postcode":"m4s 1z7",
    "addr:street":"Yonge St",
    "iso:country":"CA",
    "sg:address":"1980 Yonge St",
    "sg:city":"Toronto",
    "sg:classifiers":[
        {
            "category":"Retail",
            "subcategory":"Repair Shop",
            "type":"Services"
        }
    ],
    "sg:phone":"+1 416 487 5626",
    "sg:postcode":"M4S 1Z7",
    "sg:province":"ON",
    "sg:tags":[
        "lamp",
        "lighting"
    ],
    "wof:name":"Dell'Ernia Lamp Ltd",
    "wof:placetype":"venue"
},
  "geometry": {"coordinates":[-79.3971481323,43.6999816895],"type":"Point"}
}