{
  "type": "Feature",
  "properties": {
    "iso:country":"CA",
    "sg:address":"4404 Legion Ave",
    "sg:city":"Terrace",
    "sg:classifiers":[
        {
            "category":"Retail",
            "subcategory":"Laundry & Dry Cleaning",
            "type":"Services"
        }
    ],
    "sg:phone":"+1 250 635 2838",
    "sg:postcode":"V8G 1N6",
    "sg:province":"BC",
    "sg:tags":[
        "cleaners"
    ],
    "wof:name":"Superior Linen Supply",
    "wof:placetype":"venue"
},
  "geometry": {"coordinates":[-128.57638549800001,54.5158691406],"type":"Point"}
}