{
  "type": "Feature",
  "properties": {
    "addr:full":"13158 Tecumseh Rd E Windsor ON N8N 3T6",
    "addr:housenumber":"13158",
    "addr:postcode":"n8n 3t6",
    "addr:street":"Tecumseh Rd E",
    "iso:country":"CA",
    "sg:address":"13158 Tecumseh Rd E",
    "sg:city":"Windsor",
    "sg:classifiers":[
        {
            "category":"Manufacturing",
            "subcategory":"Retail Goods",
            "type":"Manufacturing & Wholesale Goods"
        }
    ],
    "sg:phone":"+1 519 979 5069",
    "sg:postcode":"N8N 3T6",
    "sg:province":"ON",
    "sg:tags":[
        "assembly",
        "fabricating"
    ],
    "wof:name":"Totem Pole Assembly Group",
    "wof:placetype":"venue"
},
  "geometry": {"coordinates":[-82.90093231199999,42.3124809265],"type":"Point"}
}