{
  "type": "Feature",
  "properties": {
    "addr:full":"5214 46th St Elk Point AB T0A 1A0",
    "addr:housenumber":"5214",
    "addr:postcode":"t0a 1a0",
    "addr:street":"46Th St",
    "iso:country":"CA",
    "sg:address":"5214 46th St",
    "sg:city":"Elk Point",
    "sg:classifiers":[
        {
            "category":"Professional",
            "subcategory":"Business Services",
            "type":"Services"
        }
    ],
    "sg:phone":"+1 780 724 2625",
    "sg:postcode":"T0A 1A0",
    "sg:province":"AB",
    "sg:tags":[
        "field",
        "oil"
    ],
    "wof:name":"Rocky Pine Oilfield Svc Ltd",
    "wof:placetype":"venue"
},
  "geometry": {"coordinates":[-110.893005,53.899376],"type":"Point"}
}