{
  "type": "Feature",
  "properties": {
    "addr:full":"Laval QC H7T 2P5",
    "addr:postcode":"h7t 2p5",
    "iso:country":"CA",
    "sg:city":"Laval",
    "sg:classifiers":[
        {
            "category":"Health Services",
            "subcategory":"Optometrist",
            "type":"Services"
        }
    ],
    "sg:phone":"+1 450 688 6574",
    "sg:postcode":"H7T 2P5",
    "sg:province":"QC",
    "sg:tags":[
        "ophthalmologist"
    ],
    "wof:name":"Iris Clinique D'Ophtalmologie",
    "wof:placetype":"venue"
},
  "geometry": {"coordinates":[-73.74919128419999,45.5685043335],"type":"Point"}
}