{
  "type": "Feature",
  "properties": {
    "iso:country":"CA",
    "sg:address":"174 Humewood Dr",
    "sg:city":"York",
    "sg:classifiers":[
        {
            "category":"Building & Trades",
            "subcategory":"Construction",
            "type":"Services"
        }
    ],
    "sg:phone":"+1 416 587 6679",
    "sg:postcode":"M6C 2W8",
    "sg:province":"ON",
    "sg:tags":[
        "home",
        "improvement"
    ],
    "wof:name":"Homecare Professionals",
    "wof:placetype":"venue"
},
  "geometry": {"coordinates":[-79.4282531738,43.6881904602],"type":"Point"}
}