{
  "type": "Feature",
  "properties": {
    "addr:full":"1128 Hastings St W # P1 Vancouver BC V6E 4R5",
    "addr:housenumber":"1128",
    "addr:postcode":"v6e 4r5",
    "addr:street":"Hastings St W # P1",
    "iso:country":"CA",
    "sg:address":"1128 Hastings St W # P1",
    "sg:city":"Vancouver",
    "sg:classifiers":[
        {
            "category":"Retail",
            "subcategory":"Car Wash",
            "type":"Services"
        }
    ],
    "sg:phone":"+1 604 689 9274",
    "sg:postcode":"V6E 4R5",
    "sg:province":"BC",
    "sg:tags":[
        "polishing",
        "washing"
    ],
    "wof:name":"Classic Car Wash",
    "wof:placetype":"venue"
},
  "geometry": {"coordinates":[-123.120789,49.288109],"type":"Point"}
}