{
  "type": "Feature",
  "properties": {
    "addr:full":"564 Bond St Watford ON N0M 2S0",
    "addr:housenumber":"564",
    "addr:postcode":"n0m 2s0",
    "addr:street":"Bond St",
    "iso:country":"CA",
    "sg:address":"564 Bond St",
    "sg:city":"Watford",
    "sg:classifiers":[
        {
            "category":"Wholesale",
            "subcategory":"Machinery & Supplies",
            "type":"Manufacturing & Wholesale Goods"
        }
    ],
    "sg:phone":"+1 519 876 2420",
    "sg:postcode":"N0M 2S0",
    "sg:province":"ON",
    "sg:tags":[
        "farm",
        "equipment"
    ],
    "wof:name":"Wilcocks Brothers of Watford",
    "wof:placetype":"venue"
},
  "geometry": {"coordinates":[-81.8779754639,42.9436798096],"type":"Point"}
}