{
  "type": "Feature",
  "properties": {
    "addr:full":"101 Kensington Rd Charlottetown PE C1A 5J3",
    "addr:housenumber":"101",
    "addr:postcode":"c1a 5j3",
    "addr:street":"Kensington Rd",
    "iso:country":"CA",
    "sg:address":"101 Kensington Rd",
    "sg:city":"Charlottetown",
    "sg:classifiers":[
        {
            "category":"Shopping",
            "subcategory":"Clothing, Apparel, & Fashions",
            "type":"Retail Goods"
        }
    ],
    "sg:phone":"+1 902 894 4544",
    "sg:postcode":"C1A 5J3",
    "sg:province":"PE",
    "sg:tags":[
        "shop",
        "bridal"
    ],
    "wof:name":"Wedding Place",
    "wof:placetype":"venue"
},
  "geometry": {"coordinates":[-63.116238,46.251793],"type":"Point"}
}