{
  "type": "Feature",
  "properties": {
    "iso:country":"CA",
    "sg:address":"90 Raddall Ave",
    "sg:city":"Dartmouth",
    "sg:classifiers":[
        {
            "category":"Wholesale",
            "subcategory":"Electrical",
            "type":"Manufacturing & Wholesale Goods"
        }
    ],
    "sg:phone":"+1 902 468 9782",
    "sg:postcode":"B3B 1T2",
    "sg:province":"NS",
    "sg:tags":[
        "control",
        "security",
        "system"
    ],
    "wof:name":"Adi",
    "wof:placetype":"venue"
},
  "geometry": {"coordinates":[-63.5893630981,44.7035140991],"type":"Point"}
}