{
  "type": "Feature",
  "properties": {
    "addr:full":"10535 65 St NW Edmonton AB T6A 3X7",
    "addr:housenumber":"10535",
    "addr:postcode":"t6a 3x7",
    "addr:street":"65 St Nw",
    "iso:country":"CA",
    "sg:address":"10535 65 St NW",
    "sg:city":"Edmonton",
    "sg:classifiers":[
        {
            "category":"Recreation",
            "type":"Entertainment"
        }
    ],
    "sg:phone":"+1 780 496 1493",
    "sg:postcode":"T6A 3X7",
    "sg:province":"AB",
    "sg:tags":[
        "pool",
        "swimming"
    ],
    "wof:name":"Hardisty Fitness & Leisure Ctr",
    "wof:placetype":"venue"
},
  "geometry": {"coordinates":[-113.431213379,53.5491790771],"type":"Point"}
}