{
  "type": "Feature",
  "properties": {
    "iso:country":"CA",
    "sg:city":"Repentigny",
    "sg:classifiers":[
        {
            "category":"Bars & Pubs",
            "type":"Food & Drink"
        }
    ],
    "sg:phone":"+1 450 654 5791",
    "sg:postcode":"J5Y 1E1",
    "sg:province":"QC",
    "sg:tags":[
        "lounge",
        "cocktail"
    ],
    "wof:name":"Bar Salon Leclerc Enr",
    "wof:placetype":"venue"
},
  "geometry": {"coordinates":[-73.4111022949,45.7749176025],"type":"Point"}
}