{
  "type": "Feature",
  "properties": {
    "addr:full":"235 Principale #B Saint-Dominique-Du-Rosaire QC J0Y 2K0",
    "addr:housenumber":"235;# b",
    "addr:postcode":"j0y 2k0",
    "addr:street":"Principale;Saint-Dominique-Du-Rosaire",
    "iso:country":"CA",
    "sg:address":"235 Principale #B",
    "sg:city":"Saint-Dominique-Du-Rosaire",
    "sg:classifiers":[
        {
            "category":"Government",
            "subcategory":"Office",
            "type":"Public Place"
        }
    ],
    "sg:phone":"+1 819 727 9544",
    "sg:postcode":"J0Y 2K0",
    "sg:province":"QC",
    "sg:tags":[
        "library",
        "village"
    ],
    "wof:name":"St Dominique Du Rosaire Biblio",
    "wof:placetype":"venue"
},
  "geometry": {"coordinates":[-78.114296,48.767757],"type":"Point"}
}