{
  "type": "Feature",
  "properties": {
    "addr:full":"Pohenegamook QC G0L 1J0",
    "addr:postcode":"g0l 1j0",
    "iso:country":"CA",
    "sg:city":"Pohenegamook",
    "sg:classifiers":[
        {
            "category":"Building & Trades",
            "subcategory":"Electrical",
            "type":"Services"
        }
    ],
    "sg:phone":"+1 418 893 5528",
    "sg:postcode":"G0L 1J0",
    "sg:province":"QC",
    "sg:tags":[
        "electric",
        "contractor"
    ],
    "wof:name":"Asselin Raynald Inc",
    "wof:placetype":"venue"
},
  "geometry": {"coordinates":[-69.1496582031,47.4572677612],"type":"Point"}
}