{
  "type": "Feature",
  "properties": {
    "addr:full":"15 St Anne's Rd Winnipeg MB R2M 2Y1",
    "addr:housenumber":"15",
    "addr:postcode":"r2m 2y1",
    "addr:street":"St Anne'S Rd",
    "iso:country":"CA",
    "sg:address":"15 St Anne's Rd",
    "sg:city":"Winnipeg",
    "sg:classifiers":[
        {
            "category":"Building & Trades",
            "subcategory":"Cleaning & Sanitation",
            "type":"Services"
        }
    ],
    "sg:phone":"+1 204 949 1623",
    "sg:postcode":"R2M 2Y1",
    "sg:province":"MB",
    "sg:tags":[
        "cleaners",
        "janitor",
        "rug",
        "carpet"
    ],
    "wof:name":"Dominion Carpet Cleaning Ltd",
    "wof:placetype":"venue"
},
  "geometry": {"coordinates":[-97.1101303101,49.8637504578],"type":"Point"}
}