{
  "type": "Feature",
  "properties": {
    "addr:full":"Palmer Rapids ON K0J 2E0",
    "addr:postcode":"k0j 2e0",
    "iso:country":"CA",
    "sg:city":"Palmer Rapids",
    "sg:classifiers":[
        {
            "category":"Recreation",
            "type":"Entertainment"
        }
    ],
    "sg:phone":"+1 613 758 1034",
    "sg:postcode":"K0J 2E0",
    "sg:province":"ON",
    "sg:tags":[
        "center"
    ],
    "wof:name":"Quadeville Community Ctr",
    "wof:placetype":"venue"
},
  "geometry": {"coordinates":[-77.51857,45.330311],"type":"Point"}
}