{
  "type": "Feature",
  "properties": {
    "addr:full":"270 Boul Charest E Quebec QC G1K 3H1",
    "addr:housenumber":"270",
    "addr:postcode":"g1k 3h1",
    "addr:street":"Boul Charest E",
    "iso:country":"CA",
    "sg:address":"270 Boul Charest E",
    "sg:city":"Quebec",
    "sg:classifiers":[
        {
            "category":"Education",
            "subcategory":"College",
            "type":"Public Place"
        }
    ],
    "sg:phone":"+1 418 529 1321",
    "sg:postcode":"G1K 3H1",
    "sg:province":"QC",
    "sg:tags":[
        "academic",
        "school"
    ],
    "wof:name":"Aviron Quebec Institut Tech",
    "wof:placetype":"venue"
},
  "geometry": {"coordinates":[-71.2265472412,46.8128700256],"type":"Point"}
}