{
  "type": "Feature",
  "properties": {
    "addr:full":"Montreal QC H3A 2R7",
    "addr:postcode":"h3a 2r7",
    "iso:country":"CA",
    "sg:city":"Montreal",
    "sg:classifiers":[
        {
            "category":"Education",
            "subcategory":"College",
            "type":"Public Place"
        }
    ],
    "sg:phone":"+1 514 985 7025",
    "sg:postcode":"H3A 2R7",
    "sg:province":"QC",
    "sg:tags":[
        "academic",
        "mutual",
        "funds"
    ],
    "wof:name":"Institut Des Fonds D'Invstsmnt",
    "wof:placetype":"venue"
},
  "geometry": {"coordinates":[-73.56554412840001,45.5208816528],"type":"Point"}
}