{
  "type": "Feature",
  "properties": {
    "addr:full":"52407 Range Road 222 Ardrossan AB T8E 2G6",
    "addr:housenumber":"52407",
    "addr:postcode":"t8e 2g6",
    "addr:street":"Range Road 222",
    "iso:country":"CA",
    "sg:address":"52407 Range Road 222",
    "sg:city":"Ardrossan",
    "sg:classifiers":[
        {
            "category":"Building & Trades",
            "subcategory":"Equipment Rental",
            "type":"Services"
        }
    ],
    "sg:phone":"+1 780 922 6534",
    "sg:postcode":"T8E 2G6",
    "sg:province":"AB",
    "sg:tags":[
        "yard"
    ],
    "wof:name":"Triple Two Rentals",
    "wof:placetype":"venue"
},
  "geometry": {"coordinates":[-113.147789,53.541389],"type":"Point"}
}