{
  "type": "Feature",
  "properties": {
    "addr:full":"691 Lasalle Blvd Sudbury ON P3A 1X3",
    "addr:housenumber":"691",
    "addr:postcode":"p3a 1x3",
    "addr:street":"Lasalle Blvd",
    "iso:country":"CA",
    "sg:address":"691 Lasalle Blvd",
    "sg:city":"Sudbury",
    "sg:classifiers":[
        {
            "category":"Education",
            "subcategory":"School",
            "type":"Public Place"
        }
    ],
    "sg:phone":"+1 705 566 8300",
    "sg:postcode":"P3A 1X3",
    "sg:province":"ON",
    "wof:name":"Felix Ricard Ecole",
    "wof:placetype":"venue"
},
  "geometry": {"coordinates":[-80.968597,46.522018],"type":"Point"}
}