{
  "type": "Feature",
  "properties": {
    "addr:full":"Montreal QC H1Y 1G7",
    "addr:postcode":"h1y 1g7",
    "iso:country":"CA",
    "sg:city":"Montreal",
    "sg:classifiers":[
        {
            "category":"Health Services",
            "subcategory":"Doctor",
            "type":"Services"
        }
    ],
    "sg:phone":"+1 514 722 3807",
    "sg:postcode":"H1Y 1G7",
    "sg:province":"QC",
    "sg:tags":[
        "physician",
        "surgeon"
    ],
    "wof:name":"Rochon, Jean MD",
    "wof:placetype":"venue"
},
  "geometry": {"coordinates":[-73.5895767212,45.551071167],"type":"Point"}
}