{
  "type": "Feature",
  "properties": {
    "addr:full":"1836 Brilliant Rd Castlegar BC V1N 4K2",
    "addr:housenumber":"1836",
    "addr:postcode":"v1n 4k2",
    "addr:street":"Brilliant Rd",
    "iso:country":"CA",
    "sg:address":"1836 Brilliant Rd",
    "sg:city":"Castlegar",
    "sg:classifiers":[
        {
            "category":"Building & Trades",
            "subcategory":"Construction",
            "type":"Services"
        }
    ],
    "sg:phone":"+1 250 365 3771",
    "sg:postcode":"V1N 4K2",
    "sg:province":"BC",
    "sg:tags":[
        "general",
        "contractor"
    ],
    "wof:name":"William Berg Construction Ltd",
    "wof:placetype":"venue"
},
  "geometry": {"coordinates":[-117.65418243400001,49.2962532043],"type":"Point"}
}