{
  "type": "Feature",
  "properties": {
    "addr:full":"11 Des Loisirs Ragueneau QC G0H 1S0",
    "addr:housenumber":"11",
    "addr:postcode":"g0h 1s0",
    "addr:street":"Des Loisirs",
    "iso:country":"CA",
    "sg:address":"11 Des Loisirs",
    "sg:city":"Ragueneau",
    "sg:classifiers":[
        {
            "category":"Education",
            "subcategory":"Library",
            "type":"Public Place"
        }
    ],
    "sg:phone":"+1 418 567 8453",
    "sg:postcode":"G0H 1S0",
    "sg:province":"QC",
    "wof:name":"Ragueneau Bibliotheque",
    "wof:placetype":"venue"
},
  "geometry": {"coordinates":[-68.46270800000001,49.076279],"type":"Point"}
}