{
  "type": "Feature",
  "properties": {
    "addr:full":"171 Rue DE L'Ermitage Laval QC H7W 4X8",
    "addr:housenumber":"171",
    "addr:postcode":"h7w 4x8",
    "addr:street":"Rue De L'Ermitage",
    "iso:country":"CA",
    "sg:address":"171 Rue DE L'Ermitage",
    "sg:city":"Laval",
    "sg:classifiers":[
        {
            "category":"Professional",
            "subcategory":"Accounting & Tax Preparation",
            "type":"Services"
        }
    ],
    "sg:phone":"+1 450 682 5106",
    "sg:postcode":"H7W 4X8",
    "sg:province":"QC",
    "sg:tags":[
        "accountant",
        "bookkeeping",
        "system"
    ],
    "wof:name":"Entreprises Saga",
    "wof:placetype":"venue"
},
  "geometry": {"coordinates":[-73.75616455079999,45.5275878906],"type":"Point"}
}