{
  "type": "Feature",
  "properties": {
    "addr:full":"Charlesbourg QC G2N 1L2",
    "addr:postcode":"g2n 1l2",
    "iso:country":"CA",
    "sg:city":"Charlesbourg",
    "sg:classifiers":[
        {
            "category":"Retail",
            "subcategory":"Auto Repair",
            "type":"Services"
        }
    ],
    "sg:phone":"+1 418 849 2175",
    "sg:postcode":"G2N 1L2",
    "sg:province":"QC",
    "sg:tags":[
        "machine",
        "automobile",
        "shop"
    ],
    "wof:name":"Garage Marcel Beaulieu Jr",
    "wof:placetype":"venue"
},
  "geometry": {"coordinates":[-71.311722,46.896751],"type":"Point"}
}