{
  "type": "Feature",
  "properties": {
    "addr:full":"Field ON P0H 1M0",
    "addr:postcode":"p0h 1m0",
    "iso:country":"CA",
    "sg:city":"Field",
    "sg:classifiers":[
        {
            "category":"Education",
            "subcategory":"Library",
            "type":"Public Place"
        }
    ],
    "sg:phone":"+1 705 758 6610",
    "sg:postcode":"P0H 1M0",
    "sg:province":"ON",
    "wof:name":"Bibliotheque Publique",
    "wof:placetype":"venue"
},
  "geometry": {"coordinates":[-79.96318100000001,46.523144],"type":"Point"}
}