{
  "type": "Feature",
  "properties": {
    "iso:country":"CA",
    "sg:address":"295 Rue Montfort",
    "sg:city":"Saint-Romuald",
    "sg:classifiers":[
        {
            "category":"Real Estate",
            "subcategory":"Real Estate Agent",
            "type":"Services"
        }
    ],
    "sg:phone":"+1 418 834 1012",
    "sg:postcode":"G6W 3L8",
    "sg:province":"QC",
    "wof:name":"Imafa Inc",
    "wof:placetype":"venue"
},
  "geometry": {"coordinates":[-71.238922,46.752731],"type":"Point"}
}