{
  "type": "Feature",
  "properties": {
    "addr:full":"17 Springfield Rd Ottawa ON K1M 1C8",
    "addr:housenumber":"17",
    "addr:postcode":"k1m 1c8",
    "addr:street":"Springfield Rd",
    "iso:country":"CA",
    "sg:address":"17 Springfield Rd",
    "sg:city":"Ottawa",
    "sg:classifiers":[
        {
            "category":"Shopping",
            "subcategory":"Clothing, Apparel, & Fashions",
            "type":"Retail Goods"
        }
    ],
    "sg:phone":"+1 613 749 8383",
    "sg:postcode":"K1M 1C8",
    "sg:province":"ON",
    "sg:tags":[
        "tailor"
    ],
    "wof:name":"Leo LA Vecchia Tailor",
    "wof:placetype":"venue"
},
  "geometry": {"coordinates":[-75.6763381958,45.4403190613],"type":"Point"}
}