{
  "type": "Feature",
  "properties": {
    "addr:full":"87 Ave & 112 St Edmonton AB T6G 2C9",
    "addr:postcode":"t6g 2c9",
    "addr:street":"87 Ave & 112 St",
    "iso:country":"CA",
    "sg:address":"87 Ave & 112 St",
    "sg:city":"Edmonton",
    "sg:classifiers":[
        {
            "category":"Arts & Performance",
            "subcategory":"Theater",
            "type":"Entertainment"
        }
    ],
    "sg:phone":"+1 780 492 2495",
    "sg:postcode":"T6G 2C9",
    "sg:province":"AB",
    "wof:name":"Studio Theatre Box Office",
    "wof:placetype":"venue"
},
  "geometry": {"coordinates":[-113.439308166,53.564540863],"type":"Point"}
}