{
  "type": "Feature",
  "properties": {
    "addr:full":"991 James St Mattawa ON P0H 1V0",
    "addr:housenumber":"991",
    "addr:postcode":"p0h 1v0",
    "addr:street":"James St",
    "iso:country":"CA",
    "sg:address":"991 James St",
    "sg:city":"Mattawa",
    "sg:classifiers":[
        {
            "category":"Organizations",
            "subcategory":"Religious Organization",
            "type":"Services"
        }
    ],
    "sg:phone":"+1 705 744 2341",
    "sg:postcode":"P0H 1V0",
    "sg:province":"ON",
    "sg:tags":[
        "church"
    ],
    "wof:name":"Pentecostal Church Mclc",
    "wof:placetype":"venue"
},
  "geometry": {"coordinates":[-78.717682,46.309689],"type":"Point"}
}