{
  "type": "Feature",
  "properties": {
    "addr:full":"RR 2 STN Main Kincardine ON N2Z 2X4",
    "addr:postcode":"n2z 2x4",
    "addr:street":"Rr 2 Stn Main",
    "iso:country":"CA",
    "sg:address":"RR 2 STN Main",
    "sg:city":"Kincardine",
    "sg:classifiers":[
        {
            "category":"Manufacturing",
            "subcategory":"Tools & Machinery",
            "type":"Manufacturing & Wholesale Goods"
        }
    ],
    "sg:phone":"+1 519 396 8024",
    "sg:postcode":"N2Z 2X4",
    "sg:province":"ON",
    "sg:tags":[
        "control"
    ],
    "wof:name":"Automation Electric",
    "wof:placetype":"venue"
},
  "geometry": {"coordinates":[-81.6317367554,44.1816139221],"type":"Point"}
}