{
  "type": "Feature",
  "properties": {
    "addr:full":"5 Rue DE Martigny E Saint-Jerome QC J7Z 6E8",
    "addr:housenumber":"5",
    "addr:postcode":"j7z 6e8",
    "addr:street":"Rue De Martigny E Saint-Jerome",
    "iso:country":"CA",
    "sg:address":"5 Rue DE Martigny E",
    "sg:city":"Saint-Jerome",
    "sg:classifiers":[
        {
            "category":"Restaurant",
            "type":"Food & Drink"
        }
    ],
    "sg:phone":"+1 450 432 6628",
    "sg:postcode":"J7Z 6E8",
    "sg:province":"QC",
    "wof:name":"Pacini Restaurant",
    "wof:placetype":"venue"
},
  "geometry": {"coordinates":[-74.00310500000001,45.780251],"type":"Point"}
}