{
  "type": "Feature",
  "properties": {
    "iso:country":"CA",
    "sg:address":"103 Main St N",
    "sg:city":"Mount Forest",
    "sg:classifiers":[
        {
            "category":"Restaurant",
            "type":"Food & Drink"
        }
    ],
    "sg:phone":"+1 519 323 2880",
    "sg:postcode":"N0G 2L0",
    "sg:province":"ON",
    "sg:tags":[
        "pizza"
    ],
    "wof:name":"Olympic Pizza",
    "wof:placetype":"venue"
},
  "geometry": {"coordinates":[-80.73589324949999,43.9818115234],"type":"Point"}
}