{
  "type": "Feature",
  "properties": {
    "addr:full":"Main St Mccord SK S0H 2T0",
    "addr:postcode":"s0h 2t0",
    "addr:street":"Main St",
    "iso:country":"CA",
    "sg:address":"Main St",
    "sg:city":"Mccord",
    "sg:classifiers":[
        {
            "category":"Home & Garden",
            "subcategory":"Building Materials",
            "type":"Retail Goods"
        }
    ],
    "sg:phone":"+1 306 478 2556",
    "sg:postcode":"S0H 2T0",
    "sg:province":"SK",
    "sg:tags":[
        "lumber"
    ],
    "wof:name":"Mc Cord CO-OP Assoc Ltd",
    "wof:placetype":"venue"
},
  "geometry": {"coordinates":[-106.83266399999999,49.429218],"type":"Point"}
}