{
  "type": "Feature",
  "properties": {
    "addr:full":"17215 Stony Plain Rd NW Edmonton AB T5S 2N2",
    "addr:housenumber":"17215",
    "addr:postcode":"t5s 2n2",
    "addr:street":"Stony Plain Rd Nw",
    "iso:country":"CA",
    "sg:address":"17215 Stony Plain Rd NW",
    "sg:city":"Edmonton",
    "sg:classifiers":[
        {
            "category":"Restaurant",
            "type":"Food & Drink"
        }
    ],
    "sg:phone":"+1 780 444 5670",
    "sg:postcode":"T5S 2N2",
    "sg:province":"AB",
    "wof:name":"Burger King",
    "wof:placetype":"venue"
},
  "geometry": {"coordinates":[-113.618209839,53.541179657],"type":"Point"}
}