{
  "type": "Feature",
  "properties": {
    "addr:full":"Port Alberni BC V9Y 1V6",
    "addr:postcode":"v9y 1v6",
    "iso:country":"CA",
    "sg:city":"Port Alberni",
    "sg:classifiers":[
        {
            "category":"Retail",
            "subcategory":"Laundry & Dry Cleaning",
            "type":"Services"
        }
    ],
    "sg:phone":"+1 250 723 1899",
    "sg:postcode":"V9Y 1V6",
    "sg:province":"BC",
    "wof:name":"Girison Laundromat",
    "wof:placetype":"venue"
},
  "geometry": {"coordinates":[-124.806793,49.234924],"type":"Point"}
}