{
  "type": "Feature",
  "properties": {
    "addr:full":"9 Melanie Cres Kanata ON K2L 2E4",
    "addr:housenumber":"9",
    "addr:postcode":"k2l 2e4",
    "addr:street":"Melanie Cres",
    "iso:country":"CA",
    "sg:address":"9 Melanie Cres",
    "sg:city":"Kanata",
    "sg:classifiers":[
        {
            "category":"Building & Trades",
            "subcategory":"Cleaning & Sanitation",
            "type":"Services"
        }
    ],
    "sg:phone":"+1 613 836 7513",
    "sg:postcode":"K2L 2E4",
    "sg:province":"ON",
    "sg:tags":[
        "house"
    ],
    "wof:name":"Classic Touch",
    "wof:placetype":"venue"
},
  "geometry": {"coordinates":[-75.885429,45.294155],"type":"Point"}
}