{
  "type": "Feature",
  "properties": {
    "addr:full":"24 Dunlop St Richmond Hill ON L4C 2M3",
    "addr:housenumber":"24",
    "addr:postcode":"l4c 2m3",
    "addr:street":"Dunlop St",
    "iso:country":"CA",
    "sg:address":"24 Dunlop St",
    "sg:city":"Richmond Hill",
    "sg:classifiers":[
        {
            "category":"Health Services",
            "subcategory":"Health Practitioner",
            "type":"Services"
        }
    ],
    "sg:phone":"+1 905 737 9730",
    "sg:postcode":"L4C 2M3",
    "sg:province":"ON",
    "sg:tags":[
        "psychologist"
    ],
    "wof:name":"Padden, Patricia",
    "wof:placetype":"venue"
},
  "geometry": {"coordinates":[-79.4375534058,43.8780899048],"type":"Point"}
}