{
  "type": "Feature",
  "properties": {
    "addr:full":"616 Baker St Nelson BC V1L 4J4",
    "addr:housenumber":"616",
    "addr:postcode":"bc v1l 4j4",
    "addr:street":"Baker St",
    "iso:country":"CA",
    "sg:address":"616 Baker St",
    "sg:city":"Nelson",
    "sg:classifiers":[
        {
            "category":"Restaurant",
            "type":"Food & Drink"
        }
    ],
    "sg:phone":"+1 250 354 4848",
    "sg:postcode":"V1L 4J4",
    "sg:province":"BC",
    "wof:name":"Main Street Diner",
    "wof:placetype":"venue"
},
  "geometry": {"coordinates":[-117.29218299999999,49.492504],"type":"Point"}
}