{
  "type": "Feature",
  "properties": {
    "addr:full":"62 Queen St S Mississauga ON L5M 1K4",
    "addr:housenumber":"62",
    "addr:postcode":"l5m 1k4",
    "addr:street":"Queen St S",
    "iso:country":"CA",
    "sg:address":"62 Queen St S",
    "sg:city":"Mississauga",
    "sg:classifiers":[
        {
            "category":"Professional",
            "subcategory":"Lawyer & Legal Services",
            "type":"Services"
        }
    ],
    "sg:phone":"+1 905 826 2511",
    "sg:postcode":"L5M 1K4",
    "sg:province":"ON",
    "sg:tags":[
        "attorney"
    ],
    "wof:name":"Brant, George F",
    "wof:placetype":"venue"
},
  "geometry": {"coordinates":[-79.59368133540001,43.5491714478],"type":"Point"}
}