{
  "type": "Feature",
  "properties": {
    "addr:full":"112 Main St Rockwood ON N0B 2K0",
    "addr:housenumber":"112",
    "addr:postcode":"n0b 2k0",
    "addr:street":"Main St",
    "iso:country":"CA",
    "sg:address":"112 Main St",
    "sg:city":"Rockwood",
    "sg:classifiers":[
        {
            "category":"Organizations",
            "subcategory":"Religious Organization",
            "type":"Services"
        }
    ],
    "sg:phone":"+1 519 856 9211",
    "sg:postcode":"N0B 2K0",
    "sg:province":"ON",
    "sg:tags":[
        "church"
    ],
    "wof:name":"St John Anglican Church",
    "wof:placetype":"venue"
},
  "geometry": {"coordinates":[-80.1443862915,43.6191482544],"type":"Point"}
}