{
  "type": "Feature",
  "properties": {
    "addr:full":"2515 Av Dalton Sainte-Foy QC G1P 3S5",
    "addr:housenumber":"2515",
    "addr:postcode":"g1p 3s5",
    "addr:street":"Av Dalton",
    "iso:country":"CA",
    "sg:address":"2515 Av Dalton",
    "sg:city":"Sainte-Foy",
    "sg:classifiers":[
        {
            "category":"Manufacturing",
            "subcategory":"Metals",
            "type":"Manufacturing & Wholesale Goods"
        }
    ],
    "sg:phone":"+1 418 653 9371",
    "sg:postcode":"G1P 3S5",
    "sg:province":"QC",
    "sg:tags":[
        "steel"
    ],
    "wof:name":"Rodrigue Metal Ltee",
    "wof:placetype":"venue"
},
  "geometry": {"coordinates":[-71.29975899999999,46.791519],"type":"Point"}
}