{
  "type": "Feature",
  "properties": {
    "addr:full":"3878 Kirkaldy St Thornhill BC V8G 3M8",
    "addr:housenumber":"3878",
    "addr:postcode":"v8g 3m8",
    "addr:street":"Kirkaldy St",
    "iso:country":"CA",
    "sg:address":"3878 Kirkaldy St",
    "sg:city":"Thornhill",
    "sg:classifiers":[
        {
            "category":"Building & Trades",
            "subcategory":"Construction",
            "type":"Services"
        }
    ],
    "sg:phone":"+1 250 635 6479",
    "sg:postcode":"V8G 3M8",
    "sg:province":"BC",
    "sg:tags":[
        "repairing",
        "remodeling",
        "contractor"
    ],
    "wof:name":"Mph Construction",
    "wof:placetype":"venue"
},
  "geometry": {"coordinates":[-128.51980599999999,54.53159],"type":"Point"}
}