{
  "type": "Feature",
  "properties": {
    "iso:country":"CA",
    "sg:address":"325 Granville St",
    "sg:city":"Bridgetown",
    "sg:classifiers":[
        {
            "category":"Shopping",
            "subcategory":"Bicycles & Sporting Goods",
            "type":"Retail Goods"
        }
    ],
    "sg:phone":"+1 902 665 4937",
    "sg:postcode":"B0S 1C0",
    "sg:province":"NS",
    "wof:name":"Kinetic Solutions",
    "wof:placetype":"venue"
},
  "geometry": {"coordinates":[-65.28848266599999,44.8414115906],"type":"Point"}
}