{
  "type": "Feature",
  "properties": {
    "addr:full":"1363 Rue Provancher Cap-Rouge QC G1Y 1R7",
    "addr:housenumber":"1363",
    "addr:postcode":"g1y 1r7",
    "addr:street":"Rue Provancher",
    "iso:country":"CA",
    "sg:address":"1363 Rue Provancher",
    "sg:city":"Cap-Rouge",
    "sg:classifiers":[
        {
            "category":"Health Services",
            "subcategory":"Doctor",
            "type":"Services"
        }
    ],
    "sg:phone":"+1 418 653 5151",
    "sg:postcode":"G1Y 1R7",
    "sg:province":"QC",
    "sg:tags":[
        "clinic",
        "psychologist"
    ],
    "wof:name":"Clinique DE Psych Cap Rouge",
    "wof:placetype":"venue"
},
  "geometry": {"coordinates":[-71.34435999999999,46.754036],"type":"Point"}
}