{
  "type": "Feature",
  "properties": {
    "addr:full":"Castlegar BC V1N 2A8",
    "addr:postcode":"v1n 2a8",
    "iso:country":"CA",
    "sg:city":"Castlegar",
    "sg:classifiers":[
        {
            "category":"Banks & Credit Unions",
            "subcategory":"Investment Brokerage",
            "type":"Services"
        }
    ],
    "sg:phone":"+1 250 365 2345",
    "sg:postcode":"V1N 2A8",
    "sg:province":"BC",
    "sg:tags":[
        "consultant",
        "planning",
        "financial"
    ],
    "wof:name":"Affolter Financial Group Inc",
    "wof:placetype":"venue"
},
  "geometry": {"coordinates":[-117.664734,49.325665],"type":"Point"}
}