{
  "type": "Feature",
  "properties": {
    "addr:full":"14604 116 Ave NW Edmonton AB T5M 3E9",
    "addr:housenumber":"14604",
    "addr:postcode":"t5m 3e9",
    "addr:street":"116 Ave Nw",
    "iso:country":"CA",
    "sg:address":"14604 116 Ave NW",
    "sg:city":"Edmonton",
    "sg:classifiers":[
        {
            "category":"Wholesale",
            "subcategory":"Machinery & Supplies",
            "type":"Manufacturing & Wholesale Goods"
        }
    ],
    "sg:phone":"+1 780 452 3797",
    "sg:postcode":"T5M 3E9",
    "sg:province":"AB",
    "sg:tags":[
        "janitor"
    ],
    "wof:name":"Venture Supply",
    "wof:placetype":"venue"
},
  "geometry": {"coordinates":[-113.57231899999999,53.568027],"type":"Point"}
}