{
  "type": "Feature",
  "properties": {
    "addr:full":"51 Regent St Guelph ON N1E 4W5",
    "addr:housenumber":"51",
    "addr:postcode":"n1e 4w5",
    "addr:street":"Regent St",
    "iso:country":"CA",
    "sg:address":"51 Regent St",
    "sg:city":"Guelph",
    "sg:classifiers":[
        {
            "category":"Building & Trades",
            "subcategory":"Landscaping Services",
            "type":"Services"
        }
    ],
    "sg:phone":"+1 519 837 2466",
    "sg:postcode":"N1E 4W5",
    "sg:province":"ON",
    "sg:tags":[
        "lawn",
        "maintenance",
        "grounds"
    ],
    "wof:name":"Schepers Property Svc Inc",
    "wof:placetype":"venue"
},
  "geometry": {"coordinates":[-80.243538,43.54924],"type":"Point"}
}