{
  "type": "Feature",
  "properties": {
    "addr:full":"Terrace BC V8G 1S2",
    "addr:postcode":"v8g 1s2",
    "iso:country":"CA",
    "sg:city":"Terrace",
    "sg:classifiers":[
        {
            "category":"Professional",
            "subcategory":"Credit Reporting & Collection",
            "type":"Services"
        }
    ],
    "sg:phone":"+1 250 635 7649",
    "sg:postcode":"V8G 1S2",
    "sg:province":"BC",
    "sg:tags":[
        "agency"
    ],
    "wof:name":"Caledonia Collection Agencies",
    "wof:placetype":"venue"
},
  "geometry": {"coordinates":[-128.58442688,54.5173454285],"type":"Point"}
}