{
  "type": "Feature",
  "properties": {
    "iso:country":"CA",
    "sg:address":"2810 127E Rue",
    "sg:city":"Saint-Georges",
    "sg:classifiers":[
        {
            "category":"Manufacturing",
            "subcategory":"Tools & Machinery",
            "type":"Manufacturing & Wholesale Goods"
        }
    ],
    "sg:phone":"+1 418 228 5763",
    "sg:postcode":"G5Y 6K9",
    "sg:province":"QC",
    "sg:tags":[
        "compressor"
    ],
    "wof:name":"Distributions Giclair Inc",
    "wof:placetype":"venue"
},
  "geometry": {"coordinates":[-70.67115,46.123348],"type":"Point"}
}