{
  "type": "Feature",
  "properties": {
    "iso:country":"CA",
    "sg:address":"267 Thompson Rd",
    "sg:city":"London",
    "sg:classifiers":[
        {
            "category":"Shopping",
            "subcategory":"Discount & Variety Stores",
            "type":"Retail Goods"
        }
    ],
    "sg:phone":"+1 519 690 1981",
    "sg:postcode":"N5Z 2Z3",
    "sg:province":"ON",
    "wof:name":"Hernandez Variety",
    "wof:placetype":"venue"
},
  "geometry": {"coordinates":[-81.220131,42.968815],"type":"Point"}
}