{
  "type": "Feature",
  "properties": {
    "addr:full":"267 Thompson Rd London ON N5Z 2Z3",
    "addr:housenumber":"267",
    "addr:postcode":"n5z 2z3",
    "addr:street":"Thompson Rd",
    "iso:country":"CA",
    "sg:address":"267 Thompson Rd",
    "sg:city":"London",
    "sg:classifiers":[
        {
            "category":"Shopping",
            "subcategory":"Discount & Variety Stores",
            "type":"Retail Goods"
        }
    ],
    "sg:phone":"+1 519 690 1981",
    "sg:postcode":"N5Z 2Z3",
    "sg:province":"ON",
    "wof:name":"Hernandez Variety",
    "wof:placetype":"venue"
},
  "geometry": {"coordinates":[-81.22013099999999,42.968815],"type":"Point"}
}