{
  "type": "Feature",
  "properties": {
    "addr:full":"3730 Rue Du Campanile # 101 Sainte-Foy QC G1X 4G6",
    "addr:housenumber":"3730",
    "addr:postcode":"g1x 4g6",
    "addr:street":"Rue Du Campanile # 101",
    "iso:country":"CA",
    "sg:address":"3730 Rue Du Campanile # 101",
    "sg:city":"Sainte-Foy",
    "sg:classifiers":[
        {
            "category":"Health Services",
            "subcategory":"Doctor",
            "type":"Services"
        }
    ],
    "sg:phone":"+1 418 656 0377",
    "sg:postcode":"G1X 4G6",
    "sg:province":"QC",
    "sg:tags":[
        "dentist"
    ],
    "wof:name":"Lamy, Lucie DDS",
    "wof:placetype":"venue"
},
  "geometry": {"coordinates":[-71.3327331543,46.7617950439],"type":"Point"}
}