{
  "type": "Feature",
  "properties": {
    "iso:country":"CA",
    "sg:address":"3237 King George Hwy",
    "sg:city":"Surrey",
    "sg:classifiers":[
        {
            "category":"Wholesale",
            "subcategory":"Office Equipment",
            "type":"Manufacturing & Wholesale Goods"
        }
    ],
    "sg:phone":"+1 604 598 8707",
    "sg:postcode":"V4P 1B7",
    "sg:province":"BC",
    "sg:tags":[
        "scanning",
        "code",
        "bar"
    ],
    "wof:name":"Ryzex",
    "wof:placetype":"venue"
},
  "geometry": {"coordinates":[-122.812965393,49.0609931946],"type":"Point"}
}