{
  "type": "Feature",
  "properties": {
    "addr:full":"484 Albert St Kingston ON K7L 3W3",
    "addr:housenumber":"484",
    "addr:postcode":"k7l 3w3",
    "addr:street":"Albert St",
    "iso:country":"CA",
    "sg:address":"484 Albert St",
    "sg:city":"Kingston",
    "sg:classifiers":[
        {
            "category":"Education",
            "subcategory":"School",
            "type":"Public Place"
        }
    ],
    "sg:phone":"+1 613 549 2004",
    "sg:postcode":"K7L 3W3",
    "sg:province":"ON",
    "wof:name":"Martello Enrichment School Inc",
    "wof:placetype":"venue"
},
  "geometry": {"coordinates":[-76.500831604,44.2359657288],"type":"Point"}
}