{
  "type": "Feature",
  "properties": {
    "addr:full":"739 Rue Des Erables Saint-Lambert-DE-Lauzon QC G0S 2W0",
    "addr:housenumber":"739",
    "addr:postcode":"g0s 2w0",
    "addr:street":"Rue Des Erables",
    "iso:country":"CA",
    "sg:address":"739 Rue Des Erables",
    "sg:city":"Saint-Lambert-DE-Lauzon",
    "sg:classifiers":[
        {
            "category":"Health Services",
            "subcategory":"Doctor",
            "type":"Services"
        }
    ],
    "sg:phone":"+1 418 889 0544",
    "sg:postcode":"G0S 2W0",
    "sg:province":"QC",
    "sg:tags":[
        "clinic",
        "chiropractor"
    ],
    "wof:name":"Clinique Chiropractique",
    "wof:placetype":"venue"
},
  "geometry": {"coordinates":[-71.236588,46.613087],"type":"Point"}
}