{
  "type": "Feature",
  "properties": {
    "iso:country":"CA",
    "sg:city":"Sainte-Anne-DE-LA-Perade",
    "sg:classifiers":[
        {
            "category":"Manufacturing",
            "subcategory":"Lumber",
            "type":"Manufacturing & Wholesale Goods"
        }
    ],
    "sg:phone":"+1 418 325 3215",
    "sg:postcode":"G0X 2J0",
    "sg:province":"QC",
    "sg:tags":[
        "sawmill"
    ],
    "wof:name":"Yvon Baril Scierie Mobile",
    "wof:placetype":"venue"
},
  "geometry": {"coordinates":[-72.75383758540001,47.6383094788],"type":"Point"}
}