{
  "type": "Feature",
  "properties": {
    "addr:full":"2520 Rue Sainte-Catherine E Montreal QC H2K 2K2",
    "addr:housenumber":"2520",
    "addr:postcode":"h2k 2k2",
    "addr:street":"Rue Sainte-Catherine E",
    "iso:country":"CA",
    "sg:address":"2520 Rue Sainte-Catherine E",
    "sg:city":"Montreal",
    "sg:classifiers":[
        {
            "category":"Personal",
            "subcategory":"Beauty Salon",
            "type":"Services"
        }
    ],
    "sg:phone":"+1 514 523 3247",
    "sg:postcode":"H2K 2K2",
    "sg:province":"QC",
    "wof:name":"Coiffure Magic-Look Enr",
    "wof:placetype":"venue"
},
  "geometry": {"coordinates":[-73.54568500000001,45.529629],"type":"Point"}
}