{
  "type": "Feature",
  "properties": {
    "addr:full":"7513 Edmonds St Burnaby BC V3N 1B5",
    "addr:housenumber":"7513",
    "addr:postcode":"v3n 1b5",
    "addr:street":"Edmonds St",
    "iso:country":"CA",
    "sg:address":"7513 Edmonds St",
    "sg:city":"Burnaby",
    "sg:classifiers":[
        {
            "category":"Manufacturing",
            "subcategory":"Glass & Minerals",
            "type":"Manufacturing & Wholesale Goods"
        }
    ],
    "sg:phone":"+1 604 830 1812",
    "sg:postcode":"V3N 1B5",
    "sg:province":"BC",
    "sg:tags":[
        "concrete",
        "brick",
        "prod",
        "block"
    ],
    "wof:name":"Cadillac Concrete",
    "wof:placetype":"venue"
},
  "geometry": {"coordinates":[-122.944641,49.222282],"type":"Point"}
}