{
  "type": "Feature",
  "properties": {
    "addr:full":"New Glasgow NS B2H 2P6",
    "addr:postcode":"b2h 2p6",
    "iso:country":"CA",
    "sg:city":"New Glasgow",
    "sg:classifiers":[
        {
            "category":"Government",
            "subcategory":"Office",
            "type":"Public Place"
        }
    ],
    "sg:phone":"+1 902 755 4266",
    "sg:postcode":"B2H 2P6",
    "sg:province":"NS",
    "sg:tags":[
        "member",
        "legislative",
        "assembly"
    ],
    "wof:name":"Hamm, John F",
    "wof:placetype":"venue"
},
  "geometry": {"coordinates":[-62.6452636719,45.5874519348],"type":"Point"}
}