{
  "type": "Feature",
  "properties": {
    "addr:full":"1850 Rue Des Cascades O Saint-Hyacinthe QC J2S 3J3",
    "addr:housenumber":"1850",
    "addr:postcode":"j2s 3j3",
    "addr:street":"Rue Des Cascades O",
    "iso:country":"CA",
    "sg:address":"1850 Rue Des Cascades O",
    "sg:city":"Saint-Hyacinthe",
    "sg:classifiers":[
        {
            "category":"Bars & Pubs",
            "type":"Food & Drink"
        }
    ],
    "sg:phone":"+1 450 771 6900",
    "sg:postcode":"J2S 3J3",
    "sg:province":"QC",
    "sg:tags":[
        "lounge",
        "cocktail"
    ],
    "wof:name":"Bar Le Bilboquet",
    "wof:placetype":"venue"
},
  "geometry": {"coordinates":[-72.94760894780001,45.6235313416],"type":"Point"}
}