{
  "type": "Feature",
  "properties": {
    "addr:full":"8890 Eighth Line Georgetown ON L7G 4S5",
    "addr:housenumber":"8890",
    "addr:postcode":"l7g 4s5",
    "addr:street":"Eighth Line",
    "iso:country":"CA",
    "sg:address":"8890 Eighth Line",
    "sg:city":"Georgetown",
    "sg:classifiers":[
        {
            "category":"Home & Garden",
            "subcategory":"Garden Supply",
            "type":"Retail Goods"
        }
    ],
    "sg:phone":"+1 905 877 9842",
    "sg:postcode":"L7G 4S5",
    "sg:province":"ON",
    "sg:tags":[
        "center"
    ],
    "wof:name":"D G Greenhouses",
    "wof:placetype":"venue"
},
  "geometry": {"coordinates":[-79.85301200000001,43.59473],"type":"Point"}
}