{
  "type": "Feature",
  "properties": {
    "addr:full":"2100 Queen St E Toronto ON M4E 1E1",
    "addr:housenumber":"2100",
    "addr:postcode":"m4e 1e1",
    "addr:street":"Queen St E",
    "iso:country":"CA",
    "sg:address":"2100 Queen St E",
    "sg:city":"Toronto",
    "sg:classifiers":[
        {
            "category":"Restaurant",
            "type":"Food & Drink"
        }
    ],
    "sg:phone":"+1 416 690 6700",
    "sg:postcode":"M4E 1E1",
    "sg:province":"ON",
    "sg:tags":[
        "store",
        "variety"
    ],
    "wof:name":"Beach Corner",
    "wof:placetype":"venue"
},
  "geometry": {"coordinates":[-79.29587554930001,43.6710014343],"type":"Point"}
}