{
  "type": "Feature",
  "properties": {
    "addr:full":"Edmonton AB T5L 0G7",
    "addr:postcode":"t5l 0g7",
    "iso:country":"CA",
    "sg:city":"Edmonton",
    "sg:classifiers":[
        {
            "category":"Health Services",
            "subcategory":"Doctor",
            "type":"Services"
        }
    ],
    "sg:phone":"+1 780 455 3498",
    "sg:postcode":"T5L 0G7",
    "sg:province":"AB",
    "sg:tags":[
        "physician",
        "surgeon"
    ],
    "wof:name":"Alam, M F MD",
    "wof:placetype":"venue"
},
  "geometry": {"coordinates":[-113.533913,53.570637],"type":"Point"}
}