{
  "type": "Feature",
  "properties": {
    "iso:country":"CA",
    "sg:address":"330 Rue Saint-Roch",
    "sg:city":"Trois-Rivieres",
    "sg:classifiers":[
        {
            "category":"Food & Beverages",
            "subcategory":"Groceries & Convenience Stores",
            "type":"Retail Goods"
        }
    ],
    "sg:phone":"+1 819 371 3111",
    "sg:postcode":"G9A 2L5",
    "sg:province":"QC",
    "wof:name":"Depanneur Du Marche Irving",
    "wof:placetype":"venue"
},
  "geometry": {"coordinates":[-72.543800354,46.3399162292],"type":"Point"}
}