{
  "type": "Feature",
  "properties": {
    "addr:full":"1221 Algonquin Ave #104 North Bay ON P1B 4Y3",
    "addr:housenumber":"1221",
    "addr:postcode":"p1b 4y3",
    "addr:street":"Algonquin Ave # 104",
    "iso:country":"CA",
    "sg:address":"1221 Algonquin Ave #104",
    "sg:city":"North Bay",
    "sg:classifiers":[
        {
            "category":"Health Services",
            "subcategory":"Medical Lab",
            "type":"Services"
        }
    ],
    "sg:phone":"+1 705 476 6228",
    "sg:postcode":"P1B 4Y3",
    "sg:province":"ON",
    "sg:tags":[
        "x"
    ],
    "wof:name":"Algonquin X Ray & Ultrasound",
    "wof:placetype":"venue"
},
  "geometry": {"coordinates":[-79.466393,46.326534],"type":"Point"}
}