{
  "type": "Feature",
  "properties": {
    "addr:full":"85 15th St W Prince Albert SK S6V 3P4",
    "addr:housenumber":"85",
    "addr:postcode":"s6v 3p4",
    "addr:street":"15Th St",
    "iso:country":"CA",
    "sg:address":"85 15th St W",
    "sg:city":"Prince Albert",
    "sg:classifiers":[
        {
            "category":"Shopping",
            "subcategory":"Computers & Home Electronics",
            "type":"Retail Goods"
        }
    ],
    "sg:phone":"+1 306 764 2956",
    "sg:postcode":"S6V 3P4",
    "sg:province":"SK",
    "sg:tags":[
        "high",
        "television",
        "stereophonic",
        "fidelity"
    ],
    "wof:name":"Audio Video Unlimited",
    "wof:placetype":"venue"
},
  "geometry": {"coordinates":[-105.756798,53.199226],"type":"Point"}
}