{
  "type": "Feature",
  "properties": {
    "addr:full":"10030 Thatcher Ave North Battleford SK S9A 2X6",
    "addr:housenumber":"10030",
    "addr:postcode":"s9a 2x6",
    "addr:street":"Thatcher Ave",
    "iso:country":"CA",
    "sg:address":"10030 Thatcher Ave",
    "sg:city":"North Battleford",
    "sg:classifiers":[
        {
            "category":"Retail",
            "subcategory":"Auto Repair",
            "type":"Services"
        }
    ],
    "sg:phone":"+1 306 446 2600",
    "sg:postcode":"S9A 2X6",
    "sg:province":"SK",
    "sg:tags":[
        "wrecker"
    ],
    "wof:name":"Lash-Berg Towing",
    "wof:placetype":"venue"
},
  "geometry": {"coordinates":[-108.252380371,52.7470359802],"type":"Point"}
}