{
  "type": "Feature",
  "properties": {
    "addr:full":"3365 Av DE Granby Montreal QC H1N 2Z7",
    "addr:housenumber":"3365",
    "addr:postcode":"h1n 2z7",
    "addr:street":"Av De Granby",
    "iso:country":"CA",
    "sg:address":"3365 Av DE Granby",
    "sg:city":"Montreal",
    "sg:classifiers":[
        {
            "category":"Shopping",
            "subcategory":"Clothing, Apparel, & Fashions",
            "type":"Retail Goods"
        }
    ],
    "sg:phone":"+1 514 255 5015",
    "sg:postcode":"H1N 2Z7",
    "sg:province":"QC",
    "sg:tags":[
        "infant",
        "wear"
    ],
    "wof:name":"Pitchous Club",
    "wof:placetype":"venue"
},
  "geometry": {"coordinates":[-73.54244199999999,45.580902],"type":"Point"}
}