{
  "type": "Feature",
  "properties": {
    "addr:full":"1366 Brentwood Crt Kelowna BC V1Z 3C2",
    "addr:housenumber":"1366",
    "addr:postcode":"v1z 3c2",
    "addr:street":"Brentwood Crt",
    "iso:country":"CA",
    "sg:address":"1366 Brentwood Crt",
    "sg:city":"Kelowna",
    "sg:classifiers":[
        {
            "category":"Building & Trades",
            "subcategory":"Construction",
            "type":"Services"
        }
    ],
    "sg:phone":"+1 250 769 4147",
    "sg:postcode":"V1Z 3C2",
    "sg:province":"BC",
    "sg:tags":[
        "concrete",
        "contractor",
        "general"
    ],
    "wof:name":"B J Concrete Finishing",
    "wof:placetype":"venue"
},
  "geometry": {"coordinates":[-119.57165500000001,49.86187],"type":"Point"}
}