{
  "type": "Feature",
  "properties": {
    "addr:full":"3017 St. Johns St Port Moody BC V3H 2C4",
    "addr:housenumber":"3017",
    "addr:postcode":"v3h 2c4",
    "addr:street":"St. Johns St",
    "iso:country":"CA",
    "sg:address":"3017 St. Johns St",
    "sg:city":"Port Moody",
    "sg:classifiers":[
        {
            "category":"Restaurant",
            "type":"Food & Drink"
        }
    ],
    "sg:phone":"+1 604 469 8623",
    "sg:postcode":"V3H 2C4",
    "sg:province":"BC",
    "wof:name":"Carefree Family Restaurant",
    "wof:placetype":"venue"
},
  "geometry": {"coordinates":[-122.844436645,49.2765007019],"type":"Point"}
}