{
  "type": "Feature",
  "properties": {
    "addr:full":"401 Main St Shediac NB E4P 2B6",
    "addr:housenumber":"401",
    "addr:postcode":"e4p 2b6",
    "addr:street":"Main St",
    "iso:country":"CA",
    "sg:address":"401 Main St",
    "sg:city":"Shediac",
    "sg:classifiers":[
        {
            "category":"Wholesale",
            "subcategory":"Hardware",
            "type":"Manufacturing & Wholesale Goods"
        }
    ],
    "sg:phone":"+1 506 532 4000",
    "sg:postcode":"E4P 2B6",
    "sg:province":"NB",
    "sg:tags":[
        "purifying",
        "cleaning",
        "air"
    ],
    "wof:name":"Robert E Poirier & Assoc",
    "wof:placetype":"venue"
},
  "geometry": {"coordinates":[-64.5365524292,46.219871521],"type":"Point"}
}