{
  "type": "Feature",
  "properties": {
    "addr:full":"103 Av Gun Pointe-Claire QC H9R 3X2",
    "addr:postcode":"h9r 3x2",
    "addr:street":"103 Av Gun",
    "iso:country":"CA",
    "sg:address":"103 Av Gun",
    "sg:city":"Pointe-Claire",
    "sg:classifiers":[
        {
            "category":"Manufacturing",
            "subcategory":"Chemicals & Compounds",
            "type":"Manufacturing & Wholesale Goods"
        }
    ],
    "sg:phone":"+1 514 697 9510",
    "sg:postcode":"H9R 3X2",
    "sg:province":"QC",
    "wof:name":"Chempro Inc",
    "wof:placetype":"venue"
},
  "geometry": {"coordinates":[-73.8099899292,45.4655227661],"type":"Point"}
}