{
  "type": "Feature",
  "properties": {
    "addr:full":"561 Elm Ashcroft BC V0K 1A0",
    "addr:housenumber":"561",
    "addr:postcode":"v0k 1a0",
    "addr:street":"Elm",
    "iso:country":"CA",
    "sg:address":"561 Elm",
    "sg:city":"Ashcroft",
    "sg:classifiers":[
        {
            "category":"Recreation",
            "type":"Entertainment"
        }
    ],
    "sg:phone":"+1 250 453 9031",
    "sg:postcode":"V0K 1A0",
    "sg:province":"BC",
    "sg:tags":[
        "pool",
        "swimming"
    ],
    "wof:name":"Ashcroft Outdoor Swimming Pool",
    "wof:placetype":"venue"
},
  "geometry": {"coordinates":[-121.281532,50.733219],"type":"Point"}
}