{
  "type": "Feature",
  "properties": {
    "iso:country":"CA",
    "sg:address":"679 Memorial Ave",
    "sg:city":"Qualicum Beach",
    "sg:classifiers":[
        {
            "category":"Real Estate",
            "subcategory":"Real Estate Agent",
            "type":"Services"
        }
    ],
    "sg:phone":"+1 250 752 6926",
    "sg:postcode":"V9K 1T4",
    "sg:province":"BC",
    "wof:name":"Parksville-Qualicum Beach Rlty",
    "wof:placetype":"venue"
},
  "geometry": {"coordinates":[-124.441833496,49.3473701477],"type":"Point"}
}