{
  "type": "Feature",
  "properties": {
    "iso:country":"CA",
    "sg:address":"300 Cabana Rd E",
    "sg:city":"Windsor",
    "sg:classifiers":[
        {
            "category":"Real Estate",
            "subcategory":"Real Estate Agent",
            "type":"Services"
        }
    ],
    "sg:phone":"+1 519 966 9940",
    "sg:postcode":"N9G 1A3",
    "sg:province":"ON",
    "sg:tags":[
        "appraiser"
    ],
    "wof:name":"Gorski Realty Appraisals",
    "wof:placetype":"venue"
},
  "geometry": {"coordinates":[-82.9974365234,42.258518219],"type":"Point"}
}