{
  "type": "Feature",
  "properties": {
    "iso:country":"CA",
    "sg:address":"17841 64 Ave",
    "sg:city":"Surrey",
    "sg:classifiers":[
        {
            "category":"Retail",
            "subcategory":"Auto Repair",
            "type":"Services"
        }
    ],
    "sg:phone":"+1 604 574 4266",
    "sg:postcode":"V3S 1Z3",
    "sg:province":"BC",
    "sg:tags":[
        "trailer"
    ],
    "wof:name":"A & K Diesel Repair Ltd",
    "wof:placetype":"venue"
},
  "geometry": {"coordinates":[-122.727378845,49.1189079285],"type":"Point"}
}