{
  "type": "Feature",
  "properties": {
    "addr:full":"93 Grant Timmins Dr Kingston ON K7M 8N3",
    "addr:housenumber":"93",
    "addr:postcode":"k7m 8n3",
    "addr:street":"Grant Timmins Dr",
    "iso:country":"CA",
    "sg:address":"93 Grant Timmins Dr",
    "sg:city":"Kingston",
    "sg:classifiers":[
        {
            "category":"Wholesale",
            "subcategory":"Hardware",
            "type":"Manufacturing & Wholesale Goods"
        }
    ],
    "sg:phone":"+1 613 546 1161",
    "sg:postcode":"K7M 8N3",
    "sg:province":"ON",
    "sg:tags":[
        "plumbing",
        "fixture",
        "supply"
    ],
    "wof:name":"Crane Supply",
    "wof:placetype":"venue"
},
  "geometry": {"coordinates":[-76.5254211426,44.2671470642],"type":"Point"}
}