{
  "type": "Feature",
  "properties": {
    "addr:full":"3385 Forest Glade Dr Windsor ON N8R 2E1",
    "addr:housenumber":"3385",
    "addr:postcode":"n8r 2e1",
    "addr:street":"Forest Glade Dr",
    "iso:country":"CA",
    "sg:address":"3385 Forest Glade Dr",
    "sg:city":"Windsor",
    "sg:classifiers":[
        {
            "category":"Organizations",
            "subcategory":"Religious Organization",
            "type":"Services"
        }
    ],
    "sg:phone":"+1 519 735 6200",
    "sg:postcode":"N8R 2E1",
    "sg:province":"ON",
    "sg:tags":[
        "church"
    ],
    "wof:name":"Forest Glade Baptist Church",
    "wof:placetype":"venue"
},
  "geometry": {"coordinates":[-82.9185638428,42.3012199402],"type":"Point"}
}