{
  "type": "Feature",
  "properties": {
    "addr:full":"114 Rue DE L'Hotel-DE-Ville Riviere-Du-Loup QC G5R 1M2",
    "addr:housenumber":"114",
    "addr:postcode":"g5r 1m2",
    "addr:street":"Rue De L'Hotel-De-Ville Riviere-Du-Loup",
    "iso:country":"CA",
    "sg:address":"114 Rue DE L'Hotel-DE-Ville",
    "sg:city":"Riviere-Du-Loup",
    "sg:classifiers":[
        {
            "category":"Building & Trades",
            "subcategory":"Cleaning & Sanitation",
            "type":"Services"
        }
    ],
    "sg:phone":"+1 418 867 1346",
    "sg:postcode":"G5R 1M2",
    "sg:province":"QC",
    "sg:tags":[
        "venetian",
        "blind"
    ],
    "wof:name":"Store Mag Inc",
    "wof:placetype":"venue"
},
  "geometry": {"coordinates":[-69.5353088379,47.8369369507],"type":"Point"}
}