{
  "type": "Feature",
  "properties": {
    "addr:full":"St Catharines ON L2N 5B6",
    "addr:postcode":"l2n 5b6",
    "iso:country":"CA",
    "sg:city":"St Catharines",
    "sg:classifiers":[
        {
            "category":"Health Services",
            "subcategory":"Doctor",
            "type":"Services"
        }
    ],
    "sg:phone":"+1 905 937 1515",
    "sg:postcode":"L2N 5B6",
    "sg:province":"ON",
    "sg:tags":[
        "dentist"
    ],
    "wof:name":"Dr Frank W Kordoy & Assoc",
    "wof:placetype":"venue"
},
  "geometry": {"coordinates":[-79.266586,43.202251],"type":"Point"}
}