{
  "type": "Feature",
  "properties": {
    "addr:full":"Gagetown NB E5M 1K1",
    "addr:postcode":"e5m 1k1",
    "iso:country":"CA",
    "sg:city":"Gagetown",
    "sg:classifiers":[
        {
            "category":"Wholesale",
            "subcategory":"Construction Materials",
            "type":"Manufacturing & Wholesale Goods"
        }
    ],
    "sg:phone":"+1 506 488 2867",
    "sg:postcode":"E5M 1K1",
    "sg:province":"NB",
    "sg:tags":[
        "sand",
        "gravel",
        "septic"
    ],
    "wof:name":"A Laws & Sons Ltd",
    "wof:placetype":"venue"
},
  "geometry": {"coordinates":[-66.166519165,45.7784042358],"type":"Point"}
}