{
  "type": "Feature",
  "properties": {
    "addr:full":"3314 17 Ave SW Medicine Hat AB T1B 4B2",
    "addr:housenumber":"3314",
    "addr:postcode":"t1b 4b2",
    "addr:street":"17 Ave Sw",
    "iso:country":"CA",
    "sg:address":"3314 17 Ave SW",
    "sg:city":"Medicine Hat",
    "sg:classifiers":[
        {
            "category":"Bus Charters",
            "type":"Transportation"
        }
    ],
    "sg:phone":"+1 403 527 6986",
    "sg:postcode":"T1B 4B2",
    "sg:province":"AB",
    "sg:tags":[
        "line",
        "rental"
    ],
    "wof:name":"Tot-Em Transportation Ltd",
    "wof:placetype":"venue"
},
  "geometry": {"coordinates":[-110.725098,50.006851],"type":"Point"}
}