{
  "type": "Feature",
  "properties": {
    "iso:country":"CA",
    "sg:address":"1545 3rd Ave W",
    "sg:city":"Vancouver",
    "sg:classifiers":[
        {
            "category":"Restaurant",
            "type":"Food & Drink"
        }
    ],
    "sg:phone":"+1 604 875 0126",
    "sg:postcode":"V6J 1J8",
    "sg:province":"BC",
    "sg:tags":[
        "caterer"
    ],
    "wof:name":"Best of the West Bbq",
    "wof:placetype":"venue"
},
  "geometry": {"coordinates":[-123.139732,49.268993],"type":"Point"}
}