{
  "type": "Feature",
  "properties": {
    "addr:full":"Halifax NS B3J 1N9",
    "addr:postcode":"ns b3j 1n9",
    "iso:country":"CA",
    "sg:city":"Halifax",
    "sg:classifiers":[
        {
            "category":"Shopping",
            "subcategory":"Clothing, Apparel, & Fashions",
            "type":"Retail Goods"
        }
    ],
    "sg:phone":"+1 902 429 6691",
    "sg:postcode":"B3J 1N9",
    "sg:province":"NS",
    "wof:name":"Jay Set",
    "wof:placetype":"venue"
},
  "geometry": {"coordinates":[-63.575245,44.649273],"type":"Point"}
}