{
  "type": "Feature",
  "properties": {
    "addr:full":"11 Vulcan St Etobicoke ON M9W 1L3",
    "addr:housenumber":"11",
    "addr:postcode":"m9w 1l3",
    "addr:street":"Vulcan St",
    "iso:country":"CA",
    "sg:address":"11 Vulcan St",
    "sg:city":"Etobicoke",
    "sg:classifiers":[
        {
            "category":"Wholesale",
            "subcategory":"Machinery & Supplies",
            "type":"Manufacturing & Wholesale Goods"
        }
    ],
    "sg:phone":"+1 416 248 2040",
    "sg:postcode":"M9W 1L3",
    "sg:province":"ON",
    "sg:tags":[
        "salon",
        "beauty"
    ],
    "wof:name":"Magna Esthetics Supply Inc",
    "wof:placetype":"venue"
},
  "geometry": {"coordinates":[-79.578506,43.704773],"type":"Point"}
}