{
  "type": "Feature",
  "properties": {
    "iso:country":"CA",
    "sg:address":"2212 Coleman Rd",
    "sg:city":"Courtenay",
    "sg:classifiers":[
        {
            "category":"Building & Trades",
            "subcategory":"Electrical",
            "type":"Services"
        }
    ],
    "sg:phone":"+1 250 334 3573",
    "sg:postcode":"V9J 1T8",
    "sg:province":"BC",
    "sg:tags":[
        "electric",
        "contractor"
    ],
    "wof:name":"Montgomery Electric Ltd",
    "wof:placetype":"venue"
},
  "geometry": {"coordinates":[-124.993141174,49.6867218018],"type":"Point"}
}