{
  "type": "Feature",
  "properties": {
    "addr:full":"115 Hurontario St Collingwood ON L9Y 2L9",
    "addr:housenumber":"115",
    "addr:postcode":"l9y 2l9",
    "addr:street":"Hurontario St",
    "iso:country":"CA",
    "sg:address":"115 Hurontario St",
    "sg:city":"Collingwood",
    "sg:classifiers":[
        {
            "category":"Professional",
            "subcategory":"Accounting & Tax Preparation",
            "type":"Services"
        }
    ],
    "sg:phone":"+1 705 445 2020",
    "sg:postcode":"L9Y 2L9",
    "sg:province":"ON",
    "sg:tags":[
        "accountant"
    ],
    "wof:name":"Gaviller & CO",
    "wof:placetype":"venue"
},
  "geometry": {"coordinates":[-80.2166442871,44.4999313354],"type":"Point"}
}