{
  "type": "Feature",
  "properties": {
    "addr:full":"2032 Hastings St E Vancouver BC V5L 1T8",
    "addr:housenumber":"2032",
    "addr:postcode":"v5l 1t8",
    "addr:street":"Hastings St E",
    "iso:country":"CA",
    "sg:address":"2032 Hastings St E",
    "sg:city":"Vancouver",
    "sg:classifiers":[
        {
            "category":"Autos & Motor Vehicles",
            "subcategory":"Auto Supplies",
            "type":"Retail Goods"
        }
    ],
    "sg:phone":"+1 604 253 2203",
    "sg:postcode":"V5L 1T8",
    "sg:province":"BC",
    "sg:tags":[
        "tire"
    ],
    "wof:name":"Tire Town Auto Svc Ltd",
    "wof:placetype":"venue"
},
  "geometry": {"coordinates":[-123.062904,49.280994],"type":"Point"}
}