{
  "type": "Feature",
  "properties": {
    "addr:full":"2828 32 Ave NE Calgary AB T1Y 5J4",
    "addr:housenumber":"2828",
    "addr:postcode":"t1y 5j4",
    "addr:street":"32 Ave Ne",
    "iso:country":"CA",
    "sg:address":"2828 32 Ave NE",
    "sg:city":"Calgary",
    "sg:classifiers":[
        {
            "category":"Wholesale",
            "subcategory":"Hardware",
            "type":"Manufacturing & Wholesale Goods"
        }
    ],
    "sg:phone":"+1 403 250 6683",
    "sg:postcode":"T1Y 5J4",
    "sg:province":"AB",
    "sg:tags":[
        "machine",
        "tool"
    ],
    "wof:name":"House of Tools Ltd",
    "wof:placetype":"venue"
},
  "geometry": {"coordinates":[-113.992935,51.081692],"type":"Point"}
}