{
  "type": "Feature",
  "properties": {
    "addr:full":"Thorhild AB T0A 3J0",
    "addr:postcode":"t0a 3j0",
    "iso:country":"CA",
    "sg:city":"Thorhild",
    "sg:classifiers":[
        {
            "category":"Food & Beverages",
            "subcategory":"Groceries & Convenience Stores",
            "type":"Retail Goods"
        }
    ],
    "sg:phone":"+1 780 398 2700",
    "sg:postcode":"T0A 3J0",
    "sg:province":"AB",
    "sg:tags":[
        "grocer"
    ],
    "wof:name":"Corner Store",
    "wof:placetype":"venue"
},
  "geometry": {"coordinates":[-113.124305725,54.1586303711],"type":"Point"}
}