{
  "type": "Feature",
  "properties": {
    "addr:full":"576 12th St W Prince Albert SK S6V 3C2",
    "addr:housenumber":"576",
    "addr:postcode":"s6v 3c2",
    "addr:street":"12Th St",
    "iso:country":"CA",
    "sg:address":"576 12th St W",
    "sg:city":"Prince Albert",
    "sg:classifiers":[
        {
            "category":"Personal",
            "type":"Services"
        }
    ],
    "sg:phone":"+1 306 922 2600",
    "sg:postcode":"S6V 3C2",
    "sg:province":"SK",
    "sg:tags":[
        "electrolysis"
    ],
    "wof:name":"Electrolysis Plus",
    "wof:placetype":"venue"
},
  "geometry": {"coordinates":[-105.76905059800001,53.2019424438],"type":"Point"}
}