{
  "type": "Feature",
  "properties": {
    "addr:full":"PO Box 277 STN Main Vernon BC V1T 6M2",
    "addr:housenumber":"po",
    "addr:postcode":"v1t 6m2",
    "addr:street":"Box 277 Stn Main",
    "iso:country":"CA",
    "sg:address":"PO Box 277 STN Main",
    "sg:city":"Vernon",
    "sg:classifiers":[
        {
            "category":"Building & Trades",
            "subcategory":"Landscaping Services",
            "type":"Services"
        }
    ],
    "sg:phone":"+1 250 549 1908",
    "sg:postcode":"V1T 6M2",
    "sg:province":"BC",
    "sg:tags":[
        "tree"
    ],
    "wof:name":"Supergreen Lawn & Tree Care",
    "wof:placetype":"venue"
},
  "geometry": {"coordinates":[-119.273803711,50.2656860352],"type":"Point"}
}