{
  "type": "Feature",
  "properties": {
    "addr:full":"526 Taylor St Wiarton ON N0H 2T0",
    "addr:housenumber":"526",
    "addr:postcode":"n0h 2t0",
    "addr:street":"Taylor St",
    "iso:country":"CA",
    "sg:address":"526 Taylor St",
    "sg:city":"Wiarton",
    "sg:classifiers":[
        {
            "category":"Arena",
            "subcategory":"Sports Club",
            "type":"Entertainment"
        }
    ],
    "sg:phone":"+1 519 534 2891",
    "sg:postcode":"N0H 2T0",
    "sg:province":"ON",
    "sg:tags":[
        "athletic",
        "fields",
        "stadium",
        "government"
    ],
    "wof:name":"Wiarton Arena",
    "wof:placetype":"venue"
},
  "geometry": {"coordinates":[-81.133774,44.741131],"type":"Point"}
}