{
  "type": "Feature",
  "properties": {
    "iso:country":"CA",
    "sg:address":"7403 Rue Saint-Hubert",
    "sg:city":"Montreal",
    "sg:classifiers":[
        {
            "category":"Shopping",
            "subcategory":"Shoes",
            "type":"Retail Goods"
        }
    ],
    "sg:phone":"+1 514 277 6622",
    "sg:postcode":"H2R 2N4",
    "sg:province":"QC",
    "wof:name":"Kin Prestige",
    "wof:placetype":"venue"
},
  "geometry": {"coordinates":[-73.61628,45.542305],"type":"Point"}
}