{
  "type": "Feature",
  "properties": {
    "addr:full":"5214 Kingsway Burnaby BC V5H 2E9",
    "addr:housenumber":"5214",
    "addr:postcode":"v5h 2e9",
    "addr:street":"Kingsway",
    "iso:country":"CA",
    "sg:address":"5214 Kingsway",
    "sg:city":"Burnaby",
    "sg:classifiers":[
        {
            "category":"Cinema",
            "subcategory":"Movie Rental",
            "type":"Entertainment"
        }
    ],
    "sg:phone":"+1 604 431 9931",
    "sg:postcode":"V5H 2E9",
    "sg:province":"BC",
    "sg:tags":[
        "compact",
        "leasing",
        "record",
        "disc",
        "video",
        "tape"
    ],
    "wof:name":"Star Video & Music",
    "wof:placetype":"venue"
},
  "geometry": {"coordinates":[-122.988418579,49.2247085571],"type":"Point"}
}