{
  "type": "Feature",
  "properties": {
    "iso:country":"CA",
    "sg:address":"201 Front St",
    "sg:city":"Belleville",
    "sg:classifiers":[
        {
            "category":"Banks & Credit Unions",
            "subcategory":"Bank",
            "type":"Services"
        }
    ],
    "sg:phone":"+1 613 967 4300",
    "sg:postcode":"K8N 5A4",
    "sg:province":"ON",
    "wof:name":"Bank of Montreal",
    "wof:placetype":"venue"
},
  "geometry": {"coordinates":[-77.3839874268,44.1637954712],"type":"Point"}
}