{
  "type": "Feature",
  "properties": {
    "addr:full":"4100 Rue Jean-Marchand Quebec QC G2C 1Y6",
    "addr:housenumber":"4100",
    "addr:postcode":"qc g2c 1y6",
    "addr:street":"Rue Jean-Marchand",
    "iso:country":"CA",
    "sg:address":"4100 Rue Jean-Marchand",
    "sg:city":"Quebec",
    "sg:classifiers":[
        {
            "category":"Manufacturing",
            "subcategory":"Tools & Machinery",
            "type":"Manufacturing & Wholesale Goods"
        }
    ],
    "sg:phone":"+1 418 845 0666",
    "sg:postcode":"G2C 1Y6",
    "sg:province":"QC",
    "sg:tags":[
        "machine",
        "shop"
    ],
    "wof:name":"Queloz & Assoc",
    "wof:placetype":"venue"
},
  "geometry": {"coordinates":[-71.3403015137,46.8249435425],"type":"Point"}
}