{
  "type": "Feature",
  "properties": {
    "iso:country":"CA",
    "sg:city":"North York",
    "sg:classifiers":[
        {
            "category":"Manufacturing",
            "subcategory":"Metals",
            "type":"Manufacturing & Wholesale Goods"
        }
    ],
    "sg:phone":"+1 416 740 9567",
    "sg:postcode":"M3N 1H8",
    "sg:province":"ON",
    "sg:tags":[
        "finisher"
    ],
    "wof:name":"Topkote Design Finishes",
    "wof:placetype":"venue"
},
  "geometry": {"coordinates":[-79.523972,43.747108],"type":"Point"}
}