{
  "type": "Feature",
  "properties": {
    "addr:full":"4170 Rue Roberval Cap-Rouge QC G1Y 1T1",
    "addr:housenumber":"4170",
    "addr:postcode":"g1y 1t1",
    "addr:street":"Rue Roberval",
    "iso:country":"CA",
    "sg:address":"4170 Rue Roberval",
    "sg:city":"Cap-Rouge",
    "sg:classifiers":[
        {
            "category":"Recreation",
            "type":"Entertainment"
        }
    ],
    "sg:phone":"+1 418 650 7776",
    "sg:postcode":"G1Y 1T1",
    "sg:province":"QC",
    "sg:tags":[
        "provincial",
        "center",
        "parks"
    ],
    "wof:name":"Cap-Rouge Parc Provancher",
    "wof:placetype":"venue"
},
  "geometry": {"coordinates":[-71.3443069458,46.7507019043],"type":"Point"}
}