{
  "type": "Feature",
  "properties": {
    "addr:full":"12 Carrying Place Rd Trenton ON K8V 3E7",
    "addr:housenumber":"12",
    "addr:postcode":"k8v 3e7",
    "addr:street":"Carrying Place Rd",
    "iso:country":"CA",
    "sg:address":"12 Carrying Place Rd",
    "sg:city":"Trenton",
    "sg:classifiers":[
        {
            "category":"Retail",
            "subcategory":"Animal Services",
            "type":"Services"
        }
    ],
    "sg:phone":"+1 613 392 7087",
    "sg:postcode":"K8V 3E7",
    "sg:province":"ON",
    "sg:tags":[
        "pet",
        "grooming",
        "washing"
    ],
    "wof:name":"Crazy Dogs Pet Styling Salon",
    "wof:placetype":"venue"
},
  "geometry": {"coordinates":[-77.57952899999999,44.087914],"type":"Point"}
}