{
  "type": "Feature",
  "properties": {
    "addr:full":"251 Rue Bellemare Yamachiche QC G0X 3L0",
    "addr:housenumber":"251",
    "addr:postcode":"g0x 3l0",
    "addr:street":"Rue Bellemare",
    "iso:country":"CA",
    "sg:address":"251 Rue Bellemare",
    "sg:city":"Yamachiche",
    "sg:classifiers":[
        {
            "category":"Manufacturing",
            "subcategory":"Metals",
            "type":"Manufacturing & Wholesale Goods"
        }
    ],
    "sg:phone":"+1 819 296 2415",
    "sg:postcode":"G0X 3L0",
    "sg:province":"QC",
    "sg:tags":[
        "steel",
        "solder"
    ],
    "wof:name":"Structure D'Acier Desilets Inc",
    "wof:placetype":"venue"
},
  "geometry": {"coordinates":[-72.84390999999999,46.280113],"type":"Point"}
}