{
  "type": "Feature",
  "properties": {
    "iso:country":"CA",
    "sg:address":"6520 Rue Beaubien E",
    "sg:city":"Montreal",
    "sg:classifiers":[
        {
            "category":"Professional",
            "subcategory":"Computer Services",
            "type":"Services"
        }
    ],
    "sg:phone":"+1 514 899 1998",
    "sg:postcode":"H1M 1A9",
    "sg:province":"QC",
    "sg:tags":[
        "information",
        "system",
        "consultant"
    ],
    "wof:name":"Hde Informatique Ltee",
    "wof:placetype":"venue"
},
  "geometry": {"coordinates":[-73.561325,45.586704],"type":"Point"}
}