{
  "type": "Feature",
  "properties": {
    "addr:full":"5333 Rue Saint-Jacques Montreal QC H4A 2C9",
    "addr:housenumber":"5333",
    "addr:postcode":"h4a 2c9",
    "addr:street":"Rue Saint-Jacques",
    "iso:country":"CA",
    "sg:address":"5333 Rue Saint-Jacques",
    "sg:city":"Montreal",
    "sg:classifiers":[
        {
            "category":"Autos & Motor Vehicles",
            "subcategory":"Automobile Sales",
            "type":"Retail Goods"
        }
    ],
    "sg:phone":"+1 514 484 7777",
    "sg:postcode":"H4A 2C9",
    "sg:province":"QC",
    "sg:tags":[
        "car",
        "dealer"
    ],
    "wof:name":"Mazda Gabriel",
    "wof:placetype":"venue"
},
  "geometry": {"coordinates":[-73.601906,45.470894],"type":"Point"}
}