{
  "type": "Feature",
  "properties": {
    "addr:full":"9632 54 Ave NW Edmonton AB T6E 5V1",
    "addr:housenumber":"9632",
    "addr:postcode":"t6e 5v1",
    "addr:street":"54 Ave Nw",
    "iso:country":"CA",
    "sg:address":"9632 54 Ave NW",
    "sg:city":"Edmonton",
    "sg:classifiers":[
        {
            "category":"Professional",
            "subcategory":"Research",
            "type":"Services"
        }
    ],
    "sg:phone":"+1 780 438 2540",
    "sg:postcode":"T6E 5V1",
    "sg:province":"AB",
    "sg:tags":[
        "environmental",
        "ecological",
        "engineer"
    ],
    "wof:name":"Shelby Engineering Ltd",
    "wof:placetype":"venue"
},
  "geometry": {"coordinates":[-113.477951,53.48978],"type":"Point"}
}