{
  "type": "Feature",
  "properties": {
    "iso:country":"CA",
    "sg:city":"Placentia",
    "sg:classifiers":[
        {
            "category":"Building & Trades",
            "subcategory":"Plumbing",
            "type":"Services"
        }
    ],
    "sg:phone":"+1 709 227 2727",
    "sg:postcode":"A0B 2Y0",
    "sg:province":"NL",
    "sg:tags":[
        "septic"
    ],
    "wof:name":"Argentia Industrial Svc",
    "wof:placetype":"venue"
},
  "geometry": {"coordinates":[-53.9622192383,47.2540740967],"type":"Point"}
}