{
  "type": "Feature",
  "properties": {
    "addr:full":"136 Rue Church #A Grand-Sault/Grand Falls NB E3Z 2N9",
    "addr:housenumber":"136",
    "addr:postcode":"e3z 2n9",
    "addr:street":"Rue Church # A Grand-Sault",
    "iso:country":"CA",
    "sg:address":"136 Rue Church #A",
    "sg:city":"Grand-Sault/Grand Falls",
    "sg:classifiers":[
        {
            "category":"Social Services",
            "type":"Services"
        }
    ],
    "sg:phone":"+1 506 473 5897",
    "sg:postcode":"E3Z 2N9",
    "sg:province":"NB",
    "sg:tags":[
        "organization",
        "welfare"
    ],
    "wof:name":"Croix Rouge Canadienne",
    "wof:placetype":"venue"
},
  "geometry": {"coordinates":[-67.73919677729999,47.0471458435],"type":"Point"}
}