{
  "type": "Feature",
  "properties": {
    "addr:full":"Richmond Hill ON L4C 8S7",
    "addr:postcode":"l4c 8s7",
    "iso:country":"CA",
    "sg:city":"Richmond Hill",
    "sg:classifiers":[
        {
            "category":"Retail",
            "subcategory":"Laundry & Dry Cleaning",
            "type":"Services"
        }
    ],
    "sg:phone":"+1 905 883 4265",
    "sg:postcode":"L4C 8S7",
    "sg:province":"ON",
    "sg:tags":[
        "cleaners"
    ],
    "wof:name":"Network Cleaners",
    "wof:placetype":"venue"
},
  "geometry": {"coordinates":[-79.435631,43.865044],"type":"Point"}
}