{
  "type": "Feature",
  "properties": {
    "iso:country":"CA",
    "sg:address":"2808 Perry Ave",
    "sg:city":"Brechin",
    "sg:classifiers":[
        {
            "category":"Building & Trades",
            "subcategory":"Cleaning & Sanitation",
            "type":"Services"
        }
    ],
    "sg:phone":"+1 705 484 5844",
    "sg:postcode":"L0K 1B0",
    "sg:province":"ON",
    "sg:tags":[
        "house"
    ],
    "wof:name":"Dust Till Dawn Cleaning",
    "wof:placetype":"venue"
},
  "geometry": {"coordinates":[-79.17636899999999,44.549751],"type":"Point"}
}