{
  "type": "Feature",
  "properties": {
    "addr:full":"27 Walnut St W Omemee ON K0L 2W0",
    "addr:housenumber":"27",
    "addr:postcode":"k0l 2w0",
    "addr:street":"Walnut St W Omemee",
    "iso:country":"CA",
    "sg:address":"27 Walnut St W",
    "sg:city":"Omemee",
    "sg:classifiers":[
        {
            "category":"Education",
            "subcategory":"School",
            "type":"Public Place"
        }
    ],
    "sg:phone":"+1 705 799 5133",
    "sg:postcode":"K0L 2W0",
    "sg:province":"ON",
    "wof:name":"Scott Young Public School",
    "wof:placetype":"venue"
},
  "geometry": {"coordinates":[-78.5704193115,44.2978286743],"type":"Point"}
}