{
  "type": "Feature",
  "properties": {
    "addr:full":"15 Rue Vezina L'Ange Gardien QC G0A 2K0",
    "addr:housenumber":"15",
    "addr:postcode":"g0a 2k0",
    "addr:street":"Rue Vezina",
    "iso:country":"CA",
    "sg:address":"15 Rue Vezina",
    "sg:city":"L'Ange Gardien",
    "sg:classifiers":[
        {
            "category":"Building & Trades",
            "subcategory":"Cleaning & Sanitation",
            "type":"Services"
        }
    ],
    "sg:phone":"+1 418 822 0311",
    "sg:postcode":"G0A 2K0",
    "sg:province":"QC",
    "sg:tags":[
        "fireplace",
        "chimney"
    ],
    "wof:name":"Entreprises Gilbert Marchand",
    "wof:placetype":"venue"
},
  "geometry": {"coordinates":[-71.0812301636,46.9208908081],"type":"Point"}
}