{
  "type": "Feature",
  "properties": {
    "iso:country":"CA",
    "sg:city":"Parrsboro",
    "sg:classifiers":[
        {
            "category":"Government",
            "subcategory":"Office",
            "type":"Public Place"
        }
    ],
    "sg:phone":"+1 902 254 3241",
    "sg:postcode":"B0M 1S0",
    "sg:province":"NS",
    "wof:name":"Nova Scotia Natural Resources",
    "wof:placetype":"venue"
},
  "geometry": {"coordinates":[-64.3259429932,45.4061546326],"type":"Point"}
}