{
  "type": "Feature",
  "properties": {
    "iso:country":"CA",
    "sg:address":"32 5th St SE",
    "sg:city":"Portage LA Prairie",
    "sg:classifiers":[
        {
            "category":"Education",
            "subcategory":"School",
            "type":"Public Place"
        }
    ],
    "sg:phone":"+1 204 857 8746",
    "sg:postcode":"R1N 1J2",
    "sg:province":"MB",
    "wof:name":"Victoria School",
    "wof:placetype":"venue"
},
  "geometry": {"coordinates":[-98.282776,49.971462],"type":"Point"}
}