{
  "type": "Feature",
  "properties": {
    "iso:country":"CA",
    "sg:address":"4250 Canada Way",
    "sg:city":"Burnaby",
    "sg:classifiers":[
        {
            "category":"Insurance",
            "subcategory":"Insurance Agent",
            "type":"Services"
        }
    ],
    "sg:phone":"+1 604 419 8000",
    "sg:postcode":"V5G 4W6",
    "sg:province":"BC",
    "wof:name":"B C Life & Casualty CO",
    "wof:placetype":"venue"
},
  "geometry": {"coordinates":[-123.01018524200001,49.2545433044],"type":"Point"}
}