{
  "type": "Feature",
  "properties": {
    "addr:full":"516 Alexander St Vancouver BC V6A 1C7",
    "addr:housenumber":"516",
    "addr:postcode":"v6a 1c7",
    "addr:street":"Alexander St",
    "iso:country":"CA",
    "sg:address":"516 Alexander St",
    "sg:city":"Vancouver",
    "sg:classifiers":[
        {
            "category":"Wholesale",
            "subcategory":"Machinery & Supplies",
            "type":"Manufacturing & Wholesale Goods"
        }
    ],
    "sg:phone":"+1 604 251 2676",
    "sg:postcode":"V6A 1C7",
    "sg:province":"BC",
    "sg:tags":[
        "cleaning"
    ],
    "wof:name":"NU-Style Exteriors Inc",
    "wof:placetype":"venue"
},
  "geometry": {"coordinates":[-123.092766,49.283855],"type":"Point"}
}