{
  "type": "Feature",
  "properties": {
    "addr:full":"Brampton ON L6S 3L7",
    "addr:postcode":"l6s 3l7",
    "iso:country":"CA",
    "sg:city":"Brampton",
    "sg:classifiers":[
        {
            "category":"Personal",
            "subcategory":"Beauty Salon",
            "type":"Services"
        }
    ],
    "sg:phone":"+1 905 791 4589",
    "sg:postcode":"L6S 3L7",
    "sg:province":"ON",
    "wof:name":"Hair Locks",
    "wof:placetype":"venue"
},
  "geometry": {"coordinates":[-79.71974945069999,43.733379364],"type":"Point"}
}