{
  "type": "Feature",
  "properties": {
    "addr:full":"Moncton NB E1C 7H1",
    "addr:postcode":"e1c 7h1",
    "iso:country":"CA",
    "sg:city":"Moncton",
    "sg:classifiers":[
        {
            "category":"Wholesale",
            "subcategory":"Machinery & Supplies",
            "type":"Manufacturing & Wholesale Goods"
        }
    ],
    "sg:phone":"+1 506 382 8665",
    "sg:postcode":"E1C 7H1",
    "sg:province":"NB",
    "sg:tags":[
        "equipment",
        "hoist",
        "hydraulic"
    ],
    "wof:name":"Maritime Tool Repair Ltd",
    "wof:placetype":"venue"
},
  "geometry": {"coordinates":[-64.80796051030001,46.0978889465],"type":"Point"}
}