{
  "type": "Feature",
  "properties": {
    "iso:country":"CA",
    "sg:city":"Toronto",
    "sg:classifiers":[
        {
            "category":"Organizations",
            "subcategory":"Non-profit Organization",
            "type":"Services"
        }
    ],
    "sg:phone":"+1 416 961 4161",
    "sg:postcode":"M4Y 1Z3",
    "sg:province":"ON",
    "sg:tags":[
        "book",
        "lesbian",
        "gay",
        "dealer"
    ],
    "wof:name":"Glad Day Bookshop",
    "wof:placetype":"venue"
},
  "geometry": {"coordinates":[-79.38497161870001,43.6654472351],"type":"Point"}
}