{
  "type": "Feature",
  "properties": {
    "iso:country":"CA",
    "sg:city":"London",
    "sg:classifiers":[
        {
            "category":"Food & Beverages",
            "subcategory":"Groceries & Convenience Stores",
            "type":"Retail Goods"
        }
    ],
    "sg:phone":"+1 519 850 0850",
    "sg:postcode":"N6G 3Y9",
    "sg:province":"ON",
    "sg:tags":[
        "product"
    ],
    "wof:name":"Bulk Barn Foods",
    "wof:placetype":"venue"
},
  "geometry": {"coordinates":[-81.281708,43.025272],"type":"Point"}
}