{
  "type": "Feature",
  "properties": {
    "iso:country":"CA",
    "sg:address":"Riverside Dr",
    "sg:city":"St Lawrence",
    "sg:classifiers":[
        {
            "category":"Social Services",
            "type":"Services"
        }
    ],
    "sg:phone":"+1 709 873 2022",
    "sg:postcode":"A0E 2V0",
    "sg:province":"NL",
    "sg:tags":[
        "senior",
        "citizen"
    ],
    "wof:name":"Golden Age Senior Citizens",
    "wof:placetype":"venue"
},
  "geometry": {"coordinates":[-55.3921356201,46.924495697],"type":"Point"}
}