{
  "type": "Feature",
  "properties": {
    "addr:full":"Revelstoke BC V0E 2S0",
    "addr:postcode":"v0e 2s0",
    "iso:country":"CA",
    "sg:city":"Revelstoke",
    "sg:classifiers":[
        {
            "category":"Building & Trades",
            "subcategory":"Electrical",
            "type":"Services"
        }
    ],
    "sg:phone":"+1 250 837 4174",
    "sg:postcode":"V0E 2S0",
    "sg:province":"BC",
    "sg:tags":[
        "electric",
        "contractor"
    ],
    "wof:name":"Canyon Industrial Electrical",
    "wof:placetype":"venue"
},
  "geometry": {"coordinates":[-118.189194,50.989414],"type":"Point"}
}