{
  "type": "Feature",
  "properties": {
    "addr:full":"4390 Government St Hazelton BC V0J 1Y0",
    "addr:housenumber":"4390",
    "addr:postcode":"v0j 1y0",
    "addr:street":"Government St",
    "iso:country":"CA",
    "sg:address":"4390 Government St",
    "sg:city":"Hazelton",
    "sg:classifiers":[
        {
            "category":"Organizations",
            "subcategory":"Religious Organization",
            "type":"Services"
        }
    ],
    "sg:phone":"+1 250 842 5222",
    "sg:postcode":"V0J 1Y0",
    "sg:province":"BC",
    "sg:tags":[
        "church"
    ],
    "wof:name":"Anglican Church of Canada",
    "wof:placetype":"venue"
},
  "geometry": {"coordinates":[-127.643867,55.264259],"type":"Point"}
}