{
  "type": "Feature",
  "properties": {
    "addr:full":"1990 Ogilvie St S # 140 Prince George BC V2N 1X1",
    "addr:housenumber":"1990",
    "addr:postcode":"v2n 1x1",
    "addr:street":"Ogilvie St S # 140",
    "iso:country":"CA",
    "sg:address":"1990 Ogilvie St S # 140",
    "sg:city":"Prince George",
    "sg:classifiers":[
        {
            "category":"Home & Garden",
            "subcategory":"Carpets & Floor Coverings",
            "type":"Retail Goods"
        }
    ],
    "sg:phone":"+1 250 563 4844",
    "sg:postcode":"V2N 1X1",
    "sg:province":"BC",
    "sg:tags":[
        "resurfacing",
        "laying",
        "refinishing",
        "rug"
    ],
    "wof:name":"P G Floor Fashions Ltd",
    "wof:placetype":"venue"
},
  "geometry": {"coordinates":[-122.788994,53.906044],"type":"Point"}
}