{
  "type": "Feature",
  "properties": {
    "iso:country":"CA",
    "sg:address":"42 Main St",
    "sg:city":"Manor",
    "sg:classifiers":[
        {
            "category":"Restaurant",
            "type":"Food & Drink"
        }
    ],
    "sg:phone":"+1 306 448 2154",
    "sg:postcode":"S0C 1R0",
    "sg:province":"SK",
    "wof:name":"Manor Restaurant",
    "wof:placetype":"venue"
},
  "geometry": {"coordinates":[-102.084686279,49.6100463867],"type":"Point"}
}