{
  "type": "Feature",
  "properties": {
    "addr:full":"Sainte-Marthe-Sur-Le-Lac QC J0N 1P0",
    "addr:postcode":"j0n 1p0",
    "iso:country":"CA",
    "sg:city":"Sainte-Marthe-Sur-Le-Lac",
    "sg:classifiers":[
        {
            "category":"Education",
            "subcategory":"Library",
            "type":"Public Place"
        }
    ],
    "sg:phone":"+1 450 974 7111",
    "sg:postcode":"J0N 1P0",
    "sg:province":"QC",
    "wof:name":"Ste-Marthe-Sur-Le-Lac Biblio",
    "wof:placetype":"venue"
},
  "geometry": {"coordinates":[-73.963188,45.523239],"type":"Point"}
}