{
  "type": "Feature",
  "properties": {
    "addr:full":"728 York Rd Guelph ON N1E 6A5",
    "addr:housenumber":"728",
    "addr:postcode":"n1e 6a5",
    "addr:street":"York Rd",
    "iso:country":"CA",
    "sg:address":"728 York Rd",
    "sg:city":"Guelph",
    "sg:classifiers":[
        {
            "category":"Restaurant",
            "type":"Food & Drink"
        }
    ],
    "sg:phone":"+1 519 763 7830",
    "sg:postcode":"N1E 6A5",
    "sg:province":"ON",
    "wof:name":"Elks Den",
    "wof:placetype":"venue"
},
  "geometry": {"coordinates":[-80.21705627439999,43.5570678711],"type":"Point"}
}