{
  "type": "Feature",
  "properties": {
    "iso:country":"CA",
    "sg:address":"19107 Seagram Rd 112N",
    "sg:city":"Gimli",
    "sg:classifiers":[
        {
            "category":"Manufacturing",
            "subcategory":"Food",
            "type":"Manufacturing & Wholesale Goods"
        }
    ],
    "sg:phone":"+1 204 642 5123",
    "sg:postcode":"R0C 1B0",
    "sg:province":"MB",
    "sg:tags":[
        "distiller"
    ],
    "wof:name":"Diageo-Gimli Plant",
    "wof:placetype":"venue"
},
  "geometry": {"coordinates":[-97.01044464109999,50.6547737122],"type":"Point"}
}