{
  "type": "Feature",
  "properties": {
    "addr:full":"10 Beechwood Cres Fonthill ON L0S 1E7",
    "addr:housenumber":"10",
    "addr:postcode":"l0s 1e7",
    "addr:street":"Beechwood Cres",
    "iso:country":"CA",
    "sg:address":"10 Beechwood Cres",
    "sg:city":"Fonthill",
    "sg:classifiers":[
        {
            "category":"Building & Trades",
            "subcategory":"Construction",
            "type":"Services"
        }
    ],
    "sg:phone":"+1 905 892 8935",
    "sg:postcode":"L0S 1E7",
    "sg:province":"ON",
    "sg:tags":[
        "contractor",
        "general"
    ],
    "wof:name":"Serafino Homes",
    "wof:placetype":"venue"
},
  "geometry": {"coordinates":[-79.2826,43.034016],"type":"Point"}
}