{
  "type": "Feature",
  "properties": {
    "addr:full":"Cap-DE-LA-Madeleine QC G8T 7B1",
    "addr:postcode":"g8t 7b1",
    "iso:country":"CA",
    "sg:city":"Cap-DE-LA-Madeleine",
    "sg:classifiers":[
        {
            "category":"Shopping",
            "subcategory":"Computers & Home Electronics",
            "type":"Retail Goods"
        }
    ],
    "sg:phone":"+1 819 371 1817",
    "sg:postcode":"G8T 7B1",
    "sg:province":"QC",
    "sg:tags":[
        "equipment",
        "dealer",
        "software"
    ],
    "wof:name":"Apex Informatique",
    "wof:placetype":"venue"
},
  "geometry": {"coordinates":[-72.554024,46.390636],"type":"Point"}
}