{
  "type": "Feature",
  "properties": {
    "addr:full":"313 3rd Ave Oyen AB T0J 2J0",
    "addr:housenumber":"313",
    "addr:postcode":"t0j 2j0",
    "addr:street":"3Rd Ave",
    "iso:country":"CA",
    "sg:address":"313 3rd Ave",
    "sg:city":"Oyen",
    "sg:classifiers":[
        {
            "category":"Health Services",
            "subcategory":"Doctor",
            "type":"Services"
        }
    ],
    "sg:phone":"+1 403 664 3774",
    "sg:postcode":"T0J 2J0",
    "sg:province":"AB",
    "sg:tags":[
        "dentist"
    ],
    "wof:name":"Oyen Dental Clinic",
    "wof:placetype":"venue"
},
  "geometry": {"coordinates":[-110.477287,51.351379],"type":"Point"}
}