{
  "type": "Feature",
  "properties": {
    "addr:full":"Farm Rosetown SK S0L 2V0",
    "addr:postcode":"s0l 2v0",
    "iso:country":"CA",
    "sg:address":"Farm",
    "sg:city":"Rosetown",
    "sg:classifiers":[
        {
            "category":"Farming",
            "subcategory":"Farm & Veterinary Services",
            "type":"Manufacturing & Wholesale Goods"
        }
    ],
    "sg:phone":"+1 306 882 4578",
    "sg:postcode":"S0L 2V0",
    "sg:province":"SK",
    "sg:tags":[
        "seed",
        "grain",
        "cleaning"
    ],
    "wof:name":"Cole Seeds",
    "wof:placetype":"venue"
},
  "geometry": {"coordinates":[-107.986946,51.550285],"type":"Point"}
}