{
  "type": "Feature",
  "properties": {
    "iso:country":"CA",
    "sg:address":"4 Ch Grenier",
    "sg:city":"Dsl DE Saint-Andre",
    "sg:classifiers":[
        {
            "category":"Home & Garden",
            "subcategory":"Garden Supply",
            "type":"Retail Goods"
        }
    ],
    "sg:phone":"+1 506 473 5510",
    "sg:postcode":"E3Y 3B1",
    "sg:province":"NB",
    "sg:tags":[
        "car",
        "lawn",
        "golf",
        "cart",
        "mower"
    ],
    "wof:name":"Fern's Golf Cars",
    "wof:placetype":"venue"
},
  "geometry": {"coordinates":[-67.75946044920001,47.105758667],"type":"Point"}
}