{
  "type": "Feature",
  "properties": {
    "iso:country":"CA",
    "sg:address":"45 Mcmurray St",
    "sg:city":"Bracebridge",
    "sg:classifiers":[
        {
            "category":"Organizations",
            "subcategory":"Religious Organization",
            "type":"Services"
        }
    ],
    "sg:phone":"+1 705 645 4521",
    "sg:postcode":"P1L 2A1",
    "sg:province":"ON",
    "sg:tags":[
        "church"
    ],
    "wof:name":"Knox Presbyterian Church",
    "wof:placetype":"venue"
},
  "geometry": {"coordinates":[-79.3145065308,45.0407104492],"type":"Point"}
}