{
  "type": "Feature",
  "properties": {
    "addr:full":"8 Rue Bridge Ormstown QC J0S 1K0",
    "addr:housenumber":"8",
    "addr:postcode":"j0s 1k0",
    "addr:street":"Rue Bridge",
    "iso:country":"CA",
    "sg:address":"8 Rue Bridge",
    "sg:city":"Ormstown",
    "sg:classifiers":[
        {
            "category":"Education",
            "subcategory":"School",
            "type":"Public Place"
        }
    ],
    "sg:phone":"+1 450 829 4221",
    "sg:postcode":"J0S 1K0",
    "sg:province":"QC",
    "wof:name":"Notre-Dame-Du-Rosaire",
    "wof:placetype":"venue"
},
  "geometry": {"coordinates":[-73.990707,45.122078],"type":"Point"}
}