{
  "type": "Feature",
  "properties": {
    "iso:country":"CA",
    "sg:address":"1621 Queensville Rd",
    "sg:city":"Queensville",
    "sg:classifiers":[
        {
            "category":"Manufacturing",
            "subcategory":"Apparel",
            "type":"Manufacturing & Wholesale Goods"
        }
    ],
    "sg:phone":"+1 905 478 8954",
    "sg:postcode":"L0G 1R0",
    "sg:province":"ON",
    "sg:tags":[
        "canvas",
        "product",
        "related"
    ],
    "wof:name":"Hobby Shop Tarp & Canvas Prods",
    "wof:placetype":"venue"
},
  "geometry": {"coordinates":[-79.4443893433,44.1400184631],"type":"Point"}
}