{
  "type": "Feature",
  "properties": {
    "iso:country":"CA",
    "sg:address":"44 Rue DE Port-Royal O",
    "sg:city":"Montreal",
    "sg:classifiers":[
        {
            "category":"Building & Trades",
            "subcategory":"Construction",
            "type":"Services"
        }
    ],
    "sg:phone":"+1 514 388 9127",
    "sg:postcode":"H3L 2A4",
    "sg:province":"QC",
    "sg:tags":[
        "excavating",
        "contractor",
        "snow",
        "removal"
    ],
    "wof:name":"Mpr Neigex Inc",
    "wof:placetype":"venue"
},
  "geometry": {"coordinates":[-73.656754,45.546631],"type":"Point"}
}