{
  "type": "Feature",
  "properties": {
    "addr:full":"44 Rue DE Port-Royal O Montreal QC H3L 2A4",
    "addr:housenumber":"44",
    "addr:postcode":"h3l 2a4",
    "addr:street":"Rue De Port-Royal O",
    "iso:country":"CA",
    "sg:address":"44 Rue DE Port-Royal O",
    "sg:city":"Montreal",
    "sg:classifiers":[
        {
            "category":"Building & Trades",
            "subcategory":"Construction",
            "type":"Services"
        }
    ],
    "sg:phone":"+1 514 388 9127",
    "sg:postcode":"H3L 2A4",
    "sg:province":"QC",
    "sg:tags":[
        "excavating",
        "contractor",
        "snow",
        "removal"
    ],
    "wof:name":"Mpr Neigex Inc",
    "wof:placetype":"venue"
},
  "geometry": {"coordinates":[-73.65675400000001,45.546631],"type":"Point"}
}