{
  "type": "Feature",
  "properties": {
    "addr:full":"157 Forbes Rd Tusket NS B0W 3M0",
    "addr:housenumber":"157",
    "addr:postcode":"b0w 3m0",
    "addr:street":"Forbes Rd",
    "iso:country":"CA",
    "sg:address":"157 Forbes Rd",
    "sg:city":"Tusket",
    "sg:classifiers":[
        {
            "category":"Manufacturing",
            "subcategory":"Food",
            "type":"Manufacturing & Wholesale Goods"
        }
    ],
    "sg:phone":"+1 902 643 2799",
    "sg:postcode":"B0W 3M0",
    "sg:province":"NS",
    "sg:tags":[
        "product",
        "seafood",
        "fish",
        "prepared"
    ],
    "wof:name":"Ocean Organic Ltd",
    "wof:placetype":"venue"
},
  "geometry": {"coordinates":[-65.976753,43.859447],"type":"Point"}
}