{
  "type": "Feature",
  "properties": {
    "addr:full":"124 Mountain Hwy North Vancouver BC V7J 2K3",
    "addr:housenumber":"124",
    "addr:postcode":"v7j 2k3",
    "addr:street":"Mountain Hwy",
    "iso:country":"CA",
    "sg:address":"124 Mountain Hwy",
    "sg:city":"North Vancouver",
    "sg:classifiers":[
        {
            "category":"Building & Trades",
            "subcategory":"Construction",
            "type":"Services"
        }
    ],
    "sg:phone":"+1 604 984 7551",
    "sg:postcode":"V7J 2K3",
    "sg:province":"BC",
    "sg:tags":[
        "repairing",
        "remodeling",
        "contractor"
    ],
    "wof:name":"Kitt Contracting Ltd",
    "wof:placetype":"venue"
},
  "geometry": {"coordinates":[-123.031898498,49.3030128479],"type":"Point"}
}