{
  "type": "Feature",
  "properties": {
    "addr:full":"1170 343 Rte Saint-Ambroise-DE-Kildare QC J0K 1C0",
    "addr:housenumber":"1170",
    "addr:postcode":"j0k 1c0",
    "addr:street":"343 Rte",
    "iso:country":"CA",
    "sg:address":"1170 343 Rte",
    "sg:city":"Saint-Ambroise-DE-Kildare",
    "sg:classifiers":[
        {
            "category":"Real Estate",
            "subcategory":"Real Estate Agent",
            "type":"Services"
        }
    ],
    "sg:phone":"+1 450 756 6927",
    "sg:postcode":"J0K 1C0",
    "sg:province":"QC",
    "sg:tags":[
        "agency",
        "rental",
        "sign"
    ],
    "wof:name":"Location D'Enseignes Dany Inc",
    "wof:placetype":"venue"
},
  "geometry": {"coordinates":[-73.55443572999999,46.0767784119],"type":"Point"}
}