{
  "type": "Feature",
  "properties": {
    "addr:full":"778 Yonge St Toronto ON M4Y 2B6",
    "addr:housenumber":"778",
    "addr:postcode":"m4y 2b6",
    "addr:street":"Yonge St",
    "iso:country":"CA",
    "sg:address":"778 Yonge St",
    "sg:city":"Toronto",
    "sg:classifiers":[
        {
            "category":"Professional",
            "subcategory":"Management & Consulting",
            "type":"Services"
        }
    ],
    "sg:phone":"+1 416 962 8868",
    "sg:postcode":"M4Y 2B6",
    "sg:province":"ON",
    "sg:tags":[
        "consultant",
        "educational"
    ],
    "wof:name":"Granada Study Inc",
    "wof:placetype":"venue"
},
  "geometry": {"coordinates":[-79.386803,43.669865],"type":"Point"}
}