{
  "type": "Feature",
  "properties": {
    "iso:country":"CA",
    "sg:city":"Beauport",
    "sg:classifiers":[
        {
            "category":"Manufacturing",
            "subcategory":"Furniture",
            "type":"Manufacturing & Wholesale Goods"
        }
    ],
    "sg:phone":"+1 418 663 1411",
    "sg:postcode":"G1E 3G1",
    "sg:province":"QC",
    "sg:tags":[
        "chair"
    ],
    "wof:name":"Industries Rouillard Inc",
    "wof:placetype":"venue"
},
  "geometry": {"coordinates":[-71.19965362550001,46.8534622192],"type":"Point"}
}