{
  "type": "Feature",
  "properties": {
    "addr:full":"Lac Du Bonnet MB R0E 1A0",
    "addr:postcode":"r0e 1a0",
    "iso:country":"CA",
    "sg:city":"Lac Du Bonnet",
    "sg:classifiers":[
        {
            "category":"Shopping",
            "subcategory":"Jewelry",
            "type":"Retail Goods"
        }
    ],
    "sg:phone":"+1 204 345 9451",
    "sg:postcode":"R0E 1A0",
    "sg:province":"MB",
    "sg:tags":[
        "jeweler"
    ],
    "wof:name":"Jewelry Arts Studio",
    "wof:placetype":"venue"
},
  "geometry": {"coordinates":[-96.061966,50.251637],"type":"Point"}
}