{
  "type": "Feature",
  "properties": {
    "addr:full":"1260 Lakeshore Rd E Mississauga ON L5E 1E9",
    "addr:housenumber":"1260",
    "addr:postcode":"l5e 1e9",
    "addr:street":"Lakeshore Rd E",
    "iso:country":"CA",
    "sg:address":"1260 Lakeshore Rd E",
    "sg:city":"Mississauga",
    "sg:classifiers":[
        {
            "category":"Restaurant",
            "type":"Food & Drink"
        }
    ],
    "sg:phone":"+1 905 274 8150",
    "sg:postcode":"L5E 1E9",
    "sg:province":"ON",
    "wof:name":"Empire Pubs Ltd",
    "wof:placetype":"venue"
},
  "geometry": {"coordinates":[-79.553078,43.582047],"type":"Point"}
}