{
  "type": "Feature",
  "properties": {
    "addr:full":"Abbotsford BC V2T 4M5",
    "addr:postcode":"v2t 4m5",
    "iso:country":"CA",
    "sg:city":"Abbotsford",
    "sg:classifiers":[
        {
            "category":"Health Services",
            "subcategory":"Doctor",
            "type":"Services"
        }
    ],
    "sg:phone":"+1 604 853 6011",
    "sg:postcode":"V2T 4M5",
    "sg:province":"BC",
    "sg:tags":[
        "dentist"
    ],
    "wof:name":"Ng, Mimi DDS",
    "wof:placetype":"venue"
},
  "geometry": {"coordinates":[-122.315055847,49.0510597229],"type":"Point"}
}