{
  "type": "Feature",
  "properties": {
    "addr:full":"9512 Alaska Rd Fort St John BC V1J 6L5",
    "addr:housenumber":"9512",
    "addr:postcode":"v1j 6l5",
    "addr:street":"Alaska Rd",
    "iso:country":"CA",
    "sg:address":"9512 Alaska Rd",
    "sg:city":"Fort St John",
    "sg:classifiers":[
        {
            "category":"Restaurant",
            "type":"Food & Drink"
        }
    ],
    "sg:phone":"+1 250 785 8336",
    "sg:postcode":"V1J 6L5",
    "sg:province":"BC",
    "wof:name":"A & W Family Restaurant",
    "wof:placetype":"venue"
},
  "geometry": {"coordinates":[-120.834473,56.233109],"type":"Point"}
}