{
  "type": "Feature",
  "properties": {
    "iso:country":"CA",
    "sg:address":"148 Book Rd W",
    "sg:city":"Ancaster",
    "sg:classifiers":[
        {
            "category":"Building & Trades",
            "subcategory":"Landscaping Services",
            "type":"Services"
        }
    ],
    "sg:phone":"+1 905 648 4511",
    "sg:postcode":"L9G 3L1",
    "sg:province":"ON",
    "sg:tags":[
        "stone",
        "interlocking",
        "landscape",
        "contractor"
    ],
    "wof:name":"K S Rogers Landscape Svc Ltd",
    "wof:placetype":"venue"
},
  "geometry": {"coordinates":[-79.9858169556,43.1827850342],"type":"Point"}
}