{
  "type": "Feature",
  "properties": {
    "iso:country":"CA",
    "sg:address":"81 Rte Du President-Kennedy",
    "sg:city":"Levis",
    "sg:classifiers":[
        {
            "category":"Shopping",
            "subcategory":"Shoes",
            "type":"Retail Goods"
        }
    ],
    "sg:phone":"+1 418 833 6872",
    "sg:postcode":"G6V 6C8",
    "sg:province":"QC",
    "wof:name":"Chaussures Yellow Ltee",
    "wof:placetype":"venue"
},
  "geometry": {"coordinates":[-71.17139434809999,46.7919921875],"type":"Point"}
}