{
  "type": "Feature",
  "properties": {
    "addr:full":"113 Wellington Rd Dover NL A0G 1X0",
    "addr:housenumber":"113",
    "addr:postcode":"a0g 1x0",
    "addr:street":"Wellington Rd",
    "iso:country":"CA",
    "sg:address":"113 Wellington Rd",
    "sg:city":"Dover",
    "sg:classifiers":[
        {
            "category":"Government",
            "subcategory":"Office",
            "type":"Public Place"
        }
    ],
    "sg:phone":"+1 709 537 2139",
    "sg:postcode":"A0G 1X0",
    "sg:province":"NL",
    "sg:tags":[
        "village"
    ],
    "wof:name":"Dover Town Council",
    "wof:placetype":"venue"
},
  "geometry": {"coordinates":[-53.9895896912,48.8704528809],"type":"Point"}
}