{
  "type": "Feature",
  "properties": {
    "addr:full":"180 Tecumseh Rd E Windsor ON N8X 2P8",
    "addr:housenumber":"180",
    "addr:postcode":"n8x 2p8",
    "addr:street":"Tecumseh Rd E",
    "iso:country":"CA",
    "sg:address":"180 Tecumseh Rd E",
    "sg:city":"Windsor",
    "sg:classifiers":[
        {
            "category":"Home & Garden",
            "subcategory":"Household Appliances",
            "type":"Retail Goods"
        }
    ],
    "sg:phone":"+1 519 258 5276",
    "sg:postcode":"N8X 2P8",
    "sg:province":"ON",
    "sg:tags":[
        "cleaners",
        "vacuum"
    ],
    "wof:name":"G L Vacuum Sales & Svc",
    "wof:placetype":"venue"
},
  "geometry": {"coordinates":[-83.022446,42.297066],"type":"Point"}
}