{
  "type": "Feature",
  "properties": {
    "iso:country":"CA",
    "sg:address":"5707 3 St SE",
    "sg:city":"Calgary",
    "sg:classifiers":[
        {
            "category":"Organizations",
            "subcategory":"Professional Association",
            "type":"Services"
        }
    ],
    "sg:phone":"+1 403 212 1855",
    "sg:postcode":"T2H 1K1",
    "sg:province":"AB",
    "wof:name":"Calgary Academy Parents Assn",
    "wof:placetype":"venue"
},
  "geometry": {"coordinates":[-114.057304382,51.003238678],"type":"Point"}
}