{
  "type": "Feature",
  "properties": {
    "addr:full":"88 Rue Saint-Jacques Saint-Jacques QC J0K 2R0",
    "addr:housenumber":"88",
    "addr:postcode":"j0k 2r0",
    "addr:street":"Rue Saint-Jacques",
    "iso:country":"CA",
    "sg:address":"88 Rue Saint-Jacques",
    "sg:city":"Saint-Jacques",
    "sg:classifiers":[
        {
            "category":"Autos & Motor Vehicles",
            "subcategory":"Auto Supplies",
            "type":"Retail Goods"
        }
    ],
    "sg:phone":"+1 450 839 3688",
    "sg:postcode":"J0K 2R0",
    "sg:province":"QC",
    "sg:tags":[
        "automobile",
        "parts"
    ],
    "wof:name":"J P Racette Inc",
    "wof:placetype":"venue"
},
  "geometry": {"coordinates":[-73.570511,45.948235],"type":"Point"}
}