{
  "type": "Feature",
  "properties": {
    "addr:full":"1028 10 Ave SE High River AB T1V 1L3",
    "addr:housenumber":"1028",
    "addr:postcode":"t1v 1l3",
    "addr:street":"10 Ave Se",
    "iso:country":"CA",
    "sg:address":"1028 10 Ave SE",
    "sg:city":"High River",
    "sg:classifiers":[
        {
            "category":"Manufacturing",
            "subcategory":"Printing",
            "type":"Manufacturing & Wholesale Goods"
        }
    ],
    "sg:phone":"+1 403 601 2334",
    "sg:postcode":"T1V 1L3",
    "sg:province":"AB",
    "sg:tags":[
        "publisher"
    ],
    "wof:name":"Red Willow Outdoors",
    "wof:placetype":"venue"
},
  "geometry": {"coordinates":[-113.849487,50.574528],"type":"Point"}
}