{
  "type": "Feature",
  "properties": {
    "iso:country":"CA",
    "sg:address":"115 Holmwood Ave",
    "sg:city":"Ottawa",
    "sg:classifiers":[
        {
            "category":"Retail",
            "subcategory":"Portrait Studio",
            "type":"Services"
        }
    ],
    "sg:phone":"+1 613 594 5896",
    "sg:postcode":"K1S 2P1",
    "sg:province":"ON",
    "sg:tags":[
        "photographer"
    ],
    "wof:name":"Andrew Balfour Photography",
    "wof:placetype":"venue"
},
  "geometry": {"coordinates":[-75.685844,45.400288],"type":"Point"}
}