{
  "type": "Feature",
  "properties": {
    "addr:full":"2352 Arbutus Cres Nanoose Bay BC V9P 9G1",
    "addr:housenumber":"2352",
    "addr:postcode":"v9p 9g1",
    "addr:street":"Arbutus Cres",
    "iso:country":"CA",
    "sg:address":"2352 Arbutus Cres",
    "sg:city":"Nanoose Bay",
    "sg:classifiers":[
        {
            "category":"Retail",
            "subcategory":"Repair Shop",
            "type":"Services"
        }
    ],
    "sg:phone":"+1 250 468 1919",
    "sg:postcode":"V9P 9G1",
    "sg:province":"BC",
    "sg:tags":[
        "appliance"
    ],
    "wof:name":"Morrow Appliance Repair Svc",
    "wof:placetype":"venue"
},
  "geometry": {"coordinates":[-124.168564,49.274601],"type":"Point"}
}