{
  "type": "Feature",
  "properties": {
    "iso:country":"CA",
    "sg:address":"1659 Argyle St",
    "sg:city":"Halifax",
    "sg:classifiers":[
        {
            "category":"Personal",
            "subcategory":"Beauty Salon",
            "type":"Services"
        }
    ],
    "sg:phone":"+1 902 425 1850",
    "sg:postcode":"B3J 2B5",
    "sg:province":"NS",
    "wof:name":"Studio Argyle Hair & Esthetics",
    "wof:placetype":"venue"
},
  "geometry": {"coordinates":[-63.5743980408,44.646697998],"type":"Point"}
}