{
  "type": "Feature",
  "properties": {
    "addr:full":"Peterborough ON K9J 3R8",
    "addr:postcode":"k9j 3r8",
    "iso:country":"CA",
    "sg:city":"Peterborough",
    "sg:classifiers":[
        {
            "category":"Insurance",
            "subcategory":"Insurance Agent",
            "type":"Services"
        }
    ],
    "sg:phone":"+1 705 740 9000",
    "sg:postcode":"K9J 3R8",
    "sg:province":"ON",
    "wof:name":"Financial Navigation Inc",
    "wof:placetype":"venue"
},
  "geometry": {"coordinates":[-78.323494,44.289333],"type":"Point"}
}