{
  "type": "Feature",
  "properties": {
    "addr:full":"Toronto ON M5E 1E5",
    "addr:postcode":"m5e 1e5",
    "iso:country":"CA",
    "sg:city":"Toronto",
    "sg:classifiers":[
        {
            "category":"Professional",
            "subcategory":"Research",
            "type":"Services"
        }
    ],
    "sg:phone":"+1 416 703 5700",
    "sg:postcode":"M5E 1E5",
    "sg:province":"ON",
    "sg:tags":[
        "development",
        "laboratory"
    ],
    "wof:name":"Light Search Technology Group",
    "wof:placetype":"venue"
},
  "geometry": {"coordinates":[-79.3745803833,43.6420516968],"type":"Point"}
}