{
  "type": "Feature",
  "properties": {
    "addr:full":"155 Champagne Dr North York ON M3J 2C6",
    "addr:housenumber":"155",
    "addr:postcode":"m3j 2c6",
    "addr:street":"Champagne Dr",
    "iso:country":"CA",
    "sg:address":"155 Champagne Dr",
    "sg:city":"North York",
    "sg:classifiers":[
        {
            "category":"Education",
            "subcategory":"Vocational School",
            "type":"Public Place"
        }
    ],
    "sg:phone":"+1 416 630 5559",
    "sg:postcode":"M3J 2C6",
    "sg:province":"ON",
    "sg:tags":[
        "technical",
        "trade"
    ],
    "wof:name":"York Construction Academy",
    "wof:placetype":"venue"
},
  "geometry": {"coordinates":[-79.470688,43.765888],"type":"Point"}
}