{
  "type": "Feature",
  "properties": {
    "addr:full":"112 181E Rue Beauceville QC G5X 2S8",
    "addr:housenumber":"112",
    "addr:postcode":"g5x 2s8",
    "addr:street":"181E Rue",
    "iso:country":"CA",
    "sg:address":"112 181E Rue",
    "sg:city":"Beauceville",
    "sg:classifiers":[
        {
            "category":"Autos & Motor Vehicles",
            "subcategory":"Auto Supplies",
            "type":"Retail Goods"
        }
    ],
    "sg:phone":"+1 418 774 2000",
    "sg:postcode":"G5X 2S8",
    "sg:province":"QC",
    "sg:tags":[
        "tire"
    ],
    "wof:name":"Rechapage 2000 Inc",
    "wof:placetype":"venue"
},
  "geometry": {"coordinates":[-70.79207599999999,46.224201],"type":"Point"}
}