{
  "type": "Feature",
  "properties": {
    "iso:country":"CA",
    "sg:city":"Montreal",
    "sg:classifiers":[
        {
            "category":"Health Services",
            "subcategory":"Health Practitioner",
            "type":"Services"
        }
    ],
    "sg:phone":"+1 514 278 5858",
    "sg:postcode":"H2V 4A2",
    "sg:province":"QC",
    "sg:tags":[
        "psychotherapist"
    ],
    "wof:name":"Centre DE Focusing DE Montreal",
    "wof:placetype":"venue"
},
  "geometry": {"coordinates":[-73.5914764404,45.5170631409],"type":"Point"}
}