{
  "type": "Feature",
  "properties": {
    "addr:full":"2069 Rue Saint-Denis Montreal QC H2X 3K8",
    "addr:housenumber":"2069",
    "addr:postcode":"h2x 3k8",
    "addr:street":"Rue Saint-Denis",
    "iso:country":"CA",
    "sg:address":"2069 Rue Saint-Denis",
    "sg:city":"Montreal",
    "sg:classifiers":[
        {
            "category":"Manufacturing",
            "subcategory":"Printing",
            "type":"Manufacturing & Wholesale Goods"
        }
    ],
    "sg:phone":"+1 514 281 0177",
    "sg:postcode":"H2X 3K8",
    "sg:province":"QC",
    "sg:tags":[
        "publisher",
        "music"
    ],
    "wof:name":"Editions Bloc-Notes",
    "wof:placetype":"venue"
},
  "geometry": {"coordinates":[-73.56619999999999,45.516521],"type":"Point"}
}