{
  "type": "Feature",
  "properties": {
    "iso:country":"CA",
    "sg:address":"22 Spackman Blvd",
    "sg:city":"St Thomas",
    "sg:classifiers":[
        {
            "category":"Building & Trades",
            "subcategory":"Construction",
            "type":"Services"
        }
    ],
    "sg:phone":"+1 519 633 6599",
    "sg:postcode":"N5P 4A3",
    "sg:province":"ON",
    "sg:tags":[
        "excavating",
        "contractor"
    ],
    "wof:name":"Lake Contracting & Mechanical",
    "wof:placetype":"venue"
},
  "geometry": {"coordinates":[-81.1552352905,42.7885475159],"type":"Point"}
}