{
  "type": "Feature",
  "properties": {
    "iso:country":"CA",
    "sg:city":"North York",
    "sg:classifiers":[
        {
            "category":"Travel",
            "subcategory":"Travel Agent",
            "type":"Entertainment"
        }
    ],
    "sg:phone":"+1 416 222 7776",
    "sg:postcode":"M2M 3W2",
    "sg:province":"ON",
    "sg:tags":[
        "agency",
        "bureau"
    ],
    "wof:name":"Atlas Travel & Holidays",
    "wof:placetype":"venue"
},
  "geometry": {"coordinates":[-79.418137,43.791077],"type":"Point"}
}