{
  "type": "Feature",
  "properties": {
    "addr:full":"137 King St Balgonie SK S0G 0E0",
    "addr:housenumber":"137",
    "addr:postcode":"s0g 0e0",
    "addr:street":"King St",
    "iso:country":"CA",
    "sg:address":"137 King St",
    "sg:city":"Balgonie",
    "sg:classifiers":[
        {
            "category":"Recreation",
            "type":"Entertainment"
        }
    ],
    "sg:phone":"+1 306 771 2342",
    "sg:postcode":"S0G 0E0",
    "sg:province":"SK",
    "sg:tags":[
        "pool",
        "swimming"
    ],
    "wof:name":"Balgonie Swimming Pool",
    "wof:placetype":"venue"
},
  "geometry": {"coordinates":[-104.27420044,50.4896736145],"type":"Point"}
}