{
  "type": "Feature",
  "properties": {
    "iso:country":"CA",
    "sg:city":"Calgary",
    "sg:classifiers":[
        {
            "category":"Restaurant",
            "type":"Food & Drink"
        }
    ],
    "sg:phone":"+1 403 547 3779",
    "sg:postcode":"T3G 3A9",
    "sg:province":"AB",
    "wof:name":"Wok With Dave",
    "wof:placetype":"venue"
},
  "geometry": {"coordinates":[-114.180503845,51.1162528992],"type":"Point"}
}