{
  "type": "Feature",
  "properties": {
    "addr:full":"905 Sackville Dr Lower Sackville NS B4E 1V3",
    "addr:housenumber":"905",
    "addr:postcode":"b4e 1v3",
    "addr:street":"Sackville Dr",
    "iso:country":"CA",
    "sg:address":"905 Sackville Dr",
    "sg:city":"Lower Sackville",
    "sg:classifiers":[
        {
            "category":"Autos & Motor Vehicles",
            "subcategory":"Recreational Vehicle Sales",
            "type":"Retail Goods"
        }
    ],
    "sg:phone":"+1 902 865 2308",
    "sg:postcode":"B4E 1V3",
    "sg:province":"NS",
    "wof:name":"Ross Trailer Sales",
    "wof:placetype":"venue"
},
  "geometry": {"coordinates":[-63.6970558167,44.7776222229],"type":"Point"}
}