{
  "type": "Feature",
  "properties": {
    "iso:country":"CA",
    "sg:address":"3975 Mystic Ave",
    "sg:city":"Quesnel",
    "sg:classifiers":[
        {
            "category":"Professional",
            "subcategory":"Business Services",
            "type":"Services"
        }
    ],
    "sg:phone":"+1 250 992 9396",
    "sg:postcode":"V2J 6V9",
    "sg:province":"BC",
    "sg:tags":[
        "water",
        "hauling"
    ],
    "wof:name":"Aqua-Serve",
    "wof:placetype":"venue"
},
  "geometry": {"coordinates":[-122.498245239,52.9781188965],"type":"Point"}
}