{
  "type": "Feature",
  "properties": {
    "addr:full":"2837 Dundas St W Toronto ON M6P 1Y6",
    "addr:housenumber":"2837",
    "addr:postcode":"m6p 1y6",
    "addr:street":"Dundas St W",
    "iso:country":"CA",
    "sg:address":"2837 Dundas St W",
    "sg:city":"Toronto",
    "sg:classifiers":[
        {
            "category":"Food & Beverages",
            "subcategory":"Specialty",
            "type":"Retail Goods"
        }
    ],
    "sg:phone":"+1 416 769 2931",
    "sg:postcode":"M6P 1Y6",
    "sg:province":"ON",
    "sg:tags":[
        "health",
        "diet"
    ],
    "wof:name":"Four Seasons Natural Food",
    "wof:placetype":"venue"
},
  "geometry": {"coordinates":[-79.4639053345,43.6652145386],"type":"Point"}
}