{
  "type": "Feature",
  "properties": {
    "addr:full":"292 Rue Queen Lennoxville QC J1M 1K6",
    "addr:housenumber":"292",
    "addr:postcode":"j1m 1k6",
    "addr:street":"Rue Queen",
    "iso:country":"CA",
    "sg:address":"292 Rue Queen",
    "sg:city":"Lennoxville",
    "sg:classifiers":[
        {
            "category":"Shopping",
            "type":"Retail Goods"
        }
    ],
    "sg:phone":"+1 819 348 1888",
    "sg:postcode":"J1M 1K6",
    "sg:province":"QC",
    "sg:tags":[
        "pet",
        "food",
        "supply"
    ],
    "wof:name":"Blue Seal Lennoxville Reg",
    "wof:placetype":"venue"
},
  "geometry": {"coordinates":[-71.86382293699999,45.3766746521],"type":"Point"}
}