{
  "type": "Feature",
  "properties": {
    "addr:full":"1110 Hwy 26 Midhurst ON L0L 1X0",
    "addr:housenumber":"1110",
    "addr:postcode":"l0l 1x0",
    "addr:street":"Hwy 26",
    "iso:country":"CA",
    "sg:address":"1110 Hwy 26",
    "sg:city":"Midhurst",
    "sg:classifiers":[
        {
            "category":"Government",
            "subcategory":"Office",
            "type":"Public Place"
        }
    ],
    "sg:phone":"+1 705 726 9300",
    "sg:postcode":"L0L 1X0",
    "sg:province":"ON",
    "wof:name":"Simcoe County Admin Office",
    "wof:placetype":"venue"
},
  "geometry": {"coordinates":[-79.73015599999999,44.444496],"type":"Point"}
}