{
  "type": "Feature",
  "properties": {
    "iso:country":"CA",
    "sg:address":"37 Spadina Rd",
    "sg:city":"Toronto",
    "sg:classifiers":[
        {
            "category":"Health Services",
            "subcategory":"Health Practitioner",
            "type":"Services"
        }
    ],
    "sg:phone":"+1 416 923 5112",
    "sg:postcode":"M5R 2S9",
    "sg:province":"ON",
    "sg:tags":[
        "psychotherapist",
        "counselor",
        "marriage",
        "family"
    ],
    "wof:name":"Campbell Consulting Ltd",
    "wof:placetype":"venue"
},
  "geometry": {"coordinates":[-79.40431976319999,43.668346405],"type":"Point"}
}