{
  "type": "Feature",
  "properties": {
    "addr:full":"605 Boul DE LA Montagne Saint-Casimir QC G0A 3L0",
    "addr:housenumber":"605",
    "addr:postcode":"g0a 3l0",
    "addr:street":"Boul De La Montagne",
    "iso:country":"CA",
    "sg:address":"605 Boul DE LA Montagne",
    "sg:city":"Saint-Casimir",
    "sg:classifiers":[
        {
            "category":"Real Estate",
            "subcategory":"Real Estate Agent",
            "type":"Services"
        }
    ],
    "sg:phone":"+1 418 339 2250",
    "sg:postcode":"G0A 3L0",
    "sg:province":"QC",
    "sg:tags":[
        "agency",
        "rental"
    ],
    "wof:name":"Joe Loue Tout",
    "wof:placetype":"venue"
},
  "geometry": {"coordinates":[-72.14756800000001,46.66103],"type":"Point"}
}