{
  "type": "Feature",
  "properties": {
    "addr:full":"10208 161 Ave NW Edmonton AB T5X 2P6",
    "addr:housenumber":"10208",
    "addr:postcode":"t5x 2p6",
    "addr:street":"161 Ave Nw",
    "iso:country":"CA",
    "sg:address":"10208 161 Ave NW",
    "sg:city":"Edmonton",
    "sg:classifiers":[
        {
            "category":"Wholesale",
            "subcategory":"Hardware",
            "type":"Manufacturing & Wholesale Goods"
        }
    ],
    "sg:phone":"+1 780 456 7046",
    "sg:postcode":"T5X 2P6",
    "sg:province":"AB",
    "sg:tags":[
        "used",
        "boiler"
    ],
    "wof:name":"Boiler Tech Svc & Building",
    "wof:placetype":"venue"
},
  "geometry": {"coordinates":[-113.499229,53.62236],"type":"Point"}
}