{
  "type": "Feature",
  "properties": {
    "iso:country":"CA",
    "sg:city":"Brampton",
    "sg:classifiers":[
        {
            "category":"Retail",
            "subcategory":"Auto Repair",
            "type":"Services"
        }
    ],
    "sg:phone":"+1 905 840 0505",
    "sg:postcode":"L7A 1A2",
    "sg:province":"ON",
    "sg:tags":[
        "repairing",
        "automobile"
    ],
    "wof:name":"Delta Auto Repair",
    "wof:placetype":"venue"
},
  "geometry": {"coordinates":[-79.652237,43.766663],"type":"Point"}
}