{
  "type": "Feature",
  "properties": {
    "addr:full":"Montreal QC H4B 2M8",
    "addr:postcode":"h4b 2m8",
    "iso:country":"CA",
    "sg:city":"Montreal",
    "sg:classifiers":[
        {
            "category":"Wholesale",
            "subcategory":"Machinery & Supplies",
            "type":"Manufacturing & Wholesale Goods"
        }
    ],
    "sg:phone":"+1 514 487 1055",
    "sg:postcode":"H4B 2M8",
    "sg:province":"QC",
    "sg:tags":[
        "mixing",
        "agitation"
    ],
    "wof:name":"Nortec Sgs Inc",
    "wof:placetype":"venue"
},
  "geometry": {"coordinates":[-73.628433,45.463341],"type":"Point"}
}