{
  "type": "Feature",
  "properties": {
    "addr:full":"North York ON M3N 2V7",
    "addr:postcode":"m3n 2v7",
    "iso:country":"CA",
    "sg:city":"North York",
    "sg:classifiers":[
        {
            "category":"Health Services",
            "subcategory":"Medical Lab",
            "type":"Services"
        }
    ],
    "sg:phone":"+1 416 743 2371",
    "sg:postcode":"M3N 2V7",
    "sg:province":"ON",
    "sg:tags":[
        "laboratory"
    ],
    "wof:name":"Canadian Medical Laboratories",
    "wof:placetype":"venue"
},
  "geometry": {"coordinates":[-79.523026,43.756096],"type":"Point"}
}