{
  "type": "Feature",
  "properties": {
    "addr:full":"6734 2E Av Montreal QC H1Y 2Z6",
    "addr:housenumber":"6734",
    "addr:postcode":"h1y 2z6",
    "addr:street":"2E Av",
    "iso:country":"CA",
    "sg:address":"6734 2E Av",
    "sg:city":"Montreal",
    "sg:classifiers":[
        {
            "category":"Building & Trades",
            "subcategory":"Construction",
            "type":"Services"
        }
    ],
    "sg:phone":"+1 514 725 9166",
    "sg:postcode":"H1Y 2Z6",
    "sg:province":"QC",
    "sg:tags":[
        "resurfacing",
        "laying",
        "refinishing",
        "floor"
    ],
    "wof:name":"Cloutier Rolland",
    "wof:placetype":"venue"
},
  "geometry": {"coordinates":[-73.594002,45.55283],"type":"Point"}
}