{
  "type": "Feature",
  "properties": {
    "addr:full":"2755 Lougheed Hwy Port Coquitlam BC V3B 5Y9",
    "addr:housenumber":"2755",
    "addr:postcode":"v3b 5y9",
    "addr:street":"Lougheed Hwy",
    "iso:country":"CA",
    "sg:address":"2755 Lougheed Hwy",
    "sg:city":"Port Coquitlam",
    "sg:classifiers":[
        {
            "category":"Banks & Credit Unions",
            "subcategory":"Bank",
            "type":"Services"
        }
    ],
    "sg:phone":"+1 604 949 8888",
    "sg:postcode":"V3B 5Y9",
    "sg:province":"BC",
    "sg:tags":[
        "investment"
    ],
    "wof:name":"Hsbc Securities Inc Retail",
    "wof:placetype":"venue"
},
  "geometry": {"coordinates":[-122.789024,49.273098],"type":"Point"}
}