{
  "type": "Feature",
  "properties": {
    "addr:full":"506 Topsail Rd St. John's NL A1E 2C2",
    "addr:housenumber":"506",
    "addr:postcode":"a1e 2c2",
    "addr:street":"Topsail Rd",
    "iso:country":"CA",
    "sg:address":"506 Topsail Rd",
    "sg:city":"St. John's",
    "sg:classifiers":[
        {
            "category":"Restaurant",
            "type":"Food & Drink"
        }
    ],
    "sg:phone":"+1 709 368 2722",
    "sg:postcode":"A1E 2C2",
    "sg:province":"NL",
    "wof:name":"Mc Donald's",
    "wof:placetype":"venue"
},
  "geometry": {"coordinates":[-52.757023,47.530743],"type":"Point"}
}