{
  "type": "Feature",
  "properties": {
    "addr:full":"200 Industrial Pky N Aurora ON L4G 4C3",
    "addr:housenumber":"200",
    "addr:postcode":"l4g 4c3",
    "addr:street":"Industrial Pky N",
    "iso:country":"CA",
    "sg:address":"200 Industrial Pky N",
    "sg:city":"Aurora",
    "sg:classifiers":[
        {
            "category":"Manufacturing",
            "subcategory":"Motor Vehicles & Parts",
            "type":"Manufacturing & Wholesale Goods"
        }
    ],
    "sg:phone":"+1 905 841 6211",
    "sg:postcode":"L4G 4C3",
    "sg:province":"ON",
    "sg:tags":[
        "automobile",
        "supply"
    ],
    "wof:name":"Plydex",
    "wof:placetype":"venue"
},
  "geometry": {"coordinates":[-79.46125000000001,44.01152],"type":"Point"}
}