{
  "type": "Feature",
  "properties": {
    "addr:full":"Etobicoke ON M9W 6H9",
    "addr:postcode":"m9w 6h9",
    "iso:country":"CA",
    "sg:city":"Etobicoke",
    "sg:classifiers":[
        {
            "category":"Retail",
            "subcategory":"Auto Repair",
            "type":"Services"
        }
    ],
    "sg:phone":"+1 416 674 7813",
    "sg:postcode":"M9W 6H9",
    "sg:province":"ON",
    "sg:tags":[
        "repairing",
        "automobile"
    ],
    "wof:name":"Little City Auto Svc Inc",
    "wof:placetype":"venue"
},
  "geometry": {"coordinates":[-79.619659,43.754066],"type":"Point"}
}