{
  "type": "Feature",
  "properties": {
    "addr:full":"Ottawa ON K1P 5Z9",
    "addr:postcode":"k1p 5z9",
    "iso:country":"CA",
    "sg:city":"Ottawa",
    "sg:classifiers":[
        {
            "category":"Professional",
            "subcategory":"Accounting & Tax Preparation",
            "type":"Services"
        }
    ],
    "sg:phone":"+1 613 565 7151",
    "sg:postcode":"K1P 5Z9",
    "sg:province":"ON",
    "sg:tags":[
        "accountant"
    ],
    "wof:name":"Mingie, Brian R CA",
    "wof:placetype":"venue"
},
  "geometry": {"coordinates":[-75.6960144043,45.4196434021],"type":"Point"}
}