{
  "type": "Feature",
  "properties": {
    "iso:country":"CA",
    "sg:address":"275 Slater St #1400",
    "sg:city":"Ottawa",
    "sg:classifiers":[
        {
            "category":"Professional",
            "subcategory":"Computer Services",
            "type":"Services"
        }
    ],
    "sg:phone":"+1 613 234 2155",
    "sg:postcode":"K1P 5H9",
    "sg:province":"ON",
    "sg:tags":[
        "information",
        "system",
        "consultant"
    ],
    "wof:name":"Cgi Information Systems",
    "wof:placetype":"venue"
},
  "geometry": {"coordinates":[-75.70175170900001,45.4186668396],"type":"Point"}
}