{
  "type": "Feature",
  "properties": {
    "addr:full":"2401 St Clair Ave W Toronto ON M6N 1K9",
    "addr:housenumber":"2401",
    "addr:postcode":"m6n 1k9",
    "addr:street":"St Clair Ave W",
    "iso:country":"CA",
    "sg:address":"2401 St Clair Ave W",
    "sg:city":"Toronto",
    "sg:classifiers":[
        {
            "category":"Retail",
            "subcategory":"Auto Repair",
            "type":"Services"
        }
    ],
    "sg:phone":"+1 416 769 1087",
    "sg:postcode":"M6N 1K9",
    "sg:province":"ON",
    "sg:tags":[
        "repairing",
        "automobile"
    ],
    "wof:name":"Rally Auto Repair",
    "wof:placetype":"venue"
},
  "geometry": {"coordinates":[-79.48179626460001,43.6692581177],"type":"Point"}
}