{
  "type": "Feature",
  "properties": {
    "addr:full":"1924 Weston Rd York ON M9N 1W2",
    "addr:housenumber":"1924",
    "addr:postcode":"m9n 1w2",
    "addr:street":"Weston Rd",
    "iso:country":"CA",
    "sg:address":"1924 Weston Rd",
    "sg:city":"York",
    "sg:classifiers":[
        {
            "category":"Health Services",
            "subcategory":"Medical Lab",
            "type":"Services"
        }
    ],
    "sg:phone":"+1 416 249 7481",
    "sg:postcode":"M9N 1W2",
    "sg:province":"ON",
    "sg:tags":[
        "laboratory"
    ],
    "wof:name":"Canadian Medical Laboratories",
    "wof:placetype":"venue"
},
  "geometry": {"coordinates":[-79.51709747309999,43.7002792358],"type":"Point"}
}