{
  "type": "Feature",
  "properties": {
    "addr:full":"174 Pitt St W Windsor ON N9A 5L4",
    "addr:housenumber":"174",
    "addr:postcode":"n9a 5l4",
    "addr:street":"Pitt St W",
    "iso:country":"CA",
    "sg:address":"174 Pitt St W",
    "sg:city":"Windsor",
    "sg:classifiers":[
        {
            "category":"Government",
            "subcategory":"Office",
            "type":"Public Place"
        }
    ],
    "sg:phone":"+1 519 252 7264",
    "sg:postcode":"N9A 5L4",
    "sg:province":"ON",
    "sg:tags":[
        "village"
    ],
    "wof:name":"Windsor International Festival",
    "wof:placetype":"venue"
},
  "geometry": {"coordinates":[-83.0418930054,42.3185386658],"type":"Point"}
}