{
  "type": "Feature",
  "properties": {
    "addr:full":"1406 Ch DE Lausanne Rimouski QC G5L 8Y9",
    "addr:postcode":"1406;g5l 8y9",
    "addr:street":"Ch De Lausanne",
    "iso:country":"CA",
    "sg:address":"1406 Ch DE Lausanne",
    "sg:city":"Rimouski",
    "sg:classifiers":[
        {
            "category":"Building & Trades",
            "subcategory":"Construction",
            "type":"Services"
        }
    ],
    "sg:phone":"+1 418 722 7090",
    "sg:postcode":"G5L 8Y9",
    "sg:province":"QC",
    "sg:tags":[
        "paint",
        "varnish",
        "removal"
    ],
    "wof:name":"Peinture Electrostatique Inc",
    "wof:placetype":"venue"
},
  "geometry": {"coordinates":[-68.6132965088,48.3927650452],"type":"Point"}
}