{
  "type": "Feature",
  "properties": {
    "iso:country":"CA",
    "sg:address":"510 Dutton Dr",
    "sg:city":"Waterloo",
    "sg:classifiers":[
        {
            "category":"Organizations",
            "subcategory":"Professional Association",
            "type":"Services"
        }
    ],
    "sg:phone":"+1 519 884 1272",
    "sg:postcode":"N2L 4C6",
    "sg:province":"ON",
    "sg:tags":[
        "club"
    ],
    "wof:name":"Rcaf Assn",
    "wof:placetype":"venue"
},
  "geometry": {"coordinates":[-80.5396575928,43.4945297241],"type":"Point"}
}