{
  "type": "Feature",
  "properties": {
    "addr:full":"237 Kent St W Lindsay ON K9V 2Z3",
    "addr:housenumber":"237",
    "addr:postcode":"k9v 2z3",
    "addr:street":"Kent St W",
    "iso:country":"CA",
    "sg:address":"237 Kent St W",
    "sg:city":"Lindsay",
    "sg:classifiers":[
        {
            "category":"Professional",
            "subcategory":"Accounting & Tax Preparation",
            "type":"Services"
        }
    ],
    "sg:phone":"+1 705 324 5031",
    "sg:postcode":"K9V 2Z3",
    "sg:province":"ON",
    "sg:tags":[
        "accountant"
    ],
    "wof:name":"Collins Barrow",
    "wof:placetype":"venue"
},
  "geometry": {"coordinates":[-78.74505600000001,44.352974],"type":"Point"}
}