{
  "type": "Feature",
  "properties": {
    "addr:full":"Winnipeg MB R3J 0K4",
    "addr:postcode":"r3j 0k4",
    "iso:country":"CA",
    "sg:city":"Winnipeg",
    "sg:classifiers":[
        {
            "category":"Social Services",
            "type":"Services"
        }
    ],
    "sg:phone":"+1 204 885 1000",
    "sg:postcode":"R3J 0K4",
    "sg:province":"MB",
    "sg:tags":[
        "family",
        "assistance",
        "program",
        "marriage",
        "employee",
        "counselor"
    ],
    "wof:name":"Gayle Swirski Counselling",
    "wof:placetype":"venue"
},
  "geometry": {"coordinates":[-97.22955322270001,49.8774414062],"type":"Point"}
}