{
  "type": "Feature",
  "properties": {
    "addr:full":"Concord ON L4K 1S4",
    "addr:postcode":"l4k 1s4",
    "iso:country":"CA",
    "sg:city":"Concord",
    "sg:classifiers":[
        {
            "category":"Retail",
            "subcategory":"Auto Repair",
            "type":"Services"
        }
    ],
    "sg:phone":"+1 905 760 0726",
    "sg:postcode":"L4K 1S4",
    "sg:province":"ON",
    "sg:tags":[
        "automobile",
        "painting",
        "dealer"
    ],
    "wof:name":"Windsor Auto Sales",
    "wof:placetype":"venue"
},
  "geometry": {"coordinates":[-79.51284,43.792843],"type":"Point"}
}