{
  "type": "Feature",
  "properties": {
    "addr:full":"1120 102 Ave Dawson Creek BC V1G 2C1",
    "addr:housenumber":"1120",
    "addr:postcode":"v1g 2c1",
    "addr:street":"102 Ave",
    "iso:country":"CA",
    "sg:address":"1120 102 Ave",
    "sg:city":"Dawson Creek",
    "sg:classifiers":[
        {
            "category":"Shopping",
            "subcategory":"Bicycles & Sporting Goods",
            "type":"Retail Goods"
        }
    ],
    "sg:phone":"+1 250 782 5066",
    "sg:postcode":"V1G 2C1",
    "sg:province":"BC",
    "wof:name":"Griffin Sport & Ski Shoppe Ltd",
    "wof:placetype":"venue"
},
  "geometry": {"coordinates":[-120.231514,55.759377],"type":"Point"}
}