{
  "type": "Feature",
  "properties": {
    "addr:full":"10104 Kalamalka Rd Coldstream BC V1B 1L7",
    "addr:postcode":"10104;bc v1b 1l7",
    "addr:street":"Kalamalka Rd",
    "iso:country":"CA",
    "sg:address":"10104 Kalamalka Rd",
    "sg:city":"Coldstream",
    "sg:classifiers":[
        {
            "category":"Education",
            "subcategory":"School",
            "type":"Public Place"
        }
    ],
    "sg:phone":"+1 250 545 0597",
    "sg:postcode":"V1B 1L7",
    "sg:province":"BC",
    "wof:name":"Coldstream Elementary",
    "wof:placetype":"venue"
},
  "geometry": {"coordinates":[-119.23387099999999,50.223557],"type":"Point"}
}