{
  "type": "Feature",
  "properties": {
    "iso:country":"CA",
    "sg:address":"450 Denman St",
    "sg:city":"Vancouver",
    "sg:classifiers":[
        {
            "category":"Recreation",
            "subcategory":"Marina",
            "type":"Entertainment"
        }
    ],
    "sg:phone":"+1 604 689 5331",
    "sg:postcode":"V6G 3J1",
    "sg:province":"BC",
    "wof:name":"Bayshore West Marina",
    "wof:placetype":"venue"
},
  "geometry": {"coordinates":[-123.132644653,49.2931518555],"type":"Point"}
}