{
  "type": "Feature",
  "properties": {
    "addr:full":"7650 Burris St Burnaby BC V5E 1Z3",
    "addr:housenumber":"7650",
    "addr:postcode":"v5e 1z3",
    "addr:street":"Burris St",
    "iso:country":"CA",
    "sg:address":"7650 Burris St",
    "sg:city":"Burnaby",
    "sg:classifiers":[
        {
            "category":"Real Estate",
            "subcategory":"Real Estate Agent",
            "type":"Services"
        }
    ],
    "sg:phone":"+1 604 522 6875",
    "sg:postcode":"V5E 1Z3",
    "sg:province":"BC",
    "wof:name":"Brookes Realty Corp",
    "wof:placetype":"venue"
},
  "geometry": {"coordinates":[-122.955673218,49.2346534729],"type":"Point"}
}