{
  "type": "Feature",
  "properties": {
    "addr:full":"8540 Manning Ave Fort Mcmurray AB T9H 5G2",
    "addr:housenumber":"8540",
    "addr:postcode":"t9h 5g2",
    "addr:street":"Manning Ave",
    "iso:country":"CA",
    "sg:address":"8540 Manning Ave",
    "sg:city":"Fort Mcmurray",
    "sg:classifiers":[
        {
            "category":"Banks & Credit Unions",
            "subcategory":"Investment Brokerage",
            "type":"Services"
        }
    ],
    "sg:phone":"+1 780 790 2953",
    "sg:postcode":"T9H 5G2",
    "sg:province":"AB",
    "sg:tags":[
        "advisory",
        "financial"
    ],
    "wof:name":"Rbc Dominion Securities Inc",
    "wof:placetype":"venue"
},
  "geometry": {"coordinates":[-111.357421875,56.719669342],"type":"Point"}
}