{
  "type": "Feature",
  "properties": {
    "addr:full":"1854 County Rd 18 Picton ON K0K 2T0",
    "addr:housenumber":"1854;18",
    "addr:postcode":"k0k 2t0",
    "addr:street":"County Rd",
    "iso:country":"CA",
    "sg:address":"1854 County Rd 18",
    "sg:city":"Picton",
    "sg:classifiers":[
        {
            "category":"Travel",
            "subcategory":"Campground",
            "type":"Entertainment"
        }
    ],
    "sg:phone":"+1 613 393 5645",
    "sg:postcode":"K0K 2T0",
    "sg:province":"ON",
    "wof:name":"Martin's River Country",
    "wof:placetype":"venue"
},
  "geometry": {"coordinates":[-77.138977,44.009224],"type":"Point"}
}