{
  "type": "Feature",
  "properties": {
    "iso:country":"CA",
    "sg:address":"224 Division St",
    "sg:city":"Welland",
    "sg:classifiers":[
        {
            "category":"Organizations",
            "subcategory":"Religious Organization",
            "type":"Services"
        }
    ],
    "sg:phone":"+1 905 732 6010",
    "sg:postcode":"L3B 4A2",
    "sg:province":"ON",
    "sg:tags":[
        "church"
    ],
    "wof:name":"Christ Community Church",
    "wof:placetype":"venue"
},
  "geometry": {"coordinates":[-79.2441253662,42.991897583],"type":"Point"}
}