{
  "type": "Feature",
  "properties": {
    "addr:full":"Toronto ON M6S 4W1",
    "addr:postcode":"m6s 4w1",
    "iso:country":"CA",
    "sg:city":"Toronto",
    "sg:classifiers":[
        {
            "category":"Education",
            "subcategory":"Special Training",
            "type":"Public Place"
        }
    ],
    "sg:phone":"+1 416 766 0171",
    "sg:postcode":"M6S 4W1",
    "sg:province":"ON",
    "sg:tags":[
        "instruction",
        "driving"
    ],
    "wof:name":"Stop Automobile Driving School",
    "wof:placetype":"venue"
},
  "geometry": {"coordinates":[-79.479958,43.650188],"type":"Point"}
}