{
  "type": "Feature",
  "properties": {
    "addr:full":"1147 Dundas St W Toronto ON M6J 1X3",
    "addr:housenumber":"1147",
    "addr:postcode":"m6j 1x3",
    "addr:street":"Dundas St W",
    "iso:country":"CA",
    "sg:address":"1147 Dundas St W",
    "sg:city":"Toronto",
    "sg:classifiers":[
        {
            "category":"Food & Beverages",
            "subcategory":"Specialty",
            "type":"Retail Goods"
        }
    ],
    "sg:phone":"+1 416 536 2139",
    "sg:postcode":"M6J 1X3",
    "sg:province":"ON",
    "sg:tags":[
        "vitamin",
        "pharmacy"
    ],
    "wof:name":"Main Drug Mart",
    "wof:placetype":"venue"
},
  "geometry": {"coordinates":[-79.4211807251,43.6491546631],"type":"Point"}
}