{
  "type": "Feature",
  "properties": {
    "addr:full":"299 Boul Sir-Wilfrid-Laurier Saint-Lambert QC J4R 2L1",
    "addr:housenumber":"299",
    "addr:postcode":"j4r 2l1",
    "addr:street":"Boul Sir-Wilfrid-Laurier",
    "iso:country":"CA",
    "sg:address":"299 Boul Sir-Wilfrid-Laurier",
    "sg:city":"Saint-Lambert",
    "sg:classifiers":[
        {
            "category":"Education",
            "subcategory":"School",
            "type":"Public Place"
        }
    ],
    "sg:phone":"+1 450 672 4010",
    "sg:postcode":"J4R 2L1",
    "sg:province":"QC",
    "wof:name":"Commission Scolaire Riverside",
    "wof:placetype":"venue"
},
  "geometry": {"coordinates":[-73.5039978027,45.4940338135],"type":"Point"}
}