{
  "type": "Feature",
  "properties": {
    "addr:full":"RR 1 Lcd Collingwood Collingwood ON L9Y 3Y9",
    "addr:postcode":"l9y 3y9",
    "addr:street":"Rr 1 Lcd",
    "iso:country":"CA",
    "sg:address":"RR 1 Lcd Collingwood",
    "sg:city":"Collingwood",
    "sg:classifiers":[
        {
            "category":"Education",
            "subcategory":"Vocational School",
            "type":"Public Place"
        }
    ],
    "sg:phone":"+1 705 444 0600",
    "sg:postcode":"L9Y 3Y9",
    "sg:province":"ON",
    "sg:tags":[
        "technical",
        "trade"
    ],
    "wof:name":"Real Time Training",
    "wof:placetype":"venue"
},
  "geometry": {"coordinates":[-80.2168273926,44.4998893738],"type":"Point"}
}