{
  "type": "Feature",
  "properties": {
    "iso:country":"CA",
    "sg:city":"Baie-Comeau",
    "sg:classifiers":[
        {
            "category":"Retail",
            "subcategory":"Repair Shop",
            "type":"Services"
        }
    ],
    "sg:phone":"+1 418 589 2600",
    "sg:postcode":"G5C 1M5",
    "sg:province":"QC",
    "sg:tags":[
        "upholsterer"
    ],
    "wof:name":"Rembourrage Lafleche Enr",
    "wof:placetype":"venue"
},
  "geometry": {"coordinates":[-68.24709320069999,49.1932258606],"type":"Point"}
}