{
  "type": "Feature",
  "properties": {
    "iso:country":"CA",
    "sg:address":"56 Rue Rachel E",
    "sg:city":"Montreal",
    "sg:classifiers":[
        {
            "category":"Personal",
            "subcategory":"Shoe Repair & Shine",
            "type":"Services"
        }
    ],
    "sg:phone":"+1 514 499 9297",
    "sg:postcode":"H2W 1C6",
    "sg:province":"QC",
    "sg:tags":[
        "repairing",
        "boot"
    ],
    "wof:name":"Karpman Hopital Des Chaussures",
    "wof:placetype":"venue"
},
  "geometry": {"coordinates":[-73.581024,45.518555],"type":"Point"}
}