{
  "type": "Feature",
  "properties": {
    "addr:full":"Vancouver BC V6H 3G6",
    "addr:postcode":"v6h 3g6",
    "iso:country":"CA",
    "sg:city":"Vancouver",
    "sg:classifiers":[
        {
            "category":"Real Estate",
            "subcategory":"Real Estate Agent",
            "type":"Services"
        }
    ],
    "sg:phone":"+1 604 731 3167",
    "sg:postcode":"V6H 3G6",
    "sg:province":"BC",
    "wof:name":"Dranly Holdings Ltd",
    "wof:placetype":"venue"
},
  "geometry": {"coordinates":[-123.13835907000001,49.2640953064],"type":"Point"}
}