{
  "type": "Feature",
  "properties": {
    "iso:country":"CA",
    "sg:address":"372 Main St N",
    "sg:city":"Mount Forest",
    "sg:classifiers":[
        {
            "category":"Building & Trades",
            "subcategory":"Construction",
            "type":"Services"
        }
    ],
    "sg:phone":"+1 519 323 1241",
    "sg:postcode":"N0G 2L2",
    "sg:province":"ON",
    "sg:tags":[
        "general",
        "contractor"
    ],
    "wof:name":"Reeves Construction Ltd",
    "wof:placetype":"venue"
},
  "geometry": {"coordinates":[-80.7407836914,43.9856147766],"type":"Point"}
}