{
  "type": "Feature",
  "properties": {
    "addr:full":"2100 Rue Royale Trois-Rivieres QC G9A 4L4",
    "addr:housenumber":"2100",
    "addr:postcode":"g9a 4l4",
    "addr:street":"Rue Royale",
    "iso:country":"CA",
    "sg:address":"2100 Rue Royale",
    "sg:city":"Trois-Rivieres",
    "sg:classifiers":[
        {
            "category":"Food & Beverages",
            "subcategory":"Groceries & Convenience Stores",
            "type":"Retail Goods"
        }
    ],
    "sg:phone":"+1 819 376 2536",
    "sg:postcode":"G9A 4L4",
    "sg:province":"QC",
    "sg:tags":[
        "grocer"
    ],
    "wof:name":"Marche Royal Enr",
    "wof:placetype":"venue"
},
  "geometry": {"coordinates":[-72.54769899999999,46.336609],"type":"Point"}
}