{
  "type": "Feature",
  "properties": {
    "addr:full":"Calgary AB T2G 4W6",
    "addr:postcode":"t2g 4w6",
    "iso:country":"CA",
    "sg:city":"Calgary",
    "sg:classifiers":[
        {
            "category":"Building & Trades",
            "subcategory":"Plumbing",
            "type":"Services"
        }
    ],
    "sg:phone":"+1 403 243 0141",
    "sg:postcode":"T2G 4W6",
    "sg:province":"AB",
    "sg:tags":[
        "refrigeration",
        "contractor"
    ],
    "wof:name":"Chinook Refrigeration & Ac",
    "wof:placetype":"venue"
},
  "geometry": {"coordinates":[-114.03961200000001,51.014103],"type":"Point"}
}