{
  "type": "Feature",
  "properties": {
    "addr:full":"20 John St S Aylmer ON N5H 2C2",
    "addr:housenumber":"20",
    "addr:postcode":"n5h 2c2",
    "addr:street":"John St S",
    "iso:country":"CA",
    "sg:address":"20 John St S",
    "sg:city":"Aylmer",
    "sg:classifiers":[
        {
            "category":"Cinema",
            "subcategory":"Movie Rental",
            "type":"Entertainment"
        }
    ],
    "sg:phone":"+1 519 765 1831",
    "sg:postcode":"N5H 2C2",
    "sg:province":"ON",
    "sg:tags":[
        "leasing",
        "video",
        "disc",
        "tape"
    ],
    "wof:name":"Aylmer Video",
    "wof:placetype":"venue"
},
  "geometry": {"coordinates":[-80.9831237793,42.7727355957],"type":"Point"}
}