{
  "type": "Feature",
  "properties": {
    "addr:full":"712 Lite St Point Edward ON N7V 1A6",
    "addr:housenumber":"712",
    "addr:postcode":"n7v 1a6",
    "addr:street":"Lite St",
    "iso:country":"CA",
    "sg:address":"712 Lite St",
    "sg:city":"Point Edward",
    "sg:classifiers":[
        {
            "category":"Recreation",
            "type":"Entertainment"
        }
    ],
    "sg:phone":"+1 519 337 4868",
    "sg:postcode":"N7V 1A6",
    "sg:province":"ON",
    "sg:tags":[
        "bingo",
        "game"
    ],
    "wof:name":"Village Bingo",
    "wof:placetype":"venue"
},
  "geometry": {"coordinates":[-82.40166473390001,42.9908714294],"type":"Point"}
}