{
  "type": "Feature",
  "properties": {
    "addr:full":"84 Northwood Dr Welland ON L3C 6S3",
    "addr:housenumber":"84",
    "addr:postcode":"l3c 6s3",
    "addr:street":"Northwood Dr",
    "iso:country":"CA",
    "sg:address":"84 Northwood Dr",
    "sg:city":"Welland",
    "sg:classifiers":[
        {
            "category":"Freight",
            "type":"Transportation"
        }
    ],
    "sg:phone":"+1 905 732 1229",
    "sg:postcode":"L3C 6S3",
    "sg:province":"ON",
    "sg:tags":[
        "trucking"
    ],
    "wof:name":"R Street City Transport Ltd",
    "wof:placetype":"venue"
},
  "geometry": {"coordinates":[-79.2768173218,43.0160331726],"type":"Point"}
}