{
  "type": "Feature",
  "properties": {
    "iso:country":"CA",
    "sg:address":"1495 Boul Du Souvenir",
    "sg:city":"Laval",
    "sg:classifiers":[
        {
            "category":"Restaurant",
            "type":"Food & Drink"
        }
    ],
    "sg:phone":"+1 450 662 2525",
    "sg:postcode":"H7N 5X1",
    "sg:province":"QC",
    "wof:name":"Place Souvenir",
    "wof:placetype":"venue"
},
  "geometry": {"coordinates":[-73.71817,45.563877],"type":"Point"}
}