{
  "type": "Feature",
  "properties": {
    "addr:full":"Saint-Honore-DE-Shenley QC G0M 1V0",
    "addr:postcode":"g0m 1v0",
    "iso:country":"CA",
    "sg:city":"Saint-Honore-DE-Shenley",
    "sg:classifiers":[
        {
            "category":"Manufacturing",
            "subcategory":"Furniture",
            "type":"Manufacturing & Wholesale Goods"
        }
    ],
    "sg:phone":"+1 418 485 6889",
    "sg:postcode":"G0M 1V0",
    "sg:province":"QC",
    "wof:name":"Cirouak 2000 Senc",
    "wof:placetype":"venue"
},
  "geometry": {"coordinates":[-70.829201,45.960655],"type":"Point"}
}