{
  "type": "Feature",
  "properties": {
    "iso:country":"CA",
    "sg:address":"2645 Portage Ave",
    "sg:city":"Winnipeg",
    "sg:classifiers":[
        {
            "category":"Professional",
            "subcategory":"Lawyer & Legal Services",
            "type":"Services"
        }
    ],
    "sg:phone":"+1 204 889 4595",
    "sg:postcode":"R3J 0P9",
    "sg:province":"MB",
    "sg:tags":[
        "attorney"
    ],
    "wof:name":"Shewchuk & Assoc",
    "wof:placetype":"venue"
},
  "geometry": {"coordinates":[-97.2704696655,49.8775901794],"type":"Point"}
}