{
  "type": "Feature",
  "properties": {
    "addr:full":"5151 Av Du Parc Montreal QC H2V 4G3",
    "addr:housenumber":"5151",
    "addr:postcode":"h2v 4g3",
    "addr:street":"Av Du Parc",
    "iso:country":"CA",
    "sg:address":"5151 Av Du Parc",
    "sg:city":"Montreal",
    "sg:classifiers":[
        {
            "category":"Retail",
            "subcategory":"Repair Shop",
            "type":"Services"
        }
    ],
    "sg:phone":"+1 514 270 6020",
    "sg:postcode":"H2V 4G3",
    "sg:province":"QC",
    "sg:tags":[
        "antique",
        "restoring"
    ],
    "wof:name":"Monnais Bijoux & Antiquites",
    "wof:placetype":"venue"
},
  "geometry": {"coordinates":[-73.5968170166,45.5202636719],"type":"Point"}
}