{
  "type": "Feature",
  "properties": {
    "addr:full":"5033 Hurontario St Mississauga ON L4Z 3X7",
    "addr:housenumber":"5033",
    "addr:postcode":"l4z 3x7",
    "addr:street":"Hurontario St",
    "iso:country":"CA",
    "sg:address":"5033 Hurontario St",
    "sg:city":"Mississauga",
    "sg:classifiers":[
        {
            "category":"Shopping",
            "subcategory":"Pharmacy",
            "type":"Retail Goods"
        }
    ],
    "sg:phone":"+1 905 890 1313",
    "sg:postcode":"L4Z 3X7",
    "sg:province":"ON",
    "sg:tags":[
        "grocer"
    ],
    "wof:name":"Shoppers Drug Mart",
    "wof:placetype":"venue"
},
  "geometry": {"coordinates":[-79.655243,43.608719],"type":"Point"}
}