{
  "type": "Feature",
  "properties": {
    "addr:full":"4709 29 St Vernon BC V1T 5C1",
    "addr:housenumber":"4709",
    "addr:postcode":"v1t 5c1",
    "addr:street":"29 St",
    "iso:country":"CA",
    "sg:address":"4709 29 St",
    "sg:city":"Vernon",
    "sg:classifiers":[
        {
            "category":"Home & Garden",
            "subcategory":"Building Materials",
            "type":"Retail Goods"
        }
    ],
    "sg:phone":"+1 250 542 7727",
    "sg:postcode":"V1T 5C1",
    "sg:province":"BC",
    "sg:tags":[
        "glass",
        "window",
        "plate"
    ],
    "wof:name":"Morgan's Glass CO Ltd",
    "wof:placetype":"venue"
},
  "geometry": {"coordinates":[-119.269745,50.280853],"type":"Point"}
}