{
  "type": "Feature",
  "properties": {
    "iso:country":"CA",
    "sg:address":"1250 Rue Graham-Bell",
    "sg:city":"Boucherville",
    "sg:classifiers":[
        {
            "category":"Building & Trades",
            "subcategory":"Construction",
            "type":"Services"
        }
    ],
    "sg:phone":"+1 450 449 2600",
    "sg:postcode":"J4B 6H5",
    "sg:province":"QC",
    "sg:tags":[
        "control",
        "corrosion"
    ],
    "wof:name":"Corrosion Service Cie Ltee",
    "wof:placetype":"venue"
},
  "geometry": {"coordinates":[-73.438339,45.563828],"type":"Point"}
}