{
  "type": "Feature",
  "properties": {
    "addr:full":"3230 Fairview St Burlington ON L7N 3H5",
    "addr:housenumber":"3230",
    "addr:postcode":"l7n 3h5",
    "addr:street":"Fairview St",
    "iso:country":"CA",
    "sg:address":"3230 Fairview St",
    "sg:city":"Burlington",
    "sg:classifiers":[
        {
            "category":"Shopping",
            "subcategory":"Department Store",
            "type":"Retail Goods"
        }
    ],
    "sg:phone":"+1 905 639 3792",
    "sg:postcode":"L7N 3H5",
    "sg:province":"ON",
    "sg:tags":[
        "shop"
    ],
    "wof:name":"Pier 1 Imports",
    "wof:placetype":"venue"
},
  "geometry": {"coordinates":[-79.789795,43.352074],"type":"Point"}
}