{
  "type": "Feature",
  "properties": {
    "addr:full":"6931 Steeles Ave W Etobicoke ON M9W 6K7",
    "addr:housenumber":"6931",
    "addr:postcode":"m9w 6k7",
    "addr:street":"Steeles Ave W",
    "iso:country":"CA",
    "sg:address":"6931 Steeles Ave W",
    "sg:city":"Etobicoke",
    "sg:classifiers":[
        {
            "category":"Restaurant",
            "type":"Food & Drink"
        }
    ],
    "sg:phone":"+1 416 213 8725",
    "sg:postcode":"M9W 6K7",
    "sg:province":"ON",
    "wof:name":"Gemelli Cafe",
    "wof:placetype":"venue"
},
  "geometry": {"coordinates":[-79.6207199097,43.7538642883],"type":"Point"}
}