{
  "type": "Feature",
  "properties": {
    "addr:full":"Surrey BC V3W 3M8",
    "addr:postcode":"v3w 3m8",
    "iso:country":"CA",
    "sg:city":"Surrey",
    "sg:classifiers":[
        {
            "category":"Restaurant",
            "type":"Food & Drink"
        }
    ],
    "sg:phone":"+1 604 572 6453",
    "sg:postcode":"V3W 3M8",
    "sg:province":"BC",
    "sg:tags":[
        "internet"
    ],
    "wof:name":"Synapse Internet",
    "wof:placetype":"venue"
},
  "geometry": {"coordinates":[-122.890151977,49.1323509216],"type":"Point"}
}