{
  "type": "Feature",
  "properties": {
    "addr:full":"5502 56 Ave SE Calgary AB T2C 4M6",
    "addr:housenumber":"5502",
    "addr:postcode":"t2c 4m6",
    "addr:street":"56 Ave Se",
    "iso:country":"CA",
    "sg:address":"5502 56 Ave SE",
    "sg:city":"Calgary",
    "sg:classifiers":[
        {
            "category":"Manufacturing",
            "subcategory":"Metals",
            "type":"Manufacturing & Wholesale Goods"
        }
    ],
    "sg:phone":"+1 403 720 4888",
    "sg:postcode":"T2C 4M6",
    "sg:province":"AB",
    "sg:tags":[
        "tank"
    ],
    "wof:name":"Advance Engineered Products",
    "wof:placetype":"venue"
},
  "geometry": {"coordinates":[-113.953712463,51.0022354126],"type":"Point"}
}