{
  "type": "Feature",
  "properties": {
    "addr:full":"2626 Av Saint-Germain Plessisville QC G6L 2J6",
    "addr:housenumber":"2626",
    "addr:postcode":"g6l 2j6",
    "addr:street":"Av Saint-Germain",
    "iso:country":"CA",
    "sg:address":"2626 Av Saint-Germain",
    "sg:city":"Plessisville",
    "sg:classifiers":[
        {
            "category":"Building & Trades",
            "subcategory":"Electrical",
            "type":"Services"
        }
    ],
    "sg:phone":"+1 819 362 1323",
    "sg:postcode":"G6L 2J6",
    "sg:province":"QC",
    "sg:tags":[
        "electric",
        "contractor"
    ],
    "wof:name":"Nadeau, Serge",
    "wof:placetype":"venue"
},
  "geometry": {"coordinates":[-71.783981,46.226341],"type":"Point"}
}