{
  "type": "Feature",
  "properties": {
    "addr:full":"2099 Gottingen St Halifax NS B3K 3B2",
    "addr:housenumber":"2099",
    "addr:postcode":"b3k 3b2",
    "addr:street":"Gottingen St",
    "iso:country":"CA",
    "sg:address":"2099 Gottingen St",
    "sg:city":"Halifax",
    "sg:classifiers":[
        {
            "category":"Organizations",
            "subcategory":"Non-profit Organization",
            "type":"Services"
        }
    ],
    "sg:phone":"+1 902 425 7677",
    "sg:postcode":"B3K 3B2",
    "sg:province":"NS",
    "sg:tags":[
        "fund",
        "counselor",
        "institution",
        "raising",
        "charitable"
    ],
    "wof:name":"Oxfam-Canada",
    "wof:placetype":"venue"
},
  "geometry": {"coordinates":[-63.58316,44.652046],"type":"Point"}
}