{
  "type": "Feature",
  "properties": {
    "addr:full":"141 Rue Industrielle Albanel QC G8M 3H8",
    "addr:housenumber":"141",
    "addr:postcode":"g8m 3h8",
    "addr:street":"Rue Industrielle",
    "iso:country":"CA",
    "sg:address":"141 Rue Industrielle",
    "sg:city":"Albanel",
    "sg:classifiers":[
        {
            "category":"Local Transit",
            "type":"Transportation"
        }
    ],
    "sg:phone":"+1 418 279 5571",
    "sg:postcode":"G8M 3H8",
    "sg:province":"QC",
    "sg:tags":[
        "bus",
        "line"
    ],
    "wof:name":"Transport Pg Inc",
    "wof:placetype":"venue"
},
  "geometry": {"coordinates":[-72.443459,48.887016],"type":"Point"}
}