{
  "type": "Feature",
  "properties": {
    "addr:full":"450 Flora Ave Winnipeg MB R2W 2R8",
    "addr:housenumber":"450",
    "addr:postcode":"r2w 2r8",
    "addr:street":"Flora Ave",
    "iso:country":"CA",
    "sg:address":"450 Flora Ave",
    "sg:city":"Winnipeg",
    "sg:classifiers":[
        {
            "category":"Education",
            "subcategory":"School",
            "type":"Public Place"
        }
    ],
    "sg:phone":"+1 204 589 6742",
    "sg:postcode":"R2W 2R8",
    "sg:province":"MB",
    "wof:name":"Niji Mahkwa School",
    "wof:placetype":"venue"
},
  "geometry": {"coordinates":[-97.143593,49.914188],"type":"Point"}
}