{
  "type": "Feature",
  "properties": {
    "addr:full":"Vancouver BC V6G 1C3",
    "addr:postcode":"v6g 1c3",
    "iso:country":"CA",
    "sg:city":"Vancouver",
    "sg:classifiers":[
        {
            "category":"Travel",
            "subcategory":"Travel Agent",
            "type":"Entertainment"
        }
    ],
    "sg:phone":"+1 604 602 7551",
    "sg:postcode":"V6G 1C3",
    "sg:province":"BC",
    "sg:tags":[
        "agency",
        "bureau"
    ],
    "wof:name":"Lace Travel Agency",
    "wof:placetype":"venue"
},
  "geometry": {"coordinates":[-123.131347656,49.2889823914],"type":"Point"}
}