{
  "type": "Feature",
  "properties": {
    "iso:country":"CA",
    "sg:city":"Toronto",
    "sg:classifiers":[
        {
            "category":"Professional",
            "subcategory":"Employment Agencies",
            "type":"Services"
        }
    ],
    "sg:phone":"+1 416 364 1515",
    "sg:postcode":"M5J 2N8",
    "sg:province":"ON",
    "sg:tags":[
        "opportunity"
    ],
    "wof:name":"Paragon Consulting",
    "wof:placetype":"venue"
},
  "geometry": {"coordinates":[-79.3774795532,43.6418685913],"type":"Point"}
}