{
  "type": "Feature",
  "properties": {
    "addr:full":"772 Willowbank Trail Mississauga ON L4W 3M1",
    "addr:housenumber":"772",
    "addr:postcode":"l4w 3m1",
    "addr:street":"Willowbank Trail",
    "iso:country":"CA",
    "sg:address":"772 Willowbank Trail",
    "sg:city":"Mississauga",
    "sg:classifiers":[
        {
            "category":"Real Estate",
            "subcategory":"Real Estate Agent",
            "type":"Services"
        }
    ],
    "sg:phone":"+1 905 848 2100",
    "sg:postcode":"L4W 3M1",
    "sg:province":"ON",
    "wof:name":"John Kuzma Real Estate Inc",
    "wof:placetype":"venue"
},
  "geometry": {"coordinates":[-79.624588,43.615379],"type":"Point"}
}