{
  "type": "Feature",
  "properties": {
    "addr:full":"1925 Rue Leon-Harmel Quebec QC G1N 4N8",
    "addr:housenumber":"1925",
    "addr:postcode":"g1n 4n8",
    "addr:street":"Rue Leon-Harmel",
    "iso:country":"CA",
    "sg:address":"1925 Rue Leon-Harmel",
    "sg:city":"Quebec",
    "sg:classifiers":[
        {
            "category":"Wholesale",
            "subcategory":"Electrical",
            "type":"Manufacturing & Wholesale Goods"
        }
    ],
    "sg:phone":"+1 418 821 2828",
    "sg:postcode":"G1N 4N8",
    "sg:province":"QC",
    "sg:tags":[
        "signal",
        "traffic",
        "sign"
    ],
    "wof:name":"Societe DE Svc En Signalisatn",
    "wof:placetype":"venue"
},
  "geometry": {"coordinates":[-71.27513122560001,46.8002471924],"type":"Point"}
}