{
  "type": "Feature",
  "properties": {
    "addr:full":"Outremont QC H2V 3Z1",
    "addr:postcode":"h2v 3z1",
    "iso:country":"CA",
    "sg:city":"Outremont",
    "sg:classifiers":[
        {
            "category":"Wholesale",
            "subcategory":"Machinery & Supplies",
            "type":"Manufacturing & Wholesale Goods"
        }
    ],
    "sg:phone":"+1 514 277 1531",
    "sg:postcode":"H2V 3Z1",
    "sg:province":"QC",
    "sg:tags":[
        "machine",
        "sewing"
    ],
    "wof:name":"National 2000",
    "wof:placetype":"venue"
},
  "geometry": {"coordinates":[-73.61372375489999,45.5255393982],"type":"Point"}
}