{
  "type": "Feature",
  "properties": {
    "iso:country":"CA",
    "sg:address":"130 Lappin Ave",
    "sg:city":"Toronto",
    "sg:classifiers":[
        {
            "category":"Food & Beverages",
            "subcategory":"Groceries & Convenience Stores",
            "type":"Retail Goods"
        }
    ],
    "sg:phone":"+1 416 588 1481",
    "sg:postcode":"M6H 1Y4",
    "sg:province":"ON",
    "sg:tags":[
        "grocer"
    ],
    "wof:name":"Lucky Food Mart",
    "wof:placetype":"venue"
},
  "geometry": {"coordinates":[-79.442909,43.6656],"type":"Point"}
}