{
  "type": "Feature",
  "properties": {
    "addr:full":"725 Boul St Paul N Riviere-Heva QC J0Y 2H0",
    "addr:housenumber":"725",
    "addr:postcode":"j0y 2h0",
    "addr:street":"Boul St;N",
    "iso:country":"CA",
    "sg:address":"725 Boul St Paul N",
    "sg:city":"Riviere-Heva",
    "sg:classifiers":[
        {
            "category":"Building & Trades",
            "subcategory":"Plumbing",
            "type":"Services"
        }
    ],
    "sg:phone":"+1 819 735 4507",
    "sg:postcode":"J0Y 2H0",
    "sg:province":"QC",
    "sg:tags":[
        "septic"
    ],
    "wof:name":"Fosses Septiques Ml Recuperat",
    "wof:placetype":"venue"
},
  "geometry": {"coordinates":[-78.220963,48.239117],"type":"Point"}
}