{
  "type": "Feature",
  "properties": {
    "addr:full":"34920 Orion Pl Abbotsford BC V2S 7R4",
    "addr:housenumber":"34920",
    "addr:postcode":"v2s 7r4",
    "addr:street":"Orion Pl",
    "iso:country":"CA",
    "sg:address":"34920 Orion Pl",
    "sg:city":"Abbotsford",
    "sg:classifiers":[
        {
            "category":"Building & Trades",
            "subcategory":"Construction",
            "type":"Services"
        }
    ],
    "sg:phone":"+1 604 852 4122",
    "sg:postcode":"V2S 7R4",
    "sg:province":"BC",
    "sg:tags":[
        "general",
        "contractor"
    ],
    "wof:name":"Jpl Construction Ltd",
    "wof:placetype":"venue"
},
  "geometry": {"coordinates":[-122.25700378400001,49.0434532166],"type":"Point"}
}