{
  "type": "Feature",
  "properties": {
    "iso:country":"CA",
    "sg:address":"100 Centre St",
    "sg:city":"Ponteix",
    "sg:classifiers":[
        {
            "category":"Building & Trades",
            "subcategory":"Construction",
            "type":"Services"
        }
    ],
    "sg:phone":"+1 306 625 3304",
    "sg:postcode":"S0N 1Z0",
    "sg:province":"SK",
    "sg:tags":[
        "excavating",
        "contractor"
    ],
    "wof:name":"Chuck's Backhoe Svc & Hauling",
    "wof:placetype":"venue"
},
  "geometry": {"coordinates":[-107.489372253,49.7462387085],"type":"Point"}
}