{
  "type": "Feature",
  "properties": {
    "addr:full":"111 Queen St E Brampton ON L6W 2A9",
    "addr:housenumber":"111",
    "addr:postcode":"l6w 2a9",
    "addr:street":"Queen St E",
    "iso:country":"CA",
    "sg:address":"111 Queen St E",
    "sg:city":"Brampton",
    "sg:classifiers":[
        {
            "category":"Personal",
            "subcategory":"Beauty Salon",
            "type":"Services"
        }
    ],
    "sg:phone":"+1 905 451 3010",
    "sg:postcode":"L6W 2A9",
    "sg:province":"ON",
    "wof:name":"Salon Spa One Eleven",
    "wof:placetype":"venue"
},
  "geometry": {"coordinates":[-79.755531311,43.6897125244],"type":"Point"}
}