{
  "type": "Feature",
  "properties": {
    "iso:country":"CA",
    "sg:address":"95 Somerset St W",
    "sg:city":"Ottawa",
    "sg:classifiers":[
        {
            "category":"Organizations",
            "subcategory":"Religious Organization",
            "type":"Services"
        }
    ],
    "sg:phone":"+1 613 235 5119",
    "sg:postcode":"K2P 0H3",
    "sg:province":"ON",
    "sg:tags":[
        "church"
    ],
    "wof:name":"St Theresa Church",
    "wof:placetype":"venue"
},
  "geometry": {"coordinates":[-75.688278,45.418892],"type":"Point"}
}