{
  "type": "Feature",
  "properties": {
    "iso:country":"CA",
    "sg:address":"5111 49 St",
    "sg:city":"Red Deer",
    "sg:classifiers":[
        {
            "category":"Restaurant",
            "type":"Food & Drink"
        }
    ],
    "sg:phone":"+1 403 347 7750",
    "sg:postcode":"T4N 1V6",
    "sg:province":"AB",
    "wof:name":"Pita Pit",
    "wof:placetype":"venue"
},
  "geometry": {"coordinates":[-113.81671900000001,52.267941],"type":"Point"}
}