{
  "type": "Feature",
  "properties": {
    "addr:full":"2544 Kingsway Vancouver BC V5R 5H2",
    "addr:housenumber":"2544",
    "addr:postcode":"v5r 5h2",
    "addr:street":"Kingsway",
    "iso:country":"CA",
    "sg:address":"2544 Kingsway",
    "sg:city":"Vancouver",
    "sg:classifiers":[
        {
            "category":"Retail",
            "subcategory":"Laundry & Dry Cleaning",
            "type":"Services"
        }
    ],
    "sg:phone":"+1 604 433 3711",
    "sg:postcode":"V5R 5H2",
    "sg:province":"BC",
    "sg:tags":[
        "cleaners"
    ],
    "wof:name":"Clean-Rite Dry Cleaners",
    "wof:placetype":"venue"
},
  "geometry": {"coordinates":[-123.053268,49.239479],"type":"Point"}
}