{
  "type": "Feature",
  "properties": {
    "addr:full":"7120 Edwards Blvd Mississauga ON L5S 1Z1",
    "addr:housenumber":"7120",
    "addr:postcode":"l5s 1z1",
    "addr:street":"Edwards Blvd",
    "iso:country":"CA",
    "sg:address":"7120 Edwards Blvd",
    "sg:city":"Mississauga",
    "sg:classifiers":[
        {
            "category":"Wholesale",
            "subcategory":"Meat",
            "type":"Manufacturing & Wholesale Goods"
        }
    ],
    "sg:phone":"+1 905 795 0001",
    "sg:postcode":"L5S 1Z1",
    "sg:province":"ON",
    "sg:tags":[
        "poultry",
        "plant",
        "processing"
    ],
    "wof:name":"Puddy Brothers Ltd",
    "wof:placetype":"venue"
},
  "geometry": {"coordinates":[-79.7068099976,43.6498985291],"type":"Point"}
}