{
  "type": "Feature",
  "properties": {
    "addr:full":"505 2 St SW Calgary AB T2P 1N8",
    "addr:housenumber":"505 2",
    "addr:postcode":"t2p 1n8",
    "addr:street":"St Sw",
    "iso:country":"CA",
    "sg:address":"505 2 St SW",
    "sg:city":"Calgary",
    "sg:classifiers":[
        {
            "category":"Banks & Credit Unions",
            "subcategory":"Investment Brokerage",
            "type":"Services"
        }
    ],
    "sg:phone":"+1 403 503 6578",
    "sg:postcode":"T2P 1N8",
    "sg:province":"AB",
    "sg:tags":[
        "stock",
        "broker",
        "bond"
    ],
    "wof:name":"Td Waterhouse",
    "wof:placetype":"venue"
},
  "geometry": {"coordinates":[-114.067863464,51.0483551025],"type":"Point"}
}