{
  "type": "Feature",
  "properties": {
    "addr:full":"Barriere BC V0E 1E0",
    "addr:postcode":"v0e 1e0",
    "iso:country":"CA",
    "sg:city":"Barriere",
    "sg:classifiers":[
        {
            "category":"Travel",
            "subcategory":"Hotels & Motels",
            "type":"Entertainment"
        }
    ],
    "sg:phone":"+1 250 672 0090",
    "sg:postcode":"V0E 1E0",
    "sg:province":"BC",
    "wof:name":"Mountain Springs Motel",
    "wof:placetype":"venue"
},
  "geometry": {"coordinates":[-120.126487732,51.1681251526],"type":"Point"}
}