{
  "type": "Feature",
  "properties": {
    "addr:full":"961 Boul Talbot Chicoutimi QC G7H 4B5",
    "addr:housenumber":"961",
    "addr:postcode":"g7h 4b5",
    "addr:street":"Boul Talbot",
    "iso:country":"CA",
    "sg:address":"961 Boul Talbot",
    "sg:city":"Chicoutimi",
    "sg:classifiers":[
        {
            "category":"Cinema",
            "subcategory":"Movie Rental",
            "type":"Entertainment"
        }
    ],
    "sg:phone":"+1 418 549 3322",
    "sg:postcode":"G7H 4B5",
    "sg:province":"QC",
    "sg:tags":[
        "leasing",
        "video",
        "disc",
        "tape"
    ],
    "wof:name":"Superclub Videotron Ltee",
    "wof:placetype":"venue"
},
  "geometry": {"coordinates":[-71.049949646,48.4130554199],"type":"Point"}
}