{
  "type": "Feature",
  "properties": {
    "addr:full":"70 Penniac Rd Penniac NB E3A 8Y7",
    "addr:housenumber":"70",
    "addr:postcode":"e3a 8y7",
    "addr:street":"Penniac Rd",
    "iso:country":"CA",
    "sg:address":"70 Penniac Rd",
    "sg:city":"Penniac",
    "sg:classifiers":[
        {
            "category":"Building & Trades",
            "subcategory":"Construction",
            "type":"Services"
        }
    ],
    "sg:phone":"+1 506 474 0353",
    "sg:postcode":"E3A 8Y7",
    "sg:province":"NB",
    "sg:tags":[
        "home",
        "improvement"
    ],
    "wof:name":"Jardine Renovations",
    "wof:placetype":"venue"
},
  "geometry": {"coordinates":[-66.56353799999999,46.03875],"type":"Point"}
}