{
  "type": "Feature",
  "properties": {
    "addr:full":"104 King Edward St E Winnipeg MB R3H 0N8",
    "addr:housenumber":"104",
    "addr:postcode":"r3h 0n8",
    "addr:street":"King Edward St E",
    "iso:country":"CA",
    "sg:address":"104 King Edward St E",
    "sg:city":"Winnipeg",
    "sg:classifiers":[
        {
            "category":"Wholesale",
            "subcategory":"Non-durable Goods",
            "type":"Manufacturing & Wholesale Goods"
        }
    ],
    "sg:phone":"+1 204 775 4995",
    "sg:postcode":"R3H 0N8",
    "sg:province":"MB",
    "sg:tags":[
        "leather",
        "saddlery",
        "harness"
    ],
    "wof:name":"Leather Factory of Canada",
    "wof:placetype":"venue"
},
  "geometry": {"coordinates":[-97.206001,49.890987],"type":"Point"}
}