{
  "type": "Feature",
  "properties": {
    "addr:full":"103 Rue Lebrun Riviere-Du-Loup QC G5R 3Z5",
    "addr:housenumber":"103",
    "addr:postcode":"g5r 3z5",
    "addr:street":"Rue Lebrun Riviere-Du-Loup",
    "iso:country":"CA",
    "sg:address":"103 Rue Lebrun",
    "sg:city":"Riviere-Du-Loup",
    "sg:classifiers":[
        {
            "category":"Manufacturing",
            "subcategory":"Buildings",
            "type":"Manufacturing & Wholesale Goods"
        }
    ],
    "sg:phone":"+1 418 862 9628",
    "sg:postcode":"G5R 3Z5",
    "sg:province":"QC",
    "sg:tags":[
        "prefab"
    ],
    "wof:name":"Construction Goscobec Inc",
    "wof:placetype":"venue"
},
  "geometry": {"coordinates":[-69.53703308110001,47.8350410461],"type":"Point"}
}