{
  "type": "Feature",
  "properties": {
    "iso:country":"CA",
    "sg:address":"45903 Wellington Ave",
    "sg:city":"Chilliwack",
    "sg:classifiers":[
        {
            "category":"Shopping",
            "subcategory":"Clothing, Apparel, & Fashions",
            "type":"Retail Goods"
        }
    ],
    "sg:phone":"+1 604 792 3215",
    "sg:postcode":"V2P 2C8",
    "sg:province":"BC",
    "sg:tags":[
        "infant",
        "wear"
    ],
    "wof:name":"Teddy Bear Dreams Infant's",
    "wof:placetype":"venue"
},
  "geometry": {"coordinates":[-121.953857422,49.1715164185],"type":"Point"}
}