{
  "type": "Feature",
  "properties": {
    "addr:full":"1911 Weston Rd York ON M9N 1W7",
    "addr:housenumber":"1911",
    "addr:postcode":"m9n 1w7",
    "addr:street":"Weston Rd",
    "iso:country":"CA",
    "sg:address":"1911 Weston Rd",
    "sg:city":"York",
    "sg:classifiers":[
        {
            "category":"Shopping",
            "subcategory":"Optical Goods",
            "type":"Retail Goods"
        }
    ],
    "sg:phone":"+1 416 244 1137",
    "sg:postcode":"M9N 1W7",
    "sg:province":"ON",
    "sg:tags":[
        "contact",
        "lense",
        "optician"
    ],
    "wof:name":"Hakim Optical Factory Outlet",
    "wof:placetype":"venue"
},
  "geometry": {"coordinates":[-79.516655,43.700439],"type":"Point"}
}