{
  "type": "Feature",
  "properties": {
    "addr:full":"159 Wellington St Kingston ON K7L 3E1",
    "addr:housenumber":"159",
    "addr:postcode":"k7l 3e1",
    "addr:street":"Wellington St",
    "iso:country":"CA",
    "sg:address":"159 Wellington St",
    "sg:city":"Kingston",
    "sg:classifiers":[
        {
            "category":"Social Services",
            "type":"Services"
        }
    ],
    "sg:phone":"+1 613 546 0600",
    "sg:postcode":"K7L 3E1",
    "sg:province":"ON",
    "sg:tags":[
        "counselor",
        "marriage",
        "family"
    ],
    "wof:name":"White, C",
    "wof:placetype":"venue"
},
  "geometry": {"coordinates":[-76.4827575684,44.2305641174],"type":"Point"}
}