{
  "type": "Feature",
  "properties": {
    "addr:full":"Scarborough ON M1G 2M3",
    "addr:postcode":"m1g 2m3",
    "iso:country":"CA",
    "sg:city":"Scarborough",
    "sg:classifiers":[
        {
            "category":"Health Services",
            "subcategory":"Medical Lab",
            "type":"Services"
        }
    ],
    "sg:phone":"+1 416 289 7571",
    "sg:postcode":"M1G 2M3",
    "sg:province":"ON",
    "sg:tags":[
        "laboratory"
    ],
    "wof:name":"Vincent Chan Dental Lab",
    "wof:placetype":"venue"
},
  "geometry": {"coordinates":[-79.226952,43.768143],"type":"Point"}
}