{
  "type": "Feature",
  "properties": {
    "addr:full":"994 2nd Ave Dawson YT Y0B 1G0",
    "addr:housenumber":"994",
    "addr:postcode":"y0b 1g0",
    "addr:street":"2Nd Ave",
    "iso:country":"CA",
    "sg:address":"994 2nd Ave",
    "sg:city":"Dawson",
    "sg:classifiers":[
        {
            "category":"Personal",
            "subcategory":"Beauty Salon",
            "type":"Services"
        }
    ],
    "sg:phone":"+1 867 993 5222",
    "sg:postcode":"Y0B 1G0",
    "sg:province":"YT",
    "wof:name":"Hair Cabaret & Esthetic's Etc",
    "wof:placetype":"venue"
},
  "geometry": {"coordinates":[-139.43377699999999,64.06199599999999],"type":"Point"}
}