{
  "type": "Feature",
  "properties": {
    "addr:full":"650 Windmill Rd Dartmouth NS B3B 1B8",
    "addr:housenumber":"650",
    "addr:postcode":"b3b 1b8",
    "addr:street":"Windmill Rd",
    "iso:country":"CA",
    "sg:address":"650 Windmill Rd",
    "sg:city":"Dartmouth",
    "sg:classifiers":[
        {
            "category":"Restaurant",
            "type":"Food & Drink"
        }
    ],
    "sg:phone":"+1 902 468 6966",
    "sg:postcode":"B3B 1B8",
    "sg:province":"NS",
    "wof:name":"A & W Family Restaurant",
    "wof:placetype":"venue"
},
  "geometry": {"coordinates":[-63.6056251526,44.6990699768],"type":"Point"}
}