{
  "type": "Feature",
  "properties": {
    "addr:full":"North York ON M6B 1W3",
    "addr:postcode":"m6b 1w3",
    "iso:country":"CA",
    "sg:city":"North York",
    "sg:classifiers":[
        {
            "category":"Wholesale",
            "subcategory":"Construction Materials",
            "type":"Manufacturing & Wholesale Goods"
        }
    ],
    "sg:phone":"+1 416 249 6581",
    "sg:postcode":"M6B 1W3",
    "sg:province":"ON",
    "sg:tags":[
        "terrazzo"
    ],
    "wof:name":"Nougart",
    "wof:placetype":"venue"
},
  "geometry": {"coordinates":[-79.45863300000001,43.704334],"type":"Point"}
}