{
  "type": "Feature",
  "properties": {
    "iso:country":"CA",
    "sg:address":"4580 Pendlebury Rd",
    "sg:city":"Richmond",
    "sg:classifiers":[
        {
            "category":"Professional",
            "type":"Services"
        }
    ],
    "sg:phone":"+1 604 241 7699",
    "sg:postcode":"V7E 1E7",
    "sg:province":"BC",
    "sg:tags":[
        "home",
        "planning"
    ],
    "wof:name":"Rafiq Shaikh Designs Ltd",
    "wof:placetype":"venue"
},
  "geometry": {"coordinates":[-123.175858,49.144115],"type":"Point"}
}