{
  "type": "Feature",
  "properties": {
    "addr:full":"PO Box 936 Sparwood BC V0B 2G0",
    "addr:housenumber":"po",
    "addr:postcode":"bc v0b 2g0",
    "addr:street":"Box 936",
    "iso:country":"CA",
    "sg:address":"PO Box 936",
    "sg:city":"Sparwood",
    "sg:classifiers":[
        {
            "category":"Organizations",
            "subcategory":"Religious Organization",
            "type":"Services"
        }
    ],
    "sg:phone":"+1 250 425 7019",
    "sg:postcode":"V0B 2G0",
    "sg:province":"BC",
    "sg:tags":[
        "church"
    ],
    "wof:name":"St Barbara Anglican Church",
    "wof:placetype":"venue"
},
  "geometry": {"coordinates":[-114.888908,49.724892],"type":"Point"}
}