{
  "type": "Feature",
  "properties": {
    "addr:full":"900 Boul Grignon Saint-Jerome QC J7Y 3S7",
    "addr:housenumber":"900",
    "addr:postcode":"j7y 3s7",
    "addr:street":"Boul Grignon Saint-Jerome",
    "iso:country":"CA",
    "sg:address":"900 Boul Grignon",
    "sg:city":"Saint-Jerome",
    "sg:classifiers":[
        {
            "category":"Real Estate",
            "subcategory":"Real Estate Agent",
            "type":"Services"
        }
    ],
    "sg:phone":"+1 450 565 6103",
    "sg:postcode":"J7Y 3S7",
    "sg:province":"QC",
    "sg:tags":[
        "consultant"
    ],
    "wof:name":"Groupe Sutton Laurentides",
    "wof:placetype":"venue"
},
  "geometry": {"coordinates":[-74.015625,45.794719696],"type":"Point"}
}