{
  "type": "Feature",
  "properties": {
    "addr:full":"584 Wentworth St N Hamilton ON L8L 5X3",
    "addr:housenumber":"584",
    "addr:postcode":"l8l 5x3",
    "addr:street":"Wentworth St N",
    "iso:country":"CA",
    "sg:address":"584 Wentworth St N",
    "sg:city":"Hamilton",
    "sg:classifiers":[
        {
            "category":"Manufacturing",
            "subcategory":"Watercraft",
            "type":"Manufacturing & Wholesale Goods"
        }
    ],
    "sg:phone":"+1 905 777 9151",
    "sg:postcode":"L8L 5X3",
    "sg:province":"ON",
    "sg:tags":[
        "builder",
        "ship",
        "repairer"
    ],
    "wof:name":"Barda Marine & Mechanical Inc",
    "wof:placetype":"venue"
},
  "geometry": {"coordinates":[-79.84137699999999,43.269127],"type":"Point"}
}