{
  "type": "Feature",
  "properties": {
    "iso:country":"CA",
    "sg:address":"500 St-Bruno",
    "sg:city":"Bon-Conseil",
    "sg:classifiers":[
        {
            "category":"Social Services",
            "subcategory":"Child Care",
            "type":"Services"
        }
    ],
    "sg:phone":"+1 819 850 1686",
    "sg:postcode":"J0C 1A0",
    "sg:province":"QC",
    "wof:name":"Service DE Garde Ecole Bon",
    "wof:placetype":"venue"
},
  "geometry": {"coordinates":[-72.3432922363,45.9990348816],"type":"Point"}
}