{
  "type": "Feature",
  "properties": {
    "addr:full":"29 Park St W Dundas ON L9H 1X3",
    "addr:housenumber":"29",
    "addr:postcode":"l9h 1x3",
    "addr:street":"Park St W",
    "iso:country":"CA",
    "sg:address":"29 Park St W",
    "sg:city":"Dundas",
    "sg:classifiers":[
        {
            "category":"Organizations",
            "subcategory":"Religious Organization",
            "type":"Services"
        }
    ],
    "sg:phone":"+1 905 628 6396",
    "sg:postcode":"L9H 1X3",
    "sg:province":"ON",
    "sg:tags":[
        "church"
    ],
    "wof:name":"St Pauls United Church",
    "wof:placetype":"venue"
},
  "geometry": {"coordinates":[-79.95486450200001,43.2674598694],"type":"Point"}
}