{
  "type": "Feature",
  "properties": {
    "addr:full":"Anjou QC H1J 2R4",
    "addr:postcode":"h1j 2r4",
    "iso:country":"CA",
    "sg:city":"Anjou",
    "sg:classifiers":[
        {
            "category":"Education",
            "subcategory":"Special Training",
            "type":"Public Place"
        }
    ],
    "sg:phone":"+1 514 353 8656",
    "sg:postcode":"H1J 2R4",
    "sg:province":"QC",
    "sg:tags":[
        "instruction",
        "music"
    ],
    "wof:name":"Louise & Erik Enr",
    "wof:placetype":"venue"
},
  "geometry": {"coordinates":[-73.583504,45.606182],"type":"Point"}
}