{
  "type": "Feature",
  "properties": {
    "iso:country":"CA",
    "sg:address":"20 Ontario St",
    "sg:city":"Port Hope",
    "sg:classifiers":[
        {
            "category":"Restaurant",
            "type":"Food & Drink"
        }
    ],
    "sg:phone":"+1 905 885 9339",
    "sg:postcode":"L1A 2T6",
    "sg:province":"ON",
    "wof:name":"Broghans",
    "wof:placetype":"venue"
},
  "geometry": {"coordinates":[-78.29406738279999,43.9521179199],"type":"Point"}
}