{
  "type": "Feature",
  "properties": {
    "iso:country":"CA",
    "sg:address":"135 2nd Ave NE",
    "sg:city":"Dauphin",
    "sg:classifiers":[
        {
            "category":"Government",
            "subcategory":"Office",
            "type":"Public Place"
        }
    ],
    "sg:phone":"+1 204 622 4002",
    "sg:postcode":"R7N 0Z6",
    "sg:province":"MB",
    "wof:name":"Canada Human Resources Ctr",
    "wof:placetype":"venue"
},
  "geometry": {"coordinates":[-100.046386719,51.1490364075],"type":"Point"}
}