{
  "type": "Feature",
  "properties": {
    "addr:full":"7500 Tecumseh Rd E Pointe Aux Roches ON N0R 1N0",
    "addr:housenumber":"7500",
    "addr:postcode":"n0r 1n0",
    "addr:street":"Tecumseh Rd E Pointe Aux Roches",
    "iso:country":"CA",
    "sg:address":"7500 Tecumseh Rd E",
    "sg:city":"Pointe Aux Roches",
    "sg:classifiers":[
        {
            "category":"Organizations",
            "subcategory":"Professional Association",
            "type":"Services"
        }
    ],
    "sg:phone":"+1 519 798 5704",
    "sg:postcode":"N0R 1N0",
    "sg:province":"ON",
    "sg:tags":[
        "club"
    ],
    "wof:name":"L'Age D'Or DE Pointe Aux Rchs",
    "wof:placetype":"venue"
},
  "geometry": {"coordinates":[-82.544296,42.304714],"type":"Point"}
}