{
  "type": "Feature",
  "properties": {
    "addr:full":"73 Rue Notre-Dame Oka QC J0N 1E0",
    "addr:housenumber":"73",
    "addr:postcode":"j0n 1e0",
    "addr:street":"Rue Notre-Dame",
    "iso:country":"CA",
    "sg:address":"73 Rue Notre-Dame",
    "sg:city":"Oka",
    "sg:classifiers":[
        {
            "category":"Home & Garden",
            "subcategory":"Home Furnishings",
            "type":"Retail Goods"
        }
    ],
    "sg:phone":"+1 450 479 6890",
    "sg:postcode":"J0N 1E0",
    "sg:province":"QC",
    "sg:tags":[
        "pottery"
    ],
    "wof:name":"Maeder, Helga",
    "wof:placetype":"venue"
},
  "geometry": {"coordinates":[-74.0830078125,45.4634666443],"type":"Point"}
}