{
  "type": "Feature",
  "properties": {
    "addr:full":"12 Mckay St Cayuga ON N0A 1E0",
    "addr:housenumber":"12",
    "addr:postcode":"n0a 1e0",
    "addr:street":"Mckay St",
    "iso:country":"CA",
    "sg:address":"12 Mckay St",
    "sg:city":"Cayuga",
    "sg:classifiers":[
        {
            "category":"Health Services",
            "subcategory":"Doctor",
            "type":"Services"
        }
    ],
    "sg:phone":"+1 905 772 3581",
    "sg:postcode":"N0A 1E0",
    "sg:province":"ON",
    "sg:tags":[
        "physician",
        "surgeon"
    ],
    "wof:name":"Bulger, W J MD",
    "wof:placetype":"venue"
},
  "geometry": {"coordinates":[-79.854591,42.949532],"type":"Point"}
}