{
  "type": "Feature",
  "properties": {
    "iso:country":"CA",
    "sg:city":"Cranbrook",
    "sg:classifiers":[
        {
            "category":"Manufacturing",
            "subcategory":"Metals",
            "type":"Manufacturing & Wholesale Goods"
        }
    ],
    "sg:phone":"+1 250 426 3711",
    "sg:postcode":"V1C 4E5",
    "sg:province":"BC",
    "sg:tags":[
        "engraver"
    ],
    "wof:name":"Champion Trophies & Signs",
    "wof:placetype":"venue"
},
  "geometry": {"coordinates":[-115.77199554400001,49.5150146484],"type":"Point"}
}