{
  "type": "Feature",
  "properties": {
    "addr:full":"4814 32 St SE Calgary AB T2B 2S6",
    "addr:housenumber":"4814",
    "addr:postcode":"t2b 2s6",
    "addr:street":"32 St Se",
    "iso:country":"CA",
    "sg:address":"4814 32 St SE",
    "sg:city":"Calgary",
    "sg:classifiers":[
        {
            "category":"Manufacturing",
            "subcategory":"Tools & Machinery",
            "type":"Manufacturing & Wholesale Goods"
        }
    ],
    "sg:phone":"+1 403 295 9440",
    "sg:postcode":"T2B 2S6",
    "sg:province":"AB",
    "sg:tags":[
        "boring",
        "drilling"
    ],
    "wof:name":"Mash Bits & Drilling Supply",
    "wof:placetype":"venue"
},
  "geometry": {"coordinates":[-113.98638200000001,51.011269],"type":"Point"}
}