{
  "type": "Feature",
  "properties": {
    "iso:country":"CA",
    "sg:address":"198 King St E",
    "sg:city":"Gananoque",
    "sg:classifiers":[
        {
            "category":"Shopping",
            "subcategory":"Gifts & Souvenirs",
            "type":"Retail Goods"
        }
    ],
    "sg:phone":"+1 613 382 8120",
    "sg:postcode":"K7G 1G2",
    "sg:province":"ON",
    "sg:tags":[
        "shop"
    ],
    "wof:name":"Perfect Place For Gifts",
    "wof:placetype":"venue"
},
  "geometry": {"coordinates":[-76.160987854,44.3307685852],"type":"Point"}
}