{
  "type": "Feature",
  "properties": {
    "iso:country":"CA",
    "sg:address":"295 Rue Saint-Joseph",
    "sg:city":"Levis",
    "sg:classifiers":[
        {
            "category":"Education",
            "subcategory":"School",
            "type":"Public Place"
        }
    ],
    "sg:phone":"+1 418 838 8562",
    "sg:postcode":"G6V 1G3",
    "sg:province":"QC",
    "wof:name":"St-Joseph Ecoles Primaries",
    "wof:placetype":"venue"
},
  "geometry": {"coordinates":[-71.1650238037,46.8260154724],"type":"Point"}
}