{
  "type": "Feature",
  "properties": {
    "addr:full":"Cambridge ON N1S 2L3",
    "addr:postcode":"n1s 2l3",
    "iso:country":"CA",
    "sg:city":"Cambridge",
    "sg:classifiers":[
        {
            "category":"Health Services",
            "subcategory":"Doctor",
            "type":"Services"
        }
    ],
    "sg:phone":"+1 519 624 6809",
    "sg:postcode":"N1S 2L3",
    "sg:province":"ON",
    "sg:tags":[
        "dentist"
    ],
    "wof:name":"Stewart, Brian DDS",
    "wof:placetype":"venue"
},
  "geometry": {"coordinates":[-80.317413,43.358234],"type":"Point"}
}