{
  "type": "Feature",
  "properties": {
    "addr:full":"550 Alden Rd # 104 Markham ON L3R 6A8",
    "addr:housenumber":"550",
    "addr:postcode":"l3r 6a8",
    "addr:street":"Alden Rd # 104",
    "iso:country":"CA",
    "sg:address":"550 Alden Rd # 104",
    "sg:city":"Markham",
    "sg:classifiers":[
        {
            "category":"Shopping",
            "subcategory":"Computers & Home Electronics",
            "type":"Retail Goods"
        }
    ],
    "sg:phone":"+1 905 477 1222",
    "sg:postcode":"L3R 6A8",
    "sg:province":"ON",
    "sg:tags":[
        "radio",
        "television",
        "video",
        "equipment"
    ],
    "wof:name":"Reliable Audio",
    "wof:placetype":"venue"
},
  "geometry": {"coordinates":[-79.3320770264,43.836681366],"type":"Point"}
}