{
  "type": "Feature",
  "properties": {
    "addr:full":"5317 Lane St Burnaby BC V5H 2H4",
    "addr:housenumber":"5317",
    "addr:postcode":"v5h 2h4",
    "addr:street":"Lane St",
    "iso:country":"CA",
    "sg:address":"5317 Lane St",
    "sg:city":"Burnaby",
    "sg:classifiers":[
        {
            "category":"Banks & Credit Unions",
            "subcategory":"Bank",
            "type":"Services"
        }
    ],
    "sg:phone":"+1 604 430 0450",
    "sg:postcode":"V5H 2H4",
    "sg:province":"BC",
    "sg:tags":[
        "factor"
    ],
    "wof:name":"Geneva Capital Corp",
    "wof:placetype":"venue"
},
  "geometry": {"coordinates":[-122.986923218,49.2226104736],"type":"Point"}
}