{
  "type": "Feature",
  "properties": {
    "addr:full":"Kirkland Lake ON P2N 2C9",
    "addr:postcode":"p2n 2c9",
    "iso:country":"CA",
    "sg:city":"Kirkland Lake",
    "sg:classifiers":[
        {
            "category":"Shopping",
            "subcategory":"Florist",
            "type":"Retail Goods"
        }
    ],
    "sg:phone":"+1 705 568 8719",
    "sg:postcode":"P2N 2C9",
    "sg:province":"ON",
    "wof:name":"Dorothy's Flower Shop",
    "wof:placetype":"venue"
},
  "geometry": {"coordinates":[-80.033165,48.150787],"type":"Point"}
}