{
  "type": "Feature",
  "properties": {
    "addr:full":"Saskatoon SK S7K 0M7",
    "addr:postcode":"s7k 0m7",
    "iso:country":"CA",
    "sg:city":"Saskatoon",
    "sg:classifiers":[
        {
            "category":"Health Services",
            "subcategory":"Health Practitioner",
            "type":"Services"
        }
    ],
    "sg:phone":"+1 306 655 8974",
    "sg:postcode":"S7K 0M7",
    "sg:province":"SK",
    "sg:tags":[
        "therapist",
        "physical"
    ],
    "wof:name":"Kinetik",
    "wof:placetype":"venue"
},
  "geometry": {"coordinates":[-106.652000427,52.1365470886],"type":"Point"}
}