{
  "type": "Feature",
  "properties": {
    "addr:full":"109 Main St W Beeton ON L0G 1A0",
    "addr:housenumber":"109",
    "addr:postcode":"l0g 1a0",
    "addr:street":"Main St W Beeton",
    "iso:country":"CA",
    "sg:address":"109 Main St W",
    "sg:city":"Beeton",
    "sg:classifiers":[
        {
            "category":"Retail",
            "subcategory":"Veterinary Services",
            "type":"Services"
        }
    ],
    "sg:phone":"+1 905 729 2273",
    "sg:postcode":"L0G 1A0",
    "sg:province":"ON",
    "sg:tags":[
        "veterinarian"
    ],
    "wof:name":"Beeton Veterinary Clinic",
    "wof:placetype":"venue"
},
  "geometry": {"coordinates":[-79.789558,44.077686],"type":"Point"}
}