{
  "type": "Feature",
  "properties": {
    "iso:country":"CA",
    "sg:address":"546 St Paul St # 440",
    "sg:city":"Kamloops",
    "sg:classifiers":[
        {
            "category":"Government",
            "subcategory":"Office",
            "type":"Public Place"
        }
    ],
    "sg:phone":"+1 250 828 4530",
    "sg:postcode":"V2C 5T1",
    "sg:province":"BC",
    "wof:name":"BC Electrical Inspectors",
    "wof:placetype":"venue"
},
  "geometry": {"coordinates":[-120.328422546,50.6741981506],"type":"Point"}
}