{
  "type": "Feature",
  "properties": {
    "addr:full":"68 Xavier St Sudbury ON P3C 2B9",
    "addr:housenumber":"68",
    "addr:postcode":"p3c 2b9",
    "addr:street":"Xavier St",
    "iso:country":"CA",
    "sg:address":"68 Xavier St",
    "sg:city":"Sudbury",
    "sg:classifiers":[
        {
            "category":"Social Services",
            "type":"Services"
        }
    ],
    "sg:phone":"+1 705 674 9996",
    "sg:postcode":"P3C 2B9",
    "sg:province":"ON",
    "sg:tags":[
        "housing",
        "assistance"
    ],
    "wof:name":"Native People of Sudbury Dev",
    "wof:placetype":"venue"
},
  "geometry": {"coordinates":[-80.993706,46.495518],"type":"Point"}
}