{
  "type": "Feature",
  "properties": {
    "addr:full":"5200 Rue Pare Montreal QC H4P 1P5",
    "addr:housenumber":"5200",
    "addr:postcode":"h4p 1p5",
    "addr:street":"Rue Pare",
    "iso:country":"CA",
    "sg:address":"5200 Rue Pare",
    "sg:city":"Montreal",
    "sg:classifiers":[
        {
            "category":"Utilities",
            "subcategory":"Mobile Phone",
            "type":"Services"
        }
    ],
    "sg:phone":"+1 514 733 5000",
    "sg:postcode":"H4P 1P5",
    "sg:province":"QC",
    "sg:tags":[
        "telephone",
        "cellular"
    ],
    "wof:name":"Cellcom Communications",
    "wof:placetype":"venue"
},
  "geometry": {"coordinates":[-73.6539077759,45.4972381592],"type":"Point"}
}