{
  "type": "Feature",
  "properties": {
    "addr:full":"236 High St Southampton ON N0H 2L0",
    "addr:housenumber":"236",
    "addr:postcode":"n0h 2l0",
    "addr:street":"High St",
    "iso:country":"CA",
    "sg:address":"236 High St",
    "sg:city":"Southampton",
    "sg:classifiers":[
        {
            "category":"Shopping",
            "subcategory":"Bicycles & Sporting Goods",
            "type":"Retail Goods"
        }
    ],
    "sg:phone":"+1 519 797 3645",
    "sg:postcode":"N0H 2L0",
    "sg:province":"ON",
    "wof:name":"Martin's Home Hardware",
    "wof:placetype":"venue"
},
  "geometry": {"coordinates":[-81.36998699999999,44.495152],"type":"Point"}
}