{
  "type": "Feature",
  "properties": {
    "addr:full":"Brossard QC J4W 1M3",
    "addr:postcode":"j4w 1m3",
    "iso:country":"CA",
    "sg:city":"Brossard",
    "sg:classifiers":[
        {
            "category":"Health Services",
            "subcategory":"Doctor",
            "type":"Services"
        }
    ],
    "sg:phone":"+1 450 445 5445",
    "sg:postcode":"J4W 1M3",
    "sg:province":"QC",
    "sg:tags":[
        "dentist"
    ],
    "wof:name":"Centre Dentaire Familial",
    "wof:placetype":"venue"
},
  "geometry": {"coordinates":[-73.46959699999999,45.473305],"type":"Point"}
}