{
  "type": "Feature",
  "properties": {
    "addr:full":"382 Mcdonnel St Peterborough ON K9H 2X4",
    "addr:housenumber":"382",
    "addr:postcode":"k9h 2x4",
    "addr:street":"Mcdonnel St",
    "iso:country":"CA",
    "sg:address":"382 Mcdonnel St",
    "sg:city":"Peterborough",
    "sg:classifiers":[
        {
            "category":"Food & Beverages",
            "subcategory":"Groceries & Convenience Stores",
            "type":"Retail Goods"
        }
    ],
    "sg:phone":"+1 705 749 6148",
    "sg:postcode":"K9H 2X4",
    "sg:province":"ON",
    "sg:tags":[
        "grocer"
    ],
    "wof:name":"Choi's Convenience",
    "wof:placetype":"venue"
},
  "geometry": {"coordinates":[-78.33061218260001,44.3093643188],"type":"Point"}
}