{
  "type": "Feature",
  "properties": {
    "iso:country":"CA",
    "sg:address":"1650 Boul Lionel-Bertrand",
    "sg:city":"Boisbriand",
    "sg:classifiers":[
        {
            "category":"Wholesale",
            "subcategory":"Books, Periodicals, & Newspapers",
            "type":"Manufacturing & Wholesale Goods"
        }
    ],
    "sg:phone":"+1 450 434 0306",
    "sg:postcode":"J7H 1N7",
    "sg:province":"QC",
    "sg:tags":[
        "dealer"
    ],
    "wof:name":"Prologue Inc",
    "wof:placetype":"venue"
},
  "geometry": {"coordinates":[-73.8519821167,45.6181716919],"type":"Point"}
}