{
  "type": "Feature",
  "properties": {
    "addr:full":"31 Edinburgh Dr Moncton NB E1E 2K6",
    "addr:housenumber":"31",
    "addr:postcode":"e1e 2k6",
    "addr:street":"Edinburgh Dr",
    "iso:country":"CA",
    "sg:address":"31 Edinburgh Dr",
    "sg:city":"Moncton",
    "sg:classifiers":[
        {
            "category":"Freight",
            "type":"Transportation"
        }
    ],
    "sg:phone":"+1 506 853 5200",
    "sg:postcode":"E1E 2K6",
    "sg:province":"NB",
    "sg:tags":[
        "trucking"
    ],
    "wof:name":"Fast As Flite",
    "wof:placetype":"venue"
},
  "geometry": {"coordinates":[-64.8322677612,46.0708885193],"type":"Point"}
}