{
  "type": "Feature",
  "properties": {
    "iso:country":"CA",
    "sg:address":"101 Empress Ave",
    "sg:city":"London",
    "sg:classifiers":[
        {
            "category":"Professional",
            "subcategory":"Secretarial Services",
            "type":"Services"
        }
    ],
    "sg:phone":"+1 519 432 7759",
    "sg:postcode":"N6H 1N1",
    "sg:province":"ON",
    "sg:tags":[
        "resume"
    ],
    "wof:name":"Flying Fingers Typing Svc",
    "wof:placetype":"venue"
},
  "geometry": {"coordinates":[-81.2644271851,42.9905853271],"type":"Point"}
}