{
  "type": "Feature",
  "properties": {
    "addr:full":"851 Av Myrand Sainte-Foy QC G1V 2V8",
    "addr:housenumber":"851",
    "addr:postcode":"g1v 2v8",
    "addr:street":"Av Myrand",
    "iso:country":"CA",
    "sg:address":"851 Av Myrand",
    "sg:city":"Sainte-Foy",
    "sg:classifiers":[
        {
            "category":"Sports & Exercise",
            "subcategory":"Bowling",
            "type":"Entertainment"
        }
    ],
    "sg:phone":"+1 418 683 8629",
    "sg:postcode":"G1V 2V8",
    "sg:province":"QC",
    "sg:tags":[
        "center"
    ],
    "wof:name":"Salle DE Quilles Myrand",
    "wof:placetype":"venue"
},
  "geometry": {"coordinates":[-71.2687,46.787888],"type":"Point"}
}