{
  "type": "Feature",
  "properties": {
    "addr:full":"1474 Ch Du Chantecler Sainte-Adele QC J8B 1A2",
    "addr:housenumber":"1474",
    "addr:postcode":"j8b 1a2",
    "addr:street":"Ch Du Chantecler Sainte-Adele",
    "iso:country":"CA",
    "sg:address":"1474 Ch Du Chantecler",
    "sg:city":"Sainte-Adele",
    "sg:classifiers":[
        {
            "category":"Personal",
            "type":"Services"
        }
    ],
    "sg:phone":"+1 450 229 8289",
    "sg:postcode":"J8B 1A2",
    "sg:province":"QC",
    "sg:tags":[
        "therapist",
        "massage"
    ],
    "wof:name":"Centre DE Sante Le Chantecler",
    "wof:placetype":"venue"
},
  "geometry": {"coordinates":[-74.147141,45.950256],"type":"Point"}
}