{
  "type": "Feature",
  "properties": {
    "addr:full":"595 St Albert Rd St Albert AB T8N 6G5",
    "addr:housenumber":"595",
    "addr:postcode":"t8n 6g5",
    "addr:street":"St Albert Rd St Albert",
    "iso:country":"CA",
    "sg:address":"595 St Albert Rd",
    "sg:city":"St Albert",
    "sg:classifiers":[
        {
            "category":"Restaurant",
            "type":"Food & Drink"
        }
    ],
    "sg:phone":"+1 780 459 1411",
    "sg:postcode":"T8N 6G5",
    "sg:province":"AB",
    "wof:name":"Sorrentino's Bistro-Bar",
    "wof:placetype":"venue"
},
  "geometry": {"coordinates":[-113.628754,53.65313],"type":"Point"}
}