{
  "type": "Feature",
  "properties": {
    "iso:country":"CA",
    "sg:address":"140 Charlesworth Ave",
    "sg:city":"Cochrane",
    "sg:classifiers":[
        {
            "category":"Manufacturing",
            "subcategory":"Signs",
            "type":"Manufacturing & Wholesale Goods"
        }
    ],
    "sg:phone":"+1 403 932 6697",
    "sg:postcode":"T4C 2B7",
    "sg:province":"AB",
    "wof:name":"Cochrane Sign & Design",
    "wof:placetype":"venue"
},
  "geometry": {"coordinates":[-114.465569,51.186504],"type":"Point"}
}