{
  "type": "Feature",
  "properties": {
    "addr:full":"Fogo NL A0G 2B0",
    "addr:postcode":"a0g 2b0",
    "iso:country":"CA",
    "sg:city":"Fogo",
    "sg:classifiers":[
        {
            "category":"Government",
            "subcategory":"Police Station",
            "type":"Public Place"
        }
    ],
    "sg:phone":"+1 709 266 2251",
    "sg:postcode":"A0G 2B0",
    "sg:province":"NL",
    "sg:tags":[
        "department"
    ],
    "wof:name":"Fogo Police Community Office",
    "wof:placetype":"venue"
},
  "geometry": {"coordinates":[-54.2747192383,49.7125167847],"type":"Point"}
}