{
  "type": "Feature",
  "properties": {
    "addr:full":"1665 Ch Du Chenal-Du-Moine Sainte-Anne-DE-Sorel QC J3P 5N3",
    "addr:housenumber":"1665",
    "addr:postcode":"j3p 5n3",
    "addr:street":"Ch Du Chenal-Du-Moine",
    "iso:country":"CA",
    "sg:address":"1665 Ch Du Chenal-Du-Moine",
    "sg:city":"Sainte-Anne-DE-Sorel",
    "sg:classifiers":[
        {
            "category":"Ferry",
            "type":"Transportation"
        }
    ],
    "sg:phone":"+1 450 743 7227",
    "sg:postcode":"J3P 5N3",
    "sg:province":"QC",
    "wof:name":"Restaurant Le Survenant",
    "wof:placetype":"venue"
},
  "geometry": {"coordinates":[-73.0211181641,46.0610656738],"type":"Point"}
}