{
  "type": "Feature",
  "properties": {
    "iso:country":"CA",
    "sg:city":"Granby",
    "sg:classifiers":[
        {
            "category":"Freight",
            "type":"Transportation"
        }
    ],
    "sg:phone":"+1 450 372 9972",
    "sg:postcode":"J2G 7M6",
    "sg:province":"QC",
    "sg:tags":[
        "courier"
    ],
    "wof:name":"Diligence Express",
    "wof:placetype":"venue"
},
  "geometry": {"coordinates":[-72.741676,45.399475],"type":"Point"}
}