{
  "type": "Feature",
  "properties": {
    "addr:full":"224 Rue Principale Saint-Cyprien QC G0L 2P0",
    "addr:housenumber":"224",
    "addr:postcode":"g0l 2p0",
    "addr:street":"Rue Principale",
    "iso:country":"CA",
    "sg:address":"224 Rue Principale",
    "sg:city":"Saint-Cyprien",
    "sg:classifiers":[
        {
            "category":"Freight",
            "type":"Transportation"
        }
    ],
    "sg:phone":"+1 418 963 2829",
    "sg:postcode":"G0L 2P0",
    "sg:province":"QC",
    "sg:tags":[
        "trucking"
    ],
    "wof:name":"J P Leblond Inc",
    "wof:placetype":"venue"
},
  "geometry": {"coordinates":[-69.0125656128,47.8919067383],"type":"Point"}
}