{
  "type": "Feature",
  "properties": {
    "addr:full":"Grand Falls NB E3Y 1A7",
    "addr:postcode":"e3y 1a7",
    "iso:country":"CA",
    "sg:city":"Grand Falls",
    "sg:classifiers":[
        {
            "category":"Shopping",
            "subcategory":"Clothing, Apparel, & Fashions",
            "type":"Retail Goods"
        }
    ],
    "sg:phone":"+1 506 473 2152",
    "sg:postcode":"E3Y 1A7",
    "sg:province":"NB",
    "wof:name":"Chez Ja-DO",
    "wof:placetype":"venue"
},
  "geometry": {"coordinates":[-67.7440109253,47.0538101196],"type":"Point"}
}