{
  "type": "Feature",
  "properties": {
    "iso:country":"CA",
    "sg:address":"9250 Boul Pie-Ix",
    "sg:city":"Montreal",
    "sg:classifiers":[
        {
            "category":"Wholesale",
            "subcategory":"Fruits & Vegetables",
            "type":"Manufacturing & Wholesale Goods"
        }
    ],
    "sg:phone":"+1 514 322 9230",
    "sg:postcode":"H1Z 4H7",
    "sg:province":"QC",
    "wof:name":"Sodi Fruit",
    "wof:placetype":"venue"
},
  "geometry": {"coordinates":[-73.62395477290001,45.5807228088],"type":"Point"}
}