{
  "type": "Feature",
  "properties": {
    "addr:full":"271 Boul Cartier Beloeil QC J3G 3R2",
    "addr:housenumber":"271",
    "addr:postcode":"j3g 3r2",
    "addr:street":"Boul Cartier",
    "iso:country":"CA",
    "sg:address":"271 Boul Cartier",
    "sg:city":"Beloeil",
    "sg:classifiers":[
        {
            "category":"Personal",
            "subcategory":"Beauty Salon",
            "type":"Services"
        }
    ],
    "sg:phone":"+1 450 467 0548",
    "sg:postcode":"J3G 3R2",
    "sg:province":"QC",
    "wof:name":"Salon DE Coiffure Fascination",
    "wof:placetype":"venue"
},
  "geometry": {"coordinates":[-73.21416473390001,45.5546188354],"type":"Point"}
}