{
  "type": "Feature",
  "properties": {
    "addr:full":"5180 Still Creek Ave Burnaby BC V5C 4E4",
    "addr:housenumber":"5180",
    "addr:postcode":"v5c 4e4",
    "addr:street":"Still Creek Ave",
    "iso:country":"CA",
    "sg:address":"5180 Still Creek Ave",
    "sg:city":"Burnaby",
    "sg:classifiers":[
        {
            "category":"Home & Garden",
            "subcategory":"Building Materials",
            "type":"Retail Goods"
        }
    ],
    "sg:phone":"+1 604 299 9702",
    "sg:postcode":"V5C 4E4",
    "sg:province":"BC",
    "sg:tags":[
        "energy",
        "conservation",
        "prod"
    ],
    "wof:name":"Finnex Agencies Ltd",
    "wof:placetype":"venue"
},
  "geometry": {"coordinates":[-122.989052,49.260719],"type":"Point"}
}