{
  "type": "Feature",
  "properties": {
    "addr:full":"Saint-Felicien QC G8K 1T2",
    "addr:postcode":"g8k 1t2",
    "iso:country":"CA",
    "sg:city":"Saint-Felicien",
    "sg:classifiers":[
        {
            "category":"Building & Trades",
            "subcategory":"Construction",
            "type":"Services"
        }
    ],
    "sg:phone":"+1 418 679 1871",
    "sg:postcode":"G8K 1T2",
    "sg:province":"QC",
    "sg:tags":[
        "janitor",
        "steam"
    ],
    "wof:name":"Nettoie-Tout",
    "wof:placetype":"venue"
},
  "geometry": {"coordinates":[-72.412994,48.641964],"type":"Point"}
}