{
  "type": "Feature",
  "properties": {
    "addr:full":"511 Maple Grove Dr # 19 Oakville ON L6J 6X8",
    "addr:housenumber":"511",
    "addr:postcode":"l6j 6x8",
    "addr:street":"Maple Grove Dr # 19",
    "iso:country":"CA",
    "sg:address":"511 Maple Grove Dr # 19",
    "sg:city":"Oakville",
    "sg:classifiers":[
        {
            "category":"Professional",
            "subcategory":"Computer Services",
            "type":"Services"
        }
    ],
    "sg:phone":"+1 905 829 8696",
    "sg:postcode":"L6J 6X8",
    "sg:province":"ON",
    "sg:tags":[
        "consultant"
    ],
    "wof:name":"Swytch Delivery Solutions Inc",
    "wof:placetype":"venue"
},
  "geometry": {"coordinates":[-79.657112,43.478992],"type":"Point"}
}