{
  "type": "Feature",
  "properties": {
    "iso:country":"CA",
    "sg:address":"9292 Rue Meilleur",
    "sg:city":"Montreal",
    "sg:classifiers":[
        {
            "category":"Professional",
            "subcategory":"Management & Consulting",
            "type":"Services"
        }
    ],
    "sg:phone":"+1 514 382 9004",
    "sg:postcode":"H2N 2A5",
    "sg:province":"QC",
    "sg:tags":[
        "textile",
        "consultant"
    ],
    "wof:name":"Laces & Textiles",
    "wof:placetype":"venue"
},
  "geometry": {"coordinates":[-73.654861,45.537323],"type":"Point"}
}