{
  "type": "Feature",
  "properties": {
    "addr:full":"459 Reid St Peterborough ON K9H 4G7",
    "addr:housenumber":"459",
    "addr:postcode":"k9h 4g7",
    "addr:street":"Reid St",
    "iso:country":"CA",
    "sg:address":"459 Reid St",
    "sg:city":"Peterborough",
    "sg:classifiers":[
        {
            "category":"Social Services",
            "type":"Services"
        }
    ],
    "sg:phone":"+1 705 743 1681",
    "sg:postcode":"K9H 4G7",
    "sg:province":"ON",
    "sg:tags":[
        "department",
        "organization",
        "police",
        "welfare"
    ],
    "wof:name":"Peterborough Youth Svc",
    "wof:placetype":"venue"
},
  "geometry": {"coordinates":[-78.3282165527,44.3075370789],"type":"Point"}
}