{
  "type": "Feature",
  "properties": {
    "addr:full":"Campbell River BC V9W 2H4",
    "addr:postcode":"v9w 2h4",
    "iso:country":"CA",
    "sg:city":"Campbell River",
    "sg:classifiers":[
        {
            "category":"Manufacturing",
            "subcategory":"Tools & Machinery",
            "type":"Manufacturing & Wholesale Goods"
        }
    ],
    "sg:phone":"+1 250 287 2627",
    "sg:postcode":"V9W 2H4",
    "sg:province":"BC",
    "sg:tags":[
        "repair",
        "marine"
    ],
    "wof:name":"White's Diesel Power & Marine",
    "wof:placetype":"venue"
},
  "geometry": {"coordinates":[-125.26887499999999,50.04335],"type":"Point"}
}