{
  "type": "Feature",
  "properties": {
    "addr:full":"Brooks AB T1R 0M9",
    "addr:postcode":"t1r 0m9",
    "iso:country":"CA",
    "sg:city":"Brooks",
    "sg:classifiers":[
        {
            "category":"Health Services",
            "subcategory":"Chiropractor",
            "type":"Services"
        }
    ],
    "sg:phone":"+1 403 362 5900",
    "sg:postcode":"T1R 0M9",
    "sg:province":"AB",
    "wof:name":"Mc Iver, Donald H DC",
    "wof:placetype":"venue"
},
  "geometry": {"coordinates":[-111.891373,50.574928],"type":"Point"}
}