{
  "type": "Feature",
  "properties": {
    "addr:full":"555 Richmond St W Toronto ON M5V 3B1",
    "addr:housenumber":"555",
    "addr:postcode":"m5v 3b1",
    "addr:street":"Richmond St W",
    "iso:country":"CA",
    "sg:address":"555 Richmond St W",
    "sg:city":"Toronto",
    "sg:classifiers":[
        {
            "category":"Wholesale",
            "subcategory":"Apparel",
            "type":"Manufacturing & Wholesale Goods"
        }
    ],
    "sg:phone":"+1 416 504 4444",
    "sg:postcode":"M5V 3B1",
    "sg:province":"ON",
    "wof:name":"Cartise International",
    "wof:placetype":"venue"
},
  "geometry": {"coordinates":[-79.40184783940001,43.6466789246],"type":"Point"}
}