{
  "type": "Feature",
  "properties": {
    "addr:full":"503 St Clair Ave W Toronto ON M6C 1A1",
    "addr:housenumber":"503",
    "addr:postcode":"m6c 1a1",
    "addr:street":"St Clair Ave W",
    "iso:country":"CA",
    "sg:address":"503 St Clair Ave W",
    "sg:city":"Toronto",
    "sg:classifiers":[
        {
            "category":"Travel",
            "subcategory":"Travel Agent",
            "type":"Entertainment"
        }
    ],
    "sg:phone":"+1 416 516 7362",
    "sg:postcode":"M6C 1A1",
    "sg:province":"ON",
    "sg:tags":[
        "agency",
        "bureau"
    ],
    "wof:name":"Flight Centre",
    "wof:placetype":"venue"
},
  "geometry": {"coordinates":[-79.41841125489999,43.6830291748],"type":"Point"}
}