{
  "type": "Feature",
  "properties": {
    "iso:country":"CA",
    "sg:address":"2420 Surveyor Rd",
    "sg:city":"Mississauga",
    "sg:classifiers":[
        {
            "category":"Travel",
            "subcategory":"Hotels & Motels",
            "type":"Entertainment"
        }
    ],
    "sg:phone":"+1 905 858 8600",
    "sg:postcode":"L5N 4E6",
    "sg:province":"ON",
    "wof:name":"Comfort Inn",
    "wof:placetype":"venue"
},
  "geometry": {"coordinates":[-79.7435,43.589783],"type":"Point"}
}