{
  "type": "Feature",
  "properties": {
    "addr:full":"385 Henderson Dr Regina SK S4N 5W8",
    "addr:housenumber":"385",
    "addr:postcode":"s4n 5w8",
    "addr:street":"Henderson Dr",
    "iso:country":"CA",
    "sg:address":"385 Henderson Dr",
    "sg:city":"Regina",
    "sg:classifiers":[
        {
            "category":"Freight",
            "type":"Transportation"
        }
    ],
    "sg:phone":"+1 306 721 8272",
    "sg:postcode":"S4N 5W8",
    "sg:province":"SK",
    "sg:tags":[
        "trucking"
    ],
    "wof:name":"Ridsdale Transport",
    "wof:placetype":"venue"
},
  "geometry": {"coordinates":[-104.56128699999999,50.469032],"type":"Point"}
}