{
  "type": "Feature",
  "properties": {
    "iso:country":"CA",
    "sg:address":"385 Henderson Dr",
    "sg:city":"Regina",
    "sg:classifiers":[
        {
            "category":"Freight",
            "type":"Transportation"
        }
    ],
    "sg:phone":"+1 306 721 8272",
    "sg:postcode":"S4N 5W8",
    "sg:province":"SK",
    "sg:tags":[
        "trucking"
    ],
    "wof:name":"Ridsdale Transport",
    "wof:placetype":"venue"
},
  "geometry": {"coordinates":[-104.561287,50.469032],"type":"Point"}
}