{
  "type": "Feature",
  "properties": {
    "addr:full":"32 Stone St S Gananoque ON K7G 1Z8",
    "addr:housenumber":"32",
    "addr:postcode":"k7g 1z8",
    "addr:street":"Stone St S",
    "iso:country":"CA",
    "sg:address":"32 Stone St S",
    "sg:city":"Gananoque",
    "sg:classifiers":[
        {
            "category":"Real Estate",
            "subcategory":"Real Estate Agent",
            "type":"Services"
        }
    ],
    "sg:phone":"+1 613 382 2129",
    "sg:postcode":"K7G 1Z8",
    "sg:province":"ON",
    "wof:name":"White, John",
    "wof:placetype":"venue"
},
  "geometry": {"coordinates":[-76.16248299999999,44.32935],"type":"Point"}
}