{
  "type": "Feature",
  "properties": {
    "iso:country":"CA",
    "sg:address":"75 Tiffany Pl",
    "sg:city":"Kanata",
    "sg:classifiers":[
        {
            "category":"Professional",
            "subcategory":"Management & Consulting",
            "type":"Services"
        }
    ],
    "sg:phone":"+1 613 591 0322",
    "sg:postcode":"K2K 1W5",
    "sg:province":"ON",
    "sg:tags":[
        "consultant",
        "telecommunication"
    ],
    "wof:name":"Tel Design Inc",
    "wof:placetype":"venue"
},
  "geometry": {"coordinates":[-75.9029083252,45.3226852417],"type":"Point"}
}