{
  "type": "Feature",
  "properties": {
    "addr:full":"134 Kent St #115 Charlottetown PE C1A 8R8",
    "addr:housenumber":"134",
    "addr:postcode":"c1a 8r8",
    "addr:street":"Kent St # 115",
    "iso:country":"CA",
    "sg:address":"134 Kent St #115",
    "sg:city":"Charlottetown",
    "sg:classifiers":[
        {
            "category":"Shopping",
            "subcategory":"Gifts & Souvenirs",
            "type":"Retail Goods"
        }
    ],
    "sg:phone":"+1 902 628 8994",
    "sg:postcode":"C1A 8R8",
    "sg:province":"PE",
    "sg:tags":[
        "shop"
    ],
    "wof:name":"Genuine Order",
    "wof:placetype":"venue"
},
  "geometry": {"coordinates":[-63.128143,46.235687],"type":"Point"}
}