{
  "type": "Feature",
  "properties": {
    "addr:full":"5085 Highway 69 N # 11 Hanmer ON P3P 1P7",
    "addr:housenumber":"5085;11",
    "addr:postcode":"p3p 1p7",
    "addr:street":"Highway 69 N #",
    "iso:country":"CA",
    "sg:address":"5085 Highway 69 N # 11",
    "sg:city":"Hanmer",
    "sg:classifiers":[
        {
            "category":"Home & Garden",
            "subcategory":"Household Appliances",
            "type":"Retail Goods"
        }
    ],
    "sg:phone":"+1 705 969 7419",
    "sg:postcode":"P3P 1P7",
    "sg:province":"ON",
    "sg:tags":[
        "cleaners",
        "vacuum"
    ],
    "wof:name":"Vacuum & Home Care Ctr",
    "wof:placetype":"venue"
},
  "geometry": {"coordinates":[-80.9448013306,46.6524963379],"type":"Point"}
}