{
  "type": "Feature",
  "properties": {
    "addr:full":"1414 Sproule St Kingston ON K7P 2V3",
    "addr:housenumber":"1414",
    "addr:postcode":"k7p 2v3",
    "addr:street":"Sproule St",
    "iso:country":"CA",
    "sg:address":"1414 Sproule St",
    "sg:city":"Kingston",
    "sg:classifiers":[
        {
            "category":"Education",
            "subcategory":"School",
            "type":"Public Place"
        }
    ],
    "sg:phone":"+1 613 389 0129",
    "sg:postcode":"K7P 2V3",
    "sg:province":"ON",
    "wof:name":"Holsgrove Public School",
    "wof:placetype":"venue"
},
  "geometry": {"coordinates":[-76.621216,44.268364],"type":"Point"}
}