{
  "type": "Feature",
  "properties": {
    "addr:full":"Brampton ON L6V 1B2",
    "addr:postcode":"l6v 1b2",
    "iso:country":"CA",
    "sg:city":"Brampton",
    "sg:classifiers":[
        {
            "category":"Health Services",
            "subcategory":"Doctor",
            "type":"Services"
        }
    ],
    "sg:phone":"+1 905 453 1444",
    "sg:postcode":"L6V 1B2",
    "sg:province":"ON",
    "sg:tags":[
        "physician",
        "surgeon"
    ],
    "wof:name":"Mac Kenzie, M T MD",
    "wof:placetype":"venue"
},
  "geometry": {"coordinates":[-79.7547531128,43.6909942627],"type":"Point"}
}