{
  "type": "Feature",
  "properties": {
    "addr:full":"117 Burnside Crt Kirkland Lake ON P2N 1M8",
    "addr:housenumber":"117",
    "addr:postcode":"p2n 1m8",
    "addr:street":"Burnside Crt",
    "iso:country":"CA",
    "sg:address":"117 Burnside Crt",
    "sg:city":"Kirkland Lake",
    "sg:classifiers":[
        {
            "category":"Building & Trades",
            "subcategory":"Construction",
            "type":"Services"
        }
    ],
    "sg:phone":"+1 705 567 5404",
    "sg:postcode":"P2N 1M8",
    "sg:province":"ON",
    "sg:tags":[
        "painter"
    ],
    "wof:name":"H W Davis Painting",
    "wof:placetype":"venue"
},
  "geometry": {"coordinates":[-80.02319300000001,48.159515],"type":"Point"}
}