{
  "type": "Feature",
  "properties": {
    "addr:full":"128 Evergreen Hill Rd Simcoe ON N3Y 4K1",
    "addr:housenumber":"128",
    "addr:postcode":"n3y 4k1",
    "addr:street":"Evergreen Hill Rd",
    "iso:country":"CA",
    "sg:address":"128 Evergreen Hill Rd",
    "sg:city":"Simcoe",
    "sg:classifiers":[
        {
            "category":"Education",
            "subcategory":"School",
            "type":"Public Place"
        }
    ],
    "sg:phone":"+1 519 429 3600",
    "sg:postcode":"N3Y 4K1",
    "sg:province":"ON",
    "wof:name":"Holy Trinity School",
    "wof:placetype":"venue"
},
  "geometry": {"coordinates":[-80.309242,42.824352],"type":"Point"}
}