{
  "type": "Feature",
  "properties": {
    "addr:full":"1333 Pine Dr Golden BC V0A 1H1",
    "addr:housenumber":"1333",
    "addr:postcode":"v0a 1h1",
    "addr:street":"Pine Dr",
    "iso:country":"CA",
    "sg:address":"1333 Pine Dr",
    "sg:city":"Golden",
    "sg:classifiers":[
        {
            "category":"Building & Trades",
            "subcategory":"Construction",
            "type":"Services"
        }
    ],
    "sg:phone":"+1 250 344 5334",
    "sg:postcode":"V0A 1H1",
    "sg:province":"BC",
    "sg:tags":[
        "consultant",
        "management",
        "general",
        "business",
        "contractor"
    ],
    "wof:name":"Choice Ventures Ltd",
    "wof:placetype":"venue"
},
  "geometry": {"coordinates":[-116.96101400000001,51.305378],"type":"Point"}
}