{
  "type": "Feature",
  "properties": {
    "addr:full":"605 33rd St W Saskatoon SK S7L 0V9",
    "addr:housenumber":"605",
    "addr:postcode":"s7l 0v9",
    "addr:street":"33Rd St W",
    "iso:country":"CA",
    "sg:address":"605 33rd St W",
    "sg:city":"Saskatoon",
    "sg:classifiers":[
        {
            "category":"Professional",
            "subcategory":"Accounting & Tax Preparation",
            "type":"Services"
        }
    ],
    "sg:phone":"+1 306 653 4885",
    "sg:postcode":"S7L 0V9",
    "sg:province":"SK",
    "sg:tags":[
        "accountant"
    ],
    "wof:name":"A 1 Lo-Cost Income Tax & Acctg",
    "wof:placetype":"venue"
},
  "geometry": {"coordinates":[-106.678696,52.143742],"type":"Point"}
}