{
  "type": "Feature",
  "properties": {
    "addr:full":"Devon AB T9G 1G2",
    "addr:postcode":"t9g 1g2",
    "iso:country":"CA",
    "sg:city":"Devon",
    "sg:classifiers":[
        {
            "category":"Food & Beverages",
            "subcategory":"Specialty",
            "type":"Retail Goods"
        }
    ],
    "sg:phone":"+1 780 987 3551",
    "sg:postcode":"T9G 1G2",
    "sg:province":"AB",
    "sg:tags":[
        "health",
        "cosmetic",
        "diet",
        "perfume"
    ],
    "wof:name":"Health 4U",
    "wof:placetype":"venue"
},
  "geometry": {"coordinates":[-113.72963,53.365982],"type":"Point"}
}