{
  "type": "Feature",
  "properties": {
    "addr:full":"255 Rue DE Martigny O Saint-Jerome QC J7Y 2G4",
    "addr:housenumber":"255",
    "addr:postcode":"j7y 2g4",
    "addr:street":"Rue De Martigny O Saint-Jerome",
    "iso:country":"CA",
    "sg:address":"255 Rue DE Martigny O",
    "sg:city":"Saint-Jerome",
    "sg:classifiers":[
        {
            "category":"Insurance",
            "subcategory":"Insurance Agent",
            "type":"Services"
        }
    ],
    "sg:phone":"+1 450 432 2555",
    "sg:postcode":"J7Y 2G4",
    "sg:province":"QC",
    "wof:name":"Assurance Jones Inc",
    "wof:placetype":"venue"
},
  "geometry": {"coordinates":[-74.01611328120001,45.779335022],"type":"Point"}
}