{
  "type": "Feature",
  "properties": {
    "addr:full":"123 Guildwood Pky # 5 Scarborough ON M1E 4V2",
    "addr:housenumber":"123;# 5",
    "addr:postcode":"m1e 4v2",
    "addr:street":"Guildwood Pky",
    "iso:country":"CA",
    "sg:address":"123 Guildwood Pky # 5",
    "sg:city":"Scarborough",
    "sg:classifiers":[
        {
            "category":"Health Services",
            "subcategory":"Doctor",
            "type":"Services"
        }
    ],
    "sg:phone":"+1 416 282 2242",
    "sg:postcode":"M1E 4V2",
    "sg:province":"ON",
    "sg:tags":[
        "physician",
        "surgeon"
    ],
    "wof:name":"Wilton, M B MD",
    "wof:placetype":"venue"
},
  "geometry": {"coordinates":[-79.19982899999999,43.747231],"type":"Point"}
}