{
  "type": "Feature",
  "properties": {
    "addr:full":"96 Norfolk St N Simcoe ON N3Y 3N7",
    "addr:housenumber":"96",
    "addr:postcode":"n3y 3n7",
    "addr:street":"Norfolk St N",
    "iso:country":"CA",
    "sg:address":"96 Norfolk St N",
    "sg:city":"Simcoe",
    "sg:classifiers":[
        {
            "category":"Retail",
            "subcategory":"Funeral Services",
            "type":"Services"
        }
    ],
    "sg:phone":"+1 519 426 0291",
    "sg:postcode":"N3Y 3N7",
    "sg:province":"ON",
    "sg:tags":[
        "director"
    ],
    "wof:name":"Baldock Funeral Home",
    "wof:placetype":"venue"
},
  "geometry": {"coordinates":[-80.3049087524,42.8394126892],"type":"Point"}
}