{
  "type": "Feature",
  "properties": {
    "addr:full":"4326 200 St Langley BC V3A 1L1",
    "addr:housenumber":"4326",
    "addr:postcode":"v3a 1l1",
    "addr:street":"200 St",
    "iso:country":"CA",
    "sg:address":"4326 200 St",
    "sg:city":"Langley",
    "sg:classifiers":[
        {
            "category":"Retail",
            "subcategory":"Animal Services",
            "type":"Services"
        }
    ],
    "sg:phone":"+1 604 539 2517",
    "sg:postcode":"V3A 1L1",
    "sg:province":"BC",
    "sg:tags":[
        "pet",
        "grooming",
        "washing"
    ],
    "wof:name":"Westcoast Canine Svc",
    "wof:placetype":"venue"
},
  "geometry": {"coordinates":[-122.66899100000001,49.080631],"type":"Point"}
}