{
  "type": "Feature",
  "properties": {
    "addr:full":"10135 100 St NW Edmonton AB T5J 0N7",
    "addr:housenumber":"10135",
    "addr:postcode":"t5j 0n7",
    "addr:street":"100 St Nw",
    "iso:country":"CA",
    "sg:address":"10135 100 St NW",
    "sg:city":"Edmonton",
    "sg:classifiers":[
        {
            "category":"Personal",
            "subcategory":"Beauty Salon",
            "type":"Services"
        }
    ],
    "sg:phone":"+1 780 424 7484",
    "sg:postcode":"T5J 0N7",
    "sg:province":"AB",
    "wof:name":"Hair Dimension",
    "wof:placetype":"venue"
},
  "geometry": {"coordinates":[-113.490127563,53.5419311523],"type":"Point"}
}