{
  "type": "Feature",
  "properties": {
    "addr:full":"99 Champaigne St Parry Sound ON P2A 3C2",
    "addr:housenumber":"99",
    "addr:postcode":"p2a 3c2",
    "addr:street":"Champaigne St",
    "iso:country":"CA",
    "sg:address":"99 Champaigne St",
    "sg:city":"Parry Sound",
    "sg:classifiers":[
        {
            "category":"Recreation",
            "type":"Entertainment"
        }
    ],
    "sg:phone":"+1 705 746 6064",
    "sg:postcode":"P2A 3C2",
    "sg:province":"ON",
    "sg:tags":[
        "charter",
        "boat"
    ],
    "wof:name":"Chippewa III",
    "wof:placetype":"venue"
},
  "geometry": {"coordinates":[-80.02993011469999,45.335849762],"type":"Point"}
}