{
  "type": "Feature",
  "properties": {
    "iso:country":"CA",
    "sg:address":"101 Boul DE LA Concorde O",
    "sg:city":"Laval",
    "sg:classifiers":[
        {
            "category":"Shopping",
            "subcategory":"Clothing, Apparel, & Fashions",
            "type":"Retail Goods"
        }
    ],
    "sg:phone":"+1 450 667 5516",
    "sg:postcode":"H7N 1H8",
    "sg:province":"QC",
    "sg:tags":[
        "dressmaker"
    ],
    "wof:name":"Au Fil D'Isabelle",
    "wof:placetype":"venue"
},
  "geometry": {"coordinates":[-73.6987075806,45.5670166016],"type":"Point"}
}