{
  "type": "Feature",
  "properties": {
    "iso:country":"CA",
    "sg:address":"35 Rue Saint-Omer",
    "sg:city":"Levis",
    "sg:classifiers":[
        {
            "category":"Health Services",
            "subcategory":"Hospital",
            "type":"Services"
        }
    ],
    "sg:phone":"+1 418 835 5281",
    "sg:postcode":"G6V 5C5",
    "sg:province":"QC",
    "sg:tags":[
        "mental"
    ],
    "wof:name":"Societe DE Readaptation",
    "wof:placetype":"venue"
},
  "geometry": {"coordinates":[-71.173187,46.813744],"type":"Point"}
}