{
  "type": "Feature",
  "properties": {
    "addr:full":"1690 Av D'Assise Quebec QC G1L 5A6",
    "addr:housenumber":"1690",
    "addr:postcode":"g1l 5a6",
    "addr:street":"Av D'Assise",
    "iso:country":"CA",
    "sg:address":"1690 Av D'Assise",
    "sg:city":"Quebec",
    "sg:classifiers":[
        {
            "category":"Social Services",
            "subcategory":"Child Care",
            "type":"Services"
        }
    ],
    "sg:phone":"+1 418 523 0299",
    "sg:postcode":"G1L 5A6",
    "sg:province":"QC",
    "wof:name":"Cpe Fanfou",
    "wof:placetype":"venue"
},
  "geometry": {"coordinates":[-71.23834228520001,46.8272705078],"type":"Point"}
}