{
  "type": "Feature",
  "properties": {
    "addr:full":"1170 Bedford Hwy Bedford NS B4A 1C1",
    "addr:housenumber":"1170",
    "addr:postcode":"b4a 1c1",
    "addr:street":"Bedford Hwy",
    "iso:country":"CA",
    "sg:address":"1170 Bedford Hwy",
    "sg:city":"Bedford",
    "sg:classifiers":[
        {
            "category":"Travel",
            "subcategory":"Hotels & Motels",
            "type":"Entertainment"
        }
    ],
    "sg:phone":"+1 902 835 8307",
    "sg:postcode":"B4A 1C1",
    "sg:province":"NS",
    "wof:name":"Maritime Motel",
    "wof:placetype":"venue"
},
  "geometry": {"coordinates":[-63.671364,44.721916],"type":"Point"}
}