{
  "type": "Feature",
  "properties": {
    "addr:full":"Richmond BC V6V 1L4",
    "addr:postcode":"v6v 1l4",
    "iso:country":"CA",
    "sg:city":"Richmond",
    "sg:classifiers":[
        {
            "category":"Professional",
            "subcategory":"Research",
            "type":"Services"
        }
    ],
    "sg:phone":"+1 604 278 7714",
    "sg:postcode":"V6V 1L4",
    "sg:province":"BC",
    "sg:tags":[
        "environmental",
        "ecological"
    ],
    "wof:name":"Integrated Resource Conslnt",
    "wof:placetype":"venue"
},
  "geometry": {"coordinates":[-123.062386,49.202629],"type":"Point"}
}