{
  "type": "Feature",
  "properties": {
    "addr:full":"4803 6 Ave Edson AB T7E 1E1",
    "addr:housenumber":"4803",
    "addr:postcode":"t7e 1e1",
    "addr:street":"6 Ave",
    "iso:country":"CA",
    "sg:address":"4803 6 Ave",
    "sg:city":"Edson",
    "sg:classifiers":[
        {
            "category":"Organizations",
            "subcategory":"Religious Organization",
            "type":"Services"
        }
    ],
    "sg:phone":"+1 780 723 3661",
    "sg:postcode":"T7E 1E1",
    "sg:province":"AB",
    "sg:tags":[
        "church"
    ],
    "wof:name":"Sacred Heart Catholic Church",
    "wof:placetype":"venue"
},
  "geometry": {"coordinates":[-116.429283,53.586475],"type":"Point"}
}