{
  "type": "Feature",
  "properties": {
    "iso:country":"CA",
    "sg:address":"6884 52 Ave",
    "sg:city":"Red Deer",
    "sg:classifiers":[
        {
            "category":"Wholesale",
            "subcategory":"Electrical",
            "type":"Manufacturing & Wholesale Goods"
        }
    ],
    "sg:phone":"+1 403 347 6001",
    "sg:postcode":"T4N 4L1",
    "sg:province":"AB",
    "sg:tags":[
        "instrument",
        "oil",
        "field"
    ],
    "wof:name":"Harvie Instruments Ltd",
    "wof:placetype":"venue"
},
  "geometry": {"coordinates":[-113.817077637,52.2951393127],"type":"Point"}
}