{
  "type": "Feature",
  "properties": {
    "iso:country":"CA",
    "sg:address":"5912 Rue DE Salaberry",
    "sg:city":"Montreal",
    "sg:classifiers":[
        {
            "category":"Personal",
            "subcategory":"Beauty Salon",
            "type":"Services"
        }
    ],
    "sg:phone":"+1 514 336 5720",
    "sg:postcode":"H4J 1J8",
    "sg:province":"QC",
    "wof:name":"Jacques Laurent Coiffure Enr",
    "wof:placetype":"venue"
},
  "geometry": {"coordinates":[-73.7132644653,45.5271224976],"type":"Point"}
}