{
  "type": "Feature",
  "properties": {
    "iso:country":"CA",
    "sg:address":"84 Lansdowne Ave",
    "sg:city":"Saint John",
    "sg:classifiers":[
        {
            "category":"Personal",
            "subcategory":"Beauty Salon",
            "type":"Services"
        }
    ],
    "sg:phone":"+1 506 634 8311",
    "sg:postcode":"E2K 2Z8",
    "sg:province":"NB",
    "wof:name":"Maritime Denture Clinic",
    "wof:placetype":"venue"
},
  "geometry": {"coordinates":[-66.07680511469999,45.2773323059],"type":"Point"}
}