{
  "type": "Feature",
  "properties": {
    "iso:country":"CA",
    "sg:address":"297 Rue DE L'Aeroport",
    "sg:city":"Saint-Honore-DE-Chicoutimi",
    "sg:classifiers":[
        {
            "category":"Building & Trades",
            "subcategory":"Construction",
            "type":"Services"
        }
    ],
    "sg:phone":"+1 418 673 7345",
    "sg:postcode":"G0V 1L0",
    "sg:province":"QC",
    "sg:tags":[
        "general",
        "contractor"
    ],
    "wof:name":"Construction R Gagnon Inc",
    "wof:placetype":"venue"
},
  "geometry": {"coordinates":[-71.1109466553,48.3475990295],"type":"Point"}
}