{
  "type": "Feature",
  "properties": {
    "addr:full":"9001 112 St Grande Prairie AB T8V 7J4",
    "addr:housenumber":"9001",
    "addr:postcode":"t8v 7j4",
    "addr:street":"112 St",
    "iso:country":"CA",
    "sg:address":"9001 112 St",
    "sg:city":"Grande Prairie",
    "sg:classifiers":[
        {
            "category":"Home & Garden",
            "subcategory":"Building Materials",
            "type":"Retail Goods"
        }
    ],
    "sg:phone":"+1 780 532 7766",
    "sg:postcode":"T8V 7J4",
    "sg:province":"AB",
    "sg:tags":[
        "mixed",
        "concrete"
    ],
    "wof:name":"Lafarge Canada Inc",
    "wof:placetype":"venue"
},
  "geometry": {"coordinates":[-118.83506800000001,55.161686],"type":"Point"}
}