{
  "type": "Feature",
  "properties": {
    "addr:full":"771 Colborne St Brantford ON N3S 3S2",
    "addr:housenumber":"771",
    "addr:postcode":"n3s 3s2",
    "addr:street":"Colborne St",
    "iso:country":"CA",
    "sg:address":"771 Colborne St",
    "sg:city":"Brantford",
    "sg:classifiers":[
        {
            "category":"Personal",
            "subcategory":"Tanning Parlor",
            "type":"Services"
        }
    ],
    "sg:phone":"+1 519 759 6902",
    "sg:postcode":"N3S 3S2",
    "sg:province":"ON",
    "sg:tags":[
        "salon"
    ],
    "wof:name":"Spa",
    "wof:placetype":"venue"
},
  "geometry": {"coordinates":[-80.227951,43.143391],"type":"Point"}
}