{
  "type": "Feature",
  "properties": {
    "iso:country":"CA",
    "sg:address":"205 4th St S",
    "sg:city":"Wakaw",
    "sg:classifiers":[
        {
            "category":"Personal",
            "subcategory":"Tattoo Parlor",
            "type":"Services"
        }
    ],
    "sg:phone":"+1 306 233 5501",
    "sg:postcode":"S0K 4P0",
    "sg:province":"SK",
    "sg:tags":[
        "tattooing"
    ],
    "wof:name":"Ink Buttle Tattoo Studio",
    "wof:placetype":"venue"
},
  "geometry": {"coordinates":[-105.74270629900001,52.6529502869],"type":"Point"}
}