{
  "type": "Feature",
  "properties": {
    "addr:full":"Grimsby ON L3M 4G1",
    "addr:postcode":"l3m 4g1",
    "iso:country":"CA",
    "sg:city":"Grimsby",
    "sg:classifiers":[
        {
            "category":"Manufacturing",
            "subcategory":"Lumber",
            "type":"Manufacturing & Wholesale Goods"
        }
    ],
    "sg:phone":"+1 905 643 9215",
    "sg:postcode":"L3M 4G1",
    "sg:province":"ON",
    "sg:tags":[
        "syrup",
        "maple",
        "sugar"
    ],
    "wof:name":"Smokey Kettle Maple CO Ltd",
    "wof:placetype":"venue"
},
  "geometry": {"coordinates":[-79.61724853520001,43.2117729187],"type":"Point"}
}