{
  "type": "Feature",
  "properties": {
    "addr:full":"3375 Route 134 Shediac Cape NB E4P 3G4",
    "addr:housenumber":"3375",
    "addr:postcode":"e4p 3g4",
    "addr:street":"Route 134 Shediac",
    "iso:country":"CA",
    "sg:address":"3375 Route 134",
    "sg:city":"Shediac Cape",
    "sg:classifiers":[
        {
            "category":"Education",
            "subcategory":"School",
            "type":"Public Place"
        }
    ],
    "sg:phone":"+1 506 533 3388",
    "sg:postcode":"E4P 3G4",
    "sg:province":"NB",
    "wof:name":"Shediac Cape School",
    "wof:placetype":"venue"
},
  "geometry": {"coordinates":[-64.566605,46.233532],"type":"Point"}
}