{
  "type": "Feature",
  "properties": {
    "iso:country":"CA",
    "sg:address":"382 138 Rte",
    "sg:city":"Saint-Augustin-DE-Desmaures",
    "sg:classifiers":[
        {
            "category":"Health Services",
            "subcategory":"Doctor",
            "type":"Services"
        }
    ],
    "sg:phone":"+1 418 878 2525",
    "sg:postcode":"G3A 2S8",
    "sg:province":"QC",
    "sg:tags":[
        "clinic",
        "chiropractor"
    ],
    "wof:name":"Centre Chiropratique St-August",
    "wof:placetype":"venue"
},
  "geometry": {"coordinates":[-71.384727478,46.7491760254],"type":"Point"}
}