{
  "type": "Feature",
  "properties": {
    "addr:full":"1357 Napier Pl Coquitlam BC V3B 7A3",
    "addr:housenumber":"1357",
    "addr:postcode":"v3b 7a3",
    "addr:street":"Napier Pl",
    "iso:country":"CA",
    "sg:address":"1357 Napier Pl",
    "sg:city":"Coquitlam",
    "sg:classifiers":[
        {
            "category":"Professional",
            "subcategory":"Management & Consulting",
            "type":"Services"
        }
    ],
    "sg:phone":"+1 604 941 1213",
    "sg:postcode":"V3B 7A3",
    "sg:province":"BC",
    "sg:tags":[
        "consultant",
        "mining"
    ],
    "wof:name":"Matrix Consultants Ltd",
    "wof:placetype":"venue"
},
  "geometry": {"coordinates":[-122.80246,49.294334],"type":"Point"}
}