{
  "type": "Feature",
  "properties": {
    "addr:full":"Toronto ON M4E 1E2",
    "addr:postcode":"m4e 1e2",
    "iso:country":"CA",
    "sg:city":"Toronto",
    "sg:classifiers":[
        {
            "category":"Personal",
            "subcategory":"Tanning Parlor",
            "type":"Services"
        }
    ],
    "sg:phone":"+1 416 693 9040",
    "sg:postcode":"M4E 1E2",
    "sg:province":"ON",
    "sg:tags":[
        "salon"
    ],
    "wof:name":"Tanning Shop",
    "wof:placetype":"venue"
},
  "geometry": {"coordinates":[-79.2950210571,43.6712417603],"type":"Point"}
}