{
  "type": "Feature",
  "properties": {
    "addr:full":"1214 Rue Tellier Laval QC H7C 2H2",
    "addr:housenumber":"1214",
    "addr:postcode":"h7c 2h2",
    "addr:street":"Rue Tellier",
    "iso:country":"CA",
    "sg:address":"1214 Rue Tellier",
    "sg:city":"Laval",
    "sg:classifiers":[
        {
            "category":"Manufacturing",
            "subcategory":"Printing",
            "type":"Manufacturing & Wholesale Goods"
        }
    ],
    "sg:phone":"+1 450 661 2711",
    "sg:postcode":"H7C 2H2",
    "sg:province":"QC",
    "sg:tags":[
        "printer"
    ],
    "wof:name":"Atelier Quebecois Offset Inc",
    "wof:placetype":"venue"
},
  "geometry": {"coordinates":[-73.6584472656,45.6156425476],"type":"Point"}
}