{
  "type": "Feature",
  "properties": {
    "addr:full":"1695 17th St W Prince Albert SK S6V 6W2",
    "addr:housenumber":"1695",
    "addr:postcode":"s6v 6w2",
    "addr:street":"17Th St",
    "iso:country":"CA",
    "sg:address":"1695 17th St W",
    "sg:city":"Prince Albert",
    "sg:classifiers":[
        {
            "category":"Education",
            "subcategory":"School",
            "type":"Public Place"
        }
    ],
    "sg:phone":"+1 306 953 7555",
    "sg:postcode":"S6V 6W2",
    "sg:province":"SK",
    "wof:name":"St Michael Community School",
    "wof:placetype":"venue"
},
  "geometry": {"coordinates":[-105.794189453,53.1969490051],"type":"Point"}
}