{
  "type": "Feature",
  "properties": {
    "addr:full":"455 Mcgaughey Ave North Bay ON P1B 1W4",
    "addr:housenumber":"455",
    "addr:postcode":"p1b 1w4",
    "addr:street":"Mcgaughey Ave",
    "iso:country":"CA",
    "sg:address":"455 Mcgaughey Ave",
    "sg:city":"North Bay",
    "sg:classifiers":[
        {
            "category":"Personal",
            "subcategory":"Beauty Salon",
            "type":"Services"
        }
    ],
    "sg:phone":"+1 705 474 1490",
    "sg:postcode":"P1B 1W4",
    "sg:province":"ON",
    "sg:tags":[
        "school"
    ],
    "wof:name":"Modern Hairstyling School",
    "wof:placetype":"venue"
},
  "geometry": {"coordinates":[-79.4439239502,46.3117904663],"type":"Point"}
}