{
  "type": "Feature",
  "properties": {
    "iso:country":"CA",
    "sg:address":"1 Whitmore Rd # 1617",
    "sg:city":"Woodbridge",
    "sg:classifiers":[
        {
            "category":"Building & Trades",
            "subcategory":"Construction",
            "type":"Services"
        }
    ],
    "sg:phone":"+1 905 850 2996",
    "sg:postcode":"L4L 8G4",
    "sg:province":"ON",
    "sg:tags":[
        "general",
        "contractor"
    ],
    "wof:name":"Princeton Developments Inc",
    "wof:placetype":"venue"
},
  "geometry": {"coordinates":[-79.554184,43.781841],"type":"Point"}
}