{
  "type": "Feature",
  "properties": {
    "addr:full":"Winnipeg MB R3K 2G6",
    "addr:postcode":"r3k 2g6",
    "iso:country":"CA",
    "sg:city":"Winnipeg",
    "sg:classifiers":[
        {
            "category":"Restaurant",
            "type":"Food & Drink"
        }
    ],
    "sg:phone":"+1 204 949 6014",
    "sg:postcode":"R3K 2G6",
    "sg:province":"MB",
    "wof:name":"Mc Donald's",
    "wof:placetype":"venue"
},
  "geometry": {"coordinates":[-97.31275939939999,49.8822822571],"type":"Point"}
}