{
  "type": "Feature",
  "properties": {
    "addr:full":"10223 Hwy 50 Kleinburg ON L0J 1C0",
    "addr:housenumber":"10223",
    "addr:postcode":"l0j 1c0",
    "addr:street":"Hwy 50",
    "iso:country":"CA",
    "sg:address":"10223 Hwy 50",
    "sg:city":"Kleinburg",
    "sg:classifiers":[
        {
            "category":"Travel",
            "subcategory":"Campground",
            "type":"Entertainment"
        }
    ],
    "sg:phone":"+1 905 893 1057",
    "sg:postcode":"L0J 1C0",
    "sg:province":"ON",
    "sg:tags":[
        "game",
        "adventure",
        "activity"
    ],
    "wof:name":"Kleinburg War Games",
    "wof:placetype":"venue"
},
  "geometry": {"coordinates":[-79.68187,43.825203],"type":"Point"}
}