{
  "type": "Feature",
  "properties": {
    "addr:full":"Sherwood Park AB T8A 6A2",
    "addr:postcode":"t8a 6a2",
    "iso:country":"CA",
    "sg:city":"Sherwood Park",
    "sg:classifiers":[
        {
            "category":"Wholesale",
            "subcategory":"Sporting Goods",
            "type":"Manufacturing & Wholesale Goods"
        }
    ],
    "sg:phone":"+1 780 417 0677",
    "sg:postcode":"T8A 6A2",
    "sg:province":"AB",
    "sg:tags":[
        "salon",
        "tanning",
        "supply"
    ],
    "wof:name":"Sundays Distributing",
    "wof:placetype":"venue"
},
  "geometry": {"coordinates":[-113.32456970200001,53.5380897522],"type":"Point"}
}