{
  "type": "Feature",
  "properties": {
    "addr:full":"815 Middlefield Rd Scarborough ON M1V 2P9",
    "addr:housenumber":"815",
    "addr:postcode":"m1v 2p9",
    "addr:street":"Middlefield Rd",
    "iso:country":"CA",
    "sg:address":"815 Middlefield Rd",
    "sg:city":"Scarborough",
    "sg:classifiers":[
        {
            "category":"Freight",
            "type":"Transportation"
        }
    ],
    "sg:phone":"+1 416 297 0024",
    "sg:postcode":"M1V 2P9",
    "sg:province":"ON",
    "wof:name":"Etg Svc Group",
    "wof:placetype":"venue"
},
  "geometry": {"coordinates":[-79.262505,43.822216],"type":"Point"}
}