{
  "type": "Feature",
  "properties": {
    "addr:full":"411 1st Ave E Carberry MB R0K 0H0",
    "addr:housenumber":"411",
    "addr:postcode":"r0k 0h0",
    "addr:street":"1St Ave E",
    "iso:country":"CA",
    "sg:address":"411 1st Ave E",
    "sg:city":"Carberry",
    "sg:classifiers":[
        {
            "category":"Home & Garden",
            "subcategory":"Hardware",
            "type":"Retail Goods"
        }
    ],
    "sg:phone":"+1 204 834 2972",
    "sg:postcode":"R0K 0H0",
    "sg:province":"MB",
    "wof:name":"Reilly's Home Hardware",
    "wof:placetype":"venue"
},
  "geometry": {"coordinates":[-99.37367999999999,49.871487],"type":"Point"}
}