{
  "type": "Feature",
  "properties": {
    "addr:full":"1227 Barton St E Hamilton ON L8H 2V4",
    "addr:housenumber":"1227",
    "addr:postcode":"l8h 2v4",
    "addr:street":"Barton St E",
    "iso:country":"CA",
    "sg:address":"1227 Barton St E",
    "sg:city":"Hamilton",
    "sg:classifiers":[
        {
            "category":"Banks & Credit Unions",
            "subcategory":"Bank",
            "type":"Services"
        }
    ],
    "sg:phone":"+1 905 549 1352",
    "sg:postcode":"L8H 2V4",
    "sg:province":"ON",
    "wof:name":"Royal Bank Financial Group",
    "wof:placetype":"venue"
},
  "geometry": {"coordinates":[-79.810974,43.250385],"type":"Point"}
}