{
  "type": "Feature",
  "properties": {
    "addr:full":"259 Sherk St Leamington ON N8H 3K8",
    "addr:housenumber":"259",
    "addr:postcode":"n8h 3k8",
    "addr:street":"Sherk St",
    "iso:country":"CA",
    "sg:address":"259 Sherk St",
    "sg:city":"Leamington",
    "sg:classifiers":[
        {
            "category":"Education",
            "subcategory":"School",
            "type":"Public Place"
        }
    ],
    "sg:phone":"+1 519 326 6603",
    "sg:postcode":"N8H 3K8",
    "sg:province":"ON",
    "wof:name":"Margaret D Bennie Public Schl",
    "wof:placetype":"venue"
},
  "geometry": {"coordinates":[-82.60558319090001,42.0403060913],"type":"Point"}
}