{
  "type": "Feature",
  "properties": {
    "addr:full":"228 Pitt St Cornwall ON K6J 3P6",
    "addr:housenumber":"228",
    "addr:postcode":"k6j 3p6",
    "addr:street":"Pitt St",
    "iso:country":"CA",
    "sg:address":"228 Pitt St",
    "sg:city":"Cornwall",
    "sg:classifiers":[
        {
            "category":"Shopping",
            "subcategory":"Clothing, Apparel, & Fashions",
            "type":"Retail Goods"
        }
    ],
    "sg:phone":"+1 613 932 6202",
    "sg:postcode":"K6J 3P6",
    "sg:province":"ON",
    "sg:tags":[
        "wear",
        "formal"
    ],
    "wof:name":"Schulman's Tuxedos & Jeans",
    "wof:placetype":"venue"
},
  "geometry": {"coordinates":[-74.72917200000001,45.01873],"type":"Point"}
}