{
  "type": "Feature",
  "properties": {
    "addr:full":"Red Deer AB T4N 6M4",
    "addr:postcode":"t4n 6m4",
    "iso:country":"CA",
    "sg:city":"Red Deer",
    "sg:classifiers":[
        {
            "category":"Real Estate",
            "subcategory":"Real Estate Agent",
            "type":"Services"
        }
    ],
    "sg:phone":"+1 403 346 5533",
    "sg:postcode":"T4N 6M4",
    "sg:province":"AB",
    "sg:tags":[
        "appraiser"
    ],
    "wof:name":"Soderquist Appraisals Ltd",
    "wof:placetype":"venue"
},
  "geometry": {"coordinates":[-113.81192799999999,52.266975],"type":"Point"}
}