{
  "type": "Feature",
  "properties": {
    "addr:full":"6053 Franklin Ave Niagara Falls ON L2G 4Z1",
    "addr:housenumber":"6053",
    "addr:postcode":"l2g 4z1",
    "addr:street":"Franklin Ave",
    "iso:country":"CA",
    "sg:address":"6053 Franklin Ave",
    "sg:city":"Niagara Falls",
    "sg:classifiers":[
        {
            "category":"Personal",
            "type":"Services"
        }
    ],
    "sg:phone":"+1 905 371 3695",
    "sg:postcode":"L2G 4Z1",
    "sg:province":"ON",
    "sg:tags":[
        "wedding",
        "chapel"
    ],
    "wof:name":"Wedding CO of Niagara",
    "wof:placetype":"venue"
},
  "geometry": {"coordinates":[-79.1042022705,43.0867233276],"type":"Point"}
}