{
  "type": "Feature",
  "properties": {
    "addr:full":"105 Adelaide St W Toronto ON M5H 1P9",
    "addr:housenumber":"105",
    "addr:postcode":"m5h 1p9",
    "addr:street":"Adelaide St W",
    "iso:country":"CA",
    "sg:address":"105 Adelaide St W",
    "sg:city":"Toronto",
    "sg:classifiers":[
        {
            "category":"Banks & Credit Unions",
            "subcategory":"Investment Brokerage",
            "type":"Services"
        }
    ],
    "sg:phone":"+1 416 645 0997",
    "sg:postcode":"M5H 1P9",
    "sg:province":"ON",
    "sg:tags":[
        "consultant",
        "financing"
    ],
    "wof:name":"Maxxcap Corporate Finance Inc",
    "wof:placetype":"venue"
},
  "geometry": {"coordinates":[-79.38298,43.649273],"type":"Point"}
}