{
  "type": "Feature",
  "properties": {
    "addr:full":"93 Main St S Newmarket ON L3Y 3Y8",
    "addr:housenumber":"93",
    "addr:postcode":"l3y 3y8",
    "addr:street":"Main St S",
    "iso:country":"CA",
    "sg:address":"93 Main St S",
    "sg:city":"Newmarket",
    "sg:classifiers":[
        {
            "category":"Manufacturing",
            "subcategory":"Glass & Minerals",
            "type":"Manufacturing & Wholesale Goods"
        }
    ],
    "sg:phone":"+1 905 895 4931",
    "sg:postcode":"L3Y 3Y8",
    "sg:province":"ON",
    "sg:tags":[
        "marble",
        "monument"
    ],
    "wof:name":"Luesby Memorial CO Ltd",
    "wof:placetype":"venue"
},
  "geometry": {"coordinates":[-79.4592514038,44.0560302734],"type":"Point"}
}