{
  "type": "Feature",
  "properties": {
    "addr:full":"150 Boul Montreal Toronto Lachine QC H8S 1B6",
    "addr:housenumber":"150",
    "addr:postcode":"h8s 1b6",
    "addr:street":"Boul Montreal",
    "iso:country":"CA",
    "sg:address":"150 Boul Montreal Toronto",
    "sg:city":"Lachine",
    "sg:classifiers":[
        {
            "category":"Freight",
            "type":"Transportation"
        }
    ],
    "sg:phone":"+1 514 634 8886",
    "sg:postcode":"H8S 1B6",
    "sg:province":"QC",
    "sg:tags":[
        "warehouse",
        "trucking"
    ],
    "wof:name":"Dec",
    "wof:placetype":"venue"
},
  "geometry": {"coordinates":[-73.65818023680001,45.4430580139],"type":"Point"}
}