{
  "type": "Feature",
  "properties": {
    "addr:full":"9 Rue Frontenac Saint-Jean-Sur-Richelieu QC J3B 2X9",
    "addr:housenumber":"9",
    "addr:postcode":"j3b 2x9",
    "addr:street":"Rue Frontenac",
    "iso:country":"CA",
    "sg:address":"9 Rue Frontenac",
    "sg:city":"Saint-Jean-Sur-Richelieu",
    "sg:classifiers":[
        {
            "category":"Retail",
            "subcategory":"Auto Rental",
            "type":"Services"
        }
    ],
    "sg:phone":"+1 450 358 3993",
    "sg:postcode":"J3B 2X9",
    "sg:province":"QC",
    "sg:tags":[
        "body",
        "automobile",
        "leasing"
    ],
    "wof:name":"Voitures DE Cinema Real",
    "wof:placetype":"venue"
},
  "geometry": {"coordinates":[-73.25147200000001,45.303036],"type":"Point"}
}