{
  "type": "Feature",
  "properties": {
    "addr:full":"3288 Av Des Eglises Charny QC G6X 1W3",
    "addr:housenumber":"3288",
    "addr:postcode":"g6x 1w3",
    "addr:street":"Av Des Eglises",
    "iso:country":"CA",
    "sg:address":"3288 Av Des Eglises",
    "sg:city":"Charny",
    "sg:classifiers":[
        {
            "category":"Health Services",
            "subcategory":"Hospital",
            "type":"Services"
        }
    ],
    "sg:phone":"+1 418 832 1555",
    "sg:postcode":"G6X 1W3",
    "sg:province":"QC",
    "sg:tags":[
        "mental"
    ],
    "wof:name":"Groupe D'Entraide-Passerelle",
    "wof:placetype":"venue"
},
  "geometry": {"coordinates":[-71.2729797363,46.7125244141],"type":"Point"}
}