{
  "type": "Feature",
  "properties": {
    "addr:full":"315 Rue Charles-Marchand Le Gardeur QC J5Z 4N8",
    "addr:housenumber":"315",
    "addr:postcode":"j5z 4n8",
    "addr:street":"Rue Charles-Marchand;Gardeur",
    "iso:country":"CA",
    "sg:address":"315 Rue Charles-Marchand",
    "sg:city":"Le Gardeur",
    "sg:classifiers":[
        {
            "category":"Building & Trades",
            "subcategory":"Construction",
            "type":"Services"
        }
    ],
    "sg:phone":"+1 450 582 3357",
    "sg:postcode":"J5Z 4N8",
    "sg:province":"QC",
    "sg:tags":[
        "excavating",
        "contractor"
    ],
    "wof:name":"Jcr Belval Inc",
    "wof:placetype":"venue"
},
  "geometry": {"coordinates":[-73.4870147705,45.7588577271],"type":"Point"}
}