{
  "type": "Feature",
  "properties": {
    "addr:full":"Halifax NS B3J 1G9",
    "addr:postcode":"ns b3j 1g9",
    "iso:country":"CA",
    "sg:city":"Halifax",
    "sg:classifiers":[
        {
            "category":"Health Services",
            "subcategory":"Doctor",
            "type":"Services"
        }
    ],
    "sg:phone":"+1 902 422 5454",
    "sg:postcode":"B3J 1G9",
    "sg:province":"NS",
    "sg:tags":[
        "dentist"
    ],
    "wof:name":"Park Lane Dental Specialists",
    "wof:placetype":"venue"
},
  "geometry": {"coordinates":[-63.578651,44.642662],"type":"Point"}
}