{
  "type": "Feature",
  "properties": {
    "addr:full":"640 Mountain Rd Moncton NB E1C 2P3",
    "addr:housenumber":"640",
    "addr:postcode":"e1c 2p3",
    "addr:street":"Mountain Rd",
    "iso:country":"CA",
    "sg:address":"640 Mountain Rd",
    "sg:city":"Moncton",
    "sg:classifiers":[
        {
            "category":"Health Services",
            "subcategory":"Medical Lab",
            "type":"Services"
        }
    ],
    "sg:phone":"+1 506 857 8696",
    "sg:postcode":"E1C 2P3",
    "sg:province":"NB",
    "sg:tags":[
        "laboratory"
    ],
    "wof:name":"Dentech Dental Laboratory",
    "wof:placetype":"venue"
},
  "geometry": {"coordinates":[-64.7990264893,46.0982093811],"type":"Point"}
}