{
  "type": "Feature",
  "properties": {
    "addr:full":"14620 Rte Arthur-Sauve Mirabel QC J7N 2C1",
    "addr:housenumber":"14620",
    "addr:postcode":"j7n 2c1",
    "addr:street":"Rte Arthur-Sauve",
    "iso:country":"CA",
    "sg:address":"14620 Rte Arthur-Sauve",
    "sg:city":"Mirabel",
    "sg:classifiers":[
        {
            "category":"Restaurant",
            "type":"Food & Drink"
        }
    ],
    "sg:phone":"+1 450 258 2851",
    "sg:postcode":"J7N 2C1",
    "sg:province":"QC",
    "wof:name":"Snack Bar Au Vieux Frene",
    "wof:placetype":"venue"
},
  "geometry": {"coordinates":[-73.993538,45.579979],"type":"Point"}
}