{
  "type": "Feature",
  "properties": {
    "addr:full":"411 Avenue J N Saskatoon SK S7L 2K4",
    "addr:housenumber":"411",
    "addr:postcode":"s7l 2k4",
    "addr:street":"Avenue J N",
    "iso:country":"CA",
    "sg:address":"411 Avenue J N",
    "sg:city":"Saskatoon",
    "sg:classifiers":[
        {
            "category":"Education",
            "subcategory":"School",
            "type":"Public Place"
        }
    ],
    "sg:phone":"+1 306 683 7490",
    "sg:postcode":"S7L 2K4",
    "sg:province":"SK",
    "wof:name":"Westmount School",
    "wof:placetype":"venue"
},
  "geometry": {"coordinates":[-106.684631,52.133663],"type":"Point"}
}