{
  "type": "Feature",
  "properties": {
    "iso:country":"CA",
    "sg:address":"279 Yonge St",
    "sg:city":"Barrie",
    "sg:classifiers":[
        {
            "category":"Restaurant",
            "type":"Food & Drink"
        }
    ],
    "sg:phone":"+1 705 737 1111",
    "sg:postcode":"L4N 7T9",
    "sg:province":"ON",
    "sg:tags":[
        "pizza"
    ],
    "wof:name":"Pizza Pizza",
    "wof:placetype":"venue"
},
  "geometry": {"coordinates":[-79.670937,44.370602],"type":"Point"}
}