{
  "type": "Feature",
  "properties": {
    "addr:full":"Concord ON L4K 4L7",
    "addr:postcode":"l4k 4l7",
    "iso:country":"CA",
    "sg:city":"Concord",
    "sg:classifiers":[
        {
            "category":"Wholesale",
            "subcategory":"Construction Materials",
            "type":"Manufacturing & Wholesale Goods"
        }
    ],
    "sg:phone":"+1 905 738 7122",
    "sg:postcode":"L4K 4L7",
    "sg:province":"ON",
    "sg:tags":[
        "granite",
        "marble"
    ],
    "wof:name":"Albano International Inc",
    "wof:placetype":"venue"
},
  "geometry": {"coordinates":[-79.52636699999999,43.803757],"type":"Point"}
}