{
  "type": "Feature",
  "properties": {
    "addr:full":"26 North Front St Belleville ON K8P 3A9",
    "addr:housenumber":"26",
    "addr:postcode":"k8p 3a9",
    "addr:street":"North Front St",
    "iso:country":"CA",
    "sg:address":"26 North Front St",
    "sg:city":"Belleville",
    "sg:classifiers":[
        {
            "category":"Home & Garden",
            "subcategory":"Garden Supply",
            "type":"Retail Goods"
        }
    ],
    "sg:phone":"+1 613 962 0690",
    "sg:postcode":"K8P 3A9",
    "sg:province":"ON",
    "sg:tags":[
        "center"
    ],
    "wof:name":"Thrasher Garden & Nursery Ctr",
    "wof:placetype":"venue"
},
  "geometry": {"coordinates":[-77.387688,44.170795],"type":"Point"}
}