{
  "type": "Feature",
  "properties": {
    "addr:full":"151 Kings Rd Dominion NS B1G 1H9",
    "addr:housenumber":"151",
    "addr:postcode":"b1g 1h9",
    "addr:street":"Kings Rd",
    "iso:country":"CA",
    "sg:address":"151 Kings Rd",
    "sg:city":"Dominion",
    "sg:classifiers":[
        {
            "category":"Retail",
            "subcategory":"Auto Repair",
            "type":"Services"
        }
    ],
    "sg:phone":"+1 902 842 0679",
    "sg:postcode":"B1G 1H9",
    "sg:province":"NS",
    "sg:tags":[
        "repairing",
        "automobile",
        "body"
    ],
    "wof:name":"Gary Somerton's Car Care",
    "wof:placetype":"venue"
},
  "geometry": {"coordinates":[-60.014107,46.213585],"type":"Point"}
}