{
  "type": "Feature",
  "properties": {
    "addr:full":"519 Upper Sherman Ave Hamilton ON L8V 3L9",
    "addr:housenumber":"519",
    "addr:postcode":"l8v 3l9",
    "addr:street":"Upper Sherman Ave",
    "iso:country":"CA",
    "sg:address":"519 Upper Sherman Ave",
    "sg:city":"Hamilton",
    "sg:classifiers":[
        {
            "category":"Insurance",
            "subcategory":"Insurance Agent",
            "type":"Services"
        }
    ],
    "sg:phone":"+1 905 383 3346",
    "sg:postcode":"L8V 3L9",
    "sg:province":"ON",
    "wof:name":"Connor Insurance Ltd",
    "wof:placetype":"venue"
},
  "geometry": {"coordinates":[-79.84721399999999,43.231918],"type":"Point"}
}