{
  "type": "Feature",
  "properties": {
    "addr:full":"601 Main St E Milton ON L9T 3J2",
    "addr:housenumber":"601",
    "addr:postcode":"l9t 3j2",
    "addr:street":"Main St E",
    "iso:country":"CA",
    "sg:address":"601 Main St E",
    "sg:city":"Milton",
    "sg:classifiers":[
        {
            "category":"Home & Garden",
            "subcategory":"Building Materials",
            "type":"Retail Goods"
        }
    ],
    "sg:phone":"+1 905 878 9452",
    "sg:postcode":"L9T 3J2",
    "sg:province":"ON",
    "sg:tags":[
        "windows",
        "glass"
    ],
    "wof:name":"Koski Glass",
    "wof:placetype":"venue"
},
  "geometry": {"coordinates":[-79.874115,43.521744],"type":"Point"}
}