{
  "type": "Feature",
  "properties": {
    "addr:full":"330 Boyd St Wiarton ON N0H 2T0",
    "addr:housenumber":"330",
    "addr:postcode":"n0h 2t0",
    "addr:street":"Boyd St",
    "iso:country":"CA",
    "sg:address":"330 Boyd St",
    "sg:city":"Wiarton",
    "sg:classifiers":[
        {
            "category":"Organizations",
            "subcategory":"Professional Association",
            "type":"Services"
        }
    ],
    "sg:phone":"+1 519 534 0622",
    "sg:postcode":"N0H 2T0",
    "sg:province":"ON",
    "wof:name":"Royal Canadian Legion Br 208",
    "wof:placetype":"venue"
},
  "geometry": {"coordinates":[-81.14064,44.745197],"type":"Point"}
}