{
  "type": "Feature",
  "properties": {
    "addr:full":"Aylmer ON N5H 2R3",
    "addr:postcode":"n5h 2r3",
    "iso:country":"CA",
    "sg:city":"Aylmer",
    "sg:classifiers":[
        {
            "category":"Organizations",
            "subcategory":"Religious Organization",
            "type":"Services"
        }
    ],
    "sg:phone":"+1 519 773 7273",
    "sg:postcode":"N5H 2R3",
    "sg:province":"ON",
    "sg:tags":[
        "church"
    ],
    "wof:name":"Kingdom Hall",
    "wof:placetype":"venue"
},
  "geometry": {"coordinates":[-80.9836273193,42.7730064392],"type":"Point"}
}