{
  "type": "Feature",
  "properties": {
    "addr:full":"70 Rue Boulet Princeville QC G6L 4M1",
    "addr:housenumber":"70",
    "addr:postcode":"g6l 4m1",
    "addr:street":"Rue Boulet",
    "iso:country":"CA",
    "sg:address":"70 Rue Boulet",
    "sg:city":"Princeville",
    "sg:classifiers":[
        {
            "category":"Building & Trades",
            "subcategory":"Construction",
            "type":"Services"
        }
    ],
    "sg:phone":"+1 819 364 6010",
    "sg:postcode":"G6L 4M1",
    "sg:province":"QC",
    "sg:tags":[
        "concrete",
        "contractor"
    ],
    "wof:name":"Beton Chevalier Inc",
    "wof:placetype":"venue"
},
  "geometry": {"coordinates":[-71.888947,46.154945],"type":"Point"}
}