{
  "type": "Feature",
  "properties": {
    "addr:full":"Saint-Jerome QC J7Y 2G3",
    "addr:postcode":"j7y 2g3",
    "iso:country":"CA",
    "sg:city":"Saint-Jerome",
    "sg:classifiers":[
        {
            "category":"Shopping",
            "subcategory":"Florist",
            "type":"Retail Goods"
        }
    ],
    "sg:phone":"+1 450 436 8188",
    "sg:postcode":"J7Y 2G3",
    "sg:province":"QC",
    "wof:name":"Utopia Art Floral",
    "wof:placetype":"venue"
},
  "geometry": {"coordinates":[-74.014877,45.779705],"type":"Point"}
}