{
  "type": "Feature",
  "properties": {
    "iso:country":"CA",
    "sg:address":"56 Rue Saint-Georges",
    "sg:city":"Windsor",
    "sg:classifiers":[
        {
            "category":"Social Services",
            "type":"Services"
        }
    ],
    "sg:phone":"+1 819 845 7200",
    "sg:postcode":"J1S 1J5",
    "sg:province":"QC",
    "sg:tags":[
        "handicapped",
        "organization",
        "welfare"
    ],
    "wof:name":"Atelier Val St-Francois",
    "wof:placetype":"venue"
},
  "geometry": {"coordinates":[-72.0027542114,45.5701675415],"type":"Point"}
}