{
  "type": "Feature",
  "properties": {
    "addr:full":"Estevan SK S4A 2A6",
    "addr:postcode":"s4a 2a6",
    "iso:country":"CA",
    "sg:city":"Estevan",
    "sg:classifiers":[
        {
            "category":"Freight",
            "type":"Transportation"
        }
    ],
    "sg:phone":"+1 306 634 6950",
    "sg:postcode":"S4A 2A6",
    "sg:province":"SK",
    "sg:tags":[
        "commercial",
        "storage"
    ],
    "wof:name":"M & T Storage",
    "wof:placetype":"venue"
},
  "geometry": {"coordinates":[-102.991936,49.147968],"type":"Point"}
}