{
  "type": "Feature",
  "properties": {
    "iso:country":"CA",
    "sg:city":"Vancouver",
    "sg:classifiers":[
        {
            "category":"Professional",
            "type":"Services"
        }
    ],
    "sg:phone":"+1 604 681 0419",
    "sg:postcode":"V6C 1Z7",
    "sg:province":"BC",
    "sg:tags":[
        "consultant",
        "geological"
    ],
    "wof:name":"Mincord Exploration Conslnts",
    "wof:placetype":"venue"
},
  "geometry": {"coordinates":[-123.114204407,49.2864685059],"type":"Point"}
}