{
  "type": "Feature",
  "properties": {
    "addr:full":"32 Av DE LA Gare # C St-Sauveur-Des-Monts QC J0R 1R0",
    "addr:postcode":"j0r 1r0",
    "addr:street":"32 Av De La Gare # C St-Sauveur-Des-Monts",
    "iso:country":"CA",
    "sg:address":"32 Av DE LA Gare # C",
    "sg:city":"St-Sauveur-Des-Monts",
    "sg:classifiers":[
        {
            "category":"Manufacturing",
            "subcategory":"Printing",
            "type":"Manufacturing & Wholesale Goods"
        }
    ],
    "sg:phone":"+1 450 227 0591",
    "sg:postcode":"J0R 1R0",
    "sg:province":"QC",
    "sg:tags":[
        "marketing",
        "multimedia",
        "consultant"
    ],
    "wof:name":"Ads Inc",
    "wof:placetype":"venue"
},
  "geometry": {"coordinates":[-74.15624200000001,45.893772],"type":"Point"}
}