{
  "type": "Feature",
  "properties": {
    "addr:full":"499 Rte Laurier Issoudun QC G0S 1L0",
    "addr:housenumber":"499",
    "addr:postcode":"g0s 1l0",
    "addr:street":"Rte Laurier",
    "iso:country":"CA",
    "sg:address":"499 Rte Laurier",
    "sg:city":"Issoudun",
    "sg:classifiers":[
        {
            "category":"Wholesale",
            "subcategory":"Farm Supplies",
            "type":"Manufacturing & Wholesale Goods"
        }
    ],
    "sg:phone":"+1 418 728 2288",
    "sg:postcode":"G0S 1L0",
    "sg:province":"QC",
    "wof:name":"Equipements S Laroche Inc",
    "wof:placetype":"venue"
},
  "geometry": {"coordinates":[-71.622756958,46.5797119141],"type":"Point"}
}