{
  "type": "Feature",
  "properties": {
    "addr:full":"5884 Beach Ave Peachland BC V0H 1X7",
    "addr:housenumber":"5884",
    "addr:postcode":"v0h 1x7",
    "addr:street":"Beach Ave",
    "iso:country":"CA",
    "sg:address":"5884 Beach Ave",
    "sg:city":"Peachland",
    "sg:classifiers":[
        {
            "category":"Shopping",
            "subcategory":"Catalog Store",
            "type":"Retail Goods"
        }
    ],
    "sg:phone":"+1 250 767 6731",
    "sg:postcode":"V0H 1X7",
    "sg:province":"BC",
    "sg:tags":[
        "mail",
        "order",
        "internet"
    ],
    "wof:name":"Sears Canada Inc",
    "wof:placetype":"venue"
},
  "geometry": {"coordinates":[-119.738998,49.771267],"type":"Point"}
}