{
  "type": "Feature",
  "properties": {
    "addr:full":"147 Overbrook Pl North York ON M3H 4R1",
    "addr:housenumber":"147",
    "addr:postcode":"m3h 4r1",
    "addr:street":"Overbrook Pl",
    "iso:country":"CA",
    "sg:address":"147 Overbrook Pl",
    "sg:city":"North York",
    "sg:classifiers":[
        {
            "category":"Organizations",
            "subcategory":"Religious Organization",
            "type":"Services"
        }
    ],
    "sg:phone":"+1 416 638 5955",
    "sg:postcode":"M3H 4R1",
    "sg:province":"ON",
    "sg:tags":[
        "synagogue"
    ],
    "wof:name":"Beth Jacob Synagogue",
    "wof:placetype":"venue"
},
  "geometry": {"coordinates":[-79.457901001,43.762462616],"type":"Point"}
}