{
  "type": "Feature",
  "properties": {
    "addr:full":"Edmonton AB T5J 2T2",
    "addr:postcode":"t5j 2t2",
    "iso:country":"CA",
    "sg:city":"Edmonton",
    "sg:classifiers":[
        {
            "category":"Freight",
            "type":"Transportation"
        }
    ],
    "sg:phone":"+1 780 890 7014",
    "sg:postcode":"T5J 2T2",
    "sg:province":"AB",
    "sg:tags":[
        "broker",
        "customs"
    ],
    "wof:name":"Affiliated Customs Brokers Ltd",
    "wof:placetype":"venue"
},
  "geometry": {"coordinates":[-113.49037199999999,53.546219],"type":"Point"}
}