{
  "type": "Feature",
  "properties": {
    "iso:country":"CA",
    "sg:city":"Burnaby",
    "sg:classifiers":[
        {
            "category":"Insurance",
            "subcategory":"Insurance Agent",
            "type":"Services"
        }
    ],
    "sg:phone":"+1 604 294 3242",
    "sg:postcode":"V5C 2K5",
    "sg:province":"BC",
    "wof:name":"Don Wotherspoon & Assoc Ltd",
    "wof:placetype":"venue"
},
  "geometry": {"coordinates":[-122.999168396,49.2807846069],"type":"Point"}
}