{
  "type": "Feature",
  "properties": {
    "addr:full":"737 Essa Rd Barrie ON L4N 9G1",
    "addr:housenumber":"737",
    "addr:postcode":"l4n 9g1",
    "addr:street":"Essa Rd",
    "iso:country":"CA",
    "sg:address":"737 Essa Rd",
    "sg:city":"Barrie",
    "sg:classifiers":[
        {
            "category":"Building & Trades",
            "subcategory":"Construction",
            "type":"Services"
        }
    ],
    "sg:phone":"+1 705 721 6648",
    "sg:postcode":"L4N 9G1",
    "sg:province":"ON",
    "sg:tags":[
        "water",
        "well",
        "drilling"
    ],
    "wof:name":"Al Hammers Well Drilling Inc",
    "wof:placetype":"venue"
},
  "geometry": {"coordinates":[-79.71653000000001,44.326077],"type":"Point"}
}