{
  "type": "Feature",
  "properties": {
    "addr:full":"155 Main St Thessalon ON P0R 1L0",
    "addr:housenumber":"155",
    "addr:postcode":"p0r 1l0",
    "addr:street":"Main St",
    "iso:country":"CA",
    "sg:address":"155 Main St",
    "sg:city":"Thessalon",
    "sg:classifiers":[
        {
            "category":"Shopping",
            "subcategory":"Pharmacy",
            "type":"Retail Goods"
        }
    ],
    "sg:phone":"+1 705 842 2322",
    "sg:postcode":"P0R 1L0",
    "sg:province":"ON",
    "wof:name":"Main Street Pharmacy",
    "wof:placetype":"venue"
},
  "geometry": {"coordinates":[-83.55698394780001,46.2557411194],"type":"Point"}
}