{
  "type": "Feature",
  "properties": {
    "iso:country":"CA",
    "sg:city":"Surrey",
    "sg:classifiers":[
        {
            "category":"Retail",
            "subcategory":"Repair Shop",
            "type":"Services"
        }
    ],
    "sg:phone":"+1 604 507 0030",
    "sg:postcode":"V3S 1X7",
    "sg:province":"BC",
    "sg:tags":[
        "welding"
    ],
    "wof:name":"Big Boyz Welding & Fabricating",
    "wof:placetype":"venue"
},
  "geometry": {"coordinates":[-122.81569671600001,49.1189727783],"type":"Point"}
}