{
  "type": "Feature",
  "properties": {
    "addr:full":"10207 Guelph Line Campbellville ON L0P 1B0",
    "addr:housenumber":"10207",
    "addr:postcode":"l0p 1b0",
    "addr:street":"Guelph Line",
    "iso:country":"CA",
    "sg:address":"10207 Guelph Line",
    "sg:city":"Campbellville",
    "sg:classifiers":[
        {
            "category":"Retail",
            "subcategory":"Animal Services",
            "type":"Services"
        }
    ],
    "sg:phone":"+1 905 854 0224",
    "sg:postcode":"L0P 1B0",
    "sg:province":"ON",
    "sg:tags":[
        "equestrian",
        "center"
    ],
    "wof:name":"Equine Swimming",
    "wof:placetype":"venue"
},
  "geometry": {"coordinates":[-80.00868199999999,43.50563],"type":"Point"}
}