{
  "type": "Feature",
  "properties": {
    "iso:country":"CA",
    "sg:city":"Burnaby",
    "sg:classifiers":[
        {
            "category":"Shopping",
            "type":"Retail Goods"
        }
    ],
    "sg:phone":"+1 604 298 9534",
    "sg:postcode":"V5B 2Y1",
    "sg:province":"BC",
    "sg:tags":[
        "trophy",
        "medal",
        "award"
    ],
    "wof:name":"Victory Trophies Ltd",
    "wof:placetype":"venue"
},
  "geometry": {"coordinates":[-122.97820282000001,49.2650642395],"type":"Point"}
}