{
  "type": "Feature",
  "properties": {
    "iso:country":"CA",
    "sg:city":"Contrecoeur",
    "sg:classifiers":[
        {
            "category":"Shopping",
            "subcategory":"Clothing, Apparel, & Fashions",
            "type":"Retail Goods"
        }
    ],
    "sg:phone":"+1 450 587 2442",
    "sg:postcode":"J0L 1C0",
    "sg:province":"QC",
    "sg:tags":[
        "item",
        "boutique"
    ],
    "wof:name":"Western Wear Round-Up Inc",
    "wof:placetype":"venue"
},
  "geometry": {"coordinates":[-73.2388534546,45.8573608398],"type":"Point"}
}