{
  "type": "Feature",
  "properties": {
    "iso:country":"CA",
    "sg:city":"Kelowna",
    "sg:classifiers":[
        {
            "category":"Manufacturing",
            "subcategory":"Chemicals & Compounds",
            "type":"Manufacturing & Wholesale Goods"
        }
    ],
    "sg:phone":"+1 250 491 3133",
    "sg:postcode":"V1X 7S5",
    "sg:province":"BC",
    "sg:tags":[
        "equipment",
        "supply"
    ],
    "wof:name":"Westmould Manufacturing",
    "wof:placetype":"venue"
},
  "geometry": {"coordinates":[-119.391479492,49.9183120728],"type":"Point"}
}