{
  "type": "Feature",
  "properties": {
    "iso:country":"CA",
    "sg:address":"240 5th Ave NE",
    "sg:city":"Altona",
    "sg:classifiers":[
        {
            "category":"Government",
            "subcategory":"Office",
            "type":"Public Place"
        }
    ],
    "sg:phone":"+1 204 324 1261",
    "sg:postcode":"R0G 0B0",
    "sg:province":"MB",
    "wof:name":"Manitoba Family Svc",
    "wof:placetype":"venue"
},
  "geometry": {"coordinates":[-97.5543136597,49.107093811],"type":"Point"}
}