{
  "type": "Feature",
  "properties": {
    "addr:full":"101 Johnstone Ave Dartmouth NS B2Y 2K6",
    "addr:housenumber":"101",
    "addr:postcode":"b2y 2k6",
    "addr:street":"Johnstone Ave",
    "iso:country":"CA",
    "sg:address":"101 Johnstone Ave",
    "sg:city":"Dartmouth",
    "sg:classifiers":[
        {
            "category":"Health Services",
            "subcategory":"Health Practitioner",
            "type":"Services"
        }
    ],
    "sg:phone":"+1 902 461 8290",
    "sg:postcode":"B2Y 2K6",
    "sg:province":"NS",
    "sg:tags":[
        "physiotherapist"
    ],
    "wof:name":"Bonnie Blink Physiotherapy",
    "wof:placetype":"venue"
},
  "geometry": {"coordinates":[-63.553024292,44.6654930115],"type":"Point"}
}