{
  "type": "Feature",
  "properties": {
    "iso:country":"CA",
    "sg:address":"1366 Coldrey Ave",
    "sg:city":"Ottawa",
    "sg:classifiers":[
        {
            "category":"Education",
            "subcategory":"School",
            "type":"Public Place"
        }
    ],
    "sg:phone":"+1 613 728 4744",
    "sg:postcode":"K1Z 7P5",
    "sg:province":"ON",
    "wof:name":"St Elizabeth School",
    "wof:placetype":"venue"
},
  "geometry": {"coordinates":[-75.7368392944,45.3819999695],"type":"Point"}
}