{
  "type": "Feature",
  "properties": {
    "addr:full":"897 3E Ave Quebec QC G1L 2W8",
    "addr:housenumber":"897",
    "addr:postcode":"g1l 2w8",
    "addr:street":"3E Ave",
    "iso:country":"CA",
    "sg:address":"897 3E Ave",
    "sg:city":"Quebec",
    "sg:classifiers":[
        {
            "category":"Real Estate",
            "subcategory":"Real Estate Agent",
            "type":"Services"
        }
    ],
    "sg:phone":"+1 418 524 4441",
    "sg:postcode":"G1L 2W8",
    "sg:province":"QC",
    "wof:name":"Turmel & Assoc Courtiers Inc",
    "wof:placetype":"venue"
},
  "geometry": {"coordinates":[-71.229294,46.825748],"type":"Point"}
}