{
  "type": "Feature",
  "properties": {
    "addr:full":"11 Sparling Rd St Thomas ON N5P 4A4",
    "addr:housenumber":"11",
    "addr:postcode":"n5p 4a4",
    "addr:street":"Sparling Rd",
    "iso:country":"CA",
    "sg:address":"11 Sparling Rd",
    "sg:city":"St Thomas",
    "sg:classifiers":[
        {
            "category":"Retail",
            "subcategory":"Auto Repair",
            "type":"Services"
        }
    ],
    "sg:phone":"+1 519 631 9210",
    "sg:postcode":"N5P 4A4",
    "sg:province":"ON",
    "sg:tags":[
        "body",
        "automobile",
        "painting"
    ],
    "wof:name":"Industrial Park Auto Body",
    "wof:placetype":"venue"
},
  "geometry": {"coordinates":[-81.156364,42.786713],"type":"Point"}
}