{
  "type": "Feature",
  "properties": {
    "iso:country":"CA",
    "sg:address":"7903 20E Av",
    "sg:city":"Montreal",
    "sg:classifiers":[
        {
            "category":"Shopping",
            "subcategory":"Computers & Home Electronics",
            "type":"Retail Goods"
        }
    ],
    "sg:phone":"+1 514 376 4990",
    "sg:postcode":"H1Z 3S6",
    "sg:province":"QC",
    "sg:tags":[
        "radio",
        "television",
        "video",
        "equipment"
    ],
    "wof:name":"Capri Electronique Inc",
    "wof:placetype":"venue"
},
  "geometry": {"coordinates":[-73.60237121580001,45.5693511963],"type":"Point"}
}