{
  "type": "Feature",
  "properties": {
    "addr:full":"1455 Rue Metcalfe Montreal QC H3A 1X5",
    "addr:housenumber":"1455",
    "addr:postcode":"h3a 1x5",
    "addr:street":"Rue Metcalfe",
    "iso:country":"CA",
    "sg:address":"1455 Rue Metcalfe",
    "sg:city":"Montreal",
    "sg:classifiers":[
        {
            "category":"Parking",
            "type":"Transportation"
        }
    ],
    "sg:phone":"+1 514 286 9389",
    "sg:postcode":"H3A 1X5",
    "sg:province":"QC",
    "sg:tags":[
        "garage"
    ],
    "wof:name":"3 P Parking",
    "wof:placetype":"venue"
},
  "geometry": {"coordinates":[-73.57283,45.501163],"type":"Point"}
}