{
  "type": "Feature",
  "properties": {
    "addr:full":"50 South St Goderich ON N7A 3L5",
    "addr:housenumber":"50",
    "addr:postcode":"n7a 3l5",
    "addr:street":"South St",
    "iso:country":"CA",
    "sg:address":"50 South St",
    "sg:city":"Goderich",
    "sg:classifiers":[
        {
            "category":"Health Services",
            "subcategory":"Doctor",
            "type":"Services"
        }
    ],
    "sg:phone":"+1 519 524 9655",
    "sg:postcode":"N7A 3L5",
    "sg:province":"ON",
    "sg:tags":[
        "dentist"
    ],
    "wof:name":"Thomasson, B T DDS",
    "wof:placetype":"venue"
},
  "geometry": {"coordinates":[-81.711349,43.741306],"type":"Point"}
}