{
  "type": "Feature",
  "properties": {
    "iso:country":"CA",
    "sg:city":"Courtenay",
    "sg:classifiers":[
        {
            "category":"Personal",
            "subcategory":"Tanning Parlor",
            "type":"Services"
        }
    ],
    "sg:phone":"+1 250 703 0207",
    "sg:postcode":"V9N 2L6",
    "sg:province":"BC",
    "sg:tags":[
        "salon"
    ],
    "wof:name":"Tan Your Hyde Studios",
    "wof:placetype":"venue"
},
  "geometry": {"coordinates":[-124.98144531200001,49.6746063232],"type":"Point"}
}