{
  "type": "Feature",
  "properties": {
    "addr:full":"Hamilton ON L8V 4R5",
    "addr:postcode":"l8v 4r5",
    "iso:country":"CA",
    "sg:city":"Hamilton",
    "sg:classifiers":[
        {
            "category":"Health Services",
            "subcategory":"Doctor",
            "type":"Services"
        }
    ],
    "sg:phone":"+1 905 575 4400",
    "sg:postcode":"L8V 4R5",
    "sg:province":"ON",
    "sg:tags":[
        "physician",
        "surgeon"
    ],
    "wof:name":"Community Medical Ctr",
    "wof:placetype":"venue"
},
  "geometry": {"coordinates":[-79.84534499999999,43.213703],"type":"Point"}
}