{
  "type": "Feature",
  "properties": {
    "addr:full":"187 Kehoe St Ottawa ON K2B 6A6",
    "addr:housenumber":"187",
    "addr:postcode":"k2b 6a6",
    "addr:street":"Kehoe St",
    "iso:country":"CA",
    "sg:address":"187 Kehoe St",
    "sg:city":"Ottawa",
    "sg:classifiers":[
        {
            "category":"Professional",
            "subcategory":"Management & Consulting",
            "type":"Services"
        }
    ],
    "sg:phone":"+1 613 721 0751",
    "sg:postcode":"K2B 6A6",
    "sg:province":"ON",
    "sg:tags":[
        "consultant",
        "telecommunication"
    ],
    "wof:name":"Cybit Corp",
    "wof:placetype":"venue"
},
  "geometry": {"coordinates":[-75.8001174927,45.3671989441],"type":"Point"}
}