{
  "type": "Feature",
  "properties": {
    "addr:full":"550 Mckeown Ave North Bay ON P1B 8K3",
    "addr:housenumber":"550",
    "addr:postcode":"p1b 8k3",
    "addr:street":"Mckeown Ave",
    "iso:country":"CA",
    "sg:address":"550 Mckeown Ave",
    "sg:city":"North Bay",
    "sg:classifiers":[
        {
            "category":"Autos & Motor Vehicles",
            "subcategory":"Automobile Sales",
            "type":"Retail Goods"
        }
    ],
    "sg:phone":"+1 705 472 3110",
    "sg:postcode":"P1B 8K3",
    "sg:province":"ON",
    "sg:tags":[
        "car",
        "dealer"
    ],
    "wof:name":"Hopper Pontiac Buick Gmc",
    "wof:placetype":"venue"
},
  "geometry": {"coordinates":[-79.4845123291,46.3325119019],"type":"Point"}
}