{
  "type": "Feature",
  "properties": {
    "addr:full":"2984 Boul Taschereau # 300 Greenfield Park QC J4V 2G9",
    "addr:housenumber":"2984",
    "addr:postcode":"j4v 2g9",
    "addr:street":"Boul Taschereau # 300;Park",
    "iso:country":"CA",
    "sg:address":"2984 Boul Taschereau # 300",
    "sg:city":"Greenfield Park",
    "sg:classifiers":[
        {
            "category":"Health Services",
            "subcategory":"Health Practitioner",
            "type":"Services"
        }
    ],
    "sg:phone":"+1 450 465 5910",
    "sg:postcode":"J4V 2G9",
    "sg:province":"QC",
    "sg:tags":[
        "physiotherapist",
        "clinic"
    ],
    "wof:name":"Clinique DE Physiotherapie",
    "wof:placetype":"venue"
},
  "geometry": {"coordinates":[-73.486679,45.498859],"type":"Point"}
}