{
  "type": "Feature",
  "properties": {
    "iso:country":"CA",
    "sg:address":"4444 Builders Rd SE",
    "sg:city":"Calgary",
    "sg:classifiers":[
        {
            "category":"Manufacturing",
            "subcategory":"Glass & Minerals",
            "type":"Manufacturing & Wholesale Goods"
        }
    ],
    "sg:phone":"+1 403 243 6031",
    "sg:postcode":"T2G 4C6",
    "sg:province":"AB",
    "sg:tags":[
        "stone",
        "structural"
    ],
    "wof:name":"Ixl Brick Supplies Ltd",
    "wof:placetype":"venue"
},
  "geometry": {"coordinates":[-114.06076049799999,51.0133132935],"type":"Point"}
}