{
  "type": "Feature",
  "properties": {
    "iso:country":"CA",
    "sg:address":"15 Robb Blvd",
    "sg:city":"Orangeville",
    "sg:classifiers":[
        {
            "category":"Retail",
            "subcategory":"Auto Repair",
            "type":"Services"
        }
    ],
    "sg:phone":"+1 519 942 5929",
    "sg:postcode":"L9W 3L1",
    "sg:province":"ON",
    "sg:tags":[
        "repairing",
        "automobile",
        "body"
    ],
    "wof:name":"Erskine's Service Ctr Ltd",
    "wof:placetype":"venue"
},
  "geometry": {"coordinates":[-80.110916,43.906624],"type":"Point"}
}