{
  "type": "Feature",
  "properties": {
    "addr:full":"62 Main St S Milverton ON N0K 1M0",
    "addr:housenumber":"62",
    "addr:postcode":"n0k 1m0",
    "addr:street":"Main St S Milverton",
    "iso:country":"CA",
    "sg:address":"62 Main St S",
    "sg:city":"Milverton",
    "sg:classifiers":[
        {
            "category":"Retail",
            "subcategory":"Veterinary Services",
            "type":"Services"
        }
    ],
    "sg:phone":"+1 519 595 8888",
    "sg:postcode":"N0K 1M0",
    "sg:province":"ON",
    "sg:tags":[
        "veterinarian"
    ],
    "wof:name":"Pauly Veterinarian Clinic",
    "wof:placetype":"venue"
},
  "geometry": {"coordinates":[-80.925072,43.562347],"type":"Point"}
}