{
  "type": "Feature",
  "properties": {
    "addr:full":"15102 128 Ave NW #100 Edmonton AB T5V 1A8",
    "addr:housenumber":"15102",
    "addr:postcode":"t5v 1a8",
    "addr:street":"128 Ave Nw # 100",
    "iso:country":"CA",
    "sg:address":"15102 128 Ave NW #100",
    "sg:city":"Edmonton",
    "sg:phone":"+1 780 454 3366",
    "sg:postcode":"T5V 1A8",
    "sg:province":"AB",
    "sg:tags":[
        "equipment",
        "supply"
    ],
    "wof:name":"Groupex Canada Inc",
    "wof:placetype":"venue"
},
  "geometry": {"coordinates":[-113.582214355,53.5851287842],"type":"Point"}
}