{
  "type": "Feature",
  "properties": {
    "addr:full":"147 Whitehorn Rd NE Calgary AB T1Y 2A1",
    "addr:housenumber":"147",
    "addr:postcode":"t1y 2a1",
    "addr:street":"Whitehorn Rd Ne",
    "iso:country":"CA",
    "sg:address":"147 Whitehorn Rd NE",
    "sg:city":"Calgary",
    "sg:classifiers":[
        {
            "category":"Building & Trades",
            "subcategory":"Electrical",
            "type":"Services"
        }
    ],
    "sg:phone":"+1 403 293 3000",
    "sg:postcode":"T1Y 2A1",
    "sg:province":"AB",
    "sg:tags":[
        "electric",
        "contractor"
    ],
    "wof:name":"Alberta Electrical Mntnc Svc",
    "wof:placetype":"venue"
},
  "geometry": {"coordinates":[-113.967781,51.086845],"type":"Point"}
}