{
  "type": "Feature",
  "properties": {
    "addr:full":"Montreal QC H2L 3R6",
    "addr:postcode":"h2l 3r6",
    "iso:country":"CA",
    "sg:city":"Montreal",
    "sg:classifiers":[
        {
            "category":"Health Services",
            "subcategory":"Health Practitioner",
            "type":"Services"
        }
    ],
    "sg:phone":"+1 514 598 1515",
    "sg:postcode":"H2L 3R6",
    "sg:province":"QC",
    "sg:tags":[
        "psychologist"
    ],
    "wof:name":"Richer, Chantal",
    "wof:placetype":"venue"
},
  "geometry": {"coordinates":[-73.5700378418,45.522315979],"type":"Point"}
}