{
  "type": "Feature",
  "properties": {
    "iso:country":"CA",
    "sg:address":"1170 Boul Lebourgneuf # 405",
    "sg:city":"Quebec",
    "sg:classifiers":[
        {
            "category":"Organizations",
            "subcategory":"Professional Association",
            "type":"Services"
        }
    ],
    "sg:phone":"+1 418 626 0861",
    "sg:postcode":"G2K 2E3",
    "sg:province":"QC",
    "wof:name":"Regroupement Des Infirmieres",
    "wof:placetype":"venue"
},
  "geometry": {"coordinates":[-71.293945,46.836075],"type":"Point"}
}