{
  "type": "Feature",
  "properties": {
    "addr:full":"1944 Merivale Rd Nepean ON K2G 1E9",
    "addr:housenumber":"1944",
    "addr:postcode":"k2g 1e9",
    "addr:street":"Merivale Rd",
    "iso:country":"CA",
    "sg:address":"1944 Merivale Rd",
    "sg:city":"Nepean",
    "sg:classifiers":[
        {
            "category":"Autos & Motor Vehicles",
            "subcategory":"Fuel & Gas Station",
            "type":"Retail Goods"
        }
    ],
    "sg:phone":"+1 613 225 5375",
    "sg:postcode":"K2G 1E9",
    "sg:province":"ON",
    "sg:tags":[
        "oil"
    ],
    "wof:name":"Gas Bar Francis",
    "wof:placetype":"venue"
},
  "geometry": {"coordinates":[-75.7199172974,45.3269233704],"type":"Point"}
}