{
  "type": "Feature",
  "properties": {
    "iso:country":"CA",
    "sg:address":"2020 Rue University",
    "sg:city":"Montreal",
    "sg:classifiers":[
        {
            "category":"Professional",
            "subcategory":"Computer Services",
            "type":"Services"
        }
    ],
    "sg:phone":"+1 514 499 1312",
    "sg:postcode":"H3A 2A5",
    "sg:province":"QC",
    "sg:tags":[
        "information",
        "system",
        "consultant"
    ],
    "wof:name":"Posera Software Inc",
    "wof:placetype":"venue"
},
  "geometry": {"coordinates":[-73.57186889650001,45.504070282],"type":"Point"}
}