{
  "type": "Feature",
  "properties": {
    "addr:full":"Ashern MB R0C 0E0",
    "addr:postcode":"r0c 0e0",
    "iso:country":"CA",
    "sg:city":"Ashern",
    "sg:classifiers":[
        {
            "category":"Autos & Motor Vehicles",
            "subcategory":"Auto Supplies",
            "type":"Retail Goods"
        }
    ],
    "sg:phone":"+1 204 768 3068",
    "sg:postcode":"R0C 0E0",
    "sg:province":"MB",
    "sg:tags":[
        "tire"
    ],
    "wof:name":"Roys' Ashern Tire & Quick Lube",
    "wof:placetype":"venue"
},
  "geometry": {"coordinates":[-98.35010528559999,51.1798210144],"type":"Point"}
}