{
  "type": "Feature",
  "properties": {
    "addr:full":"Rouyn-Noranda QC J9X 5E5",
    "addr:postcode":"j9x 5e5",
    "iso:country":"CA",
    "sg:city":"Rouyn-Noranda",
    "sg:classifiers":[
        {
            "category":"Organizations",
            "subcategory":"Labor Organization",
            "type":"Services"
        }
    ],
    "sg:phone":"+1 819 762 6265",
    "sg:postcode":"J9X 5E5",
    "sg:province":"QC",
    "wof:name":"Syndicat Des Enseignantes",
    "wof:placetype":"venue"
},
  "geometry": {"coordinates":[-79.00775899999999,48.227497],"type":"Point"}
}