{
  "type": "Feature",
  "properties": {
    "addr:full":"Carrying Place ON K0K 1L0",
    "addr:postcode":"k0k 1l0",
    "addr:street":"Carrying Place",
    "iso:country":"CA",
    "sg:city":"Carrying Place",
    "sg:classifiers":[
        {
            "category":"Retail",
            "subcategory":"Repair Shop",
            "type":"Services"
        }
    ],
    "sg:phone":"+1 613 394 2233",
    "sg:postcode":"K0K 1L0",
    "sg:province":"ON",
    "sg:tags":[
        "sharpening",
        "lawn",
        "mower"
    ],
    "wof:name":"Bob's Small Engine Repair",
    "wof:placetype":"venue"
},
  "geometry": {"coordinates":[-77.579628,44.047871],"type":"Point"}
}