{
  "type": "Feature",
  "properties": {
    "iso:country":"CA",
    "sg:city":"Surrey",
    "sg:classifiers":[
        {
            "category":"Professional",
            "subcategory":"Detective & Security Services",
            "type":"Services"
        }
    ],
    "sg:phone":"+1 604 591 7459",
    "sg:postcode":"V3W 0T7",
    "sg:province":"BC",
    "sg:tags":[
        "ironwork",
        "system"
    ],
    "wof:name":"Security Machine & Allspan Mfg",
    "wof:placetype":"venue"
},
  "geometry": {"coordinates":[-122.830215454,49.105178833],"type":"Point"}
}