{
  "type": "Feature",
  "properties": {
    "addr:full":"57 Mississauga Ave Elliot Lake ON P5A 1E1",
    "addr:housenumber":"57",
    "addr:postcode":"p5a 1e1",
    "addr:street":"Mississauga Ave",
    "iso:country":"CA",
    "sg:address":"57 Mississauga Ave",
    "sg:city":"Elliot Lake",
    "sg:classifiers":[
        {
            "category":"Wholesale",
            "subcategory":"Electrical",
            "type":"Manufacturing & Wholesale Goods"
        }
    ],
    "sg:phone":"+1 705 848 3929",
    "sg:postcode":"P5A 1E1",
    "sg:province":"ON",
    "sg:tags":[
        "fire",
        "equipment",
        "protection"
    ],
    "wof:name":"North Shore Fire Extinguishers",
    "wof:placetype":"venue"
},
  "geometry": {"coordinates":[-82.650543,46.377022],"type":"Point"}
}