{
  "type": "Feature",
  "properties": {
    "addr:full":"North York ON M4A 2S8",
    "addr:postcode":"m4a 2s8",
    "iso:country":"CA",
    "sg:city":"North York",
    "sg:classifiers":[
        {
            "category":"Banks & Credit Unions",
            "subcategory":"Bank",
            "type":"Services"
        }
    ],
    "sg:phone":"+1 416 757 3603",
    "sg:postcode":"M4A 2S8",
    "sg:province":"ON",
    "sg:tags":[
        "loan",
        "real estate"
    ],
    "wof:name":"Citifinancial Canada Inc",
    "wof:placetype":"venue"
},
  "geometry": {"coordinates":[-79.313248,43.741722],"type":"Point"}
}