{
  "type": "Feature",
  "properties": {
    "addr:full":"346 Rue Racine Granby QC J2G 3B8",
    "addr:housenumber":"346",
    "addr:postcode":"j2g 3b8",
    "addr:street":"Rue Racine",
    "iso:country":"CA",
    "sg:address":"346 Rue Racine",
    "sg:city":"Granby",
    "sg:classifiers":[
        {
            "category":"Education",
            "subcategory":"Special Training",
            "type":"Public Place"
        }
    ],
    "sg:phone":"+1 450 378 7177",
    "sg:postcode":"J2G 3B8",
    "sg:province":"QC",
    "sg:tags":[
        "cocoa",
        "chocolate"
    ],
    "wof:name":"Chocolats Pauline",
    "wof:placetype":"venue"
},
  "geometry": {"coordinates":[-72.733124,45.400917],"type":"Point"}
}