{
  "type": "Feature",
  "properties": {
    "addr:full":"20673 Kitsequecla Lake Rd Smithers BC V0J 2N1",
    "addr:postcode":"20673;v0j 2n1",
    "addr:street":"Kitsequecla Lake Rd",
    "iso:country":"CA",
    "sg:address":"20673 Kitsequecla Lake Rd",
    "sg:city":"Smithers",
    "sg:classifiers":[
        {
            "category":"Travel",
            "subcategory":"Hotels & Motels",
            "type":"Entertainment"
        }
    ],
    "sg:phone":"+1 250 847 9940",
    "sg:postcode":"V0J 2N1",
    "sg:province":"BC",
    "sg:tags":[
        "resort"
    ],
    "wof:name":"Mapleleaf Cabin",
    "wof:placetype":"venue"
},
  "geometry": {"coordinates":[-127.16812899999999,54.782803],"type":"Point"}
}