{
  "type": "Feature",
  "properties": {
    "addr:full":"Vancouver BC V5P 2S7",
    "addr:postcode":"v5p 2s7",
    "iso:country":"CA",
    "sg:city":"Vancouver",
    "sg:classifiers":[
        {
            "category":"Wholesale",
            "subcategory":"Sporting Goods",
            "type":"Manufacturing & Wholesale Goods"
        }
    ],
    "sg:phone":"+1 604 325 4080",
    "sg:postcode":"V5P 2S7",
    "sg:province":"BC",
    "wof:name":"Cindy Menzies Agency",
    "wof:placetype":"venue"
},
  "geometry": {"coordinates":[-123.06842041,49.2077598572],"type":"Point"}
}