{
  "type": "Feature",
  "properties": {
    "addr:full":"6339 Egremont Dr Komoka ON N0L 1R0",
    "addr:housenumber":"6339",
    "addr:postcode":"n0l 1r0",
    "addr:street":"Egremont Dr",
    "iso:country":"CA",
    "sg:address":"6339 Egremont Dr",
    "sg:city":"Komoka",
    "sg:classifiers":[
        {
            "category":"Autos & Motor Vehicles",
            "subcategory":"Automobile Sales",
            "type":"Retail Goods"
        }
    ],
    "sg:phone":"+1 519 666 0508",
    "sg:postcode":"N0L 1R0",
    "sg:province":"ON",
    "sg:tags":[
        "car",
        "dealer"
    ],
    "wof:name":"G & J Used Cars",
    "wof:placetype":"venue"
},
  "geometry": {"coordinates":[-81.42440000000001,43.000233],"type":"Point"}
}