{
  "type": "Feature",
  "properties": {
    "addr:full":"Temagami ON P0H 2H0",
    "addr:postcode":"p0h 2h0",
    "iso:country":"CA",
    "sg:city":"Temagami",
    "sg:classifiers":[
        {
            "category":"Travel",
            "subcategory":"Hotels & Motels",
            "type":"Entertainment"
        }
    ],
    "sg:phone":"+1 705 569 3800",
    "sg:postcode":"P0H 2H0",
    "sg:province":"ON",
    "sg:tags":[
        "resort"
    ],
    "wof:name":"Papa John's Place",
    "wof:placetype":"venue"
},
  "geometry": {"coordinates":[-79.789551,47.065605],"type":"Point"}
}