{
  "type": "Feature",
  "properties": {
    "addr:full":"Souris MB R0K 2C0",
    "addr:postcode":"r0k 2c0",
    "iso:country":"CA",
    "sg:city":"Souris",
    "sg:classifiers":[
        {
            "category":"Education",
            "subcategory":"Library",
            "type":"Public Place"
        }
    ],
    "sg:phone":"+1 204 483 2757",
    "sg:postcode":"R0K 2C0",
    "sg:province":"MB",
    "wof:name":"Souris & Glenwood Reg Library",
    "wof:placetype":"venue"
},
  "geometry": {"coordinates":[-100.258865356,49.6208343506],"type":"Point"}
}