{
  "type": "Feature",
  "properties": {
    "iso:country":"CA",
    "sg:address":"2051 Boul Rosemont",
    "sg:city":"Montreal",
    "sg:classifiers":[
        {
            "category":"Restaurant",
            "type":"Food & Drink"
        }
    ],
    "sg:phone":"+1 514 722 8530",
    "sg:postcode":"H2G 1T2",
    "sg:province":"QC",
    "wof:name":"Capri Restaurant Delicatessen",
    "wof:placetype":"venue"
},
  "geometry": {"coordinates":[-73.589661,45.542839],"type":"Point"}
}