{
  "type": "Feature",
  "properties": {
    "addr:full":"2051 Boul Rosemont Montreal QC H2G 1T2",
    "addr:housenumber":"2051",
    "addr:postcode":"h2g 1t2",
    "addr:street":"Boul Rosemont",
    "iso:country":"CA",
    "sg:address":"2051 Boul Rosemont",
    "sg:city":"Montreal",
    "sg:classifiers":[
        {
            "category":"Restaurant",
            "type":"Food & Drink"
        }
    ],
    "sg:phone":"+1 514 722 8530",
    "sg:postcode":"H2G 1T2",
    "sg:province":"QC",
    "wof:name":"Capri Restaurant Delicatessen",
    "wof:placetype":"venue"
},
  "geometry": {"coordinates":[-73.58966100000001,45.542839],"type":"Point"}
}