{
  "type": "Feature",
  "properties": {
    "addr:full":"361 Simon Fraser Fort St James BC V0J 1P0",
    "addr:housenumber":"361",
    "addr:postcode":"v0j 1p0",
    "addr:street":"Simon Fraser Fort St",
    "iso:country":"CA",
    "sg:address":"361 Simon Fraser",
    "sg:city":"Fort St James",
    "sg:classifiers":[
        {
            "category":"Manufacturing",
            "subcategory":"Lumber",
            "type":"Manufacturing & Wholesale Goods"
        }
    ],
    "sg:phone":"+1 250 996 8072",
    "sg:postcode":"V0J 1P0",
    "sg:province":"BC",
    "sg:tags":[
        "forester"
    ],
    "wof:name":"Bell Heather Contracting Ltd",
    "wof:placetype":"venue"
},
  "geometry": {"coordinates":[-124.252022,54.443287],"type":"Point"}
}