{
  "type": "Feature",
  "properties": {
    "iso:country":"CA",
    "sg:city":"Vancouver",
    "sg:classifiers":[
        {
            "category":"Professional",
            "subcategory":"Management & Consulting",
            "type":"Services"
        }
    ],
    "sg:phone":"+1 604 687 5552",
    "sg:postcode":"V6E 4A2",
    "sg:province":"BC",
    "sg:tags":[
        "training",
        "sales"
    ],
    "wof:name":"Kison Inc",
    "wof:placetype":"venue"
},
  "geometry": {"coordinates":[-123.125007629,49.2867851257],"type":"Point"}
}