{
  "type": "Feature",
  "properties": {
    "addr:full":"705 Av Du Pont N Alma QC G8B 6T5",
    "addr:postcode":"g8b 6t5",
    "addr:street":"705 Av Du Pont N",
    "iso:country":"CA",
    "sg:address":"705 Av Du Pont N",
    "sg:city":"Alma",
    "sg:classifiers":[
        {
            "category":"Shopping",
            "subcategory":"Clothing, Apparel, & Fashions",
            "type":"Retail Goods"
        }
    ],
    "sg:phone":"+1 418 662 4882",
    "sg:postcode":"G8B 6T5",
    "sg:province":"QC",
    "sg:tags":[
        "item",
        "boutique"
    ],
    "wof:name":"Jeans Plus Inc",
    "wof:placetype":"venue"
},
  "geometry": {"coordinates":[-71.642212,48.56197],"type":"Point"}
}