{
  "type": "Feature",
  "properties": {
    "iso:country":"CA",
    "sg:address":"1318 Dominion Rd",
    "sg:city":"Fort Erie",
    "sg:classifiers":[
        {
            "category":"Restaurant",
            "type":"Food & Drink"
        }
    ],
    "sg:phone":"+1 905 871 8431",
    "sg:postcode":"L2A 1J3",
    "sg:province":"ON",
    "wof:name":"Antonio's Pizzeria",
    "wof:placetype":"venue"
},
  "geometry": {"coordinates":[-78.9633407593,42.8862495422],"type":"Point"}
}