{
  "type": "Feature",
  "properties": {
    "addr:full":"6055 Monterey Rd Prince George BC V2K 4M2",
    "addr:housenumber":"6055",
    "addr:postcode":"v2k 4m2",
    "addr:street":"Monterey Rd",
    "iso:country":"CA",
    "sg:address":"6055 Monterey Rd",
    "sg:city":"Prince George",
    "sg:classifiers":[
        {
            "category":"Retail",
            "subcategory":"Auto Repair",
            "type":"Services"
        }
    ],
    "sg:phone":"+1 250 962 2377",
    "sg:postcode":"V2K 4M2",
    "sg:province":"BC",
    "sg:tags":[
        "repairing",
        "automobile"
    ],
    "wof:name":"Lucien's Auto Svc Ltd",
    "wof:placetype":"venue"
},
  "geometry": {"coordinates":[-122.771644592,53.9790687561],"type":"Point"}
}