{
  "type": "Feature",
  "properties": {
    "addr:full":"69 Pickett Cres Richmond Hill ON L4C 9L9",
    "addr:housenumber":"69",
    "addr:postcode":"l4c 9l9",
    "addr:street":"Pickett Cres",
    "iso:country":"CA",
    "sg:address":"69 Pickett Cres",
    "sg:city":"Richmond Hill",
    "sg:classifiers":[
        {
            "category":"Building & Trades",
            "subcategory":"Construction",
            "type":"Services"
        }
    ],
    "sg:phone":"+1 905 770 5711",
    "sg:postcode":"L4C 9L9",
    "sg:province":"ON",
    "sg:tags":[
        "contractor"
    ],
    "wof:name":"Di Davide General Contracting",
    "wof:placetype":"venue"
},
  "geometry": {"coordinates":[-79.4491271973,43.8909683228],"type":"Point"}
}