{
  "type": "Feature",
  "properties": {
    "addr:full":"PO Box 329 Ile Des Chenes MB R0A 0T0",
    "addr:housenumber":"po",
    "addr:postcode":"r0a 0t0",
    "addr:street":"Box 329 Ile Des Chenes",
    "iso:country":"CA",
    "sg:address":"PO Box 329",
    "sg:city":"Ile Des Chenes",
    "sg:classifiers":[
        {
            "category":"Building & Trades",
            "subcategory":"Equipment Rental",
            "type":"Services"
        }
    ],
    "sg:phone":"+1 204 878 9279",
    "sg:postcode":"R0A 0T0",
    "sg:province":"MB",
    "sg:tags":[
        "yard"
    ],
    "wof:name":"Ags Rentals",
    "wof:placetype":"venue"
},
  "geometry": {"coordinates":[-96.9940109253,49.7110710144],"type":"Point"}
}