{
  "type": "Feature",
  "properties": {
    "addr:full":"6720 Meadowvale Town Centre Ci Mississauga ON L5N 4B7",
    "addr:housenumber":"6720",
    "addr:postcode":"l5n 4b7",
    "addr:street":"Meadowvale Town Centre Ci",
    "iso:country":"CA",
    "sg:address":"6720 Meadowvale Town Centre Ci",
    "sg:city":"Mississauga",
    "sg:classifiers":[
        {
            "category":"Food & Beverages",
            "subcategory":"Groceries & Convenience Stores",
            "type":"Retail Goods"
        }
    ],
    "sg:phone":"+1 905 826 4710",
    "sg:postcode":"L5N 4B7",
    "sg:province":"ON",
    "sg:tags":[
        "grocer"
    ],
    "wof:name":"Rabba Fine Foods",
    "wof:placetype":"venue"
},
  "geometry": {"coordinates":[-79.7615356445,43.5825004578],"type":"Point"}
}