{
  "type": "Feature",
  "properties": {
    "addr:full":"RR 1 Moorefield ON N0G 2K0",
    "addr:postcode":"n0g 2k0",
    "addr:street":"Rr 1 Moorefield",
    "iso:country":"CA",
    "sg:address":"RR 1",
    "sg:city":"Moorefield",
    "sg:classifiers":[
        {
            "category":"Building & Trades",
            "subcategory":"Plumbing",
            "type":"Services"
        }
    ],
    "sg:phone":"+1 519 638 5053",
    "sg:postcode":"N0G 2K0",
    "sg:province":"ON",
    "sg:tags":[
        "contractor"
    ],
    "wof:name":"Dray N' Way Plumbing",
    "wof:placetype":"venue"
},
  "geometry": {"coordinates":[-80.7473068237,43.7595252991],"type":"Point"}
}