{
  "type": "Feature",
  "properties": {
    "addr:full":"Brampton ON L6W 3P1",
    "addr:postcode":"l6w 3p1",
    "iso:country":"CA",
    "sg:city":"Brampton",
    "sg:classifiers":[
        {
            "category":"Professional",
            "subcategory":"Accounting & Tax Preparation",
            "type":"Services"
        }
    ],
    "sg:phone":"+1 905 459 5616",
    "sg:postcode":"L6W 3P1",
    "sg:province":"ON",
    "sg:tags":[
        "accountant"
    ],
    "wof:name":"Carson, Andrew I CA",
    "wof:placetype":"venue"
},
  "geometry": {"coordinates":[-79.759247,43.686325],"type":"Point"}
}