{
  "type": "Feature",
  "properties": {
    "iso:country":"CA",
    "sg:address":"1956 River Rd",
    "sg:city":"London",
    "sg:classifiers":[
        {
            "category":"Autos & Motor Vehicles",
            "subcategory":"Automobile Sales",
            "type":"Retail Goods"
        }
    ],
    "sg:phone":"+1 519 659 6532",
    "sg:postcode":"N5W 6C2",
    "sg:province":"ON",
    "sg:tags":[
        "car",
        "dealer"
    ],
    "wof:name":"Jfj Auto Sales",
    "wof:placetype":"venue"
},
  "geometry": {"coordinates":[-81.1540756226,42.9812812805],"type":"Point"}
}