{
  "type": "Feature",
  "properties": {
    "addr:full":"107 High St Southampton ON N0H 2L0",
    "addr:housenumber":"107",
    "addr:postcode":"n0h 2l0",
    "addr:street":"High St",
    "iso:country":"CA",
    "sg:address":"107 High St",
    "sg:city":"Southampton",
    "sg:classifiers":[
        {
            "category":"Travel",
            "subcategory":"Hotels & Motels",
            "type":"Entertainment"
        }
    ],
    "sg:phone":"+1 519 797 1818",
    "sg:postcode":"N0H 2L0",
    "sg:province":"ON",
    "sg:tags":[
        "breakfast",
        "accommodation",
        "bed"
    ],
    "wof:name":"Chantry Breezes Bed & Breakfst",
    "wof:placetype":"venue"
},
  "geometry": {"coordinates":[-81.374672,44.496712],"type":"Point"}
}