{
  "type": "Feature",
  "properties": {
    "addr:full":"10106 138 St NW Edmonton AB T5N 2H7",
    "addr:housenumber":"10106",
    "addr:postcode":"t5n 2h7",
    "addr:street":"138 St Nw",
    "iso:country":"CA",
    "sg:address":"10106 138 St NW",
    "sg:city":"Edmonton",
    "sg:classifiers":[
        {
            "category":"Building & Trades",
            "subcategory":"Landscaping Services",
            "type":"Services"
        }
    ],
    "sg:phone":"+1 780 455 1510",
    "sg:postcode":"T5N 2H7",
    "sg:province":"AB",
    "sg:tags":[
        "landscape",
        "contractor"
    ],
    "wof:name":"Konrad's Green Spot Enterprise",
    "wof:placetype":"venue"
},
  "geometry": {"coordinates":[-113.560653687,53.5419464111],"type":"Point"}
}