{
  "type": "Feature",
  "properties": {
    "addr:full":"665 Barton St E Hamilton ON L8L 3A3",
    "addr:housenumber":"665",
    "addr:postcode":"l8l 3a3",
    "addr:street":"Barton St E",
    "iso:country":"CA",
    "sg:address":"665 Barton St E",
    "sg:city":"Hamilton",
    "sg:classifiers":[
        {
            "category":"Organizations",
            "subcategory":"Professional Association",
            "type":"Services"
        }
    ],
    "sg:phone":"+1 905 544 3847",
    "sg:postcode":"L8L 3A3",
    "sg:province":"ON",
    "sg:tags":[
        "club"
    ],
    "wof:name":"Terminal Social Club",
    "wof:placetype":"venue"
},
  "geometry": {"coordinates":[-79.83663199999999,43.256744],"type":"Point"}
}