{
  "type": "Feature",
  "properties": {
    "addr:full":"4095 Rue Tupper Westmount QC H3Z 3E5",
    "addr:housenumber":"4095",
    "addr:postcode":"h3z 3e5",
    "addr:street":"Rue Tupper",
    "iso:country":"CA",
    "sg:address":"4095 Rue Tupper",
    "sg:city":"Westmount",
    "sg:classifiers":[
        {
            "category":"Health Services",
            "subcategory":"Doctor",
            "type":"Services"
        }
    ],
    "sg:phone":"+1 514 935 6020",
    "sg:postcode":"H3Z 3E5",
    "sg:province":"QC",
    "sg:tags":[
        "ophthalmologist"
    ],
    "wof:name":"Leith, Arthur B",
    "wof:placetype":"venue"
},
  "geometry": {"coordinates":[-73.5850906372,45.4879722595],"type":"Point"}
}