{
  "type": "Feature",
  "properties": {
    "addr:full":"2653 Elmhurst St Ottawa ON K2B 7N7",
    "addr:housenumber":"2653",
    "addr:postcode":"k2b 7n7",
    "addr:street":"Elmhurst St",
    "iso:country":"CA",
    "sg:address":"2653 Elmhurst St",
    "sg:city":"Ottawa",
    "sg:classifiers":[
        {
            "category":"Education",
            "subcategory":"Special Training",
            "type":"Public Place"
        }
    ],
    "sg:phone":"+1 613 721 9200",
    "sg:postcode":"K2B 7N7",
    "sg:province":"ON",
    "sg:tags":[
        "management"
    ],
    "wof:name":"Collaborative Work Group",
    "wof:placetype":"venue"
},
  "geometry": {"coordinates":[-75.789581,45.359509],"type":"Point"}
}