{
  "type": "Feature",
  "properties": {
    "iso:country":"CA",
    "sg:city":"North York",
    "sg:classifiers":[
        {
            "category":"Wholesale",
            "subcategory":"Toys & Hobbies",
            "type":"Manufacturing & Wholesale Goods"
        }
    ],
    "sg:phone":"+1 416 744 3643",
    "sg:postcode":"M9L 1V8",
    "sg:province":"ON",
    "wof:name":"Boley Toys Corp",
    "wof:placetype":"venue"
},
  "geometry": {"coordinates":[-79.5436248779,43.7575759888],"type":"Point"}
}