{
  "type": "Feature",
  "properties": {
    "addr:full":"4260 Government St Hazelton BC V0J 1Y0",
    "addr:housenumber":"4260",
    "addr:postcode":"v0j 1y0",
    "addr:street":"Government St",
    "iso:country":"CA",
    "sg:address":"4260 Government St",
    "sg:city":"Hazelton",
    "sg:classifiers":[
        {
            "category":"Government",
            "subcategory":"Office",
            "type":"Public Place"
        }
    ],
    "sg:phone":"+1 250 842 5275",
    "sg:postcode":"V0J 1Y0",
    "sg:province":"BC",
    "wof:name":"BC Health Unit",
    "wof:placetype":"venue"
},
  "geometry": {"coordinates":[-127.643867,55.264259],"type":"Point"}
}