{
  "type": "Feature",
  "properties": {
    "addr:full":"7609 Rue Saint-Hubert Montreal QC H2R 2N7",
    "addr:housenumber":"7609",
    "addr:postcode":"h2r 2n7",
    "addr:street":"Rue Saint-Hubert",
    "iso:country":"CA",
    "sg:address":"7609 Rue Saint-Hubert",
    "sg:city":"Montreal",
    "sg:classifiers":[
        {
            "category":"Home & Garden",
            "subcategory":"Household Appliances",
            "type":"Retail Goods"
        }
    ],
    "sg:phone":"+1 514 271 2888",
    "sg:postcode":"H2R 2N7",
    "sg:province":"QC",
    "sg:tags":[
        "machine",
        "sewing"
    ],
    "wof:name":"Kava Machine A Coudre Inc",
    "wof:placetype":"venue"
},
  "geometry": {"coordinates":[-73.619468689,45.5437507629],"type":"Point"}
}