{
  "type": "Feature",
  "properties": {
    "addr:full":"8310 Manitoba St Vancouver BC V5X 3A5",
    "addr:housenumber":"8310",
    "addr:postcode":"v5x 3a5",
    "addr:street":"Manitoba St",
    "iso:country":"CA",
    "sg:address":"8310 Manitoba St",
    "sg:city":"Vancouver",
    "sg:classifiers":[
        {
            "category":"Wholesale",
            "subcategory":"Plants",
            "type":"Manufacturing & Wholesale Goods"
        }
    ],
    "sg:phone":"+1 604 321 6776",
    "sg:postcode":"V5X 3A5",
    "sg:province":"BC",
    "sg:tags":[
        "florist"
    ],
    "wof:name":"Ratana Trading CO Ltd",
    "wof:placetype":"venue"
},
  "geometry": {"coordinates":[-123.109917,49.209351],"type":"Point"}
}