{
  "type": "Feature",
  "properties": {
    "addr:full":"1027 6th St E Saskatoon SK S7H 1E1",
    "addr:housenumber":"1027",
    "addr:postcode":"s7h 1e1",
    "addr:street":"6Th St E",
    "iso:country":"CA",
    "sg:address":"1027 6th St E",
    "sg:city":"Saskatoon",
    "sg:classifiers":[
        {
            "category":"Shopping",
            "type":"Retail Goods"
        }
    ],
    "sg:phone":"+1 306 665 8827",
    "sg:postcode":"S7H 1E1",
    "sg:province":"SK",
    "sg:tags":[
        "spa",
        "hot",
        "tub"
    ],
    "wof:name":"Happy Hot Tubs",
    "wof:placetype":"venue"
},
  "geometry": {"coordinates":[-106.64570617699999,52.1130218506],"type":"Point"}
}