{
  "type": "Feature",
  "properties": {
    "addr:full":"1410 17 Ave SW Calgary AB T2T 0C3",
    "addr:housenumber":"1410",
    "addr:postcode":"t2t 0c3",
    "addr:street":"17 Ave Sw",
    "iso:country":"CA",
    "sg:address":"1410 17 Ave SW",
    "sg:city":"Calgary",
    "sg:classifiers":[
        {
            "category":"Restaurant",
            "type":"Food & Drink"
        }
    ],
    "sg:phone":"+1 403 244 4811",
    "sg:postcode":"T2T 0C3",
    "sg:province":"AB",
    "wof:name":"Homestead Restaurant & Pizza",
    "wof:placetype":"venue"
},
  "geometry": {"coordinates":[-114.09431499999999,51.037941],"type":"Point"}
}