{
  "type": "Feature",
  "properties": {
    "addr:full":"2629 Riverside Dr W Windsor ON N9B 1B4",
    "addr:housenumber":"2629",
    "addr:postcode":"n9b 1b4",
    "addr:street":"Riverside Dr W",
    "iso:country":"CA",
    "sg:address":"2629 Riverside Dr W",
    "sg:city":"Windsor",
    "sg:classifiers":[
        {
            "category":"Health Services",
            "subcategory":"Health Practitioner",
            "type":"Services"
        }
    ],
    "sg:phone":"+1 519 255 7999",
    "sg:postcode":"N9B 1B4",
    "sg:province":"ON",
    "sg:tags":[
        "psychologist"
    ],
    "wof:name":"Rourke, Byron P",
    "wof:placetype":"venue"
},
  "geometry": {"coordinates":[-83.069771,42.309895],"type":"Point"}
}