{
  "type": "Feature",
  "properties": {
    "iso:country":"CA",
    "sg:address":"501 Broadway Ave",
    "sg:city":"Killarney",
    "sg:classifiers":[
        {
            "category":"Professional",
            "subcategory":"Accounting & Tax Preparation",
            "type":"Services"
        }
    ],
    "sg:phone":"+1 204 523 4633",
    "sg:postcode":"R0K 1G0",
    "sg:province":"MB",
    "sg:tags":[
        "accountant"
    ],
    "wof:name":"Meyers Norris Penny",
    "wof:placetype":"venue"
},
  "geometry": {"coordinates":[-99.6643295288,49.1834602356],"type":"Point"}
}