{
  "type": "Feature",
  "properties": {
    "addr:full":"207 LA Ronge Ave LA Ronge SK S0J 1L0",
    "addr:housenumber":"207",
    "addr:postcode":"s0j 1l0",
    "addr:street":"La Ronge Ave",
    "iso:country":"CA",
    "sg:address":"207 LA Ronge Ave",
    "sg:city":"LA Ronge",
    "sg:classifiers":[
        {
            "category":"Organizations",
            "subcategory":"Non-profit Organization",
            "type":"Services"
        }
    ],
    "sg:phone":"+1 306 425 5505",
    "sg:postcode":"S0J 1L0",
    "sg:province":"SK",
    "sg:tags":[
        "charitable",
        "institution"
    ],
    "wof:name":"New North Sanc Svc Inc",
    "wof:placetype":"venue"
},
  "geometry": {"coordinates":[-105.295326,55.112495],"type":"Point"}
}