{
  "type": "Feature",
  "properties": {
    "addr:full":"18 Cambridge St N Lindsay ON K9V 4C3",
    "addr:housenumber":"18",
    "addr:postcode":"k9v 4c3",
    "addr:street":"Cambridge St N",
    "iso:country":"CA",
    "sg:address":"18 Cambridge St N",
    "sg:city":"Lindsay",
    "sg:classifiers":[
        {
            "category":"Professional",
            "subcategory":"Lawyer & Legal Services",
            "type":"Services"
        }
    ],
    "sg:phone":"+1 705 878 8864",
    "sg:postcode":"K9V 4C3",
    "sg:province":"ON",
    "sg:tags":[
        "attorney"
    ],
    "wof:name":"Jamieson, Carol E",
    "wof:placetype":"venue"
},
  "geometry": {"coordinates":[-78.73949399999999,44.355286],"type":"Point"}
}