{
  "type": "Feature",
  "properties": {
    "addr:full":"Haliburton ON K0M 1S0",
    "addr:postcode":"k0m 1s0",
    "iso:country":"CA",
    "sg:city":"Haliburton",
    "sg:classifiers":[
        {
            "category":"Home & Garden",
            "subcategory":"Building Materials",
            "type":"Retail Goods"
        }
    ],
    "sg:phone":"+1 705 457 1395",
    "sg:postcode":"K0M 1S0",
    "sg:province":"ON",
    "sg:tags":[
        "concrete",
        "product"
    ],
    "wof:name":"Brooklin Concrete Products Ltd",
    "wof:placetype":"venue"
},
  "geometry": {"coordinates":[-78.550186,45.043522],"type":"Point"}
}