{
  "type": "Feature",
  "properties": {
    "addr:full":"Labelle QC J0T 1H0",
    "addr:postcode":"j0t 1h0",
    "iso:country":"CA",
    "sg:city":"Labelle",
    "sg:classifiers":[
        {
            "category":"Shopping",
            "subcategory":"Florist",
            "type":"Retail Goods"
        }
    ],
    "sg:phone":"+1 819 686 5858",
    "sg:postcode":"J0T 1H0",
    "sg:province":"QC",
    "wof:name":"Fleuriste Andre",
    "wof:placetype":"venue"
},
  "geometry": {"coordinates":[-74.7327804565,46.2790641785],"type":"Point"}
}