{
  "type": "Feature",
  "properties": {
    "iso:country":"CA",
    "sg:city":"New Westminster",
    "sg:classifiers":[
        {
            "category":"Manufacturing",
            "subcategory":"Building Materials",
            "type":"Manufacturing & Wholesale Goods"
        }
    ],
    "sg:phone":"+1 604 522 7745",
    "sg:postcode":"V3L 5M3",
    "sg:province":"BC",
    "wof:name":"Turn of the Century Furniture",
    "wof:placetype":"venue"
},
  "geometry": {"coordinates":[-122.884788513,49.2250022888],"type":"Point"}
}