{
  "type": "Feature",
  "properties": {
    "addr:full":"5773 Victoria Dr Vancouver BC V5P 3W5",
    "addr:housenumber":"5773",
    "addr:postcode":"v5p 3w5",
    "addr:street":"Victoria Dr",
    "iso:country":"CA",
    "sg:address":"5773 Victoria Dr",
    "sg:city":"Vancouver",
    "sg:classifiers":[
        {
            "category":"Personal",
            "subcategory":"Beauty Salon",
            "type":"Services"
        }
    ],
    "sg:phone":"+1 604 321 0613",
    "sg:postcode":"V5P 3W5",
    "sg:province":"BC",
    "wof:name":"Hairway",
    "wof:placetype":"venue"
},
  "geometry": {"coordinates":[-123.06574999999999,49.231915],"type":"Point"}
}