{
  "type": "Feature",
  "properties": {
    "addr:full":"1600 Cook St Victoria BC V8T 3P1",
    "addr:housenumber":"1600",
    "addr:postcode":"v8t 3p1",
    "addr:street":"Cook St",
    "iso:country":"CA",
    "sg:address":"1600 Cook St",
    "sg:city":"Victoria",
    "sg:classifiers":[
        {
            "category":"Organizations",
            "subcategory":"Religious Organization",
            "type":"Services"
        }
    ],
    "sg:phone":"+1 250 383 2293",
    "sg:postcode":"V8T 3P1",
    "sg:province":"BC",
    "sg:tags":[
        "church"
    ],
    "wof:name":"Open Door Spiritualist Church",
    "wof:placetype":"venue"
},
  "geometry": {"coordinates":[-123.353149,48.428169],"type":"Point"}
}