{
  "type": "Feature",
  "properties": {
    "iso:country":"CA",
    "sg:address":"12152 Hwy 8",
    "sg:city":"Caledonia",
    "sg:classifiers":[
        {
            "category":"Travel",
            "subcategory":"Travel Agent",
            "type":"Entertainment"
        }
    ],
    "sg:phone":"+1 902 682 2116",
    "sg:postcode":"B0T 1B0",
    "sg:province":"NS",
    "sg:tags":[
        "information",
        "tourist"
    ],
    "wof:name":"Canadvac Travel Svc Ltd",
    "wof:placetype":"venue"
},
  "geometry": {"coordinates":[-65.0206985474,44.3780097961],"type":"Point"}
}