{
  "type": "Feature",
  "properties": {
    "addr:full":"Toronto ON M5R 2A7",
    "addr:postcode":"m5r 2a7",
    "iso:country":"CA",
    "sg:city":"Toronto",
    "sg:classifiers":[
        {
            "category":"Professional",
            "subcategory":"Accounting & Tax Preparation",
            "type":"Services"
        }
    ],
    "sg:phone":"+1 416 966 5922",
    "sg:postcode":"M5R 2A7",
    "sg:province":"ON",
    "sg:tags":[
        "accountant",
        "return",
        "filing"
    ],
    "wof:name":"Ron Chu & Assoc",
    "wof:placetype":"venue"
},
  "geometry": {"coordinates":[-79.389893,43.670403],"type":"Point"}
}