{
  "type": "Feature",
  "properties": {
    "iso:country":"CA",
    "sg:address":"1997 Mckeown Ave",
    "sg:city":"North Bay",
    "sg:classifiers":[
        {
            "category":"Personal",
            "subcategory":"Beauty Salon",
            "type":"Services"
        }
    ],
    "sg:phone":"+1 705 495 8917",
    "sg:postcode":"P1B 7N7",
    "sg:province":"ON",
    "sg:tags":[
        "manicuring"
    ],
    "wof:name":"Trillium Nails & Esthetics",
    "wof:placetype":"venue"
},
  "geometry": {"coordinates":[-79.45035552980001,46.3328018188],"type":"Point"}
}