{
  "type": "Feature",
  "properties": {
    "iso:country":"CA",
    "sg:city":"Winnipeg",
    "sg:classifiers":[
        {
            "category":"Government",
            "subcategory":"Office",
            "type":"Public Place"
        }
    ],
    "sg:phone":"+1 204 945 1301",
    "sg:postcode":"R3N 2B2",
    "sg:province":"MB",
    "wof:name":"Manitoba Health Office",
    "wof:placetype":"venue"
},
  "geometry": {"coordinates":[-97.210541,49.869949],"type":"Point"}
}