{
  "type": "Feature",
  "properties": {
    "addr:full":"Winnipeg MB R3N 2B2",
    "addr:postcode":"r3n 2b2",
    "iso:country":"CA",
    "sg:city":"Winnipeg",
    "sg:classifiers":[
        {
            "category":"Government",
            "subcategory":"Office",
            "type":"Public Place"
        }
    ],
    "sg:phone":"+1 204 945 1301",
    "sg:postcode":"R3N 2B2",
    "sg:province":"MB",
    "wof:name":"Manitoba Health Office",
    "wof:placetype":"venue"
},
  "geometry": {"coordinates":[-97.21054100000001,49.869949],"type":"Point"}
}