{
  "type": "Feature",
  "properties": {
    "addr:full":"614 Sixth St New Westminster BC V3L 3C3",
    "addr:housenumber":"614",
    "addr:postcode":"v3l 3c3",
    "addr:street":"Sixth St",
    "iso:country":"CA",
    "sg:address":"614 Sixth St",
    "sg:city":"New Westminster",
    "sg:classifiers":[
        {
            "category":"Health Services",
            "subcategory":"Optometrist",
            "type":"Services"
        }
    ],
    "sg:phone":"+1 604 522 1120",
    "sg:postcode":"V3L 3C3",
    "sg:province":"BC",
    "wof:name":"Lifetime Eyecare & Contact Len",
    "wof:placetype":"venue"
},
  "geometry": {"coordinates":[-122.920998,49.213455],"type":"Point"}
}