{
  "type": "Feature",
  "properties": {
    "addr:full":"Villebois QC J0Z 3V0",
    "addr:postcode":"j0z 3v0",
    "addr:street":"Villebois",
    "iso:country":"CA",
    "sg:city":"Villebois",
    "sg:phone":"+1 819 941 2699",
    "sg:postcode":"J0Z 3V0",
    "sg:province":"QC",
    "sg:tags":[
        "strainer"
    ],
    "wof:name":"Proulx & Genesse Inc",
    "wof:placetype":"venue"
},
  "geometry": {"coordinates":[-79.1467208862,49.0965843201],"type":"Point"}
}