{
  "type": "Feature",
  "properties": {
    "iso:country":"CA",
    "sg:address":"5911 56 Ave NW",
    "sg:city":"Edmonton",
    "sg:classifiers":[
        {
            "category":"Manufacturing",
            "subcategory":"Tools & Machinery",
            "type":"Manufacturing & Wholesale Goods"
        }
    ],
    "sg:phone":"+1 780 490 0939",
    "sg:postcode":"T6B 3E2",
    "sg:province":"AB",
    "sg:tags":[
        "field",
        "oil",
        "equipment"
    ],
    "wof:name":"Lri Oil Tools Inc",
    "wof:placetype":"venue"
},
  "geometry": {"coordinates":[-113.42375946,53.492225647],"type":"Point"}
}