{
  "type": "Feature",
  "properties": {
    "addr:full":"3295 Rankin Ave Windsor ON N9E 3C2",
    "addr:housenumber":"3295",
    "addr:postcode":"n9e 3c2",
    "addr:street":"Rankin Ave",
    "iso:country":"CA",
    "sg:address":"3295 Rankin Ave",
    "sg:city":"Windsor",
    "sg:classifiers":[
        {
            "category":"Professional",
            "subcategory":"Business Services",
            "type":"Services"
        }
    ],
    "sg:phone":"+1 519 969 8768",
    "sg:postcode":"N9E 3C2",
    "sg:province":"ON",
    "sg:tags":[
        "process",
        "server"
    ],
    "wof:name":"Dependable Process Svc",
    "wof:placetype":"venue"
},
  "geometry": {"coordinates":[-83.030289,42.260281],"type":"Point"}
}