{
  "type": "Feature",
  "properties": {
    "addr:full":"2371 Marshall Ave Port Coquitlam BC V3C 1M4",
    "addr:housenumber":"2371",
    "addr:postcode":"v3c 1m4",
    "addr:street":"Marshall Ave",
    "iso:country":"CA",
    "sg:address":"2371 Marshall Ave",
    "sg:city":"Port Coquitlam",
    "sg:classifiers":[
        {
            "category":"Manufacturing",
            "subcategory":"Tools & Machinery",
            "type":"Manufacturing & Wholesale Goods"
        }
    ],
    "sg:phone":"+1 604 942 3039",
    "sg:postcode":"V3C 1M4",
    "sg:province":"BC",
    "sg:tags":[
        "equipment",
        "labeling"
    ],
    "wof:name":"Resolution Technologies",
    "wof:placetype":"venue"
},
  "geometry": {"coordinates":[-122.783501,49.252636],"type":"Point"}
}