{
  "type": "Feature",
  "properties": {
    "iso:country":"CA",
    "sg:address":"287 Glidden Rd",
    "sg:city":"Brampton",
    "sg:classifiers":[
        {
            "category":"Manufacturing",
            "subcategory":"Food",
            "type":"Manufacturing & Wholesale Goods"
        }
    ],
    "sg:phone":"+1 905 453 6888",
    "sg:postcode":"L6W 1H9",
    "sg:province":"ON",
    "sg:tags":[
        "grocer",
        "cookie",
        "bakery"
    ],
    "wof:name":"Apar Bakery Inc",
    "wof:placetype":"venue"
},
  "geometry": {"coordinates":[-79.73017120359999,43.6829986572],"type":"Point"}
}