{
  "type": "Feature",
  "properties": {
    "iso:country":"CA",
    "sg:address":"65 Sky Acres Dr",
    "sg:city":"Brantford",
    "sg:classifiers":[
        {
            "category":"Education",
            "subcategory":"School",
            "type":"Public Place"
        }
    ],
    "sg:phone":"+1 519 756 5751",
    "sg:postcode":"N3R 5W6",
    "sg:province":"ON",
    "wof:name":"St Bernard School",
    "wof:placetype":"venue"
},
  "geometry": {"coordinates":[-80.28647613530001,43.1626319885],"type":"Point"}
}