{
  "type": "Feature",
  "properties": {
    "addr:full":"Saskatoon SK S7K 1L9",
    "addr:postcode":"s7k 1l9",
    "iso:country":"CA",
    "sg:city":"Saskatoon",
    "sg:classifiers":[
        {
            "category":"Shopping",
            "type":"Retail Goods"
        }
    ],
    "sg:phone":"+1 306 665 0626",
    "sg:postcode":"S7K 1L9",
    "sg:province":"SK",
    "sg:tags":[
        "coin",
        "dealer",
        "supply"
    ],
    "wof:name":"Sceptre Coin & Stamp",
    "wof:placetype":"venue"
},
  "geometry": {"coordinates":[-106.662758,52.126564],"type":"Point"}
}