{
  "type": "Feature",
  "properties": {
    "iso:country":"CA",
    "sg:address":"223 Rebecca St",
    "sg:city":"Oakville",
    "sg:classifiers":[
        {
            "category":"Professional",
            "subcategory":"Management & Consulting",
            "type":"Services"
        }
    ],
    "sg:phone":"+1 905 339 2010",
    "sg:postcode":"L6K 1J8",
    "sg:province":"ON",
    "sg:tags":[
        "consultant",
        "business"
    ],
    "wof:name":"Process Improvement Institute",
    "wof:placetype":"venue"
},
  "geometry": {"coordinates":[-79.68068695069999,43.4372253418],"type":"Point"}
}