{
  "type": "Feature",
  "properties": {
    "addr:full":"St George Brant ON N0E 1N0",
    "addr:postcode":"n0e 1n0",
    "addr:street":"St",
    "iso:country":"CA",
    "sg:city":"St George Brant",
    "sg:classifiers":[
        {
            "category":"Manufacturing",
            "subcategory":"Tools & Machinery",
            "type":"Manufacturing & Wholesale Goods"
        }
    ],
    "sg:phone":"+1 519 448 1622",
    "sg:postcode":"N0E 1N0",
    "sg:province":"ON",
    "sg:tags":[
        "machine",
        "shop"
    ],
    "wof:name":"Brant Custom Machining Ltd",
    "wof:placetype":"venue"
},
  "geometry": {"coordinates":[-80.249596,43.246796],"type":"Point"}
}