{
  "type": "Feature",
  "properties": {
    "iso:country":"CA",
    "sg:address":"1905 Rue Notre-Dame",
    "sg:city":"L'Ancienne-Lorette",
    "sg:classifiers":[
        {
            "category":"Shopping",
            "subcategory":"Computers & Home Electronics",
            "type":"Retail Goods"
        }
    ],
    "sg:phone":"+1 418 877 4281",
    "sg:postcode":"G2E 3E1",
    "sg:province":"QC",
    "sg:tags":[
        "equipment",
        "video"
    ],
    "wof:name":"Club International Video Film",
    "wof:placetype":"venue"
},
  "geometry": {"coordinates":[-71.3693161011,46.8103256226],"type":"Point"}
}