{
  "type": "Feature",
  "properties": {
    "addr:full":"2136 Queen St E Toronto ON M4E 1E3",
    "addr:housenumber":"2136",
    "addr:postcode":"m4e 1e3",
    "addr:street":"Queen St E",
    "iso:country":"CA",
    "sg:address":"2136 Queen St E",
    "sg:city":"Toronto",
    "sg:classifiers":[
        {
            "category":"Shopping",
            "subcategory":"Optical Goods",
            "type":"Retail Goods"
        }
    ],
    "sg:phone":"+1 416 698 3937",
    "sg:postcode":"M4E 1E3",
    "sg:province":"ON",
    "sg:tags":[
        "optician"
    ],
    "wof:name":"Crystal Beach Optical",
    "wof:placetype":"venue"
},
  "geometry": {"coordinates":[-79.293694,43.671474],"type":"Point"}
}