{
  "type": "Feature",
  "properties": {
    "addr:full":"300 Sackville Dr Lower Sackville NS B4C 2R6",
    "addr:housenumber":"300",
    "addr:postcode":"b4c 2r6",
    "addr:street":"Sackville Dr",
    "iso:country":"CA",
    "sg:address":"300 Sackville Dr",
    "sg:city":"Lower Sackville",
    "sg:classifiers":[
        {
            "category":"Recreation",
            "type":"Entertainment"
        }
    ],
    "sg:phone":"+1 902 864 2910",
    "sg:postcode":"B4C 2R6",
    "sg:province":"NS",
    "sg:tags":[
        "parlor",
        "billiard"
    ],
    "wof:name":"Super Cue Billiards",
    "wof:placetype":"venue"
},
  "geometry": {"coordinates":[-63.672737,44.760906],"type":"Point"}
}