{
  "type": "Feature",
  "properties": {
    "iso:country":"CA",
    "sg:address":"1100 Rue Prospect",
    "sg:city":"Sherbrooke",
    "sg:classifiers":[
        {
            "category":"Real Estate",
            "subcategory":"Architect",
            "type":"Services"
        }
    ],
    "sg:phone":"+1 819 823 2078",
    "sg:postcode":"J1H 1B4",
    "sg:province":"QC",
    "wof:name":"Gautier, Raymond",
    "wof:placetype":"venue"
},
  "geometry": {"coordinates":[-71.9047088623,45.4089241028],"type":"Point"}
}