{
  "type": "Feature",
  "properties": {
    "iso:country":"CA",
    "sg:address":"520 Simcoe St S",
    "sg:city":"Oshawa",
    "sg:classifiers":[
        {
            "category":"Personal",
            "subcategory":"Beauty Salon",
            "type":"Services"
        }
    ],
    "sg:phone":"+1 905 725 0119",
    "sg:postcode":"L1H 4J8",
    "sg:province":"ON",
    "wof:name":"Playtime Hairtime",
    "wof:placetype":"venue"
},
  "geometry": {"coordinates":[-78.857498,43.88401],"type":"Point"}
}