{
  "type": "Feature",
  "properties": {
    "addr:full":"PO Box 206 Delburne AB T0M 0V0",
    "addr:housenumber":"po",
    "addr:postcode":"t0m 0v0",
    "addr:street":"Box 206",
    "iso:country":"CA",
    "sg:address":"PO Box 206",
    "sg:city":"Delburne",
    "sg:classifiers":[
        {
            "category":"Professional",
            "type":"Services"
        }
    ],
    "sg:phone":"+1 403 749 2375",
    "sg:postcode":"T0M 0V0",
    "sg:province":"AB",
    "sg:tags":[
        "geophysical"
    ],
    "wof:name":"Jackson Environmental Seismic",
    "wof:placetype":"venue"
},
  "geometry": {"coordinates":[-113.243042,52.195656],"type":"Point"}
}