{
  "type": "Feature",
  "properties": {
    "addr:full":"2285 Boul DE LA Rive-Sud Saint-Romuald QC G6W 2S2",
    "addr:housenumber":"2285",
    "addr:postcode":"g6w 2s2",
    "addr:street":"Boul De La Rive-Sud",
    "iso:country":"CA",
    "sg:address":"2285 Boul DE LA Rive-Sud",
    "sg:city":"Saint-Romuald",
    "sg:classifiers":[
        {
            "category":"Professional",
            "subcategory":"Computer Services",
            "type":"Services"
        }
    ],
    "sg:phone":"+1 418 839 0330",
    "sg:postcode":"G6W 2S2",
    "sg:province":"QC",
    "sg:tags":[
        "information",
        "system",
        "consultant"
    ],
    "wof:name":"Consultants Dda Ltee",
    "wof:placetype":"venue"
},
  "geometry": {"coordinates":[-71.2320327759,46.7558174133],"type":"Point"}
}