{
  "type": "Feature",
  "properties": {
    "addr:full":"286 Stephen St London ON N6K 2N1",
    "addr:housenumber":"286",
    "addr:postcode":"n6k 2n1",
    "addr:street":"Stephen St",
    "iso:country":"CA",
    "sg:address":"286 Stephen St",
    "sg:city":"London",
    "sg:classifiers":[
        {
            "category":"Organizations",
            "subcategory":"Religious Organization",
            "type":"Services"
        }
    ],
    "sg:phone":"+1 519 657 8779",
    "sg:postcode":"N6K 2N1",
    "sg:province":"ON",
    "sg:tags":[
        "church"
    ],
    "wof:name":"Forest City Flshp Brethren Ch",
    "wof:placetype":"venue"
},
  "geometry": {"coordinates":[-81.3383407593,42.959312439],"type":"Point"}
}