{
  "type": "Feature",
  "properties": {
    "addr:full":"290 Main St Picton ON K0K 2T0",
    "addr:housenumber":"290",
    "addr:postcode":"k0k 2t0",
    "addr:street":"Main St",
    "iso:country":"CA",
    "sg:address":"290 Main St",
    "sg:city":"Picton",
    "sg:classifiers":[
        {
            "category":"Professional",
            "subcategory":"Accounting & Tax Preparation",
            "type":"Services"
        }
    ],
    "sg:phone":"+1 613 476 3283",
    "sg:postcode":"K0K 2T0",
    "sg:province":"ON",
    "sg:tags":[
        "accountant"
    ],
    "wof:name":"Welch & CO",
    "wof:placetype":"venue"
},
  "geometry": {"coordinates":[-77.13967100000001,44.008286],"type":"Point"}
}