{
  "type": "Feature",
  "properties": {
    "addr:full":"130 Great Lakes Dr Brampton ON L6R 2K7",
    "addr:housenumber":"130",
    "addr:postcode":"l6r 2k7",
    "addr:street":"Great Lakes Dr",
    "iso:country":"CA",
    "sg:address":"130 Great Lakes Dr",
    "sg:city":"Brampton",
    "sg:classifiers":[
        {
            "category":"Restaurant",
            "type":"Food & Drink"
        }
    ],
    "sg:phone":"+1 905 790 0040",
    "sg:postcode":"L6R 2K7",
    "sg:province":"ON",
    "wof:name":"East Side Mario's",
    "wof:placetype":"venue"
},
  "geometry": {"coordinates":[-79.76350402830001,43.7322311401],"type":"Point"}
}