{
  "type": "Feature",
  "properties": {
    "addr:full":"610 Rue Papineau Sherbrooke QC J1E 1Y4",
    "addr:housenumber":"610",
    "addr:postcode":"j1e 1y4",
    "addr:street":"Rue Papineau",
    "iso:country":"CA",
    "sg:address":"610 Rue Papineau",
    "sg:city":"Sherbrooke",
    "sg:classifiers":[
        {
            "category":"Organizations",
            "subcategory":"Religious Organization",
            "type":"Services"
        }
    ],
    "sg:phone":"+1 819 569 9961",
    "sg:postcode":"J1E 1Y4",
    "sg:province":"QC",
    "sg:tags":[
        "church"
    ],
    "wof:name":"Ste-Famille",
    "wof:placetype":"venue"
},
  "geometry": {"coordinates":[-71.875427,45.410278],"type":"Point"}
}