{
  "type": "Feature",
  "properties": {
    "addr:full":"4028 7 St SE Calgary AB T2G 2Y8",
    "addr:housenumber":"4028 7",
    "addr:postcode":"t2g 2y8",
    "addr:street":"St Se",
    "iso:country":"CA",
    "sg:address":"4028 7 St SE",
    "sg:city":"Calgary",
    "sg:classifiers":[
        {
            "category":"Wholesale",
            "subcategory":"Electrical",
            "type":"Manufacturing & Wholesale Goods"
        }
    ],
    "sg:phone":"+1 403 243 1425",
    "sg:postcode":"T2G 2Y8",
    "sg:province":"AB",
    "sg:tags":[
        "meter"
    ],
    "wof:name":"Accu-Flo Meter Svc Ltd",
    "wof:placetype":"venue"
},
  "geometry": {"coordinates":[-114.045684815,51.018611908],"type":"Point"}
}