{
  "type": "Feature",
  "properties": {
    "addr:full":"222 Spadina Ave Toronto ON M5T 2C2",
    "addr:housenumber":"222",
    "addr:postcode":"m5t 2c2",
    "addr:street":"Spadina Ave",
    "iso:country":"CA",
    "sg:address":"222 Spadina Ave",
    "sg:city":"Toronto",
    "sg:classifiers":[
        {
            "category":"Shopping",
            "subcategory":"Clothing, Apparel, & Fashions",
            "type":"Retail Goods"
        }
    ],
    "sg:phone":"+1 416 593 1830",
    "sg:postcode":"M5T 2C2",
    "sg:province":"ON",
    "sg:tags":[
        "infant"
    ],
    "wof:name":"See See CO",
    "wof:placetype":"venue"
},
  "geometry": {"coordinates":[-79.397575,43.650982],"type":"Point"}
}