{
  "type": "Feature",
  "properties": {
    "addr:full":"1159 Victoria Park Ave Scarborough ON M4B 2K5",
    "addr:housenumber":"1159",
    "addr:postcode":"m4b 2k5",
    "addr:street":"Victoria Park Ave",
    "iso:country":"CA",
    "sg:address":"1159 Victoria Park Ave",
    "sg:city":"Scarborough",
    "sg:classifiers":[
        {
            "category":"Retail",
            "subcategory":"Portrait Studio",
            "type":"Services"
        }
    ],
    "sg:phone":"+1 416 757 9976",
    "sg:postcode":"M4B 2K5",
    "sg:province":"ON",
    "sg:tags":[
        "photographer"
    ],
    "wof:name":"National Daycare Photographers",
    "wof:placetype":"venue"
},
  "geometry": {"coordinates":[-79.2963256836,43.7100791931],"type":"Point"}
}