{
  "type": "Feature",
  "properties": {
    "addr:full":"216 Callowhill Rd Riverview NB E1B 4L4",
    "addr:housenumber":"216",
    "addr:postcode":"e1b 4l4",
    "addr:street":"Callowhill Rd",
    "iso:country":"CA",
    "sg:address":"216 Callowhill Rd",
    "sg:city":"Riverview",
    "sg:classifiers":[
        {
            "category":"Home & Garden",
            "subcategory":"Household Appliances",
            "type":"Retail Goods"
        }
    ],
    "sg:phone":"+1 506 387 4431",
    "sg:postcode":"E1B 4L4",
    "sg:province":"NB",
    "wof:name":"Riverview Appliance Repair",
    "wof:placetype":"venue"
},
  "geometry": {"coordinates":[-64.80518341059999,46.0417480469],"type":"Point"}
}