{
  "type": "Feature",
  "properties": {
    "addr:full":"332 2nd Ave E Hanna AB T0J 1P0",
    "addr:housenumber":"332",
    "addr:postcode":"t0j 1p0",
    "addr:street":"2Nd Ave E",
    "iso:country":"CA",
    "sg:address":"332 2nd Ave E",
    "sg:city":"Hanna",
    "sg:classifiers":[
        {
            "category":"Autos & Motor Vehicles",
            "subcategory":"Fuel & Gas Station",
            "type":"Retail Goods"
        }
    ],
    "sg:phone":"+1 403 854 2800",
    "sg:postcode":"T0J 1P0",
    "sg:province":"AB",
    "sg:tags":[
        "convenience",
        "oil",
        "store"
    ],
    "wof:name":"Bi-Lo Gas & Convenience Store",
    "wof:placetype":"venue"
},
  "geometry": {"coordinates":[-111.920029,51.64476],"type":"Point"}
}