{
  "type": "Feature",
  "properties": {
    "addr:full":"1508 Thomas Argue Rd Carp ON K0A 1L0",
    "addr:housenumber":"1508",
    "addr:postcode":"k0a 1l0",
    "addr:street":"Thomas Argue Rd",
    "iso:country":"CA",
    "sg:address":"1508 Thomas Argue Rd",
    "sg:city":"Carp",
    "sg:classifiers":[
        {
            "category":"Airport",
            "type":"Transportation"
        }
    ],
    "sg:phone":"+1 613 839 5276",
    "sg:postcode":"K0A 1L0",
    "sg:province":"ON",
    "wof:name":"Carp Airport Authority",
    "wof:placetype":"venue"
},
  "geometry": {"coordinates":[-76.03154000000001,45.323555],"type":"Point"}
}