{
  "type": "Feature",
  "properties": {
    "addr:full":"3179 Thunderbird Cres Burnaby BC V5A 3G1",
    "addr:housenumber":"3179",
    "addr:postcode":"v5a 3g1",
    "addr:street":"Thunderbird Cres",
    "iso:country":"CA",
    "sg:address":"3179 Thunderbird Cres",
    "sg:city":"Burnaby",
    "sg:classifiers":[
        {
            "category":"Wholesale",
            "subcategory":"Hardware",
            "type":"Manufacturing & Wholesale Goods"
        }
    ],
    "sg:phone":"+1 604 421 3096",
    "sg:postcode":"V5A 3G1",
    "sg:province":"BC",
    "sg:tags":[
        "fastener"
    ],
    "wof:name":"Denco Warehousing Ltd",
    "wof:placetype":"venue"
},
  "geometry": {"coordinates":[-122.920936584,49.2547111511],"type":"Point"}
}