{
  "type": "Feature",
  "properties": {
    "addr:full":"760 Erin St Winnipeg MB R3G 2W4",
    "addr:housenumber":"760",
    "addr:postcode":"r3g 2w4",
    "addr:street":"Erin St",
    "iso:country":"CA",
    "sg:address":"760 Erin St",
    "sg:city":"Winnipeg",
    "sg:classifiers":[
        {
            "category":"Professional",
            "subcategory":"Testing Lab",
            "type":"Services"
        }
    ],
    "sg:phone":"+1 204 774 8889",
    "sg:postcode":"R3G 2W4",
    "sg:province":"MB",
    "sg:tags":[
        "laboratory",
        "grain"
    ],
    "wof:name":"Tri-Met Instruments Ltd",
    "wof:placetype":"venue"
},
  "geometry": {"coordinates":[-97.185028,49.888699],"type":"Point"}
}