{
  "type": "Feature",
  "properties": {
    "addr:full":"Bowen Island BC V0N 1G0",
    "addr:postcode":"v0n 1g0",
    "iso:country":"CA",
    "sg:city":"Bowen Island",
    "sg:classifiers":[
        {
            "category":"Professional",
            "subcategory":"Management & Consulting",
            "type":"Services"
        }
    ],
    "sg:phone":"+1 604 947 9024",
    "sg:postcode":"V0N 1G0",
    "sg:province":"BC",
    "sg:tags":[
        "consultant",
        "government"
    ],
    "wof:name":"Bowen Island Chamber-Commerce",
    "wof:placetype":"venue"
},
  "geometry": {"coordinates":[-123.337273,49.379539],"type":"Point"}
}