{
  "type": "Feature",
  "properties": {
    "iso:country":"CA",
    "sg:address":"515 Rue Marie-Anne E",
    "sg:city":"Montreal",
    "sg:classifiers":[
        {
            "category":"Retail",
            "subcategory":"Repair Shop",
            "type":"Services"
        }
    ],
    "sg:phone":"+1 514 522 1668",
    "sg:postcode":"H2J 2A4",
    "sg:province":"QC",
    "sg:tags":[
        "sporting",
        "good"
    ],
    "wof:name":"DE Fil En Montagne",
    "wof:placetype":"venue"
},
  "geometry": {"coordinates":[-73.579636,45.524033],"type":"Point"}
}