{
  "type": "Feature",
  "properties": {
    "addr:full":"515 Rue Marie-Anne E Montreal QC H2J 2A4",
    "addr:housenumber":"515",
    "addr:postcode":"h2j 2a4",
    "addr:street":"Rue Marie-Anne E",
    "iso:country":"CA",
    "sg:address":"515 Rue Marie-Anne E",
    "sg:city":"Montreal",
    "sg:classifiers":[
        {
            "category":"Retail",
            "subcategory":"Repair Shop",
            "type":"Services"
        }
    ],
    "sg:phone":"+1 514 522 1668",
    "sg:postcode":"H2J 2A4",
    "sg:province":"QC",
    "sg:tags":[
        "sporting",
        "good"
    ],
    "wof:name":"DE Fil En Montagne",
    "wof:placetype":"venue"
},
  "geometry": {"coordinates":[-73.57963599999999,45.524033],"type":"Point"}
}