{
  "type": "Feature",
  "properties": {
    "addr:full":"829 Rue Antle Greenfield Park QC J4V 3G6",
    "addr:housenumber":"829",
    "addr:postcode":"j4v 3g6",
    "addr:street":"Rue Antle;Park",
    "iso:country":"CA",
    "sg:address":"829 Rue Antle",
    "sg:city":"Greenfield Park",
    "sg:classifiers":[
        {
            "category":"Professional",
            "subcategory":"Computer Services",
            "type":"Services"
        }
    ],
    "sg:phone":"+1 450 678 4741",
    "sg:postcode":"J4V 3G6",
    "sg:province":"QC",
    "sg:tags":[
        "information",
        "system",
        "consultant"
    ],
    "wof:name":"Gagnon & Assoc",
    "wof:placetype":"venue"
},
  "geometry": {"coordinates":[-73.446251,45.489182],"type":"Point"}
}