{
  "type": "Feature",
  "properties": {
    "addr:full":"Tyndall MB R0E 2B0",
    "addr:postcode":"r0e 2b0",
    "iso:country":"CA",
    "sg:city":"Tyndall",
    "sg:classifiers":[
        {
            "category":"Building & Trades",
            "subcategory":"Plumbing",
            "type":"Services"
        }
    ],
    "sg:phone":"+1 204 268 1954",
    "sg:postcode":"R0E 2B0",
    "sg:province":"MB",
    "sg:tags":[
        "contractor"
    ],
    "wof:name":"Tyndall Plumbing & Heating",
    "wof:placetype":"venue"
},
  "geometry": {"coordinates":[-96.66069793699999,50.0768852234],"type":"Point"}
}