{
  "type": "Feature",
  "properties": {
    "iso:country":"CA",
    "sg:address":"1116 Dundas St E",
    "sg:city":"Mississauga",
    "sg:classifiers":[
        {
            "category":"Retail",
            "subcategory":"Auto Repair",
            "type":"Services"
        }
    ],
    "sg:phone":"+1 905 270 7070",
    "sg:postcode":"L4Y 2C1",
    "sg:province":"ON",
    "sg:tags":[
        "repairing",
        "automobile"
    ],
    "wof:name":"Midas Auto Svc Experts",
    "wof:placetype":"venue"
},
  "geometry": {"coordinates":[-79.5899734497,43.6036529541],"type":"Point"}
}