{
  "type": "Feature",
  "properties": {
    "addr:full":"Victoria BC V8W 1E2",
    "addr:postcode":"v8w 1e2",
    "iso:country":"CA",
    "sg:city":"Victoria",
    "sg:classifiers":[
        {
            "category":"Professional",
            "subcategory":"Research",
            "type":"Services"
        }
    ],
    "sg:phone":"+1 250 480 7103",
    "sg:postcode":"V8W 1E2",
    "sg:province":"BC",
    "sg:tags":[
        "environmental",
        "ecological",
        "engineer"
    ],
    "wof:name":"Enkon Environmental Ltd",
    "wof:placetype":"venue"
},
  "geometry": {"coordinates":[-123.365227,48.423649],"type":"Point"}
}