{
  "type": "Feature",
  "properties": {
    "addr:full":"106 Quebec St Schreiber ON P0T 2S0",
    "addr:housenumber":"106",
    "addr:postcode":"p0t 2s0",
    "addr:street":"Quebec St",
    "iso:country":"CA",
    "sg:address":"106 Quebec St",
    "sg:city":"Schreiber",
    "sg:classifiers":[
        {
            "category":"Travel",
            "subcategory":"Hotels & Motels",
            "type":"Entertainment"
        }
    ],
    "sg:phone":"+1 807 824 1391",
    "sg:postcode":"P0T 2S0",
    "sg:province":"ON",
    "wof:name":"Barrel Inn",
    "wof:placetype":"venue"
},
  "geometry": {"coordinates":[-87.2605438232,48.8082733154],"type":"Point"}
}