{
  "type": "Feature",
  "properties": {
    "addr:full":"473 Scott Rd Sarnia ON N7T 8G3",
    "addr:housenumber":"473",
    "addr:postcode":"n7t 8g3",
    "addr:street":"Scott Rd",
    "iso:country":"CA",
    "sg:address":"473 Scott Rd",
    "sg:city":"Sarnia",
    "sg:classifiers":[
        {
            "category":"Building & Trades",
            "subcategory":"Plumbing",
            "type":"Services"
        }
    ],
    "sg:phone":"+1 519 336 5490",
    "sg:postcode":"N7T 8G3",
    "sg:province":"ON",
    "sg:tags":[
        "mechanical",
        "painter",
        "contractor"
    ],
    "wof:name":"Matrix Service Inc",
    "wof:placetype":"venue"
},
  "geometry": {"coordinates":[-82.39665222169999,42.9526405334],"type":"Point"}
}