{
  "type": "Feature",
  "properties": {
    "addr:full":"1582 Eglinton Ave W York ON M6E 2G8",
    "addr:housenumber":"1582",
    "addr:postcode":"m6e 2g8",
    "addr:street":"Eglinton Ave W",
    "iso:country":"CA",
    "sg:address":"1582 Eglinton Ave W",
    "sg:city":"York",
    "sg:classifiers":[
        {
            "category":"Food & Beverages",
            "subcategory":"Groceries & Convenience Stores",
            "type":"Retail Goods"
        }
    ],
    "sg:phone":"+1 416 789 2387",
    "sg:postcode":"M6E 2G8",
    "sg:province":"ON",
    "sg:tags":[
        "grocer"
    ],
    "wof:name":"Gus's Tropical Foods",
    "wof:placetype":"venue"
},
  "geometry": {"coordinates":[-79.44255800000001,43.697479],"type":"Point"}
}