{
  "type": "Feature",
  "properties": {
    "iso:country":"CA",
    "sg:address":"56 Lake St S",
    "sg:city":"Echo Bay",
    "sg:classifiers":[
        {
            "category":"Organizations",
            "subcategory":"Religious Organization",
            "type":"Services"
        }
    ],
    "sg:phone":"+1 705 248 2598",
    "sg:postcode":"P0S 1C0",
    "sg:province":"ON",
    "sg:tags":[
        "church"
    ],
    "wof:name":"Faith Baptist Church",
    "wof:placetype":"venue"
},
  "geometry": {"coordinates":[-84.068031311,46.4842720032],"type":"Point"}
}