{
  "type": "Feature",
  "properties": {
    "addr:full":"399 Yonge St Toronto ON M5B 1S9",
    "addr:housenumber":"399",
    "addr:postcode":"m5b 1s9",
    "addr:street":"Yonge St",
    "iso:country":"CA",
    "sg:address":"399 Yonge St",
    "sg:city":"Toronto",
    "sg:classifiers":[
        {
            "category":"Shopping",
            "subcategory":"Luggage & Leather Goods",
            "type":"Retail Goods"
        }
    ],
    "sg:phone":"+1 416 260 0909",
    "sg:postcode":"M5B 1S9",
    "sg:province":"ON",
    "wof:name":"All Leather",
    "wof:placetype":"venue"
},
  "geometry": {"coordinates":[-79.382034,43.659382],"type":"Point"}
}