{
  "type": "Feature",
  "properties": {
    "addr:full":"1275 Av Saint-Edouard Plessisville QC G6L 2K1",
    "addr:housenumber":"1275",
    "addr:postcode":"g6l 2k1",
    "addr:street":"Av Saint-Edouard",
    "iso:country":"CA",
    "sg:address":"1275 Av Saint-Edouard",
    "sg:city":"Plessisville",
    "sg:classifiers":[
        {
            "category":"Organizations",
            "subcategory":"Professional Association",
            "type":"Services"
        }
    ],
    "sg:phone":"+1 819 362 8452",
    "sg:postcode":"G6L 2K1",
    "sg:province":"QC",
    "wof:name":"Amis Des Scouts Plessisville",
    "wof:placetype":"venue"
},
  "geometry": {"coordinates":[-71.7688903809,46.2160758972],"type":"Point"}
}