{
  "type": "Feature",
  "properties": {
    "iso:country":"CA",
    "sg:address":"103 Bruneau Rd",
    "sg:city":"Lac Du Bonnet",
    "sg:classifiers":[
        {
            "category":"Wholesale",
            "subcategory":"Electrical",
            "type":"Manufacturing & Wholesale Goods"
        }
    ],
    "sg:phone":"+1 204 345 2944",
    "sg:postcode":"R0E 1A0",
    "sg:province":"MB",
    "sg:tags":[
        "appliance"
    ],
    "wof:name":"Elbee Tv & Appliances",
    "wof:placetype":"venue"
},
  "geometry": {"coordinates":[-96.06196594239999,50.2516365051],"type":"Point"}
}