{
  "type": "Feature",
  "properties": {
    "addr:full":"178 Water St Lakefield ON K0L 2H0",
    "addr:housenumber":"178",
    "addr:postcode":"k0l 2h0",
    "addr:street":"Water St",
    "iso:country":"CA",
    "sg:address":"178 Water St",
    "sg:city":"Lakefield",
    "sg:classifiers":[
        {
            "category":"Home & Garden",
            "subcategory":"Building Materials",
            "type":"Retail Goods"
        }
    ],
    "sg:phone":"+1 705 652 3347",
    "sg:postcode":"K0L 2H0",
    "sg:province":"ON",
    "sg:tags":[
        "lumber"
    ],
    "wof:name":"Rona Cashway Building Ctr",
    "wof:placetype":"venue"
},
  "geometry": {"coordinates":[-78.2711715698,44.4213447571],"type":"Point"}
}