{
  "type": "Feature",
  "properties": {
    "addr:full":"72 Av Du Pont O Saint-Martin QC G0M 1B0",
    "addr:postcode":"g0m 1b0",
    "addr:street":"72 Av Du Pont O Saint-Martin",
    "iso:country":"CA",
    "sg:address":"72 Av Du Pont O",
    "sg:city":"Saint-Martin",
    "sg:classifiers":[
        {
            "category":"Restaurant",
            "type":"Food & Drink"
        }
    ],
    "sg:phone":"+1 418 382 5243",
    "sg:postcode":"G0M 1B0",
    "sg:province":"QC",
    "wof:name":"Casse-Croute DE L'Ouest",
    "wof:placetype":"venue"
},
  "geometry": {"coordinates":[-70.666527,45.959362],"type":"Point"}
}