{
  "type": "Feature",
  "properties": {
    "addr:full":"6359 Rue Pierre Montreal-Nord QC H1G 1P3",
    "addr:housenumber":"6359",
    "addr:postcode":"h1g 1p3",
    "addr:street":"Rue Pierre",
    "iso:country":"CA",
    "sg:address":"6359 Rue Pierre",
    "sg:city":"Montreal-Nord",
    "sg:classifiers":[
        {
            "category":"Personal",
            "subcategory":"Beauty Salon",
            "type":"Services"
        }
    ],
    "sg:phone":"+1 514 325 5662",
    "sg:postcode":"H1G 1P3",
    "sg:province":"QC",
    "wof:name":"Nash Coiffure Enr",
    "wof:placetype":"venue"
},
  "geometry": {"coordinates":[-73.620765686,45.6193695068],"type":"Point"}
}