{
  "type": "Feature",
  "properties": {
    "addr:full":"162 Main St N Campbellville ON L0P 1B0",
    "addr:housenumber":"162",
    "addr:postcode":"l0p 1b0",
    "addr:street":"Main St N",
    "iso:country":"CA",
    "sg:address":"162 Main St N",
    "sg:city":"Campbellville",
    "sg:classifiers":[
        {
            "category":"Shopping",
            "type":"Retail Goods"
        }
    ],
    "sg:phone":"+1 905 854 2512",
    "sg:postcode":"L0P 1B0",
    "sg:province":"ON",
    "sg:tags":[
        "art",
        "gallery",
        "dealer"
    ],
    "wof:name":"Sunset Gallery",
    "wof:placetype":"venue"
},
  "geometry": {"coordinates":[-79.985794,43.489555],"type":"Point"}
}