{
  "type": "Feature",
  "properties": {
    "iso:country":"CA",
    "sg:address":"480 Rue Samuel-DE Champlain",
    "sg:city":"Boucherville",
    "sg:classifiers":[
        {
            "category":"Freight",
            "type":"Transportation"
        }
    ],
    "sg:phone":"+1 450 655 4391",
    "sg:postcode":"J4B 6P7",
    "sg:province":"QC",
    "sg:tags":[
        "trucking"
    ],
    "wof:name":"Serge Dupont Transport Inc",
    "wof:placetype":"venue"
},
  "geometry": {"coordinates":[-73.44645690919999,45.599521637],"type":"Point"}
}