{
  "type": "Feature",
  "properties": {
    "addr:full":"Farm Unity SK S0K 4L0",
    "addr:postcode":"s0k 4l0",
    "addr:street":"Unity",
    "iso:country":"CA",
    "sg:address":"Farm",
    "sg:city":"Unity",
    "sg:classifiers":[
        {
            "category":"Freight",
            "type":"Transportation"
        }
    ],
    "sg:phone":"+1 306 228 3601",
    "sg:postcode":"S0K 4L0",
    "sg:province":"SK",
    "sg:tags":[
        "grain",
        "hauling",
        "trucking"
    ],
    "wof:name":"Wallace Brothers Trucking Ltd",
    "wof:placetype":"venue"
},
  "geometry": {"coordinates":[-109.145546,52.437111],"type":"Point"}
}