{
  "type": "Feature",
  "properties": {
    "addr:full":"4th Ave W Outlook SK S0L 2N0",
    "addr:postcode":"s0l 2n0",
    "addr:street":"4Th Ave W Outlook",
    "iso:country":"CA",
    "sg:address":"4th Ave W",
    "sg:city":"Outlook",
    "sg:classifiers":[
        {
            "category":"Education",
            "subcategory":"School",
            "type":"Public Place"
        }
    ],
    "sg:phone":"+1 306 867 8971",
    "sg:postcode":"S0L 2N0",
    "sg:province":"SK",
    "wof:name":"Lutheran Collegiate Bible Inst",
    "wof:placetype":"venue"
},
  "geometry": {"coordinates":[-107.05843400000001,51.487324],"type":"Point"}
}