{
  "type": "Feature",
  "properties": {
    "iso:country":"CA",
    "sg:city":"Halifax",
    "sg:classifiers":[
        {
            "category":"Banks & Credit Unions",
            "subcategory":"Investment Brokerage",
            "type":"Services"
        }
    ],
    "sg:phone":"+1 902 422 9098",
    "sg:postcode":"B3J 3R7",
    "sg:province":"NS",
    "sg:tags":[
        "consultant",
        "planning",
        "financial"
    ],
    "wof:name":"Union Securities Ltd",
    "wof:placetype":"venue"
},
  "geometry": {"coordinates":[-63.576625824,44.6527557373],"type":"Point"}
}