{
  "type": "Feature",
  "properties": {
    "iso:country":"CA",
    "sg:address":"131 Saunders Rd",
    "sg:city":"Barrie",
    "sg:classifiers":[
        {
            "category":"Home & Garden",
            "subcategory":"Carpets & Floor Coverings",
            "type":"Retail Goods"
        }
    ],
    "sg:phone":"+1 705 720 2287",
    "sg:postcode":"L4N 9A7",
    "sg:province":"ON",
    "sg:tags":[
        "material"
    ],
    "wof:name":"Woodwin",
    "wof:placetype":"venue"
},
  "geometry": {"coordinates":[-79.679115,44.33165],"type":"Point"}
}