{
  "type": "Feature",
  "properties": {
    "addr:full":"530 Boul Des Ruisseaux Mont-Laurier QC J9L 3G6",
    "addr:housenumber":"530",
    "addr:postcode":"j9l 3g6",
    "addr:street":"Boul Des Ruisseaux",
    "iso:country":"CA",
    "sg:address":"530 Boul Des Ruisseaux",
    "sg:city":"Mont-Laurier",
    "sg:classifiers":[
        {
            "category":"Real Estate",
            "subcategory":"Real Estate Agent",
            "type":"Services"
        }
    ],
    "sg:phone":"+1 819 623 4246",
    "sg:postcode":"J9L 3G6",
    "sg:province":"QC",
    "sg:tags":[
        "tool",
        "agency",
        "rental"
    ],
    "wof:name":"Location Mont-Laurier Inc",
    "wof:placetype":"venue"
},
  "geometry": {"coordinates":[-75.5344543457,46.5557174683],"type":"Point"}
}