{
  "type": "Feature",
  "properties": {
    "addr:full":"3023 Shakespeare St Victoria BC V8R 4H6",
    "addr:housenumber":"3023",
    "addr:postcode":"v8r 4h6",
    "addr:street":"Shakespeare St",
    "iso:country":"CA",
    "sg:address":"3023 Shakespeare St",
    "sg:city":"Victoria",
    "sg:classifiers":[
        {
            "category":"Personal",
            "subcategory":"Beauty Salon",
            "type":"Services"
        }
    ],
    "sg:phone":"+1 250 370 1800",
    "sg:postcode":"V8R 4H6",
    "sg:province":"BC",
    "wof:name":"Island Haircutting CO",
    "wof:placetype":"venue"
},
  "geometry": {"coordinates":[-123.335540772,48.4440116882],"type":"Point"}
}