{
  "type": "Feature",
  "properties": {
    "addr:full":"2017 33 Ave SW Calgary AB T2T 1Z5",
    "addr:housenumber":"2017",
    "addr:postcode":"t2t 1z5",
    "addr:street":"33 Ave Sw",
    "iso:country":"CA",
    "sg:address":"2017 33 Ave SW",
    "sg:city":"Calgary",
    "sg:classifiers":[
        {
            "category":"Home & Garden",
            "subcategory":"Household Appliances",
            "type":"Retail Goods"
        }
    ],
    "sg:phone":"+1 403 249 5563",
    "sg:postcode":"T2T 1Z5",
    "sg:province":"AB",
    "sg:tags":[
        "cleaners",
        "vacuum"
    ],
    "wof:name":"Electrolux Canada",
    "wof:placetype":"venue"
},
  "geometry": {"coordinates":[-114.107552,51.023853],"type":"Point"}
}