{
  "type": "Feature",
  "properties": {
    "addr:full":"29 Rue Du Golf Loretteville QC G2A 1G1",
    "addr:housenumber":"29",
    "addr:postcode":"g2a 1g1",
    "addr:street":"Rue Du Golf",
    "iso:country":"CA",
    "sg:address":"29 Rue Du Golf",
    "sg:city":"Loretteville",
    "sg:classifiers":[
        {
            "category":"Organizations",
            "subcategory":"Professional Association",
            "type":"Services"
        }
    ],
    "sg:phone":"+1 418 845 0732",
    "sg:postcode":"G2A 1G1",
    "sg:province":"QC",
    "wof:name":"Scouts & Guides Chateau D'Eau",
    "wof:placetype":"venue"
},
  "geometry": {"coordinates":[-71.37027,46.8591],"type":"Point"}
}