{
  "type": "Feature",
  "properties": {
    "iso:country":"CA",
    "sg:address":"408 Gagnon St",
    "sg:city":"Bonfield",
    "sg:classifiers":[
        {
            "category":"Organizations",
            "subcategory":"Religious Organization",
            "type":"Services"
        }
    ],
    "sg:phone":"+1 705 776 2244",
    "sg:postcode":"P0H 1E0",
    "sg:province":"ON",
    "sg:tags":[
        "church"
    ],
    "wof:name":"Paroisse Ste Bernadette",
    "wof:placetype":"venue"
},
  "geometry": {"coordinates":[-79.1425628662,46.2309799194],"type":"Point"}
}