{
  "type": "Feature",
  "properties": {
    "addr:full":"SE 15-24-3E Riverton MB R0C 2R0",
    "addr:postcode":"r0c 2r0",
    "addr:street":"Se 15-24-3E",
    "iso:country":"CA",
    "sg:address":"SE 15-24-3E",
    "sg:city":"Riverton",
    "sg:classifiers":[
        {
            "category":"Freight",
            "type":"Transportation"
        }
    ],
    "sg:phone":"+1 204 378 2167",
    "sg:postcode":"R0C 2R0",
    "sg:province":"MB",
    "sg:tags":[
        "trucking"
    ],
    "wof:name":"Muzyka Cartage Ltd",
    "wof:placetype":"venue"
},
  "geometry": {"coordinates":[-96.99645200000001,50.998413],"type":"Point"}
}