{
  "type": "Feature",
  "properties": {
    "addr:full":"217 Franklin St Outlook SK S0L 2N0",
    "addr:housenumber":"217",
    "addr:postcode":"s0l 2n0",
    "addr:street":"Franklin St",
    "iso:country":"CA",
    "sg:address":"217 Franklin St",
    "sg:city":"Outlook",
    "sg:classifiers":[
        {
            "category":"Insurance",
            "subcategory":"Insurance Agent",
            "type":"Services"
        }
    ],
    "sg:phone":"+1 306 867 9300",
    "sg:postcode":"S0L 2N0",
    "sg:province":"SK",
    "wof:name":"A & E Enterprises Ltd",
    "wof:placetype":"venue"
},
  "geometry": {"coordinates":[-107.053856,51.484833],"type":"Point"}
}