{
  "type": "Feature",
  "properties": {
    "iso:country":"CA",
    "sg:city":"Ascot Corner",
    "sg:classifiers":[
        {
            "category":"Social Services",
            "type":"Services"
        }
    ],
    "sg:phone":"+1 819 563 1804",
    "sg:postcode":"J0B 1A0",
    "sg:province":"QC",
    "sg:tags":[
        "organization",
        "welfare"
    ],
    "wof:name":"Centre Nuhab Inc",
    "wof:placetype":"venue"
},
  "geometry": {"coordinates":[-71.7536621094,45.4504089355],"type":"Point"}
}