{
  "type": "Feature",
  "properties": {
    "addr:full":"2342 Sales Rd E Quesnel BC V2J 6K4",
    "addr:housenumber":"2342",
    "addr:postcode":"v2j 6k4",
    "addr:street":"Sales Rd E",
    "iso:country":"CA",
    "sg:address":"2342 Sales Rd E",
    "sg:city":"Quesnel",
    "sg:classifiers":[
        {
            "category":"Freight",
            "type":"Transportation"
        }
    ],
    "sg:phone":"+1 250 747 2773",
    "sg:postcode":"V2J 6K4",
    "sg:province":"BC",
    "sg:tags":[
        "trucking"
    ],
    "wof:name":"Timber Service",
    "wof:placetype":"venue"
},
  "geometry": {"coordinates":[-122.498245239,52.9781188965],"type":"Point"}
}