{
  "type": "Feature",
  "properties": {
    "addr:full":"191 Roncesvalles Ave Toronto ON M6R 2L5",
    "addr:housenumber":"191",
    "addr:postcode":"m6r 2l5",
    "addr:street":"Roncesvalles Ave",
    "iso:country":"CA",
    "sg:address":"191 Roncesvalles Ave",
    "sg:city":"Toronto",
    "sg:classifiers":[
        {
            "category":"Travel",
            "subcategory":"Travel Agent",
            "type":"Entertainment"
        }
    ],
    "sg:phone":"+1 416 588 1397",
    "sg:postcode":"M6R 2L5",
    "sg:province":"ON",
    "sg:tags":[
        "ticket",
        "agency",
        "bureau",
        "airline"
    ],
    "wof:name":"Pekao Trading CO",
    "wof:placetype":"venue"
},
  "geometry": {"coordinates":[-79.44832599999999,43.644981],"type":"Point"}
}