{
  "type": "Feature",
  "properties": {
    "addr:full":"PO Box 53 Sechelt BC V0N 3A0",
    "addr:housenumber":"po box 53",
    "addr:postcode":"v0n 3a0",
    "iso:country":"CA",
    "sg:address":"PO Box 53",
    "sg:city":"Sechelt",
    "sg:classifiers":[
        {
            "category":"Retail",
            "subcategory":"Portrait Studio",
            "type":"Services"
        }
    ],
    "sg:phone":"+1 604 885 4106",
    "sg:postcode":"V0N 3A0",
    "sg:province":"BC",
    "sg:tags":[
        "photographer"
    ],
    "wof:name":"Clearly Now Photography",
    "wof:placetype":"venue"
},
  "geometry": {"coordinates":[-123.754707,49.472565],"type":"Point"}
}