{
  "type": "Feature",
  "properties": {
    "iso:country":"CA",
    "sg:address":"636 138 Rte",
    "sg:city":"Neuville",
    "sg:classifiers":[
        {
            "category":"Retail",
            "subcategory":"Auto Repair",
            "type":"Services"
        }
    ],
    "sg:phone":"+1 418 876 2018",
    "sg:postcode":"G0A 2R0",
    "sg:province":"QC",
    "sg:tags":[
        "repairing",
        "automobile"
    ],
    "wof:name":"R Bouffard & Fils Inc",
    "wof:placetype":"venue"
},
  "geometry": {"coordinates":[-71.5853271484,46.6966133118],"type":"Point"}
}