{
  "type": "Feature",
  "properties": {
    "addr:full":"8 Rue Dragon Kirkland QC H9J 3B1",
    "addr:housenumber":"8",
    "addr:postcode":"h9j 3b1",
    "addr:street":"Rue Dragon",
    "iso:country":"CA",
    "sg:address":"8 Rue Dragon",
    "sg:city":"Kirkland",
    "sg:classifiers":[
        {
            "category":"Professional",
            "subcategory":"Management & Consulting",
            "type":"Services"
        }
    ],
    "sg:phone":"+1 514 630 9981",
    "sg:postcode":"H9J 3B1",
    "sg:province":"QC",
    "sg:tags":[
        "consultant",
        "business"
    ],
    "wof:name":"Lisara Logic",
    "wof:placetype":"venue"
},
  "geometry": {"coordinates":[-73.8760147095,45.4542160034],"type":"Point"}
}