{
  "type": "Feature",
  "properties": {
    "addr:full":"9602 92E Av Petite-Riviere-Saint-Francois QC G0A 2L0",
    "addr:housenumber":"9602",
    "addr:postcode":"g0a 2l0",
    "addr:street":"92E Av Petite-Riviere-Saint-Francois",
    "iso:country":"CA",
    "sg:address":"9602 92E Av",
    "sg:city":"Petite-Riviere-Saint-Francois",
    "sg:classifiers":[
        {
            "category":"Organizations",
            "subcategory":"Religious Organization",
            "type":"Services"
        }
    ],
    "sg:phone":"+1 418 539 4691",
    "sg:postcode":"G0A 2L0",
    "sg:province":"QC",
    "sg:tags":[
        "church"
    ],
    "wof:name":"Church of Christ",
    "wof:placetype":"venue"
},
  "geometry": {"coordinates":[-70.56830600000001,47.307259],"type":"Point"}
}