{
  "type": "Feature",
  "properties": {
    "addr:full":"65 Beaty Ave Toronto ON M6K 3B3",
    "addr:housenumber":"65",
    "addr:postcode":"m6k 3b3",
    "addr:street":"Beaty Ave",
    "iso:country":"CA",
    "sg:address":"65 Beaty Ave",
    "sg:city":"Toronto",
    "sg:classifiers":[
        {
            "category":"Real Estate",
            "subcategory":"Architect",
            "type":"Services"
        }
    ],
    "sg:phone":"+1 416 532 7855",
    "sg:postcode":"M6K 3B3",
    "sg:province":"ON",
    "sg:tags":[
        "home",
        "planning",
        "design"
    ],
    "wof:name":"Articulations",
    "wof:placetype":"venue"
},
  "geometry": {"coordinates":[-79.440506,43.638489],"type":"Point"}
}