{
  "type": "Feature",
  "properties": {
    "iso:country":"CA",
    "sg:address":"280 Spadina Ave",
    "sg:city":"Toronto",
    "sg:classifiers":[
        {
            "category":"Social Services",
            "type":"Services"
        }
    ],
    "sg:phone":"+1 416 599 9333",
    "sg:postcode":"M5T 3A5",
    "sg:province":"ON",
    "sg:tags":[
        "organization",
        "welfare"
    ],
    "wof:name":"University Settlement Recrtn",
    "wof:placetype":"venue"
},
  "geometry": {"coordinates":[-79.3982162476,43.6525650024],"type":"Point"}
}