{
  "type": "Feature",
  "properties": {
    "addr:full":"1045 King St W Hamilton ON L8S 1L6",
    "addr:housenumber":"1045",
    "addr:postcode":"l8s 1l6",
    "addr:street":"King St W",
    "iso:country":"CA",
    "sg:address":"1045 King St W",
    "sg:city":"Hamilton",
    "sg:classifiers":[
        {
            "category":"Shopping",
            "type":"Retail Goods"
        }
    ],
    "sg:phone":"+1 905 523 5440",
    "sg:postcode":"L8S 1L6",
    "sg:province":"ON",
    "sg:tags":[
        "picture",
        "frame"
    ],
    "wof:name":"Picture Frame of Westdale",
    "wof:placetype":"venue"
},
  "geometry": {"coordinates":[-79.90675400000001,43.261379],"type":"Point"}
}