{
  "type": "Feature",
  "properties": {
    "addr:full":"63 Milner St Winnipeg MB R2X 2P7",
    "addr:housenumber":"63",
    "addr:postcode":"r2x 2p7",
    "addr:street":"Milner St",
    "iso:country":"CA",
    "sg:address":"63 Milner St",
    "sg:city":"Winnipeg",
    "sg:classifiers":[
        {
            "category":"Manufacturing",
            "subcategory":"Metals",
            "type":"Manufacturing & Wholesale Goods"
        }
    ],
    "sg:phone":"+1 204 633 5767",
    "sg:postcode":"R2X 2P7",
    "sg:province":"MB",
    "sg:tags":[
        "product",
        "wire"
    ],
    "wof:name":"J R Wire & Metal Specialty Ltd",
    "wof:placetype":"venue"
},
  "geometry": {"coordinates":[-97.17459100000001,49.939709],"type":"Point"}
}