{
  "type": "Feature",
  "properties": {
    "addr:full":"2609 Fanshawe Park Rd E London ON N5X 4A1",
    "addr:housenumber":"2609",
    "addr:postcode":"n5x 4a1",
    "addr:street":"Fanshawe Park Rd E",
    "iso:country":"CA",
    "sg:address":"2609 Fanshawe Park Rd E",
    "sg:city":"London",
    "sg:classifiers":[
        {
            "category":"Museum",
            "type":"Entertainment"
        }
    ],
    "sg:phone":"+1 519 457 1296",
    "sg:postcode":"N5X 4A1",
    "sg:province":"ON",
    "wof:name":"Fanshawe Pioneer Village",
    "wof:placetype":"venue"
},
  "geometry": {"coordinates":[-81.184769,43.054142],"type":"Point"}
}