{
  "type": "Feature",
  "properties": {
    "addr:full":"935 Boul Decarie Saint-Laurent QC H4L 3M3",
    "addr:housenumber":"935",
    "addr:postcode":"h4l 3m3",
    "addr:street":"Boul Decarie",
    "iso:country":"CA",
    "sg:address":"935 Boul Decarie",
    "sg:city":"Saint-Laurent",
    "sg:classifiers":[
        {
            "category":"Manufacturing",
            "subcategory":"Tools & Machinery",
            "type":"Manufacturing & Wholesale Goods"
        }
    ],
    "sg:phone":"+1 514 748 6476",
    "sg:postcode":"H4L 3M3",
    "sg:province":"QC",
    "sg:tags":[
        "fuse",
        "electric"
    ],
    "wof:name":"Ferraz Shawmut CO",
    "wof:placetype":"venue"
},
  "geometry": {"coordinates":[-73.681084,45.513439],"type":"Point"}
}