{
  "type": "Feature",
  "properties": {
    "addr:full":"Langley BC V3A 4K6",
    "addr:postcode":"v3a 4k6",
    "iso:country":"CA",
    "sg:city":"Langley",
    "sg:classifiers":[
        {
            "category":"Autos & Motor Vehicles",
            "subcategory":"Auto Supplies",
            "type":"Retail Goods"
        }
    ],
    "sg:phone":"+1 604 530 2104",
    "sg:postcode":"V3A 4K6",
    "sg:province":"BC",
    "sg:tags":[
        "automobile",
        "parts"
    ],
    "wof:name":"Uap Napa Auto Parts",
    "wof:placetype":"venue"
},
  "geometry": {"coordinates":[-122.667472839,49.1098747253],"type":"Point"}
}