{
  "type": "Feature",
  "properties": {
    "addr:full":"113 Rue Principale Notre-Dame-Du-Laus QC J0X 2M0",
    "addr:housenumber":"113",
    "addr:postcode":"j0x 2m0",
    "addr:street":"Rue Principale",
    "iso:country":"CA",
    "sg:address":"113 Rue Principale",
    "sg:city":"Notre-Dame-Du-Laus",
    "sg:classifiers":[
        {
            "category":"Travel",
            "subcategory":"Hotels & Motels",
            "type":"Entertainment"
        }
    ],
    "sg:phone":"+1 819 767 2215",
    "sg:postcode":"J0X 2M0",
    "sg:province":"QC",
    "wof:name":"Laus-Berge",
    "wof:placetype":"venue"
},
  "geometry": {"coordinates":[-75.62468699999999,46.089249],"type":"Point"}
}