{
  "type": "Feature",
  "properties": {
    "addr:full":"49 Rue Des Jardins Quebec QC G1R 4L6",
    "addr:housenumber":"49",
    "addr:postcode":"g1r 4l6",
    "addr:street":"Rue Des Jardins",
    "iso:country":"CA",
    "sg:address":"49 Rue Des Jardins",
    "sg:city":"Quebec",
    "sg:classifiers":[
        {
            "category":"Shopping",
            "subcategory":"Shoes",
            "type":"Retail Goods"
        }
    ],
    "sg:phone":"+1 418 692 5424",
    "sg:postcode":"G1R 4L6",
    "sg:province":"QC",
    "wof:name":"Chaussures Soli Terre Lit-Pied",
    "wof:placetype":"venue"
},
  "geometry": {"coordinates":[-71.20742799999999,46.812126],"type":"Point"}
}