{
  "type": "Feature",
  "properties": {
    "addr:full":"162 Boul LA Salle Baie-Comeau QC G4Z 1S4",
    "addr:housenumber":"162",
    "addr:postcode":"g4z 1s4",
    "addr:street":"Boul La",
    "iso:country":"CA",
    "sg:address":"162 Boul LA Salle",
    "sg:city":"Baie-Comeau",
    "sg:classifiers":[
        {
            "category":"Shopping",
            "subcategory":"Tobacco",
            "type":"Retail Goods"
        }
    ],
    "sg:phone":"+1 418 296 6442",
    "sg:postcode":"G4Z 1S4",
    "sg:province":"QC",
    "sg:tags":[
        "cigarette",
        "convenience",
        "cigar",
        "store"
    ],
    "wof:name":"Tabagie Baie-Comeau Inc",
    "wof:placetype":"venue"
},
  "geometry": {"coordinates":[-68.162598,49.217373],"type":"Point"}
}