{
  "type": "Feature",
  "properties": {
    "addr:full":"542 Keele St Toronto ON M6N 3E2",
    "addr:housenumber":"542",
    "addr:postcode":"m6n 3e2",
    "addr:street":"Keele St",
    "iso:country":"CA",
    "sg:address":"542 Keele St",
    "sg:city":"Toronto",
    "sg:classifiers":[
        {
            "category":"Shopping",
            "subcategory":"Stationery & Office Supplies",
            "type":"Retail Goods"
        }
    ],
    "sg:phone":"+1 416 762 2816",
    "sg:postcode":"M6N 3E2",
    "sg:province":"ON",
    "wof:name":"Business Depot Ltd",
    "wof:placetype":"venue"
},
  "geometry": {"coordinates":[-79.466736,43.670177],"type":"Point"}
}