{
  "type": "Feature",
  "properties": {
    "iso:country":"CA",
    "sg:address":"40 Heathview Ave",
    "sg:city":"North York",
    "sg:classifiers":[
        {
            "category":"Building & Trades",
            "subcategory":"Construction",
            "type":"Services"
        }
    ],
    "sg:phone":"+1 416 222 9694",
    "sg:postcode":"M2K 2C1",
    "sg:province":"ON",
    "sg:tags":[
        "home",
        "fence",
        "improvement"
    ],
    "wof:name":"Forest Grove Construction",
    "wof:placetype":"venue"
},
  "geometry": {"coordinates":[-79.385506,43.78315],"type":"Point"}
}