{
  "type": "Feature",
  "properties": {
    "addr:full":"40 Heathview Ave North York ON M2K 2C1",
    "addr:housenumber":"40",
    "addr:postcode":"m2k 2c1",
    "addr:street":"Heathview Ave",
    "iso:country":"CA",
    "sg:address":"40 Heathview Ave",
    "sg:city":"North York",
    "sg:classifiers":[
        {
            "category":"Building & Trades",
            "subcategory":"Construction",
            "type":"Services"
        }
    ],
    "sg:phone":"+1 416 222 9694",
    "sg:postcode":"M2K 2C1",
    "sg:province":"ON",
    "sg:tags":[
        "home",
        "fence",
        "improvement"
    ],
    "wof:name":"Forest Grove Construction",
    "wof:placetype":"venue"
},
  "geometry": {"coordinates":[-79.38550600000001,43.78315],"type":"Point"}
}