{
  "type": "Feature",
  "properties": {
    "addr:full":"712 Daly Ave Hedley BC V0X 1K0",
    "addr:housenumber":"712",
    "addr:postcode":"v0x 1k0",
    "addr:street":"Daly Ave",
    "iso:country":"CA",
    "sg:address":"712 Daly Ave",
    "sg:city":"Hedley",
    "sg:classifiers":[
        {
            "category":"Shopping",
            "subcategory":"Gifts & Souvenirs",
            "type":"Retail Goods"
        }
    ],
    "sg:phone":"+1 250 292 8422",
    "sg:postcode":"V0X 1K0",
    "sg:province":"BC",
    "sg:tags":[
        "shop"
    ],
    "wof:name":"Wild Goat Gift Shop & Tea Room",
    "wof:placetype":"venue"
},
  "geometry": {"coordinates":[-120.077934265,49.3564109802],"type":"Point"}
}