{
  "type": "Feature",
  "properties": {
    "addr:full":"Vauxhall AB T0K 2K0",
    "addr:postcode":"t0k 2k0",
    "iso:country":"CA",
    "sg:city":"Vauxhall",
    "sg:classifiers":[
        {
            "category":"Organizations",
            "subcategory":"Religious Organization",
            "type":"Services"
        }
    ],
    "sg:phone":"+1 403 654 4282",
    "sg:postcode":"T0K 2K0",
    "sg:province":"AB",
    "sg:tags":[
        "church"
    ],
    "wof:name":"Vauxhall Mennonite Brethren",
    "wof:placetype":"venue"
},
  "geometry": {"coordinates":[-112.113647461,50.0696601868],"type":"Point"}
}