{
  "type": "Feature",
  "properties": {
    "addr:full":"84 Blake St Toronto ON M4J 3C9",
    "addr:housenumber":"84",
    "addr:postcode":"m4j 3c9",
    "addr:street":"Blake St",
    "iso:country":"CA",
    "sg:address":"84 Blake St",
    "sg:city":"Toronto",
    "sg:classifiers":[
        {
            "category":"Social Services",
            "subcategory":"Child Care",
            "type":"Services"
        }
    ],
    "sg:phone":"+1 416 392 5055",
    "sg:postcode":"M4J 3C9",
    "sg:province":"ON",
    "sg:tags":[
        "government"
    ],
    "wof:name":"Toronto Child Care Ctr",
    "wof:placetype":"venue"
},
  "geometry": {"coordinates":[-79.339050293,43.6740455627],"type":"Point"}
}