{
  "type": "Feature",
  "properties": {
    "addr:full":"173 Rue Sainte-Catherine Longueuil QC J4H 2B4",
    "addr:housenumber":"173",
    "addr:postcode":"j4h 2b4",
    "addr:street":"Rue Sainte-Catherine",
    "iso:country":"CA",
    "sg:address":"173 Rue Sainte-Catherine",
    "sg:city":"Longueuil",
    "sg:classifiers":[
        {
            "category":"Health Services",
            "subcategory":"Health Practitioner",
            "type":"Services"
        }
    ],
    "sg:phone":"+1 450 646 6886",
    "sg:postcode":"J4H 2B4",
    "sg:province":"QC",
    "sg:tags":[
        "physiotherapist",
        "surgeon",
        "physician"
    ],
    "wof:name":"Clinique Ldl",
    "wof:placetype":"venue"
},
  "geometry": {"coordinates":[-73.49560546879999,45.5331726074],"type":"Point"}
}