{
  "type": "Feature",
  "properties": {
    "iso:country":"CA",
    "sg:address":"4208 55 Ave",
    "sg:city":"High Prairie",
    "sg:classifiers":[
        {
            "category":"Professional",
            "subcategory":"Engineering",
            "type":"Services"
        }
    ],
    "sg:phone":"+1 780 523 4842",
    "sg:postcode":"T0G 1E0",
    "sg:province":"AB",
    "sg:tags":[
        "engineer"
    ],
    "wof:name":"Amec Infrastructure",
    "wof:placetype":"venue"
},
  "geometry": {"coordinates":[-116.48300170900001,55.4348602295],"type":"Point"}
}