{
  "type": "Feature",
  "properties": {
    "addr:full":"Elmira ON N3B 2E1",
    "addr:postcode":"n3b 2e1",
    "iso:country":"CA",
    "sg:city":"Elmira",
    "sg:classifiers":[
        {
            "category":"Manufacturing",
            "subcategory":"Tools & Machinery",
            "type":"Manufacturing & Wholesale Goods"
        }
    ],
    "sg:phone":"+1 519 669 8003",
    "sg:postcode":"N3B 2E1",
    "sg:province":"ON",
    "sg:tags":[
        "pump"
    ],
    "wof:name":"Elmira Pump CO",
    "wof:placetype":"venue"
},
  "geometry": {"coordinates":[-80.5568161011,43.5900382996],"type":"Point"}
}