{
  "type": "Feature",
  "properties": {
    "iso:country":"CA",
    "sg:address":"3 Park Home Ave",
    "sg:city":"North York",
    "sg:classifiers":[
        {
            "category":"Travel",
            "subcategory":"Hotels & Motels",
            "type":"Entertainment"
        }
    ],
    "sg:phone":"+1 416 733 2929",
    "sg:postcode":"M2N 6L3",
    "sg:province":"ON",
    "sg:tags":[
        "establishment"
    ],
    "wof:name":"Novotel North York",
    "wof:placetype":"venue"
},
  "geometry": {"coordinates":[-79.413414,43.769016],"type":"Point"}
}