{
  "type": "Feature",
  "properties": {
    "iso:country":"CA",
    "sg:address":"428 Rue Des Erables",
    "sg:city":"Laurier-Station",
    "sg:classifiers":[
        {
            "category":"Retail",
            "subcategory":"Veterinary Services",
            "type":"Services"
        }
    ],
    "sg:phone":"+1 418 728 5121",
    "sg:postcode":"G0S 1N0",
    "sg:province":"QC",
    "sg:tags":[
        "veterinarian"
    ],
    "wof:name":"Clinique Veterinaire Laurier",
    "wof:placetype":"venue"
},
  "geometry": {"coordinates":[-71.6235580444,46.5349197388],"type":"Point"}
}