{
  "type": "Feature",
  "properties": {
    "addr:full":"371 King St Highgate ON N0P 1T0",
    "addr:housenumber":"371",
    "addr:postcode":"n0p 1t0",
    "addr:street":"King St Highgate",
    "iso:country":"CA",
    "sg:address":"371 King St",
    "sg:city":"Highgate",
    "sg:classifiers":[
        {
            "category":"Building & Trades",
            "subcategory":"Construction",
            "type":"Services"
        }
    ],
    "sg:phone":"+1 519 678 3928",
    "sg:postcode":"N0P 1T0",
    "sg:province":"ON",
    "sg:tags":[
        "excavating",
        "contractor"
    ],
    "wof:name":"Bruce Paine Backhoe Svc",
    "wof:placetype":"venue"
},
  "geometry": {"coordinates":[-81.82186900000001,42.505432],"type":"Point"}
}