{
  "type": "Feature",
  "properties": {
    "addr:full":"235 Av DE LA Mennais LA Prairie QC J5R 2E8",
    "addr:housenumber":"235",
    "addr:postcode":"j5r 2e8",
    "addr:street":"Av De La Mennais",
    "iso:country":"CA",
    "sg:address":"235 Av DE LA Mennais",
    "sg:city":"LA Prairie",
    "sg:classifiers":[
        {
            "category":"Health Services",
            "subcategory":"Health Practitioner",
            "type":"Services"
        }
    ],
    "sg:phone":"+1 450 659 6089",
    "sg:postcode":"J5R 2E8",
    "sg:province":"QC",
    "sg:tags":[
        "physician"
    ],
    "wof:name":"Maison Sante En Douce",
    "wof:placetype":"venue"
},
  "geometry": {"coordinates":[-73.477081,45.415264],"type":"Point"}
}