{
  "type": "Feature",
  "properties": {
    "addr:full":"NW 34 28 1W Dallas MB R0C 0S0",
    "addr:housenumber":"28",
    "addr:postcode":"r0c 0s0",
    "addr:street":"Nw 34",
    "iso:country":"CA",
    "sg:address":"NW 34 28 1W",
    "sg:city":"Dallas",
    "sg:classifiers":[
        {
            "category":"Organizations",
            "subcategory":"Community Association",
            "type":"Services"
        }
    ],
    "sg:phone":"+1 204 645 2619",
    "sg:postcode":"R0C 0S0",
    "sg:province":"MB",
    "sg:tags":[
        "club"
    ],
    "wof:name":"Dallas Red Rose Community Hall",
    "wof:placetype":"venue"
},
  "geometry": {"coordinates":[-97.485771,51.397034],"type":"Point"}
}