{
  "type": "Feature",
  "properties": {
    "addr:full":"96 Great Northern Rd Sault Ste Marie ON P6B 4Y5",
    "addr:housenumber":"96",
    "addr:postcode":"p6b 4y5",
    "addr:street":"Great Northern Rd",
    "iso:country":"CA",
    "sg:address":"96 Great Northern Rd",
    "sg:city":"Sault Ste Marie",
    "sg:classifiers":[
        {
            "category":"Organizations",
            "subcategory":"Professional Association",
            "type":"Services"
        }
    ],
    "sg:phone":"+1 705 945 8721",
    "sg:postcode":"P6B 4Y5",
    "sg:province":"ON",
    "wof:name":"Royal Canadian Legion",
    "wof:placetype":"venue"
},
  "geometry": {"coordinates":[-84.319427,46.528065],"type":"Point"}
}