{
  "type": "Feature",
  "properties": {
    "iso:country":"CA",
    "sg:address":"1231 Kingston Ave",
    "sg:city":"Ottawa",
    "sg:classifiers":[
        {
            "category":"Organizations",
            "subcategory":"Religious Organization",
            "type":"Services"
        }
    ],
    "sg:phone":"+1 613 798 8182",
    "sg:postcode":"K1Z 8K8",
    "sg:province":"ON",
    "wof:name":"Canadian Friends Svc Committee",
    "wof:placetype":"venue"
},
  "geometry": {"coordinates":[-75.7258605957,45.3769493103],"type":"Point"}
}