{
  "type": "Feature",
  "properties": {
    "addr:full":"Highway 34 Crystal City MB R0K 0N0",
    "addr:postcode":"r0k 0n0",
    "addr:street":"Highway 34",
    "iso:country":"CA",
    "sg:address":"Highway 34",
    "sg:city":"Crystal City",
    "sg:classifiers":[
        {
            "category":"Government",
            "subcategory":"Office",
            "type":"Public Place"
        }
    ],
    "sg:phone":"+1 204 873 2250",
    "sg:postcode":"R0K 0N0",
    "sg:province":"MB",
    "wof:name":"Canada Customs",
    "wof:placetype":"venue"
},
  "geometry": {"coordinates":[-98.9430007935,49.1477165222],"type":"Point"}
}