{
  "type": "Feature",
  "properties": {
    "addr:full":"303 2E Rue Shawinigan QC G9N 1J4",
    "addr:housenumber":"303",
    "addr:postcode":"g9n 1j4",
    "addr:street":"2E Rue",
    "iso:country":"CA",
    "sg:address":"303 2E Rue",
    "sg:city":"Shawinigan",
    "sg:classifiers":[
        {
            "category":"Health Services",
            "subcategory":"Nursing And Care Facility",
            "type":"Services"
        }
    ],
    "sg:phone":"+1 819 536 4241",
    "sg:postcode":"G9N 1J4",
    "sg:province":"QC",
    "sg:tags":[
        "home",
        "retirement",
        "community"
    ],
    "wof:name":"Residence Castel Des Cedres",
    "wof:placetype":"venue"
},
  "geometry": {"coordinates":[-72.746055603,46.5383262634],"type":"Point"}
}