{
  "type": "Feature",
  "properties": {
    "addr:full":"Calgary AB T2H 2L7",
    "addr:postcode":"t2h 2l7",
    "iso:country":"CA",
    "sg:city":"Calgary",
    "sg:classifiers":[
        {
            "category":"Shopping",
            "subcategory":"Computers & Home Electronics",
            "type":"Retail Goods"
        }
    ],
    "sg:phone":"+1 403 259 3339",
    "sg:postcode":"T2H 2L7",
    "sg:province":"AB",
    "sg:tags":[
        "equipment",
        "dealer"
    ],
    "wof:name":"Alberta Data Systems",
    "wof:placetype":"venue"
},
  "geometry": {"coordinates":[-114.03733800000001,50.997673],"type":"Point"}
}