{
  "type": "Feature",
  "properties": {
    "addr:full":"1643 Union Ave Ruthven ON N0P 2G0",
    "addr:housenumber":"1643",
    "addr:postcode":"n0p 2g0",
    "addr:street":"Union Ave",
    "iso:country":"CA",
    "sg:address":"1643 Union Ave",
    "sg:city":"Ruthven",
    "sg:classifiers":[
        {
            "category":"Building & Trades",
            "subcategory":"Construction",
            "type":"Services"
        }
    ],
    "sg:phone":"+1 519 326 2301",
    "sg:postcode":"N0P 2G0",
    "sg:province":"ON",
    "sg:tags":[
        "drainage",
        "contractor"
    ],
    "wof:name":"Di Menna Excavating",
    "wof:placetype":"venue"
},
  "geometry": {"coordinates":[-82.672173,42.049541],"type":"Point"}
}