{
  "type": "Feature",
  "properties": {
    "iso:country":"CA",
    "sg:address":"2275 Lake Shore Blvd W # 200",
    "sg:city":"Etobicoke",
    "sg:classifiers":[
        {
            "category":"Education",
            "subcategory":"Special Training",
            "type":"Public Place"
        }
    ],
    "sg:phone":"+1 416 255 3463",
    "sg:postcode":"M8V 3Y3",
    "sg:province":"ON",
    "sg:tags":[
        "school",
        "language"
    ],
    "wof:name":"Lakeshore Linc",
    "wof:placetype":"venue"
},
  "geometry": {"coordinates":[-79.48523712159999,43.6197738647],"type":"Point"}
}