{
  "type": "Feature",
  "properties": {
    "addr:full":"516 High St S Thunder Bay ON P7B 3M3",
    "addr:housenumber":"516",
    "addr:postcode":"p7b 3m3",
    "addr:street":"High St S Thunder",
    "iso:country":"CA",
    "sg:address":"516 High St S",
    "sg:city":"Thunder Bay",
    "sg:classifiers":[
        {
            "category":"Organizations",
            "subcategory":"Labor Organization",
            "type":"Services"
        }
    ],
    "sg:phone":"+1 807 346 1737",
    "sg:postcode":"P7B 3M3",
    "sg:province":"ON",
    "wof:name":"Cep Ctr",
    "wof:placetype":"venue"
},
  "geometry": {"coordinates":[-89.2386627197,48.418888092],"type":"Point"}
}