{
  "type": "Feature",
  "properties": {
    "addr:full":"Red Deer AB T4N 6M4",
    "addr:postcode":"t4n 6m4",
    "iso:country":"CA",
    "sg:city":"Red Deer",
    "sg:classifiers":[
        {
            "category":"Professional",
            "subcategory":"Lawyer & Legal Services",
            "type":"Services"
        }
    ],
    "sg:phone":"+1 403 343 2444",
    "sg:postcode":"T4N 6M4",
    "sg:province":"AB",
    "sg:tags":[
        "attorney"
    ],
    "wof:name":"Melnyk, Buddy G",
    "wof:placetype":"venue"
},
  "geometry": {"coordinates":[-113.811927795,52.2669754028],"type":"Point"}
}