{
  "type": "Feature",
  "properties": {
    "iso:country":"CA",
    "sg:address":"1785 Rue Nancy",
    "sg:city":"Brossard",
    "sg:classifiers":[
        {
            "category":"Wholesale",
            "subcategory":"Machinery & Supplies",
            "type":"Manufacturing & Wholesale Goods"
        }
    ],
    "sg:phone":"+1 450 443 3670",
    "sg:postcode":"J4Y 2M4",
    "sg:province":"QC",
    "sg:tags":[
        "ramp",
        "marine",
        "equipment"
    ],
    "wof:name":"Dsc Dock Svc Ctr",
    "wof:placetype":"venue"
},
  "geometry": {"coordinates":[-73.46756,45.448097],"type":"Point"}
}