{
  "type": "Feature",
  "properties": {
    "iso:country":"CA",
    "sg:city":"Winnipeg",
    "sg:classifiers":[
        {
            "category":"Government",
            "subcategory":"Office",
            "type":"Public Place"
        }
    ],
    "sg:phone":"+1 204 945 4915",
    "sg:postcode":"R3C 0V8",
    "sg:province":"MB",
    "wof:name":"Manitoba Finance",
    "wof:placetype":"venue"
},
  "geometry": {"coordinates":[-97.147865,49.885696],"type":"Point"}
}