{
  "type": "Feature",
  "properties": {
    "addr:full":"2430 Deer Run Ave Oakville ON L6J 6K9",
    "addr:housenumber":"2430",
    "addr:postcode":"l6j 6k9",
    "addr:street":"Deer Run Ave",
    "iso:country":"CA",
    "sg:address":"2430 Deer Run Ave",
    "sg:city":"Oakville",
    "sg:classifiers":[
        {
            "category":"Real Estate",
            "subcategory":"Real Estate Agent",
            "type":"Services"
        }
    ],
    "sg:phone":"+1 905 844 4309",
    "sg:postcode":"L6J 6K9",
    "sg:province":"ON",
    "sg:tags":[
        "investment"
    ],
    "wof:name":"Herefordshire Capital Corp",
    "wof:placetype":"venue"
},
  "geometry": {"coordinates":[-79.63771800000001,43.484741],"type":"Point"}
}