{
  "type": "Feature",
  "properties": {
    "addr:full":"31 9th St E Cornwall ON K6H 6R3",
    "addr:housenumber":"31",
    "addr:postcode":"k6h 6r3",
    "addr:street":"9Th St E",
    "iso:country":"CA",
    "sg:address":"31 9th St E",
    "sg:city":"Cornwall",
    "sg:classifiers":[
        {
            "category":"Recreation",
            "type":"Entertainment"
        }
    ],
    "sg:phone":"+1 613 933 0248",
    "sg:postcode":"K6H 6R3",
    "sg:province":"ON",
    "sg:tags":[
        "lottery",
        "agent"
    ],
    "wof:name":"Cnib Corner Store",
    "wof:placetype":"venue"
},
  "geometry": {"coordinates":[-74.7336730957,45.0291595459],"type":"Point"}
}