{
  "type": "Feature",
  "properties": {
    "addr:full":"3050 Boul DE Portland Sherbrooke QC J1L 1K1",
    "addr:housenumber":"3050",
    "addr:postcode":"j1l 1k1",
    "addr:street":"Boul De Portland",
    "iso:country":"CA",
    "sg:address":"3050 Boul DE Portland",
    "sg:city":"Sherbrooke",
    "sg:classifiers":[
        {
            "category":"Shopping",
            "type":"Retail Goods"
        }
    ],
    "sg:phone":"+1 819 569 6231",
    "sg:postcode":"J1L 1K1",
    "sg:province":"QC",
    "sg:tags":[
        "pet",
        "shop"
    ],
    "wof:name":"Animalerie Roufi",
    "wof:placetype":"venue"
},
  "geometry": {"coordinates":[-71.9493103027,45.4033050537],"type":"Point"}
}