{
  "type": "Feature",
  "properties": {
    "addr:full":"1773 Boul Graham Mont-Royal QC H3R 1G7",
    "addr:housenumber":"1773",
    "addr:postcode":"h3r 1g7",
    "addr:street":"Boul Graham",
    "iso:country":"CA",
    "sg:address":"1773 Boul Graham",
    "sg:city":"Mont-Royal",
    "sg:classifiers":[
        {
            "category":"Personal",
            "subcategory":"Barber",
            "type":"Services"
        }
    ],
    "sg:phone":"+1 514 738 5343",
    "sg:postcode":"H3R 1G7",
    "sg:province":"QC",
    "wof:name":"Salon Graham Enr",
    "wof:placetype":"venue"
},
  "geometry": {"coordinates":[-73.6455001831,45.5149154663],"type":"Point"}
}