{
  "type": "Feature",
  "properties": {
    "addr:full":"5802 47 Ave Olds AB T4H 1V1",
    "addr:housenumber":"5802",
    "addr:postcode":"t4h 1v1",
    "addr:street":"47 Ave",
    "iso:country":"CA",
    "sg:address":"5802 47 Ave",
    "sg:city":"Olds",
    "sg:classifiers":[
        {
            "category":"Freight",
            "type":"Transportation"
        }
    ],
    "sg:phone":"+1 403 556 3484",
    "sg:postcode":"T4H 1V1",
    "sg:province":"AB",
    "sg:tags":[
        "trucking"
    ],
    "wof:name":"Schmidt Transport",
    "wof:placetype":"venue"
},
  "geometry": {"coordinates":[-114.098839,51.784061],"type":"Point"}
}