{
  "type": "Feature",
  "properties": {
    "addr:full":"2643 22 Ave S Lethbridge AB T1K 1J8",
    "addr:housenumber":"2643",
    "addr:postcode":"t1k 1j8",
    "addr:street":"22 Ave S",
    "iso:country":"CA",
    "sg:address":"2643 22 Ave S",
    "sg:city":"Lethbridge",
    "sg:classifiers":[
        {
            "category":"Freight",
            "type":"Transportation"
        }
    ],
    "sg:phone":"+1 403 327 5351",
    "sg:postcode":"T1K 1J8",
    "sg:province":"AB",
    "sg:tags":[
        "mobile",
        "home"
    ],
    "wof:name":"Cps Transport Ltd",
    "wof:placetype":"venue"
},
  "geometry": {"coordinates":[-112.803391,49.671803],"type":"Point"}
}