{
  "type": "Feature",
  "properties": {
    "addr:full":"445 Rue Des Volontaires Trois-Rivieres QC G9A 2E7",
    "addr:housenumber":"445",
    "addr:postcode":"g9a 2e7",
    "addr:street":"Rue Des Volontaires Trois-Rivieres",
    "iso:country":"CA",
    "sg:address":"445 Rue Des Volontaires",
    "sg:city":"Trois-Rivieres",
    "sg:classifiers":[
        {
            "category":"Retail",
            "subcategory":"Funeral Services",
            "type":"Services"
        }
    ],
    "sg:phone":"+1 819 374 6225",
    "sg:postcode":"G9A 2E7",
    "sg:province":"QC",
    "sg:tags":[
        "director"
    ],
    "wof:name":"Center Funeraire Rousseau",
    "wof:placetype":"venue"
},
  "geometry": {"coordinates":[-72.5445098877,46.3429336548],"type":"Point"}
}