{
  "type": "Feature",
  "properties": {
    "addr:full":"144 University Ave W Windsor ON N9A 5N9",
    "addr:housenumber":"144",
    "addr:postcode":"n9a 5n9",
    "addr:street":"University Ave W",
    "iso:country":"CA",
    "sg:address":"144 University Ave W",
    "sg:city":"Windsor",
    "sg:classifiers":[
        {
            "category":"Retail",
            "subcategory":"Laundry & Dry Cleaning",
            "type":"Services"
        }
    ],
    "sg:phone":"+1 519 256 1058",
    "sg:postcode":"N9A 5N9",
    "sg:province":"ON",
    "sg:tags":[
        "cleaners"
    ],
    "wof:name":"Metro Dry Cleaners",
    "wof:placetype":"venue"
},
  "geometry": {"coordinates":[-83.040604,42.317345],"type":"Point"}
}