{
  "type": "Feature",
  "properties": {
    "addr:full":"598 Queen St W Toronto ON M6J 1E3",
    "addr:housenumber":"598",
    "addr:postcode":"m6j 1e3",
    "addr:street":"Queen St W",
    "iso:country":"CA",
    "sg:address":"598 Queen St W",
    "sg:city":"Toronto",
    "sg:classifiers":[
        {
            "category":"Restaurant",
            "type":"Food & Drink"
        }
    ],
    "sg:phone":"+1 416 504 9874",
    "sg:postcode":"M6J 1E3",
    "sg:province":"ON",
    "wof:name":"Barn Restaurant",
    "wof:placetype":"venue"
},
  "geometry": {"coordinates":[-79.404533,43.647224],"type":"Point"}
}