{
  "type": "Feature",
  "properties": {
    "addr:full":"2132 Dundas St W Mississauga ON L5K 2K7",
    "addr:housenumber":"2132",
    "addr:postcode":"l5k 2k7",
    "addr:street":"Dundas St W",
    "iso:country":"CA",
    "sg:address":"2132 Dundas St W",
    "sg:city":"Mississauga",
    "sg:classifiers":[
        {
            "category":"Health Services",
            "subcategory":"Nursing And Care Facility",
            "type":"Services"
        }
    ],
    "sg:phone":"+1 905 823 7273",
    "sg:postcode":"L5K 2K7",
    "sg:province":"ON",
    "sg:tags":[
        "home",
        "convalescent"
    ],
    "wof:name":"Erin Mills Nursing Home West",
    "wof:placetype":"venue"
},
  "geometry": {"coordinates":[-79.668503,43.534599],"type":"Point"}
}