{
  "type": "Feature",
  "properties": {
    "addr:full":"410 114E Rue Shawinigan-Sud QC G9P 2X5",
    "addr:housenumber":"410",
    "addr:postcode":"g9p 2x5",
    "addr:street":"114E Rue Shawinigan-Sud",
    "iso:country":"CA",
    "sg:address":"410 114E Rue",
    "sg:city":"Shawinigan-Sud",
    "sg:classifiers":[
        {
            "category":"Wholesale",
            "subcategory":"Office Equipment",
            "type":"Manufacturing & Wholesale Goods"
        }
    ],
    "sg:phone":"+1 819 537 7482",
    "sg:postcode":"G9P 2X5",
    "sg:province":"QC",
    "sg:tags":[
        "accounting",
        "bookkeeping",
        "system"
    ],
    "wof:name":"Info-Gestion Val Des Chutes",
    "wof:placetype":"venue"
},
  "geometry": {"coordinates":[-72.7494888306,46.523979187],"type":"Point"}
}