{
  "type": "Feature",
  "properties": {
    "addr:full":"7 Paul St Picton ON K0K 2T0",
    "addr:housenumber":"7",
    "addr:postcode":"k0k 2t0",
    "addr:street":"Paul St",
    "iso:country":"CA",
    "sg:address":"7 Paul St",
    "sg:city":"Picton",
    "sg:classifiers":[
        {
            "category":"Personal",
            "subcategory":"Barber",
            "type":"Services"
        }
    ],
    "sg:phone":"+1 613 476 6962",
    "sg:postcode":"K0K 2T0",
    "sg:province":"ON",
    "wof:name":"Grahams Barber Shop & Family",
    "wof:placetype":"venue"
},
  "geometry": {"coordinates":[-77.1399307251,44.0096282959],"type":"Point"}
}