{
  "type": "Feature",
  "properties": {
    "addr:full":"Blumenort MB R0A 0C0",
    "addr:postcode":"r0a 0c0",
    "iso:country":"CA",
    "sg:city":"Blumenort",
    "sg:classifiers":[
        {
            "category":"Building & Trades",
            "subcategory":"Plumbing",
            "type":"Services"
        }
    ],
    "sg:phone":"+1 204 326 2979",
    "sg:postcode":"R0A 0C0",
    "sg:province":"MB",
    "sg:tags":[
        "conditioning",
        "air",
        "system",
        "contractor"
    ],
    "wof:name":"Bert's Refrigeration Svc",
    "wof:placetype":"venue"
},
  "geometry": {"coordinates":[-96.69016999999999,49.604256],"type":"Point"}
}