{
  "type": "Feature",
  "properties": {
    "addr:full":"7516 Portage Rd Niagara Falls ON L2E 6X8",
    "addr:housenumber":"7516",
    "addr:postcode":"l2e 6x8",
    "addr:street":"Portage Rd",
    "iso:country":"CA",
    "sg:address":"7516 Portage Rd",
    "sg:city":"Niagara Falls",
    "sg:classifiers":[
        {
            "category":"Recreation",
            "type":"Entertainment"
        }
    ],
    "sg:phone":"+1 905 358 6418",
    "sg:postcode":"L2E 6X8",
    "sg:province":"ON",
    "sg:tags":[
        "course",
        "golf"
    ],
    "wof:name":"Oak Hall Par 3 Golf Course",
    "wof:placetype":"venue"
},
  "geometry": {"coordinates":[-79.0724945068,43.0662002563],"type":"Point"}
}