{
  "type": "Feature",
  "properties": {
    "addr:full":"1281 Rue Notre-Dame Saint-Cesaire QC J0L 1T0",
    "addr:housenumber":"1281",
    "addr:postcode":"j0l 1t0",
    "addr:street":"Rue Notre-Dame Saint-Cesaire",
    "iso:country":"CA",
    "sg:address":"1281 Rue Notre-Dame",
    "sg:city":"Saint-Cesaire",
    "sg:classifiers":[
        {
            "category":"Insurance",
            "subcategory":"Insurance Agent",
            "type":"Services"
        }
    ],
    "sg:phone":"+1 450 469 3191",
    "sg:postcode":"J0L 1T0",
    "sg:province":"QC",
    "wof:name":"Bienvenu Assurances Inc",
    "wof:placetype":"venue"
},
  "geometry": {"coordinates":[-73.002045,45.41061],"type":"Point"}
}