{
  "type": "Feature",
  "properties": {
    "iso:country":"CA",
    "sg:address":"274 Rue Birch",
    "sg:city":"Chateauguay",
    "sg:classifiers":[
        {
            "category":"Building & Trades",
            "subcategory":"Construction",
            "type":"Services"
        }
    ],
    "sg:phone":"+1 450 698 0329",
    "sg:postcode":"J6J 3S8",
    "sg:province":"QC",
    "sg:tags":[
        "contractor"
    ],
    "wof:name":"Construction R Desgroseilliers",
    "wof:placetype":"venue"
},
  "geometry": {"coordinates":[-73.7306518555,45.377117157],"type":"Point"}
}