{
  "type": "Feature",
  "properties": {
    "addr:full":"222 2 St N Vauxhall AB T0K 2K0",
    "addr:housenumber":"222 2",
    "addr:postcode":"t0k 2k0",
    "addr:street":"St N",
    "iso:country":"CA",
    "sg:address":"222 2 St N",
    "sg:city":"Vauxhall",
    "sg:classifiers":[
        {
            "category":"Organizations",
            "subcategory":"Religious Organization",
            "type":"Services"
        }
    ],
    "sg:phone":"+1 403 654 2055",
    "sg:postcode":"T0K 2K0",
    "sg:province":"AB",
    "sg:tags":[
        "church"
    ],
    "wof:name":"Church of Jesus Christ of Lds",
    "wof:placetype":"venue"
},
  "geometry": {"coordinates":[-112.099434,50.068424],"type":"Point"}
}