{
  "type": "Feature",
  "properties": {
    "iso:country":"CA",
    "sg:address":"6461 Mississauga Rd",
    "sg:city":"Mississauga",
    "sg:classifiers":[
        {
            "category":"Restaurant",
            "type":"Food & Drink"
        }
    ],
    "sg:phone":"+1 905 821 4055",
    "sg:postcode":"L5N 1A6",
    "sg:province":"ON",
    "wof:name":"Skyway Jacks",
    "wof:placetype":"venue"
},
  "geometry": {"coordinates":[-79.736038,43.59795],"type":"Point"}
}