{
  "type": "Feature",
  "properties": {
    "iso:country":"CA",
    "sg:address":"5347 Ch Du Quai",
    "sg:city":"Lac-Kenogami",
    "sg:classifiers":[
        {
            "category":"Bars & Pubs",
            "type":"Food & Drink"
        }
    ],
    "sg:phone":"+1 418 542 5222",
    "sg:postcode":"G7X 7V6",
    "sg:province":"QC",
    "sg:tags":[
        "lounge",
        "cocktail"
    ],
    "wof:name":"Bar Le Blitz Enr",
    "wof:placetype":"venue"
},
  "geometry": {"coordinates":[-71.327995,48.353626],"type":"Point"}
}