{
  "type": "Feature",
  "properties": {
    "addr:full":"11003 107 Ave NW Edmonton AB T5H 0X6",
    "addr:housenumber":"11003",
    "addr:postcode":"t5h 0x6",
    "addr:street":"107 Ave Nw",
    "iso:country":"CA",
    "sg:address":"11003 107 Ave NW",
    "sg:city":"Edmonton",
    "sg:classifiers":[
        {
            "category":"Food & Beverages",
            "subcategory":"Groceries & Convenience Stores",
            "type":"Retail Goods"
        }
    ],
    "sg:phone":"+1 780 415 5276",
    "sg:postcode":"T5H 0X6",
    "sg:province":"AB",
    "sg:tags":[
        "grocer"
    ],
    "wof:name":"Kwiki Mart",
    "wof:placetype":"venue"
},
  "geometry": {"coordinates":[-113.510490417,53.5513000488],"type":"Point"}
}