{
  "type": "Feature",
  "properties": {
    "addr:full":"Winnipeg MB R2Y 2G9",
    "addr:postcode":"r2y 2g9",
    "iso:country":"CA",
    "sg:city":"Winnipeg",
    "sg:classifiers":[
        {
            "category":"Professional",
            "subcategory":"Management & Consulting",
            "type":"Services"
        }
    ],
    "sg:phone":"+1 204 831 7661",
    "sg:postcode":"R2Y 2G9",
    "sg:province":"MB",
    "sg:tags":[
        "consultant",
        "relation",
        "business",
        "labor"
    ],
    "wof:name":"Hill Advisory Svc",
    "wof:placetype":"venue"
},
  "geometry": {"coordinates":[-97.28469800000001,49.899937],"type":"Point"}
}