{
  "type": "Feature",
  "properties": {
    "addr:full":"Surrey BC V3W 5B9",
    "addr:postcode":"v3w 5b9",
    "iso:country":"CA",
    "sg:city":"Surrey",
    "sg:classifiers":[
        {
            "category":"Building & Trades",
            "subcategory":"Construction",
            "type":"Services"
        }
    ],
    "sg:phone":"+1 604 590 3131",
    "sg:postcode":"V3W 5B9",
    "sg:province":"BC",
    "sg:tags":[
        "general",
        "contractor"
    ],
    "wof:name":"Double V Construction Ltd",
    "wof:placetype":"venue"
},
  "geometry": {"coordinates":[-122.85392,49.144737],"type":"Point"}
}