{
  "type": "Feature",
  "properties": {
    "addr:full":"High Prairie AB T0G 1E0",
    "addr:postcode":"t0g 1e0",
    "iso:country":"CA",
    "sg:city":"High Prairie",
    "sg:classifiers":[
        {
            "category":"Sports & Exercise",
            "subcategory":"Golf",
            "type":"Entertainment"
        }
    ],
    "sg:phone":"+1 780 523 2696",
    "sg:postcode":"T0G 1E0",
    "sg:province":"AB",
    "sg:tags":[
        "course"
    ],
    "wof:name":"High Prairie Golf & Cntry Club",
    "wof:placetype":"venue"
},
  "geometry": {"coordinates":[-116.48042297400001,55.4328842163],"type":"Point"}
}