{
  "type": "Feature",
  "properties": {
    "addr:full":"320 Main St E Dundalk ON N0C 1B0",
    "addr:housenumber":"320",
    "addr:postcode":"n0c 1b0",
    "addr:street":"Main St E",
    "iso:country":"CA",
    "sg:address":"320 Main St E",
    "sg:city":"Dundalk",
    "sg:classifiers":[
        {
            "category":"Food & Beverages",
            "subcategory":"Groceries & Convenience Stores",
            "type":"Retail Goods"
        }
    ],
    "sg:phone":"+1 519 923 3630",
    "sg:postcode":"N0C 1B0",
    "sg:province":"ON",
    "sg:tags":[
        "grocer"
    ],
    "wof:name":"Dundalk Iga Foods",
    "wof:placetype":"venue"
},
  "geometry": {"coordinates":[-80.38904599999999,44.171883],"type":"Point"}
}