{
  "type": "Feature",
  "properties": {
    "addr:full":"288 Rue Principale Saint-Basile NB E7C 1H9",
    "addr:housenumber":"288",
    "addr:postcode":"e7c 1h9",
    "addr:street":"Rue Principale",
    "iso:country":"CA",
    "sg:address":"288 Rue Principale",
    "sg:city":"Saint-Basile",
    "sg:classifiers":[
        {
            "category":"Insurance",
            "subcategory":"Insurance Agent",
            "type":"Services"
        }
    ],
    "sg:phone":"+1 506 263 4455",
    "sg:postcode":"E7C 1H9",
    "sg:province":"NB",
    "wof:name":"Assurance Daigle Ltee",
    "wof:placetype":"venue"
},
  "geometry": {"coordinates":[-68.1958618164,47.4211044312],"type":"Point"}
}