{
  "type": "Feature",
  "properties": {
    "addr:full":"10803 100 St Grande Prairie AB T8V 2M7",
    "addr:housenumber":"10803",
    "addr:postcode":"t8v 2m7",
    "addr:street":"100 St",
    "iso:country":"CA",
    "sg:address":"10803 100 St",
    "sg:city":"Grande Prairie",
    "sg:classifiers":[
        {
            "category":"Shopping",
            "subcategory":"Florist",
            "type":"Retail Goods"
        }
    ],
    "sg:phone":"+1 780 539 4888",
    "sg:postcode":"T8V 2M7",
    "sg:province":"AB",
    "wof:name":"Flowers For Less",
    "wof:placetype":"venue"
},
  "geometry": {"coordinates":[-118.794631958,55.1780815125],"type":"Point"}
}