{
  "type": "Feature",
  "properties": {
    "addr:full":"114 Dunington Dr Scarborough ON M1N 3E6",
    "addr:housenumber":"114",
    "addr:postcode":"m1n 3e6",
    "addr:street":"Dunington Dr",
    "iso:country":"CA",
    "sg:address":"114 Dunington Dr",
    "sg:city":"Scarborough",
    "sg:classifiers":[
        {
            "category":"Building & Trades",
            "subcategory":"Construction",
            "type":"Services"
        }
    ],
    "sg:phone":"+1 416 694 2639",
    "sg:postcode":"M1N 3E6",
    "sg:province":"ON",
    "sg:tags":[
        "general",
        "contractor"
    ],
    "wof:name":"Greenwall Renovators",
    "wof:placetype":"venue"
},
  "geometry": {"coordinates":[-79.271553,43.691517],"type":"Point"}
}