{
  "type": "Feature",
  "properties": {
    "addr:full":"1465 Corydon Ave Winnipeg MB R3N 0J4",
    "addr:housenumber":"1465",
    "addr:postcode":"r3n 0j4",
    "addr:street":"Corydon Ave",
    "iso:country":"CA",
    "sg:address":"1465 Corydon Ave",
    "sg:city":"Winnipeg",
    "sg:classifiers":[
        {
            "category":"Insurance",
            "subcategory":"Insurance Agent",
            "type":"Services"
        }
    ],
    "sg:phone":"+1 204 488 4547",
    "sg:postcode":"R3N 0J4",
    "sg:province":"MB",
    "wof:name":"Turnbull Whitaker Insurance",
    "wof:placetype":"venue"
},
  "geometry": {"coordinates":[-97.1863708496,49.8635864258],"type":"Point"}
}