{
  "type": "Feature",
  "properties": {
    "addr:full":"4820 Watson Cresent Rd Swan Hills AB T0G 2C0",
    "addr:housenumber":"4820",
    "addr:postcode":"t0g 2c0",
    "addr:street":"Watson Cresent Rd",
    "iso:country":"CA",
    "sg:address":"4820 Watson Cresent Rd",
    "sg:city":"Swan Hills",
    "sg:classifiers":[
        {
            "category":"Building & Trades",
            "subcategory":"Equipment Rental",
            "type":"Services"
        }
    ],
    "sg:phone":"+1 780 333 2116",
    "sg:postcode":"T0G 2C0",
    "sg:province":"AB",
    "sg:tags":[
        "oil",
        "well",
        "supply"
    ],
    "wof:name":"Northwell Rentals Ltd",
    "wof:placetype":"venue"
},
  "geometry": {"coordinates":[-115.41317749,54.7186851501],"type":"Point"}
}