{
  "type": "Feature",
  "properties": {
    "addr:full":"181 Main St S Acton ON L7J 1Y1",
    "addr:housenumber":"181",
    "addr:postcode":"l7j 1y1",
    "addr:street":"Main St S Acton",
    "iso:country":"CA",
    "sg:address":"181 Main St S",
    "sg:city":"Acton",
    "sg:classifiers":[
        {
            "category":"Social Services",
            "subcategory":"Child Care",
            "type":"Services"
        }
    ],
    "sg:phone":"+1 905 877 7322",
    "sg:postcode":"L7J 1Y1",
    "sg:province":"ON",
    "sg:tags":[
        "kindergarten",
        "academic",
        "school"
    ],
    "wof:name":"Maple Nursery School",
    "wof:placetype":"venue"
},
  "geometry": {"coordinates":[-80.0353393555,43.6251602173],"type":"Point"}
}