{
  "type": "Feature",
  "properties": {
    "addr:full":"Saint-Eustache QC J7P 5G1",
    "addr:postcode":"j7p 5g1",
    "iso:country":"CA",
    "sg:city":"Saint-Eustache",
    "sg:classifiers":[
        {
            "category":"Personal",
            "subcategory":"Beauty Salon",
            "type":"Services"
        }
    ],
    "sg:phone":"+1 450 472 8247",
    "sg:postcode":"J7P 5G1",
    "sg:province":"QC",
    "wof:name":"Centre D'Esthetique L'Energie",
    "wof:placetype":"venue"
},
  "geometry": {"coordinates":[-73.884697,45.568771],"type":"Point"}
}