{
  "type": "Feature",
  "properties": {
    "addr:full":"Winnipeg MB R3B 0M5",
    "addr:postcode":"r3b 0m5",
    "iso:country":"CA",
    "sg:city":"Winnipeg",
    "sg:classifiers":[
        {
            "category":"Health Services",
            "subcategory":"Doctor",
            "type":"Services"
        }
    ],
    "sg:phone":"+1 204 949 9058",
    "sg:postcode":"R3B 0M5",
    "sg:province":"MB",
    "sg:tags":[
        "dentist"
    ],
    "wof:name":"Eng, Eileen DDS",
    "wof:placetype":"venue"
},
  "geometry": {"coordinates":[-97.13722229,49.9013671875],"type":"Point"}
}