{
  "type": "Feature",
  "properties": {
    "addr:full":"19 School Lane Sackville NB E4L 3J8",
    "addr:housenumber":"19",
    "addr:postcode":"e4l 3j8",
    "addr:street":"School Lane",
    "iso:country":"CA",
    "sg:address":"19 School Lane",
    "sg:city":"Sackville",
    "sg:classifiers":[
        {
            "category":"Home & Garden",
            "subcategory":"Garden Supply",
            "type":"Retail Goods"
        }
    ],
    "sg:phone":"+1 506 536 3094",
    "sg:postcode":"E4L 3J8",
    "sg:province":"NB",
    "sg:tags":[
        "center"
    ],
    "wof:name":"Anderson's Greenhouse",
    "wof:placetype":"venue"
},
  "geometry": {"coordinates":[-64.35895499999999,45.924522],"type":"Point"}
}