{
  "type": "Feature",
  "properties": {
    "addr:full":"455 Rue Chasse Drummondville QC J2C 4E5",
    "addr:housenumber":"455",
    "addr:postcode":"j2c 4e5",
    "addr:street":"Rue Chasse",
    "iso:country":"CA",
    "sg:address":"455 Rue Chasse",
    "sg:city":"Drummondville",
    "sg:classifiers":[
        {
            "category":"Wholesale",
            "subcategory":"Machinery & Supplies",
            "type":"Manufacturing & Wholesale Goods"
        }
    ],
    "sg:phone":"+1 819 477 5686",
    "sg:postcode":"J2C 4E5",
    "sg:province":"QC",
    "sg:tags":[
        "equipment",
        "pile",
        "driving"
    ],
    "wof:name":"D R Pilotech",
    "wof:placetype":"venue"
},
  "geometry": {"coordinates":[-72.4992675781,45.8825492859],"type":"Point"}
}