{
  "type": "Feature",
  "properties": {
    "addr:full":"3 Holomego Rd Kakabeka Falls ON P0T 1W0",
    "addr:housenumber":"3",
    "addr:postcode":"p0t 1w0",
    "addr:street":"Holomego Rd Kakabeka",
    "iso:country":"CA",
    "sg:address":"3 Holomego Rd",
    "sg:city":"Kakabeka Falls",
    "sg:classifiers":[
        {
            "category":"Organizations",
            "subcategory":"Religious Organization",
            "type":"Services"
        }
    ],
    "sg:phone":"+1 807 473 9362",
    "sg:postcode":"P0T 1W0",
    "sg:province":"ON",
    "sg:tags":[
        "church"
    ],
    "wof:name":"O'Connor Conmee Baptist Church",
    "wof:placetype":"venue"
},
  "geometry": {"coordinates":[-89.61456298829999,48.4017410278],"type":"Point"}
}