{
  "type": "Feature",
  "properties": {
    "addr:full":"507 Main St Bruno SK S0K 0S0",
    "addr:housenumber":"507",
    "addr:postcode":"s0k 0s0",
    "addr:street":"Main St Bruno",
    "iso:country":"CA",
    "sg:address":"507 Main St",
    "sg:city":"Bruno",
    "sg:classifiers":[
        {
            "category":"Shopping",
            "subcategory":"Catalog Store",
            "type":"Retail Goods"
        }
    ],
    "sg:phone":"+1 306 369 2900",
    "sg:postcode":"S0K 0S0",
    "sg:province":"SK",
    "sg:tags":[
        "mail",
        "order",
        "internet"
    ],
    "wof:name":"Sears Canada Inc",
    "wof:placetype":"venue"
},
  "geometry": {"coordinates":[-105.527122498,52.2653617859],"type":"Point"}
}