{
  "type": "Feature",
  "properties": {
    "addr:full":"149 Rue Principale S Maniwaki QC J9E 1Z8",
    "addr:housenumber":"149",
    "addr:postcode":"j9e 1z8",
    "addr:street":"Rue Principale S",
    "iso:country":"CA",
    "sg:address":"149 Rue Principale S",
    "sg:city":"Maniwaki",
    "sg:classifiers":[
        {
            "category":"Taxi",
            "type":"Transportation"
        }
    ],
    "sg:phone":"+1 819 449 1010",
    "sg:postcode":"J9E 1Z8",
    "sg:province":"QC",
    "sg:tags":[
        "taxicab"
    ],
    "wof:name":"Haute-Gatineau Taxi Enr",
    "wof:placetype":"venue"
},
  "geometry": {"coordinates":[-75.981483,46.375557],"type":"Point"}
}