{
  "type": "Feature",
  "properties": {
    "iso:country":"CA",
    "sg:address":"100 Park St #24",
    "sg:city":"Kitchener",
    "sg:classifiers":[
        {
            "category":"Retail",
            "subcategory":"Repair Shop",
            "type":"Services"
        }
    ],
    "sg:phone":"+1 519 741 1444",
    "sg:postcode":"N2G 1M6",
    "sg:province":"ON",
    "sg:tags":[
        "refinishing",
        "furniture"
    ],
    "wof:name":"Avalon Custom Woodworking",
    "wof:placetype":"venue"
},
  "geometry": {"coordinates":[-80.50342559809999,43.4490852356],"type":"Point"}
}