{
  "type": "Feature",
  "properties": {
    "addr:full":"261 Boul Antonio-Barrette Notre-Dame-Des-Prairies QC J6E 1G1",
    "addr:housenumber":"261",
    "addr:postcode":"j6e 1g1",
    "addr:street":"Boul Antonio-Barrette",
    "iso:country":"CA",
    "sg:address":"261 Boul Antonio-Barrette",
    "sg:city":"Notre-Dame-Des-Prairies",
    "sg:classifiers":[
        {
            "category":"Retail",
            "subcategory":"Auto Repair",
            "type":"Services"
        }
    ],
    "sg:phone":"+1 450 752 1045",
    "sg:postcode":"J6E 1G1",
    "sg:province":"QC",
    "sg:tags":[
        "repairing",
        "automobile"
    ],
    "wof:name":"Beaudry Garage Pierre Autopro",
    "wof:placetype":"venue"
},
  "geometry": {"coordinates":[-73.42720031739999,46.0455474854],"type":"Point"}
}