{
  "type": "Feature",
  "properties": {
    "addr:full":"274 Ch DE Saint-Jean LA Prairie QC J5R 2K3",
    "addr:housenumber":"274",
    "addr:postcode":"j5r 2k3",
    "addr:street":"Ch De Saint-Jean",
    "iso:country":"CA",
    "sg:address":"274 Ch DE Saint-Jean",
    "sg:city":"LA Prairie",
    "sg:classifiers":[
        {
            "category":"Personal",
            "subcategory":"Beauty Salon",
            "type":"Services"
        }
    ],
    "sg:phone":"+1 450 659 2457",
    "sg:postcode":"J5R 2K3",
    "sg:province":"QC",
    "wof:name":"Coiffure Micheline Mayer",
    "wof:placetype":"venue"
},
  "geometry": {"coordinates":[-73.4926071167,45.4185180664],"type":"Point"}
}