{
  "type": "Feature",
  "properties": {
    "addr:full":"352 Bayly St W Ajax ON L1S 1P1",
    "addr:housenumber":"352",
    "addr:postcode":"l1s 1p1",
    "addr:street":"Bayly St W",
    "iso:country":"CA",
    "sg:address":"352 Bayly St W",
    "sg:city":"Ajax",
    "sg:classifiers":[
        {
            "category":"Wholesale",
            "subcategory":"Sporting Goods",
            "type":"Manufacturing & Wholesale Goods"
        }
    ],
    "sg:phone":"+1 905 619 0017",
    "sg:postcode":"L1S 1P1",
    "sg:province":"ON",
    "wof:name":"Centre Distribution",
    "wof:placetype":"venue"
},
  "geometry": {"coordinates":[-79.031609,43.841187],"type":"Point"}
}