{
  "type": "Feature",
  "properties": {
    "addr:full":"45 Industrial Rd Leamington ON N8H 4W4",
    "addr:housenumber":"45",
    "addr:postcode":"n8h 4w4",
    "addr:street":"Industrial Rd",
    "iso:country":"CA",
    "sg:address":"45 Industrial Rd",
    "sg:city":"Leamington",
    "sg:classifiers":[
        {
            "category":"Manufacturing",
            "subcategory":"Printing",
            "type":"Manufacturing & Wholesale Goods"
        }
    ],
    "sg:phone":"+1 519 322 2679",
    "sg:postcode":"N8H 4W4",
    "sg:province":"ON",
    "sg:tags":[
        "printer"
    ],
    "wof:name":"Speedprint Ltd",
    "wof:placetype":"venue"
},
  "geometry": {"coordinates":[-82.60891700000001,42.047718],"type":"Point"}
}