{
  "type": "Feature",
  "properties": {
    "addr:full":"2444 Finch Ave W North York ON M9M 2E9",
    "addr:housenumber":"2444",
    "addr:postcode":"m9m 2e9",
    "addr:street":"Finch Ave W",
    "iso:country":"CA",
    "sg:address":"2444 Finch Ave W",
    "sg:city":"North York",
    "sg:classifiers":[
        {
            "category":"Food & Beverages",
            "subcategory":"Bakery",
            "type":"Retail Goods"
        }
    ],
    "sg:phone":"+1 416 746 6914",
    "sg:postcode":"M9M 2E9",
    "sg:province":"ON",
    "sg:tags":[
        "doughnut"
    ],
    "wof:name":"Country Style Donuts",
    "wof:placetype":"venue"
},
  "geometry": {"coordinates":[-79.5530166626,43.7499389648],"type":"Point"}
}