{
  "type": "Feature",
  "properties": {
    "iso:country":"CA",
    "sg:address":"400 Steeles Ave E",
    "sg:city":"Brampton",
    "sg:classifiers":[
        {
            "category":"Restaurant",
            "type":"Food & Drink"
        }
    ],
    "sg:phone":"+1 905 456 2093",
    "sg:postcode":"L6W 3R2",
    "sg:province":"ON",
    "wof:name":"Brewster's Roadhouse & Rstrnt",
    "wof:placetype":"venue"
},
  "geometry": {"coordinates":[-79.72309112550001,43.6754608154],"type":"Point"}
}