{
  "type": "Feature",
  "properties": {
    "addr:full":"996 Eastlawn Ave Windsor ON N8S 3H9",
    "addr:housenumber":"996",
    "addr:postcode":"n8s 3h9",
    "addr:street":"Eastlawn Ave",
    "iso:country":"CA",
    "sg:address":"996 Eastlawn Ave",
    "sg:city":"Windsor",
    "sg:classifiers":[
        {
            "category":"Building & Trades",
            "subcategory":"Construction",
            "type":"Services"
        }
    ],
    "sg:phone":"+1 519 944 7257",
    "sg:postcode":"N8S 3H9",
    "sg:province":"ON",
    "sg:tags":[
        "dry wall",
        "contractor"
    ],
    "wof:name":"Drywall Connection",
    "wof:placetype":"venue"
},
  "geometry": {"coordinates":[-82.94458,42.328381],"type":"Point"}
}