{
  "type": "Feature",
  "properties": {
    "addr:full":"Victoria BC V8Z 2A7",
    "addr:postcode":"v8z 2a7",
    "iso:country":"CA",
    "sg:city":"Victoria",
    "sg:classifiers":[
        {
            "category":"Professional",
            "subcategory":"Management & Consulting",
            "type":"Services"
        }
    ],
    "sg:phone":"+1 250 479 8505",
    "sg:postcode":"V8Z 2A7",
    "sg:province":"BC",
    "sg:tags":[
        "party",
        "planning"
    ],
    "wof:name":"Rights of Passage Event Plng",
    "wof:placetype":"venue"
},
  "geometry": {"coordinates":[-123.35633900000001,48.414982],"type":"Point"}
}