{
  "type": "Feature",
  "properties": {
    "addr:full":"170 Bristol Ave # 398 Liverpool NS B0T 1K0",
    "addr:housenumber":"170",
    "addr:postcode":"b0t 1k0",
    "addr:street":"Bristol Ave # 398",
    "iso:country":"CA",
    "sg:address":"170 Bristol Ave # 398",
    "sg:city":"Liverpool",
    "sg:classifiers":[
        {
            "category":"Food & Beverages",
            "subcategory":"Bakery",
            "type":"Retail Goods"
        }
    ],
    "sg:phone":"+1 902 354 2719",
    "sg:postcode":"B0T 1K0",
    "sg:province":"NS",
    "sg:tags":[
        "tea",
        "coffee",
        "doughnut"
    ],
    "wof:name":"Tim Hortons",
    "wof:placetype":"venue"
},
  "geometry": {"coordinates":[-64.72225952150001,44.0455131531],"type":"Point"}
}