{
  "type": "Feature",
  "properties": {
    "addr:full":"Thunder Bay ON P7E 6H8",
    "addr:postcode":"p7e 6h8",
    "iso:country":"CA",
    "sg:city":"Thunder Bay",
    "sg:classifiers":[
        {
            "category":"Professional",
            "subcategory":"Business Services",
            "type":"Services"
        }
    ],
    "sg:phone":"+1 807 626 9626",
    "sg:postcode":"P7E 6H8",
    "sg:province":"ON",
    "sg:tags":[
        "information",
        "referral",
        "government"
    ],
    "wof:name":"Thunder Bay Comm Info Ctr",
    "wof:placetype":"venue"
},
  "geometry": {"coordinates":[-89.247963,48.382175],"type":"Point"}
}