{
  "type": "Feature",
  "properties": {
    "iso:country":"CA",
    "sg:address":"242 Rue Saint-Robert",
    "sg:city":"Matane",
    "sg:classifiers":[
        {
            "category":"Personal",
            "subcategory":"Beauty Salon",
            "type":"Services"
        }
    ],
    "sg:phone":"+1 418 562 1995",
    "sg:postcode":"G4W 1B8",
    "sg:province":"QC",
    "wof:name":"L'Ynedit",
    "wof:placetype":"venue"
},
  "geometry": {"coordinates":[-67.5149688721,48.8505363464],"type":"Point"}
}