{
  "type": "Feature",
  "properties": {
    "iso:country":"CA",
    "sg:address":"19355 Enterprise Way",
    "sg:city":"Surrey",
    "sg:classifiers":[
        {
            "category":"Wholesale",
            "subcategory":"Metals & Minerals",
            "type":"Manufacturing & Wholesale Goods"
        }
    ],
    "sg:phone":"+1 604 514 0413",
    "sg:postcode":"V3S 6J8",
    "sg:province":"BC",
    "sg:tags":[
        "rope",
        "equipment",
        "wire",
        "log",
        "splitting"
    ],
    "wof:name":"Pacific Wire Rope Ltd",
    "wof:placetype":"venue"
},
  "geometry": {"coordinates":[-122.687363,49.108932],"type":"Point"}
}