{
  "type": "Feature",
  "properties": {
    "addr:full":"612 O'Connor Dr Kingston ON K7P 1N3",
    "addr:housenumber":"612",
    "addr:postcode":"k7p 1n3",
    "addr:street":"O'Connor Dr",
    "iso:country":"CA",
    "sg:address":"612 O'Connor Dr",
    "sg:city":"Kingston",
    "sg:classifiers":[
        {
            "category":"Shopping",
            "subcategory":"Computers & Home Electronics",
            "type":"Retail Goods"
        }
    ],
    "sg:phone":"+1 613 389 8877",
    "sg:postcode":"K7P 1N3",
    "sg:province":"ON",
    "sg:tags":[
        "television",
        "radio"
    ],
    "wof:name":"Colborne's Tv & Stereo Ltd",
    "wof:placetype":"venue"
},
  "geometry": {"coordinates":[-76.566086,44.259853],"type":"Point"}
}