{
  "type": "Feature",
  "properties": {
    "addr:full":"19669 Willowbrook Dr Langley BC V2Y 1A5",
    "addr:housenumber":"19669",
    "addr:postcode":"v2y 1a5",
    "addr:street":"Willowbrook Dr",
    "iso:country":"CA",
    "sg:address":"19669 Willowbrook Dr",
    "sg:city":"Langley",
    "sg:classifiers":[
        {
            "category":"Home & Garden",
            "subcategory":"Carpets & Floor Coverings",
            "type":"Retail Goods"
        }
    ],
    "sg:phone":"+1 604 532 8483",
    "sg:postcode":"V2Y 1A5",
    "sg:province":"BC",
    "sg:tags":[
        "dealer",
        "rug"
    ],
    "wof:name":"End of the Roll",
    "wof:placetype":"venue"
},
  "geometry": {"coordinates":[-122.678726196,49.1160736084],"type":"Point"}
}