{
  "type": "Feature",
  "properties": {
    "addr:full":"Edmonton AB T5G 0X5",
    "addr:postcode":"t5g 0x5",
    "iso:country":"CA",
    "sg:city":"Edmonton",
    "sg:classifiers":[
        {
            "category":"Organizations",
            "subcategory":"Professional Association",
            "type":"Services"
        }
    ],
    "sg:phone":"+1 780 455 2200",
    "sg:postcode":"T5G 0X5",
    "sg:province":"AB",
    "wof:name":"Metis Association of Alberta",
    "wof:placetype":"venue"
},
  "geometry": {"coordinates":[-113.521987915,53.5671882629],"type":"Point"}
}