{
  "type": "Feature",
  "properties": {
    "addr:full":"405 Victoria Ave Windsor ON N9A 4N1",
    "addr:housenumber":"405",
    "addr:postcode":"n9a 4n1",
    "addr:street":"Victoria Ave",
    "iso:country":"CA",
    "sg:address":"405 Victoria Ave",
    "sg:city":"Windsor",
    "sg:classifiers":[
        {
            "category":"Organizations",
            "subcategory":"Religious Organization",
            "type":"Services"
        }
    ],
    "sg:phone":"+1 519 977 6565",
    "sg:postcode":"N9A 4N1",
    "sg:province":"ON",
    "sg:tags":[
        "church"
    ],
    "wof:name":"Windsor Chinese Presbyterian",
    "wof:placetype":"venue"
},
  "geometry": {"coordinates":[-83.04033660890001,42.3155288696],"type":"Point"}
}