{
  "type": "Feature",
  "properties": {
    "addr:full":"Saskatoon SK S7M 2C9",
    "addr:postcode":"s7m 2c9",
    "iso:country":"CA",
    "sg:city":"Saskatoon",
    "sg:classifiers":[
        {
            "category":"Building & Trades",
            "subcategory":"Construction",
            "type":"Services"
        }
    ],
    "sg:phone":"+1 306 244 0192",
    "sg:postcode":"S7M 2C9",
    "sg:province":"SK",
    "sg:tags":[
        "maker",
        "cabinet"
    ],
    "wof:name":"C & T Cabinet Exchange",
    "wof:placetype":"venue"
},
  "geometry": {"coordinates":[-106.686104,52.125832],"type":"Point"}
}