{
  "type": "Feature",
  "properties": {
    "addr:full":"56 Cayuga Ave Mississauga ON L5G 3S9",
    "addr:housenumber":"56",
    "addr:postcode":"l5g 3s9",
    "addr:street":"Cayuga Ave",
    "iso:country":"CA",
    "sg:address":"56 Cayuga Ave",
    "sg:city":"Mississauga",
    "sg:classifiers":[
        {
            "category":"Education",
            "subcategory":"School",
            "type":"Public Place"
        }
    ],
    "sg:phone":"+1 905 271 7100",
    "sg:postcode":"L5G 3S9",
    "sg:province":"ON",
    "wof:name":"Mentor College",
    "wof:placetype":"venue"
},
  "geometry": {"coordinates":[-79.57819366459999,43.5628013611],"type":"Point"}
}