{
  "type": "Feature",
  "properties": {
    "addr:full":"900 Rathburn Rd W # D6 Mississauga ON L5C 4L3",
    "addr:housenumber":"900",
    "addr:postcode":"l5c 4l3",
    "addr:street":"Rathburn Rd W # D6",
    "iso:country":"CA",
    "sg:address":"900 Rathburn Rd W # D6",
    "sg:city":"Mississauga",
    "sg:classifiers":[
        {
            "category":"Food & Beverages",
            "subcategory":"Bakery",
            "type":"Retail Goods"
        }
    ],
    "sg:phone":"+1 905 615 1999",
    "sg:postcode":"L5C 4L3",
    "sg:province":"ON",
    "sg:tags":[
        "baker"
    ],
    "wof:name":"Old Mill Bakery & Deli",
    "wof:placetype":"venue"
},
  "geometry": {"coordinates":[-79.6608886719,43.5788955688],"type":"Point"}
}