{
  "type": "Feature",
  "properties": {
    "addr:full":"1230 North Shore Blvd E Burlington ON L7S 1W7",
    "addr:housenumber":"1230",
    "addr:postcode":"l7s 1w7",
    "addr:street":"North Shore Blvd E",
    "iso:country":"CA",
    "sg:address":"1230 North Shore Blvd E",
    "sg:city":"Burlington",
    "sg:classifiers":[
        {
            "category":"Health Services",
            "subcategory":"Hospital",
            "type":"Services"
        }
    ],
    "sg:phone":"+1 905 632 3730",
    "sg:postcode":"L7S 1W7",
    "sg:province":"ON",
    "wof:name":"Joseph Brant Memorial Hospital",
    "wof:placetype":"venue"
},
  "geometry": {"coordinates":[-79.80341300000001,43.317741],"type":"Point"}
}