{
  "type": "Feature",
  "properties": {
    "addr:full":"4747 67 St Red Deer AB T4N 6H3",
    "addr:housenumber":"4747",
    "addr:postcode":"t4n 6h3",
    "addr:street":"67 St",
    "iso:country":"CA",
    "sg:address":"4747 67 St",
    "sg:city":"Red Deer",
    "sg:classifiers":[
        {
            "category":"Banks & Credit Unions",
            "subcategory":"Investment Brokerage",
            "type":"Services"
        }
    ],
    "sg:phone":"+1 403 341 4702",
    "sg:postcode":"T4N 6H3",
    "sg:province":"AB",
    "sg:tags":[
        "consultant",
        "planning",
        "financial"
    ],
    "wof:name":"Summit Wealth Management",
    "wof:placetype":"venue"
},
  "geometry": {"coordinates":[-113.801552,52.28751],"type":"Point"}
}