{
  "type": "Feature",
  "properties": {
    "addr:full":"Hwy 37 Iskut BC V0J 1K0",
    "addr:postcode":"v0j 1k0",
    "addr:street":"Hwy 37",
    "iso:country":"CA",
    "sg:address":"Hwy 37",
    "sg:city":"Iskut",
    "sg:classifiers":[
        {
            "category":"Travel",
            "subcategory":"Hotels & Motels",
            "type":"Entertainment"
        }
    ],
    "sg:phone":"+1 250 234 3141",
    "sg:postcode":"V0J 1K0",
    "sg:province":"BC",
    "wof:name":"Tenajon Motel",
    "wof:placetype":"venue"
},
  "geometry": {"coordinates":[-129.98321533199999,57.8336105347],"type":"Point"}
}