{
  "type": "Feature",
  "properties": {
    "addr:full":"375 Wilson St E Ancaster ON L9G 2C1",
    "addr:housenumber":"375",
    "addr:postcode":"l9g 2c1",
    "addr:street":"Wilson St E",
    "iso:country":"CA",
    "sg:address":"375 Wilson St E",
    "sg:city":"Ancaster",
    "sg:classifiers":[
        {
            "category":"Restaurant",
            "type":"Food & Drink"
        }
    ],
    "sg:phone":"+1 905 648 8863",
    "sg:postcode":"L9G 2C1",
    "sg:province":"ON",
    "wof:name":"Rousseau House Restaurant",
    "wof:placetype":"venue"
},
  "geometry": {"coordinates":[-79.976028,43.227722],"type":"Point"}
}