{
  "type": "Feature",
  "properties": {
    "addr:full":"116 George St Brantford ON N3T 2Y6",
    "addr:housenumber":"116",
    "addr:postcode":"n3t 2y6",
    "addr:street":"George St",
    "iso:country":"CA",
    "sg:address":"116 George St",
    "sg:city":"Brantford",
    "sg:classifiers":[
        {
            "category":"Health Services",
            "subcategory":"Hospital",
            "type":"Services"
        }
    ],
    "sg:phone":"+1 519 756 4400",
    "sg:postcode":"N3T 2Y6",
    "sg:province":"ON",
    "sg:tags":[
        "mental"
    ],
    "wof:name":"George Street Residence",
    "wof:placetype":"venue"
},
  "geometry": {"coordinates":[-80.2630157471,43.1432723999],"type":"Point"}
}