{
  "type": "Feature",
  "properties": {
    "addr:full":"165 Industrial Rd 3 Sparwood BC V0B 2G1",
    "addr:housenumber":"165",
    "addr:postcode":"bc v0b 2g1",
    "addr:street":"Industrial Rd 3",
    "iso:country":"CA",
    "sg:address":"165 Industrial Rd 3",
    "sg:city":"Sparwood",
    "sg:classifiers":[
        {
            "category":"Building & Trades",
            "subcategory":"Construction",
            "type":"Services"
        }
    ],
    "sg:phone":"+1 250 425 6231",
    "sg:postcode":"V0B 2G1",
    "sg:province":"BC",
    "sg:tags":[
        "erectors",
        "general",
        "contractor"
    ],
    "wof:name":"Sil Maintenance Inc",
    "wof:placetype":"venue"
},
  "geometry": {"coordinates":[-114.88441467299999,49.7434654236],"type":"Point"}
}