{
  "type": "Feature",
  "properties": {
    "addr:full":"Meteghan NS B0W 2J0",
    "addr:postcode":"b0w 2j0",
    "iso:country":"CA",
    "sg:city":"Meteghan",
    "sg:classifiers":[
        {
            "category":"Manufacturing",
            "subcategory":"Wood Products",
            "type":"Manufacturing & Wholesale Goods"
        }
    ],
    "sg:phone":"+1 902 645 2310",
    "sg:postcode":"B0W 2J0",
    "sg:province":"NS",
    "sg:tags":[
        "box"
    ],
    "wof:name":"Comeau Lumber",
    "wof:placetype":"venue"
},
  "geometry": {"coordinates":[-66.160393,44.188843],"type":"Point"}
}