{
  "type": "Feature",
  "properties": {
    "addr:full":"720 Boul Decarie Saint-Laurent QC H4L 3L5",
    "addr:housenumber":"720",
    "addr:postcode":"h4l 3l5",
    "addr:street":"Boul Decarie",
    "iso:country":"CA",
    "sg:address":"720 Boul Decarie",
    "sg:city":"Saint-Laurent",
    "sg:classifiers":[
        {
            "category":"Manufacturing",
            "subcategory":"Printing",
            "type":"Manufacturing & Wholesale Goods"
        }
    ],
    "sg:phone":"+1 514 748 2923",
    "sg:postcode":"H4L 3L5",
    "sg:province":"QC",
    "sg:tags":[
        "publisher",
        "guide"
    ],
    "wof:name":"Infosearch Publications",
    "wof:placetype":"venue"
},
  "geometry": {"coordinates":[-73.67742919920001,45.5106506348],"type":"Point"}
}