{
  "type": "Feature",
  "properties": {
    "addr:full":"Dartmouth NS B3B 1T4",
    "addr:postcode":"b3b 1t4",
    "iso:country":"CA",
    "sg:city":"Dartmouth",
    "sg:classifiers":[
        {
            "category":"Home & Garden",
            "subcategory":"Household Appliances",
            "type":"Retail Goods"
        }
    ],
    "sg:phone":"+1 902 468 5483",
    "sg:postcode":"B3B 1T4",
    "sg:province":"NS",
    "sg:tags":[
        "lighting",
        "fixture"
    ],
    "wof:name":"Classic Lighting",
    "wof:placetype":"venue"
},
  "geometry": {"coordinates":[-63.5878334045,44.7030715942],"type":"Point"}
}