{
  "type": "Feature",
  "properties": {
    "iso:country":"CA",
    "sg:address":"873 Francis Ave",
    "sg:city":"Kelowna",
    "sg:classifiers":[
        {
            "category":"Building & Trades",
            "subcategory":"Construction",
            "type":"Services"
        }
    ],
    "sg:phone":"+1 250 860 1126",
    "sg:postcode":"V1Y 5G6",
    "sg:province":"BC",
    "sg:tags":[
        "painter"
    ],
    "wof:name":"Galley & Son Painting",
    "wof:placetype":"venue"
},
  "geometry": {"coordinates":[-119.48391,49.869873],"type":"Point"}
}