{
  "type": "Feature",
  "properties": {
    "addr:full":"85 Rue Saint-Charles O Longueuil QC J4H 1C5",
    "addr:housenumber":"85",
    "addr:postcode":"j4h 1c5",
    "addr:street":"Rue Saint-Charles O",
    "iso:country":"CA",
    "sg:address":"85 Rue Saint-Charles O",
    "sg:city":"Longueuil",
    "sg:classifiers":[
        {
            "category":"Real Estate",
            "subcategory":"Real Estate Agent",
            "type":"Services"
        }
    ],
    "sg:phone":"+1 450 928 1141",
    "sg:postcode":"J4H 1C5",
    "sg:province":"QC",
    "sg:tags":[
        "desk",
        "management",
        "space"
    ],
    "wof:name":"Centre D'Affaires Du Vieux",
    "wof:placetype":"venue"
},
  "geometry": {"coordinates":[-73.507828,45.541626],"type":"Point"}
}