{
  "type": "Feature",
  "properties": {
    "addr:full":"2 Main St N Hagersville ON N0A 1H0",
    "addr:housenumber":"2",
    "addr:postcode":"n0a 1h0",
    "addr:street":"Main St N",
    "iso:country":"CA",
    "sg:address":"2 Main St N",
    "sg:city":"Hagersville",
    "sg:classifiers":[
        {
            "category":"Shopping",
            "subcategory":"Department Store",
            "type":"Retail Goods"
        }
    ],
    "sg:phone":"+1 905 768 0777",
    "sg:postcode":"N0A 1H0",
    "sg:province":"ON",
    "sg:tags":[
        "shop"
    ],
    "wof:name":"Galaxy Dollar Store",
    "wof:placetype":"venue"
},
  "geometry": {"coordinates":[-80.05139200000001,42.962101],"type":"Point"}
}