{
  "type": "Feature",
  "properties": {
    "addr:full":"Oakville ON L6K 3W4",
    "addr:postcode":"l6k 3w4",
    "iso:country":"CA",
    "sg:city":"Oakville",
    "sg:classifiers":[
        {
            "category":"Building & Trades",
            "subcategory":"Construction",
            "type":"Services"
        }
    ],
    "sg:phone":"+1 905 842 2543",
    "sg:postcode":"L6K 3W4",
    "sg:province":"ON",
    "sg:tags":[
        "concrete",
        "contractor"
    ],
    "wof:name":"Lee Rocca Forming Ltd",
    "wof:placetype":"venue"
},
  "geometry": {"coordinates":[-79.69547271730001,43.4413986206],"type":"Point"}
}