{
  "type": "Feature",
  "properties": {
    "iso:country":"CA",
    "sg:address":"5645 Morrison St",
    "sg:city":"Niagara Falls",
    "sg:classifiers":[
        {
            "category":"Organizations",
            "subcategory":"Religious Organization",
            "type":"Services"
        }
    ],
    "sg:phone":"+1 905 356 1624",
    "sg:postcode":"L2E 2E8",
    "sg:province":"ON",
    "sg:tags":[
        "church"
    ],
    "wof:name":"St Andrew's United Church",
    "wof:placetype":"venue"
},
  "geometry": {"coordinates":[-79.0876922607,43.1045722961],"type":"Point"}
}