{
  "type": "Feature",
  "properties": {
    "addr:full":"Vancouver BC V5S 1Z1",
    "addr:postcode":"v5s 1z1",
    "iso:country":"CA",
    "sg:city":"Vancouver",
    "sg:classifiers":[
        {
            "category":"Food & Beverages",
            "subcategory":"Liquor & Beverages",
            "type":"Retail Goods"
        }
    ],
    "sg:phone":"+1 604 660 1277",
    "sg:postcode":"V5S 1Z1",
    "sg:province":"BC",
    "sg:tags":[
        "store"
    ],
    "wof:name":"Liquor Stores-Government",
    "wof:placetype":"venue"
},
  "geometry": {"coordinates":[-123.04016876199999,49.2200431824],"type":"Point"}
}