{
  "type": "Feature",
  "properties": {
    "iso:country":"CA",
    "sg:city":"Dunnville",
    "sg:classifiers":[
        {
            "category":"Shopping",
            "subcategory":"Pharmacy",
            "type":"Retail Goods"
        }
    ],
    "sg:phone":"+1 905 774 7766",
    "sg:postcode":"N1A 2W4",
    "sg:province":"ON",
    "sg:tags":[
        "aid",
        "first",
        "supply"
    ],
    "wof:name":"International Stretcher System",
    "wof:placetype":"venue"
},
  "geometry": {"coordinates":[-79.5669937134,42.9241333008],"type":"Point"}
}