{
  "type": "Feature",
  "properties": {
    "addr:full":"Etobicoke ON M9C 2Y3",
    "addr:postcode":"m9c 2y3",
    "iso:country":"CA",
    "sg:city":"Etobicoke",
    "sg:classifiers":[
        {
            "category":"Health Services",
            "subcategory":"Health Practitioner",
            "type":"Services"
        }
    ],
    "sg:phone":"+1 416 695 2132",
    "sg:postcode":"M9C 2Y3",
    "sg:province":"ON",
    "sg:tags":[
        "acupuncture"
    ],
    "wof:name":"Chinese Medicine & Acupuncture",
    "wof:placetype":"venue"
},
  "geometry": {"coordinates":[-79.568321228,43.6444702148],"type":"Point"}
}