{
  "type": "Feature",
  "properties": {
    "addr:full":"600 Railway St Davidson SK S0G 1A0",
    "addr:housenumber":"600",
    "addr:postcode":"s0g 1a0",
    "addr:street":"Railway St",
    "iso:country":"CA",
    "sg:address":"600 Railway St",
    "sg:city":"Davidson",
    "sg:classifiers":[
        {
            "category":"Building & Trades",
            "subcategory":"Plumbing",
            "type":"Services"
        }
    ],
    "sg:phone":"+1 306 567 3202",
    "sg:postcode":"S0G 1A0",
    "sg:province":"SK",
    "sg:tags":[
        "heating",
        "contractor"
    ],
    "wof:name":"Schmiedge Plumbing & Heating",
    "wof:placetype":"venue"
},
  "geometry": {"coordinates":[-105.995987,51.267365],"type":"Point"}
}