{
  "type": "Feature",
  "properties": {
    "addr:full":"2150 Av Deblois Beauport QC G1E 3V7",
    "addr:housenumber":"2150",
    "addr:postcode":"qc g1e 3v7",
    "addr:street":"Av Deblois",
    "iso:country":"CA",
    "sg:address":"2150 Av Deblois",
    "sg:city":"Beauport",
    "sg:classifiers":[
        {
            "category":"Retail",
            "subcategory":"Funeral Services",
            "type":"Services"
        }
    ],
    "sg:phone":"+1 418 529 3371",
    "sg:postcode":"G1E 3V7",
    "sg:province":"QC",
    "sg:tags":[
        "director"
    ],
    "wof:name":"Lepine-Cloutier Ltee",
    "wof:placetype":"venue"
},
  "geometry": {"coordinates":[-71.2123641968,46.8501548767],"type":"Point"}
}