{
  "type": "Feature",
  "properties": {
    "addr:full":"115 DE LA Fabrique Sainte-Lucie-DE-Beauregard QC G0R 3L0",
    "addr:housenumber":"115",
    "addr:postcode":"g0r 3l0",
    "addr:street":"De La Fabrique",
    "iso:country":"CA",
    "sg:address":"115 DE LA Fabrique",
    "sg:city":"Sainte-Lucie-DE-Beauregard",
    "sg:classifiers":[
        {
            "category":"Recreation",
            "type":"Entertainment"
        }
    ],
    "sg:phone":"+1 418 636 2263",
    "sg:postcode":"G0R 3L0",
    "sg:province":"QC",
    "sg:tags":[
        "center"
    ],
    "wof:name":"Chalet Des Sports",
    "wof:placetype":"venue"
},
  "geometry": {"coordinates":[-70.02267500000001,46.738033],"type":"Point"}
}