{
  "type": "Feature",
  "properties": {
    "iso:country":"CA",
    "sg:city":"Saint-Pierre-Les-Becquets",
    "sg:classifiers":[
        {
            "category":"Retail",
            "subcategory":"Auto Repair",
            "type":"Services"
        }
    ],
    "sg:phone":"+1 819 263 2921",
    "sg:postcode":"G0X 2Z0",
    "sg:province":"QC",
    "sg:tags":[
        "repairing",
        "automobile"
    ],
    "wof:name":"Garage Michel Lavigne",
    "wof:placetype":"venue"
},
  "geometry": {"coordinates":[-72.1851272583,46.5142173767],"type":"Point"}
}