{
  "type": "Feature",
  "properties": {
    "addr:full":"1365 Montee Masson Laval QC H7E 4P2",
    "addr:housenumber":"1365",
    "addr:postcode":"h7e 4p2",
    "addr:street":"Montee Masson",
    "iso:country":"CA",
    "sg:address":"1365 Montee Masson",
    "sg:city":"Laval",
    "sg:classifiers":[
        {
            "category":"Recreation",
            "type":"Entertainment"
        }
    ],
    "sg:phone":"+1 450 661 2544",
    "sg:postcode":"H7E 4P2",
    "sg:province":"QC",
    "sg:tags":[
        "hall",
        "auditorium"
    ],
    "wof:name":"Bellavista Restaurant",
    "wof:placetype":"venue"
},
  "geometry": {"coordinates":[-73.6423110962,45.6405258179],"type":"Point"}
}