{
  "type": "Feature",
  "properties": {
    "addr:full":"3288 Main St Vancouver BC V5V 3M5",
    "addr:housenumber":"3288",
    "addr:postcode":"v5v 3m5",
    "addr:street":"Main St",
    "iso:country":"CA",
    "sg:address":"3288 Main St",
    "sg:city":"Vancouver",
    "sg:classifiers":[
        {
            "category":"Shopping",
            "subcategory":"Used Merchandise",
            "type":"Retail Goods"
        }
    ],
    "sg:phone":"+1 604 874 5550",
    "sg:postcode":"V5V 3M5",
    "sg:province":"BC",
    "sg:tags":[
        "shop",
        "second",
        "consignment",
        "store",
        "hand"
    ],
    "wof:name":"Echo-Unique Resale",
    "wof:placetype":"venue"
},
  "geometry": {"coordinates":[-123.101013184,49.2559051514],"type":"Point"}
}