{
  "type": "Feature",
  "properties": {
    "addr:full":"1420 Ernest Ave London ON N6E 2H8",
    "addr:housenumber":"1420",
    "addr:postcode":"n6e 2h8",
    "addr:street":"Ernest Ave",
    "iso:country":"CA",
    "sg:address":"1420 Ernest Ave",
    "sg:city":"London",
    "sg:classifiers":[
        {
            "category":"Personal",
            "subcategory":"Beauty Salon",
            "type":"Services"
        }
    ],
    "sg:phone":"+1 519 686 7540",
    "sg:postcode":"N6E 2H8",
    "sg:province":"ON",
    "wof:name":"Short & Classy",
    "wof:placetype":"venue"
},
  "geometry": {"coordinates":[-81.236313,42.932938],"type":"Point"}
}