{
  "type": "Feature",
  "properties": {
    "addr:full":"Banff AB T1L 1A8",
    "addr:postcode":"t1l 1a8",
    "iso:country":"CA",
    "sg:city":"Banff",
    "sg:classifiers":[
        {
            "category":"Shopping",
            "subcategory":"Bicycles & Sporting Goods",
            "type":"Retail Goods"
        }
    ],
    "sg:phone":"+1 403 760 1650",
    "sg:postcode":"T1L 1A8",
    "sg:province":"AB",
    "sg:tags":[
        "equipment",
        "skiing"
    ],
    "wof:name":"Ski Stop",
    "wof:placetype":"venue"
},
  "geometry": {"coordinates":[-115.572624,51.176853],"type":"Point"}
}