{
  "type": "Feature",
  "properties": {
    "addr:full":"167 Bakers Lane Windham Centre ON N0E 2A0",
    "addr:housenumber":"167",
    "addr:postcode":"n0e 2a0",
    "addr:street":"Bakers Lane Windham",
    "iso:country":"CA",
    "sg:address":"167 Bakers Lane",
    "sg:city":"Windham Centre",
    "sg:classifiers":[
        {
            "category":"Freight",
            "type":"Transportation"
        }
    ],
    "sg:phone":"+1 519 443 5664",
    "sg:postcode":"N0E 2A0",
    "sg:province":"ON",
    "sg:tags":[
        "grain",
        "elevator"
    ],
    "wof:name":"DE Pauw Elevators",
    "wof:placetype":"venue"
},
  "geometry": {"coordinates":[-80.400063,42.915516],"type":"Point"}
}