{
  "type": "Feature",
  "properties": {
    "addr:full":"42 Villa Dr Little Bras D'Or NS B1Y 2X1",
    "addr:housenumber":"42",
    "addr:postcode":"b1y 2x1",
    "addr:street":"Villa Dr",
    "iso:country":"CA",
    "sg:address":"42 Villa Dr",
    "sg:city":"Little Bras D'Or",
    "sg:classifiers":[
        {
            "category":"Retail",
            "subcategory":"Repair Shop",
            "type":"Services"
        }
    ],
    "sg:phone":"+1 902 736 9771",
    "sg:postcode":"B1Y 2X1",
    "sg:province":"NS",
    "sg:tags":[
        "taxidermist"
    ],
    "wof:name":"Grant Mac Leod Freeze-Dried",
    "wof:placetype":"venue"
},
  "geometry": {"coordinates":[-63.587551,44.727379],"type":"Point"}
}