{
  "type": "Feature",
  "properties": {
    "addr:full":"300 King St E Toronto ON M5A 1K4",
    "addr:housenumber":"300",
    "addr:postcode":"m5a 1k4",
    "addr:street":"King St E",
    "iso:country":"CA",
    "sg:address":"300 King St E",
    "sg:city":"Toronto",
    "sg:classifiers":[
        {
            "category":"Manufacturing",
            "subcategory":"Furniture",
            "type":"Manufacturing & Wholesale Goods"
        }
    ],
    "sg:phone":"+1 416 362 3434",
    "sg:postcode":"M5A 1K4",
    "sg:province":"ON",
    "wof:name":"Nienkamper",
    "wof:placetype":"venue"
},
  "geometry": {"coordinates":[-79.3646774292,43.6521911621],"type":"Point"}
}