{
  "type": "Feature",
  "properties": {
    "iso:country":"CA",
    "sg:city":"Courtenay",
    "sg:classifiers":[
        {
            "category":"Professional",
            "subcategory":"Accounting & Tax Preparation",
            "type":"Services"
        }
    ],
    "sg:phone":"+1 250 338 1941",
    "sg:postcode":"V9N 2R4",
    "sg:province":"BC",
    "sg:tags":[
        "accountant"
    ],
    "wof:name":"Pietrzykowski Bay & Assocs Inc",
    "wof:placetype":"venue"
},
  "geometry": {"coordinates":[-125.00041961700001,49.6883277893],"type":"Point"}
}