{
  "type": "Feature",
  "properties": {
    "addr:full":"277 Royal York Rd Etobicoke ON M8V 2V8",
    "addr:housenumber":"277",
    "addr:postcode":"m8v 2v8",
    "addr:street":"Royal York Rd",
    "iso:country":"CA",
    "sg:address":"277 Royal York Rd",
    "sg:city":"Etobicoke",
    "sg:classifiers":[
        {
            "category":"Organizations",
            "subcategory":"Religious Organization",
            "type":"Services"
        }
    ],
    "sg:phone":"+1 416 251 1109",
    "sg:postcode":"M8V 2V8",
    "sg:province":"ON",
    "sg:tags":[
        "church"
    ],
    "wof:name":"St Leo's Church",
    "wof:placetype":"venue"
},
  "geometry": {"coordinates":[-79.4973144531,43.6141319275],"type":"Point"}
}