{
  "type": "Feature",
  "properties": {
    "addr:full":"240 Leighland Ave Oakville ON L6H 3H6",
    "addr:housenumber":"240",
    "addr:postcode":"l6h 3h6",
    "addr:street":"Leighland Ave",
    "iso:country":"CA",
    "sg:address":"240 Leighland Ave",
    "sg:city":"Oakville",
    "sg:classifiers":[
        {
            "category":"Shopping",
            "subcategory":"Pharmacy",
            "type":"Retail Goods"
        }
    ],
    "sg:phone":"+1 905 842 3730",
    "sg:postcode":"L6H 3H6",
    "sg:province":"ON",
    "wof:name":"Shoppers Drug Mart",
    "wof:placetype":"venue"
},
  "geometry": {"coordinates":[-79.6887054443,43.4624137878],"type":"Point"}
}