{
  "type": "Feature",
  "properties": {
    "addr:full":"52459 Range Road 221 Ardrossan AB T8E 2H8",
    "addr:housenumber":"52459",
    "addr:postcode":"t8e 2h8",
    "addr:street":"Range Road 221",
    "iso:country":"CA",
    "sg:address":"52459 Range Road 221",
    "sg:city":"Ardrossan",
    "sg:classifiers":[
        {
            "category":"Building & Trades",
            "subcategory":"Construction",
            "type":"Services"
        }
    ],
    "sg:phone":"+1 780 922 2670",
    "sg:postcode":"T8E 2H8",
    "sg:province":"AB",
    "sg:tags":[
        "excavating",
        "contractor"
    ],
    "wof:name":"Woolsey Enterprises",
    "wof:placetype":"venue"
},
  "geometry": {"coordinates":[-113.123367,53.54147],"type":"Point"}
}