{
  "type": "Feature",
  "properties": {
    "iso:country":"CA",
    "sg:city":"Coquitlam",
    "sg:classifiers":[
        {
            "category":"Shopping",
            "subcategory":"Gifts & Souvenirs",
            "type":"Retail Goods"
        }
    ],
    "sg:phone":"+1 604 945 0506",
    "sg:postcode":"V3B 5R5",
    "sg:province":"BC",
    "sg:tags":[
        "shop"
    ],
    "wof:name":"Fruits & Passion Boutiques",
    "wof:placetype":"venue"
},
  "geometry": {"coordinates":[-122.800247192,49.2771530151],"type":"Point"}
}