{
  "type": "Feature",
  "properties": {
    "addr:full":"106 Ch Tache O Saint-Cyprien QC G0L 2P0",
    "addr:housenumber":"106",
    "addr:postcode":"g0l 2p0",
    "addr:street":"Ch Tache O",
    "iso:country":"CA",
    "sg:address":"106 Ch Tache O",
    "sg:city":"Saint-Cyprien",
    "sg:classifiers":[
        {
            "category":"Freight",
            "type":"Transportation"
        }
    ],
    "sg:phone":"+1 418 963 1692",
    "sg:postcode":"G0L 2P0",
    "sg:province":"QC",
    "sg:tags":[
        "trucking"
    ],
    "wof:name":"Transport Gabriel Dupuis Inc",
    "wof:placetype":"venue"
},
  "geometry": {"coordinates":[-69.03051000000001,47.898666],"type":"Point"}
}