{
  "type": "Feature",
  "properties": {
    "iso:country":"CA",
    "sg:address":"475 Saskatchewan Ave E",
    "sg:city":"Portage LA Prairie",
    "sg:classifiers":[
        {
            "category":"Autos & Motor Vehicles",
            "subcategory":"Auto Supplies",
            "type":"Retail Goods"
        }
    ],
    "sg:phone":"+1 204 857 7831",
    "sg:postcode":"R1N 0L5",
    "sg:province":"MB",
    "sg:tags":[
        "body",
        "automobile",
        "parts",
        "shop"
    ],
    "wof:name":"Linco Automotive",
    "wof:placetype":"venue"
},
  "geometry": {"coordinates":[-98.28314208979999,49.9725837708],"type":"Point"}
}