{
  "type": "Feature",
  "properties": {
    "iso:country":"CA",
    "sg:address":"5115 Maingate Dr",
    "sg:city":"Mississauga",
    "sg:classifiers":[
        {
            "category":"Building & Trades",
            "subcategory":"Construction",
            "type":"Services"
        }
    ],
    "sg:phone":"+1 905 238 6813",
    "sg:postcode":"L4W 1G4",
    "sg:province":"ON",
    "sg:tags":[
        "general",
        "contractor"
    ],
    "wof:name":"B A Consultant Svc",
    "wof:placetype":"venue"
},
  "geometry": {"coordinates":[-79.6289596558,43.6316337585],"type":"Point"}
}