{
  "type": "Feature",
  "properties": {
    "addr:full":"1316 Victoria Park Ave East York ON M4B 2L4",
    "addr:housenumber":"1316",
    "addr:postcode":"m4b 2l4",
    "addr:street":"Victoria Park Ave",
    "iso:country":"CA",
    "sg:address":"1316 Victoria Park Ave",
    "sg:city":"East York",
    "sg:classifiers":[
        {
            "category":"Personal",
            "subcategory":"Beauty Salon",
            "type":"Services"
        }
    ],
    "sg:phone":"+1 416 759 6454",
    "sg:postcode":"M4B 2L4",
    "sg:province":"ON",
    "wof:name":"Pat's Mens Hairstyling Salon",
    "wof:placetype":"venue"
},
  "geometry": {"coordinates":[-79.29834747309999,43.7140464783],"type":"Point"}
}