{
  "type": "Feature",
  "properties": {
    "addr:full":"499 Paul St Dieppe NB E1A 6S5",
    "addr:housenumber":"499",
    "addr:postcode":"e1a 6s5",
    "addr:street":"Paul St",
    "iso:country":"CA",
    "sg:address":"499 Paul St",
    "sg:city":"Dieppe",
    "sg:classifiers":[
        {
            "category":"Restaurant",
            "type":"Food & Drink"
        }
    ],
    "sg:phone":"+1 506 856 6995",
    "sg:postcode":"E1A 6S5",
    "sg:province":"NB",
    "wof:name":"Mc Ginnis Landing Restaurant",
    "wof:placetype":"venue"
},
  "geometry": {"coordinates":[-64.7582626343,46.0974082947],"type":"Point"}
}