{
  "type": "Feature",
  "properties": {
    "addr:full":"210 Hilliard Ave Waterloo ON N2L 1G1",
    "addr:housenumber":"210",
    "addr:postcode":"n2l 1g1",
    "addr:street":"Hilliard Ave",
    "iso:country":"CA",
    "sg:address":"210 Hilliard Ave",
    "sg:city":"Waterloo",
    "sg:classifiers":[
        {
            "category":"Organizations",
            "subcategory":"Religious Organization",
            "type":"Services"
        }
    ],
    "sg:phone":"+1 519 570 3950",
    "sg:postcode":"N2L 1G1",
    "sg:province":"ON",
    "sg:tags":[
        "church"
    ],
    "wof:name":"Abundant Life Mennonite Church",
    "wof:placetype":"venue"
},
  "geometry": {"coordinates":[-80.5314941406,43.4539031982],"type":"Point"}
}