{
  "type": "Feature",
  "properties": {
    "addr:full":"1821 13 St N Lethbridge AB T1H 2V4",
    "addr:housenumber":"1821",
    "addr:postcode":"t1h 2v4",
    "addr:street":"13 St N",
    "iso:country":"CA",
    "sg:address":"1821 13 St N",
    "sg:city":"Lethbridge",
    "sg:classifiers":[
        {
            "category":"Health Services",
            "subcategory":"Nursing And Care Facility",
            "type":"Services"
        }
    ],
    "sg:phone":"+1 403 328 6664",
    "sg:postcode":"T1H 2V4",
    "sg:province":"AB",
    "sg:tags":[
        "home",
        "convalescent"
    ],
    "wof:name":"Extendicare",
    "wof:placetype":"venue"
},
  "geometry": {"coordinates":[-112.823860169,49.7212715149],"type":"Point"}
}