{
  "type": "Feature",
  "properties": {
    "addr:full":"218 Steeles Ave E Thornhill ON L3T 1A6",
    "addr:housenumber":"218",
    "addr:postcode":"l3t 1a6",
    "addr:street":"Steeles Ave E",
    "iso:country":"CA",
    "sg:address":"218 Steeles Ave E",
    "sg:city":"Thornhill",
    "sg:classifiers":[
        {
            "category":"Health Services",
            "subcategory":"Chiropractor",
            "type":"Services"
        }
    ],
    "sg:phone":"+1 905 889 3781",
    "sg:postcode":"L3T 1A6",
    "sg:province":"ON",
    "wof:name":"Rennicks Chiropractic Office",
    "wof:placetype":"venue"
},
  "geometry": {"coordinates":[-79.400345,43.802494],"type":"Point"}
}