{
  "type": "Feature",
  "properties": {
    "iso:country":"CA",
    "sg:address":"1974 Woodburn Rd",
    "sg:city":"Joyceville",
    "sg:classifiers":[
        {
            "category":"Wholesale",
            "subcategory":"Meat",
            "type":"Manufacturing & Wholesale Goods"
        }
    ],
    "sg:phone":"+1 613 542 0572",
    "sg:postcode":"K0H 1Y0",
    "sg:province":"ON",
    "sg:tags":[
        "product"
    ],
    "wof:name":"Bill Greenlees Meat Packers",
    "wof:placetype":"venue"
},
  "geometry": {"coordinates":[-76.35887146,44.3356742859],"type":"Point"}
}