{
  "type": "Feature",
  "properties": {
    "addr:full":"Mont-Saint-Hilaire QC J3H 3P2",
    "addr:postcode":"j3h 3p2",
    "iso:country":"CA",
    "sg:city":"Mont-Saint-Hilaire",
    "sg:classifiers":[
        {
            "category":"Health Services",
            "subcategory":"Doctor",
            "type":"Services"
        }
    ],
    "sg:phone":"+1 450 464 1777",
    "sg:postcode":"J3H 3P2",
    "sg:province":"QC",
    "sg:tags":[
        "clinic"
    ],
    "wof:name":"Centre Medical DE LA Montagne",
    "wof:placetype":"venue"
},
  "geometry": {"coordinates":[-73.1842422485,45.565448761],"type":"Point"}
}