{
  "type": "Feature",
  "properties": {
    "addr:full":"Montreal QC H3A 1M8",
    "addr:postcode":"h3a 1m8",
    "iso:country":"CA",
    "sg:city":"Montreal",
    "sg:classifiers":[
        {
            "category":"Professional",
            "subcategory":"Engineering",
            "type":"Services"
        }
    ],
    "sg:phone":"+1 514 985 0930",
    "sg:postcode":"H3A 1M8",
    "sg:province":"QC",
    "sg:tags":[
        "engineer"
    ],
    "wof:name":"Canarail Consultants Inc",
    "wof:placetype":"venue"
},
  "geometry": {"coordinates":[-73.55805969239999,45.5184402466],"type":"Point"}
}