{
  "type": "Feature",
  "properties": {
    "iso:country":"CA",
    "sg:address":"25141 53 Ave",
    "sg:city":"Aldergrove",
    "sg:classifiers":[
        {
            "category":"Professional",
            "subcategory":"Art Services",
            "type":"Services"
        }
    ],
    "sg:phone":"+1 604 856 6167",
    "sg:postcode":"V4W 1T1",
    "sg:province":"BC",
    "sg:tags":[
        "graphic"
    ],
    "wof:name":"Ad Works",
    "wof:placetype":"venue"
},
  "geometry": {"coordinates":[-122.47229,49.056866],"type":"Point"}
}