{
  "type": "Feature",
  "properties": {
    "addr:full":"635 Queens Quay W Toronto ON M5V 3G3",
    "addr:housenumber":"635",
    "addr:postcode":"m5v 3g3",
    "addr:street":"Queens Quay W",
    "iso:country":"CA",
    "sg:address":"635 Queens Quay W",
    "sg:city":"Toronto",
    "sg:classifiers":[
        {
            "category":"Education",
            "subcategory":"School",
            "type":"Public Place"
        }
    ],
    "sg:phone":"+1 416 393 8500",
    "sg:postcode":"M5V 3G3",
    "sg:province":"ON",
    "wof:name":"Waterfront School",
    "wof:placetype":"venue"
},
  "geometry": {"coordinates":[-79.397751,43.635841],"type":"Point"}
}