{
  "type": "Feature",
  "properties": {
    "addr:full":"Murtle Lake Rd Blue River BC V0E 1J0",
    "addr:postcode":"v0e 1j0",
    "addr:street":"Murtle Lake Rd",
    "iso:country":"CA",
    "sg:address":"Murtle Lake Rd",
    "sg:city":"Blue River",
    "sg:classifiers":[
        {
            "category":"Travel",
            "subcategory":"Campground",
            "type":"Entertainment"
        }
    ],
    "sg:phone":"+1 250 673 8203",
    "sg:postcode":"V0E 1J0",
    "sg:province":"BC",
    "wof:name":"Blue River Campground & Rv Prk",
    "wof:placetype":"venue"
},
  "geometry": {"coordinates":[-119.31033325200001,52.107131958],"type":"Point"}
}