{
  "type": "Feature",
  "properties": {
    "iso:country":"CA",
    "sg:city":"Hearst",
    "sg:classifiers":[
        {
            "category":"Restaurant",
            "type":"Food & Drink"
        }
    ],
    "sg:phone":"+1 705 362 0205",
    "sg:postcode":"P0L 1N0",
    "sg:province":"ON",
    "wof:name":"Micko's Chip Stand",
    "wof:placetype":"venue"
},
  "geometry": {"coordinates":[-83.6649398804,49.6893196106],"type":"Point"}
}