{
  "type": "Feature",
  "properties": {
    "addr:full":"123 Rue Mc Conville Joliette QC J6E 4L2",
    "addr:housenumber":"123",
    "addr:postcode":"j6e 4l2",
    "addr:street":"Rue Mc Conville",
    "iso:country":"CA",
    "sg:address":"123 Rue Mc Conville",
    "sg:city":"Joliette",
    "sg:classifiers":[
        {
            "category":"Manufacturing",
            "subcategory":"Food",
            "type":"Manufacturing & Wholesale Goods"
        }
    ],
    "sg:phone":"+1 450 752 1125",
    "sg:postcode":"J6E 4L2",
    "sg:province":"QC",
    "sg:tags":[
        "grocer",
        "product",
        "manufacturer"
    ],
    "wof:name":"Aliments Bdf Inc",
    "wof:placetype":"venue"
},
  "geometry": {"coordinates":[-73.43212127690001,46.027305603],"type":"Point"}
}