{
  "type": "Feature",
  "properties": {
    "addr:full":"181 Rue Principale Cowansville QC J2K 1J3",
    "addr:housenumber":"181",
    "addr:postcode":"j2k 1j3",
    "addr:street":"Rue Principale",
    "iso:country":"CA",
    "sg:address":"181 Rue Principale",
    "sg:city":"Cowansville",
    "sg:classifiers":[
        {
            "category":"Shopping",
            "type":"Retail Goods"
        }
    ],
    "sg:phone":"+1 450 263 9422",
    "sg:postcode":"J2K 1J3",
    "sg:province":"QC",
    "sg:tags":[
        "shop",
        "supply",
        "pet",
        "water",
        "equipment",
        "works"
    ],
    "wof:name":"Animalerie DE Cowansville Inc",
    "wof:placetype":"venue"
},
  "geometry": {"coordinates":[-72.744995,45.208118],"type":"Point"}
}