{
  "type": "Feature",
  "properties": {
    "iso:country":"CA",
    "sg:address":"30 Rymal Rd E",
    "sg:city":"Hamilton",
    "sg:classifiers":[
        {
            "category":"Home & Garden",
            "subcategory":"Household Appliances",
            "type":"Retail Goods"
        }
    ],
    "sg:phone":"+1 905 318 4880",
    "sg:postcode":"L9B 1T7",
    "sg:province":"ON",
    "sg:tags":[
        "cleaners",
        "vacuum"
    ],
    "wof:name":"Mountain Vacuum",
    "wof:placetype":"venue"
},
  "geometry": {"coordinates":[-79.892082,43.202087],"type":"Point"}
}