{
  "type": "Feature",
  "properties": {
    "addr:full":"1098 Eglinton Ave W Toronto ON M6C 2E2",
    "addr:housenumber":"1098",
    "addr:postcode":"m6c 2e2",
    "addr:street":"Eglinton Ave W",
    "iso:country":"CA",
    "sg:address":"1098 Eglinton Ave W",
    "sg:city":"Toronto",
    "sg:classifiers":[
        {
            "category":"Home & Garden",
            "subcategory":"Furniture",
            "type":"Retail Goods"
        }
    ],
    "sg:phone":"+1 416 789 9862",
    "sg:postcode":"M6C 2E2",
    "sg:province":"ON",
    "wof:name":"Kates & CO",
    "wof:placetype":"venue"
},
  "geometry": {"coordinates":[-79.4316253662,43.6998252869],"type":"Point"}
}