{
  "type": "Feature",
  "properties": {
    "addr:full":"61 Rte Jacques-Cartier Ste-Catherine-DE-LA-J-Cartier QC G0A 3M0",
    "addr:housenumber":"61",
    "addr:postcode":"g0a 3m0",
    "addr:street":"Rte Jacques-Cartier Ste-Catherine-De-La-J-Cartier",
    "iso:country":"CA",
    "sg:address":"61 Rte Jacques-Cartier",
    "sg:city":"Ste-Catherine-DE-LA-J-Cartier",
    "sg:classifiers":[
        {
            "category":"Manufacturing",
            "subcategory":"Tools & Machinery",
            "type":"Manufacturing & Wholesale Goods"
        }
    ],
    "sg:phone":"+1 418 875 2724",
    "sg:postcode":"G0A 3M0",
    "sg:province":"QC",
    "sg:tags":[
        "machine",
        "shop"
    ],
    "wof:name":"Mdm Precision",
    "wof:placetype":"venue"
},
  "geometry": {"coordinates":[-71.60562899999999,46.846176],"type":"Point"}
}