{
  "type": "Feature",
  "properties": {
    "iso:country":"CA",
    "sg:address":"5580 LA Grande-Allee",
    "sg:city":"Saint-Hubert",
    "sg:classifiers":[
        {
            "category":"Bars & Pubs",
            "type":"Food & Drink"
        }
    ],
    "sg:phone":"+1 450 676 5555",
    "sg:postcode":"J3Y 1A8",
    "sg:province":"QC",
    "sg:tags":[
        "lounge",
        "discotheque",
        "cocktail"
    ],
    "wof:name":"Zoopsie Club",
    "wof:placetype":"venue"
},
  "geometry": {"coordinates":[-73.443878,45.47543],"type":"Point"}
}