{
  "type": "Feature",
  "properties": {
    "addr:full":"9162 Rue Hochelaga Montreal QC H1L 2P3",
    "addr:housenumber":"9162",
    "addr:postcode":"h1l 2p3",
    "addr:street":"Rue Hochelaga",
    "iso:country":"CA",
    "sg:address":"9162 Rue Hochelaga",
    "sg:city":"Montreal",
    "sg:classifiers":[
        {
            "category":"Retail",
            "subcategory":"Auto Repair",
            "type":"Services"
        }
    ],
    "sg:phone":"+1 514 352 5720",
    "sg:postcode":"H1L 2P3",
    "sg:province":"QC",
    "sg:tags":[
        "repairing",
        "automobile"
    ],
    "wof:name":"Mecanique Specialitees Enrg",
    "wof:placetype":"venue"
},
  "geometry": {"coordinates":[-73.5167541504,45.6065063477],"type":"Point"}
}