{
  "type": "Feature",
  "properties": {
    "addr:full":"51 Mckenna Rd Mckenna NB E7N 1V2",
    "addr:housenumber":"51",
    "addr:postcode":"e7n 1v2",
    "addr:street":"Mckenna Rd",
    "iso:country":"CA",
    "sg:address":"51 Mckenna Rd",
    "sg:city":"Mckenna",
    "sg:classifiers":[
        {
            "category":"Manufacturing",
            "subcategory":"Metals",
            "type":"Manufacturing & Wholesale Goods"
        }
    ],
    "sg:phone":"+1 506 328 6514",
    "sg:postcode":"E7N 1V2",
    "sg:province":"NB",
    "sg:tags":[
        "steel"
    ],
    "wof:name":"R S Black Welding & Fabricatin",
    "wof:placetype":"venue"
},
  "geometry": {"coordinates":[-67.502014,46.218121],"type":"Point"}
}