{
  "type": "Feature",
  "properties": {
    "addr:full":"Etobicoke ON M9W 6Y1",
    "addr:postcode":"m9w 6y1",
    "iso:country":"CA",
    "sg:city":"Etobicoke",
    "sg:classifiers":[
        {
            "category":"Wholesale",
            "subcategory":"Electrical",
            "type":"Manufacturing & Wholesale Goods"
        }
    ],
    "sg:phone":"+1 416 213 9009",
    "sg:postcode":"M9W 6Y1",
    "sg:province":"ON",
    "sg:tags":[
        "equipment",
        "electric",
        "supply"
    ],
    "wof:name":"Tullo Lighting & Electrical",
    "wof:placetype":"venue"
},
  "geometry": {"coordinates":[-79.60786437989999,43.7397384644],"type":"Point"}
}