{
  "type": "Feature",
  "properties": {
    "addr:full":"372 Green St Port Elgin ON N0H 2C0",
    "addr:housenumber":"372",
    "addr:postcode":"n0h 2c0",
    "addr:street":"Green St",
    "iso:country":"CA",
    "sg:address":"372 Green St",
    "sg:city":"Port Elgin",
    "sg:classifiers":[
        {
            "category":"Travel",
            "subcategory":"Hotels & Motels",
            "type":"Entertainment"
        }
    ],
    "sg:phone":"+1 519 389 4346",
    "sg:postcode":"N0H 2C0",
    "sg:province":"ON",
    "sg:tags":[
        "cottage",
        "cabin"
    ],
    "wof:name":"Shady Lane Cottages",
    "wof:placetype":"venue"
},
  "geometry": {"coordinates":[-81.396225,44.439659],"type":"Point"}
}