{
  "type": "Feature",
  "properties": {
    "addr:full":"PO Box 370 STN Main Grande Prairie AB T8V 3A5",
    "addr:housenumber":"po",
    "addr:postcode":"370;t8v 3a5",
    "addr:street":"Box;Stn Main",
    "iso:country":"CA",
    "sg:address":"PO Box 370 STN Main",
    "sg:city":"Grande Prairie",
    "sg:classifiers":[
        {
            "category":"Travel",
            "subcategory":"Campground",
            "type":"Entertainment"
        }
    ],
    "sg:phone":"+1 780 532 4568",
    "sg:postcode":"T8V 3A5",
    "sg:province":"AB",
    "wof:name":"Stompede Campsite",
    "wof:placetype":"venue"
},
  "geometry": {"coordinates":[-118.79489100000001,55.171162],"type":"Point"}
}