{
  "type": "Feature",
  "properties": {
    "iso:country":"CA",
    "sg:address":"5098 Rue Francois-Cusson",
    "sg:city":"Lachine",
    "sg:classifiers":[
        {
            "category":"Wholesale",
            "subcategory":"Durable Goods & Equipment",
            "type":"Manufacturing & Wholesale Goods"
        }
    ],
    "sg:phone":"+1 514 631 2497",
    "sg:postcode":"H8T 1B3",
    "sg:province":"QC",
    "sg:tags":[
        "importer"
    ],
    "wof:name":"Pacific Home Products",
    "wof:placetype":"venue"
},
  "geometry": {"coordinates":[-73.7177276611,45.4566993713],"type":"Point"}
}