{
  "type": "Feature",
  "properties": {
    "addr:full":"2160 Shawanaga Trail Mississauga ON L5H 3X7",
    "addr:housenumber":"2160",
    "addr:postcode":"l5h 3x7",
    "addr:street":"Shawanaga Trail",
    "iso:country":"CA",
    "sg:address":"2160 Shawanaga Trail",
    "sg:city":"Mississauga",
    "sg:classifiers":[
        {
            "category":"Professional",
            "subcategory":"Management & Consulting",
            "type":"Services"
        }
    ],
    "sg:phone":"+1 905 271 6155",
    "sg:postcode":"L5H 3X7",
    "sg:province":"ON",
    "sg:tags":[
        "consultant",
        "mining"
    ],
    "wof:name":"Maltui Consulting Inc",
    "wof:placetype":"venue"
},
  "geometry": {"coordinates":[-79.634277,43.544277],"type":"Point"}
}