{
  "type": "Feature",
  "properties": {
    "addr:full":"186 Rue Fraser Riviere-Du-Loup QC G5R 1C8",
    "addr:housenumber":"186",
    "addr:postcode":"g5r 1c8",
    "addr:street":"Rue Fraser Riviere-Du-Loup",
    "iso:country":"CA",
    "sg:address":"186 Rue Fraser",
    "sg:city":"Riviere-Du-Loup",
    "sg:classifiers":[
        {
            "category":"Insurance",
            "subcategory":"Insurance Agent",
            "type":"Services"
        }
    ],
    "sg:phone":"+1 418 862 6913",
    "sg:postcode":"G5R 1C8",
    "sg:province":"QC",
    "wof:name":"Services Fiananciers R April I",
    "wof:placetype":"venue"
},
  "geometry": {"coordinates":[-69.5530090332,47.8297042847],"type":"Point"}
}