{
  "type": "Feature",
  "properties": {
    "addr:full":"Clearwater BC V0E 1N0",
    "addr:postcode":"v0e 1n0",
    "iso:country":"CA",
    "sg:city":"Clearwater",
    "sg:classifiers":[
        {
            "category":"Professional",
            "subcategory":"Accounting & Tax Preparation",
            "type":"Services"
        }
    ],
    "sg:phone":"+1 250 674 3974",
    "sg:postcode":"V0E 1N0",
    "sg:province":"BC",
    "sg:tags":[
        "bookkeeping",
        "general"
    ],
    "wof:name":"For the Record",
    "wof:placetype":"venue"
},
  "geometry": {"coordinates":[-120.034820557,51.6509246826],"type":"Point"}
}