{
  "type": "Feature",
  "properties": {
    "addr:full":"90 Elm St Sudbury ON P3C 1T2",
    "addr:housenumber":"90",
    "addr:postcode":"p3c 1t2",
    "addr:street":"Elm St",
    "iso:country":"CA",
    "sg:address":"90 Elm St",
    "sg:city":"Sudbury",
    "sg:classifiers":[
        {
            "category":"Parking",
            "type":"Transportation"
        }
    ],
    "sg:phone":"+1 705 670 0323",
    "sg:postcode":"P3C 1T2",
    "sg:province":"ON",
    "sg:tags":[
        "garage"
    ],
    "wof:name":"North Renaissance Ctr",
    "wof:placetype":"venue"
},
  "geometry": {"coordinates":[-80.9970779419,46.4933166504],"type":"Point"}
}