{
  "type": "Feature",
  "properties": {
    "addr:full":"2499 Ocean Ave Sidney BC V8L 1T3",
    "addr:housenumber":"2499",
    "addr:postcode":"v8l 1t3",
    "addr:street":"Ocean Ave",
    "iso:country":"CA",
    "sg:address":"2499 Ocean Ave",
    "sg:city":"Sidney",
    "sg:classifiers":[
        {
            "category":"Government",
            "subcategory":"Office",
            "type":"Public Place"
        }
    ],
    "sg:phone":"+1 250 363 6645",
    "sg:postcode":"V8L 1T3",
    "sg:province":"BC",
    "wof:name":"Canada Customs",
    "wof:placetype":"venue"
},
  "geometry": {"coordinates":[-123.397071838,48.6443405151],"type":"Point"}
}