{
  "type": "Feature",
  "properties": {
    "iso:country":"CA",
    "sg:address":"1346 Dundas St W",
    "sg:city":"Toronto",
    "sg:classifiers":[
        {
            "category":"Wholesale",
            "subcategory":"Meat",
            "type":"Manufacturing & Wholesale Goods"
        }
    ],
    "sg:phone":"+1 416 539 0478",
    "sg:postcode":"M6J 1Y2",
    "sg:province":"ON",
    "wof:name":"Mendes Fine Foods Ltd",
    "wof:placetype":"venue"
},
  "geometry": {"coordinates":[-79.42720031739999,43.6496543884],"type":"Point"}
}