{
  "type": "Feature",
  "properties": {
    "iso:country":"CA",
    "sg:address":"14615 116 Ave NW",
    "sg:city":"Edmonton",
    "sg:classifiers":[
        {
            "category":"Wholesale",
            "subcategory":"Construction Materials",
            "type":"Manufacturing & Wholesale Goods"
        }
    ],
    "sg:phone":"+1 780 447 4888",
    "sg:postcode":"T5M 3E8",
    "sg:province":"AB",
    "sg:tags":[
        "floor"
    ],
    "wof:name":"W G Chanin Hardwoods Ltd",
    "wof:placetype":"venue"
},
  "geometry": {"coordinates":[-113.57245636,53.5675735474],"type":"Point"}
}