{
  "type": "Feature",
  "properties": {
    "addr:full":"3550 Boul Des Forges Trois-Rivieres QC G8Y 5H5",
    "addr:housenumber":"3550",
    "addr:postcode":"g8y 5h5",
    "addr:street":"Boul Des Forges Trois-Rivieres",
    "iso:country":"CA",
    "sg:address":"3550 Boul Des Forges",
    "sg:city":"Trois-Rivieres",
    "sg:classifiers":[
        {
            "category":"Shopping",
            "subcategory":"Gifts & Souvenirs",
            "type":"Retail Goods"
        }
    ],
    "sg:phone":"+1 819 376 8655",
    "sg:postcode":"G8Y 5H5",
    "sg:province":"QC",
    "sg:tags":[
        "shop",
        "party",
        "fabric",
        "supply"
    ],
    "wof:name":"Bou Clair Maison DE Tissus",
    "wof:placetype":"venue"
},
  "geometry": {"coordinates":[-72.5810241699,46.3528785706],"type":"Point"}
}