{
  "type": "Feature",
  "properties": {
    "addr:full":"Fort Mcmurray AB T9H 4A4",
    "addr:postcode":"t9h 4a4",
    "iso:country":"CA",
    "sg:city":"Fort Mcmurray",
    "sg:classifiers":[
        {
            "category":"Health Services",
            "subcategory":"Doctor",
            "type":"Services"
        }
    ],
    "sg:phone":"+1 780 790 9455",
    "sg:postcode":"T9H 4A4",
    "sg:province":"AB",
    "sg:tags":[
        "physician",
        "surgeon"
    ],
    "wof:name":"Sauve, Michel MD",
    "wof:placetype":"venue"
},
  "geometry": {"coordinates":[-111.385375977,56.7281990051],"type":"Point"}
}