{
  "type": "Feature",
  "properties": {
    "addr:full":"105 Bayly St W Ajax ON L1S 7K7",
    "addr:housenumber":"105",
    "addr:postcode":"l1s 7k7",
    "addr:street":"Bayly St W",
    "iso:country":"CA",
    "sg:address":"105 Bayly St W",
    "sg:city":"Ajax",
    "sg:classifiers":[
        {
            "category":"Food & Beverages",
            "subcategory":"Groceries & Convenience Stores",
            "type":"Retail Goods"
        }
    ],
    "sg:phone":"+1 905 686 1440",
    "sg:postcode":"L1S 7K7",
    "sg:province":"ON",
    "sg:tags":[
        "grocer"
    ],
    "wof:name":"No Frills",
    "wof:placetype":"venue"
},
  "geometry": {"coordinates":[-79.02207900000001,43.843033],"type":"Point"}
}