{
  "type": "Feature",
  "properties": {
    "addr:full":"10574 Tecumseh Rd E Windsor ON N8R 1A7",
    "addr:housenumber":"10574",
    "addr:postcode":"n8r 1a7",
    "addr:street":"Tecumseh Rd E",
    "iso:country":"CA",
    "sg:address":"10574 Tecumseh Rd E",
    "sg:city":"Windsor",
    "sg:classifiers":[
        {
            "category":"Retail",
            "subcategory":"Auto Repair",
            "type":"Services"
        }
    ],
    "sg:phone":"+1 519 735 5778",
    "sg:postcode":"N8R 1A7",
    "sg:province":"ON",
    "sg:tags":[
        "automobile",
        "top",
        "upholstery",
        "customizing"
    ],
    "wof:name":"E & S Trim & Top",
    "wof:placetype":"venue"
},
  "geometry": {"coordinates":[-82.9109802246,42.3138046265],"type":"Point"}
}