{
  "type": "Feature",
  "properties": {
    "addr:full":"Mascouche QC J7K 2L8",
    "addr:postcode":"j7k 2l8",
    "iso:country":"CA",
    "sg:city":"Mascouche",
    "sg:classifiers":[
        {
            "category":"Cinema",
            "subcategory":"Movie Rental",
            "type":"Entertainment"
        }
    ],
    "sg:phone":"+1 450 474 5888",
    "sg:postcode":"J7K 2L8",
    "sg:province":"QC",
    "sg:tags":[
        "leasing",
        "video",
        "disc",
        "tape"
    ],
    "wof:name":"Video Super Choix",
    "wof:placetype":"venue"
},
  "geometry": {"coordinates":[-73.6062927246,45.7478637695],"type":"Point"}
}