{
  "type": "Feature",
  "properties": {
    "addr:full":"Montreal QC H3B 1R2",
    "addr:postcode":"h3b 1r2",
    "iso:country":"CA",
    "sg:city":"Montreal",
    "sg:classifiers":[
        {
            "category":"Professional",
            "subcategory":"Management & Consulting",
            "type":"Services"
        }
    ],
    "sg:phone":"+1 514 861 1125",
    "sg:postcode":"H3B 1R2",
    "sg:province":"QC",
    "sg:tags":[
        "consultant",
        "business"
    ],
    "wof:name":"Richer Group",
    "wof:placetype":"venue"
},
  "geometry": {"coordinates":[-73.567108,45.502544],"type":"Point"}
}