{
  "type": "Feature",
  "properties": {
    "addr:full":"23 7E Rue O Saint-Martin QC G0M 1B0",
    "addr:housenumber":"23",
    "addr:postcode":"g0m 1b0",
    "addr:street":"7E Rue O Saint-Martin",
    "iso:country":"CA",
    "sg:address":"23 7E Rue O",
    "sg:city":"Saint-Martin",
    "sg:classifiers":[
        {
            "category":"Building & Trades",
            "subcategory":"Construction",
            "type":"Services"
        }
    ],
    "sg:phone":"+1 418 382 5151",
    "sg:postcode":"G0M 1B0",
    "sg:province":"QC",
    "sg:tags":[
        "maker",
        "cabinet"
    ],
    "wof:name":"Produits Matra Inc",
    "wof:placetype":"venue"
},
  "geometry": {"coordinates":[-70.65464799999999,45.95734],"type":"Point"}
}