{
  "type": "Feature",
  "properties": {
    "addr:full":"859 Aikens Rd Dunnville ON N1A 2W3",
    "addr:housenumber":"859",
    "addr:postcode":"n1a 2w3",
    "addr:street":"Aikens Rd",
    "iso:country":"CA",
    "sg:address":"859 Aikens Rd",
    "sg:city":"Dunnville",
    "sg:classifiers":[
        {
            "category":"Shopping",
            "subcategory":"Bicycles & Sporting Goods",
            "type":"Retail Goods"
        }
    ],
    "sg:phone":"+1 519 774 3238",
    "sg:postcode":"N1A 2W3",
    "sg:province":"ON",
    "sg:tags":[
        "saddlery",
        "harness",
        "establishment"
    ],
    "wof:name":"Mason Horse Equipment",
    "wof:placetype":"venue"
},
  "geometry": {"coordinates":[-79.619873,42.904362],"type":"Point"}
}