{
  "type": "Feature",
  "properties": {
    "addr:full":"500 Selkirk Ave Winnipeg MB R2W 2M7",
    "addr:housenumber":"500",
    "addr:postcode":"r2w 2m7",
    "addr:street":"Selkirk Ave",
    "iso:country":"CA",
    "sg:address":"500 Selkirk Ave",
    "sg:city":"Winnipeg",
    "sg:classifiers":[
        {
            "category":"Manufacturing",
            "subcategory":"Food",
            "type":"Manufacturing & Wholesale Goods"
        }
    ],
    "sg:phone":"+1 204 589 8397",
    "sg:postcode":"R2W 2M7",
    "sg:province":"MB",
    "sg:tags":[
        "baker",
        "product",
        "manufacturer"
    ],
    "wof:name":"Donut House Ltd",
    "wof:placetype":"venue"
},
  "geometry": {"coordinates":[-97.14465300000001,49.915413],"type":"Point"}
}