{
  "type": "Feature",
  "properties": {
    "iso:country":"CA",
    "sg:city":"Tignish",
    "sg:classifiers":[
        {
            "category":"Professional",
            "subcategory":"Management & Consulting",
            "type":"Services"
        }
    ],
    "sg:phone":"+1 902 882 2746",
    "sg:postcode":"C0B 2B0",
    "sg:province":"PE",
    "sg:tags":[
        "consultant",
        "energy",
        "conservation"
    ],
    "wof:name":"Atlantic Wind Test Site",
    "wof:placetype":"venue"
},
  "geometry": {"coordinates":[-64.0333862305,46.9513168335],"type":"Point"}
}