{
  "type": "Feature",
  "properties": {
    "addr:full":"10480 Islington Ave Kleinburg ON L0J 1C0",
    "addr:housenumber":"10480",
    "addr:postcode":"l0j 1c0",
    "addr:street":"Islington Ave",
    "iso:country":"CA",
    "sg:address":"10480 Islington Ave",
    "sg:city":"Kleinburg",
    "sg:classifiers":[
        {
            "category":"Shopping",
            "subcategory":"Gifts & Souvenirs",
            "type":"Retail Goods"
        }
    ],
    "sg:phone":"+1 905 893 3184",
    "sg:postcode":"L0J 1C0",
    "sg:province":"ON",
    "sg:tags":[
        "shop"
    ],
    "wof:name":"Oggettini",
    "wof:placetype":"venue"
},
  "geometry": {"coordinates":[-79.62769299999999,43.843414],"type":"Point"}
}