{
  "type": "Feature",
  "properties": {
    "addr:full":"10901 Hwy 3A Boswell BC V0B 1A0",
    "addr:housenumber":"10901",
    "addr:postcode":"bc v0b 1a0",
    "addr:street":"Hwy 3A",
    "iso:country":"CA",
    "sg:address":"10901 Hwy 3A",
    "sg:city":"Boswell",
    "sg:classifiers":[
        {
            "category":"Travel",
            "subcategory":"Campground",
            "type":"Entertainment"
        }
    ],
    "sg:phone":"+1 250 223 8282",
    "sg:postcode":"V0B 1A0",
    "sg:province":"BC",
    "sg:tags":[
        "camp"
    ],
    "wof:name":"Elks Recreation Children's Soc",
    "wof:placetype":"venue"
},
  "geometry": {"coordinates":[-116.766113,49.465832],"type":"Point"}
}