{
  "type": "Feature",
  "properties": {
    "iso:country":"CA",
    "sg:address":"1005 Broad St",
    "sg:city":"Victoria",
    "sg:classifiers":[
        {
            "category":"Shopping",
            "subcategory":"Florist",
            "type":"Retail Goods"
        }
    ],
    "sg:phone":"+1 250 383 5262",
    "sg:postcode":"V8W 2A1",
    "sg:province":"BC",
    "wof:name":"Flowers on Top",
    "wof:placetype":"venue"
},
  "geometry": {"coordinates":[-123.366562,48.424114],"type":"Point"}
}