{
  "type": "Feature",
  "properties": {
    "addr:full":"272 Avenue Rd Toronto ON M4V 2G7",
    "addr:housenumber":"272",
    "addr:postcode":"m4v 2g7",
    "addr:street":"Avenue Rd",
    "iso:country":"CA",
    "sg:address":"272 Avenue Rd",
    "sg:city":"Toronto",
    "sg:classifiers":[
        {
            "category":"Manufacturing",
            "subcategory":"Printing",
            "type":"Manufacturing & Wholesale Goods"
        }
    ],
    "sg:phone":"+1 416 324 8661",
    "sg:postcode":"M4V 2G7",
    "sg:province":"ON",
    "sg:tags":[
        "multimedia"
    ],
    "wof:name":"New Media Architects",
    "wof:placetype":"venue"
},
  "geometry": {"coordinates":[-79.398338,43.678516],"type":"Point"}
}