{
  "type": "Feature",
  "properties": {
    "addr:full":"313 Rue Notre-Dame Gatineau QC J8P 1L2",
    "addr:housenumber":"313",
    "addr:postcode":"j8p 1l2",
    "addr:street":"Rue Notre-Dame",
    "iso:country":"CA",
    "sg:address":"313 Rue Notre-Dame",
    "sg:city":"Gatineau",
    "sg:classifiers":[
        {
            "category":"Shopping",
            "subcategory":"Books",
            "type":"Retail Goods"
        }
    ],
    "sg:phone":"+1 819 643 1861",
    "sg:postcode":"J8P 1L2",
    "sg:province":"QC",
    "sg:tags":[
        "dealer"
    ],
    "wof:name":"Librairie Louis-Frechette Enrg",
    "wof:placetype":"venue"
},
  "geometry": {"coordinates":[-75.644806,45.481537],"type":"Point"}
}