{
  "type": "Feature",
  "properties": {
    "iso:country":"CA",
    "sg:address":"602 Vine St",
    "sg:city":"Birtle",
    "sg:classifiers":[
        {
            "category":"Organizations",
            "subcategory":"Religious Organization",
            "type":"Services"
        }
    ],
    "sg:phone":"+1 204 842 5217",
    "sg:postcode":"R0M 0C0",
    "sg:province":"MB",
    "sg:tags":[
        "church"
    ],
    "wof:name":"Anglican Church",
    "wof:placetype":"venue"
},
  "geometry": {"coordinates":[-101.03984069800001,50.4221572876],"type":"Point"}
}