{
  "type": "Feature",
  "properties": {
    "addr:full":"2901 Bayview Ave North York ON M2K 1E6",
    "addr:housenumber":"2901",
    "addr:postcode":"m2k 1e6",
    "addr:street":"Bayview Ave",
    "iso:country":"CA",
    "sg:address":"2901 Bayview Ave",
    "sg:city":"North York",
    "sg:classifiers":[
        {
            "category":"Shopping",
            "subcategory":"Clothing, Apparel, & Fashions",
            "type":"Retail Goods"
        }
    ],
    "sg:phone":"+1 416 733 1717",
    "sg:postcode":"M2K 1E6",
    "sg:province":"ON",
    "sg:tags":[
        "infant",
        "wear"
    ],
    "wof:name":"Jacadi",
    "wof:placetype":"venue"
},
  "geometry": {"coordinates":[-79.388542,43.769115],"type":"Point"}
}