{
  "type": "Feature",
  "properties": {
    "addr:full":"9926 105 Ave Grande Prairie AB T8V 1G9",
    "addr:housenumber":"9926",
    "addr:postcode":"t8v 1g9",
    "addr:street":"105 Ave",
    "iso:country":"CA",
    "sg:address":"9926 105 Ave",
    "sg:city":"Grande Prairie",
    "sg:classifiers":[
        {
            "category":"Real Estate",
            "subcategory":"Real Estate Operator",
            "type":"Services"
        }
    ],
    "sg:phone":"+1 780 532 3258",
    "sg:postcode":"T8V 1G9",
    "sg:province":"AB",
    "sg:tags":[
        "apartment"
    ],
    "wof:name":"Montrose Apartments",
    "wof:placetype":"venue"
},
  "geometry": {"coordinates":[-118.792648,55.175396],"type":"Point"}
}