{
  "type": "Feature",
  "properties": {
    "iso:country":"CA",
    "sg:address":"287 Boul Des Prairies",
    "sg:city":"Laval",
    "sg:classifiers":[
        {
            "category":"Retail",
            "subcategory":"Auto Repair",
            "type":"Services"
        }
    ],
    "sg:phone":"+1 450 967 5690",
    "sg:postcode":"H7N 2V2",
    "sg:province":"QC",
    "sg:tags":[
        "repairing",
        "automobile"
    ],
    "wof:name":"Auto Dpj Inc",
    "wof:placetype":"venue"
},
  "geometry": {"coordinates":[-73.7007141113,45.5500297546],"type":"Point"}
}