{
  "type": "Feature",
  "properties": {
    "addr:full":"4311 Buchanan St Burnaby BC V5C 3X7",
    "addr:housenumber":"4311",
    "addr:postcode":"v5c 3x7",
    "addr:street":"Buchanan St",
    "iso:country":"CA",
    "sg:address":"4311 Buchanan St",
    "sg:city":"Burnaby",
    "sg:classifiers":[
        {
            "category":"Home & Garden",
            "subcategory":"Garden Supply",
            "type":"Retail Goods"
        }
    ],
    "sg:phone":"+1 604 299 8358",
    "sg:postcode":"V5C 3X7",
    "sg:province":"BC",
    "sg:tags":[
        "lawn",
        "tool",
        "mower"
    ],
    "wof:name":"Able Tool Rentals",
    "wof:placetype":"venue"
},
  "geometry": {"coordinates":[-123.008408,49.267593],"type":"Point"}
}