{
  "type": "Feature",
  "properties": {
    "addr:full":"Waterloo QC J0E 2N0",
    "addr:postcode":"j0e 2n0",
    "iso:country":"CA",
    "sg:city":"Waterloo",
    "sg:classifiers":[
        {
            "category":"Shopping",
            "subcategory":"Florist",
            "type":"Retail Goods"
        }
    ],
    "sg:phone":"+1 450 539 2090",
    "sg:postcode":"J0E 2N0",
    "sg:province":"QC",
    "wof:name":"Fleuriste Pierre-Michel",
    "wof:placetype":"venue"
},
  "geometry": {"coordinates":[-72.516869,45.345573],"type":"Point"}
}