{
  "type": "Feature",
  "properties": {
    "addr:full":"Chetwynd BC V0C 1J0",
    "addr:postcode":"bc v0c 1j0",
    "iso:country":"CA",
    "sg:city":"Chetwynd",
    "sg:classifiers":[
        {
            "category":"Freight",
            "type":"Transportation"
        }
    ],
    "sg:phone":"+1 250 788 9717",
    "sg:postcode":"V0C 1J0",
    "sg:province":"BC",
    "sg:tags":[
        "trucking"
    ],
    "wof:name":"Grimshaw Trucking & Distr",
    "wof:placetype":"venue"
},
  "geometry": {"coordinates":[-121.61211400000001,55.697861],"type":"Point"}
}