{
  "type": "Feature",
  "properties": {
    "addr:full":"121 Galena Rd Whitehorse YT Y1A 2W7",
    "addr:housenumber":"121",
    "addr:postcode":"y1a 2w7",
    "addr:street":"Galena Rd",
    "iso:country":"CA",
    "sg:address":"121 Galena Rd",
    "sg:city":"Whitehorse",
    "sg:classifiers":[
        {
            "category":"Retail",
            "subcategory":"Auto Repair",
            "type":"Services"
        }
    ],
    "sg:phone":"+1 867 668 6288",
    "sg:postcode":"Y1A 2W7",
    "sg:province":"YT",
    "sg:tags":[
        "body",
        "automobile",
        "painting"
    ],
    "wof:name":"A-1 Autobody",
    "wof:placetype":"venue"
},
  "geometry": {"coordinates":[-135.07325700000001,60.740688],"type":"Point"}
}