{
  "type": "Feature",
  "properties": {
    "iso:country":"CA",
    "sg:address":"1621 Welch St",
    "sg:city":"North Vancouver",
    "sg:classifiers":[
        {
            "category":"Wholesale",
            "subcategory":"Groceries",
            "type":"Manufacturing & Wholesale Goods"
        }
    ],
    "sg:phone":"+1 604 990 6920",
    "sg:postcode":"V7P 3G9",
    "sg:province":"BC",
    "sg:tags":[
        "grocer"
    ],
    "wof:name":"Heros International Food",
    "wof:placetype":"venue"
},
  "geometry": {"coordinates":[-123.116386414,49.3175201416],"type":"Point"}
}