{
  "type": "Feature",
  "properties": {
    "addr:full":"6814 Jubilee Ave Burnaby BC V5J 4B3",
    "addr:housenumber":"6814",
    "addr:postcode":"v5j 4b3",
    "addr:street":"Jubilee Ave",
    "iso:country":"CA",
    "sg:address":"6814 Jubilee Ave",
    "sg:city":"Burnaby",
    "sg:classifiers":[
        {
            "category":"Shopping",
            "subcategory":"Computers & Home Electronics",
            "type":"Retail Goods"
        }
    ],
    "sg:phone":"+1 604 609 2882",
    "sg:postcode":"V5J 4B3",
    "sg:province":"BC",
    "sg:tags":[
        "parts",
        "supply"
    ],
    "wof:name":"Synergy 2000",
    "wof:placetype":"venue"
},
  "geometry": {"coordinates":[-122.995628,49.221485],"type":"Point"}
}