{
  "type": "Feature",
  "properties": {
    "addr:full":"5 Commerce Rd Lindsay ON K9V 5Y3",
    "addr:housenumber":"5",
    "addr:postcode":"k9v 5y3",
    "addr:street":"Commerce Rd",
    "iso:country":"CA",
    "sg:address":"5 Commerce Rd",
    "sg:city":"Lindsay",
    "sg:classifiers":[
        {
            "category":"Shopping",
            "subcategory":"Florist",
            "type":"Retail Goods"
        }
    ],
    "sg:phone":"+1 705 324 9574",
    "sg:postcode":"K9V 5Y3",
    "sg:province":"ON",
    "sg:tags":[
        "garden",
        "center"
    ],
    "wof:name":"Garry's Garden Gallery",
    "wof:placetype":"venue"
},
  "geometry": {"coordinates":[-78.7621459961,44.3492164612],"type":"Point"}
}