{
  "type": "Feature",
  "properties": {
    "iso:country":"CA",
    "sg:address":"292 Mackay St",
    "sg:city":"Ottawa",
    "sg:classifiers":[
        {
            "category":"Shopping",
            "subcategory":"Used Merchandise",
            "type":"Retail Goods"
        }
    ],
    "sg:phone":"+1 613 741 8565",
    "sg:postcode":"K1M 2B8",
    "sg:province":"ON",
    "sg:tags":[
        "antique"
    ],
    "wof:name":"Ernest Johnson Antiques",
    "wof:placetype":"venue"
},
  "geometry": {"coordinates":[-75.6826019287,45.4406738281],"type":"Point"}
}