{
  "type": "Feature",
  "properties": {
    "addr:full":"1104 Thompson Rd Fort Erie ON L2A 6A8",
    "addr:housenumber":"1104",
    "addr:postcode":"l2a 6a8",
    "addr:street":"Thompson Rd",
    "iso:country":"CA",
    "sg:address":"1104 Thompson Rd",
    "sg:city":"Fort Erie",
    "sg:classifiers":[
        {
            "category":"Retail",
            "subcategory":"Veterinary Services",
            "type":"Services"
        }
    ],
    "sg:phone":"+1 905 871 4366",
    "sg:postcode":"L2A 6A8",
    "sg:province":"ON",
    "sg:tags":[
        "veterinarian"
    ],
    "wof:name":"Waller, Sandra L DVM",
    "wof:placetype":"venue"
},
  "geometry": {"coordinates":[-78.9401550293,42.9069480896],"type":"Point"}
}