{
  "type": "Feature",
  "properties": {
    "iso:country":"CA",
    "sg:address":"1715 St Clair Ave W",
    "sg:city":"Toronto",
    "sg:classifiers":[
        {
            "category":"Shopping",
            "subcategory":"Discount & Variety Stores",
            "type":"Retail Goods"
        }
    ],
    "sg:phone":"+1 416 653 2625",
    "sg:postcode":"M6N 1J2",
    "sg:province":"ON",
    "wof:name":"Santa Lucia Variety",
    "wof:placetype":"venue"
},
  "geometry": {"coordinates":[-79.459404,43.674221],"type":"Point"}
}