{
  "type": "Feature",
  "properties": {
    "iso:country":"CA",
    "sg:address":"160 Saint-Andre Quai",
    "sg:city":"Quebec",
    "sg:classifiers":[
        {
            "category":"Restaurant",
            "type":"Food & Drink"
        }
    ],
    "sg:phone":"+1 418 694 9615",
    "sg:postcode":"G1K 3Y2",
    "sg:province":"QC",
    "wof:name":"Restaurant Du Marche",
    "wof:placetype":"venue"
},
  "geometry": {"coordinates":[-71.208664,46.817528],"type":"Point"}
}