{
  "type": "Feature",
  "properties": {
    "iso:country":"CA",
    "sg:address":"5112 61st Ave",
    "sg:city":"Viking",
    "sg:classifiers":[
        {
            "category":"Shopping",
            "type":"Retail Goods"
        }
    ],
    "sg:phone":"+1 780 336 2600",
    "sg:postcode":"T0B 4N0",
    "sg:province":"AB",
    "sg:tags":[
        "sign",
        "monument"
    ],
    "wof:name":"Creative Sandblasting",
    "wof:placetype":"venue"
},
  "geometry": {"coordinates":[-111.783828735,53.0951271057],"type":"Point"}
}