{
  "type": "Feature",
  "properties": {
    "addr:full":"4777 Boul Bourque Rock Forest QC J1N 2G6",
    "addr:housenumber":"4777",
    "addr:postcode":"j1n 2g6",
    "addr:street":"Boul Bourque",
    "iso:country":"CA",
    "sg:address":"4777 Boul Bourque",
    "sg:city":"Rock Forest",
    "sg:classifiers":[
        {
            "category":"Professional",
            "subcategory":"Accounting & Tax Preparation",
            "type":"Services"
        }
    ],
    "sg:phone":"+1 819 820 2228",
    "sg:postcode":"J1N 2G6",
    "sg:province":"QC",
    "sg:tags":[
        "accountant"
    ],
    "wof:name":"Buteau, Helene",
    "wof:placetype":"venue"
},
  "geometry": {"coordinates":[-71.984596,45.373573],"type":"Point"}
}