{
  "type": "Feature",
  "properties": {
    "addr:full":"3511 27 Ave Vernon BC V1T 1S5",
    "addr:housenumber":"3511",
    "addr:postcode":"v1t 1s5",
    "addr:street":"27 Ave",
    "iso:country":"CA",
    "sg:address":"3511 27 Ave",
    "sg:city":"Vernon",
    "sg:classifiers":[
        {
            "category":"Health Services",
            "subcategory":"Nursing And Care Facility",
            "type":"Services"
        }
    ],
    "sg:phone":"+1 250 542 3711",
    "sg:postcode":"V1T 1S5",
    "sg:province":"BC",
    "sg:tags":[
        "home",
        "retirement",
        "community"
    ],
    "wof:name":"Abbeyfield Houses of Vernon",
    "wof:placetype":"venue"
},
  "geometry": {"coordinates":[-119.280029297,50.2618293762],"type":"Point"}
}