{
  "type": "Feature",
  "properties": {
    "addr:full":"175 Wallace Ave N Listowel ON N4W 1K8",
    "addr:housenumber":"175",
    "addr:postcode":"n4w 1k8",
    "addr:street":"Wallace Ave N",
    "iso:country":"CA",
    "sg:address":"175 Wallace Ave N",
    "sg:city":"Listowel",
    "sg:classifiers":[
        {
            "category":"Banks & Credit Unions",
            "subcategory":"Bank",
            "type":"Services"
        }
    ],
    "sg:phone":"+1 519 291 1590",
    "sg:postcode":"N4W 1K8",
    "sg:province":"ON",
    "wof:name":"Royal Bank Financial Group",
    "wof:placetype":"venue"
},
  "geometry": {"coordinates":[-80.9528121948,43.7323036194],"type":"Point"}
}