{
  "type": "Feature",
  "properties": {
    "iso:country":"CA",
    "sg:address":"244 Main St",
    "sg:city":"Wellington",
    "sg:classifiers":[
        {
            "category":"Organizations",
            "subcategory":"Religious Organization",
            "type":"Services"
        }
    ],
    "sg:phone":"+1 613 399 3082",
    "sg:postcode":"K0K 3L0",
    "sg:province":"ON",
    "sg:tags":[
        "church"
    ],
    "wof:name":"St Andrew Anglican Church",
    "wof:placetype":"venue"
},
  "geometry": {"coordinates":[-77.3470840454,43.9519462585],"type":"Point"}
}