{
  "type": "Feature",
  "properties": {
    "iso:country":"CA",
    "sg:address":"26 Ronell Cres",
    "sg:city":"Collingwood",
    "sg:classifiers":[
        {
            "category":"Manufacturing",
            "subcategory":"Printing",
            "type":"Manufacturing & Wholesale Goods"
        }
    ],
    "sg:phone":"+1 705 445 2880",
    "sg:postcode":"L9Y 4J7",
    "sg:province":"ON",
    "sg:tags":[
        "printer"
    ],
    "wof:name":"Print Shop",
    "wof:placetype":"venue"
},
  "geometry": {"coordinates":[-80.1946716309,44.5027656555],"type":"Point"}
}