{
  "type": "Feature",
  "properties": {
    "addr:full":"Whistler BC V0N 1B3",
    "addr:postcode":"v0n 1b3",
    "iso:country":"CA",
    "sg:city":"Whistler",
    "sg:classifiers":[
        {
            "category":"Building & Trades",
            "subcategory":"Construction",
            "type":"Services"
        }
    ],
    "sg:phone":"+1 604 935 3933",
    "sg:postcode":"V0N 1B3",
    "sg:province":"BC",
    "sg:tags":[
        "repairing",
        "remodeling",
        "contractor"
    ],
    "wof:name":"Clydesdale Maintenance Ltd",
    "wof:placetype":"venue"
},
  "geometry": {"coordinates":[-122.97017700000001,50.112396],"type":"Point"}
}