{
  "type": "Feature",
  "properties": {
    "iso:country":"CA",
    "sg:address":"33 Main St E",
    "sg:city":"Ridgetown",
    "sg:classifiers":[
        {
            "category":"Shopping",
            "subcategory":"Florist",
            "type":"Retail Goods"
        }
    ],
    "sg:phone":"+1 519 674 5132",
    "sg:postcode":"N0P 2C0",
    "sg:province":"ON",
    "wof:name":"A Touch of Green",
    "wof:placetype":"venue"
},
  "geometry": {"coordinates":[-81.88627624510001,42.4395904541],"type":"Point"}
}