{
  "type": "Feature",
  "properties": {
    "addr:full":"1059 Rue Du Parc-Industriel Saint-Jean-Chrysostome QC G6Z 1C5",
    "addr:housenumber":"1059",
    "addr:postcode":"g6z 1c5",
    "addr:street":"Rue Du Parc-Industriel Saint-Jean-Chrysostome",
    "iso:country":"CA",
    "sg:address":"1059 Rue Du Parc-Industriel",
    "sg:city":"Saint-Jean-Chrysostome",
    "sg:classifiers":[
        {
            "category":"Wholesale",
            "subcategory":"Machinery & Supplies",
            "type":"Manufacturing & Wholesale Goods"
        }
    ],
    "sg:phone":"+1 418 839 6938",
    "sg:postcode":"G6Z 1C5",
    "sg:province":"QC",
    "sg:tags":[
        "truck"
    ],
    "wof:name":"Centre Du Diesel St-Jean Inc",
    "wof:placetype":"venue"
},
  "geometry": {"coordinates":[-71.212875,46.730251],"type":"Point"}
}