{
  "type": "Feature",
  "properties": {
    "addr:full":"4907 Pool Rd Garden Bay BC V0N 1S0",
    "addr:housenumber":"4907",
    "addr:postcode":"v0n 1s0",
    "addr:street":"Pool Rd",
    "iso:country":"CA",
    "sg:address":"4907 Pool Rd",
    "sg:city":"Garden Bay",
    "sg:classifiers":[
        {
            "category":"Food & Beverages",
            "subcategory":"Groceries & Convenience Stores",
            "type":"Retail Goods"
        }
    ],
    "sg:phone":"+1 604 883 2253",
    "sg:postcode":"V0N 1S0",
    "sg:province":"BC",
    "sg:tags":[
        "marina"
    ],
    "wof:name":"John Henry's Marinas Inc",
    "wof:placetype":"venue"
},
  "geometry": {"coordinates":[-123.97172500000001,49.638954],"type":"Point"}
}