{
  "type": "Feature",
  "properties": {
    "addr:full":"4710 50th Ave Calmar AB T0C 0V0",
    "addr:housenumber":"4710",
    "addr:postcode":"t0c 0v0",
    "addr:street":"50Th Ave",
    "iso:country":"CA",
    "sg:address":"4710 50th Ave",
    "sg:city":"Calmar",
    "sg:classifiers":[
        {
            "category":"Autos & Motor Vehicles",
            "subcategory":"Fuel & Gas Station",
            "type":"Retail Goods"
        }
    ],
    "sg:phone":"+1 780 985 2070",
    "sg:postcode":"T0C 0V0",
    "sg:province":"AB",
    "sg:tags":[
        "oil"
    ],
    "wof:name":"Shell",
    "wof:placetype":"venue"
},
  "geometry": {"coordinates":[-113.800972,53.265175],"type":"Point"}
}