{
  "type": "Feature",
  "properties": {
    "addr:full":"2510 Del Zotto Ave Gloucester ON K1T 3V7",
    "addr:housenumber":"2510",
    "addr:postcode":"k1t 3v7",
    "addr:street":"Del Zotto Ave",
    "iso:country":"CA",
    "sg:address":"2510 Del Zotto Ave",
    "sg:city":"Gloucester",
    "sg:classifiers":[
        {
            "category":"Building & Trades",
            "subcategory":"Construction",
            "type":"Services"
        }
    ],
    "sg:phone":"+1 613 822 7112",
    "sg:postcode":"K1T 3V7",
    "sg:province":"ON",
    "sg:tags":[
        "pipe",
        "line",
        "contractor"
    ],
    "wof:name":"Robert B Somerville CO Ltd",
    "wof:placetype":"venue"
},
  "geometry": {"coordinates":[-75.625328,45.311817],"type":"Point"}
}