{
  "type": "Feature",
  "properties": {
    "addr:full":"North York ON M3H 2S1",
    "addr:postcode":"m3h 2s1",
    "iso:country":"CA",
    "sg:city":"North York",
    "sg:classifiers":[
        {
            "category":"Professional",
            "subcategory":"Business Services",
            "type":"Services"
        }
    ],
    "sg:phone":"+1 416 630 8300",
    "sg:postcode":"M3H 2S1",
    "sg:province":"ON",
    "sg:tags":[
        "paralegal"
    ],
    "wof:name":"M G & Assoc",
    "wof:placetype":"venue"
},
  "geometry": {"coordinates":[-79.441002,43.75515],"type":"Point"}
}