{
  "type": "Feature",
  "properties": {
    "addr:full":"1249 169 Rte Metabetchouan-Lac-A-LA-Croix QC G8G 1A4",
    "addr:housenumber":"1249",
    "addr:postcode":"g8g 1a4",
    "addr:street":"169 Rte Metabetchouan-Lac-A-La-Croix",
    "iso:country":"CA",
    "sg:address":"1249 169 Rte",
    "sg:city":"Metabetchouan-Lac-A-LA-Croix",
    "sg:classifiers":[
        {
            "category":"Retail",
            "subcategory":"Auto Repair",
            "type":"Services"
        }
    ],
    "sg:phone":"+1 418 349 8407",
    "sg:postcode":"G8G 1A4",
    "sg:province":"QC",
    "sg:tags":[
        "repairing",
        "automobile"
    ],
    "wof:name":"Garage Laurent Lavoie",
    "wof:placetype":"venue"
},
  "geometry": {"coordinates":[-71.8765792847,48.4169006348],"type":"Point"}
}