{
  "type": "Feature",
  "properties": {
    "addr:full":"1768 Rte 1 Church Point NS B0W 1M0",
    "addr:housenumber":"1768",
    "addr:postcode":"b0w 1m0",
    "addr:street":"Rte 1",
    "iso:country":"CA",
    "sg:address":"1768 Rte 1",
    "sg:city":"Church Point",
    "sg:classifiers":[
        {
            "category":"Travel",
            "subcategory":"Hotels & Motels",
            "type":"Entertainment"
        }
    ],
    "sg:phone":"+1 902 769 2526",
    "sg:postcode":"B0W 1M0",
    "sg:province":"NS",
    "wof:name":"Manoir Samson Inn",
    "wof:placetype":"venue"
},
  "geometry": {"coordinates":[-66.1148223877,44.3379058838],"type":"Point"}
}