{
  "type": "Feature",
  "properties": {
    "addr:full":"LA Baie QC G7B 3K1",
    "addr:postcode":"g7b 3k1",
    "iso:country":"CA",
    "sg:city":"LA Baie",
    "sg:classifiers":[
        {
            "category":"Health Services",
            "subcategory":"Doctor",
            "type":"Services"
        }
    ],
    "sg:phone":"+1 418 544 6801",
    "sg:postcode":"G7B 3K1",
    "sg:province":"QC",
    "sg:tags":[
        "dentist"
    ],
    "wof:name":"Simard, Daniel DDS",
    "wof:placetype":"venue"
},
  "geometry": {"coordinates":[-70.8807144165,48.3334922791],"type":"Point"}
}