{
  "type": "Feature",
  "properties": {
    "iso:country":"CA",
    "sg:city":"Warwick",
    "sg:classifiers":[
        {
            "category":"Building & Trades",
            "subcategory":"Electrical",
            "type":"Services"
        }
    ],
    "sg:phone":"+1 819 358 5525",
    "sg:postcode":"J0A 1M0",
    "sg:province":"QC",
    "sg:tags":[
        "electric",
        "contractor"
    ],
    "wof:name":"Service Electrique 4 Saisons",
    "wof:placetype":"venue"
},
  "geometry": {"coordinates":[-71.97918701170001,45.9390106201],"type":"Point"}
}