{
  "type": "Feature",
  "properties": {
    "addr:full":"5376 Yonge St North York ON M2N 5R5",
    "addr:housenumber":"5376",
    "addr:postcode":"m2n 5r5",
    "addr:street":"Yonge St",
    "iso:country":"CA",
    "sg:address":"5376 Yonge St",
    "sg:city":"North York",
    "sg:classifiers":[
        {
            "category":"Travel",
            "subcategory":"Travel Agent",
            "type":"Entertainment"
        }
    ],
    "sg:phone":"+1 416 226 0990",
    "sg:postcode":"M2N 5R5",
    "sg:province":"ON",
    "sg:tags":[
        "agency",
        "bureau"
    ],
    "wof:name":"Riviera Travel Agency Ltd",
    "wof:placetype":"venue"
},
  "geometry": {"coordinates":[-79.41440582280001,43.7745475769],"type":"Point"}
}