{
  "type": "Feature",
  "properties": {
    "addr:full":"260 Rue Beauvilliers Saint-Gabriel-DE-Brandon QC J0K 2N0",
    "addr:housenumber":"260",
    "addr:postcode":"j0k 2n0",
    "addr:street":"Rue Beauvilliers",
    "iso:country":"CA",
    "sg:address":"260 Rue Beauvilliers",
    "sg:city":"Saint-Gabriel-DE-Brandon",
    "sg:classifiers":[
        {
            "category":"Food & Beverages",
            "subcategory":"Groceries & Convenience Stores",
            "type":"Retail Goods"
        }
    ],
    "sg:phone":"+1 450 835 7474",
    "sg:postcode":"J0K 2N0",
    "sg:province":"QC",
    "sg:tags":[
        "grocer"
    ],
    "wof:name":"Depanneur Brandon Enr",
    "wof:placetype":"venue"
},
  "geometry": {"coordinates":[-73.3775558472,46.294757843],"type":"Point"}
}