{
  "type": "Feature",
  "properties": {
    "addr:full":"6 Rue Des Erables Warwick QC J0A 1M0",
    "addr:housenumber":"6",
    "addr:postcode":"j0a 1m0",
    "addr:street":"Rue Des Erables",
    "iso:country":"CA",
    "sg:address":"6 Rue Des Erables",
    "sg:city":"Warwick",
    "sg:classifiers":[
        {
            "category":"Building & Trades",
            "subcategory":"Landscaping Services",
            "type":"Services"
        }
    ],
    "sg:phone":"+1 819 358 6282",
    "sg:postcode":"J0A 1M0",
    "sg:province":"QC",
    "sg:tags":[
        "lawn",
        "maintenance",
        "grounds"
    ],
    "wof:name":"Perreault, Carl",
    "wof:placetype":"venue"
},
  "geometry": {"coordinates":[-71.982086,45.944149],"type":"Point"}
}