{
  "type": "Feature",
  "properties": {
    "addr:full":"Dollard-Des-Ormeaux QC H9H 2A7",
    "addr:postcode":"h9h 2a7",
    "iso:country":"CA",
    "sg:city":"Dollard-Des-Ormeaux",
    "sg:classifiers":[
        {
            "category":"Shopping",
            "subcategory":"Clothing, Apparel, & Fashions",
            "type":"Retail Goods"
        }
    ],
    "sg:phone":"+1 514 626 9603",
    "sg:postcode":"H9H 2A7",
    "sg:province":"QC",
    "sg:tags":[
        "dressmaker"
    ],
    "wof:name":"Couture Chic",
    "wof:placetype":"venue"
},
  "geometry": {"coordinates":[-73.840042,45.478512],"type":"Point"}
}