{
  "type": "Feature",
  "properties": {
    "addr:full":"55 Rue Racine E Chicoutimi QC G7H 1P9",
    "addr:housenumber":"55",
    "addr:postcode":"g7h 1p9",
    "addr:street":"Rue Racine E",
    "iso:country":"CA",
    "sg:address":"55 Rue Racine E",
    "sg:city":"Chicoutimi",
    "sg:classifiers":[
        {
            "category":"Professional",
            "subcategory":"Detective & Security Services",
            "type":"Services"
        }
    ],
    "sg:phone":"+1 418 543 9973",
    "sg:postcode":"G7H 1P9",
    "sg:province":"QC",
    "sg:tags":[
        "guard",
        "patrol"
    ],
    "wof:name":"Securite Kolossal Inc",
    "wof:placetype":"venue"
},
  "geometry": {"coordinates":[-71.066795,48.42802],"type":"Point"}
}