{
  "type": "Feature",
  "properties": {
    "addr:full":"2705 Ch Bates Montreal QC H3S 1B4",
    "addr:housenumber":"2705",
    "addr:postcode":"h3s 1b4",
    "addr:street":"Ch Bates",
    "iso:country":"CA",
    "sg:address":"2705 Ch Bates",
    "sg:city":"Montreal",
    "sg:classifiers":[
        {
            "category":"Retail",
            "subcategory":"Repair Shop",
            "type":"Services"
        }
    ],
    "sg:phone":"+1 514 277 6370",
    "sg:postcode":"H3S 1B4",
    "sg:province":"QC",
    "sg:tags":[
        "ironwork"
    ],
    "wof:name":"D M Ironworks Regd",
    "wof:placetype":"venue"
},
  "geometry": {"coordinates":[-73.632172,45.512623],"type":"Point"}
}