{
  "type": "Feature",
  "properties": {
    "addr:full":"Toronto ON M5A 1A9",
    "addr:postcode":"m5a 1a9",
    "iso:country":"CA",
    "sg:city":"Toronto",
    "sg:classifiers":[
        {
            "category":"Professional",
            "subcategory":"Business Services",
            "type":"Services"
        }
    ],
    "sg:phone":"+1 416 461 4224",
    "sg:postcode":"M5A 1A9",
    "sg:province":"ON",
    "sg:tags":[
        "recording",
        "studio"
    ],
    "wof:name":"Cherry Beach Sound Ltd",
    "wof:placetype":"venue"
},
  "geometry": {"coordinates":[-79.352722,43.647034],"type":"Point"}
}