{
  "type": "Feature",
  "properties": {
    "addr:full":"5 Ferndale Dr N Barrie ON L4N 9V3",
    "addr:housenumber":"5",
    "addr:postcode":"l4n 9v3",
    "addr:street":"Ferndale Dr N",
    "iso:country":"CA",
    "sg:address":"5 Ferndale Dr N",
    "sg:city":"Barrie",
    "sg:classifiers":[
        {
            "category":"Retail",
            "subcategory":"Auto Repair",
            "type":"Services"
        }
    ],
    "sg:phone":"+1 705 737 5931",
    "sg:postcode":"L4N 9V3",
    "sg:province":"ON",
    "sg:tags":[
        "repairing",
        "automobile"
    ],
    "wof:name":"North Star Motors",
    "wof:placetype":"venue"
},
  "geometry": {"coordinates":[-79.7147521973,44.3700561523],"type":"Point"}
}