{
  "type": "Feature",
  "properties": {
    "iso:country":"CA",
    "sg:address":"5240 Ch DE Chambly",
    "sg:city":"Saint-Hubert",
    "sg:classifiers":[
        {
            "category":"Health Services",
            "subcategory":"Medical Lab",
            "type":"Services"
        }
    ],
    "sg:phone":"+1 450 445 0699",
    "sg:postcode":"J3Y 3N7",
    "sg:province":"QC",
    "sg:tags":[
        "laboratory"
    ],
    "wof:name":"Laboratoire Dentaire Lumin-Art",
    "wof:placetype":"venue"
},
  "geometry": {"coordinates":[-73.422737,45.504707],"type":"Point"}
}