{
  "type": "Feature",
  "properties": {
    "iso:country":"CA",
    "sg:address":"110 Main St E",
    "sg:city":"Vankleek Hill",
    "sg:classifiers":[
        {
            "category":"Shopping",
            "subcategory":"Catalog Store",
            "type":"Retail Goods"
        }
    ],
    "sg:phone":"+1 613 678 2661",
    "sg:postcode":"K0B 1R0",
    "sg:province":"ON",
    "sg:tags":[
        "mail",
        "order",
        "internet"
    ],
    "wof:name":"Sears Canada Inc",
    "wof:placetype":"venue"
},
  "geometry": {"coordinates":[-74.6490478516,45.5186538696],"type":"Point"}
}