{
  "type": "Feature",
  "properties": {
    "iso:country":"CA",
    "sg:city":"Calgary",
    "sg:classifiers":[
        {
            "category":"Banks & Credit Unions",
            "subcategory":"Investment Brokerage",
            "type":"Services"
        }
    ],
    "sg:phone":"+1 403 239 8632",
    "sg:postcode":"T3G 3K2",
    "sg:province":"AB",
    "wof:name":"Edward Jones",
    "wof:placetype":"venue"
},
  "geometry": {"coordinates":[-114.17771911600001,51.1298522949],"type":"Point"}
}