{
  "type": "Feature",
  "properties": {
    "addr:full":"261 Main St Cardston AB T0K 0K0",
    "addr:housenumber":"261",
    "addr:postcode":"t0k 0k0",
    "addr:street":"Main St",
    "iso:country":"CA",
    "sg:address":"261 Main St",
    "sg:city":"Cardston",
    "sg:classifiers":[
        {
            "category":"Real Estate",
            "subcategory":"Real Estate Agent",
            "type":"Services"
        }
    ],
    "sg:phone":"+1 403 653 4949",
    "sg:postcode":"T0K 0K0",
    "sg:province":"AB",
    "wof:name":"Remax- Cardston Realty",
    "wof:placetype":"venue"
},
  "geometry": {"coordinates":[-113.30197099999999,49.1996],"type":"Point"}
}