{
  "type": "Feature",
  "properties": {
    "addr:full":"4011 5 St SW Calgary AB T2S 2C9",
    "addr:housenumber":"4011 5",
    "addr:postcode":"t2s 2c9",
    "addr:street":"St Sw",
    "iso:country":"CA",
    "sg:address":"4011 5 St SW",
    "sg:city":"Calgary",
    "sg:classifiers":[
        {
            "category":"Professional",
            "subcategory":"Accounting & Tax Preparation",
            "type":"Services"
        }
    ],
    "sg:phone":"+1 403 237 5505",
    "sg:postcode":"T2S 2C9",
    "sg:province":"AB",
    "sg:tags":[
        "accountant"
    ],
    "wof:name":"Dayal, U",
    "wof:placetype":"venue"
},
  "geometry": {"coordinates":[-114.076492,51.019047],"type":"Point"}
}