{
  "type": "Feature",
  "properties": {
    "addr:full":"918 2nd Ave Dunmore AB T0J 1A0",
    "addr:housenumber":"918",
    "addr:postcode":"t0j 1a0",
    "addr:street":"2Nd Ave",
    "iso:country":"CA",
    "sg:address":"918 2nd Ave",
    "sg:city":"Dunmore",
    "sg:classifiers":[
        {
            "category":"Education",
            "subcategory":"School",
            "type":"Public Place"
        }
    ],
    "sg:phone":"+1 403 527 5516",
    "sg:postcode":"T0J 1A0",
    "sg:province":"AB",
    "wof:name":"Prairie Rose Regional School",
    "wof:placetype":"venue"
},
  "geometry": {"coordinates":[-110.585701,49.969913],"type":"Point"}
}