{
  "type": "Feature",
  "properties": {
    "addr:full":"Edmonton AB T5E 5R8",
    "addr:postcode":"t5e 5r8",
    "iso:country":"CA",
    "sg:city":"Edmonton",
    "sg:classifiers":[
        {
            "category":"Health Services",
            "subcategory":"Optometrist",
            "type":"Services"
        }
    ],
    "sg:phone":"+1 780 472 7740",
    "sg:postcode":"T5E 5R8",
    "sg:province":"AB",
    "wof:name":"Total Focus Optometry",
    "wof:placetype":"venue"
},
  "geometry": {"coordinates":[-113.486763,53.597015],"type":"Point"}
}