{
  "type": "Feature",
  "properties": {
    "iso:country":"CA",
    "sg:city":"Rosemere",
    "sg:classifiers":[
        {
            "category":"Education",
            "subcategory":"Dance Studio",
            "type":"Public Place"
        }
    ],
    "sg:phone":"+1 450 965 0311",
    "sg:postcode":"J7A 4K3",
    "sg:province":"QC",
    "sg:tags":[
        "instruction",
        "dancing"
    ],
    "wof:name":"Amydanse Studio",
    "wof:placetype":"venue"
},
  "geometry": {"coordinates":[-73.78405761720001,45.6516914368],"type":"Point"}
}