{
  "type": "Feature",
  "properties": {
    "addr:full":"6 Sanford Ave N Hamilton ON L8L 5Y6",
    "addr:housenumber":"6",
    "addr:postcode":"l8l 5y6",
    "addr:street":"Sanford Ave N",
    "iso:country":"CA",
    "sg:address":"6 Sanford Ave N",
    "sg:city":"Hamilton",
    "sg:classifiers":[
        {
            "category":"Retail",
            "subcategory":"Auto Repair",
            "type":"Services"
        }
    ],
    "sg:phone":"+1 905 525 5323",
    "sg:postcode":"L8L 5Y6",
    "sg:province":"ON",
    "sg:tags":[
        "transmission",
        "automobile",
        "repairing"
    ],
    "wof:name":"Danny's Transmission Svc Ltd",
    "wof:placetype":"venue"
},
  "geometry": {"coordinates":[-79.84609985349999,43.2519874573],"type":"Point"}
}