{
  "type": "Feature",
  "properties": {
    "addr:full":"Wainfleet ON L0S 1V0",
    "addr:postcode":"l0s 1v0",
    "iso:country":"CA",
    "sg:city":"Wainfleet",
    "sg:classifiers":[
        {
            "category":"Organizations",
            "subcategory":"Religious Organization",
            "type":"Services"
        }
    ],
    "sg:phone":"+1 905 899 1343",
    "sg:postcode":"L0S 1V0",
    "sg:province":"ON",
    "sg:tags":[
        "church"
    ],
    "wof:name":"Wainfleet Brethren in Christ",
    "wof:placetype":"venue"
},
  "geometry": {"coordinates":[-79.42955000000001,42.94339],"type":"Point"}
}