{
  "type": "Feature",
  "properties": {
    "addr:full":"433 Main St Winnipeg MB R3B 1B3",
    "addr:housenumber":"433",
    "addr:postcode":"r3b 1b3",
    "addr:street":"Main St",
    "iso:country":"CA",
    "sg:address":"433 Main St",
    "sg:city":"Winnipeg",
    "sg:classifiers":[
        {
            "category":"Banks & Credit Unions",
            "subcategory":"Bank",
            "type":"Services"
        }
    ],
    "sg:phone":"+1 204 942 5149",
    "sg:postcode":"R3B 1B3",
    "sg:province":"MB",
    "wof:name":"Civic Credit Union",
    "wof:placetype":"venue"
},
  "geometry": {"coordinates":[-97.13858,49.897545],"type":"Point"}
}