{
  "type": "Feature",
  "properties": {
    "addr:full":"183 Principale Saint-Aime-Des-Lacs QC G0T 1S0",
    "addr:housenumber":"183",
    "addr:postcode":"g0t 1s0",
    "addr:street":"Principale Saint-Aime-Des-Lacs",
    "iso:country":"CA",
    "sg:address":"183 Principale",
    "sg:city":"Saint-Aime-Des-Lacs",
    "sg:classifiers":[
        {
            "category":"Recreation",
            "type":"Entertainment"
        }
    ],
    "sg:phone":"+1 418 439 4660",
    "sg:postcode":"G0T 1S0",
    "sg:province":"QC",
    "sg:tags":[
        "charter",
        "boat"
    ],
    "wof:name":"Camping Sport Action",
    "wof:placetype":"venue"
},
  "geometry": {"coordinates":[-70.335587,47.690407],"type":"Point"}
}