{
  "type": "Feature",
  "properties": {
    "addr:full":"957 Granville St Vancouver BC V6Z 1L3",
    "addr:housenumber":"957",
    "addr:postcode":"v6z 1l3",
    "addr:street":"Granville St",
    "iso:country":"CA",
    "sg:address":"957 Granville St",
    "sg:city":"Vancouver",
    "sg:classifiers":[
        {
            "category":"Bars & Pubs",
            "type":"Food & Drink"
        }
    ],
    "sg:phone":"+1 604 633 0056",
    "sg:postcode":"V6Z 1L3",
    "sg:province":"BC",
    "wof:name":"Granville Room",
    "wof:placetype":"venue"
},
  "geometry": {"coordinates":[-123.122451782,49.2798423767],"type":"Point"}
}