{
  "type": "Feature",
  "properties": {
    "iso:country":"CA",
    "sg:address":"241 Rue Jarry E",
    "sg:city":"Montreal",
    "sg:classifiers":[
        {
            "category":"Food & Beverages",
            "subcategory":"Groceries & Convenience Stores",
            "type":"Retail Goods"
        }
    ],
    "sg:phone":"+1 514 388 5972",
    "sg:postcode":"H2P 1T6",
    "sg:province":"QC",
    "sg:tags":[
        "grocer"
    ],
    "wof:name":"Depanneur Vadeboncoeur",
    "wof:placetype":"venue"
},
  "geometry": {"coordinates":[-73.6303329468,45.5410270691],"type":"Point"}
}