{
  "type": "Feature",
  "properties": {
    "addr:full":"770 Main St # 200 Moncton NB E1C 1E7",
    "addr:housenumber":"770",
    "addr:postcode":"e1c 1e7",
    "addr:street":"Main St # 200",
    "iso:country":"CA",
    "sg:address":"770 Main St # 200",
    "sg:city":"Moncton",
    "sg:classifiers":[
        {
            "category":"Insurance",
            "subcategory":"Insurance Agent",
            "type":"Services"
        }
    ],
    "sg:phone":"+1 506 857 0064",
    "sg:postcode":"E1C 1E7",
    "sg:province":"NB",
    "wof:name":"Caissie, Luc",
    "wof:placetype":"venue"
},
  "geometry": {"coordinates":[-64.7780456543,46.0883369446],"type":"Point"}
}