{
  "type": "Feature",
  "properties": {
    "addr:full":"1251 Rue Rachel E Montreal QC H2J 2J9",
    "addr:housenumber":"1251",
    "addr:postcode":"h2j 2j9",
    "addr:street":"Rue Rachel E",
    "iso:country":"CA",
    "sg:address":"1251 Rue Rachel E",
    "sg:city":"Montreal",
    "sg:classifiers":[
        {
            "category":"Travel",
            "subcategory":"Travel Agent",
            "type":"Entertainment"
        }
    ],
    "sg:phone":"+1 514 521 8356",
    "sg:postcode":"H2J 2J9",
    "sg:province":"QC",
    "sg:tags":[
        "agency",
        "bureau"
    ],
    "wof:name":"Voyages Tour DE L'Ile",
    "wof:placetype":"venue"
},
  "geometry": {"coordinates":[-73.572929,45.527061],"type":"Point"}
}