{
  "type": "Feature",
  "properties": {
    "addr:full":"New Westminster BC V3L 5N7",
    "addr:postcode":"v3l 5n7",
    "iso:country":"CA",
    "sg:city":"New Westminster",
    "sg:classifiers":[
        {
            "category":"Shopping",
            "type":"Retail Goods"
        }
    ],
    "sg:phone":"+1 604 521 2611",
    "sg:postcode":"V3L 5N7",
    "sg:province":"BC",
    "sg:tags":[
        "monument"
    ],
    "wof:name":"Remco Memorials Ltd",
    "wof:placetype":"venue"
},
  "geometry": {"coordinates":[-122.909568787,49.2063407898],"type":"Point"}
}