{
  "type": "Feature",
  "properties": {
    "addr:full":"Thurso QC J0X 3B0",
    "addr:postcode":"j0x 3b0",
    "iso:country":"CA",
    "sg:city":"Thurso",
    "sg:classifiers":[
        {
            "category":"Real Estate",
            "subcategory":"Real Estate Agent",
            "type":"Services"
        }
    ],
    "sg:phone":"+1 819 985 3406",
    "sg:postcode":"J0X 3B0",
    "sg:province":"QC",
    "sg:tags":[
        "cooperative"
    ],
    "wof:name":"Cooperative Agro Alimentaire",
    "wof:placetype":"venue"
},
  "geometry": {"coordinates":[-75.2306060791,45.6112289429],"type":"Point"}
}