{
  "type": "Feature",
  "properties": {
    "iso:country":"CA",
    "sg:address":"5124 50 St",
    "sg:city":"Hardisty",
    "sg:classifiers":[
        {
            "category":"Food & Beverages",
            "subcategory":"Liquor & Beverages",
            "type":"Retail Goods"
        }
    ],
    "sg:phone":"+1 780 888 3857",
    "sg:postcode":"T0B 1V0",
    "sg:province":"AB",
    "sg:tags":[
        "convenience",
        "store"
    ],
    "wof:name":"Flag City Confectionery",
    "wof:placetype":"venue"
},
  "geometry": {"coordinates":[-111.30342865,52.6762542725],"type":"Point"}
}