{
  "type": "Feature",
  "properties": {
    "addr:full":"PO Box 3295 STN Lcd 1 Langley BC V3A 4R6",
    "addr:housenumber":"po;1",
    "addr:postcode":"3295;v3a 4r6",
    "addr:street":"Box;Lcd",
    "iso:country":"CA",
    "sg:address":"PO Box 3295 STN Lcd 1",
    "sg:city":"Langley",
    "sg:classifiers":[
        {
            "category":"Manufacturing",
            "subcategory":"Rubber & Plastics",
            "type":"Manufacturing & Wholesale Goods"
        }
    ],
    "sg:phone":"+1 604 530 3123",
    "sg:postcode":"V3A 4R6",
    "sg:province":"BC",
    "wof:name":"Marc Industries Ltd",
    "wof:placetype":"venue"
},
  "geometry": {"coordinates":[-122.65657,49.104122],"type":"Point"}
}