{
  "type": "Feature",
  "properties": {
    "addr:full":"3813 Boul Harvey Jonquiere QC G7X 3A1",
    "addr:housenumber":"3813",
    "addr:postcode":"g7x 3a1",
    "addr:street":"Boul Harvey",
    "iso:country":"CA",
    "sg:address":"3813 Boul Harvey",
    "sg:city":"Jonquiere",
    "sg:classifiers":[
        {
            "category":"Retail",
            "subcategory":"Auto Repair",
            "type":"Services"
        }
    ],
    "sg:phone":"+1 418 547 4731",
    "sg:postcode":"G7X 3A1",
    "sg:province":"QC",
    "sg:tags":[
        "repairing",
        "automobile"
    ],
    "wof:name":"Monsieur Muffler",
    "wof:placetype":"venue"
},
  "geometry": {"coordinates":[-71.245209,48.413055],"type":"Point"}
}