{
  "type": "Feature",
  "properties": {
    "addr:full":"703 the Queensway Etobicoke ON M8Y 1L2",
    "addr:housenumber":"703",
    "addr:postcode":"m8y 1l2",
    "addr:street":"The Queensway",
    "iso:country":"CA",
    "sg:address":"703 the Queensway",
    "sg:city":"Etobicoke",
    "sg:classifiers":[
        {
            "category":"Home & Garden",
            "subcategory":"Building Materials",
            "type":"Retail Goods"
        }
    ],
    "sg:phone":"+1 416 252 6868",
    "sg:postcode":"M8Y 1L2",
    "sg:province":"ON",
    "sg:tags":[
        "craft",
        "leaded",
        "supply"
    ],
    "wof:name":"Fantasy in Glass Glassworks",
    "wof:placetype":"venue"
},
  "geometry": {"coordinates":[-79.5009231567,43.62657547],"type":"Point"}
}