{
  "type": "Feature",
  "properties": {
    "iso:country":"CA",
    "sg:city":"Napanee",
    "sg:classifiers":[
        {
            "category":"Building & Trades",
            "subcategory":"Landscaping Services",
            "type":"Services"
        }
    ],
    "sg:phone":"+1 613 354 3255",
    "sg:postcode":"K7R 3K8",
    "sg:province":"ON",
    "sg:tags":[
        "landscape",
        "contractor"
    ],
    "wof:name":"Griffiths, Ralph B",
    "wof:placetype":"venue"
},
  "geometry": {"coordinates":[-76.9515838623,44.2483253479],"type":"Point"}
}