{
  "type": "Feature",
  "properties": {
    "addr:full":"40 Waterloo St Brantford ON N3T 3R7",
    "addr:housenumber":"40",
    "addr:postcode":"n3t 3r7",
    "addr:street":"Waterloo St",
    "iso:country":"CA",
    "sg:address":"40 Waterloo St",
    "sg:city":"Brantford",
    "sg:classifiers":[
        {
            "category":"Retail",
            "subcategory":"Portrait Studio",
            "type":"Services"
        }
    ],
    "sg:phone":"+1 519 753 0701",
    "sg:postcode":"N3T 3R7",
    "sg:province":"ON",
    "sg:tags":[
        "photographer"
    ],
    "wof:name":"Tomkins Photography Svc",
    "wof:placetype":"venue"
},
  "geometry": {"coordinates":[-80.2716751099,43.1419219971],"type":"Point"}
}