{
  "type": "Feature",
  "properties": {
    "addr:full":"850 Airport Rd Timmins ON P4N 7C3",
    "addr:housenumber":"850",
    "addr:postcode":"p4n 7c3",
    "addr:street":"Airport Rd",
    "iso:country":"CA",
    "sg:address":"850 Airport Rd",
    "sg:city":"Timmins",
    "sg:classifiers":[
        {
            "category":"Social Services",
            "subcategory":"Child Care",
            "type":"Services"
        }
    ],
    "sg:phone":"+1 705 268 8687",
    "sg:postcode":"P4N 7C3",
    "sg:province":"ON",
    "wof:name":"Sonshine Nursery School",
    "wof:placetype":"venue"
},
  "geometry": {"coordinates":[-81.3560256958,48.5004119873],"type":"Point"}
}