{
  "type": "Feature",
  "properties": {
    "addr:full":"5408 Chief Lake Rd Prince George BC V2K 5R1",
    "addr:housenumber":"5408",
    "addr:postcode":"v2k 5r1",
    "addr:street":"Chief Lake Rd",
    "iso:country":"CA",
    "sg:address":"5408 Chief Lake Rd",
    "sg:city":"Prince George",
    "sg:classifiers":[
        {
            "category":"Manufacturing",
            "subcategory":"Lumber",
            "type":"Manufacturing & Wholesale Goods"
        }
    ],
    "sg:phone":"+1 250 962 8639",
    "sg:postcode":"V2K 5R1",
    "sg:province":"BC",
    "sg:tags":[
        "company",
        "logging"
    ],
    "wof:name":"Den-Mit Enterprises Ltd",
    "wof:placetype":"venue"
},
  "geometry": {"coordinates":[-122.817398,54.009544],"type":"Point"}
}