{
  "type": "Feature",
  "properties": {
    "iso:country":"CA",
    "sg:address":"458 Markham St",
    "sg:city":"Toronto",
    "sg:classifiers":[
        {
            "category":"Health Services",
            "subcategory":"Doctor",
            "type":"Services"
        }
    ],
    "sg:phone":"+1 416 536 1300",
    "sg:postcode":"M6G 2L2",
    "sg:province":"ON",
    "sg:tags":[
        "dentist"
    ],
    "wof:name":"Kazmierowski, A DDS",
    "wof:placetype":"venue"
},
  "geometry": {"coordinates":[-79.41105651860001,43.6610298157],"type":"Point"}
}