{
  "type": "Feature",
  "properties": {
    "addr:full":"55 Front St S Orillia ON L3V 4S2",
    "addr:housenumber":"55",
    "addr:postcode":"l3v 4s2",
    "addr:street":"Front St S",
    "iso:country":"CA",
    "sg:address":"55 Front St S",
    "sg:city":"Orillia",
    "sg:classifiers":[
        {
            "category":"Restaurant",
            "type":"Food & Drink"
        }
    ],
    "sg:phone":"+1 705 326 2626",
    "sg:postcode":"L3V 4S2",
    "sg:province":"ON",
    "sg:tags":[
        "pizza"
    ],
    "wof:name":"Pizzaville",
    "wof:placetype":"venue"
},
  "geometry": {"coordinates":[-79.41381072999999,44.609046936],"type":"Point"}
}