{
  "type": "Feature",
  "properties": {
    "addr:full":"201 4th Ave W Owen Sound ON N4K 4V1",
    "addr:housenumber":"201",
    "addr:postcode":"n4k 4v1",
    "addr:street":"4Th Ave W",
    "iso:country":"CA",
    "sg:address":"201 4th Ave W",
    "sg:city":"Owen Sound",
    "sg:classifiers":[
        {
            "category":"Organizations",
            "subcategory":"Religious Organization",
            "type":"Services"
        }
    ],
    "sg:phone":"+1 519 376 8411",
    "sg:postcode":"N4K 4V1",
    "sg:province":"ON",
    "sg:tags":[
        "church"
    ],
    "wof:name":"First Christian Reformed",
    "wof:placetype":"venue"
},
  "geometry": {"coordinates":[-80.945831,44.551785],"type":"Point"}
}