{
  "type": "Feature",
  "properties": {
    "iso:country":"CA",
    "sg:city":"Scarborough",
    "sg:classifiers":[
        {
            "category":"Health Services",
            "subcategory":"Doctor",
            "type":"Services"
        }
    ],
    "sg:phone":"+1 416 284 8153",
    "sg:postcode":"M1E 3E6",
    "sg:province":"ON",
    "sg:tags":[
        "dentist"
    ],
    "wof:name":"Patrician, Michael W DDS",
    "wof:placetype":"venue"
},
  "geometry": {"coordinates":[-79.1860733032,43.7688293457],"type":"Point"}
}