{
  "type": "Feature",
  "properties": {
    "addr:full":"75 Ch Jette Sainte-Sabine QC J0J 2B0",
    "addr:housenumber":"75",
    "addr:postcode":"j0j 2b0",
    "addr:street":"Ch Jette",
    "iso:country":"CA",
    "sg:address":"75 Ch Jette",
    "sg:city":"Sainte-Sabine",
    "sg:classifiers":[
        {
            "category":"Wholesale",
            "subcategory":"Meat",
            "type":"Manufacturing & Wholesale Goods"
        }
    ],
    "sg:phone":"+1 450 293 5061",
    "sg:postcode":"J0J 2B0",
    "sg:province":"QC",
    "sg:tags":[
        "packer",
        "butchering"
    ],
    "wof:name":"Abattoir Gicaso Enr",
    "wof:placetype":"venue"
},
  "geometry": {"coordinates":[-72.9904556274,45.2463302612],"type":"Point"}
}