{
  "type": "Feature",
  "properties": {
    "addr:full":"380 Av Laurier O Montreal QC H2V 2K7",
    "addr:housenumber":"380",
    "addr:postcode":"h2v 2k7",
    "addr:street":"Av Laurier O",
    "iso:country":"CA",
    "sg:address":"380 Av Laurier O",
    "sg:city":"Montreal",
    "sg:classifiers":[
        {
            "category":"Cinema",
            "subcategory":"Movie Rental",
            "type":"Entertainment"
        }
    ],
    "sg:phone":"+1 514 277 6979",
    "sg:postcode":"H2V 2K7",
    "sg:province":"QC",
    "sg:tags":[
        "leasing",
        "video",
        "disc",
        "tape"
    ],
    "wof:name":"Boite Noire Outremont",
    "wof:placetype":"venue"
},
  "geometry": {"coordinates":[-73.58954620359999,45.5266151428],"type":"Point"}
}