{
  "type": "Feature",
  "properties": {
    "addr:full":"Red Deer AB T4N 1S6",
    "addr:postcode":"t4n 1s6",
    "iso:country":"CA",
    "sg:city":"Red Deer",
    "sg:classifiers":[
        {
            "category":"Professional",
            "subcategory":"Accounting & Tax Preparation",
            "type":"Services"
        }
    ],
    "sg:phone":"+1 403 342 2229",
    "sg:postcode":"T4N 1S6",
    "sg:province":"AB",
    "sg:tags":[
        "accountant"
    ],
    "wof:name":"Bowers, Alan J",
    "wof:placetype":"venue"
},
  "geometry": {"coordinates":[-113.80937957800001,52.2668914795],"type":"Point"}
}