{
  "type": "Feature",
  "properties": {
    "addr:full":"19278 56 Ave Surrey BC V3S 6K4",
    "addr:housenumber":"19278",
    "addr:postcode":"v3s 6k4",
    "addr:street":"56 Ave",
    "iso:country":"CA",
    "sg:address":"19278 56 Ave",
    "sg:city":"Surrey",
    "sg:classifiers":[
        {
            "category":"Manufacturing",
            "subcategory":"Lumber",
            "type":"Manufacturing & Wholesale Goods"
        }
    ],
    "sg:phone":"+1 604 533 3431",
    "sg:postcode":"V3S 6K4",
    "sg:province":"BC",
    "wof:name":"Central Cedar Ltd",
    "wof:placetype":"venue"
},
  "geometry": {"coordinates":[-122.68938446,49.1043395996],"type":"Point"}
}