{
  "type": "Feature",
  "properties": {
    "addr:full":"172 Rue Principale N Sacre-Coeur-Saguenay QC G0T 1Y0",
    "addr:housenumber":"172",
    "addr:postcode":"g0t 1y0",
    "addr:street":"Rue Principale N",
    "iso:country":"CA",
    "sg:address":"172 Rue Principale N",
    "sg:city":"Sacre-Coeur-Saguenay",
    "sg:classifiers":[
        {
            "category":"Home & Garden",
            "subcategory":"Hardware",
            "type":"Retail Goods"
        }
    ],
    "sg:phone":"+1 418 236 4897",
    "sg:postcode":"G0T 1Y0",
    "sg:province":"QC",
    "wof:name":"Laurian Dufour Rona",
    "wof:placetype":"venue"
},
  "geometry": {"coordinates":[-69.805817,48.238022],"type":"Point"}
}