{
  "type": "Feature",
  "properties": {
    "addr:full":"180 Mary St Hamilton ON L8L 4V8",
    "addr:housenumber":"180",
    "addr:postcode":"l8l 4v8",
    "addr:street":"Mary St",
    "iso:country":"CA",
    "sg:address":"180 Mary St",
    "sg:city":"Hamilton",
    "sg:classifiers":[
        {
            "category":"Manufacturing",
            "subcategory":"Printing",
            "type":"Manufacturing & Wholesale Goods"
        }
    ],
    "sg:phone":"+1 905 527 2326",
    "sg:postcode":"L8L 4V8",
    "sg:province":"ON",
    "sg:tags":[
        "printer"
    ],
    "wof:name":"Seagers Press",
    "wof:placetype":"venue"
},
  "geometry": {"coordinates":[-79.8616409302,43.2602539062],"type":"Point"}
}