{
  "type": "Feature",
  "properties": {
    "addr:full":"82 Boul Salaberry S Chateauguay QC J6J 4J6",
    "addr:housenumber":"82",
    "addr:postcode":"j6j 4j6",
    "addr:street":"Boul Salaberry S Chateauguay",
    "iso:country":"CA",
    "sg:address":"82 Boul Salaberry S",
    "sg:city":"Chateauguay",
    "sg:classifiers":[
        {
            "category":"Manufacturing",
            "subcategory":"Printing",
            "type":"Manufacturing & Wholesale Goods"
        }
    ],
    "sg:phone":"+1 450 692 8552",
    "sg:postcode":"J6J 4J6",
    "sg:province":"QC",
    "sg:tags":[
        "newspaper"
    ],
    "wof:name":"Journal Le Soleil-St-Laurent",
    "wof:placetype":"venue"
},
  "geometry": {"coordinates":[-73.745010376,45.3618812561],"type":"Point"}
}