{
  "type": "Feature",
  "properties": {
    "addr:full":"4997 Rice Lake Dr Bewdley ON K0L 1E0",
    "addr:housenumber":"4997",
    "addr:postcode":"k0l 1e0",
    "addr:street":"Rice Lake Dr",
    "iso:country":"CA",
    "sg:address":"4997 Rice Lake Dr",
    "sg:city":"Bewdley",
    "sg:classifiers":[
        {
            "category":"Recreation",
            "type":"Entertainment"
        }
    ],
    "sg:phone":"+1 905 797 2877",
    "sg:postcode":"K0L 1E0",
    "sg:province":"ON",
    "sg:tags":[
        "charter",
        "boat"
    ],
    "wof:name":"Captains Marina",
    "wof:placetype":"venue"
},
  "geometry": {"coordinates":[-78.3159484863,44.0819969177],"type":"Point"}
}