{
  "type": "Feature",
  "properties": {
    "addr:full":"2120 Thurston Dr Ottawa ON K1G 6E1",
    "addr:housenumber":"2120",
    "addr:postcode":"k1g 6e1",
    "addr:street":"Thurston Dr",
    "iso:country":"CA",
    "sg:address":"2120 Thurston Dr",
    "sg:city":"Ottawa",
    "sg:classifiers":[
        {
            "category":"Home & Garden",
            "subcategory":"Furniture",
            "type":"Retail Goods"
        }
    ],
    "sg:phone":"+1 613 521 2545",
    "sg:postcode":"K1G 6E1",
    "sg:province":"ON",
    "sg:tags":[
        "equipment",
        "kitchen",
        "cabinet"
    ],
    "wof:name":"Multiplex Kitchens",
    "wof:placetype":"venue"
},
  "geometry": {"coordinates":[-75.6209487915,45.3796691895],"type":"Point"}
}