{
  "type": "Feature",
  "properties": {
    "addr:full":"100 Esplanade Ave Harrison Hot Springs BC V0M 1K0",
    "addr:housenumber":"100",
    "addr:postcode":"v0m 1k0",
    "addr:street":"Esplanade Ave",
    "iso:country":"CA",
    "sg:address":"100 Esplanade Ave",
    "sg:city":"Harrison Hot Springs",
    "sg:classifiers":[
        {
            "category":"Recreation",
            "type":"Entertainment"
        }
    ],
    "sg:phone":"+1 604 796 2244",
    "sg:postcode":"V0M 1K0",
    "sg:province":"BC",
    "sg:tags":[
        "resort",
        "golf"
    ],
    "wof:name":"Harrison Hot Springs Resort",
    "wof:placetype":"venue"
},
  "geometry": {"coordinates":[-121.787598,49.303539],"type":"Point"}
}