{
  "type": "Feature",
  "properties": {
    "iso:country":"CA",
    "sg:address":"12770 116 Ave",
    "sg:city":"Surrey",
    "sg:classifiers":[
        {
            "category":"Manufacturing",
            "subcategory":"Lumber",
            "type":"Manufacturing & Wholesale Goods"
        }
    ],
    "sg:phone":"+1 604 580 2781",
    "sg:postcode":"V3V 7H9",
    "sg:province":"BC",
    "wof:name":"Mill & Timber Products Ltd",
    "wof:placetype":"venue"
},
  "geometry": {"coordinates":[-122.868438721,49.213344574],"type":"Point"}
}