{
  "type": "Feature",
  "properties": {
    "addr:full":"425 Adelaide St Dalhousie NB E8C 1B7",
    "addr:housenumber":"425",
    "addr:postcode":"e8c 1b7",
    "addr:street":"Adelaide St",
    "iso:country":"CA",
    "sg:address":"425 Adelaide St",
    "sg:city":"Dalhousie",
    "sg:classifiers":[
        {
            "category":"Building & Trades",
            "subcategory":"Electrical",
            "type":"Services"
        }
    ],
    "sg:phone":"+1 506 684 3797",
    "sg:postcode":"E8C 1B7",
    "sg:province":"NB",
    "sg:tags":[
        "electric",
        "contractor"
    ],
    "wof:name":"Cfm Electrical Contractor CO",
    "wof:placetype":"venue"
},
  "geometry": {"coordinates":[-66.37897491459999,48.0655136108],"type":"Point"}
}