{
  "type": "Feature",
  "properties": {
    "addr:full":"1134 Smythe Street Fredericton NB E3B 3H5",
    "addr:housenumber":"1134",
    "addr:postcode":"e3b 3h5",
    "addr:street":"Smythe Street",
    "iso:country":"CA",
    "sg:address":"1134 Smythe Street",
    "sg:city":"Fredericton",
    "sg:classifiers":[
        {
            "category":"Shopping",
            "subcategory":"Clothing, Apparel, & Fashions",
            "type":"Retail Goods"
        }
    ],
    "sg:phone":"+1 506 455 0595",
    "sg:postcode":"E3B 3H5",
    "sg:province":"NB",
    "wof:name":"Penningtons Superstore",
    "wof:placetype":"venue"
},
  "geometry": {"coordinates":[-66.66789199999999,45.944408],"type":"Point"}
}