{
  "type": "Feature",
  "properties": {
    "addr:full":"233 3rd Ave NW Swan River MB R0L 1Z0",
    "addr:housenumber":"233",
    "addr:postcode":"r0l 1z0",
    "addr:street":"3Rd Ave Nw",
    "iso:country":"CA",
    "sg:address":"233 3rd Ave NW",
    "sg:city":"Swan River",
    "sg:classifiers":[
        {
            "category":"Building & Trades",
            "subcategory":"Construction",
            "type":"Services"
        }
    ],
    "sg:phone":"+1 204 734 4732",
    "sg:postcode":"R0L 1Z0",
    "sg:province":"MB",
    "sg:tags":[
        "woodworker"
    ],
    "wof:name":"Leon's Woodwork",
    "wof:placetype":"venue"
},
  "geometry": {"coordinates":[-101.267944336,52.092918396],"type":"Point"}
}