{
  "type": "Feature",
  "properties": {
    "iso:country":"CA",
    "sg:address":"350 Rue Saint-Paul E",
    "sg:city":"Montreal",
    "sg:classifiers":[
        {
            "category":"Manufacturing",
            "subcategory":"Printing",
            "type":"Manufacturing & Wholesale Goods"
        }
    ],
    "sg:phone":"+1 514 398 0720",
    "sg:postcode":"H2Y 1H2",
    "sg:province":"QC",
    "sg:tags":[
        "publisher",
        "art"
    ],
    "wof:name":"Begin Edition Intl Inc",
    "wof:placetype":"venue"
},
  "geometry": {"coordinates":[-73.5517196655,45.5090255737],"type":"Point"}
}