{
  "type": "Feature",
  "properties": {
    "addr:full":"901 the Rapids Pky Sarnia ON N7S 6K2",
    "addr:housenumber":"901",
    "addr:postcode":"n7s 6k2",
    "addr:street":"The Rapids Pky",
    "iso:country":"CA",
    "sg:address":"901 the Rapids Pky",
    "sg:city":"Sarnia",
    "sg:classifiers":[
        {
            "category":"Education",
            "subcategory":"School",
            "type":"Public Place"
        }
    ],
    "sg:phone":"+1 519 542 1055",
    "sg:postcode":"N7S 6K2",
    "sg:province":"ON",
    "wof:name":"Ecole Sec St Francois Xavier",
    "wof:placetype":"venue"
},
  "geometry": {"coordinates":[-82.349884,43.001556],"type":"Point"}
}