{
  "type": "Feature",
  "properties": {
    "addr:full":"245 Wallace Ave N Listowel ON N4W 1L1",
    "addr:housenumber":"245",
    "addr:postcode":"n4w 1l1",
    "addr:street":"Wallace Ave N",
    "iso:country":"CA",
    "sg:address":"245 Wallace Ave N",
    "sg:city":"Listowel",
    "sg:classifiers":[
        {
            "category":"Banks & Credit Unions",
            "subcategory":"Bank",
            "type":"Services"
        }
    ],
    "sg:phone":"+1 519 291 3800",
    "sg:postcode":"N4W 1L1",
    "sg:province":"ON",
    "sg:tags":[
        "loan",
        "real estate"
    ],
    "wof:name":"Citifinancial",
    "wof:placetype":"venue"
},
  "geometry": {"coordinates":[-80.9522476196,43.7329978943],"type":"Point"}
}