{
  "type": "Feature",
  "properties": {
    "addr:full":"901 Rue Notre-Dame Repentigny QC J5Y 1C6",
    "addr:housenumber":"901",
    "addr:postcode":"j5y 1c6",
    "addr:street":"Rue Notre-Dame",
    "iso:country":"CA",
    "sg:address":"901 Rue Notre-Dame",
    "sg:city":"Repentigny",
    "sg:classifiers":[
        {
            "category":"Professional",
            "subcategory":"Art Services",
            "type":"Services"
        }
    ],
    "sg:phone":"+1 450 654 7093",
    "sg:postcode":"J5Y 1C6",
    "sg:province":"QC",
    "sg:tags":[
        "graphic",
        "printer",
        "designer"
    ],
    "wof:name":"Imprimerie Jacques Ross",
    "wof:placetype":"venue"
},
  "geometry": {"coordinates":[-73.41849499999999,45.767208],"type":"Point"}
}