{
  "type": "Feature",
  "properties": {
    "addr:full":"1786 Weston Rd York ON M9N 1V8",
    "addr:housenumber":"1786",
    "addr:postcode":"m9n 1v8",
    "addr:street":"Weston Rd",
    "iso:country":"CA",
    "sg:address":"1786 Weston Rd",
    "sg:city":"York",
    "sg:classifiers":[
        {
            "category":"Retail",
            "subcategory":"Laundry & Dry Cleaning",
            "type":"Services"
        }
    ],
    "sg:phone":"+1 416 248 9274",
    "sg:postcode":"M9N 1V8",
    "sg:province":"ON",
    "sg:tags":[
        "cleaners"
    ],
    "wof:name":"Mega Wash Coin Laundry & Dry",
    "wof:placetype":"venue"
},
  "geometry": {"coordinates":[-79.5129394531,43.6987991333],"type":"Point"}
}