{
  "type": "Feature",
  "properties": {
    "addr:full":"Dundurn SK S0K 1K0",
    "addr:postcode":"s0k 1k0",
    "iso:country":"CA",
    "sg:city":"Dundurn",
    "sg:classifiers":[
        {
            "category":"Travel",
            "subcategory":"Travel Agent",
            "type":"Entertainment"
        }
    ],
    "sg:phone":"+1 306 310 7253",
    "sg:postcode":"S0K 1K0",
    "sg:province":"SK",
    "sg:tags":[
        "agency",
        "bureau"
    ],
    "wof:name":"Sask Tel",
    "wof:placetype":"venue"
},
  "geometry": {"coordinates":[-106.50012207,51.8109817505],"type":"Point"}
}