{
  "type": "Feature",
  "properties": {
    "addr:full":"555 Island Hwy E Parksville BC V9P 1T5",
    "addr:housenumber":"555",
    "addr:postcode":"v9p 1t5",
    "addr:street":"Island Hwy E",
    "iso:country":"CA",
    "sg:address":"555 Island Hwy E",
    "sg:city":"Parksville",
    "sg:classifiers":[
        {
            "category":"Autos & Motor Vehicles",
            "subcategory":"Auto Supplies",
            "type":"Retail Goods"
        }
    ],
    "sg:phone":"+1 250 248 2055",
    "sg:postcode":"V9P 1T5",
    "sg:province":"BC",
    "sg:tags":[
        "repairing",
        "automobile"
    ],
    "wof:name":"Sidney Tire Ltd",
    "wof:placetype":"venue"
},
  "geometry": {"coordinates":[-124.295174,49.317638],"type":"Point"}
}