{
  "type": "Feature",
  "properties": {
    "addr:full":"4553 Boul Saint-Laurent Montreal QC H2T 1R2",
    "addr:housenumber":"4553",
    "addr:postcode":"h2t 1r2",
    "addr:street":"Boul Saint-Laurent",
    "iso:country":"CA",
    "sg:address":"4553 Boul Saint-Laurent",
    "sg:city":"Montreal",
    "sg:classifiers":[
        {
            "category":"Wholesale",
            "subcategory":"Groceries",
            "type":"Manufacturing & Wholesale Goods"
        }
    ],
    "sg:phone":"+1 514 289 8786",
    "sg:postcode":"H2T 1R2",
    "sg:province":"QC",
    "sg:tags":[
        "grocer"
    ],
    "wof:name":"Marche Picado",
    "wof:placetype":"venue"
},
  "geometry": {"coordinates":[-73.5869522095,45.5205459595],"type":"Point"}
}