{
  "type": "Feature",
  "properties": {
    "iso:country":"CA",
    "sg:city":"Sudbury",
    "sg:classifiers":[
        {
            "category":"Freight",
            "type":"Transportation"
        }
    ],
    "sg:phone":"+1 705 522 0683",
    "sg:postcode":"P3E 2M7",
    "sg:province":"ON",
    "sg:tags":[
        "delivery",
        "courier"
    ],
    "wof:name":"Crash Courier",
    "wof:placetype":"venue"
},
  "geometry": {"coordinates":[-81.000458,46.459999],"type":"Point"}
}