{
  "type": "Feature",
  "properties": {
    "addr:full":"2834 Rue Lafleche Saint-Paulin QC J0K 3G0",
    "addr:housenumber":"2834",
    "addr:postcode":"j0k 3g0",
    "addr:street":"Rue Lafleche",
    "iso:country":"CA",
    "sg:address":"2834 Rue Lafleche",
    "sg:city":"Saint-Paulin",
    "sg:classifiers":[
        {
            "category":"Personal",
            "subcategory":"Beauty Salon",
            "type":"Services"
        }
    ],
    "sg:phone":"+1 819 268 2627",
    "sg:postcode":"J0K 3G0",
    "sg:province":"QC",
    "wof:name":"Salon Rodolphe Plourde",
    "wof:placetype":"venue"
},
  "geometry": {"coordinates":[-73.012894,46.418468],"type":"Point"}
}