{
  "type": "Feature",
  "properties": {
    "addr:full":"4515 25 St SE Calgary AB T2B 3R9",
    "addr:housenumber":"4515",
    "addr:postcode":"t2b 3r9",
    "addr:street":"25 St Se",
    "iso:country":"CA",
    "sg:address":"4515 25 St SE",
    "sg:city":"Calgary",
    "sg:classifiers":[
        {
            "category":"Restaurant",
            "type":"Food & Drink"
        }
    ],
    "sg:phone":"+1 403 248 0700",
    "sg:postcode":"T2B 3R9",
    "sg:province":"AB",
    "wof:name":"Denny's Restaurant",
    "wof:placetype":"venue"
},
  "geometry": {"coordinates":[-113.999405,51.014797],"type":"Point"}
}