{
  "type": "Feature",
  "properties": {
    "iso:country":"CA",
    "sg:address":"6091 Gilbert Rd # 750",
    "sg:city":"Richmond",
    "sg:classifiers":[
        {
            "category":"Health Services",
            "subcategory":"Doctor",
            "type":"Services"
        }
    ],
    "sg:phone":"+1 604 273 1555",
    "sg:postcode":"V7C 5L9",
    "sg:province":"BC",
    "sg:tags":[
        "physician",
        "surgeon"
    ],
    "wof:name":"Richmond Cardiology",
    "wof:placetype":"venue"
},
  "geometry": {"coordinates":[-123.14788799999999,49.169239],"type":"Point"}
}