{
  "type": "Feature",
  "properties": {
    "addr:full":"645 Lansdowne St W # 22 Peterborough ON K9J 7Y5",
    "addr:housenumber":"645",
    "addr:postcode":"k9j 7y5",
    "addr:street":"Lansdowne St W # 22",
    "iso:country":"CA",
    "sg:address":"645 Lansdowne St W # 22",
    "sg:city":"Peterborough",
    "sg:classifiers":[
        {
            "category":"Shopping",
            "subcategory":"Jewelry",
            "type":"Retail Goods"
        }
    ],
    "sg:phone":"+1 705 743 1213",
    "sg:postcode":"K9J 7Y5",
    "sg:province":"ON",
    "sg:tags":[
        "jeweler"
    ],
    "wof:name":"Twain Gold & Diamond Ctr",
    "wof:placetype":"venue"
},
  "geometry": {"coordinates":[-78.332855,44.284908],"type":"Point"}
}