{
  "type": "Feature",
  "properties": {
    "addr:full":"11222 87 Ave Fort Saskatchewan AB T8L 2S4",
    "addr:housenumber":"11222",
    "addr:postcode":"t8l 2s4",
    "addr:street":"87 Ave",
    "iso:country":"CA",
    "sg:address":"11222 87 Ave",
    "sg:city":"Fort Saskatchewan",
    "sg:classifiers":[
        {
            "category":"Retail",
            "subcategory":"Auto Repair",
            "type":"Services"
        }
    ],
    "sg:phone":"+1 780 998 0588",
    "sg:postcode":"T8L 2S4",
    "sg:province":"AB",
    "sg:tags":[
        "repairing",
        "automobile"
    ],
    "wof:name":"Thistle Automotive Ltd",
    "wof:placetype":"venue"
},
  "geometry": {"coordinates":[-113.19119999999999,53.707134],"type":"Point"}
}