{
  "type": "Feature",
  "properties": {
    "addr:full":"1604 Summerfield Blvd SE Airdrie AB T4B 1C7",
    "addr:housenumber":"1604",
    "addr:postcode":"t4b 1c7",
    "addr:street":"Summerfield Blvd Se",
    "iso:country":"CA",
    "sg:address":"1604 Summerfield Blvd SE",
    "sg:city":"Airdrie",
    "sg:classifiers":[
        {
            "category":"Organizations",
            "subcategory":"Religious Organization",
            "type":"Services"
        }
    ],
    "sg:phone":"+1 403 948 3818",
    "sg:postcode":"T4B 1C7",
    "sg:province":"AB",
    "sg:tags":[
        "church"
    ],
    "wof:name":"Airdrie Alliance Church",
    "wof:placetype":"venue"
},
  "geometry": {"coordinates":[-114.00580596899999,51.2792892456],"type":"Point"}
}