{
  "type": "Feature",
  "properties": {
    "addr:full":"Froese Rd Grunthal MB R0A 0R0",
    "addr:postcode":"r0a 0r0",
    "addr:street":"Froese Rd",
    "iso:country":"CA",
    "sg:address":"Froese Rd",
    "sg:city":"Grunthal",
    "sg:classifiers":[
        {
            "category":"Shopping",
            "subcategory":"Crafts & Fabrics",
            "type":"Retail Goods"
        }
    ],
    "sg:phone":"+1 204 434 6919",
    "sg:postcode":"R0A 0R0",
    "sg:province":"MB",
    "sg:tags":[
        "shop"
    ],
    "wof:name":"Hiebert Fabric Sales",
    "wof:placetype":"venue"
},
  "geometry": {"coordinates":[-96.85130310060001,49.4066886902],"type":"Point"}
}