{
  "type": "Feature",
  "properties": {
    "addr:full":"10805 102 Ave Grande Prairie AB T8V 7T7",
    "addr:housenumber":"10805",
    "addr:postcode":"t8v 7t7",
    "addr:street":"102 Ave",
    "iso:country":"CA",
    "sg:address":"10805 102 Ave",
    "sg:city":"Grande Prairie",
    "sg:classifiers":[
        {
            "category":"Wholesale",
            "subcategory":"Sporting Goods",
            "type":"Manufacturing & Wholesale Goods"
        }
    ],
    "sg:phone":"+1 780 402 7722",
    "sg:postcode":"T8V 7T7",
    "sg:province":"AB",
    "sg:tags":[
        "equipment",
        "billiard",
        "supply"
    ],
    "wof:name":"Backyardz 'N Billiardz",
    "wof:placetype":"venue"
},
  "geometry": {"coordinates":[-118.82353973399999,55.1714706421],"type":"Point"}
}