{
  "type": "Feature",
  "properties": {
    "addr:full":"Hudson Bay SK S0E 0Y0",
    "addr:postcode":"s0e 0y0",
    "addr:street":"Hudson Bay",
    "iso:country":"CA",
    "sg:city":"Hudson Bay",
    "sg:classifiers":[
        {
            "category":"Personal",
            "subcategory":"Beauty Salon",
            "type":"Services"
        }
    ],
    "sg:phone":"+1 306 865 3740",
    "sg:postcode":"S0E 0Y0",
    "sg:province":"SK",
    "sg:tags":[
        "barber"
    ],
    "wof:name":"Richard's Barbering & Hair Sty",
    "wof:placetype":"venue"
},
  "geometry": {"coordinates":[-102.38938140899999,52.862361908],"type":"Point"}
}