{
  "type": "Feature",
  "properties": {
    "addr:full":"333 Rte 236 Saint-Stanislas-DE-Kostka QC J0S 1W0",
    "addr:housenumber":"333",
    "addr:postcode":"j0s 1w0",
    "addr:street":"Rte 236",
    "iso:country":"CA",
    "sg:address":"333 Rte 236",
    "sg:city":"Saint-Stanislas-DE-Kostka",
    "sg:classifiers":[
        {
            "category":"Retail",
            "subcategory":"Auto Repair",
            "type":"Services"
        }
    ],
    "sg:phone":"+1 450 371 7746",
    "sg:postcode":"J0S 1W0",
    "sg:province":"QC",
    "sg:tags":[
        "repairing",
        "automobile"
    ],
    "wof:name":"Garage Normand Poirier",
    "wof:placetype":"venue"
},
  "geometry": {"coordinates":[-74.12660980219999,45.1806716919],"type":"Point"}
}