{
  "type": "Feature",
  "properties": {
    "addr:full":"451 Mohawk Rd W Hamilton ON L9C 1X3",
    "addr:housenumber":"451",
    "addr:postcode":"l9c 1x3",
    "addr:street":"Mohawk Rd W",
    "iso:country":"CA",
    "sg:address":"451 Mohawk Rd W",
    "sg:city":"Hamilton",
    "sg:classifiers":[
        {
            "category":"Building & Trades",
            "subcategory":"Cleaning & Sanitation",
            "type":"Services"
        }
    ],
    "sg:phone":"+1 905 387 0003",
    "sg:postcode":"L9C 1X3",
    "sg:province":"ON",
    "sg:tags":[
        "maintenance",
        "caulking",
        "contractor"
    ],
    "wof:name":"J & T Caulking & Sealing Corp",
    "wof:placetype":"venue"
},
  "geometry": {"coordinates":[-79.9028625488,43.2313804626],"type":"Point"}
}