{
  "type": "Feature",
  "properties": {
    "addr:full":"1007 6th St Rosthern SK S0K 3R0",
    "addr:housenumber":"1007",
    "addr:postcode":"s0k 3r0",
    "addr:street":"6Th St",
    "iso:country":"CA",
    "sg:address":"1007 6th St",
    "sg:city":"Rosthern",
    "sg:classifiers":[
        {
            "category":"Food & Beverages",
            "subcategory":"Groceries & Convenience Stores",
            "type":"Retail Goods"
        }
    ],
    "sg:phone":"+1 306 232 4300",
    "sg:postcode":"S0K 3R0",
    "sg:province":"SK",
    "sg:tags":[
        "grocer"
    ],
    "wof:name":"Wing's Lucky Dollar Food",
    "wof:placetype":"venue"
},
  "geometry": {"coordinates":[-106.33169599999999,52.657753],"type":"Point"}
}