{
  "type": "Feature",
  "properties": {
    "addr:full":"7 Rue Principale S Sutton QC J0E 2K0",
    "addr:housenumber":"7",
    "addr:postcode":"j0e 2k0",
    "addr:street":"Rue Principale S",
    "iso:country":"CA",
    "sg:address":"7 Rue Principale S",
    "sg:city":"Sutton",
    "sg:classifiers":[
        {
            "category":"Food & Beverages",
            "subcategory":"Groceries & Convenience Stores",
            "type":"Retail Goods"
        }
    ],
    "sg:phone":"+1 450 538 2337",
    "sg:postcode":"J0E 2K0",
    "sg:province":"QC",
    "wof:name":"Epicerie Andre Galipault",
    "wof:placetype":"venue"
},
  "geometry": {"coordinates":[-72.6153259277,45.1062088013],"type":"Point"}
}