{
  "type": "Feature",
  "properties": {
    "addr:full":"15270 Hebbville Rd Bridgewater NS B4V 2W4",
    "addr:postcode":"15270;b4v 2w4",
    "addr:street":"Hebbville Rd",
    "iso:country":"CA",
    "sg:address":"15270 Hebbville Rd",
    "sg:city":"Bridgewater",
    "sg:phone":"+1 902 354 4237",
    "sg:postcode":"B4V 2W4",
    "sg:province":"NS",
    "sg:tags":[
        "oil"
    ],
    "wof:name":"Esso Home Comfort Ctr",
    "wof:placetype":"venue"
},
  "geometry": {"coordinates":[-64.523033,44.380497],"type":"Point"}
}