{
  "type": "Feature",
  "properties": {
    "addr:full":"Mississauga ON L5M 6B5",
    "addr:postcode":"l5m 6b5",
    "iso:country":"CA",
    "sg:city":"Mississauga",
    "sg:classifiers":[
        {
            "category":"Health Services",
            "subcategory":"Doctor",
            "type":"Services"
        }
    ],
    "sg:phone":"+1 905 567 8899",
    "sg:postcode":"L5M 6B5",
    "sg:province":"ON",
    "sg:tags":[
        "dentist"
    ],
    "wof:name":"Streetsville Dental",
    "wof:placetype":"venue"
},
  "geometry": {"coordinates":[-79.596947,43.546093],"type":"Point"}
}