{
  "type": "Feature",
  "properties": {
    "addr:full":"303 Eglinton Ave E Toronto ON M4P 1L3",
    "addr:housenumber":"303",
    "addr:postcode":"m4p 1l3",
    "addr:street":"Eglinton Ave E",
    "iso:country":"CA",
    "sg:address":"303 Eglinton Ave E",
    "sg:city":"Toronto",
    "sg:classifiers":[
        {
            "category":"Government",
            "subcategory":"Office",
            "type":"Public Place"
        }
    ],
    "sg:phone":"+1 416 598 3008",
    "sg:postcode":"M4P 1L3",
    "sg:province":"ON",
    "sg:tags":[
        "federal",
        "affairs"
    ],
    "wof:name":"Jamaican Consulate General",
    "wof:placetype":"venue"
},
  "geometry": {"coordinates":[-79.3877029419,43.7088241577],"type":"Point"}
}