{
  "type": "Feature",
  "properties": {
    "iso:country":"CA",
    "sg:address":"6037 Rue Pascal",
    "sg:city":"Montreal-Nord",
    "sg:classifiers":[
        {
            "category":"Building & Trades",
            "subcategory":"Construction",
            "type":"Services"
        }
    ],
    "sg:phone":"+1 514 984 1267",
    "sg:postcode":"H1G 1T1",
    "sg:province":"QC",
    "sg:tags":[
        "tile",
        "dealer"
    ],
    "wof:name":"Tony Marbre Ceramique Inc",
    "wof:placetype":"venue"
},
  "geometry": {"coordinates":[-73.6235198975,45.6162986755],"type":"Point"}
}