{
  "type": "Feature",
  "properties": {
    "addr:full":"Terrace BC V8G 2N6",
    "addr:postcode":"v8g 2n6",
    "iso:country":"CA",
    "sg:city":"Terrace",
    "sg:classifiers":[
        {
            "category":"Real Estate",
            "subcategory":"Real Estate Operator",
            "type":"Services"
        }
    ],
    "sg:phone":"+1 250 638 1619",
    "sg:postcode":"V8G 2N6",
    "sg:province":"BC",
    "sg:tags":[
        "apartment"
    ],
    "wof:name":"B C Housing Management Comm",
    "wof:placetype":"venue"
},
  "geometry": {"coordinates":[-128.58621199999999,54.520725],"type":"Point"}
}