{
  "type": "Feature",
  "properties": {
    "iso:country":"CA",
    "sg:city":"Selkirk",
    "sg:classifiers":[
        {
            "category":"Shopping",
            "subcategory":"Discount & Variety Stores",
            "type":"Retail Goods"
        }
    ],
    "sg:phone":"+1 905 776 2718",
    "sg:postcode":"N0A 1P0",
    "sg:province":"ON",
    "wof:name":"Lakeside Convenience",
    "wof:placetype":"venue"
},
  "geometry": {"coordinates":[-79.93207550050001,42.834236145],"type":"Point"}
}