{
  "type": "Feature",
  "properties": {
    "addr:full":"8760 149 St NW Edmonton AB T5R 1B6",
    "addr:housenumber":"8760",
    "addr:postcode":"t5r 1b6",
    "addr:street":"149 St Nw",
    "iso:country":"CA",
    "sg:address":"8760 149 St NW",
    "sg:city":"Edmonton",
    "sg:classifiers":[
        {
            "category":"Professional",
            "subcategory":"Computer Services",
            "type":"Services"
        }
    ],
    "sg:phone":"+1 780 486 3254",
    "sg:postcode":"T5R 1B6",
    "sg:province":"AB",
    "wof:name":"Western Computer Shack",
    "wof:placetype":"venue"
},
  "geometry": {"coordinates":[-113.578231812,53.5203170776],"type":"Point"}
}