{
  "type": "Feature",
  "properties": {
    "iso:country":"CA",
    "sg:address":"3540 Boul Gaetan-Boucher",
    "sg:city":"Saint-Hubert",
    "sg:classifiers":[
        {
            "category":"Professional",
            "subcategory":"Accounting & Tax Preparation",
            "type":"Services"
        }
    ],
    "sg:phone":"+1 450 443 4610",
    "sg:postcode":"J3Y 7S3",
    "sg:province":"QC",
    "sg:tags":[
        "accountant"
    ],
    "wof:name":"Loiselle, Yves",
    "wof:placetype":"venue"
},
  "geometry": {"coordinates":[-73.41398620610001,45.4880371094],"type":"Point"}
}