{
  "type": "Feature",
  "properties": {
    "addr:full":"545 John St Victoria BC V8T 5B4",
    "addr:housenumber":"545",
    "addr:postcode":"v8t 5b4",
    "addr:street":"John St",
    "iso:country":"CA",
    "sg:address":"545 John St",
    "sg:city":"Victoria",
    "sg:classifiers":[
        {
            "category":"Manufacturing",
            "subcategory":"Rubber & Plastics",
            "type":"Manufacturing & Wholesale Goods"
        }
    ],
    "sg:phone":"+1 250 382 7539",
    "sg:postcode":"V8T 5B4",
    "sg:province":"BC",
    "wof:name":"Plexi-Klass Mfg",
    "wof:placetype":"venue"
},
  "geometry": {"coordinates":[-123.371429443,48.4363136292],"type":"Point"}
}