{
  "type": "Feature",
  "properties": {
    "addr:full":"Port Coquitlam BC V3B 6P2",
    "addr:postcode":"v3b 6p2",
    "iso:country":"CA",
    "sg:city":"Port Coquitlam",
    "sg:classifiers":[
        {
            "category":"Shopping",
            "subcategory":"Used Merchandise",
            "type":"Retail Goods"
        }
    ],
    "sg:phone":"+1 604 945 2044",
    "sg:postcode":"V3B 6P2",
    "sg:province":"BC",
    "sg:tags":[
        "shop",
        "consignment"
    ],
    "wof:name":"Christie's Cottage For Kids",
    "wof:placetype":"venue"
},
  "geometry": {"coordinates":[-122.789398193,49.2727851868],"type":"Point"}
}