{
  "type": "Feature",
  "properties": {
    "addr:full":"3228 Rainbow Crt Burlington ON L7M 2T8",
    "addr:housenumber":"3228",
    "addr:postcode":"l7m 2t8",
    "addr:street":"Rainbow Crt",
    "iso:country":"CA",
    "sg:address":"3228 Rainbow Crt",
    "sg:city":"Burlington",
    "sg:classifiers":[
        {
            "category":"Retail",
            "subcategory":"Laundry & Dry Cleaning",
            "type":"Services"
        }
    ],
    "sg:phone":"+1 905 335 2031",
    "sg:postcode":"L7M 2T8",
    "sg:province":"ON",
    "sg:tags":[
        "cleaners",
        "rug",
        "carpet"
    ],
    "wof:name":"Carpet Care",
    "wof:placetype":"venue"
},
  "geometry": {"coordinates":[-79.816734314,43.3718414307],"type":"Point"}
}