{
  "type": "Feature",
  "properties": {
    "iso:country":"CA",
    "sg:address":"1375 Hopkins St",
    "sg:city":"Whitby",
    "sg:classifiers":[
        {
            "category":"Recreation",
            "type":"Entertainment"
        }
    ],
    "sg:phone":"+1 905 665 8875",
    "sg:postcode":"L1N 2C2",
    "sg:province":"ON",
    "sg:tags":[
        "range",
        "practice",
        "golf",
        "amusement"
    ],
    "wof:name":"Ttg Academy of Golf",
    "wof:placetype":"venue"
},
  "geometry": {"coordinates":[-78.917015,43.872059],"type":"Point"}
}