{
  "type": "Feature",
  "properties": {
    "iso:country":"CA",
    "sg:address":"440 Boul Armand-Frappier",
    "sg:city":"Laval",
    "sg:classifiers":[
        {
            "category":"Manufacturing",
            "subcategory":"Tools & Machinery",
            "type":"Manufacturing & Wholesale Goods"
        }
    ],
    "sg:phone":"+1 450 682 1003",
    "sg:postcode":"H7V 4B4",
    "sg:province":"QC",
    "sg:tags":[
        "industry",
        "aerospace"
    ],
    "wof:name":"Simgraph Inc",
    "wof:placetype":"venue"
},
  "geometry": {"coordinates":[-73.732101,45.552135],"type":"Point"}
}