{
  "type": "Feature",
  "properties": {
    "addr:full":"409 George St Thunder Bay ON P7E 5Y9",
    "addr:housenumber":"409",
    "addr:postcode":"p7e 5y9",
    "addr:street":"George St",
    "iso:country":"CA",
    "sg:address":"409 George St",
    "sg:city":"Thunder Bay",
    "sg:classifiers":[
        {
            "category":"Organizations",
            "subcategory":"Professional Association",
            "type":"Services"
        }
    ],
    "sg:phone":"+1 807 622 1711",
    "sg:postcode":"P7E 5Y9",
    "sg:province":"ON",
    "wof:name":"Seven Generations Education",
    "wof:placetype":"venue"
},
  "geometry": {"coordinates":[-89.2435684204,48.383441925],"type":"Point"}
}