{
  "type": "Feature",
  "properties": {
    "addr:full":"17525 Jane St Kettleby ON L0G 1J0",
    "addr:housenumber":"17525",
    "addr:postcode":"l0g 1j0",
    "addr:street":"Jane St",
    "iso:country":"CA",
    "sg:address":"17525 Jane St",
    "sg:city":"Kettleby",
    "sg:classifiers":[
        {
            "category":"Building & Trades",
            "subcategory":"Landscaping Services",
            "type":"Services"
        }
    ],
    "sg:phone":"+1 905 729 2415",
    "sg:postcode":"L0G 1J0",
    "sg:province":"ON",
    "sg:tags":[
        "lawn",
        "sodding",
        "sod",
        "maintenance",
        "grounds"
    ],
    "wof:name":"Zander Sod CO Ltd",
    "wof:placetype":"venue"
},
  "geometry": {"coordinates":[-79.5818862915,44.0329055786],"type":"Point"}
}