{
  "type": "Feature",
  "properties": {
    "iso:country":"CA",
    "sg:city":"Richmond",
    "sg:classifiers":[
        {
            "category":"Wholesale",
            "subcategory":"Sporting Goods",
            "type":"Manufacturing & Wholesale Goods"
        }
    ],
    "sg:phone":"+1 604 271 2453",
    "sg:postcode":"V7A 4V5",
    "sg:province":"BC",
    "sg:tags":[
        "bicycle"
    ],
    "wof:name":"Asama Bicycles",
    "wof:placetype":"venue"
},
  "geometry": {"coordinates":[-123.095626831,49.1288757324],"type":"Point"}
}