{
  "type": "Feature",
  "properties": {
    "addr:full":"Toronto ON M5A 3A2",
    "addr:postcode":"m5a 3a2",
    "iso:country":"CA",
    "sg:city":"Toronto",
    "sg:classifiers":[
        {
            "category":"Personal",
            "subcategory":"Beauty Salon",
            "type":"Services"
        }
    ],
    "sg:phone":"+1 416 966 2637",
    "sg:postcode":"M5A 3A2",
    "sg:province":"ON",
    "wof:name":"Capability Brown Hair Studio",
    "wof:placetype":"venue"
},
  "geometry": {"coordinates":[-79.36792,43.663685],"type":"Point"}
}