{
  "type": "Feature",
  "properties": {
    "addr:full":"3426 Queen St Rawdon QC J0K 1S0",
    "addr:housenumber":"3426",
    "addr:postcode":"j0k 1s0",
    "addr:street":"Queen St",
    "iso:country":"CA",
    "sg:address":"3426 Queen St",
    "sg:city":"Rawdon",
    "sg:classifiers":[
        {
            "category":"Manufacturing",
            "subcategory":"Metals",
            "type":"Manufacturing & Wholesale Goods"
        }
    ],
    "sg:phone":"+1 450 834 2666",
    "sg:postcode":"J0K 1S0",
    "sg:province":"QC",
    "sg:tags":[
        "steel"
    ],
    "wof:name":"Rawdon Metal Inc",
    "wof:placetype":"venue"
},
  "geometry": {"coordinates":[-73.69935599999999,46.037235],"type":"Point"}
}