{
  "type": "Feature",
  "properties": {
    "addr:full":"33 Upton Rd Scarborough ON M1L 2C1",
    "addr:housenumber":"33",
    "addr:postcode":"m1l 2c1",
    "addr:street":"Upton Rd",
    "iso:country":"CA",
    "sg:address":"33 Upton Rd",
    "sg:city":"Scarborough",
    "sg:classifiers":[
        {
            "category":"Wholesale",
            "subcategory":"Seafood",
            "type":"Manufacturing & Wholesale Goods"
        }
    ],
    "sg:phone":"+1 416 757 2800",
    "sg:postcode":"M1L 2C1",
    "sg:province":"ON",
    "wof:name":"Starlight Seafood Inc",
    "wof:placetype":"venue"
},
  "geometry": {"coordinates":[-79.28164672849999,43.7185287476],"type":"Point"}
}