{
  "type": "Feature",
  "properties": {
    "iso:country":"CA",
    "sg:city":"Oakville",
    "sg:classifiers":[
        {
            "category":"Real Estate",
            "subcategory":"Developer",
            "type":"Services"
        }
    ],
    "sg:phone":"+1 905 829 1500",
    "sg:postcode":"L6J 7L7",
    "sg:province":"ON",
    "sg:tags":[
        "company",
        "land"
    ],
    "wof:name":"United Lands Corp Inc",
    "wof:placetype":"venue"
},
  "geometry": {"coordinates":[-79.665123,43.507359],"type":"Point"}
}