{
  "type": "Feature",
  "properties": {
    "addr:full":"Westbank BC V4T 2N6",
    "addr:postcode":"v4t 2n6",
    "iso:country":"CA",
    "sg:city":"Westbank",
    "sg:classifiers":[
        {
            "category":"Banks & Credit Unions",
            "subcategory":"Investment Brokerage",
            "type":"Services"
        }
    ],
    "sg:phone":"+1 250 768 8218",
    "sg:postcode":"V4T 2N6",
    "sg:province":"BC",
    "wof:name":"Edward Jones Investments",
    "wof:placetype":"venue"
},
  "geometry": {"coordinates":[-119.621178,49.829948],"type":"Point"}
}