{
  "type": "Feature",
  "properties": {
    "addr:full":"15842 Cliff Ave White Rock BC V4B 5B1",
    "addr:housenumber":"15842",
    "addr:postcode":"v4b 5b1",
    "addr:street":"Cliff Ave",
    "iso:country":"CA",
    "sg:address":"15842 Cliff Ave",
    "sg:city":"White Rock",
    "sg:classifiers":[
        {
            "category":"Professional",
            "subcategory":"Business Services",
            "type":"Services"
        }
    ],
    "sg:phone":"+1 604 541 8409",
    "sg:postcode":"V4B 5B1",
    "sg:province":"BC",
    "sg:tags":[
        "interior",
        "consultant",
        "design",
        "decorator"
    ],
    "wof:name":"Etruscan Design Assoc",
    "wof:placetype":"venue"
},
  "geometry": {"coordinates":[-122.783089,49.021847],"type":"Point"}
}