{
  "type": "Feature",
  "properties": {
    "addr:full":"158 Boul Edgar-Hebert Melocheville QC J0S 1J0",
    "addr:housenumber":"158",
    "addr:postcode":"j0s 1j0",
    "addr:street":"Boul Edgar-Hebert",
    "iso:country":"CA",
    "sg:address":"158 Boul Edgar-Hebert",
    "sg:city":"Melocheville",
    "sg:classifiers":[
        {
            "category":"Building & Trades",
            "subcategory":"Construction",
            "type":"Services"
        }
    ],
    "sg:phone":"+1 450 225 4403",
    "sg:postcode":"J0S 1J0",
    "sg:province":"QC",
    "sg:tags":[
        "equipment",
        "kitchen",
        "maker",
        "cabinet"
    ],
    "wof:name":"Ebenisterie Paquet Inc",
    "wof:placetype":"venue"
},
  "geometry": {"coordinates":[-73.9343414307,45.316444397],"type":"Point"}
}