{
  "type": "Feature",
  "properties": {
    "addr:full":"501 Ottawa St N Hamilton ON L8H 4A9",
    "addr:housenumber":"501",
    "addr:postcode":"l8h 4a9",
    "addr:street":"Ottawa St N",
    "iso:country":"CA",
    "sg:address":"501 Ottawa St N",
    "sg:city":"Hamilton",
    "sg:classifiers":[
        {
            "category":"Autos & Motor Vehicles",
            "subcategory":"Fuel & Gas Station",
            "type":"Retail Goods"
        }
    ],
    "sg:phone":"+1 905 548 0606",
    "sg:postcode":"L8H 4A9",
    "sg:province":"ON",
    "sg:tags":[
        "muffler",
        "exhaust",
        "oil",
        "system"
    ],
    "wof:name":"Running Pump",
    "wof:placetype":"venue"
},
  "geometry": {"coordinates":[-79.815147,43.254311],"type":"Point"}
}