{
  "type": "Feature",
  "properties": {
    "iso:country":"CA",
    "sg:address":"184 Christina St N",
    "sg:city":"Sarnia",
    "sg:classifiers":[
        {
            "category":"Shopping",
            "subcategory":"Clothing, Apparel, & Fashions",
            "type":"Retail Goods"
        }
    ],
    "sg:phone":"+1 519 332 8700",
    "sg:postcode":"N7T 5T9",
    "sg:province":"ON",
    "sg:tags":[
        "shop",
        "bridal"
    ],
    "wof:name":"Aliya Fashions Ltd",
    "wof:placetype":"venue"
},
  "geometry": {"coordinates":[-82.4069442749,42.9729118347],"type":"Point"}
}