{
  "type": "Feature",
  "properties": {
    "addr:full":"389 Dissette St Bradford ON L3Z 3G9",
    "addr:housenumber":"389",
    "addr:postcode":"l3z 3g9",
    "addr:street":"Dissette St",
    "iso:country":"CA",
    "sg:address":"389 Dissette St",
    "sg:city":"Bradford",
    "sg:classifiers":[
        {
            "category":"Health Services",
            "subcategory":"Health Practitioner",
            "type":"Services"
        }
    ],
    "sg:phone":"+1 905 775 3117",
    "sg:postcode":"L3Z 3G9",
    "sg:province":"ON",
    "sg:tags":[
        "homeopath"
    ],
    "wof:name":"Bradford Homeopathy & Natural",
    "wof:placetype":"venue"
},
  "geometry": {"coordinates":[-79.5563049316,44.1264762878],"type":"Point"}
}