{
  "type": "Feature",
  "properties": {
    "iso:country":"CA",
    "sg:address":"91 Friuli Crt",
    "sg:city":"Woodbridge",
    "sg:classifiers":[
        {
            "category":"Autos & Motor Vehicles",
            "subcategory":"Automobile Sales",
            "type":"Retail Goods"
        }
    ],
    "sg:phone":"+1 905 856 9722",
    "sg:postcode":"L4L 7H2",
    "sg:province":"ON",
    "sg:tags":[
        "car",
        "dealer"
    ],
    "wof:name":"Badmos Auto Sales",
    "wof:placetype":"venue"
},
  "geometry": {"coordinates":[-79.57312011720001,43.7656784058],"type":"Point"}
}