{
  "type": "Feature",
  "properties": {
    "iso:country":"CA",
    "sg:address":"2310 Av Bourgogne",
    "sg:city":"Chambly",
    "sg:classifiers":[
        {
            "category":"Building & Trades",
            "subcategory":"Construction",
            "type":"Services"
        }
    ],
    "sg:phone":"+1 450 658 1949",
    "sg:postcode":"J3L 2A2",
    "sg:province":"QC",
    "sg:tags":[
        "designer",
        "dealer",
        "pool",
        "swimming"
    ],
    "wof:name":"Piscine Chambly Enr",
    "wof:placetype":"venue"
},
  "geometry": {"coordinates":[-73.26708221440001,45.4451675415],"type":"Point"}
}