{
  "type": "Feature",
  "properties": {
    "iso:country":"CA",
    "sg:address":"35454 Huron Rd",
    "sg:city":"Goderich",
    "sg:classifiers":[
        {
            "category":"Real Estate",
            "subcategory":"Developer",
            "type":"Services"
        }
    ],
    "sg:phone":"+1 519 524 8471",
    "sg:postcode":"N7A 3X8",
    "sg:province":"ON",
    "sg:tags":[
        "cemetery"
    ],
    "wof:name":"Maitland Cemetery",
    "wof:placetype":"venue"
},
  "geometry": {"coordinates":[-81.6897201538,43.7303504944],"type":"Point"}
}