{
  "type": "Feature",
  "properties": {
    "addr:full":"1849 30 St SW Medicine Hat AB T1B 3N6",
    "addr:housenumber":"1849",
    "addr:postcode":"t1b 3n6",
    "addr:street":"30 St Sw",
    "iso:country":"CA",
    "sg:address":"1849 30 St SW",
    "sg:city":"Medicine Hat",
    "sg:classifiers":[
        {
            "category":"Freight",
            "type":"Transportation"
        }
    ],
    "sg:phone":"+1 403 526 5961",
    "sg:postcode":"T1B 3N6",
    "sg:province":"AB",
    "sg:tags":[
        "trucking"
    ],
    "wof:name":"Exalta Transport Corp",
    "wof:placetype":"venue"
},
  "geometry": {"coordinates":[-110.728439331,50.0114936829],"type":"Point"}
}