{
  "type": "Feature",
  "properties": {
    "iso:country":"CA",
    "sg:city":"Nepean",
    "sg:classifiers":[
        {
            "category":"Health Services",
            "subcategory":"Health Practitioner",
            "type":"Services"
        }
    ],
    "sg:phone":"+1 613 723 8778",
    "sg:postcode":"K2G 6E2",
    "sg:province":"ON",
    "sg:tags":[
        "psychologist"
    ],
    "wof:name":"Dion, Pierre",
    "wof:placetype":"venue"
},
  "geometry": {"coordinates":[-75.7688903809,45.3483963013],"type":"Point"}
}