{
  "type": "Feature",
  "properties": {
    "addr:full":"16829 Boul Hymus Kirkland QC H9H 3L4",
    "addr:housenumber":"16829",
    "addr:postcode":"h9h 3l4",
    "addr:street":"Boul Hymus",
    "iso:country":"CA",
    "sg:address":"16829 Boul Hymus",
    "sg:city":"Kirkland",
    "sg:classifiers":[
        {
            "category":"Shopping",
            "subcategory":"Computers & Home Electronics",
            "type":"Retail Goods"
        }
    ],
    "sg:phone":"+1 514 694 1333",
    "sg:postcode":"H9H 3L4",
    "sg:province":"QC",
    "wof:name":"D P Consultants Inc",
    "wof:placetype":"venue"
},
  "geometry": {"coordinates":[-73.8510055542,45.4500999451],"type":"Point"}
}