{
  "type": "Feature",
  "properties": {
    "addr:full":"10812 129 Ave NW Edmonton AB T5E 0L6",
    "addr:housenumber":"10812",
    "addr:postcode":"t5e 0l6",
    "addr:street":"129 Ave Nw",
    "iso:country":"CA",
    "sg:address":"10812 129 Ave NW",
    "sg:city":"Edmonton",
    "sg:classifiers":[
        {
            "category":"Personal",
            "subcategory":"Beauty Salon",
            "type":"Services"
        }
    ],
    "sg:phone":"+1 780 475 7112",
    "sg:postcode":"T5E 0L6",
    "sg:province":"AB",
    "wof:name":"Hair Handlers",
    "wof:placetype":"venue"
},
  "geometry": {"coordinates":[-113.50696600000001,53.587666],"type":"Point"}
}