{
  "type": "Feature",
  "properties": {
    "addr:full":"565 Otto Rd Mississauga ON L5T 2Y7",
    "addr:housenumber":"565",
    "addr:postcode":"l5t 2y7",
    "addr:street":"Otto Rd",
    "iso:country":"CA",
    "sg:address":"565 Otto Rd",
    "sg:city":"Mississauga",
    "sg:classifiers":[
        {
            "category":"Wholesale",
            "subcategory":"Furniture",
            "type":"Manufacturing & Wholesale Goods"
        }
    ],
    "sg:phone":"+1 905 362 5555",
    "sg:postcode":"L5T 2Y7",
    "sg:province":"ON",
    "wof:name":"Brassex Inc",
    "wof:placetype":"venue"
},
  "geometry": {"coordinates":[-79.677132,43.644032],"type":"Point"}
}