{
  "type": "Feature",
  "properties": {
    "iso:country":"CA",
    "sg:city":"Glen Robertson",
    "sg:classifiers":[
        {
            "category":"Home & Garden",
            "subcategory":"Building Materials",
            "type":"Retail Goods"
        }
    ],
    "sg:phone":"+1 613 874 2290",
    "sg:postcode":"K0B 1H0",
    "sg:province":"ON",
    "sg:tags":[
        "lumber"
    ],
    "wof:name":"White Pine Lumber Reg'd",
    "wof:placetype":"venue"
},
  "geometry": {"coordinates":[-74.5487976074,45.373134613],"type":"Point"}
}