{
  "type": "Feature",
  "properties": {
    "iso:country":"CA",
    "sg:address":"22 Erie St",
    "sg:city":"Stratford",
    "sg:classifiers":[
        {
            "category":"Retail",
            "subcategory":"Animal Services",
            "type":"Services"
        }
    ],
    "sg:phone":"+1 519 272 0108",
    "sg:postcode":"N5A 2M4",
    "sg:province":"ON",
    "sg:tags":[
        "pet",
        "grooming",
        "washing"
    ],
    "wof:name":"Margo's Pet Grooming",
    "wof:placetype":"venue"
},
  "geometry": {"coordinates":[-80.9833679199,43.3709945679],"type":"Point"}
}