{
  "type": "Feature",
  "properties": {
    "addr:full":"46 Dunlop St W Barrie ON L4N 1A4",
    "addr:housenumber":"46",
    "addr:postcode":"l4n 1a4",
    "addr:street":"Dunlop St W",
    "iso:country":"CA",
    "sg:address":"46 Dunlop St W",
    "sg:city":"Barrie",
    "sg:classifiers":[
        {
            "category":"Bars & Pubs",
            "type":"Food & Drink"
        }
    ],
    "sg:phone":"+1 705 734 1044",
    "sg:postcode":"L4N 1A4",
    "sg:province":"ON",
    "wof:name":"Roxx Entertainment Hotline",
    "wof:placetype":"venue"
},
  "geometry": {"coordinates":[-79.6916885376,44.3887405396],"type":"Point"}
}