{
  "type": "Feature",
  "properties": {
    "addr:full":"764 Rue Jette Acton Vale QC J0H 1A0",
    "addr:housenumber":"764",
    "addr:postcode":"j0h 1a0",
    "addr:street":"Rue Jette",
    "iso:country":"CA",
    "sg:address":"764 Rue Jette",
    "sg:city":"Acton Vale",
    "sg:classifiers":[
        {
            "category":"Building & Trades",
            "subcategory":"Construction",
            "type":"Services"
        }
    ],
    "sg:phone":"+1 450 546 3660",
    "sg:postcode":"J0H 1A0",
    "sg:province":"QC",
    "sg:tags":[
        "general",
        "contractor"
    ],
    "wof:name":"Constructions Daniel Laliberte",
    "wof:placetype":"venue"
},
  "geometry": {"coordinates":[-72.56266021730001,45.6630249023],"type":"Point"}
}