{
  "type": "Feature",
  "properties": {
    "addr:full":"930 Woodlawn Rd W # 1 Guelph ON N1K 1T2",
    "addr:housenumber":"930",
    "addr:postcode":"n1k 1t2",
    "addr:street":"Woodlawn Rd W # 1",
    "iso:country":"CA",
    "sg:address":"930 Woodlawn Rd W # 1",
    "sg:city":"Guelph",
    "sg:classifiers":[
        {
            "category":"Restaurant",
            "type":"Food & Drink"
        }
    ],
    "sg:phone":"+1 519 822 0070",
    "sg:postcode":"N1K 1T2",
    "sg:province":"ON",
    "wof:name":"Delainey's Casual Dining Inc",
    "wof:placetype":"venue"
},
  "geometry": {"coordinates":[-80.319016,43.534721],"type":"Point"}
}