{
  "type": "Feature",
  "properties": {
    "addr:full":"195 Main St Wolfville NS B4P 1C3",
    "addr:housenumber":"195",
    "addr:postcode":"b4p 1c3",
    "addr:street":"Main St",
    "iso:country":"CA",
    "sg:address":"195 Main St",
    "sg:city":"Wolfville",
    "sg:classifiers":[
        {
            "category":"Travel",
            "subcategory":"Hotels & Motels",
            "type":"Entertainment"
        }
    ],
    "sg:phone":"+1 902 542 2291",
    "sg:postcode":"B4P 1C3",
    "sg:province":"NS",
    "sg:tags":[
        "breakfast",
        "accommodation",
        "bed"
    ],
    "wof:name":"Blomidon Inn",
    "wof:placetype":"venue"
},
  "geometry": {"coordinates":[-64.3728256226,45.0900688171],"type":"Point"}
}