{
  "type": "Feature",
  "properties": {
    "iso:country":"CA",
    "sg:address":"449 Anderson St S",
    "sg:city":"Fergus",
    "sg:classifiers":[
        {
            "category":"Wholesale",
            "subcategory":"Poultry",
            "type":"Manufacturing & Wholesale Goods"
        }
    ],
    "sg:phone":"+1 519 843 2571",
    "sg:postcode":"N1M 2W7",
    "sg:province":"ON",
    "wof:name":"James Wilson & Sons Ltd",
    "wof:placetype":"venue"
},
  "geometry": {"coordinates":[-80.3571929932,43.7174530029],"type":"Point"}
}