{
  "type": "Feature",
  "properties": {
    "addr:full":"3591 Prospect Rd Shad Bay NS B3T 1Z3",
    "addr:housenumber":"3591",
    "addr:postcode":"b3t 1z3",
    "addr:street":"Prospect Rd",
    "iso:country":"CA",
    "sg:address":"3591 Prospect Rd",
    "sg:city":"Shad Bay",
    "sg:classifiers":[
        {
            "category":"Education",
            "subcategory":"School",
            "type":"Public Place"
        }
    ],
    "sg:phone":"+1 902 852 2166",
    "sg:postcode":"B3T 1Z3",
    "sg:province":"NS",
    "wof:name":"Atlantic Memorial School",
    "wof:placetype":"venue"
},
  "geometry": {"coordinates":[-63.7755393982,44.5231323242],"type":"Point"}
}