{
  "type": "Feature",
  "properties": {
    "addr:full":"5675 Boul Des Grandes-Prairies #121 Saint-Leonard QC H1R 1B3",
    "addr:housenumber":"5675",
    "addr:postcode":"h1r 1b3",
    "addr:street":"Boul Des Grandes-Prairies # 121",
    "iso:country":"CA",
    "sg:address":"5675 Boul Des Grandes-Prairies #121",
    "sg:city":"Saint-Leonard",
    "sg:classifiers":[
        {
            "category":"Home & Garden",
            "subcategory":"Furniture",
            "type":"Retail Goods"
        }
    ],
    "sg:phone":"+1 514 327 6667",
    "sg:postcode":"H1R 1B3",
    "sg:province":"QC",
    "sg:tags":[
        "kitchen",
        "cabinet"
    ],
    "wof:name":"Verstile Inc",
    "wof:placetype":"venue"
},
  "geometry": {"coordinates":[-73.61325836180001,45.5974273682],"type":"Point"}
}