{
  "type": "Feature",
  "properties": {
    "addr:full":"10 Factory Lane St. John's NL A1C 6H5",
    "addr:housenumber":"10",
    "addr:postcode":"a1c 6h5",
    "addr:street":"Factory Lane",
    "iso:country":"CA",
    "sg:address":"10 Factory Lane",
    "sg:city":"St. John's",
    "sg:classifiers":[
        {
            "category":"Professional",
            "subcategory":"Accounting & Tax Preparation",
            "type":"Services"
        }
    ],
    "sg:phone":"+1 709 576 8480",
    "sg:postcode":"A1C 6H5",
    "sg:province":"NL",
    "sg:tags":[
        "accountant"
    ],
    "wof:name":"Deloitte & Touche",
    "wof:placetype":"venue"
},
  "geometry": {"coordinates":[-52.6991043091,47.5723457336],"type":"Point"}
}