{
  "type": "Feature",
  "properties": {
    "addr:full":"PO Box 154 Conception Harbour NL A0A 1Z0",
    "addr:housenumber":"po",
    "addr:postcode":"a0a 1z0",
    "addr:street":"Box 154",
    "iso:country":"CA",
    "sg:address":"PO Box 154",
    "sg:city":"Conception Harbour",
    "sg:classifiers":[
        {
            "category":"Organizations",
            "subcategory":"Religious Organization",
            "type":"Services"
        }
    ],
    "sg:phone":"+1 709 229 4011",
    "sg:postcode":"A0A 1Z0",
    "sg:province":"NL",
    "sg:tags":[
        "church"
    ],
    "wof:name":"St Anne Catholic Church",
    "wof:placetype":"venue"
},
  "geometry": {"coordinates":[-53.211624,47.440193],"type":"Point"}
}