{
  "type": "Feature",
  "properties": {
    "addr:full":"167 Thames St S Ingersoll ON N5C 2T6",
    "addr:housenumber":"167",
    "addr:postcode":"n5c 2t6",
    "addr:street":"Thames St S",
    "iso:country":"CA",
    "sg:address":"167 Thames St S",
    "sg:city":"Ingersoll",
    "sg:classifiers":[
        {
            "category":"Insurance",
            "subcategory":"Insurance Agent",
            "type":"Services"
        }
    ],
    "sg:phone":"+1 519 485 3190",
    "sg:postcode":"N5C 2T6",
    "sg:province":"ON",
    "wof:name":"White, Andrew",
    "wof:placetype":"venue"
},
  "geometry": {"coordinates":[-80.881798,43.037617],"type":"Point"}
}