{
  "type": "Feature",
  "properties": {
    "addr:full":"11 Holland Ave # 100 Ottawa ON K1Y 4S1",
    "addr:housenumber":"11",
    "addr:postcode":"k1y 4s1",
    "addr:street":"Holland Ave # 100",
    "iso:country":"CA",
    "sg:address":"11 Holland Ave # 100",
    "sg:city":"Ottawa",
    "sg:classifiers":[
        {
            "category":"Education",
            "subcategory":"Vocational School",
            "type":"Public Place"
        }
    ],
    "sg:phone":"+1 613 798 5353",
    "sg:postcode":"K1Y 4S1",
    "sg:province":"ON",
    "sg:tags":[
        "training",
        "computer"
    ],
    "wof:name":"Cte Solutions",
    "wof:placetype":"venue"
},
  "geometry": {"coordinates":[-75.73394012449999,45.4032516479],"type":"Point"}
}