{
  "type": "Feature",
  "properties": {
    "addr:full":"Granby QC J2G 2T5",
    "addr:postcode":"j2g 2t5",
    "iso:country":"CA",
    "sg:city":"Granby",
    "sg:classifiers":[
        {
            "category":"Shopping",
            "type":"Retail Goods"
        }
    ],
    "sg:phone":"+1 450 375 2313",
    "sg:postcode":"J2G 2T5",
    "sg:province":"QC",
    "sg:tags":[
        "miscellaneous",
        "store"
    ],
    "wof:name":"Boutique Sexatisfait Enr",
    "wof:placetype":"venue"
},
  "geometry": {"coordinates":[-72.72069500000001,45.397732],"type":"Point"}
}