{
  "type": "Feature",
  "properties": {
    "iso:country":"CA",
    "sg:address":"369 Main St Hwy 1",
    "sg:city":"Middleton",
    "sg:classifiers":[
        {
            "category":"Retail",
            "subcategory":"Auto Repair",
            "type":"Services"
        }
    ],
    "sg:phone":"+1 902 825 4322",
    "sg:postcode":"B0S 1P0",
    "sg:province":"NS",
    "sg:tags":[
        "repairing",
        "automobile"
    ],
    "wof:name":"Westcott Svc Ctr Ltd",
    "wof:placetype":"venue"
},
  "geometry": {"coordinates":[-65.06690979,44.9434928894],"type":"Point"}
}