{
  "type": "Feature",
  "properties": {
    "addr:full":"47 Jenkins Ave Summerside PE C1N 1E3",
    "addr:housenumber":"47",
    "addr:postcode":"c1n 1e3",
    "addr:street":"Jenkins Ave",
    "iso:country":"CA",
    "sg:address":"47 Jenkins Ave",
    "sg:city":"Summerside",
    "sg:classifiers":[
        {
            "category":"Wholesale",
            "subcategory":"Electrical",
            "type":"Manufacturing & Wholesale Goods"
        }
    ],
    "sg:phone":"+1 902 436 6182",
    "sg:postcode":"C1N 1E3",
    "sg:province":"PE",
    "sg:tags":[
        "equipment",
        "electric",
        "supply"
    ],
    "wof:name":"Rogers Electrical Wholesale",
    "wof:placetype":"venue"
},
  "geometry": {"coordinates":[-63.778553,46.392208],"type":"Point"}
}