{
  "type": "Feature",
  "properties": {
    "iso:country":"CA",
    "sg:address":"53 Downie St",
    "sg:city":"Stratford",
    "sg:classifiers":[
        {
            "category":"Shopping",
            "type":"Retail Goods"
        }
    ],
    "sg:phone":"+1 519 271 9518",
    "sg:postcode":"N5A 1W7",
    "sg:province":"ON",
    "sg:tags":[
        "art",
        "gallery",
        "dealer"
    ],
    "wof:name":"Classic Art",
    "wof:placetype":"venue"
},
  "geometry": {"coordinates":[-80.98178863530001,43.3702468872],"type":"Point"}
}