{
  "type": "Feature",
  "properties": {
    "addr:full":"Corner Brook NL A2H 6J7",
    "addr:postcode":"a2h 6j7",
    "iso:country":"CA",
    "sg:city":"Corner Brook",
    "sg:classifiers":[
        {
            "category":"Health Services",
            "subcategory":"Hospital",
            "type":"Services"
        }
    ],
    "sg:phone":"+1 709 639 2728",
    "sg:postcode":"A2H 6J7",
    "sg:province":"NL",
    "wof:name":"Clinical Skills Assessment",
    "wof:placetype":"venue"
},
  "geometry": {"coordinates":[-57.9290924072,48.9473953247],"type":"Point"}
}