{
  "type": "Feature",
  "properties": {
    "addr:full":"Mississauga ON L4W 2Z4",
    "addr:postcode":"l4w 2z4",
    "iso:country":"CA",
    "sg:city":"Mississauga",
    "sg:classifiers":[
        {
            "category":"Retail",
            "subcategory":"Laundry & Dry Cleaning",
            "type":"Services"
        }
    ],
    "sg:phone":"+1 905 624 3630",
    "sg:postcode":"L4W 2Z4",
    "sg:province":"ON",
    "sg:tags":[
        "cleaners",
        "rug",
        "carpet"
    ],
    "wof:name":"Carpet Land Cleaning",
    "wof:placetype":"venue"
},
  "geometry": {"coordinates":[-79.6459350586,43.6364631653],"type":"Point"}
}