{
  "type": "Feature",
  "properties": {
    "addr:full":"1 Ch Ile St-Quentin Trois-Rivieres QC G9A 5E3",
    "addr:housenumber":"1",
    "addr:postcode":"g9a 5e3",
    "addr:street":"Ch Ile St-Quentin Trois-Rivieres",
    "iso:country":"CA",
    "sg:address":"1 Ch Ile St-Quentin",
    "sg:city":"Trois-Rivieres",
    "sg:classifiers":[
        {
            "category":"Recreation",
            "subcategory":"Marina",
            "type":"Entertainment"
        }
    ],
    "sg:phone":"+1 819 374 5862",
    "sg:postcode":"G9A 5E3",
    "sg:province":"QC",
    "wof:name":"Marina DE Trois-Rivieres Inc",
    "wof:placetype":"venue"
},
  "geometry": {"coordinates":[-72.545036,46.340179],"type":"Point"}
}