{
  "type": "Feature",
  "properties": {
    "iso:country":"CA",
    "sg:address":"230 Broadway",
    "sg:city":"Orangeville",
    "sg:classifiers":[
        {
            "category":"Health Services",
            "subcategory":"Optometrist",
            "type":"Services"
        }
    ],
    "sg:phone":"+1 519 941 3770",
    "sg:postcode":"L9W 1K5",
    "sg:province":"ON",
    "wof:name":"Brodie, Patrick J OD",
    "wof:placetype":"venue"
},
  "geometry": {"coordinates":[-80.099113,43.918739],"type":"Point"}
}