{
  "type": "Feature",
  "properties": {
    "addr:full":"Edmonton AB T5K 0L5",
    "addr:postcode":"t5k 0l5",
    "iso:country":"CA",
    "sg:city":"Edmonton",
    "sg:classifiers":[
        {
            "category":"Organizations",
            "subcategory":"Non-profit Organization",
            "type":"Services"
        }
    ],
    "sg:phone":"+1 780 482 5111",
    "sg:postcode":"T5K 0L5",
    "sg:province":"AB",
    "sg:tags":[
        "pregnancy",
        "counseling",
        "information",
        "institution",
        "charitable"
    ],
    "wof:name":"Edmonton Pregnancy Crisis Ctr",
    "wof:placetype":"venue"
},
  "geometry": {"coordinates":[-113.514526,53.540798],"type":"Point"}
}