{
  "type": "Feature",
  "properties": {
    "addr:full":"1155 Richland Rd NE Calgary AB T2E 5M3",
    "addr:housenumber":"1155",
    "addr:postcode":"t2e 5m3",
    "addr:street":"Richland Rd Ne",
    "iso:country":"CA",
    "sg:address":"1155 Richland Rd NE",
    "sg:city":"Calgary",
    "sg:classifiers":[
        {
            "category":"Retail",
            "subcategory":"Laundry & Dry Cleaning",
            "type":"Services"
        }
    ],
    "sg:phone":"+1 403 277 7867",
    "sg:postcode":"T2E 5M3",
    "sg:province":"AB",
    "sg:tags":[
        "cleaners",
        "rug",
        "carpet"
    ],
    "wof:name":"Kenneth's Carpet Svc",
    "wof:placetype":"venue"
},
  "geometry": {"coordinates":[-114.063194,51.045074],"type":"Point"}
}