{
  "type": "Feature",
  "properties": {
    "addr:full":"Scarborough ON M1V 3Z4",
    "addr:postcode":"m1v 3z4",
    "iso:country":"CA",
    "sg:city":"Scarborough",
    "sg:classifiers":[
        {
            "category":"Restaurant",
            "type":"Food & Drink"
        }
    ],
    "sg:phone":"+1 416 269 0000",
    "sg:postcode":"M1V 3Z4",
    "sg:province":"ON",
    "wof:name":"Dick 'N Jane Chicken 'N Shrimp",
    "wof:placetype":"venue"
},
  "geometry": {"coordinates":[-79.276993,43.826633],"type":"Point"}
}