{
  "type": "Feature",
  "properties": {
    "addr:full":"North York ON M3C 1W3",
    "addr:postcode":"m3c 1w3",
    "iso:country":"CA",
    "sg:city":"North York",
    "sg:classifiers":[
        {
            "category":"Real Estate",
            "subcategory":"Architect",
            "type":"Services"
        }
    ],
    "sg:phone":"+1 416 444 5422",
    "sg:postcode":"M3C 1W3",
    "sg:province":"ON",
    "sg:tags":[
        "course",
        "golf"
    ],
    "wof:name":"Golf Course Development Assoc",
    "wof:placetype":"venue"
},
  "geometry": {"coordinates":[-79.3399963379,43.7255134583],"type":"Point"}
}