{
  "type": "Feature",
  "properties": {
    "addr:full":"1435 Rue King O Sherbrooke QC J1J 2C1",
    "addr:housenumber":"1435",
    "addr:postcode":"j1j 2c1",
    "addr:street":"Rue King O",
    "iso:country":"CA",
    "sg:address":"1435 Rue King O",
    "sg:city":"Sherbrooke",
    "sg:classifiers":[
        {
            "category":"Shopping",
            "type":"Retail Goods"
        }
    ],
    "sg:phone":"+1 819 566 5661",
    "sg:postcode":"J1J 2C1",
    "sg:province":"QC",
    "sg:tags":[
        "facility",
        "supply",
        "deaf",
        "hearing",
        "equipment",
        "impaired"
    ],
    "wof:name":"Cliniques Auditives Daniel Roy",
    "wof:placetype":"venue"
},
  "geometry": {"coordinates":[-71.9120635986,45.398815155],"type":"Point"}
}