{
  "type": "Feature",
  "properties": {
    "addr:full":"167 Queen St E Toronto ON M5A 1S2",
    "addr:housenumber":"167",
    "addr:postcode":"m5a 1s2",
    "addr:street":"Queen St E",
    "iso:country":"CA",
    "sg:address":"167 Queen St E",
    "sg:city":"Toronto",
    "sg:classifiers":[
        {
            "category":"Home & Garden",
            "subcategory":"Carpets & Floor Coverings",
            "type":"Retail Goods"
        }
    ],
    "sg:phone":"+1 416 943 0538",
    "sg:postcode":"M5A 1S2",
    "sg:province":"ON",
    "sg:tags":[
        "dealer",
        "rug"
    ],
    "wof:name":"Woven Treasures Persian Rug",
    "wof:placetype":"venue"
},
  "geometry": {"coordinates":[-79.371674,43.6539],"type":"Point"}
}