{
  "type": "Feature",
  "properties": {
    "iso:country":"CA",
    "sg:city":"Port Coquitlam",
    "sg:classifiers":[
        {
            "category":"Manufacturing",
            "subcategory":"Electronics",
            "type":"Manufacturing & Wholesale Goods"
        }
    ],
    "sg:phone":"+1 604 944 8248",
    "sg:postcode":"V3C 4Z1",
    "sg:province":"BC",
    "sg:tags":[
        "instrument",
        "electronic"
    ],
    "wof:name":"Imagenex Technology Corp",
    "wof:placetype":"venue"
},
  "geometry": {"coordinates":[-122.76239776600001,49.2507591248],"type":"Point"}
}