{
  "type": "Feature",
  "properties": {
    "addr:full":"2360 Southcott Rd Pickering ON L1X 2S9",
    "addr:housenumber":"2360",
    "addr:postcode":"l1x 2s9",
    "addr:street":"Southcott Rd",
    "iso:country":"CA",
    "sg:address":"2360 Southcott Rd",
    "sg:city":"Pickering",
    "sg:classifiers":[
        {
            "category":"Social Services",
            "subcategory":"Child Care",
            "type":"Services"
        }
    ],
    "sg:phone":"+1 905 619 2407",
    "sg:postcode":"L1X 2S9",
    "sg:province":"ON",
    "wof:name":"St Wilfrid Junior Y",
    "wof:placetype":"venue"
},
  "geometry": {"coordinates":[-79.080421,43.865452],"type":"Point"}
}