{
  "type": "Feature",
  "properties": {
    "addr:full":"6909 14 St SW Calgary AB T2V 1P8",
    "addr:housenumber":"6909",
    "addr:postcode":"t2v 1p8",
    "addr:street":"14 St Sw",
    "iso:country":"CA",
    "sg:address":"6909 14 St SW",
    "sg:city":"Calgary",
    "sg:classifiers":[
        {
            "category":"Health Services",
            "subcategory":"Nursing And Care Facility",
            "type":"Services"
        }
    ],
    "sg:phone":"+1 403 258 7650",
    "sg:postcode":"T2V 1P8",
    "sg:province":"AB",
    "sg:tags":[
        "home",
        "convalescent"
    ],
    "wof:name":"Glenmore Park",
    "wof:placetype":"venue"
},
  "geometry": {"coordinates":[-114.09535200000001,50.990978],"type":"Point"}
}