{
  "type": "Feature",
  "properties": {
    "addr:full":"531 13 St N Lethbridge AB T1H 2S6",
    "addr:housenumber":"13",
    "addr:postcode":"t1h 2s6",
    "addr:street":"531;St N",
    "iso:country":"CA",
    "sg:address":"531 13 St N",
    "sg:city":"Lethbridge",
    "sg:classifiers":[
        {
            "category":"Restaurant",
            "type":"Food & Drink"
        }
    ],
    "sg:phone":"+1 403 329 0346",
    "sg:postcode":"T1H 2S6",
    "sg:province":"AB",
    "wof:name":"Henry's Restaurant",
    "wof:placetype":"venue"
},
  "geometry": {"coordinates":[-112.823997498,49.70677948],"type":"Point"}
}