{
  "type": "Feature",
  "properties": {
    "iso:country":"CA",
    "sg:city":"Vancouver",
    "sg:classifiers":[
        {
            "category":"Restaurant",
            "type":"Food & Drink"
        }
    ],
    "sg:phone":"+1 604 688 0871",
    "sg:postcode":"V6A 1X5",
    "sg:province":"BC",
    "wof:name":"Hon's Wun-Tun House Ltd",
    "wof:placetype":"venue"
},
  "geometry": {"coordinates":[-123.098038,49.279297],"type":"Point"}
}