{
  "type": "Feature",
  "properties": {
    "addr:full":"134 Waterloo St S Stratford ON N5A 4B4",
    "addr:housenumber":"134",
    "addr:postcode":"n5a 4b4",
    "addr:street":"Waterloo St S",
    "iso:country":"CA",
    "sg:address":"134 Waterloo St S",
    "sg:city":"Stratford",
    "sg:classifiers":[
        {
            "category":"Professional",
            "subcategory":"Accounting & Tax Preparation",
            "type":"Services"
        }
    ],
    "sg:phone":"+1 519 271 2491",
    "sg:postcode":"N5A 4B4",
    "sg:province":"ON",
    "sg:tags":[
        "consultant",
        "accountant",
        "planning",
        "financial"
    ],
    "wof:name":"Bdo Dunwoody Llp",
    "wof:placetype":"venue"
},
  "geometry": {"coordinates":[-80.980057,43.368877],"type":"Point"}
}