{
  "type": "Feature",
  "properties": {
    "addr:full":"98 Orfus Rd North York ON M6A 1L9",
    "addr:housenumber":"98",
    "addr:postcode":"m6a 1l9",
    "addr:street":"Orfus Rd",
    "iso:country":"CA",
    "sg:address":"98 Orfus Rd",
    "sg:city":"North York",
    "sg:classifiers":[
        {
            "category":"Home & Garden",
            "subcategory":"Home Furnishings",
            "type":"Retail Goods"
        }
    ],
    "sg:phone":"+1 416 780 0226",
    "sg:postcode":"M6A 1L9",
    "sg:province":"ON",
    "sg:tags":[
        "housewares",
        "kitchen",
        "accessory"
    ],
    "wof:name":"Barnes & Castle",
    "wof:placetype":"venue"
},
  "geometry": {"coordinates":[-79.46427199999999,43.718739],"type":"Point"}
}