{
  "type": "Feature",
  "properties": {
    "addr:full":"Toronto ON M5T 1Z7",
    "addr:postcode":"m5t 1z7",
    "iso:country":"CA",
    "sg:city":"Toronto",
    "sg:classifiers":[
        {
            "category":"Arts & Performance",
            "subcategory":"Theater",
            "type":"Entertainment"
        }
    ],
    "sg:phone":"+1 416 351 9111",
    "sg:postcode":"M5T 1Z7",
    "sg:province":"ON",
    "sg:tags":[
        "bureau"
    ],
    "wof:name":"Lone Eagle Entertainment",
    "wof:placetype":"venue"
},
  "geometry": {"coordinates":[-79.393944,43.65015],"type":"Point"}
}