{
  "type": "Feature",
  "properties": {
    "addr:full":"412 Tuscany Dr Thunder Bay ON P7G 1B7",
    "addr:housenumber":"412",
    "addr:postcode":"p7g 1b7",
    "addr:street":"Tuscany Dr",
    "iso:country":"CA",
    "sg:address":"412 Tuscany Dr",
    "sg:city":"Thunder Bay",
    "sg:classifiers":[
        {
            "category":"Building & Trades",
            "subcategory":"Construction",
            "type":"Services"
        }
    ],
    "sg:phone":"+1 807 624 8392",
    "sg:postcode":"P7G 1B7",
    "sg:province":"ON",
    "sg:tags":[
        "roofing",
        "contractor"
    ],
    "wof:name":"Romu Roofing & Contracting",
    "wof:placetype":"venue"
},
  "geometry": {"coordinates":[-89.259377,48.465542],"type":"Point"}
}