{
  "type": "Feature",
  "properties": {
    "addr:full":"5045 Boul Des Laurentides Laval QC H7K 2J7",
    "addr:housenumber":"5045",
    "addr:postcode":"qc h7k 2j7",
    "addr:street":"Boul Des Laurentides",
    "iso:country":"CA",
    "sg:address":"5045 Boul Des Laurentides",
    "sg:city":"Laval",
    "sg:classifiers":[
        {
            "category":"Retail",
            "subcategory":"Auto Repair",
            "type":"Services"
        }
    ],
    "sg:phone":"+1 450 963 3735",
    "sg:postcode":"H7K 2J7",
    "sg:province":"QC",
    "sg:tags":[
        "transmission",
        "automobile",
        "repairing"
    ],
    "wof:name":"Transmission Samson Inc",
    "wof:placetype":"venue"
},
  "geometry": {"coordinates":[-73.745064,45.620392],"type":"Point"}
}