{
  "type": "Feature",
  "properties": {
    "addr:full":"Irvine AB T0J 1V0",
    "addr:postcode":"t0j 1v0",
    "iso:country":"CA",
    "sg:city":"Irvine",
    "sg:classifiers":[
        {
            "category":"Education",
            "subcategory":"School",
            "type":"Public Place"
        }
    ],
    "sg:phone":"+1 403 834 3783",
    "sg:postcode":"T0J 1V0",
    "sg:province":"AB",
    "wof:name":"Irvine School",
    "wof:placetype":"venue"
},
  "geometry": {"coordinates":[-110.27401733400001,49.9604606628],"type":"Point"}
}