{
  "type": "Feature",
  "properties": {
    "addr:full":"720 Belleville St Victoria BC V8W 1A3",
    "addr:housenumber":"720",
    "addr:postcode":"v8w 1a3",
    "addr:street":"Belleville St",
    "iso:country":"CA",
    "sg:address":"720 Belleville St",
    "sg:city":"Victoria",
    "sg:classifiers":[
        {
            "category":"Recreation",
            "type":"Entertainment"
        }
    ],
    "sg:phone":"+1 250 385 3577",
    "sg:postcode":"V8W 1A3",
    "sg:province":"BC",
    "sg:tags":[
        "amusement"
    ],
    "wof:name":"C P Lawn Bowling Club",
    "wof:placetype":"venue"
},
  "geometry": {"coordinates":[-123.365883,48.420223],"type":"Point"}
}