{
  "type": "Feature",
  "properties": {
    "addr:full":"277 Cumberland St N Thunder Bay ON P7A 4N7",
    "addr:housenumber":"277",
    "addr:postcode":"p7a 4n7",
    "addr:street":"Cumberland St N",
    "iso:country":"CA",
    "sg:address":"277 Cumberland St N",
    "sg:city":"Thunder Bay",
    "sg:classifiers":[
        {
            "category":"Autos & Motor Vehicles",
            "subcategory":"Fuel & Gas Station",
            "type":"Retail Goods"
        }
    ],
    "sg:phone":"+1 807 344 8075",
    "sg:postcode":"P7A 4N7",
    "sg:province":"ON",
    "sg:tags":[
        "oil"
    ],
    "wof:name":"Shell Canada Products Ltd",
    "wof:placetype":"venue"
},
  "geometry": {"coordinates":[-89.208862,48.442928],"type":"Point"}
}