{
  "type": "Feature",
  "properties": {
    "addr:full":"17 Prom Ronald Montreal-Ouest QC H4X 1M9",
    "addr:housenumber":"17",
    "addr:postcode":"h4x 1m9",
    "addr:street":"Prom Ronald Montreal-Ouest",
    "iso:country":"CA",
    "sg:address":"17 Prom Ronald",
    "sg:city":"Montreal-Ouest",
    "sg:classifiers":[
        {
            "category":"Shopping",
            "subcategory":"Musical Instruments",
            "type":"Retail Goods"
        }
    ],
    "sg:phone":"+1 514 486 5373",
    "sg:postcode":"H4X 1M9",
    "sg:province":"QC",
    "wof:name":"Westend Piano Ltd",
    "wof:placetype":"venue"
},
  "geometry": {"coordinates":[-73.637085,45.45042],"type":"Point"}
}