{
  "type": "Feature",
  "properties": {
    "iso:country":"CA",
    "sg:address":"191 Castor St",
    "sg:city":"Russell",
    "sg:classifiers":[
        {
            "category":"Manufacturing",
            "subcategory":"Printing",
            "type":"Manufacturing & Wholesale Goods"
        }
    ],
    "sg:phone":"+1 613 445 3804",
    "sg:postcode":"K4R 1C7",
    "sg:province":"ON",
    "sg:tags":[
        "newspaper"
    ],
    "wof:name":"Russell Villager",
    "wof:placetype":"venue"
},
  "geometry": {"coordinates":[-75.35749816889999,45.2576560974],"type":"Point"}
}