{
  "type": "Feature",
  "properties": {
    "addr:full":"Etobicoke ON M9W 5T7",
    "addr:postcode":"m9w 5t7",
    "iso:country":"CA",
    "sg:city":"Etobicoke",
    "sg:classifiers":[
        {
            "category":"Professional",
            "subcategory":"Accounting & Tax Preparation",
            "type":"Services"
        }
    ],
    "sg:phone":"+1 416 675 1444",
    "sg:postcode":"M9W 5T7",
    "sg:province":"ON",
    "sg:tags":[
        "accountant"
    ],
    "wof:name":"Samuels Malachi & Assoc",
    "wof:placetype":"venue"
},
  "geometry": {"coordinates":[-79.60626999999999,43.739044],"type":"Point"}
}