{
  "type": "Feature",
  "properties": {
    "iso:country":"CA",
    "sg:address":"10 Rue Notre Dame",
    "sg:city":"Hebertville-Station",
    "sg:classifiers":[
        {
            "category":"Manufacturing",
            "subcategory":"Rubber & Plastics",
            "type":"Manufacturing & Wholesale Goods"
        }
    ],
    "sg:phone":"+1 418 343 2204",
    "sg:postcode":"G0W 1T0",
    "sg:province":"QC",
    "sg:tags":[
        "bag"
    ],
    "wof:name":"Sacs Munger Ltee",
    "wof:placetype":"venue"
},
  "geometry": {"coordinates":[-71.6636047363,48.4440536499],"type":"Point"}
}