{
  "type": "Feature",
  "properties": {
    "addr:full":"57 Arthur St S Elmira ON N3B 2M6",
    "addr:housenumber":"57",
    "addr:postcode":"n3b 2m6",
    "addr:street":"Arthur St S",
    "iso:country":"CA",
    "sg:address":"57 Arthur St S",
    "sg:city":"Elmira",
    "sg:classifiers":[
        {
            "category":"Shopping",
            "type":"Retail Goods"
        }
    ],
    "sg:phone":"+1 519 669 3456",
    "sg:postcode":"N3B 2M6",
    "sg:province":"ON",
    "sg:tags":[
        "photographer",
        "picture"
    ],
    "wof:name":"Elmira Photo Lab",
    "wof:placetype":"venue"
},
  "geometry": {"coordinates":[-80.55864,43.598476],"type":"Point"}
}