{
  "type": "Feature",
  "properties": {
    "iso:country":"CA",
    "sg:address":"913 Elm St",
    "sg:city":"Campbell River",
    "sg:classifiers":[
        {
            "category":"Manufacturing",
            "subcategory":"Tools & Machinery",
            "type":"Manufacturing & Wholesale Goods"
        }
    ],
    "sg:phone":"+1 250 287 8882",
    "sg:postcode":"V9W 2Z9",
    "sg:province":"BC",
    "sg:tags":[
        "machine",
        "shop"
    ],
    "wof:name":"Rogers Precision Machine Ltd",
    "wof:placetype":"venue"
},
  "geometry": {"coordinates":[-125.24932098399999,50.0235557556],"type":"Point"}
}