{
  "type": "Feature",
  "properties": {
    "iso:country":"CA",
    "sg:address":"10815 23 Ave NW",
    "sg:city":"Edmonton",
    "sg:classifiers":[
        {
            "category":"Health Services",
            "subcategory":"Chiropractor",
            "type":"Services"
        }
    ],
    "sg:phone":"+1 780 989 3880",
    "sg:postcode":"T6J 7B5",
    "sg:province":"AB",
    "wof:name":"Heritage Lane Chiropractic",
    "wof:placetype":"venue"
},
  "geometry": {"coordinates":[-113.507453919,53.4536132812],"type":"Point"}
}