{
  "type": "Feature",
  "properties": {
    "addr:full":"304 3rd St E Youngstown AB T0J 3P0",
    "addr:housenumber":"304",
    "addr:postcode":"t0j 3p0",
    "addr:street":"3Rd St E",
    "iso:country":"CA",
    "sg:address":"304 3rd St E",
    "sg:city":"Youngstown",
    "sg:classifiers":[
        {
            "category":"Government",
            "subcategory":"Office",
            "type":"Public Place"
        }
    ],
    "sg:phone":"+1 403 779 3920",
    "sg:postcode":"T0J 3P0",
    "sg:province":"AB",
    "wof:name":"Alberta Youngstown Home",
    "wof:placetype":"venue"
},
  "geometry": {"coordinates":[-111.203789,51.525043],"type":"Point"}
}