{
  "type": "Feature",
  "properties": {
    "addr:full":"29 Mary St Parry Sound ON P2A 1E3",
    "addr:housenumber":"29",
    "addr:postcode":"p2a 1e3",
    "addr:street":"Mary St",
    "iso:country":"CA",
    "sg:address":"29 Mary St",
    "sg:city":"Parry Sound",
    "sg:classifiers":[
        {
            "category":"Education",
            "subcategory":"Library",
            "type":"Public Place"
        }
    ],
    "sg:phone":"+1 705 746 9601",
    "sg:postcode":"P2A 1E3",
    "sg:province":"ON",
    "wof:name":"Parry Sound Public Library",
    "wof:placetype":"venue"
},
  "geometry": {"coordinates":[-80.034317,45.34568],"type":"Point"}
}