{
  "type": "Feature",
  "properties": {
    "addr:full":"363 5E Rue Shawinigan QC G9N 1E4",
    "addr:housenumber":"363",
    "addr:postcode":"g9n 1e4",
    "addr:street":"5E Rue",
    "iso:country":"CA",
    "sg:address":"363 5E Rue",
    "sg:city":"Shawinigan",
    "sg:classifiers":[
        {
            "category":"Shopping",
            "subcategory":"Bicycles & Sporting Goods",
            "type":"Retail Goods"
        }
    ],
    "sg:phone":"+1 819 537 1142",
    "sg:postcode":"G9N 1E4",
    "sg:province":"QC",
    "wof:name":"Yeti",
    "wof:placetype":"venue"
},
  "geometry": {"coordinates":[-72.746826,46.54052],"type":"Point"}
}