{
  "type": "Feature",
  "properties": {
    "addr:full":"240 Heath St W # P4 York ON M5P 3L5",
    "addr:housenumber":"240",
    "addr:postcode":"m5p 3l5",
    "addr:street":"Heath St W # P4",
    "iso:country":"CA",
    "sg:address":"240 Heath St W # P4",
    "sg:city":"York",
    "sg:classifiers":[
        {
            "category":"Professional",
            "subcategory":"Business Services",
            "type":"Services"
        }
    ],
    "sg:phone":"+1 416 922 4616",
    "sg:postcode":"M5P 3L5",
    "sg:province":"ON",
    "sg:tags":[
        "consultant",
        "motel",
        "hotel",
        "reservation"
    ],
    "wof:name":"Dimension Incentive Hotels",
    "wof:placetype":"venue"
},
  "geometry": {"coordinates":[-79.41306304930001,43.6866607666],"type":"Point"}
}