{
  "type": "Feature",
  "properties": {
    "iso:country":"CA",
    "sg:address":"272 Mackenzie St",
    "sg:city":"Bella Coola",
    "sg:classifiers":[
        {
            "category":"Recreation",
            "type":"Entertainment"
        }
    ],
    "sg:phone":"+1 250 799 5130",
    "sg:postcode":"V0T 1C0",
    "sg:province":"BC",
    "sg:tags":[
        "hall",
        "auditorium"
    ],
    "wof:name":"Moose Hall",
    "wof:placetype":"venue"
},
  "geometry": {"coordinates":[-126.74919128400001,52.3709564209],"type":"Point"}
}