{
  "type": "Feature",
  "properties": {
    "addr:full":"340 Main St Stonewall MB R0C 2Z0",
    "addr:housenumber":"340",
    "addr:postcode":"r0c 2z0",
    "addr:street":"Main St",
    "iso:country":"CA",
    "sg:address":"340 Main St",
    "sg:city":"Stonewall",
    "sg:classifiers":[
        {
            "category":"Banks & Credit Unions",
            "subcategory":"Bank",
            "type":"Services"
        }
    ],
    "sg:phone":"+1 204 467 5544",
    "sg:postcode":"R0C 2Z0",
    "sg:province":"MB",
    "wof:name":"Royal Bank Financial Group",
    "wof:placetype":"venue"
},
  "geometry": {"coordinates":[-97.32642364500001,50.1349906921],"type":"Point"}
}