{
  "type": "Feature",
  "properties": {
    "addr:full":"367 Main St Aroostook NB E7H 2Z4",
    "addr:housenumber":"367",
    "addr:postcode":"e7h 2z4",
    "addr:street":"Main St",
    "iso:country":"CA",
    "sg:address":"367 Main St",
    "sg:city":"Aroostook",
    "sg:classifiers":[
        {
            "category":"Building & Trades",
            "subcategory":"Electrical",
            "type":"Services"
        }
    ],
    "sg:phone":"+1 506 273 3948",
    "sg:postcode":"E7H 2Z4",
    "sg:province":"NB",
    "sg:tags":[
        "electric",
        "contractor"
    ],
    "wof:name":"Carl's Electric Ltd",
    "wof:placetype":"venue"
},
  "geometry": {"coordinates":[-67.72865299999999,46.807484],"type":"Point"}
}