{
  "type": "Feature",
  "properties": {
    "addr:full":"106 Rue Maclaren E Buckingham QC J8L 1K1",
    "addr:housenumber":"106",
    "addr:postcode":"j8l 1k1",
    "addr:street":"Rue Maclaren E",
    "iso:country":"CA",
    "sg:address":"106 Rue Maclaren E",
    "sg:city":"Buckingham",
    "sg:classifiers":[
        {
            "category":"Banks & Credit Unions",
            "subcategory":"Financial Services",
            "type":"Services"
        }
    ],
    "sg:phone":"+1 819 281 2716",
    "sg:postcode":"J8L 1K1",
    "sg:province":"QC",
    "sg:tags":[
        "bankruptcy",
        "trustee"
    ],
    "wof:name":"Ginsberg Gingras",
    "wof:placetype":"venue"
},
  "geometry": {"coordinates":[-75.41628300000001,45.58651],"type":"Point"}
}