{
  "type": "Feature",
  "properties": {
    "addr:full":"7715 Boul Jean-Xxiii Trois-Rivieres-Ouest QC G9A 5C9",
    "addr:housenumber":"7715",
    "addr:postcode":"g9a 5c9",
    "addr:street":"Boul Jean-Xxiii Trois-Rivieres-Ouest",
    "iso:country":"CA",
    "sg:address":"7715 Boul Jean-Xxiii",
    "sg:city":"Trois-Rivieres-Ouest",
    "sg:classifiers":[
        {
            "category":"Autos & Motor Vehicles",
            "subcategory":"Automobile Sales",
            "type":"Retail Goods"
        }
    ],
    "sg:phone":"+1 819 377 0888",
    "sg:postcode":"G9A 5C9",
    "sg:province":"QC",
    "sg:tags":[
        "car",
        "dealer"
    ],
    "wof:name":"Automobiles Denis Lemay",
    "wof:placetype":"venue"
},
  "geometry": {"coordinates":[-72.6057128906,46.3204727173],"type":"Point"}
}