{
  "type": "Feature",
  "properties": {
    "addr:full":"288 Speers Rd Oakville ON L6K 2E9",
    "addr:housenumber":"288",
    "addr:postcode":"l6k 2e9",
    "addr:street":"Speers Rd",
    "iso:country":"CA",
    "sg:address":"288 Speers Rd",
    "sg:city":"Oakville",
    "sg:classifiers":[
        {
            "category":"Home & Garden",
            "subcategory":"Furniture",
            "type":"Retail Goods"
        }
    ],
    "sg:phone":"+1 905 815 1923",
    "sg:postcode":"L6K 2E9",
    "sg:province":"ON",
    "sg:tags":[
        "equipment",
        "kitchen",
        "cabinet"
    ],
    "wof:name":"Oakeville Quarry",
    "wof:placetype":"venue"
},
  "geometry": {"coordinates":[-79.6916732788,43.4419975281],"type":"Point"}
}