{
  "type": "Feature",
  "properties": {
    "addr:full":"Price QC G0J 1Z0",
    "addr:postcode":"g0j 1z0",
    "iso:country":"CA",
    "sg:city":"Price",
    "sg:classifiers":[
        {
            "category":"Freight",
            "type":"Transportation"
        }
    ],
    "sg:phone":"+1 418 775 9484",
    "sg:postcode":"G0J 1Z0",
    "sg:province":"QC",
    "sg:tags":[
        "trucking"
    ],
    "wof:name":"Transport Gino Bois Inc",
    "wof:placetype":"venue"
},
  "geometry": {"coordinates":[-68.1201019287,48.5956077576],"type":"Point"}
}