{
  "type": "Feature",
  "properties": {
    "addr:full":"68 13th St NW Portage LA Prairie MB R1N 2T6",
    "addr:housenumber":"68",
    "addr:postcode":"r1n 2t6",
    "addr:street":"13Th St Nw",
    "iso:country":"CA",
    "sg:address":"68 13th St NW",
    "sg:city":"Portage LA Prairie",
    "sg:classifiers":[
        {
            "category":"Utilities",
            "subcategory":"Refuse",
            "type":"Services"
        }
    ],
    "sg:phone":"+1 204 857 8653",
    "sg:postcode":"R1N 2T6",
    "sg:province":"MB",
    "sg:tags":[
        "control",
        "equipment",
        "recycling",
        "system",
        "weight"
    ],
    "wof:name":"Herbalife Distributors",
    "wof:placetype":"venue"
},
  "geometry": {"coordinates":[-98.30703735349999,49.9751358032],"type":"Point"}
}