{
  "type": "Feature",
  "properties": {
    "addr:full":"699 Rue DE Quen Dolbeau-Mistassini QC G8L 5M6",
    "addr:housenumber":"699",
    "addr:postcode":"g8l 5m6",
    "addr:street":"Rue De Quen",
    "iso:country":"CA",
    "sg:address":"699 Rue DE Quen",
    "sg:city":"Dolbeau-Mistassini",
    "sg:classifiers":[
        {
            "category":"Building & Trades",
            "subcategory":"Landscaping Services",
            "type":"Services"
        }
    ],
    "sg:phone":"+1 418 276 9064",
    "sg:postcode":"G8L 5M6",
    "sg:province":"QC",
    "sg:tags":[
        "landscape",
        "contractor"
    ],
    "wof:name":"Serres Pepiniere Turvil Inc",
    "wof:placetype":"venue"
},
  "geometry": {"coordinates":[-72.187927,48.858311],"type":"Point"}
}