{
  "type": "Feature",
  "properties": {
    "addr:full":"6575 Farmers Dr Kelowna BC V1P 1A2",
    "addr:housenumber":"6575",
    "addr:postcode":"v1p 1a2",
    "addr:street":"Farmers Dr",
    "iso:country":"CA",
    "sg:address":"6575 Farmers Dr",
    "sg:city":"Kelowna",
    "sg:classifiers":[
        {
            "category":"Home & Garden",
            "subcategory":"Garden Supply",
            "type":"Retail Goods"
        }
    ],
    "sg:phone":"+1 250 765 1132",
    "sg:postcode":"V1P 1A2",
    "sg:province":"BC",
    "sg:tags":[
        "ornament"
    ],
    "wof:name":"Lang's House of Arts",
    "wof:placetype":"venue"
},
  "geometry": {"coordinates":[-119.348510742,49.9773216248],"type":"Point"}
}