{
  "type": "Feature",
  "properties": {
    "addr:full":"3075 Av Lebrun Montreal QC H1L 5G2",
    "addr:housenumber":"3075",
    "addr:postcode":"h1l 5g2",
    "addr:street":"Av Lebrun",
    "iso:country":"CA",
    "sg:address":"3075 Av Lebrun",
    "sg:city":"Montreal",
    "sg:classifiers":[
        {
            "category":"Education",
            "subcategory":"School",
            "type":"Public Place"
        }
    ],
    "sg:phone":"+1 514 596 4000",
    "sg:postcode":"H1L 5G2",
    "sg:province":"QC",
    "wof:name":"Regroupement 4",
    "wof:placetype":"venue"
},
  "geometry": {"coordinates":[-73.5286026001,45.6017990112],"type":"Point"}
}