{
  "type": "Feature",
  "properties": {
    "iso:country":"CA",
    "sg:address":"1401 Broad St",
    "sg:city":"Regina",
    "sg:classifiers":[
        {
            "category":"Utilities",
            "subcategory":"Mobile Phone",
            "type":"Services"
        }
    ],
    "sg:phone":"+1 306 525 1721",
    "sg:postcode":"S4R 1Y8",
    "sg:province":"SK",
    "sg:tags":[
        "telephone",
        "cellular"
    ],
    "wof:name":"Wireless Age",
    "wof:placetype":"venue"
},
  "geometry": {"coordinates":[-104.606086731,50.4565696716],"type":"Point"}
}