{
  "type": "Feature",
  "properties": {
    "iso:country":"CA",
    "sg:address":"883 Islington Ave",
    "sg:city":"Etobicoke",
    "sg:classifiers":[
        {
            "category":"Wholesale",
            "subcategory":"Drugs",
            "type":"Manufacturing & Wholesale Goods"
        }
    ],
    "sg:phone":"+1 416 252 0125",
    "sg:postcode":"M8Z 4N9",
    "sg:province":"ON",
    "sg:tags":[
        "cosmetic"
    ],
    "wof:name":"Mitomo Imports Inc",
    "wof:placetype":"venue"
},
  "geometry": {"coordinates":[-79.5143280029,43.6231002808],"type":"Point"}
}