{
  "type": "Feature",
  "properties": {
    "addr:full":"7 Queen St W Brampton ON L6Y 1L9",
    "addr:housenumber":"7",
    "addr:postcode":"l6y 1l9",
    "addr:street":"Queen St W",
    "iso:country":"CA",
    "sg:address":"7 Queen St W",
    "sg:city":"Brampton",
    "sg:classifiers":[
        {
            "category":"Travel",
            "subcategory":"Travel Agent",
            "type":"Entertainment"
        }
    ],
    "sg:phone":"+1 905 453 1855",
    "sg:postcode":"L6Y 1L9",
    "sg:province":"ON",
    "sg:tags":[
        "agency",
        "bureau"
    ],
    "wof:name":"Brampton Travel Agency",
    "wof:placetype":"venue"
},
  "geometry": {"coordinates":[-79.759933,43.68568],"type":"Point"}
}