{
  "type": "Feature",
  "properties": {
    "addr:full":"11 Coldwater St E Orillia ON L3V 1W4",
    "addr:housenumber":"11",
    "addr:postcode":"l3v 1w4",
    "addr:street":"Coldwater St E",
    "iso:country":"CA",
    "sg:address":"11 Coldwater St E",
    "sg:city":"Orillia",
    "sg:classifiers":[
        {
            "category":"Professional",
            "subcategory":"Business Services",
            "type":"Services"
        }
    ],
    "sg:phone":"+1 705 325 4545",
    "sg:postcode":"L3V 1W4",
    "sg:province":"ON",
    "sg:tags":[
        "interior",
        "consultant",
        "design",
        "decorator"
    ],
    "wof:name":"Hamilton & CO",
    "wof:placetype":"venue"
},
  "geometry": {"coordinates":[-79.42002100000001,44.609562],"type":"Point"}
}