{
  "type": "Feature",
  "properties": {
    "addr:full":"155 Adelaide St S London ON N5Z 3K8",
    "addr:housenumber":"155",
    "addr:postcode":"n5z 3k8",
    "addr:street":"Adelaide St S",
    "iso:country":"CA",
    "sg:address":"155 Adelaide St S",
    "sg:city":"London",
    "sg:classifiers":[
        {
            "category":"Retail",
            "subcategory":"Laundry & Dry Cleaning",
            "type":"Services"
        }
    ],
    "sg:phone":"+1 519 686 5000",
    "sg:postcode":"N5Z 3K8",
    "sg:province":"ON",
    "sg:tags":[
        "linen",
        "supply",
        "rental",
        "uniform"
    ],
    "wof:name":"Canadian Linen & Uniform Svc",
    "wof:placetype":"venue"
},
  "geometry": {"coordinates":[-81.222168,42.966545],"type":"Point"}
}