{
  "type": "Feature",
  "properties": {
    "addr:full":"94 Kenyon St W Alexandria ON K0C 1A0",
    "addr:housenumber":"94",
    "addr:postcode":"k0c 1a0",
    "addr:street":"Kenyon St W",
    "iso:country":"CA",
    "sg:address":"94 Kenyon St W",
    "sg:city":"Alexandria",
    "sg:classifiers":[
        {
            "category":"Travel",
            "subcategory":"Hotels & Motels",
            "type":"Entertainment"
        }
    ],
    "sg:phone":"+1 613 525 0321",
    "sg:postcode":"K0C 1A0",
    "sg:province":"ON",
    "sg:tags":[
        "breakfast",
        "accommodation",
        "bed"
    ],
    "wof:name":"Carriage House",
    "wof:placetype":"venue"
},
  "geometry": {"coordinates":[-74.6398239136,45.3096351624],"type":"Point"}
}