{
  "type": "Feature",
  "properties": {
    "addr:full":"Edmonton AB T5K 2L4",
    "addr:postcode":"t5k 2l4",
    "iso:country":"CA",
    "sg:city":"Edmonton",
    "sg:classifiers":[
        {
            "category":"Real Estate",
            "subcategory":"Real Estate Operator",
            "type":"Services"
        }
    ],
    "sg:phone":"+1 780 423 5119",
    "sg:postcode":"T5K 2L4",
    "sg:province":"AB",
    "sg:tags":[
        "apartment"
    ],
    "wof:name":"Shaughnessy House",
    "wof:placetype":"venue"
},
  "geometry": {"coordinates":[-113.51741800000001,53.542389],"type":"Point"}
}