{
  "type": "Feature",
  "properties": {
    "addr:full":"636 Hugel Ave Midland ON L4R 1W7",
    "addr:housenumber":"636",
    "addr:postcode":"l4r 1w7",
    "addr:street":"Hugel Ave",
    "iso:country":"CA",
    "sg:address":"636 Hugel Ave",
    "sg:city":"Midland",
    "sg:classifiers":[
        {
            "category":"Building & Trades",
            "subcategory":"Construction",
            "type":"Services"
        }
    ],
    "sg:phone":"+1 705 526 8212",
    "sg:postcode":"L4R 1W7",
    "sg:province":"ON",
    "sg:tags":[
        "general",
        "contractor"
    ],
    "wof:name":"Bandana Construction Ltd",
    "wof:placetype":"venue"
},
  "geometry": {"coordinates":[-79.891014,44.747726],"type":"Point"}
}