{
  "type": "Feature",
  "properties": {
    "addr:full":"100 Burncrest Rd Markham ON L3R 0B7",
    "addr:housenumber":"100",
    "addr:postcode":"l3r 0b7",
    "addr:street":"Burncrest Rd",
    "iso:country":"CA",
    "sg:address":"100 Burncrest Rd",
    "sg:city":"Markham",
    "sg:classifiers":[
        {
            "category":"Freight",
            "type":"Transportation"
        }
    ],
    "sg:phone":"+1 905 475 6262",
    "sg:postcode":"L3R 0B7",
    "sg:province":"ON",
    "sg:tags":[
        "commercial",
        "storage"
    ],
    "wof:name":"Dayton Self Storage Inc",
    "wof:placetype":"venue"
},
  "geometry": {"coordinates":[-79.35827636720001,43.8378334045],"type":"Point"}
}