{
  "type": "Feature",
  "properties": {
    "addr:full":"213 10th St Beaverlodge AB T0H 0C0",
    "addr:housenumber":"213",
    "addr:postcode":"t0h 0c0",
    "addr:street":"10Th St",
    "iso:country":"CA",
    "sg:address":"213 10th St",
    "sg:city":"Beaverlodge",
    "sg:classifiers":[
        {
            "category":"Health Services",
            "subcategory":"Doctor",
            "type":"Services"
        }
    ],
    "sg:phone":"+1 780 354 8288",
    "sg:postcode":"T0H 0C0",
    "sg:province":"AB",
    "sg:tags":[
        "dentist"
    ],
    "wof:name":"Beaverlodge Dental Ctr",
    "wof:placetype":"venue"
},
  "geometry": {"coordinates":[-119.428131103,55.2098884583],"type":"Point"}
}