{
  "type": "Feature",
  "properties": {
    "addr:full":"White Pine Rd Sioux Narrows ON P0X 1N0",
    "addr:postcode":"p0x 1n0",
    "addr:street":"White Pine Rd",
    "iso:country":"CA",
    "sg:address":"White Pine Rd",
    "sg:city":"Sioux Narrows",
    "sg:classifiers":[
        {
            "category":"Travel",
            "subcategory":"Hotels & Motels",
            "type":"Entertainment"
        }
    ],
    "sg:phone":"+1 807 226 5267",
    "sg:postcode":"P0X 1N0",
    "sg:province":"ON",
    "sg:tags":[
        "resort"
    ],
    "wof:name":"White Pine Lodge",
    "wof:placetype":"venue"
},
  "geometry": {"coordinates":[-94.0960693359,49.4190254211],"type":"Point"}
}