{
  "type": "Feature",
  "properties": {
    "iso:country":"CA",
    "sg:address":"89 Route 172",
    "sg:city":"Upper Letang",
    "sg:classifiers":[
        {
            "category":"Organizations",
            "subcategory":"Religious Organization",
            "type":"Services"
        }
    ],
    "sg:phone":"+1 506 755 3759",
    "sg:postcode":"E5C 2C7",
    "sg:province":"NB",
    "sg:tags":[
        "church"
    ],
    "wof:name":"Family Worship Ctr",
    "wof:placetype":"venue"
},
  "geometry": {"coordinates":[-66.8264083862,45.0821113586],"type":"Point"}
}