{
  "type": "Feature",
  "properties": {
    "iso:country":"CA",
    "sg:address":"Hwy 750",
    "sg:city":"Gift Lake",
    "sg:classifiers":[
        {
            "category":"Manufacturing",
            "subcategory":"Lumber",
            "type":"Manufacturing & Wholesale Goods"
        }
    ],
    "sg:phone":"+1 780 767 2230",
    "sg:postcode":"T0G 1B0",
    "sg:province":"AB",
    "sg:tags":[
        "company",
        "logging"
    ],
    "wof:name":"Gift Lake Logging",
    "wof:placetype":"venue"
},
  "geometry": {"coordinates":[-115.835342407,55.8366127014],"type":"Point"}
}