{
  "type": "Feature",
  "properties": {
    "addr:full":"1270 Sunningdale Rd E London ON N5X 3Y6",
    "addr:housenumber":"1270",
    "addr:postcode":"n5x 3y6",
    "addr:street":"Sunningdale Rd E",
    "iso:country":"CA",
    "sg:address":"1270 Sunningdale Rd E",
    "sg:city":"London",
    "sg:classifiers":[
        {
            "category":"Recreation",
            "type":"Entertainment"
        }
    ],
    "sg:phone":"+1 519 660 6808",
    "sg:postcode":"N5X 3Y6",
    "sg:province":"ON",
    "sg:tags":[
        "riding",
        "academy"
    ],
    "wof:name":"Woodacre Farms",
    "wof:placetype":"venue"
},
  "geometry": {"coordinates":[-81.245949,43.051174],"type":"Point"}
}