{
  "type": "Feature",
  "properties": {
    "iso:country":"CA",
    "sg:address":"3920 County Rd 1",
    "sg:city":"Yarker",
    "sg:classifiers":[
        {
            "category":"Building & Trades",
            "subcategory":"Construction",
            "type":"Services"
        }
    ],
    "sg:phone":"+1 613 377 6525",
    "sg:postcode":"K0K 3N0",
    "sg:province":"ON",
    "sg:tags":[
        "siding",
        "material",
        "contractor"
    ],
    "wof:name":"Angle Aluminum",
    "wof:placetype":"venue"
},
  "geometry": {"coordinates":[-76.7711029053,44.3717460632],"type":"Point"}
}