{
  "type": "Feature",
  "properties": {
    "iso:country":"CA",
    "sg:city":"Plantagenet",
    "sg:classifiers":[
        {
            "category":"Restaurant",
            "type":"Food & Drink"
        }
    ],
    "sg:phone":"+1 613 673 5220",
    "sg:postcode":"K0B 1L0",
    "sg:province":"ON",
    "wof:name":"Champlain Motel & Restaurant",
    "wof:placetype":"venue"
},
  "geometry": {"coordinates":[-74.99030303959999,45.5402374268],"type":"Point"}
}