{
  "type": "Feature",
  "properties": {
    "addr:full":"10210 Macleod Trail SE Calgary AB T2J 0P8",
    "addr:housenumber":"10210",
    "addr:postcode":"t2j 0p8",
    "addr:street":"Macleod Trail Se",
    "iso:country":"CA",
    "sg:address":"10210 Macleod Trail SE",
    "sg:city":"Calgary",
    "sg:classifiers":[
        {
            "category":"Building & Trades",
            "subcategory":"Equipment Rental",
            "type":"Services"
        }
    ],
    "sg:phone":"+1 403 271 7848",
    "sg:postcode":"T2J 0P8",
    "sg:province":"AB",
    "sg:tags":[
        "player",
        "recorder",
        "video"
    ],
    "wof:name":"Source Adult Video",
    "wof:placetype":"venue"
},
  "geometry": {"coordinates":[-114.071266174,50.9606552124],"type":"Point"}
}