{
  "type": "Feature",
  "properties": {
    "iso:country":"CA",
    "sg:address":"4909 51 Ave",
    "sg:city":"Stettler",
    "sg:classifiers":[
        {
            "category":"Professional",
            "subcategory":"Management & Consulting",
            "type":"Services"
        }
    ],
    "sg:phone":"+1 403 742 6673",
    "sg:postcode":"T0C 2L2",
    "sg:province":"AB",
    "sg:tags":[
        "marketing",
        "consultant"
    ],
    "wof:name":"Marketing & More",
    "wof:placetype":"venue"
},
  "geometry": {"coordinates":[-112.704574585,52.3274154663],"type":"Point"}
}