{
  "type": "Feature",
  "properties": {
    "iso:country":"CA",
    "sg:address":"2220 Ch Saint-Roch",
    "sg:city":"Sorel-Tracy",
    "sg:classifiers":[
        {
            "category":"Professional",
            "subcategory":"Business Services",
            "type":"Services"
        }
    ],
    "sg:phone":"+1 450 742 2739",
    "sg:postcode":"J3R 3L2",
    "sg:province":"QC",
    "sg:tags":[
        "water",
        "company",
        "treatment"
    ],
    "wof:name":"Eau DE Source Naturelle",
    "wof:placetype":"venue"
},
  "geometry": {"coordinates":[-73.13042449949999,46.0336761475],"type":"Point"}
}