{
  "type": "Feature",
  "properties": {
    "addr:full":"Quebec QC G1S 1C1",
    "addr:postcode":"g1s 1c1",
    "iso:country":"CA",
    "sg:city":"Quebec",
    "sg:classifiers":[
        {
            "category":"Professional",
            "subcategory":"Research",
            "type":"Services"
        }
    ],
    "sg:phone":"+1 418 647 1122",
    "sg:postcode":"G1S 1C1",
    "sg:province":"QC",
    "sg:tags":[
        "market",
        "analysis"
    ],
    "wof:name":"Impact Recherche",
    "wof:placetype":"venue"
},
  "geometry": {"coordinates":[-71.3399963379,46.7499885559],"type":"Point"}
}