{
  "type": "Feature",
  "properties": {
    "iso:country":"CA",
    "sg:address":"897 Stremel Rd",
    "sg:city":"Kelowna",
    "sg:classifiers":[
        {
            "category":"Freight",
            "type":"Transportation"
        }
    ],
    "sg:phone":"+1 250 765 7779",
    "sg:postcode":"V1X 5E6",
    "sg:province":"BC",
    "sg:tags":[
        "mover"
    ],
    "wof:name":"British Columbia Trailer",
    "wof:placetype":"venue"
},
  "geometry": {"coordinates":[-119.402222,49.904793],"type":"Point"}
}