{
  "type": "Feature",
  "properties": {
    "addr:full":"897 Stremel Rd Kelowna BC V1X 5E6",
    "addr:housenumber":"897",
    "addr:postcode":"v1x 5e6",
    "addr:street":"Stremel Rd",
    "iso:country":"CA",
    "sg:address":"897 Stremel Rd",
    "sg:city":"Kelowna",
    "sg:classifiers":[
        {
            "category":"Freight",
            "type":"Transportation"
        }
    ],
    "sg:phone":"+1 250 765 7779",
    "sg:postcode":"V1X 5E6",
    "sg:province":"BC",
    "sg:tags":[
        "mover"
    ],
    "wof:name":"British Columbia Trailer",
    "wof:placetype":"venue"
},
  "geometry": {"coordinates":[-119.40222199999999,49.904793],"type":"Point"}
}