{
  "type": "Feature",
  "properties": {
    "iso:country":"CA",
    "sg:address":"3690 Walker Rd",
    "sg:city":"Windsor",
    "sg:classifiers":[
        {
            "category":"Wholesale",
            "subcategory":"Auto Parts",
            "type":"Manufacturing & Wholesale Goods"
        }
    ],
    "sg:phone":"+1 519 966 3090",
    "sg:postcode":"N8W 3S7",
    "sg:province":"ON",
    "sg:tags":[
        "automobile",
        "rebuilt",
        "supply"
    ],
    "wof:name":"Bray's Automotive",
    "wof:placetype":"venue"
},
  "geometry": {"coordinates":[-82.9736709595,42.2702445984],"type":"Point"}
}