{
  "type": "Feature",
  "properties": {
    "addr:full":"1561 Polesden Dr Mississauga ON L5G 4S9",
    "addr:housenumber":"1561",
    "addr:postcode":"l5g 4s9",
    "addr:street":"Polesden Dr",
    "iso:country":"CA",
    "sg:address":"1561 Polesden Dr",
    "sg:city":"Mississauga",
    "sg:classifiers":[
        {
            "category":"Building & Trades",
            "subcategory":"Construction",
            "type":"Services"
        }
    ],
    "sg:phone":"+1 905 278 0641",
    "sg:postcode":"L5G 4S9",
    "sg:province":"ON",
    "sg:tags":[
        "painter"
    ],
    "wof:name":"Mississauga Painting Svc",
    "wof:placetype":"venue"
},
  "geometry": {"coordinates":[-79.596497,43.565277],"type":"Point"}
}