{
  "type": "Feature",
  "properties": {
    "addr:full":"1110 Yonge St Toronto ON M4W 2L6",
    "addr:housenumber":"1110",
    "addr:postcode":"m4w 2l6",
    "addr:street":"Yonge St",
    "iso:country":"CA",
    "sg:address":"1110 Yonge St",
    "sg:city":"Toronto",
    "sg:classifiers":[
        {
            "category":"Home & Garden",
            "subcategory":"Furniture",
            "type":"Retail Goods"
        }
    ],
    "sg:phone":"+1 416 929 1177",
    "sg:postcode":"M4W 2L6",
    "sg:province":"ON",
    "wof:name":"Constantine Interiors Inc",
    "wof:placetype":"venue"
},
  "geometry": {"coordinates":[-79.390396,43.678665],"type":"Point"}
}