{
  "type": "Feature",
  "properties": {
    "addr:full":"Sainte-Foy QC G1N 4N6",
    "addr:postcode":"g1n 4n6",
    "iso:country":"CA",
    "sg:city":"Sainte-Foy",
    "sg:classifiers":[
        {
            "category":"Real Estate",
            "subcategory":"Real Estate Agent",
            "type":"Services"
        }
    ],
    "sg:phone":"+1 418 682 0241",
    "sg:postcode":"G1N 4N6",
    "sg:province":"QC",
    "sg:tags":[
        "desk",
        "space"
    ],
    "wof:name":"Carrefour DE L'Entrepreneur",
    "wof:placetype":"venue"
},
  "geometry": {"coordinates":[-71.2708740234,46.7961273193],"type":"Point"}
}