{
  "type": "Feature",
  "properties": {
    "addr:full":"375 Mcgregor Side Rd Sarnia ON N7T 7H5",
    "addr:housenumber":"375",
    "addr:postcode":"n7t 7h5",
    "addr:street":"Mcgregor Side Rd",
    "iso:country":"CA",
    "sg:address":"375 Mcgregor Side Rd",
    "sg:city":"Sarnia",
    "sg:classifiers":[
        {
            "category":"Freight",
            "type":"Transportation"
        }
    ],
    "sg:phone":"+1 519 336 9854",
    "sg:postcode":"N7T 7H5",
    "sg:province":"ON",
    "sg:tags":[
        "trucking"
    ],
    "wof:name":"Brian Pite Freight",
    "wof:placetype":"venue"
},
  "geometry": {"coordinates":[-82.4033660889,42.9787712097],"type":"Point"}
}