{
  "type": "Feature",
  "properties": {
    "iso:country":"CA",
    "sg:city":"White Rock",
    "sg:classifiers":[
        {
            "category":"Building & Trades",
            "subcategory":"Landscaping Services",
            "type":"Services"
        }
    ],
    "sg:phone":"+1 604 531 1783",
    "sg:postcode":"V4B 3Z5",
    "sg:province":"BC",
    "sg:tags":[
        "landscape",
        "contractor"
    ],
    "wof:name":"AAA Lawn & Garden Ltd",
    "wof:placetype":"venue"
},
  "geometry": {"coordinates":[-122.800956726,49.0284156799],"type":"Point"}
}