{
  "type": "Feature",
  "properties": {
    "addr:full":"60 Robertson Rd Nepean ON K2H 5Y8",
    "addr:housenumber":"60",
    "addr:postcode":"k2h 5y8",
    "addr:street":"Robertson Rd",
    "iso:country":"CA",
    "sg:address":"60 Robertson Rd",
    "sg:city":"Nepean",
    "sg:classifiers":[
        {
            "category":"Retail",
            "subcategory":"Auto Repair",
            "type":"Services"
        }
    ],
    "sg:phone":"+1 613 829 7980",
    "sg:postcode":"K2H 5Y8",
    "sg:province":"ON",
    "sg:tags":[
        "repairing",
        "automobile"
    ],
    "wof:name":"Midas Auto Svc Experts",
    "wof:placetype":"venue"
},
  "geometry": {"coordinates":[-75.830909729,45.322883606],"type":"Point"}
}