{
  "type": "Feature",
  "properties": {
    "addr:full":"155 Henri Dunant St Moncton NB E1E 1E4",
    "addr:housenumber":"155",
    "addr:postcode":"e1e 1e4",
    "addr:street":"Henri Dunant St",
    "iso:country":"CA",
    "sg:address":"155 Henri Dunant St",
    "sg:city":"Moncton",
    "sg:classifiers":[
        {
            "category":"Manufacturing",
            "subcategory":"Rubber & Plastics",
            "type":"Manufacturing & Wholesale Goods"
        }
    ],
    "sg:phone":"+1 506 857 0004",
    "sg:postcode":"E1E 1E4",
    "sg:province":"NB",
    "sg:tags":[
        "product"
    ],
    "wof:name":"Laird Plastics Inc",
    "wof:placetype":"venue"
},
  "geometry": {"coordinates":[-64.8276748657,46.0786056519],"type":"Point"}
}