{
  "type": "Feature",
  "properties": {
    "iso:country":"CA",
    "sg:address":"341 Centre St",
    "sg:city":"Shaunavon",
    "sg:classifiers":[
        {
            "category":"Restaurant",
            "type":"Food & Drink"
        }
    ],
    "sg:phone":"+1 306 297 2654",
    "sg:postcode":"S0N 2M0",
    "sg:province":"SK",
    "wof:name":"Shaunee Restaurant",
    "wof:placetype":"venue"
},
  "geometry": {"coordinates":[-108.408607483,49.6470451355],"type":"Point"}
}