{
  "type": "Feature",
  "properties": {
    "addr:full":"Toronto ON M6K 1A5",
    "addr:postcode":"m6k 1a5",
    "iso:country":"CA",
    "sg:city":"Toronto",
    "sg:classifiers":[
        {
            "category":"Building & Trades",
            "subcategory":"Equipment Rental",
            "type":"Services"
        }
    ],
    "sg:phone":"+1 416 516 2373",
    "sg:postcode":"M6K 1A5",
    "sg:province":"ON",
    "sg:tags":[
        "audio",
        "leasing"
    ],
    "wof:name":"Staging Connection",
    "wof:placetype":"venue"
},
  "geometry": {"coordinates":[-79.42037999999999,43.638458],"type":"Point"}
}