{
  "type": "Feature",
  "properties": {
    "addr:full":"268 Ox Cart Trail E Oak Lake MB R0M 1P0",
    "addr:housenumber":"268",
    "addr:postcode":"r0m 1p0",
    "addr:street":"Ox Cart Trail E Oak",
    "iso:country":"CA",
    "sg:address":"268 Ox Cart Trail E",
    "sg:city":"Oak Lake",
    "sg:classifiers":[
        {
            "category":"Wholesale",
            "subcategory":"Farm Supplies",
            "type":"Manufacturing & Wholesale Goods"
        }
    ],
    "sg:phone":"+1 204 855 2982",
    "sg:postcode":"R0M 1P0",
    "sg:province":"MB",
    "sg:tags":[
        "cattle"
    ],
    "wof:name":"Morcombe Holdings Ltd",
    "wof:placetype":"venue"
},
  "geometry": {"coordinates":[-100.633865,49.76627],"type":"Point"}
}