{
  "type": "Feature",
  "properties": {
    "addr:full":"Coquitlam BC V3B 6S2",
    "addr:postcode":"v3b 6s2",
    "iso:country":"CA",
    "sg:city":"Coquitlam",
    "sg:classifiers":[
        {
            "category":"Restaurant",
            "type":"Food & Drink"
        }
    ],
    "sg:phone":"+1 604 941 3877",
    "sg:postcode":"V3B 6S2",
    "sg:province":"BC",
    "wof:name":"Nagasaki-Ya Japanese Rstrnt",
    "wof:placetype":"venue"
},
  "geometry": {"coordinates":[-122.792243958,49.274433136],"type":"Point"}
}