{
  "type": "Feature",
  "properties": {
    "addr:full":"516 Glengrove Ave North York ON M6B 2H2",
    "addr:housenumber":"516",
    "addr:postcode":"m6b 2h2",
    "addr:street":"Glengrove Ave",
    "iso:country":"CA",
    "sg:address":"516 Glengrove Ave",
    "sg:city":"North York",
    "sg:classifiers":[
        {
            "category":"Professional",
            "subcategory":"Business Services",
            "type":"Services"
        }
    ],
    "sg:phone":"+1 416 787 9700",
    "sg:postcode":"M6B 2H2",
    "sg:province":"ON",
    "sg:tags":[
        "arbitration"
    ],
    "wof:name":"Mester, Fiore",
    "wof:placetype":"venue"
},
  "geometry": {"coordinates":[-79.42994689939999,43.7139587402],"type":"Point"}
}