{
  "type": "Feature",
  "properties": {
    "addr:full":"Ajax ON L1S 6V4",
    "addr:postcode":"l1s 6v4",
    "iso:country":"CA",
    "sg:city":"Ajax",
    "sg:classifiers":[
        {
            "category":"Retail",
            "subcategory":"Laundry & Dry Cleaning",
            "type":"Services"
        }
    ],
    "sg:phone":"+1 905 683 7900",
    "sg:postcode":"L1S 6V4",
    "sg:province":"ON",
    "sg:tags":[
        "cleaners"
    ],
    "wof:name":"Cadet Cleaners",
    "wof:placetype":"venue"
},
  "geometry": {"coordinates":[-79.0320053101,43.8302154541],"type":"Point"}
}