{
  "type": "Feature",
  "properties": {
    "addr:full":"Vancouver BC V6H 1A6",
    "addr:postcode":"v6h 1a6",
    "iso:country":"CA",
    "sg:city":"Vancouver",
    "sg:classifiers":[
        {
            "category":"Food & Beverages",
            "subcategory":"Specialty",
            "type":"Retail Goods"
        }
    ],
    "sg:phone":"+1 604 736 0330",
    "sg:postcode":"V6H 1A6",
    "sg:province":"BC",
    "sg:tags":[
        "salt"
    ],
    "wof:name":"Magnesium Interface Inc",
    "wof:placetype":"venue"
},
  "geometry": {"coordinates":[-123.13305699999999,49.266327],"type":"Point"}
}