{
  "type": "Feature",
  "properties": {
    "addr:full":"Yorkton SK S3N 3G7",
    "addr:postcode":"s3n 3g7",
    "iso:country":"CA",
    "sg:city":"Yorkton",
    "sg:classifiers":[
        {
            "category":"Shopping",
            "subcategory":"Clothing, Apparel, & Fashions",
            "type":"Retail Goods"
        }
    ],
    "sg:phone":"+1 306 782 3151",
    "sg:postcode":"S3N 3G7",
    "sg:province":"SK",
    "wof:name":"Mariposa Stores Ltd",
    "wof:placetype":"venue"
},
  "geometry": {"coordinates":[-102.445808,51.210457],"type":"Point"}
}