{
  "type": "Feature",
  "properties": {
    "addr:full":"495 Walkers Line Burlington ON L7N 2E3",
    "addr:housenumber":"495",
    "addr:postcode":"l7n 2e3",
    "addr:street":"Walkers Line",
    "iso:country":"CA",
    "sg:address":"495 Walkers Line",
    "sg:city":"Burlington",
    "sg:classifiers":[
        {
            "category":"Personal",
            "subcategory":"Beauty Salon",
            "type":"Services"
        }
    ],
    "sg:phone":"+1 905 632 4222",
    "sg:postcode":"L7N 2E3",
    "sg:province":"ON",
    "wof:name":"A'Marylis Studio",
    "wof:placetype":"venue"
},
  "geometry": {"coordinates":[-79.8197860718,43.3938217163],"type":"Point"}
}