{
  "type": "Feature",
  "properties": {
    "addr:full":"201 Rue Notre-Dame Repentigny QC J6A 2R3",
    "addr:housenumber":"201",
    "addr:postcode":"j6a 2r3",
    "addr:street":"Rue Notre-Dame",
    "iso:country":"CA",
    "sg:address":"201 Rue Notre-Dame",
    "sg:city":"Repentigny",
    "sg:classifiers":[
        {
            "category":"Manufacturing",
            "subcategory":"Wood Products",
            "type":"Manufacturing & Wholesale Goods"
        }
    ],
    "sg:phone":"+1 450 581 0011",
    "sg:postcode":"J6A 2R3",
    "sg:province":"QC",
    "sg:tags":[
        "picture",
        "frame"
    ],
    "wof:name":"Encadrement LA Vieille Maison",
    "wof:placetype":"venue"
},
  "geometry": {"coordinates":[-73.46546936039999,45.7203826904],"type":"Point"}
}