{
  "type": "Feature",
  "properties": {
    "addr:full":"5661 Ch Saint-Francois Saint-Laurent QC H4S 1W6",
    "addr:postcode":"5661;h4s 1w6",
    "addr:street":"Ch Saint-Francois",
    "iso:country":"CA",
    "sg:address":"5661 Ch Saint-Francois",
    "sg:city":"Saint-Laurent",
    "sg:classifiers":[
        {
            "category":"Wholesale",
            "subcategory":"Electrical",
            "type":"Manufacturing & Wholesale Goods"
        }
    ],
    "sg:phone":"+1 514 335 2335",
    "sg:postcode":"H4S 1W6",
    "sg:province":"QC",
    "sg:tags":[
        "equipment",
        "electronic",
        "supply"
    ],
    "wof:name":"R F Microwave Ltd",
    "wof:placetype":"venue"
},
  "geometry": {"coordinates":[-73.73745,45.48785],"type":"Point"}
}