{
  "type": "Feature",
  "properties": {
    "addr:full":"34 Rue Saint-Joseph Bedford QC J0J 1A0",
    "addr:housenumber":"34",
    "addr:postcode":"j0j 1a0",
    "addr:street":"Rue Saint-Joseph",
    "iso:country":"CA",
    "sg:address":"34 Rue Saint-Joseph",
    "sg:city":"Bedford",
    "sg:classifiers":[
        {
            "category":"Health Services",
            "subcategory":"Health Practitioner",
            "type":"Services"
        }
    ],
    "sg:phone":"+1 450 248 7487",
    "sg:postcode":"J0J 1A0",
    "sg:province":"QC",
    "sg:tags":[
        "physiotherapist"
    ],
    "wof:name":"Clinique DE Physiotherapie DE",
    "wof:placetype":"venue"
},
  "geometry": {"coordinates":[-72.98281900000001,45.125477],"type":"Point"}
}