{
  "type": "Feature",
  "properties": {
    "iso:country":"CA",
    "sg:address":"23022 Pth 44",
    "sg:city":"Lockport",
    "sg:classifiers":[
        {
            "category":"Restaurant",
            "type":"Food & Drink"
        }
    ],
    "sg:phone":"+1 204 757 2704",
    "sg:postcode":"R1B 1A1",
    "sg:province":"MB",
    "wof:name":"A & W Family Restaurant",
    "wof:placetype":"venue"
},
  "geometry": {"coordinates":[-96.95495605470001,50.089389801],"type":"Point"}
}