{
  "type": "Feature",
  "properties": {
    "addr:full":"Golden Valley ON P0H 1N0",
    "addr:postcode":"p0h 1n0",
    "iso:country":"CA",
    "sg:city":"Golden Valley",
    "sg:classifiers":[
        {
            "category":"Travel",
            "subcategory":"Hotels & Motels",
            "type":"Entertainment"
        }
    ],
    "sg:phone":"+1 705 757 5432",
    "sg:postcode":"P0H 1N0",
    "sg:province":"ON",
    "sg:tags":[
        "resort"
    ],
    "wof:name":"Falcon's Lair",
    "wof:placetype":"venue"
},
  "geometry": {"coordinates":[-79.78504180909999,45.9285087585],"type":"Point"}
}