{
  "type": "Feature",
  "properties": {
    "addr:full":"3349 Lovett Rd Kentville NS B4N 3V7",
    "addr:housenumber":"3349",
    "addr:postcode":"b4n 3v7",
    "addr:street":"Lovett Rd",
    "iso:country":"CA",
    "sg:address":"3349 Lovett Rd",
    "sg:city":"Kentville",
    "sg:classifiers":[
        {
            "category":"Retail",
            "subcategory":"Animal Services",
            "type":"Services"
        }
    ],
    "sg:phone":"+1 902 678 3183",
    "sg:postcode":"B4N 3V7",
    "sg:province":"NS",
    "sg:tags":[
        "pet",
        "boarding",
        "sitting"
    ],
    "wof:name":"Happy Valley Boarding Kennels",
    "wof:placetype":"venue"
},
  "geometry": {"coordinates":[-64.49443817140001,45.0769195557],"type":"Point"}
}