{
  "type": "Feature",
  "properties": {
    "addr:full":"1970 Rue Notre-Dame L'Ancienne-Lorette QC G2E 3E3",
    "addr:housenumber":"1970",
    "addr:postcode":"g2e 3e3",
    "addr:street":"Rue Notre-Dame",
    "iso:country":"CA",
    "sg:address":"1970 Rue Notre-Dame",
    "sg:city":"L'Ancienne-Lorette",
    "sg:classifiers":[
        {
            "category":"Shopping",
            "subcategory":"Jewelry",
            "type":"Retail Goods"
        }
    ],
    "sg:phone":"+1 418 872 8472",
    "sg:postcode":"G2E 3E3",
    "sg:province":"QC",
    "sg:tags":[
        "jeweler"
    ],
    "wof:name":"Bijouterie Mode L'Or Inc",
    "wof:placetype":"venue"
},
  "geometry": {"coordinates":[-71.37117000000001,46.811672],"type":"Point"}
}