{
  "type": "Feature",
  "properties": {
    "addr:full":"292 Rg 3 S Saint-Victor QC G0M 2B0",
    "addr:housenumber":"292;3",
    "addr:postcode":"g0m 2b0",
    "addr:street":"Rg;S",
    "iso:country":"CA",
    "sg:address":"292 Rg 3 S",
    "sg:city":"Saint-Victor",
    "sg:classifiers":[
        {
            "category":"Manufacturing",
            "subcategory":"Food",
            "type":"Manufacturing & Wholesale Goods"
        }
    ],
    "sg:phone":"+1 418 588 3315",
    "sg:postcode":"G0M 2B0",
    "sg:province":"QC",
    "sg:tags":[
        "syrup",
        "maple",
        "sugar"
    ],
    "wof:name":"Produits DE L'Erable Bolduc",
    "wof:placetype":"venue"
},
  "geometry": {"coordinates":[-70.906189,46.146645],"type":"Point"}
}