{
  "type": "Feature",
  "properties": {
    "iso:country":"CA",
    "sg:city":"Castor",
    "sg:classifiers":[
        {
            "category":"Food & Beverages",
            "subcategory":"Groceries & Convenience Stores",
            "type":"Retail Goods"
        }
    ],
    "sg:phone":"+1 403 882 3031",
    "sg:postcode":"T0C 0X0",
    "sg:province":"AB",
    "sg:tags":[
        "grocer"
    ],
    "wof:name":"Food Town",
    "wof:placetype":"venue"
},
  "geometry": {"coordinates":[-111.90511322,52.2191200256],"type":"Point"}
}