{
  "type": "Feature",
  "properties": {
    "addr:full":"115 Commander Blvd Scarborough ON M1S 3M7",
    "addr:housenumber":"115",
    "addr:postcode":"m1s 3m7",
    "addr:street":"Commander Blvd",
    "iso:country":"CA",
    "sg:address":"115 Commander Blvd",
    "sg:city":"Scarborough",
    "sg:classifiers":[
        {
            "category":"Manufacturing",
            "subcategory":"Food",
            "type":"Manufacturing & Wholesale Goods"
        }
    ],
    "sg:phone":"+1 416 291 3226",
    "sg:postcode":"M1S 3M7",
    "sg:province":"ON",
    "sg:tags":[
        "product",
        "health"
    ],
    "wof:name":"Grain Process Enterprises Ltd",
    "wof:placetype":"venue"
},
  "geometry": {"coordinates":[-79.2664031982,43.7934837341],"type":"Point"}
}