{
  "type": "Feature",
  "properties": {
    "iso:country":"CA",
    "sg:address":"551 Richmond St",
    "sg:city":"London",
    "sg:classifiers":[
        {
            "category":"Cinema",
            "subcategory":"Movie Rental",
            "type":"Entertainment"
        }
    ],
    "sg:phone":"+1 519 439 3549",
    "sg:postcode":"N6A 3E9",
    "sg:province":"ON",
    "sg:tags":[
        "leasing",
        "video",
        "disc",
        "tape"
    ],
    "wof:name":"Flixx Movie Store",
    "wof:placetype":"venue"
},
  "geometry": {"coordinates":[-81.250755,42.988579],"type":"Point"}
}