{
  "type": "Feature",
  "properties": {
    "addr:full":"390 Richmond St London ON N6A 3C7",
    "addr:housenumber":"390",
    "addr:postcode":"n6a 3c7",
    "addr:street":"Richmond St",
    "iso:country":"CA",
    "sg:address":"390 Richmond St",
    "sg:city":"London",
    "sg:classifiers":[
        {
            "category":"Restaurant",
            "type":"Food & Drink"
        }
    ],
    "sg:phone":"+1 519 434 9268",
    "sg:postcode":"N6A 3C7",
    "sg:province":"ON",
    "wof:name":"Jewel of India Restaurant Inc",
    "wof:placetype":"venue"
},
  "geometry": {"coordinates":[-81.249168,42.983093],"type":"Point"}
}