{
  "type": "Feature",
  "properties": {
    "addr:full":"205 Boul DE L'Ange-Gardien L'Assomption QC J5W 1R6",
    "addr:housenumber":"205",
    "addr:postcode":"j5w 1r6",
    "addr:street":"Boul De L'Ange-Gardien",
    "iso:country":"CA",
    "sg:address":"205 Boul DE L'Ange-Gardien",
    "sg:city":"L'Assomption",
    "sg:classifiers":[
        {
            "category":"Manufacturing",
            "subcategory":"Printing",
            "type":"Manufacturing & Wholesale Goods"
        }
    ],
    "sg:phone":"+1 450 589 2941",
    "sg:postcode":"J5W 1R6",
    "sg:province":"QC",
    "sg:tags":[
        "printer"
    ],
    "wof:name":"Imprimerie Litho Lanaudiere",
    "wof:placetype":"venue"
},
  "geometry": {"coordinates":[-73.4175872803,45.8330383301],"type":"Point"}
}