{
  "type": "Feature",
  "properties": {
    "iso:country":"CA",
    "sg:address":"1358 Rue DE Dolbeau",
    "sg:city":"Gatineau",
    "sg:classifiers":[
        {
            "category":"Manufacturing",
            "subcategory":"Buildings",
            "type":"Manufacturing & Wholesale Goods"
        }
    ],
    "sg:phone":"+1 819 663 6265",
    "sg:postcode":"J8R 2V1",
    "sg:province":"QC",
    "sg:tags":[
        "home",
        "log",
        "cabin"
    ],
    "wof:name":"Structures En Bois Massif",
    "wof:placetype":"venue"
},
  "geometry": {"coordinates":[-75.6368484497,45.5283508301],"type":"Point"}
}