{
  "type": "Feature",
  "properties": {
    "addr:full":"571 Bronson Ave Ottawa ON K1R 6K2",
    "addr:housenumber":"571",
    "addr:postcode":"k1r 6k2",
    "addr:street":"Bronson Ave",
    "iso:country":"CA",
    "sg:address":"571 Bronson Ave",
    "sg:city":"Ottawa",
    "sg:classifiers":[
        {
            "category":"Retail",
            "subcategory":"Laundry & Dry Cleaning",
            "type":"Services"
        }
    ],
    "sg:phone":"+1 613 235 1497",
    "sg:postcode":"K1R 6K2",
    "sg:province":"ON",
    "sg:tags":[
        "cleaners"
    ],
    "wof:name":"Modern Dry Cleaners",
    "wof:placetype":"venue"
},
  "geometry": {"coordinates":[-75.702164,45.405647],"type":"Point"}
}