{
  "type": "Feature",
  "properties": {
    "addr:full":"390 Aquaduct Dr Brooks AB T1R 1B9",
    "addr:housenumber":"390",
    "addr:postcode":"t1r 1b9",
    "addr:street":"Aquaduct Dr",
    "iso:country":"CA",
    "sg:address":"390 Aquaduct Dr",
    "sg:city":"Brooks",
    "sg:classifiers":[
        {
            "category":"Mining & Drilling",
            "type":"Manufacturing & Wholesale Goods"
        }
    ],
    "sg:phone":"+1 403 362 5050",
    "sg:postcode":"T1R 1B9",
    "sg:province":"AB",
    "sg:tags":[
        "field",
        "oil"
    ],
    "wof:name":"Trican Well Svc Ltd",
    "wof:placetype":"venue"
},
  "geometry": {"coordinates":[-111.889641,50.554512],"type":"Point"}
}