{
  "type": "Feature",
  "properties": {
    "addr:full":"1121 Hwy 4 Cadillac SK S0N 0K0",
    "addr:housenumber":"1121",
    "addr:postcode":"s0n 0k0",
    "addr:street":"Hwy 4",
    "iso:country":"CA",
    "sg:address":"1121 Hwy 4",
    "sg:city":"Cadillac",
    "sg:classifiers":[
        {
            "category":"Autos & Motor Vehicles",
            "subcategory":"Fuel & Gas Station",
            "type":"Retail Goods"
        }
    ],
    "sg:phone":"+1 306 785 2222",
    "sg:postcode":"S0N 0K0",
    "sg:province":"SK",
    "sg:tags":[
        "oil"
    ],
    "wof:name":"Lacelle Brothers",
    "wof:placetype":"venue"
},
  "geometry": {"coordinates":[-107.74369799999999,49.723942],"type":"Point"}
}