{
  "type": "Feature",
  "properties": {
    "addr:full":"Coquitlam BC V3K 1R1",
    "addr:postcode":"v3k 1r1",
    "iso:country":"CA",
    "sg:city":"Coquitlam",
    "sg:classifiers":[
        {
            "category":"Government",
            "subcategory":"Office",
            "type":"Public Place"
        }
    ],
    "sg:phone":"+1 604 527 1200",
    "sg:postcode":"V3K 1R1",
    "sg:province":"BC",
    "wof:name":"BC Prevention Compliance",
    "wof:placetype":"venue"
},
  "geometry": {"coordinates":[-122.872459412,49.2378311157],"type":"Point"}
}