{
  "type": "Feature",
  "properties": {
    "addr:full":"Merritt BC V1K 1B8",
    "addr:postcode":"v1k 1b8",
    "iso:country":"CA",
    "sg:city":"Merritt",
    "sg:classifiers":[
        {
            "category":"Restaurant",
            "type":"Food & Drink"
        }
    ],
    "sg:phone":"+1 250 315 0007",
    "sg:postcode":"V1K 1B8",
    "sg:province":"BC",
    "sg:tags":[
        "shop",
        "coffee"
    ],
    "wof:name":"Mandolin's Bagel & Coffeehouse",
    "wof:placetype":"venue"
},
  "geometry": {"coordinates":[-120.788818359,50.1073684692],"type":"Point"}
}