{
  "type": "Feature",
  "properties": {
    "addr:full":"Lorrainville QC J0Z 2R0",
    "addr:postcode":"j0z 2r0",
    "iso:country":"CA",
    "sg:city":"Lorrainville",
    "sg:classifiers":[
        {
            "category":"Travel",
            "subcategory":"Travel Agent",
            "type":"Entertainment"
        }
    ],
    "sg:phone":"+1 819 625 2096",
    "sg:postcode":"J0Z 2R0",
    "sg:province":"QC",
    "sg:tags":[
        "agency",
        "bureau"
    ],
    "wof:name":"Voyage L'Eau Claire",
    "wof:placetype":"venue"
},
  "geometry": {"coordinates":[-79.353241,47.357063],"type":"Point"}
}