{
  "type": "Feature",
  "properties": {
    "iso:country":"CA",
    "sg:address":"5100 Rue DE LA Savane",
    "sg:city":"Montreal",
    "sg:classifiers":[
        {
            "category":"Wholesale",
            "subcategory":"Electrical",
            "type":"Manufacturing & Wholesale Goods"
        }
    ],
    "sg:phone":"+1 514 738 7385",
    "sg:postcode":"H4P 1T8",
    "sg:province":"QC",
    "sg:tags":[
        "equipment",
        "electronic",
        "supply"
    ],
    "wof:name":"F M Electroniques",
    "wof:placetype":"venue"
},
  "geometry": {"coordinates":[-73.65696716310001,45.4995536804],"type":"Point"}
}