{
  "type": "Feature",
  "properties": {
    "addr:full":"PO Box 622 Sedgewick AB T0B 4C0",
    "addr:housenumber":"po",
    "addr:postcode":"t0b 4c0",
    "addr:street":"Box 622 Sedgewick",
    "iso:country":"CA",
    "sg:address":"PO Box 622",
    "sg:city":"Sedgewick",
    "sg:classifiers":[
        {
            "category":"Mining & Drilling",
            "type":"Manufacturing & Wholesale Goods"
        }
    ],
    "sg:phone":"+1 780 384 2479",
    "sg:postcode":"T0B 4C0",
    "sg:province":"AB",
    "sg:tags":[
        "field",
        "oil",
        "septic"
    ],
    "wof:name":"Allan's Vacuum Truck Svc",
    "wof:placetype":"venue"
},
  "geometry": {"coordinates":[-111.69705999999999,52.776264],"type":"Point"}
}