{
  "type": "Feature",
  "properties": {
    "addr:full":"1900 Dixie Rd Pickering ON L1V 6M4",
    "addr:housenumber":"1900",
    "addr:postcode":"l1v 6m4",
    "addr:street":"Dixie Rd",
    "iso:country":"CA",
    "sg:address":"1900 Dixie Rd",
    "sg:city":"Pickering",
    "sg:classifiers":[
        {
            "category":"Food & Beverages",
            "subcategory":"Bakery",
            "type":"Retail Goods"
        }
    ],
    "sg:phone":"+1 905 839 8644",
    "sg:postcode":"L1V 6M4",
    "sg:province":"ON",
    "sg:tags":[
        "doughnut"
    ],
    "wof:name":"Coffee Time Donuts",
    "wof:placetype":"venue"
},
  "geometry": {"coordinates":[-79.103843689,43.8409538269],"type":"Point"}
}