{
  "type": "Feature",
  "properties": {
    "addr:full":"2103 Princess Ave Brandon MB R7B 0H7",
    "addr:housenumber":"2103",
    "addr:postcode":"r7b 0h7",
    "addr:street":"Princess Ave",
    "iso:country":"CA",
    "sg:address":"2103 Princess Ave",
    "sg:city":"Brandon",
    "sg:classifiers":[
        {
            "category":"Personal",
            "subcategory":"Beauty Salon",
            "type":"Services"
        }
    ],
    "sg:phone":"+1 204 728 4800",
    "sg:postcode":"R7B 0H7",
    "sg:province":"MB",
    "wof:name":"Hairistocracy",
    "wof:placetype":"venue"
},
  "geometry": {"coordinates":[-99.96636199949999,49.8470191956],"type":"Point"}
}