{
  "type": "Feature",
  "properties": {
    "addr:full":"5282 Hinchinvrooke Rd Hartington ON K0H 1W0",
    "addr:housenumber":"5282",
    "addr:postcode":"k0h 1w0",
    "addr:street":"Hinchinvrooke Rd",
    "iso:country":"CA",
    "sg:address":"5282 Hinchinvrooke Rd",
    "sg:city":"Hartington",
    "sg:classifiers":[
        {
            "category":"Government",
            "subcategory":"Police Station",
            "type":"Public Place"
        }
    ],
    "sg:phone":"+1 613 372 1932",
    "sg:postcode":"K0H 1W0",
    "sg:province":"ON",
    "sg:tags":[
        "department"
    ],
    "wof:name":"Frontenac Police Department",
    "wof:placetype":"venue"
},
  "geometry": {"coordinates":[-76.6686630249,44.4409065247],"type":"Point"}
}