{
  "type": "Feature",
  "properties": {
    "addr:full":"Heidelberg ON N0B 1Y0",
    "addr:postcode":"n0b 1y0",
    "iso:country":"CA",
    "sg:city":"Heidelberg",
    "sg:classifiers":[
        {
            "category":"Wholesale",
            "subcategory":"Construction Materials",
            "type":"Manufacturing & Wholesale Goods"
        }
    ],
    "sg:phone":"+1 519 699 4646",
    "sg:postcode":"N0B 1Y0",
    "sg:province":"ON",
    "sg:tags":[
        "sand",
        "gravel",
        "paving",
        "contractor"
    ],
    "wof:name":"Steed & Evans Ltd",
    "wof:placetype":"venue"
},
  "geometry": {"coordinates":[-80.621414,43.520626],"type":"Point"}
}