{
  "type": "Feature",
  "properties": {
    "addr:full":"420 Lock St W Dunnville ON N1A 1V6",
    "addr:housenumber":"420",
    "addr:postcode":"n1a 1v6",
    "addr:street":"Lock St W",
    "iso:country":"CA",
    "sg:address":"420 Lock St W",
    "sg:city":"Dunnville",
    "sg:classifiers":[
        {
            "category":"Health Services",
            "subcategory":"Doctor",
            "type":"Services"
        }
    ],
    "sg:phone":"+1 905 774 7541",
    "sg:postcode":"N1A 1V6",
    "sg:province":"ON",
    "sg:tags":[
        "physician",
        "clinic",
        "surgeon"
    ],
    "wof:name":"Medical Centre",
    "wof:placetype":"venue"
},
  "geometry": {"coordinates":[-79.625793,42.905022],"type":"Point"}
}