{
  "type": "Feature",
  "properties": {
    "addr:full":"5804 Highway 2A Lacombe AB T4L 2G5",
    "addr:housenumber":"5804",
    "addr:postcode":"t4l 2g5",
    "addr:street":"Highway 2A",
    "iso:country":"CA",
    "sg:address":"5804 Highway 2A",
    "sg:city":"Lacombe",
    "sg:classifiers":[
        {
            "category":"Retail",
            "subcategory":"Car Wash",
            "type":"Services"
        }
    ],
    "sg:phone":"+1 403 782 6074",
    "sg:postcode":"T4L 2G5",
    "sg:province":"AB",
    "sg:tags":[
        "polishing",
        "washing"
    ],
    "wof:name":"Lacombe Husky",
    "wof:placetype":"venue"
},
  "geometry": {"coordinates":[-113.7192,52.472294],"type":"Point"}
}