{
  "type": "Feature",
  "properties": {
    "addr:full":"979 Rue Longpre Mascouche QC J7K 2X6",
    "addr:housenumber":"979",
    "addr:postcode":"j7k 2x6",
    "addr:street":"Rue Longpre",
    "iso:country":"CA",
    "sg:address":"979 Rue Longpre",
    "sg:city":"Mascouche",
    "sg:classifiers":[
        {
            "category":"Building & Trades",
            "subcategory":"Construction",
            "type":"Services"
        }
    ],
    "sg:phone":"+1 514 996 2568",
    "sg:postcode":"J7K 2X6",
    "sg:province":"QC",
    "sg:tags":[
        "repairing",
        "remodeling",
        "contractor"
    ],
    "wof:name":"Construction Girard",
    "wof:placetype":"venue"
},
  "geometry": {"coordinates":[-73.596642,45.743744],"type":"Point"}
}