{
  "type": "Feature",
  "properties": {
    "addr:full":"517 Lorne Ave E Stratford ON N5A 6S4",
    "addr:housenumber":"517",
    "addr:postcode":"n5a 6s4",
    "addr:street":"Lorne Ave E",
    "iso:country":"CA",
    "sg:address":"517 Lorne Ave E",
    "sg:city":"Stratford",
    "sg:classifiers":[
        {
            "category":"Wholesale",
            "subcategory":"Hardware",
            "type":"Manufacturing & Wholesale Goods"
        }
    ],
    "sg:phone":"+1 519 273 2320",
    "sg:postcode":"N5A 6S4",
    "sg:province":"ON",
    "sg:tags":[
        "tool"
    ],
    "wof:name":"Keep Industrial Supply Ltd",
    "wof:placetype":"venue"
},
  "geometry": {"coordinates":[-80.976822,43.352863],"type":"Point"}
}