{
  "type": "Feature",
  "properties": {
    "addr:full":"4714 Rue Sainte-Catherine E Montreal QC H1V 1Z2",
    "addr:housenumber":"4714",
    "addr:postcode":"h1v 1z2",
    "addr:street":"Rue Sainte-Catherine E",
    "iso:country":"CA",
    "sg:address":"4714 Rue Sainte-Catherine E",
    "sg:city":"Montreal",
    "sg:classifiers":[
        {
            "category":"Health Services",
            "subcategory":"Nursing And Care Facility",
            "type":"Services"
        }
    ],
    "sg:phone":"+1 514 255 6789",
    "sg:postcode":"H1V 1Z2",
    "sg:province":"QC",
    "sg:tags":[
        "home",
        "retirement",
        "community"
    ],
    "wof:name":"Manoir Ste-Catherine",
    "wof:placetype":"venue"
},
  "geometry": {"coordinates":[-73.5312347412,45.5546379089],"type":"Point"}
}