{
  "type": "Feature",
  "properties": {
    "addr:full":"13939 104 Ave Surrey BC V3T 1X1",
    "addr:housenumber":"13939",
    "addr:postcode":"v3t 1x1",
    "addr:street":"104 Ave",
    "iso:country":"CA",
    "sg:address":"13939 104 Ave",
    "sg:city":"Surrey",
    "sg:classifiers":[
        {
            "category":"Travel",
            "subcategory":"Hotels & Motels",
            "type":"Entertainment"
        }
    ],
    "sg:phone":"+1 604 589 1033",
    "sg:postcode":"V3T 1X1",
    "sg:province":"BC",
    "wof:name":"Happy Holiday Inn",
    "wof:placetype":"venue"
},
  "geometry": {"coordinates":[-122.834205627,49.1914787292],"type":"Point"}
}