{
  "type": "Feature",
  "properties": {
    "addr:full":"101 Rue Principale Granby QC J2G 2T9",
    "addr:housenumber":"101",
    "addr:postcode":"j2g 2t9",
    "addr:street":"Rue Principale",
    "iso:country":"CA",
    "sg:address":"101 Rue Principale",
    "sg:city":"Granby",
    "sg:classifiers":[
        {
            "category":"Organizations",
            "subcategory":"Religious Organization",
            "type":"Services"
        }
    ],
    "sg:phone":"+1 450 372 1417",
    "sg:postcode":"J2G 2T9",
    "sg:province":"QC",
    "sg:tags":[
        "church"
    ],
    "wof:name":"United Church of Canada Granby",
    "wof:placetype":"venue"
},
  "geometry": {"coordinates":[-72.72328899999999,45.39872],"type":"Point"}
}