{
  "type": "Feature",
  "properties": {
    "addr:full":"6190 Kingsway Burnaby BC V5J 1H5",
    "addr:housenumber":"6190",
    "addr:postcode":"v5j 1h5",
    "addr:street":"Kingsway",
    "iso:country":"CA",
    "sg:address":"6190 Kingsway",
    "sg:city":"Burnaby",
    "sg:classifiers":[
        {
            "category":"Home & Garden",
            "subcategory":"Household Appliances",
            "type":"Retail Goods"
        }
    ],
    "sg:phone":"+1 604 437 1633",
    "sg:postcode":"V5J 1H5",
    "sg:province":"BC",
    "sg:tags":[
        "machine",
        "sewing"
    ],
    "wof:name":"Burnaby Sewing Ctr",
    "wof:placetype":"venue"
},
  "geometry": {"coordinates":[-122.973655701,49.2201919556],"type":"Point"}
}