{
  "type": "Feature",
  "properties": {
    "addr:full":"2770 Matheson Blvd E Mississauga ON L4W 4M5",
    "addr:housenumber":"2770",
    "addr:postcode":"l4w 4m5",
    "addr:street":"Matheson Blvd E",
    "iso:country":"CA",
    "sg:address":"2770 Matheson Blvd E",
    "sg:city":"Mississauga",
    "sg:classifiers":[
        {
            "category":"Professional",
            "subcategory":"Advertising",
            "type":"Services"
        }
    ],
    "sg:phone":"+1 905 238 3466",
    "sg:postcode":"L4W 4M5",
    "sg:province":"ON",
    "sg:tags":[
        "designer",
        "display",
        "producer"
    ],
    "wof:name":"Gorrie Marketing Svc",
    "wof:placetype":"venue"
},
  "geometry": {"coordinates":[-79.596985,43.66423],"type":"Point"}
}