{
  "type": "Feature",
  "properties": {
    "iso:country":"CA",
    "sg:address":"1175 Av Bernard",
    "sg:city":"Outremont",
    "sg:classifiers":[
        {
            "category":"Manufacturing",
            "subcategory":"Printing",
            "type":"Manufacturing & Wholesale Goods"
        }
    ],
    "sg:phone":"+1 514 276 0386",
    "sg:postcode":"H2V 1V5",
    "sg:province":"QC",
    "sg:tags":[
        "advertising",
        "guide"
    ],
    "wof:name":"Annuaire D'Outremont",
    "wof:placetype":"venue"
},
  "geometry": {"coordinates":[-73.608238,45.520916],"type":"Point"}
}