{
  "type": "Feature",
  "properties": {
    "iso:country":"CA",
    "sg:address":"44 Mitchell Ave",
    "sg:city":"Alliston",
    "sg:classifiers":[
        {
            "category":"Building & Trades",
            "subcategory":"Construction",
            "type":"Services"
        }
    ],
    "sg:phone":"+1 705 435 2331",
    "sg:postcode":"L9R 1C2",
    "sg:province":"ON",
    "sg:tags":[
        "water",
        "contractor",
        "well",
        "heating",
        "drilling"
    ],
    "wof:name":"Dontere Drilling",
    "wof:placetype":"venue"
},
  "geometry": {"coordinates":[-79.874207,44.146072],"type":"Point"}
}