{
  "type": "Feature",
  "properties": {
    "addr:full":"593 Ave L'Abbe-Bourg Chandler QC G0C 1K0",
    "addr:housenumber":"593",
    "addr:postcode":"g0c 1k0",
    "addr:street":"Ave L'Abbe-Bourg",
    "iso:country":"CA",
    "sg:address":"593 Ave L'Abbe-Bourg",
    "sg:city":"Chandler",
    "sg:classifiers":[
        {
            "category":"Personal",
            "subcategory":"Beauty Salon",
            "type":"Services"
        }
    ],
    "sg:phone":"+1 418 689 2750",
    "sg:postcode":"G0C 1K0",
    "sg:province":"QC",
    "wof:name":"Salon DE Coiffure-Unisexe",
    "wof:placetype":"venue"
},
  "geometry": {"coordinates":[-66.0778579712,48.1018486023],"type":"Point"}
}