{
  "type": "Feature",
  "properties": {
    "addr:full":"3009 New St Burlington ON L7R 1K3",
    "addr:housenumber":"3009",
    "addr:postcode":"l7r 1k3",
    "addr:street":"New St",
    "iso:country":"CA",
    "sg:address":"3009 New St",
    "sg:city":"Burlington",
    "sg:classifiers":[
        {
            "category":"Health Services",
            "subcategory":"Doctor",
            "type":"Services"
        }
    ],
    "sg:phone":"+1 905 681 0102",
    "sg:postcode":"L7R 1K3",
    "sg:province":"ON",
    "sg:tags":[
        "dentist"
    ],
    "wof:name":"Brooks, Stephen E DDS",
    "wof:placetype":"venue"
},
  "geometry": {"coordinates":[-79.7849349976,43.3388595581],"type":"Point"}
}