{
  "type": "Feature",
  "properties": {
    "addr:full":"440 Rue Saint-Georges Saint-Jerome QC J7Z 5B1",
    "addr:housenumber":"440",
    "addr:postcode":"j7z 5b1",
    "addr:street":"Rue Saint-Georges Saint-Jerome",
    "iso:country":"CA",
    "sg:address":"440 Rue Saint-Georges",
    "sg:city":"Saint-Jerome",
    "sg:classifiers":[
        {
            "category":"Shopping",
            "subcategory":"Bicycles & Sporting Goods",
            "type":"Retail Goods"
        }
    ],
    "sg:phone":"+1 450 438 5005",
    "sg:postcode":"J7Z 5B1",
    "sg:province":"QC",
    "wof:name":"Refuge Sport Plein Air",
    "wof:placetype":"venue"
},
  "geometry": {"coordinates":[-74.00253295900001,45.7796821594],"type":"Point"}
}