{
  "type": "Feature",
  "properties": {
    "addr:full":"Oka QC J0N 1E0",
    "addr:postcode":"j0n 1e0",
    "iso:country":"CA",
    "sg:city":"Oka",
    "sg:classifiers":[
        {
            "category":"Government",
            "subcategory":"Fire Station",
            "type":"Public Place"
        }
    ],
    "sg:phone":"+1 450 479 8383",
    "sg:postcode":"J0N 1E0",
    "sg:province":"QC",
    "sg:tags":[
        "department"
    ],
    "wof:name":"Oka Fire Dept",
    "wof:placetype":"venue"
},
  "geometry": {"coordinates":[-74.09142300000001,45.45969],"type":"Point"}
}