{
  "type": "Feature",
  "properties": {
    "addr:full":"115 Norfolk St Guelph ON N1H 4J7",
    "addr:housenumber":"115",
    "addr:postcode":"n1h 4j7",
    "addr:street":"Norfolk St",
    "iso:country":"CA",
    "sg:address":"115 Norfolk St",
    "sg:city":"Guelph",
    "sg:classifiers":[
        {
            "category":"Personal",
            "type":"Services"
        }
    ],
    "sg:phone":"+1 519 763 4363",
    "sg:postcode":"N1H 4J7",
    "sg:province":"ON",
    "sg:tags":[
        "therapist",
        "massage"
    ],
    "wof:name":"Norfolk Massage Therapy Ctr",
    "wof:placetype":"venue"
},
  "geometry": {"coordinates":[-80.2524795532,43.5459518433],"type":"Point"}
}