{
  "type": "Feature",
  "properties": {
    "addr:full":"Fond Du Lac Indian Reserve Fond Du Lac SK S0J 0W0",
    "addr:postcode":"s0j 0w0",
    "addr:street":"Du",
    "iso:country":"CA",
    "sg:address":"Fond Du Lac Indian Reserve",
    "sg:city":"Fond Du Lac",
    "sg:classifiers":[
        {
            "category":"Taxi",
            "type":"Transportation"
        }
    ],
    "sg:phone":"+1 306 686 2073",
    "sg:postcode":"S0J 0W0",
    "sg:province":"SK",
    "sg:tags":[
        "taxicab"
    ],
    "wof:name":"Trapper's Taxi",
    "wof:placetype":"venue"
},
  "geometry": {"coordinates":[-107.187569,59.327782],"type":"Point"}
}