{
  "type": "Feature",
  "properties": {
    "addr:full":"16 Mcintyre Ave St Catharines ON L2S 3W9",
    "addr:housenumber":"16",
    "addr:postcode":"l2s 3w9",
    "addr:street":"Mcintyre Ave",
    "iso:country":"CA",
    "sg:address":"16 Mcintyre Ave",
    "sg:city":"St Catharines",
    "sg:classifiers":[
        {
            "category":"Social Services",
            "type":"Services"
        }
    ],
    "sg:phone":"+1 905 684 5415",
    "sg:postcode":"L2S 3W9",
    "sg:province":"ON",
    "sg:tags":[
        "counselor",
        "marriage",
        "family"
    ],
    "wof:name":"Lucyk, J Robert",
    "wof:placetype":"venue"
},
  "geometry": {"coordinates":[-79.2678604126,43.1278152466],"type":"Point"}
}