{
  "type": "Feature",
  "properties": {
    "addr:full":"Brossard QC J4W 1V9",
    "addr:postcode":"j4w 1v9",
    "iso:country":"CA",
    "sg:city":"Brossard",
    "sg:classifiers":[
        {
            "category":"Real Estate",
            "subcategory":"Real Estate Operator",
            "type":"Services"
        }
    ],
    "sg:phone":"+1 450 672 7717",
    "sg:postcode":"J4W 1V9",
    "sg:province":"QC",
    "sg:tags":[
        "condominium"
    ],
    "wof:name":"Sentiers DE Brossard",
    "wof:placetype":"venue"
},
  "geometry": {"coordinates":[-73.488686,45.474503],"type":"Point"}
}