{
  "type": "Feature",
  "properties": {
    "iso:country":"CA",
    "sg:address":"1737 Richmond St",
    "sg:city":"London",
    "sg:classifiers":[
        {
            "category":"Shopping",
            "subcategory":"Hobbies, Toys, & Games",
            "type":"Retail Goods"
        }
    ],
    "sg:phone":"+1 519 661 2688",
    "sg:postcode":"N5X 3Y2",
    "sg:province":"ON",
    "sg:tags":[
        "craft",
        "supply"
    ],
    "wof:name":"Michaels Arts & Crafts",
    "wof:placetype":"venue"
},
  "geometry": {"coordinates":[-81.2833938599,43.0277328491],"type":"Point"}
}