{
  "type": "Feature",
  "properties": {
    "iso:country":"CA",
    "sg:address":"425 Banff Ave",
    "sg:city":"Banff",
    "sg:classifiers":[
        {
            "category":"Travel",
            "subcategory":"Hotels & Motels",
            "type":"Entertainment"
        }
    ],
    "sg:phone":"+1 403 762 4184",
    "sg:postcode":"T1L 1B6",
    "sg:province":"AB",
    "wof:name":"Red Carpet Inn",
    "wof:placetype":"venue"
},
  "geometry": {"coordinates":[-115.56671900000001,51.181984],"type":"Point"}
}