{
  "type": "Feature",
  "properties": {
    "addr:full":"Amqui QC G5J 2C7",
    "addr:postcode":"g5j 2c7",
    "iso:country":"CA",
    "sg:city":"Amqui",
    "sg:classifiers":[
        {
            "category":"Shopping",
            "subcategory":"Clothing, Apparel, & Fashions",
            "type":"Retail Goods"
        }
    ],
    "sg:phone":"+1 418 629 3000",
    "sg:postcode":"G5J 2C7",
    "sg:province":"QC",
    "wof:name":"Varietes Pour Elle",
    "wof:placetype":"venue"
},
  "geometry": {"coordinates":[-67.424988,48.464401],"type":"Point"}
}