{
  "type": "Feature",
  "properties": {
    "addr:full":"235 Dixon Rd # 21 Etobicoke ON M9P 2M5",
    "addr:housenumber":"235",
    "addr:postcode":"m9p 2m5",
    "addr:street":"Dixon Rd # 21",
    "iso:country":"CA",
    "sg:address":"235 Dixon Rd # 21",
    "sg:city":"Etobicoke",
    "sg:classifiers":[
        {
            "category":"Shopping",
            "subcategory":"Stationery & Office Supplies",
            "type":"Retail Goods"
        }
    ],
    "sg:phone":"+1 416 235 2571",
    "sg:postcode":"M9P 2M5",
    "sg:province":"ON",
    "sg:tags":[
        "shop",
        "gift"
    ],
    "wof:name":"Precious Thoughts",
    "wof:placetype":"venue"
},
  "geometry": {"coordinates":[-79.5440292358,43.6976165771],"type":"Point"}
}