{
  "type": "Feature",
  "properties": {
    "addr:full":"Guelph ON N1H 7K4",
    "addr:postcode":"n1h 7k4",
    "iso:country":"CA",
    "sg:city":"Guelph",
    "sg:classifiers":[
        {
            "category":"Restaurant",
            "type":"Food & Drink"
        }
    ],
    "sg:phone":"+1 519 836 1179",
    "sg:postcode":"N1H 7K4",
    "sg:province":"ON",
    "wof:name":"Ample Annie's Roadhouse",
    "wof:placetype":"venue"
},
  "geometry": {"coordinates":[-80.2847518921,43.5432853699],"type":"Point"}
}