{
  "type": "Feature",
  "properties": {
    "addr:full":"5669 Spring Garden Rd Halifax NS B3J 1G9",
    "addr:housenumber":"5669",
    "addr:postcode":"ns b3j 1g9",
    "addr:street":"Spring Garden Rd",
    "iso:country":"CA",
    "sg:address":"5669 Spring Garden Rd",
    "sg:city":"Halifax",
    "sg:classifiers":[
        {
            "category":"Restaurant",
            "type":"Food & Drink"
        }
    ],
    "sg:phone":"+1 902 429 6226",
    "sg:postcode":"B3J 1G9",
    "sg:province":"NS",
    "wof:name":"Subway Sandwiches & Salads",
    "wof:placetype":"venue"
},
  "geometry": {"coordinates":[-63.579109,44.642605],"type":"Point"}
}