{
  "type": "Feature",
  "properties": {
    "iso:country":"CA",
    "sg:address":"32 Cecil St",
    "sg:city":"St Catharines",
    "sg:classifiers":[
        {
            "category":"Arts & Performance",
            "subcategory":"Theater",
            "type":"Entertainment"
        }
    ],
    "sg:phone":"+1 905 646 0334",
    "sg:postcode":"L2N 4B2",
    "sg:province":"ON",
    "sg:tags":[
        "live",
        "music"
    ],
    "wof:name":"Dancemaster Disc Jockey",
    "wof:placetype":"venue"
},
  "geometry": {"coordinates":[-79.263634,43.183018],"type":"Point"}
}