{
  "type": "Feature",
  "properties": {
    "addr:full":"8134 134 St Surrey BC V3W 4T9",
    "addr:housenumber":"8134",
    "addr:postcode":"v3w 4t9",
    "addr:street":"134 St",
    "iso:country":"CA",
    "sg:address":"8134 134 St",
    "sg:city":"Surrey",
    "sg:classifiers":[
        {
            "category":"Freight",
            "type":"Transportation"
        }
    ],
    "sg:phone":"+1 604 599 8633",
    "sg:postcode":"V3W 4T9",
    "sg:province":"BC",
    "sg:tags":[
        "trucking"
    ],
    "wof:name":"Azur Transport Ltd",
    "wof:placetype":"venue"
},
  "geometry": {"coordinates":[-122.85105900000001,49.150642],"type":"Point"}
}