{
  "type": "Feature",
  "properties": {
    "addr:full":"135 Marlee Ave York ON M6B 4C6",
    "addr:housenumber":"135",
    "addr:postcode":"m6b 4c6",
    "addr:street":"Marlee Ave",
    "iso:country":"CA",
    "sg:address":"135 Marlee Ave",
    "sg:city":"York",
    "sg:classifiers":[
        {
            "category":"Banks & Credit Unions",
            "subcategory":"Investment Brokerage",
            "type":"Services"
        }
    ],
    "sg:phone":"+1 416 781 1883",
    "sg:postcode":"M6B 4C6",
    "sg:province":"ON",
    "sg:tags":[
        "consultant",
        "planning",
        "financial"
    ],
    "wof:name":"Wia Financial Strategy",
    "wof:placetype":"venue"
},
  "geometry": {"coordinates":[-79.441086,43.70224],"type":"Point"}
}