{
  "type": "Feature",
  "properties": {
    "addr:full":"Weyakwin Rd Weyakwin SK S0J 1W0",
    "addr:postcode":"s0j 1w0",
    "addr:street":"Weyakwin Rd",
    "iso:country":"CA",
    "sg:address":"Weyakwin Rd",
    "sg:city":"Weyakwin",
    "sg:classifiers":[
        {
            "category":"Health Services",
            "subcategory":"Clinic",
            "type":"Services"
        }
    ],
    "sg:phone":"+1 306 663 6100",
    "sg:postcode":"S0J 1W0",
    "sg:province":"SK",
    "sg:tags":[
        "home"
    ],
    "wof:name":"Weyakwin Home Care",
    "wof:placetype":"venue"
},
  "geometry": {"coordinates":[-105.80407700000001,54.421593],"type":"Point"}
}