{
  "type": "Feature",
  "properties": {
    "addr:full":"1180 Moon Ave Williams Lake BC V2G 4A6",
    "addr:housenumber":"1180",
    "addr:postcode":"v2g 4a6",
    "addr:street":"Moon Ave",
    "iso:country":"CA",
    "sg:address":"1180 Moon Ave",
    "sg:city":"Williams Lake",
    "sg:classifiers":[
        {
            "category":"Education",
            "subcategory":"School",
            "type":"Public Place"
        }
    ],
    "sg:phone":"+1 250 398 7192",
    "sg:postcode":"V2G 4A6",
    "sg:province":"BC",
    "wof:name":"Nesika Elementary",
    "wof:placetype":"venue"
},
  "geometry": {"coordinates":[-122.15451,52.146309],"type":"Point"}
}