{
  "type": "Feature",
  "properties": {
    "addr:full":"1520 Jefferson Ave Winnipeg MB R2P 1K1",
    "addr:housenumber":"1520",
    "addr:postcode":"r2p 1k1",
    "addr:street":"Jefferson Ave",
    "iso:country":"CA",
    "sg:address":"1520 Jefferson Ave",
    "sg:city":"Winnipeg",
    "sg:classifiers":[
        {
            "category":"Education",
            "subcategory":"School",
            "type":"Public Place"
        }
    ],
    "sg:phone":"+1 204 632 6314",
    "sg:postcode":"R2P 1K1",
    "sg:province":"MB",
    "wof:name":"Arthur E Wright School",
    "wof:placetype":"venue"
},
  "geometry": {"coordinates":[-97.17492675779999,49.958530426],"type":"Point"}
}