{
  "type": "Feature",
  "properties": {
    "addr:full":"3056 Christopher Cres Prince George BC V2N 4S9",
    "addr:housenumber":"3056",
    "addr:postcode":"v2n 4s9",
    "addr:street":"Christopher Cres",
    "iso:country":"CA",
    "sg:address":"3056 Christopher Cres",
    "sg:city":"Prince George",
    "sg:classifiers":[
        {
            "category":"Manufacturing",
            "subcategory":"Metals",
            "type":"Manufacturing & Wholesale Goods"
        }
    ],
    "sg:phone":"+1 250 563 9545",
    "sg:postcode":"V2N 4S9",
    "sg:province":"BC",
    "sg:tags":[
        "production",
        "grinding"
    ],
    "wof:name":"C D Grinding Intl Ltd",
    "wof:placetype":"venue"
},
  "geometry": {"coordinates":[-122.791183,53.889416],"type":"Point"}
}