{
  "type": "Feature",
  "properties": {
    "addr:full":"Woodbridge ON L4L 7Z6",
    "addr:postcode":"l4l 7z6",
    "iso:country":"CA",
    "sg:city":"Woodbridge",
    "sg:classifiers":[
        {
            "category":"Manufacturing",
            "subcategory":"Jewelry",
            "type":"Manufacturing & Wholesale Goods"
        }
    ],
    "sg:phone":"+1 905 850 1189",
    "sg:postcode":"L4L 7Z6",
    "sg:province":"ON",
    "wof:name":"Arezzo Jewellery Design Ltd",
    "wof:placetype":"venue"
},
  "geometry": {"coordinates":[-79.5478057861,43.8003540039],"type":"Point"}
}