{
  "type": "Feature",
  "properties": {
    "iso:country":"CA",
    "sg:address":"88 Portage Ave",
    "sg:city":"Fort Smith",
    "sg:classifiers":[
        {
            "category":"Shopping",
            "subcategory":"Department Store",
            "type":"Retail Goods"
        }
    ],
    "sg:phone":"+1 867 872 3130",
    "sg:postcode":"X0E 0P0",
    "sg:province":"NT",
    "wof:name":"Fields Stores",
    "wof:placetype":"venue"
},
  "geometry": {"coordinates":[-111.902633667,60.0000953674],"type":"Point"}
}