{
  "type": "Feature",
  "properties": {
    "iso:country":"CA",
    "sg:address":"126 Boul Des Laurentides",
    "sg:city":"Laval",
    "sg:classifiers":[
        {
            "category":"Health Services",
            "subcategory":"Hospital",
            "type":"Services"
        }
    ],
    "sg:phone":"+1 450 668 6432",
    "sg:postcode":"H7G 2T3",
    "sg:province":"QC",
    "sg:tags":[
        "mental"
    ],
    "wof:name":"Cafgraf Inc",
    "wof:placetype":"venue"
},
  "geometry": {"coordinates":[-73.683983,45.562866],"type":"Point"}
}