{
  "type": "Feature",
  "properties": {
    "addr:full":"368 Sherman Ave N Hamilton ON L8L 6N7",
    "addr:housenumber":"368",
    "addr:postcode":"l8l 6n7",
    "addr:street":"Sherman Ave N",
    "iso:country":"CA",
    "sg:address":"368 Sherman Ave N",
    "sg:city":"Hamilton",
    "sg:classifiers":[
        {
            "category":"Professional",
            "subcategory":"Management & Consulting",
            "type":"Services"
        }
    ],
    "sg:phone":"+1 905 544 3558",
    "sg:postcode":"L8L 6N7",
    "sg:province":"ON",
    "sg:tags":[
        "roofing",
        "consultant"
    ],
    "wof:name":"Buss Roof Inspection Svc Inc",
    "wof:placetype":"venue"
},
  "geometry": {"coordinates":[-79.833061,43.263477],"type":"Point"}
}