{
  "type": "Feature",
  "properties": {
    "iso:country":"CA",
    "sg:address":"1505 Harvey Ave # 202",
    "sg:city":"Kelowna",
    "sg:classifiers":[
        {
            "category":"Health Services",
            "subcategory":"Medical Lab",
            "type":"Services"
        }
    ],
    "sg:phone":"+1 250 860 3911",
    "sg:postcode":"V1Y 6G1",
    "sg:province":"BC",
    "sg:tags":[
        "laboratory"
    ],
    "wof:name":"Isis Dental Ceramics",
    "wof:placetype":"venue"
},
  "geometry": {"coordinates":[-119.465377808,49.881729126],"type":"Point"}
}