{
  "type": "Feature",
  "properties": {
    "iso:country":"CA",
    "sg:city":"Ottawa",
    "sg:classifiers":[
        {
            "category":"Education",
            "subcategory":"Special Training",
            "type":"Public Place"
        }
    ],
    "sg:phone":"+1 613 721 5957",
    "sg:postcode":"K2B 8C8",
    "sg:province":"ON",
    "sg:tags":[
        "personnel",
        "management",
        "consultant"
    ],
    "wof:name":"Institute of Professional Mgmt",
    "wof:placetype":"venue"
},
  "geometry": {"coordinates":[-75.780571,45.373024],"type":"Point"}
}