{
  "type": "Feature",
  "properties": {
    "addr:full":"3419 Petawawa Blvd Petawawa ON K8H 1X4",
    "addr:housenumber":"3419",
    "addr:postcode":"k8h 1x4",
    "addr:street":"Petawawa Blvd",
    "iso:country":"CA",
    "sg:address":"3419 Petawawa Blvd",
    "sg:city":"Petawawa",
    "sg:classifiers":[
        {
            "category":"Restaurant",
            "type":"Food & Drink"
        }
    ],
    "sg:phone":"+1 613 687 5534",
    "sg:postcode":"K8H 1X4",
    "sg:province":"ON",
    "sg:tags":[
        "grocer"
    ],
    "wof:name":"Giesebrecht's Limited",
    "wof:placetype":"venue"
},
  "geometry": {"coordinates":[-77.28198999999999,45.897411],"type":"Point"}
}