{
  "type": "Feature",
  "properties": {
    "addr:full":"Niagara Falls ON L2J 1M6",
    "addr:postcode":"l2j 1m6",
    "iso:country":"CA",
    "sg:city":"Niagara Falls",
    "sg:classifiers":[
        {
            "category":"Insurance",
            "subcategory":"Insurance Agent",
            "type":"Services"
        }
    ],
    "sg:phone":"+1 905 353 9159",
    "sg:postcode":"L2J 1M6",
    "sg:province":"ON",
    "wof:name":"Dale Mellway Insurance",
    "wof:placetype":"venue"
},
  "geometry": {"coordinates":[-79.3340682983,43.0491905212],"type":"Point"}
}