{
  "type": "Feature",
  "properties": {
    "addr:full":"35 Eisener Blvd Dartmouth NS B2W 6K2",
    "addr:housenumber":"35",
    "addr:postcode":"b2w 6k2",
    "addr:street":"Eisener Blvd",
    "iso:country":"CA",
    "sg:address":"35 Eisener Blvd",
    "sg:city":"Dartmouth",
    "sg:classifiers":[
        {
            "category":"Personal",
            "subcategory":"Beauty Salon",
            "type":"Services"
        }
    ],
    "sg:phone":"+1 902 434 5048",
    "sg:postcode":"B2W 6K2",
    "sg:province":"NS",
    "wof:name":"Bozenka's Hair Studio",
    "wof:placetype":"venue"
},
  "geometry": {"coordinates":[-63.520641,44.667114],"type":"Point"}
}