{
  "type": "Feature",
  "properties": {
    "addr:full":"1025 Harkness Ave Ottawa ON K1V 6N9",
    "addr:housenumber":"1025",
    "addr:postcode":"k1v 6n9",
    "addr:street":"Harkness Ave",
    "iso:country":"CA",
    "sg:address":"1025 Harkness Ave",
    "sg:city":"Ottawa",
    "sg:classifiers":[
        {
            "category":"Education",
            "subcategory":"School",
            "type":"Public Place"
        }
    ],
    "sg:phone":"+1 613 731 3631",
    "sg:postcode":"K1V 6N9",
    "sg:province":"ON",
    "wof:name":"General Vanier School",
    "wof:placetype":"venue"
},
  "geometry": {"coordinates":[-75.674637,45.367138],"type":"Point"}
}