{
  "type": "Feature",
  "properties": {
    "addr:full":"2020 Boul Lemire Drummondville QC J2B 6X5",
    "addr:housenumber":"2020",
    "addr:postcode":"j2b 6x5",
    "addr:street":"Boul Lemire",
    "iso:country":"CA",
    "sg:address":"2020 Boul Lemire",
    "sg:city":"Drummondville",
    "sg:classifiers":[
        {
            "category":"Autos & Motor Vehicles",
            "subcategory":"Auto Supplies",
            "type":"Retail Goods"
        }
    ],
    "sg:phone":"+1 819 472 8040",
    "sg:postcode":"J2B 6X5",
    "sg:province":"QC",
    "sg:tags":[
        "automobile",
        "stereo",
        "radio"
    ],
    "wof:name":"Ace Electronique Inc",
    "wof:placetype":"venue"
},
  "geometry": {"coordinates":[-72.499084,45.864399],"type":"Point"}
}