{
  "type": "Feature",
  "properties": {
    "addr:full":"925 Terminal Ave Vancouver BC V6A 2M9",
    "addr:housenumber":"925",
    "addr:postcode":"v6a 2m9",
    "addr:street":"Terminal Ave",
    "iso:country":"CA",
    "sg:address":"925 Terminal Ave",
    "sg:city":"Vancouver",
    "sg:classifiers":[
        {
            "category":"Professional",
            "subcategory":"Business Services",
            "type":"Services"
        }
    ],
    "sg:phone":"+1 604 669 1196",
    "sg:postcode":"V6A 2M9",
    "sg:province":"BC",
    "sg:tags":[
        "record"
    ],
    "wof:name":"Butler Box & Storage Inc",
    "wof:placetype":"venue"
},
  "geometry": {"coordinates":[-123.082977,49.270264],"type":"Point"}
}