{
  "type": "Feature",
  "properties": {
    "addr:full":"1580 Columbia St North Vancouver BC V7J 1A4",
    "addr:housenumber":"1580",
    "addr:postcode":"v7j 1a4",
    "addr:street":"Columbia St",
    "iso:country":"CA",
    "sg:address":"1580 Columbia St",
    "sg:city":"North Vancouver",
    "sg:classifiers":[
        {
            "category":"Freight",
            "type":"Transportation"
        }
    ],
    "sg:phone":"+1 604 986 9817",
    "sg:postcode":"V7J 1A4",
    "sg:province":"BC",
    "sg:tags":[
        "mover"
    ],
    "wof:name":"Ellis Moving & Storage Ltd",
    "wof:placetype":"venue"
},
  "geometry": {"coordinates":[-123.030312,49.302521],"type":"Point"}
}