{
  "type": "Feature",
  "properties": {
    "iso:country":"CA",
    "sg:address":"313 Sherbourne St",
    "sg:city":"Toronto",
    "sg:classifiers":[
        {
            "category":"Organizations",
            "subcategory":"Religious Organization",
            "type":"Services"
        }
    ],
    "sg:phone":"+1 416 921 5996",
    "sg:postcode":"M5A 2S3",
    "sg:province":"ON",
    "sg:tags":[
        "association"
    ],
    "wof:name":"British Israel World Fdrtn",
    "wof:placetype":"venue"
},
  "geometry": {"coordinates":[-79.372154,43.661533],"type":"Point"}
}