{
  "type": "Feature",
  "properties": {
    "addr:full":"313 Sherbourne St Toronto ON M5A 2S3",
    "addr:housenumber":"313",
    "addr:postcode":"m5a 2s3",
    "addr:street":"Sherbourne St",
    "iso:country":"CA",
    "sg:address":"313 Sherbourne St",
    "sg:city":"Toronto",
    "sg:classifiers":[
        {
            "category":"Organizations",
            "subcategory":"Religious Organization",
            "type":"Services"
        }
    ],
    "sg:phone":"+1 416 921 5996",
    "sg:postcode":"M5A 2S3",
    "sg:province":"ON",
    "sg:tags":[
        "association"
    ],
    "wof:name":"British Israel World Fdrtn",
    "wof:placetype":"venue"
},
  "geometry": {"coordinates":[-79.37215399999999,43.661533],"type":"Point"}
}