{
  "type": "Feature",
  "properties": {
    "addr:full":"2230 Fern Rd Nanaimo BC V9S 2W9",
    "addr:housenumber":"2230",
    "addr:postcode":"v9s 2w9",
    "addr:street":"Fern Rd",
    "iso:country":"CA",
    "sg:address":"2230 Fern Rd",
    "sg:city":"Nanaimo",
    "sg:classifiers":[
        {
            "category":"Health Services",
            "subcategory":"Clinic",
            "type":"Services"
        }
    ],
    "sg:phone":"+1 250 758 9120",
    "sg:postcode":"V9S 2W9",
    "sg:province":"BC",
    "wof:name":"Footloose Reflexology",
    "wof:placetype":"venue"
},
  "geometry": {"coordinates":[-123.99247,49.19025],"type":"Point"}
}