{
  "type": "Feature",
  "properties": {
    "addr:full":"200 Commercial St Berwick NS B0P 1E0",
    "addr:housenumber":"200",
    "addr:postcode":"b0p 1e0",
    "addr:street":"Commercial St",
    "iso:country":"CA",
    "sg:address":"200 Commercial St",
    "sg:city":"Berwick",
    "sg:classifiers":[
        {
            "category":"Food & Beverages",
            "subcategory":"Liquor & Beverages",
            "type":"Retail Goods"
        }
    ],
    "sg:phone":"+1 902 538 9310",
    "sg:postcode":"B0P 1E0",
    "sg:province":"NS",
    "sg:tags":[
        "government"
    ],
    "wof:name":"Nova Scotia Liquor Commission",
    "wof:placetype":"venue"
},
  "geometry": {"coordinates":[-64.7353668213,45.0433082581],"type":"Point"}
}