{
  "type": "Feature",
  "properties": {
    "addr:full":"95 Rue Desbiens Amqui QC G5J 3P7",
    "addr:housenumber":"95",
    "addr:postcode":"g5j 3p7",
    "addr:street":"Rue Desbiens",
    "iso:country":"CA",
    "sg:address":"95 Rue Desbiens",
    "sg:city":"Amqui",
    "sg:classifiers":[
        {
            "category":"Real Estate",
            "subcategory":"Real Estate Operator",
            "type":"Services"
        }
    ],
    "sg:phone":"+1 418 629 2661",
    "sg:postcode":"G5J 3P7",
    "sg:province":"QC",
    "sg:tags":[
        "boarding",
        "house"
    ],
    "wof:name":"Manoir Des Pignons",
    "wof:placetype":"venue"
},
  "geometry": {"coordinates":[-67.429573,48.466869],"type":"Point"}
}