{
  "type": "Feature",
  "properties": {
    "addr:full":"Mississauga ON L4V 1X1",
    "addr:postcode":"l4v 1x1",
    "iso:country":"CA",
    "sg:city":"Mississauga",
    "sg:classifiers":[
        {
            "category":"Building & Trades",
            "subcategory":"Construction",
            "type":"Services"
        }
    ],
    "sg:phone":"+1 905 677 7207",
    "sg:postcode":"L4V 1X1",
    "sg:province":"ON",
    "sg:tags":[
        "contractor"
    ],
    "wof:name":"Glen Orchard Homes",
    "wof:placetype":"venue"
},
  "geometry": {"coordinates":[-79.6193847656,43.7018318176],"type":"Point"}
}