{
  "type": "Feature",
  "properties": {
    "addr:full":"3 Car Westmount Westmount QC H3Z 2S5",
    "addr:postcode":"h3z 2s5",
    "addr:street":"Car Westmount",
    "iso:country":"CA",
    "sg:address":"3 Car Westmount",
    "sg:city":"Westmount",
    "sg:classifiers":[
        {
            "category":"Manufacturing",
            "subcategory":"Printing",
            "type":"Manufacturing & Wholesale Goods"
        }
    ],
    "sg:phone":"+1 514 935 4343",
    "sg:postcode":"H3Z 2S5",
    "sg:province":"QC",
    "sg:tags":[
        "publisher"
    ],
    "wof:name":"Codital Development Corp",
    "wof:placetype":"venue"
},
  "geometry": {"coordinates":[-73.587509,45.486759],"type":"Point"}
}