{
  "type": "Feature",
  "properties": {
    "iso:country":"CA",
    "sg:address":"9128 97 Ave",
    "sg:city":"Fort St John",
    "sg:classifiers":[
        {
            "category":"Mining & Drilling",
            "type":"Manufacturing & Wholesale Goods"
        }
    ],
    "sg:phone":"+1 250 787 8773",
    "sg:postcode":"V1J 5E3",
    "sg:province":"BC",
    "sg:tags":[
        "field",
        "oil",
        "welding"
    ],
    "wof:name":"Advantage Industries Inc",
    "wof:placetype":"venue"
},
  "geometry": {"coordinates":[-120.83118438699999,56.2440109253],"type":"Point"}
}