{
  "type": "Feature",
  "properties": {
    "addr:full":"6263 Boul Maurice-Duplessis Montreal-Nord QC H1G 1Y7",
    "addr:housenumber":"6263",
    "addr:postcode":"h1g 1y7",
    "addr:street":"Boul Maurice-Duplessis",
    "iso:country":"CA",
    "sg:address":"6263 Boul Maurice-Duplessis",
    "sg:city":"Montreal-Nord",
    "sg:classifiers":[
        {
            "category":"Professional",
            "subcategory":"Business Services",
            "type":"Services"
        }
    ],
    "sg:phone":"+1 514 255 1188",
    "sg:postcode":"H1G 1Y7",
    "sg:province":"QC",
    "wof:name":"Opac Inc",
    "wof:placetype":"venue"
},
  "geometry": {"coordinates":[-73.6186904907,45.6153106689],"type":"Point"}
}