{
  "type": "Feature",
  "properties": {
    "addr:full":"249 Mcphillips St Winnipeg MB R3E 2K5",
    "addr:housenumber":"249",
    "addr:postcode":"r3e 2k5",
    "addr:street":"Mcphillips St",
    "iso:country":"CA",
    "sg:address":"249 Mcphillips St",
    "sg:city":"Winnipeg",
    "sg:classifiers":[
        {
            "category":"Manufacturing",
            "subcategory":"Rubber & Plastics",
            "type":"Manufacturing & Wholesale Goods"
        }
    ],
    "sg:phone":"+1 204 772 7927",
    "sg:postcode":"R3E 2K5",
    "sg:province":"MB",
    "sg:tags":[
        "equipment",
        "hose",
        "hydraulic",
        "supply"
    ],
    "wof:name":"Westcan Hydraulic Lines Ltd",
    "wof:placetype":"venue"
},
  "geometry": {"coordinates":[-97.17042499999999,49.912148],"type":"Point"}
}