{
  "type": "Feature",
  "properties": {
    "addr:full":"266 Kingscourt Ave Kingston ON K7K 6C9",
    "addr:housenumber":"266",
    "addr:postcode":"k7k 6c9",
    "addr:street":"Kingscourt Ave",
    "iso:country":"CA",
    "sg:address":"266 Kingscourt Ave",
    "sg:city":"Kingston",
    "sg:classifiers":[
        {
            "category":"Professional",
            "subcategory":"Lawyer & Legal Services",
            "type":"Services"
        }
    ],
    "sg:phone":"+1 613 547 4272",
    "sg:postcode":"K7K 6C9",
    "sg:province":"ON",
    "sg:tags":[
        "attorney"
    ],
    "wof:name":"Voino, David",
    "wof:placetype":"venue"
},
  "geometry": {"coordinates":[-76.50206799999999,44.250446],"type":"Point"}
}