{
  "type": "Feature",
  "properties": {
    "addr:full":"911 1st Ave NW Moose Jaw SK S6H 3M9",
    "addr:housenumber":"911",
    "addr:postcode":"s6h 3m9",
    "addr:street":"1St Ave Nw",
    "iso:country":"CA",
    "sg:address":"911 1st Ave NW",
    "sg:city":"Moose Jaw",
    "sg:classifiers":[
        {
            "category":"Health Services",
            "subcategory":"Doctor",
            "type":"Services"
        }
    ],
    "sg:phone":"+1 306 692 3880",
    "sg:postcode":"S6H 3M9",
    "sg:province":"SK",
    "sg:tags":[
        "dentist"
    ],
    "wof:name":"Bernard, Earl S DDS",
    "wof:placetype":"venue"
},
  "geometry": {"coordinates":[-105.53717041,50.3980979919],"type":"Point"}
}