{
  "type": "Feature",
  "properties": {
    "addr:full":"24 Boudreau Rd St Albert AB T8N 6K3",
    "addr:housenumber":"24",
    "addr:postcode":"t8n 6k3",
    "addr:street":"Boudreau Rd St Albert",
    "iso:country":"CA",
    "sg:address":"24 Boudreau Rd",
    "sg:city":"St Albert",
    "sg:classifiers":[
        {
            "category":"Restaurant",
            "type":"Food & Drink"
        }
    ],
    "sg:phone":"+1 780 460 1961",
    "sg:postcode":"T8N 6K3",
    "sg:province":"AB",
    "sg:tags":[
        "lounge",
        "cocktail"
    ],
    "wof:name":"Mvp Sports Bar & Grill",
    "wof:placetype":"venue"
},
  "geometry": {"coordinates":[-113.57384500000001,53.635754],"type":"Point"}
}