{
  "type": "Feature",
  "properties": {
    "addr:full":"265 8E Rang Saint-Germain-DE-Grantham QC J0C 1K0",
    "addr:housenumber":"265",
    "addr:postcode":"j0c 1k0",
    "addr:street":"8E Rang",
    "iso:country":"CA",
    "sg:address":"265 8E Rang",
    "sg:city":"Saint-Germain-DE-Grantham",
    "sg:classifiers":[
        {
            "category":"Wholesale",
            "subcategory":"Stationery",
            "type":"Manufacturing & Wholesale Goods"
        }
    ],
    "sg:phone":"+1 819 395 2829",
    "sg:postcode":"J0C 1K0",
    "sg:province":"QC",
    "sg:tags":[
        "packaging",
        "material"
    ],
    "wof:name":"Entreprises DE Papiers Amdray",
    "wof:placetype":"venue"
},
  "geometry": {"coordinates":[-72.565071,45.845036],"type":"Point"}
}