{
  "type": "Feature",
  "properties": {
    "addr:full":"8210 36 Ave NW Edmonton AB T6K 0C7",
    "addr:housenumber":"8210",
    "addr:postcode":"t6k 0c7",
    "addr:street":"36 Ave Nw",
    "iso:country":"CA",
    "sg:address":"8210 36 Ave NW",
    "sg:city":"Edmonton",
    "sg:classifiers":[
        {
            "category":"Education",
            "subcategory":"School",
            "type":"Public Place"
        }
    ],
    "sg:phone":"+1 780 462 7121",
    "sg:postcode":"T6K 0C7",
    "sg:province":"AB",
    "wof:name":"Grace Martin Elementary School",
    "wof:placetype":"venue"
},
  "geometry": {"coordinates":[-113.456924,53.46891],"type":"Point"}
}