{
  "type": "Feature",
  "properties": {
    "addr:full":"56 Glenashton Dr Stoney Creek ON L8G 4E9",
    "addr:housenumber":"56",
    "addr:postcode":"l8g 4e9",
    "addr:street":"Glenashton Dr",
    "iso:country":"CA",
    "sg:address":"56 Glenashton Dr",
    "sg:city":"Stoney Creek",
    "sg:classifiers":[
        {
            "category":"Building & Trades",
            "subcategory":"Electrical",
            "type":"Services"
        }
    ],
    "sg:phone":"+1 905 662 1750",
    "sg:postcode":"L8G 4E9",
    "sg:province":"ON",
    "sg:tags":[
        "electric",
        "contractor"
    ],
    "wof:name":"Orlic Electric Ltd",
    "wof:placetype":"venue"
},
  "geometry": {"coordinates":[-79.7181854248,43.2124404907],"type":"Point"}
}