{
  "type": "Feature",
  "properties": {
    "iso:country":"CA",
    "sg:address":"100 Rue Hall",
    "sg:city":"Verdun",
    "sg:classifiers":[
        {
            "category":"Banks & Credit Unions",
            "subcategory":"Investment Brokerage",
            "type":"Services"
        }
    ],
    "sg:phone":"+1 514 766 7054",
    "sg:postcode":"H3E 1P3",
    "sg:province":"QC",
    "sg:tags":[
        "consultant",
        "planning",
        "financial"
    ],
    "wof:name":"Fintech International Inc",
    "wof:placetype":"venue"
},
  "geometry": {"coordinates":[-73.571762085,45.4590187073],"type":"Point"}
}