{
  "type": "Feature",
  "properties": {
    "addr:full":"95 Cree Rd Thompson MB R8N 0B9",
    "addr:housenumber":"95",
    "addr:postcode":"r8n 0b9",
    "addr:street":"Cree Rd",
    "iso:country":"CA",
    "sg:address":"95 Cree Rd",
    "sg:city":"Thompson",
    "sg:classifiers":[
        {
            "category":"Travel",
            "subcategory":"Hotels & Motels",
            "type":"Entertainment"
        }
    ],
    "sg:phone":"+1 204 677 4111",
    "sg:postcode":"R8N 0B9",
    "sg:province":"MB",
    "sg:tags":[
        "breakfast",
        "accommodation",
        "bed"
    ],
    "wof:name":"Northern Lights Bed & Breakfst",
    "wof:placetype":"venue"
},
  "geometry": {"coordinates":[-97.85958099370001,55.7419929504],"type":"Point"}
}