{
  "type": "Feature",
  "properties": {
    "addr:full":"16262 Rue Bureau Pointe-Aux-Trembles QC H1A 1Z1",
    "addr:housenumber":"16262",
    "addr:postcode":"h1a 1z1",
    "addr:street":"Rue Bureau",
    "iso:country":"CA",
    "sg:address":"16262 Rue Bureau",
    "sg:city":"Pointe-Aux-Trembles",
    "sg:classifiers":[
        {
            "category":"Building & Trades",
            "subcategory":"Construction",
            "type":"Services"
        }
    ],
    "sg:phone":"+1 514 591 0642",
    "sg:postcode":"H1A 1Z1",
    "sg:province":"QC",
    "sg:tags":[
        "masonry",
        "contractor"
    ],
    "wof:name":"Maconnerie Jean Bedard Inc",
    "wof:placetype":"venue"
},
  "geometry": {"coordinates":[-73.4812164307,45.6988105774],"type":"Point"}
}