{
  "type": "Feature",
  "properties": {
    "addr:full":"Vancouver BC V5Z 3N8",
    "addr:postcode":"v5z 3n8",
    "iso:country":"CA",
    "sg:city":"Vancouver",
    "sg:classifiers":[
        {
            "category":"Shopping",
            "type":"Retail Goods"
        }
    ],
    "sg:phone":"+1 604 879 4327",
    "sg:postcode":"V5Z 3N8",
    "sg:province":"BC",
    "sg:tags":[
        "supply",
        "equipment",
        "audiologists",
        "hearing",
        "impaired"
    ],
    "wof:name":"Sonus",
    "wof:placetype":"venue"
},
  "geometry": {"coordinates":[-123.122062683,49.2630653381],"type":"Point"}
}