{
  "type": "Feature",
  "properties": {
    "iso:country":"CA",
    "sg:address":"1 Schofield Hwy",
    "sg:city":"Trail",
    "sg:classifiers":[
        {
            "category":"Retail",
            "subcategory":"Auto Repair",
            "type":"Services"
        }
    ],
    "sg:phone":"+1 250 364 1933",
    "sg:postcode":"V1R 2J9",
    "sg:province":"BC",
    "sg:tags":[
        "body",
        "automobile",
        "painting"
    ],
    "wof:name":"A & J Body Shop Ltd",
    "wof:placetype":"venue"
},
  "geometry": {"coordinates":[-117.71221160899999,49.0964508057],"type":"Point"}
}