{
  "type": "Feature",
  "properties": {
    "addr:full":"4710 8th Ave Regina SK S4T 0V7",
    "addr:housenumber":"4710",
    "addr:postcode":"s4t 0v7",
    "addr:street":"8Th Ave",
    "iso:country":"CA",
    "sg:address":"4710 8th Ave",
    "sg:city":"Regina",
    "sg:classifiers":[
        {
            "category":"Organizations",
            "subcategory":"Religious Organization",
            "type":"Services"
        }
    ],
    "sg:phone":"+1 306 545 2544",
    "sg:postcode":"S4T 0V7",
    "sg:province":"SK",
    "sg:tags":[
        "church"
    ],
    "wof:name":"Community of Christ Church",
    "wof:placetype":"venue"
},
  "geometry": {"coordinates":[-104.6484375,50.4569778442],"type":"Point"}
}