{
  "type": "Feature",
  "properties": {
    "addr:full":"Scarborough ON M1J 1K2",
    "addr:postcode":"m1j 1k2",
    "iso:country":"CA",
    "sg:city":"Scarborough",
    "sg:classifiers":[
        {
            "category":"Health Services",
            "subcategory":"Doctor",
            "type":"Services"
        }
    ],
    "sg:phone":"+1 416 431 4633",
    "sg:postcode":"M1J 1K2",
    "sg:province":"ON",
    "sg:tags":[
        "dentist"
    ],
    "wof:name":"Gay, John DDS",
    "wof:placetype":"venue"
},
  "geometry": {"coordinates":[-79.24517822270001,43.7551956177],"type":"Point"}
}