{
  "type": "Feature",
  "properties": {
    "iso:country":"CA",
    "sg:address":"516 6th Ave",
    "sg:city":"Stewart",
    "sg:classifiers":[
        {
            "category":"Building & Trades",
            "subcategory":"Electrical",
            "type":"Services"
        }
    ],
    "sg:phone":"+1 250 636 2511",
    "sg:postcode":"V0T 1W0",
    "sg:province":"BC",
    "sg:tags":[
        "electric",
        "contractor"
    ],
    "wof:name":"Three Point Electric",
    "wof:placetype":"venue"
},
  "geometry": {"coordinates":[-129.98988342300001,55.9368553162],"type":"Point"}
}