{
  "type": "Feature",
  "properties": {
    "addr:full":"Bedford NS B4A 2X9",
    "addr:postcode":"b4a 2x9",
    "iso:country":"CA",
    "sg:city":"Bedford",
    "sg:classifiers":[
        {
            "category":"Real Estate",
            "subcategory":"Real Estate Operator",
            "type":"Services"
        }
    ],
    "sg:phone":"+1 902 835 8381",
    "sg:postcode":"B4A 2X9",
    "sg:province":"NS",
    "sg:tags":[
        "mall",
        "shopping",
        "center"
    ],
    "wof:name":"Bedford Place Mall",
    "wof:placetype":"venue"
},
  "geometry": {"coordinates":[-63.654804,44.736401],"type":"Point"}
}