{
  "type": "Feature",
  "properties": {
    "addr:full":"1460 Byland Rd Kelowna BC V1Z 1A7",
    "addr:housenumber":"1460",
    "addr:postcode":"v1z 1a7",
    "addr:street":"Byland Rd",
    "iso:country":"CA",
    "sg:address":"1460 Byland Rd",
    "sg:city":"Kelowna",
    "sg:classifiers":[
        {
            "category":"Autos & Motor Vehicles",
            "subcategory":"Recreational Vehicle Sales",
            "type":"Retail Goods"
        }
    ],
    "sg:phone":"+1 250 769 4525",
    "sg:postcode":"V1Z 1A7",
    "sg:province":"BC",
    "wof:name":"Westgate Rv Ctr Ltd",
    "wof:placetype":"venue"
},
  "geometry": {"coordinates":[-119.577980041,49.8630371094],"type":"Point"}
}