{
  "type": "Feature",
  "properties": {
    "addr:full":"Montcerf QC J0W 1N0",
    "addr:postcode":"j0w 1n0",
    "addr:street":"Montcerf",
    "iso:country":"CA",
    "sg:city":"Montcerf",
    "sg:classifiers":[
        {
            "category":"Travel",
            "subcategory":"Campground",
            "type":"Entertainment"
        }
    ],
    "sg:phone":"+1 819 438 2013",
    "sg:postcode":"J0W 1N0",
    "sg:province":"QC",
    "sg:tags":[
        "camp",
        "fishing"
    ],
    "wof:name":"Pavillon Des Pins Gris",
    "wof:placetype":"venue"
},
  "geometry": {"coordinates":[-76.039597,46.715042],"type":"Point"}
}