{
  "type": "Feature",
  "properties": {
    "addr:full":"Halifax NS B3S 1B3",
    "addr:postcode":"b3s 1b3",
    "iso:country":"CA",
    "sg:city":"Halifax",
    "sg:classifiers":[
        {
            "category":"Professional",
            "subcategory":"Engineering",
            "type":"Services"
        }
    ],
    "sg:phone":"+1 902 494 5700",
    "sg:postcode":"B3S 1B3",
    "sg:province":"NS",
    "sg:tags":[
        "advertising"
    ],
    "wof:name":"Fleetway Design Communications",
    "wof:placetype":"venue"
},
  "geometry": {"coordinates":[-63.6670188904,44.6448707581],"type":"Point"}
}