{
  "type": "Feature",
  "properties": {
    "iso:country":"CA",
    "sg:address":"645 Ch DE Sainte-Anne-Des-Lacs",
    "sg:city":"Sainte-Anne-Des-Lacs",
    "sg:classifiers":[
        {
            "category":"Home & Garden",
            "subcategory":"Building Materials",
            "type":"Retail Goods"
        }
    ],
    "sg:phone":"+1 450 224 8638",
    "sg:postcode":"J0R 1B0",
    "sg:province":"QC",
    "wof:name":"Materiaux Ste-Anne-Des-Lacs",
    "wof:placetype":"venue"
},
  "geometry": {"coordinates":[-74.12757873539999,45.8598480225],"type":"Point"}
}