{
  "type": "Feature",
  "properties": {
    "addr:full":"445 2nd Ave W Vancouver BC V5Y 1E3",
    "addr:housenumber":"445",
    "addr:postcode":"v5y 1e3",
    "addr:street":"2Nd Ave W",
    "iso:country":"CA",
    "sg:address":"445 2nd Ave W",
    "sg:city":"Vancouver",
    "sg:classifiers":[
        {
            "category":"Manufacturing",
            "subcategory":"Furniture",
            "type":"Manufacturing & Wholesale Goods"
        }
    ],
    "sg:phone":"+1 604 877 2255",
    "sg:postcode":"V5Y 1E3",
    "sg:province":"BC",
    "sg:tags":[
        "woodworker"
    ],
    "wof:name":"Joint",
    "wof:placetype":"venue"
},
  "geometry": {"coordinates":[-123.113624573,49.267414093],"type":"Point"}
}