{
  "type": "Feature",
  "properties": {
    "addr:full":"460 Hopkins St Whitby ON L1N 2B9",
    "addr:housenumber":"460",
    "addr:postcode":"l1n 2b9",
    "addr:street":"Hopkins St",
    "iso:country":"CA",
    "sg:address":"460 Hopkins St",
    "sg:city":"Whitby",
    "sg:classifiers":[
        {
            "category":"Manufacturing",
            "subcategory":"Food",
            "type":"Manufacturing & Wholesale Goods"
        }
    ],
    "sg:phone":"+1 905 430 1652",
    "sg:postcode":"L1N 2B9",
    "sg:province":"ON",
    "sg:tags":[
        "cocoa",
        "chocolate"
    ],
    "wof:name":"Williams Chocolate",
    "wof:placetype":"venue"
},
  "geometry": {"coordinates":[-78.9197311401,43.8773384094],"type":"Point"}
}