{
  "type": "Feature",
  "properties": {
    "addr:full":"991 King's Hwy Fort Frances ON P9A 2X5",
    "addr:housenumber":"991",
    "addr:postcode":"p9a 2x5",
    "addr:street":"King'S Hwy",
    "iso:country":"CA",
    "sg:address":"991 King's Hwy",
    "sg:city":"Fort Frances",
    "sg:classifiers":[
        {
            "category":"Retail",
            "subcategory":"Auto Repair",
            "type":"Services"
        }
    ],
    "sg:phone":"+1 807 274 5535",
    "sg:postcode":"P9A 2X5",
    "sg:province":"ON",
    "sg:tags":[
        "repairing",
        "automobile"
    ],
    "wof:name":"Lakewood Tire Ctr",
    "wof:placetype":"venue"
},
  "geometry": {"coordinates":[-93.4268569946,48.6071472168],"type":"Point"}
}