{
  "type": "Feature",
  "properties": {
    "addr:full":"3220 Kingston Rd Scarborough ON M1M 1P4",
    "addr:housenumber":"3220",
    "addr:postcode":"m1m 1p4",
    "addr:street":"Kingston Rd",
    "iso:country":"CA",
    "sg:address":"3220 Kingston Rd",
    "sg:city":"Scarborough",
    "sg:classifiers":[
        {
            "category":"Retail",
            "subcategory":"Auto Repair",
            "type":"Services"
        }
    ],
    "sg:phone":"+1 416 265 8052",
    "sg:postcode":"M1M 1P4",
    "sg:province":"ON",
    "sg:tags":[
        "automobile",
        "lubrication"
    ],
    "wof:name":"Pennzoil 10 Minute Oil Change",
    "wof:placetype":"venue"
},
  "geometry": {"coordinates":[-79.22602081300001,43.731048584],"type":"Point"}
}