{
  "type": "Feature",
  "properties": {
    "addr:full":"Rimouski QC G5L 1A1",
    "addr:postcode":"g5l 1a1",
    "iso:country":"CA",
    "sg:city":"Rimouski",
    "sg:classifiers":[
        {
            "category":"Banks & Credit Unions",
            "subcategory":"Financial Services",
            "type":"Services"
        }
    ],
    "sg:phone":"+1 418 724 4422",
    "sg:postcode":"G5L 1A1",
    "sg:province":"QC",
    "sg:tags":[
        "bankruptcy",
        "trustee"
    ],
    "wof:name":"Lemieux Nolet Inc",
    "wof:placetype":"venue"
},
  "geometry": {"coordinates":[-68.5273513794,48.4513168335],"type":"Point"}
}