{
  "type": "Feature",
  "properties": {
    "addr:full":"541 Parliament St Toronto ON M4X 1P7",
    "addr:housenumber":"541",
    "addr:postcode":"m4x 1p7",
    "addr:street":"Parliament St",
    "iso:country":"CA",
    "sg:address":"541 Parliament St",
    "sg:city":"Toronto",
    "sg:classifiers":[
        {
            "category":"Cinema",
            "subcategory":"Movie Rental",
            "type":"Entertainment"
        }
    ],
    "sg:phone":"+1 416 975 1650",
    "sg:postcode":"M4X 1P7",
    "sg:province":"ON",
    "sg:tags":[
        "leasing",
        "video",
        "tape",
        "equipment"
    ],
    "wof:name":"Blockbuster Video",
    "wof:placetype":"venue"
},
  "geometry": {"coordinates":[-79.36854599999999,43.665985],"type":"Point"}
}