{
  "type": "Feature",
  "properties": {
    "addr:full":"250 Besserer St Ottawa ON K1N 6B3",
    "addr:housenumber":"250",
    "addr:postcode":"k1n 6b3",
    "addr:street":"Besserer St",
    "iso:country":"CA",
    "sg:address":"250 Besserer St",
    "sg:city":"Ottawa",
    "sg:classifiers":[
        {
            "category":"Manufacturing",
            "subcategory":"Printing",
            "type":"Manufacturing & Wholesale Goods"
        }
    ],
    "sg:phone":"+1 613 238 6631",
    "sg:postcode":"K1N 6B3",
    "sg:province":"ON",
    "sg:tags":[
        "bookbinder"
    ],
    "wof:name":"Canadiana Book Binding Ltd",
    "wof:placetype":"venue"
},
  "geometry": {"coordinates":[-75.68497499999999,45.428101],"type":"Point"}
}