{
  "type": "Feature",
  "properties": {
    "addr:full":"174 First Ave Ottawa ON K1S 2G4",
    "addr:housenumber":"174",
    "addr:postcode":"k1s 2g4",
    "addr:street":"First Ave",
    "iso:country":"CA",
    "sg:address":"174 First Ave",
    "sg:city":"Ottawa",
    "sg:classifiers":[
        {
            "category":"Social Services",
            "subcategory":"Child Care",
            "type":"Services"
        }
    ],
    "sg:phone":"+1 613 276 7974",
    "sg:postcode":"K1S 2G4",
    "sg:province":"ON",
    "sg:tags":[
        "kindergarten",
        "academic"
    ],
    "wof:name":"Good Morning Preschool",
    "wof:placetype":"venue"
},
  "geometry": {"coordinates":[-75.688293,45.404613],"type":"Point"}
}