{
  "type": "Feature",
  "properties": {
    "addr:full":"484 East 16th St Hamilton ON L9A 4K8",
    "addr:housenumber":"484",
    "addr:postcode":"l9a 4k8",
    "addr:street":"East 16Th St",
    "iso:country":"CA",
    "sg:address":"484 East 16th St",
    "sg:city":"Hamilton",
    "sg:classifiers":[
        {
            "category":"Organizations",
            "subcategory":"Religious Organization",
            "type":"Services"
        }
    ],
    "sg:phone":"+1 905 385 7891",
    "sg:postcode":"L9A 4K8",
    "sg:province":"ON",
    "sg:tags":[
        "church"
    ],
    "wof:name":"Linden Park Community Church",
    "wof:placetype":"venue"
},
  "geometry": {"coordinates":[-79.86534881590001,43.2272186279],"type":"Point"}
}