{
  "type": "Feature",
  "properties": {
    "addr:full":"51 Balsam Ave Toronto ON M4E 3B6",
    "addr:housenumber":"51",
    "addr:postcode":"m4e 3b6",
    "addr:street":"Balsam Ave",
    "iso:country":"CA",
    "sg:address":"51 Balsam Ave",
    "sg:city":"Toronto",
    "sg:classifiers":[
        {
            "category":"Shopping",
            "subcategory":"Books",
            "type":"Retail Goods"
        }
    ],
    "sg:phone":"+1 416 698 7559",
    "sg:postcode":"M4E 3B6",
    "sg:province":"ON",
    "sg:tags":[
        "dealer"
    ],
    "wof:name":"Canav Books",
    "wof:placetype":"venue"
},
  "geometry": {"coordinates":[-79.289581,43.671829],"type":"Point"}
}