{
  "type": "Feature",
  "properties": {
    "addr:full":"8655 Ch Delmeade Mont-Royal QC H4T 1M1",
    "addr:postcode":"8655;h4t 1m1",
    "addr:street":"Ch Delmeade",
    "iso:country":"CA",
    "sg:address":"8655 Ch Delmeade",
    "sg:city":"Mont-Royal",
    "sg:classifiers":[
        {
            "category":"Home & Garden",
            "subcategory":"Home Furnishings",
            "type":"Retail Goods"
        }
    ],
    "sg:phone":"+1 514 343 3740",
    "sg:postcode":"H4T 1M1",
    "sg:province":"QC",
    "sg:tags":[
        "linen",
        "bedspread"
    ],
    "wof:name":"Linge DE Maison Lawrence",
    "wof:placetype":"venue"
},
  "geometry": {"coordinates":[-73.67767333979999,45.4907188416],"type":"Point"}
}