{
  "type": "Feature",
  "properties": {
    "addr:full":"515 5E Rue Shawinigan QC G9N 1E7",
    "addr:housenumber":"515",
    "addr:postcode":"g9n 1e7",
    "addr:street":"5E Rue",
    "iso:country":"CA",
    "sg:address":"515 5E Rue",
    "sg:city":"Shawinigan",
    "sg:classifiers":[
        {
            "category":"Shopping",
            "subcategory":"Clothing, Apparel, & Fashions",
            "type":"Retail Goods"
        }
    ],
    "sg:phone":"+1 819 536 2911",
    "sg:postcode":"G9N 1E7",
    "sg:province":"QC",
    "sg:tags":[
        "furnishing"
    ],
    "wof:name":"Mercerie Harnois",
    "wof:placetype":"venue"
},
  "geometry": {"coordinates":[-72.74858856199999,46.540397644],"type":"Point"}
}