{
  "type": "Feature",
  "properties": {
    "addr:full":"North York ON M2N 7C1",
    "addr:postcode":"m2n 7c1",
    "iso:country":"CA",
    "sg:city":"North York",
    "sg:classifiers":[
        {
            "category":"Shopping",
            "type":"Retail Goods"
        }
    ],
    "sg:phone":"+1 416 996 9472",
    "sg:postcode":"M2N 7C1",
    "sg:province":"ON",
    "sg:tags":[
        "equipment",
        "telephone",
        "supply"
    ],
    "wof:name":"Integrated Connections Consltg",
    "wof:placetype":"venue"
},
  "geometry": {"coordinates":[-79.4082183838,43.7584686279],"type":"Point"}
}