{
  "type": "Feature",
  "properties": {
    "iso:country":"CA",
    "sg:address":"300 Boul DE LA Concorde E",
    "sg:city":"Laval",
    "sg:classifiers":[
        {
            "category":"Health Services",
            "subcategory":"Doctor",
            "type":"Services"
        }
    ],
    "sg:phone":"+1 450 668 8735",
    "sg:postcode":"H7G 2E6",
    "sg:province":"QC",
    "sg:tags":[
        "clinic"
    ],
    "wof:name":"Marguerite & Guy Deom",
    "wof:placetype":"venue"
},
  "geometry": {"coordinates":[-73.68151855470001,45.5776252747],"type":"Point"}
}