{
  "type": "Feature",
  "properties": {
    "addr:full":"48 Lansdowne St W Peterborough ON K9J 1Y1",
    "addr:housenumber":"48",
    "addr:postcode":"k9j 1y1",
    "addr:street":"Lansdowne St W",
    "iso:country":"CA",
    "sg:address":"48 Lansdowne St W",
    "sg:city":"Peterborough",
    "sg:classifiers":[
        {
            "category":"Autos & Motor Vehicles",
            "subcategory":"Automobile Sales",
            "type":"Retail Goods"
        }
    ],
    "sg:phone":"+1 705 742 1150",
    "sg:postcode":"K9J 1Y1",
    "sg:province":"ON",
    "sg:tags":[
        "car",
        "dealer"
    ],
    "wof:name":"Del Mastro Motors",
    "wof:placetype":"venue"
},
  "geometry": {"coordinates":[-78.311211,44.290558],"type":"Point"}
}