{
  "type": "Feature",
  "properties": {
    "addr:full":"Oakville ON L6K 2E4",
    "addr:postcode":"l6k 2e4",
    "iso:country":"CA",
    "sg:city":"Oakville",
    "sg:classifiers":[
        {
            "category":"Retail",
            "subcategory":"Repair Shop",
            "type":"Services"
        }
    ],
    "sg:phone":"+1 905 842 1139",
    "sg:postcode":"L6K 2E4",
    "sg:province":"ON",
    "sg:tags":[
        "restoring",
        "furniture"
    ],
    "wof:name":"Bailey's Refinishing",
    "wof:placetype":"venue"
},
  "geometry": {"coordinates":[-79.68566894529999,43.4485321045],"type":"Point"}
}