{
  "type": "Feature",
  "properties": {
    "iso:country":"CA",
    "sg:address":"9555 Av Illinois",
    "sg:city":"Brossard",
    "sg:classifiers":[
        {
            "category":"Building & Trades",
            "subcategory":"Construction",
            "type":"Services"
        }
    ],
    "sg:phone":"+1 450 659 5376",
    "sg:postcode":"J4Y 3A5",
    "sg:province":"QC",
    "sg:tags":[
        "excavating",
        "contractor"
    ],
    "wof:name":"Sols Brossard Ltee",
    "wof:placetype":"venue"
},
  "geometry": {"coordinates":[-73.469025,45.42873],"type":"Point"}
}