{
  "type": "Feature",
  "properties": {
    "addr:full":"2724 Beverly St Duncan BC V9L 5C7",
    "addr:housenumber":"2724",
    "addr:postcode":"v9l 5c7",
    "addr:street":"Beverly St",
    "iso:country":"CA",
    "sg:address":"2724 Beverly St",
    "sg:city":"Duncan",
    "sg:classifiers":[
        {
            "category":"Autos & Motor Vehicles",
            "subcategory":"Auto Supplies",
            "type":"Retail Goods"
        }
    ],
    "sg:phone":"+1 250 748 0161",
    "sg:postcode":"V9L 5C7",
    "sg:province":"BC",
    "sg:tags":[
        "repairing",
        "automobile",
        "parts"
    ],
    "wof:name":"Canadian Tire",
    "wof:placetype":"venue"
},
  "geometry": {"coordinates":[-123.708527,48.784664],"type":"Point"}
}