{
  "type": "Feature",
  "properties": {
    "addr:full":"500 Rexdale Blvd Etobicoke ON M9W 6K5",
    "addr:housenumber":"500",
    "addr:postcode":"m9w 6k5",
    "addr:street":"Rexdale Blvd",
    "iso:country":"CA",
    "sg:address":"500 Rexdale Blvd",
    "sg:city":"Etobicoke",
    "sg:classifiers":[
        {
            "category":"Shopping",
            "subcategory":"Gifts & Souvenirs",
            "type":"Retail Goods"
        }
    ],
    "sg:phone":"+1 416 674 5735",
    "sg:postcode":"M9W 6K5",
    "sg:province":"ON",
    "sg:tags":[
        "shop",
        "engraver"
    ],
    "wof:name":"Key Man Engravables",
    "wof:placetype":"venue"
},
  "geometry": {"coordinates":[-79.597084,43.717823],"type":"Point"}
}