{
  "type": "Feature",
  "properties": {
    "addr:full":"Surrey BC V3T 2W1",
    "addr:postcode":"v3t 2w1",
    "iso:country":"CA",
    "sg:city":"Surrey",
    "sg:classifiers":[
        {
            "category":"Personal",
            "subcategory":"Beauty Salon",
            "type":"Services"
        }
    ],
    "sg:phone":"+1 604 589 0067",
    "sg:postcode":"V3T 2W1",
    "sg:province":"BC",
    "wof:name":"Attraction Barber & Hair Style",
    "wof:placetype":"venue"
},
  "geometry": {"coordinates":[-122.830215454,49.105178833],"type":"Point"}
}