{
  "type": "Feature",
  "properties": {
    "iso:country":"CA",
    "sg:address":"251 Hanlan Rd",
    "sg:city":"Woodbridge",
    "sg:classifiers":[
        {
            "category":"Professional",
            "subcategory":"Advertising",
            "type":"Services"
        }
    ],
    "sg:phone":"+1 905 851 7319",
    "sg:postcode":"L4L 3R7",
    "sg:province":"ON",
    "sg:tags":[
        "designer",
        "display",
        "producer"
    ],
    "wof:name":"R Guidolin Industries Ltd",
    "wof:placetype":"venue"
},
  "geometry": {"coordinates":[-79.559219,43.769962],"type":"Point"}
}