{
  "type": "Feature",
  "properties": {
    "addr:full":"475 Richmond Rd Ottawa ON K2A 3Y8",
    "addr:housenumber":"475",
    "addr:postcode":"k2a 3y8",
    "addr:street":"Richmond Rd",
    "iso:country":"CA",
    "sg:address":"475 Richmond Rd",
    "sg:city":"Ottawa",
    "sg:classifiers":[
        {
            "category":"Utilities",
            "subcategory":"Cable",
            "type":"Services"
        }
    ],
    "sg:phone":"+1 613 728 2222",
    "sg:postcode":"K2A 3Y8",
    "sg:province":"ON",
    "sg:tags":[
        "television"
    ],
    "wof:name":"Roger Community 22",
    "wof:placetype":"venue"
},
  "geometry": {"coordinates":[-75.7596664429,45.389213562],"type":"Point"}
}