{
  "type": "Feature",
  "properties": {
    "addr:full":"572 Artisan Lane Bowen Island BC V0N 1G0",
    "addr:housenumber":"572",
    "addr:postcode":"v0n 1g0",
    "addr:street":"Artisan Lane",
    "iso:country":"CA",
    "sg:address":"572 Artisan Lane",
    "sg:city":"Bowen Island",
    "sg:classifiers":[
        {
            "category":"Home & Garden",
            "subcategory":"Carpets & Floor Coverings",
            "type":"Retail Goods"
        }
    ],
    "sg:phone":"+1 604 947 2088",
    "sg:postcode":"V0N 1G0",
    "sg:province":"BC",
    "sg:tags":[
        "dealer",
        "rug"
    ],
    "wof:name":"Bowen Island Interiors",
    "wof:placetype":"venue"
},
  "geometry": {"coordinates":[-123.345039368,49.3804397583],"type":"Point"}
}