{
  "type": "Feature",
  "properties": {
    "addr:full":"Okotoks AB T1S 1A4",
    "addr:postcode":"t1s 1a4",
    "iso:country":"CA",
    "sg:city":"Okotoks",
    "sg:classifiers":[
        {
            "category":"Wholesale",
            "subcategory":"Farm Supplies",
            "type":"Manufacturing & Wholesale Goods"
        }
    ],
    "sg:phone":"+1 403 995 0562",
    "sg:postcode":"T1S 1A4",
    "sg:province":"AB",
    "sg:tags":[
        "equipment",
        "livestock"
    ],
    "wof:name":"Chinook Stalls",
    "wof:placetype":"venue"
},
  "geometry": {"coordinates":[-113.976585,50.724579],"type":"Point"}
}