{
  "type": "Feature",
  "properties": {
    "iso:country":"CA",
    "sg:city":"Woodbridge",
    "sg:classifiers":[
        {
            "category":"Building & Trades",
            "subcategory":"Construction",
            "type":"Services"
        }
    ],
    "sg:phone":"+1 905 851 6402",
    "sg:postcode":"L4L 8K5",
    "sg:province":"ON",
    "sg:tags":[
        "general",
        "contractor"
    ],
    "wof:name":"Bian Bel & Assoc Ltd",
    "wof:placetype":"venue"
},
  "geometry": {"coordinates":[-79.60424,43.77417],"type":"Point"}
}