{
  "type": "Feature",
  "properties": {
    "addr:full":"715 Boul Tache O Montmagny QC G5V 3R8",
    "addr:housenumber":"715",
    "addr:postcode":"g5v 3r8",
    "addr:street":"Boul Tache O",
    "iso:country":"CA",
    "sg:address":"715 Boul Tache O",
    "sg:city":"Montmagny",
    "sg:classifiers":[
        {
            "category":"Organizations",
            "subcategory":"Professional Association",
            "type":"Services"
        }
    ],
    "sg:phone":"+1 418 248 4906",
    "sg:postcode":"G5V 3R8",
    "sg:province":"QC",
    "wof:name":"Temoins DE Jehovah",
    "wof:placetype":"venue"
},
  "geometry": {"coordinates":[-70.6525878906,46.9528999329],"type":"Point"}
}