{
  "type": "Feature",
  "properties": {
    "addr:full":"186 Main St Plaster Rock NB E7G 2E3",
    "addr:housenumber":"186",
    "addr:postcode":"e7g 2e3",
    "addr:street":"Main St",
    "iso:country":"CA",
    "sg:address":"186 Main St",
    "sg:city":"Plaster Rock",
    "sg:classifiers":[
        {
            "category":"Retail",
            "subcategory":"Auto Repair",
            "type":"Services"
        }
    ],
    "sg:phone":"+1 506 356 2944",
    "sg:postcode":"E7G 2E3",
    "sg:province":"NB",
    "sg:tags":[
        "wrecker"
    ],
    "wof:name":"Green Brothers Garage Ltd",
    "wof:placetype":"venue"
},
  "geometry": {"coordinates":[-67.3949432373,46.9002418518],"type":"Point"}
}