{
  "type": "Feature",
  "properties": {
    "addr:full":"Edmonton AB T6E 5Y1",
    "addr:postcode":"t6e 5y1",
    "iso:country":"CA",
    "sg:city":"Edmonton",
    "sg:classifiers":[
        {
            "category":"Insurance",
            "subcategory":"Insurance Agent",
            "type":"Services"
        }
    ],
    "sg:phone":"+1 780 433 0052",
    "sg:postcode":"T6E 5Y1",
    "sg:province":"AB",
    "wof:name":"Trans West Insurance",
    "wof:placetype":"venue"
},
  "geometry": {"coordinates":[-113.471085,53.468449],"type":"Point"}
}