{
  "type": "Feature",
  "properties": {
    "iso:country":"CA",
    "sg:address":"4840 Boul DE LA Rive-Sud",
    "sg:city":"Levis",
    "sg:classifiers":[
        {
            "category":"Wholesale",
            "subcategory":"Electrical",
            "type":"Manufacturing & Wholesale Goods"
        }
    ],
    "sg:phone":"+1 418 837 7618",
    "sg:postcode":"G6W 5N6",
    "sg:province":"QC",
    "sg:tags":[
        "repairing",
        "automobile"
    ],
    "wof:name":"Batteries Metivier Inc",
    "wof:placetype":"venue"
},
  "geometry": {"coordinates":[-71.18700408940001,46.7878952026],"type":"Point"}
}