{
  "type": "Feature",
  "properties": {
    "addr:full":"1419 Rue Saint-Clement Montreal QC H1V 3E1",
    "addr:housenumber":"1419",
    "addr:postcode":"h1v 3e1",
    "addr:street":"Rue Saint-Clement",
    "iso:country":"CA",
    "sg:address":"1419 Rue Saint-Clement",
    "sg:city":"Montreal",
    "sg:classifiers":[
        {
            "category":"Building & Trades",
            "subcategory":"Construction",
            "type":"Services"
        }
    ],
    "sg:phone":"+1 514 251 9972",
    "sg:postcode":"H1V 3E1",
    "sg:province":"QC",
    "sg:tags":[
        "contractor"
    ],
    "wof:name":"Serge Nadeau Construction",
    "wof:placetype":"venue"
},
  "geometry": {"coordinates":[-73.5304031372,45.5568466187],"type":"Point"}
}