{
  "type": "Feature",
  "properties": {
    "addr:full":"2333 18 Ave NE Calgary AB T2E 8T6",
    "addr:housenumber":"2333",
    "addr:postcode":"t2e 8t6",
    "addr:street":"18 Ave Ne",
    "iso:country":"CA",
    "sg:address":"2333 18 Ave NE",
    "sg:city":"Calgary",
    "sg:classifiers":[
        {
            "category":"Personal",
            "type":"Services"
        }
    ],
    "sg:phone":"+1 403 250 8160",
    "sg:postcode":"T2E 8T6",
    "sg:province":"AB",
    "sg:tags":[
        "department",
        "motor",
        "license",
        "vehicle"
    ],
    "wof:name":"Provincial Registry Svc Ctr",
    "wof:placetype":"venue"
},
  "geometry": {"coordinates":[-114.006820679,51.0687141418],"type":"Point"}
}