{
  "type": "Feature",
  "properties": {
    "addr:full":"Montreal QC H3A 1K2",
    "addr:postcode":"h3a 1k2",
    "iso:country":"CA",
    "sg:city":"Montreal",
    "sg:classifiers":[
        {
            "category":"Professional",
            "subcategory":"Business Services",
            "type":"Services"
        }
    ],
    "sg:phone":"+1 514 878 2563",
    "sg:postcode":"H3A 1K2",
    "sg:province":"QC",
    "sg:tags":[
        "consultant",
        "petroleum"
    ],
    "wof:name":"Reiter Petroleum Inc",
    "wof:placetype":"venue"
},
  "geometry": {"coordinates":[-73.572281,45.504887],"type":"Point"}
}