{
  "type": "Feature",
  "properties": {
    "addr:full":"Toronto ON M5M 4M1",
    "addr:postcode":"m5m 4m1",
    "iso:country":"CA",
    "sg:city":"Toronto",
    "sg:classifiers":[
        {
            "category":"Health Services",
            "subcategory":"Health Practitioner",
            "type":"Services"
        }
    ],
    "sg:phone":"+1 416 783 3606",
    "sg:postcode":"M5M 4M1",
    "sg:province":"ON",
    "sg:tags":[
        "psychologist"
    ],
    "wof:name":"Ford & Assoc",
    "wof:placetype":"venue"
},
  "geometry": {"coordinates":[-79.41443599999999,43.72253],"type":"Point"}
}