{
  "type": "Feature",
  "properties": {
    "addr:full":"362 Erin Trail Newmarket ON L3Y 6K1",
    "addr:housenumber":"362",
    "addr:postcode":"l3y 6k1",
    "addr:street":"Erin Trail",
    "iso:country":"CA",
    "sg:address":"362 Erin Trail",
    "sg:city":"Newmarket",
    "sg:classifiers":[
        {
            "category":"Professional",
            "subcategory":"Business Services",
            "type":"Services"
        }
    ],
    "sg:phone":"+1 905 868 9316",
    "sg:postcode":"L3Y 6K1",
    "sg:province":"ON",
    "sg:tags":[
        "inspection"
    ],
    "wof:name":"Inspection Support Svc",
    "wof:placetype":"venue"
},
  "geometry": {"coordinates":[-79.461136,44.072472],"type":"Point"}
}