{
  "type": "Feature",
  "properties": {
    "iso:country":"CA",
    "sg:address":"1111 Pembroke St W",
    "sg:city":"Pembroke",
    "sg:classifiers":[
        {
            "category":"Health Services",
            "subcategory":"Nursing And Care Facility",
            "type":"Services"
        }
    ],
    "sg:phone":"+1 613 635 7926",
    "sg:postcode":"K8A 5R3",
    "sg:province":"ON",
    "sg:tags":[
        "home",
        "retirement",
        "community"
    ],
    "wof:name":"Heritage Manor",
    "wof:placetype":"venue"
},
  "geometry": {"coordinates":[-77.14292907710001,45.8315467834],"type":"Point"}
}