{
  "type": "Feature",
  "properties": {
    "addr:full":"12606 Stony Plain Rd NW Edmonton AB T5N 3N7",
    "addr:housenumber":"12606",
    "addr:postcode":"t5n 3n7",
    "addr:street":"Stony Plain Rd Nw",
    "iso:country":"CA",
    "sg:address":"12606 Stony Plain Rd NW",
    "sg:city":"Edmonton",
    "sg:classifiers":[
        {
            "category":"Shopping",
            "subcategory":"Used Merchandise",
            "type":"Retail Goods"
        }
    ],
    "sg:phone":"+1 780 453 2935",
    "sg:postcode":"T5N 3N7",
    "sg:province":"AB",
    "sg:tags":[
        "infant",
        "wear"
    ],
    "wof:name":"Boy Girl Rewear",
    "wof:placetype":"venue"
},
  "geometry": {"coordinates":[-113.539672852,53.5474967957],"type":"Point"}
}