{
  "type": "Feature",
  "properties": {
    "addr:full":"6456 Boul Saint-Laurent Montreal QC H2S 3C4",
    "addr:housenumber":"6456",
    "addr:postcode":"h2s 3c4",
    "addr:street":"Boul Saint-Laurent",
    "iso:country":"CA",
    "sg:address":"6456 Boul Saint-Laurent",
    "sg:city":"Montreal",
    "sg:classifiers":[
        {
            "category":"Shopping",
            "subcategory":"Used Merchandise",
            "type":"Retail Goods"
        }
    ],
    "sg:phone":"+1 514 277 1402",
    "sg:postcode":"H2S 3C4",
    "sg:province":"QC",
    "sg:tags":[
        "pawnbroker"
    ],
    "wof:name":"Pretons Comtant",
    "wof:placetype":"venue"
},
  "geometry": {"coordinates":[-73.6089553833,45.5302734375],"type":"Point"}
}