{
  "type": "Feature",
  "properties": {
    "iso:country":"CA",
    "sg:address":"4708 151 St NW",
    "sg:city":"Edmonton",
    "sg:classifiers":[
        {
            "category":"Professional",
            "subcategory":"Computer Services",
            "type":"Services"
        }
    ],
    "sg:phone":"+1 780 430 8946",
    "sg:postcode":"T6H 5N8",
    "sg:province":"AB",
    "sg:tags":[
        "consultant"
    ],
    "wof:name":"Csp Consulting Ltd",
    "wof:placetype":"venue"
},
  "geometry": {"coordinates":[-113.580604553,53.4855651855],"type":"Point"}
}