{
  "type": "Feature",
  "properties": {
    "addr:full":"1820 14 Ave NE # 32 Calgary AB T2E 1G6",
    "addr:housenumber":"1820",
    "addr:postcode":"t2e 1g6",
    "addr:street":"14 Ave Ne # 32",
    "iso:country":"CA",
    "sg:address":"1820 14 Ave NE # 32",
    "sg:city":"Calgary",
    "sg:classifiers":[
        {
            "category":"Real Estate",
            "subcategory":"Real Estate Operator",
            "type":"Services"
        }
    ],
    "sg:phone":"+1 403 215 9401",
    "sg:postcode":"T2E 1G6",
    "sg:province":"AB",
    "sg:tags":[
        "apartment"
    ],
    "wof:name":"Cedar Court Gardens",
    "wof:placetype":"venue"
},
  "geometry": {"coordinates":[-114.01593800000001,51.065544],"type":"Point"}
}