{
  "type": "Feature",
  "properties": {
    "addr:full":"2600 Rang Du Ruisseau Sainte-Elisabeth QC J0K 2J0",
    "addr:housenumber":"2600",
    "addr:postcode":"j0k 2j0",
    "addr:street":"Rang Du Ruisseau Sainte-Elisabeth",
    "iso:country":"CA",
    "sg:address":"2600 Rang Du Ruisseau",
    "sg:city":"Sainte-Elisabeth",
    "sg:classifiers":[
        {
            "category":"Building & Trades",
            "subcategory":"Construction",
            "type":"Services"
        }
    ],
    "sg:phone":"+1 450 756 0623",
    "sg:postcode":"J0K 2J0",
    "sg:province":"QC",
    "sg:tags":[
        "general",
        "contractor"
    ],
    "wof:name":"Construction Michel Harnois",
    "wof:placetype":"venue"
},
  "geometry": {"coordinates":[-73.365036,46.094231],"type":"Point"}
}