{
  "type": "Feature",
  "properties": {
    "addr:full":"255 Durham St Kincardine ON N2Z 2X9",
    "addr:housenumber":"255",
    "addr:postcode":"n2z 2x9",
    "addr:street":"Durham St",
    "iso:country":"CA",
    "sg:address":"255 Durham St",
    "sg:city":"Kincardine",
    "sg:classifiers":[
        {
            "category":"Health Services",
            "subcategory":"Nursing And Care Facility",
            "type":"Services"
        }
    ],
    "sg:phone":"+1 519 396 5800",
    "sg:postcode":"N2Z 2X9",
    "sg:province":"ON",
    "sg:tags":[
        "home",
        "retirement",
        "community",
        "rest"
    ],
    "wof:name":"Malcolm Place Retirement Rsdnc",
    "wof:placetype":"venue"
},
  "geometry": {"coordinates":[-81.635216,44.179562],"type":"Point"}
}