{
  "type": "Feature",
  "properties": {
    "addr:full":"55 Upper Canada Dr Kitchener ON N2P 1G2",
    "addr:housenumber":"55",
    "addr:postcode":"n2p 1g2",
    "addr:street":"Upper Canada Dr",
    "iso:country":"CA",
    "sg:address":"55 Upper Canada Dr",
    "sg:city":"Kitchener",
    "sg:classifiers":[
        {
            "category":"Education",
            "subcategory":"School",
            "type":"Public Place"
        }
    ],
    "sg:phone":"+1 519 748 0142",
    "sg:postcode":"N2P 1G2",
    "sg:province":"ON",
    "wof:name":"Pioneer Park Public School",
    "wof:placetype":"venue"
},
  "geometry": {"coordinates":[-80.44380187989999,43.3974189758],"type":"Point"}
}