{
  "type": "Feature",
  "properties": {
    "addr:full":"126 Rue Sherbrooke O Thetford Mines QC G6G 5R2",
    "addr:housenumber":"126",
    "addr:postcode":"g6g 5r2",
    "addr:street":"Rue Sherbrooke O",
    "iso:country":"CA",
    "sg:address":"126 Rue Sherbrooke O",
    "sg:city":"Thetford Mines",
    "sg:classifiers":[
        {
            "category":"Retail",
            "subcategory":"Auto Repair",
            "type":"Services"
        }
    ],
    "sg:phone":"+1 418 335 5758",
    "sg:postcode":"G6G 5R2",
    "sg:province":"QC",
    "sg:tags":[
        "repairing",
        "automobile"
    ],
    "wof:name":"Garage Normand Libre Svc",
    "wof:placetype":"venue"
},
  "geometry": {"coordinates":[-71.2596740723,46.1177940369],"type":"Point"}
}