{
  "type": "Feature",
  "properties": {
    "addr:full":"Dundalk ON N0C 1B0",
    "addr:postcode":"n0c 1b0",
    "iso:country":"CA",
    "sg:city":"Dundalk",
    "sg:classifiers":[
        {
            "category":"Building & Trades",
            "subcategory":"Construction",
            "type":"Services"
        }
    ],
    "sg:phone":"+1 519 923 3130",
    "sg:postcode":"N0C 1B0",
    "sg:province":"ON",
    "sg:tags":[
        "excavating",
        "contractor"
    ],
    "wof:name":"K W Mather & Sons Ltd",
    "wof:placetype":"venue"
},
  "geometry": {"coordinates":[-80.391327,44.16967],"type":"Point"}
}