{
  "type": "Feature",
  "properties": {
    "addr:full":"St Catharines ON L2R 4M8",
    "addr:postcode":"l2r 4m8",
    "iso:country":"CA",
    "sg:city":"St Catharines",
    "sg:classifiers":[
        {
            "category":"Personal",
            "subcategory":"Beauty Salon",
            "type":"Services"
        }
    ],
    "sg:phone":"+1 905 684 0450",
    "sg:postcode":"L2R 4M8",
    "sg:province":"ON",
    "wof:name":"Vincent Hair Stylist",
    "wof:placetype":"venue"
},
  "geometry": {"coordinates":[-79.2399902344,43.1642150879],"type":"Point"}
}