{
  "type": "Feature",
  "properties": {
    "addr:full":"192 Dinsley St W Blyth ON N0M 1H0",
    "addr:housenumber":"192",
    "addr:postcode":"n0m 1h0",
    "addr:street":"Dinsley St W",
    "iso:country":"CA",
    "sg:address":"192 Dinsley St W",
    "sg:city":"Blyth",
    "sg:classifiers":[
        {
            "category":"Social Services",
            "type":"Services"
        }
    ],
    "sg:phone":"+1 519 523 9535",
    "sg:postcode":"N0M 1H0",
    "sg:province":"ON",
    "sg:tags":[
        "organization",
        "welfare"
    ],
    "wof:name":"Royal Canadian Legion",
    "wof:placetype":"venue"
},
  "geometry": {"coordinates":[-81.429726,43.736782],"type":"Point"}
}