{
  "type": "Feature",
  "properties": {
    "addr:full":"475 St Patrick St W Fergus ON N1M 1M2",
    "addr:housenumber":"475",
    "addr:postcode":"n1m 1m2",
    "addr:street":"St Patrick St W",
    "iso:country":"CA",
    "sg:address":"475 St Patrick St W",
    "sg:city":"Fergus",
    "sg:classifiers":[
        {
            "category":"Communications",
            "subcategory":"Television Station",
            "type":"Services"
        }
    ],
    "sg:phone":"+1 519 843 3700",
    "sg:postcode":"N1M 1M2",
    "sg:province":"ON",
    "sg:tags":[
        "broadcasting",
        "co"
    ],
    "wof:name":"Cogeco Cable Solutions",
    "wof:placetype":"venue"
},
  "geometry": {"coordinates":[-80.38221,43.702263],"type":"Point"}
}