{
  "type": "Feature",
  "properties": {
    "addr:full":"12 Durham St E Lindsay ON K9V 1W7",
    "addr:housenumber":"12",
    "addr:postcode":"k9v 1w7",
    "addr:street":"Durham St",
    "iso:country":"CA",
    "sg:address":"12 Durham St E",
    "sg:city":"Lindsay",
    "sg:classifiers":[
        {
            "category":"Home & Garden",
            "subcategory":"Building Materials",
            "type":"Retail Goods"
        }
    ],
    "sg:phone":"+1 705 324 8360",
    "sg:postcode":"K9V 1W7",
    "sg:province":"ON",
    "sg:tags":[
        "glass",
        "window",
        "plate"
    ],
    "wof:name":"Doc's Auto Glass",
    "wof:placetype":"venue"
},
  "geometry": {"coordinates":[-78.73090362550001,44.3508682251],"type":"Point"}
}