{
  "type": "Feature",
  "properties": {
    "addr:full":"4150 Finch Ave E Scarborough ON M1S 3T9",
    "addr:housenumber":"4150",
    "addr:postcode":"m1s 3t9",
    "addr:street":"Finch Ave E",
    "iso:country":"CA",
    "sg:address":"4150 Finch Ave E",
    "sg:city":"Scarborough",
    "sg:classifiers":[
        {
            "category":"Retail",
            "subcategory":"Auto Rental",
            "type":"Services"
        }
    ],
    "sg:phone":"+1 416 293 3110",
    "sg:postcode":"M1S 3T9",
    "sg:province":"ON",
    "sg:tags":[
        "renting",
        "automobile"
    ],
    "wof:name":"Hertz Rent A Car",
    "wof:placetype":"venue"
},
  "geometry": {"coordinates":[-79.289497,43.803162],"type":"Point"}
}