{
  "type": "Feature",
  "properties": {
    "addr:full":"373 Main St Kentville NS B4N 1K7",
    "addr:housenumber":"373",
    "addr:postcode":"b4n 1k7",
    "addr:street":"Main St",
    "iso:country":"CA",
    "sg:address":"373 Main St",
    "sg:city":"Kentville",
    "sg:classifiers":[
        {
            "category":"Shopping",
            "subcategory":"Florist",
            "type":"Retail Goods"
        }
    ],
    "sg:phone":"+1 902 678 4728",
    "sg:postcode":"B4N 1K7",
    "sg:province":"NS",
    "wof:name":"Pulsifer Flowers & Foliage",
    "wof:placetype":"venue"
},
  "geometry": {"coordinates":[-64.490517,45.075756],"type":"Point"}
}