{
  "type": "Feature",
  "properties": {
    "iso:country":"CA",
    "sg:address":"400 Boul Laure",
    "sg:city":"Sept-Iles",
    "sg:classifiers":[
        {
            "category":"Wholesale",
            "subcategory":"Machinery & Supplies",
            "type":"Manufacturing & Wholesale Goods"
        }
    ],
    "sg:phone":"+1 418 962 7791",
    "sg:postcode":"G4R 1X4",
    "sg:province":"QC",
    "sg:tags":[
        "contractor"
    ],
    "wof:name":"Hewitt Equipement Ltee",
    "wof:placetype":"venue"
},
  "geometry": {"coordinates":[-66.3726272583,50.2110595703],"type":"Point"}
}