{
  "type": "Feature",
  "properties": {
    "iso:country":"CA",
    "sg:address":"8244 Rte 6",
    "sg:city":"Pugwash",
    "sg:classifiers":[
        {
            "category":"Restaurant",
            "type":"Food & Drink"
        }
    ],
    "sg:phone":"+1 902 243 2859",
    "sg:postcode":"B0K 1L0",
    "sg:province":"NS",
    "wof:name":"Sandpiper Restaurant",
    "wof:placetype":"venue"
},
  "geometry": {"coordinates":[-63.6545524597,45.8505821228],"type":"Point"}
}