{
  "type": "Feature",
  "properties": {
    "addr:full":"7034 Tecumseh Rd E Windsor ON N8T 1E6",
    "addr:housenumber":"7034",
    "addr:postcode":"n8t 1e6",
    "addr:street":"Tecumseh Rd E",
    "iso:country":"CA",
    "sg:address":"7034 Tecumseh Rd E",
    "sg:city":"Windsor",
    "sg:classifiers":[
        {
            "category":"Food & Beverages",
            "subcategory":"Groceries & Convenience Stores",
            "type":"Retail Goods"
        }
    ],
    "sg:phone":"+1 519 798 3029",
    "sg:postcode":"N8T 1E6",
    "sg:province":"ON",
    "sg:tags":[
        "grocer"
    ],
    "wof:name":"Stoney Point Supermarket",
    "wof:placetype":"venue"
},
  "geometry": {"coordinates":[-82.9425354004,42.312335968],"type":"Point"}
}