{
  "type": "Feature",
  "properties": {
    "iso:country":"CA",
    "sg:address":"501 Gladstone Ave",
    "sg:city":"Ottawa",
    "sg:classifiers":[
        {
            "category":"Manufacturing",
            "subcategory":"Electronics",
            "type":"Manufacturing & Wholesale Goods"
        }
    ],
    "sg:phone":"+1 613 567 1152",
    "sg:postcode":"K1R 5N9",
    "sg:province":"ON",
    "sg:tags":[
        "communication",
        "television",
        "radio"
    ],
    "wof:name":"Electro Pulse",
    "wof:placetype":"venue"
},
  "geometry": {"coordinates":[-75.6981582642,45.4104194641],"type":"Point"}
}