{
  "type": "Feature",
  "properties": {
    "addr:full":"340 Saskatoon St London ON N5W 4R3",
    "addr:housenumber":"340",
    "addr:postcode":"n5w 4r3",
    "addr:street":"Saskatoon St",
    "iso:country":"CA",
    "sg:address":"340 Saskatoon St",
    "sg:city":"London",
    "sg:classifiers":[
        {
            "category":"Professional",
            "subcategory":"Research",
            "type":"Services"
        }
    ],
    "sg:phone":"+1 519 457 0878",
    "sg:postcode":"N5W 4R3",
    "sg:province":"ON",
    "sg:tags":[
        "development",
        "electronic"
    ],
    "wof:name":"Oci Vacuum Microengineering",
    "wof:placetype":"venue"
},
  "geometry": {"coordinates":[-81.187416,42.998016],"type":"Point"}
}