{
  "type": "Feature",
  "properties": {
    "addr:full":"Toronto ON M4M 1Y2",
    "addr:postcode":"m4m 1y2",
    "iso:country":"CA",
    "sg:city":"Toronto",
    "sg:classifiers":[
        {
            "category":"Health Services",
            "subcategory":"Health Practitioner",
            "type":"Services"
        }
    ],
    "sg:phone":"+1 416 466 8638",
    "sg:postcode":"M4M 1Y2",
    "sg:province":"ON",
    "sg:tags":[
        "acupuncture"
    ],
    "wof:name":"Chen's Acupuncture & Herbs",
    "wof:placetype":"venue"
},
  "geometry": {"coordinates":[-79.3519897461,43.6654434204],"type":"Point"}
}