{
  "type": "Feature",
  "properties": {
    "addr:full":"1553 Jane St North York ON M9N 2R3",
    "addr:housenumber":"1553",
    "addr:postcode":"m9n 2r3",
    "addr:street":"Jane St",
    "iso:country":"CA",
    "sg:address":"1553 Jane St",
    "sg:city":"North York",
    "sg:classifiers":[
        {
            "category":"Retail",
            "subcategory":"Laundry & Dry Cleaning",
            "type":"Services"
        }
    ],
    "sg:phone":"+1 416 244 9392",
    "sg:postcode":"M9N 2R3",
    "sg:province":"ON",
    "sg:tags":[
        "cleaners"
    ],
    "wof:name":"Trethewey Cleaners",
    "wof:placetype":"venue"
},
  "geometry": {"coordinates":[-79.50251,43.698826],"type":"Point"}
}