{
  "type": "Feature",
  "properties": {
    "iso:country":"CA",
    "sg:city":"Montreal",
    "sg:classifiers":[
        {
            "category":"Health Services",
            "subcategory":"Doctor",
            "type":"Services"
        }
    ],
    "sg:phone":"+1 514 487 1463",
    "sg:postcode":"H4A 1H1",
    "sg:province":"QC",
    "sg:tags":[
        "clinic",
        "dentist"
    ],
    "wof:name":"A LA Clinique Dentaire Duc",
    "wof:placetype":"venue"
},
  "geometry": {"coordinates":[-73.626701,45.471573],"type":"Point"}
}