{
  "type": "Feature",
  "properties": {
    "addr:full":"19 Riverside Dr Kapuskasing ON P5N 1A4",
    "addr:housenumber":"19",
    "addr:postcode":"p5n 1a4",
    "addr:street":"Riverside Dr",
    "iso:country":"CA",
    "sg:address":"19 Riverside Dr",
    "sg:city":"Kapuskasing",
    "sg:classifiers":[
        {
            "category":"Insurance",
            "subcategory":"Insurance Agent",
            "type":"Services"
        }
    ],
    "sg:phone":"+1 705 335 8546",
    "sg:postcode":"P5N 1A4",
    "sg:province":"ON",
    "wof:name":"Industrial Alliance Insurance",
    "wof:placetype":"venue"
},
  "geometry": {"coordinates":[-82.421257,49.414227],"type":"Point"}
}