{
  "type": "Feature",
  "properties": {
    "addr:full":"23 Alderdale Crt North York ON M3B 2H8",
    "addr:housenumber":"23",
    "addr:postcode":"m3b 2h8",
    "addr:street":"Alderdale Crt",
    "iso:country":"CA",
    "sg:address":"23 Alderdale Crt",
    "sg:city":"North York",
    "sg:classifiers":[
        {
            "category":"Building & Trades",
            "subcategory":"Construction",
            "type":"Services"
        }
    ],
    "sg:phone":"+1 416 449 6204",
    "sg:postcode":"M3B 2H8",
    "sg:province":"ON",
    "sg:tags":[
        "painter"
    ],
    "wof:name":"Performance Painters",
    "wof:placetype":"venue"
},
  "geometry": {"coordinates":[-79.361923,43.749081],"type":"Point"}
}