{
  "type": "Feature",
  "properties": {
    "addr:full":"225 16th St West Vancouver BC V7V 3R6",
    "addr:housenumber":"225",
    "addr:postcode":"v7v 3r6",
    "addr:street":"16Th St",
    "iso:country":"CA",
    "sg:address":"225 16th St",
    "sg:city":"West Vancouver",
    "sg:classifiers":[
        {
            "category":"Personal",
            "subcategory":"Beauty Salon",
            "type":"Services"
        }
    ],
    "sg:phone":"+1 604 922 4467",
    "sg:postcode":"V7V 3R6",
    "sg:province":"BC",
    "wof:name":"Hair By Marianne",
    "wof:placetype":"venue"
},
  "geometry": {"coordinates":[-123.158996582,49.3277893066],"type":"Point"}
}