{
  "type": "Feature",
  "properties": {
    "addr:full":"226 2nd Ave W Hanna AB T0J 1P0",
    "addr:housenumber":"226",
    "addr:postcode":"t0j 1p0",
    "addr:street":"2Nd Ave W",
    "iso:country":"CA",
    "sg:address":"226 2nd Ave W",
    "sg:city":"Hanna",
    "sg:classifiers":[
        {
            "category":"Restaurant",
            "type":"Food & Drink"
        }
    ],
    "sg:phone":"+1 403 854 3424",
    "sg:postcode":"T0J 1P0",
    "sg:province":"AB",
    "wof:name":"Hanna Pizza & Steak House Ltd",
    "wof:placetype":"venue"
},
  "geometry": {"coordinates":[-111.92930603000001,51.6429595947],"type":"Point"}
}