{
  "type": "Feature",
  "properties": {
    "addr:full":"Calgary AB T2X 1P1",
    "addr:postcode":"t2x 1p1",
    "iso:country":"CA",
    "sg:city":"Calgary",
    "sg:classifiers":[
        {
            "category":"Professional",
            "subcategory":"Accounting & Tax Preparation",
            "type":"Services"
        }
    ],
    "sg:phone":"+1 403 254 8689",
    "sg:postcode":"T2X 1P1",
    "sg:province":"AB",
    "sg:tags":[
        "return",
        "filing"
    ],
    "wof:name":"H & R Block Canada Inc",
    "wof:placetype":"venue"
},
  "geometry": {"coordinates":[-114.062637,50.908295],"type":"Point"}
}