{
  "type": "Feature",
  "properties": {
    "addr:full":"King St St Charles ON P0M 2W0",
    "addr:postcode":"p0m 2w0",
    "addr:street":"King St",
    "iso:country":"CA",
    "sg:address":"King St",
    "sg:city":"St Charles",
    "sg:classifiers":[
        {
            "category":"Recreation",
            "type":"Entertainment"
        }
    ],
    "sg:phone":"+1 705 867 2813",
    "sg:postcode":"P0M 2W0",
    "sg:province":"ON",
    "sg:tags":[
        "skating",
        "rink"
    ],
    "wof:name":"St Charles Arena",
    "wof:placetype":"venue"
},
  "geometry": {"coordinates":[-80.4114685059,46.3623466492],"type":"Point"}
}