{
  "type": "Feature",
  "properties": {
    "addr:full":"351 3rd St W North Vancouver BC V7M 1G3",
    "addr:housenumber":"351",
    "addr:postcode":"v7m 1g3",
    "addr:street":"3Rd St W",
    "iso:country":"CA",
    "sg:address":"351 3rd St W",
    "sg:city":"North Vancouver",
    "sg:classifiers":[
        {
            "category":"Autos & Motor Vehicles",
            "subcategory":"Fuel & Gas Station",
            "type":"Retail Goods"
        }
    ],
    "sg:phone":"+1 604 987 3030",
    "sg:postcode":"V7M 1G3",
    "sg:province":"BC",
    "sg:tags":[
        "oil"
    ],
    "wof:name":"Mohawk North Vancouver Svc",
    "wof:placetype":"venue"
},
  "geometry": {"coordinates":[-123.084640503,49.3166236877],"type":"Point"}
}