{
  "type": "Feature",
  "properties": {
    "addr:full":"15 Briggs Rd Lindsay NB E7M 5M8",
    "addr:housenumber":"15",
    "addr:postcode":"e7m 5m8",
    "addr:street":"Briggs Rd",
    "iso:country":"CA",
    "sg:address":"15 Briggs Rd",
    "sg:city":"Lindsay",
    "sg:classifiers":[
        {
            "category":"Organizations",
            "subcategory":"Religious Organization",
            "type":"Services"
        }
    ],
    "sg:phone":"+1 506 328 8310",
    "sg:postcode":"E7M 5M8",
    "sg:province":"NB",
    "sg:tags":[
        "church"
    ],
    "wof:name":"Lindsay Baptist Church",
    "wof:placetype":"venue"
},
  "geometry": {"coordinates":[-67.69951629640001,46.2497444153],"type":"Point"}
}