{
  "type": "Feature",
  "properties": {
    "addr:full":"19 Rue Church Quyon QC J0X 2V0",
    "addr:housenumber":"19",
    "addr:postcode":"j0x 2v0",
    "addr:street":"Rue Church",
    "iso:country":"CA",
    "sg:address":"19 Rue Church",
    "sg:city":"Quyon",
    "sg:classifiers":[
        {
            "category":"Education",
            "subcategory":"School",
            "type":"Public Place"
        }
    ],
    "sg:phone":"+1 819 458 2352",
    "sg:postcode":"J0X 2V0",
    "sg:province":"QC",
    "wof:name":"Ecole Sainte-Marie",
    "wof:placetype":"venue"
},
  "geometry": {"coordinates":[-76.2322387695,45.518901825],"type":"Point"}
}