{
  "type": "Feature",
  "properties": {
    "addr:full":"Calgary AB T2E 4R1",
    "addr:postcode":"t2e 4r1",
    "iso:country":"CA",
    "sg:city":"Calgary",
    "sg:classifiers":[
        {
            "category":"Manufacturing",
            "subcategory":"Signs",
            "type":"Manufacturing & Wholesale Goods"
        }
    ],
    "sg:phone":"+1 403 250 1331",
    "sg:postcode":"T2E 4R1",
    "sg:province":"AB",
    "wof:name":"Signs For Less",
    "wof:placetype":"venue"
},
  "geometry": {"coordinates":[-114.033638001,51.0921936035],"type":"Point"}
}