{
  "type": "Feature",
  "properties": {
    "addr:full":"45 Stag Hill Dr East York ON M4B 1K9",
    "addr:housenumber":"45",
    "addr:postcode":"m4b 1k9",
    "addr:street":"Stag Hill Dr",
    "iso:country":"CA",
    "sg:address":"45 Stag Hill Dr",
    "sg:city":"East York",
    "sg:classifiers":[
        {
            "category":"Building & Trades",
            "subcategory":"Construction",
            "type":"Services"
        }
    ],
    "sg:phone":"+1 416 751 7440",
    "sg:postcode":"M4B 1K9",
    "sg:province":"ON",
    "sg:tags":[
        "home",
        "improvement"
    ],
    "wof:name":"Crown Construction",
    "wof:placetype":"venue"
},
  "geometry": {"coordinates":[-79.30866241459999,43.7045516968],"type":"Point"}
}