{
  "type": "Feature",
  "properties": {
    "addr:full":"215 Rue Principale Saint-Cyprien QC G0L 2P0",
    "addr:housenumber":"215",
    "addr:postcode":"g0l 2p0",
    "addr:street":"Rue Principale",
    "iso:country":"CA",
    "sg:address":"215 Rue Principale",
    "sg:city":"Saint-Cyprien",
    "sg:classifiers":[
        {
            "category":"Bars & Pubs",
            "type":"Food & Drink"
        }
    ],
    "sg:phone":"+1 418 963 6634",
    "sg:postcode":"G0L 2P0",
    "sg:province":"QC",
    "sg:tags":[
        "lounge",
        "cocktail"
    ],
    "wof:name":"Bar DE LA Cote",
    "wof:placetype":"venue"
},
  "geometry": {"coordinates":[-69.013847,47.892384],"type":"Point"}
}