{
  "type": "Feature",
  "properties": {
    "iso:country":"CA",
    "sg:address":"3826 Sunset St",
    "sg:city":"Burnaby",
    "sg:classifiers":[
        {
            "category":"Restaurant",
            "type":"Food & Drink"
        }
    ],
    "sg:phone":"+1 604 434 4545",
    "sg:postcode":"V5G 1T3",
    "sg:province":"BC",
    "sg:tags":[
        "delicatessen"
    ],
    "wof:name":"Grandma's Deli",
    "wof:placetype":"venue"
},
  "geometry": {"coordinates":[-123.019096,49.249615],"type":"Point"}
}