{
  "type": "Feature",
  "properties": {
    "addr:full":"808 Muriel St Winnipeg MB R2Y 0Y3",
    "addr:housenumber":"808",
    "addr:postcode":"r2y 0y3",
    "addr:street":"Muriel St",
    "iso:country":"CA",
    "sg:address":"808 Muriel St",
    "sg:city":"Winnipeg",
    "sg:classifiers":[
        {
            "category":"Organizations",
            "subcategory":"Professional Association",
            "type":"Services"
        }
    ],
    "sg:phone":"+1 204 889 5981",
    "sg:postcode":"R2Y 0Y3",
    "sg:province":"MB",
    "wof:name":"Landscape Manitoba",
    "wof:placetype":"venue"
},
  "geometry": {"coordinates":[-97.2967376709,49.889629364],"type":"Point"}
}