{
  "type": "Feature",
  "properties": {
    "addr:full":"Tobermory ON N0H 2R0",
    "addr:postcode":"n0h 2r0",
    "iso:country":"CA",
    "sg:city":"Tobermory",
    "sg:classifiers":[
        {
            "category":"Recreation",
            "type":"Entertainment"
        }
    ],
    "sg:phone":"+1 519 596 2263",
    "sg:postcode":"N0H 2R0",
    "sg:province":"ON",
    "sg:tags":[
        "provincial",
        "parks"
    ],
    "wof:name":"Canada Heritage Cyprus Lake",
    "wof:placetype":"venue"
},
  "geometry": {"coordinates":[-81.6650924683,45.2538261414],"type":"Point"}
}