{
  "type": "Feature",
  "properties": {
    "addr:full":"Delta BC V4E 2A6",
    "addr:postcode":"v4e 2a6",
    "iso:country":"CA",
    "sg:city":"Delta",
    "sg:classifiers":[
        {
            "category":"Personal",
            "type":"Services"
        }
    ],
    "sg:phone":"+1 604 599 5575",
    "sg:postcode":"V4E 2A6",
    "sg:province":"BC",
    "sg:tags":[
        "therapist",
        "massage"
    ],
    "wof:name":"Body Mechanics Massage Therapy",
    "wof:placetype":"venue"
},
  "geometry": {"coordinates":[-122.890586853,49.118144989],"type":"Point"}
}