{
  "type": "Feature",
  "properties": {
    "iso:country":"CA",
    "sg:city":"Winnipeg",
    "sg:classifiers":[
        {
            "category":"Professional",
            "subcategory":"Accounting & Tax Preparation",
            "type":"Services"
        }
    ],
    "sg:phone":"+1 204 982 4490",
    "sg:postcode":"R3B 3B1",
    "sg:province":"MB",
    "sg:tags":[
        "accountant"
    ],
    "wof:name":"Kurbis, Ernest A",
    "wof:placetype":"venue"
},
  "geometry": {"coordinates":[-97.134147644,49.8956489563],"type":"Point"}
}