{
  "type": "Feature",
  "properties": {
    "addr:full":"17480 Yonge St # 2A Newmarket ON L3Y 8A7",
    "addr:housenumber":"17480;2a",
    "addr:postcode":"l3y 8a7",
    "addr:street":"Yonge St #",
    "iso:country":"CA",
    "sg:address":"17480 Yonge St # 2A",
    "sg:city":"Newmarket",
    "sg:classifiers":[
        {
            "category":"Building & Trades",
            "subcategory":"Construction",
            "type":"Services"
        }
    ],
    "sg:phone":"+1 905 853 8500",
    "sg:postcode":"L3Y 8A7",
    "sg:province":"ON",
    "sg:tags":[
        "designer",
        "dealer",
        "pool",
        "swimming"
    ],
    "wof:name":"Seaway Pools & Hot Tubs",
    "wof:placetype":"venue"
},
  "geometry": {"coordinates":[-79.48036999999999,44.054043],"type":"Point"}
}