{
  "type": "Feature",
  "properties": {
    "iso:country":"CA",
    "sg:address":"1880 Crois Sauve",
    "sg:city":"Brossard",
    "sg:classifiers":[
        {
            "category":"Professional",
            "subcategory":"Management & Consulting",
            "type":"Services"
        }
    ],
    "sg:phone":"+1 450 466 7332",
    "sg:postcode":"J4X 1L1",
    "sg:province":"QC",
    "sg:tags":[
        "personnel",
        "consultant"
    ],
    "wof:name":"Jean Yves Pilon & Assoc",
    "wof:placetype":"venue"
},
  "geometry": {"coordinates":[-73.469292,45.45496],"type":"Point"}
}