{
  "type": "Feature",
  "properties": {
    "addr:full":"5691 Parkwood Way Richmond BC V6V 2M6",
    "addr:housenumber":"5691",
    "addr:postcode":"v6v 2m6",
    "addr:street":"Parkwood Way",
    "iso:country":"CA",
    "sg:address":"5691 Parkwood Way",
    "sg:city":"Richmond",
    "sg:classifiers":[
        {
            "category":"Autos & Motor Vehicles",
            "subcategory":"Automobile Sales",
            "type":"Retail Goods"
        }
    ],
    "sg:phone":"+1 604 278 7662",
    "sg:postcode":"V6V 2M6",
    "sg:province":"BC",
    "sg:tags":[
        "car",
        "dealer"
    ],
    "wof:name":"Mercedes-Benz Canada Inc",
    "wof:placetype":"venue"
},
  "geometry": {"coordinates":[-123.07807922400001,49.1726837158],"type":"Point"}
}