{
  "type": "Feature",
  "properties": {
    "addr:full":"1345 Rue Notre-Dame E Champlain QC G0X 1C0",
    "addr:housenumber":"1345",
    "addr:postcode":"g0x 1c0",
    "addr:street":"Rue Notre-Dame E",
    "iso:country":"CA",
    "sg:address":"1345 Rue Notre-Dame E",
    "sg:city":"Champlain",
    "sg:classifiers":[
        {
            "category":"Home & Garden",
            "subcategory":"Building Materials",
            "type":"Retail Goods"
        }
    ],
    "sg:phone":"+1 819 295 3219",
    "sg:postcode":"G0X 1C0",
    "sg:province":"QC",
    "sg:tags":[
        "paint"
    ],
    "wof:name":"Peinture Jean Carignan",
    "wof:placetype":"venue"
},
  "geometry": {"coordinates":[-72.299477,46.445835],"type":"Point"}
}