{
  "type": "Feature",
  "properties": {
    "addr:full":"241 Clarence St Brampton ON L6W 4P2",
    "addr:housenumber":"241",
    "addr:postcode":"l6w 4p2",
    "addr:street":"Clarence St",
    "iso:country":"CA",
    "sg:address":"241 Clarence St",
    "sg:city":"Brampton",
    "sg:classifiers":[
        {
            "category":"Manufacturing",
            "subcategory":"Rubber & Plastics",
            "type":"Manufacturing & Wholesale Goods"
        }
    ],
    "sg:phone":"+1 905 451 9949",
    "sg:postcode":"L6W 4P2",
    "sg:province":"ON",
    "sg:tags":[
        "mold",
        "maker"
    ],
    "wof:name":"Scl A1 Plastics Inc",
    "wof:placetype":"venue"
},
  "geometry": {"coordinates":[-79.737213,43.690651],"type":"Point"}
}