{
  "type": "Feature",
  "properties": {
    "addr:full":"North York ON M3J 2G2",
    "addr:postcode":"m3j 2g2",
    "iso:country":"CA",
    "sg:city":"North York",
    "sg:classifiers":[
        {
            "category":"Wholesale",
            "subcategory":"Durable Goods & Equipment",
            "type":"Manufacturing & Wholesale Goods"
        }
    ],
    "sg:phone":"+1 416 663 0375",
    "sg:postcode":"M3J 2G2",
    "sg:province":"ON",
    "sg:tags":[
        "importer"
    ],
    "wof:name":"Doma Enterprises",
    "wof:placetype":"venue"
},
  "geometry": {"coordinates":[-79.4818115234,43.7653770447],"type":"Point"}
}