{
  "type": "Feature",
  "properties": {
    "addr:full":"417 St Anne's Rd Winnipeg MB R2M 3C4",
    "addr:housenumber":"417",
    "addr:postcode":"r2m 3c4",
    "addr:street":"St Anne'S Rd",
    "iso:country":"CA",
    "sg:address":"417 St Anne's Rd",
    "sg:city":"Winnipeg",
    "sg:classifiers":[
        {
            "category":"Health Services",
            "subcategory":"Doctor",
            "type":"Services"
        }
    ],
    "sg:phone":"+1 204 255 6256",
    "sg:postcode":"R2M 3C4",
    "sg:province":"MB",
    "sg:tags":[
        "physician",
        "surgeon"
    ],
    "wof:name":"Berrydale Family Medical Ctr",
    "wof:placetype":"venue"
},
  "geometry": {"coordinates":[-97.097336,49.846619],"type":"Point"}
}