{
  "type": "Feature",
  "properties": {
    "addr:full":"126 Van Horne St N Cranbrook BC V1C 3P3",
    "addr:housenumber":"126",
    "addr:postcode":"v1c 3p3",
    "addr:street":"Van Horne St N",
    "iso:country":"CA",
    "sg:address":"126 Van Horne St N",
    "sg:city":"Cranbrook",
    "sg:classifiers":[
        {
            "category":"Manufacturing",
            "subcategory":"Tools & Machinery",
            "type":"Manufacturing & Wholesale Goods"
        }
    ],
    "sg:phone":"+1 250 426 2521",
    "sg:postcode":"V1C 3P3",
    "sg:province":"BC",
    "sg:tags":[
        "machine",
        "shop"
    ],
    "wof:name":"Alan Reekie's Machine Shop Ltd",
    "wof:placetype":"venue"
},
  "geometry": {"coordinates":[-115.767509,49.514252],"type":"Point"}
}