{
  "type": "Feature",
  "properties": {
    "addr:full":"611 50th Ave E Vancouver BC V5X 1A9",
    "addr:housenumber":"611",
    "addr:postcode":"v5x 1a9",
    "addr:street":"50Th Ave E",
    "iso:country":"CA",
    "sg:address":"611 50th Ave E",
    "sg:city":"Vancouver",
    "sg:classifiers":[
        {
            "category":"Organizations",
            "subcategory":"Religious Organization",
            "type":"Services"
        }
    ],
    "sg:phone":"+1 604 325 5300",
    "sg:postcode":"V5X 1A9",
    "sg:province":"BC",
    "sg:tags":[
        "church"
    ],
    "wof:name":"S Vancouver Pacific Grace",
    "wof:placetype":"venue"
},
  "geometry": {"coordinates":[-123.09243774399999,49.22473526],"type":"Point"}
}