{
  "type": "Feature",
  "properties": {
    "addr:full":"1539 Johnston Rd White Rock BC V4B 3Z6",
    "addr:housenumber":"1539",
    "addr:postcode":"v4b 3z6",
    "addr:street":"Johnston Rd",
    "iso:country":"CA",
    "sg:address":"1539 Johnston Rd",
    "sg:city":"White Rock",
    "sg:classifiers":[
        {
            "category":"Shopping",
            "type":"Retail Goods"
        }
    ],
    "sg:phone":"+1 604 535 7445",
    "sg:postcode":"V4B 3Z6",
    "sg:province":"BC",
    "sg:tags":[
        "art",
        "gallery",
        "dealer"
    ],
    "wof:name":"Jenkins Showler Gallery",
    "wof:placetype":"venue"
},
  "geometry": {"coordinates":[-122.801376,49.030155],"type":"Point"}
}