{
  "type": "Feature",
  "properties": {
    "addr:full":"2049 Meadowbrook Rd Gloucester ON K1B 4W7",
    "addr:housenumber":"2049",
    "addr:postcode":"k1b 4w7",
    "addr:street":"Meadowbrook Rd",
    "iso:country":"CA",
    "sg:address":"2049 Meadowbrook Rd",
    "sg:city":"Gloucester",
    "sg:classifiers":[
        {
            "category":"Real Estate",
            "subcategory":"Real Estate Operator",
            "type":"Services"
        }
    ],
    "sg:phone":"+1 613 236 3902",
    "sg:postcode":"K1B 4W7",
    "sg:province":"ON",
    "sg:tags":[
        "condominium"
    ],
    "wof:name":"Premiere Property Management",
    "wof:placetype":"venue"
},
  "geometry": {"coordinates":[-75.601715,45.427071],"type":"Point"}
}