{
  "type": "Feature",
  "properties": {
    "addr:full":"630 Mcallister Dr Saint John NB E2J 4N9",
    "addr:housenumber":"630",
    "addr:postcode":"e2j 4n9",
    "addr:street":"Mcallister Dr",
    "iso:country":"CA",
    "sg:address":"630 Mcallister Dr",
    "sg:city":"Saint John",
    "sg:classifiers":[
        {
            "category":"Wholesale",
            "subcategory":"Machinery & Supplies",
            "type":"Manufacturing & Wholesale Goods"
        }
    ],
    "sg:phone":"+1 506 634 8960",
    "sg:postcode":"E2J 4N9",
    "sg:province":"NB",
    "sg:tags":[
        "equipment",
        "welding"
    ],
    "wof:name":"Air Liquid Canada",
    "wof:placetype":"venue"
},
  "geometry": {"coordinates":[-66.0064163208,45.3009185791],"type":"Point"}
}