{
  "type": "Feature",
  "properties": {
    "iso:country":"CA",
    "sg:address":"38 Arthur St S",
    "sg:city":"Elmira",
    "sg:classifiers":[
        {
            "category":"Shopping",
            "subcategory":"Florist",
            "type":"Retail Goods"
        }
    ],
    "sg:phone":"+1 519 669 5652",
    "sg:postcode":"N3B 2M7",
    "sg:province":"ON",
    "wof:name":"Blooms & Tunes",
    "wof:placetype":"venue"
},
  "geometry": {"coordinates":[-80.5587310791,43.5989227295],"type":"Point"}
}