{
  "type": "Feature",
  "properties": {
    "addr:full":"Edmonton AB T6B 1E7",
    "addr:postcode":"t6b 1e7",
    "iso:country":"CA",
    "sg:city":"Edmonton",
    "sg:classifiers":[
        {
            "category":"Communications",
            "subcategory":"Film & Video Production",
            "type":"Services"
        }
    ],
    "sg:phone":"+1 780 463 3126",
    "sg:postcode":"T6B 1E7",
    "sg:province":"AB",
    "sg:tags":[
        "taping"
    ],
    "wof:name":"Creative Control Communication",
    "wof:placetype":"venue"
},
  "geometry": {"coordinates":[-113.41791499999999,53.519894],"type":"Point"}
}