{
  "type": "Feature",
  "properties": {
    "addr:full":"70 Brushwood Cres Barrie ON L4N 7E6",
    "addr:housenumber":"70",
    "addr:postcode":"l4n 7e6",
    "addr:street":"Brushwood Cres",
    "iso:country":"CA",
    "sg:address":"70 Brushwood Cres",
    "sg:city":"Barrie",
    "sg:classifiers":[
        {
            "category":"Organizations",
            "subcategory":"Non-profit Organization",
            "type":"Services"
        }
    ],
    "sg:phone":"+1 705 726 1243",
    "sg:postcode":"L4N 7E6",
    "sg:province":"ON",
    "sg:tags":[
        "fund",
        "counselor",
        "raising"
    ],
    "wof:name":"Huronia Casino Entertainment",
    "wof:placetype":"venue"
},
  "geometry": {"coordinates":[-79.6374664307,44.3607139587],"type":"Point"}
}