{
  "type": "Feature",
  "properties": {
    "addr:full":"12456 Rue Saint-Louis Pierrefonds QC H8Z 1A2",
    "addr:housenumber":"12456",
    "addr:postcode":"h8z 1a2",
    "addr:street":"Rue Saint-Louis",
    "iso:country":"CA",
    "sg:address":"12456 Rue Saint-Louis",
    "sg:city":"Pierrefonds",
    "sg:classifiers":[
        {
            "category":"Building & Trades",
            "subcategory":"Construction",
            "type":"Services"
        }
    ],
    "sg:phone":"+1 514 685 5028",
    "sg:postcode":"H8Z 1A2",
    "sg:province":"QC",
    "sg:tags":[
        "waterproofing",
        "contractor"
    ],
    "wof:name":"Bwn 2896788 Canada Inc",
    "wof:placetype":"venue"
},
  "geometry": {"coordinates":[-73.83986663819999,45.513420105],"type":"Point"}
}