{
  "type": "Feature",
  "properties": {
    "addr:full":"120 2nd Ave N # 3 Saskatoon SK S7K 2B2",
    "addr:housenumber":"120",
    "addr:postcode":"s7k 2b2",
    "addr:street":"2Nd Ave N # 3",
    "iso:country":"CA",
    "sg:address":"120 2nd Ave N # 3",
    "sg:city":"Saskatoon",
    "sg:classifiers":[
        {
            "category":"Restaurant",
            "type":"Food & Drink"
        }
    ],
    "sg:phone":"+1 306 244 1513",
    "sg:postcode":"S7K 2B2",
    "sg:province":"SK",
    "wof:name":"Olympia Restaurant",
    "wof:placetype":"venue"
},
  "geometry": {"coordinates":[-106.663422,52.129154],"type":"Point"}
}