{
  "type": "Feature",
  "properties": {
    "addr:full":"1100 Venables St Vancouver BC V6A 2E2",
    "addr:housenumber":"1100",
    "addr:postcode":"v6a 2e2",
    "addr:street":"Venables St",
    "iso:country":"CA",
    "sg:address":"1100 Venables St",
    "sg:city":"Vancouver",
    "sg:classifiers":[
        {
            "category":"Wholesale",
            "subcategory":"Machinery & Supplies",
            "type":"Manufacturing & Wholesale Goods"
        }
    ],
    "sg:phone":"+1 604 251 1661",
    "sg:postcode":"V6A 2E2",
    "sg:province":"BC",
    "sg:tags":[
        "ship",
        "chandler"
    ],
    "wof:name":"Vanport Ship Supply",
    "wof:placetype":"venue"
},
  "geometry": {"coordinates":[-123.08118438699999,49.2767562866],"type":"Point"}
}