{
  "type": "Feature",
  "properties": {
    "addr:full":"124 Prince William St Saint John NB E2L 2B6",
    "addr:housenumber":"124",
    "addr:postcode":"nb e2l 2b6",
    "addr:street":"Prince William St",
    "iso:country":"CA",
    "sg:address":"124 Prince William St",
    "sg:city":"Saint John",
    "sg:classifiers":[
        {
            "category":"Travel",
            "subcategory":"Travel Agent",
            "type":"Entertainment"
        }
    ],
    "sg:phone":"+1 506 633 1224",
    "sg:postcode":"E2L 2B6",
    "sg:province":"NB",
    "sg:tags":[
        "agency",
        "bureau"
    ],
    "wof:name":"Aquila Tours Inc",
    "wof:placetype":"venue"
},
  "geometry": {"coordinates":[-66.061554,45.270996],"type":"Point"}
}