{
  "type": "Feature",
  "properties": {
    "addr:full":"2390 Mcmillan Rd Abbotsford BC V2S 7R3",
    "addr:housenumber":"2390",
    "addr:postcode":"v2s 7r3",
    "addr:street":"Mcmillan Rd",
    "iso:country":"CA",
    "sg:address":"2390 Mcmillan Rd",
    "sg:city":"Abbotsford",
    "sg:classifiers":[
        {
            "category":"Social Services",
            "subcategory":"Child Care",
            "type":"Services"
        }
    ],
    "sg:phone":"+1 604 859 8406",
    "sg:postcode":"V2S 7R3",
    "sg:province":"BC",
    "wof:name":"Open Door Daycare Preschool",
    "wof:placetype":"venue"
},
  "geometry": {"coordinates":[-122.259865,49.045254],"type":"Point"}
}