{
  "type": "Feature",
  "properties": {
    "addr:full":"Manitouwadge ON P0T 2C0",
    "addr:postcode":"p0t 2c0",
    "iso:country":"CA",
    "sg:city":"Manitouwadge",
    "sg:classifiers":[
        {
            "category":"Shopping",
            "subcategory":"Discount & Variety Stores",
            "type":"Retail Goods"
        }
    ],
    "sg:phone":"+1 807 826 3873",
    "sg:postcode":"P0T 2C0",
    "sg:province":"ON",
    "wof:name":"Bargain Shop",
    "wof:placetype":"venue"
},
  "geometry": {"coordinates":[-85.82860599999999,49.126755],"type":"Point"}
}