{
  "type": "Feature",
  "properties": {
    "addr:full":"Meaghers Grant NS B0N 1V0",
    "addr:postcode":"b0n 1v0",
    "iso:country":"CA",
    "sg:city":"Meaghers Grant",
    "sg:classifiers":[
        {
            "category":"Autos & Motor Vehicles",
            "subcategory":"Boat Sales",
            "type":"Retail Goods"
        }
    ],
    "sg:phone":"+1 902 384 2513",
    "sg:postcode":"B0N 1V0",
    "sg:province":"NS",
    "sg:tags":[
        "dealer"
    ],
    "wof:name":"Meaghers Grant Canoe Rentals",
    "wof:placetype":"venue"
},
  "geometry": {"coordinates":[-63.229401,44.912132],"type":"Point"}
}