{
  "type": "Feature",
  "properties": {
    "addr:full":"Sarnia ON N7S 1P8",
    "addr:postcode":"n7s 1p8",
    "iso:country":"CA",
    "sg:city":"Sarnia",
    "sg:classifiers":[
        {
            "category":"Personal",
            "subcategory":"Beauty Salon",
            "type":"Services"
        }
    ],
    "sg:phone":"+1 519 542 4344",
    "sg:postcode":"N7S 1P8",
    "sg:province":"ON",
    "wof:name":"Mastercuts",
    "wof:placetype":"venue"
},
  "geometry": {"coordinates":[-82.35488100000001,42.983768],"type":"Point"}
}