{
  "type": "Feature",
  "properties": {
    "addr:full":"7273 4th Cassan Rockton ON L0R 1X0",
    "addr:housenumber":"7273",
    "addr:postcode":"l0r 1x0",
    "addr:street":"4Th Cassan",
    "iso:country":"CA",
    "sg:address":"7273 4th Cassan",
    "sg:city":"Rockton",
    "sg:classifiers":[
        {
            "category":"Home & Garden",
            "subcategory":"Building Materials",
            "type":"Retail Goods"
        }
    ],
    "sg:phone":"+1 519 647 2744",
    "sg:postcode":"L0R 1X0",
    "sg:province":"ON",
    "sg:tags":[
        "windows"
    ],
    "wof:name":"Rockton Window & Door Products",
    "wof:placetype":"venue"
},
  "geometry": {"coordinates":[-80.12999000000001,43.30188],"type":"Point"}
}