{
  "type": "Feature",
  "properties": {
    "addr:full":"707 Boul Saint-Joseph Roberval QC G8H 2L3",
    "addr:housenumber":"707",
    "addr:postcode":"g8h 2l3",
    "addr:street":"Boul Saint-Joseph",
    "iso:country":"CA",
    "sg:address":"707 Boul Saint-Joseph",
    "sg:city":"Roberval",
    "sg:classifiers":[
        {
            "category":"Shopping",
            "subcategory":"Computers & Home Electronics",
            "type":"Retail Goods"
        }
    ],
    "sg:phone":"+1 418 275 7525",
    "sg:postcode":"G8H 2L3",
    "sg:province":"QC",
    "sg:tags":[
        "equipment",
        "dealer",
        "furniture"
    ],
    "wof:name":"Megaburo Inc",
    "wof:placetype":"venue"
},
  "geometry": {"coordinates":[-72.220985,48.514973],"type":"Point"}
}