{
  "type": "Feature",
  "properties": {
    "addr:full":"514 Baringham Pl Waterloo ON N2T 2J4",
    "addr:housenumber":"514",
    "addr:postcode":"n2t 2j4",
    "addr:street":"Baringham Pl",
    "iso:country":"CA",
    "sg:address":"514 Baringham Pl",
    "sg:city":"Waterloo",
    "sg:classifiers":[
        {
            "category":"Manufacturing",
            "subcategory":"Tools & Machinery",
            "type":"Manufacturing & Wholesale Goods"
        }
    ],
    "sg:phone":"+1 519 886 0148",
    "sg:postcode":"N2T 2J4",
    "sg:province":"ON",
    "sg:tags":[
        "equipment",
        "automation",
        "electronic",
        "system",
        "supply"
    ],
    "wof:name":"Stecksoft Systems",
    "wof:placetype":"venue"
},
  "geometry": {"coordinates":[-80.571945,43.467342],"type":"Point"}
}