{
  "type": "Feature",
  "properties": {
    "iso:country":"CA",
    "sg:address":"2401 Rue Bauman",
    "sg:city":"Jonquiere",
    "sg:classifiers":[
        {
            "category":"Retail",
            "subcategory":"Auto Repair",
            "type":"Services"
        }
    ],
    "sg:phone":"+1 418 548 3956",
    "sg:postcode":"G7S 5A9",
    "sg:province":"QC",
    "sg:tags":[
        "body",
        "automobile",
        "painting"
    ],
    "wof:name":"Debosselage Roger Simard Enr",
    "wof:placetype":"venue"
},
  "geometry": {"coordinates":[-71.1620788574,48.4050445557],"type":"Point"}
}