{
  "type": "Feature",
  "properties": {
    "addr:full":"5580 Kalar Rd Niagara Falls ON L2H 3L1",
    "addr:housenumber":"5580",
    "addr:postcode":"l2h 3l1",
    "addr:street":"Kalar Rd",
    "iso:country":"CA",
    "sg:address":"5580 Kalar Rd",
    "sg:city":"Niagara Falls",
    "sg:classifiers":[
        {
            "category":"Manufacturing",
            "subcategory":"Metals",
            "type":"Manufacturing & Wholesale Goods"
        }
    ],
    "sg:phone":"+1 905 356 8132",
    "sg:postcode":"L2H 3L1",
    "sg:province":"ON",
    "sg:tags":[
        "steel"
    ],
    "wof:name":"Hodgson Custom Rolling Inc",
    "wof:placetype":"venue"
},
  "geometry": {"coordinates":[-79.13608600000001,43.092381],"type":"Point"}
}