{
  "type": "Feature",
  "properties": {
    "addr:full":"49 Viscount Ave SW Medicine Hat AB T1A 5G4",
    "addr:housenumber":"49",
    "addr:postcode":"t1a 5g4",
    "addr:street":"Viscount Ave Sw",
    "iso:country":"CA",
    "sg:address":"49 Viscount Ave SW",
    "sg:city":"Medicine Hat",
    "sg:classifiers":[
        {
            "category":"Airline",
            "type":"Transportation"
        }
    ],
    "sg:phone":"+1 403 527 7787",
    "sg:postcode":"T1A 5G4",
    "sg:province":"AB",
    "sg:tags":[
        "cargo",
        "air"
    ],
    "wof:name":"Air Canada Regional Inc",
    "wof:placetype":"venue"
},
  "geometry": {"coordinates":[-110.727158,50.024967],"type":"Point"}
}