{
  "type": "Feature",
  "properties": {
    "iso:country":"CA",
    "sg:address":"1313 Queen St W",
    "sg:city":"Toronto",
    "sg:classifiers":[
        {
            "category":"Social Services",
            "type":"Services"
        }
    ],
    "sg:phone":"+1 416 532 3888",
    "sg:postcode":"M6K 1L8",
    "sg:province":"ON",
    "sg:tags":[
        "organization",
        "welfare"
    ],
    "wof:name":"Kababayan Community Svc Ctr",
    "wof:placetype":"venue"
},
  "geometry": {"coordinates":[-79.433235,43.641151],"type":"Point"}
}