{
  "type": "Feature",
  "properties": {
    "addr:full":"47 King St W Harrow ON N0R 1G0",
    "addr:housenumber":"47",
    "addr:postcode":"n0r 1g0",
    "addr:street":"King St W",
    "iso:country":"CA",
    "sg:address":"47 King St W",
    "sg:city":"Harrow",
    "sg:classifiers":[
        {
            "category":"Wholesale",
            "subcategory":"Drugs",
            "type":"Manufacturing & Wholesale Goods"
        }
    ],
    "sg:phone":"+1 519 738 3511",
    "sg:postcode":"N0R 1G0",
    "sg:province":"ON",
    "sg:tags":[
        "cosmetic"
    ],
    "wof:name":"Cool Eyes Inc",
    "wof:placetype":"venue"
},
  "geometry": {"coordinates":[-82.91888400000001,42.035431],"type":"Point"}
}