{
  "type": "Feature",
  "properties": {
    "addr:full":"79 East Don Roadway Toronto ON M4M 2A5",
    "addr:housenumber":"79",
    "addr:postcode":"m4m 2a5",
    "addr:street":"East Don Roadway",
    "iso:country":"CA",
    "sg:address":"79 East Don Roadway",
    "sg:city":"Toronto",
    "sg:classifiers":[
        {
            "category":"Communications",
            "subcategory":"Film & Video Production",
            "type":"Services"
        }
    ],
    "sg:phone":"+1 416 461 6604",
    "sg:postcode":"M4M 2A5",
    "sg:province":"ON",
    "sg:tags":[
        "motion",
        "picture"
    ],
    "wof:name":"Undercover Film & Electronics",
    "wof:placetype":"venue"
},
  "geometry": {"coordinates":[-79.3529891968,43.6578483582],"type":"Point"}
}