{
  "type": "Feature",
  "properties": {
    "addr:full":"Surrey BC V4N 3R3",
    "addr:postcode":"v4n 3r3",
    "iso:country":"CA",
    "sg:city":"Surrey",
    "sg:classifiers":[
        {
            "category":"Manufacturing",
            "subcategory":"Tools & Machinery",
            "type":"Manufacturing & Wholesale Goods"
        }
    ],
    "sg:phone":"+1 604 888 0318",
    "sg:postcode":"V4N 3R3",
    "sg:province":"BC",
    "sg:tags":[
        "sprinkler"
    ],
    "wof:name":"Phaser Fire Protection",
    "wof:placetype":"venue"
},
  "geometry": {"coordinates":[-122.69394699999999,49.176785],"type":"Point"}
}