{
  "type": "Feature",
  "properties": {
    "iso:country":"CA",
    "sg:address":"1645 Av Desjardins",
    "sg:city":"Montreal",
    "sg:classifiers":[
        {
            "category":"Organizations",
            "subcategory":"Religious Organization",
            "type":"Services"
        }
    ],
    "sg:phone":"+1 514 253 7563",
    "sg:postcode":"H1V 2G7",
    "sg:province":"QC",
    "sg:tags":[
        "church"
    ],
    "wof:name":"Tres-St-Nom-DE-Jesus Eglise",
    "wof:placetype":"venue"
},
  "geometry": {"coordinates":[-73.537201,45.550137],"type":"Point"}
}