{
  "type": "Feature",
  "properties": {
    "iso:country":"CA",
    "sg:address":"6768 Av Papineau",
    "sg:city":"Montreal",
    "sg:classifiers":[
        {
            "category":"Travel",
            "subcategory":"Travel Agent",
            "type":"Entertainment"
        }
    ],
    "sg:phone":"+1 514 725 9225",
    "sg:postcode":"H2G 2X7",
    "sg:province":"QC",
    "sg:tags":[
        "agency",
        "bureau"
    ],
    "wof:name":"Voyages Ramses Inc",
    "wof:placetype":"venue"
},
  "geometry": {"coordinates":[-73.600998,45.545101],"type":"Point"}
}