{
  "type": "Feature",
  "properties": {
    "addr:full":"53 Owl Ridge Dr Richmond Hill ON L4S 1P8",
    "addr:housenumber":"53",
    "addr:postcode":"l4s 1p8",
    "addr:street":"Owl Ridge Dr",
    "iso:country":"CA",
    "sg:address":"53 Owl Ridge Dr",
    "sg:city":"Richmond Hill",
    "sg:classifiers":[
        {
            "category":"Shopping",
            "subcategory":"Gifts & Souvenirs",
            "type":"Retail Goods"
        }
    ],
    "sg:phone":"+1 905 737 3497",
    "sg:postcode":"L4S 1P8",
    "sg:province":"ON",
    "sg:tags":[
        "party",
        "supply"
    ],
    "wof:name":"Premier Linens",
    "wof:placetype":"venue"
},
  "geometry": {"coordinates":[-79.46307400000001,43.899174],"type":"Point"}
}