{
  "type": "Feature",
  "properties": {
    "iso:country":"CA",
    "sg:address":"53 Owl Ridge Dr",
    "sg:city":"Richmond Hill",
    "sg:classifiers":[
        {
            "category":"Shopping",
            "subcategory":"Gifts & Souvenirs",
            "type":"Retail Goods"
        }
    ],
    "sg:phone":"+1 905 737 3497",
    "sg:postcode":"L4S 1P8",
    "sg:province":"ON",
    "sg:tags":[
        "party",
        "supply"
    ],
    "wof:name":"Premier Linens",
    "wof:placetype":"venue"
},
  "geometry": {"coordinates":[-79.463074,43.899174],"type":"Point"}
}