{
  "type": "Feature",
  "properties": {
    "addr:full":"Quebec QC G1N 2E7",
    "addr:postcode":"g1n 2e7",
    "iso:country":"CA",
    "sg:city":"Quebec",
    "sg:classifiers":[
        {
            "category":"Wholesale",
            "subcategory":"Durable Goods & Equipment",
            "type":"Manufacturing & Wholesale Goods"
        }
    ],
    "sg:phone":"+1 418 688 7474",
    "sg:postcode":"G1N 2E7",
    "sg:province":"QC",
    "sg:tags":[
        "engineering",
        "material",
        "artist",
        "supply"
    ],
    "wof:name":"Dutech Materiel D'Art Applique",
    "wof:placetype":"venue"
},
  "geometry": {"coordinates":[-71.2593460083,46.7978248596],"type":"Point"}
}