{
  "type": "Feature",
  "properties": {
    "iso:country":"CA",
    "sg:address":"Hwy 41A",
    "sg:city":"Melfort",
    "sg:classifiers":[
        {
            "category":"Freight",
            "type":"Transportation"
        }
    ],
    "sg:phone":"+1 306 752 1955",
    "sg:postcode":"S0E 1A0",
    "sg:province":"SK",
    "sg:tags":[
        "grain",
        "elevator"
    ],
    "wof:name":"Sask Wheat Pool",
    "wof:placetype":"venue"
},
  "geometry": {"coordinates":[-104.63977813699999,52.8669013977],"type":"Point"}
}