{
  "type": "Feature",
  "properties": {
    "addr:full":"236 Rue Saint-Jacques Montreal QC H2Y 1L9",
    "addr:housenumber":"236",
    "addr:postcode":"h2y 1l9",
    "addr:street":"Rue Saint-Jacques",
    "iso:country":"CA",
    "sg:address":"236 Rue Saint-Jacques",
    "sg:city":"Montreal",
    "sg:classifiers":[
        {
            "category":"Restaurant",
            "type":"Food & Drink"
        }
    ],
    "sg:phone":"+1 514 842 3079",
    "sg:postcode":"H2Y 1L9",
    "sg:province":"QC",
    "sg:tags":[
        "cafe"
    ],
    "wof:name":"Brioche St-Jacques",
    "wof:placetype":"venue"
},
  "geometry": {"coordinates":[-73.5584106445,45.5036201477],"type":"Point"}
}