{
  "type": "Feature",
  "properties": {
    "addr:full":"2210 Wilgress Rd Nanaimo BC V9S 4N4",
    "addr:housenumber":"2210",
    "addr:postcode":"v9s 4n4",
    "addr:street":"Wilgress Rd",
    "iso:country":"CA",
    "sg:address":"2210 Wilgress Rd",
    "sg:city":"Nanaimo",
    "sg:classifiers":[
        {
            "category":"Retail",
            "subcategory":"Auto Repair",
            "type":"Services"
        }
    ],
    "sg:phone":"+1 250 758 2333",
    "sg:postcode":"V9S 4N4",
    "sg:province":"BC",
    "sg:tags":[
        "repairing",
        "automobile",
        "machine",
        "shop"
    ],
    "wof:name":"Island D Automotive Machine",
    "wof:placetype":"venue"
},
  "geometry": {"coordinates":[-123.97659299999999,49.192482],"type":"Point"}
}