{
  "type": "Feature",
  "properties": {
    "addr:full":"911 Main St SW Falher AB T0H 1M0",
    "addr:housenumber":"911",
    "addr:postcode":"t0h 1m0",
    "addr:street":"Main St Sw",
    "iso:country":"CA",
    "sg:address":"911 Main St SW",
    "sg:city":"Falher",
    "sg:classifiers":[
        {
            "category":"Farming",
            "subcategory":"Farm & Veterinary Services",
            "type":"Manufacturing & Wholesale Goods"
        }
    ],
    "sg:phone":"+1 780 837 2382",
    "sg:postcode":"T0H 1M0",
    "sg:province":"AB",
    "sg:tags":[
        "seed",
        "grain",
        "cleaning"
    ],
    "wof:name":"Falher Seed Cleaning Plant",
    "wof:placetype":"venue"
},
  "geometry": {"coordinates":[-117.20211792000001,55.7274627686],"type":"Point"}
}