{
  "type": "Feature",
  "properties": {
    "addr:full":"741 Rue Du Clocher #A Auclair QC G0L 1A0",
    "addr:housenumber":"741",
    "addr:postcode":"g0l 1a0",
    "addr:street":"Rue Du Clocher # A",
    "iso:country":"CA",
    "sg:address":"741 Rue Du Clocher #A",
    "sg:city":"Auclair",
    "sg:classifiers":[
        {
            "category":"Organizations",
            "subcategory":"Religious Organization",
            "type":"Services"
        }
    ],
    "sg:phone":"+1 418 899 2530",
    "sg:postcode":"G0L 1A0",
    "sg:province":"QC",
    "sg:tags":[
        "church"
    ],
    "wof:name":"Presbytere St-Emile D'Auclair",
    "wof:placetype":"venue"
},
  "geometry": {"coordinates":[-68.643738,47.728268],"type":"Point"}
}