{
  "type": "Feature",
  "properties": {
    "addr:full":"36 Alfred St # 4 Fordwich ON N0G 1V0",
    "addr:housenumber":"36",
    "addr:postcode":"n0g 1v0",
    "addr:street":"Alfred St # 4 Fordwich",
    "iso:country":"CA",
    "sg:address":"36 Alfred St # 4",
    "sg:city":"Fordwich",
    "sg:classifiers":[
        {
            "category":"Building & Trades",
            "subcategory":"Construction",
            "type":"Services"
        }
    ],
    "sg:phone":"+1 519 335 3473",
    "sg:postcode":"N0G 1V0",
    "sg:province":"ON",
    "sg:tags":[
        "contractor",
        "general"
    ],
    "wof:name":"Listowel Holdings Ltd",
    "wof:placetype":"venue"
},
  "geometry": {"coordinates":[-81.034691,43.864281],"type":"Point"}
}