{
  "type": "Feature",
  "properties": {
    "addr:full":"Coldwater ON L0K 1E0",
    "addr:postcode":"l0k 1e0",
    "iso:country":"CA",
    "sg:city":"Coldwater",
    "sg:classifiers":[
        {
            "category":"Travel",
            "subcategory":"Hotels & Motels",
            "type":"Entertainment"
        }
    ],
    "sg:phone":"+1 705 835 7000",
    "sg:postcode":"L0K 1E0",
    "sg:province":"ON",
    "sg:tags":[
        "breakfast",
        "accommodation",
        "bed"
    ],
    "wof:name":"Lazy Dayz",
    "wof:placetype":"venue"
},
  "geometry": {"coordinates":[-79.64436340330001,44.7102241516],"type":"Point"}
}