{
  "type": "Feature",
  "properties": {
    "addr:full":"846 Broughton St Victoria BC V8W 1E4",
    "addr:housenumber":"846",
    "addr:postcode":"v8w 1e4",
    "addr:street":"Broughton St",
    "iso:country":"CA",
    "sg:address":"846 Broughton St",
    "sg:city":"Victoria",
    "sg:classifiers":[
        {
            "category":"Professional",
            "subcategory":"Accounting & Tax Preparation",
            "type":"Services"
        }
    ],
    "sg:phone":"+1 250 388 6768",
    "sg:postcode":"V8W 1E4",
    "sg:province":"BC",
    "sg:tags":[
        "accountant"
    ],
    "wof:name":"Larkin, Lorraine",
    "wof:placetype":"venue"
},
  "geometry": {"coordinates":[-123.36134300000001,48.423481],"type":"Point"}
}