{
  "type": "Feature",
  "properties": {
    "addr:full":"803 202 Rte Canton Bedford QC J0J 1A0",
    "addr:housenumber":"202",
    "addr:postcode":"j0j 1a0",
    "addr:street":"Rte Canton",
    "iso:country":"CA",
    "sg:address":"803 202 Rte",
    "sg:city":"Canton Bedford",
    "sg:classifiers":[
        {
            "category":"Autos & Motor Vehicles",
            "subcategory":"Auto Supplies",
            "type":"Retail Goods"
        }
    ],
    "sg:phone":"+1 450 248 3911",
    "sg:postcode":"J0J 1A0",
    "sg:province":"QC",
    "sg:tags":[
        "filter",
        "gas"
    ],
    "wof:name":"Filtration Quebec Ltee",
    "wof:placetype":"venue"
},
  "geometry": {"coordinates":[-72.987381,45.121014],"type":"Point"}
}