{
  "type": "Feature",
  "properties": {
    "addr:full":"187 Exeter Rd London ON N6L 1A4",
    "addr:housenumber":"187",
    "addr:postcode":"n6l 1a4",
    "addr:street":"Exeter Rd",
    "iso:country":"CA",
    "sg:address":"187 Exeter Rd",
    "sg:city":"London",
    "sg:classifiers":[
        {
            "category":"Wholesale",
            "subcategory":"Construction Materials",
            "type":"Manufacturing & Wholesale Goods"
        }
    ],
    "sg:phone":"+1 519 652 2557",
    "sg:postcode":"N6L 1A4",
    "sg:province":"ON",
    "sg:tags":[
        "tile"
    ],
    "wof:name":"Greco Iberian Ceramic Tile Ltd",
    "wof:placetype":"venue"
},
  "geometry": {"coordinates":[-81.262184,42.921848],"type":"Point"}
}