{
  "type": "Feature",
  "properties": {
    "addr:full":"Erin ON N0B 1T0",
    "addr:postcode":"n0b 1t0",
    "iso:country":"CA",
    "sg:city":"Erin",
    "sg:classifiers":[
        {
            "category":"Health Services",
            "subcategory":"Doctor",
            "type":"Services"
        }
    ],
    "sg:phone":"+1 519 833 2946",
    "sg:postcode":"N0B 1T0",
    "sg:province":"ON",
    "sg:tags":[
        "physician",
        "surgeon"
    ],
    "wof:name":"Sasaki, S MD",
    "wof:placetype":"venue"
},
  "geometry": {"coordinates":[-80.059608,43.763088],"type":"Point"}
}