{
  "type": "Feature",
  "properties": {
    "addr:full":"Hwy 49 W Preeceville SK S0A 3B0",
    "addr:postcode":"s0a 3b0",
    "addr:street":"Hwy 49 W Preeceville",
    "iso:country":"CA",
    "sg:address":"Hwy 49 W",
    "sg:city":"Preeceville",
    "sg:classifiers":[
        {
            "category":"Wholesale",
            "subcategory":"Machinery & Supplies",
            "type":"Manufacturing & Wholesale Goods"
        }
    ],
    "sg:phone":"+1 306 547 2125",
    "sg:postcode":"S0A 3B0",
    "sg:province":"SK",
    "sg:tags":[
        "agricultural",
        "implement",
        "salvage",
        "surplus",
        "merchandise"
    ],
    "wof:name":"Preeceville Salvage Inc",
    "wof:placetype":"venue"
},
  "geometry": {"coordinates":[-102.666878,51.954235],"type":"Point"}
}