{
  "type": "Feature",
  "properties": {
    "addr:full":"80 Rideau Terr # 1 Ottawa ON K1M 2C6",
    "addr:housenumber":"80",
    "addr:postcode":"k1m 2c6",
    "addr:street":"Rideau Terr # 1",
    "iso:country":"CA",
    "sg:address":"80 Rideau Terr # 1",
    "sg:city":"Ottawa",
    "sg:classifiers":[
        {
            "category":"Restaurant",
            "type":"Food & Drink"
        }
    ],
    "sg:phone":"+1 613 230 2733",
    "sg:postcode":"K1M 2C6",
    "sg:province":"ON",
    "wof:name":"Burger King",
    "wof:placetype":"venue"
},
  "geometry": {"coordinates":[-75.691513,45.444332],"type":"Point"}
}