{
  "type": "Feature",
  "properties": {
    "addr:full":"10480 Boul Henri-Bourassa O Saint-Laurent QC H4S 1N6",
    "addr:housenumber":"10480",
    "addr:postcode":"h4s 1n6",
    "addr:street":"Boul Henri-Bourassa O",
    "iso:country":"CA",
    "sg:address":"10480 Boul Henri-Bourassa O",
    "sg:city":"Saint-Laurent",
    "sg:classifiers":[
        {
            "category":"Retail",
            "subcategory":"Auto Rental",
            "type":"Services"
        }
    ],
    "sg:phone":"+1 514 310 2277",
    "sg:postcode":"H4S 1N6",
    "sg:province":"QC",
    "sg:tags":[
        "renting",
        "automobile"
    ],
    "wof:name":"A Discount Location D'Autos",
    "wof:placetype":"venue"
},
  "geometry": {"coordinates":[-73.756416,45.493538],"type":"Point"}
}