{
  "type": "Feature",
  "properties": {
    "addr:full":"2 Garden Court Terr Dartmouth NS B3A 3S6",
    "addr:housenumber":"2",
    "addr:postcode":"b3a 3s6",
    "addr:street":"Garden Court Terr",
    "iso:country":"CA",
    "sg:address":"2 Garden Court Terr",
    "sg:city":"Dartmouth",
    "sg:classifiers":[
        {
            "category":"Education",
            "subcategory":"Special Training",
            "type":"Public Place"
        }
    ],
    "sg:phone":"+1 902 469 5013",
    "sg:postcode":"B3A 3S6",
    "sg:province":"NS",
    "sg:tags":[
        "instruction",
        "music"
    ],
    "wof:name":"Keddy's School of Music",
    "wof:placetype":"venue"
},
  "geometry": {"coordinates":[-63.5590591431,44.6839942932],"type":"Point"}
}