{
  "type": "Feature",
  "properties": {
    "addr:full":"1388 Cliveden Ave Delta BC V3M 6K2",
    "addr:housenumber":"1388",
    "addr:postcode":"v3m 6k2",
    "addr:street":"Cliveden Ave",
    "iso:country":"CA",
    "sg:address":"1388 Cliveden Ave",
    "sg:city":"Delta",
    "sg:classifiers":[
        {
            "category":"Manufacturing",
            "subcategory":"Food",
            "type":"Manufacturing & Wholesale Goods"
        }
    ],
    "sg:phone":"+1 604 521 1585",
    "sg:postcode":"V3M 6K2",
    "sg:province":"BC",
    "sg:tags":[
        "product",
        "manufacturer"
    ],
    "wof:name":"Grantham Foods Ltd",
    "wof:placetype":"venue"
},
  "geometry": {"coordinates":[-122.960037231,49.1680870056],"type":"Point"}
}