{
  "type": "Feature",
  "properties": {
    "iso:country":"CA",
    "sg:address":"18 Alayne Cres",
    "sg:city":"London",
    "sg:classifiers":[
        {
            "category":"Wholesale",
            "subcategory":"Electrical",
            "type":"Manufacturing & Wholesale Goods"
        }
    ],
    "sg:phone":"+1 519 686 7695",
    "sg:postcode":"N6E 2A3",
    "sg:province":"ON",
    "sg:tags":[
        "alarm",
        "burglar",
        "system"
    ],
    "wof:name":"Coyote Communications",
    "wof:placetype":"venue"
},
  "geometry": {"coordinates":[-81.228264,42.929008],"type":"Point"}
}