{
  "type": "Feature",
  "properties": {
    "iso:country":"CA",
    "sg:address":"1800 Britannia Rd E",
    "sg:city":"Mississauga",
    "sg:classifiers":[
        {
            "category":"Retail",
            "subcategory":"Auto Repair",
            "type":"Services"
        }
    ],
    "sg:phone":"+1 905 696 0027",
    "sg:postcode":"L4W 1J3",
    "sg:province":"ON",
    "sg:tags":[
        "repairing",
        "automobile"
    ],
    "wof:name":"Universal Truck & Equipment",
    "wof:placetype":"venue"
},
  "geometry": {"coordinates":[-79.6402435303,43.6616439819],"type":"Point"}
}