{
  "type": "Feature",
  "properties": {
    "addr:full":"1 Fraser Ave Craven SK S0G 0W0",
    "addr:housenumber":"1",
    "addr:postcode":"s0g 0w0",
    "addr:street":"Fraser Ave",
    "iso:country":"CA",
    "sg:address":"1 Fraser Ave",
    "sg:city":"Craven",
    "sg:classifiers":[
        {
            "category":"Travel",
            "subcategory":"Hotels & Motels",
            "type":"Entertainment"
        }
    ],
    "sg:phone":"+1 306 731 3455",
    "sg:postcode":"S0G 0W0",
    "sg:province":"SK",
    "wof:name":"Craven Motor Inn",
    "wof:placetype":"venue"
},
  "geometry": {"coordinates":[-104.808792114,50.707988739],"type":"Point"}
}