{
  "type": "Feature",
  "properties": {
    "addr:full":"Saskatoon SK S7H 5M2",
    "addr:postcode":"s7h 5m2",
    "iso:country":"CA",
    "sg:city":"Saskatoon",
    "sg:classifiers":[
        {
            "category":"Restaurant",
            "type":"Food & Drink"
        }
    ],
    "sg:phone":"+1 306 955 3900",
    "sg:postcode":"S7H 5M2",
    "sg:province":"SK",
    "wof:name":"Oceania Inn",
    "wof:placetype":"venue"
},
  "geometry": {"coordinates":[-106.590523,52.114914],"type":"Point"}
}