{
  "type": "Feature",
  "properties": {
    "addr:full":"336 Primrose Lane Newmarket ON L3Y 5Z2",
    "addr:housenumber":"336",
    "addr:postcode":"l3y 5z2",
    "addr:street":"Primrose Lane",
    "iso:country":"CA",
    "sg:address":"336 Primrose Lane",
    "sg:city":"Newmarket",
    "sg:classifiers":[
        {
            "category":"Building & Trades",
            "subcategory":"Electrical",
            "type":"Services"
        }
    ],
    "sg:phone":"+1 905 895 1438",
    "sg:postcode":"L3Y 5Z2",
    "sg:province":"ON",
    "sg:tags":[
        "electric",
        "contractor"
    ],
    "wof:name":"Miller Electric",
    "wof:placetype":"venue"
},
  "geometry": {"coordinates":[-79.48097199999999,44.065525],"type":"Point"}
}