{
  "type": "Feature",
  "properties": {
    "iso:country":"CA",
    "sg:address":"742 Simpson St",
    "sg:city":"Thunder Bay",
    "sg:classifiers":[
        {
            "category":"Retail",
            "subcategory":"Auto Repair",
            "type":"Services"
        }
    ],
    "sg:phone":"+1 807 623 0333",
    "sg:postcode":"P7C 3K1",
    "sg:province":"ON",
    "sg:tags":[
        "repairing",
        "automobile"
    ],
    "wof:name":"East End Svc",
    "wof:placetype":"venue"
},
  "geometry": {"coordinates":[-89.2362976074,48.3945121765],"type":"Point"}
}