{
  "type": "Feature",
  "properties": {
    "addr:full":"LA Pocatiere QC G0R 1Z0",
    "addr:postcode":"g0r 1z0",
    "iso:country":"CA",
    "sg:city":"LA Pocatiere",
    "sg:classifiers":[
        {
            "category":"Railroad",
            "type":"Transportation"
        }
    ],
    "sg:phone":"+1 418 856 2424",
    "sg:postcode":"G0R 1Z0",
    "sg:province":"QC",
    "wof:name":"Via Rail Canada Inc",
    "wof:placetype":"venue"
},
  "geometry": {"coordinates":[-70.03224899999999,47.369015],"type":"Point"}
}