{
  "type": "Feature",
  "properties": {
    "addr:full":"70 Exhibition St # 210 Kentville NS B4N 4K9",
    "addr:housenumber":"70",
    "addr:postcode":"b4n 4k9",
    "addr:street":"Exhibition St # 210",
    "iso:country":"CA",
    "sg:address":"70 Exhibition St # 210",
    "sg:city":"Kentville",
    "sg:classifiers":[
        {
            "category":"Health Services",
            "subcategory":"Doctor",
            "type":"Services"
        }
    ],
    "sg:phone":"+1 902 678 4404",
    "sg:postcode":"B4N 4K9",
    "sg:province":"NS",
    "sg:tags":[
        "physician",
        "surgeon"
    ],
    "wof:name":"E B Howatt Orthopedic Svc Inc",
    "wof:placetype":"venue"
},
  "geometry": {"coordinates":[-64.492836,45.08379],"type":"Point"}
}