{
  "type": "Feature",
  "properties": {
    "addr:full":"1497 Marine Dr # 300 West Vancouver BC V7T 1B8",
    "addr:housenumber":"1497",
    "addr:postcode":"v7t 1b8",
    "addr:street":"Marine Dr # 300",
    "iso:country":"CA",
    "sg:address":"1497 Marine Dr # 300",
    "sg:city":"West Vancouver",
    "sg:classifiers":[
        {
            "category":"Professional",
            "subcategory":"Business Services",
            "type":"Services"
        }
    ],
    "sg:phone":"+1 604 922 5972",
    "sg:postcode":"V7T 1B8",
    "sg:province":"BC",
    "sg:tags":[
        "arbitration",
        "notary"
    ],
    "wof:name":"Sherk, Ken",
    "wof:placetype":"venue"
},
  "geometry": {"coordinates":[-123.156418,49.328392],"type":"Point"}
}