{
  "type": "Feature",
  "properties": {
    "addr:full":"3524 Massey Dr Prince George BC V2N 2M4",
    "addr:housenumber":"3524",
    "addr:postcode":"v2n 2m4",
    "addr:street":"Massey Dr",
    "iso:country":"CA",
    "sg:address":"3524 Massey Dr",
    "sg:city":"Prince George",
    "sg:classifiers":[
        {
            "category":"Retail",
            "subcategory":"Auto Repair",
            "type":"Services"
        }
    ],
    "sg:phone":"+1 250 564 5553",
    "sg:postcode":"V2N 2M4",
    "sg:province":"BC",
    "sg:tags":[
        "repairing",
        "automobile",
        "radiator"
    ],
    "wof:name":"Prince George Radiators Ltd",
    "wof:placetype":"venue"
},
  "geometry": {"coordinates":[-122.787109,53.899822],"type":"Point"}
}