{
  "type": "Feature",
  "properties": {
    "addr:full":"999 6th Ave Hope BC V0X 1L4",
    "addr:housenumber":"999",
    "addr:postcode":"v0x 1l4",
    "addr:street":"6Th Ave",
    "iso:country":"CA",
    "sg:address":"999 6th Ave",
    "sg:city":"Hope",
    "sg:classifiers":[
        {
            "category":"Restaurant",
            "type":"Food & Drink"
        }
    ],
    "sg:phone":"+1 604 869 3834",
    "sg:postcode":"V0X 1L4",
    "sg:province":"BC",
    "wof:name":"Sandwich Tree",
    "wof:placetype":"venue"
},
  "geometry": {"coordinates":[-121.431572,49.378368],"type":"Point"}
}