{
  "type": "Feature",
  "properties": {
    "addr:full":"580 Devonshire Rd Windsor ON N8Y 2L7",
    "addr:housenumber":"580",
    "addr:postcode":"n8y 2l7",
    "addr:street":"Devonshire Rd",
    "iso:country":"CA",
    "sg:address":"580 Devonshire Rd",
    "sg:city":"Windsor",
    "sg:classifiers":[
        {
            "category":"Health Services",
            "subcategory":"Nursing And Care Facility",
            "type":"Services"
        }
    ],
    "sg:phone":"+1 519 258 6255",
    "sg:postcode":"N8Y 2L7",
    "sg:province":"ON",
    "sg:tags":[
        "home",
        "rest"
    ],
    "wof:name":"Willistead Inn",
    "wof:placetype":"venue"
},
  "geometry": {"coordinates":[-83.012016,42.323345],"type":"Point"}
}