{
  "type": "Feature",
  "properties": {
    "addr:full":"Calgary AB T2H 0H2",
    "addr:postcode":"t2h 0h2",
    "iso:country":"CA",
    "sg:city":"Calgary",
    "sg:classifiers":[
        {
            "category":"Professional",
            "type":"Services"
        }
    ],
    "sg:phone":"+1 403 252 5090",
    "sg:postcode":"T2H 0H2",
    "sg:province":"AB",
    "sg:tags":[
        "geophysical"
    ],
    "wof:name":"Cossack Land Svc Ltd",
    "wof:placetype":"venue"
},
  "geometry": {"coordinates":[-114.068375,51.002274],"type":"Point"}
}