{
  "type": "Feature",
  "properties": {
    "addr:full":"Mississauga ON L4V 1T1",
    "addr:postcode":"l4v 1t1",
    "iso:country":"CA",
    "sg:city":"Mississauga",
    "sg:classifiers":[
        {
            "category":"Professional",
            "subcategory":"Computer Services",
            "type":"Services"
        }
    ],
    "sg:phone":"+1 905 678 7588",
    "sg:postcode":"L4V 1T1",
    "sg:province":"ON",
    "sg:tags":[
        "internet"
    ],
    "wof:name":"Canadian Internet Corp",
    "wof:placetype":"venue"
},
  "geometry": {"coordinates":[-79.607956,43.68605],"type":"Point"}
}