{
  "type": "Feature",
  "properties": {
    "addr:full":"Rockland ON K4K 1A9",
    "addr:postcode":"k4k 1a9",
    "addr:street":"Rockland",
    "iso:country":"CA",
    "sg:city":"Rockland",
    "sg:classifiers":[
        {
            "category":"Wholesale",
            "subcategory":"Machinery & Supplies",
            "type":"Manufacturing & Wholesale Goods"
        }
    ],
    "sg:phone":"+1 613 446 5539",
    "sg:postcode":"K4K 1A9",
    "sg:province":"ON",
    "sg:tags":[
        "equipment",
        "industrial"
    ],
    "wof:name":"Industrial Installations Inc",
    "wof:placetype":"venue"
},
  "geometry": {"coordinates":[-75.3013763428,45.5337600708],"type":"Point"}
}