{
  "type": "Feature",
  "properties": {
    "addr:full":"Shawville QC J0X 2Y0",
    "addr:postcode":"j0x 2y0",
    "iso:country":"CA",
    "sg:city":"Shawville",
    "sg:classifiers":[
        {
            "category":"Government",
            "subcategory":"Office",
            "type":"Public Place"
        }
    ],
    "sg:phone":"+1 819 647 3862",
    "sg:postcode":"J0X 2Y0",
    "sg:province":"QC",
    "sg:tags":[
        "village"
    ],
    "wof:name":"Clarendon Municipality",
    "wof:placetype":"venue"
},
  "geometry": {"coordinates":[-76.49992399999999,45.602203],"type":"Point"}
}