{
  "type": "Feature",
  "properties": {
    "iso:country":"CA",
    "sg:city":"Mississauga",
    "sg:classifiers":[
        {
            "category":"Wholesale",
            "subcategory":"Medical Equipment & Supplies",
            "type":"Manufacturing & Wholesale Goods"
        }
    ],
    "sg:phone":"+1 905 275 8000",
    "sg:postcode":"L4Y 3Y3",
    "sg:province":"ON",
    "sg:tags":[
        "hospital"
    ],
    "wof:name":"Bard Canada Inc",
    "wof:placetype":"venue"
},
  "geometry": {"coordinates":[-79.583015,43.598454],"type":"Point"}
}