{
  "type": "Feature",
  "properties": {
    "iso:country":"CA",
    "sg:city":"West Vancouver",
    "sg:classifiers":[
        {
            "category":"Home & Garden",
            "subcategory":"Household Appliances",
            "type":"Retail Goods"
        }
    ],
    "sg:phone":"+1 604 922 9335",
    "sg:postcode":"V7V 1L3",
    "sg:province":"BC",
    "sg:tags":[
        "cleaners",
        "vacuum"
    ],
    "wof:name":"West Van Vacuum Ctr",
    "wof:placetype":"venue"
},
  "geometry": {"coordinates":[-123.180160523,49.3346405029],"type":"Point"}
}