{
  "type": "Feature",
  "properties": {
    "addr:full":"580 Bedford Hwy Halifax NS B3M 2L8",
    "addr:housenumber":"580",
    "addr:postcode":"b3m 2l8",
    "addr:street":"Bedford Hwy",
    "iso:country":"CA",
    "sg:address":"580 Bedford Hwy",
    "sg:city":"Halifax",
    "sg:classifiers":[
        {
            "category":"Real Estate",
            "subcategory":"Real Estate Operator",
            "type":"Services"
        }
    ],
    "sg:phone":"+1 902 457 0001",
    "sg:postcode":"B3M 2L8",
    "sg:province":"NS",
    "sg:tags":[
        "apartment"
    ],
    "wof:name":"Shaunslieve Apartments",
    "wof:placetype":"venue"
},
  "geometry": {"coordinates":[-63.66103,44.695675],"type":"Point"}
}