{
  "type": "Feature",
  "properties": {
    "addr:full":"120 Festival Way Sherwood Park AB T8A 5Z1",
    "addr:housenumber":"120",
    "addr:postcode":"t8a 5z1",
    "addr:street":"Festival Way",
    "iso:country":"CA",
    "sg:address":"120 Festival Way",
    "sg:city":"Sherwood Park",
    "sg:classifiers":[
        {
            "category":"Organizations",
            "subcategory":"Religious Organization",
            "type":"Services"
        }
    ],
    "sg:phone":"+1 780 467 2355",
    "sg:postcode":"T8A 5Z1",
    "sg:province":"AB",
    "sg:tags":[
        "church"
    ],
    "wof:name":"Sherwood Park Seventh-Day Chr",
    "wof:placetype":"venue"
},
  "geometry": {"coordinates":[-113.301582,53.527981],"type":"Point"}
}