{
  "type": "Feature",
  "properties": {
    "addr:full":"22191 Cliff Ave Maple Ridge BC V2X 2L4",
    "addr:housenumber":"22191",
    "addr:postcode":"v2x 2l4",
    "addr:street":"Cliff Ave",
    "iso:country":"CA",
    "sg:address":"22191 Cliff Ave",
    "sg:city":"Maple Ridge",
    "sg:classifiers":[
        {
            "category":"Building & Trades",
            "subcategory":"Construction",
            "type":"Services"
        }
    ],
    "sg:phone":"+1 604 467 0640",
    "sg:postcode":"V2X 2L4",
    "sg:province":"BC",
    "sg:tags":[
        "designer",
        "dealer",
        "pool",
        "swimming"
    ],
    "wof:name":"Catalina Pool Svc Ltd",
    "wof:placetype":"venue"
},
  "geometry": {"coordinates":[-122.60749054,49.2159957886],"type":"Point"}
}