{
  "type": "Feature",
  "properties": {
    "addr:full":"Mississauga ON L5N 5M1",
    "addr:postcode":"l5n 5m1",
    "iso:country":"CA",
    "sg:city":"Mississauga",
    "sg:classifiers":[
        {
            "category":"Wholesale",
            "subcategory":"Electrical",
            "type":"Manufacturing & Wholesale Goods"
        }
    ],
    "sg:phone":"+1 905 812 9636",
    "sg:postcode":"L5N 5M1",
    "sg:province":"ON",
    "sg:tags":[
        "control",
        "security",
        "system"
    ],
    "wof:name":"Ohm Security Ltd",
    "wof:placetype":"venue"
},
  "geometry": {"coordinates":[-79.73671,43.606262],"type":"Point"}
}