{
  "type": "Feature",
  "properties": {
    "addr:full":"1826 Weston Rd York ON M9N 1V8",
    "addr:housenumber":"1826",
    "addr:postcode":"m9n 1v8",
    "addr:street":"Weston Rd",
    "iso:country":"CA",
    "sg:address":"1826 Weston Rd",
    "sg:city":"York",
    "sg:classifiers":[
        {
            "category":"Personal",
            "subcategory":"Beauty Salon",
            "type":"Services"
        }
    ],
    "sg:phone":"+1 416 614 9393",
    "sg:postcode":"M9N 1V8",
    "sg:province":"ON",
    "wof:name":"A & J Hair Creations",
    "wof:placetype":"venue"
},
  "geometry": {"coordinates":[-79.51435089109999,43.6993103027],"type":"Point"}
}