{
  "type": "Feature",
  "properties": {
    "iso:country":"CA",
    "sg:address":"411 Amethyst Cres",
    "sg:city":"Thunder Bay",
    "sg:classifiers":[
        {
            "category":"Shopping",
            "type":"Retail Goods"
        }
    ],
    "sg:phone":"+1 807 577 1379",
    "sg:postcode":"P7C 1T2",
    "sg:province":"ON",
    "sg:tags":[
        "trophy",
        "medal",
        "award"
    ],
    "wof:name":"W N Belbas Enterprises",
    "wof:placetype":"venue"
},
  "geometry": {"coordinates":[-89.2857971191,48.3883781433],"type":"Point"}
}