{
  "type": "Feature",
  "properties": {
    "addr:full":"501 Anderson Ave Radville SK S0C 2G0",
    "addr:housenumber":"501",
    "addr:postcode":"s0c 2g0",
    "addr:street":"Anderson Ave",
    "iso:country":"CA",
    "sg:address":"501 Anderson Ave",
    "sg:city":"Radville",
    "sg:classifiers":[
        {
            "category":"Wholesale",
            "subcategory":"Machinery & Supplies",
            "type":"Manufacturing & Wholesale Goods"
        }
    ],
    "sg:phone":"+1 306 869 3000",
    "sg:postcode":"S0C 2G0",
    "sg:province":"SK",
    "sg:tags":[
        "agricultural",
        "implement",
        "dealer",
        "automobile"
    ],
    "wof:name":"Nelson Motors & Equipment Ltd",
    "wof:placetype":"venue"
},
  "geometry": {"coordinates":[-104.294662,49.460075],"type":"Point"}
}