{
  "type": "Feature",
  "properties": {
    "addr:full":"124 Eglinton Ave W # 103 Toronto ON M4R 2G8",
    "addr:housenumber":"124",
    "addr:postcode":"m4r 2g8",
    "addr:street":"Eglinton Ave W # 103",
    "iso:country":"CA",
    "sg:address":"124 Eglinton Ave W # 103",
    "sg:city":"Toronto",
    "sg:classifiers":[
        {
            "category":"Restaurant",
            "type":"Food & Drink"
        }
    ],
    "sg:phone":"+1 416 483 7289",
    "sg:postcode":"M4R 2G8",
    "sg:province":"ON",
    "wof:name":"Dinah E Cafe",
    "wof:placetype":"venue"
},
  "geometry": {"coordinates":[-79.402199,43.7061],"type":"Point"}
}