{
  "type": "Feature",
  "properties": {
    "addr:full":"62 Pine Dr Sluice Point Tusket NS B0W 3M0",
    "addr:housenumber":"62",
    "addr:postcode":"b0w 3m0",
    "addr:street":"Pine Dr",
    "iso:country":"CA",
    "sg:address":"62 Pine Dr Sluice Point",
    "sg:city":"Tusket",
    "sg:classifiers":[
        {
            "category":"Building & Trades",
            "subcategory":"Construction",
            "type":"Services"
        }
    ],
    "sg:phone":"+1 902 648 3397",
    "sg:postcode":"B0W 3M0",
    "sg:province":"NS",
    "sg:tags":[
        "excavating",
        "contractor",
        "general"
    ],
    "wof:name":"Hoe Hoe Hoe Construction",
    "wof:placetype":"venue"
},
  "geometry": {"coordinates":[-65.976753,43.859447],"type":"Point"}
}