{
  "type": "Feature",
  "properties": {
    "addr:full":"8500 Boul Henri-Bourassa Charlesbourg QC G1G 5X1",
    "addr:housenumber":"8500",
    "addr:postcode":"g1g 5x1",
    "addr:street":"Boul Henri-Bourassa",
    "iso:country":"CA",
    "sg:address":"8500 Boul Henri-Bourassa",
    "sg:city":"Charlesbourg",
    "sg:classifiers":[
        {
            "category":"Real Estate",
            "subcategory":"Real Estate Operator",
            "type":"Services"
        }
    ],
    "sg:phone":"+1 418 626 1547",
    "sg:postcode":"G1G 5X1",
    "sg:province":"QC",
    "sg:tags":[
        "mall",
        "shopping",
        "center"
    ],
    "wof:name":"Centre Commercial Carrefour",
    "wof:placetype":"venue"
},
  "geometry": {"coordinates":[-71.270775,46.865112],"type":"Point"}
}