{
  "type": "Feature",
  "properties": {
    "addr:full":"London ON N6B 3R5",
    "addr:postcode":"n6b 3r5",
    "iso:country":"CA",
    "sg:city":"London",
    "sg:classifiers":[
        {
            "category":"Professional",
            "subcategory":"Business Services",
            "type":"Services"
        }
    ],
    "sg:phone":"+1 519 858 3447",
    "sg:postcode":"N6B 3R5",
    "sg:province":"ON",
    "sg:tags":[
        "interior",
        "consultant",
        "design",
        "decorator"
    ],
    "wof:name":"Fran Rubin Interiors",
    "wof:placetype":"venue"
},
  "geometry": {"coordinates":[-81.24453735349999,42.9870033264],"type":"Point"}
}