{
  "type": "Feature",
  "properties": {
    "addr:full":"261 College St Toronto ON M5T 1R5",
    "addr:housenumber":"261",
    "addr:postcode":"m5t 1r5",
    "addr:street":"College St",
    "iso:country":"CA",
    "sg:address":"261 College St",
    "sg:city":"Toronto",
    "sg:classifiers":[
        {
            "category":"Food & Beverages",
            "subcategory":"Groceries & Convenience Stores",
            "type":"Retail Goods"
        }
    ],
    "sg:phone":"+1 416 971 7878",
    "sg:postcode":"M5T 1R5",
    "sg:province":"ON",
    "wof:name":"Mega Convenience",
    "wof:placetype":"venue"
},
  "geometry": {"coordinates":[-79.3993225098,43.6578788757],"type":"Point"}
}