{
  "type": "Feature",
  "properties": {
    "addr:full":"Montreal QC H4C 1R1",
    "addr:postcode":"h4c 1r1",
    "iso:country":"CA",
    "sg:city":"Montreal",
    "sg:classifiers":[
        {
            "category":"Banks & Credit Unions",
            "subcategory":"Financial Services",
            "type":"Services"
        }
    ],
    "sg:phone":"+1 514 933 4511",
    "sg:postcode":"H4C 1R1",
    "sg:province":"QC",
    "sg:tags":[
        "bankruptcy",
        "trustee"
    ],
    "wof:name":"H H Davis & Assoc Inc",
    "wof:placetype":"venue"
},
  "geometry": {"coordinates":[-73.5340270996,45.5463905334],"type":"Point"}
}