{
  "type": "Feature",
  "properties": {
    "addr:full":"990 Ch Saint-Joseph Saint-Nicolas QC G7A 2A2",
    "addr:housenumber":"990",
    "addr:postcode":"g7a 2a2",
    "addr:street":"Ch Saint-Joseph",
    "iso:country":"CA",
    "sg:address":"990 Ch Saint-Joseph",
    "sg:city":"Saint-Nicolas",
    "sg:classifiers":[
        {
            "category":"Retail",
            "subcategory":"Auto Repair",
            "type":"Services"
        }
    ],
    "sg:phone":"+1 418 831 4574",
    "sg:postcode":"G7A 2A2",
    "sg:province":"QC",
    "sg:tags":[
        "repairing",
        "automobile"
    ],
    "wof:name":"Garage Yves Pomerleau Enr",
    "wof:placetype":"venue"
},
  "geometry": {"coordinates":[-71.34256000000001,46.696171],"type":"Point"}
}