{
  "type": "Feature",
  "properties": {
    "addr:full":"548 Ch D'Aylmer Aylmer QC J9H 1B1",
    "addr:housenumber":"548",
    "addr:postcode":"j9h 1b1",
    "addr:street":"Ch D'Aylmer",
    "iso:country":"CA",
    "sg:address":"548 Ch D'Aylmer",
    "sg:city":"Aylmer",
    "sg:classifiers":[
        {
            "category":"Food & Beverages",
            "subcategory":"Groceries & Convenience Stores",
            "type":"Retail Goods"
        }
    ],
    "sg:phone":"+1 819 684 2289",
    "sg:postcode":"J9H 1B1",
    "sg:province":"QC",
    "wof:name":"Magasin General",
    "wof:placetype":"venue"
},
  "geometry": {"coordinates":[-75.824608,45.396294],"type":"Point"}
}