{
  "type": "Feature",
  "properties": {
    "addr:full":"122 Pears Ave Toronto ON M5R 1T2",
    "addr:housenumber":"122",
    "addr:postcode":"m5r 1t2",
    "addr:street":"Pears Ave",
    "iso:country":"CA",
    "sg:address":"122 Pears Ave",
    "sg:city":"Toronto",
    "sg:classifiers":[
        {
            "category":"Professional",
            "subcategory":"Management & Consulting",
            "type":"Services"
        }
    ],
    "sg:phone":"+1 416 944 9900",
    "sg:postcode":"M5R 1T2",
    "sg:province":"ON",
    "sg:tags":[
        "project",
        "general",
        "contractor"
    ],
    "wof:name":"Murakami Design Build Inc",
    "wof:placetype":"venue"
},
  "geometry": {"coordinates":[-79.397369,43.675617],"type":"Point"}
}