{
  "type": "Feature",
  "properties": {
    "iso:country":"CA",
    "sg:address":"99 Rue Beaubien O",
    "sg:city":"Montreal",
    "sg:classifiers":[
        {
            "category":"Retail",
            "subcategory":"Auto Repair",
            "type":"Services"
        }
    ],
    "sg:phone":"+1 514 271 5112",
    "sg:postcode":"H2S 1V4",
    "sg:province":"QC",
    "sg:tags":[
        "repairing",
        "automobile"
    ],
    "wof:name":"Excellent Garage Beaubien Inc",
    "wof:placetype":"venue"
},
  "geometry": {"coordinates":[-73.60748291020001,45.5314102173],"type":"Point"}
}