{
  "type": "Feature",
  "properties": {
    "addr:full":"356 Boul Jessop Rimouski QC G5L 1M8",
    "addr:housenumber":"356",
    "addr:postcode":"g5l 1m8",
    "addr:street":"Boul Jessop",
    "iso:country":"CA",
    "sg:address":"356 Boul Jessop",
    "sg:city":"Rimouski",
    "sg:classifiers":[
        {
            "category":"Autos & Motor Vehicles",
            "subcategory":"Fuel & Gas Station",
            "type":"Retail Goods"
        }
    ],
    "sg:phone":"+1 418 724 6212",
    "sg:postcode":"G5L 1M8",
    "sg:province":"QC",
    "sg:tags":[
        "oil"
    ],
    "wof:name":"Depanneur Jessop Enr",
    "wof:placetype":"venue"
},
  "geometry": {"coordinates":[-68.516907,48.464577],"type":"Point"}
}