{
  "type": "Feature",
  "properties": {
    "addr:full":"728 Tagish St Kamloops BC V2H 1B7",
    "addr:housenumber":"728",
    "addr:postcode":"bc v2h 1b7",
    "addr:street":"Tagish St",
    "iso:country":"CA",
    "sg:address":"728 Tagish St",
    "sg:city":"Kamloops",
    "sg:classifiers":[
        {
            "category":"Manufacturing",
            "subcategory":"Tools & Machinery",
            "type":"Manufacturing & Wholesale Goods"
        }
    ],
    "sg:phone":"+1 250 372 3933",
    "sg:postcode":"V2H 1B7",
    "sg:province":"BC",
    "sg:tags":[
        "equipment",
        "hydraulic",
        "supply"
    ],
    "wof:name":"Norcan Fluid Power Ltd",
    "wof:placetype":"venue"
},
  "geometry": {"coordinates":[-120.324234,50.692265],"type":"Point"}
}