{
  "type": "Feature",
  "properties": {
    "addr:full":"Scarborough ON M1P 4P5",
    "addr:postcode":"m1p 4p5",
    "iso:country":"CA",
    "sg:city":"Scarborough",
    "sg:classifiers":[
        {
            "category":"Shopping",
            "subcategory":"Computers & Home Electronics",
            "type":"Retail Goods"
        }
    ],
    "sg:phone":"+1 416 296 0013",
    "sg:postcode":"M1P 4P5",
    "sg:province":"ON",
    "sg:tags":[
        "equipment",
        "dealer"
    ],
    "wof:name":"Compucentre",
    "wof:placetype":"venue"
},
  "geometry": {"coordinates":[-79.25417299999999,43.775551],"type":"Point"}
}