{
  "type": "Feature",
  "properties": {
    "addr:full":"100 Main St Dartmouth NS B2X 1R5",
    "addr:housenumber":"100",
    "addr:postcode":"b2x 1r5",
    "addr:street":"Main St",
    "iso:country":"CA",
    "sg:address":"100 Main St",
    "sg:city":"Dartmouth",
    "sg:classifiers":[
        {
            "category":"Restaurant",
            "type":"Food & Drink"
        }
    ],
    "sg:phone":"+1 902 462 0906",
    "sg:postcode":"B2X 1R5",
    "sg:province":"NS",
    "wof:name":"Swiss Chalet Rotisserie",
    "wof:placetype":"venue"
},
  "geometry": {"coordinates":[-63.5411682129,44.681602478],"type":"Point"}
}