{
  "type": "Feature",
  "properties": {
    "iso:country":"CA",
    "sg:address":"1851 Rue Vincent",
    "sg:city":"Baie-Comeau",
    "sg:classifiers":[
        {
            "category":"Building & Trades",
            "subcategory":"Construction",
            "type":"Services"
        }
    ],
    "sg:phone":"+1 418 589 9009",
    "sg:postcode":"G5C 1C2",
    "sg:province":"QC",
    "sg:tags":[
        "excavating",
        "contractor",
        "general"
    ],
    "wof:name":"Entreprises Laurien Jean Inc",
    "wof:placetype":"venue"
},
  "geometry": {"coordinates":[-68.2818069458,49.1971168518],"type":"Point"}
}