{
  "type": "Feature",
  "properties": {
    "addr:full":"488 Bartholomew Dr Newmarket ON L3X 2E5",
    "addr:housenumber":"488",
    "addr:postcode":"l3x 2e5",
    "addr:street":"Bartholomew Dr",
    "iso:country":"CA",
    "sg:address":"488 Bartholomew Dr",
    "sg:city":"Newmarket",
    "sg:classifiers":[
        {
            "category":"Arts & Performance",
            "subcategory":"Theater",
            "type":"Entertainment"
        }
    ],
    "sg:phone":"+1 905 830 1082",
    "sg:postcode":"L3X 2E5",
    "sg:province":"ON",
    "wof:name":"Newmarket Stage CO",
    "wof:placetype":"venue"
},
  "geometry": {"coordinates":[-79.4866104126,44.0391197205],"type":"Point"}
}