{
  "type": "Feature",
  "properties": {
    "addr:full":"2825 2 Ave S # C Lethbridge AB T1J 0G8",
    "addr:housenumber":"2825",
    "addr:postcode":"t1j 0g8",
    "addr:street":"2 Ave S # C",
    "iso:country":"CA",
    "sg:address":"2825 2 Ave S # C",
    "sg:city":"Lethbridge",
    "sg:classifiers":[
        {
            "category":"Organizations",
            "subcategory":"Professional Association",
            "type":"Services"
        }
    ],
    "sg:phone":"+1 403 327 6399",
    "sg:postcode":"T1J 0G8",
    "sg:province":"AB",
    "sg:tags":[
        "club"
    ],
    "wof:name":"Downtown Optomists-Lethbridge",
    "wof:placetype":"venue"
},
  "geometry": {"coordinates":[-112.80085800000001,49.697369],"type":"Point"}
}