{
  "type": "Feature",
  "properties": {
    "addr:full":"8810 Rue Champ D'Eau Saint-Leonard QC H1P 2Y8",
    "addr:housenumber":"8810",
    "addr:postcode":"h1p 2y8",
    "addr:street":"Rue Champ D'Eau",
    "iso:country":"CA",
    "sg:address":"8810 Rue Champ D'Eau",
    "sg:city":"Saint-Leonard",
    "sg:classifiers":[
        {
            "category":"Wholesale",
            "subcategory":"Hardware",
            "type":"Manufacturing & Wholesale Goods"
        }
    ],
    "sg:phone":"+1 514 327 6444",
    "sg:postcode":"H1P 2Y8",
    "sg:province":"QC",
    "wof:name":"Quincaillerie Architecturale",
    "wof:placetype":"venue"
},
  "geometry": {"coordinates":[-73.5953369141,45.589389801],"type":"Point"}
}