{
  "type": "Feature",
  "properties": {
    "addr:full":"74 Nanwood Dr Brampton ON L6W 1L9",
    "addr:housenumber":"74",
    "addr:postcode":"l6w 1l9",
    "addr:street":"Nanwood Dr",
    "iso:country":"CA",
    "sg:address":"74 Nanwood Dr",
    "sg:city":"Brampton",
    "sg:classifiers":[
        {
            "category":"Wholesale",
            "subcategory":"Scrap",
            "type":"Manufacturing & Wholesale Goods"
        }
    ],
    "sg:phone":"+1 905 450 7798",
    "sg:postcode":"L6W 1L9",
    "sg:province":"ON",
    "sg:tags":[
        "plastic"
    ],
    "wof:name":"G & L Plastic Recycling",
    "wof:placetype":"venue"
},
  "geometry": {"coordinates":[-79.7441329956,43.6810379028],"type":"Point"}
}