{
  "type": "Feature",
  "properties": {
    "addr:full":"5 Rowanwood Ave Brantford ON N3S 7B4",
    "addr:housenumber":"5",
    "addr:postcode":"n3s 7b4",
    "addr:street":"Rowanwood Ave",
    "iso:country":"CA",
    "sg:address":"5 Rowanwood Ave",
    "sg:city":"Brantford",
    "sg:classifiers":[
        {
            "category":"Retail",
            "subcategory":"Auto Repair",
            "type":"Services"
        }
    ],
    "sg:phone":"+1 519 756 5710",
    "sg:postcode":"N3S 7B4",
    "sg:province":"ON",
    "sg:tags":[
        "repairing",
        "automobile"
    ],
    "wof:name":"Maple Leaf Svc Ctr A & N Ltd",
    "wof:placetype":"venue"
},
  "geometry": {"coordinates":[-80.219902,43.144588],"type":"Point"}
}