{
  "type": "Feature",
  "properties": {
    "addr:full":"516 1st Ave N Maple Creek SK S0N 1N0",
    "addr:housenumber":"516",
    "addr:postcode":"s0n 1n0",
    "addr:street":"1St Ave N",
    "iso:country":"CA",
    "sg:address":"516 1st Ave N",
    "sg:city":"Maple Creek",
    "sg:classifiers":[
        {
            "category":"Building & Trades",
            "subcategory":"Construction",
            "type":"Services"
        }
    ],
    "sg:phone":"+1 306 662 3192",
    "sg:postcode":"S0N 1N0",
    "sg:province":"SK",
    "sg:tags":[
        "excavating",
        "contractor"
    ],
    "wof:name":"Prairie Diggers",
    "wof:placetype":"venue"
},
  "geometry": {"coordinates":[-109.480408,49.906586],"type":"Point"}
}