{
  "type": "Feature",
  "properties": {
    "addr:full":"270 Rue Des Aulnaies Saint-Michel-Des-Saints QC J0K 3B0",
    "addr:housenumber":"270",
    "addr:postcode":"j0k 3b0",
    "addr:street":"Rue Des Aulnaies",
    "iso:country":"CA",
    "sg:address":"270 Rue Des Aulnaies",
    "sg:city":"Saint-Michel-Des-Saints",
    "sg:classifiers":[
        {
            "category":"Building & Trades",
            "subcategory":"Construction",
            "type":"Services"
        }
    ],
    "sg:phone":"+1 450 833 1649",
    "sg:postcode":"J0K 3B0",
    "sg:province":"QC",
    "sg:tags":[
        "excavating",
        "contractor"
    ],
    "wof:name":"Champoux S & Fils Inc",
    "wof:placetype":"venue"
},
  "geometry": {"coordinates":[-73.919853,46.68066],"type":"Point"}
}