{
  "type": "Feature",
  "properties": {
    "iso:country":"CA",
    "sg:address":"161 Av Frontenac",
    "sg:city":"Pointe-Claire",
    "sg:classifiers":[
        {
            "category":"Education",
            "subcategory":"Special Training",
            "type":"Public Place"
        }
    ],
    "sg:phone":"+1 514 694 7178",
    "sg:postcode":"H9R 4Z7",
    "sg:province":"QC",
    "sg:tags":[
        "school",
        "language"
    ],
    "wof:name":"Communications Anima Ltee",
    "wof:placetype":"venue"
},
  "geometry": {"coordinates":[-73.827194,45.469086],"type":"Point"}
}