{
  "type": "Feature",
  "properties": {
    "iso:country":"CA",
    "sg:city":"Montreal",
    "sg:classifiers":[
        {
            "category":"Real Estate",
            "subcategory":"Real Estate Agent",
            "type":"Services"
        }
    ],
    "sg:phone":"+1 514 522 4558",
    "sg:postcode":"H2K 1C3",
    "sg:province":"QC",
    "sg:tags":[
        "building",
        "parks",
        "desk"
    ],
    "wof:name":"Edifice Lafontaine",
    "wof:placetype":"venue"
},
  "geometry": {"coordinates":[-73.562744,45.531067],"type":"Point"}
}