{
  "type": "Feature",
  "properties": {
    "addr:full":"2388 Fairview St Burlington ON L7R 2E4",
    "addr:housenumber":"2388",
    "addr:postcode":"l7r 2e4",
    "addr:street":"Fairview St",
    "iso:country":"CA",
    "sg:address":"2388 Fairview St",
    "sg:city":"Burlington",
    "sg:classifiers":[
        {
            "category":"Shopping",
            "subcategory":"Musical Instruments",
            "type":"Retail Goods"
        }
    ],
    "sg:phone":"+1 905 639 4465",
    "sg:postcode":"L7R 2E4",
    "sg:province":"ON",
    "sg:tags":[
        "piano"
    ],
    "wof:name":"Keyboard Centre",
    "wof:placetype":"venue"
},
  "geometry": {"coordinates":[-79.8010635376,43.3442726135],"type":"Point"}
}