{
  "type": "Feature",
  "properties": {
    "addr:full":"70 Rue Simonds N Granby QC J2J 2L1",
    "addr:housenumber":"70",
    "addr:postcode":"j2j 2l1",
    "addr:street":"Rue Simonds N",
    "iso:country":"CA",
    "sg:address":"70 Rue Simonds N",
    "sg:city":"Granby",
    "sg:classifiers":[
        {
            "category":"Autos & Motor Vehicles",
            "subcategory":"Auto Supplies",
            "type":"Retail Goods"
        }
    ],
    "sg:phone":"+1 450 378 9884",
    "sg:postcode":"J2J 2L1",
    "sg:province":"QC",
    "sg:tags":[
        "automobile",
        "parts"
    ],
    "wof:name":"Canadian Tire",
    "wof:placetype":"venue"
},
  "geometry": {"coordinates":[-72.753891,45.416466],"type":"Point"}
}