{
  "type": "Feature",
  "properties": {
    "addr:full":"Surrey BC V3W 4Z9",
    "addr:postcode":"v3w 4z9",
    "iso:country":"CA",
    "sg:city":"Surrey",
    "sg:classifiers":[
        {
            "category":"Wholesale",
            "subcategory":"Machinery & Supplies",
            "type":"Manufacturing & Wholesale Goods"
        }
    ],
    "sg:phone":"+1 604 597 9122",
    "sg:postcode":"V3W 4Z9",
    "sg:province":"BC",
    "sg:tags":[
        "dyer",
        "cleaners",
        "equipment",
        "heating",
        "contractor"
    ],
    "wof:name":"Canadian Heat Installations",
    "wof:placetype":"venue"
},
  "geometry": {"coordinates":[-122.845589,49.126202],"type":"Point"}
}