{
  "type": "Feature",
  "properties": {
    "addr:full":"911 Eadie Rd Russell ON K4R 1E5",
    "addr:housenumber":"911",
    "addr:postcode":"k4r 1e5",
    "addr:street":"Eadie Rd",
    "iso:country":"CA",
    "sg:address":"911 Eadie Rd",
    "sg:city":"Russell",
    "sg:classifiers":[
        {
            "category":"Retail",
            "subcategory":"Animal Services",
            "type":"Services"
        }
    ],
    "sg:phone":"+1 613 445 3308",
    "sg:postcode":"K4R 1E5",
    "sg:province":"ON",
    "sg:tags":[
        "pet",
        "boarding",
        "sitting"
    ],
    "wof:name":"Willow Glen Pet Lodge & Spa",
    "wof:placetype":"venue"
},
  "geometry": {"coordinates":[-75.350311,45.273907],"type":"Point"}
}