{
  "type": "Feature",
  "properties": {
    "addr:full":"117 Churchill Rd Foam Lake SK S0A 1A0",
    "addr:housenumber":"117",
    "addr:postcode":"s0a 1a0",
    "addr:street":"Churchill Rd",
    "iso:country":"CA",
    "sg:address":"117 Churchill Rd",
    "sg:city":"Foam Lake",
    "sg:classifiers":[
        {
            "category":"Building & Trades",
            "subcategory":"Construction",
            "type":"Services"
        }
    ],
    "sg:phone":"+1 306 272 4407",
    "sg:postcode":"S0A 1A0",
    "sg:province":"SK",
    "sg:tags":[
        "sandblasting"
    ],
    "wof:name":"Norm's Sandblasting & Painting",
    "wof:placetype":"venue"
},
  "geometry": {"coordinates":[-103.539390564,51.6393051147],"type":"Point"}
}