{
  "type": "Feature",
  "properties": {
    "iso:country":"CA",
    "sg:address":"1155 Boul Rene-Levesque O",
    "sg:city":"Montreal",
    "sg:classifiers":[
        {
            "category":"Restaurant",
            "type":"Food & Drink"
        }
    ],
    "sg:phone":"+1 514 874 9412",
    "sg:postcode":"H3B 4P7",
    "sg:province":"QC",
    "wof:name":"Fontaine Sante",
    "wof:placetype":"venue"
},
  "geometry": {"coordinates":[-73.554436,45.517063],"type":"Point"}
}