{
  "type": "Feature",
  "properties": {
    "addr:full":"Labrador City NL A2V 2B7",
    "addr:postcode":"a2v 2b7",
    "iso:country":"CA",
    "sg:city":"Labrador City",
    "sg:classifiers":[
        {
            "category":"Wholesale",
            "subcategory":"Machinery & Supplies",
            "type":"Manufacturing & Wholesale Goods"
        }
    ],
    "sg:phone":"+1 709 944 5899",
    "sg:postcode":"A2V 2B7",
    "sg:province":"NL",
    "sg:tags":[
        "equipment",
        "mining"
    ],
    "wof:name":"Bucyrus Canada Ltd",
    "wof:placetype":"venue"
},
  "geometry": {"coordinates":[-66.9059753418,52.9438667297],"type":"Point"}
}