{
  "type": "Feature",
  "properties": {
    "iso:country":"CA",
    "sg:address":"106 Elgin St",
    "sg:city":"Almonte",
    "sg:classifiers":[
        {
            "category":"Organizations",
            "subcategory":"Religious Organization",
            "type":"Services"
        }
    ],
    "sg:phone":"+1 613 256 1355",
    "sg:postcode":"K0A 1A0",
    "sg:province":"ON",
    "sg:tags":[
        "church"
    ],
    "wof:name":"Almonte United Church",
    "wof:placetype":"venue"
},
  "geometry": {"coordinates":[-76.1934127808,45.2235908508],"type":"Point"}
}