{
  "type": "Feature",
  "properties": {
    "iso:country":"CA",
    "sg:city":"King City",
    "sg:classifiers":[
        {
            "category":"Shopping",
            "subcategory":"Discount & Variety Stores",
            "type":"Retail Goods"
        }
    ],
    "sg:phone":"+1 905 833 3548",
    "sg:postcode":"L7B 1L5",
    "sg:province":"ON",
    "wof:name":"King's Variety",
    "wof:placetype":"venue"
},
  "geometry": {"coordinates":[-79.525665,43.929405],"type":"Point"}
}