{
  "type": "Feature",
  "properties": {
    "addr:full":"1395 Rue Mantha Evain QC J0Z 1Y0",
    "addr:housenumber":"1395",
    "addr:postcode":"j0z 1y0",
    "addr:street":"Rue Mantha Evain",
    "iso:country":"CA",
    "sg:address":"1395 Rue Mantha",
    "sg:city":"Evain",
    "sg:classifiers":[
        {
            "category":"Health Services",
            "subcategory":"Medical Lab",
            "type":"Services"
        }
    ],
    "sg:phone":"+1 819 768 5411",
    "sg:postcode":"J0Z 1Y0",
    "sg:province":"QC",
    "wof:name":"Cabinet DE Denturologie",
    "wof:placetype":"venue"
},
  "geometry": {"coordinates":[-79.230698,48.322769],"type":"Point"}
}