{
  "type": "Feature",
  "properties": {
    "addr:full":"6516 Tronson Rd Vernon BC V1H 1N5",
    "addr:housenumber":"6516",
    "addr:postcode":"v1h 1n5",
    "addr:street":"Tronson Rd",
    "iso:country":"CA",
    "sg:address":"6516 Tronson Rd",
    "sg:city":"Vernon",
    "sg:classifiers":[
        {
            "category":"Retail",
            "subcategory":"Repair Shop",
            "type":"Services"
        }
    ],
    "sg:phone":"+1 250 542 0014",
    "sg:postcode":"V1H 1N5",
    "sg:province":"BC",
    "sg:tags":[
        "upholsterer"
    ],
    "wof:name":"Capricorn Upholstery",
    "wof:placetype":"venue"
},
  "geometry": {"coordinates":[-119.326004,50.248981],"type":"Point"}
}