{
  "type": "Feature",
  "properties": {
    "addr:full":"725 Boul Cure-Labelle Laval QC H7V 2V2",
    "addr:housenumber":"725",
    "addr:postcode":"h7v 2v2",
    "addr:street":"Boul Cure-Labelle",
    "iso:country":"CA",
    "sg:address":"725 Boul Cure-Labelle",
    "sg:city":"Laval",
    "sg:classifiers":[
        {
            "category":"Retail",
            "subcategory":"Auto Repair",
            "type":"Services"
        }
    ],
    "sg:phone":"+1 450 682 1913",
    "sg:postcode":"H7V 2V2",
    "sg:province":"QC",
    "sg:tags":[
        "repairing",
        "automobile"
    ],
    "wof:name":"Garage Delphi Inc",
    "wof:placetype":"venue"
},
  "geometry": {"coordinates":[-73.74579620359999,45.5385818481],"type":"Point"}
}