{
  "type": "Feature",
  "properties": {
    "iso:country":"CA",
    "sg:city":"Surrey",
    "sg:classifiers":[
        {
            "category":"Insurance",
            "subcategory":"Insurance Agent",
            "type":"Services"
        }
    ],
    "sg:phone":"+1 604 205 1000",
    "sg:postcode":"V3R 9V8",
    "sg:province":"BC",
    "wof:name":"British Columbia Automobile",
    "wof:placetype":"venue"
},
  "geometry": {"coordinates":[-122.798667908,49.1863250732],"type":"Point"}
}