{
  "type": "Feature",
  "properties": {
    "addr:full":"PO Box 150 Duffield AB T0E 0N0",
    "addr:housenumber":"po",
    "addr:postcode":"t0e 0n0",
    "addr:street":"Box 150",
    "iso:country":"CA",
    "sg:address":"PO Box 150",
    "sg:city":"Duffield",
    "sg:classifiers":[
        {
            "category":"Manufacturing",
            "subcategory":"Tools & Machinery",
            "type":"Manufacturing & Wholesale Goods"
        }
    ],
    "sg:phone":"+1 780 963 6981",
    "sg:postcode":"T0E 0N0",
    "sg:province":"AB",
    "sg:tags":[
        "machine",
        "shop"
    ],
    "wof:name":"Grund Industries",
    "wof:placetype":"venue"
},
  "geometry": {"coordinates":[-114.345657,53.527634],"type":"Point"}
}