{
  "type": "Feature",
  "properties": {
    "addr:full":"Port Perry ON L9L 1H9",
    "addr:postcode":"l9l 1h9",
    "iso:country":"CA",
    "sg:city":"Port Perry",
    "sg:classifiers":[
        {
            "category":"Food & Beverages",
            "subcategory":"Groceries & Convenience Stores",
            "type":"Retail Goods"
        }
    ],
    "sg:phone":"+1 905 985 0096",
    "sg:postcode":"L9L 1H9",
    "sg:province":"ON",
    "wof:name":"Mister Convenience",
    "wof:placetype":"venue"
},
  "geometry": {"coordinates":[-78.93931600000001,44.101707],"type":"Point"}
}