{
  "type": "Feature",
  "properties": {
    "iso:country":"CA",
    "sg:address":"3636 46 Ave SE",
    "sg:city":"Calgary",
    "sg:classifiers":[
        {
            "category":"Freight",
            "type":"Transportation"
        }
    ],
    "sg:phone":"+1 403 276 9003",
    "sg:postcode":"T2B 3P9",
    "sg:province":"AB",
    "sg:tags":[
        "mover"
    ],
    "wof:name":"Jay's Moving & Storage Ltd",
    "wof:placetype":"venue"
},
  "geometry": {"coordinates":[-113.980461121,51.0124588013],"type":"Point"}
}