{
  "type": "Feature",
  "properties": {
    "addr:full":"3636 46 Ave SE Calgary AB T2B 3P9",
    "addr:housenumber":"3636",
    "addr:postcode":"t2b 3p9",
    "addr:street":"46 Ave Se",
    "iso:country":"CA",
    "sg:address":"3636 46 Ave SE",
    "sg:city":"Calgary",
    "sg:classifiers":[
        {
            "category":"Freight",
            "type":"Transportation"
        }
    ],
    "sg:phone":"+1 403 276 9003",
    "sg:postcode":"T2B 3P9",
    "sg:province":"AB",
    "sg:tags":[
        "mover"
    ],
    "wof:name":"Jay's Moving & Storage Ltd",
    "wof:placetype":"venue"
},
  "geometry": {"coordinates":[-113.980461121,51.0124588013],"type":"Point"}
}