{
  "type": "Feature",
  "properties": {
    "iso:country":"CA",
    "sg:address":"1 Poplar Cres",
    "sg:city":"Brechin",
    "sg:classifiers":[
        {
            "category":"Travel",
            "subcategory":"Hotels & Motels",
            "type":"Entertainment"
        }
    ],
    "sg:phone":"+1 705 484 5366",
    "sg:postcode":"L0K 1B0",
    "sg:province":"ON",
    "sg:tags":[
        "resort"
    ],
    "wof:name":"Harbour Inn & Resort Club",
    "wof:placetype":"venue"
},
  "geometry": {"coordinates":[-79.215469,44.549255],"type":"Point"}
}