{
  "type": "Feature",
  "properties": {
    "addr:full":"26 Notre Dame St Sydney Mines NS B1V 2R7",
    "addr:housenumber":"26",
    "addr:postcode":"b1v 2r7",
    "addr:street":"Notre Dame St",
    "iso:country":"CA",
    "sg:address":"26 Notre Dame St",
    "sg:city":"Sydney Mines",
    "sg:classifiers":[
        {
            "category":"Organizations",
            "subcategory":"Non-profit Organization",
            "type":"Services"
        }
    ],
    "sg:phone":"+1 902 736 2804",
    "sg:postcode":"B1V 2R7",
    "sg:province":"NS",
    "sg:tags":[
        "charitable",
        "institution"
    ],
    "wof:name":"Resi-Care Cb Assoc",
    "wof:placetype":"venue"
},
  "geometry": {"coordinates":[-60.21553,46.241234],"type":"Point"}
}