{
  "type": "Feature",
  "properties": {
    "iso:country":"CA",
    "sg:city":"Vancouver",
    "sg:classifiers":[
        {
            "category":"Education",
            "subcategory":"College",
            "type":"Public Place"
        }
    ],
    "sg:phone":"+1 604 915 9675",
    "sg:postcode":"V6B 1Y1",
    "sg:province":"BC",
    "sg:tags":[
        "academic",
        "school"
    ],
    "wof:name":"Vancouver Career College",
    "wof:placetype":"venue"
},
  "geometry": {"coordinates":[-123.11518096899999,49.2826538086],"type":"Point"}
}