{
  "type": "Feature",
  "properties": {
    "addr:full":"60 Main St S Minnedosa MB R0J 1E0",
    "addr:housenumber":"60",
    "addr:postcode":"r0j 1e0",
    "addr:street":"Main St S Minnedosa",
    "iso:country":"CA",
    "sg:address":"60 Main St S",
    "sg:city":"Minnedosa",
    "sg:classifiers":[
        {
            "category":"Banks & Credit Unions",
            "subcategory":"Bank",
            "type":"Services"
        }
    ],
    "sg:phone":"+1 204 867 2781",
    "sg:postcode":"R0J 1E0",
    "sg:province":"MB",
    "wof:name":"Minnedosa Credit Union Ltd",
    "wof:placetype":"venue"
},
  "geometry": {"coordinates":[-99.838623,50.247021],"type":"Point"}
}