{
  "type": "Feature",
  "properties": {
    "iso:country":"CA",
    "sg:address":"2102 Dalecroft Cres",
    "sg:city":"Burlington",
    "sg:classifiers":[
        {
            "category":"Professional",
            "subcategory":"Management & Consulting",
            "type":"Services"
        }
    ],
    "sg:phone":"+1 905 331 2691",
    "sg:postcode":"L7M 4B3",
    "sg:province":"ON",
    "sg:tags":[
        "consultant",
        "business"
    ],
    "wof:name":"Lenvil Industries Ltd",
    "wof:placetype":"venue"
},
  "geometry": {"coordinates":[-79.8095245361,43.3871498108],"type":"Point"}
}