{
  "type": "Feature",
  "properties": {
    "iso:country":"CA",
    "sg:address":"6405 Main St",
    "sg:city":"Comber",
    "sg:classifiers":[
        {
            "category":"Health Services",
            "subcategory":"Doctor",
            "type":"Services"
        }
    ],
    "sg:phone":"+1 519 687 2333",
    "sg:postcode":"N0P 1J0",
    "sg:province":"ON",
    "sg:tags":[
        "physician",
        "surgeon"
    ],
    "wof:name":"Anderson, R MD",
    "wof:placetype":"venue"
},
  "geometry": {"coordinates":[-82.5529556274,42.2309837341],"type":"Point"}
}