{
  "type": "Feature",
  "properties": {
    "iso:country":"CA",
    "sg:address":"10441 Hollybank Dr",
    "sg:city":"Richmond",
    "sg:classifiers":[
        {
            "category":"Wholesale",
            "subcategory":"Durable Goods & Equipment",
            "type":"Manufacturing & Wholesale Goods"
        }
    ],
    "sg:phone":"+1 604 277 4200",
    "sg:postcode":"V7E 4S4",
    "sg:province":"BC",
    "sg:tags":[
        "importer"
    ],
    "wof:name":"Grand Prospect Enterprises Ltd",
    "wof:placetype":"venue"
},
  "geometry": {"coordinates":[-123.16759491000001,49.1365814209],"type":"Point"}
}