{
  "type": "Feature",
  "properties": {
    "iso:country":"CA",
    "sg:city":"Toronto",
    "sg:classifiers":[
        {
            "category":"Professional",
            "subcategory":"Management & Consulting",
            "type":"Services"
        }
    ],
    "sg:phone":"+1 416 359 0311",
    "sg:postcode":"M5A 2V1",
    "sg:province":"ON",
    "sg:tags":[
        "marketing",
        "consultant"
    ],
    "wof:name":"M Marketing Svc Inc",
    "wof:placetype":"venue"
},
  "geometry": {"coordinates":[-79.36609649659999,43.6528816223],"type":"Point"}
}