{
  "type": "Feature",
  "properties": {
    "addr:full":"774 Beach Blvd Hamilton ON L8H 6Z1",
    "addr:housenumber":"774",
    "addr:postcode":"l8h 6z1",
    "addr:street":"Beach Blvd",
    "iso:country":"CA",
    "sg:address":"774 Beach Blvd",
    "sg:city":"Hamilton",
    "sg:classifiers":[
        {
            "category":"Building & Trades",
            "subcategory":"Construction",
            "type":"Services"
        }
    ],
    "sg:phone":"+1 905 549 3903",
    "sg:postcode":"L8H 6Z1",
    "sg:province":"ON",
    "sg:tags":[
        "roofing",
        "contractor"
    ],
    "wof:name":"W A Scott & Son",
    "wof:placetype":"venue"
},
  "geometry": {"coordinates":[-79.787216,43.284004],"type":"Point"}
}