{
  "type": "Feature",
  "properties": {
    "addr:full":"Warman SK S0K 4S0",
    "addr:postcode":"s0k 4s0",
    "iso:country":"CA",
    "sg:city":"Warman",
    "sg:classifiers":[
        {
            "category":"Building & Trades",
            "subcategory":"Construction",
            "type":"Services"
        }
    ],
    "sg:phone":"+1 306 933 3334",
    "sg:postcode":"S0K 4S0",
    "sg:province":"SK",
    "sg:tags":[
        "downspouts",
        "gutter",
        "general",
        "contractor"
    ],
    "wof:name":"Vic's Eavestroughing Ltd",
    "wof:placetype":"venue"
},
  "geometry": {"coordinates":[-106.572525,52.318489],"type":"Point"}
}