{
  "type": "Feature",
  "properties": {
    "addr:full":"703 Sandy Beach Rd RR 7 Pembroke ON K8A 6W8",
    "addr:housenumber":"703;7",
    "addr:postcode":"k8a 6w8",
    "addr:street":"Sandy Beach Rd Rr",
    "iso:country":"CA",
    "sg:address":"703 Sandy Beach Rd RR 7",
    "sg:city":"Pembroke",
    "sg:classifiers":[
        {
            "category":"Manufacturing",
            "subcategory":"Tools & Machinery",
            "type":"Manufacturing & Wholesale Goods"
        }
    ],
    "sg:phone":"+1 613 735 0400",
    "sg:postcode":"K8A 6W8",
    "sg:province":"ON",
    "sg:tags":[
        "sheet",
        "work",
        "metal",
        "contractor"
    ],
    "wof:name":"Balance Sheet Metal",
    "wof:placetype":"venue"
},
  "geometry": {"coordinates":[-77.1122131348,45.8264808655],"type":"Point"}
}