{
  "type": "Feature",
  "properties": {
    "addr:full":"785 Main St Woodstock NB E7M 2E9",
    "addr:housenumber":"785",
    "addr:postcode":"e7m 2e9",
    "addr:street":"Main St",
    "iso:country":"CA",
    "sg:address":"785 Main St",
    "sg:city":"Woodstock",
    "sg:classifiers":[
        {
            "category":"Health Services",
            "subcategory":"Hospital",
            "type":"Services"
        }
    ],
    "sg:phone":"+1 506 325 6700",
    "sg:postcode":"E7M 2E9",
    "sg:province":"NB",
    "wof:name":"Carleton Memorial Hospital",
    "wof:placetype":"venue"
},
  "geometry": {"coordinates":[-67.57386,46.159588],"type":"Point"}
}