{
  "type": "Feature",
  "properties": {
    "iso:country":"CA",
    "sg:address":"147 Ch Du Lac Bleu",
    "sg:city":"Saint-Hippolyte",
    "sg:classifiers":[
        {
            "category":"Building & Trades",
            "subcategory":"Landscaping Services",
            "type":"Services"
        }
    ],
    "sg:phone":"+1 450 563 3486",
    "sg:postcode":"J8A 1L7",
    "sg:province":"QC",
    "sg:tags":[
        "excavating",
        "landscape",
        "contractor"
    ],
    "wof:name":"Lachance, Michel",
    "wof:placetype":"venue"
},
  "geometry": {"coordinates":[-73.9946594238,45.8760910034],"type":"Point"}
}