{
  "type": "Feature",
  "properties": {
    "addr:full":"454 Broadway W Vancouver BC V5Y 1R3",
    "addr:housenumber":"454",
    "addr:postcode":"v5y 1r3",
    "addr:street":"Broadway W",
    "iso:country":"CA",
    "sg:address":"454 Broadway W",
    "sg:city":"Vancouver",
    "sg:classifiers":[
        {
            "category":"Insurance",
            "subcategory":"Insurance Agent",
            "type":"Services"
        }
    ],
    "sg:phone":"+1 604 876 0126",
    "sg:postcode":"V5Y 1R3",
    "sg:province":"BC",
    "wof:name":"Cassells Insurance Ltd",
    "wof:placetype":"venue"
},
  "geometry": {"coordinates":[-123.113998,49.263088],"type":"Point"}
}