{
  "type": "Feature",
  "properties": {
    "iso:country":"CA",
    "sg:address":"1062 Adelaide St N",
    "sg:city":"London",
    "sg:classifiers":[
        {
            "category":"Sports & Exercise",
            "subcategory":"Bowling",
            "type":"Entertainment"
        }
    ],
    "sg:phone":"+1 519 433 0681",
    "sg:postcode":"N5Y 2N1",
    "sg:province":"ON",
    "sg:tags":[
        "center"
    ],
    "wof:name":"Brunswick Huron Bowl",
    "wof:placetype":"venue"
},
  "geometry": {"coordinates":[-81.241447,43.009178],"type":"Point"}
}