{
  "type": "Feature",
  "properties": {
    "addr:full":"Airport Rd Timmins ON P4N 7C3",
    "addr:postcode":"p4n 7c3",
    "addr:street":"Airport Rd",
    "iso:country":"CA",
    "sg:address":"Airport Rd",
    "sg:city":"Timmins",
    "sg:classifiers":[
        {
            "category":"Professional",
            "subcategory":"Detective & Security Services",
            "type":"Services"
        }
    ],
    "sg:phone":"+1 705 360 1055",
    "sg:postcode":"P4N 7C3",
    "sg:province":"ON",
    "sg:tags":[
        "guard",
        "patrol"
    ],
    "wof:name":"Aeroguard Eastern Ltd",
    "wof:placetype":"venue"
},
  "geometry": {"coordinates":[-81.370682,48.560265],"type":"Point"}
}