{
  "type": "Feature",
  "properties": {
    "addr:full":"900 Rue Notre-Dame E Victoriaville QC G6P 4B7",
    "addr:housenumber":"900",
    "addr:postcode":"g6p 4b7",
    "addr:street":"Rue Notre-Dame E",
    "iso:country":"CA",
    "sg:address":"900 Rue Notre-Dame E",
    "sg:city":"Victoriaville",
    "sg:classifiers":[
        {
            "category":"Autos & Motor Vehicles",
            "subcategory":"Auto Supplies",
            "type":"Retail Goods"
        }
    ],
    "sg:phone":"+1 819 752 4567",
    "sg:postcode":"G6P 4B7",
    "sg:province":"QC",
    "sg:tags":[
        "repairing",
        "automobile"
    ],
    "wof:name":"Alignement Rondeau Inc",
    "wof:placetype":"venue"
},
  "geometry": {"coordinates":[-71.94001799999999,46.066978],"type":"Point"}
}