{
  "type": "Feature",
  "properties": {
    "addr:full":"450 Av Michel-Jasmin Dorval QC H9P 1C1",
    "addr:housenumber":"450",
    "addr:postcode":"h9p 1c1",
    "addr:street":"Av Michel-Jasmin",
    "iso:country":"CA",
    "sg:address":"450 Av Michel-Jasmin",
    "sg:city":"Dorval",
    "sg:classifiers":[
        {
            "category":"Manufacturing",
            "subcategory":"Tools & Machinery",
            "type":"Manufacturing & Wholesale Goods"
        }
    ],
    "sg:phone":"+1 514 631 4608",
    "sg:postcode":"H9P 1C1",
    "sg:province":"QC",
    "sg:tags":[
        "machine",
        "shop"
    ],
    "wof:name":"A-Z Tooling & Machine Works",
    "wof:placetype":"venue"
},
  "geometry": {"coordinates":[-73.73465,45.453758],"type":"Point"}
}