{
  "type": "Feature",
  "properties": {
    "addr:full":"186 Main St NW Roblin MB R0L 1P0",
    "addr:housenumber":"186",
    "addr:postcode":"roblin;r0l 1p0",
    "addr:street":"Main St Nw",
    "iso:country":"CA",
    "sg:address":"186 Main St NW",
    "sg:city":"Roblin",
    "sg:classifiers":[
        {
            "category":"Shopping",
            "subcategory":"Department Store",
            "type":"Retail Goods"
        }
    ],
    "sg:phone":"+1 204 937 4866",
    "sg:postcode":"R0L 1P0",
    "sg:province":"MB",
    "sg:tags":[
        "shop"
    ],
    "wof:name":"Your Dollar Store With More",
    "wof:placetype":"venue"
},
  "geometry": {"coordinates":[-101.351692,51.230598],"type":"Point"}
}