{
  "type": "Feature",
  "properties": {
    "addr:full":"281 Rue Saint-Jean-Baptiste Coaticook QC J1A 2J5",
    "addr:housenumber":"281",
    "addr:postcode":"j1a 2j5",
    "addr:street":"Rue Saint-Jean-Baptiste",
    "iso:country":"CA",
    "sg:address":"281 Rue Saint-Jean-Baptiste",
    "sg:city":"Coaticook",
    "sg:classifiers":[
        {
            "category":"Personal",
            "subcategory":"Beauty Salon",
            "type":"Services"
        }
    ],
    "sg:phone":"+1 819 849 0321",
    "sg:postcode":"J1A 2J5",
    "sg:province":"QC",
    "wof:name":"Design Beaute",
    "wof:placetype":"venue"
},
  "geometry": {"coordinates":[-71.802116,45.136024],"type":"Point"}
}