{
  "type": "Feature",
  "properties": {
    "addr:full":"450 Alliance Ave York ON M6N 2H8",
    "addr:housenumber":"450",
    "addr:postcode":"m6n 2h8",
    "addr:street":"Alliance Ave",
    "iso:country":"CA",
    "sg:address":"450 Alliance Ave",
    "sg:city":"York",
    "sg:classifiers":[
        {
            "category":"Real Estate",
            "subcategory":"Real Estate Agent",
            "type":"Services"
        }
    ],
    "sg:phone":"+1 416 769 4158",
    "sg:postcode":"M6N 2H8",
    "sg:province":"ON",
    "sg:tags":[
        "management"
    ],
    "wof:name":"First National Mgmt Corp",
    "wof:placetype":"venue"
},
  "geometry": {"coordinates":[-79.4876861572,43.6773986816],"type":"Point"}
}