{
  "type": "Feature",
  "properties": {
    "iso:country":"CA",
    "sg:address":"1487 Rue Mirka",
    "sg:city":"Rock Forest",
    "sg:classifiers":[
        {
            "category":"Retail",
            "subcategory":"Portrait Studio",
            "type":"Services"
        }
    ],
    "sg:phone":"+1 819 564 6538",
    "sg:postcode":"J1N 1W5",
    "sg:province":"QC",
    "sg:tags":[
        "photographer"
    ],
    "wof:name":"Studio Ap",
    "wof:placetype":"venue"
},
  "geometry": {"coordinates":[-71.9859085083,45.3791007996],"type":"Point"}
}