{
  "type": "Feature",
  "properties": {
    "addr:full":"885 Rue Fleury E Montreal QC H2C 1P3",
    "addr:housenumber":"885",
    "addr:postcode":"h2c 1p3",
    "addr:street":"Rue Fleury E",
    "iso:country":"CA",
    "sg:address":"885 Rue Fleury E",
    "sg:city":"Montreal",
    "sg:classifiers":[
        {
            "category":"Banks & Credit Unions",
            "subcategory":"Bank",
            "type":"Services"
        }
    ],
    "sg:phone":"+1 514 522 1846",
    "sg:postcode":"H2C 1P3",
    "sg:province":"QC",
    "wof:name":"Banque Laurentienne Du Canada",
    "wof:placetype":"venue"
},
  "geometry": {"coordinates":[-73.66005699999999,45.55695],"type":"Point"}
}