{
  "type": "Feature",
  "properties": {
    "addr:full":"Calgary AB T2S 2T8",
    "addr:postcode":"t2s 2t8",
    "iso:country":"CA",
    "sg:city":"Calgary",
    "sg:classifiers":[
        {
            "category":"Health Services",
            "subcategory":"Chiropractor",
            "type":"Services"
        }
    ],
    "sg:phone":"+1 403 299 0170",
    "sg:postcode":"T2S 2T8",
    "sg:province":"AB",
    "wof:name":"Chiropractic Family Care Ctr",
    "wof:placetype":"venue"
},
  "geometry": {"coordinates":[-114.06735229500001,51.0376815796],"type":"Point"}
}