{
  "type": "Feature",
  "properties": {
    "addr:full":"Leduc AB T9E 7K6",
    "addr:postcode":"t9e 7k6",
    "iso:country":"CA",
    "sg:city":"Leduc",
    "sg:classifiers":[
        {
            "category":"Professional",
            "subcategory":"Lawyer & Legal Services",
            "type":"Services"
        }
    ],
    "sg:phone":"+1 780 986 5335",
    "sg:postcode":"T9E 7K6",
    "sg:province":"AB",
    "sg:tags":[
        "attorney"
    ],
    "wof:name":"Campbell & CO",
    "wof:placetype":"venue"
},
  "geometry": {"coordinates":[-113.546157837,53.2647705078],"type":"Point"}
}