{
  "type": "Feature",
  "properties": {
    "addr:full":"Lumsden SK S0G 3C0",
    "addr:postcode":"s0g 3c0",
    "iso:country":"CA",
    "sg:city":"Lumsden",
    "sg:classifiers":[
        {
            "category":"Government",
            "subcategory":"Office",
            "type":"Public Place"
        }
    ],
    "sg:phone":"+1 306 731 3142",
    "sg:postcode":"S0G 3C0",
    "sg:province":"SK",
    "sg:tags":[
        "village"
    ],
    "wof:name":"Lumsden Town Shop",
    "wof:placetype":"venue"
},
  "geometry": {"coordinates":[-104.87041499999999,50.643791],"type":"Point"}
}