{
  "type": "Feature",
  "properties": {
    "addr:full":"155 Main St S Rockwood ON N0B 2K0",
    "addr:housenumber":"155",
    "addr:postcode":"n0b 2k0",
    "addr:street":"Main St S",
    "iso:country":"CA",
    "sg:address":"155 Main St S",
    "sg:city":"Rockwood",
    "sg:classifiers":[
        {
            "category":"Personal",
            "subcategory":"Beauty Salon",
            "type":"Services"
        }
    ],
    "sg:phone":"+1 519 856 0803",
    "sg:postcode":"N0B 2K0",
    "sg:province":"ON",
    "wof:name":"Village Beauty Boutique",
    "wof:placetype":"venue"
},
  "geometry": {"coordinates":[-80.14305877690001,43.617816925],"type":"Point"}
}