{
  "type": "Feature",
  "properties": {
    "iso:country":"CA",
    "sg:address":"200 1st St",
    "sg:city":"Fox Creek",
    "sg:classifiers":[
        {
            "category":"Recreation",
            "type":"Entertainment"
        }
    ],
    "sg:phone":"+1 780 622 2770",
    "sg:postcode":"T0H 1P0",
    "sg:province":"AB",
    "sg:tags":[
        "hall",
        "auditorium"
    ],
    "wof:name":"Fox Creek Community Hall",
    "wof:placetype":"venue"
},
  "geometry": {"coordinates":[-116.802131653,54.4007911682],"type":"Point"}
}