{
  "type": "Feature",
  "properties": {
    "iso:country":"CA",
    "sg:address":"9741 Boul Saint-Laurent",
    "sg:city":"Montreal",
    "sg:classifiers":[
        {
            "category":"Organizations",
            "subcategory":"Religious Organization",
            "type":"Services"
        }
    ],
    "sg:phone":"+1 514 384 5212",
    "sg:postcode":"H3L 2N4",
    "sg:province":"QC",
    "sg:tags":[
        "church"
    ],
    "wof:name":"Eglise Baptiste Evangelique",
    "wof:placetype":"venue"
},
  "geometry": {"coordinates":[-73.656326,45.545952],"type":"Point"}
}