{
  "type": "Feature",
  "properties": {
    "addr:full":"801 Baker St Cranbrook BC V1C 1A3",
    "addr:housenumber":"801",
    "addr:postcode":"bc v1c 1a3",
    "addr:street":"Baker St",
    "iso:country":"CA",
    "sg:address":"801 Baker St",
    "sg:city":"Cranbrook",
    "sg:classifiers":[
        {
            "category":"Social Services",
            "type":"Services"
        }
    ],
    "sg:phone":"+1 250 426 3351",
    "sg:postcode":"V1C 1A3",
    "sg:province":"BC",
    "sg:tags":[
        "organization",
        "welfare"
    ],
    "wof:name":"Kootenay East Youth Program",
    "wof:placetype":"venue"
},
  "geometry": {"coordinates":[-115.77018,49.512032],"type":"Point"}
}