{
  "type": "Feature",
  "properties": {
    "addr:full":"Nanaimo BC V9S 3H5",
    "addr:postcode":"v9s 3h5",
    "iso:country":"CA",
    "sg:city":"Nanaimo",
    "sg:classifiers":[
        {
            "category":"Retail",
            "subcategory":"Auto Repair",
            "type":"Services"
        }
    ],
    "sg:phone":"+1 250 756 2902",
    "sg:postcode":"V9S 3H5",
    "sg:province":"BC",
    "sg:tags":[
        "body",
        "automobile",
        "painting"
    ],
    "wof:name":"Details Auto Body",
    "wof:placetype":"venue"
},
  "geometry": {"coordinates":[-123.98333700000001,49.193958],"type":"Point"}
}