{
  "type": "Feature",
  "properties": {
    "addr:full":"Greenfield Park QC J4V 1L9",
    "addr:postcode":"j4v 1l9",
    "addr:street":"Park",
    "iso:country":"CA",
    "sg:city":"Greenfield Park",
    "sg:classifiers":[
        {
            "category":"Wholesale",
            "subcategory":"Home Furnishings",
            "type":"Manufacturing & Wholesale Goods"
        }
    ],
    "sg:phone":"+1 450 676 0185",
    "sg:postcode":"J4V 1L9",
    "sg:province":"QC",
    "sg:tags":[
        "curtain",
        "drapery"
    ],
    "wof:name":"Slovcan",
    "wof:placetype":"venue"
},
  "geometry": {"coordinates":[-73.49391900000001,45.490803],"type":"Point"}
}