{
  "type": "Feature",
  "properties": {
    "addr:full":"Utterson ON P0B 1M0",
    "addr:postcode":"p0b 1m0",
    "iso:country":"CA",
    "sg:city":"Utterson",
    "sg:classifiers":[
        {
            "category":"Museum",
            "subcategory":"Botanical Garden",
            "type":"Entertainment"
        }
    ],
    "sg:phone":"+1 705 385 0847",
    "sg:postcode":"P0B 1M0",
    "sg:province":"ON",
    "sg:tags":[
        "accounting",
        "bookkeeping",
        "system",
        "zoo"
    ],
    "wof:name":"Guha's Northern General Svc",
    "wof:placetype":"venue"
},
  "geometry": {"coordinates":[-79.327866,45.21104],"type":"Point"}
}