{
  "type": "Feature",
  "properties": {
    "iso:country":"CA",
    "sg:address":"7050 Malden Rd",
    "sg:city":"Windsor",
    "sg:classifiers":[
        {
            "category":"Education",
            "subcategory":"School",
            "type":"Public Place"
        }
    ],
    "sg:phone":"+1 519 734 1237",
    "sg:postcode":"N9J 2T5",
    "sg:province":"ON",
    "wof:name":"Sandwich Secondary School",
    "wof:placetype":"venue"
},
  "geometry": {"coordinates":[-83.060508728,42.2527389526],"type":"Point"}
}