{
  "type": "Feature",
  "properties": {
    "addr:full":"843 Union St Fredericton NB E3A 3P6",
    "addr:housenumber":"843",
    "addr:postcode":"e3a 3p6",
    "addr:street":"Union St",
    "iso:country":"CA",
    "sg:address":"843 Union St",
    "sg:city":"Fredericton",
    "sg:classifiers":[
        {
            "category":"Travel",
            "subcategory":"Hotels & Motels",
            "type":"Entertainment"
        }
    ],
    "sg:phone":"+1 506 452 2802",
    "sg:postcode":"E3A 3P6",
    "sg:province":"NB",
    "sg:tags":[
        "breakfast",
        "accommodation",
        "bed"
    ],
    "wof:name":"Colonel's in",
    "wof:placetype":"venue"
},
  "geometry": {"coordinates":[-66.6245422363,45.9608726501],"type":"Point"}
}