{
  "type": "Feature",
  "properties": {
    "iso:country":"CA",
    "sg:address":"51 Simcoe St",
    "sg:city":"Tillsonburg",
    "sg:classifiers":[
        {
            "category":"Personal",
            "subcategory":"Beauty Salon",
            "type":"Services"
        }
    ],
    "sg:phone":"+1 519 688 0166",
    "sg:postcode":"N4G 2H6",
    "sg:province":"ON",
    "wof:name":"First Choice Haircutters",
    "wof:placetype":"venue"
},
  "geometry": {"coordinates":[-80.7158203125,42.8597755432],"type":"Point"}
}