{
  "type": "Feature",
  "properties": {
    "addr:full":"Calgary AB T2P 3W2",
    "addr:postcode":"t2p 3w2",
    "iso:country":"CA",
    "sg:city":"Calgary",
    "sg:classifiers":[
        {
            "category":"Mining & Drilling",
            "type":"Manufacturing & Wholesale Goods"
        }
    ],
    "sg:phone":"+1 403 269 9103",
    "sg:postcode":"T2P 3W2",
    "sg:province":"AB",
    "sg:tags":[
        "development",
        "gas",
        "oil",
        "exploration"
    ],
    "wof:name":"Bolter Resource Consulting",
    "wof:placetype":"venue"
},
  "geometry": {"coordinates":[-114.078941,51.047756],"type":"Point"}
}