{
  "type": "Feature",
  "properties": {
    "addr:full":"9653 45 Ave NW Edmonton AB T6E 5Z8",
    "addr:housenumber":"9653",
    "addr:postcode":"t6e 5z8",
    "addr:street":"45 Ave Nw",
    "iso:country":"CA",
    "sg:address":"9653 45 Ave NW",
    "sg:city":"Edmonton",
    "sg:classifiers":[
        {
            "category":"Building & Trades",
            "subcategory":"Construction",
            "type":"Services"
        }
    ],
    "sg:phone":"+1 780 439 1333",
    "sg:postcode":"T6E 5Z8",
    "sg:province":"AB",
    "sg:tags":[
        "home",
        "builder"
    ],
    "wof:name":"Stoneridge Developments Ltd",
    "wof:placetype":"venue"
},
  "geometry": {"coordinates":[-113.478165,53.483013],"type":"Point"}
}