{
  "type": "Feature",
  "properties": {
    "addr:full":"1425 Rue Dandonneau Mont-Joli QC G5H 2C6",
    "addr:housenumber":"1425",
    "addr:postcode":"g5h 2c6",
    "addr:street":"Rue Dandonneau",
    "iso:country":"CA",
    "sg:address":"1425 Rue Dandonneau",
    "sg:city":"Mont-Joli",
    "sg:classifiers":[
        {
            "category":"Personal",
            "type":"Services"
        }
    ],
    "sg:phone":"+1 418 775 5668",
    "sg:postcode":"G5H 2C6",
    "sg:province":"QC",
    "sg:tags":[
        "therapist",
        "massage"
    ],
    "wof:name":"Clinique D'Acupuncture",
    "wof:placetype":"venue"
},
  "geometry": {"coordinates":[-68.187789917,48.5937385559],"type":"Point"}
}