{
  "type": "Feature",
  "properties": {
    "iso:country":"CA",
    "sg:address":"10 Connors Rd",
    "sg:city":"Corner Brook",
    "sg:classifiers":[
        {
            "category":"Organizations",
            "subcategory":"Membership Organization",
            "type":"Services"
        }
    ],
    "sg:phone":"+1 709 785 2747",
    "sg:postcode":"A2H 3G4",
    "sg:province":"NL",
    "sg:tags":[
        "protection",
        "animal"
    ],
    "wof:name":"Spca",
    "wof:placetype":"venue"
},
  "geometry": {"coordinates":[-58.0155830383,48.9635391235],"type":"Point"}
}