{
  "type": "Feature",
  "properties": {
    "addr:full":"901 Rue DE LA Montagne Saint-Tite QC G0X 3H0",
    "addr:housenumber":"901",
    "addr:postcode":"g0x 3h0",
    "addr:street":"Rue De La Montagne",
    "iso:country":"CA",
    "sg:address":"901 Rue DE LA Montagne",
    "sg:city":"Saint-Tite",
    "sg:classifiers":[
        {
            "category":"Freight",
            "type":"Transportation"
        }
    ],
    "sg:phone":"+1 418 365 7218",
    "sg:postcode":"G0X 3H0",
    "sg:province":"QC",
    "sg:tags":[
        "trucking"
    ],
    "wof:name":"Transports Gaetan Allaire",
    "wof:placetype":"venue"
},
  "geometry": {"coordinates":[-72.558098,46.721581],"type":"Point"}
}