{
  "type": "Feature",
  "properties": {
    "addr:full":"4520 10th Ave W Vancouver BC V6R 2J1",
    "addr:housenumber":"4520",
    "addr:postcode":"v6r 2j1",
    "addr:street":"10Th Ave W",
    "iso:country":"CA",
    "sg:address":"4520 10th Ave W",
    "sg:city":"Vancouver",
    "sg:classifiers":[
        {
            "category":"Shopping",
            "subcategory":"Pharmacy",
            "type":"Retail Goods"
        }
    ],
    "sg:phone":"+1 604 224 1377",
    "sg:postcode":"V6R 2J1",
    "sg:province":"BC",
    "wof:name":"Point Grey Pharmacy",
    "wof:placetype":"venue"
},
  "geometry": {"coordinates":[-123.209907532,49.2637176514],"type":"Point"}
}