{
  "type": "Feature",
  "properties": {
    "iso:country":"CA",
    "sg:address":"171 Rue Simard",
    "sg:city":"Saint-Jean-Sur-Richelieu",
    "sg:classifiers":[
        {
            "category":"Building & Trades",
            "subcategory":"Construction",
            "type":"Services"
        }
    ],
    "sg:phone":"+1 450 347 2114",
    "sg:postcode":"J3B 7X3",
    "sg:province":"QC",
    "sg:tags":[
        "foundation",
        "contractor"
    ],
    "wof:name":"G G Formes Inc",
    "wof:placetype":"venue"
},
  "geometry": {"coordinates":[-73.257889,45.288841],"type":"Point"}
}