{
  "type": "Feature",
  "properties": {
    "addr:full":"290 North Service Rd W Oakville ON L6M 2S2",
    "addr:housenumber":"290",
    "addr:postcode":"l6m 2s2",
    "addr:street":"North Service Rd W",
    "iso:country":"CA",
    "sg:address":"290 North Service Rd W",
    "sg:city":"Oakville",
    "sg:classifiers":[
        {
            "category":"Shopping",
            "subcategory":"Computers & Home Electronics",
            "type":"Retail Goods"
        }
    ],
    "sg:phone":"+1 905 338 2275",
    "sg:postcode":"L6M 2S2",
    "sg:province":"ON",
    "sg:tags":[
        "high",
        "television",
        "stereophonic",
        "radio",
        "fidelity"
    ],
    "wof:name":"Oakville Sight & Sound",
    "wof:placetype":"venue"
},
  "geometry": {"coordinates":[-79.705826,43.44595],"type":"Point"}
}