{
  "type": "Feature",
  "properties": {
    "addr:full":"11486 149 St NW Edmonton AB T5M 1W7",
    "addr:housenumber":"11486",
    "addr:postcode":"t5m 1w7",
    "addr:street":"149 St Nw",
    "iso:country":"CA",
    "sg:address":"11486 149 St NW",
    "sg:city":"Edmonton",
    "sg:classifiers":[
        {
            "category":"Shopping",
            "type":"Retail Goods"
        }
    ],
    "sg:phone":"+1 780 453 1137",
    "sg:postcode":"T5M 1W7",
    "sg:province":"AB",
    "sg:tags":[
        "cosmetic",
        "perfume"
    ],
    "wof:name":"Images & Shades Cosmetics",
    "wof:placetype":"venue"
},
  "geometry": {"coordinates":[-113.57820100000001,53.565006],"type":"Point"}
}