{
  "type": "Feature",
  "properties": {
    "addr:full":"Mississauga ON L5A 2X2",
    "addr:postcode":"l5a 2x2",
    "iso:country":"CA",
    "sg:city":"Mississauga",
    "sg:classifiers":[
        {
            "category":"Wholesale",
            "subcategory":"Meat",
            "type":"Manufacturing & Wholesale Goods"
        }
    ],
    "sg:phone":"+1 905 279 2107",
    "sg:postcode":"L5A 2X2",
    "sg:province":"ON",
    "sg:tags":[
        "product"
    ],
    "wof:name":"Garcia Meats",
    "wof:placetype":"venue"
},
  "geometry": {"coordinates":[-79.5965042114,43.5920715332],"type":"Point"}
}