{
  "type": "Feature",
  "properties": {
    "iso:country":"CA",
    "sg:address":"3217 2 Ave N",
    "sg:city":"Lethbridge",
    "sg:classifiers":[
        {
            "category":"Shopping",
            "subcategory":"Bicycles & Sporting Goods",
            "type":"Retail Goods"
        }
    ],
    "sg:phone":"+1 403 380 2626",
    "sg:postcode":"T1H 0C5",
    "sg:province":"AB",
    "sg:tags":[
        "equipment",
        "archery",
        "supply"
    ],
    "wof:name":"Lane Archery & Sport Shop",
    "wof:placetype":"venue"
},
  "geometry": {"coordinates":[-112.793190002,49.7003211975],"type":"Point"}
}