{
  "type": "Feature",
  "properties": {
    "iso:country":"CA",
    "sg:address":"348 Rue Saint-Emile",
    "sg:city":"Chicoutimi",
    "sg:classifiers":[
        {
            "category":"Manufacturing",
            "subcategory":"Chemicals & Compounds",
            "type":"Manufacturing & Wholesale Goods"
        }
    ],
    "sg:phone":"+1 418 545 8244",
    "sg:postcode":"G7G 2L2",
    "sg:province":"QC",
    "sg:tags":[
        "drug"
    ],
    "wof:name":"Pastilles Charbonneau Inc",
    "wof:placetype":"venue"
},
  "geometry": {"coordinates":[-71.04541015620001,48.4450149536],"type":"Point"}
}