{
  "type": "Feature",
  "properties": {
    "addr:full":"Farm Midale SK S0C 1S0",
    "addr:postcode":"s0c 1s0",
    "iso:country":"CA",
    "sg:address":"Farm",
    "sg:city":"Midale",
    "sg:classifiers":[
        {
            "category":"Building & Trades",
            "subcategory":"Electrical",
            "type":"Services"
        }
    ],
    "sg:phone":"+1 306 458 2228",
    "sg:postcode":"S0C 1S0",
    "sg:province":"SK",
    "sg:tags":[
        "electric",
        "contractor"
    ],
    "wof:name":"Isabey Electric Ltd",
    "wof:placetype":"venue"
},
  "geometry": {"coordinates":[-103.410499573,49.3946762085],"type":"Point"}
}