{
  "type": "Feature",
  "properties": {
    "addr:full":"Surrey BC V3X 3K1",
    "addr:postcode":"v3x 3k1",
    "iso:country":"CA",
    "sg:city":"Surrey",
    "sg:classifiers":[
        {
            "category":"Shopping",
            "subcategory":"Used Merchandise",
            "type":"Retail Goods"
        }
    ],
    "sg:phone":"+1 604 501 1700",
    "sg:postcode":"V3X 3K1",
    "sg:province":"BC",
    "sg:tags":[
        "shop",
        "consignment"
    ],
    "wof:name":"Ooh LA LA Consignment Boutique",
    "wof:placetype":"venue"
},
  "geometry": {"coordinates":[-122.890175,49.118237],"type":"Point"}
}