{
  "type": "Feature",
  "properties": {
    "addr:full":"506 Oxford St E London ON N5Y 3H7",
    "addr:housenumber":"506",
    "addr:postcode":"n5y 3h7",
    "addr:street":"Oxford St E",
    "iso:country":"CA",
    "sg:address":"506 Oxford St E",
    "sg:city":"London",
    "sg:classifiers":[
        {
            "category":"Health Services",
            "subcategory":"Doctor",
            "type":"Services"
        }
    ],
    "sg:phone":"+1 519 434 2555",
    "sg:postcode":"N5Y 3H7",
    "sg:province":"ON",
    "sg:tags":[
        "physician",
        "surgeon"
    ],
    "wof:name":"Clement, John S MD",
    "wof:placetype":"venue"
},
  "geometry": {"coordinates":[-81.2417755127,42.9990234375],"type":"Point"}
}