{
  "type": "Feature",
  "properties": {
    "addr:full":"75 Clendenan Ave Toronto ON M6P 2W7",
    "addr:housenumber":"75",
    "addr:postcode":"m6p 2w7",
    "addr:street":"Clendenan Ave",
    "iso:country":"CA",
    "sg:address":"75 Clendenan Ave",
    "sg:city":"Toronto",
    "sg:classifiers":[
        {
            "category":"Building & Trades",
            "subcategory":"Construction",
            "type":"Services"
        }
    ],
    "sg:phone":"+1 416 767 3569",
    "sg:postcode":"M6P 2W7",
    "sg:province":"ON",
    "sg:tags":[
        "general",
        "contractor"
    ],
    "wof:name":"A D Construction",
    "wof:placetype":"venue"
},
  "geometry": {"coordinates":[-79.470322,43.653725],"type":"Point"}
}