{
  "type": "Feature",
  "properties": {
    "iso:country":"CA",
    "sg:city":"Vancouver",
    "sg:classifiers":[
        {
            "category":"Professional",
            "subcategory":"Lawyer & Legal Services",
            "type":"Services"
        }
    ],
    "sg:phone":"+1 604 689 8350",
    "sg:postcode":"V6B 1R8",
    "sg:province":"BC",
    "sg:tags":[
        "naturalization",
        "immigration"
    ],
    "wof:name":"Canada Investment & Consultant",
    "wof:placetype":"venue"
},
  "geometry": {"coordinates":[-123.107796,49.281048],"type":"Point"}
}