{
  "type": "Feature",
  "properties": {
    "addr:full":"2630 Rue King O Sherbrooke QC J1J 2H1",
    "addr:housenumber":"2630",
    "addr:postcode":"j1j 2h1",
    "addr:street":"Rue King O",
    "iso:country":"CA",
    "sg:address":"2630 Rue King O",
    "sg:city":"Sherbrooke",
    "sg:classifiers":[
        {
            "category":"Banks & Credit Unions",
            "subcategory":"Investment Brokerage",
            "type":"Services"
        }
    ],
    "sg:phone":"+1 819 564 1887",
    "sg:postcode":"J1J 2H1",
    "sg:province":"QC",
    "wof:name":"Placements Gilles Sirois Ltee",
    "wof:placetype":"venue"
},
  "geometry": {"coordinates":[-71.9368591309,45.398021698],"type":"Point"}
}