{
  "type": "Feature",
  "properties": {
    "addr:full":"21 Rte Maritime Baie-Comeau QC G4Z 2L6",
    "addr:housenumber":"21",
    "addr:postcode":"g4z 2l6",
    "addr:street":"Rte Maritime",
    "iso:country":"CA",
    "sg:address":"21 Rte Maritime",
    "sg:city":"Baie-Comeau",
    "sg:classifiers":[
        {
            "category":"Utilities",
            "subcategory":"Fuel Oil & Lpg",
            "type":"Services"
        }
    ],
    "sg:phone":"+1 418 296 3782",
    "sg:postcode":"G4Z 2L6",
    "sg:province":"QC",
    "wof:name":"Petro Plus Inc",
    "wof:placetype":"venue"
},
  "geometry": {"coordinates":[-68.13370500000001,49.244179],"type":"Point"}
}