{
  "type": "Feature",
  "properties": {
    "addr:full":"Riverview NB E1B 3L8",
    "addr:postcode":"e1b 3l8",
    "iso:country":"CA",
    "sg:city":"Riverview",
    "sg:classifiers":[
        {
            "category":"Shopping",
            "subcategory":"Clothing, Apparel, & Fashions",
            "type":"Retail Goods"
        }
    ],
    "sg:phone":"+1 506 386 4181",
    "sg:postcode":"E1B 3L8",
    "sg:province":"NB",
    "wof:name":"Reitmans",
    "wof:placetype":"venue"
},
  "geometry": {"coordinates":[-64.8166046143,46.0609664917],"type":"Point"}
}