{
  "type": "Feature",
  "properties": {
    "iso:country":"CA",
    "sg:address":"8 Richmond Park Dr",
    "sg:city":"Napanee",
    "sg:classifiers":[
        {
            "category":"Professional",
            "subcategory":"Research",
            "type":"Services"
        }
    ],
    "sg:phone":"+1 613 354 6511",
    "sg:postcode":"K7R 2Z4",
    "sg:province":"ON",
    "sg:tags":[
        "foundation",
        "hospital",
        "philanthropic"
    ],
    "wof:name":"Lennox & Addington CO Gen Hosp",
    "wof:placetype":"venue"
},
  "geometry": {"coordinates":[-76.9659118652,44.2401847839],"type":"Point"}
}