{
  "type": "Feature",
  "properties": {
    "iso:country":"CA",
    "sg:address":"610 the Queensway",
    "sg:city":"Peterborough",
    "sg:classifiers":[
        {
            "category":"Building & Trades",
            "subcategory":"Plumbing",
            "type":"Services"
        }
    ],
    "sg:phone":"+1 705 742 4791",
    "sg:postcode":"K9J 7H2",
    "sg:province":"ON",
    "sg:tags":[
        "contractor"
    ],
    "wof:name":"Berardi Brothers Plumbing Ltd",
    "wof:placetype":"venue"
},
  "geometry": {"coordinates":[-78.33818817140001,44.2763786316],"type":"Point"}
}