{
  "type": "Feature",
  "properties": {
    "addr:full":"Gimli MB R0C 1B0",
    "addr:postcode":"r0c 1b0",
    "iso:country":"CA",
    "sg:city":"Gimli",
    "sg:classifiers":[
        {
            "category":"Health Services",
            "subcategory":"Medical Lab",
            "type":"Services"
        }
    ],
    "sg:phone":"+1 204 642 8836",
    "sg:postcode":"R0C 1B0",
    "sg:province":"MB",
    "wof:name":"Vandor Denture Clinic",
    "wof:placetype":"venue"
},
  "geometry": {"coordinates":[-96.994148,50.63195],"type":"Point"}
}