{
  "type": "Feature",
  "properties": {
    "addr:full":"RR 1 Lombardy ON K0G 1L0",
    "addr:postcode":"k0g 1l0",
    "addr:street":"Rr 1 Lombardy",
    "iso:country":"CA",
    "sg:address":"RR 1",
    "sg:city":"Lombardy",
    "sg:classifiers":[
        {
            "category":"Manufacturing",
            "subcategory":"Printing",
            "type":"Manufacturing & Wholesale Goods"
        }
    ],
    "sg:phone":"+1 613 283 4040",
    "sg:postcode":"K0G 1L0",
    "sg:province":"ON",
    "sg:tags":[
        "publisher",
        "guide"
    ],
    "wof:name":"Valley Homes Monthly",
    "wof:placetype":"venue"
},
  "geometry": {"coordinates":[-76.0916061401,44.823261261],"type":"Point"}
}