{
  "type": "Feature",
  "properties": {
    "iso:country":"CA",
    "sg:address":"5100 Eagle Tree Pl",
    "sg:city":"Victoria",
    "sg:classifiers":[
        {
            "category":"Professional",
            "subcategory":"Management & Consulting",
            "type":"Services"
        }
    ],
    "sg:phone":"+1 250 474 2278",
    "sg:postcode":"V9C 4H9",
    "sg:province":"BC",
    "sg:tags":[
        "consultant",
        "business"
    ],
    "wof:name":"Calibre Strategic Svc",
    "wof:placetype":"venue"
},
  "geometry": {"coordinates":[-123.364517,48.428314],"type":"Point"}
}