{
  "type": "Feature",
  "properties": {
    "addr:full":"2600 New Lakeshore Rd Brights Grove ON N0N 1C0",
    "addr:housenumber":"2600",
    "addr:postcode":"n0n 1c0",
    "addr:street":"New Lakeshore Rd",
    "iso:country":"CA",
    "sg:address":"2600 New Lakeshore Rd",
    "sg:city":"Brights Grove",
    "sg:classifiers":[
        {
            "category":"Food & Beverages",
            "subcategory":"Groceries & Convenience Stores",
            "type":"Retail Goods"
        }
    ],
    "sg:phone":"+1 519 869 4433",
    "sg:postcode":"N0N 1C0",
    "sg:province":"ON",
    "sg:tags":[
        "grocer"
    ],
    "wof:name":"Brights Grove Iga",
    "wof:placetype":"venue"
},
  "geometry": {"coordinates":[-82.25792694090001,43.0273895264],"type":"Point"}
}