{
  "type": "Feature",
  "properties": {
    "addr:full":"3555 Bathurst St North York ON M6A 2Y8",
    "addr:housenumber":"3555",
    "addr:postcode":"m6a 2y8",
    "addr:street":"Bathurst St",
    "iso:country":"CA",
    "sg:address":"3555 Bathurst St",
    "sg:city":"North York",
    "sg:classifiers":[
        {
            "category":"Personal",
            "subcategory":"Shoe Repair & Shine",
            "type":"Services"
        }
    ],
    "sg:phone":"+1 416 256 0360",
    "sg:postcode":"M6A 2Y8",
    "sg:province":"ON",
    "sg:tags":[
        "shining"
    ],
    "wof:name":"Toronto Factory Auto House Ltd",
    "wof:placetype":"venue"
},
  "geometry": {"coordinates":[-79.4321899414,43.730632782],"type":"Point"}
}