{
  "type": "Feature",
  "properties": {
    "addr:full":"449 Scott Rd Sarnia ON N7T 8G3",
    "addr:housenumber":"449",
    "addr:postcode":"n7t 8g3",
    "addr:street":"Scott Rd",
    "iso:country":"CA",
    "sg:address":"449 Scott Rd",
    "sg:city":"Sarnia",
    "sg:classifiers":[
        {
            "category":"Manufacturing",
            "subcategory":"Metals",
            "type":"Manufacturing & Wholesale Goods"
        }
    ],
    "sg:phone":"+1 519 336 4265",
    "sg:postcode":"N7T 8G3",
    "sg:province":"ON",
    "sg:tags":[
        "steel"
    ],
    "wof:name":"Anj Ind Fabricating Ltd",
    "wof:placetype":"venue"
},
  "geometry": {"coordinates":[-82.396637,42.953278],"type":"Point"}
}