{
  "type": "Feature",
  "properties": {
    "addr:full":"PO Box 87 Bashaw AB T0B 0H0",
    "addr:housenumber":"po box 87",
    "addr:postcode":"t0b 0h0",
    "iso:country":"CA",
    "sg:address":"PO Box 87",
    "sg:city":"Bashaw",
    "sg:classifiers":[
        {
            "category":"Organizations",
            "subcategory":"Religious Organization",
            "type":"Services"
        }
    ],
    "sg:phone":"+1 403 372 3645",
    "sg:postcode":"T0B 0H0",
    "sg:province":"AB",
    "sg:tags":[
        "church"
    ],
    "wof:name":"Immaculate Heart of Mary Ch",
    "wof:placetype":"venue"
},
  "geometry": {"coordinates":[-112.970879,52.583778],"type":"Point"}
}