{
  "type": "Feature",
  "properties": {
    "addr:full":"364 Lawrence Ave Kelowna BC V1Y 6L4",
    "addr:housenumber":"364",
    "addr:postcode":"v1y 6l4",
    "addr:street":"Lawrence Ave",
    "iso:country":"CA",
    "sg:address":"364 Lawrence Ave",
    "sg:city":"Kelowna",
    "sg:classifiers":[
        {
            "category":"Personal",
            "subcategory":"Adult",
            "type":"Services"
        }
    ],
    "sg:phone":"+1 250 868 9439",
    "sg:postcode":"V1Y 6L4",
    "sg:province":"BC",
    "sg:tags":[
        "escort"
    ],
    "wof:name":"Garden of Eden",
    "wof:placetype":"venue"
},
  "geometry": {"coordinates":[-119.495651,49.885548],"type":"Point"}
}