{
  "type": "Feature",
  "properties": {
    "addr:full":"888 Main St N Moose Jaw SK S6H 3K6",
    "addr:housenumber":"888",
    "addr:postcode":"s6h 3k6",
    "addr:street":"Main St N",
    "iso:country":"CA",
    "sg:address":"888 Main St N",
    "sg:city":"Moose Jaw",
    "sg:classifiers":[
        {
            "category":"Home & Garden",
            "subcategory":"Building Materials",
            "type":"Retail Goods"
        }
    ],
    "sg:phone":"+1 306 691 0024",
    "sg:postcode":"S6H 3K6",
    "sg:province":"SK",
    "sg:tags":[
        "glass",
        "window",
        "plate"
    ],
    "wof:name":"Speedy Auto & Window Glass",
    "wof:placetype":"venue"
},
  "geometry": {"coordinates":[-105.535004,50.397675],"type":"Point"}
}