{
  "type": "Feature",
  "properties": {
    "addr:full":"Montreal QC H2R 2Y9",
    "addr:postcode":"h2r 2y9",
    "iso:country":"CA",
    "sg:city":"Montreal",
    "sg:classifiers":[
        {
            "category":"Professional",
            "subcategory":"Advertising",
            "type":"Services"
        }
    ],
    "sg:phone":"+1 514 727 9900",
    "sg:postcode":"H2R 2Y9",
    "sg:province":"QC",
    "sg:tags":[
        "counselor"
    ],
    "wof:name":"Blue Communications Inc",
    "wof:placetype":"venue"
},
  "geometry": {"coordinates":[-73.62106300000001,45.532928],"type":"Point"}
}