{
  "type": "Feature",
  "properties": {
    "iso:country":"CA",
    "sg:city":"Montreal",
    "sg:classifiers":[
        {
            "category":"Manufacturing",
            "subcategory":"Printing",
            "type":"Manufacturing & Wholesale Goods"
        }
    ],
    "sg:phone":"+1 514 982 2401",
    "sg:postcode":"H3A 3L4",
    "sg:province":"QC",
    "sg:tags":[
        "publisher"
    ],
    "wof:name":"Shafter Properties Inc",
    "wof:placetype":"venue"
},
  "geometry": {"coordinates":[-73.5590133667,45.5176773071],"type":"Point"}
}