{
  "type": "Feature",
  "properties": {
    "iso:country":"CA",
    "sg:address":"469 Waterloo St",
    "sg:city":"London",
    "sg:classifiers":[
        {
            "category":"Personal",
            "subcategory":"Beauty Salon",
            "type":"Services"
        }
    ],
    "sg:phone":"+1 519 439 5811",
    "sg:postcode":"N6B 2P4",
    "sg:province":"ON",
    "wof:name":"Brunner Moore & Ross",
    "wof:placetype":"venue"
},
  "geometry": {"coordinates":[-81.2435836792,42.9874687195],"type":"Point"}
}