{
  "type": "Feature",
  "properties": {
    "iso:country":"CA",
    "sg:city":"Sedgewick",
    "sg:classifiers":[
        {
            "category":"Wholesale",
            "subcategory":"Petroleum",
            "type":"Manufacturing & Wholesale Goods"
        }
    ],
    "sg:phone":"+1 780 384 3863",
    "sg:postcode":"T0B 4C0",
    "sg:province":"AB",
    "sg:tags":[
        "bulk",
        "oil",
        "gasoline"
    ],
    "wof:name":"Imperial Oil Ltd",
    "wof:placetype":"venue"
},
  "geometry": {"coordinates":[-111.691116333,52.7671737671],"type":"Point"}
}