{
  "type": "Feature",
  "properties": {
    "addr:full":"194 Rosario Ch Stoke QC J0B 3G0",
    "addr:housenumber":"194",
    "addr:postcode":"j0b 3g0",
    "iso:country":"CA",
    "sg:address":"194 Rosario Ch",
    "sg:city":"Stoke",
    "sg:classifiers":[
        {
            "category":"Freight",
            "type":"Transportation"
        }
    ],
    "sg:phone":"+1 819 878 3833",
    "sg:postcode":"J0B 3G0",
    "sg:province":"QC",
    "sg:tags":[
        "building",
        "house",
        "mover"
    ],
    "wof:name":"Demenagement DE Maison Guertin",
    "wof:placetype":"venue"
},
  "geometry": {"coordinates":[-71.81134,45.503471],"type":"Point"}
}