{
  "type": "Feature",
  "properties": {
    "addr:full":"200 Rue Saint-Jean Longueuil QC J4H 2X5",
    "addr:housenumber":"200",
    "addr:postcode":"j4h 2x5",
    "addr:street":"Rue Saint-Jean",
    "iso:country":"CA",
    "sg:address":"200 Rue Saint-Jean",
    "sg:city":"Longueuil",
    "sg:classifiers":[
        {
            "category":"Real Estate",
            "subcategory":"Real Estate Agent",
            "type":"Services"
        }
    ],
    "sg:phone":"+1 450 346 1231",
    "sg:postcode":"J4H 2X5",
    "sg:province":"QC",
    "wof:name":"Mailloux, Lise",
    "wof:placetype":"venue"
},
  "geometry": {"coordinates":[-73.5098724365,45.536239624],"type":"Point"}
}