{
  "type": "Feature",
  "properties": {
    "addr:full":"84 Rue Ontario Notre-Dame-Du-Nord QC J0Z 3B0",
    "addr:housenumber":"84",
    "addr:postcode":"j0z 3b0",
    "addr:street":"Rue Ontario",
    "iso:country":"CA",
    "sg:address":"84 Rue Ontario",
    "sg:city":"Notre-Dame-Du-Nord",
    "sg:classifiers":[
        {
            "category":"Building & Trades",
            "subcategory":"Construction",
            "type":"Services"
        }
    ],
    "sg:phone":"+1 819 723 2009",
    "sg:postcode":"J0Z 3B0",
    "sg:province":"QC",
    "sg:tags":[
        "contractor"
    ],
    "wof:name":"King Konstruction Enr",
    "wof:placetype":"venue"
},
  "geometry": {"coordinates":[-79.494102478,47.5933532715],"type":"Point"}
}