{
  "type": "Feature",
  "properties": {
    "iso:country":"CA",
    "sg:address":"203 Rue Alexandre",
    "sg:city":"Sherbrooke",
    "sg:classifiers":[
        {
            "category":"Shopping",
            "type":"Retail Goods"
        }
    ],
    "sg:phone":"+1 819 822 2124",
    "sg:postcode":"J1H 4S8",
    "sg:province":"QC",
    "sg:tags":[
        "picture",
        "frame"
    ],
    "wof:name":"Courchesne Lapalme",
    "wof:placetype":"venue"
},
  "geometry": {"coordinates":[-71.8924407959,45.3972511292],"type":"Point"}
}