{
  "type": "Feature",
  "properties": {
    "addr:full":"2031 Main St Walsingham ON N0E 1X0",
    "addr:housenumber":"2031",
    "addr:postcode":"n0e 1x0",
    "addr:street":"Main St Walsingham",
    "iso:country":"CA",
    "sg:address":"2031 Main St",
    "sg:city":"Walsingham",
    "sg:classifiers":[
        {
            "category":"Retail",
            "subcategory":"Repair Shop",
            "type":"Services"
        }
    ],
    "sg:phone":"+1 519 586 8090",
    "sg:postcode":"N0E 1X0",
    "sg:province":"ON",
    "sg:tags":[
        "steel",
        "welding"
    ],
    "wof:name":"Robillard's Welding",
    "wof:placetype":"venue"
},
  "geometry": {"coordinates":[-80.52357499999999,42.673561],"type":"Point"}
}