{
  "type": "Feature",
  "properties": {
    "addr:full":"1732 Rue Berlier Laval QC H7L 4A1",
    "addr:housenumber":"1732",
    "addr:postcode":"h7l 4a1",
    "addr:street":"Rue Berlier",
    "iso:country":"CA",
    "sg:address":"1732 Rue Berlier",
    "sg:city":"Laval",
    "sg:classifiers":[
        {
            "category":"Wholesale",
            "subcategory":"Machinery & Supplies",
            "type":"Manufacturing & Wholesale Goods"
        }
    ],
    "sg:phone":"+1 450 686 0404",
    "sg:postcode":"H7L 4A1",
    "sg:province":"QC",
    "sg:tags":[
        "compressor",
        "gas"
    ],
    "wof:name":"Controle Air Compresseur",
    "wof:placetype":"venue"
},
  "geometry": {"coordinates":[-73.744362,45.583992],"type":"Point"}
}