{
  "type": "Feature",
  "properties": {
    "iso:country":"CA",
    "sg:address":"105 Rue Sainte-Anne",
    "sg:city":"Baie-Saint-Paul",
    "sg:classifiers":[
        {
            "category":"Professional",
            "subcategory":"Business Services",
            "type":"Services"
        }
    ],
    "sg:phone":"+1 418 240 2555",
    "sg:postcode":"G3Z 1N9",
    "sg:province":"QC",
    "sg:tags":[
        "notary"
    ],
    "wof:name":"Simard, Mireille",
    "wof:placetype":"venue"
},
  "geometry": {"coordinates":[-70.5003814697,47.4397544861],"type":"Point"}
}