{
  "type": "Feature",
  "properties": {
    "addr:full":"674 Bras D'Or - Florence Rd Florence NS B1Y 1E4",
    "addr:housenumber":"674",
    "addr:postcode":"b1y 1e4",
    "addr:street":"Bras D'Or Florence Rd",
    "iso:country":"CA",
    "sg:address":"674 Bras D'Or - Florence Rd",
    "sg:city":"Florence",
    "sg:classifiers":[
        {
            "category":"Restaurant",
            "type":"Food & Drink"
        }
    ],
    "sg:phone":"+1 902 736 2216",
    "sg:postcode":"B1Y 1E4",
    "sg:province":"NS",
    "sg:tags":[
        "pizza"
    ],
    "wof:name":"Munchiees Pizza",
    "wof:placetype":"venue"
},
  "geometry": {"coordinates":[-60.262871,46.257999],"type":"Point"}
}