{
  "type": "Feature",
  "properties": {
    "addr:full":"12611 Rue Raiche Pierrefonds QC H9A 3J1",
    "addr:housenumber":"12611",
    "addr:postcode":"h9a 3j1",
    "addr:street":"Rue Raiche",
    "iso:country":"CA",
    "sg:address":"12611 Rue Raiche",
    "sg:city":"Pierrefonds",
    "sg:classifiers":[
        {
            "category":"Building & Trades",
            "subcategory":"Cleaning & Sanitation",
            "type":"Services"
        }
    ],
    "sg:phone":"+1 514 683 7335",
    "sg:postcode":"H9A 3J1",
    "sg:province":"QC",
    "sg:tags":[
        "website",
        "design",
        "snow",
        "removal"
    ],
    "wof:name":"Polar",
    "wof:placetype":"venue"
},
  "geometry": {"coordinates":[-73.8321609497,45.50233078],"type":"Point"}
}