{
  "type": "Feature",
  "properties": {
    "iso:country":"CA",
    "sg:city":"Waterloo",
    "sg:classifiers":[
        {
            "category":"Health Services",
            "subcategory":"Doctor",
            "type":"Services"
        }
    ],
    "sg:phone":"+1 519 885 7272",
    "sg:postcode":"N2J 2J9",
    "sg:province":"ON",
    "sg:tags":[
        "clinic",
        "dentist"
    ],
    "wof:name":"Bridgeport Weber Dental Ctr",
    "wof:placetype":"venue"
},
  "geometry": {"coordinates":[-80.515251,43.469246],"type":"Point"}
}