{
  "type": "Feature",
  "properties": {
    "addr:full":"4375 152 St Surrey BC V3S 0L2",
    "addr:housenumber":"4375",
    "addr:postcode":"v3s 0l2",
    "addr:street":"152 St",
    "iso:country":"CA",
    "sg:address":"4375 152 St",
    "sg:city":"Surrey",
    "sg:classifiers":[
        {
            "category":"Wholesale",
            "subcategory":"Plants",
            "type":"Manufacturing & Wholesale Goods"
        }
    ],
    "sg:phone":"+1 604 576 1156",
    "sg:postcode":"V3S 0L2",
    "sg:province":"BC",
    "sg:tags":[
        "nursery",
        "tree"
    ],
    "wof:name":"Casino Tropical Plants Ltd",
    "wof:placetype":"venue"
},
  "geometry": {"coordinates":[-122.801338,49.082733],"type":"Point"}
}