{
  "type": "Feature",
  "properties": {
    "addr:full":"66 Main St Greenspond NL A0G 2N0",
    "addr:housenumber":"66",
    "addr:postcode":"a0g 2n0",
    "addr:street":"Main St",
    "iso:country":"CA",
    "sg:address":"66 Main St",
    "sg:city":"Greenspond",
    "sg:classifiers":[
        {
            "category":"Government",
            "subcategory":"Office",
            "type":"Public Place"
        }
    ],
    "sg:phone":"+1 709 269 3111",
    "sg:postcode":"A0G 2N0",
    "sg:province":"NL",
    "sg:tags":[
        "village"
    ],
    "wof:name":"Greespond Town Council Office",
    "wof:placetype":"venue"
},
  "geometry": {"coordinates":[-53.570324,49.069061],"type":"Point"}
}