{
  "type": "Feature",
  "properties": {
    "iso:country":"CA",
    "sg:address":"4435 Boul Des Grandes-Prairies",
    "sg:city":"Saint-Leonard",
    "sg:classifiers":[
        {
            "category":"Shopping",
            "subcategory":"Clothing, Apparel, & Fashions",
            "type":"Retail Goods"
        }
    ],
    "sg:phone":"+1 514 324 1240",
    "sg:postcode":"H1R 3N4",
    "sg:province":"QC",
    "sg:tags":[
        "uniform"
    ],
    "wof:name":"Piacente Maison DE Vetements",
    "wof:placetype":"venue"
},
  "geometry": {"coordinates":[-73.622756958,45.585144043],"type":"Point"}
}