{
  "type": "Feature",
  "properties": {
    "addr:full":"18991 96 Ave Surrey BC V4N 3P3",
    "addr:housenumber":"18991",
    "addr:postcode":"v4n 3p3",
    "addr:street":"96 Ave",
    "iso:country":"CA",
    "sg:address":"18991 96 Ave",
    "sg:city":"Surrey",
    "sg:classifiers":[
        {
            "category":"Wholesale",
            "subcategory":"Motor Vehicles",
            "type":"Manufacturing & Wholesale Goods"
        }
    ],
    "sg:phone":"+1 604 888 4188",
    "sg:postcode":"V4N 3P3",
    "sg:province":"BC",
    "sg:tags":[
        "trailer"
    ],
    "wof:name":"Manac Trailer Sales",
    "wof:placetype":"venue"
},
  "geometry": {"coordinates":[-122.69654800000001,49.177128],"type":"Point"}
}