{
  "type": "Feature",
  "properties": {
    "iso:country":"CA",
    "sg:city":"Sherwood Park",
    "sg:classifiers":[
        {
            "category":"Shopping",
            "subcategory":"Used Merchandise",
            "type":"Retail Goods"
        }
    ],
    "sg:phone":"+1 780 464 5522",
    "sg:postcode":"T8A 4E3",
    "sg:province":"AB",
    "sg:tags":[
        "book",
        "rare",
        "dealer"
    ],
    "wof:name":"Bookworm",
    "wof:placetype":"venue"
},
  "geometry": {"coordinates":[-113.323036194,53.5365447998],"type":"Point"}
}