{
  "type": "Feature",
  "properties": {
    "addr:full":"1151 10 St SW Salmon Arm BC V1E 1T2",
    "addr:housenumber":"1151",
    "addr:postcode":"v1e 1t2",
    "addr:street":"10 St Sw",
    "iso:country":"CA",
    "sg:address":"1151 10 St SW",
    "sg:city":"Salmon Arm",
    "sg:classifiers":[
        {
            "category":"Shopping",
            "subcategory":"Clothing, Apparel, & Fashions",
            "type":"Retail Goods"
        }
    ],
    "sg:phone":"+1 250 833 1455",
    "sg:postcode":"V1E 1T2",
    "sg:province":"BC",
    "wof:name":"Ashton's Ladies Wear",
    "wof:placetype":"venue"
},
  "geometry": {"coordinates":[-119.296905518,50.6908798218],"type":"Point"}
}