{
  "type": "Feature",
  "properties": {
    "addr:full":"1099 Britannia Rd E Mississauga ON L4W 3X1",
    "addr:housenumber":"1099",
    "addr:postcode":"l4w 3x1",
    "addr:street":"Britannia Rd E",
    "iso:country":"CA",
    "sg:address":"1099 Britannia Rd E",
    "sg:city":"Mississauga",
    "sg:classifiers":[
        {
            "category":"Manufacturing",
            "subcategory":"Printing",
            "type":"Manufacturing & Wholesale Goods"
        }
    ],
    "sg:phone":"+1 905 670 3312",
    "sg:postcode":"L4W 3X1",
    "sg:province":"ON",
    "sg:tags":[
        "printer"
    ],
    "wof:name":"Britannia Printing CO",
    "wof:placetype":"venue"
},
  "geometry": {"coordinates":[-79.6569824219,43.6470909119],"type":"Point"}
}