{
  "type": "Feature",
  "properties": {
    "addr:full":"Regina SK S4S 0W9",
    "addr:postcode":"s4s 0w9",
    "iso:country":"CA",
    "sg:city":"Regina",
    "sg:classifiers":[
        {
            "category":"Health Services",
            "subcategory":"Chiropractor",
            "type":"Services"
        }
    ],
    "sg:phone":"+1 306 585 1411",
    "sg:postcode":"S4S 0W9",
    "sg:province":"SK",
    "wof:name":"Chiropractors' Assn of Sask",
    "wof:placetype":"venue"
},
  "geometry": {"coordinates":[-104.629989624,50.4284286499],"type":"Point"}
}