{
  "type": "Feature",
  "properties": {
    "iso:country":"CA",
    "sg:address":"1051 Rue Principale",
    "sg:city":"Saint-Come",
    "sg:classifiers":[
        {
            "category":"Social Services",
            "type":"Services"
        }
    ],
    "sg:phone":"+1 450 883 6693",
    "sg:postcode":"J0K 2B0",
    "sg:province":"QC",
    "sg:tags":[
        "organization",
        "welfare"
    ],
    "wof:name":"Pavillon St Come Inc",
    "wof:placetype":"venue"
},
  "geometry": {"coordinates":[-73.765213,46.276859],"type":"Point"}
}