{
  "type": "Feature",
  "properties": {
    "addr:full":"Barrie ON L4N 4C3",
    "addr:postcode":"l4n 4c3",
    "iso:country":"CA",
    "sg:city":"Barrie",
    "sg:classifiers":[
        {
            "category":"Food & Beverages",
            "subcategory":"Meat & Fish",
            "type":"Retail Goods"
        }
    ],
    "sg:phone":"+1 705 737 3497",
    "sg:postcode":"L4N 4C3",
    "sg:province":"ON",
    "sg:tags":[
        "frozen"
    ],
    "wof:name":"M & M Meat Shops",
    "wof:placetype":"venue"
},
  "geometry": {"coordinates":[-79.68631744379999,44.3893013],"type":"Point"}
}