{
  "type": "Feature",
  "properties": {
    "addr:full":"1988 Rue Sainte-Catherine E Montreal QC H2K 2H7",
    "addr:housenumber":"1988",
    "addr:postcode":"h2k 2h7",
    "addr:street":"Rue Sainte-Catherine E",
    "iso:country":"CA",
    "sg:address":"1988 Rue Sainte-Catherine E",
    "sg:city":"Montreal",
    "sg:classifiers":[
        {
            "category":"Health Services",
            "subcategory":"Doctor",
            "type":"Services"
        }
    ],
    "sg:phone":"+1 514 524 3637",
    "sg:postcode":"H2K 2H7",
    "sg:province":"QC",
    "sg:tags":[
        "clinic"
    ],
    "wof:name":"Polyclinique Medicale Populair",
    "wof:placetype":"venue"
},
  "geometry": {"coordinates":[-73.55089599999999,45.523933],"type":"Point"}
}