{
  "type": "Feature",
  "properties": {
    "addr:full":"St Albert AB T8N 3V4",
    "addr:postcode":"t8n 3v4",
    "iso:country":"CA",
    "sg:city":"St Albert",
    "sg:classifiers":[
        {
            "category":"Health Services",
            "subcategory":"Health Practitioner",
            "type":"Services"
        }
    ],
    "sg:phone":"+1 780 458 8505",
    "sg:postcode":"T8N 3V4",
    "sg:province":"AB",
    "sg:tags":[
        "therapist",
        "physical"
    ],
    "wof:name":"St Albert Physical Therapy",
    "wof:placetype":"venue"
},
  "geometry": {"coordinates":[-113.627349853,53.633518219],"type":"Point"}
}