{
  "type": "Feature",
  "properties": {
    "addr:full":"675 Progress Ave Kingston ON K7L 4Y8",
    "addr:housenumber":"675",
    "addr:postcode":"k7l 4y8",
    "addr:street":"Progress Ave",
    "iso:country":"CA",
    "sg:address":"675 Progress Ave",
    "sg:city":"Kingston",
    "sg:classifiers":[
        {
            "category":"Manufacturing",
            "subcategory":"Paper Products",
            "type":"Manufacturing & Wholesale Goods"
        }
    ],
    "sg:phone":"+1 613 389 4330",
    "sg:postcode":"K7L 4Y8",
    "sg:province":"ON",
    "sg:tags":[
        "fiber"
    ],
    "wof:name":"Hartford Fibres Ltd",
    "wof:placetype":"venue"
},
  "geometry": {"coordinates":[-76.57099151609999,44.246471405],"type":"Point"}
}