{
  "type": "Feature",
  "properties": {
    "addr:full":"8519 Main St Osoyoos BC V0H 1V0",
    "addr:housenumber":"8519",
    "addr:postcode":"v0h 1v0",
    "addr:street":"Main St",
    "iso:country":"CA",
    "sg:address":"8519 Main St",
    "sg:city":"Osoyoos",
    "sg:classifiers":[
        {
            "category":"Cinema",
            "subcategory":"Movie Rental",
            "type":"Entertainment"
        }
    ],
    "sg:phone":"+1 250 495 2744",
    "sg:postcode":"V0H 1V0",
    "sg:province":"BC",
    "sg:tags":[
        "leasing",
        "video",
        "disc",
        "tape"
    ],
    "wof:name":"Yore Movie Store",
    "wof:placetype":"venue"
},
  "geometry": {"coordinates":[-119.466369629,49.0326957703],"type":"Point"}
}