{
  "type": "Feature",
  "properties": {
    "addr:full":"Invermere BC V0A 1K0",
    "addr:postcode":"v0a 1k0",
    "iso:country":"CA",
    "sg:city":"Invermere",
    "sg:classifiers":[
        {
            "category":"Building & Trades",
            "subcategory":"Plumbing",
            "type":"Services"
        }
    ],
    "sg:phone":"+1 250 342 6375",
    "sg:postcode":"V0A 1K0",
    "sg:province":"BC",
    "sg:tags":[
        "contractor"
    ],
    "wof:name":"K C's Plumbing",
    "wof:placetype":"venue"
},
  "geometry": {"coordinates":[-116.033821,50.502705],"type":"Point"}
}