{
  "type": "Feature",
  "properties": {
    "addr:full":"Orono ON L0B 1M0",
    "addr:postcode":"l0b 1m0",
    "iso:country":"CA",
    "sg:city":"Orono",
    "sg:classifiers":[
        {
            "category":"Professional",
            "type":"Services"
        }
    ],
    "sg:phone":"+1 905 983 9550",
    "sg:postcode":"L0B 1M0",
    "sg:province":"ON",
    "sg:tags":[
        "aromatherapy",
        "establishment"
    ],
    "wof:name":"Natural Sense Aromatherapy",
    "wof:placetype":"venue"
},
  "geometry": {"coordinates":[-78.61676,43.976742],"type":"Point"}
}