{
  "type": "Feature",
  "properties": {
    "addr:full":"40 Finch Cres Whitehorse YT Y1A 5X5",
    "addr:housenumber":"40",
    "addr:postcode":"y1a 5x5",
    "addr:street":"Finch Cres",
    "iso:country":"CA",
    "sg:address":"40 Finch Cres",
    "sg:city":"Whitehorse",
    "sg:classifiers":[
        {
            "category":"Professional",
            "subcategory":"Management & Consulting",
            "type":"Services"
        }
    ],
    "sg:phone":"+1 867 393 3281",
    "sg:postcode":"Y1A 5X5",
    "sg:province":"YT",
    "sg:tags":[
        "consultant",
        "business"
    ],
    "wof:name":"Moffatt Management Corp",
    "wof:placetype":"venue"
},
  "geometry": {"coordinates":[-135.11880500000001,60.707901],"type":"Point"}
}