{
  "type": "Feature",
  "properties": {
    "addr:full":"Sainte-Foy QC G1V 3V7",
    "addr:postcode":"g1v 3v7",
    "iso:country":"CA",
    "sg:city":"Sainte-Foy",
    "sg:classifiers":[
        {
            "category":"Professional",
            "subcategory":"Advertising",
            "type":"Services"
        }
    ],
    "sg:phone":"+1 418 659 5540",
    "sg:postcode":"G1V 3V7",
    "sg:province":"QC",
    "sg:tags":[
        "publisher",
        "list",
        "mailing"
    ],
    "wof:name":"Quebec Dans Le Monde",
    "wof:placetype":"venue"
},
  "geometry": {"coordinates":[-71.2917633057,46.7692108154],"type":"Point"}
}