{
  "type": "Feature",
  "properties": {
    "addr:full":"99 Montee Des Bouleaux Saint-Constant QC J5A 1A9",
    "addr:housenumber":"99",
    "addr:postcode":"j5a 1a9",
    "addr:street":"Montee Des Bouleaux",
    "iso:country":"CA",
    "sg:address":"99 Montee Des Bouleaux",
    "sg:city":"Saint-Constant",
    "sg:classifiers":[
        {
            "category":"Education",
            "subcategory":"Dance Studio",
            "type":"Public Place"
        }
    ],
    "sg:phone":"+1 450 632 9841",
    "sg:postcode":"J5A 1A9",
    "sg:province":"QC",
    "sg:tags":[
        "instruction",
        "dancing"
    ],
    "wof:name":"Ecole DE Danse Manon Benette",
    "wof:placetype":"venue"
},
  "geometry": {"coordinates":[-73.5552062988,45.3787727356],"type":"Point"}
}