{
  "type": "Feature",
  "properties": {
    "addr:full":"270 North Service Rd W Oakville ON L6M 2R8",
    "addr:housenumber":"270",
    "addr:postcode":"l6m 2r8",
    "addr:street":"North Service Rd W",
    "iso:country":"CA",
    "sg:address":"270 North Service Rd W",
    "sg:city":"Oakville",
    "sg:classifiers":[
        {
            "category":"Food & Beverages",
            "subcategory":"Liquor & Beverages",
            "type":"Retail Goods"
        }
    ],
    "sg:phone":"+1 905 338 1039",
    "sg:postcode":"L6M 2R8",
    "sg:province":"ON",
    "sg:tags":[
        "store"
    ],
    "wof:name":"Liquor Control Board of Ont",
    "wof:placetype":"venue"
},
  "geometry": {"coordinates":[-79.70665,43.446812],"type":"Point"}
}