{
  "type": "Feature",
  "properties": {
    "addr:full":"210 Mill Rd Moncton NB E1A 4B1",
    "addr:housenumber":"210",
    "addr:postcode":"e1a 4b1",
    "addr:street":"Mill Rd",
    "iso:country":"CA",
    "sg:address":"210 Mill Rd",
    "sg:city":"Moncton",
    "sg:classifiers":[
        {
            "category":"Social Services",
            "subcategory":"Child Care",
            "type":"Services"
        }
    ],
    "sg:phone":"+1 506 857 8999",
    "sg:postcode":"E1A 4B1",
    "sg:province":"NB",
    "wof:name":"Garderie Abc Daycare",
    "wof:placetype":"venue"
},
  "geometry": {"coordinates":[-64.7692642212,46.1116065979],"type":"Point"}
}