{
  "type": "Feature",
  "properties": {
    "addr:full":"Richmond Hill ON L4B 1H4",
    "addr:postcode":"l4b 1h4",
    "iso:country":"CA",
    "sg:city":"Richmond Hill",
    "sg:classifiers":[
        {
            "category":"Food & Beverages",
            "subcategory":"Bakery",
            "type":"Retail Goods"
        }
    ],
    "sg:phone":"+1 905 882 5718",
    "sg:postcode":"L4B 1H4",
    "sg:province":"ON",
    "sg:tags":[
        "baker"
    ],
    "wof:name":"Nancy's Sweets",
    "wof:placetype":"venue"
},
  "geometry": {"coordinates":[-79.392853,43.85125],"type":"Point"}
}