{
  "type": "Feature",
  "properties": {
    "iso:country":"CA",
    "sg:address":"61 8 St NE",
    "sg:city":"Medicine Hat",
    "sg:classifiers":[
        {
            "category":"Retail",
            "subcategory":"Repair Shop",
            "type":"Services"
        }
    ],
    "sg:phone":"+1 403 529 6017",
    "sg:postcode":"T1A 5R2",
    "sg:province":"AB",
    "sg:tags":[
        "plumbing",
        "drain",
        "cleaning",
        "sewer"
    ],
    "wof:name":"Les's Drain Cleaning",
    "wof:placetype":"venue"
},
  "geometry": {"coordinates":[-110.685569763,50.049659729],"type":"Point"}
}