{
  "type": "Feature",
  "properties": {
    "addr:full":"Vancouver BC V6A 1A4",
    "addr:postcode":"v6a 1a4",
    "iso:country":"CA",
    "sg:city":"Vancouver",
    "sg:classifiers":[
        {
            "category":"Manufacturing",
            "subcategory":"Pottery",
            "type":"Manufacturing & Wholesale Goods"
        }
    ],
    "sg:phone":"+1 604 682 2956",
    "sg:postcode":"V6A 1A4",
    "sg:province":"BC",
    "wof:name":"Nicole & CO",
    "wof:placetype":"venue"
},
  "geometry": {"coordinates":[-123.096717834,49.2847175598],"type":"Point"}
}