{
  "type": "Feature",
  "properties": {
    "addr:full":"1609 Rue Superieur Mascouche QC J7K 3C2",
    "addr:housenumber":"1609",
    "addr:postcode":"j7k 3c2",
    "addr:street":"Rue Superieur",
    "iso:country":"CA",
    "sg:address":"1609 Rue Superieur",
    "sg:city":"Mascouche",
    "sg:classifiers":[
        {
            "category":"Shopping",
            "subcategory":"Computers & Home Electronics",
            "type":"Retail Goods"
        }
    ],
    "sg:phone":"+1 450 474 4487",
    "sg:postcode":"J7K 3C2",
    "sg:province":"QC",
    "sg:tags":[
        "software"
    ],
    "wof:name":"Informatiqueservicesplus Inc",
    "wof:placetype":"venue"
},
  "geometry": {"coordinates":[-73.664390564,45.7684898376],"type":"Point"}
}