{
  "type": "Feature",
  "properties": {
    "addr:full":"RR 1 Hawkestone ON L0L 1T0",
    "addr:postcode":"l0l 1t0",
    "addr:street":"Rr 1",
    "iso:country":"CA",
    "sg:address":"RR 1",
    "sg:city":"Hawkestone",
    "sg:classifiers":[
        {
            "category":"Retail",
            "subcategory":"Auto Repair",
            "type":"Services"
        }
    ],
    "sg:phone":"+1 705 487 7007",
    "sg:postcode":"L0L 1T0",
    "sg:province":"ON",
    "sg:tags":[
        "wrecker"
    ],
    "wof:name":"Whitechurch Towing",
    "wof:placetype":"venue"
},
  "geometry": {"coordinates":[-79.4678726196,44.497467041],"type":"Point"}
}