{
  "type": "Feature",
  "properties": {
    "addr:full":"16 Hwy 6 S Ashern MB R0C 0E0",
    "addr:postcode":"r0c 0e0",
    "addr:street":"16 Hwy 6 S",
    "iso:country":"CA",
    "sg:address":"16 Hwy 6 S",
    "sg:city":"Ashern",
    "sg:classifiers":[
        {
            "category":"Home & Garden",
            "subcategory":"Building Materials",
            "type":"Retail Goods"
        }
    ],
    "sg:phone":"+1 204 768 2259",
    "sg:postcode":"R0C 0E0",
    "sg:province":"MB",
    "wof:name":"Interlake Building Supplies",
    "wof:placetype":"venue"
},
  "geometry": {"coordinates":[-98.350121,51.182175],"type":"Point"}
}