{
  "type": "Feature",
  "properties": {
    "addr:full":"118 Bruce St Merrickville ON K0G 1N0",
    "addr:housenumber":"118",
    "addr:postcode":"k0g 1n0",
    "addr:street":"Bruce St",
    "iso:country":"CA",
    "sg:address":"118 Bruce St",
    "sg:city":"Merrickville",
    "sg:classifiers":[
        {
            "category":"Shopping",
            "type":"Retail Goods"
        }
    ],
    "sg:phone":"+1 613 269 3953",
    "sg:postcode":"K0G 1N0",
    "sg:province":"ON",
    "sg:tags":[
        "art",
        "gallery",
        "dealer"
    ],
    "wof:name":"James Jordan Gallery Studio",
    "wof:placetype":"venue"
},
  "geometry": {"coordinates":[-75.83541099999999,44.911591],"type":"Point"}
}