{
  "type": "Feature",
  "properties": {
    "addr:full":"5328 Boul Hebert Saint-Timothee QC J6S 6H3",
    "addr:housenumber":"5328",
    "addr:postcode":"j6s 6h3",
    "addr:street":"Boul Hebert Saint-Timothee",
    "iso:country":"CA",
    "sg:address":"5328 Boul Hebert",
    "sg:city":"Saint-Timothee",
    "sg:classifiers":[
        {
            "category":"Restaurant",
            "type":"Food & Drink"
        }
    ],
    "sg:phone":"+1 450 377 3322",
    "sg:postcode":"J6S 6H3",
    "sg:province":"QC",
    "wof:name":"Restaurant Le Nouveau Plaza",
    "wof:placetype":"venue"
},
  "geometry": {"coordinates":[-74.0384521484,45.289730072],"type":"Point"}
}