{
  "type": "Feature",
  "properties": {
    "addr:full":"Toronto ON M4Y 2P9",
    "addr:postcode":"m4y 2p9",
    "iso:country":"CA",
    "sg:city":"Toronto",
    "sg:classifiers":[
        {
            "category":"Organizations",
            "subcategory":"Labor Organization",
            "type":"Services"
        }
    ],
    "sg:phone":"+1 416 979 9594",
    "sg:postcode":"M4Y 2P9",
    "sg:province":"ON",
    "wof:name":"Cupe",
    "wof:placetype":"venue"
},
  "geometry": {"coordinates":[-79.381485,43.662312],"type":"Point"}
}