{
  "type": "Feature",
  "properties": {
    "addr:full":"5632 4 St NW Calgary AB T2K 1B2",
    "addr:housenumber":"5632 4",
    "addr:postcode":"t2k 1b2",
    "addr:street":"St Nw",
    "iso:country":"CA",
    "sg:address":"5632 4 St NW",
    "sg:city":"Calgary",
    "sg:classifiers":[
        {
            "category":"Personal",
            "subcategory":"Beauty Salon",
            "type":"Services"
        }
    ],
    "sg:phone":"+1 403 295 0170",
    "sg:postcode":"T2K 1B2",
    "sg:province":"AB",
    "wof:name":"Rosa's Beauty Salon",
    "wof:placetype":"venue"
},
  "geometry": {"coordinates":[-114.07122039799999,51.1017036438],"type":"Point"}
}