{
  "type": "Feature",
  "properties": {
    "addr:full":"478 Brunswick St Stratford ON N5A 3N6",
    "addr:housenumber":"478",
    "addr:postcode":"n5a 3n6",
    "addr:street":"Brunswick St",
    "iso:country":"CA",
    "sg:address":"478 Brunswick St",
    "sg:city":"Stratford",
    "sg:classifiers":[
        {
            "category":"Organizations",
            "subcategory":"Religious Organization",
            "type":"Services"
        }
    ],
    "sg:phone":"+1 519 273 5280",
    "sg:postcode":"N5A 3N6",
    "sg:province":"ON",
    "sg:tags":[
        "church"
    ],
    "wof:name":"Church of Christ",
    "wof:placetype":"venue"
},
  "geometry": {"coordinates":[-80.962311,43.369499],"type":"Point"}
}