{
  "type": "Feature",
  "properties": {
    "addr:full":"835 Eglinton Ave E East York ON M4G 4G9",
    "addr:housenumber":"835",
    "addr:postcode":"m4g 4g9",
    "addr:street":"Eglinton Ave E",
    "iso:country":"CA",
    "sg:address":"835 Eglinton Ave E",
    "sg:city":"East York",
    "sg:classifiers":[
        {
            "category":"Retail",
            "subcategory":"Animal Services",
            "type":"Services"
        }
    ],
    "sg:phone":"+1 416 696 0388",
    "sg:postcode":"M4G 4G9",
    "sg:province":"ON",
    "sg:tags":[
        "pet",
        "grooming",
        "washing"
    ],
    "wof:name":"Petsmart",
    "wof:placetype":"venue"
},
  "geometry": {"coordinates":[-79.363243103,43.7137794495],"type":"Point"}
}