{
  "type": "Feature",
  "properties": {
    "addr:full":"1 Goulbourn St Stittsville ON K2S 1N9",
    "addr:housenumber":"1",
    "addr:postcode":"k2s 1n9",
    "addr:street":"Goulbourn St",
    "iso:country":"CA",
    "sg:address":"1 Goulbourn St",
    "sg:city":"Stittsville",
    "sg:classifiers":[
        {
            "category":"Education",
            "subcategory":"School",
            "type":"Public Place"
        }
    ],
    "sg:phone":"+1 613 836 1547",
    "sg:postcode":"K2S 1N9",
    "sg:province":"ON",
    "wof:name":"Ottawa Waldorf School",
    "wof:placetype":"venue"
},
  "geometry": {"coordinates":[-75.921646,45.256348],"type":"Point"}
}