{
  "type": "Feature",
  "properties": {
    "iso:country":"CA",
    "sg:address":"8245 Boul Taschereau",
    "sg:city":"Brossard",
    "sg:classifiers":[
        {
            "category":"Food & Beverages",
            "subcategory":"Groceries & Convenience Stores",
            "type":"Retail Goods"
        }
    ],
    "sg:phone":"+1 450 926 2662",
    "sg:postcode":"J4Y 1A4",
    "sg:province":"QC",
    "sg:tags":[
        "grocer"
    ],
    "wof:name":"Depanneur Taschereau",
    "wof:placetype":"venue"
},
  "geometry": {"coordinates":[-73.469795,45.447025],"type":"Point"}
}