{
  "type": "Feature",
  "properties": {
    "addr:full":"12 Rue Lussier Napierville QC J0J 1L0",
    "addr:housenumber":"12",
    "addr:postcode":"j0j 1l0",
    "addr:street":"Rue Lussier",
    "iso:country":"CA",
    "sg:address":"12 Rue Lussier",
    "sg:city":"Napierville",
    "sg:classifiers":[
        {
            "category":"Travel",
            "subcategory":"Campground",
            "type":"Entertainment"
        }
    ],
    "sg:phone":"+1 450 245 3638",
    "sg:postcode":"J0J 1L0",
    "sg:province":"QC",
    "wof:name":"Camping Des Arpents Verts",
    "wof:placetype":"venue"
},
  "geometry": {"coordinates":[-73.41564200000001,45.193989],"type":"Point"}
}