{
  "type": "Feature",
  "properties": {
    "addr:full":"Sillery QC G1S 1T8",
    "addr:postcode":"g1s 1t8",
    "iso:country":"CA",
    "sg:city":"Sillery",
    "sg:classifiers":[
        {
            "category":"Social Services",
            "type":"Services"
        }
    ],
    "sg:phone":"+1 418 688 5530",
    "sg:postcode":"G1S 1T8",
    "sg:province":"QC",
    "sg:tags":[
        "organization",
        "welfare"
    ],
    "wof:name":"Centre International Des Femme",
    "wof:placetype":"venue"
},
  "geometry": {"coordinates":[-71.239441,46.796787],"type":"Point"}
}