{
  "type": "Feature",
  "properties": {
    "iso:country":"CA",
    "sg:address":"910 Queen St",
    "sg:city":"Saskatoon",
    "sg:classifiers":[
        {
            "category":"Social Services",
            "type":"Services"
        }
    ],
    "sg:phone":"+1 306 664 2409",
    "sg:postcode":"S7K 0N2",
    "sg:province":"SK",
    "sg:tags":[
        "counseling"
    ],
    "wof:name":"A Better Way Professional",
    "wof:placetype":"venue"
},
  "geometry": {"coordinates":[-106.64875793500001,52.1367454529],"type":"Point"}
}