{
  "type": "Feature",
  "properties": {
    "addr:full":"173 Rue Georges Masson-Angers QC J8M 1T6",
    "addr:housenumber":"173",
    "addr:postcode":"j8m 1t6",
    "addr:street":"Rue Georges Masson-Angers",
    "iso:country":"CA",
    "sg:address":"173 Rue Georges",
    "sg:city":"Masson-Angers",
    "sg:classifiers":[
        {
            "category":"Real Estate",
            "subcategory":"Real Estate Agent",
            "type":"Services"
        }
    ],
    "sg:phone":"+1 819 986 8794",
    "sg:postcode":"J8M 1T6",
    "sg:province":"QC",
    "sg:tags":[
        "agency",
        "rental"
    ],
    "wof:name":"Location J'En Loue",
    "wof:placetype":"venue"
},
  "geometry": {"coordinates":[-75.429047,45.559593],"type":"Point"}
}