{
  "type": "Feature",
  "properties": {
    "addr:full":"1331 1E Rue # 200 Sainte-Marie QC G6E 3L9",
    "addr:housenumber":"1331",
    "addr:postcode":"g6e 3l9",
    "addr:street":"1E Rue # 200",
    "iso:country":"CA",
    "sg:address":"1331 1E Rue # 200",
    "sg:city":"Sainte-Marie",
    "sg:classifiers":[
        {
            "category":"Freight",
            "type":"Transportation"
        }
    ],
    "sg:phone":"+1 418 387 7149",
    "sg:postcode":"G6E 3L9",
    "sg:province":"QC",
    "sg:tags":[
        "building",
        "commercial",
        "contractor"
    ],
    "wof:name":"Construmar & Assoc Inc",
    "wof:placetype":"venue"
},
  "geometry": {"coordinates":[-65.9838256836,48.1726264954],"type":"Point"}
}