{
  "type": "Feature",
  "properties": {
    "addr:full":"Port Robinson ON L0S 1K0",
    "addr:postcode":"l0s 1k0",
    "addr:street":"Port Robinson",
    "iso:country":"CA",
    "sg:city":"Port Robinson",
    "sg:classifiers":[
        {
            "category":"Building & Trades",
            "subcategory":"Plumbing",
            "type":"Services"
        }
    ],
    "sg:phone":"+1 905 384 9884",
    "sg:postcode":"L0S 1K0",
    "sg:province":"ON",
    "sg:tags":[
        "sewer",
        "tank",
        "septic",
        "contractor"
    ],
    "wof:name":"Bob Robinson Construction",
    "wof:placetype":"venue"
},
  "geometry": {"coordinates":[-79.210098,43.038399],"type":"Point"}
}