{
  "type": "Feature",
  "properties": {
    "addr:full":"105 Rue Saint-Eustache Saint-Eustache QC J7R 2L4",
    "addr:housenumber":"105",
    "addr:postcode":"j7r 2l4",
    "addr:street":"Rue Saint-Eustache",
    "iso:country":"CA",
    "sg:address":"105 Rue Saint-Eustache",
    "sg:city":"Saint-Eustache",
    "sg:classifiers":[
        {
            "category":"Restaurant",
            "type":"Food & Drink"
        }
    ],
    "sg:phone":"+1 450 473 6881",
    "sg:postcode":"J7R 2L4",
    "sg:province":"QC",
    "sg:tags":[
        "shop",
        "coffee"
    ],
    "wof:name":"Astoria Bistro Cafe",
    "wof:placetype":"venue"
},
  "geometry": {"coordinates":[-73.8921127319,45.5588302612],"type":"Point"}
}