{
  "type": "Feature",
  "properties": {
    "addr:full":"4551 Chase Rd Winfield BC V4V 1L7",
    "addr:housenumber":"4551",
    "addr:postcode":"v4v 1l7",
    "addr:street":"Chase Rd",
    "iso:country":"CA",
    "sg:address":"4551 Chase Rd",
    "sg:city":"Winfield",
    "sg:classifiers":[
        {
            "category":"Building & Trades",
            "subcategory":"Landscaping Services",
            "type":"Services"
        }
    ],
    "sg:phone":"+1 250 766 4418",
    "sg:postcode":"V4V 1L7",
    "sg:province":"BC",
    "sg:tags":[
        "excavating",
        "landscape",
        "contractor"
    ],
    "wof:name":"Lake Country Excavating Ltd",
    "wof:placetype":"venue"
},
  "geometry": {"coordinates":[-119.405602,50.024536],"type":"Point"}
}