{
  "type": "Feature",
  "properties": {
    "iso:country":"CA",
    "sg:address":"17 Dean St",
    "sg:city":"Brampton",
    "sg:classifiers":[
        {
            "category":"Social Services",
            "type":"Services"
        }
    ],
    "sg:phone":"+1 905 457 6055",
    "sg:postcode":"L6W 1M7",
    "sg:province":"ON",
    "sg:tags":[
        "organization",
        "welfare"
    ],
    "wof:name":"Elder Help Peel",
    "wof:placetype":"venue"
},
  "geometry": {"coordinates":[-79.738617,43.685593],"type":"Point"}
}