{
  "type": "Feature",
  "properties": {
    "addr:full":"8414 Wyandotte St E Windsor ON N8S 1T6",
    "addr:housenumber":"8414",
    "addr:postcode":"n8s 1t6",
    "addr:street":"Wyandotte St E",
    "iso:country":"CA",
    "sg:address":"8414 Wyandotte St E",
    "sg:city":"Windsor",
    "sg:classifiers":[
        {
            "category":"Restaurant",
            "type":"Food & Drink"
        }
    ],
    "sg:phone":"+1 519 945 9800",
    "sg:postcode":"N8S 1T6",
    "sg:province":"ON",
    "sg:tags":[
        "pizza"
    ],
    "wof:name":"Domino's Pizza",
    "wof:placetype":"venue"
},
  "geometry": {"coordinates":[-82.93718,42.333576],"type":"Point"}
}