{
  "type": "Feature",
  "properties": {
    "addr:full":"2818 Round Lake Rd Round Lake Centre ON K0J 2J0",
    "addr:housenumber":"2818",
    "addr:postcode":"k0j 2j0",
    "addr:street":"Round Lake Rd",
    "iso:country":"CA",
    "sg:address":"2818 Round Lake Rd",
    "sg:city":"Round Lake Centre",
    "sg:classifiers":[
        {
            "category":"Wholesale",
            "subcategory":"Hardware",
            "type":"Manufacturing & Wholesale Goods"
        }
    ],
    "sg:phone":"+1 613 757 3428",
    "sg:postcode":"K0J 2J0",
    "sg:province":"ON",
    "sg:tags":[
        "equipment",
        "energy",
        "solar"
    ],
    "wof:name":"Sunstream Solar",
    "wof:placetype":"venue"
},
  "geometry": {"coordinates":[-77.538391,45.616329],"type":"Point"}
}