{
  "type": "Feature",
  "properties": {
    "addr:full":"1040 343 Rte Saint-Alphonse-Rodriguez QC J0K 1W0",
    "addr:housenumber":"1040",
    "addr:postcode":"j0k 1w0",
    "addr:street":"343 Rte",
    "iso:country":"CA",
    "sg:address":"1040 343 Rte",
    "sg:city":"Saint-Alphonse-Rodriguez",
    "sg:classifiers":[
        {
            "category":"Shopping",
            "subcategory":"Catalog Store",
            "type":"Retail Goods"
        }
    ],
    "sg:phone":"+1 450 883 3579",
    "sg:postcode":"J0K 1W0",
    "sg:province":"QC",
    "sg:tags":[
        "mail",
        "order",
        "internet"
    ],
    "wof:name":"Sears Canada Inc",
    "wof:placetype":"venue"
},
  "geometry": {"coordinates":[-73.6927032471,46.1866722107],"type":"Point"}
}