{
  "type": "Feature",
  "properties": {
    "addr:full":"369 Boul Laure Sept-Iles QC G4R 1X2",
    "addr:housenumber":"369",
    "addr:postcode":"g4r 1x2",
    "addr:street":"Boul Laure Sept-Iles",
    "iso:country":"CA",
    "sg:address":"369 Boul Laure",
    "sg:city":"Sept-Iles",
    "sg:classifiers":[
        {
            "category":"Utilities",
            "subcategory":"Fuel Oil & Lpg",
            "type":"Services"
        }
    ],
    "sg:phone":"+1 418 961 4141",
    "sg:postcode":"G4R 1X2",
    "sg:province":"QC",
    "sg:tags":[
        "propane",
        "gas"
    ],
    "wof:name":"Propane Nord Cotier",
    "wof:placetype":"venue"
},
  "geometry": {"coordinates":[-66.372322,50.210297],"type":"Point"}
}