{
  "type": "Feature",
  "properties": {
    "addr:full":"4135 Rue Jean-Talon O Montreal QC H4P 1W6",
    "addr:housenumber":"4135",
    "addr:postcode":"h4p 1w6",
    "addr:street":"Rue Jean-Talon O",
    "iso:country":"CA",
    "sg:address":"4135 Rue Jean-Talon O",
    "sg:city":"Montreal",
    "sg:classifiers":[
        {
            "category":"Shopping",
            "type":"Retail Goods"
        }
    ],
    "sg:phone":"+1 514 733 1733",
    "sg:postcode":"H4P 1W6",
    "sg:province":"QC",
    "sg:tags":[
        "picture",
        "frame"
    ],
    "wof:name":"Bank S Art Studio",
    "wof:placetype":"venue"
},
  "geometry": {"coordinates":[-73.646179,45.50116],"type":"Point"}
}