{
  "type": "Feature",
  "properties": {
    "iso:country":"CA",
    "sg:address":"307 Main St",
    "sg:city":"Vancouver",
    "sg:classifiers":[
        {
            "category":"Food & Beverages",
            "subcategory":"Groceries & Convenience Stores",
            "type":"Retail Goods"
        }
    ],
    "sg:phone":"+1 604 685 6255",
    "sg:postcode":"V6A 2S9",
    "sg:province":"BC",
    "sg:tags":[
        "grocer"
    ],
    "wof:name":"Main Street Pit Stop",
    "wof:placetype":"venue"
},
  "geometry": {"coordinates":[-123.099815369,49.2821617126],"type":"Point"}
}