{
  "type": "Feature",
  "properties": {
    "addr:full":"1368 Ch Du Bord-DE-L'Eau Laval QC H7Y 1C4",
    "addr:postcode":"1368;h7y 1c4",
    "addr:street":"Ch Du Bord-De-L'Eau",
    "iso:country":"CA",
    "sg:address":"1368 Ch Du Bord-DE-L'Eau",
    "sg:city":"Laval",
    "sg:classifiers":[
        {
            "category":"Building & Trades",
            "subcategory":"Pest Control",
            "type":"Services"
        }
    ],
    "sg:phone":"+1 450 752 2747",
    "sg:postcode":"H7Y 1C4",
    "sg:province":"QC",
    "wof:name":"Centre D'Extermination Rawdon",
    "wof:placetype":"venue"
},
  "geometry": {"coordinates":[-73.77748099999999,45.52153],"type":"Point"}
}