{
  "type": "Feature",
  "properties": {
    "iso:country":"CA",
    "sg:address":"551 Huron St",
    "sg:city":"Stratford",
    "sg:classifiers":[
        {
            "category":"Cinema",
            "subcategory":"Movie Theater",
            "type":"Entertainment"
        }
    ],
    "sg:phone":"+1 519 273 6780",
    "sg:postcode":"N5A 5T8",
    "sg:province":"ON",
    "wof:name":"Stratford Cinemas",
    "wof:placetype":"venue"
},
  "geometry": {"coordinates":[-81.00280761720001,43.3804702759],"type":"Point"}
}