{
  "type": "Feature",
  "properties": {
    "addr:full":"Calgary AB T2S 2T8",
    "addr:postcode":"t2s 2t8",
    "iso:country":"CA",
    "sg:city":"Calgary",
    "sg:classifiers":[
        {
            "category":"Utilities",
            "subcategory":"Fuel Oil & Lpg",
            "type":"Services"
        }
    ],
    "sg:phone":"+1 403 228 5815",
    "sg:postcode":"T2S 2T8",
    "sg:province":"AB",
    "sg:tags":[
        "propane",
        "gas"
    ],
    "wof:name":"Stittco Energy Ltd",
    "wof:placetype":"venue"
},
  "geometry": {"coordinates":[-114.067352,51.037682],"type":"Point"}
}