{
  "type": "Feature",
  "properties": {
    "addr:full":"139 Rue Saint-Omer Levis QC G6V 7L6",
    "addr:housenumber":"139",
    "addr:postcode":"g6v 7l6",
    "addr:street":"Rue Saint-Omer",
    "iso:country":"CA",
    "sg:address":"139 Rue Saint-Omer",
    "sg:city":"Levis",
    "sg:classifiers":[
        {
            "category":"Manufacturing",
            "subcategory":"Metals",
            "type":"Manufacturing & Wholesale Goods"
        }
    ],
    "sg:phone":"+1 418 837 7688",
    "sg:postcode":"G6V 7L6",
    "sg:province":"QC",
    "sg:tags":[
        "trophy",
        "medal",
        "award"
    ],
    "wof:name":"Au Royaume Du Trophee",
    "wof:placetype":"venue"
},
  "geometry": {"coordinates":[-71.166061,46.809841],"type":"Point"}
}