{
  "type": "Feature",
  "properties": {
    "addr:full":"4 Rue DE LA Porte Quebec QC G1R 4M9",
    "addr:housenumber":"4",
    "addr:postcode":"g1r 4m9",
    "addr:street":"Rue De La Porte",
    "iso:country":"CA",
    "sg:address":"4 Rue DE LA Porte",
    "sg:city":"Quebec",
    "sg:classifiers":[
        {
            "category":"Travel",
            "subcategory":"Hotels & Motels",
            "type":"Entertainment"
        }
    ],
    "sg:phone":"+1 418 694 1592",
    "sg:postcode":"G1R 4M9",
    "sg:province":"QC",
    "wof:name":"Manoir DE LA Terrasse",
    "wof:placetype":"venue"
},
  "geometry": {"coordinates":[-71.206429,46.810886],"type":"Point"}
}