{
  "type": "Feature",
  "properties": {
    "addr:full":"20816 Newlands Dr Langley BC V3A 4M2",
    "addr:housenumber":"20816",
    "addr:postcode":"v3a 4m2",
    "addr:street":"Newlands Dr",
    "iso:country":"CA",
    "sg:address":"20816 Newlands Dr",
    "sg:city":"Langley",
    "sg:classifiers":[
        {
            "category":"Retail",
            "subcategory":"Laundry & Dry Cleaning",
            "type":"Services"
        }
    ],
    "sg:phone":"+1 604 530 4982",
    "sg:postcode":"V3A 4M2",
    "sg:province":"BC",
    "sg:tags":[
        "cleaners",
        "rug",
        "carpet"
    ],
    "wof:name":"Coit Drapery & Carpet Cleaning",
    "wof:placetype":"venue"
},
  "geometry": {"coordinates":[-122.64621,49.088875],"type":"Point"}
}