{
  "type": "Feature",
  "properties": {
    "addr:full":"314 James St Wallaceburg ON N8A 2N5",
    "addr:housenumber":"314",
    "addr:postcode":"n8a 2n5",
    "addr:street":"James St",
    "iso:country":"CA",
    "sg:address":"314 James St",
    "sg:city":"Wallaceburg",
    "sg:classifiers":[
        {
            "category":"Shopping",
            "subcategory":"Computers & Home Electronics",
            "type":"Retail Goods"
        }
    ],
    "sg:phone":"+1 519 627 1441",
    "sg:postcode":"N8A 2N5",
    "sg:province":"ON",
    "sg:tags":[
        "equipment",
        "dealer"
    ],
    "wof:name":"P C Business Systems",
    "wof:placetype":"venue"
},
  "geometry": {"coordinates":[-82.3830413818,42.5946578979],"type":"Point"}
}