{
  "type": "Feature",
  "properties": {
    "addr:full":"1558 Ellis St Kelowna BC V1Y 2A6",
    "addr:housenumber":"1558",
    "addr:postcode":"v1y 2a6",
    "addr:street":"Ellis St",
    "iso:country":"CA",
    "sg:address":"1558 Ellis St",
    "sg:city":"Kelowna",
    "sg:classifiers":[
        {
            "category":"Personal",
            "subcategory":"Barber",
            "type":"Services"
        }
    ],
    "sg:phone":"+1 250 763 7224",
    "sg:postcode":"V1Y 2A6",
    "sg:province":"BC",
    "wof:name":"Pete's Barber-Stylists",
    "wof:placetype":"venue"
},
  "geometry": {"coordinates":[-119.493743897,49.8857536316],"type":"Point"}
}