{
  "type": "Feature",
  "properties": {
    "addr:full":"225 Broadway Winnipeg MB R3C 5R4",
    "addr:housenumber":"225",
    "addr:postcode":"r3c 5r4",
    "addr:street":"Broadway",
    "iso:country":"CA",
    "sg:address":"225 Broadway",
    "sg:city":"Winnipeg",
    "sg:classifiers":[
        {
            "category":"Banks & Credit Unions",
            "subcategory":"Bank",
            "type":"Services"
        }
    ],
    "sg:phone":"+1 204 925 2600",
    "sg:postcode":"R3C 5R4",
    "sg:province":"MB",
    "wof:name":"Cambrian Credit Union",
    "wof:placetype":"venue"
},
  "geometry": {"coordinates":[-97.13726043699999,49.8885345459],"type":"Point"}
}