{
  "type": "Feature",
  "properties": {
    "iso:country":"CA",
    "sg:address":"95 Rue Quevillon",
    "sg:city":"Varennes",
    "sg:classifiers":[
        {
            "category":"Personal",
            "subcategory":"Beauty Salon",
            "type":"Services"
        }
    ],
    "sg:phone":"+1 450 652 0720",
    "sg:postcode":"J3X 1X6",
    "sg:province":"QC",
    "wof:name":"Cajolie Coiffure",
    "wof:placetype":"venue"
},
  "geometry": {"coordinates":[-73.4312133789,45.6863479614],"type":"Point"}
}