{
  "type": "Feature",
  "properties": {
    "addr:full":"Sainte-Julie QC J3E 1R6",
    "addr:postcode":"j3e 1r6",
    "iso:country":"CA",
    "sg:city":"Sainte-Julie",
    "sg:classifiers":[
        {
            "category":"Professional",
            "subcategory":"Art Services",
            "type":"Services"
        }
    ],
    "sg:phone":"+1 450 922 1666",
    "sg:postcode":"J3E 1R6",
    "sg:province":"QC",
    "sg:tags":[
        "graphic",
        "designer"
    ],
    "wof:name":"Art Image Communication Design",
    "wof:placetype":"venue"
},
  "geometry": {"coordinates":[-73.331238,45.599262],"type":"Point"}
}