{
  "type": "Feature",
  "properties": {
    "addr:full":"55 Costa Rd Concord ON L4K 1M8",
    "addr:housenumber":"55",
    "addr:postcode":"l4k 1m8",
    "addr:street":"Costa Rd",
    "iso:country":"CA",
    "sg:address":"55 Costa Rd",
    "sg:city":"Concord",
    "sg:classifiers":[
        {
            "category":"Building & Trades",
            "subcategory":"Construction",
            "type":"Services"
        }
    ],
    "sg:phone":"+1 905 669 5282",
    "sg:postcode":"L4K 1M8",
    "sg:province":"ON",
    "sg:tags":[
        "scaffolding",
        "contractor"
    ],
    "wof:name":"Aluma Systems Canada Inc",
    "wof:placetype":"venue"
},
  "geometry": {"coordinates":[-79.51409099999999,43.793743],"type":"Point"}
}