{
  "type": "Feature",
  "properties": {
    "addr:full":"3502 Cordiale Dr Vancouver BC V5S 4H3",
    "addr:housenumber":"3502",
    "addr:postcode":"v5s 4h3",
    "addr:street":"Cordiale Dr",
    "iso:country":"CA",
    "sg:address":"3502 Cordiale Dr",
    "sg:city":"Vancouver",
    "sg:classifiers":[
        {
            "category":"Real Estate",
            "subcategory":"Real Estate Agent",
            "type":"Services"
        }
    ],
    "sg:phone":"+1 604 436 5646",
    "sg:postcode":"V5S 4H3",
    "sg:province":"BC",
    "sg:tags":[
        "cooperative"
    ],
    "wof:name":"Coeur Housing CO-OP",
    "wof:placetype":"venue"
},
  "geometry": {"coordinates":[-123.027596,49.209789],"type":"Point"}
}