{
  "type": "Feature",
  "properties": {
    "iso:country":"CA",
    "sg:address":"5 James St",
    "sg:city":"St Catharines",
    "sg:classifiers":[
        {
            "category":"Restaurant",
            "type":"Food & Drink"
        }
    ],
    "sg:phone":"+1 905 685 3621",
    "sg:postcode":"L2R 5B7",
    "sg:province":"ON",
    "sg:tags":[
        "delicatessen",
        "caterer"
    ],
    "wof:name":"New Delicatessen",
    "wof:placetype":"venue"
},
  "geometry": {"coordinates":[-79.244392,43.157921],"type":"Point"}
}