{
  "type": "Feature",
  "properties": {
    "addr:full":"13081 Tenth Line Stouffville ON L4A 7X4",
    "addr:housenumber":"13081",
    "addr:postcode":"l4a 7x4",
    "addr:street":"Tenth Line",
    "iso:country":"CA",
    "sg:address":"13081 Tenth Line",
    "sg:city":"Stouffville",
    "sg:classifiers":[
        {
            "category":"Manufacturing",
            "subcategory":"Metals",
            "type":"Manufacturing & Wholesale Goods"
        }
    ],
    "sg:phone":"+1 905 640 4161",
    "sg:postcode":"L4A 7X4",
    "sg:province":"ON",
    "sg:tags":[
        "steel"
    ],
    "wof:name":"William J Barry Welding Ltd",
    "wof:placetype":"venue"
},
  "geometry": {"coordinates":[-79.235764,43.995358],"type":"Point"}
}