{
  "type": "Feature",
  "properties": {
    "addr:full":"RR 2 STN Main Parry Sound ON P2A 2W8",
    "addr:postcode":"p2a 2w8",
    "addr:street":"Rr 2 Stn Main",
    "iso:country":"CA",
    "sg:address":"RR 2 STN Main",
    "sg:city":"Parry Sound",
    "sg:classifiers":[
        {
            "category":"Recreation",
            "type":"Entertainment"
        }
    ],
    "sg:phone":"+1 705 378 2823",
    "sg:postcode":"P2A 2W8",
    "sg:province":"ON",
    "sg:tags":[
        "caterer",
        "hall",
        "auditorium"
    ],
    "wof:name":"Foley Agric Soc",
    "wof:placetype":"venue"
},
  "geometry": {"coordinates":[-80.036362,45.344769],"type":"Point"}
}