{
  "type": "Feature",
  "properties": {
    "addr:full":"35 Rue DE Salaberry Saint-Jean-Sur-Richelieu QC J3B 6P7",
    "addr:housenumber":"35",
    "addr:postcode":"j3b 6p7",
    "addr:street":"Rue De Salaberry",
    "iso:country":"CA",
    "sg:address":"35 Rue DE Salaberry",
    "sg:city":"Saint-Jean-Sur-Richelieu",
    "sg:classifiers":[
        {
            "category":"Bars & Pubs",
            "type":"Food & Drink"
        }
    ],
    "sg:phone":"+1 450 346 0259",
    "sg:postcode":"J3B 6P7",
    "sg:province":"QC",
    "sg:tags":[
        "lounge",
        "cocktail"
    ],
    "wof:name":"Bar Du Parc",
    "wof:placetype":"venue"
},
  "geometry": {"coordinates":[-73.254059,45.308746],"type":"Point"}
}