{
  "type": "Feature",
  "properties": {
    "addr:full":"249 Rue Sainte-Anne Varennes QC J3X 1R6",
    "addr:housenumber":"249",
    "addr:postcode":"j3x 1r6",
    "addr:street":"Rue Sainte-Anne",
    "iso:country":"CA",
    "sg:address":"249 Rue Sainte-Anne",
    "sg:city":"Varennes",
    "sg:classifiers":[
        {
            "category":"Professional",
            "subcategory":"Business Services",
            "type":"Services"
        }
    ],
    "sg:phone":"+1 450 652 9336",
    "sg:postcode":"J3X 1R6",
    "sg:province":"QC",
    "sg:tags":[
        "upholstery",
        "top",
        "cover",
        "sign",
        "painter",
        "boat"
    ],
    "wof:name":"Ateliers Provost Jodoin Enr",
    "wof:placetype":"venue"
},
  "geometry": {"coordinates":[-73.442116,45.685307],"type":"Point"}
}