{
  "type": "Feature",
  "properties": {
    "addr:full":"Vancouver BC V6H 3X8",
    "addr:postcode":"v6h 3x8",
    "iso:country":"CA",
    "sg:city":"Vancouver",
    "sg:classifiers":[
        {
            "category":"Banks & Credit Unions",
            "subcategory":"Investment Brokerage",
            "type":"Services"
        }
    ],
    "sg:phone":"+1 604 733 9335",
    "sg:postcode":"V6H 3X8",
    "sg:province":"BC",
    "sg:tags":[
        "consultant",
        "planning",
        "financial"
    ],
    "wof:name":"Assante Capital Management Ltd",
    "wof:placetype":"venue"
},
  "geometry": {"coordinates":[-123.133201599,49.2636566162],"type":"Point"}
}