{
  "type": "Feature",
  "properties": {
    "addr:full":"39 Studney Dr Hay River NT X0E 0R6",
    "addr:housenumber":"39",
    "addr:postcode":"x0e 0r6",
    "addr:street":"Studney Dr",
    "iso:country":"CA",
    "sg:address":"39 Studney Dr",
    "sg:city":"Hay River",
    "sg:classifiers":[
        {
            "category":"Mining & Drilling",
            "type":"Manufacturing & Wholesale Goods"
        }
    ],
    "sg:phone":"+1 867 874 2720",
    "sg:postcode":"X0E 0R6",
    "sg:province":"NT",
    "sg:tags":[
        "field",
        "oil",
        "trucking"
    ],
    "wof:name":"Hay River Disposals Ltd",
    "wof:placetype":"venue"
},
  "geometry": {"coordinates":[-115.799576,60.807224],"type":"Point"}
}