{
  "type": "Feature",
  "properties": {
    "addr:full":"PO Box 630 Breton AB T0C 0P0",
    "addr:housenumber":"po;630",
    "addr:postcode":"t0c 0p0",
    "addr:street":"Box",
    "iso:country":"CA",
    "sg:address":"PO Box 630",
    "sg:city":"Breton",
    "sg:classifiers":[
        {
            "category":"Freight",
            "type":"Transportation"
        }
    ],
    "sg:phone":"+1 780 696 3585",
    "sg:postcode":"T0C 0P0",
    "sg:province":"AB",
    "sg:tags":[
        "field",
        "oil"
    ],
    "wof:name":"W C Trucking Ltd",
    "wof:placetype":"venue"
},
  "geometry": {"coordinates":[-114.46608734100001,53.1123580933],"type":"Point"}
}