{
  "type": "Feature",
  "properties": {
    "addr:full":"217 Av Leonidas S Rimouski QC G5L 2T5",
    "addr:postcode":"g5l 2t5",
    "addr:street":"217 Av Leonidas S",
    "iso:country":"CA",
    "sg:address":"217 Av Leonidas S",
    "sg:city":"Rimouski",
    "sg:classifiers":[
        {
            "category":"Recreation",
            "type":"Entertainment"
        }
    ],
    "sg:phone":"+1 418 724 9300",
    "sg:postcode":"G5L 2T5",
    "sg:province":"QC",
    "sg:tags":[
        "bingo",
        "game"
    ],
    "wof:name":"Regroupement Du Grand Rimouski",
    "wof:placetype":"venue"
},
  "geometry": {"coordinates":[-68.507614,48.461155],"type":"Point"}
}