{
  "type": "Feature",
  "properties": {
    "addr:full":"563 Queen St W Toronto ON M5V 2B6",
    "addr:housenumber":"563",
    "addr:postcode":"m5v 2b6",
    "addr:street":"Queen St W",
    "iso:country":"CA",
    "sg:address":"563 Queen St W",
    "sg:city":"Toronto",
    "sg:classifiers":[
        {
            "category":"Home & Garden",
            "subcategory":"Hardware",
            "type":"Retail Goods"
        }
    ],
    "sg:phone":"+1 416 504 3569",
    "sg:postcode":"M5V 2B6",
    "sg:province":"ON",
    "wof:name":"Simply Pro Hardware",
    "wof:placetype":"venue"
},
  "geometry": {"coordinates":[-79.400429,43.647823],"type":"Point"}
}