{
  "type": "Feature",
  "properties": {
    "iso:country":"CA",
    "sg:address":"16 Superior St",
    "sg:city":"Devon",
    "sg:classifiers":[
        {
            "category":"Autos & Motor Vehicles",
            "subcategory":"Fuel & Gas Station",
            "type":"Retail Goods"
        }
    ],
    "sg:phone":"+1 780 987 5551",
    "sg:postcode":"T9G 1Z1",
    "sg:province":"AB",
    "sg:tags":[
        "oil"
    ],
    "wof:name":"Extra Foods Gas Bar",
    "wof:placetype":"venue"
},
  "geometry": {"coordinates":[-113.73286438,53.3651847839],"type":"Point"}
}