{
  "type": "Feature",
  "properties": {
    "iso:country":"CA",
    "sg:address":"975 Rue King E",
    "sg:city":"Sherbrooke",
    "sg:classifiers":[
        {
            "category":"Restaurant",
            "type":"Food & Drink"
        }
    ],
    "sg:phone":"+1 819 563 0585",
    "sg:postcode":"J1G 1E3",
    "sg:province":"QC",
    "wof:name":"Mc Donald's",
    "wof:placetype":"venue"
},
  "geometry": {"coordinates":[-71.86795043950001,45.4081878662],"type":"Point"}
}