{
  "type": "Feature",
  "properties": {
    "addr:full":"41 Salisbury Ave Toronto ON M4X 1C5",
    "addr:housenumber":"41",
    "addr:postcode":"m4x 1c5",
    "addr:street":"Salisbury Ave",
    "iso:country":"CA",
    "sg:address":"41 Salisbury Ave",
    "sg:city":"Toronto",
    "sg:classifiers":[
        {
            "category":"Social Services",
            "type":"Services"
        }
    ],
    "sg:phone":"+1 416 923 2719",
    "sg:postcode":"M4X 1C5",
    "sg:province":"ON",
    "sg:tags":[
        "instruction",
        "health",
        "care"
    ],
    "wof:name":"J Goulding Consultants Ltd",
    "wof:placetype":"venue"
},
  "geometry": {"coordinates":[-79.365486,43.667168],"type":"Point"}
}