{
  "type": "Feature",
  "properties": {
    "iso:country":"CA",
    "sg:address":"41950 Government Rd",
    "sg:city":"Brackendale",
    "sg:classifiers":[
        {
            "category":"Shopping",
            "type":"Retail Goods"
        }
    ],
    "sg:phone":"+1 604 898 3333",
    "sg:postcode":"V0N 1H0",
    "sg:province":"BC",
    "sg:tags":[
        "art",
        "gallery",
        "dealer"
    ],
    "wof:name":"Brackendale Art Gallery",
    "wof:placetype":"venue"
},
  "geometry": {"coordinates":[-123.150535584,49.7677688599],"type":"Point"}
}