{
  "type": "Feature",
  "properties": {
    "addr:full":"Calgary AB T2C 1Y3",
    "addr:postcode":"t2c 1y3",
    "iso:country":"CA",
    "sg:city":"Calgary",
    "sg:classifiers":[
        {
            "category":"Building & Trades",
            "subcategory":"Landscaping Services",
            "type":"Services"
        }
    ],
    "sg:phone":"+1 403 279 9791",
    "sg:postcode":"T2C 1Y3",
    "sg:province":"AB",
    "sg:tags":[
        "landscape",
        "contractor"
    ],
    "wof:name":"Greentree Landscapes",
    "wof:placetype":"venue"
},
  "geometry": {"coordinates":[-113.971619,51.000755],"type":"Point"}
}