{
  "type": "Feature",
  "properties": {
    "addr:full":"1681 Church Ave Winnipeg MB R2X 2Y7",
    "addr:housenumber":"1681",
    "addr:postcode":"r2x 2y7",
    "addr:street":"Church Ave",
    "iso:country":"CA",
    "sg:address":"1681 Church Ave",
    "sg:city":"Winnipeg",
    "sg:classifiers":[
        {
            "category":"Manufacturing",
            "subcategory":"Printing",
            "type":"Manufacturing & Wholesale Goods"
        }
    ],
    "sg:phone":"+1 204 694 1034",
    "sg:postcode":"R2X 2Y7",
    "sg:province":"MB",
    "sg:tags":[
        "printer"
    ],
    "wof:name":"Lorne's Litho Ltd",
    "wof:placetype":"venue"
},
  "geometry": {"coordinates":[-97.19016999999999,49.94117],"type":"Point"}
}