{
  "type": "Feature",
  "properties": {
    "addr:full":"1335 Plains Rd E Burlington ON L7R 3P7",
    "addr:housenumber":"1335",
    "addr:postcode":"l7r 3p7",
    "addr:street":"Plains Rd E",
    "iso:country":"CA",
    "sg:address":"1335 Plains Rd E",
    "sg:city":"Burlington",
    "sg:classifiers":[
        {
            "category":"Social Services",
            "subcategory":"Child Care",
            "type":"Services"
        }
    ],
    "sg:phone":"+1 905 637 2037",
    "sg:postcode":"L7R 3P7",
    "sg:province":"ON",
    "wof:name":"Ressel Day Nursery School",
    "wof:placetype":"venue"
},
  "geometry": {"coordinates":[-79.82053399999999,43.335072],"type":"Point"}
}