{
  "type": "Feature",
  "properties": {
    "addr:full":"116 Thames St S Ingersoll ON N5C 2T4",
    "addr:housenumber":"116",
    "addr:postcode":"n5c 2t4",
    "addr:street":"Thames St S",
    "iso:country":"CA",
    "sg:address":"116 Thames St S",
    "sg:city":"Ingersoll",
    "sg:classifiers":[
        {
            "category":"Personal",
            "subcategory":"Beauty Salon",
            "type":"Services"
        }
    ],
    "sg:phone":"+1 519 485 0511",
    "sg:postcode":"N5C 2T4",
    "sg:province":"ON",
    "wof:name":"Tony & Gus Hair Styling",
    "wof:placetype":"venue"
},
  "geometry": {"coordinates":[-80.883331,43.038696],"type":"Point"}
}