{
  "type": "Feature",
  "properties": {
    "addr:full":"960 103rd St North Battleford SK S9A 1K2",
    "addr:housenumber":"960",
    "addr:postcode":"s9a 1k2",
    "addr:street":"103Rd St",
    "iso:country":"CA",
    "sg:address":"960 103rd St",
    "sg:city":"North Battleford",
    "sg:classifiers":[
        {
            "category":"Recreation",
            "type":"Entertainment"
        }
    ],
    "sg:phone":"+1 306 445 8216",
    "sg:postcode":"S9A 1K2",
    "sg:province":"SK",
    "sg:tags":[
        "center"
    ],
    "wof:name":"Battleford's Indian Metis",
    "wof:placetype":"venue"
},
  "geometry": {"coordinates":[-108.294426,52.771381],"type":"Point"}
}