{
  "type": "Feature",
  "properties": {
    "addr:full":"22865 14 Ave Langley BC V2Z 2W8",
    "addr:housenumber":"22865",
    "addr:postcode":"v2z 2w8",
    "addr:street":"14 Ave",
    "iso:country":"CA",
    "sg:address":"22865 14 Ave",
    "sg:city":"Langley",
    "sg:classifiers":[
        {
            "category":"Wholesale",
            "subcategory":"Durable Goods & Equipment",
            "type":"Manufacturing & Wholesale Goods"
        }
    ],
    "sg:phone":"+1 604 533 9663",
    "sg:postcode":"V2Z 2W8",
    "sg:province":"BC",
    "sg:tags":[
        "sawdust",
        "firewood",
        "shaving"
    ],
    "wof:name":"Woodshed",
    "wof:placetype":"venue"
},
  "geometry": {"coordinates":[-122.59141540500001,49.0277900696],"type":"Point"}
}