{
  "type": "Feature",
  "properties": {
    "addr:full":"225 Parker Rd Scoudouc NB E4P 3P7",
    "addr:housenumber":"225",
    "addr:postcode":"e4p 3p7",
    "addr:street":"Parker Rd",
    "iso:country":"CA",
    "sg:address":"225 Parker Rd",
    "sg:city":"Scoudouc",
    "sg:classifiers":[
        {
            "category":"Manufacturing",
            "subcategory":"Glass & Minerals",
            "type":"Manufacturing & Wholesale Goods"
        }
    ],
    "sg:phone":"+1 506 532 7200",
    "sg:postcode":"E4P 3P7",
    "sg:province":"NB",
    "wof:name":"O I Canada Corp",
    "wof:placetype":"venue"
},
  "geometry": {"coordinates":[-64.58844000000001,46.166683],"type":"Point"}
}