{
  "type": "Feature",
  "properties": {
    "iso:country":"CA",
    "sg:address":"1425 Boul Pitfield",
    "sg:city":"Saint-Laurent",
    "sg:classifiers":[
        {
            "category":"Shopping",
            "subcategory":"Bicycles & Sporting Goods",
            "type":"Retail Goods"
        }
    ],
    "sg:phone":"+1 514 333 8420",
    "sg:postcode":"H4S 1G3",
    "sg:province":"QC",
    "sg:tags":[
        "skating",
        "scaffolding",
        "supply"
    ],
    "wof:name":"Robert Boileau Inc",
    "wof:placetype":"venue"
},
  "geometry": {"coordinates":[-73.7260971069,45.4840087891],"type":"Point"}
}