{
  "type": "Feature",
  "properties": {
    "addr:full":"490 York Rd Guelph ON N1E 6V1",
    "addr:housenumber":"490",
    "addr:postcode":"n1e 6v1",
    "addr:street":"York Rd",
    "iso:country":"CA",
    "sg:address":"490 York Rd",
    "sg:city":"Guelph",
    "sg:classifiers":[
        {
            "category":"Wholesale",
            "subcategory":"Durable Goods & Equipment",
            "type":"Manufacturing & Wholesale Goods"
        }
    ],
    "sg:phone":"+1 519 766 9023",
    "sg:postcode":"N1E 6V1",
    "sg:province":"ON",
    "sg:tags":[
        "magnet",
        "magnetic",
        "devices"
    ],
    "wof:name":"Bunting Magnetics CO",
    "wof:placetype":"venue"
},
  "geometry": {"coordinates":[-80.2247848511,43.5513076782],"type":"Point"}
}