{
  "type": "Feature",
  "properties": {
    "iso:country":"CA",
    "sg:address":"10607 Princess Elizabeth Ave N",
    "sg:city":"Edmonton",
    "sg:classifiers":[
        {
            "category":"Shopping",
            "subcategory":"Bicycles & Sporting Goods",
            "type":"Retail Goods"
        }
    ],
    "sg:phone":"+1 780 477 2427",
    "sg:postcode":"T5G 0Y6",
    "sg:province":"AB",
    "sg:tags":[
        "club",
        "curling"
    ],
    "wof:name":"Avonair Curling Club",
    "wof:placetype":"venue"
},
  "geometry": {"coordinates":[-113.50385300000001,53.56583],"type":"Point"}
}