{
  "type": "Feature",
  "properties": {
    "iso:country":"CA",
    "sg:address":"208 Broadway Ave N",
    "sg:city":"Williams Lake",
    "sg:classifiers":[
        {
            "category":"Wholesale",
            "subcategory":"Machinery & Supplies",
            "type":"Manufacturing & Wholesale Goods"
        }
    ],
    "sg:phone":"+1 250 392 4022",
    "sg:postcode":"V2G 2X9",
    "sg:province":"BC",
    "sg:tags":[
        "farm",
        "equipment"
    ],
    "wof:name":"Lake City Central Equipment",
    "wof:placetype":"venue"
},
  "geometry": {"coordinates":[-122.133399963,52.135055542],"type":"Point"}
}