{
  "type": "Feature",
  "properties": {
    "addr:full":"208 Broadway Ave N Williams Lake BC V2G 2X9",
    "addr:housenumber":"208",
    "addr:postcode":"v2g 2x9",
    "addr:street":"Broadway Ave N",
    "iso:country":"CA",
    "sg:address":"208 Broadway Ave N",
    "sg:city":"Williams Lake",
    "sg:classifiers":[
        {
            "category":"Wholesale",
            "subcategory":"Machinery & Supplies",
            "type":"Manufacturing & Wholesale Goods"
        }
    ],
    "sg:phone":"+1 250 392 4022",
    "sg:postcode":"V2G 2X9",
    "sg:province":"BC",
    "sg:tags":[
        "farm",
        "equipment"
    ],
    "wof:name":"Lake City Central Equipment",
    "wof:placetype":"venue"
},
  "geometry": {"coordinates":[-122.133399963,52.135055542],"type":"Point"}
}