{
  "type": "Feature",
  "properties": {
    "addr:full":"681 Douglas Fir Rd Sparwood BC V0B 2G0",
    "addr:housenumber":"681",
    "addr:postcode":"bc v0b 2g0",
    "addr:street":"Douglas Fir Rd",
    "iso:country":"CA",
    "sg:address":"681 Douglas Fir Rd",
    "sg:city":"Sparwood",
    "sg:classifiers":[
        {
            "category":"Retail",
            "subcategory":"Repair Shop",
            "type":"Services"
        }
    ],
    "sg:phone":"+1 250 425 2818",
    "sg:postcode":"V0B 2G0",
    "sg:province":"BC",
    "sg:tags":[
        "equipment",
        "hydraulic"
    ],
    "wof:name":"Columbia Industries Ltd",
    "wof:placetype":"venue"
},
  "geometry": {"coordinates":[-114.894271851,49.7137641907],"type":"Point"}
}