{
  "type": "Feature",
  "properties": {
    "iso:country":"CA",
    "sg:address":"1110 Finch Ave W #808",
    "sg:city":"North York",
    "sg:classifiers":[
        {
            "category":"Professional",
            "subcategory":"Accounting & Tax Preparation",
            "type":"Services"
        }
    ],
    "sg:phone":"+1 416 665 0396",
    "sg:postcode":"M3J 2T2",
    "sg:province":"ON",
    "sg:tags":[
        "accountant"
    ],
    "wof:name":"Blackstien & Salem",
    "wof:placetype":"venue"
},
  "geometry": {"coordinates":[-79.475906,43.766987],"type":"Point"}
}