{
  "type": "Feature",
  "properties": {
    "addr:full":"691 Logan Ave Winnipeg MB R3E 1M5",
    "addr:housenumber":"691",
    "addr:postcode":"r3e 1m5",
    "addr:street":"Logan Ave",
    "iso:country":"CA",
    "sg:address":"691 Logan Ave",
    "sg:city":"Winnipeg",
    "sg:classifiers":[
        {
            "category":"Building & Trades",
            "subcategory":"Plumbing",
            "type":"Services"
        }
    ],
    "sg:phone":"+1 204 783 7234",
    "sg:postcode":"R3E 1M5",
    "sg:province":"MB",
    "sg:tags":[
        "contractor"
    ],
    "wof:name":"Westwood Mechanical Inc",
    "wof:placetype":"venue"
},
  "geometry": {"coordinates":[-97.1538696289,49.9084739685],"type":"Point"}
}