{
  "type": "Feature",
  "properties": {
    "iso:country":"CA",
    "sg:address":"301 Grenville Ave",
    "sg:city":"Thunder Bay",
    "sg:classifiers":[
        {
            "category":"Food & Beverages",
            "subcategory":"Bakery",
            "type":"Retail Goods"
        }
    ],
    "sg:phone":"+1 807 683 8911",
    "sg:postcode":"P7A 2B2",
    "sg:province":"ON",
    "sg:tags":[
        "baker"
    ],
    "wof:name":"Current River Bakery",
    "wof:placetype":"venue"
},
  "geometry": {"coordinates":[-89.187721,48.460903],"type":"Point"}
}