{
  "type": "Feature",
  "properties": {
    "addr:full":"2145 Jones Ave North Vancouver BC V7M 2W7",
    "addr:housenumber":"2145",
    "addr:postcode":"v7m 2w7",
    "addr:street":"Jones Ave",
    "iso:country":"CA",
    "sg:address":"2145 Jones Ave",
    "sg:city":"North Vancouver",
    "sg:classifiers":[
        {
            "category":"Education",
            "subcategory":"School",
            "type":"Public Place"
        }
    ],
    "sg:phone":"+1 604 903 3555",
    "sg:postcode":"V7M 2W7",
    "sg:province":"BC",
    "wof:name":"Carson Graham Secondary",
    "wof:placetype":"venue"
},
  "geometry": {"coordinates":[-123.081665039,49.3288497925],"type":"Point"}
}