{
  "type": "Feature",
  "properties": {
    "addr:full":"188 Giles Blvd E Windsor ON N9A 4B9",
    "addr:housenumber":"188",
    "addr:postcode":"n9a 4b9",
    "addr:street":"Giles Blvd E",
    "iso:country":"CA",
    "sg:address":"188 Giles Blvd E",
    "sg:city":"Windsor",
    "sg:classifiers":[
        {
            "category":"Health Services",
            "subcategory":"Doctor",
            "type":"Services"
        }
    ],
    "sg:phone":"+1 519 258 9314",
    "sg:postcode":"N9A 4B9",
    "sg:province":"ON",
    "sg:tags":[
        "physician",
        "surgeon"
    ],
    "wof:name":"Leung, Michael MD",
    "wof:placetype":"venue"
},
  "geometry": {"coordinates":[-83.0286331177,42.3066139221],"type":"Point"}
}