{
  "type": "Feature",
  "properties": {
    "addr:full":"211 Bronson Ave Ottawa ON K1R 6H5",
    "addr:housenumber":"211",
    "addr:postcode":"k1r 6h5",
    "addr:street":"Bronson Ave",
    "iso:country":"CA",
    "sg:address":"211 Bronson Ave",
    "sg:city":"Ottawa",
    "sg:classifiers":[
        {
            "category":"Social Services",
            "type":"Services"
        }
    ],
    "sg:phone":"+1 613 233 0574",
    "sg:postcode":"K1R 6H5",
    "sg:province":"ON",
    "sg:tags":[
        "organization",
        "welfare"
    ],
    "wof:name":"House of Hope Administration",
    "wof:placetype":"venue"
},
  "geometry": {"coordinates":[-75.70672607420001,45.4133148193],"type":"Point"}
}