{
  "type": "Feature",
  "properties": {
    "addr:full":"4 Av Addison Scoudouc NB E4P 3N4",
    "addr:postcode":"e4p 3n4",
    "addr:street":"Av Addison",
    "iso:country":"CA",
    "sg:address":"4 Av Addison",
    "sg:city":"Scoudouc",
    "sg:classifiers":[
        {
            "category":"Wholesale",
            "subcategory":"Groceries",
            "type":"Manufacturing & Wholesale Goods"
        }
    ],
    "sg:phone":"+1 506 532 5157",
    "sg:postcode":"E4P 3N4",
    "sg:province":"NB",
    "sg:tags":[
        "beverage"
    ],
    "wof:name":"Cott Beverages Canada",
    "wof:placetype":"venue"
},
  "geometry": {"coordinates":[-64.587456,46.168007],"type":"Point"}
}