{
  "type": "Feature",
  "properties": {
    "addr:full":"1886 St Clair Pky Courtright ON N0N 1H0",
    "addr:housenumber":"1886",
    "addr:postcode":"n0n 1h0",
    "addr:street":"St Clair Pky",
    "iso:country":"CA",
    "sg:address":"1886 St Clair Pky",
    "sg:city":"Courtright",
    "sg:classifiers":[
        {
            "category":"Building & Trades",
            "subcategory":"Electrical",
            "type":"Services"
        }
    ],
    "sg:phone":"+1 519 867 5527",
    "sg:postcode":"N0N 1H0",
    "sg:province":"ON",
    "sg:tags":[
        "contractor",
        "electric",
        "mechanical"
    ],
    "wof:name":"Comstock Canada",
    "wof:placetype":"venue"
},
  "geometry": {"coordinates":[-82.473488,42.7994],"type":"Point"}
}