{
  "type": "Feature",
  "properties": {
    "addr:full":"5700 Langley Bypass Langley BC V3A 8L7",
    "addr:housenumber":"5700",
    "addr:postcode":"v3a 8l7",
    "addr:street":"Langley Bypass",
    "iso:country":"CA",
    "sg:address":"5700 Langley Bypass",
    "sg:city":"Langley",
    "sg:classifiers":[
        {
            "category":"Shopping",
            "subcategory":"Shoes",
            "type":"Retail Goods"
        }
    ],
    "sg:phone":"+1 604 533 5633",
    "sg:postcode":"V3A 8L7",
    "sg:province":"BC",
    "wof:name":"Kintec Footlabs",
    "wof:placetype":"venue"
},
  "geometry": {"coordinates":[-122.64263153100001,49.1059608459],"type":"Point"}
}