{
  "type": "Feature",
  "properties": {
    "iso:country":"CA",
    "sg:address":"4134 3rd St E",
    "sg:city":"Claresholm",
    "sg:classifiers":[
        {
            "category":"Freight",
            "type":"Transportation"
        }
    ],
    "sg:phone":"+1 403 625 4436",
    "sg:postcode":"T0L 0T0",
    "sg:province":"AB",
    "sg:tags":[
        "trucking"
    ],
    "wof:name":"Watt & Stewart Commodities Inc",
    "wof:placetype":"venue"
},
  "geometry": {"coordinates":[-113.57400512700001,50.0154533386],"type":"Point"}
}