{
  "type": "Feature",
  "properties": {
    "addr:full":"431 Queenston St St Catharines ON L2P 2Y3",
    "addr:housenumber":"431",
    "addr:postcode":"l2p 2y3",
    "addr:street":"Queenston St",
    "iso:country":"CA",
    "sg:address":"431 Queenston St",
    "sg:city":"St Catharines",
    "sg:classifiers":[
        {
            "category":"Organizations",
            "subcategory":"Professional Association",
            "type":"Services"
        }
    ],
    "sg:phone":"+1 905 684 0952",
    "sg:postcode":"L2P 2Y3",
    "sg:province":"ON",
    "wof:name":"St Catharines & Dist Retiries",
    "wof:placetype":"venue"
},
  "geometry": {"coordinates":[-79.206169,43.159847],"type":"Point"}
}