{
  "type": "Feature",
  "properties": {
    "addr:full":"286 Green St Flin Flon MB R8A 0H1",
    "addr:housenumber":"286",
    "addr:postcode":"r8a 0h1",
    "addr:street":"Green St",
    "iso:country":"CA",
    "sg:address":"286 Green St",
    "sg:city":"Flin Flon",
    "sg:classifiers":[
        {
            "category":"Recreation",
            "type":"Entertainment"
        }
    ],
    "sg:phone":"+1 204 687 3741",
    "sg:postcode":"R8A 0H1",
    "sg:province":"MB",
    "sg:tags":[
        "hall",
        "auditorium"
    ],
    "wof:name":"Elks Hall",
    "wof:placetype":"venue"
},
  "geometry": {"coordinates":[-101.850891113,54.7712898254],"type":"Point"}
}