{
  "type": "Feature",
  "properties": {
    "iso:country":"CA",
    "sg:address":"4860 Rue Boisclair",
    "sg:city":"Notre-Dame-Du-Mont-Carmel",
    "sg:classifiers":[
        {
            "category":"Personal",
            "subcategory":"Beauty Salon",
            "type":"Services"
        }
    ],
    "sg:phone":"+1 819 537 9143",
    "sg:postcode":"G0X 3J0",
    "sg:province":"QC",
    "wof:name":"Salon DE Coiffure Arabelle",
    "wof:placetype":"venue"
},
  "geometry": {"coordinates":[-69.8557052612,47.4413299561],"type":"Point"}
}