{
  "type": "Feature",
  "properties": {
    "iso:country":"CA",
    "sg:address":"9750 47 Ave NW",
    "sg:city":"Edmonton",
    "sg:classifiers":[
        {
            "category":"Shopping",
            "subcategory":"Bicycles & Sporting Goods",
            "type":"Retail Goods"
        }
    ],
    "sg:phone":"+1 780 439 3099",
    "sg:postcode":"T6E 5P3",
    "sg:province":"AB",
    "wof:name":"Running Room Canada Ltd",
    "wof:placetype":"venue"
},
  "geometry": {"coordinates":[-113.481384277,53.4849967957],"type":"Point"}
}