{
  "type": "Feature",
  "properties": {
    "addr:full":"395 Matheson Blvd E Mississauga ON L4Z 2H2",
    "addr:housenumber":"395",
    "addr:postcode":"l4z 2h2",
    "addr:street":"Matheson Blvd E",
    "iso:country":"CA",
    "sg:address":"395 Matheson Blvd E",
    "sg:city":"Mississauga",
    "sg:classifiers":[
        {
            "category":"Professional",
            "subcategory":"Computer Services",
            "type":"Services"
        }
    ],
    "sg:phone":"+1 905 890 0188",
    "sg:postcode":"L4Z 2H2",
    "sg:province":"ON",
    "sg:tags":[
        "consultant"
    ],
    "wof:name":"Oto Technologies Inc",
    "wof:placetype":"venue"
},
  "geometry": {"coordinates":[-79.65877500000001,43.623886],"type":"Point"}
}