{
  "type": "Feature",
  "properties": {
    "iso:country":"CA",
    "sg:city":"Doyles",
    "sg:classifiers":[
        {
            "category":"Food & Beverages",
            "subcategory":"Groceries & Convenience Stores",
            "type":"Retail Goods"
        }
    ],
    "sg:phone":"+1 709 955 2460",
    "sg:postcode":"A0N 1J0",
    "sg:province":"NL",
    "wof:name":"Mountain Side General Store",
    "wof:placetype":"venue"
},
  "geometry": {"coordinates":[-59.1959114075,47.8246078491],"type":"Point"}
}