{
  "type": "Feature",
  "properties": {
    "addr:full":"Trail BC V1R 4T2",
    "addr:postcode":"bc v1r 4t2",
    "addr:street":"Trail",
    "iso:country":"CA",
    "sg:city":"Trail",
    "sg:classifiers":[
        {
            "category":"Banks & Credit Unions",
            "subcategory":"Investment Brokerage",
            "type":"Services"
        }
    ],
    "sg:phone":"+1 250 368 4500",
    "sg:postcode":"V1R 4T2",
    "sg:province":"BC",
    "wof:name":"Bmo Nesbitt Burns",
    "wof:placetype":"venue"
},
  "geometry": {"coordinates":[-117.707268,49.096714],"type":"Point"}
}