{
  "type": "Feature",
  "properties": {
    "addr:full":"217 Railway Ave Milo AB T0L 1L0",
    "addr:housenumber":"217",
    "addr:postcode":"t0l 1l0",
    "addr:street":"Railway Ave",
    "iso:country":"CA",
    "sg:address":"217 Railway Ave",
    "sg:city":"Milo",
    "sg:classifiers":[
        {
            "category":"Farming",
            "subcategory":"Nursery",
            "type":"Manufacturing & Wholesale Goods"
        }
    ],
    "sg:phone":"+1 403 599 2381",
    "sg:postcode":"T0L 1L0",
    "sg:province":"AB",
    "sg:tags":[
        "greenhouse"
    ],
    "wof:name":"Agricore United",
    "wof:placetype":"venue"
},
  "geometry": {"coordinates":[-112.88236999999999,50.571636],"type":"Point"}
}