{
  "type": "Feature",
  "properties": {
    "addr:full":"9350 Mary St Chilliwack BC V2P 4H1",
    "addr:housenumber":"9350",
    "addr:postcode":"v2p 4h1",
    "addr:street":"Mary St",
    "iso:country":"CA",
    "sg:address":"9350 Mary St",
    "sg:city":"Chilliwack",
    "sg:classifiers":[
        {
            "category":"Organizations",
            "subcategory":"Community Association",
            "type":"Services"
        }
    ],
    "sg:phone":"+1 604 792 2337",
    "sg:postcode":"V2P 4H1",
    "sg:province":"BC",
    "sg:tags":[
        "fraternal"
    ],
    "wof:name":"Royal Canadian Legion",
    "wof:placetype":"venue"
},
  "geometry": {"coordinates":[-121.957305908,49.1718025208],"type":"Point"}
}