{
  "type": "Feature",
  "properties": {
    "addr:full":"1993 Danforth Ave Toronto ON M4C 1J7",
    "addr:housenumber":"1993",
    "addr:postcode":"m4c 1j7",
    "addr:street":"Danforth Ave",
    "iso:country":"CA",
    "sg:address":"1993 Danforth Ave",
    "sg:city":"Toronto",
    "sg:classifiers":[
        {
            "category":"Shopping",
            "subcategory":"Computers & Home Electronics",
            "type":"Retail Goods"
        }
    ],
    "sg:phone":"+1 416 698 0633",
    "sg:postcode":"M4C 1J7",
    "sg:province":"ON",
    "sg:tags":[
        "equipment",
        "video"
    ],
    "wof:name":"Nippon Video",
    "wof:placetype":"venue"
},
  "geometry": {"coordinates":[-79.314629,43.685135],"type":"Point"}
}