{
  "type": "Feature",
  "properties": {
    "addr:full":"6571 Marine Dr West Vancouver BC V7W 2S8",
    "addr:housenumber":"6571",
    "addr:postcode":"v7w 2s8",
    "addr:street":"Marine Dr",
    "iso:country":"CA",
    "sg:address":"6571 Marine Dr",
    "sg:city":"West Vancouver",
    "sg:classifiers":[
        {
            "category":"Building & Trades",
            "subcategory":"Construction",
            "type":"Services"
        }
    ],
    "sg:phone":"+1 604 921 9309",
    "sg:postcode":"V7W 2S8",
    "sg:province":"BC",
    "sg:tags":[
        "general",
        "contractor"
    ],
    "wof:name":"Zurbrugg & Son Constr Ltd",
    "wof:placetype":"venue"
},
  "geometry": {"coordinates":[-123.281639,49.370468],"type":"Point"}
}