{
  "type": "Feature",
  "properties": {
    "addr:full":"103 Rue Principale Saint-Elie QC G0X 2N0",
    "addr:housenumber":"103",
    "addr:postcode":"g0x 2n0",
    "addr:street":"Rue Principale",
    "iso:country":"CA",
    "sg:address":"103 Rue Principale",
    "sg:city":"Saint-Elie",
    "sg:classifiers":[
        {
            "category":"Restaurant",
            "type":"Food & Drink"
        }
    ],
    "sg:phone":"+1 819 221 5622",
    "sg:postcode":"G0X 2N0",
    "sg:province":"QC",
    "wof:name":"Casse-Croute Chez MO-Nik",
    "wof:placetype":"venue"
},
  "geometry": {"coordinates":[-72.96023599999999,46.491856],"type":"Point"}
}