{
  "type": "Feature",
  "properties": {
    "addr:full":"9613 98 St Grande Prairie AB T8V 2E3",
    "addr:housenumber":"9613",
    "addr:postcode":"t8v 2e3",
    "addr:street":"98 St",
    "iso:country":"CA",
    "sg:address":"9613 98 St",
    "sg:city":"Grande Prairie",
    "sg:classifiers":[
        {
            "category":"Professional",
            "subcategory":"Business Services",
            "type":"Services"
        }
    ],
    "sg:phone":"+1 780 532 4352",
    "sg:postcode":"T8V 2E3",
    "sg:province":"AB",
    "sg:tags":[
        "auctioneer"
    ],
    "wof:name":"Swan City Auction",
    "wof:placetype":"venue"
},
  "geometry": {"coordinates":[-118.78480500000001,55.140091],"type":"Point"}
}