{
  "type": "Feature",
  "properties": {
    "addr:full":"191 Mackenzie Rd Inuvik NT X0E 0T0",
    "addr:housenumber":"191",
    "addr:postcode":"x0e 0t0",
    "addr:street":"Mackenzie Rd",
    "iso:country":"CA",
    "sg:address":"191 Mackenzie Rd",
    "sg:city":"Inuvik",
    "sg:classifiers":[
        {
            "category":"Professional",
            "subcategory":"Research",
            "type":"Services"
        }
    ],
    "sg:phone":"+1 867 777 3838",
    "sg:postcode":"X0E 0T0",
    "sg:province":"NT",
    "sg:tags":[
        "development",
        "laboratory"
    ],
    "wof:name":"Inuvik Research Ctr",
    "wof:placetype":"venue"
},
  "geometry": {"coordinates":[-133.734939575,68.3610534668],"type":"Point"}
}