{
  "type": "Feature",
  "properties": {
    "addr:full":"685 Rte Du President-Kennedy Pintendre QC G6C 1E1",
    "addr:housenumber":"685",
    "addr:postcode":"g6c 1e1",
    "addr:street":"Rte Du President-Kennedy Pintendre",
    "iso:country":"CA",
    "sg:address":"685 Rte Du President-Kennedy",
    "sg:city":"Pintendre",
    "sg:classifiers":[
        {
            "category":"Building & Trades",
            "subcategory":"Construction",
            "type":"Services"
        }
    ],
    "sg:phone":"+1 418 835 1451",
    "sg:postcode":"G6C 1E1",
    "sg:province":"QC",
    "sg:tags":[
        "general",
        "contractor"
    ],
    "wof:name":"Construction Dutran Inc",
    "wof:placetype":"venue"
},
  "geometry": {"coordinates":[-71.13022599999999,46.763271],"type":"Point"}
}