{
  "type": "Feature",
  "properties": {
    "iso:country":"CA",
    "sg:address":"111 Riveroaks Dr",
    "sg:city":"Winnipeg",
    "sg:classifiers":[
        {
            "category":"Shopping",
            "subcategory":"Computers & Home Electronics",
            "type":"Retail Goods"
        }
    ],
    "sg:phone":"+1 204 925 6161",
    "sg:postcode":"R3J 1R2",
    "sg:province":"MB",
    "sg:tags":[
        "consultant",
        "software"
    ],
    "wof:name":"Cansys West Ltd",
    "wof:placetype":"venue"
},
  "geometry": {"coordinates":[-97.213959,49.876045],"type":"Point"}
}