{
  "type": "Feature",
  "properties": {
    "addr:full":"89 Geddes St Elora ON N0B 1S0",
    "addr:housenumber":"89",
    "addr:postcode":"n0b 1s0",
    "addr:street":"Geddes St",
    "iso:country":"CA",
    "sg:address":"89 Geddes St",
    "sg:city":"Elora",
    "sg:classifiers":[
        {
            "category":"Food & Beverages",
            "subcategory":"Groceries & Convenience Stores",
            "type":"Retail Goods"
        }
    ],
    "sg:phone":"+1 519 846 5379",
    "sg:postcode":"N0B 1S0",
    "sg:province":"ON",
    "sg:tags":[
        "pharmacy"
    ],
    "wof:name":"Shoppers Drug Mart",
    "wof:placetype":"venue"
},
  "geometry": {"coordinates":[-80.429558,43.682976],"type":"Point"}
}