{
  "type": "Feature",
  "properties": {
    "addr:full":"Parrsboro NS B0M 1S0",
    "addr:postcode":"b0m 1s0",
    "iso:country":"CA",
    "sg:city":"Parrsboro",
    "sg:classifiers":[
        {
            "category":"Banks & Credit Unions",
            "subcategory":"Bank",
            "type":"Services"
        }
    ],
    "sg:phone":"+1 902 254 2051",
    "sg:postcode":"B0M 1S0",
    "sg:province":"NS",
    "wof:name":"Royal Bank Financial Group",
    "wof:placetype":"venue"
},
  "geometry": {"coordinates":[-64.32672100000001,45.403461],"type":"Point"}
}