{
  "type": "Feature",
  "properties": {
    "iso:country":"CA",
    "sg:address":"3800 Boul Casavant O",
    "sg:city":"Saint-Hyacinthe",
    "sg:classifiers":[
        {
            "category":"Professional",
            "subcategory":"Management & Consulting",
            "type":"Services"
        }
    ],
    "sg:phone":"+1 450 774 2502",
    "sg:postcode":"J2S 8E3",
    "sg:province":"QC",
    "sg:tags":[
        "agricultural",
        "consultant",
        "organization",
        "labor"
    ],
    "wof:name":"Progestion Groupe Conseils",
    "wof:placetype":"venue"
},
  "geometry": {"coordinates":[-72.98765563960001,45.6210212708],"type":"Point"}
}