{
  "type": "Feature",
  "properties": {
    "addr:full":"RR 1 Lansdowne ON K0E 1L0",
    "addr:postcode":"k0e 1l0",
    "addr:street":"Rr 1",
    "iso:country":"CA",
    "sg:address":"RR 1",
    "sg:city":"Lansdowne",
    "sg:classifiers":[
        {
            "category":"Building & Trades",
            "subcategory":"Construction",
            "type":"Services"
        }
    ],
    "sg:phone":"+1 613 659 4045",
    "sg:postcode":"K0E 1L0",
    "sg:province":"ON",
    "sg:tags":[
        "insulation",
        "heat",
        "contractor"
    ],
    "wof:name":"J & J Insulating",
    "wof:placetype":"venue"
},
  "geometry": {"coordinates":[-76.018936,44.405739],"type":"Point"}
}