{
  "type": "Feature",
  "properties": {
    "iso:country":"CA",
    "sg:address":"11 Rue Du College",
    "sg:city":"Saint-Andre-Du-Lac-Saint-Jean",
    "sg:classifiers":[
        {
            "category":"Government",
            "subcategory":"Office",
            "type":"Public Place"
        }
    ],
    "sg:phone":"+1 418 349 8167",
    "sg:postcode":"G0W 2K0",
    "sg:province":"QC",
    "sg:tags":[
        "village"
    ],
    "wof:name":"St-Andre Municipalite Ofc",
    "wof:placetype":"venue"
},
  "geometry": {"coordinates":[-70.8897018433,46.9212303162],"type":"Point"}
}