{
  "type": "Feature",
  "properties": {
    "addr:full":"LA Tuque QC G9X 3N6",
    "addr:postcode":"g9x 3n6",
    "iso:country":"CA",
    "sg:city":"LA Tuque",
    "sg:classifiers":[
        {
            "category":"Home & Garden",
            "subcategory":"Building Materials",
            "type":"Retail Goods"
        }
    ],
    "sg:phone":"+1 819 523 4545",
    "sg:postcode":"G9X 3N6",
    "sg:province":"QC",
    "sg:tags":[
        "mixed",
        "concrete"
    ],
    "wof:name":"Beton Mistral Inc",
    "wof:placetype":"venue"
},
  "geometry": {"coordinates":[-72.75456200000001,47.462486],"type":"Point"}
}