{
  "type": "Feature",
  "properties": {
    "iso:country":"CA",
    "sg:address":"2025 Av Saint-Edouard",
    "sg:city":"Plessisville",
    "sg:classifiers":[
        {
            "category":"Organizations",
            "subcategory":"Religious Organization",
            "type":"Services"
        }
    ],
    "sg:phone":"+1 418 362 7252",
    "sg:postcode":"G6L 2L3",
    "sg:province":"QC",
    "sg:tags":[
        "church"
    ],
    "wof:name":"Eglise Notre Dame DE Fatima",
    "wof:placetype":"venue"
},
  "geometry": {"coordinates":[-71.77903747560001,46.2237205505],"type":"Point"}
}