{
  "type": "Feature",
  "properties": {
    "iso:country":"CA",
    "sg:address":"43 Hillcrest Dr",
    "sg:city":"Toronto",
    "sg:classifiers":[
        {
            "category":"Professional",
            "subcategory":"Management & Consulting",
            "type":"Services"
        }
    ],
    "sg:phone":"+1 416 364 7707",
    "sg:postcode":"M6G 2E2",
    "sg:province":"ON",
    "sg:tags":[
        "consultant",
        "business"
    ],
    "wof:name":"Hexagram & CO",
    "wof:placetype":"venue"
},
  "geometry": {"coordinates":[-79.427124,43.675434],"type":"Point"}
}