{
  "type": "Feature",
  "properties": {
    "addr:full":"43 Hillcrest Dr Toronto ON M6G 2E2",
    "addr:housenumber":"43",
    "addr:postcode":"m6g 2e2",
    "addr:street":"Hillcrest Dr",
    "iso:country":"CA",
    "sg:address":"43 Hillcrest Dr",
    "sg:city":"Toronto",
    "sg:classifiers":[
        {
            "category":"Professional",
            "subcategory":"Management & Consulting",
            "type":"Services"
        }
    ],
    "sg:phone":"+1 416 364 7707",
    "sg:postcode":"M6G 2E2",
    "sg:province":"ON",
    "sg:tags":[
        "consultant",
        "business"
    ],
    "wof:name":"Hexagram & CO",
    "wof:placetype":"venue"
},
  "geometry": {"coordinates":[-79.42712400000001,43.675434],"type":"Point"}
}