{
  "type": "Feature",
  "properties": {
    "iso:country":"CA",
    "sg:city":"Manning",
    "sg:classifiers":[
        {
            "category":"Real Estate",
            "subcategory":"Real Estate Operator",
            "type":"Services"
        }
    ],
    "sg:phone":"+1 780 836 3325",
    "sg:postcode":"T0H 2M0",
    "sg:province":"AB",
    "sg:tags":[
        "apartment"
    ],
    "wof:name":"Manning Senior Apartments",
    "wof:placetype":"venue"
},
  "geometry": {"coordinates":[-117.628410339,56.9239768982],"type":"Point"}
}