{
  "type": "Feature",
  "properties": {
    "addr:full":"199 Mac Donald Blvd Alexandria ON K0C 1A0",
    "addr:housenumber":"199",
    "addr:postcode":"k0c 1a0",
    "addr:street":"Mac Donald Blvd",
    "iso:country":"CA",
    "sg:address":"199 Mac Donald Blvd",
    "sg:city":"Alexandria",
    "sg:classifiers":[
        {
            "category":"Personal",
            "subcategory":"Beauty Salon",
            "type":"Services"
        }
    ],
    "sg:phone":"+1 613 525 2296",
    "sg:postcode":"K0C 1A0",
    "sg:province":"ON",
    "wof:name":"Salon Unisex",
    "wof:placetype":"venue"
},
  "geometry": {"coordinates":[-74.644272,45.312939],"type":"Point"}
}