{
  "type": "Feature",
  "properties": {
    "addr:full":"650 Elizabeth Rd Winnipeg MB R2J 1A4",
    "addr:housenumber":"650",
    "addr:postcode":"r2j 1a4",
    "addr:street":"Elizabeth Rd",
    "iso:country":"CA",
    "sg:address":"650 Elizabeth Rd",
    "sg:city":"Winnipeg",
    "sg:classifiers":[
        {
            "category":"Food & Beverages",
            "subcategory":"Groceries & Convenience Stores",
            "type":"Retail Goods"
        }
    ],
    "sg:phone":"+1 204 256 4633",
    "sg:postcode":"R2J 1A4",
    "sg:province":"MB",
    "sg:tags":[
        "grocer"
    ],
    "wof:name":"Hosegood's Iga",
    "wof:placetype":"venue"
},
  "geometry": {"coordinates":[-97.09008,49.870869],"type":"Point"}
}