{
  "type": "Feature",
  "properties": {
    "addr:full":"1740 Ellice Ave Winnipeg MB R3H 0B3",
    "addr:housenumber":"1740",
    "addr:postcode":"r3h 0b3",
    "addr:street":"Ellice Ave",
    "iso:country":"CA",
    "sg:address":"1740 Ellice Ave",
    "sg:city":"Winnipeg",
    "sg:classifiers":[
        {
            "category":"Travel",
            "subcategory":"Hotels & Motels",
            "type":"Entertainment"
        }
    ],
    "sg:phone":"+1 204 775 7131",
    "sg:postcode":"R3H 0B3",
    "sg:province":"MB",
    "wof:name":"Howard Johnson Hotel",
    "wof:placetype":"venue"
},
  "geometry": {"coordinates":[-97.205612,49.894245],"type":"Point"}
}