{
  "type": "Feature",
  "properties": {
    "addr:full":"4110 Boul Industriel Sherbrooke QC J1L 2S6",
    "addr:housenumber":"4110",
    "addr:postcode":"j1l 2s6",
    "addr:street":"Boul Industriel",
    "iso:country":"CA",
    "sg:address":"4110 Boul Industriel",
    "sg:city":"Sherbrooke",
    "sg:classifiers":[
        {
            "category":"Manufacturing",
            "subcategory":"Food",
            "type":"Manufacturing & Wholesale Goods"
        }
    ],
    "sg:phone":"+1 819 563 8544",
    "sg:postcode":"J1L 2S6",
    "sg:province":"QC",
    "sg:tags":[
        "chips"
    ],
    "wof:name":"Frito-Lay Canada",
    "wof:placetype":"venue"
},
  "geometry": {"coordinates":[-71.965683,45.396],"type":"Point"}
}