{
  "type": "Feature",
  "properties": {
    "addr:full":"PO Box 88 Leslieville AB T0M 1H0",
    "addr:housenumber":"po box 88;ab",
    "addr:postcode":"t0m 1h0",
    "addr:street":"Leslieville",
    "iso:country":"CA",
    "sg:address":"PO Box 88",
    "sg:city":"Leslieville",
    "sg:classifiers":[
        {
            "category":"Wholesale",
            "subcategory":"Construction Materials",
            "type":"Manufacturing & Wholesale Goods"
        }
    ],
    "sg:phone":"+1 403 845 8869",
    "sg:postcode":"T0M 1H0",
    "sg:province":"AB",
    "sg:tags":[
        "sand",
        "gravel"
    ],
    "wof:name":"L S Contracting",
    "wof:placetype":"venue"
},
  "geometry": {"coordinates":[-114.601456,52.383816],"type":"Point"}
}