{
  "type": "Feature",
  "properties": {
    "addr:full":"53 Woodstream Blvd Woodbridge ON L4L 7Y8",
    "addr:housenumber":"53",
    "addr:postcode":"l4l 7y8",
    "addr:street":"Woodstream Blvd",
    "iso:country":"CA",
    "sg:address":"53 Woodstream Blvd",
    "sg:city":"Woodbridge",
    "sg:classifiers":[
        {
            "category":"Manufacturing",
            "subcategory":"Metals",
            "type":"Manufacturing & Wholesale Goods"
        }
    ],
    "sg:phone":"+1 905 856 7172",
    "sg:postcode":"L4L 7Y8",
    "sg:province":"ON",
    "sg:tags":[
        "door"
    ],
    "wof:name":"Frasca Glass Ltd",
    "wof:placetype":"venue"
},
  "geometry": {"coordinates":[-79.6044769287,43.7754364014],"type":"Point"}
}