{
  "type": "Feature",
  "properties": {
    "iso:country":"CA",
    "sg:city":"Winnipeg",
    "sg:classifiers":[
        {
            "category":"Food & Beverages",
            "subcategory":"Specialty",
            "type":"Retail Goods"
        }
    ],
    "sg:phone":"+1 204 947 3777",
    "sg:postcode":"R3C 4L8",
    "sg:province":"MB",
    "sg:tags":[
        "tea",
        "coffee"
    ],
    "wof:name":"Human Bean Coffee & Tea",
    "wof:placetype":"venue"
},
  "geometry": {"coordinates":[-97.1312484741,49.8879585266],"type":"Point"}
}