{
  "type": "Feature",
  "properties": {
    "addr:full":"61 Belcourt Ave Barrie ON L4M 4E5",
    "addr:housenumber":"61",
    "addr:postcode":"l4m 4e5",
    "addr:street":"Belcourt Ave",
    "iso:country":"CA",
    "sg:address":"61 Belcourt Ave",
    "sg:city":"Barrie",
    "sg:classifiers":[
        {
            "category":"Building & Trades",
            "subcategory":"Construction",
            "type":"Services"
        }
    ],
    "sg:phone":"+1 705 737 3392",
    "sg:postcode":"L4M 4E5",
    "sg:province":"ON",
    "sg:tags":[
        "contractor"
    ],
    "wof:name":"Dutch Masters Construction Svc",
    "wof:placetype":"venue"
},
  "geometry": {"coordinates":[-79.67306499999999,44.406139],"type":"Point"}
}