{
  "type": "Feature",
  "properties": {
    "iso:country":"CA",
    "sg:city":"Belleville",
    "sg:classifiers":[
        {
            "category":"Wholesale",
            "subcategory":"Machinery & Supplies",
            "type":"Manufacturing & Wholesale Goods"
        }
    ],
    "sg:phone":"+1 613 966 2626",
    "sg:postcode":"K8N 4Z2",
    "sg:province":"ON",
    "sg:tags":[
        "contractor"
    ],
    "wof:name":"Rent All Ctr",
    "wof:placetype":"venue"
},
  "geometry": {"coordinates":[-77.38189697270001,44.1610450745],"type":"Point"}
}