{
  "type": "Feature",
  "properties": {
    "addr:full":"9 Michael Anne Dr Coldwater ON L0K 1E0",
    "addr:housenumber":"9",
    "addr:postcode":"l0k 1e0",
    "addr:street":"Michael Anne Dr",
    "iso:country":"CA",
    "sg:address":"9 Michael Anne Dr",
    "sg:city":"Coldwater",
    "sg:classifiers":[
        {
            "category":"Recreation",
            "type":"Entertainment"
        }
    ],
    "sg:phone":"+1 705 686 3946",
    "sg:postcode":"L0K 1E0",
    "sg:province":"ON",
    "sg:tags":[
        "center"
    ],
    "wof:name":"Coldwater Curling Club",
    "wof:placetype":"venue"
},
  "geometry": {"coordinates":[-79.642296,44.708588],"type":"Point"}
}