{
  "type": "Feature",
  "properties": {
    "addr:full":"505-1975 boul. de Maisonneuve Ouest Montreal H3H1K4",
    "addr:housenumber":"505-1975",
    "addr:postcode":"h3h1k4",
    "addr:street":"Boul. De Maisonneuve Ouest",
    "iso:country":"CA",
    "sg:address":"505-1975 boul. de Maisonneuve Ouest",
    "sg:city":"Montreal",
    "sg:classifiers":[
        {
            "category":"Professional",
            "subcategory":"Computer Services",
            "type":"Services"
        }
    ],
    "sg:postcode":"H3H1K4",
    "sg:tags":[
        "travel",
        "web-2-0",
        "social-netwrok",
        "travel-companion"
    ],
    "sg:website":"http://www.yowtrip.com",
    "wof:name":"YowTRIP",
    "wof:placetype":"venue"
},
  "geometry": {"coordinates":[-73.582542,45.492859],"type":"Point"}
}