{
  "type": "Feature",
  "properties": {
    "addr:full":"249 Av Du Pont N Alma QC G8B 5C4",
    "addr:postcode":"g8b 5c4",
    "addr:street":"249 Av Du Pont N",
    "iso:country":"CA",
    "sg:address":"249 Av Du Pont N",
    "sg:city":"Alma",
    "sg:classifiers":[
        {
            "category":"Autos & Motor Vehicles",
            "subcategory":"Motorcycle Sales",
            "type":"Retail Goods"
        }
    ],
    "sg:phone":"+1 418 668 5167",
    "sg:postcode":"G8B 5C4",
    "sg:province":"QC",
    "sg:tags":[
        "scooter"
    ],
    "wof:name":"Alma Pieces Motoneiges Enr",
    "wof:placetype":"venue"
},
  "geometry": {"coordinates":[-71.640198,48.552887],"type":"Point"}
}