{
  "type": "Feature",
  "properties": {
    "addr:full":"1544 Johnston Rd White Rock BC V4B 3Z7",
    "addr:housenumber":"1544",
    "addr:postcode":"v4b 3z7",
    "addr:street":"Johnston Rd",
    "iso:country":"CA",
    "sg:address":"1544 Johnston Rd",
    "sg:city":"White Rock",
    "sg:classifiers":[
        {
            "category":"Travel",
            "subcategory":"Travel Agent",
            "type":"Entertainment"
        }
    ],
    "sg:phone":"+1 604 538 4499",
    "sg:postcode":"V4B 3Z7",
    "sg:province":"BC",
    "sg:tags":[
        "agency",
        "bureau"
    ],
    "wof:name":"Marlin Travel",
    "wof:placetype":"venue"
},
  "geometry": {"coordinates":[-122.80096399999999,49.030239],"type":"Point"}
}