{
  "type": "Feature",
  "properties": {
    "addr:full":"1 Melanie Dr Brampton ON L6T 4K8",
    "addr:housenumber":"1",
    "addr:postcode":"l6t 4k8",
    "addr:street":"Melanie Dr",
    "iso:country":"CA",
    "sg:address":"1 Melanie Dr",
    "sg:city":"Brampton",
    "sg:classifiers":[
        {
            "category":"Autos & Motor Vehicles",
            "subcategory":"Automobile Sales",
            "type":"Retail Goods"
        }
    ],
    "sg:phone":"+1 905 791 3300",
    "sg:postcode":"L6T 4K8",
    "sg:province":"ON",
    "sg:tags":[
        "car",
        "dealer"
    ],
    "wof:name":"B R Auto Sales",
    "wof:placetype":"venue"
},
  "geometry": {"coordinates":[-79.683334,43.710182],"type":"Point"}
}