{
  "type": "Feature",
  "properties": {
    "addr:full":"900 Keg Lane Paris ON N3L 3E2",
    "addr:housenumber":"900",
    "addr:postcode":"n3l 3e2",
    "addr:street":"Keg Lane",
    "iso:country":"CA",
    "sg:address":"900 Keg Lane",
    "sg:city":"Paris",
    "sg:classifiers":[
        {
            "category":"Building & Trades",
            "subcategory":"Construction",
            "type":"Services"
        }
    ],
    "sg:phone":"+1 519 442 2289",
    "sg:postcode":"N3L 3E2",
    "sg:province":"ON",
    "sg:tags":[
        "paving",
        "contractor"
    ],
    "wof:name":"Brant Asphalt Paving Inc",
    "wof:placetype":"venue"
},
  "geometry": {"coordinates":[-80.41474151609999,43.2014961243],"type":"Point"}
}