{
  "type": "Feature",
  "properties": {
    "addr:full":"107 Queen St E Brampton ON L6W 2A9",
    "addr:housenumber":"107",
    "addr:postcode":"l6w 2a9",
    "addr:street":"Queen St E",
    "iso:country":"CA",
    "sg:address":"107 Queen St E",
    "sg:city":"Brampton",
    "sg:classifiers":[
        {
            "category":"Health Services",
            "subcategory":"Doctor",
            "type":"Services"
        }
    ],
    "sg:phone":"+1 905 866 6657",
    "sg:postcode":"L6W 2A9",
    "sg:province":"ON",
    "sg:tags":[
        "dentist"
    ],
    "wof:name":"Dr Svoboda Dental Implants",
    "wof:placetype":"venue"
},
  "geometry": {"coordinates":[-79.75592041020001,43.6894721985],"type":"Point"}
}