{
  "type": "Feature",
  "properties": {
    "addr:full":"2415 Rue Evangeline Beauport QC G1E 1M7",
    "addr:housenumber":"2415",
    "addr:postcode":"qc g1e 1m7",
    "addr:street":"Rue Evangeline",
    "iso:country":"CA",
    "sg:address":"2415 Rue Evangeline",
    "sg:city":"Beauport",
    "sg:classifiers":[
        {
            "category":"Food & Beverages",
            "subcategory":"Groceries & Convenience Stores",
            "type":"Retail Goods"
        }
    ],
    "sg:phone":"+1 418 663 9102",
    "sg:postcode":"G1E 1M7",
    "sg:province":"QC",
    "sg:tags":[
        "grocer"
    ],
    "wof:name":"Marche Simard Enr",
    "wof:placetype":"venue"
},
  "geometry": {"coordinates":[-71.228554,46.847969],"type":"Point"}
}