{
  "type": "Feature",
  "properties": {
    "iso:country":"CA",
    "sg:address":"34 Court House Sq",
    "sg:city":"Goderich",
    "sg:classifiers":[
        {
            "category":"Shopping",
            "subcategory":"Computers & Home Electronics",
            "type":"Retail Goods"
        }
    ],
    "sg:phone":"+1 519 524 9432",
    "sg:postcode":"N7A 1M4",
    "sg:province":"ON",
    "sg:tags":[
        "television",
        "radio"
    ],
    "wof:name":"Rivett's Audio Video Microwave",
    "wof:placetype":"venue"
},
  "geometry": {"coordinates":[-81.7123031616,43.7433738708],"type":"Point"}
}