{
  "type": "Feature",
  "properties": {
    "addr:full":"529 Rue Gerard-Proulx Deux-Montagnes QC J7R 6G1",
    "addr:housenumber":"529",
    "addr:postcode":"j7r 6g1",
    "addr:street":"Rue Gerard-Proulx",
    "iso:country":"CA",
    "sg:address":"529 Rue Gerard-Proulx",
    "sg:city":"Deux-Montagnes",
    "sg:classifiers":[
        {
            "category":"Building & Trades",
            "subcategory":"Construction",
            "type":"Services"
        }
    ],
    "sg:phone":"+1 450 473 1942",
    "sg:postcode":"J7R 6G1",
    "sg:province":"QC",
    "sg:tags":[
        "repairing",
        "remodeling",
        "contractor"
    ],
    "wof:name":"Constructions Niatruss Inc",
    "wof:placetype":"venue"
},
  "geometry": {"coordinates":[-73.9009170532,45.5556106567],"type":"Point"}
}