{
  "type": "Feature",
  "properties": {
    "addr:full":"1525 Portugal Cove Rd Portugal Cove-St Philips NL A1M 3H3",
    "addr:housenumber":"1525",
    "addr:postcode":"a1m 3h3",
    "addr:street":"Portugal Cove Rd",
    "iso:country":"CA",
    "sg:address":"1525 Portugal Cove Rd",
    "sg:city":"Portugal Cove-St Philips",
    "sg:classifiers":[
        {
            "category":"Building & Trades",
            "subcategory":"Landscaping Services",
            "type":"Services"
        }
    ],
    "sg:phone":"+1 709 895 2800",
    "sg:postcode":"A1M 3H3",
    "sg:province":"NL",
    "sg:tags":[
        "tree",
        "landscape",
        "contractor"
    ],
    "wof:name":"Murray's Horticultural Svc Ltd",
    "wof:placetype":"venue"
},
  "geometry": {"coordinates":[-52.849174,47.628063],"type":"Point"}
}