{
  "type": "Feature",
  "properties": {
    "addr:full":"8553 Franklin Ave Fort Mcmurray AB T9H 2J5",
    "addr:housenumber":"8553",
    "addr:postcode":"t9h 2j5",
    "addr:street":"Franklin Ave",
    "iso:country":"CA",
    "sg:address":"8553 Franklin Ave",
    "sg:city":"Fort Mcmurray",
    "sg:classifiers":[
        {
            "category":"Education",
            "subcategory":"School",
            "type":"Public Place"
        }
    ],
    "sg:phone":"+1 780 799 5772",
    "sg:postcode":"T9H 2J5",
    "sg:province":"AB",
    "wof:name":"Omi School",
    "wof:placetype":"venue"
},
  "geometry": {"coordinates":[-111.359482,56.718845],"type":"Point"}
}