{
  "type": "Feature",
  "properties": {
    "addr:full":"Toronto ON M4P 2Y3",
    "addr:postcode":"m4p 2y3",
    "iso:country":"CA",
    "sg:city":"Toronto",
    "sg:classifiers":[
        {
            "category":"Professional",
            "subcategory":"Employment Agencies",
            "type":"Services"
        }
    ],
    "sg:phone":"+1 416 440 8434",
    "sg:postcode":"M4P 2Y3",
    "sg:province":"ON",
    "sg:tags":[
        "consultant",
        "search",
        "executive"
    ],
    "wof:name":"Morris Group Intl",
    "wof:placetype":"venue"
},
  "geometry": {"coordinates":[-79.3959655762,43.7073974609],"type":"Point"}
}