{
  "type": "Feature",
  "properties": {
    "iso:country":"CA",
    "sg:address":"108 Centre St",
    "sg:city":"Middle Lake",
    "sg:classifiers":[
        {
            "category":"Food & Beverages",
            "subcategory":"Groceries & Convenience Stores",
            "type":"Retail Goods"
        }
    ],
    "sg:phone":"+1 306 367 2136",
    "sg:postcode":"S0K 2X0",
    "sg:province":"SK",
    "sg:tags":[
        "grocer"
    ],
    "wof:name":"Terry's Lucky Dollar",
    "wof:placetype":"venue"
},
  "geometry": {"coordinates":[-105.301537,52.482044],"type":"Point"}
}