{
  "type": "Feature",
  "properties": {
    "addr:full":"Marshfield Charlottetown PE C1A 7L3",
    "addr:postcode":"c1a 7l3",
    "iso:country":"CA",
    "sg:address":"Marshfield",
    "sg:city":"Charlottetown",
    "sg:classifiers":[
        {
            "category":"Wholesale",
            "subcategory":"Hardware",
            "type":"Manufacturing & Wholesale Goods"
        }
    ],
    "sg:phone":"+1 902 629 1231",
    "sg:postcode":"C1A 7L3",
    "sg:province":"PE",
    "sg:tags":[
        "parts",
        "boiler"
    ],
    "wof:name":"Angus Mac Donald Burner",
    "wof:placetype":"venue"
},
  "geometry": {"coordinates":[-63.1243667603,46.2639503479],"type":"Point"}
}