{
  "type": "Feature",
  "properties": {
    "addr:full":"Lloydminster AB T9V 0H9",
    "addr:postcode":"t9v 0h9",
    "iso:country":"CA",
    "sg:city":"Lloydminster",
    "sg:classifiers":[
        {
            "category":"Professional",
            "subcategory":"Accounting & Tax Preparation",
            "type":"Services"
        }
    ],
    "sg:phone":"+1 780 875 5585",
    "sg:postcode":"T9V 0H9",
    "sg:province":"AB",
    "sg:tags":[
        "accountant"
    ],
    "wof:name":"Brannick & Blanchard",
    "wof:placetype":"venue"
},
  "geometry": {"coordinates":[-110.008217,53.28149],"type":"Point"}
}