{
  "type": "Feature",
  "properties": {
    "addr:full":"242209 Range Road 33 Calgary AB T3Z 3J4",
    "addr:housenumber":"242209",
    "addr:postcode":"t3z 3j4",
    "addr:street":"Range Road 33",
    "iso:country":"CA",
    "sg:address":"242209 Range Road 33",
    "sg:city":"Calgary",
    "sg:classifiers":[
        {
            "category":"Retail",
            "subcategory":"Animal Services",
            "type":"Services"
        }
    ],
    "sg:phone":"+1 403 242 2332",
    "sg:postcode":"T3Z 3J4",
    "sg:province":"AB",
    "sg:tags":[
        "pet",
        "boarding",
        "sitting"
    ],
    "wof:name":"R C & M Springbank Kennels Ltd",
    "wof:placetype":"venue"
},
  "geometry": {"coordinates":[-114.063194,51.045074],"type":"Point"}
}