{
  "type": "Feature",
  "properties": {
    "addr:full":"6800 Ch DE LA Cote-DE-Liesse # 109 Saint-Laurent QC H4T 2A7",
    "addr:postcode":"6800;h4t 2a7",
    "addr:street":"Ch De La Cote-De-Liesse # 109",
    "iso:country":"CA",
    "sg:address":"6800 Ch DE LA Cote-DE-Liesse # 109",
    "sg:city":"Saint-Laurent",
    "sg:classifiers":[
        {
            "category":"Professional",
            "subcategory":"Computer Services",
            "type":"Services"
        }
    ],
    "sg:phone":"+1 514 734 4020",
    "sg:postcode":"H4T 2A7",
    "sg:province":"QC",
    "sg:tags":[
        "internet"
    ],
    "wof:name":"Praxinet Inc",
    "wof:placetype":"venue"
},
  "geometry": {"coordinates":[-73.6949539185,45.4828224182],"type":"Point"}
}