{
  "type": "Feature",
  "properties": {
    "iso:country":"CA",
    "sg:address":"9065 Boul Saint-Michel",
    "sg:city":"Montreal",
    "sg:classifiers":[
        {
            "category":"Food & Beverages",
            "subcategory":"Liquor & Beverages",
            "type":"Retail Goods"
        }
    ],
    "sg:phone":"+1 514 328 2971",
    "sg:postcode":"H1Z 3G6",
    "sg:province":"QC",
    "sg:tags":[
        "store"
    ],
    "wof:name":"Saq",
    "wof:placetype":"venue"
},
  "geometry": {"coordinates":[-73.62786865229999,45.572101593],"type":"Point"}
}