{
  "type": "Feature",
  "properties": {
    "iso:country":"CA",
    "sg:address":"11530 97 Ave",
    "sg:city":"Grande Prairie",
    "sg:classifiers":[
        {
            "category":"Wholesale",
            "subcategory":"Machinery & Supplies",
            "type":"Manufacturing & Wholesale Goods"
        }
    ],
    "sg:phone":"+1 780 532 0738",
    "sg:postcode":"T8V 6R8",
    "sg:province":"AB",
    "sg:tags":[
        "equipment",
        "welding"
    ],
    "wof:name":"Praxair",
    "wof:placetype":"venue"
},
  "geometry": {"coordinates":[-118.844353,55.167286],"type":"Point"}
}