{
  "type": "Feature",
  "properties": {
    "addr:full":"PO Box 2554 STN Main Orillia ON L3V 7A3",
    "addr:housenumber":"po",
    "addr:postcode":"l3v 7a3",
    "addr:street":"Box 2554 Stn Main",
    "iso:country":"CA",
    "sg:address":"PO Box 2554 STN Main",
    "sg:city":"Orillia",
    "sg:classifiers":[
        {
            "category":"Building & Trades",
            "subcategory":"Construction",
            "type":"Services"
        }
    ],
    "sg:phone":"+1 705 326 2185",
    "sg:postcode":"L3V 7A3",
    "sg:province":"ON",
    "sg:tags":[
        "general",
        "contractor"
    ],
    "wof:name":"R Payne Construction",
    "wof:placetype":"venue"
},
  "geometry": {"coordinates":[-79.418228,44.60659],"type":"Point"}
}