{
  "type": "Feature",
  "properties": {
    "addr:full":"1425 Boul Rene-Levesque O Montreal QC H3G 1T7",
    "addr:housenumber":"1425",
    "addr:postcode":"h3g 1t7",
    "addr:street":"Boul Rene-Levesque O",
    "iso:country":"CA",
    "sg:address":"1425 Boul Rene-Levesque O",
    "sg:city":"Montreal",
    "sg:classifiers":[
        {
            "category":"Manufacturing",
            "subcategory":"Printing",
            "type":"Manufacturing & Wholesale Goods"
        }
    ],
    "sg:phone":"+1 514 871 1333",
    "sg:postcode":"H3G 1T7",
    "sg:province":"QC",
    "sg:tags":[
        "multimedia"
    ],
    "wof:name":"Integration Nouveaux Medias",
    "wof:placetype":"venue"
},
  "geometry": {"coordinates":[-73.551796,45.519581],"type":"Point"}
}