{
  "type": "Feature",
  "properties": {
    "addr:full":"801 Buxton St Indian Head SK S0G 2K0",
    "addr:housenumber":"801",
    "addr:postcode":"s0g 2k0",
    "addr:street":"Buxton St",
    "iso:country":"CA",
    "sg:address":"801 Buxton St",
    "sg:city":"Indian Head",
    "sg:classifiers":[
        {
            "category":"Organizations",
            "subcategory":"Religious Organization",
            "type":"Services"
        }
    ],
    "sg:phone":"+1 306 695 3838",
    "sg:postcode":"S0G 2K0",
    "sg:province":"SK",
    "sg:tags":[
        "church"
    ],
    "wof:name":"United Church",
    "wof:placetype":"venue"
},
  "geometry": {"coordinates":[-103.67376709,50.5355033875],"type":"Point"}
}