{
  "type": "Feature",
  "properties": {
    "iso:country":"CA",
    "sg:address":"338 Decimal Pl",
    "sg:city":"Scarborough",
    "sg:classifiers":[
        {
            "category":"Building & Trades",
            "subcategory":"Landscaping Services",
            "type":"Services"
        }
    ],
    "sg:phone":"+1 416 724 0942",
    "sg:postcode":"M1C 2V9",
    "sg:province":"ON",
    "sg:tags":[
        "tree"
    ],
    "wof:name":"Twigs & Trunks Prof Tree Care",
    "wof:placetype":"venue"
},
  "geometry": {"coordinates":[-79.138016,43.792984],"type":"Point"}
}