{
  "type": "Feature",
  "properties": {
    "addr:full":"691 Rue Arkust Coaticook QC J1A 2S2",
    "addr:housenumber":"691",
    "addr:postcode":"j1a 2s2",
    "addr:street":"Rue Arkust",
    "iso:country":"CA",
    "sg:address":"691 Rue Arkust",
    "sg:city":"Coaticook",
    "sg:classifiers":[
        {
            "category":"Wholesale",
            "subcategory":"Farm Supplies",
            "type":"Manufacturing & Wholesale Goods"
        }
    ],
    "sg:phone":"+1 819 849 9123",
    "sg:postcode":"J1A 2S2",
    "sg:province":"QC",
    "sg:tags":[
        "fertilizer"
    ],
    "wof:name":"Centre Vegetal Coop-L'Estrie",
    "wof:placetype":"venue"
},
  "geometry": {"coordinates":[-71.804146,45.113262],"type":"Point"}
}