{
  "type": "Feature",
  "properties": {
    "addr:full":"3377 Lake Shore Blvd W Etobicoke ON M8W 1N1",
    "addr:housenumber":"3377",
    "addr:postcode":"m8w 1n1",
    "addr:street":"Lake Shore Blvd W",
    "iso:country":"CA",
    "sg:address":"3377 Lake Shore Blvd W",
    "sg:city":"Etobicoke",
    "sg:classifiers":[
        {
            "category":"Shopping",
            "subcategory":"Clothing, Apparel, & Fashions",
            "type":"Retail Goods"
        }
    ],
    "sg:phone":"+1 416 251 6000",
    "sg:postcode":"M8W 1N1",
    "sg:province":"ON",
    "sg:tags":[
        "item",
        "boutique"
    ],
    "wof:name":"C J's Boutique",
    "wof:placetype":"venue"
},
  "geometry": {"coordinates":[-79.5270996094,43.5957946777],"type":"Point"}
}