{
  "type": "Feature",
  "properties": {
    "addr:full":"250 Robert St Toronto ON M5S 2K7",
    "addr:housenumber":"250",
    "addr:postcode":"m5s 2k7",
    "addr:street":"Robert St",
    "iso:country":"CA",
    "sg:address":"250 Robert St",
    "sg:city":"Toronto",
    "sg:classifiers":[
        {
            "category":"Professional",
            "subcategory":"Accounting & Tax Preparation",
            "type":"Services"
        }
    ],
    "sg:phone":"+1 416 975 9462",
    "sg:postcode":"M5S 2K7",
    "sg:province":"ON",
    "sg:tags":[
        "return",
        "filing"
    ],
    "wof:name":"Baldwin Accounting Svc Inc",
    "wof:placetype":"venue"
},
  "geometry": {"coordinates":[-79.404586792,43.6640434265],"type":"Point"}
}