{
  "type": "Feature",
  "properties": {
    "addr:full":"778 College St Toronto ON M6G 1C6",
    "addr:housenumber":"778",
    "addr:postcode":"m6g 1c6",
    "addr:street":"College St",
    "iso:country":"CA",
    "sg:address":"778 College St",
    "sg:city":"Toronto",
    "sg:classifiers":[
        {
            "category":"Manufacturing",
            "subcategory":"Printing",
            "type":"Manufacturing & Wholesale Goods"
        }
    ],
    "sg:phone":"+1 416 535 1500",
    "sg:postcode":"M6G 1C6",
    "sg:province":"ON",
    "sg:tags":[
        "printer"
    ],
    "wof:name":"Kwik Kopy Printing",
    "wof:placetype":"venue"
},
  "geometry": {"coordinates":[-79.4207077026,43.6549377441],"type":"Point"}
}