{
  "type": "Feature",
  "properties": {
    "addr:full":"Surrey BC V3W 4G2",
    "addr:postcode":"v3w 4g2",
    "iso:country":"CA",
    "sg:city":"Surrey",
    "sg:classifiers":[
        {
            "category":"Freight",
            "type":"Transportation"
        }
    ],
    "sg:phone":"+1 604 502 0240",
    "sg:postcode":"V3W 4G2",
    "sg:province":"BC",
    "sg:tags":[
        "trucking"
    ],
    "wof:name":"Canada Road Carrier Ltd",
    "wof:placetype":"venue"
},
  "geometry": {"coordinates":[-122.867813,49.152489],"type":"Point"}
}