{
  "type": "Feature",
  "properties": {
    "addr:full":"520 Scott St Fort Frances ON P9A 1H4",
    "addr:housenumber":"520",
    "addr:postcode":"p9a 1h4",
    "addr:street":"Scott St",
    "iso:country":"CA",
    "sg:address":"520 Scott St",
    "sg:city":"Fort Frances",
    "sg:classifiers":[
        {
            "category":"Home & Garden",
            "subcategory":"Carpets & Floor Coverings",
            "type":"Retail Goods"
        }
    ],
    "sg:phone":"+1 807 274 2229",
    "sg:postcode":"P9A 1H4",
    "sg:province":"ON",
    "sg:tags":[
        "rug",
        "furniture"
    ],
    "wof:name":"Home Suite Home",
    "wof:placetype":"venue"
},
  "geometry": {"coordinates":[-93.388817,48.610161],"type":"Point"}
}