{
  "type": "Feature",
  "properties": {
    "iso:country":"CA",
    "sg:address":"16 Kennedy Rd S",
    "sg:city":"Brampton",
    "sg:classifiers":[
        {
            "category":"Real Estate",
            "subcategory":"Real Estate Agent",
            "type":"Services"
        }
    ],
    "sg:phone":"+1 905 453 5555",
    "sg:postcode":"L6W 3E1",
    "sg:province":"ON",
    "wof:name":"Caldwell Banker",
    "wof:placetype":"venue"
},
  "geometry": {"coordinates":[-79.748169,43.694847],"type":"Point"}
}