{
  "type": "Feature",
  "properties": {
    "addr:full":"124 Des Beaux Lieux Rte Saint-Eusebe QC G0L 2Y0",
    "addr:housenumber":"124",
    "addr:postcode":"g0l 2y0",
    "addr:street":"Des Beaux Lieux Rte Saint-Eusebe",
    "iso:country":"CA",
    "sg:address":"124 Des Beaux Lieux Rte",
    "sg:city":"Saint-Eusebe",
    "sg:classifiers":[
        {
            "category":"Organizations",
            "subcategory":"Professional Association",
            "type":"Services"
        }
    ],
    "sg:phone":"+1 418 899 2886",
    "sg:postcode":"G0L 2Y0",
    "sg:province":"QC",
    "wof:name":"Association Sportive St-Eusebe",
    "wof:placetype":"venue"
},
  "geometry": {"coordinates":[-68.9056015015,47.538482666],"type":"Point"}
}