{
  "type": "Feature",
  "properties": {
    "addr:full":"Farm Unity SK S0K 4L0",
    "addr:postcode":"s0k 4l0",
    "addr:street":"Unity",
    "iso:country":"CA",
    "sg:address":"Farm",
    "sg:city":"Unity",
    "sg:classifiers":[
        {
            "category":"Building & Trades",
            "subcategory":"Construction",
            "type":"Services"
        }
    ],
    "sg:phone":"+1 306 228 2241",
    "sg:postcode":"S0K 4L0",
    "sg:province":"SK",
    "sg:tags":[
        "pipe",
        "line",
        "contractor"
    ],
    "wof:name":"Plains Marketing Canada Lp",
    "wof:placetype":"venue"
},
  "geometry": {"coordinates":[-109.145545959,52.4371109009],"type":"Point"}
}