{
  "type": "Feature",
  "properties": {
    "iso:country":"CA",
    "sg:address":"3854 Ch DE Tilly",
    "sg:city":"Saint-Antoine-DE-Tilly",
    "sg:classifiers":[
        {
            "category":"Travel",
            "subcategory":"Hotels & Motels",
            "type":"Entertainment"
        }
    ],
    "sg:phone":"+1 418 886 2407",
    "sg:postcode":"G0S 2C0",
    "sg:province":"QC",
    "wof:name":"Manoir DE Tilly",
    "wof:placetype":"venue"
},
  "geometry": {"coordinates":[-71.5717926025,46.6641120911],"type":"Point"}
}