{
  "type": "Feature",
  "properties": {
    "addr:full":"784 Baker Cres Kingston ON K7M 6P6",
    "addr:housenumber":"784",
    "addr:postcode":"k7m 6p6",
    "addr:street":"Baker Cres",
    "iso:country":"CA",
    "sg:address":"784 Baker Cres",
    "sg:city":"Kingston",
    "sg:classifiers":[
        {
            "category":"Retail",
            "subcategory":"Auto Repair",
            "type":"Services"
        }
    ],
    "sg:phone":"+1 613 389 4465",
    "sg:postcode":"K7M 6P6",
    "sg:province":"ON",
    "sg:tags":[
        "repairing",
        "automobile"
    ],
    "wof:name":"Ian Carmichael's Auto Svc",
    "wof:placetype":"venue"
},
  "geometry": {"coordinates":[-76.57624053959999,44.2449760437],"type":"Point"}
}