{
  "type": "Feature",
  "properties": {
    "addr:full":"Winnipeg MB R3P 0N6",
    "addr:postcode":"r3p 0n6",
    "iso:country":"CA",
    "sg:city":"Winnipeg",
    "sg:classifiers":[
        {
            "category":"Social Services",
            "subcategory":"Child Care",
            "type":"Services"
        }
    ],
    "sg:phone":"+1 204 896 6052",
    "sg:postcode":"R3P 0N6",
    "sg:province":"MB",
    "wof:name":"Checkerberry House Inc",
    "wof:placetype":"venue"
},
  "geometry": {"coordinates":[-97.2171554565,49.8664550781],"type":"Point"}
}