{
  "type": "Feature",
  "properties": {
    "addr:full":"PO Box 5 Little Smoky AB T0H 3Z0",
    "addr:housenumber":"po;5",
    "addr:postcode":"t0h 3z0",
    "addr:street":"Box;Little",
    "iso:country":"CA",
    "sg:address":"PO Box 5",
    "sg:city":"Little Smoky",
    "sg:classifiers":[
        {
            "category":"Mining & Drilling",
            "type":"Manufacturing & Wholesale Goods"
        }
    ],
    "sg:phone":"+1 780 524 2477",
    "sg:postcode":"T0H 3Z0",
    "sg:province":"AB",
    "sg:tags":[
        "field",
        "oil"
    ],
    "wof:name":"Leanin' Tree Contracting Ltd",
    "wof:placetype":"venue"
},
  "geometry": {"coordinates":[-117.14457702599999,54.7479133606],"type":"Point"}
}