{
  "type": "Feature",
  "properties": {
    "addr:full":"3731 Moncton St Richmond BC V7E 3A5",
    "addr:housenumber":"3731",
    "addr:postcode":"v7e 3a5",
    "addr:street":"Moncton St",
    "iso:country":"CA",
    "sg:address":"3731 Moncton St",
    "sg:city":"Richmond",
    "sg:classifiers":[
        {
            "category":"Shopping",
            "subcategory":"Bicycles & Sporting Goods",
            "type":"Retail Goods"
        }
    ],
    "sg:phone":"+1 604 274 7238",
    "sg:postcode":"V7E 3A5",
    "sg:province":"BC",
    "sg:tags":[
        "tackle",
        "fishing"
    ],
    "wof:name":"Pacific Net & Twine Ltd",
    "wof:placetype":"venue"
},
  "geometry": {"coordinates":[-123.18337200000001,49.125324],"type":"Point"}
}