{
  "type": "Feature",
  "properties": {
    "addr:full":"RR 4 Box 547 Warkworth ON K0K 3K0",
    "addr:housenumber":"547",
    "addr:postcode":"k0k 3k0",
    "addr:street":"Rr 4 Box",
    "iso:country":"CA",
    "sg:address":"RR 4 Box 547",
    "sg:city":"Warkworth",
    "sg:classifiers":[
        {
            "category":"Building & Trades",
            "subcategory":"Plumbing",
            "type":"Services"
        }
    ],
    "sg:phone":"+1 705 924 3219",
    "sg:postcode":"K0K 3K0",
    "sg:province":"ON",
    "sg:tags":[
        "contractor"
    ],
    "wof:name":"Kirkland Plumbing & Mechanical",
    "wof:placetype":"venue"
},
  "geometry": {"coordinates":[-77.8898468018,44.2007331848],"type":"Point"}
}