{
  "type": "Feature",
  "properties": {
    "addr:full":"953 Topsail Rd Mount Pearl NL A1N 3K1",
    "addr:housenumber":"953",
    "addr:postcode":"a1n 3k1",
    "addr:street":"Topsail Rd",
    "iso:country":"CA",
    "sg:address":"953 Topsail Rd",
    "sg:city":"Mount Pearl",
    "sg:classifiers":[
        {
            "category":"Shopping",
            "subcategory":"Clothing, Apparel, & Fashions",
            "type":"Retail Goods"
        }
    ],
    "sg:phone":"+1 709 368 2255",
    "sg:postcode":"A1N 3K1",
    "sg:province":"NL",
    "sg:tags":[
        "salvage",
        "surplus",
        "merchandise",
        "liquidator"
    ],
    "wof:name":"East Coast Liquidators",
    "wof:placetype":"venue"
},
  "geometry": {"coordinates":[-52.8021774292,47.5233154297],"type":"Point"}
}