{
  "type": "Feature",
  "properties": {
    "addr:full":"5107 43A St Chetwynd BC V0C 1J0",
    "addr:housenumber":"5107",
    "addr:postcode":"bc v0c 1j0",
    "addr:street":"43A St",
    "iso:country":"CA",
    "sg:address":"5107 43A St",
    "sg:city":"Chetwynd",
    "sg:classifiers":[
        {
            "category":"Organizations",
            "subcategory":"Religious Organization",
            "type":"Services"
        }
    ],
    "sg:phone":"+1 250 788 9127",
    "sg:postcode":"V0C 1J0",
    "sg:province":"BC",
    "sg:tags":[
        "church"
    ],
    "wof:name":"Church of Jesus Christ",
    "wof:placetype":"venue"
},
  "geometry": {"coordinates":[-121.60129499999999,55.694546],"type":"Point"}
}