{
  "type": "Feature",
  "properties": {
    "addr:full":"12 Dominic St Bishops Falls NL A0H 1C0",
    "addr:housenumber":"12",
    "addr:postcode":"a0h 1c0",
    "addr:street":"Dominic St",
    "iso:country":"CA",
    "sg:address":"12 Dominic St",
    "sg:city":"Bishops Falls",
    "sg:classifiers":[
        {
            "category":"Manufacturing",
            "subcategory":"Tools & Machinery",
            "type":"Manufacturing & Wholesale Goods"
        }
    ],
    "sg:phone":"+1 709 258 5890",
    "sg:postcode":"A0H 1C0",
    "sg:province":"NL",
    "sg:tags":[
        "box",
        "packer",
        "fish",
        "equipment"
    ],
    "wof:name":"Newfoundland Styro Inc",
    "wof:placetype":"venue"
},
  "geometry": {"coordinates":[-52.96508,47.519077],"type":"Point"}
}