{
  "type": "Feature",
  "properties": {
    "iso:country":"CA",
    "sg:address":"10005 84 St NW",
    "sg:city":"Edmonton",
    "sg:classifiers":[
        {
            "category":"Social Services",
            "subcategory":"Child Care",
            "type":"Services"
        }
    ],
    "sg:phone":"+1 780 469 0219",
    "sg:postcode":"T6A 3P8",
    "sg:province":"AB",
    "sg:tags":[
        "kindergarten",
        "academic",
        "school",
        "montessori"
    ],
    "wof:name":"Childrens Day Out Play School",
    "wof:placetype":"venue"
},
  "geometry": {"coordinates":[-113.456436157,53.5403289795],"type":"Point"}
}