{
  "type": "Feature",
  "properties": {
    "addr:full":"5015 Rue Belanger Montreal QC H1T 1C7",
    "addr:housenumber":"5015",
    "addr:postcode":"h1t 1c7",
    "addr:street":"Rue Belanger",
    "iso:country":"CA",
    "sg:address":"5015 Rue Belanger",
    "sg:city":"Montreal",
    "sg:classifiers":[
        {
            "category":"Health Services",
            "subcategory":"Chiropractor",
            "type":"Services"
        }
    ],
    "sg:phone":"+1 514 729 2505",
    "sg:postcode":"H1T 1C7",
    "sg:province":"QC",
    "wof:name":"Bois, Dominique DC",
    "wof:placetype":"venue"
},
  "geometry": {"coordinates":[-73.579308,45.57439],"type":"Point"}
}