{
  "type": "Feature",
  "properties": {
    "addr:full":"Winnipeg MB R3C 3J7",
    "addr:postcode":"r3c 3j7",
    "iso:country":"CA",
    "sg:city":"Winnipeg",
    "sg:classifiers":[
        {
            "category":"Real Estate",
            "subcategory":"Real Estate Agent",
            "type":"Services"
        }
    ],
    "sg:phone":"+1 204 957 0305",
    "sg:postcode":"R3C 3J7",
    "sg:province":"MB",
    "wof:name":"Flanders Real Estate Ltd",
    "wof:placetype":"venue"
},
  "geometry": {"coordinates":[-97.139633,49.888],"type":"Point"}
}