{
  "type": "Feature",
  "properties": {
    "iso:country":"CA",
    "sg:address":"2303 4 St",
    "sg:city":"Nisku",
    "sg:classifiers":[
        {
            "category":"Manufacturing",
            "subcategory":"Metals",
            "type":"Manufacturing & Wholesale Goods"
        }
    ],
    "sg:phone":"+1 780 955 2633",
    "sg:postcode":"T9E 7W7",
    "sg:province":"AB",
    "sg:tags":[
        "painter"
    ],
    "wof:name":"Frank's Sandblasting & Paint",
    "wof:placetype":"venue"
},
  "geometry": {"coordinates":[-113.537071228,53.3479537964],"type":"Point"}
}