{
  "type": "Feature",
  "properties": {
    "iso:country":"CA",
    "sg:city":"Milton",
    "sg:classifiers":[
        {
            "category":"Health Services",
            "subcategory":"Doctor",
            "type":"Services"
        }
    ],
    "sg:phone":"+1 905 876 2423",
    "sg:postcode":"L9T 3K8",
    "sg:province":"ON",
    "sg:tags":[
        "dentist"
    ],
    "wof:name":"Galli, Guido DDS",
    "wof:placetype":"venue"
},
  "geometry": {"coordinates":[-79.862137,43.509399],"type":"Point"}
}