{
  "type": "Feature",
  "properties": {
    "addr:full":"30 Front St Nanaimo BC V9R 5H7",
    "addr:housenumber":"30",
    "addr:postcode":"v9r 5h7",
    "addr:street":"Front St",
    "iso:country":"CA",
    "sg:address":"30 Front St",
    "sg:city":"Nanaimo",
    "sg:classifiers":[
        {
            "category":"Professional",
            "subcategory":"Lawyer & Legal Services",
            "type":"Services"
        }
    ],
    "sg:phone":"+1 250 754 1234",
    "sg:postcode":"V9R 5H7",
    "sg:province":"BC",
    "sg:tags":[
        "attorney"
    ],
    "wof:name":"Vining, Brett",
    "wof:placetype":"venue"
},
  "geometry": {"coordinates":[-123.93708038299999,49.1692085266],"type":"Point"}
}