{
  "type": "Feature",
  "properties": {
    "iso:country":"CA",
    "sg:address":"104 5th St",
    "sg:city":"100 Mile House",
    "sg:classifiers":[
        {
            "category":"Home & Garden",
            "subcategory":"Building Materials",
            "type":"Retail Goods"
        }
    ],
    "sg:phone":"+1 250 395 3709",
    "sg:postcode":"V0K 2E0",
    "sg:province":"BC",
    "sg:tags":[
        "glass",
        "window",
        "plate"
    ],
    "wof:name":"Mr Otto Glass",
    "wof:placetype":"venue"
},
  "geometry": {"coordinates":[-121.391159058,51.3140258789],"type":"Point"}
}