{
  "type": "Feature",
  "properties": {
    "addr:full":"Arran SK S0A 0B0",
    "addr:postcode":"s0a 0b0",
    "addr:street":"Arran",
    "iso:country":"CA",
    "sg:city":"Arran",
    "sg:classifiers":[
        {
            "category":"Recreation",
            "type":"Entertainment"
        }
    ],
    "sg:phone":"+1 306 595 4717",
    "sg:postcode":"S0A 0B0",
    "sg:province":"SK",
    "sg:tags":[
        "center"
    ],
    "wof:name":"Arran Rec Ctr",
    "wof:placetype":"venue"
},
  "geometry": {"coordinates":[-101.718666,51.885849],"type":"Point"}
}