{
  "type": "Feature",
  "properties": {
    "iso:country":"CA",
    "sg:address":"76 West Main St",
    "sg:city":"Welland",
    "sg:classifiers":[
        {
            "category":"Personal",
            "subcategory":"Beauty Salon",
            "type":"Services"
        }
    ],
    "sg:phone":"+1 905 714 1966",
    "sg:postcode":"L3C 4Z9",
    "sg:province":"ON",
    "wof:name":"Professional Academy of Hair",
    "wof:placetype":"venue"
},
  "geometry": {"coordinates":[-79.25364685060001,42.991519928],"type":"Point"}
}