{
  "type": "Feature",
  "properties": {
    "addr:full":"5800 Boul Thimens Saint-Laurent QC H4S 1S5",
    "addr:housenumber":"5800",
    "addr:postcode":"h4s 1s5",
    "addr:street":"Boul Thimens",
    "iso:country":"CA",
    "sg:address":"5800 Boul Thimens",
    "sg:city":"Saint-Laurent",
    "sg:classifiers":[
        {
            "category":"Freight",
            "type":"Transportation"
        }
    ],
    "sg:phone":"+1 514 227 5800",
    "sg:postcode":"H4S 1S5",
    "sg:province":"QC",
    "sg:tags":[
        "broker",
        "customs"
    ],
    "wof:name":"Alpha Logistiques",
    "wof:placetype":"venue"
},
  "geometry": {"coordinates":[-73.7348480225,45.5007209778],"type":"Point"}
}