{
  "type": "Feature",
  "properties": {
    "addr:full":"359 Boul Des Laurentides Saint-Jerome QC J7Z 4L9",
    "addr:housenumber":"359",
    "addr:postcode":"j7z 4l9",
    "addr:street":"Boul Des Laurentides",
    "iso:country":"CA",
    "sg:address":"359 Boul Des Laurentides",
    "sg:city":"Saint-Jerome",
    "sg:classifiers":[
        {
            "category":"Autos & Motor Vehicles",
            "subcategory":"Auto Supplies",
            "type":"Retail Goods"
        }
    ],
    "sg:phone":"+1 450 432 1484",
    "sg:postcode":"J7Z 4L9",
    "sg:province":"QC",
    "sg:tags":[
        "automobile",
        "parts"
    ],
    "wof:name":"Pieces D'Autos Francoeur Inc",
    "wof:placetype":"venue"
},
  "geometry": {"coordinates":[-73.994995,45.764252],"type":"Point"}
}