{
  "type": "Feature",
  "properties": {
    "addr:full":"Vancouver BC V5Z 2M9",
    "addr:postcode":"v5z 2m9",
    "iso:country":"CA",
    "sg:city":"Vancouver",
    "sg:classifiers":[
        {
            "category":"Food & Beverages",
            "subcategory":"Specialty",
            "type":"Retail Goods"
        }
    ],
    "sg:phone":"+1 604 263 3235",
    "sg:postcode":"V5Z 2M9",
    "sg:province":"BC",
    "sg:tags":[
        "health",
        "vitamin",
        "diet"
    ],
    "wof:name":"Alive Health Ctr Ltd",
    "wof:placetype":"venue"
},
  "geometry": {"coordinates":[-123.117675781,49.2335510254],"type":"Point"}
}