{
  "type": "Feature",
  "properties": {
    "addr:full":"Oxford Tavistock ON N0B 2R0",
    "addr:postcode":"n0b 2r0",
    "iso:country":"CA",
    "sg:address":"Oxford",
    "sg:city":"Tavistock",
    "sg:classifiers":[
        {
            "category":"Organizations",
            "subcategory":"Religious Organization",
            "type":"Services"
        }
    ],
    "sg:phone":"+1 519 655 2413",
    "sg:postcode":"N0B 2R0",
    "sg:province":"ON",
    "sg:tags":[
        "church"
    ],
    "wof:name":"Tavistock Bible Chapel",
    "wof:placetype":"venue"
},
  "geometry": {"coordinates":[-80.839066,43.321098],"type":"Point"}
}