{
  "type": "Feature",
  "properties": {
    "addr:full":"49 Queen St Kapuskasing ON P5N 1H1",
    "addr:housenumber":"49",
    "addr:postcode":"p5n 1h1",
    "addr:street":"Queen St",
    "iso:country":"CA",
    "sg:address":"49 Queen St",
    "sg:city":"Kapuskasing",
    "sg:classifiers":[
        {
            "category":"Professional",
            "subcategory":"Accounting & Tax Preparation",
            "type":"Services"
        }
    ],
    "sg:phone":"+1 705 335 2000",
    "sg:postcode":"P5N 1H1",
    "sg:province":"ON",
    "sg:tags":[
        "return",
        "filing"
    ],
    "wof:name":"H & R Block Canada Inc",
    "wof:placetype":"venue"
},
  "geometry": {"coordinates":[-82.42614,49.418331],"type":"Point"}
}