{
  "type": "Feature",
  "properties": {
    "addr:full":"3 Parklane Way Strathmore AB T1P 1N6",
    "addr:housenumber":"3",
    "addr:postcode":"t1p 1n6",
    "addr:street":"Parklane Way",
    "iso:country":"CA",
    "sg:address":"3 Parklane Way",
    "sg:city":"Strathmore",
    "sg:classifiers":[
        {
            "category":"Social Services",
            "subcategory":"Adult Care",
            "type":"Services"
        }
    ],
    "sg:phone":"+1 403 934 2269",
    "sg:postcode":"T1P 1N6",
    "sg:province":"AB",
    "sg:tags":[
        "senior",
        "housing",
        "citizen"
    ],
    "wof:name":"Lambert Village",
    "wof:placetype":"venue"
},
  "geometry": {"coordinates":[-113.391777039,51.0450897217],"type":"Point"}
}