{
  "type": "Feature",
  "properties": {
    "addr:full":"Kindersley SK S0L 1S2",
    "addr:postcode":"s0l 1s2",
    "addr:street":"Kindersley",
    "iso:country":"CA",
    "sg:city":"Kindersley",
    "sg:classifiers":[
        {
            "category":"Insurance",
            "subcategory":"Insurance Agent",
            "type":"Services"
        }
    ],
    "sg:phone":"+1 306 463 4777",
    "sg:postcode":"S0L 1S2",
    "sg:province":"SK",
    "wof:name":"CO-Operators General Insurance",
    "wof:placetype":"venue"
},
  "geometry": {"coordinates":[-109.148040772,51.475353241],"type":"Point"}
}