{
  "type": "Feature",
  "properties": {
    "addr:full":"Edmonton AB T6J 2S4",
    "addr:postcode":"t6j 2s4",
    "iso:country":"CA",
    "sg:city":"Edmonton",
    "sg:classifiers":[
        {
            "category":"Real Estate",
            "subcategory":"Real Estate Operator",
            "type":"Services"
        }
    ],
    "sg:phone":"+1 780 434 4980",
    "sg:postcode":"T6J 2S4",
    "sg:province":"AB",
    "sg:tags":[
        "apartment"
    ],
    "wof:name":"Southbury House",
    "wof:placetype":"venue"
},
  "geometry": {"coordinates":[-113.50457,53.479263],"type":"Point"}
}