{
  "type": "Feature",
  "properties": {
    "addr:full":"6650 Roblin Blvd Winnipeg MB R3R 2P9",
    "addr:postcode":"6650;r3r 2p9",
    "addr:street":"Roblin Blvd",
    "iso:country":"CA",
    "sg:address":"6650 Roblin Blvd",
    "sg:city":"Winnipeg",
    "sg:classifiers":[
        {
            "category":"Real Estate",
            "subcategory":"Real Estate Operator",
            "type":"Services"
        }
    ],
    "sg:phone":"+1 204 958 4822",
    "sg:postcode":"R3R 2P9",
    "sg:province":"MB",
    "sg:tags":[
        "mall",
        "shopping",
        "center"
    ],
    "wof:name":"Park West Mall",
    "wof:placetype":"venue"
},
  "geometry": {"coordinates":[-97.315269,49.863361],"type":"Point"}
}