{
  "type": "Feature",
  "properties": {
    "addr:full":"340 Boul Des Laurentides Saint-Jerome QC J7Z 4L7",
    "addr:housenumber":"340",
    "addr:postcode":"j7z 4l7",
    "addr:street":"Boul Des Laurentides",
    "iso:country":"CA",
    "sg:address":"340 Boul Des Laurentides",
    "sg:city":"Saint-Jerome",
    "sg:classifiers":[
        {
            "category":"Restaurant",
            "type":"Food & Drink"
        }
    ],
    "sg:phone":"+1 450 438 5888",
    "sg:postcode":"J7Z 4L7",
    "sg:province":"QC",
    "wof:name":"Mikes Restaurant",
    "wof:placetype":"venue"
},
  "geometry": {"coordinates":[-73.99592590330001,45.7644882202],"type":"Point"}
}