{
  "type": "Feature",
  "properties": {
    "addr:full":"Burnaby BC V5A 3H4",
    "addr:postcode":"v5a 3h4",
    "iso:country":"CA",
    "sg:city":"Burnaby",
    "sg:classifiers":[
        {
            "category":"Professional",
            "subcategory":"Engineering",
            "type":"Services"
        }
    ],
    "sg:phone":"+1 604 420 0367",
    "sg:postcode":"V5A 3H4",
    "sg:province":"BC",
    "sg:tags":[
        "engineer"
    ],
    "wof:name":"Coanda Research & Development",
    "wof:placetype":"venue"
},
  "geometry": {"coordinates":[-122.91877700000001,49.252674],"type":"Point"}
}