{
  "type": "Feature",
  "properties": {
    "iso:country":"CA",
    "sg:city":"Burlington",
    "sg:classifiers":[
        {
            "category":"Professional",
            "subcategory":"Research",
            "type":"Services"
        }
    ],
    "sg:phone":"+1 905 681 6899",
    "sg:postcode":"L7L 6A5",
    "sg:province":"ON",
    "sg:tags":[
        "environmental",
        "ecological"
    ],
    "wof:name":"Dja Environmental Consultant",
    "wof:placetype":"venue"
},
  "geometry": {"coordinates":[-79.7696,43.381969],"type":"Point"}
}