{
  "type": "Feature",
  "properties": {
    "addr:full":"125 Roland Michener Dr Kanata ON K2T 1G7",
    "addr:housenumber":"125",
    "addr:postcode":"k2t 1g7",
    "addr:street":"Roland Michener Dr",
    "iso:country":"CA",
    "sg:address":"125 Roland Michener Dr",
    "sg:city":"Kanata",
    "sg:classifiers":[
        {
            "category":"Restaurant",
            "type":"Food & Drink"
        }
    ],
    "sg:phone":"+1 613 271 1041",
    "sg:postcode":"K2T 1G7",
    "sg:province":"ON",
    "wof:name":"Jack Astor's Bar & Grill",
    "wof:placetype":"venue"
},
  "geometry": {"coordinates":[-75.913223,45.30859],"type":"Point"}
}