{
  "type": "Feature",
  "properties": {
    "iso:country":"CA",
    "sg:address":"56 Nelson St",
    "sg:city":"Scarborough",
    "sg:classifiers":[
        {
            "category":"Social Services",
            "subcategory":"Child Care",
            "type":"Services"
        }
    ],
    "sg:phone":"+1 416 431 7704",
    "sg:postcode":"M1J 2V6",
    "sg:province":"ON",
    "wof:name":"Nyad Cedarbrook",
    "wof:placetype":"venue"
},
  "geometry": {"coordinates":[-79.2293930054,43.7470207214],"type":"Point"}
}