{
  "type": "Feature",
  "properties": {
    "addr:full":"161 Hartland Ave Victoria BC V9E 1L7",
    "addr:housenumber":"161",
    "addr:postcode":"v9e 1l7",
    "addr:street":"Hartland Ave",
    "iso:country":"CA",
    "sg:address":"161 Hartland Ave",
    "sg:city":"Victoria",
    "sg:classifiers":[
        {
            "category":"Building & Trades",
            "subcategory":"Landscaping Services",
            "type":"Services"
        }
    ],
    "sg:phone":"+1 250 479 4332",
    "sg:postcode":"V9E 1L7",
    "sg:province":"BC",
    "sg:tags":[
        "lawn",
        "maintenance",
        "grounds"
    ],
    "wof:name":"Weed Man",
    "wof:placetype":"venue"
},
  "geometry": {"coordinates":[-123.36451700000001,48.428314],"type":"Point"}
}