{
  "type": "Feature",
  "properties": {
    "addr:full":"9624 Lakeshore Rd Port Alberni BC V9Y 7L7",
    "addr:housenumber":"9624",
    "addr:postcode":"v9y 7l7",
    "addr:street":"Lakeshore Rd",
    "iso:country":"CA",
    "sg:address":"9624 Lakeshore Rd",
    "sg:city":"Port Alberni",
    "sg:classifiers":[
        {
            "category":"Travel",
            "subcategory":"Hotels & Motels",
            "type":"Entertainment"
        }
    ],
    "sg:phone":"+1 250 723 7533",
    "sg:postcode":"V9Y 7L7",
    "sg:province":"BC",
    "wof:name":"Maples Resort Motel",
    "wof:placetype":"venue"
},
  "geometry": {"coordinates":[-124.807571411,49.2339859009],"type":"Point"}
}