{
  "type": "Feature",
  "properties": {
    "addr:full":"3709 26 Ave NE Calgary AB T1Y 4S3",
    "addr:housenumber":"3709",
    "addr:postcode":"t1y 4s3",
    "addr:street":"26 Ave Ne",
    "iso:country":"CA",
    "sg:address":"3709 26 Ave NE",
    "sg:city":"Calgary",
    "sg:classifiers":[
        {
            "category":"Food & Beverages",
            "subcategory":"Groceries & Convenience Stores",
            "type":"Retail Goods"
        }
    ],
    "sg:phone":"+1 403 285 7117",
    "sg:postcode":"T1Y 4S3",
    "sg:province":"AB",
    "wof:name":"Mac's Convenience Stores Ltd",
    "wof:placetype":"venue"
},
  "geometry": {"coordinates":[-113.980476379,51.0777702332],"type":"Point"}
}