{
  "type": "Feature",
  "properties": {
    "iso:country":"CA",
    "sg:city":"Gloucester",
    "sg:classifiers":[
        {
            "category":"Airline",
            "type":"Transportation"
        }
    ],
    "sg:phone":"+1 613 736 7230",
    "sg:postcode":"K1V 0R4",
    "sg:province":"ON",
    "sg:tags":[
        "company"
    ],
    "wof:name":"Canadian North Cargo",
    "wof:placetype":"venue"
},
  "geometry": {"coordinates":[-75.6520614624,45.3266906738],"type":"Point"}
}