{
  "type": "Feature",
  "properties": {
    "addr:full":"8505 Rue Lafrenaie Saint-Leonard QC H1P 2B3",
    "addr:housenumber":"8505",
    "addr:postcode":"h1p 2b3",
    "addr:street":"Rue Lafrenaie",
    "iso:country":"CA",
    "sg:address":"8505 Rue Lafrenaie",
    "sg:city":"Saint-Leonard",
    "sg:classifiers":[
        {
            "category":"Retail",
            "subcategory":"Auto Repair",
            "type":"Services"
        }
    ],
    "sg:phone":"+1 514 323 5337",
    "sg:postcode":"H1P 2B3",
    "sg:province":"QC",
    "sg:tags":[
        "van",
        "conversion",
        "truck",
        "accessory"
    ],
    "wof:name":"Leer Quebec",
    "wof:placetype":"venue"
},
  "geometry": {"coordinates":[-73.5879440308,45.5991821289],"type":"Point"}
}