{
  "type": "Feature",
  "properties": {
    "iso:country":"CA",
    "sg:address":"90 Bolton St",
    "sg:city":"Bobcaygeon",
    "sg:classifiers":[
        {
            "category":"Shopping",
            "subcategory":"Books",
            "type":"Retail Goods"
        }
    ],
    "sg:phone":"+1 705 738 5800",
    "sg:postcode":"K0M 1A0",
    "sg:province":"ON",
    "sg:tags":[
        "dealer"
    ],
    "wof:name":"Canal Book Store",
    "wof:placetype":"venue"
},
  "geometry": {"coordinates":[-78.54368591310001,44.5359802246],"type":"Point"}
}