{
  "type": "Feature",
  "properties": {
    "addr:full":"30 Macdonell St Guelph ON N1H 2Z3",
    "addr:housenumber":"30",
    "addr:postcode":"n1h 2z3",
    "addr:street":"Macdonell St",
    "iso:country":"CA",
    "sg:address":"30 Macdonell St",
    "sg:city":"Guelph",
    "sg:classifiers":[
        {
            "category":"Shopping",
            "subcategory":"Clothing, Apparel, & Fashions",
            "type":"Retail Goods"
        }
    ],
    "sg:phone":"+1 519 821 9961",
    "sg:postcode":"N1H 2Z3",
    "sg:province":"ON",
    "sg:tags":[
        "tailor"
    ],
    "wof:name":"Giovanni's Tailoring",
    "wof:placetype":"venue"
},
  "geometry": {"coordinates":[-80.249206543,43.5443725586],"type":"Point"}
}