{
  "type": "Feature",
  "properties": {
    "addr:full":"1238 Broadway Ave S Williams Lake BC V2G 1A2",
    "addr:housenumber":"1238",
    "addr:postcode":"v2g 1a2",
    "addr:street":"Broadway Ave S Williams",
    "iso:country":"CA",
    "sg:address":"1238 Broadway Ave S",
    "sg:city":"Williams Lake",
    "sg:classifiers":[
        {
            "category":"Autos & Motor Vehicles",
            "subcategory":"Fuel & Gas Station",
            "type":"Retail Goods"
        }
    ],
    "sg:phone":"+1 250 398 8994",
    "sg:postcode":"V2G 1A2",
    "sg:province":"BC",
    "sg:tags":[
        "oil"
    ],
    "wof:name":"Broadway Shell",
    "wof:placetype":"venue"
},
  "geometry": {"coordinates":[-122.120895386,52.1256828308],"type":"Point"}
}