{
  "type": "Feature",
  "properties": {
    "addr:full":"Hunta ON P0L 1P0",
    "addr:postcode":"p0l 1p0",
    "iso:country":"CA",
    "sg:city":"Hunta",
    "sg:classifiers":[
        {
            "category":"Organizations",
            "subcategory":"Religious Organization",
            "type":"Services"
        }
    ],
    "sg:phone":"+1 705 272 6344",
    "sg:postcode":"P0L 1P0",
    "sg:province":"ON",
    "sg:tags":[
        "church"
    ],
    "wof:name":"Hunta Mennonite Church",
    "wof:placetype":"venue"
},
  "geometry": {"coordinates":[-81.27233099999999,49.102024],"type":"Point"}
}