{
  "type": "Feature",
  "properties": {
    "addr:full":"1053 Ch Du Rivage Saint-Antoine-Sur-Richelieu QC J0L 1R0",
    "addr:postcode":"1053;j0l 1r0",
    "addr:street":"Ch Du Rivage",
    "iso:country":"CA",
    "sg:address":"1053 Ch Du Rivage",
    "sg:city":"Saint-Antoine-Sur-Richelieu",
    "sg:classifiers":[
        {
            "category":"Manufacturing",
            "subcategory":"Chemicals & Compounds",
            "type":"Manufacturing & Wholesale Goods"
        }
    ],
    "sg:phone":"+1 450 787 2544",
    "sg:postcode":"J0L 1R0",
    "sg:province":"QC",
    "sg:tags":[
        "rubber",
        "urethane",
        "product"
    ],
    "wof:name":"Van Specialties",
    "wof:placetype":"venue"
},
  "geometry": {"coordinates":[-73.171204,45.779785],"type":"Point"}
}