{
  "type": "Feature",
  "properties": {
    "addr:full":"405 Aviation Ave Brandon MB R7A 5Y5",
    "addr:housenumber":"405",
    "addr:postcode":"r7a 5y5",
    "addr:street":"Aviation Ave",
    "iso:country":"CA",
    "sg:address":"405 Aviation Ave",
    "sg:city":"Brandon",
    "sg:classifiers":[
        {
            "category":"Autos & Motor Vehicles",
            "subcategory":"Auto Supplies",
            "type":"Retail Goods"
        }
    ],
    "sg:phone":"+1 204 725 4777",
    "sg:postcode":"R7A 5Y5",
    "sg:province":"MB",
    "sg:tags":[
        "equipment",
        "air",
        "conditioning",
        "automobile"
    ],
    "wof:name":"Assiniboia Air Conditioning",
    "wof:placetype":"venue"
},
  "geometry": {"coordinates":[-99.9619522095,49.8476982117],"type":"Point"}
}