{
  "type": "Feature",
  "properties": {
    "addr:full":"1211 Madison Ave Burnaby BC V5C 4Y4",
    "addr:housenumber":"1211",
    "addr:postcode":"v5c 4y4",
    "addr:street":"Madison Ave",
    "iso:country":"CA",
    "sg:address":"1211 Madison Ave",
    "sg:city":"Burnaby",
    "sg:classifiers":[
        {
            "category":"Personal",
            "subcategory":"Beauty Salon",
            "type":"Services"
        }
    ],
    "sg:phone":"+1 604 299 3300",
    "sg:postcode":"V5C 4Y4",
    "sg:province":"BC",
    "wof:name":"Dye Jobs Etc Inc",
    "wof:placetype":"venue"
},
  "geometry": {"coordinates":[-123.009010315,49.2736587524],"type":"Point"}
}