{
  "type": "Feature",
  "properties": {
    "addr:full":"601 Aspen Rd Pickering ON L1V 3S7",
    "addr:housenumber":"601",
    "addr:postcode":"l1v 3s7",
    "addr:street":"Aspen Rd",
    "iso:country":"CA",
    "sg:address":"601 Aspen Rd",
    "sg:city":"Pickering",
    "sg:classifiers":[
        {
            "category":"Home & Garden",
            "subcategory":"Building Materials",
            "type":"Retail Goods"
        }
    ],
    "sg:phone":"+1 905 831 1989",
    "sg:postcode":"L1V 3S7",
    "sg:province":"ON",
    "sg:tags":[
        "windows"
    ],
    "wof:name":"Leatherdale Window Solarium",
    "wof:placetype":"venue"
},
  "geometry": {"coordinates":[-79.117546,43.830631],"type":"Point"}
}