{
  "type": "Feature",
  "properties": {
    "addr:full":"Swan River MB R0L 1Z0",
    "addr:postcode":"r0l 1z0",
    "iso:country":"CA",
    "sg:city":"Swan River",
    "sg:classifiers":[
        {
            "category":"Travel",
            "subcategory":"Travel Agent",
            "type":"Entertainment"
        }
    ],
    "sg:phone":"+1 204 734 2354",
    "sg:postcode":"R0L 1Z0",
    "sg:province":"MB",
    "sg:tags":[
        "agency",
        "bureau"
    ],
    "wof:name":"Swan Valley Travel Svc",
    "wof:placetype":"venue"
},
  "geometry": {"coordinates":[-101.261550903,52.1066894531],"type":"Point"}
}