{
  "type": "Feature",
  "properties": {
    "addr:full":"609 Greer St Wynyard SK S0A 4T0",
    "addr:housenumber":"609",
    "addr:postcode":"s0a 4t0",
    "addr:street":"Greer St",
    "iso:country":"CA",
    "sg:address":"609 Greer St",
    "sg:city":"Wynyard",
    "sg:classifiers":[
        {
            "category":"Government",
            "subcategory":"Fire Station",
            "type":"Public Place"
        }
    ],
    "sg:phone":"+1 ",
    "sg:postcode":"S0A 4T0",
    "sg:province":"SK",
    "sg:tags":[
        "department"
    ],
    "wof:name":"Wynyard Fire Hall Club Room",
    "wof:placetype":"venue"
},
  "geometry": {"coordinates":[-104.180091858,51.7652053833],"type":"Point"}
}