{
  "type": "Feature",
  "properties": {
    "addr:full":"Iqaluit NU X0A 0H0",
    "addr:postcode":"x0a 0h0",
    "iso:country":"CA",
    "sg:city":"Iqaluit",
    "sg:classifiers":[
        {
            "category":"Cinema",
            "subcategory":"Movie Rental",
            "type":"Entertainment"
        }
    ],
    "sg:phone":"+1 867 979 1351",
    "sg:postcode":"X0A 0H0",
    "sg:province":"NU",
    "sg:tags":[
        "leasing",
        "video",
        "disc",
        "tape"
    ],
    "wof:name":"Video Shack",
    "wof:placetype":"venue"
},
  "geometry": {"coordinates":[-68.5190200806,63.7514762878],"type":"Point"}
}