{
  "type": "Feature",
  "properties": {
    "addr:full":"351 Rue Racine Loretteville QC G2B 1E9",
    "addr:housenumber":"351",
    "addr:postcode":"g2b 1e9",
    "addr:street":"Rue Racine",
    "iso:country":"CA",
    "sg:address":"351 Rue Racine",
    "sg:city":"Loretteville",
    "sg:classifiers":[
        {
            "category":"Education",
            "subcategory":"Special Training",
            "type":"Public Place"
        }
    ],
    "sg:phone":"+1 418 847 2297",
    "sg:postcode":"G2B 1E9",
    "sg:province":"QC",
    "sg:tags":[
        "instruction",
        "driving"
    ],
    "wof:name":"Ecole DE Conduite Tecnic",
    "wof:placetype":"venue"
},
  "geometry": {"coordinates":[-71.361214,46.850384],"type":"Point"}
}