{
  "type": "Feature",
  "properties": {
    "addr:full":"Valleyview AB T0H 3N0",
    "addr:postcode":"t0h 3n0",
    "iso:country":"CA",
    "sg:city":"Valleyview",
    "sg:classifiers":[
        {
            "category":"Real Estate",
            "subcategory":"Real Estate Agent",
            "type":"Services"
        }
    ],
    "sg:phone":"+1 780 524 4250",
    "sg:postcode":"T0H 3N0",
    "sg:province":"AB",
    "sg:tags":[
        "management"
    ],
    "wof:name":"Bradick & CO",
    "wof:placetype":"venue"
},
  "geometry": {"coordinates":[-117.280655,55.065693],"type":"Point"}
}