{
  "type": "Feature",
  "properties": {
    "addr:full":"902 Rte Begin Saint-Anselme QC G0R 2N0",
    "addr:housenumber":"902",
    "addr:postcode":"g0r 2n0",
    "addr:street":"Rte Begin",
    "iso:country":"CA",
    "sg:address":"902 Rte Begin",
    "sg:city":"Saint-Anselme",
    "sg:classifiers":[
        {
            "category":"Education",
            "subcategory":"Special Training",
            "type":"Public Place"
        }
    ],
    "sg:phone":"+1 418 885 8176",
    "sg:postcode":"G0R 2N0",
    "sg:province":"QC",
    "sg:tags":[
        "instruction",
        "driving"
    ],
    "wof:name":"Ecole DE Conduite St-Anselme",
    "wof:placetype":"venue"
},
  "geometry": {"coordinates":[-70.962959,46.625954],"type":"Point"}
}