{
  "type": "Feature",
  "properties": {
    "addr:full":"Cambridge ON N1R 7Z1",
    "addr:postcode":"n1r 7z1",
    "iso:country":"CA",
    "sg:city":"Cambridge",
    "sg:classifiers":[
        {
            "category":"Shopping",
            "subcategory":"Florist",
            "type":"Retail Goods"
        }
    ],
    "sg:phone":"+1 519 740 9559",
    "sg:postcode":"N1R 7Z1",
    "sg:province":"ON",
    "wof:name":"Floresta Flowers & Giftware",
    "wof:placetype":"venue"
},
  "geometry": {"coordinates":[-80.29908,43.380329],"type":"Point"}
}