{
  "type": "Feature",
  "properties": {
    "addr:full":"Edmonton AB T6E 5E8",
    "addr:postcode":"t6e 5e8",
    "iso:country":"CA",
    "sg:city":"Edmonton",
    "sg:classifiers":[
        {
            "category":"Personal",
            "type":"Services"
        }
    ],
    "sg:phone":"+1 780 465 9012",
    "sg:postcode":"T6E 5E8",
    "sg:province":"AB",
    "sg:tags":[
        "hair",
        "barber",
        "replacement"
    ],
    "wof:name":"Champion Hair",
    "wof:placetype":"venue"
},
  "geometry": {"coordinates":[-113.45807647700001,53.4882774353],"type":"Point"}
}