{
  "type": "Feature",
  "properties": {
    "iso:country":"CA",
    "sg:city":"Waterloo",
    "sg:classifiers":[
        {
            "category":"Recreation",
            "type":"Entertainment"
        }
    ],
    "sg:phone":"+1 450 539 4764",
    "sg:postcode":"J0E 2N0",
    "sg:province":"QC",
    "sg:tags":[
        "information",
        "arts",
        "auditorium",
        "hall",
        "organization"
    ],
    "wof:name":"Maison DE LA Culture-Waterloo",
    "wof:placetype":"venue"
},
  "geometry": {"coordinates":[-72.5160980225,45.3435668945],"type":"Point"}
}