{
  "type": "Feature",
  "properties": {
    "addr:full":"204 1E Av O Sainte-Anne-Des-Monts QC G4V 1E1",
    "addr:housenumber":"204",
    "addr:postcode":"g4v 1e1",
    "addr:street":"1E Av O",
    "iso:country":"CA",
    "sg:address":"204 1E Av O",
    "sg:city":"Sainte-Anne-Des-Monts",
    "sg:classifiers":[
        {
            "category":"Shopping",
            "subcategory":"Computers & Home Electronics",
            "type":"Retail Goods"
        }
    ],
    "sg:phone":"+1 418 763 5445",
    "sg:postcode":"G4V 1E1",
    "sg:province":"QC",
    "sg:tags":[
        "high",
        "fidelity",
        "stereophonic"
    ],
    "wof:name":"Electro Service J Pelletier",
    "wof:placetype":"venue"
},
  "geometry": {"coordinates":[-66.48639678959999,49.1292152405],"type":"Point"}
}