{
  "type": "Feature",
  "properties": {
    "iso:country":"CA",
    "sg:city":"Sarnia",
    "sg:classifiers":[
        {
            "category":"Education",
            "subcategory":"School",
            "type":"Public Place"
        }
    ],
    "sg:phone":"+1 519 383 6350",
    "sg:postcode":"N7S 6G5",
    "sg:province":"ON",
    "wof:name":"Sylvan Learning Ctr",
    "wof:placetype":"venue"
},
  "geometry": {"coordinates":[-82.35427900000001,42.971111],"type":"Point"}
}