{
  "type": "Feature",
  "properties": {
    "addr:full":"Oakville ON L6L 6M6",
    "addr:postcode":"l6l 6m6",
    "iso:country":"CA",
    "sg:city":"Oakville",
    "sg:classifiers":[
        {
            "category":"Manufacturing",
            "subcategory":"Metals",
            "type":"Manufacturing & Wholesale Goods"
        }
    ],
    "sg:phone":"+1 905 465 3949",
    "sg:postcode":"L6L 6M6",
    "sg:province":"ON",
    "sg:tags":[
        "steel"
    ],
    "wof:name":"Mrg Fabricating",
    "wof:placetype":"venue"
},
  "geometry": {"coordinates":[-79.73299400000001,43.410725],"type":"Point"}
}