{
  "type": "Feature",
  "properties": {
    "addr:full":"Lloydminster SK S9V 0M8",
    "addr:postcode":"s9v 0m8",
    "iso:country":"CA",
    "sg:city":"Lloydminster",
    "sg:classifiers":[
        {
            "category":"Government",
            "subcategory":"Office",
            "type":"Public Place"
        }
    ],
    "sg:phone":"+1 306 825 6420",
    "sg:postcode":"S9V 0M8",
    "sg:province":"SK",
    "wof:name":"Saskatchewan Provincial Court",
    "wof:placetype":"venue"
},
  "geometry": {"coordinates":[-110.001358,53.28334],"type":"Point"}
}