{
  "type": "Feature",
  "properties": {
    "addr:full":"301 Burnham St Peterborough ON K9H 1T5",
    "addr:housenumber":"301",
    "addr:postcode":"k9h 1t5",
    "addr:street":"Burnham St",
    "iso:country":"CA",
    "sg:address":"301 Burnham St",
    "sg:city":"Peterborough",
    "sg:classifiers":[
        {
            "category":"Building & Trades",
            "subcategory":"Construction",
            "type":"Services"
        }
    ],
    "sg:phone":"+1 705 743 3403",
    "sg:postcode":"K9H 1T5",
    "sg:province":"ON",
    "sg:tags":[
        "home",
        "improvement"
    ],
    "wof:name":"Darryl Simmons Eavestroughing",
    "wof:placetype":"venue"
},
  "geometry": {"coordinates":[-78.312027,44.303261],"type":"Point"}
}