{
  "type": "Feature",
  "properties": {
    "iso:country":"CA",
    "sg:address":"5844 Malden Rd",
    "sg:city":"Windsor",
    "sg:classifiers":[
        {
            "category":"Shopping",
            "subcategory":"Shoes",
            "type":"Retail Goods"
        }
    ],
    "sg:phone":"+1 519 967 9119",
    "sg:postcode":"N9H 1S4",
    "sg:province":"ON",
    "wof:name":"Lily's Shoes & Accessories",
    "wof:placetype":"venue"
},
  "geometry": {"coordinates":[-83.060509,42.252739],"type":"Point"}
}