{
  "type": "Feature",
  "properties": {
    "addr:full":"1455 Courtneypark Dr E Mississauga ON L5T 2E3",
    "addr:housenumber":"1455",
    "addr:postcode":"l5t 2e3",
    "addr:street":"Courtneypark Dr E",
    "iso:country":"CA",
    "sg:address":"1455 Courtneypark Dr E",
    "sg:city":"Mississauga",
    "sg:classifiers":[
        {
            "category":"Home & Garden",
            "subcategory":"Building Materials",
            "type":"Retail Goods"
        }
    ],
    "sg:phone":"+1 905 670 5052",
    "sg:postcode":"L5T 2E3",
    "sg:province":"ON",
    "sg:tags":[
        "windows"
    ],
    "wof:name":"Marvin Windows & Doors",
    "wof:placetype":"venue"
},
  "geometry": {"coordinates":[-79.660751,43.661362],"type":"Point"}
}