{
  "type": "Feature",
  "properties": {
    "addr:full":"2939 Lake Shore Blvd W Etobicoke ON M8V 1J5",
    "addr:housenumber":"2939",
    "addr:postcode":"m8v 1j5",
    "addr:street":"Lake Shore Blvd W",
    "iso:country":"CA",
    "sg:address":"2939 Lake Shore Blvd W",
    "sg:city":"Etobicoke",
    "sg:classifiers":[
        {
            "category":"Restaurant",
            "type":"Food & Drink"
        }
    ],
    "sg:phone":"+1 416 252 4371",
    "sg:postcode":"M8V 1J5",
    "sg:province":"ON",
    "sg:tags":[
        "sandwich"
    ],
    "wof:name":"Lakeshore Super Submarine",
    "wof:placetype":"venue"
},
  "geometry": {"coordinates":[-79.50543999999999,43.60062],"type":"Point"}
}