{
  "type": "Feature",
  "properties": {
    "addr:full":"1070 Webbwood Dr Sudbury ON P3C 3B7",
    "addr:housenumber":"1070",
    "addr:postcode":"p3c 3b7",
    "addr:street":"Webbwood Dr",
    "iso:country":"CA",
    "sg:address":"1070 Webbwood Dr",
    "sg:city":"Sudbury",
    "sg:classifiers":[
        {
            "category":"Food & Beverages",
            "subcategory":"Groceries & Convenience Stores",
            "type":"Retail Goods"
        }
    ],
    "sg:phone":"+1 705 673 3606",
    "sg:postcode":"P3C 3B7",
    "sg:province":"ON",
    "sg:tags":[
        "grocer"
    ],
    "wof:name":"National Grocers Cash & Carry",
    "wof:placetype":"venue"
},
  "geometry": {"coordinates":[-81.028885,46.471291],"type":"Point"}
}