{
  "type": "Feature",
  "properties": {
    "addr:full":"121 George St N Peterborough ON K9J 3G3",
    "addr:housenumber":"121",
    "addr:postcode":"k9j 3g3",
    "addr:street":"George St N",
    "iso:country":"CA",
    "sg:address":"121 George St N",
    "sg:city":"Peterborough",
    "sg:classifiers":[
        {
            "category":"Professional",
            "subcategory":"Lawyer & Legal Services",
            "type":"Services"
        }
    ],
    "sg:phone":"+1 705 743 1801",
    "sg:postcode":"K9J 3G3",
    "sg:province":"ON",
    "sg:tags":[
        "attorney"
    ],
    "wof:name":"Moldaver Mc Fadden",
    "wof:placetype":"venue"
},
  "geometry": {"coordinates":[-78.31958770750001,44.2967681885],"type":"Point"}
}