{
  "type": "Feature",
  "properties": {
    "iso:country":"CA",
    "sg:city":"Mississauga",
    "sg:classifiers":[
        {
            "category":"Freight",
            "type":"Transportation"
        }
    ],
    "sg:phone":"+1 905 670 4721",
    "sg:postcode":"L5T 2C1",
    "sg:province":"ON",
    "sg:tags":[
        "trucking"
    ],
    "wof:name":"Garry Mercer Trucking Inc",
    "wof:placetype":"venue"
},
  "geometry": {"coordinates":[-79.6719589233,43.661819458],"type":"Point"}
}