{
  "type": "Feature",
  "properties": {
    "addr:full":"Winnipeg MB R2J 0K4",
    "addr:postcode":"r2j 0k4",
    "iso:country":"CA",
    "sg:city":"Winnipeg",
    "sg:classifiers":[
        {
            "category":"Professional",
            "subcategory":"Advertising",
            "type":"Services"
        }
    ],
    "sg:phone":"+1 204 237 3367",
    "sg:postcode":"R2J 0K4",
    "sg:province":"MB",
    "sg:tags":[
        "installation",
        "display"
    ],
    "wof:name":"Central Display Ltd",
    "wof:placetype":"venue"
},
  "geometry": {"coordinates":[-97.084587,49.881702],"type":"Point"}
}