{
  "type": "Feature",
  "properties": {
    "addr:full":"1406 Bank St Ottawa ON K1H 7Y9",
    "addr:housenumber":"1406",
    "addr:postcode":"k1h 7y9",
    "addr:street":"Bank St",
    "iso:country":"CA",
    "sg:address":"1406 Bank St",
    "sg:city":"Ottawa",
    "sg:classifiers":[
        {
            "category":"Autos & Motor Vehicles",
            "subcategory":"Automobile Sales",
            "type":"Retail Goods"
        }
    ],
    "sg:phone":"+1 613 738 3332",
    "sg:postcode":"K1H 7Y9",
    "sg:province":"ON",
    "sg:tags":[
        "repairing",
        "car"
    ],
    "wof:name":"Adria Auto Ctr Inc",
    "wof:placetype":"venue"
},
  "geometry": {"coordinates":[-75.6717758179,45.3834724426],"type":"Point"}
}