{
  "type": "Feature",
  "properties": {
    "addr:full":"89 Cook St Meaford ON N4L 1N2",
    "addr:housenumber":"89",
    "addr:postcode":"n4l 1n2",
    "addr:street":"Cook St",
    "iso:country":"CA",
    "sg:address":"89 Cook St",
    "sg:city":"Meaford",
    "sg:classifiers":[
        {
            "category":"Health Services",
            "subcategory":"Doctor",
            "type":"Services"
        }
    ],
    "sg:phone":"+1 519 538 5282",
    "sg:postcode":"N4L 1N2",
    "sg:province":"ON",
    "sg:tags":[
        "physician",
        "surgeon"
    ],
    "wof:name":"Collins, Alexandra MD",
    "wof:placetype":"venue"
},
  "geometry": {"coordinates":[-80.59386444090001,44.6066131592],"type":"Point"}
}