{
  "type": "Feature",
  "properties": {
    "addr:full":"990 Laurel Ave Kelowna BC V1Y 7G5",
    "addr:housenumber":"990",
    "addr:postcode":"v1y 7g5",
    "addr:street":"Laurel Ave",
    "iso:country":"CA",
    "sg:address":"990 Laurel Ave",
    "sg:city":"Kelowna",
    "sg:classifiers":[
        {
            "category":"Retail",
            "subcategory":"Auto Repair",
            "type":"Services"
        }
    ],
    "sg:phone":"+1 250 763 2325",
    "sg:postcode":"V1Y 7G5",
    "sg:province":"BC",
    "sg:tags":[
        "repairing",
        "automobile",
        "radiator"
    ],
    "wof:name":"Mangold Radiator",
    "wof:placetype":"venue"
},
  "geometry": {"coordinates":[-119.477287,49.895786],"type":"Point"}
}