{
  "type": "Feature",
  "properties": {
    "addr:full":"127 North St Stirling ON K0K 3E0",
    "addr:housenumber":"127",
    "addr:postcode":"k0k 3e0",
    "addr:street":"North St",
    "iso:country":"CA",
    "sg:address":"127 North St",
    "sg:city":"Stirling",
    "sg:classifiers":[
        {
            "category":"Professional",
            "subcategory":"Accounting & Tax Preparation",
            "type":"Services"
        }
    ],
    "sg:phone":"+1 613 395 5151",
    "sg:postcode":"K0K 3E0",
    "sg:province":"ON",
    "sg:tags":[
        "return",
        "filing"
    ],
    "wof:name":"H & R Block Canada Inc",
    "wof:placetype":"venue"
},
  "geometry": {"coordinates":[-77.5490188599,44.2994384766],"type":"Point"}
}