{
  "type": "Feature",
  "properties": {
    "iso:country":"CA",
    "sg:address":"116 Hampton Rd",
    "sg:city":"Rothesay",
    "sg:classifiers":[
        {
            "category":"Shopping",
            "subcategory":"Gifts & Souvenirs",
            "type":"Retail Goods"
        }
    ],
    "sg:phone":"+1 506 849 3509",
    "sg:postcode":"E2E 2P8",
    "sg:province":"NB",
    "sg:tags":[
        "shop"
    ],
    "wof:name":"Country Treasures",
    "wof:placetype":"venue"
},
  "geometry": {"coordinates":[-65.97960662840001,45.3984832764],"type":"Point"}
}