{
  "type": "Feature",
  "properties": {
    "addr:full":"2289 Broadway W Vancouver BC V6K 2E4",
    "addr:housenumber":"2289",
    "addr:postcode":"v6k 2e4",
    "addr:street":"Broadway W",
    "iso:country":"CA",
    "sg:address":"2289 Broadway W",
    "sg:city":"Vancouver",
    "sg:classifiers":[
        {
            "category":"Travel",
            "subcategory":"Travel Agent",
            "type":"Entertainment"
        }
    ],
    "sg:phone":"+1 604 736 7515",
    "sg:postcode":"V6K 2E4",
    "sg:province":"BC",
    "sg:tags":[
        "agency",
        "bureau"
    ],
    "wof:name":"Crown Travel Svc",
    "wof:placetype":"venue"
},
  "geometry": {"coordinates":[-123.15713501,49.2640571594],"type":"Point"}
}