{
  "type": "Feature",
  "properties": {
    "addr:full":"2960 39 St Red Deer AB T4R 2G2",
    "addr:housenumber":"2960",
    "addr:postcode":"t4r 2g2",
    "addr:street":"39 St",
    "iso:country":"CA",
    "sg:address":"2960 39 St",
    "sg:city":"Red Deer",
    "sg:classifiers":[
        {
            "category":"Organizations",
            "subcategory":"Religious Organization",
            "type":"Services"
        }
    ],
    "sg:phone":"+1 403 343 1511",
    "sg:postcode":"T4R 2G2",
    "sg:province":"AB",
    "sg:tags":[
        "church"
    ],
    "wof:name":"Deer Park Alliance Church",
    "wof:placetype":"venue"
},
  "geometry": {"coordinates":[-113.773788,52.25964],"type":"Point"}
}