{
  "type": "Feature",
  "properties": {
    "addr:full":"The Pas MB R9A 1L5",
    "addr:postcode":"r9a 1l5",
    "iso:country":"CA",
    "sg:city":"The Pas",
    "sg:classifiers":[
        {
            "category":"Professional",
            "subcategory":"Accounting & Tax Preparation",
            "type":"Services"
        }
    ],
    "sg:phone":"+1 204 623 7425",
    "sg:postcode":"R9A 1L5",
    "sg:province":"MB",
    "sg:tags":[
        "accountant"
    ],
    "wof:name":"Group Two Accounting Svc",
    "wof:placetype":"venue"
},
  "geometry": {"coordinates":[-101.253204,53.822933],"type":"Point"}
}