{
  "type": "Feature",
  "properties": {
    "addr:full":"2425 Paulsen Pl Kamloops BC V2B 5A2",
    "addr:housenumber":"2425",
    "addr:postcode":"bc v2b 5a2",
    "addr:street":"Paulsen Pl",
    "iso:country":"CA",
    "sg:address":"2425 Paulsen Pl",
    "sg:city":"Kamloops",
    "sg:classifiers":[
        {
            "category":"Building & Trades",
            "subcategory":"Construction",
            "type":"Services"
        }
    ],
    "sg:phone":"+1 250 554 1522",
    "sg:postcode":"V2B 5A2",
    "sg:province":"BC",
    "sg:tags":[
        "painter"
    ],
    "wof:name":"Interior Sprayways",
    "wof:placetype":"venue"
},
  "geometry": {"coordinates":[-120.41652679400001,50.7095336914],"type":"Point"}
}