{
  "type": "Feature",
  "properties": {
    "iso:country":"CA",
    "sg:address":"RR 1 STN Main",
    "sg:city":"Strathmore",
    "sg:classifiers":[
        {
            "category":"Building & Trades",
            "subcategory":"Landscaping Services",
            "type":"Services"
        }
    ],
    "sg:phone":"+1 403 934 4421",
    "sg:postcode":"T1P 1J6",
    "sg:province":"AB",
    "sg:tags":[
        "landscape",
        "contractor"
    ],
    "wof:name":"Landscape Plus",
    "wof:placetype":"venue"
},
  "geometry": {"coordinates":[-113.400291443,51.041305542],"type":"Point"}
}