{
  "type": "Feature",
  "properties": {
    "addr:full":"323 Rue DE LA Madone Mont-Laurier QC J9L 1R8",
    "addr:housenumber":"323",
    "addr:postcode":"j9l 1r8",
    "addr:street":"Rue De La Madone",
    "iso:country":"CA",
    "sg:address":"323 Rue DE LA Madone",
    "sg:city":"Mont-Laurier",
    "sg:classifiers":[
        {
            "category":"Shopping",
            "subcategory":"Bicycles & Sporting Goods",
            "type":"Retail Goods"
        }
    ],
    "sg:phone":"+1 819 623 6233",
    "sg:postcode":"J9L 1R8",
    "sg:province":"QC",
    "wof:name":"Sport R & J Lauzon Inc",
    "wof:placetype":"venue"
},
  "geometry": {"coordinates":[-75.503975,46.550632],"type":"Point"}
}