{
  "type": "Feature",
  "properties": {
    "addr:full":"Kelowna BC V1Y 7S5",
    "addr:postcode":"v1y 7s5",
    "iso:country":"CA",
    "sg:city":"Kelowna",
    "sg:classifiers":[
        {
            "category":"Professional",
            "subcategory":"Accounting & Tax Preparation",
            "type":"Services"
        }
    ],
    "sg:phone":"+1 250 868 0144",
    "sg:postcode":"V1Y 7S5",
    "sg:province":"BC",
    "sg:tags":[
        "bookkeeping",
        "general"
    ],
    "wof:name":"Bookkeeping Plus",
    "wof:placetype":"venue"
},
  "geometry": {"coordinates":[-119.49776458700001,49.883731842],"type":"Point"}
}