{
  "type": "Feature",
  "properties": {
    "addr:full":"Wilberforce ON K0L 3C0",
    "addr:postcode":"k0l 3c0",
    "iso:country":"CA",
    "sg:city":"Wilberforce",
    "sg:classifiers":[
        {
            "category":"Real Estate",
            "subcategory":"Real Estate Agent",
            "type":"Services"
        }
    ],
    "sg:phone":"+1 705 448 2311",
    "sg:postcode":"K0L 3C0",
    "sg:province":"ON",
    "wof:name":"Bowes & Cocks Ltd",
    "wof:placetype":"venue"
},
  "geometry": {"coordinates":[-78.2234573364,45.0383071899],"type":"Point"}
}