{
  "type": "Feature",
  "properties": {
    "addr:full":"Saint-Jerome QC J7Y 3S9",
    "addr:postcode":"j7y 3s9",
    "iso:country":"CA",
    "sg:city":"Saint-Jerome",
    "sg:classifiers":[
        {
            "category":"Professional",
            "subcategory":"Lawyer & Legal Services",
            "type":"Services"
        }
    ],
    "sg:phone":"+1 450 431 2202",
    "sg:postcode":"J7Y 3S9",
    "sg:province":"QC",
    "sg:tags":[
        "attorney"
    ],
    "wof:name":"Auclair Durocher",
    "wof:placetype":"venue"
},
  "geometry": {"coordinates":[-74.003212,45.780499],"type":"Point"}
}