{
  "type": "Feature",
  "properties": {
    "addr:full":"585 Old Weston Rd York ON M6N 3B2",
    "addr:housenumber":"585",
    "addr:postcode":"m6n 3b2",
    "addr:street":"Old Weston Rd",
    "iso:country":"CA",
    "sg:address":"585 Old Weston Rd",
    "sg:city":"York",
    "sg:classifiers":[
        {
            "category":"Shopping",
            "subcategory":"Computers & Home Electronics",
            "type":"Retail Goods"
        }
    ],
    "sg:phone":"+1 416 656 8126",
    "sg:postcode":"M6N 3B2",
    "sg:province":"ON",
    "sg:tags":[
        "video",
        "disc",
        "tape",
        "equipment"
    ],
    "wof:name":"Richards, N",
    "wof:placetype":"venue"
},
  "geometry": {"coordinates":[-79.4661407471,43.6803207397],"type":"Point"}
}