{
  "type": "Feature",
  "properties": {
    "addr:full":"1545 St Mary's Rd Winnipeg MB R2M 3V8",
    "addr:housenumber":"1545",
    "addr:postcode":"r2m 3v8",
    "addr:street":"St Mary'S Rd",
    "iso:country":"CA",
    "sg:address":"1545 St Mary's Rd",
    "sg:city":"Winnipeg",
    "sg:classifiers":[
        {
            "category":"Banks & Credit Unions",
            "subcategory":"Bank",
            "type":"Services"
        }
    ],
    "sg:phone":"+1 204 944 6803",
    "sg:postcode":"R2M 3V8",
    "sg:province":"MB",
    "wof:name":"Cibc",
    "wof:placetype":"venue"
},
  "geometry": {"coordinates":[-97.11395263670001,49.8249130249],"type":"Point"}
}