{
  "type": "Feature",
  "properties": {
    "addr:full":"270 Bernard Ave Kelowna BC V1Y 6N4",
    "addr:housenumber":"270",
    "addr:postcode":"v1y 6n4",
    "addr:street":"Bernard Ave",
    "iso:country":"CA",
    "sg:address":"270 Bernard Ave",
    "sg:city":"Kelowna",
    "sg:classifiers":[
        {
            "category":"Restaurant",
            "type":"Food & Drink"
        }
    ],
    "sg:phone":"+1 250 860 1846",
    "sg:postcode":"V1Y 6N4",
    "sg:province":"BC",
    "wof:name":"Saigon Restaurant",
    "wof:placetype":"venue"
},
  "geometry": {"coordinates":[-119.49736799999999,49.88644],"type":"Point"}
}