{
  "type": "Feature",
  "properties": {
    "addr:full":"Bell Island NL A0A 4H0",
    "addr:postcode":"a0a 4h0",
    "iso:country":"CA",
    "sg:city":"Bell Island",
    "sg:classifiers":[
        {
            "category":"Social Services",
            "type":"Services"
        }
    ],
    "sg:phone":"+1 709 488 2699",
    "sg:postcode":"A0A 4H0",
    "sg:province":"NL",
    "sg:tags":[
        "organization",
        "welfare"
    ],
    "wof:name":"Bell Island Brighter Futures",
    "wof:placetype":"venue"
},
  "geometry": {"coordinates":[-52.94907,47.622978],"type":"Point"}
}