{
  "type": "Feature",
  "properties": {
    "addr:full":"Main St Little Smoky AB T0H 3Z0",
    "addr:postcode":"t0h 3z0",
    "addr:street":"Main St",
    "iso:country":"CA",
    "sg:address":"Main St",
    "sg:city":"Little Smoky",
    "sg:classifiers":[
        {
            "category":"Autos & Motor Vehicles",
            "subcategory":"Fuel & Gas Station",
            "type":"Retail Goods"
        }
    ],
    "sg:phone":"+1 780 524 2467",
    "sg:postcode":"T0H 3Z0",
    "sg:province":"AB",
    "sg:tags":[
        "oil"
    ],
    "wof:name":"Little Smoky Svc",
    "wof:placetype":"venue"
},
  "geometry": {"coordinates":[-117.14457702599999,54.7479133606],"type":"Point"}
}