{
  "type": "Feature",
  "properties": {
    "iso:country":"CA",
    "sg:address":"70 King St E",
    "sg:city":"Stoney Creek",
    "sg:classifiers":[
        {
            "category":"Health Services",
            "subcategory":"Chiropractor",
            "type":"Services"
        }
    ],
    "sg:phone":"+1 905 664 8662",
    "sg:postcode":"L8G 1K2",
    "sg:province":"ON",
    "wof:name":"Assessment Centre",
    "wof:placetype":"venue"
},
  "geometry": {"coordinates":[-79.753944397,43.2163543701],"type":"Point"}
}