{
  "type": "Feature",
  "properties": {
    "addr:full":"Richmond BC V6V 2N4",
    "addr:postcode":"v6v 2n4",
    "iso:country":"CA",
    "sg:city":"Richmond",
    "sg:classifiers":[
        {
            "category":"Health Services",
            "subcategory":"Medical Lab",
            "type":"Services"
        }
    ],
    "sg:phone":"+1 604 821 1038",
    "sg:postcode":"V6V 2N4",
    "sg:province":"BC",
    "sg:tags":[
        "laboratory"
    ],
    "wof:name":"Vetech Dental Laboratories Ltd",
    "wof:placetype":"venue"
},
  "geometry": {"coordinates":[-123.08474,49.191437],"type":"Point"}
}