{
  "type": "Feature",
  "properties": {
    "iso:country":"CA",
    "sg:city":"Richmond",
    "sg:classifiers":[
        {
            "category":"Insurance",
            "subcategory":"Insurance Agent",
            "type":"Services"
        }
    ],
    "sg:phone":"+1 604 270 2518",
    "sg:postcode":"V6X 2C4",
    "sg:province":"BC",
    "wof:name":"Sussex Insurance",
    "wof:placetype":"venue"
},
  "geometry": {"coordinates":[-123.13684082,49.1796112061],"type":"Point"}
}