{
  "type": "Feature",
  "properties": {
    "addr:full":"201 Main St SW Falher AB T0H 1M0",
    "addr:housenumber":"201",
    "addr:postcode":"t0h 1m0",
    "addr:street":"Main St Sw",
    "iso:country":"CA",
    "sg:address":"201 Main St SW",
    "sg:city":"Falher",
    "sg:classifiers":[
        {
            "category":"Shopping",
            "subcategory":"Department Store",
            "type":"Retail Goods"
        }
    ],
    "sg:phone":"+1 780 837 2541",
    "sg:postcode":"T0H 1M0",
    "sg:province":"AB",
    "wof:name":"Mac Leods True Value",
    "wof:placetype":"venue"
},
  "geometry": {"coordinates":[-117.202011,55.735279],"type":"Point"}
}