{
  "type": "Feature",
  "properties": {
    "addr:full":"3911 48 Ave Camrose AB T4V 2Z1",
    "addr:housenumber":"3911",
    "addr:postcode":"t4v 2z1",
    "addr:street":"48 Ave",
    "iso:country":"CA",
    "sg:address":"3911 48 Ave",
    "sg:city":"Camrose",
    "sg:classifiers":[
        {
            "category":"Real Estate",
            "subcategory":"Real Estate Agent",
            "type":"Services"
        }
    ],
    "sg:phone":"+1 780 679 2271",
    "sg:postcode":"T4V 2Z1",
    "sg:province":"AB",
    "wof:name":"Swan City Realty",
    "wof:placetype":"venue"
},
  "geometry": {"coordinates":[-112.80742600000001,53.017799],"type":"Point"}
}