{
  "type": "Feature",
  "properties": {
    "addr:full":"1717 Boucher Lake Rd Moberly Lake BC V0C 1X0",
    "addr:housenumber":"1717",
    "addr:postcode":"bc v0c 1x0",
    "addr:street":"Boucher Lake Rd",
    "iso:country":"CA",
    "sg:address":"1717 Boucher Lake Rd",
    "sg:city":"Moberly Lake",
    "sg:classifiers":[
        {
            "category":"Organizations",
            "subcategory":"Community Association",
            "type":"Services"
        }
    ],
    "sg:phone":"+1 250 788 3955",
    "sg:postcode":"V0C 1X0",
    "sg:province":"BC",
    "sg:tags":[
        "native"
    ],
    "wof:name":"Saulteau First Nations Admin",
    "wof:placetype":"venue"
},
  "geometry": {"coordinates":[-121.72489166299999,55.8353881836],"type":"Point"}
}