{
  "type": "Feature",
  "properties": {
    "addr:full":"186 Worthington St W North Bay ON P1B 3B2",
    "addr:housenumber":"186",
    "addr:postcode":"p1b 3b2",
    "addr:street":"Worthington St W",
    "iso:country":"CA",
    "sg:address":"186 Worthington St W",
    "sg:city":"North Bay",
    "sg:classifiers":[
        {
            "category":"Food & Beverages",
            "subcategory":"Liquor & Beverages",
            "type":"Retail Goods"
        }
    ],
    "sg:phone":"+1 705 494 4065",
    "sg:postcode":"P1B 3B2",
    "sg:province":"ON",
    "sg:tags":[
        "store"
    ],
    "wof:name":"Liquor Control Board of Ont",
    "wof:placetype":"venue"
},
  "geometry": {"coordinates":[-79.4629364014,46.3128471375],"type":"Point"}
}