{
  "type": "Feature",
  "properties": {
    "addr:full":"Beaumont AB T4X 1E5",
    "addr:postcode":"t4x 1e5",
    "iso:country":"CA",
    "sg:city":"Beaumont",
    "sg:classifiers":[
        {
            "category":"Building & Trades",
            "subcategory":"Equipment Rental",
            "type":"Services"
        }
    ],
    "sg:phone":"+1 780 929 5001",
    "sg:postcode":"T4X 1E5",
    "sg:province":"AB",
    "sg:tags":[
        "player",
        "recorder",
        "video"
    ],
    "wof:name":"Canadian Video Megastore",
    "wof:placetype":"venue"
},
  "geometry": {"coordinates":[-113.416611,53.354485],"type":"Point"}
}