{
  "type": "Feature",
  "properties": {
    "addr:full":"6560 Hastings St Burnaby BC V5B 1S2",
    "addr:housenumber":"6560",
    "addr:postcode":"bc v5b 1s2",
    "addr:street":"Hastings St",
    "iso:country":"CA",
    "sg:address":"6560 Hastings St",
    "sg:city":"Burnaby",
    "sg:classifiers":[
        {
            "category":"Restaurant",
            "type":"Food & Drink"
        }
    ],
    "sg:phone":"+1 604 294 1971",
    "sg:postcode":"V5B 1S2",
    "sg:province":"BC",
    "wof:name":"Oriental Kitchen",
    "wof:placetype":"venue"
},
  "geometry": {"coordinates":[-122.967911,49.280132],"type":"Point"}
}