{
  "type": "Feature",
  "properties": {
    "addr:full":"103 Main St Erin ON N0B 1T0",
    "addr:housenumber":"103",
    "addr:postcode":"n0b 1t0",
    "addr:street":"Main St",
    "iso:country":"CA",
    "sg:address":"103 Main St",
    "sg:city":"Erin",
    "sg:classifiers":[
        {
            "category":"Organizations",
            "subcategory":"Religious Organization",
            "type":"Services"
        }
    ],
    "sg:phone":"+1 519 833 2033",
    "sg:postcode":"N0B 1T0",
    "sg:province":"ON",
    "sg:tags":[
        "church"
    ],
    "wof:name":"Erin Full Gospel Fellowship",
    "wof:placetype":"venue"
},
  "geometry": {"coordinates":[-80.063728,43.770287],"type":"Point"}
}