{
  "type": "Feature",
  "properties": {
    "iso:country":"CA",
    "sg:address":"233 Garrison Rd",
    "sg:city":"Fort Erie",
    "sg:classifiers":[
        {
            "category":"Shopping",
            "subcategory":"Computers & Home Electronics",
            "type":"Retail Goods"
        }
    ],
    "sg:phone":"+1 905 871 3499",
    "sg:postcode":"L2A 1M8",
    "sg:province":"ON",
    "sg:tags":[
        "equipment",
        "dealer"
    ],
    "wof:name":"Softcom",
    "wof:placetype":"venue"
},
  "geometry": {"coordinates":[-78.922996521,42.9057388306],"type":"Point"}
}