{
  "type": "Feature",
  "properties": {
    "iso:country":"CA",
    "sg:address":"35 Anne St S # 4",
    "sg:city":"Barrie",
    "sg:classifiers":[
        {
            "category":"Professional",
            "subcategory":"Accounting & Tax Preparation",
            "type":"Services"
        }
    ],
    "sg:phone":"+1 705 726 7261",
    "sg:postcode":"L4N 2C7",
    "sg:province":"ON",
    "sg:tags":[
        "bookkeeping",
        "general"
    ],
    "wof:name":"Business Services Unlimited",
    "wof:placetype":"venue"
},
  "geometry": {"coordinates":[-79.703339,44.380512],"type":"Point"}
}