{
  "type": "Feature",
  "properties": {
    "addr:full":"5103 50 Ave Wetaskiwin AB T9A 0S5",
    "addr:housenumber":"5103",
    "addr:postcode":"t9a 0s5",
    "addr:street":"50 Ave",
    "iso:country":"CA",
    "sg:address":"5103 50 Ave",
    "sg:city":"Wetaskiwin",
    "sg:classifiers":[
        {
            "category":"Restaurant",
            "type":"Food & Drink"
        }
    ],
    "sg:phone":"+1 780 352 7711",
    "sg:postcode":"T9A 0S5",
    "sg:province":"AB",
    "wof:name":"Grandma Lee's Bakery & Eating",
    "wof:placetype":"venue"
},
  "geometry": {"coordinates":[-113.37648799999999,52.969715],"type":"Point"}
}