{
  "type": "Feature",
  "properties": {
    "addr:full":"1105 Wellington Rd # 120 London ON N6E 1V4",
    "addr:housenumber":"1105",
    "addr:postcode":"n6e 1v4",
    "addr:street":"Wellington Rd # 120",
    "iso:country":"CA",
    "sg:address":"1105 Wellington Rd # 120",
    "sg:city":"London",
    "sg:classifiers":[
        {
            "category":"Shopping",
            "subcategory":"Clothing, Apparel, & Fashions",
            "type":"Retail Goods"
        }
    ],
    "sg:phone":"+1 519 685 6408",
    "sg:postcode":"N6E 1V4",
    "sg:province":"ON",
    "sg:tags":[
        "item",
        "boutique"
    ],
    "wof:name":"Ardene",
    "wof:placetype":"venue"
},
  "geometry": {"coordinates":[-81.221642,42.931622],"type":"Point"}
}