{
  "type": "Feature",
  "properties": {
    "addr:full":"120 Kaskie St Atikokan ON P0T 1C0",
    "addr:housenumber":"120",
    "addr:postcode":"p0t 1c0",
    "addr:street":"Kaskie St",
    "iso:country":"CA",
    "sg:address":"120 Kaskie St",
    "sg:city":"Atikokan",
    "sg:classifiers":[
        {
            "category":"Retail",
            "subcategory":"Auto Repair",
            "type":"Services"
        }
    ],
    "sg:phone":"+1 807 597 2443",
    "sg:postcode":"P0T 1C0",
    "sg:province":"ON",
    "sg:tags":[
        "body",
        "automobile",
        "painting"
    ],
    "wof:name":"Ravenwood",
    "wof:placetype":"venue"
},
  "geometry": {"coordinates":[-91.592873,48.759232],"type":"Point"}
}