{
  "type": "Feature",
  "properties": {
    "iso:country":"CA",
    "sg:address":"50 Rue Boulet",
    "sg:city":"Princeville",
    "sg:classifiers":[
        {
            "category":"Education",
            "subcategory":"School",
            "type":"Public Place"
        }
    ],
    "sg:phone":"+1 819 364 7859",
    "sg:postcode":"G6L 4M1",
    "sg:province":"QC",
    "wof:name":"Ecole-Entreprise",
    "wof:placetype":"venue"
},
  "geometry": {"coordinates":[-71.8889465332,46.1546440125],"type":"Point"}
}