{
  "type": "Feature",
  "properties": {
    "addr:full":"22474 Adelaide Rd Mount Brydges ON N0L 1W0",
    "addr:housenumber":"22474",
    "addr:postcode":"n0l 1w0",
    "addr:street":"Adelaide Rd",
    "iso:country":"CA",
    "sg:address":"22474 Adelaide Rd",
    "sg:city":"Mount Brydges",
    "sg:classifiers":[
        {
            "category":"Shopping",
            "subcategory":"Pharmacy",
            "type":"Retail Goods"
        }
    ],
    "sg:phone":"+1 519 264 2000",
    "sg:postcode":"N0L 1W0",
    "sg:province":"ON",
    "wof:name":"Cds Pharmacy",
    "wof:placetype":"venue"
},
  "geometry": {"coordinates":[-81.492912,42.908314],"type":"Point"}
}