{
  "type": "Feature",
  "properties": {
    "addr:full":"123 Empire Ave St. John's NL A1C 3G1",
    "addr:housenumber":"123",
    "addr:postcode":"a1c 3g1",
    "addr:street":"Empire Ave",
    "iso:country":"CA",
    "sg:address":"123 Empire Ave",
    "sg:city":"St. John's",
    "sg:classifiers":[
        {
            "category":"Retail",
            "subcategory":"Auto Repair",
            "type":"Services"
        }
    ],
    "sg:phone":"+1 709 579 0117",
    "sg:postcode":"A1C 3G1",
    "sg:province":"NL",
    "sg:tags":[
        "repairing",
        "automobile"
    ],
    "wof:name":"Murphys All Car Svc",
    "wof:placetype":"venue"
},
  "geometry": {"coordinates":[-52.7167167664,47.5714645386],"type":"Point"}
}