{
  "type": "Feature",
  "properties": {
    "iso:country":"CA",
    "sg:address":"8170 Cummington Sq W",
    "sg:city":"Niagara Falls",
    "sg:classifiers":[
        {
            "category":"Banks & Credit Unions",
            "subcategory":"Bank",
            "type":"Services"
        }
    ],
    "sg:phone":"+1 905 295 4301",
    "sg:postcode":"L2G 6V9",
    "sg:province":"ON",
    "wof:name":"Royal Bank Financial Group",
    "wof:placetype":"venue"
},
  "geometry": {"coordinates":[-79.0511932373,43.0588493347],"type":"Point"}
}