{
  "type": "Feature",
  "properties": {
    "addr:full":"Mississauga ON L5A 3N7",
    "addr:postcode":"l5a 3n7",
    "iso:country":"CA",
    "sg:city":"Mississauga",
    "sg:classifiers":[
        {
            "category":"Health Services",
            "subcategory":"Doctor",
            "type":"Services"
        }
    ],
    "sg:phone":"+1 905 276 8900",
    "sg:postcode":"L5A 3N7",
    "sg:province":"ON",
    "sg:tags":[
        "physician",
        "surgeon"
    ],
    "wof:name":"Martina Rabzel Medical Office",
    "wof:placetype":"venue"
},
  "geometry": {"coordinates":[-79.5924072266,43.5766181946],"type":"Point"}
}