{
  "type": "Feature",
  "properties": {
    "addr:full":"279 Burnhamthorpe Rd Etobicoke ON M9B 1Z6",
    "addr:housenumber":"279",
    "addr:postcode":"m9b 1z6",
    "addr:street":"Burnhamthorpe Rd",
    "iso:country":"CA",
    "sg:address":"279 Burnhamthorpe Rd",
    "sg:city":"Etobicoke",
    "sg:classifiers":[
        {
            "category":"Shopping",
            "subcategory":"Books",
            "type":"Retail Goods"
        }
    ],
    "sg:phone":"+1 416 233 3929",
    "sg:postcode":"M9B 1Z6",
    "sg:province":"ON",
    "sg:tags":[
        "organization",
        "religious"
    ],
    "wof:name":"Information Swedenborg Inc",
    "wof:placetype":"venue"
},
  "geometry": {"coordinates":[-79.545074,43.649807],"type":"Point"}
}