{
  "type": "Feature",
  "properties": {
    "addr:full":"9520 Trans Canada Hwy Whycocomagh NS B0E 3M0",
    "addr:housenumber":"9520",
    "addr:postcode":"b0e 3m0",
    "addr:street":"Trans Canada Hwy",
    "iso:country":"CA",
    "sg:address":"9520 Trans Canada Hwy",
    "sg:city":"Whycocomagh",
    "sg:classifiers":[
        {
            "category":"Food & Beverages",
            "subcategory":"Groceries & Convenience Stores",
            "type":"Retail Goods"
        }
    ],
    "sg:phone":"+1 902 756 2000",
    "sg:postcode":"B0E 3M0",
    "sg:province":"NS",
    "sg:tags":[
        "liquor"
    ],
    "wof:name":"Whycocomagh CO-OP Ltd",
    "wof:placetype":"venue"
},
  "geometry": {"coordinates":[-61.117718,45.974667],"type":"Point"}
}