{
  "type": "Feature",
  "properties": {
    "iso:country":"CA",
    "sg:address":"365 Rue Sainte-Catherine E",
    "sg:city":"Montreal",
    "sg:classifiers":[
        {
            "category":"Shopping",
            "subcategory":"Tobacco",
            "type":"Retail Goods"
        }
    ],
    "sg:phone":"+1 514 842 9753",
    "sg:postcode":"H2X 3X2",
    "sg:province":"QC",
    "sg:tags":[
        "cigarette",
        "cigar",
        "dealer"
    ],
    "wof:name":"Tabagie Quam",
    "wof:placetype":"venue"
},
  "geometry": {"coordinates":[-73.560913,45.513428],"type":"Point"}
}