{
  "type": "Feature",
  "properties": {
    "addr:full":"Edmonton AB T6E 6M9",
    "addr:postcode":"t6e 6m9",
    "iso:country":"CA",
    "sg:city":"Edmonton",
    "sg:classifiers":[
        {
            "category":"Wholesale",
            "subcategory":"Machinery & Supplies",
            "type":"Manufacturing & Wholesale Goods"
        }
    ],
    "sg:phone":"+1 780 465 2131",
    "sg:postcode":"T6E 6M9",
    "sg:province":"AB",
    "sg:tags":[
        "salon",
        "beauty"
    ],
    "wof:name":"Star Nail",
    "wof:placetype":"venue"
},
  "geometry": {"coordinates":[-113.479767,53.476334],"type":"Point"}
}