{
  "type": "Feature",
  "properties": {
    "addr:full":"3704 Roblin Blvd Winnipeg MB R3R 0E1",
    "addr:housenumber":"3704",
    "addr:postcode":"r3r 0e1",
    "addr:street":"Roblin Blvd",
    "iso:country":"CA",
    "sg:address":"3704 Roblin Blvd",
    "sg:city":"Winnipeg",
    "sg:classifiers":[
        {
            "category":"Personal",
            "subcategory":"Beauty Salon",
            "type":"Services"
        }
    ],
    "sg:phone":"+1 204 832 6163",
    "sg:postcode":"R3R 0E1",
    "sg:province":"MB",
    "wof:name":"Divita Hair Design",
    "wof:placetype":"venue"
},
  "geometry": {"coordinates":[-97.261742,49.867985],"type":"Point"}
}