{
  "type": "Feature",
  "properties": {
    "addr:full":"3600 Lakeridge Rd Pickering ON L1X 2X2",
    "addr:housenumber":"3600",
    "addr:postcode":"l1x 2x2",
    "addr:street":"Lakeridge Rd",
    "iso:country":"CA",
    "sg:address":"3600 Lakeridge Rd",
    "sg:city":"Pickering",
    "sg:classifiers":[
        {
            "category":"Social Services",
            "subcategory":"Child Care",
            "type":"Services"
        }
    ],
    "sg:phone":"+1 905 655 4990",
    "sg:postcode":"L1X 2X2",
    "sg:province":"ON",
    "wof:name":"My School",
    "wof:placetype":"venue"
},
  "geometry": {"coordinates":[-79.0163116455,43.9383544922],"type":"Point"}
}