{
  "type": "Feature",
  "properties": {
    "addr:full":"18178 102 Ave NW Edmonton AB T5S 1S7",
    "addr:housenumber":"18178",
    "addr:postcode":"t5s 1s7",
    "addr:street":"102 Ave Nw",
    "iso:country":"CA",
    "sg:address":"18178 102 Ave NW",
    "sg:city":"Edmonton",
    "sg:classifiers":[
        {
            "category":"Organizations",
            "subcategory":"Non-profit Organization",
            "type":"Services"
        }
    ],
    "sg:phone":"+1 780 444 9366",
    "sg:postcode":"T5S 1S7",
    "sg:province":"AB",
    "sg:tags":[
        "charitable",
        "institution"
    ],
    "wof:name":"Treaty 8 First Nations-Alberta",
    "wof:placetype":"venue"
},
  "geometry": {"coordinates":[-113.63568100000001,53.543537],"type":"Point"}
}