{
  "type": "Feature",
  "properties": {
    "addr:full":"3230 Rue Sartelon Saint-Laurent QC H4R 1E3",
    "addr:housenumber":"3230",
    "addr:postcode":"h4r 1e3",
    "addr:street":"Rue Sartelon",
    "iso:country":"CA",
    "sg:address":"3230 Rue Sartelon",
    "sg:city":"Saint-Laurent",
    "sg:classifiers":[
        {
            "category":"Building & Trades",
            "subcategory":"Plumbing",
            "type":"Services"
        }
    ],
    "sg:phone":"+1 514 337 6206",
    "sg:postcode":"H4R 1E3",
    "sg:province":"QC",
    "sg:tags":[
        "contractor"
    ],
    "wof:name":"Decarie Plumbing & Heating Ltd",
    "wof:placetype":"venue"
},
  "geometry": {"coordinates":[-73.7330322266,45.5132484436],"type":"Point"}
}