{
  "type": "Feature",
  "properties": {
    "addr:full":"1295 Roberts Creek Rd Roberts Creek BC V0N 2W2",
    "addr:housenumber":"1295",
    "addr:postcode":"v0n 2w2",
    "addr:street":"Roberts Creek Rd",
    "iso:country":"CA",
    "sg:address":"1295 Roberts Creek Rd",
    "sg:city":"Roberts Creek",
    "sg:classifiers":[
        {
            "category":"Professional",
            "subcategory":"Detective & Security Services",
            "type":"Services"
        }
    ],
    "sg:phone":"+1 604 885 5615",
    "sg:postcode":"V0N 2W2",
    "sg:province":"BC",
    "sg:tags":[
        "control",
        "traffic"
    ],
    "wof:name":"All-Clear Traffic Control",
    "wof:placetype":"venue"
},
  "geometry": {"coordinates":[-123.606461,49.413261],"type":"Point"}
}