{
  "type": "Feature",
  "properties": {
    "addr:full":"18151 107 Ave NW Edmonton AB T5S 1K4",
    "addr:housenumber":"18151",
    "addr:postcode":"t5s 1k4",
    "addr:street":"107 Ave Nw",
    "iso:country":"CA",
    "sg:address":"18151 107 Ave NW",
    "sg:city":"Edmonton",
    "sg:classifiers":[
        {
            "category":"Freight",
            "type":"Transportation"
        }
    ],
    "sg:phone":"+1 780 484 8800",
    "sg:postcode":"T5S 1K4",
    "sg:province":"AB",
    "sg:tags":[
        "mover"
    ],
    "wof:name":"Matco Transportation Systems",
    "wof:placetype":"venue"
},
  "geometry": {"coordinates":[-113.63470459,53.5530319214],"type":"Point"}
}