{
  "type": "Feature",
  "properties": {
    "iso:country":"CA",
    "sg:address":"1125 Rue Clark",
    "sg:city":"Montreal",
    "sg:classifiers":[
        {
            "category":"Personal",
            "type":"Services"
        }
    ],
    "sg:phone":"+1 514 954 9702",
    "sg:postcode":"H2Z 1K3",
    "sg:province":"QC",
    "sg:tags":[
        "therapist",
        "massage"
    ],
    "wof:name":"Keen Wah",
    "wof:placetype":"venue"
},
  "geometry": {"coordinates":[-73.5611343384,45.5082969666],"type":"Point"}
}