{
  "type": "Feature",
  "properties": {
    "addr:full":"1492 Rue Du Couvent Saint-Bernard QC G0S 2G0",
    "addr:housenumber":"1492",
    "addr:postcode":"g0s 2g0",
    "addr:street":"Rue Du Couvent",
    "iso:country":"CA",
    "sg:address":"1492 Rue Du Couvent",
    "sg:city":"Saint-Bernard",
    "sg:classifiers":[
        {
            "category":"Education",
            "subcategory":"School",
            "type":"Public Place"
        }
    ],
    "sg:phone":"+1 418 475 6668",
    "sg:postcode":"G0S 2G0",
    "sg:province":"QC",
    "wof:name":"Ecole L'Aquarelle DE Sante",
    "wof:placetype":"venue"
},
  "geometry": {"coordinates":[-71.1366348267,46.4974784851],"type":"Point"}
}