{
  "type": "Feature",
  "properties": {
    "addr:full":"Drummondville QC J2C 6Y7",
    "addr:postcode":"j2c 6y7",
    "iso:country":"CA",
    "sg:city":"Drummondville",
    "sg:classifiers":[
        {
            "category":"Shopping",
            "subcategory":"Clothing, Apparel, & Fashions",
            "type":"Retail Goods"
        }
    ],
    "sg:phone":"+1 819 477 4389",
    "sg:postcode":"J2C 6Y7",
    "sg:province":"QC",
    "sg:tags":[
        "dressmaker"
    ],
    "wof:name":"Couture D'Or Enr",
    "wof:placetype":"venue"
},
  "geometry": {"coordinates":[-72.5157089233,45.8992500305],"type":"Point"}
}