{
  "type": "Feature",
  "properties": {
    "iso:country":"CA",
    "sg:city":"Duck Lake",
    "sg:classifiers":[
        {
            "category":"Wholesale",
            "subcategory":"Meat",
            "type":"Manufacturing & Wholesale Goods"
        }
    ],
    "sg:phone":"+1 306 467 4422",
    "sg:postcode":"S0K 1J0",
    "sg:province":"SK",
    "sg:tags":[
        "packer"
    ],
    "wof:name":"Country Choice Meats",
    "wof:placetype":"venue"
},
  "geometry": {"coordinates":[-106.224205017,52.8091964722],"type":"Point"}
}