{
  "type": "Feature",
  "properties": {
    "iso:country":"CA",
    "sg:address":"676 King St W",
    "sg:city":"Hamilton",
    "sg:classifiers":[
        {
            "category":"Shopping",
            "type":"Retail Goods"
        }
    ],
    "sg:phone":"+1 905 627 7122",
    "sg:postcode":"L8P 1C5",
    "sg:province":"ON",
    "sg:tags":[
        "monument"
    ],
    "wof:name":"Dundas Monument Works",
    "wof:placetype":"venue"
},
  "geometry": {"coordinates":[-79.888992,43.262669],"type":"Point"}
}