{
  "type": "Feature",
  "properties": {
    "addr:full":"1025 Rue Principale O Magog QC J1X 2B7",
    "addr:housenumber":"1025",
    "addr:postcode":"j1x 2b7",
    "addr:street":"Rue Principale O",
    "iso:country":"CA",
    "sg:address":"1025 Rue Principale O",
    "sg:city":"Magog",
    "sg:classifiers":[
        {
            "category":"Restaurant",
            "type":"Food & Drink"
        }
    ],
    "sg:phone":"+1 819 868 1585",
    "sg:postcode":"J1X 2B7",
    "sg:province":"QC",
    "wof:name":"Cantine Du Lac",
    "wof:placetype":"venue"
},
  "geometry": {"coordinates":[-72.131653,45.260437],"type":"Point"}
}