{
  "type": "Feature",
  "properties": {
    "addr:full":"108 Fairglen Ave Scarborough ON M1W 1A7",
    "addr:housenumber":"108",
    "addr:postcode":"m1w 1a7",
    "addr:street":"Fairglen Ave",
    "iso:country":"CA",
    "sg:address":"108 Fairglen Ave",
    "sg:city":"Scarborough",
    "sg:classifiers":[
        {
            "category":"Building & Trades",
            "subcategory":"Construction",
            "type":"Services"
        }
    ],
    "sg:phone":"+1 416 497 2841",
    "sg:postcode":"M1W 1A7",
    "sg:province":"ON",
    "sg:tags":[
        "concrete",
        "contractor"
    ],
    "wof:name":"Pagnello & Sons",
    "wof:placetype":"venue"
},
  "geometry": {"coordinates":[-79.32357,43.782185],"type":"Point"}
}