{
  "type": "Feature",
  "properties": {
    "addr:full":"Huntingdon QC J0S 1H0",
    "addr:postcode":"j0s 1h0",
    "iso:country":"CA",
    "sg:city":"Huntingdon",
    "sg:classifiers":[
        {
            "category":"Health Services",
            "subcategory":"Doctor",
            "type":"Services"
        }
    ],
    "sg:phone":"+1 450 264 6101",
    "sg:postcode":"J0S 1H0",
    "sg:province":"QC",
    "sg:tags":[
        "physician",
        "surgeon"
    ],
    "wof:name":"Rosenberg, Jean Claire MD",
    "wof:placetype":"venue"
},
  "geometry": {"coordinates":[-74.1734161377,45.0870018005],"type":"Point"}
}