{
  "type": "Feature",
  "properties": {
    "addr:full":"11032 154 St NW Edmonton AB T5P 2K1",
    "addr:housenumber":"11032",
    "addr:postcode":"t5p 2k1",
    "addr:street":"154 St Nw",
    "iso:country":"CA",
    "sg:address":"11032 154 St NW",
    "sg:city":"Edmonton",
    "sg:classifiers":[
        {
            "category":"Organizations",
            "subcategory":"Professional Association",
            "type":"Services"
        }
    ],
    "sg:phone":"+1 780 484 4646",
    "sg:postcode":"T5P 2K1",
    "sg:province":"AB",
    "wof:name":"High Park Community League",
    "wof:placetype":"venue"
},
  "geometry": {"coordinates":[-113.58744812,53.5569801331],"type":"Point"}
}