{
  "type": "Feature",
  "properties": {
    "iso:country":"CA",
    "sg:address":"2498 Robin Dr",
    "sg:city":"Mississauga",
    "sg:classifiers":[
        {
            "category":"Wholesale",
            "subcategory":"Apparel",
            "type":"Manufacturing & Wholesale Goods"
        }
    ],
    "sg:phone":"+1 905 855 0095",
    "sg:postcode":"L5K 2G3",
    "sg:province":"ON",
    "sg:tags":[
        "textile"
    ],
    "wof:name":"Brintex Marketing Ltd",
    "wof:placetype":"venue"
},
  "geometry": {"coordinates":[-79.659034729,43.535736084],"type":"Point"}
}