{
  "type": "Feature",
  "properties": {
    "addr:full":"92 Front St Emo ON P0W 1E0",
    "addr:housenumber":"92",
    "addr:postcode":"p0w 1e0",
    "addr:street":"Front St",
    "iso:country":"CA",
    "sg:address":"92 Front St",
    "sg:city":"Emo",
    "sg:classifiers":[
        {
            "category":"Banks & Credit Unions",
            "subcategory":"Bank",
            "type":"Services"
        }
    ],
    "sg:phone":"+1 807 482 2770",
    "sg:postcode":"P0W 1E0",
    "sg:province":"ON",
    "wof:name":"Cibc",
    "wof:placetype":"venue"
},
  "geometry": {"coordinates":[-93.83684539790001,48.6295928955],"type":"Point"}
}