{
  "type": "Feature",
  "properties": {
    "iso:country":"CA",
    "sg:city":"Saint-Laurent",
    "sg:classifiers":[
        {
            "category":"Professional",
            "subcategory":"Art Services",
            "type":"Services"
        }
    ],
    "sg:phone":"+1 514 856 2350",
    "sg:postcode":"H4R 2M6",
    "sg:province":"QC",
    "sg:tags":[
        "graphic",
        "designer"
    ],
    "wof:name":"Communidee",
    "wof:placetype":"venue"
},
  "geometry": {"coordinates":[-73.710922,45.520515],"type":"Point"}
}