{
  "type": "Feature",
  "properties": {
    "iso:country":"CA",
    "sg:city":"Kitchener",
    "sg:classifiers":[
        {
            "category":"Restaurant",
            "type":"Food & Drink"
        }
    ],
    "sg:phone":"+1 519 742 2274",
    "sg:postcode":"N2G 4L1",
    "sg:province":"ON",
    "sg:tags":[
        "pizza"
    ],
    "wof:name":"Party Pizza",
    "wof:placetype":"venue"
},
  "geometry": {"coordinates":[-80.48638916020001,43.4390563965],"type":"Point"}
}