{
  "type": "Feature",
  "properties": {
    "addr:full":"528 Wellington St N Kitchener ON N2H 5L5",
    "addr:housenumber":"528",
    "addr:postcode":"n2h 5l5",
    "addr:street":"Wellington St N",
    "iso:country":"CA",
    "sg:address":"528 Wellington St N",
    "sg:city":"Kitchener",
    "sg:classifiers":[
        {
            "category":"Museum",
            "type":"Entertainment"
        }
    ],
    "sg:phone":"+1 519 571 5684",
    "sg:postcode":"N2H 5L5",
    "sg:province":"ON",
    "wof:name":"Woodside National Historic Sit",
    "wof:placetype":"venue"
},
  "geometry": {"coordinates":[-80.480019,43.462624],"type":"Point"}
}