{
  "type": "Feature",
  "properties": {
    "addr:full":"4840 Wascana Pky Regina SK S4S 7J6",
    "addr:housenumber":"4840",
    "addr:postcode":"s4s 7j6",
    "addr:street":"Wascana Pky",
    "iso:country":"CA",
    "sg:address":"4840 Wascana Pky",
    "sg:city":"Regina",
    "sg:classifiers":[
        {
            "category":"Retail",
            "subcategory":"Veterinary Services",
            "type":"Services"
        }
    ],
    "sg:phone":"+1 306 787 6435",
    "sg:postcode":"S4S 7J6",
    "sg:province":"SK",
    "sg:tags":[
        "veterinarian",
        "government"
    ],
    "wof:name":"Sask Prairie Diagnostic Svc",
    "wof:placetype":"venue"
},
  "geometry": {"coordinates":[-104.574623,50.405659],"type":"Point"}
}