{
  "type": "Feature",
  "properties": {
    "addr:full":"New Liskeard ON P0J 1P0",
    "addr:postcode":"p0j 1p0",
    "iso:country":"CA",
    "sg:city":"New Liskeard",
    "sg:classifiers":[
        {
            "category":"Restaurant",
            "type":"Food & Drink"
        }
    ],
    "sg:phone":"+1 705 647 7272",
    "sg:postcode":"P0J 1P0",
    "sg:province":"ON",
    "wof:name":"Kfc",
    "wof:placetype":"venue"
},
  "geometry": {"coordinates":[-79.67134094239999,47.5146751404],"type":"Point"}
}