{
  "type": "Feature",
  "properties": {
    "addr:full":"2420 Rue Du Ruisseau Sainte-Elisabeth QC J0K 2J0",
    "addr:housenumber":"2420",
    "addr:postcode":"j0k 2j0",
    "addr:street":"Rue Du Ruisseau Sainte-Elisabeth",
    "iso:country":"CA",
    "sg:address":"2420 Rue Du Ruisseau",
    "sg:city":"Sainte-Elisabeth",
    "sg:classifiers":[
        {
            "category":"Personal",
            "subcategory":"Beauty Salon",
            "type":"Services"
        }
    ],
    "sg:phone":"+1 450 753 7724",
    "sg:postcode":"J0K 2J0",
    "sg:province":"QC",
    "wof:name":"Salon DE Coiffure Louise",
    "wof:placetype":"venue"
},
  "geometry": {"coordinates":[-73.35746,46.09362],"type":"Point"}
}