{
  "type": "Feature",
  "properties": {
    "addr:full":"7169 Pioneer Agassiz BC V0M 1A0",
    "addr:housenumber":"7169",
    "addr:postcode":"v0m 1a0",
    "addr:street":"Pioneer",
    "iso:country":"CA",
    "sg:address":"7169 Pioneer",
    "sg:city":"Agassiz",
    "sg:classifiers":[
        {
            "category":"Government",
            "subcategory":"Office",
            "type":"Public Place"
        }
    ],
    "sg:phone":"+1 604 796 3133",
    "sg:postcode":"V0M 1A0",
    "sg:province":"BC",
    "sg:tags":[
        "village"
    ],
    "wof:name":"Aberdeen Inforamtion Ctr",
    "wof:placetype":"venue"
},
  "geometry": {"coordinates":[-121.759658813,49.2385139465],"type":"Point"}
}