{
  "type": "Feature",
  "properties": {
    "addr:full":"Scarborough ON M1S 3L1",
    "addr:postcode":"m1s 3l1",
    "iso:country":"CA",
    "sg:city":"Scarborough",
    "sg:classifiers":[
        {
            "category":"Professional",
            "subcategory":"Engineering",
            "type":"Services"
        }
    ],
    "sg:phone":"+1 416 298 9563",
    "sg:postcode":"M1S 3L1",
    "sg:province":"ON",
    "sg:tags":[
        "engineer"
    ],
    "wof:name":"Miley CO Ltd",
    "wof:placetype":"venue"
},
  "geometry": {"coordinates":[-79.257217,43.792564],"type":"Point"}
}