{
  "type": "Feature",
  "properties": {
    "addr:full":"4901 Sooke Rd E Sooke BC V0S 1N0",
    "addr:housenumber":"4901",
    "addr:postcode":"v0s 1n0",
    "addr:street":"Sooke Rd E",
    "iso:country":"CA",
    "sg:address":"4901 Sooke Rd E",
    "sg:city":"Sooke",
    "sg:classifiers":[
        {
            "category":"Recreation",
            "subcategory":"Marina",
            "type":"Entertainment"
        }
    ],
    "sg:phone":"+1 250 478 4880",
    "sg:postcode":"V0S 1N0",
    "sg:province":"BC",
    "wof:name":"Cheanuh Marina",
    "wof:placetype":"venue"
},
  "geometry": {"coordinates":[-123.61643981900001,48.3980407715],"type":"Point"}
}