{
  "type": "Feature",
  "properties": {
    "addr:full":"Surrey BC V3R 6A7",
    "addr:postcode":"v3r 6a7",
    "iso:country":"CA",
    "sg:city":"Surrey",
    "sg:classifiers":[
        {
            "category":"Health Services",
            "subcategory":"Doctor",
            "type":"Services"
        }
    ],
    "sg:phone":"+1 604 588 0101",
    "sg:postcode":"V3R 6A7",
    "sg:province":"BC",
    "sg:tags":[
        "physician",
        "surgeon"
    ],
    "wof:name":"Singh, Parminder MD",
    "wof:placetype":"venue"
},
  "geometry": {"coordinates":[-122.79780599999999,49.193134],"type":"Point"}
}