{
  "type": "Feature",
  "properties": {
    "addr:full":"4632 Rue Wellington Verdun QC H4G 1W9",
    "addr:housenumber":"4632",
    "addr:postcode":"h4g 1w9",
    "addr:street":"Rue Wellington",
    "iso:country":"CA",
    "sg:address":"4632 Rue Wellington",
    "sg:city":"Verdun",
    "sg:classifiers":[
        {
            "category":"Restaurant",
            "type":"Food & Drink"
        }
    ],
    "sg:phone":"+1 514 767 5999",
    "sg:postcode":"H4G 1W9",
    "sg:province":"QC",
    "wof:name":"Pizza Expreso",
    "wof:placetype":"venue"
},
  "geometry": {"coordinates":[-73.56727600000001,45.458195],"type":"Point"}
}