{
  "type": "Feature",
  "properties": {
    "addr:full":"1260 Highfield Cres SE Calgary AB T2G 5M3",
    "addr:housenumber":"1260",
    "addr:postcode":"t2g 5m3",
    "addr:street":"Highfield Cres Se",
    "iso:country":"CA",
    "sg:address":"1260 Highfield Cres SE",
    "sg:city":"Calgary",
    "sg:classifiers":[
        {
            "category":"Autos & Motor Vehicles",
            "subcategory":"Recreational Vehicle Sales",
            "type":"Retail Goods"
        }
    ],
    "sg:phone":"+1 403 240 1814",
    "sg:postcode":"T2G 5M3",
    "sg:province":"AB",
    "sg:tags":[
        "home"
    ],
    "wof:name":"Go West Campers Ltd",
    "wof:placetype":"venue"
},
  "geometry": {"coordinates":[-114.03505699999999,51.010792],"type":"Point"}
}