{
  "type": "Feature",
  "properties": {
    "addr:full":"10 Railway St Maple ON L6A 1P6",
    "addr:housenumber":"10",
    "addr:postcode":"l6a 1p6",
    "addr:street":"Railway St",
    "iso:country":"CA",
    "sg:address":"10 Railway St",
    "sg:city":"Maple",
    "sg:classifiers":[
        {
            "category":"Manufacturing",
            "subcategory":"Printing",
            "type":"Manufacturing & Wholesale Goods"
        }
    ],
    "sg:phone":"+1 905 832 2231",
    "sg:postcode":"L6A 1P6",
    "sg:province":"ON",
    "sg:tags":[
        "printer"
    ],
    "wof:name":"Beacon Press Ltd",
    "wof:placetype":"venue"
},
  "geometry": {"coordinates":[-79.511756897,43.8571243286],"type":"Point"}
}