{
  "type": "Feature",
  "properties": {
    "addr:full":"51 Old Church Rd Lower West Pubnico NS B0W 2C0",
    "addr:housenumber":"51",
    "addr:postcode":"b0w 2c0",
    "addr:street":"Old Church Rd",
    "iso:country":"CA",
    "sg:address":"51 Old Church Rd",
    "sg:city":"Lower West Pubnico",
    "sg:classifiers":[
        {
            "category":"Manufacturing",
            "subcategory":"Watercraft",
            "type":"Manufacturing & Wholesale Goods"
        }
    ],
    "sg:phone":"+1 902 762 2020",
    "sg:postcode":"B0W 2C0",
    "sg:province":"NS",
    "sg:tags":[
        "boat"
    ],
    "wof:name":"James D'Entremont Boat Buildrs",
    "wof:placetype":"venue"
},
  "geometry": {"coordinates":[-65.80112457280001,43.6314697266],"type":"Point"}
}