{
  "type": "Feature",
  "properties": {
    "addr:full":"50 Main St E Neepawa MB R0J 1H0",
    "addr:housenumber":"50",
    "addr:postcode":"r0j 1h0",
    "addr:street":"Main St E",
    "iso:country":"CA",
    "sg:address":"50 Main St E",
    "sg:city":"Neepawa",
    "sg:classifiers":[
        {
            "category":"Local Transit",
            "type":"Transportation"
        }
    ],
    "sg:phone":"+1 204 476 2267",
    "sg:postcode":"R0J 1H0",
    "sg:province":"MB",
    "sg:tags":[
        "bus",
        "line",
        "courier"
    ],
    "wof:name":"Greyhound Courier Express",
    "wof:placetype":"venue"
},
  "geometry": {"coordinates":[-99.4748,50.226398],"type":"Point"}
}