{
  "type": "Feature",
  "properties": {
    "iso:country":"CA",
    "sg:city":"Mississauga",
    "sg:classifiers":[
        {
            "category":"Home & Garden",
            "subcategory":"Household Appliances",
            "type":"Retail Goods"
        }
    ],
    "sg:phone":"+1 905 279 5820",
    "sg:postcode":"L4Y 4C1",
    "sg:province":"ON",
    "wof:name":"Crawford Appliances & Air Cond",
    "wof:placetype":"venue"
},
  "geometry": {"coordinates":[-79.583946228,43.5960197449],"type":"Point"}
}