{
  "type": "Feature",
  "properties": {
    "addr:full":"367 Pitfield Rd Scarborough ON M1S 3E5",
    "addr:housenumber":"367",
    "addr:postcode":"m1s 3e5",
    "addr:street":"Pitfield Rd",
    "iso:country":"CA",
    "sg:address":"367 Pitfield Rd",
    "sg:city":"Scarborough",
    "sg:classifiers":[
        {
            "category":"Food & Beverages",
            "subcategory":"Specialty",
            "type":"Retail Goods"
        }
    ],
    "sg:phone":"+1 416 291 8317",
    "sg:postcode":"M1S 3E5",
    "sg:province":"ON",
    "sg:tags":[
        "oriental"
    ],
    "wof:name":"Seoul Foods",
    "wof:placetype":"venue"
},
  "geometry": {"coordinates":[-79.25839999999999,43.787067],"type":"Point"}
}