{
  "type": "Feature",
  "properties": {
    "addr:full":"233 Esplanade Sydney NS B1P 1A6",
    "addr:housenumber":"233",
    "addr:postcode":"b1p 1a6",
    "addr:street":"Esplanade",
    "iso:country":"CA",
    "sg:address":"233 Esplanade",
    "sg:city":"Sydney",
    "sg:classifiers":[
        {
            "category":"Restaurant",
            "type":"Food & Drink"
        }
    ],
    "sg:phone":"+1 902 564 9350",
    "sg:postcode":"B1P 1A6",
    "sg:province":"NS",
    "wof:name":"Country Inn",
    "wof:placetype":"venue"
},
  "geometry": {"coordinates":[-60.1960296631,46.1395645142],"type":"Point"}
}