{
  "type": "Feature",
  "properties": {
    "addr:full":"282 Dundas St E Trenton ON K8V 1M2",
    "addr:housenumber":"282",
    "addr:postcode":"k8v 1m2",
    "addr:street":"Dundas St E",
    "iso:country":"CA",
    "sg:address":"282 Dundas St E",
    "sg:city":"Trenton",
    "sg:classifiers":[
        {
            "category":"Restaurant",
            "type":"Food & Drink"
        }
    ],
    "sg:phone":"+1 613 965 6414",
    "sg:postcode":"K8V 1M2",
    "sg:province":"ON",
    "wof:name":"Dapp's Restaurant",
    "wof:placetype":"venue"
},
  "geometry": {"coordinates":[-77.555115,44.10508],"type":"Point"}
}