{
  "type": "Feature",
  "properties": {
    "iso:country":"CA",
    "sg:address":"1057 Rue Levis",
    "sg:city":"Lachenaie",
    "sg:classifiers":[
        {
            "category":"Recreation",
            "type":"Entertainment"
        }
    ],
    "sg:phone":"+1 450 961 2682",
    "sg:postcode":"J6W 4L2",
    "sg:province":"QC",
    "sg:tags":[
        "martial",
        "arts",
        "instruction"
    ],
    "wof:name":"Kyokushin Karate",
    "wof:placetype":"venue"
},
  "geometry": {"coordinates":[-73.6244888306,45.7126502991],"type":"Point"}
}