{
  "type": "Feature",
  "properties": {
    "addr:full":"9610 39 Ave NW Edmonton AB T6E 5T9",
    "addr:housenumber":"9610",
    "addr:postcode":"t6e 5t9",
    "addr:street":"39 Ave Nw",
    "iso:country":"CA",
    "sg:address":"9610 39 Ave NW",
    "sg:city":"Edmonton",
    "sg:classifiers":[
        {
            "category":"Mining & Drilling",
            "type":"Manufacturing & Wholesale Goods"
        }
    ],
    "sg:phone":"+1 780 469 8122",
    "sg:postcode":"T6E 5T9",
    "sg:province":"AB",
    "sg:tags":[
        "field",
        "oil"
    ],
    "wof:name":"Midfield Supply Ltd",
    "wof:placetype":"venue"
},
  "geometry": {"coordinates":[-113.47772999999999,53.474236],"type":"Point"}
}