{
  "type": "Feature",
  "properties": {
    "addr:full":"Maynooth ON K0L 2S0",
    "addr:postcode":"k0l 2s0",
    "iso:country":"CA",
    "sg:city":"Maynooth",
    "sg:classifiers":[
        {
            "category":"Government",
            "subcategory":"Office",
            "type":"Public Place"
        }
    ],
    "sg:phone":"+1 613 338 2811",
    "sg:postcode":"K0L 2S0",
    "sg:province":"ON",
    "sg:tags":[
        "village"
    ],
    "wof:name":"Hastings Highlands Trans",
    "wof:placetype":"venue"
},
  "geometry": {"coordinates":[-77.936829,45.231323],"type":"Point"}
}