{
  "type": "Feature",
  "properties": {
    "addr:full":"6315 Rue Hotel DE Ville Saint-Calixte QC J0K 1Z0",
    "addr:housenumber":"6315",
    "addr:postcode":"j0k 1z0",
    "addr:street":"Rue Hotel De Ville",
    "iso:country":"CA",
    "sg:address":"6315 Rue Hotel DE Ville",
    "sg:city":"Saint-Calixte",
    "sg:classifiers":[
        {
            "category":"Education",
            "subcategory":"School",
            "type":"Public Place"
        }
    ],
    "sg:phone":"+1 450 222 2765",
    "sg:postcode":"J0K 1Z0",
    "sg:province":"QC",
    "wof:name":"Commission Scolaire-Cascades",
    "wof:placetype":"venue"
},
  "geometry": {"coordinates":[-73.848739624,45.9520797729],"type":"Point"}
}