{
  "type": "Feature",
  "properties": {
    "addr:full":"9 Rue Jeannotte Vaudreuil-Dorion QC J7V 6E6",
    "addr:housenumber":"9",
    "addr:postcode":"j7v 6e6",
    "addr:street":"Rue Jeannotte",
    "iso:country":"CA",
    "sg:address":"9 Rue Jeannotte",
    "sg:city":"Vaudreuil-Dorion",
    "sg:classifiers":[
        {
            "category":"Government",
            "subcategory":"Office",
            "type":"Public Place"
        }
    ],
    "sg:phone":"+1 450 455 5505",
    "sg:postcode":"J7V 6E6",
    "sg:province":"QC",
    "sg:tags":[
        "village"
    ],
    "wof:name":"Vaudreuil-Dorion Arena",
    "wof:placetype":"venue"
},
  "geometry": {"coordinates":[-74.0271606445,45.3985023499],"type":"Point"}
}