{
  "type": "Feature",
  "properties": {
    "addr:full":"330 Rue Charron Contrecoeur QC J0L 1C0",
    "addr:housenumber":"330",
    "addr:postcode":"j0l 1c0",
    "addr:street":"Rue Charron",
    "iso:country":"CA",
    "sg:address":"330 Rue Charron",
    "sg:city":"Contrecoeur",
    "sg:classifiers":[
        {
            "category":"Personal",
            "subcategory":"Beauty Salon",
            "type":"Services"
        }
    ],
    "sg:phone":"+1 450 587 2283",
    "sg:postcode":"J0L 1C0",
    "sg:province":"QC",
    "wof:name":"Salon DE Coiffure Lise",
    "wof:placetype":"venue"
},
  "geometry": {"coordinates":[-73.24041699999999,45.85437],"type":"Point"}
}