{
  "type": "Feature",
  "properties": {
    "addr:full":"5825 Boul Henri-Bourassa E Montreal-Nord QC H1G 2V1",
    "addr:housenumber":"5825",
    "addr:postcode":"h1g 2v1",
    "addr:street":"Boul Henri-Bourassa E",
    "iso:country":"CA",
    "sg:address":"5825 Boul Henri-Bourassa E",
    "sg:city":"Montreal-Nord",
    "sg:classifiers":[
        {
            "category":"Food & Beverages",
            "subcategory":"Bakery",
            "type":"Retail Goods"
        }
    ],
    "sg:phone":"+1 514 327 4550",
    "sg:postcode":"H1G 2V1",
    "sg:province":"QC",
    "sg:tags":[
        "doughnut"
    ],
    "wof:name":"Dunkin' Donuts Ltee",
    "wof:placetype":"venue"
},
  "geometry": {"coordinates":[-73.618942,45.607258],"type":"Point"}
}