{
  "type": "Feature",
  "properties": {
    "addr:full":"511 Fraser Ave Ottawa ON K2A 2R1",
    "addr:housenumber":"511",
    "addr:postcode":"k2a 2r1",
    "addr:street":"Fraser Ave",
    "iso:country":"CA",
    "sg:address":"511 Fraser Ave",
    "sg:city":"Ottawa",
    "sg:classifiers":[
        {
            "category":"Building & Trades",
            "subcategory":"Electrical",
            "type":"Services"
        }
    ],
    "sg:phone":"+1 613 729 8556",
    "sg:postcode":"K2A 2R1",
    "sg:province":"ON",
    "sg:tags":[
        "electric",
        "contractor"
    ],
    "wof:name":"Tripp Electric",
    "wof:placetype":"venue"
},
  "geometry": {"coordinates":[-75.7621841431,45.3849945068],"type":"Point"}
}