{
  "type": "Feature",
  "properties": {
    "iso:country":"CA",
    "sg:address":"118 Elizabeth St",
    "sg:city":"Okotoks",
    "sg:classifiers":[
        {
            "category":"Utilities",
            "subcategory":"Mobile Phone",
            "type":"Services"
        }
    ],
    "sg:phone":"+1 403 938 1455",
    "sg:postcode":"T1S 1A4",
    "sg:province":"AB",
    "sg:tags":[
        "telephone",
        "cellular"
    ],
    "wof:name":"Big Rock Communications",
    "wof:placetype":"venue"
},
  "geometry": {"coordinates":[-113.98141479500001,50.7260284424],"type":"Point"}
}