{
  "type": "Feature",
  "properties": {
    "addr:full":"419 Rue Richard Longueuil QC J4L 3A6",
    "addr:housenumber":"419",
    "addr:postcode":"j4l 3a6",
    "addr:street":"Rue Richard",
    "iso:country":"CA",
    "sg:address":"419 Rue Richard",
    "sg:city":"Longueuil",
    "sg:classifiers":[
        {
            "category":"Professional",
            "type":"Services"
        }
    ],
    "sg:phone":"+1 450 651 4513",
    "sg:postcode":"J4L 3A6",
    "sg:province":"QC",
    "sg:tags":[
        "accounting",
        "bookkeeping",
        "establishment",
        "system"
    ],
    "wof:name":"Serge Cournoyer Inc",
    "wof:placetype":"venue"
},
  "geometry": {"coordinates":[-73.455871582,45.5148048401],"type":"Point"}
}