{
  "type": "Feature",
  "properties": {
    "addr:full":"Calgary AB T2E 6J9",
    "addr:postcode":"t2e 6j9",
    "iso:country":"CA",
    "sg:city":"Calgary",
    "sg:classifiers":[
        {
            "category":"Wholesale",
            "subcategory":"Medical Equipment & Supplies",
            "type":"Manufacturing & Wholesale Goods"
        }
    ],
    "sg:phone":"+1 403 272 9590",
    "sg:postcode":"T2E 6J9",
    "sg:province":"AB",
    "sg:tags":[
        "microscope",
        "geologist"
    ],
    "wof:name":"Petrocraft Products Ltd",
    "wof:placetype":"venue"
},
  "geometry": {"coordinates":[-114.003342,51.050854],"type":"Point"}
}