{
  "type": "Feature",
  "properties": {
    "addr:full":"720 Confederation St Sarnia ON N7T 2C9",
    "addr:housenumber":"720",
    "addr:postcode":"n7t 2c9",
    "addr:street":"Confederation St",
    "iso:country":"CA",
    "sg:address":"720 Confederation St",
    "sg:city":"Sarnia",
    "sg:classifiers":[
        {
            "category":"Manufacturing",
            "subcategory":"Tools & Machinery",
            "type":"Manufacturing & Wholesale Goods"
        }
    ],
    "sg:phone":"+1 519 344 4112",
    "sg:postcode":"N7T 2C9",
    "sg:province":"ON",
    "sg:tags":[
        "electric",
        "motor"
    ],
    "wof:name":"Lawrence Electric Motor Repair",
    "wof:placetype":"venue"
},
  "geometry": {"coordinates":[-82.386383,42.960941],"type":"Point"}
}