{
  "type": "Feature",
  "properties": {
    "addr:full":"772 Boul Arthur-Sauve Saint-Eustache QC J7R 4K3",
    "addr:housenumber":"772",
    "addr:postcode":"j7r 4k3",
    "addr:street":"Boul Arthur-Sauve",
    "iso:country":"CA",
    "sg:address":"772 Boul Arthur-Sauve",
    "sg:city":"Saint-Eustache",
    "sg:classifiers":[
        {
            "category":"Home & Garden",
            "subcategory":"Furniture",
            "type":"Retail Goods"
        }
    ],
    "sg:phone":"+1 450 472 6131",
    "sg:postcode":"J7R 4K3",
    "sg:province":"QC",
    "sg:tags":[
        "bathroom",
        "kitchen",
        "remodeling",
        "cabinet"
    ],
    "wof:name":"Armoires DE Chez Nous Ltee",
    "wof:placetype":"venue"
},
  "geometry": {"coordinates":[-73.9210891724,45.5805015564],"type":"Point"}
}