{
  "type": "Feature",
  "properties": {
    "addr:full":"2055 Rang Saint-Paul Saint-Remi QC J0L 2L0",
    "addr:housenumber":"2055",
    "addr:postcode":"j0l 2l0",
    "addr:street":"Rang Saint-Paul Saint-Remi",
    "iso:country":"CA",
    "sg:address":"2055 Rang Saint-Paul",
    "sg:city":"Saint-Remi",
    "sg:classifiers":[
        {
            "category":"Wholesale",
            "subcategory":"Fruits & Vegetables",
            "type":"Manufacturing & Wholesale Goods"
        }
    ],
    "sg:phone":"+1 450 454 5026",
    "sg:postcode":"J0L 2L0",
    "sg:province":"QC",
    "sg:tags":[
        "shipper"
    ],
    "wof:name":"Carottine Inc",
    "wof:placetype":"venue"
},
  "geometry": {"coordinates":[-73.6436538696,45.2077484131],"type":"Point"}
}