{
  "type": "Feature",
  "properties": {
    "addr:full":"179 King St W Brockville ON K6V 3R6",
    "addr:housenumber":"179",
    "addr:postcode":"k6v 3r6",
    "addr:street":"King St W",
    "iso:country":"CA",
    "sg:address":"179 King St W",
    "sg:city":"Brockville",
    "sg:classifiers":[
        {
            "category":"Food & Beverages",
            "subcategory":"Liquor & Beverages",
            "type":"Retail Goods"
        }
    ],
    "sg:phone":"+1 613 342 2202",
    "sg:postcode":"K6V 3R6",
    "sg:province":"ON",
    "sg:tags":[
        "store"
    ],
    "wof:name":"Liquor Control Board",
    "wof:placetype":"venue"
},
  "geometry": {"coordinates":[-75.68761444090001,44.5875434875],"type":"Point"}
}