{
  "type": "Feature",
  "properties": {
    "addr:full":"1131 Rue Decarie Saint-Laurent QC H4L 3M8",
    "addr:housenumber":"1131",
    "addr:postcode":"h4l 3m8",
    "addr:street":"Rue Decarie",
    "iso:country":"CA",
    "sg:address":"1131 Rue Decarie",
    "sg:city":"Saint-Laurent",
    "sg:classifiers":[
        {
            "category":"Travel",
            "subcategory":"Travel Agent",
            "type":"Entertainment"
        }
    ],
    "sg:phone":"+1 514 748 5051",
    "sg:postcode":"H4L 3M8",
    "sg:province":"QC",
    "sg:tags":[
        "agency",
        "bureau"
    ],
    "wof:name":"Voyages Decarie Enrg",
    "wof:placetype":"venue"
},
  "geometry": {"coordinates":[-73.68414300000001,45.515411],"type":"Point"}
}