{
  "type": "Feature",
  "properties": {
    "addr:full":"12041 86 Ave Surrey BC V3W 7X5",
    "addr:housenumber":"12041",
    "addr:postcode":"v3w 7x5",
    "addr:street":"86 Ave",
    "iso:country":"CA",
    "sg:address":"12041 86 Ave",
    "sg:city":"Surrey",
    "sg:classifiers":[
        {
            "category":"Retail",
            "subcategory":"Auto Repair",
            "type":"Services"
        }
    ],
    "sg:phone":"+1 604 590 6077",
    "sg:postcode":"V3W 7X5",
    "sg:province":"BC",
    "sg:tags":[
        "repairing",
        "automobile"
    ],
    "wof:name":"Knight Automotive",
    "wof:placetype":"venue"
},
  "geometry": {"coordinates":[-122.889236,49.159794],"type":"Point"}
}