{
  "type": "Feature",
  "properties": {
    "addr:full":"35 High Drayton ON N0G 1P0",
    "addr:housenumber":"35",
    "addr:postcode":"n0g 1p0",
    "addr:street":"High Drayton",
    "iso:country":"CA",
    "sg:address":"35 High",
    "sg:city":"Drayton",
    "sg:classifiers":[
        {
            "category":"Social Services",
            "subcategory":"Child Care",
            "type":"Services"
        }
    ],
    "sg:phone":"+1 519 638 3331",
    "sg:postcode":"N0G 1P0",
    "sg:province":"ON",
    "sg:tags":[
        "kindergarten",
        "academic",
        "school"
    ],
    "wof:name":"Drayton Peel Maryborough Schl",
    "wof:placetype":"venue"
},
  "geometry": {"coordinates":[-80.6696014404,43.7520103455],"type":"Point"}
}