{
  "type": "Feature",
  "properties": {
    "addr:full":"10251 Gibraltar Mine Rd Mcleese Lake BC V0L 1P0",
    "addr:housenumber":"10251",
    "addr:postcode":"v0l 1p0",
    "addr:street":"Gibraltar Mine Rd Mcleese",
    "iso:country":"CA",
    "sg:address":"10251 Gibraltar Mine Rd",
    "sg:city":"Mcleese Lake",
    "sg:classifiers":[
        {
            "category":"Mining & Drilling",
            "type":"Manufacturing & Wholesale Goods"
        }
    ],
    "sg:phone":"+1 250 297 6211",
    "sg:postcode":"V0L 1P0",
    "sg:province":"BC",
    "sg:tags":[
        "company"
    ],
    "wof:name":"Gibraltar Mines Ltd",
    "wof:placetype":"venue"
},
  "geometry": {"coordinates":[-122.30152893099999,52.4261322021],"type":"Point"}
}