{
  "type": "Feature",
  "properties": {
    "iso:country":"CA",
    "sg:city":"Concord",
    "sg:classifiers":[
        {
            "category":"Real Estate",
            "subcategory":"Real Estate Agent",
            "type":"Services"
        }
    ],
    "sg:phone":"+1 905 660 7843",
    "sg:postcode":"L4K 4L8",
    "sg:province":"ON",
    "wof:name":"Spectrum Realty Svc Inc",
    "wof:placetype":"venue"
},
  "geometry": {"coordinates":[-79.528526,43.812141],"type":"Point"}
}