{
  "type": "Feature",
  "properties": {
    "addr:full":"5007 50 Ave Bonnyville AB T9N 2G6",
    "addr:housenumber":"5007",
    "addr:postcode":"t9n 2g6",
    "addr:street":"50 Ave",
    "iso:country":"CA",
    "sg:address":"5007 50 Ave",
    "sg:city":"Bonnyville",
    "sg:classifiers":[
        {
            "category":"Restaurant",
            "type":"Food & Drink"
        }
    ],
    "sg:phone":"+1 780 826 3750",
    "sg:postcode":"T9N 2G6",
    "sg:province":"AB",
    "wof:name":"Panda Garden",
    "wof:placetype":"venue"
},
  "geometry": {"coordinates":[-110.74030304,54.2681007385],"type":"Point"}
}