{
  "type": "Feature",
  "properties": {
    "addr:full":"Surrey BC V4N 3M9",
    "addr:postcode":"v4n 3m9",
    "iso:country":"CA",
    "sg:city":"Surrey",
    "sg:classifiers":[
        {
            "category":"Building & Trades",
            "subcategory":"Construction",
            "type":"Services"
        }
    ],
    "sg:phone":"+1 604 882 8608",
    "sg:postcode":"V4N 3M9",
    "sg:province":"BC",
    "sg:tags":[
        "painter"
    ],
    "wof:name":"Clara Industrial Svc Ltd",
    "wof:placetype":"venue"
},
  "geometry": {"coordinates":[-122.695961,49.179443],"type":"Point"}
}