{
  "type": "Feature",
  "properties": {
    "addr:full":"Kitchener ON N2N 3G6",
    "addr:postcode":"n2n 3g6",
    "iso:country":"CA",
    "sg:city":"Kitchener",
    "sg:classifiers":[
        {
            "category":"Health Services",
            "subcategory":"Doctor",
            "type":"Services"
        }
    ],
    "sg:phone":"+1 519 744 4293",
    "sg:postcode":"N2N 3G6",
    "sg:province":"ON",
    "sg:tags":[
        "physician",
        "surgeon"
    ],
    "wof:name":"Beechwood Forest Medical Ctr",
    "wof:placetype":"venue"
},
  "geometry": {"coordinates":[-80.54289199999999,43.442322],"type":"Point"}
}