{
  "type": "Feature",
  "properties": {
    "addr:full":"1145 Grand Lake Rd Sydney NS B1M 1A2",
    "addr:housenumber":"1145",
    "addr:postcode":"b1m 1a2",
    "addr:street":"Grand Lake Rd",
    "iso:country":"CA",
    "sg:address":"1145 Grand Lake Rd",
    "sg:city":"Sydney",
    "sg:classifiers":[
        {
            "category":"Recreation",
            "subcategory":"Amusement Park",
            "type":"Entertainment"
        }
    ],
    "sg:phone":"+1 902 567 0688",
    "sg:postcode":"B1M 1A2",
    "sg:province":"NS",
    "wof:name":"Hinchey's Rides & Amusements",
    "wof:placetype":"venue"
},
  "geometry": {"coordinates":[-60.105789,46.166039],"type":"Point"}
}