{
  "type": "Feature",
  "properties": {
    "addr:full":"241 Bay St Orillia ON L3V 3W9",
    "addr:housenumber":"241",
    "addr:postcode":"l3v 3w9",
    "addr:street":"Bay St",
    "iso:country":"CA",
    "sg:address":"241 Bay St",
    "sg:city":"Orillia",
    "sg:classifiers":[
        {
            "category":"Social Services",
            "type":"Services"
        }
    ],
    "sg:phone":"+1 705 329 2854",
    "sg:postcode":"L3V 3W9",
    "sg:province":"ON",
    "sg:tags":[
        "counselor",
        "marriage",
        "family"
    ],
    "wof:name":"Adams, Brian R",
    "wof:placetype":"venue"
},
  "geometry": {"coordinates":[-79.41477999999999,44.620007],"type":"Point"}
}