{
  "type": "Feature",
  "properties": {
    "addr:full":"353 Main St Selkirk MB R1A 1T5",
    "addr:housenumber":"353",
    "addr:postcode":"r1a 1t5",
    "addr:street":"Main St",
    "iso:country":"CA",
    "sg:address":"353 Main St",
    "sg:city":"Selkirk",
    "sg:classifiers":[
        {
            "category":"Health Services",
            "subcategory":"Optometrist",
            "type":"Services"
        }
    ],
    "sg:phone":"+1 204 482 3713",
    "sg:postcode":"R1A 1T5",
    "sg:province":"MB",
    "sg:tags":[
        "optician"
    ],
    "wof:name":"Carriage Optical",
    "wof:placetype":"venue"
},
  "geometry": {"coordinates":[-96.8755493164,50.1430053711],"type":"Point"}
}