{
  "type": "Feature",
  "properties": {
    "addr:full":"1564 Rue Prieur E Montreal QC H2C 1M1",
    "addr:housenumber":"1564",
    "addr:postcode":"h2c 1m1",
    "addr:street":"Rue Prieur E",
    "iso:country":"CA",
    "sg:address":"1564 Rue Prieur E",
    "sg:city":"Montreal",
    "sg:classifiers":[
        {
            "category":"Building & Trades",
            "subcategory":"Construction",
            "type":"Services"
        }
    ],
    "sg:phone":"+1 514 384 9227",
    "sg:postcode":"H2C 1M1",
    "sg:province":"QC",
    "sg:tags":[
        "contractor"
    ],
    "wof:name":"Guyon Construction",
    "wof:placetype":"venue"
},
  "geometry": {"coordinates":[-73.6590270996,45.5641288757],"type":"Point"}
}