{
  "type": "Feature",
  "properties": {
    "addr:full":"1325 Indian Rd Mississauga ON L5H 1S3",
    "addr:housenumber":"1325",
    "addr:postcode":"l5h 1s3",
    "addr:street":"Indian Rd",
    "iso:country":"CA",
    "sg:address":"1325 Indian Rd",
    "sg:city":"Mississauga",
    "sg:classifiers":[
        {
            "category":"Education",
            "subcategory":"School",
            "type":"Public Place"
        }
    ],
    "sg:phone":"+1 905 278 8771",
    "sg:postcode":"L5H 1S3",
    "sg:province":"ON",
    "wof:name":"Lorne Park Public School",
    "wof:placetype":"venue"
},
  "geometry": {"coordinates":[-79.627251,43.536861],"type":"Point"}
}