{
  "type": "Feature",
  "properties": {
    "addr:full":"Mississauga ON L5A 3P1",
    "addr:postcode":"l5a 3p1",
    "iso:country":"CA",
    "sg:city":"Mississauga",
    "sg:classifiers":[
        {
            "category":"Autos & Motor Vehicles",
            "subcategory":"Auto Supplies",
            "type":"Retail Goods"
        }
    ],
    "sg:phone":"+1 905 897 0644",
    "sg:postcode":"L5A 3P1",
    "sg:province":"ON",
    "sg:tags":[
        "automobile",
        "parts"
    ],
    "wof:name":"National Auto Parts",
    "wof:placetype":"venue"
},
  "geometry": {"coordinates":[-79.5958862305,43.592010498],"type":"Point"}
}