{
  "type": "Feature",
  "properties": {
    "addr:full":"210 Ch Kipawa Temiscaming QC J0Z 3R0",
    "addr:housenumber":"210",
    "addr:postcode":"j0z 3r0",
    "addr:street":"Ch Kipawa Temiscaming",
    "iso:country":"CA",
    "sg:address":"210 Ch Kipawa",
    "sg:city":"Temiscaming",
    "sg:classifiers":[
        {
            "category":"Organizations",
            "subcategory":"Professional Association",
            "type":"Services"
        }
    ],
    "sg:phone":"+1 819 627 9772",
    "sg:postcode":"J0Z 3R0",
    "sg:province":"QC",
    "wof:name":"Royal Canadian Legion",
    "wof:placetype":"venue"
},
  "geometry": {"coordinates":[-79.102936,46.717667],"type":"Point"}
}