{
  "type": "Feature",
  "properties": {
    "addr:full":"2537 Ch Du Fleuve Saint-Romuald QC G6W 1X5",
    "addr:housenumber":"2537",
    "addr:postcode":"g6w 1x5",
    "addr:street":"Ch Du Fleuve",
    "iso:country":"CA",
    "sg:address":"2537 Ch Du Fleuve",
    "sg:city":"Saint-Romuald",
    "sg:classifiers":[
        {
            "category":"Shopping",
            "subcategory":"Bicycles & Sporting Goods",
            "type":"Retail Goods"
        }
    ],
    "sg:phone":"+1 418 839 7422",
    "sg:postcode":"G6W 1X5",
    "sg:province":"QC",
    "sg:tags":[
        "skating",
        "equipment",
        "supply"
    ],
    "wof:name":"Entreprises Rodebec Inc",
    "wof:placetype":"venue"
},
  "geometry": {"coordinates":[-71.230087,46.759182],"type":"Point"}
}