{
  "type": "Feature",
  "properties": {
    "addr:full":"Niagara Falls ON L2E 6S5",
    "addr:postcode":"l2e 6s5",
    "iso:country":"CA",
    "sg:city":"Niagara Falls",
    "sg:classifiers":[
        {
            "category":"Retail",
            "subcategory":"Auto Repair",
            "type":"Services"
        }
    ],
    "sg:phone":"+1 905 374 4323",
    "sg:postcode":"L2E 6S5",
    "sg:province":"ON",
    "sg:tags":[
        "repairing",
        "automobile"
    ],
    "wof:name":"John's Bug Shop",
    "wof:placetype":"venue"
},
  "geometry": {"coordinates":[-79.1214828491,43.0636787415],"type":"Point"}
}