{
  "type": "Feature",
  "properties": {
    "addr:full":"20 Rue Lauziere Yamaska QC J0G 1W0",
    "addr:housenumber":"20",
    "addr:postcode":"j0g 1w0",
    "addr:street":"Rue Lauziere",
    "iso:country":"CA",
    "sg:address":"20 Rue Lauziere",
    "sg:city":"Yamaska",
    "sg:classifiers":[
        {
            "category":"Building & Trades",
            "subcategory":"Construction",
            "type":"Services"
        }
    ],
    "sg:phone":"+1 450 789 2331",
    "sg:postcode":"J0G 1W0",
    "sg:province":"QC",
    "sg:tags":[
        "siding",
        "contractor"
    ],
    "wof:name":"Revetement Caplette & Danis",
    "wof:placetype":"venue"
},
  "geometry": {"coordinates":[-72.915688,46.009678],"type":"Point"}
}