{
  "type": "Feature",
  "properties": {
    "addr:full":"4177 Boul Decarie Montreal QC H4A 3J8",
    "addr:housenumber":"4177",
    "addr:postcode":"h4a 3j8",
    "addr:street":"Boul Decarie",
    "iso:country":"CA",
    "sg:address":"4177 Boul Decarie",
    "sg:city":"Montreal",
    "sg:classifiers":[
        {
            "category":"Health Services",
            "subcategory":"Health Practitioner",
            "type":"Services"
        }
    ],
    "sg:phone":"+1 514 483 6669",
    "sg:postcode":"H4A 3J8",
    "sg:province":"QC",
    "sg:tags":[
        "acupuncture"
    ],
    "wof:name":"Clinique Sinocare Aina Zhang",
    "wof:placetype":"venue"
},
  "geometry": {"coordinates":[-73.61962890620001,45.4792098999],"type":"Point"}
}