{
  "type": "Feature",
  "properties": {
    "addr:full":"1651 Sackville Dr Middle Sackville NS B4E 3A9",
    "addr:housenumber":"1651",
    "addr:postcode":"b4e 3a9",
    "addr:street":"Sackville Dr",
    "iso:country":"CA",
    "sg:address":"1651 Sackville Dr",
    "sg:city":"Middle Sackville",
    "sg:classifiers":[
        {
            "category":"Autos & Motor Vehicles",
            "subcategory":"Automobile Sales",
            "type":"Retail Goods"
        }
    ],
    "sg:phone":"+1 902 864 8886",
    "sg:postcode":"B4E 3A9",
    "sg:province":"NS",
    "sg:tags":[
        "car",
        "truck",
        "broker"
    ],
    "wof:name":"Keizer's Auto Sales",
    "wof:placetype":"venue"
},
  "geometry": {"coordinates":[-63.726681,44.795578],"type":"Point"}
}