{
  "type": "Feature",
  "properties": {
    "addr:full":"Dieppe NB E1A 4X5",
    "addr:postcode":"e1a 4x5",
    "iso:country":"CA",
    "sg:city":"Dieppe",
    "sg:classifiers":[
        {
            "category":"Shopping",
            "subcategory":"Clothing, Apparel, & Fashions",
            "type":"Retail Goods"
        }
    ],
    "sg:phone":"+1 506 855 4078",
    "sg:postcode":"E1A 4X5",
    "sg:province":"NB",
    "wof:name":"Suzy Shier",
    "wof:placetype":"venue"
},
  "geometry": {"coordinates":[-64.76091003419999,46.0988502502],"type":"Point"}
}