{
  "type": "Feature",
  "properties": {
    "addr:full":"4122 15th Ave Prince George BC V2M 1V9",
    "addr:housenumber":"4122",
    "addr:postcode":"v2m 1v9",
    "addr:street":"15Th Ave",
    "iso:country":"CA",
    "sg:address":"4122 15th Ave",
    "sg:city":"Prince George",
    "sg:classifiers":[
        {
            "category":"Health Services",
            "subcategory":"Doctor",
            "type":"Services"
        }
    ],
    "sg:phone":"+1 250 562 5551",
    "sg:postcode":"V2M 1V9",
    "sg:province":"BC",
    "sg:tags":[
        "dentist"
    ],
    "wof:name":"Suen, Richard A DDS",
    "wof:placetype":"venue"
},
  "geometry": {"coordinates":[-122.798592,53.91066],"type":"Point"}
}