{
  "type": "Feature",
  "properties": {
    "iso:country":"CA",
    "sg:address":"15151 Fraser Hwy",
    "sg:city":"Surrey",
    "sg:classifiers":[
        {
            "category":"Restaurant",
            "type":"Food & Drink"
        }
    ],
    "sg:phone":"+1 604 589 2488",
    "sg:postcode":"V3R 3P2",
    "sg:province":"BC",
    "sg:tags":[
        "delicatessen"
    ],
    "wof:name":"Marini Italian Foods",
    "wof:placetype":"venue"
},
  "geometry": {"coordinates":[-122.80266571,49.1667404175],"type":"Point"}
}