{
  "type": "Feature",
  "properties": {
    "addr:full":"2025 Spinks Rd Kingsville ON N9Y 2E5",
    "addr:housenumber":"2025",
    "addr:postcode":"n9y 2e5",
    "addr:street":"Spinks Rd",
    "iso:country":"CA",
    "sg:address":"2025 Spinks Rd",
    "sg:city":"Kingsville",
    "sg:classifiers":[
        {
            "category":"Farming",
            "subcategory":"Nursery",
            "type":"Manufacturing & Wholesale Goods"
        }
    ],
    "sg:phone":"+1 519 322 5995",
    "sg:postcode":"N9Y 2E5",
    "sg:province":"ON",
    "sg:tags":[
        "steel",
        "greenhouse"
    ],
    "wof:name":"South Essex Fabricating Inc",
    "wof:placetype":"venue"
},
  "geometry": {"coordinates":[-82.65650939939999,42.0644645691],"type":"Point"}
}