{
  "type": "Feature",
  "properties": {
    "addr:full":"7904 101 Ave Fort St John BC V1J 2A3",
    "addr:housenumber":"7904",
    "addr:postcode":"v1j 2a3",
    "addr:street":"101 Ave",
    "iso:country":"CA",
    "sg:address":"7904 101 Ave",
    "sg:city":"Fort St John",
    "sg:classifiers":[
        {
            "category":"Building & Trades",
            "subcategory":"Construction",
            "type":"Services"
        }
    ],
    "sg:phone":"+1 250 785 0033",
    "sg:postcode":"V1J 2A3",
    "sg:province":"BC",
    "sg:tags":[
        "pipe",
        "line",
        "contractor"
    ],
    "wof:name":"Macro Industries Inc",
    "wof:placetype":"venue"
},
  "geometry": {"coordinates":[-120.825286865,56.2476806641],"type":"Point"}
}