{
  "type": "Feature",
  "properties": {
    "addr:full":"5004 121 Ave NW Edmonton AB T5W 1N3",
    "addr:housenumber":"5004",
    "addr:postcode":"t5w 1n3",
    "addr:street":"121 Ave Nw",
    "iso:country":"CA",
    "sg:address":"5004 121 Ave NW",
    "sg:city":"Edmonton",
    "sg:classifiers":[
        {
            "category":"Organizations",
            "subcategory":"Religious Organization",
            "type":"Services"
        }
    ],
    "sg:phone":"+1 780 475 5550",
    "sg:postcode":"T5W 1N3",
    "sg:province":"AB",
    "sg:tags":[
        "church"
    ],
    "wof:name":"Jehovah's Witnesses",
    "wof:placetype":"venue"
},
  "geometry": {"coordinates":[-113.418587,53.575253],"type":"Point"}
}