{
  "type": "Feature",
  "properties": {
    "addr:full":"442 Rte DE L'Eglise # 7 Saint-Jean-Port-Joli QC G0R 3G0",
    "addr:housenumber":"442",
    "addr:postcode":"g0r 3g0",
    "addr:street":"Rte De L'Eglise # 7",
    "iso:country":"CA",
    "sg:address":"442 Rte DE L'Eglise # 7",
    "sg:city":"Saint-Jean-Port-Joli",
    "sg:classifiers":[
        {
            "category":"Retail",
            "subcategory":"Veterinary Services",
            "type":"Services"
        }
    ],
    "sg:phone":"+1 418 598 7035",
    "sg:postcode":"G0R 3G0",
    "sg:province":"QC",
    "sg:tags":[
        "veterinarian"
    ],
    "wof:name":"Bureau Veterinaire L'Islet",
    "wof:placetype":"venue"
},
  "geometry": {"coordinates":[-70.26676940919999,47.2121009827],"type":"Point"}
}