{
  "type": "Feature",
  "properties": {
    "addr:full":"1579 9th Ave Prince George BC V2L 3R8",
    "addr:housenumber":"1579",
    "addr:postcode":"v2l 3r8",
    "addr:street":"9Th Ave",
    "iso:country":"CA",
    "sg:address":"1579 9th Ave",
    "sg:city":"Prince George",
    "sg:classifiers":[
        {
            "category":"Manufacturing",
            "subcategory":"Lumber",
            "type":"Manufacturing & Wholesale Goods"
        }
    ],
    "sg:phone":"+1 250 562 2628",
    "sg:postcode":"V2L 3R8",
    "sg:province":"BC",
    "sg:tags":[
        "forester"
    ],
    "wof:name":"Timberline Forest Inventory",
    "wof:placetype":"venue"
},
  "geometry": {"coordinates":[-122.754311,53.913494],"type":"Point"}
}