{
  "type": "Feature",
  "properties": {
    "iso:country":"CA",
    "sg:city":"Saskatoon",
    "sg:classifiers":[
        {
            "category":"Health Services",
            "subcategory":"Doctor",
            "type":"Services"
        }
    ],
    "sg:phone":"+1 306 933 3233",
    "sg:postcode":"S7K 5S6",
    "sg:province":"SK",
    "sg:tags":[
        "dentist"
    ],
    "wof:name":"Taylor, Monica DDS",
    "wof:placetype":"venue"
},
  "geometry": {"coordinates":[-106.64041137700001,52.1674613953],"type":"Point"}
}