{
  "type": "Feature",
  "properties": {
    "addr:full":"Oakville ON L6J 7J9",
    "addr:postcode":"l6j 7j9",
    "iso:country":"CA",
    "sg:city":"Oakville",
    "sg:classifiers":[
        {
            "category":"Building & Trades",
            "subcategory":"Plumbing",
            "type":"Services"
        }
    ],
    "sg:phone":"+1 905 829 1705",
    "sg:postcode":"L6J 7J9",
    "sg:province":"ON",
    "sg:tags":[
        "contractor"
    ],
    "wof:name":"A C Mechanical Contractors Ltd",
    "wof:placetype":"venue"
},
  "geometry": {"coordinates":[-79.666664,43.504349],"type":"Point"}
}