{
  "type": "Feature",
  "properties": {
    "addr:full":"17338 106A Ave NW Edmonton AB T5S 1E6",
    "addr:housenumber":"17338",
    "addr:postcode":"t5s 1e6",
    "addr:street":"106A Ave Nw",
    "iso:country":"CA",
    "sg:address":"17338 106A Ave NW",
    "sg:city":"Edmonton",
    "sg:classifiers":[
        {
            "category":"Wholesale",
            "subcategory":"Chemicals & Plastics",
            "type":"Manufacturing & Wholesale Goods"
        }
    ],
    "sg:phone":"+1 780 414 1463",
    "sg:postcode":"T5S 1E6",
    "sg:province":"AB",
    "sg:tags":[
        "oxygen"
    ],
    "wof:name":"O-Gen Industries Inc",
    "wof:placetype":"venue"
},
  "geometry": {"coordinates":[-113.620323,53.552048],"type":"Point"}
}