{
  "type": "Feature",
  "properties": {
    "addr:full":"877 Alness St North York ON M3J 2X4",
    "addr:housenumber":"877",
    "addr:postcode":"m3j 2x4",
    "addr:street":"Alness St",
    "iso:country":"CA",
    "sg:address":"877 Alness St",
    "sg:city":"North York",
    "sg:classifiers":[
        {
            "category":"Shopping",
            "type":"Retail Goods"
        }
    ],
    "sg:phone":"+1 416 661 5079",
    "sg:postcode":"M3J 2X4",
    "sg:province":"ON",
    "sg:tags":[
        "picture",
        "frame"
    ],
    "wof:name":"G & H Gallery Fine Arts",
    "wof:placetype":"venue"
},
  "geometry": {"coordinates":[-79.4752960205,43.7792854309],"type":"Point"}
}