{
  "type": "Feature",
  "properties": {
    "addr:full":"1398 Cartwright St Vancouver BC V6H 3R8",
    "addr:housenumber":"1398",
    "addr:postcode":"v6h 3r8",
    "addr:street":"Cartwright St",
    "iso:country":"CA",
    "sg:address":"1398 Cartwright St",
    "sg:city":"Vancouver",
    "sg:classifiers":[
        {
            "category":"Cinema",
            "subcategory":"Movie Theater",
            "type":"Entertainment"
        }
    ],
    "sg:phone":"+1 604 681 6330",
    "sg:postcode":"V6H 3R8",
    "sg:province":"BC",
    "sg:tags":[
        "association"
    ],
    "wof:name":"Vancouver International Comedy",
    "wof:placetype":"venue"
},
  "geometry": {"coordinates":[-123.135109,49.269962],"type":"Point"}
}