{
  "type": "Feature",
  "properties": {
    "addr:full":"100 Steeles Ave W # 10 Thornhill ON L4J 7Y1",
    "addr:housenumber":"100",
    "addr:postcode":"l4j 7y1",
    "addr:street":"Steeles Ave W # 10",
    "iso:country":"CA",
    "sg:address":"100 Steeles Ave W # 10",
    "sg:city":"Thornhill",
    "sg:classifiers":[
        {
            "category":"Health Services",
            "subcategory":"Doctor",
            "type":"Services"
        }
    ],
    "sg:phone":"+1 905 707 8682",
    "sg:postcode":"L4J 7Y1",
    "sg:province":"ON",
    "sg:tags":[
        "physician",
        "surgeon"
    ],
    "wof:name":"Lai, Albert MD",
    "wof:placetype":"venue"
},
  "geometry": {"coordinates":[-79.424629,43.797218],"type":"Point"}
}