{
  "type": "Feature",
  "properties": {
    "addr:full":"4105 Bridgeport Dr Jordan Station ON L0R 1S0",
    "addr:housenumber":"4105",
    "addr:postcode":"l0r 1s0",
    "addr:street":"Bridgeport Dr",
    "iso:country":"CA",
    "sg:address":"4105 Bridgeport Dr",
    "sg:city":"Jordan Station",
    "sg:classifiers":[
        {
            "category":"Organizations",
            "subcategory":"Religious Organization",
            "type":"Services"
        }
    ],
    "sg:phone":"+1 905 562 4454",
    "sg:postcode":"L0R 1S0",
    "sg:province":"ON",
    "sg:tags":[
        "church"
    ],
    "wof:name":"Jordan Station United Church",
    "wof:placetype":"venue"
},
  "geometry": {"coordinates":[-79.367531,43.161903],"type":"Point"}
}