{
  "type": "Feature",
  "properties": {
    "addr:full":"91 Hampton St E Macgregor MB R0H 0R0",
    "addr:housenumber":"91",
    "addr:postcode":"r0h 0r0",
    "addr:street":"Hampton St",
    "iso:country":"CA",
    "sg:address":"91 Hampton St E",
    "sg:city":"Macgregor",
    "sg:classifiers":[
        {
            "category":"Home & Garden",
            "subcategory":"Carpets & Floor Coverings",
            "type":"Retail Goods"
        }
    ],
    "sg:phone":"+1 204 685 2158",
    "sg:postcode":"R0H 0R0",
    "sg:province":"MB",
    "sg:tags":[
        "dealer",
        "rug"
    ],
    "wof:name":"Mac Gregor Carpets",
    "wof:placetype":"venue"
},
  "geometry": {"coordinates":[-98.779297,49.965221],"type":"Point"}
}