{
  "type": "Feature",
  "properties": {
    "addr:full":"85 Grand Beach Rd S Grand Marais MB R0E 0T0",
    "addr:housenumber":"85",
    "addr:postcode":"r0e 0t0",
    "addr:street":"Grand Beach Rd S",
    "iso:country":"CA",
    "sg:address":"85 Grand Beach Rd S",
    "sg:city":"Grand Marais",
    "sg:classifiers":[
        {
            "category":"Restaurant",
            "type":"Food & Drink"
        }
    ],
    "sg:phone":"+1 204 754 2106",
    "sg:postcode":"R0E 0T0",
    "sg:province":"MB",
    "wof:name":"Lanky's",
    "wof:placetype":"venue"
},
  "geometry": {"coordinates":[-96.61734800000001,50.54047],"type":"Point"}
}