{
  "type": "Feature",
  "properties": {
    "iso:country":"CA",
    "sg:address":"Monte Lake Rd",
    "sg:city":"Monte Lake",
    "sg:classifiers":[
        {
            "category":"Manufacturing",
            "subcategory":"Motor Vehicles & Parts",
            "type":"Manufacturing & Wholesale Goods"
        }
    ],
    "sg:phone":"+1 250 375 2525",
    "sg:postcode":"V0E 2N0",
    "sg:province":"BC",
    "sg:tags":[
        "automobile"
    ],
    "wof:name":"Chevy Heaven",
    "wof:placetype":"venue"
},
  "geometry": {"coordinates":[-119.835281372,50.5233154297],"type":"Point"}
}