{
  "type": "Feature",
  "properties": {
    "addr:full":"North York ON M3H 5X2",
    "addr:postcode":"m3h 5x2",
    "iso:country":"CA",
    "sg:city":"North York",
    "sg:classifiers":[
        {
            "category":"Wholesale",
            "subcategory":"Non-durable Goods",
            "type":"Manufacturing & Wholesale Goods"
        }
    ],
    "sg:phone":"+1 416 663 8558",
    "sg:postcode":"M3H 5X2",
    "sg:province":"ON",
    "wof:name":"Tokoloshe Inc",
    "wof:placetype":"venue"
},
  "geometry": {"coordinates":[-79.467018,43.768482],"type":"Point"}
}