{
  "type": "Feature",
  "properties": {
    "addr:full":"3050 Mountain Hwy North Vancouver BC V7J 2P1",
    "addr:housenumber":"3050",
    "addr:postcode":"v7j 2p1",
    "addr:street":"Mountain Hwy",
    "iso:country":"CA",
    "sg:address":"3050 Mountain Hwy",
    "sg:city":"North Vancouver",
    "sg:classifiers":[
        {
            "category":"Wholesale",
            "subcategory":"Photographic Equipment",
            "type":"Manufacturing & Wholesale Goods"
        }
    ],
    "sg:phone":"+1 604 985 4020",
    "sg:postcode":"V7J 2P1",
    "sg:province":"BC",
    "sg:tags":[
        "motion",
        "picture",
        "supply"
    ],
    "wof:name":"International Military Surplus",
    "wof:placetype":"venue"
},
  "geometry": {"coordinates":[-123.03797900000001,49.336662],"type":"Point"}
}