{
  "type": "Feature",
  "properties": {
    "addr:full":"24 Harbourfront Cres Louisbourg NS B1C 1C4",
    "addr:housenumber":"24",
    "addr:postcode":"b1c 1c4",
    "addr:street":"Harbourfront Cres",
    "iso:country":"CA",
    "sg:address":"24 Harbourfront Cres",
    "sg:city":"Louisbourg",
    "sg:classifiers":[
        {
            "category":"Travel",
            "subcategory":"Campground",
            "type":"Entertainment"
        }
    ],
    "sg:phone":"+1 902 733 3631",
    "sg:postcode":"B1C 1C4",
    "sg:province":"NS",
    "wof:name":"Louisbourg Rv Park & Campgrnd",
    "wof:placetype":"venue"
},
  "geometry": {"coordinates":[-59.9709358215,45.9201698303],"type":"Point"}
}