{
  "type": "Feature",
  "properties": {
    "addr:full":"19238 Yonge St Holland Landing ON L9N 1L4",
    "addr:housenumber":"19238",
    "addr:postcode":"l9n 1l4",
    "addr:street":"Yonge St",
    "iso:country":"CA",
    "sg:address":"19238 Yonge St",
    "sg:city":"Holland Landing",
    "sg:classifiers":[
        {
            "category":"Building & Trades",
            "subcategory":"Construction",
            "type":"Services"
        }
    ],
    "sg:phone":"+1 905 895 8144",
    "sg:postcode":"L9N 1L4",
    "sg:province":"ON",
    "sg:tags":[
        "general",
        "contractor"
    ],
    "wof:name":"Rjb Construction Ltd",
    "wof:placetype":"venue"
},
  "geometry": {"coordinates":[-79.490669,44.097221],"type":"Point"}
}