{
  "type": "Feature",
  "properties": {
    "addr:full":"20468 Lougheed Hwy # 4 Maple Ridge BC V2X 2P8",
    "addr:housenumber":"20468",
    "addr:postcode":"v2x 2p8",
    "addr:street":"Lougheed Hwy # 4",
    "iso:country":"CA",
    "sg:address":"20468 Lougheed Hwy # 4",
    "sg:city":"Maple Ridge",
    "sg:classifiers":[
        {
            "category":"Retail",
            "subcategory":"Auto Rental",
            "type":"Services"
        }
    ],
    "sg:phone":"+1 604 460 1888",
    "sg:postcode":"V2X 2P8",
    "sg:province":"BC",
    "sg:tags":[
        "renting",
        "automobile"
    ],
    "wof:name":"Enterprise Rent-A-Car",
    "wof:placetype":"venue"
},
  "geometry": {"coordinates":[-122.654076,49.218613],"type":"Point"}
}