{
  "type": "Feature",
  "properties": {
    "addr:full":"725 Main St E Milton ON L9T 3Z3",
    "addr:housenumber":"725",
    "addr:postcode":"l9t 3z3",
    "addr:street":"Main St E",
    "iso:country":"CA",
    "sg:address":"725 Main St E",
    "sg:city":"Milton",
    "sg:classifiers":[
        {
            "category":"Professional",
            "subcategory":"Business Services",
            "type":"Services"
        }
    ],
    "sg:phone":"+1 905 878 2336",
    "sg:postcode":"L9T 3Z3",
    "sg:province":"ON",
    "sg:tags":[
        "packaging"
    ],
    "wof:name":"Horizon Packaging",
    "wof:placetype":"venue"
},
  "geometry": {"coordinates":[-79.87172700000001,43.523949],"type":"Point"}
}