{
  "type": "Feature",
  "properties": {
    "iso:country":"CA",
    "sg:address":"1067 Ontario St",
    "sg:city":"Stratford",
    "sg:classifiers":[
        {
            "category":"Shopping",
            "type":"Retail Goods"
        }
    ],
    "sg:phone":"+1 519 275 3998",
    "sg:postcode":"N5A 6W6",
    "sg:province":"ON",
    "sg:tags":[
        "telephone",
        "cellular"
    ],
    "wof:name":"Bell World",
    "wof:placetype":"venue"
},
  "geometry": {"coordinates":[-80.94510650629999,43.3706359863],"type":"Point"}
}