{
  "type": "Feature",
  "properties": {
    "addr:full":"4430 Ladysmith Ave Ladysmith BC V9G 1A7",
    "addr:housenumber":"4430",
    "addr:postcode":"v9g 1a7",
    "addr:street":"Ladysmith Ave",
    "iso:country":"CA",
    "sg:address":"4430 Ladysmith Ave",
    "sg:city":"Ladysmith",
    "sg:classifiers":[
        {
            "category":"Recreation",
            "subcategory":"Marina",
            "type":"Entertainment"
        }
    ],
    "sg:phone":"+1 250 714 8469",
    "sg:postcode":"V9G 1A7",
    "sg:province":"BC",
    "sg:tags":[
        "repairing",
        "boat"
    ],
    "wof:name":"Steamers Marine Repair Inc",
    "wof:placetype":"venue"
},
  "geometry": {"coordinates":[-123.820541382,48.9973564148],"type":"Point"}
}