{
  "type": "Feature",
  "properties": {
    "addr:full":"31441 Hwy 2 Richmond PE C0B 1Y0",
    "addr:housenumber":"31441",
    "addr:postcode":"c0b 1y0",
    "addr:street":"Hwy 2",
    "iso:country":"CA",
    "sg:address":"31441 Hwy 2",
    "sg:city":"Richmond",
    "sg:classifiers":[
        {
            "category":"Autos & Motor Vehicles",
            "subcategory":"Fuel & Gas Station",
            "type":"Retail Goods"
        }
    ],
    "sg:phone":"+1 902 854 2333",
    "sg:postcode":"C0B 1Y0",
    "sg:province":"PE",
    "sg:tags":[
        "oil"
    ],
    "wof:name":"Mac Arthur's Petro-Canada",
    "wof:placetype":"venue"
},
  "geometry": {"coordinates":[-63.991234,46.505146],"type":"Point"}
}