{
  "type": "Feature",
  "properties": {
    "addr:full":"100 Rue Principale S # 17 Maniwaki QC J9E 3L4",
    "addr:housenumber":"100",
    "addr:postcode":"j9e 3l4",
    "addr:street":"Rue Principale S # 17",
    "iso:country":"CA",
    "sg:address":"100 Rue Principale S # 17",
    "sg:city":"Maniwaki",
    "sg:classifiers":[
        {
            "category":"Shopping",
            "subcategory":"Department Store",
            "type":"Retail Goods"
        }
    ],
    "sg:phone":"+1 819 441 1919",
    "sg:postcode":"J9E 3L4",
    "sg:province":"QC",
    "sg:tags":[
        "shop"
    ],
    "wof:name":"Dollar En Folie",
    "wof:placetype":"venue"
},
  "geometry": {"coordinates":[-75.98198699949999,46.3759117126],"type":"Point"}
}