{
  "type": "Feature",
  "properties": {
    "addr:full":"1770 White Cedar Dr Pickering ON L1V 6Z1",
    "addr:housenumber":"1770",
    "addr:postcode":"l1v 6z1",
    "addr:street":"White Cedar Dr",
    "iso:country":"CA",
    "sg:address":"1770 White Cedar Dr",
    "sg:city":"Pickering",
    "sg:classifiers":[
        {
            "category":"Shopping",
            "subcategory":"Computers & Home Electronics",
            "type":"Retail Goods"
        }
    ],
    "sg:phone":"+1 905 831 3793",
    "sg:postcode":"L1V 6Z1",
    "sg:province":"ON",
    "sg:tags":[
        "software"
    ],
    "wof:name":"Orangesoft",
    "wof:placetype":"venue"
},
  "geometry": {"coordinates":[-79.13098100000001,43.823715],"type":"Point"}
}