{
  "type": "Feature",
  "properties": {
    "iso:country":"CA",
    "sg:city":"Dorval",
    "sg:classifiers":[
        {
            "category":"Shopping",
            "subcategory":"Computers & Home Electronics",
            "type":"Retail Goods"
        }
    ],
    "sg:phone":"+1 514 683 7655",
    "sg:postcode":"H9P 2P2",
    "sg:province":"QC",
    "sg:tags":[
        "parts",
        "supply"
    ],
    "wof:name":"A-Plus Systems Canada Ltd",
    "wof:placetype":"venue"
},
  "geometry": {"coordinates":[-73.778824,45.481869],"type":"Point"}
}