{
  "type": "Feature",
  "properties": {
    "iso:country":"CA",
    "sg:address":"3 Blackmarsh Rd",
    "sg:city":"St. John's",
    "sg:classifiers":[
        {
            "category":"Shopping",
            "subcategory":"Computers & Home Electronics",
            "type":"Retail Goods"
        }
    ],
    "sg:phone":"+1 709 579 2222",
    "sg:postcode":"A1E 1S2",
    "sg:province":"NL",
    "sg:tags":[
        "high",
        "fidelity",
        "stereophonic",
        "telephone",
        "cellular"
    ],
    "wof:name":"West End Electronics Ltd",
    "wof:placetype":"venue"
},
  "geometry": {"coordinates":[-52.7268562317,47.5543327332],"type":"Point"}
}