{
  "type": "Feature",
  "properties": {
    "addr:full":"Vancouver BC V6B 1S5",
    "addr:postcode":"v6b 1s5",
    "iso:country":"CA",
    "sg:city":"Vancouver",
    "sg:classifiers":[
        {
            "category":"Wholesale",
            "subcategory":"Durable Goods & Equipment",
            "type":"Manufacturing & Wholesale Goods"
        }
    ],
    "sg:phone":"+1 604 689 8299",
    "sg:postcode":"V6B 1S5",
    "sg:province":"BC",
    "sg:tags":[
        "exporter"
    ],
    "wof:name":"Richon Enterprises Ltd",
    "wof:placetype":"venue"
},
  "geometry": {"coordinates":[-123.108391,49.281391],"type":"Point"}
}