{
  "type": "Feature",
  "properties": {
    "iso:country":"CA",
    "sg:address":"269 Fielding Rd",
    "sg:city":"Lively",
    "sg:classifiers":[
        {
            "category":"Building & Trades",
            "subcategory":"Equipment Rental",
            "type":"Services"
        }
    ],
    "sg:phone":"+1 705 682 1120",
    "sg:postcode":"P3Y 1L8",
    "sg:province":"ON",
    "sg:tags":[
        "yard"
    ],
    "wof:name":"Equipment North Inc",
    "wof:placetype":"venue"
},
  "geometry": {"coordinates":[-81.0976409912,46.4328804016],"type":"Point"}
}