{
  "type": "Feature",
  "properties": {
    "addr:full":"1940 Deer Run Rd Leamington ON N8H 3V7",
    "addr:housenumber":"1940",
    "addr:postcode":"n8h 3v7",
    "addr:street":"Deer Run Rd",
    "iso:country":"CA",
    "sg:address":"1940 Deer Run Rd",
    "sg:city":"Leamington",
    "sg:classifiers":[
        {
            "category":"Professional",
            "subcategory":"Engineering",
            "type":"Services"
        }
    ],
    "sg:phone":"+1 519 326 6161",
    "sg:postcode":"N8H 3V7",
    "sg:province":"ON",
    "sg:tags":[
        "engineer"
    ],
    "wof:name":"Bruce D Crozier Engineering",
    "wof:placetype":"venue"
},
  "geometry": {"coordinates":[-82.504677,42.058296],"type":"Point"}
}