{
  "type": "Feature",
  "properties": {
    "addr:full":"20 Alpine Ave Winnipeg MB R2M 0Y5",
    "addr:housenumber":"20",
    "addr:postcode":"r2m 0y5",
    "addr:street":"Alpine Ave",
    "iso:country":"CA",
    "sg:address":"20 Alpine Ave",
    "sg:city":"Winnipeg",
    "sg:classifiers":[
        {
            "category":"Travel",
            "subcategory":"Hotels & Motels",
            "type":"Entertainment"
        }
    ],
    "sg:phone":"+1 204 255 6000",
    "sg:postcode":"R2M 0Y5",
    "sg:province":"MB",
    "wof:name":"Travelodge Winnipeg East",
    "wof:placetype":"venue"
},
  "geometry": {"coordinates":[-97.10050200000001,49.856236],"type":"Point"}
}