{
  "type": "Feature",
  "properties": {
    "addr:full":"PO Box 18130 Rpo Kerrisdale Vancouver BC V6M 4L3",
    "addr:housenumber":"po box 18130",
    "addr:postcode":"v6m 4l3",
    "iso:country":"CA",
    "sg:address":"PO Box 18130 Rpo Kerrisdale",
    "sg:city":"Vancouver",
    "sg:classifiers":[
        {
            "category":"Building & Trades",
            "subcategory":"Landscaping Services",
            "type":"Services"
        }
    ],
    "sg:phone":"+1 604 731 3436",
    "sg:postcode":"V6M 4L3",
    "sg:province":"BC",
    "sg:tags":[
        "lawn",
        "maintenance",
        "grounds"
    ],
    "wof:name":"Chauncey Gardener",
    "wof:placetype":"venue"
},
  "geometry": {"coordinates":[-123.11403656,49.2604408264],"type":"Point"}
}