{
  "type": "Feature",
  "properties": {
    "addr:full":"393 Danforth Ave Toronto ON M4K 1P1",
    "addr:housenumber":"393",
    "addr:postcode":"m4k 1p1",
    "addr:street":"Danforth Ave",
    "iso:country":"CA",
    "sg:address":"393 Danforth Ave",
    "sg:city":"Toronto",
    "sg:classifiers":[
        {
            "category":"Personal",
            "subcategory":"Beauty Salon",
            "type":"Services"
        }
    ],
    "sg:phone":"+1 416 778 9585",
    "sg:postcode":"M4K 1P1",
    "sg:province":"ON",
    "wof:name":"Alan Davis Salon",
    "wof:placetype":"venue"
},
  "geometry": {"coordinates":[-79.352074,43.677383],"type":"Point"}
}