{
  "type": "Feature",
  "properties": {
    "addr:full":"499 Pender St E Vancouver BC V6A 1V2",
    "addr:housenumber":"499",
    "addr:postcode":"v6a 1v2",
    "addr:street":"Pender St E",
    "iso:country":"CA",
    "sg:address":"499 Pender St E",
    "sg:city":"Vancouver",
    "sg:classifiers":[
        {
            "category":"Social Services",
            "type":"Services"
        }
    ],
    "sg:phone":"+1 604 255 3311",
    "sg:postcode":"V6A 1V2",
    "sg:province":"BC",
    "sg:tags":[
        "organization",
        "welfare"
    ],
    "wof:name":"Chinese Social Development",
    "wof:placetype":"venue"
},
  "geometry": {"coordinates":[-123.093582153,49.2803421021],"type":"Point"}
}