{
  "type": "Feature",
  "properties": {
    "addr:full":"705 Boul Jacques-Cartier N Sherbrooke QC J1J 4C8",
    "addr:housenumber":"705",
    "addr:postcode":"j1j 4c8",
    "addr:street":"Boul Jacques-Cartier N",
    "iso:country":"CA",
    "sg:address":"705 Boul Jacques-Cartier N",
    "sg:city":"Sherbrooke",
    "sg:classifiers":[
        {
            "category":"Food & Beverages",
            "subcategory":"Groceries & Convenience Stores",
            "type":"Retail Goods"
        }
    ],
    "sg:phone":"+1 819 822 4533",
    "sg:postcode":"J1J 4C8",
    "sg:province":"QC",
    "wof:name":"Depan-Escompte Couche-Tard",
    "wof:placetype":"venue"
},
  "geometry": {"coordinates":[-71.918655,45.40974],"type":"Point"}
}