{
  "type": "Feature",
  "properties": {
    "addr:full":"3272 Creekford Rd Westbrook ON K7P 2Z8",
    "addr:housenumber":"3272",
    "addr:postcode":"k7p 2z8",
    "addr:street":"Creekford Rd",
    "iso:country":"CA",
    "sg:address":"3272 Creekford Rd",
    "sg:city":"Westbrook",
    "sg:classifiers":[
        {
            "category":"Building & Trades",
            "subcategory":"Plumbing",
            "type":"Services"
        }
    ],
    "sg:phone":"+1 613 634 7298",
    "sg:postcode":"K7P 2Z8",
    "sg:province":"ON",
    "sg:tags":[
        "mechanical",
        "contractor"
    ],
    "wof:name":"Allen Mechanical",
    "wof:placetype":"venue"
},
  "geometry": {"coordinates":[-76.608864,44.278053],"type":"Point"}
}