{
  "type": "Feature",
  "properties": {
    "addr:full":"175 the West Mall Etobicoke ON M9C 1C2",
    "addr:housenumber":"175",
    "addr:postcode":"m9c 1c2",
    "addr:street":"The West Mall",
    "iso:country":"CA",
    "sg:address":"175 the West Mall",
    "sg:city":"Etobicoke",
    "sg:classifiers":[
        {
            "category":"Professional",
            "subcategory":"Business Services",
            "type":"Services"
        }
    ],
    "sg:phone":"+1 905 634 8003",
    "sg:postcode":"M9C 1C2",
    "sg:province":"ON",
    "sg:tags":[
        "fund",
        "promotion",
        "raising"
    ],
    "wof:name":"Town Publishing & Productions",
    "wof:placetype":"venue"
},
  "geometry": {"coordinates":[-79.5594863892,43.6234588623],"type":"Point"}
}