{
  "type": "Feature",
  "properties": {
    "addr:full":"45920 First Ave Chilliwack BC V2P 7K1",
    "addr:housenumber":"45920",
    "addr:postcode":"v2p 7k1",
    "addr:street":"First Ave",
    "iso:country":"CA",
    "sg:address":"45920 First Ave",
    "sg:city":"Chilliwack",
    "sg:classifiers":[
        {
            "category":"Bars & Pubs",
            "type":"Food & Drink"
        }
    ],
    "sg:phone":"+1 604 795 4788",
    "sg:postcode":"V2P 7K1",
    "sg:province":"BC",
    "wof:name":"Blue Diamond Lounge",
    "wof:placetype":"venue"
},
  "geometry": {"coordinates":[-121.953796387,49.1686820984],"type":"Point"}
}