{
  "type": "Feature",
  "properties": {
    "addr:full":"5 Luther Pl Mount Pearl NL A1N 3E7",
    "addr:housenumber":"5",
    "addr:postcode":"a1n 3e7",
    "addr:street":"Luther Pl",
    "iso:country":"CA",
    "sg:address":"5 Luther Pl",
    "sg:city":"Mount Pearl",
    "sg:classifiers":[
        {
            "category":"Building & Trades",
            "subcategory":"Plumbing",
            "type":"Services"
        }
    ],
    "sg:phone":"+1 709 364 5320",
    "sg:postcode":"A1N 3E7",
    "sg:province":"NL",
    "sg:tags":[
        "contractor"
    ],
    "wof:name":"Vivian's Plumbing & Heating",
    "wof:placetype":"venue"
},
  "geometry": {"coordinates":[-52.800861,47.525169],"type":"Point"}
}