{
  "type": "Feature",
  "properties": {
    "addr:full":"261123 Conc 18 Hanover ON N4N 3B8",
    "addr:housenumber":"261123;18",
    "addr:postcode":"n4n 3b8",
    "addr:street":"Conc",
    "iso:country":"CA",
    "sg:address":"261123 Conc 18",
    "sg:city":"Hanover",
    "sg:classifiers":[
        {
            "category":"Government",
            "subcategory":"Office",
            "type":"Public Place"
        }
    ],
    "sg:phone":"+1 519 364 1255",
    "sg:postcode":"N4N 3B8",
    "sg:province":"ON",
    "sg:tags":[
        "campground",
        "village"
    ],
    "wof:name":"Saugeen Valley Conservation",
    "wof:placetype":"venue"
},
  "geometry": {"coordinates":[-81.015869,44.156658],"type":"Point"}
}