{
  "type": "Feature",
  "properties": {
    "addr:full":"9908 Franklin Ave Fort Mcmurray AB T9H 2K5",
    "addr:housenumber":"9908",
    "addr:postcode":"t9h 2k5",
    "addr:street":"Franklin Ave",
    "iso:country":"CA",
    "sg:address":"9908 Franklin Ave",
    "sg:city":"Fort Mcmurray",
    "sg:classifiers":[
        {
            "category":"Insurance",
            "subcategory":"Insurance Agent",
            "type":"Services"
        }
    ],
    "sg:phone":"+1 780 743 8233",
    "sg:postcode":"T9H 2K5",
    "sg:province":"AB",
    "sg:tags":[
        "consultant",
        "accountant"
    ],
    "wof:name":"Fort Mc Murray Tax & Accountng",
    "wof:placetype":"venue"
},
  "geometry": {"coordinates":[-111.379227,56.726929],"type":"Point"}
}