{
  "type": "Feature",
  "properties": {
    "addr:full":"92 Temple Bay Winnipeg MB R3T 2T9",
    "addr:housenumber":"92",
    "addr:postcode":"r3t 2t9",
    "addr:street":"Temple Bay",
    "iso:country":"CA",
    "sg:address":"92 Temple Bay",
    "sg:city":"Winnipeg",
    "sg:classifiers":[
        {
            "category":"Education",
            "subcategory":"Special Training",
            "type":"Public Place"
        }
    ],
    "sg:phone":"+1 204 291 4043",
    "sg:postcode":"R3T 2T9",
    "sg:province":"MB",
    "sg:tags":[
        "instruction",
        "driving"
    ],
    "wof:name":"A-Fort Richmond Driving School",
    "wof:placetype":"venue"
},
  "geometry": {"coordinates":[-97.143463,49.800072],"type":"Point"}
}