{
  "type": "Feature",
  "properties": {
    "addr:full":"1311 Trans Canada Way SE Medicine Hat AB T1B 1J1",
    "addr:housenumber":"1311",
    "addr:postcode":"t1b 1j1",
    "addr:street":"Trans Canada Way Se",
    "iso:country":"CA",
    "sg:address":"1311 Trans Canada Way SE",
    "sg:city":"Medicine Hat",
    "sg:classifiers":[
        {
            "category":"Home & Garden",
            "subcategory":"Building Materials",
            "type":"Retail Goods"
        }
    ],
    "sg:phone":"+1 403 527 5588",
    "sg:postcode":"T1B 1J1",
    "sg:province":"AB",
    "sg:tags":[
        "paint"
    ],
    "wof:name":"Cloverdale Paint",
    "wof:placetype":"venue"
},
  "geometry": {"coordinates":[-110.65784499999999,50.004158],"type":"Point"}
}