{
  "type": "Feature",
  "properties": {
    "addr:full":"5750 Grousewoods Cres North Vancouver BC V7R 4V8",
    "addr:housenumber":"5750",
    "addr:postcode":"v7r 4v8",
    "addr:street":"Grousewoods Cres",
    "iso:country":"CA",
    "sg:address":"5750 Grousewoods Cres",
    "sg:city":"North Vancouver",
    "sg:classifiers":[
        {
            "category":"Professional",
            "subcategory":"Management & Consulting",
            "type":"Services"
        }
    ],
    "sg:phone":"+1 604 983 2225",
    "sg:postcode":"V7R 4V8",
    "sg:province":"BC",
    "sg:tags":[
        "consultant",
        "business"
    ],
    "wof:name":"Rescom Consultants Ltd",
    "wof:placetype":"venue"
},
  "geometry": {"coordinates":[-123.09831200000001,49.367489],"type":"Point"}
}