{
  "type": "Feature",
  "properties": {
    "addr:full":"43 Prince Rupert Dr Stephenville NL A2N 3W8",
    "addr:housenumber":"43",
    "addr:postcode":"a2n 3w8",
    "addr:street":"Prince Rupert Dr",
    "iso:country":"CA",
    "sg:address":"43 Prince Rupert Dr",
    "sg:city":"Stephenville",
    "sg:classifiers":[
        {
            "category":"Autos & Motor Vehicles",
            "subcategory":"Automobile Sales",
            "type":"Retail Goods"
        }
    ],
    "sg:phone":"+1 709 643 5141",
    "sg:postcode":"A2N 3W8",
    "sg:province":"NL",
    "sg:tags":[
        "car",
        "dealer"
    ],
    "wof:name":"Dennis Chev Olds Pontiac Buick",
    "wof:placetype":"venue"
},
  "geometry": {"coordinates":[-58.5809173584,48.5463256836],"type":"Point"}
}