{
  "type": "Feature",
  "properties": {
    "addr:full":"11 Roy Blvd Brantford ON N3R 7K1",
    "addr:housenumber":"11",
    "addr:postcode":"n3r 7k1",
    "addr:street":"Roy Blvd",
    "iso:country":"CA",
    "sg:address":"11 Roy Blvd",
    "sg:city":"Brantford",
    "sg:classifiers":[
        {
            "category":"Retail",
            "subcategory":"Auto Repair",
            "type":"Services"
        }
    ],
    "sg:phone":"+1 519 759 0707",
    "sg:postcode":"N3R 7K1",
    "sg:province":"ON",
    "sg:tags":[
        "repairing",
        "automobile"
    ],
    "wof:name":"Transmissions & Gears",
    "wof:placetype":"venue"
},
  "geometry": {"coordinates":[-80.22586099999999,43.174767],"type":"Point"}
}