{
  "type": "Feature",
  "properties": {
    "addr:full":"68 Boul Cartier O # 202 Laval QC H7N 2H5",
    "addr:housenumber":"68",
    "addr:postcode":"h7n 2h5",
    "addr:street":"Boul Cartier O # 202",
    "iso:country":"CA",
    "sg:address":"68 Boul Cartier O # 202",
    "sg:city":"Laval",
    "sg:classifiers":[
        {
            "category":"Organizations",
            "subcategory":"Professional Association",
            "type":"Services"
        }
    ],
    "sg:phone":"+1 450 667 5187",
    "sg:postcode":"H7N 2H5",
    "sg:province":"QC",
    "wof:name":"Assn-Eclaireurs Baden-Powell",
    "wof:placetype":"venue"
},
  "geometry": {"coordinates":[-73.6897659302,45.5590705872],"type":"Point"}
}