{
  "type": "Feature",
  "properties": {
    "addr:full":"North York ON M3J 2B9",
    "addr:postcode":"m3j 2b9",
    "iso:country":"CA",
    "sg:city":"North York",
    "sg:classifiers":[
        {
            "category":"Wholesale",
            "subcategory":"Durable Goods & Equipment",
            "type":"Manufacturing & Wholesale Goods"
        }
    ],
    "sg:phone":"+1 416 383 0208",
    "sg:postcode":"M3J 2B9",
    "sg:province":"ON",
    "sg:tags":[
        "importer"
    ],
    "wof:name":"Develcorp Enterprise",
    "wof:placetype":"venue"
},
  "geometry": {"coordinates":[-79.4764175415,43.7631759644],"type":"Point"}
}