{
  "type": "Feature",
  "properties": {
    "iso:country":"CA",
    "sg:address":"1 Roy Jackson St",
    "sg:city":"St George",
    "sg:classifiers":[
        {
            "category":"Retail",
            "subcategory":"Laundry & Dry Cleaning",
            "type":"Services"
        }
    ],
    "sg:phone":"+1 506 755 6226",
    "sg:postcode":"E5C 3M8",
    "sg:province":"NB",
    "sg:tags":[
        "cleaners",
        "rug",
        "carpet"
    ],
    "wof:name":"Companys Coming Cleaning",
    "wof:placetype":"venue"
},
  "geometry": {"coordinates":[-66.8255691528,45.1293067932],"type":"Point"}
}