{
  "type": "Feature",
  "properties": {
    "addr:full":"Toronto ON M5R 2A9",
    "addr:postcode":"m5r 2a9",
    "iso:country":"CA",
    "sg:city":"Toronto",
    "sg:classifiers":[
        {
            "category":"Professional",
            "subcategory":"Management & Consulting",
            "type":"Services"
        }
    ],
    "sg:phone":"+1 416 975 1556",
    "sg:postcode":"M5R 2A9",
    "sg:province":"ON",
    "sg:tags":[
        "town",
        "city",
        "regional",
        "planner"
    ],
    "wof:name":"Planning Partnership",
    "wof:placetype":"venue"
},
  "geometry": {"coordinates":[-79.389915,43.671207],"type":"Point"}
}