{
  "type": "Feature",
  "properties": {
    "addr:full":"PO Box 141 Benalto AB T0M 0H0",
    "addr:housenumber":"po",
    "addr:postcode":"t0m 0h0",
    "addr:street":"Box 141 Benalto",
    "iso:country":"CA",
    "sg:address":"PO Box 141",
    "sg:city":"Benalto",
    "sg:classifiers":[
        {
            "category":"Wholesale",
            "subcategory":"Petroleum",
            "type":"Manufacturing & Wholesale Goods"
        }
    ],
    "sg:phone":"+1 403 746 3230",
    "sg:postcode":"T0M 0H0",
    "sg:province":"AB",
    "sg:tags":[
        "pipe",
        "company",
        "oil",
        "line"
    ],
    "wof:name":"Talisman Energy Inc",
    "wof:placetype":"venue"
},
  "geometry": {"coordinates":[-114.275513,52.30862],"type":"Point"}
}