{
  "type": "Feature",
  "properties": {
    "addr:full":"North York ON M3J 2N8",
    "addr:postcode":"m3j 2n8",
    "iso:country":"CA",
    "sg:city":"North York",
    "sg:classifiers":[
        {
            "category":"Home & Garden",
            "subcategory":"Furniture",
            "type":"Retail Goods"
        }
    ],
    "sg:phone":"+1 416 736 7558",
    "sg:postcode":"M3J 2N8",
    "sg:province":"ON",
    "wof:name":"European Furniture Warehouse",
    "wof:placetype":"venue"
},
  "geometry": {"coordinates":[-79.49364471440001,43.7750930786],"type":"Point"}
}