{
  "type": "Feature",
  "properties": {
    "iso:country":"CA",
    "sg:address":"612 8 Ave SW",
    "sg:city":"Calgary",
    "sg:classifiers":[
        {
            "category":"Cinema",
            "subcategory":"Movie Theater",
            "type":"Entertainment"
        }
    ],
    "sg:phone":"+1 403 265 0120",
    "sg:postcode":"T2P 1G4",
    "sg:province":"AB",
    "wof:name":"Uptown Stage & Screen",
    "wof:placetype":"venue"
},
  "geometry": {"coordinates":[-114.074326,51.046009],"type":"Point"}
}