{
  "type": "Feature",
  "properties": {
    "addr:full":"612 8 Ave SW Calgary AB T2P 1G4",
    "addr:housenumber":"612",
    "addr:postcode":"t2p 1g4",
    "addr:street":"8 Ave Sw",
    "iso:country":"CA",
    "sg:address":"612 8 Ave SW",
    "sg:city":"Calgary",
    "sg:classifiers":[
        {
            "category":"Cinema",
            "subcategory":"Movie Theater",
            "type":"Entertainment"
        }
    ],
    "sg:phone":"+1 403 265 0120",
    "sg:postcode":"T2P 1G4",
    "sg:province":"AB",
    "wof:name":"Uptown Stage & Screen",
    "wof:placetype":"venue"
},
  "geometry": {"coordinates":[-114.074326,51.046009],"type":"Point"}
}