{
  "type": "Feature",
  "properties": {
    "addr:full":"3495 Rue Hochelaga Montreal QC H1W 1H6",
    "addr:housenumber":"3495",
    "addr:postcode":"h1w 1h6",
    "addr:street":"Rue Hochelaga",
    "iso:country":"CA",
    "sg:address":"3495 Rue Hochelaga",
    "sg:city":"Montreal",
    "sg:classifiers":[
        {
            "category":"Shopping",
            "subcategory":"Pharmacy",
            "type":"Retail Goods"
        }
    ],
    "sg:phone":"+1 514 524 3613",
    "sg:postcode":"H1W 1H6",
    "sg:province":"QC",
    "wof:name":"Pharmacie Sylvain Dubois",
    "wof:placetype":"venue"
},
  "geometry": {"coordinates":[-73.5520324707,45.5461883545],"type":"Point"}
}