{
  "type": "Feature",
  "properties": {
    "addr:full":"29 Wild Cherry Lane Thornhill ON L3T 3T3",
    "addr:housenumber":"29",
    "addr:postcode":"l3t 3t3",
    "addr:street":"Wild Cherry Lane",
    "iso:country":"CA",
    "sg:address":"29 Wild Cherry Lane",
    "sg:city":"Thornhill",
    "sg:classifiers":[
        {
            "category":"Wholesale",
            "subcategory":"Groceries",
            "type":"Manufacturing & Wholesale Goods"
        }
    ],
    "sg:phone":"+1 905 709 3910",
    "sg:postcode":"L3T 3T3",
    "sg:province":"ON",
    "sg:tags":[
        "cocoa",
        "chocolate"
    ],
    "wof:name":"Surj Bolaro Intl",
    "wof:placetype":"venue"
},
  "geometry": {"coordinates":[-79.42021942140001,43.8222579956],"type":"Point"}
}