{
  "type": "Feature",
  "properties": {
    "iso:country":"CA",
    "sg:address":"2709 River Rd",
    "sg:city":"Manotick",
    "sg:classifiers":[
        {
            "category":"Home & Garden",
            "subcategory":"Garden Supply",
            "type":"Retail Goods"
        }
    ],
    "sg:phone":"+1 613 692 3382",
    "sg:postcode":"K4M 1B4",
    "sg:province":"ON",
    "sg:tags":[
        "nurseryman"
    ],
    "wof:name":"Green Acres Garden Ctr",
    "wof:placetype":"venue"
},
  "geometry": {"coordinates":[-75.66226959230001,45.2183914185],"type":"Point"}
}