{
  "type": "Feature",
  "properties": {
    "iso:country":"CA",
    "sg:address":"394 Alfred St",
    "sg:city":"Corunna",
    "sg:classifiers":[
        {
            "category":"Organizations",
            "subcategory":"Religious Organization",
            "type":"Services"
        }
    ],
    "sg:phone":"+1 519 862 3016",
    "sg:postcode":"N0N 1G0",
    "sg:province":"ON",
    "sg:tags":[
        "church"
    ],
    "wof:name":"First Baptist Church",
    "wof:placetype":"venue"
},
  "geometry": {"coordinates":[-82.4398193359,42.8888664246],"type":"Point"}
}