{
  "type": "Feature",
  "properties": {
    "addr:full":"Montreal QC H2S 3L5",
    "addr:postcode":"h2s 3l5",
    "iso:country":"CA",
    "sg:city":"Montreal",
    "sg:classifiers":[
        {
            "category":"Professional",
            "subcategory":"Business Services",
            "type":"Services"
        }
    ],
    "sg:phone":"+1 514 272 9906",
    "sg:postcode":"H2S 3L5",
    "sg:province":"QC",
    "sg:tags":[
        "telemarketing"
    ],
    "wof:name":"Joncas Telexperts",
    "wof:placetype":"venue"
},
  "geometry": {"coordinates":[-73.5981063843,45.5306968689],"type":"Point"}
}