{
  "type": "Feature",
  "properties": {
    "addr:full":"33 Landry St Vanier ON K1L 5W7",
    "addr:housenumber":"33",
    "addr:postcode":"k1l 5w7",
    "addr:street":"Landry St",
    "iso:country":"CA",
    "sg:address":"33 Landry St",
    "sg:city":"Vanier",
    "sg:classifiers":[
        {
            "category":"Building & Trades",
            "subcategory":"Cleaning & Sanitation",
            "type":"Services"
        }
    ],
    "sg:phone":"+1 613 822 1175",
    "sg:postcode":"K1L 5W7",
    "sg:province":"ON",
    "sg:tags":[
        "janitor"
    ],
    "wof:name":"United Cleaning Svc",
    "wof:placetype":"venue"
},
  "geometry": {"coordinates":[-75.6742095947,45.4383239746],"type":"Point"}
}