{
  "type": "Feature",
  "properties": {
    "addr:full":"NE 7-26-6W Ashern MB R0C 0E0",
    "addr:postcode":"r0c 0e0",
    "addr:street":"Ne;Ashern",
    "iso:country":"CA",
    "sg:address":"NE 7-26-6W",
    "sg:city":"Ashern",
    "sg:classifiers":[
        {
            "category":"Wholesale",
            "subcategory":"Meat",
            "type":"Manufacturing & Wholesale Goods"
        }
    ],
    "sg:phone":"+1 204 768 3542",
    "sg:postcode":"R0C 0E0",
    "sg:province":"MB",
    "sg:tags":[
        "packer"
    ],
    "wof:name":"Don's Meat Processing",
    "wof:placetype":"venue"
},
  "geometry": {"coordinates":[-98.35010528559999,51.1798210144],"type":"Point"}
}