{
  "type": "Feature",
  "properties": {
    "addr:full":"2078 Avenue Rd North York ON M5M 4A6",
    "addr:housenumber":"2078",
    "addr:postcode":"m5m 4a6",
    "addr:street":"Avenue Rd",
    "iso:country":"CA",
    "sg:address":"2078 Avenue Rd",
    "sg:city":"North York",
    "sg:classifiers":[
        {
            "category":"Shopping",
            "subcategory":"Discount & Variety Stores",
            "type":"Retail Goods"
        }
    ],
    "sg:phone":"+1 416 489 4308",
    "sg:postcode":"M5M 4A6",
    "sg:province":"ON",
    "wof:name":"A & J Milk & Variety",
    "wof:placetype":"venue"
},
  "geometry": {"coordinates":[-79.41255200000001,43.767914],"type":"Point"}
}