{
  "type": "Feature",
  "properties": {
    "addr:full":"2200 Balmer Dr Elkford BC V0B 1H0",
    "addr:housenumber":"2200",
    "addr:postcode":"bc v0b 1h0",
    "addr:street":"Balmer Dr",
    "iso:country":"CA",
    "sg:address":"2200 Balmer Dr",
    "sg:city":"Elkford",
    "sg:classifiers":[
        {
            "category":"Bars & Pubs",
            "type":"Food & Drink"
        }
    ],
    "sg:phone":"+1 250 865 4320",
    "sg:postcode":"V0B 1H0",
    "sg:province":"BC",
    "wof:name":"Lamplighter Pub",
    "wof:placetype":"venue"
},
  "geometry": {"coordinates":[-114.927002,50.006119],"type":"Point"}
}