{
  "type": "Feature",
  "properties": {
    "addr:full":"3035 Utah Dr NW Calgary AB T2N 3Z9",
    "addr:housenumber":"3035",
    "addr:postcode":"t2n 3z9",
    "addr:street":"Utah Dr Nw",
    "iso:country":"CA",
    "sg:address":"3035 Utah Dr NW",
    "sg:city":"Calgary",
    "sg:classifiers":[
        {
            "category":"Education",
            "subcategory":"School",
            "type":"Public Place"
        }
    ],
    "sg:phone":"+1 403 777 6240",
    "sg:postcode":"T2N 3Z9",
    "sg:province":"AB",
    "wof:name":"University Elementary School",
    "wof:placetype":"venue"
},
  "geometry": {"coordinates":[-114.133804,51.070839],"type":"Point"}
}