{
  "type": "Feature",
  "properties": {
    "addr:full":"Vancouver BC V6E 3J7",
    "addr:postcode":"v6e 3j7",
    "iso:country":"CA",
    "sg:city":"Vancouver",
    "sg:classifiers":[
        {
            "category":"Real Estate",
            "subcategory":"Real Estate Agent",
            "type":"Services"
        }
    ],
    "sg:phone":"+1 604 684 6291",
    "sg:postcode":"V6E 3J7",
    "sg:province":"BC",
    "sg:tags":[
        "management"
    ],
    "wof:name":"Vancouver Condominium Svc Ltd",
    "wof:placetype":"venue"
},
  "geometry": {"coordinates":[-123.126282,49.287998],"type":"Point"}
}