{
  "type": "Feature",
  "properties": {
    "iso:country":"CA",
    "sg:address":"870 Boul DE Maisonneuve E",
    "sg:city":"Montreal",
    "sg:classifiers":[
        {
            "category":"Sports & Exercise",
            "subcategory":"Race Track",
            "type":"Entertainment"
        }
    ],
    "sg:phone":"+1 514 288 7274",
    "sg:postcode":"H2L 4S8",
    "sg:province":"QC",
    "wof:name":"Hippo Club",
    "wof:placetype":"venue"
},
  "geometry": {"coordinates":[-73.559593,45.516716],"type":"Point"}
}