{
  "type": "Feature",
  "properties": {
    "addr:full":"870 Boul DE Maisonneuve E Montreal QC H2L 4S8",
    "addr:housenumber":"870",
    "addr:postcode":"h2l 4s8",
    "addr:street":"Boul De Maisonneuve E",
    "iso:country":"CA",
    "sg:address":"870 Boul DE Maisonneuve E",
    "sg:city":"Montreal",
    "sg:classifiers":[
        {
            "category":"Sports & Exercise",
            "subcategory":"Race Track",
            "type":"Entertainment"
        }
    ],
    "sg:phone":"+1 514 288 7274",
    "sg:postcode":"H2L 4S8",
    "sg:province":"QC",
    "wof:name":"Hippo Club",
    "wof:placetype":"venue"
},
  "geometry": {"coordinates":[-73.55959300000001,45.516716],"type":"Point"}
}