{
  "type": "Feature",
  "properties": {
    "addr:full":"900 Rue Belanger Montreal QC H2S 3P4",
    "addr:housenumber":"900",
    "addr:postcode":"h2s 3p4",
    "addr:street":"Rue Belanger",
    "iso:country":"CA",
    "sg:address":"900 Rue Belanger",
    "sg:city":"Montreal",
    "sg:classifiers":[
        {
            "category":"Manufacturing",
            "subcategory":"Printing",
            "type":"Manufacturing & Wholesale Goods"
        }
    ],
    "sg:phone":"+1 514 270 8088",
    "sg:postcode":"H2S 3P4",
    "sg:province":"QC",
    "sg:tags":[
        "newspaper"
    ],
    "wof:name":"Nouvelles DE L'Est",
    "wof:placetype":"venue"
},
  "geometry": {"coordinates":[-73.6095275879,45.5396652222],"type":"Point"}
}