{
  "type": "Feature",
  "properties": {
    "addr:full":"820 Rue DE LA Rive Saint-Jean-Chrysostome QC G6Z 2L1",
    "addr:housenumber":"820",
    "addr:postcode":"g6z 2l1",
    "addr:street":"Rue De La Rive Saint-Jean-Chrysostome",
    "iso:country":"CA",
    "sg:address":"820 Rue DE LA Rive",
    "sg:city":"Saint-Jean-Chrysostome",
    "sg:classifiers":[
        {
            "category":"Manufacturing",
            "subcategory":"Metals",
            "type":"Manufacturing & Wholesale Goods"
        }
    ],
    "sg:phone":"+1 418 832 7999",
    "sg:postcode":"G6Z 2L1",
    "sg:province":"QC",
    "sg:tags":[
        "steel"
    ],
    "wof:name":"Fabrications A Ouellette Inc",
    "wof:placetype":"venue"
},
  "geometry": {"coordinates":[-71.270691,46.695705],"type":"Point"}
}