{
  "type": "Feature",
  "properties": {
    "addr:full":"2437 Rue Allard Montreal QC H4E 2L3",
    "addr:housenumber":"2437",
    "addr:postcode":"h4e 2l3",
    "addr:street":"Rue Allard",
    "iso:country":"CA",
    "sg:address":"2437 Rue Allard",
    "sg:city":"Montreal",
    "sg:classifiers":[
        {
            "category":"Food & Beverages",
            "subcategory":"Bakery",
            "type":"Retail Goods"
        }
    ],
    "sg:phone":"+1 514 766 5921",
    "sg:postcode":"H4E 2L3",
    "sg:province":"QC",
    "sg:tags":[
        "baker"
    ],
    "wof:name":"Gourmet Aldo",
    "wof:placetype":"venue"
},
  "geometry": {"coordinates":[-73.5936508179,45.4512062073],"type":"Point"}
}