{
  "type": "Feature",
  "properties": {
    "addr:full":"175 Main St Toronto ON M4E 2W2",
    "addr:housenumber":"175",
    "addr:postcode":"m4e 2w2",
    "addr:street":"Main St",
    "iso:country":"CA",
    "sg:address":"175 Main St",
    "sg:city":"Toronto",
    "sg:classifiers":[
        {
            "category":"Organizations",
            "subcategory":"Professional Association",
            "type":"Services"
        }
    ],
    "sg:phone":"+1 416 699 5792",
    "sg:postcode":"M4E 2W2",
    "sg:province":"ON",
    "sg:tags":[
        "club"
    ],
    "wof:name":"Ted Reeve Hockey Assn",
    "wof:placetype":"venue"
},
  "geometry": {"coordinates":[-79.299988,43.684303],"type":"Point"}
}