{
  "type": "Feature",
  "properties": {
    "iso:country":"CA",
    "sg:address":"5151 Harbour View Rd",
    "sg:city":"Burnaby",
    "sg:classifiers":[
        {
            "category":"Professional",
            "subcategory":"Management & Consulting",
            "type":"Services"
        }
    ],
    "sg:phone":"+1 604 421 4866",
    "sg:postcode":"V5B 1C9",
    "sg:province":"BC",
    "sg:tags":[
        "consultant",
        "safety"
    ],
    "wof:name":"David King Enterprises",
    "wof:placetype":"venue"
},
  "geometry": {"coordinates":[-122.98790700000001,49.288776],"type":"Point"}
}