{
  "type": "Feature",
  "properties": {
    "addr:full":"14013 Rue DE Montigny Montreal QC H1A 1J8",
    "addr:housenumber":"14013",
    "addr:postcode":"h1a 1j8",
    "addr:street":"Rue De Montigny",
    "iso:country":"CA",
    "sg:address":"14013 Rue DE Montigny",
    "sg:city":"Montreal",
    "sg:classifiers":[
        {
            "category":"Social Services",
            "subcategory":"Child Care",
            "type":"Services"
        }
    ],
    "sg:phone":"+1 514 644 2258",
    "sg:postcode":"H1A 1J8",
    "sg:province":"QC",
    "wof:name":"Centre D'Aide Familiale",
    "wof:placetype":"venue"
},
  "geometry": {"coordinates":[-73.499725,45.668732],"type":"Point"}
}