{
  "type": "Feature",
  "properties": {
    "addr:full":"7262 Highway 207 Head of Chezzetcook NS B0J 1N0",
    "addr:housenumber":"7262",
    "addr:postcode":"b0j 1n0",
    "addr:street":"Highway 207",
    "iso:country":"CA",
    "sg:address":"7262 Highway 207",
    "sg:city":"Head of Chezzetcook",
    "sg:classifiers":[
        {
            "category":"Retail",
            "subcategory":"Auto Repair",
            "type":"Services"
        }
    ],
    "sg:phone":"+1 902 827 5225",
    "sg:postcode":"B0J 1N0",
    "sg:province":"NS",
    "sg:tags":[
        "repairing",
        "automobile"
    ],
    "wof:name":"Robert's Truck & Autobody",
    "wof:placetype":"venue"
},
  "geometry": {"coordinates":[-63.237865448,44.7506942749],"type":"Point"}
}