{
  "type": "Feature",
  "properties": {
    "iso:country":"CA",
    "sg:address":"131 Rue Jean-Proulx",
    "sg:city":"Hull",
    "sg:classifiers":[
        {
            "category":"Shopping",
            "subcategory":"Florist",
            "type":"Retail Goods"
        }
    ],
    "sg:phone":"+1 819 777 2755",
    "sg:postcode":"J8Z 1T4",
    "sg:province":"QC",
    "wof:name":"Fleuriste Michel Jean-Wright",
    "wof:placetype":"venue"
},
  "geometry": {"coordinates":[-75.73384094239999,45.4655418396],"type":"Point"}
}