{
  "type": "Feature",
  "properties": {
    "addr:full":"Richmond BC V6Y 3X9",
    "addr:postcode":"v6y 3x9",
    "iso:country":"CA",
    "sg:city":"Richmond",
    "sg:classifiers":[
        {
            "category":"Sports & Exercise",
            "subcategory":"Gym",
            "type":"Entertainment"
        }
    ],
    "sg:phone":"+1 604 233 6991",
    "sg:postcode":"V6Y 3X9",
    "sg:province":"BC",
    "sg:tags":[
        "club",
        "health",
        "studio",
        "gymnasium"
    ],
    "wof:name":"Planet Woman",
    "wof:placetype":"venue"
},
  "geometry": {"coordinates":[-123.123848,49.155323],"type":"Point"}
}