{
  "type": "Feature",
  "properties": {
    "addr:full":"11760 109 St NW # E108 Edmonton AB T5G 2T8",
    "addr:housenumber":"11760",
    "addr:postcode":"t5g 2t8",
    "addr:street":"109 St Nw # E108",
    "iso:country":"CA",
    "sg:address":"11760 109 St NW # E108",
    "sg:city":"Edmonton",
    "sg:classifiers":[
        {
            "category":"Real Estate",
            "subcategory":"Real Estate Agent",
            "type":"Services"
        }
    ],
    "sg:phone":"+1 780 413 9676",
    "sg:postcode":"T5G 2T8",
    "sg:province":"AB",
    "sg:tags":[
        "aircraft",
        "management",
        "maintenance"
    ],
    "wof:name":"Hangar 11 Corp",
    "wof:placetype":"venue"
},
  "geometry": {"coordinates":[-113.507789612,53.5692977905],"type":"Point"}
}