{
  "type": "Feature",
  "properties": {
    "addr:full":"6000 Iona Dr Vancouver BC V6T 1L4",
    "addr:housenumber":"6000",
    "addr:postcode":"v6t 1l4",
    "addr:street":"Iona Dr",
    "iso:country":"CA",
    "sg:address":"6000 Iona Dr",
    "sg:city":"Vancouver",
    "sg:classifiers":[
        {
            "category":"Organizations",
            "subcategory":"Religious Organization",
            "type":"Services"
        }
    ],
    "sg:phone":"+1 604 822 9583",
    "sg:postcode":"V6T 1L4",
    "sg:province":"BC",
    "sg:tags":[
        "church"
    ],
    "wof:name":"Anglican Church Archives",
    "wof:placetype":"venue"
},
  "geometry": {"coordinates":[-123.25013,49.271141],"type":"Point"}
}