{
  "type": "Feature",
  "properties": {
    "iso:country":"CA",
    "sg:city":"Montreal",
    "sg:classifiers":[
        {
            "category":"Real Estate",
            "subcategory":"Real Estate Agent",
            "type":"Services"
        }
    ],
    "sg:phone":"+1 514 881 1253",
    "sg:postcode":"H1E 5N4",
    "sg:province":"QC",
    "sg:tags":[
        "cooperative"
    ],
    "wof:name":"Cooperative Claire Heureuse",
    "wof:placetype":"venue"
},
  "geometry": {"coordinates":[-73.601135,45.630608],"type":"Point"}
}