{
  "type": "Feature",
  "properties": {
    "addr:full":"North York ON M3B 2S7",
    "addr:postcode":"m3b 2s7",
    "iso:country":"CA",
    "sg:city":"North York",
    "sg:classifiers":[
        {
            "category":"Real Estate",
            "subcategory":"Architect",
            "type":"Services"
        }
    ],
    "sg:phone":"+1 416 467 8000",
    "sg:postcode":"M3B 2S7",
    "sg:province":"ON",
    "wof:name":"Parkin Architects Ltd",
    "wof:placetype":"venue"
},
  "geometry": {"coordinates":[-79.35414900000001,43.758175],"type":"Point"}
}