{
  "type": "Feature",
  "properties": {
    "addr:full":"120 North Queen St Etobicoke ON M8Z 2E2",
    "addr:housenumber":"120",
    "addr:postcode":"m8z 2e2",
    "addr:street":"North Queen St",
    "iso:country":"CA",
    "sg:address":"120 North Queen St",
    "sg:city":"Etobicoke",
    "sg:classifiers":[
        {
            "category":"Recreation",
            "type":"Entertainment"
        }
    ],
    "sg:phone":"+1 416 236 5278",
    "sg:postcode":"M8Z 2E2",
    "sg:province":"ON",
    "sg:tags":[
        "amusement"
    ],
    "wof:name":"Prokart Indoor Raceways",
    "wof:placetype":"venue"
},
  "geometry": {"coordinates":[-79.54894299999999,43.620724],"type":"Point"}
}