{
  "type": "Feature",
  "properties": {
    "iso:country":"CA",
    "sg:address":"106 Airport Rd",
    "sg:city":"Labrador City",
    "sg:classifiers":[
        {
            "category":"Professional",
            "type":"Services"
        }
    ],
    "sg:phone":"+1 709 944 4066",
    "sg:postcode":"A2V 2J7",
    "sg:province":"NL",
    "sg:tags":[
        "bus",
        "establishment"
    ],
    "wof:name":"J & S Busing",
    "wof:placetype":"venue"
},
  "geometry": {"coordinates":[-66.9007034302,52.9462547302],"type":"Point"}
}