{
  "type": "Feature",
  "properties": {
    "addr:full":"1985 Garden Dr #103 Prince George BC V2M 2V9",
    "addr:housenumber":"1985",
    "addr:postcode":"v2m 2v9",
    "addr:street":"Garden Dr # 103",
    "iso:country":"CA",
    "sg:address":"1985 Garden Dr #103",
    "sg:city":"Prince George",
    "sg:classifiers":[
        {
            "category":"Manufacturing",
            "subcategory":"Lumber",
            "type":"Manufacturing & Wholesale Goods"
        }
    ],
    "sg:phone":"+1 250 564 4427",
    "sg:postcode":"V2M 2V9",
    "sg:province":"BC",
    "sg:tags":[
        "forester"
    ],
    "wof:name":"Kim Forest Management",
    "wof:placetype":"venue"
},
  "geometry": {"coordinates":[-122.776641846,53.905960083],"type":"Point"}
}