{
  "type": "Feature",
  "properties": {
    "addr:full":"383 Rue Canada Saint-Quentin NB E8A 1K4",
    "addr:housenumber":"383",
    "addr:postcode":"e8a 1k4",
    "addr:street":"Rue",
    "iso:country":"CA",
    "sg:address":"383 Rue Canada",
    "sg:city":"Saint-Quentin",
    "sg:classifiers":[
        {
            "category":"Professional",
            "subcategory":"Business Services",
            "type":"Services"
        }
    ],
    "sg:phone":"+1 506 235 2729",
    "sg:postcode":"E8A 1K4",
    "sg:province":"NB",
    "sg:tags":[
        "painter",
        "sign"
    ],
    "wof:name":"Lettrage Royal",
    "wof:placetype":"venue"
},
  "geometry": {"coordinates":[-67.392105,47.52317],"type":"Point"}
}