{
  "type": "Feature",
  "properties": {
    "addr:full":"69 Pl Quevillon Lebel-Sur-Quevillon QC J0Y 1X0",
    "addr:housenumber":"69",
    "addr:postcode":"j0y 1x0",
    "addr:street":"Pl Quevillon Lebel-Sur-Quevillon",
    "iso:country":"CA",
    "sg:address":"69 Pl Quevillon",
    "sg:city":"Lebel-Sur-Quevillon",
    "sg:classifiers":[
        {
            "category":"Shopping",
            "subcategory":"Shoes",
            "type":"Retail Goods"
        }
    ],
    "sg:phone":"+1 819 755 4521",
    "sg:postcode":"J0Y 1X0",
    "sg:province":"QC",
    "wof:name":"Chaussures Mike Ltee",
    "wof:placetype":"venue"
},
  "geometry": {"coordinates":[-76.979156,49.053116],"type":"Point"}
}