{
  "type": "Feature",
  "properties": {
    "addr:full":"575 Larsen Ave Winnipeg MB R2K 1R5",
    "addr:housenumber":"575",
    "addr:postcode":"r2k 1r5",
    "addr:street":"Larsen Ave",
    "iso:country":"CA",
    "sg:address":"575 Larsen Ave",
    "sg:city":"Winnipeg",
    "sg:classifiers":[
        {
            "category":"Recreation",
            "type":"Entertainment"
        }
    ],
    "sg:phone":"+1 204 986 3445",
    "sg:postcode":"R2K 1R5",
    "sg:province":"MB",
    "sg:tags":[
        "center"
    ],
    "wof:name":"East End Cultural & Leisure",
    "wof:placetype":"venue"
},
  "geometry": {"coordinates":[-97.09882399999999,49.913223],"type":"Point"}
}