{
  "type": "Feature",
  "properties": {
    "iso:country":"CA",
    "sg:address":"575 Larsen Ave",
    "sg:city":"Winnipeg",
    "sg:classifiers":[
        {
            "category":"Recreation",
            "type":"Entertainment"
        }
    ],
    "sg:phone":"+1 204 986 3445",
    "sg:postcode":"R2K 1R5",
    "sg:province":"MB",
    "sg:tags":[
        "center"
    ],
    "wof:name":"East End Cultural & Leisure",
    "wof:placetype":"venue"
},
  "geometry": {"coordinates":[-97.098824,49.913223],"type":"Point"}
}