{
  "type": "Feature",
  "properties": {
    "iso:country":"CA",
    "sg:address":"74 Lindsay St S",
    "sg:city":"Lindsay",
    "sg:classifiers":[
        {
            "category":"Real Estate",
            "subcategory":"Architect",
            "type":"Services"
        }
    ],
    "sg:phone":"+1 705 328 0175",
    "sg:postcode":"K9V 2M2",
    "sg:province":"ON",
    "wof:name":"Wilcox Architects Inc",
    "wof:placetype":"venue"
},
  "geometry": {"coordinates":[-78.73361199999999,44.353451],"type":"Point"}
}