{
  "type": "Feature",
  "properties": {
    "addr:full":"Sept-Iles QC G4R 2X1",
    "addr:postcode":"g4r 2x1",
    "iso:country":"CA",
    "sg:city":"Sept-Iles",
    "sg:classifiers":[
        {
            "category":"Insurance",
            "subcategory":"Insurance Agent",
            "type":"Services"
        }
    ],
    "sg:phone":"+1 418 962 2372",
    "sg:postcode":"G4R 2X1",
    "sg:province":"QC",
    "wof:name":"Assurances Jean-P Gauthier",
    "wof:placetype":"venue"
},
  "geometry": {"coordinates":[-66.386756897,50.2073440552],"type":"Point"}
}