{
  "type": "Feature",
  "properties": {
    "addr:full":"130 Hampton Rd Rothesay NB E2E 2N6",
    "addr:housenumber":"130",
    "addr:postcode":"e2e 2n6",
    "addr:street":"Hampton Rd",
    "iso:country":"CA",
    "sg:address":"130 Hampton Rd",
    "sg:city":"Rothesay",
    "sg:classifiers":[
        {
            "category":"Health Services",
            "subcategory":"Optometrist",
            "type":"Services"
        }
    ],
    "sg:phone":"+1 506 849 2444",
    "sg:postcode":"E2E 2N6",
    "sg:province":"NB",
    "wof:name":"Mc Cue, Thomas OD",
    "wof:placetype":"venue"
},
  "geometry": {"coordinates":[-65.977058,45.400173],"type":"Point"}
}