{
  "type": "Feature",
  "properties": {
    "iso:country":"CA",
    "sg:address":"4350 Mainway",
    "sg:city":"Burlington",
    "sg:classifiers":[
        {
            "category":"Shopping",
            "type":"Retail Goods"
        }
    ],
    "sg:phone":"+1 905 335 6444",
    "sg:postcode":"L7L 5R7",
    "sg:province":"ON",
    "sg:tags":[
        "picture",
        "frame"
    ],
    "wof:name":"Celadon Imports Inc",
    "wof:placetype":"venue"
},
  "geometry": {"coordinates":[-79.7872009277,43.3812446594],"type":"Point"}
}