{
  "type": "Feature",
  "properties": {
    "iso:country":"CA",
    "sg:address":"621 Main St W",
    "sg:city":"North Bay",
    "sg:classifiers":[
        {
            "category":"Government",
            "subcategory":"Office",
            "type":"Public Place"
        }
    ],
    "sg:phone":"+1 705 474 3540",
    "sg:postcode":"P1B 2V6",
    "sg:province":"ON",
    "wof:name":"Ontario Community & Social Svc",
    "wof:placetype":"venue"
},
  "geometry": {"coordinates":[-79.4696960449,46.3160362244],"type":"Point"}
}