{
  "type": "Feature",
  "properties": {
    "iso:country":"CA",
    "sg:address":"SE 21-24-4E",
    "sg:city":"Riverton",
    "sg:classifiers":[
        {
            "category":"Professional",
            "subcategory":"Accounting & Tax Preparation",
            "type":"Services"
        }
    ],
    "sg:phone":"+1 204 378 5532",
    "sg:postcode":"R0C 2R0",
    "sg:province":"MB",
    "sg:tags":[
        "accountant"
    ],
    "wof:name":"Nidan Management Ltd",
    "wof:placetype":"venue"
},
  "geometry": {"coordinates":[-96.9964523315,50.9984130859],"type":"Point"}
}