{
  "type": "Feature",
  "properties": {
    "addr:full":"2277 Riverside Dr Ottawa ON K1H 7X6",
    "addr:housenumber":"2277",
    "addr:postcode":"k1h 7x6",
    "addr:street":"Riverside Dr",
    "iso:country":"CA",
    "sg:address":"2277 Riverside Dr",
    "sg:city":"Ottawa",
    "sg:classifiers":[
        {
            "category":"Shopping",
            "type":"Retail Goods"
        }
    ],
    "sg:phone":"+1 613 733 8992",
    "sg:postcode":"K1H 7X6",
    "sg:province":"ON",
    "sg:tags":[
        "telephone",
        "cellular"
    ],
    "wof:name":"Magasins Bell World",
    "wof:placetype":"venue"
},
  "geometry": {"coordinates":[-75.67991600000001,45.386597],"type":"Point"}
}