{
  "type": "Feature",
  "properties": {
    "addr:full":"PO Box 640 Calmar AB T0C 0V0",
    "addr:housenumber":"po;640",
    "addr:postcode":"t0c 0v0",
    "addr:street":"Box",
    "iso:country":"CA",
    "sg:address":"PO Box 640",
    "sg:city":"Calmar",
    "sg:classifiers":[
        {
            "category":"Retail",
            "subcategory":"Auto Repair",
            "type":"Services"
        }
    ],
    "sg:phone":"+1 780 985 2222",
    "sg:postcode":"T0C 0V0",
    "sg:province":"AB",
    "sg:tags":[
        "repairing",
        "automobile"
    ],
    "wof:name":"Acro Automotive",
    "wof:placetype":"venue"
},
  "geometry": {"coordinates":[-113.80455000000001,53.265041],"type":"Point"}
}