{
  "type": "Feature",
  "properties": {
    "addr:full":"PO Box 476 Pincher Creek AB T0K 1W0",
    "addr:housenumber":"po",
    "addr:postcode":"t0k 1w0",
    "addr:street":"Box 476;Creek",
    "iso:country":"CA",
    "sg:address":"PO Box 476",
    "sg:city":"Pincher Creek",
    "sg:classifiers":[
        {
            "category":"Professional",
            "subcategory":"Business Services",
            "type":"Services"
        }
    ],
    "sg:phone":"+1 403 627 2811",
    "sg:postcode":"T0K 1W0",
    "sg:province":"AB",
    "wof:name":"Deep Hole Locky Bell Ltd",
    "wof:placetype":"venue"
},
  "geometry": {"coordinates":[-113.950096,49.485668],"type":"Point"}
}