{
  "type": "Feature",
  "properties": {
    "addr:full":"23000 116 Ave Maple Ridge BC V2X 0T8",
    "addr:housenumber":"23000",
    "addr:postcode":"v2x 0t8",
    "addr:street":"116 Ave",
    "iso:country":"CA",
    "sg:address":"23000 116 Ave",
    "sg:city":"Maple Ridge",
    "sg:classifiers":[
        {
            "category":"Education",
            "subcategory":"School",
            "type":"Public Place"
        }
    ],
    "sg:phone":"+1 604 463 2001",
    "sg:postcode":"V2X 0T8",
    "sg:province":"BC",
    "wof:name":"Thomas Haney Secondary School",
    "wof:placetype":"venue"
},
  "geometry": {"coordinates":[-122.586006165,49.2123832703],"type":"Point"}
}