{
  "type": "Feature",
  "properties": {
    "iso:country":"CA",
    "sg:city":"Cranbrook",
    "sg:classifiers":[
        {
            "category":"Retail",
            "subcategory":"Funeral Services",
            "type":"Services"
        }
    ],
    "sg:phone":"+1 250 426 4864",
    "sg:postcode":"V1C 6R2",
    "sg:province":"BC",
    "sg:tags":[
        "director"
    ],
    "wof:name":"Mark Memorial Funeral Svc",
    "wof:placetype":"venue"
},
  "geometry": {"coordinates":[-115.765228272,49.5340309143],"type":"Point"}
}