{
  "type": "Feature",
  "properties": {
    "addr:full":"Toronto ON M4V 1J8",
    "addr:postcode":"m4v 1j8",
    "iso:country":"CA",
    "sg:city":"Toronto",
    "sg:classifiers":[
        {
            "category":"Health Services",
            "subcategory":"Health Practitioner",
            "type":"Services"
        }
    ],
    "sg:phone":"+1 416 967 7107",
    "sg:postcode":"M4V 1J8",
    "sg:province":"ON",
    "sg:tags":[
        "psychologist"
    ],
    "wof:name":"Turrall, Graham PhD",
    "wof:placetype":"venue"
},
  "geometry": {"coordinates":[-79.401268,43.684017],"type":"Point"}
}