{
  "type": "Feature",
  "properties": {
    "addr:full":"625 Boul Rene-Levesque O Montreal QC H3B 1R2",
    "addr:housenumber":"625",
    "addr:postcode":"h3b 1r2",
    "addr:street":"Boul Rene-Levesque O",
    "iso:country":"CA",
    "sg:address":"625 Boul Rene-Levesque O",
    "sg:city":"Montreal",
    "sg:classifiers":[
        {
            "category":"Insurance",
            "subcategory":"Insurance Agent",
            "type":"Services"
        }
    ],
    "sg:phone":"+1 514 875 4570",
    "sg:postcode":"H3B 1R2",
    "sg:province":"QC",
    "wof:name":"Compagnie D'Assur-Missisquoi",
    "wof:placetype":"venue"
},
  "geometry": {"coordinates":[-73.5671081543,45.5025444031],"type":"Point"}
}