{
  "type": "Feature",
  "properties": {
    "addr:full":"615 Boul Rene-Levesque O Montreal QC H3B 1P6",
    "addr:housenumber":"615",
    "addr:postcode":"h3b 1p6",
    "addr:street":"Boul Rene-Levesque O",
    "iso:country":"CA",
    "sg:address":"615 Boul Rene-Levesque O",
    "sg:city":"Montreal",
    "sg:classifiers":[
        {
            "category":"Professional",
            "subcategory":"Employment Agencies",
            "type":"Services"
        }
    ],
    "sg:phone":"+1 514 338 3800",
    "sg:postcode":"H3B 1P6",
    "sg:province":"QC",
    "sg:tags":[
        "opportunity"
    ],
    "wof:name":"Ian Martin Ltee",
    "wof:placetype":"venue"
},
  "geometry": {"coordinates":[-73.56697800000001,45.502811],"type":"Point"}
}