{
  "type": "Feature",
  "properties": {
    "iso:country":"CA",
    "sg:city":"Montreal",
    "sg:classifiers":[
        {
            "category":"Wholesale",
            "subcategory":"Apparel",
            "type":"Manufacturing & Wholesale Goods"
        }
    ],
    "sg:phone":"+1 514 526 3636",
    "sg:postcode":"H2H 2S6",
    "sg:province":"QC",
    "sg:tags":[
        "shoes"
    ],
    "wof:name":"Importations Vb Inc",
    "wof:placetype":"venue"
},
  "geometry": {"coordinates":[-73.6125793457,45.6988143921],"type":"Point"}
}