{
  "type": "Feature",
  "properties": {
    "iso:country":"CA",
    "sg:city":"Vancouver",
    "sg:classifiers":[
        {
            "category":"Personal",
            "subcategory":"Beauty Salon",
            "type":"Services"
        }
    ],
    "sg:phone":"+1 604 684 2630",
    "sg:postcode":"V6C 2V6",
    "sg:province":"BC",
    "wof:name":"Etg Hair Treatment Ctr",
    "wof:placetype":"venue"
},
  "geometry": {"coordinates":[-123.11592102,49.2853050232],"type":"Point"}
}