{
  "type": "Feature",
  "properties": {
    "addr:full":"3650 91 St NW Edmonton AB T6E 6P1",
    "addr:housenumber":"3650",
    "addr:postcode":"t6e 6p1",
    "addr:street":"91 St Nw",
    "iso:country":"CA",
    "sg:address":"3650 91 St NW",
    "sg:city":"Edmonton",
    "sg:classifiers":[
        {
            "category":"Social Services",
            "subcategory":"Child Care",
            "type":"Services"
        }
    ],
    "sg:phone":"+1 780 436 1823",
    "sg:postcode":"T6E 6P1",
    "sg:province":"AB",
    "wof:name":"Southview Child Care",
    "wof:placetype":"venue"
},
  "geometry": {"coordinates":[-113.467468,53.469997],"type":"Point"}
}