{
  "type": "Feature",
  "properties": {
    "addr:full":"2954 Boul Laframboise Saint-Hyacinthe QC J2S 4Z2",
    "addr:housenumber":"2954",
    "addr:postcode":"j2s 4z2",
    "addr:street":"Boul Laframboise",
    "iso:country":"CA",
    "sg:address":"2954 Boul Laframboise",
    "sg:city":"Saint-Hyacinthe",
    "sg:classifiers":[
        {
            "category":"Health Services",
            "subcategory":"Doctor",
            "type":"Services"
        }
    ],
    "sg:phone":"+1 450 773 0222",
    "sg:postcode":"J2S 4Z2",
    "sg:province":"QC",
    "sg:tags":[
        "physician",
        "surgeon"
    ],
    "wof:name":"Renaud, Jacques MD",
    "wof:placetype":"venue"
},
  "geometry": {"coordinates":[-72.96412658689999,45.6346931458],"type":"Point"}
}