{
  "type": "Feature",
  "properties": {
    "addr:full":"341 Madeline St Thunder Bay ON P7A 5Y9",
    "addr:housenumber":"341",
    "addr:postcode":"p7a 5y9",
    "addr:street":"Madeline St",
    "iso:country":"CA",
    "sg:address":"341 Madeline St",
    "sg:city":"Thunder Bay",
    "sg:classifiers":[
        {
            "category":"Education",
            "subcategory":"Special Training",
            "type":"Public Place"
        }
    ],
    "sg:phone":"+1 807 346 1266",
    "sg:postcode":"P7A 5Y9",
    "sg:province":"ON",
    "sg:tags":[
        "management"
    ],
    "wof:name":"Centre For Life Skills Dev",
    "wof:placetype":"venue"
},
  "geometry": {"coordinates":[-89.2340393066,48.4504928589],"type":"Point"}
}