{
  "type": "Feature",
  "properties": {
    "iso:country":"CA",
    "sg:city":"Burlington",
    "sg:classifiers":[
        {
            "category":"Health Services",
            "subcategory":"Doctor",
            "type":"Services"
        }
    ],
    "sg:phone":"+1 905 681 2700",
    "sg:postcode":"L7S 2J8",
    "sg:province":"ON",
    "sg:tags":[
        "dentist"
    ],
    "wof:name":"Mapleview Dental Ctr",
    "wof:placetype":"venue"
},
  "geometry": {"coordinates":[-79.819702,43.327843],"type":"Point"}
}