{
  "type": "Feature",
  "properties": {
    "iso:country":"CA",
    "sg:city":"Cap-DE-LA-Madeleine",
    "sg:classifiers":[
        {
            "category":"Insurance",
            "subcategory":"Insurance Agent",
            "type":"Services"
        }
    ],
    "sg:phone":"+1 819 691 2225",
    "sg:postcode":"G8T 1Y5",
    "sg:province":"QC",
    "wof:name":"Assurance Michel Giroux",
    "wof:placetype":"venue"
},
  "geometry": {"coordinates":[-72.545197,46.380943],"type":"Point"}
}