{
  "type": "Feature",
  "properties": {
    "addr:full":"Calgary AB T2P 0M2",
    "addr:postcode":"t2p 0m2",
    "iso:country":"CA",
    "sg:city":"Calgary",
    "sg:classifiers":[
        {
            "category":"Real Estate",
            "subcategory":"Developer",
            "type":"Services"
        }
    ],
    "sg:phone":"+1 403 571 3199",
    "sg:postcode":"T2P 0M2",
    "sg:province":"AB",
    "wof:name":"Yale Properties",
    "wof:placetype":"venue"
},
  "geometry": {"coordinates":[-114.072365,51.048763],"type":"Point"}
}