{
  "type": "Feature",
  "properties": {
    "addr:full":"Cp 1350 Warwick QC J0A 1M0",
    "addr:housenumber":"1350",
    "addr:postcode":"j0a 1m0",
    "addr:street":"Cp",
    "iso:country":"CA",
    "sg:address":"Cp 1350",
    "sg:city":"Warwick",
    "sg:classifiers":[
        {
            "category":"Health Services",
            "subcategory":"Health Practitioner",
            "type":"Services"
        }
    ],
    "sg:phone":"+1 819 752 1920",
    "sg:postcode":"J0A 1M0",
    "sg:province":"QC",
    "sg:tags":[
        "home",
        "nurse",
        "registry"
    ],
    "wof:name":"Medic-Action Soins Infirmiers",
    "wof:placetype":"venue"
},
  "geometry": {"coordinates":[-71.996689,45.949215],"type":"Point"}
}