{
  "type": "Feature",
  "properties": {
    "addr:full":"34 Mill St Almonte ON K0A 1A0",
    "addr:housenumber":"34",
    "addr:postcode":"k0a 1a0",
    "addr:street":"Mill St",
    "iso:country":"CA",
    "sg:address":"34 Mill St",
    "sg:city":"Almonte",
    "sg:classifiers":[
        {
            "category":"Food & Beverages",
            "subcategory":"Specialty",
            "type":"Retail Goods"
        }
    ],
    "sg:phone":"+1 613 256 1833",
    "sg:postcode":"K0A 1A0",
    "sg:province":"ON",
    "sg:tags":[
        "health",
        "diet"
    ],
    "wof:name":"Almonte Natural Food Ctr",
    "wof:placetype":"venue"
},
  "geometry": {"coordinates":[-76.196915,45.225143],"type":"Point"}
}