{
  "type": "Feature",
  "properties": {
    "iso:country":"CA",
    "sg:address":"550 Rue Louis-Pasteur",
    "sg:city":"Boucherville",
    "sg:classifiers":[
        {
            "category":"Wholesale",
            "subcategory":"Groceries",
            "type":"Manufacturing & Wholesale Goods"
        }
    ],
    "sg:phone":"+1 450 655 4400",
    "sg:postcode":"J4B 7Z1",
    "sg:province":"QC",
    "sg:tags":[
        "food",
        "product"
    ],
    "wof:name":"Distal Inc",
    "wof:placetype":"venue"
},
  "geometry": {"coordinates":[-73.4011917114,45.5657157898],"type":"Point"}
}