{
  "type": "Feature",
  "properties": {
    "addr:full":"286 Boul Labelle Sainte-Therese QC J7E 2X9",
    "addr:housenumber":"286",
    "addr:postcode":"j7e 2x9",
    "addr:street":"Boul Labelle Sainte-Therese",
    "iso:country":"CA",
    "sg:address":"286 Boul Labelle",
    "sg:city":"Sainte-Therese",
    "sg:classifiers":[
        {
            "category":"Personal",
            "subcategory":"Beauty Salon",
            "type":"Services"
        }
    ],
    "sg:phone":"+1 450 979 0377",
    "sg:postcode":"J7E 2X9",
    "sg:province":"QC",
    "wof:name":"Profession Artiste",
    "wof:placetype":"venue"
},
  "geometry": {"coordinates":[-73.838081,45.64637],"type":"Point"}
}