{
  "type": "Feature",
  "properties": {
    "addr:full":"Harrow ON N0R 1G0",
    "addr:postcode":"n0r 1g0",
    "iso:country":"CA",
    "sg:city":"Harrow",
    "sg:classifiers":[
        {
            "category":"Restaurant",
            "type":"Food & Drink"
        }
    ],
    "sg:phone":"+1 519 738 9303",
    "sg:postcode":"N0R 1G0",
    "sg:province":"ON",
    "wof:name":"Drifter's Inn",
    "wof:placetype":"venue"
},
  "geometry": {"coordinates":[-82.92049400000001,42.035767],"type":"Point"}
}