{
  "type": "Feature",
  "properties": {
    "addr:full":"Toronto ON M5V 1X6",
    "addr:postcode":"m5v 1x6",
    "iso:country":"CA",
    "sg:city":"Toronto",
    "sg:classifiers":[
        {
            "category":"Professional",
            "subcategory":"Employment Agencies",
            "type":"Services"
        }
    ],
    "sg:phone":"+1 416 599 1825",
    "sg:postcode":"M5V 1X6",
    "sg:province":"ON",
    "sg:tags":[
        "consultant",
        "search",
        "executive"
    ],
    "wof:name":"Tal Group Inc",
    "wof:placetype":"venue"
},
  "geometry": {"coordinates":[-79.39415700000001,43.648327],"type":"Point"}
}