{
  "type": "Feature",
  "properties": {
    "addr:full":"4262 Rue Jean-Talon E Saint-Leonard QC H1S 1J7",
    "addr:housenumber":"4262",
    "addr:postcode":"h1s 1j7",
    "addr:street":"Rue Jean-Talon E",
    "iso:country":"CA",
    "sg:address":"4262 Rue Jean-Talon E",
    "sg:city":"Saint-Leonard",
    "sg:classifiers":[
        {
            "category":"Shopping",
            "type":"Retail Goods"
        }
    ],
    "sg:phone":"+1 514 376 2288",
    "sg:postcode":"H1S 1J7",
    "sg:province":"QC",
    "sg:tags":[
        "telephone",
        "cellular"
    ],
    "wof:name":"Espace Bell",
    "wof:placetype":"venue"
},
  "geometry": {"coordinates":[-73.595856,45.586124],"type":"Point"}
}