{
  "type": "Feature",
  "properties": {
    "iso:country":"CA",
    "sg:address":"40 Rue Chiasson",
    "sg:city":"Grand Falls",
    "sg:classifiers":[
        {
            "category":"Freight",
            "type":"Transportation"
        }
    ],
    "sg:phone":"+1 506 473 3621",
    "sg:postcode":"E3Y 1G1",
    "sg:province":"NB",
    "sg:tags":[
        "building",
        "house",
        "mover"
    ],
    "wof:name":"David Cote Housemovers",
    "wof:placetype":"venue"
},
  "geometry": {"coordinates":[-67.7188796997,47.0580368042],"type":"Point"}
}