{
  "type": "Feature",
  "properties": {
    "addr:full":"1430 Boul Saint-Jude S Alma QC G8B 3L4",
    "addr:housenumber":"1430",
    "addr:postcode":"g8b 3l4",
    "addr:street":"Boul Saint-Jude S",
    "iso:country":"CA",
    "sg:address":"1430 Boul Saint-Jude S",
    "sg:city":"Alma",
    "sg:classifiers":[
        {
            "category":"Shopping",
            "subcategory":"Computers & Home Electronics",
            "type":"Retail Goods"
        }
    ],
    "sg:phone":"+1 418 662 8011",
    "sg:postcode":"G8B 3L4",
    "sg:province":"QC",
    "sg:tags":[
        "parts",
        "supply"
    ],
    "wof:name":"Fournitures Informatiques Reg",
    "wof:placetype":"venue"
},
  "geometry": {"coordinates":[-71.667633,48.53146],"type":"Point"}
}