{
  "type": "Feature",
  "properties": {
    "addr:full":"1907 Ellesmere Rd Scarborough ON M1H 2W5",
    "addr:housenumber":"1907",
    "addr:postcode":"m1h 2w5",
    "addr:street":"Ellesmere Rd",
    "iso:country":"CA",
    "sg:address":"1907 Ellesmere Rd",
    "sg:city":"Scarborough",
    "sg:classifiers":[
        {
            "category":"Personal",
            "subcategory":"Beauty Salon",
            "type":"Services"
        }
    ],
    "sg:phone":"+1 416 438 4444",
    "sg:postcode":"M1H 2W5",
    "sg:province":"ON",
    "sg:tags":[
        "barber"
    ],
    "wof:name":"John Spanos Barber Shop",
    "wof:placetype":"venue"
},
  "geometry": {"coordinates":[-79.239525,43.774628],"type":"Point"}
}