{
  "type": "Feature",
  "properties": {
    "addr:full":"1322 Georgia St W Vancouver BC V6E 4S2",
    "addr:housenumber":"1322",
    "addr:postcode":"v6e 4s2",
    "addr:street":"Georgia St W",
    "iso:country":"CA",
    "sg:address":"1322 Georgia St W",
    "sg:city":"Vancouver",
    "sg:classifiers":[
        {
            "category":"Shopping",
            "subcategory":"Gifts & Souvenirs",
            "type":"Retail Goods"
        }
    ],
    "sg:phone":"+1 604 696 6116",
    "sg:postcode":"V6E 4S2",
    "sg:province":"BC",
    "sg:tags":[
        "shop"
    ],
    "wof:name":"Yonko International",
    "wof:placetype":"venue"
},
  "geometry": {"coordinates":[-123.127258,49.288361],"type":"Point"}
}