{
  "type": "Feature",
  "properties": {
    "addr:full":"712 Broad Rd Geary NB E2V 3W6",
    "addr:housenumber":"712",
    "addr:postcode":"e2v 3w6",
    "addr:street":"Broad Rd",
    "iso:country":"CA",
    "sg:address":"712 Broad Rd",
    "sg:city":"Geary",
    "sg:classifiers":[
        {
            "category":"Organizations",
            "subcategory":"Professional Association",
            "type":"Services"
        }
    ],
    "sg:phone":"+1 506 357 5463",
    "sg:postcode":"E2V 3W6",
    "sg:province":"NB",
    "wof:name":"Geary Lions Club",
    "wof:placetype":"venue"
},
  "geometry": {"coordinates":[-66.4767456055,45.7739448547],"type":"Point"}
}