{
  "type": "Feature",
  "properties": {
    "addr:full":"4483 Boul Samson Laval QC H7W 2H2",
    "addr:housenumber":"4483",
    "addr:postcode":"h7w 2h2",
    "addr:street":"Boul Samson",
    "iso:country":"CA",
    "sg:address":"4483 Boul Samson",
    "sg:city":"Laval",
    "sg:classifiers":[
        {
            "category":"Personal",
            "subcategory":"Beauty Salon",
            "type":"Services"
        }
    ],
    "sg:phone":"+1 450 686 2997",
    "sg:postcode":"H7W 2H2",
    "sg:province":"QC",
    "wof:name":"Coiffure DE L'Ile Paton",
    "wof:placetype":"venue"
},
  "geometry": {"coordinates":[-73.7552871704,45.5301094055],"type":"Point"}
}