{
  "type": "Feature",
  "properties": {
    "addr:full":"Markdale ON N0C 1H0",
    "addr:postcode":"n0c 1h0",
    "iso:country":"CA",
    "sg:city":"Markdale",
    "sg:classifiers":[
        {
            "category":"Building & Trades",
            "subcategory":"Construction",
            "type":"Services"
        }
    ],
    "sg:phone":"+1 519 986 2674",
    "sg:postcode":"N0C 1H0",
    "sg:province":"ON",
    "sg:tags":[
        "excavating",
        "contractor"
    ],
    "wof:name":"Al Thompson Excavating",
    "wof:placetype":"venue"
},
  "geometry": {"coordinates":[-80.648895,44.319134],"type":"Point"}
}