{
  "type": "Feature",
  "properties": {
    "addr:full":"2459 Islington Ave Etobicoke ON M9W 3X9",
    "addr:housenumber":"2459",
    "addr:postcode":"m9w 3x9",
    "addr:street":"Islington Ave",
    "iso:country":"CA",
    "sg:address":"2459 Islington Ave",
    "sg:city":"Etobicoke",
    "sg:classifiers":[
        {
            "category":"Organizations",
            "subcategory":"Religious Organization",
            "type":"Services"
        }
    ],
    "sg:phone":"+1 416 741 1110",
    "sg:postcode":"M9W 3X9",
    "sg:province":"ON",
    "sg:tags":[
        "church"
    ],
    "wof:name":"Rexdale Alliance Church",
    "wof:placetype":"venue"
},
  "geometry": {"coordinates":[-79.560394,43.726768],"type":"Point"}
}