{
  "type": "Feature",
  "properties": {
    "iso:country":"CA",
    "sg:city":"Toronto",
    "sg:classifiers":[
        {
            "category":"Real Estate",
            "subcategory":"Architect",
            "type":"Services"
        }
    ],
    "sg:phone":"+1 416 968 7654",
    "sg:postcode":"M4W 3M3",
    "sg:province":"ON",
    "wof:name":"Dodd, Lawrence",
    "wof:placetype":"venue"
},
  "geometry": {"coordinates":[-79.37837219239999,43.6721725464],"type":"Point"}
}