{
  "type": "Feature",
  "properties": {
    "iso:country":"CA",
    "sg:address":"572 Rue Guenard",
    "sg:city":"Beauport",
    "sg:classifiers":[
        {
            "category":"Professional",
            "subcategory":"Advertising",
            "type":"Services"
        }
    ],
    "sg:phone":"+1 418 666 3355",
    "sg:postcode":"G1B 3B4",
    "sg:province":"QC",
    "sg:tags":[
        "counselor"
    ],
    "wof:name":"Groupe Multi Media",
    "wof:placetype":"venue"
},
  "geometry": {"coordinates":[-71.211784,46.896214],"type":"Point"}
}