{
  "type": "Feature",
  "properties": {
    "iso:country":"CA",
    "sg:address":"252 Main St S",
    "sg:city":"Winkler",
    "sg:classifiers":[
        {
            "category":"Shopping",
            "subcategory":"Florist",
            "type":"Retail Goods"
        }
    ],
    "sg:phone":"+1 204 325 1907",
    "sg:postcode":"R6W 2P5",
    "sg:province":"MB",
    "wof:name":"Heide's Florist",
    "wof:placetype":"venue"
},
  "geometry": {"coordinates":[-97.9392547607,49.1717224121],"type":"Point"}
}