{
  "type": "Feature",
  "properties": {
    "addr:full":"1206 Rue Drummond Montreal QC H3G 1V7",
    "addr:housenumber":"1206",
    "addr:postcode":"h3g 1v7",
    "addr:street":"Rue Drummond",
    "iso:country":"CA",
    "sg:address":"1206 Rue Drummond",
    "sg:city":"Montreal",
    "sg:classifiers":[
        {
            "category":"Personal",
            "subcategory":"Beauty Salon",
            "type":"Services"
        }
    ],
    "sg:phone":"+1 514 875 5464",
    "sg:postcode":"H3G 1V7",
    "sg:province":"QC",
    "wof:name":"King Cuts",
    "wof:placetype":"venue"
},
  "geometry": {"coordinates":[-73.57313499999999,45.497959],"type":"Point"}
}