{
  "type": "Feature",
  "properties": {
    "iso:country":"CA",
    "sg:city":"Belleville",
    "sg:classifiers":[
        {
            "category":"Food & Beverages",
            "subcategory":"Liquor & Beverages",
            "type":"Retail Goods"
        }
    ],
    "sg:phone":"+1 613 966 2693",
    "sg:postcode":"K8N 5P9",
    "sg:province":"ON",
    "sg:tags":[
        "beer",
        "ale"
    ],
    "wof:name":"Belleville Beer & Wine Supls",
    "wof:placetype":"venue"
},
  "geometry": {"coordinates":[-77.343307,44.16885],"type":"Point"}
}