{
  "type": "Feature",
  "properties": {
    "addr:full":"50 Finkle St Woodstock ON N4S 3C8",
    "addr:housenumber":"50",
    "addr:postcode":"n4s 3c8",
    "addr:street":"Finkle St",
    "iso:country":"CA",
    "sg:address":"50 Finkle St",
    "sg:city":"Woodstock",
    "sg:classifiers":[
        {
            "category":"Organizations",
            "subcategory":"Religious Organization",
            "type":"Services"
        }
    ],
    "sg:phone":"+1 519 421 1249",
    "sg:postcode":"N4S 3C8",
    "sg:province":"ON",
    "sg:tags":[
        "church"
    ],
    "wof:name":"Grace Presbyterian Church",
    "wof:placetype":"venue"
},
  "geometry": {"coordinates":[-80.757721,43.128696],"type":"Point"}
}