{
  "type": "Feature",
  "properties": {
    "addr:full":"Richmond BC V7E 3L6",
    "addr:postcode":"v7e 3l6",
    "iso:country":"CA",
    "sg:city":"Richmond",
    "sg:classifiers":[
        {
            "category":"Shopping",
            "subcategory":"Clothing, Apparel, & Fashions",
            "type":"Retail Goods"
        }
    ],
    "sg:phone":"+1 604 277 3331",
    "sg:postcode":"V7E 3L6",
    "sg:province":"BC",
    "sg:tags":[
        "boutique"
    ],
    "wof:name":"Jet-Lag Travel Boutique Inc",
    "wof:placetype":"venue"
},
  "geometry": {"coordinates":[-123.18446400000001,49.125996],"type":"Point"}
}