{
  "type": "Feature",
  "properties": {
    "addr:full":"504 Old Hope Princeton Way Hope BC V0X 1L4",
    "addr:housenumber":"504",
    "addr:postcode":"v0x 1l4",
    "addr:street":"Old Hope Princeton Way",
    "iso:country":"CA",
    "sg:address":"504 Old Hope Princeton Way",
    "sg:city":"Hope",
    "sg:classifiers":[
        {
            "category":"Travel",
            "subcategory":"Hotels & Motels",
            "type":"Entertainment"
        }
    ],
    "sg:phone":"+1 604 869 5715",
    "sg:postcode":"V0X 1L4",
    "sg:province":"BC",
    "wof:name":"Lucky Strike Motel",
    "wof:placetype":"venue"
},
  "geometry": {"coordinates":[-121.43454699999999,49.375034],"type":"Point"}
}