{
  "type": "Feature",
  "properties": {
    "addr:full":"1235 Queen St E Sault Ste Marie ON P6A 2E5",
    "addr:housenumber":"1235",
    "addr:postcode":"p6a 2e5",
    "addr:street":"Queen St E",
    "iso:country":"CA",
    "sg:address":"1235 Queen St E",
    "sg:city":"Sault Ste Marie",
    "sg:classifiers":[
        {
            "category":"Government",
            "subcategory":"Office",
            "type":"Public Place"
        }
    ],
    "sg:phone":"+1 705 946 2981",
    "sg:postcode":"P6A 2E5",
    "sg:province":"ON",
    "wof:name":"Ontario Forest Research Inst",
    "wof:placetype":"venue"
},
  "geometry": {"coordinates":[-84.3025512695,46.5042419434],"type":"Point"}
}