{
  "type": "Feature",
  "properties": {
    "addr:full":"4385 Rue Lavoisier Quebec QC G2C 1G8",
    "addr:housenumber":"4385",
    "addr:postcode":"g2c 1g8",
    "addr:street":"Rue Lavoisier",
    "iso:country":"CA",
    "sg:address":"4385 Rue Lavoisier",
    "sg:city":"Quebec",
    "sg:classifiers":[
        {
            "category":"Building & Trades",
            "subcategory":"Construction",
            "type":"Services"
        }
    ],
    "sg:phone":"+1 418 842 3346",
    "sg:postcode":"G2C 1G8",
    "sg:province":"QC",
    "sg:tags":[
        "general",
        "contractor"
    ],
    "wof:name":"Construction Jp Goulet Inc",
    "wof:placetype":"venue"
},
  "geometry": {"coordinates":[-71.3524551392,46.8280944824],"type":"Point"}
}