{
  "type": "Feature",
  "properties": {
    "iso:country":"CA",
    "sg:city":"Mississauga",
    "sg:classifiers":[
        {
            "category":"Wholesale",
            "subcategory":"Meat",
            "type":"Manufacturing & Wholesale Goods"
        }
    ],
    "sg:phone":"+1 905 826 7545",
    "sg:postcode":"L5N 3L9",
    "sg:province":"ON",
    "wof:name":"Shannon's Meats Inc",
    "wof:placetype":"venue"
},
  "geometry": {"coordinates":[-79.72547149659999,43.5930213928],"type":"Point"}
}