{
  "type": "Feature",
  "properties": {
    "addr:full":"188 Hilltop Dr Quesnel BC V2J 3P9",
    "addr:housenumber":"188",
    "addr:postcode":"v2j 3p9",
    "addr:street":"Hilltop Dr",
    "iso:country":"CA",
    "sg:address":"188 Hilltop Dr",
    "sg:city":"Quesnel",
    "sg:classifiers":[
        {
            "category":"Manufacturing",
            "subcategory":"Tools & Machinery",
            "type":"Manufacturing & Wholesale Goods"
        }
    ],
    "sg:phone":"+1 250 992 8991",
    "sg:postcode":"V2J 3P9",
    "sg:province":"BC",
    "sg:tags":[
        "equipment",
        "industrial",
        "hydraulic",
        "supply"
    ],
    "wof:name":"Carmar Supplies Ltd",
    "wof:placetype":"venue"
},
  "geometry": {"coordinates":[-122.505424,53.007366],"type":"Point"}
}