{
  "type": "Feature",
  "properties": {
    "addr:full":"405 Tower St S Fergus ON N1M 2P8",
    "addr:housenumber":"405",
    "addr:postcode":"n1m 2p8",
    "addr:street":"Tower St S",
    "iso:country":"CA",
    "sg:address":"405 Tower St S",
    "sg:city":"Fergus",
    "sg:classifiers":[
        {
            "category":"Shopping",
            "subcategory":"Musical Instruments",
            "type":"Retail Goods"
        }
    ],
    "sg:phone":"+1 519 831 6635",
    "sg:postcode":"N1M 2P8",
    "sg:province":"ON",
    "wof:name":"Bronte Group Inc",
    "wof:placetype":"venue"
},
  "geometry": {"coordinates":[-80.3753662109,43.7014656067],"type":"Point"}
}