{
  "type": "Feature",
  "properties": {
    "iso:country":"CA",
    "sg:address":"1250 2E Rue",
    "sg:city":"Sainte-Marie",
    "sg:classifiers":[
        {
            "category":"Home & Garden",
            "subcategory":"Home Furnishings",
            "type":"Retail Goods"
        }
    ],
    "sg:phone":"+1 418 386 3378",
    "sg:postcode":"G6E 1G8",
    "sg:province":"QC",
    "sg:tags":[
        "equipment",
        "bath",
        "supply"
    ],
    "wof:name":"Entreprises Airbrass Inc",
    "wof:placetype":"venue"
},
  "geometry": {"coordinates":[-65.9838256836,48.1726264954],"type":"Point"}
}