{
  "type": "Feature",
  "properties": {
    "addr:full":"908 King St E Cambridge ON N3H 3P3",
    "addr:housenumber":"908",
    "addr:postcode":"n3h 3p3",
    "addr:street":"King St E",
    "iso:country":"CA",
    "sg:address":"908 King St E",
    "sg:city":"Cambridge",
    "sg:classifiers":[
        {
            "category":"Shopping",
            "subcategory":"Bicycles & Sporting Goods",
            "type":"Retail Goods"
        }
    ],
    "sg:phone":"+1 519 650 9883",
    "sg:postcode":"N3H 3P3",
    "sg:province":"ON",
    "sg:tags":[
        "shoes"
    ],
    "wof:name":"Ortho Kinetics Inc",
    "wof:placetype":"venue"
},
  "geometry": {"coordinates":[-80.3554382324,43.3941688538],"type":"Point"}
}