{
  "type": "Feature",
  "properties": {
    "iso:country":"CA",
    "sg:city":"Bathurst",
    "sg:classifiers":[
        {
            "category":"Food & Beverages",
            "subcategory":"Meat & Fish",
            "type":"Retail Goods"
        }
    ],
    "sg:phone":"+1 506 826 3335",
    "sg:postcode":"E2A 1Y5",
    "sg:province":"NB",
    "wof:name":"M & R Quality Meats",
    "wof:placetype":"venue"
},
  "geometry": {"coordinates":[-65.62512207029999,47.6054267883],"type":"Point"}
}