{
  "type": "Feature",
  "properties": {
    "addr:full":"6450 27 St NW Edmonton AB T6P 1M6",
    "addr:housenumber":"6450",
    "addr:postcode":"t6p 1m6",
    "addr:street":"27 St Nw",
    "iso:country":"CA",
    "sg:address":"6450 27 St NW",
    "sg:city":"Edmonton",
    "sg:classifiers":[
        {
            "category":"Freight",
            "type":"Transportation"
        }
    ],
    "sg:phone":"+1 780 465 7705",
    "sg:postcode":"T6P 1M6",
    "sg:province":"AB",
    "sg:tags":[
        "trucking"
    ],
    "wof:name":"Double C Trucking Inc",
    "wof:placetype":"venue"
},
  "geometry": {"coordinates":[-113.38208,53.50119],"type":"Point"}
}