{
  "type": "Feature",
  "properties": {
    "iso:country":"CA",
    "sg:city":"Guelph",
    "sg:classifiers":[
        {
            "category":"Building & Trades",
            "subcategory":"Electrical",
            "type":"Services"
        }
    ],
    "sg:phone":"+1 519 824 8192",
    "sg:postcode":"N1E 1N4",
    "sg:province":"ON",
    "sg:tags":[
        "electric",
        "contractor"
    ],
    "wof:name":"S Jamrik Electric Ltd",
    "wof:placetype":"venue"
},
  "geometry": {"coordinates":[-80.25835418699999,43.5654258728],"type":"Point"}
}