{
  "type": "Feature",
  "properties": {
    "addr:full":"Main St Point Leamington NL A0H 1Z0",
    "addr:postcode":"a0h 1z0",
    "addr:street":"Main St Point",
    "iso:country":"CA",
    "sg:address":"Main St",
    "sg:city":"Point Leamington",
    "sg:classifiers":[
        {
            "category":"Food & Beverages",
            "subcategory":"Groceries & Convenience Stores",
            "type":"Retail Goods"
        }
    ],
    "sg:phone":"+1 709 484 3737",
    "sg:postcode":"A0H 1Z0",
    "sg:province":"NL",
    "wof:name":"Uptown Convenience",
    "wof:placetype":"venue"
},
  "geometry": {"coordinates":[-55.406029,49.319309],"type":"Point"}
}