{
  "type": "Feature",
  "properties": {
    "addr:full":"73 Alness St North York ON M3J 2H2",
    "addr:housenumber":"73",
    "addr:postcode":"m3j 2h2",
    "addr:street":"Alness St",
    "iso:country":"CA",
    "sg:address":"73 Alness St",
    "sg:city":"North York",
    "sg:classifiers":[
        {
            "category":"Shopping",
            "subcategory":"Computers & Home Electronics",
            "type":"Retail Goods"
        }
    ],
    "sg:phone":"+1 416 663 9315",
    "sg:postcode":"M3J 2H2",
    "sg:province":"ON",
    "sg:tags":[
        "parts",
        "supply"
    ],
    "wof:name":"Sistek Data",
    "wof:placetype":"venue"
},
  "geometry": {"coordinates":[-79.472786,43.773354],"type":"Point"}
}