{
  "type": "Feature",
  "properties": {
    "addr:full":"1199 St. Peter Ave Bathurst NB E2A 3A1",
    "addr:housenumber":"1199",
    "addr:postcode":"e2a 3a1",
    "addr:street":"St. Peter Ave",
    "iso:country":"CA",
    "sg:address":"1199 St. Peter Ave",
    "sg:city":"Bathurst",
    "sg:classifiers":[
        {
            "category":"Professional",
            "subcategory":"Accounting & Tax Preparation",
            "type":"Services"
        }
    ],
    "sg:phone":"+1 506 546 9822",
    "sg:postcode":"E2A 3A1",
    "sg:province":"NB",
    "sg:tags":[
        "accountant"
    ],
    "wof:name":"Nepisiguit Accounting & Bkpg",
    "wof:placetype":"venue"
},
  "geometry": {"coordinates":[-65.6776351929,47.6373634338],"type":"Point"}
}