{
  "type": "Feature",
  "properties": {
    "iso:country":"CA",
    "sg:address":"37 King St W",
    "sg:city":"Harrow",
    "sg:classifiers":[
        {
            "category":"Professional",
            "subcategory":"Accounting & Tax Preparation",
            "type":"Services"
        }
    ],
    "sg:phone":"+1 519 738 2236",
    "sg:postcode":"N0R 1G0",
    "sg:province":"ON",
    "sg:tags":[
        "accountant"
    ],
    "wof:name":"Wolfe, Mary CA",
    "wof:placetype":"venue"
},
  "geometry": {"coordinates":[-82.91873168950001,42.0354232788],"type":"Point"}
}