{
  "type": "Feature",
  "properties": {
    "addr:full":"1065 Cambie St Vancouver BC V6B 5L7",
    "addr:housenumber":"1065",
    "addr:postcode":"bc v6b 5l7",
    "addr:street":"Cambie St",
    "iso:country":"CA",
    "sg:address":"1065 Cambie St",
    "sg:city":"Vancouver",
    "sg:classifiers":[
        {
            "category":"Health Services",
            "subcategory":"Chiropractor",
            "type":"Services"
        }
    ],
    "sg:phone":"+1 604 687 2900",
    "sg:postcode":"V6B 5L7",
    "sg:province":"BC",
    "wof:name":"Pacific Chiropractic",
    "wof:placetype":"venue"
},
  "geometry": {"coordinates":[-123.119179,49.275269],"type":"Point"}
}