{
  "type": "Feature",
  "properties": {
    "addr:full":"149 Rose Glen Rd Port Hope ON L1A 3V6",
    "addr:housenumber":"149",
    "addr:postcode":"l1a 3v6",
    "addr:street":"Rose Glen Rd",
    "iso:country":"CA",
    "sg:address":"149 Rose Glen Rd",
    "sg:city":"Port Hope",
    "sg:classifiers":[
        {
            "category":"Retail",
            "subcategory":"Auto Repair",
            "type":"Services"
        }
    ],
    "sg:phone":"+1 905 372 0705",
    "sg:postcode":"L1A 3V6",
    "sg:province":"ON",
    "sg:tags":[
        "repairing",
        "automobile",
        "body",
        "painting"
    ],
    "wof:name":"Lakeshore Auto Body & Glass",
    "wof:placetype":"venue"
},
  "geometry": {"coordinates":[-78.2855,43.968922],"type":"Point"}
}