{
  "type": "Feature",
  "properties": {
    "addr:full":"4935 Rue Bourg Saint-Laurent QC H4T 1H9",
    "addr:housenumber":"4935",
    "addr:postcode":"h4t 1h9",
    "addr:street":"Rue Bourg",
    "iso:country":"CA",
    "sg:address":"4935 Rue Bourg",
    "sg:city":"Saint-Laurent",
    "sg:classifiers":[
        {
            "category":"Wholesale",
            "subcategory":"Hardware",
            "type":"Manufacturing & Wholesale Goods"
        }
    ],
    "sg:phone":"+1 514 344 1555",
    "sg:postcode":"H4T 1H9",
    "sg:province":"QC",
    "sg:tags":[
        "conditioning",
        "air",
        "system",
        "contractor"
    ],
    "wof:name":"Brock Engineering",
    "wof:placetype":"venue"
},
  "geometry": {"coordinates":[-73.701492,45.472763],"type":"Point"}
}