{
  "type": "Feature",
  "properties": {
    "addr:full":"2019 Eglinton Ave W York ON M6E 2K1",
    "addr:housenumber":"2019",
    "addr:postcode":"m6e 2k1",
    "addr:street":"Eglinton Ave W",
    "iso:country":"CA",
    "sg:address":"2019 Eglinton Ave W",
    "sg:city":"York",
    "sg:classifiers":[
        {
            "category":"Personal",
            "subcategory":"Beauty Salon",
            "type":"Services"
        }
    ],
    "sg:phone":"+1 416 780 0438",
    "sg:postcode":"M6E 2K1",
    "sg:province":"ON",
    "wof:name":"Mena's Braiding & Hair Salon",
    "wof:placetype":"venue"
},
  "geometry": {"coordinates":[-79.455521,43.694393],"type":"Point"}
}