{
  "type": "Feature",
  "properties": {
    "addr:full":"2950 11 Ave NE Salmon Arm BC V1E 2S3",
    "addr:housenumber":"2950",
    "addr:postcode":"v1e 2s3",
    "addr:street":"11 Ave Ne",
    "iso:country":"CA",
    "sg:address":"2950 11 Ave NE",
    "sg:city":"Salmon Arm",
    "sg:classifiers":[
        {
            "category":"Bars & Pubs",
            "type":"Food & Drink"
        }
    ],
    "sg:phone":"+1 250 832 0266",
    "sg:postcode":"V1E 2S3",
    "sg:province":"BC",
    "wof:name":"Setters Neighborhood Pub Ltd",
    "wof:placetype":"venue"
},
  "geometry": {"coordinates":[-119.25254099999999,50.707977],"type":"Point"}
}