{
  "type": "Feature",
  "properties": {
    "addr:full":"1020 Mainland St # 28 Vancouver BC V6B 2T5",
    "addr:housenumber":"1020",
    "addr:postcode":"bc v6b 2t5",
    "addr:street":"Mainland St # 28",
    "iso:country":"CA",
    "sg:address":"1020 Mainland St # 28",
    "sg:city":"Vancouver",
    "sg:classifiers":[
        {
            "category":"Real Estate",
            "subcategory":"Architect",
            "type":"Services"
        }
    ],
    "sg:phone":"+1 604 685 4919",
    "sg:postcode":"V6B 2T5",
    "sg:province":"BC",
    "sg:tags":[
        "illustrator",
        "architectural"
    ],
    "wof:name":"Calum Srigley Design Conslnt",
    "wof:placetype":"venue"
},
  "geometry": {"coordinates":[-123.119163513,49.2762985229],"type":"Point"}
}