{
  "type": "Feature",
  "properties": {
    "addr:full":"96 Cornwallis Ave New Minas NS B4N 3M7",
    "addr:housenumber":"96",
    "addr:postcode":"b4n 3m7",
    "addr:street":"Cornwallis Ave",
    "iso:country":"CA",
    "sg:address":"96 Cornwallis Ave",
    "sg:city":"New Minas",
    "sg:classifiers":[
        {
            "category":"Home & Garden",
            "subcategory":"Building Materials",
            "type":"Retail Goods"
        }
    ],
    "sg:phone":"+1 902 681 4219",
    "sg:postcode":"B4N 3M7",
    "sg:province":"NS",
    "sg:tags":[
        "mixed",
        "concrete"
    ],
    "wof:name":"Quality Concrete",
    "wof:placetype":"venue"
},
  "geometry": {"coordinates":[-64.44446600000001,45.070202],"type":"Point"}
}