{
  "type": "Feature",
  "properties": {
    "iso:country":"CA",
    "sg:address":"7228 Rue Cordner",
    "sg:city":"Lasalle",
    "sg:classifiers":[
        {
            "category":"Manufacturing",
            "subcategory":"Tools & Machinery",
            "type":"Manufacturing & Wholesale Goods"
        }
    ],
    "sg:phone":"+1 514 595 3490",
    "sg:postcode":"H8N 2W8",
    "sg:province":"QC",
    "sg:tags":[
        "machine",
        "shop",
        "cutting",
        "gear"
    ],
    "wof:name":"Engrenages Lasalle Inc",
    "wof:placetype":"venue"
},
  "geometry": {"coordinates":[-73.621704,45.446671],"type":"Point"}
}