{
  "type": "Feature",
  "properties": {
    "addr:full":"40 Rue Saint-Jean-Baptiste O Rigaud QC J0P 1P0",
    "addr:housenumber":"40",
    "addr:postcode":"j0p 1p0",
    "addr:street":"Rue Saint-Jean-Baptiste O",
    "iso:country":"CA",
    "sg:address":"40 Rue Saint-Jean-Baptiste O",
    "sg:city":"Rigaud",
    "sg:classifiers":[
        {
            "category":"Personal",
            "subcategory":"Beauty Salon",
            "type":"Services"
        }
    ],
    "sg:phone":"+1 450 451 5420",
    "sg:postcode":"J0P 1P0",
    "sg:province":"QC",
    "wof:name":"Myrage Coiffure",
    "wof:placetype":"venue"
},
  "geometry": {"coordinates":[-74.298706,45.479156],"type":"Point"}
}