{
  "type": "Feature",
  "properties": {
    "addr:full":"12606 124 St NW Edmonton AB T5L 0N7",
    "addr:housenumber":"12606",
    "addr:postcode":"t5l 0n7",
    "addr:street":"124 St Nw",
    "iso:country":"CA",
    "sg:address":"12606 124 St NW",
    "sg:city":"Edmonton",
    "sg:classifiers":[
        {
            "category":"Retail",
            "subcategory":"Auto Repair",
            "type":"Services"
        }
    ],
    "sg:phone":"+1 780 455 7422",
    "sg:postcode":"T5L 0N7",
    "sg:province":"AB",
    "sg:tags":[
        "repairing",
        "automobile"
    ],
    "wof:name":"Arlon Car Care",
    "wof:placetype":"venue"
},
  "geometry": {"coordinates":[-113.536072,53.582512],"type":"Point"}
}