{
  "type": "Feature",
  "properties": {
    "iso:country":"CA",
    "sg:address":"12606 124 St NW",
    "sg:city":"Edmonton",
    "sg:classifiers":[
        {
            "category":"Retail",
            "subcategory":"Auto Repair",
            "type":"Services"
        }
    ],
    "sg:phone":"+1 780 455 7422",
    "sg:postcode":"T5L 0N7",
    "sg:province":"AB",
    "sg:tags":[
        "repairing",
        "automobile"
    ],
    "wof:name":"Arlon Car Care",
    "wof:placetype":"venue"
},
  "geometry": {"coordinates":[-113.536072,53.582512],"type":"Point"}
}