{
  "type": "Feature",
  "properties": {
    "addr:full":"1312 Wellington St W King City ON L7B 1K5",
    "addr:housenumber":"1312",
    "addr:postcode":"l7b 1k5",
    "addr:street":"Wellington St W",
    "iso:country":"CA",
    "sg:address":"1312 Wellington St W",
    "sg:city":"King City",
    "sg:classifiers":[
        {
            "category":"Retail",
            "subcategory":"Auto Repair",
            "type":"Services"
        }
    ],
    "sg:phone":"+1 905 727 8880",
    "sg:postcode":"L7B 1K5",
    "sg:province":"ON",
    "sg:tags":[
        "wrecker"
    ],
    "wof:name":"Home Town Towing",
    "wof:placetype":"venue"
},
  "geometry": {"coordinates":[-79.510902,43.990791],"type":"Point"}
}