{
  "type": "Feature",
  "properties": {
    "addr:full":"41 Water St Pictou NS B0K 1H0",
    "addr:housenumber":"41",
    "addr:postcode":"b0k 1h0",
    "addr:street":"Water St",
    "iso:country":"CA",
    "sg:address":"41 Water St",
    "sg:city":"Pictou",
    "sg:classifiers":[
        {
            "category":"Insurance",
            "subcategory":"Insurance Agent",
            "type":"Services"
        }
    ],
    "sg:phone":"+1 902 485 4485",
    "sg:postcode":"B0K 1H0",
    "sg:province":"NS",
    "wof:name":"Fraser & Hoyt Insurance Ltd",
    "wof:placetype":"venue"
},
  "geometry": {"coordinates":[-62.7105636597,45.6759376526],"type":"Point"}
}