{
  "type": "Feature",
  "properties": {
    "addr:full":"665 Dundas St London ON N5W 2Z1",
    "addr:housenumber":"665",
    "addr:postcode":"n5w 2z1",
    "addr:street":"Dundas St",
    "iso:country":"CA",
    "sg:address":"665 Dundas St",
    "sg:city":"London",
    "sg:classifiers":[
        {
            "category":"Shopping",
            "subcategory":"Used Merchandise",
            "type":"Retail Goods"
        }
    ],
    "sg:phone":"+1 519 679 2035",
    "sg:postcode":"N5W 2Z1",
    "sg:province":"ON",
    "sg:tags":[
        "pawnbroker"
    ],
    "wof:name":"Centretown Pawn Broker",
    "wof:placetype":"venue"
},
  "geometry": {"coordinates":[-81.229767,42.989208],"type":"Point"}
}