{
  "type": "Feature",
  "properties": {
    "addr:full":"Liverpool NS B0T 1K0",
    "addr:postcode":"b0t 1k0",
    "iso:country":"CA",
    "sg:city":"Liverpool",
    "sg:classifiers":[
        {
            "category":"Food & Beverages",
            "subcategory":"Liquor & Beverages",
            "type":"Retail Goods"
        }
    ],
    "sg:phone":"+1 902 354 4197",
    "sg:postcode":"B0T 1K0",
    "sg:province":"NS",
    "sg:tags":[
        "store"
    ],
    "wof:name":"Nova Scotia Liquor Corp",
    "wof:placetype":"venue"
},
  "geometry": {"coordinates":[-64.71579742430001,44.0384025574],"type":"Point"}
}