{
  "type": "Feature",
  "properties": {
    "addr:full":"350 Burnhamthorpe Rd W Mississauga ON L5B 3J1",
    "addr:housenumber":"350",
    "addr:postcode":"l5b 3j1",
    "addr:street":"Burnhamthorpe Rd W",
    "iso:country":"CA",
    "sg:address":"350 Burnhamthorpe Rd W",
    "sg:city":"Mississauga",
    "sg:classifiers":[
        {
            "category":"Banks & Credit Unions",
            "subcategory":"Bank",
            "type":"Services"
        }
    ],
    "sg:phone":"+1 905 272 4680",
    "sg:postcode":"L5B 3J1",
    "sg:province":"ON",
    "wof:name":"National Bank of Canada",
    "wof:placetype":"venue"
},
  "geometry": {"coordinates":[-79.644417,43.585567],"type":"Point"}
}