{
  "type": "Feature",
  "properties": {
    "addr:full":"1947 Keele St York ON M6M 3X9",
    "addr:housenumber":"1947",
    "addr:postcode":"m6m 3x9",
    "addr:street":"Keele St",
    "iso:country":"CA",
    "sg:address":"1947 Keele St",
    "sg:city":"York",
    "sg:classifiers":[
        {
            "category":"Organizations",
            "subcategory":"Religious Organization",
            "type":"Services"
        }
    ],
    "sg:phone":"+1 416 652 1764",
    "sg:postcode":"M6M 3X9",
    "sg:province":"ON",
    "sg:tags":[
        "church"
    ],
    "wof:name":"Church of God",
    "wof:placetype":"venue"
},
  "geometry": {"coordinates":[-79.4743423462,43.6889801025],"type":"Point"}
}