{
  "type": "Feature",
  "properties": {
    "iso:country":"CA",
    "sg:address":"100 Kinosota Rd S",
    "sg:city":"Amaranth",
    "sg:classifiers":[
        {
            "category":"Travel",
            "subcategory":"Hotels & Motels",
            "type":"Entertainment"
        }
    ],
    "sg:phone":"+1 204 843 2248",
    "sg:postcode":"R0H 0B0",
    "sg:province":"MB",
    "wof:name":"Amaranth Inn",
    "wof:placetype":"venue"
},
  "geometry": {"coordinates":[-98.73797607420001,50.5949554443],"type":"Point"}
}