{
  "type": "Feature",
  "properties": {
    "iso:country":"CA",
    "sg:address":"1807 42 St SE",
    "sg:city":"Calgary",
    "sg:classifiers":[
        {
            "category":"Wholesale",
            "subcategory":"Painting Supplies",
            "type":"Manufacturing & Wholesale Goods"
        }
    ],
    "sg:phone":"+1 403 278 1778",
    "sg:postcode":"T2B 1G1",
    "sg:province":"AB",
    "sg:tags":[
        "paint"
    ],
    "wof:name":"Micron Coatings Inc",
    "wof:placetype":"venue"
},
  "geometry": {"coordinates":[-113.97302999999999,51.037605],"type":"Point"}
}