{
  "type": "Feature",
  "properties": {
    "iso:country":"CA",
    "sg:address":"2100 Boul Des Laurentides",
    "sg:city":"Laval",
    "sg:classifiers":[
        {
            "category":"Retail",
            "subcategory":"Auto Repair",
            "type":"Services"
        }
    ],
    "sg:phone":"+1 450 667 9900",
    "sg:postcode":"H7M 2Y6",
    "sg:province":"QC",
    "sg:tags":[
        "repairing",
        "automobile"
    ],
    "wof:name":"Centre DE L'Auto Msl Inc",
    "wof:placetype":"venue"
},
  "geometry": {"coordinates":[-73.711823,45.587502],"type":"Point"}
}