{
  "type": "Feature",
  "properties": {
    "addr:full":"501 Ch DE LA Riviere S Saint-Eustache QC J7R 4K3",
    "addr:housenumber":"501",
    "addr:postcode":"j7r 4k3",
    "addr:street":"Ch De La Riviere S",
    "iso:country":"CA",
    "sg:address":"501 Ch DE LA Riviere S",
    "sg:city":"Saint-Eustache",
    "sg:classifiers":[
        {
            "category":"Professional",
            "subcategory":"Business Services",
            "type":"Services"
        }
    ],
    "sg:phone":"+1 450 491 0882",
    "sg:postcode":"J7R 4K3",
    "sg:province":"QC",
    "sg:tags":[
        "water",
        "treatment"
    ],
    "wof:name":"Systemes D'Eau Classiques Inc",
    "wof:placetype":"venue"
},
  "geometry": {"coordinates":[-73.9260177612,45.5626602173],"type":"Point"}
}