{
  "type": "Feature",
  "properties": {
    "iso:country":"CA",
    "sg:city":"Longueuil",
    "sg:classifiers":[
        {
            "category":"Real Estate",
            "subcategory":"Real Estate Agent",
            "type":"Services"
        }
    ],
    "sg:phone":"+1 450 670 5010",
    "sg:postcode":"J4J 5C3",
    "sg:province":"QC",
    "sg:tags":[
        "management"
    ],
    "wof:name":"Administration Villeneuve Inc",
    "wof:placetype":"venue"
},
  "geometry": {"coordinates":[-73.47825622560001,45.52318573],"type":"Point"}
}