{
  "type": "Feature",
  "properties": {
    "addr:full":"1300 Granville St Vancouver BC V6Z 1M7",
    "addr:housenumber":"1300",
    "addr:postcode":"v6z 1m7",
    "addr:street":"Granville St",
    "iso:country":"CA",
    "sg:address":"1300 Granville St",
    "sg:city":"Vancouver",
    "sg:classifiers":[
        {
            "category":"Bars & Pubs",
            "type":"Food & Drink"
        }
    ],
    "sg:phone":"+1 604 681 9253",
    "sg:postcode":"V6Z 1M7",
    "sg:province":"BC",
    "sg:tags":[
        "club",
        "night"
    ],
    "wof:name":"Yale Hotel",
    "wof:placetype":"venue"
},
  "geometry": {"coordinates":[-123.127831,49.276028],"type":"Point"}
}