{
  "type": "Feature",
  "properties": {
    "addr:full":"3330 Av Laurier E Montreal QC H1X 1V2",
    "addr:housenumber":"3330",
    "addr:postcode":"h1x 1v2",
    "addr:street":"Av Laurier E",
    "iso:country":"CA",
    "sg:address":"3330 Av Laurier E",
    "sg:city":"Montreal",
    "sg:classifiers":[
        {
            "category":"Organizations",
            "subcategory":"Religious Organization",
            "type":"Services"
        }
    ],
    "sg:phone":"+1 514 524 9564",
    "sg:postcode":"H1X 1V2",
    "sg:province":"QC",
    "sg:tags":[
        "church"
    ],
    "wof:name":"Holy Cross Parish",
    "wof:placetype":"venue"
},
  "geometry": {"coordinates":[-73.570206,45.551128],"type":"Point"}
}