{
  "type": "Feature",
  "properties": {
    "addr:full":"290 Rue Napoleon Saint-Tite QC G0X 3H0",
    "addr:housenumber":"290",
    "addr:postcode":"g0x 3h0",
    "addr:street":"Rue Napoleon",
    "iso:country":"CA",
    "sg:address":"290 Rue Napoleon",
    "sg:city":"Saint-Tite",
    "sg:classifiers":[
        {
            "category":"Health Services",
            "subcategory":"Nursing And Care Facility",
            "type":"Services"
        }
    ],
    "sg:phone":"+1 418 365 3717",
    "sg:postcode":"G0X 3H0",
    "sg:province":"QC",
    "sg:tags":[
        "home",
        "retirement",
        "community"
    ],
    "wof:name":"Residence Villa DE LA Montagne",
    "wof:placetype":"venue"
},
  "geometry": {"coordinates":[-72.5647201538,46.7221794128],"type":"Point"}
}