{
  "type": "Feature",
  "properties": {
    "addr:full":"25 Rue Principale O Notre-Dame-Des-Bois QC J0B 2E0",
    "addr:housenumber":"25",
    "addr:postcode":"j0b 2e0",
    "addr:street":"Rue Principale O",
    "iso:country":"CA",
    "sg:address":"25 Rue Principale O",
    "sg:city":"Notre-Dame-Des-Bois",
    "sg:classifiers":[
        {
            "category":"Banks & Credit Unions",
            "subcategory":"Bank",
            "type":"Services"
        }
    ],
    "sg:phone":"+1 819 888 2433",
    "sg:postcode":"J0B 2E0",
    "sg:province":"QC",
    "wof:name":"Caisses Desjardins",
    "wof:placetype":"venue"
},
  "geometry": {"coordinates":[-71.067139,45.394405],"type":"Point"}
}