{
  "type": "Feature",
  "properties": {
    "addr:full":"3310 8th St E Saskatoon SK S7H 4K1",
    "addr:housenumber":"3310",
    "addr:postcode":"s7h 4k1",
    "addr:street":"8Th St E",
    "iso:country":"CA",
    "sg:address":"3310 8th St E",
    "sg:city":"Saskatoon",
    "sg:classifiers":[
        {
            "category":"Personal",
            "subcategory":"Beauty Salon",
            "type":"Services"
        }
    ],
    "sg:phone":"+1 306 374 2773",
    "sg:postcode":"S7H 4K1",
    "sg:province":"SK",
    "wof:name":"Magicuts",
    "wof:placetype":"venue"
},
  "geometry": {"coordinates":[-106.602676,52.114422],"type":"Point"}
}