{
  "type": "Feature",
  "properties": {
    "addr:full":"840 Shore Rd Sydney Mines NS B1V 1A6",
    "addr:housenumber":"840",
    "addr:postcode":"b1v 1a6",
    "addr:street":"Shore Rd",
    "iso:country":"CA",
    "sg:address":"840 Shore Rd",
    "sg:city":"Sydney Mines",
    "sg:classifiers":[
        {
            "category":"Travel",
            "subcategory":"Hotels & Motels",
            "type":"Entertainment"
        }
    ],
    "sg:phone":"+1 902 544 1050",
    "sg:postcode":"B1V 1A6",
    "sg:province":"NS",
    "sg:tags":[
        "inn"
    ],
    "wof:name":"Gowrie House",
    "wof:placetype":"venue"
},
  "geometry": {"coordinates":[-60.222401,46.231716],"type":"Point"}
}