{
  "type": "Feature",
  "properties": {
    "addr:full":"3516 8 Ave NE # 1873 Calgary AB T2A 6K5",
    "addr:housenumber":"3516",
    "addr:postcode":"t2a 6k5",
    "addr:street":"8 Ave Ne # 1873",
    "iso:country":"CA",
    "sg:address":"3516 8 Ave NE # 1873",
    "sg:city":"Calgary",
    "sg:classifiers":[
        {
            "category":"Autos & Motor Vehicles",
            "subcategory":"Auto Supplies",
            "type":"Retail Goods"
        }
    ],
    "sg:phone":"+1 403 235 2254",
    "sg:postcode":"T2A 6K5",
    "sg:province":"AB",
    "sg:tags":[
        "automobile",
        "parts"
    ],
    "wof:name":"Canadian Tire Gas Bar",
    "wof:placetype":"venue"
},
  "geometry": {"coordinates":[-113.983688355,51.0596885681],"type":"Point"}
}