{
  "type": "Feature",
  "properties": {
    "addr:full":"88 Doran Rd Midhurst ON L0L 1X0",
    "addr:housenumber":"88",
    "addr:postcode":"l0l 1x0",
    "addr:street":"Doran Rd",
    "iso:country":"CA",
    "sg:address":"88 Doran Rd",
    "sg:city":"Midhurst",
    "sg:classifiers":[
        {
            "category":"Food & Beverages",
            "subcategory":"Specialty",
            "type":"Retail Goods"
        }
    ],
    "sg:phone":"+1 705 721 5318",
    "sg:postcode":"L0L 1X0",
    "sg:province":"ON",
    "sg:tags":[
        "distribution",
        "health",
        "diet"
    ],
    "wof:name":"Rawleigh Products Distributors",
    "wof:placetype":"venue"
},
  "geometry": {"coordinates":[-79.72966,44.451393],"type":"Point"}
}