{
  "type": "Feature",
  "properties": {
    "addr:full":"9598 170 St NW Edmonton AB T5T 5R5",
    "addr:housenumber":"9598",
    "addr:postcode":"t5t 5r5",
    "addr:street":"170 St Nw",
    "iso:country":"CA",
    "sg:address":"9598 170 St NW",
    "sg:city":"Edmonton",
    "sg:classifiers":[
        {
            "category":"Restaurant",
            "type":"Food & Drink"
        }
    ],
    "sg:phone":"+1 780 484 2160",
    "sg:postcode":"T5T 5R5",
    "sg:province":"AB",
    "wof:name":"Wendy's",
    "wof:placetype":"venue"
},
  "geometry": {"coordinates":[-113.615493774,53.5333442688],"type":"Point"}
}