{
  "type": "Feature",
  "properties": {
    "iso:country":"CA",
    "sg:city":"Barrie",
    "sg:classifiers":[
        {
            "category":"Personal",
            "subcategory":"Beauty Salon",
            "type":"Services"
        }
    ],
    "sg:phone":"+1 705 728 2200",
    "sg:postcode":"L4N 7Z9",
    "sg:province":"ON",
    "wof:name":"Scissor's Touch Hair Design",
    "wof:placetype":"venue"
},
  "geometry": {"coordinates":[-79.7222061157,44.4022903442],"type":"Point"}
}