{
  "type": "Feature",
  "properties": {
    "iso:country":"CA",
    "sg:city":"Wawa",
    "sg:classifiers":[
        {
            "category":"Shopping",
            "subcategory":"Gifts & Souvenirs",
            "type":"Retail Goods"
        }
    ],
    "sg:phone":"+1 705 856 2221",
    "sg:postcode":"P0S 1K0",
    "sg:province":"ON",
    "sg:tags":[
        "shop"
    ],
    "wof:name":"Rainbow Gifts",
    "wof:placetype":"venue"
},
  "geometry": {"coordinates":[-84.7706451416,47.9943695068],"type":"Point"}
}