{
  "type": "Feature",
  "properties": {
    "iso:country":"CA",
    "sg:address":"14 Keewatin Cres",
    "sg:city":"Nepean",
    "sg:classifiers":[
        {
            "category":"Building & Trades",
            "subcategory":"Landscaping Services",
            "type":"Services"
        }
    ],
    "sg:phone":"+1 613 224 8440",
    "sg:postcode":"K2E 6Z1",
    "sg:province":"ON",
    "sg:tags":[
        "designer",
        "landscape"
    ],
    "wof:name":"Altorio Design Consultants",
    "wof:placetype":"venue"
},
  "geometry": {"coordinates":[-75.72565460209999,45.3490486145],"type":"Point"}
}