{
  "type": "Feature",
  "properties": {
    "addr:full":"Mission BC V2V 1A4",
    "addr:postcode":"v2v 1a4",
    "iso:country":"CA",
    "sg:city":"Mission",
    "sg:classifiers":[
        {
            "category":"Retail",
            "subcategory":"Repair Shop",
            "type":"Services"
        }
    ],
    "sg:phone":"+1 604 826 8866",
    "sg:postcode":"V2V 1A4",
    "sg:province":"BC",
    "sg:tags":[
        "lock",
        "locksmith"
    ],
    "wof:name":"Mission Locksmith",
    "wof:placetype":"venue"
},
  "geometry": {"coordinates":[-122.261627197,49.147731781],"type":"Point"}
}