{
  "type": "Feature",
  "properties": {
    "addr:full":"40 Crossburn Dr North York ON M3B 2Z2",
    "addr:housenumber":"40",
    "addr:postcode":"m3b 2z2",
    "addr:street":"Crossburn Dr",
    "iso:country":"CA",
    "sg:address":"40 Crossburn Dr",
    "sg:city":"North York",
    "sg:classifiers":[
        {
            "category":"Shopping",
            "subcategory":"Computers & Home Electronics",
            "type":"Retail Goods"
        }
    ],
    "sg:phone":"+1 416 449 9173",
    "sg:postcode":"M3B 2Z2",
    "sg:province":"ON",
    "sg:tags":[
        "equipment",
        "dealer",
        "software"
    ],
    "wof:name":"Sumware Corp",
    "wof:placetype":"venue"
},
  "geometry": {"coordinates":[-79.34293365480001,43.7434501648],"type":"Point"}
}