{
  "type": "Feature",
  "properties": {
    "addr:full":"Salmon Arm BC V1E 1S9",
    "addr:postcode":"v1e 1s9",
    "iso:country":"CA",
    "sg:city":"Salmon Arm",
    "sg:classifiers":[
        {
            "category":"Retail",
            "subcategory":"Laundry & Dry Cleaning",
            "type":"Services"
        }
    ],
    "sg:phone":"+1 250 833 1470",
    "sg:postcode":"V1E 1S9",
    "sg:province":"BC",
    "sg:tags":[
        "cleaners"
    ],
    "wof:name":"Salmon Arm Drycleaners",
    "wof:placetype":"venue"
},
  "geometry": {"coordinates":[-119.292526245,50.69921875],"type":"Point"}
}