{
  "type": "Feature",
  "properties": {
    "addr:full":"6109 41 Ave Stettler AB T0C 2L1",
    "addr:housenumber":"6109",
    "addr:postcode":"t0c 2l1",
    "addr:street":"41 Ave",
    "iso:country":"CA",
    "sg:address":"6109 41 Ave",
    "sg:city":"Stettler",
    "sg:classifiers":[
        {
            "category":"Organizations",
            "subcategory":"Religious Organization",
            "type":"Services"
        }
    ],
    "sg:phone":"+1 403 742 5344",
    "sg:postcode":"T0C 2L1",
    "sg:province":"AB",
    "sg:tags":[
        "church"
    ],
    "wof:name":"Stettler Baptist Church",
    "wof:placetype":"venue"
},
  "geometry": {"coordinates":[-112.723876953,52.3143501282],"type":"Point"}
}