{
  "type": "Feature",
  "properties": {
    "iso:country":"CA",
    "sg:city":"Calgary",
    "sg:classifiers":[
        {
            "category":"Shopping",
            "subcategory":"Optical Goods",
            "type":"Retail Goods"
        }
    ],
    "sg:phone":"+1 403 219 3442",
    "sg:postcode":"T1Y 6H6",
    "sg:province":"AB",
    "sg:tags":[
        "sun",
        "goggles",
        "sunglasses",
        "optician"
    ],
    "wof:name":"Spectacles",
    "wof:placetype":"venue"
},
  "geometry": {"coordinates":[-113.982147217,51.0768585205],"type":"Point"}
}