{
  "type": "Feature",
  "properties": {
    "addr:full":"Burnaby BC V5C 5R4",
    "addr:postcode":"v5c 5r4",
    "iso:country":"CA",
    "sg:city":"Burnaby",
    "sg:classifiers":[
        {
            "category":"Health Services",
            "subcategory":"Doctor",
            "type":"Services"
        }
    ],
    "sg:phone":"+1 604 299 2411",
    "sg:postcode":"V5C 5R4",
    "sg:province":"BC",
    "sg:tags":[
        "physician",
        "surgeon"
    ],
    "wof:name":"Rasool, Meenaz H A MD",
    "wof:placetype":"venue"
},
  "geometry": {"coordinates":[-123.00502,49.267864],"type":"Point"}
}