{
  "type": "Feature",
  "properties": {
    "addr:full":"1925 Victoria Ave Regina SK S4P 0R3",
    "addr:housenumber":"1925",
    "addr:postcode":"s4p 0r3",
    "addr:street":"Victoria Ave",
    "iso:country":"CA",
    "sg:address":"1925 Victoria Ave",
    "sg:city":"Regina",
    "sg:classifiers":[
        {
            "category":"Organizations",
            "subcategory":"Community Association",
            "type":"Services"
        }
    ],
    "sg:phone":"+1 306 522 2641",
    "sg:postcode":"S4P 0R3",
    "sg:province":"SK",
    "sg:tags":[
        "club"
    ],
    "wof:name":"Assiniboia Club",
    "wof:placetype":"venue"
},
  "geometry": {"coordinates":[-104.60839799999999,50.446968],"type":"Point"}
}