{
  "type": "Feature",
  "properties": {
    "iso:country":"CA",
    "sg:city":"Bonavista",
    "sg:classifiers":[
        {
            "category":"Social Services",
            "type":"Services"
        }
    ],
    "sg:phone":"+1 709 468 2997",
    "sg:postcode":"A0C 1B0",
    "sg:province":"NL",
    "sg:tags":[
        "info",
        "program",
        "referral"
    ],
    "wof:name":"Crime Prevention Skateboard",
    "wof:placetype":"venue"
},
  "geometry": {"coordinates":[-53.0991287231,48.6561279297],"type":"Point"}
}