{
  "type": "Feature",
  "properties": {
    "addr:full":"Beaupre QC G0A 1E0",
    "addr:postcode":"g0a 1e0",
    "addr:street":"Beaupre",
    "iso:country":"CA",
    "sg:city":"Beaupre",
    "sg:classifiers":[
        {
            "category":"Retail",
            "subcategory":"Auto Repair",
            "type":"Services"
        }
    ],
    "sg:phone":"+1 418 827 4357",
    "sg:postcode":"G0A 1E0",
    "sg:province":"QC",
    "sg:tags":[
        "repairing",
        "automobile"
    ],
    "wof:name":"Garage Paul Fortin",
    "wof:placetype":"venue"
},
  "geometry": {"coordinates":[-70.894218,47.040871],"type":"Point"}
}