{
  "type": "Feature",
  "properties": {
    "addr:full":"2075 Danforth Ave Toronto ON M4C 1J8",
    "addr:housenumber":"2075",
    "addr:postcode":"m4c 1j8",
    "addr:street":"Danforth Ave",
    "iso:country":"CA",
    "sg:address":"2075 Danforth Ave",
    "sg:city":"Toronto",
    "sg:classifiers":[
        {
            "category":"Food & Beverages",
            "subcategory":"Bakery",
            "type":"Retail Goods"
        }
    ],
    "sg:phone":"+1 416 694 9153",
    "sg:postcode":"M4C 1J8",
    "sg:province":"ON",
    "sg:tags":[
        "doughnut"
    ],
    "wof:name":"King Donut Deli",
    "wof:placetype":"venue"
},
  "geometry": {"coordinates":[-79.3129119873,43.6855163574],"type":"Point"}
}