{
  "type": "Feature",
  "properties": {
    "addr:full":"Ave Commerciale Saint-Charles-DE-Bellechasse QC G0R 2T0",
    "addr:postcode":"g0r 2t0",
    "addr:street":"Ave Commerciale",
    "iso:country":"CA",
    "sg:address":"Ave Commerciale",
    "sg:city":"Saint-Charles-DE-Bellechasse",
    "sg:classifiers":[
        {
            "category":"Organizations",
            "subcategory":"Professional Association",
            "type":"Services"
        }
    ],
    "sg:phone":"+1 418 887 3445",
    "sg:postcode":"G0R 2T0",
    "sg:province":"QC",
    "wof:name":"Chevaliers DE Colomb",
    "wof:placetype":"venue"
},
  "geometry": {"coordinates":[-70.94620500000001,46.772785],"type":"Point"}
}