{
  "type": "Feature",
  "properties": {
    "addr:full":"255 Ouellette Ave Windsor ON N9A 4H9",
    "addr:housenumber":"255",
    "addr:postcode":"n9a 4h9",
    "addr:street":"Ouellette Ave",
    "iso:country":"CA",
    "sg:address":"255 Ouellette Ave",
    "sg:city":"Windsor",
    "sg:classifiers":[
        {
            "category":"Restaurant",
            "type":"Food & Drink"
        }
    ],
    "sg:phone":"+1 519 971 9768",
    "sg:postcode":"N9A 4H9",
    "sg:province":"ON",
    "sg:tags":[
        "caterer"
    ],
    "wof:name":"Chanoso's Limited",
    "wof:placetype":"venue"
},
  "geometry": {"coordinates":[-83.03939800000001,42.317799],"type":"Point"}
}