{
  "type": "Feature",
  "properties": {
    "addr:full":"1198 Cedar Ave Trail BC V1R 4B7",
    "addr:housenumber":"1198",
    "addr:postcode":"bc v1r 4b7",
    "addr:street":"Cedar Ave Trail",
    "iso:country":"CA",
    "sg:address":"1198 Cedar Ave",
    "sg:city":"Trail",
    "sg:classifiers":[
        {
            "category":"Personal",
            "subcategory":"Beauty Salon",
            "type":"Services"
        }
    ],
    "sg:phone":"+1 250 364 2377",
    "sg:postcode":"V1R 4B7",
    "sg:province":"BC",
    "wof:name":"Jones & CO Hair Studio",
    "wof:placetype":"venue"
},
  "geometry": {"coordinates":[-117.71005249,49.0964508057],"type":"Point"}
}