{
  "type": "Feature",
  "properties": {
    "addr:full":"44 Rte Du President-Kennedy Levis QC G6V 6C5",
    "addr:housenumber":"44",
    "addr:postcode":"g6v 6c5",
    "addr:street":"Rte Du President-Kennedy",
    "iso:country":"CA",
    "sg:address":"44 Rte Du President-Kennedy",
    "sg:city":"Levis",
    "sg:classifiers":[
        {
            "category":"Government",
            "subcategory":"Office",
            "type":"Public Place"
        }
    ],
    "sg:phone":"+1 418 643 7620",
    "sg:postcode":"G6V 6C5",
    "sg:province":"QC",
    "wof:name":"Quebec Societe Assurance Auto",
    "wof:placetype":"venue"
},
  "geometry": {"coordinates":[-71.177879,46.795959],"type":"Point"}
}