{
  "type": "Feature",
  "properties": {
    "iso:country":"CA",
    "sg:city":"Vilna",
    "sg:classifiers":[
        {
            "category":"Education",
            "subcategory":"School",
            "type":"Public Place"
        }
    ],
    "sg:phone":"+1 780 636 3651",
    "sg:postcode":"T0A 3L0",
    "sg:province":"AB",
    "wof:name":"Vilna School",
    "wof:placetype":"venue"
},
  "geometry": {"coordinates":[-111.92237900000001,54.117447],"type":"Point"}
}