{
  "type": "Feature",
  "properties": {
    "addr:full":"89 Vista Blvd Mississauga ON L5M 1V8",
    "addr:housenumber":"89",
    "addr:postcode":"l5m 1v8",
    "addr:street":"Vista Blvd",
    "iso:country":"CA",
    "sg:address":"89 Vista Blvd",
    "sg:city":"Mississauga",
    "sg:classifiers":[
        {
            "category":"Education",
            "subcategory":"School",
            "type":"Public Place"
        }
    ],
    "sg:phone":"+1 905 826 1581",
    "sg:postcode":"L5M 1V8",
    "sg:province":"ON",
    "wof:name":"Vista Heights School",
    "wof:placetype":"venue"
},
  "geometry": {"coordinates":[-79.72545599999999,43.574848],"type":"Point"}
}