{
  "type": "Feature",
  "properties": {
    "addr:full":"Water Valley AB T0M 2E0",
    "addr:postcode":"t0m 2e0",
    "iso:country":"CA",
    "sg:city":"Water Valley",
    "sg:classifiers":[
        {
            "category":"Recreation",
            "type":"Entertainment"
        }
    ],
    "sg:phone":"+1 403 637 2777",
    "sg:postcode":"T0M 2E0",
    "sg:province":"AB",
    "sg:tags":[
        "raft",
        "trip"
    ],
    "wof:name":"Hunter Valley Recreational",
    "wof:placetype":"venue"
},
  "geometry": {"coordinates":[-114.605553,51.503891],"type":"Point"}
}