{
  "type": "Feature",
  "properties": {
    "addr:full":"2710 Millar Ave #1 Saskatoon SK S7K 4J4",
    "addr:housenumber":"2710",
    "addr:postcode":"s7k 4j4",
    "addr:street":"Millar Ave # 1",
    "iso:country":"CA",
    "sg:address":"2710 Millar Ave #1",
    "sg:city":"Saskatoon",
    "sg:classifiers":[
        {
            "category":"Communications",
            "subcategory":"Film & Video Production",
            "type":"Services"
        }
    ],
    "sg:phone":"+1 306 933 4212",
    "sg:postcode":"S7K 4J4",
    "sg:province":"SK",
    "sg:tags":[
        "taping"
    ],
    "wof:name":"Media Group",
    "wof:placetype":"venue"
},
  "geometry": {"coordinates":[-106.646049499,52.1712913513],"type":"Point"}
}