{
  "type": "Feature",
  "properties": {
    "addr:full":"11 Ch Pointe-Du-Chene Shediac NB E4P 2L9",
    "addr:housenumber":"11",
    "addr:postcode":"e4p 2l9",
    "addr:street":"Ch Pointe-Du-Chene",
    "iso:country":"CA",
    "sg:address":"11 Ch Pointe-Du-Chene",
    "sg:city":"Shediac",
    "sg:classifiers":[
        {
            "category":"Home & Garden",
            "subcategory":"Building Materials",
            "type":"Retail Goods"
        }
    ],
    "sg:phone":"+1 506 532 4438",
    "sg:postcode":"E4P 2L9",
    "sg:province":"NB",
    "sg:tags":[
        "lumber"
    ],
    "wof:name":"Shediac Building Supplies Ltd",
    "wof:placetype":"venue"
},
  "geometry": {"coordinates":[-64.516396,46.230129],"type":"Point"}
}