{
  "type": "Feature",
  "properties": {
    "addr:full":"151 Macdonald Dr Fort Mcmurray AB T9H 5C5",
    "addr:housenumber":"151",
    "addr:postcode":"t9h 5c5",
    "addr:street":"Macdonald Dr",
    "iso:country":"CA",
    "sg:address":"151 Macdonald Dr",
    "sg:city":"Fort Mcmurray",
    "sg:classifiers":[
        {
            "category":"Sports & Exercise",
            "subcategory":"Golf",
            "type":"Entertainment"
        }
    ],
    "sg:phone":"+1 780 791 0070",
    "sg:postcode":"T9H 5C5",
    "sg:province":"AB",
    "sg:tags":[
        "recreation",
        "center"
    ],
    "wof:name":"Mac Donald Island Park Society",
    "wof:placetype":"venue"
},
  "geometry": {"coordinates":[-111.38961792000001,56.7335853577],"type":"Point"}
}