{
  "type": "Feature",
  "properties": {
    "addr:full":"6334 Bay St West Vancouver BC V7W 2G9",
    "addr:housenumber":"6334",
    "addr:postcode":"v7w 2g9",
    "addr:street":"Bay St",
    "iso:country":"CA",
    "sg:address":"6334 Bay St",
    "sg:city":"West Vancouver",
    "sg:classifiers":[
        {
            "category":"Restaurant",
            "type":"Food & Drink"
        }
    ],
    "sg:phone":"+1 604 921 7611",
    "sg:postcode":"V7W 2G9",
    "sg:province":"BC",
    "sg:tags":[
        "parlor",
        "ice",
        "cream"
    ],
    "wof:name":"Baskin-Robbins Ice Cream",
    "wof:placetype":"venue"
},
  "geometry": {"coordinates":[-123.273246765,49.3741722107],"type":"Point"}
}