{
  "type": "Feature",
  "properties": {
    "addr:full":"253 Jevlan Dr Woodbridge ON L4L 7Z6",
    "addr:housenumber":"253",
    "addr:postcode":"l4l 7z6",
    "addr:street":"Jevlan Dr",
    "iso:country":"CA",
    "sg:address":"253 Jevlan Dr",
    "sg:city":"Woodbridge",
    "sg:classifiers":[
        {
            "category":"Building & Trades",
            "subcategory":"Construction",
            "type":"Services"
        }
    ],
    "sg:phone":"+1 905 264 1674",
    "sg:postcode":"L4L 7Z6",
    "sg:province":"ON",
    "sg:tags":[
        "contractor",
        "dry wall",
        "general"
    ],
    "wof:name":"On Centre Developments",
    "wof:placetype":"venue"
},
  "geometry": {"coordinates":[-79.54780599999999,43.800354],"type":"Point"}
}