{
  "type": "Feature",
  "properties": {
    "iso:country":"CA",
    "sg:address":"253 Jevlan Dr",
    "sg:city":"Woodbridge",
    "sg:classifiers":[
        {
            "category":"Building & Trades",
            "subcategory":"Construction",
            "type":"Services"
        }
    ],
    "sg:phone":"+1 905 264 1674",
    "sg:postcode":"L4L 7Z6",
    "sg:province":"ON",
    "sg:tags":[
        "contractor",
        "dry wall",
        "general"
    ],
    "wof:name":"On Centre Developments",
    "wof:placetype":"venue"
},
  "geometry": {"coordinates":[-79.547806,43.800354],"type":"Point"}
}