{
  "type": "Feature",
  "properties": {
    "addr:full":"1802 45 Ave Vernon BC V1T 3M7",
    "addr:housenumber":"1802",
    "addr:postcode":"v1t 3m7",
    "addr:street":"45 Ave",
    "iso:country":"CA",
    "sg:address":"1802 45 Ave",
    "sg:city":"Vernon",
    "sg:classifiers":[
        {
            "category":"Organizations",
            "subcategory":"Religious Organization",
            "type":"Services"
        }
    ],
    "sg:phone":"+1 250 545 3969",
    "sg:postcode":"V1T 3M7",
    "sg:province":"BC",
    "sg:tags":[
        "church"
    ],
    "wof:name":"Seventh-Day Adventist Church",
    "wof:placetype":"venue"
},
  "geometry": {"coordinates":[-119.254311,50.277443],"type":"Point"}
}