{
  "type": "Feature",
  "properties": {
    "addr:full":"24018 Woodbine Ave Keswick ON L4P 3E9",
    "addr:housenumber":"24018",
    "addr:postcode":"l4p 3e9",
    "addr:street":"Woodbine Ave",
    "iso:country":"CA",
    "sg:address":"24018 Woodbine Ave",
    "sg:city":"Keswick",
    "sg:classifiers":[
        {
            "category":"Restaurant",
            "type":"Food & Drink"
        }
    ],
    "sg:phone":"+1 905 989 2211",
    "sg:postcode":"L4P 3E9",
    "sg:province":"ON",
    "wof:name":"Mc Donald's",
    "wof:placetype":"venue"
},
  "geometry": {"coordinates":[-79.447593689,44.228603363],"type":"Point"}
}