{
  "type": "Feature",
  "properties": {
    "addr:full":"Longueuil QC J4J 3X6",
    "addr:postcode":"j4j 3x6",
    "iso:country":"CA",
    "sg:city":"Longueuil",
    "sg:classifiers":[
        {
            "category":"Personal",
            "subcategory":"Barber",
            "type":"Services"
        }
    ],
    "sg:phone":"+1 450 677 8303",
    "sg:postcode":"J4J 3X6",
    "sg:province":"QC",
    "wof:name":"Salon Cartier",
    "wof:placetype":"venue"
},
  "geometry": {"coordinates":[-73.485039,45.530922],"type":"Point"}
}