{
  "type": "Feature",
  "properties": {
    "addr:full":"751 Tabor Blvd S Prince George BC V2M 5V1",
    "addr:housenumber":"751",
    "addr:postcode":"v2m 5v1",
    "addr:street":"Tabor Blvd S",
    "iso:country":"CA",
    "sg:address":"751 Tabor Blvd S",
    "sg:city":"Prince George",
    "sg:classifiers":[
        {
            "category":"Real Estate",
            "subcategory":"Real Estate Operator",
            "type":"Services"
        }
    ],
    "sg:phone":"+1 250 563 7505",
    "sg:postcode":"V2M 5V1",
    "sg:province":"BC",
    "sg:tags":[
        "apartment"
    ],
    "wof:name":"Afton Place",
    "wof:placetype":"venue"
},
  "geometry": {"coordinates":[-122.80738067599999,53.9175872803],"type":"Point"}
}