{
  "type": "Feature",
  "properties": {
    "addr:full":"5000 Av Albert-Tessier Shawinigan QC G9N 8P9",
    "addr:postcode":"g9n 8p9",
    "addr:street":"Av Albert-Tessier",
    "iso:country":"CA",
    "sg:address":"5000 Av Albert-Tessier",
    "sg:city":"Shawinigan",
    "sg:classifiers":[
        {
            "category":"Health Services",
            "subcategory":"Nursing And Care Facility",
            "type":"Services"
        }
    ],
    "sg:phone":"+1 819 539 5408",
    "sg:postcode":"G9N 8P9",
    "sg:province":"QC",
    "sg:tags":[
        "home",
        "rest"
    ],
    "wof:name":"Centre D'Accueil Les Chutes",
    "wof:placetype":"venue"
},
  "geometry": {"coordinates":[-72.7328033447,46.5735397339],"type":"Point"}
}