{
  "type": "Feature",
  "properties": {
    "addr:full":"1210 Main St N Moose Jaw SK S6H 3L1",
    "addr:housenumber":"1210",
    "addr:postcode":"s6h 3l1",
    "addr:street":"Main St N",
    "iso:country":"CA",
    "sg:address":"1210 Main St N",
    "sg:city":"Moose Jaw",
    "sg:classifiers":[
        {
            "category":"Shopping",
            "subcategory":"Discount & Variety Stores",
            "type":"Retail Goods"
        }
    ],
    "sg:phone":"+1 306 693 2266",
    "sg:postcode":"S6H 3L1",
    "sg:province":"SK",
    "sg:tags":[
        "department"
    ],
    "wof:name":"Your Dollar Store With More",
    "wof:placetype":"venue"
},
  "geometry": {"coordinates":[-105.534934998,50.4034729004],"type":"Point"}
}