{
  "type": "Feature",
  "properties": {
    "addr:full":"New Westminster BC V3M 6B6",
    "addr:postcode":"v3m 6b6",
    "iso:country":"CA",
    "sg:city":"New Westminster",
    "sg:classifiers":[
        {
            "category":"Real Estate",
            "subcategory":"Real Estate Agent",
            "type":"Services"
        }
    ],
    "sg:phone":"+1 604 521 8338",
    "sg:postcode":"V3M 6B6",
    "sg:province":"BC",
    "sg:tags":[
        "cooperative"
    ],
    "wof:name":"Westminster Landing Housing",
    "wof:placetype":"venue"
},
  "geometry": {"coordinates":[-122.915565,49.198685],"type":"Point"}
}