{
  "type": "Feature",
  "properties": {
    "addr:full":"180 King Street South Suite 505 Waterloo N2J 1P8",
    "addr:housenumber":"180",
    "addr:postcode":"n2j 1p8",
    "addr:street":"King Street South Suite 505",
    "iso:country":"CA",
    "sg:address":"180 King Street South Suite 505",
    "sg:city":"Waterloo",
    "sg:classifiers":[
        {
            "category":"Professional",
            "subcategory":"Computer Services",
            "type":"Services"
        }
    ],
    "sg:postcode":"N2J 1P8",
    "sg:tags":[
        "rss",
        "information-overload",
        "personal-productivity",
        "feed-management",
        "analytics",
        "social-media",
        "measurement",
        "monitoring"
    ],
    "sg:website":"http://www.postrank.com",
    "wof:name":"PostRank",
    "wof:placetype":"venue"
},
  "geometry": {"coordinates":[-80.519538,43.460515],"type":"Point"}
}