{
  "type": "Feature",
  "properties": {
    "iso:country":"CA",
    "sg:city":"Montreal",
    "sg:classifiers":[
        {
            "category":"Shopping",
            "subcategory":"Clothing, Apparel, & Fashions",
            "type":"Retail Goods"
        }
    ],
    "sg:phone":"+1 514 878 1220",
    "sg:postcode":"H3B 1N4",
    "sg:province":"QC",
    "sg:tags":[
        "item",
        "boutique"
    ],
    "wof:name":"Boutique Moura Cuir Inc",
    "wof:placetype":"venue"
},
  "geometry": {"coordinates":[-73.5663146973,45.5029182434],"type":"Point"}
}