{
  "type": "Feature",
  "properties": {
    "addr:full":"Surrey BC V3W 8V3",
    "addr:postcode":"v3w 8v3",
    "iso:country":"CA",
    "sg:city":"Surrey",
    "sg:classifiers":[
        {
            "category":"Home & Garden",
            "subcategory":"Furniture",
            "type":"Retail Goods"
        }
    ],
    "sg:phone":"+1 604 502 8611",
    "sg:postcode":"V3W 8V3",
    "sg:province":"BC",
    "wof:name":"Roma Furniture",
    "wof:placetype":"venue"
},
  "geometry": {"coordinates":[-122.846633911,49.1443862915],"type":"Point"}
}