{
  "type": "Feature",
  "properties": {
    "addr:full":"Toronto ON M5S 2T9",
    "addr:postcode":"m5s 2t9",
    "iso:country":"CA",
    "sg:city":"Toronto",
    "sg:classifiers":[
        {
            "category":"Manufacturing",
            "subcategory":"Printing",
            "type":"Manufacturing & Wholesale Goods"
        }
    ],
    "sg:phone":"+1 416 961 2679",
    "sg:postcode":"M5S 2T9",
    "sg:province":"ON",
    "sg:tags":[
        "printer",
        "duplicating",
        "copying"
    ],
    "wof:name":"Copy Place",
    "wof:placetype":"venue"
},
  "geometry": {"coordinates":[-79.40329,43.665295],"type":"Point"}
}