{
  "type": "Feature",
  "properties": {
    "addr:full":"Westlock AB T7P 2K2",
    "addr:postcode":"t7p 2k2",
    "iso:country":"CA",
    "sg:city":"Westlock",
    "sg:classifiers":[
        {
            "category":"Shopping",
            "type":"Retail Goods"
        }
    ],
    "sg:phone":"+1 780 349 4355",
    "sg:postcode":"T7P 2K2",
    "sg:province":"AB",
    "sg:tags":[
        "monument"
    ],
    "wof:name":"Rose City Memorials Ltd",
    "wof:placetype":"venue"
},
  "geometry": {"coordinates":[-113.86316680900001,54.1543998718],"type":"Point"}
}