{
  "type": "Feature",
  "properties": {
    "addr:full":"1700 Blair Rd Gloucester ON K1B 4E6",
    "addr:housenumber":"1700",
    "addr:postcode":"k1b 4e6",
    "addr:street":"Blair Rd",
    "iso:country":"CA",
    "sg:address":"1700 Blair Rd",
    "sg:city":"Gloucester",
    "sg:classifiers":[
        {
            "category":"Government",
            "subcategory":"Police Station",
            "type":"Public Place"
        }
    ],
    "sg:phone":"+1 613 236 1222",
    "sg:postcode":"K1B 4E6",
    "sg:province":"ON",
    "sg:tags":[
        "department"
    ],
    "wof:name":"Ottawa Carleton Svc DE Police",
    "wof:placetype":"venue"
},
  "geometry": {"coordinates":[-75.596756,45.421017],"type":"Point"}
}