{
  "type": "Feature",
  "properties": {
    "iso:country":"CA",
    "sg:address":"155 Main St",
    "sg:city":"Toronto",
    "sg:classifiers":[
        {
            "category":"Shopping",
            "subcategory":"Music",
            "type":"Retail Goods"
        }
    ],
    "sg:phone":"+1 416 690 6399",
    "sg:postcode":"M4E 2V9",
    "sg:province":"ON",
    "sg:tags":[
        "compact",
        "record",
        "disc",
        "tape"
    ],
    "wof:name":"Ric Collectibles",
    "wof:placetype":"venue"
},
  "geometry": {"coordinates":[-79.2997970581,43.6834907532],"type":"Point"}
}