{
  "type": "Feature",
  "properties": {
    "addr:full":"8971 Rue Airlie Lasalle QC H8R 2A2",
    "addr:housenumber":"8971",
    "addr:postcode":"h8r 2a2",
    "addr:street":"Rue Airlie",
    "iso:country":"CA",
    "sg:address":"8971 Rue Airlie",
    "sg:city":"Lasalle",
    "sg:classifiers":[
        {
            "category":"Retail",
            "subcategory":"Auto Repair",
            "type":"Services"
        }
    ],
    "sg:phone":"+1 514 365 1119",
    "sg:postcode":"H8R 2A2",
    "sg:province":"QC",
    "sg:tags":[
        "repairing",
        "automobile"
    ],
    "wof:name":"E Blanchard Garage Inc",
    "wof:placetype":"venue"
},
  "geometry": {"coordinates":[-73.6301651001,45.4205703735],"type":"Point"}
}