{
  "type": "Feature",
  "properties": {
    "iso:country":"CA",
    "sg:city":"Thunder Bay",
    "sg:classifiers":[
        {
            "category":"Health Services",
            "subcategory":"Doctor",
            "type":"Services"
        }
    ],
    "sg:phone":"+1 807 345 5922",
    "sg:postcode":"P7A 4L8",
    "sg:province":"ON",
    "sg:tags":[
        "dentist"
    ],
    "wof:name":"C Nils Dental Care",
    "wof:placetype":"venue"
},
  "geometry": {"coordinates":[-89.21677398680001,48.4371452332],"type":"Point"}
}