{
  "type": "Feature",
  "properties": {
    "iso:country":"CA",
    "sg:address":"995 Rue Beaulieu",
    "sg:city":"Saint-Jean-Chrysostome",
    "sg:classifiers":[
        {
            "category":"Autos & Motor Vehicles",
            "subcategory":"Automobile Sales",
            "type":"Retail Goods"
        }
    ],
    "sg:phone":"+1 418 832 1177",
    "sg:postcode":"G6Z 2L1",
    "sg:province":"QC",
    "sg:tags":[
        "car",
        "dealer"
    ],
    "wof:name":"Roy Gaston Automobiles",
    "wof:placetype":"venue"
},
  "geometry": {"coordinates":[-71.2481842041,46.6971206665],"type":"Point"}
}