{
  "type": "Feature",
  "properties": {
    "addr:full":"1268 Lynn Valley Rd North Vancouver BC V7J 2A3",
    "addr:housenumber":"1268",
    "addr:postcode":"v7j 2a3",
    "addr:street":"Lynn Valley Rd",
    "iso:country":"CA",
    "sg:address":"1268 Lynn Valley Rd",
    "sg:city":"North Vancouver",
    "sg:classifiers":[
        {
            "category":"Retail",
            "subcategory":"Veterinary Services",
            "type":"Services"
        }
    ],
    "sg:phone":"+1 604 980 0584",
    "sg:postcode":"V7J 2A3",
    "sg:province":"BC",
    "sg:tags":[
        "veterinarian"
    ],
    "wof:name":"Lynn Valley Vet Clinic Ltd",
    "wof:placetype":"venue"
},
  "geometry": {"coordinates":[-123.038971,49.336823],"type":"Point"}
}