{
  "type": "Feature",
  "properties": {
    "addr:full":"951 Park Royal S West Vancouver BC V7T 1A1",
    "addr:housenumber":"951",
    "addr:postcode":"v7t 1a1",
    "addr:street":"Park Royal S West",
    "iso:country":"CA",
    "sg:address":"951 Park Royal S",
    "sg:city":"West Vancouver",
    "sg:classifiers":[
        {
            "category":"Shopping",
            "subcategory":"Clothing, Apparel, & Fashions",
            "type":"Retail Goods"
        }
    ],
    "sg:phone":"+1 604 922 0960",
    "sg:postcode":"V7T 1A1",
    "sg:province":"BC",
    "sg:tags":[
        "dressmaker"
    ],
    "wof:name":"Magic Needle",
    "wof:placetype":"venue"
},
  "geometry": {"coordinates":[-123.134857178,49.3262786865],"type":"Point"}
}