{
  "type": "Feature",
  "properties": {
    "addr:full":"3528 Highway 16 E Smithers BC V0J 2N6",
    "addr:housenumber":"3528",
    "addr:postcode":"v0j 2n6",
    "addr:street":"Highway 16 E",
    "iso:country":"CA",
    "sg:address":"3528 Highway 16 E",
    "sg:city":"Smithers",
    "sg:classifiers":[
        {
            "category":"Home & Garden",
            "subcategory":"Building Materials",
            "type":"Retail Goods"
        }
    ],
    "sg:phone":"+1 250 847 2246",
    "sg:postcode":"V0J 2N6",
    "sg:province":"BC",
    "sg:tags":[
        "carpet",
        "dealer",
        "rug"
    ],
    "wof:name":"Smithers Lumber Yard Ltd",
    "wof:placetype":"venue"
},
  "geometry": {"coordinates":[-127.16812899999999,54.782803],"type":"Point"}
}