{
  "type": "Feature",
  "properties": {
    "addr:full":"33804 Fourth Ave Mission BC V2V 1T4",
    "addr:housenumber":"33804",
    "addr:postcode":"v2v 1t4",
    "addr:street":"Fourth Ave",
    "iso:country":"CA",
    "sg:address":"33804 Fourth Ave",
    "sg:city":"Mission",
    "sg:classifiers":[
        {
            "category":"Professional",
            "subcategory":"Business Services",
            "type":"Services"
        }
    ],
    "sg:phone":"+1 604 826 5772",
    "sg:postcode":"V2V 1T4",
    "sg:province":"BC",
    "sg:tags":[
        "drafting"
    ],
    "wof:name":"Mark 2 Design",
    "wof:placetype":"venue"
},
  "geometry": {"coordinates":[-122.288047791,49.1367988586],"type":"Point"}
}