{
  "type": "Feature",
  "properties": {
    "addr:full":"646 Rue Sainte-Catherine O Montreal QC H3B 1B8",
    "addr:housenumber":"646",
    "addr:postcode":"h3b 1b8",
    "addr:street":"Rue Sainte-Catherine O",
    "iso:country":"CA",
    "sg:address":"646 Rue Sainte-Catherine O",
    "sg:city":"Montreal",
    "sg:classifiers":[
        {
            "category":"Professional",
            "subcategory":"Printing & Photocopies",
            "type":"Services"
        }
    ],
    "sg:phone":"+1 514 868 0900",
    "sg:postcode":"H3B 1B8",
    "sg:province":"QC",
    "sg:tags":[
        "duplicating",
        "copying"
    ],
    "wof:name":"Reproduction Images Inc",
    "wof:placetype":"venue"
},
  "geometry": {"coordinates":[-73.55895200000001,45.515125],"type":"Point"}
}