{
  "type": "Feature",
  "properties": {
    "addr:full":"Winnipeg MB R3H 1B5",
    "addr:postcode":"r3h 1b5",
    "iso:country":"CA",
    "sg:city":"Winnipeg",
    "sg:classifiers":[
        {
            "category":"Organizations",
            "subcategory":"Professional Association",
            "type":"Services"
        }
    ],
    "sg:phone":"+1 204 949 0533",
    "sg:postcode":"R3H 1B5",
    "sg:province":"MB",
    "wof:name":"Community Therapy Svc Inc",
    "wof:placetype":"venue"
},
  "geometry": {"coordinates":[-97.1991195679,49.9100494385],"type":"Point"}
}