{
  "type": "Feature",
  "properties": {
    "addr:full":"Toronto ON M5H 2M5",
    "addr:postcode":"m5h 2m5",
    "iso:country":"CA",
    "sg:city":"Toronto",
    "sg:classifiers":[
        {
            "category":"Food & Beverages",
            "subcategory":"Groceries & Convenience Stores",
            "type":"Retail Goods"
        }
    ],
    "sg:phone":"+1 416 703 9473",
    "sg:postcode":"M5H 2M5",
    "sg:province":"ON",
    "sg:tags":[
        "grocer"
    ],
    "wof:name":"Gateway Newsstand",
    "wof:placetype":"venue"
},
  "geometry": {"coordinates":[-79.381897,43.651714],"type":"Point"}
}