{
  "type": "Feature",
  "properties": {
    "addr:full":"Duncan BC V9L 3V3",
    "addr:postcode":"v9l 3v3",
    "iso:country":"CA",
    "sg:city":"Duncan",
    "sg:classifiers":[
        {
            "category":"Shopping",
            "type":"Retail Goods"
        }
    ],
    "sg:phone":"+1 250 746 4246",
    "sg:postcode":"V9L 3V3",
    "sg:province":"BC",
    "sg:tags":[
        "hearing",
        "equipment",
        "supply",
        "impaired"
    ],
    "wof:name":"Beltone Hearing Aid Svc",
    "wof:placetype":"venue"
},
  "geometry": {"coordinates":[-123.704620361,48.7799453735],"type":"Point"}
}