{
  "type": "Feature",
  "properties": {
    "iso:country":"CA",
    "sg:city":"Mont-Royal",
    "sg:classifiers":[
        {
            "category":"Restaurant",
            "type":"Food & Drink"
        }
    ],
    "sg:phone":"+1 514 737 9259",
    "sg:postcode":"H3P 3E9",
    "sg:province":"QC",
    "wof:name":"Restaurant Tiki Ming Rockland",
    "wof:placetype":"venue"
},
  "geometry": {"coordinates":[-73.648483,45.52673],"type":"Point"}
}