{
  "type": "Feature",
  "properties": {
    "addr:full":"5316 Nauvoo Rd Watford ON N0M 2S0",
    "addr:housenumber":"5316",
    "addr:postcode":"n0m 2s0",
    "addr:street":"Nauvoo Rd",
    "iso:country":"CA",
    "sg:address":"5316 Nauvoo Rd",
    "sg:city":"Watford",
    "sg:classifiers":[
        {
            "category":"Autos & Motor Vehicles",
            "subcategory":"Auto Supplies",
            "type":"Retail Goods"
        }
    ],
    "sg:phone":"+1 519 876 2617",
    "sg:postcode":"N0M 2S0",
    "sg:province":"ON",
    "sg:tags":[
        "tire"
    ],
    "wof:name":"Acton's Service Ctr",
    "wof:placetype":"venue"
},
  "geometry": {"coordinates":[-81.8798294067,42.9492607117],"type":"Point"}
}