{
  "type": "Feature",
  "properties": {
    "addr:full":"1860 Boul Le Corbusier Laval QC H7S 2K1",
    "addr:housenumber":"1860",
    "addr:postcode":"h7s 2k1",
    "addr:street":"Boul Le Corbusier",
    "iso:country":"CA",
    "sg:address":"1860 Boul Le Corbusier",
    "sg:city":"Laval",
    "sg:classifiers":[
        {
            "category":"Wholesale",
            "subcategory":"Auto Parts",
            "type":"Manufacturing & Wholesale Goods"
        }
    ],
    "sg:phone":"+1 450 688 4006",
    "sg:postcode":"H7S 2K1",
    "sg:province":"QC",
    "sg:tags":[
        "automobile",
        "supply"
    ],
    "wof:name":"Mark IV Automotive",
    "wof:placetype":"venue"
},
  "geometry": {"coordinates":[-73.737274,45.56879],"type":"Point"}
}