{
  "type": "Feature",
  "properties": {
    "addr:full":"Calgary AB T2B 3M1",
    "addr:postcode":"t2b 3m1",
    "iso:country":"CA",
    "sg:city":"Calgary",
    "sg:classifiers":[
        {
            "category":"Wholesale",
            "subcategory":"Machinery & Supplies",
            "type":"Manufacturing & Wholesale Goods"
        }
    ],
    "sg:phone":"+1 403 235 3116",
    "sg:postcode":"T2B 3M1",
    "sg:province":"AB",
    "sg:tags":[
        "director",
        "funeral"
    ],
    "wof:name":"Batesville Canada Ltd",
    "wof:placetype":"venue"
},
  "geometry": {"coordinates":[-113.992774963,51.0133895874],"type":"Point"}
}