{
  "type": "Feature",
  "properties": {
    "addr:full":"Ingersoll ON N5C 3J7",
    "addr:postcode":"n5c 3j7",
    "iso:country":"CA",
    "sg:city":"Ingersoll",
    "sg:classifiers":[
        {
            "category":"Health Services",
            "subcategory":"Doctor",
            "type":"Services"
        }
    ],
    "sg:phone":"+1 519 485 3908",
    "sg:postcode":"N5C 3J7",
    "sg:province":"ON",
    "sg:tags":[
        "physician",
        "surgeon"
    ],
    "wof:name":"Mayberry, Tom R MD",
    "wof:placetype":"venue"
},
  "geometry": {"coordinates":[-80.88385009770001,43.0381164551],"type":"Point"}
}