{
  "type": "Feature",
  "properties": {
    "iso:country":"CA",
    "sg:address":"PO Box 40",
    "sg:city":"Robinsons",
    "sg:phone":"+1 709 645 2879",
    "sg:postcode":"A0N 1V0",
    "sg:province":"NL",
    "sg:tags":[
        "oil"
    ],
    "wof:name":"North Atlantic Petroleum",
    "wof:placetype":"venue"
},
  "geometry": {"coordinates":[-58.8087081909,48.242515564],"type":"Point"}
}