{
  "type": "Feature",
  "properties": {
    "addr:full":"22499 Gray Line Rodney ON N0L 2C0",
    "addr:housenumber":"22499",
    "addr:postcode":"n0l 2c0",
    "addr:street":"Gray Line",
    "iso:country":"CA",
    "sg:address":"22499 Gray Line",
    "sg:city":"Rodney",
    "sg:classifiers":[
        {
            "category":"Travel",
            "subcategory":"Campground",
            "type":"Entertainment"
        }
    ],
    "sg:phone":"+1 519 785 2020",
    "sg:postcode":"N0L 2C0",
    "sg:province":"ON",
    "wof:name":"Lakewood Trailer Estates",
    "wof:placetype":"venue"
},
  "geometry": {"coordinates":[-81.68309021,42.5680351257],"type":"Point"}
}