{
  "type": "Feature",
  "properties": {
    "addr:full":"3615 Rue Principale Dunham QC J0E 1M0",
    "addr:housenumber":"3615",
    "addr:postcode":"j0e 1m0",
    "addr:street":"Rue Principale",
    "iso:country":"CA",
    "sg:address":"3615 Rue Principale",
    "sg:city":"Dunham",
    "sg:classifiers":[
        {
            "category":"Shopping",
            "subcategory":"Clothing, Apparel, & Fashions",
            "type":"Retail Goods"
        }
    ],
    "sg:phone":"+1 450 295 2766",
    "sg:postcode":"J0E 1M0",
    "sg:province":"QC",
    "sg:tags":[
        "salvage",
        "surplus",
        "merchandise"
    ],
    "wof:name":"J P & F Larochelle Surplus",
    "wof:placetype":"venue"
},
  "geometry": {"coordinates":[-72.8003311157,45.1372528076],"type":"Point"}
}