{
  "type": "Feature",
  "properties": {
    "iso:country":"CA",
    "sg:address":"2168 Guelph Line",
    "sg:city":"Burlington",
    "sg:classifiers":[
        {
            "category":"Museum",
            "type":"Entertainment"
        }
    ],
    "sg:phone":"+1 905 332 9888",
    "sg:postcode":"L7P 5A8",
    "sg:province":"ON",
    "wof:name":"Ireland House Museum",
    "wof:placetype":"venue"
},
  "geometry": {"coordinates":[-79.82888793950001,43.3694992065],"type":"Point"}
}