{
  "type": "Feature",
  "properties": {
    "addr:full":"462 Rue Principale Piopolis QC G0Y 1H0",
    "addr:housenumber":"462",
    "addr:postcode":"g0y 1h0",
    "addr:street":"Rue Principale",
    "iso:country":"CA",
    "sg:address":"462 Rue Principale",
    "sg:city":"Piopolis",
    "sg:classifiers":[
        {
            "category":"Shopping",
            "subcategory":"Clothing, Apparel, & Fashions",
            "type":"Retail Goods"
        }
    ],
    "sg:phone":"+1 819 583 4447",
    "sg:postcode":"G0Y 1H0",
    "sg:province":"QC",
    "sg:tags":[
        "boutique"
    ],
    "wof:name":"Confection Maillot",
    "wof:placetype":"venue"
},
  "geometry": {"coordinates":[-70.90269499999999,45.486362],"type":"Point"}
}