{
  "type": "Feature",
  "properties": {
    "addr:full":"1355 Kingston Rd Pickering ON L1V 1B8",
    "addr:housenumber":"1355",
    "addr:postcode":"l1v 1b8",
    "addr:street":"Kingston Rd",
    "iso:country":"CA",
    "sg:address":"1355 Kingston Rd",
    "sg:city":"Pickering",
    "sg:classifiers":[
        {
            "category":"Shopping",
            "type":"Retail Goods"
        }
    ],
    "sg:phone":"+1 905 837 1212",
    "sg:postcode":"L1V 1B8",
    "sg:province":"ON",
    "sg:tags":[
        "telephone",
        "cellular"
    ],
    "wof:name":"Bell World",
    "wof:placetype":"venue"
},
  "geometry": {"coordinates":[-79.0872421265,43.8379707336],"type":"Point"}
}