{
  "type": "Feature",
  "properties": {
    "addr:full":"119 Neville Park Blvd Toronto ON M4E 3P7",
    "addr:housenumber":"119",
    "addr:postcode":"m4e 3p7",
    "addr:street":"Neville Park Blvd",
    "iso:country":"CA",
    "sg:address":"119 Neville Park Blvd",
    "sg:city":"Toronto",
    "sg:classifiers":[
        {
            "category":"Shopping",
            "subcategory":"Computers & Home Electronics",
            "type":"Retail Goods"
        }
    ],
    "sg:phone":"+1 416 690 0730",
    "sg:postcode":"M4E 3P7",
    "sg:province":"ON",
    "sg:tags":[
        "software"
    ],
    "wof:name":"Softworx",
    "wof:placetype":"venue"
},
  "geometry": {"coordinates":[-79.28215789790001,43.6750831604],"type":"Point"}
}