{
  "type": "Feature",
  "properties": {
    "iso:country":"CA",
    "sg:address":"1333 Rue Frigon",
    "sg:city":"Shawinigan",
    "sg:classifiers":[
        {
            "category":"Bars & Pubs",
            "type":"Food & Drink"
        }
    ],
    "sg:phone":"+1 819 539 9933",
    "sg:postcode":"G9N 3Z7",
    "sg:province":"QC",
    "sg:tags":[
        "lounge",
        "cocktail"
    ],
    "wof:name":"Bar Salon L'Ecluse",
    "wof:placetype":"venue"
},
  "geometry": {"coordinates":[-72.74184417719999,46.5586433411],"type":"Point"}
}