{
  "type": "Feature",
  "properties": {
    "addr:full":"69 Queen St Chester NS B0J 1J0",
    "addr:housenumber":"69",
    "addr:postcode":"b0j 1j0",
    "addr:street":"Queen St",
    "iso:country":"CA",
    "sg:address":"69 Queen St",
    "sg:city":"Chester",
    "sg:classifiers":[
        {
            "category":"Personal",
            "subcategory":"Tanning Parlor",
            "type":"Services"
        }
    ],
    "sg:phone":"+1 902 275 5103",
    "sg:postcode":"B0J 1J0",
    "sg:province":"NS",
    "sg:tags":[
        "salon"
    ],
    "wof:name":"Innovation Beauty & Body",
    "wof:placetype":"venue"
},
  "geometry": {"coordinates":[-64.24112700000001,44.545673],"type":"Point"}
}