{
  "type": "Feature",
  "properties": {
    "addr:full":"2760 Derry Rd W Mississauga ON L5N 3N5",
    "addr:housenumber":"2760",
    "addr:postcode":"l5n 3n5",
    "addr:street":"Derry Rd W",
    "iso:country":"CA",
    "sg:address":"2760 Derry Rd W",
    "sg:city":"Mississauga",
    "sg:classifiers":[
        {
            "category":"Shopping",
            "subcategory":"Pharmacy",
            "type":"Retail Goods"
        }
    ],
    "sg:phone":"+1 905 858 9449",
    "sg:postcode":"L5N 3N5",
    "sg:province":"ON",
    "wof:name":"Glen Derry Drug Mart",
    "wof:placetype":"venue"
},
  "geometry": {"coordinates":[-79.7653503418,43.5931854248],"type":"Point"}
}