{
  "type": "Feature",
  "properties": {
    "addr:full":"Fallis AB T0E 0V0",
    "addr:postcode":"t0e 0v0",
    "iso:country":"CA",
    "sg:city":"Fallis",
    "sg:classifiers":[
        {
            "category":"Sports & Exercise",
            "subcategory":"Golf",
            "type":"Entertainment"
        }
    ],
    "sg:phone":"+1 780 797 2340",
    "sg:postcode":"T0E 0V0",
    "sg:province":"AB",
    "sg:tags":[
        "course"
    ],
    "wof:name":"Silver Sands Golf Course",
    "wof:placetype":"venue"
},
  "geometry": {"coordinates":[-114.639824,53.575134],"type":"Point"}
}