{
  "type": "Feature",
  "properties": {
    "addr:full":"Saskatoon SK S7K 5C6",
    "addr:postcode":"s7k 5c6",
    "iso:country":"CA",
    "sg:city":"Saskatoon",
    "sg:classifiers":[
        {
            "category":"Food & Beverages",
            "subcategory":"Specialty",
            "type":"Retail Goods"
        }
    ],
    "sg:phone":"+1 306 653 0099",
    "sg:postcode":"S7K 5C6",
    "sg:province":"SK",
    "sg:tags":[
        "water",
        "bulk",
        "company"
    ],
    "wof:name":"World of Water",
    "wof:placetype":"venue"
},
  "geometry": {"coordinates":[-106.649864197,52.1728134155],"type":"Point"}
}