{
  "type": "Feature",
  "properties": {
    "addr:full":"51 Commercial Dr Burks Falls ON P0A 1C0",
    "addr:housenumber":"51",
    "addr:postcode":"p0a 1c0",
    "addr:street":"Commercial Dr Burks",
    "iso:country":"CA",
    "sg:address":"51 Commercial Dr",
    "sg:city":"Burks Falls",
    "sg:classifiers":[
        {
            "category":"Shopping",
            "subcategory":"Musical Instruments",
            "type":"Retail Goods"
        }
    ],
    "sg:phone":"+1 705 382 0555",
    "sg:postcode":"P0A 1C0",
    "sg:province":"ON",
    "wof:name":"Northern Notes Music",
    "wof:placetype":"venue"
},
  "geometry": {"coordinates":[-78.48088799999999,45.033714],"type":"Point"}
}