{
  "type": "Feature",
  "properties": {
    "iso:country":"CA",
    "sg:address":"1004 North Park St",
    "sg:city":"Victoria",
    "sg:classifiers":[
        {
            "category":"Social Services",
            "type":"Services"
        }
    ],
    "sg:phone":"+1 250 383 4355",
    "sg:postcode":"V8T 1C6",
    "sg:province":"BC",
    "sg:tags":[
        "organization",
        "welfare"
    ],
    "wof:name":"M S Support Line",
    "wof:placetype":"venue"
},
  "geometry": {"coordinates":[-123.35542297400001,48.4298057556],"type":"Point"}
}