{
  "type": "Feature",
  "properties": {
    "addr:full":"2901 Bayview Ave North York ON M2K 1E6",
    "addr:housenumber":"2901",
    "addr:postcode":"m2k 1e6",
    "addr:street":"Bayview Ave",
    "iso:country":"CA",
    "sg:address":"2901 Bayview Ave",
    "sg:city":"North York",
    "sg:classifiers":[
        {
            "category":"Shopping",
            "subcategory":"Tobacco",
            "type":"Retail Goods"
        }
    ],
    "sg:phone":"+1 416 733 9736",
    "sg:postcode":"M2K 1E6",
    "sg:province":"ON",
    "sg:tags":[
        "cigarette",
        "cigar",
        "dealer"
    ],
    "wof:name":"Havanna Tobacconist",
    "wof:placetype":"venue"
},
  "geometry": {"coordinates":[-79.3885421753,43.769115448],"type":"Point"}
}