{
  "type": "Feature",
  "properties": {
    "addr:full":"500 Trumpeter Dr Gold River BC V0P 1G0",
    "addr:housenumber":"500",
    "addr:postcode":"v0p 1g0",
    "addr:street":"Trumpeter Dr",
    "iso:country":"CA",
    "sg:address":"500 Trumpeter Dr",
    "sg:city":"Gold River",
    "sg:classifiers":[
        {
            "category":"Education",
            "subcategory":"School",
            "type":"Public Place"
        }
    ],
    "sg:phone":"+1 250 283 2220",
    "sg:postcode":"V0P 1G0",
    "sg:province":"BC",
    "wof:name":"Ray Watkins Elementary School",
    "wof:placetype":"venue"
},
  "geometry": {"coordinates":[-126.052063,49.779568],"type":"Point"}
}