{
  "type": "Feature",
  "properties": {
    "addr:full":"337 Richmond St London ON N6A 3C2",
    "addr:housenumber":"337",
    "addr:postcode":"n6a 3c2",
    "addr:street":"Richmond St",
    "iso:country":"CA",
    "sg:address":"337 Richmond St",
    "sg:city":"London",
    "sg:classifiers":[
        {
            "category":"Restaurant",
            "type":"Food & Drink"
        }
    ],
    "sg:phone":"+1 519 679 0208",
    "sg:postcode":"N6A 3C2",
    "sg:province":"ON",
    "wof:name":"Clicks Bar & Grill",
    "wof:placetype":"venue"
},
  "geometry": {"coordinates":[-81.2488021851,42.9815940857],"type":"Point"}
}