{
  "type": "Feature",
  "properties": {
    "iso:country":"CA",
    "sg:address":"772 James St N",
    "sg:city":"Thunder Bay",
    "sg:classifiers":[
        {
            "category":"Restaurant",
            "type":"Food & Drink"
        }
    ],
    "sg:phone":"+1 807 475 4222",
    "sg:postcode":"P7C 5N3",
    "sg:province":"ON",
    "sg:tags":[
        "out",
        "pizza"
    ],
    "wof:name":"Domino's Pizza",
    "wof:placetype":"venue"
},
  "geometry": {"coordinates":[-89.27899932859999,48.4003181458],"type":"Point"}
}