{
  "type": "Feature",
  "properties": {
    "addr:full":"1045 Rue Racine Valcourt QC J0E 2L0",
    "addr:housenumber":"1045",
    "addr:postcode":"j0e 2l0",
    "addr:street":"Rue Racine",
    "iso:country":"CA",
    "sg:address":"1045 Rue Racine",
    "sg:city":"Valcourt",
    "sg:classifiers":[
        {
            "category":"Professional",
            "subcategory":"Research",
            "type":"Services"
        }
    ],
    "sg:phone":"+1 450 532 2154",
    "sg:postcode":"J0E 2L0",
    "sg:province":"QC",
    "sg:tags":[
        "development",
        "electronic"
    ],
    "wof:name":"Lysir Communications",
    "wof:placetype":"venue"
},
  "geometry": {"coordinates":[-72.3018493652,45.4959411621],"type":"Point"}
}