{
  "type": "Feature",
  "properties": {
    "iso:country":"CA",
    "sg:city":"Acton",
    "sg:classifiers":[
        {
            "category":"Building & Trades",
            "subcategory":"Construction",
            "type":"Services"
        }
    ],
    "sg:phone":"+1 519 853 4344",
    "sg:postcode":"L7J 2L7",
    "sg:province":"ON",
    "sg:tags":[
        "excavating",
        "landscape",
        "contractor"
    ],
    "wof:name":"Erik Schubert Excavating Ltd",
    "wof:placetype":"venue"
},
  "geometry": {"coordinates":[-80.0403289795,43.63073349],"type":"Point"}
}