{
  "type": "Feature",
  "properties": {
    "addr:full":"Mississauga ON L5A 3P2",
    "addr:postcode":"l5a 3p2",
    "iso:country":"CA",
    "sg:city":"Mississauga",
    "sg:classifiers":[
        {
            "category":"Manufacturing",
            "subcategory":"Tools & Machinery",
            "type":"Manufacturing & Wholesale Goods"
        }
    ],
    "sg:phone":"+1 905 275 2183",
    "sg:postcode":"L5A 3P2",
    "sg:province":"ON",
    "sg:tags":[
        "machine",
        "shop"
    ],
    "wof:name":"Salco & Assoc",
    "wof:placetype":"venue"
},
  "geometry": {"coordinates":[-79.5960845947,43.5921554565],"type":"Point"}
}