{
  "type": "Feature",
  "properties": {
    "addr:full":"Invermere BC V0A 1K0",
    "addr:postcode":"v0a 1k0",
    "iso:country":"CA",
    "sg:city":"Invermere",
    "sg:classifiers":[
        {
            "category":"Education",
            "subcategory":"School",
            "type":"Public Place"
        }
    ],
    "sg:phone":"+1 250 342 3060",
    "sg:postcode":"V0A 1K0",
    "sg:province":"BC",
    "wof:name":"Open Doors",
    "wof:placetype":"venue"
},
  "geometry": {"coordinates":[-116.028396606,50.5128707886],"type":"Point"}
}