{
  "type": "Feature",
  "properties": {
    "iso:country":"CA",
    "sg:city":"Caraquet",
    "sg:classifiers":[
        {
            "category":"Shopping",
            "subcategory":"Catalog Store",
            "type":"Retail Goods"
        }
    ],
    "sg:phone":"+1 506 727 3491",
    "sg:postcode":"E1W 1B2",
    "sg:province":"NB",
    "sg:tags":[
        "mail",
        "order",
        "internet"
    ],
    "wof:name":"Sears Canada Inc",
    "wof:placetype":"venue"
},
  "geometry": {"coordinates":[-64.99039459230001,47.7774276733],"type":"Point"}
}