{
  "type": "Feature",
  "properties": {
    "addr:full":"4175 29th Ave W Vancouver BC V6S 1V1",
    "addr:housenumber":"4175",
    "addr:postcode":"v6s 1v1",
    "addr:street":"29Th Ave W",
    "iso:country":"CA",
    "sg:address":"4175 29th Ave W",
    "sg:city":"Vancouver",
    "sg:classifiers":[
        {
            "category":"Education",
            "subcategory":"School",
            "type":"Public Place"
        }
    ],
    "sg:phone":"+1 604 224 3464",
    "sg:postcode":"V6S 1V1",
    "sg:province":"BC",
    "wof:name":"St George's School",
    "wof:placetype":"venue"
},
  "geometry": {"coordinates":[-123.199905,49.246941],"type":"Point"}
}