{
  "type": "Feature",
  "properties": {
    "addr:full":"6416 Yonge St North York ON M2M 3X4",
    "addr:housenumber":"6416",
    "addr:postcode":"m2m 3x4",
    "addr:street":"Yonge St",
    "iso:country":"CA",
    "sg:address":"6416 Yonge St",
    "sg:city":"North York",
    "sg:classifiers":[
        {
            "category":"Banks & Credit Unions",
            "subcategory":"Bank",
            "type":"Services"
        }
    ],
    "sg:phone":"+1 416 590 7488",
    "sg:postcode":"M2M 3X4",
    "sg:province":"ON",
    "wof:name":"Scotiabank",
    "wof:placetype":"venue"
},
  "geometry": {"coordinates":[-79.41970825200001,43.7959213257],"type":"Point"}
}