{
  "type": "Feature",
  "properties": {
    "addr:full":"1076 Granville St Vancouver BC V6Z 1L5",
    "addr:housenumber":"1076",
    "addr:postcode":"v6z 1l5",
    "addr:street":"Granville St",
    "iso:country":"CA",
    "sg:address":"1076 Granville St",
    "sg:city":"Vancouver",
    "sg:classifiers":[
        {
            "category":"Shopping",
            "subcategory":"Clothing, Apparel, & Fashions",
            "type":"Retail Goods"
        }
    ],
    "sg:phone":"+1 604 685 9228",
    "sg:postcode":"V6Z 1L5",
    "sg:province":"BC",
    "sg:tags":[
        "t"
    ],
    "wof:name":"Rock Shop",
    "wof:placetype":"venue"
},
  "geometry": {"coordinates":[-123.124008,49.278446],"type":"Point"}
}