{
  "type": "Feature",
  "properties": {
    "addr:full":"211 Kimberly Ave Winnipeg MB R2K 0X3",
    "addr:housenumber":"211",
    "addr:postcode":"r2k 0x3",
    "addr:street":"Kimberly Ave",
    "iso:country":"CA",
    "sg:address":"211 Kimberly Ave",
    "sg:city":"Winnipeg",
    "sg:classifiers":[
        {
            "category":"Social Services",
            "subcategory":"Child Care",
            "type":"Services"
        }
    ],
    "sg:phone":"+1 204 661 9474",
    "sg:postcode":"R2K 0X3",
    "sg:province":"MB",
    "wof:name":"Kimberly Kids Before & After",
    "wof:placetype":"venue"
},
  "geometry": {"coordinates":[-97.10298899999999,49.92741],"type":"Point"}
}