{
  "type": "Feature",
  "properties": {
    "addr:full":"Lethbridge AB T1H 0E4",
    "addr:postcode":"t1h 0e4",
    "iso:country":"CA",
    "sg:city":"Lethbridge",
    "sg:classifiers":[
        {
            "category":"Manufacturing",
            "subcategory":"Leather Goods",
            "type":"Manufacturing & Wholesale Goods"
        }
    ],
    "sg:phone":"+1 403 380 3939",
    "sg:postcode":"T1H 0E4",
    "sg:province":"AB",
    "wof:name":"Caribou Clothes",
    "wof:placetype":"venue"
},
  "geometry": {"coordinates":[-112.83374000000001,49.693836],"type":"Point"}
}