{
  "type": "Feature",
  "properties": {
    "addr:full":"29 Kelfield St Etobicoke ON M9W 5A1",
    "addr:housenumber":"29",
    "addr:postcode":"m9w 5a1",
    "addr:street":"Kelfield St",
    "iso:country":"CA",
    "sg:address":"29 Kelfield St",
    "sg:city":"Etobicoke",
    "sg:classifiers":[
        {
            "category":"Wholesale",
            "subcategory":"Hardware",
            "type":"Manufacturing & Wholesale Goods"
        }
    ],
    "sg:phone":"+1 416 235 1994",
    "sg:postcode":"M9W 5A1",
    "sg:province":"ON",
    "sg:tags":[
        "equipment",
        "heating",
        "system"
    ],
    "wof:name":"Ridler Heating & Cooling",
    "wof:placetype":"venue"
},
  "geometry": {"coordinates":[-79.576042,43.688347],"type":"Point"}
}