{
  "type": "Feature",
  "properties": {
    "addr:full":"8355 Ch Montview Mont-Royal QC H4P 2L9",
    "addr:postcode":"8355;h4p 2l9",
    "addr:street":"Ch Montview",
    "iso:country":"CA",
    "sg:address":"8355 Ch Montview",
    "sg:city":"Mont-Royal",
    "sg:classifiers":[
        {
            "category":"Wholesale",
            "subcategory":"Apparel",
            "type":"Manufacturing & Wholesale Goods"
        }
    ],
    "sg:phone":"+1 514 344 2525",
    "sg:postcode":"H4P 2L9",
    "sg:province":"QC",
    "sg:tags":[
        "lingerie"
    ],
    "wof:name":"Evabelle Inc",
    "wof:placetype":"venue"
},
  "geometry": {"coordinates":[-73.67035675050001,45.4926338196],"type":"Point"}
}