{
  "type": "Feature",
  "properties": {
    "addr:full":"30 Rue Gounod Montreal QC H2R 1A5",
    "addr:housenumber":"30",
    "addr:postcode":"h2r 1a5",
    "addr:street":"Rue Gounod",
    "iso:country":"CA",
    "sg:address":"30 Rue Gounod",
    "sg:city":"Montreal",
    "sg:classifiers":[
        {
            "category":"Home & Garden",
            "subcategory":"Building Materials",
            "type":"Retail Goods"
        }
    ],
    "sg:phone":"+1 514 277 1128",
    "sg:postcode":"H2R 1A5",
    "sg:province":"QC",
    "sg:tags":[
        "front",
        "plate",
        "window",
        "store"
    ],
    "wof:name":"Tiv-Tov Glass CO",
    "wof:placetype":"venue"
},
  "geometry": {"coordinates":[-73.6278839111,45.5383834839],"type":"Point"}
}