{
  "type": "Feature",
  "properties": {
    "addr:full":"10711 Av Racette Montreal-Nord QC H1G 5H5",
    "addr:housenumber":"10711",
    "addr:postcode":"h1g 5h5",
    "addr:street":"Av Racette",
    "iso:country":"CA",
    "sg:address":"10711 Av Racette",
    "sg:city":"Montreal-Nord",
    "sg:classifiers":[
        {
            "category":"Wholesale",
            "subcategory":"Machinery & Supplies",
            "type":"Manufacturing & Wholesale Goods"
        }
    ],
    "sg:phone":"+1 514 328 9360",
    "sg:postcode":"H1G 5H5",
    "sg:province":"QC",
    "sg:tags":[
        "truck"
    ],
    "wof:name":"Equipement Hydraulique",
    "wof:placetype":"venue"
},
  "geometry": {"coordinates":[-73.62241400000001,45.596481],"type":"Point"}
}