{
  "type": "Feature",
  "properties": {
    "iso:country":"CA",
    "sg:address":"10711 Av Racette",
    "sg:city":"Montreal-Nord",
    "sg:classifiers":[
        {
            "category":"Wholesale",
            "subcategory":"Machinery & Supplies",
            "type":"Manufacturing & Wholesale Goods"
        }
    ],
    "sg:phone":"+1 514 328 9360",
    "sg:postcode":"H1G 5H5",
    "sg:province":"QC",
    "sg:tags":[
        "truck"
    ],
    "wof:name":"Equipement Hydraulique",
    "wof:placetype":"venue"
},
  "geometry": {"coordinates":[-73.622414,45.596481],"type":"Point"}
}