{
  "type": "Feature",
  "properties": {
    "addr:full":"4906 54 St W Forestburg AB T0B 1N0",
    "addr:housenumber":"4906",
    "addr:postcode":"t0b 1n0",
    "addr:street":"54 St W",
    "iso:country":"CA",
    "sg:address":"4906 54 St W",
    "sg:city":"Forestburg",
    "sg:classifiers":[
        {
            "category":"Travel",
            "subcategory":"Hotels & Motels",
            "type":"Entertainment"
        }
    ],
    "sg:phone":"+1 780 582 3935",
    "sg:postcode":"T0B 1N0",
    "sg:province":"AB",
    "wof:name":"Forestburg Motor Inn",
    "wof:placetype":"venue"
},
  "geometry": {"coordinates":[-112.068695068,52.585849762],"type":"Point"}
}