{
  "type": "Feature",
  "properties": {
    "addr:full":"3 Rue Du Chambertin Kirkland QC H9H 5E5",
    "addr:housenumber":"3",
    "addr:postcode":"h9h 5e5",
    "addr:street":"Rue Du Chambertin",
    "iso:country":"CA",
    "sg:address":"3 Rue Du Chambertin",
    "sg:city":"Kirkland",
    "sg:classifiers":[
        {
            "category":"Professional",
            "subcategory":"Computer Services",
            "type":"Services"
        }
    ],
    "sg:phone":"+1 514 695 5384",
    "sg:postcode":"H9H 5E5",
    "sg:province":"QC",
    "sg:tags":[
        "internet"
    ],
    "wof:name":"Xwits Inc",
    "wof:placetype":"venue"
},
  "geometry": {"coordinates":[-73.86004638670001,45.4582176208],"type":"Point"}
}