{
  "type": "Feature",
  "properties": {
    "addr:full":"208 Rue Sauve Buckingham QC J8L 1V4",
    "addr:housenumber":"208",
    "addr:postcode":"j8l 1v4",
    "addr:street":"Rue Sauve",
    "iso:country":"CA",
    "sg:address":"208 Rue Sauve",
    "sg:city":"Buckingham",
    "sg:classifiers":[
        {
            "category":"Shopping",
            "type":"Retail Goods"
        }
    ],
    "sg:phone":"+1 819 281 1888",
    "sg:postcode":"J8L 1V4",
    "sg:province":"QC",
    "sg:tags":[
        "equipment",
        "telephone",
        "supply"
    ],
    "wof:name":"Protel Jlt Telecommunication",
    "wof:placetype":"venue"
},
  "geometry": {"coordinates":[-75.40656300000001,45.581371],"type":"Point"}
}