{
  "type": "Feature",
  "properties": {
    "addr:full":"16 Archibald Ave North Sydney NS B2A 2W1",
    "addr:housenumber":"16",
    "addr:postcode":"b2a 2w1",
    "addr:street":"Archibald Ave",
    "iso:country":"CA",
    "sg:address":"16 Archibald Ave",
    "sg:city":"North Sydney",
    "sg:classifiers":[
        {
            "category":"Organizations",
            "subcategory":"Professional Association",
            "type":"Services"
        }
    ],
    "sg:phone":"+1 902 794 4816",
    "sg:postcode":"B2A 2W1",
    "sg:province":"NS",
    "wof:name":"Royal Canadian Legion",
    "wof:placetype":"venue"
},
  "geometry": {"coordinates":[-60.24966,46.209595],"type":"Point"}
}