{
  "type": "Feature",
  "properties": {
    "addr:full":"5102 48 Ave Ponoka AB T4J 1P7",
    "addr:housenumber":"5102",
    "addr:postcode":"t4j 1p7",
    "addr:street":"48 Ave",
    "iso:country":"CA",
    "sg:address":"5102 48 Ave",
    "sg:city":"Ponoka",
    "sg:classifiers":[
        {
            "category":"Social Services",
            "subcategory":"Adult Care",
            "type":"Services"
        }
    ],
    "sg:phone":"+1 403 783 0128",
    "sg:postcode":"T4J 1P7",
    "sg:province":"AB",
    "sg:tags":[
        "senior",
        "housing",
        "citizen"
    ],
    "wof:name":"Rimoka Housing Foundation",
    "wof:placetype":"venue"
},
  "geometry": {"coordinates":[-113.57975,52.675167],"type":"Point"}
}