{
  "type": "Feature",
  "properties": {
    "iso:country":"CA",
    "sg:address":"200 338 Rte",
    "sg:city":"Les Coteaux",
    "sg:classifiers":[
        {
            "category":"Retail",
            "subcategory":"Auto Repair",
            "type":"Services"
        }
    ],
    "sg:phone":"+1 450 267 9238",
    "sg:postcode":"J7X 1A2",
    "sg:province":"QC",
    "sg:tags":[
        "repairing",
        "automobile"
    ],
    "wof:name":"Alignement Lebire Ltee",
    "wof:placetype":"venue"
},
  "geometry": {"coordinates":[-74.2030334473,45.2599945068],"type":"Point"}
}