{
  "type": "Feature",
  "properties": {
    "iso:country":"CA",
    "sg:address":"4830 Headquarters Rd",
    "sg:city":"Courtenay",
    "sg:classifiers":[
        {
            "category":"Social Services",
            "subcategory":"Child Care",
            "type":"Services"
        }
    ],
    "sg:phone":"+1 250 338 8445",
    "sg:postcode":"V9J 1P2",
    "sg:province":"BC",
    "wof:name":"Teddies 'N Toddlers Child Care",
    "wof:placetype":"venue"
},
  "geometry": {"coordinates":[-124.99375915500001,49.7025718689],"type":"Point"}
}