{
  "type": "Feature",
  "properties": {
    "addr:full":"348 Lyndock St Corunna ON N0N 1G0",
    "addr:housenumber":"348",
    "addr:postcode":"n0n 1g0",
    "addr:street":"Lyndock St",
    "iso:country":"CA",
    "sg:address":"348 Lyndock St",
    "sg:city":"Corunna",
    "sg:classifiers":[
        {
            "category":"Banks & Credit Unions",
            "subcategory":"Bank",
            "type":"Services"
        }
    ],
    "sg:phone":"+1 519 862 1456",
    "sg:postcode":"N0N 1G0",
    "sg:province":"ON",
    "wof:name":"Royal Bank Financial Group",
    "wof:placetype":"venue"
},
  "geometry": {"coordinates":[-82.45305633540001,42.8913421631],"type":"Point"}
}