{
  "type": "Feature",
  "properties": {
    "addr:full":"1495 8th Ave W Vancouver BC V6H 1C9",
    "addr:housenumber":"1495",
    "addr:postcode":"v6h 1c9",
    "addr:street":"8Th Ave W",
    "iso:country":"CA",
    "sg:address":"1495 8th Ave W",
    "sg:city":"Vancouver",
    "sg:classifiers":[
        {
            "category":"Restaurant",
            "type":"Food & Drink"
        }
    ],
    "sg:phone":"+1 604 731 0575",
    "sg:postcode":"V6H 1C9",
    "sg:province":"BC",
    "sg:tags":[
        "caterer"
    ],
    "wof:name":"Round Table Catering",
    "wof:placetype":"venue"
},
  "geometry": {"coordinates":[-123.138214,49.264652],"type":"Point"}
}