{
  "type": "Feature",
  "properties": {
    "addr:full":"205 King St Sturgeon Falls ON P2B 1R8",
    "addr:housenumber":"205",
    "addr:postcode":"p2b 1r8",
    "addr:street":"King St",
    "iso:country":"CA",
    "sg:address":"205 King St",
    "sg:city":"Sturgeon Falls",
    "sg:classifiers":[
        {
            "category":"Banks & Credit Unions",
            "subcategory":"Bank",
            "type":"Services"
        }
    ],
    "sg:phone":"+1 705 753 0330",
    "sg:postcode":"P2B 1R8",
    "sg:province":"ON",
    "wof:name":"Banque Nationale Du Canada",
    "wof:placetype":"venue"
},
  "geometry": {"coordinates":[-79.929703,46.367714],"type":"Point"}
}