{
  "type": "Feature",
  "properties": {
    "addr:full":"3000 Navan Rd Orleans ON K1C 7G4",
    "addr:housenumber":"3000",
    "addr:postcode":"k1c 7g4",
    "addr:street":"Navan Rd",
    "iso:country":"CA",
    "sg:address":"3000 Navan Rd",
    "sg:city":"Orleans",
    "sg:classifiers":[
        {
            "category":"Building & Trades",
            "subcategory":"Construction",
            "type":"Services"
        }
    ],
    "sg:phone":"+1 613 830 0066",
    "sg:postcode":"K1C 7G4",
    "sg:province":"ON",
    "sg:tags":[
        "material",
        "paving",
        "contractor"
    ],
    "wof:name":"Streetprint",
    "wof:placetype":"venue"
},
  "geometry": {"coordinates":[-75.5275421143,45.4331283569],"type":"Point"}
}