{
  "type": "Feature",
  "properties": {
    "iso:country":"CA",
    "sg:address":"977 Boul Jean-DE Brebeuf",
    "sg:city":"Drummondville",
    "sg:classifiers":[
        {
            "category":"Health Services",
            "subcategory":"Doctor",
            "type":"Services"
        }
    ],
    "sg:phone":"+1 819 478 8121",
    "sg:postcode":"J2B 4T2",
    "sg:province":"QC",
    "sg:tags":[
        "clinic",
        "dentist"
    ],
    "wof:name":"Centre Dentaire Blanchet",
    "wof:placetype":"venue"
},
  "geometry": {"coordinates":[-72.47389221189999,45.8629989624],"type":"Point"}
}