{
  "type": "Feature",
  "properties": {
    "addr:full":"6560 28 Ave NW Edmonton AB T6L 6N3",
    "addr:housenumber":"6560",
    "addr:postcode":"t6l 6n3",
    "addr:street":"28 Ave Nw",
    "iso:country":"CA",
    "sg:address":"6560 28 Ave NW",
    "sg:city":"Edmonton",
    "sg:classifiers":[
        {
            "category":"Retail",
            "subcategory":"Laundry & Dry Cleaning",
            "type":"Services"
        }
    ],
    "sg:phone":"+1 780 461 3838",
    "sg:postcode":"T6L 6N3",
    "sg:province":"AB",
    "sg:tags":[
        "cleaners"
    ],
    "wof:name":"First Class Cleaners",
    "wof:placetype":"venue"
},
  "geometry": {"coordinates":[-113.43291499999999,53.458488],"type":"Point"}
}