{
  "type": "Feature",
  "properties": {
    "addr:full":"1050 Nottinghill Gate Oakville ON L6M 2G3",
    "addr:housenumber":"1050",
    "addr:postcode":"l6m 2g3",
    "addr:street":"Nottinghill Gate",
    "iso:country":"CA",
    "sg:address":"1050 Nottinghill Gate",
    "sg:city":"Oakville",
    "sg:classifiers":[
        {
            "category":"Education",
            "subcategory":"School",
            "type":"Public Place"
        }
    ],
    "sg:phone":"+1 905 847 0088",
    "sg:postcode":"L6M 2G3",
    "sg:province":"ON",
    "wof:name":"St Matthew's School",
    "wof:placetype":"venue"
},
  "geometry": {"coordinates":[-79.71701049799999,43.4403800964],"type":"Point"}
}