{
  "type": "Feature",
  "properties": {
    "addr:full":"London ON N5X 1V7",
    "addr:postcode":"n5x 1v7",
    "iso:country":"CA",
    "sg:city":"London",
    "sg:classifiers":[
        {
            "category":"Banks & Credit Unions",
            "subcategory":"Investment Brokerage",
            "type":"Services"
        }
    ],
    "sg:phone":"+1 519 645 7236",
    "sg:postcode":"N5X 1V7",
    "sg:province":"ON",
    "wof:name":"Edward Jones",
    "wof:placetype":"venue"
},
  "geometry": {"coordinates":[-81.238876,43.038914],"type":"Point"}
}