{
  "type": "Feature",
  "properties": {
    "addr:full":"4381 46A St Delta BC V4K 2M2",
    "addr:housenumber":"4381",
    "addr:postcode":"v4k 2m2",
    "addr:street":"46A St",
    "iso:country":"CA",
    "sg:address":"4381 46A St",
    "sg:city":"Delta",
    "sg:classifiers":[
        {
            "category":"Education",
            "subcategory":"School",
            "type":"Public Place"
        }
    ],
    "sg:phone":"+1 604 946 0321",
    "sg:postcode":"V4K 2M2",
    "sg:province":"BC",
    "wof:name":"Port Guichon Elementary School",
    "wof:placetype":"venue"
},
  "geometry": {"coordinates":[-123.05961600000001,49.084801],"type":"Point"}
}