{
  "type": "Feature",
  "properties": {
    "addr:full":"898 Queen St E Sault Ste Marie ON P6A 2B4",
    "addr:housenumber":"898",
    "addr:postcode":"p6a 2b4",
    "addr:street":"Queen St E",
    "iso:country":"CA",
    "sg:address":"898 Queen St E",
    "sg:city":"Sault Ste Marie",
    "sg:classifiers":[
        {
            "category":"Real Estate",
            "subcategory":"Real Estate Agent",
            "type":"Services"
        }
    ],
    "sg:phone":"+1 705 253 6722",
    "sg:postcode":"P6A 2B4",
    "sg:province":"ON",
    "sg:tags":[
        "appraiser"
    ],
    "wof:name":"J E Luzzi Appraisal Svc",
    "wof:placetype":"venue"
},
  "geometry": {"coordinates":[-84.32186900000001,46.505882],"type":"Point"}
}