{
  "type": "Feature",
  "properties": {
    "addr:full":"4625 Route 11 Tabusintac NB E9H 1H5",
    "addr:housenumber":"4625",
    "addr:postcode":"e9h 1h5",
    "addr:street":"Route 11",
    "iso:country":"CA",
    "sg:address":"4625 Route 11",
    "sg:city":"Tabusintac",
    "sg:classifiers":[
        {
            "category":"Professional",
            "subcategory":"Lawyer & Legal Services",
            "type":"Services"
        }
    ],
    "sg:phone":"+1 506 779 4466",
    "sg:postcode":"E9H 1H5",
    "sg:province":"NB",
    "sg:tags":[
        "attorney"
    ],
    "wof:name":"Munroe, William C",
    "wof:placetype":"venue"
},
  "geometry": {"coordinates":[-65.010704,47.328445],"type":"Point"}
}