{
  "type": "Feature",
  "properties": {
    "addr:full":"525 91E Rue Saint-Georges QC G5Y 3K7",
    "addr:housenumber":"525",
    "addr:postcode":"g5y 3k7",
    "addr:street":"91E Rue",
    "iso:country":"CA",
    "sg:address":"525 91E Rue",
    "sg:city":"Saint-Georges",
    "sg:classifiers":[
        {
            "category":"Real Estate",
            "subcategory":"Real Estate Agent",
            "type":"Services"
        }
    ],
    "sg:phone":"+1 418 228 1718",
    "sg:postcode":"G5Y 3K7",
    "sg:province":"QC",
    "sg:tags":[
        "agency",
        "rental"
    ],
    "wof:name":"Lou-Tec",
    "wof:placetype":"venue"
},
  "geometry": {"coordinates":[-70.67115020750001,46.1233482361],"type":"Point"}
}