{
  "type": "Feature",
  "properties": {
    "addr:full":"Coquitlam BC V3B 7K1",
    "addr:postcode":"v3b 7k1",
    "iso:country":"CA",
    "sg:city":"Coquitlam",
    "sg:classifiers":[
        {
            "category":"Restaurant",
            "type":"Food & Drink"
        }
    ],
    "sg:phone":"+1 604 552 8100",
    "sg:postcode":"V3B 7K1",
    "sg:province":"BC",
    "sg:tags":[
        "pizza"
    ],
    "wof:name":"Little Caesars Pizza",
    "wof:placetype":"venue"
},
  "geometry": {"coordinates":[-122.801498413,49.2823181152],"type":"Point"}
}