{
  "type": "Feature",
  "properties": {
    "addr:full":"10387 Nordel Crt Delta BC V4G 1J9",
    "addr:housenumber":"10387",
    "addr:postcode":"v4g 1j9",
    "addr:street":"Nordel Crt",
    "iso:country":"CA",
    "sg:address":"10387 Nordel Crt",
    "sg:city":"Delta",
    "sg:classifiers":[
        {
            "category":"Freight",
            "type":"Transportation"
        }
    ],
    "sg:phone":"+1 604 581 5331",
    "sg:postcode":"V4G 1J9",
    "sg:province":"BC",
    "wof:name":"Seacon Services Ltd",
    "wof:placetype":"venue"
},
  "geometry": {"coordinates":[-122.938492,49.149555],"type":"Point"}
}