{
  "type": "Feature",
  "properties": {
    "iso:country":"CA",
    "sg:address":"General Delivery",
    "sg:city":"Mount Carmel",
    "sg:classifiers":[
        {
            "category":"Government",
            "subcategory":"Office",
            "type":"Public Place"
        }
    ],
    "sg:phone":"+1 709 521 2040",
    "sg:postcode":"A0B 2M0",
    "sg:province":"NL",
    "sg:tags":[
        "village"
    ],
    "wof:name":"Mount Carmel Town Council",
    "wof:placetype":"venue"
},
  "geometry": {"coordinates":[-53.4977111816,47.13230896],"type":"Point"}
}