{
  "type": "Feature",
  "properties": {
    "addr:full":"1151 Mcdonald St Regina SK S4N 4X4",
    "addr:housenumber":"1151",
    "addr:postcode":"s4n 4x4",
    "addr:street":"Mcdonald St",
    "iso:country":"CA",
    "sg:address":"1151 Mcdonald St",
    "sg:city":"Regina",
    "sg:classifiers":[
        {
            "category":"Manufacturing",
            "subcategory":"Tools & Machinery",
            "type":"Manufacturing & Wholesale Goods"
        }
    ],
    "sg:phone":"+1 306 352 8113",
    "sg:postcode":"S4N 4X4",
    "sg:province":"SK",
    "sg:tags":[
        "machine",
        "shop"
    ],
    "wof:name":"Abs Competition Enterprises",
    "wof:placetype":"venue"
},
  "geometry": {"coordinates":[-104.58340454099999,50.4606056213],"type":"Point"}
}