{
  "type": "Feature",
  "properties": {
    "addr:full":"6945 Meadowvale Town Centre Ci Mississauga ON L5N 2W7",
    "addr:housenumber":"6945",
    "addr:postcode":"l5n 2w7",
    "addr:street":"Meadowvale Town Centre Ci",
    "iso:country":"CA",
    "sg:address":"6945 Meadowvale Town Centre Ci",
    "sg:city":"Mississauga",
    "sg:classifiers":[
        {
            "category":"Social Services",
            "subcategory":"Child Care",
            "type":"Services"
        }
    ],
    "sg:phone":"+1 905 567 3037",
    "sg:postcode":"L5N 2W7",
    "sg:province":"ON",
    "wof:name":"Neighbourhood Nursery School",
    "wof:placetype":"venue"
},
  "geometry": {"coordinates":[-79.75709500000001,43.58279],"type":"Point"}
}