{
  "type": "Feature",
  "properties": {
    "addr:full":"1400 Rue Sauve O Montreal QC H4N 1C5",
    "addr:housenumber":"1400",
    "addr:postcode":"h4n 1c5",
    "addr:street":"Rue Sauve O",
    "iso:country":"CA",
    "sg:address":"1400 Rue Sauve O",
    "sg:city":"Montreal",
    "sg:classifiers":[
        {
            "category":"Wholesale",
            "subcategory":"Apparel",
            "type":"Manufacturing & Wholesale Goods"
        }
    ],
    "sg:phone":"+1 514 830 3196",
    "sg:postcode":"H4N 1C5",
    "sg:province":"QC",
    "wof:name":"Agence Mark Stein",
    "wof:placetype":"venue"
},
  "geometry": {"coordinates":[-73.6653671265,45.535358429],"type":"Point"}
}