{
  "type": "Feature",
  "properties": {
    "addr:full":"515 Wilson St Hamilton ON L8L 1T4",
    "addr:housenumber":"515",
    "addr:postcode":"l8l 1t4",
    "addr:street":"Wilson St",
    "iso:country":"CA",
    "sg:address":"515 Wilson St",
    "sg:city":"Hamilton",
    "sg:classifiers":[
        {
            "category":"Wholesale",
            "subcategory":"Electrical",
            "type":"Manufacturing & Wholesale Goods"
        }
    ],
    "sg:phone":"+1 905 528 0261",
    "sg:postcode":"L8L 1T4",
    "sg:province":"ON",
    "sg:tags":[
        "equipment",
        "electric",
        "supply"
    ],
    "wof:name":"Nedco",
    "wof:placetype":"venue"
},
  "geometry": {"coordinates":[-79.84729799999999,43.254063],"type":"Point"}
}