{
  "type": "Feature",
  "properties": {
    "iso:country":"CA",
    "sg:address":"515 Wilson St",
    "sg:city":"Hamilton",
    "sg:classifiers":[
        {
            "category":"Wholesale",
            "subcategory":"Electrical",
            "type":"Manufacturing & Wholesale Goods"
        }
    ],
    "sg:phone":"+1 905 528 0261",
    "sg:postcode":"L8L 1T4",
    "sg:province":"ON",
    "sg:tags":[
        "equipment",
        "electric",
        "supply"
    ],
    "wof:name":"Nedco",
    "wof:placetype":"venue"
},
  "geometry": {"coordinates":[-79.847298,43.254063],"type":"Point"}
}