{
  "type": "Feature",
  "properties": {
    "addr:full":"Saint-Georges QC G5Y 7R6",
    "addr:postcode":"g5y 7r6",
    "iso:country":"CA",
    "sg:city":"Saint-Georges",
    "sg:classifiers":[
        {
            "category":"Retail",
            "subcategory":"Repair Shop",
            "type":"Services"
        }
    ],
    "sg:phone":"+1 418 228 7431",
    "sg:postcode":"G5Y 7R6",
    "sg:province":"QC",
    "sg:tags":[
        "upholsterer"
    ],
    "wof:name":"Rembourrage Cstb",
    "wof:placetype":"venue"
},
  "geometry": {"coordinates":[-70.67115020750001,46.1233482361],"type":"Point"}
}