{
  "type": "Feature",
  "properties": {
    "addr:full":"Port Coquitlam BC V3C 6N2",
    "addr:postcode":"v3c 6n2",
    "iso:country":"CA",
    "sg:city":"Port Coquitlam",
    "sg:classifiers":[
        {
            "category":"Shopping",
            "type":"Retail Goods"
        }
    ],
    "sg:phone":"+1 604 944 7818",
    "sg:postcode":"V3C 6N2",
    "sg:province":"BC",
    "sg:tags":[
        "shop",
        "equipment",
        "wine",
        "gift",
        "supply"
    ],
    "wof:name":"Just Fine Wine",
    "wof:placetype":"venue"
},
  "geometry": {"coordinates":[-122.773208618,49.2575378418],"type":"Point"}
}