{
  "type": "Feature",
  "properties": {
    "addr:full":"1860 Sismet Rd Mississauga ON L4W 1W9",
    "addr:housenumber":"1860",
    "addr:postcode":"l4w 1w9",
    "addr:street":"Sismet Rd",
    "iso:country":"CA",
    "sg:address":"1860 Sismet Rd",
    "sg:city":"Mississauga",
    "sg:classifiers":[
        {
            "category":"Manufacturing",
            "subcategory":"Tools & Machinery",
            "type":"Manufacturing & Wholesale Goods"
        }
    ],
    "sg:phone":"+1 905 629 1011",
    "sg:postcode":"L4W 1W9",
    "sg:province":"ON",
    "sg:tags":[
        "machine",
        "shop"
    ],
    "wof:name":"Mnk Tool & Machine CO",
    "wof:placetype":"venue"
},
  "geometry": {"coordinates":[-79.61824799999999,43.648331],"type":"Point"}
}