{
  "type": "Feature",
  "properties": {
    "addr:full":"6551 No. 3 Rd #1916 Richmond BC V6Y 2B6",
    "addr:postcode":"6551;v6y 2b6",
    "addr:street":"3 Rd # 1916",
    "iso:country":"CA",
    "sg:address":"6551 No. 3 Rd #1916",
    "sg:city":"Richmond",
    "sg:classifiers":[
        {
            "category":"Shopping",
            "subcategory":"Gifts & Souvenirs",
            "type":"Retail Goods"
        }
    ],
    "sg:phone":"+1 604 273 0585",
    "sg:postcode":"V6Y 2B6",
    "sg:province":"BC",
    "sg:tags":[
        "basket",
        "parcel"
    ],
    "wof:name":"Crabtree & Evelyn",
    "wof:placetype":"venue"
},
  "geometry": {"coordinates":[-123.136658,49.166374],"type":"Point"}
}