{
  "type": "Feature",
  "properties": {
    "iso:country":"CA",
    "sg:address":"1597 117 Rte",
    "sg:city":"Mont-Tremblant",
    "sg:classifiers":[
        {
            "category":"Building & Trades",
            "subcategory":"Electrical",
            "type":"Services"
        }
    ],
    "sg:phone":"+1 819 425 2597",
    "sg:postcode":"J8E 2X9",
    "sg:province":"QC",
    "sg:tags":[
        "electric",
        "contractor"
    ],
    "wof:name":"Robert Boisjoli Electricien",
    "wof:placetype":"venue"
},
  "geometry": {"coordinates":[-74.60168457029999,46.1183395386],"type":"Point"}
}