{
  "type": "Feature",
  "properties": {
    "addr:full":"116 Main St Fredericton NB E3A 9N6",
    "addr:housenumber":"116",
    "addr:postcode":"e3a 9n6",
    "addr:street":"Main St",
    "iso:country":"CA",
    "sg:address":"116 Main St",
    "sg:city":"Fredericton",
    "sg:classifiers":[
        {
            "category":"Food & Beverages",
            "subcategory":"Groceries & Convenience Stores",
            "type":"Retail Goods"
        }
    ],
    "sg:phone":"+1 506 474 1270",
    "sg:postcode":"E3A 9N6",
    "sg:province":"NB",
    "sg:tags":[
        "florist",
        "grocer"
    ],
    "wof:name":"Atlantic Superstore Flower",
    "wof:placetype":"venue"
},
  "geometry": {"coordinates":[-66.656548,45.979446],"type":"Point"}
}