{
  "type": "Feature",
  "properties": {
    "addr:full":"102 Lindsay St S Lindsay ON K9V 2M6",
    "addr:housenumber":"102",
    "addr:postcode":"k9v 2m6",
    "addr:street":"Lindsay St S",
    "iso:country":"CA",
    "sg:address":"102 Lindsay St S",
    "sg:city":"Lindsay",
    "sg:classifiers":[
        {
            "category":"Social Services",
            "type":"Services"
        }
    ],
    "sg:phone":"+1 705 878 3379",
    "sg:postcode":"K9V 2M6",
    "sg:province":"ON",
    "sg:tags":[
        "organization",
        "welfare"
    ],
    "wof:name":"Survivors Psychiatric Advocacy",
    "wof:placetype":"venue"
},
  "geometry": {"coordinates":[-78.732727,44.351479],"type":"Point"}
}