{
  "type": "Feature",
  "properties": {
    "addr:full":"109 Magill St Lively ON P3Y 1K6",
    "addr:housenumber":"109",
    "addr:postcode":"p3y 1k6",
    "addr:street":"Magill St",
    "iso:country":"CA",
    "sg:address":"109 Magill St",
    "sg:city":"Lively",
    "sg:classifiers":[
        {
            "category":"Manufacturing",
            "subcategory":"Metals",
            "type":"Manufacturing & Wholesale Goods"
        }
    ],
    "sg:phone":"+1 705 692 5858",
    "sg:postcode":"P3Y 1K6",
    "sg:province":"ON",
    "sg:tags":[
        "plating"
    ],
    "wof:name":"Northern Plating Inc",
    "wof:placetype":"venue"
},
  "geometry": {"coordinates":[-81.12249799999999,46.435074],"type":"Point"}
}