{
  "type": "Feature",
  "properties": {
    "addr:full":"95 First St Orangeville ON L9W 2E8",
    "addr:housenumber":"95",
    "addr:postcode":"l9w 2e8",
    "addr:street":"First St",
    "iso:country":"CA",
    "sg:address":"95 First St",
    "sg:city":"Orangeville",
    "sg:classifiers":[
        {
            "category":"Travel",
            "subcategory":"Travel Agent",
            "type":"Entertainment"
        }
    ],
    "sg:phone":"+1 519 942 9552",
    "sg:postcode":"L9W 2E8",
    "sg:province":"ON",
    "sg:tags":[
        "agency",
        "bureau"
    ],
    "wof:name":"Marlin Travel",
    "wof:placetype":"venue"
},
  "geometry": {"coordinates":[-80.099823,43.929443],"type":"Point"}
}