{
  "type": "Feature",
  "properties": {
    "addr:full":"2300 6E Av Saint-Georges QC G5Y 3X5",
    "addr:housenumber":"2300",
    "addr:postcode":"g5y 3x5",
    "addr:street":"6E Av",
    "iso:country":"CA",
    "sg:address":"2300 6E Av",
    "sg:city":"Saint-Georges",
    "sg:classifiers":[
        {
            "category":"Personal",
            "subcategory":"Beauty Salon",
            "type":"Services"
        }
    ],
    "sg:phone":"+1 418 228 9557",
    "sg:postcode":"G5Y 3X5",
    "sg:province":"QC",
    "wof:name":"Duo Coiffure",
    "wof:placetype":"venue"
},
  "geometry": {"coordinates":[-70.67115,46.123348],"type":"Point"}
}