{
  "type": "Feature",
  "properties": {
    "iso:country":"CA",
    "sg:city":"Vancouver",
    "sg:classifiers":[
        {
            "category":"Food & Beverages",
            "subcategory":"Specialty",
            "type":"Retail Goods"
        }
    ],
    "sg:phone":"+1 604 683 5551",
    "sg:postcode":"V6C 2W2",
    "sg:province":"BC",
    "sg:tags":[
        "tea",
        "coffee"
    ],
    "wof:name":"Biega Cafe",
    "wof:placetype":"venue"
},
  "geometry": {"coordinates":[-123.116889954,49.287147522],"type":"Point"}
}