{
  "type": "Feature",
  "properties": {
    "addr:full":"RR 6 Lcd 9 Calgary AB T2M 4L5",
    "addr:housenumber":"9",
    "addr:postcode":"t2m 4l5",
    "addr:street":"Rr 6 Lcd",
    "iso:country":"CA",
    "sg:address":"RR 6 Lcd 9",
    "sg:city":"Calgary",
    "sg:classifiers":[
        {
            "category":"Freight",
            "type":"Transportation"
        }
    ],
    "sg:phone":"+1 403 248 5885",
    "sg:postcode":"T2M 4L5",
    "sg:province":"AB",
    "sg:tags":[
        "mover",
        "hauling"
    ],
    "wof:name":"Mark's City Hauling",
    "wof:placetype":"venue"
},
  "geometry": {"coordinates":[-114.063194,51.045074],"type":"Point"}
}