{
  "type": "Feature",
  "properties": {
    "addr:full":"38 Brydon Dr Etobicoke ON M9W 4N2",
    "addr:housenumber":"38",
    "addr:postcode":"m9w 4n2",
    "addr:street":"Brydon Dr",
    "iso:country":"CA",
    "sg:address":"38 Brydon Dr",
    "sg:city":"Etobicoke",
    "sg:classifiers":[
        {
            "category":"Manufacturing",
            "subcategory":"Tools & Machinery",
            "type":"Manufacturing & Wholesale Goods"
        }
    ],
    "sg:phone":"+1 416 744 2494",
    "sg:postcode":"M9W 4N2",
    "sg:province":"ON",
    "sg:tags":[
        "mold"
    ],
    "wof:name":"Glendan Mold Inc",
    "wof:placetype":"venue"
},
  "geometry": {"coordinates":[-79.572388,43.716171],"type":"Point"}
}