{
  "type": "Feature",
  "properties": {
    "addr:full":"1356 Rue Jarry E Montreal QC H2E 1A5",
    "addr:housenumber":"1356",
    "addr:postcode":"h2e 1a5",
    "addr:street":"Rue Jarry E",
    "iso:country":"CA",
    "sg:address":"1356 Rue Jarry E",
    "sg:city":"Montreal",
    "sg:classifiers":[
        {
            "category":"Restaurant",
            "type":"Food & Drink"
        }
    ],
    "sg:phone":"+1 514 722 3694",
    "sg:postcode":"H2E 1A5",
    "sg:province":"QC",
    "wof:name":"Belle Province GA Enr",
    "wof:placetype":"venue"
},
  "geometry": {"coordinates":[-73.6213378906,45.550453186],"type":"Point"}
}