{
  "type": "Feature",
  "properties": {
    "addr:full":"282 Roncesvalles Ave Toronto ON M6R 2M2",
    "addr:housenumber":"282",
    "addr:postcode":"m6r 2m2",
    "addr:street":"Roncesvalles Ave",
    "iso:country":"CA",
    "sg:address":"282 Roncesvalles Ave",
    "sg:city":"Toronto",
    "sg:classifiers":[
        {
            "category":"Health Services",
            "subcategory":"Optometrist",
            "type":"Services"
        }
    ],
    "sg:phone":"+1 416 531 4251",
    "sg:postcode":"M6R 2M2",
    "sg:province":"ON",
    "wof:name":"Galek, L OD",
    "wof:placetype":"venue"
},
  "geometry": {"coordinates":[-79.449806,43.647793],"type":"Point"}
}