{
  "type": "Feature",
  "properties": {
    "addr:full":"665 Pine St Nanaimo BC V9R 2C9",
    "addr:housenumber":"665",
    "addr:postcode":"v9r 2c9",
    "addr:street":"Pine St",
    "iso:country":"CA",
    "sg:address":"665 Pine St",
    "sg:city":"Nanaimo",
    "sg:classifiers":[
        {
            "category":"Building & Trades",
            "subcategory":"Plumbing",
            "type":"Services"
        }
    ],
    "sg:phone":"+1 250 753 1341",
    "sg:postcode":"V9R 2C9",
    "sg:province":"BC",
    "sg:tags":[
        "contractor"
    ],
    "wof:name":"Mason Plumbing & Heating Ltd",
    "wof:placetype":"venue"
},
  "geometry": {"coordinates":[-123.938301,49.155636],"type":"Point"}
}