{
  "type": "Feature",
  "properties": {
    "addr:full":"PO Box 839 Vulcan AB T0L 2B0",
    "addr:housenumber":"po",
    "addr:postcode":"t0l 2b0",
    "addr:street":"Box 839 Vulcan",
    "iso:country":"CA",
    "sg:address":"PO Box 839",
    "sg:city":"Vulcan",
    "sg:classifiers":[
        {
            "category":"Professional",
            "subcategory":"Business Services",
            "type":"Services"
        }
    ],
    "sg:phone":"+1 403 485 2440",
    "sg:postcode":"T0L 2B0",
    "sg:province":"AB",
    "sg:tags":[
        "auctioneer"
    ],
    "wof:name":"Frank Mc Inenly Auctions Ltd",
    "wof:placetype":"venue"
},
  "geometry": {"coordinates":[-113.258179,50.397339],"type":"Point"}
}