{
  "type": "Feature",
  "properties": {
    "iso:country":"CA",
    "sg:city":"Trois-Rivieres",
    "sg:classifiers":[
        {
            "category":"Retail",
            "subcategory":"Repair Shop",
            "type":"Services"
        }
    ],
    "sg:phone":"+1 819 373 8256",
    "sg:postcode":"G8Y 3C8",
    "sg:province":"QC",
    "sg:tags":[
        "upholsterer"
    ],
    "wof:name":"S L St Louis Rembourrage",
    "wof:placetype":"venue"
},
  "geometry": {"coordinates":[-72.601761,46.372021],"type":"Point"}
}