{
  "type": "Feature",
  "properties": {
    "addr:full":"2881 Richmond Rd Ottawa ON K2B 8J5",
    "addr:housenumber":"2881",
    "addr:postcode":"k2b 8j5",
    "addr:street":"Richmond Rd",
    "iso:country":"CA",
    "sg:address":"2881 Richmond Rd",
    "sg:city":"Ottawa",
    "sg:classifiers":[
        {
            "category":"Real Estate",
            "subcategory":"Real Estate Operator",
            "type":"Services"
        }
    ],
    "sg:phone":"+1 613 729 4115",
    "sg:postcode":"K2B 8J5",
    "sg:province":"ON",
    "sg:tags":[
        "apartment"
    ],
    "wof:name":"William Mosgrove Tower",
    "wof:placetype":"venue"
},
  "geometry": {"coordinates":[-75.797127,45.355278],"type":"Point"}
}