{
  "type": "Feature",
  "properties": {
    "addr:full":"8100 Boul Du Golf Anjou QC H1J 3A4",
    "addr:housenumber":"8100",
    "addr:postcode":"h1j 3a4",
    "addr:street":"Boul Du Golf",
    "iso:country":"CA",
    "sg:address":"8100 Boul Du Golf",
    "sg:city":"Anjou",
    "sg:classifiers":[
        {
            "category":"Autos & Motor Vehicles",
            "subcategory":"Fuel & Gas Station",
            "type":"Retail Goods"
        }
    ],
    "sg:phone":"+1 514 355 1467",
    "sg:postcode":"H1J 3A4",
    "sg:province":"QC",
    "sg:tags":[
        "oil"
    ],
    "wof:name":"Petro-Canada",
    "wof:placetype":"venue"
},
  "geometry": {"coordinates":[-73.55387115480001,45.6199645996],"type":"Point"}
}