{
  "type": "Feature",
  "properties": {
    "addr:full":"251 Ch Ulderic-Brien Sainte-Anne-DE-LA-Rochelle QC J0E 2B0",
    "addr:housenumber":"251",
    "addr:postcode":"j0e 2b0",
    "addr:street":"Ch Ulderic-Brien",
    "iso:country":"CA",
    "sg:address":"251 Ch Ulderic-Brien",
    "sg:city":"Sainte-Anne-DE-LA-Rochelle",
    "sg:classifiers":[
        {
            "category":"Mining & Drilling",
            "type":"Manufacturing & Wholesale Goods"
        }
    ],
    "sg:phone":"+1 450 535 6877",
    "sg:postcode":"J0E 2B0",
    "sg:province":"QC",
    "sg:tags":[
        "stone",
        "quarry"
    ],
    "wof:name":"Carriere Ste-Anne-LA Rochelle",
    "wof:placetype":"venue"
},
  "geometry": {"coordinates":[-72.3597946167,45.3904190063],"type":"Point"}
}