{
  "type": "Feature",
  "properties": {
    "addr:full":"424 Rue St-Jean Wotton QC J0A 1N0",
    "addr:housenumber":"424",
    "addr:postcode":"j0a 1n0",
    "addr:street":"Rue St-Jean",
    "iso:country":"CA",
    "sg:address":"424 Rue St-Jean",
    "sg:city":"Wotton",
    "sg:classifiers":[
        {
            "category":"Retail",
            "subcategory":"Auto Repair",
            "type":"Services"
        }
    ],
    "sg:phone":"+1 819 828 2660",
    "sg:postcode":"J0A 1N0",
    "sg:province":"QC",
    "sg:tags":[
        "repairing",
        "automobile"
    ],
    "wof:name":"Gilles Goulet Auto Inc",
    "wof:placetype":"venue"
},
  "geometry": {"coordinates":[-71.796967,45.73267],"type":"Point"}
}