{
  "type": "Feature",
  "properties": {
    "addr:full":"19990 Langley Bypass Langley BC V3A 4Y1",
    "addr:housenumber":"19990",
    "addr:postcode":"v3a 4y1",
    "addr:street":"Langley Bypass",
    "iso:country":"CA",
    "sg:address":"19990 Langley Bypass",
    "sg:city":"Langley",
    "sg:classifiers":[
        {
            "category":"Autos & Motor Vehicles",
            "subcategory":"Automobile Sales",
            "type":"Retail Goods"
        }
    ],
    "sg:phone":"+1 604 534 4154",
    "sg:postcode":"V3A 4Y1",
    "sg:province":"BC",
    "sg:tags":[
        "car",
        "dealer"
    ],
    "wof:name":"Preston Chevrolet Oldsmobile",
    "wof:placetype":"venue"
},
  "geometry": {"coordinates":[-122.669151,49.113289],"type":"Point"}
}