{
  "type": "Feature",
  "properties": {
    "iso:country":"CA",
    "sg:address":"2 Fisherman's Rd",
    "sg:city":"Saint John",
    "sg:classifiers":[
        {
            "category":"Food & Beverages",
            "subcategory":"Specialty",
            "type":"Retail Goods"
        }
    ],
    "sg:phone":"+1 506 635 4122",
    "sg:postcode":"E2M 3G9",
    "sg:province":"NB",
    "sg:tags":[
        "nutritionist",
        "health",
        "diet"
    ],
    "wof:name":"Shaklee Products Distributor",
    "wof:placetype":"venue"
},
  "geometry": {"coordinates":[-66.18427276609999,45.2930526733],"type":"Point"}
}