{
  "type": "Feature",
  "properties": {
    "addr:full":"Greenfield Park QC J4V 2L7",
    "addr:postcode":"j4v 2l7",
    "addr:street":"Park",
    "iso:country":"CA",
    "sg:city":"Greenfield Park",
    "sg:classifiers":[
        {
            "category":"Health Services",
            "subcategory":"Health Practitioner",
            "type":"Services"
        }
    ],
    "sg:phone":"+1 450 923 9800",
    "sg:postcode":"J4V 2L7",
    "sg:province":"QC",
    "sg:tags":[
        "speech",
        "therapy",
        "hearing"
    ],
    "wof:name":"Danielle Noreau Moa",
    "wof:placetype":"venue"
},
  "geometry": {"coordinates":[-73.49142500000001,45.489361],"type":"Point"}
}