{
  "type": "Feature",
  "properties": {
    "addr:full":"2336 Craig Side Rd Carp ON K0A 1L0",
    "addr:housenumber":"2336",
    "addr:postcode":"k0a 1l0",
    "addr:street":"Craig Side Rd",
    "iso:country":"CA",
    "sg:address":"2336 Craig Side Rd",
    "sg:city":"Carp",
    "sg:classifiers":[
        {
            "category":"Professional",
            "subcategory":"Management & Consulting",
            "type":"Services"
        }
    ],
    "sg:phone":"+1 613 839 1555",
    "sg:postcode":"K0A 1L0",
    "sg:province":"ON",
    "sg:tags":[
        "consultant",
        "business"
    ],
    "wof:name":"Peter W Maddocks Consulting",
    "wof:placetype":"venue"
},
  "geometry": {"coordinates":[-76.042587,45.350044],"type":"Point"}
}