{
  "type": "Feature",
  "properties": {
    "addr:full":"1469 Birmingham St Halifax NS B3J 2J4",
    "addr:housenumber":"1469",
    "addr:postcode":"ns b3j 2j4",
    "addr:street":"Birmingham St",
    "iso:country":"CA",
    "sg:address":"1469 Birmingham St",
    "sg:city":"Halifax",
    "sg:classifiers":[
        {
            "category":"Professional",
            "subcategory":"Art Services",
            "type":"Services"
        }
    ],
    "sg:phone":"+1 902 423 8840",
    "sg:postcode":"B3J 2J4",
    "sg:province":"NS",
    "sg:tags":[
        "photographer"
    ],
    "wof:name":"Calnen of Canada Ltd",
    "wof:placetype":"venue"
},
  "geometry": {"coordinates":[-63.576515,44.642677],"type":"Point"}
}