{
  "type": "Feature",
  "properties": {
    "addr:full":"18 Gray St Coldwater ON L0K 1E0",
    "addr:housenumber":"18",
    "addr:postcode":"l0k 1e0",
    "addr:street":"Gray St",
    "iso:country":"CA",
    "sg:address":"18 Gray St",
    "sg:city":"Coldwater",
    "sg:classifiers":[
        {
            "category":"Organizations",
            "subcategory":"Religious Organization",
            "type":"Services"
        }
    ],
    "sg:phone":"+1 705 686 3663",
    "sg:postcode":"L0K 1E0",
    "sg:province":"ON",
    "sg:tags":[
        "church"
    ],
    "wof:name":"St Matthias Anglican Church",
    "wof:placetype":"venue"
},
  "geometry": {"coordinates":[-79.64093800000001,44.711224],"type":"Point"}
}