{
  "type": "Feature",
  "properties": {
    "addr:full":"1366 Marine Dr Gibsons BC V0N 1V1",
    "addr:housenumber":"1366",
    "addr:postcode":"v0n 1v1",
    "addr:street":"Marine Dr",
    "iso:country":"CA",
    "sg:address":"1366 Marine Dr",
    "sg:city":"Gibsons",
    "sg:classifiers":[
        {
            "category":"Travel",
            "subcategory":"Campground",
            "type":"Entertainment"
        }
    ],
    "sg:phone":"+1 604 886 7232",
    "sg:postcode":"V0N 1V1",
    "sg:province":"BC",
    "sg:tags":[
        "camp"
    ],
    "wof:name":"Salvation Army Camp",
    "wof:placetype":"venue"
},
  "geometry": {"coordinates":[-123.50151099999999,49.405689],"type":"Point"}
}