{
  "type": "Feature",
  "properties": {
    "addr:full":"240 3E Rue Quebec QC G1L 2S8",
    "addr:housenumber":"240",
    "addr:postcode":"g1l 2s8",
    "addr:street":"3E Rue Quebec",
    "iso:country":"CA",
    "sg:address":"240 3E Rue",
    "sg:city":"Quebec",
    "sg:classifiers":[
        {
            "category":"Wholesale",
            "subcategory":"Motor Vehicles",
            "type":"Manufacturing & Wholesale Goods"
        }
    ],
    "sg:phone":"+1 418 529 0616",
    "sg:postcode":"G1L 2S8",
    "sg:province":"QC",
    "sg:tags":[
        "bus"
    ],
    "wof:name":"Dupontroley Industries Inc",
    "wof:placetype":"venue"
},
  "geometry": {"coordinates":[-71.226692,46.821613],"type":"Point"}
}