{
  "type": "Feature",
  "properties": {
    "addr:full":"RR 1 Kakabeka Falls ON P0T 1W0",
    "addr:postcode":"p0t 1w0",
    "addr:street":"Rr 1 Kakabeka",
    "iso:country":"CA",
    "sg:address":"RR 1",
    "sg:city":"Kakabeka Falls",
    "sg:classifiers":[
        {
            "category":"Government",
            "subcategory":"Office",
            "type":"Public Place"
        }
    ],
    "sg:phone":"+1 807 475 5337",
    "sg:postcode":"P0T 1W0",
    "sg:province":"ON",
    "sg:tags":[
        "village"
    ],
    "wof:name":"Conmee Garage",
    "wof:placetype":"venue"
},
  "geometry": {"coordinates":[-89.614563,48.401741],"type":"Point"}
}