{
  "type": "Feature",
  "properties": {
    "iso:country":"CA",
    "sg:address":"471 Rothesay Ave",
    "sg:city":"Saint John",
    "sg:classifiers":[
        {
            "category":"Restaurant",
            "type":"Food & Drink"
        }
    ],
    "sg:phone":"+1 506 633 8114",
    "sg:postcode":"E2J 2C6",
    "sg:province":"NB",
    "wof:name":"Deluxe French Fries Ltd",
    "wof:placetype":"venue"
},
  "geometry": {"coordinates":[-66.0308456421,45.3081817627],"type":"Point"}
}