{
  "type": "Feature",
  "properties": {
    "addr:full":"98 Bayfield St Barrie ON L4M 3A8",
    "addr:housenumber":"98",
    "addr:postcode":"l4m 3a8",
    "addr:street":"Bayfield St",
    "iso:country":"CA",
    "sg:address":"98 Bayfield St",
    "sg:city":"Barrie",
    "sg:classifiers":[
        {
            "category":"Shopping",
            "subcategory":"Musical Instruments",
            "type":"Retail Goods"
        }
    ],
    "sg:phone":"+1 705 726 3665",
    "sg:postcode":"L4M 3A8",
    "sg:province":"ON",
    "sg:tags":[
        "machine",
        "karaoke",
        "sales"
    ],
    "wof:name":"Fred Desjardins Sales",
    "wof:placetype":"venue"
},
  "geometry": {"coordinates":[-79.69229900000001,44.391563],"type":"Point"}
}