{
  "type": "Feature",
  "properties": {
    "addr:full":"227 Glendora Ave North York ON M2N 2W6",
    "addr:housenumber":"227",
    "addr:postcode":"m2n 2w6",
    "addr:street":"Glendora Ave",
    "iso:country":"CA",
    "sg:address":"227 Glendora Ave",
    "sg:city":"North York",
    "sg:classifiers":[
        {
            "category":"Wholesale",
            "subcategory":"Groceries",
            "type":"Manufacturing & Wholesale Goods"
        }
    ],
    "sg:phone":"+1 416 225 1777",
    "sg:postcode":"M2N 2W6",
    "sg:province":"ON",
    "sg:tags":[
        "food",
        "broker"
    ],
    "wof:name":"Provision Sales & Marketing",
    "wof:placetype":"venue"
},
  "geometry": {"coordinates":[-79.39581298829999,43.7621307373],"type":"Point"}
}