{
  "type": "Feature",
  "properties": {
    "addr:full":"65 Rue Principale Messines QC J0X 2J0",
    "addr:housenumber":"65",
    "addr:postcode":"j0x 2j0",
    "addr:street":"Rue Principale",
    "iso:country":"CA",
    "sg:address":"65 Rue Principale",
    "sg:city":"Messines",
    "sg:classifiers":[
        {
            "category":"Food & Beverages",
            "subcategory":"Groceries & Convenience Stores",
            "type":"Retail Goods"
        }
    ],
    "sg:phone":"+1 819 465 2367",
    "sg:postcode":"J0X 2J0",
    "sg:province":"QC",
    "sg:tags":[
        "grocer"
    ],
    "wof:name":"Alex Lafreniere & Fils Epcr",
    "wof:placetype":"venue"
},
  "geometry": {"coordinates":[-76.02178192140001,46.2424049377],"type":"Point"}
}