{
  "type": "Feature",
  "properties": {
    "addr:full":"84 Place Bourget N Joliette QC J6E 5E5",
    "addr:housenumber":"84",
    "addr:postcode":"j6e 5e5",
    "addr:street":"Place Bourget N",
    "iso:country":"CA",
    "sg:address":"84 Place Bourget N",
    "sg:city":"Joliette",
    "sg:classifiers":[
        {
            "category":"Shopping",
            "subcategory":"Discount & Variety Stores",
            "type":"Retail Goods"
        }
    ],
    "sg:phone":"+1 450 752 4127",
    "sg:postcode":"J6E 5E5",
    "sg:province":"QC",
    "wof:name":"Village Des Bons Prix",
    "wof:placetype":"venue"
},
  "geometry": {"coordinates":[-73.441238,46.025524],"type":"Point"}
}