{
  "type": "Feature",
  "properties": {
    "iso:country":"CA",
    "sg:address":"250 Boul DE Quen N",
    "sg:city":"Alma",
    "sg:classifiers":[
        {
            "category":"Personal",
            "type":"Services"
        }
    ],
    "sg:phone":"+1 418 662 7991",
    "sg:postcode":"G8B 5N7",
    "sg:province":"QC",
    "sg:tags":[
        "electrolysis"
    ],
    "wof:name":"Centre D'Esthetique",
    "wof:placetype":"venue"
},
  "geometry": {"coordinates":[-71.64841461180001,48.5564575195],"type":"Point"}
}