{
  "type": "Feature",
  "properties": {
    "addr:full":"St Isidore AB T0H 3B0",
    "addr:housenumber":"3b0",
    "addr:street":"St;T0H",
    "iso:country":"CA",
    "sg:city":"St Isidore",
    "sg:classifiers":[
        {
            "category":"Manufacturing",
            "subcategory":"Metals",
            "type":"Manufacturing & Wholesale Goods"
        }
    ],
    "sg:phone":"+1 780 624 2487",
    "sg:postcode":"T0H 3B0",
    "sg:province":"AB",
    "sg:tags":[
        "steel"
    ],
    "wof:name":"Marcel's Mobile Mechanic",
    "wof:placetype":"venue"
},
  "geometry": {"coordinates":[-117.108810425,56.2059364319],"type":"Point"}
}