{
  "type": "Feature",
  "properties": {
    "addr:full":"87 Kent Ave North E Vancouver BC V5X 2X5",
    "addr:housenumber":"87",
    "addr:postcode":"v5x 2x5",
    "addr:street":"Kent Ave North E",
    "iso:country":"CA",
    "sg:address":"87 Kent Ave North E",
    "sg:city":"Vancouver",
    "sg:classifiers":[
        {
            "category":"Building & Trades",
            "subcategory":"Construction",
            "type":"Services"
        }
    ],
    "sg:phone":"+1 604 301 2012",
    "sg:postcode":"V5X 2X5",
    "sg:province":"BC",
    "sg:tags":[
        "waterproofing",
        "contractor"
    ],
    "wof:name":"Hallmark Decking-Waterproofing",
    "wof:placetype":"venue"
},
  "geometry": {"coordinates":[-123.104881287,49.2071990967],"type":"Point"}
}