{
  "type": "Feature",
  "properties": {
    "addr:full":"6787 Dorchester Rd Niagara Falls ON L2G 5V1",
    "addr:housenumber":"6787",
    "addr:postcode":"l2g 5v1",
    "addr:street":"Dorchester Rd",
    "iso:country":"CA",
    "sg:address":"6787 Dorchester Rd",
    "sg:city":"Niagara Falls",
    "sg:classifiers":[
        {
            "category":"Retail",
            "subcategory":"Car Wash",
            "type":"Services"
        }
    ],
    "sg:phone":"+1 905 356 4993",
    "sg:postcode":"L2G 5V1",
    "sg:province":"ON",
    "sg:tags":[
        "automobile",
        "detail",
        "clean"
    ],
    "wof:name":"Rust Stops",
    "wof:placetype":"venue"
},
  "geometry": {"coordinates":[-79.11023712159999,43.0767097473],"type":"Point"}
}