{
  "type": "Feature",
  "properties": {
    "iso:country":"CA",
    "sg:address":"281 Falconbridge Rd",
    "sg:city":"Sudbury",
    "sg:classifiers":[
        {
            "category":"Health Services",
            "subcategory":"Nursing And Care Facility",
            "type":"Services"
        }
    ],
    "sg:phone":"+1 705 566 7980",
    "sg:postcode":"P3A 5K4",
    "sg:province":"ON",
    "sg:tags":[
        "home",
        "convalescent"
    ],
    "wof:name":"Extendicare",
    "wof:placetype":"venue"
},
  "geometry": {"coordinates":[-80.9362792969,46.50730896],"type":"Point"}
}