{
  "type": "Feature",
  "properties": {
    "addr:full":"3450 Boul Sir-Wilfrid-Laurier Saint-Hubert QC J3Y 6T1",
    "addr:housenumber":"3450",
    "addr:postcode":"j3y 6t1",
    "addr:street":"Boul Sir-Wilfrid-Laurier",
    "iso:country":"CA",
    "sg:address":"3450 Boul Sir-Wilfrid-Laurier",
    "sg:city":"Saint-Hubert",
    "sg:classifiers":[
        {
            "category":"Wholesale",
            "subcategory":"Machinery & Supplies",
            "type":"Manufacturing & Wholesale Goods"
        }
    ],
    "sg:phone":"+1 450 678 6091",
    "sg:postcode":"J3Y 6T1",
    "sg:province":"QC",
    "sg:tags":[
        "contractor"
    ],
    "wof:name":"Hewitt Equipement Ltee",
    "wof:placetype":"venue"
},
  "geometry": {"coordinates":[-73.45536800000001,45.506008],"type":"Point"}
}