{
  "type": "Feature",
  "properties": {
    "addr:full":"132 Demers Dr Fort Mcmurray AB T9H 2B1",
    "addr:housenumber":"132",
    "addr:postcode":"t9h 2b1",
    "addr:street":"Demers Dr",
    "iso:country":"CA",
    "sg:address":"132 Demers Dr",
    "sg:city":"Fort Mcmurray",
    "sg:classifiers":[
        {
            "category":"Organizations",
            "subcategory":"Professional Association",
            "type":"Services"
        }
    ],
    "sg:phone":"+1 780 715 2744",
    "sg:postcode":"T9H 2B1",
    "sg:province":"AB",
    "wof:name":"Multple Sclerosis Society",
    "wof:placetype":"venue"
},
  "geometry": {"coordinates":[-111.372276306,56.7284698486],"type":"Point"}
}