{
  "type": "Feature",
  "properties": {
    "addr:full":"10007 98 Ave Grande Prairie AB T8V 6P8",
    "addr:housenumber":"10007",
    "addr:postcode":"t8v 6p8",
    "addr:street":"98 Ave",
    "iso:country":"CA",
    "sg:address":"10007 98 Ave",
    "sg:city":"Grande Prairie",
    "sg:classifiers":[
        {
            "category":"Retail",
            "subcategory":"Laundry & Dry Cleaning",
            "type":"Services"
        }
    ],
    "sg:phone":"+1 780 532 7610",
    "sg:postcode":"T8V 6P8",
    "sg:province":"AB",
    "sg:tags":[
        "cleaners"
    ],
    "wof:name":"Crouse's Cleaners",
    "wof:placetype":"venue"
},
  "geometry": {"coordinates":[-118.795196533,55.1686401367],"type":"Point"}
}