{
  "type": "Feature",
  "properties": {
    "addr:full":"Mississauga ON L5C 1T8",
    "addr:postcode":"l5c 1t8",
    "iso:country":"CA",
    "sg:city":"Mississauga",
    "sg:classifiers":[
        {
            "category":"Retail",
            "subcategory":"Auto Repair",
            "type":"Services"
        }
    ],
    "sg:phone":"+1 905 276 7250",
    "sg:postcode":"L5C 1T8",
    "sg:province":"ON",
    "sg:tags":[
        "repairing",
        "automobile"
    ],
    "wof:name":"Larry's Auto Repair",
    "wof:placetype":"venue"
},
  "geometry": {"coordinates":[-79.64273799999999,43.572685],"type":"Point"}
}