{
  "type": "Feature",
  "properties": {
    "iso:country":"CA",
    "sg:city":"Calgary",
    "sg:classifiers":[
        {
            "category":"Shopping",
            "type":"Retail Goods"
        }
    ],
    "sg:phone":"+1 403 262 2839",
    "sg:postcode":"T2A 0P9",
    "sg:province":"AB",
    "sg:tags":[
        "hearing",
        "equipment",
        "supply",
        "impaired"
    ],
    "wof:name":"Calgary Hearing Aid Ctr Ltd",
    "wof:placetype":"venue"
},
  "geometry": {"coordinates":[-113.992637634,51.0380325317],"type":"Point"}
}