{
  "type": "Feature",
  "properties": {
    "addr:full":"791 Bradford St Winnipeg MB R3H 0N2",
    "addr:housenumber":"791",
    "addr:postcode":"r3h 0n2",
    "addr:street":"Bradford St",
    "iso:country":"CA",
    "sg:address":"791 Bradford St",
    "sg:city":"Winnipeg",
    "sg:classifiers":[
        {
            "category":"Shopping",
            "subcategory":"Computers & Home Electronics",
            "type":"Retail Goods"
        }
    ],
    "sg:phone":"+1 204 633 9264",
    "sg:postcode":"R3H 0N2",
    "sg:province":"MB",
    "sg:tags":[
        "machine",
        "equipment",
        "duplicating",
        "copying",
        "dealer"
    ],
    "wof:name":"Gold Business Machines Ltd",
    "wof:placetype":"venue"
},
  "geometry": {"coordinates":[-97.2044219971,49.9007606506],"type":"Point"}
}