{
  "type": "Feature",
  "properties": {
    "iso:country":"CA",
    "sg:address":"477 Thorold Rd",
    "sg:city":"Welland",
    "sg:classifiers":[
        {
            "category":"Shopping",
            "subcategory":"Florist",
            "type":"Retail Goods"
        }
    ],
    "sg:phone":"+1 905 732 5633",
    "sg:postcode":"L3C 3W7",
    "sg:province":"ON",
    "wof:name":"Flowers Niagara",
    "wof:placetype":"venue"
},
  "geometry": {"coordinates":[-79.2796554565,43.0035171509],"type":"Point"}
}