{
  "type": "Feature",
  "properties": {
    "iso:country":"CA",
    "sg:address":"60 Victoria St N",
    "sg:city":"Kitchener",
    "sg:classifiers":[
        {
            "category":"Wholesale",
            "subcategory":"Toys & Hobbies",
            "type":"Manufacturing & Wholesale Goods"
        }
    ],
    "sg:phone":"+1 519 743 6341",
    "sg:postcode":"N2H 5B9",
    "sg:province":"ON",
    "sg:tags":[
        "arts",
        "craft"
    ],
    "wof:name":"Rumpel Felt CO Ltd",
    "wof:placetype":"venue"
},
  "geometry": {"coordinates":[-80.496628,43.454025],"type":"Point"}
}