{
  "type": "Feature",
  "properties": {
    "addr:full":"2957 Ch D'Oka Sainte-Marthe-Sur-Le-Lac QC J0N 1P0",
    "addr:housenumber":"2957",
    "addr:postcode":"j0n 1p0",
    "addr:street":"Ch D'Oka",
    "iso:country":"CA",
    "sg:address":"2957 Ch D'Oka",
    "sg:city":"Sainte-Marthe-Sur-Le-Lac",
    "sg:classifiers":[
        {
            "category":"Shopping",
            "subcategory":"Florist",
            "type":"Retail Goods"
        }
    ],
    "sg:phone":"+1 450 472 8120",
    "sg:postcode":"J0N 1P0",
    "sg:province":"QC",
    "wof:name":"Fleuriste Du Reve",
    "wof:placetype":"venue"
},
  "geometry": {"coordinates":[-73.99458300000001,45.501686],"type":"Point"}
}