{
  "type": "Feature",
  "properties": {
    "iso:country":"CA",
    "sg:address":"566 Mount Pleasant Rd",
    "sg:city":"Toronto",
    "sg:classifiers":[
        {
            "category":"Retail",
            "subcategory":"Self-service Laundry",
            "type":"Services"
        }
    ],
    "sg:phone":"+1 416 487 0465",
    "sg:postcode":"M4S 2M6",
    "sg:province":"ON",
    "sg:tags":[
        "cleaners"
    ],
    "wof:name":"24 Hour Coin Laundry",
    "wof:placetype":"venue"
},
  "geometry": {"coordinates":[-79.3881988525,43.7030105591],"type":"Point"}
}