{
  "type": "Feature",
  "properties": {
    "addr:full":"1310 Monashee Dr North Vancouver BC V7J 2J2",
    "addr:housenumber":"1310",
    "addr:postcode":"v7j 2j2",
    "addr:street":"Monashee Dr",
    "iso:country":"CA",
    "sg:address":"1310 Monashee Dr",
    "sg:city":"North Vancouver",
    "sg:classifiers":[
        {
            "category":"Retail",
            "subcategory":"Animal Services",
            "type":"Services"
        }
    ],
    "sg:phone":"+1 604 985 4913",
    "sg:postcode":"V7J 2J2",
    "sg:province":"BC",
    "sg:tags":[
        "pet",
        "boarding",
        "sitting"
    ],
    "wof:name":"Northwest Boarding Kennels Ltd",
    "wof:placetype":"venue"
},
  "geometry": {"coordinates":[-123.018074,49.319462],"type":"Point"}
}