{
  "type": "Feature",
  "properties": {
    "addr:full":"11750 162 Ave NW Edmonton AB T5X 4L9",
    "addr:housenumber":"11750",
    "addr:postcode":"t5x 4l9",
    "addr:street":"162 Ave Nw",
    "iso:country":"CA",
    "sg:address":"11750 162 Ave NW",
    "sg:city":"Edmonton",
    "sg:classifiers":[
        {
            "category":"Education",
            "subcategory":"School",
            "type":"Public Place"
        }
    ],
    "sg:phone":"+1 780 456 0053",
    "sg:postcode":"T5X 4L9",
    "sg:province":"AB",
    "wof:name":"St Lucy Catholic Elementary",
    "wof:placetype":"venue"
},
  "geometry": {"coordinates":[-113.52729034399999,53.6228713989],"type":"Point"}
}