{
  "type": "Feature",
  "properties": {
    "iso:country":"CA",
    "sg:address":"1091 Lauzon Rd",
    "sg:city":"Windsor",
    "sg:classifiers":[
        {
            "category":"Restaurant",
            "type":"Food & Drink"
        }
    ],
    "sg:phone":"+1 519 974 9535",
    "sg:postcode":"N8S 3M8",
    "sg:province":"ON",
    "sg:tags":[
        "pizza"
    ],
    "wof:name":"Little Caesars Pizza",
    "wof:placetype":"venue"
},
  "geometry": {"coordinates":[-82.9403915405,42.3275146484],"type":"Point"}
}