{
  "type": "Feature",
  "properties": {
    "addr:full":"West Vancouver BC V7T 1E2",
    "addr:postcode":"v7t 1e2",
    "iso:country":"CA",
    "sg:city":"West Vancouver",
    "sg:classifiers":[
        {
            "category":"Professional",
            "subcategory":"Computer Services",
            "type":"Services"
        }
    ],
    "sg:phone":"+1 604 925 0825",
    "sg:postcode":"V7T 1E2",
    "sg:province":"BC",
    "sg:tags":[
        "consultant",
        "designer"
    ],
    "wof:name":"Balaclava Investments Ltd",
    "wof:placetype":"venue"
},
  "geometry": {"coordinates":[-123.133781433,49.3281402588],"type":"Point"}
}