{
  "type": "Feature",
  "properties": {
    "iso:country":"CA",
    "sg:address":"904 Cordova St E",
    "sg:city":"Vancouver",
    "sg:classifiers":[
        {
            "category":"Professional",
            "subcategory":"Detective & Security Services",
            "type":"Services"
        }
    ],
    "sg:phone":"+1 604 258 4112",
    "sg:postcode":"V6A 1M6",
    "sg:province":"BC",
    "sg:tags":[
        "car",
        "armored"
    ],
    "wof:name":"Churchill Armoured Car Svc",
    "wof:placetype":"venue"
},
  "geometry": {"coordinates":[-123.08442688,49.2819213867],"type":"Point"}
}