{
  "type": "Feature",
  "properties": {
    "addr:full":"3355 William Ave North Vancouver BC V7K 1Z7",
    "addr:housenumber":"3355",
    "addr:postcode":"v7k 1z7",
    "addr:street":"William Ave",
    "iso:country":"CA",
    "sg:address":"3355 William Ave",
    "sg:city":"North Vancouver",
    "sg:classifiers":[
        {
            "category":"Recreation",
            "type":"Entertainment"
        }
    ],
    "sg:phone":"+1 604 986 8714",
    "sg:postcode":"V7K 1Z7",
    "sg:province":"BC",
    "sg:tags":[
        "stable"
    ],
    "wof:name":"Laura-Lynn Equestrian Ctr",
    "wof:placetype":"venue"
},
  "geometry": {"coordinates":[-123.050949097,49.3386535645],"type":"Point"}
}