{
  "type": "Feature",
  "properties": {
    "addr:full":"3111 Underhill Ave Burnaby BC V5A 3C8",
    "addr:housenumber":"3111",
    "addr:postcode":"v5a 3c8",
    "addr:street":"Underhill Ave",
    "iso:country":"CA",
    "sg:address":"3111 Underhill Ave",
    "sg:city":"Burnaby",
    "sg:classifiers":[
        {
            "category":"Retail",
            "subcategory":"Repair Shop",
            "type":"Services"
        }
    ],
    "sg:phone":"+1 604 444 1272",
    "sg:postcode":"V5A 3C8",
    "sg:province":"BC",
    "sg:tags":[
        "sound",
        "system",
        "high",
        "equipment",
        "stereophonic",
        "fidelity"
    ],
    "wof:name":"Lts Professional Sound",
    "wof:placetype":"venue"
},
  "geometry": {"coordinates":[-122.927734,49.256062],"type":"Point"}
}