{
  "type": "Feature",
  "properties": {
    "addr:full":"66 Tipton Cres Ajax ON L1T 4A6",
    "addr:housenumber":"66",
    "addr:postcode":"l1t 4a6",
    "addr:street":"Tipton Cres",
    "iso:country":"CA",
    "sg:address":"66 Tipton Cres",
    "sg:city":"Ajax",
    "sg:classifiers":[
        {
            "category":"Building & Trades",
            "subcategory":"Construction",
            "type":"Services"
        }
    ],
    "sg:phone":"+1 905 619 2797",
    "sg:postcode":"L1T 4A6",
    "sg:province":"ON",
    "sg:tags":[
        "maker",
        "cabinet"
    ],
    "wof:name":"Homeworthy Products Ltd",
    "wof:placetype":"venue"
},
  "geometry": {"coordinates":[-79.040108,43.86755],"type":"Point"}
}