{
  "type": "Feature",
  "properties": {
    "addr:full":"1260 Rue DE LA Gauchetiere O Montreal QC H3B 2S2",
    "addr:housenumber":"1260",
    "addr:postcode":"h3b 2s2",
    "addr:street":"Rue De La Gauchetiere O",
    "iso:country":"CA",
    "sg:address":"1260 Rue DE LA Gauchetiere O",
    "sg:city":"Montreal",
    "sg:classifiers":[
        {
            "category":"Cinema",
            "subcategory":"Movie Theater",
            "type":"Entertainment"
        }
    ],
    "sg:phone":"+1 514 932 2582",
    "sg:postcode":"H3B 2S2",
    "sg:province":"QC",
    "wof:name":"Centre Bell",
    "wof:placetype":"venue"
},
  "geometry": {"coordinates":[-73.56996917719999,45.496509552],"type":"Point"}
}