{
  "type": "Feature",
  "properties": {
    "addr:full":"26 Regan Rd Brampton ON L7A 1A7",
    "addr:housenumber":"26",
    "addr:postcode":"l7a 1a7",
    "addr:street":"Regan Rd",
    "iso:country":"CA",
    "sg:address":"26 Regan Rd",
    "sg:city":"Brampton",
    "sg:classifiers":[
        {
            "category":"Manufacturing",
            "subcategory":"Tools & Machinery",
            "type":"Manufacturing & Wholesale Goods"
        }
    ],
    "sg:phone":"+1 905 840 1579",
    "sg:postcode":"L7A 1A7",
    "sg:province":"ON",
    "sg:tags":[
        "spraying",
        "equipment"
    ],
    "wof:name":"Servair Inc",
    "wof:placetype":"venue"
},
  "geometry": {"coordinates":[-79.804397583,43.7032318115],"type":"Point"}
}