{
  "type": "Feature",
  "properties": {
    "addr:full":"2971 Springfield Rd Kelowna BC V1X 4N5",
    "addr:housenumber":"2971",
    "addr:postcode":"v1x 4n5",
    "addr:street":"Springfield Rd",
    "iso:country":"CA",
    "sg:address":"2971 Springfield Rd",
    "sg:city":"Kelowna",
    "sg:classifiers":[
        {
            "category":"Retail",
            "subcategory":"Auto Repair",
            "type":"Services"
        }
    ],
    "sg:phone":"+1 250 862 7799",
    "sg:postcode":"V1X 4N5",
    "sg:province":"BC",
    "sg:tags":[
        "glass",
        "coating",
        "tinting"
    ],
    "wof:name":"Ace Trim & Tint",
    "wof:placetype":"venue"
},
  "geometry": {"coordinates":[-119.39415741000001,49.8742752075],"type":"Point"}
}