{
  "type": "Feature",
  "properties": {
    "addr:full":"1586 Fairbank Lake Rd E Whitefish ON P0M 3E0",
    "addr:housenumber":"1586",
    "addr:postcode":"p0m 3e0",
    "addr:street":"Fairbank Lake Rd E",
    "iso:country":"CA",
    "sg:address":"1586 Fairbank Lake Rd E",
    "sg:city":"Whitefish",
    "sg:classifiers":[
        {
            "category":"Travel",
            "subcategory":"Hotels & Motels",
            "type":"Entertainment"
        }
    ],
    "sg:phone":"+1 705 866 2773",
    "sg:postcode":"P0M 3E0",
    "sg:province":"ON",
    "sg:tags":[
        "resort"
    ],
    "wof:name":"Fairbank Lake Resort",
    "wof:placetype":"venue"
},
  "geometry": {"coordinates":[-81.370895,46.374893],"type":"Point"}
}