{
  "type": "Feature",
  "properties": {
    "addr:full":"Langley BC V3A 6K8",
    "addr:postcode":"v3a 6k8",
    "iso:country":"CA",
    "sg:city":"Langley",
    "sg:classifiers":[
        {
            "category":"Building & Trades",
            "subcategory":"Plumbing",
            "type":"Services"
        }
    ],
    "sg:phone":"+1 604 533 8686",
    "sg:postcode":"V3A 6K8",
    "sg:province":"BC",
    "sg:tags":[
        "mechanical",
        "contractor"
    ],
    "wof:name":"Tri West Mechanical Ltd",
    "wof:placetype":"venue"
},
  "geometry": {"coordinates":[-122.653229,49.113052],"type":"Point"}
}