{
  "type": "Feature",
  "properties": {
    "addr:full":"1275 Av Bourgogne Chambly QC J3L 1X8",
    "addr:housenumber":"1275",
    "addr:postcode":"j3l 1x8",
    "addr:street":"Av Bourgogne",
    "iso:country":"CA",
    "sg:address":"1275 Av Bourgogne",
    "sg:city":"Chambly",
    "sg:classifiers":[
        {
            "category":"Retail",
            "subcategory":"Auto Repair",
            "type":"Services"
        }
    ],
    "sg:phone":"+1 450 447 7606",
    "sg:postcode":"J3L 1X8",
    "sg:province":"QC",
    "sg:tags":[
        "transmission"
    ],
    "wof:name":"Chambly Auto Transmission Inc",
    "wof:placetype":"venue"
},
  "geometry": {"coordinates":[-73.2991104126,45.4537734985],"type":"Point"}
}