{
  "type": "Feature",
  "properties": {
    "addr:full":"40 Bennett St Carleton Place ON K7C 4J9",
    "addr:housenumber":"40",
    "addr:postcode":"k7c 4j9",
    "addr:street":"Bennett St",
    "iso:country":"CA",
    "sg:address":"40 Bennett St",
    "sg:city":"Carleton Place",
    "sg:classifiers":[
        {
            "category":"Professional",
            "type":"Services"
        }
    ],
    "sg:phone":"+1 613 253 3378",
    "sg:postcode":"K7C 4J9",
    "sg:province":"ON",
    "sg:tags":[
        "establishment",
        "brewer"
    ],
    "wof:name":"Silicone North Brewing CO",
    "wof:placetype":"venue"
},
  "geometry": {"coordinates":[-76.130348,45.127895],"type":"Point"}
}