{
  "type": "Feature",
  "properties": {
    "iso:country":"CA",
    "sg:address":"2022 Rue Peel",
    "sg:city":"Montreal",
    "sg:classifiers":[
        {
            "category":"Restaurant",
            "type":"Food & Drink"
        }
    ],
    "sg:phone":"+1 514 281 6492",
    "sg:postcode":"H3A 1W5",
    "sg:province":"QC",
    "wof:name":"Entrecote St Jean",
    "wof:placetype":"venue"
},
  "geometry": {"coordinates":[-73.575340271,45.5010719299],"type":"Point"}
}