{
  "type": "Feature",
  "properties": {
    "addr:full":"Ingersoll ON N5C 3J6",
    "addr:postcode":"n5c 3j6",
    "iso:country":"CA",
    "sg:city":"Ingersoll",
    "sg:classifiers":[
        {
            "category":"Home & Garden",
            "subcategory":"Building Materials",
            "type":"Retail Goods"
        }
    ],
    "sg:phone":"+1 519 485 0702",
    "sg:postcode":"N5C 3J6",
    "sg:province":"ON",
    "sg:tags":[
        "insulation"
    ],
    "wof:name":"Canadian Comfort Insulation",
    "wof:placetype":"venue"
},
  "geometry": {"coordinates":[-80.88385,43.038116],"type":"Point"}
}