{
  "type": "Feature",
  "properties": {
    "addr:full":"4215 46 St Ponoka AB T4J 1C1",
    "addr:housenumber":"4215",
    "addr:postcode":"t4j 1c1",
    "addr:street":"46 St",
    "iso:country":"CA",
    "sg:address":"4215 46 St",
    "sg:city":"Ponoka",
    "sg:classifiers":[
        {
            "category":"Organizations",
            "subcategory":"Religious Organization",
            "type":"Services"
        }
    ],
    "sg:phone":"+1 403 783 3958",
    "sg:postcode":"T4J 1C1",
    "sg:province":"AB",
    "sg:tags":[
        "church"
    ],
    "wof:name":"Alliance Church Ponoka",
    "wof:placetype":"venue"
},
  "geometry": {"coordinates":[-113.570999,52.670963],"type":"Point"}
}