{
  "type": "Feature",
  "properties": {
    "addr:full":"24 Union St Corner Brook NL A2H 5P8",
    "addr:housenumber":"24",
    "addr:postcode":"a2h 5p8",
    "addr:street":"Union St",
    "iso:country":"CA",
    "sg:address":"24 Union St",
    "sg:city":"Corner Brook",
    "sg:classifiers":[
        {
            "category":"Wholesale",
            "subcategory":"Hardware",
            "type":"Manufacturing & Wholesale Goods"
        }
    ],
    "sg:phone":"+1 709 634 4307",
    "sg:postcode":"A2H 5P8",
    "sg:province":"NL",
    "sg:tags":[
        "plumbing",
        "fixture",
        "supply"
    ],
    "wof:name":"Crane Supply",
    "wof:placetype":"venue"
},
  "geometry": {"coordinates":[-57.949551,48.943359],"type":"Point"}
}