{
  "type": "Feature",
  "properties": {
    "iso:country":"CA",
    "sg:address":"7 Erie St S",
    "sg:city":"Wheatley",
    "sg:classifiers":[
        {
            "category":"Personal",
            "subcategory":"Beauty Salon",
            "type":"Services"
        }
    ],
    "sg:phone":"+1 519 825 4670",
    "sg:postcode":"N0P 2P0",
    "sg:province":"ON",
    "wof:name":"Haircraft 77",
    "wof:placetype":"venue"
},
  "geometry": {"coordinates":[-82.462753,42.094753],"type":"Point"}
}