{
  "type": "Feature",
  "properties": {
    "addr:full":"3129 Boul Industriel Laval QC H7L 4P8",
    "addr:housenumber":"3129",
    "addr:postcode":"h7l 4p8",
    "addr:street":"Boul Industriel",
    "iso:country":"CA",
    "sg:address":"3129 Boul Industriel",
    "sg:city":"Laval",
    "sg:classifiers":[
        {
            "category":"Home & Garden",
            "subcategory":"Building Materials",
            "type":"Retail Goods"
        }
    ],
    "sg:phone":"+1 450 669 4668",
    "sg:postcode":"H7L 4P8",
    "sg:province":"QC",
    "sg:tags":[
        "door"
    ],
    "wof:name":"Gestion Crt Enr",
    "wof:placetype":"venue"
},
  "geometry": {"coordinates":[-73.742424,45.590801],"type":"Point"}
}