{
  "type": "Feature",
  "properties": {
    "addr:full":"626 4th St Estevan SK S4A 0V5",
    "addr:housenumber":"626",
    "addr:postcode":"s4a 0v5",
    "addr:street":"4Th St",
    "iso:country":"CA",
    "sg:address":"626 4th St",
    "sg:city":"Estevan",
    "sg:classifiers":[
        {
            "category":"Retail",
            "subcategory":"Repair Shop",
            "type":"Services"
        }
    ],
    "sg:phone":"+1 306 634 6943",
    "sg:postcode":"S4A 0V5",
    "sg:province":"SK",
    "sg:tags":[
        "lock",
        "locksmith"
    ],
    "wof:name":"Estevan Lock & Security",
    "wof:placetype":"venue"
},
  "geometry": {"coordinates":[-102.983375549,49.1359405518],"type":"Point"}
}