{
  "type": "Feature",
  "properties": {
    "addr:full":"Scarborough ON M1V 5E4",
    "addr:postcode":"m1v 5e4",
    "iso:country":"CA",
    "sg:city":"Scarborough",
    "sg:classifiers":[
        {
            "category":"Building & Trades",
            "subcategory":"Plumbing",
            "type":"Services"
        }
    ],
    "sg:phone":"+1 416 754 8147",
    "sg:postcode":"M1V 5E4",
    "sg:province":"ON",
    "sg:tags":[
        "conditioning",
        "air",
        "system",
        "contractor"
    ],
    "wof:name":"V K Mechanical Svc",
    "wof:placetype":"venue"
},
  "geometry": {"coordinates":[-79.256767,43.818161],"type":"Point"}
}