{
  "type": "Feature",
  "properties": {
    "addr:full":"4407 2nd St Peachland BC V0H 1X7",
    "addr:housenumber":"4407",
    "addr:postcode":"v0h 1x7",
    "addr:street":"2Nd St",
    "iso:country":"CA",
    "sg:address":"4407 2nd St",
    "sg:city":"Peachland",
    "sg:classifiers":[
        {
            "category":"Organizations",
            "subcategory":"Professional Association",
            "type":"Services"
        }
    ],
    "sg:phone":"+1 250 767 9404",
    "sg:postcode":"V0H 1X7",
    "sg:province":"BC",
    "wof:name":"Royal Canadian Legion",
    "wof:placetype":"venue"
},
  "geometry": {"coordinates":[-119.73696899399999,49.7731513977],"type":"Point"}
}