{
  "type": "Feature",
  "properties": {
    "iso:country":"CA",
    "sg:address":"2194 Rue Galt O",
    "sg:city":"Sherbrooke",
    "sg:classifiers":[
        {
            "category":"Personal",
            "subcategory":"Beauty Salon",
            "type":"Services"
        }
    ],
    "sg:phone":"+1 819 562 8311",
    "sg:postcode":"J1K 1K4",
    "sg:province":"QC",
    "wof:name":"Salon Loic Coiffure",
    "wof:placetype":"venue"
},
  "geometry": {"coordinates":[-71.926735,45.386787],"type":"Point"}
}