{
  "type": "Feature",
  "properties": {
    "addr:full":"105 Rue Principale S Lebel-Sur-Quevillon QC J0Y 1X0",
    "addr:housenumber":"105",
    "addr:postcode":"j0y 1x0",
    "addr:street":"Rue Principale S Lebel-Sur-Quevillon",
    "iso:country":"CA",
    "sg:address":"105 Rue Principale S",
    "sg:city":"Lebel-Sur-Quevillon",
    "sg:classifiers":[
        {
            "category":"Bars & Pubs",
            "type":"Food & Drink"
        }
    ],
    "sg:phone":"+1 819 755 2550",
    "sg:postcode":"J0Y 1X0",
    "sg:province":"QC",
    "wof:name":"Taverne Des Sports",
    "wof:placetype":"venue"
},
  "geometry": {"coordinates":[-76.97891199999999,49.051792],"type":"Point"}
}