{
  "type": "Feature",
  "properties": {
    "iso:country":"CA",
    "sg:address":"11515 37A Ave NW",
    "sg:city":"Edmonton",
    "sg:classifiers":[
        {
            "category":"Shopping",
            "subcategory":"Pharmacy",
            "type":"Retail Goods"
        }
    ],
    "sg:phone":"+1 780 431 1013",
    "sg:postcode":"T6J 0J6",
    "sg:province":"AB",
    "sg:tags":[
        "aid",
        "first",
        "supply"
    ],
    "wof:name":"Fal & Assoc-Health & Safety",
    "wof:placetype":"venue"
},
  "geometry": {"coordinates":[-113.530181885,53.4724235535],"type":"Point"}
}