{
  "type": "Feature",
  "properties": {
    "addr:full":"1137 Princess St Kingston ON K7M 3E1",
    "addr:housenumber":"1137",
    "addr:postcode":"k7m 3e1",
    "addr:street":"Princess St",
    "iso:country":"CA",
    "sg:address":"1137 Princess St",
    "sg:city":"Kingston",
    "sg:classifiers":[
        {
            "category":"Retail",
            "subcategory":"Auto Repair",
            "type":"Services"
        }
    ],
    "sg:phone":"+1 613 549 3313",
    "sg:postcode":"K7M 3E1",
    "sg:province":"ON",
    "sg:tags":[
        "repairing",
        "automobile"
    ],
    "wof:name":"Midas Auto Svc Experts",
    "wof:placetype":"venue"
},
  "geometry": {"coordinates":[-76.520447,44.245483],"type":"Point"}
}