{
  "type": "Feature",
  "properties": {
    "addr:full":"8235 Av Mountain Sights Montreal QC H4P 2B4",
    "addr:housenumber":"8235",
    "addr:postcode":"h4p 2b4",
    "addr:street":"Av Mountain Sights",
    "iso:country":"CA",
    "sg:address":"8235 Av Mountain Sights",
    "sg:city":"Montreal",
    "sg:classifiers":[
        {
            "category":"Professional",
            "subcategory":"Management & Consulting",
            "type":"Services"
        }
    ],
    "sg:phone":"+1 514 733 8232",
    "sg:postcode":"H4P 2B4",
    "sg:province":"QC",
    "sg:tags":[
        "marketing",
        "consultant"
    ],
    "wof:name":"New Ventures",
    "wof:placetype":"venue"
},
  "geometry": {"coordinates":[-73.657913208,45.5005264282],"type":"Point"}
}