{
  "type": "Feature",
  "properties": {
    "addr:full":"Oka QC J0N 1E0",
    "addr:postcode":"j0n 1e0",
    "iso:country":"CA",
    "sg:city":"Oka",
    "sg:classifiers":[
        {
            "category":"Restaurant",
            "type":"Food & Drink"
        }
    ],
    "sg:phone":"+1 450 479 8787",
    "sg:postcode":"J0N 1E0",
    "sg:province":"QC",
    "wof:name":"Resto al Dente",
    "wof:placetype":"venue"
},
  "geometry": {"coordinates":[-74.02106499999999,45.498333],"type":"Point"}
}