{
  "type": "Feature",
  "properties": {
    "iso:country":"CA",
    "sg:city":"Burnaby",
    "sg:classifiers":[
        {
            "category":"Shopping",
            "type":"Retail Goods"
        }
    ],
    "sg:phone":"+1 604 421 2929",
    "sg:postcode":"V5A 3C2",
    "sg:province":"BC",
    "sg:tags":[
        "equipment",
        "beer",
        "supply"
    ],
    "wof:name":"Burnaby Brewing CO Ltd",
    "wof:placetype":"venue"
},
  "geometry": {"coordinates":[-122.92779541,49.2570114136],"type":"Point"}
}