{
  "type": "Feature",
  "properties": {
    "addr:full":"2432 Ch DE L'Eglise Sainte-Clotilde-DE-Chateauguay QC J0L 1W0",
    "addr:postcode":"2432;j0l 1w0",
    "addr:street":"Ch De L'Eglise Sainte-Clotilde-De-Chateauguay",
    "iso:country":"CA",
    "sg:address":"2432 Ch DE L'Eglise",
    "sg:city":"Sainte-Clotilde-DE-Chateauguay",
    "sg:classifiers":[
        {
            "category":"Retail",
            "subcategory":"Auto Repair",
            "type":"Services"
        }
    ],
    "sg:phone":"+1 450 826 4422",
    "sg:postcode":"J0L 1W0",
    "sg:province":"QC",
    "sg:tags":[
        "repairing",
        "automobile"
    ],
    "wof:name":"H Souliere & Fils Inc",
    "wof:placetype":"venue"
},
  "geometry": {"coordinates":[-73.543762,45.202499],"type":"Point"}
}