{
  "type": "Feature",
  "properties": {
    "addr:full":"180 Townsend Melita MB R0M 1L0",
    "addr:housenumber":"180",
    "addr:postcode":"r0m 1l0",
    "addr:street":"Townsend Melita",
    "iso:country":"CA",
    "sg:address":"180 Townsend",
    "sg:city":"Melita",
    "sg:classifiers":[
        {
            "category":"Arena",
            "subcategory":"Sports Club",
            "type":"Entertainment"
        }
    ],
    "sg:phone":"+1 204 522 8257",
    "sg:postcode":"R0M 1L0",
    "sg:province":"MB",
    "sg:tags":[
        "athletic",
        "fields",
        "stadium"
    ],
    "wof:name":"Melita & Area Arena",
    "wof:placetype":"venue"
},
  "geometry": {"coordinates":[-100.99518585200001,49.2677001953],"type":"Point"}
}