{
  "type": "Feature",
  "properties": {
    "addr:full":"1748 Pooles Rd Midhurst ON L0L 1X0",
    "addr:housenumber":"1748",
    "addr:postcode":"l0l 1x0",
    "addr:street":"Pooles Rd",
    "iso:country":"CA",
    "sg:address":"1748 Pooles Rd",
    "sg:city":"Midhurst",
    "sg:classifiers":[
        {
            "category":"Manufacturing",
            "subcategory":"Printing",
            "type":"Manufacturing & Wholesale Goods"
        }
    ],
    "sg:phone":"+1 705 734 0308",
    "sg:postcode":"L0L 1X0",
    "sg:province":"ON",
    "sg:tags":[
        "printer"
    ],
    "wof:name":"Annan & Sons Lithographing",
    "wof:placetype":"venue"
},
  "geometry": {"coordinates":[-79.69115447999999,44.4567260742],"type":"Point"}
}