{
  "type": "Feature",
  "properties": {
    "iso:country":"CA",
    "sg:address":"467 Rita St",
    "sg:city":"Winnipeg",
    "sg:classifiers":[
        {
            "category":"Building & Trades",
            "subcategory":"Construction",
            "type":"Services"
        }
    ],
    "sg:phone":"+1 204 889 4422",
    "sg:postcode":"R3J 2Y7",
    "sg:province":"MB",
    "sg:tags":[
        "resurfacing",
        "laying",
        "refinishing",
        "floor"
    ],
    "wof:name":"Emmanuels Flooring Ltd",
    "wof:placetype":"venue"
},
  "geometry": {"coordinates":[-97.2568206787,49.8846321106],"type":"Point"}
}