{
  "type": "Feature",
  "properties": {
    "addr:full":"105 Joy Rd Penticton BC V2A 8V6",
    "addr:housenumber":"105",
    "addr:postcode":"v2a 8v6",
    "addr:street":"Joy Rd",
    "iso:country":"CA",
    "sg:address":"105 Joy Rd",
    "sg:city":"Penticton",
    "sg:classifiers":[
        {
            "category":"Building & Trades",
            "subcategory":"Construction",
            "type":"Services"
        }
    ],
    "sg:phone":"+1 250 770 0214",
    "sg:postcode":"V2A 8V6",
    "sg:province":"BC",
    "sg:tags":[
        "plumbing",
        "contractor",
        "general"
    ],
    "wof:name":"Clem-N-Sons Enterprises",
    "wof:placetype":"venue"
},
  "geometry": {"coordinates":[-119.593857,49.500229],"type":"Point"}
}