{
  "type": "Feature",
  "properties": {
    "addr:full":"207 Sunbury Dr Fredericton Junction NB E5L 1R7",
    "addr:housenumber":"207",
    "addr:postcode":"e5l 1r7",
    "addr:street":"Sunbury Dr",
    "iso:country":"CA",
    "sg:address":"207 Sunbury Dr",
    "sg:city":"Fredericton Junction",
    "sg:classifiers":[
        {
            "category":"Restaurant",
            "type":"Food & Drink"
        }
    ],
    "sg:phone":"+1 506 368 2313",
    "sg:postcode":"E5L 1R7",
    "sg:province":"NB",
    "sg:tags":[
        "pizza"
    ],
    "wof:name":"Pizza Shack Fredericton Jct",
    "wof:placetype":"venue"
},
  "geometry": {"coordinates":[-66.615234,45.663689],"type":"Point"}
}