{
  "type": "Feature",
  "properties": {
    "addr:full":"136 Moore Ave S Waterloo ON N2J 1X5",
    "addr:housenumber":"136",
    "addr:postcode":"n2j 1x5",
    "addr:street":"Moore Ave S",
    "iso:country":"CA",
    "sg:address":"136 Moore Ave S",
    "sg:city":"Waterloo",
    "sg:classifiers":[
        {
            "category":"Building & Trades",
            "subcategory":"Landscaping Services",
            "type":"Services"
        }
    ],
    "sg:phone":"+1 519 579 8270",
    "sg:postcode":"N2J 1X5",
    "sg:province":"ON",
    "sg:tags":[
        "tree",
        "landscape",
        "contractor"
    ],
    "wof:name":"Jed's Tree Svc",
    "wof:placetype":"venue"
},
  "geometry": {"coordinates":[-80.510307,43.462666],"type":"Point"}
}