{
  "type": "Feature",
  "properties": {
    "addr:full":"Rosebud AB T0J 2T0",
    "addr:postcode":"t0j 2t0",
    "iso:country":"CA",
    "sg:city":"Rosebud",
    "sg:classifiers":[
        {
            "category":"Recreation",
            "type":"Entertainment"
        }
    ],
    "sg:phone":"+1 403 677 2006",
    "sg:postcode":"T0J 2T0",
    "sg:province":"AB",
    "sg:tags":[
        "center"
    ],
    "wof:name":"Rosebud Recreation Ctr",
    "wof:placetype":"venue"
},
  "geometry": {"coordinates":[-112.949455,51.29966],"type":"Point"}
}