{
  "type": "Feature",
  "properties": {
    "addr:full":"44 Line 9 S Hawkestone ON L0L 1T0",
    "addr:postcode":"l0l 1t0",
    "addr:street":"44 Line 9 S",
    "iso:country":"CA",
    "sg:address":"44 Line 9 S",
    "sg:city":"Hawkestone",
    "sg:classifiers":[
        {
            "category":"Retail",
            "subcategory":"Auto Repair",
            "type":"Services"
        }
    ],
    "sg:phone":"+1 705 487 5735",
    "sg:postcode":"L0L 1T0",
    "sg:province":"ON",
    "sg:tags":[
        "body",
        "automobile",
        "painting"
    ],
    "wof:name":"Tcb Autobody & Painting",
    "wof:placetype":"venue"
},
  "geometry": {"coordinates":[-79.467873,44.497467],"type":"Point"}
}