{
  "type": "Feature",
  "properties": {
    "iso:country":"CA",
    "sg:address":"1056 Little Britain Rd",
    "sg:city":"Little Britain",
    "sg:classifiers":[
        {
            "category":"Autos & Motor Vehicles",
            "subcategory":"Boat Sales",
            "type":"Retail Goods"
        }
    ],
    "sg:phone":"+1 705 786 3470",
    "sg:postcode":"K0M 2C0",
    "sg:province":"ON",
    "sg:tags":[
        "top",
        "upholstery",
        "cover"
    ],
    "wof:name":"Rainbow Yacht Tops & Uphlstry",
    "wof:placetype":"venue"
},
  "geometry": {"coordinates":[-78.8580245972,44.2857627869],"type":"Point"}
}