{
  "type": "Feature",
  "properties": {
    "iso:country":"CA",
    "sg:address":"3671 Rue Saint-Hubert",
    "sg:city":"Montreal",
    "sg:classifiers":[
        {
            "category":"Education",
            "subcategory":"School",
            "type":"Public Place"
        }
    ],
    "sg:phone":"+1 514 596 5578",
    "sg:postcode":"H2L 3Z9",
    "sg:province":"QC",
    "wof:name":"Regroupement 7",
    "wof:placetype":"venue"
},
  "geometry": {"coordinates":[-73.568649,45.520126],"type":"Point"}
}