{
  "type": "Feature",
  "properties": {
    "addr:full":"642 4E Rue E Amos QC J9T 1Z2",
    "addr:housenumber":"642",
    "addr:postcode":"j9t 1z2",
    "addr:street":"4E Rue E Amos",
    "iso:country":"CA",
    "sg:address":"642 4E Rue E",
    "sg:city":"Amos",
    "sg:classifiers":[
        {
            "category":"Food & Beverages",
            "subcategory":"Groceries & Convenience Stores",
            "type":"Retail Goods"
        }
    ],
    "sg:phone":"+1 819 727 1225",
    "sg:postcode":"J9T 1Z2",
    "sg:province":"QC",
    "wof:name":"Depanneur DE L'Est Enr",
    "wof:placetype":"venue"
},
  "geometry": {"coordinates":[-78.11103799999999,48.562431],"type":"Point"}
}