{
  "type": "Feature",
  "properties": {
    "iso:country":"CA",
    "sg:address":"681 Rue Jarry E",
    "sg:city":"Montreal",
    "sg:classifiers":[
        {
            "category":"Travel",
            "subcategory":"Travel Agent",
            "type":"Entertainment"
        }
    ],
    "sg:phone":"+1 514 277 1934",
    "sg:postcode":"H2P 1W1",
    "sg:province":"QC",
    "sg:tags":[
        "agency",
        "bureau"
    ],
    "wof:name":"Agence DE Voyages Svc Plus Inc",
    "wof:placetype":"venue"
},
  "geometry": {"coordinates":[-73.627563,45.545303],"type":"Point"}
}