{
  "type": "Feature",
  "properties": {
    "addr:full":"133 W 2nd Ave Qualicum Beach BC V9K 1T1",
    "addr:housenumber":"133",
    "addr:postcode":"v9k 1t1",
    "addr:street":"W 2Nd Ave",
    "iso:country":"CA",
    "sg:address":"133 W 2nd Ave",
    "sg:city":"Qualicum Beach",
    "sg:classifiers":[
        {
            "category":"Banks & Credit Unions",
            "subcategory":"Bank",
            "type":"Services"
        }
    ],
    "sg:phone":"+1 250 752 6981",
    "sg:postcode":"V9K 1T1",
    "sg:province":"BC",
    "wof:name":"Royal Bank Financial Group",
    "wof:placetype":"venue"
},
  "geometry": {"coordinates":[-124.445335388,49.347328186],"type":"Point"}
}