{
  "type": "Feature",
  "properties": {
    "addr:full":"140 Boul Greber Gatineau QC J8T 6H5",
    "addr:housenumber":"140",
    "addr:postcode":"j8t 6h5",
    "addr:street":"Boul Greber",
    "iso:country":"CA",
    "sg:address":"140 Boul Greber",
    "sg:city":"Gatineau",
    "sg:classifiers":[
        {
            "category":"Recreation",
            "type":"Entertainment"
        }
    ],
    "sg:phone":"+1 819 243 8498",
    "sg:postcode":"J8T 6H5",
    "sg:province":"QC",
    "sg:tags":[
        "bingo",
        "game"
    ],
    "wof:name":"Bingo Greber",
    "wof:placetype":"venue"
},
  "geometry": {"coordinates":[-75.7008895874,45.4689292908],"type":"Point"}
}