{
  "type": "Feature",
  "properties": {
    "addr:full":"Brampton ON L6V 1B4",
    "addr:postcode":"l6v 1b4",
    "iso:country":"CA",
    "sg:city":"Brampton",
    "sg:classifiers":[
        {
            "category":"Health Services",
            "subcategory":"Doctor",
            "type":"Services"
        }
    ],
    "sg:phone":"+1 905 456 5656",
    "sg:postcode":"L6V 1B4",
    "sg:province":"ON",
    "sg:tags":[
        "physician",
        "surgeon"
    ],
    "wof:name":"Bikangaga, Peter MD",
    "wof:placetype":"venue"
},
  "geometry": {"coordinates":[-79.7532958984,43.6923942566],"type":"Point"}
}