{
  "type": "Feature",
  "properties": {
    "addr:full":"5004 48 St Red Deer AB T4N 5K4",
    "addr:housenumber":"5004",
    "addr:postcode":"t4n 5k4",
    "addr:street":"48 St",
    "iso:country":"CA",
    "sg:address":"5004 48 St",
    "sg:city":"Red Deer",
    "sg:classifiers":[
        {
            "category":"Restaurant",
            "type":"Food & Drink"
        }
    ],
    "sg:phone":"+1 403 347 5320",
    "sg:postcode":"T4N 5K4",
    "sg:province":"AB",
    "wof:name":"Monsieur Wong's",
    "wof:placetype":"venue"
},
  "geometry": {"coordinates":[-113.816238403,52.2673301697],"type":"Point"}
}