{
  "type": "Feature",
  "properties": {
    "addr:full":"1940 Boul Henri-Bourassa E Montreal QC H2B 1S1",
    "addr:housenumber":"1940",
    "addr:postcode":"h2b 1s1",
    "addr:street":"Boul Henri-Bourassa E",
    "iso:country":"CA",
    "sg:address":"1940 Boul Henri-Bourassa E",
    "sg:city":"Montreal",
    "sg:classifiers":[
        {
            "category":"Professional",
            "subcategory":"Lawyer & Legal Services",
            "type":"Services"
        }
    ],
    "sg:phone":"+1 514 384 6100",
    "sg:postcode":"H2B 1S1",
    "sg:province":"QC",
    "sg:tags":[
        "attorney"
    ],
    "wof:name":"Fleurant, Jacques",
    "wof:placetype":"venue"
},
  "geometry": {"coordinates":[-73.65772200000001,45.571087],"type":"Point"}
}