{
  "type": "Feature",
  "properties": {
    "addr:full":"Gormley ON L0H 1G0",
    "addr:postcode":"l0h 1g0",
    "iso:country":"CA",
    "sg:city":"Gormley",
    "sg:classifiers":[
        {
            "category":"Building & Trades",
            "subcategory":"Construction",
            "type":"Services"
        }
    ],
    "sg:phone":"+1 905 887 9174",
    "sg:postcode":"L0H 1G0",
    "sg:province":"ON",
    "sg:tags":[
        "designer",
        "dealer",
        "pool",
        "swimming"
    ],
    "wof:name":"Custom Pools & Landscaping",
    "wof:placetype":"venue"
},
  "geometry": {"coordinates":[-79.3790054321,43.9433898926],"type":"Point"}
}