{
  "type": "Feature",
  "properties": {
    "addr:full":"1837 Romani Crt Mississauga ON L5T 1H7",
    "addr:housenumber":"1837",
    "addr:postcode":"l5t 1h7",
    "addr:street":"Romani Crt",
    "iso:country":"CA",
    "sg:address":"1837 Romani Crt",
    "sg:city":"Mississauga",
    "sg:classifiers":[
        {
            "category":"Wholesale",
            "subcategory":"Auto Parts",
            "type":"Manufacturing & Wholesale Goods"
        }
    ],
    "sg:phone":"+1 905 564 5600",
    "sg:postcode":"L5T 1H7",
    "sg:province":"ON",
    "sg:tags":[
        "repairing",
        "automobile",
        "wrecker",
        "wrecking"
    ],
    "wof:name":"Mississauga Auto Wreckers Ltd",
    "wof:placetype":"venue"
},
  "geometry": {"coordinates":[-79.64143371580001,43.6634674072],"type":"Point"}
}