{
  "type": "Feature",
  "properties": {
    "addr:full":"1338 Queen St W Toronto ON M6K 1L4",
    "addr:housenumber":"1338",
    "addr:postcode":"m6k 1l4",
    "addr:street":"Queen St W",
    "iso:country":"CA",
    "sg:address":"1338 Queen St W",
    "sg:city":"Toronto",
    "sg:classifiers":[
        {
            "category":"Shopping",
            "subcategory":"Jewelry",
            "type":"Retail Goods"
        }
    ],
    "sg:phone":"+1 416 463 2136",
    "sg:postcode":"M6K 1L4",
    "sg:province":"ON",
    "sg:tags":[
        "jeweler"
    ],
    "wof:name":"Made You Look",
    "wof:placetype":"venue"
},
  "geometry": {"coordinates":[-79.43195299999999,43.641685],"type":"Point"}
}