{
  "type": "Feature",
  "properties": {
    "addr:full":"PO Box 10 Irma AB T0B 2H0",
    "addr:housenumber":"po box 10",
    "addr:postcode":"t0b 2h0",
    "iso:country":"CA",
    "sg:address":"PO Box 10",
    "sg:city":"Irma",
    "sg:classifiers":[
        {
            "category":"Wholesale",
            "subcategory":"Farm Supplies",
            "type":"Manufacturing & Wholesale Goods"
        }
    ],
    "sg:phone":"+1 780 754 3859",
    "sg:postcode":"T0B 2H0",
    "sg:province":"AB",
    "sg:tags":[
        "livestock"
    ],
    "wof:name":"Fenton, Stuart",
    "wof:placetype":"venue"
},
  "geometry": {"coordinates":[-111.231995,52.911755],"type":"Point"}
}