{
  "type": "Feature",
  "properties": {
    "addr:full":"Iqaluit NU X0A 0H0",
    "addr:postcode":"x0a 0h0",
    "iso:country":"CA",
    "sg:city":"Iqaluit",
    "sg:classifiers":[
        {
            "category":"Government",
            "subcategory":"Office",
            "type":"Public Place"
        }
    ],
    "sg:phone":"+1 867 979 6714",
    "sg:postcode":"X0A 0H0",
    "sg:province":"NU",
    "wof:name":"Canada Excise Information",
    "wof:placetype":"venue"
},
  "geometry": {"coordinates":[-68.51902,63.751476],"type":"Point"}
}