{
  "type": "Feature",
  "properties": {
    "iso:country":"CA",
    "sg:address":"50 Rue DE Louvain O",
    "sg:city":"Montreal",
    "sg:classifiers":[
        {
            "category":"Wholesale",
            "subcategory":"Construction Materials",
            "type":"Manufacturing & Wholesale Goods"
        }
    ],
    "sg:phone":"+1 514 384 9362",
    "sg:postcode":"H2N 1B4",
    "sg:province":"QC",
    "sg:tags":[
        "product",
        "marble"
    ],
    "wof:name":"Carrara Marble Inc",
    "wof:placetype":"venue"
},
  "geometry": {"coordinates":[-73.655121,45.544434],"type":"Point"}
}