{
  "type": "Feature",
  "properties": {
    "iso:country":"CA",
    "sg:city":"Abbotsford",
    "sg:classifiers":[
        {
            "category":"Professional",
            "subcategory":"Lawyer & Legal Services",
            "type":"Services"
        }
    ],
    "sg:phone":"+1 604 504 7710",
    "sg:postcode":"V2T 3L3",
    "sg:province":"BC",
    "sg:tags":[
        "attorney"
    ],
    "wof:name":"Malloch, Doug",
    "wof:placetype":"venue"
},
  "geometry": {"coordinates":[-122.330963135,49.0509262085],"type":"Point"}
}