{
  "type": "Feature",
  "properties": {
    "addr:full":"3887 Rue Saint-Mathieu Laval QC H7P 1A9",
    "addr:housenumber":"3887",
    "addr:postcode":"h7p 1a9",
    "addr:street":"Rue Saint-Mathieu",
    "iso:country":"CA",
    "sg:address":"3887 Rue Saint-Mathieu",
    "sg:city":"Laval",
    "sg:classifiers":[
        {
            "category":"Building & Trades",
            "subcategory":"Plumbing",
            "type":"Services"
        }
    ],
    "sg:phone":"+1 450 628 5060",
    "sg:postcode":"H7P 1A9",
    "sg:province":"QC",
    "sg:tags":[
        "heating",
        "contractor"
    ],
    "wof:name":"Hydro Combustion Inc",
    "wof:placetype":"venue"
},
  "geometry": {"coordinates":[-73.829247,45.580471],"type":"Point"}
}