{
  "type": "Feature",
  "properties": {
    "iso:country":"CA",
    "sg:address":"6600 Ch Saint-Francois",
    "sg:city":"Saint-Laurent",
    "sg:classifiers":[
        {
            "category":"Freight",
            "type":"Transportation"
        }
    ],
    "sg:phone":"+1 514 856 7500",
    "sg:postcode":"H4S 1B7",
    "sg:province":"QC",
    "sg:tags":[
        "trucking"
    ],
    "wof:name":"Trans Force Inc",
    "wof:placetype":"venue"
},
  "geometry": {"coordinates":[-73.744003,45.483067],"type":"Point"}
}