{
  "type": "Feature",
  "properties": {
    "addr:full":"Quebec QC G1J 1A7",
    "addr:postcode":"g1j 1a7",
    "iso:country":"CA",
    "sg:city":"Quebec",
    "sg:classifiers":[
        {
            "category":"Organizations",
            "subcategory":"Professional Association",
            "type":"Services"
        }
    ],
    "sg:phone":"+1 418 660 8403",
    "sg:postcode":"G1J 1A7",
    "sg:province":"QC",
    "wof:name":"Evasion St-Pie X Inc",
    "wof:placetype":"venue"
},
  "geometry": {"coordinates":[-71.23369599999999,46.847927],"type":"Point"}
}