{
  "type": "Feature",
  "properties": {
    "iso:country":"CA",
    "sg:address":"3550 Derry Rd E",
    "sg:city":"Mississauga",
    "sg:classifiers":[
        {
            "category":"Restaurant",
            "type":"Food & Drink"
        }
    ],
    "sg:phone":"+1 905 673 1278",
    "sg:postcode":"L4T 3V7",
    "sg:province":"ON",
    "sg:tags":[
        "caterer",
        "rooms",
        "banquet"
    ],
    "wof:name":"Verdi Hospitality Ctr",
    "wof:placetype":"venue"
},
  "geometry": {"coordinates":[-79.63014221189999,43.7146110535],"type":"Point"}
}