{
  "type": "Feature",
  "properties": {
    "addr:full":"1122 Rue Sauve E Montreal QC H2C 1Z7",
    "addr:housenumber":"1122",
    "addr:postcode":"h2c 1z7",
    "addr:street":"Rue Sauve E",
    "iso:country":"CA",
    "sg:address":"1122 Rue Sauve E",
    "sg:city":"Montreal",
    "sg:classifiers":[
        {
            "category":"Personal",
            "subcategory":"Beauty Salon",
            "type":"Services"
        }
    ],
    "sg:phone":"+1 514 381 4301",
    "sg:postcode":"H2C 1Z7",
    "sg:province":"QC",
    "wof:name":"Coiffure 1122 Enr",
    "wof:placetype":"venue"
},
  "geometry": {"coordinates":[-73.6525421143,45.5567550659],"type":"Point"}
}