{
  "type": "Feature",
  "properties": {
    "addr:full":"Bentley AB T0C 0J0",
    "addr:postcode":"t0c 0j0",
    "iso:country":"CA",
    "sg:city":"Bentley",
    "sg:classifiers":[
        {
            "category":"Building & Trades",
            "subcategory":"Equipment Rental",
            "type":"Services"
        }
    ],
    "sg:phone":"+1 403 748 3740",
    "sg:postcode":"T0C 0J0",
    "sg:province":"AB",
    "sg:tags":[
        "player",
        "recorder",
        "video"
    ],
    "wof:name":"Bentley Video Rentals",
    "wof:placetype":"venue"
},
  "geometry": {"coordinates":[-114.047668,52.464828],"type":"Point"}
}