{
  "type": "Feature",
  "properties": {
    "iso:country":"CA",
    "sg:address":"1910 St Laurent Blvd",
    "sg:city":"Ottawa",
    "sg:classifiers":[
        {
            "category":"Organizations",
            "subcategory":"Religious Organization",
            "type":"Services"
        }
    ],
    "sg:phone":"+1 613 731 5350",
    "sg:postcode":"K1G 1A4",
    "sg:province":"ON",
    "sg:tags":[
        "church"
    ],
    "wof:name":"Calvary United Pentecostal Ch",
    "wof:placetype":"venue"
},
  "geometry": {"coordinates":[-75.62404632569999,45.4000587463],"type":"Point"}
}