{
  "type": "Feature",
  "properties": {
    "addr:full":"11 Bowhill Cres North York ON M2J 3S1",
    "addr:housenumber":"11",
    "addr:postcode":"m2j 3s1",
    "addr:street":"Bowhill Cres",
    "iso:country":"CA",
    "sg:address":"11 Bowhill Cres",
    "sg:city":"North York",
    "sg:classifiers":[
        {
            "category":"Manufacturing",
            "subcategory":"Rubber & Plastics",
            "type":"Manufacturing & Wholesale Goods"
        }
    ],
    "sg:phone":"+1 416 491 2446",
    "sg:postcode":"M2J 3S1",
    "sg:province":"ON",
    "wof:name":"Eko Rubber Inc",
    "wof:placetype":"venue"
},
  "geometry": {"coordinates":[-79.33015399999999,43.786011],"type":"Point"}
}