{
  "type": "Feature",
  "properties": {
    "addr:full":"2600 Broadway E Vancouver BC V5M 1Y5",
    "addr:housenumber":"2600",
    "addr:postcode":"v5m 1y5",
    "addr:street":"Broadway E",
    "iso:country":"CA",
    "sg:address":"2600 Broadway E",
    "sg:city":"Vancouver",
    "sg:classifiers":[
        {
            "category":"Education",
            "subcategory":"School",
            "type":"Public Place"
        }
    ],
    "sg:phone":"+1 604 713 8215",
    "sg:postcode":"V5M 1Y5",
    "sg:province":"BC",
    "wof:name":"Vancouver Technical Secondary",
    "wof:placetype":"venue"
},
  "geometry": {"coordinates":[-123.051895,49.261814],"type":"Point"}
}