{
  "type": "Feature",
  "properties": {
    "iso:country":"CA",
    "sg:address":"Cribbons Point Wharf",
    "sg:city":"Aspen",
    "sg:classifiers":[
        {
            "category":"Restaurant",
            "type":"Food & Drink"
        }
    ],
    "sg:phone":"+1 902 863 0279",
    "sg:postcode":"B0H 1E0",
    "sg:province":"NS",
    "wof:name":"Boyd's Seafood Gallery",
    "wof:placetype":"venue"
},
  "geometry": {"coordinates":[-62.0522537231,45.3009681702],"type":"Point"}
}