{
  "type": "Feature",
  "properties": {
    "addr:full":"Red Deer AB T4P 2T4",
    "addr:postcode":"t4p 2t4",
    "iso:country":"CA",
    "sg:city":"Red Deer",
    "sg:classifiers":[
        {
            "category":"Professional",
            "subcategory":"Research",
            "type":"Services"
        }
    ],
    "sg:phone":"+1 403 342 2673",
    "sg:postcode":"T4P 2T4",
    "sg:province":"AB",
    "sg:tags":[
        "laboratory"
    ],
    "wof:name":"Core Laboratories Canada Ltd",
    "wof:placetype":"venue"
},
  "geometry": {"coordinates":[-113.80897521999999,52.3120307922],"type":"Point"}
}