{
  "type": "Feature",
  "properties": {
    "addr:full":"395 Ch Ouellette Cleveland QC J0B 2H0",
    "addr:housenumber":"395",
    "addr:postcode":"j0b 2h0",
    "addr:street":"Ch Ouellette",
    "iso:country":"CA",
    "sg:address":"395 Ch Ouellette",
    "sg:city":"Cleveland",
    "sg:classifiers":[
        {
            "category":"Building & Trades",
            "subcategory":"Construction",
            "type":"Services"
        }
    ],
    "sg:phone":"+1 819 826 3956",
    "sg:postcode":"J0B 2H0",
    "sg:province":"QC",
    "sg:tags":[
        "excavating",
        "contractor"
    ],
    "wof:name":"Pavage Richmond Inc",
    "wof:placetype":"venue"
},
  "geometry": {"coordinates":[-72.134056,45.673832],"type":"Point"}
}