{
  "type": "Feature",
  "properties": {
    "iso:country":"CA",
    "sg:address":"870 Simcoe St N",
    "sg:city":"Oshawa",
    "sg:classifiers":[
        {
            "category":"Building & Trades",
            "subcategory":"Cleaning & Sanitation",
            "type":"Services"
        }
    ],
    "sg:phone":"+1 905 434 7276",
    "sg:postcode":"L1G 4V8",
    "sg:province":"ON",
    "sg:tags":[
        "snow",
        "removal"
    ],
    "wof:name":"Snow Patrol Equipment",
    "wof:placetype":"venue"
},
  "geometry": {"coordinates":[-78.8736038208,43.9203720093],"type":"Point"}
}