{
  "type": "Feature",
  "properties": {
    "iso:country":"CA",
    "sg:address":"11860 Rue Depatie",
    "sg:city":"Montreal",
    "sg:classifiers":[
        {
            "category":"Shopping",
            "subcategory":"Stationery & Office Supplies",
            "type":"Retail Goods"
        }
    ],
    "sg:phone":"+1 514 334 7418",
    "sg:postcode":"H4J 1W5",
    "sg:province":"QC",
    "sg:tags":[
        "map"
    ],
    "wof:name":"Cartes Anciennes Ptolemee Plus",
    "wof:placetype":"venue"
},
  "geometry": {"coordinates":[-73.7031707764,45.5316925049],"type":"Point"}
}