{
  "type": "Feature",
  "properties": {
    "addr:full":"Inglis MB R0J 0X0",
    "addr:postcode":"r0j 0x0",
    "iso:country":"CA",
    "sg:city":"Inglis",
    "sg:classifiers":[
        {
            "category":"Government",
            "subcategory":"Office",
            "type":"Public Place"
        }
    ],
    "sg:phone":"+1 204 564 2473",
    "sg:postcode":"R0J 0X0",
    "sg:province":"MB",
    "wof:name":"Manitoba Campground Office",
    "wof:placetype":"venue"
},
  "geometry": {"coordinates":[-101.25147200000001,50.948357],"type":"Point"}
}