{
  "type": "Feature",
  "properties": {
    "addr:full":"Merritt BC V1K 1C4",
    "addr:postcode":"v1k 1c4",
    "iso:country":"CA",
    "sg:city":"Merritt",
    "sg:classifiers":[
        {
            "category":"Autos & Motor Vehicles",
            "subcategory":"Fuel & Gas Station",
            "type":"Retail Goods"
        }
    ],
    "sg:phone":"+1 250 378 4525",
    "sg:postcode":"V1K 1C4",
    "sg:province":"BC",
    "sg:tags":[
        "oil"
    ],
    "wof:name":"Shell Canada Ltd",
    "wof:placetype":"venue"
},
  "geometry": {"coordinates":[-120.76364100000001,50.123463],"type":"Point"}
}