{
  "type": "Feature",
  "properties": {
    "addr:full":"17720 56 Ave Surrey BC V3S 1C7",
    "addr:housenumber":"17720",
    "addr:postcode":"v3s 1c7",
    "addr:street":"56 Ave",
    "iso:country":"CA",
    "sg:address":"17720 56 Ave",
    "sg:city":"Surrey",
    "sg:classifiers":[
        {
            "category":"Restaurant",
            "type":"Food & Drink"
        }
    ],
    "sg:phone":"+1 604 576 4811",
    "sg:postcode":"V3S 1C7",
    "sg:province":"BC",
    "sg:tags":[
        "parlor",
        "ice",
        "cream"
    ],
    "wof:name":"Dairy Queen",
    "wof:placetype":"venue"
},
  "geometry": {"coordinates":[-122.731826782,49.1040229797],"type":"Point"}
}