{
  "type": "Feature",
  "properties": {
    "addr:full":"3445 Gardner Crt Burnaby BC V5G 3K8",
    "addr:housenumber":"3445",
    "addr:postcode":"v5g 3k8",
    "addr:street":"Gardner Crt",
    "iso:country":"CA",
    "sg:address":"3445 Gardner Crt",
    "sg:city":"Burnaby",
    "sg:classifiers":[
        {
            "category":"Wholesale",
            "subcategory":"Groceries",
            "type":"Manufacturing & Wholesale Goods"
        }
    ],
    "sg:phone":"+1 604 291 7700",
    "sg:postcode":"V5G 3K8",
    "sg:province":"BC",
    "sg:tags":[
        "grocer"
    ],
    "wof:name":"Toyo Importing CO Ltd",
    "wof:placetype":"venue"
},
  "geometry": {"coordinates":[-122.996689,49.253181],"type":"Point"}
}