{
  "type": "Feature",
  "properties": {
    "addr:full":"312 Ch Val D'Amour Atholville NB E3N 4E2",
    "addr:housenumber":"312",
    "addr:postcode":"e3n 4e2",
    "addr:street":"Ch Val D'Amour Atholville",
    "iso:country":"CA",
    "sg:address":"312 Ch Val D'Amour",
    "sg:city":"Atholville",
    "sg:classifiers":[
        {
            "category":"Shopping",
            "subcategory":"Pharmacy",
            "type":"Retail Goods"
        }
    ],
    "sg:phone":"+1 506 753 7678",
    "sg:postcode":"E3N 4E2",
    "sg:province":"NB",
    "wof:name":"Shoppers Drug Mart",
    "wof:placetype":"venue"
},
  "geometry": {"coordinates":[-66.714119,47.99308],"type":"Point"}
}