{
  "type": "Feature",
  "properties": {
    "addr:full":"Montreal QC H2Y 2A4",
    "addr:postcode":"h2y 2a4",
    "iso:country":"CA",
    "sg:city":"Montreal",
    "sg:classifiers":[
        {
            "category":"Professional",
            "subcategory":"Art Services",
            "type":"Services"
        }
    ],
    "sg:phone":"+1 514 845 9555",
    "sg:postcode":"H2Y 2A4",
    "sg:province":"QC",
    "sg:tags":[
        "graphic",
        "designer"
    ],
    "wof:name":"Studio Michael Fog Inc",
    "wof:placetype":"venue"
},
  "geometry": {"coordinates":[-73.554359436,45.5123100281],"type":"Point"}
}