{
  "type": "Feature",
  "properties": {
    "addr:full":"Abbotsford BC V2T 4V6",
    "addr:postcode":"v2t 4v6",
    "iso:country":"CA",
    "sg:city":"Abbotsford",
    "sg:classifiers":[
        {
            "category":"Wholesale",
            "subcategory":"Hardware",
            "type":"Manufacturing & Wholesale Goods"
        }
    ],
    "sg:phone":"+1 604 850 1186",
    "sg:postcode":"V2T 4V6",
    "sg:province":"BC",
    "sg:tags":[
        "water",
        "cooler",
        "fountain",
        "filter"
    ],
    "wof:name":"Wiebe's Natural Steam Distill",
    "wof:placetype":"venue"
},
  "geometry": {"coordinates":[-122.316596985,49.0564117432],"type":"Point"}
}