{
  "type": "Feature",
  "properties": {
    "iso:country":"CA",
    "sg:address":"80 Whitfield Trites Rd",
    "sg:city":"Moncton",
    "sg:classifiers":[
        {
            "category":"Manufacturing",
            "subcategory":"Petroleum Products",
            "type":"Manufacturing & Wholesale Goods"
        }
    ],
    "sg:phone":"+1 506 384 1484",
    "sg:postcode":"E1G 3H1",
    "sg:province":"NB",
    "sg:tags":[
        "oil",
        "septic"
    ],
    "wof:name":"A-1 Septic Tank Ltd",
    "wof:placetype":"venue"
},
  "geometry": {"coordinates":[-64.90204620359999,46.1390609741],"type":"Point"}
}