{
  "type": "Feature",
  "properties": {
    "addr:full":"Prevost QC J0R 1T0",
    "addr:postcode":"j0r 1t0",
    "addr:street":"Prevost",
    "iso:country":"CA",
    "sg:city":"Prevost",
    "sg:classifiers":[
        {
            "category":"Personal",
            "subcategory":"Beauty Salon",
            "type":"Services"
        }
    ],
    "sg:phone":"+1 450 224 2331",
    "sg:postcode":"J0R 1T0",
    "sg:province":"QC",
    "wof:name":"Francine Novash Estheticienne",
    "wof:placetype":"venue"
},
  "geometry": {"coordinates":[-74.0699462891,45.8589859009],"type":"Point"}
}