{
  "type": "Feature",
  "properties": {
    "addr:full":"2990 Rue DE LA Faune Loretteville QC G2A 1H8",
    "addr:housenumber":"2990",
    "addr:postcode":"g2a 1h8",
    "addr:street":"Rue De La Faune",
    "iso:country":"CA",
    "sg:address":"2990 Rue DE LA Faune",
    "sg:city":"Loretteville",
    "sg:classifiers":[
        {
            "category":"Professional",
            "subcategory":"Lawyer & Legal Services",
            "type":"Services"
        }
    ],
    "sg:phone":"+1 418 842 7448",
    "sg:postcode":"G2A 1H8",
    "sg:province":"QC",
    "sg:tags":[
        "attorney"
    ],
    "wof:name":"Simoneau, Susan",
    "wof:placetype":"venue"
},
  "geometry": {"coordinates":[-71.364487,46.858658],"type":"Point"}
}