{
  "type": "Feature",
  "properties": {
    "addr:full":"755 Av Du Mont-Royal E Montreal QC H2J 1W8",
    "addr:housenumber":"755",
    "addr:postcode":"h2j 1w8",
    "addr:street":"Av Du Mont-Royal E",
    "iso:country":"CA",
    "sg:address":"755 Av Du Mont-Royal E",
    "sg:city":"Montreal",
    "sg:classifiers":[
        {
            "category":"Health Services",
            "subcategory":"Hospital",
            "type":"Services"
        }
    ],
    "sg:phone":"+1 514 525 0504",
    "sg:postcode":"H2J 1W8",
    "sg:province":"QC",
    "sg:tags":[
        "mental"
    ],
    "wof:name":"Suivi Communautaire Le Fil",
    "wof:placetype":"venue"
},
  "geometry": {"coordinates":[-73.581413269,45.5256843567],"type":"Point"}
}