{
  "type": "Feature",
  "properties": {
    "iso:country":"CA",
    "sg:address":"675 the Parkway",
    "sg:city":"Peterborough",
    "sg:classifiers":[
        {
            "category":"Manufacturing",
            "subcategory":"Rubber & Plastics",
            "type":"Manufacturing & Wholesale Goods"
        }
    ],
    "sg:phone":"+1 705 743 5361",
    "sg:postcode":"K9J 7K2",
    "sg:province":"ON",
    "sg:tags":[
        "mold",
        "maker"
    ],
    "wof:name":"Harco Enterprises Ltd",
    "wof:placetype":"venue"
},
  "geometry": {"coordinates":[-78.341156,44.27599],"type":"Point"}
}