{
  "type": "Feature",
  "properties": {
    "iso:country":"CA",
    "sg:address":"106 Rue Church",
    "sg:city":"Cowansville",
    "sg:classifiers":[
        {
            "category":"Professional",
            "subcategory":"Business Services",
            "type":"Services"
        }
    ],
    "sg:phone":"+1 450 263 8909",
    "sg:postcode":"J2K 1T8",
    "sg:province":"QC",
    "sg:tags":[
        "appraiser"
    ],
    "wof:name":"Evaluation Yamaska Enr",
    "wof:placetype":"venue"
},
  "geometry": {"coordinates":[-72.74639892579999,45.2036705017],"type":"Point"}
}