{
  "type": "Feature",
  "properties": {
    "addr:full":"743 Gerrard St E Toronto ON M4M 1Y5",
    "addr:housenumber":"743",
    "addr:postcode":"m4m 1y5",
    "addr:street":"Gerrard St E",
    "iso:country":"CA",
    "sg:address":"743 Gerrard St E",
    "sg:city":"Toronto",
    "sg:classifiers":[
        {
            "category":"Shopping",
            "type":"Retail Goods"
        }
    ],
    "sg:phone":"+1 416 466 9975",
    "sg:postcode":"M4M 1Y5",
    "sg:province":"ON",
    "sg:tags":[
        "monument"
    ],
    "wof:name":"Yorkshire Monument CO",
    "wof:placetype":"venue"
},
  "geometry": {"coordinates":[-79.347443,43.666431],"type":"Point"}
}