{
  "type": "Feature",
  "properties": {
    "iso:country":"CA",
    "sg:address":"10 Windsor Ave",
    "sg:city":"Leamington",
    "sg:classifiers":[
        {
            "category":"Wholesale",
            "subcategory":"Machinery & Supplies",
            "type":"Manufacturing & Wholesale Goods"
        }
    ],
    "sg:phone":"+1 519 326 4496",
    "sg:postcode":"N8H 3W3",
    "sg:province":"ON",
    "sg:tags":[
        "pump",
        "electric",
        "motor"
    ],
    "wof:name":"L J Fleming Ltd",
    "wof:placetype":"venue"
},
  "geometry": {"coordinates":[-82.5997161865,42.0541534424],"type":"Point"}
}