{
  "type": "Feature",
  "properties": {
    "addr:full":"4865 L Heureux Contrecoeur QC J0L 1C0",
    "addr:housenumber":"4865 l",
    "addr:postcode":"j0l 1c0",
    "addr:street":"Heureux",
    "iso:country":"CA",
    "sg:address":"4865 L Heureux",
    "sg:city":"Contrecoeur",
    "sg:classifiers":[
        {
            "category":"Sports & Exercise",
            "subcategory":"Bowling",
            "type":"Entertainment"
        }
    ],
    "sg:phone":"+1 450 587 2377",
    "sg:postcode":"J0L 1C0",
    "sg:province":"QC",
    "sg:tags":[
        "center"
    ],
    "wof:name":"Centre DE Quilles DE Contr Inc",
    "wof:placetype":"venue"
},
  "geometry": {"coordinates":[-73.23709100000001,45.854668],"type":"Point"}
}