{
  "type": "Feature",
  "properties": {
    "addr:full":"10805 95 St NW Edmonton AB T5H 2E2",
    "addr:housenumber":"10805",
    "addr:postcode":"t5h 2e2",
    "addr:street":"95 St Nw",
    "iso:country":"CA",
    "sg:address":"10805 95 St NW",
    "sg:city":"Edmonton",
    "sg:classifiers":[
        {
            "category":"Retail",
            "subcategory":"Repair Shop",
            "type":"Services"
        }
    ],
    "sg:phone":"+1 780 422 0367",
    "sg:postcode":"T5H 2E2",
    "sg:province":"AB",
    "sg:tags":[
        "equipment",
        "video"
    ],
    "wof:name":"Superior Tv Sales Ltd",
    "wof:placetype":"venue"
},
  "geometry": {"coordinates":[-113.483940124,53.5549545288],"type":"Point"}
}