{
  "type": "Feature",
  "properties": {
    "addr:full":"2080 Queen St E Toronto ON M4E 1E1",
    "addr:housenumber":"2080",
    "addr:postcode":"m4e 1e1",
    "addr:street":"Queen St E",
    "iso:country":"CA",
    "sg:address":"2080 Queen St E",
    "sg:city":"Toronto",
    "sg:classifiers":[
        {
            "category":"Banks & Credit Unions",
            "subcategory":"Bank",
            "type":"Services"
        }
    ],
    "sg:phone":"+1 416 693 3939",
    "sg:postcode":"M4E 1E1",
    "sg:province":"ON",
    "wof:name":"Scotiabank",
    "wof:placetype":"venue"
},
  "geometry": {"coordinates":[-79.296448,43.670914],"type":"Point"}
}