{
  "type": "Feature",
  "properties": {
    "addr:full":"275 3rd St E Fox Valley SK S0N 0V0",
    "addr:housenumber":"275",
    "addr:postcode":"s0n 0v0",
    "addr:street":"3Rd St E Fox",
    "iso:country":"CA",
    "sg:address":"275 3rd St E",
    "sg:city":"Fox Valley",
    "sg:classifiers":[
        {
            "category":"Recreation",
            "type":"Entertainment"
        }
    ],
    "sg:phone":"+1 306 666 2152",
    "sg:postcode":"S0N 0V0",
    "sg:province":"SK",
    "sg:tags":[
        "pool",
        "swimming"
    ],
    "wof:name":"Fox Valley Swimming Pool",
    "wof:placetype":"venue"
},
  "geometry": {"coordinates":[-109.47869900000001,50.465923],"type":"Point"}
}