{
  "type": "Feature",
  "properties": {
    "addr:full":"Ottawa ON K1G 3V4",
    "addr:postcode":"k1g 3v4",
    "iso:country":"CA",
    "sg:city":"Ottawa",
    "sg:classifiers":[
        {
            "category":"Professional",
            "subcategory":"Lawyer & Legal Services",
            "type":"Services"
        }
    ],
    "sg:phone":"+1 613 523 0307",
    "sg:postcode":"K1G 3V4",
    "sg:province":"ON",
    "sg:tags":[
        "attorney"
    ],
    "wof:name":"Laveaux, Frank",
    "wof:placetype":"venue"
},
  "geometry": {"coordinates":[-75.626633,45.405602],"type":"Point"}
}