{
  "type": "Feature",
  "properties": {
    "addr:full":"13 Mission Ave St Albert AB T8N 1H6",
    "addr:housenumber":"13",
    "addr:postcode":"t8n 1h6",
    "addr:street":"Mission Ave",
    "iso:country":"CA",
    "sg:address":"13 Mission Ave",
    "sg:city":"St Albert",
    "sg:classifiers":[
        {
            "category":"Insurance",
            "subcategory":"Insurance Agent",
            "type":"Services"
        }
    ],
    "sg:phone":"+1 780 458 7600",
    "sg:postcode":"T8N 1H6",
    "sg:province":"AB",
    "sg:tags":[
        "adjuster"
    ],
    "wof:name":"Asi Alternative Solutions",
    "wof:placetype":"venue"
},
  "geometry": {"coordinates":[-113.62915802000001,53.6353874207],"type":"Point"}
}