{
  "type": "Feature",
  "properties": {
    "addr:full":"48998 Yale Rd Chilliwack BC V2P 6H4",
    "addr:housenumber":"48998",
    "addr:postcode":"v2p 6h4",
    "addr:street":"Yale Rd",
    "iso:country":"CA",
    "sg:address":"48998 Yale Rd",
    "sg:city":"Chilliwack",
    "sg:classifiers":[
        {
            "category":"Retail",
            "subcategory":"Auto Repair",
            "type":"Services"
        }
    ],
    "sg:phone":"+1 604 794 7789",
    "sg:postcode":"V2P 6H4",
    "sg:province":"BC",
    "sg:tags":[
        "glass",
        "coating",
        "tinting"
    ],
    "wof:name":"Sunstop Window Tinting",
    "wof:placetype":"venue"
},
  "geometry": {"coordinates":[-121.869041443,49.1763076782],"type":"Point"}
}