{
  "type": "Feature",
  "properties": {
    "addr:full":"65 Forty Second St Markham ON L3P 7K3",
    "addr:housenumber":"65",
    "addr:postcode":"l3p 7k3",
    "addr:street":"Forty Second St",
    "iso:country":"CA",
    "sg:address":"65 Forty Second St",
    "sg:city":"Markham",
    "sg:classifiers":[
        {
            "category":"Professional",
            "subcategory":"Computer Services",
            "type":"Services"
        }
    ],
    "sg:phone":"+1 905 479 6727",
    "sg:postcode":"L3P 7K3",
    "sg:province":"ON",
    "sg:tags":[
        "consultant"
    ],
    "wof:name":"4Gl Solutions",
    "wof:placetype":"venue"
},
  "geometry": {"coordinates":[-79.29740099999999,43.879894],"type":"Point"}
}