{
  "type": "Feature",
  "properties": {
    "iso:country":"CA",
    "sg:address":"3680 Rue Fleury E",
    "sg:city":"Montreal-Nord",
    "sg:classifiers":[
        {
            "category":"Wholesale",
            "subcategory":"Meat",
            "type":"Manufacturing & Wholesale Goods"
        }
    ],
    "sg:phone":"+1 514 852 5975",
    "sg:postcode":"H1H 2S6",
    "sg:province":"QC",
    "sg:tags":[
        "butchering"
    ],
    "wof:name":"Boucherie-Boulangerie al-Hilal",
    "wof:placetype":"venue"
},
  "geometry": {"coordinates":[-73.638237,45.583214],"type":"Point"}
}