{
  "type": "Feature",
  "properties": {
    "addr:full":"2840 Boul Talbot Chicoutimi QC G7H 5B1",
    "addr:housenumber":"2840",
    "addr:postcode":"g7h 5b1",
    "addr:street":"Boul Talbot",
    "iso:country":"CA",
    "sg:address":"2840 Boul Talbot",
    "sg:city":"Chicoutimi",
    "sg:classifiers":[
        {
            "category":"Professional",
            "subcategory":"Business Services",
            "type":"Services"
        }
    ],
    "sg:phone":"+1 418 549 4410",
    "sg:postcode":"G7H 5B1",
    "sg:province":"QC",
    "sg:tags":[
        "establishment",
        "leasing"
    ],
    "wof:name":"Equipement Carluc Inc",
    "wof:placetype":"venue"
},
  "geometry": {"coordinates":[-71.0888671875,48.3777236938],"type":"Point"}
}