{
  "type": "Feature",
  "properties": {
    "addr:full":"2 Cann St Yarmouth NS B5A 2R6",
    "addr:housenumber":"2",
    "addr:postcode":"b5a 2r6",
    "addr:street":"Cann St",
    "iso:country":"CA",
    "sg:address":"2 Cann St",
    "sg:city":"Yarmouth",
    "sg:classifiers":[
        {
            "category":"Restaurant",
            "type":"Food & Drink"
        }
    ],
    "sg:phone":"+1 902 742 7702",
    "sg:postcode":"B5A 2R6",
    "sg:province":"NS",
    "wof:name":"Snack Place",
    "wof:placetype":"venue"
},
  "geometry": {"coordinates":[-66.115517,43.849842],"type":"Point"}
}