{
  "type": "Feature",
  "properties": {
    "addr:full":"16 Strathcona St Happy Valley-Goose Bay NL A0P 1E0",
    "addr:housenumber":"16",
    "addr:postcode":"a0p 1e0",
    "addr:street":"Strathcona St",
    "iso:country":"CA",
    "sg:address":"16 Strathcona St",
    "sg:city":"Happy Valley-Goose Bay",
    "sg:classifiers":[
        {
            "category":"Education",
            "subcategory":"School",
            "type":"Public Place"
        }
    ],
    "sg:phone":"+1 709 896 2431",
    "sg:postcode":"A0P 1E0",
    "sg:province":"NL",
    "wof:name":"Labrador School Board",
    "wof:placetype":"venue"
},
  "geometry": {"coordinates":[-60.3043136597,53.2965393066],"type":"Point"}
}