{
  "type": "Feature",
  "properties": {
    "iso:country":"CA",
    "sg:address":"380 Rue Saint-Paul",
    "sg:city":"Le Gardeur",
    "sg:classifiers":[
        {
            "category":"Building & Trades",
            "subcategory":"Plumbing",
            "type":"Services"
        }
    ],
    "sg:phone":"+1 450 581 4844",
    "sg:postcode":"J5Z 4H9",
    "sg:province":"QC",
    "sg:tags":[
        "septic"
    ],
    "wof:name":"Nettoyeur D'Egouts Jm Boucher",
    "wof:placetype":"venue"
},
  "geometry": {"coordinates":[-73.485153,45.759556],"type":"Point"}
}