{
  "type": "Feature",
  "properties": {
    "addr:full":"Saulnierville NS B0W 2Z0",
    "addr:postcode":"b0w 2z0",
    "iso:country":"CA",
    "sg:city":"Saulnierville",
    "sg:classifiers":[
        {
            "category":"Personal",
            "subcategory":"Hair Removal",
            "type":"Services"
        }
    ],
    "sg:phone":"+1 902 769 3249",
    "sg:postcode":"B0W 2Z0",
    "sg:province":"NS",
    "sg:tags":[
        "removing"
    ],
    "wof:name":"Laser Hair Professionals Ltd",
    "wof:placetype":"venue"
},
  "geometry": {"coordinates":[-66.1291885376,44.254650116],"type":"Point"}
}