{
  "type": "Feature",
  "properties": {
    "iso:country":"CA",
    "sg:address":"24 Ross",
    "sg:city":"Pictou",
    "sg:classifiers":[
        {
            "category":"Personal",
            "type":"Services"
        }
    ],
    "sg:phone":"+1 902 485 9622",
    "sg:postcode":"B0K 1H0",
    "sg:province":"NS",
    "sg:tags":[
        "program",
        "physical",
        "exercise",
        "fitness"
    ],
    "wof:name":"Pictou County Ymca/Ywca",
    "wof:placetype":"venue"
},
  "geometry": {"coordinates":[-62.7016105652,45.6795043945],"type":"Point"}
}