{
  "type": "Feature",
  "properties": {
    "addr:full":"PO Box 266 Nestor Falls ON P0X 1K0",
    "addr:housenumber":"po",
    "addr:postcode":"p0x 1k0",
    "addr:street":"Box 266",
    "iso:country":"CA",
    "sg:address":"PO Box 266",
    "sg:city":"Nestor Falls",
    "sg:classifiers":[
        {
            "category":"Travel",
            "subcategory":"Hotels & Motels",
            "type":"Entertainment"
        }
    ],
    "sg:phone":"+1 807 484 2664",
    "sg:postcode":"P0X 1K0",
    "sg:province":"ON",
    "sg:tags":[
        "resort"
    ],
    "wof:name":"Tinker's Places Ltd",
    "wof:placetype":"venue"
},
  "geometry": {"coordinates":[-93.946129,49.196758],"type":"Point"}
}