{
  "type": "Feature",
  "properties": {
    "addr:full":"590 Rue Labonte Sainte-Agathe-Des-Monts QC J8C 2Z2",
    "addr:housenumber":"590",
    "addr:postcode":"j8c 2z2",
    "addr:street":"Rue Labonte",
    "iso:country":"CA",
    "sg:address":"590 Rue Labonte",
    "sg:city":"Sainte-Agathe-Des-Monts",
    "sg:classifiers":[
        {
            "category":"Building & Trades",
            "subcategory":"Landscaping Services",
            "type":"Services"
        }
    ],
    "sg:phone":"+1 819 323 4334",
    "sg:postcode":"J8C 2Z2",
    "sg:province":"QC",
    "sg:tags":[
        "landscape",
        "contractor"
    ],
    "wof:name":"Enterprises P Roy",
    "wof:placetype":"venue"
},
  "geometry": {"coordinates":[-74.2607040405,46.0435791016],"type":"Point"}
}