{
  "type": "Feature",
  "properties": {
    "addr:full":"34981 Lougheed Hwy Mission BC V2V 6T1",
    "addr:housenumber":"34981",
    "addr:postcode":"v2v 6t1",
    "addr:street":"Lougheed Hwy",
    "iso:country":"CA",
    "sg:address":"34981 Lougheed Hwy",
    "sg:city":"Mission",
    "sg:classifiers":[
        {
            "category":"Autos & Motor Vehicles",
            "subcategory":"Fuel & Gas Station",
            "type":"Retail Goods"
        }
    ],
    "sg:phone":"+1 604 826 6421",
    "sg:postcode":"V2V 6T1",
    "sg:province":"BC",
    "sg:tags":[
        "oil"
    ],
    "wof:name":"Hatzic Shell",
    "wof:placetype":"venue"
},
  "geometry": {"coordinates":[-122.255852,49.149658],"type":"Point"}
}