{
  "type": "Feature",
  "properties": {
    "addr:full":"208 St David St Lindsay ON K9V 4Z4",
    "addr:housenumber":"208",
    "addr:postcode":"k9v 4z4",
    "addr:street":"St David St",
    "iso:country":"CA",
    "sg:address":"208 St David St",
    "sg:city":"Lindsay",
    "sg:classifiers":[
        {
            "category":"Farming",
            "subcategory":"Farm & Veterinary Services",
            "type":"Manufacturing & Wholesale Goods"
        }
    ],
    "sg:phone":"+1 705 328 1648",
    "sg:postcode":"K9V 4Z4",
    "sg:province":"ON",
    "wof:name":"Canadian Seed Laboratories Ltd",
    "wof:placetype":"venue"
},
  "geometry": {"coordinates":[-78.7320861816,44.3728408813],"type":"Point"}
}