{
  "type": "Feature",
  "properties": {
    "addr:full":"90 Stinson St Hamilton ON L8N 1S2",
    "addr:housenumber":"90",
    "addr:postcode":"l8n 1s2",
    "addr:street":"Stinson St",
    "iso:country":"CA",
    "sg:address":"90 Stinson St",
    "sg:city":"Hamilton",
    "sg:classifiers":[
        {
            "category":"Social Services",
            "type":"Services"
        }
    ],
    "sg:phone":"+1 905 308 8401",
    "sg:postcode":"L8N 1S2",
    "sg:province":"ON",
    "sg:tags":[
        "organization",
        "welfare"
    ],
    "wof:name":"Emmenuel House",
    "wof:placetype":"venue"
},
  "geometry": {"coordinates":[-79.85730743409999,43.2486038208],"type":"Point"}
}