{
  "type": "Feature",
  "properties": {
    "addr:full":"414 Baxter St Whitehorse YT Y1A 2T5",
    "addr:housenumber":"414",
    "addr:postcode":"y1a 2t5",
    "addr:street":"Baxter St",
    "iso:country":"CA",
    "sg:address":"414 Baxter St",
    "sg:city":"Whitehorse",
    "sg:classifiers":[
        {
            "category":"Home & Garden",
            "subcategory":"Hardware",
            "type":"Retail Goods"
        }
    ],
    "sg:phone":"+1 867 668 6068",
    "sg:postcode":"Y1A 2T5",
    "sg:province":"YT",
    "sg:tags":[
        "building",
        "material"
    ],
    "wof:name":"Builders Supply",
    "wof:placetype":"venue"
},
  "geometry": {"coordinates":[-135.06655883799999,60.7276535034],"type":"Point"}
}