{
  "type": "Feature",
  "properties": {
    "addr:full":"North York ON M9L 1Z8",
    "addr:postcode":"m9l 1z8",
    "iso:country":"CA",
    "sg:city":"North York",
    "sg:classifiers":[
        {
            "category":"Autos & Motor Vehicles",
            "subcategory":"Automobile Sales",
            "type":"Retail Goods"
        }
    ],
    "sg:phone":"+1 416 740 7878",
    "sg:postcode":"M9L 1Z8",
    "sg:province":"ON",
    "sg:tags":[
        "car",
        "dealer"
    ],
    "wof:name":"Lawrence Auto Sales",
    "wof:placetype":"venue"
},
  "geometry": {"coordinates":[-79.5633926392,43.7576370239],"type":"Point"}
}