{
  "type": "Feature",
  "properties": {
    "addr:full":"6727 Chippawa Rd S Wellandport ON L0R 2J0",
    "addr:housenumber":"6727",
    "addr:postcode":"l0r 2j0",
    "addr:street":"Chippawa Rd",
    "iso:country":"CA",
    "sg:address":"6727 Chippawa Rd S",
    "sg:city":"Wellandport",
    "sg:classifiers":[
        {
            "category":"Education",
            "subcategory":"School",
            "type":"Public Place"
        }
    ],
    "sg:phone":"+1 905 386 6203",
    "sg:postcode":"L0R 2J0",
    "sg:province":"ON",
    "wof:name":"Robert Land Academy",
    "wof:placetype":"venue"
},
  "geometry": {"coordinates":[-79.47817230219999,43.004573822],"type":"Point"}
}