{
  "type": "Feature",
  "properties": {
    "addr:full":"5849 University Ave Halifax NS B3H 1W2",
    "addr:housenumber":"5849",
    "addr:postcode":"b3h 1w2",
    "addr:street":"University Ave",
    "iso:country":"CA",
    "sg:address":"5849 University Ave",
    "sg:city":"Halifax",
    "sg:classifiers":[
        {
            "category":"Professional",
            "subcategory":"Research",
            "type":"Services"
        }
    ],
    "sg:phone":"+1 902 494 6491",
    "sg:postcode":"B3H 1W2",
    "sg:province":"NS",
    "sg:tags":[
        "development",
        "laboratory"
    ],
    "wof:name":"Atlantic Research Ctr",
    "wof:placetype":"venue"
},
  "geometry": {"coordinates":[-63.583187,44.639015],"type":"Point"}
}