{
  "type": "Feature",
  "properties": {
    "iso:country":"CA",
    "sg:address":"65 Palace St",
    "sg:city":"Brantford",
    "sg:classifiers":[
        {
            "category":"Professional",
            "type":"Services"
        }
    ],
    "sg:phone":"+1 519 758 0374",
    "sg:postcode":"N3T 3W8",
    "sg:province":"ON",
    "sg:tags":[
        "arts",
        "brush",
        "air"
    ],
    "wof:name":"Crazy Chameleon Artistic Prod",
    "wof:placetype":"venue"
},
  "geometry": {"coordinates":[-80.268471,43.144844],"type":"Point"}
}