{
  "type": "Feature",
  "properties": {
    "addr:full":"High Level AB T0H 1Z0",
    "addr:postcode":"t0h 1z0",
    "iso:country":"CA",
    "sg:city":"High Level",
    "sg:classifiers":[
        {
            "category":"Shopping",
            "subcategory":"Pharmacy",
            "type":"Retail Goods"
        }
    ],
    "sg:phone":"+1 780 926 3516",
    "sg:postcode":"T0H 1Z0",
    "sg:province":"AB",
    "wof:name":"High Level Valu-Drugs Ltd",
    "wof:placetype":"venue"
},
  "geometry": {"coordinates":[-117.135414123,58.5197982788],"type":"Point"}
}