{
  "type": "Feature",
  "properties": {
    "addr:full":"Calgary AB T2S 2S5",
    "addr:postcode":"t2s 2s5",
    "iso:country":"CA",
    "sg:city":"Calgary",
    "sg:classifiers":[
        {
            "category":"Real Estate",
            "subcategory":"Developer",
            "type":"Services"
        }
    ],
    "sg:phone":"+1 403 228 9261",
    "sg:postcode":"T2S 2S5",
    "sg:province":"AB",
    "sg:tags":[
        "company",
        "land"
    ],
    "wof:name":"Jason Corp",
    "wof:placetype":"venue"
},
  "geometry": {"coordinates":[-114.071411,51.036865],"type":"Point"}
}