{
  "type": "Feature",
  "properties": {
    "addr:full":"17360 Yonge St Newmarket ON L3Y 7R6",
    "addr:housenumber":"17360",
    "addr:postcode":"l3y 7r6",
    "addr:street":"Yonge St",
    "iso:country":"CA",
    "sg:address":"17360 Yonge St",
    "sg:city":"Newmarket",
    "sg:classifiers":[
        {
            "category":"Wholesale",
            "subcategory":"Office Equipment",
            "type":"Manufacturing & Wholesale Goods"
        }
    ],
    "sg:phone":"+1 905 895 2700",
    "sg:postcode":"L3Y 7R6",
    "sg:province":"ON",
    "sg:tags":[
        "register",
        "cash",
        "supply"
    ],
    "wof:name":"J L Ribbons & Rolls",
    "wof:placetype":"venue"
},
  "geometry": {"coordinates":[-79.4797821045,44.0515556335],"type":"Point"}
}