{
  "type": "Feature",
  "properties": {
    "addr:full":"669 Baron Canyon Rd Pembroke ON K8A 6W7",
    "addr:housenumber":"669",
    "addr:postcode":"k8a 6w7",
    "addr:street":"Baron Canyon Rd",
    "iso:country":"CA",
    "sg:address":"669 Baron Canyon Rd",
    "sg:city":"Pembroke",
    "sg:classifiers":[
        {
            "category":"Government",
            "subcategory":"Office",
            "type":"Public Place"
        }
    ],
    "sg:phone":"+1 613 735 2432",
    "sg:postcode":"K8A 6W7",
    "sg:province":"ON",
    "sg:tags":[
        "organization",
        "protection",
        "animal",
        "village"
    ],
    "wof:name":"Animal Control Svc",
    "wof:placetype":"venue"
},
  "geometry": {"coordinates":[-77.1122131348,45.8264808655],"type":"Point"}
}