{
  "type": "Feature",
  "properties": {
    "addr:full":"8 Fourth Line W Sault Ste Marie ON P6A 5K8",
    "addr:housenumber":"8",
    "addr:postcode":"p6a 5k8",
    "addr:street":"Fourth Line W",
    "iso:country":"CA",
    "sg:address":"8 Fourth Line W",
    "sg:city":"Sault Ste Marie",
    "sg:classifiers":[
        {
            "category":"Education",
            "subcategory":"School",
            "type":"Public Place"
        }
    ],
    "sg:phone":"+1 705 945 7118",
    "sg:postcode":"P6A 5K8",
    "sg:province":"ON",
    "wof:name":"Greenwood Elementary School",
    "wof:placetype":"venue"
},
  "geometry": {"coordinates":[-84.3531417847,46.5668296814],"type":"Point"}
}