{
  "type": "Feature",
  "properties": {
    "iso:country":"CA",
    "sg:address":"315 1st Ave E",
    "sg:city":"Regina",
    "sg:classifiers":[
        {
            "category":"Manufacturing",
            "subcategory":"Metals",
            "type":"Manufacturing & Wholesale Goods"
        }
    ],
    "sg:phone":"+1 306 721 6677",
    "sg:postcode":"S4N 4Z3",
    "sg:province":"SK",
    "sg:tags":[
        "scrap",
        "iron"
    ],
    "wof:name":"Inland Steel Products Inc",
    "wof:placetype":"venue"
},
  "geometry": {"coordinates":[-104.57860565199999,50.4673995972],"type":"Point"}
}