{
  "type": "Feature",
  "properties": {
    "addr:full":"Red Deer AB T4N 1X9",
    "addr:postcode":"t4n 1x9",
    "iso:country":"CA",
    "sg:city":"Red Deer",
    "sg:classifiers":[
        {
            "category":"Health Services",
            "subcategory":"Chiropractor",
            "type":"Services"
        }
    ],
    "sg:phone":"+1 403 346 4700",
    "sg:postcode":"T4N 1X9",
    "sg:province":"AB",
    "wof:name":"Smith, R Lyle DC",
    "wof:placetype":"venue"
},
  "geometry": {"coordinates":[-113.812828064,52.2688903809],"type":"Point"}
}