{
  "type": "Feature",
  "properties": {
    "addr:full":"202 6th Ave E Watrous SK S0K 4T0",
    "addr:housenumber":"202",
    "addr:postcode":"s0k 4t0",
    "addr:street":"6Th Ave E Watrous",
    "iso:country":"CA",
    "sg:address":"202 6th Ave E",
    "sg:city":"Watrous",
    "sg:classifiers":[
        {
            "category":"Education",
            "subcategory":"School",
            "type":"Public Place"
        }
    ],
    "sg:phone":"+1 306 946 3309",
    "sg:postcode":"S0K 4T0",
    "sg:province":"SK",
    "wof:name":"Watrous High School",
    "wof:placetype":"venue"
},
  "geometry": {"coordinates":[-105.46383667000001,51.675983429],"type":"Point"}
}