{
  "type": "Feature",
  "properties": {
    "addr:full":"Saint-Paul QC J0K 3E0",
    "addr:postcode":"j0k 3e0",
    "iso:country":"CA",
    "sg:city":"Saint-Paul",
    "sg:classifiers":[
        {
            "category":"Autos & Motor Vehicles",
            "subcategory":"Recreational Vehicle Sales",
            "type":"Retail Goods"
        }
    ],
    "sg:phone":"+1 450 756 1029",
    "sg:postcode":"J0K 3E0",
    "sg:province":"QC",
    "wof:name":"Roulottes Rg Gagnon Inc",
    "wof:placetype":"venue"
},
  "geometry": {"coordinates":[-73.4455566406,45.9850387573],"type":"Point"}
}