{
  "type": "Feature",
  "properties": {
    "iso:country":"CA",
    "sg:address":"4190 Finch Ave E # Ll7",
    "sg:city":"Scarborough",
    "sg:classifiers":[
        {
            "category":"Health Services",
            "subcategory":"Doctor",
            "type":"Services"
        }
    ],
    "sg:phone":"+1 416 292 0084",
    "sg:postcode":"M1S 4T7",
    "sg:province":"ON",
    "sg:tags":[
        "physician",
        "surgeon"
    ],
    "wof:name":"Alvarez, Carlos MD",
    "wof:placetype":"venue"
},
  "geometry": {"coordinates":[-79.2870635986,43.8037338257],"type":"Point"}
}