{
  "type": "Feature",
  "properties": {
    "addr:full":"1656 Rue Sherbrooke E Montreal QC H2L 1M5",
    "addr:housenumber":"1656",
    "addr:postcode":"h2l 1m5",
    "addr:street":"Rue Sherbrooke E",
    "iso:country":"CA",
    "sg:address":"1656 Rue Sherbrooke E",
    "sg:city":"Montreal",
    "sg:classifiers":[
        {
            "category":"Health Services",
            "subcategory":"Doctor",
            "type":"Services"
        }
    ],
    "sg:phone":"+1 514 527 2417",
    "sg:postcode":"H2L 1M5",
    "sg:province":"QC",
    "sg:tags":[
        "clinic",
        "cosmetic",
        "surgery"
    ],
    "wof:name":"Institut DE Chirurgie Esthtq",
    "wof:placetype":"venue"
},
  "geometry": {"coordinates":[-73.56395721440001,45.5273208618],"type":"Point"}
}