{
  "type": "Feature",
  "properties": {
    "addr:full":"4252 Madeley Rd North Vancouver BC V7N 4C9",
    "addr:postcode":"4252;v7n 4c9",
    "addr:street":"Madeley Rd",
    "iso:country":"CA",
    "sg:address":"4252 Madeley Rd",
    "sg:city":"North Vancouver",
    "sg:classifiers":[
        {
            "category":"Professional",
            "subcategory":"Management & Consulting",
            "type":"Services"
        }
    ],
    "sg:phone":"+1 604 983 2794",
    "sg:postcode":"V7N 4C9",
    "sg:province":"BC",
    "sg:tags":[
        "marketing",
        "program",
        "counselor",
        "public",
        "relations"
    ],
    "wof:name":"New Rave Productions",
    "wof:placetype":"venue"
},
  "geometry": {"coordinates":[-123.077698,49.348396],"type":"Point"}
}