{
  "type": "Feature",
  "properties": {
    "iso:country":"CA",
    "sg:address":"1 Goreham St",
    "sg:city":"Liverpool",
    "sg:classifiers":[
        {
            "category":"Government",
            "subcategory":"Jail",
            "type":"Public Place"
        }
    ],
    "sg:phone":"+1 902 354 5532",
    "sg:postcode":"B0T 1K0",
    "sg:province":"NS",
    "sg:tags":[
        "provincial",
        "institution"
    ],
    "wof:name":"Nova Scotia Comm Corrections",
    "wof:placetype":"venue"
},
  "geometry": {"coordinates":[-64.72068023680001,44.0357627869],"type":"Point"}
}