{
  "type": "Feature",
  "properties": {
    "addr:full":"2016 Ogilvie Rd # 18 Gloucester ON K1J 7N9",
    "addr:housenumber":"2016;18",
    "addr:postcode":"k1j 7n9",
    "addr:street":"Ogilvie Rd #",
    "iso:country":"CA",
    "sg:address":"2016 Ogilvie Rd # 18",
    "sg:city":"Gloucester",
    "sg:classifiers":[
        {
            "category":"Shopping",
            "subcategory":"Pharmacy",
            "type":"Retail Goods"
        }
    ],
    "sg:phone":"+1 613 741 5151",
    "sg:postcode":"K1J 7N9",
    "sg:province":"ON",
    "sg:tags":[
        "grocer"
    ],
    "wof:name":"Shoppers Drug Mart",
    "wof:placetype":"venue"
},
  "geometry": {"coordinates":[-75.604004,45.437069],"type":"Point"}
}