{
  "type": "Feature",
  "properties": {
    "iso:country":"CA",
    "sg:address":"4211 Vanguard Rd",
    "sg:city":"Richmond",
    "sg:classifiers":[
        {
            "category":"Building & Trades",
            "subcategory":"Construction",
            "type":"Services"
        }
    ],
    "sg:phone":"+1 604 279 0402",
    "sg:postcode":"V6X 2P6",
    "sg:province":"BC",
    "sg:tags":[
        "railing"
    ],
    "wof:name":"Creative Woodworking Inc",
    "wof:placetype":"venue"
},
  "geometry": {"coordinates":[-123.101074219,49.1818237305],"type":"Point"}
}