{
  "type": "Feature",
  "properties": {
    "addr:full":"3645 Rue Principale Saint-Jean-Baptiste QC J0L 2B0",
    "addr:housenumber":"3645",
    "addr:postcode":"j0l 2b0",
    "addr:street":"Rue Principale",
    "iso:country":"CA",
    "sg:address":"3645 Rue Principale",
    "sg:city":"Saint-Jean-Baptiste",
    "sg:classifiers":[
        {
            "category":"Professional",
            "subcategory":"Research",
            "type":"Services"
        }
    ],
    "sg:phone":"+1 450 446 2660",
    "sg:postcode":"J0L 2B0",
    "sg:province":"QC",
    "sg:tags":[
        "development",
        "laboratory"
    ],
    "wof:name":"Wisent Inc",
    "wof:placetype":"venue"
},
  "geometry": {"coordinates":[-73.13329299999999,45.513649],"type":"Point"}
}