{
  "type": "Feature",
  "properties": {
    "iso:country":"CA",
    "sg:address":"65 Brock Ave",
    "sg:city":"Toronto",
    "sg:classifiers":[
        {
            "category":"Food & Beverages",
            "subcategory":"Liquor & Beverages",
            "type":"Retail Goods"
        }
    ],
    "sg:phone":"+1 416 532 5702",
    "sg:postcode":"M6K 2L3",
    "sg:province":"ON",
    "sg:tags":[
        "beer",
        "ale"
    ],
    "wof:name":"Beer Store",
    "wof:placetype":"venue"
},
  "geometry": {"coordinates":[-79.4331741333,43.6440162659],"type":"Point"}
}