{
  "type": "Feature",
  "properties": {
    "addr:full":"Petersburg ON N0B 2H0",
    "addr:postcode":"n0b 2h0",
    "iso:country":"CA",
    "sg:city":"Petersburg",
    "sg:classifiers":[
        {
            "category":"Building & Trades",
            "subcategory":"Construction",
            "type":"Services"
        }
    ],
    "sg:phone":"+1 519 634 5152",
    "sg:postcode":"N0B 2H0",
    "sg:province":"ON",
    "sg:tags":[
        "silo"
    ],
    "wof:name":"Kitchener Silo CO Ltd",
    "wof:placetype":"venue"
},
  "geometry": {"coordinates":[-80.606956,43.413097],"type":"Point"}
}