{
  "type": "Feature",
  "properties": {
    "addr:full":"366 Wilson Ave North York ON M3H 1S9",
    "addr:housenumber":"366",
    "addr:postcode":"m3h 1s9",
    "addr:street":"Wilson Ave",
    "iso:country":"CA",
    "sg:address":"366 Wilson Ave",
    "sg:city":"North York",
    "sg:classifiers":[
        {
            "category":"Retail",
            "subcategory":"Laundry & Dry Cleaning",
            "type":"Services"
        }
    ],
    "sg:phone":"+1 416 636 4529",
    "sg:postcode":"M3H 1S9",
    "sg:province":"ON",
    "sg:tags":[
        "cleaners"
    ],
    "wof:name":"Dixie Cleaners",
    "wof:placetype":"venue"
},
  "geometry": {"coordinates":[-79.438782,43.736546],"type":"Point"}
}