{
  "type": "Feature",
  "properties": {
    "addr:full":"Mississauga ON L5L 4L9",
    "addr:postcode":"l5l 4l9",
    "iso:country":"CA",
    "sg:city":"Mississauga",
    "sg:classifiers":[
        {
            "category":"Banks & Credit Unions",
            "subcategory":"Investment Brokerage",
            "type":"Services"
        }
    ],
    "sg:phone":"+1 905 607 7981",
    "sg:postcode":"L5L 4L9",
    "sg:province":"ON",
    "sg:tags":[
        "consultant",
        "planning",
        "financial"
    ],
    "wof:name":"Assante Capital Management",
    "wof:placetype":"venue"
},
  "geometry": {"coordinates":[-79.6719665527,43.5343780518],"type":"Point"}
}