{
  "type": "Feature",
  "properties": {
    "addr:full":"121 2nd St NW Dauphin MB R7N 1G6",
    "addr:housenumber":"121",
    "addr:postcode":"dauphin;r7n 1g6",
    "addr:street":"2Nd St Nw",
    "iso:country":"CA",
    "sg:address":"121 2nd St NW",
    "sg:city":"Dauphin",
    "sg:classifiers":[
        {
            "category":"Government",
            "subcategory":"Fire Station",
            "type":"Public Place"
        }
    ],
    "sg:phone":"+1 ",
    "sg:postcode":"R7N 1G6",
    "sg:province":"MB",
    "sg:tags":[
        "department"
    ],
    "wof:name":"Dauphin Fire Dept",
    "wof:placetype":"venue"
},
  "geometry": {"coordinates":[-100.05305481000001,51.1522331238],"type":"Point"}
}