{
  "type": "Feature",
  "properties": {
    "addr:full":"5399 Eglinton Ave W Etobicoke ON M9C 5K6",
    "addr:housenumber":"5399",
    "addr:postcode":"m9c 5k6",
    "addr:street":"Eglinton Ave W",
    "iso:country":"CA",
    "sg:address":"5399 Eglinton Ave W",
    "sg:city":"Etobicoke",
    "sg:classifiers":[
        {
            "category":"Shopping",
            "subcategory":"Hobbies, Toys, & Games",
            "type":"Retail Goods"
        }
    ],
    "sg:phone":"+1 416 620 9191",
    "sg:postcode":"M9C 5K6",
    "sg:province":"ON",
    "wof:name":"Discovery Toys Canada",
    "wof:placetype":"venue"
},
  "geometry": {"coordinates":[-79.58974499999999,43.663609],"type":"Point"}
}