{
  "type": "Feature",
  "properties": {
    "addr:full":"455 36 St NE Calgary AB T2A 6K3",
    "addr:housenumber":"36",
    "addr:postcode":"t2a 6k3",
    "addr:street":"455;St Ne",
    "iso:country":"CA",
    "sg:address":"455 36 St NE",
    "sg:city":"Calgary",
    "sg:classifiers":[
        {
            "category":"Banks & Credit Unions",
            "subcategory":"Bank",
            "type":"Services"
        }
    ],
    "sg:phone":"+1 403 272 8821",
    "sg:postcode":"T2A 6K3",
    "sg:province":"AB",
    "wof:name":"First Calgary Savings Cu",
    "wof:placetype":"venue"
},
  "geometry": {"coordinates":[-113.982201,51.055454],"type":"Point"}
}