{
  "type": "Feature",
  "properties": {
    "addr:full":"Woodbridge ON L4L 1H8",
    "addr:postcode":"l4l 1h8",
    "iso:country":"CA",
    "sg:city":"Woodbridge",
    "sg:classifiers":[
        {
            "category":"Retail",
            "subcategory":"Laundry & Dry Cleaning",
            "type":"Services"
        }
    ],
    "sg:phone":"+1 905 851 2552",
    "sg:postcode":"L4L 1H8",
    "sg:province":"ON",
    "sg:tags":[
        "cleaners"
    ],
    "wof:name":"Woodbridge Cleaners",
    "wof:placetype":"venue"
},
  "geometry": {"coordinates":[-79.5832366943,43.7820587158],"type":"Point"}
}