{
  "type": "Feature",
  "properties": {
    "addr:full":"Bay Roberts NL A0A 1G0",
    "addr:postcode":"a0a 1g0",
    "iso:country":"CA",
    "sg:city":"Bay Roberts",
    "sg:classifiers":[
        {
            "category":"Health Services",
            "subcategory":"Doctor",
            "type":"Services"
        }
    ],
    "sg:phone":"+1 709 786 3380",
    "sg:postcode":"A0A 1G0",
    "sg:province":"NL",
    "sg:tags":[
        "physician",
        "surgeon"
    ],
    "wof:name":"Shandera, R H MD",
    "wof:placetype":"venue"
},
  "geometry": {"coordinates":[-53.2815093994,47.583984375],"type":"Point"}
}