{
  "type": "Feature",
  "properties": {
    "iso:country":"CA",
    "sg:city":"Thunder Bay",
    "sg:classifiers":[
        {
            "category":"Building & Trades",
            "subcategory":"Landscaping Services",
            "type":"Services"
        }
    ],
    "sg:phone":"+1 807 473 9695",
    "sg:postcode":"P7C 5N5",
    "sg:province":"ON",
    "sg:tags":[
        "tree"
    ],
    "wof:name":"Oliver Creek Tree Specialists",
    "wof:placetype":"venue"
},
  "geometry": {"coordinates":[-89.4159164429,48.4136123657],"type":"Point"}
}