{
  "type": "Feature",
  "properties": {
    "addr:full":"48 Seal Rd Thompson MB R8N 1S4",
    "addr:housenumber":"48",
    "addr:postcode":"r8n 1s4",
    "addr:street":"Seal Rd",
    "iso:country":"CA",
    "sg:address":"48 Seal Rd",
    "sg:city":"Thompson",
    "sg:classifiers":[
        {
            "category":"Wholesale",
            "subcategory":"Hardware",
            "type":"Manufacturing & Wholesale Goods"
        }
    ],
    "sg:phone":"+1 204 677 4595",
    "sg:postcode":"R8N 1S4",
    "sg:province":"MB",
    "sg:tags":[
        "plumbing",
        "fixture",
        "supply"
    ],
    "wof:name":"B A Robinson CO Ltd",
    "wof:placetype":"venue"
},
  "geometry": {"coordinates":[-97.87042236329999,55.7264976501],"type":"Point"}
}