{
  "type": "Feature",
  "properties": {
    "addr:full":"30 Woodbison Ave Fort Smith NT X0E 0P0",
    "addr:housenumber":"30",
    "addr:postcode":"x0e 0p0",
    "addr:street":"Woodbison Ave",
    "iso:country":"CA",
    "sg:address":"30 Woodbison Ave",
    "sg:city":"Fort Smith",
    "sg:classifiers":[
        {
            "category":"Organizations",
            "subcategory":"Religious Organization",
            "type":"Services"
        }
    ],
    "sg:phone":"+1 867 872 5628",
    "sg:postcode":"X0E 0P0",
    "sg:province":"NT",
    "sg:tags":[
        "church"
    ],
    "wof:name":"Pentecostal Salt",
    "wof:placetype":"venue"
},
  "geometry": {"coordinates":[-111.90263400000001,60.000095],"type":"Point"}
}