{
  "type": "Feature",
  "properties": {
    "addr:full":"2441 Lakeshore Rd W Oakville ON L6L 5V5",
    "addr:housenumber":"2441",
    "addr:postcode":"l6l 5v5",
    "addr:street":"Lakeshore Rd W",
    "iso:country":"CA",
    "sg:address":"2441 Lakeshore Rd W",
    "sg:city":"Oakville",
    "sg:classifiers":[
        {
            "category":"Retail",
            "subcategory":"Laundry & Dry Cleaning",
            "type":"Services"
        }
    ],
    "sg:phone":"+1 905 827 7675",
    "sg:postcode":"L6L 5V5",
    "sg:province":"ON",
    "sg:tags":[
        "cleaners"
    ],
    "wof:name":"Smarter Dry Cleaners",
    "wof:placetype":"venue"
},
  "geometry": {"coordinates":[-79.711555,43.394775],"type":"Point"}
}