{
  "type": "Feature",
  "properties": {
    "addr:full":"Westmount QC H3Z 3B9",
    "addr:postcode":"h3z 3b9",
    "iso:country":"CA",
    "sg:city":"Westmount",
    "sg:classifiers":[
        {
            "category":"Professional",
            "subcategory":"Lawyer & Legal Services",
            "type":"Services"
        }
    ],
    "sg:phone":"+1 514 667 5086",
    "sg:postcode":"H3Z 3B9",
    "sg:province":"QC",
    "sg:tags":[
        "attorney"
    ],
    "wof:name":"Bernier, Jean L",
    "wof:placetype":"venue"
},
  "geometry": {"coordinates":[-73.60189800000001,45.47591],"type":"Point"}
}