{
  "type": "Feature",
  "properties": {
    "iso:country":"CA",
    "sg:address":"60 Meg Dr #2",
    "sg:city":"London",
    "sg:classifiers":[
        {
            "category":"Wholesale",
            "subcategory":"Machinery & Supplies",
            "type":"Manufacturing & Wholesale Goods"
        }
    ],
    "sg:phone":"+1 519 681 9445",
    "sg:postcode":"N6E 3T6",
    "sg:province":"ON",
    "sg:tags":[
        "tool"
    ],
    "wof:name":"Agent Industrial Supply",
    "wof:placetype":"venue"
},
  "geometry": {"coordinates":[-81.231171,42.922947],"type":"Point"}
}