{
  "type": "Feature",
  "properties": {
    "addr:full":"609 Church St Port Hawkesbury NS B9A 2X4",
    "addr:housenumber":"609",
    "addr:postcode":"b9a 2x4",
    "addr:street":"Church St",
    "iso:country":"CA",
    "sg:address":"609 Church St",
    "sg:city":"Port Hawkesbury",
    "sg:classifiers":[
        {
            "category":"Organizations",
            "subcategory":"Professional Association",
            "type":"Services"
        }
    ],
    "sg:phone":"+1 902 625 3800",
    "sg:postcode":"B9A 2X4",
    "sg:province":"NS",
    "wof:name":"Nova Scotia Landowners",
    "wof:placetype":"venue"
},
  "geometry": {"coordinates":[-61.349495,45.612835],"type":"Point"}
}