{
  "type": "Feature",
  "properties": {
    "addr:full":"1763 Boul Maloney E Gatineau QC J8R 1B4",
    "addr:housenumber":"1763",
    "addr:postcode":"j8r 1b4",
    "addr:street":"Boul Maloney E",
    "iso:country":"CA",
    "sg:address":"1763 Boul Maloney E",
    "sg:city":"Gatineau",
    "sg:classifiers":[
        {
            "category":"Freight",
            "type":"Transportation"
        }
    ],
    "sg:phone":"+1 819 643 9100",
    "sg:postcode":"J8R 1B4",
    "sg:province":"QC",
    "sg:tags":[
        "trucking"
    ],
    "wof:name":"Chalco",
    "wof:placetype":"venue"
},
  "geometry": {"coordinates":[-75.55568700000001,45.505608],"type":"Point"}
}