{
  "type": "Feature",
  "properties": {
    "addr:full":"North York ON M3J 3K6",
    "addr:postcode":"m3j 3k6",
    "iso:country":"CA",
    "sg:city":"North York",
    "sg:classifiers":[
        {
            "category":"Personal",
            "subcategory":"Beauty Salon",
            "type":"Services"
        }
    ],
    "sg:phone":"+1 416 650 9212",
    "sg:postcode":"M3J 3K6",
    "sg:province":"ON",
    "wof:name":"Beautiful You Hair Salon",
    "wof:placetype":"venue"
},
  "geometry": {"coordinates":[-79.488609,43.764145],"type":"Point"}
}