{
  "type": "Feature",
  "properties": {
    "addr:full":"Canmore AB T1W 1R4",
    "addr:postcode":"t1w 1r4",
    "iso:country":"CA",
    "sg:city":"Canmore",
    "sg:classifiers":[
        {
            "category":"Recreation",
            "type":"Entertainment"
        }
    ],
    "sg:phone":"+1 403 678 5459",
    "sg:postcode":"T1W 1R4",
    "sg:province":"AB",
    "sg:tags":[
        "tours",
        "sightseeing"
    ],
    "wof:name":"Assiniboine Heli Tours Inc",
    "wof:placetype":"venue"
},
  "geometry": {"coordinates":[-115.35792499999999,51.092308],"type":"Point"}
}