{
  "type": "Feature",
  "properties": {
    "addr:full":"22519 Adelaide Rd Mount Brydges ON N0L 1W0",
    "addr:housenumber":"22519",
    "addr:postcode":"n0l 1w0",
    "addr:street":"Adelaide Rd",
    "iso:country":"CA",
    "sg:address":"22519 Adelaide Rd",
    "sg:city":"Mount Brydges",
    "sg:classifiers":[
        {
            "category":"Restaurant",
            "type":"Food & Drink"
        }
    ],
    "sg:phone":"+1 519 264 1174",
    "sg:postcode":"N0L 1W0",
    "sg:province":"ON",
    "wof:name":"Village Pizza",
    "wof:placetype":"venue"
},
  "geometry": {"coordinates":[-81.49537658689999,42.9092750549],"type":"Point"}
}