{
  "type": "Feature",
  "properties": {
    "addr:full":"Warwick QC J0A 1M0",
    "addr:postcode":"j0a 1m0",
    "iso:country":"CA",
    "sg:city":"Warwick",
    "sg:classifiers":[
        {
            "category":"Shopping",
            "type":"Retail Goods"
        }
    ],
    "sg:phone":"+1 819 358 5113",
    "sg:postcode":"J0A 1M0",
    "sg:province":"QC",
    "sg:tags":[
        "ice"
    ],
    "wof:name":"Glace Frigo-Lamb Enr",
    "wof:placetype":"venue"
},
  "geometry": {"coordinates":[-71.984596,45.960732],"type":"Point"}
}