{
  "type": "Feature",
  "properties": {
    "iso:country":"CA",
    "sg:address":"5199 Rue Sherbrooke E",
    "sg:city":"Montreal",
    "sg:classifiers":[
        {
            "category":"Professional",
            "subcategory":"Business Services",
            "type":"Services"
        }
    ],
    "sg:phone":"+1 514 255 5533",
    "sg:postcode":"H1T 3X1",
    "sg:province":"QC",
    "sg:tags":[
        "notary"
    ],
    "wof:name":"Robert & Bourgouin",
    "wof:placetype":"venue"
},
  "geometry": {"coordinates":[-73.552773,45.568336],"type":"Point"}
}