{
  "type": "Feature",
  "properties": {
    "addr:full":"1350 Mountain Rd Thunder Bay ON P7J 1C2",
    "addr:housenumber":"1350",
    "addr:postcode":"p7j 1c2",
    "addr:street":"Mountain Rd",
    "iso:country":"CA",
    "sg:address":"1350 Mountain Rd",
    "sg:city":"Thunder Bay",
    "sg:classifiers":[
        {
            "category":"Recreation",
            "type":"Entertainment"
        }
    ],
    "sg:phone":"+1 807 475 8925",
    "sg:postcode":"P7J 1C2",
    "sg:province":"ON",
    "sg:tags":[
        "course",
        "golf"
    ],
    "wof:name":"Fort William Country Club",
    "wof:placetype":"venue"
},
  "geometry": {"coordinates":[-89.3221817017,48.325553894],"type":"Point"}
}