{
  "type": "Feature",
  "properties": {
    "addr:full":"1254 Av Lariviere Rouyn-Noranda QC J9X 4L1",
    "addr:housenumber":"1254",
    "addr:postcode":"j9x 4l1",
    "addr:street":"Av Lariviere",
    "iso:country":"CA",
    "sg:address":"1254 Av Lariviere",
    "sg:city":"Rouyn-Noranda",
    "sg:classifiers":[
        {
            "category":"Shopping",
            "subcategory":"Clothing, Apparel, & Fashions",
            "type":"Retail Goods"
        }
    ],
    "sg:phone":"+1 819 762 2834",
    "sg:postcode":"J9X 4L1",
    "sg:province":"QC",
    "sg:tags":[
        "item",
        "boutique"
    ],
    "wof:name":"Chiffon Plus",
    "wof:placetype":"venue"
},
  "geometry": {"coordinates":[-78.9929351807,48.2232627869],"type":"Point"}
}