{
  "type": "Feature",
  "properties": {
    "addr:full":"1920 Ellesmere Rd # 1 Scarborough ON M1H 2V6",
    "addr:housenumber":"1920",
    "addr:postcode":"m1h 2v6",
    "addr:street":"Ellesmere Rd # 1",
    "iso:country":"CA",
    "sg:address":"1920 Ellesmere Rd # 1",
    "sg:city":"Scarborough",
    "sg:classifiers":[
        {
            "category":"Real Estate",
            "subcategory":"Real Estate Agent",
            "type":"Services"
        }
    ],
    "sg:phone":"+1 416 289 6628",
    "sg:postcode":"M1H 2V6",
    "sg:province":"ON",
    "sg:tags":[
        "desk",
        "space"
    ],
    "wof:name":"Dinco Holdings Inc",
    "wof:placetype":"venue"
},
  "geometry": {"coordinates":[-79.24050099999999,43.774696],"type":"Point"}
}