{
  "type": "Feature",
  "properties": {
    "addr:full":"2305 Boul Wallberg Dolbeau-Mistassini QC G8L 1K3",
    "addr:housenumber":"2305",
    "addr:postcode":"g8l 1k3",
    "addr:street":"Boul Wallberg",
    "iso:country":"CA",
    "sg:address":"2305 Boul Wallberg",
    "sg:city":"Dolbeau-Mistassini",
    "sg:classifiers":[
        {
            "category":"Manufacturing",
            "subcategory":"Tools & Machinery",
            "type":"Manufacturing & Wholesale Goods"
        }
    ],
    "sg:phone":"+1 418 276 1874",
    "sg:postcode":"G8L 1K3",
    "sg:province":"QC",
    "sg:tags":[
        "repairing",
        "automobile"
    ],
    "wof:name":"Moteurs Dolbeau Inc",
    "wof:placetype":"venue"
},
  "geometry": {"coordinates":[-72.25599699999999,48.88324],"type":"Point"}
}