{
  "type": "Feature",
  "properties": {
    "addr:full":"25 Rue Saint-Jacques E Princeville QC G6L 4X2",
    "addr:housenumber":"25",
    "addr:postcode":"g6l 4x2",
    "addr:street":"Rue Saint-Jacques E",
    "iso:country":"CA",
    "sg:address":"25 Rue Saint-Jacques E",
    "sg:city":"Princeville",
    "sg:classifiers":[
        {
            "category":"Food & Beverages",
            "subcategory":"Groceries & Convenience Stores",
            "type":"Retail Goods"
        }
    ],
    "sg:phone":"+1 819 364 5253",
    "sg:postcode":"G6L 4X2",
    "sg:province":"QC",
    "sg:tags":[
        "grocer"
    ],
    "wof:name":"Provigo",
    "wof:placetype":"venue"
},
  "geometry": {"coordinates":[-71.8749160767,46.1728096008],"type":"Point"}
}