{
  "type": "Feature",
  "properties": {
    "addr:full":"4232 Village Stroll Whistler BC V0N 1B4",
    "addr:housenumber":"4232",
    "addr:postcode":"v0n 1b4",
    "addr:street":"Village Stroll",
    "iso:country":"CA",
    "sg:address":"4232 Village Stroll",
    "sg:city":"Whistler",
    "sg:classifiers":[
        {
            "category":"Bars & Pubs",
            "type":"Food & Drink"
        }
    ],
    "sg:phone":"+1 604 932 1904",
    "sg:postcode":"V0N 1B4",
    "sg:province":"BC",
    "sg:tags":[
        "club",
        "night"
    ],
    "wof:name":"Maxx Fish",
    "wof:placetype":"venue"
},
  "geometry": {"coordinates":[-122.955856,50.114475],"type":"Point"}
}