{
  "type": "Feature",
  "properties": {
    "addr:full":"82 Piney Cres Winnipeg MB R2P 1E7",
    "addr:housenumber":"82",
    "addr:postcode":"r2p 1e7",
    "addr:street":"Piney Cres",
    "iso:country":"CA",
    "sg:address":"82 Piney Cres",
    "sg:city":"Winnipeg",
    "sg:classifiers":[
        {
            "category":"Building & Trades",
            "subcategory":"Construction",
            "type":"Services"
        }
    ],
    "sg:phone":"+1 204 694 2660",
    "sg:postcode":"R2P 1E7",
    "sg:province":"MB",
    "sg:tags":[
        "insulation",
        "heat",
        "contractor"
    ],
    "wof:name":"Fibre Man Insulation",
    "wof:placetype":"venue"
},
  "geometry": {"coordinates":[-97.18282318120001,49.9570732117],"type":"Point"}
}