{
  "type": "Feature",
  "properties": {
    "addr:full":"334 Oakwood Ave York ON M6E 2V9",
    "addr:housenumber":"334",
    "addr:postcode":"m6e 2v9",
    "addr:street":"Oakwood Ave",
    "iso:country":"CA",
    "sg:address":"334 Oakwood Ave",
    "sg:city":"York",
    "sg:classifiers":[
        {
            "category":"Shopping",
            "subcategory":"Clothing, Apparel, & Fashions",
            "type":"Retail Goods"
        }
    ],
    "sg:phone":"+1 416 651 1653",
    "sg:postcode":"M6E 2V9",
    "sg:province":"ON",
    "sg:tags":[
        "boutique"
    ],
    "wof:name":"M Ricci Boutique & Tailor",
    "wof:placetype":"venue"
},
  "geometry": {"coordinates":[-79.43845399999999,43.686127],"type":"Point"}
}