{
  "type": "Feature",
  "properties": {
    "addr:full":"Kingston ON K7L 1C9",
    "addr:postcode":"k7l 1c9",
    "iso:country":"CA",
    "sg:city":"Kingston",
    "sg:classifiers":[
        {
            "category":"Professional",
            "subcategory":"Lawyer & Legal Services",
            "type":"Services"
        }
    ],
    "sg:phone":"+1 613 544 1482",
    "sg:postcode":"K7L 1C9",
    "sg:province":"ON",
    "sg:tags":[
        "attorney"
    ],
    "wof:name":"Brioux, Paul A",
    "wof:placetype":"venue"
},
  "geometry": {"coordinates":[-76.499382,44.23584],"type":"Point"}
}