{
  "type": "Feature",
  "properties": {
    "addr:full":"Thunder Bay ON P7E 6E7",
    "addr:postcode":"p7e 6e7",
    "iso:country":"CA",
    "sg:city":"Thunder Bay",
    "sg:classifiers":[
        {
            "category":"Health Services",
            "subcategory":"Doctor",
            "type":"Services"
        }
    ],
    "sg:phone":"+1 807 622 3995",
    "sg:postcode":"P7E 6E7",
    "sg:province":"ON",
    "sg:tags":[
        "physician",
        "surgeon"
    ],
    "wof:name":"Mapeso, Gabriel V MD",
    "wof:placetype":"venue"
},
  "geometry": {"coordinates":[-89.25476074220001,48.381061554],"type":"Point"}
}