{
  "type": "Feature",
  "properties": {
    "iso:country":"CA",
    "sg:address":"548 Carlton Rd",
    "sg:city":"Markham",
    "sg:classifiers":[
        {
            "category":"Health Services",
            "subcategory":"Doctor",
            "type":"Services"
        }
    ],
    "sg:phone":"+1 905 477 7560",
    "sg:postcode":"L3R 0C6",
    "sg:province":"ON",
    "sg:tags":[
        "physician",
        "surgeon"
    ],
    "wof:name":"Telch, Joseph MD",
    "wof:placetype":"venue"
},
  "geometry": {"coordinates":[-79.303474,43.870541],"type":"Point"}
}