{
  "type": "Feature",
  "properties": {
    "addr:full":"301 Vaughan St Winnipeg MB R3B 2N7",
    "addr:housenumber":"301",
    "addr:postcode":"r3b 2n7",
    "addr:street":"Vaughan St",
    "iso:country":"CA",
    "sg:address":"301 Vaughan St",
    "sg:city":"Winnipeg",
    "sg:classifiers":[
        {
            "category":"Social Services",
            "subcategory":"Child Care",
            "type":"Services"
        }
    ],
    "sg:phone":"+1 204 947 3044",
    "sg:postcode":"R3B 2N7",
    "sg:province":"MB",
    "sg:tags":[
        "association"
    ],
    "wof:name":"Ymca-Ywca of Winnipeg",
    "wof:placetype":"venue"
},
  "geometry": {"coordinates":[-97.15003967289999,49.8925285339],"type":"Point"}
}