{
  "type": "Feature",
  "properties": {
    "addr:full":"1324 Pembroke St W Pembroke ON K8A 7A2",
    "addr:housenumber":"1324",
    "addr:postcode":"k8a 7a2",
    "addr:street":"Pembroke St W",
    "iso:country":"CA",
    "sg:address":"1324 Pembroke St W",
    "sg:city":"Pembroke",
    "sg:classifiers":[
        {
            "category":"Professional",
            "subcategory":"Art Services",
            "type":"Services"
        }
    ],
    "sg:phone":"+1 613 732 7775",
    "sg:postcode":"K8A 7A2",
    "sg:province":"ON",
    "sg:tags":[
        "graphic",
        "designer",
        "sign"
    ],
    "wof:name":"Speedpro Signs Plus",
    "wof:placetype":"venue"
},
  "geometry": {"coordinates":[-77.153008,45.834469],"type":"Point"}
}