{
  "type": "Feature",
  "properties": {
    "addr:full":"112 Main St Oyen AB T0J 2J0",
    "addr:housenumber":"112",
    "addr:postcode":"t0j 2j0",
    "addr:street":"Main St",
    "iso:country":"CA",
    "sg:address":"112 Main St",
    "sg:city":"Oyen",
    "sg:classifiers":[
        {
            "category":"Personal",
            "subcategory":"Beauty Salon",
            "type":"Services"
        }
    ],
    "sg:phone":"+1 403 664 2487",
    "sg:postcode":"T0J 2J0",
    "sg:province":"AB",
    "wof:name":"Hair Affair",
    "wof:placetype":"venue"
},
  "geometry": {"coordinates":[-110.483383,51.355659],"type":"Point"}
}