{
  "type": "Feature",
  "properties": {
    "iso:country":"CA",
    "sg:city":"Saint-Leonard-D'Aston",
    "sg:classifiers":[
        {
            "category":"Health Services",
            "subcategory":"Health Practitioner",
            "type":"Services"
        }
    ],
    "sg:phone":"+1 819 399 2329",
    "sg:postcode":"J0C 1M0",
    "sg:province":"QC",
    "sg:tags":[
        "physiotherapist"
    ],
    "wof:name":"Physiotherapie Du Ctr-Quebec",
    "wof:placetype":"venue"
},
  "geometry": {"coordinates":[-72.3718719482,46.1063690186],"type":"Point"}
}