{
  "type": "Feature",
  "properties": {
    "addr:full":"7225 Wyandotte St E Windsor ON N8S 1R5",
    "addr:housenumber":"7225",
    "addr:postcode":"n8s 1r5",
    "addr:street":"Wyandotte St E",
    "iso:country":"CA",
    "sg:address":"7225 Wyandotte St E",
    "sg:city":"Windsor",
    "sg:classifiers":[
        {
            "category":"Shopping",
            "subcategory":"Discount & Variety Stores",
            "type":"Retail Goods"
        }
    ],
    "sg:phone":"+1 519 944 4940",
    "sg:postcode":"N8S 1R5",
    "sg:province":"ON",
    "wof:name":"Quick Mart Plus",
    "wof:placetype":"venue"
},
  "geometry": {"coordinates":[-82.95161437989999,42.3320121765],"type":"Point"}
}