{
  "type": "Feature",
  "properties": {
    "addr:full":"Coquitlam BC V3K 4H2",
    "addr:postcode":"v3k 4h2",
    "iso:country":"CA",
    "sg:city":"Coquitlam",
    "sg:classifiers":[
        {
            "category":"Organizations",
            "subcategory":"Labor Organization",
            "type":"Services"
        }
    ],
    "sg:phone":"+1 604 939 8990",
    "sg:postcode":"V3K 4H2",
    "sg:province":"BC",
    "wof:name":"Canadian Merchant Svc Guild",
    "wof:placetype":"venue"
},
  "geometry": {"coordinates":[-122.873283,49.237625],"type":"Point"}
}