{
  "type": "Feature",
  "properties": {
    "iso:country":"CA",
    "sg:city":"Mississauga",
    "sg:classifiers":[
        {
            "category":"Health Services",
            "subcategory":"Health Practitioner",
            "type":"Services"
        }
    ],
    "sg:phone":"+1 905 501 8851",
    "sg:postcode":"L4Z 2Z1",
    "sg:province":"ON",
    "sg:tags":[
        "acupuncture"
    ],
    "wof:name":"Acupuncture Shiatsu Clinic",
    "wof:placetype":"venue"
},
  "geometry": {"coordinates":[-79.671768,43.621677],"type":"Point"}
}