{
  "type": "Feature",
  "properties": {
    "iso:country":"CA",
    "sg:city":"West Vancouver",
    "sg:classifiers":[
        {
            "category":"Food & Beverages",
            "subcategory":"Bakery",
            "type":"Retail Goods"
        }
    ],
    "sg:phone":"+1 604 926 4401",
    "sg:postcode":"V7T 1A1",
    "sg:province":"BC",
    "sg:tags":[
        "baker"
    ],
    "wof:name":"Park Royal Artisan Bakery",
    "wof:placetype":"venue"
},
  "geometry": {"coordinates":[-123.136711121,49.3240242004],"type":"Point"}
}