{
  "type": "Feature",
  "properties": {
    "addr:full":"101 2nd St E The Pas MB R9A 1S4",
    "addr:housenumber":"101",
    "addr:postcode":"r9a 1s4",
    "addr:street":"2Nd St E",
    "iso:country":"CA",
    "sg:address":"101 2nd St E",
    "sg:city":"The Pas",
    "sg:classifiers":[
        {
            "category":"Travel",
            "subcategory":"Hotels & Motels",
            "type":"Entertainment"
        }
    ],
    "sg:phone":"+1 204 623 2272",
    "sg:postcode":"R9A 1S4",
    "sg:province":"MB",
    "wof:name":"Alouette Hotel",
    "wof:placetype":"venue"
},
  "geometry": {"coordinates":[-101.25035099999999,53.813435],"type":"Point"}
}