{
  "type": "Feature",
  "properties": {
    "addr:full":"240 Queenston St St Catharines ON L2P 2X3",
    "addr:housenumber":"240",
    "addr:postcode":"l2p 2x3",
    "addr:street":"Queenston St",
    "iso:country":"CA",
    "sg:address":"240 Queenston St",
    "sg:city":"St Catharines",
    "sg:classifiers":[
        {
            "category":"Health Services",
            "subcategory":"Health Practitioner",
            "type":"Services"
        }
    ],
    "sg:phone":"+1 905 685 7011",
    "sg:postcode":"L2P 2X3",
    "sg:province":"ON",
    "sg:tags":[
        "psychologist"
    ],
    "wof:name":"Queenston Psychological Svc",
    "wof:placetype":"venue"
},
  "geometry": {"coordinates":[-79.22235107420001,43.1609458923],"type":"Point"}
}