{
  "type": "Feature",
  "properties": {
    "addr:full":"6275 6E Av E Charlesbourg QC G1H 3T4",
    "addr:housenumber":"6275",
    "addr:postcode":"g1h 3t4",
    "addr:street":"6E Av E",
    "iso:country":"CA",
    "sg:address":"6275 6E Av E",
    "sg:city":"Charlesbourg",
    "sg:classifiers":[
        {
            "category":"Personal",
            "subcategory":"Beauty Salon",
            "type":"Services"
        }
    ],
    "sg:phone":"+1 418 628 4192",
    "sg:postcode":"G1H 3T4",
    "sg:province":"QC",
    "sg:tags":[
        "treatment",
        "scalp"
    ],
    "wof:name":"Haute Coiffure Saroy Ltee",
    "wof:placetype":"venue"
},
  "geometry": {"coordinates":[-71.251694,46.855488],"type":"Point"}
}