{
  "type": "Feature",
  "properties": {
    "iso:country":"CA",
    "sg:address":"5396 Portage Ave",
    "sg:city":"Headingley",
    "sg:classifiers":[
        {
            "category":"Autos & Motor Vehicles",
            "subcategory":"Auto Supplies",
            "type":"Retail Goods"
        }
    ],
    "sg:phone":"+1 204 889 3178",
    "sg:postcode":"R4H 1G4",
    "sg:province":"MB",
    "sg:tags":[
        "trailer",
        "hitch"
    ],
    "wof:name":"Bell's Trailer Hitches",
    "wof:placetype":"venue"
},
  "geometry": {"coordinates":[-97.404121,49.875828],"type":"Point"}
}