{
  "type": "Feature",
  "properties": {
    "addr:full":"10 Park Ave E Elmira ON N3B 2H3",
    "addr:housenumber":"10",
    "addr:postcode":"n3b 2h3",
    "addr:street":"Park Ave E",
    "iso:country":"CA",
    "sg:address":"10 Park Ave E",
    "sg:city":"Elmira",
    "sg:classifiers":[
        {
            "category":"Manufacturing",
            "subcategory":"Signs",
            "type":"Manufacturing & Wholesale Goods"
        }
    ],
    "sg:phone":"+1 519 669 2145",
    "sg:postcode":"N3B 2H3",
    "sg:province":"ON",
    "wof:name":"Burrows Signs & Graphics Inc",
    "wof:placetype":"venue"
},
  "geometry": {"coordinates":[-80.55529,43.595539],"type":"Point"}
}