{
  "type": "Feature",
  "properties": {
    "addr:full":"2004 10 Ave SW Calgary AB T3C 0J8",
    "addr:housenumber":"2004",
    "addr:postcode":"t3c 0j8",
    "addr:street":"10 Ave Sw",
    "iso:country":"CA",
    "sg:address":"2004 10 Ave SW",
    "sg:city":"Calgary",
    "sg:classifiers":[
        {
            "category":"Retail",
            "subcategory":"Portrait Studio",
            "type":"Services"
        }
    ],
    "sg:phone":"+1 403 228 2099",
    "sg:postcode":"T3C 0J8",
    "sg:province":"AB",
    "sg:tags":[
        "photographer"
    ],
    "wof:name":"Illusions Photographic",
    "wof:placetype":"venue"
},
  "geometry": {"coordinates":[-114.10685700000001,51.044678],"type":"Point"}
}