{
  "type": "Feature",
  "properties": {
    "addr:full":"1775 Rue Favreau Laval QC H7T 2H1",
    "addr:housenumber":"1775",
    "addr:postcode":"h7t 2h1",
    "addr:street":"Rue Favreau",
    "iso:country":"CA",
    "sg:address":"1775 Rue Favreau",
    "sg:city":"Laval",
    "sg:classifiers":[
        {
            "category":"Personal",
            "subcategory":"Beauty Salon",
            "type":"Services"
        }
    ],
    "sg:phone":"+1 450 681 5555",
    "sg:postcode":"H7T 2H1",
    "sg:province":"QC",
    "wof:name":"Coiffure Maurice Vanier Enr",
    "wof:placetype":"venue"
},
  "geometry": {"coordinates":[-73.766708374,45.5508346558],"type":"Point"}
}