{
  "type": "Feature",
  "properties": {
    "addr:full":"164 Bennett Rd Scarborough ON M1E 3Y3",
    "addr:housenumber":"164",
    "addr:postcode":"m1e 3y3",
    "addr:street":"Bennett Rd",
    "iso:country":"CA",
    "sg:address":"164 Bennett Rd",
    "sg:city":"Scarborough",
    "sg:classifiers":[
        {
            "category":"Shopping",
            "subcategory":"Pharmacy",
            "type":"Retail Goods"
        }
    ],
    "sg:phone":"+1 416 282 2004",
    "sg:postcode":"M1E 3Y3",
    "sg:province":"ON",
    "wof:name":"Medicine Shoppe",
    "wof:placetype":"venue"
},
  "geometry": {"coordinates":[-79.166305542,43.7723846436],"type":"Point"}
}