{
  "type": "Feature",
  "properties": {
    "addr:full":"9843 Av Charton Montreal QC H2B 2C7",
    "addr:housenumber":"9843",
    "addr:postcode":"h2b 2c7",
    "addr:street":"Av Charton",
    "iso:country":"CA",
    "sg:address":"9843 Av Charton",
    "sg:city":"Montreal",
    "sg:classifiers":[
        {
            "category":"Health Services",
            "subcategory":"Health Practitioner",
            "type":"Services"
        }
    ],
    "sg:phone":"+1 514 990 7825",
    "sg:postcode":"H2B 2C7",
    "sg:province":"QC",
    "wof:name":"Bisson Lise",
    "wof:placetype":"venue"
},
  "geometry": {"coordinates":[-73.6472625732,45.5674514771],"type":"Point"}
}