{
  "type": "Feature",
  "properties": {
    "iso:country":"CA",
    "sg:address":"2394 Bloor St W",
    "sg:city":"Toronto",
    "sg:classifiers":[
        {
            "category":"Food & Beverages",
            "subcategory":"Bakery",
            "type":"Retail Goods"
        }
    ],
    "sg:phone":"+1 416 769 8065",
    "sg:postcode":"M6S 1P5",
    "sg:province":"ON",
    "sg:tags":[
        "baker"
    ],
    "wof:name":"Anna's Bakery & Deli",
    "wof:placetype":"venue"
},
  "geometry": {"coordinates":[-79.48272705079999,43.6498603821],"type":"Point"}
}