{
  "type": "Feature",
  "properties": {
    "iso:country":"CA",
    "sg:address":"44 Advance Rd",
    "sg:city":"Etobicoke",
    "sg:classifiers":[
        {
            "category":"Organizations",
            "subcategory":"Labor Organization",
            "type":"Services"
        }
    ],
    "sg:phone":"+1 416 234 5008",
    "sg:postcode":"M8Z 2T4",
    "sg:province":"ON",
    "wof:name":"Caw",
    "wof:placetype":"venue"
},
  "geometry": {"coordinates":[-79.5282211304,43.6341209412],"type":"Point"}
}