{
  "type": "Feature",
  "properties": {
    "addr:full":"383 Ellis St # 100 Penticton BC V2A 4L9",
    "addr:housenumber":"383",
    "addr:postcode":"v2a 4l9",
    "addr:street":"Ellis St # 100",
    "iso:country":"CA",
    "sg:address":"383 Ellis St # 100",
    "sg:city":"Penticton",
    "sg:classifiers":[
        {
            "category":"Health Services",
            "subcategory":"Doctor",
            "type":"Services"
        }
    ],
    "sg:phone":"+1 250 492 3024",
    "sg:postcode":"V2A 4L9",
    "sg:province":"BC",
    "sg:tags":[
        "physician",
        "surgeon"
    ],
    "wof:name":"Caskey, W A MD",
    "wof:placetype":"venue"
},
  "geometry": {"coordinates":[-119.59078979500001,49.4977111816],"type":"Point"}
}