{
  "type": "Feature",
  "properties": {
    "addr:full":"139 Duke St Miramichi NB E1N 1H6",
    "addr:housenumber":"139",
    "addr:postcode":"e1n 1h6",
    "addr:street":"Duke St",
    "iso:country":"CA",
    "sg:address":"139 Duke St",
    "sg:city":"Miramichi",
    "sg:classifiers":[
        {
            "category":"Social Services",
            "type":"Services"
        }
    ],
    "sg:phone":"+1 506 773 4719",
    "sg:postcode":"E1N 1H6",
    "sg:province":"NB",
    "sg:tags":[
        "counselor",
        "marriage",
        "family"
    ],
    "wof:name":"Family Services",
    "wof:placetype":"venue"
},
  "geometry": {"coordinates":[-65.4689025879,47.0297012329],"type":"Point"}
}