{
  "type": "Feature",
  "properties": {
    "addr:full":"Surrey BC V3R 8X7",
    "addr:postcode":"v3r 8x7",
    "iso:country":"CA",
    "sg:city":"Surrey",
    "sg:classifiers":[
        {
            "category":"Banks & Credit Unions",
            "subcategory":"Bank",
            "type":"Services"
        }
    ],
    "sg:phone":"+1 604 597 7840",
    "sg:postcode":"V3R 8X7",
    "sg:province":"BC",
    "sg:tags":[
        "financing"
    ],
    "wof:name":"Philmark Commercial Finance",
    "wof:placetype":"venue"
},
  "geometry": {"coordinates":[-122.798828,49.186081],"type":"Point"}
}