{
  "type": "Feature",
  "properties": {
    "addr:full":"712 Alderwood Pl SE Calgary AB T2H 2B4",
    "addr:housenumber":"712",
    "addr:postcode":"t2h 2b4",
    "addr:street":"Alderwood Pl Se",
    "iso:country":"CA",
    "sg:address":"712 Alderwood Pl SE",
    "sg:city":"Calgary",
    "sg:classifiers":[
        {
            "category":"Real Estate",
            "subcategory":"Real Estate Agent",
            "type":"Services"
        }
    ],
    "sg:phone":"+1 403 253 7326",
    "sg:postcode":"T2H 2B4",
    "sg:province":"AB",
    "wof:name":"Dream Scape Real Estate Inc",
    "wof:placetype":"venue"
},
  "geometry": {"coordinates":[-114.04791299999999,50.974342],"type":"Point"}
}