{
  "type": "Feature",
  "properties": {
    "iso:country":"CA",
    "sg:address":"555 Third St",
    "sg:city":"London",
    "sg:classifiers":[
        {
            "category":"Building & Trades",
            "subcategory":"Plumbing",
            "type":"Services"
        }
    ],
    "sg:phone":"+1 519 451 8342",
    "sg:postcode":"N5V 2C1",
    "sg:province":"ON",
    "sg:tags":[
        "sewer",
        "contractor"
    ],
    "wof:name":"Discount Drain Svc",
    "wof:placetype":"venue"
},
  "geometry": {"coordinates":[-81.18866,43.008671],"type":"Point"}
}