{
  "type": "Feature",
  "properties": {
    "addr:full":"8940 192 St Surrey BC V4N 3W8",
    "addr:housenumber":"8940",
    "addr:postcode":"v4n 3w8",
    "addr:street":"192 St",
    "iso:country":"CA",
    "sg:address":"8940 192 St",
    "sg:city":"Surrey",
    "sg:classifiers":[
        {
            "category":"Shopping",
            "subcategory":"Florist",
            "type":"Retail Goods"
        }
    ],
    "sg:phone":"+1 604 882 1201",
    "sg:postcode":"V4N 3W8",
    "sg:province":"BC",
    "sg:tags":[
        "nursery"
    ],
    "wof:name":"Art's Nursery Wholesale & Rtl",
    "wof:placetype":"venue"
},
  "geometry": {"coordinates":[-122.6902771,49.1651992798],"type":"Point"}
}