{
  "type": "Feature",
  "properties": {
    "addr:full":"PO Box 568 Vilna AB T0A 3L0",
    "addr:housenumber":"po",
    "addr:postcode":"t0a 3l0",
    "addr:street":"Box 568",
    "iso:country":"CA",
    "sg:address":"PO Box 568",
    "sg:city":"Vilna",
    "sg:classifiers":[
        {
            "category":"Sports & Exercise",
            "subcategory":"Golf",
            "type":"Entertainment"
        }
    ],
    "sg:phone":"+1 780 636 3660",
    "sg:postcode":"T0A 3L0",
    "sg:province":"AB",
    "sg:tags":[
        "course"
    ],
    "wof:name":"Vilna Golf Course",
    "wof:placetype":"venue"
},
  "geometry": {"coordinates":[-111.91909,54.114029],"type":"Point"}
}