{
  "type": "Feature",
  "properties": {
    "iso:country":"CA",
    "sg:address":"280 Frecker Dr",
    "sg:city":"St. John's",
    "sg:classifiers":[
        {
            "category":"Shopping",
            "type":"Retail Goods"
        }
    ],
    "sg:phone":"+1 709 368 8018",
    "sg:postcode":"A1E 5S6",
    "sg:province":"NL",
    "sg:tags":[
        "cosmetic",
        "perfume"
    ],
    "wof:name":"Mary Kay Cosmetics",
    "wof:placetype":"venue"
},
  "geometry": {"coordinates":[-52.7721099854,47.5346755981],"type":"Point"}
}