{
  "type": "Feature",
  "properties": {
    "iso:country":"CA",
    "sg:address":"3700 Richmond Rd",
    "sg:city":"Nepean",
    "sg:classifiers":[
        {
            "category":"Travel",
            "subcategory":"Hotels & Motels",
            "type":"Entertainment"
        }
    ],
    "sg:phone":"+1 613 828 2741",
    "sg:postcode":"K2H 5B8",
    "sg:province":"ON",
    "wof:name":"Best Western Barons Hotel",
    "wof:placetype":"venue"
},
  "geometry": {"coordinates":[-75.8210983276,45.3269081116],"type":"Point"}
}