{
  "type": "Feature",
  "properties": {
    "addr:full":"2742 Windt Rd Westbank BC V4T 1L8",
    "addr:housenumber":"2742",
    "addr:postcode":"v4t 1l8",
    "addr:street":"Windt Rd",
    "iso:country":"CA",
    "sg:address":"2742 Windt Rd",
    "sg:city":"Westbank",
    "sg:classifiers":[
        {
            "category":"Manufacturing",
            "subcategory":"Tools & Machinery",
            "type":"Manufacturing & Wholesale Goods"
        }
    ],
    "sg:phone":"+1 250 707 0063",
    "sg:postcode":"V4T 1L8",
    "sg:province":"BC",
    "sg:tags":[
        "equipment",
        "safety",
        "clothing"
    ],
    "wof:name":"Sear Search & Rescue Equipment",
    "wof:placetype":"venue"
},
  "geometry": {"coordinates":[-119.64267700000001,49.831661],"type":"Point"}
}