{
  "type": "Feature",
  "properties": {
    "iso:country":"CA",
    "sg:address":"3911 78 Ave NW",
    "sg:city":"Edmonton",
    "sg:classifiers":[
        {
            "category":"Wholesale",
            "subcategory":"Metals & Minerals",
            "type":"Manufacturing & Wholesale Goods"
        }
    ],
    "sg:phone":"+1 780 469 9752",
    "sg:postcode":"T6B 2N3",
    "sg:province":"AB",
    "sg:tags":[
        "pipe"
    ],
    "wof:name":"G R Tubular Svc Inc",
    "wof:placetype":"venue"
},
  "geometry": {"coordinates":[-113.401847839,53.5141677856],"type":"Point"}
}