{
  "type": "Feature",
  "properties": {
    "addr:full":"4188 Hwy 601 Dryden ON P8N 2Z2",
    "addr:housenumber":"4188",
    "addr:postcode":"p8n 2z2",
    "addr:street":"Hwy 601",
    "iso:country":"CA",
    "sg:address":"4188 Hwy 601",
    "sg:city":"Dryden",
    "sg:classifiers":[
        {
            "category":"Professional",
            "subcategory":"Business Services",
            "type":"Services"
        }
    ],
    "sg:phone":"+1 807 937 2233",
    "sg:postcode":"P8N 2Z2",
    "sg:province":"ON",
    "sg:tags":[
        "appraiser"
    ],
    "wof:name":"Patricia Region Appraisal",
    "wof:placetype":"venue"
},
  "geometry": {"coordinates":[-92.756409,49.807575],"type":"Point"}
}