{
  "type": "Feature",
  "properties": {
    "addr:full":"349 Rue DE LA Couronne Quebec QC G1K 6E7",
    "addr:housenumber":"349",
    "addr:postcode":"g1k 6e7",
    "addr:street":"Rue De La Couronne",
    "iso:country":"CA",
    "sg:address":"349 Rue DE LA Couronne",
    "sg:city":"Quebec",
    "sg:classifiers":[
        {
            "category":"Restaurant",
            "type":"Food & Drink"
        }
    ],
    "sg:phone":"+1 418 523 2634",
    "sg:postcode":"G1K 6E7",
    "sg:province":"QC",
    "wof:name":"Restaurant Saigon-Bangkok",
    "wof:placetype":"venue"
},
  "geometry": {"coordinates":[-71.225075,46.814938],"type":"Point"}
}