{
  "type": "Feature",
  "properties": {
    "addr:full":"900 Boul Quevillon Lebel-Sur-Quevillon QC J0Y 1X0",
    "addr:housenumber":"900",
    "addr:postcode":"j0y 1x0",
    "addr:street":"Boul Quevillon Lebel-Sur-Quevillon",
    "iso:country":"CA",
    "sg:address":"900 Boul Quevillon",
    "sg:city":"Lebel-Sur-Quevillon",
    "sg:classifiers":[
        {
            "category":"Travel",
            "subcategory":"Campground",
            "type":"Entertainment"
        }
    ],
    "sg:phone":"+1 819 755 3363",
    "sg:postcode":"J0Y 1X0",
    "sg:province":"QC",
    "sg:tags":[
        "government"
    ],
    "wof:name":"Lebel-Sur-Quevillon Terrain",
    "wof:placetype":"venue"
},
  "geometry": {"coordinates":[-76.982574,49.054775],"type":"Point"}
}