{
  "type": "Feature",
  "properties": {
    "addr:full":"6267 Lundy's Lane Niagara Falls ON L2G 1T5",
    "addr:housenumber":"6267",
    "addr:postcode":"l2g 1t5",
    "addr:street":"Lundy'S Lane",
    "iso:country":"CA",
    "sg:address":"6267 Lundy's Lane",
    "sg:city":"Niagara Falls",
    "sg:classifiers":[
        {
            "category":"Travel",
            "subcategory":"Hotels & Motels",
            "type":"Entertainment"
        }
    ],
    "sg:phone":"+1 905 356 5135",
    "sg:postcode":"L2G 1T5",
    "sg:province":"ON",
    "wof:name":"Bonanza Motel",
    "wof:placetype":"venue"
},
  "geometry": {"coordinates":[-77.565369,45.042416],"type":"Point"}
}