{
  "type": "Feature",
  "properties": {
    "addr:full":"4500 Boul Kimber Saint-Hubert QC J3Y 8K5",
    "addr:housenumber":"4500",
    "addr:postcode":"j3y 8k5",
    "addr:street":"Boul Kimber",
    "iso:country":"CA",
    "sg:address":"4500 Boul Kimber",
    "sg:city":"Saint-Hubert",
    "sg:classifiers":[
        {
            "category":"Manufacturing",
            "subcategory":"Furniture",
            "type":"Manufacturing & Wholesale Goods"
        }
    ],
    "sg:phone":"+1 450 462 2002",
    "sg:postcode":"J3Y 8K5",
    "sg:province":"QC",
    "sg:tags":[
        "equipment",
        "supply"
    ],
    "wof:name":"Meridiana Canada Inc",
    "wof:placetype":"venue"
},
  "geometry": {"coordinates":[-73.44422900000001,45.496452],"type":"Point"}
}