{
  "type": "Feature",
  "properties": {
    "addr:full":"33 Manor Rd St George NB E5C 3N6",
    "addr:housenumber":"33",
    "addr:postcode":"e5c 3n6",
    "addr:street":"Manor Rd",
    "iso:country":"CA",
    "sg:address":"33 Manor Rd",
    "sg:city":"St George",
    "sg:classifiers":[
        {
            "category":"Organizations",
            "subcategory":"Religious Organization",
            "type":"Services"
        }
    ],
    "sg:phone":"+1 506 755 3291",
    "sg:postcode":"E5C 3N6",
    "sg:province":"NB",
    "sg:tags":[
        "church"
    ],
    "wof:name":"United Pentecostal Church",
    "wof:placetype":"venue"
},
  "geometry": {"coordinates":[-66.84144592289999,45.143989563],"type":"Point"}
}