{
  "type": "Feature",
  "properties": {
    "iso:country":"CA",
    "sg:address":"202 Main St",
    "sg:city":"Maidstone",
    "sg:classifiers":[
        {
            "category":"Personal",
            "subcategory":"Beauty Salon",
            "type":"Services"
        }
    ],
    "sg:phone":"+1 306 893 4242",
    "sg:postcode":"S0M 1M0",
    "sg:province":"SK",
    "wof:name":"Curl Up & Dye Shoppe",
    "wof:placetype":"venue"
},
  "geometry": {"coordinates":[-109.28984832800001,53.0874786377],"type":"Point"}
}