{
  "type": "Feature",
  "properties": {
    "addr:full":"250 Idylwyld Dr N Saskatoon SK S7L 0Y9",
    "addr:housenumber":"250",
    "addr:postcode":"s7l 0y9",
    "addr:street":"Idylwyld Dr N",
    "iso:country":"CA",
    "sg:address":"250 Idylwyld Dr N",
    "sg:city":"Saskatoon",
    "sg:classifiers":[
        {
            "category":"Shopping",
            "subcategory":"Clothing, Apparel, & Fashions",
            "type":"Retail Goods"
        }
    ],
    "sg:phone":"+1 306 934 2100",
    "sg:postcode":"S7L 0Y9",
    "sg:province":"SK",
    "sg:tags":[
        "entertainer"
    ],
    "wof:name":"For Lovers Only",
    "wof:placetype":"venue"
},
  "geometry": {"coordinates":[-106.670043945,52.1320304871],"type":"Point"}
}