{
  "type": "Feature",
  "properties": {
    "addr:full":"Lindsay ON K9V 6A5",
    "addr:postcode":"k9v 6a5",
    "iso:country":"CA",
    "sg:city":"Lindsay",
    "sg:classifiers":[
        {
            "category":"Professional",
            "subcategory":"Business Services",
            "type":"Services"
        }
    ],
    "sg:phone":"+1 705 324 0499",
    "sg:postcode":"K9V 6A5",
    "sg:province":"ON",
    "sg:tags":[
        "consultant",
        "design",
        "decorator",
        "interior",
        "curtain",
        "drapery"
    ],
    "wof:name":"Kawartha Drapery & Decorating",
    "wof:placetype":"venue"
},
  "geometry": {"coordinates":[-78.7413406372,44.3527297974],"type":"Point"}
}