{
  "type": "Feature",
  "properties": {
    "addr:full":"1344 Walter St Lefroy ON L0L 1W0",
    "addr:housenumber":"1344",
    "addr:postcode":"l0l 1w0",
    "addr:street":"Walter St",
    "iso:country":"CA",
    "sg:address":"1344 Walter St",
    "sg:city":"Lefroy",
    "sg:classifiers":[
        {
            "category":"Building & Trades",
            "subcategory":"Electrical",
            "type":"Services"
        }
    ],
    "sg:phone":"+1 705 456 2722",
    "sg:postcode":"L0L 1W0",
    "sg:province":"ON",
    "sg:tags":[
        "electric",
        "contractor"
    ],
    "wof:name":"R Corner Electric",
    "wof:placetype":"venue"
},
  "geometry": {"coordinates":[-79.555725,44.265423],"type":"Point"}
}