{
  "type": "Feature",
  "properties": {
    "addr:full":"4560 Dixie Rd Mississauga ON L4W 1N2",
    "addr:housenumber":"4560",
    "addr:postcode":"l4w 1n2",
    "addr:street":"Dixie Rd",
    "iso:country":"CA",
    "sg:address":"4560 Dixie Rd",
    "sg:city":"Mississauga",
    "sg:classifiers":[
        {
            "category":"Social Services",
            "subcategory":"Child Care",
            "type":"Services"
        }
    ],
    "sg:phone":"+1 905 629 8849",
    "sg:postcode":"L4W 1N2",
    "sg:province":"ON",
    "wof:name":"Peekaboo Childcare",
    "wof:placetype":"venue"
},
  "geometry": {"coordinates":[-79.617203,43.632874],"type":"Point"}
}