{
  "type": "Feature",
  "properties": {
    "iso:country":"CA",
    "sg:city":"Burnaby",
    "sg:classifiers":[
        {
            "category":"Health Services",
            "subcategory":"Doctor",
            "type":"Services"
        }
    ],
    "sg:phone":"+1 604 439 1277",
    "sg:postcode":"V5H 2E3",
    "sg:province":"BC",
    "sg:tags":[
        "physician",
        "surgeon"
    ],
    "wof:name":"Metro Cardiology Svc Ltd",
    "wof:placetype":"venue"
},
  "geometry": {"coordinates":[-122.99402618400001,49.2265090942],"type":"Point"}
}