{
  "type": "Feature",
  "properties": {
    "addr:full":"7175 Royal Oak Ave Burnaby BC V5J 4J3",
    "addr:housenumber":"7175",
    "addr:postcode":"v5j 4j3",
    "addr:street":"Royal Oak Ave",
    "iso:country":"CA",
    "sg:address":"7175 Royal Oak Ave",
    "sg:city":"Burnaby",
    "sg:classifiers":[
        {
            "category":"Organizations",
            "subcategory":"Religious Organization",
            "type":"Services"
        }
    ],
    "sg:phone":"+1 604 433 2822",
    "sg:postcode":"V5J 4J3",
    "sg:province":"BC",
    "sg:tags":[
        "church"
    ],
    "wof:name":"Royal Oak Community Church",
    "wof:placetype":"venue"
},
  "geometry": {"coordinates":[-122.988716,49.218754],"type":"Point"}
}