{
  "type": "Feature",
  "properties": {
    "iso:country":"CA",
    "sg:address":"1140 Ironwood St",
    "sg:city":"Campbell River",
    "sg:classifiers":[
        {
            "category":"Bars & Pubs",
            "type":"Food & Drink"
        }
    ],
    "sg:phone":"+1 250 287 8686",
    "sg:postcode":"V9W 5P7",
    "sg:province":"BC",
    "sg:tags":[
        "club",
        "night"
    ],
    "wof:name":"Voodoo Lounge",
    "wof:placetype":"venue"
},
  "geometry": {"coordinates":[-125.255210877,50.0262908936],"type":"Point"}
}