{
  "type": "Feature",
  "properties": {
    "addr:full":"3437 Hammond Bay Rd Nanaimo BC V9T 1E7",
    "addr:housenumber":"3437",
    "addr:postcode":"v9t 1e7",
    "addr:street":"Hammond Bay Rd",
    "iso:country":"CA",
    "sg:address":"3437 Hammond Bay Rd",
    "sg:city":"Nanaimo",
    "sg:classifiers":[
        {
            "category":"Retail",
            "subcategory":"Animal Services",
            "type":"Services"
        }
    ],
    "sg:phone":"+1 250 756 0206",
    "sg:postcode":"V9T 1E7",
    "sg:province":"BC",
    "sg:tags":[
        "pet",
        "grooming",
        "washing"
    ],
    "wof:name":"Foxy Dog",
    "wof:placetype":"venue"
},
  "geometry": {"coordinates":[-123.953445,49.218735],"type":"Point"}
}