{
  "type": "Feature",
  "properties": {
    "addr:full":"7 Union St E Waterloo ON N2J 1B5",
    "addr:housenumber":"7",
    "addr:postcode":"n2j 1b5",
    "addr:street":"Union St E",
    "iso:country":"CA",
    "sg:address":"7 Union St E",
    "sg:city":"Waterloo",
    "sg:classifiers":[
        {
            "category":"Professional",
            "subcategory":"Lawyer & Legal Services",
            "type":"Services"
        }
    ],
    "sg:phone":"+1 519 579 5600",
    "sg:postcode":"N2J 1B5",
    "sg:province":"ON",
    "sg:tags":[
        "attorney"
    ],
    "wof:name":"Welch, Lorene P",
    "wof:placetype":"venue"
},
  "geometry": {"coordinates":[-80.51519,43.45871],"type":"Point"}
}