{
  "type": "Feature",
  "properties": {
    "iso:country":"CA",
    "sg:address":"1 Burling Cres",
    "sg:city":"St. John's",
    "sg:classifiers":[
        {
            "category":"Professional",
            "subcategory":"Management & Consulting",
            "type":"Services"
        }
    ],
    "sg:phone":"+1 709 747 7999",
    "sg:postcode":"A1E 5G9",
    "sg:province":"NL",
    "sg:tags":[
        "roofing",
        "contractor",
        "consultant"
    ],
    "wof:name":"Roofing & Safety Consultants",
    "wof:placetype":"venue"
},
  "geometry": {"coordinates":[-52.7695846558,47.5299720764],"type":"Point"}
}