{
  "type": "Feature",
  "properties": {
    "iso:country":"CA",
    "sg:address":"2766 Keele St",
    "sg:city":"North York",
    "sg:classifiers":[
        {
            "category":"Banks & Credit Unions",
            "subcategory":"Bank",
            "type":"Services"
        }
    ],
    "sg:phone":"+1 416 636 2030",
    "sg:postcode":"M3M 2G2",
    "sg:province":"ON",
    "wof:name":"Royal Bank Financial Group",
    "wof:placetype":"venue"
},
  "geometry": {"coordinates":[-79.482383728,43.7274093628],"type":"Point"}
}