{
  "type": "Feature",
  "properties": {
    "addr:full":"4256 Eton St Burnaby BC V5C 1K3",
    "addr:housenumber":"4256",
    "addr:postcode":"v5c 1k3",
    "addr:street":"Eton St",
    "iso:country":"CA",
    "sg:address":"4256 Eton St",
    "sg:city":"Burnaby",
    "sg:classifiers":[
        {
            "category":"Building & Trades",
            "subcategory":"Electrical",
            "type":"Services"
        }
    ],
    "sg:phone":"+1 604 299 3660",
    "sg:postcode":"V5C 1K3",
    "sg:province":"BC",
    "sg:tags":[
        "electric",
        "contractor"
    ],
    "wof:name":"Charles Electric Ltd",
    "wof:placetype":"venue"
},
  "geometry": {"coordinates":[-123.00942999999999,49.287224],"type":"Point"}
}