{
  "type": "Feature",
  "properties": {
    "addr:full":"3800 Big Rideau Lake Rd Portland ON K0G 1V0",
    "addr:housenumber":"3800",
    "addr:postcode":"k0g 1v0",
    "addr:street":"Big Rideau Lake Rd",
    "iso:country":"CA",
    "sg:address":"3800 Big Rideau Lake Rd",
    "sg:city":"Portland",
    "sg:classifiers":[
        {
            "category":"Travel",
            "subcategory":"Hotels & Motels",
            "type":"Entertainment"
        }
    ],
    "sg:phone":"+1 613 272 2791",
    "sg:postcode":"K0G 1V0",
    "sg:province":"ON",
    "sg:tags":[
        "cottage",
        "cabin"
    ],
    "wof:name":"Waterways Campground",
    "wof:placetype":"venue"
},
  "geometry": {"coordinates":[-76.27153,44.698116],"type":"Point"}
}