{
  "type": "Feature",
  "properties": {
    "addr:full":"66 Brock St E Uxbridge ON L9P 1K3",
    "addr:housenumber":"66",
    "addr:postcode":"l9p 1k3",
    "addr:street":"Brock St E",
    "iso:country":"CA",
    "sg:address":"66 Brock St E",
    "sg:city":"Uxbridge",
    "sg:classifiers":[
        {
            "category":"Retail",
            "subcategory":"Auto Repair",
            "type":"Services"
        }
    ],
    "sg:phone":"+1 905 862 0539",
    "sg:postcode":"L9P 1K3",
    "sg:province":"ON",
    "sg:tags":[
        "repairing",
        "automobile"
    ],
    "wof:name":"Vision Automotive Svc",
    "wof:placetype":"venue"
},
  "geometry": {"coordinates":[-79.1169662476,44.1099967957],"type":"Point"}
}