{
  "type": "Feature",
  "properties": {
    "addr:full":"40 Wellington St N Hamilton ON L8R 1M8",
    "addr:housenumber":"40",
    "addr:postcode":"l8r 1m8",
    "addr:street":"Wellington St N",
    "iso:country":"CA",
    "sg:address":"40 Wellington St N",
    "sg:city":"Hamilton",
    "sg:classifiers":[
        {
            "category":"Social Services",
            "type":"Services"
        }
    ],
    "sg:phone":"+1 905 522 9767",
    "sg:postcode":"L8R 1M8",
    "sg:province":"ON",
    "sg:tags":[
        "organization",
        "welfare"
    ],
    "wof:name":"Wellington Psychiatric Outrch",
    "wof:placetype":"venue"
},
  "geometry": {"coordinates":[-79.8586273193,43.2546081543],"type":"Point"}
}