{
  "type": "Feature",
  "properties": {
    "addr:full":"Burnaby BC V5C 6C6",
    "addr:postcode":"v5c 6c6",
    "iso:country":"CA",
    "sg:city":"Burnaby",
    "sg:classifiers":[
        {
            "category":"Wholesale",
            "subcategory":"Electrical",
            "type":"Manufacturing & Wholesale Goods"
        }
    ],
    "sg:phone":"+1 604 918 6300",
    "sg:postcode":"V5C 6C6",
    "sg:province":"BC",
    "sg:tags":[
        "video",
        "telecommunication",
        "conferencing"
    ],
    "wof:name":"Convedia Corp",
    "wof:placetype":"venue"
},
  "geometry": {"coordinates":[-123.011421,49.259697],"type":"Point"}
}