{
  "type": "Feature",
  "properties": {
    "iso:country":"CA",
    "sg:city":"Vancouver",
    "sg:classifiers":[
        {
            "category":"Communications",
            "subcategory":"Film & Video Production",
            "type":"Services"
        }
    ],
    "sg:phone":"+1 604 696 0820",
    "sg:postcode":"V6B 1T6",
    "sg:province":"BC",
    "sg:tags":[
        "motion",
        "picture",
        "studio",
        "producer"
    ],
    "wof:name":"Aviv Films",
    "wof:placetype":"venue"
},
  "geometry": {"coordinates":[-123.111969,49.282738],"type":"Point"}
}