{
  "type": "Feature",
  "properties": {
    "addr:full":"287 Mount Pleasant St Brantford ON N3T 1V2",
    "addr:housenumber":"287",
    "addr:postcode":"n3t 1v2",
    "addr:street":"Mount Pleasant St",
    "iso:country":"CA",
    "sg:address":"287 Mount Pleasant St",
    "sg:city":"Brantford",
    "sg:classifiers":[
        {
            "category":"Organizations",
            "subcategory":"Religious Organization",
            "type":"Services"
        }
    ],
    "sg:phone":"+1 519 759 2495",
    "sg:postcode":"N3T 1V2",
    "sg:province":"ON",
    "sg:tags":[
        "church"
    ],
    "wof:name":"Farringdon Independent Church",
    "wof:placetype":"venue"
},
  "geometry": {"coordinates":[-80.275894165,43.1161193848],"type":"Point"}
}