{
  "type": "Feature",
  "properties": {
    "addr:full":"133 Rue Saint-Georges Granby QC J2G 2Z9",
    "addr:housenumber":"133",
    "addr:postcode":"j2g 2z9",
    "addr:street":"Rue Saint-Georges",
    "iso:country":"CA",
    "sg:address":"133 Rue Saint-Georges",
    "sg:city":"Granby",
    "sg:classifiers":[
        {
            "category":"Professional",
            "subcategory":"Lawyer & Legal Services",
            "type":"Services"
        }
    ],
    "sg:phone":"+1 450 776 6766",
    "sg:postcode":"J2G 2Z9",
    "sg:province":"QC",
    "sg:tags":[
        "attorney"
    ],
    "wof:name":"Nadeau, Line",
    "wof:placetype":"venue"
},
  "geometry": {"coordinates":[-72.725578,45.398266],"type":"Point"}
}