{
  "type": "Feature",
  "properties": {
    "addr:full":"4 Park Ave Lac Du Bonnet MB R0E 1A0",
    "addr:housenumber":"4",
    "addr:postcode":"r0e 1a0",
    "addr:street":"Park Ave",
    "iso:country":"CA",
    "sg:address":"4 Park Ave",
    "sg:city":"Lac Du Bonnet",
    "sg:classifiers":[
        {
            "category":"Professional",
            "subcategory":"Management & Consulting",
            "type":"Services"
        }
    ],
    "sg:phone":"+1 204 345 2686",
    "sg:postcode":"R0E 1A0",
    "sg:province":"MB",
    "sg:tags":[
        "consultant",
        "educational"
    ],
    "wof:name":"Just Training Corp",
    "wof:placetype":"venue"
},
  "geometry": {"coordinates":[-96.05912780760001,50.2581634521],"type":"Point"}
}