{
  "type": "Feature",
  "properties": {
    "iso:country":"CA",
    "sg:address":"1440 Barberry Dr",
    "sg:city":"Port Coquitlam",
    "sg:classifiers":[
        {
            "category":"Social Services",
            "subcategory":"Job Training",
            "type":"Services"
        }
    ],
    "sg:phone":"+1 604 941 9022",
    "sg:postcode":"V3B 1G3",
    "sg:province":"BC",
    "sg:tags":[
        "rehabilitation"
    ],
    "wof:name":"Barberry Lodge",
    "wof:placetype":"venue"
},
  "geometry": {"coordinates":[-122.753112793,49.2651672363],"type":"Point"}
}