{
  "type": "Feature",
  "properties": {
    "addr:full":"265 Hysert Rd Grimsby ON L3M 4E7",
    "addr:housenumber":"265",
    "addr:postcode":"l3m 4e7",
    "addr:street":"Hysert Rd",
    "iso:country":"CA",
    "sg:address":"265 Hysert Rd",
    "sg:city":"Grimsby",
    "sg:classifiers":[
        {
            "category":"Building & Trades",
            "subcategory":"Electrical",
            "type":"Services"
        }
    ],
    "sg:phone":"+1 905 643 6699",
    "sg:postcode":"L3M 4E7",
    "sg:province":"ON",
    "sg:tags":[
        "electric",
        "contractor"
    ],
    "wof:name":"R K Electric",
    "wof:placetype":"venue"
},
  "geometry": {"coordinates":[-79.6257476807,43.1797294617],"type":"Point"}
}