{
  "type": "Feature",
  "properties": {
    "addr:full":"8946 Rte 1 Meteghan River NS B0W 2L0",
    "addr:housenumber":"8946",
    "addr:postcode":"b0w 2l0",
    "addr:street":"Rte 1",
    "iso:country":"CA",
    "sg:address":"8946 Rte 1",
    "sg:city":"Meteghan River",
    "sg:classifiers":[
        {
            "category":"Restaurant",
            "type":"Food & Drink"
        }
    ],
    "sg:phone":"+1 902 645 3660",
    "sg:postcode":"B0W 2L0",
    "sg:province":"NS",
    "wof:name":"Taverne Acadienne Ltd",
    "wof:placetype":"venue"
},
  "geometry": {"coordinates":[-66.14347100000001,44.215351],"type":"Point"}
}