{
  "type": "Feature",
  "properties": {
    "addr:full":"3443 Rue Du Transport Jonquiere QC G7X 0B6",
    "addr:housenumber":"3443",
    "addr:postcode":"g7x 0b6",
    "addr:street":"Rue Du Transport",
    "iso:country":"CA",
    "sg:address":"3443 Rue Du Transport",
    "sg:city":"Jonquiere",
    "sg:classifiers":[
        {
            "category":"Building & Trades",
            "subcategory":"Construction",
            "type":"Services"
        }
    ],
    "sg:phone":"+1 418 542 2100",
    "sg:postcode":"G7X 0B6",
    "sg:province":"QC",
    "sg:tags":[
        "excavating",
        "contractor"
    ],
    "wof:name":"Excavation Marc Belley",
    "wof:placetype":"venue"
},
  "geometry": {"coordinates":[-71.229553,48.404202],"type":"Point"}
}