{
  "type": "Feature",
  "properties": {
    "addr:full":"632 Main St Hampton NB E5N 6C5",
    "addr:housenumber":"632",
    "addr:postcode":"e5n 6c5",
    "addr:street":"Main St",
    "iso:country":"CA",
    "sg:address":"632 Main St",
    "sg:city":"Hampton",
    "sg:classifiers":[
        {
            "category":"Food & Beverages",
            "subcategory":"Groceries & Convenience Stores",
            "type":"Retail Goods"
        }
    ],
    "sg:phone":"+1 506 832 7000",
    "sg:postcode":"E5N 6C5",
    "sg:province":"NB",
    "wof:name":"Hampton Mainway",
    "wof:placetype":"venue"
},
  "geometry": {"coordinates":[-65.82781982420001,45.5250701904],"type":"Point"}
}