{
  "type": "Feature",
  "properties": {
    "addr:full":"Truro NS B2N 5N6",
    "addr:postcode":"b2n 5n6",
    "iso:country":"CA",
    "sg:city":"Truro",
    "sg:classifiers":[
        {
            "category":"Food & Beverages",
            "subcategory":"Bakery",
            "type":"Retail Goods"
        }
    ],
    "sg:phone":"+1 902 893 1103",
    "sg:postcode":"B2N 5N6",
    "sg:province":"NS",
    "sg:tags":[
        "tea",
        "coffee",
        "doughnut"
    ],
    "wof:name":"Tim Hortons",
    "wof:placetype":"venue"
},
  "geometry": {"coordinates":[-63.303238,45.369549],"type":"Point"}
}