{
  "type": "Feature",
  "properties": {
    "addr:full":"318 15E Av Deux-Montagnes QC J7R 3X5",
    "addr:housenumber":"318",
    "addr:postcode":"j7r 3x5",
    "addr:street":"15E Av",
    "iso:country":"CA",
    "sg:address":"318 15E Av",
    "sg:city":"Deux-Montagnes",
    "sg:classifiers":[
        {
            "category":"Freight",
            "type":"Transportation"
        }
    ],
    "sg:phone":"+1 450 472 4355",
    "sg:postcode":"J7R 3X5",
    "sg:province":"QC",
    "sg:tags":[
        "trucking"
    ],
    "wof:name":"Camionnage Mcdk Inc",
    "wof:placetype":"venue"
},
  "geometry": {"coordinates":[-73.902748,45.540901],"type":"Point"}
}