{
  "type": "Feature",
  "properties": {
    "addr:full":"261 277 Rte Standon QC G0R 4L0",
    "addr:housenumber":"277",
    "addr:postcode":"g0r 4l0",
    "addr:street":"Rte Standon",
    "iso:country":"CA",
    "sg:address":"261 277 Rte",
    "sg:city":"Standon",
    "sg:classifiers":[
        {
            "category":"Freight",
            "type":"Transportation"
        }
    ],
    "sg:phone":"+1 418 642 2438",
    "sg:postcode":"G0R 4L0",
    "sg:province":"QC",
    "sg:tags":[
        "building",
        "house",
        "excavating",
        "mover",
        "contractor"
    ],
    "wof:name":"Excavations St-Leon Inc",
    "wof:placetype":"venue"
},
  "geometry": {"coordinates":[-70.618416,46.47913],"type":"Point"}
}