{
  "type": "Feature",
  "properties": {
    "iso:country":"CA",
    "sg:address":"66 Main St E",
    "sg:city":"Dundalk",
    "sg:classifiers":[
        {
            "category":"Personal",
            "subcategory":"Beauty Salon",
            "type":"Services"
        }
    ],
    "sg:phone":"+1 519 923 2514",
    "sg:postcode":"N0C 1B0",
    "sg:province":"ON",
    "wof:name":"Hair Shoppe",
    "wof:placetype":"venue"
},
  "geometry": {"coordinates":[-80.3922653198,44.1690597534],"type":"Point"}
}