{
  "type": "Feature",
  "properties": {
    "iso:country":"CA",
    "sg:city":"Saint-Romuald",
    "sg:classifiers":[
        {
            "category":"Organizations",
            "subcategory":"Professional Association",
            "type":"Services"
        }
    ],
    "sg:phone":"+1 418 839 6888",
    "sg:postcode":"G6W 5M6",
    "sg:province":"QC",
    "sg:tags":[
        "social",
        "welfare"
    ],
    "wof:name":"Centre Jeunesse Chaudiere Appa",
    "wof:placetype":"venue"
},
  "geometry": {"coordinates":[-71.267616272,46.7327461243],"type":"Point"}
}