{
  "type": "Feature",
  "properties": {
    "addr:full":"203 Boston Rd Longlac ON P0T 2A0",
    "addr:housenumber":"203",
    "addr:postcode":"p0t 2a0",
    "addr:street":"Boston Rd",
    "iso:country":"CA",
    "sg:address":"203 Boston Rd",
    "sg:city":"Longlac",
    "sg:classifiers":[
        {
            "category":"Organizations",
            "subcategory":"Professional Association",
            "type":"Services"
        }
    ],
    "sg:phone":"+1 807 876 4214",
    "sg:postcode":"P0T 2A0",
    "sg:province":"ON",
    "sg:tags":[
        "government"
    ],
    "wof:name":"Ginoogaming Family Support",
    "wof:placetype":"venue"
},
  "geometry": {"coordinates":[-86.535049,49.780537],"type":"Point"}
}