{
  "type": "Feature",
  "properties": {
    "addr:full":"6664 Ch DE LA Cote-Saint-Luc Montreal QC H4V 1H1",
    "addr:housenumber":"6664",
    "addr:postcode":"h4v 1h1",
    "addr:street":"Ch De La Cote-Saint-Luc",
    "iso:country":"CA",
    "sg:address":"6664 Ch DE LA Cote-Saint-Luc",
    "sg:city":"Montreal",
    "sg:classifiers":[
        {
            "category":"Food & Beverages",
            "subcategory":"Groceries & Convenience Stores",
            "type":"Retail Goods"
        }
    ],
    "sg:phone":"+1 514 486 1282",
    "sg:postcode":"H4V 1H1",
    "sg:province":"QC",
    "wof:name":"Mano Depanneur & Fumee Plus",
    "wof:placetype":"venue"
},
  "geometry": {"coordinates":[-73.649658,45.469654],"type":"Point"}
}