{
  "type": "Feature",
  "properties": {
    "addr:full":"37 Miller St Parry Sound ON P2A 1S9",
    "addr:housenumber":"37",
    "addr:postcode":"p2a 1s9",
    "addr:street":"Miller St",
    "iso:country":"CA",
    "sg:address":"37 Miller St",
    "sg:city":"Parry Sound",
    "sg:classifiers":[
        {
            "category":"Personal",
            "type":"Services"
        }
    ],
    "sg:phone":"+1 705 746 7735",
    "sg:postcode":"P2A 1S9",
    "sg:province":"ON",
    "sg:tags":[
        "dating"
    ],
    "wof:name":"Northern Connections",
    "wof:placetype":"venue"
},
  "geometry": {"coordinates":[-80.03228759770001,45.3461074829],"type":"Point"}
}