{
  "type": "Feature",
  "properties": {
    "iso:country":"CA",
    "sg:address":"3240 Smith Dr",
    "sg:city":"Armstrong",
    "sg:classifiers":[
        {
            "category":"Restaurant",
            "type":"Food & Drink"
        }
    ],
    "sg:phone":"+1 250 546 1948",
    "sg:postcode":"V0E 1B1",
    "sg:province":"BC",
    "wof:name":"Mc Donald's",
    "wof:placetype":"venue"
},
  "geometry": {"coordinates":[-119.183952331,50.4465827942],"type":"Point"}
}