{
  "type": "Feature",
  "properties": {
    "addr:full":"7925 127E Rue Saint-Georges-Est QC G5Y 5B9",
    "addr:housenumber":"7925",
    "addr:postcode":"g5y 5b9",
    "addr:street":"127E Rue Saint-Georges-Est",
    "iso:country":"CA",
    "sg:address":"7925 127E Rue",
    "sg:city":"Saint-Georges-Est",
    "sg:classifiers":[
        {
            "category":"Organizations",
            "subcategory":"Professional Association",
            "type":"Services"
        }
    ],
    "sg:phone":"+1 418 228 4341",
    "sg:postcode":"G5Y 5B9",
    "sg:province":"QC",
    "sg:tags":[
        "club"
    ],
    "wof:name":"Club Rendez-Vous Moto-Neige",
    "wof:placetype":"venue"
},
  "geometry": {"coordinates":[-70.6133346558,46.1560325623],"type":"Point"}
}