{
  "type": "Feature",
  "properties": {
    "addr:full":"680 Foothill Rd SW Salmon Arm BC V1E 1T6",
    "addr:housenumber":"680",
    "addr:postcode":"v1e 1t6",
    "addr:street":"Foothill Rd Sw",
    "iso:country":"CA",
    "sg:address":"680 Foothill Rd SW",
    "sg:city":"Salmon Arm",
    "sg:classifiers":[
        {
            "category":"Retail",
            "subcategory":"Animal Services",
            "type":"Services"
        }
    ],
    "sg:phone":"+1 250 833 1028",
    "sg:postcode":"V1E 1T6",
    "sg:province":"BC",
    "sg:tags":[
        "pet",
        "grooming",
        "washing"
    ],
    "wof:name":"Foothill Dog & Cat Grooming",
    "wof:placetype":"venue"
},
  "geometry": {"coordinates":[-119.29511261,50.6843223572],"type":"Point"}
}