{
  "type": "Feature",
  "properties": {
    "iso:country":"CA",
    "sg:address":"260 Rue Alexandre",
    "sg:city":"Sherbrooke",
    "sg:classifiers":[
        {
            "category":"Personal",
            "subcategory":"Barber",
            "type":"Services"
        }
    ],
    "sg:phone":"+1 819 822 0228",
    "sg:postcode":"J1H 4S7",
    "sg:province":"QC",
    "wof:name":"Salon Alexandre",
    "wof:placetype":"venue"
},
  "geometry": {"coordinates":[-71.8916397095,45.3965644836],"type":"Point"}
}