{
  "type": "Feature",
  "properties": {
    "addr:full":"81 Rue Child Coaticook QC J1A 2B2",
    "addr:housenumber":"81",
    "addr:postcode":"j1a 2b2",
    "addr:street":"Rue Child",
    "iso:country":"CA",
    "sg:address":"81 Rue Child",
    "sg:city":"Coaticook",
    "sg:classifiers":[
        {
            "category":"Food & Beverages",
            "subcategory":"Bakery",
            "type":"Retail Goods"
        }
    ],
    "sg:phone":"+1 819 849 3074",
    "sg:postcode":"J1A 2B2",
    "sg:province":"QC",
    "sg:tags":[
        "baker"
    ],
    "wof:name":"Patisserie Coaticook Inc",
    "wof:placetype":"venue"
},
  "geometry": {"coordinates":[-71.805008,45.133568],"type":"Point"}
}