{
  "type": "Feature",
  "properties": {
    "addr:full":"8370 Ch DE LA Cote-Saint-Luc Montreal QC H4W 1S3",
    "addr:postcode":"8370;h4w 1s3",
    "addr:street":"Ch De La Cote-Saint-Luc",
    "iso:country":"CA",
    "sg:address":"8370 Ch DE LA Cote-Saint-Luc",
    "sg:city":"Montreal",
    "sg:classifiers":[
        {
            "category":"Sports & Exercise",
            "subcategory":"Golf",
            "type":"Entertainment"
        }
    ],
    "sg:phone":"+1 514 488 6612",
    "sg:postcode":"H4W 1S3",
    "sg:province":"QC",
    "sg:tags":[
        "course"
    ],
    "wof:name":"Club DE Golf Meadowbrook",
    "wof:placetype":"venue"
},
  "geometry": {"coordinates":[-73.66966247560001,45.4541816711],"type":"Point"}
}