{
  "type": "Feature",
  "properties": {
    "addr:full":"1828 Danforth Ave Toronto ON M4C 1H8",
    "addr:housenumber":"1828",
    "addr:postcode":"m4c 1h8",
    "addr:street":"Danforth Ave",
    "iso:country":"CA",
    "sg:address":"1828 Danforth Ave",
    "sg:city":"Toronto",
    "sg:classifiers":[
        {
            "category":"Insurance",
            "subcategory":"Insurance Agent",
            "type":"Services"
        }
    ],
    "sg:phone":"+1 416 469 4111",
    "sg:postcode":"M4C 1H8",
    "sg:province":"ON",
    "sg:tags":[
        "control",
        "pest"
    ],
    "wof:name":"Aetna Pest Control Ltd",
    "wof:placetype":"venue"
},
  "geometry": {"coordinates":[-79.3179855347,43.6846923828],"type":"Point"}
}