{
  "type": "Feature",
  "properties": {
    "addr:full":"1231 Pembroke St W Pembroke ON K8A 5R3",
    "addr:housenumber":"1231",
    "addr:postcode":"k8a 5r3",
    "addr:street":"Pembroke St W",
    "iso:country":"CA",
    "sg:address":"1231 Pembroke St W",
    "sg:city":"Pembroke",
    "sg:classifiers":[
        {
            "category":"Shopping",
            "subcategory":"Pharmacy",
            "type":"Retail Goods"
        }
    ],
    "sg:phone":"+1 613 735 1079",
    "sg:postcode":"K8A 5R3",
    "sg:province":"ON",
    "wof:name":"Mulvihill Drug Mart",
    "wof:placetype":"venue"
},
  "geometry": {"coordinates":[-77.1471710205,45.832824707],"type":"Point"}
}