{
  "type": "Feature",
  "properties": {
    "addr:full":"200 Richmond St Charlottetown PE C1A 1J2",
    "addr:housenumber":"200",
    "addr:postcode":"c1a 1j2",
    "addr:street":"Richmond St",
    "iso:country":"CA",
    "sg:address":"200 Richmond St",
    "sg:city":"Charlottetown",
    "sg:classifiers":[
        {
            "category":"Social Services",
            "subcategory":"Child Care",
            "type":"Services"
        }
    ],
    "sg:phone":"+1 902 566 9259",
    "sg:postcode":"C1A 1J2",
    "sg:province":"PE",
    "sg:tags":[
        "recreation",
        "center",
        "bowling"
    ],
    "wof:name":"Basilica Recreation Ctr Child",
    "wof:placetype":"venue"
},
  "geometry": {"coordinates":[-63.1248016357,46.2349433899],"type":"Point"}
}