{
  "type": "Feature",
  "properties": {
    "iso:country":"CA",
    "sg:address":"11 Cann St",
    "sg:city":"Huntsville",
    "sg:classifiers":[
        {
            "category":"Food & Beverages",
            "subcategory":"Liquor & Beverages",
            "type":"Retail Goods"
        }
    ],
    "sg:phone":"+1 705 789 2741",
    "sg:postcode":"P1H 1H3",
    "sg:province":"ON",
    "sg:tags":[
        "beer",
        "ale"
    ],
    "wof:name":"Beer Store",
    "wof:placetype":"venue"
},
  "geometry": {"coordinates":[-79.2127990723,45.329826355],"type":"Point"}
}