{
  "type": "Feature",
  "properties": {
    "iso:country":"CA",
    "sg:address":"2025 Rue Monterey",
    "sg:city":"Laval",
    "sg:classifiers":[
        {
            "category":"Retail",
            "subcategory":"Auto Repair",
            "type":"Services"
        }
    ],
    "sg:phone":"+1 450 688 5781",
    "sg:postcode":"H7L 3T6",
    "sg:province":"QC",
    "sg:tags":[
        "trailer"
    ],
    "wof:name":"Services DE Reparation Rb",
    "wof:placetype":"venue"
},
  "geometry": {"coordinates":[-73.7542953491,45.58411026],"type":"Point"}
}