{
  "type": "Feature",
  "properties": {
    "addr:full":"Regina SK S4P 0R7",
    "addr:postcode":"s4p 0r7",
    "iso:country":"CA",
    "sg:city":"Regina",
    "sg:classifiers":[
        {
            "category":"Health Services",
            "subcategory":"Optometrist",
            "type":"Services"
        }
    ],
    "sg:phone":"+1 306 525 0587",
    "sg:postcode":"S4P 0R7",
    "sg:province":"SK",
    "wof:name":"Indepentant Optical",
    "wof:placetype":"venue"
},
  "geometry": {"coordinates":[-104.609573,50.447334],"type":"Point"}
}