{
  "type": "Feature",
  "properties": {
    "addr:full":"1341 4 Rang W Val-Alain QC G0S 3H0",
    "addr:housenumber":"1341 4",
    "addr:postcode":"g0s 3h0",
    "addr:street":"Rang W Val-Alain",
    "iso:country":"CA",
    "sg:address":"1341 4 Rang W",
    "sg:city":"Val-Alain",
    "sg:classifiers":[
        {
            "category":"Wholesale",
            "subcategory":"Machinery & Supplies",
            "type":"Manufacturing & Wholesale Goods"
        }
    ],
    "sg:phone":"+1 418 744 3512",
    "sg:postcode":"G0S 3H0",
    "sg:province":"QC",
    "wof:name":"Entreprises Perfort Inc",
    "wof:placetype":"venue"
},
  "geometry": {"coordinates":[-71.797539,46.421768],"type":"Point"}
}