{
  "type": "Feature",
  "properties": {
    "iso:country":"CA",
    "sg:address":"520 Cosburn Ave",
    "sg:city":"East York",
    "sg:classifiers":[
        {
            "category":"Education",
            "subcategory":"School",
            "type":"Public Place"
        }
    ],
    "sg:phone":"+1 416 396 2335",
    "sg:postcode":"M4J 2P1",
    "sg:province":"ON",
    "wof:name":"Cosburn Middle School",
    "wof:placetype":"venue"
},
  "geometry": {"coordinates":[-79.33094024659999,43.6936531067],"type":"Point"}
}