{
  "type": "Feature",
  "properties": {
    "addr:full":"22 Hamilton Ave N Ottawa ON K1Y 1B6",
    "addr:housenumber":"22",
    "addr:postcode":"k1y 1b6",
    "addr:street":"Hamilton Ave N",
    "iso:country":"CA",
    "sg:address":"22 Hamilton Ave N",
    "sg:city":"Ottawa",
    "sg:classifiers":[
        {
            "category":"Communications",
            "subcategory":"Film & Video Production",
            "type":"Services"
        }
    ],
    "sg:phone":"+1 613 729 8987",
    "sg:postcode":"K1Y 1B6",
    "sg:province":"ON",
    "sg:tags":[
        "duplication",
        "tape"
    ],
    "wof:name":"Precision Transfer Techs",
    "wof:placetype":"venue"
},
  "geometry": {"coordinates":[-75.7307052612,45.401058197],"type":"Point"}
}