{
  "type": "Feature",
  "properties": {
    "iso:country":"CA",
    "sg:address":"240 Rue Lafontaine",
    "sg:city":"Riviere-Du-Loup",
    "sg:classifiers":[
        {
            "category":"Shopping",
            "subcategory":"Pharmacy",
            "type":"Retail Goods"
        }
    ],
    "sg:phone":"+1 418 862 6326",
    "sg:postcode":"G5R 3A7",
    "sg:province":"QC",
    "wof:name":"Jean Coutu Pharmacie",
    "wof:placetype":"venue"
},
  "geometry": {"coordinates":[-69.5372619629,47.8344535828],"type":"Point"}
}