{
  "type": "Feature",
  "properties": {
    "iso:country":"CA",
    "sg:address":"2230 Springer Ave",
    "sg:city":"Burnaby",
    "sg:classifiers":[
        {
            "category":"Wholesale",
            "subcategory":"Durable Goods & Equipment",
            "type":"Manufacturing & Wholesale Goods"
        }
    ],
    "sg:phone":"+1 604 294 8591",
    "sg:postcode":"V5B 3M7",
    "sg:province":"BC",
    "sg:tags":[
        "room",
        "drafting"
    ],
    "wof:name":"Canadian Drafting & Engr Supls",
    "wof:placetype":"venue"
},
  "geometry": {"coordinates":[-122.98744201700001,49.2638549805],"type":"Point"}
}