{
  "type": "Feature",
  "properties": {
    "addr:full":"654 Main St E Hamilton ON L8M 1J8",
    "addr:housenumber":"654",
    "addr:postcode":"l8m 1j8",
    "addr:street":"Main St E",
    "iso:country":"CA",
    "sg:address":"654 Main St E",
    "sg:city":"Hamilton",
    "sg:classifiers":[
        {
            "category":"Utilities",
            "subcategory":"Telephone",
            "type":"Services"
        }
    ],
    "sg:phone":"+1 905 545 8184",
    "sg:postcode":"L8M 1J8",
    "sg:province":"ON",
    "sg:tags":[
        "distance",
        "long"
    ],
    "wof:name":"Mann Telecommunications",
    "wof:placetype":"venue"
},
  "geometry": {"coordinates":[-79.84425400000001,43.248692],"type":"Point"}
}