{
  "type": "Feature",
  "properties": {
    "addr:full":"1092 Dupont St Toronto ON M6H 1Z6",
    "addr:housenumber":"1092",
    "addr:postcode":"m6h 1z6",
    "addr:street":"Dupont St",
    "iso:country":"CA",
    "sg:address":"1092 Dupont St",
    "sg:city":"Toronto",
    "sg:classifiers":[
        {
            "category":"Building & Trades",
            "subcategory":"Construction",
            "type":"Services"
        }
    ],
    "sg:phone":"+1 416 573 9640",
    "sg:postcode":"M6H 1Z6",
    "sg:province":"ON",
    "sg:tags":[
        "masonry",
        "contractor",
        "general"
    ],
    "wof:name":"A Restoration Specialist",
    "wof:placetype":"venue"
},
  "geometry": {"coordinates":[-79.436104,43.669155],"type":"Point"}
}