{
  "type": "Feature",
  "properties": {
    "addr:full":"119 Wellington St Stratford ON N5A 2L4",
    "addr:housenumber":"119",
    "addr:postcode":"n5a 2l4",
    "addr:street":"Wellington St",
    "iso:country":"CA",
    "sg:address":"119 Wellington St",
    "sg:city":"Stratford",
    "sg:classifiers":[
        {
            "category":"Personal",
            "subcategory":"Beauty Salon",
            "type":"Services"
        }
    ],
    "sg:phone":"+1 519 271 7766",
    "sg:postcode":"N5A 2L4",
    "sg:province":"ON",
    "wof:name":"Marion's Hair Design Inc",
    "wof:placetype":"venue"
},
  "geometry": {"coordinates":[-80.98388671879999,43.3682441711],"type":"Point"}
}