{
  "type": "Feature",
  "properties": {
    "addr:full":"1400 Ch Du Fer-A-Cheval Sainte-Julie QC J3E 1Y2",
    "addr:housenumber":"1400",
    "addr:postcode":"j3e 1y2",
    "addr:street":"Ch Du Fer-A-Cheval",
    "iso:country":"CA",
    "sg:address":"1400 Ch Du Fer-A-Cheval",
    "sg:city":"Sainte-Julie",
    "sg:classifiers":[
        {
            "category":"Wholesale",
            "subcategory":"Durable Goods & Equipment",
            "type":"Manufacturing & Wholesale Goods"
        }
    ],
    "sg:phone":"+1 450 649 1516",
    "sg:postcode":"J3E 1Y2",
    "sg:province":"QC",
    "sg:tags":[
        "magnet",
        "packaging",
        "magnetic",
        "machinery",
        "devices"
    ],
    "wof:name":"Richard Gaston Inc",
    "wof:placetype":"venue"
},
  "geometry": {"coordinates":[-73.32733899999999,45.592762],"type":"Point"}
}