{
  "type": "Feature",
  "properties": {
    "addr:full":"11220 Voyageur Way Richmond BC V6X 3E1",
    "addr:housenumber":"11220",
    "addr:postcode":"v6x 3e1",
    "addr:street":"Voyageur Way",
    "iso:country":"CA",
    "sg:address":"11220 Voyageur Way",
    "sg:city":"Richmond",
    "sg:classifiers":[
        {
            "category":"Home & Garden",
            "subcategory":"Home Furnishings",
            "type":"Retail Goods"
        }
    ],
    "sg:phone":"+1 604 303 0628",
    "sg:postcode":"V6X 3E1",
    "sg:province":"BC",
    "sg:tags":[
        "curtain",
        "made",
        "drapery"
    ],
    "wof:name":"United Bedding Ltd",
    "wof:placetype":"venue"
},
  "geometry": {"coordinates":[-123.09967041,49.1912193298],"type":"Point"}
}