{
  "type": "Feature",
  "properties": {
    "addr:full":"7457 Rte Transcanadienne Saint-Laurent QC H4T 1T3",
    "addr:housenumber":"7457",
    "addr:postcode":"h4t 1t3",
    "addr:street":"Rte Transcanadienne",
    "iso:country":"CA",
    "sg:address":"7457 Rte Transcanadienne",
    "sg:city":"Saint-Laurent",
    "sg:classifiers":[
        {
            "category":"Wholesale",
            "subcategory":"Electrical",
            "type":"Manufacturing & Wholesale Goods"
        }
    ],
    "sg:phone":"+1 514 336 6867",
    "sg:postcode":"H4T 1T3",
    "sg:province":"QC",
    "sg:tags":[
        "parts",
        "electric",
        "motor"
    ],
    "wof:name":"Snowdon Electric",
    "wof:placetype":"venue"
},
  "geometry": {"coordinates":[-73.710105896,45.4894104004],"type":"Point"}
}