{
  "type": "Feature",
  "properties": {
    "iso:country":"CA",
    "sg:address":"24 Wellington St",
    "sg:city":"Orangeville",
    "sg:classifiers":[
        {
            "category":"Retail",
            "subcategory":"Auto Repair",
            "type":"Services"
        }
    ],
    "sg:phone":"+1 519 941 5200",
    "sg:postcode":"L9W 2L5",
    "sg:province":"ON",
    "sg:tags":[
        "wrecker"
    ],
    "wof:name":"Royal Towing",
    "wof:placetype":"venue"
},
  "geometry": {"coordinates":[-80.091782,43.91692],"type":"Point"}
}