{
  "type": "Feature",
  "properties": {
    "addr:full":"9636 109 Ave Grande Prairie AB T8V 1R2",
    "addr:housenumber":"9636",
    "addr:postcode":"t8v 1r2",
    "addr:street":"109 Ave",
    "iso:country":"CA",
    "sg:address":"9636 109 Ave",
    "sg:city":"Grande Prairie",
    "sg:classifiers":[
        {
            "category":"Education",
            "subcategory":"School",
            "type":"Public Place"
        }
    ],
    "sg:phone":"+1 780 532 4698",
    "sg:postcode":"T8V 1R2",
    "sg:province":"AB",
    "wof:name":"St Clement Catholic School",
    "wof:placetype":"venue"
},
  "geometry": {"coordinates":[-118.786170959,55.1791305542],"type":"Point"}
}