{
  "type": "Feature",
  "properties": {
    "addr:full":"16 Mill St E Milverton ON N0K 1M0",
    "addr:housenumber":"16",
    "addr:postcode":"n0k 1m0",
    "addr:street":"Mill St;Milverton",
    "iso:country":"CA",
    "sg:address":"16 Mill St E",
    "sg:city":"Milverton",
    "sg:classifiers":[
        {
            "category":"Utilities",
            "subcategory":"Telephone",
            "type":"Services"
        }
    ],
    "sg:phone":"+1 519 595 8331",
    "sg:postcode":"N0K 1M0",
    "sg:province":"ON",
    "sg:tags":[
        "company"
    ],
    "wof:name":"Mornington Communications Coop",
    "wof:placetype":"venue"
},
  "geometry": {"coordinates":[-80.9208145142,43.5653686523],"type":"Point"}
}