{
  "type": "Feature",
  "properties": {
    "addr:full":"818 Rue Du Centenaire Paquetville NB E8R 1B8",
    "addr:housenumber":"818",
    "addr:postcode":"e8r 1b8",
    "addr:street":"Rue Du Centenaire Paquetville",
    "iso:country":"CA",
    "sg:address":"818 Rue Du Centenaire",
    "sg:city":"Paquetville",
    "sg:classifiers":[
        {
            "category":"Farming",
            "subcategory":"Aquatic Farm",
            "type":"Manufacturing & Wholesale Goods"
        }
    ],
    "sg:phone":"+1 506 764 9010",
    "sg:postcode":"E8R 1B8",
    "sg:province":"NB",
    "sg:tags":[
        "hatchery",
        "consultant",
        "fish",
        "fishery"
    ],
    "wof:name":"Elite Consultant Inc",
    "wof:placetype":"venue"
},
  "geometry": {"coordinates":[-65.10468299999999,47.671291],"type":"Point"}
}