{
  "type": "Feature",
  "properties": {
    "addr:full":"Saint-Michel QC J0L 2J0",
    "addr:postcode":"j0l 2j0",
    "iso:country":"CA",
    "sg:city":"Saint-Michel",
    "sg:classifiers":[
        {
            "category":"Building & Trades",
            "subcategory":"Construction",
            "type":"Services"
        }
    ],
    "sg:phone":"+1 450 454 7069",
    "sg:postcode":"J0L 2J0",
    "sg:province":"QC",
    "sg:tags":[
        "general",
        "contractor"
    ],
    "wof:name":"Cardinal Immotech Inc",
    "wof:placetype":"venue"
},
  "geometry": {"coordinates":[-73.559639,45.251614],"type":"Point"}
}