{
  "type": "Feature",
  "properties": {
    "addr:full":"1760 Kingsway Vancouver BC V5N 2S6",
    "addr:housenumber":"1760",
    "addr:postcode":"v5n 2s6",
    "addr:street":"Kingsway",
    "iso:country":"CA",
    "sg:address":"1760 Kingsway",
    "sg:city":"Vancouver",
    "sg:classifiers":[
        {
            "category":"Recreation",
            "type":"Entertainment"
        }
    ],
    "sg:phone":"+1 604 873 5355",
    "sg:postcode":"V5N 2S6",
    "sg:province":"BC",
    "sg:tags":[
        "martial",
        "arts",
        "instruction"
    ],
    "wof:name":"Kee's Tae Kwon DO",
    "wof:placetype":"venue"
},
  "geometry": {"coordinates":[-123.068611,49.246597],"type":"Point"}
}