{
  "type": "Feature",
  "properties": {
    "addr:full":"York ON M6M 1S7",
    "addr:postcode":"m6m 1s7",
    "iso:country":"CA",
    "sg:city":"York",
    "sg:classifiers":[
        {
            "category":"Health Services",
            "subcategory":"Doctor",
            "type":"Services"
        }
    ],
    "sg:phone":"+1 416 752 4121",
    "sg:postcode":"M6M 1S7",
    "sg:province":"ON",
    "sg:tags":[
        "dentist"
    ],
    "wof:name":"Denkovski, Dragi DDS",
    "wof:placetype":"venue"
},
  "geometry": {"coordinates":[-79.4649353027,43.6919212341],"type":"Point"}
}