{
  "type": "Feature",
  "properties": {
    "iso:country":"CA",
    "sg:address":"466 Bowlen St",
    "sg:city":"Fredericton",
    "sg:classifiers":[
        {
            "category":"Professional",
            "subcategory":"Lawyer & Legal Services",
            "type":"Services"
        }
    ],
    "sg:phone":"+1 506 472 2172",
    "sg:postcode":"E3A 2T4",
    "sg:province":"NB",
    "sg:tags":[
        "attorney"
    ],
    "wof:name":"Youssef, Jack Elias",
    "wof:placetype":"venue"
},
  "geometry": {"coordinates":[-66.635078,45.969582],"type":"Point"}
}