{
  "type": "Feature",
  "properties": {
    "addr:full":"480 Rue Cremazie Sherbrooke QC J1J 2X2",
    "addr:housenumber":"480",
    "addr:postcode":"j1j 2x2",
    "addr:street":"Rue Cremazie",
    "iso:country":"CA",
    "sg:address":"480 Rue Cremazie",
    "sg:city":"Sherbrooke",
    "sg:classifiers":[
        {
            "category":"Health Services",
            "subcategory":"Health Practitioner",
            "type":"Services"
        }
    ],
    "sg:phone":"+1 819 562 6662",
    "sg:postcode":"J1J 2X2",
    "sg:province":"QC",
    "sg:tags":[
        "psychologist"
    ],
    "wof:name":"Pouliot, Angele",
    "wof:placetype":"venue"
},
  "geometry": {"coordinates":[-71.9214172363,45.4053421021],"type":"Point"}
}