{
  "type": "Feature",
  "properties": {
    "iso:country":"CA",
    "sg:address":"Lac Des Cedres",
    "sg:city":"Saint-Malachie",
    "sg:classifiers":[
        {
            "category":"Travel",
            "subcategory":"Campground",
            "type":"Entertainment"
        }
    ],
    "sg:phone":"+1 418 642 2955",
    "sg:postcode":"G0R 3N0",
    "sg:province":"QC",
    "sg:tags":[
        "camp",
        "fishing"
    ],
    "wof:name":"Belle Chasse & Peche Inc",
    "wof:placetype":"venue"
},
  "geometry": {"coordinates":[-70.708480835,46.5872802734],"type":"Point"}
}