{
  "type": "Feature",
  "properties": {
    "addr:full":"2895 Rte Elgin N Saint-Pamphile QC G0R 3X0",
    "addr:housenumber":"2895",
    "addr:postcode":"g0r 3x0",
    "addr:street":"Rte Elgin N",
    "iso:country":"CA",
    "sg:address":"2895 Rte Elgin N",
    "sg:city":"Saint-Pamphile",
    "sg:classifiers":[
        {
            "category":"Wholesale",
            "subcategory":"Machinery & Supplies",
            "type":"Manufacturing & Wholesale Goods"
        }
    ],
    "sg:phone":"+1 418 356 3060",
    "sg:postcode":"G0R 3X0",
    "sg:province":"QC",
    "sg:tags":[
        "heavy",
        "equipment",
        "repairing"
    ],
    "wof:name":"Garage Rosaire Thibodeau Inc",
    "wof:placetype":"venue"
},
  "geometry": {"coordinates":[-69.846512,47.00491],"type":"Point"}
}