{
  "type": "Feature",
  "properties": {
    "addr:full":"158 Catherine St Blenheim ON N0P 1A0",
    "addr:housenumber":"158",
    "addr:postcode":"n0p 1a0",
    "addr:street":"Catherine St",
    "iso:country":"CA",
    "sg:address":"158 Catherine St",
    "sg:city":"Blenheim",
    "sg:classifiers":[
        {
            "category":"Professional",
            "subcategory":"Accounting & Tax Preparation",
            "type":"Services"
        }
    ],
    "sg:phone":"+1 519 676 5002",
    "sg:postcode":"N0P 1A0",
    "sg:province":"ON",
    "sg:tags":[
        "bookkeeping",
        "return",
        "filing",
        "general"
    ],
    "wof:name":"Glenden House Bookkeeping",
    "wof:placetype":"venue"
},
  "geometry": {"coordinates":[-81.9993438721,42.3316383362],"type":"Point"}
}