{
  "type": "Feature",
  "properties": {
    "addr:full":"St. John's NL A1E 4N1",
    "addr:postcode":"a1e 4n1",
    "iso:country":"CA",
    "sg:city":"St. John's",
    "sg:classifiers":[
        {
            "category":"Shopping",
            "subcategory":"Department Store",
            "type":"Retail Goods"
        }
    ],
    "sg:phone":"+1 709 368 6891",
    "sg:postcode":"A1E 4N1",
    "sg:province":"NL",
    "sg:tags":[
        "shop"
    ],
    "wof:name":"A Buck or Two",
    "wof:placetype":"venue"
},
  "geometry": {"coordinates":[-52.72423172,47.5452461243],"type":"Point"}
}