{
  "type": "Feature",
  "properties": {
    "addr:full":"Calgary AB T2H 2W4",
    "addr:postcode":"t2h 2w4",
    "iso:country":"CA",
    "sg:city":"Calgary",
    "sg:classifiers":[
        {
            "category":"Real Estate",
            "subcategory":"Real Estate Operator",
            "type":"Services"
        }
    ],
    "sg:phone":"+1 403 258 0703",
    "sg:postcode":"T2H 2W4",
    "sg:province":"AB",
    "sg:tags":[
        "building",
        "condominium",
        "contractor"
    ],
    "wof:name":"Streetside Development Corp",
    "wof:placetype":"venue"
},
  "geometry": {"coordinates":[-114.060272,51.003075],"type":"Point"}
}