{
  "type": "Feature",
  "properties": {
    "addr:full":"332 Main St Haileybury ON P0J 1K0",
    "addr:housenumber":"332",
    "addr:postcode":"p0j 1k0",
    "addr:street":"Main St",
    "iso:country":"CA",
    "sg:address":"332 Main St",
    "sg:city":"Haileybury",
    "sg:classifiers":[
        {
            "category":"Recreation",
            "type":"Entertainment"
        }
    ],
    "sg:phone":"+1 705 672 3740",
    "sg:postcode":"P0J 1K0",
    "sg:province":"ON",
    "sg:tags":[
        "parlor",
        "billiard"
    ],
    "wof:name":"Limo Billiards",
    "wof:placetype":"venue"
},
  "geometry": {"coordinates":[-79.6320571899,47.4488983154],"type":"Point"}
}