{
  "type": "Feature",
  "properties": {
    "addr:full":"506 Seventh Ave New Westminster BC V3L 1W9",
    "addr:housenumber":"506",
    "addr:postcode":"v3l 1w9",
    "addr:street":"Seventh Ave",
    "iso:country":"CA",
    "sg:address":"506 Seventh Ave",
    "sg:city":"New Westminster",
    "sg:classifiers":[
        {
            "category":"Health Services",
            "subcategory":"Doctor",
            "type":"Services"
        }
    ],
    "sg:phone":"+1 604 526 7871",
    "sg:postcode":"V3L 1W9",
    "sg:province":"BC",
    "sg:tags":[
        "physician",
        "surgeon"
    ],
    "wof:name":"Mac Kenzie, Andrew J MD",
    "wof:placetype":"venue"
},
  "geometry": {"coordinates":[-122.92074599999999,49.214943],"type":"Point"}
}