{
  "type": "Feature",
  "properties": {
    "addr:full":"196 Wellington St W Sault Ste Marie ON P6A 1H4",
    "addr:housenumber":"196",
    "addr:postcode":"p6a 1h4",
    "addr:street":"Wellington St W",
    "iso:country":"CA",
    "sg:address":"196 Wellington St W",
    "sg:city":"Sault Ste Marie",
    "sg:classifiers":[
        {
            "category":"Personal",
            "subcategory":"Beauty Salon",
            "type":"Services"
        }
    ],
    "sg:phone":"+1 705 253 3045",
    "sg:postcode":"P6A 1H4",
    "sg:province":"ON",
    "wof:name":"Hair Play",
    "wof:placetype":"venue"
},
  "geometry": {"coordinates":[-84.343796,46.523758],"type":"Point"}
}