{
  "type": "Feature",
  "properties": {
    "addr:full":"3454 Errington Ave #1 Chelmsford ON P0M 1L0",
    "addr:housenumber":"3454",
    "addr:postcode":"p0m 1l0",
    "addr:street":"Errington Ave # 1",
    "iso:country":"CA",
    "sg:address":"3454 Errington Ave #1",
    "sg:city":"Chelmsford",
    "sg:classifiers":[
        {
            "category":"Banks & Credit Unions",
            "subcategory":"Bank",
            "type":"Services"
        }
    ],
    "sg:phone":"+1 705 855 4552",
    "sg:postcode":"P0M 1L0",
    "sg:province":"ON",
    "wof:name":"Banque Scotia",
    "wof:placetype":"venue"
},
  "geometry": {"coordinates":[-81.19789886469999,46.5784111023],"type":"Point"}
}