{
  "type": "Feature",
  "properties": {
    "addr:full":"121 Peter St Port Hope ON L1A 1C5",
    "addr:housenumber":"121",
    "addr:postcode":"l1a 1c5",
    "addr:street":"Peter St",
    "iso:country":"CA",
    "sg:address":"121 Peter St",
    "sg:city":"Port Hope",
    "sg:classifiers":[
        {
            "category":"Health Services",
            "subcategory":"Medical Lab",
            "type":"Services"
        }
    ],
    "sg:phone":"+1 905 885 0044",
    "sg:postcode":"L1A 1C5",
    "sg:province":"ON",
    "wof:name":"Port Hope Denture Clinic",
    "wof:placetype":"venue"
},
  "geometry": {"coordinates":[-78.2832107544,43.9498748779],"type":"Point"}
}