{
  "type": "Feature",
  "properties": {
    "iso:country":"CA",
    "sg:address":"27528 Fraser Hwy",
    "sg:city":"Aldergrove",
    "sg:classifiers":[
        {
            "category":"Personal",
            "subcategory":"Barber",
            "type":"Services"
        }
    ],
    "sg:phone":"+1 604 856 1707",
    "sg:postcode":"V4W 3N5",
    "sg:province":"BC",
    "sg:tags":[
        "salon",
        "beauty"
    ],
    "wof:name":"Magicuts",
    "wof:placetype":"venue"
},
  "geometry": {"coordinates":[-122.46198272700001,49.0575637817],"type":"Point"}
}