{
  "type": "Feature",
  "properties": {
    "addr:full":"9614 100 Ave Grande Prairie AB T8V 0T2",
    "addr:housenumber":"9614",
    "addr:postcode":"t8v 0t2",
    "addr:street":"100 Ave",
    "iso:country":"CA",
    "sg:address":"9614 100 Ave",
    "sg:city":"Grande Prairie",
    "sg:classifiers":[
        {
            "category":"Social Services",
            "subcategory":"Child Care",
            "type":"Services"
        }
    ],
    "sg:phone":"+1 780 532 9684",
    "sg:postcode":"T8V 0T2",
    "sg:province":"AB",
    "wof:name":"Stepping Stones Day Care",
    "wof:placetype":"venue"
},
  "geometry": {"coordinates":[-118.78268432599999,55.1708259583],"type":"Point"}
}