{
  "type": "Feature",
  "properties": {
    "iso:country":"CA",
    "sg:address":"375 Bond St W",
    "sg:city":"Oshawa",
    "sg:classifiers":[
        {
            "category":"Shopping",
            "subcategory":"Books",
            "type":"Retail Goods"
        }
    ],
    "sg:phone":"+1 905 723 6831",
    "sg:postcode":"L1J 8A2",
    "sg:province":"ON",
    "sg:tags":[
        "dealer"
    ],
    "wof:name":"Tiny's Christian Bookstore",
    "wof:placetype":"venue"
},
  "geometry": {"coordinates":[-78.87729644780001,43.8953552246],"type":"Point"}
}