{
  "type": "Feature",
  "properties": {
    "addr:full":"225 Main St S Slave Lake AB T0G 2A3",
    "addr:housenumber":"225",
    "addr:postcode":"t0g 2a3",
    "addr:street":"Main St S Slave",
    "iso:country":"CA",
    "sg:address":"225 Main St S",
    "sg:city":"Slave Lake",
    "sg:classifiers":[
        {
            "category":"Home & Garden",
            "subcategory":"Hardware",
            "type":"Retail Goods"
        }
    ],
    "sg:phone":"+1 780 849 3879",
    "sg:postcode":"T0G 2A3",
    "sg:province":"AB",
    "wof:name":"True Value Hardware",
    "wof:placetype":"venue"
},
  "geometry": {"coordinates":[-114.771911621,55.2691841125],"type":"Point"}
}