{
  "type": "Feature",
  "properties": {
    "addr:full":"5540 Rue Jean-Talon E Saint-Leonard QC H1S 1L9",
    "addr:housenumber":"5540",
    "addr:postcode":"h1s 1l9",
    "addr:street":"Rue Jean-Talon E",
    "iso:country":"CA",
    "sg:address":"5540 Rue Jean-Talon E",
    "sg:city":"Saint-Leonard",
    "sg:classifiers":[
        {
            "category":"Food & Beverages",
            "subcategory":"Bakery",
            "type":"Retail Goods"
        }
    ],
    "sg:phone":"+1 514 259 0746",
    "sg:postcode":"H1S 1L9",
    "sg:province":"QC",
    "sg:tags":[
        "baker"
    ],
    "wof:name":"Boulangerie & Patisserie",
    "wof:placetype":"venue"
},
  "geometry": {"coordinates":[-73.58046,45.581913],"type":"Point"}
}