{
  "type": "Feature",
  "properties": {
    "addr:full":"1117 Conception Bay Hwy Conception Bay South NL A1X 4E7",
    "addr:housenumber":"1117",
    "addr:postcode":"a1x 4e7",
    "addr:street":"Conception Bay Hwy",
    "iso:country":"CA",
    "sg:address":"1117 Conception Bay Hwy",
    "sg:city":"Conception Bay South",
    "sg:classifiers":[
        {
            "category":"Home & Garden",
            "subcategory":"Building Materials",
            "type":"Retail Goods"
        }
    ],
    "sg:phone":"+1 709 744 2132",
    "sg:postcode":"A1X 4E7",
    "sg:province":"NL",
    "wof:name":"Hickey's Building Supplies",
    "wof:placetype":"venue"
},
  "geometry": {"coordinates":[-53.046394,47.483444],"type":"Point"}
}