{
  "type": "Feature",
  "properties": {
    "iso:country":"CA",
    "sg:address":"9930 Glendon Dr",
    "sg:city":"Komoka",
    "sg:classifiers":[
        {
            "category":"Shopping",
            "subcategory":"Computers & Home Electronics",
            "type":"Retail Goods"
        }
    ],
    "sg:phone":"+1 519 657 4428",
    "sg:postcode":"N0L 1R0",
    "sg:province":"ON",
    "sg:tags":[
        "equipment",
        "satellite",
        "system"
    ],
    "wof:name":"R C Enterprises",
    "wof:placetype":"venue"
},
  "geometry": {"coordinates":[-81.4339294434,42.9433364868],"type":"Point"}
}