{
  "type": "Feature",
  "properties": {
    "addr:full":"10 Main St W Kingsville ON N9Y 1H1",
    "addr:housenumber":"10",
    "addr:postcode":"n9y 1h1",
    "addr:street":"Main St W",
    "iso:country":"CA",
    "sg:address":"10 Main St W",
    "sg:city":"Kingsville",
    "sg:classifiers":[
        {
            "category":"Shopping",
            "subcategory":"Clothing, Apparel, & Fashions",
            "type":"Retail Goods"
        }
    ],
    "sg:phone":"+1 519 733 4672",
    "sg:postcode":"N9Y 1H1",
    "sg:province":"ON",
    "wof:name":"Mary Kathryn Ladies' Shop",
    "wof:placetype":"venue"
},
  "geometry": {"coordinates":[-82.74009700000001,42.038013],"type":"Point"}
}