{
  "type": "Feature",
  "properties": {
    "addr:full":"340 Gilmour St Ottawa ON K2P 0R3",
    "addr:housenumber":"340",
    "addr:postcode":"k2p 0r3",
    "addr:street":"Gilmour St",
    "iso:country":"CA",
    "sg:address":"340 Gilmour St",
    "sg:city":"Ottawa",
    "sg:classifiers":[
        {
            "category":"Health Services",
            "subcategory":"Doctor",
            "type":"Services"
        }
    ],
    "sg:phone":"+1 613 233 0101",
    "sg:postcode":"K2P 0R3",
    "sg:province":"ON",
    "sg:tags":[
        "dentist"
    ],
    "wof:name":"Carl Brownstein & Assoc",
    "wof:placetype":"venue"
},
  "geometry": {"coordinates":[-75.6934890747,45.4146652222],"type":"Point"}
}