{
  "type": "Feature",
  "properties": {
    "addr:full":"12926 82 St NW Edmonton AB T5E 2T2",
    "addr:housenumber":"12926",
    "addr:postcode":"t5e 2t2",
    "addr:street":"82 St Nw",
    "iso:country":"CA",
    "sg:address":"12926 82 St NW",
    "sg:city":"Edmonton",
    "sg:classifiers":[
        {
            "category":"Retail",
            "subcategory":"Laundry & Dry Cleaning",
            "type":"Services"
        }
    ],
    "sg:phone":"+1 780 476 0657",
    "sg:postcode":"T5E 2T2",
    "sg:province":"AB",
    "sg:tags":[
        "cleaners"
    ],
    "wof:name":"All Fashion Cleaners",
    "wof:placetype":"venue"
},
  "geometry": {"coordinates":[-113.4674,53.587395],"type":"Point"}
}