{
  "type": "Feature",
  "properties": {
    "addr:full":"7464 132 St Surrey BC V3W 4M7",
    "addr:housenumber":"7464",
    "addr:postcode":"v3w 4m7",
    "addr:street":"132 St",
    "iso:country":"CA",
    "sg:address":"7464 132 St",
    "sg:city":"Surrey",
    "sg:classifiers":[
        {
            "category":"Manufacturing",
            "subcategory":"Glass & Minerals",
            "type":"Manufacturing & Wholesale Goods"
        }
    ],
    "sg:phone":"+1 604 594 4999",
    "sg:postcode":"V3W 4M7",
    "sg:province":"BC",
    "sg:tags":[
        "bottle"
    ],
    "wof:name":"Polybottle Group Ltd",
    "wof:placetype":"venue"
},
  "geometry": {"coordinates":[-122.85675000000001,49.140961],"type":"Point"}
}