{
  "type": "Feature",
  "properties": {
    "iso:country":"CA",
    "sg:city":"Abbotsford",
    "sg:classifiers":[
        {
            "category":"Professional",
            "subcategory":"Lawyer & Legal Services",
            "type":"Services"
        }
    ],
    "sg:phone":"+1 604 859 3887",
    "sg:postcode":"V2S 2H1",
    "sg:province":"BC",
    "sg:tags":[
        "attorney"
    ],
    "wof:name":"Palmer Gillen",
    "wof:placetype":"venue"
},
  "geometry": {"coordinates":[-122.289634705,49.0492134094],"type":"Point"}
}