{
  "type": "Feature",
  "properties": {
    "addr:full":"19087 96 Ave Surrey BC V4N 3P2",
    "addr:housenumber":"19087",
    "addr:postcode":"v4n 3p2",
    "addr:street":"96 Ave",
    "iso:country":"CA",
    "sg:address":"19087 96 Ave",
    "sg:city":"Surrey",
    "sg:classifiers":[
        {
            "category":"Wholesale",
            "subcategory":"Machinery & Supplies",
            "type":"Manufacturing & Wholesale Goods"
        }
    ],
    "sg:phone":"+1 604 888 2959",
    "sg:postcode":"V4N 3P2",
    "sg:province":"BC",
    "sg:tags":[
        "equipment",
        "sawmill"
    ],
    "wof:name":"Salton Fabrication Ltd",
    "wof:placetype":"venue"
},
  "geometry": {"coordinates":[-122.69381,49.177197],"type":"Point"}
}