{
  "type": "Feature",
  "properties": {
    "addr:full":"435 Fares St Port Colborne ON L3K 1X4",
    "addr:housenumber":"435",
    "addr:postcode":"l3k 1x4",
    "addr:street":"Fares St",
    "iso:country":"CA",
    "sg:address":"435 Fares St",
    "sg:city":"Port Colborne",
    "sg:classifiers":[
        {
            "category":"Education",
            "subcategory":"School",
            "type":"Public Place"
        }
    ],
    "sg:phone":"+1 905 834 7440",
    "sg:postcode":"L3K 1X4",
    "sg:province":"ON",
    "wof:name":"DE Witt Carter Elementary Schl",
    "wof:placetype":"venue"
},
  "geometry": {"coordinates":[-79.244598,42.89024],"type":"Point"}
}