{
  "type": "Feature",
  "properties": {
    "iso:country":"CA",
    "sg:address":"77 Matheson Blvd E # 7",
    "sg:city":"Mississauga",
    "sg:classifiers":[
        {
            "category":"Health Services",
            "subcategory":"Chiropractor",
            "type":"Services"
        }
    ],
    "sg:phone":"+1 905 848 8900",
    "sg:postcode":"L4Z 2Y5",
    "sg:province":"ON",
    "wof:name":"Lanoue, Serge DC",
    "wof:placetype":"venue"
},
  "geometry": {"coordinates":[-79.669052124,43.6200904846],"type":"Point"}
}