{
  "type": "Feature",
  "properties": {
    "addr:full":"5 Greentree Rd Markham ON L3R 3A9",
    "addr:housenumber":"5",
    "addr:postcode":"l3r 3a9",
    "addr:street":"Greentree Rd",
    "iso:country":"CA",
    "sg:address":"5 Greentree Rd",
    "sg:city":"Markham",
    "sg:classifiers":[
        {
            "category":"Manufacturing",
            "subcategory":"Signs",
            "type":"Manufacturing & Wholesale Goods"
        }
    ],
    "sg:phone":"+1 905 475 6090",
    "sg:postcode":"L3R 3A9",
    "sg:province":"ON",
    "wof:name":"Freud Signs Ltd",
    "wof:placetype":"venue"
},
  "geometry": {"coordinates":[-79.317184,43.861656],"type":"Point"}
}