{
  "type": "Feature",
  "properties": {
    "addr:full":"5871 Av Victoria Montreal QC H3W 2R7",
    "addr:housenumber":"5871",
    "addr:postcode":"h3w 2r7",
    "addr:street":"Av Victoria",
    "iso:country":"CA",
    "sg:address":"5871 Av Victoria",
    "sg:city":"Montreal",
    "sg:classifiers":[
        {
            "category":"Professional",
            "subcategory":"Computer Services",
            "type":"Services"
        }
    ],
    "sg:phone":"+1 514 344 8009",
    "sg:postcode":"H3W 2R7",
    "sg:province":"QC",
    "sg:tags":[
        "consultant"
    ],
    "wof:name":"Pre-Thunk Solutions",
    "wof:placetype":"venue"
},
  "geometry": {"coordinates":[-73.635269165,45.4934806824],"type":"Point"}
}