{
  "type": "Feature",
  "properties": {
    "addr:full":"Calgary AB T2A 0P9",
    "addr:postcode":"t2a 0p9",
    "iso:country":"CA",
    "sg:city":"Calgary",
    "sg:classifiers":[
        {
            "category":"Restaurant",
            "type":"Food & Drink"
        }
    ],
    "sg:phone":"+1 403 235 2332",
    "sg:postcode":"T2A 0P9",
    "sg:province":"AB",
    "wof:name":"Momma Jean's",
    "wof:placetype":"venue"
},
  "geometry": {"coordinates":[-113.992637634,51.0380325317],"type":"Point"}
}