{
  "type": "Feature",
  "properties": {
    "addr:full":"161 Raglan St S Renfrew ON K7V 1R2",
    "addr:housenumber":"161",
    "addr:postcode":"k7v 1r2",
    "addr:street":"Raglan St S",
    "iso:country":"CA",
    "sg:address":"161 Raglan St S",
    "sg:city":"Renfrew",
    "sg:classifiers":[
        {
            "category":"Professional",
            "subcategory":"Management & Consulting",
            "type":"Services"
        }
    ],
    "sg:phone":"+1 613 432 6848",
    "sg:postcode":"K7V 1R2",
    "sg:province":"ON",
    "sg:tags":[
        "consultant",
        "business"
    ],
    "wof:name":"Enterprise Renfrew County",
    "wof:placetype":"venue"
},
  "geometry": {"coordinates":[-76.6844177246,45.4723968506],"type":"Point"}
}