{
  "type": "Feature",
  "properties": {
    "addr:full":"37 Carol St Alberton PE C0B 1B0",
    "addr:housenumber":"37",
    "addr:postcode":"c0b 1b0",
    "addr:street":"Carol St",
    "iso:country":"CA",
    "sg:address":"37 Carol St",
    "sg:city":"Alberton",
    "sg:classifiers":[
        {
            "category":"Professional",
            "subcategory":"Advertising",
            "type":"Services"
        }
    ],
    "sg:phone":"+1 902 853 4325",
    "sg:postcode":"C0B 1B0",
    "sg:province":"PE",
    "wof:name":"Prince County Penny Saver",
    "wof:placetype":"venue"
},
  "geometry": {"coordinates":[-64.057777,46.807823],"type":"Point"}
}