{
  "type": "Feature",
  "properties": {
    "addr:full":"2 Browns Rd Englehart ON P0J 1H0",
    "addr:housenumber":"2",
    "addr:postcode":"p0j 1h0",
    "addr:street":"Browns Rd",
    "iso:country":"CA",
    "sg:address":"2 Browns Rd",
    "sg:city":"Englehart",
    "sg:classifiers":[
        {
            "category":"Taxi",
            "type":"Transportation"
        }
    ],
    "sg:phone":"+1 705 544 2041",
    "sg:postcode":"P0J 1H0",
    "sg:province":"ON",
    "sg:tags":[
        "taxicab"
    ],
    "wof:name":"Bond's Cab Svc",
    "wof:placetype":"venue"
},
  "geometry": {"coordinates":[-79.87764,47.820286],"type":"Point"}
}