{
  "type": "Feature",
  "properties": {
    "addr:full":"1224 Gordon Rd Moose Jaw SK S6H 3E4",
    "addr:housenumber":"1224",
    "addr:postcode":"s6h 3e4",
    "addr:street":"Gordon Rd",
    "iso:country":"CA",
    "sg:address":"1224 Gordon Rd",
    "sg:city":"Moose Jaw",
    "sg:classifiers":[
        {
            "category":"Health Services",
            "subcategory":"Doctor",
            "type":"Services"
        }
    ],
    "sg:phone":"+1 306 694 1010",
    "sg:postcode":"S6H 3E4",
    "sg:province":"SK",
    "sg:tags":[
        "physician",
        "surgeon"
    ],
    "wof:name":"Amies, D R MD",
    "wof:placetype":"venue"
},
  "geometry": {"coordinates":[-105.569427,50.403839],"type":"Point"}
}