{
  "type": "Feature",
  "properties": {
    "iso:country":"CA",
    "sg:address":"507 6th A St",
    "sg:city":"Hanover",
    "sg:classifiers":[
        {
            "category":"Personal",
            "subcategory":"Beauty Salon",
            "type":"Services"
        }
    ],
    "sg:phone":"+1 519 364 2976",
    "sg:postcode":"N4N 1E9",
    "sg:province":"ON",
    "wof:name":"Classic Cuts",
    "wof:placetype":"venue"
},
  "geometry": {"coordinates":[-81.0192489624,44.1495819092],"type":"Point"}
}