{
  "type": "Feature",
  "properties": {
    "addr:full":"Calgary AB T1Y 5E1",
    "addr:postcode":"t1y 5e1",
    "iso:country":"CA",
    "sg:city":"Calgary",
    "sg:classifiers":[
        {
            "category":"Professional",
            "subcategory":"Management & Consulting",
            "type":"Services"
        }
    ],
    "sg:phone":"+1 403 230 3361",
    "sg:postcode":"T1Y 5E1",
    "sg:province":"AB",
    "sg:tags":[
        "consultant",
        "industrial"
    ],
    "wof:name":"Shannon Developments Corp",
    "wof:placetype":"venue"
},
  "geometry": {"coordinates":[-113.99797821,51.0852928162],"type":"Point"}
}