{
  "type": "Feature",
  "properties": {
    "iso:country":"CA",
    "sg:address":"46 Rue Du Banc",
    "sg:city":"Gaspe",
    "sg:classifiers":[
        {
            "category":"Retail",
            "subcategory":"Auto Repair",
            "type":"Services"
        }
    ],
    "sg:phone":"+1 418 269 3991",
    "sg:postcode":"G4X 5E2",
    "sg:province":"QC",
    "sg:tags":[
        "automobile",
        "customizing",
        "parts",
        "supply"
    ],
    "wof:name":"Gaspesie Pieces D'Autos Enr",
    "wof:placetype":"venue"
},
  "geometry": {"coordinates":[-64.3908538818,48.9957962036],"type":"Point"}
}