{
  "type": "Feature",
  "properties": {
    "addr:full":"7455 Boul Langelier Saint-Leonard QC H1S 1V6",
    "addr:housenumber":"7455",
    "addr:postcode":"h1s 1v6",
    "addr:street":"Boul Langelier",
    "iso:country":"CA",
    "sg:address":"7455 Boul Langelier",
    "sg:city":"Saint-Leonard",
    "sg:classifiers":[
        {
            "category":"Shopping",
            "subcategory":"Used Merchandise",
            "type":"Retail Goods"
        }
    ],
    "sg:phone":"+1 514 252 0508",
    "sg:postcode":"H1S 1V6",
    "sg:province":"QC",
    "sg:tags":[
        "flea",
        "market"
    ],
    "wof:name":"Grand Marche Puces Langelier",
    "wof:placetype":"venue"
},
  "geometry": {"coordinates":[-73.57330322270001,45.5918083191],"type":"Point"}
}