{
  "type": "Feature",
  "properties": {
    "addr:full":"5028 50 Ave N Fort Nelson BC V0C 1R0",
    "addr:housenumber":"5028",
    "addr:postcode":"bc v0c 1r0",
    "addr:street":"50 Ave N",
    "iso:country":"CA",
    "sg:address":"5028 50 Ave N",
    "sg:city":"Fort Nelson",
    "sg:classifiers":[
        {
            "category":"Banks & Credit Unions",
            "subcategory":"Bank",
            "type":"Services"
        }
    ],
    "sg:phone":"+1 250 774 2555",
    "sg:postcode":"V0C 1R0",
    "sg:province":"BC",
    "wof:name":"Cibc",
    "wof:placetype":"venue"
},
  "geometry": {"coordinates":[-122.702827454,58.8051071167],"type":"Point"}
}