{
  "type": "Feature",
  "properties": {
    "iso:country":"CA",
    "sg:address":"14 Rue Grenier",
    "sg:city":"Melocheville",
    "sg:classifiers":[
        {
            "category":"Building & Trades",
            "subcategory":"Construction",
            "type":"Services"
        }
    ],
    "sg:phone":"+1 514 984 5039",
    "sg:postcode":"J0S 1J0",
    "sg:province":"QC",
    "sg:tags":[
        "builder",
        "repairer",
        "chimney"
    ],
    "wof:name":"Construction Jo-Rent Inc",
    "wof:placetype":"venue"
},
  "geometry": {"coordinates":[-73.93347930909999,45.3173866272],"type":"Point"}
}