{
  "type": "Feature",
  "properties": {
    "addr:full":"585 Rue Principale Saint-Edmond-Les-Plaines QC G0W 2M0",
    "addr:housenumber":"585",
    "addr:postcode":"g0w 2m0",
    "addr:street":"Rue Principale",
    "iso:country":"CA",
    "sg:address":"585 Rue Principale",
    "sg:city":"Saint-Edmond-Les-Plaines",
    "sg:classifiers":[
        {
            "category":"Banks & Credit Unions",
            "subcategory":"Bank",
            "type":"Services"
        }
    ],
    "sg:phone":"+1 418 274 3067",
    "sg:postcode":"G0W 2M0",
    "sg:province":"QC",
    "wof:name":"Caisse Populaire Desjardins",
    "wof:placetype":"venue"
},
  "geometry": {"coordinates":[-72.559364,48.912373],"type":"Point"}
}