{
  "type": "Feature",
  "properties": {
    "addr:full":"5304 48A Ave Camrose AB T4V 0L1",
    "addr:housenumber":"5304",
    "addr:postcode":"t4v 0l1",
    "addr:street":"48A Ave",
    "iso:country":"CA",
    "sg:address":"5304 48A Ave",
    "sg:city":"Camrose",
    "sg:classifiers":[
        {
            "category":"Organizations",
            "subcategory":"Religious Organization",
            "type":"Services"
        }
    ],
    "sg:phone":"+1 780 672 2197",
    "sg:postcode":"T4V 0L1",
    "sg:province":"AB",
    "sg:tags":[
        "church"
    ],
    "wof:name":"Ukrainian Catholic Church",
    "wof:placetype":"venue"
},
  "geometry": {"coordinates":[-112.831359863,53.0197410583],"type":"Point"}
}