{
  "type": "Feature",
  "properties": {
    "iso:country":"CA",
    "sg:address":"2351 Rossini Blvd",
    "sg:city":"Windsor",
    "sg:classifiers":[
        {
            "category":"Home & Garden",
            "subcategory":"Home Furnishings",
            "type":"Retail Goods"
        }
    ],
    "sg:phone":"+1 519 966 8966",
    "sg:postcode":"N8W 4P7",
    "sg:province":"ON",
    "sg:tags":[
        "curtain",
        "made",
        "drapery"
    ],
    "wof:name":"Blind Spot",
    "wof:placetype":"venue"
},
  "geometry": {"coordinates":[-82.97272491459999,42.3052787781],"type":"Point"}
}