{
  "type": "Feature",
  "properties": {
    "addr:full":"Newmarket ON L3Y 7B6",
    "addr:postcode":"l3y 7b6",
    "iso:country":"CA",
    "sg:city":"Newmarket",
    "sg:classifiers":[
        {
            "category":"Professional",
            "subcategory":"Advertising",
            "type":"Services"
        }
    ],
    "sg:phone":"+1 905 967 1193",
    "sg:postcode":"L3Y 7B6",
    "sg:province":"ON",
    "sg:tags":[
        "station",
        "radio",
        "representative"
    ],
    "wof:name":"Key North Productions Inc",
    "wof:placetype":"venue"
},
  "geometry": {"coordinates":[-79.429176,44.071659],"type":"Point"}
}