{
  "type": "Feature",
  "properties": {
    "addr:full":"Mississauga ON L5C 4P8",
    "addr:postcode":"l5c 4p8",
    "iso:country":"CA",
    "sg:city":"Mississauga",
    "sg:classifiers":[
        {
            "category":"Professional",
            "subcategory":"Engineering",
            "type":"Services"
        }
    ],
    "sg:phone":"+1 905 276 5100",
    "sg:postcode":"L5C 4P8",
    "sg:province":"ON",
    "sg:tags":[
        "engineer"
    ],
    "wof:name":"Skira & Assoc Ltd",
    "wof:placetype":"venue"
},
  "geometry": {"coordinates":[-79.65329,43.56839],"type":"Point"}
}