{
  "type": "Feature",
  "properties": {
    "addr:full":"1759 Avenue Rd North York ON M5M 3Y8",
    "addr:housenumber":"1759",
    "addr:postcode":"m5m 3y8",
    "addr:street":"Avenue Rd",
    "iso:country":"CA",
    "sg:address":"1759 Avenue Rd",
    "sg:city":"North York",
    "sg:classifiers":[
        {
            "category":"Shopping",
            "subcategory":"Clothing, Apparel, & Fashions",
            "type":"Retail Goods"
        }
    ],
    "sg:phone":"+1 416 782 6632",
    "sg:postcode":"M5M 3Y8",
    "sg:province":"ON",
    "sg:tags":[
        "lingerie"
    ],
    "wof:name":"Kathryn's Lingerie",
    "wof:placetype":"venue"
},
  "geometry": {"coordinates":[-79.41822052000001,43.7292366028],"type":"Point"}
}