{
  "type": "Feature",
  "properties": {
    "addr:full":"56 Manitoba St Bracebridge ON P1L 1S1",
    "addr:housenumber":"56",
    "addr:postcode":"p1l 1s1",
    "addr:street":"Manitoba St",
    "iso:country":"CA",
    "sg:address":"56 Manitoba St",
    "sg:city":"Bracebridge",
    "sg:classifiers":[
        {
            "category":"Food & Beverages",
            "subcategory":"Specialty",
            "type":"Retail Goods"
        }
    ],
    "sg:phone":"+1 705 645 7210",
    "sg:postcode":"P1L 1S1",
    "sg:province":"ON",
    "sg:tags":[
        "health",
        "diet"
    ],
    "wof:name":"Northern Nutrition",
    "wof:placetype":"venue"
},
  "geometry": {"coordinates":[-79.3105010986,45.0410766602],"type":"Point"}
}