{
  "type": "Feature",
  "properties": {
    "addr:full":"8203 98 St Fort St John BC V1J 6W5",
    "addr:housenumber":"8203",
    "addr:postcode":"v1j 6w5",
    "addr:street":"98 St",
    "iso:country":"CA",
    "sg:address":"8203 98 St",
    "sg:city":"Fort St John",
    "sg:classifiers":[
        {
            "category":"Building & Trades",
            "subcategory":"Equipment Rental",
            "type":"Services"
        }
    ],
    "sg:phone":"+1 250 785 6829",
    "sg:postcode":"V1J 6W5",
    "sg:province":"BC",
    "sg:tags":[
        "yard",
        "flag",
        "banner"
    ],
    "wof:name":"Conway Visions Inc",
    "wof:placetype":"venue"
},
  "geometry": {"coordinates":[-120.814621,56.244156],"type":"Point"}
}