{
  "type": "Feature",
  "properties": {
    "iso:country":"CA",
    "sg:address":"12178 Bonson Rd",
    "sg:city":"Pitt Meadows",
    "sg:classifiers":[
        {
            "category":"Education",
            "subcategory":"School",
            "type":"Public Place"
        }
    ],
    "sg:phone":"+1 604 460 9993",
    "sg:postcode":"V3Y 2L5",
    "sg:province":"BC",
    "wof:name":"Edith Mc Dermott Elementary",
    "wof:placetype":"venue"
},
  "geometry": {"coordinates":[-122.68043518099999,49.2240638733],"type":"Point"}
}