{
  "type": "Feature",
  "properties": {
    "addr:full":"634047 Hwy 10 & 24 Orangeville ON L9W 2Z1",
    "addr:housenumber":"634047",
    "addr:postcode":"l9w 2z1",
    "addr:street":"Hwy 10 & 24",
    "iso:country":"CA",
    "sg:address":"634047 Hwy 10 & 24",
    "sg:city":"Orangeville",
    "sg:classifiers":[
        {
            "category":"Building & Trades",
            "subcategory":"Construction",
            "type":"Services"
        }
    ],
    "sg:phone":"+1 519 941 7463",
    "sg:postcode":"L9W 2Z1",
    "sg:province":"ON",
    "sg:tags":[
        "builder",
        "repairer",
        "masonry",
        "chimney",
        "contractor"
    ],
    "wof:name":"Mono Construction Ltd",
    "wof:placetype":"venue"
},
  "geometry": {"coordinates":[-80.0727844238,43.9168701172],"type":"Point"}
}