{
  "type": "Feature",
  "properties": {
    "addr:full":"149 Rue Laurier Granby QC J2G 5K3",
    "addr:housenumber":"149",
    "addr:postcode":"j2g 5k3",
    "addr:street":"Rue Laurier",
    "iso:country":"CA",
    "sg:address":"149 Rue Laurier",
    "sg:city":"Granby",
    "sg:classifiers":[
        {
            "category":"Shopping",
            "subcategory":"Clothing, Apparel, & Fashions",
            "type":"Retail Goods"
        }
    ],
    "sg:phone":"+1 450 372 8243",
    "sg:postcode":"J2G 5K3",
    "sg:province":"QC",
    "sg:tags":[
        "furnishing"
    ],
    "wof:name":"Joseph Lamoureux Inc",
    "wof:placetype":"venue"
},
  "geometry": {"coordinates":[-72.729996,45.405907],"type":"Point"}
}