{
  "type": "Feature",
  "properties": {
    "addr:full":"45 Main St N Alexandria ON K0C 1A0",
    "addr:housenumber":"45",
    "addr:postcode":"k0c 1a0",
    "addr:street":"Main St N",
    "iso:country":"CA",
    "sg:address":"45 Main St N",
    "sg:city":"Alexandria",
    "sg:classifiers":[
        {
            "category":"Retail",
            "subcategory":"Portrait Studio",
            "type":"Services"
        }
    ],
    "sg:phone":"+1 613 525 2115",
    "sg:postcode":"K0C 1A0",
    "sg:province":"ON",
    "sg:tags":[
        "photographer"
    ],
    "wof:name":"Thompson Photographers",
    "wof:placetype":"venue"
},
  "geometry": {"coordinates":[-74.636848,45.311699],"type":"Point"}
}