{
  "type": "Feature",
  "properties": {
    "addr:full":"General Delivery Jordan River BC V0S 1L0",
    "addr:postcode":"v0s 1l0",
    "iso:country":"CA",
    "sg:address":"General Delivery",
    "sg:city":"Jordan River",
    "sg:classifiers":[
        {
            "category":"Manufacturing",
            "subcategory":"Lumber",
            "type":"Manufacturing & Wholesale Goods"
        }
    ],
    "sg:phone":"+1 250 646 2031",
    "sg:postcode":"V0S 1L0",
    "sg:province":"BC",
    "sg:tags":[
        "company",
        "logging"
    ],
    "wof:name":"Western Forest Products Ltd",
    "wof:placetype":"venue"
},
  "geometry": {"coordinates":[-124.06296500000001,48.427574],"type":"Point"}
}