{
  "type": "Feature",
  "properties": {
    "addr:full":"5845 Route 515 Saint-Paul NB E4T 3P3",
    "addr:housenumber":"5845",
    "addr:postcode":"e4t 3p3",
    "addr:street":"Route 515",
    "iso:country":"CA",
    "sg:address":"5845 Route 515",
    "sg:city":"Saint-Paul",
    "sg:classifiers":[
        {
            "category":"Building & Trades",
            "subcategory":"Construction",
            "type":"Services"
        }
    ],
    "sg:phone":"+1 506 955 3881",
    "sg:postcode":"E4T 3P3",
    "sg:province":"NB",
    "sg:tags":[
        "general",
        "contractor"
    ],
    "wof:name":"Roger Nowlan Contractor Ltd",
    "wof:placetype":"venue"
},
  "geometry": {"coordinates":[-64.9925537109,46.3160896301],"type":"Point"}
}