{
  "type": "Feature",
  "properties": {
    "addr:full":"5086 8A Ave Delta BC V4M 1T4",
    "addr:housenumber":"5086",
    "addr:postcode":"v4m 1t4",
    "addr:street":"8A Ave",
    "iso:country":"CA",
    "sg:address":"5086 8A Ave",
    "sg:city":"Delta",
    "sg:classifiers":[
        {
            "category":"Wholesale",
            "subcategory":"Office Equipment",
            "type":"Manufacturing & Wholesale Goods"
        }
    ],
    "sg:phone":"+1 604 948 2289",
    "sg:postcode":"V4M 1T4",
    "sg:province":"BC",
    "sg:tags":[
        "scanning",
        "code",
        "bar"
    ],
    "wof:name":"Ryzex Re-Marketing",
    "wof:placetype":"venue"
},
  "geometry": {"coordinates":[-123.05961600000001,49.084801],"type":"Point"}
}