{
  "type": "Feature",
  "properties": {
    "addr:full":"221 Rte Marie-Victorin Saint-Nicolas QC G7A 2W9",
    "addr:housenumber":"221",
    "addr:postcode":"g7a 2w9",
    "addr:street":"Rte Marie-Victorin",
    "iso:country":"CA",
    "sg:address":"221 Rte Marie-Victorin",
    "sg:city":"Saint-Nicolas",
    "sg:classifiers":[
        {
            "category":"Food & Beverages",
            "subcategory":"Groceries & Convenience Stores",
            "type":"Retail Goods"
        }
    ],
    "sg:phone":"+1 418 831 9455",
    "sg:postcode":"G7A 2W9",
    "sg:province":"QC",
    "wof:name":"Accommodation LA Halte Bouffe",
    "wof:placetype":"venue"
},
  "geometry": {"coordinates":[-71.29510500000001,46.735676],"type":"Point"}
}