{
  "type": "Feature",
  "properties": {
    "addr:full":"54 1/2 Rue Champlain Quebec QC G1K 4H7",
    "addr:housenumber":"1 / 2",
    "addr:postcode":"g1k 4h7",
    "addr:street":"54;Rue Champlain",
    "iso:country":"CA",
    "sg:address":"54 1/2 Rue Champlain",
    "sg:city":"Quebec",
    "sg:classifiers":[
        {
            "category":"Wholesale",
            "subcategory":"Non-durable Goods",
            "type":"Manufacturing & Wholesale Goods"
        }
    ],
    "sg:phone":"+1 418 694 1701",
    "sg:postcode":"G1K 4H7",
    "sg:province":"QC",
    "sg:tags":[
        "souvenir"
    ],
    "wof:name":"Entreprises Dubois & Girard",
    "wof:placetype":"venue"
},
  "geometry": {"coordinates":[-71.2062530518,46.8049468994],"type":"Point"}
}