{
  "type": "Feature",
  "properties": {
    "addr:full":"453 Truro Heights Rd Truro NS B2N 5A9",
    "addr:housenumber":"453",
    "addr:postcode":"b2n 5a9",
    "addr:street":"Truro Heights Rd",
    "iso:country":"CA",
    "sg:address":"453 Truro Heights Rd",
    "sg:city":"Truro",
    "sg:classifiers":[
        {
            "category":"Building & Trades",
            "subcategory":"Cleaning & Sanitation",
            "type":"Services"
        }
    ],
    "sg:phone":"+1 902 893 2000",
    "sg:postcode":"B2N 5A9",
    "sg:province":"NS",
    "sg:tags":[
        "snow",
        "removal"
    ],
    "wof:name":"Circle H Equipment Ltd",
    "wof:placetype":"venue"
},
  "geometry": {"coordinates":[-63.30481,45.339199],"type":"Point"}
}