{
  "type": "Feature",
  "properties": {
    "addr:full":"103 Victoria St W #1 Alliston ON L9R 1T5",
    "addr:housenumber":"103",
    "addr:postcode":"l9r 1t5",
    "addr:street":"Victoria St W # 1 Alliston",
    "iso:country":"CA",
    "sg:address":"103 Victoria St W #1",
    "sg:city":"Alliston",
    "sg:classifiers":[
        {
            "category":"Real Estate",
            "subcategory":"Real Estate Agent",
            "type":"Services"
        }
    ],
    "sg:phone":"+1 705 434 1551",
    "sg:postcode":"L9R 1T5",
    "sg:province":"ON",
    "wof:name":"New Tecumseth Realty",
    "wof:placetype":"venue"
},
  "geometry": {"coordinates":[-79.872322,44.153282],"type":"Point"}
}