{
  "type": "Feature",
  "properties": {
    "addr:full":"106 Rue Des Erables Saint-Alphonse-DE-Granby QC J0E 2A0",
    "addr:housenumber":"106",
    "addr:postcode":"j0e 2a0",
    "addr:street":"Rue Des Erables",
    "iso:country":"CA",
    "sg:address":"106 Rue Des Erables",
    "sg:city":"Saint-Alphonse-DE-Granby",
    "sg:classifiers":[
        {
            "category":"Recreation",
            "type":"Entertainment"
        }
    ],
    "sg:phone":"+1 450 375 5959",
    "sg:postcode":"J0E 2A0",
    "sg:province":"QC",
    "sg:tags":[
        "sugar",
        "syrup",
        "hall",
        "maple",
        "auditorium"
    ],
    "wof:name":"Erabliere LA Grillade Inc",
    "wof:placetype":"venue"
},
  "geometry": {"coordinates":[-72.721771,45.397995],"type":"Point"}
}