{
  "type": "Feature",
  "properties": {
    "addr:full":"110 12E Rue Laval QC H7N 1S6",
    "addr:housenumber":"110",
    "addr:postcode":"h7n 1s6",
    "addr:street":"12E Rue",
    "iso:country":"CA",
    "sg:address":"110 12E Rue",
    "sg:city":"Laval",
    "sg:classifiers":[
        {
            "category":"Freight",
            "type":"Transportation"
        }
    ],
    "sg:phone":"+1 450 629 2768",
    "sg:postcode":"H7N 1S6",
    "sg:province":"QC",
    "sg:tags":[
        "customs",
        "broker",
        "trucking"
    ],
    "wof:name":"Gen-Cha Transport Logistiques",
    "wof:placetype":"venue"
},
  "geometry": {"coordinates":[-73.695915,45.563988],"type":"Point"}
}