{
  "type": "Feature",
  "properties": {
    "addr:full":"Burnaby BC V5C 5N1",
    "addr:postcode":"v5c 5n1",
    "iso:country":"CA",
    "sg:city":"Burnaby",
    "sg:classifiers":[
        {
            "category":"Wholesale",
            "subcategory":"Furniture",
            "type":"Manufacturing & Wholesale Goods"
        }
    ],
    "sg:phone":"+1 604 430 4246",
    "sg:postcode":"V5C 5N1",
    "sg:province":"BC",
    "sg:tags":[
        "protection",
        "check",
        "mach"
    ],
    "wof:name":"Paymaster Chequewriters",
    "wof:placetype":"venue"
},
  "geometry": {"coordinates":[-122.997825623,49.263469696],"type":"Point"}
}