{
  "type": "Feature",
  "properties": {
    "addr:full":"546 Portage Ave Winnipeg MB R3C 0G3",
    "addr:housenumber":"546",
    "addr:postcode":"r3c 0g3",
    "addr:street":"Portage Ave",
    "iso:country":"CA",
    "sg:address":"546 Portage Ave",
    "sg:city":"Winnipeg",
    "sg:classifiers":[
        {
            "category":"Organizations",
            "subcategory":"Religious Organization",
            "type":"Services"
        }
    ],
    "sg:phone":"+1 204 786 7477",
    "sg:postcode":"R3C 0G3",
    "sg:province":"MB",
    "sg:tags":[
        "church"
    ],
    "wof:name":"Elim Chapel",
    "wof:placetype":"venue"
},
  "geometry": {"coordinates":[-97.154586792,49.8894081116],"type":"Point"}
}