{
  "type": "Feature",
  "properties": {
    "addr:full":"6300 Boul DE L'Ormiere Quebec QC G1P 1K7",
    "addr:housenumber":"6300",
    "addr:postcode":"g1p 1k7",
    "addr:street":"Boul De L'Ormiere",
    "iso:country":"CA",
    "sg:address":"6300 Boul DE L'Ormiere",
    "sg:city":"Quebec",
    "sg:classifiers":[
        {
            "category":"Bars & Pubs",
            "type":"Food & Drink"
        }
    ],
    "sg:phone":"+1 418 872 8382",
    "sg:postcode":"G1P 1K7",
    "sg:province":"QC",
    "sg:tags":[
        "lounge",
        "parlor",
        "billiard",
        "cocktail"
    ],
    "wof:name":"Sporalie Pro Billard",
    "wof:placetype":"venue"
},
  "geometry": {"coordinates":[-71.3399353027,46.8249206543],"type":"Point"}
}