{
  "type": "Feature",
  "properties": {
    "addr:full":"8050 Boul Cavendish Saint-Laurent QC H4T 1T1",
    "addr:housenumber":"8050",
    "addr:postcode":"h4t 1t1",
    "addr:street":"Boul Cavendish",
    "iso:country":"CA",
    "sg:address":"8050 Boul Cavendish",
    "sg:city":"Saint-Laurent",
    "sg:classifiers":[
        {
            "category":"Wholesale",
            "subcategory":"Chemicals & Plastics",
            "type":"Manufacturing & Wholesale Goods"
        }
    ],
    "sg:phone":"+1 514 731 0333",
    "sg:postcode":"H4T 1T1",
    "sg:province":"QC",
    "sg:tags":[
        "product",
        "polyurethane"
    ],
    "wof:name":"Montel",
    "wof:placetype":"venue"
},
  "geometry": {"coordinates":[-73.686806,45.486828],"type":"Point"}
}