{
  "type": "Feature",
  "properties": {
    "addr:full":"Dorchester ON N0L 1G6",
    "addr:postcode":"n0l 1g6",
    "iso:country":"CA",
    "sg:city":"Dorchester",
    "sg:classifiers":[
        {
            "category":"Building & Trades",
            "subcategory":"Construction",
            "type":"Services"
        }
    ],
    "sg:phone":"+1 519 268 3252",
    "sg:postcode":"N0L 1G6",
    "sg:province":"ON",
    "sg:tags":[
        "excavating",
        "contractor",
        "general"
    ],
    "wof:name":"Nethercott Excavating Ltd",
    "wof:placetype":"venue"
},
  "geometry": {"coordinates":[-81.0499420166,42.986114502],"type":"Point"}
}