{
  "type": "Feature",
  "properties": {
    "addr:full":"352 High St E Strathroy ON N7G 3W4",
    "addr:housenumber":"352",
    "addr:postcode":"n7g 3w4",
    "addr:street":"High St E",
    "iso:country":"CA",
    "sg:address":"352 High St E",
    "sg:city":"Strathroy",
    "sg:classifiers":[
        {
            "category":"Building & Trades",
            "subcategory":"Construction",
            "type":"Services"
        }
    ],
    "sg:phone":"+1 519 245 4050",
    "sg:postcode":"N7G 3W4",
    "sg:province":"ON",
    "sg:tags":[
        "excavating",
        "tank",
        "septic",
        "contractor"
    ],
    "wof:name":"Zwart Excavating Ltd",
    "wof:placetype":"venue"
},
  "geometry": {"coordinates":[-81.6078720093,42.9608078003],"type":"Point"}
}