{
  "type": "Feature",
  "properties": {
    "addr:full":"415 Willow St Truro NS B2N 6T2",
    "addr:housenumber":"415",
    "addr:postcode":"b2n 6t2",
    "addr:street":"Willow St",
    "iso:country":"CA",
    "sg:address":"415 Willow St",
    "sg:city":"Truro",
    "sg:classifiers":[
        {
            "category":"Education",
            "subcategory":"Dance Studio",
            "type":"Public Place"
        }
    ],
    "sg:phone":"+1 902 895 2827",
    "sg:postcode":"B2N 6T2",
    "sg:province":"NS",
    "sg:tags":[
        "instruction",
        "dancing"
    ],
    "wof:name":"Lauri Morash School of Dance",
    "wof:placetype":"venue"
},
  "geometry": {"coordinates":[-63.293427,45.350143],"type":"Point"}
}