{
  "type": "Feature",
  "properties": {
    "addr:full":"733 Rue Gaudreault Saint-Ludger-DE-Milot QC G0W 2B0",
    "addr:housenumber":"733",
    "addr:postcode":"g0w 2b0",
    "addr:street":"Rue Gaudreault",
    "iso:country":"CA",
    "sg:address":"733 Rue Gaudreault",
    "sg:city":"Saint-Ludger-DE-Milot",
    "sg:classifiers":[
        {
            "category":"Social Services",
            "type":"Services"
        }
    ],
    "sg:phone":"+1 418 373 2324",
    "sg:postcode":"G0W 2B0",
    "sg:province":"QC",
    "sg:tags":[
        "organization",
        "association",
        "welfare"
    ],
    "wof:name":"Centre DE Svc DE Sante",
    "wof:placetype":"venue"
},
  "geometry": {"coordinates":[-71.81926727290001,48.8986816406],"type":"Point"}
}