{
  "type": "Feature",
  "properties": {
    "iso:country":"CA",
    "sg:address":"1680 Richmond St",
    "sg:city":"London",
    "sg:classifiers":[
        {
            "category":"Shopping",
            "subcategory":"Clothing, Apparel, & Fashions",
            "type":"Retail Goods"
        }
    ],
    "sg:phone":"+1 519 679 4505",
    "sg:postcode":"N6G 3Y9",
    "sg:province":"ON",
    "sg:tags":[
        "t"
    ],
    "wof:name":"Backstage",
    "wof:placetype":"venue"
},
  "geometry": {"coordinates":[-81.2817077637,43.0252723694],"type":"Point"}
}