{
  "type": "Feature",
  "properties": {
    "iso:country":"CA",
    "sg:city":"Montreal-Est",
    "sg:classifiers":[
        {
            "category":"Autos & Motor Vehicles",
            "subcategory":"Fuel & Gas Station",
            "type":"Retail Goods"
        }
    ],
    "sg:phone":"+1 514 645 6526",
    "sg:postcode":"H1L 6J7",
    "sg:province":"QC",
    "sg:tags":[
        "oil"
    ],
    "wof:name":"Olco Petroleum Group Inc",
    "wof:placetype":"venue"
},
  "geometry": {"coordinates":[-73.518089,45.612907],"type":"Point"}
}