{
  "type": "Feature",
  "properties": {
    "addr:full":"6343 Boul Robert Saint-Leonard QC H1P 1N2",
    "addr:housenumber":"6343",
    "addr:postcode":"h1p 1n2",
    "addr:street":"Boul Robert",
    "iso:country":"CA",
    "sg:address":"6343 Boul Robert",
    "sg:city":"Saint-Leonard",
    "sg:classifiers":[
        {
            "category":"Food & Beverages",
            "subcategory":"Groceries & Convenience Stores",
            "type":"Retail Goods"
        }
    ],
    "sg:phone":"+1 514 321 1132",
    "sg:postcode":"H1P 1N2",
    "sg:province":"QC",
    "wof:name":"Depanneur Pina",
    "wof:placetype":"venue"
},
  "geometry": {"coordinates":[-73.58869900000001,45.596107],"type":"Point"}
}