{
  "type": "Feature",
  "properties": {
    "addr:full":"27 Harwood Ave S Ajax ON L1S 2B8",
    "addr:housenumber":"27",
    "addr:postcode":"l1s 2b8",
    "addr:street":"Harwood Ave S",
    "iso:country":"CA",
    "sg:address":"27 Harwood Ave S",
    "sg:city":"Ajax",
    "sg:classifiers":[
        {
            "category":"Cinema",
            "subcategory":"Movie Rental",
            "type":"Entertainment"
        }
    ],
    "sg:phone":"+1 905 426 6434",
    "sg:postcode":"L1S 2B8",
    "sg:province":"ON",
    "sg:tags":[
        "leasing",
        "video",
        "disc",
        "tape"
    ],
    "wof:name":"Adult Movie Warehouse",
    "wof:placetype":"venue"
},
  "geometry": {"coordinates":[-79.024292,43.858135],"type":"Point"}
}