{
  "type": "Feature",
  "properties": {
    "iso:country":"CA",
    "sg:address":"843 Park St S",
    "sg:city":"Peterborough",
    "sg:classifiers":[
        {
            "category":"Manufacturing",
            "subcategory":"Food",
            "type":"Manufacturing & Wholesale Goods"
        }
    ],
    "sg:phone":"+1 705 876 9110",
    "sg:postcode":"K9J 3V1",
    "sg:province":"ON",
    "sg:tags":[
        "malt",
        "extract"
    ],
    "wof:name":"United Canadian Malt Ltd",
    "wof:placetype":"venue"
},
  "geometry": {"coordinates":[-78.3225784302,44.2875099182],"type":"Point"}
}