{
  "type": "Feature",
  "properties": {
    "addr:full":"114 Whites Rd Trenton ON K8V 5P5",
    "addr:housenumber":"114",
    "addr:postcode":"k8v 5p5",
    "addr:street":"Whites Rd",
    "iso:country":"CA",
    "sg:address":"114 Whites Rd",
    "sg:city":"Trenton",
    "sg:classifiers":[
        {
            "category":"Health Services",
            "subcategory":"Nursing And Care Facility",
            "type":"Services"
        }
    ],
    "sg:phone":"+1 613 392 1615",
    "sg:postcode":"K8V 5P5",
    "sg:province":"ON",
    "sg:tags":[
        "home",
        "retirement",
        "community"
    ],
    "wof:name":"Carrington Retirement Rsdnce",
    "wof:placetype":"venue"
},
  "geometry": {"coordinates":[-77.57630899999999,44.101139],"type":"Point"}
}