{
  "type": "Feature",
  "properties": {
    "addr:full":"1872 Queen St E Toronto ON M4L 1H2",
    "addr:housenumber":"1872",
    "addr:postcode":"m4l 1h2",
    "addr:street":"Queen St E",
    "iso:country":"CA",
    "sg:address":"1872 Queen St E",
    "sg:city":"Toronto",
    "sg:classifiers":[
        {
            "category":"Personal",
            "type":"Services"
        }
    ],
    "sg:phone":"+1 416 699 8180",
    "sg:postcode":"M4L 1H2",
    "sg:province":"ON",
    "sg:tags":[
        "spa",
        "electrolysis"
    ],
    "wof:name":"Ingrid's Place",
    "wof:placetype":"venue"
},
  "geometry": {"coordinates":[-79.30645,43.668755],"type":"Point"}
}