{
  "type": "Feature",
  "properties": {
    "iso:country":"CA",
    "sg:address":"59 Main St",
    "sg:city":"Iroquois Falls A",
    "sg:classifiers":[
        {
            "category":"Social Services",
            "subcategory":"Child Care",
            "type":"Services"
        }
    ],
    "sg:phone":"+1 705 232 5302",
    "sg:postcode":"P0K 1G0",
    "sg:province":"ON",
    "wof:name":"Daycare Centre",
    "wof:placetype":"venue"
},
  "geometry": {"coordinates":[-80.6819076538,48.7580299377],"type":"Point"}
}