{
  "type": "Feature",
  "properties": {
    "addr:full":"5600 Av DE Gaspe Montreal QC H2T 2A7",
    "addr:housenumber":"5600",
    "addr:postcode":"h2t 2a7",
    "addr:street":"Av De Gaspe",
    "iso:country":"CA",
    "sg:address":"5600 Av DE Gaspe",
    "sg:city":"Montreal",
    "sg:classifiers":[
        {
            "category":"Home & Garden",
            "subcategory":"Building Materials",
            "type":"Retail Goods"
        }
    ],
    "sg:phone":"+1 514 271 3225",
    "sg:postcode":"H2T 2A7",
    "sg:province":"QC",
    "sg:tags":[
        "windows",
        "door"
    ],
    "wof:name":"Aluminium St Viateur Ltee",
    "wof:placetype":"venue"
},
  "geometry": {"coordinates":[-73.59802999999999,45.527832],"type":"Point"}
}