{
  "type": "Feature",
  "properties": {
    "iso:country":"CA",
    "sg:address":"5659 Rue Chambord",
    "sg:city":"Montreal",
    "sg:classifiers":[
        {
            "category":"Retail",
            "subcategory":"Auto Repair",
            "type":"Services"
        }
    ],
    "sg:phone":"+1 514 273 4341",
    "sg:postcode":"H2G 3B5",
    "sg:province":"QC",
    "sg:tags":[
        "repairing",
        "automobile"
    ],
    "wof:name":"Garage Francisco",
    "wof:placetype":"venue"
},
  "geometry": {"coordinates":[-73.5918502808,45.5365829468],"type":"Point"}
}