{
  "type": "Feature",
  "properties": {
    "addr:full":"152 Pemberton Ave North Vancouver BC V7P 2R5",
    "addr:housenumber":"152",
    "addr:postcode":"v7p 2r5",
    "addr:street":"Pemberton Ave",
    "iso:country":"CA",
    "sg:address":"152 Pemberton Ave",
    "sg:city":"North Vancouver",
    "sg:classifiers":[
        {
            "category":"Restaurant",
            "type":"Food & Drink"
        }
    ],
    "sg:phone":"+1 604 988 8162",
    "sg:postcode":"V7P 2R5",
    "sg:province":"BC",
    "wof:name":"Lunch Bucket Deli",
    "wof:placetype":"venue"
},
  "geometry": {"coordinates":[-123.107704,49.318012],"type":"Point"}
}