{
  "type": "Feature",
  "properties": {
    "iso:country":"CA",
    "sg:city":"Saskatoon",
    "sg:classifiers":[
        {
            "category":"Shopping",
            "type":"Retail Goods"
        }
    ],
    "sg:phone":"+1 306 665 9911",
    "sg:postcode":"S7L 7L1",
    "sg:province":"SK",
    "sg:tags":[
        "art",
        "gallery",
        "dealer"
    ],
    "wof:name":"Prairie Unique Gifts",
    "wof:placetype":"venue"
},
  "geometry": {"coordinates":[-106.691184998,52.1682777405],"type":"Point"}
}