{
  "type": "Feature",
  "properties": {
    "addr:full":"St. John's NL A1C 1K4",
    "addr:postcode":"a1c 1k4",
    "iso:country":"CA",
    "sg:city":"St. John's",
    "sg:classifiers":[
        {
            "category":"Professional",
            "subcategory":"Lawyer & Legal Services",
            "type":"Services"
        }
    ],
    "sg:phone":"+1 709 722 7584",
    "sg:postcode":"A1C 1K4",
    "sg:province":"NL",
    "sg:tags":[
        "attorney"
    ],
    "wof:name":"Joy, John L",
    "wof:placetype":"venue"
},
  "geometry": {"coordinates":[-52.699375,47.572086],"type":"Point"}
}