{
  "type": "Feature",
  "properties": {
    "addr:full":"312 Lake St St Catharines ON L2N 4H4",
    "addr:housenumber":"312",
    "addr:postcode":"l2n 4h4",
    "addr:street":"Lake St",
    "iso:country":"CA",
    "sg:address":"312 Lake St",
    "sg:city":"St Catharines",
    "sg:classifiers":[
        {
            "category":"Restaurant",
            "type":"Food & Drink"
        }
    ],
    "sg:phone":"+1 905 934 7715",
    "sg:postcode":"L2N 4H4",
    "sg:province":"ON",
    "wof:name":"Frego's Grillhouse & Bar",
    "wof:placetype":"venue"
},
  "geometry": {"coordinates":[-79.25157900000001,43.185585],"type":"Point"}
}