{
  "type": "Feature",
  "properties": {
    "addr:full":"1028 Boul Saint-Joseph E Montreal QC H2J 1L1",
    "addr:housenumber":"1028",
    "addr:postcode":"h2j 1l1",
    "addr:street":"Boul Saint-Joseph E",
    "iso:country":"CA",
    "sg:address":"1028 Boul Saint-Joseph E",
    "sg:city":"Montreal",
    "sg:classifiers":[
        {
            "category":"Health Services",
            "subcategory":"Doctor",
            "type":"Services"
        }
    ],
    "sg:phone":"+1 514 523 0522",
    "sg:postcode":"H2J 1L1",
    "sg:province":"QC",
    "sg:tags":[
        "psychoanalyst"
    ],
    "wof:name":"Pelletier, Robert",
    "wof:placetype":"venue"
},
  "geometry": {"coordinates":[-73.58438110349999,45.5297279358],"type":"Point"}
}