{
  "type": "Feature",
  "properties": {
    "addr:full":"100 Rue Belvedere S Sherbrooke QC J1H 4B5",
    "addr:housenumber":"100",
    "addr:postcode":"j1h 4b5",
    "addr:street":"Rue Belvedere S",
    "iso:country":"CA",
    "sg:address":"100 Rue Belvedere S",
    "sg:city":"Sherbrooke",
    "sg:classifiers":[
        {
            "category":"Organizations",
            "subcategory":"Professional Association",
            "type":"Services"
        }
    ],
    "sg:phone":"+1 819 563 9292",
    "sg:postcode":"J1H 4B5",
    "sg:province":"QC",
    "wof:name":"Regroupement DE Proprietaires",
    "wof:placetype":"venue"
},
  "geometry": {"coordinates":[-71.89585113530001,45.3973884583],"type":"Point"}
}