{
  "type": "Feature",
  "properties": {
    "addr:full":"Abbotsford BC V2T 6K8",
    "addr:postcode":"v2t 6k8",
    "iso:country":"CA",
    "sg:city":"Abbotsford",
    "sg:classifiers":[
        {
            "category":"Retail",
            "subcategory":"Car Wash",
            "type":"Services"
        }
    ],
    "sg:phone":"+1 604 864 4998",
    "sg:postcode":"V2T 6K8",
    "sg:province":"BC",
    "sg:tags":[
        "polishing",
        "washing"
    ],
    "wof:name":"Fraser Valley Auto Glass",
    "wof:placetype":"venue"
},
  "geometry": {"coordinates":[-122.358116,49.045765],"type":"Point"}
}