{
  "type": "Feature",
  "properties": {
    "addr:full":"RR 4 STN Main Owen Sound ON N4K 5N6",
    "addr:postcode":"n4k 5n6",
    "addr:street":"Rr 4 Stn Main",
    "iso:country":"CA",
    "sg:address":"RR 4 STN Main",
    "sg:city":"Owen Sound",
    "sg:classifiers":[
        {
            "category":"Travel",
            "subcategory":"Campground",
            "type":"Entertainment"
        }
    ],
    "sg:phone":"+1 519 794 3297",
    "sg:postcode":"N4K 5N6",
    "sg:province":"ON",
    "wof:name":"Sunny Valley Park",
    "wof:placetype":"venue"
},
  "geometry": {"coordinates":[-80.942604,44.564877],"type":"Point"}
}