{
  "type": "Feature",
  "properties": {
    "addr:full":"3259 County Rd 47 Brechin ON L0K 1B0",
    "addr:housenumber":"3259;47",
    "addr:postcode":"l0k 1b0",
    "addr:street":"County Rd",
    "iso:country":"CA",
    "sg:address":"3259 County Rd 47",
    "sg:city":"Brechin",
    "sg:classifiers":[
        {
            "category":"Health Services",
            "subcategory":"Doctor",
            "type":"Services"
        }
    ],
    "sg:phone":"+1 705 484 5319",
    "sg:postcode":"L0K 1B0",
    "sg:province":"ON",
    "sg:tags":[
        "dentist"
    ],
    "wof:name":"Skobe, V G DDS",
    "wof:placetype":"venue"
},
  "geometry": {"coordinates":[-79.1767730713,44.5475654602],"type":"Point"}
}