{
  "type": "Feature",
  "properties": {
    "addr:full":"610 30 St N Lethbridge AB T1H 5G6",
    "addr:housenumber":"610 30",
    "addr:postcode":"t1h 5g6",
    "addr:street":"St N",
    "iso:country":"CA",
    "sg:address":"610 30 St N",
    "sg:city":"Lethbridge",
    "sg:classifiers":[
        {
            "category":"Wholesale",
            "subcategory":"Machinery & Supplies",
            "type":"Manufacturing & Wholesale Goods"
        }
    ],
    "sg:phone":"+1 403 329 6011",
    "sg:postcode":"T1H 5G6",
    "sg:province":"AB",
    "sg:tags":[
        "contractor"
    ],
    "wof:name":"Evcon Farm Equipment Ltd",
    "wof:placetype":"venue"
},
  "geometry": {"coordinates":[-112.796905518,49.7086334229],"type":"Point"}
}