{
  "type": "Feature",
  "properties": {
    "addr:full":"Sarnia ON N7T 7H3",
    "addr:postcode":"n7t 7h3",
    "iso:country":"CA",
    "sg:city":"Sarnia",
    "sg:classifiers":[
        {
            "category":"Wholesale",
            "subcategory":"Machinery & Supplies",
            "type":"Manufacturing & Wholesale Goods"
        }
    ],
    "sg:phone":"+1 519 332 0005",
    "sg:postcode":"N7T 7H3",
    "sg:province":"ON",
    "sg:tags":[
        "equipment",
        "pump",
        "hydraulic"
    ],
    "wof:name":"Kinecor Inc",
    "wof:placetype":"venue"
},
  "geometry": {"coordinates":[-82.36093139650001,42.9455795288],"type":"Point"}
}