{
  "type": "Feature",
  "properties": {
    "iso:country":"CA",
    "sg:address":"685 Wilson St",
    "sg:city":"Victoria",
    "sg:classifiers":[
        {
            "category":"Building & Trades",
            "subcategory":"Construction",
            "type":"Services"
        }
    ],
    "sg:phone":"+1 250 388 6844",
    "sg:postcode":"V9A 3H3",
    "sg:province":"BC",
    "sg:tags":[
        "general",
        "contractor"
    ],
    "wof:name":"Glacier Insulation Ltd",
    "wof:placetype":"venue"
},
  "geometry": {"coordinates":[-123.390121,48.432423],"type":"Point"}
}