{
  "type": "Feature",
  "properties": {
    "addr:full":"104 4th St W Kindersley SK S0L 1S0",
    "addr:housenumber":"104",
    "addr:postcode":"s0l 1s0",
    "addr:street":"4Th St W Kindersley",
    "iso:country":"CA",
    "sg:address":"104 4th St W",
    "sg:city":"Kindersley",
    "sg:classifiers":[
        {
            "category":"Autos & Motor Vehicles",
            "subcategory":"Auto Supplies",
            "type":"Retail Goods"
        }
    ],
    "sg:phone":"+1 306 463 2667",
    "sg:postcode":"S0L 1S0",
    "sg:province":"SK",
    "sg:tags":[
        "automobile",
        "parts"
    ],
    "wof:name":"Uap Napa Auto Parts",
    "wof:placetype":"venue"
},
  "geometry": {"coordinates":[-109.161484,51.462921],"type":"Point"}
}