{
  "type": "Feature",
  "properties": {
    "addr:full":"160 Pinewood Park Dr North Bay ON P1B 8Z4",
    "addr:housenumber":"160",
    "addr:postcode":"p1b 8z4",
    "addr:street":"Pinewood Park Dr",
    "iso:country":"CA",
    "sg:address":"160 Pinewood Park Dr",
    "sg:city":"North Bay",
    "sg:classifiers":[
        {
            "category":"Professional",
            "subcategory":"Accounting & Tax Preparation",
            "type":"Services"
        }
    ],
    "sg:phone":"+1 705 495 2522",
    "sg:postcode":"P1B 8Z4",
    "sg:province":"ON",
    "sg:tags":[
        "accountant"
    ],
    "wof:name":"Hebert, Carolyn",
    "wof:placetype":"venue"
},
  "geometry": {"coordinates":[-79.3899688721,46.2602844238],"type":"Point"}
}