{
  "type": "Feature",
  "properties": {
    "addr:full":"295 Paxton Cres Newmarket ON L3X 2C3",
    "addr:housenumber":"295",
    "addr:postcode":"l3x 2c3",
    "addr:street":"Paxton Cres",
    "iso:country":"CA",
    "sg:address":"295 Paxton Cres",
    "sg:city":"Newmarket",
    "sg:classifiers":[
        {
            "category":"Retail",
            "subcategory":"Repair Shop",
            "type":"Services"
        }
    ],
    "sg:phone":"+1 905 954 0062",
    "sg:postcode":"L3X 2C3",
    "sg:province":"ON",
    "sg:tags":[
        "tool",
        "parts"
    ],
    "wof:name":"Just Postholes",
    "wof:placetype":"venue"
},
  "geometry": {"coordinates":[-79.488876,44.034328],"type":"Point"}
}