{
  "type": "Feature",
  "properties": {
    "addr:full":"1129 Capreol Lake Rd Capreol ON P0M 1H0",
    "addr:housenumber":"1129",
    "addr:postcode":"p0m 1h0",
    "addr:street":"Capreol Lake Rd",
    "iso:country":"CA",
    "sg:address":"1129 Capreol Lake Rd",
    "sg:city":"Capreol",
    "sg:classifiers":[
        {
            "category":"Freight",
            "type":"Transportation"
        }
    ],
    "sg:phone":"+1 705 690 3613",
    "sg:postcode":"P0M 1H0",
    "sg:province":"ON",
    "sg:tags":[
        "contractor",
        "landscape",
        "trucking"
    ],
    "wof:name":"Jetty's Contracting",
    "wof:placetype":"venue"
},
  "geometry": {"coordinates":[-80.91938,46.665329],"type":"Point"}
}