{
  "type": "Feature",
  "properties": {
    "iso:country":"CA",
    "sg:address":"8170 Ch Montview",
    "sg:city":"Mont-Royal",
    "sg:classifiers":[
        {
            "category":"Wholesale",
            "subcategory":"Durable Goods & Equipment",
            "type":"Manufacturing & Wholesale Goods"
        }
    ],
    "sg:phone":"+1 514 736 2744",
    "sg:postcode":"H4P 2L7",
    "sg:province":"QC",
    "sg:tags":[
        "importer"
    ],
    "wof:name":"Cinotex Canada",
    "wof:placetype":"venue"
},
  "geometry": {"coordinates":[-73.6690750122,45.4914550781],"type":"Point"}
}