{
  "type": "Feature",
  "properties": {
    "addr:full":"2108A St George Ave Saskatoon SK S7M 0K7",
    "addr:housenumber":"2108a",
    "addr:postcode":"s7m 0k7",
    "addr:street":"St George Ave",
    "iso:country":"CA",
    "sg:address":"2108A St George Ave",
    "sg:city":"Saskatoon",
    "sg:classifiers":[
        {
            "category":"Manufacturing",
            "subcategory":"Toys & Sporting Goods",
            "type":"Manufacturing & Wholesale Goods"
        }
    ],
    "sg:phone":"+1 306 955 9907",
    "sg:postcode":"S7M 0K7",
    "sg:province":"SK",
    "sg:tags":[
        "hobby",
        "model",
        "supply"
    ],
    "wof:name":"Draganfly Innovations Inc",
    "wof:placetype":"venue"
},
  "geometry": {"coordinates":[-106.673531,52.105019],"type":"Point"}
}