{
  "type": "Feature",
  "properties": {
    "addr:full":"1582 Pembina Ave Winkler MB R6W 4B4",
    "addr:housenumber":"1582",
    "addr:postcode":"r6w 4b4",
    "addr:street":"Pembina Ave",
    "iso:country":"CA",
    "sg:address":"1582 Pembina Ave",
    "sg:city":"Winkler",
    "sg:classifiers":[
        {
            "category":"Manufacturing",
            "subcategory":"Rubber & Plastics",
            "type":"Manufacturing & Wholesale Goods"
        }
    ],
    "sg:phone":"+1 204 325 7304",
    "sg:postcode":"R6W 4B4",
    "sg:province":"MB",
    "sg:tags":[
        "mat",
        "matting"
    ],
    "wof:name":"Gateway Resources Inc",
    "wof:placetype":"venue"
},
  "geometry": {"coordinates":[-97.955482,49.177513],"type":"Point"}
}