{
  "type": "Feature",
  "properties": {
    "addr:full":"Casselman ON K0A 1M0",
    "addr:postcode":"k0a 1m0",
    "iso:country":"CA",
    "sg:city":"Casselman",
    "sg:classifiers":[
        {
            "category":"Education",
            "subcategory":"School",
            "type":"Public Place"
        }
    ],
    "sg:phone":"+1 613 764 7332",
    "sg:postcode":"K0A 1M0",
    "sg:province":"ON",
    "wof:name":"Campus DE Casselman",
    "wof:placetype":"venue"
},
  "geometry": {"coordinates":[-75.087891,45.314308],"type":"Point"}
}