{
  "type": "Feature",
  "properties": {
    "addr:full":"Vercheres QC J0L 2R0",
    "addr:postcode":"j0l 2r0",
    "iso:country":"CA",
    "sg:city":"Vercheres",
    "sg:classifiers":[
        {
            "category":"Building & Trades",
            "subcategory":"Construction",
            "type":"Services"
        }
    ],
    "sg:phone":"+1 450 583 3222",
    "sg:postcode":"J0L 2R0",
    "sg:province":"QC",
    "sg:tags":[
        "excavating",
        "contractor"
    ],
    "wof:name":"C Perreault Construction Inc",
    "wof:placetype":"venue"
},
  "geometry": {"coordinates":[-73.346771,45.768845],"type":"Point"}
}