{
  "type": "Feature",
  "properties": {
    "addr:full":"423 3E Av Saint-Romuald QC G6W 5M6",
    "addr:housenumber":"423",
    "addr:postcode":"g6w 5m6",
    "addr:street":"3E Av Saint-Romuald",
    "iso:country":"CA",
    "sg:address":"423 3E Av",
    "sg:city":"Saint-Romuald",
    "sg:classifiers":[
        {
            "category":"Freight",
            "type":"Transportation"
        }
    ],
    "sg:phone":"+1 418 834 2943",
    "sg:postcode":"G6W 5M6",
    "sg:province":"QC",
    "sg:tags":[
        "trucking"
    ],
    "wof:name":"Transport Slh",
    "wof:placetype":"venue"
},
  "geometry": {"coordinates":[-71.2400894165,46.7581214905],"type":"Point"}
}