{
  "type": "Feature",
  "properties": {
    "addr:full":"259 Ward St Port Hope ON L1A 4A4",
    "addr:housenumber":"259",
    "addr:postcode":"l1a 4a4",
    "addr:street":"Ward St",
    "iso:country":"CA",
    "sg:address":"259 Ward St",
    "sg:city":"Port Hope",
    "sg:classifiers":[
        {
            "category":"Building & Trades",
            "subcategory":"Construction",
            "type":"Services"
        }
    ],
    "sg:phone":"+1 905 885 4061",
    "sg:postcode":"L1A 4A4",
    "sg:province":"ON",
    "sg:tags":[
        "excavating",
        "contractor"
    ],
    "wof:name":"Don Oliver Excavating",
    "wof:placetype":"venue"
},
  "geometry": {"coordinates":[-78.27607,43.960178],"type":"Point"}
}