{
  "type": "Feature",
  "properties": {
    "addr:full":"Hay River NT X0E 1G3",
    "addr:postcode":"x0e 1g3",
    "iso:country":"CA",
    "sg:city":"Hay River",
    "sg:classifiers":[
        {
            "category":"Professional",
            "subcategory":"Accounting & Tax Preparation",
            "type":"Services"
        }
    ],
    "sg:phone":"+1 867 874 2700",
    "sg:postcode":"X0E 1G3",
    "sg:province":"NT",
    "sg:tags":[
        "consultant",
        "return",
        "filing"
    ],
    "wof:name":"H & R Block Canada Inc",
    "wof:placetype":"venue"
},
  "geometry": {"coordinates":[-115.788551,60.806931],"type":"Point"}
}