{
  "type": "Feature",
  "properties": {
    "addr:full":"24736 Winterline Rd Pain Court ON N0P 1Z0",
    "addr:postcode":"24736;n0p 1z0",
    "addr:street":"Winterline Rd Pain",
    "iso:country":"CA",
    "sg:address":"24736 Winterline Rd",
    "sg:city":"Pain Court",
    "sg:classifiers":[
        {
            "category":"Manufacturing",
            "subcategory":"Tools & Machinery",
            "type":"Manufacturing & Wholesale Goods"
        }
    ],
    "sg:phone":"+1 519 351 9260",
    "sg:postcode":"N0P 1Z0",
    "sg:province":"ON",
    "sg:tags":[
        "machine",
        "shop"
    ],
    "wof:name":"Cartier Fabricating & Welding",
    "wof:placetype":"venue"
},
  "geometry": {"coordinates":[-82.3083572388,42.404209137],"type":"Point"}
}