{
  "type": "Feature",
  "properties": {
    "iso:country":"CA",
    "sg:address":"5023 49th Ave",
    "sg:city":"Millet",
    "sg:classifiers":[
        {
            "category":"Organizations",
            "subcategory":"Professional Association",
            "type":"Services"
        }
    ],
    "sg:phone":"+1 780 387 4185",
    "sg:postcode":"T0C 1Z0",
    "sg:province":"AB",
    "sg:tags":[
        "club"
    ],
    "wof:name":"Millet & District Lions Club",
    "wof:placetype":"venue"
},
  "geometry": {"coordinates":[-113.47228241000001,53.0944900513],"type":"Point"}
}