{
  "type": "Feature",
  "properties": {
    "addr:full":"1309 Carling Ave # L2 Ottawa ON K1Z 7L3",
    "addr:housenumber":"1309",
    "addr:postcode":"k1z 7l3",
    "addr:street":"Carling Ave # L2",
    "iso:country":"CA",
    "sg:address":"1309 Carling Ave # L2",
    "sg:city":"Ottawa",
    "sg:classifiers":[
        {
            "category":"Home & Garden",
            "subcategory":"Home Furnishings",
            "type":"Retail Goods"
        }
    ],
    "sg:phone":"+1 613 725 1222",
    "sg:postcode":"K1Z 7L3",
    "sg:province":"ON",
    "sg:tags":[
        "curtain",
        "made",
        "drapery"
    ],
    "wof:name":"Cozzy Coverings",
    "wof:placetype":"venue"
},
  "geometry": {"coordinates":[-75.734306,45.386238],"type":"Point"}
}