{
  "type": "Feature",
  "properties": {
    "addr:full":"2956 Queen St E Brampton ON L6S 5Y1",
    "addr:housenumber":"2956",
    "addr:postcode":"l6s 5y1",
    "addr:street":"Queen St E",
    "iso:country":"CA",
    "sg:address":"2956 Queen St E",
    "sg:city":"Brampton",
    "sg:classifiers":[
        {
            "category":"Autos & Motor Vehicles",
            "subcategory":"Fuel & Gas Station",
            "type":"Retail Goods"
        }
    ],
    "sg:phone":"+1 905 793 3839",
    "sg:postcode":"L6S 5Y1",
    "sg:province":"ON",
    "sg:tags":[
        "oil"
    ],
    "wof:name":"Shell Canada Ltd",
    "wof:placetype":"venue"
},
  "geometry": {"coordinates":[-79.69750999999999,43.742325],"type":"Point"}
}