{
  "type": "Feature",
  "properties": {
    "addr:full":"Granby QC J2G 9L1",
    "addr:postcode":"j2g 9l1",
    "iso:country":"CA",
    "sg:city":"Granby",
    "sg:classifiers":[
        {
            "category":"Real Estate",
            "subcategory":"Real Estate Agent",
            "type":"Services"
        }
    ],
    "sg:phone":"+1 450 378 3472",
    "sg:postcode":"J2G 9L1",
    "sg:province":"QC",
    "sg:tags":[
        "management"
    ],
    "wof:name":"Domaine Acrotere Inc",
    "wof:placetype":"venue"
},
  "geometry": {"coordinates":[-72.7434997559,45.4061965942],"type":"Point"}
}