{
  "type": "Feature",
  "properties": {
    "addr:full":"319 Danforth Ave Toronto ON M4K 1N7",
    "addr:housenumber":"319",
    "addr:postcode":"m4k 1n7",
    "addr:street":"Danforth Ave",
    "iso:country":"CA",
    "sg:address":"319 Danforth Ave",
    "sg:city":"Toronto",
    "sg:classifiers":[
        {
            "category":"Shopping",
            "subcategory":"Florist",
            "type":"Retail Goods"
        }
    ],
    "sg:phone":"+1 416 461 0704",
    "sg:postcode":"M4K 1N7",
    "sg:province":"ON",
    "wof:name":"Peter Pauls Flowers",
    "wof:placetype":"venue"
},
  "geometry": {"coordinates":[-79.35350800000001,43.677082],"type":"Point"}
}