{
  "type": "Feature",
  "properties": {
    "addr:full":"134 Main St W Huntsville ON P1H 1W5",
    "addr:housenumber":"134",
    "addr:postcode":"p1h 1w5",
    "addr:street":"Main St W",
    "iso:country":"CA",
    "sg:address":"134 Main St W",
    "sg:city":"Huntsville",
    "sg:classifiers":[
        {
            "category":"Autos & Motor Vehicles",
            "subcategory":"Automobile Sales",
            "type":"Retail Goods"
        }
    ],
    "sg:phone":"+1 705 789 5591",
    "sg:postcode":"P1H 1W5",
    "sg:province":"ON",
    "sg:tags":[
        "car",
        "dealer"
    ],
    "wof:name":"West End Motors",
    "wof:placetype":"venue"
},
  "geometry": {"coordinates":[-79.2339706421,45.3208503723],"type":"Point"}
}