{
  "type": "Feature",
  "properties": {
    "addr:full":"5 Spring Garden Ave North York ON M2N 3G1",
    "addr:housenumber":"5",
    "addr:postcode":"m2n 3g1",
    "addr:street":"Spring Garden Ave",
    "iso:country":"CA",
    "sg:address":"5 Spring Garden Ave",
    "sg:city":"North York",
    "sg:classifiers":[
        {
            "category":"Personal",
            "subcategory":"Beauty Salon",
            "type":"Services"
        }
    ],
    "sg:phone":"+1 416 222 5957",
    "sg:postcode":"M2N 3G1",
    "sg:province":"ON",
    "wof:name":"New Koa Hair Salon",
    "wof:placetype":"venue"
},
  "geometry": {"coordinates":[-79.411118,43.764282],"type":"Point"}
}