{
  "type": "Feature",
  "properties": {
    "addr:full":"Vegreville AB T9C 1L1",
    "addr:postcode":"t9c 1l1",
    "iso:country":"CA",
    "sg:city":"Vegreville",
    "sg:classifiers":[
        {
            "category":"Wholesale",
            "subcategory":"Machinery & Supplies",
            "type":"Manufacturing & Wholesale Goods"
        }
    ],
    "sg:phone":"+1 780 632 3127",
    "sg:postcode":"T9C 1L1",
    "sg:province":"AB",
    "sg:tags":[
        "farm",
        "equipment"
    ],
    "wof:name":"G & S Implements Ltd",
    "wof:placetype":"venue"
},
  "geometry": {"coordinates":[-112.045639038,53.4908981323],"type":"Point"}
}