{
  "type": "Feature",
  "properties": {
    "addr:full":"144 Moxam Landing Rd Lively ON P3Y 1N6",
    "addr:housenumber":"144",
    "addr:postcode":"p3y 1n6",
    "addr:street":"Moxam Landing Rd",
    "iso:country":"CA",
    "sg:address":"144 Moxam Landing Rd",
    "sg:city":"Lively",
    "sg:classifiers":[
        {
            "category":"Recreation",
            "type":"Entertainment"
        }
    ],
    "sg:phone":"+1 705 692 1250",
    "sg:postcode":"P3Y 1N6",
    "sg:province":"ON",
    "sg:tags":[
        "stable"
    ],
    "wof:name":"Hillsview Stables",
    "wof:placetype":"venue"
},
  "geometry": {"coordinates":[-81.08703613279999,46.4138793945],"type":"Point"}
}