{
  "type": "Feature",
  "properties": {
    "addr:full":"880 St James St Rockland ON K4K 1K2",
    "addr:housenumber":"880",
    "addr:postcode":"k4k 1k2",
    "addr:street":"St James St",
    "iso:country":"CA",
    "sg:address":"880 St James St",
    "sg:city":"Rockland",
    "sg:classifiers":[
        {
            "category":"Shopping",
            "subcategory":"Clothing, Apparel, & Fashions",
            "type":"Retail Goods"
        }
    ],
    "sg:phone":"+1 613 446 4721",
    "sg:postcode":"K4K 1K2",
    "sg:province":"ON",
    "sg:tags":[
        "item",
        "boutique"
    ],
    "wof:name":"Boutique Zodiaque",
    "wof:placetype":"venue"
},
  "geometry": {"coordinates":[-75.29304504389999,45.5460357666],"type":"Point"}
}