{
  "type": "Feature",
  "properties": {
    "addr:full":"9762 45 Ave NW Edmonton AB T6E 5C5",
    "addr:housenumber":"9762",
    "addr:postcode":"t6e 5c5",
    "addr:street":"45 Ave Nw",
    "iso:country":"CA",
    "sg:address":"9762 45 Ave NW",
    "sg:city":"Edmonton",
    "sg:classifiers":[
        {
            "category":"Manufacturing",
            "subcategory":"Rubber & Plastics",
            "type":"Manufacturing & Wholesale Goods"
        }
    ],
    "sg:phone":"+1 780 435 3771",
    "sg:postcode":"T6E 5C5",
    "sg:province":"AB",
    "sg:tags":[
        "field",
        "oil"
    ],
    "wof:name":"Shurseal Industries Ltd",
    "wof:placetype":"venue"
},
  "geometry": {"coordinates":[-113.481704712,53.4833564758],"type":"Point"}
}