{
  "type": "Feature",
  "properties": {
    "addr:full":"Kamloops BC V2C 5P2",
    "addr:postcode":"bc v2c 5p2",
    "iso:country":"CA",
    "sg:city":"Kamloops",
    "sg:classifiers":[
        {
            "category":"Wholesale",
            "subcategory":"Machinery & Supplies",
            "type":"Manufacturing & Wholesale Goods"
        }
    ],
    "sg:phone":"+1 250 314 0708",
    "sg:postcode":"V2C 5P2",
    "sg:province":"BC",
    "sg:tags":[
        "contractor"
    ],
    "wof:name":"Candig Mini Excavators Ltd",
    "wof:placetype":"venue"
},
  "geometry": {"coordinates":[-120.360291,50.661346],"type":"Point"}
}