{
  "type": "Feature",
  "properties": {
    "addr:full":"Richmond BC V6X 3Z7",
    "addr:postcode":"v6x 3z7",
    "iso:country":"CA",
    "sg:city":"Richmond",
    "sg:classifiers":[
        {
            "category":"Professional",
            "type":"Services"
        }
    ],
    "sg:phone":"+1 604 233 8886",
    "sg:postcode":"V6X 3Z7",
    "sg:province":"BC",
    "sg:tags":[
        "scientist"
    ],
    "wof:name":"Pan Universe Tech Consultants",
    "wof:placetype":"venue"
},
  "geometry": {"coordinates":[-123.127075195,49.183303833],"type":"Point"}
}