{
  "type": "Feature",
  "properties": {
    "addr:full":"4080 78 Ave NW Edmonton AB T6B 3M8",
    "addr:housenumber":"4080",
    "addr:postcode":"t6b 3m8",
    "addr:street":"78 Ave Nw",
    "iso:country":"CA",
    "sg:address":"4080 78 Ave NW",
    "sg:city":"Edmonton",
    "sg:classifiers":[
        {
            "category":"Wholesale",
            "subcategory":"Machinery & Supplies",
            "type":"Manufacturing & Wholesale Goods"
        }
    ],
    "sg:phone":"+1 780 465 4582",
    "sg:postcode":"T6B 3M8",
    "sg:province":"AB",
    "sg:tags":[
        "heat",
        "exchanger"
    ],
    "wof:name":"Fieldco Heat Exchanger Svc",
    "wof:placetype":"venue"
},
  "geometry": {"coordinates":[-113.403694,53.514404],"type":"Point"}
}