{
  "type": "Feature",
  "properties": {
    "addr:full":"150 Primrose Lane Fort Smith NT X0E 0P0",
    "addr:housenumber":"150",
    "addr:postcode":"x0e 0p0",
    "addr:street":"Primrose Lane",
    "iso:country":"CA",
    "sg:address":"150 Primrose Lane",
    "sg:city":"Fort Smith",
    "sg:classifiers":[
        {
            "category":"Travel",
            "subcategory":"Hotels & Motels",
            "type":"Entertainment"
        }
    ],
    "sg:phone":"+1 867 872 5245",
    "sg:postcode":"X0E 0P0",
    "sg:province":"NT",
    "sg:tags":[
        "breakfast",
        "accommodation",
        "bed"
    ],
    "wof:name":"Kana'Kes Tours",
    "wof:placetype":"venue"
},
  "geometry": {"coordinates":[-111.90263400000001,60.000095],"type":"Point"}
}