{
  "type": "Feature",
  "properties": {
    "iso:country":"CA",
    "sg:address":"5560 Wyandotte St E",
    "sg:city":"Windsor",
    "sg:classifiers":[
        {
            "category":"Real Estate",
            "subcategory":"Real Estate Agent",
            "type":"Services"
        }
    ],
    "sg:phone":"+1 519 948 3993",
    "sg:postcode":"N8S 1M1",
    "sg:province":"ON",
    "wof:name":"Action Plus Real Estate Market",
    "wof:placetype":"venue"
},
  "geometry": {"coordinates":[-82.96980285639999,42.3284835815],"type":"Point"}
}