{
  "type": "Feature",
  "properties": {
    "addr:full":"344 Johnson St Picton ON K0K 2T0",
    "addr:housenumber":"344",
    "addr:postcode":"k0k 2t0",
    "addr:street":"Johnson St",
    "iso:country":"CA",
    "sg:address":"344 Johnson St",
    "sg:city":"Picton",
    "sg:classifiers":[
        {
            "category":"Home & Garden",
            "subcategory":"Furniture",
            "type":"Retail Goods"
        }
    ],
    "sg:phone":"+1 613 476 6124",
    "sg:postcode":"K0K 2T0",
    "sg:province":"ON",
    "wof:name":"Duane's Furniture Outlet",
    "wof:placetype":"venue"
},
  "geometry": {"coordinates":[-77.13897705079999,44.009223938],"type":"Point"}
}