{
  "type": "Feature",
  "properties": {
    "addr:full":"1717 5th Ave W Vancouver BC V6J 1P1",
    "addr:housenumber":"1717",
    "addr:postcode":"v6j 1p1",
    "addr:street":"5Th Ave W",
    "iso:country":"CA",
    "sg:address":"1717 5th Ave W",
    "sg:city":"Vancouver",
    "sg:classifiers":[
        {
            "category":"Wholesale",
            "subcategory":"Groceries",
            "type":"Manufacturing & Wholesale Goods"
        }
    ],
    "sg:phone":"+1 604 731 4422",
    "sg:postcode":"V6J 1P1",
    "sg:province":"BC",
    "sg:tags":[
        "food",
        "product"
    ],
    "wof:name":"L B Maple Treat Inc",
    "wof:placetype":"venue"
},
  "geometry": {"coordinates":[-123.143798828,49.2672576904],"type":"Point"}
}