{
  "type": "Feature",
  "properties": {
    "addr:full":"5430 47 Ave Lacombe AB T4L 1G8",
    "addr:housenumber":"5430",
    "addr:postcode":"t4l 1g8",
    "addr:street":"47 Ave",
    "iso:country":"CA",
    "sg:address":"5430 47 Ave",
    "sg:city":"Lacombe",
    "sg:classifiers":[
        {
            "category":"Health Services",
            "subcategory":"Hospital",
            "type":"Services"
        }
    ],
    "sg:phone":"+1 403 782 3336",
    "sg:postcode":"T4L 1G8",
    "sg:province":"AB",
    "wof:name":"Lacombe Hospital & Care Ctr",
    "wof:placetype":"venue"
},
  "geometry": {"coordinates":[-113.74034899999999,52.460312],"type":"Point"}
}