{
  "type": "Feature",
  "properties": {
    "iso:country":"CA",
    "sg:address":"85 Rue D'Ottawa",
    "sg:city":"Granby",
    "sg:classifiers":[
        {
            "category":"Manufacturing",
            "subcategory":"Metals",
            "type":"Manufacturing & Wholesale Goods"
        }
    ],
    "sg:phone":"+1 450 777 1075",
    "sg:postcode":"J2G 2R9",
    "sg:province":"QC",
    "sg:tags":[
        "foundry"
    ],
    "wof:name":"Fonderie Shefford",
    "wof:placetype":"venue"
},
  "geometry": {"coordinates":[-72.7208328247,45.3996734619],"type":"Point"}
}