{
  "type": "Feature",
  "properties": {
    "iso:country":"CA",
    "sg:address":"481 Morden Rd",
    "sg:city":"Oakville",
    "sg:classifiers":[
        {
            "category":"Building & Trades",
            "subcategory":"Equipment Rental",
            "type":"Services"
        }
    ],
    "sg:phone":"+1 905 842 1770",
    "sg:postcode":"L6K 3W6",
    "sg:province":"ON",
    "sg:tags":[
        "leasing"
    ],
    "wof:name":"Key Equipment Finance",
    "wof:placetype":"venue"
},
  "geometry": {"coordinates":[-79.69501495359999,43.4414482117],"type":"Point"}
}