{
  "type": "Feature",
  "properties": {
    "addr:full":"765 Gillard St Wallaceburg ON N8A 5G7",
    "addr:housenumber":"765",
    "addr:postcode":"n8a 5g7",
    "addr:street":"Gillard St",
    "iso:country":"CA",
    "sg:address":"765 Gillard St",
    "sg:city":"Wallaceburg",
    "sg:classifiers":[
        {
            "category":"Freight",
            "type":"Transportation"
        }
    ],
    "sg:phone":"+1 519 627 1116",
    "sg:postcode":"N8A 5G7",
    "sg:province":"ON",
    "sg:tags":[
        "commercial",
        "storage"
    ],
    "wof:name":"Wallaceburg Mini Storage",
    "wof:placetype":"venue"
},
  "geometry": {"coordinates":[-82.389664,42.582081],"type":"Point"}
}