{
  "type": "Feature",
  "properties": {
    "addr:full":"2261 Rue Industrielle Bas-Caraquet NB E1W 5Z1",
    "addr:housenumber":"2261",
    "addr:postcode":"e1w 5z1",
    "addr:street":"Rue Industrielle Bas-Caraquet",
    "iso:country":"CA",
    "sg:address":"2261 Rue Industrielle",
    "sg:city":"Bas-Caraquet",
    "sg:classifiers":[
        {
            "category":"Manufacturing",
            "subcategory":"Food",
            "type":"Manufacturing & Wholesale Goods"
        }
    ],
    "sg:phone":"+1 506 727 7247",
    "sg:postcode":"E1W 5Z1",
    "sg:province":"NB",
    "sg:tags":[
        "packer",
        "fish"
    ],
    "wof:name":"Pecheries St Paul Ltee",
    "wof:placetype":"venue"
},
  "geometry": {"coordinates":[-64.8507385254,47.8069610596],"type":"Point"}
}