{
  "type": "Feature",
  "properties": {
    "addr:full":"Rockland ON K4K 1K7",
    "addr:postcode":"k4k 1k7",
    "addr:street":"Rockland",
    "iso:country":"CA",
    "sg:city":"Rockland",
    "sg:classifiers":[
        {
            "category":"Autos & Motor Vehicles",
            "subcategory":"Automobile Sales",
            "type":"Retail Goods"
        }
    ],
    "sg:phone":"+1 613 446 0173",
    "sg:postcode":"K4K 1K7",
    "sg:province":"ON",
    "sg:tags":[
        "car",
        "dealer"
    ],
    "wof:name":"Doug's Auto & Equipment Repair",
    "wof:placetype":"venue"
},
  "geometry": {"coordinates":[-75.29304504389999,45.5460357666],"type":"Point"}
}