{
  "type": "Feature",
  "properties": {
    "addr:full":"5150 72 Ave NW Edmonton AB T6B 3H4",
    "addr:housenumber":"5150",
    "addr:postcode":"t6b 3h4",
    "addr:street":"72 Ave Nw",
    "iso:country":"CA",
    "sg:address":"5150 72 Ave NW",
    "sg:city":"Edmonton",
    "sg:classifiers":[
        {
            "category":"Shopping",
            "subcategory":"Luggage & Leather Goods",
            "type":"Retail Goods"
        }
    ],
    "sg:phone":"+1 780 436 3733",
    "sg:postcode":"T6B 3H4",
    "sg:province":"AB",
    "sg:tags":[
        "case"
    ],
    "wof:name":"Rock Solid Cases Inc",
    "wof:placetype":"venue"
},
  "geometry": {"coordinates":[-113.419601,53.508286],"type":"Point"}
}