{
  "type": "Feature",
  "properties": {
    "iso:country":"CA",
    "sg:address":"30 Beech Ave",
    "sg:city":"Toronto",
    "sg:classifiers":[
        {
            "category":"Professional",
            "subcategory":"Business Services",
            "type":"Services"
        }
    ],
    "sg:phone":"+1 416 694 6438",
    "sg:postcode":"M4E 3H2",
    "sg:province":"ON",
    "sg:tags":[
        "event"
    ],
    "wof:name":"Lavender Poodle Productions",
    "wof:placetype":"venue"
},
  "geometry": {"coordinates":[-79.2872085571,43.671333313],"type":"Point"}
}