{
  "type": "Feature",
  "properties": {
    "addr:full":"Mississauga ON L5T 2J5",
    "addr:postcode":"l5t 2j5",
    "iso:country":"CA",
    "sg:city":"Mississauga",
    "sg:phone":"+1 905 670 9713",
    "sg:postcode":"L5T 2J5",
    "sg:province":"ON",
    "sg:tags":[
        "fixture",
        "store"
    ],
    "wof:name":"Ashford Interiors",
    "wof:placetype":"venue"
},
  "geometry": {"coordinates":[-79.66753387449999,43.6661376953],"type":"Point"}
}