{
  "type": "Feature",
  "properties": {
    "addr:full":"4005 Whistler Way Whistler BC V0N 1B4",
    "addr:housenumber":"4005",
    "addr:postcode":"v0n 1b4",
    "addr:street":"Whistler Way",
    "iso:country":"CA",
    "sg:address":"4005 Whistler Way",
    "sg:city":"Whistler",
    "sg:classifiers":[
        {
            "category":"Travel",
            "subcategory":"Hotels & Motels",
            "type":"Entertainment"
        }
    ],
    "sg:phone":"+1 604 682 6278",
    "sg:postcode":"V0N 1B4",
    "sg:province":"BC",
    "sg:tags":[
        "reservation"
    ],
    "wof:name":"Coast Resort At Whistler",
    "wof:placetype":"venue"
},
  "geometry": {"coordinates":[-122.957779,50.114101],"type":"Point"}
}