{
  "type": "Feature",
  "properties": {
    "addr:full":"420 Av Michel-Jasmin Dorval QC H9P 1C1",
    "addr:housenumber":"420",
    "addr:postcode":"h9p 1c1",
    "addr:street":"Av Michel-Jasmin",
    "iso:country":"CA",
    "sg:address":"420 Av Michel-Jasmin",
    "sg:city":"Dorval",
    "sg:classifiers":[
        {
            "category":"Retail",
            "subcategory":"Auto Rental",
            "type":"Services"
        }
    ],
    "sg:phone":"+1 514 631 9090",
    "sg:postcode":"H9P 1C1",
    "sg:province":"QC",
    "sg:tags":[
        "renting",
        "leasing",
        "trailer"
    ],
    "wof:name":"Remorques Le Convoi Inc",
    "wof:placetype":"venue"
},
  "geometry": {"coordinates":[-73.7342,45.454079],"type":"Point"}
}