{
  "type": "Feature",
  "properties": {
    "addr:full":"100 Bonnie Cres Elmira ON N3B 3J7",
    "addr:housenumber":"100",
    "addr:postcode":"n3b 3j7",
    "addr:street":"Bonnie Cres",
    "iso:country":"CA",
    "sg:address":"100 Bonnie Cres",
    "sg:city":"Elmira",
    "sg:classifiers":[
        {
            "category":"Retail",
            "subcategory":"Repair Shop",
            "type":"Services"
        }
    ],
    "sg:phone":"+1 519 669 1412",
    "sg:postcode":"N3B 3J7",
    "sg:province":"ON",
    "sg:tags":[
        "welding"
    ],
    "wof:name":"Vogel Welding Inc",
    "wof:placetype":"venue"
},
  "geometry": {"coordinates":[-80.554039,43.588413],"type":"Point"}
}