{
  "type": "Feature",
  "properties": {
    "addr:full":"Toronto ON M5V 1P9",
    "addr:postcode":"m5v 1p9",
    "iso:country":"CA",
    "sg:city":"Toronto",
    "sg:classifiers":[
        {
            "category":"Manufacturing",
            "subcategory":"Printing",
            "type":"Manufacturing & Wholesale Goods"
        }
    ],
    "sg:phone":"+1 416 977 2100",
    "sg:postcode":"M5V 1P9",
    "sg:province":"ON",
    "sg:tags":[
        "publisher"
    ],
    "wof:name":"Pedal Magazine",
    "wof:placetype":"venue"
},
  "geometry": {"coordinates":[-79.3922195435,43.6472930908],"type":"Point"}
}