{
  "type": "Feature",
  "properties": {
    "iso:country":"CA",
    "sg:city":"Port Coquitlam",
    "sg:classifiers":[
        {
            "category":"Government",
            "subcategory":"Office",
            "type":"Public Place"
        }
    ],
    "sg:phone":"+1 604 927 2240",
    "sg:postcode":"V3B 5Y9",
    "sg:province":"BC",
    "wof:name":"B C Employment Standards Act",
    "wof:placetype":"venue"
},
  "geometry": {"coordinates":[-122.789024353,49.2730979919],"type":"Point"}
}