{
  "type": "Feature",
  "properties": {
    "addr:full":"Markham ON L3R 5M9",
    "addr:postcode":"l3r 5m9",
    "iso:country":"CA",
    "sg:city":"Markham",
    "sg:classifiers":[
        {
            "category":"Wholesale",
            "subcategory":"Durable Goods & Equipment",
            "type":"Manufacturing & Wholesale Goods"
        }
    ],
    "sg:phone":"+1 905 305 8135",
    "sg:postcode":"L3R 5M9",
    "sg:province":"ON",
    "sg:tags":[
        "exporter"
    ],
    "wof:name":"Revell Trading Corp",
    "wof:placetype":"venue"
},
  "geometry": {"coordinates":[-79.3346862793,43.8257141113],"type":"Point"}
}