{
  "type": "Feature",
  "properties": {
    "addr:full":"2025 Av O'Brien Saint-Laurent QC H4L 3X1",
    "addr:housenumber":"2025",
    "addr:postcode":"h4l 3x1",
    "addr:street":"Av O'Brien",
    "iso:country":"CA",
    "sg:address":"2025 Av O'Brien",
    "sg:city":"Saint-Laurent",
    "sg:classifiers":[
        {
            "category":"Building & Trades",
            "subcategory":"Construction",
            "type":"Services"
        }
    ],
    "sg:phone":"+1 514 334 2595",
    "sg:postcode":"H4L 3X1",
    "sg:province":"QC",
    "sg:tags":[
        "paving",
        "contractor"
    ],
    "wof:name":"Gravel & Gravel Inc",
    "wof:placetype":"venue"
},
  "geometry": {"coordinates":[-73.680611,45.515816],"type":"Point"}
}