{
  "type": "Feature",
  "properties": {
    "iso:country":"CA",
    "sg:city":"Saskatoon",
    "sg:classifiers":[
        {
            "category":"Retail",
            "subcategory":"Auto Repair",
            "type":"Services"
        }
    ],
    "sg:phone":"+1 306 651 0232",
    "sg:postcode":"S7N 1Z3",
    "sg:province":"SK",
    "sg:tags":[
        "repairing",
        "automobile"
    ],
    "wof:name":"Fleetmaster Service",
    "wof:placetype":"venue"
},
  "geometry": {"coordinates":[-106.58872985799999,52.1315231323],"type":"Point"}
}