{
  "type": "Feature",
  "properties": {
    "addr:full":"1699 St Clair Ave W Toronto ON M6N 1J2",
    "addr:housenumber":"1699",
    "addr:postcode":"m6n 1j2",
    "addr:street":"St Clair Ave W",
    "iso:country":"CA",
    "sg:address":"1699 St Clair Ave W",
    "sg:city":"Toronto",
    "sg:classifiers":[
        {
            "category":"Shopping",
            "subcategory":"Jewelry",
            "type":"Retail Goods"
        }
    ],
    "sg:phone":"+1 416 656 6377",
    "sg:postcode":"M6N 1J2",
    "sg:province":"ON",
    "sg:tags":[
        "jeweler"
    ],
    "wof:name":"Modesto Jeweller's",
    "wof:placetype":"venue"
},
  "geometry": {"coordinates":[-79.45915222169999,43.6742935181],"type":"Point"}
}