{
  "type": "Feature",
  "properties": {
    "addr:full":"810 Edgar St Regina SK S4N 3H9",
    "addr:housenumber":"810",
    "addr:postcode":"s4n 3h9",
    "addr:street":"Edgar St",
    "iso:country":"CA",
    "sg:address":"810 Edgar St",
    "sg:city":"Regina",
    "sg:classifiers":[
        {
            "category":"Organizations",
            "subcategory":"Non-profit Organization",
            "type":"Services"
        }
    ],
    "sg:phone":"+1 306 569 0535",
    "sg:postcode":"S4N 3H9",
    "sg:province":"SK",
    "sg:tags":[
        "charitable",
        "institution"
    ],
    "wof:name":"Cosmopolitan Learning Ctr",
    "wof:placetype":"venue"
},
  "geometry": {"coordinates":[-104.588127,50.465248],"type":"Point"}
}