{
  "type": "Feature",
  "properties": {
    "addr:full":"3970 Boul Leman Laval QC H7E 1A1",
    "addr:housenumber":"3970",
    "addr:postcode":"h7e 1a1",
    "addr:street":"Boul Leman",
    "iso:country":"CA",
    "sg:address":"3970 Boul Leman",
    "sg:city":"Laval",
    "sg:classifiers":[
        {
            "category":"Building & Trades",
            "subcategory":"Construction",
            "type":"Services"
        }
    ],
    "sg:phone":"+1 450 661 6519",
    "sg:postcode":"H7E 1A1",
    "sg:province":"QC",
    "sg:tags":[
        "paving",
        "contractor"
    ],
    "wof:name":"G Giuliani Inc",
    "wof:placetype":"venue"
},
  "geometry": {"coordinates":[-73.669785,45.61367],"type":"Point"}
}