{
  "type": "Feature",
  "properties": {
    "addr:full":"854 1st Ave W Owen Sound ON N4K 4K4",
    "addr:housenumber":"854",
    "addr:postcode":"n4k 4k4",
    "addr:street":"1St Ave W",
    "iso:country":"CA",
    "sg:address":"854 1st Ave W",
    "sg:city":"Owen Sound",
    "sg:classifiers":[
        {
            "category":"Professional",
            "subcategory":"Lawyer & Legal Services",
            "type":"Services"
        }
    ],
    "sg:phone":"+1 519 376 2050",
    "sg:postcode":"N4K 4K4",
    "sg:province":"ON",
    "sg:tags":[
        "attorney"
    ],
    "wof:name":"Mc Kerroll & Mc Kerroll",
    "wof:placetype":"venue"
},
  "geometry": {"coordinates":[-80.94496154789999,44.5645561218],"type":"Point"}
}