{
  "type": "Feature",
  "properties": {
    "iso:country":"CA",
    "sg:address":"300 Guelph St",
    "sg:city":"Georgetown",
    "sg:classifiers":[
        {
            "category":"Shopping",
            "subcategory":"Pharmacy",
            "type":"Retail Goods"
        }
    ],
    "sg:phone":"+1 905 877 8761",
    "sg:postcode":"L7G 4B1",
    "sg:province":"ON",
    "wof:name":"Zellers Pharmacy",
    "wof:placetype":"venue"
},
  "geometry": {"coordinates":[-79.894234,43.64962],"type":"Point"}
}