{
  "type": "Feature",
  "properties": {
    "addr:full":"Lethbridge AB T1J 2L2",
    "addr:postcode":"t1j 2l2",
    "iso:country":"CA",
    "sg:city":"Lethbridge",
    "sg:classifiers":[
        {
            "category":"Professional",
            "subcategory":"Lawyer & Legal Services",
            "type":"Services"
        }
    ],
    "sg:phone":"+1 403 329 1330",
    "sg:postcode":"T1J 2L2",
    "sg:province":"AB",
    "sg:tags":[
        "attorney"
    ],
    "wof:name":"Mac Lean, Rick S",
    "wof:placetype":"venue"
},
  "geometry": {"coordinates":[-112.833946,49.694275],"type":"Point"}
}