{
  "type": "Feature",
  "properties": {
    "addr:full":"181 W Island Hwy Parksville BC V9P 2G5",
    "addr:housenumber":"181",
    "addr:postcode":"v9p 2g5",
    "addr:street":"W Island Hwy",
    "iso:country":"CA",
    "sg:address":"181 W Island Hwy",
    "sg:city":"Parksville",
    "sg:classifiers":[
        {
            "category":"Bars & Pubs",
            "type":"Food & Drink"
        }
    ],
    "sg:phone":"+1 250 248 4744",
    "sg:postcode":"V9P 2G5",
    "sg:province":"BC",
    "wof:name":"Sand Bar Pub",
    "wof:placetype":"venue"
},
  "geometry": {"coordinates":[-124.31590271,49.3218803406],"type":"Point"}
}