{
  "type": "Feature",
  "properties": {
    "addr:full":"565 Yonge St Toronto ON M4Y 1Z2",
    "addr:housenumber":"565",
    "addr:postcode":"m4y 1z2",
    "addr:street":"Yonge St",
    "iso:country":"CA",
    "sg:address":"565 Yonge St",
    "sg:city":"Toronto",
    "sg:classifiers":[
        {
            "category":"Restaurant",
            "type":"Food & Drink"
        }
    ],
    "sg:phone":"+1 416 968 1032",
    "sg:postcode":"M4Y 1Z2",
    "sg:province":"ON",
    "wof:name":"Pita Break Inc",
    "wof:placetype":"venue"
},
  "geometry": {"coordinates":[-79.384514,43.665264],"type":"Point"}
}