{
  "type": "Feature",
  "properties": {
    "addr:full":"2522 Eastview Cres North Bay ON P1B 7W5",
    "addr:housenumber":"2522",
    "addr:postcode":"p1b 7w5",
    "addr:street":"Eastview Cres",
    "iso:country":"CA",
    "sg:address":"2522 Eastview Cres",
    "sg:city":"North Bay",
    "sg:classifiers":[
        {
            "category":"Building & Trades",
            "subcategory":"Construction",
            "type":"Services"
        }
    ],
    "sg:phone":"+1 705 476 5691",
    "sg:postcode":"P1B 7W5",
    "sg:province":"ON",
    "sg:tags":[
        "general",
        "contractor"
    ],
    "wof:name":"Mc Donagh Plastering & Drywall",
    "wof:placetype":"venue"
},
  "geometry": {"coordinates":[-79.436279,46.324188],"type":"Point"}
}