{
  "type": "Feature",
  "properties": {
    "iso:country":"CA",
    "sg:address":"633 18th St # C",
    "sg:city":"Brandon",
    "sg:classifiers":[
        {
            "category":"Wholesale",
            "subcategory":"Farm Supplies",
            "type":"Manufacturing & Wholesale Goods"
        }
    ],
    "sg:phone":"+1 204 571 3440",
    "sg:postcode":"R7A 5B3",
    "sg:province":"MB",
    "sg:tags":[
        "product",
        "health",
        "animal"
    ],
    "wof:name":"Elite Swine Inc",
    "wof:placetype":"venue"
},
  "geometry": {"coordinates":[-99.9616394043,49.8401641846],"type":"Point"}
}