{
  "type": "Feature",
  "properties": {
    "iso:country":"CA",
    "sg:city":"North York",
    "sg:classifiers":[
        {
            "category":"Social Services",
            "subcategory":"Child Care",
            "type":"Services"
        }
    ],
    "sg:phone":"+1 416 663 0596",
    "sg:postcode":"M3N 2C4",
    "sg:province":"ON",
    "wof:name":"Seafield Day Nursery",
    "wof:placetype":"venue"
},
  "geometry": {"coordinates":[-79.52038574220001,43.7616691589],"type":"Point"}
}