{
  "type": "Feature",
  "properties": {
    "addr:full":"12 Park Lane Barrington NS B0W 1E0",
    "addr:housenumber":"12",
    "addr:postcode":"b0w 1e0",
    "addr:street":"Park Lane",
    "iso:country":"CA",
    "sg:address":"12 Park Lane",
    "sg:city":"Barrington",
    "sg:classifiers":[
        {
            "category":"Arena",
            "subcategory":"Sports Club",
            "type":"Entertainment"
        }
    ],
    "sg:phone":"+1 902 637 2760",
    "sg:postcode":"B0W 1E0",
    "sg:province":"NS",
    "sg:tags":[
        "athletic",
        "fields",
        "stadium"
    ],
    "wof:name":"Barrington Municipal Arena",
    "wof:placetype":"venue"
},
  "geometry": {"coordinates":[-65.56322479249999,43.5638275146],"type":"Point"}
}