{
  "type": "Feature",
  "properties": {
    "iso:country":"CA",
    "sg:address":"2 King St W",
    "sg:city":"Hamilton",
    "sg:classifiers":[
        {
            "category":"Restaurant",
            "type":"Food & Drink"
        }
    ],
    "sg:phone":"+1 905 526 7533",
    "sg:postcode":"L8P 1A1",
    "sg:province":"ON",
    "sg:tags":[
        "shop",
        "tea",
        "coffee"
    ],
    "wof:name":"Second Cup",
    "wof:placetype":"venue"
},
  "geometry": {"coordinates":[-79.869217,43.256809],"type":"Point"}
}