{
  "type": "Feature",
  "properties": {
    "addr:full":"2 King St W Hamilton ON L8P 1A1",
    "addr:housenumber":"2",
    "addr:postcode":"l8p 1a1",
    "addr:street":"King St W",
    "iso:country":"CA",
    "sg:address":"2 King St W",
    "sg:city":"Hamilton",
    "sg:classifiers":[
        {
            "category":"Restaurant",
            "type":"Food & Drink"
        }
    ],
    "sg:phone":"+1 905 526 7533",
    "sg:postcode":"L8P 1A1",
    "sg:province":"ON",
    "sg:tags":[
        "shop",
        "tea",
        "coffee"
    ],
    "wof:name":"Second Cup",
    "wof:placetype":"venue"
},
  "geometry": {"coordinates":[-79.86921700000001,43.256809],"type":"Point"}
}