{
  "type": "Feature",
  "properties": {
    "addr:full":"780 Rue Fisk Abbotsford QC J0E 1A0",
    "addr:housenumber":"780",
    "addr:postcode":"j0e 1a0",
    "addr:street":"Rue Fisk",
    "iso:country":"CA",
    "sg:address":"780 Rue Fisk",
    "sg:city":"Abbotsford",
    "sg:classifiers":[
        {
            "category":"Manufacturing",
            "subcategory":"Food",
            "type":"Manufacturing & Wholesale Goods"
        }
    ],
    "sg:phone":"+1 450 379 5364",
    "sg:postcode":"J0E 1A0",
    "sg:province":"QC",
    "sg:tags":[
        "product",
        "syrup",
        "manufacturer"
    ],
    "wof:name":"Erabliere LA Coulee D'Abtsfrd",
    "wof:placetype":"venue"
},
  "geometry": {"coordinates":[-72.891914,45.436012],"type":"Point"}
}