{
  "type": "Feature",
  "properties": {
    "iso:country":"CA",
    "sg:city":"Lloydminster",
    "sg:classifiers":[
        {
            "category":"Restaurant",
            "type":"Food & Drink"
        }
    ],
    "sg:phone":"+1 780 875 8888",
    "sg:postcode":"T9V 0B6",
    "sg:province":"AB",
    "wof:name":"Woo's Kitchen",
    "wof:placetype":"venue"
},
  "geometry": {"coordinates":[-110.025619507,53.2780838013],"type":"Point"}
}