{
  "type": "Feature",
  "properties": {
    "addr:full":"973 Rue Principale Eel River Crossing NB E8E 1S9",
    "addr:housenumber":"973",
    "addr:postcode":"e8e 1s9",
    "addr:street":"Rue Principale Eel River Crossing",
    "iso:country":"CA",
    "sg:address":"973 Rue Principale",
    "sg:city":"Eel River Crossing",
    "sg:classifiers":[
        {
            "category":"Retail",
            "subcategory":"Auto Repair",
            "type":"Services"
        }
    ],
    "sg:phone":"+1 506 826 3014",
    "sg:postcode":"E8E 1S9",
    "sg:province":"NB",
    "sg:tags":[
        "body",
        "automobile",
        "painting"
    ],
    "wof:name":"Thibeault & Fontaine Body Shop",
    "wof:placetype":"venue"
},
  "geometry": {"coordinates":[-66.4103317261,47.9913825989],"type":"Point"}
}