{
  "type": "Feature",
  "properties": {
    "addr:full":"111 Anthony Rd North York ON M3K 1B7",
    "addr:housenumber":"111",
    "addr:postcode":"m3k 1b7",
    "addr:street":"Anthony Rd",
    "iso:country":"CA",
    "sg:address":"111 Anthony Rd",
    "sg:city":"North York",
    "sg:classifiers":[
        {
            "category":"Education",
            "subcategory":"School",
            "type":"Public Place"
        }
    ],
    "sg:phone":"+1 416 633 3971",
    "sg:postcode":"M3K 1B7",
    "sg:province":"ON",
    "wof:name":"Muki Baum Childrens Program",
    "wof:placetype":"venue"
},
  "geometry": {"coordinates":[-79.4677352905,43.7285041809],"type":"Point"}
}