{
  "type": "Feature",
  "properties": {
    "addr:full":"Mont-Louis QC G0E 1T0",
    "addr:postcode":"g0e 1t0",
    "iso:country":"CA",
    "sg:city":"Mont-Louis",
    "sg:classifiers":[
        {
            "category":"Government",
            "subcategory":"Office",
            "type":"Public Place"
        }
    ],
    "sg:phone":"+1 418 797 2310",
    "sg:postcode":"G0E 1T0",
    "sg:province":"QC",
    "sg:tags":[
        "municipality"
    ],
    "wof:name":"Municipalite St-Maxime Du",
    "wof:placetype":"venue"
},
  "geometry": {"coordinates":[-65.7292098999,49.2294158936],"type":"Point"}
}