{
  "type": "Feature",
  "properties": {
    "addr:full":"1013 Hwy 528A Noelville ON P0M 2N0",
    "addr:housenumber":"1013",
    "addr:postcode":"p0m 2n0",
    "addr:street":"Hwy 528A",
    "iso:country":"CA",
    "sg:address":"1013 Hwy 528A",
    "sg:city":"Noelville",
    "sg:classifiers":[
        {
            "category":"Travel",
            "subcategory":"Hotels & Motels",
            "type":"Entertainment"
        }
    ],
    "sg:phone":"+1 705 898 2500",
    "sg:postcode":"P0M 2N0",
    "sg:province":"ON",
    "sg:tags":[
        "resort"
    ],
    "wof:name":"Pine Cove Lodge Inc",
    "wof:placetype":"venue"
},
  "geometry": {"coordinates":[-80.43167099999999,46.134171],"type":"Point"}
}