{
  "type": "Feature",
  "properties": {
    "addr:full":"120 Boul Saint-Joseph Drummondville QC J2C 8J5",
    "addr:housenumber":"120",
    "addr:postcode":"j2c 8j5",
    "addr:street":"Boul Saint-Joseph",
    "iso:country":"CA",
    "sg:address":"120 Boul Saint-Joseph",
    "sg:city":"Drummondville",
    "sg:classifiers":[
        {
            "category":"Restaurant",
            "type":"Food & Drink"
        }
    ],
    "sg:phone":"+1 819 478 6060",
    "sg:postcode":"J2C 8J5",
    "sg:province":"QC",
    "wof:name":"Rotisserie Scores",
    "wof:placetype":"venue"
},
  "geometry": {"coordinates":[-72.52298,45.898479],"type":"Point"}
}