{
  "type": "Feature",
  "properties": {
    "addr:full":"NW 27 3 7W Darlingford MB R0G 0L0",
    "addr:housenumber":"3 7w",
    "addr:postcode":"r0g 0l0",
    "addr:street":"Nw 27",
    "iso:country":"CA",
    "sg:address":"NW 27 3 7W",
    "sg:city":"Darlingford",
    "sg:classifiers":[
        {
            "category":"Wholesale",
            "subcategory":"Machinery & Supplies",
            "type":"Manufacturing & Wholesale Goods"
        }
    ],
    "sg:phone":"+1 204 246 2219",
    "sg:postcode":"R0G 0L0",
    "sg:province":"MB",
    "sg:tags":[
        "farm",
        "equipment",
        "parts",
        "tractor"
    ],
    "wof:name":"Storey Enterprises",
    "wof:placetype":"venue"
},
  "geometry": {"coordinates":[-98.3776626587,49.2043609619],"type":"Point"}
}