{
  "type": "Feature",
  "properties": {
    "addr:full":"244 7 Ave SW Calgary AB T2P 0W6",
    "addr:housenumber":"244",
    "addr:postcode":"t2p 0w6",
    "addr:street":"7 Ave Sw",
    "iso:country":"CA",
    "sg:address":"244 7 Ave SW",
    "sg:city":"Calgary",
    "sg:classifiers":[
        {
            "category":"Shopping",
            "subcategory":"Shoes",
            "type":"Retail Goods"
        }
    ],
    "sg:phone":"+1 403 264 1275",
    "sg:postcode":"T2P 0W6",
    "sg:province":"AB",
    "wof:name":"O'Connors Instride",
    "wof:placetype":"venue"
},
  "geometry": {"coordinates":[-114.06652099999999,51.046688],"type":"Point"}
}