{
  "type": "Feature",
  "properties": {
    "iso:country":"CA",
    "sg:address":"175 Lahr Dr",
    "sg:city":"Belleville",
    "sg:classifiers":[
        {
            "category":"Autos & Motor Vehicles",
            "subcategory":"Auto Supplies",
            "type":"Retail Goods"
        }
    ],
    "sg:phone":"+1 613 967 4521",
    "sg:postcode":"K8N 5S2",
    "sg:province":"ON",
    "sg:tags":[
        "tire"
    ],
    "wof:name":"Hercules Tire",
    "wof:placetype":"venue"
},
  "geometry": {"coordinates":[-77.38092803959999,44.1934089661],"type":"Point"}
}