{
  "type": "Feature",
  "properties": {
    "addr:full":"1295 Maryhill Rd Maryhill ON N0B 2B0",
    "addr:housenumber":"1295",
    "addr:postcode":"n0b 2b0",
    "addr:street":"Maryhill Rd",
    "iso:country":"CA",
    "sg:address":"1295 Maryhill Rd",
    "sg:city":"Maryhill",
    "sg:classifiers":[
        {
            "category":"Retail",
            "subcategory":"Auto Repair",
            "type":"Services"
        }
    ],
    "sg:phone":"+1 519 648 2263",
    "sg:postcode":"N0B 2B0",
    "sg:province":"ON",
    "sg:tags":[
        "repairing",
        "automobile"
    ],
    "wof:name":"G & C Voisin Automotive Ltd",
    "wof:placetype":"venue"
},
  "geometry": {"coordinates":[-80.389923,43.533928],"type":"Point"}
}