{
  "type": "Feature",
  "properties": {
    "addr:full":"295 Rouge Rd Winnipeg MB R3K 1J7",
    "addr:housenumber":"295",
    "addr:postcode":"r3k 1j7",
    "addr:street":"Rouge Rd",
    "iso:country":"CA",
    "sg:address":"295 Rouge Rd",
    "sg:city":"Winnipeg",
    "sg:classifiers":[
        {
            "category":"Professional",
            "subcategory":"Management & Consulting",
            "type":"Services"
        }
    ],
    "sg:phone":"+1 204 897 5115",
    "sg:postcode":"R3K 1J7",
    "sg:province":"MB",
    "sg:tags":[
        "construction"
    ],
    "wof:name":"Neville Sampson",
    "wof:placetype":"venue"
},
  "geometry": {"coordinates":[-97.29959100000001,49.873596],"type":"Point"}
}