{
  "type": "Feature",
  "properties": {
    "iso:country":"CA",
    "sg:address":"1037 Springfield Rd",
    "sg:city":"Winnipeg",
    "sg:classifiers":[
        {
            "category":"Retail",
            "subcategory":"Auto Repair",
            "type":"Services"
        }
    ],
    "sg:phone":"+1 204 654 4891",
    "sg:postcode":"R2G 3T2",
    "sg:province":"MB",
    "sg:tags":[
        "transmission",
        "automobile",
        "repairing"
    ],
    "wof:name":"Mister Clutch",
    "wof:placetype":"venue"
},
  "geometry": {"coordinates":[-97.04907989500001,49.9312553406],"type":"Point"}
}