{
  "type": "Feature",
  "properties": {
    "iso:country":"CA",
    "sg:address":"1011 Clover Bar Rd",
    "sg:city":"Sherwood Park",
    "sg:classifiers":[
        {
            "category":"Organizations",
            "subcategory":"Religious Organization",
            "type":"Services"
        }
    ],
    "sg:phone":"+1 780 467 8404",
    "sg:postcode":"T8A 4V7",
    "sg:province":"AB",
    "sg:tags":[
        "church"
    ],
    "wof:name":"Sherwood Park Alliance Church",
    "wof:placetype":"venue"
},
  "geometry": {"coordinates":[-113.270149231,53.5165023804],"type":"Point"}
}