{
  "type": "Feature",
  "properties": {
    "addr:full":"2 Rue Leblanc Baie-Saint-Paul QC G3Z 1W9",
    "addr:housenumber":"2",
    "addr:postcode":"g3z 1w9",
    "addr:street":"Rue Leblanc",
    "iso:country":"CA",
    "sg:address":"2 Rue Leblanc",
    "sg:city":"Baie-Saint-Paul",
    "sg:classifiers":[
        {
            "category":"Retail",
            "subcategory":"Portrait Studio",
            "type":"Services"
        }
    ],
    "sg:phone":"+1 418 435 3217",
    "sg:postcode":"G3Z 1W9",
    "sg:province":"QC",
    "sg:tags":[
        "photographer"
    ],
    "wof:name":"Rivard, Francois",
    "wof:placetype":"venue"
},
  "geometry": {"coordinates":[-70.5016708374,47.4390029907],"type":"Point"}
}