{
  "type": "Feature",
  "properties": {
    "addr:full":"507 Dundas St Woodstock ON N4S 1C3",
    "addr:housenumber":"507",
    "addr:postcode":"n4s 1c3",
    "addr:street":"Dundas St",
    "iso:country":"CA",
    "sg:address":"507 Dundas St",
    "sg:city":"Woodstock",
    "sg:classifiers":[
        {
            "category":"Shopping",
            "subcategory":"Florist",
            "type":"Retail Goods"
        }
    ],
    "sg:phone":"+1 519 537 5700",
    "sg:postcode":"N4S 1C3",
    "sg:province":"ON",
    "wof:name":"Floral Buds & Design",
    "wof:placetype":"venue"
},
  "geometry": {"coordinates":[-80.75588226319999,43.1303405762],"type":"Point"}
}