{
  "type": "Feature",
  "properties": {
    "addr:full":"5508 46 St Olds AB T4H 1B8",
    "addr:housenumber":"5508",
    "addr:postcode":"t4h 1b8",
    "addr:street":"46 St",
    "iso:country":"CA",
    "sg:address":"5508 46 St",
    "sg:city":"Olds",
    "sg:classifiers":[
        {
            "category":"Food & Beverages",
            "subcategory":"Bakery",
            "type":"Retail Goods"
        }
    ],
    "sg:phone":"+1 403 556 8467",
    "sg:postcode":"T4H 1B8",
    "sg:province":"AB",
    "sg:tags":[
        "doughnut"
    ],
    "wof:name":"Tim Hortons",
    "wof:placetype":"venue"
},
  "geometry": {"coordinates":[-114.115585,51.795162],"type":"Point"}
}