{
  "type": "Feature",
  "properties": {
    "addr:full":"1028 Hwy 335 Middle West Pubnico NS B0W 2M0",
    "addr:housenumber":"1028",
    "addr:postcode":"b0w 2m0",
    "addr:street":"Hwy 335",
    "iso:country":"CA",
    "sg:address":"1028 Hwy 335",
    "sg:city":"Middle West Pubnico",
    "sg:classifiers":[
        {
            "category":"Manufacturing",
            "subcategory":"Metals",
            "type":"Manufacturing & Wholesale Goods"
        }
    ],
    "sg:phone":"+1 902 762 2779",
    "sg:postcode":"B0W 2M0",
    "sg:province":"NS",
    "sg:tags":[
        "welding"
    ],
    "wof:name":"R & N D'Entremont Fab",
    "wof:placetype":"venue"
},
  "geometry": {"coordinates":[-65.801163,43.63789],"type":"Point"}
}