{
  "type": "Feature",
  "properties": {
    "addr:full":"220 Royal Crest Crt # 21 Markham ON L3R 9Y2",
    "addr:housenumber":"220",
    "addr:postcode":"l3r 9y2",
    "addr:street":"Royal Crest Crt # 21",
    "iso:country":"CA",
    "sg:address":"220 Royal Crest Crt # 21",
    "sg:city":"Markham",
    "sg:classifiers":[
        {
            "category":"Professional",
            "subcategory":"Computer Services",
            "type":"Services"
        }
    ],
    "sg:phone":"+1 905 305 6612",
    "sg:postcode":"L3R 9Y2",
    "sg:province":"ON",
    "sg:tags":[
        "repair"
    ],
    "wof:name":"Supreme Computing Svc CO",
    "wof:placetype":"venue"
},
  "geometry": {"coordinates":[-79.32353999999999,43.841938],"type":"Point"}
}