{
  "type": "Feature",
  "properties": {
    "addr:full":"1680 Oxford St E London ON N5V 4X7",
    "addr:housenumber":"1680",
    "addr:postcode":"n5v 4x7",
    "addr:street":"Oxford St E",
    "iso:country":"CA",
    "sg:address":"1680 Oxford St E",
    "sg:city":"London",
    "sg:classifiers":[
        {
            "category":"Social Services",
            "type":"Services"
        }
    ],
    "sg:phone":"+1 519 455 9000",
    "sg:postcode":"N5V 4X7",
    "sg:province":"ON",
    "sg:tags":[
        "organization",
        "welfare"
    ],
    "wof:name":"Children's Aid Society",
    "wof:placetype":"venue"
},
  "geometry": {"coordinates":[-81.192123,43.013405],"type":"Point"}
}