{
  "type": "Feature",
  "properties": {
    "addr:full":"34 Wilmot Rd Wilmot NB E7P 2V5",
    "addr:housenumber":"34",
    "addr:postcode":"e7p 2v5",
    "addr:street":"Wilmot Rd",
    "iso:country":"CA",
    "sg:address":"34 Wilmot Rd",
    "sg:city":"Wilmot",
    "sg:classifiers":[
        {
            "category":"Professional",
            "subcategory":"Business Services",
            "type":"Services"
        }
    ],
    "sg:phone":"+1 506 375 6981",
    "sg:postcode":"E7P 2V5",
    "sg:province":"NB",
    "sg:tags":[
        "appraiser"
    ],
    "wof:name":"Peterson Appraisals",
    "wof:placetype":"venue"
},
  "geometry": {"coordinates":[-67.69008599999999,46.357517],"type":"Point"}
}