{
  "type": "Feature",
  "properties": {
    "addr:full":"1918 Hamilton Rd London ON N6M 1G3",
    "addr:housenumber":"1918",
    "addr:postcode":"n6m 1g3",
    "addr:street":"Hamilton Rd",
    "iso:country":"CA",
    "sg:address":"1918 Hamilton Rd",
    "sg:city":"London",
    "sg:classifiers":[
        {
            "category":"Building & Trades",
            "subcategory":"Landscaping Services",
            "type":"Services"
        }
    ],
    "sg:phone":"+1 519 455 4189",
    "sg:postcode":"N6M 1G3",
    "sg:province":"ON",
    "sg:tags":[
        "topsoil"
    ],
    "wof:name":"Cerro Topsoil",
    "wof:placetype":"venue"
},
  "geometry": {"coordinates":[-81.1349563599,42.9652404785],"type":"Point"}
}