{
  "type": "Feature",
  "properties": {
    "iso:country":"CA",
    "sg:address":"41 Adelaide St S",
    "sg:city":"London",
    "sg:classifiers":[
        {
            "category":"Autos & Motor Vehicles",
            "subcategory":"Auto Supplies",
            "type":"Retail Goods"
        }
    ],
    "sg:phone":"+1 519 439 7132",
    "sg:postcode":"N5Z 3K1",
    "sg:province":"ON",
    "sg:tags":[
        "automobile",
        "parts"
    ],
    "wof:name":"Foreign Car Parts",
    "wof:placetype":"venue"
},
  "geometry": {"coordinates":[-81.224625,42.972309],"type":"Point"}
}