{
  "type": "Feature",
  "properties": {
    "addr:full":"11830 Kingsway NW Edmonton AB T5G 0X5",
    "addr:housenumber":"11830",
    "addr:postcode":"t5g 0x5",
    "addr:street":"Kingsway Nw",
    "iso:country":"CA",
    "sg:address":"11830 Kingsway NW",
    "sg:city":"Edmonton",
    "sg:classifiers":[
        {
            "category":"Shopping",
            "subcategory":"Gifts & Souvenirs",
            "type":"Retail Goods"
        }
    ],
    "sg:phone":"+1 780 451 0171",
    "sg:postcode":"T5G 0X5",
    "sg:province":"AB",
    "sg:tags":[
        "shop"
    ],
    "wof:name":"Picadilly Place",
    "wof:placetype":"venue"
},
  "geometry": {"coordinates":[-113.52417,53.567753],"type":"Point"}
}