{
  "type": "Feature",
  "properties": {
    "addr:full":"145 Rue Saint-Vallier O Quebec QC G1K 1J9",
    "addr:housenumber":"145",
    "addr:postcode":"g1k 1j9",
    "addr:street":"Rue Saint-Vallier O",
    "iso:country":"CA",
    "sg:address":"145 Rue Saint-Vallier O",
    "sg:city":"Quebec",
    "sg:classifiers":[
        {
            "category":"Restaurant",
            "type":"Food & Drink"
        }
    ],
    "sg:phone":"+1 418 640 9222",
    "sg:postcode":"G1K 1J9",
    "sg:province":"QC",
    "sg:tags":[
        "baker"
    ],
    "wof:name":"Patisserie Soria Inc",
    "wof:placetype":"venue"
},
  "geometry": {"coordinates":[-71.2283248901,46.8111991882],"type":"Point"}
}