{
  "type": "Feature",
  "properties": {
    "addr:full":"RR 2 Kenilworth ON N0G 2E0",
    "addr:postcode":"n0g 2e0",
    "addr:street":"Rr 2",
    "iso:country":"CA",
    "sg:address":"RR 2",
    "sg:city":"Kenilworth",
    "sg:classifiers":[
        {
            "category":"Building & Trades",
            "subcategory":"Construction",
            "type":"Services"
        }
    ],
    "sg:phone":"+1 519 848 3740",
    "sg:postcode":"N0G 2E0",
    "sg:province":"ON",
    "sg:tags":[
        "general",
        "contractor"
    ],
    "wof:name":"Ivan Ireland Back Hoe Svc",
    "wof:placetype":"venue"
},
  "geometry": {"coordinates":[-80.630241394,43.8981208801],"type":"Point"}
}