{
  "type": "Feature",
  "properties": {
    "iso:country":"CA",
    "sg:city":"St Agatha",
    "sg:classifiers":[
        {
            "category":"Social Services",
            "type":"Services"
        }
    ],
    "sg:phone":"+1 519 746 2323",
    "sg:postcode":"N0B 2L0",
    "sg:province":"ON",
    "sg:tags":[
        "counselor",
        "marriage",
        "family"
    ],
    "wof:name":"Southern Ontario Counselling",
    "wof:placetype":"venue"
},
  "geometry": {"coordinates":[-80.6235961914,43.4357185364],"type":"Point"}
}