{
  "type": "Feature",
  "properties": {
    "addr:full":"1905 Quebec Ave Saskatoon SK S7K 1W3",
    "addr:housenumber":"1905",
    "addr:postcode":"s7k 1w3",
    "addr:street":"Quebec Ave",
    "iso:country":"CA",
    "sg:address":"1905 Quebec Ave",
    "sg:city":"Saskatoon",
    "sg:classifiers":[
        {
            "category":"Wholesale",
            "subcategory":"Machinery & Supplies",
            "type":"Manufacturing & Wholesale Goods"
        }
    ],
    "sg:phone":"+1 306 665 0800",
    "sg:postcode":"S7K 1W3",
    "sg:province":"SK",
    "sg:tags":[
        "barbecue",
        "equipment"
    ],
    "wof:name":"Weber Barbecue Shop",
    "wof:placetype":"venue"
},
  "geometry": {"coordinates":[-106.663597107,52.1551246643],"type":"Point"}
}