{
  "type": "Feature",
  "properties": {
    "addr:full":"4819 55 Ave Grimshaw AB T0H 1W0",
    "addr:housenumber":"4819",
    "addr:postcode":"t0h 1w0",
    "addr:street":"55 Ave",
    "iso:country":"CA",
    "sg:address":"4819 55 Ave",
    "sg:city":"Grimshaw",
    "sg:classifiers":[
        {
            "category":"Building & Trades",
            "subcategory":"Electrical",
            "type":"Services"
        }
    ],
    "sg:phone":"+1 780 332 3944",
    "sg:postcode":"T0H 1W0",
    "sg:province":"AB",
    "sg:tags":[
        "electric",
        "contractor"
    ],
    "wof:name":"Nor-Tech Systems Ltd",
    "wof:placetype":"venue"
},
  "geometry": {"coordinates":[-117.60270690900001,56.1926498413],"type":"Point"}
}