{
  "type": "Feature",
  "properties": {
    "iso:country":"CA",
    "sg:address":"5181 Sackville St",
    "sg:city":"Halifax",
    "sg:classifiers":[
        {
            "category":"Travel",
            "subcategory":"Travel Agent",
            "type":"Entertainment"
        }
    ],
    "sg:phone":"+1 902 425 6360",
    "sg:postcode":"B3J 1K5",
    "sg:province":"NS",
    "sg:tags":[
        "agency",
        "bureau"
    ],
    "wof:name":"Brooks Travel-Carlson Wagonlit",
    "wof:placetype":"venue"
},
  "geometry": {"coordinates":[-63.5730743408,44.6464614868],"type":"Point"}
}