{
  "type": "Feature",
  "properties": {
    "iso:country":"CA",
    "sg:city":"Scarborough",
    "sg:classifiers":[
        {
            "category":"Manufacturing",
            "subcategory":"Leather Goods",
            "type":"Manufacturing & Wholesale Goods"
        }
    ],
    "sg:phone":"+1 416 332 2801",
    "sg:postcode":"M1V 4C4",
    "sg:province":"ON",
    "sg:tags":[
        "clothes"
    ],
    "wof:name":"Karman Kong Enterprise Ltd",
    "wof:placetype":"venue"
},
  "geometry": {"coordinates":[-79.24831399999999,43.819656],"type":"Point"}
}