{
  "type": "Feature",
  "properties": {
    "addr:full":"14 Brock St E Uxbridge ON L9P 1P1",
    "addr:housenumber":"14",
    "addr:postcode":"l9p 1p1",
    "addr:street":"Brock St E",
    "iso:country":"CA",
    "sg:address":"14 Brock St E",
    "sg:city":"Uxbridge",
    "sg:classifiers":[
        {
            "category":"Shopping",
            "subcategory":"Florist",
            "type":"Retail Goods"
        }
    ],
    "sg:phone":"+1 905 852 3029",
    "sg:postcode":"L9P 1P1",
    "sg:province":"ON",
    "wof:name":"Keith's Flowers",
    "wof:placetype":"venue"
},
  "geometry": {"coordinates":[-79.119675,44.109402],"type":"Point"}
}