{
  "type": "Feature",
  "properties": {
    "addr:full":"100 Rue Sainte-Anne Sainte-Anne-DE-Bellevue QC H9X 1L8",
    "addr:housenumber":"100",
    "addr:postcode":"h9x 1l8",
    "addr:street":"Rue Sainte-Anne",
    "iso:country":"CA",
    "sg:address":"100 Rue Sainte-Anne",
    "sg:city":"Sainte-Anne-DE-Bellevue",
    "sg:classifiers":[
        {
            "category":"Restaurant",
            "type":"Food & Drink"
        }
    ],
    "sg:phone":"+1 514 457 7166",
    "sg:postcode":"H9X 1L8",
    "sg:province":"QC",
    "wof:name":"Mc Donald's",
    "wof:placetype":"venue"
},
  "geometry": {"coordinates":[-73.9524688721,45.4037246704],"type":"Point"}
}