{
  "type": "Feature",
  "properties": {
    "addr:full":"3460 Rue Drummond Montreal QC H3G 1Y1",
    "addr:housenumber":"3460",
    "addr:postcode":"h3g 1y1",
    "addr:street":"Rue Drummond",
    "iso:country":"CA",
    "sg:address":"3460 Rue Drummond",
    "sg:city":"Montreal",
    "sg:classifiers":[
        {
            "category":"Retail",
            "subcategory":"Laundry & Dry Cleaning",
            "type":"Services"
        }
    ],
    "sg:phone":"+1 514 845 4638",
    "sg:postcode":"H3G 1Y1",
    "sg:province":"QC",
    "sg:tags":[
        "cleaners"
    ],
    "wof:name":"Emmanuel Cleaners",
    "wof:placetype":"venue"
},
  "geometry": {"coordinates":[-73.57996368409999,45.5012588501],"type":"Point"}
}