{
  "type": "Feature",
  "properties": {
    "addr:full":"492 Av Westminster Dollard-Des-Ormeaux QC H9G 1E5",
    "addr:postcode":"h9g 1e5",
    "addr:street":"492 Av Westminster",
    "iso:country":"CA",
    "sg:address":"492 Av Westminster",
    "sg:city":"Dollard-Des-Ormeaux",
    "sg:classifiers":[
        {
            "category":"Professional",
            "subcategory":"Business Services",
            "type":"Services"
        }
    ],
    "sg:phone":"+1 514 267 1144",
    "sg:postcode":"H9G 1E5",
    "sg:province":"QC",
    "wof:name":"A K Electromagnetique Inc",
    "wof:placetype":"venue"
},
  "geometry": {"coordinates":[-73.8413848877,45.4754142761],"type":"Point"}
}