{
  "type": "Feature",
  "properties": {
    "addr:full":"2158 Rue Montgomery Montreal QC H2K 2R8",
    "addr:housenumber":"2158",
    "addr:postcode":"h2k 2r8",
    "addr:street":"Rue Montgomery",
    "iso:country":"CA",
    "sg:address":"2158 Rue Montgomery",
    "sg:city":"Montreal",
    "sg:classifiers":[
        {
            "category":"Professional",
            "type":"Services"
        }
    ],
    "sg:phone":"+1 514 598 5709",
    "sg:postcode":"H2K 2R8",
    "sg:province":"QC",
    "sg:tags":[
        "arts",
        "artist"
    ],
    "wof:name":"Plotek, Leopold",
    "wof:placetype":"venue"
},
  "geometry": {"coordinates":[-73.55323,45.53669],"type":"Point"}
}