{
  "type": "Feature",
  "properties": {
    "addr:full":"Calgary AB T2X 2X7",
    "addr:postcode":"t2x 2x7",
    "iso:country":"CA",
    "sg:city":"Calgary",
    "sg:classifiers":[
        {
            "category":"Building & Trades",
            "subcategory":"Plumbing",
            "type":"Services"
        }
    ],
    "sg:phone":"+1 403 254 5685",
    "sg:postcode":"T2X 2X7",
    "sg:province":"AB",
    "sg:tags":[
        "balancing",
        "air"
    ],
    "wof:name":"Airco Airbalancing",
    "wof:placetype":"venue"
},
  "geometry": {"coordinates":[-114.06312561,50.9147071838],"type":"Point"}
}