{
  "type": "Feature",
  "properties": {
    "addr:full":"General Delivery Glendon AB T0A 1P0",
    "addr:postcode":"t0a 1p0",
    "iso:country":"CA",
    "sg:address":"General Delivery",
    "sg:city":"Glendon",
    "sg:classifiers":[
        {
            "category":"Recreation",
            "type":"Entertainment"
        }
    ],
    "sg:phone":"+1 780 635 2118",
    "sg:postcode":"T0A 1P0",
    "sg:province":"AB",
    "sg:tags":[
        "hall",
        "auditorium"
    ],
    "wof:name":"Goodridge Jubilee Hall",
    "wof:placetype":"venue"
},
  "geometry": {"coordinates":[-111.153831,54.247196],"type":"Point"}
}