{
  "type": "Feature",
  "properties": {
    "addr:full":"1903 Barrington St Halifax NS B3J 3L7",
    "addr:housenumber":"1903",
    "addr:postcode":"ns b3j 3l7",
    "addr:street":"Barrington St",
    "iso:country":"CA",
    "sg:address":"1903 Barrington St",
    "sg:city":"Halifax",
    "sg:classifiers":[
        {
            "category":"Travel",
            "subcategory":"Travel Agent",
            "type":"Entertainment"
        }
    ],
    "sg:phone":"+1 902 421 5000",
    "sg:postcode":"B3J 3L7",
    "sg:province":"NS",
    "sg:tags":[
        "agency",
        "bureau"
    ],
    "wof:name":"Maritime Marlin Travel",
    "wof:placetype":"venue"
},
  "geometry": {"coordinates":[-63.575249,44.649963],"type":"Point"}
}