{
  "type": "Feature",
  "properties": {
    "addr:full":"555 Rue Richelieu Saint-Marc-Sur-Richelieu QC J0L 2E0",
    "addr:housenumber":"555",
    "addr:postcode":"j0l 2e0",
    "addr:street":"Rue Richelieu",
    "iso:country":"CA",
    "sg:address":"555 Rue Richelieu",
    "sg:city":"Saint-Marc-Sur-Richelieu",
    "sg:classifiers":[
        {
            "category":"Travel",
            "subcategory":"Hotels & Motels",
            "type":"Entertainment"
        }
    ],
    "sg:phone":"+1 450 584 2226",
    "sg:postcode":"J0L 2E0",
    "sg:province":"QC",
    "wof:name":"Auberge Handfield",
    "wof:placetype":"venue"
},
  "geometry": {"coordinates":[-73.193909,45.674419],"type":"Point"}
}