{
  "type": "Feature",
  "properties": {
    "addr:full":"2452 Boul Laurier Sainte-Foy QC G1V 2L1",
    "addr:housenumber":"2452",
    "addr:postcode":"g1v 2l1",
    "addr:street":"Boul Laurier",
    "iso:country":"CA",
    "sg:address":"2452 Boul Laurier",
    "sg:city":"Sainte-Foy",
    "sg:classifiers":[
        {
            "category":"Personal",
            "subcategory":"Beauty Salon",
            "type":"Services"
        }
    ],
    "sg:phone":"+1 418 652 8898",
    "sg:postcode":"G1V 2L1",
    "sg:province":"QC",
    "wof:name":"Salon Jacques Despars",
    "wof:placetype":"venue"
},
  "geometry": {"coordinates":[-71.2763137817,46.7736816406],"type":"Point"}
}