{
  "type": "Feature",
  "properties": {
    "addr:full":"Toronto ON M5H 3R4",
    "addr:postcode":"m5h 3r4",
    "iso:country":"CA",
    "sg:city":"Toronto",
    "sg:classifiers":[
        {
            "category":"Real Estate",
            "subcategory":"Real Estate Agent",
            "type":"Services"
        }
    ],
    "sg:phone":"+1 416 598 8200",
    "sg:postcode":"M5H 3R4",
    "sg:province":"ON",
    "sg:tags":[
        "management"
    ],
    "wof:name":"Cadillac Fairview Corp",
    "wof:placetype":"venue"
},
  "geometry": {"coordinates":[-79.380043,43.652378],"type":"Point"}
}