{
  "type": "Feature",
  "properties": {
    "iso:country":"CA",
    "sg:address":"25 Water St N",
    "sg:city":"St Marys",
    "sg:classifiers":[
        {
            "category":"Real Estate",
            "subcategory":"Developer",
            "type":"Services"
        }
    ],
    "sg:phone":"+1 519 284 2580",
    "sg:postcode":"N4X 1B1",
    "sg:province":"ON",
    "wof:name":"Meadowridge Properties Ltd",
    "wof:placetype":"venue"
},
  "geometry": {"coordinates":[-81.14344800000001,43.259964],"type":"Point"}
}