{
  "type": "Feature",
  "properties": {
    "addr:full":"Paspebiac QC G0C 2K0",
    "addr:postcode":"g0c 2k0",
    "iso:country":"CA",
    "sg:city":"Paspebiac",
    "sg:classifiers":[
        {
            "category":"Autos & Motor Vehicles",
            "subcategory":"Automobile Sales",
            "type":"Retail Goods"
        }
    ],
    "sg:phone":"+1 418 752 6030",
    "sg:postcode":"G0C 2K0",
    "sg:province":"QC",
    "sg:tags":[
        "car",
        "dealer"
    ],
    "wof:name":"Automobiles Roland Roussy",
    "wof:placetype":"venue"
},
  "geometry": {"coordinates":[-65.2492675781,48.028968811],"type":"Point"}
}