{
  "type": "Feature",
  "properties": {
    "addr:full":"740 4E Ave Grandes-Piles QC G0X 1H0",
    "addr:housenumber":"740",
    "addr:postcode":"g0x 1h0",
    "addr:street":"4E Ave",
    "iso:country":"CA",
    "sg:address":"740 4E Ave",
    "sg:city":"Grandes-Piles",
    "sg:classifiers":[
        {
            "category":"Health Services",
            "subcategory":"Doctor",
            "type":"Services"
        }
    ],
    "sg:phone":"+1 819 536 9566",
    "sg:postcode":"G0X 1H0",
    "sg:province":"QC",
    "sg:tags":[
        "clinic",
        "chiropractor"
    ],
    "wof:name":"Centre Sante Chiropratique3",
    "wof:placetype":"venue"
},
  "geometry": {"coordinates":[-72.72827100000001,46.688286],"type":"Point"}
}