{
  "type": "Feature",
  "properties": {
    "iso:country":"CA",
    "sg:city":"Milton",
    "sg:classifiers":[
        {
            "category":"Health Services",
            "subcategory":"Doctor",
            "type":"Services"
        }
    ],
    "sg:phone":"+1 905 878 8700",
    "sg:postcode":"L9T 3K8",
    "sg:province":"ON",
    "sg:tags":[
        "physician",
        "surgeon"
    ],
    "wof:name":"Tam, H A MD",
    "wof:placetype":"venue"
},
  "geometry": {"coordinates":[-79.86213684080001,43.5093994141],"type":"Point"}
}