{
  "type": "Feature",
  "properties": {
    "addr:full":"3951 Boul Des Fondateurs Saint-Isidore NB E8M 1C1",
    "addr:housenumber":"3951",
    "addr:postcode":"e8m 1c1",
    "addr:street":"Boul Des Fondateurs",
    "iso:country":"CA",
    "sg:address":"3951 Boul Des Fondateurs",
    "sg:city":"Saint-Isidore",
    "sg:classifiers":[
        {
            "category":"Food & Beverages",
            "subcategory":"Groceries & Convenience Stores",
            "type":"Retail Goods"
        }
    ],
    "sg:phone":"+1 506 358 2224",
    "sg:postcode":"E8M 1C1",
    "sg:province":"NB",
    "sg:tags":[
        "grocer"
    ],
    "wof:name":"Epiciers G Sivret Ltee",
    "wof:placetype":"venue"
},
  "geometry": {"coordinates":[-65.052223,47.553928],"type":"Point"}
}