{
  "type": "Feature",
  "properties": {
    "iso:country":"CA",
    "sg:city":"Medicine Hat",
    "sg:classifiers":[
        {
            "category":"Food & Beverages",
            "subcategory":"Liquor & Beverages",
            "type":"Retail Goods"
        }
    ],
    "sg:phone":"+1 403 528 2269",
    "sg:postcode":"T1A 6P1",
    "sg:province":"AB",
    "sg:tags":[
        "store"
    ],
    "wof:name":"8th Street Cold Beer & Liquor",
    "wof:placetype":"venue"
},
  "geometry": {"coordinates":[-110.689018249,50.0499305725],"type":"Point"}
}