{
  "type": "Feature",
  "properties": {
    "addr:full":"10 Barton St E Hamilton ON L8L 2V5",
    "addr:housenumber":"10",
    "addr:postcode":"l8l 2v5",
    "addr:street":"Barton St E",
    "iso:country":"CA",
    "sg:address":"10 Barton St E",
    "sg:city":"Hamilton",
    "sg:classifiers":[
        {
            "category":"Travel",
            "subcategory":"Travel Agent",
            "type":"Entertainment"
        }
    ],
    "sg:phone":"+1 905 522 5544",
    "sg:postcode":"L8L 2V5",
    "sg:province":"ON",
    "sg:tags":[
        "agency",
        "bureau"
    ],
    "wof:name":"Canada Travel",
    "wof:placetype":"venue"
},
  "geometry": {"coordinates":[-79.86548614500001,43.2638473511],"type":"Point"}
}