{
  "type": "Feature",
  "properties": {
    "addr:full":"RR 1 Fournier ON K0B 1G0",
    "addr:postcode":"k0b 1g0",
    "addr:street":"Rr 1 Fournier",
    "iso:country":"CA",
    "sg:address":"RR 1",
    "sg:city":"Fournier",
    "sg:classifiers":[
        {
            "category":"Organizations",
            "subcategory":"Religious Organization",
            "type":"Services"
        }
    ],
    "sg:phone":"+1 613 224 6235",
    "sg:postcode":"K0B 1G0",
    "sg:province":"ON",
    "sg:tags":[
        "church"
    ],
    "wof:name":"United Church of Canada",
    "wof:placetype":"venue"
},
  "geometry": {"coordinates":[-74.89949799999999,45.441303],"type":"Point"}
}