{
  "type": "Feature",
  "properties": {
    "addr:full":"126 Higginsville Rd Middle Musquodoboit NS B0N 1X0",
    "addr:housenumber":"126",
    "addr:postcode":"b0n 1x0",
    "addr:street":"Higginsville Rd",
    "iso:country":"CA",
    "sg:address":"126 Higginsville Rd",
    "sg:city":"Middle Musquodoboit",
    "sg:classifiers":[
        {
            "category":"Health Services",
            "subcategory":"Nursing And Care Facility",
            "type":"Services"
        }
    ],
    "sg:phone":"+1 902 384 3007",
    "sg:postcode":"B0N 1X0",
    "sg:province":"NS",
    "sg:tags":[
        "home",
        "convalescent"
    ],
    "wof:name":"Braeside Nursing Home",
    "wof:placetype":"venue"
},
  "geometry": {"coordinates":[-63.141148,45.041382],"type":"Point"}
}