{
  "type": "Feature",
  "properties": {
    "iso:country":"CA",
    "sg:address":"1105 Wellington Rd",
    "sg:city":"London",
    "sg:classifiers":[
        {
            "category":"Shopping",
            "subcategory":"Gifts & Souvenirs",
            "type":"Retail Goods"
        }
    ],
    "sg:phone":"+1 519 686 4722",
    "sg:postcode":"N6E 1V4",
    "sg:province":"ON",
    "sg:tags":[
        "cards",
        "greeting"
    ],
    "wof:name":"Carlton Cards",
    "wof:placetype":"venue"
},
  "geometry": {"coordinates":[-81.221642,42.931622],"type":"Point"}
}