{
  "type": "Feature",
  "properties": {
    "addr:full":"3020 Dougall Ave # 7 Windsor ON N9E 1S4",
    "addr:housenumber":"3020",
    "addr:postcode":"n9e 1s4",
    "addr:street":"Dougall Ave # 7",
    "iso:country":"CA",
    "sg:address":"3020 Dougall Ave # 7",
    "sg:city":"Windsor",
    "sg:classifiers":[
        {
            "category":"Insurance",
            "subcategory":"Insurance Agent",
            "type":"Services"
        }
    ],
    "sg:phone":"+1 519 966 6335",
    "sg:postcode":"N9E 1S4",
    "sg:province":"ON",
    "wof:name":"Gibb, Chris",
    "wof:placetype":"venue"
},
  "geometry": {"coordinates":[-83.0134735107,42.2726287842],"type":"Point"}
}