{
  "type": "Feature",
  "properties": {
    "addr:full":"Sainte-Croix QC G0S 2H0",
    "addr:postcode":"g0s 2h0",
    "iso:country":"CA",
    "sg:city":"Sainte-Croix",
    "sg:classifiers":[
        {
            "category":"Building & Trades",
            "subcategory":"Construction",
            "type":"Services"
        }
    ],
    "sg:phone":"+1 418 926 3309",
    "sg:postcode":"G0S 2H0",
    "sg:province":"QC",
    "sg:tags":[
        "excavating",
        "contractor"
    ],
    "wof:name":"Excavation Ste-Croix Inc",
    "wof:placetype":"venue"
},
  "geometry": {"coordinates":[-71.7614974976,46.6254692078],"type":"Point"}
}