{
  "type": "Feature",
  "properties": {
    "addr:full":"Wolfville NS B4P 2A6",
    "addr:postcode":"b4p 2a6",
    "iso:country":"CA",
    "sg:city":"Wolfville",
    "sg:classifiers":[
        {
            "category":"Personal",
            "subcategory":"Barber",
            "type":"Services"
        }
    ],
    "sg:phone":"+1 902 542 1745",
    "sg:postcode":"B4P 2A6",
    "sg:province":"NS",
    "wof:name":"What's the Buzz-Barber Shop",
    "wof:placetype":"venue"
},
  "geometry": {"coordinates":[-64.361862,45.091854],"type":"Point"}
}