{
  "type": "Feature",
  "properties": {
    "iso:country":"CA",
    "sg:city":"London",
    "sg:classifiers":[
        {
            "category":"Food & Beverages",
            "subcategory":"Fruits & Vegetables",
            "type":"Retail Goods"
        }
    ],
    "sg:phone":"+1 519 666 0286",
    "sg:postcode":"N5X 4B2",
    "sg:province":"ON",
    "sg:tags":[
        "produce"
    ],
    "wof:name":"Crunican Brothers Orchard",
    "wof:placetype":"venue"
},
  "geometry": {"coordinates":[-81.246216,42.986897],"type":"Point"}
}