{
  "type": "Feature",
  "properties": {
    "addr:full":"1185 Rue Saint-Mathieu Montreal QC H3H 2H6",
    "addr:housenumber":"1185",
    "addr:postcode":"h3h 2h6",
    "addr:street":"Rue Saint-Mathieu",
    "iso:country":"CA",
    "sg:address":"1185 Rue Saint-Mathieu",
    "sg:city":"Montreal",
    "sg:classifiers":[
        {
            "category":"Organizations",
            "subcategory":"Professional Association",
            "type":"Services"
        }
    ],
    "sg:phone":"+1 514 933 8354",
    "sg:postcode":"H3H 2H6",
    "sg:province":"QC",
    "wof:name":"Respect DE LA Vie Mouvement",
    "wof:placetype":"venue"
},
  "geometry": {"coordinates":[-73.577309,45.492912],"type":"Point"}
}