{
  "type": "Feature",
  "properties": {
    "iso:country":"CA",
    "sg:address":"34810 Clayburn Rd",
    "sg:city":"Abbotsford",
    "sg:classifiers":[
        {
            "category":"Food & Beverages",
            "subcategory":"Groceries & Convenience Stores",
            "type":"Retail Goods"
        }
    ],
    "sg:phone":"+1 604 853 4020",
    "sg:postcode":"V2S 7Y9",
    "sg:province":"BC",
    "sg:tags":[
        "grocer"
    ],
    "wof:name":"Clayburn Village Store",
    "wof:placetype":"venue"
},
  "geometry": {"coordinates":[-122.260398865,49.0817451477],"type":"Point"}
}