{
  "type": "Feature",
  "properties": {
    "addr:full":"16 Cumberland St Toronto ON M4W 1J5",
    "addr:housenumber":"16",
    "addr:postcode":"m4w 1j5",
    "addr:street":"Cumberland St",
    "iso:country":"CA",
    "sg:address":"16 Cumberland St",
    "sg:city":"Toronto",
    "sg:classifiers":[
        {
            "category":"Professional",
            "subcategory":"Printing & Photocopies",
            "type":"Services"
        }
    ],
    "sg:phone":"+1 416 924 1416",
    "sg:postcode":"M4W 1J5",
    "sg:province":"ON",
    "sg:tags":[
        "duplicating",
        "copying"
    ],
    "wof:name":"Printing House",
    "wof:placetype":"venue"
},
  "geometry": {"coordinates":[-79.387878418,43.6710929871],"type":"Point"}
}