{
  "type": "Feature",
  "properties": {
    "addr:full":"1490 Hwy 69 Pointe-Au-Baril-Station ON P0G 1K0",
    "addr:housenumber":"1490",
    "addr:postcode":"p0g 1k0",
    "addr:street":"Hwy 69",
    "iso:country":"CA",
    "sg:address":"1490 Hwy 69",
    "sg:city":"Pointe-Au-Baril-Station",
    "sg:classifiers":[
        {
            "category":"Restaurant",
            "type":"Food & Drink"
        }
    ],
    "sg:phone":"+1 705 366 2396",
    "sg:postcode":"P0G 1K0",
    "sg:province":"ON",
    "wof:name":"Larry's Tavern Restaurant",
    "wof:placetype":"venue"
},
  "geometry": {"coordinates":[-80.37716674799999,45.6002883911],"type":"Point"}
}