{
  "type": "Feature",
  "properties": {
    "addr:full":"2558 Duryea St Oil Springs ON N0N 1P0",
    "addr:housenumber":"2558",
    "addr:postcode":"n0n 1p0",
    "addr:street":"Duryea St",
    "iso:country":"CA",
    "sg:address":"2558 Duryea St",
    "sg:city":"Oil Springs",
    "sg:classifiers":[
        {
            "category":"Mining & Drilling",
            "type":"Manufacturing & Wholesale Goods"
        }
    ],
    "sg:phone":"+1 519 834 2677",
    "sg:postcode":"N0N 1P0",
    "sg:province":"ON",
    "sg:tags":[
        "oil",
        "gas",
        "producer"
    ],
    "wof:name":"Charles Fairbank Oil Prprtys",
    "wof:placetype":"venue"
},
  "geometry": {"coordinates":[-82.109146,42.782337],"type":"Point"}
}