{
  "type": "Feature",
  "properties": {
    "iso:country":"CA",
    "sg:address":"4567 Dixie Rd",
    "sg:city":"Mississauga",
    "sg:classifiers":[
        {
            "category":"Banks & Credit Unions",
            "subcategory":"Bank",
            "type":"Services"
        }
    ],
    "sg:phone":"+1 905 625 6973",
    "sg:postcode":"L4W 1S2",
    "sg:province":"ON",
    "wof:name":"United Employees Credit Union",
    "wof:placetype":"venue"
},
  "geometry": {"coordinates":[-79.6181793213,43.634147644],"type":"Point"}
}