{
  "type": "Feature",
  "properties": {
    "addr:full":"1009 Rue Galt O Sherbrooke QC J1H 1Z9",
    "addr:housenumber":"1009",
    "addr:postcode":"j1h 1z9",
    "addr:street":"Rue Galt O",
    "iso:country":"CA",
    "sg:address":"1009 Rue Galt O",
    "sg:city":"Sherbrooke",
    "sg:classifiers":[
        {
            "category":"Organizations",
            "subcategory":"Labor Organization",
            "type":"Services"
        }
    ],
    "sg:phone":"+1 819 569 9377",
    "sg:postcode":"J1H 1Z9",
    "sg:province":"QC",
    "wof:name":"Centrale-Syndicats Democratiqu",
    "wof:placetype":"venue"
},
  "geometry": {"coordinates":[-71.902863,45.391727],"type":"Point"}
}