{
  "type": "Feature",
  "properties": {
    "iso:country":"CA",
    "sg:address":"1240 Rue DE Carillon",
    "sg:city":"Saint-Bruno",
    "sg:classifiers":[
        {
            "category":"Insurance",
            "subcategory":"Insurance Agent",
            "type":"Services"
        }
    ],
    "sg:phone":"+1 450 653 2753",
    "sg:postcode":"J3V 3G2",
    "sg:province":"QC",
    "wof:name":"Assurances Rolland Gagne Inc",
    "wof:placetype":"venue"
},
  "geometry": {"coordinates":[-71.67552185060001,48.4717712402],"type":"Point"}
}