{
  "type": "Feature",
  "properties": {
    "addr:full":"471 Hazeldean Rd Kanata ON K2L 4B8",
    "addr:housenumber":"471",
    "addr:postcode":"k2l 4b8",
    "addr:street":"Hazeldean Rd",
    "iso:country":"CA",
    "sg:address":"471 Hazeldean Rd",
    "sg:city":"Kanata",
    "sg:classifiers":[
        {
            "category":"Shopping",
            "subcategory":"Florist",
            "type":"Retail Goods"
        }
    ],
    "sg:phone":"+1 613 831 3939",
    "sg:postcode":"K2L 4B8",
    "sg:province":"ON",
    "wof:name":"Talisman Flowers",
    "wof:placetype":"venue"
},
  "geometry": {"coordinates":[-75.88861083979999,45.2981910706],"type":"Point"}
}