{
  "type": "Feature",
  "properties": {
    "iso:country":"CA",
    "sg:city":"Winnipeg",
    "sg:classifiers":[
        {
            "category":"Health Services",
            "subcategory":"Medical Lab",
            "type":"Services"
        }
    ],
    "sg:phone":"+1 204 942 0299",
    "sg:postcode":"R3E 0B9",
    "sg:province":"MB",
    "sg:tags":[
        "laboratory"
    ],
    "wof:name":"Custom Dental Technologies",
    "wof:placetype":"venue"
},
  "geometry": {"coordinates":[-97.169593811,49.8970222473],"type":"Point"}
}