{
  "type": "Feature",
  "properties": {
    "addr:full":"99 Ch Merrill Chibougamau QC G8P 1C3",
    "addr:housenumber":"99",
    "addr:postcode":"g8p 1c3",
    "addr:street":"Ch Merrill",
    "iso:country":"CA",
    "sg:address":"99 Ch Merrill",
    "sg:city":"Chibougamau",
    "sg:classifiers":[
        {
            "category":"Food & Beverages",
            "subcategory":"Groceries & Convenience Stores",
            "type":"Retail Goods"
        }
    ],
    "sg:phone":"+1 418 748 3298",
    "sg:postcode":"G8P 1C3",
    "sg:province":"QC",
    "sg:tags":[
        "grocer"
    ],
    "wof:name":"Tabagie Depanneur Merrill Ltee",
    "wof:placetype":"venue"
},
  "geometry": {"coordinates":[-74.3782043457,49.9133911133],"type":"Point"}
}