{
  "type": "Feature",
  "properties": {
    "addr:full":"131 Savage Dr Cambridge ON N1T 1S5",
    "addr:housenumber":"131",
    "addr:postcode":"n1t 1s5",
    "addr:street":"Savage Dr",
    "iso:country":"CA",
    "sg:address":"131 Savage Dr",
    "sg:city":"Cambridge",
    "sg:classifiers":[
        {
            "category":"Retail",
            "subcategory":"Auto Repair",
            "type":"Services"
        }
    ],
    "sg:phone":"+1 519 622 9600",
    "sg:postcode":"N1T 1S5",
    "sg:province":"ON",
    "sg:tags":[
        "truck"
    ],
    "wof:name":"Acores Truck & Trailer Svc",
    "wof:placetype":"venue"
},
  "geometry": {"coordinates":[-80.284362793,43.3667907715],"type":"Point"}
}