{
  "type": "Feature",
  "properties": {
    "iso:country":"CA",
    "sg:address":"4401 Rollyview Rd",
    "sg:city":"Leduc",
    "sg:classifiers":[
        {
            "category":"Organizations",
            "subcategory":"Religious Organization",
            "type":"Services"
        }
    ],
    "sg:phone":"+1 780 986 9299",
    "sg:postcode":"T9E 7H4",
    "sg:province":"AB",
    "sg:tags":[
        "church"
    ],
    "wof:name":"Leduc Fellowship Church",
    "wof:placetype":"venue"
},
  "geometry": {"coordinates":[-113.52537536600001,53.250579834],"type":"Point"}
}