{
  "type": "Feature",
  "properties": {
    "addr:full":"325 Boul Baril O #A Princeville QC G6L 3V8",
    "addr:housenumber":"325",
    "addr:postcode":"g6l 3v8",
    "addr:street":"Boul Baril O # A",
    "iso:country":"CA",
    "sg:address":"325 Boul Baril O #A",
    "sg:city":"Princeville",
    "sg:classifiers":[
        {
            "category":"Retail",
            "subcategory":"Auto Repair",
            "type":"Services"
        }
    ],
    "sg:phone":"+1 819 364 3804",
    "sg:postcode":"G6L 3V8",
    "sg:province":"QC",
    "sg:tags":[
        "repairing",
        "automobile"
    ],
    "wof:name":"Atelier Mecanique Importek",
    "wof:placetype":"venue"
},
  "geometry": {"coordinates":[-71.88121032710001,46.1622962952],"type":"Point"}
}