{
  "type": "Feature",
  "properties": {
    "addr:full":"1903 Ramsay St SE Calgary AB T2G 4H6",
    "addr:housenumber":"1903",
    "addr:postcode":"t2g 4h6",
    "addr:street":"Ramsay St Se",
    "iso:country":"CA",
    "sg:address":"1903 Ramsay St SE",
    "sg:city":"Calgary",
    "sg:classifiers":[
        {
            "category":"Shopping",
            "type":"Retail Goods"
        }
    ],
    "sg:phone":"+1 403 264 2852",
    "sg:postcode":"T2G 4H6",
    "sg:province":"AB",
    "sg:tags":[
        "picture",
        "frame"
    ],
    "wof:name":"Treasured Memories Picture Frm",
    "wof:placetype":"venue"
},
  "geometry": {"coordinates":[-114.045372009,51.0368461609],"type":"Point"}
}