{
  "type": "Feature",
  "properties": {
    "addr:full":"8765 Rue Du Parcours Anjou QC H1J 1B9",
    "addr:housenumber":"8765",
    "addr:postcode":"h1j 1b9",
    "addr:street":"Rue Du Parcours",
    "iso:country":"CA",
    "sg:address":"8765 Rue Du Parcours",
    "sg:city":"Anjou",
    "sg:classifiers":[
        {
            "category":"Manufacturing",
            "subcategory":"Paper Products",
            "type":"Manufacturing & Wholesale Goods"
        }
    ],
    "sg:phone":"+1 514 354 5192",
    "sg:postcode":"H1J 1B9",
    "sg:province":"QC",
    "sg:tags":[
        "label"
    ],
    "wof:name":"Etiquettes Flexo",
    "wof:placetype":"venue"
},
  "geometry": {"coordinates":[-73.567474,45.620033],"type":"Point"}
}