{
  "type": "Feature",
  "properties": {
    "addr:full":"36 Ellesmere Rd Scarborough ON M1R 4C1",
    "addr:housenumber":"36",
    "addr:postcode":"m1r 4c1",
    "addr:street":"Ellesmere Rd",
    "iso:country":"CA",
    "sg:address":"36 Ellesmere Rd",
    "sg:city":"Scarborough",
    "sg:classifiers":[
        {
            "category":"Retail",
            "subcategory":"Self-service Laundry",
            "type":"Services"
        }
    ],
    "sg:phone":"+1 416 441 6118",
    "sg:postcode":"M1R 4C1",
    "sg:province":"ON",
    "wof:name":"Millenium Coin Laundry",
    "wof:placetype":"venue"
},
  "geometry": {"coordinates":[-79.3136672974,43.7583885193],"type":"Point"}
}