{
  "type": "Feature",
  "properties": {
    "addr:full":"Edmundston NB E3V 4Y6",
    "addr:postcode":"e3v 4y6",
    "iso:country":"CA",
    "sg:city":"Edmundston",
    "sg:classifiers":[
        {
            "category":"Insurance",
            "subcategory":"Insurance Agent",
            "type":"Services"
        }
    ],
    "sg:phone":"+1 506 735 8468",
    "sg:postcode":"E3V 4Y6",
    "sg:province":"NB",
    "wof:name":"Clarica Life Insurance CO",
    "wof:placetype":"venue"
},
  "geometry": {"coordinates":[-68.32997899999999,47.364525],"type":"Point"}
}