{
  "type": "Feature",
  "properties": {
    "iso:country":"CA",
    "sg:address":"70 Rue Elizabeth",
    "sg:city":"Sorel-Tracy",
    "sg:classifiers":[
        {
            "category":"Organizations",
            "subcategory":"Professional Association",
            "type":"Services"
        }
    ],
    "sg:phone":"+1 450 743 0081",
    "sg:postcode":"J3P 4G5",
    "sg:province":"QC",
    "wof:name":"Fraternite Nationale Des",
    "wof:placetype":"venue"
},
  "geometry": {"coordinates":[-73.11278533940001,46.0444641113],"type":"Point"}
}