{
  "type": "Feature",
  "properties": {
    "addr:full":"Montreal QC H3N 1S7",
    "addr:postcode":"h3n 1s7",
    "iso:country":"CA",
    "sg:city":"Montreal",
    "sg:classifiers":[
        {
            "category":"Health Services",
            "subcategory":"Doctor",
            "type":"Services"
        }
    ],
    "sg:phone":"+1 514 277 8088",
    "sg:postcode":"H3N 1S7",
    "sg:province":"QC",
    "sg:tags":[
        "physician",
        "surgeon"
    ],
    "wof:name":"Lambrinos, D J MD",
    "wof:placetype":"venue"
},
  "geometry": {"coordinates":[-73.613029,45.541279],"type":"Point"}
}