{
  "type": "Feature",
  "properties": {
    "addr:full":"10 Rue Saint-Aime Louiseville QC J5V 2A7",
    "addr:housenumber":"10",
    "addr:postcode":"j5v 2a7",
    "addr:street":"Rue Saint-Aime",
    "iso:country":"CA",
    "sg:address":"10 Rue Saint-Aime",
    "sg:city":"Louiseville",
    "sg:classifiers":[
        {
            "category":"Food & Beverages",
            "subcategory":"Specialty",
            "type":"Retail Goods"
        }
    ],
    "sg:phone":"+1 819 228 9994",
    "sg:postcode":"J5V 2A7",
    "sg:province":"QC",
    "wof:name":"Fleur DE Sarrasin",
    "wof:placetype":"venue"
},
  "geometry": {"coordinates":[-72.9433746338,46.2559661865],"type":"Point"}
}