{
  "type": "Feature",
  "properties": {
    "addr:full":"191 Lakeshore Rd E Oakville ON L6J 1H5",
    "addr:housenumber":"191",
    "addr:postcode":"l6j 1h5",
    "addr:street":"Lakeshore Rd E",
    "iso:country":"CA",
    "sg:address":"191 Lakeshore Rd E",
    "sg:city":"Oakville",
    "sg:classifiers":[
        {
            "category":"Home & Garden",
            "subcategory":"Furniture",
            "type":"Retail Goods"
        }
    ],
    "sg:phone":"+1 905 815 0856",
    "sg:postcode":"L6J 1H5",
    "sg:province":"ON",
    "wof:name":"Majenta Home Furnishings",
    "wof:placetype":"venue"
},
  "geometry": {"coordinates":[-79.6686630249,43.4455718994],"type":"Point"}
}