{
  "type": "Feature",
  "properties": {
    "addr:full":"160 Av Lamontagne Quebec QC G1L 2C2",
    "addr:housenumber":"160",
    "addr:postcode":"g1l 2c2",
    "addr:street":"Av Lamontagne",
    "iso:country":"CA",
    "sg:address":"160 Av Lamontagne",
    "sg:city":"Quebec",
    "sg:classifiers":[
        {
            "category":"Building & Trades",
            "subcategory":"Plumbing",
            "type":"Services"
        }
    ],
    "sg:phone":"+1 418 525 9060",
    "sg:postcode":"G1L 2C2",
    "sg:province":"QC",
    "sg:tags":[
        "contractor"
    ],
    "wof:name":"Garneau, Raymond",
    "wof:placetype":"venue"
},
  "geometry": {"coordinates":[-71.24297300000001,46.8283],"type":"Point"}
}