{
  "type": "Feature",
  "properties": {
    "iso:country":"CA",
    "sg:city":"Winnipeg",
    "sg:classifiers":[
        {
            "category":"Social Services",
            "type":"Services"
        }
    ],
    "sg:phone":"+1 204 339 4428",
    "sg:postcode":"R2G 2B9",
    "sg:province":"MB",
    "sg:tags":[
        "senior",
        "citizen"
    ],
    "wof:name":"Parkside Plaza Meal Program",
    "wof:placetype":"venue"
},
  "geometry": {"coordinates":[-97.0813903809,49.9500808716],"type":"Point"}
}