{
  "type": "Feature",
  "properties": {
    "addr:full":"6206 11 Ave NW Edmonton AB T6L 2G4",
    "addr:housenumber":"6206",
    "addr:postcode":"t6l 2g4",
    "addr:street":"11 Ave Nw",
    "iso:country":"CA",
    "sg:address":"6206 11 Ave NW",
    "sg:city":"Edmonton",
    "sg:classifiers":[
        {
            "category":"Building & Trades",
            "subcategory":"Construction",
            "type":"Services"
        }
    ],
    "sg:phone":"+1 780 462 7013",
    "sg:postcode":"T6L 2G4",
    "sg:province":"AB",
    "sg:tags":[
        "masonry",
        "contractor"
    ],
    "wof:name":"Cherry Lane Brick & Stone Ltd",
    "wof:placetype":"venue"
},
  "geometry": {"coordinates":[-113.43338799999999,53.439552],"type":"Point"}
}