{
  "type": "Feature",
  "properties": {
    "addr:full":"298 Lakeshore Rd E Mississauga ON L5G 1H2",
    "addr:housenumber":"298",
    "addr:postcode":"l5g 1h2",
    "addr:street":"Lakeshore Rd E",
    "iso:country":"CA",
    "sg:address":"298 Lakeshore Rd E",
    "sg:city":"Mississauga",
    "sg:classifiers":[
        {
            "category":"Professional",
            "subcategory":"Accounting & Tax Preparation",
            "type":"Services"
        }
    ],
    "sg:phone":"+1 905 271 1077",
    "sg:postcode":"L5G 1H2",
    "sg:province":"ON",
    "sg:tags":[
        "accountant"
    ],
    "wof:name":"Pilutti, Bryan M CA",
    "wof:placetype":"venue"
},
  "geometry": {"coordinates":[-79.575531,43.561275],"type":"Point"}
}