{
  "type": "Feature",
  "properties": {
    "addr:full":"221 Coronation Ave Duncan BC V9L 2T1",
    "addr:housenumber":"221",
    "addr:postcode":"v9l 2t1",
    "addr:street":"Coronation Ave",
    "iso:country":"CA",
    "sg:address":"221 Coronation Ave",
    "sg:city":"Duncan",
    "sg:classifiers":[
        {
            "category":"Real Estate",
            "subcategory":"Surveying",
            "type":"Services"
        }
    ],
    "sg:phone":"+1 250 746 4745",
    "sg:postcode":"V9L 2T1",
    "sg:province":"BC",
    "sg:tags":[
        "surveyor"
    ],
    "wof:name":"Kenyon & Wilson",
    "wof:placetype":"venue"
},
  "geometry": {"coordinates":[-123.70295,48.778873],"type":"Point"}
}