{
  "type": "Feature",
  "properties": {
    "addr:full":"Vancouver BC V6A 1P9",
    "addr:postcode":"v6a 1p9",
    "iso:country":"CA",
    "sg:city":"Vancouver",
    "sg:classifiers":[
        {
            "category":"Retail",
            "subcategory":"Repair Shop",
            "type":"Services"
        }
    ],
    "sg:phone":"+1 604 669 8008",
    "sg:postcode":"V6A 1P9",
    "sg:province":"BC",
    "sg:tags":[
        "lock",
        "locksmith"
    ],
    "wof:name":"Trust Lock & Security",
    "wof:placetype":"venue"
},
  "geometry": {"coordinates":[-123.092285156,49.2813224792],"type":"Point"}
}