{
  "type": "Feature",
  "properties": {
    "addr:full":"PO Box 39588 Rpo White Rock White Rock BC V4B 5L6",
    "addr:housenumber":"po box",
    "addr:postcode":"39588;v4b 5l6",
    "iso:country":"CA",
    "sg:address":"PO Box 39588 Rpo White Rock",
    "sg:city":"White Rock",
    "sg:classifiers":[
        {
            "category":"Professional",
            "subcategory":"Business Services",
            "type":"Services"
        }
    ],
    "sg:phone":"+1 604 538 3478",
    "sg:postcode":"V4B 5L6",
    "sg:province":"BC",
    "sg:tags":[
        "literary",
        "agent"
    ],
    "wof:name":"Carolyn Swayze Literary Agency",
    "wof:placetype":"venue"
},
  "geometry": {"coordinates":[-122.79679107699999,49.0239181519],"type":"Point"}
}