{
  "type": "Feature",
  "properties": {
    "iso:country":"CA",
    "sg:address":"381 Birch St",
    "sg:city":"Orillia",
    "sg:classifiers":[
        {
            "category":"Education",
            "subcategory":"School",
            "type":"Public Place"
        }
    ],
    "sg:phone":"+1 705 325 1318",
    "sg:postcode":"L3V 2P5",
    "sg:province":"ON",
    "wof:name":"Twin Lakes Secondary School",
    "wof:placetype":"venue"
},
  "geometry": {"coordinates":[-79.43376159669999,44.5941390991],"type":"Point"}
}