{
  "type": "Feature",
  "properties": {
    "iso:country":"CA",
    "sg:city":"Red Deer",
    "sg:classifiers":[
        {
            "category":"Building & Trades",
            "subcategory":"Cleaning & Sanitation",
            "type":"Services"
        }
    ],
    "sg:phone":"+1 403 357 0096",
    "sg:postcode":"T4N 6V3",
    "sg:province":"AB",
    "sg:tags":[
        "janitor"
    ],
    "wof:name":"Allpro Building Maintenance",
    "wof:placetype":"venue"
},
  "geometry": {"coordinates":[-113.817108154,52.287979126],"type":"Point"}
}