{
  "type": "Feature",
  "properties": {
    "iso:country":"CA",
    "sg:address":"1725 Kingston Rd",
    "sg:city":"Pickering",
    "sg:classifiers":[
        {
            "category":"Personal",
            "subcategory":"Beauty Salon",
            "type":"Services"
        }
    ],
    "sg:phone":"+1 905 428 3484",
    "sg:postcode":"L1V 4L9",
    "sg:province":"ON",
    "wof:name":"Little Tots Hair Shop Ltd",
    "wof:placetype":"venue"
},
  "geometry": {"coordinates":[-79.072433,43.848789],"type":"Point"}
}