{
  "type": "Feature",
  "properties": {
    "iso:country":"CA",
    "sg:city":"North York",
    "sg:classifiers":[
        {
            "category":"Personal",
            "subcategory":"Beauty Salon",
            "type":"Services"
        }
    ],
    "sg:phone":"+1 416 755 2943",
    "sg:postcode":"M4A 2M2",
    "sg:province":"ON",
    "wof:name":"Hair Junction",
    "wof:placetype":"venue"
},
  "geometry": {"coordinates":[-79.302002,43.722713],"type":"Point"}
}