{
  "type": "Feature",
  "properties": {
    "addr:full":"3750 Mowat Rd East St Paul MB R2E 1B6",
    "addr:housenumber":"3750",
    "addr:postcode":"r2e 1b6",
    "addr:street":"Mowat Rd East",
    "iso:country":"CA",
    "sg:address":"3750 Mowat Rd",
    "sg:city":"East St Paul",
    "sg:classifiers":[
        {
            "category":"Manufacturing",
            "subcategory":"Tools & Machinery",
            "type":"Manufacturing & Wholesale Goods"
        }
    ],
    "sg:phone":"+1 204 255 8611",
    "sg:postcode":"R2E 1B6",
    "sg:province":"MB",
    "sg:tags":[
        "lubricating",
        "system",
        "devices"
    ],
    "wof:name":"Rti Cunsulting & Mechanical",
    "wof:placetype":"venue"
},
  "geometry": {"coordinates":[-97.016159,50.009468],"type":"Point"}
}