{
  "type": "Feature",
  "properties": {
    "addr:full":"255 St George St Annapolis Royal NS B0S 1A0",
    "addr:housenumber":"255",
    "addr:postcode":"b0s 1a0",
    "addr:street":"St George St",
    "iso:country":"CA",
    "sg:address":"255 St George St",
    "sg:city":"Annapolis Royal",
    "sg:classifiers":[
        {
            "category":"Health Services",
            "subcategory":"Doctor",
            "type":"Services"
        }
    ],
    "sg:phone":"+1 902 532 2242",
    "sg:postcode":"B0S 1A0",
    "sg:province":"NS",
    "sg:tags":[
        "dentist"
    ],
    "wof:name":"Murray-Allen, Chantal DDS",
    "wof:placetype":"venue"
},
  "geometry": {"coordinates":[-65.519524,44.743896],"type":"Point"}
}