{
  "type": "Feature",
  "properties": {
    "iso:country":"CA",
    "sg:address":"3750 Mcphillips St",
    "sg:city":"West St Paul",
    "sg:classifiers":[
        {
            "category":"Restaurant",
            "type":"Food & Drink"
        }
    ],
    "sg:phone":"+1 204 339 4439",
    "sg:postcode":"R4A 5A5",
    "sg:province":"MB",
    "wof:name":"Grassmere Family Restaurant",
    "wof:placetype":"venue"
},
  "geometry": {"coordinates":[-97.1002197266,49.995349884],"type":"Point"}
}