{
  "type": "Feature",
  "properties": {
    "iso:country":"CA",
    "sg:address":"123 Main St",
    "sg:city":"Odessa",
    "sg:classifiers":[
        {
            "category":"Autos & Motor Vehicles",
            "subcategory":"Auto Supplies",
            "type":"Retail Goods"
        }
    ],
    "sg:phone":"+1 613 386 5617",
    "sg:postcode":"K0H 2H0",
    "sg:province":"ON",
    "sg:tags":[
        "automobile",
        "parts"
    ],
    "wof:name":"Odessa Auto Supply",
    "wof:placetype":"venue"
},
  "geometry": {"coordinates":[-76.7194061279,44.2768707275],"type":"Point"}
}