{
  "type": "Feature",
  "properties": {
    "addr:full":"7051 Moffatt Rd Richmond BC V6Y 3W2",
    "addr:housenumber":"7051",
    "addr:postcode":"v6y 3w2",
    "addr:street":"Moffatt Rd",
    "iso:country":"CA",
    "sg:address":"7051 Moffatt Rd",
    "sg:city":"Richmond",
    "sg:classifiers":[
        {
            "category":"Health Services",
            "subcategory":"Nursing And Care Facility",
            "type":"Services"
        }
    ],
    "sg:phone":"+1 604 273 1225",
    "sg:postcode":"V6Y 3W2",
    "sg:province":"BC",
    "sg:tags":[
        "home",
        "retirement",
        "community"
    ],
    "wof:name":"Courtyard Gardens",
    "wof:placetype":"venue"
},
  "geometry": {"coordinates":[-123.143806,49.161674],"type":"Point"}
}