{
  "type": "Feature",
  "properties": {
    "addr:full":"3767 Commercial St Vancouver BC V5N 4G1",
    "addr:housenumber":"3767",
    "addr:postcode":"v5n 4g1",
    "addr:street":"Commercial St",
    "iso:country":"CA",
    "sg:address":"3767 Commercial St",
    "sg:city":"Vancouver",
    "sg:classifiers":[
        {
            "category":"Manufacturing",
            "subcategory":"Wood Products",
            "type":"Manufacturing & Wholesale Goods"
        }
    ],
    "sg:phone":"+1 604 327 1717",
    "sg:postcode":"V5N 4G1",
    "sg:province":"BC",
    "sg:tags":[
        "picture",
        "frame"
    ],
    "wof:name":"Art Connections Inc",
    "wof:placetype":"venue"
},
  "geometry": {"coordinates":[-123.068192,49.251305],"type":"Point"}
}