{
  "type": "Feature",
  "properties": {
    "addr:full":"9104 Yonge St Richmond Hill ON L4C 6Z9",
    "addr:housenumber":"9104",
    "addr:postcode":"l4c 6z9",
    "addr:street":"Yonge St",
    "iso:country":"CA",
    "sg:address":"9104 Yonge St",
    "sg:city":"Richmond Hill",
    "sg:classifiers":[
        {
            "category":"Professional",
            "subcategory":"Business Services",
            "type":"Services"
        }
    ],
    "sg:phone":"+1 905 889 5887",
    "sg:postcode":"L4C 6Z9",
    "sg:province":"ON",
    "sg:tags":[
        "decorating",
        "contractor"
    ],
    "wof:name":"Empire Homes Decor Ctr",
    "wof:placetype":"venue"
},
  "geometry": {"coordinates":[-79.4322814941,43.8492774963],"type":"Point"}
}