{
  "type": "Feature",
  "properties": {
    "iso:country":"CA",
    "sg:address":"750 Av Du Phare O",
    "sg:city":"Matane",
    "sg:classifiers":[
        {
            "category":"Restaurant",
            "type":"Food & Drink"
        }
    ],
    "sg:phone":"+1 418 562 4602",
    "sg:postcode":"G4W 3W8",
    "sg:province":"QC",
    "wof:name":"L'Illot Du Vieux Port Enr",
    "wof:placetype":"venue"
},
  "geometry": {"coordinates":[-67.5010757446,48.8525123596],"type":"Point"}
}