{
  "type": "Feature",
  "properties": {
    "iso:country":"CA",
    "sg:address":"105 St Lawrence St W # B",
    "sg:city":"Madoc",
    "sg:classifiers":[
        {
            "category":"Retail",
            "subcategory":"Auto Repair",
            "type":"Services"
        }
    ],
    "sg:phone":"+1 613 473 4642",
    "sg:postcode":"K0K 2K0",
    "sg:province":"ON",
    "sg:tags":[
        "repairing",
        "automobile"
    ],
    "wof:name":"Bell Mechanical",
    "wof:placetype":"venue"
},
  "geometry": {"coordinates":[-77.47533416749999,44.5044288635],"type":"Point"}
}