{
  "type": "Feature",
  "properties": {
    "iso:country":"CA",
    "sg:address":"8100 Boul Newman",
    "sg:city":"Lasalle",
    "sg:classifiers":[
        {
            "category":"Shopping",
            "subcategory":"Computers & Home Electronics",
            "type":"Retail Goods"
        }
    ],
    "sg:phone":"+1 514 364 5511",
    "sg:postcode":"H8N 1X9",
    "sg:province":"QC",
    "sg:tags":[
        "equipment",
        "dealer"
    ],
    "wof:name":"Compusmart Lasalle",
    "wof:placetype":"venue"
},
  "geometry": {"coordinates":[-73.626877,45.434826],"type":"Point"}
}