{
  "type": "Feature",
  "properties": {
    "addr:full":"738 Main St Woodstock NB E7M 2E7",
    "addr:housenumber":"738",
    "addr:postcode":"e7m 2e7",
    "addr:street":"Main St",
    "iso:country":"CA",
    "sg:address":"738 Main St",
    "sg:city":"Woodstock",
    "sg:classifiers":[
        {
            "category":"Personal",
            "subcategory":"Beauty Salon",
            "type":"Services"
        }
    ],
    "sg:phone":"+1 506 325 2010",
    "sg:postcode":"E7M 2E7",
    "sg:province":"NB",
    "wof:name":"Looks Unlimited",
    "wof:placetype":"venue"
},
  "geometry": {"coordinates":[-67.572495,46.155266],"type":"Point"}
}