{
  "type": "Feature",
  "properties": {
    "addr:full":"375 Water Street Suite 645 Vancouver, BC V6B 5C6",
    "addr:housenumber":"375",
    "addr:postcode":"v6b 5c6",
    "addr:street":"Water Street Suite 645",
    "iso:country":"CA",
    "sg:address":"375 Water Street Suite 645",
    "sg:city":"Vancouver, BC",
    "sg:classifiers":[
        {
            "category":"Professional",
            "subcategory":"Computer Services",
            "type":"Services"
        }
    ],
    "sg:postcode":"V6B 5C6",
    "sg:tags":[
        "domains",
        "domain-names"
    ],
    "sg:website":"http://www.livecurrent.com/",
    "wof:name":"Live Current Media",
    "wof:placetype":"venue"
},
  "geometry": {"coordinates":[-123.110394,49.284608],"type":"Point"}
}