{
  "type": "Feature",
  "properties": {
    "iso:country":"CA",
    "sg:address":"4959 Route 17",
    "sg:city":"Alfred",
    "sg:classifiers":[
        {
            "category":"Building & Trades",
            "subcategory":"Construction",
            "type":"Services"
        }
    ],
    "sg:phone":"+1 613 679 4397",
    "sg:postcode":"K0B 1A0",
    "sg:province":"ON",
    "sg:tags":[
        "excavating",
        "contractor"
    ],
    "wof:name":"Martin Leclair Excavation",
    "wof:placetype":"venue"
},
  "geometry": {"coordinates":[-74.9013290405,45.5526237488],"type":"Point"}
}