{
  "type": "Feature",
  "properties": {
    "addr:full":"108 Winnipeg N White River ON P0M 3G0",
    "addr:housenumber":"108",
    "addr:postcode":"p0m 3g0",
    "addr:street":"Winnipeg N",
    "iso:country":"CA",
    "sg:address":"108 Winnipeg N",
    "sg:city":"White River",
    "sg:classifiers":[
        {
            "category":"Organizations",
            "subcategory":"Professional Association",
            "type":"Services"
        }
    ],
    "sg:phone":"+1 807 822 2399",
    "sg:postcode":"P0M 3G0",
    "sg:province":"ON",
    "wof:name":"Canadian Legion",
    "wof:placetype":"venue"
},
  "geometry": {"coordinates":[-85.2885055542,48.5966644287],"type":"Point"}
}