{
  "type": "Feature",
  "properties": {
    "addr:full":"Penetanguishene ON L9M 1M2",
    "addr:postcode":"l9m 1m2",
    "iso:country":"CA",
    "sg:city":"Penetanguishene",
    "sg:classifiers":[
        {
            "category":"Government",
            "subcategory":"Office",
            "type":"Public Place"
        }
    ],
    "sg:phone":"+1 705 549 2921",
    "sg:postcode":"L9M 1M2",
    "sg:province":"ON",
    "sg:tags":[
        "member",
        "legislative",
        "assembly"
    ],
    "wof:name":"DE Villers, Paul",
    "wof:placetype":"venue"
},
  "geometry": {"coordinates":[-79.9330444336,44.7672996521],"type":"Point"}
}