{
  "type": "Feature",
  "properties": {
    "addr:full":"171 Main St St Lunaire-Griquet NL A0K 2X0",
    "addr:housenumber":"171",
    "addr:postcode":"a0k 2x0",
    "addr:street":"Main St",
    "iso:country":"CA",
    "sg:address":"171 Main St",
    "sg:city":"St Lunaire-Griquet",
    "sg:classifiers":[
        {
            "category":"Personal",
            "subcategory":"Beauty Salon",
            "type":"Services"
        }
    ],
    "sg:phone":"+1 709 623 2077",
    "sg:postcode":"A0K 2X0",
    "sg:province":"NL",
    "wof:name":"Ruth's Beauty Salon",
    "wof:placetype":"venue"
},
  "geometry": {"coordinates":[-55.4839439392,51.5050582886],"type":"Point"}
}