{
  "type": "Feature",
  "properties": {
    "addr:full":"2120 Rue Sherbrooke E #608 Montreal QC H2K 1C3",
    "addr:housenumber":"2120",
    "addr:postcode":"h2k 1c3",
    "addr:street":"Rue Sherbrooke E # 608",
    "iso:country":"CA",
    "sg:address":"2120 Rue Sherbrooke E #608",
    "sg:city":"Montreal",
    "sg:classifiers":[
        {
            "category":"Professional",
            "subcategory":"Management & Consulting",
            "type":"Services"
        }
    ],
    "sg:phone":"+1 514 521 5464",
    "sg:postcode":"H2K 1C3",
    "sg:province":"QC",
    "sg:tags":[
        "marketing",
        "advertising",
        "consultant"
    ],
    "wof:name":"Soleil Communication-Marketing",
    "wof:placetype":"venue"
},
  "geometry": {"coordinates":[-73.5627441406,45.5310668945],"type":"Point"}
}