{
  "type": "Feature",
  "properties": {
    "addr:full":"301 Dundas St E Waterdown ON L0R 2H0",
    "addr:housenumber":"301",
    "addr:postcode":"l0r 2h0",
    "addr:street":"Dundas St E",
    "iso:country":"CA",
    "sg:address":"301 Dundas St E",
    "sg:city":"Waterdown",
    "sg:classifiers":[
        {
            "category":"Health Services",
            "subcategory":"Chiropractor",
            "type":"Services"
        }
    ],
    "sg:phone":"+1 905 335 5433",
    "sg:postcode":"L0R 2H0",
    "sg:province":"ON",
    "wof:name":"Waterdown Chiropractic Clinic",
    "wof:placetype":"venue"
},
  "geometry": {"coordinates":[-79.89348602290001,43.3330421448],"type":"Point"}
}