{
  "type": "Feature",
  "properties": {
    "iso:country":"CA",
    "sg:city":"Regina",
    "sg:classifiers":[
        {
            "category":"Shopping",
            "subcategory":"Luggage & Leather Goods",
            "type":"Retail Goods"
        }
    ],
    "sg:phone":"+1 306 586 0929",
    "sg:postcode":"S4S 3R1",
    "sg:province":"SK",
    "wof:name":"Doig's Handbags & Luggage Ltd",
    "wof:placetype":"venue"
},
  "geometry": {"coordinates":[-104.618370056,50.4185142517],"type":"Point"}
}