{
  "type": "Feature",
  "properties": {
    "addr:full":"545 Huxley Pl Kamloops BC V2B 5E6",
    "addr:housenumber":"545",
    "addr:postcode":"bc v2b 5e6",
    "addr:street":"Huxley Pl",
    "iso:country":"CA",
    "sg:address":"545 Huxley Pl",
    "sg:city":"Kamloops",
    "sg:classifiers":[
        {
            "category":"Building & Trades",
            "subcategory":"Plumbing",
            "type":"Services"
        }
    ],
    "sg:phone":"+1 250 554 2776",
    "sg:postcode":"V2B 5E6",
    "sg:province":"BC",
    "sg:tags":[
        "heating",
        "contractor"
    ],
    "wof:name":"Specialty Heating & Air Cond",
    "wof:placetype":"venue"
},
  "geometry": {"coordinates":[-120.387283325,50.697593689],"type":"Point"}
}