{
  "type": "Feature",
  "properties": {
    "addr:full":"1777 Tenth Line Rd Orleans ON K1E 3X2",
    "addr:housenumber":"1777",
    "addr:postcode":"k1e 3x2",
    "addr:street":"Tenth Line Rd",
    "iso:country":"CA",
    "sg:address":"1777 Tenth Line Rd",
    "sg:city":"Orleans",
    "sg:classifiers":[
        {
            "category":"Autos & Motor Vehicles",
            "subcategory":"Auto Supplies",
            "type":"Retail Goods"
        }
    ],
    "sg:phone":"+1 613 830 7000",
    "sg:postcode":"K1E 3X2",
    "sg:province":"ON",
    "sg:tags":[
        "automobile",
        "parts"
    ],
    "wof:name":"Canadian Tire",
    "wof:placetype":"venue"
},
  "geometry": {"coordinates":[-75.511414,45.480122],"type":"Point"}
}