{
  "type": "Feature",
  "properties": {
    "addr:full":"1100 Pleasant Dr Minto NB E4B 2V7",
    "addr:housenumber":"1100",
    "addr:postcode":"e4b 2v7",
    "addr:street":"Pleasant Dr",
    "iso:country":"CA",
    "sg:address":"1100 Pleasant Dr",
    "sg:city":"Minto",
    "sg:classifiers":[
        {
            "category":"Health Services",
            "subcategory":"Hospital",
            "type":"Services"
        }
    ],
    "sg:phone":"+1 506 327 7800",
    "sg:postcode":"E4B 2V7",
    "sg:province":"NB",
    "wof:name":"Queens North Health Complex",
    "wof:placetype":"venue"
},
  "geometry": {"coordinates":[-66.0503692627,46.0963592529],"type":"Point"}
}