{
  "type": "Feature",
  "properties": {
    "addr:full":"21 Ridgeway Cir Woodstock ON N4V 1C9",
    "addr:housenumber":"21",
    "addr:postcode":"n4v 1c9",
    "addr:street":"Ridgeway Cir",
    "iso:country":"CA",
    "sg:address":"21 Ridgeway Cir",
    "sg:city":"Woodstock",
    "sg:classifiers":[
        {
            "category":"Communications",
            "subcategory":"Television Station",
            "type":"Services"
        }
    ],
    "sg:phone":"+1 519 539 3701",
    "sg:postcode":"N4V 1C9",
    "sg:province":"ON",
    "sg:tags":[
        "broadcasting",
        "co"
    ],
    "wof:name":"Rogers Television",
    "wof:placetype":"venue"
},
  "geometry": {"coordinates":[-80.72674600000001,43.112343],"type":"Point"}
}