{
  "type": "Feature",
  "properties": {
    "iso:country":"CA",
    "sg:address":"171 Carlingview Dr",
    "sg:city":"Etobicoke",
    "sg:classifiers":[
        {
            "category":"Restaurant",
            "type":"Food & Drink"
        }
    ],
    "sg:phone":"+1 416 798 3203",
    "sg:postcode":"M9W 5E8",
    "sg:province":"ON",
    "wof:name":"Fox & Fiddle",
    "wof:placetype":"venue"
},
  "geometry": {"coordinates":[-79.592934,43.681541],"type":"Point"}
}