{
  "type": "Feature",
  "properties": {
    "addr:full":"308 10 Ave SE Slave Lake AB T0G 2A3",
    "addr:postcode":"t0g 2a3",
    "addr:street":"308 10 Ave Se",
    "iso:country":"CA",
    "sg:address":"308 10 Ave SE",
    "sg:city":"Slave Lake",
    "sg:classifiers":[
        {
            "category":"Retail",
            "subcategory":"Auto Repair",
            "type":"Services"
        }
    ],
    "sg:phone":"+1 780 849 3056",
    "sg:postcode":"T0G 2A3",
    "sg:province":"AB",
    "sg:tags":[
        "body",
        "automobile",
        "painting"
    ],
    "wof:name":"Avalon Auto Body",
    "wof:placetype":"venue"
},
  "geometry": {"coordinates":[-114.770500183,55.2736816406],"type":"Point"}
}