{
  "type": "Feature",
  "properties": {
    "addr:full":"PO Box 605 Beaverlodge AB T0H 0C0",
    "addr:housenumber":"po",
    "addr:postcode":"t0h 0c0",
    "addr:street":"Box 605 Beaverlodge",
    "iso:country":"CA",
    "sg:address":"PO Box 605",
    "sg:city":"Beaverlodge",
    "sg:classifiers":[
        {
            "category":"Mining & Drilling",
            "type":"Manufacturing & Wholesale Goods"
        }
    ],
    "sg:phone":"+1 780 354 8366",
    "sg:postcode":"T0H 0C0",
    "sg:province":"AB",
    "sg:tags":[
        "field",
        "oil"
    ],
    "wof:name":"Northwest Vibration Consulting",
    "wof:placetype":"venue"
},
  "geometry": {"coordinates":[-119.43632507300001,55.2148132324],"type":"Point"}
}