{
  "type": "Feature",
  "properties": {
    "addr:full":"1698 Rue Des Pins Dolbeau-Mistassini QC G8L 1M8",
    "addr:housenumber":"1698",
    "addr:postcode":"g8l 1m8",
    "addr:street":"Rue Des Pins",
    "iso:country":"CA",
    "sg:address":"1698 Rue Des Pins",
    "sg:city":"Dolbeau-Mistassini",
    "sg:classifiers":[
        {
            "category":"Travel",
            "subcategory":"Hotels & Motels",
            "type":"Entertainment"
        }
    ],
    "sg:phone":"+1 418 276 3792",
    "sg:postcode":"G8L 1M8",
    "sg:province":"QC",
    "wof:name":"Motel Dolbeau",
    "wof:placetype":"venue"
},
  "geometry": {"coordinates":[-72.23246,48.880547],"type":"Point"}
}