{
  "type": "Feature",
  "properties": {
    "addr:full":"2124 154 St Surrey BC V4A 4S3",
    "addr:housenumber":"2124",
    "addr:postcode":"v4a 4s3",
    "addr:street":"154 St",
    "iso:country":"CA",
    "sg:address":"2124 154 St",
    "sg:city":"Surrey",
    "sg:classifiers":[
        {
            "category":"Social Services",
            "subcategory":"Child Care",
            "type":"Services"
        }
    ],
    "sg:phone":"+1 604 541 8433",
    "sg:postcode":"V4A 4S3",
    "sg:province":"BC",
    "wof:name":"Peninsula Child Care Ctr",
    "wof:placetype":"venue"
},
  "geometry": {"coordinates":[-122.79541,49.040569],"type":"Point"}
}