{
  "type": "Feature",
  "properties": {
    "addr:full":"53 Advance Rd Etobicoke ON M8Z 2S6",
    "addr:housenumber":"53",
    "addr:postcode":"m8z 2s6",
    "addr:street":"Advance Rd",
    "iso:country":"CA",
    "sg:address":"53 Advance Rd",
    "sg:city":"Etobicoke",
    "sg:classifiers":[
        {
            "category":"Building & Trades",
            "subcategory":"Construction",
            "type":"Services"
        }
    ],
    "sg:phone":"+1 416 233 4457",
    "sg:postcode":"M8Z 2S6",
    "sg:province":"ON",
    "sg:tags":[
        "carpenter"
    ],
    "wof:name":"Buildon Enterprises Ltd",
    "wof:placetype":"venue"
},
  "geometry": {"coordinates":[-79.5260467529,43.6343154907],"type":"Point"}
}