{
  "type": "Feature",
  "properties": {
    "addr:full":"560 Rue Judd Saint-Eustache QC J7R 4N8",
    "addr:housenumber":"560",
    "addr:postcode":"j7r 4n8",
    "addr:street":"Rue Judd",
    "iso:country":"CA",
    "sg:address":"560 Rue Judd",
    "sg:city":"Saint-Eustache",
    "sg:classifiers":[
        {
            "category":"Building & Trades",
            "subcategory":"Construction",
            "type":"Services"
        }
    ],
    "sg:phone":"+1 450 472 1938",
    "sg:postcode":"J7R 4N8",
    "sg:province":"QC",
    "sg:tags":[
        "masonry",
        "contractor"
    ],
    "wof:name":"Maconnerie At Inc",
    "wof:placetype":"venue"
},
  "geometry": {"coordinates":[-73.906631,45.554897],"type":"Point"}
}