{
  "type": "Feature",
  "properties": {
    "addr:full":"39 Norwood Terr Toronto ON M4E 2H2",
    "addr:housenumber":"39",
    "addr:postcode":"m4e 2h2",
    "addr:street":"Norwood Terr",
    "iso:country":"CA",
    "sg:address":"39 Norwood Terr",
    "sg:city":"Toronto",
    "sg:classifiers":[
        {
            "category":"Retail",
            "subcategory":"Portrait Studio",
            "type":"Services"
        }
    ],
    "sg:phone":"+1 416 698 5310",
    "sg:postcode":"M4E 2H2",
    "sg:province":"ON",
    "sg:tags":[
        "photographer"
    ],
    "wof:name":"Frozen Images Photography",
    "wof:placetype":"venue"
},
  "geometry": {"coordinates":[-79.301399231,43.6849403381],"type":"Point"}
}