{
  "type": "Feature",
  "properties": {
    "addr:full":"75 Mississaga St E Orillia ON L3V 1V4",
    "addr:housenumber":"75",
    "addr:postcode":"l3v 1v4",
    "addr:street":"Mississaga St E",
    "iso:country":"CA",
    "sg:address":"75 Mississaga St E",
    "sg:city":"Orillia",
    "sg:classifiers":[
        {
            "category":"Shopping",
            "subcategory":"Clothing, Apparel, & Fashions",
            "type":"Retail Goods"
        }
    ],
    "sg:phone":"+1 705 327 1595",
    "sg:postcode":"L3V 1V4",
    "sg:province":"ON",
    "wof:name":"Kelly's Klothing",
    "wof:placetype":"venue"
},
  "geometry": {"coordinates":[-79.4178771973,44.6088790894],"type":"Point"}
}