{
  "type": "Feature",
  "properties": {
    "addr:full":"42 Lakeshore Dr North Bay ON P1A 2A3",
    "addr:housenumber":"42",
    "addr:postcode":"p1a 2a3",
    "addr:street":"Lakeshore Dr",
    "iso:country":"CA",
    "sg:address":"42 Lakeshore Dr",
    "sg:city":"North Bay",
    "sg:classifiers":[
        {
            "category":"Autos & Motor Vehicles",
            "subcategory":"Automobile Sales",
            "type":"Retail Goods"
        }
    ],
    "sg:phone":"+1 705 840 2886",
    "sg:postcode":"P1A 2A3",
    "sg:province":"ON",
    "sg:tags":[
        "car",
        "dealer"
    ],
    "wof:name":"Thomson Auto Sales",
    "wof:placetype":"venue"
},
  "geometry": {"coordinates":[-79.4544372559,46.2947616577],"type":"Point"}
}