{
  "type": "Feature",
  "properties": {
    "addr:full":"251 Osilinka St Mackenzie BC V0J 2C0",
    "addr:housenumber":"251",
    "addr:postcode":"v0j 2c0",
    "addr:street":"Osilinka St",
    "iso:country":"CA",
    "sg:address":"251 Osilinka St",
    "sg:city":"Mackenzie",
    "sg:classifiers":[
        {
            "category":"Building & Trades",
            "subcategory":"Electrical",
            "type":"Services"
        }
    ],
    "sg:phone":"+1 250 997 3559",
    "sg:postcode":"V0J 2C0",
    "sg:province":"BC",
    "sg:tags":[
        "electric",
        "contractor"
    ],
    "wof:name":"T R Electric Ltd",
    "wof:placetype":"venue"
},
  "geometry": {"coordinates":[-123.096115,55.334969],"type":"Point"}
}