{
  "type": "Feature",
  "properties": {
    "iso:country":"CA",
    "sg:address":"6801 Aut Transcanadienne",
    "sg:city":"Pointe-Claire",
    "sg:classifiers":[
        {
            "category":"Shopping",
            "subcategory":"Shoes",
            "type":"Retail Goods"
        }
    ],
    "sg:phone":"+1 514 695 4104",
    "sg:postcode":"H9R 5J2",
    "sg:province":"QC",
    "wof:name":"Chaussures Aldo Inc",
    "wof:placetype":"venue"
},
  "geometry": {"coordinates":[-73.838219,45.457832],"type":"Point"}
}