{
  "type": "Feature",
  "properties": {
    "addr:full":"Edmonton AB T5T 4M2",
    "addr:postcode":"t5t 4m2",
    "iso:country":"CA",
    "sg:city":"Edmonton",
    "sg:classifiers":[
        {
            "category":"Shopping",
            "type":"Retail Goods"
        }
    ],
    "sg:phone":"+1 780 444 7387",
    "sg:postcode":"T5T 4M2",
    "sg:province":"AB",
    "sg:tags":[
        "pet",
        "shop"
    ],
    "wof:name":"P J's Pet Ctr",
    "wof:placetype":"venue"
},
  "geometry": {"coordinates":[-113.615600586,53.5235862732],"type":"Point"}
}