{
  "type": "Feature",
  "properties": {
    "iso:country":"CA",
    "sg:address":"60 Crowfoot Terr NW",
    "sg:city":"Calgary",
    "sg:classifiers":[
        {
            "category":"Shopping",
            "subcategory":"Computers & Home Electronics",
            "type":"Retail Goods"
        }
    ],
    "sg:phone":"+1 403 212 0008",
    "sg:postcode":"T3G 4J8",
    "sg:province":"AB",
    "sg:tags":[
        "equipment",
        "dealer",
        "software"
    ],
    "wof:name":"Compu Smart",
    "wof:placetype":"venue"
},
  "geometry": {"coordinates":[-114.20032501199999,51.1273765564],"type":"Point"}
}