{
  "type": "Feature",
  "properties": {
    "iso:country":"CA",
    "sg:address":"962980 Rd 96",
    "sg:city":"Lakeside",
    "sg:classifiers":[
        {
            "category":"Retail",
            "subcategory":"Repair Shop",
            "type":"Services"
        }
    ],
    "sg:phone":"+1 519 349 2307",
    "sg:postcode":"N0M 2G0",
    "sg:province":"ON",
    "sg:tags":[
        "taxidermist"
    ],
    "wof:name":"George Whittaker Taxidermist",
    "wof:placetype":"venue"
},
  "geometry": {"coordinates":[-81.024520874,43.2020874023],"type":"Point"}
}