{
  "type": "Feature",
  "properties": {
    "addr:full":"3801 8 St SW Calgary AB T2T 3B1",
    "addr:housenumber":"3801 8",
    "addr:postcode":"t2t 3b1",
    "addr:street":"St Sw",
    "iso:country":"CA",
    "sg:address":"3801 8 St SW",
    "sg:city":"Calgary",
    "sg:classifiers":[
        {
            "category":"Mining & Drilling",
            "type":"Manufacturing & Wholesale Goods"
        }
    ],
    "sg:phone":"+1 403 243 5754",
    "sg:postcode":"T2T 3B1",
    "sg:province":"AB",
    "sg:tags":[
        "field",
        "oil",
        "well"
    ],
    "wof:name":"Pi Resource Consultants Ltd",
    "wof:placetype":"venue"
},
  "geometry": {"coordinates":[-114.083878,51.020874],"type":"Point"}
}