{
  "type": "Feature",
  "properties": {
    "iso:country":"CA",
    "sg:address":"76803 Morrison Line",
    "sg:city":"Clinton",
    "sg:classifiers":[
        {
            "category":"Home & Garden",
            "subcategory":"Garden Supply",
            "type":"Retail Goods"
        }
    ],
    "sg:phone":"+1 519 233 3333",
    "sg:postcode":"N0M 1L0",
    "sg:province":"ON",
    "sg:tags":[
        "engine",
        "lawn",
        "mower"
    ],
    "wof:name":"K & J Small Engines",
    "wof:placetype":"venue"
},
  "geometry": {"coordinates":[-81.53969573969999,43.6176681519],"type":"Point"}
}