{
  "type": "Feature",
  "properties": {
    "iso:country":"CA",
    "sg:city":"Fort Mcmurray",
    "sg:classifiers":[
        {
            "category":"Shopping",
            "subcategory":"Florist",
            "type":"Retail Goods"
        }
    ],
    "sg:phone":"+1 780 743 3878",
    "sg:postcode":"T9H 3E1",
    "sg:province":"AB",
    "sg:tags":[
        "shop",
        "gift"
    ],
    "wof:name":"Chocolates & Candlelight",
    "wof:placetype":"venue"
},
  "geometry": {"coordinates":[-111.36273956300001,56.7238540649],"type":"Point"}
}