{
  "type": "Feature",
  "properties": {
    "addr:full":"Sioux Lookout ON P8T 1J8",
    "addr:postcode":"p8t 1j8",
    "iso:country":"CA",
    "sg:city":"Sioux Lookout",
    "sg:classifiers":[
        {
            "category":"Wholesale",
            "subcategory":"Office Equipment",
            "type":"Manufacturing & Wholesale Goods"
        }
    ],
    "sg:phone":"+1 807 737 4223",
    "sg:postcode":"P8T 1J8",
    "sg:province":"ON",
    "sg:tags":[
        "accounting",
        "bookkeeping",
        "system"
    ],
    "wof:name":"G R Daignault Accounting Svc",
    "wof:placetype":"venue"
},
  "geometry": {"coordinates":[-91.9150314331,50.0980911255],"type":"Point"}
}