{
  "type": "Feature",
  "properties": {
    "iso:country":"CA",
    "sg:address":"422 Dunlop St W",
    "sg:city":"Barrie",
    "sg:classifiers":[
        {
            "category":"Autos & Motor Vehicles",
            "subcategory":"Auto Supplies",
            "type":"Retail Goods"
        }
    ],
    "sg:phone":"+1 705 735 1274",
    "sg:postcode":"L4N 1C2",
    "sg:province":"ON",
    "sg:tags":[
        "automobile",
        "parts",
        "racing",
        "car",
        "equipment"
    ],
    "wof:name":"Performance Improvements",
    "wof:placetype":"venue"
},
  "geometry": {"coordinates":[-79.717659,44.377281],"type":"Point"}
}