{
  "type": "Feature",
  "properties": {
    "addr:full":"Langley BC V2Y 1K9",
    "addr:postcode":"v2y 1k9",
    "iso:country":"CA",
    "sg:city":"Langley",
    "sg:classifiers":[
        {
            "category":"Shopping",
            "subcategory":"Bicycles & Sporting Goods",
            "type":"Retail Goods"
        }
    ],
    "sg:phone":"+1 604 532 1902",
    "sg:postcode":"V2Y 1K9",
    "sg:province":"BC",
    "sg:tags":[
        "equipment",
        "snowboard",
        "skateboard"
    ],
    "wof:name":"Fluid Sports",
    "wof:placetype":"venue"
},
  "geometry": {"coordinates":[-122.670143,49.116631],"type":"Point"}
}