{
  "type": "Feature",
  "properties": {
    "addr:full":"195 Healey Rd Bolton ON L7E 5B2",
    "addr:housenumber":"195",
    "addr:postcode":"l7e 5b2",
    "addr:street":"Healey Rd",
    "iso:country":"CA",
    "sg:address":"195 Healey Rd",
    "sg:city":"Bolton",
    "sg:classifiers":[
        {
            "category":"Manufacturing",
            "subcategory":"Tools & Machinery",
            "type":"Manufacturing & Wholesale Goods"
        }
    ],
    "sg:phone":"+1 905 857 4700",
    "sg:postcode":"L7E 5B2",
    "sg:province":"ON",
    "sg:tags":[
        "ventilating",
        "equipment"
    ],
    "wof:name":"Ventex Inc",
    "wof:placetype":"venue"
},
  "geometry": {"coordinates":[-79.7269363403,43.8635559082],"type":"Point"}
}