{
  "type": "Feature",
  "properties": {
    "addr:full":"32 Rue Deslandes Canton-DE-Granby QC J2G 9J1",
    "addr:housenumber":"32",
    "addr:postcode":"j2g 9j1",
    "addr:street":"Rue Deslandes Canton-De-Granby",
    "iso:country":"CA",
    "sg:address":"32 Rue Deslandes",
    "sg:city":"Canton-DE-Granby",
    "sg:classifiers":[
        {
            "category":"Wholesale",
            "subcategory":"Electrical",
            "type":"Manufacturing & Wholesale Goods"
        }
    ],
    "sg:phone":"+1 450 375 9200",
    "sg:postcode":"J2G 9J1",
    "sg:province":"QC",
    "sg:tags":[
        "communication",
        "radio",
        "system"
    ],
    "wof:name":"Communication 2000 Enr",
    "wof:placetype":"venue"
},
  "geometry": {"coordinates":[-72.7197341919,45.4373016357],"type":"Point"}
}