{
  "type": "Feature",
  "properties": {
    "addr:full":"153 Meadowlands Dr W Nepean ON K2G 2S3",
    "addr:housenumber":"153",
    "addr:postcode":"k2g 2s3",
    "addr:street":"Meadowlands Dr W",
    "iso:country":"CA",
    "sg:address":"153 Meadowlands Dr W",
    "sg:city":"Nepean",
    "sg:classifiers":[
        {
            "category":"Personal",
            "subcategory":"Beauty Salon",
            "type":"Services"
        }
    ],
    "sg:phone":"+1 613 224 2388",
    "sg:postcode":"K2G 2S3",
    "sg:province":"ON",
    "wof:name":"Katy John Hair Salon",
    "wof:placetype":"venue"
},
  "geometry": {"coordinates":[-75.75400500000001,45.343254],"type":"Point"}
}