{
  "type": "Feature",
  "properties": {
    "addr:full":"Etobicoke ON M9C 2Y3",
    "addr:postcode":"m9c 2y3",
    "iso:country":"CA",
    "sg:city":"Etobicoke",
    "sg:classifiers":[
        {
            "category":"Professional",
            "subcategory":"Accounting & Tax Preparation",
            "type":"Services"
        }
    ],
    "sg:phone":"+1 416 622 7823",
    "sg:postcode":"M9C 2Y3",
    "sg:province":"ON",
    "sg:tags":[
        "accountant"
    ],
    "wof:name":"May & CO",
    "wof:placetype":"venue"
},
  "geometry": {"coordinates":[-79.568321228,43.6444702148],"type":"Point"}
}