{
  "type": "Feature",
  "properties": {
    "iso:country":"CA",
    "sg:city":"Calgary",
    "sg:classifiers":[
        {
            "category":"Organizations",
            "subcategory":"Professional Association",
            "type":"Services"
        }
    ],
    "sg:phone":"+1 403 253 3454",
    "sg:postcode":"T2H 0X4",
    "sg:province":"AB",
    "wof:name":"Calgary Society of Community",
    "wof:placetype":"venue"
},
  "geometry": {"coordinates":[-114.063537598,50.989616394],"type":"Point"}
}