{
  "type": "Feature",
  "properties": {
    "addr:full":"15831 Stony Plain Rd NW Edmonton AB T5P 3Z7",
    "addr:housenumber":"15831",
    "addr:postcode":"t5p 3z7",
    "addr:street":"Stony Plain Rd Nw",
    "iso:country":"CA",
    "sg:address":"15831 Stony Plain Rd NW",
    "sg:city":"Edmonton",
    "sg:classifiers":[
        {
            "category":"Retail",
            "subcategory":"Auto Repair",
            "type":"Services"
        }
    ],
    "sg:phone":"+1 780 483 7037",
    "sg:postcode":"T5P 3Z7",
    "sg:province":"AB",
    "sg:tags":[
        "transmission"
    ],
    "wof:name":"Aamco Transmissions",
    "wof:placetype":"venue"
},
  "geometry": {"coordinates":[-113.594444,53.541161],"type":"Point"}
}