{
  "type": "Feature",
  "properties": {
    "addr:full":"1792 Rue Duchesne Val-D'Or QC J9P 2T2",
    "addr:housenumber":"1792",
    "addr:postcode":"j9p 2t2",
    "addr:street":"Rue Duchesne",
    "iso:country":"CA",
    "sg:address":"1792 Rue Duchesne",
    "sg:city":"Val-D'Or",
    "sg:classifiers":[
        {
            "category":"Professional",
            "subcategory":"Business Services",
            "type":"Services"
        }
    ],
    "sg:phone":"+1 819 824 4045",
    "sg:postcode":"J9P 2T2",
    "sg:province":"QC",
    "sg:tags":[
        "water",
        "pump",
        "treatment"
    ],
    "wof:name":"Pompes & Eau Rene Rochefort",
    "wof:placetype":"venue"
},
  "geometry": {"coordinates":[-71.003319,45.383507],"type":"Point"}
}