{
  "type": "Feature",
  "properties": {
    "addr:full":"135 117 Rte Sainte-Anne-Des-Lacs QC J0R 1B0",
    "addr:housenumber":"117",
    "addr:postcode":"j0r 1b0",
    "addr:street":"Rte Sainte-Anne-Des-Lacs",
    "iso:country":"CA",
    "sg:address":"135 117 Rte",
    "sg:city":"Sainte-Anne-Des-Lacs",
    "sg:classifiers":[
        {
            "category":"Home & Garden",
            "subcategory":"Building Materials",
            "type":"Retail Goods"
        }
    ],
    "sg:phone":"+1 450 227 4407",
    "sg:postcode":"J0R 1B0",
    "sg:province":"QC",
    "sg:tags":[
        "lumber"
    ],
    "wof:name":"Bois D'Ebenisterie Boyer Inc",
    "wof:placetype":"venue"
},
  "geometry": {"coordinates":[-74.12757873539999,45.8598480225],"type":"Point"}
}