{
  "type": "Feature",
  "properties": {
    "addr:full":"151 Lincoln St Lunenburg NS B0J 2C0",
    "addr:housenumber":"151",
    "addr:postcode":"b0j 2c0",
    "addr:street":"Lincoln St",
    "iso:country":"CA",
    "sg:address":"151 Lincoln St",
    "sg:city":"Lunenburg",
    "sg:classifiers":[
        {
            "category":"Shopping",
            "subcategory":"Optical Goods",
            "type":"Retail Goods"
        }
    ],
    "sg:phone":"+1 902 634 4911",
    "sg:postcode":"B0J 2C0",
    "sg:province":"NS",
    "sg:tags":[
        "optician"
    ],
    "wof:name":"South Shore Optical",
    "wof:placetype":"venue"
},
  "geometry": {"coordinates":[-64.3128128052,44.3777236938],"type":"Point"}
}