{
  "type": "Feature",
  "properties": {
    "addr:full":"461 Phillip Murray Ave Oshawa ON L1J 1H6",
    "addr:housenumber":"461",
    "addr:postcode":"l1j 1h6",
    "addr:street":"Phillip Murray Ave",
    "iso:country":"CA",
    "sg:address":"461 Phillip Murray Ave",
    "sg:city":"Oshawa",
    "sg:classifiers":[
        {
            "category":"Organizations",
            "subcategory":"Religious Organization",
            "type":"Services"
        }
    ],
    "sg:phone":"+1 905 432 7204",
    "sg:postcode":"L1J 1H6",
    "sg:province":"ON",
    "sg:tags":[
        "church"
    ],
    "wof:name":"Emmanuel Baptist Church",
    "wof:placetype":"venue"
},
  "geometry": {"coordinates":[-78.848732,43.860725],"type":"Point"}
}