{
  "type": "Feature",
  "properties": {
    "addr:full":"1795 14E Av Shawinigan-Sud QC G9P 2C5",
    "addr:housenumber":"1795",
    "addr:postcode":"g9p 2c5",
    "addr:street":"14E Av Shawinigan-Sud",
    "iso:country":"CA",
    "sg:address":"1795 14E Av",
    "sg:city":"Shawinigan-Sud",
    "sg:classifiers":[
        {
            "category":"Organizations",
            "subcategory":"Religious Organization",
            "type":"Services"
        }
    ],
    "sg:phone":"+1 819 537 6556",
    "sg:postcode":"G9P 2C5",
    "sg:province":"QC",
    "sg:tags":[
        "church"
    ],
    "wof:name":"Presbytere St-Andre",
    "wof:placetype":"venue"
},
  "geometry": {"coordinates":[-72.75346399999999,46.517822],"type":"Point"}
}