{
  "type": "Feature",
  "properties": {
    "addr:full":"3679 Boul Taschereau Saint-Hubert QC J4T 2G3",
    "addr:housenumber":"3679",
    "addr:postcode":"j4t 2g3",
    "addr:street":"Boul Taschereau",
    "iso:country":"CA",
    "sg:address":"3679 Boul Taschereau",
    "sg:city":"Saint-Hubert",
    "sg:classifiers":[
        {
            "category":"Home & Garden",
            "subcategory":"Building Materials",
            "type":"Retail Goods"
        }
    ],
    "sg:phone":"+1 450 926 9606",
    "sg:postcode":"J4T 2G3",
    "sg:province":"QC",
    "sg:tags":[
        "glass",
        "window",
        "plate"
    ],
    "wof:name":"Vitrerie Centrale",
    "wof:placetype":"venue"
},
  "geometry": {"coordinates":[-73.47286200000001,45.489502],"type":"Point"}
}