{
  "type": "Feature",
  "properties": {
    "addr:full":"1133 Hastings St W Vancouver BC V6E 3T3",
    "addr:housenumber":"1133",
    "addr:postcode":"v6e 3t3",
    "addr:street":"Hastings St W",
    "iso:country":"CA",
    "sg:address":"1133 Hastings St W",
    "sg:city":"Vancouver",
    "sg:classifiers":[
        {
            "category":"Travel",
            "subcategory":"Hotels & Motels",
            "type":"Entertainment"
        }
    ],
    "sg:phone":"+1 604 689 9211",
    "sg:postcode":"V6E 3T3",
    "sg:province":"BC",
    "sg:tags":[
        "caterer"
    ],
    "wof:name":"Vancouver Renaissance Hotel",
    "wof:placetype":"venue"
},
  "geometry": {"coordinates":[-123.12071991000001,49.2883834839],"type":"Point"}
}