{
  "type": "Feature",
  "properties": {
    "iso:country":"CA",
    "sg:city":"Calgary",
    "sg:classifiers":[
        {
            "category":"Freight",
            "type":"Transportation"
        }
    ],
    "sg:phone":"+1 403 216 5500",
    "sg:postcode":"T2H 2J7",
    "sg:province":"AB",
    "sg:tags":[
        "trucking"
    ],
    "wof:name":"Titan Transport Ltd",
    "wof:placetype":"venue"
},
  "geometry": {"coordinates":[-114.037933,50.995171],"type":"Point"}
}