{
  "type": "Feature",
  "properties": {
    "iso:country":"CA",
    "sg:city":"Falmouth",
    "sg:classifiers":[
        {
            "category":"Retail",
            "subcategory":"Auto Repair",
            "type":"Services"
        }
    ],
    "sg:phone":"+1 902 798 8080",
    "sg:postcode":"B0P 1L0",
    "sg:province":"NS",
    "sg:tags":[
        "repairing",
        "automobile"
    ],
    "wof:name":"Greg Frank Auto Repair",
    "wof:placetype":"venue"
},
  "geometry": {"coordinates":[-64.155166626,44.9964904785],"type":"Point"}
}