{
  "type": "Feature",
  "properties": {
    "addr:full":"409 Boul Maloney O Gatineau QC J8P 3W1",
    "addr:housenumber":"409",
    "addr:postcode":"j8p 3w1",
    "addr:street":"Boul Maloney O",
    "iso:country":"CA",
    "sg:address":"409 Boul Maloney O",
    "sg:city":"Gatineau",
    "sg:classifiers":[
        {
            "category":"Wholesale",
            "subcategory":"Auto Parts",
            "type":"Manufacturing & Wholesale Goods"
        }
    ],
    "sg:phone":"+1 819 663 9273",
    "sg:postcode":"J8P 3W1",
    "sg:province":"QC",
    "sg:tags":[
        "body",
        "automobile",
        "shop",
        "supply"
    ],
    "wof:name":"Lacroix Pieces D'Auto",
    "wof:placetype":"venue"
},
  "geometry": {"coordinates":[-75.639473,45.484882],"type":"Point"}
}