{
  "type": "Feature",
  "properties": {
    "addr:full":"76 Lake St St Catharines ON L2R 5X4",
    "addr:housenumber":"76",
    "addr:postcode":"l2r 5x4",
    "addr:street":"Lake St",
    "iso:country":"CA",
    "sg:address":"76 Lake St",
    "sg:city":"St Catharines",
    "sg:classifiers":[
        {
            "category":"Travel",
            "subcategory":"Travel Agent",
            "type":"Entertainment"
        }
    ],
    "sg:phone":"+1 905 688 0321",
    "sg:postcode":"L2R 5X4",
    "sg:province":"ON",
    "sg:tags":[
        "agency",
        "bureau"
    ],
    "wof:name":"Caa Niagara",
    "wof:placetype":"venue"
},
  "geometry": {"coordinates":[-79.25049591059999,43.1620101929],"type":"Point"}
}