{
  "type": "Feature",
  "properties": {
    "addr:full":"Richmond BC V6X 2R2",
    "addr:postcode":"v6x 2r2",
    "iso:country":"CA",
    "sg:city":"Richmond",
    "sg:classifiers":[
        {
            "category":"Manufacturing",
            "subcategory":"Pottery",
            "type":"Manufacturing & Wholesale Goods"
        }
    ],
    "sg:phone":"+1 604 270 1661",
    "sg:postcode":"V6X 2R2",
    "sg:province":"BC",
    "wof:name":"Pacific Stoneware Ltd",
    "wof:placetype":"venue"
},
  "geometry": {"coordinates":[-123.099174,49.193195],"type":"Point"}
}