{
  "type": "Feature",
  "properties": {
    "addr:full":"1270 Trans Canada Way SE Medicine Hat AB T1B 1J5",
    "addr:housenumber":"1270",
    "addr:postcode":"t1b 1j5",
    "addr:street":"Trans Canada Way Se",
    "iso:country":"CA",
    "sg:address":"1270 Trans Canada Way SE",
    "sg:city":"Medicine Hat",
    "sg:classifiers":[
        {
            "category":"Autos & Motor Vehicles",
            "subcategory":"Automobile Sales",
            "type":"Retail Goods"
        }
    ],
    "sg:phone":"+1 403 527 1141",
    "sg:postcode":"T1B 1J5",
    "sg:province":"AB",
    "sg:tags":[
        "car",
        "dealer"
    ],
    "wof:name":"Murray Chevrolet Geo Olds Cad",
    "wof:placetype":"venue"
},
  "geometry": {"coordinates":[-110.65709686300001,50.0042152405],"type":"Point"}
}