{
  "type": "Feature",
  "properties": {
    "iso:country":"CA",
    "sg:address":"10 Union St W",
    "sg:city":"Kingston",
    "sg:classifiers":[
        {
            "category":"Organizations",
            "subcategory":"Religious Organization",
            "type":"Services"
        }
    ],
    "sg:phone":"+1 613 548 7254",
    "sg:postcode":"K7L 2N7",
    "sg:province":"ON",
    "sg:tags":[
        "church"
    ],
    "wof:name":"St James Church",
    "wof:placetype":"venue"
},
  "geometry": {"coordinates":[-76.491699,44.227516],"type":"Point"}
}