{
  "type": "Feature",
  "properties": {
    "addr:full":"380 Cumberland St Ottawa ON K1N 9P3",
    "addr:housenumber":"380",
    "addr:postcode":"k1n 9p3",
    "addr:street":"Cumberland St",
    "iso:country":"CA",
    "sg:address":"380 Cumberland St",
    "sg:city":"Ottawa",
    "sg:classifiers":[
        {
            "category":"Social Services",
            "type":"Services"
        }
    ],
    "sg:phone":"+1 613 241 6363",
    "sg:postcode":"K1N 9P3",
    "sg:province":"ON",
    "sg:tags":[
        "organization",
        "welfare"
    ],
    "wof:name":"Options Bytown Non Profit Hsng",
    "wof:placetype":"venue"
},
  "geometry": {"coordinates":[-75.688683,45.429043],"type":"Point"}
}