{
  "type": "Feature",
  "properties": {
    "addr:full":"606 Hot Springs Rd Harrison Hot Springs BC V0M 1K0",
    "addr:housenumber":"606",
    "addr:postcode":"v0m 1k0",
    "addr:street":"Hot Springs Rd",
    "iso:country":"CA",
    "sg:address":"606 Hot Springs Rd",
    "sg:city":"Harrison Hot Springs",
    "sg:classifiers":[
        {
            "category":"Real Estate",
            "subcategory":"Real Estate Operator",
            "type":"Services"
        }
    ],
    "sg:phone":"+1 604 796 9417",
    "sg:postcode":"V0M 1K0",
    "sg:province":"BC",
    "sg:tags":[
        "mobile",
        "home",
        "community"
    ],
    "wof:name":"Rainbows End Camping Resort",
    "wof:placetype":"venue"
},
  "geometry": {"coordinates":[-121.78398900000001,49.295254],"type":"Point"}
}