{
  "type": "Feature",
  "properties": {
    "addr:full":"Atims St Moosonee ON P0L 1Y0",
    "addr:postcode":"p0l 1y0",
    "iso:country":"CA",
    "sg:address":"Atims St",
    "sg:city":"Moosonee",
    "sg:classifiers":[
        {
            "category":"Health Services",
            "subcategory":"Doctor",
            "type":"Services"
        }
    ],
    "sg:phone":"+1 705 336 2341",
    "sg:postcode":"P0L 1Y0",
    "sg:province":"ON",
    "sg:tags":[
        "clinic"
    ],
    "wof:name":"Moosonee Health Clinic",
    "wof:placetype":"venue"
},
  "geometry": {"coordinates":[-80.64669799799999,51.274684906],"type":"Point"}
}