{
  "type": "Feature",
  "properties": {
    "addr:full":"9722 27 Ave NW Edmonton AB T6N 1B2",
    "addr:housenumber":"9722",
    "addr:postcode":"t6n 1b2",
    "addr:street":"27 Ave Nw",
    "iso:country":"CA",
    "sg:address":"9722 27 Ave NW",
    "sg:city":"Edmonton",
    "sg:classifiers":[
        {
            "category":"Manufacturing",
            "subcategory":"Tools & Machinery",
            "type":"Manufacturing & Wholesale Goods"
        }
    ],
    "sg:phone":"+1 780 414 6062",
    "sg:postcode":"T6N 1B2",
    "sg:province":"AB",
    "sg:tags":[
        "equipment",
        "plating",
        "supply"
    ],
    "wof:name":"Canadian Superior Plating Inc",
    "wof:placetype":"venue"
},
  "geometry": {"coordinates":[-113.478081,53.457039],"type":"Point"}
}