{
  "type": "Feature",
  "properties": {
    "addr:full":"215 Donald Rd Williams Lake BC V2G 4K4",
    "addr:housenumber":"215",
    "addr:postcode":"v2g 4k4",
    "addr:street":"Donald Rd",
    "iso:country":"CA",
    "sg:address":"215 Donald Rd",
    "sg:city":"Williams Lake",
    "sg:classifiers":[
        {
            "category":"Restaurant",
            "type":"Food & Drink"
        }
    ],
    "sg:phone":"+1 250 398 8334",
    "sg:postcode":"V2G 4K4",
    "sg:province":"BC",
    "wof:name":"Eddy's Restaurant",
    "wof:placetype":"venue"
},
  "geometry": {"coordinates":[-122.134300232,52.1345825195],"type":"Point"}
}