{
  "type": "Feature",
  "properties": {
    "addr:full":"150 Rue Saint-Pierre S Joliette QC J6E 5Y7",
    "addr:housenumber":"150",
    "addr:postcode":"j6e 5y7",
    "addr:street":"Rue Saint-Pierre S",
    "iso:country":"CA",
    "sg:address":"150 Rue Saint-Pierre S",
    "sg:city":"Joliette",
    "sg:classifiers":[
        {
            "category":"Home & Garden",
            "subcategory":"Household Appliances",
            "type":"Retail Goods"
        }
    ],
    "sg:phone":"+1 450 759 3091",
    "sg:postcode":"J6E 5Y7",
    "sg:province":"QC",
    "sg:tags":[
        "television",
        "radio"
    ],
    "wof:name":"B G Electronique",
    "wof:placetype":"venue"
},
  "geometry": {"coordinates":[-73.44491600000001,46.018578],"type":"Point"}
}