{
  "type": "Feature",
  "properties": {
    "addr:full":"24 Leo St S Azilda ON P0M 1B0",
    "addr:housenumber":"24",
    "addr:postcode":"p0m 1b0",
    "addr:street":"Leo St S",
    "iso:country":"CA",
    "sg:address":"24 Leo St S",
    "sg:city":"Azilda",
    "sg:classifiers":[
        {
            "category":"Home & Garden",
            "subcategory":"Home Furnishings",
            "type":"Retail Goods"
        }
    ],
    "sg:phone":"+1 705 983 2009",
    "sg:postcode":"P0M 1B0",
    "sg:province":"ON",
    "sg:tags":[
        "venetian",
        "blind"
    ],
    "wof:name":"Blinds Unlimited",
    "wof:placetype":"venue"
},
  "geometry": {"coordinates":[-81.1224822998,46.5508155823],"type":"Point"}
}