{
  "type": "Feature",
  "properties": {
    "addr:full":"13470 66A Ave Surrey BC V3W 6M3",
    "addr:housenumber":"13470",
    "addr:postcode":"v3w 6m3",
    "addr:street":"66A Ave",
    "iso:country":"CA",
    "sg:address":"13470 66A Ave",
    "sg:city":"Surrey",
    "sg:classifiers":[
        {
            "category":"Social Services",
            "subcategory":"Child Care",
            "type":"Services"
        }
    ],
    "sg:phone":"+1 604 591 7481",
    "sg:postcode":"V3W 6M3",
    "sg:province":"BC",
    "wof:name":"Child's World Nursery School",
    "wof:placetype":"venue"
},
  "geometry": {"coordinates":[-122.830215454,49.105178833],"type":"Point"}
}