{
  "type": "Feature",
  "properties": {
    "addr:full":"10616 87 Ave Fort St John BC V1J 5K7",
    "addr:housenumber":"10616",
    "addr:postcode":"v1j 5k7",
    "addr:street":"87 Ave",
    "iso:country":"CA",
    "sg:address":"10616 87 Ave",
    "sg:city":"Fort St John",
    "sg:classifiers":[
        {
            "category":"Home & Garden",
            "subcategory":"Building Materials",
            "type":"Retail Goods"
        }
    ],
    "sg:phone":"+1 250 787 0674",
    "sg:postcode":"V1J 5K7",
    "sg:province":"BC",
    "sg:tags":[
        "mixed",
        "concrete"
    ],
    "wof:name":"Inland Concrete Ltd",
    "wof:placetype":"venue"
},
  "geometry": {"coordinates":[-120.857376,56.233646],"type":"Point"}
}