{
  "type": "Feature",
  "properties": {
    "addr:full":"2029 28 St SW Calgary AB T3E 2H3",
    "addr:housenumber":"2029",
    "addr:postcode":"t3e 2h3",
    "addr:street":"28 St Sw",
    "iso:country":"CA",
    "sg:address":"2029 28 St SW",
    "sg:city":"Calgary",
    "sg:classifiers":[
        {
            "category":"Building & Trades",
            "subcategory":"Construction",
            "type":"Services"
        }
    ],
    "sg:phone":"+1 403 246 2629",
    "sg:postcode":"T3E 2H3",
    "sg:province":"AB",
    "sg:tags":[
        "builder",
        "deck"
    ],
    "wof:name":"Decks By Design",
    "wof:placetype":"venue"
},
  "geometry": {"coordinates":[-114.12832641599999,51.0359230042],"type":"Point"}
}