{
  "type": "Feature",
  "properties": {
    "iso:country":"CA",
    "sg:address":"East Basin",
    "sg:city":"Port Dover",
    "sg:classifiers":[
        {
            "category":"Government",
            "subcategory":"Office",
            "type":"Public Place"
        }
    ],
    "sg:phone":"+1 519 583 1581",
    "sg:postcode":"N0A 1N0",
    "sg:province":"ON",
    "wof:name":"Port Dover Harbour Marina",
    "wof:placetype":"venue"
},
  "geometry": {"coordinates":[-80.2011642456,42.7849845886],"type":"Point"}
}