{
  "type": "Feature",
  "properties": {
    "iso:country":"CA",
    "sg:address":"213 Rue DE Woodstock",
    "sg:city":"Saint-Lambert",
    "sg:classifiers":[
        {
            "category":"Health Services",
            "subcategory":"Doctor",
            "type":"Services"
        }
    ],
    "sg:phone":"+1 450 671 5031",
    "sg:postcode":"J4P 1W7",
    "sg:province":"QC",
    "sg:tags":[
        "dentist"
    ],
    "wof:name":"Clinique Dentaire Familiale",
    "wof:placetype":"venue"
},
  "geometry": {"coordinates":[-73.5098190308,45.5005378723],"type":"Point"}
}