{
  "type": "Feature",
  "properties": {
    "iso:country":"CA",
    "sg:address":"71 Wingold Ave",
    "sg:city":"North York",
    "sg:classifiers":[
        {
            "category":"Wholesale",
            "subcategory":"Apparel",
            "type":"Manufacturing & Wholesale Goods"
        }
    ],
    "sg:phone":"+1 416 599 0300",
    "sg:postcode":"M6B 1P8",
    "sg:province":"ON",
    "sg:tags":[
        "clothing"
    ],
    "wof:name":"Woolrich Canada",
    "wof:placetype":"venue"
},
  "geometry": {"coordinates":[-79.457291,43.702591],"type":"Point"}
}