{
  "type": "Feature",
  "properties": {
    "iso:country":"CA",
    "sg:address":"5245 Boul Cousineau # 123",
    "sg:city":"Saint-Hubert",
    "sg:classifiers":[
        {
            "category":"Personal",
            "subcategory":"Beauty Salon",
            "type":"Services"
        }
    ],
    "sg:phone":"+1 450 676 7883",
    "sg:postcode":"J3Y 6J8",
    "sg:province":"QC",
    "sg:tags":[
        "manicuring"
    ],
    "wof:name":"Ongles Cartise",
    "wof:placetype":"venue"
},
  "geometry": {"coordinates":[-73.425148,45.501904],"type":"Point"}
}