{
  "type": "Feature",
  "properties": {
    "addr:full":"105 Pinnacle St S Belleville ON K8N 3A3",
    "addr:housenumber":"105",
    "addr:postcode":"k8n 3a3",
    "addr:street":"Pinnacle St S",
    "iso:country":"CA",
    "sg:address":"105 Pinnacle St S",
    "sg:city":"Belleville",
    "sg:classifiers":[
        {
            "category":"Wholesale",
            "subcategory":"Groceries",
            "type":"Manufacturing & Wholesale Goods"
        }
    ],
    "sg:phone":"+1 613 962 2595",
    "sg:postcode":"K8N 3A3",
    "sg:province":"ON",
    "sg:tags":[
        "food",
        "grocer",
        "product"
    ],
    "wof:name":"W T Hawkins Ltd",
    "wof:placetype":"venue"
},
  "geometry": {"coordinates":[-77.38059199999999,44.160206],"type":"Point"}
}