{
  "type": "Feature",
  "properties": {
    "addr:full":"24 Laidlaw St S Cannington ON L0E 1E0",
    "addr:housenumber":"24",
    "addr:postcode":"l0e 1e0",
    "addr:street":"Laidlaw St S",
    "iso:country":"CA",
    "sg:address":"24 Laidlaw St S",
    "sg:city":"Cannington",
    "sg:classifiers":[
        {
            "category":"Organizations",
            "subcategory":"Professional Association",
            "type":"Services"
        }
    ],
    "sg:phone":"+1 705 432 3453",
    "sg:postcode":"L0E 1E0",
    "sg:province":"ON",
    "wof:name":"Cannington Lions Club",
    "wof:placetype":"venue"
},
  "geometry": {"coordinates":[-79.03816999999999,44.349571],"type":"Point"}
}