{
  "type": "Feature",
  "properties": {
    "addr:full":"Vancouver BC V5T 3G4",
    "addr:postcode":"v5t 3g4",
    "iso:country":"CA",
    "sg:city":"Vancouver",
    "sg:classifiers":[
        {
            "category":"Shopping",
            "subcategory":"Photographic Equipment",
            "type":"Retail Goods"
        }
    ],
    "sg:phone":"+1 604 873 1651",
    "sg:postcode":"V5T 3G4",
    "sg:province":"BC",
    "sg:tags":[
        "photo",
        "finishing"
    ],
    "wof:name":"Holiday Photo",
    "wof:placetype":"venue"
},
  "geometry": {"coordinates":[-123.101257,49.258934],"type":"Point"}
}