{
  "type": "Feature",
  "properties": {
    "addr:full":"304 Birch Rd Slave Lake AB T0G 2A0",
    "addr:housenumber":"304",
    "addr:postcode":"t0g 2a0",
    "addr:street":"Birch Rd",
    "iso:country":"CA",
    "sg:address":"304 Birch Rd",
    "sg:city":"Slave Lake",
    "sg:classifiers":[
        {
            "category":"Wholesale",
            "subcategory":"Construction Materials",
            "type":"Manufacturing & Wholesale Goods"
        }
    ],
    "sg:phone":"+1 780 849 5399",
    "sg:postcode":"T0G 2A0",
    "sg:province":"AB",
    "sg:tags":[
        "sand",
        "gravel",
        "trucking"
    ],
    "wof:name":"C Herman Trucking Ltd",
    "wof:placetype":"venue"
},
  "geometry": {"coordinates":[-114.767143249,55.2944564819],"type":"Point"}
}