{
  "type": "Feature",
  "properties": {
    "addr:full":"556 Rue Lafontaine Riviere-Du-Loup QC G5R 3C6",
    "addr:housenumber":"556",
    "addr:postcode":"g5r 3c6",
    "addr:street":"Rue Lafontaine",
    "iso:country":"CA",
    "sg:address":"556 Rue Lafontaine",
    "sg:city":"Riviere-Du-Loup",
    "sg:classifiers":[
        {
            "category":"Restaurant",
            "type":"Food & Drink"
        }
    ],
    "sg:phone":"+1 418 867 4332",
    "sg:postcode":"G5R 3C6",
    "sg:province":"QC",
    "wof:name":"Frais Delices Enr",
    "wof:placetype":"venue"
},
  "geometry": {"coordinates":[-69.529785,47.827106],"type":"Point"}
}