{
  "type": "Feature",
  "properties": {
    "addr:full":"780 Baseline Rd Ottawa ON K2C 3V8",
    "addr:housenumber":"780",
    "addr:postcode":"k2c 3v8",
    "addr:street":"Baseline Rd",
    "iso:country":"CA",
    "sg:address":"780 Baseline Rd",
    "sg:city":"Ottawa",
    "sg:classifiers":[
        {
            "category":"Wholesale",
            "subcategory":"Wine & Distilled Alcoholic Beverages",
            "type":"Manufacturing & Wholesale Goods"
        }
    ],
    "sg:phone":"+1 613 523 0074",
    "sg:postcode":"K2C 3V8",
    "sg:province":"ON",
    "sg:tags":[
        "equipment",
        "brewer",
        "supply"
    ],
    "wof:name":"Brew Bye You",
    "wof:placetype":"venue"
},
  "geometry": {"coordinates":[-75.71877288819999,45.3703155518],"type":"Point"}
}