{
  "type": "Feature",
  "properties": {
    "iso:country":"CA",
    "sg:address":"2601 Matheson Blvd E",
    "sg:city":"Mississauga",
    "sg:classifiers":[
        {
            "category":"Wholesale",
            "subcategory":"Photographic Equipment",
            "type":"Manufacturing & Wholesale Goods"
        }
    ],
    "sg:phone":"+1 905 238 3290",
    "sg:postcode":"L4W 5A8",
    "sg:province":"ON",
    "sg:tags":[
        "supply"
    ],
    "wof:name":"Furama Optics & Trading Inc",
    "wof:placetype":"venue"
},
  "geometry": {"coordinates":[-79.601418,43.659748],"type":"Point"}
}