{
  "type": "Feature",
  "properties": {
    "addr:full":"2720 Queensview Dr # 1118 Ottawa ON K2B 1A5",
    "addr:housenumber":"2720",
    "addr:postcode":"k2b 1a5",
    "addr:street":"Queensview Dr # 1118",
    "iso:country":"CA",
    "sg:address":"2720 Queensview Dr # 1118",
    "sg:city":"Ottawa",
    "sg:classifiers":[
        {
            "category":"Communications",
            "subcategory":"Film & Video Production",
            "type":"Services"
        }
    ],
    "sg:phone":"+1 613 820 0654",
    "sg:postcode":"K2B 1A5",
    "sg:province":"ON",
    "sg:tags":[
        "consultant",
        "audio"
    ],
    "wof:name":"Global Exhibit Technology",
    "wof:placetype":"venue"
},
  "geometry": {"coordinates":[-75.788132,45.352467],"type":"Point"}
}