{
  "type": "Feature",
  "properties": {
    "addr:full":"178 Algoma St N Thunder Bay ON P7A 5A1",
    "addr:housenumber":"178",
    "addr:postcode":"p7a 5a1",
    "addr:street":"Algoma St N",
    "iso:country":"CA",
    "sg:address":"178 Algoma St N",
    "sg:city":"Thunder Bay",
    "sg:classifiers":[
        {
            "category":"Shopping",
            "subcategory":"Florist",
            "type":"Retail Goods"
        }
    ],
    "sg:phone":"+1 807 345 4245",
    "sg:postcode":"P7A 5A1",
    "sg:province":"ON",
    "wof:name":"Vaillant Florists",
    "wof:placetype":"venue"
},
  "geometry": {"coordinates":[-89.218711853,48.4423522949],"type":"Point"}
}