{
  "type": "Feature",
  "properties": {
    "addr:full":"Grande-Vallee QC G0E 1K0",
    "addr:postcode":"g0e 1k0",
    "iso:country":"CA",
    "sg:city":"Grande-Vallee",
    "sg:classifiers":[
        {
            "category":"Freight",
            "type":"Transportation"
        }
    ],
    "sg:phone":"+1 418 393 2140",
    "sg:postcode":"G0E 1K0",
    "sg:province":"QC",
    "sg:tags":[
        "trucking"
    ],
    "wof:name":"Bois & Transport M Chicoine",
    "wof:placetype":"venue"
},
  "geometry": {"coordinates":[-65.129417,49.218033],"type":"Point"}
}