{
  "type": "Feature",
  "properties": {
    "addr:full":"331 Green Acres Dr Waterloo ON N2K 1Y9",
    "addr:housenumber":"331",
    "addr:postcode":"n2k 1y9",
    "addr:street":"Green Acres Dr",
    "iso:country":"CA",
    "sg:address":"331 Green Acres Dr",
    "sg:city":"Waterloo",
    "sg:classifiers":[
        {
            "category":"Real Estate",
            "subcategory":"Real Estate Agent",
            "type":"Services"
        }
    ],
    "sg:phone":"+1 519 888 7800",
    "sg:postcode":"N2K 1Y9",
    "sg:province":"ON",
    "wof:name":"John Menyes Real Estate Ltd",
    "wof:placetype":"venue"
},
  "geometry": {"coordinates":[-80.509613,43.501709],"type":"Point"}
}