{
  "type": "Feature",
  "properties": {
    "iso:country":"CA",
    "sg:address":"331 Green Acres Dr",
    "sg:city":"Waterloo",
    "sg:classifiers":[
        {
            "category":"Real Estate",
            "subcategory":"Real Estate Agent",
            "type":"Services"
        }
    ],
    "sg:phone":"+1 519 888 7800",
    "sg:postcode":"N2K 1Y9",
    "sg:province":"ON",
    "wof:name":"John Menyes Real Estate Ltd",
    "wof:placetype":"venue"
},
  "geometry": {"coordinates":[-80.509613,43.501709],"type":"Point"}
}