{
  "type": "Feature",
  "properties": {
    "addr:full":"36 Greenfield Ave North York ON M2N 3C8",
    "addr:housenumber":"36",
    "addr:postcode":"m2n 3c8",
    "addr:street":"Greenfield Ave",
    "iso:country":"CA",
    "sg:address":"36 Greenfield Ave",
    "sg:city":"North York",
    "sg:classifiers":[
        {
            "category":"Education",
            "subcategory":"School",
            "type":"Public Place"
        }
    ],
    "sg:phone":"+1 416 393 5556",
    "sg:postcode":"M2N 3C8",
    "sg:province":"ON",
    "wof:name":"Cardinal Carter Academy",
    "wof:placetype":"venue"
},
  "geometry": {"coordinates":[-79.41038500000001,43.76368],"type":"Point"}
}