{
  "type": "Feature",
  "properties": {
    "iso:country":"CA",
    "sg:address":"36 Greenfield Ave",
    "sg:city":"North York",
    "sg:classifiers":[
        {
            "category":"Education",
            "subcategory":"School",
            "type":"Public Place"
        }
    ],
    "sg:phone":"+1 416 393 5556",
    "sg:postcode":"M2N 3C8",
    "sg:province":"ON",
    "wof:name":"Cardinal Carter Academy",
    "wof:placetype":"venue"
},
  "geometry": {"coordinates":[-79.410385,43.76368],"type":"Point"}
}