{
  "type": "Feature",
  "properties": {
    "addr:full":"136 King St E Bowmanville ON L1C 1N7",
    "addr:housenumber":"136",
    "addr:postcode":"l1c 1n7",
    "addr:street":"King St",
    "iso:country":"CA",
    "sg:address":"136 King St E",
    "sg:city":"Bowmanville",
    "sg:classifiers":[
        {
            "category":"Retail",
            "subcategory":"Laundry & Dry Cleaning",
            "type":"Services"
        }
    ],
    "sg:phone":"+1 905 623 6833",
    "sg:postcode":"L1C 1N7",
    "sg:province":"ON",
    "wof:name":"Sangor Coin Laundry",
    "wof:placetype":"venue"
},
  "geometry": {"coordinates":[-78.683617,43.910973],"type":"Point"}
}