{
  "type": "Feature",
  "properties": {
    "addr:full":"122 15th St W North Vancouver BC V7M 1R5",
    "addr:housenumber":"122",
    "addr:postcode":"v7m 1r5",
    "addr:street":"15Th St W",
    "iso:country":"CA",
    "sg:address":"122 15th St W",
    "sg:city":"North Vancouver",
    "sg:classifiers":[
        {
            "category":"Banks & Credit Unions",
            "subcategory":"Bank",
            "type":"Services"
        }
    ],
    "sg:phone":"+1 604 980 9977",
    "sg:postcode":"V7M 1R5",
    "sg:province":"BC",
    "sg:tags":[
        "broker",
        "foreign",
        "dealer",
        "exchange"
    ],
    "wof:name":"Salamat Exchange Ltd",
    "wof:placetype":"venue"
},
  "geometry": {"coordinates":[-123.073188782,49.3222160339],"type":"Point"}
}