{
  "type": "Feature",
  "properties": {
    "addr:full":"427 Bloor St W #206 Toronto ON M5S 1X7",
    "addr:housenumber":"427",
    "addr:postcode":"m5s 1x7",
    "addr:street":"Bloor St W # 206",
    "iso:country":"CA",
    "sg:address":"427 Bloor St W #206",
    "sg:city":"Toronto",
    "sg:classifiers":[
        {
            "category":"Health Services",
            "subcategory":"Nursing And Care Facility",
            "type":"Services"
        }
    ],
    "sg:phone":"+1 416 920 7483",
    "sg:postcode":"M5S 1X7",
    "sg:province":"ON",
    "sg:tags":[
        "home",
        "retirement",
        "community"
    ],
    "wof:name":"Abbeyfield Houses Society",
    "wof:placetype":"venue"
},
  "geometry": {"coordinates":[-79.405418396,43.6662445068],"type":"Point"}
}