{
  "type": "Feature",
  "properties": {
    "addr:full":"152 Silver Lode Lane Vernon BC V1B 3M1",
    "addr:housenumber":"152",
    "addr:postcode":"bc v1b 3m1",
    "addr:street":"Silver Lode Lane",
    "iso:country":"CA",
    "sg:address":"152 Silver Lode Lane",
    "sg:city":"Vernon",
    "sg:classifiers":[
        {
            "category":"Shopping",
            "subcategory":"Bicycles & Sporting Goods",
            "type":"Retail Goods"
        }
    ],
    "sg:phone":"+1 250 558 4292",
    "sg:postcode":"V1B 3M1",
    "sg:province":"BC",
    "wof:name":"Valhalla Pure Outfitters",
    "wof:placetype":"venue"
},
  "geometry": {"coordinates":[-119.273804,50.265686],"type":"Point"}
}