{
  "type": "Feature",
  "properties": {
    "iso:country":"CA",
    "sg:address":"1729 Water St",
    "sg:city":"Miramichi",
    "sg:classifiers":[
        {
            "category":"Restaurant",
            "type":"Food & Drink"
        }
    ],
    "sg:phone":"+1 506 773 4214",
    "sg:postcode":"E1N 1B2",
    "sg:province":"NB",
    "wof:name":"Saddlers Cafe",
    "wof:placetype":"venue"
},
  "geometry": {"coordinates":[-65.4705581665,47.0297966003],"type":"Point"}
}