{
  "type": "Feature",
  "properties": {
    "addr:full":"3255 Airport Rd Timmins ON P4N 7C3",
    "addr:housenumber":"3255",
    "addr:postcode":"p4n 7c3",
    "addr:street":"Airport Rd",
    "iso:country":"CA",
    "sg:address":"3255 Airport Rd",
    "sg:city":"Timmins",
    "sg:classifiers":[
        {
            "category":"Social Services",
            "type":"Services"
        }
    ],
    "sg:phone":"+1 705 264 4661",
    "sg:postcode":"P4N 7C3",
    "sg:province":"ON",
    "sg:tags":[
        "organization",
        "welfare"
    ],
    "wof:name":"Kapashewakamik",
    "wof:placetype":"venue"
},
  "geometry": {"coordinates":[-81.37172700000001,48.563114],"type":"Point"}
}