{
  "type": "Feature",
  "properties": {
    "addr:full":"3354 Rue Laval Lac-Megantic QC G6B 1A4",
    "addr:housenumber":"3354",
    "addr:postcode":"g6b 1a4",
    "addr:street":"Rue Laval Lac-Megantic",
    "iso:country":"CA",
    "sg:address":"3354 Rue Laval",
    "sg:city":"Lac-Megantic",
    "sg:classifiers":[
        {
            "category":"Autos & Motor Vehicles",
            "subcategory":"Automobile Sales",
            "type":"Retail Goods"
        }
    ],
    "sg:phone":"+1 819 583 4545",
    "sg:postcode":"G6B 1A4",
    "sg:province":"QC",
    "sg:tags":[
        "car",
        "dealer"
    ],
    "wof:name":"Amical Automobiles Inc",
    "wof:placetype":"venue"
},
  "geometry": {"coordinates":[-70.9081878662,45.5913238525],"type":"Point"}
}