{
  "type": "Feature",
  "properties": {
    "addr:full":"2954 4th Ave W Vancouver BC V6K 1R4",
    "addr:housenumber":"2954",
    "addr:postcode":"v6k 1r4",
    "addr:street":"4Th Ave W",
    "iso:country":"CA",
    "sg:address":"2954 4th Ave W",
    "sg:city":"Vancouver",
    "sg:classifiers":[
        {
            "category":"Home & Garden",
            "subcategory":"Garden Supply",
            "type":"Retail Goods"
        }
    ],
    "sg:phone":"+1 604 736 8404",
    "sg:postcode":"V6K 1R4",
    "sg:province":"BC",
    "sg:tags":[
        "center"
    ],
    "wof:name":"Earthrise Garden Store",
    "wof:placetype":"venue"
},
  "geometry": {"coordinates":[-123.171318,49.268269],"type":"Point"}
}