{
  "type": "Feature",
  "properties": {
    "addr:full":"143 8 Ave SE High River AB T1V 1R8",
    "addr:housenumber":"143",
    "addr:postcode":"t1v 1r8",
    "addr:street":"8 Ave Se",
    "iso:country":"CA",
    "sg:address":"143 8 Ave SE",
    "sg:city":"High River",
    "sg:classifiers":[
        {
            "category":"Sports & Exercise",
            "subcategory":"Gym",
            "type":"Entertainment"
        }
    ],
    "sg:phone":"+1 403 652 1400",
    "sg:postcode":"T1V 1R8",
    "sg:province":"AB",
    "sg:tags":[
        "club",
        "health",
        "studio",
        "gymnasium"
    ],
    "wof:name":"Fitness Factory",
    "wof:placetype":"venue"
},
  "geometry": {"coordinates":[-113.866264,50.57552],"type":"Point"}
}