{
  "type": "Feature",
  "properties": {
    "iso:country":"CA",
    "sg:city":"Sault Ste Marie",
    "sg:classifiers":[
        {
            "category":"Organizations",
            "subcategory":"Labor Organization",
            "type":"Services"
        }
    ],
    "sg:phone":"+1 705 949 6221",
    "sg:postcode":"P6A 2Z5",
    "sg:province":"ON",
    "wof:name":"Canadian Union of Public Empl",
    "wof:placetype":"venue"
},
  "geometry": {"coordinates":[-84.33168792719999,46.5113372803],"type":"Point"}
}