{
  "type": "Feature",
  "properties": {
    "addr:full":"1051 Coulter Ave Winnipeg MB R3E 0X9",
    "addr:housenumber":"1051",
    "addr:postcode":"r3e 0x9",
    "addr:street":"Coulter Ave",
    "iso:country":"CA",
    "sg:address":"1051 Coulter Ave",
    "sg:city":"Winnipeg",
    "sg:classifiers":[
        {
            "category":"Freight",
            "type":"Transportation"
        }
    ],
    "sg:phone":"+1 204 988 9500",
    "sg:postcode":"R3E 0X9",
    "sg:province":"MB",
    "sg:tags":[
        "grain",
        "elevator"
    ],
    "wof:name":"Ag Pro Grain",
    "wof:placetype":"venue"
},
  "geometry": {"coordinates":[-97.17203499999999,49.909054],"type":"Point"}
}