{
  "type": "Feature",
  "properties": {
    "iso:country":"CA",
    "sg:address":"11103 182 St NW",
    "sg:city":"Edmonton",
    "sg:classifiers":[
        {
            "category":"Building & Trades",
            "subcategory":"Construction",
            "type":"Services"
        }
    ],
    "sg:phone":"+1 780 489 1600",
    "sg:postcode":"T5S 2R3",
    "sg:province":"AB",
    "sg:tags":[
        "general",
        "contractor"
    ],
    "wof:name":"Buildexx Industrial Corp",
    "wof:placetype":"venue"
},
  "geometry": {"coordinates":[-113.635857,53.559986],"type":"Point"}
}