{
  "type": "Feature",
  "properties": {
    "addr:full":"155 Carlton St Winnipeg MB R3C 3H8",
    "addr:housenumber":"155",
    "addr:postcode":"r3c 3h8",
    "addr:street":"Carlton St",
    "iso:country":"CA",
    "sg:address":"155 Carlton St",
    "sg:city":"Winnipeg",
    "sg:classifiers":[
        {
            "category":"Government",
            "subcategory":"Office",
            "type":"Public Place"
        }
    ],
    "sg:phone":"+1 204 945 3798",
    "sg:postcode":"R3C 3H8",
    "sg:province":"MB",
    "wof:name":"Manitoba Maps",
    "wof:placetype":"venue"
},
  "geometry": {"coordinates":[-97.14361572270001,49.8889541626],"type":"Point"}
}