{
  "type": "Feature",
  "properties": {
    "addr:full":"222 Boul Sir-Wilfrid-Laurier Beloeil QC J3G 4G7",
    "addr:housenumber":"222",
    "addr:postcode":"j3g 4g7",
    "addr:street":"Boul Sir-Wilfrid-Laurier",
    "iso:country":"CA",
    "sg:address":"222 Boul Sir-Wilfrid-Laurier",
    "sg:city":"Beloeil",
    "sg:classifiers":[
        {
            "category":"Personal",
            "subcategory":"Beauty Salon",
            "type":"Services"
        }
    ],
    "sg:phone":"+1 450 464 2922",
    "sg:postcode":"J3G 4G7",
    "sg:province":"QC",
    "wof:name":"Picasso Coiffure",
    "wof:placetype":"venue"
},
  "geometry": {"coordinates":[-73.2141113281,45.5534744263],"type":"Point"}
}