{
  "type": "Feature",
  "properties": {
    "addr:full":"4200 Whistler Way Whistler BC V0N 1B4",
    "addr:housenumber":"4200",
    "addr:postcode":"v0n 1b4",
    "addr:street":"Whistler Way",
    "iso:country":"CA",
    "sg:address":"4200 Whistler Way",
    "sg:city":"Whistler",
    "sg:classifiers":[
        {
            "category":"Travel",
            "subcategory":"Hotels & Motels",
            "type":"Entertainment"
        }
    ],
    "sg:phone":"+1 604 932 4146",
    "sg:postcode":"V0N 1B4",
    "sg:province":"BC",
    "sg:tags":[
        "resort"
    ],
    "wof:name":"Tantalus Resort Lodge",
    "wof:placetype":"venue"
},
  "geometry": {"coordinates":[-122.95891571,50.111164093],"type":"Point"}
}