{
  "type": "Feature",
  "properties": {
    "addr:full":"1873 Lawrence Ave E Scarborough ON M1R 2Y3",
    "addr:housenumber":"1873",
    "addr:postcode":"m1r 2y3",
    "addr:street":"Lawrence Ave E",
    "iso:country":"CA",
    "sg:address":"1873 Lawrence Ave E",
    "sg:city":"Scarborough",
    "sg:classifiers":[
        {
            "category":"Restaurant",
            "type":"Food & Drink"
        }
    ],
    "sg:phone":"+1 416 751 2188",
    "sg:postcode":"M1R 2Y3",
    "sg:province":"ON",
    "wof:name":"Mister Chop Suey",
    "wof:placetype":"venue"
},
  "geometry": {"coordinates":[-79.3020477295,43.7437171936],"type":"Point"}
}