{
  "type": "Feature",
  "properties": {
    "addr:full":"724 Chiniki Dr Cochrane AB T4C 1Y4",
    "addr:housenumber":"724",
    "addr:postcode":"t4c 1y4",
    "addr:street":"Chiniki Dr",
    "iso:country":"CA",
    "sg:address":"724 Chiniki Dr",
    "sg:city":"Cochrane",
    "sg:classifiers":[
        {
            "category":"Education",
            "subcategory":"School",
            "type":"Public Place"
        }
    ],
    "sg:phone":"+1 403 932 2215",
    "sg:postcode":"T4C 1Y4",
    "sg:province":"AB",
    "wof:name":"Manachaban School",
    "wof:placetype":"venue"
},
  "geometry": {"coordinates":[-114.474998474,51.1961288452],"type":"Point"}
}