{
  "type": "Feature",
  "properties": {
    "addr:full":"900 Devine St Sarnia ON N7T 1X5",
    "addr:housenumber":"900",
    "addr:postcode":"n7t 1x5",
    "addr:street":"Devine St",
    "iso:country":"CA",
    "sg:address":"900 Devine St",
    "sg:city":"Sarnia",
    "sg:classifiers":[
        {
            "category":"Organizations",
            "subcategory":"Labor Organization",
            "type":"Services"
        }
    ],
    "sg:phone":"+1 519 332 4102",
    "sg:postcode":"N7T 1X5",
    "sg:province":"ON",
    "wof:name":"Comm Energy & Paperworkers",
    "wof:placetype":"venue"
},
  "geometry": {"coordinates":[-82.377861,42.964355],"type":"Point"}
}