{
  "type": "Feature",
  "properties": {
    "addr:full":"75 Lancing Dr Hamilton ON L8W 2Z9",
    "addr:housenumber":"75",
    "addr:postcode":"l8w 2z9",
    "addr:street":"Lancing Dr",
    "iso:country":"CA",
    "sg:address":"75 Lancing Dr",
    "sg:city":"Hamilton",
    "sg:classifiers":[
        {
            "category":"Real Estate",
            "subcategory":"Real Estate Agent",
            "type":"Services"
        }
    ],
    "sg:phone":"+1 905 574 6433",
    "sg:postcode":"L8W 2Z9",
    "sg:province":"ON",
    "wof:name":"Crowncorp Realty Group Inc",
    "wof:placetype":"venue"
},
  "geometry": {"coordinates":[-79.84032440190001,43.1925163269],"type":"Point"}
}