{
  "type": "Feature",
  "properties": {
    "addr:full":"Calgary AB T2C 2Y4",
    "addr:postcode":"t2c 2y4",
    "iso:country":"CA",
    "sg:city":"Calgary",
    "sg:classifiers":[
        {
            "category":"Wholesale",
            "subcategory":"Machinery & Supplies",
            "type":"Manufacturing & Wholesale Goods"
        }
    ],
    "sg:phone":"+1 403 203 2644",
    "sg:postcode":"T2C 2Y4",
    "sg:province":"AB",
    "sg:tags":[
        "equipment",
        "sand",
        "gravel",
        "handling"
    ],
    "wof:name":"Mormak Equipment Ltd",
    "wof:placetype":"venue"
},
  "geometry": {"coordinates":[-113.97465515099999,50.9822044373],"type":"Point"}
}