{
  "type": "Feature",
  "properties": {
    "addr:full":"15 Rue Costello Edmundston NB E3V 3Y4",
    "addr:housenumber":"15",
    "addr:postcode":"e3v 3y4",
    "addr:street":"Rue Costello",
    "iso:country":"CA",
    "sg:address":"15 Rue Costello",
    "sg:city":"Edmundston",
    "sg:classifiers":[
        {
            "category":"Organizations",
            "subcategory":"Non-profit Organization",
            "type":"Services"
        }
    ],
    "sg:phone":"+1 506 735 4500",
    "sg:postcode":"E3V 3Y4",
    "sg:province":"NB",
    "sg:tags":[
        "addiction",
        "treatment",
        "recreation",
        "center"
    ],
    "wof:name":"Alcoholics Anonymous",
    "wof:placetype":"venue"
},
  "geometry": {"coordinates":[-68.3280410767,47.3643074036],"type":"Point"}
}