{
  "type": "Feature",
  "properties": {
    "addr:full":"795 Av Des Noisetiers Alma QC G8B 7W3",
    "addr:housenumber":"795",
    "addr:postcode":"g8b 7w3",
    "addr:street":"Av Des Noisetiers",
    "iso:country":"CA",
    "sg:address":"795 Av Des Noisetiers",
    "sg:city":"Alma",
    "sg:classifiers":[
        {
            "category":"Organizations",
            "subcategory":"Religious Organization",
            "type":"Services"
        }
    ],
    "sg:phone":"+1 418 669 2121",
    "sg:postcode":"G8B 7W3",
    "sg:province":"QC",
    "sg:tags":[
        "home",
        "retirement",
        "community",
        "retreat",
        "house"
    ],
    "wof:name":"Villa D'Alma",
    "wof:placetype":"venue"
},
  "geometry": {"coordinates":[-71.636390686,48.5647621155],"type":"Point"}
}