{
  "type": "Feature",
  "properties": {
    "addr:full":"414 Windsor Junction Rd Windsor Junction NS B2T 1G2",
    "addr:housenumber":"414",
    "addr:postcode":"b2t 1g2",
    "addr:street":"Windsor Junction Rd",
    "iso:country":"CA",
    "sg:address":"414 Windsor Junction Rd",
    "sg:city":"Windsor Junction",
    "sg:classifiers":[
        {
            "category":"Retail",
            "subcategory":"Repair Shop",
            "type":"Services"
        }
    ],
    "sg:phone":"+1 902 861 3028",
    "sg:postcode":"B2T 1G2",
    "sg:province":"NS",
    "sg:tags":[
        "refinishing",
        "furniture"
    ],
    "wof:name":"W S Barkhouse Furniture Rfnsh",
    "wof:placetype":"venue"
},
  "geometry": {"coordinates":[-63.642754,44.792637],"type":"Point"}
}