{
  "type": "Feature",
  "properties": {
    "addr:full":"839 24 Ave SE Calgary AB T2G 1P6",
    "addr:housenumber":"839",
    "addr:postcode":"t2g 1p6",
    "addr:street":"24 Ave Se",
    "iso:country":"CA",
    "sg:address":"839 24 Ave SE",
    "sg:city":"Calgary",
    "sg:classifiers":[
        {
            "category":"Building & Trades",
            "subcategory":"Construction",
            "type":"Services"
        }
    ],
    "sg:phone":"+1 403 262 6116",
    "sg:postcode":"T2G 1P6",
    "sg:province":"AB",
    "sg:tags":[
        "roofing",
        "contractor"
    ],
    "wof:name":"Western Roofing & Contracting",
    "wof:placetype":"venue"
},
  "geometry": {"coordinates":[-114.041702,51.032028],"type":"Point"}
}