{
  "type": "Feature",
  "properties": {
    "addr:full":"257 Seymour St Kamloops BC V2C 2E7",
    "addr:housenumber":"257",
    "addr:postcode":"bc v2c 2e7",
    "addr:street":"Seymour St",
    "iso:country":"CA",
    "sg:address":"257 Seymour St",
    "sg:city":"Kamloops",
    "sg:classifiers":[
        {
            "category":"Education",
            "subcategory":"Special Training",
            "type":"Public Place"
        }
    ],
    "sg:phone":"+1 250 851 3829",
    "sg:postcode":"V2C 2E7",
    "sg:province":"BC",
    "sg:tags":[
        "tutoring"
    ],
    "wof:name":"Sylvan Learning Ctr",
    "wof:placetype":"venue"
},
  "geometry": {"coordinates":[-120.335419,50.674809],"type":"Point"}
}