{
  "type": "Feature",
  "properties": {
    "addr:full":"PO Box 1154 Cambridge Bay NU X0B 0C0",
    "addr:housenumber":"po",
    "addr:postcode":"x0b 0c0",
    "addr:street":"Box 1154",
    "iso:country":"CA",
    "sg:address":"PO Box 1154",
    "sg:city":"Cambridge Bay",
    "sg:classifiers":[
        {
            "category":"Social Services",
            "subcategory":"Child Care",
            "type":"Services"
        }
    ],
    "sg:phone":"+1 867 983 2523",
    "sg:postcode":"X0B 0C0",
    "sg:province":"NU",
    "wof:name":"Cambridge Bay Childcare Ctr",
    "wof:placetype":"venue"
},
  "geometry": {"coordinates":[-105.05755600000001,69.11428100000001],"type":"Point"}
}