{
  "type": "Feature",
  "properties": {
    "addr:full":"314 Main St Schomberg ON L0G 1T0",
    "addr:housenumber":"314",
    "addr:postcode":"l0g 1t0",
    "addr:street":"Main St",
    "iso:country":"CA",
    "sg:address":"314 Main St",
    "sg:city":"Schomberg",
    "sg:classifiers":[
        {
            "category":"Wholesale",
            "subcategory":"Meat",
            "type":"Manufacturing & Wholesale Goods"
        }
    ],
    "sg:phone":"+1 905 939 2851",
    "sg:postcode":"L0G 1T0",
    "sg:province":"ON",
    "sg:tags":[
        "butchering"
    ],
    "wof:name":"Schomberg Quality Meats",
    "wof:placetype":"venue"
},
  "geometry": {"coordinates":[-79.684044,44.003887],"type":"Point"}
}