{
  "type": "Feature",
  "properties": {
    "addr:full":"2032 Boul Saint-Laurent Montreal QC H2X 2T2",
    "addr:housenumber":"2032",
    "addr:postcode":"h2x 2t2",
    "addr:street":"Boul Saint-Laurent",
    "iso:country":"CA",
    "sg:address":"2032 Boul Saint-Laurent",
    "sg:city":"Montreal",
    "sg:classifiers":[
        {
            "category":"Shopping",
            "subcategory":"Gifts & Souvenirs",
            "type":"Retail Goods"
        }
    ],
    "sg:phone":"+1 514 845 5114",
    "sg:postcode":"H2X 2T2",
    "sg:province":"QC",
    "sg:tags":[
        "shop"
    ],
    "wof:name":"Chang Cheng Enterprise Intl",
    "wof:placetype":"venue"
},
  "geometry": {"coordinates":[-73.567581,45.511505],"type":"Point"}
}