{
  "type": "Feature",
  "properties": {
    "iso:country":"CA",
    "sg:address":"9042 Rue Jamay",
    "sg:city":"Saint-Leonard",
    "sg:classifiers":[
        {
            "category":"Building & Trades",
            "subcategory":"Electrical",
            "type":"Services"
        }
    ],
    "sg:phone":"+1 514 324 5781",
    "sg:postcode":"H1R 2L1",
    "sg:province":"QC",
    "sg:tags":[
        "electric",
        "contractor"
    ],
    "wof:name":"Onna Electrique Enr",
    "wof:placetype":"venue"
},
  "geometry": {"coordinates":[-73.608871,45.59074],"type":"Point"}
}