{
  "type": "Feature",
  "properties": {
    "addr:full":"558 Park Royal N # A West Vancouver BC V7T 1H9",
    "addr:housenumber":"558",
    "addr:postcode":"v7t 1h9",
    "addr:street":"Park Royal N # A",
    "iso:country":"CA",
    "sg:address":"558 Park Royal N # A",
    "sg:city":"West Vancouver",
    "sg:classifiers":[
        {
            "category":"Shopping",
            "subcategory":"Optical Goods",
            "type":"Retail Goods"
        }
    ],
    "sg:phone":"+1 604 990 3937",
    "sg:postcode":"V7T 1H9",
    "sg:province":"BC",
    "sg:tags":[
        "optician"
    ],
    "wof:name":"Image Optical Svc",
    "wof:placetype":"venue"
},
  "geometry": {"coordinates":[-123.134888,49.327591],"type":"Point"}
}