{
  "type": "Feature",
  "properties": {
    "addr:full":"643 Corydon Ave Winnipeg MB R3M 0W3",
    "addr:housenumber":"643",
    "addr:postcode":"r3m 0w3",
    "addr:street":"Corydon Ave",
    "iso:country":"CA",
    "sg:address":"643 Corydon Ave",
    "sg:city":"Winnipeg",
    "sg:classifiers":[
        {
            "category":"Restaurant",
            "type":"Food & Drink"
        }
    ],
    "sg:phone":"+1 204 475 8765",
    "sg:postcode":"R3M 0W3",
    "sg:province":"MB",
    "sg:tags":[
        "parlor",
        "ice",
        "cream"
    ],
    "wof:name":"Nucci's Gelati",
    "wof:placetype":"venue"
},
  "geometry": {"coordinates":[-97.14962768549999,49.8722038269],"type":"Point"}
}