{
  "type": "Feature",
  "properties": {
    "addr:full":"435 Second St W Brooks AB T1R 0E8",
    "addr:housenumber":"435",
    "addr:postcode":"ab t1r 0e8",
    "addr:street":"Second St W Brooks",
    "iso:country":"CA",
    "sg:address":"435 Second St W",
    "sg:city":"Brooks",
    "sg:classifiers":[
        {
            "category":"Restaurant",
            "type":"Food & Drink"
        }
    ],
    "sg:phone":"+1 403 362 3361",
    "sg:postcode":"T1R 0E8",
    "sg:province":"AB",
    "wof:name":"Kfc",
    "wof:placetype":"venue"
},
  "geometry": {"coordinates":[-111.897644043,50.5695571899],"type":"Point"}
}