{
  "type": "Feature",
  "properties": {
    "addr:full":"331 22nd St W Battleford SK S0M 0E0",
    "addr:housenumber":"331",
    "addr:postcode":"s0m 0e0",
    "addr:street":"22Nd St W",
    "iso:country":"CA",
    "sg:address":"331 22nd St W",
    "sg:city":"Battleford",
    "sg:classifiers":[
        {
            "category":"Restaurant",
            "type":"Food & Drink"
        }
    ],
    "sg:phone":"+1 306 937 2884",
    "sg:postcode":"S0M 0E0",
    "sg:province":"SK",
    "wof:name":"My Friend's Place",
    "wof:placetype":"venue"
},
  "geometry": {"coordinates":[-108.31314086899999,52.7362365723],"type":"Point"}
}