{
  "type": "Feature",
  "properties": {
    "iso:country":"CA",
    "sg:address":"33 Rue Huot",
    "sg:city":"Notre-Dame-DE-L'Ile-Perrot",
    "sg:classifiers":[
        {
            "category":"Manufacturing",
            "subcategory":"Tools & Machinery",
            "type":"Manufacturing & Wholesale Goods"
        }
    ],
    "sg:phone":"+1 514 453 6910",
    "sg:postcode":"J7V 7M4",
    "sg:province":"QC",
    "sg:tags":[
        "water",
        "equipment",
        "works",
        "supply"
    ],
    "wof:name":"Stelem",
    "wof:placetype":"venue"
},
  "geometry": {"coordinates":[-73.955368042,45.3937644958],"type":"Point"}
}