{
  "type": "Feature",
  "properties": {
    "iso:country":"CA",
    "sg:city":"Etobicoke",
    "sg:classifiers":[
        {
            "category":"Wholesale",
            "subcategory":"Electrical",
            "type":"Manufacturing & Wholesale Goods"
        }
    ],
    "sg:phone":"+1 416 252 6036",
    "sg:postcode":"M8V 1C6",
    "sg:province":"ON",
    "sg:tags":[
        "control",
        "security",
        "system"
    ],
    "wof:name":"Fidelity Monitoring Ltd",
    "wof:placetype":"venue"
},
  "geometry": {"coordinates":[-79.4887313843,43.6144371033],"type":"Point"}
}