{
  "type": "Feature",
  "properties": {
    "addr:full":"255 3E Rue E # 19 LA Sarre QC J9Z 3N7",
    "addr:housenumber":"255",
    "addr:postcode":"j9z 3n7",
    "addr:street":"3E Rue E # 19 La Sarre",
    "iso:country":"CA",
    "sg:address":"255 3E Rue E # 19",
    "sg:city":"LA Sarre",
    "sg:classifiers":[
        {
            "category":"Shopping",
            "subcategory":"Clothing, Apparel, & Fashions",
            "type":"Retail Goods"
        }
    ],
    "sg:phone":"+1 819 339 2512",
    "sg:postcode":"J9Z 3N7",
    "sg:province":"QC",
    "sg:tags":[
        "jean"
    ],
    "wof:name":"Caveau Des Jeans Ltee",
    "wof:placetype":"venue"
},
  "geometry": {"coordinates":[-79.200073,48.815502],"type":"Point"}
}