{
  "type": "Feature",
  "properties": {
    "addr:full":"Maple Ridge BC V2X 6E6",
    "addr:postcode":"v2x 6e6",
    "iso:country":"CA",
    "sg:city":"Maple Ridge",
    "sg:classifiers":[
        {
            "category":"Wholesale",
            "subcategory":"Scrap",
            "type":"Manufacturing & Wholesale Goods"
        }
    ],
    "sg:phone":"+1 604 467 0870",
    "sg:postcode":"V2X 6E6",
    "sg:province":"BC",
    "sg:tags":[
        "recycling",
        "center"
    ],
    "wof:name":"Mainland Cartridge Works Inc",
    "wof:placetype":"venue"
},
  "geometry": {"coordinates":[-122.599151611,49.2164382935],"type":"Point"}
}