{
  "type": "Feature",
  "properties": {
    "iso:country":"CA",
    "sg:address":"5531 Perth Line 86",
    "sg:city":"Listowel",
    "sg:classifiers":[
        {
            "category":"Wholesale",
            "subcategory":"Farm Supplies",
            "type":"Manufacturing & Wholesale Goods"
        }
    ],
    "sg:phone":"+1 519 291 1094",
    "sg:postcode":"N4W 3G8",
    "sg:province":"ON",
    "wof:name":"Carson's Feed Supply & Tack",
    "wof:placetype":"venue"
},
  "geometry": {"coordinates":[-80.92543792719999,43.7200698853],"type":"Point"}
}