{
  "type": "Feature",
  "properties": {
    "addr:full":"125 Boul Des Laurentides Laval QC H7G 2T4",
    "addr:housenumber":"125",
    "addr:postcode":"qc h7g 2t4",
    "addr:street":"Boul Des Laurentides",
    "iso:country":"CA",
    "sg:address":"125 Boul Des Laurentides",
    "sg:city":"Laval",
    "sg:classifiers":[
        {
            "category":"Shopping",
            "subcategory":"Used Merchandise",
            "type":"Retail Goods"
        }
    ],
    "sg:phone":"+1 450 667 6730",
    "sg:postcode":"H7G 2T4",
    "sg:province":"QC",
    "sg:tags":[
        "book",
        "rare",
        "dealer"
    ],
    "wof:name":"Librairie Mini-Prix Inc",
    "wof:placetype":"venue"
},
  "geometry": {"coordinates":[-73.684608,45.563877],"type":"Point"}
}