{
  "type": "Feature",
  "properties": {
    "addr:full":"Ottawa ON K2P 0A9",
    "addr:postcode":"k2p 0a9",
    "iso:country":"CA",
    "sg:city":"Ottawa",
    "sg:classifiers":[
        {
            "category":"Real Estate",
            "subcategory":"Real Estate Operator",
            "type":"Services"
        }
    ],
    "sg:phone":"+1 613 233 8108",
    "sg:postcode":"K2P 0A9",
    "sg:province":"ON",
    "sg:tags":[
        "apartment"
    ],
    "wof:name":"Gloucester Apartments",
    "wof:placetype":"venue"
},
  "geometry": {"coordinates":[-75.6997833252,45.4172668457],"type":"Point"}
}