{
  "type": "Feature",
  "properties": {
    "addr:full":"Richmond BC V6X 3R8",
    "addr:postcode":"v6x 3r8",
    "iso:country":"CA",
    "sg:city":"Richmond",
    "sg:classifiers":[
        {
            "category":"Shopping",
            "subcategory":"Books",
            "type":"Retail Goods"
        }
    ],
    "sg:phone":"+1 604 303 1102",
    "sg:postcode":"V6X 3R8",
    "sg:province":"BC",
    "sg:tags":[
        "dealer"
    ],
    "wof:name":"Manna Book Store Inc",
    "wof:placetype":"venue"
},
  "geometry": {"coordinates":[-123.133247,49.181732],"type":"Point"}
}