{
  "type": "Feature",
  "properties": {
    "addr:full":"1125 Rife Rd Cambridge ON N1R 5S3",
    "addr:housenumber":"1125",
    "addr:postcode":"n1r 5s3",
    "addr:street":"Rife Rd",
    "iso:country":"CA",
    "sg:address":"1125 Rife Rd",
    "sg:city":"Cambridge",
    "sg:classifiers":[
        {
            "category":"Home & Garden",
            "subcategory":"Building Materials",
            "type":"Retail Goods"
        }
    ],
    "sg:phone":"+1 519 623 1200",
    "sg:postcode":"N1R 5S3",
    "sg:province":"ON",
    "sg:tags":[
        "lumber"
    ],
    "wof:name":"Rockett Lumber Ltd",
    "wof:placetype":"venue"
},
  "geometry": {"coordinates":[-80.300766,43.43005],"type":"Point"}
}