{
  "type": "Feature",
  "properties": {
    "addr:full":"99 Blackmarsh Rd St. John's NL A1E 1S6",
    "addr:housenumber":"99",
    "addr:postcode":"a1e 1s6",
    "addr:street":"Blackmarsh Rd",
    "iso:country":"CA",
    "sg:address":"99 Blackmarsh Rd",
    "sg:city":"St. John's",
    "sg:classifiers":[
        {
            "category":"Real Estate",
            "subcategory":"Real Estate Agent",
            "type":"Services"
        }
    ],
    "sg:phone":"+1 709 724 6400",
    "sg:postcode":"A1E 1S6",
    "sg:province":"NL",
    "sg:tags":[
        "management"
    ],
    "wof:name":"Onshore Investments Inc",
    "wof:placetype":"venue"
},
  "geometry": {"coordinates":[-52.7341575623,47.5494194031],"type":"Point"}
}