{
  "type": "Feature",
  "properties": {
    "addr:full":"44531 Southdale Line St Thomas ON N5P 3S6",
    "addr:housenumber":"44531",
    "addr:postcode":"n5p 3s6",
    "addr:street":"Southdale Line",
    "iso:country":"CA",
    "sg:address":"44531 Southdale Line",
    "sg:city":"St Thomas",
    "sg:classifiers":[
        {
            "category":"Building & Trades",
            "subcategory":"Construction",
            "type":"Services"
        }
    ],
    "sg:phone":"+1 519 631 5759",
    "sg:postcode":"N5P 3S6",
    "sg:province":"ON",
    "sg:tags":[
        "roofing",
        "contractor"
    ],
    "wof:name":"R Doan Roofing Ltd",
    "wof:placetype":"venue"
},
  "geometry": {"coordinates":[-81.19314575200001,42.7789382935],"type":"Point"}
}