{
  "type": "Feature",
  "properties": {
    "addr:full":"484 Bay St Port Perry ON L9L 1M7",
    "addr:housenumber":"484",
    "addr:postcode":"l9l 1m7",
    "addr:street":"Bay St",
    "iso:country":"CA",
    "sg:address":"484 Bay St",
    "sg:city":"Port Perry",
    "sg:classifiers":[
        {
            "category":"Organizations",
            "subcategory":"Professional Association",
            "type":"Services"
        }
    ],
    "sg:phone":"+1 905 985 8502",
    "sg:postcode":"L9L 1M7",
    "sg:province":"ON",
    "wof:name":"Royal Canadian Legion Branch",
    "wof:placetype":"venue"
},
  "geometry": {"coordinates":[-78.9558334351,44.1069564819],"type":"Point"}
}