{
  "type": "Feature",
  "properties": {
    "addr:full":"277 Boul Des Promenades Saint-Bruno QC J3V 5K3",
    "addr:housenumber":"277",
    "addr:postcode":"j3v 5k3",
    "addr:street":"Boul Des Promenades",
    "iso:country":"CA",
    "sg:address":"277 Boul Des Promenades",
    "sg:city":"Saint-Bruno",
    "sg:classifiers":[
        {
            "category":"Shopping",
            "subcategory":"Clothing, Apparel, & Fashions",
            "type":"Retail Goods"
        }
    ],
    "sg:phone":"+1 450 461 1042",
    "sg:postcode":"J3V 5K3",
    "sg:province":"QC",
    "sg:tags":[
        "bathing",
        "suit",
        "accessory"
    ],
    "wof:name":"Boutiques San Francisco Inc",
    "wof:placetype":"venue"
},
  "geometry": {"coordinates":[-71.67552185060001,48.4717712402],"type":"Point"}
}