{
  "type": "Feature",
  "properties": {
    "addr:full":"54 Rue DE LA Fabrique Saint-Benoit-Labre QC G0M 1P0",
    "addr:housenumber":"54",
    "addr:postcode":"g0m 1p0",
    "addr:street":"Rue De La Fabrique",
    "iso:country":"CA",
    "sg:address":"54 Rue DE LA Fabrique",
    "sg:city":"Saint-Benoit-Labre",
    "sg:classifiers":[
        {
            "category":"Organizations",
            "subcategory":"Religious Organization",
            "type":"Services"
        }
    ],
    "sg:phone":"+1 418 228 9212",
    "sg:postcode":"G0M 1P0",
    "sg:province":"QC",
    "sg:tags":[
        "church"
    ],
    "wof:name":"Presbytere St-Benoit-Labre",
    "wof:placetype":"venue"
},
  "geometry": {"coordinates":[-70.79265599999999,46.068027],"type":"Point"}
}