{
  "type": "Feature",
  "properties": {
    "addr:full":"536 Broadway St E Hwy 10 E Yorkton SK S3N 2X1",
    "addr:housenumber":"536",
    "addr:postcode":"s3n 2x1",
    "addr:street":"Broadway St E Hwy 10 E",
    "iso:country":"CA",
    "sg:address":"536 Broadway St E Hwy 10 E",
    "sg:city":"Yorkton",
    "sg:classifiers":[
        {
            "category":"Wholesale",
            "subcategory":"Farm Supplies",
            "type":"Manufacturing & Wholesale Goods"
        }
    ],
    "sg:phone":"+1 306 782 1710",
    "sg:postcode":"S3N 2X1",
    "sg:province":"SK",
    "sg:tags":[
        "feed"
    ],
    "wof:name":"Park Allen Farm & Ranch Supply",
    "wof:placetype":"venue"
},
  "geometry": {"coordinates":[-102.449874878,51.2040557861],"type":"Point"}
}