{
  "type": "Feature",
  "properties": {
    "addr:full":"3605 Beam Rd Creston BC V0B 1G1",
    "addr:housenumber":"3605",
    "addr:postcode":"bc v0b 1g1",
    "addr:street":"Beam Rd",
    "iso:country":"CA",
    "sg:address":"3605 Beam Rd",
    "sg:city":"Creston",
    "sg:classifiers":[
        {
            "category":"Shopping",
            "subcategory":"Musical Instruments",
            "type":"Retail Goods"
        }
    ],
    "sg:phone":"+1 250 428 5152",
    "sg:postcode":"V0B 1G1",
    "sg:province":"BC",
    "wof:name":"Anderson Music",
    "wof:placetype":"venue"
},
  "geometry": {"coordinates":[-116.51267199999999,49.095463],"type":"Point"}
}