{
  "type": "Feature",
  "properties": {
    "iso:country":"CA",
    "sg:city":"Montreal",
    "sg:classifiers":[
        {
            "category":"Real Estate",
            "subcategory":"Real Estate Agent",
            "type":"Services"
        }
    ],
    "sg:phone":"+1 514 939 1561",
    "sg:postcode":"H4C 1G8",
    "sg:province":"QC",
    "sg:tags":[
        "management"
    ],
    "wof:name":"Immeubles Huron Inc",
    "wof:placetype":"venue"
},
  "geometry": {"coordinates":[-73.5813751221,45.482875824],"type":"Point"}
}