{
  "type": "Feature",
  "properties": {
    "addr:full":"383 Sorauren Ave Toronto ON M6R 2G5",
    "addr:housenumber":"383",
    "addr:postcode":"m6r 2g5",
    "addr:street":"Sorauren Ave",
    "iso:country":"CA",
    "sg:address":"383 Sorauren Ave",
    "sg:city":"Toronto",
    "sg:classifiers":[
        {
            "category":"Wholesale",
            "subcategory":"Machinery & Supplies",
            "type":"Manufacturing & Wholesale Goods"
        }
    ],
    "sg:phone":"+1 416 532 1118",
    "sg:postcode":"M6R 2G5",
    "sg:province":"ON",
    "sg:tags":[
        "contractor"
    ],
    "wof:name":"Roofmart Limited",
    "wof:placetype":"venue"
},
  "geometry": {"coordinates":[-79.444824,43.650318],"type":"Point"}
}