{
  "type": "Feature",
  "properties": {
    "addr:full":"North York ON M3M 1H7",
    "addr:postcode":"m3m 1h7",
    "iso:country":"CA",
    "sg:city":"North York",
    "sg:classifiers":[
        {
            "category":"Travel",
            "subcategory":"Travel Agent",
            "type":"Entertainment"
        }
    ],
    "sg:phone":"+1 416 245 4212",
    "sg:postcode":"M3M 1H7",
    "sg:province":"ON",
    "sg:tags":[
        "agency",
        "bureau"
    ],
    "wof:name":"Eglinton Travel Ltd",
    "wof:placetype":"venue"
},
  "geometry": {"coordinates":[-79.498169,43.722961],"type":"Point"}
}