{
  "type": "Feature",
  "properties": {
    "addr:full":"3451 Av DE L'Hotel-DE-Ville Montreal QC H2X 3B5",
    "addr:housenumber":"3451",
    "addr:postcode":"h2x 3b5",
    "addr:street":"Av De L'Hotel-De-Ville",
    "iso:country":"CA",
    "sg:address":"3451 Av DE L'Hotel-DE-Ville",
    "sg:city":"Montreal",
    "sg:classifiers":[
        {
            "category":"Arts & Performance",
            "subcategory":"Theater",
            "type":"Entertainment"
        }
    ],
    "sg:phone":"+1 514 844 7653",
    "sg:postcode":"H2X 3B5",
    "sg:province":"QC",
    "sg:tags":[
        "talent",
        "agency",
        "casting"
    ],
    "wof:name":"Premier Role Inc",
    "wof:placetype":"venue"
},
  "geometry": {"coordinates":[-73.556549,45.509182],"type":"Point"}
}