{
  "type": "Feature",
  "properties": {
    "addr:full":"100 Osborne St N Winnipeg MB R3C 1V3",
    "addr:housenumber":"100",
    "addr:postcode":"r3c 1v3",
    "addr:street":"Osborne St N",
    "iso:country":"CA",
    "sg:address":"100 Osborne St N",
    "sg:city":"Winnipeg",
    "sg:classifiers":[
        {
            "category":"Insurance",
            "subcategory":"Insurance Agent",
            "type":"Services"
        }
    ],
    "sg:phone":"+1 204 946 1190",
    "sg:postcode":"R3C 1V3",
    "sg:province":"MB",
    "wof:name":"Great-West Life Assurance CO",
    "wof:placetype":"venue"
},
  "geometry": {"coordinates":[-97.149399,49.884109],"type":"Point"}
}