{
  "type": "Feature",
  "properties": {
    "iso:country":"CA",
    "sg:city":"Kanata",
    "sg:classifiers":[
        {
            "category":"Health Services",
            "subcategory":"Chiropractor",
            "type":"Services"
        }
    ],
    "sg:phone":"+1 613 592 7660",
    "sg:postcode":"K2L 3C8",
    "sg:province":"ON",
    "wof:name":"Lovsin, David C DC",
    "wof:placetype":"venue"
},
  "geometry": {"coordinates":[-75.895004,45.304806],"type":"Point"}
}