{
  "type": "Feature",
  "properties": {
    "addr:full":"122 Galaxy Blvd Etobicoke ON M9W 4Y6",
    "addr:housenumber":"122",
    "addr:postcode":"m9w 4y6",
    "addr:street":"Galaxy Blvd",
    "iso:country":"CA",
    "sg:address":"122 Galaxy Blvd",
    "sg:city":"Etobicoke",
    "sg:classifiers":[
        {
            "category":"Building & Trades",
            "subcategory":"Cleaning & Sanitation",
            "type":"Services"
        }
    ],
    "sg:phone":"+1 416 675 4676",
    "sg:postcode":"M9W 4Y6",
    "sg:province":"ON",
    "sg:tags":[
        "janitor"
    ],
    "wof:name":"Service Master of York",
    "wof:placetype":"venue"
},
  "geometry": {"coordinates":[-79.58543396,43.6790390015],"type":"Point"}
}