{
  "type": "Feature",
  "properties": {
    "addr:full":"2134 34 Ave SW Calgary AB T2T 5P6",
    "addr:housenumber":"2134",
    "addr:postcode":"t2t 5p6",
    "addr:street":"34 Ave Sw",
    "iso:country":"CA",
    "sg:address":"2134 34 Ave SW",
    "sg:city":"Calgary",
    "sg:classifiers":[
        {
            "category":"Health Services",
            "subcategory":"Doctor",
            "type":"Services"
        }
    ],
    "sg:phone":"+1 403 246 4423",
    "sg:postcode":"T2T 5P6",
    "sg:province":"AB",
    "sg:tags":[
        "dentist"
    ],
    "wof:name":"Hall, Bryce F DDS",
    "wof:placetype":"venue"
},
  "geometry": {"coordinates":[-114.11039,51.023258],"type":"Point"}
}