{
  "type": "Feature",
  "properties": {
    "addr:full":"39 Av Begin Levis QC G6V 4B8",
    "addr:postcode":"g6v 4b8",
    "addr:street":"39 Av Begin",
    "iso:country":"CA",
    "sg:address":"39 Av Begin",
    "sg:city":"Levis",
    "sg:classifiers":[
        {
            "category":"Education",
            "subcategory":"School",
            "type":"Public Place"
        }
    ],
    "sg:phone":"+1 418 833 2744",
    "sg:postcode":"G6V 4B8",
    "sg:province":"QC",
    "sg:tags":[
        "academic",
        "instruction",
        "special",
        "driving"
    ],
    "wof:name":"Ecole DE Conduite Rond-Point",
    "wof:placetype":"venue"
},
  "geometry": {"coordinates":[-71.18195299999999,46.807785],"type":"Point"}
}