{
  "type": "Feature",
  "properties": {
    "addr:full":"2121 Hastings St E Vancouver BC V5L 1V2",
    "addr:housenumber":"2121",
    "addr:postcode":"v5l 1v2",
    "addr:street":"Hastings St E",
    "iso:country":"CA",
    "sg:address":"2121 Hastings St E",
    "sg:city":"Vancouver",
    "sg:classifiers":[
        {
            "category":"Building & Trades",
            "subcategory":"Construction",
            "type":"Services"
        }
    ],
    "sg:phone":"+1 604 254 9864",
    "sg:postcode":"V5L 1V2",
    "sg:province":"BC",
    "sg:tags":[
        "tile",
        "dealer"
    ],
    "wof:name":"Star Tile CO Ltd",
    "wof:placetype":"venue"
},
  "geometry": {"coordinates":[-123.06115699999999,49.28133],"type":"Point"}
}