{
  "type": "Feature",
  "properties": {
    "iso:country":"CA",
    "sg:address":"650 Weber St N",
    "sg:city":"Waterloo",
    "sg:classifiers":[
        {
            "category":"Building & Trades",
            "subcategory":"Landscaping Services",
            "type":"Services"
        }
    ],
    "sg:phone":"+1 519 888 9992",
    "sg:postcode":"N2V 2N2",
    "sg:province":"ON",
    "sg:tags":[
        "equipment",
        "supply",
        "landscape",
        "contractor"
    ],
    "wof:name":"Kuntz Landscaping Depot",
    "wof:placetype":"venue"
},
  "geometry": {"coordinates":[-80.5544509888,43.5034866333],"type":"Point"}
}