{
  "type": "Feature",
  "properties": {
    "addr:full":"RR 2 STN Main Essex ON N8M 2X6",
    "addr:postcode":"n8m 2x6",
    "addr:street":"Rr 2 Stn Main",
    "iso:country":"CA",
    "sg:address":"RR 2 STN Main",
    "sg:city":"Essex",
    "sg:classifiers":[
        {
            "category":"Wholesale",
            "subcategory":"Construction Materials",
            "type":"Manufacturing & Wholesale Goods"
        }
    ],
    "sg:phone":"+1 519 776 6342",
    "sg:postcode":"N8M 2X6",
    "sg:province":"ON",
    "sg:tags":[
        "stakes"
    ],
    "wof:name":"G & R Stakes",
    "wof:placetype":"venue"
},
  "geometry": {"coordinates":[-82.819672,42.172825],"type":"Point"}
}