{
  "type": "Feature",
  "properties": {
    "addr:full":"8104 112 Ave NW Edmonton AB T5B 4W4",
    "addr:housenumber":"8104",
    "addr:postcode":"t5b 4w4",
    "addr:street":"112 Ave Nw",
    "iso:country":"CA",
    "sg:address":"8104 112 Ave NW",
    "sg:city":"Edmonton",
    "sg:classifiers":[
        {
            "category":"Restaurant",
            "type":"Food & Drink"
        }
    ],
    "sg:phone":"+1 780 477 5508",
    "sg:postcode":"T5B 4W4",
    "sg:province":"AB",
    "wof:name":"Subway Sandwiches & Salads",
    "wof:placetype":"venue"
},
  "geometry": {"coordinates":[-113.465919,53.561378],"type":"Point"}
}