{
  "type": "Feature",
  "properties": {
    "iso:country":"CA",
    "sg:city":"Toronto",
    "sg:classifiers":[
        {
            "category":"Professional",
            "subcategory":"Lawyer & Legal Services",
            "type":"Services"
        }
    ],
    "sg:phone":"+1 416 961 2868",
    "sg:postcode":"M4W 3E2",
    "sg:province":"ON",
    "sg:tags":[
        "attorney"
    ],
    "wof:name":"Fleming White & Burgess",
    "wof:placetype":"venue"
},
  "geometry": {"coordinates":[-79.3874282837,43.6702308655],"type":"Point"}
}