{
  "type": "Feature",
  "properties": {
    "iso:country":"CA",
    "sg:address":"471 Korah Rd",
    "sg:city":"Sault Ste Marie",
    "sg:classifiers":[
        {
            "category":"Home & Garden",
            "subcategory":"Building Materials",
            "type":"Retail Goods"
        }
    ],
    "sg:phone":"+1 705 759 0661",
    "sg:postcode":"P6C 4J1",
    "sg:province":"ON",
    "sg:tags":[
        "windows",
        "siding"
    ],
    "wof:name":"Home Siding Shop",
    "wof:placetype":"venue"
},
  "geometry": {"coordinates":[-84.36553955079999,46.5359992981],"type":"Point"}
}