{
  "type": "Feature",
  "properties": {
    "iso:country":"CA",
    "sg:address":"7931 Av Andre-Ampere",
    "sg:city":"Montreal",
    "sg:classifiers":[
        {
            "category":"Retail",
            "subcategory":"Laundry & Dry Cleaning",
            "type":"Services"
        }
    ],
    "sg:phone":"+1 514 648 5180",
    "sg:postcode":"H1E 3N1",
    "sg:province":"QC",
    "sg:tags":[
        "cleaners"
    ],
    "wof:name":"Nettoyeur Marie-Claire Enrg",
    "wof:placetype":"venue"
},
  "geometry": {"coordinates":[-73.59372711180001,45.6345558167],"type":"Point"}
}