{
  "type": "Feature",
  "properties": {
    "addr:full":"Surrey BC V3T 2W1",
    "addr:postcode":"v3t 2w1",
    "iso:country":"CA",
    "sg:city":"Surrey",
    "sg:classifiers":[
        {
            "category":"Shopping",
            "subcategory":"Gifts & Souvenirs",
            "type":"Retail Goods"
        }
    ],
    "sg:phone":"+1 604 585 0454",
    "sg:postcode":"V3T 2W1",
    "sg:province":"BC",
    "sg:tags":[
        "cards",
        "greeting"
    ],
    "wof:name":"Carlton Card Shop",
    "wof:placetype":"venue"
},
  "geometry": {"coordinates":[-122.830215454,49.105178833],"type":"Point"}
}