{
  "type": "Feature",
  "properties": {
    "addr:full":"10536 108 St NW Edmonton AB T5H 2Z9",
    "addr:housenumber":"10536",
    "addr:postcode":"t5h 2z9",
    "addr:street":"108 St Nw",
    "iso:country":"CA",
    "sg:address":"10536 108 St NW",
    "sg:city":"Edmonton",
    "sg:classifiers":[
        {
            "category":"Wholesale",
            "subcategory":"Hardware",
            "type":"Manufacturing & Wholesale Goods"
        }
    ],
    "sg:phone":"+1 780 420 0040",
    "sg:postcode":"T5H 2Z9",
    "sg:province":"AB",
    "sg:tags":[
        "system",
        "equipment",
        "heating",
        "heater"
    ],
    "wof:name":"Kehoe Equipment Ltd",
    "wof:placetype":"venue"
},
  "geometry": {"coordinates":[-113.50681299999999,53.548874],"type":"Point"}
}