{
  "type": "Feature",
  "properties": {
    "addr:full":"413 Central Port Mouton Rd Port Mouton NS B0T 1T0",
    "addr:housenumber":"413",
    "addr:postcode":"b0t 1t0",
    "addr:street":"Central Port Mouton Rd",
    "iso:country":"CA",
    "sg:address":"413 Central Port Mouton Rd",
    "sg:city":"Port Mouton",
    "sg:classifiers":[
        {
            "category":"Manufacturing",
            "subcategory":"Food",
            "type":"Manufacturing & Wholesale Goods"
        }
    ],
    "sg:phone":"+1 902 683 2044",
    "sg:postcode":"B0T 1T0",
    "sg:province":"NS",
    "sg:tags":[
        "seafood",
        "product",
        "fish",
        "prepared"
    ],
    "wof:name":"Blue Wave Seafoods Inc",
    "wof:placetype":"venue"
},
  "geometry": {"coordinates":[-64.841461,43.914589],"type":"Point"}
}