{
  "type": "Feature",
  "properties": {
    "addr:full":"105 Ainslie St N Cambridge ON N1R 3P2",
    "addr:housenumber":"105",
    "addr:postcode":"n1r 3p2",
    "addr:street":"Ainslie St N",
    "iso:country":"CA",
    "sg:address":"105 Ainslie St N",
    "sg:city":"Cambridge",
    "sg:classifiers":[
        {
            "category":"Personal",
            "subcategory":"Beauty Salon",
            "type":"Services"
        }
    ],
    "sg:phone":"+1 519 622 8183",
    "sg:postcode":"N1R 3P2",
    "sg:province":"ON",
    "wof:name":"Sarah's Spa of Aesthetics",
    "wof:placetype":"venue"
},
  "geometry": {"coordinates":[-80.3136978149,43.362285614],"type":"Point"}
}