{
  "type": "Feature",
  "properties": {
    "addr:full":"5255 Boul Arthur-Sauve Laval QC H7R 3X4",
    "addr:housenumber":"5255",
    "addr:postcode":"h7r 3x4",
    "addr:street":"Boul Arthur-Sauve",
    "iso:country":"CA",
    "sg:address":"5255 Boul Arthur-Sauve",
    "sg:city":"Laval",
    "sg:classifiers":[
        {
            "category":"Retail",
            "subcategory":"Auto Repair",
            "type":"Services"
        }
    ],
    "sg:phone":"+1 450 627 2727",
    "sg:postcode":"H7R 3X4",
    "sg:province":"QC",
    "sg:tags":[
        "repairing",
        "automobile",
        "parts",
        "supply"
    ],
    "wof:name":"Jean-Guy Breton Entreprises",
    "wof:placetype":"venue"
},
  "geometry": {"coordinates":[-73.867065,45.550579],"type":"Point"}
}