{
  "type": "Feature",
  "properties": {
    "addr:full":"6716 Montrose Rd Niagara Falls ON L2E 6S5",
    "addr:housenumber":"6716",
    "addr:postcode":"l2e 6s5",
    "addr:street":"Montrose Rd",
    "iso:country":"CA",
    "sg:address":"6716 Montrose Rd",
    "sg:city":"Niagara Falls",
    "sg:classifiers":[
        {
            "category":"Building & Trades",
            "subcategory":"Construction",
            "type":"Services"
        }
    ],
    "sg:phone":"+1 905 354 8225",
    "sg:postcode":"L2E 6S5",
    "sg:province":"ON",
    "sg:tags":[
        "excavating",
        "sewer",
        "contractor"
    ],
    "wof:name":"Sebben Construction",
    "wof:placetype":"venue"
},
  "geometry": {"coordinates":[-79.1227111816,43.0775527954],"type":"Point"}
}