{
  "type": "Feature",
  "properties": {
    "addr:full":"24 Av DE Gaspe E Saint-Jean-Port-Joli QC G0R 3G0",
    "addr:postcode":"g0r 3g0",
    "addr:street":"24 Av De Gaspe E",
    "iso:country":"CA",
    "sg:address":"24 Av DE Gaspe E",
    "sg:city":"Saint-Jean-Port-Joli",
    "sg:classifiers":[
        {
            "category":"Health Services",
            "subcategory":"Health Practitioner",
            "type":"Services"
        }
    ],
    "sg:phone":"+1 418 598 6560",
    "sg:postcode":"G0R 3G0",
    "sg:province":"QC",
    "sg:tags":[
        "homeopath"
    ],
    "wof:name":"Ardehq Inc",
    "wof:placetype":"venue"
},
  "geometry": {"coordinates":[-70.269058,47.215698],"type":"Point"}
}