{
  "type": "Feature",
  "properties": {
    "addr:full":"1038 Venture Way Gibsons BC V0N 1V7",
    "addr:housenumber":"1038",
    "addr:postcode":"v0n 1v7",
    "addr:street":"Venture Way",
    "iso:country":"CA",
    "sg:address":"1038 Venture Way",
    "sg:city":"Gibsons",
    "sg:classifiers":[
        {
            "category":"Manufacturing",
            "subcategory":"Watercraft",
            "type":"Manufacturing & Wholesale Goods"
        }
    ],
    "sg:phone":"+1 604 886 3004",
    "sg:postcode":"V0N 1V7",
    "sg:province":"BC",
    "sg:tags":[
        "boat"
    ],
    "wof:name":"Coastal Craft Welded Aluminum",
    "wof:placetype":"venue"
},
  "geometry": {"coordinates":[-123.527565,49.408356],"type":"Point"}
}