{
  "type": "Feature",
  "properties": {
    "iso:country":"CA",
    "sg:address":"12525 21st Ave",
    "sg:city":"Blairmore",
    "sg:classifiers":[
        {
            "category":"Government",
            "subcategory":"Office",
            "type":"Public Place"
        }
    ],
    "sg:phone":"+1 403 563 5633",
    "sg:postcode":"T0K 0E0",
    "sg:province":"AB",
    "sg:tags":[
        "village"
    ],
    "wof:name":"Crowsnest Pass Warehouse",
    "wof:placetype":"venue"
},
  "geometry": {"coordinates":[-114.44254303,49.6093635559],"type":"Point"}
}