{
  "type": "Feature",
  "properties": {
    "addr:full":"28 Ch DE LA Fabrique Trois-Pistoles QC G0L 4K0",
    "addr:housenumber":"28",
    "addr:postcode":"g0l 4k0",
    "addr:street":"Ch De La Fabrique",
    "iso:country":"CA",
    "sg:address":"28 Ch DE LA Fabrique",
    "sg:city":"Trois-Pistoles",
    "sg:classifiers":[
        {
            "category":"Health Services",
            "subcategory":"Nursing And Care Facility",
            "type":"Services"
        }
    ],
    "sg:phone":"+1 418 851 1376",
    "sg:postcode":"G0L 4K0",
    "sg:province":"QC",
    "sg:tags":[
        "home",
        "rest",
        "site",
        "reception",
        "wedding"
    ],
    "wof:name":"Centre D'Accueil Jesus Marie",
    "wof:placetype":"venue"
},
  "geometry": {"coordinates":[-69.1734085083,48.1251754761],"type":"Point"}
}