{
  "type": "Feature",
  "properties": {
    "addr:full":"425 Rue Hickson Verdun QC H4G 2J9",
    "addr:housenumber":"425",
    "addr:postcode":"h4g 2j9",
    "addr:street":"Rue Hickson",
    "iso:country":"CA",
    "sg:address":"425 Rue Hickson",
    "sg:city":"Verdun",
    "sg:classifiers":[
        {
            "category":"Restaurant",
            "type":"Food & Drink"
        }
    ],
    "sg:phone":"+1 514 766 5888",
    "sg:postcode":"H4G 2J9",
    "sg:province":"QC",
    "wof:name":"Restaurant Le Patio",
    "wof:placetype":"venue"
},
  "geometry": {"coordinates":[-73.5693283081,45.4651489258],"type":"Point"}
}