{
  "type": "Feature",
  "properties": {
    "iso:country":"CA",
    "sg:address":"227 Main St",
    "sg:city":"Port Dover",
    "sg:classifiers":[
        {
            "category":"Real Estate",
            "subcategory":"Real Estate Agent",
            "type":"Services"
        }
    ],
    "sg:phone":"+1 519 583 3555",
    "sg:postcode":"N0A 1N0",
    "sg:province":"ON",
    "wof:name":"Erie Shores Realty Inc",
    "wof:placetype":"venue"
},
  "geometry": {"coordinates":[-80.2022476196,42.7855644226],"type":"Point"}
}