{
  "type": "Feature",
  "properties": {
    "addr:full":"Regina SK S4P 0S4",
    "addr:postcode":"s4p 0s4",
    "iso:country":"CA",
    "sg:city":"Regina",
    "sg:classifiers":[
        {
            "category":"Shopping",
            "subcategory":"Department Store",
            "type":"Retail Goods"
        }
    ],
    "sg:phone":"+1 306 789 0777",
    "sg:postcode":"S4P 0S4",
    "sg:province":"SK",
    "wof:name":"Zellers",
    "wof:placetype":"venue"
},
  "geometry": {"coordinates":[-104.61264,50.446972],"type":"Point"}
}