{
  "type": "Feature",
  "properties": {
    "addr:full":"180 Rte Leclerc Saint-Edouard-DE-Lotbiniere QC G0S 1Y0",
    "addr:housenumber":"180",
    "addr:postcode":"g0s 1y0",
    "addr:street":"Rte Leclerc",
    "iso:country":"CA",
    "sg:address":"180 Rte Leclerc",
    "sg:city":"Saint-Edouard-DE-Lotbiniere",
    "sg:classifiers":[
        {
            "category":"Building & Trades",
            "subcategory":"Electrical",
            "type":"Services"
        }
    ],
    "sg:phone":"+1 418 888 1777",
    "sg:postcode":"G0S 1Y0",
    "sg:province":"QC",
    "sg:tags":[
        "electric",
        "contractor"
    ],
    "wof:name":"Groupe Gaetan Castonguay Inc",
    "wof:placetype":"venue"
},
  "geometry": {"coordinates":[-71.8335266113,46.567615509],"type":"Point"}
}