{
  "type": "Feature",
  "properties": {
    "addr:full":"318 Main St S Dauphin MB R7N 1K7",
    "addr:housenumber":"318",
    "addr:postcode":"r7n 1k7",
    "addr:street":"Main St S Dauphin",
    "iso:country":"CA",
    "sg:address":"318 Main St S",
    "sg:city":"Dauphin",
    "sg:classifiers":[
        {
            "category":"Shopping",
            "subcategory":"Hobbies, Toys, & Games",
            "type":"Retail Goods"
        }
    ],
    "sg:phone":"+1 204 638 4417",
    "sg:postcode":"R7N 1K7",
    "sg:province":"MB",
    "sg:tags":[
        "balloon",
        "craft",
        "artist",
        "supply"
    ],
    "wof:name":"Balloon Tycoons",
    "wof:placetype":"venue"
},
  "geometry": {"coordinates":[-100.052734,51.147099],"type":"Point"}
}