{
  "type": "Feature",
  "properties": {
    "iso:country":"CA",
    "sg:city":"Toronto",
    "sg:classifiers":[
        {
            "category":"Shopping",
            "subcategory":"Clothing, Apparel, & Fashions",
            "type":"Retail Goods"
        }
    ],
    "sg:phone":"+1 416 489 2631",
    "sg:postcode":"M4P 1E4",
    "sg:province":"ON",
    "wof:name":"Fairweather",
    "wof:placetype":"venue"
},
  "geometry": {"coordinates":[-79.3986358643,43.707244873],"type":"Point"}
}