{
  "type": "Feature",
  "properties": {
    "iso:country":"CA",
    "sg:address":"PO Box 8161 Rpo Marine Lake",
    "sg:city":"Cold Lake",
    "sg:classifiers":[
        {
            "category":"Professional",
            "subcategory":"Detective & Security Services",
            "type":"Services"
        }
    ],
    "sg:phone":"+1 780 594 3449",
    "sg:postcode":"T9M 1N1",
    "sg:province":"AB",
    "sg:tags":[
        "investigator"
    ],
    "wof:name":"Complete Investigations",
    "wof:placetype":"venue"
},
  "geometry": {"coordinates":[-110.173789978,54.4650268555],"type":"Point"}
}