{
  "type": "Feature",
  "properties": {
    "iso:country":"CA",
    "sg:address":"833 Armit Ave",
    "sg:city":"Fort Frances",
    "sg:classifiers":[
        {
            "category":"Building & Trades",
            "subcategory":"Construction",
            "type":"Services"
        }
    ],
    "sg:phone":"+1 807 274 9386",
    "sg:postcode":"P9A 2J5",
    "sg:province":"ON",
    "sg:tags":[
        "carpenter"
    ],
    "wof:name":"Herbert Brock Construction",
    "wof:placetype":"venue"
},
  "geometry": {"coordinates":[-93.38980865480001,48.6139945984],"type":"Point"}
}