{
  "type": "Feature",
  "properties": {
    "addr:full":"35 Main St N Latchford ON P0J 1N0",
    "addr:housenumber":"35",
    "addr:postcode":"p0j 1n0",
    "addr:street":"Main St N",
    "iso:country":"CA",
    "sg:address":"35 Main St N",
    "sg:city":"Latchford",
    "sg:classifiers":[
        {
            "category":"Travel",
            "subcategory":"Hotels & Motels",
            "type":"Entertainment"
        }
    ],
    "sg:phone":"+1 705 676 2424",
    "sg:postcode":"P0J 1N0",
    "sg:province":"ON",
    "wof:name":"Frontiersman Motel",
    "wof:placetype":"venue"
},
  "geometry": {"coordinates":[-79.811172,47.327068],"type":"Point"}
}