{
  "type": "Feature",
  "properties": {
    "addr:full":"Oshawa ON L1H 1J3",
    "addr:postcode":"l1h 1j3",
    "iso:country":"CA",
    "sg:city":"Oshawa",
    "sg:classifiers":[
        {
            "category":"Restaurant",
            "type":"Food & Drink"
        }
    ],
    "sg:phone":"+1 905 433 4614",
    "sg:postcode":"L1H 1J3",
    "sg:province":"ON",
    "sg:tags":[
        "out"
    ],
    "wof:name":"Square Boy Pizza",
    "wof:placetype":"venue"
},
  "geometry": {"coordinates":[-78.837418,43.904106],"type":"Point"}
}