{
  "type": "Feature",
  "properties": {
    "addr:full":"444 Av Dorval Dorval QC H9S 3H7",
    "addr:postcode":"h9s 3h7",
    "addr:street":"444 Av Dorval",
    "iso:country":"CA",
    "sg:address":"444 Av Dorval",
    "sg:city":"Dorval",
    "sg:classifiers":[
        {
            "category":"Restaurant",
            "type":"Food & Drink"
        }
    ],
    "sg:phone":"+1 514 636 6060",
    "sg:postcode":"H9S 3H7",
    "sg:province":"QC",
    "sg:tags":[
        "chicken",
        "dinner"
    ],
    "wof:name":"Rotisserie Scores",
    "wof:placetype":"venue"
},
  "geometry": {"coordinates":[-73.74128,45.444839],"type":"Point"}
}