{
  "type": "Feature",
  "properties": {
    "iso:country":"CA",
    "sg:address":"515 Beaverbrook Crt",
    "sg:city":"Fredericton",
    "sg:classifiers":[
        {
            "category":"Professional",
            "subcategory":"Engineering",
            "type":"Services"
        }
    ],
    "sg:phone":"+1 506 458 8425",
    "sg:postcode":"E3B 1X6",
    "sg:province":"NB",
    "sg:tags":[
        "engineer"
    ],
    "wof:name":"Peake Design Ltd",
    "wof:placetype":"venue"
},
  "geometry": {"coordinates":[-66.64711761469999,45.9544677734],"type":"Point"}
}