{
  "type": "Feature",
  "properties": {
    "addr:full":"380 Av Richard # 110 Rouyn-Noranda QC J9X 4L3",
    "addr:housenumber":"380",
    "addr:postcode":"j9x 4l3",
    "addr:street":"Av Richard # 110",
    "iso:country":"CA",
    "sg:address":"380 Av Richard # 110",
    "sg:city":"Rouyn-Noranda",
    "sg:classifiers":[
        {
            "category":"Social Services",
            "type":"Services"
        }
    ],
    "sg:phone":"+1 819 764 5243",
    "sg:postcode":"J9X 4L3",
    "sg:province":"QC",
    "sg:tags":[
        "organization",
        "welfare"
    ],
    "wof:name":"Maison DE LA Famille DE Rouyn",
    "wof:placetype":"venue"
},
  "geometry": {"coordinates":[-79.01593017579999,48.2326087952],"type":"Point"}
}