{
  "type": "Feature",
  "properties": {
    "addr:full":"2675 Mac St Gloucester ON K1V 7B4",
    "addr:housenumber":"2675",
    "addr:postcode":"k1v 7b4",
    "addr:street":"Mac St",
    "iso:country":"CA",
    "sg:address":"2675 Mac St",
    "sg:city":"Gloucester",
    "sg:classifiers":[
        {
            "category":"Retail",
            "subcategory":"Auto Repair",
            "type":"Services"
        }
    ],
    "sg:phone":"+1 613 731 2704",
    "sg:postcode":"K1V 7B4",
    "sg:province":"ON",
    "sg:tags":[
        "repairing",
        "automobile",
        "radiator"
    ],
    "wof:name":"Kemco Radiator Ltd",
    "wof:placetype":"venue"
},
  "geometry": {"coordinates":[-75.65022277830001,45.3484802246],"type":"Point"}
}