{
  "type": "Feature",
  "properties": {
    "addr:full":"1111 3rd Ave Prince George BC V2L 3E4",
    "addr:housenumber":"1111",
    "addr:postcode":"v2l 3e4",
    "addr:street":"3Rd Ave",
    "iso:country":"CA",
    "sg:address":"1111 3rd Ave",
    "sg:city":"Prince George",
    "sg:classifiers":[
        {
            "category":"Shopping",
            "subcategory":"Clothing, Apparel, & Fashions",
            "type":"Retail Goods"
        }
    ],
    "sg:phone":"+1 250 562 2949",
    "sg:postcode":"V2L 3E4",
    "sg:province":"BC",
    "sg:tags":[
        "furnishing"
    ],
    "wof:name":"Morrison's Men's Wear Ltd",
    "wof:placetype":"venue"
},
  "geometry": {"coordinates":[-122.743172,53.916035],"type":"Point"}
}