{
  "type": "Feature",
  "properties": {
    "addr:full":"2506 41 St Vernon BC V1T 6J9",
    "addr:housenumber":"2506",
    "addr:postcode":"v1t 6j9",
    "addr:street":"41 St",
    "iso:country":"CA",
    "sg:address":"2506 41 St",
    "sg:city":"Vernon",
    "sg:classifiers":[
        {
            "category":"Wholesale",
            "subcategory":"Books, Periodicals, & Newspapers",
            "type":"Manufacturing & Wholesale Goods"
        }
    ],
    "sg:phone":"+1 250 545 3235",
    "sg:postcode":"V1T 6J9",
    "sg:province":"BC",
    "sg:tags":[
        "magazine"
    ],
    "wof:name":"Monahan Agency Ltd",
    "wof:placetype":"venue"
},
  "geometry": {"coordinates":[-119.29193100000001,50.259594],"type":"Point"}
}