{
  "type": "Feature",
  "properties": {
    "addr:full":"150 Wissler Rd Waterloo ON N2K 3C6",
    "addr:housenumber":"150",
    "addr:postcode":"n2k 3c6",
    "addr:street":"Wissler Rd",
    "iso:country":"CA",
    "sg:address":"150 Wissler Rd",
    "sg:city":"Waterloo",
    "sg:classifiers":[
        {
            "category":"Food & Beverages",
            "subcategory":"Groceries & Convenience Stores",
            "type":"Retail Goods"
        }
    ],
    "sg:phone":"+1 519 746 2630",
    "sg:postcode":"N2K 3C6",
    "sg:province":"ON",
    "wof:name":"Northfield Mini Mart",
    "wof:placetype":"venue"
},
  "geometry": {"coordinates":[-80.52439099999999,43.505009],"type":"Point"}
}