{
  "type": "Feature",
  "properties": {
    "addr:full":"180 Peninsula Point Rd Tatamagouche NS B0K 1V0",
    "addr:housenumber":"180",
    "addr:postcode":"b0k 1v0",
    "addr:street":"Peninsula Point Rd",
    "iso:country":"CA",
    "sg:address":"180 Peninsula Point Rd",
    "sg:city":"Tatamagouche",
    "sg:classifiers":[
        {
            "category":"Travel",
            "subcategory":"Campground",
            "type":"Entertainment"
        }
    ],
    "sg:phone":"+1 902 657 0009",
    "sg:postcode":"B0K 1V0",
    "sg:province":"NS",
    "wof:name":"Sunset Watch",
    "wof:placetype":"venue"
},
  "geometry": {"coordinates":[-63.291798,45.71233],"type":"Point"}
}