{
  "type": "Feature",
  "properties": {
    "addr:full":"Toronto ON M6G 1A5",
    "addr:postcode":"m6g 1a5",
    "iso:country":"CA",
    "sg:city":"Toronto",
    "sg:classifiers":[
        {
            "category":"Manufacturing",
            "subcategory":"Printing",
            "type":"Manufacturing & Wholesale Goods"
        }
    ],
    "sg:phone":"+1 416 964 7799",
    "sg:postcode":"M6G 1A5",
    "sg:province":"ON",
    "sg:tags":[
        "publisher"
    ],
    "wof:name":"Sources Directory For the News",
    "wof:placetype":"venue"
},
  "geometry": {"coordinates":[-79.40935500000001,43.656036],"type":"Point"}
}