{
  "type": "Feature",
  "properties": {
    "addr:full":"50 Well St Stratford ON N5A 4L7",
    "addr:housenumber":"50",
    "addr:postcode":"n5a 4l7",
    "addr:street":"Well St",
    "iso:country":"CA",
    "sg:address":"50 Well St",
    "sg:city":"Stratford",
    "sg:classifiers":[
        {
            "category":"Organizations",
            "subcategory":"Religious Organization",
            "type":"Services"
        }
    ],
    "sg:phone":"+1 519 271 2434",
    "sg:postcode":"N5A 4L7",
    "sg:province":"ON",
    "sg:tags":[
        "church"
    ],
    "wof:name":"Immaculate Conception Church",
    "wof:placetype":"venue"
},
  "geometry": {"coordinates":[-80.97142028810001,43.3681602478],"type":"Point"}
}