{
  "type": "Feature",
  "properties": {
    "iso:country":"CA",
    "sg:address":"5961 Highway 17 W",
    "sg:city":"Whitefish",
    "sg:classifiers":[
        {
            "category":"Food & Beverages",
            "subcategory":"Groceries & Convenience Stores",
            "type":"Retail Goods"
        }
    ],
    "sg:phone":"+1 705 866 0001",
    "sg:postcode":"P0M 3E0",
    "sg:province":"ON",
    "sg:tags":[
        "grocer"
    ],
    "wof:name":"Blueberry Station",
    "wof:placetype":"venue"
},
  "geometry": {"coordinates":[-81.31559753419999,46.3781814575],"type":"Point"}
}