{
  "type": "Feature",
  "properties": {
    "addr:full":"209 Rte Du Village Rapide-Danseur QC J0Z 3G0",
    "addr:housenumber":"209",
    "addr:postcode":"j0z 3g0",
    "addr:street":"Rte Du Village",
    "iso:country":"CA",
    "sg:address":"209 Rte Du Village",
    "sg:city":"Rapide-Danseur",
    "sg:classifiers":[
        {
            "category":"Travel",
            "subcategory":"Campground",
            "type":"Entertainment"
        }
    ],
    "sg:phone":"+1 819 948 2323",
    "sg:postcode":"J0Z 3G0",
    "sg:province":"QC",
    "sg:tags":[
        "camp",
        "fishing"
    ],
    "wof:name":"Pourvoirie Du Portage",
    "wof:placetype":"venue"
},
  "geometry": {"coordinates":[-79.29370900000001,48.544376],"type":"Point"}
}