{
  "type": "Feature",
  "properties": {
    "addr:full":"46 Hale Rd Brampton ON L6W 3M1",
    "addr:housenumber":"46",
    "addr:postcode":"l6w 3m1",
    "addr:street":"Hale Rd",
    "iso:country":"CA",
    "sg:address":"46 Hale Rd",
    "sg:city":"Brampton",
    "sg:classifiers":[
        {
            "category":"Professional",
            "subcategory":"Art Services",
            "type":"Services"
        }
    ],
    "sg:phone":"+1 905 454 2900",
    "sg:postcode":"L6W 3M1",
    "sg:province":"ON",
    "sg:tags":[
        "development",
        "package",
        "designing"
    ],
    "wof:name":"Dopaco Canada Inc",
    "wof:placetype":"venue"
},
  "geometry": {"coordinates":[-79.720528,43.685764],"type":"Point"}
}