{
  "type": "Feature",
  "properties": {
    "addr:full":"Hanover ON N4N 1S2",
    "addr:postcode":"n4n 1s2",
    "iso:country":"CA",
    "sg:city":"Hanover",
    "sg:classifiers":[
        {
            "category":"Food & Beverages",
            "subcategory":"Meat & Fish",
            "type":"Retail Goods"
        }
    ],
    "sg:phone":"+1 519 364 7747",
    "sg:postcode":"N4N 1S2",
    "sg:province":"ON",
    "sg:tags":[
        "frozen"
    ],
    "wof:name":"M & M Meat Shops",
    "wof:placetype":"venue"
},
  "geometry": {"coordinates":[-81.01205400000001,44.154667],"type":"Point"}
}