{
  "type": "Feature",
  "properties": {
    "addr:full":"Calgary AB T2G 2L2",
    "addr:postcode":"t2g 2l2",
    "iso:country":"CA",
    "sg:city":"Calgary",
    "sg:classifiers":[
        {
            "category":"Retail",
            "subcategory":"Repair Shop",
            "type":"Services"
        }
    ],
    "sg:phone":"+1 403 243 2032",
    "sg:postcode":"T2G 2L2",
    "sg:province":"AB",
    "sg:tags":[
        "lock",
        "locksmith"
    ],
    "wof:name":"Head's Lock & Key Works Ltd",
    "wof:placetype":"venue"
},
  "geometry": {"coordinates":[-114.06150100000001,51.015675],"type":"Point"}
}