{
  "type": "Feature",
  "properties": {
    "addr:full":"360 Elgin St # A Ottawa ON K2P 1M8",
    "addr:housenumber":"360",
    "addr:postcode":"k2p 1m8",
    "addr:street":"Elgin St # A",
    "iso:country":"CA",
    "sg:address":"360 Elgin St # A",
    "sg:city":"Ottawa",
    "sg:classifiers":[
        {
            "category":"Restaurant",
            "type":"Food & Drink"
        }
    ],
    "sg:phone":"+1 613 232 6274",
    "sg:postcode":"K2P 1M8",
    "sg:province":"ON",
    "wof:name":"Mash",
    "wof:placetype":"venue"
},
  "geometry": {"coordinates":[-75.6883926392,45.4153327942],"type":"Point"}
}