{
  "type": "Feature",
  "properties": {
    "addr:full":"Campbell River BC V9W 1R2",
    "addr:postcode":"v9w 1r2",
    "iso:country":"CA",
    "sg:city":"Campbell River",
    "sg:classifiers":[
        {
            "category":"Professional",
            "subcategory":"Accounting & Tax Preparation",
            "type":"Services"
        }
    ],
    "sg:phone":"+1 250 923 2578",
    "sg:postcode":"V9W 1R2",
    "sg:province":"BC",
    "sg:tags":[
        "accountant"
    ],
    "wof:name":"Darrell M Tomlinson Inc",
    "wof:placetype":"venue"
},
  "geometry": {"coordinates":[-125.21772799999999,49.970814],"type":"Point"}
}