{
  "type": "Feature",
  "properties": {
    "addr:full":"1374 Benjamin Ave Windsor ON N8X 4M9",
    "addr:housenumber":"1374",
    "addr:postcode":"n8x 4m9",
    "addr:street":"Benjamin Ave",
    "iso:country":"CA",
    "sg:address":"1374 Benjamin Ave",
    "sg:city":"Windsor",
    "sg:classifiers":[
        {
            "category":"Organizations",
            "subcategory":"Religious Organization",
            "type":"Services"
        }
    ],
    "sg:phone":"+1 519 252 9236",
    "sg:postcode":"N8X 4M9",
    "sg:province":"ON",
    "wof:name":"Madonna House",
    "wof:placetype":"venue"
},
  "geometry": {"coordinates":[-83.013611,42.307903],"type":"Point"}
}