{
  "type": "Feature",
  "properties": {
    "addr:full":"1360 Kelly Lake Rd Sudbury ON P3E 5P4",
    "addr:housenumber":"1360",
    "addr:postcode":"p3e 5p4",
    "addr:street":"Kelly Lake Rd",
    "iso:country":"CA",
    "sg:address":"1360 Kelly Lake Rd",
    "sg:city":"Sudbury",
    "sg:classifiers":[
        {
            "category":"Building & Trades",
            "subcategory":"Construction",
            "type":"Services"
        }
    ],
    "sg:phone":"+1 705 522 9096",
    "sg:postcode":"P3E 5P4",
    "sg:province":"ON",
    "sg:tags":[
        "masonry",
        "contractor"
    ],
    "wof:name":"Corfab CO Ltd",
    "wof:placetype":"venue"
},
  "geometry": {"coordinates":[-81.0300979614,46.4651451111],"type":"Point"}
}