{
  "type": "Feature",
  "properties": {
    "addr:full":"8288 Boul Maurice-Duplessis Montreal QC H1E 3A3",
    "addr:housenumber":"8288",
    "addr:postcode":"h1e 3a3",
    "addr:street":"Boul Maurice-Duplessis",
    "iso:country":"CA",
    "sg:address":"8288 Boul Maurice-Duplessis",
    "sg:city":"Montreal",
    "sg:classifiers":[
        {
            "category":"Home & Garden",
            "subcategory":"Hardware",
            "type":"Retail Goods"
        }
    ],
    "sg:phone":"+1 514 648 1325",
    "sg:postcode":"H1E 3A3",
    "sg:province":"QC",
    "wof:name":"Maison Decor 2000",
    "wof:placetype":"venue"
},
  "geometry": {"coordinates":[-73.584846,45.634743],"type":"Point"}
}