{
  "type": "Feature",
  "properties": {
    "addr:full":"17035 Boul Brunswick Kirkland QC H9H 5G6",
    "addr:housenumber":"17035",
    "addr:postcode":"h9h 5g6",
    "addr:street":"Boul Brunswick",
    "iso:country":"CA",
    "sg:address":"17035 Boul Brunswick",
    "sg:city":"Kirkland",
    "sg:classifiers":[
        {
            "category":"Organizations",
            "subcategory":"Professional Association",
            "type":"Services"
        }
    ],
    "sg:phone":"+1 514 694 9777",
    "sg:postcode":"H9H 5G6",
    "sg:province":"QC",
    "wof:name":"Provincial Assn-Teachers",
    "wof:placetype":"venue"
},
  "geometry": {"coordinates":[-73.8482055664,45.4591217041],"type":"Point"}
}