{
  "type": "Feature",
  "properties": {
    "addr:full":"Whitney ON K0J 2M0",
    "addr:postcode":"k0j 2m0",
    "iso:country":"CA",
    "sg:city":"Whitney",
    "sg:classifiers":[
        {
            "category":"Government",
            "subcategory":"Office",
            "type":"Public Place"
        }
    ],
    "sg:phone":"+1 613 637 1087",
    "sg:postcode":"K0J 2M0",
    "sg:province":"ON",
    "sg:tags":[
        "village"
    ],
    "wof:name":"Municipal Garages",
    "wof:placetype":"venue"
},
  "geometry": {"coordinates":[-78.24499511720001,45.4991912842],"type":"Point"}
}