{
  "type": "Feature",
  "properties": {
    "addr:full":"Lloydminster AB T9V 0A7",
    "addr:postcode":"t9v 0a7",
    "iso:country":"CA",
    "sg:city":"Lloydminster",
    "sg:classifiers":[
        {
            "category":"Social Services",
            "type":"Services"
        }
    ],
    "sg:phone":"+1 780 875 3571",
    "sg:postcode":"T9V 0A7",
    "sg:province":"AB",
    "sg:tags":[
        "information",
        "organization",
        "treatment",
        "alcoholism",
        "welfare"
    ],
    "wof:name":"Alcoholics Anonymous",
    "wof:placetype":"venue"
},
  "geometry": {"coordinates":[-110.011002,53.277935],"type":"Point"}
}