{
  "type": "Feature",
  "properties": {
    "iso:country":"CA",
    "sg:address":"100 Stephen St",
    "sg:city":"Morden",
    "sg:classifiers":[
        {
            "category":"Home & Garden",
            "subcategory":"Carpets & Floor Coverings",
            "type":"Retail Goods"
        }
    ],
    "sg:phone":"+1 204 822 4616",
    "sg:postcode":"R6M 1T3",
    "sg:province":"MB",
    "sg:tags":[
        "dealer",
        "rug"
    ],
    "wof:name":"Vern's Carpets Inc",
    "wof:placetype":"venue"
},
  "geometry": {"coordinates":[-98.0952301025,49.1898536682],"type":"Point"}
}