{
  "type": "Feature",
  "properties": {
    "addr:full":"North Vancouver BC V7M 1B5",
    "addr:postcode":"v7m 1b5",
    "iso:country":"CA",
    "sg:city":"North Vancouver",
    "sg:classifiers":[
        {
            "category":"Professional",
            "subcategory":"Advertising",
            "type":"Services"
        }
    ],
    "sg:phone":"+1 604 987 8401",
    "sg:postcode":"V7M 1B5",
    "sg:province":"BC",
    "sg:tags":[
        "counselor"
    ],
    "wof:name":"Creative Wonders Comm Inc",
    "wof:placetype":"venue"
},
  "geometry": {"coordinates":[-123.085166931,49.3145294189],"type":"Point"}
}