{
  "type": "Feature",
  "properties": {
    "iso:country":"CA",
    "sg:address":"6969 Boul Saint-Laurent",
    "sg:city":"Montreal",
    "sg:classifiers":[
        {
            "category":"Shopping",
            "subcategory":"Jewelry",
            "type":"Retail Goods"
        }
    ],
    "sg:phone":"+1 514 278 9597",
    "sg:postcode":"H2S 3E1",
    "sg:province":"QC",
    "sg:tags":[
        "jeweler"
    ],
    "wof:name":"Joaillerie Oritalia",
    "wof:placetype":"venue"
},
  "geometry": {"coordinates":[-73.6150436401,45.5333824158],"type":"Point"}
}