{
  "type": "Feature",
  "properties": {
    "addr:full":"5200 Robinson St Niagara Falls ON L2G 2A2",
    "addr:housenumber":"5200",
    "addr:postcode":"l2g 2a2",
    "addr:street":"Robinson St",
    "iso:country":"CA",
    "sg:address":"5200 Robinson St",
    "sg:city":"Niagara Falls",
    "sg:classifiers":[
        {
            "category":"Shopping",
            "subcategory":"Gifts & Souvenirs",
            "type":"Retail Goods"
        }
    ],
    "sg:phone":"+1 905 353 0021",
    "sg:postcode":"L2G 2A2",
    "sg:province":"ON",
    "sg:tags":[
        "shop"
    ],
    "wof:name":"International Gifts",
    "wof:placetype":"venue"
},
  "geometry": {"coordinates":[-79.07971999999999,43.086399],"type":"Point"}
}