{
  "type": "Feature",
  "properties": {
    "addr:full":"15319 116 Ave NW Edmonton AB T5M 3Z5",
    "addr:housenumber":"15319",
    "addr:postcode":"t5m 3z5",
    "addr:street":"116 Ave Nw",
    "iso:country":"CA",
    "sg:address":"15319 116 Ave NW",
    "sg:city":"Edmonton",
    "sg:classifiers":[
        {
            "category":"Manufacturing",
            "subcategory":"Signs",
            "type":"Manufacturing & Wholesale Goods"
        }
    ],
    "sg:phone":"+1 780 451 5400",
    "sg:postcode":"T5M 3Z5",
    "sg:province":"AB",
    "wof:name":"Alberta Neon Ltd",
    "wof:placetype":"venue"
},
  "geometry": {"coordinates":[-113.58562499999999,53.567822],"type":"Point"}
}