{
  "type": "Feature",
  "properties": {
    "addr:full":"6334 Rue Sherbrooke O Montreal QC H4B 1M7",
    "addr:housenumber":"6334",
    "addr:postcode":"h4b 1m7",
    "addr:street":"Rue Sherbrooke O",
    "iso:country":"CA",
    "sg:address":"6334 Rue Sherbrooke O",
    "sg:city":"Montreal",
    "sg:classifiers":[
        {
            "category":"Restaurant",
            "type":"Food & Drink"
        }
    ],
    "sg:phone":"+1 514 369 4222",
    "sg:postcode":"H4B 1M7",
    "sg:province":"QC",
    "wof:name":"Subway Sandwiches & Salads",
    "wof:placetype":"venue"
},
  "geometry": {"coordinates":[-73.544593811,45.5797767639],"type":"Point"}
}