{
  "type": "Feature",
  "properties": {
    "addr:full":"Montreal QC H2T 1X1",
    "addr:postcode":"h2t 1x1",
    "iso:country":"CA",
    "sg:city":"Montreal",
    "sg:classifiers":[
        {
            "category":"Restaurant",
            "type":"Food & Drink"
        }
    ],
    "sg:phone":"+1 514 270 2555",
    "sg:postcode":"H2T 1X1",
    "sg:province":"QC",
    "wof:name":"Au Coin DE Casgrain",
    "wof:placetype":"venue"
},
  "geometry": {"coordinates":[-73.594223,45.52562],"type":"Point"}
}