{
  "type": "Feature",
  "properties": {
    "addr:full":"Grand Falls NB E3Z 3E9",
    "addr:postcode":"e3z 3e9",
    "iso:country":"CA",
    "sg:city":"Grand Falls",
    "sg:classifiers":[
        {
            "category":"Building & Trades",
            "subcategory":"Plumbing",
            "type":"Services"
        }
    ],
    "sg:phone":"+1 506 473 4477",
    "sg:postcode":"E3Z 3E9",
    "sg:province":"NB",
    "sg:tags":[
        "septic"
    ],
    "wof:name":"Sani Way Inc",
    "wof:placetype":"venue"
},
  "geometry": {"coordinates":[-67.754707,47.061417],"type":"Point"}
}