{
  "type": "Feature",
  "properties": {
    "iso:country":"CA",
    "sg:city":"Mississauga",
    "sg:classifiers":[
        {
            "category":"Social Services",
            "subcategory":"Job Training",
            "type":"Services"
        }
    ],
    "sg:phone":"+1 905 795 0079",
    "sg:postcode":"L5T 2E1",
    "sg:province":"ON",
    "sg:tags":[
        "rehabilitation"
    ],
    "wof:name":"Total Rehabilitation Mgmt Inc",
    "wof:placetype":"venue"
},
  "geometry": {"coordinates":[-79.6530303955,43.6591415405],"type":"Point"}
}