{
  "type": "Feature",
  "properties": {
    "addr:full":"1050 Boul Casavant O # 1000 Saint-Hyacinthe QC J2S 8B9",
    "addr:housenumber":"1050",
    "addr:postcode":"j2s 8b9",
    "addr:street":"Boul Casavant O # 1000",
    "iso:country":"CA",
    "sg:address":"1050 Boul Casavant O # 1000",
    "sg:city":"Saint-Hyacinthe",
    "sg:classifiers":[
        {
            "category":"Banks & Credit Unions",
            "subcategory":"Bank",
            "type":"Services"
        }
    ],
    "sg:phone":"+1 450 771 3800",
    "sg:postcode":"J2S 8B9",
    "sg:province":"QC",
    "wof:name":"Banque Royale",
    "wof:placetype":"venue"
},
  "geometry": {"coordinates":[-72.9552993774,45.6448097229],"type":"Point"}
}