{
  "type": "Feature",
  "properties": {
    "addr:full":"3047 Mcnaughton Ave Mississauga ON L4T 1R8",
    "addr:housenumber":"3047",
    "addr:postcode":"l4t 1r8",
    "addr:street":"Mcnaughton Ave",
    "iso:country":"CA",
    "sg:address":"3047 Mcnaughton Ave",
    "sg:city":"Mississauga",
    "sg:classifiers":[
        {
            "category":"Shopping",
            "subcategory":"Computers & Home Electronics",
            "type":"Retail Goods"
        }
    ],
    "sg:phone":"+1 905 677 6478",
    "sg:postcode":"L4T 1R8",
    "sg:province":"ON",
    "sg:tags":[
        "television",
        "radio"
    ],
    "wof:name":"Elliott Tv",
    "wof:placetype":"venue"
},
  "geometry": {"coordinates":[-79.646164,43.707886],"type":"Point"}
}