{
  "type": "Feature",
  "properties": {
    "addr:full":"14 Pl Daviault Fermont QC G0G 1J0",
    "addr:housenumber":"14",
    "addr:postcode":"g0g 1j0",
    "addr:street":"Pl Daviault",
    "iso:country":"CA",
    "sg:address":"14 Pl Daviault",
    "sg:city":"Fermont",
    "sg:classifiers":[
        {
            "category":"Shopping",
            "subcategory":"Pharmacy",
            "type":"Retail Goods"
        }
    ],
    "sg:phone":"+1 418 287 5732",
    "sg:postcode":"G0G 1J0",
    "sg:province":"QC",
    "wof:name":"Pharmacie Francois Alarie",
    "wof:placetype":"venue"
},
  "geometry": {"coordinates":[-67.09191894529999,52.8022956848],"type":"Point"}
}