{
  "type": "Feature",
  "properties": {
    "addr:full":"126 Martin St N Almonte ON K0A 1A0",
    "addr:housenumber":"126",
    "addr:postcode":"k0a 1a0",
    "addr:street":"Martin St N",
    "iso:country":"CA",
    "sg:address":"126 Martin St N",
    "sg:city":"Almonte",
    "sg:classifiers":[
        {
            "category":"Education",
            "subcategory":"School",
            "type":"Public Place"
        }
    ],
    "sg:phone":"+1 613 256 1470",
    "sg:postcode":"K0A 1A0",
    "sg:province":"ON",
    "wof:name":"Almonte & District High School",
    "wof:placetype":"venue"
},
  "geometry": {"coordinates":[-76.1962738037,45.2318382263],"type":"Point"}
}