{
  "type": "Feature",
  "properties": {
    "addr:full":"10421 10 St Dawson Creek BC V1G 3T8",
    "addr:housenumber":"10421",
    "addr:postcode":"v1g 3t8",
    "addr:street":"10 St",
    "iso:country":"CA",
    "sg:address":"10421 10 St",
    "sg:city":"Dawson Creek",
    "sg:classifiers":[
        {
            "category":"Real Estate",
            "subcategory":"Real Estate Agent",
            "type":"Services"
        }
    ],
    "sg:phone":"+1 250 782 1598",
    "sg:postcode":"V1G 3T8",
    "sg:province":"BC",
    "sg:tags":[
        "authorities",
        "housing"
    ],
    "wof:name":"Dawson Creek Native Housing",
    "wof:placetype":"venue"
},
  "geometry": {"coordinates":[-120.230812073,55.7561798096],"type":"Point"}
}