{
  "type": "Feature",
  "properties": {
    "addr:full":"265 Shawville Blvd SE Calgary AB T2Y 3H9",
    "addr:housenumber":"265",
    "addr:postcode":"t2y 3h9",
    "addr:street":"Shawville Blvd Se",
    "iso:country":"CA",
    "sg:address":"265 Shawville Blvd SE",
    "sg:city":"Calgary",
    "sg:classifiers":[
        {
            "category":"Restaurant",
            "type":"Food & Drink"
        }
    ],
    "sg:phone":"+1 403 254 1902",
    "sg:postcode":"T2Y 3H9",
    "sg:province":"AB",
    "wof:name":"Swiss Chalet Rotisserie/Grill",
    "wof:placetype":"venue"
},
  "geometry": {"coordinates":[-114.06496429400001,50.9016838074],"type":"Point"}
}