{
  "type": "Feature",
  "properties": {
    "addr:full":"60 Mcculloch Ave Etobicoke ON M9W 4M6",
    "addr:housenumber":"60",
    "addr:postcode":"m9w 4m6",
    "addr:street":"Mcculloch Ave",
    "iso:country":"CA",
    "sg:address":"60 Mcculloch Ave",
    "sg:city":"Etobicoke",
    "sg:classifiers":[
        {
            "category":"Local Transit",
            "type":"Transportation"
        }
    ],
    "sg:phone":"+1 416 244 5341",
    "sg:postcode":"M9W 4M6",
    "sg:province":"ON",
    "sg:tags":[
        "bus",
        "line"
    ],
    "wof:name":"Stock Transportation Ltd",
    "wof:placetype":"venue"
},
  "geometry": {"coordinates":[-79.57254,43.701256],"type":"Point"}
}