{
  "type": "Feature",
  "properties": {
    "addr:full":"170 Boul Laurier Laurier-Station QC G0S 1N0",
    "addr:housenumber":"170",
    "addr:postcode":"g0s 1n0",
    "addr:street":"Boul Laurier",
    "iso:country":"CA",
    "sg:address":"170 Boul Laurier",
    "sg:city":"Laurier-Station",
    "sg:classifiers":[
        {
            "category":"Personal",
            "subcategory":"Beauty Salon",
            "type":"Services"
        }
    ],
    "sg:phone":"+1 418 728 4525",
    "sg:postcode":"G0S 1N0",
    "sg:province":"QC",
    "wof:name":"Salon Des Jumelles",
    "wof:placetype":"venue"
},
  "geometry": {"coordinates":[-71.62887600000001,46.542725],"type":"Point"}
}