{
  "type": "Feature",
  "properties": {
    "addr:full":"649 Winblest Ave London ON N6C 3C6",
    "addr:housenumber":"649",
    "addr:postcode":"n6c 3c6",
    "addr:street":"Winblest Ave",
    "iso:country":"CA",
    "sg:address":"649 Winblest Ave",
    "sg:city":"London",
    "sg:classifiers":[
        {
            "category":"Personal",
            "type":"Services"
        }
    ],
    "sg:phone":"+1 519 690 2860",
    "sg:postcode":"N6C 3C6",
    "sg:province":"ON",
    "sg:tags":[
        "electrolysis"
    ],
    "wof:name":"Jean Hudson Electrolysis",
    "wof:placetype":"venue"
},
  "geometry": {"coordinates":[-81.229332,42.944382],"type":"Point"}
}