{
  "type": "Feature",
  "properties": {
    "addr:full":"26 Mccourt Close Conception Bay South NL A1X 1H9",
    "addr:housenumber":"26",
    "addr:postcode":"a1x 1h9",
    "addr:street":"Mccourt Close",
    "iso:country":"CA",
    "sg:address":"26 Mccourt Close",
    "sg:city":"Conception Bay South",
    "sg:classifiers":[
        {
            "category":"Professional",
            "subcategory":"Management & Consulting",
            "type":"Services"
        }
    ],
    "sg:phone":"+1 709 834 6272",
    "sg:postcode":"A1X 1H9",
    "sg:province":"NL",
    "sg:tags":[
        "consultant",
        "educational"
    ],
    "wof:name":"North Atlantic Telelearning",
    "wof:placetype":"venue"
},
  "geometry": {"coordinates":[-53.023129,47.485481],"type":"Point"}
}