{
  "type": "Feature",
  "properties": {
    "addr:full":"14200 Entertainment Blvd # 150 Richmond BC V6W 1K3",
    "addr:housenumber":"14200;150",
    "addr:postcode":"v6w 1k3",
    "addr:street":"Entertainment Blvd #",
    "iso:country":"CA",
    "sg:address":"14200 Entertainment Blvd # 150",
    "sg:city":"Richmond",
    "sg:classifiers":[
        {
            "category":"Sports & Exercise",
            "subcategory":"Bowling",
            "type":"Entertainment"
        }
    ],
    "sg:phone":"+1 604 271 2695",
    "sg:postcode":"V6W 1K3",
    "sg:province":"BC",
    "sg:tags":[
        "center"
    ],
    "wof:name":"Zone Bowling Ctr",
    "wof:placetype":"venue"
},
  "geometry": {"coordinates":[-123.065971,49.133762],"type":"Point"}
}