{
  "type": "Feature",
  "properties": {
    "addr:full":"158 Sackville Rd Sault Ste Marie ON P6B 4T6",
    "addr:housenumber":"158",
    "addr:postcode":"p6b 4t6",
    "addr:street":"Sackville Rd",
    "iso:country":"CA",
    "sg:address":"158 Sackville Rd",
    "sg:city":"Sault Ste Marie",
    "sg:classifiers":[
        {
            "category":"Building & Trades",
            "subcategory":"Electrical",
            "type":"Services"
        }
    ],
    "sg:phone":"+1 705 942 3043",
    "sg:postcode":"P6B 4T6",
    "sg:province":"ON",
    "sg:tags":[
        "electric",
        "contractor"
    ],
    "wof:name":"S & T Group",
    "wof:placetype":"venue"
},
  "geometry": {"coordinates":[-84.329567,46.544037],"type":"Point"}
}