{
  "type": "Feature",
  "properties": {
    "addr:full":"44 Rue Saint-Louis Saint-Eustache QC J7R 1X7",
    "addr:housenumber":"44",
    "addr:postcode":"j7r 1x7",
    "addr:street":"Rue Saint-Louis",
    "iso:country":"CA",
    "sg:address":"44 Rue Saint-Louis",
    "sg:city":"Saint-Eustache",
    "sg:classifiers":[
        {
            "category":"Shopping",
            "subcategory":"Clothing, Apparel, & Fashions",
            "type":"Retail Goods"
        }
    ],
    "sg:phone":"+1 450 472 9307",
    "sg:postcode":"J7R 1X7",
    "sg:province":"QC",
    "wof:name":"Au Parfum DE LA Mode",
    "wof:placetype":"venue"
},
  "geometry": {"coordinates":[-73.8923416138,45.5546875],"type":"Point"}
}