{
  "type": "Feature",
  "properties": {
    "addr:full":"1260 Ch Du Fleuve Les Cedres QC J7T 1C4",
    "addr:housenumber":"1260",
    "addr:postcode":"j7t 1c4",
    "addr:street":"Ch Du Fleuve",
    "iso:country":"CA",
    "sg:address":"1260 Ch Du Fleuve",
    "sg:city":"Les Cedres",
    "sg:classifiers":[
        {
            "category":"Retail",
            "subcategory":"Funeral Services",
            "type":"Services"
        }
    ],
    "sg:phone":"+1 450 452 4435",
    "sg:postcode":"J7T 1C4",
    "sg:province":"QC",
    "sg:tags":[
        "director"
    ],
    "wof:name":"Ernest Montpetit & Fils Inc",
    "wof:placetype":"venue"
},
  "geometry": {"coordinates":[-74.0599975586,45.3086662292],"type":"Point"}
}