{
  "type": "Feature",
  "properties": {
    "addr:full":"563 Kennedy Rd Scarborough ON M1K 2B1",
    "addr:housenumber":"563",
    "addr:postcode":"m1k 2b1",
    "addr:street":"Kennedy Rd",
    "iso:country":"CA",
    "sg:address":"563 Kennedy Rd",
    "sg:city":"Scarborough",
    "sg:classifiers":[
        {
            "category":"Autos & Motor Vehicles",
            "subcategory":"Automobile Sales",
            "type":"Retail Goods"
        }
    ],
    "sg:phone":"+1 416 261 8999",
    "sg:postcode":"M1K 2B1",
    "sg:province":"ON",
    "sg:tags":[
        "car",
        "dealer"
    ],
    "wof:name":"General Car Sales",
    "wof:placetype":"venue"
},
  "geometry": {"coordinates":[-79.263474,43.722271],"type":"Point"}
}