{
  "type": "Feature",
  "properties": {
    "iso:country":"CA",
    "sg:address":"1330 Rue Jarry E",
    "sg:city":"Montreal",
    "sg:classifiers":[
        {
            "category":"Autos & Motor Vehicles",
            "subcategory":"Fuel & Gas Station",
            "type":"Retail Goods"
        }
    ],
    "sg:phone":"+1 514 722 8311",
    "sg:postcode":"H2E 1A4",
    "sg:province":"QC",
    "sg:tags":[
        "oil"
    ],
    "wof:name":"Garage Pare Cote Inc",
    "wof:placetype":"venue"
},
  "geometry": {"coordinates":[-73.6216049194,45.5501098633],"type":"Point"}
}