{
  "type": "Feature",
  "properties": {
    "iso:country":"CA",
    "sg:city":"Prince George",
    "sg:classifiers":[
        {
            "category":"Health Services",
            "subcategory":"Doctor",
            "type":"Services"
        }
    ],
    "sg:phone":"+1 250 564 8869",
    "sg:postcode":"V2L 2L6",
    "sg:province":"BC",
    "sg:tags":[
        "physician",
        "surgeon"
    ],
    "wof:name":"Kingston, William MD",
    "wof:placetype":"venue"
},
  "geometry": {"coordinates":[-122.755424499,53.9075775146],"type":"Point"}
}