{
  "type": "Feature",
  "properties": {
    "addr:full":"1130 Rue DE LA Manic Chicoutimi QC G7K 1A2",
    "addr:housenumber":"1130",
    "addr:postcode":"g7k 1a2",
    "addr:street":"Rue De La Manic",
    "iso:country":"CA",
    "sg:address":"1130 Rue DE LA Manic",
    "sg:city":"Chicoutimi",
    "sg:classifiers":[
        {
            "category":"Manufacturing",
            "subcategory":"Metals",
            "type":"Manufacturing & Wholesale Goods"
        }
    ],
    "sg:phone":"+1 418 543 2000",
    "sg:postcode":"G7K 1A2",
    "sg:province":"QC",
    "sg:tags":[
        "plate",
        "system",
        "air",
        "tin",
        "conditioning",
        "contractor"
    ],
    "wof:name":"Ferblanterie 2000 Inc",
    "wof:placetype":"venue"
},
  "geometry": {"coordinates":[-71.109596,48.397041],"type":"Point"}
}