{
  "type": "Feature",
  "properties": {
    "addr:full":"Toronto ON M4V 2L1",
    "addr:postcode":"m4v 2l1",
    "iso:country":"CA",
    "sg:city":"Toronto",
    "sg:classifiers":[
        {
            "category":"Professional",
            "subcategory":"Business Services",
            "type":"Services"
        }
    ],
    "sg:phone":"+1 416 961 7153",
    "sg:postcode":"M4V 2L1",
    "sg:province":"ON",
    "sg:tags":[
        "interior",
        "consultant",
        "design",
        "decorator"
    ],
    "wof:name":"Ivey Design Concepts Ltd",
    "wof:placetype":"venue"
},
  "geometry": {"coordinates":[-79.4004211426,43.6822853088],"type":"Point"}
}