{
  "type": "Feature",
  "properties": {
    "iso:country":"CA",
    "sg:address":"1 Elliot St",
    "sg:city":"Sydney Mines",
    "sg:classifiers":[
        {
            "category":"Manufacturing",
            "subcategory":"Apparel",
            "type":"Manufacturing & Wholesale Goods"
        }
    ],
    "sg:phone":"+1 902 736 1748",
    "sg:postcode":"B1V 2N2",
    "sg:province":"NS",
    "sg:tags":[
        "boy",
        "work",
        "clothing"
    ],
    "wof:name":"National Work Clothing Ltd",
    "wof:placetype":"venue"
},
  "geometry": {"coordinates":[-60.2293739319,46.2436447144],"type":"Point"}
}