{
  "type": "Feature",
  "properties": {
    "addr:full":"654 Fortune Dr Kamloops BC V2B 2K6",
    "addr:housenumber":"654",
    "addr:postcode":"bc v2b 2k6",
    "addr:street":"Fortune Dr",
    "iso:country":"CA",
    "sg:address":"654 Fortune Dr",
    "sg:city":"Kamloops",
    "sg:classifiers":[
        {
            "category":"Travel",
            "subcategory":"Hotels & Motels",
            "type":"Entertainment"
        }
    ],
    "sg:phone":"+1 250 376 7211",
    "sg:postcode":"V2B 2K6",
    "sg:province":"BC",
    "wof:name":"Fortune Motel",
    "wof:placetype":"venue"
},
  "geometry": {"coordinates":[-120.355903626,50.6957893372],"type":"Point"}
}