{
  "type": "Feature",
  "properties": {
    "iso:country":"CA",
    "sg:address":"615 Vaughan Rd",
    "sg:city":"York",
    "sg:classifiers":[
        {
            "category":"Organizations",
            "subcategory":"Religious Organization",
            "type":"Services"
        }
    ],
    "sg:phone":"+1 416 652 6544",
    "sg:postcode":"M6C 2R4",
    "sg:province":"ON",
    "wof:name":"House of God",
    "wof:placetype":"venue"
},
  "geometry": {"coordinates":[-79.44031524659999,43.6924057007],"type":"Point"}
}