{
  "type": "Feature",
  "properties": {
    "addr:full":"663 Colborne St W Brantford ON N3T 5L5",
    "addr:housenumber":"663",
    "addr:postcode":"n3t 5l5",
    "addr:street":"Colborne St W",
    "iso:country":"CA",
    "sg:address":"663 Colborne St W",
    "sg:city":"Brantford",
    "sg:classifiers":[
        {
            "category":"Retail",
            "subcategory":"Auto Repair",
            "type":"Services"
        }
    ],
    "sg:phone":"+1 519 753 3172",
    "sg:postcode":"N3T 5L5",
    "sg:province":"ON",
    "sg:tags":[
        "body",
        "automobile",
        "painting"
    ],
    "wof:name":"Cars Truck & Auto Collision",
    "wof:placetype":"venue"
},
  "geometry": {"coordinates":[-80.2375259399,43.141078949],"type":"Point"}
}