{
  "type": "Feature",
  "properties": {
    "addr:full":"5979 Sooke Rd Sooke BC V0S 1N0",
    "addr:housenumber":"5979",
    "addr:postcode":"v0s 1n0",
    "addr:street":"Sooke Rd",
    "iso:country":"CA",
    "sg:address":"5979 Sooke Rd",
    "sg:city":"Sooke",
    "sg:classifiers":[
        {
            "category":"Building & Trades",
            "subcategory":"Plumbing",
            "type":"Services"
        }
    ],
    "sg:phone":"+1 250 642 7171",
    "sg:postcode":"V0S 1N0",
    "sg:province":"BC",
    "sg:tags":[
        "contractor"
    ],
    "wof:name":"Sooke Plumbing",
    "wof:placetype":"venue"
},
  "geometry": {"coordinates":[-123.68362399999999,48.388084],"type":"Point"}
}