{
  "type": "Feature",
  "properties": {
    "addr:full":"1263 Boul Jolibourg Laval QC H7Y 1Z8",
    "addr:housenumber":"1263",
    "addr:postcode":"h7y 1z8",
    "addr:street":"Boul Jolibourg",
    "iso:country":"CA",
    "sg:address":"1263 Boul Jolibourg",
    "sg:city":"Laval",
    "sg:classifiers":[
        {
            "category":"Retail",
            "subcategory":"Laundry & Dry Cleaning",
            "type":"Services"
        }
    ],
    "sg:phone":"+1 450 689 4658",
    "sg:postcode":"H7Y 1Z8",
    "sg:province":"QC",
    "sg:tags":[
        "cleaners"
    ],
    "wof:name":"Nettoyeur Jolibourg",
    "wof:placetype":"venue"
},
  "geometry": {"coordinates":[-73.853325,45.524452],"type":"Point"}
}