{
  "type": "Feature",
  "properties": {
    "iso:country":"CA",
    "sg:address":"134 11E Rue O",
    "sg:city":"Sainte-Anne-Des-Monts",
    "sg:classifiers":[
        {
            "category":"Organizations",
            "subcategory":"Professional Association",
            "type":"Services"
        }
    ],
    "sg:phone":"+1 418 763 2353",
    "sg:postcode":"G4V 2N7",
    "sg:province":"QC",
    "wof:name":"Club DE L'Age D'Or",
    "wof:placetype":"venue"
},
  "geometry": {"coordinates":[-66.48639678959999,49.1292152405],"type":"Point"}
}