{
  "type": "Feature",
  "properties": {
    "iso:country":"CA",
    "sg:address":"1714 Eighth Ave",
    "sg:city":"New Westminster",
    "sg:classifiers":[
        {
            "category":"Education",
            "subcategory":"School",
            "type":"Public Place"
        }
    ],
    "sg:phone":"+1 604 517 6070",
    "sg:postcode":"V3M 2S7",
    "sg:province":"BC",
    "wof:name":"Lord Tweedsmuir Elementary",
    "wof:placetype":"venue"
},
  "geometry": {"coordinates":[-122.942528,49.205818],"type":"Point"}
}