{
  "type": "Feature",
  "properties": {
    "addr:full":"3700 Yellow Point Rd Ladysmith BC V9G 1E8",
    "addr:housenumber":"3700",
    "addr:postcode":"v9g 1e8",
    "addr:street":"Yellow Point Rd",
    "iso:country":"CA",
    "sg:address":"3700 Yellow Point Rd",
    "sg:city":"Ladysmith",
    "sg:classifiers":[
        {
            "category":"Travel",
            "subcategory":"Hotels & Motels",
            "type":"Entertainment"
        }
    ],
    "sg:phone":"+1 250 245 7422",
    "sg:postcode":"V9G 1E8",
    "sg:province":"BC",
    "sg:tags":[
        "resort"
    ],
    "wof:name":"Yellow Point Lodge Ltd",
    "wof:placetype":"venue"
},
  "geometry": {"coordinates":[-123.82054100000001,48.997356],"type":"Point"}
}