{
  "type": "Feature",
  "properties": {
    "addr:full":"Bishops Falls NL A0H 1C0",
    "addr:postcode":"a0h 1c0",
    "iso:country":"CA",
    "sg:city":"Bishops Falls",
    "sg:classifiers":[
        {
            "category":"Home & Garden",
            "subcategory":"Building Materials",
            "type":"Retail Goods"
        }
    ],
    "sg:phone":"+1 709 258 5471",
    "sg:postcode":"A0H 1C0",
    "sg:province":"NL",
    "wof:name":"Bishop's Falls Building Sppls",
    "wof:placetype":"venue"
},
  "geometry": {"coordinates":[-55.683235,48.946602],"type":"Point"}
}