{
  "type": "Feature",
  "properties": {
    "addr:full":"33 Bastedo Cres Marathon ON P0T 2E0",
    "addr:housenumber":"33",
    "addr:postcode":"p0t 2e0",
    "addr:street":"Bastedo Cres",
    "iso:country":"CA",
    "sg:address":"33 Bastedo Cres",
    "sg:city":"Marathon",
    "sg:classifiers":[
        {
            "category":"Real Estate",
            "subcategory":"Real Estate Agent",
            "type":"Services"
        }
    ],
    "sg:phone":"+1 807 229 3245",
    "sg:postcode":"P0T 2E0",
    "sg:province":"ON",
    "wof:name":"Lannon Realty Ltd",
    "wof:placetype":"venue"
},
  "geometry": {"coordinates":[-86.36632537840001,48.7189826965],"type":"Point"}
}