{
  "type": "Feature",
  "properties": {
    "addr:full":"23 Rhineland St Altona MB R0G 0B0",
    "addr:housenumber":"23",
    "addr:postcode":"r0g 0b0",
    "addr:street":"Rhineland St",
    "iso:country":"CA",
    "sg:address":"23 Rhineland St",
    "sg:city":"Altona",
    "sg:classifiers":[
        {
            "category":"Organizations",
            "subcategory":"Religious Organization",
            "type":"Services"
        }
    ],
    "sg:phone":"+1 204 324 1497",
    "sg:postcode":"R0G 0B0",
    "sg:province":"MB",
    "sg:tags":[
        "church"
    ],
    "wof:name":"Sommerfeld Sommerfelder Church",
    "wof:placetype":"venue"
},
  "geometry": {"coordinates":[-97.551216,49.103539],"type":"Point"}
}