{
  "type": "Feature",
  "properties": {
    "addr:full":"419C 9th St N Golden BC V0A 1H0",
    "addr:housenumber":"419c",
    "addr:postcode":"v0a 1h0",
    "addr:street":"9Th St N",
    "iso:country":"CA",
    "sg:address":"419C 9th St N",
    "sg:city":"Golden",
    "sg:classifiers":[
        {
            "category":"Social Services",
            "type":"Services"
        }
    ],
    "sg:phone":"+1 250 344 2101",
    "sg:postcode":"V0A 1H0",
    "sg:province":"BC",
    "sg:tags":[
        "crisis",
        "center"
    ],
    "wof:name":"Safe Homes",
    "wof:placetype":"venue"
},
  "geometry": {"coordinates":[-116.976005554,51.3050918579],"type":"Point"}
}