{
  "type": "Feature",
  "properties": {
    "addr:full":"19 High St Grand Falls-Windsor NL A2A 1C7",
    "addr:housenumber":"19",
    "addr:postcode":"a2a 1c7",
    "addr:street":"High St",
    "iso:country":"CA",
    "sg:address":"19 High St",
    "sg:city":"Grand Falls-Windsor",
    "sg:classifiers":[
        {
            "category":"Home & Garden",
            "subcategory":"Building Materials",
            "type":"Retail Goods"
        }
    ],
    "sg:phone":"+1 709 489 4347",
    "sg:postcode":"A2A 1C7",
    "sg:province":"NL",
    "sg:tags":[
        "glass",
        "window",
        "plate"
    ],
    "wof:name":"Standard Auto Glass",
    "wof:placetype":"venue"
},
  "geometry": {"coordinates":[-55.657478,48.927505],"type":"Point"}
}