{
  "type": "Feature",
  "properties": {
    "addr:full":"Vancouver BC V6B 4Z9",
    "addr:postcode":"v6b 4z9",
    "iso:country":"CA",
    "sg:city":"Vancouver",
    "sg:classifiers":[
        {
            "category":"Food & Beverages",
            "subcategory":"Specialty",
            "type":"Retail Goods"
        }
    ],
    "sg:phone":"+1 604 681 8558",
    "sg:postcode":"V6B 4Z9",
    "sg:province":"BC",
    "sg:tags":[
        "tea",
        "coffee"
    ],
    "wof:name":"Grounds For Appeal",
    "wof:placetype":"venue"
},
  "geometry": {"coordinates":[-123.11582199999999,49.277805],"type":"Point"}
}