{
  "type": "Feature",
  "properties": {
    "addr:full":"1 Riviere Gatineau Ferme-Neuve QC J0W 1C0",
    "addr:housenumber":"1",
    "addr:postcode":"j0w 1c0",
    "addr:street":"Riviere",
    "iso:country":"CA",
    "sg:address":"1 Riviere Gatineau",
    "sg:city":"Ferme-Neuve",
    "sg:classifiers":[
        {
            "category":"Travel",
            "subcategory":"Campground",
            "type":"Entertainment"
        }
    ],
    "sg:phone":"+1 819 440 9566",
    "sg:postcode":"J0W 1C0",
    "sg:province":"QC",
    "sg:tags":[
        "camp",
        "fishing"
    ],
    "wof:name":"Club Gatineau Inc",
    "wof:placetype":"venue"
},
  "geometry": {"coordinates":[-75.708488,47.007996],"type":"Point"}
}