{
  "type": "Feature",
  "properties": {
    "addr:full":"537 St. Peters Rd Charlottetown PE C1A 7J7",
    "addr:housenumber":"537",
    "addr:postcode":"c1a 7j7",
    "addr:street":"St. Peters Rd",
    "iso:country":"CA",
    "sg:address":"537 St. Peters Rd",
    "sg:city":"Charlottetown",
    "sg:classifiers":[
        {
            "category":"Professional",
            "subcategory":"Business Services",
            "type":"Services"
        }
    ],
    "sg:phone":"+1 902 368 1756",
    "sg:postcode":"C1A 7J7",
    "sg:province":"PE",
    "sg:tags":[
        "interior",
        "consultant",
        "design",
        "decorator"
    ],
    "wof:name":"Interiors By Lynette",
    "wof:placetype":"venue"
},
  "geometry": {"coordinates":[-63.091999054,46.2867546082],"type":"Point"}
}