{
  "type": "Feature",
  "properties": {
    "addr:full":"4500 Av Jean-Duchesne Shawinigan-Sud QC G9N 6T5",
    "addr:housenumber":"4500",
    "addr:postcode":"g9n 6t5",
    "addr:street":"Av Jean-Duchesne",
    "iso:country":"CA",
    "sg:address":"4500 Av Jean-Duchesne",
    "sg:city":"Shawinigan-Sud",
    "sg:classifiers":[
        {
            "category":"Freight",
            "type":"Transportation"
        }
    ],
    "sg:phone":"+1 819 537 9724",
    "sg:postcode":"G9N 6T5",
    "sg:province":"QC",
    "sg:tags":[
        "trucking"
    ],
    "wof:name":"Vivier Transport Enr",
    "wof:placetype":"venue"
},
  "geometry": {"coordinates":[-72.7521972656,46.5189781189],"type":"Point"}
}