{
  "type": "Feature",
  "properties": {
    "addr:full":"535 Huron St Stratford ON N5A 5T8",
    "addr:housenumber":"535",
    "addr:postcode":"n5a 5t8",
    "addr:street":"Huron St",
    "iso:country":"CA",
    "sg:address":"535 Huron St",
    "sg:city":"Stratford",
    "sg:classifiers":[
        {
            "category":"Education",
            "subcategory":"School",
            "type":"Public Place"
        }
    ],
    "sg:phone":"+1 519 271 9551",
    "sg:postcode":"N5A 5T8",
    "sg:province":"ON",
    "wof:name":"Festival School of Hairstyling",
    "wof:placetype":"venue"
},
  "geometry": {"coordinates":[-81.002441,43.380306],"type":"Point"}
}