{
  "type": "Feature",
  "properties": {
    "iso:country":"CA",
    "sg:address":"115 Ritchie Ave",
    "sg:city":"Ajax",
    "sg:classifiers":[
        {
            "category":"Organizations",
            "subcategory":"Religious Organization",
            "type":"Services"
        }
    ],
    "sg:phone":"+1 905 427 6613",
    "sg:postcode":"L1S 7E8",
    "sg:province":"ON",
    "sg:tags":[
        "church"
    ],
    "wof:name":"Ajax Alliance Church",
    "wof:placetype":"venue"
},
  "geometry": {"coordinates":[-79.039818,43.85429],"type":"Point"}
}