{
  "type": "Feature",
  "properties": {
    "addr:full":"30 Lansdowne Ave Saint John NB E2K 2Z8",
    "addr:housenumber":"30",
    "addr:postcode":"e2k 2z8",
    "addr:street":"Lansdowne Ave",
    "iso:country":"CA",
    "sg:address":"30 Lansdowne Ave",
    "sg:city":"Saint John",
    "sg:classifiers":[
        {
            "category":"Shopping",
            "subcategory":"Catalog Store",
            "type":"Retail Goods"
        }
    ],
    "sg:phone":"+1 506 632 3699",
    "sg:postcode":"E2K 2Z8",
    "sg:province":"NB",
    "sg:tags":[
        "mail",
        "order",
        "internet"
    ],
    "wof:name":"Sears",
    "wof:placetype":"venue"
},
  "geometry": {"coordinates":[-66.077011,45.276569],"type":"Point"}
}