{
  "type": "Feature",
  "properties": {
    "iso:country":"CA",
    "sg:address":"1055 Holgate Pl NW",
    "sg:city":"Edmonton",
    "sg:classifiers":[
        {
            "category":"Wholesale",
            "subcategory":"Machinery & Supplies",
            "type":"Manufacturing & Wholesale Goods"
        }
    ],
    "sg:phone":"+1 780 437 8811",
    "sg:postcode":"T6R 2T7",
    "sg:province":"AB",
    "sg:tags":[
        "crane",
        "derrick",
        "parts"
    ],
    "wof:name":"H & S Material Handling Ltd",
    "wof:placetype":"venue"
},
  "geometry": {"coordinates":[-113.598571777,53.458404541],"type":"Point"}
}