{
  "type": "Feature",
  "properties": {
    "addr:full":"40 Rue Turgeon Sainte-Therese QC J7E 3H4",
    "addr:housenumber":"40",
    "addr:postcode":"j7e 3h4",
    "addr:street":"Rue Turgeon Sainte-Therese",
    "iso:country":"CA",
    "sg:address":"40 Rue Turgeon",
    "sg:city":"Sainte-Therese",
    "sg:classifiers":[
        {
            "category":"Personal",
            "type":"Services"
        }
    ],
    "sg:phone":"+1 450 435 5522",
    "sg:postcode":"J7E 3H4",
    "sg:province":"QC",
    "sg:tags":[
        "electrolysis"
    ],
    "wof:name":"Clinique D'Electrolyse Enr",
    "wof:placetype":"venue"
},
  "geometry": {"coordinates":[-73.8405761719,45.6383247375],"type":"Point"}
}