{
  "type": "Feature",
  "properties": {
    "addr:full":"Chatham ON N7L 1C1",
    "addr:postcode":"n7l 1c1",
    "iso:country":"CA",
    "sg:city":"Chatham",
    "sg:classifiers":[
        {
            "category":"Banks & Credit Unions",
            "subcategory":"Investment Brokerage",
            "type":"Services"
        }
    ],
    "sg:phone":"+1 519 352 6840",
    "sg:postcode":"N7L 1C1",
    "sg:province":"ON",
    "sg:tags":[
        "consultant",
        "planning",
        "financial"
    ],
    "wof:name":"Freedom 55 Financial",
    "wof:placetype":"venue"
},
  "geometry": {"coordinates":[-82.197777,42.403141],"type":"Point"}
}