{
  "type": "Feature",
  "properties": {
    "addr:full":"Grand-Mere QC G9T 2H7",
    "addr:postcode":"g9t 2h7",
    "iso:country":"CA",
    "sg:city":"Grand-Mere",
    "sg:classifiers":[
        {
            "category":"Travel",
            "subcategory":"Travel Agent",
            "type":"Entertainment"
        }
    ],
    "sg:phone":"+1 819 538 1786",
    "sg:postcode":"G9T 2H7",
    "sg:province":"QC",
    "sg:tags":[
        "agency",
        "bureau"
    ],
    "wof:name":"Agence DE Voyages Beau-Mont",
    "wof:placetype":"venue"
},
  "geometry": {"coordinates":[-72.694237,46.613415],"type":"Point"}
}