{
  "type": "Feature",
  "properties": {
    "addr:full":"Nakusp BC V0G 1R0",
    "addr:postcode":"v0g 1r0",
    "iso:country":"CA",
    "sg:city":"Nakusp",
    "sg:classifiers":[
        {
            "category":"Food & Beverages",
            "subcategory":"Groceries & Convenience Stores",
            "type":"Retail Goods"
        }
    ],
    "sg:phone":"+1 250 265 4959",
    "sg:postcode":"V0G 1R0",
    "sg:province":"BC",
    "sg:tags":[
        "grocer"
    ],
    "wof:name":"Valley Food Store",
    "wof:placetype":"venue"
},
  "geometry": {"coordinates":[-117.800293,50.238827],"type":"Point"}
}