{
  "type": "Feature",
  "properties": {
    "addr:full":"49 Main St Flin Flon MB R8A 1J7",
    "addr:housenumber":"49",
    "addr:postcode":"r8a 1j7",
    "addr:street":"Main St",
    "iso:country":"CA",
    "sg:address":"49 Main St",
    "sg:city":"Flin Flon",
    "sg:classifiers":[
        {
            "category":"Social Services",
            "type":"Services"
        }
    ],
    "sg:phone":"+1 204 687 6010",
    "sg:postcode":"R8A 1J7",
    "sg:province":"MB",
    "sg:tags":[
        "organization",
        "welfare"
    ],
    "wof:name":"Anxiety Disorders Assn",
    "wof:placetype":"venue"
},
  "geometry": {"coordinates":[-101.87548099999999,54.76506],"type":"Point"}
}