{
  "type": "Feature",
  "properties": {
    "addr:full":"1138 Davenport Rd Toronto ON M6G 2C6",
    "addr:housenumber":"1138",
    "addr:postcode":"m6g 2c6",
    "addr:street":"Davenport Rd",
    "iso:country":"CA",
    "sg:address":"1138 Davenport Rd",
    "sg:city":"Toronto",
    "sg:classifiers":[
        {
            "category":"Bars & Pubs",
            "type":"Food & Drink"
        }
    ],
    "sg:phone":"+1 416 653 2818",
    "sg:postcode":"M6G 2C6",
    "sg:province":"ON",
    "sg:tags":[
        "cafe"
    ],
    "wof:name":"End Zone Sports Bar & Cafe",
    "wof:placetype":"venue"
},
  "geometry": {"coordinates":[-79.43087800000001,43.674767],"type":"Point"}
}