{
  "type": "Feature",
  "properties": {
    "addr:full":"25 Meadow Bank Rd Cornwall PE C0A 1H0",
    "addr:housenumber":"25",
    "addr:postcode":"c0a 1h0",
    "addr:street":"Meadow Bank Rd",
    "iso:country":"CA",
    "sg:address":"25 Meadow Bank Rd",
    "sg:city":"Cornwall",
    "sg:classifiers":[
        {
            "category":"Cinema",
            "subcategory":"Movie Rental",
            "type":"Entertainment"
        }
    ],
    "sg:phone":"+1 902 894 4444",
    "sg:postcode":"C0A 1H0",
    "sg:province":"PE",
    "sg:tags":[
        "leasing",
        "video",
        "disc",
        "tape"
    ],
    "wof:name":"Box Office",
    "wof:placetype":"venue"
},
  "geometry": {"coordinates":[-63.219166,46.226143],"type":"Point"}
}