{
  "type": "Feature",
  "properties": {
    "addr:full":"Cambridge ON N1T 1N4",
    "addr:postcode":"n1t 1n4",
    "iso:country":"CA",
    "sg:city":"Cambridge",
    "sg:classifiers":[
        {
            "category":"Manufacturing",
            "subcategory":"Tools & Machinery",
            "type":"Manufacturing & Wholesale Goods"
        }
    ],
    "sg:phone":"+1 519 622 1133",
    "sg:postcode":"N1T 1N4",
    "sg:province":"ON",
    "sg:tags":[
        "control",
        "static"
    ],
    "wof:name":"W S Wood Assoc Ltd",
    "wof:placetype":"venue"
},
  "geometry": {"coordinates":[-80.3005981445,43.3987922668],"type":"Point"}
}