{
  "type": "Feature",
  "properties": {
    "addr:full":"33839 Essendene Ave Abbotsford BC V2S 2H3",
    "addr:housenumber":"33839",
    "addr:postcode":"v2s 2h3",
    "addr:street":"Essendene Ave",
    "iso:country":"CA",
    "sg:address":"33839 Essendene Ave",
    "sg:city":"Abbotsford",
    "sg:classifiers":[
        {
            "category":"Retail",
            "subcategory":"Auto Repair",
            "type":"Services"
        }
    ],
    "sg:phone":"+1 604 853 2352",
    "sg:postcode":"V2S 2H3",
    "sg:province":"BC",
    "sg:tags":[
        "repairing",
        "automobile"
    ],
    "wof:name":"Hub Motor Svc",
    "wof:placetype":"venue"
},
  "geometry": {"coordinates":[-122.287735,49.049026],"type":"Point"}
}