{
  "type": "Feature",
  "properties": {
    "addr:full":"Saint-Laurent QC H4R 1Y8",
    "addr:postcode":"h4r 1y8",
    "iso:country":"CA",
    "sg:city":"Saint-Laurent",
    "sg:classifiers":[
        {
            "category":"Shopping",
            "subcategory":"Clothing, Apparel, & Fashions",
            "type":"Retail Goods"
        }
    ],
    "sg:phone":"+1 514 337 1950",
    "sg:postcode":"H4R 1Y8",
    "sg:province":"QC",
    "wof:name":"Laura Canada",
    "wof:placetype":"venue"
},
  "geometry": {"coordinates":[-73.70355987550001,45.4979896545],"type":"Point"}
}