{
  "type": "Feature",
  "properties": {
    "addr:full":"2040 Walsh St E Thunder Bay ON P7E 4W2",
    "addr:housenumber":"2040",
    "addr:postcode":"p7e 4w2",
    "addr:street":"Walsh St E",
    "iso:country":"CA",
    "sg:address":"2040 Walsh St E",
    "sg:city":"Thunder Bay",
    "sg:classifiers":[
        {
            "category":"Education",
            "subcategory":"School",
            "type":"Public Place"
        }
    ],
    "sg:phone":"+1 807 623 1541",
    "sg:postcode":"P7E 4W2",
    "sg:province":"ON",
    "wof:name":"Hyde Park School",
    "wof:placetype":"venue"
},
  "geometry": {"coordinates":[-89.2662658691,48.3740768433],"type":"Point"}
}