{
  "type": "Feature",
  "properties": {
    "addr:full":"7900 Nelson Rd Richmond BC V6W 1G4",
    "addr:housenumber":"7900",
    "addr:postcode":"v6w 1g4",
    "addr:street":"Nelson Rd",
    "iso:country":"CA",
    "sg:address":"7900 Nelson Rd",
    "sg:city":"Richmond",
    "sg:classifiers":[
        {
            "category":"Manufacturing",
            "subcategory":"Glass & Minerals",
            "type":"Manufacturing & Wholesale Goods"
        }
    ],
    "sg:phone":"+1 604 278 9766",
    "sg:postcode":"V6W 1G4",
    "sg:province":"BC",
    "sg:tags":[
        "building",
        "concrete",
        "brick",
        "material",
        "block"
    ],
    "wof:name":"Con-Force Structures Ltd",
    "wof:placetype":"venue"
},
  "geometry": {"coordinates":[-123.012665,49.155762],"type":"Point"}
}