{
  "type": "Feature",
  "properties": {
    "addr:full":"3004 Rue Des Aubepines Jonquiere QC G7S 5P4",
    "addr:housenumber":"3004",
    "addr:postcode":"g7s 5p4",
    "addr:street":"Rue Des Aubepines",
    "iso:country":"CA",
    "sg:address":"3004 Rue Des Aubepines",
    "sg:city":"Jonquiere",
    "sg:classifiers":[
        {
            "category":"Building & Trades",
            "subcategory":"Construction",
            "type":"Services"
        }
    ],
    "sg:phone":"+1 418 548 0960",
    "sg:postcode":"G7S 5P4",
    "sg:province":"QC",
    "sg:tags":[
        "downspouts",
        "gutter"
    ],
    "wof:name":"Gouttiere Cite Inc",
    "wof:placetype":"venue"
},
  "geometry": {"coordinates":[-71.206093,48.417912],"type":"Point"}
}