{
  "type": "Feature",
  "properties": {
    "iso:country":"CA",
    "sg:address":"4795 Gertrude St",
    "sg:city":"Port Alberni",
    "sg:classifiers":[
        {
            "category":"Sports & Exercise",
            "subcategory":"Gym",
            "type":"Entertainment"
        }
    ],
    "sg:phone":"+1 250 723 2133",
    "sg:postcode":"V9Y 6K4",
    "sg:province":"BC",
    "sg:tags":[
        "club",
        "health",
        "studio",
        "gymnasium"
    ],
    "wof:name":"Alberni Fitness Ctr",
    "wof:placetype":"venue"
},
  "geometry": {"coordinates":[-124.813194275,49.2614479065],"type":"Point"}
}