{
  "type": "Feature",
  "properties": {
    "addr:full":"640 Rue DE Boucherville Drummondville QC J2C 5C8",
    "addr:housenumber":"640",
    "addr:postcode":"j2c 5c8",
    "addr:street":"Rue De Boucherville",
    "iso:country":"CA",
    "sg:address":"640 Rue DE Boucherville",
    "sg:city":"Drummondville",
    "sg:classifiers":[
        {
            "category":"Personal",
            "subcategory":"Beauty Salon",
            "type":"Services"
        }
    ],
    "sg:phone":"+1 819 474 1417",
    "sg:postcode":"J2C 5C8",
    "sg:province":"QC",
    "wof:name":"Coiffure Lyne",
    "wof:placetype":"venue"
},
  "geometry": {"coordinates":[-72.50720200000001,45.896034],"type":"Point"}
}