{
  "type": "Feature",
  "properties": {
    "iso:country":"CA",
    "sg:address":"7776 Kipling Ave",
    "sg:city":"Woodbridge",
    "sg:classifiers":[
        {
            "category":"Retail",
            "subcategory":"Funeral Services",
            "type":"Services"
        }
    ],
    "sg:phone":"+1 905 851 2229",
    "sg:postcode":"L4L 1Z2",
    "sg:province":"ON",
    "sg:tags":[
        "director"
    ],
    "wof:name":"Scott Funeral Home",
    "wof:placetype":"venue"
},
  "geometry": {"coordinates":[-79.5976104736,43.7792434692],"type":"Point"}
}