{
  "type": "Feature",
  "properties": {
    "addr:full":"2245 Yonge St Toronto ON M4S 2B1",
    "addr:housenumber":"2245",
    "addr:postcode":"m4s 2b1",
    "addr:street":"Yonge St",
    "iso:country":"CA",
    "sg:address":"2245 Yonge St",
    "sg:city":"Toronto",
    "sg:classifiers":[
        {
            "category":"Personal",
            "subcategory":"Beauty Salon",
            "type":"Services"
        }
    ],
    "sg:phone":"+1 416 483 2582",
    "sg:postcode":"M4S 2B1",
    "sg:province":"ON",
    "wof:name":"Beautyclub Salon",
    "wof:placetype":"venue"
},
  "geometry": {"coordinates":[-79.3981018066,43.7062759399],"type":"Point"}
}