{
  "type": "Feature",
  "properties": {
    "iso:country":"CA",
    "sg:city":"Vercheres",
    "sg:classifiers":[
        {
            "category":"Retail",
            "subcategory":"Auto Repair",
            "type":"Services"
        }
    ],
    "sg:phone":"+1 450 583 3133",
    "sg:postcode":"J0L 2R0",
    "sg:province":"QC",
    "sg:tags":[
        "repairing",
        "automobile"
    ],
    "wof:name":"Daniel Larose Garage Enr",
    "wof:placetype":"venue"
},
  "geometry": {"coordinates":[-73.3404312134,45.7848777771],"type":"Point"}
}