{
  "type": "Feature",
  "properties": {
    "addr:full":"328 Centre St SE # 357 Calgary AB T2G 4X6",
    "addr:housenumber":"328",
    "addr:postcode":"t2g 4x6",
    "addr:street":"Centre St Se # 357",
    "iso:country":"CA",
    "sg:address":"328 Centre St SE # 357",
    "sg:city":"Calgary",
    "sg:classifiers":[
        {
            "category":"Organizations",
            "subcategory":"Professional Association",
            "type":"Services"
        }
    ],
    "sg:phone":"+1 403 266 4939",
    "sg:postcode":"T2G 4X6",
    "sg:province":"AB",
    "wof:name":"Chao Chow Community Assn",
    "wof:placetype":"venue"
},
  "geometry": {"coordinates":[-114.062592,51.049904],"type":"Point"}
}