{
  "type": "Feature",
  "properties": {
    "addr:full":"1120 East Ave Weyburn SK S4H 3E4",
    "addr:housenumber":"1120",
    "addr:postcode":"s4h 3e4",
    "addr:street":"East Ave",
    "iso:country":"CA",
    "sg:address":"1120 East Ave",
    "sg:city":"Weyburn",
    "sg:classifiers":[
        {
            "category":"Building & Trades",
            "subcategory":"Electrical",
            "type":"Services"
        }
    ],
    "sg:phone":"+1 306 842 7290",
    "sg:postcode":"S4H 3E4",
    "sg:province":"SK",
    "sg:tags":[
        "electric",
        "contractor"
    ],
    "wof:name":"Industrial Electric",
    "wof:placetype":"venue"
},
  "geometry": {"coordinates":[-103.842658997,49.6589431763],"type":"Point"}
}