{
  "type": "Feature",
  "properties": {
    "addr:full":"Bracebridge ON P1L 2A6",
    "addr:postcode":"p1l 2a6",
    "iso:country":"CA",
    "sg:city":"Bracebridge",
    "sg:classifiers":[
        {
            "category":"Real Estate",
            "subcategory":"Surveying",
            "type":"Services"
        }
    ],
    "sg:phone":"+1 705 645 4611",
    "sg:postcode":"P1L 2A6",
    "sg:province":"ON",
    "sg:tags":[
        "surveyor"
    ],
    "wof:name":"Coote Hiley Jemmett Ltd",
    "wof:placetype":"venue"
},
  "geometry": {"coordinates":[-79.3109664917,45.0398826599],"type":"Point"}
}