{
  "type": "Feature",
  "properties": {
    "addr:full":"Winnipeg MB R2G 0L8",
    "addr:postcode":"r2g 0l8",
    "iso:country":"CA",
    "sg:city":"Winnipeg",
    "sg:classifiers":[
        {
            "category":"Personal",
            "subcategory":"Beauty Salon",
            "type":"Services"
        }
    ],
    "sg:phone":"+1 204 338 1123",
    "sg:postcode":"R2G 0L8",
    "sg:province":"MB",
    "wof:name":"Amanda's Beauty Salon",
    "wof:placetype":"venue"
},
  "geometry": {"coordinates":[-97.07972700000001,49.938065],"type":"Point"}
}