{
  "type": "Feature",
  "properties": {
    "addr:full":"6833 Rue Louis-Hemon Montreal QC H2G 2L4",
    "addr:housenumber":"6833",
    "addr:postcode":"h2g 2l4",
    "addr:street":"Rue Louis-Hemon",
    "iso:country":"CA",
    "sg:address":"6833 Rue Louis-Hemon",
    "sg:city":"Montreal",
    "sg:classifiers":[
        {
            "category":"Building & Trades",
            "subcategory":"Cleaning & Sanitation",
            "type":"Services"
        }
    ],
    "sg:phone":"+1 514 728 1266",
    "sg:postcode":"H2G 2L4",
    "sg:province":"QC",
    "sg:tags":[
        "fireplace",
        "chimney"
    ],
    "wof:name":"J P Charette Enr",
    "wof:placetype":"venue"
},
  "geometry": {"coordinates":[-73.59912872309999,45.5500068665],"type":"Point"}
}