{
  "type": "Feature",
  "properties": {
    "addr:full":"193 Roncesvalles Ave Toronto ON M6R 2L5",
    "addr:housenumber":"193",
    "addr:postcode":"m6r 2l5",
    "addr:street":"Roncesvalles Ave",
    "iso:country":"CA",
    "sg:address":"193 Roncesvalles Ave",
    "sg:city":"Toronto",
    "sg:classifiers":[
        {
            "category":"Retail",
            "subcategory":"Laundry & Dry Cleaning",
            "type":"Services"
        }
    ],
    "sg:phone":"+1 416 537 6764",
    "sg:postcode":"M6R 2L5",
    "sg:province":"ON",
    "sg:tags":[
        "cleaners"
    ],
    "wof:name":"Brite Star One Hour Dry Clean",
    "wof:placetype":"venue"
},
  "geometry": {"coordinates":[-79.448341,43.645023],"type":"Point"}
}