{
  "type": "Feature",
  "properties": {
    "addr:full":"5550 Boul Saint-Laurent Montreal QC H2T 1S8",
    "addr:housenumber":"5550",
    "addr:postcode":"h2t 1s8",
    "addr:street":"Boul Saint-Laurent",
    "iso:country":"CA",
    "sg:address":"5550 Boul Saint-Laurent",
    "sg:city":"Montreal",
    "sg:classifiers":[
        {
            "category":"Bars & Pubs",
            "type":"Food & Drink"
        }
    ],
    "sg:phone":"+1 514 273 2359",
    "sg:postcode":"H2T 1S8",
    "sg:province":"QC",
    "sg:tags":[
        "lounge",
        "cocktail"
    ],
    "wof:name":"Bar St Laurent 2",
    "wof:placetype":"venue"
},
  "geometry": {"coordinates":[-73.59968600000001,45.526031],"type":"Point"}
}