{
  "type": "Feature",
  "properties": {
    "addr:full":"138 6th St SE Portage LA Prairie MB R1N 1E5",
    "addr:housenumber":"138",
    "addr:postcode":"r1n 1e5",
    "addr:street":"6Th St Se",
    "iso:country":"CA",
    "sg:address":"138 6th St SE",
    "sg:city":"Portage LA Prairie",
    "sg:classifiers":[
        {
            "category":"Home & Garden",
            "subcategory":"Carpets & Floor Coverings",
            "type":"Retail Goods"
        }
    ],
    "sg:phone":"+1 204 239 1417",
    "sg:postcode":"R1N 1E5",
    "sg:province":"MB",
    "sg:tags":[
        "dealer",
        "rug"
    ],
    "wof:name":"Keystone Flooring",
    "wof:placetype":"venue"
},
  "geometry": {"coordinates":[-98.281677,49.970016],"type":"Point"}
}