{
  "type": "Feature",
  "properties": {
    "addr:full":"2 10th St Happy Valley-Goose Bay NL A0P 1S0",
    "addr:housenumber":"2",
    "addr:postcode":"a0p 1s0",
    "addr:street":"10Th St",
    "iso:country":"CA",
    "sg:address":"2 10th St",
    "sg:city":"Happy Valley-Goose Bay",
    "sg:classifiers":[
        {
            "category":"Retail",
            "subcategory":"Auto Rental",
            "type":"Services"
        }
    ],
    "sg:phone":"+1 709 896 5575",
    "sg:postcode":"A0P 1S0",
    "sg:province":"NL",
    "sg:tags":[
        "renting",
        "automobile"
    ],
    "wof:name":"National Car Rental",
    "wof:placetype":"venue"
},
  "geometry": {"coordinates":[-60.3239440918,53.2994842529],"type":"Point"}
}