{
  "type": "Feature",
  "properties": {
    "iso:country":"CA",
    "sg:city":"Quebec",
    "sg:classifiers":[
        {
            "category":"Real Estate",
            "subcategory":"Architect",
            "type":"Services"
        }
    ],
    "sg:phone":"+1 418 681 8220",
    "sg:postcode":"G1S 2G8",
    "sg:province":"QC",
    "wof:name":"Hurtubise, Luc",
    "wof:placetype":"venue"
},
  "geometry": {"coordinates":[-71.254265,46.793213],"type":"Point"}
}