{
  "type": "Feature",
  "properties": {
    "addr:full":"10212 112 St NW Edmonton AB T5K 1M4",
    "addr:housenumber":"10212",
    "addr:postcode":"t5k 1m4",
    "addr:street":"112 St Nw",
    "iso:country":"CA",
    "sg:address":"10212 112 St NW",
    "sg:city":"Edmonton",
    "sg:classifiers":[
        {
            "category":"Organizations",
            "subcategory":"Labor Organization",
            "type":"Services"
        }
    ],
    "sg:phone":"+1 780 488 0168",
    "sg:postcode":"T5K 1M4",
    "sg:province":"AB",
    "wof:name":"Health Sciences Assn-Alberta",
    "wof:placetype":"venue"
},
  "geometry": {"coordinates":[-113.514160156,53.5433273315],"type":"Point"}
}