{
  "type": "Feature",
  "properties": {
    "addr:full":"226 6 St Beiseker AB T0M 0G0",
    "addr:housenumber":"226 6",
    "addr:postcode":"t0m 0g0",
    "addr:street":"St",
    "iso:country":"CA",
    "sg:address":"226 6 St",
    "sg:city":"Beiseker",
    "sg:classifiers":[
        {
            "category":"Wholesale",
            "subcategory":"Scrap",
            "type":"Manufacturing & Wholesale Goods"
        }
    ],
    "sg:phone":"+1 403 947 2436",
    "sg:postcode":"T0M 0G0",
    "sg:province":"AB",
    "sg:tags":[
        "recycling",
        "can",
        "bottle",
        "depot"
    ],
    "wof:name":"Ziebart Bottle Depot",
    "wof:placetype":"venue"
},
  "geometry": {"coordinates":[-113.537437439,51.3849983215],"type":"Point"}
}