{
  "type": "Feature",
  "properties": {
    "addr:full":"138 Rue Nobel Chateauguay QC J6K 2Y1",
    "addr:housenumber":"138",
    "addr:postcode":"j6k 2y1",
    "addr:street":"Rue Nobel",
    "iso:country":"CA",
    "sg:address":"138 Rue Nobel",
    "sg:city":"Chateauguay",
    "sg:classifiers":[
        {
            "category":"Building & Trades",
            "subcategory":"Construction",
            "type":"Services"
        }
    ],
    "sg:phone":"+1 450 692 8658",
    "sg:postcode":"J6K 2Y1",
    "sg:province":"QC",
    "sg:tags":[
        "information"
    ],
    "wof:name":"Indicateur Des Projets Au QC",
    "wof:placetype":"venue"
},
  "geometry": {"coordinates":[-73.71189099999999,45.360233],"type":"Point"}
}