{
  "type": "Feature",
  "properties": {
    "addr:full":"126 Jackson St E Hamilton ON L8N 1L3",
    "addr:housenumber":"126",
    "addr:postcode":"l8n 1l3",
    "addr:street":"Jackson St E",
    "iso:country":"CA",
    "sg:address":"126 Jackson St E",
    "sg:city":"Hamilton",
    "sg:classifiers":[
        {
            "category":"Professional",
            "subcategory":"Lawyer & Legal Services",
            "type":"Services"
        }
    ],
    "sg:phone":"+1 905 527 4477",
    "sg:postcode":"L8N 1L3",
    "sg:province":"ON",
    "sg:tags":[
        "attorney"
    ],
    "wof:name":"Schreiber Bordonaro",
    "wof:placetype":"venue"
},
  "geometry": {"coordinates":[-79.865173,43.25309],"type":"Point"}
}