{
  "type": "Feature",
  "properties": {
    "iso:country":"CA",
    "sg:address":"1616 27 Ave NE",
    "sg:city":"Calgary",
    "sg:classifiers":[
        {
            "category":"Manufacturing",
            "subcategory":"Furniture",
            "type":"Manufacturing & Wholesale Goods"
        }
    ],
    "sg:phone":"+1 403 291 4444",
    "sg:postcode":"T2E 8W4",
    "sg:province":"AB",
    "wof:name":"Evans Consoles Inc",
    "wof:placetype":"venue"
},
  "geometry": {"coordinates":[-114.021461487,51.0770149231],"type":"Point"}
}