{
  "type": "Feature",
  "properties": {
    "iso:country":"CA",
    "sg:address":"3545 Boul Des Entreprises",
    "sg:city":"Terrebonne",
    "sg:classifiers":[
        {
            "category":"Wholesale",
            "subcategory":"Meat",
            "type":"Manufacturing & Wholesale Goods"
        }
    ],
    "sg:phone":"+1 450 477 2772",
    "sg:postcode":"J6X 4J9",
    "sg:province":"QC",
    "sg:tags":[
        "butchering"
    ],
    "wof:name":"Viandes Rossi Inc",
    "wof:placetype":"venue"
},
  "geometry": {"coordinates":[-73.677536,45.729767],"type":"Point"}
}