{
  "type": "Feature",
  "properties": {
    "addr:full":"122 Scott Walkerton ON N0G 2V0",
    "addr:housenumber":"122",
    "addr:postcode":"n0g 2v0",
    "addr:street":"Scott Walkerton",
    "iso:country":"CA",
    "sg:address":"122 Scott",
    "sg:city":"Walkerton",
    "sg:classifiers":[
        {
            "category":"Government",
            "subcategory":"Fire Station",
            "type":"Public Place"
        }
    ],
    "sg:phone":"+1 ",
    "sg:postcode":"N0G 2V0",
    "sg:province":"ON",
    "sg:tags":[
        "department"
    ],
    "wof:name":"Walkerton Fire Dept",
    "wof:placetype":"venue"
},
  "geometry": {"coordinates":[-81.15141300000001,44.132629],"type":"Point"}
}