{
  "type": "Feature",
  "properties": {
    "addr:full":"3190 Dover Cres Mississauga ON L5L 5T6",
    "addr:housenumber":"3190",
    "addr:postcode":"l5l 5t6",
    "addr:street":"Dover Cres",
    "iso:country":"CA",
    "sg:address":"3190 Dover Cres",
    "sg:city":"Mississauga",
    "sg:classifiers":[
        {
            "category":"Real Estate",
            "subcategory":"Real Estate Agent",
            "type":"Services"
        }
    ],
    "sg:phone":"+1 905 820 7500",
    "sg:postcode":"L5L 5T6",
    "sg:province":"ON",
    "wof:name":"Alma Real Estate Ltd",
    "wof:placetype":"venue"
},
  "geometry": {"coordinates":[-79.69055899999999,43.525421],"type":"Point"}
}