{
  "type": "Feature",
  "properties": {
    "addr:full":"333 Egerton St London ON N5Z 2H3",
    "addr:housenumber":"333",
    "addr:postcode":"n5z 2h3",
    "addr:street":"Egerton St",
    "iso:country":"CA",
    "sg:address":"333 Egerton St",
    "sg:city":"London",
    "sg:classifiers":[
        {
            "category":"Utilities",
            "subcategory":"Refuse",
            "type":"Services"
        }
    ],
    "sg:phone":"+1 519 451 0680",
    "sg:postcode":"N5Z 2H3",
    "sg:province":"ON",
    "sg:tags":[
        "scrap",
        "metal",
        "garbage",
        "collection",
        "iron"
    ],
    "wof:name":"London Salvage & Trading CO",
    "wof:placetype":"venue"
},
  "geometry": {"coordinates":[-81.21444700000001,42.985428],"type":"Point"}
}