{
  "type": "Feature",
  "properties": {
    "addr:full":"115 Woodmont Cres SW Calgary AB T2W 4G8",
    "addr:housenumber":"115",
    "addr:postcode":"t2w 4g8",
    "addr:street":"Woodmont Cres Sw",
    "iso:country":"CA",
    "sg:address":"115 Woodmont Cres SW",
    "sg:city":"Calgary",
    "sg:classifiers":[
        {
            "category":"Retail",
            "subcategory":"Portrait Studio",
            "type":"Services"
        }
    ],
    "sg:phone":"+1 403 607 6712",
    "sg:postcode":"T2W 4G8",
    "sg:province":"AB",
    "sg:tags":[
        "photographer"
    ],
    "wof:name":"Photography-Robert J Couture",
    "wof:placetype":"venue"
},
  "geometry": {"coordinates":[-114.129455566,50.939201355],"type":"Point"}
}