{
  "type": "Feature",
  "properties": {
    "addr:full":"6061 Arden Rd Arden ON K0H 1B0",
    "addr:housenumber":"6061",
    "addr:postcode":"k0h 1b0",
    "addr:street":"Arden Rd",
    "iso:country":"CA",
    "sg:address":"6061 Arden Rd",
    "sg:city":"Arden",
    "sg:classifiers":[
        {
            "category":"Home & Garden",
            "subcategory":"Furniture",
            "type":"Retail Goods"
        }
    ],
    "sg:phone":"+1 613 335 2450",
    "sg:postcode":"K0H 1B0",
    "sg:province":"ON",
    "wof:name":"Garden Club Wood Designs Ltd",
    "wof:placetype":"venue"
},
  "geometry": {"coordinates":[-76.925049,44.722519],"type":"Point"}
}