{
  "type": "Feature",
  "properties": {
    "addr:full":"26595 127 Ave Maple Ridge BC V2W 1C6",
    "addr:housenumber":"26595",
    "addr:postcode":"v2w 1c6",
    "addr:street":"127 Ave",
    "iso:country":"CA",
    "sg:address":"26595 127 Ave",
    "sg:city":"Maple Ridge",
    "sg:classifiers":[
        {
            "category":"Building & Trades",
            "subcategory":"Construction",
            "type":"Services"
        }
    ],
    "sg:phone":"+1 604 462 1443",
    "sg:postcode":"V2W 1C6",
    "sg:province":"BC",
    "sg:tags":[
        "excavating",
        "contractor"
    ],
    "wof:name":"Kev Construction",
    "wof:placetype":"venue"
},
  "geometry": {"coordinates":[-122.485717773,49.2333755493],"type":"Point"}
}