{
  "type": "Feature",
  "properties": {
    "addr:full":"1599 Hurontario St Mississauga ON L5G 4S1",
    "addr:housenumber":"1599",
    "addr:postcode":"l5g 4s1",
    "addr:street":"Hurontario St",
    "iso:country":"CA",
    "sg:address":"1599 Hurontario St",
    "sg:city":"Mississauga",
    "sg:classifiers":[
        {
            "category":"Professional",
            "subcategory":"Computer Services",
            "type":"Services"
        }
    ],
    "sg:phone":"+1 905 278 9444",
    "sg:postcode":"L5G 4S1",
    "sg:province":"ON",
    "sg:tags":[
        "consultant"
    ],
    "wof:name":"Affinity Systems",
    "wof:placetype":"venue"
},
  "geometry": {"coordinates":[-79.59660339360001,43.5661697388],"type":"Point"}
}