{
  "type": "Feature",
  "properties": {
    "addr:full":"2950 Ulverston Ave Cumberland BC V0R 1S0",
    "addr:postcode":"2950;v0r 1s0",
    "addr:street":"Ulverston Ave",
    "iso:country":"CA",
    "sg:address":"2950 Ulverston Ave",
    "sg:city":"Cumberland",
    "sg:classifiers":[
        {
            "category":"Retail",
            "subcategory":"Laundry & Dry Cleaning",
            "type":"Services"
        }
    ],
    "sg:phone":"+1 250 336 8577",
    "sg:postcode":"V0R 1S0",
    "sg:province":"BC",
    "wof:name":"Cumberland Regional Hosp Lndry",
    "wof:placetype":"venue"
},
  "geometry": {"coordinates":[-125.022797,49.622879],"type":"Point"}
}