{
  "type": "Feature",
  "properties": {
    "addr:full":"1575 Trinity Dr #4 Mississauga ON L5T 1K4",
    "addr:housenumber":"1575",
    "addr:postcode":"l5t 1k4",
    "addr:street":"Trinity Dr # 4",
    "iso:country":"CA",
    "sg:address":"1575 Trinity Dr #4",
    "sg:city":"Mississauga",
    "sg:classifiers":[
        {
            "category":"Manufacturing",
            "subcategory":"Furniture",
            "type":"Manufacturing & Wholesale Goods"
        }
    ],
    "sg:phone":"+1 905 564 5528",
    "sg:postcode":"L5T 1K4",
    "sg:province":"ON",
    "sg:tags":[
        "exposition",
        "stand"
    ],
    "wof:name":"Trade Show Displays Inc",
    "wof:placetype":"venue"
},
  "geometry": {"coordinates":[-79.64962005620001,43.6597557068],"type":"Point"}
}