{
  "type": "Feature",
  "properties": {
    "addr:full":"1011 Route 105 Southampton NB E6G 1L2",
    "addr:housenumber":"1011",
    "addr:postcode":"e6g 1l2",
    "addr:street":"Route 105",
    "iso:country":"CA",
    "sg:address":"1011 Route 105",
    "sg:city":"Southampton",
    "sg:classifiers":[
        {
            "category":"Building & Trades",
            "subcategory":"Plumbing",
            "type":"Services"
        }
    ],
    "sg:phone":"+1 506 575 8187",
    "sg:postcode":"E6G 1L2",
    "sg:province":"NB",
    "sg:tags":[
        "heating",
        "contractor"
    ],
    "wof:name":"Laverne Drost Plumbing",
    "wof:placetype":"venue"
},
  "geometry": {"coordinates":[-67.254379,45.965431],"type":"Point"}
}