{
  "type": "Feature",
  "properties": {
    "addr:full":"2177 Rue Masson Montreal QC H2H 1B1",
    "addr:housenumber":"2177",
    "addr:postcode":"h2h 1b1",
    "addr:street":"Rue Masson",
    "iso:country":"CA",
    "sg:address":"2177 Rue Masson",
    "sg:city":"Montreal",
    "sg:classifiers":[
        {
            "category":"Professional",
            "subcategory":"Art Services",
            "type":"Services"
        }
    ],
    "sg:phone":"+1 514 523 8184",
    "sg:postcode":"H2H 1B1",
    "sg:province":"QC",
    "sg:tags":[
        "artist"
    ],
    "wof:name":"Crovatto, Lucie",
    "wof:placetype":"venue"
},
  "geometry": {"coordinates":[-73.580879,45.540764],"type":"Point"}
}