{
  "type": "Feature",
  "properties": {
    "addr:full":"10211 No. 5 Rd Richmond BC V7A 4E4",
    "addr:housenumber":"10211",
    "addr:postcode":"v7a 4e4",
    "addr:street":"No. 5 Rd",
    "iso:country":"CA",
    "sg:address":"10211 No. 5 Rd",
    "sg:city":"Richmond",
    "sg:classifiers":[
        {
            "category":"Building & Trades",
            "subcategory":"Construction",
            "type":"Services"
        }
    ],
    "sg:phone":"+1 604 271 4878",
    "sg:postcode":"V7A 4E4",
    "sg:province":"BC",
    "sg:tags":[
        "skylight"
    ],
    "wof:name":"Abc Aluminum Installations",
    "wof:placetype":"venue"
},
  "geometry": {"coordinates":[-123.092033386,49.138874054],"type":"Point"}
}