{
  "type": "Feature",
  "properties": {
    "addr:full":"Calgary AB T2P 3G6",
    "addr:postcode":"t2p 3g6",
    "iso:country":"CA",
    "sg:city":"Calgary",
    "sg:classifiers":[
        {
            "category":"Shopping",
            "subcategory":"Computers & Home Electronics",
            "type":"Retail Goods"
        }
    ],
    "sg:phone":"+1 403 233 9400",
    "sg:postcode":"T2P 3G6",
    "sg:province":"AB",
    "sg:tags":[
        "software"
    ],
    "wof:name":"Energy Navigator Inc",
    "wof:placetype":"venue"
},
  "geometry": {"coordinates":[-114.06656599999999,51.048306],"type":"Point"}
}