{
  "type": "Feature",
  "properties": {
    "addr:full":"1796 Commissioners Rd E London ON N6M 1E7",
    "addr:housenumber":"1796",
    "addr:postcode":"n6m 1e7",
    "addr:street":"Commissioners Rd E",
    "iso:country":"CA",
    "sg:address":"1796 Commissioners Rd E",
    "sg:city":"London",
    "sg:classifiers":[
        {
            "category":"Building & Trades",
            "subcategory":"Construction",
            "type":"Services"
        }
    ],
    "sg:phone":"+1 519 455 0630",
    "sg:postcode":"N6M 1E7",
    "sg:province":"ON",
    "sg:tags":[
        "paving",
        "contractor"
    ],
    "wof:name":"Walmsley Brothers Ltd",
    "wof:placetype":"venue"
},
  "geometry": {"coordinates":[-81.15907300000001,42.961964],"type":"Point"}
}