{
  "type": "Feature",
  "properties": {
    "addr:full":"425 University Ave E # J Waterloo ON N2K 4C9",
    "addr:housenumber":"425",
    "addr:postcode":"n2k 4c9",
    "addr:street":"University Ave E # J",
    "iso:country":"CA",
    "sg:address":"425 University Ave E # J",
    "sg:city":"Waterloo",
    "sg:classifiers":[
        {
            "category":"Cinema",
            "subcategory":"Movie Rental",
            "type":"Entertainment"
        }
    ],
    "sg:phone":"+1 519 585 7721",
    "sg:postcode":"N2K 4C9",
    "sg:province":"ON",
    "sg:tags":[
        "leasing",
        "video",
        "disc",
        "tape"
    ],
    "wof:name":"Gone Hollywood Video",
    "wof:placetype":"venue"
},
  "geometry": {"coordinates":[-80.49176,43.490829],"type":"Point"}
}