{
  "type": "Feature",
  "properties": {
    "addr:full":"2214 Ch Filteau Saint-Nicolas QC G7A 2N4",
    "addr:postcode":"2214;g7a 2n4",
    "addr:street":"Ch Filteau",
    "iso:country":"CA",
    "sg:address":"2214 Ch Filteau",
    "sg:city":"Saint-Nicolas",
    "sg:classifiers":[
        {
            "category":"Building & Trades",
            "subcategory":"Construction",
            "type":"Services"
        }
    ],
    "sg:phone":"+1 418 831 9692",
    "sg:postcode":"G7A 2N4",
    "sg:province":"QC",
    "sg:tags":[
        "contractor"
    ],
    "wof:name":"Entreprises Denys Hamel Inc",
    "wof:placetype":"venue"
},
  "geometry": {"coordinates":[-71.422493,46.653469],"type":"Point"}
}