{
  "type": "Feature",
  "properties": {
    "addr:full":"1299 Seacliff Dr Kingsville ON N9Y 2M3",
    "addr:housenumber":"1299",
    "addr:postcode":"n9y 2m3",
    "addr:street":"Seacliff Dr",
    "iso:country":"CA",
    "sg:address":"1299 Seacliff Dr",
    "sg:city":"Kingsville",
    "sg:classifiers":[
        {
            "category":"Shopping",
            "type":"Retail Goods"
        }
    ],
    "sg:phone":"+1 519 733 2222",
    "sg:postcode":"N9Y 2M3",
    "sg:province":"ON",
    "sg:tags":[
        "picture",
        "frame",
        "art",
        "gallery",
        "dealer"
    ],
    "wof:name":"Somerset Gallery Inc",
    "wof:placetype":"venue"
},
  "geometry": {"coordinates":[-82.68531,42.037926],"type":"Point"}
}