{
  "type": "Feature",
  "properties": {
    "addr:full":"Sundre AB T0M 1X0",
    "addr:postcode":"t0m 1x0",
    "iso:country":"CA",
    "sg:city":"Sundre",
    "sg:classifiers":[
        {
            "category":"Building & Trades",
            "subcategory":"Construction",
            "type":"Services"
        }
    ],
    "sg:phone":"+1 403 638 4322",
    "sg:postcode":"T0M 1X0",
    "sg:province":"AB",
    "sg:tags":[
        "excavating",
        "contractor"
    ],
    "wof:name":"R & V Excavating Ltd",
    "wof:placetype":"venue"
},
  "geometry": {"coordinates":[-114.635200501,51.8120002747],"type":"Point"}
}