{
  "type": "Feature",
  "properties": {
    "addr:full":"431 Main St Kentville NS B4N 1K9",
    "addr:housenumber":"431",
    "addr:postcode":"b4n 1k9",
    "addr:street":"Main St",
    "iso:country":"CA",
    "sg:address":"431 Main St",
    "sg:city":"Kentville",
    "sg:classifiers":[
        {
            "category":"Food & Beverages",
            "subcategory":"Fruits & Vegetables",
            "type":"Retail Goods"
        }
    ],
    "sg:phone":"+1 902 678 6469",
    "sg:postcode":"B4N 1K9",
    "sg:province":"NS",
    "sg:tags":[
        "produce"
    ],
    "wof:name":"Avery's Farm Market",
    "wof:placetype":"venue"
},
  "geometry": {"coordinates":[-64.490517,45.075756],"type":"Point"}
}