{
  "type": "Feature",
  "properties": {
    "addr:full":"2518 St. Johns St Port Moody BC V3H 2B4",
    "addr:housenumber":"2518",
    "addr:postcode":"v3h 2b4",
    "addr:street":"St. Johns St",
    "iso:country":"CA",
    "sg:address":"2518 St. Johns St",
    "sg:city":"Port Moody",
    "sg:classifiers":[
        {
            "category":"Restaurant",
            "type":"Food & Drink"
        }
    ],
    "sg:phone":"+1 604 936 1969",
    "sg:postcode":"V3H 2B4",
    "sg:province":"BC",
    "wof:name":"Rehanah's Roti & Trinidadian",
    "wof:placetype":"venue"
},
  "geometry": {"coordinates":[-122.856148,49.276917],"type":"Point"}
}