{
  "type": "Feature",
  "properties": {
    "addr:full":"1450 Provincial Rd Windsor ON N8W 5W1",
    "addr:housenumber":"1450",
    "addr:postcode":"n8w 5w1",
    "addr:street":"Provincial Rd",
    "iso:country":"CA",
    "sg:address":"1450 Provincial Rd",
    "sg:city":"Windsor",
    "sg:classifiers":[
        {
            "category":"Home & Garden",
            "subcategory":"Furniture",
            "type":"Retail Goods"
        }
    ],
    "sg:phone":"+1 519 972 5304",
    "sg:postcode":"N8W 5W1",
    "sg:province":"ON",
    "wof:name":"Furniture Warehouse",
    "wof:placetype":"venue"
},
  "geometry": {"coordinates":[-82.9799194336,42.2596511841],"type":"Point"}
}