{
  "type": "Feature",
  "properties": {
    "iso:country":"CA",
    "sg:city":"Ottawa",
    "sg:classifiers":[
        {
            "category":"Professional",
            "subcategory":"Lawyer & Legal Services",
            "type":"Services"
        }
    ],
    "sg:phone":"+1 613 236 8712",
    "sg:postcode":"K2P 0C3",
    "sg:province":"ON",
    "sg:tags":[
        "attorney"
    ],
    "wof:name":"Macdonald Affleck",
    "wof:placetype":"venue"
},
  "geometry": {"coordinates":[-75.683411,45.446903],"type":"Point"}
}