{
  "type": "Feature",
  "properties": {
    "addr:full":"Bay St Charlton ON P0J 1B0",
    "addr:postcode":"p0j 1b0",
    "addr:street":"St",
    "iso:country":"CA",
    "sg:address":"Bay St",
    "sg:city":"Charlton",
    "sg:classifiers":[
        {
            "category":"Organizations",
            "subcategory":"Professional Association",
            "type":"Services"
        }
    ],
    "sg:phone":"+1 705 544 7620",
    "sg:postcode":"P0J 1B0",
    "sg:province":"ON",
    "wof:name":"Charlton Legion",
    "wof:placetype":"venue"
},
  "geometry": {"coordinates":[-80.0006027222,47.8102340698],"type":"Point"}
}