{
  "type": "Feature",
  "properties": {
    "addr:full":"260 Seneca Hill Dr # 1710 North York ON M2J 4S6",
    "addr:housenumber":"260",
    "addr:postcode":"m2j 4s6",
    "addr:street":"Seneca Hill Dr # 1710",
    "iso:country":"CA",
    "sg:address":"260 Seneca Hill Dr # 1710",
    "sg:city":"North York",
    "sg:classifiers":[
        {
            "category":"Retail",
            "subcategory":"Auto Repair",
            "type":"Services"
        }
    ],
    "sg:phone":"+1 416 562 5625",
    "sg:postcode":"M2J 4S6",
    "sg:province":"ON",
    "sg:tags":[
        "wrecker"
    ],
    "wof:name":"A M Towing & Storage",
    "wof:placetype":"venue"
},
  "geometry": {"coordinates":[-79.356934,43.78989],"type":"Point"}
}