{
  "type": "Feature",
  "properties": {
    "addr:full":"38 John St S Aylmer ON N5H 2C2",
    "addr:housenumber":"38",
    "addr:postcode":"n5h 2c2",
    "addr:street":"John St S",
    "iso:country":"CA",
    "sg:address":"38 John St S",
    "sg:city":"Aylmer",
    "sg:classifiers":[
        {
            "category":"Education",
            "subcategory":"Library",
            "type":"Public Place"
        }
    ],
    "sg:phone":"+1 519 773 2439",
    "sg:postcode":"N5H 2C2",
    "sg:province":"ON",
    "wof:name":"Aylmer Public Library",
    "wof:placetype":"venue"
},
  "geometry": {"coordinates":[-80.983124,42.772572],"type":"Point"}
}