{
  "type": "Feature",
  "properties": {
    "addr:full":"15 Deerfox Dr Nepean ON K2J 4W3",
    "addr:housenumber":"15",
    "addr:postcode":"k2j 4w3",
    "addr:street":"Deerfox Dr",
    "iso:country":"CA",
    "sg:address":"15 Deerfox Dr",
    "sg:city":"Nepean",
    "sg:classifiers":[
        {
            "category":"Building & Trades",
            "subcategory":"Construction",
            "type":"Services"
        }
    ],
    "sg:phone":"+1 613 825 7609",
    "sg:postcode":"K2J 4W3",
    "sg:province":"ON",
    "sg:tags":[
        "paving",
        "pavement",
        "sealing",
        "contractor"
    ],
    "wof:name":"Pro Seal Asphalt Repair",
    "wof:placetype":"venue"
},
  "geometry": {"coordinates":[-75.72240447999999,45.2801780701],"type":"Point"}
}