{
  "type": "Feature",
  "properties": {
    "addr:full":"12224 142 St NW Edmonton AB T5L 2G9",
    "addr:housenumber":"12224",
    "addr:postcode":"t5l 2g9",
    "addr:street":"142 St Nw",
    "iso:country":"CA",
    "sg:address":"12224 142 St NW",
    "sg:city":"Edmonton",
    "sg:classifiers":[
        {
            "category":"Home & Garden",
            "subcategory":"Building Materials",
            "type":"Retail Goods"
        }
    ],
    "sg:phone":"+1 780 453 3776",
    "sg:postcode":"T5L 2G9",
    "sg:province":"AB",
    "sg:tags":[
        "plywood",
        "veneer"
    ],
    "wof:name":"Alpine Forest Products Ltd",
    "wof:placetype":"venue"
},
  "geometry": {"coordinates":[-113.565956116,53.5752105713],"type":"Point"}
}