{
  "type": "Feature",
  "properties": {
    "addr:full":"1993 Lakehurst Rd Buckhorn ON K0L 1J0",
    "addr:housenumber":"1993",
    "addr:postcode":"k0l 1j0",
    "addr:street":"Lakehurst Rd",
    "iso:country":"CA",
    "sg:address":"1993 Lakehurst Rd",
    "sg:city":"Buckhorn",
    "sg:classifiers":[
        {
            "category":"Food & Beverages",
            "subcategory":"Liquor & Beverages",
            "type":"Retail Goods"
        }
    ],
    "sg:phone":"+1 705 657 3211",
    "sg:postcode":"K0L 1J0",
    "sg:province":"ON",
    "sg:tags":[
        "store"
    ],
    "wof:name":"Liquor Control Board of Ont",
    "wof:placetype":"venue"
},
  "geometry": {"coordinates":[-78.3500823975,44.5568733215],"type":"Point"}
}