{
  "type": "Feature",
  "properties": {
    "addr:full":"111 Fifth Ave Orangeville ON L9W 5B7",
    "addr:housenumber":"111",
    "addr:postcode":"l9w 5b7",
    "addr:street":"Fifth Ave",
    "iso:country":"CA",
    "sg:address":"111 Fifth Ave",
    "sg:city":"Orangeville",
    "sg:classifiers":[
        {
            "category":"Restaurant",
            "type":"Food & Drink"
        }
    ],
    "sg:phone":"+1 519 941 2121",
    "sg:postcode":"L9W 5B7",
    "sg:province":"ON",
    "wof:name":"Montana's Cookhouse Saloon",
    "wof:placetype":"venue"
},
  "geometry": {"coordinates":[-80.09405517579999,43.9289169312],"type":"Point"}
}