{
  "type": "Feature",
  "properties": {
    "addr:full":"416 South Railway St Boissevain MB R0K 0E0",
    "addr:housenumber":"416",
    "addr:postcode":"r0k 0e0",
    "addr:street":"South Railway St",
    "iso:country":"CA",
    "sg:address":"416 South Railway St",
    "sg:city":"Boissevain",
    "sg:classifiers":[
        {
            "category":"Shopping",
            "subcategory":"Gifts & Souvenirs",
            "type":"Retail Goods"
        }
    ],
    "sg:phone":"+1 204 534 6002",
    "sg:postcode":"R0K 0E0",
    "sg:province":"MB",
    "sg:tags":[
        "shop"
    ],
    "wof:name":"Station",
    "wof:placetype":"venue"
},
  "geometry": {"coordinates":[-100.058975,49.230293],"type":"Point"}
}