{
  "type": "Feature",
  "properties": {
    "addr:full":"510 Barriere Town Rd Barriere BC V0E 1E0",
    "addr:housenumber":"510",
    "addr:postcode":"bc v0e 1e0",
    "addr:street":"Barriere Town Rd",
    "iso:country":"CA",
    "sg:address":"510 Barriere Town Rd",
    "sg:city":"Barriere",
    "sg:classifiers":[
        {
            "category":"Food & Beverages",
            "subcategory":"Groceries & Convenience Stores",
            "type":"Retail Goods"
        }
    ],
    "sg:phone":"+1 250 672 9929",
    "sg:postcode":"V0E 1E0",
    "sg:province":"BC",
    "sg:tags":[
        "grocer"
    ],
    "wof:name":"A G Foods",
    "wof:placetype":"venue"
},
  "geometry": {"coordinates":[-120.126671,51.188274],"type":"Point"}
}