{
  "type": "Feature",
  "properties": {
    "addr:full":"2765 Ch Gascon Mascouche QC J7L 3X7",
    "addr:postcode":"2765;j7l 3x7",
    "addr:street":"Ch Gascon",
    "iso:country":"CA",
    "sg:address":"2765 Ch Gascon",
    "sg:city":"Mascouche",
    "sg:classifiers":[
        {
            "category":"Autos & Motor Vehicles",
            "subcategory":"Fuel & Gas Station",
            "type":"Retail Goods"
        }
    ],
    "sg:phone":"+1 450 968 9034",
    "sg:postcode":"J7L 3X7",
    "sg:province":"QC",
    "sg:tags":[
        "oil"
    ],
    "wof:name":"Super Gaz",
    "wof:placetype":"venue"
},
  "geometry": {"coordinates":[-73.671021,45.728222],"type":"Point"}
}