{
  "type": "Feature",
  "properties": {
    "addr:full":"401 Edmonton Hwy Dawson Creek BC V1G 4H7",
    "addr:housenumber":"401",
    "addr:postcode":"v1g 4h7",
    "addr:street":"Edmonton Hwy",
    "iso:country":"CA",
    "sg:address":"401 Edmonton Hwy",
    "sg:city":"Dawson Creek",
    "sg:classifiers":[
        {
            "category":"Autos & Motor Vehicles",
            "subcategory":"Fuel & Gas Station",
            "type":"Retail Goods"
        }
    ],
    "sg:phone":"+1 250 782 9288",
    "sg:postcode":"V1G 4H7",
    "sg:province":"BC",
    "sg:tags":[
        "oil"
    ],
    "wof:name":"United Farmers-Alberta CO-OP",
    "wof:placetype":"venue"
},
  "geometry": {"coordinates":[-120.237061,55.761726],"type":"Point"}
}