{
  "type": "Feature",
  "properties": {
    "addr:full":"234 Fischer Ave The Pas MB R9A 1S5",
    "addr:housenumber":"234",
    "addr:postcode":"r9a 1s5",
    "addr:street":"Fischer Ave",
    "iso:country":"CA",
    "sg:address":"234 Fischer Ave",
    "sg:city":"The Pas",
    "sg:classifiers":[
        {
            "category":"Personal",
            "subcategory":"Beauty Salon",
            "type":"Services"
        }
    ],
    "sg:phone":"+1 204 623 7339",
    "sg:postcode":"R9A 1S5",
    "sg:province":"MB",
    "wof:name":"Casual Cuts Hair Salon",
    "wof:placetype":"venue"
},
  "geometry": {"coordinates":[-101.2526474,53.8233184814],"type":"Point"}
}