{
  "type": "Feature",
  "properties": {
    "iso:country":"CA",
    "sg:address":"8102 Av Du Zoo",
    "sg:city":"Charlesbourg",
    "sg:classifiers":[
        {
            "category":"Bars & Pubs",
            "type":"Food & Drink"
        }
    ],
    "sg:phone":"+1 418 622 1113",
    "sg:postcode":"G1G 4G3",
    "sg:province":"QC",
    "sg:tags":[
        "lounge",
        "cocktail"
    ],
    "wof:name":"Brasserie Du Zoo",
    "wof:placetype":"venue"
},
  "geometry": {"coordinates":[-71.297966,46.890011],"type":"Point"}
}