{
  "type": "Feature",
  "properties": {
    "addr:full":"178 Waterloo St Liverpool NS B0T 1K0",
    "addr:housenumber":"178",
    "addr:postcode":"b0t 1k0",
    "addr:street":"Waterloo St",
    "iso:country":"CA",
    "sg:address":"178 Waterloo St",
    "sg:city":"Liverpool",
    "sg:classifiers":[
        {
            "category":"Education",
            "subcategory":"School",
            "type":"Public Place"
        }
    ],
    "sg:phone":"+1 902 354 7640",
    "sg:postcode":"B0T 1K0",
    "sg:province":"NS",
    "wof:name":"South Queens Jr High School",
    "wof:placetype":"venue"
},
  "geometry": {"coordinates":[-64.72068023680001,44.0357627869],"type":"Point"}
}