{
  "type": "Feature",
  "properties": {
    "addr:full":"801 York Mills Rd North York ON M3B 1X7",
    "addr:housenumber":"801",
    "addr:postcode":"m3b 1x7",
    "addr:street":"York Mills Rd",
    "iso:country":"CA",
    "sg:address":"801 York Mills Rd",
    "sg:city":"North York",
    "sg:classifiers":[
        {
            "category":"Building & Trades",
            "subcategory":"Construction",
            "type":"Services"
        }
    ],
    "sg:phone":"+1 416 449 0450",
    "sg:postcode":"M3B 1X7",
    "sg:province":"ON",
    "sg:tags":[
        "general",
        "contractor"
    ],
    "wof:name":"Trist Construction",
    "wof:placetype":"venue"
},
  "geometry": {"coordinates":[-79.35916137700001,43.7529830933],"type":"Point"}
}