{
  "type": "Feature",
  "properties": {
    "addr:full":"2374 Millstream Rd Victoria BC V9B 3R3",
    "addr:housenumber":"2374",
    "addr:postcode":"v9b 3r3",
    "addr:street":"Millstream Rd",
    "iso:country":"CA",
    "sg:address":"2374 Millstream Rd",
    "sg:city":"Victoria",
    "sg:classifiers":[
        {
            "category":"Professional",
            "subcategory":"Business Services",
            "type":"Services"
        }
    ],
    "sg:phone":"+1 250 478 8947",
    "sg:postcode":"V9B 3R3",
    "sg:province":"BC",
    "sg:tags":[
        "interior",
        "consultant",
        "design",
        "decorator"
    ],
    "wof:name":"Karen West Designs",
    "wof:placetype":"venue"
},
  "geometry": {"coordinates":[-123.36451700000001,48.428314],"type":"Point"}
}