{
  "type": "Feature",
  "properties": {
    "addr:full":"3224 Hwy 3 Lockeport NS B0T 1L0",
    "addr:housenumber":"3224",
    "addr:postcode":"b0t 1l0",
    "addr:street":"Hwy 3",
    "iso:country":"CA",
    "sg:address":"3224 Hwy 3",
    "sg:city":"Lockeport",
    "sg:classifiers":[
        {
            "category":"Autos & Motor Vehicles",
            "subcategory":"Auto Supplies",
            "type":"Retail Goods"
        }
    ],
    "sg:phone":"+1 902 656 2454",
    "sg:postcode":"B0T 1L0",
    "sg:province":"NS",
    "sg:tags":[
        "automobile",
        "parts"
    ],
    "wof:name":"Lenny's Auto Ctr",
    "wof:placetype":"venue"
},
  "geometry": {"coordinates":[-65.121056,43.717255],"type":"Point"}
}