{
  "type": "Feature",
  "properties": {
    "addr:full":"Saskatoon SK S7K 3H1",
    "addr:postcode":"s7k 3h1",
    "iso:country":"CA",
    "sg:city":"Saskatoon",
    "sg:classifiers":[
        {
            "category":"Banks & Credit Unions",
            "subcategory":"Investment Brokerage",
            "type":"Services"
        }
    ],
    "sg:phone":"+1 306 934 7060",
    "sg:postcode":"S7K 3H1",
    "sg:province":"SK",
    "sg:tags":[
        "consultant",
        "planning",
        "financial"
    ],
    "wof:name":"London Life Insurance CO",
    "wof:placetype":"venue"
},
  "geometry": {"coordinates":[-106.65944671600001,52.1265182495],"type":"Point"}
}