{
  "type": "Feature",
  "properties": {
    "addr:full":"6363 126 St Surrey BC V3X 1V1",
    "addr:housenumber":"6363",
    "addr:postcode":"v3x 1v1",
    "addr:street":"126 St",
    "iso:country":"CA",
    "sg:address":"6363 126 St",
    "sg:city":"Surrey",
    "sg:classifiers":[
        {
            "category":"Retail",
            "subcategory":"Repair Shop",
            "type":"Services"
        }
    ],
    "sg:phone":"+1 604 597 6677",
    "sg:postcode":"V3X 1V1",
    "sg:province":"BC",
    "sg:tags":[
        "cleaners",
        "parts",
        "vacuum"
    ],
    "wof:name":"Master Central Vacuum",
    "wof:placetype":"venue"
},
  "geometry": {"coordinates":[-122.873383,49.119171],"type":"Point"}
}