{
  "type": "Feature",
  "properties": {
    "addr:full":"52 Town Line Orangeville ON L9W 1V2",
    "addr:housenumber":"52",
    "addr:postcode":"l9w 1v2",
    "addr:street":"Town Line",
    "iso:country":"CA",
    "sg:address":"52 Town Line",
    "sg:city":"Orangeville",
    "sg:classifiers":[
        {
            "category":"Shopping",
            "subcategory":"Florist",
            "type":"Retail Goods"
        }
    ],
    "sg:phone":"+1 519 941 2500",
    "sg:postcode":"L9W 1V2",
    "sg:province":"ON",
    "wof:name":"Parsons' Florist",
    "wof:placetype":"venue"
},
  "geometry": {"coordinates":[-80.0926742554,43.9122161865],"type":"Point"}
}