{
  "type": "Feature",
  "properties": {
    "iso:country":"CA",
    "sg:address":"13957 Boul Du Cure-Labelle",
    "sg:city":"Mirabel",
    "sg:classifiers":[
        {
            "category":"Restaurant",
            "type":"Food & Drink"
        }
    ],
    "sg:phone":"+1 450 430 7490",
    "sg:postcode":"J7J 1M3",
    "sg:province":"QC",
    "wof:name":"Barbecue Mirabel Enrg",
    "wof:placetype":"venue"
},
  "geometry": {"coordinates":[-73.9310836792,45.7066345215],"type":"Point"}
}