{
  "type": "Feature",
  "properties": {
    "addr:full":"825 7th Ave W Melville SK S0A 2P0",
    "addr:housenumber":"825",
    "addr:postcode":"s0a 2p0",
    "addr:street":"7Th Ave W",
    "iso:country":"CA",
    "sg:address":"825 7th Ave W",
    "sg:city":"Melville",
    "sg:classifiers":[
        {
            "category":"Travel",
            "subcategory":"Travel Agent",
            "type":"Entertainment"
        }
    ],
    "sg:phone":"+1 306 728 5119",
    "sg:postcode":"S0A 2P0",
    "sg:province":"SK",
    "sg:tags":[
        "agency",
        "bureau"
    ],
    "wof:name":"Tpi Dream Quest Travel",
    "wof:placetype":"venue"
},
  "geometry": {"coordinates":[-102.804573,50.932465],"type":"Point"}
}