{
  "type": "Feature",
  "properties": {
    "addr:full":"Woodstock NB E7M 1Z7",
    "addr:postcode":"e7m 1z7",
    "iso:country":"CA",
    "sg:city":"Woodstock",
    "sg:classifiers":[
        {
            "category":"Government",
            "subcategory":"Office",
            "type":"Public Place"
        }
    ],
    "sg:phone":"+1 506 325 4419",
    "sg:postcode":"E7M 1Z7",
    "sg:province":"NB",
    "sg:tags":[
        "clinic"
    ],
    "wof:name":"Mental Health Ctr",
    "wof:placetype":"venue"
},
  "geometry": {"coordinates":[-67.571701,46.148548],"type":"Point"}
}