{
  "type": "Feature",
  "properties": {
    "iso:country":"CA",
    "sg:address":"77 Airport Rd NW # 19",
    "sg:city":"Edmonton",
    "sg:classifiers":[
        {
            "category":"Building & Trades",
            "subcategory":"Equipment Rental",
            "type":"Services"
        }
    ],
    "sg:phone":"+1 780 455 2824",
    "sg:postcode":"T5G 0W6",
    "sg:province":"AB",
    "sg:tags":[
        "aircraft",
        "leasing",
        "charter"
    ],
    "wof:name":"Kenn Borek Air Ltd",
    "wof:placetype":"venue"
},
  "geometry": {"coordinates":[-113.521149,53.568882],"type":"Point"}
}