{
  "type": "Feature",
  "properties": {
    "addr:full":"1424 Dundas St W Toronto ON M6J 1Y5",
    "addr:housenumber":"1424",
    "addr:postcode":"m6j 1y5",
    "addr:street":"Dundas St W",
    "iso:country":"CA",
    "sg:address":"1424 Dundas St W",
    "sg:city":"Toronto",
    "sg:classifiers":[
        {
            "category":"Restaurant",
            "type":"Food & Drink"
        }
    ],
    "sg:phone":"+1 416 538 3443",
    "sg:postcode":"M6J 1Y5",
    "sg:province":"ON",
    "sg:tags":[
        "cafe",
        "caterer"
    ],
    "wof:name":"Gayley Cafe & Catering",
    "wof:placetype":"venue"
},
  "geometry": {"coordinates":[-79.429436,43.649708],"type":"Point"}
}