{
  "type": "Feature",
  "properties": {
    "addr:full":"4433 Av Papineau Montreal QC H2H 1T7",
    "addr:housenumber":"4433",
    "addr:postcode":"h2h 1t7",
    "addr:street":"Av Papineau",
    "iso:country":"CA",
    "sg:address":"4433 Av Papineau",
    "sg:city":"Montreal",
    "sg:classifiers":[
        {
            "category":"Retail",
            "subcategory":"Auto Repair",
            "type":"Services"
        }
    ],
    "sg:phone":"+1 514 523 8228",
    "sg:postcode":"H2H 1T7",
    "sg:province":"QC",
    "sg:tags":[
        "repairing",
        "automobile"
    ],
    "wof:name":"Les Trois Portes",
    "wof:placetype":"venue"
},
  "geometry": {"coordinates":[-73.57334899999999,45.532528],"type":"Point"}
}