{
  "type": "Feature",
  "properties": {
    "addr:full":"Gillam MB R0B 0L0",
    "addr:postcode":"r0b 0l0",
    "iso:country":"CA",
    "sg:city":"Gillam",
    "sg:classifiers":[
        {
            "category":"Government",
            "subcategory":"Office",
            "type":"Public Place"
        }
    ],
    "sg:phone":"+1 204 456 2649",
    "sg:postcode":"R0B 0L0",
    "sg:province":"MB",
    "wof:name":"Canada Public Health",
    "wof:placetype":"venue"
},
  "geometry": {"coordinates":[-94.7089309692,56.3494224548],"type":"Point"}
}