{
  "type": "Feature",
  "properties": {
    "addr:full":"2017 Ballpark Rd Southwold ON N0L 2G0",
    "addr:housenumber":"2017",
    "addr:postcode":"n0l 2g0",
    "addr:street":"Ballpark Rd",
    "iso:country":"CA",
    "sg:address":"2017 Ballpark Rd",
    "sg:city":"Southwold",
    "sg:classifiers":[
        {
            "category":"Recreation",
            "type":"Entertainment"
        }
    ],
    "sg:phone":"+1 519 652 0855",
    "sg:postcode":"N0L 2G0",
    "sg:province":"ON",
    "sg:tags":[
        "government",
        "hall",
        "auditorium"
    ],
    "wof:name":"Oneida Community Ctr",
    "wof:placetype":"venue"
},
  "geometry": {"coordinates":[-81.35702499999999,42.810307],"type":"Point"}
}