{
  "type": "Feature",
  "properties": {
    "addr:full":"1200 Boul Ducharme LA Tuque QC G9X 3Z9",
    "addr:housenumber":"1200",
    "addr:postcode":"g9x 3z9",
    "addr:street":"Boul Ducharme",
    "iso:country":"CA",
    "sg:address":"1200 Boul Ducharme",
    "sg:city":"LA Tuque",
    "sg:classifiers":[
        {
            "category":"Shopping",
            "subcategory":"Clothing, Apparel, & Fashions",
            "type":"Retail Goods"
        }
    ],
    "sg:phone":"+1 819 523 4400",
    "sg:postcode":"G9X 3Z9",
    "sg:province":"QC",
    "sg:tags":[
        "item",
        "boutique"
    ],
    "wof:name":"Boutique Studio Mode",
    "wof:placetype":"venue"
},
  "geometry": {"coordinates":[-72.784904,47.419277],"type":"Point"}
}