{
  "type": "Feature",
  "properties": {
    "addr:full":"2720 St Etienne Blvd Windsor ON N8W 5E6",
    "addr:housenumber":"2720",
    "addr:postcode":"n8w 5e6",
    "addr:street":"St Etienne Blvd",
    "iso:country":"CA",
    "sg:address":"2720 St Etienne Blvd",
    "sg:city":"Windsor",
    "sg:classifiers":[
        {
            "category":"Building & Trades",
            "subcategory":"Construction",
            "type":"Services"
        }
    ],
    "sg:phone":"+1 519 944 2868",
    "sg:postcode":"N8W 5E6",
    "sg:province":"ON",
    "sg:tags":[
        "concrete",
        "cutting",
        "breaking",
        "sawing"
    ],
    "wof:name":"Papak Sawing & Drilling Ltd",
    "wof:placetype":"venue"
},
  "geometry": {"coordinates":[-82.97291564939999,42.2792282104],"type":"Point"}
}