{
  "type": "Feature",
  "properties": {
    "addr:full":"17504 98A Ave NW Edmonton AB T5T 5T8",
    "addr:housenumber":"17504",
    "addr:postcode":"t5t 5t8",
    "addr:street":"98A Ave Nw",
    "iso:country":"CA",
    "sg:address":"17504 98A Ave NW",
    "sg:city":"Edmonton",
    "sg:classifiers":[
        {
            "category":"Organizations",
            "subcategory":"Religious Organization",
            "type":"Services"
        }
    ],
    "sg:phone":"+1 780 486 4010",
    "sg:postcode":"T5T 5T8",
    "sg:province":"AB",
    "sg:tags":[
        "church"
    ],
    "wof:name":"Beulah Alliance Church",
    "wof:placetype":"venue"
},
  "geometry": {"coordinates":[-113.62387099999999,53.534336],"type":"Point"}
}