{
  "type": "Feature",
  "properties": {
    "addr:full":"3330 8 Ave SW Calgary AB T3C 0E7",
    "addr:housenumber":"3330",
    "addr:postcode":"t3c 0e7",
    "addr:street":"8 Ave Sw",
    "iso:country":"CA",
    "sg:address":"3330 8 Ave SW",
    "sg:city":"Calgary",
    "sg:classifiers":[
        {
            "category":"Health Services",
            "subcategory":"Nursing And Care Facility",
            "type":"Services"
        }
    ],
    "sg:phone":"+1 403 249 8915",
    "sg:postcode":"T3C 0E7",
    "sg:province":"AB",
    "sg:tags":[
        "home",
        "convalescent"
    ],
    "wof:name":"Extendicare",
    "wof:placetype":"venue"
},
  "geometry": {"coordinates":[-114.130295,51.044815],"type":"Point"}
}