{
  "type": "Feature",
  "properties": {
    "addr:full":"60 Sarsons Pl Coldstream BC V1B 2K8",
    "addr:housenumber":"60",
    "addr:postcode":"bc v1b 2k8",
    "addr:street":"Sarsons Pl",
    "iso:country":"CA",
    "sg:address":"60 Sarsons Pl",
    "sg:city":"Coldstream",
    "sg:classifiers":[
        {
            "category":"Professional",
            "type":"Services"
        }
    ],
    "sg:phone":"+1 250 549 1255",
    "sg:postcode":"V1B 2K8",
    "sg:province":"BC",
    "sg:tags":[
        "scientist"
    ],
    "wof:name":"Philtech Services",
    "wof:placetype":"venue"
},
  "geometry": {"coordinates":[-119.240219,50.244732],"type":"Point"}
}