{
  "type": "Feature",
  "properties": {
    "addr:full":"Stoney Creek ON L8E 5Y7",
    "addr:postcode":"l8e 5y7",
    "iso:country":"CA",
    "sg:city":"Stoney Creek",
    "sg:classifiers":[
        {
            "category":"Home & Garden",
            "subcategory":"Furniture",
            "type":"Retail Goods"
        }
    ],
    "sg:phone":"+1 905 643 6458",
    "sg:postcode":"L8E 5Y7",
    "sg:province":"ON",
    "wof:name":"Expressions in Wood Inc",
    "wof:placetype":"venue"
},
  "geometry": {"coordinates":[-79.6578445435,43.2171325684],"type":"Point"}
}