{
  "type": "Feature",
  "properties": {
    "addr:full":"Calgary AB T2J 0S3",
    "addr:postcode":"t2j 0s3",
    "iso:country":"CA",
    "sg:city":"Calgary",
    "sg:classifiers":[
        {
            "category":"Real Estate",
            "subcategory":"Real Estate Agent",
            "type":"Services"
        }
    ],
    "sg:phone":"+1 403 259 4111",
    "sg:postcode":"T2J 0S3",
    "sg:province":"AB",
    "sg:tags":[
        "management"
    ],
    "wof:name":"Boswell Krieger Mgmt & Rlty",
    "wof:placetype":"venue"
},
  "geometry": {"coordinates":[-114.058846,50.963337],"type":"Point"}
}