{
  "type": "Feature",
  "properties": {
    "addr:full":"10075 166 St NW Edmonton AB T5P 4Y1",
    "addr:housenumber":"10075",
    "addr:postcode":"t5p 4y1",
    "addr:street":"166 St Nw",
    "iso:country":"CA",
    "sg:address":"10075 166 St NW",
    "sg:city":"Edmonton",
    "sg:classifiers":[
        {
            "category":"Banks & Credit Unions",
            "subcategory":"Financial Services",
            "type":"Services"
        }
    ],
    "sg:phone":"+1 780 487 8700",
    "sg:postcode":"T5P 4Y1",
    "sg:province":"AB",
    "sg:tags":[
        "bankruptcy",
        "trustee"
    ],
    "wof:name":"Cameron-Okolita Inc",
    "wof:placetype":"venue"
},
  "geometry": {"coordinates":[-113.607422,53.541222],"type":"Point"}
}