{
  "type": "Feature",
  "properties": {
    "addr:full":"Richmond BC V6V 1K9",
    "addr:postcode":"v6v 1k9",
    "iso:country":"CA",
    "sg:city":"Richmond",
    "sg:classifiers":[
        {
            "category":"Manufacturing",
            "subcategory":"Rubber & Plastics",
            "type":"Manufacturing & Wholesale Goods"
        }
    ],
    "sg:phone":"+1 604 279 5535",
    "sg:postcode":"V6V 1K9",
    "sg:province":"BC",
    "sg:tags":[
        "forming"
    ],
    "wof:name":"Dha Plastics Mfg Inc",
    "wof:placetype":"venue"
},
  "geometry": {"coordinates":[-123.06648300000001,49.197521],"type":"Point"}
}