{
  "type": "Feature",
  "properties": {
    "addr:full":"43 Ormiston St Hampton ON L0B 1J0",
    "addr:housenumber":"43",
    "addr:postcode":"l0b 1j0",
    "addr:street":"Ormiston St",
    "iso:country":"CA",
    "sg:address":"43 Ormiston St",
    "sg:city":"Hampton",
    "sg:classifiers":[
        {
            "category":"Education",
            "subcategory":"School",
            "type":"Public Place"
        }
    ],
    "sg:phone":"+1 905 263 2252",
    "sg:postcode":"L0B 1J0",
    "sg:province":"ON",
    "wof:name":"Hampton Junior Public School",
    "wof:placetype":"venue"
},
  "geometry": {"coordinates":[-78.743607,43.973419],"type":"Point"}
}