{
  "type": "Feature",
  "properties": {
    "iso:country":"CA",
    "sg:address":"141 Park Rd S",
    "sg:city":"Oshawa",
    "sg:classifiers":[
        {
            "category":"Shopping",
            "subcategory":"Clothing, Apparel, & Fashions",
            "type":"Retail Goods"
        }
    ],
    "sg:phone":"+1 905 576 9219",
    "sg:postcode":"L1J 4H1",
    "sg:province":"ON",
    "sg:tags":[
        "tailor"
    ],
    "wof:name":"Neway Tailor",
    "wof:placetype":"venue"
},
  "geometry": {"coordinates":[-78.871696,43.891613],"type":"Point"}
}