{
  "type": "Feature",
  "properties": {
    "addr:full":"6075 Kestrel Rd Mississauga ON L5T 1Y8",
    "addr:housenumber":"6075",
    "addr:postcode":"l5t 1y8",
    "addr:street":"Kestrel Rd",
    "iso:country":"CA",
    "sg:address":"6075 Kestrel Rd",
    "sg:city":"Mississauga",
    "sg:classifiers":[
        {
            "category":"Manufacturing",
            "subcategory":"Printing",
            "type":"Manufacturing & Wholesale Goods"
        }
    ],
    "sg:phone":"+1 905 564 2323",
    "sg:postcode":"L5T 1Y8",
    "sg:province":"ON",
    "sg:tags":[
        "printer",
        "business",
        "form",
        "system"
    ],
    "wof:name":"Taurus Business Systems",
    "wof:placetype":"venue"
},
  "geometry": {"coordinates":[-79.662811,43.645493],"type":"Point"}
}