{
  "type": "Feature",
  "properties": {
    "addr:full":"80 Wilmot Pl Winnipeg MB R3L 2K1",
    "addr:housenumber":"80",
    "addr:postcode":"r3l 2k1",
    "addr:street":"Wilmot Pl",
    "iso:country":"CA",
    "sg:address":"80 Wilmot Pl",
    "sg:city":"Winnipeg",
    "sg:classifiers":[
        {
            "category":"Professional",
            "subcategory":"Business Services",
            "type":"Services"
        }
    ],
    "sg:phone":"+1 204 478 1773",
    "sg:postcode":"R3L 2K1",
    "sg:province":"MB",
    "sg:tags":[
        "interior",
        "consultant",
        "design",
        "decorator"
    ],
    "wof:name":"Solomon Design Group",
    "wof:placetype":"venue"
},
  "geometry": {"coordinates":[-97.150597,49.878044],"type":"Point"}
}