{
  "type": "Feature",
  "properties": {
    "iso:country":"CA",
    "sg:address":"4950 Boul Metropolitain E",
    "sg:city":"Saint-Leonard",
    "sg:classifiers":[
        {
            "category":"Autos & Motor Vehicles",
            "subcategory":"Recreational Vehicle Sales",
            "type":"Retail Goods"
        }
    ],
    "sg:phone":"+1 514 376 3633",
    "sg:postcode":"H1S 2Y4",
    "sg:province":"QC",
    "sg:tags":[
        "parts",
        "trailer",
        "hitch"
    ],
    "wof:name":"Attache DE Montreal",
    "wof:placetype":"venue"
},
  "geometry": {"coordinates":[-73.5921096802,45.5781860352],"type":"Point"}
}