{
  "type": "Feature",
  "properties": {
    "addr:full":"Pointe-Claire QC H9S 4K8",
    "addr:postcode":"h9s 4k8",
    "iso:country":"CA",
    "sg:city":"Pointe-Claire",
    "sg:classifiers":[
        {
            "category":"Personal",
            "subcategory":"Beauty Salon",
            "type":"Services"
        }
    ],
    "sg:phone":"+1 514 426 2694",
    "sg:postcode":"H9S 4K8",
    "sg:province":"QC",
    "sg:tags":[
        "barber"
    ],
    "wof:name":"Bolivar Coiffure",
    "wof:placetype":"venue"
},
  "geometry": {"coordinates":[-73.82284545900001,45.4300537109],"type":"Point"}
}