{
  "type": "Feature",
  "properties": {
    "addr:full":"5656 Av Du Parc Montreal QC H2V 4H1",
    "addr:housenumber":"5656",
    "addr:postcode":"h2v 4h1",
    "addr:street":"Av Du Parc",
    "iso:country":"CA",
    "sg:address":"5656 Av Du Parc",
    "sg:city":"Montreal",
    "sg:classifiers":[
        {
            "category":"Bars & Pubs",
            "type":"Food & Drink"
        }
    ],
    "sg:phone":"+1 514 276 0594",
    "sg:postcode":"H2V 4H1",
    "sg:province":"QC",
    "sg:tags":[
        "lounge",
        "cocktail"
    ],
    "wof:name":"Cabaret Play House",
    "wof:placetype":"venue"
},
  "geometry": {"coordinates":[-73.604027,45.522854],"type":"Point"}
}