{
  "type": "Feature",
  "properties": {
    "addr:full":"Oakville MB R0H 0Y0",
    "addr:postcode":"r0h 0y0",
    "iso:country":"CA",
    "sg:city":"Oakville",
    "sg:classifiers":[
        {
            "category":"Manufacturing",
            "subcategory":"Tools & Machinery",
            "type":"Manufacturing & Wholesale Goods"
        }
    ],
    "sg:phone":"+1 204 267 2235",
    "sg:postcode":"R0H 0Y0",
    "sg:province":"MB",
    "sg:tags":[
        "equipment",
        "livestock",
        "welding"
    ],
    "wof:name":"Brantwood Manufacturing",
    "wof:placetype":"venue"
},
  "geometry": {"coordinates":[-98.0039520264,49.9297599792],"type":"Point"}
}