{
  "type": "Feature",
  "properties": {
    "addr:full":"Trenton ON K8V 5P8",
    "addr:postcode":"k8v 5p8",
    "iso:country":"CA",
    "sg:city":"Trenton",
    "sg:classifiers":[
        {
            "category":"Real Estate",
            "subcategory":"Surveying",
            "type":"Services"
        }
    ],
    "sg:phone":"+1 613 392 2177",
    "sg:postcode":"K8V 5P8",
    "sg:province":"ON",
    "sg:tags":[
        "surveyor"
    ],
    "wof:name":"Gifford Harris Surveying Ltd",
    "wof:placetype":"venue"
},
  "geometry": {"coordinates":[-77.58493799999999,44.139179],"type":"Point"}
}