{
  "type": "Feature",
  "properties": {
    "iso:country":"CA",
    "sg:address":"10136 Av DE London",
    "sg:city":"Montreal-Nord",
    "sg:classifiers":[
        {
            "category":"Building & Trades",
            "subcategory":"Plumbing",
            "type":"Services"
        }
    ],
    "sg:phone":"+1 514 325 6421",
    "sg:postcode":"H1H 4H3",
    "sg:province":"QC",
    "sg:tags":[
        "furnace",
        "cleaning"
    ],
    "wof:name":"Bercoil Inc",
    "wof:placetype":"venue"
},
  "geometry": {"coordinates":[-73.633972,45.583374],"type":"Point"}
}