{
  "type": "Feature",
  "properties": {
    "addr:full":"155 Arthur St Truro NS B2N 1Y3",
    "addr:housenumber":"155",
    "addr:postcode":"b2n 1y3",
    "addr:street":"Arthur St",
    "iso:country":"CA",
    "sg:address":"155 Arthur St",
    "sg:city":"Truro",
    "sg:classifiers":[
        {
            "category":"Health Services",
            "subcategory":"Optometrist",
            "type":"Services"
        }
    ],
    "sg:phone":"+1 902 893 2299",
    "sg:postcode":"B2N 1Y3",
    "sg:province":"NS",
    "wof:name":"Gillam, David OD",
    "wof:placetype":"venue"
},
  "geometry": {"coordinates":[-63.281544,45.361885],"type":"Point"}
}