{
  "type": "Feature",
  "properties": {
    "addr:full":"3840 Broadway Ave Smithers BC V0J 2N0",
    "addr:housenumber":"3840",
    "addr:postcode":"v0j 2n0",
    "addr:street":"Broadway Ave",
    "iso:country":"CA",
    "sg:address":"3840 Broadway Ave",
    "sg:city":"Smithers",
    "sg:classifiers":[
        {
            "category":"Manufacturing",
            "subcategory":"Food",
            "type":"Manufacturing & Wholesale Goods"
        }
    ],
    "sg:phone":"+1 250 847 9742",
    "sg:postcode":"V0J 2N0",
    "sg:province":"BC",
    "sg:tags":[
        "baker",
        "product",
        "manufacturer"
    ],
    "wof:name":"Paul's Bakery Ltd",
    "wof:placetype":"venue"
},
  "geometry": {"coordinates":[-127.174217224,54.7800292969],"type":"Point"}
}