{
  "type": "Feature",
  "properties": {
    "addr:full":"71 Lakeshore Dr North Bay ON P1A 2A4",
    "addr:housenumber":"71",
    "addr:postcode":"p1a 2a4",
    "addr:street":"Lakeshore Dr",
    "iso:country":"CA",
    "sg:address":"71 Lakeshore Dr",
    "sg:city":"North Bay",
    "sg:classifiers":[
        {
            "category":"Home & Garden",
            "subcategory":"Home Furnishings",
            "type":"Retail Goods"
        }
    ],
    "sg:phone":"+1 705 472 1200",
    "sg:postcode":"P1A 2A4",
    "sg:province":"ON",
    "sg:tags":[
        "venetian",
        "blind"
    ],
    "wof:name":"Factory Blind Outlet",
    "wof:placetype":"venue"
},
  "geometry": {"coordinates":[-79.453827,46.293091],"type":"Point"}
}