{
  "type": "Feature",
  "properties": {
    "addr:full":"210 Main St E Listowel ON N4W 2B7",
    "addr:housenumber":"210",
    "addr:postcode":"n4w 2b7",
    "addr:street":"Main St E",
    "iso:country":"CA",
    "sg:address":"210 Main St E",
    "sg:city":"Listowel",
    "sg:classifiers":[
        {
            "category":"Professional",
            "subcategory":"Employment Agencies",
            "type":"Services"
        }
    ],
    "sg:phone":"+1 519 291 2726",
    "sg:postcode":"N4W 2B7",
    "sg:province":"ON",
    "sg:tags":[
        "equipment",
        "opportunity",
        "electric",
        "supply"
    ],
    "wof:name":"Partners in Employment",
    "wof:placetype":"venue"
},
  "geometry": {"coordinates":[-80.95156860349999,43.7308197021],"type":"Point"}
}