{
  "type": "Feature",
  "properties": {
    "iso:country":"CA",
    "sg:city":"Pointe Du Bois",
    "sg:classifiers":[
        {
            "category":"Travel",
            "subcategory":"Hotels & Motels",
            "type":"Entertainment"
        }
    ],
    "sg:phone":"+1 204 884 2321",
    "sg:postcode":"R0E 1N0",
    "sg:province":"MB",
    "sg:tags":[
        "resort",
        "camp",
        "fishing"
    ],
    "wof:name":"Trail End Camp",
    "wof:placetype":"venue"
},
  "geometry": {"coordinates":[-95.5507965088,50.2994537354],"type":"Point"}
}