{
  "type": "Feature",
  "properties": {
    "addr:full":"Orono ON L0B 1M0",
    "addr:postcode":"l0b 1m0",
    "iso:country":"CA",
    "sg:city":"Orono",
    "sg:classifiers":[
        {
            "category":"Local Transit",
            "type":"Transportation"
        }
    ],
    "sg:phone":"+1 905 983 5245",
    "sg:postcode":"L0B 1M0",
    "sg:province":"ON",
    "sg:tags":[
        "limousine"
    ],
    "wof:name":"Hourglass Distributors",
    "wof:placetype":"venue"
},
  "geometry": {"coordinates":[-78.6164855957,43.977230072],"type":"Point"}
}