{
  "type": "Feature",
  "properties": {
    "addr:full":"129 Riding Ranch Rd South River ON P0A 1X0",
    "addr:housenumber":"129",
    "addr:postcode":"p0a 1x0",
    "addr:street":"Riding Ranch Rd",
    "iso:country":"CA",
    "sg:address":"129 Riding Ranch Rd",
    "sg:city":"South River",
    "sg:classifiers":[
        {
            "category":"Recreation",
            "type":"Entertainment"
        }
    ],
    "sg:phone":"+1 705 386 7465",
    "sg:postcode":"P0A 1X0",
    "sg:province":"ON",
    "sg:tags":[
        "riding",
        "academy"
    ],
    "wof:name":"Stewart Coughlin Riding Ranch",
    "wof:placetype":"venue"
},
  "geometry": {"coordinates":[-79.38183600000001,45.840519],"type":"Point"}
}