{
  "type": "Feature",
  "properties": {
    "addr:full":"11815 145 St NW Edmonton AB T5L 2H4",
    "addr:housenumber":"11815",
    "addr:postcode":"t5l 2h4",
    "addr:street":"145 St Nw",
    "iso:country":"CA",
    "sg:address":"11815 145 St NW",
    "sg:city":"Edmonton",
    "sg:classifiers":[
        {
            "category":"Shopping",
            "subcategory":"Musical Instruments",
            "type":"Retail Goods"
        }
    ],
    "sg:phone":"+1 780 453 5033",
    "sg:postcode":"T5L 2H4",
    "sg:province":"AB",
    "sg:tags":[
        "instruction",
        "music"
    ],
    "wof:name":"Impromptu Music Studios Inc",
    "wof:placetype":"venue"
},
  "geometry": {"coordinates":[-113.571014404,53.5707588196],"type":"Point"}
}