{
  "type": "Feature",
  "properties": {
    "addr:full":"Tichborne ON K0H 2V0",
    "addr:postcode":"k0h 2v0",
    "iso:country":"CA",
    "sg:city":"Tichborne",
    "sg:classifiers":[
        {
            "category":"Travel",
            "subcategory":"Hotels & Motels",
            "type":"Entertainment"
        }
    ],
    "sg:phone":"+1 613 375 6649",
    "sg:postcode":"K0H 2V0",
    "sg:province":"ON",
    "sg:tags":[
        "campground",
        "resort"
    ],
    "wof:name":"Sunset Country Camp Ground Inc",
    "wof:placetype":"venue"
},
  "geometry": {"coordinates":[-76.6769790649,44.6643676758],"type":"Point"}
}