{
  "type": "Feature",
  "properties": {
    "addr:full":"345 Lakeshore Rd E # 305 Oakville ON L6J 1J5",
    "addr:housenumber":"345",
    "addr:postcode":"l6j 1j5",
    "addr:street":"Lakeshore Rd E # 305",
    "iso:country":"CA",
    "sg:address":"345 Lakeshore Rd E # 305",
    "sg:city":"Oakville",
    "sg:classifiers":[
        {
            "category":"Freight",
            "type":"Transportation"
        }
    ],
    "sg:phone":"+1 905 337 2732",
    "sg:postcode":"L6J 1J5",
    "sg:province":"ON",
    "wof:name":"Biglift Shipping Bv",
    "wof:placetype":"venue"
},
  "geometry": {"coordinates":[-79.66527600000001,43.448742],"type":"Point"}
}