{
  "type": "Feature",
  "properties": {
    "addr:full":"251 Rue Principale Saint-Cyrille-DE-L'Islet QC G0R 2W0",
    "addr:housenumber":"251",
    "addr:postcode":"g0r 2w0",
    "addr:street":"Rue Principale",
    "iso:country":"CA",
    "sg:address":"251 Rue Principale",
    "sg:city":"Saint-Cyrille-DE-L'Islet",
    "sg:classifiers":[
        {
            "category":"Bars & Pubs",
            "type":"Food & Drink"
        }
    ],
    "sg:phone":"+1 418 247 7844",
    "sg:postcode":"G0R 2W0",
    "sg:province":"QC",
    "sg:tags":[
        "lounge",
        "cocktail"
    ],
    "wof:name":"Bar Le Rendez-Vous",
    "wof:placetype":"venue"
},
  "geometry": {"coordinates":[-70.331535,47.089802],"type":"Point"}
}