{
  "type": "Feature",
  "properties": {
    "addr:full":"125 Moatfield Dr North York ON M3B 3L6",
    "addr:housenumber":"125",
    "addr:postcode":"m3b 3l6",
    "addr:street":"Moatfield Dr",
    "iso:country":"CA",
    "sg:address":"125 Moatfield Dr",
    "sg:city":"North York",
    "sg:classifiers":[
        {
            "category":"Restaurant",
            "type":"Food & Drink"
        }
    ],
    "sg:phone":"+1 416 391 1424",
    "sg:postcode":"M3B 3L6",
    "sg:province":"ON",
    "wof:name":"Duncan House Fine Dining",
    "wof:placetype":"venue"
},
  "geometry": {"coordinates":[-79.349648,43.759735],"type":"Point"}
}