{
  "type": "Feature",
  "properties": {
    "addr:full":"2962 4th Ave W Vancouver BC V6K 1R4",
    "addr:housenumber":"2962",
    "addr:postcode":"v6k 1r4",
    "addr:street":"4Th Ave W",
    "iso:country":"CA",
    "sg:address":"2962 4th Ave W",
    "sg:city":"Vancouver",
    "sg:classifiers":[
        {
            "category":"Retail",
            "subcategory":"Laundry & Dry Cleaning",
            "type":"Services"
        }
    ],
    "sg:phone":"+1 604 736 6821",
    "sg:postcode":"V6K 1R4",
    "sg:province":"BC",
    "wof:name":"Ocean Marine Laundry & Dry Cln",
    "wof:placetype":"venue"
},
  "geometry": {"coordinates":[-123.17144,49.268272],"type":"Point"}
}