{
  "type": "Feature",
  "properties": {
    "addr:full":"926 Pointe Line Port Lambton ON N0P 2B0",
    "addr:housenumber":"926",
    "addr:postcode":"n0p 2b0",
    "addr:street":"Pointe Line Port",
    "iso:country":"CA",
    "sg:address":"926 Pointe Line",
    "sg:city":"Port Lambton",
    "sg:classifiers":[
        {
            "category":"Building & Trades",
            "subcategory":"Construction",
            "type":"Services"
        }
    ],
    "sg:phone":"+1 519 627 6510",
    "sg:postcode":"N0P 2B0",
    "sg:province":"ON",
    "sg:tags":[
        "general",
        "contractor"
    ],
    "wof:name":"Lozon & Kilbride Gen Contr",
    "wof:placetype":"venue"
},
  "geometry": {"coordinates":[-82.40173299999999,42.642506],"type":"Point"}
}