{
  "type": "Feature",
  "properties": {
    "addr:full":"8914 140A St Surrey BC V3V 7H3",
    "addr:housenumber":"8914",
    "addr:postcode":"v3v 7h3",
    "addr:street":"140A St",
    "iso:country":"CA",
    "sg:address":"8914 140A St",
    "sg:city":"Surrey",
    "sg:classifiers":[
        {
            "category":"Shopping",
            "subcategory":"Clothing, Apparel, & Fashions",
            "type":"Retail Goods"
        }
    ],
    "sg:phone":"+1 604 592 4567",
    "sg:postcode":"V3V 7H3",
    "sg:province":"BC",
    "sg:tags":[
        "tailor"
    ],
    "wof:name":"Glamour Ladies Tailor & Btq",
    "wof:placetype":"venue"
},
  "geometry": {"coordinates":[-122.830215454,49.105178833],"type":"Point"}
}