{
  "type": "Feature",
  "properties": {
    "addr:full":"5575 Route 117 Baie-Sainte-Anne NB E9A 1H2",
    "addr:housenumber":"5575",
    "addr:postcode":"e9a 1h2",
    "addr:street":"Route 117",
    "iso:country":"CA",
    "sg:address":"5575 Route 117",
    "sg:city":"Baie-Sainte-Anne",
    "sg:classifiers":[
        {
            "category":"Food & Beverages",
            "subcategory":"Groceries & Convenience Stores",
            "type":"Retail Goods"
        }
    ],
    "sg:phone":"+1 506 228 4211",
    "sg:postcode":"E9A 1H2",
    "sg:province":"NB",
    "sg:tags":[
        "grocer"
    ],
    "wof:name":"Baie Ste Anne CO Op Ltd",
    "wof:placetype":"venue"
},
  "geometry": {"coordinates":[-64.95611599999999,47.051205],"type":"Point"}
}