{
  "type": "Feature",
  "properties": {
    "addr:full":"1632 3rd Ave W Vancouver BC V6J 1K2",
    "addr:housenumber":"1632",
    "addr:postcode":"v6j 1k2",
    "addr:street":"3Rd Ave W",
    "iso:country":"CA",
    "sg:address":"1632 3rd Ave W",
    "sg:city":"Vancouver",
    "sg:classifiers":[
        {
            "category":"Wholesale",
            "subcategory":"Non-durable Goods",
            "type":"Manufacturing & Wholesale Goods"
        }
    ],
    "sg:phone":"+1 604 731 0503",
    "sg:postcode":"V6J 1K2",
    "sg:province":"BC",
    "wof:name":"Made By Humans",
    "wof:placetype":"venue"
},
  "geometry": {"coordinates":[-123.14170799999999,49.268711],"type":"Point"}
}