{
  "type": "Feature",
  "properties": {
    "iso:country":"CA",
    "sg:address":"1632 3rd Ave W",
    "sg:city":"Vancouver",
    "sg:classifiers":[
        {
            "category":"Wholesale",
            "subcategory":"Non-durable Goods",
            "type":"Manufacturing & Wholesale Goods"
        }
    ],
    "sg:phone":"+1 604 731 0503",
    "sg:postcode":"V6J 1K2",
    "sg:province":"BC",
    "wof:name":"Made By Humans",
    "wof:placetype":"venue"
},
  "geometry": {"coordinates":[-123.141708,49.268711],"type":"Point"}
}