{
  "type": "Feature",
  "properties": {
    "addr:full":"1780 Chancellor Dr Winnipeg MB R3T 4B6",
    "addr:housenumber":"1780",
    "addr:postcode":"r3t 4b6",
    "addr:street":"Chancellor Dr",
    "iso:country":"CA",
    "sg:address":"1780 Chancellor Dr",
    "sg:city":"Winnipeg",
    "sg:classifiers":[
        {
            "category":"Health Services",
            "subcategory":"Health Practitioner",
            "type":"Services"
        }
    ],
    "sg:phone":"+1 204 269 4706",
    "sg:postcode":"R3T 4B6",
    "sg:province":"MB",
    "sg:tags":[
        "psychologist"
    ],
    "wof:name":"Turner, L Craig",
    "wof:placetype":"venue"
},
  "geometry": {"coordinates":[-97.1605148315,49.8059272766],"type":"Point"}
}