{
  "type": "Feature",
  "properties": {
    "addr:full":"47 Westpark Dr Gloucester ON K1B 3G5",
    "addr:housenumber":"47",
    "addr:postcode":"k1b 3g5",
    "addr:street":"Westpark Dr",
    "iso:country":"CA",
    "sg:address":"47 Westpark Dr",
    "sg:city":"Gloucester",
    "sg:classifiers":[
        {
            "category":"Professional",
            "subcategory":"Business Services",
            "type":"Services"
        }
    ],
    "sg:phone":"+1 613 830 5706",
    "sg:postcode":"K1B 3G5",
    "sg:province":"ON",
    "sg:tags":[
        "interior",
        "consultant",
        "design",
        "decorator"
    ],
    "wof:name":"Textile Decor",
    "wof:placetype":"venue"
},
  "geometry": {"coordinates":[-75.573128,45.435589],"type":"Point"}
}