{
  "type": "Feature",
  "properties": {
    "addr:full":"463 Rue Du Cardinal-Taschereau Quebec QC G1K 1H3",
    "addr:housenumber":"463",
    "addr:postcode":"g1k 1h3",
    "addr:street":"Rue Du Cardinal-Taschereau",
    "iso:country":"CA",
    "sg:address":"463 Rue Du Cardinal-Taschereau",
    "sg:city":"Quebec",
    "sg:classifiers":[
        {
            "category":"Retail",
            "subcategory":"Auto Repair",
            "type":"Services"
        }
    ],
    "sg:phone":"+1 418 649 0081",
    "sg:postcode":"G1K 1H3",
    "sg:province":"QC",
    "sg:tags":[
        "body",
        "automobile",
        "painting"
    ],
    "wof:name":"Carrossier Robitaille Enr",
    "wof:placetype":"venue"
},
  "geometry": {"coordinates":[-71.240295,46.811523],"type":"Point"}
}