{
  "type": "Feature",
  "properties": {
    "addr:full":"414 Rue Collard O Alma QC G8B 1N2",
    "addr:housenumber":"414",
    "addr:postcode":"g8b 1n2",
    "addr:street":"Rue Collard O",
    "iso:country":"CA",
    "sg:address":"414 Rue Collard O",
    "sg:city":"Alma",
    "sg:classifiers":[
        {
            "category":"Professional",
            "subcategory":"Management & Consulting",
            "type":"Services"
        }
    ],
    "sg:phone":"+1 418 480 2228",
    "sg:postcode":"G8B 1N2",
    "sg:province":"QC",
    "sg:tags":[
        "consultant",
        "recreation",
        "program"
    ],
    "wof:name":"Regroupement Loisirs & Sports",
    "wof:placetype":"venue"
},
  "geometry": {"coordinates":[-71.64906311039999,48.5479431152],"type":"Point"}
}