{
  "type": "Feature",
  "properties": {
    "iso:country":"CA",
    "sg:address":"180 Rue Joseph-Robertson",
    "sg:city":"Sherbrooke",
    "sg:classifiers":[
        {
            "category":"Wholesale",
            "subcategory":"Fruits & Vegetables",
            "type":"Manufacturing & Wholesale Goods"
        }
    ],
    "sg:phone":"+1 819 823 8817",
    "sg:postcode":"J1L 2X3",
    "sg:province":"QC",
    "wof:name":"Fruits & Legumes DE L'Estrie",
    "wof:placetype":"venue"
},
  "geometry": {"coordinates":[-71.9733581543,45.3926773071],"type":"Point"}
}