{
  "type": "Feature",
  "properties": {
    "addr:full":"220 Boul D'Anjou Chateauguay QC J6K 1C5",
    "addr:housenumber":"220",
    "addr:postcode":"j6k 1c5",
    "addr:street":"Boul D'Anjou",
    "iso:country":"CA",
    "sg:address":"220 Boul D'Anjou",
    "sg:city":"Chateauguay",
    "sg:classifiers":[
        {
            "category":"Shopping",
            "subcategory":"Shoes",
            "type":"Retail Goods"
        }
    ],
    "sg:phone":"+1 450 698 3550",
    "sg:postcode":"J6K 1C5",
    "sg:province":"QC",
    "wof:name":"Foot Locker",
    "wof:placetype":"venue"
},
  "geometry": {"coordinates":[-73.740112,45.361485],"type":"Point"}
}