{
  "type": "Feature",
  "properties": {
    "iso:country":"CA",
    "sg:city":"Toronto",
    "sg:classifiers":[
        {
            "category":"Professional",
            "subcategory":"Accounting & Tax Preparation",
            "type":"Services"
        }
    ],
    "sg:phone":"+1 416 955 1214",
    "sg:postcode":"M5E 1R4",
    "sg:province":"ON",
    "sg:tags":[
        "accountant"
    ],
    "wof:name":"Basic Line Inc",
    "wof:placetype":"venue"
},
  "geometry": {"coordinates":[-79.375206,43.64249],"type":"Point"}
}