{
  "type": "Feature",
  "properties": {
    "addr:full":"334 Bradwick Dr Concord ON L4K 1K8",
    "addr:housenumber":"334",
    "addr:postcode":"l4k 1k8",
    "addr:street":"Bradwick Dr",
    "iso:country":"CA",
    "sg:address":"334 Bradwick Dr",
    "sg:city":"Concord",
    "sg:classifiers":[
        {
            "category":"Building & Trades",
            "subcategory":"Landscaping Services",
            "type":"Services"
        }
    ],
    "sg:phone":"+1 905 669 6838",
    "sg:postcode":"L4K 1K8",
    "sg:province":"ON",
    "sg:tags":[
        "designer",
        "landscape"
    ],
    "wof:name":"Landscape Planning Ltd",
    "wof:placetype":"venue"
},
  "geometry": {"coordinates":[-79.4845123291,43.8158493042],"type":"Point"}
}