{
  "type": "Feature",
  "properties": {
    "iso:country":"CA",
    "sg:address":"156 Bridge St",
    "sg:city":"Princeton",
    "sg:classifiers":[
        {
            "category":"Travel",
            "subcategory":"Hotels & Motels",
            "type":"Entertainment"
        }
    ],
    "sg:phone":"+1 250 295 6906",
    "sg:postcode":"V0X 1W0",
    "sg:province":"BC",
    "wof:name":"Princeton Motel",
    "wof:placetype":"venue"
},
  "geometry": {"coordinates":[-120.50753021200001,49.4597167969],"type":"Point"}
}