{
  "type": "Feature",
  "properties": {
    "addr:full":"800 Rue Sherbrooke Lachine QC H8S 1H2",
    "addr:housenumber":"800",
    "addr:postcode":"h8s 1h2",
    "addr:street":"Rue Sherbrooke",
    "iso:country":"CA",
    "sg:address":"800 Rue Sherbrooke",
    "sg:city":"Lachine",
    "sg:classifiers":[
        {
            "category":"Professional",
            "subcategory":"Research",
            "type":"Services"
        }
    ],
    "sg:phone":"+1 514 634 7205",
    "sg:postcode":"H8S 1H2",
    "sg:province":"QC",
    "sg:tags":[
        "environmental",
        "ecological"
    ],
    "wof:name":"Grame",
    "wof:placetype":"venue"
},
  "geometry": {"coordinates":[-73.67124938960001,45.4451065063],"type":"Point"}
}