{
  "type": "Feature",
  "properties": {
    "addr:full":"91 Cumberland Street South Suite 301 Thunder Bay P7B 6A7",
    "addr:housenumber":"91",
    "addr:postcode":"p7b 6a7",
    "addr:street":"Cumberland Street South Suite 301",
    "iso:country":"CA",
    "sg:address":"91 Cumberland Street South Suite 301",
    "sg:city":"Thunder Bay",
    "sg:classifiers":[
        {
            "category":"Professional",
            "subcategory":"Computer Services",
            "type":"Services"
        }
    ],
    "sg:postcode":"P7B 6A7",
    "sg:tags":[
        "web-design",
        "web-development",
        "lms",
        "lcms",
        "search-engine-optimization",
        "seo",
        "training-management-system",
        "learning-management-system"
    ],
    "sg:website":"http://www.sencia.ca",
    "wof:name":"Sencia ",
    "wof:placetype":"venue"
},
  "geometry": {"coordinates":[-89.22255149999999,48.4317715],"type":"Point"}
}