{
  "type": "Feature",
  "properties": {
    "addr:full":"5605 Av DE Gaspe Montreal QC H2T 2A4",
    "addr:housenumber":"5605",
    "addr:postcode":"h2t 2a4",
    "addr:street":"Av De Gaspe",
    "iso:country":"CA",
    "sg:address":"5605 Av DE Gaspe",
    "sg:city":"Montreal",
    "sg:classifiers":[
        {
            "category":"Wholesale",
            "subcategory":"Non-durable Goods",
            "type":"Manufacturing & Wholesale Goods"
        }
    ],
    "sg:phone":"+1 514 279 6328",
    "sg:postcode":"H2T 2A4",
    "sg:province":"QC",
    "sg:tags":[
        "leather",
        "suspender",
        "belt"
    ],
    "wof:name":"Belgo Lux Inc",
    "wof:placetype":"venue"
},
  "geometry": {"coordinates":[-73.5980453491,45.528175354],"type":"Point"}
}