{
  "type": "Feature",
  "properties": {
    "addr:full":"30 Av DE L'Eglise Evain QC J0Z 1Y0",
    "addr:postcode":"j0z 1y0",
    "addr:street":"30 Av De L'Eglise Evain",
    "iso:country":"CA",
    "sg:address":"30 Av DE L'Eglise",
    "sg:city":"Evain",
    "sg:classifiers":[
        {
            "category":"Social Services",
            "subcategory":"Child Care",
            "type":"Services"
        }
    ],
    "sg:phone":"+1 819 768 8372",
    "sg:postcode":"J0Z 1Y0",
    "sg:province":"QC",
    "wof:name":"Garderie Scolaire L'Oasis",
    "wof:placetype":"venue"
},
  "geometry": {"coordinates":[-79.230698,48.322769],"type":"Point"}
}