{
  "type": "Feature",
  "properties": {
    "addr:full":"Calgary AB T2N 1M7",
    "addr:postcode":"t2n 1m7",
    "iso:country":"CA",
    "sg:city":"Calgary",
    "sg:classifiers":[
        {
            "category":"Shopping",
            "subcategory":"Florist",
            "type":"Retail Goods"
        }
    ],
    "sg:phone":"+1 403 245 5759",
    "sg:postcode":"T2N 1M7",
    "sg:province":"AB",
    "wof:name":"Itinerant Flowers Design Ltd",
    "wof:placetype":"venue"
},
  "geometry": {"coordinates":[-114.098457,51.06451],"type":"Point"}
}