{
  "type": "Feature",
  "properties": {
    "addr:full":"221 Rue Pie-Ix Saint-Joseph-DE-Sorel QC J3R 3W6",
    "addr:housenumber":"221",
    "addr:postcode":"j3r 3w6",
    "addr:street":"Rue Pie-Ix",
    "iso:country":"CA",
    "sg:address":"221 Rue Pie-Ix",
    "sg:city":"Saint-Joseph-DE-Sorel",
    "sg:classifiers":[
        {
            "category":"Retail",
            "subcategory":"Auto Repair",
            "type":"Services"
        }
    ],
    "sg:phone":"+1 450 742 2888",
    "sg:postcode":"J3R 3W6",
    "sg:province":"QC",
    "sg:tags":[
        "repairing",
        "automobile"
    ],
    "wof:name":"Garage Special Svc",
    "wof:placetype":"venue"
},
  "geometry": {"coordinates":[-73.1311340332,46.0432395935],"type":"Point"}
}