{
  "type": "Feature",
  "properties": {
    "addr:full":"Quebec QC G1K 5Y3",
    "addr:postcode":"g1k 5y3",
    "iso:country":"CA",
    "sg:city":"Quebec",
    "sg:classifiers":[
        {
            "category":"Manufacturing",
            "subcategory":"Furniture",
            "type":"Manufacturing & Wholesale Goods"
        }
    ],
    "sg:phone":"+1 418 648 9100",
    "sg:postcode":"G1K 5Y3",
    "sg:province":"QC",
    "sg:tags":[
        "maker",
        "store",
        "cabinet"
    ],
    "wof:name":"Menuiserie DE LA Capitale Inc",
    "wof:placetype":"venue"
},
  "geometry": {"coordinates":[-71.2349243164,46.8207473755],"type":"Point"}
}