{
  "type": "Feature",
  "properties": {
    "iso:country":"CA",
    "sg:address":"315 Rue Moreau",
    "sg:city":"Saint-Nicolas",
    "sg:classifiers":[
        {
            "category":"Manufacturing",
            "subcategory":"Metals",
            "type":"Manufacturing & Wholesale Goods"
        }
    ],
    "sg:phone":"+1 418 831 3069",
    "sg:postcode":"G7A 3J8",
    "sg:province":"QC",
    "sg:tags":[
        "shelter",
        "garage",
        "temporary"
    ],
    "wof:name":"Abris DE LA Capitale Enr",
    "wof:placetype":"venue"
},
  "geometry": {"coordinates":[-71.300697,46.731014],"type":"Point"}
}