{
  "type": "Feature",
  "properties": {
    "iso:country":"CA",
    "sg:address":"3405 Boul Wilfrid-Hamel # 330",
    "sg:city":"Quebec",
    "sg:classifiers":[
        {
            "category":"Professional",
            "subcategory":"Detective & Security Services",
            "type":"Services"
        }
    ],
    "sg:phone":"+1 418 681 0609",
    "sg:postcode":"G1P 2J3",
    "sg:province":"QC",
    "sg:tags":[
        "guard",
        "patrol"
    ],
    "wof:name":"Corps Canadien-Commissionnaire",
    "wof:placetype":"venue"
},
  "geometry": {"coordinates":[-71.3097457886,46.8061561584],"type":"Point"}
}