{
  "type": "Feature",
  "properties": {
    "addr:full":"Kemptville ON K0G 1J0",
    "addr:postcode":"k0g 1j0",
    "iso:country":"CA",
    "sg:city":"Kemptville",
    "sg:classifiers":[
        {
            "category":"Personal",
            "subcategory":"Beauty Salon",
            "type":"Services"
        }
    ],
    "sg:phone":"+1 613 258 4604",
    "sg:postcode":"K0G 1J0",
    "sg:province":"ON",
    "wof:name":"Hair Diversity",
    "wof:placetype":"venue"
},
  "geometry": {"coordinates":[-75.6376037598,45.0158309937],"type":"Point"}
}