{
  "type": "Feature",
  "properties": {
    "addr:full":"14345 123 Ave NW Edmonton AB T5L 2Y1",
    "addr:housenumber":"14345",
    "addr:postcode":"t5l 2y1",
    "addr:street":"123 Ave Nw",
    "iso:country":"CA",
    "sg:address":"14345 123 Ave NW",
    "sg:city":"Edmonton",
    "sg:classifiers":[
        {
            "category":"Manufacturing",
            "subcategory":"Glass & Minerals",
            "type":"Manufacturing & Wholesale Goods"
        }
    ],
    "sg:phone":"+1 780 452 4710",
    "sg:postcode":"T5L 2Y1",
    "sg:province":"AB",
    "sg:tags":[
        "building",
        "home",
        "log",
        "cabin"
    ],
    "wof:name":"Steels Industrial Products",
    "wof:placetype":"venue"
},
  "geometry": {"coordinates":[-113.568901,53.576622],"type":"Point"}
}