{
  "type": "Feature",
  "properties": {
    "iso:country":"CA",
    "sg:address":"783 Rue Notre-Dame",
    "sg:city":"Repentigny",
    "sg:classifiers":[
        {
            "category":"Shopping",
            "type":"Retail Goods"
        }
    ],
    "sg:phone":"+1 450 657 1000",
    "sg:postcode":"J5Y 1B4",
    "sg:province":"QC",
    "sg:tags":[
        "hearing",
        "equipment",
        "supply",
        "impaired"
    ],
    "wof:name":"Chantal Labelle Audioprothesis",
    "wof:placetype":"venue"
},
  "geometry": {"coordinates":[-73.4247970581,45.7606620789],"type":"Point"}
}