{
  "type": "Feature",
  "properties": {
    "addr:full":"149 Tall Pines Dr Penetanguishene ON L9M 1R3",
    "addr:housenumber":"149",
    "addr:postcode":"l9m 1r3",
    "addr:street":"Tall Pines Dr",
    "iso:country":"CA",
    "sg:address":"149 Tall Pines Dr",
    "sg:city":"Penetanguishene",
    "sg:classifiers":[
        {
            "category":"Building & Trades",
            "subcategory":"Construction",
            "type":"Services"
        }
    ],
    "sg:phone":"+1 705 533 0881",
    "sg:postcode":"L9M 1R3",
    "sg:province":"ON",
    "sg:tags":[
        "woodworker"
    ],
    "wof:name":"Pinedale Woodworking",
    "wof:placetype":"venue"
},
  "geometry": {"coordinates":[-79.935356,44.76812],"type":"Point"}
}