{
  "type": "Feature",
  "properties": {
    "addr:full":"Wimborne AB T0M 2G0",
    "addr:postcode":"t0m 2g0",
    "iso:country":"CA",
    "sg:city":"Wimborne",
    "sg:classifiers":[
        {
            "category":"Retail",
            "subcategory":"Auto Repair",
            "type":"Services"
        }
    ],
    "sg:phone":"+1 403 631 3747",
    "sg:postcode":"T0M 2G0",
    "sg:province":"AB",
    "sg:tags":[
        "repairing",
        "automobile"
    ],
    "wof:name":"Wimborne Motors",
    "wof:placetype":"venue"
},
  "geometry": {"coordinates":[-113.58317599999999,51.867352],"type":"Point"}
}