{
  "type": "Feature",
  "properties": {
    "addr:full":"Anjou QC H1M 1W6",
    "addr:postcode":"h1m 1w6",
    "iso:country":"CA",
    "sg:city":"Anjou",
    "sg:classifiers":[
        {
            "category":"Shopping",
            "subcategory":"Computers & Home Electronics",
            "type":"Retail Goods"
        }
    ],
    "sg:phone":"+1 514 353 3585",
    "sg:postcode":"H1M 1W6",
    "sg:province":"QC",
    "sg:tags":[
        "television",
        "radio"
    ],
    "wof:name":"Maison Sony",
    "wof:placetype":"venue"
},
  "geometry": {"coordinates":[-73.5396652222,45.6102523804],"type":"Point"}
}