{
  "type": "Feature",
  "properties": {
    "iso:country":"CA",
    "sg:city":"Montreal",
    "sg:classifiers":[
        {
            "category":"Shopping",
            "subcategory":"Shoes",
            "type":"Retail Goods"
        }
    ],
    "sg:phone":"+1 514 351 6503",
    "sg:postcode":"H1N 1E9",
    "sg:province":"QC",
    "wof:name":"Chaussures Panda Inc",
    "wof:placetype":"venue"
},
  "geometry": {"coordinates":[-73.539093,45.590172],"type":"Point"}
}