{
  "type": "Feature",
  "properties": {
    "addr:full":"676 Sheppard Ave W North York ON M3H 2S5",
    "addr:housenumber":"676",
    "addr:postcode":"m3h 2s5",
    "addr:street":"Sheppard Ave W",
    "iso:country":"CA",
    "sg:address":"676 Sheppard Ave W",
    "sg:city":"North York",
    "sg:classifiers":[
        {
            "category":"Recreation",
            "type":"Entertainment"
        }
    ],
    "sg:phone":"+1 416 630 7169",
    "sg:postcode":"M3H 2S5",
    "sg:province":"ON",
    "sg:tags":[
        "parlor",
        "billiard"
    ],
    "wof:name":"Phantom Billiards",
    "wof:placetype":"venue"
},
  "geometry": {"coordinates":[-79.44287872309999,43.7547454834],"type":"Point"}
}