{
  "type": "Feature",
  "properties": {
    "iso:country":"CA",
    "sg:city":"Montreal",
    "sg:classifiers":[
        {
            "category":"Professional",
            "subcategory":"Lawyer & Legal Services",
            "type":"Services"
        }
    ],
    "sg:phone":"+1 514 939 2129",
    "sg:postcode":"H3H 2P5",
    "sg:province":"QC",
    "sg:tags":[
        "attorney"
    ],
    "wof:name":"Lucrece, Joseph",
    "wof:placetype":"venue"
},
  "geometry": {"coordinates":[-73.54927062989999,45.5222892761],"type":"Point"}
}