{
  "type": "Feature",
  "properties": {
    "addr:full":"573 Rue Bonaventure Trois-Rivieres QC G9A 2B6",
    "addr:housenumber":"573",
    "addr:postcode":"g9a 2b6",
    "addr:street":"Rue Bonaventure Trois-Rivieres",
    "iso:country":"CA",
    "sg:address":"573 Rue Bonaventure",
    "sg:city":"Trois-Rivieres",
    "sg:classifiers":[
        {
            "category":"Health Services",
            "subcategory":"Doctor",
            "type":"Services"
        }
    ],
    "sg:phone":"+1 819 691 1077",
    "sg:postcode":"G9A 2B6",
    "sg:province":"QC",
    "sg:tags":[
        "physician",
        "surgeon"
    ],
    "wof:name":"Truchon, Christian MD",
    "wof:placetype":"venue"
},
  "geometry": {"coordinates":[-72.54518899999999,46.344463],"type":"Point"}
}