{
  "type": "Feature",
  "properties": {
    "addr:full":"5001 47th Ave Thorsby AB T0C 2P0",
    "addr:housenumber":"5001",
    "addr:postcode":"t0c 2p0",
    "addr:street":"47Th Ave",
    "iso:country":"CA",
    "sg:address":"5001 47th Ave",
    "sg:city":"Thorsby",
    "sg:classifiers":[
        {
            "category":"Building & Trades",
            "subcategory":"Electrical",
            "type":"Services"
        }
    ],
    "sg:phone":"+1 780 789 3753",
    "sg:postcode":"T0C 2P0",
    "sg:province":"AB",
    "sg:tags":[
        "electric",
        "contractor"
    ],
    "wof:name":"Bacsik Electric Ltd",
    "wof:placetype":"venue"
},
  "geometry": {"coordinates":[-114.046852,53.22377],"type":"Point"}
}