{
  "type": "Feature",
  "properties": {
    "addr:full":"659 Exeter Rd London ON N6E 1L3",
    "addr:housenumber":"659",
    "addr:postcode":"n6e 1l3",
    "addr:street":"Exeter Rd",
    "iso:country":"CA",
    "sg:address":"659 Exeter Rd",
    "sg:city":"London",
    "sg:classifiers":[
        {
            "category":"Government",
            "subcategory":"Office",
            "type":"Public Place"
        }
    ],
    "sg:phone":"+1 519 873 4100",
    "sg:postcode":"N6E 1L3",
    "sg:province":"ON",
    "wof:name":"Ontario Transportation Dept",
    "wof:placetype":"venue"
},
  "geometry": {"coordinates":[-81.222954,42.925217],"type":"Point"}
}