{
  "type": "Feature",
  "properties": {
    "iso:country":"CA",
    "sg:address":"415 Spruce",
    "sg:city":"Kaslo",
    "sg:classifiers":[
        {
            "category":"Government",
            "subcategory":"Office",
            "type":"Public Place"
        }
    ],
    "sg:phone":"+1 250 353 7568",
    "sg:postcode":"V0G 1M0",
    "sg:province":"BC",
    "sg:tags":[
        "village"
    ],
    "wof:name":"Kaslo Village Works Dept",
    "wof:placetype":"venue"
},
  "geometry": {"coordinates":[-116.911743164,49.9132118225],"type":"Point"}
}