{
  "type": "Feature",
  "properties": {
    "addr:full":"1414 112 Rte Weedon QC J0B 3J0",
    "addr:housenumber":"1414",
    "addr:postcode":"j0b 3j0",
    "addr:street":"112 Rte",
    "iso:country":"CA",
    "sg:address":"1414 112 Rte",
    "sg:city":"Weedon",
    "sg:classifiers":[
        {
            "category":"Freight",
            "type":"Transportation"
        }
    ],
    "sg:phone":"+1 819 877 5168",
    "sg:postcode":"J0B 3J0",
    "sg:province":"QC",
    "sg:tags":[
        "trucking"
    ],
    "wof:name":"Francis Lachance Inc",
    "wof:placetype":"venue"
},
  "geometry": {"coordinates":[-71.4597167969,45.7093696594],"type":"Point"}
}