{
  "type": "Feature",
  "properties": {
    "iso:country":"CA",
    "sg:city":"Montreal",
    "sg:classifiers":[
        {
            "category":"Professional",
            "subcategory":"Employment Agencies",
            "type":"Services"
        }
    ],
    "sg:phone":"+1 514 842 7771",
    "sg:postcode":"H2Y 2P1",
    "sg:province":"QC",
    "sg:tags":[
        "consultant",
        "search",
        "executive"
    ],
    "wof:name":"Sag Ressources Humaines Inc",
    "wof:placetype":"venue"
},
  "geometry": {"coordinates":[-73.555321,45.502117],"type":"Point"}
}