{
  "type": "Feature",
  "properties": {
    "addr:full":"465 Rogers Rd York ON M6M 1A8",
    "addr:housenumber":"465",
    "addr:postcode":"m6m 1a8",
    "addr:street":"Rogers Rd",
    "iso:country":"CA",
    "sg:address":"465 Rogers Rd",
    "sg:city":"York",
    "sg:classifiers":[
        {
            "category":"Shopping",
            "subcategory":"Musical Instruments",
            "type":"Retail Goods"
        }
    ],
    "sg:phone":"+1 416 651 3332",
    "sg:postcode":"M6M 1A8",
    "sg:province":"ON",
    "wof:name":"Rogers Music Ctr",
    "wof:placetype":"venue"
},
  "geometry": {"coordinates":[-79.46588134770001,43.6820602417],"type":"Point"}
}