{
  "type": "Feature",
  "properties": {
    "addr:full":"3264 Lawrence Ave E Scarborough ON M1H 1A4",
    "addr:housenumber":"3264",
    "addr:postcode":"m1h 1a4",
    "addr:street":"Lawrence Ave E",
    "iso:country":"CA",
    "sg:address":"3264 Lawrence Ave E",
    "sg:city":"Scarborough",
    "sg:classifiers":[
        {
            "category":"Restaurant",
            "type":"Food & Drink"
        }
    ],
    "sg:phone":"+1 416 438 4949",
    "sg:postcode":"M1H 1A4",
    "sg:province":"ON",
    "wof:name":"Bendale Restaurant",
    "wof:placetype":"venue"
},
  "geometry": {"coordinates":[-79.238739,43.757107],"type":"Point"}
}