{
  "type": "Feature",
  "properties": {
    "iso:country":"CA",
    "sg:city":"Roxboro",
    "sg:classifiers":[
        {
            "category":"Restaurant",
            "type":"Food & Drink"
        }
    ],
    "sg:phone":"+1 514 421 2723",
    "sg:postcode":"H8Y 1W4",
    "sg:province":"QC",
    "wof:name":"Resto Cafes Rex",
    "wof:placetype":"venue"
},
  "geometry": {"coordinates":[-73.8530654907,45.4935646057],"type":"Point"}
}