{
  "type": "Feature",
  "properties": {
    "addr:full":"2028 Stephens St Vancouver BC V6K 3W1",
    "addr:housenumber":"2028",
    "addr:postcode":"v6k 3w1",
    "addr:street":"Stephens St",
    "iso:country":"CA",
    "sg:address":"2028 Stephens St",
    "sg:city":"Vancouver",
    "sg:classifiers":[
        {
            "category":"Personal",
            "subcategory":"Beauty Salon",
            "type":"Services"
        }
    ],
    "sg:phone":"+1 604 732 0433",
    "sg:postcode":"V6K 3W1",
    "sg:province":"BC",
    "wof:name":"Hair By Negar",
    "wof:placetype":"venue"
},
  "geometry": {"coordinates":[-123.166061,49.268066],"type":"Point"}
}