{
  "type": "Feature",
  "properties": {
    "addr:full":"700 Rue DE Saint-Jovite Mont-Tremblant QC J8E 3J8",
    "addr:housenumber":"700",
    "addr:postcode":"j8e 3j8",
    "addr:street":"Rue De Saint-Jovite",
    "iso:country":"CA",
    "sg:address":"700 Rue DE Saint-Jovite",
    "sg:city":"Mont-Tremblant",
    "sg:classifiers":[
        {
            "category":"Social Services",
            "subcategory":"Child Care",
            "type":"Services"
        }
    ],
    "sg:phone":"+1 819 425 9922",
    "sg:postcode":"J8E 3J8",
    "sg:province":"QC",
    "wof:name":"Centre DE LA Petite Enfance",
    "wof:placetype":"venue"
},
  "geometry": {"coordinates":[-74.586342,46.119034],"type":"Point"}
}