{
  "type": "Feature",
  "properties": {
    "iso:country":"CA",
    "sg:address":"265 St Vincent St",
    "sg:city":"Barrie",
    "sg:classifiers":[
        {
            "category":"Organizations",
            "subcategory":"Religious Organization",
            "type":"Services"
        }
    ],
    "sg:phone":"+1 705 722 6620",
    "sg:postcode":"L4M 3Z9",
    "sg:province":"ON",
    "sg:tags":[
        "church"
    ],
    "wof:name":"Church of the Nazarene",
    "wof:placetype":"venue"
},
  "geometry": {"coordinates":[-79.681961,44.403622],"type":"Point"}
}