{
  "type": "Feature",
  "properties": {
    "addr:full":"247 Centre Ave Blumenort MB R0A 0C0",
    "addr:housenumber":"247",
    "addr:postcode":"r0a 0c0",
    "addr:street":"Centre Ave",
    "iso:country":"CA",
    "sg:address":"247 Centre Ave",
    "sg:city":"Blumenort",
    "sg:classifiers":[
        {
            "category":"Farming",
            "subcategory":"Poultry Farm",
            "type":"Manufacturing & Wholesale Goods"
        }
    ],
    "sg:phone":"+1 204 326 2384",
    "sg:postcode":"R0A 0C0",
    "sg:province":"MB",
    "wof:name":"Friendly Family Farms Ltd",
    "wof:placetype":"venue"
},
  "geometry": {"coordinates":[-96.69016999999999,49.604256],"type":"Point"}
}