{
  "type": "Feature",
  "properties": {
    "addr:full":"714 10 St # 1 Canmore AB T1W 2A6",
    "addr:housenumber":"10;# 1",
    "addr:postcode":"t1w 2a6",
    "addr:street":"714;St",
    "iso:country":"CA",
    "sg:address":"714 10 St # 1",
    "sg:city":"Canmore",
    "sg:classifiers":[
        {
            "category":"Professional",
            "subcategory":"Accounting & Tax Preparation",
            "type":"Services"
        }
    ],
    "sg:phone":"+1 403 678 4444",
    "sg:postcode":"T1W 2A6",
    "sg:province":"AB",
    "sg:tags":[
        "accountant"
    ],
    "wof:name":"Collins Barrow",
    "wof:placetype":"venue"
},
  "geometry": {"coordinates":[-115.358902,51.090603],"type":"Point"}
}