{
  "type": "Feature",
  "properties": {
    "addr:full":"4402 55 St Red Deer AB T4N 2H1",
    "addr:housenumber":"4402",
    "addr:postcode":"t4n 2h1",
    "addr:street":"55 St",
    "iso:country":"CA",
    "sg:address":"4402 55 St",
    "sg:city":"Red Deer",
    "sg:classifiers":[
        {
            "category":"Organizations",
            "subcategory":"Professional Association",
            "type":"Services"
        }
    ],
    "sg:phone":"+1 403 342 0010",
    "sg:postcode":"T4N 2H1",
    "sg:province":"AB",
    "wof:name":"Army Cadets",
    "wof:placetype":"venue"
},
  "geometry": {"coordinates":[-113.79966735799999,52.2741394043],"type":"Point"}
}