{
  "type": "Feature",
  "properties": {
    "iso:country":"CA",
    "sg:address":"17532 County Rd 21",
    "sg:city":"Trenton",
    "sg:classifiers":[
        {
            "category":"Retail",
            "subcategory":"Veterinary Services",
            "type":"Services"
        }
    ],
    "sg:phone":"+1 613 394 4811",
    "sg:postcode":"K8V 5P8",
    "sg:province":"ON",
    "sg:tags":[
        "veterinarian"
    ],
    "wof:name":"Steen, Mike DVM",
    "wof:placetype":"venue"
},
  "geometry": {"coordinates":[-77.5763092041,44.1011390686],"type":"Point"}
}