{
  "type": "Feature",
  "properties": {
    "addr:full":"250 Sherbrooke St Peterborough ON K9J 2N4",
    "addr:housenumber":"250",
    "addr:postcode":"k9j 2n4",
    "addr:street":"Sherbrooke St",
    "iso:country":"CA",
    "sg:address":"250 Sherbrooke St",
    "sg:city":"Peterborough",
    "sg:classifiers":[
        {
            "category":"Restaurant",
            "type":"Food & Drink"
        }
    ],
    "sg:phone":"+1 705 876 6155",
    "sg:postcode":"K9J 2N4",
    "sg:province":"ON",
    "wof:name":"Two Fifty Cafe",
    "wof:placetype":"venue"
},
  "geometry": {"coordinates":[-78.323357,44.300781],"type":"Point"}
}