{
  "type": "Feature",
  "properties": {
    "addr:full":"11 Aldgate Ave Etobicoke ON M8Y 3L4",
    "addr:housenumber":"11",
    "addr:postcode":"m8y 3l4",
    "addr:street":"Aldgate Ave",
    "iso:country":"CA",
    "sg:address":"11 Aldgate Ave",
    "sg:city":"Etobicoke",
    "sg:classifiers":[
        {
            "category":"Organizations",
            "subcategory":"Religious Organization",
            "type":"Services"
        }
    ],
    "sg:phone":"+1 416 503 8854",
    "sg:postcode":"M8Y 3L4",
    "sg:province":"ON",
    "sg:tags":[
        "church"
    ],
    "wof:name":"Church of the Transfiguration",
    "wof:placetype":"venue"
},
  "geometry": {"coordinates":[-79.486786,43.630436],"type":"Point"}
}