{
  "type": "Feature",
  "properties": {
    "addr:full":"40 Norfinch Dr North York ON M3N 1X1",
    "addr:housenumber":"40",
    "addr:postcode":"m3n 1x1",
    "addr:street":"Norfinch Dr",
    "iso:country":"CA",
    "sg:address":"40 Norfinch Dr",
    "sg:city":"North York",
    "sg:classifiers":[
        {
            "category":"Government",
            "subcategory":"Police Station",
            "type":"Public Place"
        }
    ],
    "sg:phone":"+1 416 808 2222",
    "sg:postcode":"M3N 1X1",
    "sg:province":"ON",
    "sg:tags":[
        "department"
    ],
    "wof:name":"Metropolitan Toronto Police",
    "wof:placetype":"venue"
},
  "geometry": {"coordinates":[-79.5277328491,43.7571334839],"type":"Point"}
}