{
  "type": "Feature",
  "properties": {
    "addr:full":"Richmond BC V7A 5J5",
    "addr:postcode":"v7a 5j5",
    "iso:country":"CA",
    "sg:city":"Richmond",
    "sg:classifiers":[
        {
            "category":"Food & Beverages",
            "subcategory":"Bakery",
            "type":"Retail Goods"
        }
    ],
    "sg:phone":"+1 604 277 8467",
    "sg:postcode":"V7A 5J5",
    "sg:province":"BC",
    "sg:tags":[
        "doughnut"
    ],
    "wof:name":"Tim Hortons",
    "wof:placetype":"venue"
},
  "geometry": {"coordinates":[-123.099091,49.133144],"type":"Point"}
}