{
  "type": "Feature",
  "properties": {
    "iso:country":"CA",
    "sg:address":"9528 120 St",
    "sg:city":"Surrey",
    "sg:classifiers":[
        {
            "category":"Food & Beverages",
            "subcategory":"Groceries & Convenience Stores",
            "type":"Retail Goods"
        }
    ],
    "sg:phone":"+1 604 581 0251",
    "sg:postcode":"V3V 4C1",
    "sg:province":"BC",
    "sg:tags":[
        "grocer"
    ],
    "wof:name":"Buy Rite Foods",
    "wof:placetype":"venue"
},
  "geometry": {"coordinates":[-122.890090942,49.175743103],"type":"Point"}
}