{
  "type": "Feature",
  "properties": {
    "addr:full":"175 Carlton St Toronto ON M5A 2K3",
    "addr:housenumber":"175",
    "addr:postcode":"m5a 2k3",
    "addr:street":"Carlton St",
    "iso:country":"CA",
    "sg:address":"175 Carlton St",
    "sg:city":"Toronto",
    "sg:classifiers":[
        {
            "category":"Professional",
            "subcategory":"Management & Consulting",
            "type":"Services"
        }
    ],
    "sg:phone":"+1 416 971 9570",
    "sg:postcode":"M5A 2K3",
    "sg:province":"ON",
    "sg:tags":[
        "consultant",
        "business"
    ],
    "wof:name":"Metrix Group",
    "wof:placetype":"venue"
},
  "geometry": {"coordinates":[-79.371696,43.66333],"type":"Point"}
}