{
  "type": "Feature",
  "properties": {
    "addr:full":"1345 Redwood Ave Winnipeg MB R2X 0Y9",
    "addr:housenumber":"1345",
    "addr:postcode":"r2x 0y9",
    "addr:street":"Redwood Ave",
    "iso:country":"CA",
    "sg:address":"1345 Redwood Ave",
    "sg:city":"Winnipeg",
    "sg:classifiers":[
        {
            "category":"Wholesale",
            "subcategory":"Auto Parts",
            "type":"Manufacturing & Wholesale Goods"
        }
    ],
    "sg:phone":"+1 204 697 5500",
    "sg:postcode":"R2X 0Y9",
    "sg:province":"MB",
    "sg:tags":[
        "automobile",
        "supply"
    ],
    "wof:name":"General Motors of Canada Ltd",
    "wof:placetype":"venue"
},
  "geometry": {"coordinates":[-97.175766,49.931889],"type":"Point"}
}