{
  "type": "Feature",
  "properties": {
    "addr:full":"Waskatenau AB T0A 3P0",
    "addr:postcode":"t0a 3p0",
    "iso:country":"CA",
    "sg:city":"Waskatenau",
    "sg:classifiers":[
        {
            "category":"Travel",
            "subcategory":"Hotels & Motels",
            "type":"Entertainment"
        }
    ],
    "sg:phone":"+1 780 358 2733",
    "sg:postcode":"T0A 3P0",
    "sg:province":"AB",
    "wof:name":"Waskatenau Motel",
    "wof:placetype":"venue"
},
  "geometry": {"coordinates":[-112.785247803,54.0970001221],"type":"Point"}
}