{
  "type": "Feature",
  "properties": {
    "addr:full":"313 Av DE LA Cathedrale Rimouski QC G5L 5J5",
    "addr:postcode":"g5l 5j5",
    "addr:street":"313 Av De La Cathedrale",
    "iso:country":"CA",
    "sg:address":"313 Av DE LA Cathedrale",
    "sg:city":"Rimouski",
    "sg:classifiers":[
        {
            "category":"Government",
            "subcategory":"Office",
            "type":"Public Place"
        }
    ],
    "sg:phone":"+1 418 724 3220",
    "sg:postcode":"G5L 5J5",
    "sg:province":"QC",
    "sg:tags":[
        "village"
    ],
    "wof:name":"Rimouski Pavillon Polyvalent",
    "wof:placetype":"venue"
},
  "geometry": {"coordinates":[-68.52010300000001,48.44627],"type":"Point"}
}