{
  "type": "Feature",
  "properties": {
    "addr:full":"PO Box 826 STN Postal Box Ctr Red Deer AB T4N 5H2",
    "addr:housenumber":"po",
    "addr:postcode":"826;t4n 5h2",
    "addr:street":"Box",
    "iso:country":"CA",
    "sg:address":"PO Box 826 STN Postal Box Ctr",
    "sg:city":"Red Deer",
    "sg:classifiers":[
        {
            "category":"Building & Trades",
            "subcategory":"Construction",
            "type":"Services"
        }
    ],
    "sg:phone":"+1 403 343 0440",
    "sg:postcode":"T4N 5H2",
    "sg:province":"AB",
    "sg:tags":[
        "masonry",
        "contractor"
    ],
    "wof:name":"S & S Masonry",
    "wof:placetype":"venue"
},
  "geometry": {"coordinates":[-113.817436,52.262302],"type":"Point"}
}