{
  "type": "Feature",
  "properties": {
    "addr:full":"6405 Stanley Ave Niagara Falls ON L2G 3Y6",
    "addr:housenumber":"6405",
    "addr:postcode":"l2g 3y6",
    "addr:street":"Stanley Ave",
    "iso:country":"CA",
    "sg:address":"6405 Stanley Ave",
    "sg:city":"Niagara Falls",
    "sg:classifiers":[
        {
            "category":"Building & Trades",
            "subcategory":"Landscaping Services",
            "type":"Services"
        }
    ],
    "sg:phone":"+1 905 354 4723",
    "sg:postcode":"L2G 3Y6",
    "sg:province":"ON",
    "sg:tags":[
        "landscape",
        "contractor"
    ],
    "wof:name":"Earthdance Landscaping",
    "wof:placetype":"venue"
},
  "geometry": {"coordinates":[-79.084487915,43.0826034546],"type":"Point"}
}