{
  "type": "Feature",
  "properties": {
    "addr:full":"257 Rue Pigeon Beloeil QC J3G 2P7",
    "addr:housenumber":"257",
    "addr:postcode":"j3g 2p7",
    "addr:street":"Rue Pigeon",
    "iso:country":"CA",
    "sg:address":"257 Rue Pigeon",
    "sg:city":"Beloeil",
    "sg:classifiers":[
        {
            "category":"Building & Trades",
            "subcategory":"Electrical",
            "type":"Services"
        }
    ],
    "sg:phone":"+1 450 464 4928",
    "sg:postcode":"J3G 2P7",
    "sg:province":"QC",
    "sg:tags":[
        "electric",
        "contractor"
    ],
    "wof:name":"Pierre Bisson Electrique",
    "wof:placetype":"venue"
},
  "geometry": {"coordinates":[-73.2063674927,45.5678825378],"type":"Point"}
}