{
  "type": "Feature",
  "properties": {
    "addr:full":"101 Maurice Dr Oakville ON L6K 2W6",
    "addr:housenumber":"101",
    "addr:postcode":"l6k 2w6",
    "addr:street":"Maurice Dr",
    "iso:country":"CA",
    "sg:address":"101 Maurice Dr",
    "sg:city":"Oakville",
    "sg:classifiers":[
        {
            "category":"Health Services",
            "subcategory":"Health Practitioner",
            "type":"Services"
        }
    ],
    "sg:phone":"+1 905 845 6922",
    "sg:postcode":"L6K 2W6",
    "sg:province":"ON",
    "sg:tags":[
        "physiotherapist"
    ],
    "wof:name":"Oakville Physiotherapy Ctr",
    "wof:placetype":"venue"
},
  "geometry": {"coordinates":[-79.677971,43.436916],"type":"Point"}
}