{
  "type": "Feature",
  "properties": {
    "addr:full":"430 204 Rte Sainte-Justine QC G0R 1Y0",
    "addr:housenumber":"430 204",
    "addr:postcode":"g0r 1y0",
    "addr:street":"Rte Sainte-Justine",
    "iso:country":"CA",
    "sg:address":"430 204 Rte",
    "sg:city":"Sainte-Justine",
    "sg:classifiers":[
        {
            "category":"Retail",
            "subcategory":"Auto Repair",
            "type":"Services"
        }
    ],
    "sg:phone":"+1 418 383 3621",
    "sg:postcode":"G0R 1Y0",
    "sg:province":"QC",
    "sg:tags":[
        "body",
        "automobile",
        "painting"
    ],
    "wof:name":"Garage Mario Cote Engr",
    "wof:placetype":"venue"
},
  "geometry": {"coordinates":[-70.347427,46.409904],"type":"Point"}
}