{
  "type": "Feature",
  "properties": {
    "addr:full":"PO Box 354 STN Main Whitecourt AB T7S 1N5",
    "addr:housenumber":"po",
    "addr:postcode":"t7s 1n5",
    "addr:street":"Box 354 Stn Main",
    "iso:country":"CA",
    "sg:address":"PO Box 354 STN Main",
    "sg:city":"Whitecourt",
    "sg:classifiers":[
        {
            "category":"Building & Trades",
            "subcategory":"Construction",
            "type":"Services"
        }
    ],
    "sg:phone":"+1 780 706 0139",
    "sg:postcode":"T7S 1N5",
    "sg:province":"AB",
    "sg:tags":[
        "contractor",
        "general"
    ],
    "wof:name":"Savage Renovations & Carpentry",
    "wof:placetype":"venue"
},
  "geometry": {"coordinates":[-115.70787799999999,54.139435],"type":"Point"}
}