{
  "type": "Feature",
  "properties": {
    "addr:full":"Newmarket ON L3Y 3E3",
    "addr:postcode":"l3y 3e3",
    "iso:country":"CA",
    "sg:city":"Newmarket",
    "sg:classifiers":[
        {
            "category":"Insurance",
            "subcategory":"Insurance Agent",
            "type":"Services"
        }
    ],
    "sg:phone":"+1 416 410 5458",
    "sg:postcode":"L3Y 3E3",
    "sg:province":"ON",
    "wof:name":"Benson Kearley & Assoc",
    "wof:placetype":"venue"
},
  "geometry": {"coordinates":[-79.4329986572,44.0708694458],"type":"Point"}
}