{
  "type": "Feature",
  "properties": {
    "iso:country":"CA",
    "sg:address":"57 Queensway Ave",
    "sg:city":"Espanola",
    "sg:classifiers":[
        {
            "category":"Retail",
            "subcategory":"Auto Repair",
            "type":"Services"
        }
    ],
    "sg:phone":"+1 705 869 1826",
    "sg:postcode":"P5E 1H9",
    "sg:province":"ON",
    "sg:tags":[
        "wrecker"
    ],
    "wof:name":"Dan's Towing & Recovery",
    "wof:placetype":"venue"
},
  "geometry": {"coordinates":[-81.7562866211,46.2497596741],"type":"Point"}
}