{
  "type": "Feature",
  "properties": {
    "iso:country":"CA",
    "sg:address":"455 Seymour St",
    "sg:city":"Kamloops",
    "sg:classifiers":[
        {
            "category":"Shopping",
            "type":"Retail Goods"
        }
    ],
    "sg:phone":"+1 250 374 5462",
    "sg:postcode":"V2C 2G7",
    "sg:province":"BC",
    "sg:tags":[
        "limb",
        "artificial"
    ],
    "wof:name":"Rowmac Orthopedic Svc Ltd",
    "wof:placetype":"venue"
},
  "geometry": {"coordinates":[-120.330696106,50.6748046875],"type":"Point"}
}