{
  "type": "Feature",
  "properties": {
    "addr:full":"PO Box 696 Duck Lake SK S0K 1J0",
    "addr:housenumber":"po",
    "addr:postcode":"s0k 1j0",
    "addr:street":"Box 696 Duck Lake",
    "iso:country":"CA",
    "sg:address":"PO Box 696",
    "sg:city":"Duck Lake",
    "sg:classifiers":[
        {
            "category":"Autos & Motor Vehicles",
            "subcategory":"Fuel & Gas Station",
            "type":"Retail Goods"
        }
    ],
    "sg:phone":"+1 306 467 4410",
    "sg:postcode":"S0K 1J0",
    "sg:province":"SK",
    "sg:tags":[
        "oil"
    ],
    "wof:name":"Mallard's Discount Gas & Rest",
    "wof:placetype":"venue"
},
  "geometry": {"coordinates":[-106.224205,52.809196],"type":"Point"}
}