{
  "type": "Feature",
  "properties": {
    "addr:full":"950 6E Av Saint-Georges QC G5Y 3T9",
    "addr:housenumber":"950",
    "addr:postcode":"g5y 3t9",
    "addr:street":"6E Av",
    "iso:country":"CA",
    "sg:address":"950 6E Av",
    "sg:city":"Saint-Georges",
    "sg:classifiers":[
        {
            "category":"Wholesale",
            "subcategory":"Machinery & Supplies",
            "type":"Manufacturing & Wholesale Goods"
        }
    ],
    "sg:phone":"+1 418 228 3622",
    "sg:postcode":"G5Y 3T9",
    "sg:province":"QC",
    "sg:tags":[
        "tractor"
    ],
    "wof:name":"Lessard Aurelien Inc",
    "wof:placetype":"venue"
},
  "geometry": {"coordinates":[-70.67115,46.123348],"type":"Point"}
}