{
  "type": "Feature",
  "properties": {
    "addr:full":"8271 Fairlane Rd Richmond BC V7C 1Y3",
    "addr:housenumber":"8271",
    "addr:postcode":"bc v7c 1y3",
    "addr:street":"Fairlane Rd",
    "iso:country":"CA",
    "sg:address":"8271 Fairlane Rd",
    "sg:city":"Richmond",
    "sg:classifiers":[
        {
            "category":"Building & Trades",
            "subcategory":"Construction",
            "type":"Services"
        }
    ],
    "sg:phone":"+1 604 272 2952",
    "sg:postcode":"V7C 1Y3",
    "sg:province":"BC",
    "sg:tags":[
        "contractor",
        "paving",
        "general"
    ],
    "wof:name":"Galaxy Paving CO Ltd",
    "wof:placetype":"venue"
},
  "geometry": {"coordinates":[-123.19180299999999,49.152332],"type":"Point"}
}