{
  "type": "Feature",
  "properties": {
    "iso:country":"CA",
    "sg:address":"24 Main St",
    "sg:city":"Rossburn",
    "sg:classifiers":[
        {
            "category":"Home & Garden",
            "subcategory":"Furniture",
            "type":"Retail Goods"
        }
    ],
    "sg:phone":"+1 204 859 2562",
    "sg:postcode":"R0J 1V0",
    "sg:province":"MB",
    "wof:name":"Cjg Farm Auto Supply",
    "wof:placetype":"venue"
},
  "geometry": {"coordinates":[-100.81082916299999,50.6689682007],"type":"Point"}
}