{
  "type": "Feature",
  "properties": {
    "addr:full":"Concord ON L4K 4B2",
    "addr:postcode":"l4k 4b2",
    "iso:country":"CA",
    "sg:city":"Concord",
    "sg:classifiers":[
        {
            "category":"Wholesale",
            "subcategory":"Durable Goods & Equipment",
            "type":"Manufacturing & Wholesale Goods"
        }
    ],
    "sg:phone":"+1 416 335 9300",
    "sg:postcode":"L4K 4B2",
    "sg:province":"ON",
    "sg:tags":[
        "engineering",
        "supply"
    ],
    "wof:name":"Wade Tech",
    "wof:placetype":"venue"
},
  "geometry": {"coordinates":[-79.5359802246,43.8072509766],"type":"Point"}
}