{
  "type": "Feature",
  "properties": {
    "addr:full":"87 Main St E Grimsby ON L3M 1N6",
    "addr:housenumber":"87",
    "addr:postcode":"l3m 1n6",
    "addr:street":"Main St E",
    "iso:country":"CA",
    "sg:address":"87 Main St E",
    "sg:city":"Grimsby",
    "sg:classifiers":[
        {
            "category":"Health Services",
            "subcategory":"Optometrist",
            "type":"Services"
        }
    ],
    "sg:phone":"+1 905 945 4823",
    "sg:postcode":"L3M 1N6",
    "sg:province":"ON",
    "wof:name":"Agate, James C OD",
    "wof:placetype":"venue"
},
  "geometry": {"coordinates":[-79.554962,43.190807],"type":"Point"}
}