{
  "type": "Feature",
  "properties": {
    "iso:country":"CA",
    "sg:address":"6400 Lundy's Lane",
    "sg:city":"Niagara Falls",
    "sg:classifiers":[
        {
            "category":"Travel",
            "subcategory":"Hotels & Motels",
            "type":"Entertainment"
        }
    ],
    "sg:phone":"+1 905 356 1161",
    "sg:postcode":"L2G 1T6",
    "sg:province":"ON",
    "wof:name":"Cairn Croft Best Western Hotel",
    "wof:placetype":"venue"
},
  "geometry": {"coordinates":[-77.56536865229999,45.0424156189],"type":"Point"}
}