{
  "type": "Feature",
  "properties": {
    "addr:full":"Orillia ON L3V 6H5",
    "addr:postcode":"l3v 6h5",
    "iso:country":"CA",
    "sg:city":"Orillia",
    "sg:classifiers":[
        {
            "category":"Manufacturing",
            "subcategory":"Glass & Minerals",
            "type":"Manufacturing & Wholesale Goods"
        }
    ],
    "sg:phone":"+1 705 327 1158",
    "sg:postcode":"L3V 6H5",
    "sg:province":"ON",
    "sg:tags":[
        "stone"
    ],
    "wof:name":"Cut Above Natural Stone",
    "wof:placetype":"venue"
},
  "geometry": {"coordinates":[-79.41822814939999,44.606590271],"type":"Point"}
}