{
  "type": "Feature",
  "properties": {
    "addr:full":"600 Agnes St New Westminster BC V3M 1G8",
    "addr:housenumber":"600",
    "addr:postcode":"v3m 1g8",
    "addr:street":"Agnes St",
    "iso:country":"CA",
    "sg:address":"600 Agnes St",
    "sg:city":"New Westminster",
    "sg:classifiers":[
        {
            "category":"Shopping",
            "subcategory":"Used Merchandise",
            "type":"Retail Goods"
        }
    ],
    "sg:phone":"+1 604 521 3332",
    "sg:postcode":"V3M 1G8",
    "sg:province":"BC",
    "sg:tags":[
        "book",
        "rare",
        "dealer"
    ],
    "wof:name":"Royal Book Mart",
    "wof:placetype":"venue"
},
  "geometry": {"coordinates":[-122.909897,49.204639],"type":"Point"}
}