{
  "type": "Feature",
  "properties": {
    "iso:country":"CA",
    "sg:address":"904 64 Ave NW",
    "sg:city":"Calgary",
    "sg:classifiers":[
        {
            "category":"Autos & Motor Vehicles",
            "subcategory":"Fuel & Gas Station",
            "type":"Retail Goods"
        }
    ],
    "sg:phone":"+1 403 274 3335",
    "sg:postcode":"T2K 0M5",
    "sg:province":"AB",
    "sg:tags":[
        "oil"
    ],
    "wof:name":"Esso Imperial Oil",
    "wof:placetype":"venue"
},
  "geometry": {"coordinates":[-114.07749939,51.1112289429],"type":"Point"}
}