{
  "type": "Feature",
  "properties": {
    "iso:country":"CA",
    "sg:address":"735 41 Ave NE",
    "sg:city":"Calgary",
    "sg:classifiers":[
        {
            "category":"Home & Garden",
            "subcategory":"Building Materials",
            "type":"Retail Goods"
        }
    ],
    "sg:phone":"+1 403 277 0771",
    "sg:postcode":"T2E 6R5",
    "sg:province":"AB",
    "sg:tags":[
        "windows"
    ],
    "wof:name":"Calgary Sash & Door Ltd",
    "wof:placetype":"venue"
},
  "geometry": {"coordinates":[-114.045310974,51.0914154053],"type":"Point"}
}