{
  "type": "Feature",
  "properties": {
    "iso:country":"CA",
    "sg:address":"17204 111 St NW",
    "sg:city":"Edmonton",
    "sg:classifiers":[
        {
            "category":"Building & Trades",
            "subcategory":"Plumbing",
            "type":"Services"
        }
    ],
    "sg:phone":"+1 780 456 7396",
    "sg:postcode":"T5X 3J8",
    "sg:province":"AB",
    "sg:tags":[
        "contractor"
    ],
    "wof:name":"Lawrence's Mechanical Svc Ltd",
    "wof:placetype":"venue"
},
  "geometry": {"coordinates":[-113.51445007300001,53.6344299316],"type":"Point"}
}