{
  "type": "Feature",
  "properties": {
    "addr:full":"2404 2 Ave N Lethbridge AB T1H 0C2",
    "addr:housenumber":"2404",
    "addr:postcode":"t1h 0c2",
    "addr:street":"2 Ave N",
    "iso:country":"CA",
    "sg:address":"2404 2 Ave N",
    "sg:city":"Lethbridge",
    "sg:classifiers":[
        {
            "category":"Building & Trades",
            "subcategory":"Electrical",
            "type":"Services"
        }
    ],
    "sg:phone":"+1 403 320 5511",
    "sg:postcode":"T1H 0C2",
    "sg:province":"AB",
    "sg:tags":[
        "electric",
        "contractor"
    ],
    "wof:name":"Bjd Electric Ltd",
    "wof:placetype":"venue"
},
  "geometry": {"coordinates":[-112.809288,49.700104],"type":"Point"}
}