{
  "type": "Feature",
  "properties": {
    "addr:full":"RR 1 Kirkfield ON K0M 2B0",
    "addr:postcode":"k0m 2b0",
    "addr:street":"Rr 1 Kirkfield",
    "iso:country":"CA",
    "sg:address":"RR 1",
    "sg:city":"Kirkfield",
    "sg:classifiers":[
        {
            "category":"Travel",
            "subcategory":"Campground",
            "type":"Entertainment"
        }
    ],
    "sg:phone":"+1 705 438 1353",
    "sg:postcode":"K0M 2B0",
    "sg:province":"ON",
    "sg:tags":[
        "camp"
    ],
    "wof:name":"Camp Kirk",
    "wof:placetype":"venue"
},
  "geometry": {"coordinates":[-78.9797821045,44.5627403259],"type":"Point"}
}