{
  "type": "Feature",
  "properties": {
    "addr:full":"Grande Prairie AB T8V 7X5",
    "addr:postcode":"t8v 7x5",
    "iso:country":"CA",
    "sg:city":"Grande Prairie",
    "sg:classifiers":[
        {
            "category":"Restaurant",
            "type":"Food & Drink"
        }
    ],
    "sg:phone":"+1 780 532 5200",
    "sg:postcode":"T8V 7X5",
    "sg:province":"AB",
    "wof:name":"Booster Juice",
    "wof:placetype":"venue"
},
  "geometry": {"coordinates":[-118.79489100000001,55.171162],"type":"Point"}
}