{
  "type": "Feature",
  "properties": {
    "addr:full":"792 East River Rd New Glasgow NS B2H 3S3",
    "addr:housenumber":"792",
    "addr:postcode":"b2h 3s3",
    "addr:street":"East River Rd",
    "iso:country":"CA",
    "sg:address":"792 East River Rd",
    "sg:city":"New Glasgow",
    "sg:classifiers":[
        {
            "category":"Health Services",
            "subcategory":"Health Practitioner",
            "type":"Services"
        }
    ],
    "sg:phone":"+1 902 752 3910",
    "sg:postcode":"B2H 3S3",
    "sg:province":"NS",
    "sg:tags":[
        "physiotherapist"
    ],
    "wof:name":"Physiotherapy Atlantic",
    "wof:placetype":"venue"
},
  "geometry": {"coordinates":[-62.642151,45.573551],"type":"Point"}
}