{
  "type": "Feature",
  "properties": {
    "iso:country":"CA",
    "sg:address":"577 Marginal Rd",
    "sg:city":"Halifax",
    "sg:classifiers":[
        {
            "category":"Professional",
            "subcategory":"Employment Agencies",
            "type":"Services"
        }
    ],
    "sg:phone":"+1 902 421 1778",
    "sg:postcode":"B3H 4P6",
    "sg:province":"NS",
    "sg:tags":[
        "contractor"
    ],
    "wof:name":"Halterm Limited",
    "wof:placetype":"venue"
},
  "geometry": {"coordinates":[-63.5684738159,44.6300773621],"type":"Point"}
}