{
  "type": "Feature",
  "properties": {
    "addr:full":"7645 Royal Oak Ave Burnaby BC V5J 4K2",
    "addr:housenumber":"7645",
    "addr:postcode":"v5j 4k2",
    "addr:street":"Royal Oak Ave",
    "iso:country":"CA",
    "sg:address":"7645 Royal Oak Ave",
    "sg:city":"Burnaby",
    "sg:classifiers":[
        {
            "category":"Restaurant",
            "type":"Food & Drink"
        }
    ],
    "sg:phone":"+1 604 430 4441",
    "sg:postcode":"V5J 4K2",
    "sg:province":"BC",
    "wof:name":"Subway Sandwiches & Salads",
    "wof:placetype":"venue"
},
  "geometry": {"coordinates":[-122.98870086700001,49.2143936157],"type":"Point"}
}