{
  "type": "Feature",
  "properties": {
    "iso:country":"CA",
    "sg:address":"62 Rue Guillaume",
    "sg:city":"Cheneville",
    "sg:classifiers":[
        {
            "category":"Building & Trades",
            "subcategory":"Construction",
            "type":"Services"
        }
    ],
    "sg:phone":"+1 819 428 3922",
    "sg:postcode":"J0V 1E0",
    "sg:province":"QC",
    "sg:tags":[
        "excavating",
        "contractor"
    ],
    "wof:name":"Lavergne Et Fils Enr",
    "wof:placetype":"venue"
},
  "geometry": {"coordinates":[-75.058265686,45.8848991394],"type":"Point"}
}