{
  "type": "Feature",
  "properties": {
    "addr:full":"467 Notre Dame St Belle River ON N0R 1A0",
    "addr:housenumber":"467",
    "addr:postcode":"n0r 1a0",
    "addr:street":"Notre Dame St",
    "iso:country":"CA",
    "sg:address":"467 Notre Dame St",
    "sg:city":"Belle River",
    "sg:classifiers":[
        {
            "category":"Health Services",
            "subcategory":"Doctor",
            "type":"Services"
        }
    ],
    "sg:phone":"+1 519 728 3355",
    "sg:postcode":"N0R 1A0",
    "sg:province":"ON",
    "sg:tags":[
        "physician",
        "surgeon"
    ],
    "wof:name":"Li Wan PO, James MD",
    "wof:placetype":"venue"
},
  "geometry": {"coordinates":[-82.704697,42.293106],"type":"Point"}
}