{
  "type": "Feature",
  "properties": {
    "addr:full":"301 1st Ave Regina SK S4N 4Z1",
    "addr:housenumber":"301",
    "addr:postcode":"s4n 4z1",
    "addr:street":"1St Ave",
    "iso:country":"CA",
    "sg:address":"301 1st Ave",
    "sg:city":"Regina",
    "sg:classifiers":[
        {
            "category":"Wholesale",
            "subcategory":"Construction Materials",
            "type":"Manufacturing & Wholesale Goods"
        }
    ],
    "sg:phone":"+1 306 543 2662",
    "sg:postcode":"S4N 4Z1",
    "sg:province":"SK",
    "sg:tags":[
        "building",
        "concrete",
        "product"
    ],
    "wof:name":"Con-Force Structures Ltd",
    "wof:placetype":"venue"
},
  "geometry": {"coordinates":[-104.584267,50.467388],"type":"Point"}
}