{
  "type": "Feature",
  "properties": {
    "addr:full":"St Albert AB T8N 1E4",
    "addr:postcode":"t8n 1e4",
    "iso:country":"CA",
    "sg:city":"St Albert",
    "sg:classifiers":[
        {
            "category":"Real Estate",
            "subcategory":"Real Estate Agent",
            "type":"Services"
        }
    ],
    "sg:phone":"+1 780 459 7786",
    "sg:postcode":"T8N 1E4",
    "sg:province":"AB",
    "wof:name":"Bermont Realty Ltd",
    "wof:placetype":"venue"
},
  "geometry": {"coordinates":[-113.625916,53.63406],"type":"Point"}
}