{
  "type": "Feature",
  "properties": {
    "addr:full":"2730 Av Des Hirondelles Becancour QC G9H 4M4",
    "addr:housenumber":"2730",
    "addr:postcode":"g9h 4m4",
    "addr:street":"Av Des Hirondelles",
    "iso:country":"CA",
    "sg:address":"2730 Av Des Hirondelles",
    "sg:city":"Becancour",
    "sg:classifiers":[
        {
            "category":"Government",
            "subcategory":"Office",
            "type":"Public Place"
        }
    ],
    "sg:phone":"+1 819 298 3916",
    "sg:postcode":"G9H 4M4",
    "sg:province":"QC",
    "sg:tags":[
        "license"
    ],
    "wof:name":"Immatriculation Des Vehicules",
    "wof:placetype":"venue"
},
  "geometry": {"coordinates":[-72.26694488530001,46.3968887329],"type":"Point"}
}