{
  "type": "Feature",
  "properties": {
    "iso:country":"CA",
    "sg:address":"2 Town Square #102",
    "sg:city":"Fonthill",
    "sg:classifiers":[
        {
            "category":"Professional",
            "subcategory":"Accounting & Tax Preparation",
            "type":"Services"
        }
    ],
    "sg:phone":"+1 905 892 3815",
    "sg:postcode":"L0S 1E0",
    "sg:province":"ON",
    "sg:tags":[
        "return",
        "filing"
    ],
    "wof:name":"H & R Block Canada Inc",
    "wof:placetype":"venue"
},
  "geometry": {"coordinates":[-79.2852859497,43.0445480347],"type":"Point"}
}