{
  "type": "Feature",
  "properties": {
    "addr:full":"45 Cranfield Rd East York ON M4B 3H6",
    "addr:housenumber":"45",
    "addr:postcode":"m4b 3h6",
    "addr:street":"Cranfield Rd",
    "iso:country":"CA",
    "sg:address":"45 Cranfield Rd",
    "sg:city":"East York",
    "sg:classifiers":[
        {
            "category":"Professional",
            "subcategory":"Business Services",
            "type":"Services"
        }
    ],
    "sg:phone":"+1 416 752 7842",
    "sg:postcode":"M4B 3H6",
    "sg:province":"ON",
    "sg:tags":[
        "paper",
        "lamination"
    ],
    "wof:name":"Plastic Laminating Inc",
    "wof:placetype":"venue"
},
  "geometry": {"coordinates":[-79.31012699999999,43.714123],"type":"Point"}
}