{
  "type": "Feature",
  "properties": {
    "addr:full":"Montreal QC H2N 1R2",
    "addr:postcode":"h2n 1r2",
    "iso:country":"CA",
    "sg:city":"Montreal",
    "sg:classifiers":[
        {
            "category":"Wholesale",
            "subcategory":"Apparel",
            "type":"Manufacturing & Wholesale Goods"
        }
    ],
    "sg:phone":"+1 514 381 1916",
    "sg:postcode":"H2N 1R2",
    "sg:province":"QC",
    "sg:tags":[
        "textile"
    ],
    "wof:name":"Metro Textiles CO",
    "wof:placetype":"venue"
},
  "geometry": {"coordinates":[-73.6558456421,45.545665741],"type":"Point"}
}