{
  "type": "Feature",
  "properties": {
    "addr:full":"Dorval QC H9P 1H6",
    "addr:postcode":"h9p 1h6",
    "iso:country":"CA",
    "sg:city":"Dorval",
    "sg:classifiers":[
        {
            "category":"Manufacturing",
            "subcategory":"Electronics",
            "type":"Manufacturing & Wholesale Goods"
        }
    ],
    "sg:phone":"+1 514 684 4141",
    "sg:postcode":"H9P 1H6",
    "sg:province":"QC",
    "sg:tags":[
        "equipment",
        "transformer",
        "electronic"
    ],
    "wof:name":"Viable Power Conversion Tech",
    "wof:placetype":"venue"
},
  "geometry": {"coordinates":[-73.786629,45.485458],"type":"Point"}
}