{
  "type": "Feature",
  "properties": {
    "addr:full":"Brougham ON L0H 1A0",
    "addr:postcode":"l0h 1a0",
    "iso:country":"CA",
    "sg:city":"Brougham",
    "sg:classifiers":[
        {
            "category":"Home & Garden",
            "subcategory":"Hardware",
            "type":"Retail Goods"
        }
    ],
    "sg:phone":"+1 905 683 1450",
    "sg:postcode":"L0H 1A0",
    "sg:province":"ON",
    "wof:name":"Brougham Hardware",
    "wof:placetype":"venue"
},
  "geometry": {"coordinates":[-79.106117,43.91901],"type":"Point"}
}