{
  "type": "Feature",
  "properties": {
    "addr:full":"Casselman ON K0A 1M0",
    "addr:postcode":"k0a 1m0",
    "iso:country":"CA",
    "sg:city":"Casselman",
    "sg:classifiers":[
        {
            "category":"Retail",
            "subcategory":"Repair Shop",
            "type":"Services"
        }
    ],
    "sg:phone":"+1 613 764 5691",
    "sg:postcode":"K0A 1M0",
    "sg:province":"ON",
    "sg:tags":[
        "refinishing",
        "furniture"
    ],
    "wof:name":"Hrs Furniture Restoration",
    "wof:placetype":"venue"
},
  "geometry": {"coordinates":[-75.088959,45.313465],"type":"Point"}
}