{
  "type": "Feature",
  "properties": {
    "addr:full":"460 Wellington St #204 St Thomas ON N5R 6H9",
    "addr:housenumber":"460",
    "addr:postcode":"n5r 6h9",
    "addr:street":"Wellington St # 204",
    "iso:country":"CA",
    "sg:address":"460 Wellington St #204",
    "sg:city":"St Thomas",
    "sg:classifiers":[
        {
            "category":"Professional",
            "subcategory":"Accounting & Tax Preparation",
            "type":"Services"
        }
    ],
    "sg:phone":"+1 519 637 3500",
    "sg:postcode":"N5R 6H9",
    "sg:province":"ON",
    "sg:tags":[
        "accountant"
    ],
    "wof:name":"Raven & Shaw",
    "wof:placetype":"venue"
},
  "geometry": {"coordinates":[-81.15904999999999,42.774448],"type":"Point"}
}