{
  "type": "Feature",
  "properties": {
    "addr:full":"5834 Douglas Line Forest ON N0N 1J0",
    "addr:housenumber":"5834",
    "addr:postcode":"n0n 1j0",
    "addr:street":"Douglas Line",
    "iso:country":"CA",
    "sg:address":"5834 Douglas Line",
    "sg:city":"Forest",
    "sg:classifiers":[
        {
            "category":"Freight",
            "type":"Transportation"
        }
    ],
    "sg:phone":"+1 519 786 5465",
    "sg:postcode":"N0N 1J0",
    "sg:province":"ON",
    "sg:tags":[
        "trucking"
    ],
    "wof:name":"Lloyd A Jones Livestock Ltd",
    "wof:placetype":"venue"
},
  "geometry": {"coordinates":[-81.9993438721,43.0979690552],"type":"Point"}
}