{
  "type": "Feature",
  "properties": {
    "addr:full":"1098 Marine Dr SW Vancouver BC V6P 5Z3",
    "addr:housenumber":"1098",
    "addr:postcode":"v6p 5z3",
    "addr:street":"Marine Dr Sw",
    "iso:country":"CA",
    "sg:address":"1098 Marine Dr SW",
    "sg:city":"Vancouver",
    "sg:classifiers":[
        {
            "category":"Home & Garden",
            "subcategory":"Furniture",
            "type":"Retail Goods"
        }
    ],
    "sg:phone":"+1 604 261 3681",
    "sg:postcode":"V6P 5Z3",
    "sg:province":"BC",
    "sg:tags":[
        "antique"
    ],
    "wof:name":"Farmhouse Collections Ltd",
    "wof:placetype":"venue"
},
  "geometry": {"coordinates":[-123.131134,49.204067],"type":"Point"}
}