{
  "type": "Feature",
  "properties": {
    "addr:full":"5500 Tomken Rd # 9 Mississauga ON L4W 2Z4",
    "addr:housenumber":"5500",
    "addr:postcode":"l4w 2z4",
    "addr:street":"Tomken Rd # 9",
    "iso:country":"CA",
    "sg:address":"5500 Tomken Rd # 9",
    "sg:city":"Mississauga",
    "sg:classifiers":[
        {
            "category":"Wholesale",
            "subcategory":"Office Equipment",
            "type":"Manufacturing & Wholesale Goods"
        }
    ],
    "sg:phone":"+1 905 568 7667",
    "sg:postcode":"L4W 2Z4",
    "sg:province":"ON",
    "sg:tags":[
        "machine",
        "mailing"
    ],
    "wof:name":"Mailing Systems Inc",
    "wof:placetype":"venue"
},
  "geometry": {"coordinates":[-79.64593499999999,43.636463],"type":"Point"}
}