{
  "type": "Feature",
  "properties": {
    "addr:full":"200 Boul Rene-Levesque O Montreal QC H2Z 1X4",
    "addr:housenumber":"200",
    "addr:postcode":"h2z 1x4",
    "addr:street":"Boul Rene-Levesque O",
    "iso:country":"CA",
    "sg:address":"200 Boul Rene-Levesque O",
    "sg:city":"Montreal",
    "sg:classifiers":[
        {
            "category":"Organizations",
            "subcategory":"Labor Organization",
            "type":"Services"
        }
    ],
    "sg:phone":"+1 514 848 9938",
    "sg:postcode":"H2Z 1X4",
    "sg:province":"QC",
    "wof:name":"Afpc Local",
    "wof:placetype":"venue"
},
  "geometry": {"coordinates":[-73.5597610474,45.5107154846],"type":"Point"}
}