{
  "type": "Feature",
  "properties": {
    "addr:full":"963 Rue Theophile-Saint-Lauren Nicolet QC J3T 1B4",
    "addr:housenumber":"963",
    "addr:postcode":"j3t 1b4",
    "addr:street":"Rue Theophile-Saint-Lauren",
    "iso:country":"CA",
    "sg:address":"963 Rue Theophile-Saint-Lauren",
    "sg:city":"Nicolet",
    "sg:classifiers":[
        {
            "category":"Manufacturing",
            "subcategory":"Tools & Machinery",
            "type":"Manufacturing & Wholesale Goods"
        }
    ],
    "sg:phone":"+1 819 293 4177",
    "sg:postcode":"J3T 1B4",
    "sg:province":"QC",
    "sg:tags":[
        "equipment",
        "system",
        "automation"
    ],
    "wof:name":"Ballons Belcan Inc",
    "wof:placetype":"venue"
},
  "geometry": {"coordinates":[-72.60533100000001,46.226299],"type":"Point"}
}