{
  "type": "Feature",
  "properties": {
    "addr:full":"11070 100 Ave # 102 Grande Prairie AB T8V 7L5",
    "addr:housenumber":"11070",
    "addr:postcode":"t8v 7l5",
    "addr:street":"100 Ave # 102",
    "iso:country":"CA",
    "sg:address":"11070 100 Ave # 102",
    "sg:city":"Grande Prairie",
    "sg:classifiers":[
        {
            "category":"Restaurant",
            "type":"Food & Drink"
        }
    ],
    "sg:phone":"+1 780 513 1223",
    "sg:postcode":"T8V 7L5",
    "sg:province":"AB",
    "wof:name":"Smitty's Restaurant",
    "wof:placetype":"venue"
},
  "geometry": {"coordinates":[-118.831917,55.170868],"type":"Point"}
}