{
  "type": "Feature",
  "properties": {
    "addr:full":"4110 Rue Sainte-Catherine O Westmount QC H3Z 1P2",
    "addr:housenumber":"4110",
    "addr:postcode":"h3z 1p2",
    "addr:street":"Rue Sainte-Catherine O",
    "iso:country":"CA",
    "sg:address":"4110 Rue Sainte-Catherine O",
    "sg:city":"Westmount",
    "sg:classifiers":[
        {
            "category":"Wholesale",
            "subcategory":"Electrical",
            "type":"Manufacturing & Wholesale Goods"
        }
    ],
    "sg:phone":"+1 514 932 2333",
    "sg:postcode":"H3Z 1P2",
    "sg:province":"QC",
    "sg:tags":[
        "tape"
    ],
    "wof:name":"Quantegy International Inc",
    "wof:placetype":"venue"
},
  "geometry": {"coordinates":[-73.586617,45.487301],"type":"Point"}
}