{
  "type": "Feature",
  "properties": {
    "iso:country":"CA",
    "sg:address":"301 Hwy 29 N",
    "sg:city":"Smiths Falls",
    "sg:classifiers":[
        {
            "category":"Organizations",
            "subcategory":"Religious Organization",
            "type":"Services"
        }
    ],
    "sg:phone":"+1 613 283 2511",
    "sg:postcode":"K7A 4W7",
    "sg:province":"ON",
    "sg:tags":[
        "church"
    ],
    "wof:name":"Pentecostal Church Paoc",
    "wof:placetype":"venue"
},
  "geometry": {"coordinates":[-76.0150985718,44.8798751831],"type":"Point"}
}