{
  "type": "Feature",
  "properties": {
    "addr:full":"7168 Boul Pie-Ix Montreal QC H2A 2G4",
    "addr:housenumber":"7168",
    "addr:postcode":"h2a 2g4",
    "addr:street":"Boul Pie-Ix",
    "iso:country":"CA",
    "sg:address":"7168 Boul Pie-Ix",
    "sg:city":"Montreal",
    "sg:classifiers":[
        {
            "category":"Professional",
            "subcategory":"Business Services",
            "type":"Services"
        }
    ],
    "sg:phone":"+1 514 385 0544",
    "sg:postcode":"H2A 2G4",
    "sg:province":"QC",
    "sg:tags":[
        "notary"
    ],
    "wof:name":"Belanger, Micheline",
    "wof:placetype":"venue"
},
  "geometry": {"coordinates":[-73.5907897949,45.5660858154],"type":"Point"}
}