{
  "type": "Feature",
  "properties": {
    "addr:full":"Calgary AB T2K 1J5",
    "addr:postcode":"t2k 1j5",
    "iso:country":"CA",
    "sg:city":"Calgary",
    "sg:classifiers":[
        {
            "category":"Personal",
            "subcategory":"Beauty Salon",
            "type":"Services"
        }
    ],
    "sg:phone":"+1 403 282 5661",
    "sg:postcode":"T2K 1J5",
    "sg:province":"AB",
    "wof:name":"Shear Concept Hair Design",
    "wof:placetype":"venue"
},
  "geometry": {"coordinates":[-114.09442901600001,51.0914764404],"type":"Point"}
}