{
  "type": "Feature",
  "properties": {
    "iso:country":"CA",
    "sg:address":"2312 4 St",
    "sg:city":"Nisku",
    "sg:classifiers":[
        {
            "category":"Building & Trades",
            "subcategory":"Construction",
            "type":"Services"
        }
    ],
    "sg:phone":"+1 780 955 2225",
    "sg:postcode":"T9E 7W5",
    "sg:province":"AB",
    "sg:tags":[
        "roof",
        "structure"
    ],
    "wof:name":"A-1 Truss Mfg Ltd",
    "wof:placetype":"venue"
},
  "geometry": {"coordinates":[-113.532966614,53.3112411499],"type":"Point"}
}