{
  "type": "Feature",
  "properties": {
    "addr:full":"Kincardine ON N2Z 2C5",
    "addr:postcode":"n2z 2c5",
    "iso:country":"CA",
    "sg:city":"Kincardine",
    "sg:classifiers":[
        {
            "category":"Restaurant",
            "type":"Food & Drink"
        }
    ],
    "sg:phone":"+1 519 396 3877",
    "sg:postcode":"N2Z 2C5",
    "sg:province":"ON",
    "wof:name":"Embassy Restaurant",
    "wof:placetype":"venue"
},
  "geometry": {"coordinates":[-81.6104812622,44.1809692383],"type":"Point"}
}