{
  "type": "Feature",
  "properties": {
    "addr:full":"Farm Battleford SK S0M 0E0",
    "addr:postcode":"s0m 0e0",
    "iso:country":"CA",
    "sg:address":"Farm",
    "sg:city":"Battleford",
    "sg:classifiers":[
        {
            "category":"Building & Trades",
            "subcategory":"Landscaping Services",
            "type":"Services"
        }
    ],
    "sg:phone":"+1 306 937 7266",
    "sg:postcode":"S0M 0E0",
    "sg:province":"SK",
    "sg:tags":[
        "landscape",
        "contractor"
    ],
    "wof:name":"Tree World Landscape Contract",
    "wof:placetype":"venue"
},
  "geometry": {"coordinates":[-108.31314086899999,52.7362365723],"type":"Point"}
}