{
  "type": "Feature",
  "properties": {
    "addr:full":"1100 Boul Cure-Labelle Laval QC H7V 2V5",
    "addr:housenumber":"1100",
    "addr:postcode":"h7v 2v5",
    "addr:street":"Boul Cure-Labelle",
    "iso:country":"CA",
    "sg:address":"1100 Boul Cure-Labelle",
    "sg:city":"Laval",
    "sg:classifiers":[
        {
            "category":"Banks & Credit Unions",
            "subcategory":"Bank",
            "type":"Services"
        }
    ],
    "sg:phone":"+1 450 682 6383",
    "sg:postcode":"H7V 2V5",
    "sg:province":"QC",
    "wof:name":"Bank of Montreal",
    "wof:placetype":"venue"
},
  "geometry": {"coordinates":[-73.7518615723,45.5439529419],"type":"Point"}
}