{
  "type": "Feature",
  "properties": {
    "iso:country":"CA",
    "sg:city":"Cobden",
    "sg:classifiers":[
        {
            "category":"Travel",
            "subcategory":"Campground",
            "type":"Entertainment"
        }
    ],
    "sg:phone":"+1 613 638 2000",
    "sg:postcode":"K0J 1K0",
    "sg:province":"ON",
    "sg:tags":[
        "camp"
    ],
    "wof:name":"Ottawa Valley Pentecostal Camp",
    "wof:placetype":"venue"
},
  "geometry": {"coordinates":[-76.8799819946,45.6270751953],"type":"Point"}
}