{
  "type": "Feature",
  "properties": {
    "iso:country":"CA",
    "sg:address":"3505 Boul Dagenais O",
    "sg:city":"Laval",
    "sg:classifiers":[
        {
            "category":"Education",
            "subcategory":"Library",
            "type":"Public Place"
        }
    ],
    "sg:phone":"+1 450 978 8909",
    "sg:postcode":"H7P 4V9",
    "sg:province":"QC",
    "wof:name":"Laval Gabrielle Roy",
    "wof:placetype":"venue"
},
  "geometry": {"coordinates":[-73.81094360349999,45.5772285461],"type":"Point"}
}