{
  "type": "Feature",
  "properties": {
    "addr:full":"315 Osler St Toronto ON M6N 2Z4",
    "addr:housenumber":"315",
    "addr:postcode":"m6n 2z4",
    "addr:street":"Osler St",
    "iso:country":"CA",
    "sg:address":"315 Osler St",
    "sg:city":"Toronto",
    "sg:classifiers":[
        {
            "category":"Social Services",
            "subcategory":"Child Care",
            "type":"Services"
        }
    ],
    "sg:phone":"+1 416 651 2550",
    "sg:postcode":"M6N 2Z4",
    "sg:province":"ON",
    "wof:name":"Perth School Day Care Satellit",
    "wof:placetype":"venue"
},
  "geometry": {"coordinates":[-79.46038799999999,43.672466],"type":"Point"}
}