{
  "type": "Feature",
  "properties": {
    "addr:full":"Barrie ON L4N 1R8",
    "addr:postcode":"l4n 1r8",
    "iso:country":"CA",
    "sg:city":"Barrie",
    "sg:classifiers":[
        {
            "category":"Real Estate",
            "subcategory":"Real Estate Agent",
            "type":"Services"
        }
    ],
    "sg:phone":"+1 705 722 3411",
    "sg:postcode":"L4N 1R8",
    "sg:province":"ON",
    "wof:name":"Barry & CO Re Ltd",
    "wof:placetype":"venue"
},
  "geometry": {"coordinates":[-79.69194,44.389427],"type":"Point"}
}