{
  "type": "Feature",
  "properties": {
    "iso:country":"CA",
    "sg:address":"1080 Industrial Way # A",
    "sg:city":"Parksville",
    "sg:classifiers":[
        {
            "category":"Freight",
            "type":"Transportation"
        }
    ],
    "sg:phone":"+1 250 248 8155",
    "sg:postcode":"V9P 2W8",
    "sg:province":"BC",
    "sg:tags":[
        "company",
        "logging",
        "trucking"
    ],
    "wof:name":"Ring Contracting Ltd",
    "wof:placetype":"venue"
},
  "geometry": {"coordinates":[-124.269325256,49.3089332581],"type":"Point"}
}