{
  "type": "Feature",
  "properties": {
    "addr:full":"300 Mystery Lake Rd Thompson MB R8N 0M2",
    "addr:housenumber":"300",
    "addr:postcode":"r8n 0m2",
    "addr:street":"Mystery Lake Rd",
    "iso:country":"CA",
    "sg:address":"300 Mystery Lake Rd",
    "sg:city":"Thompson",
    "sg:classifiers":[
        {
            "category":"Restaurant",
            "type":"Food & Drink"
        }
    ],
    "sg:phone":"+1 204 677 3997",
    "sg:postcode":"R8N 0M2",
    "sg:province":"MB",
    "sg:tags":[
        "delicatessen"
    ],
    "wof:name":"Corner Deli Ltd",
    "wof:placetype":"venue"
},
  "geometry": {"coordinates":[-97.8506164551,55.7446365356],"type":"Point"}
}