{
  "type": "Feature",
  "properties": {
    "iso:country":"CA",
    "sg:address":"1256 Talbot St",
    "sg:city":"St Thomas",
    "sg:classifiers":[
        {
            "category":"Shopping",
            "type":"Retail Goods"
        }
    ],
    "sg:phone":"+1 519 631 2105",
    "sg:postcode":"N5P 1G9",
    "sg:province":"ON",
    "sg:tags":[
        "picture",
        "frame"
    ],
    "wof:name":"Matted Memories",
    "wof:placetype":"venue"
},
  "geometry": {"coordinates":[-81.14804077150001,42.7781562805],"type":"Point"}
}