{
  "type": "Feature",
  "properties": {
    "iso:country":"CA",
    "sg:address":"25188 52 Ave",
    "sg:city":"Aldergrove",
    "sg:classifiers":[
        {
            "category":"Building & Trades",
            "subcategory":"Construction",
            "type":"Services"
        }
    ],
    "sg:phone":"+1 604 857 0008",
    "sg:postcode":"V4W 1G2",
    "sg:province":"BC",
    "sg:tags":[
        "boring",
        "drilling",
        "contractor"
    ],
    "wof:name":"Columbia Water Wells Ltd",
    "wof:placetype":"venue"
},
  "geometry": {"coordinates":[-122.472290039,49.0568656921],"type":"Point"}
}