{
  "type": "Feature",
  "properties": {
    "addr:full":"Ingonish NS B0C 1K0",
    "addr:postcode":"b0c 1k0",
    "iso:country":"CA",
    "sg:city":"Ingonish",
    "sg:classifiers":[
        {
            "category":"Shopping",
            "subcategory":"Bicycles & Sporting Goods",
            "type":"Retail Goods"
        }
    ],
    "sg:phone":"+1 902 285 2077",
    "sg:postcode":"B0C 1K0",
    "sg:province":"NS",
    "wof:name":"Ingonish Sport Shop",
    "wof:placetype":"venue"
},
  "geometry": {"coordinates":[-60.3830986023,46.6901893616],"type":"Point"}
}