{
  "type": "Feature",
  "properties": {
    "addr:full":"Mississauga ON L5N 1A6",
    "addr:postcode":"l5n 1a6",
    "iso:country":"CA",
    "sg:city":"Mississauga",
    "sg:classifiers":[
        {
            "category":"Professional",
            "subcategory":"Management & Consulting",
            "type":"Services"
        }
    ],
    "sg:phone":"+1 905 567 7190",
    "sg:postcode":"L5N 1A6",
    "sg:province":"ON",
    "sg:tags":[
        "association"
    ],
    "wof:name":"Fletcher Wright Assoc Inc",
    "wof:placetype":"venue"
},
  "geometry": {"coordinates":[-79.73850299999999,43.598011],"type":"Point"}
}