{
  "type": "Feature",
  "properties": {
    "addr:full":"Nordegg AB T0M 2H0",
    "addr:postcode":"t0m 2h0",
    "iso:country":"CA",
    "sg:city":"Nordegg",
    "sg:classifiers":[
        {
            "category":"Recreation",
            "type":"Entertainment"
        }
    ],
    "sg:phone":"+1 403 721 2208",
    "sg:postcode":"T0M 2H0",
    "sg:province":"AB",
    "sg:tags":[
        "camp",
        "amusement"
    ],
    "wof:name":"Centre For Outdoor Education",
    "wof:placetype":"venue"
},
  "geometry": {"coordinates":[-116.075462,52.482452],"type":"Point"}
}