{
  "type": "Feature",
  "properties": {
    "addr:full":"Columbia Dr Marystown NL A0E 2M0",
    "addr:postcode":"a0e 2m0",
    "addr:street":"Columbia",
    "iso:country":"CA",
    "sg:address":"Columbia Dr",
    "sg:city":"Marystown",
    "sg:classifiers":[
        {
            "category":"Restaurant",
            "type":"Food & Drink"
        }
    ],
    "sg:phone":"+1 709 279 5504",
    "sg:postcode":"A0E 2M0",
    "sg:province":"NL",
    "wof:name":"First Venture Cafeteria",
    "wof:placetype":"venue"
},
  "geometry": {"coordinates":[-55.2424125671,47.1614303589],"type":"Point"}
}