{
  "type": "Feature",
  "properties": {
    "addr:full":"39 Montee DE Sandy Beach # 30 Gaspe QC G4X 2A9",
    "addr:housenumber":"39",
    "addr:postcode":"g4x 2a9",
    "addr:street":"Montee De Sandy Beach # 30 Gaspe",
    "iso:country":"CA",
    "sg:address":"39 Montee DE Sandy Beach # 30",
    "sg:city":"Gaspe",
    "sg:classifiers":[
        {
            "category":"Shopping",
            "subcategory":"Tobacco",
            "type":"Retail Goods"
        }
    ],
    "sg:phone":"+1 418 368 6013",
    "sg:postcode":"G4X 2A9",
    "sg:province":"QC",
    "sg:tags":[
        "cigarette",
        "cigar",
        "dealer"
    ],
    "wof:name":"Tabagie Ka-Tout",
    "wof:placetype":"venue"
},
  "geometry": {"coordinates":[-64.47268699999999,48.82383],"type":"Point"}
}