{
  "type": "Feature",
  "properties": {
    "addr:full":"Whitehorse YT Y1A 4A2",
    "addr:postcode":"y1a 4a2",
    "iso:country":"CA",
    "sg:city":"Whitehorse",
    "sg:classifiers":[
        {
            "category":"Social Services",
            "subcategory":"Child Care",
            "type":"Services"
        }
    ],
    "sg:phone":"+1 867 633 4614",
    "sg:postcode":"Y1A 4A2",
    "sg:province":"YT",
    "wof:name":"Tree House Play School",
    "wof:placetype":"venue"
},
  "geometry": {"coordinates":[-135.141357,60.774349],"type":"Point"}
}