{
  "type": "Feature",
  "properties": {
    "iso:country":"CA",
    "sg:address":"205 8E Av",
    "sg:city":"Richelieu",
    "sg:classifiers":[
        {
            "category":"Education",
            "subcategory":"School",
            "type":"Public Place"
        }
    ],
    "sg:phone":"+1 450 658 8284",
    "sg:postcode":"J3L 3N5",
    "sg:province":"QC",
    "wof:name":"Ecole Saint-Joseph",
    "wof:placetype":"venue"
},
  "geometry": {"coordinates":[-73.255402,45.445503],"type":"Point"}
}