{
  "type": "Feature",
  "properties": {
    "addr:full":"Unity SK S0K 4L0",
    "addr:postcode":"s0k 4l0",
    "iso:country":"CA",
    "sg:city":"Unity",
    "sg:classifiers":[
        {
            "category":"Building & Trades",
            "subcategory":"Construction",
            "type":"Services"
        }
    ],
    "sg:phone":"+1 306 228 4200",
    "sg:postcode":"S0K 4L0",
    "sg:province":"SK",
    "sg:tags":[
        "dry wall",
        "contractor"
    ],
    "wof:name":"Bachman Drywalling",
    "wof:placetype":"venue"
},
  "geometry": {"coordinates":[-109.14722442599999,52.4374237061],"type":"Point"}
}