{
  "type": "Feature",
  "properties": {
    "addr:full":"426 Harper Rd Tignish PE C0B 2B0",
    "addr:housenumber":"426",
    "addr:postcode":"c0b 2b0",
    "addr:street":"Harper Rd",
    "iso:country":"CA",
    "sg:address":"426 Harper Rd",
    "sg:city":"Tignish",
    "sg:classifiers":[
        {
            "category":"Retail",
            "subcategory":"Auto Repair",
            "type":"Services"
        }
    ],
    "sg:phone":"+1 902 882 4105",
    "sg:postcode":"C0B 2B0",
    "sg:province":"PE",
    "sg:tags":[
        "body",
        "automobile",
        "painting"
    ],
    "wof:name":"R C's Autobody",
    "wof:placetype":"venue"
},
  "geometry": {"coordinates":[-64.03338599999999,46.951317],"type":"Point"}
}