{
  "type": "Feature",
  "properties": {
    "iso:country":"CA",
    "sg:address":"3390 Walker Rd",
    "sg:city":"Windsor",
    "sg:classifiers":[
        {
            "category":"Shopping",
            "subcategory":"Music",
            "type":"Retail Goods"
        }
    ],
    "sg:phone":"+1 519 250 0525",
    "sg:postcode":"N8W 3S1",
    "sg:province":"ON",
    "sg:tags":[
        "compact",
        "record",
        "disc",
        "tape"
    ],
    "wof:name":"C D Plus",
    "wof:placetype":"venue"
},
  "geometry": {"coordinates":[-82.9777145386,42.2766838074],"type":"Point"}
}