{
  "type": "Feature",
  "properties": {
    "iso:country":"CA",
    "sg:address":"5 Perma Crt # 2",
    "sg:city":"St Catharines",
    "sg:classifiers":[
        {
            "category":"Retail",
            "subcategory":"Auto Repair",
            "type":"Services"
        }
    ],
    "sg:phone":"+1 905 685 5182",
    "sg:postcode":"L2R 7K8",
    "sg:province":"ON",
    "sg:tags":[
        "machine",
        "automobile",
        "shop"
    ],
    "wof:name":"Balancing Act",
    "wof:placetype":"venue"
},
  "geometry": {"coordinates":[-79.229782,43.168457],"type":"Point"}
}