{
  "type": "Feature",
  "properties": {
    "iso:country":"CA",
    "sg:address":"344 Peel St",
    "sg:city":"Acton",
    "sg:classifiers":[
        {
            "category":"Building & Trades",
            "subcategory":"Construction",
            "type":"Services"
        }
    ],
    "sg:phone":"+1 519 853 1720",
    "sg:postcode":"L7J 1N1",
    "sg:province":"ON",
    "sg:tags":[
        "windows",
        "roofing",
        "contractor"
    ],
    "wof:name":"Haefner Siding & Roofing",
    "wof:placetype":"venue"
},
  "geometry": {"coordinates":[-80.029915,43.637035],"type":"Point"}
}