{
  "type": "Feature",
  "properties": {
    "addr:full":"Etobicoke ON M8Z 2Z6",
    "addr:postcode":"m8z 2z6",
    "iso:country":"CA",
    "sg:city":"Etobicoke",
    "sg:classifiers":[
        {
            "category":"Building & Trades",
            "subcategory":"Construction",
            "type":"Services"
        }
    ],
    "sg:phone":"+1 416 233 0424",
    "sg:postcode":"M8Z 2Z6",
    "sg:province":"ON",
    "sg:tags":[
        "roofing",
        "contractor"
    ],
    "wof:name":"M M Roofing Ltd",
    "wof:placetype":"venue"
},
  "geometry": {"coordinates":[-79.5297012329,43.636051178],"type":"Point"}
}