{
  "type": "Feature",
  "properties": {
    "addr:full":"2285 Av Raymond Saint-Hyacinthe QC J2S 7E7",
    "addr:housenumber":"2285",
    "addr:postcode":"j2s 7e7",
    "addr:street":"Av Raymond",
    "iso:country":"CA",
    "sg:address":"2285 Av Raymond",
    "sg:city":"Saint-Hyacinthe",
    "sg:classifiers":[
        {
            "category":"Home & Garden",
            "subcategory":"Home Furnishings",
            "type":"Retail Goods"
        }
    ],
    "sg:phone":"+1 450 774 7885",
    "sg:postcode":"J2S 7E7",
    "sg:province":"QC",
    "sg:tags":[
        "curtain",
        "made",
        "drapery"
    ],
    "wof:name":"Brolem Textiles Enr",
    "wof:placetype":"venue"
},
  "geometry": {"coordinates":[-72.95770263670001,45.6274795532],"type":"Point"}
}