{
  "type": "Feature",
  "properties": {
    "addr:full":"Calgary AB T2E 6X7",
    "addr:postcode":"t2e 6x7",
    "iso:country":"CA",
    "sg:city":"Calgary",
    "sg:classifiers":[
        {
            "category":"Professional",
            "subcategory":"Computer Services",
            "type":"Services"
        }
    ],
    "sg:phone":"+1 403 250 8488",
    "sg:postcode":"T2E 6X7",
    "sg:province":"AB",
    "sg:tags":[
        "consultant"
    ],
    "wof:name":"Scorpio Computer & Consulting",
    "wof:placetype":"venue"
},
  "geometry": {"coordinates":[-114.00488300000001,51.090649],"type":"Point"}
}