{
  "type": "Feature",
  "properties": {
    "addr:full":"743 Rue Sherbrooke Magog QC J1X 2S8",
    "addr:housenumber":"743",
    "addr:postcode":"j1x 2s8",
    "addr:street":"Rue Sherbrooke",
    "iso:country":"CA",
    "sg:address":"743 Rue Sherbrooke",
    "sg:city":"Magog",
    "sg:classifiers":[
        {
            "category":"Professional",
            "subcategory":"Computer Services",
            "type":"Services"
        }
    ],
    "sg:phone":"+1 819 868 1400",
    "sg:postcode":"J1X 2S8",
    "sg:province":"QC",
    "sg:tags":[
        "repair",
        "dealer",
        "equipment"
    ],
    "wof:name":"Blar Informatique",
    "wof:placetype":"venue"
},
  "geometry": {"coordinates":[-72.140381,45.270405],"type":"Point"}
}