{
  "type": "Feature",
  "properties": {
    "addr:full":"2600 Rue William-Tremblay # 301 Montreal QC H1Y 3J2",
    "addr:housenumber":"2600",
    "addr:postcode":"h1y 3j2",
    "addr:street":"Rue William-Tremblay # 301",
    "iso:country":"CA",
    "sg:address":"2600 Rue William-Tremblay # 301",
    "sg:city":"Montreal",
    "sg:classifiers":[
        {
            "category":"Communications",
            "subcategory":"Film & Video Production",
            "type":"Services"
        }
    ],
    "sg:phone":"+1 514 879 0020",
    "sg:postcode":"H1Y 3J2",
    "sg:province":"QC",
    "sg:tags":[
        "motion",
        "picture"
    ],
    "wof:name":"Vision Global Inc",
    "wof:placetype":"venue"
},
  "geometry": {"coordinates":[-73.5645065308,45.5426330566],"type":"Point"}
}