{
  "type": "Feature",
  "properties": {
    "addr:full":"5019 3rd St Boyle AB T0A 0M0",
    "addr:housenumber":"5019",
    "addr:postcode":"t0a 0m0",
    "addr:street":"3Rd St",
    "iso:country":"CA",
    "sg:address":"5019 3rd St",
    "sg:city":"Boyle",
    "sg:classifiers":[
        {
            "category":"Organizations",
            "subcategory":"Professional Association",
            "type":"Services"
        }
    ],
    "sg:phone":"+1 780 689 3845",
    "sg:postcode":"T0A 0M0",
    "sg:province":"AB",
    "sg:tags":[
        "club"
    ],
    "wof:name":"Royal Canadian Legion",
    "wof:placetype":"venue"
},
  "geometry": {"coordinates":[-112.805702,54.587688],"type":"Point"}
}