{
  "type": "Feature",
  "properties": {
    "addr:full":"45 Mount Hope St Lindsay ON K9V 5J1",
    "addr:housenumber":"45",
    "addr:postcode":"k9v 5j1",
    "addr:street":"Mount Hope St",
    "iso:country":"CA",
    "sg:address":"45 Mount Hope St",
    "sg:city":"Lindsay",
    "sg:classifiers":[
        {
            "category":"Professional",
            "subcategory":"Management & Consulting",
            "type":"Services"
        }
    ],
    "sg:phone":"+1 705 328 1717",
    "sg:postcode":"K9V 5J1",
    "sg:province":"ON",
    "sg:tags":[
        "break",
        "water",
        "coffee",
        "company",
        "supply"
    ],
    "wof:name":"Imperial Coffee & Svc Inc",
    "wof:placetype":"venue"
},
  "geometry": {"coordinates":[-78.72627300000001,44.367741],"type":"Point"}
}