{
  "type": "Feature",
  "properties": {
    "addr:full":"801 Commissioners Rd E London ON N6C 5J1",
    "addr:housenumber":"801",
    "addr:postcode":"n6c 5j1",
    "addr:street":"Commissioners Rd E",
    "iso:country":"CA",
    "sg:address":"801 Commissioners Rd E",
    "sg:city":"London",
    "sg:classifiers":[
        {
            "category":"Social Services",
            "subcategory":"Child Care",
            "type":"Services"
        }
    ],
    "sg:phone":"+1 519 685 4058",
    "sg:postcode":"N6C 5J1",
    "sg:province":"ON",
    "wof:name":"Parkwood Children's Day Care",
    "wof:placetype":"venue"
},
  "geometry": {"coordinates":[-81.2257614136,42.9582481384],"type":"Point"}
}