{
  "type": "Feature",
  "properties": {
    "iso:country":"CA",
    "sg:address":"4280 Boul DE Port-Royal",
    "sg:city":"Becancour",
    "sg:classifiers":[
        {
            "category":"Communications",
            "subcategory":"Film & Video Production",
            "type":"Services"
        }
    ],
    "sg:phone":"+1 819 233 2119",
    "sg:postcode":"G9H 1Z4",
    "sg:province":"QC",
    "sg:tags":[
        "taping"
    ],
    "wof:name":"Productions Video Jgg",
    "wof:placetype":"venue"
},
  "geometry": {"coordinates":[-72.51104736329999,46.2711982727],"type":"Point"}
}