{
  "type": "Feature",
  "properties": {
    "iso:country":"CA",
    "sg:address":"557 St-Lawrence St",
    "sg:city":"Winchester",
    "sg:classifiers":[
        {
            "category":"Retail",
            "subcategory":"Auto Repair",
            "type":"Services"
        }
    ],
    "sg:phone":"+1 613 774 2009",
    "sg:postcode":"K0C 2K0",
    "sg:province":"ON",
    "sg:tags":[
        "wrecker"
    ],
    "wof:name":"Kelly's Garage & Towing",
    "wof:placetype":"venue"
},
  "geometry": {"coordinates":[-75.35102081300001,45.0895843506],"type":"Point"}
}