{
  "type": "Feature",
  "properties": {
    "iso:country":"CA",
    "sg:city":"Simcoe",
    "sg:classifiers":[
        {
            "category":"Home & Garden",
            "subcategory":"Building Materials",
            "type":"Retail Goods"
        }
    ],
    "sg:phone":"+1 519 426 8328",
    "sg:postcode":"N3Y 4J9",
    "sg:province":"ON",
    "sg:tags":[
        "siding"
    ],
    "wof:name":"J & J Aluminum & Vinyl Prods",
    "wof:placetype":"venue"
},
  "geometry": {"coordinates":[-80.306640625,42.8361282349],"type":"Point"}
}