{
  "type": "Feature",
  "properties": {
    "addr:full":"Prince Albert SK S6V 2R7",
    "addr:postcode":"s6v 2r7",
    "iso:country":"CA",
    "sg:city":"Prince Albert",
    "sg:classifiers":[
        {
            "category":"Wholesale",
            "subcategory":"Machinery & Supplies",
            "type":"Manufacturing & Wholesale Goods"
        }
    ],
    "sg:phone":"+1 306 764 6366",
    "sg:postcode":"S6V 2R7",
    "sg:province":"SK",
    "sg:tags":[
        "agricultural",
        "implement"
    ],
    "wof:name":"Agri Salvage",
    "wof:placetype":"venue"
},
  "geometry": {"coordinates":[-105.721695,53.191154],"type":"Point"}
}