{
  "type": "Feature",
  "properties": {
    "addr:full":"Scarborough ON M1B 5K1",
    "addr:postcode":"m1b 5k1",
    "iso:country":"CA",
    "sg:city":"Scarborough",
    "sg:classifiers":[
        {
            "category":"Wholesale",
            "subcategory":"Meat",
            "type":"Manufacturing & Wholesale Goods"
        }
    ],
    "sg:phone":"+1 416 297 9822",
    "sg:postcode":"M1B 5K1",
    "sg:province":"ON",
    "sg:tags":[
        "product"
    ],
    "wof:name":"Crescent Premium Foods",
    "wof:placetype":"venue"
},
  "geometry": {"coordinates":[-79.2352218628,43.8018455505],"type":"Point"}
}