{
  "type": "Feature",
  "properties": {
    "addr:full":"8642 Rue Rejane Lasalle QC H8N 1Z1",
    "addr:housenumber":"8642",
    "addr:postcode":"h8n 1z1",
    "addr:street":"Rue Rejane",
    "iso:country":"CA",
    "sg:address":"8642 Rue Rejane",
    "sg:city":"Lasalle",
    "sg:classifiers":[
        {
            "category":"Wholesale",
            "subcategory":"Chemicals & Plastics",
            "type":"Manufacturing & Wholesale Goods"
        }
    ],
    "sg:phone":"+1 514 365 6348",
    "sg:postcode":"H8N 1Z1",
    "sg:province":"QC",
    "sg:tags":[
        "cleaning",
        "compound"
    ],
    "wof:name":"Kinbir Marketing",
    "wof:placetype":"venue"
},
  "geometry": {"coordinates":[-73.6305007935,45.4299545288],"type":"Point"}
}