{
  "type": "Feature",
  "properties": {
    "addr:full":"264 Huggard Rd Calgary AB T3Z 2C3",
    "addr:housenumber":"264",
    "addr:postcode":"t3z 2c3",
    "addr:street":"Huggard Rd",
    "iso:country":"CA",
    "sg:address":"264 Huggard Rd",
    "sg:city":"Calgary",
    "sg:classifiers":[
        {
            "category":"Building & Trades",
            "subcategory":"Landscaping Services",
            "type":"Services"
        }
    ],
    "sg:phone":"+1 403 240 4291",
    "sg:postcode":"T3Z 2C3",
    "sg:province":"AB",
    "sg:tags":[
        "tree"
    ],
    "wof:name":"Country Hills Development Inc",
    "wof:placetype":"venue"
},
  "geometry": {"coordinates":[-114.063194,51.045074],"type":"Point"}
}