{
  "type": "Feature",
  "properties": {
    "addr:full":"99 Strada Dr Woodbridge ON L4L 5V9",
    "addr:postcode":"l4l 5v9",
    "addr:street":"Strada Dr",
    "iso:country":"CA",
    "sg:address":"99 Strada Dr",
    "sg:city":"Woodbridge",
    "sg:classifiers":[
        {
            "category":"Building & Trades",
            "subcategory":"Plumbing",
            "type":"Services"
        }
    ],
    "sg:phone":"+1 905 851 2823",
    "sg:postcode":"L4L 5V9",
    "sg:province":"ON",
    "sg:tags":[
        "contractor",
        "mechanical"
    ],
    "wof:name":"Omico Mechanical Ltd",
    "wof:placetype":"venue"
},
  "geometry": {"coordinates":[-79.568687,43.780727],"type":"Point"}
}