{
  "type": "Feature",
  "properties": {
    "addr:full":"5943 Spring Garden Rd Halifax NS B3H 1Y4",
    "addr:housenumber":"5943",
    "addr:postcode":"b3h 1y4",
    "addr:street":"Spring Garden Rd",
    "iso:country":"CA",
    "sg:address":"5943 Spring Garden Rd",
    "sg:city":"Halifax",
    "sg:classifiers":[
        {
            "category":"Health Services",
            "subcategory":"Doctor",
            "type":"Services"
        }
    ],
    "sg:phone":"+1 902 422 9354",
    "sg:postcode":"B3H 1Y4",
    "sg:province":"NS",
    "sg:tags":[
        "dentist"
    ],
    "wof:name":"Stirling, Peter F G DDS",
    "wof:placetype":"venue"
},
  "geometry": {"coordinates":[-63.5859069824,44.6407699585],"type":"Point"}
}