{
  "type": "Feature",
  "properties": {
    "addr:full":"1235 Wellington St W Ottawa ON K1Y 3A3",
    "addr:housenumber":"1235",
    "addr:postcode":"k1y 3a3",
    "addr:street":"Wellington St W",
    "iso:country":"CA",
    "sg:address":"1235 Wellington St W",
    "sg:city":"Ottawa",
    "sg:classifiers":[
        {
            "category":"Shopping",
            "subcategory":"Books",
            "type":"Retail Goods"
        }
    ],
    "sg:phone":"+1 613 724 6776",
    "sg:postcode":"K1Y 3A3",
    "sg:province":"ON",
    "sg:tags":[
        "map"
    ],
    "wof:name":"A World of Maps & Travel Books",
    "wof:placetype":"venue"
},
  "geometry": {"coordinates":[-75.732208,45.399761],"type":"Point"}
}