{
  "type": "Feature",
  "properties": {
    "iso:country":"CA",
    "sg:address":"193 Willand Lane",
    "sg:city":"Woodlawn",
    "sg:classifiers":[
        {
            "category":"Wholesale",
            "subcategory":"Construction Materials",
            "type":"Manufacturing & Wholesale Goods"
        }
    ],
    "sg:phone":"+1 613 832 7233",
    "sg:postcode":"K0A 3M0",
    "sg:province":"ON",
    "sg:tags":[
        "stone",
        "interlocking"
    ],
    "wof:name":"Alpine Interlocking",
    "wof:placetype":"venue"
},
  "geometry": {"coordinates":[-76.0752792358,45.4623985291],"type":"Point"}
}