{
  "type": "Feature",
  "properties": {
    "addr:full":"1 Yorkdale Rd North York ON M6A 3A1",
    "addr:housenumber":"1",
    "addr:postcode":"m6a 3a1",
    "addr:street":"Yorkdale Rd",
    "iso:country":"CA",
    "sg:address":"1 Yorkdale Rd",
    "sg:city":"North York",
    "sg:classifiers":[
        {
            "category":"Shopping",
            "subcategory":"Clothing, Apparel, & Fashions",
            "type":"Retail Goods"
        }
    ],
    "sg:phone":"+1 416 783 4017",
    "sg:postcode":"M6A 3A1",
    "sg:province":"ON",
    "sg:tags":[
        "accessory"
    ],
    "wof:name":"Pashmina Collection",
    "wof:placetype":"venue"
},
  "geometry": {"coordinates":[-79.453407,43.728207],"type":"Point"}
}