{
  "type": "Feature",
  "properties": {
    "addr:full":"2254 Dogwood Cres Masset BC V0T 1M0",
    "addr:housenumber":"2254",
    "addr:postcode":"v0t 1m0",
    "addr:street":"Dogwood Cres",
    "iso:country":"CA",
    "sg:address":"2254 Dogwood Cres",
    "sg:city":"Masset",
    "sg:classifiers":[
        {
            "category":"Travel",
            "subcategory":"Hotels & Motels",
            "type":"Entertainment"
        }
    ],
    "sg:phone":"+1 250 626 3554",
    "sg:postcode":"V0T 1M0",
    "sg:province":"BC",
    "sg:tags":[
        "breakfast",
        "accommodation",
        "bed"
    ],
    "wof:name":"Dogwood Lodge",
    "wof:placetype":"venue"
},
  "geometry": {"coordinates":[-132.148712158,54.0165786743],"type":"Point"}
}