{
  "type": "Feature",
  "properties": {
    "iso:country":"CA",
    "sg:address":"2254 Dogwood Cres",
    "sg:city":"Masset",
    "sg:classifiers":[
        {
            "category":"Travel",
            "subcategory":"Hotels & Motels",
            "type":"Entertainment"
        }
    ],
    "sg:phone":"+1 250 626 3554",
    "sg:postcode":"V0T 1M0",
    "sg:province":"BC",
    "sg:tags":[
        "breakfast",
        "accommodation",
        "bed"
    ],
    "wof:name":"Dogwood Lodge",
    "wof:placetype":"venue"
},
  "geometry": {"coordinates":[-132.148712158,54.0165786743],"type":"Point"}
}