{
  "type": "Feature",
  "properties": {
    "iso:country":"CA",
    "sg:address":"846 Broughton St",
    "sg:city":"Victoria",
    "sg:classifiers":[
        {
            "category":"Professional",
            "subcategory":"Accounting & Tax Preparation",
            "type":"Services"
        }
    ],
    "sg:phone":"+1 250 388 5135",
    "sg:postcode":"V8W 1E4",
    "sg:province":"BC",
    "sg:tags":[
        "accountant"
    ],
    "wof:name":"English Seabrook & Pringle",
    "wof:placetype":"venue"
},
  "geometry": {"coordinates":[-123.361343,48.423481],"type":"Point"}
}