{
  "type": "Feature",
  "properties": {
    "addr:full":"Ottawa ON K1V 0C2",
    "addr:postcode":"k1v 0c2",
    "iso:country":"CA",
    "sg:city":"Ottawa",
    "sg:classifiers":[
        {
            "category":"Health Services",
            "subcategory":"Doctor",
            "type":"Services"
        }
    ],
    "sg:phone":"+1 613 737 7321",
    "sg:postcode":"K1V 0C2",
    "sg:province":"ON",
    "sg:tags":[
        "dentist"
    ],
    "wof:name":"Herongate Dental Clinic",
    "wof:placetype":"venue"
},
  "geometry": {"coordinates":[-75.645927,45.37991],"type":"Point"}
}