{
  "type": "Feature",
  "properties": {
    "addr:full":"5 Rang Saint-Philippe Amqui QC G5J 2N7",
    "addr:housenumber":"5",
    "addr:postcode":"g5j 2n7",
    "addr:street":"Rang Saint-Philippe",
    "iso:country":"CA",
    "sg:address":"5 Rang Saint-Philippe",
    "sg:city":"Amqui",
    "sg:classifiers":[
        {
            "category":"Building & Trades",
            "subcategory":"Construction",
            "type":"Services"
        }
    ],
    "sg:phone":"+1 418 629 2384",
    "sg:postcode":"G5J 2N7",
    "sg:province":"QC",
    "sg:tags":[
        "contractor"
    ],
    "wof:name":"Construction Beaulieu Enr",
    "wof:placetype":"venue"
},
  "geometry": {"coordinates":[-67.4161148071,48.4748191833],"type":"Point"}
}