{
  "type": "Feature",
  "properties": {
    "addr:full":"246 Rue Dufferin Sherbrooke QC J1H 4M4",
    "addr:housenumber":"246",
    "addr:postcode":"j1h 4m4",
    "addr:street":"Rue Dufferin",
    "iso:country":"CA",
    "sg:address":"246 Rue Dufferin",
    "sg:city":"Sherbrooke",
    "sg:classifiers":[
        {
            "category":"Restaurant",
            "type":"Food & Drink"
        }
    ],
    "sg:phone":"+1 819 820 0399",
    "sg:postcode":"J1H 4M4",
    "sg:province":"QC",
    "wof:name":"Restaurant Casa Chirico",
    "wof:placetype":"venue"
},
  "geometry": {"coordinates":[-71.8942871094,45.4053878784],"type":"Point"}
}