{
  "type": "Feature",
  "properties": {
    "addr:full":"165 Pemberton Ave North Vancouver BC V7P 2R4",
    "addr:housenumber":"165",
    "addr:postcode":"v7p 2r4",
    "addr:street":"Pemberton Ave",
    "iso:country":"CA",
    "sg:address":"165 Pemberton Ave",
    "sg:city":"North Vancouver",
    "sg:classifiers":[
        {
            "category":"Wholesale",
            "subcategory":"Machinery & Supplies",
            "type":"Manufacturing & Wholesale Goods"
        }
    ],
    "sg:phone":"+1 604 985 0234",
    "sg:postcode":"V7P 2R4",
    "sg:province":"BC",
    "sg:tags":[
        "barbecue",
        "gas",
        "appliance",
        "equipment"
    ],
    "wof:name":"Johnstone's Barbecue Parts",
    "wof:placetype":"venue"
},
  "geometry": {"coordinates":[-123.108109,49.31818],"type":"Point"}
}