{
  "type": "Feature",
  "properties": {
    "addr:full":"8487 19E Av Montreal QC H1Z 4J2",
    "addr:housenumber":"8487",
    "addr:postcode":"h1z 4j2",
    "addr:street":"19E Av",
    "iso:country":"CA",
    "sg:address":"8487 19E Av",
    "sg:city":"Montreal",
    "sg:classifiers":[
        {
            "category":"Home & Garden",
            "subcategory":"Household Appliances",
            "type":"Retail Goods"
        }
    ],
    "sg:phone":"+1 514 722 2000",
    "sg:postcode":"H1Z 4J2",
    "sg:province":"QC",
    "sg:tags":[
        "equipment"
    ],
    "wof:name":"Choquette Cks Inc",
    "wof:placetype":"venue"
},
  "geometry": {"coordinates":[-73.6114807129,45.573261261],"type":"Point"}
}