{
  "type": "Feature",
  "properties": {
    "iso:country":"CA",
    "sg:city":"Mississauga",
    "sg:classifiers":[
        {
            "category":"Restaurant",
            "type":"Food & Drink"
        }
    ],
    "sg:phone":"+1 905 564 1580",
    "sg:postcode":"L5T 2E1",
    "sg:province":"ON",
    "wof:name":"Select Sandwich",
    "wof:placetype":"venue"
},
  "geometry": {"coordinates":[-79.6530303955,43.6591415405],"type":"Point"}
}