{
  "type": "Feature",
  "properties": {
    "addr:full":"1785 Rue DE L'Islet Quebec QC G2K 2G8",
    "addr:housenumber":"1785",
    "addr:postcode":"g2k 2g8",
    "addr:street":"Rue De L'Islet",
    "iso:country":"CA",
    "sg:address":"1785 Rue DE L'Islet",
    "sg:city":"Quebec",
    "sg:classifiers":[
        {
            "category":"Professional",
            "subcategory":"Art Services",
            "type":"Services"
        }
    ],
    "sg:phone":"+1 418 260 9221",
    "sg:postcode":"G2K 2G8",
    "sg:province":"QC",
    "sg:tags":[
        "graphic",
        "designer"
    ],
    "wof:name":"Keo Communication",
    "wof:placetype":"venue"
},
  "geometry": {"coordinates":[-70.048119,47.071621],"type":"Point"}
}