{
  "type": "Feature",
  "properties": {
    "iso:country":"CA",
    "sg:address":"3956 64 Ave SE",
    "sg:city":"Calgary",
    "sg:classifiers":[
        {
            "category":"Manufacturing",
            "subcategory":"Chemicals & Compounds",
            "type":"Manufacturing & Wholesale Goods"
        }
    ],
    "sg:phone":"+1 403 279 9040",
    "sg:postcode":"T2C 2B4",
    "sg:province":"AB",
    "sg:tags":[
        "paint"
    ],
    "wof:name":"Spectrum Powder Mfg Ltd",
    "wof:placetype":"venue"
},
  "geometry": {"coordinates":[-113.977584839,50.9967536926],"type":"Point"}
}