{
  "type": "Feature",
  "properties": {
    "addr:full":"1655 Finfar Crt #1 Mississauga ON L5J 4K1",
    "addr:housenumber":"1655",
    "addr:postcode":"l5j 4k1",
    "addr:street":"Finfar Crt # 1",
    "iso:country":"CA",
    "sg:address":"1655 Finfar Crt #1",
    "sg:city":"Mississauga",
    "sg:phone":"+1 905 823 1110",
    "sg:postcode":"L5J 4K1",
    "sg:province":"ON",
    "sg:tags":[
        "equipment",
        "sharpening",
        "supply"
    ],
    "wof:name":"Nella Cutlery Inc",
    "wof:placetype":"venue"
},
  "geometry": {"coordinates":[-79.65239699999999,43.518383],"type":"Point"}
}