{
  "type": "Feature",
  "properties": {
    "addr:full":"198 Rue Notre-Dame # 202 Maniwaki QC J9E 2J5",
    "addr:housenumber":"198",
    "addr:postcode":"j9e 2j5",
    "addr:street":"Rue Notre-Dame # 202",
    "iso:country":"CA",
    "sg:address":"198 Rue Notre-Dame # 202",
    "sg:city":"Maniwaki",
    "sg:classifiers":[
        {
            "category":"Professional",
            "subcategory":"Lawyer & Legal Services",
            "type":"Services"
        }
    ],
    "sg:phone":"+1 819 449 4800",
    "sg:postcode":"J9E 2J5",
    "sg:province":"QC",
    "sg:tags":[
        "attorney"
    ],
    "wof:name":"Aide Juridique",
    "wof:placetype":"venue"
},
  "geometry": {"coordinates":[-75.979141,46.374573],"type":"Point"}
}