{
  "type": "Feature",
  "properties": {
    "addr:full":"Chazel QC J0Z 1N0",
    "addr:postcode":"j0z 1n0",
    "iso:country":"CA",
    "sg:city":"Chazel",
    "sg:classifiers":[
        {
            "category":"Freight",
            "type":"Transportation"
        }
    ],
    "sg:phone":"+1 819 333 4780",
    "sg:postcode":"J0Z 1N0",
    "sg:province":"QC",
    "sg:tags":[
        "trucking"
    ],
    "wof:name":"Entreprises Labranche & Fils",
    "wof:placetype":"venue"
},
  "geometry": {"coordinates":[-79.042419,48.864552],"type":"Point"}
}