{
  "type": "Feature",
  "properties": {
    "addr:full":"20 West Ave Woodstock ON N4S 8H9",
    "addr:housenumber":"20",
    "addr:postcode":"n4s 8h9",
    "addr:street":"West Ave",
    "iso:country":"CA",
    "sg:address":"20 West Ave",
    "sg:city":"Woodstock",
    "sg:classifiers":[
        {
            "category":"Professional",
            "subcategory":"Accounting & Tax Preparation",
            "type":"Services"
        }
    ],
    "sg:phone":"+1 519 539 1278",
    "sg:postcode":"N4S 8H9",
    "sg:province":"ON",
    "sg:tags":[
        "accountant"
    ],
    "wof:name":"Symons Wearn & Smith",
    "wof:placetype":"venue"
},
  "geometry": {"coordinates":[-80.73996,43.132732],"type":"Point"}
}