{
  "type": "Feature",
  "properties": {
    "addr:full":"150 Weldon St Moncton NB E1C 5W4",
    "addr:housenumber":"150",
    "addr:postcode":"e1c 5w4",
    "addr:street":"Weldon St",
    "iso:country":"CA",
    "sg:address":"150 Weldon St",
    "sg:city":"Moncton",
    "sg:classifiers":[
        {
            "category":"Organizations",
            "subcategory":"Professional Association",
            "type":"Services"
        }
    ],
    "sg:phone":"+1 506 857 0014",
    "sg:postcode":"E1C 5W4",
    "sg:province":"NB",
    "wof:name":"Ergon Inc",
    "wof:placetype":"venue"
},
  "geometry": {"coordinates":[-64.788116,46.090202],"type":"Point"}
}