{
  "type": "Feature",
  "properties": {
    "addr:full":"315 Rosemary Rd Toronto ON M5P 3E4",
    "addr:housenumber":"315",
    "addr:postcode":"m5p 3e4",
    "addr:street":"Rosemary Rd",
    "iso:country":"CA",
    "sg:address":"315 Rosemary Rd",
    "sg:city":"Toronto",
    "sg:classifiers":[
        {
            "category":"Real Estate",
            "subcategory":"Architect",
            "type":"Services"
        }
    ],
    "sg:phone":"+1 416 922 0518",
    "sg:postcode":"M5P 3E4",
    "sg:province":"ON",
    "wof:name":"Young, Allan M",
    "wof:placetype":"venue"
},
  "geometry": {"coordinates":[-79.42128,43.697174],"type":"Point"}
}