{
  "type": "Feature",
  "properties": {
    "addr:full":"640 Connaught Dr Jasper AB T0E 1E0",
    "addr:housenumber":"640",
    "addr:postcode":"t0e 1e0",
    "addr:street":"Connaught Dr",
    "iso:country":"CA",
    "sg:address":"640 Connaught Dr",
    "sg:city":"Jasper",
    "sg:classifiers":[
        {
            "category":"Restaurant",
            "type":"Food & Drink"
        }
    ],
    "sg:phone":"+1 780 852 5520",
    "sg:postcode":"T0E 1E0",
    "sg:province":"AB",
    "wof:name":"Kfc",
    "wof:placetype":"venue"
},
  "geometry": {"coordinates":[-118.080833435,52.8750190735],"type":"Point"}
}