{
  "type": "Feature",
  "properties": {
    "addr:full":"7215 Macleod Trail SW Calgary AB T2H 0L8",
    "addr:housenumber":"7215",
    "addr:postcode":"t2h 0l8",
    "addr:street":"Macleod Trail Sw",
    "iso:country":"CA",
    "sg:address":"7215 Macleod Trail SW",
    "sg:city":"Calgary",
    "sg:classifiers":[
        {
            "category":"Restaurant",
            "type":"Food & Drink"
        }
    ],
    "sg:phone":"+1 403 253 4818",
    "sg:postcode":"T2H 0L8",
    "sg:province":"AB",
    "wof:name":"Denny's Restaurant",
    "wof:placetype":"venue"
},
  "geometry": {"coordinates":[-114.071884,50.989349],"type":"Point"}
}