{
  "type": "Feature",
  "properties": {
    "iso:country":"CA",
    "sg:address":"4820 Herald St",
    "sg:city":"Macklin",
    "sg:classifiers":[
        {
            "category":"Home & Garden",
            "subcategory":"Hardware",
            "type":"Retail Goods"
        }
    ],
    "sg:phone":"+1 306 753 2144",
    "sg:postcode":"S0L 2C0",
    "sg:province":"SK",
    "wof:name":"Thomas Home Furnishings & Hdwr",
    "wof:placetype":"venue"
},
  "geometry": {"coordinates":[-109.935890198,52.3328132629],"type":"Point"}
}