{
  "type": "Feature",
  "properties": {
    "iso:country":"CA",
    "sg:address":"33417 Huntingdon Rd",
    "sg:city":"Abbotsford",
    "sg:classifiers":[
        {
            "category":"Building & Trades",
            "subcategory":"Electrical",
            "type":"Services"
        }
    ],
    "sg:phone":"+1 604 850 5024",
    "sg:postcode":"V2S 7Z6",
    "sg:province":"BC",
    "sg:tags":[
        "electric",
        "contractor"
    ],
    "wof:name":"Aec Electric",
    "wof:placetype":"venue"
},
  "geometry": {"coordinates":[-122.298652649,49.0170440674],"type":"Point"}
}