{
  "type": "Feature",
  "properties": {
    "iso:country":"CA",
    "sg:address":"2082 James St",
    "sg:city":"Burlington",
    "sg:classifiers":[
        {
            "category":"Personal",
            "subcategory":"Beauty Salon",
            "type":"Services"
        }
    ],
    "sg:phone":"+1 905 681 9887",
    "sg:postcode":"L7R 1H6",
    "sg:province":"ON",
    "wof:name":"Kate's Hair Expressions",
    "wof:placetype":"venue"
},
  "geometry": {"coordinates":[-79.795761,43.327679],"type":"Point"}
}