{
  "type": "Feature",
  "properties": {
    "iso:country":"CA",
    "sg:address":"304 6th Ave",
    "sg:city":"New Denver",
    "sg:classifiers":[
        {
            "category":"Recreation",
            "type":"Entertainment"
        }
    ],
    "sg:phone":"+1 250 358 2821",
    "sg:postcode":"V0G 1S0",
    "sg:province":"BC",
    "sg:tags":[
        "lottery",
        "agent"
    ],
    "wof:name":"My Aunt's General Store",
    "wof:placetype":"venue"
},
  "geometry": {"coordinates":[-117.37720489500001,49.9915466309],"type":"Point"}
}