{
  "type": "Feature",
  "properties": {
    "iso:country":"CA",
    "sg:address":"15357 117 Ave NW",
    "sg:city":"Edmonton",
    "sg:classifiers":[
        {
            "category":"Manufacturing",
            "subcategory":"Furniture",
            "type":"Manufacturing & Wholesale Goods"
        }
    ],
    "sg:phone":"+1 780 944 9407",
    "sg:postcode":"T5M 3X4",
    "sg:province":"AB",
    "sg:tags":[
        "equipment",
        "motel",
        "hotel",
        "bar"
    ],
    "wof:name":"Newton's Draft Beer Equipment",
    "wof:placetype":"venue"
},
  "geometry": {"coordinates":[-113.5859375,53.5692405701],"type":"Point"}
}