{
  "type": "Feature",
  "properties": {
    "addr:full":"Rigaud QC J0P 1P0",
    "addr:postcode":"j0p 1p0",
    "iso:country":"CA",
    "sg:city":"Rigaud",
    "sg:classifiers":[
        {
            "category":"Retail",
            "subcategory":"Auto Repair",
            "type":"Services"
        }
    ],
    "sg:phone":"+1 450 451 6475",
    "sg:postcode":"J0P 1P0",
    "sg:province":"QC",
    "sg:tags":[
        "repairing",
        "automobile"
    ],
    "wof:name":"Mecanique Gaetan Reid",
    "wof:placetype":"venue"
},
  "geometry": {"coordinates":[-74.2948150635,45.479549408],"type":"Point"}
}