{
  "type": "Feature",
  "properties": {
    "addr:full":"Highway 3 Maidstone ON N0R 1K0",
    "addr:postcode":"n0r 1k0",
    "addr:street":"Highway 3",
    "iso:country":"CA",
    "sg:address":"Highway 3",
    "sg:city":"Maidstone",
    "sg:classifiers":[
        {
            "category":"Government",
            "subcategory":"Office",
            "type":"Public Place"
        }
    ],
    "sg:phone":"+1 519 737 6181",
    "sg:postcode":"N0R 1K0",
    "sg:province":"ON",
    "wof:name":"Ontario Transportation Patrol",
    "wof:placetype":"venue"
},
  "geometry": {"coordinates":[-82.890511,42.210068],"type":"Point"}
}