{
  "type": "Feature",
  "properties": {
    "addr:full":"Garson ON P3L 1V4",
    "addr:postcode":"p3l 1v4",
    "iso:country":"CA",
    "sg:city":"Garson",
    "sg:classifiers":[
        {
            "category":"Education",
            "subcategory":"Special Training",
            "type":"Public Place"
        }
    ],
    "sg:phone":"+1 705 693 2527",
    "sg:postcode":"P3L 1V4",
    "sg:province":"ON",
    "sg:tags":[
        "aircraft",
        "school"
    ],
    "wof:name":"Sudbury Flying Club",
    "wof:placetype":"venue"
},
  "geometry": {"coordinates":[-80.795349,46.62291],"type":"Point"}
}