{
  "type": "Feature",
  "properties": {
    "addr:full":"2848 Carp Rd Carp ON K0A 1L0",
    "addr:housenumber":"2848",
    "addr:postcode":"k0a 1l0",
    "addr:street":"Carp Rd",
    "iso:country":"CA",
    "sg:address":"2848 Carp Rd",
    "sg:city":"Carp",
    "sg:classifiers":[
        {
            "category":"Autos & Motor Vehicles",
            "subcategory":"Automobile Sales",
            "type":"Retail Goods"
        }
    ],
    "sg:phone":"+1 613 831 4631",
    "sg:postcode":"K0A 1L0",
    "sg:province":"ON",
    "sg:tags":[
        "car",
        "dealer"
    ],
    "wof:name":"Import Extra Ltd",
    "wof:placetype":"venue"
},
  "geometry": {"coordinates":[-75.989372,45.30743],"type":"Point"}
}