{
  "type": "Feature",
  "properties": {
    "iso:country":"CA",
    "sg:city":"Kitimat",
    "sg:classifiers":[
        {
            "category":"Professional",
            "subcategory":"Research",
            "type":"Services"
        }
    ],
    "sg:phone":"+1 250 632 2282",
    "sg:postcode":"V8C 1T6",
    "sg:province":"BC",
    "sg:tags":[
        "environmental",
        "ecological",
        "engineer"
    ],
    "wof:name":"Earth Tech Inc",
    "wof:placetype":"venue"
},
  "geometry": {"coordinates":[-128.65541076700001,54.0533256531],"type":"Point"}
}