{
  "type": "Feature",
  "properties": {
    "addr:full":"16669 113 Ave NW Edmonton AB T5M 2X2",
    "addr:housenumber":"16669",
    "addr:postcode":"t5m 2x2",
    "addr:street":"113 Ave Nw",
    "iso:country":"CA",
    "sg:address":"16669 113 Ave NW",
    "sg:city":"Edmonton",
    "sg:classifiers":[
        {
            "category":"Building & Trades",
            "subcategory":"Construction",
            "type":"Services"
        }
    ],
    "sg:phone":"+1 780 483 4540",
    "sg:postcode":"T5M 2X2",
    "sg:province":"AB",
    "sg:tags":[
        "maker",
        "cabinet"
    ],
    "wof:name":"Hi-Lite Cabinets",
    "wof:placetype":"venue"
},
  "geometry": {"coordinates":[-113.608459,53.561211],"type":"Point"}
}