{
  "type": "Feature",
  "properties": {
    "addr:full":"6000 122 Rte Saint-Cyrille-DE-Wendover QC J1Z 1G1",
    "addr:housenumber":"6000",
    "addr:postcode":"j1z 1g1",
    "addr:street":"122 Rte",
    "iso:country":"CA",
    "sg:address":"6000 122 Rte",
    "sg:city":"Saint-Cyrille-DE-Wendover",
    "sg:classifiers":[
        {
            "category":"Autos & Motor Vehicles",
            "subcategory":"Automobile Sales",
            "type":"Retail Goods"
        }
    ],
    "sg:phone":"+1 819 397 4373",
    "sg:postcode":"J1Z 1G1",
    "sg:province":"QC",
    "sg:tags":[
        "car",
        "dealer"
    ],
    "wof:name":"Denis Boucher Automobiles Inc",
    "wof:placetype":"venue"
},
  "geometry": {"coordinates":[-72.425026,45.932411],"type":"Point"}
}