{
  "type": "Feature",
  "properties": {
    "addr:full":"1522 Sunningdale Rd E London ON N5X 3Y6",
    "addr:housenumber":"1522",
    "addr:postcode":"n5x 3y6",
    "addr:street":"Sunningdale Rd E",
    "iso:country":"CA",
    "sg:address":"1522 Sunningdale Rd E",
    "sg:city":"London",
    "sg:classifiers":[
        {
            "category":"Shopping",
            "subcategory":"Bicycles & Sporting Goods",
            "type":"Retail Goods"
        }
    ],
    "sg:phone":"+1 519 672 3100",
    "sg:postcode":"N5X 3Y6",
    "sg:province":"ON",
    "sg:tags":[
        "diving",
        "instruction"
    ],
    "wof:name":"Dive With Mar",
    "wof:placetype":"venue"
},
  "geometry": {"coordinates":[-81.2372970581,43.053730011],"type":"Point"}
}