{
  "type": "Feature",
  "properties": {
    "addr:full":"Richmond Hill ON L4B 4K3",
    "addr:postcode":"l4b 4k3",
    "iso:country":"CA",
    "sg:city":"Richmond Hill",
    "sg:classifiers":[
        {
            "category":"Home & Garden",
            "subcategory":"Furniture",
            "type":"Retail Goods"
        }
    ],
    "sg:phone":"+1 905 882 1811",
    "sg:postcode":"L4B 4K3",
    "sg:province":"ON",
    "wof:name":"Decorative Deminsions",
    "wof:placetype":"venue"
},
  "geometry": {"coordinates":[-79.3834533691,43.8496665955],"type":"Point"}
}