{
  "type": "Feature",
  "properties": {
    "iso:country":"CA",
    "sg:address":"26 Earl Ave",
    "sg:city":"Dryden",
    "sg:classifiers":[
        {
            "category":"Banks & Credit Unions",
            "subcategory":"Investment Brokerage",
            "type":"Services"
        }
    ],
    "sg:phone":"+1 807 223 2600",
    "sg:postcode":"P8N 1X5",
    "sg:province":"ON",
    "wof:name":"Bmo Nesbitt Burns Inc",
    "wof:placetype":"venue"
},
  "geometry": {"coordinates":[-92.8410110474,49.7839775085],"type":"Point"}
}