{
  "type": "Feature",
  "properties": {
    "iso:country":"CA",
    "sg:address":"35 Pine St S",
    "sg:city":"Timmins",
    "sg:classifiers":[
        {
            "category":"Professional",
            "subcategory":"Business Services",
            "type":"Services"
        }
    ],
    "sg:phone":"+1 705 264 1010",
    "sg:postcode":"P4N 2J9",
    "sg:province":"ON",
    "sg:tags":[
        "sporting",
        "good",
        "embroidery"
    ],
    "wof:name":"Source For Sports Timmins",
    "wof:placetype":"venue"
},
  "geometry": {"coordinates":[-81.3285369873,48.4754638672],"type":"Point"}
}