{
  "type": "Feature",
  "properties": {
    "addr:full":"779 Vaughan Rd York ON M6E 2Z5",
    "addr:housenumber":"779",
    "addr:postcode":"m6e 2z5",
    "addr:street":"Vaughan Rd",
    "iso:country":"CA",
    "sg:address":"779 Vaughan Rd",
    "sg:city":"York",
    "sg:classifiers":[
        {
            "category":"Manufacturing",
            "subcategory":"Printing",
            "type":"Manufacturing & Wholesale Goods"
        }
    ],
    "sg:phone":"+1 416 781 9150",
    "sg:postcode":"M6E 2Z5",
    "sg:province":"ON",
    "sg:tags":[
        "printer"
    ],
    "wof:name":"D L Graphics",
    "wof:placetype":"venue"
},
  "geometry": {"coordinates":[-79.447372,43.694916],"type":"Point"}
}