{
  "type": "Feature",
  "properties": {
    "addr:full":"Lac Du Bonnet MB R0E 1A0",
    "addr:postcode":"r0e 1a0",
    "iso:country":"CA",
    "sg:city":"Lac Du Bonnet",
    "sg:classifiers":[
        {
            "category":"Social Services",
            "type":"Services"
        }
    ],
    "sg:phone":"+1 204 345 8529",
    "sg:postcode":"R0E 1A0",
    "sg:province":"MB",
    "sg:tags":[
        "youth",
        "organization",
        "center"
    ],
    "wof:name":"Youth For Christ",
    "wof:placetype":"venue"
},
  "geometry": {"coordinates":[-96.06196594239999,50.2516365051],"type":"Point"}
}