{
  "type": "Feature",
  "properties": {
    "iso:country":"CA",
    "sg:address":"505 Village Green Ave",
    "sg:city":"London",
    "sg:classifiers":[
        {
            "category":"Organizations",
            "subcategory":"Religious Organization",
            "type":"Services"
        }
    ],
    "sg:phone":"+1 519 473 5505",
    "sg:postcode":"N6J 4G4",
    "sg:province":"ON",
    "sg:tags":[
        "church"
    ],
    "wof:name":"Village Green Baptist Church",
    "wof:placetype":"venue"
},
  "geometry": {"coordinates":[-81.288734436,42.9512252808],"type":"Point"}
}