{
  "type": "Feature",
  "properties": {
    "addr:full":"120 Broadway St N Deloraine MB R0M 0M0",
    "addr:housenumber":"120",
    "addr:postcode":"r0m 0m0",
    "addr:street":"Broadway St N Deloraine",
    "iso:country":"CA",
    "sg:address":"120 Broadway St N",
    "sg:city":"Deloraine",
    "sg:classifiers":[
        {
            "category":"Manufacturing",
            "subcategory":"Printing",
            "type":"Manufacturing & Wholesale Goods"
        }
    ],
    "sg:phone":"+1 204 747 2249",
    "sg:postcode":"R0M 0M0",
    "sg:province":"MB",
    "sg:tags":[
        "newspaper"
    ],
    "wof:name":"Deloraine Times & Star",
    "wof:placetype":"venue"
},
  "geometry": {"coordinates":[-100.496071,49.193336],"type":"Point"}
}