{
  "type": "Feature",
  "properties": {
    "iso:country":"CA",
    "sg:address":"2525 Carling Ave # 20",
    "sg:city":"Ottawa",
    "sg:classifiers":[
        {
            "category":"Real Estate",
            "subcategory":"Real Estate Operator",
            "type":"Services"
        }
    ],
    "sg:phone":"+1 613 828 3783",
    "sg:postcode":"K2B 7Z2",
    "sg:province":"ON",
    "sg:tags":[
        "mall",
        "shopping",
        "center"
    ],
    "wof:name":"Lincoln Fields Shopping Ctr",
    "wof:placetype":"venue"
},
  "geometry": {"coordinates":[-75.785194397,45.3640632629],"type":"Point"}
}