{
  "type": "Feature",
  "properties": {
    "addr:full":"8 Tower Rd Nepean ON K2G 2E3",
    "addr:housenumber":"8",
    "addr:postcode":"k2g 2e3",
    "addr:street":"Tower Rd",
    "iso:country":"CA",
    "sg:address":"8 Tower Rd",
    "sg:city":"Nepean",
    "sg:classifiers":[
        {
            "category":"Home & Garden",
            "subcategory":"Building Materials",
            "type":"Retail Goods"
        }
    ],
    "sg:phone":"+1 613 274 7626",
    "sg:postcode":"K2G 2E3",
    "sg:province":"ON",
    "sg:tags":[
        "windows",
        "improvement"
    ],
    "wof:name":"J R Windows Doors & Renovation",
    "wof:placetype":"venue"
},
  "geometry": {"coordinates":[-75.7386703491,45.3558731079],"type":"Point"}
}