{
  "type": "Feature",
  "properties": {
    "addr:full":"750 Boul Lemire Drummondville QC J2C 7W9",
    "addr:housenumber":"750",
    "addr:postcode":"j2c 7w9",
    "addr:street":"Boul Lemire",
    "iso:country":"CA",
    "sg:address":"750 Boul Lemire",
    "sg:city":"Drummondville",
    "sg:classifiers":[
        {
            "category":"Autos & Motor Vehicles",
            "subcategory":"Auto Supplies",
            "type":"Retail Goods"
        }
    ],
    "sg:phone":"+1 819 474 5200",
    "sg:postcode":"J2C 7W9",
    "sg:province":"QC",
    "sg:tags":[
        "tire"
    ],
    "wof:name":"Centre Du Pneu Patry Inc",
    "wof:placetype":"venue"
},
  "geometry": {"coordinates":[-72.527573,45.880116],"type":"Point"}
}