{
  "type": "Feature",
  "properties": {
    "addr:full":"1281 Jefferson Ave Winnipeg MB R2P 1S7",
    "addr:housenumber":"1281",
    "addr:postcode":"r2p 1s7",
    "addr:street":"Jefferson Ave",
    "iso:country":"CA",
    "sg:address":"1281 Jefferson Ave",
    "sg:city":"Winnipeg",
    "sg:classifiers":[
        {
            "category":"Health Services",
            "subcategory":"Doctor",
            "type":"Services"
        }
    ],
    "sg:phone":"+1 204 632 6980",
    "sg:postcode":"R2P 1S7",
    "sg:province":"MB",
    "sg:tags":[
        "dentist"
    ],
    "wof:name":"Maples Dental Ctr",
    "wof:placetype":"venue"
},
  "geometry": {"coordinates":[-97.17067,49.953098],"type":"Point"}
}