{
  "type": "Feature",
  "properties": {
    "addr:full":"64 Brookland St Sydney NS B1P 5B2",
    "addr:housenumber":"64",
    "addr:postcode":"b1p 5b2",
    "addr:street":"Brookland St",
    "iso:country":"CA",
    "sg:address":"64 Brookland St",
    "sg:city":"Sydney",
    "sg:classifiers":[
        {
            "category":"Wholesale",
            "subcategory":"Hardware",
            "type":"Manufacturing & Wholesale Goods"
        }
    ],
    "sg:phone":"+1 902 564 1144",
    "sg:postcode":"B1P 5B2",
    "sg:province":"NS",
    "sg:tags":[
        "plumbing",
        "fixture",
        "supply"
    ],
    "wof:name":"Sumner Plumbing Supply",
    "wof:placetype":"venue"
},
  "geometry": {"coordinates":[-60.1883277893,46.1337203979],"type":"Point"}
}