{
  "type": "Feature",
  "properties": {
    "addr:full":"Sorel-Tracy QC J3P 3P9",
    "addr:postcode":"j3p 3p9",
    "iso:country":"CA",
    "sg:city":"Sorel-Tracy",
    "sg:classifiers":[
        {
            "category":"Shopping",
            "type":"Retail Goods"
        }
    ],
    "sg:phone":"+1 450 742 9366",
    "sg:postcode":"J3P 3P9",
    "sg:province":"QC",
    "sg:tags":[
        "equipment",
        "telephone",
        "supply"
    ],
    "wof:name":"Desmarais Protection Elec",
    "wof:placetype":"venue"
},
  "geometry": {"coordinates":[-73.09689299999999,46.038723],"type":"Point"}
}