{
  "type": "Feature",
  "properties": {
    "iso:country":"CA",
    "sg:address":"192 Main St E",
    "sg:city":"Milton",
    "sg:classifiers":[
        {
            "category":"Banks & Credit Unions",
            "subcategory":"Bank",
            "type":"Services"
        }
    ],
    "sg:phone":"+1 905 876 2165",
    "sg:postcode":"L9T 1N8",
    "sg:province":"ON",
    "sg:tags":[
        "loan"
    ],
    "wof:name":"Jashin Financial Svc",
    "wof:placetype":"venue"
},
  "geometry": {"coordinates":[-79.883575,43.512531],"type":"Point"}
}