{
  "type": "Feature",
  "properties": {
    "addr:full":"1200 Boul Rome Brossard QC J4W 3H3",
    "addr:housenumber":"1200",
    "addr:postcode":"j4w 3h3",
    "addr:street":"Boul Rome",
    "iso:country":"CA",
    "sg:address":"1200 Boul Rome",
    "sg:city":"Brossard",
    "sg:classifiers":[
        {
            "category":"Personal",
            "subcategory":"Beauty Salon",
            "type":"Services"
        }
    ],
    "sg:phone":"+1 450 465 0016",
    "sg:postcode":"J4W 3H3",
    "sg:province":"QC",
    "wof:name":"L'Equipe Passion",
    "wof:placetype":"venue"
},
  "geometry": {"coordinates":[-73.4921417236,45.4571990967],"type":"Point"}
}