{
  "type": "Feature",
  "properties": {
    "addr:full":"3381 Tennyson Ave Victoria BC V8Z 3P7",
    "addr:housenumber":"3381",
    "addr:postcode":"v8z 3p7",
    "addr:street":"Tennyson Ave",
    "iso:country":"CA",
    "sg:address":"3381 Tennyson Ave",
    "sg:city":"Victoria",
    "sg:classifiers":[
        {
            "category":"Home & Garden",
            "subcategory":"Home Furnishings",
            "type":"Retail Goods"
        }
    ],
    "sg:phone":"+1 250 475 2600",
    "sg:postcode":"V8Z 3P7",
    "sg:province":"BC",
    "sg:tags":[
        "venetian",
        "curtain",
        "drapery"
    ],
    "wof:name":"Island Window Coverings Ltd",
    "wof:placetype":"venue"
},
  "geometry": {"coordinates":[-123.364517212,48.428314209],"type":"Point"}
}