{
  "type": "Feature",
  "properties": {
    "iso:country":"CA",
    "sg:city":"Montreal",
    "sg:classifiers":[
        {
            "category":"Banks & Credit Unions",
            "subcategory":"Financial Services",
            "type":"Services"
        }
    ],
    "sg:phone":"+1 514 849 4581",
    "sg:postcode":"H3A 1K2",
    "sg:province":"QC",
    "sg:tags":[
        "bankruptcy",
        "trustee"
    ],
    "wof:name":"Hoppenheim & Assoc",
    "wof:placetype":"venue"
},
  "geometry": {"coordinates":[-73.572281,45.504887],"type":"Point"}
}