{
  "type": "Feature",
  "properties": {
    "iso:country":"CA",
    "sg:address":"29 Parkside Dr",
    "sg:city":"St Jacobs",
    "sg:classifiers":[
        {
            "category":"Arena",
            "subcategory":"Sports Club",
            "type":"Entertainment"
        }
    ],
    "sg:phone":"+1 519 664 3310",
    "sg:postcode":"N0B 2N0",
    "sg:province":"ON",
    "sg:tags":[
        "athletic",
        "fields",
        "stadium",
        "government"
    ],
    "wof:name":"St Jacobs Arena",
    "wof:placetype":"venue"
},
  "geometry": {"coordinates":[-80.5507354736,43.5436820984],"type":"Point"}
}