{
  "type": "Feature",
  "properties": {
    "addr:full":"1531 Queen St W Toronto ON M6R 1A5",
    "addr:housenumber":"1531",
    "addr:postcode":"m6r 1a5",
    "addr:street":"Queen St W",
    "iso:country":"CA",
    "sg:address":"1531 Queen St W",
    "sg:city":"Toronto",
    "sg:classifiers":[
        {
            "category":"Manufacturing",
            "subcategory":"Printing",
            "type":"Manufacturing & Wholesale Goods"
        }
    ],
    "sg:phone":"+1 416 534 7836",
    "sg:postcode":"M6R 1A5",
    "sg:province":"ON",
    "sg:tags":[
        "newspaper"
    ],
    "wof:name":"Filipiniana News",
    "wof:placetype":"venue"
},
  "geometry": {"coordinates":[-79.442314,43.639374],"type":"Point"}
}