{
  "type": "Feature",
  "properties": {
    "addr:full":"808 Greenbank Rd Nepean ON K2J 1A2",
    "addr:housenumber":"808",
    "addr:postcode":"k2j 1a2",
    "addr:street":"Greenbank Rd",
    "iso:country":"CA",
    "sg:address":"808 Greenbank Rd",
    "sg:city":"Nepean",
    "sg:classifiers":[
        {
            "category":"Personal",
            "subcategory":"Beauty Salon",
            "type":"Services"
        }
    ],
    "sg:phone":"+1 613 825 4213",
    "sg:postcode":"K2J 1A2",
    "sg:province":"ON",
    "wof:name":"Barrhaven Beauty Salon",
    "wof:placetype":"venue"
},
  "geometry": {"coordinates":[-75.75691223139999,45.2874984741],"type":"Point"}
}