{
  "type": "Feature",
  "properties": {
    "addr:full":"74 Scott St New Liskeard ON P0J 1P0",
    "addr:housenumber":"74",
    "addr:postcode":"p0j 1p0",
    "addr:street":"Scott St",
    "iso:country":"CA",
    "sg:address":"74 Scott St",
    "sg:city":"New Liskeard",
    "sg:classifiers":[
        {
            "category":"Wholesale",
            "subcategory":"Machinery & Supplies",
            "type":"Manufacturing & Wholesale Goods"
        }
    ],
    "sg:phone":"+1 705 647 6900",
    "sg:postcode":"P0J 1P0",
    "sg:province":"ON",
    "sg:tags":[
        "equipment",
        "hydraulic"
    ],
    "wof:name":"Northern Hydraulic & Ind Sales",
    "wof:placetype":"venue"
},
  "geometry": {"coordinates":[-79.684219,47.510433],"type":"Point"}
}