{
  "type": "Feature",
  "properties": {
    "addr:full":"1260 Boul Lionel-Boulet Varennes QC J3X 1P7",
    "addr:housenumber":"1260",
    "addr:postcode":"j3x 1p7",
    "addr:street":"Boul Lionel-Boulet",
    "iso:country":"CA",
    "sg:address":"1260 Boul Lionel-Boulet",
    "sg:city":"Varennes",
    "sg:classifiers":[
        {
            "category":"Wholesale",
            "subcategory":"Electrical",
            "type":"Manufacturing & Wholesale Goods"
        }
    ],
    "sg:phone":"+1 450 929 1441",
    "sg:postcode":"J3X 1P7",
    "sg:province":"QC",
    "sg:tags":[
        "generator"
    ],
    "wof:name":"Mechinerie Parent Canada Inc",
    "wof:placetype":"venue"
},
  "geometry": {"coordinates":[-73.40673828120001,45.6442604065],"type":"Point"}
}