{
  "type": "Feature",
  "properties": {
    "addr:full":"5401 Moriarty Cres Prince George BC V2N 4C5",
    "addr:housenumber":"5401",
    "addr:postcode":"v2n 4c5",
    "addr:street":"Moriarty Cres",
    "iso:country":"CA",
    "sg:address":"5401 Moriarty Cres",
    "sg:city":"Prince George",
    "sg:classifiers":[
        {
            "category":"Organizations",
            "subcategory":"Religious Organization",
            "type":"Services"
        }
    ],
    "sg:phone":"+1 250 964 4181",
    "sg:postcode":"V2N 4C5",
    "sg:province":"BC",
    "sg:tags":[
        "church"
    ],
    "wof:name":"College Heights Baptist Church",
    "wof:placetype":"venue"
},
  "geometry": {"coordinates":[-122.773499,53.86829],"type":"Point"}
}