{
  "type": "Feature",
  "properties": {
    "addr:full":"179 Rue Hemond Saint-Eustache QC J7P 2C2",
    "addr:housenumber":"179",
    "addr:postcode":"j7p 2c2",
    "addr:street":"Rue Hemond",
    "iso:country":"CA",
    "sg:address":"179 Rue Hemond",
    "sg:city":"Saint-Eustache",
    "sg:classifiers":[
        {
            "category":"Personal",
            "subcategory":"Beauty Salon",
            "type":"Services"
        }
    ],
    "sg:phone":"+1 450 473 8304",
    "sg:postcode":"J7P 2C2",
    "sg:province":"QC",
    "wof:name":"Esthetique Belle DE Jour Enr",
    "wof:placetype":"venue"
},
  "geometry": {"coordinates":[-73.89901733400001,45.5614471436],"type":"Point"}
}