{
  "type": "Feature",
  "properties": {
    "addr:full":"497 Corydon Ave Winnipeg MB R3L 0N9",
    "addr:housenumber":"497",
    "addr:postcode":"r3l 0n9",
    "addr:street":"Corydon Ave",
    "iso:country":"CA",
    "sg:address":"497 Corydon Ave",
    "sg:city":"Winnipeg",
    "sg:classifiers":[
        {
            "category":"Banks & Credit Unions",
            "subcategory":"Investment Brokerage",
            "type":"Services"
        }
    ],
    "sg:phone":"+1 204 589 8446",
    "sg:postcode":"R3L 0N9",
    "sg:province":"MB",
    "sg:tags":[
        "funds",
        "mutual"
    ],
    "wof:name":"Galarnyk Financial",
    "wof:placetype":"venue"
},
  "geometry": {"coordinates":[-97.1442565918,49.8740081787],"type":"Point"}
}