{
  "type": "Feature",
  "properties": {
    "addr:full":"39 Main St W Grimsby ON L3M 1R3",
    "addr:housenumber":"39",
    "addr:postcode":"l3m 1r3",
    "addr:street":"Main St W",
    "iso:country":"CA",
    "sg:address":"39 Main St W",
    "sg:city":"Grimsby",
    "sg:classifiers":[
        {
            "category":"Professional",
            "subcategory":"Employment Agencies",
            "type":"Services"
        }
    ],
    "sg:phone":"+1 905 309 5627",
    "sg:postcode":"L3M 1R3",
    "sg:province":"ON",
    "sg:tags":[
        "opportunity"
    ],
    "wof:name":"Employment Help Ctr",
    "wof:placetype":"venue"
},
  "geometry": {"coordinates":[-79.56205,43.19371],"type":"Point"}
}