{
  "type": "Feature",
  "properties": {
    "addr:full":"427 Belleville St Victoria BC V8V 1X3",
    "addr:housenumber":"427",
    "addr:postcode":"v8v 1x3",
    "addr:street":"Belleville St",
    "iso:country":"CA",
    "sg:address":"427 Belleville St",
    "sg:city":"Victoria",
    "sg:classifiers":[
        {
            "category":"Travel",
            "subcategory":"Hotels & Motels",
            "type":"Entertainment"
        }
    ],
    "sg:phone":"+1 250 386 3451",
    "sg:postcode":"V8V 1X3",
    "sg:province":"BC",
    "wof:name":"Days Inn on the Harbour",
    "wof:placetype":"venue"
},
  "geometry": {"coordinates":[-123.373062,48.421131],"type":"Point"}
}