{
  "type": "Feature",
  "properties": {
    "addr:full":"Timmins ON P4N 4X5",
    "addr:postcode":"p4n 4x5",
    "iso:country":"CA",
    "sg:city":"Timmins",
    "sg:classifiers":[
        {
            "category":"Food & Beverages",
            "subcategory":"Meat & Fish",
            "type":"Retail Goods"
        }
    ],
    "sg:phone":"+1 705 267 2066",
    "sg:postcode":"P4N 4X5",
    "sg:province":"ON",
    "sg:tags":[
        "frozen"
    ],
    "wof:name":"M & M Meat Shops",
    "wof:placetype":"venue"
},
  "geometry": {"coordinates":[-81.33805084230001,48.4787979126],"type":"Point"}
}