{
  "type": "Feature",
  "properties": {
    "addr:full":"472 Knowlton St Knowlton QC J0E 1V0",
    "addr:housenumber":"472",
    "addr:postcode":"j0e 1v0",
    "addr:street":"Knowlton St",
    "iso:country":"CA",
    "sg:address":"472 Knowlton St",
    "sg:city":"Knowlton",
    "sg:classifiers":[
        {
            "category":"Food & Beverages",
            "subcategory":"Liquor & Beverages",
            "type":"Retail Goods"
        }
    ],
    "sg:phone":"+1 450 242 1414",
    "sg:postcode":"J0E 1V0",
    "sg:province":"QC",
    "sg:tags":[
        "store"
    ],
    "wof:name":"Saq",
    "wof:placetype":"venue"
},
  "geometry": {"coordinates":[-72.52941894529999,45.214263916],"type":"Point"}
}