{
  "type": "Feature",
  "properties": {
    "addr:full":"416 Ch Saint-Louis Saint-Etienne-DE-Beauharnois QC J0S 1S0",
    "addr:housenumber":"416",
    "addr:postcode":"j0s 1s0",
    "addr:street":"Ch Saint-Louis",
    "iso:country":"CA",
    "sg:address":"416 Ch Saint-Louis",
    "sg:city":"Saint-Etienne-DE-Beauharnois",
    "sg:classifiers":[
        {
            "category":"Organizations",
            "subcategory":"Religious Organization",
            "type":"Services"
        }
    ],
    "sg:phone":"+1 450 429 5236",
    "sg:postcode":"J0S 1S0",
    "sg:province":"QC",
    "sg:tags":[
        "church"
    ],
    "wof:name":"Presbytere St-Etienne",
    "wof:placetype":"venue"
},
  "geometry": {"coordinates":[-73.914238,45.247509],"type":"Point"}
}