{
  "type": "Feature",
  "properties": {
    "iso:country":"CA",
    "sg:address":"183 Wellington St",
    "sg:city":"Delaware",
    "sg:classifiers":[
        {
            "category":"Building & Trades",
            "subcategory":"Construction",
            "type":"Services"
        }
    ],
    "sg:phone":"+1 519 652 9317",
    "sg:postcode":"N0L 1E0",
    "sg:province":"ON",
    "sg:tags":[
        "roofing",
        "contractor"
    ],
    "wof:name":"Harry Swinkels Roofing",
    "wof:placetype":"venue"
},
  "geometry": {"coordinates":[-81.4009933472,42.9126548767],"type":"Point"}
}