{
  "type": "Feature",
  "properties": {
    "iso:country":"CA",
    "sg:address":"1094 Victoria Park Ave",
    "sg:city":"East York",
    "sg:classifiers":[
        {
            "category":"Shopping",
            "subcategory":"Discount & Variety Stores",
            "type":"Retail Goods"
        }
    ],
    "sg:phone":"+1 416 755 3289",
    "sg:postcode":"M4B 2K3",
    "sg:province":"ON",
    "wof:name":"Glencrest Variety",
    "wof:placetype":"venue"
},
  "geometry": {"coordinates":[-79.295609,43.707531],"type":"Point"}
}