{
  "type": "Feature",
  "properties": {
    "iso:country":"CA",
    "sg:address":"42 Dorothy Cres",
    "sg:city":"Timberlea",
    "sg:classifiers":[
        {
            "category":"Building & Trades",
            "subcategory":"Construction",
            "type":"Services"
        }
    ],
    "sg:phone":"+1 902 876 2345",
    "sg:postcode":"B3T 1E2",
    "sg:province":"NS",
    "sg:tags":[
        "general",
        "contractor"
    ],
    "wof:name":"Right-Step Renovators-Builders",
    "wof:placetype":"venue"
},
  "geometry": {"coordinates":[-63.7364006042,44.6490211487],"type":"Point"}
}