{
  "type": "Feature",
  "properties": {
    "addr:full":"77 Ontario St Stratford ON N5A 3H1",
    "addr:housenumber":"77",
    "addr:postcode":"n5a 3h1",
    "addr:street":"Ontario St",
    "iso:country":"CA",
    "sg:address":"77 Ontario St",
    "sg:city":"Stratford",
    "sg:classifiers":[
        {
            "category":"Shopping",
            "subcategory":"Clothing, Apparel, & Fashions",
            "type":"Retail Goods"
        }
    ],
    "sg:phone":"+1 519 271 2181",
    "sg:postcode":"N5A 3H1",
    "sg:province":"ON",
    "sg:tags":[
        "furnishing"
    ],
    "wof:name":"Gordon's Men's Fashion Shop",
    "wof:placetype":"venue"
},
  "geometry": {"coordinates":[-80.981956,43.371296],"type":"Point"}
}