{
  "type": "Feature",
  "properties": {
    "addr:full":"Scarborough ON M1S 1T9",
    "addr:postcode":"m1s 1t9",
    "iso:country":"CA",
    "sg:city":"Scarborough",
    "sg:classifiers":[
        {
            "category":"Personal",
            "subcategory":"Beauty Salon",
            "type":"Services"
        }
    ],
    "sg:phone":"+1 416 298 6818",
    "sg:postcode":"M1S 1T9",
    "sg:province":"ON",
    "wof:name":"New Pearl Hair Salon Unisex",
    "wof:placetype":"venue"
},
  "geometry": {"coordinates":[-79.27021000000001,43.787041],"type":"Point"}
}