{
  "type": "Feature",
  "properties": {
    "addr:full":"54 Industrial Pky S Aurora ON L4G 3V6",
    "addr:housenumber":"54",
    "addr:postcode":"l4g 3v6",
    "addr:street":"Industrial Pky",
    "iso:country":"CA",
    "sg:address":"54 Industrial Pky S",
    "sg:city":"Aurora",
    "sg:classifiers":[
        {
            "category":"Autos & Motor Vehicles",
            "subcategory":"Auto Supplies",
            "type":"Retail Goods"
        }
    ],
    "sg:phone":"+1 905 727 8345",
    "sg:postcode":"L4G 3V6",
    "sg:province":"ON",
    "sg:tags":[
        "tire"
    ],
    "wof:name":"A & T Tire & Wheels",
    "wof:placetype":"venue"
},
  "geometry": {"coordinates":[-79.45884700000001,43.998978],"type":"Point"}
}