{
  "type": "Feature",
  "properties": {
    "addr:full":"East York ON M4B 2T8",
    "addr:postcode":"m4b 2t8",
    "iso:country":"CA",
    "sg:city":"East York",
    "sg:classifiers":[
        {
            "category":"Personal",
            "subcategory":"Beauty Salon",
            "type":"Services"
        }
    ],
    "sg:phone":"+1 416 751 5500",
    "sg:postcode":"M4B 2T8",
    "sg:province":"ON",
    "wof:name":"C & C Hair & Esthetics",
    "wof:placetype":"venue"
},
  "geometry": {"coordinates":[-79.3366928101,43.6990509033],"type":"Point"}
}