{
  "type": "Feature",
  "properties": {
    "iso:country":"CA",
    "sg:address":"1171 Smith Rd",
    "sg:city":"Navan",
    "sg:classifiers":[
        {
            "category":"Organizations",
            "subcategory":"Religious Organization",
            "type":"Services"
        }
    ],
    "sg:phone":"+1 613 835 2200",
    "sg:postcode":"K4B 1N7",
    "sg:province":"ON",
    "sg:tags":[
        "church"
    ],
    "wof:name":"St Mary's Anglican Church",
    "wof:placetype":"venue"
},
  "geometry": {"coordinates":[-75.42816925050001,45.420501709],"type":"Point"}
}