{
  "type": "Feature",
  "properties": {
    "addr:full":"786 Rang Saint-Pierre Saint-Zephirin-DE-Courval QC J0G 1V0",
    "addr:housenumber":"786",
    "addr:postcode":"j0g 1v0",
    "addr:street":"Rang Saint-Pierre Saint-Zephirin-De-Courval",
    "iso:country":"CA",
    "sg:address":"786 Rang Saint-Pierre",
    "sg:city":"Saint-Zephirin-DE-Courval",
    "sg:classifiers":[
        {
            "category":"Home & Garden",
            "subcategory":"Household Appliances",
            "type":"Retail Goods"
        }
    ],
    "sg:phone":"+1 450 564 2707",
    "sg:postcode":"J0G 1V0",
    "sg:province":"QC",
    "wof:name":"Belanger, Jacques",
    "wof:placetype":"venue"
},
  "geometry": {"coordinates":[-72.63069900000001,46.06271],"type":"Point"}
}