{
  "type": "Feature",
  "properties": {
    "addr:full":"8 Highland Park Blvd Thornhill ON L3T 1B1",
    "addr:housenumber":"8",
    "addr:postcode":"l3t 1b1",
    "addr:street":"Highland Park Blvd",
    "iso:country":"CA",
    "sg:address":"8 Highland Park Blvd",
    "sg:city":"Thornhill",
    "sg:classifiers":[
        {
            "category":"Retail",
            "subcategory":"Veterinary Services",
            "type":"Services"
        }
    ],
    "sg:phone":"+1 905 881 8310",
    "sg:postcode":"L3T 1B1",
    "sg:province":"ON",
    "sg:tags":[
        "pet",
        "veterinarian",
        "grooming",
        "washing"
    ],
    "wof:name":"Smith Veterinary Hospital",
    "wof:placetype":"venue"
},
  "geometry": {"coordinates":[-79.419601,43.799271],"type":"Point"}
}