{
  "type": "Feature",
  "properties": {
    "addr:full":"189 Rue Notre-Dame E Victoriaville QC G6P 3Z8",
    "addr:housenumber":"189",
    "addr:postcode":"g6p 3z8",
    "addr:street":"Rue Notre-Dame E",
    "iso:country":"CA",
    "sg:address":"189 Rue Notre-Dame E",
    "sg:city":"Victoriaville",
    "sg:classifiers":[
        {
            "category":"Shopping",
            "subcategory":"Clothing, Apparel, & Fashions",
            "type":"Retail Goods"
        }
    ],
    "sg:phone":"+1 819 751 2755",
    "sg:postcode":"G6P 3Z8",
    "sg:province":"QC",
    "sg:tags":[
        "item",
        "boutique"
    ],
    "wof:name":"Boutique Camee",
    "wof:placetype":"venue"
},
  "geometry": {"coordinates":[-71.955124,46.056839],"type":"Point"}
}