{
  "type": "Feature",
  "properties": {
    "iso:country":"CA",
    "sg:city":"Saint-Polycarpe",
    "sg:classifiers":[
        {
            "category":"Health Services",
            "subcategory":"Doctor",
            "type":"Services"
        }
    ],
    "sg:phone":"+1 450 265 3254",
    "sg:postcode":"J0P 1X0",
    "sg:province":"QC",
    "sg:tags":[
        "dentist"
    ],
    "wof:name":"Clinique Dentaire St Polycarpe",
    "wof:placetype":"venue"
},
  "geometry": {"coordinates":[-74.3038406372,45.3018836975],"type":"Point"}
}