{
  "type": "Feature",
  "properties": {
    "addr:full":"1060 Ch Du Lac-Beaulne Chertsey QC J0K 3K0",
    "addr:postcode":"1060;j0k 3k0",
    "addr:street":"Ch Du Lac-Beaulne",
    "iso:country":"CA",
    "sg:address":"1060 Ch Du Lac-Beaulne",
    "sg:city":"Chertsey",
    "sg:classifiers":[
        {
            "category":"Organizations",
            "subcategory":"Religious Organization",
            "type":"Services"
        }
    ],
    "sg:phone":"+1 450 882 3065",
    "sg:postcode":"J0K 3K0",
    "sg:province":"QC",
    "wof:name":"Societe Des Saints Apotres",
    "wof:placetype":"venue"
},
  "geometry": {"coordinates":[-73.9331665039,46.0259399414],"type":"Point"}
}