{
  "type": "Feature",
  "properties": {
    "addr:full":"4574 Ch DE LA Baronnie Varennes QC J3X 1P7",
    "addr:postcode":"4574;j3x 1p7",
    "addr:street":"Ch De La Baronnie",
    "iso:country":"CA",
    "sg:address":"4574 Ch DE LA Baronnie",
    "sg:city":"Varennes",
    "sg:classifiers":[
        {
            "category":"Retail",
            "subcategory":"Auto Repair",
            "type":"Services"
        }
    ],
    "sg:phone":"+1 450 652 3552",
    "sg:postcode":"J3X 1P7",
    "sg:province":"QC",
    "sg:tags":[
        "body",
        "automobile",
        "painting"
    ],
    "wof:name":"Debosselage Rive-Sud",
    "wof:placetype":"venue"
},
  "geometry": {"coordinates":[-73.37788399999999,45.720806],"type":"Point"}
}