{
  "type": "Feature",
  "properties": {
    "addr:full":"2360 Brooklyn St Aylesford NS B0P 1C0",
    "addr:housenumber":"2360",
    "addr:postcode":"b0p 1c0",
    "addr:street":"Brooklyn St",
    "iso:country":"CA",
    "sg:address":"2360 Brooklyn St",
    "sg:city":"Aylesford",
    "sg:classifiers":[
        {
            "category":"Farming",
            "subcategory":"Livestock Farm",
            "type":"Manufacturing & Wholesale Goods"
        }
    ],
    "sg:phone":"+1 902 847 3266",
    "sg:postcode":"B0P 1C0",
    "sg:province":"NS",
    "sg:tags":[
        "beekeeper"
    ],
    "wof:name":"Bragg Lumber",
    "wof:placetype":"venue"
},
  "geometry": {"coordinates":[-64.837524,45.027794],"type":"Point"}
}