{
  "type": "Feature",
  "properties": {
    "addr:full":"Burnaby BC V5H 2R4",
    "addr:postcode":"v5h 2r4",
    "iso:country":"CA",
    "sg:city":"Burnaby",
    "sg:classifiers":[
        {
            "category":"Autos & Motor Vehicles",
            "subcategory":"Boat Sales",
            "type":"Retail Goods"
        }
    ],
    "sg:phone":"+1 604 438 5977",
    "sg:postcode":"V5H 2R4",
    "sg:province":"BC",
    "sg:tags":[
        "dealer"
    ],
    "wof:name":"Navi Sport Enterprises",
    "wof:placetype":"venue"
},
  "geometry": {"coordinates":[-123.009514,49.22979],"type":"Point"}
}