{
  "type": "Feature",
  "properties": {
    "addr:full":"RR 2 Port Elgin ON N0H 2C6",
    "addr:postcode":"n0h 2c6",
    "addr:street":"Rr 2 Port",
    "iso:country":"CA",
    "sg:address":"RR 2",
    "sg:city":"Port Elgin",
    "sg:classifiers":[
        {
            "category":"Retail",
            "subcategory":"Auto Repair",
            "type":"Services"
        }
    ],
    "sg:phone":"+1 519 389 4151",
    "sg:postcode":"N0H 2C6",
    "sg:province":"ON",
    "sg:tags":[
        "body",
        "automobile",
        "painting"
    ],
    "wof:name":"Tibor's Auto Painting & Weld",
    "wof:placetype":"venue"
},
  "geometry": {"coordinates":[-76.2204284668,44.6089019775],"type":"Point"}
}