{
  "type": "Feature",
  "properties": {
    "addr:full":"Sainte-Julie QC J3E 1R6",
    "addr:postcode":"j3e 1r6",
    "iso:country":"CA",
    "sg:city":"Sainte-Julie",
    "sg:classifiers":[
        {
            "category":"Education",
            "subcategory":"Dance Studio",
            "type":"Public Place"
        }
    ],
    "sg:phone":"+1 450 922 5276",
    "sg:postcode":"J3E 1R6",
    "sg:province":"QC",
    "sg:tags":[
        "club",
        "instruction",
        "health",
        "gymnasium",
        "dancing"
    ],
    "wof:name":"Karo-Forme Enr",
    "wof:placetype":"venue"
},
  "geometry": {"coordinates":[-73.331886,45.598835],"type":"Point"}
}