{
  "type": "Feature",
  "properties": {
    "iso:country":"CA",
    "sg:address":"62 Main St # A",
    "sg:city":"Whitbourne",
    "sg:classifiers":[
        {
            "category":"Banks & Credit Unions",
            "subcategory":"Bank",
            "type":"Services"
        }
    ],
    "sg:phone":"+1 709 759 2720",
    "sg:postcode":"A0B 3K0",
    "sg:province":"NL",
    "wof:name":"Scotiabank",
    "wof:placetype":"venue"
},
  "geometry": {"coordinates":[-53.5358047485,47.4200057983],"type":"Point"}
}