{
  "type": "Feature",
  "properties": {
    "addr:full":"Chard's Hill Bonavista NL A0C 1B0",
    "addr:postcode":"a0c 1b0",
    "addr:street":"Chard'S Hill",
    "iso:country":"CA",
    "sg:address":"Chard's Hill",
    "sg:city":"Bonavista",
    "sg:classifiers":[
        {
            "category":"Building & Trades",
            "subcategory":"Equipment Rental",
            "type":"Services"
        }
    ],
    "sg:phone":"+1 709 468 7878",
    "sg:postcode":"A0C 1B0",
    "sg:province":"NL",
    "sg:tags":[
        "general",
        "contractor"
    ],
    "wof:name":"Chard's Construction",
    "wof:placetype":"venue"
},
  "geometry": {"coordinates":[-53.099121,48.65612],"type":"Point"}
}