{
  "type": "Feature",
  "properties": {
    "addr:full":"1532 Dundas St W Toronto ON M6K 1T5",
    "addr:housenumber":"1532",
    "addr:postcode":"m6k 1t5",
    "addr:street":"Dundas St W",
    "iso:country":"CA",
    "sg:address":"1532 Dundas St W",
    "sg:city":"Toronto",
    "sg:classifiers":[
        {
            "category":"Restaurant",
            "type":"Food & Drink"
        }
    ],
    "sg:phone":"+1 416 534 5939",
    "sg:postcode":"M6K 1T5",
    "sg:province":"ON",
    "wof:name":"Cafe Dong Phuong",
    "wof:placetype":"venue"
},
  "geometry": {"coordinates":[-79.432975769,43.649848938],"type":"Point"}
}