{
  "type": "Feature",
  "properties": {
    "addr:full":"373 Rue Jacques-Bedard # 101 Lac-Saint-Charles QC G3G 1P6",
    "addr:housenumber":"373",
    "addr:postcode":"g3g 1p6",
    "addr:street":"Rue Jacques-Bedard # 101 Lac-Saint-Charles",
    "iso:country":"CA",
    "sg:address":"373 Rue Jacques-Bedard # 101",
    "sg:city":"Lac-Saint-Charles",
    "sg:classifiers":[
        {
            "category":"Autos & Motor Vehicles",
            "subcategory":"Auto Supplies",
            "type":"Retail Goods"
        }
    ],
    "sg:phone":"+1 418 849 6526",
    "sg:postcode":"G3G 1P6",
    "sg:province":"QC",
    "sg:tags":[
        "automobile",
        "parts"
    ],
    "wof:name":"Carquest Pieces D'Autos",
    "wof:placetype":"venue"
},
  "geometry": {"coordinates":[-71.36391399999999,46.904671],"type":"Point"}
}