{
  "type": "Feature",
  "properties": {
    "iso:country":"CA",
    "sg:address":"3435 Rte 206",
    "sg:city":"Petit DE Grat",
    "sg:classifiers":[
        {
            "category":"Social Services",
            "type":"Services"
        }
    ],
    "sg:phone":"+1 902 226 0149",
    "sg:postcode":"B0E 2L0",
    "sg:province":"NS",
    "sg:tags":[
        "organization",
        "welfare"
    ],
    "wof:name":"Picasse Centre Educatif",
    "wof:placetype":"venue"
},
  "geometry": {"coordinates":[-60.9570388794,45.5050888062],"type":"Point"}
}