{
  "type": "Feature",
  "properties": {
    "iso:country":"CA",
    "sg:address":"5881 Thorold Stone Rd",
    "sg:city":"Niagara Falls",
    "sg:classifiers":[
        {
            "category":"Social Services",
            "type":"Services"
        }
    ],
    "sg:phone":"+1 905 358 0081",
    "sg:postcode":"L2J 1A1",
    "sg:province":"ON",
    "sg:tags":[
        "youth",
        "organization",
        "center"
    ],
    "wof:name":"Royal Canadian Army Cadet Corp",
    "wof:placetype":"venue"
},
  "geometry": {"coordinates":[-79.0930404663,43.1155395508],"type":"Point"}
}