{
  "type": "Feature",
  "properties": {
    "iso:country":"CA",
    "sg:address":"170 Holland St W",
    "sg:city":"Bradford",
    "sg:classifiers":[
        {
            "category":"Shopping",
            "type":"Retail Goods"
        }
    ],
    "sg:phone":"+1 905 775 4638",
    "sg:postcode":"L3Z 1H7",
    "sg:province":"ON",
    "sg:tags":[
        "pet",
        "food",
        "supply"
    ],
    "wof:name":"Pet Valu Canada Inc",
    "wof:placetype":"venue"
},
  "geometry": {"coordinates":[-79.5711517334,44.112739563],"type":"Point"}
}