{
  "type": "Feature",
  "properties": {
    "addr:full":"2857 Foul Bay Rd Victoria BC V8R 5C5",
    "addr:housenumber":"2857",
    "addr:postcode":"v8r 5c5",
    "addr:street":"Foul Bay Rd",
    "iso:country":"CA",
    "sg:address":"2857 Foul Bay Rd",
    "sg:city":"Victoria",
    "sg:classifiers":[
        {
            "category":"Shopping",
            "type":"Retail Goods"
        }
    ],
    "sg:phone":"+1 250 592 3532",
    "sg:postcode":"V8R 5C5",
    "sg:province":"BC",
    "sg:tags":[
        "florist",
        "wedding",
        "supply"
    ],
    "wof:name":"Dean Heights Florist",
    "wof:placetype":"venue"
},
  "geometry": {"coordinates":[-123.323128,48.419788],"type":"Point"}
}