{
  "type": "Feature",
  "properties": {
    "iso:country":"CA",
    "sg:city":"London",
    "sg:classifiers":[
        {
            "category":"Health Services",
            "subcategory":"Doctor",
            "type":"Services"
        }
    ],
    "sg:phone":"+1 519 439 8021",
    "sg:postcode":"N6A 1S2",
    "sg:province":"ON",
    "sg:tags":[
        "physician",
        "surgeon"
    ],
    "wof:name":"Somerton, Kenneth F MD",
    "wof:placetype":"venue"
},
  "geometry": {"coordinates":[-81.252922,42.994274],"type":"Point"}
}