{
  "type": "Feature",
  "properties": {
    "addr:full":"170 Rue Jean-Talon O # 408 Montreal QC H2R 2X4",
    "addr:housenumber":"170",
    "addr:postcode":"h2r 2x4",
    "addr:street":"Rue Jean-Talon O # 408",
    "iso:country":"CA",
    "sg:address":"170 Rue Jean-Talon O # 408",
    "sg:city":"Montreal",
    "sg:classifiers":[
        {
            "category":"Manufacturing",
            "subcategory":"Apparel",
            "type":"Manufacturing & Wholesale Goods"
        }
    ],
    "sg:phone":"+1 514 495 9968",
    "sg:postcode":"H2R 2X4",
    "sg:province":"QC",
    "sg:tags":[
        "clothing"
    ],
    "wof:name":"Raymond Collection",
    "wof:placetype":"venue"
},
  "geometry": {"coordinates":[-73.6164474487,45.5359153748],"type":"Point"}
}