{
  "type": "Feature",
  "properties": {
    "addr:full":"Langton ON N0E 1G0",
    "addr:postcode":"n0e 1g0",
    "iso:country":"CA",
    "sg:city":"Langton",
    "sg:classifiers":[
        {
            "category":"Restaurant",
            "type":"Food & Drink"
        }
    ],
    "sg:phone":"+1 519 875 2631",
    "sg:postcode":"N0E 1G0",
    "sg:province":"ON",
    "wof:name":"Andy's Drive in Restaurant",
    "wof:placetype":"venue"
},
  "geometry": {"coordinates":[-80.592880249,42.7620353699],"type":"Point"}
}