{
  "type": "Feature",
  "properties": {
    "iso:country":"CA",
    "sg:address":"1340 Rue Sauve E",
    "sg:city":"Montreal",
    "sg:classifiers":[
        {
            "category":"Banks & Credit Unions",
            "subcategory":"Bank",
            "type":"Services"
        }
    ],
    "sg:phone":"+1 514 388 3434",
    "sg:postcode":"H2C 2A1",
    "sg:province":"QC",
    "wof:name":"Du Cnetre Ahuntsic",
    "wof:placetype":"venue"
},
  "geometry": {"coordinates":[-73.651566,45.558407],"type":"Point"}
}