{
  "type": "Feature",
  "properties": {
    "addr:full":"50 Rue Principale Durham-Sud QC J0H 2C0",
    "addr:housenumber":"50",
    "addr:postcode":"j0h 2c0",
    "addr:street":"Rue Principale",
    "iso:country":"CA",
    "sg:address":"50 Rue Principale",
    "sg:city":"Durham-Sud",
    "sg:classifiers":[
        {
            "category":"Home & Garden",
            "subcategory":"Hardware",
            "type":"Retail Goods"
        }
    ],
    "sg:phone":"+1 819 858 2228",
    "sg:postcode":"J0H 2C0",
    "sg:province":"QC",
    "wof:name":"CO-OP DE Durham Sud",
    "wof:placetype":"venue"
},
  "geometry": {"coordinates":[-72.34032440190001,45.6622047424],"type":"Point"}
}