{
  "type": "Feature",
  "properties": {
    "addr:full":"4504 Bowness Ave Powell River BC V8A 3S1",
    "addr:housenumber":"4504",
    "addr:postcode":"v8a 3s1",
    "addr:street":"Bowness Ave Powell",
    "iso:country":"CA",
    "sg:address":"4504 Bowness Ave",
    "sg:city":"Powell River",
    "sg:classifiers":[
        {
            "category":"Professional",
            "subcategory":"Detective & Security Services",
            "type":"Services"
        }
    ],
    "sg:phone":"+1 604 485 0966",
    "sg:postcode":"V8A 3S1",
    "sg:province":"BC",
    "sg:tags":[
        "control",
        "traffic"
    ],
    "wof:name":"Ace Traffic Control Ltd",
    "wof:placetype":"venue"
},
  "geometry": {"coordinates":[-124.50644699999999,49.83757],"type":"Point"}
}