{
  "type": "Feature",
  "properties": {
    "addr:full":"54 Rue Elie-Rochefort Port-Cartier QC G5B 1N2",
    "addr:housenumber":"54",
    "addr:postcode":"g5b 1n2",
    "addr:street":"Rue Elie-Rochefort",
    "iso:country":"CA",
    "sg:address":"54 Rue Elie-Rochefort",
    "sg:city":"Port-Cartier",
    "sg:classifiers":[
        {
            "category":"Home & Garden",
            "subcategory":"Garden Supply",
            "type":"Retail Goods"
        }
    ],
    "sg:phone":"+1 418 766 5705",
    "sg:postcode":"G5B 1N2",
    "sg:province":"QC",
    "sg:tags":[
        "recreational",
        "vehicle"
    ],
    "wof:name":"Mini-Mecanique F Beaulieu Inc",
    "wof:placetype":"venue"
},
  "geometry": {"coordinates":[-66.88977800000001,50.026573],"type":"Point"}
}