{
  "type": "Feature",
  "properties": {
    "addr:full":"1636 Acadia Dr Saskatoon SK S7H 5H7",
    "addr:housenumber":"1636",
    "addr:postcode":"s7h 5h7",
    "addr:street":"Acadia Dr",
    "iso:country":"CA",
    "sg:address":"1636 Acadia Dr",
    "sg:city":"Saskatoon",
    "sg:classifiers":[
        {
            "category":"Organizations",
            "subcategory":"Religious Organization",
            "type":"Services"
        }
    ],
    "sg:phone":"+1 306 477 1234",
    "sg:postcode":"S7H 5H7",
    "sg:province":"SK",
    "sg:tags":[
        "church"
    ],
    "wof:name":"Emmanuel Baptist Church",
    "wof:placetype":"venue"
},
  "geometry": {"coordinates":[-106.599113,52.106113],"type":"Point"}
}