{
  "type": "Feature",
  "properties": {
    "iso:country":"CA",
    "sg:address":"5557 Rue Pare",
    "sg:city":"Mont-Royal",
    "sg:classifiers":[
        {
            "category":"Manufacturing",
            "subcategory":"Tools & Machinery",
            "type":"Manufacturing & Wholesale Goods"
        }
    ],
    "sg:phone":"+1 514 731 4860",
    "sg:postcode":"H4P 1P7",
    "sg:province":"QC",
    "sg:tags":[
        "machine",
        "shop"
    ],
    "wof:name":"Precision Parthenon Ltd",
    "wof:placetype":"venue"
},
  "geometry": {"coordinates":[-73.661049,45.491898],"type":"Point"}
}