{
  "type": "Feature",
  "properties": {
    "addr:full":"5557 Rue Pare Mont-Royal QC H4P 1P7",
    "addr:housenumber":"5557",
    "addr:postcode":"h4p 1p7",
    "addr:street":"Rue Pare",
    "iso:country":"CA",
    "sg:address":"5557 Rue Pare",
    "sg:city":"Mont-Royal",
    "sg:classifiers":[
        {
            "category":"Manufacturing",
            "subcategory":"Tools & Machinery",
            "type":"Manufacturing & Wholesale Goods"
        }
    ],
    "sg:phone":"+1 514 731 4860",
    "sg:postcode":"H4P 1P7",
    "sg:province":"QC",
    "sg:tags":[
        "machine",
        "shop"
    ],
    "wof:name":"Precision Parthenon Ltd",
    "wof:placetype":"venue"
},
  "geometry": {"coordinates":[-73.66104900000001,45.491898],"type":"Point"}
}