{
  "type": "Feature",
  "properties": {
    "addr:full":"Windsor ON N8X 4V2",
    "addr:postcode":"n8x 4v2",
    "iso:country":"CA",
    "sg:city":"Windsor",
    "sg:classifiers":[
        {
            "category":"Real Estate",
            "subcategory":"Real Estate Operator",
            "type":"Services"
        }
    ],
    "sg:phone":"+1 519 977 6812",
    "sg:postcode":"N8X 4V2",
    "sg:province":"ON",
    "sg:tags":[
        "apartment"
    ],
    "wof:name":"Marine City Apartments Ltd",
    "wof:placetype":"venue"
},
  "geometry": {"coordinates":[-83.02565002439999,42.2970161438],"type":"Point"}
}