{
  "type": "Feature",
  "properties": {
    "addr:full":"3355 Grandview Hwy Vancouver BC V5M 1Z5",
    "addr:housenumber":"3355",
    "addr:postcode":"v5m 1z5",
    "addr:street":"Grandview Hwy",
    "iso:country":"CA",
    "sg:address":"3355 Grandview Hwy",
    "sg:city":"Vancouver",
    "sg:classifiers":[
        {
            "category":"Manufacturing",
            "subcategory":"Printing",
            "type":"Manufacturing & Wholesale Goods"
        }
    ],
    "sg:phone":"+1 604 439 2660",
    "sg:postcode":"V5M 1Z5",
    "sg:province":"BC",
    "sg:tags":[
        "newspaper"
    ],
    "wof:name":"Vancouver Courier Newspaper",
    "wof:placetype":"venue"
},
  "geometry": {"coordinates":[-123.032173,49.258274],"type":"Point"}
}