{
  "type": "Feature",
  "properties": {
    "iso:country":"CA",
    "sg:address":"493 Kensington St",
    "sg:city":"Winnipeg",
    "sg:classifiers":[
        {
            "category":"Building & Trades",
            "subcategory":"Construction",
            "type":"Services"
        }
    ],
    "sg:phone":"+1 204 772 0408",
    "sg:postcode":"R3J 1J8",
    "sg:province":"MB",
    "sg:tags":[
        "contractor",
        "general"
    ],
    "wof:name":"Sundek Construction & Dev",
    "wof:placetype":"venue"
},
  "geometry": {"coordinates":[-97.20458984379999,49.8900108337],"type":"Point"}
}