{
  "type": "Feature",
  "properties": {
    "addr:full":"5500 Rose Cherry Pl Mississauga ON L4Z 4B6",
    "addr:housenumber":"5500",
    "addr:postcode":"l4z 4b6",
    "addr:street":"Rose Cherry Pl",
    "iso:country":"CA",
    "sg:address":"5500 Rose Cherry Pl",
    "sg:city":"Mississauga",
    "sg:classifiers":[
        {
            "category":"Government",
            "subcategory":"Office",
            "type":"Public Place"
        }
    ],
    "sg:phone":"+1 905 502 9100",
    "sg:postcode":"L4Z 4B6",
    "sg:province":"ON",
    "sg:tags":[
        "village"
    ],
    "wof:name":"Mississauga Hershey Ctr",
    "wof:placetype":"venue"
},
  "geometry": {"coordinates":[-79.651779,43.629372],"type":"Point"}
}