{
  "type": "Feature",
  "properties": {
    "iso:country":"CA",
    "sg:address":"541 Huron St",
    "sg:city":"Toronto",
    "sg:classifiers":[
        {
            "category":"Social Services",
            "subcategory":"Child Care",
            "type":"Services"
        }
    ],
    "sg:phone":"+1 416 921 7551",
    "sg:postcode":"M5R 2R6",
    "sg:province":"ON",
    "wof:name":"Huron Superfriends Inc",
    "wof:placetype":"venue"
},
  "geometry": {"coordinates":[-79.4028091431,43.671043396],"type":"Point"}
}