{
  "type": "Feature",
  "properties": {
    "addr:full":"1555 Boul Jean-Paul-Vincent Longueuil QC J4N 1L6",
    "addr:housenumber":"1555",
    "addr:postcode":"j4n 1l6",
    "addr:street":"Boul Jean-Paul-Vincent",
    "iso:country":"CA",
    "sg:address":"1555 Boul Jean-Paul-Vincent",
    "sg:city":"Longueuil",
    "sg:classifiers":[
        {
            "category":"Social Services",
            "subcategory":"Child Care",
            "type":"Services"
        }
    ],
    "sg:phone":"+1 450 448 2653",
    "sg:postcode":"J4N 1L6",
    "sg:province":"QC",
    "wof:name":"Parcours Du Faon",
    "wof:placetype":"venue"
},
  "geometry": {"coordinates":[-73.46509552000001,45.5541877747],"type":"Point"}
}