{
  "type": "Feature",
  "properties": {
    "iso:country":"CA",
    "sg:address":"488 Rue Cartier",
    "sg:city":"Montebello",
    "sg:classifiers":[
        {
            "category":"Real Estate",
            "subcategory":"Surveying",
            "type":"Services"
        }
    ],
    "sg:phone":"+1 819 423 5723",
    "sg:postcode":"J0V 1L0",
    "sg:province":"QC",
    "sg:tags":[
        "surveyor"
    ],
    "wof:name":"Gauthier, Francois",
    "wof:placetype":"venue"
},
  "geometry": {"coordinates":[-74.94384002690001,45.6517448425],"type":"Point"}
}