{
  "type": "Feature",
  "properties": {
    "addr:full":"707 South Railway St Shoal Lake MB R0J 1Z0",
    "addr:housenumber":"707",
    "addr:postcode":"r0j 1z0",
    "addr:street":"South Railway St",
    "iso:country":"CA",
    "sg:address":"707 South Railway St",
    "sg:city":"Shoal Lake",
    "sg:classifiers":[
        {
            "category":"Manufacturing",
            "subcategory":"Tools & Machinery",
            "type":"Manufacturing & Wholesale Goods"
        }
    ],
    "sg:phone":"+1 204 759 2547",
    "sg:postcode":"R0J 1Z0",
    "sg:province":"MB",
    "sg:tags":[
        "machine",
        "shop"
    ],
    "wof:name":"Allen's Machine Works",
    "wof:placetype":"venue"
},
  "geometry": {"coordinates":[-100.59072113000001,50.436920166],"type":"Point"}
}