{
  "type": "Feature",
  "properties": {
    "addr:full":"389 Jane St Toronto ON M6S 3Z3",
    "addr:housenumber":"389",
    "addr:postcode":"m6s 3z3",
    "addr:street":"Jane St",
    "iso:country":"CA",
    "sg:address":"389 Jane St",
    "sg:city":"Toronto",
    "sg:classifiers":[
        {
            "category":"Retail",
            "subcategory":"Laundry & Dry Cleaning",
            "type":"Services"
        }
    ],
    "sg:phone":"+1 416 762 9386",
    "sg:postcode":"M6S 3Z3",
    "sg:province":"ON",
    "sg:tags":[
        "cleaners"
    ],
    "wof:name":"Quality Cleaners",
    "wof:placetype":"venue"
},
  "geometry": {"coordinates":[-79.487854,43.658043],"type":"Point"}
}