{
  "type": "Feature",
  "properties": {
    "addr:full":"10 Hodder Dr Pasadena NL A0L 1K0",
    "addr:housenumber":"10",
    "addr:postcode":"a0l 1k0",
    "addr:street":"Hodder Dr",
    "iso:country":"CA",
    "sg:address":"10 Hodder Dr",
    "sg:city":"Pasadena",
    "sg:classifiers":[
        {
            "category":"Organizations",
            "subcategory":"Membership Organization",
            "type":"Services"
        }
    ],
    "sg:phone":"+1 709 686 5868",
    "sg:postcode":"A0L 1K0",
    "sg:province":"NL",
    "wof:name":"Lions Club",
    "wof:placetype":"venue"
},
  "geometry": {"coordinates":[-57.5980377197,49.0142478943],"type":"Point"}
}