{
  "type": "Feature",
  "properties": {
    "addr:full":"3507 Wilmot Cres Oakville ON L6L 6E2",
    "addr:housenumber":"3507",
    "addr:postcode":"l6l 6e2",
    "addr:street":"Wilmot Cres",
    "iso:country":"CA",
    "sg:address":"3507 Wilmot Cres",
    "sg:city":"Oakville",
    "sg:classifiers":[
        {
            "category":"Building & Trades",
            "subcategory":"Cleaning & Sanitation",
            "type":"Services"
        }
    ],
    "sg:phone":"+1 905 847 5237",
    "sg:postcode":"L6L 6E2",
    "sg:province":"ON",
    "sg:tags":[
        "window"
    ],
    "wof:name":"Aasta Window Cleaning",
    "wof:placetype":"venue"
},
  "geometry": {"coordinates":[-79.72704315190001,43.3765029907],"type":"Point"}
}