{
  "type": "Feature",
  "properties": {
    "addr:full":"103 Warner Dr Long Sault ON K0C 1P0",
    "addr:housenumber":"103",
    "addr:postcode":"k0c 1p0",
    "addr:street":"Warner Dr",
    "iso:country":"CA",
    "sg:address":"103 Warner Dr",
    "sg:city":"Long Sault",
    "sg:classifiers":[
        {
            "category":"Building & Trades",
            "subcategory":"Plumbing",
            "type":"Services"
        }
    ],
    "sg:phone":"+1 613 936 0518",
    "sg:postcode":"K0C 1P0",
    "sg:province":"ON",
    "sg:tags":[
        "ventilating",
        "contractor"
    ],
    "wof:name":"Legalett Canada Inc",
    "wof:placetype":"venue"
},
  "geometry": {"coordinates":[-74.898315,45.029984],"type":"Point"}
}