{
  "type": "Feature",
  "properties": {
    "iso:country":"CA",
    "sg:city":"Repentigny",
    "sg:classifiers":[
        {
            "category":"Wholesale",
            "subcategory":"Apparel",
            "type":"Manufacturing & Wholesale Goods"
        }
    ],
    "sg:phone":"+1 450 585 4898",
    "sg:postcode":"J6A 3Z3",
    "sg:province":"QC",
    "sg:tags":[
        "advertising"
    ],
    "wof:name":"Promotions 13-15",
    "wof:placetype":"venue"
},
  "geometry": {"coordinates":[-73.461678,45.731567],"type":"Point"}
}