{
  "type": "Feature",
  "properties": {
    "addr:full":"Palmerston ON N0G 2P0",
    "addr:postcode":"n0g 2p0",
    "iso:country":"CA",
    "sg:city":"Palmerston",
    "sg:classifiers":[
        {
            "category":"Professional",
            "subcategory":"Accounting & Tax Preparation",
            "type":"Services"
        }
    ],
    "sg:phone":"+1 519 343 3052",
    "sg:postcode":"N0G 2P0",
    "sg:province":"ON",
    "sg:tags":[
        "bookkeeping",
        "general"
    ],
    "wof:name":"Craig Financial",
    "wof:placetype":"venue"
},
  "geometry": {"coordinates":[-80.85095200000001,43.834137],"type":"Point"}
}