{
  "type": "Feature",
  "properties": {
    "addr:full":"1237 Guildford Town Ctr Surrey BC V3R 7B7",
    "addr:housenumber":"1237",
    "addr:postcode":"v3r 7b7",
    "addr:street":"Guildford Town Ctr",
    "iso:country":"CA",
    "sg:address":"1237 Guildford Town Ctr",
    "sg:city":"Surrey",
    "sg:classifiers":[
        {
            "category":"Autos & Motor Vehicles",
            "subcategory":"Auto Supplies",
            "type":"Retail Goods"
        }
    ],
    "sg:phone":"+1 604 581 1116",
    "sg:postcode":"V3R 7B7",
    "sg:province":"BC",
    "sg:tags":[
        "automobile",
        "parts"
    ],
    "wof:name":"Overdrive Auto Accessories",
    "wof:placetype":"venue"
},
  "geometry": {"coordinates":[-122.80175,49.188522],"type":"Point"}
}