{
  "type": "Feature",
  "properties": {
    "iso:country":"CA",
    "sg:address":"7250 Rue Marconi",
    "sg:city":"Montreal",
    "sg:classifiers":[
        {
            "category":"Manufacturing",
            "subcategory":"Textiles",
            "type":"Manufacturing & Wholesale Goods"
        }
    ],
    "sg:phone":"+1 514 495 1531",
    "sg:postcode":"H2R 2Z5",
    "sg:province":"QC",
    "sg:tags":[
        "knitted",
        "fabric"
    ],
    "wof:name":"Calko Canada Inc",
    "wof:placetype":"venue"
},
  "geometry": {"coordinates":[-73.621956,45.532261],"type":"Point"}
}