{
  "type": "Feature",
  "properties": {
    "addr:full":"165 Rue Le Moyne O Longueuil QC J4H 1V7",
    "addr:housenumber":"165",
    "addr:postcode":"j4h 1v7",
    "addr:street":"Rue Le Moyne O",
    "iso:country":"CA",
    "sg:address":"165 Rue Le Moyne O",
    "sg:city":"Longueuil",
    "sg:classifiers":[
        {
            "category":"Food & Beverages",
            "subcategory":"Groceries & Convenience Stores",
            "type":"Retail Goods"
        }
    ],
    "sg:phone":"+1 450 651 6928",
    "sg:postcode":"J4H 1V7",
    "sg:province":"QC",
    "sg:tags":[
        "grocer"
    ],
    "wof:name":"Depanneur Comeau Enr",
    "wof:placetype":"venue"
},
  "geometry": {"coordinates":[-73.4982681274,45.5381240845],"type":"Point"}
}