{
  "type": "Feature",
  "properties": {
    "addr:full":"11925 Boul Lacroix Saint-Georges QC G5Y 1L6",
    "addr:housenumber":"11925",
    "addr:postcode":"g5y 1l6",
    "addr:street":"Boul Lacroix",
    "iso:country":"CA",
    "sg:address":"11925 Boul Lacroix",
    "sg:city":"Saint-Georges",
    "sg:classifiers":[
        {
            "category":"Manufacturing",
            "subcategory":"Printing",
            "type":"Manufacturing & Wholesale Goods"
        }
    ],
    "sg:phone":"+1 418 228 4011",
    "sg:postcode":"G5Y 1L6",
    "sg:province":"QC",
    "sg:tags":[
        "printer"
    ],
    "wof:name":"Imprimerie Moderne DE Beauce",
    "wof:placetype":"venue"
},
  "geometry": {"coordinates":[-70.66950199999999,46.122459],"type":"Point"}
}