{
  "type": "Feature",
  "properties": {
    "addr:full":"Calgary AB T2P 0J9",
    "addr:postcode":"t2p 0j9",
    "iso:country":"CA",
    "sg:city":"Calgary",
    "sg:classifiers":[
        {
            "category":"Professional",
            "subcategory":"Accounting & Tax Preparation",
            "type":"Services"
        }
    ],
    "sg:phone":"+1 403 218 3913",
    "sg:postcode":"T2P 0J9",
    "sg:province":"AB",
    "sg:tags":[
        "accountant"
    ],
    "wof:name":"Ronald P Yager Corp",
    "wof:placetype":"venue"
},
  "geometry": {"coordinates":[-114.074394226,51.0497627258],"type":"Point"}
}