{
  "type": "Feature",
  "properties": {
    "iso:country":"CA",
    "sg:address":"4115 Boul DE LA Rive-Sud",
    "sg:city":"Levis",
    "sg:classifiers":[
        {
            "category":"Travel",
            "subcategory":"Hotels & Motels",
            "type":"Entertainment"
        }
    ],
    "sg:phone":"+1 418 837 9777",
    "sg:postcode":"G6W 6M9",
    "sg:province":"QC",
    "wof:name":"Auberge Moka-Creme",
    "wof:placetype":"venue"
},
  "geometry": {"coordinates":[-71.195557,46.776981],"type":"Point"}
}