{
  "type": "Feature",
  "properties": {
    "addr:full":"12 Columbia Ave W Devon AB T9G 1Y6",
    "addr:housenumber":"12",
    "addr:postcode":"t9g 1y6",
    "addr:street":"Columbia Ave W",
    "iso:country":"CA",
    "sg:address":"12 Columbia Ave W",
    "sg:city":"Devon",
    "sg:classifiers":[
        {
            "category":"Manufacturing",
            "subcategory":"Signs",
            "type":"Manufacturing & Wholesale Goods"
        }
    ],
    "sg:phone":"+1 780 987 2999",
    "sg:postcode":"T9G 1Y6",
    "sg:province":"AB",
    "wof:name":"Navajo Printing & Copy Shop",
    "wof:placetype":"venue"
},
  "geometry": {"coordinates":[-113.731163,53.363792],"type":"Point"}
}