{
  "type": "Feature",
  "properties": {
    "addr:full":"Calgary AB T2W 4J3",
    "addr:postcode":"t2w 4j3",
    "iso:country":"CA",
    "sg:city":"Calgary",
    "sg:classifiers":[
        {
            "category":"Banks & Credit Unions",
            "subcategory":"Investment Brokerage",
            "type":"Services"
        }
    ],
    "sg:phone":"+1 403 257 6088",
    "sg:postcode":"T2W 4J3",
    "sg:province":"AB",
    "wof:name":"Edward Jones",
    "wof:placetype":"venue"
},
  "geometry": {"coordinates":[-114.109207,50.940907],"type":"Point"}
}