{
  "type": "Feature",
  "properties": {
    "addr:full":"286 Rue Principale Saint-Antonin QC G0L 2J0",
    "addr:housenumber":"286",
    "addr:postcode":"g0l 2j0",
    "addr:street":"Rue Principale",
    "iso:country":"CA",
    "sg:address":"286 Rue Principale",
    "sg:city":"Saint-Antonin",
    "sg:classifiers":[
        {
            "category":"Health Services",
            "subcategory":"Hospital",
            "type":"Services"
        }
    ],
    "sg:phone":"+1 418 862 7993",
    "sg:postcode":"G0L 2J0",
    "sg:province":"QC",
    "wof:name":"Foyer DE St-Antonin Inc",
    "wof:placetype":"venue"
},
  "geometry": {"coordinates":[-69.47853851319999,47.7621841431],"type":"Point"}
}