{
  "type": "Feature",
  "properties": {
    "addr:full":"1640 Midland Ave Scarborough ON M1P 3C2",
    "addr:housenumber":"1640",
    "addr:postcode":"m1p 3c2",
    "addr:street":"Midland Ave",
    "iso:country":"CA",
    "sg:address":"1640 Midland Ave",
    "sg:city":"Scarborough",
    "sg:classifiers":[
        {
            "category":"Wholesale",
            "subcategory":"Auto Parts",
            "type":"Manufacturing & Wholesale Goods"
        }
    ],
    "sg:phone":"+1 416 751 4604",
    "sg:postcode":"M1P 3C2",
    "sg:province":"ON",
    "sg:tags":[
        "automobile",
        "wrecking"
    ],
    "wof:name":"City Japanese Used Auto Parts",
    "wof:placetype":"venue"
},
  "geometry": {"coordinates":[-79.26741800000001,43.757404],"type":"Point"}
}