{
  "type": "Feature",
  "properties": {
    "addr:full":"3323 Dunbar St Vancouver BC V6S 2B9",
    "addr:housenumber":"3323",
    "addr:postcode":"v6s 2b9",
    "addr:street":"Dunbar St",
    "iso:country":"CA",
    "sg:address":"3323 Dunbar St",
    "sg:city":"Vancouver",
    "sg:classifiers":[
        {
            "category":"Professional",
            "subcategory":"Business Services",
            "type":"Services"
        }
    ],
    "sg:phone":"+1 604 222 8282",
    "sg:postcode":"V6S 2B9",
    "sg:province":"BC",
    "sg:tags":[
        "translator",
        "interpreter"
    ],
    "wof:name":"Jebsen Imaging",
    "wof:placetype":"venue"
},
  "geometry": {"coordinates":[-123.185303,49.257141],"type":"Point"}
}