{
  "type": "Feature",
  "properties": {
    "iso:country":"CA",
    "sg:address":"885 Broadway W",
    "sg:city":"Vancouver",
    "sg:classifiers":[
        {
            "category":"Shopping",
            "subcategory":"Pharmacy",
            "type":"Retail Goods"
        }
    ],
    "sg:phone":"+1 604 708 1135",
    "sg:postcode":"V5Z 1J9",
    "sg:province":"BC",
    "wof:name":"Shoppers Drug Mart",
    "wof:placetype":"venue"
},
  "geometry": {"coordinates":[-123.12368774399999,49.263507843],"type":"Point"}
}