{
  "type": "Feature",
  "properties": {
    "addr:full":"63 Columbus Ave Timmins ON P4N 3H2",
    "addr:housenumber":"63",
    "addr:postcode":"p4n 3h2",
    "addr:street":"Columbus Ave",
    "iso:country":"CA",
    "sg:address":"63 Columbus Ave",
    "sg:city":"Timmins",
    "sg:classifiers":[
        {
            "category":"Building & Trades",
            "subcategory":"Landscaping Services",
            "type":"Services"
        }
    ],
    "sg:phone":"+1 705 264 7691",
    "sg:postcode":"P4N 3H2",
    "sg:province":"ON",
    "sg:tags":[
        "landscape",
        "contractor"
    ],
    "wof:name":"Tbr Lockstone",
    "wof:placetype":"venue"
},
  "geometry": {"coordinates":[-81.3368,48.468033],"type":"Point"}
}