{
  "type": "Feature",
  "properties": {
    "addr:full":"9808 100 Ave High Level AB T0H 1Z0",
    "addr:housenumber":"9808",
    "addr:postcode":"t0h 1z0",
    "addr:street":"100 Ave",
    "iso:country":"CA",
    "sg:address":"9808 100 Ave",
    "sg:city":"High Level",
    "sg:classifiers":[
        {
            "category":"Professional",
            "subcategory":"Lawyer & Legal Services",
            "type":"Services"
        }
    ],
    "sg:phone":"+1 780 926 3373",
    "sg:postcode":"T0H 1Z0",
    "sg:province":"AB",
    "sg:tags":[
        "attorney"
    ],
    "wof:name":"Mathieu Hryniuk",
    "wof:placetype":"venue"
},
  "geometry": {"coordinates":[-117.128768921,58.5174636841],"type":"Point"}
}