{
  "type": "Feature",
  "properties": {
    "addr:full":"434 Lakehill Rd Kaleden BC V0H 1K0",
    "addr:housenumber":"434",
    "addr:postcode":"v0h 1k0",
    "addr:street":"Lakehill Rd",
    "iso:country":"CA",
    "sg:address":"434 Lakehill Rd",
    "sg:city":"Kaleden",
    "sg:classifiers":[
        {
            "category":"Organizations",
            "subcategory":"Religious Organization",
            "type":"Services"
        }
    ],
    "sg:phone":"+1 250 497 5995",
    "sg:postcode":"V0H 1K0",
    "sg:province":"BC",
    "sg:tags":[
        "church"
    ],
    "wof:name":"Kaleden Community Baptist Chr",
    "wof:placetype":"venue"
},
  "geometry": {"coordinates":[-119.58996582,49.3881378174],"type":"Point"}
}