{
  "type": "Feature",
  "properties": {
    "addr:full":"2844 Mcgee Side Rd Carp ON K0A 1L0",
    "addr:housenumber":"2844",
    "addr:postcode":"k0a 1l0",
    "addr:street":"Mcgee Side Rd",
    "iso:country":"CA",
    "sg:address":"2844 Mcgee Side Rd",
    "sg:city":"Carp",
    "sg:classifiers":[
        {
            "category":"Retail",
            "subcategory":"Repair Shop",
            "type":"Services"
        }
    ],
    "sg:phone":"+1 613 831 2551",
    "sg:postcode":"K0A 1L0",
    "sg:province":"ON",
    "sg:tags":[
        "welding",
        "contractor"
    ],
    "wof:name":"G Whiteman Ent Ltd",
    "wof:placetype":"venue"
},
  "geometry": {"coordinates":[-76.0330047607,45.2911071777],"type":"Point"}
}