{
  "type": "Feature",
  "properties": {
    "addr:full":"North York ON M2K 2Z3",
    "addr:postcode":"m2k 2z3",
    "iso:country":"CA",
    "sg:city":"North York",
    "sg:classifiers":[
        {
            "category":"Health Services",
            "subcategory":"Doctor",
            "type":"Services"
        }
    ],
    "sg:phone":"+1 416 221 0176",
    "sg:postcode":"M2K 2Z3",
    "sg:province":"ON",
    "sg:tags":[
        "physician",
        "surgeon"
    ],
    "wof:name":"Devi, Shashi MD",
    "wof:placetype":"venue"
},
  "geometry": {"coordinates":[-79.3793182373,43.7684898376],"type":"Point"}
}