{
  "type": "Feature",
  "properties": {
    "addr:full":"5370 Hwy 3 Chester Basin NS B0J 1K0",
    "addr:housenumber":"5370",
    "addr:postcode":"b0j 1k0",
    "addr:street":"Hwy 3",
    "iso:country":"CA",
    "sg:address":"5370 Hwy 3",
    "sg:city":"Chester Basin",
    "sg:classifiers":[
        {
            "category":"Health Services",
            "subcategory":"Doctor",
            "type":"Services"
        }
    ],
    "sg:phone":"+1 902 275 5666",
    "sg:postcode":"B0J 1K0",
    "sg:province":"NS",
    "sg:tags":[
        "physician",
        "surgeon"
    ],
    "wof:name":"Chester Basin Medical Clinic",
    "wof:placetype":"venue"
},
  "geometry": {"coordinates":[-64.30796813960001,44.565536499],"type":"Point"}
}