{
  "type": "Feature",
  "properties": {
    "addr:full":"119 Herkimer St Hamilton ON L8P 2G8",
    "addr:housenumber":"119",
    "addr:postcode":"l8p 2g8",
    "addr:street":"Herkimer St",
    "iso:country":"CA",
    "sg:address":"119 Herkimer St",
    "sg:city":"Hamilton",
    "sg:classifiers":[
        {
            "category":"Food & Beverages",
            "subcategory":"Groceries & Convenience Stores",
            "type":"Retail Goods"
        }
    ],
    "sg:phone":"+1 905 523 7070",
    "sg:postcode":"L8P 2G8",
    "sg:province":"ON",
    "wof:name":"Mac's Convenience Stores Ltd",
    "wof:placetype":"venue"
},
  "geometry": {"coordinates":[-79.878952,43.25021],"type":"Point"}
}