{
  "type": "Feature",
  "properties": {
    "addr:full":"7 Mandeville Dr Yellowknife NT X1A 3N2",
    "addr:housenumber":"7",
    "addr:postcode":"x1a 3n2",
    "addr:street":"Mandeville Dr",
    "iso:country":"CA",
    "sg:address":"7 Mandeville Dr",
    "sg:city":"Yellowknife",
    "sg:classifiers":[
        {
            "category":"Manufacturing",
            "subcategory":"Metals",
            "type":"Manufacturing & Wholesale Goods"
        }
    ],
    "sg:phone":"+1 867 873 2522",
    "sg:postcode":"X1A 3N2",
    "sg:province":"NT",
    "sg:tags":[
        "welding"
    ],
    "wof:name":"Paul Brothers Welding Ltd",
    "wof:placetype":"venue"
},
  "geometry": {"coordinates":[-114.426788,62.440456],"type":"Point"}
}