{
  "type": "Feature",
  "properties": {
    "iso:country":"CA",
    "sg:address":"953 Boul Du Seminaire N",
    "sg:city":"Saint-Jean-Sur-Richelieu",
    "sg:classifiers":[
        {
            "category":"Shopping",
            "type":"Retail Goods"
        }
    ],
    "sg:phone":"+1 450 349 5558",
    "sg:postcode":"J3A 1K1",
    "sg:province":"QC",
    "sg:tags":[
        "pet",
        "food",
        "supply"
    ],
    "wof:name":"J E Mondou Ltee",
    "wof:placetype":"venue"
},
  "geometry": {"coordinates":[-73.2675933838,45.3340301514],"type":"Point"}
}