{
  "type": "Feature",
  "properties": {
    "iso:country":"CA",
    "sg:city":"Abbotsford",
    "sg:classifiers":[
        {
            "category":"Food & Beverages",
            "subcategory":"Meat & Fish",
            "type":"Retail Goods"
        }
    ],
    "sg:phone":"+1 604 859 9011",
    "sg:postcode":"V2S 2E6",
    "sg:province":"BC",
    "sg:tags":[
        "delicatessen"
    ],
    "wof:name":"Karl's Dutch Meat Market",
    "wof:placetype":"venue"
},
  "geometry": {"coordinates":[-122.289154,49.049477],"type":"Point"}
}