{
  "type": "Feature",
  "properties": {
    "iso:country":"CA",
    "sg:city":"Edmonton",
    "sg:classifiers":[
        {
            "category":"Organizations",
            "subcategory":"Non-profit Organization",
            "type":"Services"
        }
    ],
    "sg:phone":"+1 780 423 2634",
    "sg:postcode":"T5J 1W8",
    "sg:province":"AB",
    "sg:tags":[
        "charitable",
        "institution"
    ],
    "wof:name":"Alberta Monitoring For Health",
    "wof:placetype":"venue"
},
  "geometry": {"coordinates":[-113.49417099999999,53.540741],"type":"Point"}
}