{
  "type": "Feature",
  "properties": {
    "addr:full":"32430 Diamond Ave Mission BC V2V 1M2",
    "addr:housenumber":"32430",
    "addr:postcode":"v2v 1m2",
    "addr:street":"Diamond Ave",
    "iso:country":"CA",
    "sg:address":"32430 Diamond Ave",
    "sg:city":"Mission",
    "sg:classifiers":[
        {
            "category":"Building & Trades",
            "subcategory":"Construction",
            "type":"Services"
        }
    ],
    "sg:phone":"+1 604 826 3388",
    "sg:postcode":"V2V 1M2",
    "sg:province":"BC",
    "sg:tags":[
        "restoration",
        "cleaning",
        "patio",
        "deck"
    ],
    "wof:name":"Custom Power Wash",
    "wof:placetype":"venue"
},
  "geometry": {"coordinates":[-122.32711792000001,49.1367988586],"type":"Point"}
}