{
  "type": "Feature",
  "properties": {
    "iso:country":"CA",
    "sg:address":"5353 Ninth Line",
    "sg:city":"Mississauga",
    "sg:classifiers":[
        {
            "category":"Building & Trades",
            "subcategory":"Construction",
            "type":"Services"
        }
    ],
    "sg:phone":"+1 905 858 9678",
    "sg:postcode":"L5M 5X5",
    "sg:province":"ON",
    "sg:tags":[
        "designer",
        "dealer",
        "pool",
        "swimming"
    ],
    "wof:name":"Paramount Pool & Spa",
    "wof:placetype":"venue"
},
  "geometry": {"coordinates":[-79.74504089360001,43.5439682007],"type":"Point"}
}