{
  "type": "Feature",
  "properties": {
    "addr:full":"Gatineau QC J8T 3H7",
    "addr:postcode":"j8t 3h7",
    "iso:country":"CA",
    "sg:city":"Gatineau",
    "sg:classifiers":[
        {
            "category":"Education",
            "subcategory":"School",
            "type":"Public Place"
        }
    ],
    "sg:phone":"+1 819 561 9395",
    "sg:postcode":"J8T 3H7",
    "sg:province":"QC",
    "wof:name":"Centre Nouvel-Horizon",
    "wof:placetype":"venue"
},
  "geometry": {"coordinates":[-75.712341,45.428631],"type":"Point"}
}