{
  "type": "Feature",
  "properties": {
    "iso:country":"CA",
    "sg:address":"9429 47 St NW",
    "sg:city":"Edmonton",
    "sg:classifiers":[
        {
            "category":"Building & Trades",
            "subcategory":"Electrical",
            "type":"Services"
        }
    ],
    "sg:phone":"+1 780 466 7536",
    "sg:postcode":"T6B 2R7",
    "sg:province":"AB",
    "sg:tags":[
        "electric",
        "contractor"
    ],
    "wof:name":"Future Electrical Contractors",
    "wof:placetype":"venue"
},
  "geometry": {"coordinates":[-113.407784,53.531425],"type":"Point"}
}