{
  "type": "Feature",
  "properties": {
    "addr:full":"3855 Rue Sainte-Catherine E Montreal QC H1W 2G3",
    "addr:housenumber":"3855",
    "addr:postcode":"h1w 2g3",
    "addr:street":"Rue Sainte-Catherine E",
    "iso:country":"CA",
    "sg:address":"3855 Rue Sainte-Catherine E",
    "sg:city":"Montreal",
    "sg:classifiers":[
        {
            "category":"Restaurant",
            "type":"Food & Drink"
        }
    ],
    "sg:phone":"+1 514 526 6606",
    "sg:postcode":"H1W 2G3",
    "sg:province":"QC",
    "wof:name":"Vincent Sous-Marine",
    "wof:placetype":"venue"
},
  "geometry": {"coordinates":[-73.53718600000001,45.545906],"type":"Point"}
}