{
  "type": "Feature",
  "properties": {
    "addr:full":"26 Home Ave Vankleek Hill ON K0B 1R0",
    "addr:housenumber":"26",
    "addr:postcode":"k0b 1r0",
    "addr:street":"Home Ave",
    "iso:country":"CA",
    "sg:address":"26 Home Ave",
    "sg:city":"Vankleek Hill",
    "sg:classifiers":[
        {
            "category":"Wholesale",
            "subcategory":"Farm Supplies",
            "type":"Manufacturing & Wholesale Goods"
        }
    ],
    "sg:phone":"+1 613 678 5800",
    "sg:postcode":"K0B 1R0",
    "sg:province":"ON",
    "wof:name":"Vankleek Hill Country Depot",
    "wof:placetype":"venue"
},
  "geometry": {"coordinates":[-74.64959,45.52],"type":"Point"}
}