{
  "type": "Feature",
  "properties": {
    "addr:full":"222 Front St Quesnel BC V2J 2K2",
    "addr:housenumber":"222",
    "addr:postcode":"v2j 2k2",
    "addr:street":"Front St",
    "iso:country":"CA",
    "sg:address":"222 Front St",
    "sg:city":"Quesnel",
    "sg:classifiers":[
        {
            "category":"Shopping",
            "subcategory":"Used Merchandise",
            "type":"Retail Goods"
        }
    ],
    "sg:phone":"+1 250 992 3980",
    "sg:postcode":"V2J 2K2",
    "sg:province":"BC",
    "sg:tags":[
        "second",
        "store",
        "hand"
    ],
    "wof:name":"Bill's Second Hand Store",
    "wof:placetype":"venue"
},
  "geometry": {"coordinates":[-122.497726,52.976028],"type":"Point"}
}