{
  "type": "Feature",
  "properties": {
    "iso:country":"CA",
    "sg:address":"246 Ottawa St N",
    "sg:city":"Hamilton",
    "sg:classifiers":[
        {
            "category":"Retail",
            "subcategory":"Laundry & Dry Cleaning",
            "type":"Services"
        }
    ],
    "sg:phone":"+1 905 545 7788",
    "sg:postcode":"L8H 3Z7",
    "sg:province":"ON",
    "sg:tags":[
        "cleaners"
    ],
    "wof:name":"Zorro One Hour Dry Cleaners",
    "wof:placetype":"venue"
},
  "geometry": {"coordinates":[-79.8168792725,43.2491722107],"type":"Point"}
}