{
  "type": "Feature",
  "properties": {
    "addr:full":"Montreal QC H4A 1Y1",
    "addr:postcode":"h4a 1y1",
    "iso:country":"CA",
    "sg:city":"Montreal",
    "sg:classifiers":[
        {
            "category":"Professional",
            "subcategory":"Accounting & Tax Preparation",
            "type":"Services"
        }
    ],
    "sg:phone":"+1 514 488 8017",
    "sg:postcode":"H4A 1Y1",
    "sg:province":"QC",
    "sg:tags":[
        "return",
        "filing"
    ],
    "wof:name":"Impot Total",
    "wof:placetype":"venue"
},
  "geometry": {"coordinates":[-73.620087,45.46822],"type":"Point"}
}