{
  "type": "Feature",
  "properties": {
    "iso:country":"CA",
    "sg:address":"802 Sawmill Rd",
    "sg:city":"Bloomingdale",
    "sg:classifiers":[
        {
            "category":"Retail",
            "subcategory":"Auto Repair",
            "type":"Services"
        }
    ],
    "sg:phone":"+1 519 742 2051",
    "sg:postcode":"N0B 1K0",
    "sg:province":"ON",
    "sg:tags":[
        "automobile",
        "rustproofing",
        "undercoating"
    ],
    "wof:name":"Bloomingdale Oil Undercoaters",
    "wof:placetype":"venue"
},
  "geometry": {"coordinates":[-80.4613876343,43.5071029663],"type":"Point"}
}