{
  "type": "Feature",
  "properties": {
    "addr:full":"Etobicoke ON M8Y 4G5",
    "addr:postcode":"m8y 4g5",
    "iso:country":"CA",
    "sg:city":"Etobicoke",
    "sg:classifiers":[
        {
            "category":"Professional",
            "subcategory":"Engineering",
            "type":"Services"
        }
    ],
    "sg:phone":"+1 416 253 8099",
    "sg:postcode":"M8Y 4G5",
    "sg:province":"ON",
    "sg:tags":[
        "engineer"
    ],
    "wof:name":"Cathro Engineering Ltd",
    "wof:placetype":"venue"
},
  "geometry": {"coordinates":[-79.50310500000001,43.627731],"type":"Point"}
}