{
  "type": "Feature",
  "properties": {
    "addr:full":"98 South Shore Rd Lake Cowichan BC V0R 2G0",
    "addr:housenumber":"98",
    "addr:postcode":"v0r 2g0",
    "addr:street":"South Shore Rd",
    "iso:country":"CA",
    "sg:address":"98 South Shore Rd",
    "sg:city":"Lake Cowichan",
    "sg:classifiers":[
        {
            "category":"Cinema",
            "subcategory":"Movie Rental",
            "type":"Entertainment"
        }
    ],
    "sg:phone":"+1 250 749 3219",
    "sg:postcode":"V0R 2G0",
    "sg:province":"BC",
    "sg:tags":[
        "radio",
        "television",
        "video",
        "leasing",
        "tape"
    ],
    "wof:name":"Mc Quinn's Custom Sound Ltd",
    "wof:placetype":"venue"
},
  "geometry": {"coordinates":[-124.0578,48.823948],"type":"Point"}
}