{
  "type": "Feature",
  "properties": {
    "addr:full":"Belleville ON K8P 1B6",
    "addr:postcode":"k8p 1b6",
    "iso:country":"CA",
    "sg:city":"Belleville",
    "sg:classifiers":[
        {
            "category":"Restaurant",
            "type":"Food & Drink"
        }
    ],
    "sg:phone":"+1 613 962 1180",
    "sg:postcode":"K8P 1B6",
    "sg:province":"ON",
    "wof:name":"Maggie's Country Korner",
    "wof:placetype":"venue"
},
  "geometry": {"coordinates":[-77.41352081300001,44.1452789307],"type":"Point"}
}