{
  "type": "Feature",
  "properties": {
    "addr:full":"23616 River Rd Maple Ridge BC V2W 1B7",
    "addr:housenumber":"23616",
    "addr:postcode":"v2w 1b7",
    "addr:street":"River Rd",
    "iso:country":"CA",
    "sg:address":"23616 River Rd",
    "sg:city":"Maple Ridge",
    "sg:classifiers":[
        {
            "category":"Home & Garden",
            "subcategory":"Building Materials",
            "type":"Retail Goods"
        }
    ],
    "sg:phone":"+1 604 467 3441",
    "sg:postcode":"V2W 1B7",
    "sg:province":"BC",
    "sg:tags":[
        "mixed",
        "concrete"
    ],
    "wof:name":"Lafarge Canada Inc",
    "wof:placetype":"venue"
},
  "geometry": {"coordinates":[-122.566895,49.18668],"type":"Point"}
}