{
  "type": "Feature",
  "properties": {
    "addr:full":"802 Pitt St Cornwall ON K6J 3S2",
    "addr:housenumber":"802",
    "addr:postcode":"k6j 3s2",
    "addr:street":"Pitt St",
    "iso:country":"CA",
    "sg:address":"802 Pitt St",
    "sg:city":"Cornwall",
    "sg:classifiers":[
        {
            "category":"Shopping",
            "type":"Retail Goods"
        }
    ],
    "sg:phone":"+1 613 932 6599",
    "sg:postcode":"K6J 3S2",
    "sg:province":"ON",
    "sg:tags":[
        "monument"
    ],
    "wof:name":"Kingston Monuments Ltd",
    "wof:placetype":"venue"
},
  "geometry": {"coordinates":[-74.7340927124,45.0273590088],"type":"Point"}
}