{
  "type": "Feature",
  "properties": {
    "addr:full":"Hearst ON P0L 1N0",
    "addr:postcode":"p0l 1n0",
    "iso:country":"CA",
    "sg:city":"Hearst",
    "sg:classifiers":[
        {
            "category":"Government",
            "subcategory":"Office",
            "type":"Public Place"
        }
    ],
    "sg:phone":"+1 705 362 5766",
    "sg:postcode":"P0L 1N0",
    "sg:province":"ON",
    "wof:name":"Ontario Agents DE I'Mmatricul",
    "wof:placetype":"venue"
},
  "geometry": {"coordinates":[-83.6592102051,49.6835975647],"type":"Point"}
}