{
  "type": "Feature",
  "properties": {
    "iso:country":"CA",
    "sg:address":"522 Av Acadie",
    "sg:city":"Dieppe",
    "sg:classifiers":[
        {
            "category":"Organizations",
            "subcategory":"Religious Organization",
            "type":"Services"
        }
    ],
    "sg:phone":"+1 506 855 8938",
    "sg:postcode":"E1A 1H9",
    "sg:province":"NB",
    "wof:name":"Soeurs Notre Dame-Sacre Coeur",
    "wof:placetype":"venue"
},
  "geometry": {"coordinates":[-64.754387,46.097778],"type":"Point"}
}