{
  "type": "Feature",
  "properties": {
    "iso:country":"CA",
    "sg:address":"131 Carrick Dr",
    "sg:city":"St. John's",
    "sg:classifiers":[
        {
            "category":"Building & Trades",
            "subcategory":"Electrical",
            "type":"Services"
        }
    ],
    "sg:phone":"+1 709 726 6888",
    "sg:postcode":"A1A 4P7",
    "sg:province":"NL",
    "sg:tags":[
        "electric",
        "contractor"
    ],
    "wof:name":"H Burton Electric Ltd",
    "wof:placetype":"venue"
},
  "geometry": {"coordinates":[-52.706111908,47.6107673645],"type":"Point"}
}