{
  "type": "Feature",
  "properties": {
    "addr:full":"24 Av Fairmount O Montreal QC H2T 2M1",
    "addr:postcode":"h2t 2m1",
    "addr:street":"24 Av Fairmount O",
    "iso:country":"CA",
    "sg:address":"24 Av Fairmount O",
    "sg:city":"Montreal",
    "sg:classifiers":[
        {
            "category":"Shopping",
            "type":"Retail Goods"
        }
    ],
    "sg:phone":"+1 514 276 6863",
    "sg:postcode":"H2T 2M1",
    "sg:province":"QC",
    "sg:tags":[
        "material",
        "artist",
        "supply"
    ],
    "wof:name":"Au Papier Japonais",
    "wof:placetype":"venue"
},
  "geometry": {"coordinates":[-73.5941390991,45.5244483948],"type":"Point"}
}