{
  "type": "Feature",
  "properties": {
    "addr:full":"5281 Westminster Ave Delta BC V4K 2J4",
    "addr:housenumber":"5281",
    "addr:postcode":"v4k 2j4",
    "addr:street":"Westminster Ave",
    "iso:country":"CA",
    "sg:address":"5281 Westminster Ave",
    "sg:city":"Delta",
    "sg:classifiers":[
        {
            "category":"Organizations",
            "subcategory":"Non-profit Organization",
            "type":"Services"
        }
    ],
    "sg:phone":"+1 604 940 1290",
    "sg:postcode":"V4K 2J4",
    "sg:province":"BC",
    "sg:tags":[
        "disability"
    ],
    "wof:name":"Ladner House",
    "wof:placetype":"venue"
},
  "geometry": {"coordinates":[-123.07607299999999,49.099133],"type":"Point"}
}