{
  "type": "Feature",
  "properties": {
    "addr:full":"234 Av DE LA Graviere Coaticook QC J1A 3E6",
    "addr:postcode":"j1a 3e6",
    "addr:street":"234 Av De La Graviere",
    "iso:country":"CA",
    "sg:address":"234 Av DE LA Graviere",
    "sg:city":"Coaticook",
    "sg:classifiers":[
        {
            "category":"Retail",
            "subcategory":"Auto Repair",
            "type":"Services"
        }
    ],
    "sg:phone":"+1 819 849 0227",
    "sg:postcode":"J1A 3E6",
    "sg:province":"QC",
    "sg:tags":[
        "truck"
    ],
    "wof:name":"Mecanique Generale Martin",
    "wof:placetype":"venue"
},
  "geometry": {"coordinates":[-71.810371,45.126011],"type":"Point"}
}