{
  "type": "Feature",
  "properties": {
    "addr:full":"69 Huron St Ripley ON N0G 2R0",
    "addr:housenumber":"69",
    "addr:postcode":"n0g 2r0",
    "addr:street":"Huron St",
    "iso:country":"CA",
    "sg:address":"69 Huron St",
    "sg:city":"Ripley",
    "sg:classifiers":[
        {
            "category":"Building & Trades",
            "subcategory":"Electrical",
            "type":"Services"
        }
    ],
    "sg:phone":"+1 519 395 2982",
    "sg:postcode":"N0G 2R0",
    "sg:province":"ON",
    "sg:tags":[
        "electric",
        "contractor"
    ],
    "wof:name":"Pollock Electric Ltd",
    "wof:placetype":"venue"
},
  "geometry": {"coordinates":[-81.579483,44.069996],"type":"Point"}
}