{
  "type": "Feature",
  "properties": {
    "iso:country":"CA",
    "sg:address":"137 5 Ave W",
    "sg:city":"Bow Island",
    "sg:classifiers":[
        {
            "category":"Wholesale",
            "subcategory":"Construction Materials",
            "type":"Manufacturing & Wholesale Goods"
        }
    ],
    "sg:phone":"+1 403 545 2454",
    "sg:postcode":"T0K 0G0",
    "sg:province":"AB",
    "sg:tags":[
        "sand",
        "gravel"
    ],
    "wof:name":"Royal Sand & Gravel Ltd",
    "wof:placetype":"venue"
},
  "geometry": {"coordinates":[-111.381111,49.869381],"type":"Point"}
}