{
  "type": "Feature",
  "properties": {
    "addr:full":"Mississauga ON L5R 3L5",
    "addr:postcode":"l5r 3l5",
    "iso:country":"CA",
    "sg:city":"Mississauga",
    "sg:classifiers":[
        {
            "category":"Social Services",
            "subcategory":"Child Care",
            "type":"Services"
        }
    ],
    "sg:phone":"+1 905 568 4770",
    "sg:postcode":"L5R 3L5",
    "sg:province":"ON",
    "wof:name":"Hearts Child Care Ctr",
    "wof:placetype":"venue"
},
  "geometry": {"coordinates":[-79.67380523680001,43.6166114807],"type":"Point"}
}