{
  "type": "Feature",
  "properties": {
    "addr:full":"2 Carlton St # 901 Toronto ON M5B 1J3",
    "addr:housenumber":"2",
    "addr:postcode":"m5b 1j3",
    "addr:street":"Carlton St # 901",
    "iso:country":"CA",
    "sg:address":"2 Carlton St # 901",
    "sg:city":"Toronto",
    "sg:classifiers":[
        {
            "category":"Health Services",
            "subcategory":"Health Practitioner",
            "type":"Services"
        }
    ],
    "sg:phone":"+1 416 977 5666",
    "sg:postcode":"M5B 1J3",
    "sg:province":"ON",
    "sg:tags":[
        "psychologist"
    ],
    "wof:name":"Pilkington, Neil",
    "wof:placetype":"venue"
},
  "geometry": {"coordinates":[-79.3826599121,43.661567688],"type":"Point"}
}