{
  "type": "Feature",
  "properties": {
    "addr:full":"St Albert AB T8N 6Z8",
    "addr:postcode":"t8n 6z8",
    "iso:country":"CA",
    "sg:city":"St Albert",
    "sg:classifiers":[
        {
            "category":"Shopping",
            "subcategory":"Florist",
            "type":"Retail Goods"
        }
    ],
    "sg:phone":"+1 780 458 3585",
    "sg:postcode":"T8N 6Z8",
    "sg:province":"AB",
    "wof:name":"Funky Petals",
    "wof:placetype":"venue"
},
  "geometry": {"coordinates":[-113.624656677,53.6327972412],"type":"Point"}
}