{
  "type": "Feature",
  "properties": {
    "addr:full":"38 Rang Lepage Sainte-Anne-Des-Plaines QC J0N 1H0",
    "addr:housenumber":"38",
    "addr:postcode":"j0n 1h0",
    "addr:street":"Rang Lepage",
    "iso:country":"CA",
    "sg:address":"38 Rang Lepage",
    "sg:city":"Sainte-Anne-Des-Plaines",
    "sg:classifiers":[
        {
            "category":"Home & Garden",
            "subcategory":"Building Materials",
            "type":"Retail Goods"
        }
    ],
    "sg:phone":"+1 450 478 2323",
    "sg:postcode":"J0N 1H0",
    "sg:province":"QC",
    "sg:tags":[
        "windows",
        "roof",
        "structure"
    ],
    "wof:name":"Lepine & Lepine Inc",
    "wof:placetype":"venue"
},
  "geometry": {"coordinates":[-73.8528594971,45.7334938049],"type":"Point"}
}