{
  "type": "Feature",
  "properties": {
    "addr:full":"3312 Kingsway Vancouver BC V5R 5K7",
    "addr:housenumber":"3312",
    "addr:postcode":"v5r 5k7",
    "addr:street":"Kingsway",
    "iso:country":"CA",
    "sg:address":"3312 Kingsway",
    "sg:city":"Vancouver",
    "sg:classifiers":[
        {
            "category":"Restaurant",
            "type":"Food & Drink"
        }
    ],
    "sg:phone":"+1 604 434 0343",
    "sg:postcode":"V5R 5K7",
    "sg:province":"BC",
    "wof:name":"Bino's Restaurants",
    "wof:placetype":"venue"
},
  "geometry": {"coordinates":[-123.0355,49.233776],"type":"Point"}
}