{
  "type": "Feature",
  "properties": {
    "addr:full":"Toronto ON M5A 1Z1",
    "addr:postcode":"m5a 1z1",
    "iso:country":"CA",
    "sg:city":"Toronto",
    "sg:classifiers":[
        {
            "category":"Wholesale",
            "subcategory":"Non-durable Goods",
            "type":"Manufacturing & Wholesale Goods"
        }
    ],
    "sg:phone":"+1 416 956 4940",
    "sg:postcode":"M5A 1Z1",
    "sg:province":"ON",
    "wof:name":"Standen House Ltd",
    "wof:placetype":"venue"
},
  "geometry": {"coordinates":[-79.35707855219999,43.6597137451],"type":"Point"}
}