{
  "type": "Feature",
  "properties": {
    "addr:full":"457 Hwy 16 Burns Lake BC V0J 1E0",
    "addr:housenumber":"457",
    "addr:postcode":"v0j 1e0",
    "addr:street":"Hwy 16 Burns",
    "iso:country":"CA",
    "sg:address":"457 Hwy 16",
    "sg:city":"Burns Lake",
    "sg:classifiers":[
        {
            "category":"Organizations",
            "subcategory":"Religious Organization",
            "type":"Services"
        }
    ],
    "sg:phone":"+1 250 692 7962",
    "sg:postcode":"V0J 1E0",
    "sg:province":"BC",
    "sg:tags":[
        "church"
    ],
    "wof:name":"Burns Lake Vineyard Fellowship",
    "wof:placetype":"venue"
},
  "geometry": {"coordinates":[-125.76293200000001,54.230171],"type":"Point"}
}