{
  "type": "Feature",
  "properties": {
    "iso:country":"CA",
    "sg:address":"2035 Boul Wilfrid-Hamel",
    "sg:city":"Quebec",
    "sg:classifiers":[
        {
            "category":"Retail",
            "subcategory":"Auto Repair",
            "type":"Services"
        }
    ],
    "sg:phone":"+1 418 687 2225",
    "sg:postcode":"G1N 3Z4",
    "sg:province":"QC",
    "sg:tags":[
        "body",
        "automobile",
        "painting"
    ],
    "wof:name":"Fix Auto",
    "wof:placetype":"venue"
},
  "geometry": {"coordinates":[-71.288086,46.806126],"type":"Point"}
}