{
  "type": "Feature",
  "properties": {
    "addr:full":"2035 Boul Wilfrid-Hamel Quebec QC G1N 3Z4",
    "addr:housenumber":"2035",
    "addr:postcode":"g1n 3z4",
    "addr:street":"Boul Wilfrid-Hamel",
    "iso:country":"CA",
    "sg:address":"2035 Boul Wilfrid-Hamel",
    "sg:city":"Quebec",
    "sg:classifiers":[
        {
            "category":"Retail",
            "subcategory":"Auto Repair",
            "type":"Services"
        }
    ],
    "sg:phone":"+1 418 687 2225",
    "sg:postcode":"G1N 3Z4",
    "sg:province":"QC",
    "sg:tags":[
        "body",
        "automobile",
        "painting"
    ],
    "wof:name":"Fix Auto",
    "wof:placetype":"venue"
},
  "geometry": {"coordinates":[-71.28808600000001,46.806126],"type":"Point"}
}