{
  "type": "Feature",
  "properties": {
    "addr:full":"619 Campbell St Lucknow ON N0G 2H0",
    "addr:housenumber":"619",
    "addr:postcode":"n0g 2h0",
    "addr:street":"Campbell St",
    "iso:country":"CA",
    "sg:address":"619 Campbell St",
    "sg:city":"Lucknow",
    "sg:classifiers":[
        {
            "category":"Manufacturing",
            "subcategory":"Printing",
            "type":"Manufacturing & Wholesale Goods"
        }
    ],
    "sg:phone":"+1 519 528 2822",
    "sg:postcode":"N0G 2H0",
    "sg:province":"ON",
    "sg:tags":[
        "newspaper"
    ],
    "wof:name":"Lucknow Sentinel",
    "wof:placetype":"venue"
},
  "geometry": {"coordinates":[-81.51619700000001,43.96151],"type":"Point"}
}