{
  "type": "Feature",
  "properties": {
    "addr:full":"440 204 Rte N Saint-Gedeon-DE-Beauce QC G0M 1T0",
    "addr:housenumber":"440 204",
    "addr:postcode":"g0m 1t0",
    "addr:street":"Rte N",
    "iso:country":"CA",
    "sg:address":"440 204 Rte N",
    "sg:city":"Saint-Gedeon-DE-Beauce",
    "sg:classifiers":[
        {
            "category":"Wholesale",
            "subcategory":"Machinery & Supplies",
            "type":"Manufacturing & Wholesale Goods"
        }
    ],
    "sg:phone":"+1 418 582 3711",
    "sg:postcode":"G0M 1T0",
    "sg:province":"QC",
    "sg:tags":[
        "farm",
        "equipment"
    ],
    "wof:name":"Equipements R Turgeon Inc",
    "wof:placetype":"venue"
},
  "geometry": {"coordinates":[-70.634987,45.856564],"type":"Point"}
}