{
  "type": "Feature",
  "properties": {
    "addr:full":"237 King St Blyth ON N0M 1H0",
    "addr:housenumber":"237",
    "addr:postcode":"n0m 1h0",
    "addr:street":"King St",
    "iso:country":"CA",
    "sg:address":"237 King St",
    "sg:city":"Blyth",
    "sg:classifiers":[
        {
            "category":"Education",
            "subcategory":"School",
            "type":"Public Place"
        }
    ],
    "sg:phone":"+1 519 523 9201",
    "sg:postcode":"N0M 1H0",
    "sg:province":"ON",
    "wof:name":"Blyth Public School",
    "wof:placetype":"venue"
},
  "geometry": {"coordinates":[-81.42781066889999,43.734413147],"type":"Point"}
}