{
  "type": "Feature",
  "properties": {
    "iso:country":"CA",
    "sg:address":"1060 Commerce St",
    "sg:city":"Thunder Bay",
    "sg:classifiers":[
        {
            "category":"Retail",
            "subcategory":"Auto Repair",
            "type":"Services"
        }
    ],
    "sg:phone":"+1 807 475 8711",
    "sg:postcode":"P7E 6E9",
    "sg:province":"ON",
    "sg:tags":[
        "repairing",
        "automobile"
    ],
    "wof:name":"Trucks Vans & Drive Line",
    "wof:placetype":"venue"
},
  "geometry": {"coordinates":[-89.297905,48.372627],"type":"Point"}
}