{
  "type": "Feature",
  "properties": {
    "addr:full":"6931 Victoria Dr Vancouver BC V5P 3Y7",
    "addr:housenumber":"6931",
    "addr:postcode":"v5p 3y7",
    "addr:street":"Victoria Dr",
    "iso:country":"CA",
    "sg:address":"6931 Victoria Dr",
    "sg:city":"Vancouver",
    "sg:classifiers":[
        {
            "category":"Retail",
            "subcategory":"Auto Repair",
            "type":"Services"
        }
    ],
    "sg:phone":"+1 604 322 1800",
    "sg:postcode":"V5P 3Y7",
    "sg:province":"BC",
    "sg:tags":[
        "automobile",
        "electric"
    ],
    "wof:name":"Colin's Auto Electric Ltd",
    "wof:placetype":"venue"
},
  "geometry": {"coordinates":[-123.06602478000001,49.2210884094],"type":"Point"}
}