{
  "type": "Feature",
  "properties": {
    "addr:full":"Halifax NS B3H 1Y1",
    "addr:postcode":"b3h 1y1",
    "iso:country":"CA",
    "sg:city":"Halifax",
    "sg:classifiers":[
        {
            "category":"Health Services",
            "subcategory":"Health Practitioner",
            "type":"Services"
        }
    ],
    "sg:phone":"+1 902 425 0542",
    "sg:postcode":"B3H 1Y1",
    "sg:province":"NS",
    "sg:tags":[
        "physician"
    ],
    "wof:name":"Stillpoint Naturopathic Clinic",
    "wof:placetype":"venue"
},
  "geometry": {"coordinates":[-63.5845222473,44.6408615112],"type":"Point"}
}