{
  "type": "Feature",
  "properties": {
    "addr:full":"Trans Canada Hwy Bishops Falls NL A0H 1C0",
    "addr:postcode":"a0h 1c0",
    "addr:street":"Trans Canada Hwy",
    "iso:country":"CA",
    "sg:address":"Trans Canada Hwy",
    "sg:city":"Bishops Falls",
    "sg:classifiers":[
        {
            "category":"Restaurant",
            "type":"Food & Drink"
        }
    ],
    "sg:phone":"+1 709 258 6852",
    "sg:postcode":"A0H 1C0",
    "sg:province":"NL",
    "wof:name":"Bishop's Falls Irving Rstrnt",
    "wof:placetype":"venue"
},
  "geometry": {"coordinates":[-55.5457229614,48.9899406433],"type":"Point"}
}