{
  "type": "Feature",
  "properties": {
    "iso:country":"CA",
    "sg:address":"44 Poneida Rd",
    "sg:city":"West St Paul",
    "sg:classifiers":[
        {
            "category":"Manufacturing",
            "subcategory":"Motor Vehicles & Parts",
            "type":"Manufacturing & Wholesale Goods"
        }
    ],
    "sg:phone":"+1 204 334 6596",
    "sg:postcode":"R4A 5A9",
    "sg:province":"MB",
    "sg:tags":[
        "trailer"
    ],
    "wof:name":"Sokal Industries Ltd",
    "wof:placetype":"venue"
},
  "geometry": {"coordinates":[-97.122428894,49.9922943115],"type":"Point"}
}