{
  "type": "Feature",
  "properties": {
    "addr:full":"33290 Glasgow Ave Mission BC V2V 4M2",
    "addr:housenumber":"33290",
    "addr:postcode":"v2v 4m2",
    "addr:street":"Glasgow Ave",
    "iso:country":"CA",
    "sg:address":"33290 Glasgow Ave",
    "sg:city":"Mission",
    "sg:classifiers":[
        {
            "category":"Restaurant",
            "type":"Food & Drink"
        }
    ],
    "sg:phone":"+1 604 826 5635",
    "sg:postcode":"V2V 4M2",
    "sg:province":"BC",
    "wof:name":"Expresso Way Coffee House",
    "wof:placetype":"venue"
},
  "geometry": {"coordinates":[-122.302689,49.131794],"type":"Point"}
}