{
  "type": "Feature",
  "properties": {
    "addr:full":"Toronto ON M5V 3E7",
    "addr:postcode":"m5v 3e7",
    "iso:country":"CA",
    "sg:city":"Toronto",
    "sg:classifiers":[
        {
            "category":"Manufacturing",
            "subcategory":"Printing",
            "type":"Manufacturing & Wholesale Goods"
        }
    ],
    "sg:phone":"+1 416 955 9969",
    "sg:postcode":"M5V 3E7",
    "sg:province":"ON",
    "sg:tags":[
        "publisher"
    ],
    "wof:name":"Clarco Communications Ltd",
    "wof:placetype":"venue"
},
  "geometry": {"coordinates":[-79.398094,43.647434],"type":"Point"}
}