{
  "type": "Feature",
  "properties": {
    "addr:full":"10 Vermillion Rd Winnipeg MB R2J 2T1",
    "addr:housenumber":"10",
    "addr:postcode":"r2j 2t1",
    "addr:street":"Vermillion Rd",
    "iso:country":"CA",
    "sg:address":"10 Vermillion Rd",
    "sg:city":"Winnipeg",
    "sg:classifiers":[
        {
            "category":"Education",
            "subcategory":"School",
            "type":"Public Place"
        }
    ],
    "sg:phone":"+1 204 255 1134",
    "sg:postcode":"R2J 2T1",
    "sg:province":"MB",
    "wof:name":"Ecole Van Belleghem School",
    "wof:placetype":"venue"
},
  "geometry": {"coordinates":[-97.07781199999999,49.853626],"type":"Point"}
}