{
  "type": "Feature",
  "properties": {
    "iso:country":"CA",
    "sg:address":"10 Vermillion Rd",
    "sg:city":"Winnipeg",
    "sg:classifiers":[
        {
            "category":"Education",
            "subcategory":"School",
            "type":"Public Place"
        }
    ],
    "sg:phone":"+1 204 255 1134",
    "sg:postcode":"R2J 2T1",
    "sg:province":"MB",
    "wof:name":"Ecole Van Belleghem School",
    "wof:placetype":"venue"
},
  "geometry": {"coordinates":[-97.077812,49.853626],"type":"Point"}
}