{
  "type": "Feature",
  "properties": {
    "addr:full":"4811 50 St Athabasca AB T9S 1C8",
    "addr:housenumber":"4811",
    "addr:postcode":"t9s 1c8",
    "addr:street":"50 St",
    "iso:country":"CA",
    "sg:address":"4811 50 St",
    "sg:city":"Athabasca",
    "sg:classifiers":[
        {
            "category":"Real Estate",
            "subcategory":"Real Estate Agent",
            "type":"Services"
        }
    ],
    "sg:phone":"+1 780 675 2100",
    "sg:postcode":"T9S 1C8",
    "sg:province":"AB",
    "wof:name":"Century 21 Lakeland Real Est",
    "wof:placetype":"venue"
},
  "geometry": {"coordinates":[-113.286125183,54.7181549072],"type":"Point"}
}