{
  "type": "Feature",
  "properties": {
    "addr:full":"10008 107 St Morinville AB T8R 1L3",
    "addr:housenumber":"10008",
    "addr:postcode":"t8r 1l3",
    "addr:street":"107 St",
    "iso:country":"CA",
    "sg:address":"10008 107 St",
    "sg:city":"Morinville",
    "sg:classifiers":[
        {
            "category":"Government",
            "subcategory":"Office",
            "type":"Public Place"
        }
    ],
    "sg:phone":"+1 780 939 6805",
    "sg:postcode":"T8R 1L3",
    "sg:province":"AB",
    "wof:name":"Alberta Provincial Court",
    "wof:placetype":"venue"
},
  "geometry": {"coordinates":[-113.657646179,53.8020820618],"type":"Point"}
}