{
  "type": "Feature",
  "properties": {
    "iso:country":"CA",
    "sg:city":"Nanaimo",
    "sg:classifiers":[
        {
            "category":"Shopping",
            "type":"Retail Goods"
        }
    ],
    "sg:phone":"+1 250 758 2727",
    "sg:postcode":"V9T 5V4",
    "sg:province":"BC",
    "sg:tags":[
        "pet",
        "shop",
        "supply"
    ],
    "wof:name":"True Blue Natural Pet Foods CO",
    "wof:placetype":"venue"
},
  "geometry": {"coordinates":[-123.988441467,49.2000694275],"type":"Point"}
}