{
  "type": "Feature",
  "properties": {
    "iso:country":"CA",
    "sg:address":"177 Munro St",
    "sg:city":"Thunder Bay",
    "sg:classifiers":[
        {
            "category":"Freight",
            "type":"Transportation"
        }
    ],
    "sg:phone":"+1 807 344 6111",
    "sg:postcode":"P7A 2M9",
    "sg:province":"ON",
    "sg:tags":[
        "trucking"
    ],
    "wof:name":"Thunder Bay Tanker Svc",
    "wof:placetype":"venue"
},
  "geometry": {"coordinates":[-89.2022781372,48.4459609985],"type":"Point"}
}