{
  "type": "Feature",
  "properties": {
    "iso:country":"CA",
    "sg:address":"610 East River Rd",
    "sg:city":"New Glasgow",
    "sg:classifiers":[
        {
            "category":"Personal",
            "subcategory":"Beauty Salon",
            "type":"Services"
        }
    ],
    "sg:phone":"+1 902 928 1018",
    "sg:postcode":"B2H 3S2",
    "sg:province":"NS",
    "wof:name":"Magicuts Inc",
    "wof:placetype":"venue"
},
  "geometry": {"coordinates":[-62.6422576904,45.5778617859],"type":"Point"}
}