{
  "type": "Feature",
  "properties": {
    "addr:full":"610 East River Rd New Glasgow NS B2H 3S2",
    "addr:housenumber":"610",
    "addr:postcode":"b2h 3s2",
    "addr:street":"East River Rd",
    "iso:country":"CA",
    "sg:address":"610 East River Rd",
    "sg:city":"New Glasgow",
    "sg:classifiers":[
        {
            "category":"Personal",
            "subcategory":"Beauty Salon",
            "type":"Services"
        }
    ],
    "sg:phone":"+1 902 928 1018",
    "sg:postcode":"B2H 3S2",
    "sg:province":"NS",
    "wof:name":"Magicuts Inc",
    "wof:placetype":"venue"
},
  "geometry": {"coordinates":[-62.6422576904,45.5778617859],"type":"Point"}
}