{
  "type": "Feature",
  "properties": {
    "addr:full":"Digby NS B0V 1A0",
    "addr:postcode":"b0v 1a0",
    "iso:country":"CA",
    "sg:city":"Digby",
    "sg:classifiers":[
        {
            "category":"Shopping",
            "subcategory":"Books",
            "type":"Retail Goods"
        }
    ],
    "sg:phone":"+1 902 245 5651",
    "sg:postcode":"B0V 1A0",
    "sg:province":"NS",
    "sg:tags":[
        "dealer"
    ],
    "wof:name":"Guiding Light Book Store",
    "wof:placetype":"venue"
},
  "geometry": {"coordinates":[-65.756882,44.625225],"type":"Point"}
}