{
  "type": "Feature",
  "properties": {
    "addr:full":"1180 Kennedy Rd Scarborough ON M1P 2L1",
    "addr:housenumber":"1180",
    "addr:postcode":"m1p 2l1",
    "addr:street":"Kennedy Rd",
    "iso:country":"CA",
    "sg:address":"1180 Kennedy Rd",
    "sg:city":"Scarborough",
    "sg:classifiers":[
        {
            "category":"Autos & Motor Vehicles",
            "subcategory":"Auto Supplies",
            "type":"Retail Goods"
        }
    ],
    "sg:phone":"+1 416 259 9656",
    "sg:postcode":"M1P 2L1",
    "sg:province":"ON",
    "sg:tags":[
        "equipment",
        "racing",
        "car",
        "automobile"
    ],
    "wof:name":"Performance Improvements Speed",
    "wof:placetype":"venue"
},
  "geometry": {"coordinates":[-79.27636699999999,43.752953],"type":"Point"}
}