{
  "type": "Feature",
  "properties": {
    "iso:country":"CA",
    "sg:address":"11880 Rue Michel-Sarrazin",
    "sg:city":"Montreal",
    "sg:classifiers":[
        {
            "category":"Education",
            "subcategory":"School",
            "type":"Public Place"
        }
    ],
    "sg:phone":"+1 514 596 5359",
    "sg:postcode":"H4J 2G7",
    "sg:province":"QC",
    "wof:name":"Ecole Louisbourg",
    "wof:placetype":"venue"
},
  "geometry": {"coordinates":[-73.7096405029,45.5271034241],"type":"Point"}
}