{
  "type": "Feature",
  "properties": {
    "addr:full":"Ottawa ON K1T 3J6",
    "addr:postcode":"k1t 3j6",
    "iso:country":"CA",
    "sg:city":"Ottawa",
    "sg:classifiers":[
        {
            "category":"Social Services",
            "subcategory":"Child Care",
            "type":"Services"
        }
    ],
    "sg:phone":"+1 613 737 3325",
    "sg:postcode":"K1T 3J6",
    "sg:province":"ON",
    "wof:name":"Southkeys Greenboro School Age",
    "wof:placetype":"venue"
},
  "geometry": {"coordinates":[-75.62693023680001,45.3657913208],"type":"Point"}
}