{
  "type": "Feature",
  "properties": {
    "addr:full":"2841 Merkel Rd Port Colborne ON L3K 5V3",
    "addr:housenumber":"2841",
    "addr:postcode":"l3k 5v3",
    "addr:street":"Merkel Rd",
    "iso:country":"CA",
    "sg:address":"2841 Merkel Rd",
    "sg:city":"Port Colborne",
    "sg:classifiers":[
        {
            "category":"Shopping",
            "subcategory":"Gifts & Souvenirs",
            "type":"Retail Goods"
        }
    ],
    "sg:phone":"+1 905 835 8108",
    "sg:postcode":"L3K 5V3",
    "sg:province":"ON",
    "sg:tags":[
        "shop"
    ],
    "wof:name":"Robert Kelly Wood Carving",
    "wof:placetype":"venue"
},
  "geometry": {"coordinates":[-79.176376,42.878296],"type":"Point"}
}