{
  "type": "Feature",
  "properties": {
    "addr:full":"9566 111 Ave NW Edmonton AB T5G 0A7",
    "addr:housenumber":"9566",
    "addr:postcode":"t5g 0a7",
    "addr:street":"111 Ave Nw",
    "iso:country":"CA",
    "sg:address":"9566 111 Ave NW",
    "sg:city":"Edmonton",
    "sg:classifiers":[
        {
            "category":"Retail",
            "subcategory":"Repair Shop",
            "type":"Services"
        }
    ],
    "sg:phone":"+1 780 474 2496",
    "sg:postcode":"T5G 0A7",
    "sg:province":"AB",
    "sg:tags":[
        "sharpening",
        "tool"
    ],
    "wof:name":"Mc Keen's Saw Ltd",
    "wof:placetype":"venue"
},
  "geometry": {"coordinates":[-113.48959350600001,53.5592689514],"type":"Point"}
}