{
  "type": "Feature",
  "properties": {
    "addr:full":"826 Princess St Kingston ON K7L 1G3",
    "addr:housenumber":"826",
    "addr:postcode":"k7l 1g3",
    "addr:street":"Princess St",
    "iso:country":"CA",
    "sg:address":"826 Princess St",
    "sg:city":"Kingston",
    "sg:classifiers":[
        {
            "category":"Health Services",
            "subcategory":"Doctor",
            "type":"Services"
        }
    ],
    "sg:phone":"+1 613 542 4975",
    "sg:postcode":"K7L 1G3",
    "sg:province":"ON",
    "sg:tags":[
        "md",
        "oculist"
    ],
    "wof:name":"Webb Ocular Prosthethics Inc",
    "wof:placetype":"venue"
},
  "geometry": {"coordinates":[-76.507645,44.239292],"type":"Point"}
}