{
  "type": "Feature",
  "properties": {
    "addr:full":"73 Rue Saint-Antoine Trois-Rivieres QC G9A 2J2",
    "addr:housenumber":"73",
    "addr:postcode":"g9a 2j2",
    "addr:street":"Rue Saint-Antoine",
    "iso:country":"CA",
    "sg:address":"73 Rue Saint-Antoine",
    "sg:city":"Trois-Rivieres",
    "sg:classifiers":[
        {
            "category":"Shopping",
            "type":"Retail Goods"
        }
    ],
    "sg:phone":"+1 819 373 1980",
    "sg:postcode":"G9A 2J2",
    "sg:province":"QC",
    "sg:tags":[
        "art",
        "gallery",
        "dealer"
    ],
    "wof:name":"Atelier Presse Papier",
    "wof:placetype":"venue"
},
  "geometry": {"coordinates":[-72.54047393800001,46.3407974243],"type":"Point"}
}