{
  "type": "Feature",
  "properties": {
    "addr:full":"129 Erie St S Leamington ON N8H 3B5",
    "addr:housenumber":"129",
    "addr:postcode":"n8h 3b5",
    "addr:street":"Erie St S",
    "iso:country":"CA",
    "sg:address":"129 Erie St S",
    "sg:city":"Leamington",
    "sg:classifiers":[
        {
            "category":"Shopping",
            "subcategory":"Clothing, Apparel, & Fashions",
            "type":"Retail Goods"
        }
    ],
    "sg:phone":"+1 519 324 0858",
    "sg:postcode":"N8H 3B5",
    "sg:province":"ON",
    "sg:tags":[
        "lingerie"
    ],
    "wof:name":"Sensuously Yours",
    "wof:placetype":"venue"
},
  "geometry": {"coordinates":[-82.6003570557,42.0474777222],"type":"Point"}
}