{
  "type": "Feature",
  "properties": {
    "iso:country":"CA",
    "sg:address":"190 Weber St N",
    "sg:city":"Waterloo",
    "sg:classifiers":[
        {
            "category":"Restaurant",
            "type":"Food & Drink"
        }
    ],
    "sg:phone":"+1 519 885 5123",
    "sg:postcode":"N2J 3H4",
    "sg:province":"ON",
    "wof:name":"Golden Griddle Family Rstrnt",
    "wof:placetype":"venue"
},
  "geometry": {"coordinates":[-80.517982,43.47617],"type":"Point"}
}