{
  "type": "Feature",
  "properties": {
    "addr:full":"705 Arcola Ave Regina SK S4N 0S8",
    "addr:housenumber":"705",
    "addr:postcode":"s4n 0s8",
    "addr:street":"Arcola Ave",
    "iso:country":"CA",
    "sg:address":"705 Arcola Ave",
    "sg:city":"Regina",
    "sg:classifiers":[
        {
            "category":"Retail",
            "subcategory":"Auto Repair",
            "type":"Services"
        }
    ],
    "sg:phone":"+1 306 522 9922",
    "sg:postcode":"S4N 0S8",
    "sg:province":"SK",
    "sg:tags":[
        "body",
        "automobile",
        "painting"
    ],
    "wof:name":"Arcola Auto Body Ltd",
    "wof:placetype":"venue"
},
  "geometry": {"coordinates":[-104.591133,50.449837],"type":"Point"}
}