{
  "type": "Feature",
  "properties": {
    "addr:full":"1999 Rue Patrick-Farrar Chambly QC J3L 4N7",
    "addr:housenumber":"1999",
    "addr:postcode":"j3l 4n7",
    "addr:street":"Rue Patrick-Farrar",
    "iso:country":"CA",
    "sg:address":"1999 Rue Patrick-Farrar",
    "sg:city":"Chambly",
    "sg:classifiers":[
        {
            "category":"Wholesale",
            "subcategory":"Durable Goods & Equipment",
            "type":"Manufacturing & Wholesale Goods"
        }
    ],
    "sg:phone":"+1 450 658 8795",
    "sg:postcode":"J3L 4N7",
    "sg:province":"QC",
    "sg:tags":[
        "magnet",
        "magnetic",
        "devices"
    ],
    "wof:name":"Simple Signman Inc",
    "wof:placetype":"venue"
},
  "geometry": {"coordinates":[-73.28299699999999,45.411072],"type":"Point"}
}