{
  "type": "Feature",
  "properties": {
    "addr:full":"4602 E Railway St Blackfalds AB T0M 0J0",
    "addr:housenumber":"4602",
    "addr:postcode":"t0m 0j0",
    "addr:street":"E Railway St",
    "iso:country":"CA",
    "sg:address":"4602 E Railway St",
    "sg:city":"Blackfalds",
    "sg:classifiers":[
        {
            "category":"Home & Garden",
            "subcategory":"Furniture",
            "type":"Retail Goods"
        }
    ],
    "sg:phone":"+1 403 885 4545",
    "sg:postcode":"T0M 0J0",
    "sg:province":"AB",
    "sg:tags":[
        "kitchen",
        "maker",
        "cabinet"
    ],
    "wof:name":"Contempo Kitchens Ltd",
    "wof:placetype":"venue"
},
  "geometry": {"coordinates":[-113.800713,52.376629],"type":"Point"}
}