{
  "type": "Feature",
  "properties": {
    "iso:country":"CA",
    "sg:city":"Bowmanville",
    "sg:classifiers":[
        {
            "category":"Cinema",
            "subcategory":"Movie Rental",
            "type":"Entertainment"
        }
    ],
    "sg:phone":"+1 905 721 2362",
    "sg:postcode":"L1C 3K2",
    "sg:province":"ON",
    "sg:tags":[
        "leasing",
        "video",
        "disc",
        "tape"
    ],
    "wof:name":"Rogers Video",
    "wof:placetype":"venue"
},
  "geometry": {"coordinates":[-78.66449737550001,43.912311554],"type":"Point"}
}