{
  "type": "Feature",
  "properties": {
    "addr:full":"1925 Kingsway Vancouver BC V5N 2T1",
    "addr:housenumber":"1925",
    "addr:postcode":"v5n 2t1",
    "addr:street":"Kingsway",
    "iso:country":"CA",
    "sg:address":"1925 Kingsway",
    "sg:city":"Vancouver",
    "sg:classifiers":[
        {
            "category":"Food & Beverages",
            "subcategory":"Specialty",
            "type":"Retail Goods"
        }
    ],
    "sg:phone":"+1 604 875 8899",
    "sg:postcode":"V5N 2T1",
    "sg:province":"BC",
    "sg:tags":[
        "health",
        "diet"
    ],
    "wof:name":"Vancouver Herbal & Health Food",
    "wof:placetype":"venue"
},
  "geometry": {"coordinates":[-123.06596399999999,49.245689],"type":"Point"}
}