{
  "type": "Feature",
  "properties": {
    "addr:full":"Winnipeg MB R3N 0M7",
    "addr:postcode":"r3n 0m7",
    "iso:country":"CA",
    "sg:city":"Winnipeg",
    "sg:classifiers":[
        {
            "category":"Health Services",
            "subcategory":"Health Practitioner",
            "type":"Services"
        }
    ],
    "sg:phone":"+1 204 487 0101",
    "sg:postcode":"R3N 0M7",
    "sg:province":"MB",
    "sg:tags":[
        "nutritionist",
        "dietitian"
    ],
    "wof:name":"Herbs & More Nutritional",
    "wof:placetype":"venue"
},
  "geometry": {"coordinates":[-97.1933746338,49.8565711975],"type":"Point"}
}