{
  "type": "Feature",
  "properties": {
    "addr:full":"44 Wright Ave Dartmouth NS B3B 1G6",
    "addr:housenumber":"44",
    "addr:postcode":"b3b 1g6",
    "addr:street":"Wright Ave",
    "iso:country":"CA",
    "sg:address":"44 Wright Ave",
    "sg:city":"Dartmouth",
    "sg:classifiers":[
        {
            "category":"Manufacturing",
            "subcategory":"Chemicals & Compounds",
            "type":"Manufacturing & Wholesale Goods"
        }
    ],
    "sg:phone":"+1 902 468 8180",
    "sg:postcode":"B3B 1G6",
    "sg:province":"NS",
    "sg:tags":[
        "janitor"
    ],
    "wof:name":"Bebbington Industries Inc",
    "wof:placetype":"venue"
},
  "geometry": {"coordinates":[-63.6018638611,44.6999664307],"type":"Point"}
}