{
  "type": "Feature",
  "properties": {
    "addr:full":"171 30 St SE Salmon Arm BC V1E 1J5",
    "addr:housenumber":"30",
    "addr:postcode":"v1e 1j5",
    "addr:street":"171;St Se",
    "iso:country":"CA",
    "sg:address":"171 30 St SE",
    "sg:city":"Salmon Arm",
    "sg:classifiers":[
        {
            "category":"Education",
            "subcategory":"School",
            "type":"Public Place"
        }
    ],
    "sg:phone":"+1 250 832 6031",
    "sg:postcode":"V1E 1J5",
    "sg:province":"BC",
    "wof:name":"Shuswap Junior Secondary Schl",
    "wof:placetype":"venue"
},
  "geometry": {"coordinates":[-119.250473,50.699837],"type":"Point"}
}