{
  "type": "Feature",
  "properties": {
    "iso:country":"CA",
    "sg:address":"4439 47 St",
    "sg:city":"Rocky Mountain House",
    "sg:classifiers":[
        {
            "category":"Home & Garden",
            "subcategory":"Household Appliances",
            "type":"Retail Goods"
        }
    ],
    "sg:phone":"+1 403 845 3391",
    "sg:postcode":"T4T 1C7",
    "sg:province":"AB",
    "sg:tags":[
        "mail",
        "catalog",
        "shopping",
        "order"
    ],
    "wof:name":"Sears Canada Inc",
    "wof:placetype":"venue"
},
  "geometry": {"coordinates":[-114.914550781,52.3681106567],"type":"Point"}
}