{
  "type": "Feature",
  "properties": {
    "addr:full":"Ottawa ON K2P 0R2",
    "addr:postcode":"k2p 0r2",
    "iso:country":"CA",
    "sg:city":"Ottawa",
    "sg:classifiers":[
        {
            "category":"Real Estate",
            "subcategory":"Real Estate Operator",
            "type":"Services"
        }
    ],
    "sg:phone":"+1 613 567 8697",
    "sg:postcode":"K2P 0R2",
    "sg:province":"ON",
    "sg:tags":[
        "apartment"
    ],
    "wof:name":"Enfield Apartments",
    "wof:placetype":"venue"
},
  "geometry": {"coordinates":[-75.694633,45.414505],"type":"Point"}
}