{
  "type": "Feature",
  "properties": {
    "addr:full":"1925 Mcara St Regina SK S4N 2V5",
    "addr:housenumber":"1925",
    "addr:postcode":"s4n 2v5",
    "addr:street":"Mcara St",
    "iso:country":"CA",
    "sg:address":"1925 Mcara St",
    "sg:city":"Regina",
    "sg:classifiers":[
        {
            "category":"Organizations",
            "subcategory":"Community Association",
            "type":"Services"
        }
    ],
    "sg:phone":"+1 306 522 8182",
    "sg:postcode":"S4N 2V5",
    "sg:province":"SK",
    "sg:tags":[
        "club"
    ],
    "wof:name":"Hungarian Cultural & Social",
    "wof:placetype":"venue"
},
  "geometry": {"coordinates":[-104.581985,50.448246],"type":"Point"}
}