{
  "type": "Feature",
  "properties": {
    "addr:full":"6655 DE LA Cote-Des-Neiges Ch Montreal QC H3S 2B4",
    "addr:housenumber":"6655",
    "addr:postcode":"h3s 2b4",
    "addr:street":"De La Cote-Des-Neiges Ch",
    "iso:country":"CA",
    "sg:address":"6655 DE LA Cote-Des-Neiges Ch",
    "sg:city":"Montreal",
    "sg:classifiers":[
        {
            "category":"Government",
            "subcategory":"Office",
            "type":"Public Place"
        }
    ],
    "sg:phone":"+1 514 872 6530",
    "sg:postcode":"H3S 2B4",
    "sg:province":"QC",
    "wof:name":"Quebec Aide Financiere",
    "wof:placetype":"venue"
},
  "geometry": {"coordinates":[-73.636185,45.502823],"type":"Point"}
}