{
  "type": "Feature",
  "properties": {
    "addr:full":"209 Dundas St W Whitby ON L1N 2M4",
    "addr:housenumber":"209",
    "addr:postcode":"l1n 2m4",
    "addr:street":"Dundas St W",
    "iso:country":"CA",
    "sg:address":"209 Dundas St W",
    "sg:city":"Whitby",
    "sg:classifiers":[
        {
            "category":"Autos & Motor Vehicles",
            "subcategory":"Automobile Sales",
            "type":"Retail Goods"
        }
    ],
    "sg:phone":"+1 905 666 2628",
    "sg:postcode":"L1N 2M4",
    "sg:province":"ON",
    "sg:tags":[
        "renting",
        "car"
    ],
    "wof:name":"Robin Thompson Motors Ltd",
    "wof:placetype":"venue"
},
  "geometry": {"coordinates":[-78.94458,43.879326],"type":"Point"}
}