{
  "type": "Feature",
  "properties": {
    "addr:full":"965 Boul Cure-Labelle # 9 Laval QC H7V 2V7",
    "addr:housenumber":"965",
    "addr:postcode":"h7v 2v7",
    "addr:street":"Boul Cure-Labelle # 9",
    "iso:country":"CA",
    "sg:address":"965 Boul Cure-Labelle # 9",
    "sg:city":"Laval",
    "sg:classifiers":[
        {
            "category":"Shopping",
            "subcategory":"Jewelry",
            "type":"Retail Goods"
        }
    ],
    "sg:phone":"+1 450 687 2502",
    "sg:postcode":"H7V 2V7",
    "sg:province":"QC",
    "sg:tags":[
        "jeweler"
    ],
    "wof:name":"Bijouterie Diamant Elizar",
    "wof:placetype":"venue"
},
  "geometry": {"coordinates":[-73.749207,45.542011],"type":"Point"}
}