{
  "type": "Feature",
  "properties": {
    "iso:country":"CA",
    "sg:address":"PO Box 5442 STN Main",
    "sg:city":"Fort Mcmurray",
    "sg:classifiers":[
        {
            "category":"Organizations",
            "subcategory":"Professional Association",
            "type":"Services"
        }
    ],
    "sg:phone":"+1 780 791 1600",
    "sg:postcode":"T9H 3G4",
    "sg:province":"AB",
    "wof:name":"Fort Mc Murray Interplay",
    "wof:placetype":"venue"
},
  "geometry": {"coordinates":[-111.380302429,56.7271881104],"type":"Point"}
}