{
  "type": "Feature",
  "properties": {
    "addr:full":"400 Laclie St Orillia ON L3V 4P5",
    "addr:housenumber":"400",
    "addr:postcode":"l3v 4p5",
    "addr:street":"Laclie St",
    "iso:country":"CA",
    "sg:address":"400 Laclie St",
    "sg:city":"Orillia",
    "sg:classifiers":[
        {
            "category":"Restaurant",
            "type":"Food & Drink"
        }
    ],
    "sg:phone":"+1 705 325 4872",
    "sg:postcode":"L3V 4P5",
    "sg:province":"ON",
    "wof:name":"Laclie Street Eatery",
    "wof:placetype":"venue"
},
  "geometry": {"coordinates":[-79.42237854,44.6239089966],"type":"Point"}
}