{
  "type": "Feature",
  "properties": {
    "addr:full":"606 Boul Provencher Winnipeg MB R2J 0C3",
    "addr:housenumber":"606",
    "addr:postcode":"r2j 0c3",
    "addr:street":"Boul Provencher",
    "iso:country":"CA",
    "sg:address":"606 Boul Provencher",
    "sg:city":"Winnipeg",
    "sg:classifiers":[
        {
            "category":"Utilities",
            "subcategory":"Refuse",
            "type":"Services"
        }
    ],
    "sg:phone":"+1 204 231 2290",
    "sg:postcode":"R2J 0C3",
    "sg:province":"MB",
    "sg:tags":[
        "garbage",
        "collection"
    ],
    "wof:name":"Ace Disposal",
    "wof:placetype":"venue"
},
  "geometry": {"coordinates":[-97.101173,49.897076],"type":"Point"}
}