{
  "type": "Feature",
  "properties": {
    "iso:country":"CA",
    "sg:address":"NE 9 1 14E",
    "sg:city":"Sprague",
    "sg:classifiers":[
        {
            "category":"Professional",
            "type":"Services"
        }
    ],
    "sg:phone":"+1 204 437 2742",
    "sg:postcode":"R0A 1Z0",
    "sg:province":"MB",
    "sg:tags":[
        "equipment",
        "establishment",
        "log",
        "sawmill",
        "splitting"
    ],
    "wof:name":"J Hovorka & Sons Ltd",
    "wof:placetype":"venue"
},
  "geometry": {"coordinates":[-95.64287567140001,49.0350494385],"type":"Point"}
}