{
  "type": "Feature",
  "properties": {
    "addr:full":"Montreal QC H3S 2B3",
    "addr:postcode":"h3s 2b3",
    "iso:country":"CA",
    "sg:city":"Montreal",
    "sg:classifiers":[
        {
            "category":"Health Services",
            "subcategory":"Health Practitioner",
            "type":"Services"
        }
    ],
    "sg:phone":"+1 514 341 4815",
    "sg:postcode":"H3S 2B3",
    "sg:province":"QC",
    "sg:tags":[
        "physiotherapist"
    ],
    "wof:name":"Centre Physiotherapie Royal",
    "wof:placetype":"venue"
},
  "geometry": {"coordinates":[-73.635834,45.502663],"type":"Point"}
}