{
  "type": "Feature",
  "properties": {
    "iso:country":"CA",
    "sg:address":"39 Talbot St E",
    "sg:city":"Leamington",
    "sg:classifiers":[
        {
            "category":"Organizations",
            "subcategory":"Religious Organization",
            "type":"Services"
        }
    ],
    "sg:phone":"+1 519 324 9654",
    "sg:postcode":"N8H 1L1",
    "sg:province":"ON",
    "sg:tags":[
        "church"
    ],
    "wof:name":"Templo Christiano DE Leamingto",
    "wof:placetype":"venue"
},
  "geometry": {"coordinates":[-82.5988540649,42.0534667969],"type":"Point"}
}