{
  "type": "Feature",
  "properties": {
    "iso:country":"CA",
    "sg:city":"Anjou",
    "sg:classifiers":[
        {
            "category":"Real Estate",
            "subcategory":"Architect",
            "type":"Services"
        }
    ],
    "sg:phone":"+1 514 493 6000",
    "sg:postcode":"H1M 2T4",
    "sg:province":"QC",
    "wof:name":"Poirier, Patrice",
    "wof:placetype":"venue"
},
  "geometry": {"coordinates":[-73.539665,45.610252],"type":"Point"}
}