{
  "type": "Feature",
  "properties": {
    "addr:full":"1209 Bute St Vancouver BC V6E 2A1",
    "addr:housenumber":"1209",
    "addr:postcode":"v6e 2a1",
    "addr:street":"Bute St",
    "iso:country":"CA",
    "sg:address":"1209 Bute St",
    "sg:city":"Vancouver",
    "sg:classifiers":[
        {
            "category":"Food & Beverages",
            "subcategory":"Groceries & Convenience Stores",
            "type":"Retail Goods"
        }
    ],
    "sg:phone":"+1 604 688 4319",
    "sg:postcode":"V6E 2A1",
    "sg:province":"BC",
    "sg:tags":[
        "grocer"
    ],
    "wof:name":"Westside Market",
    "wof:placetype":"venue"
},
  "geometry": {"coordinates":[-123.133674622,49.2817764282],"type":"Point"}
}