{
  "type": "Feature",
  "properties": {
    "addr:full":"4505 Roburn Rd Hornby Island BC V0R 1Z0",
    "addr:housenumber":"4505",
    "addr:postcode":"v0r 1z0",
    "addr:street":"Roburn Rd",
    "iso:country":"CA",
    "sg:address":"4505 Roburn Rd",
    "sg:city":"Hornby Island",
    "sg:classifiers":[
        {
            "category":"Real Estate",
            "subcategory":"Architect",
            "type":"Services"
        }
    ],
    "sg:phone":"+1 250 335 0115",
    "sg:postcode":"V0R 1Z0",
    "sg:province":"BC",
    "sg:tags":[
        "specification",
        "architectural"
    ],
    "wof:name":"Blue Sky Design",
    "wof:placetype":"venue"
},
  "geometry": {"coordinates":[-124.637337,49.507774],"type":"Point"}
}