{
  "type": "Feature",
  "properties": {
    "iso:country":"CA",
    "sg:city":"Cold Lake",
    "sg:classifiers":[
        {
            "category":"Insurance",
            "subcategory":"Insurance Agent",
            "type":"Services"
        }
    ],
    "sg:phone":"+1 780 594 4471",
    "sg:postcode":"T9M 1P1",
    "sg:province":"AB",
    "wof:name":"CO-Operators",
    "wof:placetype":"venue"
},
  "geometry": {"coordinates":[-110.205574036,54.4131088257],"type":"Point"}
}