{
  "type": "Feature",
  "properties": {
    "addr:full":"Repentigny QC J5Y 3L1",
    "addr:postcode":"j5y 3l1",
    "iso:country":"CA",
    "sg:city":"Repentigny",
    "sg:classifiers":[
        {
            "category":"Professional",
            "subcategory":"Business Services",
            "type":"Services"
        }
    ],
    "sg:phone":"+1 450 657 8416",
    "sg:postcode":"J5Y 3L1",
    "sg:province":"QC",
    "sg:tags":[
        "paging",
        "answering"
    ],
    "wof:name":"Centre Professionnels DE L'Est",
    "wof:placetype":"venue"
},
  "geometry": {"coordinates":[-73.41928863530001,45.7759284973],"type":"Point"}
}