{
  "type": "Feature",
  "properties": {
    "addr:full":"5247 River Rd Delta BC V4K 1S8",
    "addr:housenumber":"5247",
    "addr:postcode":"v4k 1s8",
    "addr:street":"River Rd",
    "iso:country":"CA",
    "sg:address":"5247 River Rd",
    "sg:city":"Delta",
    "sg:classifiers":[
        {
            "category":"Building & Trades",
            "subcategory":"Landscaping Services",
            "type":"Services"
        }
    ],
    "sg:phone":"+1 604 940 6423",
    "sg:postcode":"V4K 1S8",
    "sg:province":"BC",
    "sg:tags":[
        "lawn",
        "maintenance",
        "grounds"
    ],
    "wof:name":"Town & Country Gardens Ltd",
    "wof:placetype":"venue"
},
  "geometry": {"coordinates":[-123.078308105,49.0997428894],"type":"Point"}
}