{
  "type": "Feature",
  "properties": {
    "addr:full":"69 First St Collingwood ON L9Y 1A2",
    "addr:housenumber":"69",
    "addr:postcode":"l9y 1a2",
    "addr:street":"First St",
    "iso:country":"CA",
    "sg:address":"69 First St",
    "sg:city":"Collingwood",
    "sg:classifiers":[
        {
            "category":"Cinema",
            "subcategory":"Movie Rental",
            "type":"Entertainment"
        }
    ],
    "sg:phone":"+1 705 444 1047",
    "sg:postcode":"L9Y 1A2",
    "sg:province":"ON",
    "sg:tags":[
        "leasing",
        "video",
        "disc",
        "tape"
    ],
    "wof:name":"1 Stop Video",
    "wof:placetype":"venue"
},
  "geometry": {"coordinates":[-80.21933,44.502804],"type":"Point"}
}