{
  "type": "Feature",
  "properties": {
    "addr:full":"715 Circle Dr E Saskatoon SK S7K 0V1",
    "addr:housenumber":"715",
    "addr:postcode":"s7k 0v1",
    "addr:street":"Circle Dr E",
    "iso:country":"CA",
    "sg:address":"715 Circle Dr E",
    "sg:city":"Saskatoon",
    "sg:classifiers":[
        {
            "category":"Autos & Motor Vehicles",
            "subcategory":"Automobile Sales",
            "type":"Retail Goods"
        }
    ],
    "sg:phone":"+1 306 242 8498",
    "sg:postcode":"S7K 0V1",
    "sg:province":"SK",
    "sg:tags":[
        "car",
        "painting",
        "dealer"
    ],
    "wof:name":"Saskatoon Motor Products Clsn",
    "wof:placetype":"venue"
},
  "geometry": {"coordinates":[-106.656814575,52.157787323],"type":"Point"}
}