{
  "type": "Feature",
  "properties": {
    "addr:full":"North Vancouver BC V7P 2R4",
    "addr:postcode":"v7p 2r4",
    "iso:country":"CA",
    "sg:city":"North Vancouver",
    "sg:classifiers":[
        {
            "category":"Communications",
            "subcategory":"Film & Video Production",
            "type":"Services"
        }
    ],
    "sg:phone":"+1 604 988 5616",
    "sg:postcode":"V7P 2R4",
    "sg:province":"BC",
    "sg:tags":[
        "taping"
    ],
    "wof:name":"Mr Edit Video Svc",
    "wof:placetype":"venue"
},
  "geometry": {"coordinates":[-123.108109,49.317993],"type":"Point"}
}