{
  "type": "Feature",
  "properties": {
    "addr:full":"919 Rte Marie-Victorin Saint-Nicolas QC G7A 3T3",
    "addr:housenumber":"919",
    "addr:postcode":"g7a 3t3",
    "addr:street":"Rte Marie-Victorin",
    "iso:country":"CA",
    "sg:address":"919 Rte Marie-Victorin",
    "sg:city":"Saint-Nicolas",
    "sg:classifiers":[
        {
            "category":"Retail",
            "subcategory":"Auto Repair",
            "type":"Services"
        }
    ],
    "sg:phone":"+1 418 831 2828",
    "sg:postcode":"G7A 3T3",
    "sg:province":"QC",
    "sg:tags":[
        "repairing",
        "automobile"
    ],
    "wof:name":"Garage Remy Brochu Inc",
    "wof:placetype":"venue"
},
  "geometry": {"coordinates":[-71.354958,46.713367],"type":"Point"}
}