{
  "type": "Feature",
  "properties": {
    "addr:full":"563 Rue Principale St Leonard NB E7E 2J3",
    "addr:housenumber":"563",
    "addr:postcode":"e7e 2j3",
    "addr:street":"Rue Principale St",
    "iso:country":"CA",
    "sg:address":"563 Rue Principale",
    "sg:city":"St Leonard",
    "sg:classifiers":[
        {
            "category":"Home & Garden",
            "subcategory":"Hardware",
            "type":"Retail Goods"
        }
    ],
    "sg:phone":"+1 506 423 6114",
    "sg:postcode":"E7E 2J3",
    "sg:province":"NB",
    "wof:name":"Ray Quincaillerie Hardware",
    "wof:placetype":"venue"
},
  "geometry": {"coordinates":[-67.92765808110001,47.169670105],"type":"Point"}
}