{
  "type": "Feature",
  "properties": {
    "addr:full":"195 St David St S Fergus ON N1M 2L4",
    "addr:housenumber":"195",
    "addr:postcode":"n1m 2l4",
    "addr:street":"St David St S",
    "iso:country":"CA",
    "sg:address":"195 St David St S",
    "sg:city":"Fergus",
    "sg:classifiers":[
        {
            "category":"Professional",
            "subcategory":"Management & Consulting",
            "type":"Services"
        }
    ],
    "sg:phone":"+1 519 787 7830",
    "sg:postcode":"N1M 2L4",
    "sg:province":"ON",
    "sg:tags":[
        "consultant",
        "business"
    ],
    "wof:name":"Mallot Creek Group Inc",
    "wof:placetype":"venue"
},
  "geometry": {"coordinates":[-80.37689208979999,43.7053794861],"type":"Point"}
}