{
  "type": "Feature",
  "properties": {
    "addr:full":"57 Church St Flin Flon MB R8A 1K8",
    "addr:housenumber":"57",
    "addr:postcode":"r8a 1k8",
    "addr:street":"Church St",
    "iso:country":"CA",
    "sg:address":"57 Church St",
    "sg:city":"Flin Flon",
    "sg:classifiers":[
        {
            "category":"Organizations",
            "subcategory":"Professional Association",
            "type":"Services"
        }
    ],
    "sg:phone":"+1 204 687 3900",
    "sg:postcode":"R8A 1K8",
    "sg:province":"MB",
    "wof:name":"Flin Flon Indian Metis Friend",
    "wof:placetype":"venue"
},
  "geometry": {"coordinates":[-101.87758599999999,54.76614],"type":"Point"}
}