{
  "type": "Feature",
  "properties": {
    "addr:full":"5369 Maingate Dr Mississauga ON L4W 1G6",
    "addr:housenumber":"5369",
    "addr:postcode":"l4w 1g6",
    "addr:street":"Maingate Dr",
    "iso:country":"CA",
    "sg:address":"5369 Maingate Dr",
    "sg:city":"Mississauga",
    "sg:classifiers":[
        {
            "category":"Wholesale",
            "subcategory":"Machinery & Supplies",
            "type":"Manufacturing & Wholesale Goods"
        }
    ],
    "sg:phone":"+1 905 361 9978",
    "sg:postcode":"L4W 1G6",
    "sg:province":"ON",
    "sg:tags":[
        "plastic"
    ],
    "wof:name":"Future Design Inc",
    "wof:placetype":"venue"
},
  "geometry": {"coordinates":[-79.634209,43.635002],"type":"Point"}
}