{
  "type": "Feature",
  "properties": {
    "addr:full":"513 5E Av Grand-Mere QC G9T 2M5",
    "addr:housenumber":"513",
    "addr:postcode":"g9t 2m5",
    "addr:street":"5E Av Grand-Mere",
    "iso:country":"CA",
    "sg:address":"513 5E Av",
    "sg:city":"Grand-Mere",
    "sg:classifiers":[
        {
            "category":"Health Services",
            "subcategory":"Doctor",
            "type":"Services"
        }
    ],
    "sg:phone":"+1 819 533 5721",
    "sg:postcode":"G9T 2M5",
    "sg:province":"QC",
    "sg:tags":[
        "physician",
        "surgeon"
    ],
    "wof:name":"Tousignant, Michel P MD",
    "wof:placetype":"venue"
},
  "geometry": {"coordinates":[-72.689804,46.614773],"type":"Point"}
}