{
  "type": "Feature",
  "properties": {
    "addr:full":"12 Ontario S Grand Bend ON N0M 1T0",
    "addr:housenumber":"12",
    "addr:postcode":"n0m 1t0",
    "addr:street":"Ontario S",
    "iso:country":"CA",
    "sg:address":"12 Ontario S",
    "sg:city":"Grand Bend",
    "sg:classifiers":[
        {
            "category":"Restaurant",
            "type":"Food & Drink"
        }
    ],
    "sg:phone":"+1 519 238 8489",
    "sg:postcode":"N0M 1T0",
    "sg:province":"ON",
    "sg:tags":[
        "caterer"
    ],
    "wof:name":"Catering By Barbara",
    "wof:placetype":"venue"
},
  "geometry": {"coordinates":[-81.75732421879999,43.3112831116],"type":"Point"}
}