{
  "type": "Feature",
  "properties": {
    "addr:full":"Lloydminster AB T9V 2P7",
    "addr:postcode":"t9v 2p7",
    "iso:country":"CA",
    "sg:city":"Lloydminster",
    "sg:classifiers":[
        {
            "category":"Health Services",
            "subcategory":"Doctor",
            "type":"Services"
        }
    ],
    "sg:phone":"+1 780 875 2221",
    "sg:postcode":"T9V 2P7",
    "sg:province":"AB",
    "sg:tags":[
        "physician",
        "surgeon"
    ],
    "wof:name":"Naude, F P MD",
    "wof:placetype":"venue"
},
  "geometry": {"coordinates":[-110.00855300000001,53.280174],"type":"Point"}
}