{
  "type": "Feature",
  "properties": {
    "addr:full":"702 Connaught Dr Jasper AB T0E 1E0",
    "addr:housenumber":"702",
    "addr:postcode":"t0e 1e0",
    "addr:street":"Connaught Dr",
    "iso:country":"CA",
    "sg:address":"702 Connaught Dr",
    "sg:city":"Jasper",
    "sg:classifiers":[
        {
            "category":"Food & Beverages",
            "subcategory":"Liquor & Beverages",
            "type":"Retail Goods"
        }
    ],
    "sg:phone":"+1 780 852 7000",
    "sg:postcode":"T0E 1E0",
    "sg:province":"AB",
    "sg:tags":[
        "store"
    ],
    "wof:name":"Avalanche Spirits",
    "wof:placetype":"venue"
},
  "geometry": {"coordinates":[-118.082977,52.873085],"type":"Point"}
}