{
  "type": "Feature",
  "properties": {
    "addr:full":"48 Church St Brockville ON K6V 6L3",
    "addr:housenumber":"48",
    "addr:postcode":"k6v 6l3",
    "addr:street":"Church St",
    "iso:country":"CA",
    "sg:address":"48 Church St",
    "sg:city":"Brockville",
    "sg:classifiers":[
        {
            "category":"Real Estate",
            "subcategory":"Real Estate Operator",
            "type":"Services"
        }
    ],
    "sg:phone":"+1 613 345 2734",
    "sg:postcode":"K6V 6L3",
    "sg:province":"ON",
    "sg:tags":[
        "apartment"
    ],
    "wof:name":"Marguerita Residence Corp",
    "wof:placetype":"venue"
},
  "geometry": {"coordinates":[-75.68821699999999,44.58947],"type":"Point"}
}