{
  "type": "Feature",
  "properties": {
    "addr:full":"800 Boyd St New Westminster BC V3M 5G7",
    "addr:housenumber":"800",
    "addr:postcode":"v3m 5g7",
    "addr:street":"Boyd St",
    "iso:country":"CA",
    "sg:address":"800 Boyd St",
    "sg:city":"New Westminster",
    "sg:classifiers":[
        {
            "category":"Autos & Motor Vehicles",
            "subcategory":"Automobile Sales",
            "type":"Retail Goods"
        }
    ],
    "sg:phone":"+1 604 515 7253",
    "sg:postcode":"V3M 5G7",
    "sg:province":"BC",
    "sg:tags":[
        "car",
        "dealer"
    ],
    "wof:name":"Queensborough Trucking Ltd",
    "wof:placetype":"venue"
},
  "geometry": {"coordinates":[-122.94606,49.190937],"type":"Point"}
}