{
  "type": "Feature",
  "properties": {
    "addr:full":"132 Hartzell Rd St Catharines ON L2P 1N7",
    "addr:housenumber":"132",
    "addr:postcode":"l2p 1n7",
    "addr:street":"Hartzell Rd",
    "iso:country":"CA",
    "sg:address":"132 Hartzell Rd",
    "sg:city":"St Catharines",
    "sg:classifiers":[
        {
            "category":"Banks & Credit Unions",
            "subcategory":"Bank",
            "type":"Services"
        }
    ],
    "sg:phone":"+1 905 988 3699",
    "sg:postcode":"L2P 1N7",
    "sg:province":"ON",
    "sg:tags":[
        "cashing",
        "check"
    ],
    "wof:name":"Money Mart",
    "wof:placetype":"venue"
},
  "geometry": {"coordinates":[-79.2140655518,43.1497840881],"type":"Point"}
}