{
  "type": "Feature",
  "properties": {
    "iso:country":"CA",
    "sg:address":"2840 Southridge Dr",
    "sg:city":"Courtenay",
    "sg:classifiers":[
        {
            "category":"Building & Trades",
            "subcategory":"Construction",
            "type":"Services"
        }
    ],
    "sg:phone":"+1 250 334 8128",
    "sg:postcode":"V9N 9K2",
    "sg:province":"BC",
    "sg:tags":[
        "contractor"
    ],
    "wof:name":"John Westbrook Construction",
    "wof:placetype":"venue"
},
  "geometry": {"coordinates":[-124.993141174,49.6867218018],"type":"Point"}
}