{
  "type": "Feature",
  "properties": {
    "addr:full":"176 2nd Ave E Melville SK S0A 2P0",
    "addr:housenumber":"176",
    "addr:postcode":"s0a 2p0",
    "addr:street":"2Nd Ave E",
    "iso:country":"CA",
    "sg:address":"176 2nd Ave E",
    "sg:city":"Melville",
    "sg:classifiers":[
        {
            "category":"Food & Beverages",
            "subcategory":"Liquor & Beverages",
            "type":"Retail Goods"
        }
    ],
    "sg:phone":"+1 306 728 7440",
    "sg:postcode":"S0A 2P0",
    "sg:province":"SK",
    "sg:tags":[
        "store",
        "government"
    ],
    "wof:name":"Sask Liquor Board Store",
    "wof:placetype":"venue"
},
  "geometry": {"coordinates":[-102.80344390899999,50.9269065857],"type":"Point"}
}