{
  "type": "Feature",
  "properties": {
    "addr:full":"2033 Headon Forest Dr Burlington ON L7M 2M2",
    "addr:housenumber":"2033",
    "addr:postcode":"l7m 2m2",
    "addr:street":"Headon Forest Dr",
    "iso:country":"CA",
    "sg:address":"2033 Headon Forest Dr",
    "sg:city":"Burlington",
    "sg:classifiers":[
        {
            "category":"Education",
            "subcategory":"Special Training",
            "type":"Public Place"
        }
    ],
    "sg:phone":"+1 905 336 1739",
    "sg:postcode":"L7M 2M2",
    "sg:province":"ON",
    "sg:tags":[
        "management"
    ],
    "wof:name":"Murdoch Training Consultants",
    "wof:placetype":"venue"
},
  "geometry": {"coordinates":[-79.818237,43.370525],"type":"Point"}
}