{
  "type": "Feature",
  "properties": {
    "addr:full":"1470 Centre Rd Carlisle ON L0R 1H2",
    "addr:housenumber":"1470",
    "addr:postcode":"l0r 1h2",
    "addr:street":"Centre Rd",
    "iso:country":"CA",
    "sg:address":"1470 Centre Rd",
    "sg:city":"Carlisle",
    "sg:classifiers":[
        {
            "category":"Shopping",
            "subcategory":"Discount & Variety Stores",
            "type":"Retail Goods"
        }
    ],
    "sg:phone":"+1 905 689 6751",
    "sg:postcode":"L0R 1H2",
    "sg:province":"ON",
    "sg:tags":[
        "merchandise",
        "general"
    ],
    "wof:name":"Carlisle General Store",
    "wof:placetype":"venue"
},
  "geometry": {"coordinates":[-79.9798965454,43.3939666748],"type":"Point"}
}