{
  "type": "Feature",
  "properties": {
    "addr:full":"315 1st St W Nipawin SK S0E 1E0",
    "addr:housenumber":"315",
    "addr:postcode":"s0e 1e0",
    "addr:street":"1St St W Nipawin",
    "iso:country":"CA",
    "sg:address":"315 1st St W",
    "sg:city":"Nipawin",
    "sg:classifiers":[
        {
            "category":"Organizations",
            "subcategory":"Religious Organization",
            "type":"Services"
        }
    ],
    "sg:phone":"+1 306 862 3387",
    "sg:postcode":"S0E 1E0",
    "sg:province":"SK",
    "sg:tags":[
        "church"
    ],
    "wof:name":"Nipawin First Baptist Church",
    "wof:placetype":"venue"
},
  "geometry": {"coordinates":[-104.018227,53.361721],"type":"Point"}
}