{
  "type": "Feature",
  "properties": {
    "addr:full":"4197 Dugald Rd Winnipeg MB R2C 5K2",
    "addr:housenumber":"4197",
    "addr:postcode":"r2c 5k2",
    "addr:street":"Dugald Rd",
    "iso:country":"CA",
    "sg:address":"4197 Dugald Rd",
    "sg:city":"Winnipeg",
    "sg:classifiers":[
        {
            "category":"Freight",
            "type":"Transportation"
        }
    ],
    "sg:phone":"+1 204 222 7309",
    "sg:postcode":"R2C 5K2",
    "sg:province":"MB",
    "sg:tags":[
        "grain",
        "elevator"
    ],
    "wof:name":"Cargill Limited",
    "wof:placetype":"venue"
},
  "geometry": {"coordinates":[-96.97598266599999,49.8861808777],"type":"Point"}
}