{
  "type": "Feature",
  "properties": {
    "iso:country":"CA",
    "sg:address":"10 Halifax St",
    "sg:city":"Moncton",
    "sg:classifiers":[
        {
            "category":"Retail",
            "subcategory":"Auto Repair",
            "type":"Services"
        }
    ],
    "sg:phone":"+1 506 859 1887",
    "sg:postcode":"E1C 9P7",
    "sg:province":"NB",
    "sg:tags":[
        "repairing",
        "automobile"
    ],
    "wof:name":"Precision Auto Clinic",
    "wof:placetype":"venue"
},
  "geometry": {"coordinates":[-64.803291,46.095032],"type":"Point"}
}