{
  "type": "Feature",
  "properties": {
    "addr:full":"South Range Weymouth NS B0W 3T0",
    "addr:postcode":"b0w 3t0",
    "addr:street":"South Range",
    "iso:country":"CA",
    "sg:address":"South Range",
    "sg:city":"Weymouth",
    "sg:classifiers":[
        {
            "category":"Recreation",
            "type":"Entertainment"
        }
    ],
    "sg:phone":"+1 902 837 5751",
    "sg:postcode":"B0W 3T0",
    "sg:province":"NS",
    "sg:tags":[
        "center"
    ],
    "wof:name":"Johnston Christian Park",
    "wof:placetype":"venue"
},
  "geometry": {"coordinates":[-66.00505099999999,44.405445],"type":"Point"}
}