{
  "type": "Feature",
  "properties": {
    "iso:country":"CA",
    "sg:city":"Varennes",
    "sg:classifiers":[
        {
            "category":"Professional",
            "subcategory":"Management & Consulting",
            "type":"Services"
        }
    ],
    "sg:phone":"+1 450 652 4627",
    "sg:postcode":"J3X 1P7",
    "sg:province":"QC",
    "sg:tags":[
        "construction",
        "landscape",
        "contractor"
    ],
    "wof:name":"Valgeau Inc",
    "wof:placetype":"venue"
},
  "geometry": {"coordinates":[-73.418182,45.653667],"type":"Point"}
}