{
  "type": "Feature",
  "properties": {
    "addr:full":"652 Robson Dr Kamloops BC V2E 2B7",
    "addr:housenumber":"652",
    "addr:postcode":"bc v2e 2b7",
    "addr:street":"Robson Dr",
    "iso:country":"CA",
    "sg:address":"652 Robson Dr",
    "sg:city":"Kamloops",
    "sg:classifiers":[
        {
            "category":"Building & Trades",
            "subcategory":"Construction",
            "type":"Services"
        }
    ],
    "sg:phone":"+1 250 372 5705",
    "sg:postcode":"V2E 2B7",
    "sg:province":"BC",
    "sg:tags":[
        "insulation",
        "heat",
        "contractor"
    ],
    "wof:name":"P & R Insulation Contracting",
    "wof:placetype":"venue"
},
  "geometry": {"coordinates":[-120.354110718,50.64793396],"type":"Point"}
}