{
  "type": "Feature",
  "properties": {
    "addr:full":"Barrie ON L4M 3G1",
    "addr:postcode":"l4m 3g1",
    "iso:country":"CA",
    "sg:city":"Barrie",
    "sg:classifiers":[
        {
            "category":"Personal",
            "type":"Services"
        }
    ],
    "sg:phone":"+1 705 790 4255",
    "sg:postcode":"L4M 3G1",
    "sg:province":"ON",
    "sg:tags":[
        "therapist",
        "rehabilitation",
        "massage"
    ],
    "wof:name":"Moulton, Ken",
    "wof:placetype":"venue"
},
  "geometry": {"coordinates":[-79.69147491459999,44.3944778442],"type":"Point"}
}