{
  "type": "Feature",
  "properties": {
    "iso:country":"CA",
    "sg:address":"1446 Av DE Salaberry",
    "sg:city":"Chambly",
    "sg:classifiers":[
        {
            "category":"Building & Trades",
            "subcategory":"Construction",
            "type":"Services"
        }
    ],
    "sg:phone":"+1 450 447 1396",
    "sg:postcode":"J3L 4V9",
    "sg:province":"QC",
    "sg:tags":[
        "tile",
        "dealer"
    ],
    "wof:name":"Entreprises Roland Nadeau-Fils",
    "wof:placetype":"venue"
},
  "geometry": {"coordinates":[-73.30977630620001,45.4433822632],"type":"Point"}
}