{
  "type": "Feature",
  "properties": {
    "addr:full":"340 12E Av N Sherbrooke QC J1E 2W4",
    "addr:housenumber":"340",
    "addr:postcode":"j1e 2w4",
    "addr:street":"12E Av N",
    "iso:country":"CA",
    "sg:address":"340 12E Av N",
    "sg:city":"Sherbrooke",
    "sg:classifiers":[
        {
            "category":"Recreation",
            "type":"Entertainment"
        }
    ],
    "sg:phone":"+1 819 821 4148",
    "sg:postcode":"J1E 2W4",
    "sg:province":"QC",
    "sg:tags":[
        "martial",
        "arts",
        "instruction"
    ],
    "wof:name":"Ecoles Taikiken",
    "wof:placetype":"venue"
},
  "geometry": {"coordinates":[-71.871819,45.41375],"type":"Point"}
}