{
  "type": "Feature",
  "properties": {
    "addr:full":"PO Box 6687 STN Main Drayton Valley AB T7A 1S1",
    "addr:housenumber":"po",
    "addr:postcode":"6687;t7a 1s1",
    "addr:street":"Box;Stn Main",
    "iso:country":"CA",
    "sg:address":"PO Box 6687 STN Main",
    "sg:city":"Drayton Valley",
    "sg:classifiers":[
        {
            "category":"Taxi",
            "type":"Transportation"
        }
    ],
    "sg:phone":"+1 780 542 6666",
    "sg:postcode":"T7A 1S1",
    "sg:province":"AB",
    "sg:tags":[
        "taxicab"
    ],
    "wof:name":"Brass Cabs",
    "wof:placetype":"venue"
},
  "geometry": {"coordinates":[-114.98689299999999,53.227997],"type":"Point"}
}