{
  "type": "Feature",
  "properties": {
    "addr:full":"217 Robinson Ave Selkirk MB R1A 2M5",
    "addr:housenumber":"217",
    "addr:postcode":"r1a 2m5",
    "addr:street":"Robinson Ave",
    "iso:country":"CA",
    "sg:address":"217 Robinson Ave",
    "sg:city":"Selkirk",
    "sg:classifiers":[
        {
            "category":"Social Services",
            "type":"Services"
        }
    ],
    "sg:phone":"+1 204 482 9723",
    "sg:postcode":"R1A 2M5",
    "sg:province":"MB",
    "sg:tags":[
        "organization",
        "welfare"
    ],
    "wof:name":"Canadian Mental Health Assn",
    "wof:placetype":"venue"
},
  "geometry": {"coordinates":[-96.8667297363,50.1468811035],"type":"Point"}
}