{
  "type": "Feature",
  "properties": {
    "addr:full":"Zant Rd Gillies Bay BC V0N 1W0",
    "addr:postcode":"v0n 1w0",
    "addr:street":"Zant Rd",
    "iso:country":"CA",
    "sg:address":"Zant Rd",
    "sg:city":"Gillies Bay",
    "sg:classifiers":[
        {
            "category":"Retail",
            "subcategory":"Animal Services",
            "type":"Services"
        }
    ],
    "sg:phone":"+1 604 486 7825",
    "sg:postcode":"V0N 1W0",
    "sg:province":"BC",
    "sg:tags":[
        "breeder",
        "horse"
    ],
    "wof:name":"Blue Yonder Farms Inc",
    "wof:placetype":"venue"
},
  "geometry": {"coordinates":[-124.48484000000001,49.677422],"type":"Point"}
}