{
  "type": "Feature",
  "properties": {
    "addr:full":"PO Box 442 STN Main Qualicum Beach BC V9K 1S9",
    "addr:housenumber":"po",
    "addr:postcode":"v9k 1s9",
    "addr:street":"Box 442 Stn Main",
    "iso:country":"CA",
    "sg:address":"PO Box 442 STN Main",
    "sg:city":"Qualicum Beach",
    "sg:classifiers":[
        {
            "category":"Organizations",
            "subcategory":"Community Association",
            "type":"Services"
        }
    ],
    "sg:phone":"+1 250 716 9292",
    "sg:postcode":"V9K 1S9",
    "sg:province":"BC",
    "sg:tags":[
        "environmental",
        "org"
    ],
    "wof:name":"Western Canada Wilderness Comm",
    "wof:placetype":"venue"
},
  "geometry": {"coordinates":[-124.441704,49.346706],"type":"Point"}
}