{
  "type": "Feature",
  "properties": {
    "addr:full":"RR 1 STN Main Olds AB T4H 1P2",
    "addr:postcode":"t4h 1p2",
    "addr:street":"Rr 1 Stn Main",
    "iso:country":"CA",
    "sg:address":"RR 1 STN Main",
    "sg:city":"Olds",
    "sg:classifiers":[
        {
            "category":"Retail",
            "subcategory":"Portrait Studio",
            "type":"Services"
        }
    ],
    "sg:phone":"+1 403 507 0528",
    "sg:postcode":"T4H 1P2",
    "sg:province":"AB",
    "sg:tags":[
        "photographer"
    ],
    "wof:name":"Dream Catcher Photography",
    "wof:placetype":"venue"
},
  "geometry": {"coordinates":[-114.110610962,51.7916259766],"type":"Point"}
}