{
  "type": "Feature",
  "properties": {
    "addr:full":"Sainte-Thecle QC G0X 3G0",
    "addr:postcode":"g0x 3g0",
    "iso:country":"CA",
    "sg:city":"Sainte-Thecle",
    "sg:classifiers":[
        {
            "category":"Shopping",
            "subcategory":"Florist",
            "type":"Retail Goods"
        }
    ],
    "sg:phone":"+1 418 289 2110",
    "sg:postcode":"G0X 3G0",
    "sg:province":"QC",
    "wof:name":"Boutique Fleur DE Mai",
    "wof:placetype":"venue"
},
  "geometry": {"coordinates":[-72.505791,46.814907],"type":"Point"}
}