{
  "type": "Feature",
  "properties": {
    "addr:full":"Fleurimont QC J1H 5H2",
    "addr:postcode":"j1h 5h2",
    "iso:country":"CA",
    "sg:city":"Fleurimont",
    "sg:classifiers":[
        {
            "category":"Wholesale",
            "subcategory":"Electrical",
            "type":"Manufacturing & Wholesale Goods"
        }
    ],
    "sg:phone":"+1 819 562 6349",
    "sg:postcode":"J1H 5H2",
    "sg:province":"QC",
    "sg:tags":[
        "generator"
    ],
    "wof:name":"Generatrices Fleurimont Enr",
    "wof:placetype":"venue"
},
  "geometry": {"coordinates":[-71.822029,45.437477],"type":"Point"}
}