{
  "type": "Feature",
  "properties": {
    "addr:full":"1811 Boul DE Perigny Chambly QC J3L 4C3",
    "addr:housenumber":"1811",
    "addr:postcode":"j3l 4c3",
    "addr:street":"Boul De Perigny",
    "iso:country":"CA",
    "sg:address":"1811 Boul DE Perigny",
    "sg:city":"Chambly",
    "sg:classifiers":[
        {
            "category":"Autos & Motor Vehicles",
            "subcategory":"Auto Supplies",
            "type":"Retail Goods"
        }
    ],
    "sg:phone":"+1 450 658 4862",
    "sg:postcode":"J3L 4C3",
    "sg:province":"QC",
    "sg:tags":[
        "automobile",
        "parts"
    ],
    "wof:name":"Pieces D'Auto Fort Chambly",
    "wof:placetype":"venue"
},
  "geometry": {"coordinates":[-73.27510100000001,45.443001],"type":"Point"}
}