{
  "type": "Feature",
  "properties": {
    "addr:full":"703 Rue Mercier Longueuil QC J4K 3K1",
    "addr:housenumber":"703",
    "addr:postcode":"j4k 3k1",
    "addr:street":"Rue Mercier",
    "iso:country":"CA",
    "sg:address":"703 Rue Mercier",
    "sg:city":"Longueuil",
    "sg:classifiers":[
        {
            "category":"Building & Trades",
            "subcategory":"Electrical",
            "type":"Services"
        }
    ],
    "sg:phone":"+1 450 463 2172",
    "sg:postcode":"J4K 3K1",
    "sg:province":"QC",
    "sg:tags":[
        "electric",
        "contractor"
    ],
    "wof:name":"Ateliers Electriques Genelec",
    "wof:placetype":"venue"
},
  "geometry": {"coordinates":[-73.5106124878,45.5204238892],"type":"Point"}
}