{
  "type": "Feature",
  "properties": {
    "addr:full":"23 Avonlea Crt Fredericton NB E3C 1N8",
    "addr:housenumber":"23",
    "addr:postcode":"e3c 1n8",
    "addr:street":"Avonlea Crt",
    "iso:country":"CA",
    "sg:address":"23 Avonlea Crt",
    "sg:city":"Fredericton",
    "sg:classifiers":[
        {
            "category":"Professional",
            "subcategory":"Engineering",
            "type":"Services"
        }
    ],
    "sg:phone":"+1 506 457 1931",
    "sg:postcode":"E3C 1N8",
    "sg:province":"NB",
    "sg:tags":[
        "engineer"
    ],
    "wof:name":"E & I Engineering",
    "wof:placetype":"venue"
},
  "geometry": {"coordinates":[-66.689674,45.945656],"type":"Point"}
}