{
  "type": "Feature",
  "properties": {
    "addr:full":"17415 106A Ave NW Edmonton AB T5S 1M7",
    "addr:housenumber":"17415",
    "addr:postcode":"t5s 1m7",
    "addr:street":"106A Ave Nw",
    "iso:country":"CA",
    "sg:address":"17415 106A Ave NW",
    "sg:city":"Edmonton",
    "sg:classifiers":[
        {
            "category":"Recreation",
            "type":"Entertainment"
        }
    ],
    "sg:phone":"+1 780 413 0140",
    "sg:postcode":"T5S 1M7",
    "sg:province":"AB",
    "sg:tags":[
        "center"
    ],
    "wof:name":"Edmonton & District Soccer",
    "wof:placetype":"venue"
},
  "geometry": {"coordinates":[-113.62130000000001,53.551781],"type":"Point"}
}