{
  "type": "Feature",
  "properties": {
    "iso:country":"CA",
    "sg:address":"17415 106A Ave NW",
    "sg:city":"Edmonton",
    "sg:classifiers":[
        {
            "category":"Recreation",
            "type":"Entertainment"
        }
    ],
    "sg:phone":"+1 780 413 0140",
    "sg:postcode":"T5S 1M7",
    "sg:province":"AB",
    "sg:tags":[
        "center"
    ],
    "wof:name":"Edmonton & District Soccer",
    "wof:placetype":"venue"
},
  "geometry": {"coordinates":[-113.6213,53.551781],"type":"Point"}
}