{
  "type": "Feature",
  "properties": {
    "addr:full":"475 Boul Talbot Chicoutimi QC G7H 4A3",
    "addr:housenumber":"475",
    "addr:postcode":"g7h 4a3",
    "addr:street":"Boul Talbot",
    "iso:country":"CA",
    "sg:address":"475 Boul Talbot",
    "sg:city":"Chicoutimi",
    "sg:classifiers":[
        {
            "category":"Health Services",
            "subcategory":"Doctor",
            "type":"Services"
        }
    ],
    "sg:phone":"+1 418 549 1034",
    "sg:postcode":"G7H 4A3",
    "sg:province":"QC",
    "sg:tags":[
        "clinic"
    ],
    "wof:name":"Clinique DE Pediatrie",
    "wof:placetype":"venue"
},
  "geometry": {"coordinates":[-71.042473,48.422764],"type":"Point"}
}