{
  "type": "Feature",
  "properties": {
    "addr:full":"Quebec QC G1S 1S3",
    "addr:postcode":"g1s 1s3",
    "iso:country":"CA",
    "sg:city":"Quebec",
    "sg:classifiers":[
        {
            "category":"Health Services",
            "subcategory":"Health Practitioner",
            "type":"Services"
        }
    ],
    "sg:phone":"+1 418 527 8310",
    "sg:postcode":"G1S 1S3",
    "sg:province":"QC",
    "sg:tags":[
        "psychologist"
    ],
    "wof:name":"Roberge, Louise",
    "wof:placetype":"venue"
},
  "geometry": {"coordinates":[-71.22081799999999,46.807674],"type":"Point"}
}