{
  "type": "Feature",
  "properties": {
    "addr:full":"Stratford ON N5A 2P6",
    "addr:postcode":"n5a 2p6",
    "iso:country":"CA",
    "sg:city":"Stratford",
    "sg:classifiers":[
        {
            "category":"Home & Garden",
            "subcategory":"Building Materials",
            "type":"Retail Goods"
        }
    ],
    "sg:phone":"+1 519 271 3777",
    "sg:postcode":"N5A 2P6",
    "sg:province":"ON",
    "sg:tags":[
        "paint"
    ],
    "wof:name":"Whitelaw Automotive & Ind Supl",
    "wof:placetype":"venue"
},
  "geometry": {"coordinates":[-80.9999847412,43.3581809998],"type":"Point"}
}