{
  "type": "Feature",
  "properties": {
    "addr:full":"458 Queen St E Sault Ste Marie ON P6A 1Z7",
    "addr:housenumber":"458",
    "addr:postcode":"p6a 1z7",
    "addr:street":"Queen St E",
    "iso:country":"CA",
    "sg:address":"458 Queen St E",
    "sg:city":"Sault Ste Marie",
    "sg:classifiers":[
        {
            "category":"Travel",
            "subcategory":"Hotels & Motels",
            "type":"Entertainment"
        }
    ],
    "sg:phone":"+1 705 946 1511",
    "sg:postcode":"P6A 1Z7",
    "sg:province":"ON",
    "wof:name":"Reggie's Place Tavern",
    "wof:placetype":"venue"
},
  "geometry": {"coordinates":[-84.332329,46.511318],"type":"Point"}
}