{
  "type": "Feature",
  "properties": {
    "iso:country":"CA",
    "sg:address":"7700 Pine Valley Dr # 2A",
    "sg:city":"Woodbridge",
    "sg:classifiers":[
        {
            "category":"Restaurant",
            "type":"Food & Drink"
        }
    ],
    "sg:phone":"+1 905 851 7000",
    "sg:postcode":"L4L 2X4",
    "sg:province":"ON",
    "sg:tags":[
        "pizza"
    ],
    "wof:name":"Pizzeria & Panzerotti",
    "wof:placetype":"venue"
},
  "geometry": {"coordinates":[-79.5728759766,43.7824325562],"type":"Point"}
}