{
  "type": "Feature",
  "properties": {
    "addr:full":"224 Centre St Drumheller AB T0J 0Y0",
    "addr:housenumber":"224",
    "addr:postcode":"t0j 0y0",
    "addr:street":"Centre St",
    "iso:country":"CA",
    "sg:address":"224 Centre St",
    "sg:city":"Drumheller",
    "sg:classifiers":[
        {
            "category":"Education",
            "subcategory":"Library",
            "type":"Public Place"
        }
    ],
    "sg:phone":"+1 403 823 5382",
    "sg:postcode":"T0J 0Y0",
    "sg:province":"AB",
    "wof:name":"Drumheller Public Library",
    "wof:placetype":"venue"
},
  "geometry": {"coordinates":[-112.59180499999999,51.39521],"type":"Point"}
}