{
  "type": "Feature",
  "properties": {
    "addr:full":"1799 Garden St Sudbury ON P3A 5E7",
    "addr:housenumber":"1799",
    "addr:postcode":"p3a 5e7",
    "addr:street":"Garden St",
    "iso:country":"CA",
    "sg:address":"1799 Garden St",
    "sg:city":"Sudbury",
    "sg:classifiers":[
        {
            "category":"Sports & Exercise",
            "subcategory":"Bowling",
            "type":"Entertainment"
        }
    ],
    "sg:phone":"+1 705 566 0201",
    "sg:postcode":"P3A 5E7",
    "sg:province":"ON",
    "sg:tags":[
        "center"
    ],
    "wof:name":"Plaza Bowl",
    "wof:placetype":"venue"
},
  "geometry": {"coordinates":[-80.93248,46.520824],"type":"Point"}
}