{
  "type": "Feature",
  "properties": {
    "addr:full":"Montreal QC H4A 1T6",
    "addr:postcode":"h4a 1t6",
    "iso:country":"CA",
    "sg:city":"Montreal",
    "sg:classifiers":[
        {
            "category":"Shopping",
            "subcategory":"Computers & Home Electronics",
            "type":"Retail Goods"
        }
    ],
    "sg:phone":"+1 514 481 4866",
    "sg:postcode":"H4A 1T6",
    "sg:province":"QC",
    "sg:tags":[
        "equipment",
        "dealer"
    ],
    "wof:name":"Majestic Laser",
    "wof:placetype":"venue"
},
  "geometry": {"coordinates":[-73.5530548096,45.567905426],"type":"Point"}
}