{
  "type": "Feature",
  "properties": {
    "addr:full":"102 13E Rue Rouyn-Noranda QC J9X 5H7",
    "addr:housenumber":"102",
    "addr:postcode":"j9x 5h7",
    "addr:street":"13E Rue",
    "iso:country":"CA",
    "sg:address":"102 13E Rue",
    "sg:city":"Rouyn-Noranda",
    "sg:classifiers":[
        {
            "category":"Local Transit",
            "type":"Transportation"
        }
    ],
    "sg:phone":"+1 819 762 7368",
    "sg:postcode":"J9X 5H7",
    "sg:province":"QC",
    "sg:tags":[
        "handicapped"
    ],
    "wof:name":"Transport Adapte Les Intrepide",
    "wof:placetype":"venue"
},
  "geometry": {"coordinates":[-79.0288391113,48.2445716858],"type":"Point"}
}