{
  "type": "Feature",
  "properties": {
    "addr:full":"145 Henderson Dr Regina SK S4N 5W4",
    "addr:housenumber":"145",
    "addr:postcode":"s4n 5w4",
    "addr:street":"Henderson Dr",
    "iso:country":"CA",
    "sg:address":"145 Henderson Dr",
    "sg:city":"Regina",
    "sg:classifiers":[
        {
            "category":"Manufacturing",
            "subcategory":"Tools & Machinery",
            "type":"Manufacturing & Wholesale Goods"
        }
    ],
    "sg:phone":"+1 306 545 7575",
    "sg:postcode":"S4N 5W4",
    "sg:province":"SK",
    "sg:tags":[
        "farm",
        "equipment",
        "fertilizing"
    ],
    "wof:name":"Aim Material Handling Systems",
    "wof:placetype":"venue"
},
  "geometry": {"coordinates":[-104.568192,50.479313],"type":"Point"}
}