{
  "type": "Feature",
  "properties": {
    "iso:country":"CA",
    "sg:address":"95 First St",
    "sg:city":"Orangeville",
    "sg:classifiers":[
        {
            "category":"Manufacturing",
            "subcategory":"Food",
            "type":"Manufacturing & Wholesale Goods"
        }
    ],
    "sg:phone":"+1 519 940 4878",
    "sg:postcode":"L9W 2E8",
    "sg:province":"ON",
    "sg:tags":[
        "winery",
        "wine"
    ],
    "wof:name":"Wine Rack",
    "wof:placetype":"venue"
},
  "geometry": {"coordinates":[-80.09982299799999,43.9294433594],"type":"Point"}
}