{
  "type": "Feature",
  "properties": {
    "addr:full":"2508 Highway 125 Cochenour ON P0V 1L0",
    "addr:housenumber":"2508",
    "addr:postcode":"p0v 1l0",
    "addr:street":"Highway 125",
    "iso:country":"CA",
    "sg:address":"2508 Highway 125",
    "sg:city":"Cochenour",
    "sg:classifiers":[
        {
            "category":"Airport",
            "type":"Transportation"
        }
    ],
    "sg:phone":"+1 807 662 2315",
    "sg:postcode":"P0V 1L0",
    "sg:province":"ON",
    "sg:tags":[
        "aircraft",
        "maintenance"
    ],
    "wof:name":"Red Lake Sea Plane Svc",
    "wof:placetype":"venue"
},
  "geometry": {"coordinates":[-93.807716,51.07362],"type":"Point"}
}