{
  "type": "Feature",
  "properties": {
    "addr:full":"6962 Maple Brook Cres Regina SK S4X 4J3",
    "addr:housenumber":"6962",
    "addr:postcode":"s4x 4j3",
    "addr:street":"Maple Brook Cres",
    "iso:country":"CA",
    "sg:address":"6962 Maple Brook Cres",
    "sg:city":"Regina",
    "sg:classifiers":[
        {
            "category":"Freight",
            "type":"Transportation"
        }
    ],
    "sg:phone":"+1 306 543 1752",
    "sg:postcode":"S4X 4J3",
    "sg:province":"SK",
    "sg:tags":[
        "mover"
    ],
    "wof:name":"Erwins Moving & Delivery Ltd",
    "wof:placetype":"venue"
},
  "geometry": {"coordinates":[-104.681442,50.502651],"type":"Point"}
}