{
  "type": "Feature",
  "properties": {
    "addr:full":"1998 Vernon St Lumby BC V0E 2G0",
    "addr:housenumber":"1998",
    "addr:postcode":"v0e 2g0",
    "addr:street":"Vernon St",
    "iso:country":"CA",
    "sg:address":"1998 Vernon St",
    "sg:city":"Lumby",
    "sg:classifiers":[
        {
            "category":"Education",
            "subcategory":"School",
            "type":"Public Place"
        }
    ],
    "sg:phone":"+1 250 547 2593",
    "sg:postcode":"V0E 2G0",
    "sg:province":"BC",
    "wof:name":"Cross Roads Learning Ctr",
    "wof:placetype":"venue"
},
  "geometry": {"coordinates":[-118.966888428,50.2472686768],"type":"Point"}
}