{
  "type": "Feature",
  "properties": {
    "addr:full":"373 Boul Taschereau LA Prairie QC J5R 1T6",
    "addr:housenumber":"373",
    "addr:postcode":"j5r 1t6",
    "addr:street":"Boul Taschereau",
    "iso:country":"CA",
    "sg:address":"373 Boul Taschereau",
    "sg:city":"LA Prairie",
    "sg:classifiers":[
        {
            "category":"Retail",
            "subcategory":"Repair Shop",
            "type":"Services"
        }
    ],
    "sg:phone":"+1 450 659 1261",
    "sg:postcode":"J5R 1T6",
    "sg:province":"QC",
    "sg:tags":[
        "lock",
        "locksmith"
    ],
    "wof:name":"Serrurier Livernois Inc",
    "wof:placetype":"venue"
},
  "geometry": {"coordinates":[-73.49052399999999,45.414326],"type":"Point"}
}