{
  "type": "Feature",
  "properties": {
    "addr:full":"Monkland ON K0C 1V0",
    "addr:postcode":"k0c 1v0",
    "iso:country":"CA",
    "sg:city":"Monkland",
    "sg:classifiers":[
        {
            "category":"Shopping",
            "subcategory":"Used Merchandise",
            "type":"Retail Goods"
        }
    ],
    "sg:phone":"+1 613 346 5768",
    "sg:postcode":"K0C 1V0",
    "sg:province":"ON",
    "sg:tags":[
        "antique"
    ],
    "wof:name":"M & G Antiques",
    "wof:placetype":"venue"
},
  "geometry": {"coordinates":[-74.8792190552,45.1904563904],"type":"Point"}
}