{
  "type": "Feature",
  "properties": {
    "addr:full":"19370 36 Ave Surrey BC V3S 0L5",
    "addr:housenumber":"19370",
    "addr:postcode":"v3s 0l5",
    "addr:street":"36 Ave",
    "iso:country":"CA",
    "sg:address":"19370 36 Ave",
    "sg:city":"Surrey",
    "sg:classifiers":[
        {
            "category":"Building & Trades",
            "subcategory":"Construction",
            "type":"Services"
        }
    ],
    "sg:phone":"+1 604 576 8190",
    "sg:postcode":"V3S 0L5",
    "sg:province":"BC",
    "sg:tags":[
        "concrete",
        "waterproofing",
        "form",
        "contractor"
    ],
    "wof:name":"Superseal Basement Systems Ltd",
    "wof:placetype":"venue"
},
  "geometry": {"coordinates":[-122.686981,49.067253],"type":"Point"}
}