{
  "type": "Feature",
  "properties": {
    "addr:full":"2328 Keele St North York ON M6M 3Z8",
    "addr:housenumber":"2328",
    "addr:postcode":"m6m 3z8",
    "addr:street":"Keele St",
    "iso:country":"CA",
    "sg:address":"2328 Keele St",
    "sg:city":"North York",
    "sg:classifiers":[
        {
            "category":"Health Services",
            "subcategory":"Nursing And Care Facility",
            "type":"Services"
        }
    ],
    "sg:phone":"+1 416 249 1265",
    "sg:postcode":"M6M 3Z8",
    "sg:province":"ON",
    "sg:tags":[
        "home",
        "retirement",
        "community",
        "rest"
    ],
    "wof:name":"Sidmet Serenity Home",
    "wof:placetype":"venue"
},
  "geometry": {"coordinates":[-79.47714999999999,43.704082],"type":"Point"}
}