{
  "type": "Feature",
  "properties": {
    "addr:full":"Victoria BC V8Z 1L1",
    "addr:postcode":"v8z 1l1",
    "iso:country":"CA",
    "sg:city":"Victoria",
    "sg:classifiers":[
        {
            "category":"Home & Garden",
            "subcategory":"Building Materials",
            "type":"Retail Goods"
        }
    ],
    "sg:phone":"+1 250 479 5517",
    "sg:postcode":"V8Z 1L1",
    "sg:province":"BC",
    "sg:tags":[
        "glass",
        "window",
        "plate"
    ],
    "wof:name":"New Tint Technology Ltd",
    "wof:placetype":"venue"
},
  "geometry": {"coordinates":[-123.41326100000001,48.462135],"type":"Point"}
}