{
  "type": "Feature",
  "properties": {
    "iso:country":"CA",
    "sg:address":"506 10 St NW",
    "sg:city":"Calgary",
    "sg:classifiers":[
        {
            "category":"Restaurant",
            "type":"Food & Drink"
        }
    ],
    "sg:phone":"+1 403 216 8370",
    "sg:postcode":"T2N 1W3",
    "sg:province":"AB",
    "wof:name":"Wok-Tu-Yu Takeout & Delivery",
    "wof:placetype":"venue"
},
  "geometry": {"coordinates":[-114.085899,51.05706],"type":"Point"}
}