{
  "type": "Feature",
  "properties": {
    "iso:country":"CA",
    "sg:address":"15 Rideau Cres",
    "sg:city":"St Catharines",
    "sg:classifiers":[
        {
            "category":"Health Services",
            "subcategory":"Chiropractor",
            "type":"Services"
        }
    ],
    "sg:phone":"+1 905 935 4663",
    "sg:postcode":"L2M 2E8",
    "sg:province":"ON",
    "wof:name":"Paroyan, Patrick DC",
    "wof:placetype":"venue"
},
  "geometry": {"coordinates":[-79.221695,43.208199],"type":"Point"}
}