{
  "type": "Feature",
  "properties": {
    "addr:full":"Toronto ON M5E 1M1",
    "addr:postcode":"m5e 1m1",
    "iso:country":"CA",
    "sg:city":"Toronto",
    "sg:classifiers":[
        {
            "category":"Banks & Credit Unions",
            "subcategory":"Financial Services",
            "type":"Services"
        }
    ],
    "sg:phone":"+1 416 947 1266",
    "sg:postcode":"M5E 1M1",
    "sg:province":"ON",
    "sg:tags":[
        "annuity",
        "insurance"
    ],
    "wof:name":"Baxter Structures",
    "wof:placetype":"venue"
},
  "geometry": {"coordinates":[-79.373589,43.647518],"type":"Point"}
}