{
  "type": "Feature",
  "properties": {
    "addr:full":"34 Marshall Ave E North Bay ON P1A 1R1",
    "addr:housenumber":"34",
    "addr:postcode":"p1a 1r1",
    "addr:street":"Marshall Ave E",
    "iso:country":"CA",
    "sg:address":"34 Marshall Ave E",
    "sg:city":"North Bay",
    "sg:classifiers":[
        {
            "category":"Home & Garden",
            "subcategory":"Carpets & Floor Coverings",
            "type":"Retail Goods"
        }
    ],
    "sg:phone":"+1 705 497 0824",
    "sg:postcode":"P1A 1R1",
    "sg:province":"ON",
    "sg:tags":[
        "material",
        "rug"
    ],
    "wof:name":"Floor Fashion World",
    "wof:placetype":"venue"
},
  "geometry": {"coordinates":[-79.4441070557,46.2803192139],"type":"Point"}
}