{
  "type": "Feature",
  "properties": {
    "addr:full":"407 Wembley Rd Parksville BC V9P 2W9",
    "addr:housenumber":"407",
    "addr:postcode":"v9p 2w9",
    "addr:street":"Wembley Rd",
    "iso:country":"CA",
    "sg:address":"407 Wembley Rd",
    "sg:city":"Parksville",
    "sg:classifiers":[
        {
            "category":"Organizations",
            "subcategory":"Religious Organization",
            "type":"Services"
        }
    ],
    "sg:phone":"+1 250 248 3114",
    "sg:postcode":"V9P 2W9",
    "sg:province":"BC",
    "sg:tags":[
        "church"
    ],
    "wof:name":"Anglican Church of Parksville",
    "wof:placetype":"venue"
},
  "geometry": {"coordinates":[-124.343445,49.328857],"type":"Point"}
}