{
  "type": "Feature",
  "properties": {
    "addr:full":"Mississauga ON L5L 5R3",
    "addr:postcode":"l5l 5r3",
    "iso:country":"CA",
    "sg:city":"Mississauga",
    "sg:classifiers":[
        {
            "category":"Building & Trades",
            "subcategory":"Construction",
            "type":"Services"
        }
    ],
    "sg:phone":"+1 905 607 4181",
    "sg:postcode":"L5L 5R3",
    "sg:province":"ON",
    "sg:tags":[
        "painter"
    ],
    "wof:name":"Manley Decor",
    "wof:placetype":"venue"
},
  "geometry": {"coordinates":[-79.71896362299999,43.5306243896],"type":"Point"}
}