{
  "type": "Feature",
  "properties": {
    "addr:full":"Okanagan Falls BC V0H 1R0",
    "addr:postcode":"v0h 1r0",
    "iso:country":"CA",
    "sg:city":"Okanagan Falls",
    "sg:classifiers":[
        {
            "category":"Restaurant",
            "type":"Food & Drink"
        }
    ],
    "sg:phone":"+1 250 497 5957",
    "sg:postcode":"V0H 1R0",
    "sg:province":"BC",
    "wof:name":"Cactus Grill",
    "wof:placetype":"venue"
},
  "geometry": {"coordinates":[-119.571236,49.338634],"type":"Point"}
}