{
  "type": "Feature",
  "properties": {
    "addr:full":"396 Rue Principale Buckingham QC J8L 2G7",
    "addr:housenumber":"396",
    "addr:postcode":"j8l 2g7",
    "addr:street":"Rue Principale",
    "iso:country":"CA",
    "sg:address":"396 Rue Principale",
    "sg:city":"Buckingham",
    "sg:classifiers":[
        {
            "category":"Shopping",
            "subcategory":"Jewelry",
            "type":"Retail Goods"
        }
    ],
    "sg:phone":"+1 819 986 5121",
    "sg:postcode":"J8L 2G7",
    "sg:province":"QC",
    "sg:tags":[
        "jeweler"
    ],
    "wof:name":"Bijouterie Trudel Inc",
    "wof:placetype":"venue"
},
  "geometry": {"coordinates":[-75.415543,45.587673],"type":"Point"}
}