{
  "type": "Feature",
  "properties": {
    "addr:full":"5678 Production Way Langley BC V3A 4N4",
    "addr:housenumber":"5678",
    "addr:postcode":"v3a 4n4",
    "addr:street":"Production Way",
    "iso:country":"CA",
    "sg:address":"5678 Production Way",
    "sg:city":"Langley",
    "sg:classifiers":[
        {
            "category":"Building & Trades",
            "subcategory":"Construction",
            "type":"Services"
        }
    ],
    "sg:phone":"+1 604 539 8765",
    "sg:postcode":"V3A 4N4",
    "sg:province":"BC",
    "wof:name":"Canadian Shelters",
    "wof:placetype":"venue"
},
  "geometry": {"coordinates":[-122.677299499,49.1065559387],"type":"Point"}
}