{
  "type": "Feature",
  "properties": {
    "addr:full":"8000 Boul Decarie Montreal QC H4P 2S4",
    "addr:housenumber":"8000",
    "addr:postcode":"h4p 2s4",
    "addr:street":"Boul Decarie",
    "iso:country":"CA",
    "sg:address":"8000 Boul Decarie",
    "sg:city":"Montreal",
    "sg:classifiers":[
        {
            "category":"Banks & Credit Unions",
            "subcategory":"Bank",
            "type":"Services"
        }
    ],
    "sg:phone":"+1 514 342 6729",
    "sg:postcode":"H4P 2S4",
    "sg:province":"QC",
    "wof:name":"Cibc",
    "wof:placetype":"venue"
},
  "geometry": {"coordinates":[-73.6585845947,45.497253418],"type":"Point"}
}