{
  "type": "Feature",
  "properties": {
    "addr:full":"237 Main St S Newmarket ON L3Y 3Z4",
    "addr:housenumber":"237",
    "addr:postcode":"l3y 3z4",
    "addr:street":"Main St S",
    "iso:country":"CA",
    "sg:address":"237 Main St S",
    "sg:city":"Newmarket",
    "sg:classifiers":[
        {
            "category":"Food & Beverages",
            "subcategory":"Groceries & Convenience Stores",
            "type":"Retail Goods"
        }
    ],
    "sg:phone":"+1 905 895 3902",
    "sg:postcode":"L3Y 3Z4",
    "sg:province":"ON",
    "sg:tags":[
        "grocer"
    ],
    "wof:name":"Neighbourhood Variety",
    "wof:placetype":"venue"
},
  "geometry": {"coordinates":[-79.45658899999999,44.052341],"type":"Point"}
}