{
  "type": "Feature",
  "properties": {
    "addr:full":"901 Baker St Cranbrook BC V1C 1A4",
    "addr:housenumber":"901",
    "addr:postcode":"bc v1c 1a4",
    "addr:street":"Baker St",
    "iso:country":"CA",
    "sg:address":"901 Baker St",
    "sg:city":"Cranbrook",
    "sg:classifiers":[
        {
            "category":"Shopping",
            "subcategory":"Bicycles & Sporting Goods",
            "type":"Retail Goods"
        }
    ],
    "sg:phone":"+1 250 426 2717",
    "sg:postcode":"V1C 1A4",
    "sg:province":"BC",
    "wof:name":"Mountain Man Outdoors Ltd",
    "wof:placetype":"venue"
},
  "geometry": {"coordinates":[-115.76879099999999,49.512016],"type":"Point"}
}