{
  "type": "Feature",
  "properties": {
    "addr:full":"Milverton ON N0K 1M0",
    "addr:postcode":"n0k 1m0",
    "iso:country":"CA",
    "sg:city":"Milverton",
    "sg:classifiers":[
        {
            "category":"Personal",
            "subcategory":"Beauty Salon",
            "type":"Services"
        }
    ],
    "sg:phone":"+1 519 595 8540",
    "sg:postcode":"N0K 1M0",
    "sg:province":"ON",
    "sg:tags":[
        "tanning"
    ],
    "wof:name":"Carol's Exotic Tanning",
    "wof:placetype":"venue"
},
  "geometry": {"coordinates":[-80.9271850586,43.5596199036],"type":"Point"}
}