{
  "type": "Feature",
  "properties": {
    "addr:full":"Lachute QC J8H 1X4",
    "addr:postcode":"j8h 1x4",
    "iso:country":"CA",
    "sg:city":"Lachute",
    "sg:classifiers":[
        {
            "category":"Health Services",
            "subcategory":"Doctor",
            "type":"Services"
        }
    ],
    "sg:phone":"+1 450 562 4942",
    "sg:postcode":"J8H 1X4",
    "sg:province":"QC",
    "sg:tags":[
        "clinic",
        "dentist"
    ],
    "wof:name":"Roy & Roy",
    "wof:placetype":"venue"
},
  "geometry": {"coordinates":[-74.343727,45.651867],"type":"Point"}
}