{
  "type": "Feature",
  "properties": {
    "addr:full":"9575 Av Illinois Brossard QC J4Y 3A5",
    "addr:housenumber":"9575",
    "addr:postcode":"j4y 3a5",
    "addr:street":"Av Illinois",
    "iso:country":"CA",
    "sg:address":"9575 Av Illinois",
    "sg:city":"Brossard",
    "sg:classifiers":[
        {
            "category":"Retail",
            "subcategory":"Auto Repair",
            "type":"Services"
        }
    ],
    "sg:phone":"+1 450 659 8333",
    "sg:postcode":"J4Y 3A5",
    "sg:province":"QC",
    "sg:tags":[
        "repairing",
        "automobile"
    ],
    "wof:name":"Lee Automobile",
    "wof:placetype":"venue"
},
  "geometry": {"coordinates":[-73.4692,45.428463],"type":"Point"}
}