{
  "type": "Feature",
  "properties": {
    "addr:full":"8918 152 St Surrey BC V3R 4E4",
    "addr:housenumber":"8918",
    "addr:postcode":"v3r 4e4",
    "addr:street":"152 St",
    "iso:country":"CA",
    "sg:address":"8918 152 St",
    "sg:city":"Surrey",
    "sg:classifiers":[
        {
            "category":"Personal",
            "subcategory":"Beauty Salon",
            "type":"Services"
        }
    ],
    "sg:phone":"+1 604 589 7655",
    "sg:postcode":"V3R 4E4",
    "sg:province":"BC",
    "wof:name":"Studio 54 Hair Design Ltd",
    "wof:placetype":"venue"
},
  "geometry": {"coordinates":[-122.801254273,49.1649055481],"type":"Point"}
}