{
  "type": "Feature",
  "properties": {
    "iso:country":"CA",
    "sg:city":"Kenora",
    "sg:classifiers":[
        {
            "category":"Professional",
            "subcategory":"Research",
            "type":"Services"
        }
    ],
    "sg:phone":"+1 807 548 2383",
    "sg:postcode":"P9N 3W8",
    "sg:province":"ON",
    "sg:tags":[
        "environmental",
        "ecological"
    ],
    "wof:name":"Dst Consulting Engineers Inc",
    "wof:placetype":"venue"
},
  "geometry": {"coordinates":[-94.4626083374,49.7596817017],"type":"Point"}
}