{
  "type": "Feature",
  "properties": {
    "addr:full":"2208 Boul Rene-Levesque O Montreal QC H3H 1R6",
    "addr:housenumber":"2208",
    "addr:postcode":"h3h 1r6",
    "addr:street":"Boul Rene-Levesque O",
    "iso:country":"CA",
    "sg:address":"2208 Boul Rene-Levesque O",
    "sg:city":"Montreal",
    "sg:classifiers":[
        {
            "category":"Professional",
            "subcategory":"Business Services",
            "type":"Services"
        }
    ],
    "sg:phone":"+1 514 393 3138",
    "sg:postcode":"H3H 1R6",
    "sg:province":"QC",
    "sg:tags":[
        "notary"
    ],
    "wof:name":"Tetrault, Michel",
    "wof:placetype":"venue"
},
  "geometry": {"coordinates":[-73.58107,45.488663],"type":"Point"}
}