{
  "type": "Feature",
  "properties": {
    "addr:full":"791 27th Ave E Vancouver BC V5V 2K8",
    "addr:housenumber":"791",
    "addr:postcode":"v5v 2k8",
    "addr:street":"27Th Ave E",
    "iso:country":"CA",
    "sg:address":"791 27th Ave E",
    "sg:city":"Vancouver",
    "sg:classifiers":[
        {
            "category":"Organizations",
            "subcategory":"Religious Organization",
            "type":"Services"
        }
    ],
    "sg:phone":"+1 604 876 0630",
    "sg:postcode":"V5V 2K8",
    "sg:province":"BC",
    "sg:tags":[
        "church"
    ],
    "wof:name":"Ruth Morton Memorial Baptist",
    "wof:placetype":"venue"
},
  "geometry": {"coordinates":[-123.088096619,49.2467803955],"type":"Point"}
}