{
  "type": "Feature",
  "properties": {
    "iso:country":"CA",
    "sg:address":"1015 Boul Vachon N",
    "sg:city":"Sainte-Marie",
    "sg:classifiers":[
        {
            "category":"Food & Beverages",
            "subcategory":"Bakery",
            "type":"Retail Goods"
        }
    ],
    "sg:phone":"+1 418 387 8803",
    "sg:postcode":"G6E 1M3",
    "sg:province":"QC",
    "sg:tags":[
        "doughnut"
    ],
    "wof:name":"Dunkin Donuts",
    "wof:placetype":"venue"
},
  "geometry": {"coordinates":[-71.0316238403,46.4501495361],"type":"Point"}
}