{
  "type": "Feature",
  "properties": {
    "addr:full":"Etobicoke ON M9W 6K5",
    "addr:postcode":"m9w 6k5",
    "iso:country":"CA",
    "sg:city":"Etobicoke",
    "sg:classifiers":[
        {
            "category":"Personal",
            "subcategory":"Shoe Repair & Shine",
            "type":"Services"
        }
    ],
    "sg:phone":"+1 416 674 5937",
    "sg:postcode":"M9W 6K5",
    "sg:province":"ON",
    "sg:tags":[
        "repairing",
        "boot"
    ],
    "wof:name":"Royal Shoe Repair",
    "wof:placetype":"venue"
},
  "geometry": {"coordinates":[-79.5970840454,43.7178230286],"type":"Point"}
}