{
  "type": "Feature",
  "properties": {
    "addr:full":"1021 Waterdown Rd Burlington ON L7T 1N4",
    "addr:housenumber":"1021",
    "addr:postcode":"l7t 1n4",
    "addr:street":"Waterdown Rd",
    "iso:country":"CA",
    "sg:address":"1021 Waterdown Rd",
    "sg:city":"Burlington",
    "sg:classifiers":[
        {
            "category":"Retail",
            "subcategory":"Repair Shop",
            "type":"Services"
        }
    ],
    "sg:phone":"+1 905 633 9214",
    "sg:postcode":"L7T 1N4",
    "sg:province":"ON",
    "sg:tags":[
        "tool",
        "parts"
    ],
    "wof:name":"Bayshore Tool & Equipment",
    "wof:placetype":"venue"
},
  "geometry": {"coordinates":[-79.85335499999999,43.307426],"type":"Point"}
}