{
  "type": "Feature",
  "properties": {
    "addr:full":"4 Rowland Cres St Albert AB T8N 5B3",
    "addr:housenumber":"4",
    "addr:postcode":"t8n 5b3",
    "addr:street":"Rowland Cres",
    "iso:country":"CA",
    "sg:address":"4 Rowland Cres",
    "sg:city":"St Albert",
    "sg:classifiers":[
        {
            "category":"Building & Trades",
            "subcategory":"Construction",
            "type":"Services"
        }
    ],
    "sg:phone":"+1 780 459 5561",
    "sg:postcode":"T8N 5B3",
    "sg:province":"AB",
    "sg:tags":[
        "roofing",
        "contractor"
    ],
    "wof:name":"Jensen Roofing Ltd",
    "wof:placetype":"venue"
},
  "geometry": {"coordinates":[-113.646507,53.617702],"type":"Point"}
}