{
  "type": "Feature",
  "properties": {
    "addr:full":"77 Rue Amy Ayer's Cliff QC J0B 1C0",
    "addr:housenumber":"77",
    "addr:postcode":"j0b 1c0",
    "addr:street":"Rue Amy",
    "iso:country":"CA",
    "sg:address":"77 Rue Amy",
    "sg:city":"Ayer's Cliff",
    "sg:classifiers":[
        {
            "category":"Manufacturing",
            "subcategory":"Signs",
            "type":"Manufacturing & Wholesale Goods"
        }
    ],
    "sg:phone":"+1 819 876 7878",
    "sg:postcode":"J0B 1C0",
    "sg:province":"QC",
    "wof:name":"Sign Center Inc",
    "wof:placetype":"venue"
},
  "geometry": {"coordinates":[-72.0398101807,45.1666183472],"type":"Point"}
}