{
  "type": "Feature",
  "properties": {
    "addr:full":"4186 Sheppard Ave E Scarborough ON M1S 1T3",
    "addr:housenumber":"4186",
    "addr:postcode":"m1s 1t3",
    "addr:street":"Sheppard Ave E",
    "iso:country":"CA",
    "sg:address":"4186 Sheppard Ave E",
    "sg:city":"Scarborough",
    "sg:classifiers":[
        {
            "category":"Personal",
            "subcategory":"Beauty Salon",
            "type":"Services"
        }
    ],
    "sg:phone":"+1 416 298 4199",
    "sg:postcode":"M1S 1T3",
    "sg:province":"ON",
    "wof:name":"Cliff's Unisex Hair Place",
    "wof:placetype":"venue"
},
  "geometry": {"coordinates":[-79.2799072266,43.785194397],"type":"Point"}
}