{
  "type": "Feature",
  "properties": {
    "addr:full":"460 Rue Labelle # 203 Saint-Jerome QC J7Z 5L3",
    "addr:housenumber":"460",
    "addr:postcode":"j7z 5l3",
    "addr:street":"Rue Labelle # 203 Saint-Jerome",
    "iso:country":"CA",
    "sg:address":"460 Rue Labelle # 203",
    "sg:city":"Saint-Jerome",
    "sg:classifiers":[
        {
            "category":"Health Services",
            "subcategory":"Doctor",
            "type":"Services"
        }
    ],
    "sg:phone":"+1 450 436 3163",
    "sg:postcode":"J7Z 5L3",
    "sg:province":"QC",
    "sg:tags":[
        "dentist"
    ],
    "wof:name":"Forget, Joceyln DDS",
    "wof:placetype":"venue"
},
  "geometry": {"coordinates":[-74.0036849976,45.7799911499],"type":"Point"}
}