{
  "type": "Feature",
  "properties": {
    "addr:full":"165 Kerr Ave Dauphin MB R7N 3M7",
    "addr:housenumber":"165",
    "addr:postcode":"r7n 3m7",
    "addr:street":"Kerr Ave",
    "iso:country":"CA",
    "sg:address":"165 Kerr Ave",
    "sg:city":"Dauphin",
    "sg:classifiers":[
        {
            "category":"Social Services",
            "subcategory":"Child Care",
            "type":"Services"
        }
    ],
    "sg:phone":"+1 204 638 8263",
    "sg:postcode":"R7N 3M7",
    "sg:province":"MB",
    "wof:name":"Peter Pan Day Nursery",
    "wof:placetype":"venue"
},
  "geometry": {"coordinates":[-100.034897,51.147503],"type":"Point"}
}