{
  "type": "Feature",
  "properties": {
    "addr:full":"280 Metcalfe St # 402 Ottawa ON K2P 1R7",
    "addr:housenumber":"280",
    "addr:postcode":"k2p 1r7",
    "addr:street":"Metcalfe St # 402",
    "iso:country":"CA",
    "sg:address":"280 Metcalfe St # 402",
    "sg:city":"Ottawa",
    "sg:classifiers":[
        {
            "category":"Professional",
            "subcategory":"Lawyer & Legal Services",
            "type":"Services"
        }
    ],
    "sg:phone":"+1 613 567 1016",
    "sg:postcode":"K2P 1R7",
    "sg:province":"ON",
    "sg:tags":[
        "attorney"
    ],
    "wof:name":"Oliveira, Michael B",
    "wof:placetype":"venue"
},
  "geometry": {"coordinates":[-75.69149,45.415741],"type":"Point"}
}