{
  "type": "Feature",
  "properties": {
    "iso:country":"CA",
    "sg:address":"1590 Rue Semple",
    "sg:city":"Quebec",
    "sg:classifiers":[
        {
            "category":"Manufacturing",
            "subcategory":"Tools & Machinery",
            "type":"Manufacturing & Wholesale Goods"
        }
    ],
    "sg:phone":"+1 418 527 1197",
    "sg:postcode":"G1N 4B4",
    "sg:province":"QC",
    "sg:tags":[
        "machine",
        "vending"
    ],
    "wof:name":"Equipements L'Heureux",
    "wof:placetype":"venue"
},
  "geometry": {"coordinates":[-71.26583862299999,46.7992553711],"type":"Point"}
}