{
  "type": "Feature",
  "properties": {
    "addr:full":"740 2nd Ave E Owen Sound ON N4K 2H1",
    "addr:housenumber":"740",
    "addr:postcode":"n4k 2h1",
    "addr:street":"2Nd Ave E",
    "iso:country":"CA",
    "sg:address":"740 2nd Ave E",
    "sg:city":"Owen Sound",
    "sg:classifiers":[
        {
            "category":"Retail",
            "subcategory":"Auto Repair",
            "type":"Services"
        }
    ],
    "sg:phone":"+1 519 372 2473",
    "sg:postcode":"N4K 2H1",
    "sg:province":"ON",
    "sg:tags":[
        "automobile",
        "rustproofing",
        "undercoating",
        "clean",
        "detail"
    ],
    "wof:name":"Mac Kinnon Motors",
    "wof:placetype":"venue"
},
  "geometry": {"coordinates":[-80.9423294067,44.5628242493],"type":"Point"}
}