{
  "type": "Feature",
  "properties": {
    "addr:full":"8115 Fraser Ave Fort Mcmurray AB T9H 1W5",
    "addr:housenumber":"8115",
    "addr:postcode":"t9h 1w5",
    "addr:street":"Fraser Ave",
    "iso:country":"CA",
    "sg:address":"8115 Fraser Ave",
    "sg:city":"Fort Mcmurray",
    "sg:classifiers":[
        {
            "category":"Food & Beverages",
            "subcategory":"Specialty",
            "type":"Retail Goods"
        }
    ],
    "sg:phone":"+1 780 790 0716",
    "sg:postcode":"T9H 1W5",
    "sg:province":"AB",
    "sg:tags":[
        "water",
        "bulk",
        "company"
    ],
    "wof:name":"Water Pure & Simple",
    "wof:placetype":"venue"
},
  "geometry": {"coordinates":[-111.34542083700001,56.7159385681],"type":"Point"}
}