{
  "type": "Feature",
  "properties": {
    "iso:country":"CA",
    "sg:address":"5015 48 St",
    "sg:city":"Red Deer",
    "sg:classifiers":[
        {
            "category":"Wholesale",
            "subcategory":"Medical Equipment & Supplies",
            "type":"Manufacturing & Wholesale Goods"
        }
    ],
    "sg:phone":"+1 403 340 3131",
    "sg:postcode":"T4N 1S9",
    "sg:province":"AB",
    "sg:tags":[
        "physician",
        "surgeon"
    ],
    "wof:name":"Healthcare & Rehab Specialties",
    "wof:placetype":"venue"
},
  "geometry": {"coordinates":[-113.81632232699999,52.266910553],"type":"Point"}
}