{
  "type": "Feature",
  "properties": {
    "addr:full":"37 Talbot St E Leamington ON N8H 1L1",
    "addr:housenumber":"37",
    "addr:postcode":"n8h 1l1",
    "addr:street":"Talbot St E",
    "iso:country":"CA",
    "sg:address":"37 Talbot St E",
    "sg:city":"Leamington",
    "sg:classifiers":[
        {
            "category":"Retail",
            "subcategory":"Laundry & Dry Cleaning",
            "type":"Services"
        }
    ],
    "sg:phone":"+1 519 326 3645",
    "sg:postcode":"N8H 1L1",
    "sg:province":"ON",
    "sg:tags":[
        "cleaners"
    ],
    "wof:name":"Kennedy's Cleaners",
    "wof:placetype":"venue"
},
  "geometry": {"coordinates":[-82.59889200000001,42.053459],"type":"Point"}
}