{
  "type": "Feature",
  "properties": {
    "iso:country":"CA",
    "sg:city":"Markham",
    "sg:classifiers":[
        {
            "category":"Manufacturing",
            "subcategory":"Furniture",
            "type":"Manufacturing & Wholesale Goods"
        }
    ],
    "sg:phone":"+1 905 947 8374",
    "sg:postcode":"L3R 0H7",
    "sg:province":"ON",
    "wof:name":"Ene Laminating & Kitchen Ltd",
    "wof:placetype":"venue"
},
  "geometry": {"coordinates":[-79.340622,43.83477],"type":"Point"}
}