{
  "type": "Feature",
  "properties": {
    "addr:full":"Surrey BC V3W 0K6",
    "addr:postcode":"v3w 0k6",
    "iso:country":"CA",
    "sg:city":"Surrey",
    "sg:classifiers":[
        {
            "category":"Professional",
            "subcategory":"Business Services",
            "type":"Services"
        }
    ],
    "sg:phone":"+1 604 596 0209",
    "sg:postcode":"V3W 0K6",
    "sg:province":"BC",
    "sg:tags":[
        "embroidery"
    ],
    "wof:name":"Smj Foreign Crafts",
    "wof:placetype":"venue"
},
  "geometry": {"coordinates":[-122.862694,49.155266],"type":"Point"}
}