{
  "type": "Feature",
  "properties": {
    "addr:full":"185 Rue Sainte-Anne Rimouski QC G5L 4H2",
    "addr:housenumber":"185",
    "addr:postcode":"g5l 4h2",
    "addr:street":"Rue Sainte-Anne",
    "iso:country":"CA",
    "sg:address":"185 Rue Sainte-Anne",
    "sg:city":"Rimouski",
    "sg:classifiers":[
        {
            "category":"Education",
            "subcategory":"Special Training",
            "type":"Public Place"
        }
    ],
    "sg:phone":"+1 418 722 1997",
    "sg:postcode":"G5L 4H2",
    "sg:province":"QC",
    "sg:tags":[
        "instruction",
        "driving"
    ],
    "wof:name":"Ecole Alpha DE Conduite",
    "wof:placetype":"venue"
},
  "geometry": {"coordinates":[-68.53182983400001,48.4450798035],"type":"Point"}
}