{
  "type": "Feature",
  "properties": {
    "addr:full":"3 Water St Summerside PE C1N 1A2",
    "addr:housenumber":"3",
    "addr:postcode":"c1n 1a2",
    "addr:street":"Water St",
    "iso:country":"CA",
    "sg:address":"3 Water St",
    "sg:city":"Summerside",
    "sg:classifiers":[
        {
            "category":"Autos & Motor Vehicles",
            "subcategory":"Automobile Sales",
            "type":"Retail Goods"
        }
    ],
    "sg:phone":"+1 902 436 9141",
    "sg:postcode":"C1N 1A2",
    "sg:province":"PE",
    "sg:tags":[
        "car",
        "dealer"
    ],
    "wof:name":"Summerside Chrysler Dodge Ltd",
    "wof:placetype":"venue"
},
  "geometry": {"coordinates":[-63.772633,46.392845],"type":"Point"}
}