{
  "type": "Feature",
  "properties": {
    "addr:full":"276 Rue Saint-Joseph LA Tuque QC G9X 1K7",
    "addr:housenumber":"276",
    "addr:postcode":"g9x 1k7",
    "addr:street":"Rue Saint-Joseph",
    "iso:country":"CA",
    "sg:address":"276 Rue Saint-Joseph",
    "sg:city":"LA Tuque",
    "sg:classifiers":[
        {
            "category":"Bars & Pubs",
            "type":"Food & Drink"
        }
    ],
    "sg:phone":"+1 819 523 9460",
    "sg:postcode":"G9X 1K7",
    "sg:province":"QC",
    "wof:name":"Brassette Du Coin",
    "wof:placetype":"venue"
},
  "geometry": {"coordinates":[-72.786789,47.441067],"type":"Point"}
}