{
  "type": "Feature",
  "properties": {
    "addr:full":"1340 32E Av Pointe-Aux-Trembles QC H1A 3L6",
    "addr:housenumber":"1340",
    "addr:postcode":"h1a 3l6",
    "addr:street":"32E Av Pointe-Aux-Trembles",
    "iso:country":"CA",
    "sg:address":"1340 32E Av",
    "sg:city":"Pointe-Aux-Trembles",
    "sg:classifiers":[
        {
            "category":"Professional",
            "subcategory":"Computer Services",
            "type":"Services"
        }
    ],
    "sg:phone":"+1 514 498 8668",
    "sg:postcode":"H1A 3L6",
    "sg:province":"QC",
    "sg:tags":[
        "internet"
    ],
    "wof:name":"Netsocius Consultant Inc",
    "wof:placetype":"venue"
},
  "geometry": {"coordinates":[-73.49884,45.656826],"type":"Point"}
}