{
  "type": "Feature",
  "properties": {
    "addr:full":"919 Boul Maloney E Gatineau QC J8P 1H7",
    "addr:housenumber":"919",
    "addr:postcode":"j8p 1h7",
    "addr:street":"Boul Maloney E",
    "iso:country":"CA",
    "sg:address":"919 Boul Maloney E",
    "sg:city":"Gatineau",
    "sg:classifiers":[
        {
            "category":"Retail",
            "subcategory":"Auto Repair",
            "type":"Services"
        }
    ],
    "sg:phone":"+1 819 663 7789",
    "sg:postcode":"J8P 1H7",
    "sg:province":"QC",
    "sg:tags":[
        "repairing",
        "automobile"
    ],
    "wof:name":"Gatineau Spring Svc",
    "wof:placetype":"venue"
},
  "geometry": {"coordinates":[-75.594353,45.49065],"type":"Point"}
}