{
  "type": "Feature",
  "properties": {
    "addr:full":"Edmonton AB T5J 3L9",
    "addr:postcode":"t5j 3l9",
    "iso:country":"CA",
    "sg:city":"Edmonton",
    "sg:classifiers":[
        {
            "category":"Professional",
            "subcategory":"Lawyer & Legal Services",
            "type":"Services"
        }
    ],
    "sg:phone":"+1 780 423 5792",
    "sg:postcode":"T5J 3L9",
    "sg:province":"AB",
    "sg:tags":[
        "attorney"
    ],
    "wof:name":"Malhotra & CO",
    "wof:placetype":"venue"
},
  "geometry": {"coordinates":[-113.508743,53.540703],"type":"Point"}
}