{
  "type": "Feature",
  "properties": {
    "addr:full":"306 Athabascan Ave Sherwood Park AB T8A 3X7",
    "addr:housenumber":"306",
    "addr:postcode":"t8a 3x7",
    "addr:street":"Athabascan Ave",
    "iso:country":"CA",
    "sg:address":"306 Athabascan Ave",
    "sg:city":"Sherwood Park",
    "sg:classifiers":[
        {
            "category":"Shopping",
            "subcategory":"Musical Instruments",
            "type":"Retail Goods"
        }
    ],
    "sg:phone":"+1 780 467 5537",
    "sg:postcode":"T8A 3X7",
    "sg:province":"AB",
    "sg:tags":[
        "instruction",
        "music",
        "dealer"
    ],
    "wof:name":"Sherwood Park School of Music",
    "wof:placetype":"venue"
},
  "geometry": {"coordinates":[-113.329033,53.535503],"type":"Point"}
}