{
  "type": "Feature",
  "properties": {
    "iso:country":"CA",
    "sg:address":"1305 Rue Des Seigneurs",
    "sg:city":"Sainte-Foy",
    "sg:classifiers":[
        {
            "category":"Building & Trades",
            "subcategory":"Cleaning & Sanitation",
            "type":"Services"
        }
    ],
    "sg:phone":"+1 418 261 8111",
    "sg:postcode":"G1W 3H8",
    "sg:province":"QC",
    "sg:tags":[
        "snow",
        "removal"
    ],
    "wof:name":"Deneigement Maurice Martin",
    "wof:placetype":"venue"
},
  "geometry": {"coordinates":[-71.277626,46.766487],"type":"Point"}
}