{
  "type": "Feature",
  "properties": {
    "addr:full":"5660 Charles St Halifax NS B3K 1K4",
    "addr:housenumber":"5660",
    "addr:postcode":"b3k 1k4",
    "addr:street":"Charles St",
    "iso:country":"CA",
    "sg:address":"5660 Charles St",
    "sg:city":"Halifax",
    "sg:classifiers":[
        {
            "category":"Retail",
            "subcategory":"Auto Repair",
            "type":"Services"
        }
    ],
    "sg:phone":"+1 902 425 0088",
    "sg:postcode":"B3K 1K4",
    "sg:province":"NS",
    "sg:tags":[
        "body",
        "automobile",
        "painting"
    ],
    "wof:name":"Aris & B Auto Body",
    "wof:placetype":"venue"
},
  "geometry": {"coordinates":[-63.591152,44.65506],"type":"Point"}
}