{
  "type": "Feature",
  "properties": {
    "addr:full":"Vancouver BC V6J 5B3",
    "addr:postcode":"v6j 5b3",
    "iso:country":"CA",
    "sg:city":"Vancouver",
    "sg:classifiers":[
        {
            "category":"Real Estate",
            "subcategory":"Architect",
            "type":"Services"
        }
    ],
    "sg:phone":"+1 604 733 3125",
    "sg:postcode":"V6J 5B3",
    "sg:province":"BC",
    "sg:tags":[
        "specification",
        "architectural"
    ],
    "wof:name":"Creekside Architects",
    "wof:placetype":"venue"
},
  "geometry": {"coordinates":[-123.140403748,49.2731742859],"type":"Point"}
}