{
  "type": "Feature",
  "properties": {
    "addr:full":"Baie-Saint-Paul QC G3Z 2Y5",
    "addr:postcode":"g3z 2y5",
    "iso:country":"CA",
    "sg:city":"Baie-Saint-Paul",
    "sg:classifiers":[
        {
            "category":"Shopping",
            "subcategory":"Department Store",
            "type":"Retail Goods"
        }
    ],
    "sg:phone":"+1 418 435 6545",
    "sg:postcode":"G3Z 2Y5",
    "sg:province":"QC",
    "wof:name":"Magasin Hart",
    "wof:placetype":"venue"
},
  "geometry": {"coordinates":[-70.51750199999999,47.447529],"type":"Point"}
}