{
  "type": "Feature",
  "properties": {
    "addr:full":"1550 Rue Du Couvent Saint-Gilles QC G0S 2P0",
    "addr:housenumber":"1550",
    "addr:postcode":"g0s 2p0",
    "addr:street":"Rue Du Couvent",
    "iso:country":"CA",
    "sg:address":"1550 Rue Du Couvent",
    "sg:city":"Saint-Gilles",
    "sg:classifiers":[
        {
            "category":"Education",
            "subcategory":"School",
            "type":"Public Place"
        }
    ],
    "sg:phone":"+1 418 888 4210",
    "sg:postcode":"G0S 2P0",
    "sg:province":"QC",
    "wof:name":"Ecole Etienne Chartier",
    "wof:placetype":"venue"
},
  "geometry": {"coordinates":[-71.362808,46.506691],"type":"Point"}
}