{
  "type": "Feature",
  "properties": {
    "addr:full":"Madoc ON K0K 2K0",
    "addr:postcode":"k0k 2k0",
    "iso:country":"CA",
    "sg:city":"Madoc",
    "sg:classifiers":[
        {
            "category":"Manufacturing",
            "subcategory":"Tools & Machinery",
            "type":"Manufacturing & Wholesale Goods"
        }
    ],
    "sg:phone":"+1 613 473 4122",
    "sg:postcode":"K0K 2K0",
    "sg:province":"ON",
    "sg:tags":[
        "woodworking"
    ],
    "wof:name":"Brettwood Machinery Works Ltd",
    "wof:placetype":"venue"
},
  "geometry": {"coordinates":[-77.5025024414,44.555103302],"type":"Point"}
}