{
  "type": "Feature",
  "properties": {
    "addr:full":"160 Boul Edgar-Hebert Melocheville QC J0S 1J0",
    "addr:housenumber":"160",
    "addr:postcode":"j0s 1j0",
    "addr:street":"Boul Edgar-Hebert",
    "iso:country":"CA",
    "sg:address":"160 Boul Edgar-Hebert",
    "sg:city":"Melocheville",
    "sg:classifiers":[
        {
            "category":"Manufacturing",
            "subcategory":"Printing",
            "type":"Manufacturing & Wholesale Goods"
        }
    ],
    "sg:phone":"+1 450 225 3141",
    "sg:postcode":"J0S 1J0",
    "sg:province":"QC",
    "sg:tags":[
        "screen"
    ],
    "wof:name":"Imag in",
    "wof:placetype":"venue"
},
  "geometry": {"coordinates":[-73.93438,45.316448],"type":"Point"}
}