{
  "type": "Feature",
  "properties": {
    "addr:full":"1353 Rue Belvedere S Sherbrooke QC J1H 4E4",
    "addr:housenumber":"1353",
    "addr:postcode":"j1h 4e4",
    "addr:street":"Rue Belvedere S",
    "iso:country":"CA",
    "sg:address":"1353 Rue Belvedere S",
    "sg:city":"Sherbrooke",
    "sg:classifiers":[
        {
            "category":"Cinema",
            "subcategory":"Movie Rental",
            "type":"Entertainment"
        }
    ],
    "sg:phone":"+1 819 822 1544",
    "sg:postcode":"J1H 4E4",
    "sg:province":"QC",
    "sg:tags":[
        "leasing",
        "video",
        "disc",
        "tape"
    ],
    "wof:name":"Club Internationale Video Film",
    "wof:placetype":"venue"
},
  "geometry": {"coordinates":[-71.89572143549999,45.3854026794],"type":"Point"}
}