{
  "type": "Feature",
  "properties": {
    "iso:country":"CA",
    "sg:city":"Waterloo",
    "sg:classifiers":[
        {
            "category":"Personal",
            "subcategory":"Beauty Salon",
            "type":"Services"
        }
    ],
    "sg:phone":"+1 519 571 1540",
    "sg:postcode":"N2K 4C9",
    "sg:province":"ON",
    "wof:name":"Bliss Hair & Skin Care Studio",
    "wof:placetype":"venue"
},
  "geometry": {"coordinates":[-80.4918670654,43.4907569885],"type":"Point"}
}