{
  "type": "Feature",
  "properties": {
    "addr:full":"2050 Hall Rd Courtenay BC V9J 1Y5",
    "addr:housenumber":"2050",
    "addr:postcode":"v9j 1y5",
    "addr:street":"Hall Rd",
    "iso:country":"CA",
    "sg:address":"2050 Hall Rd",
    "sg:city":"Courtenay",
    "sg:classifiers":[
        {
            "category":"Professional",
            "subcategory":"Business Services",
            "type":"Services"
        }
    ],
    "sg:phone":"+1 250 792 0310",
    "sg:postcode":"V9J 1Y5",
    "sg:province":"BC",
    "sg:tags":[
        "inspection"
    ],
    "wof:name":"Home Inspection By Stephen",
    "wof:placetype":"venue"
},
  "geometry": {"coordinates":[-124.993141174,49.6867218018],"type":"Point"}
}