{
  "type": "Feature",
  "properties": {
    "addr:full":"9799 Route 105 Beechwood NB E7J 1W2",
    "addr:housenumber":"9799",
    "addr:postcode":"e7j 1w2",
    "addr:street":"Route 105",
    "iso:country":"CA",
    "sg:address":"9799 Route 105",
    "sg:city":"Beechwood",
    "sg:classifiers":[
        {
            "category":"Retail",
            "subcategory":"Auto Repair",
            "type":"Services"
        }
    ],
    "sg:phone":"+1 506 278 3192",
    "sg:postcode":"E7J 1W2",
    "sg:province":"NB",
    "sg:tags":[
        "repairing",
        "automobile"
    ],
    "wof:name":"Gorey's Auto Repair",
    "wof:placetype":"venue"
},
  "geometry": {"coordinates":[-67.66037,46.543228],"type":"Point"}
}