{
  "type": "Feature",
  "properties": {
    "addr:full":"21 Rte Norbert-Morin LA Durantaye QC G0R 1W0",
    "addr:housenumber":"21",
    "addr:postcode":"g0r 1w0",
    "addr:street":"Rte Norbert-Morin",
    "iso:country":"CA",
    "sg:address":"21 Rte Norbert-Morin",
    "sg:city":"LA Durantaye",
    "sg:classifiers":[
        {
            "category":"Personal",
            "subcategory":"Beauty Salon",
            "type":"Services"
        }
    ],
    "sg:phone":"+1 418 884 2420",
    "sg:postcode":"G0R 1W0",
    "sg:province":"QC",
    "wof:name":"Salon Lyne Mercier",
    "wof:placetype":"venue"
},
  "geometry": {"coordinates":[-70.85475158689999,46.8356513977],"type":"Point"}
}