{
  "type": "Feature",
  "properties": {
    "addr:full":"113 Rte Marie Victorin Pierreville QC J0G 1J0",
    "addr:housenumber":"113",
    "addr:postcode":"j0g 1j0",
    "addr:street":"Rte Marie Victorin",
    "iso:country":"CA",
    "sg:address":"113 Rte Marie Victorin",
    "sg:city":"Pierreville",
    "sg:classifiers":[
        {
            "category":"Building & Trades",
            "subcategory":"Construction",
            "type":"Services"
        }
    ],
    "sg:phone":"+1 450 568 2979",
    "sg:postcode":"J0G 1J0",
    "sg:province":"QC",
    "sg:tags":[
        "excavating",
        "contractor"
    ],
    "wof:name":"Maurice Lauziere Soudure Enr",
    "wof:placetype":"venue"
},
  "geometry": {"coordinates":[-72.767715,46.09827],"type":"Point"}
}