{
  "type": "Feature",
  "properties": {
    "iso:country":"CA",
    "sg:address":"3999 Rue Saint-Denis",
    "sg:city":"Montreal",
    "sg:classifiers":[
        {
            "category":"Home & Garden",
            "subcategory":"Home Furnishings",
            "type":"Retail Goods"
        }
    ],
    "sg:phone":"+1 514 847 0729",
    "sg:postcode":"H2W 2M4",
    "sg:province":"QC",
    "sg:tags":[
        "linen"
    ],
    "wof:name":"Carre Blanc Quebec Inc",
    "wof:placetype":"venue"
},
  "geometry": {"coordinates":[-73.5748138428,45.5204582214],"type":"Point"}
}