{
  "type": "Feature",
  "properties": {
    "iso:country":"CA",
    "sg:address":"13831 Riverside Dr E",
    "sg:city":"Windsor",
    "sg:classifiers":[
        {
            "category":"Personal",
            "subcategory":"Beauty Salon",
            "type":"Services"
        }
    ],
    "sg:phone":"+1 519 735 3748",
    "sg:postcode":"N8N 1B5",
    "sg:province":"ON",
    "wof:name":"Bold & Beautiful",
    "wof:placetype":"venue"
},
  "geometry": {"coordinates":[-82.89599609379999,42.3327407837],"type":"Point"}
}