{
  "type": "Feature",
  "properties": {
    "addr:full":"1158 Rue Patrick Laval QC H7Y 2C4",
    "addr:housenumber":"1158",
    "addr:postcode":"h7y 2c4",
    "addr:street":"Rue Patrick",
    "iso:country":"CA",
    "sg:address":"1158 Rue Patrick",
    "sg:city":"Laval",
    "sg:classifiers":[
        {
            "category":"Wholesale",
            "subcategory":"Metals & Minerals",
            "type":"Manufacturing & Wholesale Goods"
        }
    ],
    "sg:phone":"+1 450 689 9851",
    "sg:postcode":"H7Y 2C4",
    "sg:province":"QC",
    "sg:tags":[
        "aluminum"
    ],
    "wof:name":"Mspal Inc",
    "wof:placetype":"venue"
},
  "geometry": {"coordinates":[-73.840744,45.523224],"type":"Point"}
}