{
  "type": "Feature",
  "properties": {
    "addr:full":"1575 Victoria St N Kitchener ON N2B 3E6",
    "addr:housenumber":"1575",
    "addr:postcode":"n2b 3e6",
    "addr:street":"Victoria St N",
    "iso:country":"CA",
    "sg:address":"1575 Victoria St N",
    "sg:city":"Kitchener",
    "sg:classifiers":[
        {
            "category":"Wholesale",
            "subcategory":"Meat",
            "type":"Manufacturing & Wholesale Goods"
        }
    ],
    "sg:phone":"+1 519 743 6481",
    "sg:postcode":"N2B 3E6",
    "sg:province":"ON",
    "sg:tags":[
        "butchering"
    ],
    "wof:name":"Kitchener Farmers Meat Market",
    "wof:placetype":"venue"
},
  "geometry": {"coordinates":[-80.43602,43.473446],"type":"Point"}
}