{
  "type": "Feature",
  "properties": {
    "addr:full":"89 Av Ashgrove Pointe-Claire QC H9R 3N5",
    "addr:postcode":"h9r 3n5",
    "addr:street":"89 Av Ashgrove",
    "iso:country":"CA",
    "sg:address":"89 Av Ashgrove",
    "sg:city":"Pointe-Claire",
    "sg:classifiers":[
        {
            "category":"Food & Beverages",
            "subcategory":"Groceries & Convenience Stores",
            "type":"Retail Goods"
        }
    ],
    "sg:phone":"+1 514 695 2790",
    "sg:postcode":"H9R 3N5",
    "sg:province":"QC",
    "wof:name":"Provisions Ouest Enr",
    "wof:placetype":"venue"
},
  "geometry": {"coordinates":[-73.803123,45.44828],"type":"Point"}
}