{
  "type": "Feature",
  "properties": {
    "addr:full":"5401 53 St Olds AB T4H 1T3",
    "addr:housenumber":"5401",
    "addr:postcode":"t4h 1t3",
    "addr:street":"53 St",
    "iso:country":"CA",
    "sg:address":"5401 53 St",
    "sg:city":"Olds",
    "sg:classifiers":[
        {
            "category":"Education",
            "subcategory":"School",
            "type":"Public Place"
        }
    ],
    "sg:phone":"+1 403 556 6310",
    "sg:postcode":"T4H 1T3",
    "sg:province":"AB",
    "wof:name":"Horizon School",
    "wof:placetype":"venue"
},
  "geometry": {"coordinates":[-114.11393700000001,51.790638],"type":"Point"}
}