{
  "type": "Feature",
  "properties": {
    "addr:full":"716 Sixth Ave New Westminster BC V3M 2B3",
    "addr:housenumber":"716",
    "addr:postcode":"v3m 2b3",
    "addr:street":"Sixth Ave",
    "iso:country":"CA",
    "sg:address":"716 Sixth Ave",
    "sg:city":"New Westminster",
    "sg:classifiers":[
        {
            "category":"Education",
            "subcategory":"Library",
            "type":"Public Place"
        }
    ],
    "sg:phone":"+1 604 527 4660",
    "sg:postcode":"V3M 2B3",
    "sg:province":"BC",
    "sg:tags":[
        "government"
    ],
    "wof:name":"New Westminster Public Library",
    "wof:placetype":"venue"
},
  "geometry": {"coordinates":[-122.922134399,49.2119903564],"type":"Point"}
}