{
  "type": "Feature",
  "properties": {
    "addr:full":"Maple Ridge BC V2X 2P7",
    "addr:postcode":"v2x 2p7",
    "iso:country":"CA",
    "sg:city":"Maple Ridge",
    "sg:classifiers":[
        {
            "category":"Retail",
            "subcategory":"Auto Repair",
            "type":"Services"
        }
    ],
    "sg:phone":"+1 604 465 1415",
    "sg:postcode":"V2X 2P7",
    "sg:province":"BC",
    "sg:tags":[
        "repairing",
        "automobile"
    ],
    "wof:name":"Minit-Tune & Brake Auto Ctr",
    "wof:placetype":"venue"
},
  "geometry": {"coordinates":[-122.661331,49.219994],"type":"Point"}
}