{
  "type": "Feature",
  "properties": {
    "addr:full":"707 Charlotte St Peterborough ON K9J 2X5",
    "addr:housenumber":"707",
    "addr:postcode":"k9j 2x5",
    "addr:street":"Charlotte St",
    "iso:country":"CA",
    "sg:address":"707 Charlotte St",
    "sg:city":"Peterborough",
    "sg:classifiers":[
        {
            "category":"Health Services",
            "subcategory":"Doctor",
            "type":"Services"
        }
    ],
    "sg:phone":"+1 705 876 4506",
    "sg:postcode":"K9J 2X5",
    "sg:province":"ON",
    "sg:tags":[
        "physician",
        "surgeon"
    ],
    "wof:name":"Elharram, Mohamed MD",
    "wof:placetype":"venue"
},
  "geometry": {"coordinates":[-78.34027862550001,44.3000869751],"type":"Point"}
}