{
  "type": "Feature",
  "properties": {
    "addr:full":"995 Front Rd Windsor ON N9J 2A5",
    "addr:housenumber":"995",
    "addr:postcode":"n9j 2a5",
    "addr:street":"Front Rd",
    "iso:country":"CA",
    "sg:address":"995 Front Rd",
    "sg:city":"Windsor",
    "sg:classifiers":[
        {
            "category":"Health Services",
            "subcategory":"Chiropractor",
            "type":"Services"
        }
    ],
    "sg:phone":"+1 519 978 3305",
    "sg:postcode":"N9J 2A5",
    "sg:province":"ON",
    "wof:name":"Nautical Mile Chiro Ctr",
    "wof:placetype":"venue"
},
  "geometry": {"coordinates":[-83.033913,42.317822],"type":"Point"}
}