{
  "type": "Feature",
  "properties": {
    "addr:full":"10 Rue Isabelle Saint-Cuthbert QC J0K 2C0",
    "addr:housenumber":"10",
    "addr:postcode":"j0k 2c0",
    "addr:street":"Rue Isabelle",
    "iso:country":"CA",
    "sg:address":"10 Rue Isabelle",
    "sg:city":"Saint-Cuthbert",
    "sg:classifiers":[
        {
            "category":"Retail",
            "subcategory":"Auto Repair",
            "type":"Services"
        }
    ],
    "sg:phone":"+1 450 836 7594",
    "sg:postcode":"J0K 2C0",
    "sg:province":"QC",
    "sg:tags":[
        "repairing",
        "automobile"
    ],
    "wof:name":"Jat Auto",
    "wof:placetype":"venue"
},
  "geometry": {"coordinates":[-73.273224,46.19754],"type":"Point"}
}