{
  "type": "Feature",
  "properties": {
    "addr:full":"2451 Du College Blvd Shawinigan QC G9N 8M7",
    "addr:housenumber":"2451",
    "addr:postcode":"g9n 8m7",
    "addr:street":"Du College Blvd",
    "iso:country":"CA",
    "sg:address":"2451 Du College Blvd",
    "sg:city":"Shawinigan",
    "sg:classifiers":[
        {
            "category":"Organizations",
            "subcategory":"Professional Association",
            "type":"Services"
        }
    ],
    "sg:phone":"+1 819 539 2778",
    "sg:postcode":"G9N 8M7",
    "sg:province":"QC",
    "wof:name":"Carrefour Jeunesse",
    "wof:placetype":"venue"
},
  "geometry": {"coordinates":[-72.751541,46.56485],"type":"Point"}
}