{
  "type": "Feature",
  "properties": {
    "addr:full":"5184 Rue Saint-Denis Montreal QC H2J 2M2",
    "addr:housenumber":"5184",
    "addr:postcode":"h2j 2m2",
    "addr:street":"Rue Saint-Denis",
    "iso:country":"CA",
    "sg:address":"5184 Rue Saint-Denis",
    "sg:city":"Montreal",
    "sg:classifiers":[
        {
            "category":"Health Services",
            "subcategory":"Doctor",
            "type":"Services"
        }
    ],
    "sg:phone":"+1 514 277 8954",
    "sg:postcode":"H2J 2M2",
    "sg:province":"QC",
    "sg:tags":[
        "physiotherapist",
        "clinic"
    ],
    "wof:name":"Clinique DE Physiotherapie",
    "wof:placetype":"venue"
},
  "geometry": {"coordinates":[-73.59073600000001,45.527344],"type":"Point"}
}