{
  "type": "Feature",
  "properties": {
    "addr:full":"1315 Highbury Ave N London ON N5Y 1B6",
    "addr:housenumber":"1315",
    "addr:postcode":"n5y 1b6",
    "addr:street":"Highbury Ave N",
    "iso:country":"CA",
    "sg:address":"1315 Highbury Ave N",
    "sg:city":"London",
    "sg:classifiers":[
        {
            "category":"Health Services",
            "subcategory":"Chiropractor",
            "type":"Services"
        }
    ],
    "sg:phone":"+1 519 451 4000",
    "sg:postcode":"N5Y 1B6",
    "sg:province":"ON",
    "wof:name":"Long, Patrick DC",
    "wof:placetype":"venue"
},
  "geometry": {"coordinates":[-81.21658325200001,43.0215873718],"type":"Point"}
}