{
  "type": "Feature",
  "properties": {
    "addr:full":"Faro YT Y0B 1K0",
    "addr:postcode":"y0b 1k0",
    "addr:street":"Faro",
    "iso:country":"CA",
    "sg:city":"Faro",
    "sg:classifiers":[
        {
            "category":"Airport",
            "type":"Transportation"
        }
    ],
    "sg:phone":"+1 867 994 2791",
    "sg:postcode":"Y0B 1K0",
    "sg:province":"YT",
    "wof:name":"Yukon Faro Airport",
    "wof:placetype":"venue"
},
  "geometry": {"coordinates":[-133.354812622,62.2291564941],"type":"Point"}
}