{
  "type": "Feature",
  "properties": {
    "addr:full":"183 Wright Ave Flin Flon MB R8A 0E4",
    "addr:housenumber":"183",
    "addr:postcode":"r8a 0e4",
    "addr:street":"Wright Ave",
    "iso:country":"CA",
    "sg:address":"183 Wright Ave",
    "sg:city":"Flin Flon",
    "sg:classifiers":[
        {
            "category":"Health Services",
            "subcategory":"Medical Lab",
            "type":"Services"
        }
    ],
    "sg:phone":"+1 204 687 5270",
    "sg:postcode":"R8A 0E4",
    "sg:province":"MB",
    "wof:name":"Parker Denture Clinic",
    "wof:placetype":"venue"
},
  "geometry": {"coordinates":[-101.845589,54.771362],"type":"Point"}
}