{
  "type": "Feature",
  "properties": {
    "iso:country":"CA",
    "sg:address":"3550 Wolfedale Rd",
    "sg:city":"Mississauga",
    "sg:classifiers":[
        {
            "category":"Restaurant",
            "type":"Food & Drink"
        }
    ],
    "sg:phone":"+1 905 803 8778",
    "sg:postcode":"L5C 2V6",
    "sg:province":"ON",
    "wof:name":"Tremendous Chinese Restaurant",
    "wof:placetype":"venue"
},
  "geometry": {"coordinates":[-79.6513977051,43.5734176636],"type":"Point"}
}