{
  "type": "Feature",
  "properties": {
    "iso:country":"CA",
    "sg:address":"239 Bering Ave",
    "sg:city":"Etobicoke",
    "sg:classifiers":[
        {
            "category":"Professional",
            "subcategory":"Accounting & Tax Preparation",
            "type":"Services"
        }
    ],
    "sg:phone":"+1 416 239 1771",
    "sg:postcode":"M8Z 3A5",
    "sg:province":"ON",
    "sg:tags":[
        "bookkeeping",
        "general"
    ],
    "wof:name":"Balance This",
    "wof:placetype":"venue"
},
  "geometry": {"coordinates":[-79.524254,43.638523],"type":"Point"}
}