{
  "type": "Feature",
  "properties": {
    "addr:full":"Red Deer AB T4P 2V3",
    "addr:postcode":"t4p 2v3",
    "iso:country":"CA",
    "sg:city":"Red Deer",
    "sg:classifiers":[
        {
            "category":"Autos & Motor Vehicles",
            "subcategory":"Automobile Sales",
            "type":"Retail Goods"
        }
    ],
    "sg:phone":"+1 403 346 2898",
    "sg:postcode":"T4P 2V3",
    "sg:province":"AB",
    "sg:tags":[
        "car",
        "dealer"
    ],
    "wof:name":"Park Motors Inc",
    "wof:placetype":"venue"
},
  "geometry": {"coordinates":[-113.81353,52.312805],"type":"Point"}
}