{
  "type": "Feature",
  "properties": {
    "addr:full":"RR 1 Pickardville AB T0G 1W0",
    "addr:postcode":"t0g 1w0",
    "addr:street":"Rr 1",
    "iso:country":"CA",
    "sg:address":"RR 1",
    "sg:city":"Pickardville",
    "sg:classifiers":[
        {
            "category":"Farming",
            "subcategory":"Nursery",
            "type":"Manufacturing & Wholesale Goods"
        }
    ],
    "sg:phone":"+1 780 349 4904",
    "sg:postcode":"T0G 1W0",
    "sg:province":"AB",
    "sg:tags":[
        "greenhouse"
    ],
    "wof:name":"Manna Greenhouses",
    "wof:placetype":"venue"
},
  "geometry": {"coordinates":[-113.880043,54.052536],"type":"Point"}
}