{
  "type": "Feature",
  "properties": {
    "addr:full":"11421 Alaska Rd Fort St John BC V1J 6N2",
    "addr:housenumber":"11421",
    "addr:postcode":"v1j 6n2",
    "addr:street":"Alaska Rd",
    "iso:country":"CA",
    "sg:address":"11421 Alaska Rd",
    "sg:city":"Fort St John",
    "sg:classifiers":[
        {
            "category":"Mining & Drilling",
            "type":"Manufacturing & Wholesale Goods"
        }
    ],
    "sg:phone":"+1 250 785 3838",
    "sg:postcode":"V1J 6N2",
    "sg:province":"BC",
    "sg:tags":[
        "field",
        "oil"
    ],
    "wof:name":"Arctic Construction Ltd",
    "wof:placetype":"venue"
},
  "geometry": {"coordinates":[-120.87022399999999,56.244343],"type":"Point"}
}