{
  "type": "Feature",
  "properties": {
    "addr:full":"Victoria Cb NL A0A 4G0",
    "addr:postcode":"a0a 4g0",
    "iso:country":"CA",
    "sg:city":"Victoria Cb",
    "sg:classifiers":[
        {
            "category":"Government",
            "subcategory":"Office",
            "type":"Public Place"
        }
    ],
    "sg:phone":"+1 709 596 3783",
    "sg:postcode":"A0A 4G0",
    "sg:province":"NL",
    "sg:tags":[
        "municipality"
    ],
    "wof:name":"Victoria Municipal Hall",
    "wof:placetype":"venue"
},
  "geometry": {"coordinates":[-54.5079193115,49.3683700562],"type":"Point"}
}