{
  "type": "Feature",
  "properties": {
    "addr:full":"Stony Plain AB T7Z 1V7",
    "addr:postcode":"t7z 1v7",
    "iso:country":"CA",
    "sg:city":"Stony Plain",
    "sg:classifiers":[
        {
            "category":"Banks & Credit Unions",
            "subcategory":"Bank",
            "type":"Services"
        }
    ],
    "sg:phone":"+1 780 963 6547",
    "sg:postcode":"T7Z 1V7",
    "sg:province":"AB",
    "sg:tags":[
        "financing"
    ],
    "wof:name":"Farm Credit Corp Canada",
    "wof:placetype":"venue"
},
  "geometry": {"coordinates":[-113.97775300000001,53.542274],"type":"Point"}
}