{
  "type": "Feature",
  "properties": {
    "addr:full":"Cold Lake AB T9M 1R6",
    "addr:postcode":"t9m 1r6",
    "iso:country":"CA",
    "sg:city":"Cold Lake",
    "sg:classifiers":[
        {
            "category":"Manufacturing",
            "subcategory":"Apparel",
            "type":"Manufacturing & Wholesale Goods"
        }
    ],
    "sg:phone":"+1 780 594 2110",
    "sg:postcode":"T9M 1R6",
    "sg:province":"AB",
    "sg:tags":[
        "sewing",
        "contractor"
    ],
    "wof:name":"Csc Custom Sewing Contractor",
    "wof:placetype":"venue"
},
  "geometry": {"coordinates":[-110.20856499999999,54.421558],"type":"Point"}
}