{
  "type": "Feature",
  "properties": {
    "iso:country":"CA",
    "sg:address":"1361 Ouellette Ave",
    "sg:city":"Windsor",
    "sg:classifiers":[
        {
            "category":"Wholesale",
            "subcategory":"Auto Parts",
            "type":"Manufacturing & Wholesale Goods"
        }
    ],
    "sg:phone":"+1 519 254 4410",
    "sg:postcode":"N8X 1J6",
    "sg:province":"ON",
    "sg:tags":[
        "automobile",
        "supply"
    ],
    "wof:name":"Schukra of North America",
    "wof:placetype":"venue"
},
  "geometry": {"coordinates":[-83.0298080444,42.3028411865],"type":"Point"}
}