{
  "type": "Feature",
  "properties": {
    "addr:full":"76 Ch DE LA Montagne Lac-Sainte-Marie QC J0X 1Z0",
    "addr:housenumber":"76",
    "addr:postcode":"j0x 1z0",
    "addr:street":"Ch De La Montagne",
    "iso:country":"CA",
    "sg:address":"76 Ch DE LA Montagne",
    "sg:city":"Lac-Sainte-Marie",
    "sg:classifiers":[
        {
            "category":"Sports & Exercise",
            "subcategory":"Golf",
            "type":"Entertainment"
        }
    ],
    "sg:phone":"+1 819 467 3111",
    "sg:postcode":"J0X 1Z0",
    "sg:province":"QC",
    "sg:tags":[
        "resort",
        "center",
        "skiing"
    ],
    "wof:name":"Mont Ste-Marie",
    "wof:placetype":"venue"
},
  "geometry": {"coordinates":[-75.878433,45.941429],"type":"Point"}
}