{
  "type": "Feature",
  "properties": {
    "addr:full":"8700 5E Crois Anjou QC H1J 1A2",
    "addr:housenumber":"8700",
    "addr:postcode":"h1j 1a2",
    "addr:street":"5E Crois",
    "iso:country":"CA",
    "sg:address":"8700 5E Crois",
    "sg:city":"Anjou",
    "sg:classifiers":[
        {
            "category":"Manufacturing",
            "subcategory":"Glass & Minerals",
            "type":"Manufacturing & Wholesale Goods"
        }
    ],
    "sg:phone":"+1 514 493 0066",
    "sg:postcode":"H1J 1A2",
    "sg:province":"QC",
    "sg:tags":[
        "stone",
        "marble"
    ],
    "wof:name":"Produits DE Pierre Francon Inc",
    "wof:placetype":"venue"
},
  "geometry": {"coordinates":[-73.55842590330001,45.6016464233],"type":"Point"}
}