{
  "type": "Feature",
  "properties": {
    "addr:full":"1770 Main St # A Penticton BC V2A 5G8",
    "addr:housenumber":"1770",
    "addr:postcode":"v2a 5g8",
    "addr:street":"Main St # A",
    "iso:country":"CA",
    "sg:address":"1770 Main St # A",
    "sg:city":"Penticton",
    "sg:classifiers":[
        {
            "category":"Restaurant",
            "type":"Food & Drink"
        }
    ],
    "sg:phone":"+1 250 490 4700",
    "sg:postcode":"V2A 5G8",
    "sg:province":"BC",
    "wof:name":"White Spot Restaurants",
    "wof:placetype":"venue"
},
  "geometry": {"coordinates":[-119.584007,49.478874],"type":"Point"}
}