{
  "type": "Feature",
  "properties": {
    "addr:full":"Cambridge ON N1R 8N7",
    "addr:postcode":"n1r 8n7",
    "iso:country":"CA",
    "sg:city":"Cambridge",
    "sg:classifiers":[
        {
            "category":"Professional",
            "subcategory":"Employment Agencies",
            "type":"Services"
        }
    ],
    "sg:phone":"+1 519 624 2877",
    "sg:postcode":"N1R 8N7",
    "sg:province":"ON",
    "sg:tags":[
        "opportunity"
    ],
    "wof:name":"Liberty Staffing Svc Inc",
    "wof:placetype":"venue"
},
  "geometry": {"coordinates":[-80.328362,43.408165],"type":"Point"}
}