{
  "type": "Feature",
  "properties": {
    "addr:full":"39 Green Lane Thornhill ON L3T 6K5",
    "addr:housenumber":"39",
    "addr:postcode":"l3t 6k5",
    "addr:street":"Green Lane",
    "iso:country":"CA",
    "sg:address":"39 Green Lane",
    "sg:city":"Thornhill",
    "sg:classifiers":[
        {
            "category":"Organizations",
            "subcategory":"Religious Organization",
            "type":"Services"
        }
    ],
    "sg:phone":"+1 905 881 2786",
    "sg:postcode":"L3T 6K5",
    "sg:province":"ON",
    "sg:tags":[
        "church"
    ],
    "wof:name":"St Luke's Church",
    "wof:placetype":"venue"
},
  "geometry": {"coordinates":[-79.39801799999999,43.821842],"type":"Point"}
}