{
  "type": "Feature",
  "properties": {
    "addr:full":"786 Eglinton Ave E East York ON M4G 2L1",
    "addr:housenumber":"786",
    "addr:postcode":"m4g 2l1",
    "addr:street":"Eglinton Ave E",
    "iso:country":"CA",
    "sg:address":"786 Eglinton Ave E",
    "sg:city":"East York",
    "sg:classifiers":[
        {
            "category":"Building & Trades",
            "subcategory":"Construction",
            "type":"Services"
        }
    ],
    "sg:phone":"+1 416 423 0300",
    "sg:postcode":"M4G 2L1",
    "sg:province":"ON",
    "sg:tags":[
        "painter"
    ],
    "wof:name":"Student Painting Inc",
    "wof:placetype":"venue"
},
  "geometry": {"coordinates":[-79.366905,43.713284],"type":"Point"}
}