{
  "type": "Feature",
  "properties": {
    "addr:full":"Calgary AB T3K 2A8",
    "addr:postcode":"t3k 2a8",
    "iso:country":"CA",
    "sg:city":"Calgary",
    "sg:classifiers":[
        {
            "category":"Building & Trades",
            "subcategory":"Landscaping Services",
            "type":"Services"
        }
    ],
    "sg:phone":"+1 403 274 6482",
    "sg:postcode":"T3K 2A8",
    "sg:province":"AB",
    "sg:tags":[
        "lawn",
        "maintenance",
        "grounds"
    ],
    "wof:name":"Green Star Lawn & Tree Care",
    "wof:placetype":"venue"
},
  "geometry": {"coordinates":[-114.074547,51.125889],"type":"Point"}
}