{
  "type": "Feature",
  "properties": {
    "addr:full":"685 11E Rang Wickham QC J0C 1S0",
    "addr:housenumber":"685",
    "addr:postcode":"j0c 1s0",
    "addr:street":"11E Rang",
    "iso:country":"CA",
    "sg:address":"685 11E Rang",
    "sg:city":"Wickham",
    "sg:classifiers":[
        {
            "category":"Farming",
            "subcategory":"Farm",
            "type":"Manufacturing & Wholesale Goods"
        }
    ],
    "sg:phone":"+1 819 398 6316",
    "sg:postcode":"J0C 1S0",
    "sg:province":"QC",
    "wof:name":"Ferme Serge Boisjoli Inc",
    "wof:placetype":"venue"
},
  "geometry": {"coordinates":[-72.51685333250001,45.7366714478],"type":"Point"}
}