{
  "type": "Feature",
  "properties": {
    "addr:full":"358 Broadway Ave North York ON M4P 1X2",
    "addr:housenumber":"358",
    "addr:postcode":"m4p 1x2",
    "addr:street":"Broadway Ave",
    "iso:country":"CA",
    "sg:address":"358 Broadway Ave",
    "sg:city":"North York",
    "sg:classifiers":[
        {
            "category":"Recreation",
            "type":"Entertainment"
        }
    ],
    "sg:phone":"+1 416 483 9410",
    "sg:postcode":"M4P 1X2",
    "sg:province":"ON",
    "sg:tags":[
        "provincial",
        "parks"
    ],
    "wof:name":"Busch Entertainment Corp",
    "wof:placetype":"venue"
},
  "geometry": {"coordinates":[-79.38119500000001,43.713226],"type":"Point"}
}