{
  "type": "Feature",
  "properties": {
    "addr:full":"5609 62 St Taber AB T1G 1Y6",
    "addr:housenumber":"5609",
    "addr:postcode":"t1g 1y6",
    "addr:street":"62 St",
    "iso:country":"CA",
    "sg:address":"5609 62 St",
    "sg:city":"Taber",
    "sg:classifiers":[
        {
            "category":"Retail",
            "subcategory":"Auto Repair",
            "type":"Services"
        }
    ],
    "sg:phone":"+1 403 223 4354",
    "sg:postcode":"T1G 1Y6",
    "sg:province":"AB",
    "sg:tags":[
        "body",
        "automobile",
        "painting"
    ],
    "wof:name":"Taber Autobody Ltd",
    "wof:placetype":"venue"
},
  "geometry": {"coordinates":[-112.130737,49.792542],"type":"Point"}
}