{
  "type": "Feature",
  "properties": {
    "addr:full":"309 Main St Radville SK S0C 2G0",
    "addr:housenumber":"309",
    "addr:postcode":"s0c 2g0",
    "addr:street":"Main St",
    "iso:country":"CA",
    "sg:address":"309 Main St",
    "sg:city":"Radville",
    "sg:classifiers":[
        {
            "category":"Wholesale",
            "subcategory":"Petroleum",
            "type":"Manufacturing & Wholesale Goods"
        }
    ],
    "sg:phone":"+1 306 869 4350",
    "sg:postcode":"S0C 2G0",
    "sg:province":"SK",
    "sg:tags":[
        "oil"
    ],
    "wof:name":"Radville CO-OP Assoc Ltd",
    "wof:placetype":"venue"
},
  "geometry": {"coordinates":[-104.294662,49.460075],"type":"Point"}
}