{
  "type": "Feature",
  "properties": {
    "addr:full":"3850 Steeles Ave W Woodbridge ON L4L 4Y6",
    "addr:housenumber":"3850",
    "addr:postcode":"l4l 4y6",
    "addr:street":"Steeles Ave W",
    "iso:country":"CA",
    "sg:address":"3850 Steeles Ave W",
    "sg:city":"Woodbridge",
    "sg:classifiers":[
        {
            "category":"Retail",
            "subcategory":"Portrait Studio",
            "type":"Services"
        }
    ],
    "sg:phone":"+1 905 856 6542",
    "sg:postcode":"L4L 4Y6",
    "sg:province":"ON",
    "sg:tags":[
        "photographer"
    ],
    "wof:name":"Di Nola Photography",
    "wof:placetype":"venue"
},
  "geometry": {"coordinates":[-79.54508972169999,43.7707443237],"type":"Point"}
}