{
  "type": "Feature",
  "properties": {
    "addr:full":"North York ON M3C 1T5",
    "addr:postcode":"m3c 1t5",
    "iso:country":"CA",
    "sg:city":"North York",
    "sg:classifiers":[
        {
            "category":"Health Services",
            "subcategory":"Clinic",
            "type":"Services"
        }
    ],
    "sg:phone":"+1 416 425 9974",
    "sg:postcode":"M3C 1T5",
    "sg:province":"ON",
    "sg:tags":[
        "midwife"
    ],
    "wof:name":"Association of Ontario Midwive",
    "wof:placetype":"venue"
},
  "geometry": {"coordinates":[-79.33799,43.718754],"type":"Point"}
}