{
  "type": "Feature",
  "properties": {
    "addr:full":"1004 Rue Saint-Antoine O Montreal QC H3C 3R7",
    "addr:housenumber":"1004",
    "addr:postcode":"h3c 3r7",
    "addr:street":"Rue Saint-Antoine O",
    "iso:country":"CA",
    "sg:address":"1004 Rue Saint-Antoine O",
    "sg:city":"Montreal",
    "sg:classifiers":[
        {
            "category":"Government",
            "subcategory":"Office",
            "type":"Public Place"
        }
    ],
    "sg:phone":"+1 514 872 4310",
    "sg:postcode":"H3C 3R7",
    "sg:province":"QC",
    "wof:name":"Quebec Centre Local D'Emploi",
    "wof:placetype":"venue"
},
  "geometry": {"coordinates":[-73.55196380620001,45.5145568848],"type":"Point"}
}