{
  "type": "Feature",
  "properties": {
    "addr:full":"19913 Hwy 6 S Wiarton ON N0H 2T0",
    "addr:housenumber":"19913",
    "addr:postcode":"n0h 2t0",
    "addr:street":"Hwy 6 S",
    "iso:country":"CA",
    "sg:address":"19913 Hwy 6 S",
    "sg:city":"Wiarton",
    "sg:classifiers":[
        {
            "category":"Organizations",
            "subcategory":"Religious Organization",
            "type":"Services"
        }
    ],
    "sg:phone":"+1 519 534 1704",
    "sg:postcode":"N0H 2T0",
    "sg:province":"ON",
    "sg:tags":[
        "church"
    ],
    "wof:name":"Full Gospel Temple",
    "wof:placetype":"venue"
},
  "geometry": {"coordinates":[-81.1404724121,44.7343635559],"type":"Point"}
}