{
  "type": "Feature",
  "properties": {
    "addr:full":"12124 Sixth Line Limehouse ON L0P 1H0",
    "addr:housenumber":"12124",
    "addr:postcode":"l0p 1h0",
    "addr:street":"Sixth Line",
    "iso:country":"CA",
    "sg:address":"12124 Sixth Line",
    "sg:city":"Limehouse",
    "sg:classifiers":[
        {
            "category":"Manufacturing",
            "subcategory":"Tools & Machinery",
            "type":"Manufacturing & Wholesale Goods"
        }
    ],
    "sg:phone":"+1 905 877 6227",
    "sg:postcode":"L0P 1H0",
    "sg:province":"ON",
    "sg:tags":[
        "equipment",
        "system",
        "automation"
    ],
    "wof:name":"Halmac Limited",
    "wof:placetype":"venue"
},
  "geometry": {"coordinates":[-79.97895050050001,43.6384086609],"type":"Point"}
}