{
  "type": "Feature",
  "properties": {
    "addr:full":"4953 50 St Camrose AB T4V 1P9",
    "addr:housenumber":"4953",
    "addr:postcode":"t4v 1p9",
    "addr:street":"50 St",
    "iso:country":"CA",
    "sg:address":"4953 50 St",
    "sg:city":"Camrose",
    "sg:classifiers":[
        {
            "category":"Shopping",
            "subcategory":"Gifts & Souvenirs",
            "type":"Retail Goods"
        }
    ],
    "sg:phone":"+1 780 679 0680",
    "sg:postcode":"T4V 1P9",
    "sg:province":"AB",
    "sg:tags":[
        "shop"
    ],
    "wof:name":"Main Street Gallery",
    "wof:placetype":"venue"
},
  "geometry": {"coordinates":[-112.824821472,53.0214805603],"type":"Point"}
}