{
  "type": "Feature",
  "properties": {
    "addr:full":"67 Circular Rd St. John's NL A1C 2Z4",
    "addr:housenumber":"67",
    "addr:postcode":"a1c 2z4",
    "addr:street":"Circular Rd",
    "iso:country":"CA",
    "sg:address":"67 Circular Rd",
    "sg:city":"St. John's",
    "sg:classifiers":[
        {
            "category":"Autos & Motor Vehicles",
            "subcategory":"Boat Sales",
            "type":"Retail Goods"
        }
    ],
    "sg:phone":"+1 709 579 6353",
    "sg:postcode":"A1C 2Z4",
    "sg:province":"NL",
    "sg:tags":[
        "attraction",
        "tourist",
        "dealer"
    ],
    "wof:name":"Stan Cook Sea Kayaking Advntrs",
    "wof:placetype":"venue"
},
  "geometry": {"coordinates":[-55.649204,48.926704],"type":"Point"}
}