{
  "type": "Feature",
  "properties": {
    "addr:full":"Calgary AB T2R 1J4",
    "addr:postcode":"t2r 1j4",
    "iso:country":"CA",
    "sg:city":"Calgary",
    "sg:classifiers":[
        {
            "category":"Professional",
            "subcategory":"Lawyer & Legal Services",
            "type":"Services"
        }
    ],
    "sg:phone":"+1 403 252 9937",
    "sg:postcode":"T2R 1J4",
    "sg:province":"AB",
    "sg:tags":[
        "attorney"
    ],
    "wof:name":"Milley, Thomas E",
    "wof:placetype":"venue"
},
  "geometry": {"coordinates":[-114.071556,51.043056],"type":"Point"}
}