{
  "type": "Feature",
  "properties": {
    "addr:full":"51 Ch Du Bord-Du-Lac- -Lakesho Pointe-Claire QC H9S 4H4",
    "addr:housenumber":"51",
    "addr:postcode":"h9s 4h4",
    "addr:street":"Ch Du Bord-Du-Lac Lakesho",
    "iso:country":"CA",
    "sg:address":"51 Ch Du Bord-Du-Lac- -Lakesho",
    "sg:city":"Pointe-Claire",
    "sg:classifiers":[
        {
            "category":"Professional",
            "subcategory":"Management & Consulting",
            "type":"Services"
        }
    ],
    "sg:phone":"+1 514 694 1872",
    "sg:postcode":"H9S 4H4",
    "sg:province":"QC",
    "sg:tags":[
        "consultant",
        "business"
    ],
    "wof:name":"Collins Groupe",
    "wof:placetype":"venue"
},
  "geometry": {"coordinates":[-73.7923202515,45.4484443665],"type":"Point"}
}