{
  "type": "Feature",
  "properties": {
    "addr:full":"401 South Industrial Dr Prince Albert SK S6V 7L9",
    "addr:housenumber":"401",
    "addr:postcode":"s6v 7l9",
    "addr:street":"South Industrial Dr",
    "iso:country":"CA",
    "sg:address":"401 South Industrial Dr",
    "sg:city":"Prince Albert",
    "sg:classifiers":[
        {
            "category":"Retail",
            "subcategory":"Auto Repair",
            "type":"Services"
        }
    ],
    "sg:phone":"+1 306 764 5666",
    "sg:postcode":"S6V 7L9",
    "sg:province":"SK",
    "sg:tags":[
        "repairing",
        "automobile",
        "tire"
    ],
    "wof:name":"Wheatland Tire & Auto Inc",
    "wof:placetype":"venue"
},
  "geometry": {"coordinates":[-105.74316399999999,53.18111],"type":"Point"}
}