{
  "type": "Feature",
  "properties": {
    "addr:full":"1118 Homer Street Vancouver V6B 6L5",
    "addr:housenumber":"1118",
    "addr:postcode":"v6b 6l5",
    "addr:street":"Homer Street",
    "iso:country":"CA",
    "sg:address":"1118 Homer Street",
    "sg:city":"Vancouver",
    "sg:classifiers":[
        {
            "category":"Professional",
            "subcategory":"Computer Services",
            "type":"Services"
        }
    ],
    "sg:postcode":"V6B 6L5",
    "sg:website":"http://www.indochino.com",
    "wof:name":"IndoChino",
    "wof:placetype":"venue"
},
  "geometry": {"coordinates":[-123.337608,48.487589],"type":"Point"}
}