{
  "type": "Feature",
  "properties": {
    "addr:full":"Dundas ON L9H 1B5",
    "addr:postcode":"l9h 1b5",
    "iso:country":"CA",
    "sg:city":"Dundas",
    "sg:classifiers":[
        {
            "category":"Home & Garden",
            "subcategory":"Furniture",
            "type":"Retail Goods"
        }
    ],
    "sg:phone":"+1 905 628 3275",
    "sg:postcode":"L9H 1B5",
    "sg:province":"ON",
    "sg:tags":[
        "equipment",
        "kitchen",
        "cabinet"
    ],
    "wof:name":"Wood Valley Kitchens",
    "wof:placetype":"venue"
},
  "geometry": {"coordinates":[-79.94620500000001,43.265499],"type":"Point"}
}