{
  "type": "Feature",
  "properties": {
    "addr:full":"114 Drury St North Bay ON P1A 3Z6",
    "addr:housenumber":"114",
    "addr:postcode":"p1a 3z6",
    "addr:street":"Drury St",
    "iso:country":"CA",
    "sg:address":"114 Drury St",
    "sg:city":"North Bay",
    "sg:classifiers":[
        {
            "category":"Food & Beverages",
            "subcategory":"Bakery",
            "type":"Retail Goods"
        }
    ],
    "sg:phone":"+1 705 495 1669",
    "sg:postcode":"P1A 3Z6",
    "sg:province":"ON",
    "sg:tags":[
        "doughnut"
    ],
    "wof:name":"Tim Hortons",
    "wof:placetype":"venue"
},
  "geometry": {"coordinates":[-79.44049072270001,46.3097038269],"type":"Point"}
}