{
  "type": "Feature",
  "properties": {
    "iso:country":"CA",
    "sg:address":"400 7 St SW",
    "sg:city":"Salmon Arm",
    "sg:classifiers":[
        {
            "category":"Retail",
            "subcategory":"Auto Repair",
            "type":"Services"
        }
    ],
    "sg:phone":"+1 250 832 3005",
    "sg:postcode":"V1E 1S9",
    "sg:province":"BC",
    "sg:tags":[
        "repairing",
        "automobile"
    ],
    "wof:name":"Stan's Auto Repair & Rental",
    "wof:placetype":"venue"
},
  "geometry": {"coordinates":[-119.293334961,50.696937561],"type":"Point"}
}