{
  "type": "Feature",
  "properties": {
    "addr:full":"669 Fairmont Rd Winnipeg MB R3R 1B2",
    "addr:housenumber":"669",
    "addr:postcode":"r3r 1b2",
    "addr:street":"Fairmont Rd",
    "iso:country":"CA",
    "sg:address":"669 Fairmont Rd",
    "sg:city":"Winnipeg",
    "sg:classifiers":[
        {
            "category":"Professional",
            "subcategory":"Management & Consulting",
            "type":"Services"
        }
    ],
    "sg:phone":"+1 204 777 5200",
    "sg:postcode":"R3R 1B2",
    "sg:province":"MB",
    "sg:tags":[
        "consultant",
        "medium"
    ],
    "wof:name":"Jazz Lynx Intl",
    "wof:placetype":"venue"
},
  "geometry": {"coordinates":[-97.27439099999999,49.853832],"type":"Point"}
}