{
  "type": "Feature",
  "properties": {
    "addr:full":"Calgary AB T2R 0L5",
    "addr:postcode":"t2r 0l5",
    "iso:country":"CA",
    "sg:city":"Calgary",
    "sg:classifiers":[
        {
            "category":"Real Estate",
            "subcategory":"Real Estate Operator",
            "type":"Services"
        }
    ],
    "sg:phone":"+1 403 244 8234",
    "sg:postcode":"T2R 0L5",
    "sg:province":"AB",
    "sg:tags":[
        "apartment"
    ],
    "wof:name":"Cavalier",
    "wof:placetype":"venue"
},
  "geometry": {"coordinates":[-114.08506800000001,51.040962],"type":"Point"}
}