{
  "type": "Feature",
  "properties": {
    "iso:country":"CA",
    "sg:address":"486 Melcrest Rd",
    "sg:city":"London",
    "sg:classifiers":[
        {
            "category":"Wholesale",
            "subcategory":"Machinery & Supplies",
            "type":"Manufacturing & Wholesale Goods"
        }
    ],
    "sg:phone":"+1 519 657 1168",
    "sg:postcode":"N6J 3T1",
    "sg:province":"ON",
    "sg:tags":[
        "seal"
    ],
    "wof:name":"Alpha Seal Corp",
    "wof:placetype":"venue"
},
  "geometry": {"coordinates":[-81.289703,42.958302],"type":"Point"}
}