{
  "type": "Feature",
  "properties": {
    "addr:full":"Lethbridge AB T1J 4L9",
    "addr:postcode":"t1j 4l9",
    "iso:country":"CA",
    "sg:city":"Lethbridge",
    "sg:classifiers":[
        {
            "category":"Personal",
            "subcategory":"Beauty Salon",
            "type":"Services"
        }
    ],
    "sg:phone":"+1 403 320 9161",
    "sg:postcode":"T1J 4L9",
    "sg:province":"AB",
    "wof:name":"Chatters Hair Salons",
    "wof:placetype":"venue"
},
  "geometry": {"coordinates":[-112.840202331,49.6980705261],"type":"Point"}
}