{
  "type": "Feature",
  "properties": {
    "addr:full":"636 Main St Vancouver BC V6A 2V3",
    "addr:housenumber":"636",
    "addr:postcode":"v6a 2v3",
    "addr:street":"Main St",
    "iso:country":"CA",
    "sg:address":"636 Main St",
    "sg:city":"Vancouver",
    "sg:classifiers":[
        {
            "category":"Shopping",
            "subcategory":"Music",
            "type":"Retail Goods"
        }
    ],
    "sg:phone":"+1 604 893 8927",
    "sg:postcode":"V6A 2V3",
    "sg:province":"BC",
    "sg:tags":[
        "compact",
        "record",
        "disc",
        "tape"
    ],
    "wof:name":"Best Music CO",
    "wof:placetype":"venue"
},
  "geometry": {"coordinates":[-123.099525,49.279114],"type":"Point"}
}