{
  "type": "Feature",
  "properties": {
    "addr:full":"294 Keltic Dr Sydney NS B1R 1V7",
    "addr:housenumber":"294",
    "addr:postcode":"b1r 1v7",
    "addr:street":"Keltic Dr",
    "iso:country":"CA",
    "sg:address":"294 Keltic Dr",
    "sg:city":"Sydney",
    "sg:classifiers":[
        {
            "category":"Travel",
            "subcategory":"Hotels & Motels",
            "type":"Entertainment"
        }
    ],
    "sg:phone":"+1 902 562 8282",
    "sg:postcode":"B1R 1V7",
    "sg:province":"NS",
    "wof:name":"Beacon Motel & Lodge",
    "wof:placetype":"venue"
},
  "geometry": {"coordinates":[-60.230835,46.116615],"type":"Point"}
}