{
  "type": "Feature",
  "properties": {
    "iso:country":"CA",
    "sg:address":"391 Birchmount Rd",
    "sg:city":"Scarborough",
    "sg:classifiers":[
        {
            "category":"Building & Trades",
            "subcategory":"Construction",
            "type":"Services"
        }
    ],
    "sg:phone":"+1 416 693 0474",
    "sg:postcode":"M1K 1N3",
    "sg:province":"ON",
    "sg:tags":[
        "general",
        "contractor"
    ],
    "wof:name":"Newborough Construction",
    "wof:placetype":"venue"
},
  "geometry": {"coordinates":[-79.2657775879,43.701839447],"type":"Point"}
}