{
  "type": "Feature",
  "properties": {
    "addr:full":"660 Columbia St New Westminster BC V3M 1A9",
    "addr:housenumber":"660",
    "addr:postcode":"v3m 1a9",
    "addr:street":"Columbia",
    "iso:country":"CA",
    "sg:address":"660 Columbia St",
    "sg:city":"New Westminster",
    "sg:classifiers":[
        {
            "category":"Travel",
            "subcategory":"Hotels & Motels",
            "type":"Entertainment"
        }
    ],
    "sg:phone":"+1 604 525 2850",
    "sg:postcode":"V3M 1A9",
    "sg:province":"BC",
    "wof:name":"Windjammer Hotel",
    "wof:placetype":"venue"
},
  "geometry": {"coordinates":[-122.90904999999999,49.20237],"type":"Point"}
}