{
  "type": "Feature",
  "properties": {
    "iso:country":"CA",
    "sg:address":"215 Drive in Rd",
    "sg:city":"Sault Ste Marie",
    "sg:classifiers":[
        {
            "category":"Manufacturing",
            "subcategory":"Tools & Machinery",
            "type":"Manufacturing & Wholesale Goods"
        }
    ],
    "sg:phone":"+1 705 256 7456",
    "sg:postcode":"P6B 5X5",
    "sg:province":"ON",
    "sg:tags":[
        "machine",
        "shop"
    ],
    "wof:name":"Soo Foundry & Machine 1980 Ltd",
    "wof:placetype":"venue"
},
  "geometry": {"coordinates":[-84.3228302002,46.5475959778],"type":"Point"}
}