{
  "type": "Feature",
  "properties": {
    "addr:full":"2552 Skimikin Rd W Tappen BC V0E 2X0",
    "addr:housenumber":"2552",
    "addr:postcode":"bc v0e 2x0",
    "addr:street":"Skimikin Rd W Tappen",
    "iso:country":"CA",
    "sg:address":"2552 Skimikin Rd W",
    "sg:city":"Tappen",
    "sg:classifiers":[
        {
            "category":"Retail",
            "subcategory":"Auto Repair",
            "type":"Services"
        }
    ],
    "sg:phone":"+1 250 833 5061",
    "sg:postcode":"V0E 2X0",
    "sg:province":"BC",
    "sg:tags":[
        "body",
        "automobile",
        "painting"
    ],
    "wof:name":"Tappen Valley Refinishing",
    "wof:placetype":"venue"
},
  "geometry": {"coordinates":[-119.349212647,50.7808265686],"type":"Point"}
}