{
  "type": "Feature",
  "properties": {
    "iso:country":"CA",
    "sg:address":"3925 Ch Du Souvenir",
    "sg:city":"Laval",
    "sg:classifiers":[
        {
            "category":"Food & Beverages",
            "subcategory":"Bakery",
            "type":"Retail Goods"
        }
    ],
    "sg:phone":"+1 450 686 9030",
    "sg:postcode":"H7W 1A9",
    "sg:province":"QC",
    "sg:tags":[
        "baker"
    ],
    "wof:name":"2847-2751 Quebec Inc",
    "wof:placetype":"venue"
},
  "geometry": {"coordinates":[-73.75788116459999,45.5488471985],"type":"Point"}
}