{
  "type": "Feature",
  "properties": {
    "addr:full":"8995 Boul Gouin E Montreal QC H1E 2P8",
    "addr:housenumber":"8995",
    "addr:postcode":"h1e 2p8",
    "addr:street":"Boul Gouin E",
    "iso:country":"CA",
    "sg:address":"8995 Boul Gouin E",
    "sg:city":"Montreal",
    "sg:classifiers":[
        {
            "category":"Autos & Motor Vehicles",
            "subcategory":"Motorcycle Sales",
            "type":"Retail Goods"
        }
    ],
    "sg:phone":"+1 514 648 4498",
    "sg:postcode":"H1E 2P8",
    "sg:province":"QC",
    "sg:tags":[
        "scooter"
    ],
    "wof:name":"Paris Scooters",
    "wof:placetype":"venue"
},
  "geometry": {"coordinates":[-73.584007,45.65263],"type":"Point"}
}