{
  "type": "Feature",
  "properties": {
    "iso:country":"CA",
    "sg:address":"387 Dundas St",
    "sg:city":"Woodstock",
    "sg:classifiers":[
        {
            "category":"Home & Garden",
            "subcategory":"Furniture",
            "type":"Retail Goods"
        }
    ],
    "sg:phone":"+1 519 537 3701",
    "sg:postcode":"N4S 1B6",
    "sg:province":"ON",
    "sg:tags":[
        "mattress"
    ],
    "wof:name":"Stubbe's Countrywide",
    "wof:placetype":"venue"
},
  "geometry": {"coordinates":[-80.7607421875,43.1296615601],"type":"Point"}
}