{
  "type": "Feature",
  "properties": {
    "addr:full":"Calgary AB T1Y 6M6",
    "addr:postcode":"t1y 6m6",
    "iso:country":"CA",
    "sg:city":"Calgary",
    "sg:classifiers":[
        {
            "category":"Health Services",
            "subcategory":"Doctor",
            "type":"Services"
        }
    ],
    "sg:phone":"+1 403 291 4945",
    "sg:postcode":"T1Y 6M6",
    "sg:province":"AB",
    "sg:tags":[
        "dentist"
    ],
    "wof:name":"London Square Dental Ctr",
    "wof:placetype":"venue"
},
  "geometry": {"coordinates":[-113.984680176,51.0813064575],"type":"Point"}
}