{
  "type": "Feature",
  "properties": {
    "addr:full":"524 Church St Toronto ON M4Y 2E1",
    "addr:housenumber":"524",
    "addr:postcode":"m4y 2e1",
    "addr:street":"Church St",
    "iso:country":"CA",
    "sg:address":"524 Church St",
    "sg:city":"Toronto",
    "sg:classifiers":[
        {
            "category":"Food & Beverages",
            "subcategory":"Groceries & Convenience Stores",
            "type":"Retail Goods"
        }
    ],
    "sg:phone":"+1 416 967 9484",
    "sg:postcode":"M4Y 2E1",
    "sg:province":"ON",
    "sg:tags":[
        "grocer"
    ],
    "wof:name":"Super Freshmart",
    "wof:placetype":"venue"
},
  "geometry": {"coordinates":[-79.38076,43.664848],"type":"Point"}
}