{
  "type": "Feature",
  "properties": {
    "addr:full":"Martintown ON K0C 1S0",
    "addr:postcode":"k0c 1s0",
    "iso:country":"CA",
    "sg:city":"Martintown",
    "sg:classifiers":[
        {
            "category":"Wholesale",
            "subcategory":"Machinery & Supplies",
            "type":"Manufacturing & Wholesale Goods"
        }
    ],
    "sg:phone":"+1 613 528 4205",
    "sg:postcode":"K0C 1S0",
    "sg:province":"ON",
    "sg:tags":[
        "farm",
        "equipment"
    ],
    "wof:name":"Len's Farm Equipment",
    "wof:placetype":"venue"
},
  "geometry": {"coordinates":[-74.71093,45.154327],"type":"Point"}
}