{
  "type": "Feature",
  "properties": {
    "addr:full":"2234 14 St SW Calgary AB T2T 3T3",
    "addr:housenumber":"2234",
    "addr:postcode":"t2t 3t3",
    "addr:street":"14 St Sw",
    "iso:country":"CA",
    "sg:address":"2234 14 St SW",
    "sg:city":"Calgary",
    "sg:classifiers":[
        {
            "category":"Education",
            "subcategory":"School",
            "type":"Public Place"
        }
    ],
    "sg:phone":"+1 403 777 7980",
    "sg:postcode":"T2T 3T3",
    "sg:province":"AB",
    "wof:name":"Mount Royal Junior High School",
    "wof:placetype":"venue"
},
  "geometry": {"coordinates":[-114.09462000000001,51.035072],"type":"Point"}
}