{
  "type": "Feature",
  "properties": {
    "addr:full":"3205 Rue Iberville Sorel-Tracy QC J3R 5K1",
    "addr:housenumber":"3205",
    "addr:postcode":"j3r 5k1",
    "addr:street":"Rue Iberville",
    "iso:country":"CA",
    "sg:address":"3205 Rue Iberville",
    "sg:city":"Sorel-Tracy",
    "sg:classifiers":[
        {
            "category":"Manufacturing",
            "subcategory":"Metals",
            "type":"Manufacturing & Wholesale Goods"
        }
    ],
    "sg:phone":"+1 450 743 0057",
    "sg:postcode":"J3R 5K1",
    "sg:province":"QC",
    "sg:tags":[
        "work",
        "sheet",
        "contractor"
    ],
    "wof:name":"Philemon Courchesne Chauffage",
    "wof:placetype":"venue"
},
  "geometry": {"coordinates":[-73.15139000000001,46.032967],"type":"Point"}
}