{
  "type": "Feature",
  "properties": {
    "addr:full":"3291 22nd Ave E Vancouver BC V5M 2Z1",
    "addr:housenumber":"3291",
    "addr:postcode":"v5m 2z1",
    "addr:street":"22Nd Ave E",
    "iso:country":"CA",
    "sg:address":"3291 22nd Ave E",
    "sg:city":"Vancouver",
    "sg:classifiers":[
        {
            "category":"Food & Beverages",
            "subcategory":"Bakery",
            "type":"Retail Goods"
        }
    ],
    "sg:phone":"+1 604 434 6903",
    "sg:postcode":"V5M 2Z1",
    "sg:province":"BC",
    "sg:tags":[
        "baker"
    ],
    "wof:name":"Lucky Bakery",
    "wof:placetype":"venue"
},
  "geometry": {"coordinates":[-123.034325,49.250805],"type":"Point"}
}