{
  "type": "Feature",
  "properties": {
    "addr:full":"4289 Hwy 31 Williamsburg ON K0C 2H0",
    "addr:housenumber":"4289",
    "addr:postcode":"k0c 2h0",
    "addr:street":"Hwy 31",
    "iso:country":"CA",
    "sg:address":"4289 Hwy 31",
    "sg:city":"Williamsburg",
    "sg:classifiers":[
        {
            "category":"Food & Beverages",
            "subcategory":"Groceries & Convenience Stores",
            "type":"Retail Goods"
        }
    ],
    "sg:phone":"+1 613 535 2199",
    "sg:postcode":"K0C 2H0",
    "sg:province":"ON",
    "sg:tags":[
        "merchandise",
        "general"
    ],
    "wof:name":"J & S Convenience Store",
    "wof:placetype":"venue"
},
  "geometry": {"coordinates":[-75.2453460693,44.9771842957],"type":"Point"}
}