{
  "type": "Feature",
  "properties": {
    "addr:full":"SE 4-10-12 E Hadashville MB R0E 0X0",
    "addr:housenumber":"4-10-12 e",
    "addr:postcode":"r0e 0x0",
    "addr:street":"Se;Hadashville",
    "iso:country":"CA",
    "sg:address":"SE 4-10-12 E",
    "sg:city":"Hadashville",
    "sg:classifiers":[
        {
            "category":"Organizations",
            "subcategory":"Religious Organization",
            "type":"Services"
        }
    ],
    "sg:phone":"+1 204 426 5629",
    "sg:postcode":"R0E 0X0",
    "sg:province":"MB",
    "sg:tags":[
        "church"
    ],
    "wof:name":"Twin Rivers Mennonite Church",
    "wof:placetype":"venue"
},
  "geometry": {"coordinates":[-95.90698999999999,49.684708],"type":"Point"}
}