{
  "type": "Feature",
  "properties": {
    "iso:country":"CA",
    "sg:address":"1674 Cow Bay Rd",
    "sg:city":"Eastern Passage",
    "sg:classifiers":[
        {
            "category":"Wholesale",
            "subcategory":"Durable Goods & Equipment",
            "type":"Manufacturing & Wholesale Goods"
        }
    ],
    "sg:phone":"+1 902 463 1758",
    "sg:postcode":"B3G 1L1",
    "sg:province":"NS",
    "sg:tags":[
        "representative",
        "manufacturer"
    ],
    "wof:name":"Partington Sales Ltd",
    "wof:placetype":"venue"
},
  "geometry": {"coordinates":[-63.4512672424,44.6234512329],"type":"Point"}
}