{
  "type": "Feature",
  "properties": {
    "addr:full":"172 Eglinton Ave E Toronto ON M4P 1A6",
    "addr:housenumber":"172",
    "addr:postcode":"m4p 1a6",
    "addr:street":"Eglinton Ave E",
    "iso:country":"CA",
    "sg:address":"172 Eglinton Ave E",
    "sg:city":"Toronto",
    "sg:classifiers":[
        {
            "category":"Travel",
            "subcategory":"Travel Agent",
            "type":"Entertainment"
        }
    ],
    "sg:phone":"+1 416 481 5106",
    "sg:postcode":"M4P 1A6",
    "sg:province":"ON",
    "sg:tags":[
        "agency",
        "bureau"
    ],
    "wof:name":"Stafford Travel Ltd",
    "wof:placetype":"venue"
},
  "geometry": {"coordinates":[-79.3933334351,43.707950592],"type":"Point"}
}