{
  "type": "Feature",
  "properties": {
    "addr:full":"107 46 Ave SW Calgary AB T2G 4T7",
    "addr:postcode":"t2g 4t7",
    "addr:street":"107 46 Ave Sw",
    "iso:country":"CA",
    "sg:address":"107 46 Ave SW",
    "sg:city":"Calgary",
    "sg:classifiers":[
        {
            "category":"Autos & Motor Vehicles",
            "subcategory":"Auto Supplies",
            "type":"Retail Goods"
        }
    ],
    "sg:phone":"+1 403 243 1090",
    "sg:postcode":"T2G 4T7",
    "sg:province":"AB",
    "sg:tags":[
        "automobile",
        "parts"
    ],
    "wof:name":"All Start Batteries Starters",
    "wof:placetype":"venue"
},
  "geometry": {"coordinates":[-114.066314697,51.0111427307],"type":"Point"}
}