{
  "type": "Feature",
  "properties": {
    "addr:full":"18 Crown Steel Dr Markham ON L3R 9X8",
    "addr:housenumber":"18",
    "addr:postcode":"l3r 9x8",
    "addr:street":"Crown Steel Dr",
    "iso:country":"CA",
    "sg:address":"18 Crown Steel Dr",
    "sg:city":"Markham",
    "sg:classifiers":[
        {
            "category":"Professional",
            "subcategory":"Management & Consulting",
            "type":"Services"
        }
    ],
    "sg:phone":"+1 905 479 5811",
    "sg:postcode":"L3R 9X8",
    "sg:province":"ON",
    "sg:tags":[
        "consultant",
        "business"
    ],
    "wof:name":"Martech Corporate & Personal",
    "wof:placetype":"venue"
},
  "geometry": {"coordinates":[-79.32536315919999,43.8392715454],"type":"Point"}
}