{
  "type": "Feature",
  "properties": {
    "addr:full":"359 Princess Ave London ON N6B 2A7",
    "addr:housenumber":"359",
    "addr:postcode":"n6b 2a7",
    "addr:street":"Princess Ave",
    "iso:country":"CA",
    "sg:address":"359 Princess Ave",
    "sg:city":"London",
    "sg:classifiers":[
        {
            "category":"Professional",
            "subcategory":"Computer Services",
            "type":"Services"
        }
    ],
    "sg:phone":"+1 519 672 8799",
    "sg:postcode":"N6B 2A7",
    "sg:province":"ON",
    "sg:tags":[
        "website",
        "design"
    ],
    "wof:name":"Hall Interactive",
    "wof:placetype":"venue"
},
  "geometry": {"coordinates":[-81.242851,42.990005],"type":"Point"}
}