{
  "type": "Feature",
  "properties": {
    "iso:country":"CA",
    "sg:address":"2332 Marpole Ave",
    "sg:city":"Port Coquitlam",
    "sg:classifiers":[
        {
            "category":"Food & Beverages",
            "subcategory":"Liquor & Beverages",
            "type":"Retail Goods"
        }
    ],
    "sg:phone":"+1 604 942 7424",
    "sg:postcode":"V3C 2A2",
    "sg:province":"BC",
    "sg:tags":[
        "store"
    ],
    "wof:name":"Liquor Stores-Government",
    "wof:placetype":"venue"
},
  "geometry": {"coordinates":[-122.783607483,49.2614707947],"type":"Point"}
}