{
  "type": "Feature",
  "properties": {
    "addr:full":"4172 Hamilton Rd Dorchester ON N0L 1G2",
    "addr:housenumber":"4172",
    "addr:postcode":"n0l 1g2",
    "addr:street":"Hamilton Rd",
    "iso:country":"CA",
    "sg:address":"4172 Hamilton Rd",
    "sg:city":"Dorchester",
    "sg:classifiers":[
        {
            "category":"Insurance",
            "subcategory":"Insurance Agent",
            "type":"Services"
        }
    ],
    "sg:phone":"+1 519 268 7306",
    "sg:postcode":"N0L 1G2",
    "sg:province":"ON",
    "wof:name":"Mc Farlan Rowlands Insurance",
    "wof:placetype":"venue"
},
  "geometry": {"coordinates":[-81.053855896,42.9882736206],"type":"Point"}
}