{
  "type": "Feature",
  "properties": {
    "addr:full":"2813 Quesnel St Victoria BC V8T 4K2",
    "addr:housenumber":"2813",
    "addr:postcode":"v8t 4k2",
    "addr:street":"Quesnel St",
    "iso:country":"CA",
    "sg:address":"2813 Quesnel St",
    "sg:city":"Victoria",
    "sg:classifiers":[
        {
            "category":"Home & Garden",
            "subcategory":"Building Materials",
            "type":"Retail Goods"
        }
    ],
    "sg:phone":"+1 250 388 4811",
    "sg:postcode":"V8T 4K2",
    "sg:province":"BC",
    "sg:tags":[
        "glass",
        "window",
        "plate"
    ],
    "wof:name":"Victoria Glass CO Ltd",
    "wof:placetype":"venue"
},
  "geometry": {"coordinates":[-123.36567688,48.4399795532],"type":"Point"}
}