{
  "type": "Feature",
  "properties": {
    "addr:full":"4915 50 Ave Camrose AB T4V 0S2",
    "addr:housenumber":"4915",
    "addr:postcode":"t4v 0s2",
    "addr:street":"50 Ave",
    "iso:country":"CA",
    "sg:address":"4915 50 Ave",
    "sg:city":"Camrose",
    "sg:classifiers":[
        {
            "category":"Professional",
            "subcategory":"Accounting & Tax Preparation",
            "type":"Services"
        }
    ],
    "sg:phone":"+1 780 672 5824",
    "sg:postcode":"T4V 0S2",
    "sg:province":"AB",
    "sg:tags":[
        "accountant"
    ],
    "wof:name":"Cam-Alta Accounting & Tax Svc",
    "wof:placetype":"venue"
},
  "geometry": {"coordinates":[-112.823692322,53.0219841003],"type":"Point"}
}