{
  "type": "Feature",
  "properties": {
    "addr:full":"205 Rue DE L'Industrie L'Assomption QC J5W 2T9",
    "addr:housenumber":"205",
    "addr:postcode":"j5w 2t9",
    "addr:street":"Rue De L'Industrie",
    "iso:country":"CA",
    "sg:address":"205 Rue DE L'Industrie",
    "sg:city":"L'Assomption",
    "sg:classifiers":[
        {
            "category":"Manufacturing",
            "subcategory":"Building Materials",
            "type":"Manufacturing & Wholesale Goods"
        }
    ],
    "sg:phone":"+1 450 589 5951",
    "sg:postcode":"J5W 2T9",
    "sg:province":"QC",
    "sg:tags":[
        "truss"
    ],
    "wof:name":"Ateliers Ferjan Inc",
    "wof:placetype":"venue"
},
  "geometry": {"coordinates":[-73.4175872803,45.8330383301],"type":"Point"}
}