{
  "type": "Feature",
  "properties": {
    "iso:country":"CA",
    "sg:address":"205 Rue DE L'Industrie",
    "sg:city":"L'Assomption",
    "sg:classifiers":[
        {
            "category":"Manufacturing",
            "subcategory":"Building Materials",
            "type":"Manufacturing & Wholesale Goods"
        }
    ],
    "sg:phone":"+1 450 589 5951",
    "sg:postcode":"J5W 2T9",
    "sg:province":"QC",
    "sg:tags":[
        "truss"
    ],
    "wof:name":"Ateliers Ferjan Inc",
    "wof:placetype":"venue"
},
  "geometry": {"coordinates":[-73.4175872803,45.8330383301],"type":"Point"}
}