{
  "type": "Feature",
  "properties": {
    "addr:full":"540 Bronson Ave Ottawa ON K1R 6J9",
    "addr:housenumber":"540",
    "addr:postcode":"k1r 6j9",
    "addr:street":"Bronson Ave",
    "iso:country":"CA",
    "sg:address":"540 Bronson Ave",
    "sg:city":"Ottawa",
    "sg:classifiers":[
        {
            "category":"Retail",
            "subcategory":"Auto Repair",
            "type":"Services"
        }
    ],
    "sg:phone":"+1 613 236 5582",
    "sg:postcode":"K1R 6J9",
    "sg:province":"ON",
    "sg:tags":[
        "repairing",
        "automobile",
        "muffler",
        "system",
        "exhaust"
    ],
    "wof:name":"Speedy Auto Svc",
    "wof:placetype":"venue"
},
  "geometry": {"coordinates":[-75.7028427124,45.4060897827],"type":"Point"}
}