{
  "type": "Feature",
  "properties": {
    "iso:country":"CA",
    "sg:address":"227 Douglasbank Dr SE",
    "sg:city":"Calgary",
    "sg:classifiers":[
        {
            "category":"Retail",
            "subcategory":"Animal Services",
            "type":"Services"
        }
    ],
    "sg:phone":"+1 403 279 4001",
    "sg:postcode":"T2Z 1X1",
    "sg:province":"AB",
    "sg:tags":[
        "pet",
        "grooming",
        "washing"
    ],
    "wof:name":"Your Pampered Pooch",
    "wof:placetype":"venue"
},
  "geometry": {"coordinates":[-114.012619019,50.9495735168],"type":"Point"}
}