{
  "type": "Feature",
  "properties": {
    "addr:full":"Cannington ON L0E 1E0",
    "addr:postcode":"l0e 1e0",
    "iso:country":"CA",
    "sg:city":"Cannington",
    "sg:classifiers":[
        {
            "category":"Organizations",
            "subcategory":"Community Association",
            "type":"Services"
        }
    ],
    "sg:phone":"+1 705 432 3006",
    "sg:postcode":"L0E 1E0",
    "sg:province":"ON",
    "sg:tags":[
        "club"
    ],
    "wof:name":"Royal Canadian Legion",
    "wof:placetype":"venue"
},
  "geometry": {"coordinates":[-79.035049,44.349068],"type":"Point"}
}