{
  "type": "Feature",
  "properties": {
    "addr:full":"2375 Rue Guenette Saint-Laurent QC H4R 2E9",
    "addr:housenumber":"2375",
    "addr:postcode":"h4r 2e9",
    "addr:street":"Rue Guenette",
    "iso:country":"CA",
    "sg:address":"2375 Rue Guenette",
    "sg:city":"Saint-Laurent",
    "sg:classifiers":[
        {
            "category":"Manufacturing",
            "subcategory":"Rubber & Plastics",
            "type":"Manufacturing & Wholesale Goods"
        }
    ],
    "sg:phone":"+1 514 333 9303",
    "sg:postcode":"H4R 2E9",
    "sg:province":"QC",
    "wof:name":"Cyb Plastique Enr",
    "wof:placetype":"venue"
},
  "geometry": {"coordinates":[-73.72709655760001,45.4994354248],"type":"Point"}
}