{
  "type": "Feature",
  "properties": {
    "addr:full":"1705 Lakeshore Dr Dorval QC H9S 2E9",
    "addr:housenumber":"1705",
    "addr:postcode":"h9s 2e9",
    "addr:street":"Lakeshore Dr",
    "iso:country":"CA",
    "sg:address":"1705 Lakeshore Dr",
    "sg:city":"Dorval",
    "sg:classifiers":[
        {
            "category":"Professional",
            "subcategory":"Management & Consulting",
            "type":"Services"
        }
    ],
    "sg:phone":"+1 514 636 9269",
    "sg:postcode":"H9S 2E9",
    "sg:province":"QC",
    "sg:tags":[
        "control",
        "consultant",
        "quality"
    ],
    "wof:name":"Soquetech Canada Ltee",
    "wof:placetype":"venue"
},
  "geometry": {"coordinates":[-73.7633514404,45.4407653809],"type":"Point"}
}