{
  "type": "Feature",
  "properties": {
    "addr:full":"44 Alagash Dr Sault Ste Marie ON P6A 5K6",
    "addr:housenumber":"44",
    "addr:postcode":"p6a 5k6",
    "addr:street":"Alagash Dr",
    "iso:country":"CA",
    "sg:address":"44 Alagash Dr",
    "sg:city":"Sault Ste Marie",
    "sg:classifiers":[
        {
            "category":"Building & Trades",
            "subcategory":"Construction",
            "type":"Services"
        }
    ],
    "sg:phone":"+1 705 779 3113",
    "sg:postcode":"P6A 5K6",
    "sg:province":"ON",
    "sg:tags":[
        "contractor",
        "general"
    ],
    "wof:name":"Jobst Construction",
    "wof:placetype":"venue"
},
  "geometry": {"coordinates":[-84.476021,46.46804],"type":"Point"}
}