{
  "type": "Feature",
  "properties": {
    "addr:full":"1102 Ridgeway Ave Coquitlam BC V3J 1S9",
    "addr:housenumber":"1102",
    "addr:postcode":"v3j 1s9",
    "addr:street":"Ridgeway Ave",
    "iso:country":"CA",
    "sg:address":"1102 Ridgeway Ave",
    "sg:city":"Coquitlam",
    "sg:classifiers":[
        {
            "category":"Health Services",
            "subcategory":"Clinic",
            "type":"Services"
        }
    ],
    "sg:phone":"+1 604 936 6555",
    "sg:postcode":"V3J 1S9",
    "sg:province":"BC",
    "sg:tags":[
        "therapist",
        "massage"
    ],
    "wof:name":"Alliance Massage Therapy Ctr",
    "wof:placetype":"venue"
},
  "geometry": {"coordinates":[-122.861656189,49.2494926453],"type":"Point"}
}