{
  "type": "Feature",
  "properties": {
    "addr:full":"5195 Timberlea Blvd Mississauga ON L4W 2S3",
    "addr:housenumber":"5195",
    "addr:postcode":"l4w 2s3",
    "addr:street":"Timberlea Blvd",
    "iso:country":"CA",
    "sg:address":"5195 Timberlea Blvd",
    "sg:city":"Mississauga",
    "sg:classifiers":[
        {
            "category":"Wholesale",
            "subcategory":"Durable Goods & Equipment",
            "type":"Manufacturing & Wholesale Goods"
        }
    ],
    "sg:phone":"+1 905 624 2064",
    "sg:postcode":"L4W 2S3",
    "sg:province":"ON",
    "sg:tags":[
        "importer"
    ],
    "wof:name":"Eurotrade Import Export Inc",
    "wof:placetype":"venue"
},
  "geometry": {"coordinates":[-79.639809,43.627419],"type":"Point"}
}