{
  "type": "Feature",
  "properties": {
    "iso:country":"CA",
    "sg:address":"545 Hillcrest Dr",
    "sg:city":"Fredericton",
    "sg:classifiers":[
        {
            "category":"Building & Trades",
            "subcategory":"Construction",
            "type":"Services"
        }
    ],
    "sg:phone":"+1 506 472 0790",
    "sg:postcode":"E3A 2X8",
    "sg:province":"NB",
    "sg:tags":[
        "home",
        "improvement"
    ],
    "wof:name":"Paul Arsenault Construction",
    "wof:placetype":"venue"
},
  "geometry": {"coordinates":[-66.627502,45.973026],"type":"Point"}
}