{
  "type": "Feature",
  "properties": {
    "addr:full":"7400 Boul Saint-Laurent Montreal QC H2R 2Y1",
    "addr:housenumber":"7400",
    "addr:postcode":"h2r 2y1",
    "addr:street":"Boul Saint-Laurent",
    "iso:country":"CA",
    "sg:address":"7400 Boul Saint-Laurent",
    "sg:city":"Montreal",
    "sg:classifiers":[
        {
            "category":"Organizations",
            "subcategory":"Professional Association",
            "type":"Services"
        }
    ],
    "sg:phone":"+1 514 948 1234",
    "sg:postcode":"H2R 2Y1",
    "sg:province":"QC",
    "wof:name":"Aquops Rescol",
    "wof:placetype":"venue"
},
  "geometry": {"coordinates":[-73.620621,45.535625],"type":"Point"}
}