{
  "type": "Feature",
  "properties": {
    "iso:country":"CA",
    "sg:address":"1030 Boul Saint-Joseph",
    "sg:city":"Hull",
    "sg:classifiers":[
        {
            "category":"Insurance",
            "subcategory":"Insurance Agent",
            "type":"Services"
        }
    ],
    "sg:phone":"+1 819 595 3500",
    "sg:postcode":"J8Z 1T3",
    "sg:province":"QC",
    "wof:name":"Allstate Du Canada CO",
    "wof:placetype":"venue"
},
  "geometry": {"coordinates":[-75.73820495610001,45.4704017639],"type":"Point"}
}