{
  "type": "Feature",
  "properties": {
    "addr:full":"6650 Hurontario St Mississauga ON L5W 1N3",
    "addr:housenumber":"6650",
    "addr:postcode":"l5w 1n3",
    "addr:street":"Hurontario St",
    "iso:country":"CA",
    "sg:address":"6650 Hurontario St",
    "sg:city":"Mississauga",
    "sg:classifiers":[
        {
            "category":"Restaurant",
            "type":"Food & Drink"
        }
    ],
    "sg:phone":"+1 905 564 0060",
    "sg:postcode":"L5W 1N3",
    "sg:province":"ON",
    "sg:tags":[
        "auditorium",
        "rooms",
        "banquet",
        "hall"
    ],
    "wof:name":"German Canadian Club Hansa",
    "wof:placetype":"venue"
},
  "geometry": {"coordinates":[-79.695671,43.638],"type":"Point"}
}