{
  "type": "Feature",
  "properties": {
    "addr:full":"503 Main St Woodstock NB E7M 3P1",
    "addr:housenumber":"503",
    "addr:postcode":"e7m 3p1",
    "addr:street":"Main St",
    "iso:country":"CA",
    "sg:address":"503 Main St",
    "sg:city":"Woodstock",
    "sg:classifiers":[
        {
            "category":"Professional",
            "subcategory":"Business Services",
            "type":"Services"
        }
    ],
    "sg:phone":"+1 506 328 2770",
    "sg:postcode":"E7M 3P1",
    "sg:province":"NB",
    "sg:tags":[
        "recording",
        "instrument",
        "studio",
        "musical"
    ],
    "wof:name":"Mes Music",
    "wof:placetype":"venue"
},
  "geometry": {"coordinates":[-67.57595825200001,46.1446228027],"type":"Point"}
}