{
  "type": "Feature",
  "properties": {
    "addr:full":"184 Belvedere Ave Charlottetown PE C1A 2Z1",
    "addr:housenumber":"184",
    "addr:postcode":"c1a 2z1",
    "addr:street":"Belvedere Ave",
    "iso:country":"CA",
    "sg:address":"184 Belvedere Ave",
    "sg:city":"Charlottetown",
    "sg:classifiers":[
        {
            "category":"Health Services",
            "subcategory":"Doctor",
            "type":"Services"
        }
    ],
    "sg:phone":"+1 902 566 4526",
    "sg:postcode":"C1A 2Z1",
    "sg:province":"PE",
    "sg:tags":[
        "dentist"
    ],
    "wof:name":"Connolly, Michael J DDS",
    "wof:placetype":"venue"
},
  "geometry": {"coordinates":[-63.125435,46.256706],"type":"Point"}
}