{
  "type": "Feature",
  "properties": {
    "iso:country":"CA",
    "sg:address":"175 Main St",
    "sg:city":"Smooth Rock Falls",
    "sg:classifiers":[
        {
            "category":"Food & Beverages",
            "subcategory":"Groceries & Convenience Stores",
            "type":"Retail Goods"
        }
    ],
    "sg:phone":"+1 705 338 2566",
    "sg:postcode":"P0L 2B0",
    "sg:province":"ON",
    "wof:name":"Chez Real Confectionery",
    "wof:placetype":"venue"
},
  "geometry": {"coordinates":[-81.621055603,49.2758789062],"type":"Point"}
}