{
  "type": "Feature",
  "properties": {
    "iso:country":"CA",
    "sg:city":"Dundas",
    "sg:classifiers":[
        {
            "category":"Shopping",
            "type":"Retail Goods"
        }
    ],
    "sg:phone":"+1 905 643 2223",
    "sg:postcode":"L9H 5E1",
    "sg:province":"ON",
    "sg:tags":[
        "equipment",
        "wine",
        "winery",
        "supply"
    ],
    "wof:name":"O'Daly's Brewing Emporium",
    "wof:placetype":"venue"
},
  "geometry": {"coordinates":[-79.9523773193,43.2637786865],"type":"Point"}
}