{
  "type": "Feature",
  "properties": {
    "addr:full":"516 Seaton St Winnipeg MB R3K 1M5",
    "addr:housenumber":"516",
    "addr:postcode":"r3k 1m5",
    "addr:street":"Seaton St",
    "iso:country":"CA",
    "sg:address":"516 Seaton St",
    "sg:city":"Winnipeg",
    "sg:classifiers":[
        {
            "category":"Personal",
            "subcategory":"Beauty Salon",
            "type":"Services"
        }
    ],
    "sg:phone":"+1 204 831 8385",
    "sg:postcode":"R3K 1M5",
    "sg:province":"MB",
    "wof:name":"Cardillo's Hair Design",
    "wof:placetype":"venue"
},
  "geometry": {"coordinates":[-97.30387899999999,49.88105],"type":"Point"}
}