{
  "type": "Feature",
  "properties": {
    "addr:full":"270 Transport Rd Springfield MB R2C 2Z2",
    "addr:housenumber":"270",
    "addr:postcode":"r2c 2z2",
    "addr:street":"Transport Rd",
    "iso:country":"CA",
    "sg:address":"270 Transport Rd",
    "sg:city":"Springfield",
    "sg:classifiers":[
        {
            "category":"Building & Trades",
            "subcategory":"Construction",
            "type":"Services"
        }
    ],
    "sg:phone":"+1 204 222 7663",
    "sg:postcode":"R2C 2Z2",
    "sg:province":"MB",
    "sg:tags":[
        "roofing",
        "contractor"
    ],
    "wof:name":"A Sarna Roofing Inc",
    "wof:placetype":"venue"
},
  "geometry": {"coordinates":[-96.971642,49.917805],"type":"Point"}
}