{
  "type": "Feature",
  "properties": {
    "iso:country":"CA",
    "sg:address":"2725 Round Lake Rd",
    "sg:city":"Round Lake Centre",
    "sg:classifiers":[
        {
            "category":"Education",
            "subcategory":"School",
            "type":"Public Place"
        }
    ],
    "sg:phone":"+1 613 757 2291",
    "sg:postcode":"K0J 2J0",
    "sg:province":"ON",
    "wof:name":"St Casimir's School",
    "wof:placetype":"venue"
},
  "geometry": {"coordinates":[-77.538391,45.616329],"type":"Point"}
}