{
  "type": "Feature",
  "properties": {
    "addr:full":"258 Van Horne St Thunder Bay ON P7A 3E7",
    "addr:housenumber":"258",
    "addr:postcode":"p7a 3e7",
    "addr:street":"Van Horne St",
    "iso:country":"CA",
    "sg:address":"258 Van Horne St",
    "sg:city":"Thunder Bay",
    "sg:classifiers":[
        {
            "category":"Organizations",
            "subcategory":"Religious Organization",
            "type":"Services"
        }
    ],
    "sg:phone":"+1 807 683 6364",
    "sg:postcode":"P7A 3E7",
    "sg:province":"ON",
    "sg:tags":[
        "church"
    ],
    "wof:name":"United Pentecostal Church",
    "wof:placetype":"venue"
},
  "geometry": {"coordinates":[-89.21118927000001,48.4437904358],"type":"Point"}
}