{
  "type": "Feature",
  "properties": {
    "addr:full":"Montreal QC H2Z 1C1",
    "addr:postcode":"h2z 1c1",
    "iso:country":"CA",
    "sg:city":"Montreal",
    "sg:classifiers":[
        {
            "category":"Shopping",
            "subcategory":"Clothing, Apparel, & Fashions",
            "type":"Retail Goods"
        }
    ],
    "sg:phone":"+1 514 397 0288",
    "sg:postcode":"H2Z 1C1",
    "sg:province":"QC",
    "sg:tags":[
        "item",
        "boutique"
    ],
    "wof:name":"L'Expression DE LA Vie",
    "wof:placetype":"venue"
},
  "geometry": {"coordinates":[-73.560181,45.507576],"type":"Point"}
}