{
  "type": "Feature",
  "properties": {
    "addr:full":"PO Box 577 Caroline AB T0M 0M0",
    "addr:housenumber":"po;577",
    "addr:postcode":"t0m 0m0",
    "addr:street":"Box",
    "iso:country":"CA",
    "sg:address":"PO Box 577",
    "sg:city":"Caroline",
    "sg:classifiers":[
        {
            "category":"Building & Trades",
            "subcategory":"Construction",
            "type":"Services"
        }
    ],
    "sg:phone":"+1 403 722 2505",
    "sg:postcode":"T0M 0M0",
    "sg:province":"AB",
    "sg:tags":[
        "sandblasting"
    ],
    "wof:name":"Slager's Painting Svc",
    "wof:placetype":"venue"
},
  "geometry": {"coordinates":[-114.740707,52.09359],"type":"Point"}
}