{
  "type": "Feature",
  "properties": {
    "addr:full":"555 Cedar 100 Mile House BC V0K 2E0",
    "addr:housenumber":"555",
    "addr:postcode":"v0k 2e0",
    "addr:street":"Cedar",
    "iso:country":"CA",
    "sg:address":"555 Cedar",
    "sg:city":"100 Mile House",
    "sg:classifiers":[
        {
            "category":"Government",
            "subcategory":"Office",
            "type":"Public Place"
        }
    ],
    "sg:phone":"+1 250 395 7606",
    "sg:postcode":"V0K 2E0",
    "sg:province":"BC",
    "wof:name":"South Cariboo Community Hlth",
    "wof:placetype":"venue"
},
  "geometry": {"coordinates":[-121.292793,51.638081],"type":"Point"}
}