{
  "type": "Feature",
  "properties": {
    "addr:full":"313 Broadway St S Crystal City MB R0K 0N0",
    "addr:housenumber":"313",
    "addr:postcode":"r0k 0n0",
    "addr:street":"Broadway St S",
    "iso:country":"CA",
    "sg:address":"313 Broadway St S",
    "sg:city":"Crystal City",
    "sg:classifiers":[
        {
            "category":"Retail",
            "subcategory":"Auto Repair",
            "type":"Services"
        }
    ],
    "sg:phone":"+1 204 873 2015",
    "sg:postcode":"R0K 0N0",
    "sg:province":"MB",
    "sg:tags":[
        "repairing",
        "automobile"
    ],
    "wof:name":"Ike's Repair Svc",
    "wof:placetype":"venue"
},
  "geometry": {"coordinates":[-98.95050000000001,49.14539],"type":"Point"}
}