{
  "type": "Feature",
  "properties": {
    "addr:full":"15 Capt Kennedy Rd St Andrews MB R1A 2X6",
    "addr:housenumber":"15",
    "addr:postcode":"r1a 2x6",
    "addr:street":"Capt Kennedy Rd",
    "iso:country":"CA",
    "sg:address":"15 Capt Kennedy Rd",
    "sg:city":"St Andrews",
    "sg:classifiers":[
        {
            "category":"Wholesale",
            "subcategory":"Medical Equipment & Supplies",
            "type":"Manufacturing & Wholesale Goods"
        }
    ],
    "sg:phone":"+1 204 783 6353",
    "sg:postcode":"R1A 2X6",
    "sg:province":"MB",
    "sg:tags":[
        "physician",
        "surgeon"
    ],
    "wof:name":"Western Therapy Supplies",
    "wof:placetype":"venue"
},
  "geometry": {"coordinates":[-96.97995,50.071712],"type":"Point"}
}