{
  "type": "Feature",
  "properties": {
    "addr:full":"Boul DE L'Aterrissment Ile-A-LA-Crosse SK S0M 1C0",
    "addr:postcode":"s0m 1c0",
    "addr:street":"Boul;Ile-A-La-Crosse",
    "iso:country":"CA",
    "sg:address":"Boul DE L'Aterrissment",
    "sg:city":"Ile-A-LA-Crosse",
    "sg:classifiers":[
        {
            "category":"Social Services",
            "subcategory":"Child Care",
            "type":"Services"
        }
    ],
    "sg:phone":"+1 306 833 2595",
    "sg:postcode":"S0M 1C0",
    "sg:province":"SK",
    "sg:tags":[
        "kindergarten",
        "academic",
        "school"
    ],
    "wof:name":"Wecihik Awasisak Program",
    "wof:placetype":"venue"
},
  "geometry": {"coordinates":[-107.90625,55.452339],"type":"Point"}
}