{
  "type": "Feature",
  "properties": {
    "iso:country":"CA",
    "sg:address":"2 Allaura Blvd",
    "sg:city":"Aurora",
    "sg:classifiers":[
        {
            "category":"Wholesale",
            "subcategory":"Auto Parts",
            "type":"Manufacturing & Wholesale Goods"
        }
    ],
    "sg:phone":"+1 905 726 4441",
    "sg:postcode":"L4G 3S5",
    "sg:province":"ON",
    "sg:tags":[
        "equipment",
        "conversion",
        "accessory",
        "truck",
        "van"
    ],
    "wof:name":"Van & Truck World",
    "wof:placetype":"venue"
},
  "geometry": {"coordinates":[-79.4628753662,43.9840621948],"type":"Point"}
}