{
  "type": "Feature",
  "properties": {
    "addr:full":"1300 Rue King E Sherbrooke QC J1G 1E4",
    "addr:housenumber":"1300",
    "addr:postcode":"j1g 1e4",
    "addr:street":"Rue King E",
    "iso:country":"CA",
    "sg:address":"1300 Rue King E",
    "sg:city":"Sherbrooke",
    "sg:classifiers":[
        {
            "category":"Retail",
            "subcategory":"Auto Repair",
            "type":"Services"
        }
    ],
    "sg:phone":"+1 819 565 4555",
    "sg:postcode":"J1G 1E4",
    "sg:province":"QC",
    "sg:tags":[
        "repairing",
        "automobile",
        "body"
    ],
    "wof:name":"Fix Auto Sherbrooke",
    "wof:placetype":"venue"
},
  "geometry": {"coordinates":[-71.85984000000001,45.408833],"type":"Point"}
}