{
  "type": "Feature",
  "properties": {
    "addr:full":"900 Rue Front Longueuil QC J4K 1Z8",
    "addr:housenumber":"900",
    "addr:postcode":"j4k 1z8",
    "addr:street":"Rue Front",
    "iso:country":"CA",
    "sg:address":"900 Rue Front",
    "sg:city":"Longueuil",
    "sg:classifiers":[
        {
            "category":"Food & Beverages",
            "subcategory":"Groceries & Convenience Stores",
            "type":"Retail Goods"
        }
    ],
    "sg:phone":"+1 450 674 1559",
    "sg:postcode":"J4K 1Z8",
    "sg:province":"QC",
    "sg:tags":[
        "grocer"
    ],
    "wof:name":"Marche Richelieu Christian",
    "wof:placetype":"venue"
},
  "geometry": {"coordinates":[-73.4919967651,45.5197677612],"type":"Point"}
}