{
  "type": "Feature",
  "properties": {
    "addr:full":"2110 Rue Sainte-Catherine O Montreal QC H3H 1M7",
    "addr:housenumber":"2110",
    "addr:postcode":"h3h 1m7",
    "addr:street":"Rue Sainte-Catherine O",
    "iso:country":"CA",
    "sg:address":"2110 Rue Sainte-Catherine O",
    "sg:city":"Montreal",
    "sg:classifiers":[
        {
            "category":"Cinema",
            "subcategory":"Movie Rental",
            "type":"Entertainment"
        }
    ],
    "sg:phone":"+1 514 932 0063",
    "sg:postcode":"H3H 1M7",
    "sg:province":"QC",
    "sg:tags":[
        "leasing",
        "video",
        "disc",
        "tape"
    ],
    "wof:name":"Blockbuster Video",
    "wof:placetype":"venue"
},
  "geometry": {"coordinates":[-73.5499420166,45.5249633789],"type":"Point"}
}