{
  "type": "Feature",
  "properties": {
    "iso:country":"CA",
    "sg:address":"35 Hillside St",
    "sg:city":"Sydney",
    "sg:classifiers":[
        {
            "category":"Building & Trades",
            "subcategory":"Plumbing",
            "type":"Services"
        }
    ],
    "sg:phone":"+1 902 562 8470",
    "sg:postcode":"B1P 3P1",
    "sg:province":"NS",
    "sg:tags":[
        "conditioning",
        "air",
        "system",
        "contractor"
    ],
    "wof:name":"Mira Road Hvac",
    "wof:placetype":"venue"
},
  "geometry": {"coordinates":[-60.1805534363,46.1247329712],"type":"Point"}
}