{
  "type": "Feature",
  "properties": {
    "addr:full":"Kitchener ON N2M 1R5",
    "addr:postcode":"n2m 1r5",
    "iso:country":"CA",
    "sg:city":"Kitchener",
    "sg:classifiers":[
        {
            "category":"Retail",
            "subcategory":"Auto Repair",
            "type":"Services"
        }
    ],
    "sg:phone":"+1 519 741 0700",
    "sg:postcode":"N2M 1R5",
    "sg:province":"ON",
    "sg:tags":[
        "transmission",
        "automobile",
        "repairing"
    ],
    "wof:name":"Mister Transmission",
    "wof:placetype":"venue"
},
  "geometry": {"coordinates":[-80.5122756958,43.4353866577],"type":"Point"}
}