{
  "type": "Feature",
  "properties": {
    "iso:country":"CA",
    "sg:city":"Calgary",
    "sg:classifiers":[
        {
            "category":"Health Services",
            "subcategory":"Doctor",
            "type":"Services"
        }
    ],
    "sg:phone":"+1 403 509 4740",
    "sg:postcode":"T2V 4R6",
    "sg:province":"AB",
    "sg:tags":[
        "clinic"
    ],
    "wof:name":"Hbot Clinic",
    "wof:placetype":"venue"
},
  "geometry": {"coordinates":[-114.087341309,50.9938240051],"type":"Point"}
}