{
  "type": "Feature",
  "properties": {
    "addr:full":"1458 Industrial Way Parksville BC V9P 1W3",
    "addr:housenumber":"1458",
    "addr:postcode":"v9p 1w3",
    "addr:street":"Industrial Way",
    "iso:country":"CA",
    "sg:address":"1458 Industrial Way",
    "sg:city":"Parksville",
    "sg:classifiers":[
        {
            "category":"Autos & Motor Vehicles",
            "subcategory":"Recreational Vehicle Sales",
            "type":"Retail Goods"
        }
    ],
    "sg:phone":"+1 250 248 3602",
    "sg:postcode":"V9P 1W3",
    "sg:province":"BC",
    "sg:tags":[
        "trailer"
    ],
    "wof:name":"Coast Rv Sales & Svc Ltd",
    "wof:placetype":"venue"
},
  "geometry": {"coordinates":[-124.267776,49.308376],"type":"Point"}
}