{
  "type": "Feature",
  "properties": {
    "addr:full":"10701 Av Bellevois Montreal-Nord QC H1H 3C7",
    "addr:housenumber":"10701",
    "addr:postcode":"h1h 3c7",
    "addr:street":"Av Bellevois",
    "iso:country":"CA",
    "sg:address":"10701 Av Bellevois",
    "sg:city":"Montreal-Nord",
    "sg:classifiers":[
        {
            "category":"Restaurant",
            "type":"Food & Drink"
        }
    ],
    "sg:phone":"+1 514 955 6932",
    "sg:postcode":"H1H 3C7",
    "sg:province":"QC",
    "wof:name":"Resto LA Spirale",
    "wof:placetype":"venue"
},
  "geometry": {"coordinates":[-73.6274108887,45.5937767029],"type":"Point"}
}