{
  "type": "Feature",
  "properties": {
    "addr:full":"Hearst ON P0L 1N0",
    "addr:postcode":"p0l 1n0",
    "iso:country":"CA",
    "sg:city":"Hearst",
    "sg:classifiers":[
        {
            "category":"Personal",
            "subcategory":"Massage",
            "type":"Services"
        }
    ],
    "sg:phone":"+1 705 362 1112",
    "sg:postcode":"P0L 1N0",
    "sg:province":"ON",
    "wof:name":"Great North Spa",
    "wof:placetype":"venue"
},
  "geometry": {"coordinates":[-83.667686,49.689095],"type":"Point"}
}