{
  "type": "Feature",
  "properties": {
    "addr:full":"701 10 St Wainwright AB T9W 1P3",
    "addr:housenumber":"701 10",
    "addr:postcode":"t9w 1p3",
    "addr:street":"St",
    "iso:country":"CA",
    "sg:address":"701 10 St",
    "sg:city":"Wainwright",
    "sg:classifiers":[
        {
            "category":"Building & Trades",
            "subcategory":"Equipment Rental",
            "type":"Services"
        }
    ],
    "sg:phone":"+1 780 842 5262",
    "sg:postcode":"T9W 1P3",
    "sg:province":"AB",
    "sg:tags":[
        "player",
        "recorder",
        "video"
    ],
    "wof:name":"Showtime Video",
    "wof:placetype":"venue"
},
  "geometry": {"coordinates":[-110.856194,52.837742],"type":"Point"}
}