{
  "type": "Feature",
  "properties": {
    "addr:full":"Sundridge ON P0A 1Z0",
    "addr:postcode":"p0a 1z0",
    "iso:country":"CA",
    "sg:city":"Sundridge",
    "sg:classifiers":[
        {
            "category":"Home & Garden",
            "subcategory":"Garden Supply",
            "type":"Retail Goods"
        }
    ],
    "sg:phone":"+1 705 384 5345",
    "sg:postcode":"P0A 1Z0",
    "sg:province":"ON",
    "sg:tags":[
        "automobile",
        "parts",
        "snow",
        "removal"
    ],
    "wof:name":"Lou Dennis Automotive Supply",
    "wof:placetype":"venue"
},
  "geometry": {"coordinates":[-79.399536,45.766579],"type":"Point"}
}