{
  "type": "Feature",
  "properties": {
    "addr:full":"10966 Ninth Line Markham ON L6B 1A8",
    "addr:housenumber":"10966",
    "addr:postcode":"l6b 1a8",
    "addr:street":"Ninth Line",
    "iso:country":"CA",
    "sg:address":"10966 Ninth Line",
    "sg:city":"Markham",
    "sg:classifiers":[
        {
            "category":"Wholesale",
            "subcategory":"Groceries",
            "type":"Manufacturing & Wholesale Goods"
        }
    ],
    "sg:phone":"+1 905 642 4753",
    "sg:postcode":"L6B 1A8",
    "sg:province":"ON",
    "sg:tags":[
        "pet",
        "food"
    ],
    "wof:name":"Markham Creek Unique Pets",
    "wof:placetype":"venue"
},
  "geometry": {"coordinates":[-79.250038,43.939281],"type":"Point"}
}