{
  "type": "Feature",
  "properties": {
    "iso:country":"CA",
    "sg:city":"Mississauga",
    "sg:classifiers":[
        {
            "category":"Insurance",
            "subcategory":"Insurance Agent",
            "type":"Services"
        }
    ],
    "sg:phone":"+1 905 755 9874",
    "sg:postcode":"L5R 3G5",
    "sg:province":"ON",
    "wof:name":"Contact Plus Insurance Network",
    "wof:placetype":"venue"
},
  "geometry": {"coordinates":[-79.6736068726,43.6217422485],"type":"Point"}
}