{
  "type": "Feature",
  "properties": {
    "addr:full":"96 Meg Dr London ON N6E 3T7",
    "addr:housenumber":"96",
    "addr:postcode":"n6e 3t7",
    "addr:street":"Meg Dr",
    "iso:country":"CA",
    "sg:address":"96 Meg Dr",
    "sg:city":"London",
    "sg:classifiers":[
        {
            "category":"Building & Trades",
            "subcategory":"Plumbing",
            "type":"Services"
        }
    ],
    "sg:phone":"+1 519 685 5983",
    "sg:postcode":"N6E 3T7",
    "sg:province":"ON",
    "sg:tags":[
        "sheet",
        "work",
        "metal",
        "contractor"
    ],
    "wof:name":"Sun Ventilating CO Ltd",
    "wof:placetype":"venue"
},
  "geometry": {"coordinates":[-81.2307891846,42.9214515686],"type":"Point"}
}