{
  "type": "Feature",
  "properties": {
    "addr:full":"150 Arden Ave Winnipeg MB R2M 2K3",
    "addr:housenumber":"150",
    "addr:postcode":"r2m 2k3",
    "addr:street":"Arden Ave",
    "iso:country":"CA",
    "sg:address":"150 Arden Ave",
    "sg:city":"Winnipeg",
    "sg:classifiers":[
        {
            "category":"Professional",
            "subcategory":"Engineering",
            "type":"Services"
        }
    ],
    "sg:phone":"+1 204 255 4015",
    "sg:postcode":"R2M 2K3",
    "sg:province":"MB",
    "sg:tags":[
        "engineer"
    ],
    "wof:name":"R B Piercy Engineering Assoc",
    "wof:placetype":"venue"
},
  "geometry": {"coordinates":[-97.126564,49.830544],"type":"Point"}
}