{
  "type": "Feature",
  "properties": {
    "addr:full":"303 Main St St Martins NB E5R 1C1",
    "addr:housenumber":"303",
    "addr:postcode":"e5r 1c1",
    "addr:street":"Main St St",
    "iso:country":"CA",
    "sg:address":"303 Main St",
    "sg:city":"St Martins",
    "sg:classifiers":[
        {
            "category":"Travel",
            "subcategory":"Hotels & Motels",
            "type":"Entertainment"
        }
    ],
    "sg:phone":"+1 506 833 4534",
    "sg:postcode":"E5R 1C1",
    "sg:province":"NB",
    "sg:tags":[
        "inn"
    ],
    "wof:name":"St Martins Country Inn",
    "wof:placetype":"venue"
},
  "geometry": {"coordinates":[-65.55317687989999,45.3495597839],"type":"Point"}
}