{
  "type": "Feature",
  "properties": {
    "iso:country":"CA",
    "sg:address":"18 Ringwood Dr",
    "sg:city":"Stouffville",
    "sg:classifiers":[
        {
            "category":"Food & Beverages",
            "subcategory":"Bakery",
            "type":"Retail Goods"
        }
    ],
    "sg:phone":"+1 905 642 4544",
    "sg:postcode":"L4A 8C1",
    "sg:province":"ON",
    "sg:tags":[
        "doughnut"
    ],
    "wof:name":"Dainty Donuts & Deli",
    "wof:placetype":"venue"
},
  "geometry": {"coordinates":[-79.274269,43.964622],"type":"Point"}
}