{
  "type": "Feature",
  "properties": {
    "addr:full":"23318 Industrial Rd Thamesville ON N0P 2K0",
    "addr:housenumber":"23318",
    "addr:postcode":"n0p 2k0",
    "addr:street":"Industrial Rd",
    "iso:country":"CA",
    "sg:address":"23318 Industrial Rd",
    "sg:city":"Thamesville",
    "sg:classifiers":[
        {
            "category":"Wholesale",
            "subcategory":"Farm Supplies",
            "type":"Manufacturing & Wholesale Goods"
        }
    ],
    "sg:phone":"+1 519 692 3804",
    "sg:postcode":"N0P 2K0",
    "sg:province":"ON",
    "sg:tags":[
        "livestock"
    ],
    "wof:name":"Thames Sales Yard Ltd",
    "wof:placetype":"venue"
},
  "geometry": {"coordinates":[-81.98571800000001,42.556416],"type":"Point"}
}