{
  "type": "Feature",
  "properties": {
    "addr:full":"10271 Rue Renaude-Lapointe Anjou QC H1J 2T4",
    "addr:housenumber":"10271",
    "addr:postcode":"h1j 2t4",
    "addr:street":"Rue Renaude-Lapointe",
    "iso:country":"CA",
    "sg:address":"10271 Rue Renaude-Lapointe",
    "sg:city":"Anjou",
    "sg:classifiers":[
        {
            "category":"Education",
            "subcategory":"School",
            "type":"Public Place"
        }
    ],
    "sg:phone":"+1 514 355 8169",
    "sg:postcode":"H1J 2T4",
    "sg:province":"QC",
    "sg:tags":[
        "academic",
        "special"
    ],
    "wof:name":"Ecole DE Pose D'Ongles Cavan",
    "wof:placetype":"venue"
},
  "geometry": {"coordinates":[-73.5885925293,45.6113815308],"type":"Point"}
}