{
  "type": "Feature",
  "properties": {
    "addr:full":"2425 Burrard St Vancouver BC V6J 3J3",
    "addr:housenumber":"2425",
    "addr:postcode":"v6j 3j3",
    "addr:street":"Burrard St",
    "iso:country":"CA",
    "sg:address":"2425 Burrard St",
    "sg:city":"Vancouver",
    "sg:classifiers":[
        {
            "category":"Insurance",
            "subcategory":"Insurance Agent",
            "type":"Services"
        }
    ],
    "sg:phone":"+1 604 736 7668",
    "sg:postcode":"V6J 3J3",
    "sg:province":"BC",
    "wof:name":"Rainbow Insurance Ltd",
    "wof:placetype":"venue"
},
  "geometry": {"coordinates":[-123.145927,49.264366],"type":"Point"}
}