{
  "type": "Feature",
  "properties": {
    "addr:full":"854 Bathurst St Toronto ON M5R 3G3",
    "addr:housenumber":"854",
    "addr:postcode":"m5r 3g3",
    "addr:street":"Bathurst St",
    "iso:country":"CA",
    "sg:address":"854 Bathurst St",
    "sg:city":"Toronto",
    "sg:classifiers":[
        {
            "category":"Food & Beverages",
            "subcategory":"Groceries & Convenience Stores",
            "type":"Retail Goods"
        }
    ],
    "sg:phone":"+1 416 533 4872",
    "sg:postcode":"M5R 3G3",
    "sg:province":"ON",
    "sg:tags":[
        "grocer"
    ],
    "wof:name":"Joyce's West Indies Food",
    "wof:placetype":"venue"
},
  "geometry": {"coordinates":[-79.41203299999999,43.666725],"type":"Point"}
}