{
  "type": "Feature",
  "properties": {
    "addr:full":"Sherbrooke QC J1H 6L1",
    "addr:postcode":"j1h 6l1",
    "iso:country":"CA",
    "sg:city":"Sherbrooke",
    "sg:classifiers":[
        {
            "category":"Wholesale",
            "subcategory":"Electrical",
            "type":"Manufacturing & Wholesale Goods"
        }
    ],
    "sg:phone":"+1 819 822 4700",
    "sg:postcode":"J1H 6L1",
    "sg:province":"QC",
    "sg:tags":[
        "electric",
        "motor"
    ],
    "wof:name":"Moteurs Electrique Gosselin",
    "wof:placetype":"venue"
},
  "geometry": {"coordinates":[-71.88604736329999,45.4180793762],"type":"Point"}
}