{
  "type": "Feature",
  "properties": {
    "addr:full":"101 9th St W Meadow Lake SK S9X 1S3",
    "addr:housenumber":"101",
    "addr:postcode":"s9x 1s3",
    "addr:street":"9Th St W Meadow",
    "iso:country":"CA",
    "sg:address":"101 9th St W",
    "sg:city":"Meadow Lake",
    "sg:classifiers":[
        {
            "category":"Manufacturing",
            "subcategory":"Motor Vehicles & Parts",
            "type":"Manufacturing & Wholesale Goods"
        }
    ],
    "sg:phone":"+1 306 236 3009",
    "sg:postcode":"S9X 1S3",
    "sg:province":"SK",
    "sg:tags":[
        "equipment",
        "all",
        "terrain",
        "truck"
    ],
    "wof:name":"Extreme Speed Rv Ltd",
    "wof:placetype":"venue"
},
  "geometry": {"coordinates":[-108.452980041,54.1245117188],"type":"Point"}
}