{
  "type": "Feature",
  "properties": {
    "addr:full":"40 2E Av Terrasse Raymond Oka QC J0N 1E0",
    "addr:housenumber":"40",
    "addr:postcode":"j0n 1e0",
    "addr:street":"2E Av Terrasse Raymond",
    "iso:country":"CA",
    "sg:address":"40 2E Av Terrasse Raymond",
    "sg:city":"Oka",
    "sg:classifiers":[
        {
            "category":"Social Services",
            "type":"Services"
        }
    ],
    "sg:phone":"+1 450 479 1700",
    "sg:postcode":"J0N 1E0",
    "sg:province":"QC",
    "sg:tags":[
        "organization",
        "welfare"
    ],
    "wof:name":"Kyot Kanasatake Youth-Today",
    "wof:placetype":"venue"
},
  "geometry": {"coordinates":[-74.130569458,45.485244751],"type":"Point"}
}