{
  "type": "Feature",
  "properties": {
    "addr:full":"149 Rue Maltais Sept-Iles QC G4R 3J8",
    "addr:housenumber":"149",
    "addr:postcode":"g4r 3j8",
    "addr:street":"Rue Maltais Sept-Iles",
    "iso:country":"CA",
    "sg:address":"149 Rue Maltais",
    "sg:city":"Sept-Iles",
    "sg:classifiers":[
        {
            "category":"Travel",
            "subcategory":"Travel Agent",
            "type":"Entertainment"
        }
    ],
    "sg:phone":"+1 418 968 4707",
    "sg:postcode":"G4R 3J8",
    "sg:province":"QC",
    "sg:tags":[
        "agency",
        "steamship"
    ],
    "wof:name":"Relais Nordik",
    "wof:placetype":"venue"
},
  "geometry": {"coordinates":[-66.367378,50.210281],"type":"Point"}
}