{
  "type": "Feature",
  "properties": {
    "addr:full":"19789 Telegraph Trail Langley BC V1M 3E6",
    "addr:housenumber":"19789",
    "addr:postcode":"v1m 3e6",
    "addr:street":"Telegraph Trail",
    "iso:country":"CA",
    "sg:address":"19789 Telegraph Trail",
    "sg:city":"Langley",
    "sg:classifiers":[
        {
            "category":"Manufacturing",
            "subcategory":"Apparel",
            "type":"Manufacturing & Wholesale Goods"
        }
    ],
    "sg:phone":"+1 604 888 1422",
    "sg:postcode":"V1M 3E6",
    "sg:province":"BC",
    "sg:tags":[
        "tarpaulin"
    ],
    "wof:name":"Fraser Valley Tarp & Tie Ltd",
    "wof:placetype":"venue"
},
  "geometry": {"coordinates":[-122.674103,49.17836],"type":"Point"}
}