{
  "type": "Feature",
  "properties": {
    "addr:full":"21 Plank Rd Straffordville ON N0J 1Y0",
    "addr:housenumber":"21",
    "addr:postcode":"n0j 1y0",
    "addr:street":"Plank Rd",
    "iso:country":"CA",
    "sg:address":"21 Plank Rd",
    "sg:city":"Straffordville",
    "sg:classifiers":[
        {
            "category":"Retail",
            "subcategory":"Auto Repair",
            "type":"Services"
        }
    ],
    "sg:phone":"+1 519 866 3454",
    "sg:postcode":"N0J 1Y0",
    "sg:province":"ON",
    "sg:tags":[
        "repairing",
        "automobile"
    ],
    "wof:name":"Cain's Auto Sales & Svc",
    "wof:placetype":"venue"
},
  "geometry": {"coordinates":[-80.7834472656,42.7287902832],"type":"Point"}
}