{
  "type": "Feature",
  "properties": {
    "addr:full":"1140 Front St North Bay ON P1B 6P2",
    "addr:housenumber":"1140",
    "addr:postcode":"p1b 6p2",
    "addr:street":"Front St",
    "iso:country":"CA",
    "sg:address":"1140 Front St",
    "sg:city":"North Bay",
    "sg:classifiers":[
        {
            "category":"Education",
            "subcategory":"School",
            "type":"Public Place"
        }
    ],
    "sg:phone":"+1 705 472 1201",
    "sg:postcode":"P1B 6P2",
    "sg:province":"ON",
    "wof:name":"Nipissing Parry Sound Catholic",
    "wof:placetype":"venue"
},
  "geometry": {"coordinates":[-79.4567489624,46.3181724548],"type":"Point"}
}