{
  "type": "Feature",
  "properties": {
    "addr:full":"1010 4 Ave S Lethbridge AB T1J 0P5",
    "addr:housenumber":"1010",
    "addr:postcode":"t1j 0p5",
    "addr:street":"4 Ave S",
    "iso:country":"CA",
    "sg:address":"1010 4 Ave S",
    "sg:city":"Lethbridge",
    "sg:classifiers":[
        {
            "category":"Social Services",
            "type":"Services"
        }
    ],
    "sg:phone":"+1 403 320 4232",
    "sg:postcode":"T1J 0P5",
    "sg:province":"AB",
    "sg:tags":[
        "counseling",
        "welfare",
        "organization"
    ],
    "wof:name":"Family Centre",
    "wof:placetype":"venue"
},
  "geometry": {"coordinates":[-112.83091735799999,49.6945648193],"type":"Point"}
}