{
  "type": "Feature",
  "properties": {
    "iso:country":"CA",
    "sg:address":"Steeles Ave W",
    "sg:city":"North York",
    "sg:classifiers":[
        {
            "category":"Home & Garden",
            "subcategory":"Building Materials",
            "type":"Retail Goods"
        }
    ],
    "sg:phone":"+1 905 274 1585",
    "sg:postcode":"M3N 1V7",
    "sg:province":"ON",
    "sg:tags":[
        "glass",
        "window",
        "plate"
    ],
    "wof:name":"Armor Shields Auto Glass",
    "wof:placetype":"venue"
},
  "geometry": {"coordinates":[-79.4214553833,43.7977600098],"type":"Point"}
}