{
  "type": "Feature",
  "properties": {
    "iso:country":"CA",
    "sg:address":"1222 Rue Bagot",
    "sg:city":"LA Baie",
    "sg:classifiers":[
        {
            "category":"Building & Trades",
            "subcategory":"Construction",
            "type":"Services"
        }
    ],
    "sg:phone":"+1 418 544 6896",
    "sg:postcode":"G7B 2P4",
    "sg:province":"QC",
    "sg:tags":[
        "sandblasting",
        "painter"
    ],
    "wof:name":"Metal Fergus Ltee",
    "wof:placetype":"venue"
},
  "geometry": {"coordinates":[-70.88483428959999,48.3379135132],"type":"Point"}
}