{
  "type": "Feature",
  "properties": {
    "addr:full":"Ottawa ON K1P 5K6",
    "addr:postcode":"k1p 5k6",
    "iso:country":"CA",
    "sg:city":"Ottawa",
    "sg:classifiers":[
        {
            "category":"Professional",
            "subcategory":"Research",
            "type":"Services"
        }
    ],
    "sg:phone":"+1 613 563 4455",
    "sg:postcode":"K1P 5K6",
    "sg:province":"ON",
    "sg:tags":[
        "market",
        "analysis"
    ],
    "wof:name":"Earnscliffe Strategy Group",
    "wof:placetype":"venue"
},
  "geometry": {"coordinates":[-75.69532,45.423283],"type":"Point"}
}