{
  "type": "Feature",
  "properties": {
    "iso:country":"CA",
    "sg:address":"6071 Fairview Rd",
    "sg:city":"St Thomas",
    "sg:classifiers":[
        {
            "category":"Organizations",
            "subcategory":"Religious Organization",
            "type":"Services"
        }
    ],
    "sg:phone":"+1 519 633 2883",
    "sg:postcode":"N5P 3S8",
    "sg:province":"ON",
    "sg:tags":[
        "church"
    ],
    "wof:name":"Plains Baptist Church",
    "wof:placetype":"venue"
},
  "geometry": {"coordinates":[-81.166527,42.749271],"type":"Point"}
}