{
  "type": "Feature",
  "properties": {
    "addr:full":"3064 Don Mills Rd North York ON M2J 3C1",
    "addr:housenumber":"3064",
    "addr:postcode":"m2j 3c1",
    "addr:street":"Don Mills Rd",
    "iso:country":"CA",
    "sg:address":"3064 Don Mills Rd",
    "sg:city":"North York",
    "sg:classifiers":[
        {
            "category":"Food & Beverages",
            "subcategory":"Bakery",
            "type":"Retail Goods"
        }
    ],
    "sg:phone":"+1 416 494 5438",
    "sg:postcode":"M2J 3C1",
    "sg:province":"ON",
    "sg:tags":[
        "baker"
    ],
    "wof:name":"Allan's Pastry Shop",
    "wof:placetype":"venue"
},
  "geometry": {"coordinates":[-79.353531,43.788082],"type":"Point"}
}