{
  "type": "Feature",
  "properties": {
    "addr:full":"636 Rue Chatelois Sainte-Adele QC J8B 2H2",
    "addr:housenumber":"636",
    "addr:postcode":"j8b 2h2",
    "addr:street":"Rue Chatelois Sainte-Adele",
    "iso:country":"CA",
    "sg:address":"636 Rue Chatelois",
    "sg:city":"Sainte-Adele",
    "sg:classifiers":[
        {
            "category":"Professional",
            "subcategory":"Management & Consulting",
            "type":"Services"
        }
    ],
    "sg:phone":"+1 450 229 4229",
    "sg:postcode":"J8B 2H2",
    "sg:province":"QC",
    "sg:tags":[
        "personnel",
        "consultant"
    ],
    "wof:name":"Consultants Lna",
    "wof:placetype":"venue"
},
  "geometry": {"coordinates":[-74.162384,45.980789],"type":"Point"}
}