{
  "type": "Feature",
  "properties": {
    "addr:full":"330 Rue Saint-Roch Quebec QC G1K 6S2",
    "addr:housenumber":"330",
    "addr:postcode":"g1k 6s2",
    "addr:street":"Rue Saint-Roch",
    "iso:country":"CA",
    "sg:address":"330 Rue Saint-Roch",
    "sg:city":"Quebec",
    "sg:classifiers":[
        {
            "category":"Professional",
            "subcategory":"Printing & Photocopies",
            "type":"Services"
        }
    ],
    "sg:phone":"+1 418 529 2533",
    "sg:postcode":"G1K 6S2",
    "sg:province":"QC",
    "sg:tags":[
        "printer",
        "duplicating",
        "copying"
    ],
    "wof:name":"Impression Pro-Copies Inc",
    "wof:placetype":"venue"
},
  "geometry": {"coordinates":[-71.218079,46.818001],"type":"Point"}
}