{
  "type": "Feature",
  "properties": {
    "addr:full":"88 College St Tweed ON K0K 3J0",
    "addr:housenumber":"88",
    "addr:postcode":"k0k 3j0",
    "addr:street":"College St",
    "iso:country":"CA",
    "sg:address":"88 College St",
    "sg:city":"Tweed",
    "sg:classifiers":[
        {
            "category":"Retail",
            "subcategory":"Repair Shop",
            "type":"Services"
        }
    ],
    "sg:phone":"+1 613 478 5715",
    "sg:postcode":"K0K 3J0",
    "sg:province":"ON",
    "sg:tags":[
        "sharpening",
        "saw"
    ],
    "wof:name":"Rosenplot Sharpening Svc",
    "wof:placetype":"venue"
},
  "geometry": {"coordinates":[-77.31959533689999,44.4748764038],"type":"Point"}
}