{
  "type": "Feature",
  "properties": {
    "iso:country":"CA",
    "sg:address":"5652 Boul Thimens",
    "sg:city":"Saint-Laurent",
    "sg:classifiers":[
        {
            "category":"Manufacturing",
            "subcategory":"Metals",
            "type":"Manufacturing & Wholesale Goods"
        }
    ],
    "sg:phone":"+1 514 335 6867",
    "sg:postcode":"H4R 2K9",
    "sg:province":"QC",
    "sg:tags":[
        "tool"
    ],
    "wof:name":"H T Mould Inc",
    "wof:placetype":"venue"
},
  "geometry": {"coordinates":[-73.7328796387,45.4994621277],"type":"Point"}
}