{
  "type": "Feature",
  "properties": {
    "addr:full":"7211 Main St Vancouver BC V5X 3J3",
    "addr:housenumber":"7211",
    "addr:postcode":"v5x 3j3",
    "addr:street":"Main St",
    "iso:country":"CA",
    "sg:address":"7211 Main St",
    "sg:city":"Vancouver",
    "sg:classifiers":[
        {
            "category":"Home & Garden",
            "subcategory":"Building Materials",
            "type":"Retail Goods"
        }
    ],
    "sg:phone":"+1 604 327 5096",
    "sg:postcode":"V5X 3J3",
    "sg:province":"BC",
    "sg:tags":[
        "plumbing",
        "fixture",
        "contractor"
    ],
    "wof:name":"Real Plumbing & Elec Supl Ltd",
    "wof:placetype":"venue"
},
  "geometry": {"coordinates":[-123.102058,49.219143],"type":"Point"}
}