{
  "type": "Feature",
  "properties": {
    "addr:full":"156 Huron St Stratford ON N5A 5S8",
    "addr:housenumber":"156",
    "addr:postcode":"n5a 5s8",
    "addr:street":"Huron St",
    "iso:country":"CA",
    "sg:address":"156 Huron St",
    "sg:city":"Stratford",
    "sg:classifiers":[
        {
            "category":"Professional",
            "subcategory":"Secretarial Services",
            "type":"Services"
        }
    ],
    "sg:phone":"+1 519 273 5620",
    "sg:postcode":"N5A 5S8",
    "sg:province":"ON",
    "sg:tags":[
        "convention",
        "court",
        "reporter"
    ],
    "wof:name":"Stratford Verbatim",
    "wof:placetype":"venue"
},
  "geometry": {"coordinates":[-80.989105,43.374557],"type":"Point"}
}