{
  "type": "Feature",
  "properties": {
    "addr:full":"St-Sauveur-Des-Monts QC J0R 1R3",
    "addr:postcode":"j0r 1r3",
    "iso:country":"CA",
    "sg:city":"St-Sauveur-Des-Monts",
    "sg:classifiers":[
        {
            "category":"Shopping",
            "type":"Retail Goods"
        }
    ],
    "sg:phone":"+1 450 227 0439",
    "sg:postcode":"J0R 1R3",
    "sg:province":"QC",
    "sg:tags":[
        "pet",
        "shop"
    ],
    "wof:name":"Animalerie DE LA Vallee",
    "wof:placetype":"venue"
},
  "geometry": {"coordinates":[-74.152351,45.891148],"type":"Point"}
}