{
  "type": "Feature",
  "properties": {
    "iso:country":"CA",
    "sg:address":"515 Hartsdale Ave",
    "sg:city":"Mississauga",
    "sg:classifiers":[
        {
            "category":"Education",
            "subcategory":"School",
            "type":"Public Place"
        }
    ],
    "sg:phone":"+1 905 278 9821",
    "sg:postcode":"L5G 2G7",
    "sg:province":"ON",
    "wof:name":"St Dominic School",
    "wof:placetype":"venue"
},
  "geometry": {"coordinates":[-79.5783996582,43.5733337402],"type":"Point"}
}