{
  "type": "Feature",
  "properties": {
    "addr:full":"212 Campbell Ave Toronto ON M6P 3V4",
    "addr:housenumber":"212",
    "addr:postcode":"m6p 3v4",
    "addr:street":"Campbell Ave",
    "iso:country":"CA",
    "sg:address":"212 Campbell Ave",
    "sg:city":"Toronto",
    "sg:classifiers":[
        {
            "category":"Retail",
            "subcategory":"Repair Shop",
            "type":"Services"
        }
    ],
    "sg:phone":"+1 416 532 3101",
    "sg:postcode":"M6P 3V4",
    "sg:province":"ON",
    "sg:tags":[
        "refinishing",
        "furniture"
    ],
    "wof:name":"Nick's Furniture Shop",
    "wof:placetype":"venue"
},
  "geometry": {"coordinates":[-79.448868,43.662632],"type":"Point"}
}