{
  "type": "Feature",
  "properties": {
    "addr:full":"36 Cromer Ave Grand Falls-Windsor NL A2A 2J7",
    "addr:housenumber":"36",
    "addr:postcode":"a2a 2j7",
    "addr:street":"Cromer Ave",
    "iso:country":"CA",
    "sg:address":"36 Cromer Ave",
    "sg:city":"Grand Falls-Windsor",
    "sg:classifiers":[
        {
            "category":"Home & Garden",
            "subcategory":"Household Appliances",
            "type":"Retail Goods"
        }
    ],
    "sg:phone":"+1 709 489 5645",
    "sg:postcode":"A2A 2J7",
    "sg:province":"NL",
    "sg:tags":[
        "mail",
        "catalog",
        "shopping",
        "order"
    ],
    "wof:name":"Sears Canada Inc",
    "wof:placetype":"venue"
},
  "geometry": {"coordinates":[-55.654499054,48.954208374],"type":"Point"}
}