{
  "type": "Feature",
  "properties": {
    "addr:full":"1698 Wilkinson Rd Nanaimo BC V9X 1V6",
    "addr:housenumber":"1698",
    "addr:postcode":"v9x 1v6",
    "addr:street":"Wilkinson Rd",
    "iso:country":"CA",
    "sg:address":"1698 Wilkinson Rd",
    "sg:city":"Nanaimo",
    "sg:classifiers":[
        {
            "category":"Real Estate",
            "subcategory":"Real Estate Operator",
            "type":"Services"
        }
    ],
    "sg:phone":"+1 250 722 3713",
    "sg:postcode":"V9X 1V6",
    "sg:province":"BC",
    "sg:tags":[
        "mobile",
        "home",
        "community"
    ],
    "wof:name":"Riverside Trailer Park",
    "wof:placetype":"venue"
},
  "geometry": {"coordinates":[-123.880188,49.114189],"type":"Point"}
}