{
  "type": "Feature",
  "properties": {
    "addr:full":"NE 22-13-24W Hamiota MB R0M 0T0",
    "addr:postcode":"r0m 0t0",
    "addr:street":"Ne 22-13-24W",
    "iso:country":"CA",
    "sg:address":"NE 22-13-24W",
    "sg:city":"Hamiota",
    "sg:classifiers":[
        {
            "category":"Farming",
            "subcategory":"Farm & Veterinary Services",
            "type":"Manufacturing & Wholesale Goods"
        }
    ],
    "sg:phone":"+1 204 764 2450",
    "sg:postcode":"R0M 0T0",
    "sg:province":"MB",
    "sg:tags":[
        "seed",
        "grain",
        "cleaning"
    ],
    "wof:name":"Knight Seeds",
    "wof:placetype":"venue"
},
  "geometry": {"coordinates":[-100.599846,50.18251],"type":"Point"}
}