{
  "type": "Feature",
  "properties": {
    "addr:full":"70 Hamilton St N Waterdown ON L0R 2H0",
    "addr:housenumber":"70",
    "addr:postcode":"l0r 2h0",
    "addr:street":"Hamilton St N",
    "iso:country":"CA",
    "sg:address":"70 Hamilton St N",
    "sg:city":"Waterdown",
    "sg:classifiers":[
        {
            "category":"Food & Beverages",
            "subcategory":"Liquor & Beverages",
            "type":"Retail Goods"
        }
    ],
    "sg:phone":"+1 905 689 6010",
    "sg:postcode":"L0R 2H0",
    "sg:province":"ON",
    "sg:tags":[
        "beer",
        "ale"
    ],
    "wof:name":"Beer Store",
    "wof:placetype":"venue"
},
  "geometry": {"coordinates":[-79.8978347778,43.332775116],"type":"Point"}
}