{
  "type": "Feature",
  "properties": {
    "addr:full":"13 Seapark Dr St Catharines ON L2M 6S5",
    "addr:housenumber":"13",
    "addr:postcode":"l2m 6s5",
    "addr:street":"Seapark Dr",
    "iso:country":"CA",
    "sg:address":"13 Seapark Dr",
    "sg:city":"St Catharines",
    "sg:classifiers":[
        {
            "category":"Manufacturing",
            "subcategory":"Metals",
            "type":"Manufacturing & Wholesale Goods"
        }
    ],
    "sg:phone":"+1 905 687 8183",
    "sg:postcode":"L2M 6S5",
    "sg:province":"ON",
    "sg:tags":[
        "finisher"
    ],
    "wof:name":"Performance Powder Coatings",
    "wof:placetype":"venue"
},
  "geometry": {"coordinates":[-79.20202636720001,43.1734275818],"type":"Point"}
}