{
  "type": "Feature",
  "properties": {
    "addr:full":"315 Ingalls Head Rd Grand Manan NB E5G 3G9",
    "addr:housenumber":"315",
    "addr:postcode":"e5g 3g9",
    "addr:street":"Ingalls Head Rd",
    "iso:country":"CA",
    "sg:address":"315 Ingalls Head Rd",
    "sg:city":"Grand Manan",
    "sg:classifiers":[
        {
            "category":"Organizations",
            "subcategory":"Professional Association",
            "type":"Services"
        }
    ],
    "sg:phone":"+1 506 662 8481",
    "sg:postcode":"E5G 3G9",
    "sg:province":"NB",
    "wof:name":"Grand Manan Fishermen's Assoc",
    "wof:placetype":"venue"
},
  "geometry": {"coordinates":[-66.79814910890001,44.675453186],"type":"Point"}
}