{
  "type": "Feature",
  "properties": {
    "addr:full":"Victoria BC V9B 1V7",
    "addr:postcode":"v9b 1v7",
    "iso:country":"CA",
    "sg:city":"Victoria",
    "sg:classifiers":[
        {
            "category":"Health Services",
            "subcategory":"Health Practitioner",
            "type":"Services"
        }
    ],
    "sg:phone":"+1 250 478 3476",
    "sg:postcode":"V9B 1V7",
    "sg:province":"BC",
    "sg:tags":[
        "psychologist"
    ],
    "wof:name":"O'Connor, Shelly PhD",
    "wof:placetype":"venue"
},
  "geometry": {"coordinates":[-123.36451700000001,48.428314],"type":"Point"}
}