{
  "type": "Feature",
  "properties": {
    "iso:country":"CA",
    "sg:address":"328 Passmore Ave # 12B",
    "sg:city":"Scarborough",
    "sg:classifiers":[
        {
            "category":"Building & Trades",
            "subcategory":"Cleaning & Sanitation",
            "type":"Services"
        }
    ],
    "sg:phone":"+1 416 292 7701",
    "sg:postcode":"M1V 5J5",
    "sg:province":"ON",
    "sg:tags":[
        "janitor"
    ],
    "wof:name":"Cardinal Caretakers CO Ltd",
    "wof:placetype":"venue"
},
  "geometry": {"coordinates":[-79.262634,43.828068],"type":"Point"}
}