{
  "type": "Feature",
  "properties": {
    "addr:full":"Banff AB T1L 1A8",
    "addr:postcode":"t1l 1a8",
    "iso:country":"CA",
    "sg:city":"Banff",
    "sg:classifiers":[
        {
            "category":"Travel",
            "subcategory":"Travel Agent",
            "type":"Entertainment"
        }
    ],
    "sg:phone":"+1 403 762 5155",
    "sg:postcode":"T1L 1A8",
    "sg:province":"AB",
    "sg:tags":[
        "information",
        "tourist"
    ],
    "wof:name":"Kintetsu International Express",
    "wof:placetype":"venue"
},
  "geometry": {"coordinates":[-115.571022,51.176987],"type":"Point"}
}