{
  "type": "Feature",
  "properties": {
    "iso:country":"CA",
    "sg:address":"1774 White Cedar Dr",
    "sg:city":"Pickering",
    "sg:classifiers":[
        {
            "category":"Building & Trades",
            "subcategory":"Electrical",
            "type":"Services"
        }
    ],
    "sg:phone":"+1 905 839 5006",
    "sg:postcode":"L1V 6Z1",
    "sg:province":"ON",
    "sg:tags":[
        "electric",
        "contractor"
    ],
    "wof:name":"Leslie & Palmer CO",
    "wof:placetype":"venue"
},
  "geometry": {"coordinates":[-79.131004,43.823772],"type":"Point"}
}