{
  "type": "Feature",
  "properties": {
    "addr:full":"605 Foster Ave Coquitlam V3J2L6",
    "addr:housenumber":"605",
    "addr:postcode":"v3j2l6",
    "addr:street":"Foster Ave",
    "iso:country":"CA",
    "sg:address":"605 Foster Ave",
    "sg:city":"Coquitlam",
    "sg:classifiers":[
        {
            "category":"Professional",
            "subcategory":"Computer Services",
            "type":"Services"
        }
    ],
    "sg:postcode":"V3J2L6",
    "sg:tags":[
        "voice",
        "voice-commands",
        "voice-search",
        "voice-assistance",
        "virtual-assistance"
    ],
    "sg:website":"http://www.bvocalized.com",
    "wof:name":"Bvocalized ",
    "wof:placetype":"venue"
},
  "geometry": {"coordinates":[-122.8856305,49.256745],"type":"Point"}
}