{
  "type": "Feature",
  "properties": {
    "addr:full":"38 Sylvia Ave Halifax NS B3R 1J9",
    "addr:housenumber":"38",
    "addr:postcode":"b3r 1j9",
    "addr:street":"Sylvia Ave",
    "iso:country":"CA",
    "sg:address":"38 Sylvia Ave",
    "sg:city":"Halifax",
    "sg:classifiers":[
        {
            "category":"Education",
            "subcategory":"School",
            "type":"Public Place"
        }
    ],
    "sg:phone":"+1 902 479 4612",
    "sg:postcode":"B3R 1J9",
    "sg:province":"NS",
    "wof:name":"J L Isley High School",
    "wof:placetype":"venue"
},
  "geometry": {"coordinates":[-63.609646,44.60511],"type":"Point"}
}