{
  "type": "Feature",
  "properties": {
    "addr:full":"732 Ch Carrier Cookshire QC J0B 1M0",
    "addr:housenumber":"732",
    "addr:postcode":"j0b 1m0",
    "addr:street":"Ch Carrier Cookshire",
    "iso:country":"CA",
    "sg:address":"732 Ch Carrier",
    "sg:city":"Cookshire",
    "sg:classifiers":[
        {
            "category":"Autos & Motor Vehicles",
            "subcategory":"Automobile Sales",
            "type":"Retail Goods"
        }
    ],
    "sg:phone":"+1 819 875 5515",
    "sg:postcode":"J0B 1M0",
    "sg:province":"QC",
    "sg:tags":[
        "car",
        "dealer"
    ],
    "wof:name":"J Paul Dumas & Fils Pieces",
    "wof:placetype":"venue"
},
  "geometry": {"coordinates":[-71.59654999999999,45.4137],"type":"Point"}
}