{
  "type": "Feature",
  "properties": {
    "addr:full":"5527 Yonge St North York ON M2N 5S3",
    "addr:housenumber":"5527",
    "addr:postcode":"m2n 5s3",
    "addr:street":"Yonge St",
    "iso:country":"CA",
    "sg:address":"5527 Yonge St",
    "sg:city":"North York",
    "sg:classifiers":[
        {
            "category":"Professional",
            "subcategory":"Accounting & Tax Preparation",
            "type":"Services"
        }
    ],
    "sg:phone":"+1 416 225 3008",
    "sg:postcode":"M2N 5S3",
    "sg:province":"ON",
    "sg:tags":[
        "return",
        "filing"
    ],
    "wof:name":"Tax Payer's Choice",
    "wof:placetype":"venue"
},
  "geometry": {"coordinates":[-79.414978,43.778267],"type":"Point"}
}