{
  "type": "Feature",
  "properties": {
    "addr:full":"301 Coteau St Arcola SK S0C 0G0",
    "addr:housenumber":"301",
    "addr:postcode":"s0c 0g0",
    "addr:street":"Coteau St",
    "iso:country":"CA",
    "sg:address":"301 Coteau St",
    "sg:city":"Arcola",
    "sg:classifiers":[
        {
            "category":"Health Services",
            "subcategory":"Clinic",
            "type":"Services"
        }
    ],
    "sg:phone":"+1 306 455 2755",
    "sg:postcode":"S0C 0G0",
    "sg:province":"SK",
    "sg:tags":[
        "home"
    ],
    "wof:name":"Coteau Place",
    "wof:placetype":"venue"
},
  "geometry": {"coordinates":[-102.49179100000001,49.634789],"type":"Point"}
}