{
  "type": "Feature",
  "properties": {
    "addr:full":"Surrey BC V4N 4C7",
    "addr:postcode":"v4n 4c7",
    "iso:country":"CA",
    "sg:city":"Surrey",
    "sg:classifiers":[
        {
            "category":"Restaurant",
            "type":"Food & Drink"
        }
    ],
    "sg:phone":"+1 604 888 6894",
    "sg:postcode":"V4N 4C7",
    "sg:province":"BC",
    "wof:name":"Midori Japanese Restaurant",
    "wof:placetype":"venue"
},
  "geometry": {"coordinates":[-122.690612793,49.1775398254],"type":"Point"}
}