{
  "type": "Feature",
  "properties": {
    "addr:full":"Etobicoke ON M9V 5E2",
    "addr:postcode":"m9v 5e2",
    "iso:country":"CA",
    "sg:city":"Etobicoke",
    "sg:classifiers":[
        {
            "category":"Professional",
            "subcategory":"Employment Agencies",
            "type":"Services"
        }
    ],
    "sg:phone":"+1 416 740 1542",
    "sg:postcode":"M9V 5E2",
    "sg:province":"ON",
    "sg:tags":[
        "opportunity"
    ],
    "wof:name":"Excel Employment Tempro",
    "wof:placetype":"venue"
},
  "geometry": {"coordinates":[-79.6015319824,43.735370636],"type":"Point"}
}