{
  "type": "Feature",
  "properties": {
    "addr:full":"6126 Yonge St North York ON M2M 3W7",
    "addr:housenumber":"6126",
    "addr:postcode":"m2m 3w7",
    "addr:street":"Yonge St",
    "iso:country":"CA",
    "sg:address":"6126 Yonge St",
    "sg:city":"North York",
    "sg:classifiers":[
        {
            "category":"Professional",
            "type":"Services"
        }
    ],
    "sg:phone":"+1 416 223 6665",
    "sg:postcode":"M2M 3W7",
    "sg:province":"ON",
    "sg:tags":[
        "establishment",
        "telephone",
        "cellular"
    ],
    "wof:name":"Alfa Communications",
    "wof:placetype":"venue"
},
  "geometry": {"coordinates":[-79.418617,43.79174],"type":"Point"}
}