{
  "type": "Feature",
  "properties": {
    "addr:full":"20954 Dalton Rd Sutton West ON L0E 1R0",
    "addr:housenumber":"20954",
    "addr:postcode":"l0e 1r0",
    "addr:street":"Dalton Rd",
    "iso:country":"CA",
    "sg:address":"20954 Dalton Rd",
    "sg:city":"Sutton West",
    "sg:classifiers":[
        {
            "category":"Food & Beverages",
            "subcategory":"Bakery",
            "type":"Retail Goods"
        }
    ],
    "sg:phone":"+1 905 722 7762",
    "sg:postcode":"L0E 1R0",
    "sg:province":"ON",
    "sg:tags":[
        "doughnut"
    ],
    "wof:name":"Tim Hortons",
    "wof:placetype":"venue"
},
  "geometry": {"coordinates":[-79.36726379389999,44.314125061],"type":"Point"}
}