{
  "type": "Feature",
  "properties": {
    "addr:full":"Cambridge ON N1R 7Z1",
    "addr:postcode":"n1r 7z1",
    "iso:country":"CA",
    "sg:city":"Cambridge",
    "sg:classifiers":[
        {
            "category":"Health Services",
            "subcategory":"Doctor",
            "type":"Services"
        }
    ],
    "sg:phone":"+1 519 740 1870",
    "sg:postcode":"N1R 7Z1",
    "sg:province":"ON",
    "sg:tags":[
        "physician",
        "surgeon"
    ],
    "wof:name":"Sikaneta, S S MD",
    "wof:placetype":"venue"
},
  "geometry": {"coordinates":[-80.29908,43.380329],"type":"Point"}
}