{
  "type": "Feature",
  "properties": {
    "addr:full":"Calgary AB T3H 2Z9",
    "addr:postcode":"t3h 2z9",
    "iso:country":"CA",
    "sg:city":"Calgary",
    "sg:classifiers":[
        {
            "category":"Health Services",
            "subcategory":"Doctor",
            "type":"Services"
        }
    ],
    "sg:phone":"+1 403 242 4111",
    "sg:postcode":"T3H 2Z9",
    "sg:province":"AB",
    "sg:tags":[
        "dentist"
    ],
    "wof:name":"Icon Orthodontics",
    "wof:placetype":"venue"
},
  "geometry": {"coordinates":[-114.184310913,51.0494232178],"type":"Point"}
}