{
  "type": "Feature",
  "properties": {
    "addr:full":"715 Rue Notre-Dame Saint-Sulpice QC J5W 3X1",
    "addr:housenumber":"715",
    "addr:postcode":"j5w 3x1",
    "addr:street":"Rue Notre-Dame",
    "iso:country":"CA",
    "sg:address":"715 Rue Notre-Dame",
    "sg:city":"Saint-Sulpice",
    "sg:classifiers":[
        {
            "category":"Retail",
            "subcategory":"Auto Repair",
            "type":"Services"
        }
    ],
    "sg:phone":"+1 450 589 4918",
    "sg:postcode":"J5W 3X1",
    "sg:province":"QC",
    "sg:tags":[
        "repairing",
        "automobile"
    ],
    "wof:name":"Centre Des Svc Paul Chausse",
    "wof:placetype":"venue"
},
  "geometry": {"coordinates":[-73.373726,45.811733],"type":"Point"}
}