{
  "type": "Feature",
  "properties": {
    "addr:full":"881 Rue Sainte-Cecile Trois-Rivieres QC G9A 1L4",
    "addr:housenumber":"881",
    "addr:postcode":"g9a 1l4",
    "addr:street":"Rue Sainte-Cecile Trois-Rivieres",
    "iso:country":"CA",
    "sg:address":"881 Rue Sainte-Cecile",
    "sg:city":"Trois-Rivieres",
    "sg:classifiers":[
        {
            "category":"Recreation",
            "type":"Entertainment"
        }
    ],
    "sg:phone":"+1 819 371 1054",
    "sg:postcode":"G9A 1L4",
    "sg:province":"QC",
    "sg:tags":[
        "spa",
        "house",
        "sauna",
        "bath"
    ],
    "wof:name":"Bain Magique",
    "wof:placetype":"venue"
},
  "geometry": {"coordinates":[-72.542145,46.350578],"type":"Point"}
}