{
  "type": "Feature",
  "properties": {
    "iso:country":"CA",
    "sg:city":"Etobicoke",
    "sg:classifiers":[
        {
            "category":"Food & Beverages",
            "subcategory":"Bakery",
            "type":"Retail Goods"
        }
    ],
    "sg:phone":"+1 416 247 0338",
    "sg:postcode":"M9P 3B6",
    "sg:province":"ON",
    "sg:tags":[
        "baker"
    ],
    "wof:name":"Open Window Bakery Ltd",
    "wof:placetype":"venue"
},
  "geometry": {"coordinates":[-79.5305633545,43.6909103394],"type":"Point"}
}