{
  "type": "Feature",
  "properties": {
    "iso:country":"CA",
    "sg:address":"5001 Yonge St",
    "sg:city":"North York",
    "sg:classifiers":[
        {
            "category":"Government",
            "subcategory":"Office",
            "type":"Public Place"
        }
    ],
    "sg:phone":"+1 416 221 3560",
    "sg:postcode":"M2N 6P6",
    "sg:province":"ON",
    "wof:name":"Canada Taxes",
    "wof:placetype":"venue"
},
  "geometry": {"coordinates":[-79.4118881226,43.7657966614],"type":"Point"}
}