{
  "type": "Feature",
  "properties": {
    "addr:full":"822 Rue Saint-Paul Shawinigan QC G9N 4K2",
    "addr:housenumber":"822",
    "addr:postcode":"g9n 4k2",
    "addr:street":"Rue Saint-Paul",
    "iso:country":"CA",
    "sg:address":"822 Rue Saint-Paul",
    "sg:city":"Shawinigan",
    "sg:classifiers":[
        {
            "category":"Health Services",
            "subcategory":"Medical Lab",
            "type":"Services"
        }
    ],
    "sg:phone":"+1 819 537 7169",
    "sg:postcode":"G9N 4K2",
    "sg:province":"QC",
    "wof:name":"Gestion Rene Miller Inc",
    "wof:placetype":"venue"
},
  "geometry": {"coordinates":[-72.741951,46.554268],"type":"Point"}
}