{
  "type": "Feature",
  "properties": {
    "addr:full":"230 Norseman St Etobicoke ON M8Z 6A2",
    "addr:housenumber":"230",
    "addr:postcode":"m8z 6a2",
    "addr:street":"Norseman St",
    "iso:country":"CA",
    "sg:address":"230 Norseman St",
    "sg:city":"Etobicoke",
    "sg:classifiers":[
        {
            "category":"Professional",
            "subcategory":"Management & Consulting",
            "type":"Services"
        }
    ],
    "sg:phone":"+1 416 234 5044",
    "sg:postcode":"M8Z 6A2",
    "sg:province":"ON",
    "sg:tags":[
        "employee",
        "consultant",
        "benefit"
    ],
    "wof:name":"Manion Wilkins & Assoc Ltd",
    "wof:placetype":"venue"
},
  "geometry": {"coordinates":[-79.52565,43.632812],"type":"Point"}
}