{
  "type": "Feature",
  "properties": {
    "addr:full":"4917 50 Ave Vermilion AB T9X 1A6",
    "addr:housenumber":"4917",
    "addr:postcode":"t9x 1a6",
    "addr:street":"50 Ave",
    "iso:country":"CA",
    "sg:address":"4917 50 Ave",
    "sg:city":"Vermilion",
    "sg:classifiers":[
        {
            "category":"Manufacturing",
            "subcategory":"Printing",
            "type":"Manufacturing & Wholesale Goods"
        }
    ],
    "sg:phone":"+1 780 853 5344",
    "sg:postcode":"T9X 1A6",
    "sg:province":"AB",
    "sg:tags":[
        "newspaper"
    ],
    "wof:name":"Vermilion Standard Ltd",
    "wof:placetype":"venue"
},
  "geometry": {"coordinates":[-110.850158691,53.3538818359],"type":"Point"}
}