{
  "type": "Feature",
  "properties": {
    "addr:full":"700 Wilson Heights Blvd North York ON M3H 2V9",
    "addr:housenumber":"700",
    "addr:postcode":"m3h 2v9",
    "addr:street":"Wilson Heights Blvd",
    "iso:country":"CA",
    "sg:address":"700 Wilson Heights Blvd",
    "sg:city":"North York",
    "sg:classifiers":[
        {
            "category":"Retail",
            "subcategory":"Auto Rental",
            "type":"Services"
        }
    ],
    "sg:phone":"+1 416 398 9900",
    "sg:postcode":"M3H 2V9",
    "sg:province":"ON",
    "sg:tags":[
        "renting",
        "automobile"
    ],
    "wof:name":"Cargo Car & Truck Rental",
    "wof:placetype":"venue"
},
  "geometry": {"coordinates":[-79.46319580079999,43.7589378357],"type":"Point"}
}