{
  "type": "Feature",
  "properties": {
    "iso:country":"CA",
    "sg:address":"200 Government Wharf Rd # 6",
    "sg:city":"Eastern Passage",
    "sg:classifiers":[
        {
            "category":"Restaurant",
            "type":"Food & Drink"
        }
    ],
    "sg:phone":"+1 902 465 3474",
    "sg:postcode":"B3G 1M7",
    "sg:province":"NS",
    "wof:name":"Boon Docks Dining Room",
    "wof:placetype":"venue"
},
  "geometry": {"coordinates":[-63.4956092834,44.6108703613],"type":"Point"}
}