{
  "type": "Feature",
  "properties": {
    "addr:full":"Western Shore NS B0J 3M0",
    "addr:postcode":"b0j 3m0",
    "iso:country":"CA",
    "sg:city":"Western Shore",
    "sg:classifiers":[
        {
            "category":"Food & Beverages",
            "subcategory":"Fruits & Vegetables",
            "type":"Retail Goods"
        }
    ],
    "sg:phone":"+1 902 627 2090",
    "sg:postcode":"B0J 3M0",
    "sg:province":"NS",
    "wof:name":"Glyda's Fruit & Vegetable",
    "wof:placetype":"venue"
},
  "geometry": {"coordinates":[-64.3086471558,44.527671814],"type":"Point"}
}