{
  "type": "Feature",
  "properties": {
    "addr:full":"17 Frank St Strathroy ON N7G 2R2",
    "addr:housenumber":"17",
    "addr:postcode":"n7g 2r2",
    "addr:street":"Frank St",
    "iso:country":"CA",
    "sg:address":"17 Frank St",
    "sg:city":"Strathroy",
    "sg:classifiers":[
        {
            "category":"Shopping",
            "subcategory":"Pharmacy",
            "type":"Retail Goods"
        }
    ],
    "sg:phone":"+1 519 245 6870",
    "sg:postcode":"N7G 2R2",
    "sg:province":"ON",
    "wof:name":"Strathroy Medical Pharmacy",
    "wof:placetype":"venue"
},
  "geometry": {"coordinates":[-81.62339,42.955853],"type":"Point"}
}