{
  "type": "Feature",
  "properties": {
    "iso:country":"CA",
    "sg:address":"705 Rue Sainte-Catherine O # 2146A",
    "sg:city":"Montreal",
    "sg:classifiers":[
        {
            "category":"Shopping",
            "subcategory":"Computers & Home Electronics",
            "type":"Retail Goods"
        }
    ],
    "sg:phone":"+1 514 843 7557",
    "sg:postcode":"H3B 4G5",
    "sg:province":"QC",
    "sg:tags":[
        "television",
        "radio"
    ],
    "wof:name":"Maison Sony",
    "wof:placetype":"venue"
},
  "geometry": {"coordinates":[-73.559196,45.515362],"type":"Point"}
}