{
  "type": "Feature",
  "properties": {
    "iso:country":"CA",
    "sg:address":"10 Ski Hill Rd Hwy 108",
    "sg:city":"Elliot Lake",
    "sg:classifiers":[
        {
            "category":"Travel",
            "subcategory":"Hotels & Motels",
            "type":"Entertainment"
        }
    ],
    "sg:phone":"+1 705 848 6655",
    "sg:postcode":"P5A 2J6",
    "sg:province":"ON",
    "sg:tags":[
        "resort",
        "center",
        "skiing"
    ],
    "wof:name":"Mount Dufour Ski Area",
    "wof:placetype":"venue"
},
  "geometry": {"coordinates":[-82.64031982420001,46.3814849854],"type":"Point"}
}