{
  "type": "Feature",
  "properties": {
    "addr:full":"51 Byron Ave Dorchester ON N0L 1G2",
    "addr:housenumber":"51",
    "addr:postcode":"n0l 1g2",
    "addr:street":"Byron Ave",
    "iso:country":"CA",
    "sg:address":"51 Byron Ave",
    "sg:city":"Dorchester",
    "sg:classifiers":[
        {
            "category":"Social Services",
            "type":"Services"
        }
    ],
    "sg:phone":"+1 519 268 8778",
    "sg:postcode":"N0L 1G2",
    "sg:province":"ON",
    "sg:tags":[
        "mission"
    ],
    "wof:name":"Pioneers Canada",
    "wof:placetype":"venue"
},
  "geometry": {"coordinates":[-81.060616,42.979767],"type":"Point"}
}