{
  "type": "Feature",
  "properties": {
    "addr:full":"328 Husky Ave Air Ronge SK S0J 3G0",
    "addr:housenumber":"328",
    "addr:postcode":"s0j 3g0",
    "addr:street":"Husky Ave",
    "iso:country":"CA",
    "sg:address":"328 Husky Ave",
    "sg:city":"Air Ronge",
    "sg:classifiers":[
        {
            "category":"Government",
            "subcategory":"Office",
            "type":"Public Place"
        }
    ],
    "sg:phone":"+1 306 425 2107",
    "sg:postcode":"S0J 3G0",
    "sg:province":"SK",
    "sg:tags":[
        "municipality"
    ],
    "wof:name":"Air Ronge Northern Village",
    "wof:placetype":"venue"
},
  "geometry": {"coordinates":[-105.318794,55.082458],"type":"Point"}
}