{
  "type": "Feature",
  "properties": {
    "addr:full":"10315 94 St Fort St John BC V1J 3L5",
    "addr:housenumber":"10315",
    "addr:postcode":"v1j 3l5",
    "addr:street":"94 St",
    "iso:country":"CA",
    "sg:address":"10315 94 St",
    "sg:city":"Fort St John",
    "sg:classifiers":[
        {
            "category":"Social Services",
            "type":"Services"
        }
    ],
    "sg:phone":"+1 250 785 6608",
    "sg:postcode":"V1J 3L5",
    "sg:province":"BC",
    "sg:tags":[
        "youth",
        "organization",
        "center"
    ],
    "wof:name":"Wjs Interchange",
    "wof:placetype":"venue"
},
  "geometry": {"coordinates":[-120.8360672,56.2494812012],"type":"Point"}
}