{
  "type": "Feature",
  "properties": {
    "addr:full":"30 Churchill Dr Barrie ON L4N 8Z5",
    "addr:housenumber":"30",
    "addr:postcode":"l4n 8z5",
    "addr:street":"Churchill Dr",
    "iso:country":"CA",
    "sg:address":"30 Churchill Dr",
    "sg:city":"Barrie",
    "sg:classifiers":[
        {
            "category":"Wholesale",
            "subcategory":"Groceries",
            "type":"Manufacturing & Wholesale Goods"
        }
    ],
    "sg:phone":"+1 705 722 6455",
    "sg:postcode":"L4N 8Z5",
    "sg:province":"ON",
    "sg:tags":[
        "product",
        "food",
        "dessert",
        "ice",
        "frozen",
        "cream"
    ],
    "wof:name":"Jayway Distribution Ltd",
    "wof:placetype":"venue"
},
  "geometry": {"coordinates":[-79.672668457,44.3448486328],"type":"Point"}
}