{
  "type": "Feature",
  "properties": {
    "addr:full":"3043 Beachwood Dr Buckhorn ON K0L 1J0",
    "addr:housenumber":"3043",
    "addr:postcode":"k0l 1j0",
    "addr:street":"Beachwood Dr",
    "iso:country":"CA",
    "sg:address":"3043 Beachwood Dr",
    "sg:city":"Buckhorn",
    "sg:classifiers":[
        {
            "category":"Manufacturing",
            "subcategory":"Building Materials",
            "type":"Manufacturing & Wholesale Goods"
        }
    ],
    "sg:phone":"+1 705 657 1311",
    "sg:postcode":"K0L 1J0",
    "sg:province":"ON",
    "sg:tags":[
        "door"
    ],
    "wof:name":"Deer Bay Overhead Door Factory",
    "wof:placetype":"venue"
},
  "geometry": {"coordinates":[-78.351952,44.554256],"type":"Point"}
}