{
  "type": "Feature",
  "properties": {
    "addr:full":"567 Lake Rd Wentworth NS B0M 1Z0",
    "addr:housenumber":"567",
    "addr:postcode":"b0m 1z0",
    "addr:street":"Lake Rd",
    "iso:country":"CA",
    "sg:address":"567 Lake Rd",
    "sg:city":"Wentworth",
    "sg:classifiers":[
        {
            "category":"Food & Beverages",
            "subcategory":"Candy",
            "type":"Retail Goods"
        }
    ],
    "sg:phone":"+1 902 548 2323",
    "sg:postcode":"B0M 1Z0",
    "sg:province":"NS",
    "sg:tags":[
        "confectionery"
    ],
    "wof:name":"Appleton Chocolates CO",
    "wof:placetype":"venue"
},
  "geometry": {"coordinates":[-63.549278,45.657459],"type":"Point"}
}