{
  "type": "Feature",
  "properties": {
    "addr:full":"5816 50 Ave Bonnyville AB T9N 2N6",
    "addr:housenumber":"5816",
    "addr:postcode":"t9n 2n6",
    "addr:street":"50 Ave",
    "iso:country":"CA",
    "sg:address":"5816 50 Ave",
    "sg:city":"Bonnyville",
    "sg:classifiers":[
        {
            "category":"Mining & Drilling",
            "type":"Manufacturing & Wholesale Goods"
        }
    ],
    "sg:phone":"+1 780 826 3409",
    "sg:postcode":"T9N 2N6",
    "sg:province":"AB",
    "sg:tags":[
        "field",
        "oil"
    ],
    "wof:name":"Baker Atlas CO",
    "wof:placetype":"venue"
},
  "geometry": {"coordinates":[-110.766533,54.267365],"type":"Point"}
}