{
  "type": "Feature",
  "properties": {
    "addr:full":"28 Industrial Rd Richmond Hill ON L4C 2Y1",
    "addr:housenumber":"28",
    "addr:postcode":"l4c 2y1",
    "addr:street":"Industrial Rd",
    "iso:country":"CA",
    "sg:address":"28 Industrial Rd",
    "sg:city":"Richmond Hill",
    "sg:classifiers":[
        {
            "category":"Home & Garden",
            "subcategory":"Building Materials",
            "type":"Retail Goods"
        }
    ],
    "sg:phone":"+1 905 889 0358",
    "sg:postcode":"L4C 2Y1",
    "sg:province":"ON",
    "sg:tags":[
        "windows"
    ],
    "wof:name":"Reliance Windows Ltd",
    "wof:placetype":"venue"
},
  "geometry": {"coordinates":[-79.4396286011,43.8867835999],"type":"Point"}
}