{
  "type": "Feature",
  "properties": {
    "addr:full":"380 Boul Larochelle Repentigny QC J6A 5W2",
    "addr:housenumber":"380",
    "addr:postcode":"j6a 5w2",
    "addr:street":"Boul Larochelle",
    "iso:country":"CA",
    "sg:address":"380 Boul Larochelle",
    "sg:city":"Repentigny",
    "sg:classifiers":[
        {
            "category":"Food & Beverages",
            "subcategory":"Groceries & Convenience Stores",
            "type":"Retail Goods"
        }
    ],
    "sg:phone":"+1 450 581 7270",
    "sg:postcode":"J6A 5W2",
    "sg:province":"QC",
    "wof:name":"Depanneur Beau-Soir Larochelle",
    "wof:placetype":"venue"
},
  "geometry": {"coordinates":[-73.46923065190001,45.7430381775],"type":"Point"}
}