{
  "type": "Feature",
  "properties": {
    "addr:full":"6686 Waterloo St Kars ON K0A 2E0",
    "addr:housenumber":"6686",
    "addr:postcode":"k0a 2e0",
    "addr:street":"Waterloo St",
    "iso:country":"CA",
    "sg:address":"6686 Waterloo St",
    "sg:city":"Kars",
    "sg:classifiers":[
        {
            "category":"Building & Trades",
            "subcategory":"Plumbing",
            "type":"Services"
        }
    ],
    "sg:phone":"+1 613 489 2073",
    "sg:postcode":"K0A 2E0",
    "sg:province":"ON",
    "sg:tags":[
        "conditioning",
        "air",
        "system",
        "contractor"
    ],
    "wof:name":"Manotick Energy Systems Ltd",
    "wof:placetype":"venue"
},
  "geometry": {"coordinates":[-75.646286,45.151985],"type":"Point"}
}