{
  "type": "Feature",
  "properties": {
    "addr:full":"Mississauga ON L5V 2A8",
    "addr:postcode":"l5v 2a8",
    "iso:country":"CA",
    "sg:city":"Mississauga",
    "sg:classifiers":[
        {
            "category":"Restaurant",
            "type":"Food & Drink"
        }
    ],
    "sg:phone":"+1 905 826 2220",
    "sg:postcode":"L5V 2A8",
    "sg:province":"ON",
    "sg:tags":[
        "sandwich"
    ],
    "wof:name":"Mr Sub",
    "wof:placetype":"venue"
},
  "geometry": {"coordinates":[-79.71434000000001,43.54686],"type":"Point"}
}