{
  "type": "Feature",
  "properties": {
    "addr:full":"222 Main St S Dauphin MB R7N 1K6",
    "addr:housenumber":"222",
    "addr:postcode":"r7n 1k6",
    "addr:street":"Main St S Dauphin",
    "iso:country":"CA",
    "sg:address":"222 Main St S",
    "sg:city":"Dauphin",
    "sg:classifiers":[
        {
            "category":"Food & Beverages",
            "subcategory":"Groceries & Convenience Stores",
            "type":"Retail Goods"
        }
    ],
    "sg:phone":"+1 204 638 8249",
    "sg:postcode":"R7N 1K6",
    "sg:province":"MB",
    "wof:name":"Dauphin Husky",
    "wof:placetype":"venue"
},
  "geometry": {"coordinates":[-100.051834,51.147839],"type":"Point"}
}