{
  "type": "Feature",
  "properties": {
    "addr:full":"1555 Rue Trudel Shawinigan QC G9N 8K8",
    "addr:housenumber":"1555",
    "addr:postcode":"g9n 8k8",
    "addr:street":"Rue Trudel",
    "iso:country":"CA",
    "sg:address":"1555 Rue Trudel",
    "sg:city":"Shawinigan",
    "sg:classifiers":[
        {
            "category":"Retail",
            "subcategory":"Auto Repair",
            "type":"Services"
        }
    ],
    "sg:phone":"+1 819 537 8999",
    "sg:postcode":"G9N 8K8",
    "sg:province":"QC",
    "sg:tags":[
        "automobile",
        "parts",
        "rustproofing",
        "undercoating",
        "supply"
    ],
    "wof:name":"Canadian Tire Store",
    "wof:placetype":"venue"
},
  "geometry": {"coordinates":[-72.7487335205,46.555519104],"type":"Point"}
}