{
  "type": "Feature",
  "properties": {
    "iso:country":"CA",
    "sg:address":"529 Rue Jette",
    "sg:city":"Laval",
    "sg:classifiers":[
        {
            "category":"Retail",
            "subcategory":"Auto Repair",
            "type":"Services"
        }
    ],
    "sg:phone":"+1 450 969 3031",
    "sg:postcode":"H7X 2N6",
    "sg:province":"QC",
    "sg:tags":[
        "automotive",
        "consultant"
    ],
    "wof:name":"Services Spenco Enr",
    "wof:placetype":"venue"
},
  "geometry": {"coordinates":[-73.803856,45.517902],"type":"Point"}
}