{
  "type": "Feature",
  "properties": {
    "addr:full":"1700 Winnipeg St Regina SK S4P 1E9",
    "addr:housenumber":"1700",
    "addr:postcode":"s4p 1e9",
    "addr:street":"Winnipeg St",
    "iso:country":"CA",
    "sg:address":"1700 Winnipeg St",
    "sg:city":"Regina",
    "sg:classifiers":[
        {
            "category":"Retail",
            "subcategory":"Auto Repair",
            "type":"Services"
        }
    ],
    "sg:phone":"+1 306 525 0559",
    "sg:postcode":"S4P 1E9",
    "sg:province":"SK",
    "sg:tags":[
        "repairing",
        "automobile"
    ],
    "wof:name":"Rudy's Brakes & Steering Ltd",
    "wof:placetype":"venue"
},
  "geometry": {"coordinates":[-104.595405579,50.4517326355],"type":"Point"}
}