{
  "type": "Feature",
  "properties": {
    "iso:country":"CA",
    "sg:address":"213 Broad St",
    "sg:city":"Cut Knife",
    "sg:classifiers":[
        {
            "category":"Cinema",
            "subcategory":"Movie Theater",
            "type":"Entertainment"
        }
    ],
    "sg:phone":"+1 306 398 2231",
    "sg:postcode":"S0M 0N0",
    "sg:province":"SK",
    "wof:name":"Cut Knife Theatre",
    "wof:placetype":"venue"
},
  "geometry": {"coordinates":[-109.024635315,52.7446212769],"type":"Point"}
}