{
  "type": "Feature",
  "properties": {
    "addr:full":"4 Wellington St Smiths Falls ON K7A 1E5",
    "addr:housenumber":"4",
    "addr:postcode":"k7a 1e5",
    "addr:street":"Wellington St",
    "iso:country":"CA",
    "sg:address":"4 Wellington St",
    "sg:city":"Smiths Falls",
    "sg:classifiers":[
        {
            "category":"Wholesale",
            "subcategory":"Electrical",
            "type":"Manufacturing & Wholesale Goods"
        }
    ],
    "sg:phone":"+1 613 283 5195",
    "sg:postcode":"K7A 1E5",
    "sg:province":"ON",
    "sg:tags":[
        "equipment",
        "testing",
        "electronic",
        "supply"
    ],
    "wof:name":"W J Ford Surplus Enterprises",
    "wof:placetype":"venue"
},
  "geometry": {"coordinates":[-76.02151499999999,44.902584],"type":"Point"}
}