{
  "type": "Feature",
  "properties": {
    "iso:country":"CA",
    "sg:city":"Toronto",
    "sg:classifiers":[
        {
            "category":"Restaurant",
            "type":"Food & Drink"
        }
    ],
    "sg:phone":"+1 416 408 4999",
    "sg:postcode":"M5T 3A5",
    "sg:province":"ON",
    "wof:name":"Sky Dragon Chinese Cuisine",
    "wof:placetype":"venue"
},
  "geometry": {"coordinates":[-79.3982162476,43.6525650024],"type":"Point"}
}