{
  "type": "Feature",
  "properties": {
    "addr:full":"Milton ON L9T 5B5",
    "addr:postcode":"l9t 5b5",
    "iso:country":"CA",
    "sg:city":"Milton",
    "sg:classifiers":[
        {
            "category":"Health Services",
            "subcategory":"Health Practitioner",
            "type":"Services"
        }
    ],
    "sg:phone":"+1 905 878 9293",
    "sg:postcode":"L9T 5B5",
    "sg:province":"ON",
    "sg:tags":[
        "physiotherapist",
        "therapist",
        "massage"
    ],
    "wof:name":"Milton Physiotherapy & Sports",
    "wof:placetype":"venue"
},
  "geometry": {"coordinates":[-79.872246,43.496281],"type":"Point"}
}