{
  "type": "Feature",
  "properties": {
    "addr:full":"200 Ch Du Rang 4 Morin-Heights QC J0R 1H0",
    "addr:housenumber":"200",
    "addr:postcode":"j0r 1h0",
    "addr:street":"Ch Du Rang 4",
    "iso:country":"CA",
    "sg:address":"200 Ch Du Rang 4",
    "sg:city":"Morin-Heights",
    "sg:classifiers":[
        {
            "category":"Communications",
            "subcategory":"Film & Video Production",
            "type":"Services"
        }
    ],
    "sg:phone":"+1 450 226 8684",
    "sg:postcode":"J0R 1H0",
    "sg:province":"QC",
    "sg:tags":[
        "motion",
        "picture",
        "studio",
        "producer"
    ],
    "wof:name":"Shootfilms",
    "wof:placetype":"venue"
},
  "geometry": {"coordinates":[-74.2125778198,45.917263031],"type":"Point"}
}