{
  "type": "Feature",
  "properties": {
    "addr:full":"94 Principale St-Francois-Xavier-DE-Brompton QC J0B 2V0",
    "addr:housenumber":"94",
    "addr:postcode":"j0b 2v0",
    "addr:street":"Principale St-Francois-Xavier-De-Brompton",
    "iso:country":"CA",
    "sg:address":"94 Principale",
    "sg:city":"St-Francois-Xavier-DE-Brompton",
    "sg:classifiers":[
        {
            "category":"Government",
            "subcategory":"Office",
            "type":"Public Place"
        }
    ],
    "sg:phone":"+1 819 845 3954",
    "sg:postcode":"J0B 2V0",
    "sg:province":"QC",
    "sg:tags":[
        "village"
    ],
    "wof:name":"St-Francois-Xavier DE Brompton",
    "wof:placetype":"venue"
},
  "geometry": {"coordinates":[-72.045502,45.54052],"type":"Point"}
}