{
  "type": "Feature",
  "properties": {
    "iso:country":"CA",
    "sg:address":"1264 Av Du Mont-Royal E",
    "sg:city":"Montreal",
    "sg:classifiers":[
        {
            "category":"Shopping",
            "subcategory":"Shoes",
            "type":"Retail Goods"
        }
    ],
    "sg:phone":"+1 514 525 3084",
    "sg:postcode":"H2J 1Y3",
    "sg:province":"QC",
    "wof:name":"Chaussures Rossini",
    "wof:placetype":"venue"
},
  "geometry": {"coordinates":[-73.577652,45.529392],"type":"Point"}
}