{
  "type": "Feature",
  "properties": {
    "addr:full":"1264 Av Du Mont-Royal E Montreal QC H2J 1Y3",
    "addr:housenumber":"1264",
    "addr:postcode":"h2j 1y3",
    "addr:street":"Av Du Mont-Royal E",
    "iso:country":"CA",
    "sg:address":"1264 Av Du Mont-Royal E",
    "sg:city":"Montreal",
    "sg:classifiers":[
        {
            "category":"Shopping",
            "subcategory":"Shoes",
            "type":"Retail Goods"
        }
    ],
    "sg:phone":"+1 514 525 3084",
    "sg:postcode":"H2J 1Y3",
    "sg:province":"QC",
    "wof:name":"Chaussures Rossini",
    "wof:placetype":"venue"
},
  "geometry": {"coordinates":[-73.577652,45.529392],"type":"Point"}
}