{
  "type": "Feature",
  "properties": {
    "addr:full":"1652 Jane St York ON M9N 2S1",
    "addr:housenumber":"1652",
    "addr:postcode":"m9n 2s1",
    "addr:street":"Jane St",
    "iso:country":"CA",
    "sg:address":"1652 Jane St",
    "sg:city":"York",
    "sg:classifiers":[
        {
            "category":"Building & Trades",
            "subcategory":"Plumbing",
            "type":"Services"
        }
    ],
    "sg:phone":"+1 416 241 6188",
    "sg:postcode":"M9N 2S1",
    "sg:province":"ON",
    "sg:tags":[
        "contractor"
    ],
    "wof:name":"Laneway Plumbing Svc",
    "wof:placetype":"venue"
},
  "geometry": {"coordinates":[-79.50356292719999,43.7016448975],"type":"Point"}
}