{
  "type": "Feature",
  "properties": {
    "addr:full":"2176 Northwest Rd Trout Brook NB E9E 1N2",
    "addr:housenumber":"2176",
    "addr:postcode":"e9e 1n2",
    "addr:street":"Northwest Rd",
    "iso:country":"CA",
    "sg:address":"2176 Northwest Rd",
    "sg:city":"Trout Brook",
    "sg:classifiers":[
        {
            "category":"Travel",
            "subcategory":"Campground",
            "type":"Entertainment"
        }
    ],
    "sg:phone":"+1 506 622 0676",
    "sg:postcode":"E9E 1N2",
    "sg:province":"NB",
    "sg:tags":[
        "tackle",
        "camp",
        "fishing"
    ],
    "wof:name":"Trout Brook Fly Shop",
    "wof:placetype":"venue"
},
  "geometry": {"coordinates":[-65.785866,47.115681],"type":"Point"}
}