{
  "type": "Feature",
  "properties": {
    "addr:full":"12433 102 Ave NW Edmonton AB T5N 0M2",
    "addr:housenumber":"12433",
    "addr:postcode":"t5n 0m2",
    "addr:street":"102 Ave Nw",
    "iso:country":"CA",
    "sg:address":"12433 102 Ave NW",
    "sg:city":"Edmonton",
    "sg:classifiers":[
        {
            "category":"Shopping",
            "subcategory":"Books",
            "type":"Retail Goods"
        }
    ],
    "sg:phone":"+1 780 488 2665",
    "sg:postcode":"T5N 0M2",
    "sg:province":"AB",
    "sg:tags":[
        "dealer"
    ],
    "wof:name":"Laurie Greenwood's Volume II",
    "wof:placetype":"venue"
},
  "geometry": {"coordinates":[-113.536552429,53.5428771973],"type":"Point"}
}