{
  "type": "Feature",
  "properties": {
    "iso:country":"CA",
    "sg:address":"3826 Collingwood Dr NW",
    "sg:city":"Calgary",
    "sg:classifiers":[
        {
            "category":"Education",
            "subcategory":"School",
            "type":"Public Place"
        }
    ],
    "sg:phone":"+1 403 777 6180",
    "sg:postcode":"T2L 0R6",
    "sg:province":"AB",
    "wof:name":"Collingwood Elementary School",
    "wof:placetype":"venue"
},
  "geometry": {"coordinates":[-114.104766846,51.085395813],"type":"Point"}
}