{
  "type": "Feature",
  "properties": {
    "addr:full":"3826 Collingwood Dr NW Calgary AB T2L 0R6",
    "addr:housenumber":"3826",
    "addr:postcode":"t2l 0r6",
    "addr:street":"Collingwood Dr Nw",
    "iso:country":"CA",
    "sg:address":"3826 Collingwood Dr NW",
    "sg:city":"Calgary",
    "sg:classifiers":[
        {
            "category":"Education",
            "subcategory":"School",
            "type":"Public Place"
        }
    ],
    "sg:phone":"+1 403 777 6180",
    "sg:postcode":"T2L 0R6",
    "sg:province":"AB",
    "wof:name":"Collingwood Elementary School",
    "wof:placetype":"venue"
},
  "geometry": {"coordinates":[-114.104766846,51.085395813],"type":"Point"}
}