{
  "type": "Feature",
  "properties": {
    "addr:full":"1000 Teron Rd Kanata ON K2K 1R1",
    "addr:housenumber":"1000",
    "addr:postcode":"k2k 1r1",
    "addr:street":"Teron Rd",
    "iso:country":"CA",
    "sg:address":"1000 Teron Rd",
    "sg:city":"Kanata",
    "sg:classifiers":[
        {
            "category":"Social Services",
            "subcategory":"Child Care",
            "type":"Services"
        }
    ],
    "sg:phone":"+1 613 592 5151",
    "sg:postcode":"K2K 1R1",
    "sg:province":"ON",
    "wof:name":"Elsie Stapleford Child Care",
    "wof:placetype":"venue"
},
  "geometry": {"coordinates":[-75.8965682983,45.3270339966],"type":"Point"}
}