{
  "type": "Feature",
  "properties": {
    "addr:full":"2230 Rue Saint-Louis Saint-Laurent QC H4M 1P3",
    "addr:housenumber":"2230",
    "addr:postcode":"h4m 1p3",
    "addr:street":"Rue Saint-Louis",
    "iso:country":"CA",
    "sg:address":"2230 Rue Saint-Louis",
    "sg:city":"Saint-Laurent",
    "sg:classifiers":[
        {
            "category":"Professional",
            "subcategory":"Computer Services",
            "type":"Services"
        }
    ],
    "sg:phone":"+1 514 747 3499",
    "sg:postcode":"H4M 1P3",
    "sg:province":"QC",
    "sg:tags":[
        "information",
        "system",
        "consultant"
    ],
    "wof:name":"Global Net",
    "wof:placetype":"venue"
},
  "geometry": {"coordinates":[-73.68319700000001,45.499428],"type":"Point"}
}