{
  "type": "Feature",
  "properties": {
    "addr:full":"Winnipeg MB R3H 0T1",
    "addr:postcode":"r3h 0t1",
    "iso:country":"CA",
    "sg:city":"Winnipeg",
    "sg:classifiers":[
        {
            "category":"Real Estate",
            "subcategory":"Surveying",
            "type":"Services"
        }
    ],
    "sg:phone":"+1 204 783 2007",
    "sg:postcode":"R3H 0T1",
    "sg:province":"MB",
    "sg:tags":[
        "surveyor"
    ],
    "wof:name":"Andre Van DE Walle Land Survey",
    "wof:placetype":"venue"
},
  "geometry": {"coordinates":[-97.215401,49.892357],"type":"Point"}
}