{
  "type": "Feature",
  "properties": {
    "addr:full":"2655 Ware St Abbotsford BC V2S 3E7",
    "addr:housenumber":"2655",
    "addr:postcode":"v2s 3e7",
    "addr:street":"Ware St",
    "iso:country":"CA",
    "sg:address":"2655 Ware St",
    "sg:city":"Abbotsford",
    "sg:classifiers":[
        {
            "category":"Food & Beverages",
            "subcategory":"Groceries & Convenience Stores",
            "type":"Retail Goods"
        }
    ],
    "sg:phone":"+1 604 850 9400",
    "sg:postcode":"V2S 3E7",
    "sg:province":"BC",
    "sg:tags":[
        "grocer"
    ],
    "wof:name":"Ware Food Market",
    "wof:placetype":"venue"
},
  "geometry": {"coordinates":[-122.30452,49.049561],"type":"Point"}
}