{
  "type": "Feature",
  "properties": {
    "addr:full":"36 Marshall Cres Ajax ON L1T 2N5",
    "addr:housenumber":"36",
    "addr:postcode":"l1t 2n5",
    "addr:street":"Marshall Cres",
    "iso:country":"CA",
    "sg:address":"36 Marshall Cres",
    "sg:city":"Ajax",
    "sg:classifiers":[
        {
            "category":"Building & Trades",
            "subcategory":"Cleaning & Sanitation",
            "type":"Services"
        }
    ],
    "sg:phone":"+1 905 427 8725",
    "sg:postcode":"L1T 2N5",
    "sg:province":"ON",
    "wof:name":"Finishing Touch Cleaning Svc",
    "wof:placetype":"venue"
},
  "geometry": {"coordinates":[-79.04248046879999,43.8734321594],"type":"Point"}
}