{
  "type": "Feature",
  "properties": {
    "addr:full":"106 Queens Rd W North Vancouver BC V7N 2K3",
    "addr:housenumber":"106",
    "addr:postcode":"v7n 2k3",
    "addr:street":"Queens Rd W",
    "iso:country":"CA",
    "sg:address":"106 Queens Rd W",
    "sg:city":"North Vancouver",
    "sg:classifiers":[
        {
            "category":"Autos & Motor Vehicles",
            "subcategory":"Fuel & Gas Station",
            "type":"Retail Goods"
        }
    ],
    "sg:phone":"+1 604 980 9124",
    "sg:postcode":"V7N 2K3",
    "sg:province":"BC",
    "sg:tags":[
        "oil"
    ],
    "wof:name":"North Van Esso",
    "wof:placetype":"venue"
},
  "geometry": {"coordinates":[-123.072159,49.336704],"type":"Point"}
}