{
  "type": "Feature",
  "properties": {
    "addr:full":"Lac-Saint-Charles QC G3G 1P5",
    "addr:postcode":"g3g 1p5",
    "addr:street":"Lac-Saint-Charles",
    "iso:country":"CA",
    "sg:city":"Lac-Saint-Charles",
    "sg:classifiers":[
        {
            "category":"Professional",
            "subcategory":"Business Services",
            "type":"Services"
        }
    ],
    "sg:phone":"+1 418 849 1857",
    "sg:postcode":"G3G 1P5",
    "sg:province":"QC",
    "sg:tags":[
        "notary"
    ],
    "wof:name":"Gilbert, Hugues",
    "wof:placetype":"venue"
},
  "geometry": {"coordinates":[-71.360283,46.9053],"type":"Point"}
}