{
  "type": "Feature",
  "properties": {
    "addr:full":"Lac Du Bonnet MB R0E 1A0",
    "addr:postcode":"r0e 1a0",
    "iso:country":"CA",
    "sg:city":"Lac Du Bonnet",
    "sg:classifiers":[
        {
            "category":"Building & Trades",
            "subcategory":"Plumbing",
            "type":"Services"
        }
    ],
    "sg:phone":"+1 204 345 6738",
    "sg:postcode":"R0E 1A0",
    "sg:province":"MB",
    "sg:tags":[
        "tank",
        "septic"
    ],
    "wof:name":"Mr Christie's Septic Cleaning",
    "wof:placetype":"venue"
},
  "geometry": {"coordinates":[-96.516975,50.069916],"type":"Point"}
}