{
  "type": "Feature",
  "properties": {
    "addr:full":"203 Ossington Ave Toronto ON M6J 2Z8",
    "addr:housenumber":"203",
    "addr:postcode":"m6j 2z8",
    "addr:street":"Ossington Ave",
    "iso:country":"CA",
    "sg:address":"203 Ossington Ave",
    "sg:city":"Toronto",
    "sg:classifiers":[
        {
            "category":"Home & Garden",
            "subcategory":"Furniture",
            "type":"Retail Goods"
        }
    ],
    "sg:phone":"+1 416 534 2242",
    "sg:postcode":"M6J 2Z8",
    "sg:province":"ON",
    "sg:tags":[
        "equipment",
        "kitchen",
        "cabinet"
    ],
    "wof:name":"Falcon Kitchens",
    "wof:placetype":"venue"
},
  "geometry": {"coordinates":[-79.42027299999999,43.648624],"type":"Point"}
}