{
  "type": "Feature",
  "properties": {
    "addr:full":"North York ON M3N 2J2",
    "addr:postcode":"m3n 2j2",
    "iso:country":"CA",
    "sg:city":"North York",
    "sg:classifiers":[
        {
            "category":"Health Services",
            "subcategory":"Doctor",
            "type":"Services"
        }
    ],
    "sg:phone":"+1 416 740 5514",
    "sg:postcode":"M3N 2J2",
    "sg:province":"ON",
    "sg:tags":[
        "dentist"
    ],
    "wof:name":"Julio Garcia Dental Office",
    "wof:placetype":"venue"
},
  "geometry": {"coordinates":[-79.5154876709,43.7478256226],"type":"Point"}
}