{
  "type": "Feature",
  "properties": {
    "addr:full":"25167 50 Ave Aldergrove BC V4W 1A4",
    "addr:housenumber":"25167",
    "addr:postcode":"v4w 1a4",
    "addr:street":"50 Ave",
    "iso:country":"CA",
    "sg:address":"25167 50 Ave",
    "sg:city":"Aldergrove",
    "sg:classifiers":[
        {
            "category":"Building & Trades",
            "subcategory":"Construction",
            "type":"Services"
        }
    ],
    "sg:phone":"+1 604 856 6518",
    "sg:postcode":"V4W 1A4",
    "sg:province":"BC",
    "sg:tags":[
        "excavating",
        "contractor",
        "trucking"
    ],
    "wof:name":"Kodiak Trucking & Equipment",
    "wof:placetype":"venue"
},
  "geometry": {"coordinates":[-122.472290039,49.0568656921],"type":"Point"}
}