{
  "type": "Feature",
  "properties": {
    "addr:full":"207 Charlotte St Fredericton NB E3B 1L5",
    "addr:housenumber":"207",
    "addr:postcode":"e3b 1l5",
    "addr:street":"Charlotte St",
    "iso:country":"CA",
    "sg:address":"207 Charlotte St",
    "sg:city":"Fredericton",
    "sg:classifiers":[
        {
            "category":"Food & Beverages",
            "subcategory":"Specialty",
            "type":"Retail Goods"
        }
    ],
    "sg:phone":"+1 506 459 4333",
    "sg:postcode":"E3B 1L5",
    "sg:province":"NB",
    "sg:tags":[
        "health",
        "diet"
    ],
    "wof:name":"True Food Organics",
    "wof:placetype":"venue"
},
  "geometry": {"coordinates":[-66.65041351319999,45.9611167908],"type":"Point"}
}