{
  "type": "Feature",
  "properties": {
    "addr:full":"1566 7th Ave Prince George BC V2L 3P4",
    "addr:housenumber":"1566",
    "addr:postcode":"v2l 3p4",
    "addr:street":"7Th Ave",
    "iso:country":"CA",
    "sg:address":"1566 7th Ave",
    "sg:city":"Prince George",
    "sg:classifiers":[
        {
            "category":"Professional",
            "subcategory":"Management & Consulting",
            "type":"Services"
        }
    ],
    "sg:phone":"+1 250 562 9622",
    "sg:postcode":"V2L 3P4",
    "sg:province":"BC",
    "sg:tags":[
        "consultant",
        "business"
    ],
    "wof:name":"Community Futures Development",
    "wof:placetype":"venue"
},
  "geometry": {"coordinates":[-122.752678,53.915241],"type":"Point"}
}