{
  "type": "Feature",
  "properties": {
    "addr:full":"Halifax NS B3J 1H6",
    "addr:postcode":"ns b3j 1h6",
    "iso:country":"CA",
    "sg:city":"Halifax",
    "sg:classifiers":[
        {
            "category":"Professional",
            "subcategory":"Accounting & Tax Preparation",
            "type":"Services"
        }
    ],
    "sg:phone":"+1 902 422 8020",
    "sg:postcode":"B3J 1H6",
    "sg:province":"NS",
    "sg:tags":[
        "accountant",
        "return",
        "filing"
    ],
    "wof:name":"A G Marsh Ltd",
    "wof:placetype":"venue"
},
  "geometry": {"coordinates":[-63.579044,44.642334],"type":"Point"}
}