{
  "type": "Feature",
  "properties": {
    "iso:country":"CA",
    "sg:address":"75 Glen Cameron Rd",
    "sg:city":"Thornhill",
    "sg:classifiers":[
        {
            "category":"Wholesale",
            "subcategory":"Electrical",
            "type":"Manufacturing & Wholesale Goods"
        }
    ],
    "sg:phone":"+1 905 889 2862",
    "sg:postcode":"L3T 1N8",
    "sg:province":"ON",
    "sg:tags":[
        "equipment",
        "electronic",
        "electric",
        "contractor"
    ],
    "wof:name":"Raymar Electrical Sales",
    "wof:placetype":"venue"
},
  "geometry": {"coordinates":[-79.414864,43.806732],"type":"Point"}
}