{
  "type": "Feature",
  "properties": {
    "addr:full":"12025 Oceola Rd Winfield BC V4V 1H1",
    "addr:housenumber":"12025",
    "addr:postcode":"v4v 1h1",
    "addr:street":"Oceola Rd",
    "iso:country":"CA",
    "sg:address":"12025 Oceola Rd",
    "sg:city":"Winfield",
    "sg:classifiers":[
        {
            "category":"Organizations",
            "subcategory":"Religious Organization",
            "type":"Services"
        }
    ],
    "sg:phone":"+1 250 766 4433",
    "sg:postcode":"V4V 1H1",
    "sg:province":"BC",
    "sg:tags":[
        "church"
    ],
    "wof:name":"Lake Country Alliance Church",
    "wof:placetype":"venue"
},
  "geometry": {"coordinates":[-119.405601502,50.0245361328],"type":"Point"}
}