{
  "type": "Feature",
  "properties": {
    "addr:full":"3401 Parkside Dr S Lethbridge AB T1J 4R3",
    "addr:housenumber":"3401",
    "addr:postcode":"t1j 4r3",
    "addr:street":"Parkside Dr S",
    "iso:country":"CA",
    "sg:address":"3401 Parkside Dr S",
    "sg:city":"Lethbridge",
    "sg:classifiers":[
        {
            "category":"Restaurant",
            "type":"Food & Drink"
        }
    ],
    "sg:phone":"+1 403 320 8224",
    "sg:postcode":"T1J 4R3",
    "sg:province":"AB",
    "sg:tags":[
        "caterer"
    ],
    "wof:name":"Country Kitchen Catering",
    "wof:placetype":"venue"
},
  "geometry": {"coordinates":[-112.78993199999999,49.690311],"type":"Point"}
}