{
  "type": "Feature",
  "properties": {
    "addr:full":"1315 Kipling Ave Etobicoke ON M9B 3N7",
    "addr:housenumber":"1315",
    "addr:postcode":"m9b 3n7",
    "addr:street":"Kipling Ave",
    "iso:country":"CA",
    "sg:address":"1315 Kipling Ave",
    "sg:city":"Etobicoke",
    "sg:classifiers":[
        {
            "category":"Organizations",
            "subcategory":"Religious Organization",
            "type":"Services"
        }
    ],
    "sg:phone":"+1 416 231 4232",
    "sg:postcode":"M9B 3N7",
    "sg:province":"ON",
    "sg:tags":[
        "church"
    ],
    "wof:name":"St Wilfrid's",
    "wof:placetype":"venue"
},
  "geometry": {"coordinates":[-79.54605100000001,43.666382],"type":"Point"}
}