{
  "type": "Feature",
  "properties": {
    "addr:full":"House 112 Little Grand Rapids MB R0B 0V0",
    "addr:housenumber":"112",
    "addr:postcode":"r0b 0v0",
    "addr:street":"Little Grand",
    "iso:country":"CA",
    "sg:address":"House 112",
    "sg:city":"Little Grand Rapids",
    "sg:classifiers":[
        {
            "category":"Travel",
            "subcategory":"Hotels & Motels",
            "type":"Entertainment"
        }
    ],
    "sg:phone":"+1 204 397 2333",
    "sg:postcode":"R0B 0V0",
    "sg:province":"MB",
    "sg:tags":[
        "tourist",
        "accommodation"
    ],
    "wof:name":"Little Grand Rapids Lodge",
    "wof:placetype":"venue"
},
  "geometry": {"coordinates":[-99.2845077515,53.1849594116],"type":"Point"}
}