{
  "type": "Feature",
  "properties": {
    "addr:full":"222 Stewart Green SW Calgary AB T3H 3C8",
    "addr:housenumber":"222",
    "addr:postcode":"t3h 3c8",
    "addr:street":"Stewart Green Sw",
    "iso:country":"CA",
    "sg:address":"222 Stewart Green SW",
    "sg:city":"Calgary",
    "sg:classifiers":[
        {
            "category":"Shopping",
            "subcategory":"Clothing, Apparel, & Fashions",
            "type":"Retail Goods"
        }
    ],
    "sg:phone":"+1 403 242 8540",
    "sg:postcode":"T3H 3C8",
    "sg:province":"AB",
    "sg:tags":[
        "alteration"
    ],
    "wof:name":"Westhills Alterations",
    "wof:placetype":"venue"
},
  "geometry": {"coordinates":[-114.16870880099999,51.0154876709],"type":"Point"}
}