{
  "type": "Feature",
  "properties": {
    "addr:full":"Surrey BC V3W 4M8",
    "addr:postcode":"v3w 4m8",
    "iso:country":"CA",
    "sg:city":"Surrey",
    "sg:classifiers":[
        {
            "category":"Professional",
            "subcategory":"Management & Consulting",
            "type":"Services"
        }
    ],
    "sg:phone":"+1 604 590 2244",
    "sg:postcode":"V3W 4M8",
    "sg:province":"BC",
    "sg:tags":[
        "party",
        "planning",
        "clown"
    ],
    "wof:name":"Amazing Scruffles the Clown",
    "wof:placetype":"venue"
},
  "geometry": {"coordinates":[-122.856987,49.143986],"type":"Point"}
}