{
  "type": "Feature",
  "properties": {
    "addr:full":"4 Saskatchewan Ave Devon AB T9G 1E7",
    "addr:housenumber":"4",
    "addr:postcode":"t9g 1e7",
    "addr:street":"Saskatchewan Ave",
    "iso:country":"CA",
    "sg:address":"4 Saskatchewan Ave",
    "sg:city":"Devon",
    "sg:classifiers":[
        {
            "category":"Freight",
            "type":"Transportation"
        }
    ],
    "sg:phone":"+1 780 987 4567",
    "sg:postcode":"T9G 1E7",
    "sg:province":"AB",
    "sg:tags":[
        "field",
        "oil"
    ],
    "wof:name":"Robin's Oilfield Hauling Svc",
    "wof:placetype":"venue"
},
  "geometry": {"coordinates":[-113.732254028,53.3669967651],"type":"Point"}
}