{
  "type": "Feature",
  "properties": {
    "addr:full":"79 Rue Saint-Pierre Quebec QC G1K 4A3",
    "addr:housenumber":"79",
    "addr:postcode":"g1k 4a3",
    "addr:street":"Rue Saint-Pierre",
    "iso:country":"CA",
    "sg:address":"79 Rue Saint-Pierre",
    "sg:city":"Quebec",
    "sg:classifiers":[
        {
            "category":"Travel",
            "subcategory":"Hotels & Motels",
            "type":"Entertainment"
        }
    ],
    "sg:phone":"+1 418 694 7981",
    "sg:postcode":"G1K 4A3",
    "sg:province":"QC",
    "wof:name":"Auberge St-Pierre",
    "wof:placetype":"venue"
},
  "geometry": {"coordinates":[-71.2030715942,46.8147544861],"type":"Point"}
}