{
  "type": "Feature",
  "properties": {
    "addr:full":"SE 11 11 6E Anola MB R0E 0A0",
    "addr:housenumber":"11 11 6e",
    "addr:postcode":"r0e 0a0",
    "addr:street":"Se",
    "iso:country":"CA",
    "sg:address":"SE 11 11 6E",
    "sg:city":"Anola",
    "sg:classifiers":[
        {
            "category":"Professional",
            "subcategory":"Accounting & Tax Preparation",
            "type":"Services"
        }
    ],
    "sg:phone":"+1 204 866 3244",
    "sg:postcode":"R0E 0A0",
    "sg:province":"MB",
    "sg:tags":[
        "accountant"
    ],
    "wof:name":"R Marko Accounting Svc",
    "wof:placetype":"venue"
},
  "geometry": {"coordinates":[-96.64109000000001,49.885063],"type":"Point"}
}