{
  "type": "Feature",
  "properties": {
    "addr:full":"Mississauga ON L4T 2T9",
    "addr:postcode":"l4t 2t9",
    "iso:country":"CA",
    "sg:city":"Mississauga",
    "sg:classifiers":[
        {
            "category":"Restaurant",
            "type":"Food & Drink"
        }
    ],
    "sg:phone":"+1 905 671 2758",
    "sg:postcode":"L4T 2T9",
    "sg:province":"ON",
    "wof:name":"Lee's Garden",
    "wof:placetype":"venue"
},
  "geometry": {"coordinates":[-79.63687896730001,43.717716217],"type":"Point"}
}