{
  "type": "Feature",
  "properties": {
    "addr:full":"Richmond BC V6X 4B1",
    "addr:postcode":"v6x 4b1",
    "iso:country":"CA",
    "sg:city":"Richmond",
    "sg:classifiers":[
        {
            "category":"Retail",
            "subcategory":"Auto Rental",
            "type":"Services"
        }
    ],
    "sg:phone":"+1 604 606 2890",
    "sg:postcode":"V6X 4B1",
    "sg:province":"BC",
    "sg:tags":[
        "renting",
        "automobile"
    ],
    "wof:name":"Avis Rent A Car",
    "wof:placetype":"venue"
},
  "geometry": {"coordinates":[-123.140327,49.171345],"type":"Point"}
}