{
  "type": "Feature",
  "properties": {
    "addr:full":"711 8th Ave E Bow Island AB T0K 0G0",
    "addr:housenumber":"711",
    "addr:postcode":"t0k 0g0",
    "addr:street":"8Th Ave E Bow Island",
    "iso:country":"CA",
    "sg:address":"711 8th Ave E",
    "sg:city":"Bow Island",
    "sg:classifiers":[
        {
            "category":"Shopping",
            "subcategory":"Florist",
            "type":"Retail Goods"
        }
    ],
    "sg:phone":"+1 403 545 2080",
    "sg:postcode":"T0K 0G0",
    "sg:province":"AB",
    "sg:tags":[
        "greenhouse"
    ],
    "wof:name":"Bow Island Greenhouses",
    "wof:placetype":"venue"
},
  "geometry": {"coordinates":[-111.36518859900001,49.8669204712],"type":"Point"}
}