{
  "type": "Feature",
  "properties": {
    "addr:full":"161 Annette St Toronto ON M6P 1P5",
    "addr:housenumber":"161",
    "addr:postcode":"m6p 1p5",
    "addr:street":"Annette St",
    "iso:country":"CA",
    "sg:address":"161 Annette St",
    "sg:city":"Toronto",
    "sg:classifiers":[
        {
            "category":"Organizations",
            "subcategory":"Religious Organization",
            "type":"Services"
        }
    ],
    "sg:phone":"+1 416 769 8104",
    "sg:postcode":"M6P 1P5",
    "sg:province":"ON",
    "sg:tags":[
        "church"
    ],
    "wof:name":"Mission of the Vietnamese",
    "wof:placetype":"venue"
},
  "geometry": {"coordinates":[-79.46704099999999,43.663296],"type":"Point"}
}