{
  "type": "Feature",
  "properties": {
    "addr:full":"Saint-Alphonse-Rodriguez QC J0K 1W0",
    "addr:postcode":"j0k 1w0",
    "iso:country":"CA",
    "sg:city":"Saint-Alphonse-Rodriguez",
    "sg:classifiers":[
        {
            "category":"Food & Beverages",
            "subcategory":"Liquor & Beverages",
            "type":"Retail Goods"
        }
    ],
    "sg:phone":"+1 450 883 2963",
    "sg:postcode":"J0K 1W0",
    "sg:province":"QC",
    "sg:tags":[
        "grocer"
    ],
    "wof:name":"Marche St-Alphonse",
    "wof:placetype":"venue"
},
  "geometry": {"coordinates":[-73.69117,46.185814],"type":"Point"}
}