{
  "type": "Feature",
  "properties": {
    "iso:country":"CA",
    "sg:address":"45 St Clair Ave W # 101",
    "sg:city":"Toronto",
    "sg:classifiers":[
        {
            "category":"Restaurant",
            "type":"Food & Drink"
        }
    ],
    "sg:phone":"+1 416 923 2000",
    "sg:postcode":"M4V 1K9",
    "sg:province":"ON",
    "sg:tags":[
        "caterer"
    ],
    "wof:name":"Executive Catering",
    "wof:placetype":"venue"
},
  "geometry": {"coordinates":[-79.3983840942,43.6870880127],"type":"Point"}
}