{
  "type": "Feature",
  "properties": {
    "iso:country":"CA",
    "sg:address":"210 Bunting Rd",
    "sg:city":"St Catharines",
    "sg:classifiers":[
        {
            "category":"Manufacturing",
            "subcategory":"Tools & Machinery",
            "type":"Manufacturing & Wholesale Goods"
        }
    ],
    "sg:phone":"+1 905 682 4927",
    "sg:postcode":"L2M 3Y1",
    "sg:province":"ON",
    "sg:tags":[
        "thermocouple"
    ],
    "wof:name":"Graham Sensor Technologies",
    "wof:placetype":"venue"
},
  "geometry": {"coordinates":[-79.20977,43.171818],"type":"Point"}
}