{
  "type": "Feature",
  "properties": {
    "iso:country":"CA",
    "sg:address":"403 Place Jacques-Cartier",
    "sg:city":"Montreal",
    "sg:classifiers":[
        {
            "category":"Restaurant",
            "type":"Food & Drink"
        }
    ],
    "sg:phone":"+1 514 398 9090",
    "sg:postcode":"H2Y 3B1",
    "sg:province":"QC",
    "wof:name":"Restaurant Homard-Fou",
    "wof:placetype":"venue"
},
  "geometry": {"coordinates":[-73.552467,45.507801],"type":"Point"}
}