{
  "type": "Feature",
  "properties": {
    "addr:full":"403 Place Jacques-Cartier Montreal QC H2Y 3B1",
    "addr:housenumber":"403",
    "addr:postcode":"h2y 3b1",
    "addr:street":"Place Jacques-Cartier",
    "iso:country":"CA",
    "sg:address":"403 Place Jacques-Cartier",
    "sg:city":"Montreal",
    "sg:classifiers":[
        {
            "category":"Restaurant",
            "type":"Food & Drink"
        }
    ],
    "sg:phone":"+1 514 398 9090",
    "sg:postcode":"H2Y 3B1",
    "sg:province":"QC",
    "wof:name":"Restaurant Homard-Fou",
    "wof:placetype":"venue"
},
  "geometry": {"coordinates":[-73.55246699999999,45.507801],"type":"Point"}
}