{
  "type": "Feature",
  "properties": {
    "addr:full":"445 Thorold Rd Welland ON L3C 3W7",
    "addr:housenumber":"445",
    "addr:postcode":"l3c 3w7",
    "addr:street":"Thorold Rd",
    "iso:country":"CA",
    "sg:address":"445 Thorold Rd",
    "sg:city":"Welland",
    "sg:classifiers":[
        {
            "category":"Restaurant",
            "type":"Food & Drink"
        }
    ],
    "sg:phone":"+1 905 734 1500",
    "sg:postcode":"L3C 3W7",
    "sg:province":"ON",
    "wof:name":"Cafe Amalia",
    "wof:placetype":"venue"
},
  "geometry": {"coordinates":[-79.2781448364,43.0035171509],"type":"Point"}
}