{
  "type": "Feature",
  "properties": {
    "addr:full":"218 Center St Tilley AB T0J 3K0",
    "addr:housenumber":"218",
    "addr:postcode":"t0j 3k0",
    "addr:street":"Center St",
    "iso:country":"CA",
    "sg:address":"218 Center St",
    "sg:city":"Tilley",
    "sg:classifiers":[
        {
            "category":"Retail",
            "subcategory":"Auto Repair",
            "type":"Services"
        }
    ],
    "sg:phone":"+1 403 377 2277",
    "sg:postcode":"T0J 3K0",
    "sg:province":"AB",
    "sg:tags":[
        "repairing",
        "automobile",
        "customizing"
    ],
    "wof:name":"Wester's Garage",
    "wof:placetype":"venue"
},
  "geometry": {"coordinates":[-111.65218400000001,50.451126],"type":"Point"}
}