{
  "type": "Feature",
  "properties": {
    "addr:full":"Dollard-Des-Ormeaux QC H9B 2C5",
    "addr:postcode":"h9b 2c5",
    "iso:country":"CA",
    "sg:city":"Dollard-Des-Ormeaux",
    "sg:classifiers":[
        {
            "category":"Manufacturing",
            "subcategory":"Signs",
            "type":"Manufacturing & Wholesale Goods"
        }
    ],
    "sg:phone":"+1 514 685 5999",
    "sg:postcode":"H9B 2C5",
    "sg:province":"QC",
    "wof:name":"Eficom Intl Inc",
    "wof:placetype":"venue"
},
  "geometry": {"coordinates":[-73.8041381836,45.4797897339],"type":"Point"}
}