{
  "type": "Feature",
  "properties": {
    "addr:full":"315 Front Ignace ON P0T 1T0",
    "addr:housenumber":"315",
    "addr:postcode":"p0t 1t0",
    "addr:street":"Front Ignace",
    "iso:country":"CA",
    "sg:address":"315 Front",
    "sg:city":"Ignace",
    "sg:classifiers":[
        {
            "category":"Government",
            "subcategory":"Fire Station",
            "type":"Public Place"
        }
    ],
    "sg:phone":"+1 807 934 2211",
    "sg:postcode":"P0T 1T0",
    "sg:province":"ON",
    "sg:tags":[
        "department"
    ],
    "wof:name":"Ignace Fire Dept",
    "wof:placetype":"venue"
},
  "geometry": {"coordinates":[-91.661827,49.418274],"type":"Point"}
}