{
  "type": "Feature",
  "properties": {
    "addr:full":"2 Rue Monseigneur-Bourget Levis QC G6V 2Y5",
    "addr:housenumber":"2",
    "addr:postcode":"g6v 2y5",
    "addr:street":"Rue Monseigneur-Bourget",
    "iso:country":"CA",
    "sg:address":"2 Rue Monseigneur-Bourget",
    "sg:city":"Levis",
    "sg:classifiers":[
        {
            "category":"Health Services",
            "subcategory":"Nursing And Care Facility",
            "type":"Services"
        }
    ],
    "sg:phone":"+1 418 835 0971",
    "sg:postcode":"G6V 2Y5",
    "sg:province":"QC",
    "sg:tags":[
        "home",
        "retirement",
        "community"
    ],
    "wof:name":"Chambriere Monseigneur Bourget",
    "wof:placetype":"venue"
},
  "geometry": {"coordinates":[-71.16561900000001,46.825588],"type":"Point"}
}