{
  "type": "Feature",
  "properties": {
    "addr:full":"London ON N6E 2H6",
    "addr:postcode":"n6e 2h6",
    "iso:country":"CA",
    "sg:city":"London",
    "sg:classifiers":[
        {
            "category":"Health Services",
            "subcategory":"Health Practitioner",
            "type":"Services"
        }
    ],
    "sg:phone":"+1 519 685 6294",
    "sg:postcode":"N6E 2H6",
    "sg:province":"ON",
    "sg:tags":[
        "nutritionist"
    ],
    "wof:name":"Herbal Magic",
    "wof:placetype":"venue"
},
  "geometry": {"coordinates":[-81.22397613530001,42.9351348877],"type":"Point"}
}