{
  "type": "Feature",
  "properties": {
    "addr:full":"111 Sundown Close SE Calgary AB T2X 3E1",
    "addr:housenumber":"111",
    "addr:postcode":"t2x 3e1",
    "addr:street":"Sundown Close Se",
    "iso:country":"CA",
    "sg:address":"111 Sundown Close SE",
    "sg:city":"Calgary",
    "sg:classifiers":[
        {
            "category":"Building & Trades",
            "subcategory":"Construction",
            "type":"Services"
        }
    ],
    "sg:phone":"+1 403 256 2170",
    "sg:postcode":"T2X 3E1",
    "sg:province":"AB",
    "sg:tags":[
        "handyman"
    ],
    "wof:name":"Husband For Hire",
    "wof:placetype":"venue"
},
  "geometry": {"coordinates":[-114.054611206,50.8988876343],"type":"Point"}
}