{
  "type": "Feature",
  "properties": {
    "addr:full":"6824 Thorold Stone Rd Niagara Falls ON L2J 1B4",
    "addr:housenumber":"6824",
    "addr:postcode":"l2j 1b4",
    "addr:street":"Thorold Stone Rd",
    "iso:country":"CA",
    "sg:address":"6824 Thorold Stone Rd",
    "sg:city":"Niagara Falls",
    "sg:classifiers":[
        {
            "category":"Restaurant",
            "type":"Food & Drink"
        }
    ],
    "sg:phone":"+1 905 358 0866",
    "sg:postcode":"L2J 1B4",
    "sg:province":"ON",
    "sg:tags":[
        "sandwich"
    ],
    "wof:name":"Substantial Sandwiches & Treat",
    "wof:placetype":"venue"
},
  "geometry": {"coordinates":[-79.1104888916,43.1149215698],"type":"Point"}
}