{
  "type": "Feature",
  "properties": {
    "addr:full":"Langley BC V1M 2R5",
    "addr:postcode":"v1m 2r5",
    "iso:country":"CA",
    "sg:city":"Langley",
    "sg:classifiers":[
        {
            "category":"Restaurant",
            "type":"Food & Drink"
        }
    ],
    "sg:phone":"+1 604 513 9934",
    "sg:postcode":"V1M 2R5",
    "sg:province":"BC",
    "wof:name":"Adobe Grill",
    "wof:placetype":"venue"
},
  "geometry": {"coordinates":[-122.57738494900001,49.1709098816],"type":"Point"}
}