{
  "type": "Feature",
  "properties": {
    "addr:full":"Williams Lake BC V2G 3P5",
    "addr:postcode":"bc v2g 3p5",
    "iso:country":"CA",
    "sg:city":"Williams Lake",
    "sg:phone":"+1 250 392 4224",
    "sg:postcode":"V2G 3P5",
    "sg:province":"BC",
    "sg:tags":[
        "oil"
    ],
    "wof:name":"Chevron Canada Ltd",
    "wof:placetype":"venue"
},
  "geometry": {"coordinates":[-122.131492615,52.1208190918],"type":"Point"}
}