{
  "type": "Feature",
  "properties": {
    "addr:full":"647 Queen St E Sault Ste Marie ON P6A 2A6",
    "addr:housenumber":"647",
    "addr:postcode":"p6a 2a6",
    "addr:street":"Queen St E",
    "iso:country":"CA",
    "sg:address":"647 Queen St E",
    "sg:city":"Sault Ste Marie",
    "sg:classifiers":[
        {
            "category":"Shopping",
            "subcategory":"Clothing, Apparel, & Fashions",
            "type":"Retail Goods"
        }
    ],
    "sg:phone":"+1 705 253 7681",
    "sg:postcode":"P6A 2A6",
    "sg:province":"ON",
    "sg:tags":[
        "shop",
        "bridal",
        "wedding",
        "supply"
    ],
    "wof:name":"Party Palace",
    "wof:placetype":"venue"
},
  "geometry": {"coordinates":[-84.329025,46.508415],"type":"Point"}
}