{
  "type": "Feature",
  "properties": {
    "addr:full":"16126 Stony Plain Rd NW Edmonton AB T5P 4A2",
    "addr:housenumber":"16126",
    "addr:postcode":"t5p 4a2",
    "addr:street":"Stony Plain Rd Nw",
    "iso:country":"CA",
    "sg:address":"16126 Stony Plain Rd NW",
    "sg:city":"Edmonton",
    "sg:classifiers":[
        {
            "category":"Retail",
            "subcategory":"Auto Repair",
            "type":"Services"
        }
    ],
    "sg:phone":"+1 780 484 0011",
    "sg:postcode":"T5P 4A2",
    "sg:province":"AB",
    "sg:tags":[
        "repairing",
        "automobile"
    ],
    "wof:name":"Midas Auto Svc Experts",
    "wof:placetype":"venue"
},
  "geometry": {"coordinates":[-113.59972381599999,53.5414390564],"type":"Point"}
}