{
  "type": "Feature",
  "properties": {
    "addr:full":"352 Sunvale Dr SE Calgary AB T2X 2P1",
    "addr:housenumber":"352",
    "addr:postcode":"t2x 2p1",
    "addr:street":"Sunvale Dr Se",
    "iso:country":"CA",
    "sg:address":"352 Sunvale Dr SE",
    "sg:city":"Calgary",
    "sg:classifiers":[
        {
            "category":"Organizations",
            "subcategory":"Professional Association",
            "type":"Services"
        }
    ],
    "sg:phone":"+1 403 240 4642",
    "sg:postcode":"T2X 2P1",
    "sg:province":"AB",
    "wof:name":"Metis Calgary Family Svc",
    "wof:placetype":"venue"
},
  "geometry": {"coordinates":[-114.049049377,50.8996887207],"type":"Point"}
}