{
  "type": "Feature",
  "properties": {
    "iso:country":"CA",
    "sg:address":"2585 Norcrest Crt",
    "sg:city":"Burnaby",
    "sg:classifiers":[
        {
            "category":"Building & Trades",
            "subcategory":"Construction",
            "type":"Services"
        }
    ],
    "sg:phone":"+1 604 420 2844",
    "sg:postcode":"V3J 1C7",
    "sg:province":"BC",
    "sg:tags":[
        "painter"
    ],
    "wof:name":"Regent Maintenance",
    "wof:placetype":"venue"
},
  "geometry": {"coordinates":[-122.897438,49.260906],"type":"Point"}
}