{
  "type": "Feature",
  "properties": {
    "addr:full":"Montreal QC H2R 2E4",
    "addr:postcode":"h2r 2e4",
    "iso:country":"CA",
    "sg:city":"Montreal",
    "sg:classifiers":[
        {
            "category":"Professional",
            "subcategory":"Business Services",
            "type":"Services"
        }
    ],
    "sg:phone":"+1 514 273 8657",
    "sg:postcode":"H2R 2E4",
    "sg:province":"QC",
    "sg:tags":[
        "interior",
        "consultant",
        "design",
        "decorator"
    ],
    "wof:name":"Suzanne Paquette Enr",
    "wof:placetype":"venue"
},
  "geometry": {"coordinates":[-73.619293,45.539673],"type":"Point"}
}