{
  "type": "Feature",
  "properties": {
    "iso:country":"CA",
    "sg:city":"Toronto",
    "sg:classifiers":[
        {
            "category":"Travel",
            "subcategory":"Travel Agent",
            "type":"Entertainment"
        }
    ],
    "sg:phone":"+1 416 367 5824",
    "sg:postcode":"M5C 1G3",
    "sg:province":"ON",
    "sg:tags":[
        "agency",
        "bureau"
    ],
    "wof:name":"Jtb Intl",
    "wof:placetype":"venue"
},
  "geometry": {"coordinates":[-79.37512207029999,43.6496124268],"type":"Point"}
}