{
  "type": "Feature",
  "properties": {
    "addr:full":"Delta BC V3M 5R8",
    "addr:postcode":"v3m 5r8",
    "iso:country":"CA",
    "sg:city":"Delta",
    "sg:classifiers":[
        {
            "category":"Retail",
            "subcategory":"Auto Repair",
            "type":"Services"
        }
    ],
    "sg:phone":"+1 604 526 6560",
    "sg:postcode":"V3M 5R8",
    "sg:province":"BC",
    "sg:tags":[
        "automobile",
        "co",
        "drive",
        "transporter"
    ],
    "wof:name":"Mcl Mcgill Carriers Ltd",
    "wof:placetype":"venue"
},
  "geometry": {"coordinates":[-122.93699646,49.178981781],"type":"Point"}
}