{
  "type": "Feature",
  "properties": {
    "addr:full":"44 Victoria Blvd York ON M6M 2C1",
    "addr:housenumber":"44",
    "addr:postcode":"m6m 2c1",
    "addr:street":"Victoria Blvd",
    "iso:country":"CA",
    "sg:address":"44 Victoria Blvd",
    "sg:city":"York",
    "sg:classifiers":[
        {
            "category":"Shopping",
            "subcategory":"Computers & Home Electronics",
            "type":"Retail Goods"
        }
    ],
    "sg:phone":"+1 416 364 9355",
    "sg:postcode":"M6M 2C1",
    "sg:province":"ON",
    "sg:tags":[
        "software"
    ],
    "wof:name":"Soliton Assoc Ltd",
    "wof:placetype":"venue"
},
  "geometry": {"coordinates":[-79.4953994751,43.6900215149],"type":"Point"}
}