{
  "type": "Feature",
  "properties": {
    "addr:full":"3640 Rue Sabrevois Montreal-Nord QC H1H 2W6",
    "addr:housenumber":"3640",
    "addr:postcode":"h1h 2w6",
    "addr:street":"Rue Sabrevois",
    "iso:country":"CA",
    "sg:address":"3640 Rue Sabrevois",
    "sg:city":"Montreal-Nord",
    "sg:classifiers":[
        {
            "category":"Building & Trades",
            "subcategory":"Construction",
            "type":"Services"
        }
    ],
    "sg:phone":"+1 514 322 8181",
    "sg:postcode":"H1H 2W6",
    "sg:province":"QC",
    "sg:tags":[
        "fire",
        "restoration",
        "damage"
    ],
    "wof:name":"Entreprises Fontana & Petrone",
    "wof:placetype":"venue"
},
  "geometry": {"coordinates":[-73.63659699999999,45.581161],"type":"Point"}
}