{
  "type": "Feature",
  "properties": {
    "addr:full":"Ottawa ON K1B 4W5",
    "addr:postcode":"k1b 4w5",
    "iso:country":"CA",
    "sg:city":"Ottawa",
    "sg:classifiers":[
        {
            "category":"Real Estate",
            "subcategory":"Real Estate Agent",
            "type":"Services"
        }
    ],
    "sg:phone":"+1 613 738 7688",
    "sg:postcode":"K1B 4W5",
    "sg:province":"ON",
    "sg:tags":[
        "management"
    ],
    "wof:name":"Mody Management Corp",
    "wof:placetype":"venue"
},
  "geometry": {"coordinates":[-75.609886,45.395115],"type":"Point"}
}