{
  "type": "Feature",
  "properties": {
    "addr:full":"27 Rue Notre-Dame Quebec QC G1K 4E9",
    "addr:housenumber":"27",
    "addr:postcode":"g1k 4e9",
    "addr:street":"Rue Notre-Dame",
    "iso:country":"CA",
    "sg:address":"27 Rue Notre-Dame",
    "sg:city":"Quebec",
    "sg:classifiers":[
        {
            "category":"Government",
            "subcategory":"Office",
            "type":"Public Place"
        }
    ],
    "sg:phone":"+1 418 646 3167",
    "sg:postcode":"G1K 4E9",
    "sg:province":"QC",
    "wof:name":"Quebec Centre D'Interpretation",
    "wof:placetype":"venue"
},
  "geometry": {"coordinates":[-71.2029800415,46.8131828308],"type":"Point"}
}