{
  "type": "Feature",
  "properties": {
    "iso:country":"CA",
    "sg:address":"193 3rd Ave W",
    "sg:city":"Vancouver",
    "sg:phone":"+1 604 873 9693",
    "sg:postcode":"V5Y 1E6",
    "sg:province":"BC",
    "sg:tags":[
        "food",
        "equipment",
        "processing"
    ],
    "wof:name":"Vancouver Used Food Equipment",
    "wof:placetype":"venue"
},
  "geometry": {"coordinates":[-123.10899353000001,49.2685165405],"type":"Point"}
}