{
  "type": "Feature",
  "properties": {
    "addr:full":"806 50th St E Saskatoon SK S7K 0X6",
    "addr:housenumber":"806",
    "addr:postcode":"s7k 0x6",
    "addr:street":"50Th St E",
    "iso:country":"CA",
    "sg:address":"806 50th St E",
    "sg:city":"Saskatoon",
    "sg:classifiers":[
        {
            "category":"Building & Trades",
            "subcategory":"Construction",
            "type":"Services"
        }
    ],
    "sg:phone":"+1 306 934 1500",
    "sg:postcode":"S7K 0X6",
    "sg:province":"SK",
    "sg:tags":[
        "product",
        "asphalt"
    ],
    "wof:name":"Pounder Emulsions",
    "wof:placetype":"venue"
},
  "geometry": {"coordinates":[-106.654037,52.17075],"type":"Point"}
}