{
  "type": "Feature",
  "properties": {
    "addr:full":"10309 174 St NW Edmonton AB T5S 1H1",
    "addr:housenumber":"10309",
    "addr:postcode":"t5s 1h1",
    "addr:street":"174 St Nw",
    "iso:country":"CA",
    "sg:address":"10309 174 St NW",
    "sg:city":"Edmonton",
    "sg:classifiers":[
        {
            "category":"Wholesale",
            "subcategory":"Hardware",
            "type":"Manufacturing & Wholesale Goods"
        }
    ],
    "sg:phone":"+1 780 454 8830",
    "sg:postcode":"T5S 1H1",
    "sg:province":"AB",
    "sg:tags":[
        "plumbing",
        "fixture",
        "supply"
    ],
    "wof:name":"R M Bellamy Sales Ltd",
    "wof:placetype":"venue"
},
  "geometry": {"coordinates":[-113.62014770499999,53.5457572937],"type":"Point"}
}