{
  "type": "Feature",
  "properties": {
    "addr:full":"Belleville ON K8N 4Z2",
    "addr:postcode":"k8n 4z2",
    "iso:country":"CA",
    "sg:city":"Belleville",
    "sg:classifiers":[
        {
            "category":"Professional",
            "subcategory":"Accounting & Tax Preparation",
            "type":"Services"
        }
    ],
    "sg:phone":"+1 613 966 6777",
    "sg:postcode":"K8N 4Z2",
    "sg:province":"ON",
    "sg:tags":[
        "accountant"
    ],
    "wof:name":"Descent, Michael CA",
    "wof:placetype":"venue"
},
  "geometry": {"coordinates":[-77.381897,44.161045],"type":"Point"}
}