{
  "type": "Feature",
  "properties": {
    "addr:full":"303 Rue Saint-Jacques Granby QC J2G 3N5",
    "addr:housenumber":"303",
    "addr:postcode":"j2g 3n5",
    "addr:street":"Rue Saint-Jacques",
    "iso:country":"CA",
    "sg:address":"303 Rue Saint-Jacques",
    "sg:city":"Granby",
    "sg:classifiers":[
        {
            "category":"Health Services",
            "subcategory":"Medical Lab",
            "type":"Services"
        }
    ],
    "sg:phone":"+1 450 372 1104",
    "sg:postcode":"J2G 3N5",
    "sg:province":"QC",
    "wof:name":"Clinic Gpr",
    "wof:placetype":"venue"
},
  "geometry": {"coordinates":[-72.732147,45.398926],"type":"Point"}
}