{
  "type": "Feature",
  "properties": {
    "addr:full":"5858 Ch DE LA Cote-Des-Neiges Montreal QC H3S 1Z1",
    "addr:housenumber":"5858",
    "addr:postcode":"h3s 1z1",
    "addr:street":"Ch De La Cote-Des-Neiges",
    "iso:country":"CA",
    "sg:address":"5858 Ch DE LA Cote-Des-Neiges",
    "sg:city":"Montreal",
    "sg:classifiers":[
        {
            "category":"Manufacturing",
            "subcategory":"Printing",
            "type":"Manufacturing & Wholesale Goods"
        }
    ],
    "sg:phone":"+1 514 733 6866",
    "sg:postcode":"H3S 1Z1",
    "sg:province":"QC",
    "sg:tags":[
        "publisher"
    ],
    "wof:name":"Wagner Investment Corp",
    "wof:placetype":"venue"
},
  "geometry": {"coordinates":[-73.6297836304,45.4997062683],"type":"Point"}
}