{
  "type": "Feature",
  "properties": {
    "addr:full":"Scarborough ON M1V 5K4",
    "addr:postcode":"m1v 5k4",
    "iso:country":"CA",
    "sg:city":"Scarborough",
    "sg:classifiers":[
        {
            "category":"Personal",
            "subcategory":"Beauty Salon",
            "type":"Services"
        }
    ],
    "sg:phone":"+1 416 292 7838",
    "sg:postcode":"M1V 5K4",
    "sg:province":"ON",
    "wof:name":"Hair Lab",
    "wof:placetype":"venue"
},
  "geometry": {"coordinates":[-79.29434999999999,43.81892],"type":"Point"}
}