{
  "type": "Feature",
  "properties": {
    "addr:full":"5320 4 St SW Calgary AB T2V 0Z5",
    "addr:housenumber":"5320 4",
    "addr:postcode":"t2v 0z5",
    "addr:street":"St Sw",
    "iso:country":"CA",
    "sg:address":"5320 4 St SW",
    "sg:city":"Calgary",
    "sg:classifiers":[
        {
            "category":"Real Estate",
            "subcategory":"Real Estate Operator",
            "type":"Services"
        }
    ],
    "sg:phone":"+1 403 258 0410",
    "sg:postcode":"T2V 0Z5",
    "sg:province":"AB",
    "sg:tags":[
        "apartment"
    ],
    "wof:name":"Anthonian Court",
    "wof:placetype":"venue"
},
  "geometry": {"coordinates":[-114.07119751,51.0065193176],"type":"Point"}
}