{
  "type": "Feature",
  "properties": {
    "addr:full":"113 Walton St Port Hope ON L1A 1N4",
    "addr:housenumber":"113",
    "addr:postcode":"l1a 1n4",
    "addr:street":"Walton St",
    "iso:country":"CA",
    "sg:address":"113 Walton St",
    "sg:city":"Port Hope",
    "sg:classifiers":[
        {
            "category":"Banks & Credit Unions",
            "subcategory":"Bank",
            "type":"Services"
        }
    ],
    "sg:phone":"+1 905 885 6361",
    "sg:postcode":"L1A 1N4",
    "sg:province":"ON",
    "wof:name":"Td Canada Trust",
    "wof:placetype":"venue"
},
  "geometry": {"coordinates":[-78.29597473139999,43.9519042969],"type":"Point"}
}