{
  "type": "Feature",
  "properties": {
    "addr:full":"7521 Macleod Trail SW Calgary AB T2H 0L8",
    "addr:housenumber":"7521",
    "addr:postcode":"t2h 0l8",
    "addr:street":"Macleod Trail Sw",
    "iso:country":"CA",
    "sg:address":"7521 Macleod Trail SW",
    "sg:city":"Calgary",
    "sg:classifiers":[
        {
            "category":"Restaurant",
            "type":"Food & Drink"
        }
    ],
    "sg:phone":"+1 403 252 8557",
    "sg:postcode":"T2H 0L8",
    "sg:province":"AB",
    "wof:name":"Joey's Only Seafood",
    "wof:placetype":"venue"
},
  "geometry": {"coordinates":[-114.07178500000001,50.985889],"type":"Point"}
}