{
  "type": "Feature",
  "properties": {
    "addr:full":"Hull QC J8Z 1W1",
    "addr:postcode":"j8z 1w1",
    "iso:country":"CA",
    "sg:city":"Hull",
    "sg:classifiers":[
        {
            "category":"Recreation",
            "type":"Entertainment"
        }
    ],
    "sg:phone":"+1 819 777 3535",
    "sg:postcode":"J8Z 1W1",
    "sg:province":"QC",
    "sg:tags":[
        "amusement"
    ],
    "wof:name":"Chez Putters",
    "wof:placetype":"venue"
},
  "geometry": {"coordinates":[-75.740128,45.467693],"type":"Point"}
}