{
  "type": "Feature",
  "properties": {
    "addr:full":"PO Box 46 Tsiigehtchic NT X0E 0B0",
    "addr:housenumber":"po box 46",
    "addr:postcode":"x0e 0b0",
    "iso:country":"CA",
    "sg:address":"PO Box 46",
    "sg:city":"Tsiigehtchic",
    "sg:classifiers":[
        {
            "category":"Organizations",
            "subcategory":"Professional Association",
            "type":"Services"
        }
    ],
    "sg:phone":"+1 867 953 3613",
    "sg:postcode":"X0E 0B0",
    "sg:province":"NT",
    "sg:tags":[
        "native"
    ],
    "wof:name":"Gwich'In Social & Cultural",
    "wof:placetype":"venue"
},
  "geometry": {"coordinates":[-133.744553,67.44227600000001],"type":"Point"}
}