{
  "type": "Feature",
  "properties": {
    "addr:full":"300 14E Av Deux-Montagnes QC J7R 3W4",
    "addr:housenumber":"300",
    "addr:postcode":"j7r 3w4",
    "addr:street":"14E Av Deux-Montagnes",
    "iso:country":"CA",
    "sg:address":"300 14E Av",
    "sg:city":"Deux-Montagnes",
    "sg:classifiers":[
        {
            "category":"Real Estate",
            "subcategory":"Architect",
            "type":"Services"
        }
    ],
    "sg:phone":"+1 450 473 3535",
    "sg:postcode":"J7R 3W4",
    "sg:province":"QC",
    "wof:name":"Claude Fregeau Architecte Enr",
    "wof:placetype":"venue"
},
  "geometry": {"coordinates":[-73.9030456543,45.5424461365],"type":"Point"}
}