{
  "type": "Feature",
  "properties": {
    "iso:country":"CA",
    "sg:address":"5101 Railway Ave",
    "sg:city":"Boyle",
    "sg:classifiers":[
        {
            "category":"Travel",
            "subcategory":"Hotels & Motels",
            "type":"Entertainment"
        }
    ],
    "sg:phone":"+1 780 689 3944",
    "sg:postcode":"T0A 0M0",
    "sg:province":"AB",
    "wof:name":"Boyle Motor Lodge Ltd",
    "wof:placetype":"venue"
},
  "geometry": {"coordinates":[-112.81423950200001,54.5873565674],"type":"Point"}
}