{
  "type": "Feature",
  "properties": {
    "iso:country":"CA",
    "sg:address":"9702 Prairie Rd",
    "sg:city":"Grande Prairie",
    "sg:classifiers":[
        {
            "category":"Real Estate",
            "subcategory":"Real Estate Operator",
            "type":"Services"
        }
    ],
    "sg:phone":"+1 780 532 7758",
    "sg:postcode":"T8V 5X1",
    "sg:province":"AB",
    "sg:tags":[
        "apartment"
    ],
    "wof:name":"North American Leaseholds Ltd",
    "wof:placetype":"venue"
},
  "geometry": {"coordinates":[-118.78702545199999,55.1529350281],"type":"Point"}
}