{
  "type": "Feature",
  "properties": {
    "addr:full":"41 Inglewood Ave Thornhill ON L4J 7T8",
    "addr:housenumber":"41",
    "addr:postcode":"l4j 7t8",
    "addr:street":"Inglewood Ave",
    "iso:country":"CA",
    "sg:address":"41 Inglewood Ave",
    "sg:city":"Thornhill",
    "sg:classifiers":[
        {
            "category":"Health Services",
            "subcategory":"Health Practitioner",
            "type":"Services"
        }
    ],
    "sg:phone":"+1 905 886 1267",
    "sg:postcode":"L4J 7T8",
    "sg:province":"ON",
    "sg:tags":[
        "employment",
        "nurse",
        "agency",
        "opportunity",
        "registry"
    ],
    "wof:name":"Senior Lifestyle Solutions",
    "wof:placetype":"venue"
},
  "geometry": {"coordinates":[-79.46075399999999,43.814678],"type":"Point"}
}