{
  "type": "Feature",
  "properties": {
    "addr:full":"1552 6 Hwy N Hamilton ON L8N 2Z7",
    "addr:housenumber":"1552",
    "addr:postcode":"l8n 2z7",
    "addr:street":"6 Hwy N",
    "iso:country":"CA",
    "sg:address":"1552 6 Hwy N",
    "sg:city":"Hamilton",
    "sg:classifiers":[
        {
            "category":"Organizations",
            "subcategory":"Religious Organization",
            "type":"Services"
        }
    ],
    "sg:phone":"+1 905 659 3343",
    "sg:postcode":"L8N 2Z7",
    "sg:province":"ON",
    "sg:tags":[
        "church"
    ],
    "wof:name":"United Church of Canada",
    "wof:placetype":"venue"
},
  "geometry": {"coordinates":[-80.013115,43.382519],"type":"Point"}
}