{
  "type": "Feature",
  "properties": {
    "iso:country":"CA",
    "sg:address":"8857 63 Ave NW",
    "sg:city":"Edmonton",
    "sg:classifiers":[
        {
            "category":"Wholesale",
            "subcategory":"Motor Vehicles",
            "type":"Manufacturing & Wholesale Goods"
        }
    ],
    "sg:phone":"+1 780 435 8911",
    "sg:postcode":"T6E 0E9",
    "sg:province":"AB",
    "sg:tags":[
        "body",
        "equipment",
        "truck"
    ],
    "wof:name":"California Tops",
    "wof:placetype":"venue"
},
  "geometry": {"coordinates":[-113.46532440199999,53.4996986389],"type":"Point"}
}