{
  "type": "Feature",
  "properties": {
    "addr:full":"PO Box 402 STN Main Brentwood Bay BC V8M 1R3",
    "addr:housenumber":"po",
    "addr:postcode":"v8m 1r3",
    "addr:street":"Box 402 Stn Main",
    "iso:country":"CA",
    "sg:address":"PO Box 402 STN Main",
    "sg:city":"Brentwood Bay",
    "sg:classifiers":[
        {
            "category":"Building & Trades",
            "subcategory":"Construction",
            "type":"Services"
        }
    ],
    "sg:phone":"+1 250 652 1365",
    "sg:postcode":"V8M 1R3",
    "sg:province":"BC",
    "sg:tags":[
        "general",
        "contractor"
    ],
    "wof:name":"A Schenck Construction Ltd",
    "wof:placetype":"venue"
},
  "geometry": {"coordinates":[-123.446266174,48.5758323669],"type":"Point"}
}