{
  "type": "Feature",
  "properties": {
    "addr:full":"Prince Albert SK S6V 4W2",
    "addr:postcode":"s6v 4w2",
    "iso:country":"CA",
    "sg:city":"Prince Albert",
    "sg:classifiers":[
        {
            "category":"Professional",
            "subcategory":"Credit Reporting & Collection",
            "type":"Services"
        }
    ],
    "sg:phone":"+1 306 763 8415",
    "sg:postcode":"S6V 4W2",
    "sg:province":"SK",
    "sg:tags":[
        "agency"
    ],
    "wof:name":"Northern Collection Agencies",
    "wof:placetype":"venue"
},
  "geometry": {"coordinates":[-105.754402,53.200932],"type":"Point"}
}