{
  "type": "Feature",
  "properties": {
    "addr:full":"10 Old Humber Rd Corner Brook NL A2H 1H8",
    "addr:housenumber":"10",
    "addr:postcode":"a2h 1h8",
    "addr:street":"Old Humber Rd",
    "iso:country":"CA",
    "sg:address":"10 Old Humber Rd",
    "sg:city":"Corner Brook",
    "sg:classifiers":[
        {
            "category":"Bars & Pubs",
            "type":"Food & Drink"
        }
    ],
    "sg:phone":"+1 709 634 8913",
    "sg:postcode":"A2H 1H8",
    "sg:province":"NL",
    "sg:tags":[
        "lounge",
        "cocktail"
    ],
    "wof:name":"Marine Lounge Takeout",
    "wof:placetype":"venue"
},
  "geometry": {"coordinates":[-57.9387893677,48.958770752],"type":"Point"}
}