{
  "type": "Feature",
  "properties": {
    "addr:full":"13 Delage Saint-Stanislas-DE-Champlain QC G0X 3E0",
    "addr:housenumber":"13",
    "addr:postcode":"g0x 3e0",
    "addr:street":"Delage Saint-Stanislas-De-Champlain",
    "iso:country":"CA",
    "sg:address":"13 Delage",
    "sg:city":"Saint-Stanislas-DE-Champlain",
    "sg:classifiers":[
        {
            "category":"Wholesale",
            "subcategory":"Farm Supplies",
            "type":"Manufacturing & Wholesale Goods"
        }
    ],
    "sg:phone":"+1 418 329 3000",
    "sg:postcode":"G0X 3E0",
    "sg:province":"QC",
    "sg:tags":[
        "hardware",
        "fertilizer"
    ],
    "wof:name":"Cooperative Agricole Pont-Rge",
    "wof:placetype":"venue"
},
  "geometry": {"coordinates":[-72.34311700000001,46.44104],"type":"Point"}
}