{
  "type": "Feature",
  "properties": {
    "iso:country":"CA",
    "sg:address":"457 Rue Racine E",
    "sg:city":"Chicoutimi",
    "sg:classifiers":[
        {
            "category":"Taxi",
            "type":"Transportation"
        }
    ],
    "sg:phone":"+1 418 543 6003",
    "sg:postcode":"G7H 1T5",
    "sg:province":"QC",
    "sg:tags":[
        "taxicab"
    ],
    "wof:name":"Taxi Du Nord",
    "wof:placetype":"venue"
},
  "geometry": {"coordinates":[-71.054008,48.428677],"type":"Point"}
}