{
  "type": "Feature",
  "properties": {
    "addr:full":"29 N Industrial Dr Prince Albert SK S6V 6V4",
    "addr:housenumber":"29",
    "addr:postcode":"s6v 6v4",
    "addr:street":"N Industrial Dr",
    "iso:country":"CA",
    "sg:address":"29 N Industrial Dr",
    "sg:city":"Prince Albert",
    "sg:classifiers":[
        {
            "category":"Freight",
            "type":"Transportation"
        }
    ],
    "sg:phone":"+1 306 764 0934",
    "sg:postcode":"S6V 6V4",
    "sg:province":"SK",
    "sg:tags":[
        "trucking"
    ],
    "wof:name":"Ridsdale Transport",
    "wof:placetype":"venue"
},
  "geometry": {"coordinates":[-105.756347656,53.2163543701],"type":"Point"}
}