{
  "type": "Feature",
  "properties": {
    "addr:full":"6083 Yonge St North York ON M2M 3W2",
    "addr:housenumber":"6083",
    "addr:postcode":"m2m 3w2",
    "addr:street":"Yonge St",
    "iso:country":"CA",
    "sg:address":"6083 Yonge St",
    "sg:city":"North York",
    "sg:classifiers":[
        {
            "category":"Manufacturing",
            "subcategory":"Metals",
            "type":"Manufacturing & Wholesale Goods"
        }
    ],
    "sg:phone":"+1 905 883 1235",
    "sg:postcode":"M2M 3W2",
    "sg:province":"ON",
    "sg:tags":[
        "lock",
        "safe",
        "locksmith"
    ],
    "wof:name":"Armor Lock Corp",
    "wof:placetype":"venue"
},
  "geometry": {"coordinates":[-79.41806800000001,43.790829],"type":"Point"}
}