{
  "type": "Feature",
  "properties": {
    "iso:country":"CA",
    "sg:address":"6 Adams St",
    "sg:city":"St Catharines",
    "sg:classifiers":[
        {
            "category":"Organizations",
            "subcategory":"Non-profit Organization",
            "type":"Services"
        }
    ],
    "sg:phone":"+1 905 687 9721",
    "sg:postcode":"L2R 2V8",
    "sg:province":"ON",
    "sg:tags":[
        "addiction",
        "treatment",
        "center"
    ],
    "wof:name":"Detox Centre Women's",
    "wof:placetype":"venue"
},
  "geometry": {"coordinates":[-79.25276947019999,43.15807724],"type":"Point"}
}