{
  "type": "Feature",
  "properties": {
    "addr:full":"314 27th St W North Vancouver BC V7N 2H4",
    "addr:housenumber":"314",
    "addr:postcode":"v7n 2h4",
    "addr:street":"27Th St W",
    "iso:country":"CA",
    "sg:address":"314 27th St W",
    "sg:city":"North Vancouver",
    "sg:classifiers":[
        {
            "category":"Professional",
            "subcategory":"Management & Consulting",
            "type":"Services"
        }
    ],
    "sg:phone":"+1 604 980 3229",
    "sg:postcode":"V7N 2H4",
    "sg:province":"BC",
    "sg:tags":[
        "consultant",
        "business"
    ],
    "wof:name":"Strategic Action Group",
    "wof:placetype":"venue"
},
  "geometry": {"coordinates":[-123.07893371599999,49.3343505859],"type":"Point"}
}