{
  "type": "Feature",
  "properties": {
    "addr:full":"12 May St Fenelon Falls ON K0M 1N0",
    "addr:housenumber":"12",
    "addr:postcode":"k0m 1n0",
    "addr:street":"May St",
    "iso:country":"CA",
    "sg:address":"12 May St",
    "sg:city":"Fenelon Falls",
    "sg:classifiers":[
        {
            "category":"Restaurant",
            "type":"Food & Drink"
        }
    ],
    "sg:phone":"+1 705 887 9292",
    "sg:postcode":"K0M 1N0",
    "sg:province":"ON",
    "wof:name":"Woodys",
    "wof:placetype":"venue"
},
  "geometry": {"coordinates":[-78.738029,44.536743],"type":"Point"}
}