{
  "type": "Feature",
  "properties": {
    "addr:full":"990 Fairville Blvd Saint John NB E2M 5T5",
    "addr:housenumber":"990",
    "addr:postcode":"e2m 5t5",
    "addr:street":"Fairville Blvd",
    "iso:country":"CA",
    "sg:address":"990 Fairville Blvd",
    "sg:city":"Saint John",
    "sg:classifiers":[
        {
            "category":"Organizations",
            "subcategory":"Professional Association",
            "type":"Services"
        }
    ],
    "sg:phone":"+1 506 635 4000",
    "sg:postcode":"E2M 5T5",
    "sg:province":"NB",
    "sg:tags":[
        "club"
    ],
    "wof:name":"Aquarius Pub & Restaurant",
    "wof:placetype":"venue"
},
  "geometry": {"coordinates":[-66.10604858400001,45.2475662231],"type":"Point"}
}