{
  "type": "Feature",
  "properties": {
    "addr:full":"520 Boul Clairevue O Saint-Bruno QC J3V 6B3",
    "addr:housenumber":"520",
    "addr:postcode":"j3v 6b3",
    "addr:street":"Boul Clairevue O",
    "iso:country":"CA",
    "sg:address":"520 Boul Clairevue O",
    "sg:city":"Saint-Bruno",
    "sg:classifiers":[
        {
            "category":"Food & Beverages",
            "subcategory":"Groceries & Convenience Stores",
            "type":"Retail Goods"
        }
    ],
    "sg:phone":"+1 450 653 5588",
    "sg:postcode":"J3V 6B3",
    "sg:province":"QC",
    "wof:name":"Couche-Tard",
    "wof:placetype":"venue"
},
  "geometry": {"coordinates":[-71.67552185060001,48.4717712402],"type":"Point"}
}