{
  "type": "Feature",
  "properties": {
    "iso:country":"CA",
    "sg:address":"8595 Boul Saint-Laurent",
    "sg:city":"Montreal",
    "sg:classifiers":[
        {
            "category":"Banks & Credit Unions",
            "subcategory":"Bank",
            "type":"Services"
        }
    ],
    "sg:phone":"+1 514 381 7223",
    "sg:postcode":"H2P 2M9",
    "sg:province":"QC",
    "wof:name":"Banque Nationale Du Canada",
    "wof:placetype":"venue"
},
  "geometry": {"coordinates":[-73.638863,45.541336],"type":"Point"}
}