{
  "type": "Feature",
  "properties": {
    "addr:full":"1784 Heritage Way Oakville ON L6M 3A4",
    "addr:housenumber":"1784",
    "addr:postcode":"l6m 3a4",
    "addr:street":"Heritage Way",
    "iso:country":"CA",
    "sg:address":"1784 Heritage Way",
    "sg:city":"Oakville",
    "sg:classifiers":[
        {
            "category":"Professional",
            "subcategory":"Lawyer & Legal Services",
            "type":"Services"
        }
    ],
    "sg:phone":"+1 905 469 9795",
    "sg:postcode":"L6M 3A4",
    "sg:province":"ON",
    "sg:tags":[
        "attorney"
    ],
    "wof:name":"Grieves, W Hedley",
    "wof:placetype":"venue"
},
  "geometry": {"coordinates":[-79.73667907710001,43.4302139282],"type":"Point"}
}