{
  "type": "Feature",
  "properties": {
    "addr:full":"1799 Kilborn Ave Ottawa ON K1H 6N1",
    "addr:housenumber":"1799",
    "addr:postcode":"k1h 6n1",
    "addr:street":"Kilborn Ave",
    "iso:country":"CA",
    "sg:address":"1799 Kilborn Ave",
    "sg:city":"Ottawa",
    "sg:classifiers":[
        {
            "category":"Personal",
            "subcategory":"Beauty Salon",
            "type":"Services"
        }
    ],
    "sg:phone":"+1 613 737 7050",
    "sg:postcode":"K1H 6N1",
    "sg:province":"ON",
    "wof:name":"Alfonso Hair Creation",
    "wof:placetype":"venue"
},
  "geometry": {"coordinates":[-75.6453094482,45.3879852295],"type":"Point"}
}