{
  "type": "Feature",
  "properties": {
    "addr:full":"Redditt Rd Kenora ON P9N 3W7",
    "addr:postcode":"p9n 3w7",
    "addr:street":"Redditt Rd",
    "iso:country":"CA",
    "sg:address":"Redditt Rd",
    "sg:city":"Kenora",
    "sg:classifiers":[
        {
            "category":"Home & Garden",
            "subcategory":"Garden Supply",
            "type":"Retail Goods"
        }
    ],
    "sg:phone":"+1 807 548 1325",
    "sg:postcode":"P9N 3W7",
    "sg:province":"ON",
    "sg:tags":[
        "center"
    ],
    "wof:name":"Debbie's Greenhouse & Garden",
    "wof:placetype":"venue"
},
  "geometry": {"coordinates":[-94.4886856079,49.7835350037],"type":"Point"}
}