{
  "type": "Feature",
  "properties": {
    "addr:full":"485 Av Sainte-Anne Saint-Hyacinthe QC J2S 5G3",
    "addr:housenumber":"485",
    "addr:postcode":"j2s 5g3",
    "addr:street":"Av Sainte-Anne",
    "iso:country":"CA",
    "sg:address":"485 Av Sainte-Anne",
    "sg:city":"Saint-Hyacinthe",
    "sg:classifiers":[
        {
            "category":"Restaurant",
            "type":"Food & Drink"
        }
    ],
    "sg:phone":"+1 450 778 9915",
    "sg:postcode":"J2S 5G3",
    "sg:province":"QC",
    "wof:name":"Le Bouffon Resto-Pub Inc",
    "wof:placetype":"venue"
},
  "geometry": {"coordinates":[-72.94657100000001,45.623795],"type":"Point"}
}