{
  "type": "Feature",
  "properties": {
    "addr:full":"Saint-Philippe-DE-Neri QC G0L 4A0",
    "addr:postcode":"g0l 4a0",
    "iso:country":"CA",
    "sg:city":"Saint-Philippe-DE-Neri",
    "sg:classifiers":[
        {
            "category":"Wholesale",
            "subcategory":"Farm Supplies",
            "type":"Manufacturing & Wholesale Goods"
        }
    ],
    "sg:phone":"+1 418 498 2366",
    "sg:postcode":"G0L 4A0",
    "sg:province":"QC",
    "sg:tags":[
        "feed"
    ],
    "wof:name":"Groupe Dynaco",
    "wof:placetype":"venue"
},
  "geometry": {"coordinates":[-69.88310199999999,47.467075],"type":"Point"}
}