{
  "type": "Feature",
  "properties": {
    "addr:full":"3405 Bathurst St North York ON M6A 2C1",
    "addr:housenumber":"3405",
    "addr:postcode":"m6a 2c1",
    "addr:street":"Bathurst St",
    "iso:country":"CA",
    "sg:address":"3405 Bathurst St",
    "sg:city":"North York",
    "sg:classifiers":[
        {
            "category":"Shopping",
            "subcategory":"Clothing, Apparel, & Fashions",
            "type":"Retail Goods"
        }
    ],
    "sg:phone":"+1 416 784 5315",
    "sg:postcode":"M6A 2C1",
    "sg:province":"ON",
    "sg:tags":[
        "wig",
        "toupee",
        "hairpiece"
    ],
    "wof:name":"Paula's Hair Works",
    "wof:placetype":"venue"
},
  "geometry": {"coordinates":[-79.43132,43.726734],"type":"Point"}
}