{
  "type": "Feature",
  "properties": {
    "addr:full":"1509 9 Ave SE Calgary AB T2G 0T6",
    "addr:housenumber":"1509",
    "addr:postcode":"t2g 0t6",
    "addr:street":"9 Ave Se",
    "iso:country":"CA",
    "sg:address":"1509 9 Ave SE",
    "sg:city":"Calgary",
    "sg:classifiers":[
        {
            "category":"Autos & Motor Vehicles",
            "subcategory":"Automobile Sales",
            "type":"Retail Goods"
        }
    ],
    "sg:phone":"+1 403 262 9683",
    "sg:postcode":"T2G 0T6",
    "sg:province":"AB",
    "sg:tags":[
        "car",
        "dealer"
    ],
    "wof:name":"Double L Motors Ltd",
    "wof:placetype":"venue"
},
  "geometry": {"coordinates":[-114.028503,51.038822],"type":"Point"}
}