{
  "type": "Feature",
  "properties": {
    "addr:full":"Disraeli QC G0N 1E0",
    "addr:postcode":"g0n 1e0",
    "addr:street":"Disraeli",
    "iso:country":"CA",
    "sg:city":"Disraeli",
    "sg:classifiers":[
        {
            "category":"Building & Trades",
            "subcategory":"Construction",
            "type":"Services"
        }
    ],
    "sg:phone":"+1 418 449 2667",
    "sg:postcode":"G0N 1E0",
    "sg:province":"QC",
    "sg:tags":[
        "boring",
        "demolition",
        "drilling",
        "contractor"
    ],
    "wof:name":"Forages Frontenac Inc",
    "wof:placetype":"venue"
},
  "geometry": {"coordinates":[-71.351952,45.904758],"type":"Point"}
}