{
  "type": "Feature",
  "properties": {
    "addr:full":"375 Rue Saint-Thomas Joliette QC J6E 3P9",
    "addr:housenumber":"375",
    "addr:postcode":"j6e 3p9",
    "addr:street":"Rue Saint-Thomas",
    "iso:country":"CA",
    "sg:address":"375 Rue Saint-Thomas",
    "sg:city":"Joliette",
    "sg:classifiers":[
        {
            "category":"Organizations",
            "subcategory":"Professional Association",
            "type":"Services"
        }
    ],
    "sg:phone":"+1 450 759 6000",
    "sg:postcode":"J6E 3P9",
    "sg:province":"QC",
    "wof:name":"Alcooliques Anonymes",
    "wof:placetype":"venue"
},
  "geometry": {"coordinates":[-73.43324279789999,46.0232696533],"type":"Point"}
}