{
  "type": "Feature",
  "properties": {
    "iso:country":"CA",
    "sg:city":"Dollard-Des-Ormeaux",
    "sg:classifiers":[
        {
            "category":"Health Services",
            "subcategory":"Doctor",
            "type":"Services"
        }
    ],
    "sg:phone":"+1 514 685 3368",
    "sg:postcode":"H8Y 3C7",
    "sg:province":"QC",
    "sg:tags":[
        "dentist"
    ],
    "wof:name":"Trinh, Caroline DDS",
    "wof:placetype":"venue"
},
  "geometry": {"coordinates":[-73.81848144529999,45.5049324036],"type":"Point"}
}