{
  "type": "Feature",
  "properties": {
    "addr:full":"Newmarket ON L3Y 7B8",
    "addr:postcode":"l3y 7b8",
    "iso:country":"CA",
    "sg:city":"Newmarket",
    "sg:classifiers":[
        {
            "category":"Social Services",
            "subcategory":"Child Care",
            "type":"Services"
        }
    ],
    "sg:phone":"+1 905 853 1074",
    "sg:postcode":"L3Y 7B8",
    "sg:province":"ON",
    "wof:name":"Leslie St Day Care Ctr",
    "wof:placetype":"venue"
},
  "geometry": {"coordinates":[-79.4316864014,44.0767364502],"type":"Point"}
}