{
  "type": "Feature",
  "properties": {
    "addr:full":"1902 1 Ave Wainwright AB T9W 1L7",
    "addr:housenumber":"1902",
    "addr:postcode":"t9w 1l7",
    "addr:street":"1 Ave",
    "iso:country":"CA",
    "sg:address":"1902 1 Ave",
    "sg:city":"Wainwright",
    "sg:classifiers":[
        {
            "category":"Mining & Drilling",
            "type":"Manufacturing & Wholesale Goods"
        }
    ],
    "sg:phone":"+1 780 842 6036",
    "sg:postcode":"T9W 1L7",
    "sg:province":"AB",
    "sg:tags":[
        "field",
        "oil"
    ],
    "wof:name":"Dowell Schlumberger Canada Inc",
    "wof:placetype":"venue"
},
  "geometry": {"coordinates":[-110.838562,52.828876],"type":"Point"}
}