{
  "type": "Feature",
  "properties": {
    "addr:full":"638 Manawagonish Rd Saint John NB E2M 3W5",
    "addr:housenumber":"638",
    "addr:postcode":"e2m 3w5",
    "addr:street":"Manawagonish Rd",
    "iso:country":"CA",
    "sg:address":"638 Manawagonish Rd",
    "sg:city":"Saint John",
    "sg:classifiers":[
        {
            "category":"Shopping",
            "subcategory":"Jewelry",
            "type":"Retail Goods"
        }
    ],
    "sg:phone":"+1 506 672 8318",
    "sg:postcode":"E2M 3W5",
    "sg:province":"NB",
    "sg:tags":[
        "jeweler"
    ],
    "wof:name":"Hamm Jewellers Ltd",
    "wof:placetype":"venue"
},
  "geometry": {"coordinates":[-66.100730896,45.256729126],"type":"Point"}
}