{
  "type": "Feature",
  "properties": {
    "addr:full":"542 Boul Pabos Pabos QC G0C 2H0",
    "addr:housenumber":"542",
    "addr:postcode":"g0c 2h0",
    "addr:street":"Boul Pabos Pabos",
    "iso:country":"CA",
    "sg:address":"542 Boul Pabos",
    "sg:city":"Pabos",
    "sg:classifiers":[
        {
            "category":"Personal",
            "subcategory":"Beauty Salon",
            "type":"Services"
        }
    ],
    "sg:phone":"+1 418 689 6555",
    "sg:postcode":"G0C 2H0",
    "sg:province":"QC",
    "wof:name":"Salon Celine Roy",
    "wof:placetype":"venue"
},
  "geometry": {"coordinates":[-64.592392,48.370327],"type":"Point"}
}