{
  "type": "Feature",
  "properties": {
    "iso:country":"CA",
    "sg:address":"310 St Anne's Rd",
    "sg:city":"Winnipeg",
    "sg:classifiers":[
        {
            "category":"Food & Beverages",
            "subcategory":"Specialty",
            "type":"Retail Goods"
        }
    ],
    "sg:phone":"+1 204 253 7696",
    "sg:postcode":"R2M 4Z5",
    "sg:province":"MB",
    "sg:tags":[
        "water",
        "company",
        "health",
        "diet"
    ],
    "wof:name":"World of Water Intl Ltd",
    "wof:placetype":"venue"
},
  "geometry": {"coordinates":[-97.101257,49.851376],"type":"Point"}
}