{
  "type": "Feature",
  "properties": {
    "addr:full":"8081 River Rd Delta BC V4G 1B4",
    "addr:housenumber":"8081",
    "addr:postcode":"v4g 1b4",
    "addr:street":"River Rd",
    "iso:country":"CA",
    "sg:address":"8081 River Rd",
    "sg:city":"Delta",
    "sg:classifiers":[
        {
            "category":"Building & Trades",
            "subcategory":"Construction",
            "type":"Services"
        }
    ],
    "sg:phone":"+1 604 940 8184",
    "sg:postcode":"V4G 1B4",
    "sg:province":"BC",
    "sg:tags":[
        "designer",
        "marine",
        "contractor"
    ],
    "wof:name":"Delta Tug & Barge Ltd",
    "wof:placetype":"venue"
},
  "geometry": {"coordinates":[-122.998718262,49.1483192444],"type":"Point"}
}