{
  "type": "Feature",
  "properties": {
    "addr:full":"3772 St. Catherines St Vancouver BC V5V 4L4",
    "addr:housenumber":"3772",
    "addr:postcode":"v5v 4l4",
    "addr:street":"St. Catherines St",
    "iso:country":"CA",
    "sg:address":"3772 St. Catherines St",
    "sg:city":"Vancouver",
    "sg:classifiers":[
        {
            "category":"Freight",
            "type":"Transportation"
        }
    ],
    "sg:phone":"+1 604 876 8413",
    "sg:postcode":"V5V 4L4",
    "sg:province":"BC",
    "sg:tags":[
        "trucking"
    ],
    "wof:name":"Steven's Trucking Ltd",
    "wof:placetype":"venue"
},
  "geometry": {"coordinates":[-123.085442,49.251289],"type":"Point"}
}