{
  "type": "Feature",
  "properties": {
    "addr:full":"575 28 St SE # 27 Calgary AB T2A 6X1",
    "addr:housenumber":"575 28",
    "addr:postcode":"t2a 6x1",
    "addr:street":"St Se # 27",
    "iso:country":"CA",
    "sg:address":"575 28 St SE # 27",
    "sg:city":"Calgary",
    "sg:classifiers":[
        {
            "category":"Restaurant",
            "type":"Food & Drink"
        }
    ],
    "sg:phone":"+1 403 508 0220",
    "sg:postcode":"T2A 6X1",
    "sg:province":"AB",
    "sg:tags":[
        "pizza"
    ],
    "wof:name":"Vern's Pizza CO Ltd",
    "wof:placetype":"venue"
},
  "geometry": {"coordinates":[-113.99007400000001,51.047993],"type":"Point"}
}