{
  "type": "Feature",
  "properties": {
    "addr:full":"370 West St S Orillia ON L3V 5G8",
    "addr:housenumber":"370",
    "addr:postcode":"l3v 5g8",
    "addr:street":"West St S",
    "iso:country":"CA",
    "sg:address":"370 West St S",
    "sg:city":"Orillia",
    "sg:classifiers":[
        {
            "category":"Manufacturing",
            "subcategory":"Tools & Machinery",
            "type":"Manufacturing & Wholesale Goods"
        }
    ],
    "sg:phone":"+1 705 326 6246",
    "sg:postcode":"L3V 5G8",
    "sg:province":"ON",
    "sg:tags":[
        "pattern",
        "maker"
    ],
    "wof:name":"J W Todd Patterns & Models Ltd",
    "wof:placetype":"venue"
},
  "geometry": {"coordinates":[-79.4120788574,44.599445343],"type":"Point"}
}