{
  "type": "Feature",
  "properties": {
    "addr:full":"1368 Boul Du Royaume O Chicoutimi QC G7H 5B1",
    "addr:housenumber":"1368",
    "addr:postcode":"g7h 5b1",
    "addr:street":"Boul Du Royaume O",
    "iso:country":"CA",
    "sg:address":"1368 Boul Du Royaume O",
    "sg:city":"Chicoutimi",
    "sg:classifiers":[
        {
            "category":"Autos & Motor Vehicles",
            "subcategory":"Auto Supplies",
            "type":"Retail Goods"
        }
    ],
    "sg:phone":"+1 418 696 3330",
    "sg:postcode":"G7H 5B1",
    "sg:province":"QC",
    "sg:tags":[
        "automobile",
        "parts"
    ],
    "wof:name":"Du-So Pieces D'Auto",
    "wof:placetype":"venue"
},
  "geometry": {"coordinates":[-71.11581420900001,48.3875160217],"type":"Point"}
}