{
  "type": "Feature",
  "properties": {
    "addr:full":"1851 Realm Rd Armstrong BC V0E 1B2",
    "addr:housenumber":"1851",
    "addr:postcode":"v0e 1b2",
    "addr:street":"Realm Rd",
    "iso:country":"CA",
    "sg:address":"1851 Realm Rd",
    "sg:city":"Armstrong",
    "sg:classifiers":[
        {
            "category":"Wholesale",
            "subcategory":"Sporting Goods",
            "type":"Manufacturing & Wholesale Goods"
        }
    ],
    "sg:phone":"+1 250 546 9355",
    "sg:postcode":"V0E 1B2",
    "sg:province":"BC",
    "sg:tags":[
        "equipment",
        "billiard",
        "supply"
    ],
    "wof:name":"Southern Music Ltd",
    "wof:placetype":"venue"
},
  "geometry": {"coordinates":[-119.183701,50.441818],"type":"Point"}
}