{
  "type": "Feature",
  "properties": {
    "addr:full":"2095 Wharncliffe Rd S London ON N6P 1K9",
    "addr:housenumber":"2095",
    "addr:postcode":"n6p 1k9",
    "addr:street":"Wharncliffe Rd",
    "iso:country":"CA",
    "sg:address":"2095 Wharncliffe Rd S",
    "sg:city":"London",
    "sg:classifiers":[
        {
            "category":"Government",
            "subcategory":"Office",
            "type":"Public Place"
        }
    ],
    "sg:phone":"+1 519 652 3222",
    "sg:postcode":"N6P 1K9",
    "sg:province":"ON",
    "sg:tags":[
        "license"
    ],
    "wof:name":"Lambeth Motor Vehicle Permit",
    "wof:placetype":"venue"
},
  "geometry": {"coordinates":[-81.285507,42.916981],"type":"Point"}
}