{
  "type": "Feature",
  "properties": {
    "addr:full":"25 8E Rue Crabtree QC J0K 1B0",
    "addr:housenumber":"25",
    "addr:postcode":"j0k 1b0",
    "addr:street":"8E Rue Crabtree",
    "iso:country":"CA",
    "sg:address":"25 8E Rue",
    "sg:city":"Crabtree",
    "sg:classifiers":[
        {
            "category":"Social Services",
            "type":"Services"
        }
    ],
    "sg:phone":"+1 450 754 3334",
    "sg:postcode":"J0K 1B0",
    "sg:province":"QC",
    "sg:tags":[
        "youth",
        "organization",
        "center"
    ],
    "wof:name":"Maison Des Jeunes DE Crabtree",
    "wof:placetype":"venue"
},
  "geometry": {"coordinates":[-73.4711532593,45.9655838013],"type":"Point"}
}