{
  "type": "Feature",
  "properties": {
    "iso:country":"CA",
    "sg:address":"5 Conc Casey",
    "sg:city":"Belle Vallee",
    "sg:classifiers":[
        {
            "category":"Building & Trades",
            "subcategory":"Landscaping Services",
            "type":"Services"
        }
    ],
    "sg:phone":"+1 705 647 7796",
    "sg:postcode":"P0J 1A0",
    "sg:province":"ON",
    "sg:tags":[
        "tree"
    ],
    "wof:name":"Ray & Son's Tree Svc",
    "wof:placetype":"venue"
},
  "geometry": {"coordinates":[-79.59014892579999,47.6531181335],"type":"Point"}
}