{
  "type": "Feature",
  "properties": {
    "addr:full":"1253 Kennedy Rd Scarborough ON M1P 2L4",
    "addr:housenumber":"1253",
    "addr:postcode":"m1p 2l4",
    "addr:street":"Kennedy Rd",
    "iso:country":"CA",
    "sg:address":"1253 Kennedy Rd",
    "sg:city":"Scarborough",
    "sg:classifiers":[
        {
            "category":"Retail",
            "subcategory":"Auto Repair",
            "type":"Services"
        }
    ],
    "sg:phone":"+1 416 285 8066",
    "sg:postcode":"M1P 2L4",
    "sg:province":"ON",
    "sg:tags":[
        "repairing",
        "automobile"
    ],
    "wof:name":"Technos Automotive Inc",
    "wof:placetype":"venue"
},
  "geometry": {"coordinates":[-79.277428,43.756672],"type":"Point"}
}