{
  "type": "Feature",
  "properties": {
    "addr:full":"235 Montee Paiement Gatineau QC J8P 6M7",
    "addr:housenumber":"235",
    "addr:postcode":"j8p 6m7",
    "addr:street":"Montee Paiement",
    "iso:country":"CA",
    "sg:address":"235 Montee Paiement",
    "sg:city":"Gatineau",
    "sg:classifiers":[
        {
            "category":"Shopping",
            "subcategory":"Stationery & Office Supplies",
            "type":"Retail Goods"
        }
    ],
    "sg:phone":"+1 819 246 9470",
    "sg:postcode":"J8P 6M7",
    "sg:province":"QC",
    "sg:tags":[
        "equipment",
        "computer",
        "dealer"
    ],
    "wof:name":"Staples Business Depot",
    "wof:placetype":"venue"
},
  "geometry": {"coordinates":[-75.674744,45.484592],"type":"Point"}
}