{
  "type": "Feature",
  "properties": {
    "addr:full":"180 Ossington Ave Toronto ON M6J 2Z7",
    "addr:housenumber":"180",
    "addr:postcode":"m6j 2z7",
    "addr:street":"Ossington Ave",
    "iso:country":"CA",
    "sg:address":"180 Ossington Ave",
    "sg:city":"Toronto",
    "sg:classifiers":[
        {
            "category":"Retail",
            "subcategory":"Self-service Laundry",
            "type":"Services"
        }
    ],
    "sg:phone":"+1 416 537 6002",
    "sg:postcode":"M6J 2Z7",
    "sg:province":"ON",
    "wof:name":"Hollywood Coin Laundry",
    "wof:placetype":"venue"
},
  "geometry": {"coordinates":[-79.42040252690001,43.6482467651],"type":"Point"}
}