{
  "type": "Feature",
  "properties": {
    "addr:full":"820 Rang DE LA Montagne N Abbotsford QC J0E 1A0",
    "addr:housenumber":"820",
    "addr:postcode":"j0e 1a0",
    "addr:street":"Rang De La Montagne N",
    "iso:country":"CA",
    "sg:address":"820 Rang DE LA Montagne N",
    "sg:city":"Abbotsford",
    "sg:classifiers":[
        {
            "category":"Professional",
            "subcategory":"Management & Consulting",
            "type":"Services"
        }
    ],
    "sg:phone":"+1 450 379 9835",
    "sg:postcode":"J0E 1A0",
    "sg:province":"QC",
    "sg:tags":[
        "agricultural",
        "consultant"
    ],
    "wof:name":"Consultants Gt & Assoc Inc",
    "wof:placetype":"venue"
},
  "geometry": {"coordinates":[-72.889664,45.453671],"type":"Point"}
}