{
  "type": "Feature",
  "properties": {
    "addr:full":"2360 Douglas Rd Burnaby BC V5C 5B2",
    "addr:housenumber":"2360",
    "addr:postcode":"v5c 5b2",
    "addr:street":"Douglas Rd",
    "iso:country":"CA",
    "sg:address":"2360 Douglas Rd",
    "sg:city":"Burnaby",
    "sg:classifiers":[
        {
            "category":"Building & Trades",
            "subcategory":"Electrical",
            "type":"Services"
        }
    ],
    "sg:phone":"+1 604 299 4341",
    "sg:postcode":"V5C 5B2",
    "sg:province":"BC",
    "sg:tags":[
        "electric",
        "contractor"
    ],
    "wof:name":"Elworthy Electrical Svc Ltd",
    "wof:placetype":"venue"
},
  "geometry": {"coordinates":[-122.987381,49.263138],"type":"Point"}
}