{
  "type": "Feature",
  "properties": {
    "addr:full":"4098 Rue Sainte-Catherine O Westmount QC H3Z 1P2",
    "addr:housenumber":"4098",
    "addr:postcode":"h3z 1p2",
    "addr:street":"Rue Sainte-Catherine O",
    "iso:country":"CA",
    "sg:address":"4098 Rue Sainte-Catherine O",
    "sg:city":"Westmount",
    "sg:classifiers":[
        {
            "category":"Professional",
            "subcategory":"Management & Consulting",
            "type":"Services"
        }
    ],
    "sg:phone":"+1 514 933 9909",
    "sg:postcode":"H3Z 1P2",
    "sg:province":"QC",
    "sg:tags":[
        "employee",
        "consultant",
        "benefit"
    ],
    "wof:name":"J S Hayes & Assoc",
    "wof:placetype":"venue"
},
  "geometry": {"coordinates":[-73.58628845210001,45.4875946045],"type":"Point"}
}