{
  "type": "Feature",
  "properties": {
    "addr:full":"215 Ryding Ave Toronto ON M6N 1H6",
    "addr:housenumber":"215",
    "addr:postcode":"m6n 1h6",
    "addr:street":"Ryding Ave",
    "iso:country":"CA",
    "sg:address":"215 Ryding Ave",
    "sg:city":"Toronto",
    "sg:classifiers":[
        {
            "category":"Arena",
            "subcategory":"Sports Club",
            "type":"Entertainment"
        }
    ],
    "sg:phone":"+1 416 762 6715",
    "sg:postcode":"M6N 1H6",
    "sg:province":"ON",
    "sg:tags":[
        "athletic",
        "fields",
        "stadium"
    ],
    "wof:name":"George Bell House Hockey Assoc",
    "wof:placetype":"venue"
},
  "geometry": {"coordinates":[-79.4779129028,43.6689529419],"type":"Point"}
}