{
  "type": "Feature",
  "properties": {
    "addr:full":"382 Main St E Hawkesbury ON K6A 1A9",
    "addr:housenumber":"382",
    "addr:postcode":"k6a 1a9",
    "addr:street":"Main St E",
    "iso:country":"CA",
    "sg:address":"382 Main St E",
    "sg:city":"Hawkesbury",
    "sg:classifiers":[
        {
            "category":"Personal",
            "subcategory":"Tanning Parlor",
            "type":"Services"
        }
    ],
    "sg:phone":"+1 613 632 6125",
    "sg:postcode":"K6A 1A9",
    "sg:province":"ON",
    "sg:tags":[
        "salon"
    ],
    "wof:name":"Magic Tan",
    "wof:placetype":"venue"
},
  "geometry": {"coordinates":[-74.60546100000001,45.61034],"type":"Point"}
}