{
  "type": "Feature",
  "properties": {
    "addr:full":"111 4th St E Spiritwood SK S0J 2M0",
    "addr:housenumber":"111",
    "addr:postcode":"s0j 2m0",
    "addr:street":"4Th St E Spiritwood",
    "iso:country":"CA",
    "sg:address":"111 4th St E",
    "sg:city":"Spiritwood",
    "sg:classifiers":[
        {
            "category":"Government",
            "subcategory":"Office",
            "type":"Public Place"
        }
    ],
    "sg:phone":"+1 306 883 8510",
    "sg:postcode":"S0J 2M0",
    "sg:province":"SK",
    "wof:name":"Sask Highways & Transportation",
    "wof:placetype":"venue"
},
  "geometry": {"coordinates":[-107.512619,53.365131],"type":"Point"}
}