{
  "type": "Feature",
  "properties": {
    "addr:full":"209 Sackville Dr Lower Sackville NS B4C 2R5",
    "addr:housenumber":"209",
    "addr:postcode":"b4c 2r5",
    "addr:street":"Sackville Dr",
    "iso:country":"CA",
    "sg:address":"209 Sackville Dr",
    "sg:city":"Lower Sackville",
    "sg:classifiers":[
        {
            "category":"Shopping",
            "subcategory":"Bicycles & Sporting Goods",
            "type":"Retail Goods"
        }
    ],
    "sg:phone":"+1 902 865 9033",
    "sg:postcode":"B4C 2R5",
    "sg:province":"NS",
    "wof:name":"Sportwheels Ltd",
    "wof:placetype":"venue"
},
  "geometry": {"coordinates":[-63.668777,44.758785],"type":"Point"}
}