{
  "type": "Feature",
  "properties": {
    "addr:full":"1755 Lasalle Blvd Sudbury ON P3A 1Z8",
    "addr:housenumber":"1755",
    "addr:postcode":"p3a 1z8",
    "addr:street":"Lasalle Blvd",
    "iso:country":"CA",
    "sg:address":"1755 Lasalle Blvd",
    "sg:city":"Sudbury",
    "sg:classifiers":[
        {
            "category":"Shopping",
            "subcategory":"Discount & Variety Stores",
            "type":"Retail Goods"
        }
    ],
    "sg:phone":"+1 705 560 1811",
    "sg:postcode":"P3A 1Z8",
    "sg:province":"ON",
    "wof:name":"Pinto Foods",
    "wof:placetype":"venue"
},
  "geometry": {"coordinates":[-80.9337387085,46.5219573975],"type":"Point"}
}