{
  "type": "Feature",
  "properties": {
    "iso:country":"CA",
    "sg:address":"910 14E Av",
    "sg:city":"LA Guadeloupe",
    "sg:classifiers":[
        {
            "category":"Retail",
            "subcategory":"Auto Repair",
            "type":"Services"
        }
    ],
    "sg:phone":"+1 418 459 3219",
    "sg:postcode":"G0M 1G0",
    "sg:province":"QC",
    "sg:tags":[
        "automobile",
        "parts",
        "painting"
    ],
    "wof:name":"Garage Gbl Inc",
    "wof:placetype":"venue"
},
  "geometry": {"coordinates":[-70.9450378418,45.9740905762],"type":"Point"}
}