{
  "type": "Feature",
  "properties": {
    "addr:full":"591 Knowlton Rd Knowlton QC J0E 1V0",
    "addr:housenumber":"591",
    "addr:postcode":"j0e 1v0",
    "addr:street":"Knowlton Rd",
    "iso:country":"CA",
    "sg:address":"591 Knowlton Rd",
    "sg:city":"Knowlton",
    "sg:classifiers":[
        {
            "category":"Wholesale",
            "subcategory":"Hardware",
            "type":"Manufacturing & Wholesale Goods"
        }
    ],
    "sg:phone":"+1 450 243 5161",
    "sg:postcode":"J0E 1V0",
    "sg:province":"QC",
    "sg:tags":[
        "coal",
        "stove"
    ],
    "wof:name":"Stove & Garden",
    "wof:placetype":"venue"
},
  "geometry": {"coordinates":[-72.5365524292,45.2128601074],"type":"Point"}
}