{
  "type": "Feature",
  "properties": {
    "addr:full":"168 Boyne Treherne MB R0G 2V0",
    "addr:housenumber":"168",
    "addr:postcode":"r0g 2v0",
    "addr:street":"Boyne Treherne",
    "iso:country":"CA",
    "sg:address":"168 Boyne",
    "sg:city":"Treherne",
    "sg:classifiers":[
        {
            "category":"Organizations",
            "subcategory":"Religious Organization",
            "type":"Services"
        }
    ],
    "sg:phone":"+1 204 723 2224",
    "sg:postcode":"R0G 2V0",
    "sg:province":"MB",
    "sg:tags":[
        "church"
    ],
    "wof:name":"Treherne United Church",
    "wof:placetype":"venue"
},
  "geometry": {"coordinates":[-98.694855,49.627861],"type":"Point"}
}