{
  "type": "Feature",
  "properties": {
    "addr:full":"420 Rue Betty Saint-Bernard QC G0S 2G0",
    "addr:housenumber":"420",
    "addr:postcode":"g0s 2g0",
    "addr:street":"Rue Betty",
    "iso:country":"CA",
    "sg:address":"420 Rue Betty",
    "sg:city":"Saint-Bernard",
    "sg:classifiers":[
        {
            "category":"Personal",
            "subcategory":"Beauty Salon",
            "type":"Services"
        }
    ],
    "sg:phone":"+1 418 475 6826",
    "sg:postcode":"G0S 2G0",
    "sg:province":"QC",
    "wof:name":"Salon Diane",
    "wof:placetype":"venue"
},
  "geometry": {"coordinates":[-71.1378860474,46.4989814758],"type":"Point"}
}