{
  "type": "Feature",
  "properties": {
    "addr:full":"98 Rue Maple RR 1 Grenville QC J0V 1J0",
    "addr:housenumber":"98;1",
    "addr:postcode":"j0v 1j0",
    "addr:street":"Rue Maple Rr",
    "iso:country":"CA",
    "sg:address":"98 Rue Maple RR 1",
    "sg:city":"Grenville",
    "sg:classifiers":[
        {
            "category":"Professional",
            "subcategory":"Lawyer & Legal Services",
            "type":"Services"
        }
    ],
    "sg:phone":"+1 819 242 9533",
    "sg:postcode":"J0V 1J0",
    "sg:province":"QC",
    "sg:tags":[
        "attorney"
    ],
    "wof:name":"Arnold, James E",
    "wof:placetype":"venue"
},
  "geometry": {"coordinates":[-74.589973,45.628033],"type":"Point"}
}