{
  "type": "Feature",
  "properties": {
    "addr:full":"2178 Rue Sainte-Catherine O Montreal QC H3H 1M7",
    "addr:housenumber":"2178",
    "addr:postcode":"h3h 1m7",
    "addr:street":"Rue Sainte-Catherine O",
    "iso:country":"CA",
    "sg:address":"2178 Rue Sainte-Catherine O",
    "sg:city":"Montreal",
    "sg:classifiers":[
        {
            "category":"Retail",
            "subcategory":"Portrait Studio",
            "type":"Services"
        }
    ],
    "sg:phone":"+1 514 846 0221",
    "sg:postcode":"H3H 1M7",
    "sg:province":"QC",
    "sg:tags":[
        "photo",
        "finishing"
    ],
    "wof:name":"Photo Shop",
    "wof:placetype":"venue"
},
  "geometry": {"coordinates":[-73.5492401123,45.5257377625],"type":"Point"}
}