{
  "type": "Feature",
  "properties": {
    "addr:full":"531 33 Ave NE Calgary AB T2E 2J2",
    "addr:housenumber":"531",
    "addr:postcode":"t2e 2j2",
    "addr:street":"33 Ave Ne",
    "iso:country":"CA",
    "sg:address":"531 33 Ave NE",
    "sg:city":"Calgary",
    "sg:classifiers":[
        {
            "category":"Professional",
            "subcategory":"Computer Services",
            "type":"Services"
        }
    ],
    "sg:phone":"+1 403 313 3323",
    "sg:postcode":"T2E 2J2",
    "sg:province":"AB",
    "sg:tags":[
        "internet"
    ],
    "wof:name":"Bisonlynx Technologies Inc",
    "wof:placetype":"venue"
},
  "geometry": {"coordinates":[-114.052085877,51.0821456909],"type":"Point"}
}