{
  "type": "Feature",
  "properties": {
    "addr:full":"Newmarket ON L3Y 8E1",
    "addr:postcode":"l3y 8e1",
    "iso:country":"CA",
    "sg:city":"Newmarket",
    "sg:classifiers":[
        {
            "category":"Recreation",
            "type":"Entertainment"
        }
    ],
    "sg:phone":"+1 905 895 4194",
    "sg:postcode":"L3Y 8E1",
    "sg:province":"ON",
    "sg:tags":[
        "instruction",
        "gymnastic"
    ],
    "wof:name":"Shenderey Gymnastic Ctr",
    "wof:placetype":"venue"
},
  "geometry": {"coordinates":[-79.42965700000001,44.05772],"type":"Point"}
}