{
  "type": "Feature",
  "properties": {
    "iso:country":"CA",
    "sg:address":"261 Montee Des Pionniers",
    "sg:city":"Lachenaie",
    "sg:classifiers":[
        {
            "category":"Restaurant",
            "type":"Food & Drink"
        }
    ],
    "sg:phone":"+1 450 654 9274",
    "sg:postcode":"J6V 1H4",
    "sg:province":"QC",
    "wof:name":"Restaurant Vulcano Inc",
    "wof:placetype":"venue"
},
  "geometry": {"coordinates":[-73.51243591310001,45.7110671997],"type":"Point"}
}