{
  "type": "Feature",
  "properties": {
    "addr:full":"668 Davie St Vancouver BC V6B 2G5",
    "addr:housenumber":"668",
    "addr:postcode":"bc v6b 2g5",
    "addr:street":"Davie St",
    "iso:country":"CA",
    "sg:address":"668 Davie St",
    "sg:city":"Vancouver",
    "sg:classifiers":[
        {
            "category":"Restaurant",
            "type":"Food & Drink"
        }
    ],
    "sg:phone":"+1 604 681 6672",
    "sg:postcode":"V6B 2G5",
    "sg:province":"BC",
    "sg:tags":[
        "parlor",
        "ice",
        "cream"
    ],
    "wof:name":"Persian Greenhouse",
    "wof:placetype":"venue"
},
  "geometry": {"coordinates":[-123.12603,49.276817],"type":"Point"}
}