{
  "type": "Feature",
  "properties": {
    "iso:country":"CA",
    "sg:address":"17575 Boul Becancour",
    "sg:city":"Becancour",
    "sg:classifiers":[
        {
            "category":"Health Services",
            "subcategory":"Health Practitioner",
            "type":"Services"
        }
    ],
    "sg:phone":"+1 819 233 4664",
    "sg:postcode":"G9H 1A5",
    "sg:province":"QC",
    "sg:tags":[
        "physiotherapist",
        "clinic"
    ],
    "wof:name":"Clinique DE Physiotherapie",
    "wof:placetype":"venue"
},
  "geometry": {"coordinates":[-72.53994,46.301781],"type":"Point"}
}