{
  "type": "Feature",
  "properties": {
    "addr:full":"1020 Denison St Markham ON L3R 3W5",
    "addr:housenumber":"1020",
    "addr:postcode":"l3r 3w5",
    "addr:street":"Denison St",
    "iso:country":"CA",
    "sg:address":"1020 Denison St",
    "sg:city":"Markham",
    "sg:classifiers":[
        {
            "category":"Building & Trades",
            "subcategory":"Construction",
            "type":"Services"
        }
    ],
    "sg:phone":"+1 905 940 9324",
    "sg:postcode":"L3R 3W5",
    "sg:province":"ON",
    "sg:tags":[
        "railroad",
        "contractor"
    ],
    "wof:name":"Applied Rail Research Tech Inc",
    "wof:placetype":"venue"
},
  "geometry": {"coordinates":[-79.3292388916,43.8269844055],"type":"Point"}
}