{
  "type": "Feature",
  "properties": {
    "addr:full":"1372 Henderson Hwy Winnipeg MB R2G 1M8",
    "addr:housenumber":"1372",
    "addr:postcode":"r2g 1m8",
    "addr:street":"Henderson Hwy",
    "iso:country":"CA",
    "sg:address":"1372 Henderson Hwy",
    "sg:city":"Winnipeg",
    "sg:classifiers":[
        {
            "category":"Retail",
            "subcategory":"Auto Repair",
            "type":"Services"
        }
    ],
    "sg:phone":"+1 204 338 1551",
    "sg:postcode":"R2G 1M8",
    "sg:province":"MB",
    "sg:tags":[
        "body",
        "automobile",
        "painting"
    ],
    "wof:name":"North Kildonan Carstar Cllsn",
    "wof:placetype":"venue"
},
  "geometry": {"coordinates":[-97.0877,49.944008],"type":"Point"}
}