{
  "type": "Feature",
  "properties": {
    "addr:full":"45700 Railway Ave Chilliwack BC V2P 1L3",
    "addr:housenumber":"45700",
    "addr:postcode":"v2p 1l3",
    "addr:street":"Railway Ave",
    "iso:country":"CA",
    "sg:address":"45700 Railway Ave",
    "sg:city":"Chilliwack",
    "sg:classifiers":[
        {
            "category":"Retail",
            "subcategory":"Auto Repair",
            "type":"Services"
        }
    ],
    "sg:phone":"+1 604 792 0674",
    "sg:postcode":"V2P 1L3",
    "sg:province":"BC",
    "sg:tags":[
        "repairing",
        "automobile",
        "muffler",
        "exhaust"
    ],
    "wof:name":"Jesperson's Brake & Muffler",
    "wof:placetype":"venue"
},
  "geometry": {"coordinates":[-121.958794,49.163002],"type":"Point"}
}