{
  "type": "Feature",
  "properties": {
    "addr:full":"Scarborough ON M1V 5A4",
    "addr:postcode":"m1v 5a4",
    "iso:country":"CA",
    "sg:city":"Scarborough",
    "sg:classifiers":[
        {
            "category":"Manufacturing",
            "subcategory":"Electronics",
            "type":"Manufacturing & Wholesale Goods"
        }
    ],
    "sg:phone":"+1 416 754 1414",
    "sg:postcode":"M1V 5A4",
    "sg:province":"ON",
    "sg:tags":[
        "sound",
        "equipment",
        "system"
    ],
    "wof:name":"Virgin Acoustics",
    "wof:placetype":"venue"
},
  "geometry": {"coordinates":[-79.25174699999999,43.82365],"type":"Point"}
}