{
  "type": "Feature",
  "properties": {
    "addr:full":"261 5th Concession Rd Langton ON N0E 1G0",
    "addr:housenumber":"261",
    "addr:postcode":"n0e 1g0",
    "addr:street":"5Th Concession Rd",
    "iso:country":"CA",
    "sg:address":"261 5th Concession Rd",
    "sg:city":"Langton",
    "sg:classifiers":[
        {
            "category":"Food & Beverages",
            "subcategory":"Specialty",
            "type":"Retail Goods"
        }
    ],
    "sg:phone":"+1 519 875 1555",
    "sg:postcode":"N0E 1G0",
    "sg:province":"ON",
    "sg:tags":[
        "poultry"
    ],
    "wof:name":"Cold Springs Farm",
    "wof:placetype":"venue"
},
  "geometry": {"coordinates":[-80.577309,42.741508],"type":"Point"}
}