{
  "type": "Feature",
  "properties": {
    "addr:full":"185 Rue Saint-Ignace Montmagny QC G5V 1R7",
    "addr:housenumber":"185",
    "addr:postcode":"g5v 1r7",
    "addr:street":"Rue Saint-Ignace",
    "iso:country":"CA",
    "sg:address":"185 Rue Saint-Ignace",
    "sg:city":"Montmagny",
    "sg:classifiers":[
        {
            "category":"Wholesale",
            "subcategory":"Meat",
            "type":"Manufacturing & Wholesale Goods"
        }
    ],
    "sg:phone":"+1 418 248 3636",
    "sg:postcode":"G5V 1R7",
    "sg:province":"QC",
    "sg:tags":[
        "packer",
        "butchering"
    ],
    "wof:name":"Boucherie Edgar Gaudreau Enr",
    "wof:placetype":"venue"
},
  "geometry": {"coordinates":[-70.550613,46.980255],"type":"Point"}
}