{
  "type": "Feature",
  "properties": {
    "addr:full":"870 Bathurst St Toronto ON M5R 3G3",
    "addr:housenumber":"870",
    "addr:postcode":"m5r 3g3",
    "addr:street":"Bathurst St",
    "iso:country":"CA",
    "sg:address":"870 Bathurst St",
    "sg:city":"Toronto",
    "sg:classifiers":[
        {
            "category":"Shopping",
            "subcategory":"Gifts & Souvenirs",
            "type":"Retail Goods"
        }
    ],
    "sg:phone":"+1 416 534 9889",
    "sg:postcode":"M5R 3G3",
    "sg:province":"ON",
    "sg:tags":[
        "shop"
    ],
    "wof:name":"Simcoe Shoppe",
    "wof:placetype":"venue"
},
  "geometry": {"coordinates":[-79.4121627808,43.6670646667],"type":"Point"}
}