{
  "type": "Feature",
  "properties": {
    "addr:full":"975 Rue Saint-Prosper Trois-Rivieres QC G9A 3V7",
    "addr:housenumber":"975",
    "addr:postcode":"g9a 3v7",
    "addr:street":"Rue Saint-Prosper Trois-Rivieres",
    "iso:country":"CA",
    "sg:address":"975 Rue Saint-Prosper",
    "sg:city":"Trois-Rivieres",
    "sg:classifiers":[
        {
            "category":"Organizations",
            "subcategory":"Professional Association",
            "type":"Services"
        }
    ],
    "sg:phone":"+1 819 373 1232",
    "sg:postcode":"G9A 3V7",
    "sg:province":"QC",
    "sg:tags":[
        "social",
        "welfare"
    ],
    "wof:name":"Calacs",
    "wof:placetype":"venue"
},
  "geometry": {"coordinates":[-72.54483,46.346619],"type":"Point"}
}