{
  "type": "Feature",
  "properties": {
    "addr:full":"9 King St N St Jacobs ON N0B 2N0",
    "addr:housenumber":"9",
    "addr:postcode":"n0b 2n0",
    "addr:street":"King St N St",
    "iso:country":"CA",
    "sg:address":"9 King St N",
    "sg:city":"St Jacobs",
    "sg:classifiers":[
        {
            "category":"Wholesale",
            "subcategory":"Non-durable Goods",
            "type":"Manufacturing & Wholesale Goods"
        }
    ],
    "sg:phone":"+1 519 664 3320",
    "sg:postcode":"N0B 2N0",
    "sg:province":"ON",
    "sg:tags":[
        "leather"
    ],
    "wof:name":"Heritage Leather Corp",
    "wof:placetype":"venue"
},
  "geometry": {"coordinates":[-80.542198,43.50946],"type":"Point"}
}