{
  "type": "Feature",
  "properties": {
    "addr:full":"90 Pearl St Bridgewater NS B4V 2P3",
    "addr:housenumber":"90",
    "addr:postcode":"b4v 2p3",
    "addr:street":"Pearl St",
    "iso:country":"CA",
    "sg:address":"90 Pearl St",
    "sg:city":"Bridgewater",
    "sg:classifiers":[
        {
            "category":"Autos & Motor Vehicles",
            "subcategory":"Automobile Sales",
            "type":"Retail Goods"
        }
    ],
    "sg:phone":"+1 902 527 7293",
    "sg:postcode":"B4V 2P3",
    "sg:province":"NS",
    "sg:tags":[
        "car",
        "dealer"
    ],
    "wof:name":"Collicutt's Coastal Classics",
    "wof:placetype":"venue"
},
  "geometry": {"coordinates":[-64.5341796875,44.375125885],"type":"Point"}
}