{
  "type": "Feature",
  "properties": {
    "addr:full":"3835 Ritson Rd N Oshawa ON L1H 7K4",
    "addr:housenumber":"3835",
    "addr:postcode":"l1h 7k4",
    "addr:street":"Ritson Rd N",
    "iso:country":"CA",
    "sg:address":"3835 Ritson Rd N",
    "sg:city":"Oshawa",
    "sg:classifiers":[
        {
            "category":"Building & Trades",
            "subcategory":"Construction",
            "type":"Services"
        }
    ],
    "sg:phone":"+1 905 655 1052",
    "sg:postcode":"L1H 7K4",
    "sg:province":"ON",
    "sg:tags":[
        "contractor"
    ],
    "wof:name":"Redwood Construction",
    "wof:placetype":"venue"
},
  "geometry": {"coordinates":[-78.89691925050001,43.9990882874],"type":"Point"}
}