{
  "type": "Feature",
  "properties": {
    "iso:country":"CA",
    "sg:address":"73 1st St S",
    "sg:city":"Souris",
    "sg:classifiers":[
        {
            "category":"Autos & Motor Vehicles",
            "subcategory":"Auto Supplies",
            "type":"Retail Goods"
        }
    ],
    "sg:phone":"+1 204 483 3728",
    "sg:postcode":"R0K 2C0",
    "sg:province":"MB",
    "sg:tags":[
        "automobile",
        "parts"
    ],
    "wof:name":"Fergie's Farm & Auto",
    "wof:placetype":"venue"
},
  "geometry": {"coordinates":[-100.258865356,49.6208343506],"type":"Point"}
}