{
  "type": "Feature",
  "properties": {
    "addr:full":"10315 109 St NW Edmonton AB T5J 1N3",
    "addr:housenumber":"10315",
    "addr:postcode":"t5j 1n3",
    "addr:street":"109 St Nw",
    "iso:country":"CA",
    "sg:address":"10315 109 St NW",
    "sg:city":"Edmonton",
    "sg:classifiers":[
        {
            "category":"Real Estate",
            "subcategory":"Real Estate Agent",
            "type":"Services"
        }
    ],
    "sg:phone":"+1 780 425 2506",
    "sg:postcode":"T5J 1N3",
    "sg:province":"AB",
    "sg:tags":[
        "management"
    ],
    "wof:name":"Five Oaks Inc",
    "wof:placetype":"venue"
},
  "geometry": {"coordinates":[-113.508179,53.54496],"type":"Point"}
}