{
  "type": "Feature",
  "properties": {
    "iso:country":"CA",
    "sg:address":"1208 Rideau Bend Cres",
    "sg:city":"Manotick",
    "sg:classifiers":[
        {
            "category":"Professional",
            "subcategory":"Business Services",
            "type":"Services"
        }
    ],
    "sg:phone":"+1 613 692 0862",
    "sg:postcode":"K4M 1B5",
    "sg:province":"ON",
    "sg:tags":[
        "lecture",
        "bureau",
        "seminar"
    ],
    "wof:name":"Traq Consulting",
    "wof:placetype":"venue"
},
  "geometry": {"coordinates":[-75.6453170776,45.2355957031],"type":"Point"}
}