{
  "type": "Feature",
  "properties": {
    "addr:full":"1500 Power Dam Dr Cornwall ON K6H 5R6",
    "addr:housenumber":"1500",
    "addr:postcode":"k6h 5r6",
    "addr:street":"Power Dam Dr",
    "iso:country":"CA",
    "sg:address":"1500 Power Dam Dr",
    "sg:city":"Cornwall",
    "sg:classifiers":[
        {
            "category":"Health Services",
            "subcategory":"Doctor",
            "type":"Services"
        }
    ],
    "sg:phone":"+1 613 938 2990",
    "sg:postcode":"K6H 5R6",
    "sg:province":"ON",
    "sg:tags":[
        "physician",
        "surgeon"
    ],
    "wof:name":"Tombler, R D MD",
    "wof:placetype":"venue"
},
  "geometry": {"coordinates":[-74.781685,45.021694],"type":"Point"}
}