{
  "type": "Feature",
  "properties": {
    "addr:full":"9189 Nielson Rd Prince George BC V2K 5T6",
    "addr:housenumber":"9189",
    "addr:postcode":"v2k 5t6",
    "addr:street":"Nielson Rd",
    "iso:country":"CA",
    "sg:address":"9189 Nielson Rd",
    "sg:city":"Prince George",
    "sg:classifiers":[
        {
            "category":"Manufacturing",
            "subcategory":"Lumber",
            "type":"Manufacturing & Wholesale Goods"
        }
    ],
    "sg:phone":"+1 250 962 7445",
    "sg:postcode":"V2K 5T6",
    "sg:province":"BC",
    "sg:tags":[
        "company",
        "logging"
    ],
    "wof:name":"K & G Logging",
    "wof:placetype":"venue"
},
  "geometry": {"coordinates":[-122.795891,54.014797],"type":"Point"}
}