{
  "type": "Feature",
  "properties": {
    "addr:full":"1571 Warden Ave Scarborough ON M1R 2S9",
    "addr:housenumber":"1571",
    "addr:postcode":"m1r 2s9",
    "addr:street":"Warden Ave",
    "iso:country":"CA",
    "sg:address":"1571 Warden Ave",
    "sg:city":"Scarborough",
    "sg:classifiers":[
        {
            "category":"Autos & Motor Vehicles",
            "subcategory":"Automobile Sales",
            "type":"Retail Goods"
        }
    ],
    "sg:phone":"+1 416 298 6886",
    "sg:postcode":"M1R 2S9",
    "sg:province":"ON",
    "sg:tags":[
        "car",
        "dealer"
    ],
    "wof:name":"Auto Style Enterprise Inc",
    "wof:placetype":"venue"
},
  "geometry": {"coordinates":[-79.301811,43.765232],"type":"Point"}
}