{
  "type": "Feature",
  "properties": {
    "iso:country":"CA",
    "sg:address":"Hospital Rd",
    "sg:city":"Chetwynd",
    "sg:classifiers":[
        {
            "category":"Organizations",
            "subcategory":"Professional Association",
            "type":"Services"
        }
    ],
    "sg:phone":"+1 250 788 9122",
    "sg:postcode":"V0C 1J0",
    "sg:province":"BC",
    "sg:tags":[
        "club"
    ],
    "wof:name":"Chetwynd Rod & Gun Club",
    "wof:placetype":"venue"
},
  "geometry": {"coordinates":[-121.643180847,55.6952972412],"type":"Point"}
}