{
  "type": "Feature",
  "properties": {
    "iso:country":"CA",
    "sg:city":"Phelpston",
    "sg:classifiers":[
        {
            "category":"Building & Trades",
            "subcategory":"Construction",
            "type":"Services"
        }
    ],
    "sg:phone":"+1 705 726 9001",
    "sg:postcode":"L0L 2K0",
    "sg:province":"ON",
    "sg:tags":[
        "home",
        "planning",
        "design",
        "contractor"
    ],
    "wof:name":"Crown Point Homes",
    "wof:placetype":"venue"
},
  "geometry": {"coordinates":[-79.84771728520001,44.5178260803],"type":"Point"}
}