{
  "type": "Feature",
  "properties": {
    "addr:full":"478 Gardiners Rd Kingston ON K7M 7W8",
    "addr:housenumber":"478",
    "addr:postcode":"k7m 7w8",
    "addr:street":"Gardiners Rd",
    "iso:country":"CA",
    "sg:address":"478 Gardiners Rd",
    "sg:city":"Kingston",
    "sg:classifiers":[
        {
            "category":"Shopping",
            "subcategory":"Computers & Home Electronics",
            "type":"Retail Goods"
        }
    ],
    "sg:phone":"+1 613 384 3240",
    "sg:postcode":"K7M 7W8",
    "sg:province":"ON",
    "sg:tags":[
        "video",
        "game",
        "disc",
        "tape"
    ],
    "wof:name":"Jumbo Video",
    "wof:placetype":"venue"
},
  "geometry": {"coordinates":[-76.5674819946,44.2366600037],"type":"Point"}
}