{
  "type": "Feature",
  "properties": {
    "addr:full":"Halifax NS B3H 1V7",
    "addr:postcode":"b3h 1v7",
    "iso:country":"CA",
    "sg:city":"Halifax",
    "sg:classifiers":[
        {
            "category":"Health Services",
            "subcategory":"Doctor",
            "type":"Services"
        }
    ],
    "sg:phone":"+1 902 473 2366",
    "sg:postcode":"B3H 1V7",
    "sg:province":"NS",
    "sg:tags":[
        "physician",
        "surgeon"
    ],
    "wof:name":"Bentley, James MD",
    "wof:placetype":"venue"
},
  "geometry": {"coordinates":[-63.5825080872,44.6387290955],"type":"Point"}
}