{
  "type": "Feature",
  "properties": {
    "addr:full":"7550 Torbram Rd Mississauga ON L4T 3L8",
    "addr:housenumber":"7550",
    "addr:postcode":"l4t 3l8",
    "addr:street":"Torbram Rd",
    "iso:country":"CA",
    "sg:address":"7550 Torbram Rd",
    "sg:city":"Mississauga",
    "sg:classifiers":[
        {
            "category":"Wholesale",
            "subcategory":"Groceries",
            "type":"Manufacturing & Wholesale Goods"
        }
    ],
    "sg:phone":"+1 905 678 6680",
    "sg:postcode":"L4T 3L8",
    "sg:province":"ON",
    "sg:tags":[
        "beverage"
    ],
    "wof:name":"Imperial Flavours Inc",
    "wof:placetype":"venue"
},
  "geometry": {"coordinates":[-79.669273,43.706306],"type":"Point"}
}