{
  "type": "Feature",
  "properties": {
    "addr:full":"2416 Sandhurst Ave SW Calgary AB T3C 2M6",
    "addr:housenumber":"2416",
    "addr:postcode":"t3c 2m6",
    "addr:street":"Sandhurst Ave Sw",
    "iso:country":"CA",
    "sg:address":"2416 Sandhurst Ave SW",
    "sg:city":"Calgary",
    "sg:classifiers":[
        {
            "category":"Professional",
            "subcategory":"Research",
            "type":"Services"
        }
    ],
    "sg:phone":"+1 403 246 8303",
    "sg:postcode":"T3C 2M6",
    "sg:province":"AB",
    "sg:tags":[
        "environmental",
        "ecological"
    ],
    "wof:name":"Scace & Assoc Ltd",
    "wof:placetype":"venue"
},
  "geometry": {"coordinates":[-114.116188049,51.0429992676],"type":"Point"}
}