{
  "type": "Feature",
  "properties": {
    "addr:full":"140 Craig St Russell ON K4R 1A1",
    "addr:housenumber":"140",
    "addr:postcode":"k4r 1a1",
    "addr:street":"Craig St",
    "iso:country":"CA",
    "sg:address":"140 Craig St",
    "sg:city":"Russell",
    "sg:classifiers":[
        {
            "category":"Retail",
            "subcategory":"Auto Repair",
            "type":"Services"
        }
    ],
    "sg:phone":"+1 613 445 3393",
    "sg:postcode":"K4R 1A1",
    "sg:province":"ON",
    "sg:tags":[
        "repairing",
        "automobile"
    ],
    "wof:name":"Duke's Garage",
    "wof:placetype":"venue"
},
  "geometry": {"coordinates":[-75.37298583979999,45.2564697266],"type":"Point"}
}