{
  "type": "Feature",
  "properties": {
    "addr:full":"Coldstream BC V1B 3A3",
    "addr:postcode":"bc v1b 3a3",
    "iso:country":"CA",
    "sg:city":"Coldstream",
    "sg:classifiers":[
        {
            "category":"Travel",
            "subcategory":"Hotels & Motels",
            "type":"Entertainment"
        }
    ],
    "sg:phone":"+1 250 542 5367",
    "sg:postcode":"V1B 3A3",
    "sg:province":"BC",
    "sg:tags":[
        "breakfast",
        "accommodation",
        "bed"
    ],
    "wof:name":"High View Bed & Breakfast",
    "wof:placetype":"venue"
},
  "geometry": {"coordinates":[-119.252670288,50.2316207886],"type":"Point"}
}