{
  "type": "Feature",
  "properties": {
    "addr:full":"3922 Hamilton Rd Dorchester ON N0L 1G2",
    "addr:housenumber":"3922",
    "addr:postcode":"n0l 1g2",
    "addr:street":"Hamilton Rd",
    "iso:country":"CA",
    "sg:address":"3922 Hamilton Rd",
    "sg:city":"Dorchester",
    "sg:classifiers":[
        {
            "category":"Autos & Motor Vehicles",
            "subcategory":"Fuel & Gas Station",
            "type":"Retail Goods"
        }
    ],
    "sg:phone":"+1 519 268 3994",
    "sg:postcode":"N0L 1G2",
    "sg:province":"ON",
    "sg:tags":[
        "oil"
    ],
    "wof:name":"Top of the Hill Shell",
    "wof:placetype":"venue"
},
  "geometry": {"coordinates":[-81.06262207029999,42.9885520935],"type":"Point"}
}