{
  "type": "Feature",
  "properties": {
    "addr:full":"615 Pembroke St E Pembroke ON K8A 3L7",
    "addr:housenumber":"615",
    "addr:postcode":"k8a 3l7",
    "addr:street":"Pembroke St E",
    "iso:country":"CA",
    "sg:address":"615 Pembroke St E",
    "sg:city":"Pembroke",
    "sg:classifiers":[
        {
            "category":"Health Services",
            "subcategory":"Clinic",
            "type":"Services"
        }
    ],
    "sg:phone":"+1 613 732 3671",
    "sg:postcode":"K8A 3L7",
    "sg:province":"ON",
    "sg:tags":[
        "equipment",
        "therapy",
        "oxygen",
        "home"
    ],
    "wof:name":"Medigas Inc",
    "wof:placetype":"venue"
},
  "geometry": {"coordinates":[-77.09703063960001,45.8278388977],"type":"Point"}
}