{
  "type": "Feature",
  "properties": {
    "addr:full":"Fort Frances ON P9A 1G9",
    "addr:postcode":"p9a 1g9",
    "iso:country":"CA",
    "sg:city":"Fort Frances",
    "sg:classifiers":[
        {
            "category":"Professional",
            "subcategory":"Accounting & Tax Preparation",
            "type":"Services"
        }
    ],
    "sg:phone":"+1 807 274 5847",
    "sg:postcode":"P9A 1G9",
    "sg:province":"ON",
    "sg:tags":[
        "return",
        "filing"
    ],
    "wof:name":"H & R Block Canada Inc",
    "wof:placetype":"venue"
},
  "geometry": {"coordinates":[-93.39543151860001,48.6101112366],"type":"Point"}
}