{
  "type": "Feature",
  "properties": {
    "iso:country":"CA",
    "sg:address":"441 Rue Principale",
    "sg:city":"St-Sauveur-Des-Monts",
    "sg:classifiers":[
        {
            "category":"Home & Garden",
            "subcategory":"Carpets & Floor Coverings",
            "type":"Retail Goods"
        }
    ],
    "sg:phone":"+1 450 227 7912",
    "sg:postcode":"J0R 1R4",
    "sg:province":"QC",
    "sg:tags":[
        "dealer",
        "rug"
    ],
    "wof:name":"Tapis St-Sauveur",
    "wof:placetype":"venue"
},
  "geometry": {"coordinates":[-74.166633606,45.8895950317],"type":"Point"}
}