{
  "type": "Feature",
  "properties": {
    "addr:full":"4010 Boul Dagenais O Laval QC H7R 1L2",
    "addr:housenumber":"4010",
    "addr:postcode":"h7r 1l2",
    "addr:street":"Boul Dagenais O",
    "iso:country":"CA",
    "sg:address":"4010 Boul Dagenais O",
    "sg:city":"Laval",
    "sg:classifiers":[
        {
            "category":"Local Transit",
            "type":"Transportation"
        }
    ],
    "sg:phone":"+1 450 625 0506",
    "sg:postcode":"H7R 1L2",
    "sg:province":"QC",
    "sg:tags":[
        "bus",
        "line"
    ],
    "wof:name":"Autobus Uncle Harry Inc",
    "wof:placetype":"venue"
},
  "geometry": {"coordinates":[-73.82907899999999,45.563282],"type":"Point"}
}