{
  "type": "Feature",
  "properties": {
    "iso:country":"CA",
    "sg:city":"Brooks",
    "sg:classifiers":[
        {
            "category":"Autos & Motor Vehicles",
            "subcategory":"Auto Supplies",
            "type":"Retail Goods"
        }
    ],
    "sg:phone":"+1 403 362 8888",
    "sg:postcode":"T1R 1B9",
    "sg:province":"AB",
    "sg:tags":[
        "tire"
    ],
    "wof:name":"Kal Tire",
    "wof:placetype":"venue"
},
  "geometry": {"coordinates":[-111.892921448,50.5633354187],"type":"Point"}
}