{
  "type": "Feature",
  "properties": {
    "iso:country":"CA",
    "sg:city":"North Vancouver",
    "sg:classifiers":[
        {
            "category":"Education",
            "subcategory":"Special Training",
            "type":"Public Place"
        }
    ],
    "sg:phone":"+1 604 987 6909",
    "sg:postcode":"V7M 2J3",
    "sg:province":"BC",
    "sg:tags":[
        "instruction",
        "driving"
    ],
    "wof:name":"Firstway Driving School Ltd",
    "wof:placetype":"venue"
},
  "geometry": {"coordinates":[-123.07207489,49.322593689],"type":"Point"}
}