{
  "type": "Feature",
  "properties": {
    "addr:full":"120 Lsr Inonoaklin Rd Fauquier BC V0G 1K0",
    "addr:housenumber":"120",
    "addr:postcode":"v0g 1k0",
    "addr:street":"Lsr Inonoaklin Rd",
    "iso:country":"CA",
    "sg:address":"120 Lsr Inonoaklin Rd",
    "sg:city":"Fauquier",
    "sg:classifiers":[
        {
            "category":"Wholesale",
            "subcategory":"Auto Parts",
            "type":"Manufacturing & Wholesale Goods"
        }
    ],
    "sg:phone":"+1 250 269 7404",
    "sg:postcode":"V0G 1K0",
    "sg:province":"BC",
    "sg:tags":[
        "automobile",
        "wrecking"
    ],
    "wof:name":"Ifi Towing & Auto Repairs",
    "wof:placetype":"venue"
},
  "geometry": {"coordinates":[-118.080078125,49.8718605042],"type":"Point"}
}