{
  "type": "Feature",
  "properties": {
    "addr:full":"Orleans ON K1C 1S6",
    "addr:postcode":"k1c 1s6",
    "iso:country":"CA",
    "sg:city":"Orleans",
    "sg:classifiers":[
        {
            "category":"Health Services",
            "subcategory":"Doctor",
            "type":"Services"
        }
    ],
    "sg:phone":"+1 613 830 1771",
    "sg:postcode":"K1C 1S6",
    "sg:province":"ON",
    "sg:tags":[
        "physician",
        "surgeon"
    ],
    "wof:name":"Neal, Ron MD",
    "wof:placetype":"venue"
},
  "geometry": {"coordinates":[-75.52552,45.470886],"type":"Point"}
}