{
  "type": "Feature",
  "properties": {
    "addr:full":"148 Prescott St Kemptville ON K0G 1J0",
    "addr:housenumber":"148",
    "addr:postcode":"k0g 1j0",
    "addr:street":"Prescott St",
    "iso:country":"CA",
    "sg:address":"148 Prescott St",
    "sg:city":"Kemptville",
    "sg:classifiers":[
        {
            "category":"Food & Beverages",
            "subcategory":"Groceries & Convenience Stores",
            "type":"Retail Goods"
        }
    ],
    "sg:phone":"+1 613 258 2310",
    "sg:postcode":"K0G 1J0",
    "sg:province":"ON",
    "wof:name":"Kemptville Red & White",
    "wof:placetype":"venue"
},
  "geometry": {"coordinates":[-75.6447677612,45.0153579712],"type":"Point"}
}