{
  "type": "Feature",
  "properties": {
    "addr:full":"1273 Weston Rd York ON M6M 4R2",
    "addr:housenumber":"1273",
    "addr:postcode":"m6m 4r2",
    "addr:street":"Weston Rd",
    "iso:country":"CA",
    "sg:address":"1273 Weston Rd",
    "sg:city":"York",
    "sg:classifiers":[
        {
            "category":"Retail",
            "subcategory":"Funeral Services",
            "type":"Services"
        }
    ],
    "sg:phone":"+1 416 243 0202",
    "sg:postcode":"M6M 4R2",
    "sg:province":"ON",
    "sg:tags":[
        "director"
    ],
    "wof:name":"Scott Funeral Homes",
    "wof:placetype":"venue"
},
  "geometry": {"coordinates":[-79.49453,43.688923],"type":"Point"}
}