{
  "type": "Feature",
  "properties": {
    "addr:full":"1045 Boul Alexis-Lebert Saint-Luc QC J2W 2V3",
    "addr:housenumber":"1045",
    "addr:postcode":"j2w 2v3",
    "addr:street":"Boul Alexis-Lebert",
    "iso:country":"CA",
    "sg:address":"1045 Boul Alexis-Lebert",
    "sg:city":"Saint-Luc",
    "sg:classifiers":[
        {
            "category":"Manufacturing",
            "subcategory":"Signs",
            "type":"Manufacturing & Wholesale Goods"
        }
    ],
    "sg:phone":"+1 450 359 2226",
    "sg:postcode":"J2W 2V3",
    "sg:province":"QC",
    "sg:tags":[
        "painter"
    ],
    "wof:name":"Bro Design",
    "wof:placetype":"venue"
},
  "geometry": {"coordinates":[-73.296181,45.336491],"type":"Point"}
}