{
  "type": "Feature",
  "properties": {
    "addr:full":"671 Ch Ste Anne Des Lacs Sainte-Anne-Des-Lacs QC J0R 1B0",
    "addr:housenumber":"671",
    "addr:postcode":"j0r 1b0",
    "addr:street":"Ch Ste",
    "iso:country":"CA",
    "sg:address":"671 Ch Ste Anne Des Lacs",
    "sg:city":"Sainte-Anne-Des-Lacs",
    "sg:classifiers":[
        {
            "category":"Personal",
            "subcategory":"Beauty Salon",
            "type":"Services"
        }
    ],
    "sg:phone":"+1 450 224 9742",
    "sg:postcode":"J0R 1B0",
    "sg:province":"QC",
    "wof:name":"Esthetique Au Masque D'Or",
    "wof:placetype":"venue"
},
  "geometry": {"coordinates":[-74.121239,45.86467],"type":"Point"}
}