{
  "type": "Feature",
  "properties": {
    "addr:full":"Cranbrook BC V1C 3S8",
    "addr:postcode":"v1c 3s8",
    "iso:country":"CA",
    "sg:city":"Cranbrook",
    "sg:classifiers":[
        {
            "category":"Cinema",
            "subcategory":"Movie Theater",
            "type":"Entertainment"
        }
    ],
    "sg:phone":"+1 250 426 3272",
    "sg:postcode":"V1C 3S8",
    "sg:province":"BC",
    "wof:name":"Armond Theatre",
    "wof:placetype":"venue"
},
  "geometry": {"coordinates":[-115.753356934,49.5244674683],"type":"Point"}
}