{
  "type": "Feature",
  "properties": {
    "addr:full":"589 Adelaide St N London ON N6B 3J7",
    "addr:housenumber":"589",
    "addr:postcode":"n6b 3j7",
    "addr:street":"Adelaide St N",
    "iso:country":"CA",
    "sg:address":"589 Adelaide St N",
    "sg:city":"London",
    "sg:classifiers":[
        {
            "category":"Retail",
            "subcategory":"Auto Repair",
            "type":"Services"
        }
    ],
    "sg:phone":"+1 519 438 4363",
    "sg:postcode":"N6B 3J7",
    "sg:province":"ON",
    "sg:tags":[
        "body",
        "automobile",
        "painting"
    ],
    "wof:name":"North End Auto Refinishing",
    "wof:placetype":"venue"
},
  "geometry": {"coordinates":[-81.23458862299999,42.9945716858],"type":"Point"}
}