{
  "type": "Feature",
  "properties": {
    "addr:full":"505 Boul DE Maisonneuve E Montreal QC H2L 4R6",
    "addr:housenumber":"505",
    "addr:postcode":"h2l 4r6",
    "addr:street":"Boul De Maisonneuve E",
    "iso:country":"CA",
    "sg:address":"505 Boul DE Maisonneuve E",
    "sg:city":"Montreal",
    "sg:classifiers":[
        {
            "category":"Local Transit",
            "type":"Transportation"
        }
    ],
    "sg:phone":"+1 514 842 2281",
    "sg:postcode":"H2L 4R6",
    "sg:province":"QC",
    "sg:tags":[
        "bus",
        "line"
    ],
    "wof:name":"Voyageur",
    "wof:placetype":"venue"
},
  "geometry": {"coordinates":[-73.561081,45.515427],"type":"Point"}
}