{
  "type": "Feature",
  "properties": {
    "addr:full":"34 Clarence St Ottawa ON K1N 5P3",
    "addr:housenumber":"34",
    "addr:postcode":"k1n 5p3",
    "addr:street":"Clarence St",
    "iso:country":"CA",
    "sg:address":"34 Clarence St",
    "sg:city":"Ottawa",
    "sg:classifiers":[
        {
            "category":"Bars & Pubs",
            "type":"Food & Drink"
        }
    ],
    "sg:phone":"+1 613 789 7770",
    "sg:postcode":"K1N 5P3",
    "sg:province":"ON",
    "sg:tags":[
        "club",
        "night"
    ],
    "wof:name":"Suite 34",
    "wof:placetype":"venue"
},
  "geometry": {"coordinates":[-75.69461099999999,45.428238],"type":"Point"}
}