{
  "type": "Feature",
  "properties": {
    "addr:full":"55 116 Rte W Warwick QC J0A 1M0",
    "addr:housenumber":"116",
    "addr:postcode":"j0a 1m0",
    "addr:street":"55;Rte W",
    "iso:country":"CA",
    "sg:address":"55 116 Rte W",
    "sg:city":"Warwick",
    "sg:classifiers":[
        {
            "category":"Education",
            "subcategory":"School",
            "type":"Public Place"
        }
    ],
    "sg:phone":"+1 819 358 2966",
    "sg:postcode":"J0A 1M0",
    "sg:province":"QC",
    "wof:name":"Ecole LA Fermentiere",
    "wof:placetype":"venue"
},
  "geometry": {"coordinates":[-71.97523498539999,45.9714164734],"type":"Point"}
}