{
  "type": "Feature",
  "properties": {
    "addr:full":"221 Rue Principale O Magog QC J1X 2A8",
    "addr:housenumber":"221",
    "addr:postcode":"j1x 2a8",
    "addr:street":"Rue Principale O",
    "iso:country":"CA",
    "sg:address":"221 Rue Principale O",
    "sg:city":"Magog",
    "sg:classifiers":[
        {
            "category":"Wholesale",
            "subcategory":"Electrical",
            "type":"Manufacturing & Wholesale Goods"
        }
    ],
    "sg:phone":"+1 819 843 4455",
    "sg:postcode":"J1X 2A8",
    "sg:province":"QC",
    "sg:tags":[
        "consultant",
        "radio",
        "telecommunication"
    ],
    "wof:name":"Solution Cellulaire",
    "wof:placetype":"venue"
},
  "geometry": {"coordinates":[-72.14057200000001,45.263226],"type":"Point"}
}