{
  "type": "Feature",
  "properties": {
    "iso:country":"CA",
    "sg:address":"7 Main St",
    "sg:city":"Belleoram",
    "sg:classifiers":[
        {
            "category":"Recreation",
            "subcategory":"Arcade",
            "type":"Entertainment"
        }
    ],
    "sg:phone":"+1 709 881 2106",
    "sg:postcode":"A0H 1B0",
    "sg:province":"NL",
    "sg:tags":[
        "amusement",
        "devices"
    ],
    "wof:name":"Road Side Arcade",
    "wof:placetype":"venue"
},
  "geometry": {"coordinates":[-55.4121627808,47.5237464905],"type":"Point"}
}