{
  "type": "Feature",
  "properties": {
    "iso:country":"CA",
    "sg:address":"RR 1 STN Main",
    "sg:city":"Parry Sound",
    "sg:classifiers":[
        {
            "category":"Recreation",
            "type":"Entertainment"
        }
    ],
    "sg:phone":"+1 705 389 3203",
    "sg:postcode":"P2A 2W7",
    "sg:province":"ON",
    "sg:tags":[
        "hall",
        "auditorium"
    ],
    "wof:name":"Waubamik Community Hall",
    "wof:placetype":"venue"
},
  "geometry": {"coordinates":[-80.036362,45.344769],"type":"Point"}
}