{
  "type": "Feature",
  "properties": {
    "addr:full":"85 Petersen Rd Campbell River BC V9W 3H1",
    "addr:housenumber":"85",
    "addr:postcode":"v9w 3h1",
    "addr:street":"Petersen Rd",
    "iso:country":"CA",
    "sg:address":"85 Petersen Rd",
    "sg:city":"Campbell River",
    "sg:classifiers":[
        {
            "category":"Building & Trades",
            "subcategory":"Construction",
            "type":"Services"
        }
    ],
    "sg:phone":"+1 250 287 8352",
    "sg:postcode":"V9W 3H1",
    "sg:province":"BC",
    "sg:tags":[
        "general",
        "contractor"
    ],
    "wof:name":"Horton Construction",
    "wof:placetype":"venue"
},
  "geometry": {"coordinates":[-125.265808105,50.0088119507],"type":"Point"}
}