{
  "type": "Feature",
  "properties": {
    "addr:full":"685 Av Lepine Dorval QC H9P 1G3",
    "addr:housenumber":"685",
    "addr:postcode":"h9p 1g3",
    "addr:street":"Av Lepine",
    "iso:country":"CA",
    "sg:address":"685 Av Lepine",
    "sg:city":"Dorval",
    "sg:classifiers":[
        {
            "category":"Manufacturing",
            "subcategory":"Printing",
            "type":"Manufacturing & Wholesale Goods"
        }
    ],
    "sg:phone":"+1 514 636 3399",
    "sg:postcode":"H9P 1G3",
    "sg:province":"QC",
    "sg:tags":[
        "printer"
    ],
    "wof:name":"Imprimerie Ora Intl",
    "wof:placetype":"venue"
},
  "geometry": {"coordinates":[-73.72937,45.455383],"type":"Point"}
}