{
  "type": "Feature",
  "properties": {
    "addr:full":"20477 Fraser Hwy Langley BC V3A 4G3",
    "addr:housenumber":"20477",
    "addr:postcode":"v3a 4g3",
    "addr:street":"Fraser Hwy",
    "iso:country":"CA",
    "sg:address":"20477 Fraser Hwy",
    "sg:city":"Langley",
    "sg:classifiers":[
        {
            "category":"Restaurant",
            "type":"Food & Drink"
        }
    ],
    "sg:phone":"+1 604 533 3336",
    "sg:postcode":"V3A 4G3",
    "sg:province":"BC",
    "wof:name":"Patsies Uptown Bistro",
    "wof:placetype":"venue"
},
  "geometry": {"coordinates":[-122.654731751,49.1044769287],"type":"Point"}
}