{
  "type": "Feature",
  "properties": {
    "addr:full":"14504 123 Ave NW Edmonton AB T5L 2Y3",
    "addr:housenumber":"14504",
    "addr:postcode":"t5l 2y3",
    "addr:street":"123 Ave Nw",
    "iso:country":"CA",
    "sg:address":"14504 123 Ave NW",
    "sg:city":"Edmonton",
    "sg:classifiers":[
        {
            "category":"Manufacturing",
            "subcategory":"Building Materials",
            "type":"Manufacturing & Wholesale Goods"
        }
    ],
    "sg:phone":"+1 780 454 6790",
    "sg:postcode":"T5L 2Y3",
    "sg:province":"AB",
    "wof:name":"Madsen's Custom Cabinets Ltd",
    "wof:placetype":"venue"
},
  "geometry": {"coordinates":[-113.57192999999999,53.576977],"type":"Point"}
}