{
  "type": "Feature",
  "properties": {
    "addr:full":"Victoriaville QC G6S 1E1",
    "addr:postcode":"g6s 1e1",
    "iso:country":"CA",
    "sg:city":"Victoriaville",
    "sg:classifiers":[
        {
            "category":"Restaurant",
            "type":"Food & Drink"
        }
    ],
    "sg:phone":"+1 819 752 3288",
    "sg:postcode":"G6S 1E1",
    "sg:province":"QC",
    "wof:name":"Restaurant Maison Wong",
    "wof:placetype":"venue"
},
  "geometry": {"coordinates":[-71.93277,46.062111],"type":"Point"}
}