{
  "type": "Feature",
  "properties": {
    "addr:full":"1235 Trafalgar Rd # 318 Oakville ON L6H 3P1",
    "addr:housenumber":"1235",
    "addr:postcode":"l6h 3p1",
    "addr:street":"Trafalgar Rd # 318",
    "iso:country":"CA",
    "sg:address":"1235 Trafalgar Rd # 318",
    "sg:city":"Oakville",
    "sg:classifiers":[
        {
            "category":"Health Services",
            "subcategory":"Doctor",
            "type":"Services"
        }
    ],
    "sg:phone":"+1 905 849 1322",
    "sg:postcode":"L6H 3P1",
    "sg:province":"ON",
    "sg:tags":[
        "physician",
        "surgeon"
    ],
    "wof:name":"Stirling, D MD",
    "wof:placetype":"venue"
},
  "geometry": {"coordinates":[-79.690521,43.467075],"type":"Point"}
}