{
  "type": "Feature",
  "properties": {
    "addr:full":"1679 Bloor St W Toronto ON M6P 1A6",
    "addr:housenumber":"1679",
    "addr:postcode":"m6p 1a6",
    "addr:street":"Bloor St W",
    "iso:country":"CA",
    "sg:address":"1679 Bloor St W",
    "sg:city":"Toronto",
    "sg:classifiers":[
        {
            "category":"Food & Beverages",
            "subcategory":"Groceries & Convenience Stores",
            "type":"Retail Goods"
        }
    ],
    "sg:phone":"+1 416 533 6219",
    "sg:postcode":"M6P 1A6",
    "sg:province":"ON",
    "sg:tags":[
        "grocer"
    ],
    "wof:name":"Kenneth Variety & Grocery",
    "wof:placetype":"venue"
},
  "geometry": {"coordinates":[-79.45693199999999,43.655315],"type":"Point"}
}