{
  "type": "Feature",
  "properties": {
    "addr:full":"1314 Cornwall St Regina SK S4R 2H5",
    "addr:housenumber":"1314",
    "addr:postcode":"s4r 2h5",
    "addr:street":"Cornwall St",
    "iso:country":"CA",
    "sg:address":"1314 Cornwall St",
    "sg:city":"Regina",
    "sg:classifiers":[
        {
            "category":"Personal",
            "subcategory":"Beauty Salon",
            "type":"Services"
        }
    ],
    "sg:phone":"+1 306 757 4247",
    "sg:postcode":"S4R 2H5",
    "sg:province":"SK",
    "wof:name":"Styles For Success Hair Design",
    "wof:placetype":"venue"
},
  "geometry": {"coordinates":[-104.612480164,50.457950592],"type":"Point"}
}