{
  "type": "Feature",
  "properties": {
    "addr:full":"312 Rue Sherbrooke E # 312 Montreal QC H2X 1E6",
    "addr:housenumber":"312",
    "addr:postcode":"h2x 1e6",
    "addr:street":"Rue Sherbrooke E # 312",
    "iso:country":"CA",
    "sg:address":"312 Rue Sherbrooke E # 312",
    "sg:city":"Montreal",
    "sg:classifiers":[
        {
            "category":"Communications",
            "subcategory":"Film & Video Production",
            "type":"Services"
        }
    ],
    "sg:phone":"+1 514 848 0579",
    "sg:postcode":"H2X 1E6",
    "sg:province":"QC",
    "sg:tags":[
        "motion",
        "picture"
    ],
    "wof:name":"Groupe Image Buzz Inc",
    "wof:placetype":"venue"
},
  "geometry": {"coordinates":[-73.56766500000001,45.516003],"type":"Point"}
}