{
  "type": "Feature",
  "properties": {
    "addr:full":"Hawkesbury ON K6A 1A1",
    "addr:postcode":"k6a 1a1",
    "iso:country":"CA",
    "sg:city":"Hawkesbury",
    "sg:classifiers":[
        {
            "category":"Health Services",
            "subcategory":"Doctor",
            "type":"Services"
        }
    ],
    "sg:phone":"+1 613 632 5656",
    "sg:postcode":"K6A 1A1",
    "sg:province":"ON",
    "sg:tags":[
        "dentist"
    ],
    "wof:name":"Dumas, Julie DDS",
    "wof:placetype":"venue"
},
  "geometry": {"coordinates":[-74.612251,45.609463],"type":"Point"}
}