{
  "type": "Feature",
  "properties": {
    "addr:full":"Calgary AB T2H 2C2",
    "addr:postcode":"t2h 2c2",
    "iso:country":"CA",
    "sg:city":"Calgary",
    "sg:classifiers":[
        {
            "category":"Wholesale",
            "subcategory":"Durable Goods & Equipment",
            "type":"Manufacturing & Wholesale Goods"
        }
    ],
    "sg:phone":"+1 403 252 9982",
    "sg:postcode":"T2H 2C2",
    "sg:province":"AB",
    "sg:tags":[
        "geophysical",
        "apparatus"
    ],
    "wof:name":"Input Output Canada Inc",
    "wof:placetype":"venue"
},
  "geometry": {"coordinates":[-114.045921326,50.9984703064],"type":"Point"}
}