{
  "type": "Feature",
  "properties": {
    "iso:country":"CA",
    "sg:city":"Montreal",
    "sg:classifiers":[
        {
            "category":"Insurance",
            "subcategory":"Insurance Agent",
            "type":"Services"
        }
    ],
    "sg:phone":"+1 514 282 1112",
    "sg:postcode":"H3G 2V3",
    "sg:province":"QC",
    "wof:name":"Dale-Parizeau Lm",
    "wof:placetype":"venue"
},
  "geometry": {"coordinates":[-73.553909,45.52063],"type":"Point"}
}