{
  "type": "Feature",
  "properties": {
    "iso:country":"CA",
    "sg:address":"677 Crown Dr",
    "sg:city":"Peterborough",
    "sg:classifiers":[
        {
            "category":"Autos & Motor Vehicles",
            "subcategory":"Auto Supplies",
            "type":"Retail Goods"
        }
    ],
    "sg:phone":"+1 705 876 1144",
    "sg:postcode":"K9J 6W2",
    "sg:province":"ON",
    "sg:tags":[
        "tire"
    ],
    "wof:name":"Tirecraft",
    "wof:placetype":"venue"
},
  "geometry": {"coordinates":[-78.339203,44.277481],"type":"Point"}
}