{
  "type": "Feature",
  "properties": {
    "iso:country":"CA",
    "sg:city":"Concord",
    "sg:classifiers":[
        {
            "category":"Wholesale",
            "subcategory":"Medical Equipment & Supplies",
            "type":"Manufacturing & Wholesale Goods"
        }
    ],
    "sg:phone":"+1 905 738 5901",
    "sg:postcode":"L4K 4N8",
    "sg:province":"ON",
    "sg:tags":[
        "hospital"
    ],
    "wof:name":"Allied Medical Instruments Inc",
    "wof:placetype":"venue"
},
  "geometry": {"coordinates":[-79.52796936039999,43.8179855347],"type":"Point"}
}