{
  "type": "Feature",
  "properties": {
    "addr:full":"Noscopie St Churchill Falls NL A0R 1A0",
    "addr:postcode":"a0r 1a0",
    "addr:street":"St",
    "iso:country":"CA",
    "sg:address":"Noscopie St",
    "sg:city":"Churchill Falls",
    "sg:classifiers":[
        {
            "category":"Real Estate",
            "subcategory":"Real Estate Operator",
            "type":"Services"
        }
    ],
    "sg:phone":"+1 709 925 3466",
    "sg:postcode":"A0R 1A0",
    "sg:province":"NL",
    "sg:tags":[
        "mall",
        "shopping",
        "center"
    ],
    "wof:name":"Sears Canada Inc",
    "wof:placetype":"venue"
},
  "geometry": {"coordinates":[-64.00151824949999,53.5303649902],"type":"Point"}
}