{
  "type": "Feature",
  "properties": {
    "addr:full":"11160 Silversmith Pl # 155 Richmond BC V7A 5E4",
    "addr:housenumber":"155",
    "addr:postcode":"11160;v7a 5e4",
    "addr:street":"Silversmith Pl #",
    "iso:country":"CA",
    "sg:address":"11160 Silversmith Pl # 155",
    "sg:city":"Richmond",
    "sg:classifiers":[
        {
            "category":"Insurance",
            "subcategory":"Insurance Agent",
            "type":"Services"
        }
    ],
    "sg:phone":"+1 604 271 5080",
    "sg:postcode":"V7A 5E4",
    "sg:province":"BC",
    "wof:name":"Bay City Insurance Svc Ltd",
    "wof:placetype":"venue"
},
  "geometry": {"coordinates":[-123.10092899999999,49.129101],"type":"Point"}
}