{
  "type": "Feature",
  "properties": {
    "iso:country":"CA",
    "sg:address":"98 Broadway St",
    "sg:city":"Tillsonburg",
    "sg:classifiers":[
        {
            "category":"Shopping",
            "subcategory":"Computers & Home Electronics",
            "type":"Retail Goods"
        }
    ],
    "sg:phone":"+1 519 842 3693",
    "sg:postcode":"N4G 3P6",
    "sg:province":"ON",
    "sg:tags":[
        "radio",
        "television",
        "video",
        "equipment"
    ],
    "wof:name":"Joe's Audio Video Svc",
    "wof:placetype":"venue"
},
  "geometry": {"coordinates":[-80.7262878418,42.8593330383],"type":"Point"}
}