{
  "type": "Feature",
  "properties": {
    "addr:full":"1520 Queen St E Toronto ON M4L 1E3",
    "addr:housenumber":"1520",
    "addr:postcode":"m4l 1e3",
    "addr:street":"Queen St E",
    "iso:country":"CA",
    "sg:address":"1520 Queen St E",
    "sg:city":"Toronto",
    "sg:classifiers":[
        {
            "category":"Professional",
            "subcategory":"Accounting & Tax Preparation",
            "type":"Services"
        }
    ],
    "sg:phone":"+1 416 405 9680",
    "sg:postcode":"M4L 1E3",
    "sg:province":"ON",
    "sg:tags":[
        "accountant"
    ],
    "wof:name":"Allman, Denis",
    "wof:placetype":"venue"
},
  "geometry": {"coordinates":[-79.31991577150001,43.66563797],"type":"Point"}
}