{
  "type": "Feature",
  "properties": {
    "addr:full":"Toronto ON M5M 1B2",
    "addr:postcode":"m5m 1b2",
    "iso:country":"CA",
    "sg:city":"Toronto",
    "sg:classifiers":[
        {
            "category":"Health Services",
            "subcategory":"Medical Lab",
            "type":"Services"
        }
    ],
    "sg:phone":"+1 416 789 1818",
    "sg:postcode":"M5M 1B2",
    "sg:province":"ON",
    "sg:tags":[
        "laboratory"
    ],
    "wof:name":"Pearce Dental Laboratory",
    "wof:placetype":"venue"
},
  "geometry": {"coordinates":[-79.4135971069,43.7228279114],"type":"Point"}
}