{
  "type": "Feature",
  "properties": {
    "addr:full":"Red Deer AB T4N 4C6",
    "addr:postcode":"t4n 4c6",
    "iso:country":"CA",
    "sg:city":"Red Deer",
    "sg:classifiers":[
        {
            "category":"Shopping",
            "subcategory":"Clothing, Apparel, & Fashions",
            "type":"Retail Goods"
        }
    ],
    "sg:phone":"+1 403 347 6666",
    "sg:postcode":"T4N 4C6",
    "sg:province":"AB",
    "sg:tags":[
        "work"
    ],
    "wof:name":"Mark's Work Wearhouse Ltd",
    "wof:placetype":"venue"
},
  "geometry": {"coordinates":[-113.814186096,52.2831306458],"type":"Point"}
}