{
  "type": "Feature",
  "properties": {
    "addr:full":"1806 11th St Coaldale AB T1M 1N1",
    "addr:housenumber":"1806",
    "addr:postcode":"t1m 1n1",
    "addr:street":"11Th St",
    "iso:country":"CA",
    "sg:address":"1806 11th St",
    "sg:city":"Coaldale",
    "sg:classifiers":[
        {
            "category":"Manufacturing",
            "subcategory":"Motor Vehicles & Parts",
            "type":"Manufacturing & Wholesale Goods"
        }
    ],
    "sg:phone":"+1 403 345 4427",
    "sg:postcode":"T1M 1N1",
    "sg:province":"AB",
    "sg:tags":[
        "body",
        "truck"
    ],
    "wof:name":"Intercontinental Truck Body",
    "wof:placetype":"venue"
},
  "geometry": {"coordinates":[-112.60740661600001,49.7313652039],"type":"Point"}
}