{
  "type": "Feature",
  "properties": {
    "addr:full":"223 Ch Madawaska Grand Falls NB E3Y 1A5",
    "addr:housenumber":"223",
    "addr:postcode":"e3y 1a5",
    "addr:street":"Ch Madawaska",
    "iso:country":"CA",
    "sg:address":"223 Ch Madawaska",
    "sg:city":"Grand Falls",
    "sg:classifiers":[
        {
            "category":"Health Services",
            "subcategory":"Doctor",
            "type":"Services"
        }
    ],
    "sg:phone":"+1 506 473 6444",
    "sg:postcode":"E3Y 1A5",
    "sg:province":"NB",
    "sg:tags":[
        "physician",
        "surgeon"
    ],
    "wof:name":"Roy, Maurice P MD",
    "wof:placetype":"venue"
},
  "geometry": {"coordinates":[-67.745064,47.054073],"type":"Point"}
}