{
  "type": "Feature",
  "properties": {
    "iso:country":"CA",
    "sg:address":"426 Keith Rd",
    "sg:city":"West Vancouver",
    "sg:classifiers":[
        {
            "category":"Building & Trades",
            "subcategory":"Cleaning & Sanitation",
            "type":"Services"
        }
    ],
    "sg:phone":"+1 604 904 4188",
    "sg:postcode":"V7T 1L7",
    "sg:province":"BC",
    "sg:tags":[
        "janitor"
    ],
    "wof:name":"Coastline Maintenance",
    "wof:placetype":"venue"
},
  "geometry": {"coordinates":[-123.127670288,49.3306427002],"type":"Point"}
}