{
  "type": "Feature",
  "properties": {
    "addr:full":"100 Harbourview Blvd Bathurst NB E2A 5B9",
    "addr:housenumber":"100",
    "addr:postcode":"e2a 5b9",
    "addr:street":"Harbourview Blvd",
    "iso:country":"CA",
    "sg:address":"100 Harbourview Blvd",
    "sg:city":"Bathurst",
    "sg:classifiers":[
        {
            "category":"Food & Beverages",
            "subcategory":"Groceries & Convenience Stores",
            "type":"Retail Goods"
        }
    ],
    "sg:phone":"+1 506 545 7687",
    "sg:postcode":"E2A 5B9",
    "sg:province":"NB",
    "wof:name":"Esso Tiger Express",
    "wof:placetype":"venue"
},
  "geometry": {"coordinates":[-65.6574554443,47.6215057373],"type":"Point"}
}