{
  "type": "Feature",
  "properties": {
    "addr:full":"72 Rue Rodier Repentigny QC J6A 6T9",
    "addr:housenumber":"72",
    "addr:postcode":"j6a 6t9",
    "addr:street":"Rue Rodier",
    "iso:country":"CA",
    "sg:address":"72 Rue Rodier",
    "sg:city":"Repentigny",
    "sg:classifiers":[
        {
            "category":"Health Services",
            "subcategory":"Health Practitioner",
            "type":"Services"
        }
    ],
    "sg:phone":"+1 450 582 0169",
    "sg:postcode":"J6A 6T9",
    "sg:province":"QC",
    "sg:tags":[
        "acupuncture"
    ],
    "wof:name":"Clinique D'Acupuncture Lise",
    "wof:placetype":"venue"
},
  "geometry": {"coordinates":[-73.44171142579999,45.7467498779],"type":"Point"}
}