{
  "type": "Feature",
  "properties": {
    "addr:full":"6 Adams St Paris ON N3L 3X4",
    "addr:housenumber":"6",
    "addr:postcode":"n3l 3x4",
    "addr:street":"Adams St",
    "iso:country":"CA",
    "sg:address":"6 Adams St",
    "sg:city":"Paris",
    "sg:classifiers":[
        {
            "category":"Manufacturing",
            "subcategory":"Metals",
            "type":"Manufacturing & Wholesale Goods"
        }
    ],
    "sg:phone":"+1 519 442 3824",
    "sg:postcode":"N3L 3X4",
    "sg:province":"ON",
    "sg:tags":[
        "steel"
    ],
    "wof:name":"Kenrod Steel Fabricating Ltd",
    "wof:placetype":"venue"
},
  "geometry": {"coordinates":[-80.39252500000001,43.204472],"type":"Point"}
}