{
  "type": "Feature",
  "properties": {
    "addr:full":"723 Mount Pleasant Rd Toronto ON M4S 2N4",
    "addr:housenumber":"723",
    "addr:postcode":"m4s 2n4",
    "addr:street":"Mount Pleasant Rd",
    "iso:country":"CA",
    "sg:address":"723 Mount Pleasant Rd",
    "sg:city":"Toronto",
    "sg:classifiers":[
        {
            "category":"Health Services",
            "subcategory":"Doctor",
            "type":"Services"
        }
    ],
    "sg:phone":"+1 416 488 8808",
    "sg:postcode":"M4S 2N4",
    "sg:province":"ON",
    "sg:tags":[
        "dentist"
    ],
    "wof:name":"Mount Pleasant Dental Ctr",
    "wof:placetype":"venue"
},
  "geometry": {"coordinates":[-79.38943500000001,43.707031],"type":"Point"}
}