{
  "type": "Feature",
  "properties": {
    "iso:country":"CA",
    "sg:address":"4411 Av Papineau",
    "sg:city":"Montreal",
    "sg:classifiers":[
        {
            "category":"Manufacturing",
            "subcategory":"Food",
            "type":"Manufacturing & Wholesale Goods"
        }
    ],
    "sg:phone":"+1 514 524 6881",
    "sg:postcode":"H2H 1T7",
    "sg:province":"QC",
    "sg:tags":[
        "product",
        "seafood",
        "fish",
        "prepared"
    ],
    "wof:name":"Moderne Limited",
    "wof:placetype":"venue"
},
  "geometry": {"coordinates":[-73.573128,45.532425],"type":"Point"}
}