{
  "type": "Feature",
  "properties": {
    "addr:full":"507 1st Ave SE Dauphin MB R7N 2Z8",
    "addr:housenumber":"507",
    "addr:postcode":"r7n 2z8",
    "addr:street":"1St Ave Se",
    "iso:country":"CA",
    "sg:address":"507 1st Ave SE",
    "sg:city":"Dauphin",
    "sg:classifiers":[
        {
            "category":"Manufacturing",
            "subcategory":"Tools & Machinery",
            "type":"Manufacturing & Wholesale Goods"
        }
    ],
    "sg:phone":"+1 204 638 1633",
    "sg:postcode":"R7N 2Z8",
    "sg:province":"MB",
    "sg:tags":[
        "machine",
        "shop"
    ],
    "wof:name":"Ritz Machine Works Inc",
    "wof:placetype":"venue"
},
  "geometry": {"coordinates":[-100.04006957999999,51.1437187195],"type":"Point"}
}