{
  "type": "Feature",
  "properties": {
    "addr:full":"3145 Rue Jarry E Montreal QC H1Z 2C2",
    "addr:housenumber":"3145",
    "addr:postcode":"h1z 2c2",
    "addr:street":"Rue Jarry E",
    "iso:country":"CA",
    "sg:address":"3145 Rue Jarry E",
    "sg:city":"Montreal",
    "sg:classifiers":[
        {
            "category":"Restaurant",
            "type":"Food & Drink"
        }
    ],
    "sg:phone":"+1 514 725 3654",
    "sg:postcode":"H1Z 2C2",
    "sg:province":"QC",
    "wof:name":"Apelia Restaurant",
    "wof:placetype":"venue"
},
  "geometry": {"coordinates":[-73.61068,45.562641],"type":"Point"}
}