{
  "type": "Feature",
  "properties": {
    "addr:full":"453 Christina St N Sarnia ON N7T 5W3",
    "addr:housenumber":"453",
    "addr:postcode":"n7t 5w3",
    "addr:street":"Christina St N",
    "iso:country":"CA",
    "sg:address":"453 Christina St N",
    "sg:city":"Sarnia",
    "sg:classifiers":[
        {
            "category":"Professional",
            "subcategory":"Engineering",
            "type":"Services"
        }
    ],
    "sg:phone":"+1 519 337 8000",
    "sg:postcode":"N7T 5W3",
    "sg:province":"ON",
    "sg:tags":[
        "engineer"
    ],
    "wof:name":"Mig Engineering Ltd",
    "wof:placetype":"venue"
},
  "geometry": {"coordinates":[-82.402672,42.981506],"type":"Point"}
}