{
  "type": "Feature",
  "properties": {
    "addr:full":"3055 Massey Dr # 116 Prince George BC V2N 2S9",
    "addr:housenumber":"3055",
    "addr:postcode":"v2n 2s9",
    "addr:street":"Massey Dr # 116",
    "iso:country":"CA",
    "sg:address":"3055 Massey Dr # 116",
    "sg:city":"Prince George",
    "sg:classifiers":[
        {
            "category":"Food & Beverages",
            "subcategory":"Specialty",
            "type":"Retail Goods"
        }
    ],
    "sg:phone":"+1 250 562 5604",
    "sg:postcode":"V2N 2S9",
    "sg:province":"BC",
    "sg:tags":[
        "health",
        "diet"
    ],
    "wof:name":"General Nutrition Ctr",
    "wof:placetype":"venue"
},
  "geometry": {"coordinates":[-122.779839,53.899452],"type":"Point"}
}