{
  "type": "Feature",
  "properties": {
    "addr:full":"30 Spetz St Kitchener ON N2H 1K1",
    "addr:housenumber":"30",
    "addr:postcode":"n2h 1k1",
    "addr:street":"Spetz St",
    "iso:country":"CA",
    "sg:address":"30 Spetz St",
    "sg:city":"Kitchener",
    "sg:classifiers":[
        {
            "category":"Professional",
            "subcategory":"Lawyer & Legal Services",
            "type":"Services"
        }
    ],
    "sg:phone":"+1 519 743 3654",
    "sg:postcode":"N2H 1K1",
    "sg:province":"ON",
    "sg:tags":[
        "attorney"
    ],
    "wof:name":"Shannon, John D E",
    "wof:placetype":"venue"
},
  "geometry": {"coordinates":[-80.484695,43.451691],"type":"Point"}
}