{
  "type": "Feature",
  "properties": {
    "addr:full":"2103 6 St Nisku AB T9E 7X8",
    "addr:housenumber":"2103 6",
    "addr:postcode":"t9e 7x8",
    "addr:street":"St",
    "iso:country":"CA",
    "sg:address":"2103 6 St",
    "sg:city":"Nisku",
    "sg:classifiers":[
        {
            "category":"Manufacturing",
            "subcategory":"Metals",
            "type":"Manufacturing & Wholesale Goods"
        }
    ],
    "sg:phone":"+1 780 955 7559",
    "sg:postcode":"T9E 7X8",
    "sg:province":"AB",
    "sg:tags":[
        "treating",
        "heat"
    ],
    "wof:name":"R & R Stress Relieving Svc Ltd",
    "wof:placetype":"venue"
},
  "geometry": {"coordinates":[-113.527016,53.339729],"type":"Point"}
}