{
  "type": "Feature",
  "properties": {
    "addr:full":"611 Duffus Rd Keewatin ON P0X 1C0",
    "addr:housenumber":"611",
    "addr:postcode":"p0x 1c0",
    "addr:street":"Duffus Rd",
    "iso:country":"CA",
    "sg:address":"611 Duffus Rd",
    "sg:city":"Keewatin",
    "sg:classifiers":[
        {
            "category":"Recreation",
            "type":"Entertainment"
        }
    ],
    "sg:phone":"+1 807 547 2093",
    "sg:postcode":"P0X 1C0",
    "sg:province":"ON",
    "sg:tags":[
        "guide"
    ],
    "wof:name":"Straight Line North Inc",
    "wof:placetype":"venue"
},
  "geometry": {"coordinates":[-94.55727400000001,49.757713],"type":"Point"}
}