{
  "type": "Feature",
  "properties": {
    "addr:full":"781 Rue Victoria LA Baie QC G7B 3M8",
    "addr:housenumber":"781",
    "addr:postcode":"g7b 3m8",
    "addr:street":"Rue Victoria",
    "iso:country":"CA",
    "sg:address":"781 Rue Victoria",
    "sg:city":"LA Baie",
    "sg:classifiers":[
        {
            "category":"Cinema",
            "subcategory":"Movie Rental",
            "type":"Entertainment"
        }
    ],
    "sg:phone":"+1 418 697 1515",
    "sg:postcode":"G7B 3M8",
    "sg:province":"QC",
    "sg:tags":[
        "leasing",
        "video",
        "disc",
        "tape"
    ],
    "wof:name":"Premiere Video",
    "wof:placetype":"venue"
},
  "geometry": {"coordinates":[-70.88055419920001,48.3422241211],"type":"Point"}
}