{
  "type": "Feature",
  "properties": {
    "addr:full":"96 Waverly Rd Bowmanville ON L1C 3W9",
    "addr:housenumber":"96",
    "addr:postcode":"l1c 3w9",
    "addr:street":"Waverly Rd",
    "iso:country":"CA",
    "sg:address":"96 Waverly Rd",
    "sg:city":"Bowmanville",
    "sg:classifiers":[
        {
            "category":"Restaurant",
            "type":"Food & Drink"
        }
    ],
    "sg:phone":"+1 905 697 2964",
    "sg:postcode":"L1C 3W9",
    "sg:province":"ON",
    "wof:name":"Jamaica Native Dish Inc",
    "wof:placetype":"venue"
},
  "geometry": {"coordinates":[-78.6933288574,43.9040718079],"type":"Point"}
}