{
  "type": "Feature",
  "properties": {
    "addr:full":"Ottawa ON K1N 8B6",
    "addr:postcode":"k1n 8b6",
    "iso:country":"CA",
    "sg:city":"Ottawa",
    "sg:classifiers":[
        {
            "category":"Shopping",
            "subcategory":"Computers & Home Electronics",
            "type":"Retail Goods"
        }
    ],
    "sg:phone":"+1 613 789 8777",
    "sg:postcode":"K1N 8B6",
    "sg:province":"ON",
    "sg:tags":[
        "software"
    ],
    "wof:name":"S J Softech",
    "wof:placetype":"venue"
},
  "geometry": {"coordinates":[-75.67951965330001,45.4317474365],"type":"Point"}
}