{
  "type": "Feature",
  "properties": {
    "iso:country":"CA",
    "sg:address":"1501 Lauzon Rd",
    "sg:city":"Windsor",
    "sg:classifiers":[
        {
            "category":"Food & Beverages",
            "subcategory":"Bakery",
            "type":"Retail Goods"
        }
    ],
    "sg:phone":"+1 519 974 1013",
    "sg:postcode":"N8S 3N4",
    "sg:province":"ON",
    "sg:tags":[
        "tea",
        "coffee",
        "doughnut"
    ],
    "wof:name":"Tim Hortons",
    "wof:placetype":"venue"
},
  "geometry": {"coordinates":[-82.9358825684,42.3203697205],"type":"Point"}
}