{
  "type": "Feature",
  "properties": {
    "addr:full":"2555 Sheffield Rd Ottawa ON K1B 3V6",
    "addr:housenumber":"2555",
    "addr:postcode":"k1b 3v6",
    "addr:street":"Sheffield Rd",
    "iso:country":"CA",
    "sg:address":"2555 Sheffield Rd",
    "sg:city":"Ottawa",
    "sg:classifiers":[
        {
            "category":"Wholesale",
            "subcategory":"Scrap",
            "type":"Manufacturing & Wholesale Goods"
        }
    ],
    "sg:phone":"+1 613 745 6000",
    "sg:postcode":"K1B 3V6",
    "sg:province":"ON",
    "sg:tags":[
        "recycling",
        "center"
    ],
    "wof:name":"Bakermet Inc",
    "wof:placetype":"venue"
},
  "geometry": {"coordinates":[-75.60732299999999,45.406422],"type":"Point"}
}