{
  "type": "Feature",
  "properties": {
    "addr:full":"8171 Seafair Dr Richmond BC V7C 1X3",
    "addr:housenumber":"8171",
    "addr:postcode":"v7c 1x3",
    "addr:street":"Seafair Dr",
    "iso:country":"CA",
    "sg:address":"8171 Seafair Dr",
    "sg:city":"Richmond",
    "sg:classifiers":[
        {
            "category":"Retail",
            "subcategory":"Laundry & Dry Cleaning",
            "type":"Services"
        }
    ],
    "sg:phone":"+1 604 275 2255",
    "sg:postcode":"V7C 1X3",
    "sg:province":"BC",
    "sg:tags":[
        "diaper"
    ],
    "wof:name":"Babykins Products Ltd",
    "wof:placetype":"venue"
},
  "geometry": {"coordinates":[-123.19152832,49.1541481018],"type":"Point"}
}