{
  "type": "Feature",
  "properties": {
    "addr:full":"4766 Wood Lane Rd Windermere BC V0B 2L0",
    "addr:housenumber":"4766",
    "addr:postcode":"bc v0b 2l0",
    "addr:street":"Wood Lane Rd",
    "iso:country":"CA",
    "sg:address":"4766 Wood Lane Rd",
    "sg:city":"Windermere",
    "sg:classifiers":[
        {
            "category":"Building & Trades",
            "subcategory":"Construction",
            "type":"Services"
        }
    ],
    "sg:phone":"+1 250 342 3461",
    "sg:postcode":"V0B 2L0",
    "sg:province":"BC",
    "sg:tags":[
        "plumbing",
        "contractor",
        "general"
    ],
    "wof:name":"Lakeview Plumbing Ltd",
    "wof:placetype":"venue"
},
  "geometry": {"coordinates":[-115.987892,50.467953],"type":"Point"}
}