{
  "type": "Feature",
  "properties": {
    "iso:country":"CA",
    "sg:address":"1171 Vicki Lane",
    "sg:city":"Mississauga",
    "sg:classifiers":[
        {
            "category":"Professional",
            "subcategory":"Accounting & Tax Preparation",
            "type":"Services"
        }
    ],
    "sg:phone":"+1 905 275 5521",
    "sg:postcode":"L5C 2X9",
    "sg:province":"ON",
    "sg:tags":[
        "accountant"
    ],
    "wof:name":"Mc Kerracher, Bruce D",
    "wof:placetype":"venue"
},
  "geometry": {"coordinates":[-79.64055633540001,43.5525550842],"type":"Point"}
}