{
  "type": "Feature",
  "properties": {
    "addr:full":"12147 Sullivan St Surrey BC V4A 3B4",
    "addr:housenumber":"12147",
    "addr:postcode":"v4a 3b4",
    "addr:street":"Sullivan St",
    "iso:country":"CA",
    "sg:address":"12147 Sullivan St",
    "sg:city":"Surrey",
    "sg:classifiers":[
        {
            "category":"Restaurant",
            "type":"Food & Drink"
        }
    ],
    "sg:phone":"+1 604 535 0880",
    "sg:postcode":"V4A 3B4",
    "sg:province":"BC",
    "wof:name":"Chestnuts By the Sea",
    "wof:placetype":"venue"
},
  "geometry": {"coordinates":[-122.885002,49.055897],"type":"Point"}
}