{
  "type": "Feature",
  "properties": {
    "iso:country":"CA",
    "sg:address":"11100 95 St",
    "sg:city":"High Level",
    "sg:classifiers":[
        {
            "category":"Freight",
            "type":"Transportation"
        }
    ],
    "sg:phone":"+1 780 926 3615",
    "sg:postcode":"T0H 1Z0",
    "sg:province":"AB",
    "sg:tags":[
        "trucking"
    ],
    "wof:name":"Grimshaw Trucking Ltd",
    "wof:placetype":"venue"
},
  "geometry": {"coordinates":[-117.15126800500001,58.4958648682],"type":"Point"}
}