{
  "type": "Feature",
  "properties": {
    "addr:full":"1140 Rue DE Senezergues Quebec QC G1R 3G3",
    "addr:housenumber":"1140",
    "addr:postcode":"g1r 3g3",
    "addr:street":"Rue De Senezergues",
    "iso:country":"CA",
    "sg:address":"1140 Rue DE Senezergues",
    "sg:city":"Quebec",
    "sg:classifiers":[
        {
            "category":"Organizations",
            "subcategory":"Religious Organization",
            "type":"Services"
        }
    ],
    "sg:phone":"+1 418 522 5251",
    "sg:postcode":"G1R 3G3",
    "sg:province":"QC",
    "wof:name":"Residence Ste-Genevieve",
    "wof:placetype":"venue"
},
  "geometry": {"coordinates":[-71.21849060060001,46.8061828613],"type":"Point"}
}