{
  "type": "Feature",
  "properties": {
    "iso:country":"CA",
    "sg:city":"Sainte-Sophie-DE-Levrard",
    "sg:classifiers":[
        {
            "category":"Health Services",
            "subcategory":"Health Practitioner",
            "type":"Services"
        }
    ],
    "sg:phone":"+1 819 288 5385",
    "sg:postcode":"G0X 3C0",
    "sg:province":"QC",
    "sg:tags":[
        "medicine",
        "orthopedic"
    ],
    "wof:name":"Paris Remi",
    "wof:placetype":"venue"
},
  "geometry": {"coordinates":[-72.1105422974,46.4268989563],"type":"Point"}
}