{
  "type": "Feature",
  "properties": {
    "addr:full":"323 Main St N Sauble Beach ON N0H 2G0",
    "addr:housenumber":"323",
    "addr:postcode":"n0h 2g0",
    "addr:street":"Main St N",
    "iso:country":"CA",
    "sg:address":"323 Main St N",
    "sg:city":"Sauble Beach",
    "sg:classifiers":[
        {
            "category":"Travel",
            "subcategory":"Hotels & Motels",
            "type":"Entertainment"
        }
    ],
    "sg:phone":"+1 519 422 1164",
    "sg:postcode":"N0H 2G0",
    "sg:province":"ON",
    "sg:tags":[
        "resort"
    ],
    "wof:name":"Golden Eagle Cottages",
    "wof:placetype":"venue"
},
  "geometry": {"coordinates":[-81.2673416138,44.6296730042],"type":"Point"}
}