{
  "type": "Feature",
  "properties": {
    "addr:full":"1208 138 Rte Neuville QC G0A 2R0",
    "addr:housenumber":"1208",
    "addr:postcode":"g0a 2r0",
    "addr:street":"138 Rte",
    "iso:country":"CA",
    "sg:address":"1208 138 Rte",
    "sg:city":"Neuville",
    "sg:classifiers":[
        {
            "category":"Restaurant",
            "type":"Food & Drink"
        }
    ],
    "sg:phone":"+1 418 876 2395",
    "sg:postcode":"G0A 2R0",
    "sg:province":"QC",
    "wof:name":"Maison DE Grand-Mere Enr",
    "wof:placetype":"venue"
},
  "geometry": {"coordinates":[-71.58532700000001,46.696613],"type":"Point"}
}