{
  "type": "Feature",
  "properties": {
    "addr:full":"4141 4th Ave Whitehorse YT Y1A 1J1",
    "addr:housenumber":"4141",
    "addr:postcode":"y1a 1j1",
    "addr:street":"4Th Ave",
    "iso:country":"CA",
    "sg:address":"4141 4th Ave",
    "sg:city":"Whitehorse",
    "sg:classifiers":[
        {
            "category":"Retail",
            "subcategory":"Auto Repair",
            "type":"Services"
        }
    ],
    "sg:phone":"+1 867 667 7231",
    "sg:postcode":"Y1A 1J1",
    "sg:province":"YT",
    "sg:tags":[
        "repairing",
        "automobile"
    ],
    "wof:name":"Whitehorse Performance Ctr",
    "wof:placetype":"venue"
},
  "geometry": {"coordinates":[-135.05789200000001,60.721474],"type":"Point"}
}