{
  "type": "Feature",
  "properties": {
    "addr:full":"182 Seventh Ave N Yorkton SK S3N 3Z2",
    "addr:housenumber":"182",
    "addr:postcode":"s3n 3z2",
    "addr:street":"Seventh Ave N",
    "iso:country":"CA",
    "sg:address":"182 Seventh Ave N",
    "sg:city":"Yorkton",
    "sg:classifiers":[
        {
            "category":"Building & Trades",
            "subcategory":"Construction",
            "type":"Services"
        }
    ],
    "sg:phone":"+1 306 783 8162",
    "sg:postcode":"S3N 3Z2",
    "sg:province":"SK",
    "sg:tags":[
        "general",
        "contractor"
    ],
    "wof:name":"Gross Construction Ltd",
    "wof:placetype":"venue"
},
  "geometry": {"coordinates":[-102.45462000000001,51.217415],"type":"Point"}
}