{
  "type": "Feature",
  "properties": {
    "addr:full":"St-Francois-Montmagny QC G0R 3A0",
    "addr:postcode":"g0r 3a0",
    "iso:country":"CA",
    "sg:city":"St-Francois-Montmagny",
    "sg:classifiers":[
        {
            "category":"Government",
            "subcategory":"Office",
            "type":"Public Place"
        }
    ],
    "sg:phone":"+1 418 259 2339",
    "sg:postcode":"G0R 3A0",
    "sg:province":"QC",
    "sg:tags":[
        "village"
    ],
    "wof:name":"Berthier-Sur-Mer Touristique",
    "wof:placetype":"venue"
},
  "geometry": {"coordinates":[-70.7139205933,46.8871536255],"type":"Point"}
}