{
  "type": "Feature",
  "properties": {
    "iso:country":"CA",
    "sg:city":"Vernon",
    "sg:classifiers":[
        {
            "category":"Wholesale",
            "subcategory":"Electrical",
            "type":"Manufacturing & Wholesale Goods"
        }
    ],
    "sg:phone":"+1 250 542 4275",
    "sg:postcode":"V1T 1P5",
    "sg:province":"BC",
    "sg:tags":[
        "repairing",
        "rebuilding",
        "supply",
        "battery",
        "automobile",
        "parts"
    ],
    "wof:name":"Vernon Battery Ltd",
    "wof:placetype":"venue"
},
  "geometry": {"coordinates":[-119.273803711,50.2656784058],"type":"Point"}
}