{
  "type": "Feature",
  "properties": {
    "addr:full":"190 Rue Saint-Joseph Levis QC G6V 1C9",
    "addr:housenumber":"190",
    "addr:postcode":"g6v 1c9",
    "addr:street":"Rue Saint-Joseph",
    "iso:country":"CA",
    "sg:address":"190 Rue Saint-Joseph",
    "sg:city":"Levis",
    "sg:classifiers":[
        {
            "category":"Health Services",
            "subcategory":"Hospital",
            "type":"Services"
        }
    ],
    "sg:phone":"+1 418 835 1967",
    "sg:postcode":"G6V 1C9",
    "sg:province":"QC",
    "sg:tags":[
        "mental",
        "association"
    ],
    "wof:name":"Contrevent Inc",
    "wof:placetype":"venue"
},
  "geometry": {"coordinates":[-71.169327,46.823059],"type":"Point"}
}