{
  "type": "Feature",
  "properties": {
    "iso:country":"CA",
    "sg:city":"Dorval",
    "sg:classifiers":[
        {
            "category":"Education",
            "subcategory":"Special Training",
            "type":"Public Place"
        }
    ],
    "sg:phone":"+1 514 631 9745",
    "sg:postcode":"H9S 3H4",
    "sg:province":"QC",
    "sg:tags":[
        "tutoring"
    ],
    "wof:name":"Strategic Learning Ctr Inc",
    "wof:placetype":"venue"
},
  "geometry": {"coordinates":[-73.7408828735,45.44323349],"type":"Point"}
}