{
  "type": "Feature",
  "properties": {
    "iso:country":"CA",
    "sg:address":"158 Dunlop St E",
    "sg:city":"Barrie",
    "sg:classifiers":[
        {
            "category":"Banks & Credit Unions",
            "subcategory":"Bank",
            "type":"Services"
        }
    ],
    "sg:phone":"+1 705 725 0440",
    "sg:postcode":"L4M 1B1",
    "sg:province":"ON",
    "sg:tags":[
        "loan",
        "real estate"
    ],
    "wof:name":"Mortgage Centre",
    "wof:placetype":"venue"
},
  "geometry": {"coordinates":[-79.683418,44.389481],"type":"Point"}
}