{
  "type": "Feature",
  "properties": {
    "iso:country":"CA",
    "sg:address":"8339 Bowness Rd NW",
    "sg:city":"Calgary",
    "sg:classifiers":[
        {
            "category":"Organizations",
            "subcategory":"Religious Organization",
            "type":"Services"
        }
    ],
    "sg:phone":"+1 403 288 3337",
    "sg:postcode":"T3B 0H5",
    "sg:province":"AB",
    "sg:tags":[
        "church"
    ],
    "wof:name":"Full Gospel Church W Calgary",
    "wof:placetype":"venue"
},
  "geometry": {"coordinates":[-114.206337,51.089325],"type":"Point"}
}