{
  "type": "Feature",
  "properties": {
    "addr:full":"184 Jackson St E Hamilton ON L8N 1L4",
    "addr:housenumber":"184",
    "addr:postcode":"l8n 1l4",
    "addr:street":"Jackson St E",
    "iso:country":"CA",
    "sg:address":"184 Jackson St E",
    "sg:city":"Hamilton",
    "sg:classifiers":[
        {
            "category":"Professional",
            "subcategory":"Lawyer & Legal Services",
            "type":"Services"
        }
    ],
    "sg:phone":"+1 905 577 6070",
    "sg:postcode":"L8N 1L4",
    "sg:province":"ON",
    "sg:tags":[
        "attorney"
    ],
    "wof:name":"Monica Scholz Law Office",
    "wof:placetype":"venue"
},
  "geometry": {"coordinates":[-79.86306,43.252537],"type":"Point"}
}