{
  "type": "Feature",
  "properties": {
    "iso:country":"CA",
    "sg:address":"170 Principal Rue",
    "sg:city":"Saint-Felix-DE-Dalquier",
    "sg:classifiers":[
        {
            "category":"Building & Trades",
            "subcategory":"Electrical",
            "type":"Services"
        }
    ],
    "sg:phone":"+1 819 732 9445",
    "sg:postcode":"J0Y 1G0",
    "sg:province":"QC",
    "sg:tags":[
        "air",
        "conditioning",
        "contractor",
        "system",
        "electric"
    ],
    "wof:name":"Entreprises Lanoix & Larouche",
    "wof:placetype":"venue"
},
  "geometry": {"coordinates":[-78.1139755249,48.6820602417],"type":"Point"}
}