{
  "type": "Feature",
  "properties": {
    "iso:country":"CA",
    "sg:city":"Edmonton",
    "sg:classifiers":[
        {
            "category":"Real Estate",
            "subcategory":"Real Estate Agent",
            "type":"Services"
        }
    ],
    "sg:phone":"+1 780 484 9321",
    "sg:postcode":"T5R 5Z3",
    "sg:province":"AB",
    "wof:name":"Calric Holdings",
    "wof:placetype":"venue"
},
  "geometry": {"coordinates":[-113.590545654,53.5217857361],"type":"Point"}
}