{
  "type": "Feature",
  "properties": {
    "addr:full":"121 Clancy Dr # 1108 Saskatoon SK S7M 5J9",
    "addr:housenumber":"121",
    "addr:postcode":"s7m 5j9",
    "addr:street":"Clancy Dr # 1108",
    "iso:country":"CA",
    "sg:address":"121 Clancy Dr # 1108",
    "sg:city":"Saskatoon",
    "sg:classifiers":[
        {
            "category":"Real Estate",
            "subcategory":"Real Estate Operator",
            "type":"Services"
        }
    ],
    "sg:phone":"+1 306 683 5654",
    "sg:postcode":"S7M 5J9",
    "sg:province":"SK",
    "sg:tags":[
        "apartment"
    ],
    "wof:name":"Reid Park Estates",
    "wof:placetype":"venue"
},
  "geometry": {"coordinates":[-106.722351074,52.1215400696],"type":"Point"}
}