{
  "type": "Feature",
  "properties": {
    "addr:full":"Calgary AB T2L 1Y2",
    "addr:postcode":"t2l 1y2",
    "iso:country":"CA",
    "sg:city":"Calgary",
    "sg:classifiers":[
        {
            "category":"Real Estate",
            "subcategory":"Real Estate Operator",
            "type":"Services"
        }
    ],
    "sg:phone":"+1 403 282 0544",
    "sg:postcode":"T2L 1Y2",
    "sg:province":"AB",
    "sg:tags":[
        "apartment"
    ],
    "wof:name":"Brentwood Heights",
    "wof:placetype":"venue"
},
  "geometry": {"coordinates":[-114.13898467999999,51.1048316956],"type":"Point"}
}