{
  "type": "Feature",
  "properties": {
    "addr:full":"North Vancouver BC V7L 2L3",
    "addr:postcode":"v7l 2l3",
    "iso:country":"CA",
    "sg:city":"North Vancouver",
    "sg:classifiers":[
        {
            "category":"Health Services",
            "subcategory":"Doctor",
            "type":"Services"
        }
    ],
    "sg:phone":"+1 604 984 9155",
    "sg:postcode":"V7L 2L3",
    "sg:province":"BC",
    "sg:tags":[
        "dentist"
    ],
    "wof:name":"Alan Ferguson Inc",
    "wof:placetype":"venue"
},
  "geometry": {"coordinates":[-123.071449,49.319859],"type":"Point"}
}