{
  "type": "Feature",
  "properties": {
    "addr:full":"Nepean ON K2E 1A3",
    "addr:postcode":"k2e 1a3",
    "iso:country":"CA",
    "sg:city":"Nepean",
    "sg:classifiers":[
        {
            "category":"Professional",
            "subcategory":"Accounting & Tax Preparation",
            "type":"Services"
        }
    ],
    "sg:phone":"+1 613 224 6808",
    "sg:postcode":"K2E 1A3",
    "sg:province":"ON",
    "sg:tags":[
        "accountant"
    ],
    "wof:name":"Abrams, Ira CA",
    "wof:placetype":"venue"
},
  "geometry": {"coordinates":[-75.72313699999999,45.338905],"type":"Point"}
}