{
  "type": "Feature",
  "properties": {
    "iso:country":"CA",
    "sg:city":"Chambly",
    "sg:classifiers":[
        {
            "category":"Personal",
            "subcategory":"Barber",
            "type":"Services"
        }
    ],
    "sg:phone":"+1 450 447 1770",
    "sg:postcode":"J3L 1W6",
    "sg:province":"QC",
    "wof:name":"Chambly Coiffure Pour Hommes",
    "wof:placetype":"venue"
},
  "geometry": {"coordinates":[-73.301758,45.45332],"type":"Point"}
}