{
  "type": "Feature",
  "properties": {
    "addr:full":"324 Main St Antigonish NS B2G 2C4",
    "addr:housenumber":"324",
    "addr:postcode":"b2g 2c4",
    "addr:street":"Main St",
    "iso:country":"CA",
    "sg:address":"324 Main St",
    "sg:city":"Antigonish",
    "sg:classifiers":[
        {
            "category":"Shopping",
            "subcategory":"Clothing, Apparel, & Fashions",
            "type":"Retail Goods"
        }
    ],
    "sg:phone":"+1 902 863 6670",
    "sg:postcode":"B2G 2C4",
    "sg:province":"NS",
    "sg:tags":[
        "tailor"
    ],
    "wof:name":"Sew Perfect Alterations",
    "wof:placetype":"venue"
},
  "geometry": {"coordinates":[-61.993439,45.622612],"type":"Point"}
}