{
  "type": "Feature",
  "properties": {
    "addr:full":"6361 Fallsview Blvd Niagara Falls ON L2G 3V9",
    "addr:housenumber":"6361",
    "addr:postcode":"l2g 3v9",
    "addr:street":"Fallsview Blvd",
    "iso:country":"CA",
    "sg:address":"6361 Fallsview Blvd",
    "sg:city":"Niagara Falls",
    "sg:classifiers":[
        {
            "category":"Wholesale",
            "subcategory":"Photographic Equipment",
            "type":"Manufacturing & Wholesale Goods"
        }
    ],
    "sg:phone":"+1 905 358 0922",
    "sg:postcode":"L2G 3V9",
    "sg:province":"ON",
    "sg:tags":[
        "audio"
    ],
    "wof:name":"Stagevision Rentals Inc",
    "wof:placetype":"venue"
},
  "geometry": {"coordinates":[-79.0829238892,43.082824707],"type":"Point"}
}