{
  "type": "Feature",
  "properties": {
    "addr:full":"75 Rue D'Auteuil Quebec QC G1R 4C3",
    "addr:housenumber":"75",
    "addr:postcode":"g1r 4c3",
    "addr:street":"Rue D'Auteuil",
    "iso:country":"CA",
    "sg:address":"75 Rue D'Auteuil",
    "sg:city":"Quebec",
    "sg:classifiers":[
        {
            "category":"Organizations",
            "subcategory":"Religious Organization",
            "type":"Services"
        }
    ],
    "sg:phone":"+1 418 692 3955",
    "sg:postcode":"G1R 4C3",
    "sg:province":"QC",
    "wof:name":"Foi Baha'Ie",
    "wof:placetype":"venue"
},
  "geometry": {"coordinates":[-71.211967,46.81197],"type":"Point"}
}