{
  "type": "Feature",
  "properties": {
    "iso:country":"CA",
    "sg:address":"20963 Dalton Rd",
    "sg:city":"Sutton West",
    "sg:classifiers":[
        {
            "category":"Travel",
            "subcategory":"Hotels & Motels",
            "type":"Entertainment"
        }
    ],
    "sg:phone":"+1 905 722 3640",
    "sg:postcode":"L0E 1R0",
    "sg:province":"ON",
    "wof:name":"Driftwood Motel",
    "wof:placetype":"venue"
},
  "geometry": {"coordinates":[-79.367027,44.314507],"type":"Point"}
}