{
  "type": "Feature",
  "properties": {
    "addr:full":"94 Rue Principale Granby QC J2G 2T4",
    "addr:housenumber":"94",
    "addr:postcode":"j2g 2t4",
    "addr:street":"Rue Principale",
    "iso:country":"CA",
    "sg:address":"94 Rue Principale",
    "sg:city":"Granby",
    "sg:classifiers":[
        {
            "category":"Food & Beverages",
            "subcategory":"Bakery",
            "type":"Retail Goods"
        }
    ],
    "sg:phone":"+1 450 375 9876",
    "sg:postcode":"J2G 2T4",
    "sg:province":"QC",
    "sg:tags":[
        "baker"
    ],
    "wof:name":"Boulangerie Bissonnette",
    "wof:placetype":"venue"
},
  "geometry": {"coordinates":[-72.7227401733,45.3982086182],"type":"Point"}
}