{
  "type": "Feature",
  "properties": {
    "addr:full":"Brampton ON L6S 5Y7",
    "addr:postcode":"l6s 5y7",
    "iso:country":"CA",
    "sg:city":"Brampton",
    "sg:classifiers":[
        {
            "category":"Shopping",
            "subcategory":"Pharmacy",
            "type":"Retail Goods"
        }
    ],
    "sg:phone":"+1 905 874 4288",
    "sg:postcode":"L6S 5Y7",
    "sg:province":"ON",
    "wof:name":"Lakeridge Pharmacy",
    "wof:placetype":"venue"
},
  "geometry": {"coordinates":[-79.74551391599999,43.7132453918],"type":"Point"}
}