{
  "type": "Feature",
  "properties": {
    "addr:full":"Kingston ON K7P 2X2",
    "addr:postcode":"k7p 2x2",
    "iso:country":"CA",
    "sg:city":"Kingston",
    "sg:classifiers":[
        {
            "category":"Shopping",
            "subcategory":"Clothing, Apparel, & Fashions",
            "type":"Retail Goods"
        }
    ],
    "sg:phone":"+1 613 384 9763",
    "sg:postcode":"K7P 2X2",
    "sg:province":"ON",
    "wof:name":"Expressions",
    "wof:placetype":"venue"
},
  "geometry": {"coordinates":[-76.58280181879999,44.2594223022],"type":"Point"}
}