{
  "type": "Feature",
  "properties": {
    "addr:full":"21 Overlea Blvd Toronto ON M4H 1P2",
    "addr:housenumber":"21",
    "addr:postcode":"m4h 1p2",
    "addr:street":"Overlea Blvd",
    "iso:country":"CA",
    "sg:address":"21 Overlea Blvd",
    "sg:city":"Toronto",
    "sg:classifiers":[
        {
            "category":"Real Estate",
            "subcategory":"Real Estate Operator",
            "type":"Services"
        }
    ],
    "sg:phone":"+1 416 425 7968",
    "sg:postcode":"M4H 1P2",
    "sg:province":"ON",
    "sg:tags":[
        "apartment"
    ],
    "wof:name":"Jockey Club Condominium Mgmt",
    "wof:placetype":"venue"
},
  "geometry": {"coordinates":[-79.35077699999999,43.703754],"type":"Point"}
}