{
  "type": "Feature",
  "properties": {
    "addr:full":"1967 Boul Rene-Levesque O Sillery QC G1S 1X8",
    "addr:housenumber":"1967",
    "addr:postcode":"g1s 1x8",
    "addr:street":"Boul Rene-Levesque O",
    "iso:country":"CA",
    "sg:address":"1967 Boul Rene-Levesque O",
    "sg:city":"Sillery",
    "sg:classifiers":[
        {
            "category":"Health Services",
            "subcategory":"Podiatrist",
            "type":"Services"
        }
    ],
    "sg:phone":"+1 418 688 1685",
    "sg:postcode":"G1S 1X8",
    "sg:province":"QC",
    "wof:name":"Leduc-Parino, Normande DPM",
    "wof:placetype":"venue"
},
  "geometry": {"coordinates":[-71.2574081421,46.7864456177],"type":"Point"}
}