{
  "type": "Feature",
  "properties": {
    "iso:country":"CA",
    "sg:address":"511 Mercy St",
    "sg:city":"Selkirk",
    "sg:classifiers":[
        {
            "category":"Home & Garden",
            "subcategory":"Building Materials",
            "type":"Retail Goods"
        }
    ],
    "sg:phone":"+1 204 482 8615",
    "sg:postcode":"R1A 2L3",
    "sg:province":"MB",
    "sg:tags":[
        "insulation",
        "heat"
    ],
    "wof:name":"Mgi Canada Inc",
    "wof:placetype":"venue"
},
  "geometry": {"coordinates":[-96.8780670166,50.1523399353],"type":"Point"}
}