{
  "type": "Feature",
  "properties": {
    "addr:full":"103 Queen St W Brampton ON L6Y 1M3",
    "addr:housenumber":"103",
    "addr:postcode":"l6y 1m3",
    "addr:street":"Queen St W",
    "iso:country":"CA",
    "sg:address":"103 Queen St W",
    "sg:city":"Brampton",
    "sg:classifiers":[
        {
            "category":"Insurance",
            "subcategory":"Insurance Agent",
            "type":"Services"
        }
    ],
    "sg:phone":"+1 905 451 2386",
    "sg:postcode":"L6Y 1M3",
    "sg:province":"ON",
    "wof:name":"Peel Mutual Insurance CO",
    "wof:placetype":"venue"
},
  "geometry": {"coordinates":[-79.76197052000001,43.6837692261],"type":"Point"}
}