{
  "type": "Feature",
  "properties": {
    "addr:full":"411 Lakeshore Bay Saskatoon SK S7J 3T5",
    "addr:housenumber":"411",
    "addr:postcode":"s7j 3t5",
    "addr:street":"Lakeshore Bay",
    "iso:country":"CA",
    "sg:address":"411 Lakeshore Bay",
    "sg:city":"Saskatoon",
    "sg:classifiers":[
        {
            "category":"Food & Beverages",
            "subcategory":"Specialty",
            "type":"Retail Goods"
        }
    ],
    "sg:phone":"+1 306 374 2250",
    "sg:postcode":"S7J 3T5",
    "sg:province":"SK",
    "sg:tags":[
        "health",
        "diet"
    ],
    "wof:name":"Watkins Products",
    "wof:placetype":"venue"
},
  "geometry": {"coordinates":[-106.59730529799999,52.0980606079],"type":"Point"}
}