{
  "type": "Feature",
  "properties": {
    "addr:full":"Edmonton AB T6A 0L4",
    "addr:postcode":"t6a 0l4",
    "iso:country":"CA",
    "sg:city":"Edmonton",
    "sg:classifiers":[
        {
            "category":"Banks & Credit Unions",
            "subcategory":"Investment Brokerage",
            "type":"Services"
        }
    ],
    "sg:phone":"+1 780 448 1777",
    "sg:postcode":"T6A 0L4",
    "sg:province":"AB",
    "sg:tags":[
        "funds",
        "mutual"
    ],
    "wof:name":"Pewter Financial Ltd",
    "wof:placetype":"venue"
},
  "geometry": {"coordinates":[-113.418007,53.539974],"type":"Point"}
}