{
  "type": "Feature",
  "properties": {
    "addr:full":"289 Bridgeland Ave North York ON M6A 1Z6",
    "addr:housenumber":"289",
    "addr:postcode":"m6a 1z6",
    "addr:street":"Bridgeland Ave",
    "iso:country":"CA",
    "sg:address":"289 Bridgeland Ave",
    "sg:city":"North York",
    "sg:classifiers":[
        {
            "category":"Building & Trades",
            "subcategory":"Landscaping Services",
            "type":"Services"
        }
    ],
    "sg:phone":"+1 416 782 6224",
    "sg:postcode":"M6A 1Z6",
    "sg:province":"ON",
    "sg:tags":[
        "landscape",
        "contractor"
    ],
    "wof:name":"Straightline Property Mntnc",
    "wof:placetype":"venue"
},
  "geometry": {"coordinates":[-79.47026824949999,43.7238693237],"type":"Point"}
}