{
  "type": "Feature",
  "properties": {
    "addr:full":"755 King St W Toronto ON M5V 1N4",
    "addr:housenumber":"755",
    "addr:postcode":"m5v 1n4",
    "addr:street":"King St W",
    "iso:country":"CA",
    "sg:address":"755 King St W",
    "sg:city":"Toronto",
    "sg:classifiers":[
        {
            "category":"Restaurant",
            "type":"Food & Drink"
        }
    ],
    "sg:phone":"+1 416 504 1045",
    "sg:postcode":"M5V 1N4",
    "sg:province":"ON",
    "wof:name":"Pizza Hut",
    "wof:placetype":"venue"
},
  "geometry": {"coordinates":[-79.40557098390001,43.6431846619],"type":"Point"}
}