{
  "type": "Feature",
  "properties": {
    "addr:full":"Surrey BC V3W 3E8",
    "addr:postcode":"v3w 3e8",
    "iso:country":"CA",
    "sg:city":"Surrey",
    "sg:classifiers":[
        {
            "category":"Building & Trades",
            "subcategory":"Construction",
            "type":"Services"
        }
    ],
    "sg:phone":"+1 604 596 1075",
    "sg:postcode":"V3W 3E8",
    "sg:province":"BC",
    "sg:tags":[
        "woodworker"
    ],
    "wof:name":"N & J Woodworking",
    "wof:placetype":"venue"
},
  "geometry": {"coordinates":[-122.87657900000001,49.152206],"type":"Point"}
}