{
  "type": "Feature",
  "properties": {
    "addr:full":"10490 Boul Pie-Ix Montreal-Nord QC H1H 4A1",
    "addr:housenumber":"10490",
    "addr:postcode":"h1h 4a1",
    "addr:street":"Boul Pie-Ix",
    "iso:country":"CA",
    "sg:address":"10490 Boul Pie-Ix",
    "sg:city":"Montreal-Nord",
    "sg:classifiers":[
        {
            "category":"Restaurant",
            "type":"Food & Drink"
        }
    ],
    "sg:phone":"+1 514 323 3942",
    "sg:postcode":"H1H 4A1",
    "sg:province":"QC",
    "wof:name":"Restaurant Le Petit Quebec",
    "wof:placetype":"venue"
},
  "geometry": {"coordinates":[-73.63417099999999,45.587612],"type":"Point"}
}