{
  "type": "Feature",
  "properties": {
    "addr:full":"12220 2E Ave Saint-Georges QC G5Y 1X4",
    "addr:housenumber":"12220",
    "addr:postcode":"g5y 1x4",
    "addr:street":"2E Ave",
    "iso:country":"CA",
    "sg:address":"12220 2E Ave",
    "sg:city":"Saint-Georges",
    "sg:classifiers":[
        {
            "category":"Social Services",
            "type":"Services"
        }
    ],
    "sg:phone":"+1 418 222 0777",
    "sg:postcode":"G5Y 1X4",
    "sg:province":"QC",
    "sg:tags":[
        "organization",
        "welfare"
    ],
    "wof:name":"Fondation Marc Doyon",
    "wof:placetype":"venue"
},
  "geometry": {"coordinates":[-70.67115020750001,46.1233482361],"type":"Point"}
}