{
  "type": "Feature",
  "properties": {
    "addr:full":"4366 Guelph Line Milton ON L9T 2X6",
    "addr:housenumber":"4366",
    "addr:postcode":"l9t 2x6",
    "addr:street":"Guelph Line",
    "iso:country":"CA",
    "sg:address":"4366 Guelph Line",
    "sg:city":"Milton",
    "sg:classifiers":[
        {
            "category":"Building & Trades",
            "subcategory":"Landscaping Services",
            "type":"Services"
        }
    ],
    "sg:phone":"+1 905 335 9469",
    "sg:postcode":"L9T 2X6",
    "sg:province":"ON",
    "sg:tags":[
        "lawn",
        "contractor",
        "landscape",
        "maintenance",
        "grounds"
    ],
    "wof:name":"Burlington Lawn",
    "wof:placetype":"venue"
},
  "geometry": {"coordinates":[-79.92626199999999,43.447472],"type":"Point"}
}