{
  "type": "Feature",
  "properties": {
    "addr:full":"12955 Ch Dumoulin Mirabel QC J7N 1L4",
    "addr:postcode":"12955;j7n 1l4",
    "addr:street":"Ch Dumoulin",
    "iso:country":"CA",
    "sg:address":"12955 Ch Dumoulin",
    "sg:city":"Mirabel",
    "sg:classifiers":[
        {
            "category":"Real Estate",
            "subcategory":"Surveying",
            "type":"Services"
        }
    ],
    "sg:phone":"+1 450 438 4424",
    "sg:postcode":"J7N 1L4",
    "sg:province":"QC",
    "sg:tags":[
        "surveyor"
    ],
    "wof:name":"Roy, Jean-Guy",
    "wof:placetype":"venue"
},
  "geometry": {"coordinates":[-74.0271148682,45.7435455322],"type":"Point"}
}