{
  "type": "Feature",
  "properties": {
    "addr:full":"35 Montressor Dr North York ON M2P 1Y9",
    "addr:housenumber":"35",
    "addr:postcode":"m2p 1y9",
    "addr:street":"Montressor Dr",
    "iso:country":"CA",
    "sg:address":"35 Montressor Dr",
    "sg:city":"North York",
    "sg:classifiers":[
        {
            "category":"Professional",
            "subcategory":"Computer Services",
            "type":"Services"
        }
    ],
    "sg:phone":"+1 416 223 7474",
    "sg:postcode":"M2P 1Y9",
    "sg:province":"ON",
    "sg:tags":[
        "consultant"
    ],
    "wof:name":"Rexcel Systems Inc",
    "wof:placetype":"venue"
},
  "geometry": {"coordinates":[-79.39238,43.756279],"type":"Point"}
}