{
  "type": "Feature",
  "properties": {
    "addr:full":"Onion Lake SK S0M 2E0",
    "addr:postcode":"s0m 2e0",
    "addr:street":"Onion Lake",
    "iso:country":"CA",
    "sg:city":"Onion Lake",
    "sg:classifiers":[
        {
            "category":"Organizations",
            "subcategory":"Community Association",
            "type":"Services"
        }
    ],
    "sg:phone":"+1 306 344 4747",
    "sg:postcode":"S0M 2E0",
    "sg:province":"SK",
    "sg:tags":[
        "native"
    ],
    "wof:name":"Onion Lake Family Svc",
    "wof:placetype":"venue"
},
  "geometry": {"coordinates":[-110.00147200000001,53.717442],"type":"Point"}
}