{
  "type": "Feature",
  "properties": {
    "addr:full":"9591 128 St Surrey BC V3V 6J2",
    "addr:housenumber":"9591",
    "addr:postcode":"v3v 6j2",
    "addr:street":"128 St",
    "iso:country":"CA",
    "sg:address":"9591 128 St",
    "sg:city":"Surrey",
    "sg:classifiers":[
        {
            "category":"Restaurant",
            "type":"Food & Drink"
        }
    ],
    "sg:phone":"+1 604 583 6622",
    "sg:postcode":"V3V 6J2",
    "sg:province":"BC",
    "wof:name":"Canadian 2 For 1 Pizza",
    "wof:placetype":"venue"
},
  "geometry": {"coordinates":[-122.868171692,49.1765136719],"type":"Point"}
}