{
  "type": "Feature",
  "properties": {
    "addr:full":"360 Ch DE LA Grande-Cote Boisbriand QC J7G 1B1",
    "addr:housenumber":"360",
    "addr:postcode":"j7g 1b1",
    "addr:street":"Ch De La Grande-Cote",
    "iso:country":"CA",
    "sg:address":"360 Ch DE LA Grande-Cote",
    "sg:city":"Boisbriand",
    "sg:classifiers":[
        {
            "category":"Personal",
            "subcategory":"Beauty Salon",
            "type":"Services"
        }
    ],
    "sg:phone":"+1 450 621 1222",
    "sg:postcode":"J7G 1B1",
    "sg:province":"QC",
    "wof:name":"Coiffure Guy Morel",
    "wof:placetype":"venue"
},
  "geometry": {"coordinates":[-73.83372497560001,45.6069221497],"type":"Point"}
}