{
  "type": "Feature",
  "properties": {
    "iso:country":"CA",
    "sg:city":"Regina",
    "sg:classifiers":[
        {
            "category":"Real Estate",
            "subcategory":"Real Estate Operator",
            "type":"Services"
        }
    ],
    "sg:phone":"+1 306 949 2811",
    "sg:postcode":"S4T 7P9",
    "sg:province":"SK",
    "sg:tags":[
        "apartment"
    ],
    "wof:name":"Medford Mews",
    "wof:placetype":"venue"
},
  "geometry": {"coordinates":[-104.669471741,50.4825210571],"type":"Point"}
}