{
  "type": "Feature",
  "properties": {
    "iso:country":"CA",
    "sg:address":"10555 Timberland Rd",
    "sg:city":"Surrey",
    "sg:classifiers":[
        {
            "category":"Freight",
            "type":"Transportation"
        }
    ],
    "sg:phone":"+1 604 953 0373",
    "sg:postcode":"V3V 3T3",
    "sg:province":"BC",
    "sg:tags":[
        "warehouse",
        "public"
    ],
    "wof:name":"Sylvan Distribution Ltd",
    "wof:placetype":"venue"
},
  "geometry": {"coordinates":[-122.902778626,49.1923904419],"type":"Point"}
}