{
  "type": "Feature",
  "properties": {
    "addr:full":"120 Main St Balcarres SK S0G 0C0",
    "addr:housenumber":"120",
    "addr:postcode":"s0g 0c0",
    "addr:street":"Main St",
    "iso:country":"CA",
    "sg:address":"120 Main St",
    "sg:city":"Balcarres",
    "sg:classifiers":[
        {
            "category":"Organizations",
            "subcategory":"Religious Organization",
            "type":"Services"
        }
    ],
    "sg:phone":"+1 306 771 2545",
    "sg:postcode":"S0G 0C0",
    "sg:province":"SK",
    "sg:tags":[
        "church"
    ],
    "wof:name":"Balcarres Baptist Church",
    "wof:placetype":"venue"
},
  "geometry": {"coordinates":[-103.54437299999999,50.802109],"type":"Point"}
}