{
  "type": "Feature",
  "properties": {
    "addr:full":"6053 Rideau Valley Dr N Manotick ON K4M 1B3",
    "addr:housenumber":"6053",
    "addr:postcode":"k4m 1b3",
    "addr:street":"Rideau Valley Dr N",
    "iso:country":"CA",
    "sg:address":"6053 Rideau Valley Dr N",
    "sg:city":"Manotick",
    "sg:classifiers":[
        {
            "category":"Recreation",
            "subcategory":"Marina",
            "type":"Entertainment"
        }
    ],
    "sg:phone":"+1 613 692 4083",
    "sg:postcode":"K4M 1B3",
    "sg:province":"ON",
    "wof:name":"Manotick Marina Inc",
    "wof:placetype":"venue"
},
  "geometry": {"coordinates":[-75.661079,45.209511],"type":"Point"}
}