{
  "type": "Feature",
  "properties": {
    "addr:full":"99 Quiring Bay Winnipeg MB R2G 1Y5",
    "addr:housenumber":"99",
    "addr:postcode":"r2g 1y5",
    "addr:street":"Quiring Bay",
    "iso:country":"CA",
    "sg:address":"99 Quiring Bay",
    "sg:city":"Winnipeg",
    "sg:classifiers":[
        {
            "category":"Building & Trades",
            "subcategory":"Construction",
            "type":"Services"
        }
    ],
    "sg:phone":"+1 204 667 6785",
    "sg:postcode":"R2G 1Y5",
    "sg:province":"MB",
    "sg:tags":[
        "dry wall",
        "contractor"
    ],
    "wof:name":"Talbot Drywall & Ceiling Tile",
    "wof:placetype":"venue"
},
  "geometry": {"coordinates":[-97.06600952150001,49.9418334961],"type":"Point"}
}