{
  "type": "Feature",
  "properties": {
    "addr:full":"2146 Robinson St # 2A Regina SK S4T 2P7",
    "addr:housenumber":"2146;2a",
    "addr:postcode":"s4t 2p7",
    "addr:street":"Robinson St #",
    "iso:country":"CA",
    "sg:address":"2146 Robinson St # 2A",
    "sg:city":"Regina",
    "sg:classifiers":[
        {
            "category":"Social Services",
            "type":"Services"
        }
    ],
    "sg:phone":"+1 306 347 2273",
    "sg:postcode":"S4T 2P7",
    "sg:province":"SK",
    "sg:tags":[
        "counseling",
        "counselor",
        "marriage",
        "family"
    ],
    "wof:name":"Caring Place",
    "wof:placetype":"venue"
},
  "geometry": {"coordinates":[-104.624084473,50.4447975159],"type":"Point"}
}