{
  "type": "Feature",
  "properties": {
    "addr:full":"2575 Midland Ave Scarborough ON M1S 1R3",
    "addr:housenumber":"2575",
    "addr:postcode":"m1s 1r3",
    "addr:street":"Midland Ave",
    "iso:country":"CA",
    "sg:address":"2575 Midland Ave",
    "sg:city":"Scarborough",
    "sg:classifiers":[
        {
            "category":"Social Services",
            "subcategory":"Child Care",
            "type":"Services"
        }
    ],
    "sg:phone":"+1 416 291 0726",
    "sg:postcode":"M1S 1R3",
    "sg:province":"ON",
    "sg:tags":[
        "kindergarten",
        "academic",
        "school"
    ],
    "wof:name":"Montessori Agincourt School",
    "wof:placetype":"venue"
},
  "geometry": {"coordinates":[-79.27866400000001,43.786129],"type":"Point"}
}