{
  "type": "Feature",
  "properties": {
    "addr:full":"10 Mosley St Aurora ON L4G 1G6",
    "addr:housenumber":"10",
    "addr:postcode":"l4g 1g6",
    "addr:street":"Mosley St",
    "iso:country":"CA",
    "sg:address":"10 Mosley St",
    "sg:city":"Aurora",
    "sg:classifiers":[
        {
            "category":"Professional",
            "subcategory":"Lawyer & Legal Services",
            "type":"Services"
        }
    ],
    "sg:phone":"+1 905 727 3127",
    "sg:postcode":"L4G 1G6",
    "sg:province":"ON",
    "sg:tags":[
        "attorney"
    ],
    "wof:name":"Smith, Clarke",
    "wof:placetype":"venue"
},
  "geometry": {"coordinates":[-79.4667434692,43.9982528687],"type":"Point"}
}