{
  "type": "Feature",
  "properties": {
    "addr:full":"550 Rue Saint-Georges Trois-Rivieres QC G9A 2K8",
    "addr:housenumber":"550",
    "addr:postcode":"g9a 2k8",
    "addr:street":"Rue Saint-Georges Trois-Rivieres",
    "iso:country":"CA",
    "sg:address":"550 Rue Saint-Georges",
    "sg:city":"Trois-Rivieres",
    "sg:classifiers":[
        {
            "category":"Organizations",
            "subcategory":"Labor Organization",
            "type":"Services"
        }
    ],
    "sg:phone":"+1 819 378 5055",
    "sg:postcode":"G9A 2K8",
    "sg:province":"QC",
    "wof:name":"Conseil Central Coeur-Quebec",
    "wof:placetype":"venue"
},
  "geometry": {"coordinates":[-72.54608899999999,46.341774],"type":"Point"}
}