{
  "type": "Feature",
  "properties": {
    "iso:country":"CA",
    "sg:address":"37 Rue Jacques-Cartier E",
    "sg:city":"Chicoutimi",
    "sg:classifiers":[
        {
            "category":"Professional",
            "subcategory":"Employment Agencies",
            "type":"Services"
        }
    ],
    "sg:phone":"+1 418 693 1049",
    "sg:postcode":"G7H 1X9",
    "sg:province":"QC",
    "sg:tags":[
        "consultant",
        "search",
        "executive",
        "resource",
        "human"
    ],
    "wof:name":"Ressources Arista Inc",
    "wof:placetype":"venue"
},
  "geometry": {"coordinates":[-71.067398,48.426773],"type":"Point"}
}