{
  "type": "Feature",
  "properties": {
    "addr:full":"520 Twelfth St New Westminster BC V3M 4H9",
    "addr:housenumber":"520",
    "addr:postcode":"v3m 4h9",
    "addr:street":"Twelfth St",
    "iso:country":"CA",
    "sg:address":"520 Twelfth St",
    "sg:city":"New Westminster",
    "sg:classifiers":[
        {
            "category":"Manufacturing",
            "subcategory":"Printing",
            "type":"Manufacturing & Wholesale Goods"
        }
    ],
    "sg:phone":"+1 604 525 5441",
    "sg:postcode":"V3M 4H9",
    "sg:province":"BC",
    "sg:tags":[
        "printer"
    ],
    "wof:name":"Royal Printers & Stationers",
    "wof:placetype":"venue"
},
  "geometry": {"coordinates":[-122.92939,49.206516],"type":"Point"}
}