{
  "type": "Feature",
  "properties": {
    "addr:full":"Edmonton AB T5J 2Z2",
    "addr:postcode":"t5j 2z2",
    "iso:country":"CA",
    "sg:city":"Edmonton",
    "sg:classifiers":[
        {
            "category":"Professional",
            "subcategory":"Lawyer & Legal Services",
            "type":"Services"
        }
    ],
    "sg:phone":"+1 780 425 3511",
    "sg:postcode":"T5J 2Z2",
    "sg:province":"AB",
    "sg:tags":[
        "attorney"
    ],
    "wof:name":"Gledhill Larocque",
    "wof:placetype":"venue"
},
  "geometry": {"coordinates":[-113.49343109100001,53.5435905457],"type":"Point"}
}