{
  "type": "Feature",
  "properties": {
    "addr:full":"5190 Willow Rd Smithers BC V0J 2N2",
    "addr:housenumber":"5190",
    "addr:postcode":"v0j 2n2",
    "addr:street":"Willow Rd",
    "iso:country":"CA",
    "sg:address":"5190 Willow Rd",
    "sg:city":"Smithers",
    "sg:classifiers":[
        {
            "category":"Wholesale",
            "subcategory":"Electrical",
            "type":"Manufacturing & Wholesale Goods"
        }
    ],
    "sg:phone":"+1 250 847 9846",
    "sg:postcode":"V0J 2N2",
    "sg:province":"BC",
    "sg:tags":[
        "fire",
        "equipment",
        "protection"
    ],
    "wof:name":"West Central Fire Protection",
    "wof:placetype":"venue"
},
  "geometry": {"coordinates":[-127.168128967,54.7828025818],"type":"Point"}
}