{
  "type": "Feature",
  "properties": {
    "addr:full":"63 Rue Fraserville Riviere-Du-Loup QC G5R 2B5",
    "addr:housenumber":"63",
    "addr:postcode":"g5r 2b5",
    "addr:street":"Rue Fraserville Riviere-Du-Loup",
    "iso:country":"CA",
    "sg:address":"63 Rue Fraserville",
    "sg:city":"Riviere-Du-Loup",
    "sg:classifiers":[
        {
            "category":"Food & Beverages",
            "subcategory":"Groceries & Convenience Stores",
            "type":"Retail Goods"
        }
    ],
    "sg:phone":"+1 418 862 8255",
    "sg:postcode":"G5R 2B5",
    "sg:province":"QC",
    "sg:tags":[
        "grocer"
    ],
    "wof:name":"Marche D'Amours Ltee",
    "wof:placetype":"venue"
},
  "geometry": {"coordinates":[-69.530052,47.823776],"type":"Point"}
}