{
  "type": "Feature",
  "properties": {
    "addr:full":"61 King William St #2 Huntsville ON P1H 1E5",
    "addr:housenumber":"61",
    "addr:postcode":"p1h 1e5",
    "addr:street":"King William St # 2",
    "iso:country":"CA",
    "sg:address":"61 King William St #2",
    "sg:city":"Huntsville",
    "sg:classifiers":[
        {
            "category":"Building & Trades",
            "subcategory":"Construction",
            "type":"Services"
        }
    ],
    "sg:phone":"+1 705 789 2425",
    "sg:postcode":"P1H 1E5",
    "sg:province":"ON",
    "sg:tags":[
        "equipment",
        "kitchen",
        "maker",
        "cabinet"
    ],
    "wof:name":"Wood Smiths of Muskoka",
    "wof:placetype":"venue"
},
  "geometry": {"coordinates":[-79.206566,45.332996],"type":"Point"}
}