{
  "type": "Feature",
  "properties": {
    "iso:country":"CA",
    "sg:address":"465 Church St",
    "sg:city":"Toronto",
    "sg:classifiers":[
        {
            "category":"Shopping",
            "type":"Retail Goods"
        }
    ],
    "sg:phone":"+1 416 586 9914",
    "sg:postcode":"M4Y 2C5",
    "sg:province":"ON",
    "sg:tags":[
        "miscellaneous",
        "store"
    ],
    "wof:name":"Priape",
    "wof:placetype":"venue"
},
  "geometry": {"coordinates":[-79.3801651001,43.6643409729],"type":"Point"}
}