{
  "type": "Feature",
  "properties": {
    "iso:country":"CA",
    "sg:address":"RR 1 673394 Hurontario St",
    "sg:city":"Orangeville",
    "sg:classifiers":[
        {
            "category":"Organizations",
            "subcategory":"Religious Organization",
            "type":"Services"
        }
    ],
    "sg:phone":"+1 519 941 0929",
    "sg:postcode":"L9W 2Y8",
    "sg:province":"ON",
    "wof:name":"Singing Waters Ministries",
    "wof:placetype":"venue"
},
  "geometry": {"coordinates":[-80.093491,43.920116],"type":"Point"}
}