{
  "type": "Feature",
  "properties": {
    "addr:full":"570 Denison St Markham ON L3R 1B9",
    "addr:housenumber":"570",
    "addr:postcode":"l3r 1b9",
    "addr:street":"Denison St",
    "iso:country":"CA",
    "sg:address":"570 Denison St",
    "sg:city":"Markham",
    "sg:classifiers":[
        {
            "category":"Manufacturing",
            "subcategory":"Printing",
            "type":"Manufacturing & Wholesale Goods"
        }
    ],
    "sg:phone":"+1 905 477 5898",
    "sg:postcode":"L3R 1B9",
    "sg:province":"ON",
    "sg:tags":[
        "typesetting"
    ],
    "wof:name":"Jay Tee Graphics Ltd",
    "wof:placetype":"venue"
},
  "geometry": {"coordinates":[-79.34279600000001,43.823872],"type":"Point"}
}