{
  "type": "Feature",
  "properties": {
    "iso:country":"CA",
    "sg:address":"570 Denison St",
    "sg:city":"Markham",
    "sg:classifiers":[
        {
            "category":"Manufacturing",
            "subcategory":"Printing",
            "type":"Manufacturing & Wholesale Goods"
        }
    ],
    "sg:phone":"+1 905 477 5898",
    "sg:postcode":"L3R 1B9",
    "sg:province":"ON",
    "sg:tags":[
        "typesetting"
    ],
    "wof:name":"Jay Tee Graphics Ltd",
    "wof:placetype":"venue"
},
  "geometry": {"coordinates":[-79.342796,43.823872],"type":"Point"}
}