{
  "type": "Feature",
  "properties": {
    "addr:full":"138 1st Ave Oak Lake MB R0M 1P0",
    "addr:housenumber":"138",
    "addr:postcode":"r0m 1p0",
    "addr:street":"1St Ave",
    "iso:country":"CA",
    "sg:address":"138 1st Ave",
    "sg:city":"Oak Lake",
    "sg:classifiers":[
        {
            "category":"Restaurant",
            "type":"Food & Drink"
        }
    ],
    "sg:phone":"+1 204 855 2089",
    "sg:postcode":"R0M 1P0",
    "sg:province":"MB",
    "wof:name":"Dandy Drive-Inn",
    "wof:placetype":"venue"
},
  "geometry": {"coordinates":[-100.633865356,49.7662696838],"type":"Point"}
}