{
  "type": "Feature",
  "properties": {
    "addr:full":"Plum Coulee MB R0G 1R0",
    "addr:postcode":"r0g 1r0",
    "iso:country":"CA",
    "sg:city":"Plum Coulee",
    "sg:classifiers":[
        {
            "category":"Autos & Motor Vehicles",
            "subcategory":"Fuel & Gas Station",
            "type":"Retail Goods"
        }
    ],
    "sg:phone":"+1 204 829 3332",
    "sg:postcode":"R0G 1R0",
    "sg:province":"MB",
    "sg:tags":[
        "oil"
    ],
    "wof:name":"Coulee Convenience",
    "wof:placetype":"venue"
},
  "geometry": {"coordinates":[-97.7672042847,49.1894493103],"type":"Point"}
}