{
  "type": "Feature",
  "properties": {
    "addr:full":"Surrey BC V3T 2X6",
    "addr:postcode":"v3t 2x6",
    "iso:country":"CA",
    "sg:city":"Surrey",
    "sg:classifiers":[
        {
            "category":"Food & Beverages",
            "subcategory":"Liquor & Beverages",
            "type":"Retail Goods"
        }
    ],
    "sg:phone":"+1 604 581 0511",
    "sg:postcode":"V3T 2X6",
    "sg:province":"BC",
    "sg:tags":[
        "store"
    ],
    "wof:name":"Whalley Government Liquor Str",
    "wof:placetype":"venue"
},
  "geometry": {"coordinates":[-122.845466614,49.1916389465],"type":"Point"}
}