{
  "type": "Feature",
  "properties": {
    "addr:full":"2659 Av Watt #5 Sainte-Foy QC G1P 3T2",
    "addr:housenumber":"2659;# 5",
    "addr:postcode":"g1p 3t2",
    "addr:street":"Av Watt;Sainte-Foy",
    "iso:country":"CA",
    "sg:address":"2659 Av Watt #5",
    "sg:city":"Sainte-Foy",
    "sg:classifiers":[
        {
            "category":"Professional",
            "subcategory":"Advertising",
            "type":"Services"
        }
    ],
    "sg:phone":"+1 418 658 1267",
    "sg:postcode":"G1P 3T2",
    "sg:province":"QC",
    "sg:tags":[
        "mailing",
        "shipping"
    ],
    "wof:name":"Post Express",
    "wof:placetype":"venue"
},
  "geometry": {"coordinates":[-71.3042755127,46.7875404358],"type":"Point"}
}