{
  "type": "Feature",
  "properties": {
    "addr:full":"10425 Kingsway NW Edmonton AB T5H 3W1",
    "addr:housenumber":"10425",
    "addr:postcode":"t5h 3w1",
    "addr:street":"Kingsway Nw",
    "iso:country":"CA",
    "sg:address":"10425 Kingsway NW",
    "sg:city":"Edmonton",
    "sg:classifiers":[
        {
            "category":"Organizations",
            "subcategory":"Professional Association",
            "type":"Services"
        }
    ],
    "sg:phone":"+1 780 425 8654",
    "sg:postcode":"T5H 3W1",
    "sg:province":"AB",
    "wof:name":"Royal Canadian Legion Kingsway",
    "wof:placetype":"venue"
},
  "geometry": {"coordinates":[-113.499923706,53.5569915771],"type":"Point"}
}