{
  "type": "Feature",
  "properties": {
    "addr:full":"850 Eglinton Ave E East York ON M4G 2L1",
    "addr:housenumber":"850",
    "addr:postcode":"m4g 2l1",
    "addr:street":"Eglinton Ave E",
    "iso:country":"CA",
    "sg:address":"850 Eglinton Ave E",
    "sg:city":"East York",
    "sg:classifiers":[
        {
            "category":"Shopping",
            "subcategory":"Books",
            "type":"Retail Goods"
        }
    ],
    "sg:phone":"+1 416 425 1555",
    "sg:postcode":"M4G 2L1",
    "sg:province":"ON",
    "sg:tags":[
        "dealer"
    ],
    "wof:name":"Autophile Car Books",
    "wof:placetype":"venue"
},
  "geometry": {"coordinates":[-79.365623,43.713554],"type":"Point"}
}