{
  "type": "Feature",
  "properties": {
    "iso:country":"CA",
    "sg:city":"Yorkton",
    "sg:classifiers":[
        {
            "category":"Real Estate",
            "subcategory":"Real Estate Operator",
            "type":"Services"
        }
    ],
    "sg:phone":"+1 306 782 6687",
    "sg:postcode":"S3N 3G4",
    "sg:province":"SK",
    "sg:tags":[
        "apartment",
        "rental",
        "agency"
    ],
    "wof:name":"Allanbrooke Apartments",
    "wof:placetype":"venue"
},
  "geometry": {"coordinates":[-102.485168457,51.2023162842],"type":"Point"}
}