{
  "type": "Feature",
  "properties": {
    "addr:full":"50 Duncairn Rd North York ON M3B 1C8",
    "addr:housenumber":"50",
    "addr:postcode":"m3b 1c8",
    "addr:street":"Duncairn Rd",
    "iso:country":"CA",
    "sg:address":"50 Duncairn Rd",
    "sg:city":"North York",
    "sg:classifiers":[
        {
            "category":"Social Services",
            "subcategory":"Child Care",
            "type":"Services"
        }
    ],
    "sg:phone":"+1 416 445 0602",
    "sg:postcode":"M3B 1C8",
    "sg:province":"ON",
    "wof:name":"Blue Wave Child Care Ctr",
    "wof:placetype":"venue"
},
  "geometry": {"coordinates":[-79.34951,43.740665],"type":"Point"}
}