{
  "type": "Feature",
  "properties": {
    "addr:full":"91 King St E Colborne ON K0K 1S0",
    "addr:housenumber":"91",
    "addr:postcode":"k0k 1s0",
    "addr:street":"King St E Colborne",
    "iso:country":"CA",
    "sg:address":"91 King St E",
    "sg:city":"Colborne",
    "sg:classifiers":[
        {
            "category":"Health Services",
            "subcategory":"Doctor",
            "type":"Services"
        }
    ],
    "sg:phone":"+1 905 355 2075",
    "sg:postcode":"K0K 1S0",
    "sg:province":"ON",
    "sg:tags":[
        "physician",
        "surgeon"
    ],
    "wof:name":"Hearnden, Trevor A MD",
    "wof:placetype":"venue"
},
  "geometry": {"coordinates":[-77.8816375732,44.0068054199],"type":"Point"}
}