{
  "type": "Feature",
  "properties": {
    "addr:full":"Calgary AB T2H 0K9",
    "addr:postcode":"t2h 0k9",
    "iso:country":"CA",
    "sg:city":"Calgary",
    "sg:classifiers":[
        {
            "category":"Health Services",
            "subcategory":"Podiatrist",
            "type":"Services"
        }
    ],
    "sg:phone":"+1 403 259 5241",
    "sg:postcode":"T2H 0K9",
    "sg:province":"AB",
    "wof:name":"Chinook Centre Podiatry",
    "wof:placetype":"venue"
},
  "geometry": {"coordinates":[-114.071830749,50.9961624146],"type":"Point"}
}