{
  "type": "Feature",
  "properties": {
    "addr:full":"67 King St Charlottetown PE C1A 1B4",
    "addr:housenumber":"67",
    "addr:postcode":"c1a 1b4",
    "addr:street":"King St",
    "iso:country":"CA",
    "sg:address":"67 King St",
    "sg:city":"Charlottetown",
    "sg:classifiers":[
        {
            "category":"Home & Garden",
            "subcategory":"Building Materials",
            "type":"Retail Goods"
        }
    ],
    "sg:phone":"+1 902 894 8043",
    "sg:postcode":"C1A 1B4",
    "sg:province":"PE",
    "sg:tags":[
        "glass",
        "window",
        "plate"
    ],
    "wof:name":"Economy Glass & Mirrors",
    "wof:placetype":"venue"
},
  "geometry": {"coordinates":[-63.126194,46.232166],"type":"Point"}
}