{
  "type": "Feature",
  "properties": {
    "addr:full":"Hull QC J8Z 1H1",
    "addr:postcode":"j8z 1h1",
    "iso:country":"CA",
    "sg:city":"Hull",
    "sg:classifiers":[
        {
            "category":"Real Estate",
            "subcategory":"Real Estate Operator",
            "type":"Services"
        }
    ],
    "sg:phone":"+1 819 777 8857",
    "sg:postcode":"J8Z 1H1",
    "sg:province":"QC",
    "sg:tags":[
        "apartment"
    ],
    "wof:name":"Montmagny",
    "wof:placetype":"venue"
},
  "geometry": {"coordinates":[-75.75881200000001,45.462002],"type":"Point"}
}