{
  "type": "Feature",
  "properties": {
    "addr:full":"Courtice ON L1E 2R7",
    "addr:postcode":"l1e 2r7",
    "iso:country":"CA",
    "sg:city":"Courtice",
    "sg:classifiers":[
        {
            "category":"Retail",
            "subcategory":"Funeral Services",
            "type":"Services"
        }
    ],
    "sg:phone":"+1 905 432 8484",
    "sg:postcode":"L1E 2R7",
    "sg:province":"ON",
    "sg:tags":[
        "director",
        "plan"
    ],
    "wof:name":"Courtice Funeral Chapel",
    "wof:placetype":"venue"
},
  "geometry": {"coordinates":[-78.79441799999999,43.909492],"type":"Point"}
}