{
  "type": "Feature",
  "properties": {
    "addr:full":"Westbank BC V4T 2G2",
    "addr:postcode":"v4t 2g2",
    "iso:country":"CA",
    "sg:city":"Westbank",
    "sg:classifiers":[
        {
            "category":"Autos & Motor Vehicles",
            "subcategory":"Auto Supplies",
            "type":"Retail Goods"
        }
    ],
    "sg:phone":"+1 250 707 0106",
    "sg:postcode":"V4T 2G2",
    "sg:province":"BC",
    "sg:tags":[
        "automobile",
        "parts"
    ],
    "wof:name":"Lordco Parts Ltd",
    "wof:placetype":"venue"
},
  "geometry": {"coordinates":[-119.63005099999999,49.829781],"type":"Point"}
}