{
  "type": "Feature",
  "properties": {
    "addr:full":"112 Colborne St E Whitby ON L1N 1V8",
    "addr:housenumber":"112",
    "addr:postcode":"l1n 1v8",
    "addr:street":"Colborne St E",
    "iso:country":"CA",
    "sg:address":"112 Colborne St E",
    "sg:city":"Whitby",
    "sg:classifiers":[
        {
            "category":"Restaurant",
            "type":"Food & Drink"
        }
    ],
    "sg:phone":"+1 905 666 9916",
    "sg:postcode":"L1N 1V8",
    "sg:province":"ON",
    "wof:name":"Crown & Firkin",
    "wof:placetype":"venue"
},
  "geometry": {"coordinates":[-78.94161224370001,43.8789634705],"type":"Point"}
}