{
  "type": "Feature",
  "properties": {
    "addr:full":"Calgary AB T2P 0M6",
    "addr:postcode":"t2p 0m6",
    "iso:country":"CA",
    "sg:city":"Calgary",
    "sg:classifiers":[
        {
            "category":"Mining & Drilling",
            "type":"Manufacturing & Wholesale Goods"
        }
    ],
    "sg:phone":"+1 403 269 8091",
    "sg:postcode":"T2P 0M6",
    "sg:province":"AB",
    "sg:tags":[
        "company",
        "oil"
    ],
    "wof:name":"Bing Energy Ltd",
    "wof:placetype":"venue"
},
  "geometry": {"coordinates":[-114.074310303,51.048828125],"type":"Point"}
}