{
  "type": "Feature",
  "properties": {
    "addr:full":"Cobden ON K0J 1K0",
    "addr:postcode":"k0j 1k0",
    "iso:country":"CA",
    "sg:city":"Cobden",
    "sg:classifiers":[
        {
            "category":"Restaurant",
            "type":"Food & Drink"
        }
    ],
    "sg:phone":"+1 613 646 7200",
    "sg:postcode":"K0J 1K0",
    "sg:province":"ON",
    "sg:tags":[
        "pizza"
    ],
    "wof:name":"Milano's Pizzeria",
    "wof:placetype":"venue"
},
  "geometry": {"coordinates":[-76.879822,45.628696],"type":"Point"}
}