{
  "type": "Feature",
  "properties": {
    "addr:full":"Norland ON K0M 2L0",
    "addr:postcode":"k0m 2l0",
    "iso:country":"CA",
    "sg:city":"Norland",
    "sg:classifiers":[
        {
            "category":"Travel",
            "subcategory":"Hotels & Motels",
            "type":"Entertainment"
        }
    ],
    "sg:phone":"+1 705 454 8298",
    "sg:postcode":"K0M 2L0",
    "sg:province":"ON",
    "wof:name":"Noble Motel & Restaurant",
    "wof:placetype":"venue"
},
  "geometry": {"coordinates":[-78.81755099999999,44.73019],"type":"Point"}
}