{
  "type": "Feature",
  "properties": {
    "iso:country":"CA",
    "sg:city":"Abbotsford",
    "sg:classifiers":[
        {
            "category":"Shopping",
            "subcategory":"Clothing, Apparel, & Fashions",
            "type":"Retail Goods"
        }
    ],
    "sg:phone":"+1 604 855 9166",
    "sg:postcode":"V2S 3T4",
    "sg:province":"BC",
    "sg:tags":[
        "shop",
        "bridal",
        "dancing",
        "supply"
    ],
    "wof:name":"Jazz-Ma-Tazz",
    "wof:placetype":"venue"
},
  "geometry": {"coordinates":[-122.290512,49.048042],"type":"Point"}
}