{
  "type": "Feature",
  "properties": {
    "addr:full":"7496 Edmonds St Burnaby BC V3N 1B2",
    "addr:housenumber":"7496",
    "addr:postcode":"v3n 1b2",
    "addr:street":"Edmonds St",
    "iso:country":"CA",
    "sg:address":"7496 Edmonds St",
    "sg:city":"Burnaby",
    "sg:classifiers":[
        {
            "category":"Wholesale",
            "subcategory":"Machinery & Supplies",
            "type":"Manufacturing & Wholesale Goods"
        }
    ],
    "sg:phone":"+1 250 852 6908",
    "sg:postcode":"V3N 1B2",
    "sg:province":"BC",
    "sg:tags":[
        "equipment",
        "bottler"
    ],
    "wof:name":"One Stop Pop & Bottle Recyclin",
    "wof:placetype":"venue"
},
  "geometry": {"coordinates":[-122.945068359,49.2217102051],"type":"Point"}
}