{
  "type": "Feature",
  "properties": {
    "iso:country":"CA",
    "sg:address":"246 Victoria St N",
    "sg:city":"Tweed",
    "sg:classifiers":[
        {
            "category":"Home & Garden",
            "subcategory":"Hardware",
            "type":"Retail Goods"
        }
    ],
    "sg:phone":"+1 613 478 2310",
    "sg:postcode":"K0K 3J0",
    "sg:province":"ON",
    "wof:name":"Miles Village Hardware & Gifts",
    "wof:placetype":"venue"
},
  "geometry": {"coordinates":[-77.3126754761,44.4768867493],"type":"Point"}
}