{
  "type": "Feature",
  "properties": {
    "addr:full":"670 Mountain Rd Moncton NB E1C 2P5",
    "addr:housenumber":"670",
    "addr:postcode":"e1c 2p5",
    "addr:street":"Mountain Rd",
    "iso:country":"CA",
    "sg:address":"670 Mountain Rd",
    "sg:city":"Moncton",
    "sg:classifiers":[
        {
            "category":"Autos & Motor Vehicles",
            "subcategory":"Automobile Sales",
            "type":"Retail Goods"
        }
    ],
    "sg:phone":"+1 506 383 2070",
    "sg:postcode":"E1C 2P5",
    "sg:province":"NB",
    "sg:tags":[
        "car",
        "dealer"
    ],
    "wof:name":"Murrays Used Cars Ltd",
    "wof:placetype":"venue"
},
  "geometry": {"coordinates":[-64.800179,46.098427],"type":"Point"}
}