{
  "type": "Feature",
  "properties": {
    "addr:full":"17 Barrie St Bradford ON L3Z 2B1",
    "addr:housenumber":"17",
    "addr:postcode":"l3z 2b1",
    "addr:street":"Barrie St",
    "iso:country":"CA",
    "sg:address":"17 Barrie St",
    "sg:city":"Bradford",
    "sg:classifiers":[
        {
            "category":"Shopping",
            "subcategory":"Used Merchandise",
            "type":"Retail Goods"
        }
    ],
    "sg:phone":"+1 905 775 3018",
    "sg:postcode":"L3Z 2B1",
    "sg:province":"ON",
    "sg:tags":[
        "second",
        "store",
        "hand"
    ],
    "wof:name":"Global Village Shoppe",
    "wof:placetype":"venue"
},
  "geometry": {"coordinates":[-79.5648193359,44.1146774292],"type":"Point"}
}