{
  "type": "Feature",
  "properties": {
    "addr:full":"247 Boul Tache O Montmagny QC G5V 3R8",
    "addr:housenumber":"247",
    "addr:postcode":"g5v 3r8",
    "addr:street":"Boul Tache O",
    "iso:country":"CA",
    "sg:address":"247 Boul Tache O",
    "sg:city":"Montmagny",
    "sg:phone":"+1 418 248 1116",
    "sg:postcode":"G5V 3R8",
    "sg:province":"QC",
    "sg:tags":[
        "oil"
    ],
    "wof:name":"Petrole Montmagny Inc",
    "wof:placetype":"venue"
},
  "geometry": {"coordinates":[-70.54890399999999,46.985256],"type":"Point"}
}