{
  "type": "Feature",
  "properties": {
    "addr:full":"Saint-Flavien QC G0S 2M0",
    "addr:postcode":"g0s 2m0",
    "iso:country":"CA",
    "sg:city":"Saint-Flavien",
    "sg:classifiers":[
        {
            "category":"Recreation",
            "type":"Entertainment"
        }
    ],
    "sg:phone":"+1 418 728 3144",
    "sg:postcode":"G0S 2M0",
    "sg:province":"QC",
    "sg:tags":[
        "center"
    ],
    "wof:name":"Chalet Des Sports",
    "wof:placetype":"venue"
},
  "geometry": {"coordinates":[-71.596977,46.512844],"type":"Point"}
}