{
  "type": "Feature",
  "properties": {
    "addr:full":"41 Rue Richelieu Saint-Jean-Sur-Richelieu QC J3B 6X2",
    "addr:housenumber":"41",
    "addr:postcode":"j3b 6x2",
    "addr:street":"Rue Richelieu",
    "iso:country":"CA",
    "sg:address":"41 Rue Richelieu",
    "sg:city":"Saint-Jean-Sur-Richelieu",
    "sg:classifiers":[
        {
            "category":"Government",
            "subcategory":"Office",
            "type":"Public Place"
        }
    ],
    "sg:phone":"+1 450 357 2273",
    "sg:postcode":"J3B 6X2",
    "sg:province":"QC",
    "sg:tags":[
        "village"
    ],
    "wof:name":"St-Jean-Sur-Rich Usine-Fltrtn",
    "wof:placetype":"venue"
},
  "geometry": {"coordinates":[-73.25057200000001,45.302708],"type":"Point"}
}