{
  "type": "Feature",
  "properties": {
    "addr:full":"302 2 Ave Thorhild AB T0A 3J0",
    "addr:housenumber":"302",
    "addr:postcode":"t0a 3j0",
    "addr:street":"2 Ave",
    "iso:country":"CA",
    "sg:address":"302 2 Ave",
    "sg:city":"Thorhild",
    "sg:classifiers":[
        {
            "category":"Social Services",
            "subcategory":"Adult Care",
            "type":"Services"
        }
    ],
    "sg:phone":"+1 780 398 3556",
    "sg:postcode":"T0A 3J0",
    "sg:province":"AB",
    "sg:tags":[
        "senior",
        "housing",
        "citizen"
    ],
    "wof:name":"Thorhild Senior Citizens Home",
    "wof:placetype":"venue"
},
  "geometry": {"coordinates":[-113.130638123,54.1534118652],"type":"Point"}
}