{
  "type": "Feature",
  "properties": {
    "addr:full":"PO Box 398 White River ON P0M 3G0",
    "addr:housenumber":"po",
    "addr:postcode":"p0m 3g0",
    "addr:street":"Box 398",
    "iso:country":"CA",
    "sg:address":"PO Box 398",
    "sg:city":"White River",
    "sg:classifiers":[
        {
            "category":"Organizations",
            "subcategory":"Religious Organization",
            "type":"Services"
        }
    ],
    "sg:phone":"+1 807 822 2342",
    "sg:postcode":"P0M 3G0",
    "sg:province":"ON",
    "sg:tags":[
        "church"
    ],
    "wof:name":"Pentecostal Christian Assembly",
    "wof:placetype":"venue"
},
  "geometry": {"coordinates":[-85.27481079099999,48.593120575],"type":"Point"}
}