{
  "type": "Feature",
  "properties": {
    "addr:full":"5713 198 St Langley BC V3A 1G5",
    "addr:housenumber":"5713",
    "addr:postcode":"v3a 1g5",
    "addr:street":"198 St",
    "iso:country":"CA",
    "sg:address":"5713 198 St",
    "sg:city":"Langley",
    "sg:classifiers":[
        {
            "category":"Government",
            "subcategory":"Office",
            "type":"Public Place"
        }
    ],
    "sg:phone":"+1 604 514 2910",
    "sg:postcode":"V3A 1G5",
    "sg:province":"BC",
    "sg:tags":[
        "village"
    ],
    "wof:name":"Langley Operations Ctr",
    "wof:placetype":"venue"
},
  "geometry": {"coordinates":[-122.673538208,49.1063690186],"type":"Point"}
}