{
  "type": "Feature",
  "properties": {
    "addr:full":"Port Coquitlam BC V3C 6G1",
    "addr:postcode":"v3c 6g1",
    "iso:country":"CA",
    "sg:city":"Port Coquitlam",
    "sg:classifiers":[
        {
            "category":"Building & Trades",
            "subcategory":"Construction",
            "type":"Services"
        }
    ],
    "sg:phone":"+1 604 945 8955",
    "sg:postcode":"V3C 6G1",
    "sg:province":"BC",
    "sg:tags":[
        "siding",
        "contractor"
    ],
    "wof:name":"Gentek Building Products Ltd",
    "wof:placetype":"venue"
},
  "geometry": {"coordinates":[-122.747825623,49.243976593],"type":"Point"}
}