{
  "type": "Feature",
  "properties": {
    "iso:country":"CA",
    "sg:address":"343 Rue Principale O",
    "sg:city":"Magog",
    "sg:classifiers":[
        {
            "category":"Building & Trades",
            "subcategory":"Landscaping Services",
            "type":"Services"
        }
    ],
    "sg:phone":"+1 819 868 2905",
    "sg:postcode":"J1X 2B1",
    "sg:province":"QC",
    "sg:tags":[
        "designer",
        "landscape",
        "contractor"
    ],
    "wof:name":"Roy, Alain",
    "wof:placetype":"venue"
},
  "geometry": {"coordinates":[-72.137878418,45.2624702454],"type":"Point"}
}