{
  "type": "Feature",
  "properties": {
    "addr:full":"Raymore SK S0A 3J0",
    "addr:postcode":"s0a 3j0",
    "iso:country":"CA",
    "sg:city":"Raymore",
    "sg:classifiers":[
        {
            "category":"Autos & Motor Vehicles",
            "subcategory":"Fuel & Gas Station",
            "type":"Retail Goods"
        }
    ],
    "sg:phone":"+1 306 746 2928",
    "sg:postcode":"S0A 3J0",
    "sg:province":"SK",
    "sg:tags":[
        "oil"
    ],
    "wof:name":"Raymore Esso",
    "wof:placetype":"venue"
},
  "geometry": {"coordinates":[-104.538033,51.408501],"type":"Point"}
}