{
  "type": "Feature",
  "properties": {
    "addr:full":"5415 272 St Langley BC V4W 1P1",
    "addr:housenumber":"5415",
    "addr:postcode":"v4w 1p1",
    "addr:street":"272 St",
    "iso:country":"CA",
    "sg:address":"5415 272 St",
    "sg:city":"Langley",
    "sg:classifiers":[
        {
            "category":"Freight",
            "type":"Transportation"
        }
    ],
    "sg:phone":"+1 604 857 2728",
    "sg:postcode":"V4W 1P1",
    "sg:province":"BC",
    "sg:tags":[
        "trucking"
    ],
    "wof:name":"T & P Trucking Ltd",
    "wof:placetype":"venue"
},
  "geometry": {"coordinates":[-122.471008301,49.1002883911],"type":"Point"}
}