{
  "type": "Feature",
  "properties": {
    "addr:full":"Markham ON L6E 1A4",
    "addr:postcode":"l6e 1a4",
    "iso:country":"CA",
    "sg:city":"Markham",
    "sg:classifiers":[
        {
            "category":"Wholesale",
            "subcategory":"Machinery & Supplies",
            "type":"Manufacturing & Wholesale Goods"
        }
    ],
    "sg:phone":"+1 905 471 0420",
    "sg:postcode":"L6E 1A4",
    "sg:province":"ON",
    "sg:tags":[
        "equipment",
        "conveyor",
        "material",
        "handling",
        "conveying"
    ],
    "wof:name":"Mc Kessock Engineering Ltd",
    "wof:placetype":"venue"
},
  "geometry": {"coordinates":[-79.26472473139999,43.9032173157],"type":"Point"}
}