{
  "type": "Feature",
  "properties": {
    "iso:country":"CA",
    "sg:address":"4799 Joyce Ave",
    "sg:city":"Powell River",
    "sg:classifiers":[
        {
            "category":"Autos & Motor Vehicles",
            "subcategory":"Fuel & Gas Station",
            "type":"Retail Goods"
        }
    ],
    "sg:phone":"+1 604 485 9721",
    "sg:postcode":"V8A 5P4",
    "sg:province":"BC",
    "sg:tags":[
        "oil"
    ],
    "wof:name":"Shell Food Store",
    "wof:placetype":"venue"
},
  "geometry": {"coordinates":[-124.52113300000001,49.846127],"type":"Point"}
}