{
  "type": "Feature",
  "properties": {
    "iso:country":"CA",
    "sg:address":"4645 Helen St",
    "sg:city":"Port Alberni",
    "sg:classifiers":[
        {
            "category":"Social Services",
            "subcategory":"Child Care",
            "type":"Services"
        }
    ],
    "sg:phone":"+1 250 723 5505",
    "sg:postcode":"V9Y 6P6",
    "sg:province":"BC",
    "wof:name":"Dinosaur Daycare",
    "wof:placetype":"venue"
},
  "geometry": {"coordinates":[-124.80785369900001,49.2612113953],"type":"Point"}
}