{
  "type": "Feature",
  "properties": {
    "addr:full":"Saint-Laurent QC H4R 2N1",
    "addr:postcode":"h4r 2n1",
    "iso:country":"CA",
    "sg:city":"Saint-Laurent",
    "sg:classifiers":[
        {
            "category":"Professional",
            "subcategory":"Management & Consulting",
            "type":"Services"
        }
    ],
    "sg:phone":"+1 514 331 1919",
    "sg:postcode":"H4R 2N1",
    "sg:province":"QC",
    "sg:tags":[
        "consultant",
        "business"
    ],
    "wof:name":"Max Stra T-J Inc",
    "wof:placetype":"venue"
},
  "geometry": {"coordinates":[-73.70565000000001,45.49633],"type":"Point"}
}