{
  "type": "Feature",
  "properties": {
    "addr:full":"51 Reenders Dr Winnipeg MB R2C 5E8",
    "addr:housenumber":"51",
    "addr:postcode":"r2c 5e8",
    "addr:street":"Reenders Dr",
    "iso:country":"CA",
    "sg:address":"51 Reenders Dr",
    "sg:city":"Winnipeg",
    "sg:classifiers":[
        {
            "category":"Restaurant",
            "type":"Food & Drink"
        }
    ],
    "sg:phone":"+1 204 661 8129",
    "sg:postcode":"R2C 5E8",
    "sg:province":"MB",
    "wof:name":"Olive Garden Italian Rstrnt",
    "wof:placetype":"venue"
},
  "geometry": {"coordinates":[-97.062416,49.901531],"type":"Point"}
}