{
  "type": "Feature",
  "properties": {
    "addr:full":"Sudbury ON P3A 4S5",
    "addr:postcode":"p3a 4s5",
    "iso:country":"CA",
    "sg:city":"Sudbury",
    "sg:classifiers":[
        {
            "category":"Real Estate",
            "subcategory":"Real Estate Operator",
            "type":"Services"
        }
    ],
    "sg:phone":"+1 705 566 8440",
    "sg:postcode":"P3A 4S5",
    "sg:province":"ON",
    "sg:tags":[
        "apartment"
    ],
    "wof:name":"Shelley Heights Apartments",
    "wof:placetype":"venue"
},
  "geometry": {"coordinates":[-80.9526748657,46.5331611633],"type":"Point"}
}