{
  "type": "Feature",
  "properties": {
    "addr:full":"599 Jackson Ave Winnipeg MB R3M 2J2",
    "addr:housenumber":"599",
    "addr:postcode":"r3m 2j2",
    "addr:street":"Jackson Ave",
    "iso:country":"CA",
    "sg:address":"599 Jackson Ave",
    "sg:city":"Winnipeg",
    "sg:classifiers":[
        {
            "category":"Building & Trades",
            "subcategory":"Construction",
            "type":"Services"
        }
    ],
    "sg:phone":"+1 204 453 9129",
    "sg:postcode":"R3M 2J2",
    "sg:province":"MB",
    "sg:tags":[
        "general",
        "contractor"
    ],
    "wof:name":"Mayer's Contract Interiors Ltd",
    "wof:placetype":"venue"
},
  "geometry": {"coordinates":[-97.149704,49.860199],"type":"Point"}
}