{
  "type": "Feature",
  "properties": {
    "addr:full":"2911 Keets Dr Coquitlam BC V3C 6J2",
    "addr:housenumber":"2911",
    "addr:postcode":"bc v3c 6j2",
    "addr:street":"Keets Dr",
    "iso:country":"CA",
    "sg:address":"2911 Keets Dr",
    "sg:city":"Coquitlam",
    "sg:classifiers":[
        {
            "category":"Building & Trades",
            "subcategory":"Construction",
            "type":"Services"
        }
    ],
    "sg:phone":"+1 604 250 3373",
    "sg:postcode":"V3C 6J2",
    "sg:province":"BC",
    "sg:tags":[
        "general",
        "contractor"
    ],
    "wof:name":"Gendi Construction Ltd",
    "wof:placetype":"venue"
},
  "geometry": {"coordinates":[-122.801391602,49.2616996765],"type":"Point"}
}