{
  "type": "Feature",
  "properties": {
    "addr:full":"1105 Des Pionniers Ave Balmoral NB E8E 1B5",
    "addr:housenumber":"1105",
    "addr:postcode":"e8e 1b5",
    "addr:street":"Des Pionniers Ave",
    "iso:country":"CA",
    "sg:address":"1105 Des Pionniers Ave",
    "sg:city":"Balmoral",
    "sg:classifiers":[
        {
            "category":"Restaurant",
            "type":"Food & Drink"
        }
    ],
    "sg:phone":"+1 506 826 3556",
    "sg:postcode":"E8E 1B5",
    "sg:province":"NB",
    "sg:tags":[
        "convenience",
        "store"
    ],
    "wof:name":"Depanneur LA Petite Ecole",
    "wof:placetype":"venue"
},
  "geometry": {"coordinates":[-66.443771,47.973259],"type":"Point"}
}