{
  "type": "Feature",
  "properties": {
    "iso:country":"CA",
    "sg:city":"Richmond",
    "sg:classifiers":[
        {
            "category":"Retail",
            "subcategory":"Auto Repair",
            "type":"Services"
        }
    ],
    "sg:phone":"+1 604 821 1133",
    "sg:postcode":"V6V 1J8",
    "sg:province":"BC",
    "sg:tags":[
        "body",
        "automobile",
        "painting"
    ],
    "wof:name":"Tristar Collision",
    "wof:placetype":"venue"
},
  "geometry": {"coordinates":[-123.085899353,49.1937446594],"type":"Point"}
}