{
  "type": "Feature",
  "properties": {
    "iso:country":"CA",
    "sg:city":"Vancouver",
    "sg:classifiers":[
        {
            "category":"Personal",
            "subcategory":"Tanning Parlor",
            "type":"Services"
        }
    ],
    "sg:phone":"+1 604 669 0028",
    "sg:postcode":"V6Z 1X9",
    "sg:province":"BC",
    "sg:tags":[
        "salon"
    ],
    "wof:name":"Sun City Tanning",
    "wof:placetype":"venue"
},
  "geometry": {"coordinates":[-123.12388610799999,49.2823562622],"type":"Point"}
}