{
  "type": "Feature",
  "properties": {
    "iso:country":"CA",
    "sg:address":"550 Comox Rd",
    "sg:city":"Courtenay",
    "sg:classifiers":[
        {
            "category":"Government",
            "subcategory":"Office",
            "type":"Public Place"
        }
    ],
    "sg:phone":"+1 250 334 6951",
    "sg:postcode":"V9N 3P6",
    "sg:province":"BC",
    "wof:name":"BC Transportation & Highways",
    "wof:placetype":"venue"
},
  "geometry": {"coordinates":[-124.991966248,49.6934280396],"type":"Point"}
}