{
  "type": "Feature",
  "properties": {
    "iso:country":"CA",
    "sg:city":"Prescott",
    "sg:classifiers":[
        {
            "category":"Wholesale",
            "subcategory":"Machinery & Supplies",
            "type":"Manufacturing & Wholesale Goods"
        }
    ],
    "sg:phone":"+1 613 925 4000",
    "sg:postcode":"K0E 1T0",
    "sg:province":"ON",
    "sg:tags":[
        "equipment",
        "winery",
        "wine"
    ],
    "wof:name":"Moonshine Supplies",
    "wof:placetype":"venue"
},
  "geometry": {"coordinates":[-75.5155334473,44.7085800171],"type":"Point"}
}