{
  "type": "Feature",
  "properties": {
    "iso:country":"CA",
    "sg:address":"2986 Ch DE Sainte-Catherine",
    "sg:city":"Rock Forest",
    "sg:classifiers":[
        {
            "category":"Professional",
            "subcategory":"Research",
            "type":"Services"
        }
    ],
    "sg:phone":"+1 819 566 8064",
    "sg:postcode":"J1N 3X9",
    "sg:province":"QC",
    "sg:tags":[
        "development",
        "laboratory"
    ],
    "wof:name":"Munger & Associes",
    "wof:placetype":"venue"
},
  "geometry": {"coordinates":[-71.94286346440001,45.3563613892],"type":"Point"}
}