{
  "type": "Feature",
  "properties": {
    "addr:full":"90 Front Rd Dildo NL A0B 1P0",
    "addr:housenumber":"90",
    "addr:postcode":"a0b 1p0",
    "addr:street":"Front Rd",
    "iso:country":"CA",
    "sg:address":"90 Front Rd",
    "sg:city":"Dildo",
    "sg:classifiers":[
        {
            "category":"Organizations",
            "subcategory":"Professional Association",
            "type":"Services"
        }
    ],
    "sg:phone":"+1 709 582 3234",
    "sg:postcode":"A0B 1P0",
    "sg:province":"NL",
    "sg:tags":[
        "club"
    ],
    "wof:name":"Suf Lodge",
    "wof:placetype":"venue"
},
  "geometry": {"coordinates":[-53.548573,47.56282],"type":"Point"}
}