{
  "type": "Feature",
  "properties": {
    "addr:full":"257 Rue Monseigneur-Courchesne Nicolet QC J3T 1B6",
    "addr:housenumber":"257",
    "addr:postcode":"j3t 1b6",
    "addr:street":"Rue Monseigneur-Courchesne",
    "iso:country":"CA",
    "sg:address":"257 Rue Monseigneur-Courchesne",
    "sg:city":"Nicolet",
    "sg:classifiers":[
        {
            "category":"Health Services",
            "subcategory":"Optometrist",
            "type":"Services"
        }
    ],
    "sg:phone":"+1 819 293 2029",
    "sg:postcode":"J3T 1B6",
    "sg:province":"QC",
    "wof:name":"Gestion Michel Morin Inc",
    "wof:placetype":"venue"
},
  "geometry": {"coordinates":[-72.6135253906,46.2277183533],"type":"Point"}
}