{
  "type": "Feature",
  "properties": {
    "iso:country":"CA",
    "sg:address":"3460 Rue Drummond",
    "sg:city":"Montreal",
    "sg:classifiers":[
        {
            "category":"Shopping",
            "subcategory":"Used Merchandise",
            "type":"Retail Goods"
        }
    ],
    "sg:phone":"+1 514 844 8445",
    "sg:postcode":"H3G 1Y1",
    "sg:province":"QC",
    "sg:tags":[
        "baker",
        "second",
        "store",
        "hand"
    ],
    "wof:name":"Varietes Drummond",
    "wof:placetype":"venue"
},
  "geometry": {"coordinates":[-73.579964,45.501259],"type":"Point"}
}