{
  "type": "Feature",
  "properties": {
    "addr:full":"Vancouver BC V6C 1A1",
    "addr:postcode":"v6c 1a1",
    "iso:country":"CA",
    "sg:city":"Vancouver",
    "sg:classifiers":[
        {
            "category":"Health Services",
            "subcategory":"Doctor",
            "type":"Services"
        }
    ],
    "sg:phone":"+1 604 683 2551",
    "sg:postcode":"V6C 1A1",
    "sg:province":"BC",
    "sg:tags":[
        "physician",
        "surgeon"
    ],
    "wof:name":"Mamacos, Mike MD",
    "wof:placetype":"venue"
},
  "geometry": {"coordinates":[-123.11431899999999,49.285721],"type":"Point"}
}