{
  "type": "Feature",
  "properties": {
    "addr:full":"111 Ch Thibodeau Cap-Pele NB E4N 2A8",
    "addr:housenumber":"111",
    "addr:postcode":"e4n 2a8",
    "addr:street":"Ch Thibodeau",
    "iso:country":"CA",
    "sg:address":"111 Ch Thibodeau",
    "sg:city":"Cap-Pele",
    "sg:classifiers":[
        {
            "category":"Personal",
            "subcategory":"Barber",
            "type":"Services"
        }
    ],
    "sg:phone":"+1 506 577 6197",
    "sg:postcode":"E4N 2A8",
    "sg:province":"NB",
    "wof:name":"Chez Anise",
    "wof:placetype":"venue"
},
  "geometry": {"coordinates":[-64.31952699999999,46.216454],"type":"Point"}
}