{
  "type": "Feature",
  "properties": {
    "addr:full":"9505 100 St Fort St John BC V1J 4N4",
    "addr:housenumber":"9505",
    "addr:postcode":"v1j 4n4",
    "addr:street":"100 St",
    "iso:country":"CA",
    "sg:address":"9505 100 St",
    "sg:city":"Fort St John",
    "sg:classifiers":[
        {
            "category":"Restaurant",
            "type":"Food & Drink"
        }
    ],
    "sg:phone":"+1 250 787 7979",
    "sg:postcode":"V1J 4N4",
    "sg:province":"BC",
    "wof:name":"Board Walk Cafe",
    "wof:placetype":"venue"
},
  "geometry": {"coordinates":[-120.847312927,56.241558075],"type":"Point"}
}