{
  "type": "Feature",
  "properties": {
    "addr:full":"10 Barnes Cres Humboldt SK S0K 2A0",
    "addr:housenumber":"10",
    "addr:postcode":"s0k 2a0",
    "addr:street":"Barnes Cres",
    "iso:country":"CA",
    "sg:address":"10 Barnes Cres",
    "sg:city":"Humboldt",
    "sg:classifiers":[
        {
            "category":"Health Services",
            "subcategory":"Nursing And Care Facility",
            "type":"Services"
        }
    ],
    "sg:phone":"+1 306 682 4584",
    "sg:postcode":"S0K 2A0",
    "sg:province":"SK",
    "sg:tags":[
        "personal",
        "home"
    ],
    "wof:name":"Connie's Care Home",
    "wof:placetype":"venue"
},
  "geometry": {"coordinates":[-105.14094543500001,52.205581665],"type":"Point"}
}