{
  "type": "Feature",
  "properties": {
    "addr:full":"803 Baker St Nelson BC V1L 4J8",
    "addr:housenumber":"803",
    "addr:postcode":"bc v1l 4j8",
    "addr:street":"Baker St",
    "iso:country":"CA",
    "sg:address":"803 Baker St",
    "sg:city":"Nelson",
    "sg:classifiers":[
        {
            "category":"Autos & Motor Vehicles",
            "subcategory":"Auto Supplies",
            "type":"Retail Goods"
        }
    ],
    "sg:phone":"+1 250 352 3542",
    "sg:postcode":"V1L 4J8",
    "sg:province":"BC",
    "sg:tags":[
        "automobile",
        "parts",
        "dealer"
    ],
    "wof:name":"Nelson Chrysler Jeep Eagle",
    "wof:placetype":"venue"
},
  "geometry": {"coordinates":[-117.289833,49.49361],"type":"Point"}
}