{
  "type": "Feature",
  "properties": {
    "iso:country":"CA",
    "sg:city":"Toronto",
    "sg:classifiers":[
        {
            "category":"Shopping",
            "subcategory":"Jewelry",
            "type":"Retail Goods"
        }
    ],
    "sg:phone":"+1 416 366 5851",
    "sg:postcode":"M5B 1M4",
    "sg:province":"ON",
    "sg:tags":[
        "jeweler"
    ],
    "wof:name":"Jennifer's Jewellers",
    "wof:placetype":"venue"
},
  "geometry": {"coordinates":[-79.37962341310001,43.6536903381],"type":"Point"}
}