{
  "type": "Feature",
  "properties": {
    "addr:full":"4555 Kingsway # 1200 Burnaby BC V5H 4T8",
    "addr:housenumber":"4555;# 1200",
    "addr:postcode":"v5h 4t8",
    "addr:street":"Kingsway",
    "iso:country":"CA",
    "sg:address":"4555 Kingsway # 1200",
    "sg:city":"Burnaby",
    "sg:classifiers":[
        {
            "category":"Building & Trades",
            "subcategory":"Construction",
            "type":"Services"
        }
    ],
    "sg:phone":"+1 604 299 1363",
    "sg:postcode":"V5H 4T8",
    "sg:province":"BC",
    "sg:tags":[
        "general",
        "contractor"
    ],
    "wof:name":"Bosa Construction Inc",
    "wof:placetype":"venue"
},
  "geometry": {"coordinates":[-123.00335699999999,49.229858],"type":"Point"}
}