{
  "type": "Feature",
  "properties": {
    "addr:full":"Beaupre QC G0A 1E0",
    "addr:postcode":"g0a 1e0",
    "addr:street":"Beaupre",
    "iso:country":"CA",
    "sg:city":"Beaupre",
    "sg:classifiers":[
        {
            "category":"Personal",
            "subcategory":"Beauty Salon",
            "type":"Services"
        }
    ],
    "sg:phone":"+1 418 827 4444",
    "sg:postcode":"G0A 1E0",
    "sg:province":"QC",
    "wof:name":"Salon Elle",
    "wof:placetype":"venue"
},
  "geometry": {"coordinates":[-70.892754,47.045551],"type":"Point"}
}