{
  "type": "Feature",
  "properties": {
    "addr:full":"Brampton ON L6W 4R6",
    "addr:postcode":"l6w 4r6",
    "iso:country":"CA",
    "sg:city":"Brampton",
    "sg:classifiers":[
        {
            "category":"Professional",
            "subcategory":"Lawyer & Legal Services",
            "type":"Services"
        }
    ],
    "sg:phone":"+1 905 454 4141",
    "sg:postcode":"L6W 4R6",
    "sg:province":"ON",
    "sg:tags":[
        "attorney"
    ],
    "wof:name":"Brown, Ed",
    "wof:placetype":"venue"
},
  "geometry": {"coordinates":[-79.7220001221,43.6601409912],"type":"Point"}
}