{
  "type": "Feature",
  "properties": {
    "addr:full":"271 Rue Bellevue LA Tuque QC G9X 1Y8",
    "addr:housenumber":"271",
    "addr:postcode":"g9x 1y8",
    "addr:street":"Rue Bellevue",
    "iso:country":"CA",
    "sg:address":"271 Rue Bellevue",
    "sg:city":"LA Tuque",
    "sg:classifiers":[
        {
            "category":"Professional",
            "type":"Services"
        }
    ],
    "sg:phone":"+1 819 676 8080",
    "sg:postcode":"G9X 1Y8",
    "sg:province":"QC",
    "sg:tags":[
        "establishment",
        "explosive"
    ],
    "wof:name":"Gilbro Sisco Inc",
    "wof:placetype":"venue"
},
  "geometry": {"coordinates":[-72.7863616943,47.4264907837],"type":"Point"}
}