{
  "type": "Feature",
  "properties": {
    "addr:full":"20 Tuxedo Crt Scarborough ON M1G 3S5",
    "addr:housenumber":"20",
    "addr:postcode":"m1g 3s5",
    "addr:street":"Tuxedo Crt",
    "iso:country":"CA",
    "sg:address":"20 Tuxedo Crt",
    "sg:city":"Scarborough",
    "sg:classifiers":[
        {
            "category":"Professional",
            "subcategory":"Computer Services",
            "type":"Services"
        }
    ],
    "sg:phone":"+1 416 439 8347",
    "sg:postcode":"M1G 3S5",
    "sg:province":"ON",
    "sg:tags":[
        "consultant"
    ],
    "wof:name":"Inram Technologies Inc",
    "wof:placetype":"venue"
},
  "geometry": {"coordinates":[-79.23156738279999,43.7796974182],"type":"Point"}
}