{
  "type": "Feature",
  "properties": {
    "addr:full":"209 Main St Biggar SK S0K 0M0",
    "addr:housenumber":"209",
    "addr:postcode":"s0k 0m0",
    "addr:street":"Main St",
    "iso:country":"CA",
    "sg:address":"209 Main St",
    "sg:city":"Biggar",
    "sg:classifiers":[
        {
            "category":"Insurance",
            "subcategory":"Insurance Agent",
            "type":"Services"
        }
    ],
    "sg:phone":"+1 306 948 3433",
    "sg:postcode":"S0K 0M0",
    "sg:province":"SK",
    "wof:name":"Biggar Agencies 1996",
    "wof:placetype":"venue"
},
  "geometry": {"coordinates":[-107.985923767,52.0551300049],"type":"Point"}
}