{
  "type": "Feature",
  "properties": {
    "iso:country":"CA",
    "sg:address":"7463 Industrial Rd",
    "sg:city":"Lantzville",
    "sg:classifiers":[
        {
            "category":"Home & Garden",
            "subcategory":"Building Materials",
            "type":"Retail Goods"
        }
    ],
    "sg:phone":"+1 250 390 2122",
    "sg:postcode":"V0R 2H0",
    "sg:province":"BC",
    "sg:tags":[
        "truss"
    ],
    "wof:name":"Hi-Tec Industries Ltd",
    "wof:placetype":"venue"
},
  "geometry": {"coordinates":[-124.083114624,49.2452697754],"type":"Point"}
}