{
  "type": "Feature",
  "properties": {
    "addr:full":"682 Rang Saint-Etienne Saint-Placide QC J0V 2B0",
    "addr:housenumber":"682",
    "addr:postcode":"j0v 2b0",
    "addr:street":"Rang Saint-Etienne",
    "iso:country":"CA",
    "sg:address":"682 Rang Saint-Etienne",
    "sg:city":"Saint-Placide",
    "sg:classifiers":[
        {
            "category":"Building & Trades",
            "subcategory":"Landscaping Services",
            "type":"Services"
        }
    ],
    "sg:phone":"+1 450 258 2530",
    "sg:postcode":"J0V 2B0",
    "sg:province":"QC",
    "sg:tags":[
        "landscape",
        "contractor"
    ],
    "wof:name":"Laviolette Daniel Paysagiste",
    "wof:placetype":"venue"
},
  "geometry": {"coordinates":[-74.147835,45.549061],"type":"Point"}
}