{
  "type": "Feature",
  "properties": {
    "addr:full":"Delisle SK S0L 0P0",
    "addr:postcode":"s0l 0p0",
    "addr:street":"Delisle",
    "iso:country":"CA",
    "sg:city":"Delisle",
    "sg:classifiers":[
        {
            "category":"Sports & Exercise",
            "subcategory":"Golf",
            "type":"Entertainment"
        }
    ],
    "sg:phone":"+1 306 493 3288",
    "sg:postcode":"S0L 0P0",
    "sg:province":"SK",
    "sg:tags":[
        "course"
    ],
    "wof:name":"Delisle Golf Course",
    "wof:placetype":"venue"
},
  "geometry": {"coordinates":[-107.13143158,51.9236030579],"type":"Point"}
}