{
  "type": "Feature",
  "properties": {
    "addr:full":"46 Panorama Crt Etobicoke ON M9V 4A4",
    "addr:housenumber":"46",
    "addr:postcode":"m9v 4a4",
    "addr:street":"Panorama Crt",
    "iso:country":"CA",
    "sg:address":"46 Panorama Crt",
    "sg:city":"Etobicoke",
    "sg:classifiers":[
        {
            "category":"Retail",
            "subcategory":"Laundry & Dry Cleaning",
            "type":"Services"
        }
    ],
    "sg:phone":"+1 416 744 0264",
    "sg:postcode":"M9V 4A4",
    "sg:province":"ON",
    "sg:tags":[
        "cleaners"
    ],
    "wof:name":"Panorama Cleaners",
    "wof:placetype":"venue"
},
  "geometry": {"coordinates":[-79.57963562010001,43.7474746704],"type":"Point"}
}