{
  "type": "Feature",
  "properties": {
    "addr:full":"3092 Rue Wilfrid-Simard LA Baie QC G7B 4C2",
    "addr:housenumber":"3092",
    "addr:postcode":"g7b 4c2",
    "addr:street":"Rue Wilfrid-Simard",
    "iso:country":"CA",
    "sg:address":"3092 Rue Wilfrid-Simard",
    "sg:city":"LA Baie",
    "sg:classifiers":[
        {
            "category":"Personal",
            "subcategory":"Beauty Salon",
            "type":"Services"
        }
    ],
    "sg:phone":"+1 418 544 3580",
    "sg:postcode":"G7B 4C2",
    "sg:province":"QC",
    "wof:name":"Salon DE Coiffure Guylaine Enr",
    "wof:placetype":"venue"
},
  "geometry": {"coordinates":[-70.855133,48.311584],"type":"Point"}
}