{
  "type": "Feature",
  "properties": {
    "addr:full":"10159 101 St NW Edmonton AB T5J 0T6",
    "addr:housenumber":"10159",
    "addr:postcode":"t5j 0t6",
    "addr:street":"101 St Nw",
    "iso:country":"CA",
    "sg:address":"10159 101 St NW",
    "sg:city":"Edmonton",
    "sg:classifiers":[
        {
            "category":"Shopping",
            "subcategory":"Photographic Equipment",
            "type":"Retail Goods"
        }
    ],
    "sg:phone":"+1 780 423 2336",
    "sg:postcode":"T5J 0T6",
    "sg:province":"AB",
    "sg:tags":[
        "photo",
        "finishing"
    ],
    "wof:name":"Mc Bain Camera Ltd",
    "wof:placetype":"venue"
},
  "geometry": {"coordinates":[-113.493484497,53.5422058105],"type":"Point"}
}