{
  "type": "Feature",
  "properties": {
    "addr:full":"11 Battle St Thorold ON L2V 3W3",
    "addr:housenumber":"11",
    "addr:postcode":"l2v 3w3",
    "addr:street":"Battle St",
    "iso:country":"CA",
    "sg:address":"11 Battle St",
    "sg:city":"Thorold",
    "sg:classifiers":[
        {
            "category":"Home & Garden",
            "subcategory":"Building Materials",
            "type":"Retail Goods"
        }
    ],
    "sg:phone":"+1 905 680 4792",
    "sg:postcode":"L2V 3W3",
    "sg:province":"ON",
    "sg:tags":[
        "windows"
    ],
    "wof:name":"Bda Home Improvements Inc",
    "wof:placetype":"venue"
},
  "geometry": {"coordinates":[-79.20314788819999,43.1162185669],"type":"Point"}
}