{
  "type": "Feature",
  "properties": {
    "iso:country":"CA",
    "sg:city":"L'Anse Au Loup",
    "sg:classifiers":[
        {
            "category":"Government",
            "subcategory":"Office",
            "type":"Public Place"
        }
    ],
    "sg:phone":"+1 709 927 5210",
    "sg:postcode":"A0K 3L0",
    "sg:province":"NL",
    "wof:name":"Canada Member of Parliament",
    "wof:placetype":"venue"
},
  "geometry": {"coordinates":[-56.8312301636,51.5265693665],"type":"Point"}
}