{
  "type": "Feature",
  "properties": {
    "addr:full":"36 Sykes St S Meaford ON N4L 1P4",
    "addr:housenumber":"36",
    "addr:postcode":"n4l 1p4",
    "addr:street":"Sykes St S",
    "iso:country":"CA",
    "sg:address":"36 Sykes St S",
    "sg:city":"Meaford",
    "sg:classifiers":[
        {
            "category":"Restaurant",
            "type":"Food & Drink"
        }
    ],
    "sg:phone":"+1 519 538 2567",
    "sg:postcode":"N4L 1P4",
    "sg:province":"ON",
    "sg:tags":[
        "sandwich"
    ],
    "wof:name":"Subway Sandwiches & Salads",
    "wof:placetype":"venue"
},
  "geometry": {"coordinates":[-80.5911407471,44.6052970886],"type":"Point"}
}