{
  "type": "Feature",
  "properties": {
    "iso:country":"CA",
    "sg:city":"Montreal",
    "sg:classifiers":[
        {
            "category":"Social Services",
            "subcategory":"Child Care",
            "type":"Services"
        }
    ],
    "sg:phone":"+1 514 331 7449",
    "sg:postcode":"H4J 1J4",
    "sg:province":"QC",
    "wof:name":"Garderie Centre Educatif",
    "wof:placetype":"venue"
},
  "geometry": {"coordinates":[-73.708359,45.53112],"type":"Point"}
}