{
  "type": "Feature",
  "properties": {
    "addr:full":"170 University Park Dr Regina SK S4V 1A3",
    "addr:housenumber":"170",
    "addr:postcode":"s4v 1a3",
    "addr:street":"University Park Dr",
    "iso:country":"CA",
    "sg:address":"170 University Park Dr",
    "sg:city":"Regina",
    "sg:classifiers":[
        {
            "category":"Restaurant",
            "type":"Food & Drink"
        }
    ],
    "sg:phone":"+1 306 789 2245",
    "sg:postcode":"S4V 1A3",
    "sg:province":"SK",
    "wof:name":"O B Kitchen",
    "wof:placetype":"venue"
},
  "geometry": {"coordinates":[-104.558502,50.431675],"type":"Point"}
}