{
  "type": "Feature",
  "properties": {
    "addr:full":"2290 Rue Jean-Perrin Quebec QC G2C 1T9",
    "addr:housenumber":"2290",
    "addr:postcode":"g2c 1t9",
    "addr:street":"Rue Jean-Perrin",
    "iso:country":"CA",
    "sg:address":"2290 Rue Jean-Perrin",
    "sg:city":"Quebec",
    "sg:classifiers":[
        {
            "category":"Social Services",
            "subcategory":"Child Care",
            "type":"Services"
        }
    ],
    "sg:phone":"+1 418 842 2521",
    "sg:postcode":"G2C 1T9",
    "sg:province":"QC",
    "wof:name":"Regroupement Des Ctr-Petite",
    "wof:placetype":"venue"
},
  "geometry": {"coordinates":[-71.305801,46.824223],"type":"Point"}
}