{
  "type": "Feature",
  "properties": {
    "addr:full":"263 Barton St #11 Stoney Creek ON L8E 2K4",
    "addr:housenumber":"263;11",
    "addr:postcode":"l8e 2k4",
    "addr:street":"Barton St #",
    "iso:country":"CA",
    "sg:address":"263 Barton St #11",
    "sg:city":"Stoney Creek",
    "sg:classifiers":[
        {
            "category":"Manufacturing",
            "subcategory":"Tools & Machinery",
            "type":"Manufacturing & Wholesale Goods"
        }
    ],
    "sg:phone":"+1 905 664 1856",
    "sg:postcode":"L8E 2K4",
    "sg:province":"ON",
    "sg:tags":[
        "machine",
        "shop"
    ],
    "wof:name":"Rajic Machine Shop Ltd",
    "wof:placetype":"venue"
},
  "geometry": {"coordinates":[-79.7308807373,43.2304344177],"type":"Point"}
}