{
  "type": "Feature",
  "properties": {
    "addr:full":"444 Academy Rd Winnipeg MB R3N 0C4",
    "addr:housenumber":"444",
    "addr:postcode":"r3n 0c4",
    "addr:street":"Academy Rd",
    "iso:country":"CA",
    "sg:address":"444 Academy Rd",
    "sg:city":"Winnipeg",
    "sg:classifiers":[
        {
            "category":"Personal",
            "subcategory":"Beauty Salon",
            "type":"Services"
        }
    ],
    "sg:phone":"+1 204 489 2404",
    "sg:postcode":"R3N 0C4",
    "sg:province":"MB",
    "wof:name":"Magic Mirror Beauty Salon",
    "wof:placetype":"venue"
},
  "geometry": {"coordinates":[-97.18697400000001,49.873798],"type":"Point"}
}