{
  "type": "Feature",
  "properties": {
    "addr:full":"278 Boul Saint-Jean-Baptiste Chateauguay QC J6K 3C2",
    "addr:housenumber":"278",
    "addr:postcode":"j6k 3c2",
    "addr:street":"Boul Saint-Jean-Baptiste",
    "iso:country":"CA",
    "sg:address":"278 Boul Saint-Jean-Baptiste",
    "sg:city":"Chateauguay",
    "sg:classifiers":[
        {
            "category":"Social Services",
            "type":"Services"
        }
    ],
    "sg:phone":"+1 450 692 6741",
    "sg:postcode":"J6K 3C2",
    "sg:province":"QC",
    "sg:tags":[
        "organization",
        "welfare"
    ],
    "wof:name":"Centres Jeunesse-LA Montergie",
    "wof:placetype":"venue"
},
  "geometry": {"coordinates":[-73.72439575200001,45.3441734314],"type":"Point"}
}