{
  "type": "Feature",
  "properties": {
    "addr:full":"156 Victoria St Ingersoll ON N5C 2N1",
    "addr:housenumber":"156",
    "addr:postcode":"n5c 2n1",
    "addr:street":"Victoria St",
    "iso:country":"CA",
    "sg:address":"156 Victoria St",
    "sg:city":"Ingersoll",
    "sg:classifiers":[
        {
            "category":"Education",
            "subcategory":"Dance Studio",
            "type":"Public Place"
        }
    ],
    "sg:phone":"+1 519 425 1888",
    "sg:postcode":"N5C 2N1",
    "sg:province":"ON",
    "sg:tags":[
        "instruction",
        "dancing"
    ],
    "wof:name":"Judith Coleman Oxford School",
    "wof:placetype":"venue"
},
  "geometry": {"coordinates":[-80.892746,43.03952],"type":"Point"}
}