{
  "type": "Feature",
  "properties": {
    "iso:country":"CA",
    "sg:address":"3261 Dundas St W",
    "sg:city":"Toronto",
    "sg:classifiers":[
        {
            "category":"Food & Beverages",
            "subcategory":"Groceries & Convenience Stores",
            "type":"Retail Goods"
        }
    ],
    "sg:phone":"+1 416 769 5956",
    "sg:postcode":"M6P 2A2",
    "sg:province":"ON",
    "sg:tags":[
        "grocer"
    ],
    "wof:name":"Star Supermarket",
    "wof:placetype":"venue"
},
  "geometry": {"coordinates":[-79.47826385499999,43.6654205322],"type":"Point"}
}