{
  "type": "Feature",
  "properties": {
    "addr:full":"RR 2 Cloyne ON K0H 1K0",
    "addr:postcode":"k0h 1k0",
    "addr:street":"Rr 2",
    "iso:country":"CA",
    "sg:address":"RR 2",
    "sg:city":"Cloyne",
    "sg:classifiers":[
        {
            "category":"Government",
            "subcategory":"Office",
            "type":"Public Place"
        }
    ],
    "sg:phone":"+1 613 336 8206",
    "sg:postcode":"K0H 1K0",
    "sg:province":"ON",
    "sg:tags":[
        "village"
    ],
    "wof:name":"Cloyne Garage",
    "wof:placetype":"venue"
},
  "geometry": {"coordinates":[-77.186989,44.82209],"type":"Point"}
}