{
  "type": "Feature",
  "properties": {
    "iso:country":"CA",
    "sg:address":"7111 No. 2 Rd",
    "sg:city":"Richmond",
    "sg:classifiers":[
        {
            "category":"Organizations",
            "subcategory":"Religious Organization",
            "type":"Services"
        }
    ],
    "sg:phone":"+1 604 277 5410",
    "sg:postcode":"V7C 3L7",
    "sg:province":"BC",
    "sg:tags":[
        "church"
    ],
    "wof:name":"Presbyterian Church in Canada",
    "wof:placetype":"venue"
},
  "geometry": {"coordinates":[-123.158997,49.161629],"type":"Point"}
}