{
  "type": "Feature",
  "properties": {
    "addr:full":"16050 Old Simcoe Rd # 3 Port Perry ON L9L 1P3",
    "addr:housenumber":"16050",
    "addr:postcode":"l9l 1p3",
    "addr:street":"Old Simcoe Rd # 3",
    "iso:country":"CA",
    "sg:address":"16050 Old Simcoe Rd # 3",
    "sg:city":"Port Perry",
    "sg:classifiers":[
        {
            "category":"Education",
            "subcategory":"Dance Studio",
            "type":"Public Place"
        }
    ],
    "sg:phone":"+1 905 985 5081",
    "sg:postcode":"L9L 1P3",
    "sg:province":"ON",
    "sg:tags":[
        "instruction",
        "dancing"
    ],
    "wof:name":"Port Perry Dance Academy Ltd",
    "wof:placetype":"venue"
},
  "geometry": {"coordinates":[-78.9570846558,44.1118392944],"type":"Point"}
}