{
  "type": "Feature",
  "properties": {
    "addr:full":"12454 Ogden Dr Mission BC V4S 1L5",
    "addr:housenumber":"12454",
    "addr:postcode":"v4s 1l5",
    "addr:street":"Ogden Dr",
    "iso:country":"CA",
    "sg:address":"12454 Ogden Dr",
    "sg:city":"Mission",
    "sg:classifiers":[
        {
            "category":"Building & Trades",
            "subcategory":"Construction",
            "type":"Services"
        }
    ],
    "sg:phone":"+1 604 826 8741",
    "sg:postcode":"V4S 1L5",
    "sg:province":"BC",
    "sg:tags":[
        "painter"
    ],
    "wof:name":"Realistic Painters",
    "wof:placetype":"venue"
},
  "geometry": {"coordinates":[-122.291816711,49.2281723022],"type":"Point"}
}