{
  "type": "Feature",
  "properties": {
    "addr:full":"Stoney Creek ON L8E 2K4",
    "addr:postcode":"l8e 2k4",
    "iso:country":"CA",
    "sg:city":"Stoney Creek",
    "sg:classifiers":[
        {
            "category":"Manufacturing",
            "subcategory":"Apparel",
            "type":"Manufacturing & Wholesale Goods"
        }
    ],
    "sg:phone":"+1 905 664 1818",
    "sg:postcode":"L8E 2K4",
    "sg:province":"ON",
    "sg:tags":[
        "sewing",
        "contractor"
    ],
    "wof:name":"Vojka Shoes Inc",
    "wof:placetype":"venue"
},
  "geometry": {"coordinates":[-79.730751,43.230396],"type":"Point"}
}