{
  "type": "Feature",
  "properties": {
    "addr:full":"46 Main St W Saint John NB E2M 3N1",
    "addr:housenumber":"46",
    "addr:postcode":"e2m 3n1",
    "addr:street":"Main St W",
    "iso:country":"CA",
    "sg:address":"46 Main St W",
    "sg:city":"Saint John",
    "sg:classifiers":[
        {
            "category":"Banks & Credit Unions",
            "subcategory":"Bank",
            "type":"Services"
        }
    ],
    "sg:phone":"+1 506 635 8193",
    "sg:postcode":"E2M 3N1",
    "sg:province":"NB",
    "wof:name":"Bayview Credit Union",
    "wof:placetype":"venue"
},
  "geometry": {"coordinates":[-66.098358,45.256931],"type":"Point"}
}