{
  "type": "Feature",
  "properties": {
    "iso:country":"CA",
    "sg:address":"3312 26 St NE",
    "sg:city":"Calgary",
    "sg:classifiers":[
        {
            "category":"Autos & Motor Vehicles",
            "subcategory":"Fuel & Gas Station",
            "type":"Retail Goods"
        }
    ],
    "sg:phone":"+1 403 291 0005",
    "sg:postcode":"T1Y 4T7",
    "sg:province":"AB",
    "sg:tags":[
        "oil"
    ],
    "wof:name":"Horizon Shell",
    "wof:placetype":"venue"
},
  "geometry": {"coordinates":[-113.99803199999999,51.08186],"type":"Point"}
}