{
  "type": "Feature",
  "properties": {
    "addr:full":"2275 Atkinson St Regina SK S4N 3X2",
    "addr:housenumber":"2275",
    "addr:postcode":"s4n 3x2",
    "addr:street":"Atkinson St",
    "iso:country":"CA",
    "sg:address":"2275 Atkinson St",
    "sg:city":"Regina",
    "sg:classifiers":[
        {
            "category":"Organizations",
            "subcategory":"Religious Organization",
            "type":"Services"
        }
    ],
    "sg:phone":"+1 306 522 3363",
    "sg:postcode":"S4N 3X2",
    "sg:province":"SK",
    "sg:tags":[
        "church"
    ],
    "wof:name":"St Anthony's Church",
    "wof:placetype":"venue"
},
  "geometry": {"coordinates":[-104.59206399999999,50.442879],"type":"Point"}
}