{
  "type": "Feature",
  "properties": {
    "addr:full":"178 Uplands Dr Kitchener ON N2M 4X6",
    "addr:housenumber":"178",
    "addr:postcode":"n2m 4x6",
    "addr:street":"Uplands Dr",
    "iso:country":"CA",
    "sg:address":"178 Uplands Dr",
    "sg:city":"Kitchener",
    "sg:classifiers":[
        {
            "category":"Home & Garden",
            "subcategory":"Home Furnishings",
            "type":"Retail Goods"
        }
    ],
    "sg:phone":"+1 519 745 4632",
    "sg:postcode":"N2M 4X6",
    "sg:province":"ON",
    "sg:tags":[
        "curtain",
        "made",
        "drapery"
    ],
    "wof:name":"D G Rockett Sales Ltd",
    "wof:placetype":"venue"
},
  "geometry": {"coordinates":[-80.51863098139999,43.4246406555],"type":"Point"}
}