{
  "type": "Feature",
  "properties": {
    "addr:full":"Vancouver BC V6C 1H2",
    "addr:postcode":"v6c 1h2",
    "iso:country":"CA",
    "sg:city":"Vancouver",
    "sg:classifiers":[
        {
            "category":"Professional",
            "subcategory":"Computer Services",
            "type":"Services"
        }
    ],
    "sg:phone":"+1 604 632 9638",
    "sg:postcode":"V6C 1H2",
    "sg:province":"BC",
    "sg:tags":[
        "internet"
    ],
    "wof:name":"Infornet Investment Corp",
    "wof:placetype":"venue"
},
  "geometry": {"coordinates":[-123.11547899999999,49.285271],"type":"Point"}
}