{
  "type": "Feature",
  "properties": {
    "addr:full":"370 Church St E Delhi ON N4B 1V1",
    "addr:housenumber":"370",
    "addr:postcode":"n4b 1v1",
    "addr:street":"Church St E",
    "iso:country":"CA",
    "sg:address":"370 Church St E",
    "sg:city":"Delhi",
    "sg:classifiers":[
        {
            "category":"Organizations",
            "subcategory":"Religious Organization",
            "type":"Services"
        }
    ],
    "sg:phone":"+1 519 582 4372",
    "sg:postcode":"N4B 1V1",
    "sg:province":"ON",
    "sg:tags":[
        "church"
    ],
    "wof:name":"Living Word Congregational Ch",
    "wof:placetype":"venue"
},
  "geometry": {"coordinates":[-80.480164,42.855709],"type":"Point"}
}