{
  "type": "Feature",
  "properties": {
    "addr:full":"163 Rue Laval Hull QC J8X 3J2",
    "addr:housenumber":"163",
    "addr:postcode":"j8x 3j2",
    "addr:street":"Rue Laval",
    "iso:country":"CA",
    "sg:address":"163 Rue Laval",
    "sg:city":"Hull",
    "sg:classifiers":[
        {
            "category":"Food & Beverages",
            "subcategory":"Groceries & Convenience Stores",
            "type":"Retail Goods"
        }
    ],
    "sg:phone":"+1 819 771 2682",
    "sg:postcode":"J8X 3J2",
    "sg:province":"QC",
    "wof:name":"Depanneur Laval",
    "wof:placetype":"venue"
},
  "geometry": {"coordinates":[-75.715294,45.433647],"type":"Point"}
}