{
  "type": "Feature",
  "properties": {
    "addr:full":"1016 Rue Boreale Havre-Saint-Pierre QC G0G 1P0",
    "addr:housenumber":"1016",
    "addr:postcode":"g0g 1p0",
    "addr:street":"Rue Boreale",
    "iso:country":"CA",
    "sg:address":"1016 Rue Boreale",
    "sg:city":"Havre-Saint-Pierre",
    "sg:classifiers":[
        {
            "category":"Shopping",
            "subcategory":"Catalog Store",
            "type":"Retail Goods"
        }
    ],
    "sg:phone":"+1 418 538 3323",
    "sg:postcode":"G0G 1P0",
    "sg:province":"QC",
    "sg:tags":[
        "mail",
        "order",
        "internet"
    ],
    "wof:name":"Sears Canada Inc",
    "wof:placetype":"venue"
},
  "geometry": {"coordinates":[-63.605762,50.238056],"type":"Point"}
}