{
  "type": "Feature",
  "properties": {
    "addr:full":"307 Ch DE LA Grande-Cote Saint-Eustache QC J7P 1C6",
    "addr:housenumber":"307",
    "addr:postcode":"j7p 1c6",
    "addr:street":"Ch De La Grande-Cote",
    "iso:country":"CA",
    "sg:address":"307 Ch DE LA Grande-Cote",
    "sg:city":"Saint-Eustache",
    "sg:classifiers":[
        {
            "category":"Shopping",
            "subcategory":"Computers & Home Electronics",
            "type":"Retail Goods"
        }
    ],
    "sg:phone":"+1 450 623 6060",
    "sg:postcode":"J7P 1C6",
    "sg:province":"QC",
    "sg:tags":[
        "television",
        "supply",
        "equipment",
        "parts",
        "radio",
        "electronic"
    ],
    "wof:name":"Service DE Tv Rive Nord",
    "wof:placetype":"venue"
},
  "geometry": {"coordinates":[-73.866028,45.57317],"type":"Point"}
}