{
  "type": "Feature",
  "properties": {
    "addr:full":"35 Rue Codaire Abbotsford QC J0E 1A0",
    "addr:housenumber":"35",
    "addr:postcode":"j0e 1a0",
    "addr:street":"Rue Codaire",
    "iso:country":"CA",
    "sg:address":"35 Rue Codaire",
    "sg:city":"Abbotsford",
    "sg:classifiers":[
        {
            "category":"Recreation",
            "type":"Entertainment"
        }
    ],
    "sg:phone":"+1 450 379 5381",
    "sg:postcode":"J0E 1A0",
    "sg:province":"QC",
    "sg:tags":[
        "center"
    ],
    "wof:name":"Loisirs St Paul D'Abbotsford",
    "wof:placetype":"venue"
},
  "geometry": {"coordinates":[-72.883224,45.435776],"type":"Point"}
}