{
  "type": "Feature",
  "properties": {
    "addr:full":"11800 Lake Fraser Dr SE Calgary AB T2J 7G8",
    "addr:housenumber":"11800",
    "addr:postcode":"t2j 7g8",
    "addr:street":"Lake Fraser Dr Se",
    "iso:country":"CA",
    "sg:address":"11800 Lake Fraser Dr SE",
    "sg:city":"Calgary",
    "sg:classifiers":[
        {
            "category":"Health Services",
            "subcategory":"Nursing And Care Facility",
            "type":"Services"
        }
    ],
    "sg:phone":"+1 403 286 3160",
    "sg:postcode":"T2J 7G8",
    "sg:province":"AB",
    "sg:tags":[
        "home",
        "apartment",
        "community",
        "retirement"
    ],
    "wof:name":"Origin Adult Communities",
    "wof:placetype":"venue"
},
  "geometry": {"coordinates":[-114.067810059,50.9479217529],"type":"Point"}
}