{
  "type": "Feature",
  "properties": {
    "iso:country":"CA",
    "sg:address":"158 Patrick St",
    "sg:city":"Kingston",
    "sg:classifiers":[
        {
            "category":"Education",
            "subcategory":"School",
            "type":"Public Place"
        }
    ],
    "sg:phone":"+1 613 542 1437",
    "sg:postcode":"K7K 3P5",
    "sg:province":"ON",
    "wof:name":"St Patrick School",
    "wof:placetype":"venue"
},
  "geometry": {"coordinates":[-76.489868,44.241093],"type":"Point"}
}