{
  "type": "Feature",
  "properties": {
    "addr:full":"3405 Rhodes Dr Windsor ON N8W 5B3",
    "addr:housenumber":"3405",
    "addr:postcode":"n8w 5b3",
    "addr:street":"Rhodes Dr",
    "iso:country":"CA",
    "sg:address":"3405 Rhodes Dr",
    "sg:city":"Windsor",
    "sg:classifiers":[
        {
            "category":"Health Services",
            "subcategory":"Doctor",
            "type":"Services"
        }
    ],
    "sg:phone":"+1 519 974 8879",
    "sg:postcode":"N8W 5B3",
    "sg:province":"ON",
    "sg:tags":[
        "physician",
        "surgeon"
    ],
    "wof:name":"Hirshberg, Eric MD",
    "wof:placetype":"venue"
},
  "geometry": {"coordinates":[-82.968460083,42.2820053101],"type":"Point"}
}