{
  "type": "Feature",
  "properties": {
    "addr:full":"9750 35 Ave NW Edmonton AB T6E 6J6",
    "addr:housenumber":"9750",
    "addr:postcode":"t6e 6j6",
    "addr:street":"35 Ave Nw",
    "iso:country":"CA",
    "sg:address":"9750 35 Ave NW",
    "sg:city":"Edmonton",
    "sg:classifiers":[
        {
            "category":"Freight",
            "type":"Transportation"
        }
    ],
    "sg:phone":"+1 780 463 4718",
    "sg:postcode":"T6E 6J6",
    "sg:province":"AB",
    "sg:tags":[
        "broker",
        "customs"
    ],
    "wof:name":"Schenker Stinnes Logistics",
    "wof:placetype":"venue"
},
  "geometry": {"coordinates":[-113.48084299999999,53.468895],"type":"Point"}
}