{
  "type": "Feature",
  "properties": {
    "iso:country":"CA",
    "sg:city":"Crossfield",
    "sg:classifiers":[
        {
            "category":"Retail",
            "subcategory":"Veterinary Services",
            "type":"Services"
        }
    ],
    "sg:phone":"+1 403 946 4567",
    "sg:postcode":"T0M 0S0",
    "sg:province":"AB",
    "sg:tags":[
        "veterinarian"
    ],
    "wof:name":"Nagel Veterinary Svc",
    "wof:placetype":"venue"
},
  "geometry": {"coordinates":[-114.028373718,51.4282569885],"type":"Point"}
}