{
  "type": "Feature",
  "properties": {
    "addr:full":"5252 Rue Sherbrooke O Montreal QC H4A 1T9",
    "addr:housenumber":"5252",
    "addr:postcode":"h4a 1t9",
    "addr:street":"Rue Sherbrooke O",
    "iso:country":"CA",
    "sg:address":"5252 Rue Sherbrooke O",
    "sg:city":"Montreal",
    "sg:classifiers":[
        {
            "category":"Cinema",
            "subcategory":"Movie Rental",
            "type":"Entertainment"
        }
    ],
    "sg:phone":"+1 514 485 2582",
    "sg:postcode":"H4A 1T9",
    "sg:province":"QC",
    "sg:tags":[
        "leasing",
        "video",
        "disc",
        "tape"
    ],
    "wof:name":"Club Video Ctr",
    "wof:placetype":"venue"
},
  "geometry": {"coordinates":[-73.552452,45.567844],"type":"Point"}
}