{
  "type": "Feature",
  "properties": {
    "addr:full":"108 3rd St N Geraldton ON P0T 1M0",
    "addr:housenumber":"108",
    "addr:postcode":"p0t 1m0",
    "addr:street":"3Rd St N",
    "iso:country":"CA",
    "sg:address":"108 3rd St N",
    "sg:city":"Geraldton",
    "sg:classifiers":[
        {
            "category":"Organizations",
            "subcategory":"Professional Association",
            "type":"Services"
        }
    ],
    "sg:phone":"+1 807 854 1090",
    "sg:postcode":"P0T 1M0",
    "sg:province":"ON",
    "sg:tags":[
        "labor"
    ],
    "wof:name":"Iwa Canada",
    "wof:placetype":"venue"
},
  "geometry": {"coordinates":[-86.94738769529999,49.7272338867],"type":"Point"}
}