{
  "type": "Feature",
  "properties": {
    "addr:full":"561 Keele St Toronto ON M6N 3E4",
    "addr:housenumber":"561",
    "addr:postcode":"m6n 3e4",
    "addr:street":"Keele St",
    "iso:country":"CA",
    "sg:address":"561 Keele St",
    "sg:city":"Toronto",
    "sg:classifiers":[
        {
            "category":"Retail",
            "subcategory":"Auto Repair",
            "type":"Services"
        }
    ],
    "sg:phone":"+1 416 762 7287",
    "sg:postcode":"M6N 3E4",
    "sg:province":"ON",
    "sg:tags":[
        "body",
        "automobile",
        "painting"
    ],
    "wof:name":"Imperial Auto Collision",
    "wof:placetype":"venue"
},
  "geometry": {"coordinates":[-79.466599,43.670712],"type":"Point"}
}