{
  "type": "Feature",
  "properties": {
    "addr:full":"1509 Av Dollard Lasalle QC H8N 1T3",
    "addr:housenumber":"1509",
    "addr:postcode":"h8n 1t3",
    "addr:street":"Av Dollard",
    "iso:country":"CA",
    "sg:address":"1509 Av Dollard",
    "sg:city":"Lasalle",
    "sg:classifiers":[
        {
            "category":"Bars & Pubs",
            "type":"Food & Drink"
        }
    ],
    "sg:phone":"+1 514 364 3488",
    "sg:postcode":"H8N 1T3",
    "sg:province":"QC",
    "sg:tags":[
        "lounge",
        "cocktail"
    ],
    "wof:name":"Bar Chez Normand",
    "wof:placetype":"venue"
},
  "geometry": {"coordinates":[-73.62808200000001,45.42749],"type":"Point"}
}