{
  "type": "Feature",
  "properties": {
    "addr:full":"Brooks AB T1R 0R9",
    "addr:postcode":"t1r 0r9",
    "iso:country":"CA",
    "sg:city":"Brooks",
    "sg:classifiers":[
        {
            "category":"Shopping",
            "subcategory":"Gifts & Souvenirs",
            "type":"Retail Goods"
        }
    ],
    "sg:phone":"+1 403 362 6650",
    "sg:postcode":"T1R 0R9",
    "sg:province":"AB",
    "sg:tags":[
        "shop"
    ],
    "wof:name":"From the Prairie",
    "wof:placetype":"venue"
},
  "geometry": {"coordinates":[-111.895836,50.564201],"type":"Point"}
}