{
  "type": "Feature",
  "properties": {
    "addr:full":"Railway St W Homewood MB R0G 0Y0",
    "addr:postcode":"r0g 0y0",
    "addr:street":"Railway St W",
    "iso:country":"CA",
    "sg:address":"Railway St W",
    "sg:city":"Homewood",
    "sg:classifiers":[
        {
            "category":"Farming",
            "subcategory":"Farm & Veterinary Services",
            "type":"Manufacturing & Wholesale Goods"
        }
    ],
    "sg:phone":"+1 204 745 6421",
    "sg:postcode":"R0G 0Y0",
    "sg:province":"MB",
    "sg:tags":[
        "product",
        "protection",
        "crop"
    ],
    "wof:name":"Homewood CO-OP",
    "wof:placetype":"venue"
},
  "geometry": {"coordinates":[-97.8650817871,49.5096435547],"type":"Point"}
}