{
  "type": "Feature",
  "properties": {
    "addr:full":"1st Ave Carroll MB R0K 0K0",
    "addr:postcode":"r0k 0k0",
    "addr:street":"1St Ave",
    "iso:country":"CA",
    "sg:address":"1st Ave",
    "sg:city":"Carroll",
    "sg:classifiers":[
        {
            "category":"Building & Trades",
            "subcategory":"Construction",
            "type":"Services"
        }
    ],
    "sg:phone":"+1 204 483 3979",
    "sg:postcode":"R0K 0K0",
    "sg:province":"MB",
    "sg:tags":[
        "painter"
    ],
    "wof:name":"Roy Painting & Decorating",
    "wof:placetype":"venue"
},
  "geometry": {"coordinates":[-100.029945373,49.6074256897],"type":"Point"}
}