{
  "type": "Feature",
  "properties": {
    "iso:country":"CA",
    "sg:address":"2039 Boul Roland-Therrien",
    "sg:city":"Longueuil",
    "sg:classifiers":[
        {
            "category":"Shopping",
            "subcategory":"Clothing, Apparel, & Fashions",
            "type":"Retail Goods"
        }
    ],
    "sg:phone":"+1 450 448 2772",
    "sg:postcode":"J4N 1A3",
    "sg:province":"QC",
    "sg:tags":[
        "boutique"
    ],
    "wof:name":"Aubaines Mignonne Modes",
    "wof:placetype":"venue"
},
  "geometry": {"coordinates":[-73.473824,45.537632],"type":"Point"}
}