{
  "type": "Feature",
  "properties": {
    "addr:full":"83 Hinton Ave N Ottawa ON K1Y 0Z7",
    "addr:housenumber":"83",
    "addr:postcode":"k1y 0z7",
    "addr:street":"Hinton Ave N",
    "iso:country":"CA",
    "sg:address":"83 Hinton Ave N",
    "sg:city":"Ottawa",
    "sg:classifiers":[
        {
            "category":"Real Estate",
            "subcategory":"Architect",
            "type":"Services"
        }
    ],
    "sg:phone":"+1 613 728 2829",
    "sg:postcode":"K1Y 0Z7",
    "sg:province":"ON",
    "wof:name":"Liff & Tolot Architects Inc",
    "wof:placetype":"venue"
},
  "geometry": {"coordinates":[-75.731415,45.401024],"type":"Point"}
}