{
  "type": "Feature",
  "properties": {
    "addr:full":"7508 29 Ave NW Edmonton AB T6K 3Y8",
    "addr:housenumber":"7508",
    "addr:postcode":"t6k 3y8",
    "addr:street":"29 Ave Nw",
    "iso:country":"CA",
    "sg:address":"7508 29 Ave NW",
    "sg:city":"Edmonton",
    "sg:classifiers":[
        {
            "category":"Organizations",
            "subcategory":"Religious Organization",
            "type":"Services"
        }
    ],
    "sg:phone":"+1 780 463 8646",
    "sg:postcode":"T6K 3Y8",
    "sg:province":"AB",
    "sg:tags":[
        "church"
    ],
    "wof:name":"St Theresa Millwoods Roman",
    "wof:placetype":"venue"
},
  "geometry": {"coordinates":[-113.446297,53.460236],"type":"Point"}
}