{
  "type": "Feature",
  "properties": {
    "iso:country":"CA",
    "sg:address":"258 Boul Des Prairies",
    "sg:city":"Laval",
    "sg:classifiers":[
        {
            "category":"Professional",
            "subcategory":"Research",
            "type":"Services"
        }
    ],
    "sg:phone":"+1 450 667 3886",
    "sg:postcode":"H7N 2T9",
    "sg:province":"QC",
    "sg:tags":[
        "development",
        "laboratory"
    ],
    "wof:name":"Ims Recherche Inc",
    "wof:placetype":"venue"
},
  "geometry": {"coordinates":[-73.698959,45.550644],"type":"Point"}
}