{
  "type": "Feature",
  "properties": {
    "addr:full":"167 Rue DE LA Reine Gaspe QC G4X 2W6",
    "addr:housenumber":"167",
    "addr:postcode":"g4x 2w6",
    "addr:street":"Rue De La Reine Gaspe",
    "iso:country":"CA",
    "sg:address":"167 Rue DE LA Reine",
    "sg:city":"Gaspe",
    "sg:classifiers":[
        {
            "category":"Banks & Credit Unions",
            "subcategory":"Bank",
            "type":"Services"
        }
    ],
    "sg:phone":"+1 418 368 5526",
    "sg:postcode":"G4X 2W6",
    "sg:province":"QC",
    "sg:tags":[
        "loan",
        "real estate"
    ],
    "wof:name":"Citi Financiere",
    "wof:placetype":"venue"
},
  "geometry": {"coordinates":[-64.48492400000001,48.828716],"type":"Point"}
}