{
  "type": "Feature",
  "properties": {
    "addr:full":"104 Elizabeth St Okotoks AB T1S 1P8",
    "addr:housenumber":"104",
    "addr:postcode":"t1s 1p8",
    "addr:street":"Elizabeth St Okotoks Ab",
    "iso:country":"CA",
    "sg:address":"104 Elizabeth St",
    "sg:city":"Okotoks",
    "sg:classifiers":[
        {
            "category":"Personal",
            "subcategory":"Beauty Salon",
            "type":"Services"
        }
    ],
    "sg:phone":"+1 403 938 6155",
    "sg:postcode":"T1S 1P8",
    "sg:province":"AB",
    "wof:name":"Hair Lounge",
    "wof:placetype":"venue"
},
  "geometry": {"coordinates":[-113.980766296,50.7259788513],"type":"Point"}
}