{
  "type": "Feature",
  "properties": {
    "iso:country":"CA",
    "sg:address":"104 Elizabeth St",
    "sg:city":"Okotoks",
    "sg:classifiers":[
        {
            "category":"Personal",
            "subcategory":"Beauty Salon",
            "type":"Services"
        }
    ],
    "sg:phone":"+1 403 938 6155",
    "sg:postcode":"T1S 1P8",
    "sg:province":"AB",
    "wof:name":"Hair Lounge",
    "wof:placetype":"venue"
},
  "geometry": {"coordinates":[-113.980766296,50.7259788513],"type":"Point"}
}