{
  "type": "Feature",
  "properties": {
    "addr:full":"2123 Otter Point Rd Sooke BC V0S 1N0",
    "addr:housenumber":"2123",
    "addr:postcode":"v0s 1n0",
    "addr:street":"Otter Point Rd",
    "iso:country":"CA",
    "sg:address":"2123 Otter Point Rd",
    "sg:city":"Sooke",
    "sg:classifiers":[
        {
            "category":"Retail",
            "subcategory":"Auto Repair",
            "type":"Services"
        }
    ],
    "sg:phone":"+1 250 642 3171",
    "sg:postcode":"V0S 1N0",
    "sg:province":"BC",
    "sg:tags":[
        "wrecker"
    ],
    "wof:name":"Sooke Towing",
    "wof:placetype":"venue"
},
  "geometry": {"coordinates":[-123.72616600000001,48.380447],"type":"Point"}
}