{
  "type": "Feature",
  "properties": {
    "addr:full":"75 Boul Industriel E Victoriaville QC G6T 1S8",
    "addr:housenumber":"75",
    "addr:postcode":"g6t 1s8",
    "addr:street":"Boul Industriel E",
    "iso:country":"CA",
    "sg:address":"75 Boul Industriel E",
    "sg:city":"Victoriaville",
    "sg:classifiers":[
        {
            "category":"Organizations",
            "subcategory":"Labor Organization",
            "type":"Services"
        }
    ],
    "sg:phone":"+1 819 751 2670",
    "sg:postcode":"G6T 1S8",
    "sg:province":"QC",
    "wof:name":"Syndicat Des Salaries",
    "wof:placetype":"venue"
},
  "geometry": {"coordinates":[-71.9715270996,46.0667648315],"type":"Point"}
}