{
  "type": "Feature",
  "properties": {
    "addr:full":"37 Royal Crt Bradford ON L3Z 2P7",
    "addr:housenumber":"37",
    "addr:postcode":"l3z 2p7",
    "addr:street":"Royal Crt",
    "iso:country":"CA",
    "sg:address":"37 Royal Crt",
    "sg:city":"Bradford",
    "sg:classifiers":[
        {
            "category":"Building & Trades",
            "subcategory":"Construction",
            "type":"Services"
        }
    ],
    "sg:phone":"+1 905 775 2759",
    "sg:postcode":"L3Z 2P7",
    "sg:province":"ON",
    "sg:tags":[
        "siding",
        "contractor"
    ],
    "wof:name":"Schmidt Aluminum Products",
    "wof:placetype":"venue"
},
  "geometry": {"coordinates":[-79.575783,44.105694],"type":"Point"}
}