{
  "type": "Feature",
  "properties": {
    "addr:full":"1021 Mcgregor St Winnipeg MB R2V 3H4",
    "addr:housenumber":"1021",
    "addr:postcode":"r2v 3h4",
    "addr:street":"Mcgregor St",
    "iso:country":"CA",
    "sg:address":"1021 Mcgregor St",
    "sg:city":"Winnipeg",
    "sg:classifiers":[
        {
            "category":"Food & Beverages",
            "subcategory":"Groceries & Convenience Stores",
            "type":"Retail Goods"
        }
    ],
    "sg:phone":"+1 204 339 2263",
    "sg:postcode":"R2V 3H4",
    "sg:province":"MB",
    "wof:name":"Mac's Convenience Stores Ltd",
    "wof:placetype":"venue"
},
  "geometry": {"coordinates":[-97.1259,49.946541],"type":"Point"}
}