{
  "type": "Feature",
  "properties": {
    "addr:full":"164 Tait Rd Nanaimo BC V9X 1C3",
    "addr:housenumber":"164",
    "addr:postcode":"v9x 1c3",
    "addr:street":"Tait Rd",
    "iso:country":"CA",
    "sg:address":"164 Tait Rd",
    "sg:city":"Nanaimo",
    "sg:classifiers":[
        {
            "category":"Home & Garden",
            "subcategory":"Building Materials",
            "type":"Retail Goods"
        }
    ],
    "sg:phone":"+1 250 755 1500",
    "sg:postcode":"V9X 1C3",
    "sg:province":"BC",
    "sg:tags":[
        "glass",
        "window",
        "plate"
    ],
    "wof:name":"Relkie Designs Art Glass",
    "wof:placetype":"venue"
},
  "geometry": {"coordinates":[-123.930351257,49.1077346802],"type":"Point"}
}