{
  "type": "Feature",
  "properties": {
    "addr:full":"160 Oakwood Ave York ON M6E 2T9",
    "addr:housenumber":"160",
    "addr:postcode":"m6e 2t9",
    "addr:street":"Oakwood Ave",
    "iso:country":"CA",
    "sg:address":"160 Oakwood Ave",
    "sg:city":"York",
    "sg:classifiers":[
        {
            "category":"Personal",
            "subcategory":"Beauty Salon",
            "type":"Services"
        }
    ],
    "sg:phone":"+1 416 530 4939",
    "sg:postcode":"M6E 2T9",
    "sg:province":"ON",
    "wof:name":"Wave of Distinction",
    "wof:placetype":"venue"
},
  "geometry": {"coordinates":[-79.436050415,43.6800003052],"type":"Point"}
}