{
  "type": "Feature",
  "properties": {
    "addr:full":"3627 Hwy 97A Armstrong BC V0E 1B8",
    "addr:housenumber":"3627",
    "addr:postcode":"v0e 1b8",
    "addr:street":"Hwy 97A",
    "iso:country":"CA",
    "sg:address":"3627 Hwy 97A",
    "sg:city":"Armstrong",
    "sg:classifiers":[
        {
            "category":"Shopping",
            "subcategory":"Bicycles & Sporting Goods",
            "type":"Retail Goods"
        }
    ],
    "sg:phone":"+1 250 546 3724",
    "sg:postcode":"V0E 1B8",
    "sg:province":"BC",
    "wof:name":"High Trails Enterprises Ltd",
    "wof:placetype":"venue"
},
  "geometry": {"coordinates":[-119.18222045900001,50.4481506348],"type":"Point"}
}