{
  "type": "Feature",
  "properties": {
    "addr:full":"237 Brunetville Rd Kapuskasing ON P5N 2H2",
    "addr:housenumber":"237",
    "addr:postcode":"p5n 2h2",
    "addr:street":"Brunetville Rd",
    "iso:country":"CA",
    "sg:address":"237 Brunetville Rd",
    "sg:city":"Kapuskasing",
    "sg:classifiers":[
        {
            "category":"Building & Trades",
            "subcategory":"Electrical",
            "type":"Services"
        }
    ],
    "sg:phone":"+1 705 335 0916",
    "sg:postcode":"P5N 2H2",
    "sg:province":"ON",
    "sg:tags":[
        "electric",
        "contractor"
    ],
    "wof:name":"After Hours Electric",
    "wof:placetype":"venue"
},
  "geometry": {"coordinates":[-82.38986199999999,49.420288],"type":"Point"}
}