{
  "type": "Feature",
  "properties": {
    "iso:country":"CA",
    "sg:address":"2264 Av DE LA Rotonde",
    "sg:city":"Charny",
    "sg:classifiers":[
        {
            "category":"Professional",
            "subcategory":"Management & Consulting",
            "type":"Services"
        }
    ],
    "sg:phone":"+1 418 832 7905",
    "sg:postcode":"G6X 2L8",
    "sg:province":"QC",
    "sg:tags":[
        "consultant",
        "telecommunication"
    ],
    "wof:name":"M3A Telecom",
    "wof:placetype":"venue"
},
  "geometry": {"coordinates":[-71.26685333250001,46.7076911926],"type":"Point"}
}