{
  "type": "Feature",
  "properties": {
    "addr:full":"Inverness NS B0E 1N0",
    "addr:postcode":"b0e 1n0",
    "iso:country":"CA",
    "sg:city":"Inverness",
    "sg:classifiers":[
        {
            "category":"Shopping",
            "type":"Retail Goods"
        }
    ],
    "sg:phone":"+1 902 258 2533",
    "sg:postcode":"B0E 1N0",
    "sg:province":"NS",
    "sg:tags":[
        "information",
        "arts",
        "art",
        "dealer",
        "organization",
        "gallery"
    ],
    "wof:name":"Inverness County Council-Arts",
    "wof:placetype":"venue"
},
  "geometry": {"coordinates":[-61.30666,46.229359],"type":"Point"}
}