{
  "type": "Feature",
  "properties": {
    "addr:full":"374 Shepherd St W Windsor ON N8X 1C3",
    "addr:housenumber":"374",
    "addr:postcode":"n8x 1c3",
    "addr:street":"Shepherd St W",
    "iso:country":"CA",
    "sg:address":"374 Shepherd St W",
    "sg:city":"Windsor",
    "sg:classifiers":[
        {
            "category":"Wholesale",
            "subcategory":"Office Equipment",
            "type":"Manufacturing & Wholesale Goods"
        }
    ],
    "sg:phone":"+1 519 977 1533",
    "sg:postcode":"N8X 1C3",
    "sg:province":"ON",
    "sg:tags":[
        "bank",
        "supply"
    ],
    "wof:name":"Atm Instant Cash",
    "wof:placetype":"venue"
},
  "geometry": {"coordinates":[-83.031738,42.299362],"type":"Point"}
}