{
  "type": "Feature",
  "properties": {
    "addr:full":"2673 Ch Sainte-Foy Sainte-Foy QC G1V 1V3",
    "addr:postcode":"2673;g1v 1v3",
    "addr:street":"Ch Sainte-Foy",
    "iso:country":"CA",
    "sg:address":"2673 Ch Sainte-Foy",
    "sg:city":"Sainte-Foy",
    "sg:classifiers":[
        {
            "category":"Home & Garden",
            "subcategory":"Household Appliances",
            "type":"Retail Goods"
        }
    ],
    "sg:phone":"+1 418 656 6202",
    "sg:postcode":"G1V 1V3",
    "sg:province":"QC",
    "sg:tags":[
        "cleaners",
        "vacuum"
    ],
    "wof:name":"Monsieur Balayeuse",
    "wof:placetype":"venue"
},
  "geometry": {"coordinates":[-71.291763,46.769211],"type":"Point"}
}