{
  "type": "Feature",
  "properties": {
    "addr:full":"1082 Weber St E Kitchener ON N2A 1B8",
    "addr:housenumber":"1082",
    "addr:postcode":"n2a 1b8",
    "addr:street":"Weber St E",
    "iso:country":"CA",
    "sg:address":"1082 Weber St E",
    "sg:city":"Kitchener",
    "sg:classifiers":[
        {
            "category":"Insurance",
            "subcategory":"Insurance Agent",
            "type":"Services"
        }
    ],
    "sg:phone":"+1 519 893 7008",
    "sg:postcode":"N2A 1B8",
    "sg:province":"ON",
    "wof:name":"Wagler, Scott",
    "wof:placetype":"venue"
},
  "geometry": {"coordinates":[-80.45002700000001,43.43539],"type":"Point"}
}