{
  "type": "Feature",
  "properties": {
    "iso:country":"CA",
    "sg:address":"1748 Main St",
    "sg:city":"Winnipeg",
    "sg:classifiers":[
        {
            "category":"Organizations",
            "subcategory":"Professional Association",
            "type":"Services"
        }
    ],
    "sg:phone":"+1 204 338 3266",
    "sg:postcode":"R2V 1Z5",
    "sg:province":"MB",
    "wof:name":"Royal Canadian Legion",
    "wof:placetype":"venue"
},
  "geometry": {"coordinates":[-97.118408,49.936161],"type":"Point"}
}