{
  "type": "Feature",
  "properties": {
    "addr:full":"1748 Main St Winnipeg MB R2V 1Z5",
    "addr:housenumber":"1748",
    "addr:postcode":"r2v 1z5",
    "addr:street":"Main St",
    "iso:country":"CA",
    "sg:address":"1748 Main St",
    "sg:city":"Winnipeg",
    "sg:classifiers":[
        {
            "category":"Organizations",
            "subcategory":"Professional Association",
            "type":"Services"
        }
    ],
    "sg:phone":"+1 204 338 3266",
    "sg:postcode":"R2V 1Z5",
    "sg:province":"MB",
    "wof:name":"Royal Canadian Legion",
    "wof:placetype":"venue"
},
  "geometry": {"coordinates":[-97.118408,49.936161],"type":"Point"}
}