{
  "type": "Feature",
  "properties": {
    "addr:full":"168 King St W Chatham ON N7M 1E3",
    "addr:housenumber":"168",
    "addr:postcode":"n7m 1e3",
    "addr:street":"King St W",
    "iso:country":"CA",
    "sg:address":"168 King St W",
    "sg:city":"Chatham",
    "sg:classifiers":[
        {
            "category":"Shopping",
            "subcategory":"Clothing, Apparel, & Fashions",
            "type":"Retail Goods"
        }
    ],
    "sg:phone":"+1 519 352 1331",
    "sg:postcode":"N7M 1E3",
    "sg:province":"ON",
    "wof:name":"Goldcoast Fashions",
    "wof:placetype":"venue"
},
  "geometry": {"coordinates":[-82.18695099999999,42.405373],"type":"Point"}
}