{
  "type": "Feature",
  "properties": {
    "addr:full":"Hwy 43 Blue Ridge AB T0E 0B0",
    "addr:postcode":"t0e 0b0",
    "addr:street":"Hwy 43",
    "iso:country":"CA",
    "sg:address":"Hwy 43",
    "sg:city":"Blue Ridge",
    "sg:classifiers":[
        {
            "category":"Autos & Motor Vehicles",
            "subcategory":"Fuel & Gas Station",
            "type":"Retail Goods"
        }
    ],
    "sg:phone":"+1 780 648 0000",
    "sg:postcode":"T0E 0B0",
    "sg:province":"AB",
    "sg:tags":[
        "oil"
    ],
    "wof:name":"Cottonwood Esso",
    "wof:placetype":"venue"
},
  "geometry": {"coordinates":[-115.39312700000001,54.154613],"type":"Point"}
}