{
  "type": "Feature",
  "properties": {
    "addr:full":"1301 Paula Pl Port Coquitlam BC V3C 2W3",
    "addr:housenumber":"1301",
    "addr:postcode":"v3c 2w3",
    "addr:street":"Paula Pl",
    "iso:country":"CA",
    "sg:address":"1301 Paula Pl",
    "sg:city":"Port Coquitlam",
    "sg:classifiers":[
        {
            "category":"Building & Trades",
            "subcategory":"Construction",
            "type":"Services"
        }
    ],
    "sg:phone":"+1 604 813 6949",
    "sg:postcode":"V3C 2W3",
    "sg:province":"BC",
    "sg:tags":[
        "concrete",
        "contractor"
    ],
    "wof:name":"Westwood Concrete",
    "wof:placetype":"venue"
},
  "geometry": {"coordinates":[-122.78171500000001,49.239513],"type":"Point"}
}