{
  "type": "Feature",
  "properties": {
    "addr:full":"Scarborough ON M1E 4V1",
    "addr:postcode":"m1e 4v1",
    "iso:country":"CA",
    "sg:city":"Scarborough",
    "sg:classifiers":[
        {
            "category":"Autos & Motor Vehicles",
            "subcategory":"Boat Sales",
            "type":"Retail Goods"
        }
    ],
    "sg:phone":"+1 416 283 4892",
    "sg:postcode":"M1E 4V1",
    "sg:province":"ON",
    "sg:tags":[
        "top",
        "upholstery",
        "cover"
    ],
    "wof:name":"Canvas Mann",
    "wof:placetype":"venue"
},
  "geometry": {"coordinates":[-79.16514599999999,43.765179],"type":"Point"}
}