{
  "type": "Feature",
  "properties": {
    "addr:full":"36 Water St Kingsville ON N9Y 1J3",
    "addr:housenumber":"36",
    "addr:postcode":"n9y 1j3",
    "addr:street":"Water St",
    "iso:country":"CA",
    "sg:address":"36 Water St",
    "sg:city":"Kingsville",
    "sg:classifiers":[
        {
            "category":"Education",
            "subcategory":"School",
            "type":"Public Place"
        }
    ],
    "sg:phone":"+1 519 733 2338",
    "sg:postcode":"N9Y 1J3",
    "sg:province":"ON",
    "wof:name":"Kingsville Public School",
    "wof:placetype":"venue"
},
  "geometry": {"coordinates":[-82.7405548096,42.0398406982],"type":"Point"}
}