{
  "type": "Feature",
  "properties": {
    "addr:full":"2117 Boul Rosemont Montreal QC H2G 1T3",
    "addr:housenumber":"2117",
    "addr:postcode":"h2g 1t3",
    "addr:street":"Boul Rosemont",
    "iso:country":"CA",
    "sg:address":"2117 Boul Rosemont",
    "sg:city":"Montreal",
    "sg:classifiers":[
        {
            "category":"Shopping",
            "subcategory":"Florist",
            "type":"Retail Goods"
        }
    ],
    "sg:phone":"+1 514 722 1292",
    "sg:postcode":"H2G 1T3",
    "sg:province":"QC",
    "wof:name":"Artiflora Rosemont",
    "wof:placetype":"venue"
},
  "geometry": {"coordinates":[-73.5892562866,45.5433082581],"type":"Point"}
}