{
  "type": "Feature",
  "properties": {
    "addr:full":"74 Victoria St # 303 Toronto ON M5C 2A5",
    "addr:housenumber":"74",
    "addr:postcode":"m5c 2a5",
    "addr:street":"Victoria St # 303",
    "iso:country":"CA",
    "sg:address":"74 Victoria St # 303",
    "sg:city":"Toronto",
    "sg:classifiers":[
        {
            "category":"Professional",
            "subcategory":"Lawyer & Legal Services",
            "type":"Services"
        }
    ],
    "sg:phone":"+1 416 861 1661",
    "sg:postcode":"M5C 2A5",
    "sg:province":"ON",
    "sg:tags":[
        "attorney",
        "naturalization",
        "immigration"
    ],
    "wof:name":"Simmons, Donald C",
    "wof:placetype":"venue"
},
  "geometry": {"coordinates":[-79.377571106,43.6512184143],"type":"Point"}
}