{
  "type": "Feature",
  "properties": {
    "addr:full":"291 King St Midland ON L4R 3M5",
    "addr:housenumber":"291",
    "addr:postcode":"l4r 3m5",
    "addr:street":"King St",
    "iso:country":"CA",
    "sg:address":"291 King St",
    "sg:city":"Midland",
    "sg:classifiers":[
        {
            "category":"Banks & Credit Unions",
            "subcategory":"Bank",
            "type":"Services"
        }
    ],
    "sg:phone":"+1 705 526 2237",
    "sg:postcode":"L4R 3M5",
    "sg:province":"ON",
    "wof:name":"Scotiabank",
    "wof:placetype":"venue"
},
  "geometry": {"coordinates":[-79.884895,44.749588],"type":"Point"}
}