{
  "type": "Feature",
  "properties": {
    "addr:full":"100 Canada Dr Harbour Breton NL A0H 1P0",
    "addr:housenumber":"100",
    "addr:postcode":"a0h 1p0",
    "addr:street":"Canada Dr",
    "iso:country":"CA",
    "sg:address":"100 Canada Dr",
    "sg:city":"Harbour Breton",
    "sg:classifiers":[
        {
            "category":"Home & Garden",
            "subcategory":"Building Materials",
            "type":"Retail Goods"
        }
    ],
    "sg:phone":"+1 709 885 2880",
    "sg:postcode":"A0H 1P0",
    "sg:province":"NL",
    "sg:tags":[
        "paint"
    ],
    "wof:name":"Paint Shop",
    "wof:placetype":"venue"
},
  "geometry": {"coordinates":[-55.8215065002,47.469493866],"type":"Point"}
}