{
  "type": "Feature",
  "properties": {
    "addr:full":"90 Curtis St St Thomas ON N5P 1J2",
    "addr:housenumber":"90",
    "addr:postcode":"n5p 1j2",
    "addr:street":"Curtis St",
    "iso:country":"CA",
    "sg:address":"90 Curtis St",
    "sg:city":"St Thomas",
    "sg:classifiers":[
        {
            "category":"Real Estate",
            "subcategory":"Surveying",
            "type":"Services"
        }
    ],
    "sg:phone":"+1 519 631 7371",
    "sg:postcode":"N5P 1J2",
    "sg:province":"ON",
    "sg:tags":[
        "surveyor"
    ],
    "wof:name":"J G Rupert Ltd",
    "wof:placetype":"venue"
},
  "geometry": {"coordinates":[-81.195549,42.77969],"type":"Point"}
}