{
  "type": "Feature",
  "properties": {
    "addr:full":"78 Vaughan Rd York ON M6C 2L7",
    "addr:housenumber":"78",
    "addr:postcode":"m6c 2l7",
    "addr:street":"Vaughan Rd",
    "iso:country":"CA",
    "sg:address":"78 Vaughan Rd",
    "sg:city":"York",
    "sg:classifiers":[
        {
            "category":"Food & Beverages",
            "subcategory":"Dairy",
            "type":"Retail Goods"
        }
    ],
    "sg:phone":"+1 416 656 6959",
    "sg:postcode":"M6C 2L7",
    "sg:province":"ON",
    "sg:tags":[
        "parlor",
        "ice",
        "cream"
    ],
    "wof:name":"Dutch Dreams Ltd",
    "wof:placetype":"venue"
},
  "geometry": {"coordinates":[-79.4207000732,43.68309021],"type":"Point"}
}