{
  "type": "Feature",
  "properties": {
    "addr:full":"5612 Templehill Rd NE Calgary AB T1Y 4W7",
    "addr:postcode":"5612;t1y 4w7",
    "addr:street":"Templehill Rd Ne",
    "iso:country":"CA",
    "sg:address":"5612 Templehill Rd NE",
    "sg:city":"Calgary",
    "sg:classifiers":[
        {
            "category":"Education",
            "subcategory":"School",
            "type":"Public Place"
        }
    ],
    "sg:phone":"+1 403 777 6740",
    "sg:postcode":"T1Y 4W7",
    "sg:province":"AB",
    "wof:name":"Guy Weadick Elementary School",
    "wof:placetype":"venue"
},
  "geometry": {"coordinates":[-113.9533,51.08672],"type":"Point"}
}