{
  "type": "Feature",
  "properties": {
    "addr:full":"1300 Dundas St E Whitby ON L1N 2K5",
    "addr:housenumber":"1300",
    "addr:postcode":"l1n 2k5",
    "addr:street":"Dundas St E",
    "iso:country":"CA",
    "sg:address":"1300 Dundas St E",
    "sg:city":"Whitby",
    "sg:classifiers":[
        {
            "category":"Autos & Motor Vehicles",
            "subcategory":"Automobile Sales",
            "type":"Retail Goods"
        }
    ],
    "sg:phone":"+1 905 668 6828",
    "sg:postcode":"L1N 2K5",
    "sg:province":"ON",
    "sg:tags":[
        "car",
        "dealer"
    ],
    "wof:name":"Midway Motors Ltd",
    "wof:placetype":"venue"
},
  "geometry": {"coordinates":[-78.920334,43.884956],"type":"Point"}
}