{
  "type": "Feature",
  "properties": {
    "iso:country":"CA",
    "sg:address":"8201 Jane St",
    "sg:city":"Concord",
    "sg:classifiers":[
        {
            "category":"Manufacturing",
            "subcategory":"Glass & Minerals",
            "type":"Manufacturing & Wholesale Goods"
        }
    ],
    "sg:phone":"+1 905 761 7666",
    "sg:postcode":"L4K 5P2",
    "sg:province":"ON",
    "sg:tags":[
        "tile",
        "marble"
    ],
    "wof:name":"Bluemar Marble & Granite",
    "wof:placetype":"venue"
},
  "geometry": {"coordinates":[-79.526939,43.806587],"type":"Point"}
}