{
  "type": "Feature",
  "properties": {
    "addr:full":"2365 Warden Ave Scarborough ON M1T 1V7",
    "addr:housenumber":"2365",
    "addr:postcode":"m1t 1v7",
    "addr:street":"Warden Ave",
    "iso:country":"CA",
    "sg:address":"2365 Warden Ave",
    "sg:city":"Scarborough",
    "sg:classifiers":[
        {
            "category":"Shopping",
            "subcategory":"Pharmacy",
            "type":"Retail Goods"
        }
    ],
    "sg:phone":"+1 416 497 5444",
    "sg:postcode":"M1T 1V7",
    "sg:province":"ON",
    "wof:name":"Shoppers Drug Mart",
    "wof:placetype":"venue"
},
  "geometry": {"coordinates":[-79.3099899292,43.7837181091],"type":"Point"}
}