{
  "type": "Feature",
  "properties": {
    "iso:country":"CA",
    "sg:address":"River Rd",
    "sg:city":"Kahnawake",
    "sg:classifiers":[
        {
            "category":"Education",
            "subcategory":"School",
            "type":"Public Place"
        }
    ],
    "sg:phone":"+1 450 632 3350",
    "sg:postcode":"J0L 1B0",
    "sg:province":"QC",
    "wof:name":"Kateri Tekakwitha School",
    "wof:placetype":"venue"
},
  "geometry": {"coordinates":[-73.6833572388,45.415802002],"type":"Point"}
}