{
  "type": "Feature",
  "properties": {
    "addr:full":"79 Bannerhill Pvt Ottawa ON K1V 0T3",
    "addr:housenumber":"79",
    "addr:postcode":"k1v 0t3",
    "addr:street":"Bannerhill Pvt",
    "iso:country":"CA",
    "sg:address":"79 Bannerhill Pvt",
    "sg:city":"Ottawa",
    "sg:classifiers":[
        {
            "category":"Building & Trades",
            "subcategory":"Cleaning & Sanitation",
            "type":"Services"
        }
    ],
    "sg:phone":"+1 613 739 1556",
    "sg:postcode":"K1V 0T3",
    "sg:province":"ON",
    "sg:tags":[
        "house"
    ],
    "wof:name":"Winnie Cleaning Svc",
    "wof:placetype":"venue"
},
  "geometry": {"coordinates":[-75.64341,45.374123],"type":"Point"}
}