{
  "type": "Feature",
  "properties": {
    "addr:full":"14421 Old Scugog Rd Blackstock ON L0B 1B0",
    "addr:housenumber":"14421",
    "addr:postcode":"l0b 1b0",
    "addr:street":"Old Scugog Rd",
    "iso:country":"CA",
    "sg:address":"14421 Old Scugog Rd",
    "sg:city":"Blackstock",
    "sg:classifiers":[
        {
            "category":"Food & Beverages",
            "subcategory":"Dairy",
            "type":"Retail Goods"
        }
    ],
    "sg:phone":"+1 905 986 5440",
    "sg:postcode":"L0B 1B0",
    "sg:province":"ON",
    "sg:tags":[
        "product"
    ],
    "wof:name":"Blackstock Mini Mart",
    "wof:placetype":"venue"
},
  "geometry": {"coordinates":[-78.823853,44.111786],"type":"Point"}
}