{
  "type": "Feature",
  "properties": {
    "addr:full":"120 Main St Canterbury NB E6H 1L9",
    "addr:housenumber":"120",
    "addr:postcode":"e6h 1l9",
    "addr:street":"Main St",
    "iso:country":"CA",
    "sg:address":"120 Main St",
    "sg:city":"Canterbury",
    "sg:classifiers":[
        {
            "category":"Shopping",
            "subcategory":"Discount & Variety Stores",
            "type":"Retail Goods"
        }
    ],
    "sg:phone":"+1 506 279 2392",
    "sg:postcode":"E6H 1L9",
    "sg:province":"NB",
    "sg:tags":[
        "merchandise",
        "general"
    ],
    "wof:name":"Russell's Place",
    "wof:placetype":"venue"
},
  "geometry": {"coordinates":[-67.46449279789999,45.8907051086],"type":"Point"}
}