{
  "type": "Feature",
  "properties": {
    "addr:full":"9797 Jasper Ave NW Edmonton AB T5J 1N9",
    "addr:housenumber":"9797",
    "addr:postcode":"t5j 1n9",
    "addr:street":"Jasper Ave Nw",
    "iso:country":"CA",
    "sg:address":"9797 Jasper Ave NW",
    "sg:city":"Edmonton",
    "sg:classifiers":[
        {
            "category":"Organizations",
            "subcategory":"Professional Association",
            "type":"Services"
        }
    ],
    "sg:phone":"+1 780 426 1874",
    "sg:postcode":"T5J 1N9",
    "sg:province":"AB",
    "wof:name":"Alberta Culinary Arts Fndtn",
    "wof:placetype":"venue"
},
  "geometry": {"coordinates":[-113.486679,53.541687],"type":"Point"}
}