{
  "type": "Feature",
  "properties": {
    "iso:country":"CA",
    "sg:address":"191 Boul DE Mortagne",
    "sg:city":"Boucherville",
    "sg:classifiers":[
        {
            "category":"Personal",
            "subcategory":"Beauty Salon",
            "type":"Services"
        }
    ],
    "sg:phone":"+1 450 449 1617",
    "sg:postcode":"J4B 1A9",
    "sg:province":"QC",
    "wof:name":"Karin Coiffure",
    "wof:placetype":"venue"
},
  "geometry": {"coordinates":[-73.4473953247,45.5796470642],"type":"Point"}
}