{
  "type": "Feature",
  "properties": {
    "iso:country":"CA",
    "sg:address":"37 Glendale Dr",
    "sg:city":"Tillsonburg",
    "sg:classifiers":[
        {
            "category":"Education",
            "subcategory":"School",
            "type":"Public Place"
        }
    ],
    "sg:phone":"+1 519 842 4207",
    "sg:postcode":"N4G 1J6",
    "sg:province":"ON",
    "wof:name":"Glendale High School",
    "wof:placetype":"venue"
},
  "geometry": {"coordinates":[-80.740906,42.868298],"type":"Point"}
}