{
  "type": "Feature",
  "properties": {
    "addr:full":"175 Main St Dartmouth NS B2X 1S1",
    "addr:housenumber":"175",
    "addr:postcode":"b2x 1s1",
    "addr:street":"Main St",
    "iso:country":"CA",
    "sg:address":"175 Main St",
    "sg:city":"Dartmouth",
    "sg:classifiers":[
        {
            "category":"Insurance",
            "subcategory":"Insurance Agent",
            "type":"Services"
        }
    ],
    "sg:phone":"+1 902 434 9070",
    "sg:postcode":"B2X 1S1",
    "sg:province":"NS",
    "wof:name":"King Insurance",
    "wof:placetype":"venue"
},
  "geometry": {"coordinates":[-63.5293579102,44.6844482422],"type":"Point"}
}