{
  "type": "Feature",
  "properties": {
    "iso:country":"CA",
    "sg:address":"80 Rue Saint-Mathieu",
    "sg:city":"Beloeil",
    "sg:classifiers":[
        {
            "category":"Restaurant",
            "type":"Food & Drink"
        }
    ],
    "sg:phone":"+1 450 467 7744",
    "sg:postcode":"J3G 6N7",
    "sg:province":"QC",
    "wof:name":"Restaurant Le Saint-Mathieu",
    "wof:placetype":"venue"
},
  "geometry": {"coordinates":[-73.2001495361,45.5706863403],"type":"Point"}
}