{
  "type": "Feature",
  "properties": {
    "iso:country":"CA",
    "sg:address":"2033 Townline Rd N",
    "sg:city":"Oshawa",
    "sg:classifiers":[
        {
            "category":"Home & Garden",
            "subcategory":"Furniture",
            "type":"Retail Goods"
        }
    ],
    "sg:phone":"+1 905 432 2074",
    "sg:postcode":"L1H 8L7",
    "sg:province":"ON",
    "sg:tags":[
        "kitchen",
        "shelving",
        "cabinet"
    ],
    "wof:name":"Cabinets By Rosebrook",
    "wof:placetype":"venue"
},
  "geometry": {"coordinates":[-78.8595046997,43.8886795044],"type":"Point"}
}