{
  "type": "Feature",
  "properties": {
    "addr:full":"Lethbridge AB T1J 4L9",
    "addr:postcode":"t1j 4l9",
    "iso:country":"CA",
    "sg:city":"Lethbridge",
    "sg:classifiers":[
        {
            "category":"Shopping",
            "subcategory":"Shoes",
            "type":"Retail Goods"
        }
    ],
    "sg:phone":"+1 403 328 6155",
    "sg:postcode":"T1J 4L9",
    "sg:province":"AB",
    "wof:name":"Rnr Outdoors",
    "wof:placetype":"venue"
},
  "geometry": {"coordinates":[-112.840378,49.698063],"type":"Point"}
}