{
  "type": "Feature",
  "properties": {
    "addr:full":"7595 Victoria Dr Vancouver BC V5P 3Z6",
    "addr:housenumber":"7595",
    "addr:postcode":"v5p 3z6",
    "addr:street":"Victoria Dr",
    "iso:country":"CA",
    "sg:address":"7595 Victoria Dr",
    "sg:city":"Vancouver",
    "sg:classifiers":[
        {
            "category":"Social Services",
            "type":"Services"
        }
    ],
    "sg:phone":"+1 604 324 2267",
    "sg:postcode":"V5P 3Z6",
    "sg:province":"BC",
    "sg:tags":[
        "club",
        "youth",
        "center",
        "organization"
    ],
    "wof:name":"Camp Potlach",
    "wof:placetype":"venue"
},
  "geometry": {"coordinates":[-123.066017151,49.2158203125],"type":"Point"}
}