{
  "type": "Feature",
  "properties": {
    "addr:full":"99 New Cove Rd St. John's NL A1A 2C2",
    "addr:housenumber":"99",
    "addr:postcode":"a1a 2c2",
    "addr:street":"New Cove Rd",
    "iso:country":"CA",
    "sg:address":"99 New Cove Rd",
    "sg:city":"St. John's",
    "sg:classifiers":[
        {
            "category":"Shopping",
            "type":"Retail Goods"
        }
    ],
    "sg:phone":"+1 709 753 8124",
    "sg:postcode":"A1A 2C2",
    "sg:province":"NL",
    "sg:tags":[
        "ice"
    ],
    "wof:name":"A-1 Ice Maker Ltd",
    "wof:placetype":"venue"
},
  "geometry": {"coordinates":[-52.709015,47.581612],"type":"Point"}
}