{
  "type": "Feature",
  "properties": {
    "addr:full":"465 Devonain St Estevan SK S4A 2A7",
    "addr:housenumber":"465",
    "addr:postcode":"s4a 2a7",
    "addr:street":"Devonain St",
    "iso:country":"CA",
    "sg:address":"465 Devonain St",
    "sg:city":"Estevan",
    "sg:classifiers":[
        {
            "category":"Mining & Drilling",
            "type":"Manufacturing & Wholesale Goods"
        }
    ],
    "sg:phone":"+1 306 634 5155",
    "sg:postcode":"S4A 2A7",
    "sg:province":"SK",
    "sg:tags":[
        "oil",
        "well"
    ],
    "wof:name":"Sanjel Corporation",
    "wof:placetype":"venue"
},
  "geometry": {"coordinates":[-102.974098,49.136459],"type":"Point"}
}