{
  "type": "Feature",
  "properties": {
    "iso:country":"CA",
    "sg:address":"1452 Rue Saint-Mathieu",
    "sg:city":"Montreal",
    "sg:classifiers":[
        {
            "category":"Professional",
            "subcategory":"Art Services",
            "type":"Services"
        }
    ],
    "sg:phone":"+1 514 933 1222",
    "sg:postcode":"H3H 2H9",
    "sg:province":"QC",
    "sg:tags":[
        "graphic",
        "designer"
    ],
    "wof:name":"Origami Communication Design",
    "wof:placetype":"venue"
},
  "geometry": {"coordinates":[-73.580032,45.494106],"type":"Point"}
}