{
  "type": "Feature",
  "properties": {
    "addr:full":"North Vancouver BC V7L 2G7",
    "addr:postcode":"v7l 2g7",
    "iso:country":"CA",
    "sg:city":"North Vancouver",
    "sg:classifiers":[
        {
            "category":"Building & Trades",
            "subcategory":"Landscaping Services",
            "type":"Services"
        }
    ],
    "sg:phone":"+1 604 980 2254",
    "sg:postcode":"V7L 2G7",
    "sg:province":"BC",
    "sg:tags":[
        "designer",
        "landscape"
    ],
    "wof:name":"James Jarvis & Assoc",
    "wof:placetype":"venue"
},
  "geometry": {"coordinates":[-123.068451,49.317997],"type":"Point"}
}