{
  "type": "Feature",
  "properties": {
    "iso:country":"CA",
    "sg:city":"Winnipeg",
    "sg:classifiers":[
        {
            "category":"Wholesale",
            "subcategory":"Machinery & Supplies",
            "type":"Manufacturing & Wholesale Goods"
        }
    ],
    "sg:phone":"+1 204 668 8886",
    "sg:postcode":"R2J 4H2",
    "sg:province":"MB",
    "sg:tags":[
        "equipment",
        "safety",
        "clothing"
    ],
    "wof:name":"Century Vallen",
    "wof:placetype":"venue"
},
  "geometry": {"coordinates":[-97.0493927002,49.8844909668],"type":"Point"}
}