{
  "type": "Feature",
  "properties": {
    "addr:full":"Edmonton AB T6E 0A6",
    "addr:postcode":"t6e 0a6",
    "iso:country":"CA",
    "sg:city":"Edmonton",
    "sg:classifiers":[
        {
            "category":"Professional",
            "subcategory":"Employment Agencies",
            "type":"Services"
        }
    ],
    "sg:phone":"+1 780 420 9999",
    "sg:postcode":"T6E 0A6",
    "sg:province":"AB",
    "sg:tags":[
        "opportunity"
    ],
    "wof:name":"I S2 Staffing Svc Inc",
    "wof:placetype":"venue"
},
  "geometry": {"coordinates":[-113.481323,53.488312],"type":"Point"}
}