{
  "type": "Feature",
  "properties": {
    "addr:full":"Saint-Felicien QC G8K 1R2",
    "addr:postcode":"g8k 1r2",
    "iso:country":"CA",
    "sg:city":"Saint-Felicien",
    "sg:classifiers":[
        {
            "category":"Professional",
            "subcategory":"Research",
            "type":"Services"
        }
    ],
    "sg:phone":"+1 418 679 9282",
    "sg:postcode":"G8K 1R2",
    "sg:province":"QC",
    "sg:tags":[
        "foundation",
        "philanthropic"
    ],
    "wof:name":"Fondation DE LA Societe Inc",
    "wof:placetype":"venue"
},
  "geometry": {"coordinates":[-72.443718,48.650993],"type":"Point"}
}