{
  "type": "Feature",
  "properties": {
    "addr:full":"1290 Ch Du Bord-DE-L'Eau Laval QC H7Y 1C1",
    "addr:housenumber":"1290",
    "addr:postcode":"h7y 1c1",
    "addr:street":"Ch Du Bord-De-L'Eau",
    "iso:country":"CA",
    "sg:address":"1290 Ch Du Bord-DE-L'Eau",
    "sg:city":"Laval",
    "sg:classifiers":[
        {
            "category":"Retail",
            "subcategory":"Auto Repair",
            "type":"Services"
        }
    ],
    "sg:phone":"+1 450 689 2933",
    "sg:postcode":"H7Y 1C1",
    "sg:province":"QC",
    "sg:tags":[
        "repairing",
        "automobile"
    ],
    "wof:name":"Garage Jean Riendeau Enr",
    "wof:placetype":"venue"
},
  "geometry": {"coordinates":[-73.77748099999999,45.52153],"type":"Point"}
}