{
  "type": "Feature",
  "properties": {
    "addr:full":"4470 Main St West St Paul MB R4A 3A1",
    "addr:housenumber":"4470",
    "addr:postcode":"r4a 3a1",
    "addr:street":"Main St",
    "iso:country":"CA",
    "sg:address":"4470 Main St",
    "sg:city":"West St Paul",
    "sg:classifiers":[
        {
            "category":"Shopping",
            "type":"Retail Goods"
        }
    ],
    "sg:phone":"+1 204 334 4721",
    "sg:postcode":"R4A 3A1",
    "sg:province":"MB",
    "sg:tags":[
        "monument"
    ],
    "wof:name":"Ray From Memorials",
    "wof:placetype":"venue"
},
  "geometry": {"coordinates":[-97.052505,50.009247],"type":"Point"}
}