{
  "type": "Feature",
  "properties": {
    "addr:full":"730 Main St Vancouver BC V6A 2V7",
    "addr:housenumber":"730",
    "addr:postcode":"v6a 2v7",
    "addr:street":"Main St",
    "iso:country":"CA",
    "sg:address":"730 Main St",
    "sg:city":"Vancouver",
    "sg:classifiers":[
        {
            "category":"Restaurant",
            "type":"Food & Drink"
        }
    ],
    "sg:phone":"+1 604 689 8645",
    "sg:postcode":"V6A 2V7",
    "sg:province":"BC",
    "wof:name":"Brickhouse",
    "wof:placetype":"venue"
},
  "geometry": {"coordinates":[-123.099541,49.278248],"type":"Point"}
}