{
  "type": "Feature",
  "properties": {
    "addr:full":"10225 Av Ryan Dorval QC H9P 1A2",
    "addr:postcode":"h9p 1a2",
    "addr:street":"Av Ryan",
    "iso:country":"CA",
    "sg:address":"10225 Av Ryan",
    "sg:city":"Dorval",
    "sg:classifiers":[
        {
            "category":"Airport",
            "type":"Transportation"
        }
    ],
    "sg:phone":"+1 514 636 6242",
    "sg:postcode":"H9P 1A2",
    "sg:province":"QC",
    "sg:tags":[
        "aircraft",
        "ferrying",
        "transporting"
    ],
    "wof:name":"Phoenix Flight Operations Ltd",
    "wof:placetype":"venue"
},
  "geometry": {"coordinates":[-73.71957399999999,45.468334],"type":"Point"}
}