{
  "type": "Feature",
  "properties": {
    "addr:full":"266 Central Ave Grimsby ON L3M 1X7",
    "addr:housenumber":"266",
    "addr:postcode":"l3m 1x7",
    "addr:street":"Central Ave",
    "iso:country":"CA",
    "sg:address":"266 Central Ave",
    "sg:city":"Grimsby",
    "sg:classifiers":[
        {
            "category":"Home & Garden",
            "subcategory":"Household Appliances",
            "type":"Retail Goods"
        }
    ],
    "sg:phone":"+1 905 945 9688",
    "sg:postcode":"L3M 1X7",
    "sg:province":"ON",
    "wof:name":"Windmill Major Appliances Rpr",
    "wof:placetype":"venue"
},
  "geometry": {"coordinates":[-79.53029600000001,43.188702],"type":"Point"}
}