{
  "type": "Feature",
  "properties": {
    "addr:full":"4247 Rue Jean-Talon E Saint-Leonard QC H1S 1J9",
    "addr:housenumber":"4247",
    "addr:postcode":"h1s 1j9",
    "addr:street":"Rue Jean-Talon E",
    "iso:country":"CA",
    "sg:address":"4247 Rue Jean-Talon E",
    "sg:city":"Saint-Leonard",
    "sg:classifiers":[
        {
            "category":"Restaurant",
            "type":"Food & Drink"
        }
    ],
    "sg:phone":"+1 514 374 3440",
    "sg:postcode":"H1S 1J9",
    "sg:province":"QC",
    "wof:name":"Harvey's",
    "wof:placetype":"venue"
},
  "geometry": {"coordinates":[-73.590171814,45.5681228638],"type":"Point"}
}