{
  "type": "Feature",
  "properties": {
    "addr:full":"146 Old Kennedy Rd Markham ON L3R 0L5",
    "addr:housenumber":"146",
    "addr:postcode":"l3r 0l5",
    "addr:street":"Old Kennedy Rd",
    "iso:country":"CA",
    "sg:address":"146 Old Kennedy Rd",
    "sg:city":"Markham",
    "sg:classifiers":[
        {
            "category":"Shopping",
            "subcategory":"Bicycles & Sporting Goods",
            "type":"Retail Goods"
        }
    ],
    "sg:phone":"+1 905 415 8777",
    "sg:postcode":"L3R 0L5",
    "sg:province":"ON",
    "sg:tags":[
        "apparel",
        "bowling",
        "accessory"
    ],
    "wof:name":"Woody's Pro Shop",
    "wof:placetype":"venue"
},
  "geometry": {"coordinates":[-79.30122375489999,43.8288764954],"type":"Point"}
}