{
  "type": "Feature",
  "properties": {
    "addr:full":"187 Charlotte St Peterborough ON K9J 2T7",
    "addr:housenumber":"187",
    "addr:postcode":"k9j 2t7",
    "addr:street":"Charlotte St",
    "iso:country":"CA",
    "sg:address":"187 Charlotte St",
    "sg:city":"Peterborough",
    "sg:classifiers":[
        {
            "category":"Restaurant",
            "type":"Food & Drink"
        }
    ],
    "sg:phone":"+1 705 749 5747",
    "sg:postcode":"K9J 2T7",
    "sg:province":"ON",
    "wof:name":"Enisa Diner",
    "wof:placetype":"venue"
},
  "geometry": {"coordinates":[-78.32089999999999,44.303257],"type":"Point"}
}