{
  "type": "Feature",
  "properties": {
    "iso:country":"CA",
    "sg:city":"Calgary",
    "sg:classifiers":[
        {
            "category":"Home & Garden",
            "subcategory":"Household Appliances",
            "type":"Retail Goods"
        }
    ],
    "sg:phone":"+1 403 568 8868",
    "sg:postcode":"T3J 4K3",
    "sg:province":"AB",
    "sg:tags":[
        "equipment",
        "video"
    ],
    "wof:name":"Avs Electronics Ltd",
    "wof:placetype":"venue"
},
  "geometry": {"coordinates":[-113.96565246599999,51.0988121033],"type":"Point"}
}