{
  "type": "Feature",
  "properties": {
    "addr:full":"3143 River Alvinston ON N0N 1A0",
    "addr:housenumber":"3143",
    "addr:postcode":"n0n 1a0",
    "addr:street":"River",
    "iso:country":"CA",
    "sg:address":"3143 River",
    "sg:city":"Alvinston",
    "sg:classifiers":[
        {
            "category":"Organizations",
            "subcategory":"Religious Organization",
            "type":"Services"
        }
    ],
    "sg:phone":"+1 519 898 2877",
    "sg:postcode":"N0N 1A0",
    "sg:province":"ON",
    "sg:tags":[
        "church"
    ],
    "wof:name":"St Matthew's Roman Catholic",
    "wof:placetype":"venue"
},
  "geometry": {"coordinates":[-81.858772,42.813675],"type":"Point"}
}