{
  "type": "Feature",
  "properties": {
    "iso:country":"CA",
    "sg:address":"9471 Emerald Dr",
    "sg:city":"Whistler",
    "sg:classifiers":[
        {
            "category":"Manufacturing",
            "subcategory":"Buildings",
            "type":"Manufacturing & Wholesale Goods"
        }
    ],
    "sg:phone":"+1 604 932 3046",
    "sg:postcode":"V0N 1B9",
    "sg:province":"BC",
    "sg:tags":[
        "home",
        "log",
        "cabin"
    ],
    "wof:name":"Colin Solly Construction",
    "wof:placetype":"venue"
},
  "geometry": {"coordinates":[-122.93135833700001,50.1603507996],"type":"Point"}
}