{
  "type": "Feature",
  "properties": {
    "addr:full":"638 the Kingsway Peterborough ON K9J 7C8",
    "addr:housenumber":"638",
    "addr:postcode":"k9j 7c8",
    "addr:street":"The Kingsway",
    "iso:country":"CA",
    "sg:address":"638 the Kingsway",
    "sg:city":"Peterborough",
    "sg:classifiers":[
        {
            "category":"Wholesale",
            "subcategory":"Durable Goods & Equipment",
            "type":"Manufacturing & Wholesale Goods"
        }
    ],
    "sg:phone":"+1 705 748 5422",
    "sg:postcode":"K9J 7C8",
    "sg:province":"ON",
    "sg:tags":[
        "compact",
        "record",
        "disc",
        "tape"
    ],
    "wof:name":"Scandinavian Record Import Ltd",
    "wof:placetype":"venue"
},
  "geometry": {"coordinates":[-78.34252166749999,44.2763442993],"type":"Point"}
}