{
  "type": "Feature",
  "properties": {
    "iso:country":"CA",
    "sg:address":"12239 Rue James-Morrice",
    "sg:city":"Montreal",
    "sg:classifiers":[
        {
            "category":"Restaurant",
            "type":"Food & Drink"
        }
    ],
    "sg:phone":"+1 514 392 0080",
    "sg:postcode":"H3M 2H2",
    "sg:province":"QC",
    "wof:name":"A K Tomelex Inc",
    "wof:placetype":"venue"
},
  "geometry": {"coordinates":[-73.70285,45.541008],"type":"Point"}
}