{
  "type": "Feature",
  "properties": {
    "addr:full":"4385 Rue Lavoisier Quebec QC G2C 1G8",
    "addr:housenumber":"4385",
    "addr:postcode":"g2c 1g8",
    "addr:street":"Rue Lavoisier",
    "iso:country":"CA",
    "sg:address":"4385 Rue Lavoisier",
    "sg:city":"Quebec",
    "sg:classifiers":[
        {
            "category":"Personal",
            "subcategory":"Beauty Salon",
            "type":"Services"
        }
    ],
    "sg:phone":"+1 418 842 8622",
    "sg:postcode":"G2C 1G8",
    "sg:province":"QC",
    "wof:name":"Salon Jeannine",
    "wof:placetype":"venue"
},
  "geometry": {"coordinates":[-71.3524551392,46.8280944824],"type":"Point"}
}