{
  "type": "Feature",
  "properties": {
    "addr:full":"800 Flint Rd North York ON M3J 2J5",
    "addr:housenumber":"800",
    "addr:postcode":"m3j 2j5",
    "addr:street":"Flint Rd",
    "iso:country":"CA",
    "sg:address":"800 Flint Rd",
    "sg:city":"North York",
    "sg:classifiers":[
        {
            "category":"Home & Garden",
            "subcategory":"Furniture",
            "type":"Retail Goods"
        }
    ],
    "sg:phone":"+1 416 661 8406",
    "sg:postcode":"M3J 2J5",
    "sg:province":"ON",
    "sg:tags":[
        "futon"
    ],
    "wof:name":"Paragon Furniture Mfg & Sales",
    "wof:placetype":"venue"
},
  "geometry": {"coordinates":[-79.481239,43.774799],"type":"Point"}
}