{
  "type": "Feature",
  "properties": {
    "addr:full":"3867 14th Ave W Vancouver BC V6R 2X1",
    "addr:housenumber":"3867",
    "addr:postcode":"v6r 2x1",
    "addr:street":"14Th Ave W",
    "iso:country":"CA",
    "sg:address":"3867 14th Ave W",
    "sg:city":"Vancouver",
    "sg:classifiers":[
        {
            "category":"Farming",
            "subcategory":"Farm",
            "type":"Manufacturing & Wholesale Goods"
        }
    ],
    "sg:phone":"+1 604 222 8599",
    "sg:postcode":"V6R 2X1",
    "sg:province":"BC",
    "sg:tags":[
        "mushroom"
    ],
    "wof:name":"Intrex Trading Inc",
    "wof:placetype":"venue"
},
  "geometry": {"coordinates":[-123.18985000000001,49.260056],"type":"Point"}
}