{
  "type": "Feature",
  "properties": {
    "addr:full":"10212 Rue Lajeunesse Montreal QC H3L 2E2",
    "addr:housenumber":"10212",
    "addr:postcode":"h3l 2e2",
    "addr:street":"Rue Lajeunesse",
    "iso:country":"CA",
    "sg:address":"10212 Rue Lajeunesse",
    "sg:city":"Montreal",
    "sg:classifiers":[
        {
            "category":"Wholesale",
            "subcategory":"Groceries",
            "type":"Manufacturing & Wholesale Goods"
        }
    ],
    "sg:phone":"+1 514 389 8228",
    "sg:postcode":"H3L 2E2",
    "sg:province":"QC",
    "sg:tags":[
        "grocer"
    ],
    "wof:name":"Distribution Normade",
    "wof:placetype":"venue"
},
  "geometry": {"coordinates":[-73.66059112550001,45.5528793335],"type":"Point"}
}