{
  "type": "Feature",
  "properties": {
    "addr:full":"Mississauga ON L4Y 4G6",
    "addr:postcode":"l4y 4g6",
    "iso:country":"CA",
    "sg:city":"Mississauga",
    "sg:classifiers":[
        {
            "category":"Personal",
            "subcategory":"Beauty Salon",
            "type":"Services"
        }
    ],
    "sg:phone":"+1 905 897 1808",
    "sg:postcode":"L4Y 4G6",
    "sg:province":"ON",
    "wof:name":"Young & Beauty Image",
    "wof:placetype":"venue"
},
  "geometry": {"coordinates":[-79.59491,43.599052],"type":"Point"}
}