{
  "type": "Feature",
  "properties": {
    "iso:country":"CA",
    "sg:address":"8378 Prince Edward St",
    "sg:city":"Vancouver",
    "sg:classifiers":[
        {
            "category":"Shopping",
            "subcategory":"Computers & Home Electronics",
            "type":"Retail Goods"
        }
    ],
    "sg:phone":"+1 604 251 3115",
    "sg:postcode":"V5X 3R9",
    "sg:province":"BC",
    "sg:tags":[
        "parts",
        "supply"
    ],
    "wof:name":"Western Imaging Solutions",
    "wof:placetype":"venue"
},
  "geometry": {"coordinates":[-123.098251343,49.2081871033],"type":"Point"}
}