{
  "type": "Feature",
  "properties": {
    "iso:country":"CA",
    "sg:address":"PO Box 819",
    "sg:city":"Stettler",
    "sg:classifiers":[
        {
            "category":"Mining & Drilling",
            "type":"Manufacturing & Wholesale Goods"
        }
    ],
    "sg:phone":"+1 403 742 1624",
    "sg:postcode":"T0C 2L0",
    "sg:province":"AB",
    "sg:tags":[
        "field",
        "oil"
    ],
    "wof:name":"Wadeall Inc",
    "wof:placetype":"venue"
},
  "geometry": {"coordinates":[-112.711014,52.323536],"type":"Point"}
}