{
  "type": "Feature",
  "properties": {
    "addr:full":"1090 Av Pratte Saint-Hyacinthe QC J2S 4B6",
    "addr:housenumber":"1090",
    "addr:postcode":"j2s 4b6",
    "addr:street":"Av Pratte",
    "iso:country":"CA",
    "sg:address":"1090 Av Pratte",
    "sg:city":"Saint-Hyacinthe",
    "sg:classifiers":[
        {
            "category":"Education",
            "subcategory":"School",
            "type":"Public Place"
        }
    ],
    "sg:phone":"+1 450 771 0644",
    "sg:postcode":"J2S 4B6",
    "sg:province":"QC",
    "wof:name":"Ecole Petite Academie Du Boise",
    "wof:placetype":"venue"
},
  "geometry": {"coordinates":[-72.94306899999999,45.632732],"type":"Point"}
}