{
  "type": "Feature",
  "properties": {
    "addr:full":"522 St Clair Ave W Toronto ON M6C 1A2",
    "addr:housenumber":"522",
    "addr:postcode":"m6c 1a2",
    "addr:street":"St Clair Ave W",
    "iso:country":"CA",
    "sg:address":"522 St Clair Ave W",
    "sg:city":"Toronto",
    "sg:classifiers":[
        {
            "category":"Retail",
            "subcategory":"Laundry & Dry Cleaning",
            "type":"Services"
        }
    ],
    "sg:phone":"+1 416 653 0167",
    "sg:postcode":"M6C 1A2",
    "sg:province":"ON",
    "sg:tags":[
        "cleaners"
    ],
    "wof:name":"Premier Cleaners",
    "wof:placetype":"venue"
},
  "geometry": {"coordinates":[-79.41894499999999,43.683159],"type":"Point"}
}