{
  "type": "Feature",
  "properties": {
    "addr:full":"2908 Yonge St Toronto ON M4N 2J7",
    "addr:housenumber":"2908",
    "addr:postcode":"m4n 2j7",
    "addr:street":"Yonge St",
    "iso:country":"CA",
    "sg:address":"2908 Yonge St",
    "sg:city":"Toronto",
    "sg:classifiers":[
        {
            "category":"Retail",
            "subcategory":"Auto Repair",
            "type":"Services"
        }
    ],
    "sg:phone":"+1 416 488 7405",
    "sg:postcode":"M4N 2J7",
    "sg:province":"ON",
    "sg:tags":[
        "repairing",
        "automobile"
    ],
    "wof:name":"Ed Ross Auto Svc",
    "wof:placetype":"venue"
},
  "geometry": {"coordinates":[-79.40171813960001,43.7217140198],"type":"Point"}
}