{
  "type": "Feature",
  "properties": {
    "addr:full":"3300 Steeles Ave W Concord ON L4K 2Y4",
    "addr:housenumber":"3300",
    "addr:postcode":"l4k 2y4",
    "addr:street":"Steeles Ave W",
    "iso:country":"CA",
    "sg:address":"3300 Steeles Ave W",
    "sg:city":"Concord",
    "sg:classifiers":[
        {
            "category":"Professional",
            "subcategory":"Accounting & Tax Preparation",
            "type":"Services"
        }
    ],
    "sg:phone":"+1 905 660 1817",
    "sg:postcode":"L4K 2Y4",
    "sg:province":"ON",
    "sg:tags":[
        "accountant"
    ],
    "wof:name":"Blumenfeld Woznica & CO",
    "wof:placetype":"venue"
},
  "geometry": {"coordinates":[-79.527199,43.774387],"type":"Point"}
}