{
  "type": "Feature",
  "properties": {
    "iso:country":"CA",
    "sg:address":"1126 Roland St",
    "sg:city":"Thunder Bay",
    "sg:classifiers":[
        {
            "category":"Professional",
            "subcategory":"Computer Services",
            "type":"Services"
        }
    ],
    "sg:phone":"+1 807 626 9777",
    "sg:postcode":"P7B 5M4",
    "sg:province":"ON",
    "sg:tags":[
        "internet"
    ],
    "wof:name":"Wabang Creative Technology",
    "wof:placetype":"venue"
},
  "geometry": {"coordinates":[-89.2567367554,48.4021644592],"type":"Point"}
}