{
  "type": "Feature",
  "properties": {
    "iso:country":"CA",
    "sg:address":"167 Rue DE LA Reine # 24",
    "sg:city":"Gaspe",
    "sg:classifiers":[
        {
            "category":"Health Services",
            "subcategory":"Optometrist",
            "type":"Services"
        }
    ],
    "sg:phone":"+1 418 368 2666",
    "sg:postcode":"G4X 2W6",
    "sg:province":"QC",
    "wof:name":"Beaulieu, Rock OD",
    "wof:placetype":"venue"
},
  "geometry": {"coordinates":[-64.4849243164,48.8287162781],"type":"Point"}
}