{
  "type": "Feature",
  "properties": {
    "addr:full":"Laval QC H7S 1Y9",
    "addr:postcode":"h7s 1y9",
    "iso:country":"CA",
    "sg:city":"Laval",
    "sg:classifiers":[
        {
            "category":"Shopping",
            "subcategory":"Optical Goods",
            "type":"Retail Goods"
        }
    ],
    "sg:phone":"+1 450 688 1771",
    "sg:postcode":"H7S 1Y9",
    "sg:province":"QC",
    "sg:tags":[
        "optometrist"
    ],
    "wof:name":"Greiche & Scaff Optometristes",
    "wof:placetype":"venue"
},
  "geometry": {"coordinates":[-73.7309799194,45.5636062622],"type":"Point"}
}