{
  "type": "Feature",
  "properties": {
    "addr:full":"3230 Mountbatten St Saskatoon SK S7M 3T6",
    "addr:housenumber":"3230",
    "addr:postcode":"s7m 3t6",
    "addr:street":"Mountbatten St",
    "iso:country":"CA",
    "sg:address":"3230 Mountbatten St",
    "sg:city":"Saskatoon",
    "sg:classifiers":[
        {
            "category":"Health Services",
            "subcategory":"Nursing And Care Facility",
            "type":"Services"
        }
    ],
    "sg:phone":"+1 306 978 1441",
    "sg:postcode":"S7M 3T6",
    "sg:province":"SK",
    "sg:tags":[
        "personal",
        "home"
    ],
    "wof:name":"A A Personal Care Home",
    "wof:placetype":"venue"
},
  "geometry": {"coordinates":[-106.728386,52.108353],"type":"Point"}
}