{
  "type": "Feature",
  "properties": {
    "iso:country":"CA",
    "sg:address":"615 6E Av N",
    "sg:city":"Aubert-Gallion",
    "sg:classifiers":[
        {
            "category":"Manufacturing",
            "subcategory":"Tools & Machinery",
            "type":"Manufacturing & Wholesale Goods"
        }
    ],
    "sg:phone":"+1 418 227 7730",
    "sg:postcode":"G5Y 8H9",
    "sg:province":"QC",
    "sg:tags":[
        "pump"
    ],
    "wof:name":"Pompes Mario Couture",
    "wof:placetype":"venue"
},
  "geometry": {"coordinates":[-70.7030410767,46.1291618347],"type":"Point"}
}