{
  "type": "Feature",
  "properties": {
    "addr:full":"Alban ON P0M 1A0",
    "addr:postcode":"p0m 1a0",
    "iso:country":"CA",
    "sg:city":"Alban",
    "sg:classifiers":[
        {
            "category":"Travel",
            "subcategory":"Hotels & Motels",
            "type":"Entertainment"
        }
    ],
    "sg:phone":"+1 705 857 2788",
    "sg:postcode":"P0M 1A0",
    "sg:province":"ON",
    "wof:name":"French River Inn",
    "wof:placetype":"venue"
},
  "geometry": {"coordinates":[-80.622711,46.104706],"type":"Point"}
}