{
  "type": "Feature",
  "properties": {
    "addr:full":"1097 Upper Prince St Sydney NS B1P 5P5",
    "addr:housenumber":"1097",
    "addr:postcode":"b1p 5p5",
    "addr:street":"Upper Prince St",
    "iso:country":"CA",
    "sg:address":"1097 Upper Prince St",
    "sg:city":"Sydney",
    "sg:classifiers":[
        {
            "category":"Wholesale",
            "subcategory":"Electrical",
            "type":"Manufacturing & Wholesale Goods"
        }
    ],
    "sg:phone":"+1 902 562 5556",
    "sg:postcode":"B1P 5P5",
    "sg:province":"NS",
    "sg:tags":[
        "equipment",
        "electric",
        "supply"
    ],
    "wof:name":"Wesco Distribution-Canada Inc",
    "wof:placetype":"venue"
},
  "geometry": {"coordinates":[-60.1545333862,46.1417617798],"type":"Point"}
}