{
  "type": "Feature",
  "properties": {
    "addr:full":"150 Boul DE Montarville # 205 Boucherville QC J4B 6N1",
    "addr:housenumber":"150",
    "addr:postcode":"j4b 6n1",
    "addr:street":"Boul De Montarville # 205",
    "iso:country":"CA",
    "sg:address":"150 Boul DE Montarville # 205",
    "sg:city":"Boucherville",
    "sg:classifiers":[
        {
            "category":"Health Services",
            "subcategory":"Health Practitioner",
            "type":"Services"
        }
    ],
    "sg:phone":"+1 450 449 3963",
    "sg:postcode":"J4B 6N1",
    "sg:province":"QC",
    "sg:tags":[
        "psychologist"
    ],
    "wof:name":"Mc Donald, Diane",
    "wof:placetype":"venue"
},
  "geometry": {"coordinates":[-73.4519119263,45.6027679443],"type":"Point"}
}