{
  "type": "Feature",
  "properties": {
    "addr:full":"925 Rathburn Rd E # 3B Mississauga ON L4W 4C3",
    "addr:housenumber":"925",
    "addr:postcode":"l4w 4c3",
    "addr:street":"Rathburn Rd E # 3B",
    "iso:country":"CA",
    "sg:address":"925 Rathburn Rd E # 3B",
    "sg:city":"Mississauga",
    "sg:classifiers":[
        {
            "category":"Restaurant",
            "type":"Food & Drink"
        }
    ],
    "sg:phone":"+1 905 277 4298",
    "sg:postcode":"L4W 4C3",
    "sg:province":"ON",
    "wof:name":"Madras Dosa Hut",
    "wof:placetype":"venue"
},
  "geometry": {"coordinates":[-79.61694300000001,43.615688],"type":"Point"}
}