{
  "type": "Feature",
  "properties": {
    "iso:country":"CA",
    "sg:address":"215 Carlingview Dr",
    "sg:city":"Etobicoke",
    "sg:classifiers":[
        {
            "category":"Restaurant",
            "type":"Food & Drink"
        }
    ],
    "sg:phone":"+1 416 674 7772",
    "sg:postcode":"M9W 5X8",
    "sg:province":"ON",
    "wof:name":"Arizona B Bar & Grill",
    "wof:placetype":"venue"
},
  "geometry": {"coordinates":[-79.5944595337,43.6848640442],"type":"Point"}
}