{
  "type": "Feature",
  "properties": {
    "iso:country":"CA",
    "sg:address":"2227 Av Old Orchard",
    "sg:city":"Montreal",
    "sg:classifiers":[
        {
            "category":"Professional",
            "subcategory":"Management & Consulting",
            "type":"Services"
        }
    ],
    "sg:phone":"+1 514 484 0344",
    "sg:postcode":"H4A 3A7",
    "sg:province":"QC",
    "sg:tags":[
        "consultant",
        "instructional"
    ],
    "wof:name":"Desmeules Formation",
    "wof:placetype":"venue"
},
  "geometry": {"coordinates":[-73.61089324949999,45.4713630676],"type":"Point"}
}