{
  "type": "Feature",
  "properties": {
    "addr:full":"3 Walnut St Pine Falls MB R0E 1M0",
    "addr:housenumber":"3",
    "addr:postcode":"r0e 1m0",
    "addr:street":"Walnut St",
    "iso:country":"CA",
    "sg:address":"3 Walnut St",
    "sg:city":"Pine Falls",
    "sg:classifiers":[
        {
            "category":"Government",
            "subcategory":"Office",
            "type":"Public Place"
        }
    ],
    "sg:phone":"+1 204 367 8954",
    "sg:postcode":"R0E 1M0",
    "sg:province":"MB",
    "sg:tags":[
        "village"
    ],
    "wof:name":"Townsite of Pine Falls",
    "wof:placetype":"venue"
},
  "geometry": {"coordinates":[-96.217575,50.567356],"type":"Point"}
}