{
  "type": "Feature",
  "properties": {
    "addr:full":"North York ON M3K 1E2",
    "addr:postcode":"m3k 1e2",
    "iso:country":"CA",
    "sg:city":"North York",
    "sg:classifiers":[
        {
            "category":"Freight",
            "type":"Transportation"
        }
    ],
    "sg:phone":"+1 416 630 6527",
    "sg:postcode":"M3K 1E2",
    "sg:province":"ON",
    "sg:tags":[
        "courier"
    ],
    "wof:name":"Paracas International",
    "wof:placetype":"venue"
},
  "geometry": {"coordinates":[-79.46333300000001,43.731571],"type":"Point"}
}