{
  "type": "Feature",
  "properties": {
    "addr:full":"5995 Hunt St Port Hardy BC V0N 2P0",
    "addr:housenumber":"5995",
    "addr:postcode":"v0n 2p0",
    "addr:street":"Hunt St",
    "iso:country":"CA",
    "sg:address":"5995 Hunt St",
    "sg:city":"Port Hardy",
    "sg:classifiers":[
        {
            "category":"Professional",
            "subcategory":"Detective & Security Services",
            "type":"Services"
        }
    ],
    "sg:phone":"+1 250 949 8483",
    "sg:postcode":"V0N 2P0",
    "sg:province":"BC",
    "sg:tags":[
        "control",
        "traffic"
    ],
    "wof:name":"Independent Flaggers",
    "wof:placetype":"venue"
},
  "geometry": {"coordinates":[-127.48490099999999,50.705296],"type":"Point"}
}