{
  "type": "Feature",
  "properties": {
    "addr:full":"4438 Cove Cliff Rd North Vancouver BC V7G 1H6",
    "addr:housenumber":"4438",
    "addr:postcode":"v7g 1h6",
    "addr:street":"Cove Cliff Rd",
    "iso:country":"CA",
    "sg:address":"4438 Cove Cliff Rd",
    "sg:city":"North Vancouver",
    "sg:classifiers":[
        {
            "category":"Professional",
            "subcategory":"Management & Consulting",
            "type":"Services"
        }
    ],
    "sg:phone":"+1 604 929 9598",
    "sg:postcode":"V7G 1H6",
    "sg:province":"BC",
    "sg:tags":[
        "control",
        "consultant",
        "quality"
    ],
    "wof:name":"Adams Consultants",
    "wof:placetype":"venue"
},
  "geometry": {"coordinates":[-122.948273,49.321907],"type":"Point"}
}