{
  "type": "Feature",
  "properties": {
    "iso:country":"CA",
    "sg:city":"Saint-Theophile",
    "sg:classifiers":[
        {
            "category":"Organizations",
            "subcategory":"Professional Association",
            "type":"Services"
        }
    ],
    "sg:phone":"+1 418 597 3019",
    "sg:postcode":"G0M 2A0",
    "sg:province":"QC",
    "sg:tags":[
        "club"
    ],
    "wof:name":"Club DE Motoneiges Liniere Inc",
    "wof:placetype":"venue"
},
  "geometry": {"coordinates":[-70.45221710209999,45.9460906982],"type":"Point"}
}