{
  "type": "Feature",
  "properties": {
    "iso:country":"CA",
    "sg:city":"Longueuil",
    "sg:classifiers":[
        {
            "category":"Health Services",
            "subcategory":"Doctor",
            "type":"Services"
        }
    ],
    "sg:phone":"+1 450 677 3200",
    "sg:postcode":"J4J 2H9",
    "sg:province":"QC",
    "sg:tags":[
        "clinic",
        "chiropractor"
    ],
    "wof:name":"Centre Chiropractique Nouvelle",
    "wof:placetype":"venue"
},
  "geometry": {"coordinates":[-73.477821,45.536083],"type":"Point"}
}