{
  "type": "Feature",
  "properties": {
    "addr:full":"215 Van Buren St Kemptville ON K0G 1J0",
    "addr:housenumber":"215",
    "addr:postcode":"k0g 1j0",
    "addr:street":"Van Buren St",
    "iso:country":"CA",
    "sg:address":"215 Van Buren St",
    "sg:city":"Kemptville",
    "sg:classifiers":[
        {
            "category":"Health Services",
            "subcategory":"Doctor",
            "type":"Services"
        }
    ],
    "sg:phone":"+1 613 258 2509",
    "sg:postcode":"K0G 1J0",
    "sg:province":"ON",
    "sg:tags":[
        "dentist"
    ],
    "wof:name":"North Grenville Dental Ctr",
    "wof:placetype":"venue"
},
  "geometry": {"coordinates":[-75.6376037598,45.0162353516],"type":"Point"}
}