{
  "type": "Feature",
  "properties": {
    "iso:country":"CA",
    "sg:city":"Arundel",
    "sg:classifiers":[
        {
            "category":"Professional",
            "subcategory":"Computer Services",
            "type":"Services"
        }
    ],
    "sg:phone":"+1 819 687 9104",
    "sg:postcode":"J0T 1A0",
    "sg:province":"QC",
    "sg:tags":[
        "information",
        "system",
        "consultant"
    ],
    "wof:name":"Rouge Net Inc",
    "wof:placetype":"venue"
},
  "geometry": {"coordinates":[-74.6153259277,45.9698104858],"type":"Point"}
}