{
  "type": "Feature",
  "properties": {
    "addr:full":"1375 Av DE Valleyfield Laval QC H7C 2K5",
    "addr:housenumber":"1375",
    "addr:postcode":"h7c 2k5",
    "addr:street":"Av De Valleyfield",
    "iso:country":"CA",
    "sg:address":"1375 Av DE Valleyfield",
    "sg:city":"Laval",
    "sg:classifiers":[
        {
            "category":"Manufacturing",
            "subcategory":"Signs",
            "type":"Manufacturing & Wholesale Goods"
        }
    ],
    "sg:phone":"+1 450 661 8389",
    "sg:postcode":"H7C 2K5",
    "sg:province":"QC",
    "wof:name":"Enseignes Technigraphe Inc",
    "wof:placetype":"venue"
},
  "geometry": {"coordinates":[-73.6613540649,45.6168212891],"type":"Point"}
}