{
  "type": "Feature",
  "properties": {
    "addr:full":"255 Rue Collard O Alma QC G8B 1M8",
    "addr:housenumber":"255",
    "addr:postcode":"g8b 1m8",
    "addr:street":"Rue Collard O",
    "iso:country":"CA",
    "sg:address":"255 Rue Collard O",
    "sg:city":"Alma",
    "sg:classifiers":[
        {
            "category":"Health Services",
            "subcategory":"Doctor",
            "type":"Services"
        }
    ],
    "sg:phone":"+1 418 662 8221",
    "sg:postcode":"G8B 1M8",
    "sg:province":"QC",
    "sg:tags":[
        "physician",
        "surgeon"
    ],
    "wof:name":"Pettersen, Carl MD",
    "wof:placetype":"venue"
},
  "geometry": {"coordinates":[-71.646484,48.546822],"type":"Point"}
}