{
  "type": "Feature",
  "properties": {
    "addr:full":"18 Marshall Ave E North Bay ON P1A 1R1",
    "addr:housenumber":"18",
    "addr:postcode":"p1a 1r1",
    "addr:street":"Marshall Ave E",
    "iso:country":"CA",
    "sg:address":"18 Marshall Ave E",
    "sg:city":"North Bay",
    "sg:classifiers":[
        {
            "category":"Education",
            "subcategory":"Vocational School",
            "type":"Public Place"
        }
    ],
    "sg:phone":"+1 705 840 2587",
    "sg:postcode":"P1A 1R1",
    "sg:province":"ON",
    "sg:tags":[
        "technical",
        "training",
        "computer",
        "trade"
    ],
    "wof:name":"Academy of Learning",
    "wof:placetype":"venue"
},
  "geometry": {"coordinates":[-79.4450454712,46.2800865173],"type":"Point"}
}