{
  "type": "Feature",
  "properties": {
    "addr:full":"15 Cayuga St N Cayuga ON N0A 1E0",
    "addr:housenumber":"15",
    "addr:postcode":"n0a 1e0",
    "addr:street":"Cayuga St N",
    "iso:country":"CA",
    "sg:address":"15 Cayuga St N",
    "sg:city":"Cayuga",
    "sg:classifiers":[
        {
            "category":"Shopping",
            "subcategory":"Catalog Store",
            "type":"Retail Goods"
        }
    ],
    "sg:phone":"+1 905 772 3317",
    "sg:postcode":"N0A 1E0",
    "sg:province":"ON",
    "sg:tags":[
        "mail",
        "order",
        "internet"
    ],
    "wof:name":"Sears Canada Inc",
    "wof:placetype":"venue"
},
  "geometry": {"coordinates":[-79.85869598390001,42.9502182007],"type":"Point"}
}