{
  "type": "Feature",
  "properties": {
    "addr:full":"1380 Rue Joliot-Curie Boucherville QC J4B 7L9",
    "addr:housenumber":"1380",
    "addr:postcode":"j4b 7l9",
    "addr:street":"Rue Joliot-Curie",
    "iso:country":"CA",
    "sg:address":"1380 Rue Joliot-Curie",
    "sg:city":"Boucherville",
    "sg:classifiers":[
        {
            "category":"Manufacturing",
            "subcategory":"Tools & Machinery",
            "type":"Manufacturing & Wholesale Goods"
        }
    ],
    "sg:phone":"+1 450 449 5835",
    "sg:postcode":"J4B 7L9",
    "sg:province":"QC",
    "sg:tags":[
        "equipment",
        "safety",
        "clothing"
    ],
    "wof:name":"Gants & Securite Universels",
    "wof:placetype":"venue"
},
  "geometry": {"coordinates":[-73.43528747560001,45.5581016541],"type":"Point"}
}