{
  "type": "Feature",
  "properties": {
    "iso:country":"CA",
    "sg:address":"31 Eversole Cres",
    "sg:city":"Red Deer",
    "sg:classifiers":[
        {
            "category":"Professional",
            "subcategory":"Engineering",
            "type":"Services"
        }
    ],
    "sg:phone":"+1 403 341 3159",
    "sg:postcode":"T4R 2J8",
    "sg:province":"AB",
    "sg:tags":[
        "engineer"
    ],
    "wof:name":"Sveinson Consulting Engineers",
    "wof:placetype":"venue"
},
  "geometry": {"coordinates":[-113.77424600000001,52.26265],"type":"Point"}
}