{
  "type": "Feature",
  "properties": {
    "addr:full":"2862 Main St Shubenacadie NS B0N 2H0",
    "addr:housenumber":"2862",
    "addr:postcode":"b0n 2h0",
    "addr:street":"Main St",
    "iso:country":"CA",
    "sg:address":"2862 Main St",
    "sg:city":"Shubenacadie",
    "sg:classifiers":[
        {
            "category":"Restaurant",
            "type":"Food & Drink"
        }
    ],
    "sg:phone":"+1 902 758 3535",
    "sg:postcode":"B0N 2H0",
    "sg:province":"NS",
    "wof:name":"Shubie's Pizza",
    "wof:placetype":"venue"
},
  "geometry": {"coordinates":[-63.405449,45.088669],"type":"Point"}
}