{
  "type": "Feature",
  "properties": {
    "addr:full":"3109 Island Hwy W Qualicum Beach BC V9K 2C5",
    "addr:housenumber":"3109",
    "addr:postcode":"v9k 2c5",
    "addr:street":"Island Hwy W",
    "iso:country":"CA",
    "sg:address":"3109 Island Hwy W",
    "sg:city":"Qualicum Beach",
    "sg:classifiers":[
        {
            "category":"Restaurant",
            "type":"Food & Drink"
        }
    ],
    "sg:phone":"+1 250 752 9111",
    "sg:postcode":"V9K 2C5",
    "sg:province":"BC",
    "wof:name":"Shady Rest Hotel",
    "wof:placetype":"venue"
},
  "geometry": {"coordinates":[-124.45966339100001,49.3543586731],"type":"Point"}
}