{
  "type": "Feature",
  "properties": {
    "addr:full":"5511 45 St Leduc AB T9E 6T6",
    "addr:housenumber":"5511",
    "addr:postcode":"t9e 6t6",
    "addr:street":"45 St",
    "iso:country":"CA",
    "sg:address":"5511 45 St",
    "sg:city":"Leduc",
    "sg:classifiers":[
        {
            "category":"Manufacturing",
            "subcategory":"Tools & Machinery",
            "type":"Manufacturing & Wholesale Goods"
        }
    ],
    "sg:phone":"+1 780 986 2566",
    "sg:postcode":"T9E 6T6",
    "sg:province":"AB",
    "sg:tags":[
        "machine",
        "shop"
    ],
    "wof:name":"Allsett Machine Ltd",
    "wof:placetype":"venue"
},
  "geometry": {"coordinates":[-113.5438,53.269558],"type":"Point"}
}