{
  "type": "Feature",
  "properties": {
    "iso:country":"CA",
    "sg:city":"Calgary",
    "sg:classifiers":[
        {
            "category":"Restaurant",
            "type":"Food & Drink"
        }
    ],
    "sg:phone":"+1 403 686 3833",
    "sg:postcode":"T3H 3V4",
    "sg:province":"AB",
    "wof:name":"Chinese Kitchen",
    "wof:placetype":"venue"
},
  "geometry": {"coordinates":[-114.175804,51.014988],"type":"Point"}
}