{
  "type": "Feature",
  "properties": {
    "addr:full":"13680 50 St NW Edmonton AB T5A 4Y3",
    "addr:housenumber":"13680",
    "addr:postcode":"t5a 4y3",
    "addr:street":"50 St Nw",
    "iso:country":"CA",
    "sg:address":"13680 50 St NW",
    "sg:city":"Edmonton",
    "sg:classifiers":[
        {
            "category":"Retail",
            "subcategory":"Animal Services",
            "type":"Services"
        }
    ],
    "sg:phone":"+1 780 456 0910",
    "sg:postcode":"T5A 4Y3",
    "sg:province":"AB",
    "sg:tags":[
        "pet",
        "food",
        "grooming",
        "washing",
        "supply"
    ],
    "wof:name":"Petsmart",
    "wof:placetype":"venue"
},
  "geometry": {"coordinates":[-113.413872,53.596272],"type":"Point"}
}