{
  "type": "Feature",
  "properties": {
    "addr:full":"Sainte-Paule QC G0J 3C0",
    "addr:postcode":"g0j 3c0",
    "iso:country":"CA",
    "sg:city":"Sainte-Paule",
    "sg:classifiers":[
        {
            "category":"Travel",
            "subcategory":"Hotels & Motels",
            "type":"Entertainment"
        }
    ],
    "sg:phone":"+1 418 737 9150",
    "sg:postcode":"G0J 3C0",
    "sg:province":"QC",
    "sg:tags":[
        "inn"
    ],
    "wof:name":"Auberge DE LA Pente Abrupte",
    "wof:placetype":"venue"
},
  "geometry": {"coordinates":[-67.594688,48.632874],"type":"Point"}
}