{
  "type": "Feature",
  "properties": {
    "addr:full":"260 Hearst Way # 315 Kanata ON K2L 3H1",
    "addr:housenumber":"260",
    "addr:postcode":"k2l 3h1",
    "addr:street":"Hearst Way # 315",
    "iso:country":"CA",
    "sg:address":"260 Hearst Way # 315",
    "sg:city":"Kanata",
    "sg:classifiers":[
        {
            "category":"Real Estate",
            "subcategory":"Real Estate Agent",
            "type":"Services"
        }
    ],
    "sg:phone":"+1 613 271 1566",
    "sg:postcode":"K2L 3H1",
    "sg:province":"ON",
    "sg:tags":[
        "management"
    ],
    "wof:name":"Progeny Management Inc",
    "wof:placetype":"venue"
},
  "geometry": {"coordinates":[-75.893387,45.314774],"type":"Point"}
}