{
  "type": "Feature",
  "properties": {
    "addr:full":"PO Box 355 STN Main Bridgewater NS B4V 2W9",
    "addr:housenumber":"po",
    "addr:postcode":"b4v 2w9",
    "addr:street":"Box 355 Stn Main",
    "iso:country":"CA",
    "sg:address":"PO Box 355 STN Main",
    "sg:city":"Bridgewater",
    "sg:classifiers":[
        {
            "category":"Social Services",
            "type":"Services"
        }
    ],
    "sg:phone":"+1 902 543 3665",
    "sg:postcode":"B4V 2W9",
    "sg:province":"NS",
    "sg:tags":[
        "organization",
        "welfare"
    ],
    "wof:name":"South Shore Transition House",
    "wof:placetype":"venue"
},
  "geometry": {"coordinates":[-64.523033,44.380497],"type":"Point"}
}