{
  "type": "Feature",
  "properties": {
    "addr:full":"633393 Hwy 10 Orangeville ON L9W 2Z1",
    "addr:housenumber":"633393",
    "addr:postcode":"l9w 2z1",
    "addr:street":"Hwy 10",
    "iso:country":"CA",
    "sg:address":"633393 Hwy 10",
    "sg:city":"Orangeville",
    "sg:classifiers":[
        {
            "category":"Autos & Motor Vehicles",
            "subcategory":"Automobile Sales",
            "type":"Retail Goods"
        }
    ],
    "sg:phone":"+1 519 942 9959",
    "sg:postcode":"L9W 2Z1",
    "sg:province":"ON",
    "sg:tags":[
        "snowmobile"
    ],
    "wof:name":"Warp 9 Sports",
    "wof:placetype":"venue"
},
  "geometry": {"coordinates":[-80.093491,43.920116],"type":"Point"}
}