{
  "type": "Feature",
  "properties": {
    "addr:full":"Nanaimo BC V9R 2T5",
    "addr:postcode":"v9r 2t5",
    "iso:country":"CA",
    "sg:city":"Nanaimo",
    "sg:classifiers":[
        {
            "category":"Shopping",
            "subcategory":"Clothing, Apparel, & Fashions",
            "type":"Retail Goods"
        }
    ],
    "sg:phone":"+1 250 754 0785",
    "sg:postcode":"V9R 2T5",
    "sg:province":"BC",
    "sg:tags":[
        "cocoa",
        "wool",
        "chocolate"
    ],
    "wof:name":"Mad About Ewe Fine Yarns",
    "wof:placetype":"venue"
},
  "geometry": {"coordinates":[-123.94136047400001,49.1649894714],"type":"Point"}
}