{
  "type": "Feature",
  "properties": {
    "iso:country":"CA",
    "sg:city":"Sarnia",
    "sg:classifiers":[
        {
            "category":"Shopping",
            "subcategory":"Optical Goods",
            "type":"Retail Goods"
        }
    ],
    "sg:phone":"+1 519 332 6463",
    "sg:postcode":"N7T 7V3",
    "sg:province":"ON",
    "sg:tags":[
        "optician"
    ],
    "wof:name":"Distinctive Eyewear",
    "wof:placetype":"venue"
},
  "geometry": {"coordinates":[-82.40590667719999,42.9750595093],"type":"Point"}
}