{
  "type": "Feature",
  "properties": {
    "iso:country":"CA",
    "sg:address":"1452 Youville Dr",
    "sg:city":"Orleans",
    "sg:classifiers":[
        {
            "category":"Autos & Motor Vehicles",
            "subcategory":"Automobile Sales",
            "type":"Retail Goods"
        }
    ],
    "sg:phone":"+1 613 824 8550",
    "sg:postcode":"K1C 2X8",
    "sg:province":"ON",
    "sg:tags":[
        "car",
        "dealer"
    ],
    "wof:name":"Marcel Belanger Pontiac Buick",
    "wof:placetype":"venue"
},
  "geometry": {"coordinates":[-75.548767,45.46521],"type":"Point"}
}