{
  "type": "Feature",
  "properties": {
    "addr:full":"5 Av Pie-X Victoriaville QC G6P 4R8",
    "addr:postcode":"g6p 4r8",
    "addr:street":"Av Pie-X",
    "iso:country":"CA",
    "sg:address":"5 Av Pie-X",
    "sg:city":"Victoriaville",
    "sg:classifiers":[
        {
            "category":"Autos & Motor Vehicles",
            "subcategory":"Auto Supplies",
            "type":"Retail Goods"
        }
    ],
    "sg:phone":"+1 819 758 0671",
    "sg:postcode":"G6P 4R8",
    "sg:province":"QC",
    "sg:tags":[
        "feed",
        "engine",
        "tire"
    ],
    "wof:name":"Cooperative Agricole Des Bois",
    "wof:placetype":"venue"
},
  "geometry": {"coordinates":[-71.96229599999999,46.047108],"type":"Point"}
}