{
  "type": "Feature",
  "properties": {
    "addr:full":"Edmonton AB T6J 0R4",
    "addr:postcode":"t6j 0r4",
    "iso:country":"CA",
    "sg:city":"Edmonton",
    "sg:classifiers":[
        {
            "category":"Social Services",
            "subcategory":"Child Care",
            "type":"Services"
        }
    ],
    "sg:phone":"+1 780 434 9261",
    "sg:postcode":"T6J 0R4",
    "sg:province":"AB",
    "wof:name":"Abc Child Development Ctr",
    "wof:placetype":"venue"
},
  "geometry": {"coordinates":[-113.526885986,53.4758338928],"type":"Point"}
}