{
  "type": "Feature",
  "properties": {
    "iso:country":"CA",
    "sg:address":"1800 Blackwater Rd",
    "sg:city":"Quesnel",
    "sg:classifiers":[
        {
            "category":"Sports & Exercise",
            "subcategory":"Golf",
            "type":"Entertainment"
        }
    ],
    "sg:phone":"+1 250 249 5550",
    "sg:postcode":"V2J 7A5",
    "sg:province":"BC",
    "sg:tags":[
        "course"
    ],
    "wof:name":"Quesnel Golf Course",
    "wof:placetype":"venue"
},
  "geometry": {"coordinates":[-122.498245239,52.9781188965],"type":"Point"}
}