{
  "type": "Feature",
  "properties": {
    "addr:full":"7275 Taft Dr Prince George BC V2K 2R4",
    "addr:housenumber":"7275",
    "addr:postcode":"v2k 2r4",
    "addr:street":"Taft Dr",
    "iso:country":"CA",
    "sg:address":"7275 Taft Dr",
    "sg:city":"Prince George",
    "sg:classifiers":[
        {
            "category":"Building & Trades",
            "subcategory":"Construction",
            "type":"Services"
        }
    ],
    "sg:phone":"+1 250 962 0166",
    "sg:postcode":"V2K 2R4",
    "sg:province":"BC",
    "sg:tags":[
        "roofing",
        "contractor"
    ],
    "wof:name":"A-Plus Roofing",
    "wof:placetype":"venue"
},
  "geometry": {"coordinates":[-122.78533899999999,53.995937],"type":"Point"}
}