{
  "type": "Feature",
  "properties": {
    "addr:full":"1550 Dunbar Rd Cambridge ON N1R 8J5",
    "addr:housenumber":"1550",
    "addr:postcode":"n1r 8j5",
    "addr:street":"Dunbar Rd",
    "iso:country":"CA",
    "sg:address":"1550 Dunbar Rd",
    "sg:city":"Cambridge",
    "sg:classifiers":[
        {
            "category":"Organizations",
            "subcategory":"Religious Organization",
            "type":"Services"
        }
    ],
    "sg:phone":"+1 519 740 6855",
    "sg:postcode":"N1R 8J5",
    "sg:province":"ON",
    "sg:tags":[
        "church"
    ],
    "wof:name":"Jami Mosque Cambridge",
    "wof:placetype":"venue"
},
  "geometry": {"coordinates":[-80.317261,43.390694],"type":"Point"}
}