{
  "type": "Feature",
  "properties": {
    "addr:full":"280 Rue DE LA Huche Sainte-Adele QC J8B 3E2",
    "addr:housenumber":"280",
    "addr:postcode":"j8b 3e2",
    "addr:street":"Rue De La Huche Sainte-Adele",
    "iso:country":"CA",
    "sg:address":"280 Rue DE LA Huche",
    "sg:city":"Sainte-Adele",
    "sg:classifiers":[
        {
            "category":"Building & Trades",
            "subcategory":"Construction",
            "type":"Services"
        }
    ],
    "sg:phone":"+1 450 229 6191",
    "sg:postcode":"J8B 3E2",
    "sg:province":"QC",
    "sg:tags":[
        "painter"
    ],
    "wof:name":"Peinture Mr Enr",
    "wof:placetype":"venue"
},
  "geometry": {"coordinates":[-74.17182200000001,45.967548],"type":"Point"}
}