{
  "type": "Feature",
  "properties": {
    "addr:full":"2527 Main Rd Upper Port LA Tour NS B0W 3N0",
    "addr:housenumber":"2527",
    "addr:postcode":"b0w 3n0",
    "addr:street":"Main Rd",
    "iso:country":"CA",
    "sg:address":"2527 Main Rd",
    "sg:city":"Upper Port LA Tour",
    "sg:classifiers":[
        {
            "category":"Wholesale",
            "subcategory":"Seafood",
            "type":"Manufacturing & Wholesale Goods"
        }
    ],
    "sg:phone":"+1 902 768 2876",
    "sg:postcode":"B0W 3N0",
    "sg:province":"NS",
    "wof:name":"R E Hatfield Fisheries Ltd",
    "wof:placetype":"venue"
},
  "geometry": {"coordinates":[-65.47895800000001,43.500797],"type":"Point"}
}