{
  "type": "Feature",
  "properties": {
    "addr:full":"St-Sauveur-Des-Monts QC J0R 1R0",
    "addr:postcode":"j0r 1r0",
    "iso:country":"CA",
    "sg:city":"St-Sauveur-Des-Monts",
    "sg:classifiers":[
        {
            "category":"Government",
            "subcategory":"Office",
            "type":"Public Place"
        }
    ],
    "sg:phone":"+1 450 227 5847",
    "sg:postcode":"J0R 1R0",
    "sg:province":"QC",
    "sg:tags":[
        "village"
    ],
    "wof:name":"St-Sauveur Tennis Municipale",
    "wof:placetype":"venue"
},
  "geometry": {"coordinates":[-74.157021,45.895332],"type":"Point"}
}