{
  "type": "Feature",
  "properties": {
    "addr:full":"97 Bowes St Parry Sound ON P2A 2L8",
    "addr:housenumber":"97",
    "addr:postcode":"p2a 2l8",
    "addr:street":"Bowes St",
    "iso:country":"CA",
    "sg:address":"97 Bowes St",
    "sg:city":"Parry Sound",
    "sg:classifiers":[
        {
            "category":"Wholesale",
            "subcategory":"Farm Supplies",
            "type":"Manufacturing & Wholesale Goods"
        }
    ],
    "sg:phone":"+1 705 746 1313",
    "sg:postcode":"P2A 2L8",
    "sg:province":"ON",
    "sg:tags":[
        "feed"
    ],
    "wof:name":"Fincham's Grains & Goods",
    "wof:placetype":"venue"
},
  "geometry": {"coordinates":[-80.016884,45.34259],"type":"Point"}
}