{
  "type": "Feature",
  "properties": {
    "addr:full":"463 Ch Portage Rd Grand-Sault/Grand Falls NB E3Z 1M4",
    "addr:housenumber":"463",
    "addr:postcode":"e3z 1m4",
    "addr:street":"Ch Portage Rd",
    "iso:country":"CA",
    "sg:address":"463 Ch Portage Rd",
    "sg:city":"Grand-Sault/Grand Falls",
    "sg:classifiers":[
        {
            "category":"Retail",
            "subcategory":"Auto Repair",
            "type":"Services"
        }
    ],
    "sg:phone":"+1 506 473 5527",
    "sg:postcode":"E3Z 1M4",
    "sg:province":"NB",
    "sg:tags":[
        "wheel",
        "alignment",
        "axle"
    ],
    "wof:name":"John Bellefleur Alignment",
    "wof:placetype":"venue"
},
  "geometry": {"coordinates":[-67.747871,47.032272],"type":"Point"}
}