{
  "type": "Feature",
  "properties": {
    "addr:full":"162 Hespeler Rd Cambridge ON N1R 6V7",
    "addr:housenumber":"162",
    "addr:postcode":"n1r 6v7",
    "addr:street":"Hespeler Rd",
    "iso:country":"CA",
    "sg:address":"162 Hespeler Rd",
    "sg:city":"Cambridge",
    "sg:classifiers":[
        {
            "category":"Social Services",
            "type":"Services"
        }
    ],
    "sg:phone":"+1 519 623 1451",
    "sg:postcode":"N1R 6V7",
    "sg:province":"ON",
    "sg:tags":[
        "organization",
        "welfare"
    ],
    "wof:name":"Carol Currier Ctr",
    "wof:placetype":"venue"
},
  "geometry": {"coordinates":[-80.3199005127,43.3809623718],"type":"Point"}
}