{
  "type": "Feature",
  "properties": {
    "addr:full":"691 Rue Principale Beresford NB E8K 1W6",
    "addr:housenumber":"691",
    "addr:postcode":"e8k 1w6",
    "addr:street":"Rue Principale",
    "iso:country":"CA",
    "sg:address":"691 Rue Principale",
    "sg:city":"Beresford",
    "sg:classifiers":[
        {
            "category":"Wholesale",
            "subcategory":"Non-durable Goods",
            "type":"Manufacturing & Wholesale Goods"
        }
    ],
    "sg:phone":"+1 506 542 9212",
    "sg:postcode":"E8K 1W6",
    "sg:province":"NB",
    "sg:tags":[
        "leather",
        "clothing"
    ],
    "wof:name":"Double R Lingerie Ltee",
    "wof:placetype":"venue"
},
  "geometry": {"coordinates":[-65.706451,47.714031],"type":"Point"}
}