{
  "type": "Feature",
  "properties": {
    "addr:full":"511 Hager Ave Burlington ON L7S 1P2",
    "addr:housenumber":"511",
    "addr:postcode":"l7s 1p2",
    "addr:street":"Hager Ave",
    "iso:country":"CA",
    "sg:address":"511 Hager Ave",
    "sg:city":"Burlington",
    "sg:classifiers":[
        {
            "category":"Freight",
            "type":"Transportation"
        }
    ],
    "sg:phone":"+1 905 634 0633",
    "sg:postcode":"L7S 1P2",
    "sg:province":"ON",
    "sg:tags":[
        "consultant"
    ],
    "wof:name":"Worldwidechain Inc",
    "wof:placetype":"venue"
},
  "geometry": {"coordinates":[-79.802711,43.324169],"type":"Point"}
}