{
  "type": "Feature",
  "properties": {
    "iso:country":"CA",
    "sg:address":"330 Holland St W",
    "sg:city":"Bradford",
    "sg:classifiers":[
        {
            "category":"Retail",
            "subcategory":"Auto Repair",
            "type":"Services"
        }
    ],
    "sg:phone":"+1 905 775 3422",
    "sg:postcode":"L3Z 1J2",
    "sg:province":"ON",
    "sg:tags":[
        "repairing",
        "automobile"
    ],
    "wof:name":"Midas Auto Svc Experts",
    "wof:placetype":"venue"
},
  "geometry": {"coordinates":[-79.5763702393,44.111541748],"type":"Point"}
}