{
  "type": "Feature",
  "properties": {
    "addr:full":"168 Simcoe St Tillsonburg ON N4G 2J1",
    "addr:housenumber":"168",
    "addr:postcode":"n4g 2j1",
    "addr:street":"Simcoe St",
    "iso:country":"CA",
    "sg:address":"168 Simcoe St",
    "sg:city":"Tillsonburg",
    "sg:classifiers":[
        {
            "category":"Restaurant",
            "type":"Food & Drink"
        }
    ],
    "sg:phone":"+1 519 688 0032",
    "sg:postcode":"N4G 2J1",
    "sg:province":"ON",
    "wof:name":"Pizza Hut",
    "wof:placetype":"venue"
},
  "geometry": {"coordinates":[-80.706322,42.857719],"type":"Point"}
}