{
  "type": "Feature",
  "properties": {
    "addr:full":"235 Main St Tatamagouche NS B0K 1V0",
    "addr:housenumber":"235",
    "addr:postcode":"b0k 1v0",
    "addr:street":"Main St",
    "iso:country":"CA",
    "sg:address":"235 Main St",
    "sg:city":"Tatamagouche",
    "sg:classifiers":[
        {
            "category":"Wholesale",
            "subcategory":"Meat",
            "type":"Manufacturing & Wholesale Goods"
        }
    ],
    "sg:phone":"+1 902 657 3078",
    "sg:postcode":"B0K 1V0",
    "sg:province":"NS",
    "sg:tags":[
        "butchering"
    ],
    "wof:name":"Huston's Butcher Shop",
    "wof:placetype":"venue"
},
  "geometry": {"coordinates":[-63.291451,45.712379],"type":"Point"}
}