{
  "type": "Feature",
  "properties": {
    "addr:full":"143 King St E Kitchener ON N2G 2K8",
    "addr:housenumber":"143",
    "addr:postcode":"n2g 2k8",
    "addr:street":"King St E",
    "iso:country":"CA",
    "sg:address":"143 King St E",
    "sg:city":"Kitchener",
    "sg:classifiers":[
        {
            "category":"Shopping",
            "subcategory":"Clothing, Apparel, & Fashions",
            "type":"Retail Goods"
        }
    ],
    "sg:phone":"+1 519 576 0552",
    "sg:postcode":"N2G 2K8",
    "sg:province":"ON",
    "wof:name":"Erika's Bavarian Fashions",
    "wof:placetype":"venue"
},
  "geometry": {"coordinates":[-80.487053,43.448696],"type":"Point"}
}