{
  "type": "Feature",
  "properties": {
    "addr:full":"78 Greystone Cres Sherwood Park AB T8A 3E6",
    "addr:housenumber":"78",
    "addr:postcode":"t8a 3e6",
    "addr:street":"Greystone Cres",
    "iso:country":"CA",
    "sg:address":"78 Greystone Cres",
    "sg:city":"Sherwood Park",
    "sg:classifiers":[
        {
            "category":"Wholesale",
            "subcategory":"Non-durable Goods",
            "type":"Manufacturing & Wholesale Goods"
        }
    ],
    "sg:phone":"+1 780 467 6964",
    "sg:postcode":"T8A 3E6",
    "sg:province":"AB",
    "sg:tags":[
        "advertising"
    ],
    "wof:name":"D & M Enterprises Inc",
    "wof:placetype":"venue"
},
  "geometry": {"coordinates":[-113.271744,53.538208],"type":"Point"}
}