{
  "type": "Feature",
  "properties": {
    "addr:full":"Barlow Trail & 144 Ave NE Balzac AB T0M 0E0",
    "addr:postcode":"t0m 0e0",
    "addr:street":"Barlow;144 Ave Ne",
    "iso:country":"CA",
    "sg:address":"Barlow Trail & 144 Ave NE",
    "sg:city":"Balzac",
    "sg:classifiers":[
        {
            "category":"Retail",
            "subcategory":"Veterinary Services",
            "type":"Services"
        }
    ],
    "sg:phone":"+1 403 226 2585",
    "sg:postcode":"T0M 0E0",
    "sg:province":"AB",
    "sg:tags":[
        "veterinarian"
    ],
    "wof:name":"Moore & CO Veterinary Clinic",
    "wof:placetype":"venue"
},
  "geometry": {"coordinates":[-114.006958,51.21257],"type":"Point"}
}