{
  "type": "Feature",
  "properties": {
    "addr:full":"Richmond BC V6X 2X9",
    "addr:postcode":"v6x 2x9",
    "iso:country":"CA",
    "sg:city":"Richmond",
    "sg:classifiers":[
        {
            "category":"Autos & Motor Vehicles",
            "subcategory":"Auto Supplies",
            "type":"Retail Goods"
        }
    ],
    "sg:phone":"+1 604 231 9905",
    "sg:postcode":"V6X 2X9",
    "sg:province":"BC",
    "sg:tags":[
        "battery"
    ],
    "wof:name":"G P Battery Marketing Inc",
    "wof:placetype":"venue"
},
  "geometry": {"coordinates":[-123.136292,49.175171],"type":"Point"}
}