{
  "type": "Feature",
  "properties": {
    "addr:full":"1215 Montee DE Liesse Saint-Laurent QC H4S 1J7",
    "addr:housenumber":"1215",
    "addr:postcode":"h4s 1j7",
    "addr:street":"Montee De Liesse",
    "iso:country":"CA",
    "sg:address":"1215 Montee DE Liesse",
    "sg:city":"Saint-Laurent",
    "sg:classifiers":[
        {
            "category":"Building & Trades",
            "subcategory":"Plumbing",
            "type":"Services"
        }
    ],
    "sg:phone":"+1 514 334 2801",
    "sg:postcode":"H4S 1J7",
    "sg:province":"QC",
    "sg:tags":[
        "sheet",
        "work",
        "metal",
        "contractor"
    ],
    "wof:name":"Gtca Met-All Inc",
    "wof:placetype":"venue"
},
  "geometry": {"coordinates":[-73.721649,45.486595],"type":"Point"}
}