{
  "type": "Feature",
  "properties": {
    "iso:country":"CA",
    "sg:address":"431 Roncesvalles Ave",
    "sg:city":"Toronto",
    "sg:classifiers":[
        {
            "category":"Personal",
            "subcategory":"Beauty Salon",
            "type":"Services"
        }
    ],
    "sg:phone":"+1 416 539 9374",
    "sg:postcode":"M6R 2N3",
    "sg:province":"ON",
    "wof:name":"Salon Di Gregorio",
    "wof:placetype":"venue"
},
  "geometry": {"coordinates":[-79.451088,43.651779],"type":"Point"}
}