{
  "type": "Feature",
  "properties": {
    "iso:country":"CA",
    "sg:address":"10312 121 St NW",
    "sg:city":"Edmonton",
    "sg:classifiers":[
        {
            "category":"Professional",
            "subcategory":"Art Services",
            "type":"Services"
        }
    ],
    "sg:phone":"+1 780 488 6820",
    "sg:postcode":"T5N 1K8",
    "sg:province":"AB",
    "sg:tags":[
        "photographer"
    ],
    "wof:name":"Ellis Brothers Photography",
    "wof:placetype":"venue"
},
  "geometry": {"coordinates":[-113.531051636,53.5449523926],"type":"Point"}
}