{
  "type": "Feature",
  "properties": {
    "addr:full":"555 15th St E Owen Sound ON N4K 1X2",
    "addr:housenumber":"555",
    "addr:postcode":"n4k 1x2",
    "addr:street":"15Th St E",
    "iso:country":"CA",
    "sg:address":"555 15th St E",
    "sg:city":"Owen Sound",
    "sg:classifiers":[
        {
            "category":"Education",
            "subcategory":"School",
            "type":"Public Place"
        }
    ],
    "sg:phone":"+1 519 376 4278",
    "sg:postcode":"N4K 1X2",
    "sg:province":"ON",
    "wof:name":"St Mary's High School",
    "wof:placetype":"venue"
},
  "geometry": {"coordinates":[-80.9343414307,44.574382782],"type":"Point"}
}