{
  "type": "Feature",
  "properties": {
    "addr:full":"PO Box 18 New Harbour Tb NL A0B 2P0",
    "addr:housenumber":"po box 18",
    "addr:postcode":"a0b 2p0",
    "iso:country":"CA",
    "sg:address":"PO Box 18",
    "sg:city":"New Harbour Tb",
    "sg:classifiers":[
        {
            "category":"Organizations",
            "subcategory":"Religious Organization",
            "type":"Services"
        }
    ],
    "sg:phone":"+1 709 582 3467",
    "sg:postcode":"A0B 2P0",
    "sg:province":"NL",
    "sg:tags":[
        "church"
    ],
    "wof:name":"New-Life Ministries",
    "wof:placetype":"venue"
},
  "geometry": {"coordinates":[-53.543179,47.584843],"type":"Point"}
}