{
  "type": "Feature",
  "properties": {
    "addr:full":"2500 Rue Jean-Talon E Montreal QC H2A 1T7",
    "addr:housenumber":"2500",
    "addr:postcode":"h2a 1t7",
    "addr:street":"Rue Jean-Talon E",
    "iso:country":"CA",
    "sg:address":"2500 Rue Jean-Talon E",
    "sg:city":"Montreal",
    "sg:classifiers":[
        {
            "category":"Food & Beverages",
            "subcategory":"Groceries & Convenience Stores",
            "type":"Retail Goods"
        }
    ],
    "sg:phone":"+1 514 376 9071",
    "sg:postcode":"H2A 1T7",
    "sg:province":"QC",
    "wof:name":"Couche-Tard",
    "wof:placetype":"venue"
},
  "geometry": {"coordinates":[-73.6020278931,45.5536308289],"type":"Point"}
}