{
  "type": "Feature",
  "properties": {
    "iso:country":"CA",
    "sg:address":"1272 3E Av",
    "sg:city":"Val-D'Or",
    "sg:classifiers":[
        {
            "category":"Restaurant",
            "type":"Food & Drink"
        }
    ],
    "sg:phone":"+1 819 825 7111",
    "sg:postcode":"J9P 1V3",
    "sg:province":"QC",
    "sg:tags":[
        "pizza"
    ],
    "wof:name":"Val D'Or Pizzeria",
    "wof:placetype":"venue"
},
  "geometry": {"coordinates":[-70.87963104249999,48.3281593323],"type":"Point"}
}