{
  "type": "Feature",
  "properties": {
    "addr:full":"2432 23 Ave NE Calgary AB T2E 8J4",
    "addr:housenumber":"2432",
    "addr:postcode":"t2e 8j4",
    "addr:street":"23 Ave Ne",
    "iso:country":"CA",
    "sg:address":"2432 23 Ave NE",
    "sg:city":"Calgary",
    "sg:classifiers":[
        {
            "category":"Retail",
            "subcategory":"Auto Repair",
            "type":"Services"
        }
    ],
    "sg:phone":"+1 403 291 1514",
    "sg:postcode":"T2E 8J4",
    "sg:province":"AB",
    "sg:tags":[
        "transmission",
        "automobile",
        "repairing"
    ],
    "wof:name":"National Transmissions",
    "wof:placetype":"venue"
},
  "geometry": {"coordinates":[-114.003319,51.073349],"type":"Point"}
}