{
  "type": "Feature",
  "properties": {
    "addr:full":"308 Main Ave W Sundre AB T0M 1X0",
    "addr:housenumber":"308",
    "addr:postcode":"t0m 1x0",
    "addr:street":"Main Ave W",
    "iso:country":"CA",
    "sg:address":"308 Main Ave W",
    "sg:city":"Sundre",
    "sg:classifiers":[
        {
            "category":"Restaurant",
            "type":"Food & Drink"
        }
    ],
    "sg:phone":"+1 403 638 4444",
    "sg:postcode":"T0M 1X0",
    "sg:province":"AB",
    "wof:name":"Subway Sandwiches & Salads",
    "wof:placetype":"venue"
},
  "geometry": {"coordinates":[-114.642173767,51.7971076965],"type":"Point"}
}