{
  "type": "Feature",
  "properties": {
    "addr:full":"5965 Ch Saint-Francois Saint-Laurent QC H4S 1B6",
    "addr:housenumber":"5965",
    "addr:postcode":"h4s 1b6",
    "addr:street":"Ch Saint-Francois",
    "iso:country":"CA",
    "sg:address":"5965 Ch Saint-Francois",
    "sg:city":"Saint-Laurent",
    "sg:classifiers":[
        {
            "category":"Manufacturing",
            "subcategory":"Tools & Machinery",
            "type":"Manufacturing & Wholesale Goods"
        }
    ],
    "sg:phone":"+1 514 333 0146",
    "sg:postcode":"H4S 1B6",
    "sg:province":"QC",
    "sg:tags":[
        "die",
        "maker"
    ],
    "wof:name":"Exacta Precision Product Ltd",
    "wof:placetype":"venue"
},
  "geometry": {"coordinates":[-73.740791,45.48587],"type":"Point"}
}