{
  "type": "Feature",
  "properties": {
    "addr:full":"Cp 113 Succ Bureau-Chef Cowansville QC J2K 3H1",
    "addr:postcode":"j2k 3h1",
    "addr:street":"Bureau-Chef",
    "iso:country":"CA",
    "sg:address":"Cp 113 Succ Bureau-Chef",
    "sg:city":"Cowansville",
    "sg:classifiers":[
        {
            "category":"Organizations",
            "subcategory":"Religious Organization",
            "type":"Services"
        }
    ],
    "sg:phone":"+1 514 263 3432",
    "sg:postcode":"J2K 3H1",
    "sg:province":"QC",
    "sg:tags":[
        "church"
    ],
    "wof:name":"L'Eglise DE LA Vie Abondante",
    "wof:placetype":"venue"
},
  "geometry": {"coordinates":[-72.74597167970001,45.2078018188],"type":"Point"}
}