{
  "type": "Feature",
  "properties": {
    "iso:country":"CA",
    "sg:address":"PO Box 1721 STN Main",
    "sg:city":"Sioux Lookout",
    "sg:classifiers":[
        {
            "category":"Travel",
            "subcategory":"Campground",
            "type":"Entertainment"
        }
    ],
    "sg:phone":"+1 807 584 2915",
    "sg:postcode":"P8T 1C4",
    "sg:province":"ON",
    "sg:tags":[
        "camp"
    ],
    "wof:name":"Cat Track Lodge",
    "wof:placetype":"venue"
},
  "geometry": {"coordinates":[-91.9150314331,50.0980911255],"type":"Point"}
}