{
  "type": "Feature",
  "properties": {
    "addr:full":"2267 Industrial St Burlington ON L7P 1A2",
    "addr:housenumber":"2267",
    "addr:postcode":"l7p 1a2",
    "addr:street":"Industrial St",
    "iso:country":"CA",
    "sg:address":"2267 Industrial St",
    "sg:city":"Burlington",
    "sg:classifiers":[
        {
            "category":"Manufacturing",
            "subcategory":"Printing",
            "type":"Manufacturing & Wholesale Goods"
        }
    ],
    "sg:phone":"+1 905 336 1590",
    "sg:postcode":"L7P 1A2",
    "sg:province":"ON",
    "sg:tags":[
        "screen"
    ],
    "wof:name":"Colour Craft Cresting",
    "wof:placetype":"venue"
},
  "geometry": {"coordinates":[-79.814163208,43.3485641479],"type":"Point"}
}