{
  "type": "Feature",
  "properties": {
    "iso:country":"CA",
    "sg:city":"Williams Lake",
    "sg:classifiers":[
        {
            "category":"Home & Garden",
            "subcategory":"Carpets & Floor Coverings",
            "type":"Retail Goods"
        }
    ],
    "sg:phone":"+1 250 392 2621",
    "sg:postcode":"V2G 1J4",
    "sg:province":"BC",
    "sg:tags":[
        "material",
        "rug"
    ],
    "wof:name":"Consumer's Carpet Warehouse",
    "wof:placetype":"venue"
},
  "geometry": {"coordinates":[-122.14251709,52.1247787476],"type":"Point"}
}