{
  "type": "Feature",
  "properties": {
    "addr:full":"651 Lakeshore Dr North Bay ON P1A 2G1",
    "addr:housenumber":"651",
    "addr:postcode":"p1a 2g1",
    "addr:street":"Lakeshore Dr",
    "iso:country":"CA",
    "sg:address":"651 Lakeshore Dr",
    "sg:city":"North Bay",
    "sg:classifiers":[
        {
            "category":"Travel",
            "subcategory":"Hotels & Motels",
            "type":"Entertainment"
        }
    ],
    "sg:phone":"+1 705 474 4883",
    "sg:postcode":"P1A 2G1",
    "sg:province":"ON",
    "sg:tags":[
        "cottage",
        "cabin"
    ],
    "wof:name":"Balsam Cottages",
    "wof:placetype":"venue"
},
  "geometry": {"coordinates":[-79.43988,46.267933],"type":"Point"}
}