{
  "type": "Feature",
  "properties": {
    "addr:full":"338 Centre St Drumheller AB T0J 0Y0",
    "addr:housenumber":"338",
    "addr:postcode":"t0j 0y0",
    "addr:street":"Centre St",
    "iso:country":"CA",
    "sg:address":"338 Centre St",
    "sg:city":"Drumheller",
    "sg:classifiers":[
        {
            "category":"Shopping",
            "subcategory":"Clothing, Apparel, & Fashions",
            "type":"Retail Goods"
        }
    ],
    "sg:phone":"+1 403 823 4855",
    "sg:postcode":"T0J 0Y0",
    "sg:province":"AB",
    "sg:tags":[
        "furnishing"
    ],
    "wof:name":"Bill Cross Men's Shop Ltd",
    "wof:placetype":"venue"
},
  "geometry": {"coordinates":[-112.592330933,51.3957443237],"type":"Point"}
}