{
  "type": "Feature",
  "properties": {
    "addr:full":"Delta BC V4G 1E2",
    "addr:postcode":"v4g 1e2",
    "iso:country":"CA",
    "sg:city":"Delta",
    "sg:classifiers":[
        {
            "category":"Professional",
            "type":"Services"
        }
    ],
    "sg:phone":"+1 604 952 4460",
    "sg:postcode":"V4G 1E2",
    "sg:province":"BC",
    "sg:tags":[
        "mold",
        "establishment",
        "maker"
    ],
    "wof:name":"Felxahopper Plastics Ltd",
    "wof:placetype":"venue"
},
  "geometry": {"coordinates":[-123.018951,49.132328],"type":"Point"}
}