{
  "type": "Feature",
  "properties": {
    "iso:country":"CA",
    "sg:address":"14800 Yonge St #149",
    "sg:city":"Aurora",
    "sg:classifiers":[
        {
            "category":"Personal",
            "subcategory":"Shoe Repair & Shine",
            "type":"Services"
        }
    ],
    "sg:phone":"+1 905 841 8922",
    "sg:postcode":"L4G 1N3",
    "sg:province":"ON",
    "sg:tags":[
        "repairing",
        "boot"
    ],
    "wof:name":"Family Shoe Repair",
    "wof:placetype":"venue"
},
  "geometry": {"coordinates":[-79.46500396730001,43.9882583618],"type":"Point"}
}