{
  "type": "Feature",
  "properties": {
    "iso:country":"CA",
    "sg:address":"PO Box 10",
    "sg:city":"Avonport",
    "sg:classifiers":[
        {
            "category":"Shopping",
            "type":"Retail Goods"
        }
    ],
    "sg:phone":"+1 902 542 5417",
    "sg:postcode":"B0P 1B0",
    "sg:province":"NS",
    "sg:tags":[
        "trophy",
        "medal",
        "award"
    ],
    "wof:name":"T & J Trophies",
    "wof:placetype":"venue"
},
  "geometry": {"coordinates":[-64.25518035890001,45.099155426],"type":"Point"}
}