{
  "type": "Feature",
  "properties": {
    "iso:country":"CA",
    "sg:address":"4317 Regional Road 15",
    "sg:city":"Chelmsford",
    "sg:classifiers":[
        {
            "category":"Food & Beverages",
            "subcategory":"Fruits & Vegetables",
            "type":"Retail Goods"
        }
    ],
    "sg:phone":"+1 705 855 9386",
    "sg:postcode":"P0M 1L0",
    "sg:province":"ON",
    "sg:tags":[
        "produce"
    ],
    "wof:name":"Lise's Strawberry Farm",
    "wof:placetype":"venue"
},
  "geometry": {"coordinates":[-81.1973571777,46.5688743591],"type":"Point"}
}