{
  "type": "Feature",
  "properties": {
    "addr:full":"6954 Market St Port Hardy BC V0N 2P0",
    "addr:housenumber":"6954",
    "addr:postcode":"v0n 2p0",
    "addr:street":"Market St",
    "iso:country":"CA",
    "sg:address":"6954 Market St",
    "sg:city":"Port Hardy",
    "sg:classifiers":[
        {
            "category":"Home & Garden",
            "subcategory":"Hardware",
            "type":"Retail Goods"
        }
    ],
    "sg:phone":"+1 250 949 6611",
    "sg:postcode":"V0N 2P0",
    "sg:province":"BC",
    "sg:tags":[
        "building",
        "material"
    ],
    "wof:name":"Port Hardy Builders' Supply",
    "wof:placetype":"venue"
},
  "geometry": {"coordinates":[-127.493377685,50.718082428],"type":"Point"}
}