{
  "type": "Feature",
  "properties": {
    "addr:full":"8410 109 St NW Edmonton AB T6G 1E2",
    "addr:housenumber":"8410",
    "addr:postcode":"t6g 1e2",
    "addr:street":"109 St Nw",
    "iso:country":"CA",
    "sg:address":"8410 109 St NW",
    "sg:city":"Edmonton",
    "sg:classifiers":[
        {
            "category":"Shopping",
            "subcategory":"Bicycles & Sporting Goods",
            "type":"Retail Goods"
        }
    ],
    "sg:phone":"+1 780 432 0350",
    "sg:postcode":"T6G 1E2",
    "sg:province":"AB",
    "wof:name":"Sweet Spot",
    "wof:placetype":"venue"
},
  "geometry": {"coordinates":[-113.51217699999999,53.520218],"type":"Point"}
}