{
  "type": "Feature",
  "properties": {
    "addr:full":"1016 Rue Carrier Thetford Mines QC G6G 3T5",
    "addr:housenumber":"1016",
    "addr:postcode":"g6g 3t5",
    "addr:street":"Rue Carrier",
    "iso:country":"CA",
    "sg:address":"1016 Rue Carrier",
    "sg:city":"Thetford Mines",
    "sg:classifiers":[
        {
            "category":"Retail",
            "subcategory":"Laundry & Dry Cleaning",
            "type":"Services"
        }
    ],
    "sg:phone":"+1 418 335 2242",
    "sg:postcode":"G6G 3T5",
    "sg:province":"QC",
    "sg:tags":[
        "cleaners",
        "steam",
        "rug",
        "carpet"
    ],
    "wof:name":"Net-Sec",
    "wof:placetype":"venue"
},
  "geometry": {"coordinates":[-71.3133468628,46.1024055481],"type":"Point"}
}