{
  "type": "Feature",
  "properties": {
    "addr:full":"Clifford ON N0G 1M0",
    "addr:postcode":"n0g 1m0",
    "iso:country":"CA",
    "sg:city":"Clifford",
    "sg:classifiers":[
        {
            "category":"Home & Garden",
            "subcategory":"Furniture",
            "type":"Retail Goods"
        }
    ],
    "sg:phone":"+1 519 327 8957",
    "sg:postcode":"N0G 1M0",
    "sg:province":"ON",
    "sg:tags":[
        "equipment",
        "kitchen",
        "cabinet"
    ],
    "wof:name":"Royal Oak Kitchen & Bath",
    "wof:placetype":"venue"
},
  "geometry": {"coordinates":[-80.953987,43.956429],"type":"Point"}
}