{
  "type": "Feature",
  "properties": {
    "addr:full":"Fort Smith NT X0E 0P0",
    "addr:postcode":"x0e 0p0",
    "iso:country":"CA",
    "sg:city":"Fort Smith",
    "sg:classifiers":[
        {
            "category":"Building & Trades",
            "subcategory":"Electrical",
            "type":"Services"
        }
    ],
    "sg:phone":"+1 867 872 3196",
    "sg:postcode":"X0E 0P0",
    "sg:province":"NT",
    "sg:tags":[
        "electric",
        "contractor"
    ],
    "wof:name":"Bzt General Contracting",
    "wof:placetype":"venue"
},
  "geometry": {"coordinates":[-111.90263400000001,60.000095],"type":"Point"}
}