{
  "type": "Feature",
  "properties": {
    "iso:country":"CA",
    "sg:city":"Saint-David-D'Yamaska",
    "sg:classifiers":[
        {
            "category":"Government",
            "subcategory":"Office",
            "type":"Public Place"
        }
    ],
    "sg:phone":"+1 450 789 2288",
    "sg:postcode":"J0G 1L0",
    "sg:province":"QC",
    "sg:tags":[
        "village"
    ],
    "wof:name":"St David Municipalite",
    "wof:placetype":"venue"
},
  "geometry": {"coordinates":[-72.9151229858,46.0043258667],"type":"Point"}
}