{
  "type": "Feature",
  "properties": {
    "addr:full":"4 Mechanic St W Maxville ON K0C 1T0",
    "addr:housenumber":"4",
    "addr:postcode":"k0c 1t0",
    "addr:street":"Mechanic St W",
    "iso:country":"CA",
    "sg:address":"4 Mechanic St W",
    "sg:city":"Maxville",
    "sg:classifiers":[
        {
            "category":"Banks & Credit Unions",
            "subcategory":"Bank",
            "type":"Services"
        }
    ],
    "sg:phone":"+1 613 527 2980",
    "sg:postcode":"K0C 1T0",
    "sg:province":"ON",
    "wof:name":"Banquescotia",
    "wof:placetype":"venue"
},
  "geometry": {"coordinates":[-74.85528600000001,45.288548],"type":"Point"}
}