{
  "type": "Feature",
  "properties": {
    "iso:country":"CA",
    "sg:address":"3675 Boul Industriel",
    "sg:city":"Laval",
    "sg:classifiers":[
        {
            "category":"Manufacturing",
            "subcategory":"Tools & Machinery",
            "type":"Manufacturing & Wholesale Goods"
        }
    ],
    "sg:phone":"+1 450 629 3454",
    "sg:postcode":"H7L 4S3",
    "sg:province":"QC",
    "sg:tags":[
        "machine",
        "shop"
    ],
    "wof:name":"Heroux Devtek",
    "wof:placetype":"venue"
},
  "geometry": {"coordinates":[-73.748008728,45.5958366394],"type":"Point"}
}