{
  "type": "Feature",
  "properties": {
    "addr:full":"Stonewall MB R0C 2Z0",
    "addr:postcode":"r0c 2z0",
    "iso:country":"CA",
    "sg:city":"Stonewall",
    "sg:classifiers":[
        {
            "category":"Shopping",
            "subcategory":"Gifts & Souvenirs",
            "type":"Retail Goods"
        }
    ],
    "sg:phone":"+1 204 467 8113",
    "sg:postcode":"R0C 2Z0",
    "sg:province":"MB",
    "sg:tags":[
        "cards",
        "shop",
        "greeting"
    ],
    "wof:name":"Hallmark Cards",
    "wof:placetype":"venue"
},
  "geometry": {"coordinates":[-97.326843,50.13522],"type":"Point"}
}