{
  "type": "Feature",
  "properties": {
    "iso:country":"CA",
    "sg:address":"411 Christina St N",
    "sg:city":"Sarnia",
    "sg:classifiers":[
        {
            "category":"Restaurant",
            "type":"Food & Drink"
        }
    ],
    "sg:phone":"+1 519 336 7096",
    "sg:postcode":"N7T 5V8",
    "sg:province":"ON",
    "wof:name":"Mc Donald's",
    "wof:placetype":"venue"
},
  "geometry": {"coordinates":[-82.403381,42.980286],"type":"Point"}
}