{
  "type": "Feature",
  "properties": {
    "addr:full":"798 Broadview Ave Toronto ON M4K 2P7",
    "addr:housenumber":"798",
    "addr:postcode":"m4k 2p7",
    "addr:street":"Broadview Ave",
    "iso:country":"CA",
    "sg:address":"798 Broadview Ave",
    "sg:city":"Toronto",
    "sg:classifiers":[
        {
            "category":"Banks & Credit Unions",
            "subcategory":"Investment Brokerage",
            "type":"Services"
        }
    ],
    "sg:phone":"+1 416 406 1140",
    "sg:postcode":"M4K 2P7",
    "sg:province":"ON",
    "wof:name":"Edward Jones",
    "wof:placetype":"venue"
},
  "geometry": {"coordinates":[-79.35888671879999,43.6773796082],"type":"Point"}
}