{
  "type": "Feature",
  "properties": {
    "addr:full":"1545 Rue Laurier Rockland ON K4K 1C8",
    "addr:housenumber":"1545",
    "addr:postcode":"k4k 1c8",
    "addr:street":"Rue Laurier",
    "iso:country":"CA",
    "sg:address":"1545 Rue Laurier",
    "sg:city":"Rockland",
    "sg:classifiers":[
        {
            "category":"Banks & Credit Unions",
            "subcategory":"Bank",
            "type":"Services"
        }
    ],
    "sg:phone":"+1 613 446 5154",
    "sg:postcode":"K4K 1C8",
    "sg:province":"ON",
    "wof:name":"Caisses Populaires Trillium",
    "wof:placetype":"venue"
},
  "geometry": {"coordinates":[-75.288567,45.550819],"type":"Point"}
}