{
  "type": "Feature",
  "properties": {
    "addr:full":"9336 120 St Surrey BC V3V 4B8",
    "addr:housenumber":"9336",
    "addr:postcode":"v3v 4b8",
    "addr:street":"120 St",
    "iso:country":"CA",
    "sg:address":"9336 120 St",
    "sg:city":"Surrey",
    "sg:classifiers":[
        {
            "category":"Food & Beverages",
            "subcategory":"Groceries & Convenience Stores",
            "type":"Retail Goods"
        }
    ],
    "sg:phone":"+1 604 951 0566",
    "sg:postcode":"V3V 4B8",
    "sg:province":"BC",
    "sg:tags":[
        "grocer"
    ],
    "wof:name":"Spiceland",
    "wof:placetype":"venue"
},
  "geometry": {"coordinates":[-122.890045,49.172646],"type":"Point"}
}