{
  "type": "Feature",
  "properties": {
    "addr:full":"Whitby ON L1N 8R1",
    "addr:postcode":"l1n 8r1",
    "iso:country":"CA",
    "sg:city":"Whitby",
    "sg:classifiers":[
        {
            "category":"Banks & Credit Unions",
            "subcategory":"Bank",
            "type":"Services"
        }
    ],
    "sg:phone":"+1 905 668 5231",
    "sg:postcode":"L1N 8R1",
    "sg:province":"ON",
    "wof:name":"Durham Employees Credit Union",
    "wof:placetype":"venue"
},
  "geometry": {"coordinates":[-78.9397277832,43.8766860962],"type":"Point"}
}