{
  "type": "Feature",
  "properties": {
    "addr:full":"Montreal QC H1Z 2K4",
    "addr:postcode":"h1z 2k4",
    "iso:country":"CA",
    "sg:city":"Montreal",
    "sg:classifiers":[
        {
            "category":"Shopping",
            "subcategory":"Clothing, Apparel, & Fashions",
            "type":"Retail Goods"
        }
    ],
    "sg:phone":"+1 514 728 9977",
    "sg:postcode":"H1Z 2K4",
    "sg:province":"QC",
    "sg:tags":[
        "uniform"
    ],
    "wof:name":"John Francis Ltee",
    "wof:placetype":"venue"
},
  "geometry": {"coordinates":[-73.603134,45.567219],"type":"Point"}
}