{
  "type": "Feature",
  "properties": {
    "addr:full":"338 Av Champlain Disraeli QC G0N 1E0",
    "addr:postcode":"g0n 1e0",
    "addr:street":"338 Av Champlain",
    "iso:country":"CA",
    "sg:address":"338 Av Champlain",
    "sg:city":"Disraeli",
    "sg:classifiers":[
        {
            "category":"Shopping",
            "subcategory":"Jewelry",
            "type":"Retail Goods"
        }
    ],
    "sg:phone":"+1 418 449 3854",
    "sg:postcode":"G0N 1E0",
    "sg:province":"QC",
    "sg:tags":[
        "jeweler"
    ],
    "wof:name":"Bijouterie Gagnon",
    "wof:placetype":"venue"
},
  "geometry": {"coordinates":[-71.356865,45.899498],"type":"Point"}
}