{
  "type": "Feature",
  "properties": {
    "addr:full":"Hwy 3 S Prince Albert SK S6V 7M4",
    "addr:postcode":"s6v 7m4",
    "addr:street":"Hwy 3 S",
    "iso:country":"CA",
    "sg:address":"Hwy 3 S",
    "sg:city":"Prince Albert",
    "sg:classifiers":[
        {
            "category":"Wholesale",
            "subcategory":"Machinery & Supplies",
            "type":"Manufacturing & Wholesale Goods"
        }
    ],
    "sg:phone":"+1 306 763 6686",
    "sg:postcode":"S6V 7M4",
    "sg:province":"SK",
    "sg:tags":[
        "farm",
        "agricultural",
        "implement",
        "equipment"
    ],
    "wof:name":"Long Tractor Inc",
    "wof:placetype":"venue"
},
  "geometry": {"coordinates":[-105.738777,53.180325],"type":"Point"}
}