{
  "type": "Feature",
  "properties": {
    "addr:full":"3660 50 Ave SE Calgary AB T2B 3N9",
    "addr:housenumber":"3660",
    "addr:postcode":"t2b 3n9",
    "addr:street":"50 Ave Se",
    "iso:country":"CA",
    "sg:address":"3660 50 Ave SE",
    "sg:city":"Calgary",
    "sg:classifiers":[
        {
            "category":"Retail",
            "subcategory":"Auto Repair",
            "type":"Services"
        }
    ],
    "sg:phone":"+1 403 273 4466",
    "sg:postcode":"T2B 3N9",
    "sg:province":"AB",
    "sg:tags":[
        "truck"
    ],
    "wof:name":"Hino Truck Sales Calgary",
    "wof:placetype":"venue"
},
  "geometry": {"coordinates":[-113.980278,51.008888],"type":"Point"}
}