{
  "type": "Feature",
  "properties": {
    "iso:country":"CA",
    "sg:address":"409 Guelph Line",
    "sg:city":"Burlington",
    "sg:classifiers":[
        {
            "category":"Manufacturing",
            "subcategory":"Printing",
            "type":"Manufacturing & Wholesale Goods"
        }
    ],
    "sg:phone":"+1 905 333 0606",
    "sg:postcode":"L7R 3L7",
    "sg:province":"ON",
    "sg:tags":[
        "printer"
    ],
    "wof:name":"Print Three",
    "wof:placetype":"venue"
},
  "geometry": {"coordinates":[-79.78421,43.337753],"type":"Point"}
}