{
  "type": "Feature",
  "properties": {
    "addr:full":"156 Third Line Oakville ON L6L 3Z8",
    "addr:housenumber":"156",
    "addr:postcode":"l6l 3z8",
    "addr:street":"Third Line",
    "iso:country":"CA",
    "sg:address":"156 Third Line",
    "sg:city":"Oakville",
    "sg:classifiers":[
        {
            "category":"Organizations",
            "subcategory":"Religious Organization",
            "type":"Services"
        }
    ],
    "sg:phone":"+1 905 827 3851",
    "sg:postcode":"L6L 3Z8",
    "sg:province":"ON",
    "sg:tags":[
        "church"
    ],
    "wof:name":"Hopedale Presbyterian Church",
    "wof:placetype":"venue"
},
  "geometry": {"coordinates":[-79.701706,43.407009],"type":"Point"}
}