{
  "type": "Feature",
  "properties": {
    "addr:full":"215 23 Ave NE Calgary AB T2E 1V8",
    "addr:housenumber":"215",
    "addr:postcode":"t2e 1v8",
    "addr:street":"23 Ave Ne",
    "iso:country":"CA",
    "sg:address":"215 23 Ave NE",
    "sg:city":"Calgary",
    "sg:classifiers":[
        {
            "category":"Building & Trades",
            "subcategory":"Construction",
            "type":"Services"
        }
    ],
    "sg:phone":"+1 403 256 4986",
    "sg:postcode":"T2E 1V8",
    "sg:province":"AB",
    "sg:tags":[
        "painter"
    ],
    "wof:name":"Rolling Along Painting",
    "wof:placetype":"venue"
},
  "geometry": {"coordinates":[-114.05934906,51.0731811523],"type":"Point"}
}