{
  "type": "Feature",
  "properties": {
    "iso:country":"CA",
    "sg:city":"Scarborough",
    "sg:classifiers":[
        {
            "category":"Banks & Credit Unions",
            "subcategory":"Financial Services",
            "type":"Services"
        }
    ],
    "sg:phone":"+1 416 298 7377",
    "sg:postcode":"M1S 5C6",
    "sg:province":"ON",
    "sg:tags":[
        "program",
        "scholarship"
    ],
    "wof:name":"Global Educational Marketing",
    "wof:placetype":"venue"
},
  "geometry": {"coordinates":[-79.2759475708,43.7798080444],"type":"Point"}
}