{
  "type": "Feature",
  "properties": {
    "addr:full":"522 Talbot Rd Delhi ON N4B 2W6",
    "addr:housenumber":"522",
    "addr:postcode":"n4b 2w6",
    "addr:street":"Talbot Rd",
    "iso:country":"CA",
    "sg:address":"522 Talbot Rd",
    "sg:city":"Delhi",
    "sg:classifiers":[
        {
            "category":"Personal",
            "type":"Services"
        }
    ],
    "sg:phone":"+1 519 582 1242",
    "sg:postcode":"N4B 2W6",
    "sg:province":"ON",
    "sg:tags":[
        "therapist",
        "massage"
    ],
    "wof:name":"Paul Rapai Registered Massage",
    "wof:placetype":"venue"
},
  "geometry": {"coordinates":[-80.51295500000001,42.854744],"type":"Point"}
}