{
  "type": "Feature",
  "properties": {
    "addr:full":"Birch Island ON P0P 1A0",
    "addr:postcode":"p0p 1a0",
    "iso:country":"CA",
    "sg:city":"Birch Island",
    "sg:classifiers":[
        {
            "category":"Professional",
            "subcategory":"Management & Consulting",
            "type":"Services"
        }
    ],
    "sg:phone":"+1 705 285 4275",
    "sg:postcode":"P0P 1A0",
    "sg:province":"ON",
    "sg:tags":[
        "consultant",
        "business"
    ],
    "wof:name":"Waubetek Business Dev Ctr",
    "wof:placetype":"venue"
},
  "geometry": {"coordinates":[-81.77177399999999,46.063595],"type":"Point"}
}