{
  "type": "Feature",
  "properties": {
    "addr:full":"142 Rue Beaulieu Morin-Heights QC J0R 1H0",
    "addr:housenumber":"142",
    "addr:postcode":"j0r 1h0",
    "addr:street":"Rue Beaulieu",
    "iso:country":"CA",
    "sg:address":"142 Rue Beaulieu",
    "sg:city":"Morin-Heights",
    "sg:classifiers":[
        {
            "category":"Insurance",
            "subcategory":"Insurance Agent",
            "type":"Services"
        }
    ],
    "sg:phone":"+1 450 226 3021",
    "sg:postcode":"J0R 1H0",
    "sg:province":"QC",
    "sg:tags":[
        "adjuster",
        "appraiser"
    ],
    "wof:name":"Sinispec Inc",
    "wof:placetype":"venue"
},
  "geometry": {"coordinates":[-74.2035903931,45.9106369019],"type":"Point"}
}