{
  "type": "Feature",
  "properties": {
    "addr:full":"3090 Rue DE Saint-Methode Saint-Felicien QC G8K 3C3",
    "addr:housenumber":"3090",
    "addr:postcode":"g8k 3c3",
    "addr:street":"Rue De Saint-Methode Saint-Felicien",
    "iso:country":"CA",
    "sg:address":"3090 Rue DE Saint-Methode",
    "sg:city":"Saint-Felicien",
    "sg:classifiers":[
        {
            "category":"Organizations",
            "subcategory":"Religious Organization",
            "type":"Services"
        }
    ],
    "sg:phone":"+1 418 679 0667",
    "sg:postcode":"G8K 3C3",
    "sg:province":"QC",
    "sg:tags":[
        "church"
    ],
    "wof:name":"Presbytere DE St-Methode",
    "wof:placetype":"venue"
},
  "geometry": {"coordinates":[-72.4111709595,48.7274742126],"type":"Point"}
}