{
  "type": "Feature",
  "properties": {
    "addr:full":"118 Niagara St St Catharines ON L2R 4L4",
    "addr:housenumber":"118",
    "addr:postcode":"l2r 4l4",
    "addr:street":"Niagara St",
    "iso:country":"CA",
    "sg:address":"118 Niagara St",
    "sg:city":"St Catharines",
    "sg:classifiers":[
        {
            "category":"Banks & Credit Unions",
            "subcategory":"Bank",
            "type":"Services"
        }
    ],
    "sg:phone":"+1 905 684 5062",
    "sg:postcode":"L2R 4L4",
    "sg:province":"ON",
    "wof:name":"Ukrainian Credit Union Ltd",
    "wof:placetype":"venue"
},
  "geometry": {"coordinates":[-79.2350158691,43.1687164307],"type":"Point"}
}