{
  "type": "Feature",
  "properties": {
    "addr:full":"695 Boul Sainte-Marguerite Mercier QC J6R 2L1",
    "addr:housenumber":"695",
    "addr:postcode":"j6r 2l1",
    "addr:street":"Boul Sainte-Marguerite",
    "iso:country":"CA",
    "sg:address":"695 Boul Sainte-Marguerite",
    "sg:city":"Mercier",
    "sg:classifiers":[
        {
            "category":"Building & Trades",
            "subcategory":"Construction",
            "type":"Services"
        }
    ],
    "sg:phone":"+1 450 692 9374",
    "sg:postcode":"J6R 2L1",
    "sg:province":"QC",
    "sg:tags":[
        "equipment",
        "kitchen",
        "maker",
        "cabinet"
    ],
    "wof:name":"Ebenisterie Praillon",
    "wof:placetype":"venue"
},
  "geometry": {"coordinates":[-73.72128295900001,45.3154563904],"type":"Point"}
}