{
  "type": "Feature",
  "properties": {
    "addr:full":"9040 Leslie St # 202 Richmond Hill ON L4B 3M4",
    "addr:housenumber":"9040;202",
    "addr:postcode":"l4b 3m4",
    "addr:street":"Leslie St #",
    "iso:country":"CA",
    "sg:address":"9040 Leslie St # 202",
    "sg:city":"Richmond Hill",
    "sg:classifiers":[
        {
            "category":"Professional",
            "subcategory":"Credit Reporting & Collection",
            "type":"Services"
        }
    ],
    "sg:phone":"+1 905 707 7711",
    "sg:postcode":"L4B 3M4",
    "sg:province":"ON",
    "sg:tags":[
        "agency"
    ],
    "wof:name":"Canadian Debt Recovery Ltd",
    "wof:placetype":"venue"
},
  "geometry": {"coordinates":[-79.383965,43.850201],"type":"Point"}
}