{
  "type": "Feature",
  "properties": {
    "addr:full":"29 Elkview Dr Fernie BC V0B 1M3",
    "addr:housenumber":"29",
    "addr:postcode":"bc v0b 1m3",
    "addr:street":"Elkview Dr",
    "iso:country":"CA",
    "sg:address":"29 Elkview Dr",
    "sg:city":"Fernie",
    "sg:classifiers":[
        {
            "category":"Home & Garden",
            "subcategory":"Garden Supply",
            "type":"Retail Goods"
        }
    ],
    "sg:phone":"+1 250 423 4888",
    "sg:postcode":"V0B 1M3",
    "sg:province":"BC",
    "sg:tags":[
        "fountain",
        "display"
    ],
    "wof:name":"Carter's Ponds Pots N' Pathwys",
    "wof:placetype":"venue"
},
  "geometry": {"coordinates":[-115.069878,49.493347],"type":"Point"}
}