{
  "type": "Feature",
  "properties": {
    "addr:full":"Toronto ON M5N 1E3",
    "addr:postcode":"m5n 1e3",
    "iso:country":"CA",
    "sg:city":"Toronto",
    "sg:classifiers":[
        {
            "category":"Real Estate",
            "subcategory":"Architect",
            "type":"Services"
        }
    ],
    "sg:phone":"+1 416 787 7575",
    "sg:postcode":"M5N 1E3",
    "sg:province":"ON",
    "wof:name":"Richard Wengle Architect Inc",
    "wof:placetype":"venue"
},
  "geometry": {"coordinates":[-79.4244308472,43.7010879517],"type":"Point"}
}