{
  "type": "Feature",
  "properties": {
    "addr:full":"4005 Rue Monseigneur-Begin Jonquiere QC G7X 3S5",
    "addr:housenumber":"4005",
    "addr:postcode":"g7x 3s5",
    "addr:street":"Rue Monseigneur-Begin",
    "iso:country":"CA",
    "sg:address":"4005 Rue Monseigneur-Begin",
    "sg:city":"Jonquiere",
    "sg:classifiers":[
        {
            "category":"Professional",
            "subcategory":"Detective & Security Services",
            "type":"Services"
        }
    ],
    "sg:phone":"+1 418 695 0600",
    "sg:postcode":"G7X 3S5",
    "sg:province":"QC",
    "sg:tags":[
        "burglary",
        "protective",
        "robbery"
    ],
    "wof:name":"Alarme Protechnique Enr",
    "wof:placetype":"venue"
},
  "geometry": {"coordinates":[-71.2534866333,48.4134597778],"type":"Point"}
}