{
  "type": "Feature",
  "properties": {
    "addr:full":"3521 Mckinley Crt Abbotsford BC V2S 8L9",
    "addr:housenumber":"3521",
    "addr:postcode":"v2s 8l9",
    "addr:street":"Mckinley Crt",
    "iso:country":"CA",
    "sg:address":"3521 Mckinley Crt",
    "sg:city":"Abbotsford",
    "sg:classifiers":[
        {
            "category":"Health Services",
            "subcategory":"Doctor",
            "type":"Services"
        }
    ],
    "sg:phone":"+1 604 852 3811",
    "sg:postcode":"V2S 8L9",
    "sg:province":"BC",
    "sg:tags":[
        "physician",
        "surgeon"
    ],
    "wof:name":"Darley, D E MD",
    "wof:placetype":"venue"
},
  "geometry": {"coordinates":[-122.24500999999999,49.066113],"type":"Point"}
}