{
  "type": "Feature",
  "properties": {
    "addr:full":"130 Castlemore Ave Markham ON L6C 2P9",
    "addr:housenumber":"130",
    "addr:postcode":"l6c 2p9",
    "addr:street":"Castlemore Ave",
    "iso:country":"CA",
    "sg:address":"130 Castlemore Ave",
    "sg:city":"Markham",
    "sg:classifiers":[
        {
            "category":"Education",
            "subcategory":"School",
            "type":"Public Place"
        }
    ],
    "sg:phone":"+1 905 887 8780",
    "sg:postcode":"L6C 2P9",
    "sg:province":"ON",
    "wof:name":"All Saints School",
    "wof:placetype":"venue"
},
  "geometry": {"coordinates":[-79.3078842163,43.896270752],"type":"Point"}
}