{
  "type": "Feature",
  "properties": {
    "addr:full":"3940 Johnston Rd Port Alberni BC V9Y 5N5",
    "addr:housenumber":"3940",
    "addr:postcode":"v9y 5n5",
    "addr:street":"Johnston Rd",
    "iso:country":"CA",
    "sg:address":"3940 Johnston Rd",
    "sg:city":"Port Alberni",
    "sg:classifiers":[
        {
            "category":"Recreation",
            "type":"Entertainment"
        }
    ],
    "sg:phone":"+1 250 723 7132",
    "sg:postcode":"V9Y 5N5",
    "sg:province":"BC",
    "sg:tags":[
        "hall",
        "auditorium"
    ],
    "wof:name":"Hansen Hall Society",
    "wof:placetype":"venue"
},
  "geometry": {"coordinates":[-124.79254913299999,49.2645149231],"type":"Point"}
}