{
  "type": "Feature",
  "properties": {
    "addr:full":"Harriston ON N0G 1Z0",
    "addr:postcode":"n0g 1z0",
    "iso:country":"CA",
    "sg:city":"Harriston",
    "sg:classifiers":[
        {
            "category":"Wholesale",
            "subcategory":"Machinery & Supplies",
            "type":"Manufacturing & Wholesale Goods"
        }
    ],
    "sg:phone":"+1 519 338 3942",
    "sg:postcode":"N0G 1Z0",
    "sg:province":"ON",
    "sg:tags":[
        "farm",
        "equipment"
    ],
    "wof:name":"Gilmore Farm Supply",
    "wof:placetype":"venue"
},
  "geometry": {"coordinates":[-80.87097900000001,43.913013],"type":"Point"}
}