{
  "type": "Feature",
  "properties": {
    "iso:country":"CA",
    "sg:address":"5525 Rue Pare",
    "sg:city":"Mont-Royal",
    "sg:classifiers":[
        {
            "category":"Wholesale",
            "subcategory":"Office Equipment",
            "type":"Manufacturing & Wholesale Goods"
        }
    ],
    "sg:phone":"+1 514 341 3020",
    "sg:postcode":"H4P 1P7",
    "sg:province":"QC",
    "sg:tags":[
        "machine",
        "duplicating",
        "copying"
    ],
    "wof:name":"Admaco Equipement DE Bureau",
    "wof:placetype":"venue"
},
  "geometry": {"coordinates":[-73.66045379640001,45.4923706055],"type":"Point"}
}