{
  "type": "Feature",
  "properties": {
    "addr:full":"1044 Boul Des Laurentides Pont-Viau QC H7G 2W1",
    "addr:housenumber":"1044",
    "addr:postcode":"h7g 2w1",
    "addr:street":"Boul Des Laurentides",
    "iso:country":"CA",
    "sg:address":"1044 Boul Des Laurentides",
    "sg:city":"Pont-Viau",
    "sg:classifiers":[
        {
            "category":"Personal",
            "subcategory":"Tattoo Parlor",
            "type":"Services"
        }
    ],
    "sg:phone":"+1 450 975 2666",
    "sg:postcode":"H7G 2W1",
    "sg:province":"QC",
    "sg:tags":[
        "tattooing",
        "shop",
        "gift"
    ],
    "wof:name":"High Times II",
    "wof:placetype":"venue"
},
  "geometry": {"coordinates":[-73.69755600000001,45.575008],"type":"Point"}
}