{
  "type": "Feature",
  "properties": {
    "addr:full":"307 University Ave Charlottetown PE C1A 4M5",
    "addr:housenumber":"307",
    "addr:postcode":"c1a 4m5",
    "addr:street":"University Ave",
    "iso:country":"CA",
    "sg:address":"307 University Ave",
    "sg:city":"Charlottetown",
    "sg:classifiers":[
        {
            "category":"Travel",
            "subcategory":"Hotels & Motels",
            "type":"Entertainment"
        }
    ],
    "sg:phone":"+1 902 892 4141",
    "sg:postcode":"C1A 4M5",
    "sg:province":"PE",
    "wof:name":"Holiday Island Motor Lodge",
    "wof:placetype":"venue"
},
  "geometry": {"coordinates":[-63.132149,46.241138],"type":"Point"}
}