{
  "type": "Feature",
  "properties": {
    "addr:full":"33 Rue LA Grande Allee E Grande-Riviere QC G0C 1V0",
    "addr:housenumber":"33",
    "addr:postcode":"g0c 1v0",
    "addr:street":"Rue La Grande Allee E Grande-Riviere",
    "iso:country":"CA",
    "sg:address":"33 Rue LA Grande Allee E",
    "sg:city":"Grande-Riviere",
    "sg:classifiers":[
        {
            "category":"Home & Garden",
            "subcategory":"Furniture",
            "type":"Retail Goods"
        }
    ],
    "sg:phone":"+1 418 385 3155",
    "sg:postcode":"G0C 1V0",
    "sg:province":"QC",
    "wof:name":"Bourget Electrique Meubles Inc",
    "wof:placetype":"venue"
},
  "geometry": {"coordinates":[-64.506996,48.397991],"type":"Point"}
}