{
  "type": "Feature",
  "properties": {
    "addr:full":"4596 3rd Line Rd Lancaster ON K0C 1N0",
    "addr:housenumber":"4596",
    "addr:postcode":"k0c 1n0",
    "addr:street":"3Rd Line Rd",
    "iso:country":"CA",
    "sg:address":"4596 3rd Line Rd",
    "sg:city":"Lancaster",
    "sg:classifiers":[
        {
            "category":"Education",
            "subcategory":"Special Training",
            "type":"Public Place"
        }
    ],
    "sg:phone":"+1 613 347 7784",
    "sg:postcode":"K0C 1N0",
    "sg:province":"ON",
    "sg:tags":[
        "instruction",
        "driving"
    ],
    "wof:name":"Highland Defensive Driving",
    "wof:placetype":"venue"
},
  "geometry": {"coordinates":[-74.48299400000001,45.273228],"type":"Point"}
}