{
  "type": "Feature",
  "properties": {
    "addr:full":"213 Boul Brien Repentigny QC J6A 6M4",
    "addr:housenumber":"213",
    "addr:postcode":"j6a 6m4",
    "addr:street":"Boul Brien",
    "iso:country":"CA",
    "sg:address":"213 Boul Brien",
    "sg:city":"Repentigny",
    "sg:classifiers":[
        {
            "category":"Home & Garden",
            "subcategory":"Building Materials",
            "type":"Retail Goods"
        }
    ],
    "sg:phone":"+1 450 581 7551",
    "sg:postcode":"J6A 6M4",
    "sg:province":"QC",
    "sg:tags":[
        "paint"
    ],
    "wof:name":"Betonel Limitee",
    "wof:placetype":"venue"
},
  "geometry": {"coordinates":[-73.46122699999999,45.747204],"type":"Point"}
}