{
  "type": "Feature",
  "properties": {
    "iso:country":"CA",
    "sg:address":"9381 Town Line Rd",
    "sg:city":"Windsor",
    "sg:classifiers":[
        {
            "category":"Education",
            "subcategory":"School",
            "type":"Public Place"
        }
    ],
    "sg:phone":"+1 519 734 1219",
    "sg:postcode":"N9J 2W6",
    "sg:province":"ON",
    "wof:name":"St Joseph Elementary School",
    "wof:placetype":"venue"
},
  "geometry": {"coordinates":[-83.0339126587,42.3178215027],"type":"Point"}
}