{
  "type": "Feature",
  "properties": {
    "iso:country":"CA",
    "sg:address":"521 Piercey Rd",
    "sg:city":"Bolton",
    "sg:classifiers":[
        {
            "category":"Manufacturing",
            "subcategory":"Furniture",
            "type":"Manufacturing & Wholesale Goods"
        }
    ],
    "sg:phone":"+1 905 857 9737",
    "sg:postcode":"L7E 5B5",
    "sg:province":"ON",
    "sg:tags":[
        "fixture",
        "store"
    ],
    "wof:name":"Peerless Custom Woodworking",
    "wof:placetype":"venue"
},
  "geometry": {"coordinates":[-79.728424,43.865383],"type":"Point"}
}