{
  "type": "Feature",
  "properties": {
    "addr:full":"707 Exeter Rd London ON N6E 1L3",
    "addr:housenumber":"707",
    "addr:postcode":"n6e 1l3",
    "addr:street":"Exeter Rd",
    "iso:country":"CA",
    "sg:address":"707 Exeter Rd",
    "sg:city":"London",
    "sg:classifiers":[
        {
            "category":"Government",
            "subcategory":"Fire Station",
            "type":"Public Place"
        }
    ],
    "sg:phone":"+1 ",
    "sg:postcode":"N6E 1L3",
    "sg:province":"ON",
    "sg:tags":[
        "department"
    ],
    "wof:name":"Ontario Fire Marshall",
    "wof:placetype":"venue"
},
  "geometry": {"coordinates":[-81.2214126587,42.9253578186],"type":"Point"}
}