{
  "type": "Feature",
  "properties": {
    "addr:full":"88 Golden Dr Coquitlam BC V3K 6T1",
    "addr:housenumber":"88",
    "addr:postcode":"v3k 6t1",
    "addr:street":"Golden Dr",
    "iso:country":"CA",
    "sg:address":"88 Golden Dr",
    "sg:city":"Coquitlam",
    "sg:classifiers":[
        {
            "category":"Freight",
            "type":"Transportation"
        }
    ],
    "sg:phone":"+1 604 464 2120",
    "sg:postcode":"V3K 6T1",
    "sg:province":"BC",
    "sg:tags":[
        "trucking"
    ],
    "wof:name":"Blanchard Transport Ltd",
    "wof:placetype":"venue"
},
  "geometry": {"coordinates":[-122.824653626,49.2314338684],"type":"Point"}
}