{
  "type": "Feature",
  "properties": {
    "iso:country":"CA",
    "sg:address":"2163 Sixth Line",
    "sg:city":"Oakville",
    "sg:classifiers":[
        {
            "category":"Food & Beverages",
            "subcategory":"Meat & Fish",
            "type":"Retail Goods"
        }
    ],
    "sg:phone":"+1 905 338 3459",
    "sg:postcode":"L6H 3N7",
    "sg:province":"ON",
    "sg:tags":[
        "frozen"
    ],
    "wof:name":"M & M Meat Shops",
    "wof:placetype":"venue"
},
  "geometry": {"coordinates":[-79.718338,43.468636],"type":"Point"}
}