{
  "type": "Feature",
  "properties": {
    "iso:country":"CA",
    "sg:address":"79 Adeline Ave",
    "sg:city":"Tottenham",
    "sg:classifiers":[
        {
            "category":"Shopping",
            "subcategory":"Gifts & Souvenirs",
            "type":"Retail Goods"
        }
    ],
    "sg:phone":"+1 905 936 2661",
    "sg:postcode":"L0G 1W0",
    "sg:province":"ON",
    "sg:tags":[
        "balloon",
        "artist"
    ],
    "wof:name":"Stewart's Baskets & Balloons",
    "wof:placetype":"venue"
},
  "geometry": {"coordinates":[-79.799622,44.018551],"type":"Point"}
}