{
  "type": "Feature",
  "properties": {
    "addr:full":"North Vancouver BC V7L 2P9",
    "addr:postcode":"v7l 2p9",
    "iso:country":"CA",
    "sg:city":"North Vancouver",
    "sg:classifiers":[
        {
            "category":"Professional",
            "subcategory":"Lawyer & Legal Services",
            "type":"Services"
        }
    ],
    "sg:phone":"+1 604 983 6670",
    "sg:postcode":"V7L 2P9",
    "sg:province":"BC",
    "sg:tags":[
        "attorney"
    ],
    "wof:name":"Haddock & CO",
    "wof:placetype":"venue"
},
  "geometry": {"coordinates":[-123.071106,49.322277],"type":"Point"}
}