{
  "type": "Feature",
  "properties": {
    "addr:full":"70 Rue Notre-Dame O Alma QC G8B 2K1",
    "addr:housenumber":"70",
    "addr:postcode":"g8b 2k1",
    "addr:street":"Rue Notre-Dame O",
    "iso:country":"CA",
    "sg:address":"70 Rue Notre-Dame O",
    "sg:city":"Alma",
    "sg:classifiers":[
        {
            "category":"Government",
            "subcategory":"Fire Station",
            "type":"Public Place"
        }
    ],
    "sg:phone":"+1 418 669 5050",
    "sg:postcode":"G8B 2K1",
    "sg:province":"QC",
    "sg:tags":[
        "department",
        "police"
    ],
    "wof:name":"Alma Feu Dept",
    "wof:placetype":"venue"
},
  "geometry": {"coordinates":[-71.6443862915,48.5382385254],"type":"Point"}
}