{
  "type": "Feature",
  "properties": {
    "addr:full":"Winnipeg MB R3C 0M6",
    "addr:postcode":"r3c 0m6",
    "iso:country":"CA",
    "sg:city":"Winnipeg",
    "sg:classifiers":[
        {
            "category":"Professional",
            "subcategory":"Management & Consulting",
            "type":"Services"
        }
    ],
    "sg:phone":"+1 204 925 2790",
    "sg:postcode":"R3C 0M6",
    "sg:province":"MB",
    "sg:tags":[
        "consultant",
        "training"
    ],
    "wof:name":"Anokiiwin Training Institute",
    "wof:placetype":"venue"
},
  "geometry": {"coordinates":[-97.139343,49.891136],"type":"Point"}
}