{
  "type": "Feature",
  "properties": {
    "addr:full":"Hwy 89 Rosemont ON L0N 1R0",
    "addr:postcode":"l0n 1r0",
    "addr:street":"Hwy 89",
    "iso:country":"CA",
    "sg:address":"Hwy 89",
    "sg:city":"Rosemont",
    "sg:classifiers":[
        {
            "category":"Real Estate",
            "subcategory":"Real Estate Agent",
            "type":"Services"
        }
    ],
    "sg:phone":"+1 705 435 6666",
    "sg:postcode":"L0N 1R0",
    "sg:province":"ON",
    "wof:name":"Country Living Realty Ltd",
    "wof:placetype":"venue"
},
  "geometry": {"coordinates":[-79.993217,44.123417],"type":"Point"}
}