{
  "type": "Feature",
  "properties": {
    "addr:full":"217 Main St Trochu AB T0M 2C0",
    "addr:housenumber":"217",
    "addr:postcode":"t0m 2c0",
    "addr:street":"Main St",
    "iso:country":"CA",
    "sg:address":"217 Main St",
    "sg:city":"Trochu",
    "sg:classifiers":[
        {
            "category":"Shopping",
            "subcategory":"Shoes",
            "type":"Retail Goods"
        }
    ],
    "sg:phone":"+1 403 442 3065",
    "sg:postcode":"T0M 2C0",
    "sg:province":"AB",
    "wof:name":"Henry's Shoes Ltd",
    "wof:placetype":"venue"
},
  "geometry": {"coordinates":[-113.22624969500001,51.8271522522],"type":"Point"}
}