{
  "type": "Feature",
  "properties": {
    "addr:full":"43 Crosby Ave Richmond Hill ON L4C 2R3",
    "addr:housenumber":"43",
    "addr:postcode":"l4c 2r3",
    "addr:street":"Crosby Ave",
    "iso:country":"CA",
    "sg:address":"43 Crosby Ave",
    "sg:city":"Richmond Hill",
    "sg:classifiers":[
        {
            "category":"Social Services",
            "subcategory":"Child Care",
            "type":"Services"
        }
    ],
    "sg:phone":"+1 905 737 4493",
    "sg:postcode":"L4C 2R3",
    "sg:province":"ON",
    "wof:name":"Genesis Community Daycare Ctr",
    "wof:placetype":"venue"
},
  "geometry": {"coordinates":[-79.43740099999999,43.880634],"type":"Point"}
}