{
  "type": "Feature",
  "properties": {
    "addr:full":"Penticton BC V2A 1H1",
    "addr:postcode":"v2a 1h1",
    "iso:country":"CA",
    "sg:city":"Penticton",
    "sg:classifiers":[
        {
            "category":"Professional",
            "subcategory":"Accounting & Tax Preparation",
            "type":"Services"
        }
    ],
    "sg:phone":"+1 250 492 6020",
    "sg:postcode":"V2A 1H1",
    "sg:province":"BC",
    "sg:tags":[
        "accountant"
    ],
    "wof:name":"Bdo Dunwoody",
    "wof:placetype":"venue"
},
  "geometry": {"coordinates":[-119.59191131599999,49.5014953613],"type":"Point"}
}