{
  "type": "Feature",
  "properties": {
    "addr:full":"6725 Pacific Cir Mississauga ON L5T 1S6",
    "addr:housenumber":"6725",
    "addr:postcode":"l5t 1s6",
    "addr:street":"Pacific Cir",
    "iso:country":"CA",
    "sg:address":"6725 Pacific Cir",
    "sg:city":"Mississauga",
    "sg:classifiers":[
        {
            "category":"Wholesale",
            "subcategory":"Non-durable Goods",
            "type":"Manufacturing & Wholesale Goods"
        }
    ],
    "sg:phone":"+1 905 670 3490",
    "sg:postcode":"L5T 1S6",
    "sg:province":"ON",
    "wof:name":"World of Gifts & Home Decor",
    "wof:placetype":"venue"
},
  "geometry": {"coordinates":[-79.67938995359999,43.6595306396],"type":"Point"}
}