{
  "type": "Feature",
  "properties": {
    "addr:full":"45 Rue Gelinas Laval QC H7M 3H8",
    "addr:housenumber":"45",
    "addr:postcode":"h7m 3h8",
    "addr:street":"Rue Gelinas",
    "iso:country":"CA",
    "sg:address":"45 Rue Gelinas",
    "sg:city":"Laval",
    "sg:classifiers":[
        {
            "category":"Retail",
            "subcategory":"Auto Repair",
            "type":"Services"
        }
    ],
    "sg:phone":"+1 450 975 4422",
    "sg:postcode":"H7M 3H8",
    "sg:province":"QC",
    "sg:tags":[
        "repairing",
        "automobile",
        "wheel",
        "alignment"
    ],
    "wof:name":"Alignement Garbis",
    "wof:placetype":"venue"
},
  "geometry": {"coordinates":[-73.71483600000001,45.588669],"type":"Point"}
}