{
  "type": "Feature",
  "properties": {
    "addr:full":"1176 Main St Smithers BC V0J 2N0",
    "addr:housenumber":"1176",
    "addr:postcode":"v0j 2n0",
    "addr:street":"Main St",
    "iso:country":"CA",
    "sg:address":"1176 Main St",
    "sg:city":"Smithers",
    "sg:classifiers":[
        {
            "category":"Travel",
            "subcategory":"Travel Agent",
            "type":"Entertainment"
        }
    ],
    "sg:phone":"+1 250 847 4314",
    "sg:postcode":"V0J 2N0",
    "sg:province":"BC",
    "sg:tags":[
        "agency",
        "bureau"
    ],
    "wof:name":"Uniglobe Priority Travel Svc",
    "wof:placetype":"venue"
},
  "geometry": {"coordinates":[-127.171234,54.779762],"type":"Point"}
}