{
  "type": "Feature",
  "properties": {
    "addr:full":"118 Dean Park Rd Scarborough ON M1B 3E6",
    "addr:housenumber":"118",
    "addr:postcode":"m1b 3e6",
    "addr:street":"Dean Park Rd",
    "iso:country":"CA",
    "sg:address":"118 Dean Park Rd",
    "sg:city":"Scarborough",
    "sg:classifiers":[
        {
            "category":"Building & Trades",
            "subcategory":"Construction",
            "type":"Services"
        }
    ],
    "sg:phone":"+1 416 621 6183",
    "sg:postcode":"M1B 3E6",
    "sg:province":"ON",
    "sg:tags":[
        "downspouts",
        "gutter"
    ],
    "wof:name":"John's Aluminium",
    "wof:placetype":"venue"
},
  "geometry": {"coordinates":[-79.17436981199999,43.8014945984],"type":"Point"}
}