{
  "type": "Feature",
  "properties": {
    "addr:full":"Stettler AB T0C 2L2",
    "addr:postcode":"t0c 2l2",
    "iso:country":"CA",
    "sg:city":"Stettler",
    "sg:classifiers":[
        {
            "category":"Travel",
            "subcategory":"Hotels & Motels",
            "type":"Entertainment"
        }
    ],
    "sg:phone":"+1 403 742 2353",
    "sg:postcode":"T0C 2L2",
    "sg:province":"AB",
    "wof:name":"Stettler Hotel",
    "wof:placetype":"venue"
},
  "geometry": {"coordinates":[-112.70504,52.326145],"type":"Point"}
}