{
  "type": "Feature",
  "properties": {
    "addr:full":"2249 Sydney Rd Reserve Mines NS B1E 1J9",
    "addr:housenumber":"2249",
    "addr:postcode":"b1e 1j9",
    "addr:street":"Sydney Rd",
    "iso:country":"CA",
    "sg:address":"2249 Sydney Rd",
    "sg:city":"Reserve Mines",
    "sg:classifiers":[
        {
            "category":"Banks & Credit Unions",
            "subcategory":"Bank",
            "type":"Services"
        }
    ],
    "sg:phone":"+1 902 849 4583",
    "sg:postcode":"B1E 1J9",
    "sg:province":"NS",
    "wof:name":"Glace Bay Central Credit Union",
    "wof:placetype":"venue"
},
  "geometry": {"coordinates":[-60.021317,46.180294],"type":"Point"}
}