{
  "type": "Feature",
  "properties": {
    "addr:full":"383 Princess St Kingston ON K7L 1B9",
    "addr:housenumber":"383",
    "addr:postcode":"k7l 1b9",
    "addr:street":"Princess St",
    "iso:country":"CA",
    "sg:address":"383 Princess St",
    "sg:city":"Kingston",
    "sg:classifiers":[
        {
            "category":"Restaurant",
            "type":"Food & Drink"
        }
    ],
    "sg:phone":"+1 613 542 9195",
    "sg:postcode":"K7L 1B9",
    "sg:province":"ON",
    "wof:name":"Pita Grill",
    "wof:placetype":"venue"
},
  "geometry": {"coordinates":[-76.491409,44.233055],"type":"Point"}
}