{
  "type": "Feature",
  "properties": {
    "addr:full":"573 Second Line E Sault Ste Marie ON P6B 4K2",
    "addr:housenumber":"573",
    "addr:postcode":"p6b 4k2",
    "addr:street":"Second Line E",
    "iso:country":"CA",
    "sg:address":"573 Second Line E",
    "sg:city":"Sault Ste Marie",
    "sg:classifiers":[
        {
            "category":"Retail",
            "subcategory":"Auto Repair",
            "type":"Services"
        }
    ],
    "sg:phone":"+1 705 942 1700",
    "sg:postcode":"P6B 4K2",
    "sg:province":"ON",
    "sg:tags":[
        "body",
        "automobile",
        "painting"
    ],
    "wof:name":"Superior Auto Body",
    "wof:placetype":"venue"
},
  "geometry": {"coordinates":[-84.323982,46.538124],"type":"Point"}
}