{
  "type": "Feature",
  "properties": {
    "addr:full":"220 4th St Rainy River ON P0W 1L0",
    "addr:housenumber":"220",
    "addr:postcode":"p0w 1l0",
    "addr:street":"4Th St",
    "iso:country":"CA",
    "sg:address":"220 4th St",
    "sg:city":"Rainy River",
    "sg:classifiers":[
        {
            "category":"Shopping",
            "subcategory":"Bicycles & Sporting Goods",
            "type":"Retail Goods"
        }
    ],
    "sg:phone":"+1 807 852 4045",
    "sg:postcode":"P0W 1L0",
    "sg:province":"ON",
    "sg:tags":[
        "hardware"
    ],
    "wof:name":"Rainy River True Value",
    "wof:placetype":"venue"
},
  "geometry": {"coordinates":[-94.5681838989,48.7194595337],"type":"Point"}
}