{
  "type": "Feature",
  "properties": {
    "addr:full":"Cobourg ON K9A 5J3",
    "addr:postcode":"k9a 5j3",
    "iso:country":"CA",
    "sg:city":"Cobourg",
    "sg:classifiers":[
        {
            "category":"Insurance",
            "subcategory":"Insurance Agent",
            "type":"Services"
        }
    ],
    "sg:phone":"+1 905 372 8701",
    "sg:postcode":"K9A 5J3",
    "sg:province":"ON",
    "wof:name":"Wilson, Harvey",
    "wof:placetype":"venue"
},
  "geometry": {"coordinates":[-78.19282531739999,43.9717826843],"type":"Point"}
}