{
  "type": "Feature",
  "properties": {
    "addr:full":"4630 Old Simcoe St Oshawa ON L1H 7K4",
    "addr:housenumber":"4630",
    "addr:postcode":"l1h 7k4",
    "addr:street":"Old Simcoe St",
    "iso:country":"CA",
    "sg:address":"4630 Old Simcoe St",
    "sg:city":"Oshawa",
    "sg:classifiers":[
        {
            "category":"Retail",
            "subcategory":"Auto Repair",
            "type":"Services"
        }
    ],
    "sg:phone":"+1 905 655 9278",
    "sg:postcode":"L1H 7K4",
    "sg:province":"ON",
    "sg:tags":[
        "automobile",
        "lubrication"
    ],
    "wof:name":"Compass Oil Changing",
    "wof:placetype":"venue"
},
  "geometry": {"coordinates":[-78.9269485474,44.0166511536],"type":"Point"}
}