{
  "type": "Feature",
  "properties": {
    "addr:full":"950 10th Ave E Vancouver BC V5T 2B2",
    "addr:housenumber":"950",
    "addr:postcode":"v5t 2b2",
    "addr:street":"10Th Ave E",
    "iso:country":"CA",
    "sg:address":"950 10th Ave E",
    "sg:city":"Vancouver",
    "sg:classifiers":[
        {
            "category":"Government",
            "subcategory":"Office",
            "type":"Public Place"
        }
    ],
    "sg:phone":"+1 604 875 4107",
    "sg:postcode":"V5T 2B2",
    "sg:province":"BC",
    "wof:name":"Bcubc Faculty of Medicine",
    "wof:placetype":"venue"
},
  "geometry": {"coordinates":[-123.084152,49.261421],"type":"Point"}
}