{
  "type": "Feature",
  "properties": {
    "addr:full":"463 Danforth Ave Toronto ON M4K 1P1",
    "addr:housenumber":"463",
    "addr:postcode":"m4k 1p1",
    "addr:street":"Danforth Ave",
    "iso:country":"CA",
    "sg:address":"463 Danforth Ave",
    "sg:city":"Toronto",
    "sg:classifiers":[
        {
            "category":"Shopping",
            "subcategory":"Discount & Variety Stores",
            "type":"Retail Goods"
        }
    ],
    "sg:phone":"+1 416 463 5855",
    "sg:postcode":"M4K 1P1",
    "sg:province":"ON",
    "wof:name":"Lucky Shop",
    "wof:placetype":"venue"
},
  "geometry": {"coordinates":[-79.3499984741,43.6777648926],"type":"Point"}
}