{
  "type": "Feature",
  "properties": {
    "addr:full":"3375 Rue Prieur E Montreal-Nord QC H1H 2K8",
    "addr:housenumber":"3375",
    "addr:postcode":"h1h 2k8",
    "addr:street":"Rue Prieur E",
    "iso:country":"CA",
    "sg:address":"3375 Rue Prieur E",
    "sg:city":"Montreal-Nord",
    "sg:classifiers":[
        {
            "category":"Health Services",
            "subcategory":"Nursing And Care Facility",
            "type":"Services"
        }
    ],
    "sg:phone":"+1 514 852 4261",
    "sg:postcode":"H1H 2K8",
    "sg:province":"QC",
    "sg:tags":[
        "home",
        "retirement",
        "community"
    ],
    "wof:name":"Manoir Guy Dore",
    "wof:placetype":"venue"
},
  "geometry": {"coordinates":[-73.64463000000001,45.582832],"type":"Point"}
}