{
  "type": "Feature",
  "properties": {
    "addr:full":"2386 Haines Rd Mississauga ON L4Y 1Y6",
    "addr:housenumber":"2386",
    "addr:postcode":"l4y 1y6",
    "addr:street":"Haines Rd",
    "iso:country":"CA",
    "sg:address":"2386 Haines Rd",
    "sg:city":"Mississauga",
    "sg:classifiers":[
        {
            "category":"Manufacturing",
            "subcategory":"Printing",
            "type":"Manufacturing & Wholesale Goods"
        }
    ],
    "sg:phone":"+1 905 281 9002",
    "sg:postcode":"L4Y 1Y6",
    "sg:province":"ON",
    "sg:tags":[
        "printer"
    ],
    "wof:name":"Accu Printing",
    "wof:placetype":"venue"
},
  "geometry": {"coordinates":[-79.5907363892,43.5930671692],"type":"Point"}
}