{
  "type": "Feature",
  "properties": {
    "addr:full":"1289 Seagull Dr Mississauga ON L5J 3T6",
    "addr:housenumber":"1289",
    "addr:postcode":"l5j 3t6",
    "addr:street":"Seagull Dr",
    "iso:country":"CA",
    "sg:address":"1289 Seagull Dr",
    "sg:city":"Mississauga",
    "sg:classifiers":[
        {
            "category":"Professional",
            "type":"Services"
        }
    ],
    "sg:phone":"+1 905 822 1212",
    "sg:postcode":"L5J 3T6",
    "sg:province":"ON",
    "sg:tags":[
        "financing",
        "establishment"
    ],
    "wof:name":"Nemeth Concepts Inc",
    "wof:placetype":"venue"
},
  "geometry": {"coordinates":[-79.6448974609,43.5105514526],"type":"Point"}
}