{
  "type": "Feature",
  "properties": {
    "addr:full":"Ohsweken ON N0A 1M0",
    "addr:postcode":"n0a 1m0",
    "iso:country":"CA",
    "sg:city":"Ohsweken",
    "sg:classifiers":[
        {
            "category":"Building & Trades",
            "subcategory":"Construction",
            "type":"Services"
        }
    ],
    "sg:phone":"+1 519 445 4822",
    "sg:postcode":"N0A 1M0",
    "sg:province":"ON",
    "sg:tags":[
        "concrete",
        "contractor"
    ],
    "wof:name":"Dan Elliott Construction",
    "wof:placetype":"venue"
},
  "geometry": {"coordinates":[-80.11879730219999,43.0690460205],"type":"Point"}
}