{
  "type": "Feature",
  "properties": {
    "addr:full":"2270 Rue Principale Sainte-Elisabeth QC J0K 2J0",
    "addr:housenumber":"2270",
    "addr:postcode":"j0k 2j0",
    "addr:street":"Rue Principale",
    "iso:country":"CA",
    "sg:address":"2270 Rue Principale",
    "sg:city":"Sainte-Elisabeth",
    "sg:classifiers":[
        {
            "category":"Government",
            "subcategory":"Office",
            "type":"Public Place"
        }
    ],
    "sg:phone":"+1 450 759 2875",
    "sg:postcode":"J0K 2J0",
    "sg:province":"QC",
    "sg:tags":[
        "village"
    ],
    "wof:name":"Ste Elisabeth Jardin D'Enfants",
    "wof:placetype":"venue"
},
  "geometry": {"coordinates":[-73.350632,46.095482],"type":"Point"}
}