{
  "type": "Feature",
  "properties": {
    "addr:full":"2335 Beacon Ave Sidney BC V8L 1W9",
    "addr:housenumber":"2335",
    "addr:postcode":"v8l 1w9",
    "addr:street":"Beacon Ave",
    "iso:country":"CA",
    "sg:address":"2335 Beacon Ave",
    "sg:city":"Sidney",
    "sg:classifiers":[
        {
            "category":"Food & Beverages",
            "subcategory":"Liquor & Beverages",
            "type":"Retail Goods"
        }
    ],
    "sg:phone":"+1 250 656 3041",
    "sg:postcode":"V8L 1W9",
    "sg:province":"BC",
    "sg:tags":[
        "store"
    ],
    "wof:name":"Liquor Stores-Government",
    "wof:placetype":"venue"
},
  "geometry": {"coordinates":[-123.402633667,48.6488189697],"type":"Point"}
}