{
  "type": "Feature",
  "properties": {
    "addr:full":"Charlesbourg QC G1G 3L8",
    "addr:postcode":"g1g 3l8",
    "iso:country":"CA",
    "sg:city":"Charlesbourg",
    "sg:classifiers":[
        {
            "category":"Retail",
            "subcategory":"Portrait Studio",
            "type":"Services"
        }
    ],
    "sg:phone":"+1 418 626 8972",
    "sg:postcode":"G1G 3L8",
    "sg:province":"QC",
    "sg:tags":[
        "photographer"
    ],
    "wof:name":"Studio Vandry Enr",
    "wof:placetype":"venue"
},
  "geometry": {"coordinates":[-71.2771682739,46.8808326721],"type":"Point"}
}