{
  "type": "Feature",
  "properties": {
    "addr:full":"1110 Stellar Dr Newmarket ON L3Y 7B7",
    "addr:housenumber":"1110",
    "addr:postcode":"l3y 7b7",
    "addr:street":"Stellar Dr",
    "iso:country":"CA",
    "sg:address":"1110 Stellar Dr",
    "sg:city":"Newmarket",
    "sg:classifiers":[
        {
            "category":"Professional",
            "type":"Services"
        }
    ],
    "sg:phone":"+1 905 898 0985",
    "sg:postcode":"L3Y 7B7",
    "sg:province":"ON",
    "sg:tags":[
        "establishment",
        "rental"
    ],
    "wof:name":"Leisure Activities Inc",
    "wof:placetype":"venue"
},
  "geometry": {"coordinates":[-79.43157196040001,44.0764808655],"type":"Point"}
}