{
  "type": "Feature",
  "properties": {
    "addr:full":"Scarborough ON M1H 3B7",
    "addr:postcode":"m1h 3b7",
    "iso:country":"CA",
    "sg:city":"Scarborough",
    "sg:classifiers":[
        {
            "category":"Health Services",
            "subcategory":"Doctor",
            "type":"Services"
        }
    ],
    "sg:phone":"+1 416 431 2323",
    "sg:postcode":"M1H 3B7",
    "sg:province":"ON",
    "sg:tags":[
        "dentist"
    ],
    "wof:name":"Segal, David N DDS",
    "wof:placetype":"venue"
},
  "geometry": {"coordinates":[-79.23215500000001,43.77647],"type":"Point"}
}