{
  "type": "Feature",
  "properties": {
    "addr:full":"Temiscaming QC J0Z 3R0",
    "addr:postcode":"j0z 3r0",
    "iso:country":"CA",
    "sg:city":"Temiscaming",
    "sg:classifiers":[
        {
            "category":"Freight",
            "type":"Transportation"
        }
    ],
    "sg:phone":"+1 819 627 1633",
    "sg:postcode":"J0Z 3R0",
    "sg:province":"QC",
    "sg:tags":[
        "warehouse",
        "self",
        "storage"
    ],
    "wof:name":"Temiscaming Warehousing",
    "wof:placetype":"venue"
},
  "geometry": {"coordinates":[-79.0622177124,46.7366485596],"type":"Point"}
}