{
  "type": "Feature",
  "properties": {
    "addr:full":"PO Box 50066 Rpo Marlborough M Calgary AB T2A 7P1",
    "addr:housenumber":"po box",
    "addr:postcode":"50066;t2a 7p1",
    "addr:street":"M",
    "iso:country":"CA",
    "sg:address":"PO Box 50066 Rpo Marlborough M",
    "sg:city":"Calgary",
    "sg:classifiers":[
        {
            "category":"Building & Trades",
            "subcategory":"Electrical",
            "type":"Services"
        }
    ],
    "sg:phone":"+1 403 248 0037",
    "sg:postcode":"T2A 7P1",
    "sg:province":"AB",
    "sg:tags":[
        "electric",
        "contractor"
    ],
    "wof:name":"4 Star Electric",
    "wof:placetype":"venue"
},
  "geometry": {"coordinates":[-114.063194275,51.0450744629],"type":"Point"}
}