{
  "type": "Feature",
  "properties": {
    "addr:full":"Calgary AB T2Y 3H9",
    "addr:postcode":"t2y 3h9",
    "iso:country":"CA",
    "sg:city":"Calgary",
    "sg:classifiers":[
        {
            "category":"Bars & Pubs",
            "type":"Food & Drink"
        }
    ],
    "sg:phone":"+1 403 256 3772",
    "sg:postcode":"T2Y 3H9",
    "sg:province":"AB",
    "sg:tags":[
        "lounge",
        "cocktail"
    ],
    "wof:name":"Plaka Greek Taverna",
    "wof:placetype":"venue"
},
  "geometry": {"coordinates":[-114.064888001,50.9015388489],"type":"Point"}
}