{
  "type": "Feature",
  "properties": {
    "addr:full":"200 Oronsay St Colonsay SK S0K 0Z0",
    "addr:housenumber":"200",
    "addr:postcode":"s0k 0z0",
    "addr:street":"Oronsay St",
    "iso:country":"CA",
    "sg:address":"200 Oronsay St",
    "sg:city":"Colonsay",
    "sg:classifiers":[
        {
            "category":"Education",
            "subcategory":"School",
            "type":"Public Place"
        }
    ],
    "sg:phone":"+1 306 255 2050",
    "sg:postcode":"S0K 0Z0",
    "sg:province":"SK",
    "wof:name":"Colonsay School",
    "wof:placetype":"venue"
},
  "geometry": {"coordinates":[-105.877464,51.982735],"type":"Point"}
}