{
  "type": "Feature",
  "properties": {
    "addr:full":"1809 4 St SW Calgary AB T2S 1W2",
    "addr:housenumber":"1809 4",
    "addr:postcode":"t2s 1w2",
    "addr:street":"St Sw",
    "iso:country":"CA",
    "sg:address":"1809 4 St SW",
    "sg:city":"Calgary",
    "sg:classifiers":[
        {
            "category":"Food & Beverages",
            "subcategory":"Liquor & Beverages",
            "type":"Retail Goods"
        }
    ],
    "sg:phone":"+1 403 229 1919",
    "sg:postcode":"T2S 1W2",
    "sg:province":"AB",
    "sg:tags":[
        "store"
    ],
    "wof:name":"4th Street Liquor & Wine",
    "wof:placetype":"venue"
},
  "geometry": {"coordinates":[-114.071716309,51.0365371704],"type":"Point"}
}