{
  "type": "Feature",
  "properties": {
    "addr:full":"43 Queen's Park Cres E Toronto ON M5S 2C3",
    "addr:housenumber":"43",
    "addr:postcode":"m5s 2c3",
    "addr:street":"Queen'S Park Cres E",
    "iso:country":"CA",
    "sg:address":"43 Queen's Park Cres E",
    "sg:city":"Toronto",
    "sg:classifiers":[
        {
            "category":"Organizations",
            "subcategory":"Professional Association",
            "type":"Services"
        }
    ],
    "sg:phone":"+1 416 979 2973",
    "sg:postcode":"M5S 2C3",
    "sg:province":"ON",
    "wof:name":"Multicultural History Society",
    "wof:placetype":"venue"
},
  "geometry": {"coordinates":[-79.384331,43.672882],"type":"Point"}
}