{
  "type": "Feature",
  "properties": {
    "iso:country":"CA",
    "sg:address":"1200 Cartier Ave",
    "sg:city":"Coquitlam",
    "sg:classifiers":[
        {
            "category":"Organizations",
            "subcategory":"Religious Organization",
            "type":"Services"
        }
    ],
    "sg:phone":"+1 604 939 2213",
    "sg:postcode":"V3K 2C3",
    "sg:province":"BC",
    "sg:tags":[
        "church"
    ],
    "wof:name":"Beacon Unitarian Church",
    "wof:placetype":"venue"
},
  "geometry": {"coordinates":[-122.858925,49.241127],"type":"Point"}
}