{
  "type": "Feature",
  "properties": {
    "iso:country":"CA",
    "sg:city":"Montreal",
    "sg:classifiers":[
        {
            "category":"Insurance",
            "subcategory":"Insurance Agent",
            "type":"Services"
        }
    ],
    "sg:phone":"+1 514 931 0111",
    "sg:postcode":"H3H 2T6",
    "sg:province":"QC",
    "wof:name":"Lawrence Joseph Assoc Ltd",
    "wof:placetype":"venue"
},
  "geometry": {"coordinates":[-73.5621261597,45.5341720581],"type":"Point"}
}