{
  "type": "Feature",
  "properties": {
    "iso:country":"CA",
    "sg:address":"1989 Old Mill Rd",
    "sg:city":"Kitchener",
    "sg:classifiers":[
        {
            "category":"Building & Trades",
            "subcategory":"Construction",
            "type":"Services"
        }
    ],
    "sg:phone":"+1 519 748 4301",
    "sg:postcode":"N2P 1E4",
    "sg:province":"ON",
    "sg:tags":[
        "contractor",
        "general"
    ],
    "wof:name":"Ivan Biuk Construction Ltd",
    "wof:placetype":"venue"
},
  "geometry": {"coordinates":[-80.410698,43.39323],"type":"Point"}
}