{
  "type": "Feature",
  "properties": {
    "addr:full":"Surrey BC V3W 2M9",
    "addr:postcode":"v3w 2m9",
    "iso:country":"CA",
    "sg:city":"Surrey",
    "sg:classifiers":[
        {
            "category":"Health Services",
            "subcategory":"Doctor",
            "type":"Services"
        }
    ],
    "sg:phone":"+1 604 572 8161",
    "sg:postcode":"V3W 2M9",
    "sg:province":"BC",
    "sg:tags":[
        "physician",
        "surgeon"
    ],
    "wof:name":"Kwantlen Medical Clinic",
    "wof:placetype":"venue"
},
  "geometry": {"coordinates":[-122.867919922,49.1339607239],"type":"Point"}
}