{
  "type": "Feature",
  "properties": {
    "iso:country":"CA",
    "sg:address":"13215 113A St NW",
    "sg:city":"Edmonton",
    "sg:classifiers":[
        {
            "category":"Education",
            "subcategory":"School",
            "type":"Public Place"
        }
    ],
    "sg:phone":"+1 780 453 1576",
    "sg:postcode":"T5E 5B9",
    "sg:province":"AB",
    "wof:name":"Rosslyn Junior High School",
    "wof:placetype":"venue"
},
  "geometry": {"coordinates":[-113.516242981,53.5923957825],"type":"Point"}
}