{
  "type": "Feature",
  "properties": {
    "iso:country":"CA",
    "sg:address":"1428 Rue Sherbrooke O",
    "sg:city":"Montreal",
    "sg:classifiers":[
        {
            "category":"Shopping",
            "type":"Retail Goods"
        }
    ],
    "sg:phone":"+1 514 840 0990",
    "sg:postcode":"H3G 1K4",
    "sg:province":"QC",
    "sg:tags":[
        "art",
        "gallery",
        "dealer"
    ],
    "wof:name":"Galeria Lamoureux Ritzenhoff",
    "wof:placetype":"venue"
},
  "geometry": {"coordinates":[-73.5645370483,45.5256004333],"type":"Point"}
}