{
  "type": "Feature",
  "properties": {
    "addr:full":"40 Rue Principale Pohenegamook QC G0L 1J0",
    "addr:housenumber":"40",
    "addr:postcode":"g0l 1j0",
    "addr:street":"Rue Principale",
    "iso:country":"CA",
    "sg:address":"40 Rue Principale",
    "sg:city":"Pohenegamook",
    "sg:classifiers":[
        {
            "category":"Manufacturing",
            "subcategory":"Lumber",
            "type":"Manufacturing & Wholesale Goods"
        }
    ],
    "sg:phone":"+1 418 893 5554",
    "sg:postcode":"G0L 1J0",
    "sg:province":"QC",
    "sg:tags":[
        "forester"
    ],
    "wof:name":"Entreprises Forestieres G & N",
    "wof:placetype":"venue"
},
  "geometry": {"coordinates":[-69.10636100000001,47.442039],"type":"Point"}
}