{
  "type": "Feature",
  "properties": {
    "iso:country":"CA",
    "sg:address":"199 Queens Ave",
    "sg:city":"London",
    "sg:classifiers":[
        {
            "category":"Professional",
            "subcategory":"Research",
            "type":"Services"
        }
    ],
    "sg:phone":"+1 519 672 7000",
    "sg:postcode":"N6A 1J1",
    "sg:province":"ON",
    "sg:tags":[
        "market",
        "analysis"
    ],
    "wof:name":"Kent Marketing Svc Ltd",
    "wof:placetype":"venue"
},
  "geometry": {"coordinates":[-81.249023,42.985203],"type":"Point"}
}