{
  "type": "Feature",
  "properties": {
    "addr:full":"199 Queens Ave London ON N6A 1J1",
    "addr:housenumber":"199",
    "addr:postcode":"n6a 1j1",
    "addr:street":"Queens Ave",
    "iso:country":"CA",
    "sg:address":"199 Queens Ave",
    "sg:city":"London",
    "sg:classifiers":[
        {
            "category":"Professional",
            "subcategory":"Research",
            "type":"Services"
        }
    ],
    "sg:phone":"+1 519 672 7000",
    "sg:postcode":"N6A 1J1",
    "sg:province":"ON",
    "sg:tags":[
        "market",
        "analysis"
    ],
    "wof:name":"Kent Marketing Svc Ltd",
    "wof:placetype":"venue"
},
  "geometry": {"coordinates":[-81.24902299999999,42.985203],"type":"Point"}
}