{
  "type": "Feature",
  "properties": {
    "addr:full":"1361 Boul DE Maisonneuve E Montreal QC H2L 2A8",
    "addr:housenumber":"1361",
    "addr:postcode":"h2l 2a8",
    "addr:street":"Boul De Maisonneuve E",
    "iso:country":"CA",
    "sg:address":"1361 Boul DE Maisonneuve E",
    "sg:city":"Montreal",
    "sg:classifiers":[
        {
            "category":"Communications",
            "subcategory":"Film & Video Production",
            "type":"Services"
        }
    ],
    "sg:phone":"+1 514 522 2269",
    "sg:postcode":"H2L 2A8",
    "sg:province":"QC",
    "sg:tags":[
        "motion",
        "picture",
        "studio",
        "producer"
    ],
    "wof:name":"Cine Doc Inc",
    "wof:placetype":"venue"
},
  "geometry": {"coordinates":[-73.55624389650001,45.5207901001],"type":"Point"}
}