{
  "type": "Feature",
  "properties": {
    "addr:full":"Thunder Bay ON P7B 6B9",
    "addr:postcode":"p7b 6b9",
    "iso:country":"CA",
    "sg:city":"Thunder Bay",
    "sg:classifiers":[
        {
            "category":"Shopping",
            "subcategory":"Clothing, Apparel, & Fashions",
            "type":"Retail Goods"
        }
    ],
    "sg:phone":"+1 807 622 8633",
    "sg:postcode":"P7B 6B9",
    "sg:province":"ON",
    "wof:name":"Cotton Ginny Plus",
    "wof:placetype":"venue"
},
  "geometry": {"coordinates":[-89.24212646479999,48.4039306641],"type":"Point"}
}