{
  "type": "Feature",
  "properties": {
    "addr:full":"RR 1 Vernon Bridge PE C0A 2E0",
    "addr:postcode":"c0a 2e0",
    "addr:street":"Rr 1",
    "iso:country":"CA",
    "sg:address":"RR 1",
    "sg:city":"Vernon Bridge",
    "sg:classifiers":[
        {
            "category":"Retail",
            "subcategory":"Funeral Services",
            "type":"Services"
        }
    ],
    "sg:phone":"+1 902 651 2248",
    "sg:postcode":"C0A 2E0",
    "sg:province":"PE",
    "sg:tags":[
        "director"
    ],
    "wof:name":"Jenkins Funeral Home",
    "wof:placetype":"venue"
},
  "geometry": {"coordinates":[-62.8825263977,46.1762771606],"type":"Point"}
}