{
  "type": "Feature",
  "properties": {
    "addr:full":"3 Rue Adams # A Gaspe QC G4X 1E5",
    "addr:housenumber":"3",
    "addr:postcode":"g4x 1e5",
    "addr:street":"Rue Adams # A Gaspe",
    "iso:country":"CA",
    "sg:address":"3 Rue Adams # A",
    "sg:city":"Gaspe",
    "sg:classifiers":[
        {
            "category":"Restaurant",
            "type":"Food & Drink"
        }
    ],
    "sg:phone":"+1 418 368 4337",
    "sg:postcode":"G4X 1E5",
    "sg:province":"QC",
    "wof:name":"Cafe Sous-Marin",
    "wof:placetype":"venue"
},
  "geometry": {"coordinates":[-64.48292499999999,48.830421],"type":"Point"}
}