{
  "type": "Feature",
  "properties": {
    "addr:full":"14971 Marine Dr White Rock BC V4B 1C3",
    "addr:housenumber":"14971",
    "addr:postcode":"v4b 1c3",
    "addr:street":"Marine Dr",
    "iso:country":"CA",
    "sg:address":"14971 Marine Dr",
    "sg:city":"White Rock",
    "sg:classifiers":[
        {
            "category":"Shopping",
            "subcategory":"Gifts & Souvenirs",
            "type":"Retail Goods"
        }
    ],
    "sg:phone":"+1 604 542 1442",
    "sg:postcode":"V4B 1C3",
    "sg:province":"BC",
    "sg:tags":[
        "shop"
    ],
    "wof:name":"Simply Irresitible",
    "wof:placetype":"venue"
},
  "geometry": {"coordinates":[-122.806854,49.021812],"type":"Point"}
}