{
  "type": "Feature",
  "properties": {
    "addr:full":"1313 Bloor St W Toronto ON M6H 1P1",
    "addr:housenumber":"1313",
    "addr:postcode":"m6h 1p1",
    "addr:street":"Bloor St W",
    "iso:country":"CA",
    "sg:address":"1313 Bloor St W",
    "sg:city":"Toronto",
    "sg:classifiers":[
        {
            "category":"Bars & Pubs",
            "type":"Food & Drink"
        }
    ],
    "sg:phone":"+1 416 535 0723",
    "sg:postcode":"M6H 1P1",
    "sg:province":"ON",
    "sg:tags":[
        "club",
        "night"
    ],
    "wof:name":"Club Paradise",
    "wof:placetype":"venue"
},
  "geometry": {"coordinates":[-79.4437866211,43.6580162048],"type":"Point"}
}