{
  "type": "Feature",
  "properties": {
    "addr:full":"502 Rue Brassard Saint-Michel-Des-Saints QC J0K 3B0",
    "addr:housenumber":"502",
    "addr:postcode":"j0k 3b0",
    "addr:street":"Rue Brassard",
    "iso:country":"CA",
    "sg:address":"502 Rue Brassard",
    "sg:city":"Saint-Michel-Des-Saints",
    "sg:classifiers":[
        {
            "category":"Retail",
            "subcategory":"Auto Repair",
            "type":"Services"
        }
    ],
    "sg:phone":"+1 450 833 6387",
    "sg:postcode":"J0K 3B0",
    "sg:province":"QC",
    "sg:tags":[
        "repairing",
        "automobile"
    ],
    "wof:name":"Garage Yves Bellerose Inc",
    "wof:placetype":"venue"
},
  "geometry": {"coordinates":[-73.916954,46.677322],"type":"Point"}
}