{
  "type": "Feature",
  "properties": {
    "addr:full":"110 Rue DE L'Industrie L'Assomption QC J5W 2V1",
    "addr:housenumber":"110",
    "addr:postcode":"j5w 2v1",
    "addr:street":"Rue De L'Industrie",
    "iso:country":"CA",
    "sg:address":"110 Rue DE L'Industrie",
    "sg:city":"L'Assomption",
    "sg:classifiers":[
        {
            "category":"Manufacturing",
            "subcategory":"Furniture",
            "type":"Manufacturing & Wholesale Goods"
        }
    ],
    "sg:phone":"+1 450 589 9897",
    "sg:postcode":"J5W 2V1",
    "sg:province":"QC",
    "wof:name":"Ebenisterie Jc Enr",
    "wof:placetype":"venue"
},
  "geometry": {"coordinates":[-73.4175872803,45.8330383301],"type":"Point"}
}