{
  "type": "Feature",
  "properties": {
    "addr:full":"Concord ON L4K 3T4",
    "addr:postcode":"l4k 3t4",
    "iso:country":"CA",
    "sg:city":"Concord",
    "sg:classifiers":[
        {
            "category":"Wholesale",
            "subcategory":"Machinery & Supplies",
            "type":"Manufacturing & Wholesale Goods"
        }
    ],
    "sg:phone":"+1 905 660 0088",
    "sg:postcode":"L4K 3T4",
    "sg:province":"ON",
    "sg:tags":[
        "tool"
    ],
    "wof:name":"Nachi Canada Ltd",
    "wof:placetype":"venue"
},
  "geometry": {"coordinates":[-79.53230285639999,43.8142166138],"type":"Point"}
}