{
  "type": "Feature",
  "properties": {
    "addr:full":"563 Rue Fridolin Laval QC H7P 3J6",
    "addr:housenumber":"563",
    "addr:postcode":"h7p 3j6",
    "addr:street":"Rue Fridolin",
    "iso:country":"CA",
    "sg:address":"563 Rue Fridolin",
    "sg:city":"Laval",
    "sg:classifiers":[
        {
            "category":"Wholesale",
            "subcategory":"Apparel",
            "type":"Manufacturing & Wholesale Goods"
        }
    ],
    "sg:phone":"+1 450 963 6405",
    "sg:postcode":"H7P 3J6",
    "sg:province":"QC",
    "sg:tags":[
        "hosiery"
    ],
    "wof:name":"Gilles Landry Agent Mfr Inc",
    "wof:placetype":"venue"
},
  "geometry": {"coordinates":[-73.808128,45.579208],"type":"Point"}
}