{
  "type": "Feature",
  "properties": {
    "addr:full":"370 Rue Sainte-Anne Chicoutimi QC G7J 2M6",
    "addr:housenumber":"370",
    "addr:postcode":"g7j 2m6",
    "addr:street":"Rue Sainte-Anne",
    "iso:country":"CA",
    "sg:address":"370 Rue Sainte-Anne",
    "sg:city":"Chicoutimi",
    "sg:classifiers":[
        {
            "category":"Recreation",
            "type":"Entertainment"
        }
    ],
    "sg:phone":"+1 418 698 3214",
    "sg:postcode":"G7J 2M6",
    "sg:province":"QC",
    "sg:tags":[
        "government",
        "hall",
        "auditorium"
    ],
    "wof:name":"Centre Communautaire Christ-Ro",
    "wof:placetype":"venue"
},
  "geometry": {"coordinates":[-71.0689163208,48.4258956909],"type":"Point"}
}