{
  "type": "Feature",
  "properties": {
    "iso:country":"CA",
    "sg:address":"471 Queensway Ave",
    "sg:city":"Kelowna",
    "sg:classifiers":[
        {
            "category":"Government",
            "subcategory":"Office",
            "type":"Public Place"
        }
    ],
    "sg:phone":"+1 250 762 9315",
    "sg:postcode":"V1Y 6S5",
    "sg:province":"BC",
    "wof:name":"Canada Human Resource Ctr",
    "wof:placetype":"venue"
},
  "geometry": {"coordinates":[-119.494057,49.887119],"type":"Point"}
}