{
  "type": "Feature",
  "properties": {
    "addr:full":"8075 Lawson Rd Milton ON L9T 5E5",
    "addr:housenumber":"8075",
    "addr:postcode":"l9t 5e5",
    "addr:street":"Lawson Rd",
    "iso:country":"CA",
    "sg:address":"8075 Lawson Rd",
    "sg:city":"Milton",
    "sg:classifiers":[
        {
            "category":"Freight",
            "type":"Transportation"
        }
    ],
    "sg:phone":"+1 905 875 4630",
    "sg:postcode":"L9T 5E5",
    "sg:province":"ON",
    "sg:tags":[
        "trucking"
    ],
    "wof:name":"Blue Line Distribution Ltd",
    "wof:placetype":"venue"
},
  "geometry": {"coordinates":[-79.879234,43.546165],"type":"Point"}
}