{
  "type": "Feature",
  "properties": {
    "addr:full":"6220 Yonge St North York ON M2M 3X4",
    "addr:housenumber":"6220",
    "addr:postcode":"m2m 3x4",
    "addr:street":"Yonge St",
    "iso:country":"CA",
    "sg:address":"6220 Yonge St",
    "sg:city":"North York",
    "sg:classifiers":[
        {
            "category":"Shopping",
            "subcategory":"Pharmacy",
            "type":"Retail Goods"
        }
    ],
    "sg:phone":"+1 416 224 8626",
    "sg:postcode":"M2M 3X4",
    "sg:province":"ON",
    "wof:name":"Drug Store Pharmacy",
    "wof:placetype":"venue"
},
  "geometry": {"coordinates":[-79.41937299999999,43.794724],"type":"Point"}
}