{
  "type": "Feature",
  "properties": {
    "addr:full":"Edmonton AB T5G 3C8",
    "addr:postcode":"t5g 3c8",
    "iso:country":"CA",
    "sg:city":"Edmonton",
    "sg:classifiers":[
        {
            "category":"Shopping",
            "type":"Retail Goods"
        }
    ],
    "sg:phone":"+1 780 424 6094",
    "sg:postcode":"T5G 3C8",
    "sg:province":"AB",
    "sg:tags":[
        "equipment",
        "care",
        "health",
        "home"
    ],
    "wof:name":"Healthcare & Rehab Specialties",
    "wof:placetype":"venue"
},
  "geometry": {"coordinates":[-113.50308200000001,53.558346],"type":"Point"}
}