{
  "type": "Feature",
  "properties": {
    "addr:full":"698 Ch Saint-Louis Beauharnois QC J6N 3G9",
    "addr:housenumber":"698",
    "addr:postcode":"j6n 3g9",
    "addr:street":"Ch Saint-Louis",
    "iso:country":"CA",
    "sg:address":"698 Ch Saint-Louis",
    "sg:city":"Beauharnois",
    "sg:classifiers":[
        {
            "category":"Retail",
            "subcategory":"Auto Repair",
            "type":"Services"
        }
    ],
    "sg:phone":"+1 450 429 7028",
    "sg:postcode":"J6N 3G9",
    "sg:province":"QC",
    "sg:tags":[
        "repairing",
        "automobile"
    ],
    "wof:name":"Garage Claude Julien",
    "wof:placetype":"venue"
},
  "geometry": {"coordinates":[-73.884254,45.287167],"type":"Point"}
}