{
  "type": "Feature",
  "properties": {
    "addr:full":"71 Charles St E Toronto ON M4Y 2T3",
    "addr:housenumber":"71",
    "addr:postcode":"m4y 2t3",
    "addr:street":"Charles St E",
    "iso:country":"CA",
    "sg:address":"71 Charles St E",
    "sg:city":"Toronto",
    "sg:classifiers":[
        {
            "category":"Professional",
            "subcategory":"Business Services",
            "type":"Services"
        }
    ],
    "sg:phone":"+1 416 925 9933",
    "sg:postcode":"M4Y 2T3",
    "sg:province":"ON",
    "sg:tags":[
        "arbitration"
    ],
    "wof:name":"Briggs Felicity",
    "wof:placetype":"venue"
},
  "geometry": {"coordinates":[-79.3821487427,43.6693191528],"type":"Point"}
}