{
  "type": "Feature",
  "properties": {
    "addr:full":"311 Markham St Toronto ON M6G 2K8",
    "addr:housenumber":"311",
    "addr:postcode":"m6g 2k8",
    "addr:street":"Markham St",
    "iso:country":"CA",
    "sg:address":"311 Markham St",
    "sg:city":"Toronto",
    "sg:classifiers":[
        {
            "category":"Professional",
            "subcategory":"Management & Consulting",
            "type":"Services"
        }
    ],
    "sg:phone":"+1 416 323 0807",
    "sg:postcode":"M6G 2K8",
    "sg:province":"ON",
    "sg:tags":[
        "town",
        "city",
        "regional",
        "planner"
    ],
    "wof:name":"Lapointe Consulting",
    "wof:placetype":"venue"
},
  "geometry": {"coordinates":[-79.4090042114,43.656829834],"type":"Point"}
}