{
  "type": "Feature",
  "properties": {
    "addr:full":"200 Front St W Toronto ON M5V 3K2",
    "addr:housenumber":"200",
    "addr:postcode":"m5v 3k2",
    "addr:street":"Front St W",
    "iso:country":"CA",
    "sg:address":"200 Front St W",
    "sg:city":"Toronto",
    "sg:classifiers":[
        {
            "category":"Restaurant",
            "type":"Food & Drink"
        }
    ],
    "sg:phone":"+1 416 977 7543",
    "sg:postcode":"M5V 3K2",
    "sg:province":"ON",
    "wof:name":"Green Curry",
    "wof:placetype":"venue"
},
  "geometry": {"coordinates":[-79.38544464109999,43.6447868347],"type":"Point"}
}