{
  "type": "Feature",
  "properties": {
    "addr:full":"Rte 3 Tusket NS B0W 3M0",
    "addr:postcode":"b0w 3m0",
    "addr:street":"Rte 3",
    "iso:country":"CA",
    "sg:address":"Rte 3",
    "sg:city":"Tusket",
    "sg:classifiers":[
        {
            "category":"Food & Beverages",
            "subcategory":"Meat & Fish",
            "type":"Retail Goods"
        }
    ],
    "sg:phone":"+1 902 648 0330",
    "sg:postcode":"B0W 3M0",
    "sg:province":"NS",
    "sg:tags":[
        "seafood"
    ],
    "wof:name":"Tusket Seafoods Ltd",
    "wof:placetype":"venue"
},
  "geometry": {"coordinates":[-65.97491455079999,43.8558425903],"type":"Point"}
}