{
  "type": "Feature",
  "properties": {
    "addr:full":"17020 95 Ave NW Edmonton AB T5T 5R5",
    "addr:housenumber":"17020",
    "addr:postcode":"t5t 5r5",
    "addr:street":"95 Ave Nw",
    "iso:country":"CA",
    "sg:address":"17020 95 Ave NW",
    "sg:city":"Edmonton",
    "sg:classifiers":[
        {
            "category":"Shopping",
            "type":"Retail Goods"
        }
    ],
    "sg:phone":"+1 780 489 9463",
    "sg:postcode":"T5T 5R5",
    "sg:province":"AB",
    "sg:tags":[
        "equipment",
        "wine",
        "supply"
    ],
    "wof:name":"Creative Connoisseur Inc",
    "wof:placetype":"venue"
},
  "geometry": {"coordinates":[-113.616753,53.531876],"type":"Point"}
}