{
  "type": "Feature",
  "properties": {
    "addr:full":"Surrey BC V3R 9W3",
    "addr:postcode":"v3r 9w3",
    "iso:country":"CA",
    "sg:city":"Surrey",
    "sg:classifiers":[
        {
            "category":"Restaurant",
            "type":"Food & Drink"
        }
    ],
    "sg:phone":"+1 604 584 0840",
    "sg:postcode":"V3R 9W3",
    "sg:province":"BC",
    "wof:name":"Earl's Restaurants",
    "wof:placetype":"venue"
},
  "geometry": {"coordinates":[-122.800713,49.187325],"type":"Point"}
}