{
  "type": "Feature",
  "properties": {
    "addr:full":"4 Avenue Rd Toronto ON M5R 2E8",
    "addr:housenumber":"4",
    "addr:postcode":"m5r 2e8",
    "addr:street":"Avenue Rd",
    "iso:country":"CA",
    "sg:address":"4 Avenue Rd",
    "sg:city":"Toronto",
    "sg:classifiers":[
        {
            "category":"Personal",
            "subcategory":"Beauty Salon",
            "type":"Services"
        }
    ],
    "sg:phone":"+1 416 926 2389",
    "sg:postcode":"M5R 2E8",
    "sg:province":"ON",
    "sg:tags":[
        "spa",
        "day"
    ],
    "wof:name":"Still Water Spa",
    "wof:placetype":"venue"
},
  "geometry": {"coordinates":[-79.394333,43.668999],"type":"Point"}
}