{
  "type": "Feature",
  "properties": {
    "iso:country":"CA",
    "sg:address":"303 8th Ave E",
    "sg:city":"Vancouver",
    "sg:classifiers":[
        {
            "category":"Arts & Performance",
            "subcategory":"Theater",
            "type":"Entertainment"
        }
    ],
    "sg:phone":"+1 604 876 9559",
    "sg:postcode":"V5T 1S1",
    "sg:province":"BC",
    "sg:tags":[
        "music"
    ],
    "wof:name":"Edam Performing Arts Soc",
    "wof:placetype":"venue"
},
  "geometry": {"coordinates":[-123.098670959,49.2638168335],"type":"Point"}
}