{
  "type": "Feature",
  "properties": {
    "addr:full":"Atholville NB E3N 4E8",
    "addr:postcode":"e3n 4e8",
    "iso:country":"CA",
    "sg:city":"Atholville",
    "sg:classifiers":[
        {
            "category":"Professional",
            "subcategory":"Research",
            "type":"Services"
        }
    ],
    "sg:phone":"+1 506 759 9678",
    "sg:postcode":"E3N 4E8",
    "sg:province":"NB",
    "sg:tags":[
        "environmental",
        "ecological",
        "engineer"
    ],
    "wof:name":"Technisol NB Inc",
    "wof:placetype":"venue"
},
  "geometry": {"coordinates":[-66.739052,47.990803],"type":"Point"}
}