{
  "type": "Feature",
  "properties": {
    "addr:full":"Levack ON P0M 2C0",
    "addr:postcode":"p0m 2c0",
    "iso:country":"CA",
    "sg:city":"Levack",
    "sg:classifiers":[
        {
            "category":"Shopping",
            "subcategory":"Pharmacy",
            "type":"Retail Goods"
        }
    ],
    "sg:phone":"+1 705 966 3612",
    "sg:postcode":"P0M 2C0",
    "sg:province":"ON",
    "wof:name":"Levack Pharmacy",
    "wof:placetype":"venue"
},
  "geometry": {"coordinates":[-81.39032,46.639065],"type":"Point"}
}