{
  "type": "Feature",
  "properties": {
    "iso:country":"CA",
    "sg:city":"Scarborough",
    "sg:classifiers":[
        {
            "category":"Manufacturing",
            "subcategory":"Food",
            "type":"Manufacturing & Wholesale Goods"
        }
    ],
    "sg:phone":"+1 416 609 2966",
    "sg:postcode":"M1S 5C6",
    "sg:province":"ON",
    "sg:tags":[
        "tea",
        "coffee"
    ],
    "wof:name":"H K Tea & Coffee CO",
    "wof:placetype":"venue"
},
  "geometry": {"coordinates":[-79.2759475708,43.7798080444],"type":"Point"}
}