{
  "type": "Feature",
  "properties": {
    "addr:full":"24 Rue Gale Ormstown QC J0S 1K0",
    "addr:housenumber":"24",
    "addr:postcode":"j0s 1k0",
    "addr:street":"Rue Gale",
    "iso:country":"CA",
    "sg:address":"24 Rue Gale",
    "sg:city":"Ormstown",
    "sg:classifiers":[
        {
            "category":"Health Services",
            "subcategory":"Doctor",
            "type":"Services"
        }
    ],
    "sg:phone":"+1 450 829 2331",
    "sg:postcode":"J0S 1K0",
    "sg:province":"QC",
    "sg:tags":[
        "clinic"
    ],
    "wof:name":"Centre Medical Ormstown",
    "wof:placetype":"venue"
},
  "geometry": {"coordinates":[-73.9987945557,45.1262283325],"type":"Point"}
}