{
  "type": "Feature",
  "properties": {
    "addr:full":"34 Av Talon Baie-Comeau QC G4Z 1J6",
    "addr:postcode":"g4z 1j6",
    "addr:street":"34 Av Talon",
    "iso:country":"CA",
    "sg:address":"34 Av Talon",
    "sg:city":"Baie-Comeau",
    "sg:classifiers":[
        {
            "category":"Building & Trades",
            "subcategory":"Electrical",
            "type":"Services"
        }
    ],
    "sg:phone":"+1 418 296 6615",
    "sg:postcode":"G4Z 1J6",
    "sg:province":"QC",
    "sg:tags":[
        "electric",
        "contractor"
    ],
    "wof:name":"Tremblay Electrique Inc",
    "wof:placetype":"venue"
},
  "geometry": {"coordinates":[-68.160828,49.218384],"type":"Point"}
}