{
  "type": "Feature",
  "properties": {
    "addr:full":"PO Box 1705 STN Bureau-Chef Chelsea QC J9B 1A1",
    "addr:housenumber":"po",
    "addr:postcode":"qc j9b 1a1",
    "addr:street":"Box 1705 Stn Bureau-Chef",
    "iso:country":"CA",
    "sg:address":"PO Box 1705 STN Bureau-Chef",
    "sg:city":"Chelsea",
    "sg:classifiers":[
        {
            "category":"Organizations",
            "subcategory":"Membership Organization",
            "type":"Services"
        }
    ],
    "sg:phone":"+1 819 827 4044",
    "sg:postcode":"J9B 1A1",
    "sg:province":"QC",
    "wof:name":"Maison Libere-Elles",
    "wof:placetype":"venue"
},
  "geometry": {"coordinates":[-75.80438232420001,45.5269737244],"type":"Point"}
}