{
  "type": "Feature",
  "properties": {
    "addr:full":"917 Alness St North York ON M3J 2J1",
    "addr:housenumber":"917",
    "addr:postcode":"m3j 2j1",
    "addr:street":"Alness St",
    "iso:country":"CA",
    "sg:address":"917 Alness St",
    "sg:city":"North York",
    "sg:classifiers":[
        {
            "category":"Wholesale",
            "subcategory":"Meat",
            "type":"Manufacturing & Wholesale Goods"
        }
    ],
    "sg:phone":"+1 416 661 9383",
    "sg:postcode":"M3J 2J1",
    "sg:province":"ON",
    "sg:tags":[
        "product"
    ],
    "wof:name":"Soloway's Hot Dog Factory",
    "wof:placetype":"venue"
},
  "geometry": {"coordinates":[-79.475708,43.780293],"type":"Point"}
}