{
  "type": "Feature",
  "properties": {
    "addr:full":"Sudbury ON P3E 1B8",
    "addr:postcode":"p3e 1b8",
    "iso:country":"CA",
    "sg:city":"Sudbury",
    "sg:classifiers":[
        {
            "category":"Health Services",
            "subcategory":"Optometrist",
            "type":"Services"
        }
    ],
    "sg:phone":"+1 705 675 2388",
    "sg:postcode":"P3E 1B8",
    "sg:province":"ON",
    "wof:name":"Kusnierczyk, Tony OD",
    "wof:placetype":"venue"
},
  "geometry": {"coordinates":[-80.994186,46.491219],"type":"Point"}
}