{
  "type": "Feature",
  "properties": {
    "addr:full":"609 Pangman St Outlook SK S0L 2N0",
    "addr:housenumber":"609",
    "addr:postcode":"s0l 2n0",
    "addr:street":"Pangman St",
    "iso:country":"CA",
    "sg:address":"609 Pangman St",
    "sg:city":"Outlook",
    "sg:classifiers":[
        {
            "category":"Health Services",
            "subcategory":"Hospital",
            "type":"Services"
        }
    ],
    "sg:phone":"+1 306 867 8676",
    "sg:postcode":"S0L 2N0",
    "sg:province":"SK",
    "wof:name":"Outlook Union Hospital",
    "wof:placetype":"venue"
},
  "geometry": {"coordinates":[-107.056816,51.486015],"type":"Point"}
}