{
  "type": "Feature",
  "properties": {
    "addr:full":"Penticton BC V2A 8J8",
    "addr:postcode":"v2a 8j8",
    "iso:country":"CA",
    "sg:city":"Penticton",
    "sg:classifiers":[
        {
            "category":"Wholesale",
            "subcategory":"Machinery & Supplies",
            "type":"Manufacturing & Wholesale Goods"
        }
    ],
    "sg:phone":"+1 250 493 4618",
    "sg:postcode":"V2A 8J8",
    "sg:province":"BC",
    "sg:tags":[
        "equipment",
        "irrigation",
        "system"
    ],
    "wof:name":"Grassroots Irrigation",
    "wof:placetype":"venue"
},
  "geometry": {"coordinates":[-119.578453064,49.4579200745],"type":"Point"}
}