{
  "type": "Feature",
  "properties": {
    "addr:full":"11 Wideford Pl North York ON M2M 4H3",
    "addr:housenumber":"11",
    "addr:postcode":"m2m 4h3",
    "addr:street":"Wideford Pl",
    "iso:country":"CA",
    "sg:address":"11 Wideford Pl",
    "sg:city":"North York",
    "sg:classifiers":[
        {
            "category":"Professional",
            "subcategory":"Management & Consulting",
            "type":"Services"
        }
    ],
    "sg:phone":"+1 416 223 5502",
    "sg:postcode":"M2M 4H3",
    "sg:province":"ON",
    "sg:tags":[
        "marketing",
        "consultant"
    ],
    "wof:name":"Unizak Enterprises Ltd",
    "wof:placetype":"venue"
},
  "geometry": {"coordinates":[-79.39683532710001,43.7887687683],"type":"Point"}
}