{
  "type": "Feature",
  "properties": {
    "addr:full":"100 White Oaks Crt Whitby ON L1P 1B7",
    "addr:housenumber":"100",
    "addr:postcode":"l1p 1b7",
    "addr:street":"White;Crt",
    "iso:country":"CA",
    "sg:address":"100 White Oaks Crt",
    "sg:city":"Whitby",
    "sg:classifiers":[
        {
            "category":"Food & Beverages",
            "subcategory":"Groceries & Convenience Stores",
            "type":"Retail Goods"
        }
    ],
    "sg:phone":"+1 905 668 4671",
    "sg:postcode":"L1P 1B7",
    "sg:province":"ON",
    "wof:name":"Cannan Food Fair",
    "wof:placetype":"venue"
},
  "geometry": {"coordinates":[-78.96447000000001,43.874763],"type":"Point"}
}