{
  "type": "Feature",
  "properties": {
    "addr:full":"191 Highland Rd E Kitchener ON N2M 3W1",
    "addr:housenumber":"191",
    "addr:postcode":"n2m 3w1",
    "addr:street":"Highland Rd E",
    "iso:country":"CA",
    "sg:address":"191 Highland Rd E",
    "sg:city":"Kitchener",
    "sg:classifiers":[
        {
            "category":"Home & Garden",
            "subcategory":"Furniture",
            "type":"Retail Goods"
        }
    ],
    "sg:phone":"+1 519 744 8240",
    "sg:postcode":"N2M 3W1",
    "sg:province":"ON",
    "sg:tags":[
        "futon"
    ],
    "wof:name":"Futon Fashions Inc",
    "wof:placetype":"venue"
},
  "geometry": {"coordinates":[-80.49253082280001,43.4379844666],"type":"Point"}
}