{
  "type": "Feature",
  "properties": {
    "addr:full":"552 Main St N Montague PE C0A 1R0",
    "addr:housenumber":"552",
    "addr:postcode":"c0a 1r0",
    "addr:street":"Main St N",
    "iso:country":"CA",
    "sg:address":"552 Main St N",
    "sg:city":"Montague",
    "sg:classifiers":[
        {
            "category":"Banks & Credit Unions",
            "subcategory":"Bank",
            "type":"Services"
        }
    ],
    "sg:phone":"+1 902 838 2252",
    "sg:postcode":"C0A 1R0",
    "sg:province":"PE",
    "wof:name":"Scotiabank",
    "wof:placetype":"venue"
},
  "geometry": {"coordinates":[-62.648884,46.165417],"type":"Point"}
}