{
  "type": "Feature",
  "properties": {
    "iso:country":"CA",
    "sg:address":"65 the East Mall",
    "sg:city":"Etobicoke",
    "sg:classifiers":[
        {
            "category":"Utilities",
            "subcategory":"Telephone",
            "type":"Services"
        }
    ],
    "sg:phone":"+1 416 251 2516",
    "sg:postcode":"M8Z 5W3",
    "sg:province":"ON",
    "sg:tags":[
        "company"
    ],
    "wof:name":"Jordan Marketing",
    "wof:placetype":"venue"
},
  "geometry": {"coordinates":[-79.54637146,43.6170120239],"type":"Point"}
}