{
  "type": "Feature",
  "properties": {
    "addr:full":"17 Rue Kataracui Pointe-Des-Cascades QC J0P 1M0",
    "addr:housenumber":"17",
    "addr:postcode":"j0p 1m0",
    "addr:street":"Rue Kataracui",
    "iso:country":"CA",
    "sg:address":"17 Rue Kataracui",
    "sg:city":"Pointe-Des-Cascades",
    "sg:classifiers":[
        {
            "category":"Building & Trades",
            "subcategory":"Construction",
            "type":"Services"
        }
    ],
    "sg:phone":"+1 450 455 3286",
    "sg:postcode":"J0P 1M0",
    "sg:province":"QC",
    "sg:tags":[
        "concrete",
        "contractor"
    ],
    "wof:name":"Betonnage It Inc",
    "wof:placetype":"venue"
},
  "geometry": {"coordinates":[-73.96590399999999,45.330078],"type":"Point"}
}