{
  "type": "Feature",
  "properties": {
    "iso:country":"CA",
    "sg:address":"1398 Cartwright St",
    "sg:city":"Vancouver",
    "sg:classifiers":[
        {
            "category":"Museum",
            "type":"Entertainment"
        }
    ],
    "sg:phone":"+1 604 687 3005",
    "sg:postcode":"V6H 3R8",
    "sg:province":"BC",
    "sg:tags":[
        "organization",
        "arts",
        "information"
    ],
    "wof:name":"Granville Island Cultural",
    "wof:placetype":"venue"
},
  "geometry": {"coordinates":[-123.135108948,49.2699623108],"type":"Point"}
}