{
  "type": "Feature",
  "properties": {
    "addr:full":"Mississauga ON L4W 4T6",
    "addr:postcode":"l4w 4t6",
    "iso:country":"CA",
    "sg:city":"Mississauga",
    "sg:classifiers":[
        {
            "category":"Building & Trades",
            "subcategory":"Plumbing",
            "type":"Services"
        }
    ],
    "sg:phone":"+1 905 624 4823",
    "sg:postcode":"L4W 4T6",
    "sg:province":"ON",
    "sg:tags":[
        "cooling",
        "tower"
    ],
    "wof:name":"Cooling Tower Maintenance Inc",
    "wof:placetype":"venue"
},
  "geometry": {"coordinates":[-79.608681,43.637177],"type":"Point"}
}