{
  "type": "Feature",
  "properties": {
    "addr:full":"575 Main St Woodstock ON N4S 1V3",
    "addr:housenumber":"575",
    "addr:postcode":"n4s 1v3",
    "addr:street":"Main St",
    "iso:country":"CA",
    "sg:address":"575 Main St",
    "sg:city":"Woodstock",
    "sg:classifiers":[
        {
            "category":"Autos & Motor Vehicles",
            "subcategory":"Auto Supplies",
            "type":"Retail Goods"
        }
    ],
    "sg:phone":"+1 519 537 5548",
    "sg:postcode":"N4S 1V3",
    "sg:province":"ON",
    "sg:tags":[
        "automobile",
        "parts"
    ],
    "wof:name":"Whitelaw Automotive & Ind Supl",
    "wof:placetype":"venue"
},
  "geometry": {"coordinates":[-80.75253295900001,43.1273994446],"type":"Point"}
}