{
  "type": "Feature",
  "properties": {
    "addr:full":"1354 Av Maguire Sillery QC G1T 1Z3",
    "addr:housenumber":"1354",
    "addr:postcode":"g1t 1z3",
    "addr:street":"Av Maguire",
    "iso:country":"CA",
    "sg:address":"1354 Av Maguire",
    "sg:city":"Sillery",
    "sg:classifiers":[
        {
            "category":"Shopping",
            "subcategory":"News",
            "type":"Retail Goods"
        }
    ],
    "sg:phone":"+1 418 527 2455",
    "sg:postcode":"G1T 1Z3",
    "sg:province":"QC",
    "sg:tags":[
        "magazine",
        "dealer"
    ],
    "wof:name":"Melomag",
    "wof:placetype":"venue"
},
  "geometry": {"coordinates":[-71.2512969971,46.7810020447],"type":"Point"}
}