{
  "type": "Feature",
  "properties": {
    "addr:full":"56 Goddard St North York ON M3H 5E2",
    "addr:housenumber":"56",
    "addr:postcode":"m3h 5e2",
    "addr:street":"Goddard St",
    "iso:country":"CA",
    "sg:address":"56 Goddard St",
    "sg:city":"North York",
    "sg:classifiers":[
        {
            "category":"Professional",
            "subcategory":"Engineering",
            "type":"Services"
        }
    ],
    "sg:phone":"+1 416 631 6355",
    "sg:postcode":"M3H 5E2",
    "sg:province":"ON",
    "sg:tags":[
        "engineer"
    ],
    "wof:name":"Prosum Engineering Ltd",
    "wof:placetype":"venue"
},
  "geometry": {"coordinates":[-79.449547,43.756824],"type":"Point"}
}