{
  "type": "Feature",
  "properties": {
    "addr:full":"Lethbridge AB T1J 2H1",
    "addr:postcode":"t1j 2h1",
    "iso:country":"CA",
    "sg:city":"Lethbridge",
    "sg:classifiers":[
        {
            "category":"Health Services",
            "subcategory":"Doctor",
            "type":"Services"
        }
    ],
    "sg:phone":"+1 403 320 1504",
    "sg:postcode":"T1J 2H1",
    "sg:province":"AB",
    "sg:tags":[
        "physician",
        "surgeon"
    ],
    "wof:name":"Lacidem Clinic",
    "wof:placetype":"venue"
},
  "geometry": {"coordinates":[-112.83696,49.692104],"type":"Point"}
}