{
  "type": "Feature",
  "properties": {
    "addr:full":"North Bay ON P1B 1X1",
    "addr:postcode":"p1b 1x1",
    "iso:country":"CA",
    "sg:city":"North Bay",
    "sg:classifiers":[
        {
            "category":"Professional",
            "subcategory":"Lawyer & Legal Services",
            "type":"Services"
        }
    ],
    "sg:phone":"+1 705 476 7200",
    "sg:postcode":"P1B 1X1",
    "sg:province":"ON",
    "sg:tags":[
        "attorney"
    ],
    "wof:name":"Ferguson, Danny W",
    "wof:placetype":"venue"
},
  "geometry": {"coordinates":[-79.46341700000001,46.310654],"type":"Point"}
}