{
  "type": "Feature",
  "properties": {
    "addr:full":"1221 Quartz Rd Cache Creek BC V0K 1H0",
    "addr:housenumber":"1221",
    "addr:postcode":"v0k 1h0",
    "addr:street":"Quartz Rd",
    "iso:country":"CA",
    "sg:address":"1221 Quartz Rd",
    "sg:city":"Cache Creek",
    "sg:classifiers":[
        {
            "category":"Travel",
            "subcategory":"Hotels & Motels",
            "type":"Entertainment"
        }
    ],
    "sg:phone":"+1 250 457 6522",
    "sg:postcode":"V0K 1H0",
    "sg:province":"BC",
    "wof:name":"Tumbleweed Motel",
    "wof:placetype":"venue"
},
  "geometry": {"coordinates":[-121.32297515899999,50.8110084534],"type":"Point"}
}