{
  "type": "Feature",
  "properties": {
    "addr:full":"Toronto ON M4S 2A4",
    "addr:postcode":"m4s 2a4",
    "iso:country":"CA",
    "sg:city":"Toronto",
    "sg:classifiers":[
        {
            "category":"Personal",
            "subcategory":"Beauty Salon",
            "type":"Services"
        }
    ],
    "sg:phone":"+1 416 489 2806",
    "sg:postcode":"M4S 2A4",
    "sg:province":"ON",
    "sg:tags":[
        "manicuring"
    ],
    "wof:name":"Star Nails Salon",
    "wof:placetype":"venue"
},
  "geometry": {"coordinates":[-79.39743,43.703144],"type":"Point"}
}