{
  "type": "Feature",
  "properties": {
    "addr:full":"5500 Hospital Rd Chetwynd BC V0C 1J0",
    "addr:housenumber":"5500",
    "addr:postcode":"bc v0c 1j0",
    "addr:street":"Hospital Rd",
    "iso:country":"CA",
    "sg:address":"5500 Hospital Rd",
    "sg:city":"Chetwynd",
    "sg:classifiers":[
        {
            "category":"Government",
            "subcategory":"Office",
            "type":"Public Place"
        }
    ],
    "sg:phone":"+1 250 788 2236",
    "sg:postcode":"V0C 1J0",
    "sg:province":"BC",
    "sg:tags":[
        "home",
        "convalescent",
        "nursing"
    ],
    "wof:name":"B C Chetwynd General Hospital",
    "wof:placetype":"venue"
},
  "geometry": {"coordinates":[-121.646148682,55.6960754395],"type":"Point"}
}