{
  "type": "Feature",
  "properties": {
    "addr:full":"Winnipeg MB R2R 1V4",
    "addr:postcode":"r2r 1v4",
    "iso:country":"CA",
    "sg:city":"Winnipeg",
    "sg:classifiers":[
        {
            "category":"Wholesale",
            "subcategory":"Electrical",
            "type":"Manufacturing & Wholesale Goods"
        }
    ],
    "sg:phone":"+1 204 694 2999",
    "sg:postcode":"R2R 1V4",
    "sg:province":"MB",
    "sg:tags":[
        "battery"
    ],
    "wof:name":"Interstate Battery Systems",
    "wof:placetype":"venue"
},
  "geometry": {"coordinates":[-97.2248916626,49.9350776672],"type":"Point"}
}