{
  "type": "Feature",
  "properties": {
    "addr:full":"79 Rue Commerciale O Chandler QC G0C 1K0",
    "addr:housenumber":"79",
    "addr:postcode":"g0c 1k0",
    "addr:street":"Rue Commerciale O",
    "iso:country":"CA",
    "sg:address":"79 Rue Commerciale O",
    "sg:city":"Chandler",
    "sg:classifiers":[
        {
            "category":"Banks & Credit Unions",
            "subcategory":"Bank",
            "type":"Services"
        }
    ],
    "sg:phone":"+1 418 689 2271",
    "sg:postcode":"G0C 1K0",
    "sg:province":"QC",
    "wof:name":"Banque Nationale Du Canada",
    "wof:placetype":"venue"
},
  "geometry": {"coordinates":[-64.67254638670001,48.3481788635],"type":"Point"}
}