{
  "type": "Feature",
  "properties": {
    "iso:country":"CA",
    "sg:city":"Cornwall",
    "sg:classifiers":[
        {
            "category":"Social Services",
            "type":"Services"
        }
    ],
    "sg:phone":"+1 613 938 1972",
    "sg:postcode":"K6H 1B1",
    "sg:province":"ON",
    "sg:tags":[
        "organization",
        "welfare"
    ],
    "wof:name":"Community Integration Svc",
    "wof:placetype":"venue"
},
  "geometry": {"coordinates":[-74.7163772583,45.0184516907],"type":"Point"}
}