{
  "type": "Feature",
  "properties": {
    "addr:full":"405 Victoria St Kamloops BC V2C 2A9",
    "addr:housenumber":"405",
    "addr:postcode":"bc v2c 2a9",
    "addr:street":"Victoria St",
    "iso:country":"CA",
    "sg:address":"405 Victoria St",
    "sg:city":"Kamloops",
    "sg:classifiers":[
        {
            "category":"Travel",
            "subcategory":"Hotels & Motels",
            "type":"Entertainment"
        }
    ],
    "sg:phone":"+1 250 377 8075",
    "sg:postcode":"V2C 2A9",
    "sg:province":"BC",
    "wof:name":"Plaza A Heritage Hotel",
    "wof:placetype":"venue"
},
  "geometry": {"coordinates":[-120.331604004,50.675743103],"type":"Point"}
}