{
  "type": "Feature",
  "properties": {
    "iso:country":"CA",
    "sg:city":"Richmond",
    "sg:classifiers":[
        {
            "category":"Building & Trades",
            "subcategory":"Construction",
            "type":"Services"
        }
    ],
    "sg:phone":"+1 604 278 3331",
    "sg:postcode":"V6X 2W8",
    "sg:province":"BC",
    "sg:tags":[
        "general",
        "contractor"
    ],
    "wof:name":"Peter Kiewit Sons CO Ltd",
    "wof:placetype":"venue"
},
  "geometry": {"coordinates":[-123.1073,49.187389],"type":"Point"}
}