{
  "type": "Feature",
  "properties": {
    "addr:full":"8484 Av Des Belges Montreal QC H2P 2B2",
    "addr:housenumber":"8484",
    "addr:postcode":"h2p 2b2",
    "addr:street":"Av Des Belges",
    "iso:country":"CA",
    "sg:address":"8484 Av Des Belges",
    "sg:city":"Montreal",
    "sg:classifiers":[
        {
            "category":"Building & Trades",
            "subcategory":"Construction",
            "type":"Services"
        }
    ],
    "sg:phone":"+1 514 381 8969",
    "sg:postcode":"H2P 2B2",
    "sg:province":"QC",
    "sg:tags":[
        "excavating",
        "contractor"
    ],
    "wof:name":"Vallieres J-C",
    "wof:placetype":"venue"
},
  "geometry": {"coordinates":[-73.633118,45.54697],"type":"Point"}
}