{
  "type": "Feature",
  "properties": {
    "addr:full":"890 Rue Roger-Lemelin Sainte-Julie QC J3E 2J6",
    "addr:housenumber":"890",
    "addr:postcode":"j3e 2j6",
    "addr:street":"Rue Roger-Lemelin",
    "iso:country":"CA",
    "sg:address":"890 Rue Roger-Lemelin",
    "sg:city":"Sainte-Julie",
    "sg:classifiers":[
        {
            "category":"Building & Trades",
            "subcategory":"Landscaping Services",
            "type":"Services"
        }
    ],
    "sg:phone":"+1 450 649 7816",
    "sg:postcode":"J3E 2J6",
    "sg:province":"QC",
    "sg:tags":[
        "designer",
        "landscape"
    ],
    "wof:name":"Conception Paysage",
    "wof:placetype":"venue"
},
  "geometry": {"coordinates":[-73.34618377690001,45.5873527527],"type":"Point"}
}