{
  "type": "Feature",
  "properties": {
    "addr:full":"Surrey BC V3W 9Z1",
    "addr:postcode":"v3w 9z1",
    "iso:country":"CA",
    "sg:city":"Surrey",
    "sg:classifiers":[
        {
            "category":"Food & Beverages",
            "subcategory":"Liquor & Beverages",
            "type":"Retail Goods"
        }
    ],
    "sg:phone":"+1 604 594 0388",
    "sg:postcode":"V3W 9Z1",
    "sg:province":"BC",
    "sg:tags":[
        "store"
    ],
    "wof:name":"Liquor Stores-Government",
    "wof:placetype":"venue"
},
  "geometry": {"coordinates":[-122.823348999,49.1337394714],"type":"Point"}
}