{
  "type": "Feature",
  "properties": {
    "addr:full":"Peterborough ON K9J 1B9",
    "addr:postcode":"k9j 1b9",
    "iso:country":"CA",
    "sg:city":"Peterborough",
    "sg:classifiers":[
        {
            "category":"Social Services",
            "type":"Services"
        }
    ],
    "sg:phone":"+1 705 742 5580",
    "sg:postcode":"K9J 1B9",
    "sg:province":"ON",
    "sg:tags":[
        "organization",
        "welfare"
    ],
    "wof:name":"Guided Independent Living",
    "wof:placetype":"venue"
},
  "geometry": {"coordinates":[-78.3154602051,44.2783508301],"type":"Point"}
}