{
  "type": "Feature",
  "properties": {
    "iso:country":"CA",
    "sg:address":"178 Lester Rd",
    "sg:city":"Trenton",
    "sg:classifiers":[
        {
            "category":"Organizations",
            "subcategory":"Religious Organization",
            "type":"Services"
        }
    ],
    "sg:phone":"+1 613 392 5284",
    "sg:postcode":"K8V 5P8",
    "sg:province":"ON",
    "sg:tags":[
        "church"
    ],
    "wof:name":"Orchard View Baptist Church",
    "wof:placetype":"venue"
},
  "geometry": {"coordinates":[-77.5694274902,44.1309356689],"type":"Point"}
}