{
  "type": "Feature",
  "properties": {
    "iso:country":"CA",
    "sg:address":"75 Cottingham St",
    "sg:city":"Winnipeg",
    "sg:classifiers":[
        {
            "category":"Education",
            "subcategory":"School",
            "type":"Public Place"
        }
    ],
    "sg:phone":"+1 204 338 7937",
    "sg:postcode":"R2V 3B5",
    "sg:province":"MB",
    "wof:name":"Collicutt School",
    "wof:placetype":"venue"
},
  "geometry": {"coordinates":[-97.15519,49.939354],"type":"Point"}
}