{
  "type": "Feature",
  "properties": {
    "iso:country":"CA",
    "sg:address":"330 Horton St E",
    "sg:city":"London",
    "sg:classifiers":[
        {
            "category":"Manufacturing",
            "subcategory":"Metals",
            "type":"Manufacturing & Wholesale Goods"
        }
    ],
    "sg:phone":"+1 519 438 1133",
    "sg:postcode":"N6B 1L4",
    "sg:province":"ON",
    "sg:tags":[
        "plating"
    ],
    "wof:name":"Antique Metal Finishing CO",
    "wof:placetype":"venue"
},
  "geometry": {"coordinates":[-81.2409439087,42.9808387756],"type":"Point"}
}