{
  "type": "Feature",
  "properties": {
    "iso:country":"CA",
    "sg:address":"7025 Tecumseh Rd E",
    "sg:city":"Windsor",
    "sg:classifiers":[
        {
            "category":"Organizations",
            "subcategory":"Religious Organization",
            "type":"Services"
        }
    ],
    "sg:phone":"+1 519 687 3118",
    "sg:postcode":"N8T 3K7",
    "sg:province":"ON",
    "sg:tags":[
        "church"
    ],
    "wof:name":"Annunciation Church",
    "wof:placetype":"venue"
},
  "geometry": {"coordinates":[-82.94249725340001,42.3120651245],"type":"Point"}
}