{
  "type": "Feature",
  "properties": {
    "addr:full":"Abbotsford BC V2T 4W1",
    "addr:postcode":"v2t 4w1",
    "iso:country":"CA",
    "sg:city":"Abbotsford",
    "sg:classifiers":[
        {
            "category":"Retail",
            "subcategory":"Laundry & Dry Cleaning",
            "type":"Services"
        }
    ],
    "sg:phone":"+1 604 850 7077",
    "sg:postcode":"V2T 4W1",
    "sg:province":"BC",
    "sg:tags":[
        "cleaners"
    ],
    "wof:name":"Save-On Cleaners",
    "wof:placetype":"venue"
},
  "geometry": {"coordinates":[-122.315056,49.05106],"type":"Point"}
}