{
  "type": "Feature",
  "properties": {
    "addr:full":"147 Broadway W Vancouver BC V5Y 1P4",
    "addr:housenumber":"147",
    "addr:postcode":"v5y 1p4",
    "addr:street":"Broadway W",
    "iso:country":"CA",
    "sg:address":"147 Broadway W",
    "sg:city":"Vancouver",
    "sg:classifiers":[
        {
            "category":"Shopping",
            "subcategory":"Bicycles & Sporting Goods",
            "type":"Retail Goods"
        }
    ],
    "sg:phone":"+1 604 874 1117",
    "sg:postcode":"V5Y 1P4",
    "sg:province":"BC",
    "wof:name":"A J Brooks Outdoor Outfitters",
    "wof:placetype":"venue"
},
  "geometry": {"coordinates":[-123.108085632,49.2632217407],"type":"Point"}
}