{
  "type": "Feature",
  "properties": {
    "addr:full":"Hwy 15 W Outlook SK S0L 2N0",
    "addr:postcode":"s0l 2n0",
    "addr:street":"Hwy 15 W Outlook",
    "iso:country":"CA",
    "sg:address":"Hwy 15 W",
    "sg:city":"Outlook",
    "sg:classifiers":[
        {
            "category":"Wholesale",
            "subcategory":"Machinery & Supplies",
            "type":"Manufacturing & Wholesale Goods"
        }
    ],
    "sg:phone":"+1 306 867 8328",
    "sg:postcode":"S0L 2N0",
    "sg:province":"SK",
    "sg:tags":[
        "engine",
        "agricultural",
        "implement"
    ],
    "wof:name":"Ofe Ag Sales Ltd",
    "wof:placetype":"venue"
},
  "geometry": {"coordinates":[-107.058624268,51.4783706665],"type":"Point"}
}