{
  "type": "Feature",
  "properties": {
    "addr:full":"1886 Rue Ontario E Montreal QC H2K 1T8",
    "addr:housenumber":"1886",
    "addr:postcode":"h2k 1t8",
    "addr:street":"Rue Ontario E",
    "iso:country":"CA",
    "sg:address":"1886 Rue Ontario E",
    "sg:city":"Montreal",
    "sg:classifiers":[
        {
            "category":"Restaurant",
            "type":"Food & Drink"
        }
    ],
    "sg:phone":"+1 514 522 1313",
    "sg:postcode":"H2K 1T8",
    "sg:province":"QC",
    "wof:name":"Restaurant Congo Leo",
    "wof:placetype":"venue"
},
  "geometry": {"coordinates":[-73.5584106445,45.5267105103],"type":"Point"}
}