{
  "type": "Feature",
  "properties": {
    "addr:full":"75 Spruce St Vermilion Bay ON P0V 2V0",
    "addr:housenumber":"75",
    "addr:postcode":"p0v 2v0",
    "addr:street":"Spruce St",
    "iso:country":"CA",
    "sg:address":"75 Spruce St",
    "sg:city":"Vermilion Bay",
    "sg:classifiers":[
        {
            "category":"Government",
            "subcategory":"Office",
            "type":"Public Place"
        }
    ],
    "sg:phone":"+1 807 227 2633",
    "sg:postcode":"P0V 2V0",
    "sg:province":"ON",
    "sg:tags":[
        "municipality"
    ],
    "wof:name":"Machin Municipal Offices",
    "wof:placetype":"venue"
},
  "geometry": {"coordinates":[-93.391357,49.855026],"type":"Point"}
}