{
  "type": "Feature",
  "properties": {
    "addr:full":"1825 Dundas St E # 4 Mississauga ON L4X 2X1",
    "addr:housenumber":"1825",
    "addr:postcode":"l4x 2x1",
    "addr:street":"Dundas St E # 4",
    "iso:country":"CA",
    "sg:address":"1825 Dundas St E # 4",
    "sg:city":"Mississauga",
    "sg:classifiers":[
        {
            "category":"Home & Garden",
            "subcategory":"Furniture",
            "type":"Retail Goods"
        }
    ],
    "sg:phone":"+1 905 629 7060",
    "sg:postcode":"L4X 2X1",
    "sg:province":"ON",
    "wof:name":"Arrow Furniture Mart",
    "wof:placetype":"venue"
},
  "geometry": {"coordinates":[-79.5734786987,43.6191482544],"type":"Point"}
}