{
  "type": "Feature",
  "properties": {
    "addr:full":"141 153 Rte Saint-Tite QC G0X 3H0",
    "addr:housenumber":"153",
    "addr:postcode":"g0x 3h0",
    "addr:street":"Rte",
    "iso:country":"CA",
    "sg:address":"141 153 Rte",
    "sg:city":"Saint-Tite",
    "sg:classifiers":[
        {
            "category":"Organizations",
            "subcategory":"Religious Organization",
            "type":"Services"
        }
    ],
    "sg:phone":"+1 418 365 3035",
    "sg:postcode":"G0X 3H0",
    "sg:province":"QC",
    "wof:name":"Kingdom Hall-Jehovah Witness'",
    "wof:placetype":"venue"
},
  "geometry": {"coordinates":[-72.58931699999999,46.712044],"type":"Point"}
}