{
  "type": "Feature",
  "properties": {
    "addr:full":"Iron Mine Rd Van Anda BC V0N 3K0",
    "addr:postcode":"v0n 3k0",
    "addr:street":"Iron Mine Rd",
    "iso:country":"CA",
    "sg:address":"Iron Mine Rd",
    "sg:city":"Van Anda",
    "sg:classifiers":[
        {
            "category":"Mining & Drilling",
            "type":"Manufacturing & Wholesale Goods"
        }
    ],
    "sg:phone":"+1 604 486 0486",
    "sg:postcode":"V0N 3K0",
    "sg:province":"BC",
    "sg:tags":[
        "limestone"
    ],
    "wof:name":"Texada Quarrying Ltd",
    "wof:placetype":"venue"
},
  "geometry": {"coordinates":[-124.554779053,49.7563591003],"type":"Point"}
}