{
  "type": "Feature",
  "properties": {
    "iso:country":"CA",
    "sg:address":"7 Queen St W",
    "sg:city":"Cambridge",
    "sg:classifiers":[
        {
            "category":"Restaurant",
            "type":"Food & Drink"
        }
    ],
    "sg:phone":"+1 519 658 9562",
    "sg:postcode":"N3C 1G2",
    "sg:province":"ON",
    "sg:tags":[
        "bars"
    ],
    "wof:name":"Ernie's Roadhouse",
    "wof:placetype":"venue"
},
  "geometry": {"coordinates":[-80.3114318848,43.4311332703],"type":"Point"}
}