{
  "type": "Feature",
  "properties": {
    "addr:full":"6701 Davand Dr Mississauga ON L5T 2R2",
    "addr:housenumber":"6701",
    "addr:postcode":"l5t 2r2",
    "addr:street":"Davand Dr",
    "iso:country":"CA",
    "sg:address":"6701 Davand Dr",
    "sg:city":"Mississauga",
    "sg:classifiers":[
        {
            "category":"Freight",
            "type":"Transportation"
        }
    ],
    "sg:phone":"+1 905 564 1495",
    "sg:postcode":"L5T 2R2",
    "sg:province":"ON",
    "sg:tags":[
        "trucking"
    ],
    "wof:name":"Roadfast",
    "wof:placetype":"venue"
},
  "geometry": {"coordinates":[-79.6680679321,43.6683769226],"type":"Point"}
}