{
  "type": "Feature",
  "properties": {
    "addr:full":"1709 Renner Rd Williams Lake BC V2G 3B4",
    "addr:housenumber":"1709",
    "addr:postcode":"v2g 3b4",
    "addr:street":"Renner Rd",
    "iso:country":"CA",
    "sg:address":"1709 Renner Rd",
    "sg:city":"Williams Lake",
    "sg:classifiers":[
        {
            "category":"Building & Trades",
            "subcategory":"Construction",
            "type":"Services"
        }
    ],
    "sg:phone":"+1 250 392 6683",
    "sg:postcode":"V2G 3B4",
    "sg:province":"BC",
    "sg:tags":[
        "painter"
    ],
    "wof:name":"Leons Painting",
    "wof:placetype":"venue"
},
  "geometry": {"coordinates":[-122.098983765,52.1097946167],"type":"Point"}
}