{
  "type": "Feature",
  "properties": {
    "addr:full":"728 52nd Ave W Vancouver BC V6P 1G4",
    "addr:housenumber":"728",
    "addr:postcode":"v6p 1g4",
    "addr:street":"52Nd Ave W",
    "iso:country":"CA",
    "sg:address":"728 52nd Ave W",
    "sg:city":"Vancouver",
    "sg:classifiers":[
        {
            "category":"Building & Trades",
            "subcategory":"Electrical",
            "type":"Services"
        }
    ],
    "sg:phone":"+1 604 327 3995",
    "sg:postcode":"V6P 1G4",
    "sg:province":"BC",
    "sg:tags":[
        "electric",
        "contractor"
    ],
    "wof:name":"Fraser Electric CO Ltd",
    "wof:placetype":"venue"
},
  "geometry": {"coordinates":[-123.12144470200001,49.2233352661],"type":"Point"}
}