{
  "type": "Feature",
  "properties": {
    "iso:country":"CA",
    "sg:address":"8356 112 St",
    "sg:city":"Delta",
    "sg:classifiers":[
        {
            "category":"Restaurant",
            "type":"Food & Drink"
        }
    ],
    "sg:phone":"+1 604 572 7588",
    "sg:postcode":"V4C 7A2",
    "sg:province":"BC",
    "wof:name":"Minori Japanese Restaurant",
    "wof:placetype":"venue"
},
  "geometry": {"coordinates":[-122.91217804,49.1552848816],"type":"Point"}
}