{
  "type": "Feature",
  "properties": {
    "addr:full":"Kelowna BC V1X 2P7",
    "addr:postcode":"v1x 2p7",
    "iso:country":"CA",
    "sg:city":"Kelowna",
    "sg:classifiers":[
        {
            "category":"Shopping",
            "subcategory":"Clothing, Apparel, & Fashions",
            "type":"Retail Goods"
        }
    ],
    "sg:phone":"+1 250 491 4921",
    "sg:postcode":"V1X 2P7",
    "sg:province":"BC",
    "sg:tags":[
        "hair",
        "salon",
        "beauty"
    ],
    "wof:name":"Grace Hair Studio",
    "wof:placetype":"venue"
},
  "geometry": {"coordinates":[-119.405441,49.901314],"type":"Point"}
}