{
  "type": "Feature",
  "properties": {
    "addr:full":"59 Rue Des Sables Sorel-Tracy QC J3P 5E7",
    "addr:housenumber":"59",
    "addr:postcode":"j3p 5e7",
    "addr:street":"Rue Des Sables",
    "iso:country":"CA",
    "sg:address":"59 Rue Des Sables",
    "sg:city":"Sorel-Tracy",
    "sg:classifiers":[
        {
            "category":"Personal",
            "type":"Services"
        }
    ],
    "sg:phone":"+1 450 742 8467",
    "sg:postcode":"J3P 5E7",
    "sg:province":"QC",
    "sg:tags":[
        "therapist",
        "massage"
    ],
    "wof:name":"Desaulniers, Louise",
    "wof:placetype":"venue"
},
  "geometry": {"coordinates":[-73.11792,46.015156],"type":"Point"}
}