{
  "type": "Feature",
  "properties": {
    "addr:full":"Richmond Hill ON L4B 1L6",
    "addr:postcode":"l4b 1l6",
    "iso:country":"CA",
    "sg:city":"Richmond Hill",
    "sg:classifiers":[
        {
            "category":"Professional",
            "subcategory":"Management & Consulting",
            "type":"Services"
        }
    ],
    "sg:phone":"+1 905 882 8871",
    "sg:postcode":"L4B 1L6",
    "sg:province":"ON",
    "sg:tags":[
        "development",
        "image",
        "corporate"
    ],
    "wof:name":"Impeccable Image Intl",
    "wof:placetype":"venue"
},
  "geometry": {"coordinates":[-79.3877487183,43.8472633362],"type":"Point"}
}