{
  "type": "Feature",
  "properties": {
    "addr:full":"3747 Rue Laval Lac-Megantic QC G6B 1A5",
    "addr:housenumber":"3747",
    "addr:postcode":"g6b 1a5",
    "addr:street":"Rue Laval Lac-Megantic",
    "iso:country":"CA",
    "sg:address":"3747 Rue Laval",
    "sg:city":"Lac-Megantic",
    "sg:classifiers":[
        {
            "category":"Shopping",
            "subcategory":"Computers & Home Electronics",
            "type":"Retail Goods"
        }
    ],
    "sg:phone":"+1 819 583 0353",
    "sg:postcode":"G6B 1A5",
    "sg:province":"QC",
    "sg:tags":[
        "equipment",
        "electronic",
        "telephone",
        "cellular"
    ],
    "wof:name":"Netvert",
    "wof:placetype":"venue"
},
  "geometry": {"coordinates":[-70.90316009519999,45.5880355835],"type":"Point"}
}