{
  "type": "Feature",
  "properties": {
    "addr:full":"80 Worcester Rd Etobicoke ON M9W 1K7",
    "addr:housenumber":"80",
    "addr:postcode":"m9w 1k7",
    "addr:street":"Worcester Rd",
    "iso:country":"CA",
    "sg:address":"80 Worcester Rd",
    "sg:city":"Etobicoke",
    "sg:classifiers":[
        {
            "category":"Wholesale",
            "subcategory":"Groceries",
            "type":"Manufacturing & Wholesale Goods"
        }
    ],
    "sg:phone":"+1 416 663 3502",
    "sg:postcode":"M9W 1K7",
    "sg:province":"ON",
    "sg:tags":[
        "food",
        "grocer",
        "broker"
    ],
    "wof:name":"Millway Frozen Foods",
    "wof:placetype":"venue"
},
  "geometry": {"coordinates":[-79.6026306152,43.6938400269],"type":"Point"}
}