{
  "type": "Feature",
  "properties": {
    "addr:full":"Red Deer AB T4N 3P7",
    "addr:postcode":"t4n 3p7",
    "iso:country":"CA",
    "sg:city":"Red Deer",
    "sg:classifiers":[
        {
            "category":"Shopping",
            "subcategory":"Used Merchandise",
            "type":"Retail Goods"
        }
    ],
    "sg:phone":"+1 403 340 0072",
    "sg:postcode":"T4N 3P7",
    "sg:province":"AB",
    "sg:tags":[
        "book",
        "rare",
        "dealer"
    ],
    "wof:name":"Nearly New Books",
    "wof:placetype":"venue"
},
  "geometry": {"coordinates":[-113.805137634,52.2701225281],"type":"Point"}
}