{
  "type": "Feature",
  "properties": {
    "addr:full":"851 Division Rd Windsor ON N8W 5R9",
    "addr:housenumber":"851",
    "addr:postcode":"n8w 5r9",
    "addr:street":"Division Rd",
    "iso:country":"CA",
    "sg:address":"851 Division Rd",
    "sg:city":"Windsor",
    "sg:classifiers":[
        {
            "category":"Shopping",
            "type":"Retail Goods"
        }
    ],
    "sg:phone":"+1 519 250 7627",
    "sg:postcode":"N8W 5R9",
    "sg:province":"ON",
    "sg:tags":[
        "spa",
        "hot",
        "tub"
    ],
    "wof:name":"D M Industries Canada Ltd",
    "wof:placetype":"venue"
},
  "geometry": {"coordinates":[-82.9962310791,42.2675895691],"type":"Point"}
}