{
  "type": "Feature",
  "properties": {
    "addr:full":"8421 Main St Vancouver BC V5X 3M3",
    "addr:housenumber":"8421",
    "addr:postcode":"v5x 3m3",
    "addr:street":"Main St",
    "iso:country":"CA",
    "sg:address":"8421 Main St",
    "sg:city":"Vancouver",
    "sg:classifiers":[
        {
            "category":"Building & Trades",
            "subcategory":"Plumbing",
            "type":"Services"
        }
    ],
    "sg:phone":"+1 604 321 1020",
    "sg:postcode":"V5X 3M3",
    "sg:province":"BC",
    "sg:tags":[
        "air",
        "conditioning",
        "material",
        "system",
        "contractor"
    ],
    "wof:name":"Thermoflo Technologies Ltd",
    "wof:placetype":"venue"
},
  "geometry": {"coordinates":[-123.10253906200001,49.2085800171],"type":"Point"}
}