{
  "type": "Feature",
  "properties": {
    "addr:full":"Charlesbourg QC G1H 5L4",
    "addr:postcode":"g1h 5l4",
    "iso:country":"CA",
    "sg:city":"Charlesbourg",
    "sg:classifiers":[
        {
            "category":"Health Services",
            "subcategory":"Medical Lab",
            "type":"Services"
        }
    ],
    "sg:phone":"+1 418 623 5845",
    "sg:postcode":"G1H 5L4",
    "sg:province":"QC",
    "wof:name":"Clinique DE Denturologie",
    "wof:placetype":"venue"
},
  "geometry": {"coordinates":[-71.25367,46.84079],"type":"Point"}
}