{
  "type": "Feature",
  "properties": {
    "iso:country":"CA",
    "sg:address":"9801 Hardin St",
    "sg:city":"Fort Mcmurray",
    "sg:classifiers":[
        {
            "category":"Shopping",
            "subcategory":"Department Store",
            "type":"Retail Goods"
        }
    ],
    "sg:phone":"+1 780 743 5510",
    "sg:postcode":"T9H 3G6",
    "sg:province":"AB",
    "wof:name":"Zellers",
    "wof:placetype":"venue"
},
  "geometry": {"coordinates":[-111.380302429,56.7271881104],"type":"Point"}
}