{
  "type": "Feature",
  "properties": {
    "addr:full":"172 White Pine Dr South River ON P0A 1X0",
    "addr:housenumber":"172",
    "addr:postcode":"p0a 1x0",
    "addr:street":"White Pine Dr",
    "iso:country":"CA",
    "sg:address":"172 White Pine Dr",
    "sg:city":"South River",
    "sg:classifiers":[
        {
            "category":"Autos & Motor Vehicles",
            "subcategory":"Boat Sales",
            "type":"Retail Goods"
        }
    ],
    "sg:phone":"+1 705 386 1559",
    "sg:postcode":"P0A 1X0",
    "sg:province":"ON",
    "sg:tags":[
        "outboard"
    ],
    "wof:name":"Thunder Bridge Small Engines",
    "wof:placetype":"venue"
},
  "geometry": {"coordinates":[-79.3818359375,45.8405189514],"type":"Point"}
}