{
  "type": "Feature",
  "properties": {
    "addr:full":"13036 Coulthard Rd Surrey BC V3X 3E6",
    "addr:housenumber":"13036",
    "addr:postcode":"v3x 3e6",
    "addr:street":"Coulthard Rd",
    "iso:country":"CA",
    "sg:address":"13036 Coulthard Rd",
    "sg:city":"Surrey",
    "sg:classifiers":[
        {
            "category":"Professional",
            "subcategory":"Engineering",
            "type":"Services"
        }
    ],
    "sg:phone":"+1 604 572 3562",
    "sg:postcode":"V3X 3E6",
    "sg:province":"BC",
    "sg:tags":[
        "engineer"
    ],
    "wof:name":"Villholth Jensen & Assoc",
    "wof:placetype":"venue"
},
  "geometry": {"coordinates":[-122.86148799999999,49.101814],"type":"Point"}
}