{
  "type": "Feature",
  "properties": {
    "addr:full":"4363 Rue Wellington Verdun QC H4G 1W3",
    "addr:housenumber":"4363",
    "addr:postcode":"h4g 1w3",
    "addr:street":"Rue Wellington",
    "iso:country":"CA",
    "sg:address":"4363 Rue Wellington",
    "sg:city":"Verdun",
    "sg:classifiers":[
        {
            "category":"Food & Beverages",
            "subcategory":"Groceries & Convenience Stores",
            "type":"Retail Goods"
        }
    ],
    "sg:phone":"+1 514 767 1241",
    "sg:postcode":"H4G 1W3",
    "sg:province":"QC",
    "sg:tags":[
        "grocer"
    ],
    "wof:name":"Marche Onkea",
    "wof:placetype":"venue"
},
  "geometry": {"coordinates":[-73.567459,45.460453],"type":"Point"}
}