{
  "type": "Feature",
  "properties": {
    "addr:full":"Etobicoke ON M9P 3B6",
    "addr:postcode":"m9p 3b6",
    "iso:country":"CA",
    "sg:city":"Etobicoke",
    "sg:classifiers":[
        {
            "category":"Retail",
            "subcategory":"Animal Services",
            "type":"Services"
        }
    ],
    "sg:phone":"+1 416 242 2501",
    "sg:postcode":"M9P 3B6",
    "sg:province":"ON",
    "sg:tags":[
        "pet",
        "grooming",
        "washing"
    ],
    "wof:name":"Dog Wash",
    "wof:placetype":"venue"
},
  "geometry": {"coordinates":[-79.5305633545,43.6909103394],"type":"Point"}
}