{
  "type": "Feature",
  "properties": {
    "addr:full":"870 Brookbury Rd Bury QC J0B 1J0",
    "addr:housenumber":"870",
    "addr:postcode":"j0b 1j0",
    "addr:street":"Brookbury Rd",
    "iso:country":"CA",
    "sg:address":"870 Brookbury Rd",
    "sg:city":"Bury",
    "sg:classifiers":[
        {
            "category":"Retail",
            "subcategory":"Auto Repair",
            "type":"Services"
        }
    ],
    "sg:phone":"+1 819 884 5444",
    "sg:postcode":"J0B 1J0",
    "sg:province":"QC",
    "sg:tags":[
        "repairing",
        "automobile"
    ],
    "wof:name":"Hilltop Garage",
    "wof:placetype":"venue"
},
  "geometry": {"coordinates":[-71.50945299999999,45.550194],"type":"Point"}
}