{
  "type": "Feature",
  "properties": {
    "addr:full":"425 Water St Peterborough ON K9H 3L9",
    "addr:housenumber":"425",
    "addr:postcode":"k9h 3l9",
    "addr:street":"Water St",
    "iso:country":"CA",
    "sg:address":"425 Water St",
    "sg:city":"Peterborough",
    "sg:classifiers":[
        {
            "category":"Professional",
            "subcategory":"Accounting & Tax Preparation",
            "type":"Services"
        }
    ],
    "sg:phone":"+1 705 745 4657",
    "sg:postcode":"K9H 3L9",
    "sg:province":"ON",
    "sg:tags":[
        "accountant"
    ],
    "wof:name":"Clark, Diane CA",
    "wof:placetype":"venue"
},
  "geometry": {"coordinates":[-78.3191833496,44.3066864014],"type":"Point"}
}