{
  "type": "Feature",
  "properties": {
    "addr:full":"226 22 St N Lethbridge AB T1H 3R7",
    "addr:housenumber":"22",
    "addr:postcode":"t1h 3r7",
    "addr:street":"226;St N",
    "iso:country":"CA",
    "sg:address":"226 22 St N",
    "sg:city":"Lethbridge",
    "sg:classifiers":[
        {
            "category":"Building & Trades",
            "subcategory":"Electrical",
            "type":"Services"
        }
    ],
    "sg:phone":"+1 403 485 6344",
    "sg:postcode":"T1H 3R7",
    "sg:province":"AB",
    "sg:tags":[
        "electric",
        "contractor"
    ],
    "wof:name":"Dorren Electric Ltd",
    "wof:placetype":"venue"
},
  "geometry": {"coordinates":[-112.810135,49.701221],"type":"Point"}
}