{
  "type": "Feature",
  "properties": {
    "iso:country":"CA",
    "sg:address":"Pine",
    "sg:city":"Milford Bay",
    "sg:classifiers":[
        {
            "category":"Government",
            "subcategory":"Office",
            "type":"Public Place"
        }
    ],
    "sg:phone":"+1 705 645 5204",
    "sg:postcode":"P0B 1E0",
    "sg:province":"ON",
    "sg:tags":[
        "village"
    ],
    "wof:name":"Ontario Property Assessment",
    "wof:placetype":"venue"
},
  "geometry": {"coordinates":[-79.4779205322,45.0757484436],"type":"Point"}
}