{
  "type": "Feature",
  "properties": {
    "addr:full":"326 Rue Principale Saint-Leonard-DE-Portneuf QC G0A 4A0",
    "addr:housenumber":"326",
    "addr:postcode":"g0a 4a0",
    "addr:street":"Rue Principale",
    "iso:country":"CA",
    "sg:address":"326 Rue Principale",
    "sg:city":"Saint-Leonard-DE-Portneuf",
    "sg:classifiers":[
        {
            "category":"Retail",
            "subcategory":"Auto Repair",
            "type":"Services"
        }
    ],
    "sg:phone":"+1 418 337 7228",
    "sg:postcode":"G0A 4A0",
    "sg:province":"QC",
    "sg:tags":[
        "repairing",
        "automobile"
    ],
    "wof:name":"Garage L Verreault Inc",
    "wof:placetype":"venue"
},
  "geometry": {"coordinates":[-71.896835,46.882607],"type":"Point"}
}