{
  "type": "Feature",
  "properties": {
    "addr:full":"Ste-Marguerite-DE-Dorchester QC G0S 2X0",
    "addr:postcode":"g0s 2x0",
    "iso:country":"CA",
    "sg:city":"Ste-Marguerite-DE-Dorchester",
    "sg:classifiers":[
        {
            "category":"Building & Trades",
            "subcategory":"Construction",
            "type":"Services"
        }
    ],
    "sg:phone":"+1 418 935 7227",
    "sg:postcode":"G0S 2X0",
    "sg:province":"QC",
    "sg:tags":[
        "builder",
        "stair"
    ],
    "wof:name":"Tournage, M G",
    "wof:placetype":"venue"
},
  "geometry": {"coordinates":[-70.93798099999999,46.512478],"type":"Point"}
}