{
  "type": "Feature",
  "properties": {
    "addr:full":"Saint-Charles-Borromee QC J6E 4N4",
    "addr:postcode":"j6e 4n4",
    "iso:country":"CA",
    "sg:city":"Saint-Charles-Borromee",
    "sg:classifiers":[
        {
            "category":"Health Services",
            "subcategory":"Doctor",
            "type":"Services"
        }
    ],
    "sg:phone":"+1 450 755 2040",
    "sg:postcode":"J6E 4N4",
    "sg:province":"QC",
    "sg:tags":[
        "clinic"
    ],
    "wof:name":"Clinique DE Pediatrie",
    "wof:placetype":"venue"
},
  "geometry": {"coordinates":[-73.44934082029999,46.0419197083],"type":"Point"}
}