{
  "type": "Feature",
  "properties": {
    "addr:full":"Delta BC V4C 6P6",
    "addr:postcode":"v4c 6p6",
    "iso:country":"CA",
    "sg:city":"Delta",
    "sg:classifiers":[
        {
            "category":"Government",
            "subcategory":"Office",
            "type":"Public Place"
        }
    ],
    "sg:phone":"+1 604 501 3257",
    "sg:postcode":"V4C 6P6",
    "sg:province":"BC",
    "wof:name":"B C Human Resources Ministry",
    "wof:placetype":"venue"
},
  "geometry": {"coordinates":[-122.890563965,49.1478233337],"type":"Point"}
}