{
  "type": "Feature",
  "properties": {
    "iso:country":"CA",
    "sg:address":"1620 Blackwell Rd",
    "sg:city":"Sarnia",
    "sg:classifiers":[
        {
            "category":"Wholesale",
            "subcategory":"Scrap",
            "type":"Manufacturing & Wholesale Goods"
        }
    ],
    "sg:phone":"+1 519 542 4712",
    "sg:postcode":"N7T 7H4",
    "sg:province":"ON",
    "sg:tags":[
        "waste"
    ],
    "wof:name":"Inter Recycling Inc",
    "wof:placetype":"venue"
},
  "geometry": {"coordinates":[-82.332253,43.016647],"type":"Point"}
}