{
  "type": "Feature",
  "properties": {
    "addr:full":"291 Chisholm Ave East York ON M4C 4W5",
    "addr:housenumber":"291",
    "addr:postcode":"m4c 4w5",
    "addr:street":"Chisholm Ave",
    "iso:country":"CA",
    "sg:address":"291 Chisholm Ave",
    "sg:city":"East York",
    "sg:classifiers":[
        {
            "category":"Social Services",
            "type":"Services"
        }
    ],
    "sg:phone":"+1 416 699 5600",
    "sg:postcode":"M4C 4W5",
    "sg:province":"ON",
    "sg:tags":[
        "organization",
        "welfare"
    ],
    "wof:name":"Oakdale Child & Family Svc Ltd",
    "wof:placetype":"venue"
},
  "geometry": {"coordinates":[-79.3062362671,43.6958770752],"type":"Point"}
}