{
  "type": "Feature",
  "properties": {
    "addr:full":"3131 32 Ave NE Calgary AB T1Y 6J1",
    "addr:housenumber":"3131",
    "addr:postcode":"t1y 6j1",
    "addr:street":"32 Ave Ne",
    "iso:country":"CA",
    "sg:address":"3131 32 Ave NE",
    "sg:city":"Calgary",
    "sg:classifiers":[
        {
            "category":"Autos & Motor Vehicles",
            "subcategory":"Automobile Sales",
            "type":"Retail Goods"
        }
    ],
    "sg:phone":"+1 403 291 2626",
    "sg:postcode":"T1Y 6J1",
    "sg:province":"AB",
    "sg:tags":[
        "car",
        "dealer"
    ],
    "wof:name":"Sunridge Nissan Ltd",
    "wof:placetype":"venue"
},
  "geometry": {"coordinates":[-113.98979187,51.0813026428],"type":"Point"}
}