{
  "type": "Feature",
  "properties": {
    "addr:full":"Calgary AB T2R 0V8",
    "addr:postcode":"t2r 0v8",
    "iso:country":"CA",
    "sg:city":"Calgary",
    "sg:classifiers":[
        {
            "category":"Professional",
            "subcategory":"Computer Services",
            "type":"Services"
        }
    ],
    "sg:phone":"+1 403 262 8404",
    "sg:postcode":"T2R 0V8",
    "sg:province":"AB",
    "sg:tags":[
        "website",
        "design"
    ],
    "wof:name":"Baja Technologies Intl Corp",
    "wof:placetype":"venue"
},
  "geometry": {"coordinates":[-114.06576538100001,51.0394630432],"type":"Point"}
}