{
  "type": "Feature",
  "properties": {
    "addr:full":"Trois-Rivieres QC G8Y 4N5",
    "addr:postcode":"g8y 4n5",
    "iso:country":"CA",
    "sg:city":"Trois-Rivieres",
    "sg:classifiers":[
        {
            "category":"Professional",
            "subcategory":"Art Services",
            "type":"Services"
        }
    ],
    "sg:phone":"+1 819 375 7322",
    "sg:postcode":"G8Y 4N5",
    "sg:province":"QC",
    "sg:tags":[
        "graphic",
        "designer"
    ],
    "wof:name":"Creations Oceanes",
    "wof:placetype":"venue"
},
  "geometry": {"coordinates":[-72.5996017456,46.3594894409],"type":"Point"}
}