{
  "type": "Feature",
  "properties": {
    "iso:country":"CA",
    "sg:address":"2400 Arbutus Rd",
    "sg:city":"Victoria",
    "sg:classifiers":[
        {
            "category":"Health Services",
            "subcategory":"Hospital",
            "type":"Services"
        }
    ],
    "sg:phone":"+1 250 477 1826",
    "sg:postcode":"V8N 1V7",
    "sg:province":"BC",
    "wof:name":"Queen Alexandra Ctr-Child Hlth",
    "wof:placetype":"venue"
},
  "geometry": {"coordinates":[-123.363464355,48.4158973694],"type":"Point"}
}