{
  "type": "Feature",
  "properties": {
    "addr:full":"2345 Yonge St Toronto ON M4P 2E5",
    "addr:housenumber":"2345",
    "addr:postcode":"m4p 2e5",
    "addr:street":"Yonge St",
    "iso:country":"CA",
    "sg:address":"2345 Yonge St",
    "sg:city":"Toronto",
    "sg:classifiers":[
        {
            "category":"Shopping",
            "subcategory":"Pharmacy",
            "type":"Retail Goods"
        }
    ],
    "sg:phone":"+1 416 487 5411",
    "sg:postcode":"M4P 2E5",
    "sg:province":"ON",
    "wof:name":"Shoppers Drug Mart",
    "wof:placetype":"venue"
},
  "geometry": {"coordinates":[-79.398552,43.708679],"type":"Point"}
}