{
  "type": "Feature",
  "properties": {
    "addr:full":"17672 57 Ave Surrey BC V3S 1H2",
    "addr:housenumber":"17672",
    "addr:postcode":"v3s 1h2",
    "addr:street":"57 Ave",
    "iso:country":"CA",
    "sg:address":"17672 57 Ave",
    "sg:city":"Surrey",
    "sg:classifiers":[
        {
            "category":"Education",
            "subcategory":"Dance Studio",
            "type":"Public Place"
        }
    ],
    "sg:phone":"+1 604 574 1107",
    "sg:postcode":"V3S 1H2",
    "sg:province":"BC",
    "sg:tags":[
        "instruction",
        "dancing"
    ],
    "wof:name":"Querin Dance Academy",
    "wof:placetype":"venue"
},
  "geometry": {"coordinates":[-122.73283386200001,49.1059951782],"type":"Point"}
}