{
  "type": "Feature",
  "properties": {
    "iso:country":"CA",
    "sg:address":"652 Bloor St",
    "sg:city":"Mississauga",
    "sg:classifiers":[
        {
            "category":"Insurance",
            "subcategory":"Insurance Agent",
            "type":"Services"
        }
    ],
    "sg:phone":"+1 905 279 6950",
    "sg:postcode":"L5A 3V9",
    "sg:province":"ON",
    "sg:tags":[
        "glass"
    ],
    "wof:name":"Aetna Glass & Mirror",
    "wof:placetype":"venue"
},
  "geometry": {"coordinates":[-79.6105422974,43.600189209],"type":"Point"}
}