{
  "type": "Feature",
  "properties": {
    "addr:full":"33411 King Rd Abbotsford BC V2S 1A1",
    "addr:housenumber":"33411",
    "addr:postcode":"v2s 1a1",
    "addr:street":"King Rd",
    "iso:country":"CA",
    "sg:address":"33411 King Rd",
    "sg:city":"Abbotsford",
    "sg:classifiers":[
        {
            "category":"Personal",
            "subcategory":"Beauty Salon",
            "type":"Services"
        }
    ],
    "sg:phone":"+1 604 852 0312",
    "sg:postcode":"V2S 1A1",
    "sg:province":"BC",
    "wof:name":"Cheryl's Cuts N Curls",
    "wof:placetype":"venue"
},
  "geometry": {"coordinates":[-122.298751831,49.0312728882],"type":"Point"}
}