{
  "type": "Feature",
  "properties": {
    "addr:full":"1500 Av Saint-Joseph Plessisville QC G6L 2H6",
    "addr:housenumber":"1500",
    "addr:postcode":"g6l 2h6",
    "addr:street":"Av Saint-Joseph",
    "iso:country":"CA",
    "sg:address":"1500 Av Saint-Joseph",
    "sg:city":"Plessisville",
    "sg:classifiers":[
        {
            "category":"Building & Trades",
            "subcategory":"Construction",
            "type":"Services"
        }
    ],
    "sg:phone":"+1 819 362 3430",
    "sg:postcode":"G6L 2H6",
    "sg:province":"QC",
    "sg:tags":[
        "general",
        "contractor"
    ],
    "wof:name":"Constructions Cote & Cote Inc",
    "wof:placetype":"venue"
},
  "geometry": {"coordinates":[-71.76544199999999,46.214893],"type":"Point"}
}