{
  "type": "Feature",
  "properties": {
    "addr:full":"470 1 St SE Salmon Arm BC V1E 4H5",
    "addr:housenumber":"470 1",
    "addr:postcode":"v1e 4h5",
    "addr:street":"St Se",
    "iso:country":"CA",
    "sg:address":"470 1 St SE",
    "sg:city":"Salmon Arm",
    "sg:classifiers":[
        {
            "category":"Communications",
            "subcategory":"Film & Video Production",
            "type":"Services"
        }
    ],
    "sg:phone":"+1 250 832 3320",
    "sg:postcode":"V1E 4H5",
    "sg:province":"BC",
    "sg:tags":[
        "taping"
    ],
    "wof:name":"Ron Marchand the Video Man",
    "wof:placetype":"venue"
},
  "geometry": {"coordinates":[-119.283592,50.69651],"type":"Point"}
}