{
  "type": "Feature",
  "properties": {
    "addr:full":"136 Terra Cotta Dr New Glasgow NS B2H 5W5",
    "addr:housenumber":"136",
    "addr:postcode":"b2h 5w5",
    "addr:street":"Terra Cotta Dr",
    "iso:country":"CA",
    "sg:address":"136 Terra Cotta Dr",
    "sg:city":"New Glasgow",
    "sg:classifiers":[
        {
            "category":"Wholesale",
            "subcategory":"Electrical",
            "type":"Manufacturing & Wholesale Goods"
        }
    ],
    "sg:phone":"+1 902 755 4673",
    "sg:postcode":"B2H 5W5",
    "sg:province":"NS",
    "sg:tags":[
        "equipment",
        "electric",
        "supply"
    ],
    "wof:name":"Harris & Roome Supply Ltd",
    "wof:placetype":"venue"
},
  "geometry": {"coordinates":[-62.657921,45.585709],"type":"Point"}
}