{
  "type": "Feature",
  "properties": {
    "addr:full":"Mississauga ON L5L 3R8",
    "addr:postcode":"l5l 3r8",
    "iso:country":"CA",
    "sg:city":"Mississauga",
    "sg:classifiers":[
        {
            "category":"Shopping",
            "type":"Retail Goods"
        }
    ],
    "sg:phone":"+1 905 820 0000",
    "sg:postcode":"L5L 3R8",
    "sg:province":"ON",
    "sg:tags":[
        "telephone",
        "cellular"
    ],
    "wof:name":"Rogers A T & T",
    "wof:placetype":"venue"
},
  "geometry": {"coordinates":[-79.68393707280001,43.5208053589],"type":"Point"}
}