{
  "type": "Feature",
  "properties": {
    "addr:full":"37323 Hawkins Pickle Rd Dewdney BC V0M 1H0",
    "addr:housenumber":"37323",
    "addr:postcode":"v0m 1h0",
    "addr:street":"Hawkins Pickle Rd",
    "iso:country":"CA",
    "sg:address":"37323 Hawkins Pickle Rd",
    "sg:city":"Dewdney",
    "sg:classifiers":[
        {
            "category":"Organizations",
            "subcategory":"Religious Organization",
            "type":"Services"
        }
    ],
    "sg:phone":"+1 604 826 9336",
    "sg:postcode":"V0M 1H0",
    "sg:province":"BC",
    "sg:tags":[
        "church"
    ],
    "wof:name":"Monastery of All Saints",
    "wof:placetype":"venue"
},
  "geometry": {"coordinates":[-122.20107299999999,49.160866],"type":"Point"}
}