{
  "type": "Feature",
  "properties": {
    "addr:full":"575 Boul DE Quen N Alma QC G8B 5Z1",
    "addr:housenumber":"575",
    "addr:postcode":"g8b 5z1",
    "addr:street":"Boul De Quen N",
    "iso:country":"CA",
    "sg:address":"575 Boul DE Quen N",
    "sg:city":"Alma",
    "sg:classifiers":[
        {
            "category":"Insurance",
            "subcategory":"Insurance Agent",
            "type":"Services"
        }
    ],
    "sg:phone":"+1 418 662 6413",
    "sg:postcode":"G8B 5Z1",
    "sg:province":"QC",
    "wof:name":"Tremblay, Marc",
    "wof:placetype":"venue"
},
  "geometry": {"coordinates":[-71.644661,48.560383],"type":"Point"}
}