{
  "type": "Feature",
  "properties": {
    "addr:full":"114 Main St Watson SK S0K 4V0",
    "addr:housenumber":"114",
    "addr:postcode":"s0k 4v0",
    "addr:street":"Main St",
    "iso:country":"CA",
    "sg:address":"114 Main St",
    "sg:city":"Watson",
    "sg:classifiers":[
        {
            "category":"Shopping",
            "subcategory":"Pharmacy",
            "type":"Retail Goods"
        }
    ],
    "sg:phone":"+1 306 287 3215",
    "sg:postcode":"S0K 4V0",
    "sg:province":"SK",
    "wof:name":"Pharmasave",
    "wof:placetype":"venue"
},
  "geometry": {"coordinates":[-104.524330139,52.1280860901],"type":"Point"}
}