{
  "type": "Feature",
  "properties": {
    "addr:full":"2827 Boul Masson Quebec QC G1P 1J7",
    "addr:housenumber":"2827",
    "addr:postcode":"g1p 1j7",
    "addr:street":"Boul Masson",
    "iso:country":"CA",
    "sg:address":"2827 Boul Masson",
    "sg:city":"Quebec",
    "sg:classifiers":[
        {
            "category":"Shopping",
            "subcategory":"Florist",
            "type":"Retail Goods"
        }
    ],
    "sg:phone":"+1 418 877 0765",
    "sg:postcode":"G1P 1J7",
    "sg:province":"QC",
    "wof:name":"Fleuriste Fleurs En Folie Enr",
    "wof:placetype":"venue"
},
  "geometry": {"coordinates":[-71.32131195069999,46.8111457825],"type":"Point"}
}