{
  "type": "Feature",
  "properties": {
    "iso:country":"CA",
    "sg:city":"Peterborough",
    "sg:classifiers":[
        {
            "category":"Wholesale",
            "subcategory":"Office Equipment",
            "type":"Manufacturing & Wholesale Goods"
        }
    ],
    "sg:phone":"+1 705 748 2766",
    "sg:postcode":"K9J 3H3",
    "sg:province":"ON",
    "sg:tags":[
        "machine",
        "duplicating",
        "copying"
    ],
    "wof:name":"Mac Kay's Business Equipment",
    "wof:placetype":"venue"
},
  "geometry": {"coordinates":[-78.31991577150001,44.3023071289],"type":"Point"}
}