{
  "type": "Feature",
  "properties": {
    "addr:full":"177 Rue Lindsay Drummondville QC J2C 1N8",
    "addr:housenumber":"177",
    "addr:postcode":"j2c 1n8",
    "addr:street":"Rue Lindsay",
    "iso:country":"CA",
    "sg:address":"177 Rue Lindsay",
    "sg:city":"Drummondville",
    "sg:classifiers":[
        {
            "category":"Shopping",
            "subcategory":"Clothing, Apparel, & Fashions",
            "type":"Retail Goods"
        }
    ],
    "sg:phone":"+1 819 475 9648",
    "sg:postcode":"J2C 1N8",
    "sg:province":"QC",
    "sg:tags":[
        "item",
        "boutique"
    ],
    "wof:name":"Unix",
    "wof:placetype":"venue"
},
  "geometry": {"coordinates":[-72.4911117554,45.8845176697],"type":"Point"}
}