{
  "type": "Feature",
  "properties": {
    "iso:country":"CA",
    "sg:address":"7500 Bell School Line",
    "sg:city":"Milton",
    "sg:classifiers":[
        {
            "category":"Building & Trades",
            "subcategory":"Construction",
            "type":"Services"
        }
    ],
    "sg:phone":"+1 905 878 4808",
    "sg:postcode":"L9T 2Y1",
    "sg:province":"ON",
    "sg:tags":[
        "woodworker"
    ],
    "wof:name":"Jvr Trim",
    "wof:placetype":"venue"
},
  "geometry": {"coordinates":[-79.912468,43.488914],"type":"Point"}
}