{
  "type": "Feature",
  "properties": {
    "iso:country":"CA",
    "sg:address":"106 Brock St S",
    "sg:city":"Whitby",
    "sg:classifiers":[
        {
            "category":"Banks & Credit Unions",
            "subcategory":"Bank",
            "type":"Services"
        }
    ],
    "sg:phone":"+1 905 666 0502",
    "sg:postcode":"L1N 4J8",
    "sg:province":"ON",
    "sg:tags":[
        "cashing",
        "check"
    ],
    "wof:name":"Money Mart",
    "wof:placetype":"venue"
},
  "geometry": {"coordinates":[-78.9423446655,43.8796730042],"type":"Point"}
}