{
  "type": "Feature",
  "properties": {
    "addr:full":"1329 Lorne St Regina SK S4R 2K2",
    "addr:housenumber":"1329",
    "addr:postcode":"s4r 2k2",
    "addr:street":"Lorne St",
    "iso:country":"CA",
    "sg:address":"1329 Lorne St",
    "sg:city":"Regina",
    "sg:classifiers":[
        {
            "category":"Utilities",
            "subcategory":"Mobile Phone",
            "type":"Services"
        }
    ],
    "sg:phone":"+1 306 525 8128",
    "sg:postcode":"S4R 2K2",
    "sg:province":"SK",
    "sg:tags":[
        "high",
        "fidelity",
        "stereophonic",
        "telephone",
        "cellular"
    ],
    "wof:name":"Audio Warehouse",
    "wof:placetype":"venue"
},
  "geometry": {"coordinates":[-104.613571167,50.4577865601],"type":"Point"}
}