{
  "type": "Feature",
  "properties": {
    "iso:country":"CA",
    "sg:address":"3685 Bathurst St",
    "sg:city":"North York",
    "sg:classifiers":[
        {
            "category":"Shopping",
            "subcategory":"Discount & Variety Stores",
            "type":"Retail Goods"
        }
    ],
    "sg:phone":"+1 416 781 4883",
    "sg:postcode":"M6A 2E6",
    "sg:province":"ON",
    "wof:name":"One Stop Convenience Store",
    "wof:placetype":"venue"
},
  "geometry": {"coordinates":[-79.433075,43.73428],"type":"Point"}
}