{
  "type": "Feature",
  "properties": {
    "addr:full":"Qualicum Beach BC V9K 2R3",
    "addr:postcode":"v9k 2r3",
    "iso:country":"CA",
    "sg:city":"Qualicum Beach",
    "sg:classifiers":[
        {
            "category":"Shopping",
            "type":"Retail Goods"
        }
    ],
    "sg:phone":"+1 250 752 4245",
    "sg:postcode":"V9K 2R3",
    "sg:province":"BC",
    "sg:tags":[
        "pottery",
        "art",
        "gallery",
        "dealer"
    ],
    "wof:name":"Braemar Pottery",
    "wof:placetype":"venue"
},
  "geometry": {"coordinates":[-124.441703796,49.3467063904],"type":"Point"}
}