{
  "type": "Feature",
  "properties": {
    "addr:full":"3316 Temple Rd NE Calgary AB T1Y 3A9",
    "addr:housenumber":"3316",
    "addr:postcode":"t1y 3a9",
    "addr:street":"Temple Rd Ne",
    "iso:country":"CA",
    "sg:address":"3316 Temple Rd NE",
    "sg:city":"Calgary",
    "sg:classifiers":[
        {
            "category":"Food & Beverages",
            "subcategory":"Specialty",
            "type":"Retail Goods"
        }
    ],
    "sg:phone":"+1 403 291 6424",
    "sg:postcode":"T1Y 3A9",
    "sg:province":"AB",
    "sg:tags":[
        "health",
        "diet"
    ],
    "wof:name":"Matol Botanical Independent",
    "wof:placetype":"venue"
},
  "geometry": {"coordinates":[-113.957848,51.082108],"type":"Point"}
}