{
  "type": "Feature",
  "properties": {
    "addr:full":"295 Saint Augustine Ave Welland ON L3C 2L2",
    "addr:housenumber":"295",
    "addr:postcode":"l3c 2l2",
    "addr:street":"Saint Augustine Ave",
    "iso:country":"CA",
    "sg:address":"295 Saint Augustine Ave",
    "sg:city":"Welland",
    "sg:classifiers":[
        {
            "category":"Organizations",
            "subcategory":"Religious Organization",
            "type":"Services"
        }
    ],
    "sg:phone":"+1 905 734 9912",
    "sg:postcode":"L3C 2L2",
    "sg:province":"ON",
    "sg:tags":[
        "church"
    ],
    "wof:name":"St Augustine's Church",
    "wof:placetype":"venue"
},
  "geometry": {"coordinates":[-79.265587,42.969303],"type":"Point"}
}