{
  "type": "Feature",
  "properties": {
    "iso:country":"CA",
    "sg:address":"200 64E Rue E",
    "sg:city":"Charlesbourg",
    "sg:classifiers":[
        {
            "category":"Shopping",
            "subcategory":"Computers & Home Electronics",
            "type":"Retail Goods"
        }
    ],
    "sg:phone":"+1 418 627 6244",
    "sg:postcode":"G1H 1X9",
    "sg:province":"QC",
    "sg:tags":[
        "equipment",
        "dealer"
    ],
    "wof:name":"Info Click",
    "wof:placetype":"venue"
},
  "geometry": {"coordinates":[-71.2512893677,46.845664978],"type":"Point"}
}