{
  "type": "Feature",
  "properties": {
    "addr:full":"Etobicoke ON M9C 1A6",
    "addr:postcode":"m9c 1a6",
    "iso:country":"CA",
    "sg:city":"Etobicoke",
    "sg:classifiers":[
        {
            "category":"Health Services",
            "subcategory":"Nursing And Care Facility",
            "type":"Services"
        }
    ],
    "sg:phone":"+1 416 626 0116",
    "sg:postcode":"M9C 1A6",
    "sg:province":"ON",
    "sg:tags":[
        "hospice"
    ],
    "wof:name":"Dorothy Ley Hospice",
    "wof:placetype":"venue"
},
  "geometry": {"coordinates":[-79.5639801025,43.6089477539],"type":"Point"}
}