{
  "type": "Feature",
  "properties": {
    "addr:full":"414 Cumberland Ave N Saskatoon SK S7N 1M6",
    "addr:housenumber":"414",
    "addr:postcode":"s7n 1m6",
    "addr:street":"Cumberland Ave N",
    "iso:country":"CA",
    "sg:address":"414 Cumberland Ave N",
    "sg:city":"Saskatoon",
    "sg:classifiers":[
        {
            "category":"Restaurant",
            "type":"Food & Drink"
        }
    ],
    "sg:phone":"+1 306 956 7777",
    "sg:postcode":"S7N 1M6",
    "sg:province":"SK",
    "wof:name":"Alexander's Restaurant & Bar",
    "wof:placetype":"venue"
},
  "geometry": {"coordinates":[-106.63485,52.128002],"type":"Point"}
}