{
  "type": "Feature",
  "properties": {
    "addr:full":"1555 Marine Dr West Vancouver BC V7V 1H9",
    "addr:housenumber":"1555",
    "addr:postcode":"v7v 1h9",
    "addr:street":"Marine Dr",
    "iso:country":"CA",
    "sg:address":"1555 Marine Dr",
    "sg:city":"West Vancouver",
    "sg:classifiers":[
        {
            "category":"Real Estate",
            "subcategory":"Real Estate Agent",
            "type":"Services"
        }
    ],
    "sg:phone":"+1 604 921 1188",
    "sg:postcode":"V7V 1H9",
    "sg:province":"BC",
    "wof:name":"Angell Hasman & Assoc Realty",
    "wof:placetype":"venue"
},
  "geometry": {"coordinates":[-123.157867432,49.3286018372],"type":"Point"}
}