{
  "type": "Feature",
  "properties": {
    "addr:full":"58 Mount Herbert Rd Stratford PE C1B 2S4",
    "addr:housenumber":"58",
    "addr:postcode":"c1b 2s4",
    "addr:street":"Mount Herbert Rd",
    "iso:country":"CA",
    "sg:address":"58 Mount Herbert Rd",
    "sg:city":"Stratford",
    "sg:classifiers":[
        {
            "category":"Retail",
            "subcategory":"Auto Repair",
            "type":"Services"
        }
    ],
    "sg:phone":"+1 902 569 2606",
    "sg:postcode":"C1B 2S4",
    "sg:province":"PE",
    "sg:tags":[
        "repairing",
        "automobile",
        "wheel",
        "alignment"
    ],
    "wof:name":"Wheel Alignment Svc",
    "wof:placetype":"venue"
},
  "geometry": {"coordinates":[-63.043114,46.219006],"type":"Point"}
}