{
  "type": "Feature",
  "properties": {
    "iso:country":"CA",
    "sg:address":"5095 Main St",
    "sg:city":"Dorchester",
    "sg:classifiers":[
        {
            "category":"Building & Trades",
            "subcategory":"Construction",
            "type":"Services"
        }
    ],
    "sg:phone":"+1 506 379 2755",
    "sg:postcode":"E4K 2Y8",
    "sg:province":"NB",
    "sg:tags":[
        "general",
        "contractor"
    ],
    "wof:name":"Swift's Service Ctr Ltd",
    "wof:placetype":"venue"
},
  "geometry": {"coordinates":[-64.51026153559999,45.8926467896],"type":"Point"}
}