{
  "type": "Feature",
  "properties": {
    "iso:country":"CA",
    "sg:address":"331 Main St",
    "sg:city":"Doaktown",
    "sg:classifiers":[
        {
            "category":"Shopping",
            "subcategory":"Bicycles & Sporting Goods",
            "type":"Retail Goods"
        }
    ],
    "sg:phone":"+1 506 365 7828",
    "sg:postcode":"E9C 1E1",
    "sg:province":"NB",
    "sg:tags":[
        "tackle",
        "fishing"
    ],
    "wof:name":"W W Doak Fly Fishing Tackle",
    "wof:placetype":"venue"
},
  "geometry": {"coordinates":[-66.1276092529,46.5560951233],"type":"Point"}
}