{
  "type": "Feature",
  "properties": {
    "addr:full":"North Vancouver BC V7P 1S3",
    "addr:postcode":"v7p 1s3",
    "iso:country":"CA",
    "sg:city":"North Vancouver",
    "sg:classifiers":[
        {
            "category":"Shopping",
            "subcategory":"Gifts & Souvenirs",
            "type":"Retail Goods"
        }
    ],
    "sg:phone":"+1 604 980 4446",
    "sg:postcode":"V7P 1S3",
    "sg:province":"BC",
    "sg:tags":[
        "cards",
        "greeting"
    ],
    "wof:name":"Carlton Cards",
    "wof:placetype":"venue"
},
  "geometry": {"coordinates":[-123.09912872300001,49.3225708008],"type":"Point"}
}