{
  "type": "Feature",
  "properties": {
    "addr:full":"4150 Rue Sainte-Catherine O # 370 Westmount QC H3Z 2Y5",
    "addr:housenumber":"4150",
    "addr:postcode":"h3z 2y5",
    "addr:street":"Rue Sainte-Catherine O # 370",
    "iso:country":"CA",
    "sg:address":"4150 Rue Sainte-Catherine O # 370",
    "sg:city":"Westmount",
    "sg:classifiers":[
        {
            "category":"Health Services",
            "subcategory":"Doctor",
            "type":"Services"
        }
    ],
    "sg:phone":"+1 514 935 5211",
    "sg:postcode":"H3Z 2Y5",
    "sg:province":"QC",
    "sg:tags":[
        "dentist"
    ],
    "wof:name":"Centre Dentaire",
    "wof:placetype":"venue"
},
  "geometry": {"coordinates":[-73.587097,45.486717],"type":"Point"}
}