{
  "type": "Feature",
  "properties": {
    "addr:full":"5007 50 St Beaumont AB T4X 1J9",
    "addr:housenumber":"5007",
    "addr:postcode":"t4x 1j9",
    "addr:street":"50 St",
    "iso:country":"CA",
    "sg:address":"5007 50 St",
    "sg:city":"Beaumont",
    "sg:classifiers":[
        {
            "category":"Professional",
            "subcategory":"Lawyer & Legal Services",
            "type":"Services"
        }
    ],
    "sg:phone":"+1 780 929 8608",
    "sg:postcode":"T4X 1J9",
    "sg:province":"AB",
    "sg:tags":[
        "attorney"
    ],
    "wof:name":"Jackie Handerek & Forester",
    "wof:placetype":"venue"
},
  "geometry": {"coordinates":[-113.415161,53.352715],"type":"Point"}
}