{
  "type": "Feature",
  "properties": {
    "addr:full":"50 Talbot St W Leamington ON N8H 1M4",
    "addr:housenumber":"50",
    "addr:postcode":"n8h 1m4",
    "addr:street":"Talbot St W",
    "iso:country":"CA",
    "sg:address":"50 Talbot St W",
    "sg:city":"Leamington",
    "sg:classifiers":[
        {
            "category":"Personal",
            "subcategory":"Barber",
            "type":"Services"
        }
    ],
    "sg:phone":"+1 519 326 4911",
    "sg:postcode":"N8H 1M4",
    "sg:province":"ON",
    "wof:name":"Mastronardi Barber Shop",
    "wof:placetype":"venue"
},
  "geometry": {"coordinates":[-82.601265,42.052605],"type":"Point"}
}