{
  "type": "Feature",
  "properties": {
    "addr:full":"85 Maitland Terr Strathroy ON N7G 1L2",
    "addr:housenumber":"85",
    "addr:postcode":"n7g 1l2",
    "addr:street":"Maitland Terr",
    "iso:country":"CA",
    "sg:address":"85 Maitland Terr",
    "sg:city":"Strathroy",
    "sg:classifiers":[
        {
            "category":"Home & Garden",
            "subcategory":"Building Materials",
            "type":"Retail Goods"
        }
    ],
    "sg:phone":"+1 519 245 0256",
    "sg:postcode":"N7G 1L2",
    "sg:province":"ON",
    "sg:tags":[
        "windows"
    ],
    "wof:name":"Stephenson Home Improvement",
    "wof:placetype":"venue"
},
  "geometry": {"coordinates":[-81.623428,42.953876],"type":"Point"}
}