{
  "type": "Feature",
  "properties": {
    "iso:country":"CA",
    "sg:address":"1511 Ch Canora",
    "sg:city":"Mont-Royal",
    "sg:classifiers":[
        {
            "category":"Arts & Performance",
            "subcategory":"Theater",
            "type":"Entertainment"
        }
    ],
    "sg:phone":"+1 514 738 0336",
    "sg:postcode":"H3P 2J8",
    "sg:province":"QC",
    "wof:name":"Arsenal A Musique Inc",
    "wof:placetype":"venue"
},
  "geometry": {"coordinates":[-73.64595031739999,45.5175743103],"type":"Point"}
}