{
  "type": "Feature",
  "properties": {
    "iso:country":"CA",
    "sg:address":"401 Allanburg Rd",
    "sg:city":"Thorold",
    "sg:classifiers":[
        {
            "category":"Building & Trades",
            "subcategory":"Construction",
            "type":"Services"
        }
    ],
    "sg:phone":"+1 905 227 2719",
    "sg:postcode":"L2V 1A5",
    "sg:province":"ON",
    "sg:tags":[
        "excavating",
        "contractor",
        "general"
    ],
    "wof:name":"DE Rose Brothers Gen Contr Ltd",
    "wof:placetype":"venue"
},
  "geometry": {"coordinates":[-79.1996765137,43.0987052917],"type":"Point"}
}