{
  "type": "Feature",
  "properties": {
    "addr:full":"Mississauga ON L4X 1M1",
    "addr:postcode":"l4x 1m1",
    "iso:country":"CA",
    "sg:city":"Mississauga",
    "sg:classifiers":[
        {
            "category":"Restaurant",
            "type":"Food & Drink"
        }
    ],
    "sg:phone":"+1 905 624 4111",
    "sg:postcode":"L4X 1M1",
    "sg:province":"ON",
    "wof:name":"Croatia Restaurant",
    "wof:placetype":"venue"
},
  "geometry": {"coordinates":[-79.5701675415,43.6222915649],"type":"Point"}
}