{
  "type": "Feature",
  "properties": {
    "addr:full":"621 Shawcliffe Gate SW Calgary AB T2Y 1W1",
    "addr:housenumber":"621",
    "addr:postcode":"t2y 1w1",
    "addr:street":"Shawcliffe Gate Sw",
    "iso:country":"CA",
    "sg:address":"621 Shawcliffe Gate SW",
    "sg:city":"Calgary",
    "sg:classifiers":[
        {
            "category":"Retail",
            "subcategory":"Laundry & Dry Cleaning",
            "type":"Services"
        }
    ],
    "sg:phone":"+1 403 254 2514",
    "sg:postcode":"T2Y 1W1",
    "sg:province":"AB",
    "sg:tags":[
        "cleaners"
    ],
    "wof:name":"Sunny Drycleaning",
    "wof:placetype":"venue"
},
  "geometry": {"coordinates":[-114.074645996,50.9114074707],"type":"Point"}
}