{
  "type": "Feature",
  "properties": {
    "iso:country":"CA",
    "sg:address":"PO Box 763 STN Main",
    "sg:city":"Morden",
    "sg:classifiers":[
        {
            "category":"Local Transit",
            "type":"Transportation"
        }
    ],
    "sg:phone":"+1 204 362 2209",
    "sg:postcode":"R6M 1A7",
    "sg:province":"MB",
    "sg:tags":[
        "limousine"
    ],
    "wof:name":"Whitecastle Limousine Svc",
    "wof:placetype":"venue"
},
  "geometry": {"coordinates":[-98.11302185060001,49.1922836304],"type":"Point"}
}