{
  "type": "Feature",
  "properties": {
    "addr:full":"5781 Steeles Ave W North York ON M9L 2W3",
    "addr:housenumber":"5781",
    "addr:postcode":"m9l 2w3",
    "addr:street":"Steeles Ave W",
    "iso:country":"CA",
    "sg:address":"5781 Steeles Ave W",
    "sg:city":"North York",
    "sg:classifiers":[
        {
            "category":"Manufacturing",
            "subcategory":"Furniture",
            "type":"Manufacturing & Wholesale Goods"
        }
    ],
    "sg:phone":"+1 416 742 9196",
    "sg:postcode":"M9L 2W3",
    "sg:province":"ON",
    "wof:name":"Apex Furniture Mfg CO",
    "wof:placetype":"venue"
},
  "geometry": {"coordinates":[-79.566315,43.76609],"type":"Point"}
}