{
  "type": "Feature",
  "properties": {
    "addr:full":"Fort Mcmurray AB T9H 3E1",
    "addr:postcode":"t9h 3e1",
    "iso:country":"CA",
    "sg:city":"Fort Mcmurray",
    "sg:classifiers":[
        {
            "category":"Health Services",
            "subcategory":"Doctor",
            "type":"Services"
        }
    ],
    "sg:phone":"+1 780 743 5888",
    "sg:postcode":"T9H 3E1",
    "sg:province":"AB",
    "sg:tags":[
        "physician",
        "surgeon"
    ],
    "wof:name":"Zuk, Lorne M MD",
    "wof:placetype":"venue"
},
  "geometry": {"coordinates":[-111.36273956300001,56.7238540649],"type":"Point"}
}