{
  "type": "Feature",
  "properties": {
    "iso:country":"CA",
    "sg:address":"5075 Falconridge Blvd NE",
    "sg:city":"Calgary",
    "sg:classifiers":[
        {
            "category":"Banks & Credit Unions",
            "subcategory":"Bank",
            "type":"Services"
        }
    ],
    "sg:phone":"+1 403 299 6270",
    "sg:postcode":"T3J 3K9",
    "sg:province":"AB",
    "wof:name":"Scotiabank",
    "wof:placetype":"venue"
},
  "geometry": {"coordinates":[-113.958724976,51.0978813171],"type":"Point"}
}