{
  "type": "Feature",
  "properties": {
    "addr:full":"North York ON M3M 3G2",
    "addr:postcode":"m3m 3g2",
    "iso:country":"CA",
    "sg:city":"North York",
    "sg:classifiers":[
        {
            "category":"Health Services",
            "subcategory":"Doctor",
            "type":"Services"
        }
    ],
    "sg:phone":"+1 416 241 1190",
    "sg:postcode":"M3M 3G2",
    "sg:province":"ON",
    "sg:tags":[
        "dentist"
    ],
    "wof:name":"Dental Clinic",
    "wof:placetype":"venue"
},
  "geometry": {"coordinates":[-79.491592,43.724396],"type":"Point"}
}