{
  "type": "Feature",
  "properties": {
    "iso:country":"CA",
    "sg:address":"1123 Industrial Dr",
    "sg:city":"Hudson Bay",
    "sg:classifiers":[
        {
            "category":"Autos & Motor Vehicles",
            "subcategory":"Auto Supplies",
            "type":"Retail Goods"
        }
    ],
    "sg:phone":"+1 306 865 2453",
    "sg:postcode":"S0E 0Y0",
    "sg:province":"SK",
    "sg:tags":[
        "tire"
    ],
    "wof:name":"Bay Tire & Auto Ctr",
    "wof:placetype":"venue"
},
  "geometry": {"coordinates":[-102.38885498,52.8626594543],"type":"Point"}
}