{
  "type": "Feature",
  "properties": {
    "addr:full":"1410 Bishop Mcclean Cres Prince Albert SK S6V 4Z2",
    "addr:housenumber":"1410",
    "addr:postcode":"s6v 4z2",
    "addr:street":"Bishop Mcclean Cres",
    "iso:country":"CA",
    "sg:address":"1410 Bishop Mcclean Cres",
    "sg:city":"Prince Albert",
    "sg:classifiers":[
        {
            "category":"Organizations",
            "subcategory":"Religious Organization",
            "type":"Services"
        }
    ],
    "sg:phone":"+1 306 922 0044",
    "sg:postcode":"S6V 4Z2",
    "sg:province":"SK",
    "sg:tags":[
        "church"
    ],
    "wof:name":"St Alban's Cathedral",
    "wof:placetype":"venue"
},
  "geometry": {"coordinates":[-105.756759644,53.2001876831],"type":"Point"}
}