{
  "type": "Feature",
  "properties": {
    "addr:full":"Vancouver BC V6B 1R8",
    "addr:postcode":"v6b 1r8",
    "iso:country":"CA",
    "sg:city":"Vancouver",
    "sg:classifiers":[
        {
            "category":"Professional",
            "type":"Services"
        }
    ],
    "sg:phone":"+1 604 681 4643",
    "sg:postcode":"V6B 1R8",
    "sg:province":"BC",
    "sg:tags":[
        "consultant",
        "geological"
    ],
    "wof:name":"Geotex Consultants Ltd",
    "wof:placetype":"venue"
},
  "geometry": {"coordinates":[-123.10779571499999,49.281047821],"type":"Point"}
}