{
  "type": "Feature",
  "properties": {
    "addr:full":"Alberton PE C0B 1B0",
    "addr:postcode":"c0b 1b0",
    "iso:country":"CA",
    "sg:city":"Alberton",
    "sg:classifiers":[
        {
            "category":"Organizations",
            "subcategory":"Non-profit Organization",
            "type":"Services"
        }
    ],
    "sg:phone":"+1 902 853 4066",
    "sg:postcode":"C0B 1B0",
    "sg:province":"PE",
    "sg:tags":[
        "youth",
        "charitable",
        "center",
        "institution"
    ],
    "wof:name":"Kids West Inc",
    "wof:placetype":"venue"
},
  "geometry": {"coordinates":[-64.068398,46.812908],"type":"Point"}
}