{
  "type": "Feature",
  "properties": {
    "addr:full":"101 Main St Lampman SK S0C 1N0",
    "addr:housenumber":"101",
    "addr:postcode":"s0c 1n0",
    "addr:street":"Main St",
    "iso:country":"CA",
    "sg:address":"101 Main St",
    "sg:city":"Lampman",
    "sg:classifiers":[
        {
            "category":"Food & Beverages",
            "subcategory":"Groceries & Convenience Stores",
            "type":"Retail Goods"
        }
    ],
    "sg:phone":"+1 306 487 2282",
    "sg:postcode":"S0C 1N0",
    "sg:province":"SK",
    "sg:tags":[
        "grocer"
    ],
    "wof:name":"Gerry's Store",
    "wof:placetype":"venue"
},
  "geometry": {"coordinates":[-102.764145,49.377258],"type":"Point"}
}