{
  "type": "Feature",
  "properties": {
    "addr:full":"3083 Broadway W Vancouver BC V6K 2G9",
    "addr:housenumber":"3083",
    "addr:postcode":"v6k 2g9",
    "addr:street":"Broadway W",
    "iso:country":"CA",
    "sg:address":"3083 Broadway W",
    "sg:city":"Vancouver",
    "sg:classifiers":[
        {
            "category":"Shopping",
            "subcategory":"Books",
            "type":"Retail Goods"
        }
    ],
    "sg:phone":"+1 604 738 5335",
    "sg:postcode":"V6K 2G9",
    "sg:province":"BC",
    "sg:tags":[
        "dealer"
    ],
    "wof:name":"Kidsbooks",
    "wof:placetype":"venue"
},
  "geometry": {"coordinates":[-123.17337000000001,49.264263],"type":"Point"}
}