{
  "type": "Feature",
  "properties": {
    "iso:country":"CA",
    "sg:address":"51 Charterhouse Cres",
    "sg:city":"London",
    "sg:classifiers":[
        {
            "category":"Retail",
            "subcategory":"Auto Repair",
            "type":"Services"
        }
    ],
    "sg:phone":"+1 519 455 8900",
    "sg:postcode":"N5W 5V3",
    "sg:province":"ON",
    "sg:tags":[
        "body",
        "automobile",
        "painting"
    ],
    "wof:name":"Paint Master Auto Refinishing",
    "wof:placetype":"venue"
},
  "geometry": {"coordinates":[-81.170265,42.989033],"type":"Point"}
}