{
  "type": "Feature",
  "properties": {
    "addr:full":"671 Fir St Qualicum Beach BC V9K 1T4",
    "addr:housenumber":"671",
    "addr:postcode":"v9k 1t4",
    "addr:street":"Fir St",
    "iso:country":"CA",
    "sg:address":"671 Fir St",
    "sg:city":"Qualicum Beach",
    "sg:classifiers":[
        {
            "category":"Shopping",
            "subcategory":"Used Merchandise",
            "type":"Retail Goods"
        }
    ],
    "sg:phone":"+1 250 752 2142",
    "sg:postcode":"V9K 1T4",
    "sg:province":"BC",
    "sg:tags":[
        "antique"
    ],
    "wof:name":"Cheshire Cat Antique Mall",
    "wof:placetype":"venue"
},
  "geometry": {"coordinates":[-124.44103200000001,49.34779],"type":"Point"}
}