{
  "type": "Feature",
  "properties": {
    "iso:country":"CA",
    "sg:address":"10 Bertal Rd",
    "sg:city":"York",
    "sg:classifiers":[
        {
            "category":"Building & Trades",
            "subcategory":"Construction",
            "type":"Services"
        }
    ],
    "sg:phone":"+1 416 762 6614",
    "sg:postcode":"M6M 4M4",
    "sg:province":"ON",
    "sg:tags":[
        "woodworker"
    ],
    "wof:name":"Italcan Woodworking Ltd",
    "wof:placetype":"venue"
},
  "geometry": {"coordinates":[-79.48955535890001,43.692325592],"type":"Point"}
}