{
  "type": "Feature",
  "properties": {
    "addr:full":"33 Alderney Dr # 100 Dartmouth NS B2Y 2N4",
    "addr:housenumber":"33",
    "addr:postcode":"b2y 2n4",
    "addr:street":"Alderney Dr # 100",
    "iso:country":"CA",
    "sg:address":"33 Alderney Dr # 100",
    "sg:city":"Dartmouth",
    "sg:classifiers":[
        {
            "category":"Restaurant",
            "type":"Food & Drink"
        }
    ],
    "sg:phone":"+1 902 465 3273",
    "sg:postcode":"B2Y 2N4",
    "sg:province":"NS",
    "wof:name":"Belmont Cafe & Catering",
    "wof:placetype":"venue"
},
  "geometry": {"coordinates":[-63.5703582764,44.6658554077],"type":"Point"}
}