{
  "type": "Feature",
  "properties": {
    "iso:country":"CA",
    "sg:address":"142 Alport Cres",
    "sg:city":"Regina",
    "sg:classifiers":[
        {
            "category":"Building & Trades",
            "subcategory":"Plumbing",
            "type":"Services"
        }
    ],
    "sg:phone":"+1 306 949 4183",
    "sg:postcode":"S4R 7Y6",
    "sg:province":"SK",
    "sg:tags":[
        "contractor"
    ],
    "wof:name":"Provincial Plumbing & Heating",
    "wof:placetype":"venue"
},
  "geometry": {"coordinates":[-104.598244,50.497826],"type":"Point"}
}