{
  "type": "Feature",
  "properties": {
    "addr:full":"351 Pitfield Rd Scarborough ON M1S 3E5",
    "addr:housenumber":"351",
    "addr:postcode":"m1s 3e5",
    "addr:street":"Pitfield Rd",
    "iso:country":"CA",
    "sg:address":"351 Pitfield Rd",
    "sg:city":"Scarborough",
    "sg:classifiers":[
        {
            "category":"Restaurant",
            "type":"Food & Drink"
        }
    ],
    "sg:phone":"+1 416 298 4153",
    "sg:postcode":"M1S 3E5",
    "sg:province":"ON",
    "wof:name":"Roti Hut",
    "wof:placetype":"venue"
},
  "geometry": {"coordinates":[-79.258942,43.787186],"type":"Point"}
}