{
  "type": "Feature",
  "properties": {
    "addr:full":"Vancouver BC V6B 1T6",
    "addr:postcode":"v6b 1t6",
    "iso:country":"CA",
    "sg:city":"Vancouver",
    "sg:classifiers":[
        {
            "category":"Professional",
            "subcategory":"Business Services",
            "type":"Services"
        }
    ],
    "sg:phone":"+1 604 687 6728",
    "sg:postcode":"V6B 1T6",
    "sg:province":"BC",
    "sg:tags":[
        "home",
        "planning",
        "drafting"
    ],
    "wof:name":"Pacific Image Home Designs Ltd",
    "wof:placetype":"venue"
},
  "geometry": {"coordinates":[-123.111969,49.282738],"type":"Point"}
}