{
  "type": "Feature",
  "properties": {
    "iso:country":"CA",
    "sg:address":"7445 Boul Langelier",
    "sg:city":"Saint-Leonard",
    "sg:classifiers":[
        {
            "category":"Shopping",
            "subcategory":"Department Store",
            "type":"Retail Goods"
        }
    ],
    "sg:phone":"+1 514 899 9548",
    "sg:postcode":"H1S 1V9",
    "sg:province":"QC",
    "wof:name":"Wal-Mart",
    "wof:placetype":"venue"
},
  "geometry": {"coordinates":[-73.572762,45.591663],"type":"Point"}
}