{
  "type": "Feature",
  "properties": {
    "iso:country":"CA",
    "sg:address":"3150 Boul Cartier O",
    "sg:city":"Laval",
    "sg:classifiers":[
        {
            "category":"Food & Beverages",
            "subcategory":"Groceries & Convenience Stores",
            "type":"Retail Goods"
        }
    ],
    "sg:phone":"+1 450 688 1184",
    "sg:postcode":"H7V 1J7",
    "sg:province":"QC",
    "wof:name":"Couche-Tard",
    "wof:placetype":"venue"
},
  "geometry": {"coordinates":[-73.728905,45.541237],"type":"Point"}
}