{
  "type": "Feature",
  "properties": {
    "addr:full":"3444 Mcbean St Richmond ON K0A 2Z0",
    "addr:housenumber":"3444",
    "addr:postcode":"k0a 2z0",
    "addr:street":"Mcbean St",
    "iso:country":"CA",
    "sg:address":"3444 Mcbean St",
    "sg:city":"Richmond",
    "sg:classifiers":[
        {
            "category":"Home & Garden",
            "subcategory":"Home Furnishings",
            "type":"Retail Goods"
        }
    ],
    "sg:phone":"+1 613 838 5541",
    "sg:postcode":"K0A 2Z0",
    "sg:province":"ON",
    "sg:tags":[
        "quilting"
    ],
    "wof:name":"Country Quilter",
    "wof:placetype":"venue"
},
  "geometry": {"coordinates":[-75.8379974365,45.1934242249],"type":"Point"}
}