{
  "type": "Feature",
  "properties": {
    "addr:full":"239 Boul J D Gauthier Shippagan NB E8S 1N2",
    "addr:housenumber":"239",
    "addr:postcode":"e8s 1n2",
    "addr:street":"Boul J D Gauthier Shippagan",
    "iso:country":"CA",
    "sg:address":"239 Boul J D Gauthier",
    "sg:city":"Shippagan",
    "sg:classifiers":[
        {
            "category":"Professional",
            "subcategory":"Lawyer & Legal Services",
            "type":"Services"
        }
    ],
    "sg:phone":"+1 506 336 0400",
    "sg:postcode":"E8S 1N2",
    "sg:province":"NB",
    "sg:tags":[
        "attorney"
    ],
    "wof:name":"Gauvin, Jean-Marc",
    "wof:placetype":"venue"
},
  "geometry": {"coordinates":[-64.708252,47.74353],"type":"Point"}
}