{
  "type": "Feature",
  "properties": {
    "addr:full":"3725 Victoria Ave #5 Brandon MB R7B 3C3",
    "addr:housenumber":"3725",
    "addr:postcode":"r7b 3c3",
    "addr:street":"Victoria Ave # 5",
    "iso:country":"CA",
    "sg:address":"3725 Victoria Ave #5",
    "sg:city":"Brandon",
    "sg:classifiers":[
        {
            "category":"Real Estate",
            "subcategory":"Real Estate Operator",
            "type":"Services"
        }
    ],
    "sg:phone":"+1 204 725 1299",
    "sg:postcode":"R7B 3C3",
    "sg:province":"MB",
    "sg:tags":[
        "apartment"
    ],
    "wof:name":"Victoria Woods Estates",
    "wof:placetype":"venue"
},
  "geometry": {"coordinates":[-99.990219,49.84248],"type":"Point"}
}