{
  "type": "Feature",
  "properties": {
    "addr:full":"4642 91 Ave NW Edmonton AB T6B 2L1",
    "addr:housenumber":"4642",
    "addr:postcode":"t6b 2l1",
    "addr:street":"91 Ave Nw",
    "iso:country":"CA",
    "sg:address":"4642 91 Ave NW",
    "sg:city":"Edmonton",
    "sg:classifiers":[
        {
            "category":"Mining & Drilling",
            "type":"Manufacturing & Wholesale Goods"
        }
    ],
    "sg:phone":"+1 780 465 0017",
    "sg:postcode":"T6B 2L1",
    "sg:province":"AB",
    "sg:tags":[
        "field",
        "oil"
    ],
    "wof:name":"Ahms Inc",
    "wof:placetype":"venue"
},
  "geometry": {"coordinates":[-113.413567,53.524887],"type":"Point"}
}