{
  "type": "Feature",
  "properties": {
    "addr:full":"595 Rue DE Beaucaire Laval QC H7N 4P2",
    "addr:housenumber":"595",
    "addr:postcode":"h7n 4p2",
    "addr:street":"Rue De Beaucaire",
    "iso:country":"CA",
    "sg:address":"595 Rue DE Beaucaire",
    "sg:city":"Laval",
    "sg:classifiers":[
        {
            "category":"Food & Beverages",
            "subcategory":"Specialty",
            "type":"Retail Goods"
        }
    ],
    "sg:phone":"+1 450 669 5456",
    "sg:postcode":"H7N 4P2",
    "sg:province":"QC",
    "sg:tags":[
        "physician"
    ],
    "wof:name":"Shaklee Products Distributor",
    "wof:placetype":"venue"
},
  "geometry": {"coordinates":[-73.6988983154,45.5709762573],"type":"Point"}
}