{
  "type": "Feature",
  "properties": {
    "addr:full":"434 Queen St W Toronto ON M5V 2A8",
    "addr:housenumber":"434",
    "addr:postcode":"m5v 2a8",
    "addr:street":"Queen St W",
    "iso:country":"CA",
    "sg:address":"434 Queen St W",
    "sg:city":"Toronto",
    "sg:classifiers":[
        {
            "category":"Wholesale",
            "subcategory":"Home Furnishings",
            "type":"Manufacturing & Wholesale Goods"
        }
    ],
    "sg:phone":"+1 416 504 8666",
    "sg:postcode":"M5V 2A8",
    "sg:province":"ON",
    "sg:tags":[
        "linen"
    ],
    "wof:name":"L & M Trading CO",
    "wof:placetype":"venue"
},
  "geometry": {"coordinates":[-79.3986816406,43.6483840942],"type":"Point"}
}