{
  "type": "Feature",
  "properties": {
    "addr:full":"155 Main St Penetanguishene ON L9M 1L7",
    "addr:housenumber":"155",
    "addr:postcode":"l9m 1l7",
    "addr:street":"Main St",
    "iso:country":"CA",
    "sg:address":"155 Main St",
    "sg:city":"Penetanguishene",
    "sg:classifiers":[
        {
            "category":"Retail",
            "subcategory":"Funeral Services",
            "type":"Services"
        }
    ],
    "sg:phone":"+1 705 549 3155",
    "sg:postcode":"L9M 1L7",
    "sg:province":"ON",
    "sg:tags":[
        "director"
    ],
    "wof:name":"Penetanguishene Funeral Home",
    "wof:placetype":"venue"
},
  "geometry": {"coordinates":[-79.931168,44.766026],"type":"Point"}
}