{
  "type": "Feature",
  "properties": {
    "addr:full":"Morinville AB T8R 1K6",
    "addr:postcode":"t8r 1k6",
    "iso:country":"CA",
    "sg:city":"Morinville",
    "sg:classifiers":[
        {
            "category":"Manufacturing",
            "subcategory":"Tools & Machinery",
            "type":"Manufacturing & Wholesale Goods"
        }
    ],
    "sg:phone":"+1 780 939 4232",
    "sg:postcode":"T8R 1K6",
    "sg:province":"AB",
    "sg:tags":[
        "farm",
        "engine"
    ],
    "wof:name":"Morinville D & J Equipment Ltd",
    "wof:placetype":"venue"
},
  "geometry": {"coordinates":[-113.638428,53.783272],"type":"Point"}
}