{
  "type": "Feature",
  "properties": {
    "addr:full":"3935 Lakeshore Rd Kelowna BC V1W 1V3",
    "addr:housenumber":"3935",
    "addr:postcode":"v1w 1v3",
    "addr:street":"Lakeshore Rd",
    "iso:country":"CA",
    "sg:address":"3935 Lakeshore Rd",
    "sg:city":"Kelowna",
    "sg:classifiers":[
        {
            "category":"Health Services",
            "subcategory":"Doctor",
            "type":"Services"
        }
    ],
    "sg:phone":"+1 250 764 4138",
    "sg:postcode":"V1W 1V3",
    "sg:province":"BC",
    "sg:tags":[
        "dentist"
    ],
    "wof:name":"Mission Creek Dental Ctr",
    "wof:placetype":"venue"
},
  "geometry": {"coordinates":[-119.48788500000001,49.842049],"type":"Point"}
}