{
  "type": "Feature",
  "properties": {
    "addr:full":"542 3rd Ave E Owen Sound ON N4K 2J8",
    "addr:housenumber":"542",
    "addr:postcode":"n4k 2j8",
    "addr:street":"3Rd Ave E",
    "iso:country":"CA",
    "sg:address":"542 3rd Ave E",
    "sg:city":"Owen Sound",
    "sg:classifiers":[
        {
            "category":"Shopping",
            "subcategory":"Books",
            "type":"Retail Goods"
        }
    ],
    "sg:phone":"+1 519 371 2100",
    "sg:postcode":"N4K 2J8",
    "sg:province":"ON",
    "sg:tags":[
        "dealer"
    ],
    "wof:name":"About Books",
    "wof:placetype":"venue"
},
  "geometry": {"coordinates":[-80.939735,44.559414],"type":"Point"}
}