{
  "type": "Feature",
  "properties": {
    "iso:country":"CA",
    "sg:address":"25 Sullivan Dr",
    "sg:city":"Ajax",
    "sg:classifiers":[
        {
            "category":"Education",
            "subcategory":"School",
            "type":"Public Place"
        }
    ],
    "sg:phone":"+1 905 686 1081",
    "sg:postcode":"L1T 3L3",
    "sg:province":"ON",
    "wof:name":"Dr Roberta Bondar Public Schl",
    "wof:placetype":"venue"
},
  "geometry": {"coordinates":[-79.03387451170001,43.8709068298],"type":"Point"}
}