{
  "type": "Feature",
  "properties": {
    "addr:full":"6365 Rue Sherbrooke O Montreal QC H4B 1N1",
    "addr:housenumber":"6365",
    "addr:postcode":"h4b 1n1",
    "addr:street":"Rue Sherbrooke O",
    "iso:country":"CA",
    "sg:address":"6365 Rue Sherbrooke O",
    "sg:city":"Montreal",
    "sg:classifiers":[
        {
            "category":"Restaurant",
            "type":"Food & Drink"
        }
    ],
    "sg:phone":"+1 514 481 5559",
    "sg:postcode":"H4B 1N1",
    "sg:province":"QC",
    "wof:name":"Restaurant Amir",
    "wof:placetype":"venue"
},
  "geometry": {"coordinates":[-73.5449142456,45.5802726746],"type":"Point"}
}