{
  "type": "Feature",
  "properties": {
    "addr:full":"2029 Cassells St North Bay ON P1B 4E1",
    "addr:housenumber":"2029",
    "addr:postcode":"p1b 4e1",
    "addr:street":"Cassells St",
    "iso:country":"CA",
    "sg:address":"2029 Cassells St",
    "sg:city":"North Bay",
    "sg:classifiers":[
        {
            "category":"Health Services",
            "subcategory":"Doctor",
            "type":"Services"
        }
    ],
    "sg:phone":"+1 705 474 1441",
    "sg:postcode":"P1B 4E1",
    "sg:province":"ON",
    "sg:tags":[
        "physician",
        "surgeon"
    ],
    "wof:name":"Aylett, Alan MD",
    "wof:placetype":"venue"
},
  "geometry": {"coordinates":[-79.44544999999999,46.317795],"type":"Point"}
}