{
  "type": "Feature",
  "properties": {
    "addr:full":"2 Macallum St Hamilton ON L8L 4E8",
    "addr:housenumber":"2",
    "addr:postcode":"l8l 4e8",
    "addr:street":"Macallum St",
    "iso:country":"CA",
    "sg:address":"2 Macallum St",
    "sg:city":"Hamilton",
    "sg:classifiers":[
        {
            "category":"Building & Trades",
            "subcategory":"Construction",
            "type":"Services"
        }
    ],
    "sg:phone":"+1 905 547 4066",
    "sg:postcode":"L8L 4E8",
    "sg:province":"ON",
    "sg:tags":[
        "roofing",
        "contractor"
    ],
    "wof:name":"Peter Van Egmond & Sons Rfng",
    "wof:placetype":"venue"
},
  "geometry": {"coordinates":[-79.84266700000001,43.267265],"type":"Point"}
}