{
  "type": "Feature",
  "properties": {
    "addr:full":"5050 Boul Des Gradins Quebec QC G2J 1P8",
    "addr:housenumber":"5050",
    "addr:postcode":"g2j 1p8",
    "addr:street":"Boul Des Gradins",
    "iso:country":"CA",
    "sg:address":"5050 Boul Des Gradins",
    "sg:city":"Quebec",
    "sg:classifiers":[
        {
            "category":"Government",
            "subcategory":"Office",
            "type":"Public Place"
        }
    ],
    "sg:phone":"+1 418 643 7620",
    "sg:postcode":"G2J 1P8",
    "sg:province":"QC",
    "wof:name":"Quebec Societe Assurance Auto",
    "wof:placetype":"venue"
},
  "geometry": {"coordinates":[-71.2716217041,46.8368453979],"type":"Point"}
}