{
  "type": "Feature",
  "properties": {
    "addr:full":"4216 Ch Blanchette Sullivan QC J0Y 2N0",
    "addr:housenumber":"4216",
    "addr:postcode":"j0y 2n0",
    "addr:street":"Ch Blanchette",
    "iso:country":"CA",
    "sg:address":"4216 Ch Blanchette",
    "sg:city":"Sullivan",
    "sg:classifiers":[
        {
            "category":"Mining & Drilling",
            "type":"Manufacturing & Wholesale Goods"
        }
    ],
    "sg:phone":"+1 819 824 8689",
    "sg:postcode":"J0Y 2N0",
    "sg:province":"QC",
    "sg:tags":[
        "mine"
    ],
    "wof:name":"Valminex Inc",
    "wof:placetype":"venue"
},
  "geometry": {"coordinates":[-77.8513412476,48.1605453491],"type":"Point"}
}