{
  "type": "Feature",
  "properties": {
    "addr:full":"5334 Kitchener St Niagara Falls ON L2G 1B5",
    "addr:housenumber":"5334",
    "addr:postcode":"l2g 1b5",
    "addr:street":"Kitchener St",
    "iso:country":"CA",
    "sg:address":"5334 Kitchener St",
    "sg:city":"Niagara Falls",
    "sg:classifiers":[
        {
            "category":"Travel",
            "subcategory":"Hotels & Motels",
            "type":"Entertainment"
        }
    ],
    "sg:phone":"+1 905 374 7666",
    "sg:postcode":"L2G 1B5",
    "sg:province":"ON",
    "wof:name":"Red Carpet Inn",
    "wof:placetype":"venue"
},
  "geometry": {"coordinates":[-79.082756,43.095291],"type":"Point"}
}