{
  "type": "Feature",
  "properties": {
    "addr:full":"460 Rue DE Chateaudun Cap-DE-LA-Madeleine QC G8V 1S6",
    "addr:housenumber":"460",
    "addr:postcode":"g8v 1s6",
    "addr:street":"Rue De Chateaudun",
    "iso:country":"CA",
    "sg:address":"460 Rue DE Chateaudun",
    "sg:city":"Cap-DE-LA-Madeleine",
    "sg:classifiers":[
        {
            "category":"Building & Trades",
            "subcategory":"Construction",
            "type":"Services"
        }
    ],
    "sg:phone":"+1 819 373 0929",
    "sg:postcode":"G8V 1S6",
    "sg:province":"QC",
    "sg:tags":[
        "contractor",
        "general"
    ],
    "wof:name":"Sylvain Bourdeau Construction",
    "wof:placetype":"venue"
},
  "geometry": {"coordinates":[-72.5426940918,46.3954734802],"type":"Point"}
}