{
  "type": "Feature",
  "properties": {
    "addr:full":"7832 6th St Burnaby BC V3N 3N2",
    "addr:housenumber":"7832",
    "addr:postcode":"v3n 3n2",
    "addr:street":"6Th St",
    "iso:country":"CA",
    "sg:address":"7832 6th St",
    "sg:city":"Burnaby",
    "sg:classifiers":[
        {
            "category":"Food & Beverages",
            "subcategory":"Meat & Fish",
            "type":"Retail Goods"
        }
    ],
    "sg:phone":"+1 604 522 4224",
    "sg:postcode":"V3N 3N2",
    "sg:province":"BC",
    "wof:name":"Farm Town Meats",
    "wof:placetype":"venue"
},
  "geometry": {"coordinates":[-122.92880249,49.2201042175],"type":"Point"}
}