{
  "type": "Feature",
  "properties": {
    "addr:full":"32900 South Fraser Way Abbotsford BC V2S 5A1",
    "addr:housenumber":"32900",
    "addr:postcode":"v2s 5a1",
    "addr:street":"South Fraser Way",
    "iso:country":"CA",
    "sg:address":"32900 South Fraser Way",
    "sg:city":"Abbotsford",
    "sg:classifiers":[
        {
            "category":"Professional",
            "subcategory":"Accounting & Tax Preparation",
            "type":"Services"
        }
    ],
    "sg:phone":"+1 604 504 5574",
    "sg:postcode":"V2S 5A1",
    "sg:province":"BC",
    "sg:tags":[
        "consultant",
        "return",
        "filing"
    ],
    "wof:name":"H & R Block Canada Inc",
    "wof:placetype":"venue"
},
  "geometry": {"coordinates":[-122.311775,49.050785],"type":"Point"}
}