{
  "type": "Feature",
  "properties": {
    "addr:full":"220 Green Mountain Rd E Stoney Creek ON L8J 2X9",
    "addr:housenumber":"220",
    "addr:postcode":"l8j 2x9",
    "addr:street":"Green Mountain Rd E",
    "iso:country":"CA",
    "sg:address":"220 Green Mountain Rd E",
    "sg:city":"Stoney Creek",
    "sg:classifiers":[
        {
            "category":"Building & Trades",
            "subcategory":"Construction",
            "type":"Services"
        }
    ],
    "sg:phone":"+1 905 560 4827",
    "sg:postcode":"L8J 2X9",
    "sg:province":"ON",
    "sg:tags":[
        "tile",
        "dealer"
    ],
    "wof:name":"Brittania Tile Ltd",
    "wof:placetype":"venue"
},
  "geometry": {"coordinates":[-79.74351501460001,43.1936836243],"type":"Point"}
}