{
  "type": "Feature",
  "properties": {
    "addr:full":"214 14E Av Deux-Montagnes QC J7R 3W2",
    "addr:housenumber":"214",
    "addr:postcode":"j7r 3w2",
    "addr:street":"14E Av Deux-Montagnes",
    "iso:country":"CA",
    "sg:address":"214 14E Av",
    "sg:city":"Deux-Montagnes",
    "sg:classifiers":[
        {
            "category":"Organizations",
            "subcategory":"Religious Organization",
            "type":"Services"
        }
    ],
    "sg:phone":"+1 450 473 4784",
    "sg:postcode":"J7R 3W2",
    "sg:province":"QC",
    "sg:tags":[
        "church"
    ],
    "wof:name":"Christ Church United",
    "wof:placetype":"venue"
},
  "geometry": {"coordinates":[-73.8976974487,45.5385818481],"type":"Point"}
}