{
  "type": "Feature",
  "properties": {
    "addr:full":"New Westminster BC V3L 2B8",
    "addr:postcode":"v3l 2b8",
    "iso:country":"CA",
    "sg:city":"New Westminster",
    "sg:classifiers":[
        {
            "category":"Health Services",
            "subcategory":"Doctor",
            "type":"Services"
        }
    ],
    "sg:phone":"+1 604 522 3656",
    "sg:postcode":"V3L 2B8",
    "sg:province":"BC",
    "sg:tags":[
        "physician",
        "surgeon"
    ],
    "wof:name":"Harding, H G MD",
    "wof:placetype":"venue"
},
  "geometry": {"coordinates":[-122.912254,49.222443],"type":"Point"}
}