{
  "type": "Feature",
  "properties": {
    "addr:full":"233 Gowan Ave East York ON M4J 2K7",
    "addr:housenumber":"233",
    "addr:postcode":"m4j 2k7",
    "addr:street":"Gowan Ave",
    "iso:country":"CA",
    "sg:address":"233 Gowan Ave",
    "sg:city":"East York",
    "sg:classifiers":[
        {
            "category":"Building & Trades",
            "subcategory":"Cleaning & Sanitation",
            "type":"Services"
        }
    ],
    "sg:phone":"+1 416 421 0867",
    "sg:postcode":"M4J 2K7",
    "sg:province":"ON",
    "wof:name":"Top Janitorial Svc",
    "wof:placetype":"venue"
},
  "geometry": {"coordinates":[-79.3462295532,43.6887397766],"type":"Point"}
}