{
  "type": "Feature",
  "properties": {
    "addr:full":"125 Clark St Fredericton NB E3A 2W8",
    "addr:housenumber":"125",
    "addr:postcode":"e3a 2w8",
    "addr:street":"Clark St",
    "iso:country":"CA",
    "sg:address":"125 Clark St",
    "sg:city":"Fredericton",
    "sg:classifiers":[
        {
            "category":"Social Services",
            "subcategory":"Child Care",
            "type":"Services"
        }
    ],
    "sg:phone":"+1 506 458 8981",
    "sg:postcode":"E3A 2W8",
    "sg:province":"NB",
    "wof:name":"Preschool Centre",
    "wof:placetype":"venue"
},
  "geometry": {"coordinates":[-66.6287536621,45.9684257507],"type":"Point"}
}