{
  "type": "Feature",
  "properties": {
    "addr:full":"1638 Rue Sainte-Helene Longueuil QC J4K 3S7",
    "addr:housenumber":"1638",
    "addr:postcode":"j4k 3s7",
    "addr:street":"Rue Sainte-Helene",
    "iso:country":"CA",
    "sg:address":"1638 Rue Sainte-Helene",
    "sg:city":"Longueuil",
    "sg:classifiers":[
        {
            "category":"Shopping",
            "subcategory":"Used Merchandise",
            "type":"Retail Goods"
        }
    ],
    "sg:phone":"+1 450 679 5500",
    "sg:postcode":"J4K 3S7",
    "sg:province":"QC",
    "sg:tags":[
        "furniture"
    ],
    "wof:name":"Ameublement Ste-Helene Ltee",
    "wof:placetype":"venue"
},
  "geometry": {"coordinates":[-73.4952926636,45.5165863037],"type":"Point"}
}