{
  "type": "Feature",
  "properties": {
    "iso:country":"CA",
    "sg:address":"556 Route 105",
    "sg:city":"Maugerville",
    "sg:classifiers":[
        {
            "category":"Building & Trades",
            "subcategory":"Construction",
            "type":"Services"
        }
    ],
    "sg:phone":"+1 506 458 9940",
    "sg:postcode":"E3A 8G5",
    "sg:province":"NB",
    "sg:tags":[
        "general",
        "contractor"
    ],
    "wof:name":"A L Gullison Ltd",
    "wof:placetype":"venue"
},
  "geometry": {"coordinates":[-66.5353088379,45.8982620239],"type":"Point"}
}