{
  "type": "Feature",
  "properties": {
    "iso:country":"CA",
    "sg:address":"845 Rue Des Frenes",
    "sg:city":"Trois-Rivieres",
    "sg:classifiers":[
        {
            "category":"Building & Trades",
            "subcategory":"Construction",
            "type":"Services"
        }
    ],
    "sg:phone":"+1 819 378 8245",
    "sg:postcode":"G8Y 1E2",
    "sg:province":"QC",
    "sg:tags":[
        "concrete",
        "contractor",
        "general"
    ],
    "wof:name":"Entreprises Alain Proteau Inc",
    "wof:placetype":"venue"
},
  "geometry": {"coordinates":[-72.5742111206,46.3632774353],"type":"Point"}
}