{
  "type": "Feature",
  "properties": {
    "addr:full":"North York ON M2N 6C6",
    "addr:postcode":"m2n 6c6",
    "iso:country":"CA",
    "sg:city":"North York",
    "sg:classifiers":[
        {
            "category":"Professional",
            "subcategory":"Lawyer & Legal Services",
            "type":"Services"
        }
    ],
    "sg:phone":"+1 416 225 5136",
    "sg:postcode":"M2N 6C6",
    "sg:province":"ON",
    "sg:tags":[
        "attorney"
    ],
    "wof:name":"Isenberg, Alvin",
    "wof:placetype":"venue"
},
  "geometry": {"coordinates":[-79.41229199999999,43.767654],"type":"Point"}
}