{
  "type": "Feature",
  "properties": {
    "iso:country":"CA",
    "sg:city":"London",
    "sg:classifiers":[
        {
            "category":"Professional",
            "subcategory":"Lawyer & Legal Services",
            "type":"Services"
        }
    ],
    "sg:phone":"+1 519 672 9330",
    "sg:postcode":"N6A 5R8",
    "sg:province":"ON",
    "sg:tags":[
        "attorney"
    ],
    "wof:name":"Mac Dougall, Rod",
    "wof:placetype":"venue"
},
  "geometry": {"coordinates":[-81.24663543699999,42.9858551025],"type":"Point"}
}