{
  "type": "Feature",
  "properties": {
    "iso:country":"CA",
    "sg:address":"5004 20 Ave SE",
    "sg:city":"Calgary",
    "sg:classifiers":[
        {
            "category":"Manufacturing",
            "subcategory":"Metals",
            "type":"Manufacturing & Wholesale Goods"
        }
    ],
    "sg:phone":"+1 403 272 7082",
    "sg:postcode":"T2B 2S8",
    "sg:province":"AB",
    "sg:tags":[
        "steel",
        "bolt"
    ],
    "wof:name":"Alberta Bolt Makers Ltd",
    "wof:placetype":"venue"
},
  "geometry": {"coordinates":[-113.963874817,51.0356941223],"type":"Point"}
}