{
  "type": "Feature",
  "properties": {
    "addr:full":"267 Rte Du Pont # A Saint-Nicolas QC G7A 2V1",
    "addr:housenumber":"267",
    "addr:postcode":"g7a 2v1",
    "addr:street":"Rte Du Pont # A Saint-Nicolas",
    "iso:country":"CA",
    "sg:address":"267 Rte Du Pont # A",
    "sg:city":"Saint-Nicolas",
    "sg:classifiers":[
        {
            "category":"Recreation",
            "type":"Entertainment"
        }
    ],
    "sg:phone":"+1 418 831 3838",
    "sg:postcode":"G7A 2V1",
    "sg:province":"QC",
    "sg:tags":[
        "martial",
        "arts",
        "instruction"
    ],
    "wof:name":"Studios D'Auto Defense",
    "wof:placetype":"venue"
},
  "geometry": {"coordinates":[-71.295975,46.727955],"type":"Point"}
}