{
  "type": "Feature",
  "properties": {
    "addr:full":"North York ON M9M 3A4",
    "addr:postcode":"m9m 3a4",
    "iso:country":"CA",
    "sg:city":"North York",
    "sg:classifiers":[
        {
            "category":"Wholesale",
            "subcategory":"Scrap",
            "type":"Manufacturing & Wholesale Goods"
        }
    ],
    "sg:phone":"+1 416 746 5757",
    "sg:postcode":"M9M 3A4",
    "sg:province":"ON",
    "sg:tags":[
        "recycling",
        "center"
    ],
    "wof:name":"Canadian Diabetes Assn Collctn",
    "wof:placetype":"venue"
},
  "geometry": {"coordinates":[-79.533226,43.735001],"type":"Point"}
}