{
  "type": "Feature",
  "properties": {
    "iso:country":"CA",
    "sg:address":"PO Box 2739 STN B",
    "sg:city":"Prince George",
    "sg:classifiers":[
        {
            "category":"Building & Trades",
            "subcategory":"Plumbing",
            "type":"Services"
        }
    ],
    "sg:phone":"+1 250 563 7557",
    "sg:postcode":"V2N 4T6",
    "sg:province":"BC",
    "sg:tags":[
        "contractor"
    ],
    "wof:name":"Apex Plumbing & Heating",
    "wof:placetype":"venue"
},
  "geometry": {"coordinates":[-122.74508667000001,53.9123497009],"type":"Point"}
}