{
  "type": "Feature",
  "properties": {
    "iso:country":"CA",
    "sg:address":"375 Boul Perrot",
    "sg:city":"L'Ile-Perrot",
    "sg:classifiers":[
        {
            "category":"Shopping",
            "subcategory":"Bicycles & Sporting Goods",
            "type":"Retail Goods"
        }
    ],
    "sg:phone":"+1 514 453 9137",
    "sg:postcode":"J7V 3G7",
    "sg:province":"QC",
    "wof:name":"J P Lemay Cycle Sports",
    "wof:placetype":"venue"
},
  "geometry": {"coordinates":[-73.9482727051,45.3931770325],"type":"Point"}
}