{
  "type": "Feature",
  "properties": {
    "iso:country":"CA",
    "sg:address":"PO Box 9",
    "sg:city":"Wrentham",
    "sg:classifiers":[
        {
            "category":"Organizations",
            "subcategory":"Religious Organization",
            "type":"Services"
        }
    ],
    "sg:phone":"+1 403 222 3944",
    "sg:postcode":"T0K 2P0",
    "sg:province":"AB",
    "sg:tags":[
        "church"
    ],
    "wof:name":"Wrentham Community Church",
    "wof:placetype":"venue"
},
  "geometry": {"coordinates":[-112.180419922,49.5190162659],"type":"Point"}
}