{
  "type": "Feature",
  "properties": {
    "iso:country":"CA",
    "sg:address":"108 Rue Sullivan",
    "sg:city":"Salaberry-DE-Valleyfield",
    "sg:classifiers":[
        {
            "category":"Health Services",
            "subcategory":"Nursing And Care Facility",
            "type":"Services"
        }
    ],
    "sg:phone":"+1 450 373 3272",
    "sg:postcode":"J6S 2J3",
    "sg:province":"QC",
    "sg:tags":[
        "home",
        "retirement",
        "community"
    ],
    "wof:name":"Residence Jeanne D'Arc",
    "wof:placetype":"venue"
},
  "geometry": {"coordinates":[-74.1202011108,45.2612228394],"type":"Point"}
}