{
  "type": "Feature",
  "properties": {
    "addr:full":"Toronto ON M4P 1J5",
    "addr:postcode":"m4p 1j5",
    "iso:country":"CA",
    "sg:city":"Toronto",
    "sg:classifiers":[
        {
            "category":"Professional",
            "subcategory":"Business Services",
            "type":"Services"
        }
    ],
    "sg:phone":"+1 416 482 2992",
    "sg:postcode":"M4P 1J5",
    "sg:province":"ON",
    "sg:tags":[
        "convention",
        "meeting",
        "facility"
    ],
    "wof:name":"Convention Planners Intl Inc",
    "wof:placetype":"venue"
},
  "geometry": {"coordinates":[-79.39250199999999,43.707851],"type":"Point"}
}