{
  "type": "Feature",
  "properties": {
    "addr:full":"2500 Rue Jean-Perrin # 200 Quebec QC G2C 1X1",
    "addr:housenumber":"2500",
    "addr:postcode":"qc g2c 1x1",
    "addr:street":"Rue Jean-Perrin # 200",
    "iso:country":"CA",
    "sg:address":"2500 Rue Jean-Perrin # 200",
    "sg:city":"Quebec",
    "sg:classifiers":[
        {
            "category":"Shopping",
            "subcategory":"Computers & Home Electronics",
            "type":"Retail Goods"
        }
    ],
    "sg:phone":"+1 418 843 8005",
    "sg:postcode":"G2C 1X1",
    "sg:province":"QC",
    "sg:tags":[
        "software"
    ],
    "wof:name":"Eco Systemes Inc",
    "wof:placetype":"venue"
},
  "geometry": {"coordinates":[-71.309235,46.823215],"type":"Point"}
}