{
  "type": "Feature",
  "properties": {
    "addr:full":"4196 4th Ave W Vancouver BC V6R 4J5",
    "addr:housenumber":"4196",
    "addr:postcode":"v6r 4j5",
    "addr:street":"4Th Ave W",
    "iso:country":"CA",
    "sg:address":"4196 4th Ave W",
    "sg:city":"Vancouver",
    "sg:classifiers":[
        {
            "category":"Education",
            "subcategory":"School",
            "type":"Public Place"
        }
    ],
    "sg:phone":"+1 604 224 3663",
    "sg:postcode":"V6R 4J5",
    "sg:province":"BC",
    "wof:name":"Wondertree Learning Ctr",
    "wof:placetype":"venue"
},
  "geometry": {"coordinates":[-123.20038599999999,49.268448],"type":"Point"}
}