{
  "type": "Feature",
  "properties": {
    "addr:full":"Edmonton AB T5J 2W2",
    "addr:postcode":"t5j 2w2",
    "iso:country":"CA",
    "sg:city":"Edmonton",
    "sg:classifiers":[
        {
            "category":"Personal",
            "type":"Services"
        }
    ],
    "sg:phone":"+1 780 423 9191",
    "sg:postcode":"T5J 2W2",
    "sg:province":"AB",
    "sg:tags":[
        "therapist",
        "massage"
    ],
    "wof:name":"Educare Therapeutic Massage",
    "wof:placetype":"venue"
},
  "geometry": {"coordinates":[-113.491844,53.541466],"type":"Point"}
}