{
  "type": "Feature",
  "properties": {
    "iso:country":"CA",
    "sg:address":"261 8E Av",
    "sg:city":"Ferme-Neuve",
    "sg:classifiers":[
        {
            "category":"Manufacturing",
            "subcategory":"Furniture",
            "type":"Manufacturing & Wholesale Goods"
        }
    ],
    "sg:phone":"+1 819 587 3173",
    "sg:postcode":"J0W 1C0",
    "sg:province":"QC",
    "sg:tags":[
        "fixture",
        "door",
        "display"
    ],
    "wof:name":"Vitrerie Ferme-Neuve Inc",
    "wof:placetype":"venue"
},
  "geometry": {"coordinates":[-75.4535827637,46.7011070251],"type":"Point"}
}