{
  "type": "Feature",
  "properties": {
    "addr:full":"Brampton ON L6Y 1Y5",
    "addr:postcode":"l6y 1y5",
    "iso:country":"CA",
    "sg:city":"Brampton",
    "sg:classifiers":[
        {
            "category":"Restaurant",
            "type":"Food & Drink"
        }
    ],
    "sg:phone":"+1 905 459 8687",
    "sg:postcode":"L6Y 1Y5",
    "sg:province":"ON",
    "wof:name":"Joe's Pizzeria & Spaghetti Hse",
    "wof:placetype":"venue"
},
  "geometry": {"coordinates":[-79.762878418,43.6789360046],"type":"Point"}
}