{
  "type": "Feature",
  "properties": {
    "iso:country":"CA",
    "sg:city":"Saint-Leonard",
    "sg:classifiers":[
        {
            "category":"Shopping",
            "subcategory":"Optical Goods",
            "type":"Retail Goods"
        }
    ],
    "sg:phone":"+1 514 327 3891",
    "sg:postcode":"H1R 1A5",
    "sg:province":"QC",
    "wof:name":"Optique Centennial Ltee",
    "wof:placetype":"venue"
},
  "geometry": {"coordinates":[-73.621567,45.586628],"type":"Point"}
}