{
  "type": "Feature",
  "properties": {
    "addr:full":"35 Sunrise Ave Mount Pearl NL A1N 1B6",
    "addr:housenumber":"35",
    "addr:postcode":"a1n 1b6",
    "addr:street":"Sunrise Ave",
    "iso:country":"CA",
    "sg:address":"35 Sunrise Ave",
    "sg:city":"Mount Pearl",
    "sg:classifiers":[
        {
            "category":"Real Estate",
            "subcategory":"Developer",
            "type":"Services"
        }
    ],
    "sg:phone":"+1 709 364 4103",
    "sg:postcode":"A1N 1B6",
    "sg:province":"NL",
    "wof:name":"East Port Properties Ltd",
    "wof:placetype":"venue"
},
  "geometry": {"coordinates":[-52.806286,47.514271],"type":"Point"}
}