{
  "type": "Feature",
  "properties": {
    "addr:full":"1660 White Sails Rd Bowen Island BC V0N 1G0",
    "addr:housenumber":"1660",
    "addr:postcode":"v0n 1g0",
    "addr:street":"White Sails Rd",
    "iso:country":"CA",
    "sg:address":"1660 White Sails Rd",
    "sg:city":"Bowen Island",
    "sg:classifiers":[
        {
            "category":"Professional",
            "subcategory":"Management & Consulting",
            "type":"Services"
        }
    ],
    "sg:phone":"+1 604 947 2789",
    "sg:postcode":"V0N 1G0",
    "sg:province":"BC",
    "sg:tags":[
        "consultant",
        "mining"
    ],
    "wof:name":"P Taggart & Assoc",
    "wof:placetype":"venue"
},
  "geometry": {"coordinates":[-123.41727400000001,49.351189],"type":"Point"}
}