{
  "type": "Feature",
  "properties": {
    "addr:full":"7824 Av DE Gaspe Montreal QC H2R 2A4",
    "addr:housenumber":"7824",
    "addr:postcode":"h2r 2a4",
    "addr:street":"Av De Gaspe",
    "iso:country":"CA",
    "sg:address":"7824 Av DE Gaspe",
    "sg:city":"Montreal",
    "sg:classifiers":[
        {
            "category":"Building & Trades",
            "subcategory":"Electrical",
            "type":"Services"
        }
    ],
    "sg:phone":"+1 514 278 6655",
    "sg:postcode":"H2R 2A4",
    "sg:province":"QC",
    "sg:tags":[
        "electric",
        "contractor"
    ],
    "wof:name":"Constructions Gam Inc",
    "wof:placetype":"venue"
},
  "geometry": {"coordinates":[-73.62603759770001,45.5393333435],"type":"Point"}
}