{
  "type": "Feature",
  "properties": {
    "addr:full":"8820 Rosehill Dr Richmond BC V7A 2K3",
    "addr:housenumber":"8820",
    "addr:postcode":"v7a 2k3",
    "addr:street":"Rosehill Dr",
    "iso:country":"CA",
    "sg:address":"8820 Rosehill Dr",
    "sg:city":"Richmond",
    "sg:classifiers":[
        {
            "category":"Professional",
            "subcategory":"Management & Consulting",
            "type":"Services"
        }
    ],
    "sg:phone":"+1 604 272 2630",
    "sg:postcode":"V7A 2K3",
    "sg:province":"BC",
    "sg:tags":[
        "consultant",
        "business"
    ],
    "wof:name":"Benjamin Tam & Assoc",
    "wof:placetype":"venue"
},
  "geometry": {"coordinates":[-123.12814299999999,49.137089],"type":"Point"}
}