{
  "type": "Feature",
  "properties": {
    "iso:country":"CA",
    "sg:address":"1294 6 Hwy N",
    "sg:city":"Hamilton",
    "sg:classifiers":[
        {
            "category":"Autos & Motor Vehicles",
            "subcategory":"Fuel & Gas Station",
            "type":"Retail Goods"
        }
    ],
    "sg:phone":"+1 905 690 7160",
    "sg:postcode":"L8N 2Z7",
    "sg:province":"ON",
    "sg:tags":[
        "convenience",
        "oil",
        "store"
    ],
    "wof:name":"Gas Rite Variety",
    "wof:placetype":"venue"
},
  "geometry": {"coordinates":[-79.9879455566,43.3638191223],"type":"Point"}
}