{
  "type": "Feature",
  "properties": {
    "addr:full":"2925 Lake Shore Blvd W Etobicoke ON M8V 1J3",
    "addr:housenumber":"2925",
    "addr:postcode":"m8v 1j3",
    "addr:street":"Lake Shore Blvd W",
    "iso:country":"CA",
    "sg:address":"2925 Lake Shore Blvd W",
    "sg:city":"Etobicoke",
    "sg:classifiers":[
        {
            "category":"Restaurant",
            "type":"Food & Drink"
        }
    ],
    "sg:phone":"+1 416 255 2582",
    "sg:postcode":"M8V 1J3",
    "sg:province":"ON",
    "sg:tags":[
        "shop",
        "coffee"
    ],
    "wof:name":"Rocket Fuel Coffee Shop Inc",
    "wof:placetype":"venue"
},
  "geometry": {"coordinates":[-79.5048828125,43.6007347107],"type":"Point"}
}