{
  "type": "Feature",
  "properties": {
    "addr:full":"Chambly QC J3L 4L6",
    "addr:postcode":"j3l 4l6",
    "iso:country":"CA",
    "sg:city":"Chambly",
    "sg:classifiers":[
        {
            "category":"Shopping",
            "type":"Retail Goods"
        }
    ],
    "sg:phone":"+1 450 658 4345",
    "sg:postcode":"J3L 4L6",
    "sg:province":"QC",
    "sg:tags":[
        "enforcement",
        "law",
        "supply"
    ],
    "wof:name":"Qpe Inc",
    "wof:placetype":"venue"
},
  "geometry": {"coordinates":[-73.303062,45.4506],"type":"Point"}
}