{
  "type": "Feature",
  "properties": {
    "addr:full":"5094 Rue Foster Waterloo QC J0E 2N0",
    "addr:housenumber":"5094",
    "addr:postcode":"j0e 2n0",
    "addr:street":"Rue Foster",
    "iso:country":"CA",
    "sg:address":"5094 Rue Foster",
    "sg:city":"Waterloo",
    "sg:classifiers":[
        {
            "category":"Cinema",
            "subcategory":"Movie Rental",
            "type":"Entertainment"
        }
    ],
    "sg:phone":"+1 450 539 5216",
    "sg:postcode":"J0E 2N0",
    "sg:province":"QC",
    "sg:tags":[
        "leasing",
        "video",
        "disc",
        "tape"
    ],
    "wof:name":"Servideo Waterloo",
    "wof:placetype":"venue"
},
  "geometry": {"coordinates":[-72.516441,45.345119],"type":"Point"}
}