{
  "type": "Feature",
  "properties": {
    "iso:country":"CA",
    "sg:address":"1003 Felix Ave",
    "sg:city":"Windsor",
    "sg:classifiers":[
        {
            "category":"Food & Beverages",
            "subcategory":"Groceries & Convenience Stores",
            "type":"Retail Goods"
        }
    ],
    "sg:phone":"+1 519 977 7087",
    "sg:postcode":"N9C 3L4",
    "sg:province":"ON",
    "wof:name":"M & S Convenience",
    "wof:placetype":"venue"
},
  "geometry": {"coordinates":[-83.067589,42.29533],"type":"Point"}
}