{
  "type": "Feature",
  "properties": {
    "addr:full":"3560 Boul Des Entreprises Terrebonne QC J6X 4J8",
    "addr:housenumber":"3560",
    "addr:postcode":"j6x 4j8",
    "addr:street":"Boul Des Entreprises",
    "iso:country":"CA",
    "sg:address":"3560 Boul Des Entreprises",
    "sg:city":"Terrebonne",
    "sg:classifiers":[
        {
            "category":"Freight",
            "type":"Transportation"
        }
    ],
    "sg:phone":"+1 450 477 9174",
    "sg:postcode":"J6X 4J8",
    "sg:province":"QC",
    "sg:tags":[
        "trucking"
    ],
    "wof:name":"Voiturier Demers Inc",
    "wof:placetype":"venue"
},
  "geometry": {"coordinates":[-73.67641399999999,45.730576],"type":"Point"}
}