{
  "type": "Feature",
  "properties": {
    "iso:country":"CA",
    "sg:address":"342 James St",
    "sg:city":"Wallaceburg",
    "sg:classifiers":[
        {
            "category":"Shopping",
            "subcategory":"Florist",
            "type":"Retail Goods"
        }
    ],
    "sg:phone":"+1 519 627 9966",
    "sg:postcode":"N8A 2N5",
    "sg:province":"ON",
    "wof:name":"Victoria's Garden",
    "wof:placetype":"venue"
},
  "geometry": {"coordinates":[-82.3832321167,42.5945968628],"type":"Point"}
}