{
  "type": "Feature",
  "properties": {
    "addr:full":"285 Rue Danis Salaberry-DE-Valleyfield QC J6S 1L8",
    "addr:housenumber":"285",
    "addr:postcode":"j6s 1l8",
    "addr:street":"Rue Danis",
    "iso:country":"CA",
    "sg:address":"285 Rue Danis",
    "sg:city":"Salaberry-DE-Valleyfield",
    "sg:classifiers":[
        {
            "category":"Organizations",
            "subcategory":"Religious Organization",
            "type":"Services"
        }
    ],
    "sg:phone":"+1 450 373 3644",
    "sg:postcode":"J6S 1L8",
    "sg:province":"QC",
    "sg:tags":[
        "church"
    ],
    "wof:name":"Eglise Notre Dame",
    "wof:placetype":"venue"
},
  "geometry": {"coordinates":[-74.1392745972,45.2628707886],"type":"Point"}
}