{
  "type": "Feature",
  "properties": {
    "addr:full":"184 Scott St St Catharines ON L2N 1H1",
    "addr:housenumber":"184",
    "addr:postcode":"l2n 1h1",
    "addr:street":"Scott St",
    "iso:country":"CA",
    "sg:address":"184 Scott St",
    "sg:city":"St Catharines",
    "sg:classifiers":[
        {
            "category":"Food & Beverages",
            "subcategory":"Groceries & Convenience Stores",
            "type":"Retail Goods"
        }
    ],
    "sg:phone":"+1 905 934 0531",
    "sg:postcode":"L2N 1H1",
    "sg:province":"ON",
    "wof:name":"Avondale Stores Ltd",
    "wof:placetype":"venue"
},
  "geometry": {"coordinates":[-79.2470169067,43.1825714111],"type":"Point"}
}