{
  "type": "Feature",
  "properties": {
    "addr:full":"503 Main St Kentville NS B4N 1L4",
    "addr:housenumber":"503",
    "addr:postcode":"b4n 1l4",
    "addr:street":"Main St",
    "iso:country":"CA",
    "sg:address":"503 Main St",
    "sg:city":"Kentville",
    "sg:classifiers":[
        {
            "category":"Organizations",
            "subcategory":"Non-profit Organization",
            "type":"Services"
        }
    ],
    "sg:phone":"+1 902 678 5760",
    "sg:postcode":"B4N 1L4",
    "sg:province":"NS",
    "sg:tags":[
        "charitable",
        "institution"
    ],
    "wof:name":"Kings County Family Resource",
    "wof:placetype":"venue"
},
  "geometry": {"coordinates":[-64.4905166626,45.075756073],"type":"Point"}
}