{
  "type": "Feature",
  "properties": {
    "addr:full":"52 Rue DE L'Industrie L'Assomption QC J5W 2V1",
    "addr:housenumber":"52",
    "addr:postcode":"j5w 2v1",
    "addr:street":"Rue De L'Industrie",
    "iso:country":"CA",
    "sg:address":"52 Rue DE L'Industrie",
    "sg:city":"L'Assomption",
    "sg:classifiers":[
        {
            "category":"Wholesale",
            "subcategory":"Scrap",
            "type":"Manufacturing & Wholesale Goods"
        }
    ],
    "sg:phone":"+1 450 589 7178",
    "sg:postcode":"J5W 2V1",
    "sg:province":"QC",
    "sg:tags":[
        "metal",
        "iron"
    ],
    "wof:name":"Metaux Recupar",
    "wof:placetype":"venue"
},
  "geometry": {"coordinates":[-73.417587,45.833038],"type":"Point"}
}