{
  "type": "Feature",
  "properties": {
    "addr:full":"1070 Rue Rielle Verdun QC H4G 2T3",
    "addr:housenumber":"1070",
    "addr:postcode":"h4g 2t3",
    "addr:street":"Rue Rielle",
    "iso:country":"CA",
    "sg:address":"1070 Rue Rielle",
    "sg:city":"Verdun",
    "sg:classifiers":[
        {
            "category":"Building & Trades",
            "subcategory":"Construction",
            "type":"Services"
        }
    ],
    "sg:phone":"+1 514 761 5245",
    "sg:postcode":"H4G 2T3",
    "sg:province":"QC",
    "sg:tags":[
        "resurfacing",
        "laying",
        "refinishing",
        "floor"
    ],
    "wof:name":"Planchers Raymond Bosse",
    "wof:placetype":"venue"
},
  "geometry": {"coordinates":[-73.5783157349,45.4604644775],"type":"Point"}
}