{
  "type": "Feature",
  "properties": {
    "addr:full":"Manseau QC G0X 1V0",
    "addr:postcode":"g0x 1v0",
    "iso:country":"CA",
    "sg:city":"Manseau",
    "sg:classifiers":[
        {
            "category":"Government",
            "subcategory":"Office",
            "type":"Public Place"
        }
    ],
    "sg:phone":"+1 819 356 2450",
    "sg:postcode":"G0X 1V0",
    "sg:province":"QC",
    "sg:tags":[
        "village"
    ],
    "wof:name":"Manseau Municipale",
    "wof:placetype":"venue"
},
  "geometry": {"coordinates":[-72.00318900000001,46.366165],"type":"Point"}
}