{
  "type": "Feature",
  "properties": {
    "addr:full":"St-Edouard Saint-Germain-DE-Grantham QC J0C 1K0",
    "addr:postcode":"j0c 1k0",
    "addr:street":"St-Edouard",
    "iso:country":"CA",
    "sg:address":"St-Edouard",
    "sg:city":"Saint-Germain-DE-Grantham",
    "sg:classifiers":[
        {
            "category":"Sports & Exercise",
            "subcategory":"Bowling",
            "type":"Entertainment"
        }
    ],
    "sg:phone":"+1 819 395 4262",
    "sg:postcode":"J0C 1K0",
    "sg:province":"QC",
    "sg:tags":[
        "center"
    ],
    "wof:name":"Salle DE Quilles St-Germain",
    "wof:placetype":"venue"
},
  "geometry": {"coordinates":[-72.569199,45.839954],"type":"Point"}
}