{
  "type": "Feature",
  "properties": {
    "iso:country":"CA",
    "sg:address":"3684 Highway 11 N",
    "sg:city":"North Bay",
    "sg:classifiers":[
        {
            "category":"Autos & Motor Vehicles",
            "subcategory":"Auto Supplies",
            "type":"Retail Goods"
        }
    ],
    "sg:phone":"+1 705 497 9459",
    "sg:postcode":"P1B 8G3",
    "sg:province":"ON",
    "sg:tags":[
        "tire"
    ],
    "wof:name":"Independent Tire Svc",
    "wof:placetype":"venue"
},
  "geometry": {"coordinates":[-79.4599304199,46.3066291809],"type":"Point"}
}