{
  "type": "Feature",
  "properties": {
    "addr:full":"79 Wingold Ave North York ON M6B 1P8",
    "addr:housenumber":"79",
    "addr:postcode":"m6b 1p8",
    "addr:street":"Wingold Ave",
    "iso:country":"CA",
    "sg:address":"79 Wingold Ave",
    "sg:city":"North York",
    "sg:classifiers":[
        {
            "category":"Shopping",
            "subcategory":"Clothing, Apparel, & Fashions",
            "type":"Retail Goods"
        }
    ],
    "sg:phone":"+1 416 256 4784",
    "sg:postcode":"M6B 1P8",
    "sg:province":"ON",
    "sg:tags":[
        "wear",
        "formal"
    ],
    "wof:name":"Syd Silver Formals Ltd",
    "wof:placetype":"venue"
},
  "geometry": {"coordinates":[-79.457764,43.702484],"type":"Point"}
}