{
  "type": "Feature",
  "properties": {
    "addr:full":"30 Woodrow Ave Toronto ON M4C 5S2",
    "addr:housenumber":"30",
    "addr:postcode":"m4c 5s2",
    "addr:street":"Woodrow Ave",
    "iso:country":"CA",
    "sg:address":"30 Woodrow Ave",
    "sg:city":"Toronto",
    "sg:classifiers":[
        {
            "category":"Education",
            "subcategory":"Vocational School",
            "type":"Public Place"
        }
    ],
    "sg:phone":"+1 416 691 6636",
    "sg:postcode":"M4C 5S2",
    "sg:province":"ON",
    "sg:tags":[
        "training",
        "computer"
    ],
    "wof:name":"Creative Training & Dev Inc",
    "wof:placetype":"venue"
},
  "geometry": {"coordinates":[-79.321861,43.682297],"type":"Point"}
}