{
  "type": "Feature",
  "properties": {
    "addr:full":"2450 Boul Laurier Sainte-Foy QC G1V 2L1",
    "addr:housenumber":"2450",
    "addr:postcode":"g1v 2l1",
    "addr:street":"Boul Laurier",
    "iso:country":"CA",
    "sg:address":"2450 Boul Laurier",
    "sg:city":"Sainte-Foy",
    "sg:classifiers":[
        {
            "category":"Professional",
            "type":"Services"
        }
    ],
    "sg:phone":"+1 418 652 8817",
    "sg:postcode":"G1V 2L1",
    "sg:province":"QC",
    "sg:tags":[
        "apparel",
        "establishment"
    ],
    "wof:name":"R W CO",
    "wof:placetype":"venue"
},
  "geometry": {"coordinates":[-71.276260376,46.7737045288],"type":"Point"}
}