{
  "type": "Feature",
  "properties": {
    "addr:full":"1242 Rue Chambly Marieville QC J3M 1H4",
    "addr:housenumber":"1242",
    "addr:postcode":"j3m 1h4",
    "addr:street":"Rue Chambly",
    "iso:country":"CA",
    "sg:address":"1242 Rue Chambly",
    "sg:city":"Marieville",
    "sg:classifiers":[
        {
            "category":"Health Services",
            "subcategory":"Optometrist",
            "type":"Services"
        }
    ],
    "sg:phone":"+1 450 460 4456",
    "sg:postcode":"J3M 1H4",
    "sg:province":"QC",
    "wof:name":"Tougas, Johanne OD",
    "wof:placetype":"venue"
},
  "geometry": {"coordinates":[-73.1635437012,45.4329528809],"type":"Point"}
}