{
  "type": "Feature",
  "properties": {
    "addr:full":"1989 Marine Dr North Vancouver BC V7P 3N5",
    "addr:housenumber":"1989",
    "addr:postcode":"v7p 3n5",
    "addr:street":"Marine Dr",
    "iso:country":"CA",
    "sg:address":"1989 Marine Dr",
    "sg:city":"North Vancouver",
    "sg:classifiers":[
        {
            "category":"Sports & Exercise",
            "subcategory":"Gym",
            "type":"Entertainment"
        }
    ],
    "sg:phone":"+1 604 986 3487",
    "sg:postcode":"V7P 3N5",
    "sg:province":"BC",
    "sg:tags":[
        "club",
        "health",
        "studio",
        "gymnasium"
    ],
    "wof:name":"Fitness World",
    "wof:placetype":"venue"
},
  "geometry": {"coordinates":[-123.121933,49.323898],"type":"Point"}
}