{
  "type": "Feature",
  "properties": {
    "addr:full":"15145 111 Ave NW Edmonton AB T5M 2R1",
    "addr:housenumber":"15145",
    "addr:postcode":"t5m 2r1",
    "addr:street":"111 Ave Nw",
    "iso:country":"CA",
    "sg:address":"15145 111 Ave NW",
    "sg:city":"Edmonton",
    "sg:classifiers":[
        {
            "category":"Travel",
            "subcategory":"Hotels & Motels",
            "type":"Entertainment"
        }
    ],
    "sg:phone":"+1 780 489 2581",
    "sg:postcode":"T5M 2R1",
    "sg:province":"AB",
    "wof:name":"Aurora Motel",
    "wof:placetype":"venue"
},
  "geometry": {"coordinates":[-113.58201599100001,53.5585594177],"type":"Point"}
}