{
  "type": "Feature",
  "properties": {
    "addr:full":"133 Colborne St W Lindsay ON K9V 3T6",
    "addr:housenumber":"133",
    "addr:postcode":"k9v 3t6",
    "addr:street":"Colborne St W",
    "iso:country":"CA",
    "sg:address":"133 Colborne St W",
    "sg:city":"Lindsay",
    "sg:classifiers":[
        {
            "category":"Real Estate",
            "subcategory":"Real Estate Operator",
            "type":"Services"
        }
    ],
    "sg:phone":"+1 705 324 2708",
    "sg:postcode":"K9V 3T6",
    "sg:province":"ON",
    "sg:tags":[
        "apartment"
    ],
    "wof:name":"Colborne Lodge Inc",
    "wof:placetype":"venue"
},
  "geometry": {"coordinates":[-78.750961,44.357868],"type":"Point"}
}