{
  "type": "Feature",
  "properties": {
    "addr:full":"8384 Woodbine Ave Markham ON L3R 2N8",
    "addr:housenumber":"8384",
    "addr:postcode":"l3r 2n8",
    "addr:street":"Woodbine Ave",
    "iso:country":"CA",
    "sg:address":"8384 Woodbine Ave",
    "sg:city":"Markham",
    "sg:classifiers":[
        {
            "category":"Restaurant",
            "type":"Food & Drink"
        }
    ],
    "sg:phone":"+1 905 948 0897",
    "sg:postcode":"L3R 2N8",
    "sg:province":"ON",
    "wof:name":"Prime Burger Inc",
    "wof:placetype":"venue"
},
  "geometry": {"coordinates":[-79.357506,43.846916],"type":"Point"}
}