{
  "type": "Feature",
  "properties": {
    "addr:full":"Edmonton AB T6E 5Y4",
    "addr:postcode":"t6e 5y4",
    "iso:country":"CA",
    "sg:city":"Edmonton",
    "sg:classifiers":[
        {
            "category":"Manufacturing",
            "subcategory":"Metals",
            "type":"Manufacturing & Wholesale Goods"
        }
    ],
    "sg:phone":"+1 780 438 3267",
    "sg:postcode":"T6E 5Y4",
    "sg:province":"AB",
    "sg:tags":[
        "heat",
        "exchanger"
    ],
    "wof:name":"Hudson Products Corp",
    "wof:placetype":"venue"
},
  "geometry": {"coordinates":[-113.47772999999999,53.479038],"type":"Point"}
}