{
  "type": "Feature",
  "properties": {
    "addr:full":"Edmonton AB T5J 0G5",
    "addr:postcode":"t5j 0g5",
    "iso:country":"CA",
    "sg:city":"Edmonton",
    "sg:classifiers":[
        {
            "category":"Shopping",
            "subcategory":"Bicycles & Sporting Goods",
            "type":"Retail Goods"
        }
    ],
    "sg:phone":"+1 780 428 7044",
    "sg:postcode":"T5J 0G5",
    "sg:province":"AB",
    "wof:name":"Eddie Bauer Outdoor Outfitter",
    "wof:placetype":"venue"
},
  "geometry": {"coordinates":[-113.49176788299999,53.5445365906],"type":"Point"}
}