{
  "type": "Feature",
  "properties": {
    "iso:country":"CA",
    "sg:address":"3931 Highland Dr",
    "sg:city":"Prince George",
    "sg:classifiers":[
        {
            "category":"Travel",
            "subcategory":"Hotels & Motels",
            "type":"Entertainment"
        }
    ],
    "sg:phone":"+1 250 561 2337",
    "sg:postcode":"V2K 3R1",
    "sg:province":"BC",
    "sg:tags":[
        "breakfast",
        "accommodation",
        "bed"
    ],
    "wof:name":"Prince George B & B Assn",
    "wof:placetype":"venue"
},
  "geometry": {"coordinates":[-122.795326233,53.9801177979],"type":"Point"}
}