{
  "type": "Feature",
  "properties": {
    "iso:country":"CA",
    "sg:address":"1475 Walsh St W",
    "sg:city":"Thunder Bay",
    "sg:classifiers":[
        {
            "category":"Travel",
            "subcategory":"Travel Agent",
            "type":"Entertainment"
        }
    ],
    "sg:phone":"+1 807 473 5955",
    "sg:postcode":"P7E 4X6",
    "sg:province":"ON",
    "sg:tags":[
        "agency",
        "bureau"
    ],
    "wof:name":"Happy Time Tours & Travel",
    "wof:placetype":"venue"
},
  "geometry": {"coordinates":[-89.304466,48.372154],"type":"Point"}
}