{
  "type": "Feature",
  "properties": {
    "addr:full":"1860 Barton St E Hamilton ON L8H 2Y6",
    "addr:housenumber":"1860",
    "addr:postcode":"l8h 2y6",
    "addr:street":"Barton St E",
    "iso:country":"CA",
    "sg:address":"1860 Barton St E",
    "sg:city":"Hamilton",
    "sg:classifiers":[
        {
            "category":"Organizations",
            "subcategory":"Membership Organization",
            "type":"Services"
        }
    ],
    "sg:phone":"+1 905 549 8191",
    "sg:postcode":"L8H 2Y6",
    "sg:province":"ON",
    "sg:tags":[
        "club"
    ],
    "wof:name":"Loyal Order of Moose Lodge",
    "wof:placetype":"venue"
},
  "geometry": {"coordinates":[-79.78521000000001,43.244041],"type":"Point"}
}