{
  "type": "Feature",
  "properties": {
    "addr:full":"4201 53rd St Forestburg AB T0B 1N0",
    "addr:housenumber":"4201",
    "addr:postcode":"t0b 1n0",
    "addr:street":"53Rd St",
    "iso:country":"CA",
    "sg:address":"4201 53rd St",
    "sg:city":"Forestburg",
    "sg:classifiers":[
        {
            "category":"Retail",
            "subcategory":"Veterinary Services",
            "type":"Services"
        }
    ],
    "sg:phone":"+1 780 582 3970",
    "sg:postcode":"T0B 1N0",
    "sg:province":"AB",
    "sg:tags":[
        "veterinarian"
    ],
    "wof:name":"Forestburg Veterinary Clinic",
    "wof:placetype":"venue"
},
  "geometry": {"coordinates":[-112.068199158,52.5801086426],"type":"Point"}
}