{
  "type": "Feature",
  "properties": {
    "iso:country":"CA",
    "sg:city":"Ottawa",
    "sg:classifiers":[
        {
            "category":"Shopping",
            "subcategory":"Books",
            "type":"Retail Goods"
        }
    ],
    "sg:phone":"+1 613 241 6999",
    "sg:postcode":"K1N 8W5",
    "sg:province":"ON",
    "sg:tags":[
        "dealer"
    ],
    "wof:name":"Librairie Du Soleil",
    "wof:placetype":"venue"
},
  "geometry": {"coordinates":[-75.69296264650001,45.4268798828],"type":"Point"}
}