{
  "type": "Feature",
  "properties": {
    "addr:full":"34 Rue Claude Vaudreuil-Dorion QC J7V 8P5",
    "addr:housenumber":"34",
    "addr:postcode":"j7v 8p5",
    "addr:street":"Rue Claude",
    "iso:country":"CA",
    "sg:address":"34 Rue Claude",
    "sg:city":"Vaudreuil-Dorion",
    "sg:classifiers":[
        {
            "category":"Real Estate",
            "subcategory":"Developer",
            "type":"Services"
        }
    ],
    "sg:phone":"+1 450 455 0007",
    "sg:postcode":"J7V 8P5",
    "sg:province":"QC",
    "sg:tags":[
        "company",
        "land"
    ],
    "wof:name":"Sentier Du Chevreuil",
    "wof:placetype":"venue"
},
  "geometry": {"coordinates":[-74.0525817871,45.4178771973],"type":"Point"}
}