{
  "type": "Feature",
  "properties": {
    "addr:full":"109 Erb St W Waterloo ON N2L 1T4",
    "addr:housenumber":"109",
    "addr:postcode":"n2l 1t4",
    "addr:street":"Erb St W",
    "iso:country":"CA",
    "sg:address":"109 Erb St W",
    "sg:city":"Waterloo",
    "sg:classifiers":[
        {
            "category":"Professional",
            "subcategory":"Lawyer & Legal Services",
            "type":"Services"
        }
    ],
    "sg:phone":"+1 519 883 1844",
    "sg:postcode":"N2L 1T4",
    "sg:province":"ON",
    "sg:tags":[
        "attorney"
    ],
    "wof:name":"Fedy, Tim",
    "wof:placetype":"venue"
},
  "geometry": {"coordinates":[-80.52862548829999,43.4628143311],"type":"Point"}
}