{
  "type": "Feature",
  "properties": {
    "addr:full":"7417 67 St NW Edmonton AB T6B 2J3",
    "addr:housenumber":"7417",
    "addr:postcode":"t6b 2j3",
    "addr:street":"67 St Nw",
    "iso:country":"CA",
    "sg:address":"7417 67 St NW",
    "sg:city":"Edmonton",
    "sg:classifiers":[
        {
            "category":"Retail",
            "subcategory":"Auto Repair",
            "type":"Services"
        }
    ],
    "sg:phone":"+1 780 448 9727",
    "sg:postcode":"T6B 2J3",
    "sg:province":"AB",
    "sg:tags":[
        "truck"
    ],
    "wof:name":"Economical Mechanical Repair",
    "wof:placetype":"venue"
},
  "geometry": {"coordinates":[-113.430358887,53.5104064941],"type":"Point"}
}