{
  "type": "Feature",
  "properties": {
    "addr:full":"Ottawa ON K1H 8P5",
    "addr:postcode":"k1h 8p5",
    "iso:country":"CA",
    "sg:city":"Ottawa",
    "sg:classifiers":[
        {
            "category":"Professional",
            "subcategory":"Engineering",
            "type":"Services"
        }
    ],
    "sg:phone":"+1 613 737 7745",
    "sg:postcode":"K1H 8P5",
    "sg:province":"ON",
    "sg:tags":[
        "engineer"
    ],
    "wof:name":"Lci Engineering Inc",
    "wof:placetype":"venue"
},
  "geometry": {"coordinates":[-75.629379,45.380459],"type":"Point"}
}