{
  "type": "Feature",
  "properties": {
    "addr:full":"Ottawa ON K2P 1P5",
    "addr:postcode":"k2p 1p5",
    "iso:country":"CA",
    "sg:city":"Ottawa",
    "sg:classifiers":[
        {
            "category":"Health Services",
            "subcategory":"Doctor",
            "type":"Services"
        }
    ],
    "sg:phone":"+1 613 233 3030",
    "sg:postcode":"K2P 1P5",
    "sg:province":"ON",
    "sg:tags":[
        "physician",
        "surgeon"
    ],
    "wof:name":"Fireman, H H MD",
    "wof:placetype":"venue"
},
  "geometry": {"coordinates":[-75.69416,45.418812],"type":"Point"}
}