{
  "type": "Feature",
  "properties": {
    "addr:full":"Repentigny QC J5Y 1B6",
    "addr:postcode":"j5y 1b6",
    "iso:country":"CA",
    "sg:city":"Repentigny",
    "sg:classifiers":[
        {
            "category":"Recreation",
            "type":"Entertainment"
        }
    ],
    "sg:phone":"+1 450 581 0725",
    "sg:postcode":"J5Y 1B6",
    "sg:province":"QC",
    "sg:tags":[
        "instruction",
        "golf"
    ],
    "wof:name":"Ecole DE Golf Pierre Picard",
    "wof:placetype":"venue"
},
  "geometry": {"coordinates":[-73.42580413819999,45.7589836121],"type":"Point"}
}