{
  "type": "Feature",
  "properties": {
    "addr:full":"104 Haylmore Ave Gold Bridge BC V0K 1P0",
    "addr:housenumber":"104",
    "addr:postcode":"v0k 1p0",
    "addr:street":"Haylmore Ave",
    "iso:country":"CA",
    "sg:address":"104 Haylmore Ave",
    "sg:city":"Gold Bridge",
    "sg:classifiers":[
        {
            "category":"Professional",
            "subcategory":"Management & Consulting",
            "type":"Services"
        }
    ],
    "sg:phone":"+1 250 238 2534",
    "sg:postcode":"V0K 1P0",
    "sg:province":"BC",
    "sg:tags":[
        "development",
        "economic",
        "agency"
    ],
    "wof:name":"Bridge River Valley Economic",
    "wof:placetype":"venue"
},
  "geometry": {"coordinates":[-122.849098,50.85136],"type":"Point"}
}