{
  "type": "Feature",
  "properties": {
    "addr:full":"55 St. Peters Rd Charlottetown PE C1A 5N6",
    "addr:housenumber":"55",
    "addr:postcode":"c1a 5n6",
    "addr:street":"St. Peters Rd",
    "iso:country":"CA",
    "sg:address":"55 St. Peters Rd",
    "sg:city":"Charlottetown",
    "sg:classifiers":[
        {
            "category":"Personal",
            "subcategory":"Tattoo Parlor",
            "type":"Services"
        }
    ],
    "sg:phone":"+1 902 626 3861",
    "sg:postcode":"C1A 5N6",
    "sg:province":"PE",
    "sg:tags":[
        "tattooing"
    ],
    "wof:name":"Eternal Dragon Tattoo",
    "wof:placetype":"venue"
},
  "geometry": {"coordinates":[-63.1225395203,46.2495651245],"type":"Point"}
}