{
  "type": "Feature",
  "properties": {
    "addr:full":"8522 Davies Rd NW Edmonton AB T6E 4Y5",
    "addr:housenumber":"8522",
    "addr:postcode":"t6e 4y5",
    "addr:street":"Davies Rd Nw",
    "iso:country":"CA",
    "sg:address":"8522 Davies Rd NW",
    "sg:city":"Edmonton",
    "sg:classifiers":[
        {
            "category":"Manufacturing",
            "subcategory":"Tools & Machinery",
            "type":"Manufacturing & Wholesale Goods"
        }
    ],
    "sg:phone":"+1 780 466 9466",
    "sg:postcode":"T6E 4Y5",
    "sg:province":"AB",
    "sg:tags":[
        "machine",
        "shop"
    ],
    "wof:name":"Flexcim Services Inc",
    "wof:placetype":"venue"
},
  "geometry": {"coordinates":[-113.453514099,53.4940948486],"type":"Point"}
}