{
  "type": "Feature",
  "properties": {
    "addr:full":"2379 Hwy 2 Bowmanville ON L1C 5A4",
    "addr:housenumber":"2379",
    "addr:postcode":"l1c 5a4",
    "addr:street":"Hwy 2",
    "iso:country":"CA",
    "sg:address":"2379 Hwy 2",
    "sg:city":"Bowmanville",
    "sg:classifiers":[
        {
            "category":"Food & Beverages",
            "subcategory":"Groceries & Convenience Stores",
            "type":"Retail Goods"
        }
    ],
    "sg:phone":"+1 905 623 3662",
    "sg:postcode":"L1C 5A4",
    "sg:province":"ON",
    "sg:tags":[
        "product"
    ],
    "wof:name":"Bulk Barn",
    "wof:placetype":"venue"
},
  "geometry": {"coordinates":[-78.7094573975,43.9094085693],"type":"Point"}
}