{
  "type": "Feature",
  "properties": {
    "iso:country":"CA",
    "sg:address":"2379 Hwy 2",
    "sg:city":"Bowmanville",
    "sg:classifiers":[
        {
            "category":"Food & Beverages",
            "subcategory":"Groceries & Convenience Stores",
            "type":"Retail Goods"
        }
    ],
    "sg:phone":"+1 905 623 3662",
    "sg:postcode":"L1C 5A4",
    "sg:province":"ON",
    "sg:tags":[
        "product"
    ],
    "wof:name":"Bulk Barn",
    "wof:placetype":"venue"
},
  "geometry": {"coordinates":[-78.7094573975,43.9094085693],"type":"Point"}
}