{
  "type": "Feature",
  "properties": {
    "addr:full":"924 Rue Angers Saint-Bruno QC J3V 3N8",
    "addr:housenumber":"924",
    "addr:postcode":"j3v 3n8",
    "addr:street":"Rue Angers",
    "iso:country":"CA",
    "sg:address":"924 Rue Angers",
    "sg:city":"Saint-Bruno",
    "sg:classifiers":[
        {
            "category":"Building & Trades",
            "subcategory":"Plumbing",
            "type":"Services"
        }
    ],
    "sg:phone":"+1 450 653 6016",
    "sg:postcode":"J3V 3N8",
    "sg:province":"QC",
    "sg:tags":[
        "refrigeration",
        "appliance",
        "contractor"
    ],
    "wof:name":"Adc Refrigeration Enr",
    "wof:placetype":"venue"
},
  "geometry": {"coordinates":[-71.67552185060001,48.4717712402],"type":"Point"}
}