{
  "type": "Feature",
  "properties": {
    "addr:full":"14812 Hwy 43 Finch ON K0C 1K0",
    "addr:housenumber":"14812",
    "addr:postcode":"k0c 1k0",
    "addr:street":"Hwy 43",
    "iso:country":"CA",
    "sg:address":"14812 Hwy 43",
    "sg:city":"Finch",
    "sg:classifiers":[
        {
            "category":"Shopping",
            "subcategory":"Gifts & Souvenirs",
            "type":"Retail Goods"
        }
    ],
    "sg:phone":"+1 613 984 2050",
    "sg:postcode":"K0C 1K0",
    "sg:province":"ON",
    "sg:tags":[
        "shop"
    ],
    "wof:name":"Karen's Tv & Appliances",
    "wof:placetype":"venue"
},
  "geometry": {"coordinates":[-75.1080856323,45.1343193054],"type":"Point"}
}