{
  "type": "Feature",
  "properties": {
    "addr:full":"683 Main St Moncton NB E1C 1E3",
    "addr:housenumber":"683",
    "addr:postcode":"e1c 1e3",
    "addr:street":"Main St",
    "iso:country":"CA",
    "sg:address":"683 Main St",
    "sg:city":"Moncton",
    "sg:classifiers":[
        {
            "category":"Restaurant",
            "type":"Food & Drink"
        }
    ],
    "sg:phone":"+1 506 855 7672",
    "sg:postcode":"E1C 1E3",
    "sg:province":"NB",
    "wof:name":"Mexicali Rosa's",
    "wof:placetype":"venue"
},
  "geometry": {"coordinates":[-64.776077,46.088951],"type":"Point"}
}