{
  "type": "Feature",
  "properties": {
    "addr:full":"317 Bank St Ottawa ON K2P 1X9",
    "addr:housenumber":"317",
    "addr:postcode":"k2p 1x9",
    "addr:street":"Bank St",
    "iso:country":"CA",
    "sg:address":"317 Bank St",
    "sg:city":"Ottawa",
    "sg:classifiers":[
        {
            "category":"Bars & Pubs",
            "type":"Food & Drink"
        }
    ],
    "sg:phone":"+1 613 594 0003",
    "sg:postcode":"K2P 1X9",
    "sg:province":"ON",
    "sg:tags":[
        "club",
        "night"
    ],
    "wof:name":"Babylon",
    "wof:placetype":"venue"
},
  "geometry": {"coordinates":[-75.695564,45.414658],"type":"Point"}
}