{
  "type": "Feature",
  "properties": {
    "addr:full":"1396 Wallbridge-Loyalist Rd Belleville ON K8N 4Z5",
    "addr:housenumber":"1396",
    "addr:postcode":"k8n 4z5",
    "addr:street":"Wallbridge-Loyalist Rd",
    "iso:country":"CA",
    "sg:address":"1396 Wallbridge-Loyalist Rd",
    "sg:city":"Belleville",
    "sg:classifiers":[
        {
            "category":"Health Services",
            "subcategory":"Chiropractor",
            "type":"Services"
        }
    ],
    "sg:phone":"+1 613 967 6351",
    "sg:postcode":"K8N 4Z5",
    "sg:province":"ON",
    "wof:name":"Tucker's Woods Chiropractic",
    "wof:placetype":"venue"
},
  "geometry": {"coordinates":[-77.436066,44.157688],"type":"Point"}
}