{
  "type": "Feature",
  "properties": {
    "addr:full":"4338 50 Ave Olds AB T4H 1A5",
    "addr:housenumber":"4338",
    "addr:postcode":"t4h 1a5",
    "addr:street":"50 Ave",
    "iso:country":"CA",
    "sg:address":"4338 50 Ave",
    "sg:city":"Olds",
    "sg:classifiers":[
        {
            "category":"Wholesale",
            "subcategory":"Machinery & Supplies",
            "type":"Manufacturing & Wholesale Goods"
        }
    ],
    "sg:phone":"+1 403 556 6711",
    "sg:postcode":"T4H 1A5",
    "sg:province":"AB",
    "sg:tags":[
        "farm",
        "equipment"
    ],
    "wof:name":"Future Ag Inc",
    "wof:placetype":"venue"
},
  "geometry": {"coordinates":[-114.10179100000001,51.799187],"type":"Point"}
}