{
  "type": "Feature",
  "properties": {
    "addr:full":"1703 22nd Ave NE Swift Current SK S9H 5B7",
    "addr:housenumber":"1703",
    "addr:postcode":"s9h 5b7",
    "addr:street":"22Nd Ave Ne",
    "iso:country":"CA",
    "sg:address":"1703 22nd Ave NE",
    "sg:city":"Swift Current",
    "sg:classifiers":[
        {
            "category":"Organizations",
            "subcategory":"Professional Association",
            "type":"Services"
        }
    ],
    "sg:phone":"+1 306 773 7268",
    "sg:postcode":"S9H 5B7",
    "sg:province":"SK",
    "sg:tags":[
        "chambers",
        "commerce"
    ],
    "wof:name":"Chamber of Commerce",
    "wof:placetype":"venue"
},
  "geometry": {"coordinates":[-107.77480300000001,50.306461],"type":"Point"}
}