{
  "type": "Feature",
  "properties": {
    "addr:full":"5300 86 Ave SE Calgary AB T2C 4L7",
    "addr:housenumber":"5300",
    "addr:postcode":"t2c 4l7",
    "addr:street":"86 Ave Se",
    "iso:country":"CA",
    "sg:address":"5300 86 Ave SE",
    "sg:city":"Calgary",
    "sg:classifiers":[
        {
            "category":"Freight",
            "type":"Transportation"
        }
    ],
    "sg:phone":"+1 403 279 4800",
    "sg:postcode":"T2C 4L7",
    "sg:province":"AB",
    "sg:tags":[
        "trucking"
    ],
    "wof:name":"Rosenau Transport Ltd",
    "wof:placetype":"venue"
},
  "geometry": {"coordinates":[-113.957199097,50.9755516052],"type":"Point"}
}