{
  "type": "Feature",
  "properties": {
    "addr:full":"Delta BC V3M 5R6",
    "addr:postcode":"v3m 5r6",
    "iso:country":"CA",
    "sg:city":"Delta",
    "sg:classifiers":[
        {
            "category":"Manufacturing",
            "subcategory":"Rubber & Plastics",
            "type":"Manufacturing & Wholesale Goods"
        }
    ],
    "sg:phone":"+1 604 523 1804",
    "sg:postcode":"V3M 5R6",
    "sg:province":"BC",
    "sg:tags":[
        "forming"
    ],
    "wof:name":"Power Packaging",
    "wof:placetype":"venue"
},
  "geometry": {"coordinates":[-122.94107099999999,49.17448],"type":"Point"}
}