{
  "type": "Feature",
  "properties": {
    "addr:full":"23 Chartwell Lane Halifax NS B3M 3S7",
    "addr:housenumber":"23",
    "addr:postcode":"b3m 3s7",
    "addr:street":"Chartwell Lane",
    "iso:country":"CA",
    "sg:address":"23 Chartwell Lane",
    "sg:city":"Halifax",
    "sg:classifiers":[
        {
            "category":"Shopping",
            "subcategory":"Hobbies, Toys, & Games",
            "type":"Retail Goods"
        }
    ],
    "sg:phone":"+1 902 445 4644",
    "sg:postcode":"B3M 3S7",
    "sg:province":"NS",
    "sg:tags":[
        "craft",
        "supply"
    ],
    "wof:name":"Highland Heart Hookery",
    "wof:placetype":"venue"
},
  "geometry": {"coordinates":[-63.651436,44.665382],"type":"Point"}
}