{
  "type": "Feature",
  "properties": {
    "iso:country":"CA",
    "sg:city":"Calgary",
    "sg:classifiers":[
        {
            "category":"Organizations",
            "subcategory":"Professional Association",
            "type":"Services"
        }
    ],
    "sg:phone":"+1 403 291 3710",
    "sg:postcode":"T2E 7J2",
    "sg:province":"AB",
    "wof:name":"Alberta Construction Sfty Assn",
    "wof:placetype":"venue"
},
  "geometry": {"coordinates":[-114.02544403100001,51.076423645],"type":"Point"}
}