{
  "type": "Feature",
  "properties": {
    "addr:full":"5 Victoria St Marmora ON K0K 2M0",
    "addr:housenumber":"5",
    "addr:postcode":"k0k 2m0",
    "addr:street":"Victoria St",
    "iso:country":"CA",
    "sg:address":"5 Victoria St",
    "sg:city":"Marmora",
    "sg:classifiers":[
        {
            "category":"Retail",
            "subcategory":"Auto Repair",
            "type":"Services"
        }
    ],
    "sg:phone":"+1 613 472 0357",
    "sg:postcode":"K0K 2M0",
    "sg:province":"ON",
    "sg:tags":[
        "repairing",
        "automobile"
    ],
    "wof:name":"Wayne's Auto Svc",
    "wof:placetype":"venue"
},
  "geometry": {"coordinates":[-77.678291,44.485268],"type":"Point"}
}