{
  "type": "Feature",
  "properties": {
    "addr:full":"665 Dupont St Toronto ON M6G 1Z5",
    "addr:housenumber":"665",
    "addr:postcode":"m6g 1z5",
    "addr:street":"Dupont St",
    "iso:country":"CA",
    "sg:address":"665 Dupont St",
    "sg:city":"Toronto",
    "sg:classifiers":[
        {
            "category":"Manufacturing",
            "subcategory":"Wood Products",
            "type":"Manufacturing & Wholesale Goods"
        }
    ],
    "sg:phone":"+1 416 532 7031",
    "sg:postcode":"M6G 1Z5",
    "sg:province":"ON",
    "sg:tags":[
        "picture",
        "frame"
    ],
    "wof:name":"Elgin Picture & Frame Inc",
    "wof:placetype":"venue"
},
  "geometry": {"coordinates":[-79.421722,43.671459],"type":"Point"}
}