{
  "type": "Feature",
  "properties": {
    "addr:full":"1361 16th Ave Campbell River BC V9W 2C9",
    "addr:housenumber":"1361",
    "addr:postcode":"v9w 2c9",
    "addr:street":"16Th Ave",
    "iso:country":"CA",
    "sg:address":"1361 16th Ave",
    "sg:city":"Campbell River",
    "sg:classifiers":[
        {
            "category":"Restaurant",
            "type":"Food & Drink"
        }
    ],
    "sg:phone":"+1 250 287 2631",
    "sg:postcode":"V9W 2C9",
    "sg:province":"BC",
    "wof:name":"Mc Donald's",
    "wof:placetype":"venue"
},
  "geometry": {"coordinates":[-125.246353149,50.0295639038],"type":"Point"}
}