{
  "type": "Feature",
  "properties": {
    "addr:full":"6887 Rochdale Blvd Regina SK S4X 2Z2",
    "addr:housenumber":"6887",
    "addr:postcode":"s4x 2z2",
    "addr:street":"Rochdale Blvd",
    "iso:country":"CA",
    "sg:address":"6887 Rochdale Blvd",
    "sg:city":"Regina",
    "sg:classifiers":[
        {
            "category":"Autos & Motor Vehicles",
            "subcategory":"Fuel & Gas Station",
            "type":"Retail Goods"
        }
    ],
    "sg:phone":"+1 306 791 6363",
    "sg:postcode":"S4X 2Z2",
    "sg:province":"SK",
    "sg:tags":[
        "convenience",
        "oil",
        "store"
    ],
    "wof:name":"Klein's Food Mart",
    "wof:placetype":"venue"
},
  "geometry": {"coordinates":[-104.679596,50.494698],"type":"Point"}
}