{
  "type": "Feature",
  "properties": {
    "addr:full":"4710 Rue Saint-Ambroise # 104 Montreal QC H4C 2C7",
    "addr:housenumber":"4710",
    "addr:postcode":"h4c 2c7",
    "addr:street":"Rue Saint-Ambroise # 104",
    "iso:country":"CA",
    "sg:address":"4710 Rue Saint-Ambroise # 104",
    "sg:city":"Montreal",
    "sg:classifiers":[
        {
            "category":"Home & Garden",
            "subcategory":"Furniture",
            "type":"Retail Goods"
        }
    ],
    "sg:phone":"+1 514 934 3960",
    "sg:postcode":"H4C 2C7",
    "sg:province":"QC",
    "sg:tags":[
        "builder",
        "custom"
    ],
    "wof:name":"Marc Richardson Designs Inc",
    "wof:placetype":"venue"
},
  "geometry": {"coordinates":[-73.58550262449999,45.4706192017],"type":"Point"}
}