{
  "type": "Feature",
  "properties": {
    "addr:full":"Kelowna BC V1Y 9M9",
    "addr:postcode":"v1y 9m9",
    "iso:country":"CA",
    "sg:city":"Kelowna",
    "sg:classifiers":[
        {
            "category":"Manufacturing",
            "subcategory":"Food",
            "type":"Manufacturing & Wholesale Goods"
        }
    ],
    "sg:phone":"+1 250 979 0091",
    "sg:postcode":"V1Y 9M9",
    "sg:province":"BC",
    "sg:tags":[
        "baker",
        "cookie",
        "bakery"
    ],
    "wof:name":"Mount Royal Bagel Factory",
    "wof:placetype":"venue"
},
  "geometry": {"coordinates":[-119.464569092,49.8806877136],"type":"Point"}
}