{
  "type": "Feature",
  "properties": {
    "addr:full":"3077 Mainway Burlington ON L7M 1A1",
    "addr:housenumber":"3077",
    "addr:postcode":"l7m 1a1",
    "addr:street":"Mainway",
    "iso:country":"CA",
    "sg:address":"3077 Mainway",
    "sg:city":"Burlington",
    "sg:classifiers":[
        {
            "category":"Insurance",
            "subcategory":"Insurance Agent",
            "type":"Services"
        }
    ],
    "sg:phone":"+1 905 319 2252",
    "sg:postcode":"L7M 1A1",
    "sg:province":"ON",
    "wof:name":"Donnell Insurance Brokers Ltd",
    "wof:placetype":"venue"
},
  "geometry": {"coordinates":[-79.80866241459999,43.3591423035],"type":"Point"}
}