{
  "type": "Feature",
  "properties": {
    "addr:full":"129 Isabel St Winnipeg MB R3A 1G3",
    "addr:housenumber":"129",
    "addr:postcode":"r3a 1g3",
    "addr:street":"Isabel St",
    "iso:country":"CA",
    "sg:address":"129 Isabel St",
    "sg:city":"Winnipeg",
    "sg:classifiers":[
        {
            "category":"Freight",
            "type":"Transportation"
        }
    ],
    "sg:phone":"+1 204 947 5888",
    "sg:postcode":"R3A 1G3",
    "sg:province":"MB",
    "sg:tags":[
        "courier"
    ],
    "wof:name":"Manila Cargo Express",
    "wof:placetype":"venue"
},
  "geometry": {"coordinates":[-97.14954400000001,49.901634],"type":"Point"}
}