{
  "type": "Feature",
  "properties": {
    "addr:full":"259 King Edward Ave Ottawa ON K1N 7M2",
    "addr:housenumber":"259",
    "addr:postcode":"k1n 7m2",
    "addr:street":"King Edward Ave",
    "iso:country":"CA",
    "sg:address":"259 King Edward Ave",
    "sg:city":"Ottawa",
    "sg:classifiers":[
        {
            "category":"Health Services",
            "subcategory":"Doctor",
            "type":"Services"
        }
    ],
    "sg:phone":"+1 613 789 5689",
    "sg:postcode":"K1N 7M2",
    "sg:province":"ON",
    "sg:tags":[
        "physician",
        "surgeon"
    ],
    "wof:name":"Villeneuve, Phil J MD",
    "wof:placetype":"venue"
},
  "geometry": {"coordinates":[-75.68800400000001,45.431698],"type":"Point"}
}