{
  "type": "Feature",
  "properties": {
    "addr:full":"12667 Hwy 35 Minden ON K0M 2K0",
    "addr:housenumber":"12667",
    "addr:postcode":"k0m 2k0",
    "addr:street":"Hwy 35",
    "iso:country":"CA",
    "sg:address":"12667 Hwy 35",
    "sg:city":"Minden",
    "sg:classifiers":[
        {
            "category":"Recreation",
            "type":"Entertainment"
        }
    ],
    "sg:phone":"+1 705 286 4826",
    "sg:postcode":"K0M 2K0",
    "sg:province":"ON",
    "sg:tags":[
        "tackle",
        "fishing",
        "guide"
    ],
    "wof:name":"Minden Live Bait & Tackle",
    "wof:placetype":"venue"
},
  "geometry": {"coordinates":[-78.71534729,44.9296607971],"type":"Point"}
}