{
  "type": "Feature",
  "properties": {
    "addr:full":"1295 Dakota St #127 Winnipeg MB R2N 3S5",
    "addr:housenumber":"1295",
    "addr:postcode":"r2n 3s5",
    "addr:street":"Dakota St # 127",
    "iso:country":"CA",
    "sg:address":"1295 Dakota St #127",
    "sg:city":"Winnipeg",
    "sg:classifiers":[
        {
            "category":"Health Services",
            "subcategory":"Nursing And Care Facility",
            "type":"Services"
        }
    ],
    "sg:phone":"+1 204 253 8690",
    "sg:postcode":"R2N 3S5",
    "sg:province":"MB",
    "sg:tags":[
        "home",
        "retirement",
        "community"
    ],
    "wof:name":"Kirchhoff Gardens",
    "wof:placetype":"venue"
},
  "geometry": {"coordinates":[-97.09815999999999,49.816601],"type":"Point"}
}