{
  "type": "Feature",
  "properties": {
    "addr:full":"200 Muskoka Rd 10 Port Sydney ON P0B 1L0",
    "addr:housenumber":"200;10",
    "addr:postcode":"p0b 1l0",
    "addr:street":"Muskoka Rd;Port Sydney",
    "iso:country":"CA",
    "sg:address":"200 Muskoka Rd 10",
    "sg:city":"Port Sydney",
    "sg:classifiers":[
        {
            "category":"Wholesale",
            "subcategory":"Construction Materials",
            "type":"Manufacturing & Wholesale Goods"
        }
    ],
    "sg:phone":"+1 705 385 4757",
    "sg:postcode":"P0B 1L0",
    "sg:province":"ON",
    "sg:tags":[
        "sand",
        "gravel"
    ],
    "wof:name":"Port Sydney Utterson Sand",
    "wof:placetype":"venue"
},
  "geometry": {"coordinates":[-79.285027,45.177113],"type":"Point"}
}