{
  "type": "Feature",
  "properties": {
    "addr:full":"928 Mcewan Dr Carstairs AB T0M 0N0",
    "addr:housenumber":"928",
    "addr:postcode":"t0m 0n0",
    "addr:street":"Mcewan Dr",
    "iso:country":"CA",
    "sg:address":"928 Mcewan Dr",
    "sg:city":"Carstairs",
    "sg:classifiers":[
        {
            "category":"Shopping",
            "type":"Retail Goods"
        }
    ],
    "sg:phone":"+1 403 337 3481",
    "sg:postcode":"T0M 0N0",
    "sg:province":"AB",
    "sg:tags":[
        "picture",
        "frame"
    ],
    "wof:name":"Picture Our Frames",
    "wof:placetype":"venue"
},
  "geometry": {"coordinates":[-114.10045599999999,51.558739],"type":"Point"}
}