{
  "type": "Feature",
  "properties": {
    "addr:full":"133 Fisher Ave Cochrane AB T4C 2C3",
    "addr:housenumber":"133",
    "addr:postcode":"t4c 2c3",
    "addr:street":"Fisher Ave",
    "iso:country":"CA",
    "sg:address":"133 Fisher Ave",
    "sg:city":"Cochrane",
    "sg:classifiers":[
        {
            "category":"Retail",
            "subcategory":"Auto Repair",
            "type":"Services"
        }
    ],
    "sg:phone":"+1 403 932 7114",
    "sg:postcode":"T4C 2C3",
    "sg:province":"AB",
    "sg:tags":[
        "repairing",
        "automobile"
    ],
    "wof:name":"Fenton Automotive",
    "wof:placetype":"venue"
},
  "geometry": {"coordinates":[-114.463279724,51.1860961914],"type":"Point"}
}