{
  "type": "Feature",
  "properties": {
    "addr:full":"600 Beach Rd Qualicum Beach BC V9K 1K7",
    "addr:housenumber":"600",
    "addr:postcode":"v9k 1k7",
    "addr:street":"Beach Rd",
    "iso:country":"CA",
    "sg:address":"600 Beach Rd",
    "sg:city":"Qualicum Beach",
    "sg:classifiers":[
        {
            "category":"Organizations",
            "subcategory":"Religious Organization",
            "type":"Services"
        }
    ],
    "sg:phone":"+1 250 752 9123",
    "sg:postcode":"V9K 1K7",
    "sg:province":"BC",
    "sg:tags":[
        "church"
    ],
    "wof:name":"Qualicum Community Baptist Chr",
    "wof:placetype":"venue"
},
  "geometry": {"coordinates":[-124.447364807,49.3499717712],"type":"Point"}
}