{
  "type": "Feature",
  "properties": {
    "addr:full":"2433 Wiggins Ave S Saskatoon SK S7J 1X1",
    "addr:housenumber":"2433",
    "addr:postcode":"s7j 1x1",
    "addr:street":"Wiggins Ave S",
    "iso:country":"CA",
    "sg:address":"2433 Wiggins Ave S",
    "sg:city":"Saskatoon",
    "sg:classifiers":[
        {
            "category":"Retail",
            "subcategory":"Repair Shop",
            "type":"Services"
        }
    ],
    "sg:phone":"+1 306 956 1333",
    "sg:postcode":"S7J 1X1",
    "sg:province":"SK",
    "sg:tags":[
        "repairing",
        "piano",
        "refinishing"
    ],
    "wof:name":"Buhler's Piano Svc",
    "wof:placetype":"venue"
},
  "geometry": {"coordinates":[-106.638023377,52.0997085571],"type":"Point"}
}