{
  "type": "Feature",
  "properties": {
    "addr:full":"213 Rue Saint-Joseph Saint-Raymond QC G3L 1H9",
    "addr:housenumber":"213",
    "addr:postcode":"g3l 1h9",
    "addr:street":"Rue Saint-Joseph",
    "iso:country":"CA",
    "sg:address":"213 Rue Saint-Joseph",
    "sg:city":"Saint-Raymond",
    "sg:classifiers":[
        {
            "category":"Shopping",
            "subcategory":"Clothing, Apparel, & Fashions",
            "type":"Retail Goods"
        }
    ],
    "sg:phone":"+1 418 337 4484",
    "sg:postcode":"G3L 1H9",
    "sg:province":"QC",
    "sg:tags":[
        "item",
        "boutique"
    ],
    "wof:name":"Boutique Chez Pierrot",
    "wof:placetype":"venue"
},
  "geometry": {"coordinates":[-71.83470153810001,46.8895683289],"type":"Point"}
}