{
  "type": "Feature",
  "properties": {
    "addr:full":"1597 Main St Penticton BC V2A 5G7",
    "addr:housenumber":"1597",
    "addr:postcode":"v2a 5g7",
    "addr:street":"Main St",
    "iso:country":"CA",
    "sg:address":"1597 Main St",
    "sg:city":"Penticton",
    "sg:classifiers":[
        {
            "category":"Autos & Motor Vehicles",
            "subcategory":"Automobile Sales",
            "type":"Retail Goods"
        }
    ],
    "sg:phone":"+1 250 492 7725",
    "sg:postcode":"V2A 5G7",
    "sg:province":"BC",
    "sg:tags":[
        "car",
        "dealer"
    ],
    "wof:name":"Select Auto Sales",
    "wof:placetype":"venue"
},
  "geometry": {"coordinates":[-119.585144043,49.4809150696],"type":"Point"}
}