{
  "type": "Feature",
  "properties": {
    "addr:full":"North York ON M3N 2V2",
    "addr:postcode":"m3n 2v2",
    "iso:country":"CA",
    "sg:city":"North York",
    "sg:classifiers":[
        {
            "category":"Professional",
            "subcategory":"Computer Services",
            "type":"Services"
        }
    ],
    "sg:phone":"+1 416 631 7779",
    "sg:postcode":"M3N 2V2",
    "sg:province":"ON",
    "sg:tags":[
        "repair",
        "dealer",
        "equipment"
    ],
    "wof:name":"Computer Exchange & Svc",
    "wof:placetype":"venue"
},
  "geometry": {"coordinates":[-79.5160293579,43.7573165894],"type":"Point"}
}