{
  "type": "Feature",
  "properties": {
    "iso:country":"CA",
    "sg:address":"1800 Laval Aut W",
    "sg:city":"Laval",
    "sg:classifiers":[
        {
            "category":"Wholesale",
            "subcategory":"Groceries",
            "type":"Manufacturing & Wholesale Goods"
        }
    ],
    "sg:phone":"+1 450 687 2680",
    "sg:postcode":"H7S 2E7",
    "sg:province":"QC",
    "sg:tags":[
        "food",
        "product"
    ],
    "wof:name":"Corporation Des Aliments I-D",
    "wof:placetype":"venue"
},
  "geometry": {"coordinates":[-73.744637,45.551567],"type":"Point"}
}