{
  "type": "Feature",
  "properties": {
    "addr:full":"1004 St Mary's Rd Winnipeg MB R2M 3S3",
    "addr:housenumber":"1004",
    "addr:postcode":"r2m 3s3",
    "addr:street":"St Mary'S Rd",
    "iso:country":"CA",
    "sg:address":"1004 St Mary's Rd",
    "sg:city":"Winnipeg",
    "sg:classifiers":[
        {
            "category":"Manufacturing",
            "subcategory":"Printing",
            "type":"Manufacturing & Wholesale Goods"
        }
    ],
    "sg:phone":"+1 204 254 2937",
    "sg:postcode":"R2M 3S3",
    "sg:province":"MB",
    "sg:tags":[
        "printer",
        "duplicating",
        "copying"
    ],
    "wof:name":"Galaxy Printing",
    "wof:placetype":"venue"
},
  "geometry": {"coordinates":[-97.1125259399,49.8405647278],"type":"Point"}
}