{
  "type": "Feature",
  "properties": {
    "iso:country":"CA",
    "sg:address":"7310 Cluff Rd",
    "sg:city":"Prince George",
    "sg:classifiers":[
        {
            "category":"Education",
            "subcategory":"School",
            "type":"Public Place"
        }
    ],
    "sg:phone":"+1 250 962 9669",
    "sg:postcode":"V2K 2M3",
    "sg:province":"BC",
    "wof:name":"Glenview Elementary School",
    "wof:placetype":"venue"
},
  "geometry": {"coordinates":[-122.777236938,53.9957695007],"type":"Point"}
}