{
  "type": "Feature",
  "properties": {
    "addr:full":"Stoney Creek ON L8E 3N9",
    "addr:postcode":"l8e 3n9",
    "iso:country":"CA",
    "sg:city":"Stoney Creek",
    "sg:classifiers":[
        {
            "category":"Professional",
            "subcategory":"Computer Services",
            "type":"Services"
        }
    ],
    "sg:phone":"+1 905 664 0940",
    "sg:postcode":"L8E 3N9",
    "sg:province":"ON",
    "wof:name":"Micro Plus Svc",
    "wof:placetype":"venue"
},
  "geometry": {"coordinates":[-79.7164077759,43.2345466614],"type":"Point"}
}