{
  "type": "Feature",
  "properties": {
    "addr:full":"Saint-Laurent QC H4T 1Z6",
    "addr:postcode":"h4t 1z6",
    "iso:country":"CA",
    "sg:city":"Saint-Laurent",
    "sg:classifiers":[
        {
            "category":"Real Estate",
            "subcategory":"Real Estate Agent",
            "type":"Services"
        }
    ],
    "sg:phone":"+1 514 281 1515",
    "sg:postcode":"H4T 1Z6",
    "sg:province":"QC",
    "wof:name":"Capitale Alliance-Comm Inc",
    "wof:placetype":"venue"
},
  "geometry": {"coordinates":[-73.6791610718,45.4955101013],"type":"Point"}
}