{
  "type": "Feature",
  "properties": {
    "addr:full":"Calgary AB T2E 7A7",
    "addr:postcode":"t2e 7a7",
    "iso:country":"CA",
    "sg:city":"Calgary",
    "sg:classifiers":[
        {
            "category":"Freight",
            "type":"Transportation"
        }
    ],
    "sg:phone":"+1 403 974 7874",
    "sg:postcode":"T2E 7A7",
    "sg:province":"AB",
    "sg:tags":[
        "courier"
    ],
    "wof:name":"A-Plus Courier Svc Ltd",
    "wof:placetype":"venue"
},
  "geometry": {"coordinates":[-114.00862100000001,51.077038],"type":"Point"}
}