{
  "type": "Feature",
  "properties": {
    "addr:full":"4 Norbert Cres Etobicoke ON M9C 3J9",
    "addr:housenumber":"4",
    "addr:postcode":"m9c 3j9",
    "addr:street":"Norbert Cres",
    "iso:country":"CA",
    "sg:address":"4 Norbert Cres",
    "sg:city":"Etobicoke",
    "sg:classifiers":[
        {
            "category":"Shopping",
            "subcategory":"Gifts & Souvenirs",
            "type":"Retail Goods"
        }
    ],
    "sg:phone":"+1 416 232 1199",
    "sg:postcode":"M9C 3J9",
    "sg:province":"ON",
    "sg:tags":[
        "shop"
    ],
    "wof:name":"Quilters' Fancy Ltd",
    "wof:placetype":"venue"
},
  "geometry": {"coordinates":[-79.580597,43.645184],"type":"Point"}
}