{
  "type": "Feature",
  "properties": {
    "addr:full":"Calgary AB T2G 0B6",
    "addr:postcode":"t2g 0b6",
    "iso:country":"CA",
    "sg:city":"Calgary",
    "sg:classifiers":[
        {
            "category":"Shopping",
            "subcategory":"Used Merchandise",
            "type":"Retail Goods"
        }
    ],
    "sg:phone":"+1 403 237 8388",
    "sg:postcode":"T2G 0B6",
    "sg:province":"AB",
    "sg:tags":[
        "antique"
    ],
    "wof:name":"Riccadag Antiquities Inc",
    "wof:placetype":"venue"
},
  "geometry": {"coordinates":[-114.062606812,51.0503387451],"type":"Point"}
}