{
  "type": "Feature",
  "properties": {
    "addr:full":"54 Kennevale Dr Nepean ON K2J 3B2",
    "addr:housenumber":"54",
    "addr:postcode":"k2j 3b2",
    "addr:street":"Kennevale Dr",
    "iso:country":"CA",
    "sg:address":"54 Kennevale Dr",
    "sg:city":"Nepean",
    "sg:classifiers":[
        {
            "category":"Education",
            "subcategory":"School",
            "type":"Public Place"
        }
    ],
    "sg:phone":"+1 613 825 4834",
    "sg:postcode":"K2J 3B2",
    "sg:province":"ON",
    "wof:name":"Mary Honeywell Elementary Schl",
    "wof:placetype":"venue"
},
  "geometry": {"coordinates":[-75.76651,45.268757],"type":"Point"}
}