{
  "type": "Feature",
  "properties": {
    "addr:full":"323 Boul Manseau # 102 Joliette QC J6E 3C9",
    "addr:housenumber":"323",
    "addr:postcode":"j6e 3c9",
    "addr:street":"Boul Manseau # 102",
    "iso:country":"CA",
    "sg:address":"323 Boul Manseau # 102",
    "sg:city":"Joliette",
    "sg:classifiers":[
        {
            "category":"Building & Trades",
            "subcategory":"Cleaning & Sanitation",
            "type":"Services"
        }
    ],
    "sg:phone":"+1 450 755 4854",
    "sg:postcode":"J6E 3C9",
    "sg:province":"QC",
    "sg:tags":[
        "house"
    ],
    "wof:name":"Cooperative DE Solidarite",
    "wof:placetype":"venue"
},
  "geometry": {"coordinates":[-73.4384,46.025871],"type":"Point"}
}