{
  "type": "Feature",
  "properties": {
    "iso:country":"CA",
    "sg:address":"735 Boul Barrette",
    "sg:city":"Chicoutimi",
    "sg:classifiers":[
        {
            "category":"Insurance",
            "subcategory":"Insurance Agent",
            "type":"Services"
        }
    ],
    "sg:phone":"+1 418 543 4622",
    "sg:postcode":"G7J 4C4",
    "sg:province":"QC",
    "wof:name":"Assurance Transamerica Vie",
    "wof:placetype":"venue"
},
  "geometry": {"coordinates":[-71.09565,48.403412],"type":"Point"}
}