{
  "type": "Feature",
  "properties": {
    "addr:full":"1516 Bishop Rd Kentville NS B4N 3V7",
    "addr:housenumber":"1516",
    "addr:postcode":"b4n 3v7",
    "addr:street":"Bishop Rd",
    "iso:country":"CA",
    "sg:address":"1516 Bishop Rd",
    "sg:city":"Kentville",
    "sg:classifiers":[
        {
            "category":"Wholesale",
            "subcategory":"Construction Materials",
            "type":"Manufacturing & Wholesale Goods"
        }
    ],
    "sg:phone":"+1 902 679 6606",
    "sg:postcode":"B4N 3V7",
    "sg:province":"NS",
    "sg:tags":[
        "sand",
        "gravel"
    ],
    "wof:name":"Shaw Resources Keddy Operation",
    "wof:placetype":"venue"
},
  "geometry": {"coordinates":[-64.494438,45.07692],"type":"Point"}
}