{
  "type": "Feature",
  "properties": {
    "iso:country":"CA",
    "sg:address":"145 Somme Blvd",
    "sg:city":"Borden",
    "sg:classifiers":[
        {
            "category":"Education",
            "subcategory":"School",
            "type":"Public Place"
        }
    ],
    "sg:phone":"+1 705 424 1039",
    "sg:postcode":"L0M 1C0",
    "sg:province":"ON",
    "wof:name":"Frederick Campbell Elem School",
    "wof:placetype":"venue"
},
  "geometry": {"coordinates":[-79.884209,44.293262],"type":"Point"}
}