{
  "type": "Feature",
  "properties": {
    "addr:full":"235 6E Rue Val-D'Or QC J9P 3V4",
    "addr:housenumber":"235",
    "addr:postcode":"j9p 3v4",
    "addr:street":"6E Rue",
    "iso:country":"CA",
    "sg:address":"235 6E Rue",
    "sg:city":"Val-D'Or",
    "sg:classifiers":[
        {
            "category":"Personal",
            "subcategory":"Beauty Salon",
            "type":"Services"
        }
    ],
    "sg:phone":"+1 819 824 6918",
    "sg:postcode":"J9P 3V4",
    "sg:province":"QC",
    "wof:name":"Salon Agathe",
    "wof:placetype":"venue"
},
  "geometry": {"coordinates":[-71.228577,46.823589],"type":"Point"}
}