{
  "type": "Feature",
  "properties": {
    "iso:country":"CA",
    "sg:address":"7103 Sherwood Dr",
    "sg:city":"Regina",
    "sg:classifiers":[
        {
            "category":"Health Services",
            "subcategory":"Nursing And Care Facility",
            "type":"Services"
        }
    ],
    "sg:phone":"+1 306 949 2929",
    "sg:postcode":"S4X 2V5",
    "sg:province":"SK",
    "sg:tags":[
        "personal",
        "home"
    ],
    "wof:name":"Victorian Care Home",
    "wof:placetype":"venue"
},
  "geometry": {"coordinates":[-104.682556152,50.4806594849],"type":"Point"}
}