{
  "type": "Feature",
  "properties": {
    "addr:full":"1550 Laurier Ave Vancouver BC V6J 2V3",
    "addr:housenumber":"1550",
    "addr:postcode":"v6j 2v3",
    "addr:street":"Laurier Ave",
    "iso:country":"CA",
    "sg:address":"1550 Laurier Ave",
    "sg:city":"Vancouver",
    "sg:classifiers":[
        {
            "category":"Building & Trades",
            "subcategory":"Construction",
            "type":"Services"
        }
    ],
    "sg:phone":"+1 604 731 3391",
    "sg:postcode":"V6J 2V3",
    "sg:province":"BC",
    "sg:tags":[
        "repairing",
        "remodeling",
        "contractor"
    ],
    "wof:name":"Landview Construction",
    "wof:placetype":"venue"
},
  "geometry": {"coordinates":[-123.14015999999999,49.250751],"type":"Point"}
}