{
  "type": "Feature",
  "properties": {
    "addr:full":"Arthur ON N0G 1A0",
    "addr:postcode":"n0g 1a0",
    "iso:country":"CA",
    "sg:city":"Arthur",
    "sg:classifiers":[
        {
            "category":"Autos & Motor Vehicles",
            "subcategory":"Automobile Sales",
            "type":"Retail Goods"
        }
    ],
    "sg:phone":"+1 519 848 2016",
    "sg:postcode":"N0G 1A0",
    "sg:province":"ON",
    "sg:tags":[
        "car",
        "dealer"
    ],
    "wof:name":"Arthur Chrysler Dodge Ltd",
    "wof:placetype":"venue"
},
  "geometry": {"coordinates":[-80.5603561401,43.8301010132],"type":"Point"}
}