{
  "type": "Feature",
  "properties": {
    "addr:full":"309 Mansfield Pl North Vancouver BC V7J 1E4",
    "addr:housenumber":"309",
    "addr:postcode":"v7j 1e4",
    "addr:street":"Mansfield Pl",
    "iso:country":"CA",
    "sg:address":"309 Mansfield Pl",
    "sg:city":"North Vancouver",
    "sg:classifiers":[
        {
            "category":"Retail",
            "subcategory":"Animal Services",
            "type":"Services"
        }
    ],
    "sg:phone":"+1 604 984 0611",
    "sg:postcode":"V7J 1E4",
    "sg:province":"BC",
    "sg:tags":[
        "pet",
        "grooming",
        "washing"
    ],
    "wof:name":"Camelot Dog Day Care & Spa",
    "wof:placetype":"venue"
},
  "geometry": {"coordinates":[-123.03727000000001,49.307171],"type":"Point"}
}