{
  "type": "Feature",
  "properties": {
    "addr:full":"425 Rea St S Timmins ON P4N 3S4",
    "addr:housenumber":"425",
    "addr:postcode":"p4n 3s4",
    "addr:street":"Rea St S",
    "iso:country":"CA",
    "sg:address":"425 Rea St S",
    "sg:city":"Timmins",
    "sg:phone":"+1 705 264 9433",
    "sg:postcode":"P4N 3S4",
    "sg:province":"ON",
    "sg:tags":[
        "oil"
    ],
    "wof:name":"Shell Canada Products Ltd",
    "wof:placetype":"venue"
},
  "geometry": {"coordinates":[-81.3413772583,48.4680747986],"type":"Point"}
}