{
  "type": "Feature",
  "properties": {
    "addr:full":"445 Laclie St Orillia ON L3V 4P7",
    "addr:housenumber":"445",
    "addr:postcode":"l3v 4p7",
    "addr:street":"Laclie St",
    "iso:country":"CA",
    "sg:address":"445 Laclie St",
    "sg:city":"Orillia",
    "sg:classifiers":[
        {
            "category":"Bus Charters",
            "type":"Transportation"
        }
    ],
    "sg:phone":"+1 705 326 7376",
    "sg:postcode":"L3V 4P7",
    "sg:province":"ON",
    "sg:tags":[
        "rental"
    ],
    "wof:name":"Laidlaw Transit Ltd",
    "wof:placetype":"venue"
},
  "geometry": {"coordinates":[-79.422798,44.626949],"type":"Point"}
}