{
  "type": "Feature",
  "properties": {
    "addr:full":"10709 105 St NW Edmonton AB T5H 2X3",
    "addr:housenumber":"10709",
    "addr:postcode":"t5h 2x3",
    "addr:street":"105 St Nw",
    "iso:country":"CA",
    "sg:address":"10709 105 St NW",
    "sg:city":"Edmonton",
    "sg:classifiers":[
        {
            "category":"Social Services",
            "type":"Services"
        }
    ],
    "sg:phone":"+1 780 420 1970",
    "sg:postcode":"T5H 2X3",
    "sg:province":"AB",
    "sg:tags":[
        "psychologist",
        "counselor",
        "marriage",
        "family"
    ],
    "wof:name":"Catholic Social Svc",
    "wof:placetype":"venue"
},
  "geometry": {"coordinates":[-113.50084699999999,53.551685],"type":"Point"}
}