{
  "type": "Feature",
  "properties": {
    "addr:full":"2020 Ogilvie Rd Gloucester ON K1J 7N8",
    "addr:housenumber":"2020",
    "addr:postcode":"k1j 7n8",
    "addr:street":"Ogilvie Rd",
    "iso:country":"CA",
    "sg:address":"2020 Ogilvie Rd",
    "sg:city":"Gloucester",
    "sg:classifiers":[
        {
            "category":"Arena",
            "subcategory":"Sports Club",
            "type":"Entertainment"
        }
    ],
    "sg:phone":"+1 613 746 7109",
    "sg:postcode":"K1J 7N8",
    "sg:province":"ON",
    "sg:tags":[
        "athletic",
        "fields",
        "stadium",
        "government"
    ],
    "wof:name":"Earl Armstrong Arena",
    "wof:placetype":"venue"
},
  "geometry": {"coordinates":[-75.60217299999999,45.437843],"type":"Point"}
}