{
  "type": "Feature",
  "properties": {
    "addr:full":"477 Century St Winnipeg MB R3J 1J9",
    "addr:housenumber":"477",
    "addr:postcode":"r3j 1j9",
    "addr:street":"Century St",
    "iso:country":"CA",
    "sg:address":"477 Century St",
    "sg:city":"Winnipeg",
    "sg:classifiers":[
        {
            "category":"Manufacturing",
            "subcategory":"Signs",
            "type":"Manufacturing & Wholesale Goods"
        }
    ],
    "sg:phone":"+1 204 942 0220",
    "sg:postcode":"R3J 1J9",
    "sg:province":"MB",
    "sg:tags":[
        "rental"
    ],
    "wof:name":"A Mobile Ad-All Around Sign CO",
    "wof:placetype":"venue"
},
  "geometry": {"coordinates":[-97.205482,49.889709],"type":"Point"}
}