{
  "type": "Feature",
  "properties": {
    "addr:full":"5304 Hubalta Rd SE Calgary AB T2B 1T6",
    "addr:housenumber":"5304",
    "addr:postcode":"t2b 1t6",
    "addr:street":"Hubalta Rd Se",
    "iso:country":"CA",
    "sg:address":"5304 Hubalta Rd SE",
    "sg:city":"Calgary",
    "sg:classifiers":[
        {
            "category":"Manufacturing",
            "subcategory":"Metals",
            "type":"Manufacturing & Wholesale Goods"
        }
    ],
    "sg:phone":"+1 403 273 2111",
    "sg:postcode":"T2B 1T6",
    "sg:province":"AB",
    "sg:tags":[
        "mold",
        "maker"
    ],
    "wof:name":"Vari Systems Inc",
    "wof:placetype":"venue"
},
  "geometry": {"coordinates":[-113.95626799999999,51.034843],"type":"Point"}
}