{
  "type": "Feature",
  "properties": {
    "addr:full":"1342 Weber St E Kitchener ON N2A 1C4",
    "addr:housenumber":"1342",
    "addr:postcode":"n2a 1c4",
    "addr:street":"Weber St E",
    "iso:country":"CA",
    "sg:address":"1342 Weber St E",
    "sg:city":"Kitchener",
    "sg:classifiers":[
        {
            "category":"Shopping",
            "subcategory":"Computers & Home Electronics",
            "type":"Retail Goods"
        }
    ],
    "sg:phone":"+1 519 895 8650",
    "sg:postcode":"N2A 1C4",
    "sg:province":"ON",
    "sg:tags":[
        "equipment",
        "dealer"
    ],
    "wof:name":"Mdg",
    "wof:placetype":"venue"
},
  "geometry": {"coordinates":[-80.441154,43.433449],"type":"Point"}
}