{
  "type": "Feature",
  "properties": {
    "addr:full":"530 Scott St St Catharines ON L2M 3X5",
    "addr:housenumber":"530",
    "addr:postcode":"l2m 3x5",
    "addr:street":"Scott St",
    "iso:country":"CA",
    "sg:address":"530 Scott St",
    "sg:city":"St Catharines",
    "sg:classifiers":[
        {
            "category":"Restaurant",
            "type":"Food & Drink"
        }
    ],
    "sg:phone":"+1 905 935 5353",
    "sg:postcode":"L2M 3X5",
    "sg:province":"ON",
    "sg:tags":[
        "pizza"
    ],
    "wof:name":"Buona Pizza",
    "wof:placetype":"venue"
},
  "geometry": {"coordinates":[-79.212006,43.194859],"type":"Point"}
}