{
  "type": "Feature",
  "properties": {
    "addr:full":"2110 150A St Surrey BC V4A 9J6",
    "addr:housenumber":"2110",
    "addr:postcode":"v4a 9j6",
    "addr:street":"150A St",
    "iso:country":"CA",
    "sg:address":"2110 150A St",
    "sg:city":"Surrey",
    "sg:classifiers":[
        {
            "category":"Professional",
            "type":"Services"
        }
    ],
    "sg:phone":"+1 604 541 8828",
    "sg:postcode":"V4A 9J6",
    "sg:province":"BC",
    "sg:tags":[
        "consultant",
        "geological"
    ],
    "wof:name":"John R Poloni & Assoc Ltd",
    "wof:placetype":"venue"
},
  "geometry": {"coordinates":[-122.830215,49.105179],"type":"Point"}
}