{
  "type": "Feature",
  "properties": {
    "addr:full":"1318 3rd St Estevan SK S4A 0S2",
    "addr:housenumber":"1318",
    "addr:postcode":"s4a 0s2",
    "addr:street":"3Rd St",
    "iso:country":"CA",
    "sg:address":"1318 3rd St",
    "sg:city":"Estevan",
    "sg:classifiers":[
        {
            "category":"Health Services",
            "subcategory":"Clinic",
            "type":"Services"
        }
    ],
    "sg:phone":"+1 306 634 8327",
    "sg:postcode":"S4A 0S2",
    "sg:province":"SK",
    "sg:tags":[
        "therapist",
        "massage"
    ],
    "wof:name":"Estevan Massage Therapy Ctr Re",
    "wof:placetype":"venue"
},
  "geometry": {"coordinates":[-102.998367,49.140453],"type":"Point"}
}