{
  "type": "Feature",
  "properties": {
    "addr:full":"Ottawa ON K2C 3N6",
    "addr:postcode":"k2c 3n6",
    "iso:country":"CA",
    "sg:city":"Ottawa",
    "sg:classifiers":[
        {
            "category":"Professional",
            "subcategory":"Management & Consulting",
            "type":"Services"
        }
    ],
    "sg:phone":"+1 613 727 3368",
    "sg:postcode":"K2C 3N6",
    "sg:province":"ON",
    "sg:tags":[
        "consultant",
        "business"
    ],
    "wof:name":"Henry Global Consulting Svc",
    "wof:placetype":"venue"
},
  "geometry": {"coordinates":[-75.70265999999999,45.369843],"type":"Point"}
}