{
  "type": "Feature",
  "properties": {
    "addr:full":"960 Tecumseh Rd E Windsor ON N8X 2S6",
    "addr:housenumber":"960",
    "addr:postcode":"n8x 2s6",
    "addr:street":"Tecumseh Rd E",
    "iso:country":"CA",
    "sg:address":"960 Tecumseh Rd E",
    "sg:city":"Windsor",
    "sg:classifiers":[
        {
            "category":"Health Services",
            "subcategory":"Health Practitioner",
            "type":"Services"
        }
    ],
    "sg:phone":"+1 519 252 2752",
    "sg:postcode":"N8X 2S6",
    "sg:province":"ON",
    "sg:tags":[
        "physiotherapist"
    ],
    "wof:name":"Wardle's Physiotherapy Clinic",
    "wof:placetype":"venue"
},
  "geometry": {"coordinates":[-83.010429,42.299408],"type":"Point"}
}