{
  "type": "Feature",
  "properties": {
    "addr:full":"441 Caledonia Rd Moncton NB E1H 2E8",
    "addr:housenumber":"441",
    "addr:postcode":"e1h 2e8",
    "addr:street":"Caledonia Rd",
    "iso:country":"CA",
    "sg:address":"441 Caledonia Rd",
    "sg:city":"Moncton",
    "sg:classifiers":[
        {
            "category":"Building & Trades",
            "subcategory":"Plumbing",
            "type":"Services"
        }
    ],
    "sg:phone":"+1 506 857 1005",
    "sg:postcode":"E1H 2E8",
    "sg:province":"NB",
    "sg:tags":[
        "contractor"
    ],
    "wof:name":"D W Fowler Ltd",
    "wof:placetype":"venue"
},
  "geometry": {"coordinates":[-64.7527542114,46.1425590515],"type":"Point"}
}