{
  "type": "Feature",
  "properties": {
    "addr:full":"RR 1 Inverness NS B0E 1N0",
    "addr:postcode":"b0e 1n0",
    "addr:street":"Rr 1",
    "iso:country":"CA",
    "sg:address":"RR 1",
    "sg:city":"Inverness",
    "sg:classifiers":[
        {
            "category":"Real Estate",
            "subcategory":"Surveying",
            "type":"Services"
        }
    ],
    "sg:phone":"+1 902 258 2219",
    "sg:postcode":"B0E 1N0",
    "sg:province":"NS",
    "sg:tags":[
        "surveyor"
    ],
    "wof:name":"Jerome Mac Eachern & Assoc Ltd",
    "wof:placetype":"venue"
},
  "geometry": {"coordinates":[-61.304523,46.231205],"type":"Point"}
}