{
  "type": "Feature",
  "properties": {
    "addr:full":"99 Rue Principale Chateauguay QC J6K 1G2",
    "addr:housenumber":"99",
    "addr:postcode":"j6k 1g2",
    "addr:street":"Rue Principale",
    "iso:country":"CA",
    "sg:address":"99 Rue Principale",
    "sg:city":"Chateauguay",
    "sg:classifiers":[
        {
            "category":"Home & Garden",
            "subcategory":"Building Materials",
            "type":"Retail Goods"
        }
    ],
    "sg:phone":"+1 450 692 9992",
    "sg:postcode":"J6K 1G2",
    "sg:province":"QC",
    "sg:tags":[
        "lumber"
    ],
    "wof:name":"Marcil Centre DE Renovation",
    "wof:placetype":"venue"
},
  "geometry": {"coordinates":[-73.754929,45.358513],"type":"Point"}
}