{
  "type": "Feature",
  "properties": {
    "addr:full":"3096 Hastings St E Vancouver BC V5K 2A3",
    "addr:housenumber":"3096",
    "addr:postcode":"v5k 2a3",
    "addr:street":"Hastings St E",
    "iso:country":"CA",
    "sg:address":"3096 Hastings St E",
    "sg:city":"Vancouver",
    "sg:classifiers":[
        {
            "category":"Government",
            "subcategory":"Office",
            "type":"Public Place"
        }
    ],
    "sg:phone":"+1 604 718 6222",
    "sg:postcode":"V5K 2A3",
    "sg:province":"BC",
    "sg:tags":[
        "village"
    ],
    "wof:name":"Hastings Community Ctr",
    "wof:placetype":"venue"
},
  "geometry": {"coordinates":[-123.03935199999999,49.280987],"type":"Point"}
}