{
  "type": "Feature",
  "properties": {
    "iso:country":"CA",
    "sg:address":"451 Paul St # 209A H",
    "sg:city":"Dieppe",
    "sg:classifiers":[
        {
            "category":"Professional",
            "subcategory":"Lawyer & Legal Services",
            "type":"Services"
        }
    ],
    "sg:phone":"+1 506 856 8199",
    "sg:postcode":"E1A 6W8",
    "sg:province":"NB",
    "sg:tags":[
        "attorney"
    ],
    "wof:name":"Gaudet, Jean-Eudes QC",
    "wof:placetype":"venue"
},
  "geometry": {"coordinates":[-64.76150512700001,46.0993080139],"type":"Point"}
}