{
  "type": "Feature",
  "properties": {
    "iso:country":"CA",
    "sg:address":"5216 Main St",
    "sg:city":"Oxford",
    "sg:classifiers":[
        {
            "category":"Insurance",
            "subcategory":"Insurance Agent",
            "type":"Services"
        }
    ],
    "sg:phone":"+1 902 447 2351",
    "sg:postcode":"B0M 1P0",
    "sg:province":"NS",
    "sg:tags":[
        "consultant"
    ],
    "wof:name":"Asbell Insurance",
    "wof:placetype":"venue"
},
  "geometry": {"coordinates":[-63.8787689209,45.7277412415],"type":"Point"}
}