{
  "type": "Feature",
  "properties": {
    "addr:full":"Burnaby BC V5G 1G6",
    "addr:postcode":"v5g 1g6",
    "iso:country":"CA",
    "sg:city":"Burnaby",
    "sg:classifiers":[
        {
            "category":"Retail",
            "subcategory":"Auto Repair",
            "type":"Services"
        }
    ],
    "sg:phone":"+1 604 436 2247",
    "sg:postcode":"V5G 1G6",
    "sg:province":"BC",
    "sg:tags":[
        "repairing",
        "automobile"
    ],
    "wof:name":"Minit-Tune & Brake Auto Ctr",
    "wof:placetype":"venue"
},
  "geometry": {"coordinates":[-123.019447,49.254936],"type":"Point"}
}