{
  "type": "Feature",
  "properties": {
    "addr:full":"6983 Boul Saint-Laurent Montreal QC H2S 3E1",
    "addr:housenumber":"6983",
    "addr:postcode":"h2s 3e1",
    "addr:street":"Boul Saint-Laurent",
    "iso:country":"CA",
    "sg:address":"6983 Boul Saint-Laurent",
    "sg:city":"Montreal",
    "sg:classifiers":[
        {
            "category":"Professional",
            "subcategory":"Management & Consulting",
            "type":"Services"
        }
    ],
    "sg:phone":"+1 514 273 7067",
    "sg:postcode":"H2S 3E1",
    "sg:province":"QC",
    "sg:tags":[
        "consultant",
        "business"
    ],
    "wof:name":"Cmt Consultant",
    "wof:placetype":"venue"
},
  "geometry": {"coordinates":[-73.6154251099,45.533454895],"type":"Point"}
}