{
  "type": "Feature",
  "properties": {
    "addr:full":"4922 Boul Levesque E Laval QC H7C 1N1",
    "addr:housenumber":"4922",
    "addr:postcode":"h7c 1n1",
    "addr:street":"Boul Levesque E",
    "iso:country":"CA",
    "sg:address":"4922 Boul Levesque E",
    "sg:city":"Laval",
    "sg:classifiers":[
        {
            "category":"Retail",
            "subcategory":"Auto Repair",
            "type":"Services"
        }
    ],
    "sg:phone":"+1 450 661 1330",
    "sg:postcode":"H7C 1N1",
    "sg:province":"QC",
    "sg:tags":[
        "body",
        "automobile",
        "painting"
    ],
    "wof:name":"Garage Gaudette Enrg",
    "wof:placetype":"venue"
},
  "geometry": {"coordinates":[-73.644707,45.609543],"type":"Point"}
}