{
  "type": "Feature",
  "properties": {
    "addr:full":"449 Pacific Dr Burstall SK S0N 0H0",
    "addr:housenumber":"449",
    "addr:postcode":"s0n 0h0",
    "addr:street":"Pacific Dr Burstall",
    "iso:country":"CA",
    "sg:address":"449 Pacific Dr",
    "sg:city":"Burstall",
    "sg:classifiers":[
        {
            "category":"Shopping",
            "subcategory":"Computers & Home Electronics",
            "type":"Retail Goods"
        }
    ],
    "sg:phone":"+1 306 679 2299",
    "sg:postcode":"S0N 0H0",
    "sg:province":"SK",
    "sg:tags":[
        "software"
    ],
    "wof:name":"Wil-Tech Software Ltd",
    "wof:placetype":"venue"
},
  "geometry": {"coordinates":[-109.90460967999999,50.659614563],"type":"Point"}
}