{
  "type": "Feature",
  "properties": {
    "addr:full":"Brampton ON L6T 4S5",
    "addr:postcode":"l6t 4s5",
    "iso:country":"CA",
    "sg:city":"Brampton",
    "sg:classifiers":[
        {
            "category":"Health Services",
            "subcategory":"Podiatrist",
            "type":"Services"
        }
    ],
    "sg:phone":"+1 905 792 4335",
    "sg:postcode":"L6T 4S5",
    "sg:province":"ON",
    "wof:name":"Bramalea Foot Clinic",
    "wof:placetype":"venue"
},
  "geometry": {"coordinates":[-79.7182769775,43.7218399048],"type":"Point"}
}