{
  "type": "Feature",
  "properties": {
    "iso:country":"CA",
    "sg:address":"13204 Henry Ave",
    "sg:city":"Summerland",
    "sg:classifiers":[
        {
            "category":"Organizations",
            "subcategory":"Religious Organization",
            "type":"Services"
        }
    ],
    "sg:phone":"+1 250 494 6181",
    "sg:postcode":"V0H 1Z0",
    "sg:province":"BC",
    "sg:tags":[
        "church"
    ],
    "wof:name":"Summerland United Church",
    "wof:placetype":"venue"
},
  "geometry": {"coordinates":[-119.68238067599999,49.601940155],"type":"Point"}
}