{
  "type": "Feature",
  "properties": {
    "addr:full":"13042 Yonge St Richmond Hill ON L4E 1A3",
    "addr:housenumber":"13042",
    "addr:postcode":"l4e 1a3",
    "addr:street":"Yonge St",
    "iso:country":"CA",
    "sg:address":"13042 Yonge St",
    "sg:city":"Richmond Hill",
    "sg:classifiers":[
        {
            "category":"Retail",
            "subcategory":"Repair Shop",
            "type":"Services"
        }
    ],
    "sg:phone":"+1 905 853 5569",
    "sg:postcode":"L4E 1A3",
    "sg:province":"ON",
    "sg:tags":[
        "lock",
        "locksmith"
    ],
    "wof:name":"Craig Security Inc",
    "wof:placetype":"venue"
},
  "geometry": {"coordinates":[-79.45513200000001,43.945709],"type":"Point"}
}