{
  "type": "Feature",
  "properties": {
    "addr:full":"267 Rue DE LA Baronnie Portneuf QC G0A 2Y0",
    "addr:housenumber":"267",
    "addr:postcode":"g0a 2y0",
    "addr:street":"Rue De La Baronnie",
    "iso:country":"CA",
    "sg:address":"267 Rue DE LA Baronnie",
    "sg:city":"Portneuf",
    "sg:classifiers":[
        {
            "category":"Personal",
            "subcategory":"Beauty Salon",
            "type":"Services"
        }
    ],
    "sg:phone":"+1 418 286 4265",
    "sg:postcode":"G0A 2Y0",
    "sg:province":"QC",
    "wof:name":"Salon Ginette Coiffure",
    "wof:placetype":"venue"
},
  "geometry": {"coordinates":[-71.89218099999999,46.691811],"type":"Point"}
}