{
  "type": "Feature",
  "properties": {
    "iso:country":"CA",
    "sg:city":"Port Hood",
    "sg:classifiers":[
        {
            "category":"Government",
            "subcategory":"Office",
            "type":"Public Place"
        }
    ],
    "sg:phone":"+1 902 787 3221",
    "sg:postcode":"B0E 2W0",
    "sg:province":"NS",
    "wof:name":"Nova Scotia Fisheries",
    "wof:placetype":"venue"
},
  "geometry": {"coordinates":[-61.5306625366,46.0158004761],"type":"Point"}
}