{
  "type": "Feature",
  "properties": {
    "addr:full":"1300 Cariboo Hwy Clinton BC V0K 1K0",
    "addr:housenumber":"1300",
    "addr:postcode":"v0k 1k0",
    "addr:street":"Cariboo Hwy",
    "iso:country":"CA",
    "sg:address":"1300 Cariboo Hwy",
    "sg:city":"Clinton",
    "sg:classifiers":[
        {
            "category":"Shopping",
            "subcategory":"Clothing, Apparel, & Fashions",
            "type":"Retail Goods"
        }
    ],
    "sg:phone":"+1 250 459 2024",
    "sg:postcode":"V0K 1K0",
    "sg:province":"BC",
    "sg:tags":[
        "western"
    ],
    "wof:name":"Clinton Western Wear",
    "wof:placetype":"venue"
},
  "geometry": {"coordinates":[-121.58731079099999,51.0916290283],"type":"Point"}
}