{
  "type": "Feature",
  "properties": {
    "iso:country":"CA",
    "sg:address":"1250 Rue Johnson O",
    "sg:city":"Saint-Hyacinthe",
    "sg:classifiers":[
        {
            "category":"Travel",
            "subcategory":"Hotels & Motels",
            "type":"Entertainment"
        }
    ],
    "sg:phone":"+1 450 774 4418",
    "sg:postcode":"J2S 7K7",
    "sg:province":"QC",
    "wof:name":"Hotel Le Dauphin",
    "wof:placetype":"venue"
},
  "geometry": {"coordinates":[-72.9671630859,45.6410331726],"type":"Point"}
}