{
  "type": "Feature",
  "properties": {
    "addr:full":"4270 Weston Rd North York ON M9L 1W9",
    "addr:housenumber":"4270",
    "addr:postcode":"m9l 1w9",
    "addr:street":"Weston Rd",
    "iso:country":"CA",
    "sg:address":"4270 Weston Rd",
    "sg:city":"North York",
    "sg:classifiers":[
        {
            "category":"Wholesale",
            "subcategory":"Chemicals & Plastics",
            "type":"Manufacturing & Wholesale Goods"
        }
    ],
    "sg:phone":"+1 416 745 1304",
    "sg:postcode":"M9L 1W9",
    "sg:province":"ON",
    "sg:tags":[
        "equipment",
        "welding",
        "gas",
        "supply"
    ],
    "wof:name":"Air Liquide Canada",
    "wof:placetype":"venue"
},
  "geometry": {"coordinates":[-79.546234,43.768208],"type":"Point"}
}