{
  "type": "Feature",
  "properties": {
    "addr:full":"Guelph ON N1H 3R3",
    "addr:postcode":"n1h 3r3",
    "iso:country":"CA",
    "sg:city":"Guelph",
    "sg:classifiers":[
        {
            "category":"Health Services",
            "subcategory":"Doctor",
            "type":"Services"
        }
    ],
    "sg:phone":"+1 519 836 7240",
    "sg:postcode":"N1H 3R3",
    "sg:province":"ON",
    "sg:tags":[
        "physician",
        "surgeon"
    ],
    "wof:name":"Fraser, R Blair MD",
    "wof:placetype":"venue"
},
  "geometry": {"coordinates":[-80.246201,43.540398],"type":"Point"}
}