{
  "type": "Feature",
  "properties": {
    "addr:full":"Mississauga ON L5T 1X2",
    "addr:postcode":"l5t 1x2",
    "iso:country":"CA",
    "sg:city":"Mississauga",
    "sg:classifiers":[
        {
            "category":"Wholesale",
            "subcategory":"Furniture",
            "type":"Manufacturing & Wholesale Goods"
        }
    ],
    "sg:phone":"+1 905 670 8559",
    "sg:postcode":"L5T 1X2",
    "sg:province":"ON",
    "sg:tags":[
        "bathroom",
        "fixture",
        "accessory"
    ],
    "wof:name":"Fasco Die Cast Inc",
    "wof:placetype":"venue"
},
  "geometry": {"coordinates":[-79.666786,43.66193],"type":"Point"}
}