{
  "type": "Feature",
  "properties": {
    "iso:country":"CA",
    "sg:address":"2201 Finch Ave W",
    "sg:city":"North York",
    "sg:classifiers":[
        {
            "category":"Government",
            "subcategory":"Office",
            "type":"Public Place"
        }
    ],
    "sg:phone":"+1 416 744 1882",
    "sg:postcode":"M9M 2Y9",
    "sg:province":"ON",
    "wof:name":"Canada Members of Parliament",
    "wof:placetype":"venue"
},
  "geometry": {"coordinates":[-79.5368423462,43.7530136108],"type":"Point"}
}