{
  "type": "Feature",
  "properties": {
    "addr:full":"Lloydminster AB T9V 2X1",
    "addr:postcode":"t9v 2x1",
    "iso:country":"CA",
    "sg:city":"Lloydminster",
    "sg:classifiers":[
        {
            "category":"Restaurant",
            "type":"Food & Drink"
        }
    ],
    "sg:phone":"+1 780 875 6503",
    "sg:postcode":"T9V 2X1",
    "sg:province":"AB",
    "sg:tags":[
        "pizza"
    ],
    "wof:name":"Pizza Hut",
    "wof:placetype":"venue"
},
  "geometry": {"coordinates":[-110.04170999999999,53.277855],"type":"Point"}
}