{
  "type": "Feature",
  "properties": {
    "addr:full":"232 Main St St Martins NB E5R 1B8",
    "addr:housenumber":"232",
    "addr:postcode":"e5r 1b8",
    "addr:street":"Main St St",
    "iso:country":"CA",
    "sg:address":"232 Main St",
    "sg:city":"St Martins",
    "sg:classifiers":[
        {
            "category":"Health Services",
            "subcategory":"Nursing And Care Facility",
            "type":"Services"
        }
    ],
    "sg:phone":"+1 506 833 2289",
    "sg:postcode":"E5R 1B8",
    "sg:province":"NB",
    "sg:tags":[
        "home",
        "rest"
    ],
    "wof:name":"Fundy Shores Special Care Home",
    "wof:placetype":"venue"
},
  "geometry": {"coordinates":[-65.55317700000001,45.34956],"type":"Point"}
}