{
  "type": "Feature",
  "properties": {
    "iso:country":"CA",
    "sg:address":"2511 Rue Guenette",
    "sg:city":"Saint-Laurent",
    "sg:classifiers":[
        {
            "category":"Manufacturing",
            "subcategory":"Tools & Machinery",
            "type":"Manufacturing & Wholesale Goods"
        }
    ],
    "sg:phone":"+1 514 337 7471",
    "sg:postcode":"H4R 2E9",
    "sg:province":"QC",
    "sg:tags":[
        "thermocouple"
    ],
    "wof:name":"Intempco Controls Ltd",
    "wof:placetype":"venue"
},
  "geometry": {"coordinates":[-73.7298965454,45.5011863708],"type":"Point"}
}