{
  "type": "Feature",
  "properties": {
    "addr:full":"583 Mohawk Rd Hagersville ON N0A 1H0",
    "addr:housenumber":"583",
    "addr:postcode":"n0a 1h0",
    "addr:street":"Mohawk Rd",
    "iso:country":"CA",
    "sg:address":"583 Mohawk Rd",
    "sg:city":"Hagersville",
    "sg:classifiers":[
        {
            "category":"Manufacturing",
            "subcategory":"Printing",
            "type":"Manufacturing & Wholesale Goods"
        }
    ],
    "sg:phone":"+1 519 445 0215",
    "sg:postcode":"N0A 1H0",
    "sg:province":"ON",
    "sg:tags":[
        "screen",
        "sportswear"
    ],
    "wof:name":"G & M Sportswear",
    "wof:placetype":"venue"
},
  "geometry": {"coordinates":[-80.051132,42.962654],"type":"Point"}
}