{
  "type": "Feature",
  "properties": {
    "iso:country":"CA",
    "sg:address":"Farm",
    "sg:city":"Briercrest",
    "sg:classifiers":[
        {
            "category":"Retail",
            "subcategory":"Auto Repair",
            "type":"Services"
        }
    ],
    "sg:phone":"+1 306 799 4437",
    "sg:postcode":"S0H 0K0",
    "sg:province":"SK",
    "sg:tags":[
        "fabricator",
        "painting",
        "aluminum",
        "automobile"
    ],
    "wof:name":"Mid Prairie Body Ctr",
    "wof:placetype":"venue"
},
  "geometry": {"coordinates":[-105.261825562,50.1659355164],"type":"Point"}
}