{
  "type": "Feature",
  "properties": {
    "iso:country":"CA",
    "sg:address":"932 St Laurent Blvd",
    "sg:city":"Ottawa",
    "sg:classifiers":[
        {
            "category":"Restaurant",
            "type":"Food & Drink"
        }
    ],
    "sg:phone":"+1 613 745 4466",
    "sg:postcode":"K1K 3B3",
    "sg:province":"ON",
    "wof:name":"Kfc",
    "wof:placetype":"venue"
},
  "geometry": {"coordinates":[-75.6416320801,45.4313697815],"type":"Point"}
}