{
  "type": "Feature",
  "properties": {
    "addr:full":"2804 33 St Vernon BC V1T 5S5",
    "addr:housenumber":"2804",
    "addr:postcode":"v1t 5s5",
    "addr:street":"33 St",
    "iso:country":"CA",
    "sg:address":"2804 33 St",
    "sg:city":"Vernon",
    "sg:classifiers":[
        {
            "category":"Professional",
            "subcategory":"Computer Services",
            "type":"Services"
        }
    ],
    "sg:phone":"+1 250 558 0033",
    "sg:postcode":"V1T 5S5",
    "sg:province":"BC",
    "sg:tags":[
        "repair",
        "dealer",
        "equipment"
    ],
    "wof:name":"Kelpro Computers Inc",
    "wof:placetype":"venue"
},
  "geometry": {"coordinates":[-119.27533,50.26223],"type":"Point"}
}