{
  "type": "Feature",
  "properties": {
    "addr:full":"651 St Clair Ave W Toronto ON M6C 1A7",
    "addr:housenumber":"651",
    "addr:postcode":"m6c 1a7",
    "addr:street":"St Clair Ave W",
    "iso:country":"CA",
    "sg:address":"651 St Clair Ave W",
    "sg:city":"Toronto",
    "sg:classifiers":[
        {
            "category":"Education",
            "subcategory":"School",
            "type":"Public Place"
        }
    ],
    "sg:phone":"+1 416 651 4480",
    "sg:postcode":"M6C 1A7",
    "sg:province":"ON",
    "wof:name":"Clay Space",
    "wof:placetype":"venue"
},
  "geometry": {"coordinates":[-79.42440000000001,43.681877],"type":"Point"}
}