{
  "type": "Feature",
  "properties": {
    "addr:full":"Bedford NS B4A 1E6",
    "addr:postcode":"b4a 1e6",
    "iso:country":"CA",
    "sg:city":"Bedford",
    "sg:classifiers":[
        {
            "category":"Wholesale",
            "subcategory":"Electrical",
            "type":"Manufacturing & Wholesale Goods"
        }
    ],
    "sg:phone":"+1 902 835 6330",
    "sg:postcode":"B4A 1E6",
    "sg:province":"NS",
    "sg:tags":[
        "control"
    ],
    "wof:name":"Vci Controls Inc",
    "wof:placetype":"venue"
},
  "geometry": {"coordinates":[-63.6574745178,44.7319450378],"type":"Point"}
}