{
  "type": "Feature",
  "properties": {
    "addr:full":"4142 Rte Marie-Victorin Saint-Robert QC J0G 1S0",
    "addr:housenumber":"4142",
    "addr:postcode":"j0g 1s0",
    "addr:street":"Rte Marie-Victorin",
    "iso:country":"CA",
    "sg:address":"4142 Rte Marie-Victorin",
    "sg:city":"Saint-Robert",
    "sg:classifiers":[
        {
            "category":"Home & Garden",
            "subcategory":"Furniture",
            "type":"Retail Goods"
        }
    ],
    "sg:phone":"+1 450 782 3166",
    "sg:postcode":"J0G 1S0",
    "sg:province":"QC",
    "sg:tags":[
        "equipment",
        "kitchen",
        "cabinet"
    ],
    "wof:name":"Menuiserie Theriault Inc",
    "wof:placetype":"venue"
},
  "geometry": {"coordinates":[-73.0136642456,46.012840271],"type":"Point"}
}