{
  "type": "Feature",
  "properties": {
    "addr:full":"4 River St Parry Sound ON P2A 2T6",
    "addr:housenumber":"4",
    "addr:postcode":"p2a 2t6",
    "addr:street":"River St",
    "iso:country":"CA",
    "sg:address":"4 River St",
    "sg:city":"Parry Sound",
    "sg:classifiers":[
        {
            "category":"Retail",
            "subcategory":"Laundry & Dry Cleaning",
            "type":"Services"
        }
    ],
    "sg:phone":"+1 705 746 5013",
    "sg:postcode":"P2A 2T6",
    "sg:province":"ON",
    "sg:tags":[
        "cleaners"
    ],
    "wof:name":"Newton's Dry Cleaners",
    "wof:placetype":"venue"
},
  "geometry": {"coordinates":[-80.03043365480001,45.3442001343],"type":"Point"}
}