{
  "type": "Feature",
  "properties": {
    "iso:country":"CA",
    "sg:address":"390 Lakeshore Rd E",
    "sg:city":"Mississauga",
    "sg:classifiers":[
        {
            "category":"Personal",
            "subcategory":"Beauty Salon",
            "type":"Services"
        }
    ],
    "sg:phone":"+1 905 278 9070",
    "sg:postcode":"L5G 1H5",
    "sg:province":"ON",
    "wof:name":"Silvenzo House of Hair Design",
    "wof:placetype":"venue"
},
  "geometry": {"coordinates":[-79.57238769529999,43.5638694763],"type":"Point"}
}