{
  "type": "Feature",
  "properties": {
    "addr:full":"1388 Rue Fleury E Montreal QC H2C 1R5",
    "addr:housenumber":"1388",
    "addr:postcode":"h2c 1r5",
    "addr:street":"Rue Fleury E",
    "iso:country":"CA",
    "sg:address":"1388 Rue Fleury E",
    "sg:city":"Montreal",
    "sg:classifiers":[
        {
            "category":"Social Services",
            "type":"Services"
        }
    ],
    "sg:phone":"+1 514 383 1222",
    "sg:postcode":"H2C 1R5",
    "sg:province":"QC",
    "sg:tags":[
        "house",
        "senior",
        "cleaning",
        "citizen"
    ],
    "wof:name":"Services D'Aide Remue-Menage",
    "wof:placetype":"venue"
},
  "geometry": {"coordinates":[-73.6573181152,45.56092453],"type":"Point"}
}