{
  "type": "Feature",
  "properties": {
    "addr:full":"110 Wilson St W Ancaster ON L9G 1N3",
    "addr:housenumber":"110",
    "addr:postcode":"l9g 1n3",
    "addr:street":"Wilson St W",
    "iso:country":"CA",
    "sg:address":"110 Wilson St W",
    "sg:city":"Ancaster",
    "sg:classifiers":[
        {
            "category":"Retail",
            "subcategory":"Veterinary Services",
            "type":"Services"
        }
    ],
    "sg:phone":"+1 905 648 2142",
    "sg:postcode":"L9G 1N3",
    "sg:province":"ON",
    "sg:tags":[
        "veterinarian"
    ],
    "wof:name":"Ancaster Animal Hospital",
    "wof:placetype":"venue"
},
  "geometry": {"coordinates":[-79.9917755127,43.2146911621],"type":"Point"}
}