{
  "type": "Feature",
  "properties": {
    "addr:full":"3625 Rue Belanger Montreal QC H1X 1B2",
    "addr:housenumber":"3625",
    "addr:postcode":"h1x 1b2",
    "addr:street":"Rue Belanger",
    "iso:country":"CA",
    "sg:address":"3625 Rue Belanger",
    "sg:city":"Montreal",
    "sg:classifiers":[
        {
            "category":"Personal",
            "subcategory":"Beauty Salon",
            "type":"Services"
        }
    ],
    "sg:phone":"+1 514 728 3360",
    "sg:postcode":"H1X 1B2",
    "sg:province":"QC",
    "wof:name":"Salon Eve Haute Coiffure",
    "wof:placetype":"venue"
},
  "geometry": {"coordinates":[-73.590996,45.560986],"type":"Point"}
}