{
  "type": "Feature",
  "properties": {
    "addr:full":"Island 1147 Lake Temagami Temagami ON P0H 2H0",
    "addr:housenumber":"1147",
    "addr:postcode":"p0h 2h0",
    "addr:street":"Island;Lake Temagami",
    "iso:country":"CA",
    "sg:address":"Island 1147 Lake Temagami",
    "sg:city":"Temagami",
    "sg:classifiers":[
        {
            "category":"Travel",
            "subcategory":"Hotels & Motels",
            "type":"Entertainment"
        }
    ],
    "sg:phone":"+1 705 237 8629",
    "sg:postcode":"P0H 2H0",
    "sg:province":"ON",
    "sg:tags":[
        "resort"
    ],
    "wof:name":"Keewaydin Camp",
    "wof:placetype":"venue"
},
  "geometry": {"coordinates":[-79.789551,47.065605],"type":"Point"}
}