{
  "type": "Feature",
  "properties": {
    "addr:full":"Lloydminster AB T9V 0B5",
    "addr:postcode":"t9v 0b5",
    "iso:country":"CA",
    "sg:city":"Lloydminster",
    "sg:classifiers":[
        {
            "category":"Restaurant",
            "type":"Food & Drink"
        }
    ],
    "sg:phone":"+1 780 875 7700",
    "sg:postcode":"T9V 0B5",
    "sg:province":"AB",
    "wof:name":"Subway Sandwiches & Salads",
    "wof:placetype":"venue"
},
  "geometry": {"coordinates":[-110.018158,53.278244],"type":"Point"}
}