{
  "type": "Feature",
  "properties": {
    "addr:full":"4439 Greenview Dr NE Calgary AB T2E 5R3",
    "addr:housenumber":"4439",
    "addr:postcode":"t2e 5r3",
    "addr:street":"Greenview Dr Ne",
    "iso:country":"CA",
    "sg:address":"4439 Greenview Dr NE",
    "sg:city":"Calgary",
    "sg:classifiers":[
        {
            "category":"Manufacturing",
            "subcategory":"Printing",
            "type":"Manufacturing & Wholesale Goods"
        }
    ],
    "sg:phone":"+1 403 277 4098",
    "sg:postcode":"T2E 5R3",
    "sg:province":"AB",
    "sg:tags":[
        "screen"
    ],
    "wof:name":"Random Art Design",
    "wof:placetype":"venue"
},
  "geometry": {"coordinates":[-114.056366,51.091412],"type":"Point"}
}