{
  "type": "Feature",
  "properties": {
    "addr:full":"1513 Wembury Rd Mississauga ON L5J 2L8",
    "addr:housenumber":"1513",
    "addr:postcode":"l5j 2l8",
    "addr:street":"Wembury Rd",
    "iso:country":"CA",
    "sg:address":"1513 Wembury Rd",
    "sg:city":"Mississauga",
    "sg:classifiers":[
        {
            "category":"Building & Trades",
            "subcategory":"Landscaping Services",
            "type":"Services"
        }
    ],
    "sg:phone":"+1 905 823 3213",
    "sg:postcode":"L5J 2L8",
    "sg:province":"ON",
    "sg:tags":[
        "landscape",
        "contractor"
    ],
    "wof:name":"Pioneer Landscaping Inc",
    "wof:placetype":"venue"
},
  "geometry": {"coordinates":[-79.633286,43.533993],"type":"Point"}
}