{
  "type": "Feature",
  "properties": {
    "addr:full":"Victoria BC V8W 2A5",
    "addr:postcode":"v8w 2a5",
    "iso:country":"CA",
    "sg:city":"Victoria",
    "sg:classifiers":[
        {
            "category":"Shopping",
            "subcategory":"Computers & Home Electronics",
            "type":"Retail Goods"
        }
    ],
    "sg:phone":"+1 250 360 2634",
    "sg:postcode":"V8W 2A5",
    "sg:province":"BC",
    "sg:tags":[
        "software"
    ],
    "wof:name":"Oracle Corp Canada Inc",
    "wof:placetype":"venue"
},
  "geometry": {"coordinates":[-123.366470337,48.4263191223],"type":"Point"}
}