{
  "type": "Feature",
  "properties": {
    "addr:full":"332 Rue DE Quen Dolbeau-Mistassini QC G8L 5N1",
    "addr:housenumber":"332",
    "addr:postcode":"g8l 5n1",
    "addr:street":"Rue De Quen",
    "iso:country":"CA",
    "sg:address":"332 Rue DE Quen",
    "sg:city":"Dolbeau-Mistassini",
    "sg:classifiers":[
        {
            "category":"Food & Beverages",
            "subcategory":"Groceries & Convenience Stores",
            "type":"Retail Goods"
        }
    ],
    "sg:phone":"+1 418 276 3382",
    "sg:postcode":"G8L 5N1",
    "sg:province":"QC",
    "wof:name":"Depanneur Jean-Lou",
    "wof:placetype":"venue"
},
  "geometry": {"coordinates":[-72.1994552612,48.8801498413],"type":"Point"}
}