{
  "type": "Feature",
  "properties": {
    "addr:full":"182 Cree Rd Sherwood Park AB T8A 3X8",
    "addr:housenumber":"182",
    "addr:postcode":"t8a 3x8",
    "addr:street":"Cree Rd",
    "iso:country":"CA",
    "sg:address":"182 Cree Rd",
    "sg:city":"Sherwood Park",
    "sg:classifiers":[
        {
            "category":"Retail",
            "subcategory":"Repair Shop",
            "type":"Services"
        }
    ],
    "sg:phone":"+1 780 449 3182",
    "sg:postcode":"T8A 3X8",
    "sg:province":"AB",
    "sg:tags":[
        "welding"
    ],
    "wof:name":"Ferrous Fabricators",
    "wof:placetype":"venue"
},
  "geometry": {"coordinates":[-113.32939910899999,53.5377502441],"type":"Point"}
}