{
  "type": "Feature",
  "properties": {
    "addr:full":"Pictou NS B0K 1H0",
    "addr:postcode":"b0k 1h0",
    "iso:country":"CA",
    "sg:city":"Pictou",
    "sg:classifiers":[
        {
            "category":"Travel",
            "subcategory":"Hotels & Motels",
            "type":"Entertainment"
        }
    ],
    "sg:phone":"+1 902 485 4157",
    "sg:postcode":"B0K 1H0",
    "sg:province":"NS",
    "wof:name":"Lionstone Inn",
    "wof:placetype":"venue"
},
  "geometry": {"coordinates":[-62.724754,45.679417],"type":"Point"}
}