{
  "type": "Feature",
  "properties": {
    "addr:full":"22 Viaduc Rd Shediac Bridge NB E4R 1Z7",
    "addr:housenumber":"22",
    "addr:postcode":"e4r 1z7",
    "addr:street":"Viaduc Rd",
    "iso:country":"CA",
    "sg:address":"22 Viaduc Rd",
    "sg:city":"Shediac Bridge",
    "sg:classifiers":[
        {
            "category":"Retail",
            "subcategory":"Auto Repair",
            "type":"Services"
        }
    ],
    "sg:phone":"+1 506 532 5676",
    "sg:postcode":"E4R 1Z7",
    "sg:province":"NB",
    "sg:tags":[
        "repairing",
        "automobile"
    ],
    "wof:name":"Tony's Esso",
    "wof:placetype":"venue"
},
  "geometry": {"coordinates":[-64.579033,46.277241],"type":"Point"}
}