{
  "type": "Feature",
  "properties": {
    "addr:full":"48 Francis St N Kitchener ON N2H 5B5",
    "addr:housenumber":"48",
    "addr:postcode":"n2h 5b5",
    "addr:street":"Francis St N",
    "iso:country":"CA",
    "sg:address":"48 Francis St N",
    "sg:city":"Kitchener",
    "sg:classifiers":[
        {
            "category":"Professional",
            "subcategory":"Accounting & Tax Preparation",
            "type":"Services"
        }
    ],
    "sg:phone":"+1 519 570 2515",
    "sg:postcode":"N2H 5B5",
    "sg:province":"ON",
    "sg:tags":[
        "consultant"
    ],
    "wof:name":"William Squibb & Assoc",
    "wof:placetype":"venue"
},
  "geometry": {"coordinates":[-80.49458312989999,43.4535102844],"type":"Point"}
}