{
  "type": "Feature",
  "properties": {
    "addr:full":"2825 25E Av Saint-Prosper-DE-Dorchester QC G0M 1Y0",
    "addr:housenumber":"2825",
    "addr:postcode":"g0m 1y0",
    "addr:street":"25E Av Saint-Prosper-De-Dorchester",
    "iso:country":"CA",
    "sg:address":"2825 25E Av",
    "sg:city":"Saint-Prosper-DE-Dorchester",
    "sg:classifiers":[
        {
            "category":"Social Services",
            "subcategory":"Child Care",
            "type":"Services"
        }
    ],
    "sg:phone":"+1 418 594 6161",
    "sg:postcode":"G0M 1Y0",
    "sg:province":"QC",
    "wof:name":"Centre DE LA Petite Enfance",
    "wof:placetype":"venue"
},
  "geometry": {"coordinates":[-70.497749,46.221554],"type":"Point"}
}