{
  "type": "Feature",
  "properties": {
    "addr:full":"1 Delorme Pl St Albert AB T8N 4V8",
    "addr:housenumber":"1",
    "addr:postcode":"t8n 4v8",
    "addr:street":"Delorme Pl",
    "iso:country":"CA",
    "sg:address":"1 Delorme Pl",
    "sg:city":"St Albert",
    "sg:classifiers":[
        {
            "category":"Arts & Performance",
            "subcategory":"Theater",
            "type":"Entertainment"
        }
    ],
    "sg:phone":"+1 780 460 2607",
    "sg:postcode":"T8N 4V8",
    "sg:province":"AB",
    "sg:tags":[
        "live",
        "music"
    ],
    "wof:name":"Garry Robertson Music Svc Inc",
    "wof:placetype":"venue"
},
  "geometry": {"coordinates":[-113.63312530499999,53.6546440125],"type":"Point"}
}