{
  "type": "Feature",
  "properties": {
    "addr:full":"New Westminster BC V3M 1K6",
    "addr:postcode":"v3m 1k6",
    "iso:country":"CA",
    "sg:city":"New Westminster",
    "sg:classifiers":[
        {
            "category":"Retail",
            "subcategory":"Auto Repair",
            "type":"Services"
        }
    ],
    "sg:phone":"+1 604 520 3222",
    "sg:postcode":"V3M 1K6",
    "sg:province":"BC",
    "sg:tags":[
        "repairing",
        "automobile",
        "starter",
        "alternator"
    ],
    "wof:name":"Amayak Auto Svc",
    "wof:placetype":"venue"
},
  "geometry": {"coordinates":[-122.91876999999999,49.202141],"type":"Point"}
}