{
  "type": "Feature",
  "properties": {
    "addr:full":"6500 Rte Transcanadienne Saint-Laurent QC H4T 1X4",
    "addr:postcode":"6500;h4t 1x4",
    "addr:street":"Rte Transcanadienne",
    "iso:country":"CA",
    "sg:address":"6500 Rte Transcanadienne",
    "sg:city":"Saint-Laurent",
    "sg:classifiers":[
        {
            "category":"Manufacturing",
            "subcategory":"Metals",
            "type":"Manufacturing & Wholesale Goods"
        }
    ],
    "sg:phone":"+1 514 344 0200",
    "sg:postcode":"H4T 1X4",
    "sg:province":"QC",
    "sg:tags":[
        "steel"
    ],
    "wof:name":"Specialties Mandrin Csi Inc",
    "wof:placetype":"venue"
},
  "geometry": {"coordinates":[-73.69058200000001,45.493919],"type":"Point"}
}