{
  "type": "Feature",
  "properties": {
    "addr:full":"Calgary AB T2H 2M5",
    "addr:postcode":"t2h 2m5",
    "iso:country":"CA",
    "sg:city":"Calgary",
    "sg:classifiers":[
        {
            "category":"Professional",
            "subcategory":"Advertising",
            "type":"Services"
        }
    ],
    "sg:phone":"+1 403 255 9668",
    "sg:postcode":"T2H 2M5",
    "sg:province":"AB",
    "sg:tags":[
        "counselor"
    ],
    "wof:name":"Ad Avenue Advertising Inc",
    "wof:placetype":"venue"
},
  "geometry": {"coordinates":[-114.069366,51.001511],"type":"Point"}
}