{
  "type": "Feature",
  "properties": {
    "addr:full":"7018 14'th Av. Burnaby V3N 1Z2",
    "addr:housenumber":"7018",
    "addr:postcode":"v3n 1z2",
    "addr:street":"14'Th Av.",
    "iso:country":"CA",
    "sg:address":"7018 14'th Av.",
    "sg:city":"Burnaby",
    "sg:classifiers":[
        {
            "category":"Professional",
            "subcategory":"Advertising",
            "type":"Services"
        }
    ],
    "sg:postcode":"V3N 1Z2",
    "sg:tags":[
        "legal-advertising",
        "lawyer-advertising",
        "lawyer-directory",
        "attorney-directory",
        "legal-directory"
    ],
    "sg:website":"http://www.legalx.net",
    "wof:name":"LegalX Inc.",
    "wof:placetype":"venue"
},
  "geometry": {"coordinates":[-122.9534652,49.2101468],"type":"Point"}
}