{
  "type": "Feature",
  "properties": {
    "addr:full":"3775 Fairgrounds Rd Orillia ON L3V 6H2",
    "addr:housenumber":"3775",
    "addr:postcode":"l3v 6h2",
    "addr:street":"Fairgrounds Rd",
    "iso:country":"CA",
    "sg:address":"3775 Fairgrounds Rd",
    "sg:city":"Orillia",
    "sg:classifiers":[
        {
            "category":"Retail",
            "subcategory":"Repair Shop",
            "type":"Services"
        }
    ],
    "sg:phone":"+1 705 326 7902",
    "sg:postcode":"L3V 6H2",
    "sg:province":"ON",
    "sg:tags":[
        "welding"
    ],
    "wof:name":"Deco Welding",
    "wof:placetype":"venue"
},
  "geometry": {"coordinates":[-79.418228,44.60659],"type":"Point"}
}