{
  "type": "Feature",
  "properties": {
    "addr:full":"39 Bishop St Toronto ON M5R 1N3",
    "addr:housenumber":"39",
    "addr:postcode":"m5r 1n3",
    "addr:street":"Bishop St",
    "iso:country":"CA",
    "sg:address":"39 Bishop St",
    "sg:city":"Toronto",
    "sg:classifiers":[
        {
            "category":"Professional",
            "subcategory":"Management & Consulting",
            "type":"Services"
        }
    ],
    "sg:phone":"+1 416 961 8559",
    "sg:postcode":"M5R 1N3",
    "sg:province":"ON",
    "sg:tags":[
        "marketing",
        "consultant"
    ],
    "wof:name":"Stewart Consulting Group",
    "wof:placetype":"venue"
},
  "geometry": {"coordinates":[-79.392624,43.673912],"type":"Point"}
}