{
  "type": "Feature",
  "properties": {
    "addr:full":"833 10 Ave SW Calgary AB T2R 0B4",
    "addr:postcode":"t2r 0b4",
    "addr:street":"833 10 Ave Sw",
    "iso:country":"CA",
    "sg:address":"833 10 Ave SW",
    "sg:city":"Calgary",
    "sg:classifiers":[
        {
            "category":"Personal",
            "subcategory":"Beauty Salon",
            "type":"Services"
        }
    ],
    "sg:phone":"+1 403 262 7001",
    "sg:postcode":"T2R 0B4",
    "sg:province":"AB",
    "wof:name":"Melanie's Hair Group",
    "wof:placetype":"venue"
},
  "geometry": {"coordinates":[-114.079826,51.043659],"type":"Point"}
}