{
  "type": "Feature",
  "properties": {
    "addr:full":"Vancouver BC V5W 2C8",
    "addr:postcode":"v5w 2c8",
    "iso:country":"CA",
    "sg:city":"Vancouver",
    "sg:classifiers":[
        {
            "category":"Health Services",
            "subcategory":"Health Practitioner",
            "type":"Services"
        }
    ],
    "sg:phone":"+1 604 879 9686",
    "sg:postcode":"V5W 2C8",
    "sg:province":"BC",
    "sg:tags":[
        "acupuncture"
    ],
    "wof:name":"Omei Integrated Chinese",
    "wof:placetype":"venue"
},
  "geometry": {"coordinates":[-123.101860046,49.2266197205],"type":"Point"}
}