{
  "type": "Feature",
  "properties": {
    "addr:full":"405 James St S Thunder Bay ON P7E 2V6",
    "addr:housenumber":"405",
    "addr:postcode":"p7e 2v6",
    "addr:street":"James St S",
    "iso:country":"CA",
    "sg:address":"405 James St S",
    "sg:city":"Thunder Bay",
    "sg:classifiers":[
        {
            "category":"Banks & Credit Unions",
            "subcategory":"Bank",
            "type":"Services"
        }
    ],
    "sg:phone":"+1 807 626 5666",
    "sg:postcode":"P7E 2V6",
    "sg:province":"ON",
    "wof:name":"Provincial Alliance Cu Ltd",
    "wof:placetype":"venue"
},
  "geometry": {"coordinates":[-89.289749,48.380432],"type":"Point"}
}