{
  "type": "Feature",
  "properties": {
    "addr:full":"1480 Lansdowne Rd Westville NS B0K 2A0",
    "addr:housenumber":"1480",
    "addr:postcode":"b0k 2a0",
    "addr:street":"Lansdowne Rd",
    "iso:country":"CA",
    "sg:address":"1480 Lansdowne Rd",
    "sg:city":"Westville",
    "sg:classifiers":[
        {
            "category":"Recreation",
            "type":"Entertainment"
        }
    ],
    "sg:phone":"+1 902 396 4470",
    "sg:postcode":"B0K 2A0",
    "sg:province":"NS",
    "sg:tags":[
        "provincial",
        "center",
        "parks"
    ],
    "wof:name":"Lorda",
    "wof:placetype":"venue"
},
  "geometry": {"coordinates":[-62.7099075317,45.5617599487],"type":"Point"}
}