{
  "type": "Feature",
  "properties": {
    "iso:country":"CA",
    "sg:address":"2044 Rue Fleury E",
    "sg:city":"Montreal",
    "sg:classifiers":[
        {
            "category":"Health Services",
            "subcategory":"Doctor",
            "type":"Services"
        }
    ],
    "sg:phone":"+1 514 387 7109",
    "sg:postcode":"H2B 1J2",
    "sg:province":"QC",
    "sg:tags":[
        "dentist"
    ],
    "wof:name":"Provencal, Benoit DDS",
    "wof:placetype":"venue"
},
  "geometry": {"coordinates":[-73.651276,45.570797],"type":"Point"}
}