{
  "type": "Feature",
  "properties": {
    "addr:full":"East York ON M4K 3Y1",
    "addr:postcode":"m4k 3y1",
    "iso:country":"CA",
    "sg:city":"East York",
    "sg:classifiers":[
        {
            "category":"Health Services",
            "subcategory":"Health Practitioner",
            "type":"Services"
        }
    ],
    "sg:phone":"+1 416 778 5799",
    "sg:postcode":"M4K 3Y1",
    "sg:province":"ON",
    "sg:tags":[
        "psychologist"
    ],
    "wof:name":"Weiner, M PhD",
    "wof:placetype":"venue"
},
  "geometry": {"coordinates":[-79.3575744629,43.6820335388],"type":"Point"}
}