{
  "type": "Feature",
  "properties": {
    "addr:full":"5400 Harvester Rd Burlington ON L7L 5N5",
    "addr:housenumber":"5400",
    "addr:postcode":"l7l 5n5",
    "addr:street":"Harvester Rd",
    "iso:country":"CA",
    "sg:address":"5400 Harvester Rd",
    "sg:city":"Burlington",
    "sg:classifiers":[
        {
            "category":"Manufacturing",
            "subcategory":"Metals",
            "type":"Manufacturing & Wholesale Goods"
        }
    ],
    "sg:phone":"+1 905 681 6811",
    "sg:postcode":"L7L 5N5",
    "sg:province":"ON",
    "sg:tags":[
        "steel",
        "mills"
    ],
    "wof:name":"Laurel Steel Corp",
    "wof:placetype":"venue"
},
  "geometry": {"coordinates":[-79.756165,43.388203],"type":"Point"}
}