{
  "type": "Feature",
  "properties": {
    "addr:full":"41 Botsford St Moncton NB E1C 4W8",
    "addr:housenumber":"41",
    "addr:postcode":"e1c 4w8",
    "addr:street":"Botsford St",
    "iso:country":"CA",
    "sg:address":"41 Botsford St",
    "sg:city":"Moncton",
    "sg:classifiers":[
        {
            "category":"Shopping",
            "subcategory":"Jewelry",
            "type":"Retail Goods"
        }
    ],
    "sg:phone":"+1 506 857 1980",
    "sg:postcode":"E1C 4W8",
    "sg:province":"NB",
    "sg:tags":[
        "jeweler"
    ],
    "wof:name":"LA Mine D'Or Jewellers",
    "wof:placetype":"venue"
},
  "geometry": {"coordinates":[-64.7761230469,46.0899734497],"type":"Point"}
}