{
  "type": "Feature",
  "properties": {
    "addr:full":"Toronto ON M4K 3Z1",
    "addr:postcode":"m4k 3z1",
    "iso:country":"CA",
    "sg:city":"Toronto",
    "sg:classifiers":[
        {
            "category":"Health Services",
            "subcategory":"Doctor",
            "type":"Services"
        }
    ],
    "sg:phone":"+1 416 466 8899",
    "sg:postcode":"M4K 3Z1",
    "sg:province":"ON",
    "sg:tags":[
        "physician",
        "surgeon"
    ],
    "wof:name":"Adatia, A MD",
    "wof:placetype":"venue"
},
  "geometry": {"coordinates":[-79.35792499999999,43.679596],"type":"Point"}
}