{
  "type": "Feature",
  "properties": {
    "addr:full":"2475 Boul Chomedey Laval QC H7T 2R2",
    "addr:housenumber":"2475",
    "addr:postcode":"h7t 2r2",
    "addr:street":"Boul Chomedey",
    "iso:country":"CA",
    "sg:address":"2475 Boul Chomedey",
    "sg:city":"Laval",
    "sg:classifiers":[
        {
            "category":"Autos & Motor Vehicles",
            "subcategory":"Automobile Sales",
            "type":"Retail Goods"
        }
    ],
    "sg:phone":"+1 450 681 8110",
    "sg:postcode":"H7T 2R2",
    "sg:province":"QC",
    "sg:tags":[
        "car",
        "dealer"
    ],
    "wof:name":"Arbour Volkswagen",
    "wof:placetype":"venue"
},
  "geometry": {"coordinates":[-73.760437,45.564568],"type":"Point"}
}