{
  "type": "Feature",
  "properties": {
    "addr:full":"5957 103A St NW Edmonton AB T6H 2J7",
    "addr:housenumber":"5957",
    "addr:postcode":"t6h 2j7",
    "addr:street":"103A St Nw",
    "iso:country":"CA",
    "sg:address":"5957 103A St NW",
    "sg:city":"Edmonton",
    "sg:classifiers":[
        {
            "category":"Building & Trades",
            "subcategory":"Construction",
            "type":"Services"
        }
    ],
    "sg:phone":"+1 780 438 3131",
    "sg:postcode":"T6H 2J7",
    "sg:province":"AB",
    "sg:tags":[
        "insulation",
        "heat",
        "contractor"
    ],
    "wof:name":"Western Foamcoaters Ltd",
    "wof:placetype":"venue"
},
  "geometry": {"coordinates":[-113.49479700000001,53.496601],"type":"Point"}
}