{
  "type": "Feature",
  "properties": {
    "iso:country":"CA",
    "sg:address":"25 Spy Crt",
    "sg:city":"Markham",
    "sg:classifiers":[
        {
            "category":"Home & Garden",
            "subcategory":"Furniture",
            "type":"Retail Goods"
        }
    ],
    "sg:phone":"+1 905 475 0185",
    "sg:postcode":"L3R 5H6",
    "sg:province":"ON",
    "sg:tags":[
        "top",
        "counter",
        "kitchen",
        "cabinet"
    ],
    "wof:name":"Janovski Counter Tops",
    "wof:placetype":"venue"
},
  "geometry": {"coordinates":[-79.35712432859999,43.8555908203],"type":"Point"}
}