{
  "type": "Feature",
  "properties": {
    "addr:full":"40 Boul Des Bois-Francs N Victoriaville QC G6P 1E5",
    "addr:housenumber":"40",
    "addr:postcode":"g6p 1e5",
    "addr:street":"Boul Des Bois-Francs N",
    "iso:country":"CA",
    "sg:address":"40 Boul Des Bois-Francs N",
    "sg:city":"Victoriaville",
    "sg:classifiers":[
        {
            "category":"Education",
            "subcategory":"School",
            "type":"Public Place"
        }
    ],
    "sg:phone":"+1 819 758 6453",
    "sg:postcode":"G6P 1E5",
    "sg:province":"QC",
    "wof:name":"Commission Scolaire-Boisfrancs",
    "wof:placetype":"venue"
},
  "geometry": {"coordinates":[-71.9522399902,46.0592536926],"type":"Point"}
}