{
  "type": "Feature",
  "properties": {
    "addr:full":"200 Front St W Toronto ON M5V 3K2",
    "addr:housenumber":"200",
    "addr:postcode":"m5v 3k2",
    "addr:street":"Front St W",
    "iso:country":"CA",
    "sg:address":"200 Front St W",
    "sg:city":"Toronto",
    "sg:classifiers":[
        {
            "category":"Social Services",
            "subcategory":"Child Care",
            "type":"Services"
        }
    ],
    "sg:phone":"+1 416 340 8757",
    "sg:postcode":"M5V 3K2",
    "sg:province":"ON",
    "wof:name":"Day Care Connection",
    "wof:placetype":"venue"
},
  "geometry": {"coordinates":[-79.385445,43.644787],"type":"Point"}
}