{
  "type": "Feature",
  "properties": {
    "iso:country":"CA",
    "sg:address":"425 Rue Racine E",
    "sg:city":"Chicoutimi",
    "sg:classifiers":[
        {
            "category":"Restaurant",
            "type":"Food & Drink"
        }
    ],
    "sg:phone":"+1 418 690 3030",
    "sg:postcode":"G7H 1T5",
    "sg:province":"QC",
    "wof:name":"Mikes Restaurant",
    "wof:placetype":"venue"
},
  "geometry": {"coordinates":[-71.0552062988,48.4283790588],"type":"Point"}
}