{
  "type": "Feature",
  "properties": {
    "iso:country":"CA",
    "sg:address":"5545 Ch Upper Lachine",
    "sg:city":"Montreal",
    "sg:classifiers":[
        {
            "category":"Restaurant",
            "type":"Food & Drink"
        }
    ],
    "sg:phone":"+1 514 485 0235",
    "sg:postcode":"H4A 2A5",
    "sg:province":"QC",
    "wof:name":"Agostini Restaurant",
    "wof:placetype":"venue"
},
  "geometry": {"coordinates":[-73.6081771851,45.470161438],"type":"Point"}
}