{
  "type": "Feature",
  "properties": {
    "iso:country":"CA",
    "sg:address":"50 Carolina Ave",
    "sg:city":"Stephenville",
    "sg:classifiers":[
        {
            "category":"Real Estate",
            "subcategory":"Real Estate Agent",
            "type":"Services"
        }
    ],
    "sg:phone":"+1 709 643 6382",
    "sg:postcode":"A2N 2S3",
    "sg:province":"NL",
    "sg:tags":[
        "cooperative"
    ],
    "wof:name":"Indian Head Consumers CO-OP",
    "wof:placetype":"venue"
},
  "geometry": {"coordinates":[-58.565186,48.551273],"type":"Point"}
}