{
  "type": "Feature",
  "properties": {
    "iso:country":"CA",
    "sg:address":"3932 Chesswood Dr",
    "sg:city":"North York",
    "sg:classifiers":[
        {
            "category":"Utilities",
            "subcategory":"Natural Gas",
            "type":"Services"
        }
    ],
    "sg:phone":"+1 416 631 8176",
    "sg:postcode":"M3J 2W6",
    "sg:province":"ON",
    "sg:tags":[
        "company"
    ],
    "wof:name":"Ossom Enterprises Inc",
    "wof:placetype":"venue"
},
  "geometry": {"coordinates":[-79.47486877439999,43.7567176819],"type":"Point"}
}