{
  "type": "Feature",
  "properties": {
    "addr:full":"6 Denison Ave Toronto ON M5T 2M4",
    "addr:housenumber":"6",
    "addr:postcode":"m5t 2m4",
    "addr:street":"Denison Ave",
    "iso:country":"CA",
    "sg:address":"6 Denison Ave",
    "sg:city":"Toronto",
    "sg:classifiers":[
        {
            "category":"Organizations",
            "subcategory":"Professional Association",
            "type":"Services"
        }
    ],
    "sg:phone":"+1 416 504 8404",
    "sg:postcode":"M5T 2M4",
    "sg:province":"ON",
    "wof:name":"Federation of Russian Canadian",
    "wof:placetype":"venue"
},
  "geometry": {"coordinates":[-79.400879,43.648117],"type":"Point"}
}