{
  "type": "Feature",
  "properties": {
    "addr:full":"46 Milvan Dr North York ON M9L 1Z3",
    "addr:housenumber":"46",
    "addr:postcode":"m9l 1z3",
    "addr:street":"Milvan Dr",
    "iso:country":"CA",
    "sg:address":"46 Milvan Dr",
    "sg:city":"North York",
    "sg:classifiers":[
        {
            "category":"Home & Garden",
            "subcategory":"Furniture",
            "type":"Retail Goods"
        }
    ],
    "sg:phone":"+1 416 741 7730",
    "sg:postcode":"M9L 1Z3",
    "sg:province":"ON",
    "sg:tags":[
        "top",
        "counter",
        "kitchen",
        "cabinet"
    ],
    "wof:name":"Nor Will Mfg CO Ltd",
    "wof:placetype":"venue"
},
  "geometry": {"coordinates":[-79.554642,43.753368],"type":"Point"}
}