{
  "type": "Feature",
  "properties": {
    "addr:full":"Whytewold Rd Winnipeg MB R3J 3Y5",
    "addr:postcode":"r3j 3y5",
    "addr:street":"Whytewold Rd",
    "iso:country":"CA",
    "sg:address":"Whytewold Rd",
    "sg:city":"Winnipeg",
    "sg:classifiers":[
        {
            "category":"Insurance",
            "subcategory":"Insurance Agent",
            "type":"Services"
        }
    ],
    "sg:phone":"+1 204 889 2204",
    "sg:postcode":"R3J 3Y5",
    "sg:province":"MB",
    "wof:name":"Baldwinson Agencies Ltd",
    "wof:placetype":"venue"
},
  "geometry": {"coordinates":[-97.2545471191,49.8775939941],"type":"Point"}
}