{
  "type": "Feature",
  "properties": {
    "iso:country":"CA",
    "sg:address":"3450 Hastings St E",
    "sg:city":"Vancouver",
    "sg:classifiers":[
        {
            "category":"Restaurant",
            "type":"Food & Drink"
        }
    ],
    "sg:phone":"+1 604 718 1099",
    "sg:postcode":"V5K 2A6",
    "sg:province":"BC",
    "wof:name":"Mc Donald's",
    "wof:placetype":"venue"
},
  "geometry": {"coordinates":[-123.029914856,49.2810020447],"type":"Point"}
}