{
  "type": "Feature",
  "properties": {
    "addr:full":"612 Ch Bernard Canton-DE-Granby QC J2G 9H9",
    "addr:housenumber":"612",
    "addr:postcode":"j2g 9h9",
    "addr:street":"Ch Bernard Canton-De-Granby",
    "iso:country":"CA",
    "sg:address":"612 Ch Bernard",
    "sg:city":"Canton-DE-Granby",
    "sg:classifiers":[
        {
            "category":"Wholesale",
            "subcategory":"Electrical",
            "type":"Manufacturing & Wholesale Goods"
        }
    ],
    "sg:phone":"+1 450 378 9018",
    "sg:postcode":"J2G 9H9",
    "sg:province":"QC",
    "sg:tags":[
        "transformer"
    ],
    "wof:name":"Pioneer Transformers Ltd",
    "wof:placetype":"venue"
},
  "geometry": {"coordinates":[-72.7217712402,45.3979949951],"type":"Point"}
}