{
  "type": "Feature",
  "properties": {
    "addr:full":"1370 Laurier St Rockland ON K4K 1L5",
    "addr:housenumber":"1370",
    "addr:postcode":"k4k 1l5",
    "addr:street":"Laurier St",
    "iso:country":"CA",
    "sg:address":"1370 Laurier St",
    "sg:city":"Rockland",
    "sg:classifiers":[
        {
            "category":"Shopping",
            "subcategory":"Florist",
            "type":"Retail Goods"
        }
    ],
    "sg:phone":"+1 613 446 6444",
    "sg:postcode":"K4K 1L5",
    "sg:province":"ON",
    "wof:name":"Fleuriste Brunet Florist",
    "wof:placetype":"venue"
},
  "geometry": {"coordinates":[-75.2867431641,45.552532196],"type":"Point"}
}