{
  "type": "Feature",
  "properties": {
    "addr:full":"1602 Cecil Lake Rd Goodlow BC V0C 1S0",
    "addr:housenumber":"1602",
    "addr:postcode":"bc v0c 1s0",
    "addr:street":"Cecil Lake Rd",
    "iso:country":"CA",
    "sg:address":"1602 Cecil Lake Rd",
    "sg:city":"Goodlow",
    "sg:classifiers":[
        {
            "category":"Food & Beverages",
            "subcategory":"Groceries & Convenience Stores",
            "type":"Retail Goods"
        }
    ],
    "sg:phone":"+1 250 781 3457",
    "sg:postcode":"V0C 1S0",
    "sg:province":"BC",
    "sg:tags":[
        "grocer"
    ],
    "wof:name":"Goodlow Store",
    "wof:placetype":"venue"
},
  "geometry": {"coordinates":[-120.18888855,56.3337211609],"type":"Point"}
}