{
  "type": "Feature",
  "properties": {
    "iso:country":"CA",
    "sg:address":"254 Queen St S",
    "sg:city":"Mississauga",
    "sg:classifiers":[
        {
            "category":"Shopping",
            "subcategory":"Computers & Home Electronics",
            "type":"Retail Goods"
        }
    ],
    "sg:phone":"+1 905 826 1582",
    "sg:postcode":"L5M 1L8",
    "sg:province":"ON",
    "sg:tags":[
        "television",
        "radio"
    ],
    "wof:name":"Huron Television & Appliances",
    "wof:placetype":"venue"
},
  "geometry": {"coordinates":[-79.6005706787,43.5429000854],"type":"Point"}
}