{
  "type": "Feature",
  "properties": {
    "addr:full":"2602 52 St SE Calgary AB T2B 1N2",
    "addr:housenumber":"2602",
    "addr:postcode":"t2b 1n2",
    "addr:street":"52 St Se",
    "iso:country":"CA",
    "sg:address":"2602 52 St SE",
    "sg:city":"Calgary",
    "sg:classifiers":[
        {
            "category":"Wholesale",
            "subcategory":"Scrap",
            "type":"Manufacturing & Wholesale Goods"
        }
    ],
    "sg:phone":"+1 403 272 8891",
    "sg:postcode":"T2B 1N2",
    "sg:province":"AB",
    "sg:tags":[
        "automobile",
        "crushing",
        "parts",
        "supply"
    ],
    "wof:name":"Western Auto & Truck Parts",
    "wof:placetype":"venue"
},
  "geometry": {"coordinates":[-113.958298,51.029964],"type":"Point"}
}