{
  "type": "Feature",
  "properties": {
    "addr:full":"Scarborough ON M1R 5G9",
    "addr:postcode":"m1r 5g9",
    "iso:country":"CA",
    "sg:city":"Scarborough",
    "sg:classifiers":[
        {
            "category":"Education",
            "subcategory":"Special Training",
            "type":"Public Place"
        }
    ],
    "sg:phone":"+1 416 750 2070",
    "sg:postcode":"M1R 5G9",
    "sg:province":"ON",
    "sg:tags":[
        "school",
        "language"
    ],
    "wof:name":"Aldebrain Linc Program",
    "wof:placetype":"venue"
},
  "geometry": {"coordinates":[-79.2851867676,43.7472877502],"type":"Point"}
}