{
  "type": "Feature",
  "properties": {
    "addr:full":"60 Skyway Ave Etobicoke ON M9W 4Y9",
    "addr:housenumber":"60",
    "addr:postcode":"m9w 4y9",
    "addr:street":"Skyway Ave",
    "iso:country":"CA",
    "sg:address":"60 Skyway Ave",
    "sg:city":"Etobicoke",
    "sg:classifiers":[
        {
            "category":"Local Transit",
            "type":"Transportation"
        }
    ],
    "sg:phone":"+1 416 674 1754",
    "sg:postcode":"M9W 4Y9",
    "sg:province":"ON",
    "sg:tags":[
        "airport"
    ],
    "wof:name":"Skyway Park",
    "wof:placetype":"venue"
},
  "geometry": {"coordinates":[-79.5835189819,43.6839752197],"type":"Point"}
}