{
  "type": "Feature",
  "properties": {
    "addr:full":"3261 Westsyde Rd Kamloops BC V2B 7G9",
    "addr:housenumber":"3261",
    "addr:postcode":"bc v2b 7g9",
    "addr:street":"Westsyde Rd",
    "iso:country":"CA",
    "sg:address":"3261 Westsyde Rd",
    "sg:city":"Kamloops",
    "sg:classifiers":[
        {
            "category":"Manufacturing",
            "subcategory":"Building Materials",
            "type":"Manufacturing & Wholesale Goods"
        }
    ],
    "sg:phone":"+1 250 579 9234",
    "sg:postcode":"V2B 7G9",
    "sg:province":"BC",
    "wof:name":"R L Palmer Mfg Ltd",
    "wof:placetype":"venue"
},
  "geometry": {"coordinates":[-120.345314026,50.7670631409],"type":"Point"}
}