{
  "type": "Feature",
  "properties": {
    "addr:full":"Dorion ON P0T 1K0",
    "addr:postcode":"p0t 1k0",
    "iso:country":"CA",
    "sg:city":"Dorion",
    "sg:classifiers":[
        {
            "category":"Manufacturing",
            "subcategory":"Lumber",
            "type":"Manufacturing & Wholesale Goods"
        }
    ],
    "sg:phone":"+1 807 857 2471",
    "sg:postcode":"P0T 1K0",
    "sg:province":"ON",
    "sg:tags":[
        "forester"
    ],
    "wof:name":"A & R Greenhouses Ltd",
    "wof:placetype":"venue"
},
  "geometry": {"coordinates":[-88.54020690919999,48.7883911133],"type":"Point"}
}