{
  "type": "Feature",
  "properties": {
    "iso:country":"CA",
    "sg:city":"Hamilton",
    "sg:classifiers":[
        {
            "category":"Restaurant",
            "type":"Food & Drink"
        }
    ],
    "sg:phone":"+1 905 561 0561",
    "sg:postcode":"L8W 2C6",
    "sg:province":"ON",
    "sg:tags":[
        "pizza"
    ],
    "wof:name":"A Royal Pizza Wings",
    "wof:placetype":"venue"
},
  "geometry": {"coordinates":[-79.8335952759,43.1977005005],"type":"Point"}
}