{
  "type": "Feature",
  "properties": {
    "iso:country":"CA",
    "sg:address":"1001 Boul Des Forges",
    "sg:city":"Trois-Rivieres",
    "sg:classifiers":[
        {
            "category":"Insurance",
            "subcategory":"Insurance Agent",
            "type":"Services"
        }
    ],
    "sg:phone":"+1 819 378 6278",
    "sg:postcode":"G8Z 1T7",
    "sg:province":"QC",
    "sg:tags":[
        "adjuster"
    ],
    "wof:name":"Laurent Bourassa Inc",
    "wof:placetype":"venue"
},
  "geometry": {"coordinates":[-72.552589,46.344078],"type":"Point"}
}