{
  "type": "Feature",
  "properties": {
    "iso:country":"CA",
    "sg:address":"3600 Boul Harvey",
    "sg:city":"Jonquiere",
    "sg:classifiers":[
        {
            "category":"Autos & Motor Vehicles",
            "subcategory":"Fuel & Gas Station",
            "type":"Retail Goods"
        }
    ],
    "sg:phone":"+1 418 695 2713",
    "sg:postcode":"G7X 3B3",
    "sg:province":"QC",
    "sg:tags":[
        "oil",
        "gasoline"
    ],
    "wof:name":"Petroles Rl Inc",
    "wof:placetype":"venue"
},
  "geometry": {"coordinates":[-71.233521,48.412128],"type":"Point"}
}