{
  "type": "Feature",
  "properties": {
    "addr:full":"Asbestos QC J1T 3P6",
    "addr:postcode":"j1t 3p6",
    "iso:country":"CA",
    "sg:city":"Asbestos",
    "sg:classifiers":[
        {
            "category":"Shopping",
            "subcategory":"Clothing, Apparel, & Fashions",
            "type":"Retail Goods"
        }
    ],
    "sg:phone":"+1 819 879 6485",
    "sg:postcode":"J1T 3P6",
    "sg:province":"QC",
    "sg:tags":[
        "boutique"
    ],
    "wof:name":"Boutique Marida",
    "wof:placetype":"venue"
},
  "geometry": {"coordinates":[-71.928963,45.770958],"type":"Point"}
}