{
  "type": "Feature",
  "properties": {
    "addr:full":"Hudson's Hope BC V0C 1V0",
    "addr:postcode":"bc v0c 1v0",
    "iso:country":"CA",
    "sg:city":"Hudson's Hope",
    "sg:classifiers":[
        {
            "category":"Government",
            "subcategory":"Fire Station",
            "type":"Public Place"
        }
    ],
    "sg:phone":"+1 250 783 9900",
    "sg:postcode":"V0C 1V0",
    "sg:province":"BC",
    "sg:tags":[
        "department"
    ],
    "wof:name":"Hudson's Hope Fire Hall",
    "wof:placetype":"venue"
},
  "geometry": {"coordinates":[-126.555511475,54.4856681824],"type":"Point"}
}