{
  "type": "Feature",
  "properties": {
    "iso:country":"CA",
    "sg:city":"Montreal",
    "sg:classifiers":[
        {
            "category":"Professional",
            "subcategory":"Computer Services",
            "type":"Services"
        }
    ],
    "sg:phone":"+1 514 281 5510",
    "sg:postcode":"H3A 2R7",
    "sg:province":"QC",
    "sg:tags":[
        "internet"
    ],
    "wof:name":"Eastman Systems",
    "wof:placetype":"venue"
},
  "geometry": {"coordinates":[-73.565544,45.520882],"type":"Point"}
}