{
  "type": "Feature",
  "properties": {
    "iso:country":"CA",
    "sg:address":"636 Main St",
    "sg:city":"Sydney Mines",
    "sg:classifiers":[
        {
            "category":"Retail",
            "subcategory":"Animal Services",
            "type":"Services"
        }
    ],
    "sg:phone":"+1 902 544 0488",
    "sg:postcode":"B1V 2L2",
    "sg:province":"NS",
    "sg:tags":[
        "pet",
        "grooming",
        "washing"
    ],
    "wof:name":"Pet Works",
    "wof:placetype":"venue"
},
  "geometry": {"coordinates":[-60.2239112854,46.2400970459],"type":"Point"}
}