{
  "type": "Feature",
  "properties": {
    "iso:country":"CA",
    "sg:address":"320 Lakehill St",
    "sg:city":"Kaleden",
    "sg:classifiers":[
        {
            "category":"Organizations",
            "subcategory":"Professional Association",
            "type":"Services"
        }
    ],
    "sg:phone":"+1 250 497 5900",
    "sg:postcode":"V0H 1K0",
    "sg:province":"BC",
    "sg:tags":[
        "club"
    ],
    "wof:name":"Kaleden Community Hall",
    "wof:placetype":"venue"
},
  "geometry": {"coordinates":[-119.59499359100001,49.3899726868],"type":"Point"}
}