{
  "type": "Feature",
  "properties": {
    "iso:country":"CA",
    "sg:city":"Calgary",
    "sg:classifiers":[
        {
            "category":"Organizations",
            "subcategory":"Political Organization",
            "type":"Services"
        }
    ],
    "sg:phone":"+1 403 269 1990",
    "sg:postcode":"T2P 0Z3",
    "sg:province":"AB",
    "wof:name":"Canadian Alliance",
    "wof:placetype":"venue"
},
  "geometry": {"coordinates":[-114.020409,50.98381],"type":"Point"}
}