{
  "type": "Feature",
  "properties": {
    "iso:country":"CA",
    "sg:address":"3299 Connolly St",
    "sg:city":"Halifax",
    "sg:classifiers":[
        {
            "category":"Education",
            "subcategory":"School",
            "type":"Public Place"
        }
    ],
    "sg:phone":"+1 902 493 5143",
    "sg:postcode":"B3L 3P7",
    "sg:province":"NS",
    "wof:name":"St Catherine's School",
    "wof:placetype":"venue"
},
  "geometry": {"coordinates":[-63.614231,44.655746],"type":"Point"}
}