{
  "type": "Feature",
  "properties": {
    "addr:full":"Invermere BC V0A 1K0",
    "addr:postcode":"v0a 1k0",
    "iso:country":"CA",
    "sg:city":"Invermere",
    "sg:classifiers":[
        {
            "category":"Shopping",
            "subcategory":"Books",
            "type":"Retail Goods"
        }
    ],
    "sg:phone":"+1 250 342 7010",
    "sg:postcode":"V0A 1K0",
    "sg:province":"BC",
    "sg:tags":[
        "dealer"
    ],
    "wof:name":"All Things Beautiful Books",
    "wof:placetype":"venue"
},
  "geometry": {"coordinates":[-116.027771,50.504486],"type":"Point"}
}