{
  "type": "Feature",
  "properties": {
    "addr:full":"Woodbridge ON L4L 6C7",
    "addr:postcode":"l4l 6c7",
    "iso:country":"CA",
    "sg:city":"Woodbridge",
    "sg:classifiers":[
        {
            "category":"Manufacturing",
            "subcategory":"Metals",
            "type":"Manufacturing & Wholesale Goods"
        }
    ],
    "sg:phone":"+1 905 856 0350",
    "sg:postcode":"L4L 6C7",
    "sg:province":"ON",
    "sg:tags":[
        "bracket"
    ],
    "wof:name":"Steelcap Industries",
    "wof:placetype":"venue"
},
  "geometry": {"coordinates":[-79.5516586304,43.7871017456],"type":"Point"}
}