{
  "type": "Feature",
  "properties": {
    "addr:full":"2244 Willoughby Way Langley BC V2Y 1C1",
    "addr:housenumber":"2244",
    "addr:postcode":"v2y 1c1",
    "addr:street":"Willoughby Way",
    "iso:country":"CA",
    "sg:address":"2244 Willoughby Way",
    "sg:city":"Langley",
    "sg:classifiers":[
        {
            "category":"Education",
            "subcategory":"School",
            "type":"Public Place"
        }
    ],
    "sg:phone":"+1 604 530 4101",
    "sg:postcode":"V2Y 1C1",
    "sg:province":"BC",
    "wof:name":"Langley Meadows Community Schl",
    "wof:placetype":"venue"
},
  "geometry": {"coordinates":[-122.672859,49.121613],"type":"Point"}
}