{
  "type": "Feature",
  "properties": {
    "iso:country":"CA",
    "sg:address":"Main St",
    "sg:city":"Paradise Hill",
    "sg:classifiers":[
        {
            "category":"Restaurant",
            "type":"Food & Drink"
        }
    ],
    "sg:phone":"+1 306 344 2344",
    "sg:postcode":"S0M 2G0",
    "sg:province":"SK",
    "wof:name":"Lam's Restaurant",
    "wof:placetype":"venue"
},
  "geometry": {"coordinates":[-109.459159851,53.5389175415],"type":"Point"}
}