{
  "type": "Feature",
  "properties": {
    "addr:full":"20 Northbrook Rd East York ON M4J 4G1",
    "addr:housenumber":"20",
    "addr:postcode":"m4j 4g1",
    "addr:street":"Northbrook Rd",
    "iso:country":"CA",
    "sg:address":"20 Northbrook Rd",
    "sg:city":"East York",
    "sg:classifiers":[
        {
            "category":"Building & Trades",
            "subcategory":"Construction",
            "type":"Services"
        }
    ],
    "sg:phone":"+1 416 421 4915",
    "sg:postcode":"M4J 4G1",
    "sg:province":"ON",
    "sg:tags":[
        "painter"
    ],
    "wof:name":"Toronto Paint Group Inc",
    "wof:placetype":"venue"
},
  "geometry": {"coordinates":[-79.3372802734,43.693069458],"type":"Point"}
}