{
  "type": "Feature",
  "properties": {
    "iso:country":"CA",
    "sg:address":"670 Goyeau St",
    "sg:city":"Windsor",
    "sg:classifiers":[
        {
            "category":"Personal",
            "subcategory":"Beauty Salon",
            "type":"Services"
        }
    ],
    "sg:phone":"+1 519 256 9331",
    "sg:postcode":"N9A 1H4",
    "sg:province":"ON",
    "wof:name":"Antoine Greige Salon Inc",
    "wof:placetype":"venue"
},
  "geometry": {"coordinates":[-83.03429412840001,42.3140106201],"type":"Point"}
}