{
  "type": "Feature",
  "properties": {
    "addr:full":"685 Gregg Ave Hinton AB T7V 1X6",
    "addr:housenumber":"685",
    "addr:postcode":"t7v 1x6",
    "addr:street":"Gregg Ave",
    "iso:country":"CA",
    "sg:address":"685 Gregg Ave",
    "sg:city":"Hinton",
    "sg:classifiers":[
        {
            "category":"Freight",
            "type":"Transportation"
        }
    ],
    "sg:phone":"+1 780 865 1873",
    "sg:postcode":"T7V 1X6",
    "sg:province":"AB",
    "sg:tags":[
        "field",
        "oil",
        "trucking"
    ],
    "wof:name":"Pines Liquid Cargo Hauling",
    "wof:placetype":"venue"
},
  "geometry": {"coordinates":[-117.608841,53.391617],"type":"Point"}
}