{
  "type": "Feature",
  "properties": {
    "addr:full":"359 Rue Jackson Quebec QC G1N 4C4",
    "addr:housenumber":"359",
    "addr:postcode":"g1n 4c4",
    "addr:street":"Rue Jackson",
    "iso:country":"CA",
    "sg:address":"359 Rue Jackson",
    "sg:city":"Quebec",
    "sg:classifiers":[
        {
            "category":"Building & Trades",
            "subcategory":"Construction",
            "type":"Services"
        }
    ],
    "sg:phone":"+1 418 683 2173",
    "sg:postcode":"G1N 4C4",
    "sg:province":"QC",
    "sg:tags":[
        "acoustical",
        "contractor"
    ],
    "wof:name":"Capitale Acoustique Inc",
    "wof:placetype":"venue"
},
  "geometry": {"coordinates":[-71.2623596191,46.8020858765],"type":"Point"}
}