{
  "type": "Feature",
  "properties": {
    "addr:full":"98 Talbot St E Wheatley ON N0P 2P0",
    "addr:housenumber":"98",
    "addr:postcode":"n0p 2p0",
    "addr:street":"Talbot St E",
    "iso:country":"CA",
    "sg:address":"98 Talbot St E",
    "sg:city":"Wheatley",
    "sg:classifiers":[
        {
            "category":"Restaurant",
            "type":"Food & Drink"
        }
    ],
    "sg:phone":"+1 519 825 9299",
    "sg:postcode":"N0P 2P0",
    "sg:province":"ON",
    "sg:tags":[
        "parlor",
        "variety",
        "store",
        "ice",
        "cream"
    ],
    "wof:name":"Captain's Corner",
    "wof:placetype":"venue"
},
  "geometry": {"coordinates":[-82.459816,42.095604],"type":"Point"}
}