{
  "type": "Feature",
  "properties": {
    "iso:country":"CA",
    "sg:city":"Red Deer County",
    "sg:classifiers":[
        {
            "category":"Building & Trades",
            "subcategory":"Construction",
            "type":"Services"
        }
    ],
    "sg:phone":"+1 403 342 6671",
    "sg:postcode":"T4E 1B9",
    "sg:province":"AB",
    "sg:tags":[
        "maker",
        "cabinet"
    ],
    "wof:name":"Westridge Cabinets Ltd",
    "wof:placetype":"venue"
},
  "geometry": {"coordinates":[-113.93549346899999,52.0221366882],"type":"Point"}
}