{
  "type": "Feature",
  "properties": {
    "addr:full":"40 Bridge St N Hastings ON K0L 1Y0",
    "addr:housenumber":"40",
    "addr:postcode":"k0l 1y0",
    "addr:street":"Bridge St N",
    "iso:country":"CA",
    "sg:address":"40 Bridge St N",
    "sg:city":"Hastings",
    "sg:classifiers":[
        {
            "category":"Arena",
            "subcategory":"Sports Club",
            "type":"Entertainment"
        }
    ],
    "sg:phone":"+1 705 696 2379",
    "sg:postcode":"K0L 1Y0",
    "sg:province":"ON",
    "sg:tags":[
        "athletic",
        "fields",
        "stadium",
        "government"
    ],
    "wof:name":"Hastings Arena",
    "wof:placetype":"venue"
},
  "geometry": {"coordinates":[-77.95708500000001,44.309963],"type":"Point"}
}