{
  "type": "Feature",
  "properties": {
    "addr:full":"30 Walgate Ave Nepean ON K2E 6M2",
    "addr:housenumber":"30",
    "addr:postcode":"k2e 6m2",
    "addr:street":"Walgate Ave",
    "iso:country":"CA",
    "sg:address":"30 Walgate Ave",
    "sg:city":"Nepean",
    "sg:classifiers":[
        {
            "category":"Personal",
            "type":"Services"
        }
    ],
    "sg:phone":"+1 613 225 8481",
    "sg:postcode":"K2E 6M2",
    "sg:province":"ON",
    "sg:tags":[
        "electrolysis"
    ],
    "wof:name":"Royal Electrolysis",
    "wof:placetype":"venue"
},
  "geometry": {"coordinates":[-75.72653200000001,45.35503],"type":"Point"}
}