{
  "type": "Feature",
  "properties": {
    "addr:full":"219 Rue St Leon Saint-Simeon QC G0T 1X0",
    "addr:housenumber":"219",
    "addr:postcode":"g0t 1x0",
    "addr:street":"Rue St Leon Saint-Simeon",
    "iso:country":"CA",
    "sg:address":"219 Rue St Leon",
    "sg:city":"Saint-Simeon",
    "sg:classifiers":[
        {
            "category":"Local Transit",
            "type":"Transportation"
        }
    ],
    "sg:phone":"+1 418 638 2928",
    "sg:postcode":"G0T 1X0",
    "sg:province":"QC",
    "sg:tags":[
        "bus",
        "line"
    ],
    "wof:name":"Transport Savary Inc",
    "wof:placetype":"venue"
},
  "geometry": {"coordinates":[-69.8846282959,47.84116745],"type":"Point"}
}