{
  "type": "Feature",
  "properties": {
    "addr:full":"1086 Clayton Rd North Saanich BC V8L 5P6",
    "addr:housenumber":"1086",
    "addr:postcode":"v8l 5p6",
    "addr:street":"Clayton Rd",
    "iso:country":"CA",
    "sg:address":"1086 Clayton Rd",
    "sg:city":"North Saanich",
    "sg:classifiers":[
        {
            "category":"Building & Trades",
            "subcategory":"Plumbing",
            "type":"Services"
        }
    ],
    "sg:phone":"+1 250 655 1202",
    "sg:postcode":"V8L 5P6",
    "sg:province":"BC",
    "sg:tags":[
        "contractor"
    ],
    "wof:name":"Omni Mechanical Inc",
    "wof:placetype":"venue"
},
  "geometry": {"coordinates":[-123.45390319800001,48.6809158325],"type":"Point"}
}