{
  "type": "Feature",
  "properties": {
    "addr:full":"7005 89 Ave NW Edmonton AB T6B 0N3",
    "addr:housenumber":"7005",
    "addr:postcode":"t6b 0n3",
    "addr:street":"89 Ave Nw",
    "iso:country":"CA",
    "sg:address":"7005 89 Ave NW",
    "sg:city":"Edmonton",
    "sg:classifiers":[
        {
            "category":"Education",
            "subcategory":"School",
            "type":"Public Place"
        }
    ],
    "sg:phone":"+1 780 466 2104",
    "sg:postcode":"T6B 0N3",
    "sg:province":"AB",
    "wof:name":"Kenilworth Junior High School",
    "wof:placetype":"venue"
},
  "geometry": {"coordinates":[-113.435165,53.524033],"type":"Point"}
}