{
  "type": "Feature",
  "properties": {
    "addr:full":"1206 Davie St Vancouver BC V6E 1N3",
    "addr:housenumber":"1206",
    "addr:postcode":"v6e 1n3",
    "addr:street":"Davie St",
    "iso:country":"CA",
    "sg:address":"1206 Davie St",
    "sg:city":"Vancouver",
    "sg:classifiers":[
        {
            "category":"Restaurant",
            "type":"Food & Drink"
        }
    ],
    "sg:phone":"+1 604 682 8424",
    "sg:postcode":"V6E 1N3",
    "sg:province":"BC",
    "wof:name":"Thai Away Home",
    "wof:placetype":"venue"
},
  "geometry": {"coordinates":[-123.133781433,49.2818641663],"type":"Point"}
}