{
  "type": "Feature",
  "properties": {
    "addr:full":"1717 Boul Don-Quichotte Notre-Dame-DE-L'Ile-Perrot QC J7V 5V6",
    "addr:housenumber":"1717",
    "addr:postcode":"j7v 5v6",
    "addr:street":"Boul Don-Quichotte Notre-Dame-De-L'Ile-Perrot",
    "iso:country":"CA",
    "sg:address":"1717 Boul Don-Quichotte",
    "sg:city":"Notre-Dame-DE-L'Ile-Perrot",
    "sg:classifiers":[
        {
            "category":"Recreation",
            "type":"Entertainment"
        }
    ],
    "sg:phone":"+1 514 453 7177",
    "sg:postcode":"J7V 5V6",
    "sg:province":"QC",
    "sg:tags":[
        "course",
        "golf"
    ],
    "wof:name":"Ile Perrot Golf Club Inc",
    "wof:placetype":"venue"
},
  "geometry": {"coordinates":[-73.955368042,45.3937644958],"type":"Point"}
}