{
  "type": "Feature",
  "properties": {
    "addr:full":"1529 Bridge St Kingston NS B0P 1R0",
    "addr:housenumber":"1529",
    "addr:postcode":"b0p 1r0",
    "addr:street":"Bridge St",
    "iso:country":"CA",
    "sg:address":"1529 Bridge St",
    "sg:city":"Kingston",
    "sg:classifiers":[
        {
            "category":"Banks & Credit Unions",
            "subcategory":"Investment Brokerage",
            "type":"Services"
        }
    ],
    "sg:phone":"+1 902 765 6366",
    "sg:postcode":"B0P 1R0",
    "sg:province":"NS",
    "sg:tags":[
        "consultant",
        "planning",
        "financial"
    ],
    "wof:name":"Assante Capital Management Ltd",
    "wof:placetype":"venue"
},
  "geometry": {"coordinates":[-64.949684,44.986401],"type":"Point"}
}