{
  "type": "Feature",
  "properties": {
    "addr:full":"349 Main St Hartland NB E7P 2N1",
    "addr:housenumber":"349",
    "addr:postcode":"e7p 2n1",
    "addr:street":"Main St",
    "iso:country":"CA",
    "sg:address":"349 Main St",
    "sg:city":"Hartland",
    "sg:classifiers":[
        {
            "category":"Organizations",
            "subcategory":"Religious Organization",
            "type":"Services"
        }
    ],
    "sg:phone":"+1 506 375 4302",
    "sg:postcode":"E7P 2N1",
    "sg:province":"NB",
    "sg:tags":[
        "church"
    ],
    "wof:name":"United Baptist Church",
    "wof:placetype":"venue"
},
  "geometry": {"coordinates":[-67.527924,46.297791],"type":"Point"}
}