{
  "type": "Feature",
  "properties": {
    "addr:full":"325 Lonsdale Rd Toronto ON M4V 1X3",
    "addr:housenumber":"325",
    "addr:postcode":"m4v 1x3",
    "addr:street":"Lonsdale Rd",
    "iso:country":"CA",
    "sg:address":"325 Lonsdale Rd",
    "sg:city":"Toronto",
    "sg:classifiers":[
        {
            "category":"Shopping",
            "subcategory":"Clothing, Apparel, & Fashions",
            "type":"Retail Goods"
        }
    ],
    "sg:phone":"+1 416 481 6712",
    "sg:postcode":"M4V 1X3",
    "sg:province":"ON",
    "sg:tags":[
        "item",
        "boutique"
    ],
    "wof:name":"Kitsch Boutique",
    "wof:placetype":"venue"
},
  "geometry": {"coordinates":[-79.4117202759,43.6887168884],"type":"Point"}
}