{
  "type": "Feature",
  "properties": {
    "addr:full":"442 Rue Cherrier L'Ile-Bizard QC H9C 1G2",
    "addr:housenumber":"442",
    "addr:postcode":"h9c 1g2",
    "addr:street":"Rue Cherrier",
    "iso:country":"CA",
    "sg:address":"442 Rue Cherrier",
    "sg:city":"L'Ile-Bizard",
    "sg:classifiers":[
        {
            "category":"Professional",
            "subcategory":"Management & Consulting",
            "type":"Services"
        }
    ],
    "sg:phone":"+1 514 696 7443",
    "sg:postcode":"H9C 1G2",
    "sg:province":"QC",
    "sg:tags":[
        "international",
        "consultant"
    ],
    "wof:name":"Agrosysts Limitee",
    "wof:placetype":"venue"
},
  "geometry": {"coordinates":[-73.877258,45.487453],"type":"Point"}
}