{
  "type": "Feature",
  "properties": {
    "iso:country":"CA",
    "sg:address":"1500 Bank St",
    "sg:city":"Ottawa",
    "sg:classifiers":[
        {
            "category":"Shopping",
            "subcategory":"Optical Goods",
            "type":"Retail Goods"
        }
    ],
    "sg:phone":"+1 613 733 3139",
    "sg:postcode":"K1H 7Z2",
    "sg:province":"ON",
    "sg:tags":[
        "optician"
    ],
    "wof:name":"Nelms Opticians",
    "wof:placetype":"venue"
},
  "geometry": {"coordinates":[-75.670311,45.381924],"type":"Point"}
}