{
  "type": "Feature",
  "properties": {
    "addr:full":"West Vancouver BC V7V 1J4",
    "addr:postcode":"v7v 1j4",
    "iso:country":"CA",
    "sg:city":"West Vancouver",
    "sg:classifiers":[
        {
            "category":"Health Services",
            "subcategory":"Doctor",
            "type":"Services"
        }
    ],
    "sg:phone":"+1 604 926 8521",
    "sg:postcode":"V7V 1J4",
    "sg:province":"BC",
    "sg:tags":[
        "dentist"
    ],
    "wof:name":"Pudritz, Ron DDS",
    "wof:placetype":"venue"
},
  "geometry": {"coordinates":[-123.1614,49.328403],"type":"Point"}
}