{
  "type": "Feature",
  "properties": {
    "iso:country":"CA",
    "sg:address":"185 North Town Mall NW",
    "sg:city":"Edmonton",
    "sg:classifiers":[
        {
            "category":"Shopping",
            "type":"Retail Goods"
        }
    ],
    "sg:phone":"+1 780 478 9916",
    "sg:postcode":"T5E 6C1",
    "sg:province":"AB",
    "sg:tags":[
        "cosmetic",
        "perfume"
    ],
    "wof:name":"London Drugs Ltd",
    "wof:placetype":"venue"
},
  "geometry": {"coordinates":[-113.490371704,53.5462188721],"type":"Point"}
}