{
  "type": "Feature",
  "properties": {
    "iso:country":"CA",
    "sg:address":"1371 227 St",
    "sg:city":"Langley",
    "sg:classifiers":[
        {
            "category":"Building & Trades",
            "subcategory":"Construction",
            "type":"Services"
        }
    ],
    "sg:phone":"+1 604 533 2115",
    "sg:postcode":"V2Z 2W8",
    "sg:province":"BC",
    "sg:tags":[
        "boring",
        "drilling",
        "contractor"
    ],
    "wof:name":"Western Industrial Drill Ltd",
    "wof:placetype":"venue"
},
  "geometry": {"coordinates":[-122.59574890099999,49.0270423889],"type":"Point"}
}