{
  "type": "Feature",
  "properties": {
    "addr:full":"2485 Boul Sainte-Anne Quebec QC G1J 1Y4",
    "addr:housenumber":"2485",
    "addr:postcode":"g1j 1y4",
    "addr:street":"Boul Sainte-Anne",
    "iso:country":"CA",
    "sg:address":"2485 Boul Sainte-Anne",
    "sg:city":"Quebec",
    "sg:classifiers":[
        {
            "category":"Restaurant",
            "type":"Food & Drink"
        }
    ],
    "sg:phone":"+1 418 667 0923",
    "sg:postcode":"G1J 1Y4",
    "sg:province":"QC",
    "wof:name":"Bel-Gaufre Inc",
    "wof:placetype":"venue"
},
  "geometry": {"coordinates":[-71.215675354,46.8439407349],"type":"Point"}
}