{
  "type": "Feature",
  "properties": {
    "addr:full":"Oshawa ON L1H 1A3",
    "addr:postcode":"l1h 1a3",
    "iso:country":"CA",
    "sg:city":"Oshawa",
    "sg:classifiers":[
        {
            "category":"Professional",
            "subcategory":"Art Services",
            "type":"Services"
        }
    ],
    "sg:phone":"+1 905 723 4448",
    "sg:postcode":"L1H 1A3",
    "sg:province":"ON",
    "sg:tags":[
        "graphic",
        "designer"
    ],
    "wof:name":"Aftershock Creative Inc",
    "wof:placetype":"venue"
},
  "geometry": {"coordinates":[-78.8645324707,43.8975219727],"type":"Point"}
}