{
  "type": "Feature",
  "properties": {
    "addr:full":"4537 44th Ave Chetwynd BC V0C 1J0",
    "addr:housenumber":"4537",
    "addr:postcode":"bc v0c 1j0",
    "addr:street":"44Th Ave",
    "iso:country":"CA",
    "sg:address":"4537 44th Ave",
    "sg:city":"Chetwynd",
    "sg:classifiers":[
        {
            "category":"Manufacturing",
            "subcategory":"Lumber",
            "type":"Manufacturing & Wholesale Goods"
        }
    ],
    "sg:phone":"+1 250 788 2846",
    "sg:postcode":"V0C 1J0",
    "sg:province":"BC",
    "sg:tags":[
        "company",
        "logging"
    ],
    "wof:name":"Young Mills Ltd",
    "wof:placetype":"venue"
},
  "geometry": {"coordinates":[-121.609932,55.706478],"type":"Point"}
}