{
  "type": "Feature",
  "properties": {
    "iso:country":"CA",
    "sg:address":"951 Swiss Hts",
    "sg:city":"Oshawa",
    "sg:classifiers":[
        {
            "category":"Banks & Credit Unions",
            "subcategory":"Investment Brokerage",
            "type":"Services"
        }
    ],
    "sg:phone":"+1 905 571 3123",
    "sg:postcode":"L1K 2A7",
    "sg:province":"ON",
    "sg:tags":[
        "consultant",
        "planning",
        "financial"
    ],
    "wof:name":"Priority Planning",
    "wof:placetype":"venue"
},
  "geometry": {"coordinates":[-78.8428039551,43.9350013733],"type":"Point"}
}