{
  "type": "Feature",
  "properties": {
    "addr:full":"2701 Huron Church Rd Windsor ON N9E 3Y7",
    "addr:housenumber":"2701",
    "addr:postcode":"n9e 3y7",
    "addr:street":"Huron Church Rd",
    "iso:country":"CA",
    "sg:address":"2701 Huron Church Rd",
    "sg:city":"Windsor",
    "sg:classifiers":[
        {
            "category":"Travel",
            "subcategory":"Hotels & Motels",
            "type":"Entertainment"
        }
    ],
    "sg:phone":"+1 519 969 7510",
    "sg:postcode":"N9E 3Y7",
    "sg:province":"ON",
    "wof:name":"Blue Bell Motel",
    "wof:placetype":"venue"
},
  "geometry": {"coordinates":[-83.04621899999999,42.268181],"type":"Point"}
}