{
  "type": "Feature",
  "properties": {
    "addr:full":"10504 100 Ave Morinville AB T8R 1A4",
    "addr:housenumber":"10504",
    "addr:postcode":"t8r 1a4",
    "addr:street":"100 Ave",
    "iso:country":"CA",
    "sg:address":"10504 100 Ave",
    "sg:city":"Morinville",
    "sg:classifiers":[
        {
            "category":"Restaurant",
            "type":"Food & Drink"
        }
    ],
    "sg:phone":"+1 780 939 3255",
    "sg:postcode":"T8R 1A4",
    "sg:province":"AB",
    "wof:name":"Friends & Neighbours Family",
    "wof:placetype":"venue"
},
  "geometry": {"coordinates":[-113.654724,53.801983],"type":"Point"}
}