{
  "type": "Feature",
  "properties": {
    "iso:country":"CA",
    "sg:city":"West Vancouver",
    "sg:classifiers":[
        {
            "category":"Wholesale",
            "subcategory":"Durable Goods & Equipment",
            "type":"Manufacturing & Wholesale Goods"
        }
    ],
    "sg:phone":"+1 604 913 9035",
    "sg:postcode":"V7T 1A2",
    "sg:province":"BC",
    "sg:tags":[
        "environmental",
        "ecological",
        "prod"
    ],
    "wof:name":"First American Scientific Corp",
    "wof:placetype":"venue"
},
  "geometry": {"coordinates":[-123.134995,49.32513],"type":"Point"}
}