{
  "type": "Feature",
  "properties": {
    "addr:full":"175 Rue Josee Rougemont QC J0L 1M0",
    "addr:housenumber":"175",
    "addr:postcode":"j0l 1m0",
    "addr:street":"Rue Josee",
    "iso:country":"CA",
    "sg:address":"175 Rue Josee",
    "sg:city":"Rougemont",
    "sg:classifiers":[
        {
            "category":"Restaurant",
            "type":"Food & Drink"
        }
    ],
    "sg:phone":"+1 450 469 3646",
    "sg:postcode":"J0L 1M0",
    "sg:province":"QC",
    "sg:tags":[
        "hall",
        "auditorium"
    ],
    "wof:name":"Bistro St-Michel Enr",
    "wof:placetype":"venue"
},
  "geometry": {"coordinates":[-73.082069397,45.4389953613],"type":"Point"}
}