{
  "type": "Feature",
  "properties": {
    "iso:country":"CA",
    "sg:address":"4600 Dundas St W",
    "sg:city":"Etobicoke",
    "sg:classifiers":[
        {
            "category":"Organizations",
            "subcategory":"Religious Organization",
            "type":"Services"
        }
    ],
    "sg:phone":"+1 416 239 2341",
    "sg:postcode":"M9A 1A5",
    "sg:province":"ON",
    "sg:tags":[
        "church"
    ],
    "wof:name":"St George's Church on the Hill",
    "wof:placetype":"venue"
},
  "geometry": {"coordinates":[-79.52072143549999,43.6568756104],"type":"Point"}
}