{
  "type": "Feature",
  "properties": {
    "addr:full":"1195 Ch Du Moulin Saint-Nicolas QC G7A 4J4",
    "addr:housenumber":"1195",
    "addr:postcode":"g7a 4j4",
    "addr:street":"Ch Du Moulin",
    "iso:country":"CA",
    "sg:address":"1195 Ch Du Moulin",
    "sg:city":"Saint-Nicolas",
    "sg:classifiers":[
        {
            "category":"Building & Trades",
            "subcategory":"Construction",
            "type":"Services"
        }
    ],
    "sg:phone":"+1 418 836 7629",
    "sg:postcode":"G7A 4J4",
    "sg:province":"QC",
    "sg:tags":[
        "plastering",
        "stucco",
        "contractor"
    ],
    "wof:name":"Art Concept Acrylique Inc",
    "wof:placetype":"venue"
},
  "geometry": {"coordinates":[-71.38526153559999,46.7066192627],"type":"Point"}
}