{
  "type": "Feature",
  "properties": {
    "addr:full":"1562 Danforth Ave Toronto ON M4J 1N4",
    "addr:housenumber":"1562",
    "addr:postcode":"m4j 1n4",
    "addr:street":"Danforth Ave",
    "iso:country":"CA",
    "sg:address":"1562 Danforth Ave",
    "sg:city":"Toronto",
    "sg:classifiers":[
        {
            "category":"Government",
            "subcategory":"Post Office",
            "type":"Public Place"
        }
    ],
    "sg:phone":"+1 416 463 0851",
    "sg:postcode":"M4J 1N4",
    "sg:province":"ON",
    "wof:name":"Canada Post Corp",
    "wof:placetype":"venue"
},
  "geometry": {"coordinates":[-79.323928833,43.6834220886],"type":"Point"}
}