{
  "type": "Feature",
  "properties": {
    "iso:country":"CA",
    "sg:city":"Baldonnel",
    "sg:classifiers":[
        {
            "category":"Home & Garden",
            "subcategory":"Garden Supply",
            "type":"Retail Goods"
        }
    ],
    "sg:phone":"+1 250 789 3646",
    "sg:postcode":"V0C 1C0",
    "sg:province":"BC",
    "sg:tags":[
        "bulb",
        "seed"
    ],
    "wof:name":"Hadland Seed Farm Ltd",
    "wof:placetype":"venue"
},
  "geometry": {"coordinates":[-120.71172332800001,56.2132949829],"type":"Point"}
}