{
  "type": "Feature",
  "properties": {
    "addr:full":"Saint-Jerome QC J5L 1T8",
    "addr:postcode":"j5l 1t8",
    "iso:country":"CA",
    "sg:city":"Saint-Jerome",
    "sg:classifiers":[
        {
            "category":"Autos & Motor Vehicles",
            "subcategory":"Automobile Sales",
            "type":"Retail Goods"
        }
    ],
    "sg:phone":"+1 450 438 6353",
    "sg:postcode":"J5L 1T8",
    "sg:province":"QC",
    "sg:tags":[
        "car",
        "dealer"
    ],
    "wof:name":"Services Expert Car",
    "wof:placetype":"venue"
},
  "geometry": {"coordinates":[-73.98876199999999,45.78503],"type":"Point"}
}