{
  "type": "Feature",
  "properties": {
    "addr:full":"2927 Norland Ave Burnaby BC V5B 3A9",
    "addr:housenumber":"2927",
    "addr:postcode":"v5b 3a9",
    "addr:street":"Norland Ave",
    "iso:country":"CA",
    "sg:address":"2927 Norland Ave",
    "sg:city":"Burnaby",
    "sg:classifiers":[
        {
            "category":"Home & Garden",
            "subcategory":"Building Materials",
            "type":"Retail Goods"
        }
    ],
    "sg:phone":"+1 604 205 9444",
    "sg:postcode":"V5B 3A9",
    "sg:province":"BC",
    "sg:tags":[
        "shower",
        "door",
        "enclosure"
    ],
    "wof:name":"Pacific Shower Doors Ltd",
    "wof:placetype":"venue"
},
  "geometry": {"coordinates":[-122.976989746,49.2567214966],"type":"Point"}
}