{
  "type": "Feature",
  "properties": {
    "iso:country":"CA",
    "sg:city":"Killam",
    "sg:classifiers":[
        {
            "category":"Health Services",
            "subcategory":"Doctor",
            "type":"Services"
        }
    ],
    "sg:phone":"+1 780 385 7890",
    "sg:postcode":"T0B 2L0",
    "sg:province":"AB",
    "sg:tags":[
        "clinic"
    ],
    "wof:name":"Killam Clinic",
    "wof:placetype":"venue"
},
  "geometry": {"coordinates":[-111.858901977,52.7893180847],"type":"Point"}
}