{
  "type": "Feature",
  "properties": {
    "addr:full":"318 Front St Belleville ON K8N 2Z8",
    "addr:housenumber":"318",
    "addr:postcode":"k8n 2z8",
    "addr:street":"Front St",
    "iso:country":"CA",
    "sg:address":"318 Front St",
    "sg:city":"Belleville",
    "sg:classifiers":[
        {
            "category":"Real Estate",
            "subcategory":"Real Estate Operator",
            "type":"Services"
        }
    ],
    "sg:phone":"+1 613 968 2242",
    "sg:postcode":"K8N 2Z8",
    "sg:province":"ON",
    "sg:tags":[
        "mall",
        "shopping",
        "center"
    ],
    "wof:name":"Belleville Business Imprvmnt",
    "wof:placetype":"venue"
},
  "geometry": {"coordinates":[-77.385735,44.166752],"type":"Point"}
}