{
  "type": "Feature",
  "properties": {
    "addr:full":"231 Mcdermot Ave Winnipeg MB R3B 0S4",
    "addr:housenumber":"231",
    "addr:postcode":"r3b 0s4",
    "addr:street":"Mcdermot Ave",
    "iso:country":"CA",
    "sg:address":"231 Mcdermot Ave",
    "sg:city":"Winnipeg",
    "sg:classifiers":[
        {
            "category":"Travel",
            "subcategory":"Hotels & Motels",
            "type":"Entertainment"
        }
    ],
    "sg:phone":"+1 204 947 9447",
    "sg:postcode":"R3B 0S4",
    "sg:province":"MB",
    "sg:tags":[
        "breakfast",
        "accommodation",
        "bed"
    ],
    "wof:name":"Mariaggi's Theme Suite Hotel",
    "wof:placetype":"venue"
},
  "geometry": {"coordinates":[-97.1403045654,49.8972167969],"type":"Point"}
}