{
  "type": "Feature",
  "properties": {
    "addr:full":"5500 Rue Fullum Montreal QC H2G 2H3",
    "addr:housenumber":"5500",
    "addr:postcode":"h2g 2h3",
    "addr:street":"Rue Fullum",
    "iso:country":"CA",
    "sg:address":"5500 Rue Fullum",
    "sg:city":"Montreal",
    "sg:classifiers":[
        {
            "category":"Professional",
            "subcategory":"Printing & Photocopies",
            "type":"Services"
        }
    ],
    "sg:phone":"+1 514 277 7535",
    "sg:postcode":"H2G 2H3",
    "sg:province":"QC",
    "sg:tags":[
        "packaging",
        "duplicating",
        "copying"
    ],
    "wof:name":"Imprime Emploi",
    "wof:placetype":"venue"
},
  "geometry": {"coordinates":[-73.5810623169,45.5424385071],"type":"Point"}
}