{
  "type": "Feature",
  "properties": {
    "addr:full":"8180 Ch Montview Mont-Royal QC H4P 2L7",
    "addr:postcode":"8180;h4p 2l7",
    "addr:street":"Ch Montview",
    "iso:country":"CA",
    "sg:address":"8180 Ch Montview",
    "sg:city":"Mont-Royal",
    "sg:classifiers":[
        {
            "category":"Autos & Motor Vehicles",
            "subcategory":"Auto Supplies",
            "type":"Retail Goods"
        }
    ],
    "sg:phone":"+1 514 736 0800",
    "sg:postcode":"H4P 2L7",
    "sg:province":"QC",
    "sg:tags":[
        "automobile",
        "parts"
    ],
    "wof:name":"Kit Motion Inc",
    "wof:placetype":"venue"
},
  "geometry": {"coordinates":[-73.669174,45.491524],"type":"Point"}
}