{
  "type": "Feature",
  "properties": {
    "addr:full":"336 Freshwater Rd St. John's NL A1B 1C2",
    "addr:housenumber":"336",
    "addr:postcode":"a1b 1c2",
    "addr:street":"Freshwater Rd",
    "iso:country":"CA",
    "sg:address":"336 Freshwater Rd",
    "sg:city":"St. John's",
    "sg:classifiers":[
        {
            "category":"Restaurant",
            "type":"Food & Drink"
        }
    ],
    "sg:phone":"+1 709 754 4485",
    "sg:postcode":"A1B 1C2",
    "sg:province":"NL",
    "sg:tags":[
        "chicken",
        "dinner"
    ],
    "wof:name":"Kfc",
    "wof:placetype":"venue"
},
  "geometry": {"coordinates":[-52.7455101013,47.5616455078],"type":"Point"}
}