{
  "type": "Feature",
  "properties": {
    "addr:full":"3324 Pollock Rd E Keswick ON L4P 3E9",
    "addr:housenumber":"3324",
    "addr:postcode":"l4p 3e9",
    "addr:street":"Pollock Rd E",
    "iso:country":"CA",
    "sg:address":"3324 Pollock Rd E",
    "sg:city":"Keswick",
    "sg:classifiers":[
        {
            "category":"Building & Trades",
            "subcategory":"Construction",
            "type":"Services"
        }
    ],
    "sg:phone":"+1 905 476 7574",
    "sg:postcode":"L4P 3E9",
    "sg:province":"ON",
    "sg:tags":[
        "pond",
        "supply"
    ],
    "wof:name":"Lily Pool",
    "wof:placetype":"venue"
},
  "geometry": {"coordinates":[-79.416893,44.242031],"type":"Point"}
}