{
  "type": "Feature",
  "properties": {
    "addr:full":"Hillsburgh ON N0B 1Z0",
    "addr:postcode":"n0b 1z0",
    "iso:country":"CA",
    "sg:city":"Hillsburgh",
    "sg:classifiers":[
        {
            "category":"Wholesale",
            "subcategory":"Construction Materials",
            "type":"Manufacturing & Wholesale Goods"
        }
    ],
    "sg:phone":"+1 519 855 4546",
    "sg:postcode":"N0B 1Z0",
    "sg:province":"ON",
    "sg:tags":[
        "sand",
        "gravel"
    ],
    "wof:name":"Strada Aggregates",
    "wof:placetype":"venue"
},
  "geometry": {"coordinates":[-80.17495700000001,43.785999],"type":"Point"}
}