{
  "type": "Feature",
  "properties": {
    "addr:full":"9 Front St N Thorold ON L2V 1X3",
    "addr:housenumber":"9",
    "addr:postcode":"l2v 1x3",
    "addr:street":"Front St N",
    "iso:country":"CA",
    "sg:address":"9 Front St N",
    "sg:city":"Thorold",
    "sg:classifiers":[
        {
            "category":"Insurance",
            "subcategory":"Insurance Agent",
            "type":"Services"
        }
    ],
    "sg:phone":"+1 905 227 6631",
    "sg:postcode":"L2V 1X3",
    "sg:province":"ON",
    "wof:name":"Hope & Harder Insurance Brkrs",
    "wof:placetype":"venue"
},
  "geometry": {"coordinates":[-79.20090500000001,43.125416],"type":"Point"}
}