{
  "type": "Feature",
  "properties": {
    "addr:full":"Millet AB T0C 1Z0",
    "addr:postcode":"t0c 1z0",
    "iso:country":"CA",
    "sg:city":"Millet",
    "sg:classifiers":[
        {
            "category":"Building & Trades",
            "subcategory":"Equipment Rental",
            "type":"Services"
        }
    ],
    "sg:phone":"+1 780 387 5886",
    "sg:postcode":"T0C 1Z0",
    "sg:province":"AB",
    "sg:tags":[
        "player",
        "recorder",
        "video"
    ],
    "wof:name":"Canadian Video",
    "wof:placetype":"venue"
},
  "geometry": {"coordinates":[-113.469352722,53.0906906128],"type":"Point"}
}