{
  "type": "Feature",
  "properties": {
    "addr:full":"Quebec QC G2K 2K8",
    "addr:postcode":"g2k 2k8",
    "iso:country":"CA",
    "sg:city":"Quebec",
    "sg:classifiers":[
        {
            "category":"Professional",
            "subcategory":"Management & Consulting",
            "type":"Services"
        }
    ],
    "sg:phone":"+1 418 626 2360",
    "sg:postcode":"G2K 2K8",
    "sg:province":"QC",
    "sg:tags":[
        "marketing",
        "consultant"
    ],
    "wof:name":"Zins Beauchesne & Assoc",
    "wof:placetype":"venue"
},
  "geometry": {"coordinates":[-71.291222,46.836147],"type":"Point"}
}