{
  "type": "Feature",
  "properties": {
    "addr:full":"1420 Jefferson Ave Winnipeg MB R2P 0Y7",
    "addr:housenumber":"1420",
    "addr:postcode":"r2p 0y7",
    "addr:street":"Jefferson Ave",
    "iso:country":"CA",
    "sg:address":"1420 Jefferson Ave",
    "sg:city":"Winnipeg",
    "sg:classifiers":[
        {
            "category":"Food & Beverages",
            "subcategory":"Groceries & Convenience Stores",
            "type":"Retail Goods"
        }
    ],
    "sg:phone":"+1 204 632 1327",
    "sg:postcode":"R2P 0Y7",
    "sg:province":"MB",
    "wof:name":"Shell Canada Products Ltd",
    "wof:placetype":"venue"
},
  "geometry": {"coordinates":[-97.17143249510001,49.9561080933],"type":"Point"}
}