{
  "type": "Feature",
  "properties": {
    "addr:full":"531 Boul Saint-Laurent O Louiseville QC J5V 1K6",
    "addr:housenumber":"531",
    "addr:postcode":"j5v 1k6",
    "addr:street":"Boul Saint-Laurent O",
    "iso:country":"CA",
    "sg:address":"531 Boul Saint-Laurent O",
    "sg:city":"Louiseville",
    "sg:classifiers":[
        {
            "category":"Wholesale",
            "subcategory":"Auto Parts",
            "type":"Manufacturing & Wholesale Goods"
        }
    ],
    "sg:phone":"+1 819 228 5585",
    "sg:postcode":"J5V 1K6",
    "sg:province":"QC",
    "sg:tags":[
        "automobile",
        "supply"
    ],
    "wof:name":"Accessoires D'Auto Rene Inc",
    "wof:placetype":"venue"
},
  "geometry": {"coordinates":[-72.92692599999999,46.257156],"type":"Point"}
}