{
  "type": "Feature",
  "properties": {
    "addr:full":"219 Main St Meductic NB E6H 2L5",
    "addr:housenumber":"219",
    "addr:postcode":"e6h 2l5",
    "addr:street":"Main St",
    "iso:country":"CA",
    "sg:address":"219 Main St",
    "sg:city":"Meductic",
    "sg:classifiers":[
        {
            "category":"Manufacturing",
            "subcategory":"Musical Instruments",
            "type":"Manufacturing & Wholesale Goods"
        }
    ],
    "sg:phone":"+1 506 272 2019",
    "sg:postcode":"E6H 2L5",
    "sg:province":"NB",
    "wof:name":"Sabian Limited",
    "wof:placetype":"venue"
},
  "geometry": {"coordinates":[-67.474403,45.993706],"type":"Point"}
}