{
  "type": "Feature",
  "properties": {
    "addr:full":"233 Lorne St E Swift Current SK S9H 1V3",
    "addr:housenumber":"233",
    "addr:postcode":"s9h 1v3",
    "addr:street":"Lorne St E",
    "iso:country":"CA",
    "sg:address":"233 Lorne St E",
    "sg:city":"Swift Current",
    "sg:classifiers":[
        {
            "category":"Retail",
            "subcategory":"Funeral Services",
            "type":"Services"
        }
    ],
    "sg:phone":"+1 306 773 8355",
    "sg:postcode":"S9H 1V3",
    "sg:province":"SK",
    "sg:tags":[
        "director"
    ],
    "wof:name":"Swift Current Funeral Home",
    "wof:placetype":"venue"
},
  "geometry": {"coordinates":[-107.797439575,50.2898902893],"type":"Point"}
}