{
  "type": "Feature",
  "properties": {
    "addr:full":"12 Langley Ave Dartmouth NS B2W 2Y6",
    "addr:housenumber":"12",
    "addr:postcode":"b2w 2y6",
    "addr:street":"Langley Ave",
    "iso:country":"CA",
    "sg:address":"12 Langley Ave",
    "sg:city":"Dartmouth",
    "sg:classifiers":[
        {
            "category":"Professional",
            "subcategory":"Detective & Security Services",
            "type":"Services"
        }
    ],
    "sg:phone":"+1 902 435 0010",
    "sg:postcode":"B2W 2Y6",
    "sg:province":"NS",
    "sg:tags":[
        "guard",
        "patrol"
    ],
    "wof:name":"White Security & Investigation",
    "wof:placetype":"venue"
},
  "geometry": {"coordinates":[-63.533066,44.674679],"type":"Point"}
}