{
  "type": "Feature",
  "properties": {
    "iso:country":"CA",
    "sg:address":"11400 Tecumseh Rd E",
    "sg:city":"Windsor",
    "sg:classifiers":[
        {
            "category":"Shopping",
            "subcategory":"Computers & Home Electronics",
            "type":"Retail Goods"
        }
    ],
    "sg:phone":"+1 519 979 7101",
    "sg:postcode":"N8N 1L7",
    "sg:province":"ON",
    "sg:tags":[
        "high",
        "fidelity",
        "stereophonic",
        "audio"
    ],
    "wof:name":"Audio Two",
    "wof:placetype":"venue"
},
  "geometry": {"coordinates":[-82.9032897949,42.3129615784],"type":"Point"}
}