{
  "type": "Feature",
  "properties": {
    "addr:full":"Thornhill ON L3T 7T1",
    "addr:postcode":"l3t 7t1",
    "iso:country":"CA",
    "sg:city":"Thornhill",
    "sg:classifiers":[
        {
            "category":"Restaurant",
            "type":"Food & Drink"
        }
    ],
    "sg:phone":"+1 905 762 1338",
    "sg:postcode":"L3T 7T1",
    "sg:province":"ON",
    "wof:name":"Korean Barbecue Restaurant",
    "wof:placetype":"venue"
},
  "geometry": {"coordinates":[-79.386787,43.84322],"type":"Point"}
}