{
  "type": "Feature",
  "properties": {
    "addr:full":"1300 Fewster Dr Mississauga ON L4W 1A4",
    "addr:housenumber":"1300",
    "addr:postcode":"l4w 1a4",
    "addr:street":"Fewster Dr",
    "iso:country":"CA",
    "sg:address":"1300 Fewster Dr",
    "sg:city":"Mississauga",
    "sg:classifiers":[
        {
            "category":"Building & Trades",
            "subcategory":"Construction",
            "type":"Services"
        }
    ],
    "sg:phone":"+1 905 625 7739",
    "sg:postcode":"L4W 1A4",
    "sg:province":"ON",
    "sg:tags":[
        "sandblasting"
    ],
    "wof:name":"Blast & Coat",
    "wof:placetype":"venue"
},
  "geometry": {"coordinates":[-79.6179733276,43.6309051514],"type":"Point"}
}