{
  "type": "Feature",
  "properties": {
    "addr:full":"Mississauga ON L5N 5L9",
    "addr:postcode":"l5n 5l9",
    "iso:country":"CA",
    "sg:city":"Mississauga",
    "sg:classifiers":[
        {
            "category":"Manufacturing",
            "subcategory":"Tools & Machinery",
            "type":"Manufacturing & Wholesale Goods"
        }
    ],
    "sg:phone":"+1 905 567 7819",
    "sg:postcode":"L5N 5L9",
    "sg:province":"ON",
    "sg:tags":[
        "manufacturer"
    ],
    "wof:name":"Promat Engineering Sales",
    "wof:placetype":"venue"
},
  "geometry": {"coordinates":[-79.73683200000001,43.60619],"type":"Point"}
}