{
  "type": "Feature",
  "properties": {
    "addr:full":"120 Cedar Dr Niverville MB R0A 1E0",
    "addr:housenumber":"120",
    "addr:postcode":"r0a 1e0",
    "addr:street":"Cedar Dr",
    "iso:country":"CA",
    "sg:address":"120 Cedar Dr",
    "sg:city":"Niverville",
    "sg:classifiers":[
        {
            "category":"Retail",
            "subcategory":"Auto Repair",
            "type":"Services"
        }
    ],
    "sg:phone":"+1 204 388 6450",
    "sg:postcode":"R0A 1E0",
    "sg:province":"MB",
    "sg:tags":[
        "truck"
    ],
    "wof:name":"Mc Naughton Mechanical Svc Inc",
    "wof:placetype":"venue"
},
  "geometry": {"coordinates":[-97.0414428711,49.6059188843],"type":"Point"}
}