{
  "type": "Feature",
  "properties": {
    "addr:full":"General Delivery Harbour Grace NL A0A 2M0",
    "addr:postcode":"a0a 2m0",
    "iso:country":"CA",
    "sg:address":"General Delivery",
    "sg:city":"Harbour Grace",
    "sg:classifiers":[
        {
            "category":"Retail",
            "subcategory":"Car Wash",
            "type":"Services"
        }
    ],
    "sg:phone":"+1 709 683 1379",
    "sg:postcode":"A0A 2M0",
    "sg:province":"NL",
    "sg:tags":[
        "automobile",
        "detail",
        "clean"
    ],
    "wof:name":"Professional Auto Boat & Care",
    "wof:placetype":"venue"
},
  "geometry": {"coordinates":[-53.24401474,47.6816673279],"type":"Point"}
}