{
  "type": "Feature",
  "properties": {
    "addr:full":"902 Railway Ave Rocanville SK S0A 3L0",
    "addr:housenumber":"902",
    "addr:postcode":"s0a 3l0",
    "addr:street":"Railway Ave",
    "iso:country":"CA",
    "sg:address":"902 Railway Ave",
    "sg:city":"Rocanville",
    "sg:classifiers":[
        {
            "category":"Building & Trades",
            "subcategory":"Construction",
            "type":"Services"
        }
    ],
    "sg:phone":"+1 306 645 2028",
    "sg:postcode":"S0A 3L0",
    "sg:province":"SK",
    "sg:tags":[
        "general",
        "contractor"
    ],
    "wof:name":"South East Construction",
    "wof:placetype":"venue"
},
  "geometry": {"coordinates":[-101.699920654,50.3824424744],"type":"Point"}
}