{
  "type": "Feature",
  "properties": {
    "addr:full":"Shelleys Rd Bonavista NL A0C 1B0",
    "addr:postcode":"a0c 1b0",
    "addr:street":"Shelleys Rd",
    "iso:country":"CA",
    "sg:address":"Shelleys Rd",
    "sg:city":"Bonavista",
    "sg:classifiers":[
        {
            "category":"Education",
            "subcategory":"School",
            "type":"Public Place"
        }
    ],
    "sg:phone":"+1 709 468 7242",
    "sg:postcode":"A0C 1B0",
    "sg:province":"NL",
    "wof:name":"Matthews Elementary School",
    "wof:placetype":"venue"
},
  "geometry": {"coordinates":[-53.099129,48.656128],"type":"Point"}
}