{
  "type": "Feature",
  "properties": {
    "addr:full":"2910 Waterford Pl Coquitlam BC V3E 2S1",
    "addr:housenumber":"2910",
    "addr:postcode":"v3e 2s1",
    "addr:street":"Waterford Pl",
    "iso:country":"CA",
    "sg:address":"2910 Waterford Pl",
    "sg:city":"Coquitlam",
    "sg:classifiers":[
        {
            "category":"Wholesale",
            "subcategory":"Durable Goods & Equipment",
            "type":"Manufacturing & Wholesale Goods"
        }
    ],
    "sg:phone":"+1 604 594 6690",
    "sg:postcode":"V3E 2S1",
    "sg:province":"BC",
    "sg:tags":[
        "representative",
        "manufacturer"
    ],
    "wof:name":"Great Canadian Coaster CO",
    "wof:placetype":"venue"
},
  "geometry": {"coordinates":[-122.793334961,49.2966918945],"type":"Point"}
}