{
  "type": "Feature",
  "properties": {
    "addr:full":"600 Gosselin Wotton QC J0A 1N0",
    "addr:housenumber":"600",
    "addr:postcode":"j0a 1n0",
    "addr:street":"Gosselin",
    "iso:country":"CA",
    "sg:address":"600 Gosselin",
    "sg:city":"Wotton",
    "sg:classifiers":[
        {
            "category":"Government",
            "subcategory":"Police Station",
            "type":"Public Place"
        }
    ],
    "sg:phone":"+1 819 828 1313",
    "sg:postcode":"J0A 1N0",
    "sg:province":"QC",
    "sg:tags":[
        "department"
    ],
    "wof:name":"Quebec Surete",
    "wof:placetype":"venue"
},
  "geometry": {"coordinates":[-71.7991409302,45.7449569702],"type":"Point"}
}