{
  "type": "Feature",
  "properties": {
    "addr:full":"2087 Montreal Rd Gloucester ON K1J 6M6",
    "addr:housenumber":"2087",
    "addr:postcode":"k1j 6m6",
    "addr:street":"Montreal Rd",
    "iso:country":"CA",
    "sg:address":"2087 Montreal Rd",
    "sg:city":"Gloucester",
    "sg:classifiers":[
        {
            "category":"Personal",
            "subcategory":"Beauty Salon",
            "type":"Services"
        }
    ],
    "sg:phone":"+1 613 748 0165",
    "sg:postcode":"K1J 6M6",
    "sg:province":"ON",
    "wof:name":"Cloud Nine",
    "wof:placetype":"venue"
},
  "geometry": {"coordinates":[-75.593452,45.447872],"type":"Point"}
}