{
  "type": "Feature",
  "properties": {
    "addr:full":"Calgary AB T2S 3C2",
    "addr:postcode":"t2s 3c2",
    "iso:country":"CA",
    "sg:city":"Calgary",
    "sg:classifiers":[
        {
            "category":"Organizations",
            "subcategory":"Professional Association",
            "type":"Services"
        }
    ],
    "sg:phone":"+1 403 283 1500",
    "sg:postcode":"T2S 3C2",
    "sg:province":"AB",
    "wof:name":"Diabetes Association",
    "wof:placetype":"venue"
},
  "geometry": {"coordinates":[-114.06871032700001,51.0331954956],"type":"Point"}
}