{
  "type": "Feature",
  "properties": {
    "addr:full":"5732 176 St Surrey BC V3S 4C8",
    "addr:housenumber":"5732",
    "addr:postcode":"v3s 4c8",
    "addr:street":"176 St",
    "iso:country":"CA",
    "sg:address":"5732 176 St",
    "sg:city":"Surrey",
    "sg:classifiers":[
        {
            "category":"Cinema",
            "subcategory":"Movie Theater",
            "type":"Entertainment"
        }
    ],
    "sg:phone":"+1 604 574 1114",
    "sg:postcode":"V3S 4C8",
    "sg:province":"BC",
    "wof:name":"Clova Cinemas",
    "wof:placetype":"venue"
},
  "geometry": {"coordinates":[-122.734909,49.10397],"type":"Point"}
}