{
  "type": "Feature",
  "properties": {
    "iso:country":"CA",
    "sg:address":"520 Boundary Rd",
    "sg:city":"Novar",
    "sg:classifiers":[
        {
            "category":"Health Services",
            "subcategory":"Doctor",
            "type":"Services"
        }
    ],
    "sg:phone":"+1 705 789 1131",
    "sg:postcode":"P0A 1R0",
    "sg:province":"ON",
    "sg:tags":[
        "physician",
        "surgeon"
    ],
    "wof:name":"Hillier, David W MD",
    "wof:placetype":"venue"
},
  "geometry": {"coordinates":[-79.25476837159999,45.4477500916],"type":"Point"}
}