{
  "type": "Feature",
  "properties": {
    "addr:full":"Mississauga ON L5L 5R4",
    "addr:postcode":"l5l 5r4",
    "iso:country":"CA",
    "sg:city":"Mississauga",
    "sg:classifiers":[
        {
            "category":"Home & Garden",
            "subcategory":"Building Materials",
            "type":"Retail Goods"
        }
    ],
    "sg:phone":"+1 905 569 9133",
    "sg:postcode":"L5L 5R4",
    "sg:province":"ON",
    "sg:tags":[
        "door"
    ],
    "wof:name":"B & M Garage Door",
    "wof:placetype":"venue"
},
  "geometry": {"coordinates":[-79.695183,43.518394],"type":"Point"}
}