{
  "type": "Feature",
  "properties": {
    "addr:full":"Hamilton ON L8W 3M6",
    "addr:postcode":"l8w 3m6",
    "iso:country":"CA",
    "sg:city":"Hamilton",
    "sg:classifiers":[
        {
            "category":"Restaurant",
            "type":"Food & Drink"
        }
    ],
    "sg:phone":"+1 905 388 5757",
    "sg:postcode":"L8W 3M6",
    "sg:province":"ON",
    "sg:tags":[
        "pizza"
    ],
    "wof:name":"Mr Grande Pizza",
    "wof:placetype":"venue"
},
  "geometry": {"coordinates":[-79.84177398680001,43.1899909973],"type":"Point"}
}