{
  "type": "Feature",
  "properties": {
    "addr:full":"60 Ch Du Golf Arundel QC J0T 1A0",
    "addr:housenumber":"60",
    "addr:postcode":"j0t 1a0",
    "addr:street":"Ch Du Golf",
    "iso:country":"CA",
    "sg:address":"60 Ch Du Golf",
    "sg:city":"Arundel",
    "sg:classifiers":[
        {
            "category":"Sports & Exercise",
            "subcategory":"Golf",
            "type":"Entertainment"
        }
    ],
    "sg:phone":"+1 819 687 3292",
    "sg:postcode":"J0T 1A0",
    "sg:province":"QC",
    "sg:tags":[
        "course"
    ],
    "wof:name":"Arundel Golf & Country Club",
    "wof:placetype":"venue"
},
  "geometry": {"coordinates":[-74.618324,45.982307],"type":"Point"}
}