{
  "type": "Feature",
  "properties": {
    "addr:full":"329 Main St Watford ON N0M 2S0",
    "addr:housenumber":"329",
    "addr:postcode":"n0m 2s0",
    "addr:street":"Main St",
    "iso:country":"CA",
    "sg:address":"329 Main St",
    "sg:city":"Watford",
    "sg:classifiers":[
        {
            "category":"Shopping",
            "subcategory":"Discount & Variety Stores",
            "type":"Retail Goods"
        }
    ],
    "sg:phone":"+1 519 876 2283",
    "sg:postcode":"N0M 2S0",
    "sg:province":"ON",
    "wof:name":"Terminal One Variety & Gift",
    "wof:placetype":"venue"
},
  "geometry": {"coordinates":[-81.87985999999999,42.946934],"type":"Point"}
}