{
  "type": "Feature",
  "properties": {
    "addr:full":"265 Rue Saint-Paul Quebec QC G1K 3W6",
    "addr:housenumber":"265",
    "addr:postcode":"g1k 3w6",
    "addr:street":"Rue Saint-Paul",
    "iso:country":"CA",
    "sg:address":"265 Rue Saint-Paul",
    "sg:city":"Quebec",
    "sg:classifiers":[
        {
            "category":"Building & Trades",
            "subcategory":"Construction",
            "type":"Services"
        }
    ],
    "sg:phone":"+1 418 692 1711",
    "sg:postcode":"G1K 3W6",
    "sg:province":"QC",
    "sg:tags":[
        "tile",
        "dealer"
    ],
    "wof:name":"Ceragres Carreaux Canada Ltee",
    "wof:placetype":"venue"
},
  "geometry": {"coordinates":[-71.21058654789999,46.8169708252],"type":"Point"}
}