{
  "type": "Feature",
  "properties": {
    "addr:full":"Mississauga ON L5T 1X4",
    "addr:postcode":"l5t 1x4",
    "iso:country":"CA",
    "sg:city":"Mississauga",
    "sg:classifiers":[
        {
            "category":"Wholesale",
            "subcategory":"Construction Materials",
            "type":"Manufacturing & Wholesale Goods"
        }
    ],
    "sg:phone":"+1 905 564 2112",
    "sg:postcode":"L5T 1X4",
    "sg:province":"ON",
    "sg:tags":[
        "frame",
        "door"
    ],
    "wof:name":"Wilson Hollow Metal Sales Ltd",
    "wof:placetype":"venue"
},
  "geometry": {"coordinates":[-79.6600265503,43.6649169922],"type":"Point"}
}