{
  "type": "Feature",
  "properties": {
    "iso:country":"CA",
    "sg:address":"1055 Mackenzie Ave S",
    "sg:city":"Williams Lake",
    "sg:classifiers":[
        {
            "category":"Retail",
            "subcategory":"Auto Repair",
            "type":"Services"
        }
    ],
    "sg:phone":"+1 250 392 7147",
    "sg:postcode":"V2G 3X9",
    "sg:province":"BC",
    "sg:tags":[
        "repairing",
        "tire"
    ],
    "wof:name":"Kal Tire",
    "wof:placetype":"venue"
},
  "geometry": {"coordinates":[-122.12539700000001,52.124615],"type":"Point"}
}