{
  "type": "Feature",
  "properties": {
    "iso:country":"CA",
    "sg:city":"Black Lake",
    "sg:classifiers":[
        {
            "category":"Restaurant",
            "type":"Food & Drink"
        }
    ],
    "sg:phone":"+1 418 423 9029",
    "sg:postcode":"G6H 2J8",
    "sg:province":"QC",
    "wof:name":"Restaurant Anne-Caro",
    "wof:placetype":"venue"
},
  "geometry": {"coordinates":[-71.3666687012,46.0529747009],"type":"Point"}
}