{
  "type": "Feature",
  "properties": {
    "addr:full":"1675 Burgess St Masset BC V0T 1M0",
    "addr:housenumber":"1675",
    "addr:postcode":"v0t 1m0",
    "addr:street":"Burgess St",
    "iso:country":"CA",
    "sg:address":"1675 Burgess St",
    "sg:city":"Masset",
    "sg:classifiers":[
        {
            "category":"Shopping",
            "subcategory":"Bicycles & Sporting Goods",
            "type":"Retail Goods"
        }
    ],
    "sg:phone":"+1 250 626 3444",
    "sg:postcode":"V0T 1M0",
    "sg:province":"BC",
    "sg:tags":[
        "gun",
        "gunsmith"
    ],
    "wof:name":"E R Robinson Firearms Safety",
    "wof:placetype":"venue"
},
  "geometry": {"coordinates":[-132.13208,54.009029],"type":"Point"}
}