{
  "type": "Feature",
  "properties": {
    "addr:full":"152 Dundas St E Trenton ON K8V 1L4",
    "addr:housenumber":"152",
    "addr:postcode":"k8v 1l4",
    "addr:street":"Dundas St E",
    "iso:country":"CA",
    "sg:address":"152 Dundas St E",
    "sg:city":"Trenton",
    "sg:classifiers":[
        {
            "category":"Health Services",
            "subcategory":"Doctor",
            "type":"Services"
        }
    ],
    "sg:phone":"+1 613 392 3546",
    "sg:postcode":"K8V 1L4",
    "sg:province":"ON",
    "sg:tags":[
        "physician",
        "surgeon"
    ],
    "wof:name":"Cooke, Donald W MD",
    "wof:placetype":"venue"
},
  "geometry": {"coordinates":[-77.56610870359999,44.1048660278],"type":"Point"}
}