{
  "type": "Feature",
  "properties": {
    "addr:full":"Sauble Beach ON N0H 2G0",
    "addr:postcode":"n0h 2g0",
    "iso:country":"CA",
    "sg:city":"Sauble Beach",
    "sg:classifiers":[
        {
            "category":"Professional",
            "type":"Services"
        }
    ],
    "sg:phone":"+1 519 422 1538",
    "sg:postcode":"N0H 2G0",
    "sg:province":"ON",
    "sg:tags":[
        "interior",
        "consultant",
        "arts",
        "design",
        "decorator"
    ],
    "wof:name":"M & D Crafts & Sewing",
    "wof:placetype":"venue"
},
  "geometry": {"coordinates":[-81.2632522583,44.6296615601],"type":"Point"}
}