{
  "type": "Feature",
  "properties": {
    "iso:country":"CA",
    "sg:address":"2714 Boul DE LA Concorde E",
    "sg:city":"Laval",
    "sg:classifiers":[
        {
            "category":"Shopping",
            "subcategory":"Clothing, Apparel, & Fashions",
            "type":"Retail Goods"
        }
    ],
    "sg:phone":"+1 450 663 6644",
    "sg:postcode":"H7E 2B4",
    "sg:province":"QC",
    "sg:tags":[
        "dressmaker"
    ],
    "wof:name":"Piorucci Inc",
    "wof:placetype":"venue"
},
  "geometry": {"coordinates":[-73.67059326170001,45.5897941589],"type":"Point"}
}