{
  "type": "Feature",
  "properties": {
    "addr:full":"20 Rue Daniel-Johnson Danville QC J0A 1A0",
    "addr:housenumber":"20",
    "addr:postcode":"j0a 1a0",
    "addr:street":"Rue Daniel-Johnson",
    "iso:country":"CA",
    "sg:address":"20 Rue Daniel-Johnson",
    "sg:city":"Danville",
    "sg:classifiers":[
        {
            "category":"Insurance",
            "subcategory":"Insurance Agent",
            "type":"Services"
        }
    ],
    "sg:phone":"+1 819 839 2714",
    "sg:postcode":"J0A 1A0",
    "sg:province":"QC",
    "wof:name":"Assurances Nicole Frechette",
    "wof:placetype":"venue"
},
  "geometry": {"coordinates":[-72.0151062012,45.7846717834],"type":"Point"}
}