{
  "type": "Feature",
  "properties": {
    "iso:country":"CA",
    "sg:address":"1280 Rue Principale",
    "sg:city":"Saint-Philemon",
    "sg:classifiers":[
        {
            "category":"Autos & Motor Vehicles",
            "subcategory":"Fuel & Gas Station",
            "type":"Retail Goods"
        }
    ],
    "sg:phone":"+1 418 469 2825",
    "sg:postcode":"G0R 4A0",
    "sg:province":"QC",
    "sg:tags":[
        "oil"
    ],
    "wof:name":"Depanneur Yvan Laflamme",
    "wof:placetype":"venue"
},
  "geometry": {"coordinates":[-70.4546661377,46.6822128296],"type":"Point"}
}