{
  "type": "Feature",
  "properties": {
    "iso:country":"CA",
    "sg:city":"Richmond",
    "sg:classifiers":[
        {
            "category":"Travel",
            "subcategory":"Travel Agent",
            "type":"Entertainment"
        }
    ],
    "sg:phone":"+1 604 278 8732",
    "sg:postcode":"V6X 2C2",
    "sg:province":"BC",
    "sg:tags":[
        "agency",
        "bureau"
    ],
    "wof:name":"Dominion Pacific Travel Ltd",
    "wof:placetype":"venue"
},
  "geometry": {"coordinates":[-123.136230469,49.18334198],"type":"Point"}
}