{
  "type": "Feature",
  "properties": {
    "addr:full":"54 Rue Principale Lac-Edouard QC G0X 3N0",
    "addr:housenumber":"54",
    "addr:postcode":"g0x 3n0",
    "addr:street":"Rue Principale",
    "iso:country":"CA",
    "sg:address":"54 Rue Principale",
    "sg:city":"Lac-Edouard",
    "sg:classifiers":[
        {
            "category":"Building & Trades",
            "subcategory":"Construction",
            "type":"Services"
        }
    ],
    "sg:phone":"+1 819 653 2288",
    "sg:postcode":"G0X 3N0",
    "sg:province":"QC",
    "sg:tags":[
        "excavating",
        "contractor"
    ],
    "wof:name":"Entrepreneur Gilles Cloutier",
    "wof:placetype":"venue"
},
  "geometry": {"coordinates":[-72.278572,47.661465],"type":"Point"}
}