{
  "type": "Feature",
  "properties": {
    "addr:full":"3185 Ch Saint-Charles Lachenaie QC J6V 1C4",
    "addr:postcode":"3185;j6v 1c4",
    "addr:street":"Ch Saint-Charles",
    "iso:country":"CA",
    "sg:address":"3185 Ch Saint-Charles",
    "sg:city":"Lachenaie",
    "sg:classifiers":[
        {
            "category":"Retail",
            "subcategory":"Auto Repair",
            "type":"Services"
        }
    ],
    "sg:phone":"+1 450 964 1944",
    "sg:postcode":"J6V 1C4",
    "sg:province":"QC",
    "sg:tags":[
        "body",
        "automobile",
        "painting"
    ],
    "wof:name":"Carrosserie Mike Enr",
    "wof:placetype":"venue"
},
  "geometry": {"coordinates":[-73.56006600000001,45.701942],"type":"Point"}
}