{
  "type": "Feature",
  "properties": {
    "addr:full":"3525 Boul DE LA Grande-Allee Boisbriand QC J7H 1H5",
    "addr:housenumber":"3525",
    "addr:postcode":"j7h 1h5",
    "addr:street":"Boul De La Grande-Allee",
    "iso:country":"CA",
    "sg:address":"3525 Boul DE LA Grande-Allee",
    "sg:city":"Boisbriand",
    "sg:classifiers":[
        {
            "category":"Manufacturing",
            "subcategory":"Signs",
            "type":"Manufacturing & Wholesale Goods"
        }
    ],
    "sg:phone":"+1 450 979 6620",
    "sg:postcode":"J7H 1H5",
    "sg:province":"QC",
    "sg:tags":[
        "designer",
        "display",
        "producer"
    ],
    "wof:name":"Damotech Inc",
    "wof:placetype":"venue"
},
  "geometry": {"coordinates":[-73.8592,45.629116],"type":"Point"}
}