{
  "type": "Feature",
  "properties": {
    "addr:full":"10970 100 Ave Grande Prairie AB T8V 7G5",
    "addr:housenumber":"10970",
    "addr:postcode":"t8v 7g5",
    "addr:street":"100 Ave",
    "iso:country":"CA",
    "sg:address":"10970 100 Ave",
    "sg:city":"Grande Prairie",
    "sg:classifiers":[
        {
            "category":"Autos & Motor Vehicles",
            "subcategory":"Fuel & Gas Station",
            "type":"Retail Goods"
        }
    ],
    "sg:phone":"+1 780 513 4416",
    "sg:postcode":"T8V 7G5",
    "sg:province":"AB",
    "sg:tags":[
        "oil"
    ],
    "wof:name":"Gateway Mohawk",
    "wof:placetype":"venue"
},
  "geometry": {"coordinates":[-118.828186,55.170883],"type":"Point"}
}