{
  "type": "Feature",
  "properties": {
    "addr:full":"8403 Hwy 1 Meteghan NS B0W 2J0",
    "addr:housenumber":"8403",
    "addr:postcode":"b0w 2j0",
    "addr:street":"Hwy 1",
    "iso:country":"CA",
    "sg:address":"8403 Hwy 1",
    "sg:city":"Meteghan",
    "sg:classifiers":[
        {
            "category":"Health Services",
            "subcategory":"Nursing And Care Facility",
            "type":"Services"
        }
    ],
    "sg:phone":"+1 902 645 2065",
    "sg:postcode":"B0W 2J0",
    "sg:province":"NS",
    "sg:tags":[
        "home",
        "convalescent"
    ],
    "wof:name":"Villa Acadienne",
    "wof:placetype":"venue"
},
  "geometry": {"coordinates":[-66.15973700000001,44.189121],"type":"Point"}
}