{
  "type": "Feature",
  "properties": {
    "addr:full":"1890 Kingsway Vancouver BC V5N 2S7",
    "addr:housenumber":"1890",
    "addr:postcode":"v5n 2s7",
    "addr:street":"Kingsway",
    "iso:country":"CA",
    "sg:address":"1890 Kingsway",
    "sg:city":"Vancouver",
    "sg:classifiers":[
        {
            "category":"Manufacturing",
            "subcategory":"Printing",
            "type":"Manufacturing & Wholesale Goods"
        }
    ],
    "sg:phone":"+1 604 708 8688",
    "sg:postcode":"V5N 2S7",
    "sg:province":"BC",
    "sg:tags":[
        "printer"
    ],
    "wof:name":"U-Save Graphic & Printing",
    "wof:placetype":"venue"
},
  "geometry": {"coordinates":[-123.06682586700001,49.2457580566],"type":"Point"}
}