{
  "type": "Feature",
  "properties": {
    "addr:full":"1811 Boul Pie-Xi N Val-Belair QC G3J 1N5",
    "addr:housenumber":"1811",
    "addr:postcode":"g3j 1n5",
    "addr:street":"Boul Pie-Xi N",
    "iso:country":"CA",
    "sg:address":"1811 Boul Pie-Xi N",
    "sg:city":"Val-Belair",
    "sg:classifiers":[
        {
            "category":"Bars & Pubs",
            "type":"Food & Drink"
        }
    ],
    "sg:phone":"+1 418 842 7777",
    "sg:postcode":"G3J 1N5",
    "sg:province":"QC",
    "sg:tags":[
        "lounge",
        "cocktail"
    ],
    "wof:name":"Bar Le Regency",
    "wof:placetype":"venue"
},
  "geometry": {"coordinates":[-71.4490280151,46.872379303],"type":"Point"}
}