{
  "type": "Feature",
  "properties": {
    "addr:full":"Cabano QC G0L 1E0",
    "addr:postcode":"g0l 1e0",
    "iso:country":"CA",
    "sg:city":"Cabano",
    "sg:classifiers":[
        {
            "category":"Health Services",
            "subcategory":"Doctor",
            "type":"Services"
        }
    ],
    "sg:phone":"+1 418 854 2762",
    "sg:postcode":"G0L 1E0",
    "sg:province":"QC",
    "sg:tags":[
        "physician",
        "surgeon"
    ],
    "wof:name":"Cote, Guildo MD",
    "wof:placetype":"venue"
},
  "geometry": {"coordinates":[-68.879486,47.683708],"type":"Point"}
}