{
  "type": "Feature",
  "properties": {
    "addr:full":"111 Boul Mercier Amos QC J9T 2P2",
    "addr:housenumber":"111",
    "addr:postcode":"j9t 2p2",
    "addr:street":"Boul Mercier",
    "iso:country":"CA",
    "sg:address":"111 Boul Mercier",
    "sg:city":"Amos",
    "sg:classifiers":[
        {
            "category":"Home & Garden",
            "subcategory":"Building Materials",
            "type":"Retail Goods"
        }
    ],
    "sg:phone":"+1 819 732 5377",
    "sg:postcode":"J9T 2P2",
    "sg:province":"QC",
    "sg:tags":[
        "glass",
        "window",
        "plate"
    ],
    "wof:name":"Vitrerie Pomerleau",
    "wof:placetype":"venue"
},
  "geometry": {"coordinates":[-78.121735,48.572117],"type":"Point"}
}