{
  "type": "Feature",
  "properties": {
    "addr:full":"St-Sauveur-Des-Monts QC J0R 1R0",
    "addr:postcode":"j0r 1r0",
    "iso:country":"CA",
    "sg:city":"St-Sauveur-Des-Monts",
    "sg:classifiers":[
        {
            "category":"Home & Garden",
            "subcategory":"Building Materials",
            "type":"Retail Goods"
        }
    ],
    "sg:phone":"+1 450 227 1213",
    "sg:postcode":"J0R 1R0",
    "sg:province":"QC",
    "sg:tags":[
        "plate",
        "window",
        "glazier"
    ],
    "wof:name":"Vitrier Du Village",
    "wof:placetype":"venue"
},
  "geometry": {"coordinates":[-74.158073,45.893433],"type":"Point"}
}