{
  "type": "Feature",
  "properties": {
    "addr:full":"252 1E Av O Amos QC J9T 1V2",
    "addr:housenumber":"252",
    "addr:postcode":"j9t 1v2",
    "addr:street":"1E Av O Amos",
    "iso:country":"CA",
    "sg:address":"252 1E Av O",
    "sg:city":"Amos",
    "sg:classifiers":[
        {
            "category":"Personal",
            "subcategory":"Barber",
            "type":"Services"
        }
    ],
    "sg:phone":"+1 819 732 2040",
    "sg:postcode":"J9T 1V2",
    "sg:province":"QC",
    "wof:name":"Salon Astragal",
    "wof:placetype":"venue"
},
  "geometry": {"coordinates":[-78.109604,48.571785],"type":"Point"}
}