{
  "type": "Feature",
  "properties": {
    "addr:full":"1353 Aster St Pemberton BC V0N 2L0",
    "addr:housenumber":"1353",
    "addr:postcode":"v0n 2l0",
    "addr:street":"Aster St",
    "iso:country":"CA",
    "sg:address":"1353 Aster St",
    "sg:city":"Pemberton",
    "sg:classifiers":[
        {
            "category":"Health Services",
            "subcategory":"Doctor",
            "type":"Services"
        }
    ],
    "sg:phone":"+1 604 894 6365",
    "sg:postcode":"V0N 2L0",
    "sg:province":"BC",
    "sg:tags":[
        "physician",
        "surgeon"
    ],
    "wof:name":"Dr Anthony Ho Chen Inc",
    "wof:placetype":"venue"
},
  "geometry": {"coordinates":[-122.809310913,50.3213386536],"type":"Point"}
}