{
  "type": "Feature",
  "properties": {
    "addr:full":"2200 Bristol Cir Oakville ON L6H 5R3",
    "addr:housenumber":"2200",
    "addr:postcode":"l6h 5r3",
    "addr:street":"Bristol Cir",
    "iso:country":"CA",
    "sg:address":"2200 Bristol Cir",
    "sg:city":"Oakville",
    "sg:classifiers":[
        {
            "category":"Wholesale",
            "subcategory":"Electrical",
            "type":"Manufacturing & Wholesale Goods"
        }
    ],
    "sg:phone":"+1 905 829 2000",
    "sg:postcode":"L6H 5R3",
    "sg:province":"ON",
    "sg:tags":[
        "control"
    ],
    "wof:name":"Davis Controls Ltd",
    "wof:placetype":"venue"
},
  "geometry": {"coordinates":[-79.6716918945,43.5134468079],"type":"Point"}
}