{
  "type": "Feature",
  "properties": {
    "addr:full":"Main St Compeer AB T0C 1A0",
    "addr:postcode":"t0c 1a0",
    "addr:street":"Main St",
    "iso:country":"CA",
    "sg:address":"Main St",
    "sg:city":"Compeer",
    "sg:classifiers":[
        {
            "category":"Travel",
            "subcategory":"Hotels & Motels",
            "type":"Entertainment"
        }
    ],
    "sg:phone":"+1 403 552 3899",
    "sg:postcode":"T0C 1A0",
    "sg:province":"AB",
    "wof:name":"Compeer Hotel",
    "wof:placetype":"venue"
},
  "geometry": {"coordinates":[-110.01224499999999,51.859627],"type":"Point"}
}