{
  "type": "Feature",
  "properties": {
    "addr:full":"562 Victoria St E # 2 Alliston ON L9R 1K1",
    "addr:housenumber":"562",
    "addr:postcode":"l9r 1k1",
    "addr:street":"Victoria St E # 2 Alliston",
    "iso:country":"CA",
    "sg:address":"562 Victoria St E # 2",
    "sg:city":"Alliston",
    "sg:classifiers":[
        {
            "category":"Home & Garden",
            "subcategory":"Carpets & Floor Coverings",
            "type":"Retail Goods"
        }
    ],
    "sg:phone":"+1 705 435 4945",
    "sg:postcode":"L9R 1K1",
    "sg:province":"ON",
    "sg:tags":[
        "material",
        "rug"
    ],
    "wof:name":"Wilton Floor & Wall Coverings",
    "wof:placetype":"venue"
},
  "geometry": {"coordinates":[-79.8388748169,44.1604881287],"type":"Point"}
}