{
  "type": "Feature",
  "properties": {
    "addr:full":"111 Prouse St Kelvington SK S0A 1W0",
    "addr:housenumber":"111",
    "addr:postcode":"s0a 1w0",
    "addr:street":"Prouse St",
    "iso:country":"CA",
    "sg:address":"111 Prouse St",
    "sg:city":"Kelvington",
    "sg:classifiers":[
        {
            "category":"Retail",
            "subcategory":"Funeral Services",
            "type":"Services"
        }
    ],
    "sg:phone":"+1 306 327 4477",
    "sg:postcode":"S0A 1W0",
    "sg:province":"SK",
    "sg:tags":[
        "director"
    ],
    "wof:name":"Narfason's Funeral Chapel",
    "wof:placetype":"venue"
},
  "geometry": {"coordinates":[-103.52950300000001,52.164566],"type":"Point"}
}