{
  "type": "Feature",
  "properties": {
    "addr:full":"173 James St Truro NS B2N 2Z9",
    "addr:housenumber":"173",
    "addr:postcode":"b2n 2z9",
    "addr:street":"James St",
    "iso:country":"CA",
    "sg:address":"173 James St",
    "sg:city":"Truro",
    "sg:classifiers":[
        {
            "category":"Cinema",
            "subcategory":"Movie Rental",
            "type":"Entertainment"
        }
    ],
    "sg:phone":"+1 902 895 3940",
    "sg:postcode":"B2N 2Z9",
    "sg:province":"NS",
    "sg:tags":[
        "leasing",
        "video",
        "disc",
        "tape"
    ],
    "wof:name":"Treaty Convenience 2",
    "wof:placetype":"venue"
},
  "geometry": {"coordinates":[-63.298225,45.349735],"type":"Point"}
}