{
  "type": "Feature",
  "properties": {
    "addr:full":"296 Rutherford Rd S Brampton ON L6W 3K7",
    "addr:housenumber":"296",
    "addr:postcode":"l6w 3k7",
    "addr:street":"Rutherford Rd S",
    "iso:country":"CA",
    "sg:address":"296 Rutherford Rd S",
    "sg:city":"Brampton",
    "sg:classifiers":[
        {
            "category":"Retail",
            "subcategory":"Auto Repair",
            "type":"Services"
        }
    ],
    "sg:phone":"+1 905 453 8142",
    "sg:postcode":"L6W 3K7",
    "sg:province":"ON",
    "sg:tags":[
        "body",
        "automobile",
        "painting"
    ],
    "wof:name":"Kennedy Auto Collision",
    "wof:placetype":"venue"
},
  "geometry": {"coordinates":[-79.72051999999999,43.683105],"type":"Point"}
}