{
  "type": "Feature",
  "properties": {
    "iso:country":"CA",
    "sg:address":"296 Rutherford Rd S",
    "sg:city":"Brampton",
    "sg:classifiers":[
        {
            "category":"Retail",
            "subcategory":"Auto Repair",
            "type":"Services"
        }
    ],
    "sg:phone":"+1 905 453 8142",
    "sg:postcode":"L6W 3K7",
    "sg:province":"ON",
    "sg:tags":[
        "body",
        "automobile",
        "painting"
    ],
    "wof:name":"Kennedy Auto Collision",
    "wof:placetype":"venue"
},
  "geometry": {"coordinates":[-79.72052,43.683105],"type":"Point"}
}