{
  "type": "Feature",
  "properties": {
    "addr:full":"45820 Wellington Ave Chilliwack BC V2P 2C9",
    "addr:housenumber":"45820",
    "addr:postcode":"v2p 2c9",
    "addr:street":"Wellington Ave",
    "iso:country":"CA",
    "sg:address":"45820 Wellington Ave",
    "sg:city":"Chilliwack",
    "sg:classifiers":[
        {
            "category":"Banks & Credit Unions",
            "subcategory":"Bank",
            "type":"Services"
        }
    ],
    "sg:phone":"+1 604 792 3301",
    "sg:postcode":"V2P 2C9",
    "sg:province":"BC",
    "sg:tags":[
        "loan"
    ],
    "wof:name":"Prospera Credit Union",
    "wof:placetype":"venue"
},
  "geometry": {"coordinates":[-121.956543,49.172188],"type":"Point"}
}