{
  "type": "Feature",
  "properties": {
    "addr:full":"PO Box 360 STN Main Whitecourt AB T7S 1N5",
    "addr:housenumber":"po",
    "addr:postcode":"t7s 1n5",
    "addr:street":"Box 360 Stn Main",
    "iso:country":"CA",
    "sg:address":"PO Box 360 STN Main",
    "sg:city":"Whitecourt",
    "sg:classifiers":[
        {
            "category":"Freight",
            "type":"Transportation"
        }
    ],
    "sg:phone":"+1 780 778 4615",
    "sg:postcode":"T7S 1N5",
    "sg:province":"AB",
    "sg:tags":[
        "field",
        "oil"
    ],
    "wof:name":"K-Lynn Trucking Ltd",
    "wof:placetype":"venue"
},
  "geometry": {"coordinates":[-115.70787811300001,54.1394348145],"type":"Point"}
}