{
  "type": "Feature",
  "properties": {
    "addr:full":"4921 52 St Camrose AB T4V 1V4",
    "addr:housenumber":"4921",
    "addr:postcode":"t4v 1v4",
    "addr:street":"52 St",
    "iso:country":"CA",
    "sg:address":"4921 52 St",
    "sg:city":"Camrose",
    "sg:classifiers":[
        {
            "category":"Organizations",
            "subcategory":"Non-profit Organization",
            "type":"Services"
        }
    ],
    "sg:phone":"+1 780 672 4677",
    "sg:postcode":"T4V 1V4",
    "sg:province":"AB",
    "sg:tags":[
        "disability"
    ],
    "wof:name":"Citizen Advocacy Society",
    "wof:placetype":"venue"
},
  "geometry": {"coordinates":[-112.827934265,53.0213775635],"type":"Point"}
}