{
  "type": "Feature",
  "properties": {
    "addr:full":"Fox Creek AB T0H 1P0",
    "addr:postcode":"t0h 1p0",
    "iso:country":"CA",
    "sg:city":"Fox Creek",
    "sg:classifiers":[
        {
            "category":"Food & Beverages",
            "subcategory":"Liquor & Beverages",
            "type":"Retail Goods"
        }
    ],
    "sg:phone":"+1 780 622 2602",
    "sg:postcode":"T0H 1P0",
    "sg:province":"AB",
    "sg:tags":[
        "store"
    ],
    "wof:name":"Oasis Liquor Outlet",
    "wof:placetype":"venue"
},
  "geometry": {"coordinates":[-116.805381775,54.3950843811],"type":"Point"}
}