{
  "type": "Feature",
  "properties": {
    "addr:full":"5920 98 St NW Edmonton AB T6E 3L5",
    "addr:housenumber":"5920",
    "addr:postcode":"t6e 3l5",
    "addr:street":"98 St Nw",
    "iso:country":"CA",
    "sg:address":"5920 98 St NW",
    "sg:city":"Edmonton",
    "sg:classifiers":[
        {
            "category":"Freight",
            "type":"Transportation"
        }
    ],
    "sg:phone":"+1 780 430 8863",
    "sg:postcode":"T6E 3L5",
    "sg:province":"AB",
    "sg:tags":[
        "trucking"
    ],
    "wof:name":"Usf Reddaway Inc",
    "wof:placetype":"venue"
},
  "geometry": {"coordinates":[-113.483284,53.494961],"type":"Point"}
}