{
  "type": "Feature",
  "properties": {
    "iso:country":"CA",
    "sg:address":"425 Queen St W",
    "sg:city":"Toronto",
    "sg:classifiers":[
        {
            "category":"Real Estate",
            "subcategory":"Real Estate Agent",
            "type":"Services"
        }
    ],
    "sg:phone":"+1 416 597 9961",
    "sg:postcode":"M5V 2A5",
    "sg:province":"ON",
    "wof:name":"Queen & Spadina Business Ctr",
    "wof:placetype":"venue"
},
  "geometry": {"coordinates":[-79.3954086304,43.6487998962],"type":"Point"}
}