{
  "type": "Feature",
  "properties": {
    "addr:full":"145 Springer Chapais QC G0W 1H0",
    "addr:housenumber":"145",
    "addr:postcode":"g0w 1h0",
    "addr:street":"Springer",
    "iso:country":"CA",
    "sg:address":"145 Springer",
    "sg:city":"Chapais",
    "sg:classifiers":[
        {
            "category":"Professional",
            "subcategory":"Management & Consulting",
            "type":"Services"
        }
    ],
    "sg:phone":"+1 418 745 3530",
    "sg:postcode":"G0W 1H0",
    "sg:province":"QC",
    "sg:tags":[
        "consultant",
        "business"
    ],
    "wof:name":"Sadc Chibourgamau Chapais",
    "wof:placetype":"venue"
},
  "geometry": {"coordinates":[-74.85414900000001,49.781815],"type":"Point"}
}