{
  "type": "Feature",
  "properties": {
    "iso:country":"CA",
    "sg:address":"433 Rue Jarry O",
    "sg:city":"Montreal",
    "sg:classifiers":[
        {
            "category":"Building & Trades",
            "subcategory":"Construction",
            "type":"Services"
        }
    ],
    "sg:phone":"+1 514 273 8234",
    "sg:postcode":"H3N 1E7",
    "sg:province":"QC",
    "sg:tags":[
        "painter"
    ],
    "wof:name":"Eric Painting Svc",
    "wof:placetype":"venue"
},
  "geometry": {"coordinates":[-73.6292266846,45.5428771973],"type":"Point"}
}