{
  "type": "Feature",
  "properties": {
    "addr:full":"24 Chickadee Dr Whitecourt AB T7S 1G3",
    "addr:housenumber":"24",
    "addr:postcode":"t7s 1g3",
    "addr:street":"Chickadee Dr",
    "iso:country":"CA",
    "sg:address":"24 Chickadee Dr",
    "sg:city":"Whitecourt",
    "sg:classifiers":[
        {
            "category":"Mining & Drilling",
            "type":"Manufacturing & Wholesale Goods"
        }
    ],
    "sg:phone":"+1 780 706 2758",
    "sg:postcode":"T7S 1G3",
    "sg:province":"AB",
    "sg:tags":[
        "field",
        "oil"
    ],
    "wof:name":"C M Skuban Battery Operators",
    "wof:placetype":"venue"
},
  "geometry": {"coordinates":[-115.678757,54.126316],"type":"Point"}
}