{
  "type": "Feature",
  "properties": {
    "addr:full":"1039 Suncastle Dr SE Calgary AB T2X 2Z1",
    "addr:housenumber":"1039",
    "addr:postcode":"t2x 2z1",
    "addr:street":"Suncastle Dr Se",
    "iso:country":"CA",
    "sg:address":"1039 Suncastle Dr SE",
    "sg:city":"Calgary",
    "sg:classifiers":[
        {
            "category":"Education",
            "subcategory":"School",
            "type":"Public Place"
        }
    ],
    "sg:phone":"+1 403 777 6400",
    "sg:postcode":"T2X 2Z1",
    "sg:province":"AB",
    "wof:name":"Fish Creek Elementary School",
    "wof:placetype":"venue"
},
  "geometry": {"coordinates":[-114.03273,50.902126],"type":"Point"}
}