{
  "type": "Feature",
  "properties": {
    "addr:full":"35 Prince Charles Dr St Catharines ON L2N 3Y8",
    "addr:housenumber":"35",
    "addr:postcode":"l2n 3y8",
    "addr:street":"Prince Charles Dr",
    "iso:country":"CA",
    "sg:address":"35 Prince Charles Dr",
    "sg:city":"St Catharines",
    "sg:classifiers":[
        {
            "category":"Education",
            "subcategory":"School",
            "type":"Public Place"
        }
    ],
    "sg:phone":"+1 905 937 4608",
    "sg:postcode":"L2N 3Y8",
    "sg:province":"ON",
    "wof:name":"Ecole Elementaire L'Heritage",
    "wof:placetype":"venue"
},
  "geometry": {"coordinates":[-79.24842099999999,43.195477],"type":"Point"}
}