{
  "type": "Feature",
  "properties": {
    "addr:full":"7343 Buller Ave Burnaby BC V5J 4S6",
    "addr:housenumber":"7343",
    "addr:postcode":"v5j 4s6",
    "addr:street":"Buller Ave",
    "iso:country":"CA",
    "sg:address":"7343 Buller Ave",
    "sg:city":"Burnaby",
    "sg:classifiers":[
        {
            "category":"Retail",
            "subcategory":"Repair Shop",
            "type":"Services"
        }
    ],
    "sg:phone":"+1 604 436 0550",
    "sg:postcode":"V5J 4S6",
    "sg:province":"BC",
    "sg:tags":[
        "plating",
        "hydraulic"
    ],
    "wof:name":"Cdm Machine Shop & Planting",
    "wof:placetype":"venue"
},
  "geometry": {"coordinates":[-122.97772979699999,49.2169418335],"type":"Point"}
}