{
  "type": "Feature",
  "properties": {
    "iso:country":"CA",
    "sg:address":"130 Ioco Rd",
    "sg:city":"Port Moody",
    "sg:classifiers":[
        {
            "category":"Home & Garden",
            "subcategory":"Building Materials",
            "type":"Retail Goods"
        }
    ],
    "sg:phone":"+1 604 461 6440",
    "sg:postcode":"V3H 2V4",
    "sg:province":"BC",
    "sg:tags":[
        "lumber"
    ],
    "wof:name":"Adanac Lumber",
    "wof:placetype":"venue"
},
  "geometry": {"coordinates":[-122.827392578,49.2780303955],"type":"Point"}
}