{
  "type": "Feature",
  "properties": {
    "addr:full":"2151 Rte Marie-Victorin Varennes QC J3X 1R4",
    "addr:housenumber":"2151",
    "addr:postcode":"j3x 1r4",
    "addr:street":"Rte Marie-Victorin",
    "iso:country":"CA",
    "sg:address":"2151 Rte Marie-Victorin",
    "sg:city":"Varennes",
    "sg:classifiers":[
        {
            "category":"Home & Garden",
            "subcategory":"Furniture",
            "type":"Retail Goods"
        }
    ],
    "sg:phone":"+1 450 652 4611",
    "sg:postcode":"J3X 1R4",
    "sg:province":"QC",
    "wof:name":"Ameublement Daviau & Racine",
    "wof:placetype":"venue"
},
  "geometry": {"coordinates":[-73.437355,45.680824],"type":"Point"}
}