{
  "type": "Feature",
  "properties": {
    "iso:country":"CA",
    "sg:address":"3255 Boul Cremazie E",
    "sg:city":"Montreal",
    "sg:classifiers":[
        {
            "category":"Retail",
            "subcategory":"Auto Repair",
            "type":"Services"
        }
    ],
    "sg:phone":"+1 514 725 5900",
    "sg:postcode":"H1Z 2H7",
    "sg:province":"QC",
    "sg:tags":[
        "repairing",
        "automobile"
    ],
    "wof:name":"Transmission Cr",
    "wof:placetype":"venue"
},
  "geometry": {"coordinates":[-73.6066207886,45.5633506775],"type":"Point"}
}