{
  "type": "Feature",
  "properties": {
    "iso:country":"CA",
    "sg:city":"Powell River",
    "sg:classifiers":[
        {
            "category":"Travel",
            "subcategory":"Travel Agent",
            "type":"Entertainment"
        }
    ],
    "sg:phone":"+1 604 485 2828",
    "sg:postcode":"V8A 5K9",
    "sg:province":"BC",
    "sg:tags":[
        "agency",
        "bureau"
    ],
    "wof:name":"Sun Coast Travel Ltd",
    "wof:placetype":"venue"
},
  "geometry": {"coordinates":[-124.518409729,49.8463439941],"type":"Point"}
}