{
  "type": "Feature",
  "properties": {
    "addr:full":"65 Water St Campbellton NB E3N 1A9",
    "addr:housenumber":"65",
    "addr:postcode":"e3n 1a9",
    "addr:street":"Water St",
    "iso:country":"CA",
    "sg:address":"65 Water St",
    "sg:city":"Campbellton",
    "sg:classifiers":[
        {
            "category":"Restaurant",
            "type":"Food & Drink"
        }
    ],
    "sg:phone":"+1 506 753 7744",
    "sg:postcode":"E3N 1A9",
    "sg:province":"NB",
    "wof:name":"Something Else Restaurant",
    "wof:placetype":"venue"
},
  "geometry": {"coordinates":[-66.671227,48.008762],"type":"Point"}
}