{
  "type": "Feature",
  "properties": {
    "addr:full":"913 14 St SE Calgary AB T2G 3K2",
    "addr:housenumber":"14",
    "addr:postcode":"t2g 3k2",
    "addr:street":"913;St Se",
    "iso:country":"CA",
    "sg:address":"913 14 St SE",
    "sg:city":"Calgary",
    "sg:classifiers":[
        {
            "category":"Professional",
            "subcategory":"Lawyer & Legal Services",
            "type":"Services"
        }
    ],
    "sg:phone":"+1 403 266 6464",
    "sg:postcode":"T2G 3K2",
    "sg:province":"AB",
    "sg:tags":[
        "planning",
        "estate"
    ],
    "wof:name":"Mac Millan Estate Planning",
    "wof:placetype":"venue"
},
  "geometry": {"coordinates":[-114.029319763,51.0390586853],"type":"Point"}
}