{
  "type": "Feature",
  "properties": {
    "iso:country":"CA",
    "sg:address":"2901 43 Ave",
    "sg:city":"Vernon",
    "sg:classifiers":[
        {
            "category":"Retail",
            "subcategory":"Auto Repair",
            "type":"Services"
        }
    ],
    "sg:phone":"+1 250 542 5344",
    "sg:postcode":"V1T 3L4",
    "sg:province":"BC",
    "sg:tags":[
        "automobile",
        "electric"
    ],
    "wof:name":"Roko Service Ltd",
    "wof:placetype":"venue"
},
  "geometry": {"coordinates":[-119.270141602,50.2748756409],"type":"Point"}
}