{
  "type": "Feature",
  "properties": {
    "addr:full":"40 Broadway Orangeville ON L9W 1J4",
    "addr:housenumber":"40",
    "addr:postcode":"l9w 1j4",
    "addr:street":"Broadway",
    "iso:country":"CA",
    "sg:address":"40 Broadway",
    "sg:city":"Orangeville",
    "sg:classifiers":[
        {
            "category":"Shopping",
            "subcategory":"Pharmacy",
            "type":"Retail Goods"
        }
    ],
    "sg:phone":"+1 519 941 2900",
    "sg:postcode":"L9W 1J4",
    "sg:province":"ON",
    "wof:name":"Shoppers Drug Mart",
    "wof:placetype":"venue"
},
  "geometry": {"coordinates":[-80.08786000000001,43.921204],"type":"Point"}
}