{
  "type": "Feature",
  "properties": {
    "addr:full":"North York ON M2N 6X4",
    "addr:postcode":"m2n 6x4",
    "iso:country":"CA",
    "sg:city":"North York",
    "sg:classifiers":[
        {
            "category":"Restaurant",
            "type":"Food & Drink"
        }
    ],
    "sg:phone":"+1 416 227 1888",
    "sg:postcode":"M2N 6X4",
    "sg:province":"ON",
    "sg:tags":[
        "shop",
        "coffee",
        "cafe"
    ],
    "wof:name":"Bellissimo Cafe Coffee",
    "wof:placetype":"venue"
},
  "geometry": {"coordinates":[-79.41475699999999,43.77597],"type":"Point"}
}