{
  "type": "Feature",
  "properties": {
    "iso:country":"CA",
    "sg:address":"370 Southport Blvd",
    "sg:city":"Winnipeg",
    "sg:classifiers":[
        {
            "category":"Recreation",
            "type":"Entertainment"
        }
    ],
    "sg:phone":"+1 204 837 3766",
    "sg:postcode":"R3P 0S9",
    "sg:province":"MB",
    "sg:tags":[
        "tennis",
        "court"
    ],
    "wof:name":"Tuxedo Tennis Club",
    "wof:placetype":"venue"
},
  "geometry": {"coordinates":[-97.214706,49.864998],"type":"Point"}
}