{
  "type": "Feature",
  "properties": {
    "addr:full":"Calgary AB T1Y 6Y7",
    "addr:postcode":"t1y 6y7",
    "iso:country":"CA",
    "sg:city":"Calgary",
    "sg:classifiers":[
        {
            "category":"Insurance",
            "subcategory":"Insurance Agent",
            "type":"Services"
        }
    ],
    "sg:phone":"+1 403 285 3200",
    "sg:postcode":"T1Y 6Y7",
    "sg:province":"AB",
    "wof:name":"John Beal Insurance",
    "wof:placetype":"venue"
},
  "geometry": {"coordinates":[-113.934845,51.071194],"type":"Point"}
}