{
  "type": "Feature",
  "properties": {
    "addr:full":"78 Balsam St Copper Cliff ON P0M 1N0",
    "addr:housenumber":"78",
    "addr:postcode":"p0m 1n0",
    "addr:street":"Balsam St",
    "iso:country":"CA",
    "sg:address":"78 Balsam St",
    "sg:city":"Copper Cliff",
    "sg:classifiers":[
        {
            "category":"Organizations",
            "subcategory":"Religious Organization",
            "type":"Services"
        }
    ],
    "sg:phone":"+1 705 682 4683",
    "sg:postcode":"P0M 1N0",
    "sg:province":"ON",
    "sg:tags":[
        "church"
    ],
    "wof:name":"Saint Stanislaus Church",
    "wof:placetype":"venue"
},
  "geometry": {"coordinates":[-81.06384300000001,46.469849],"type":"Point"}
}