{
  "type": "Feature",
  "properties": {
    "addr:full":"30 Rue Du Parc Amqui QC G5J 2L5",
    "addr:housenumber":"30",
    "addr:postcode":"g5j 2l5",
    "addr:street":"Rue Du Parc",
    "iso:country":"CA",
    "sg:address":"30 Rue Du Parc",
    "sg:city":"Amqui",
    "sg:classifiers":[
        {
            "category":"Government",
            "subcategory":"Fire Station",
            "type":"Public Place"
        }
    ],
    "sg:phone":"+1 ",
    "sg:postcode":"G5J 2L5",
    "sg:province":"QC",
    "sg:tags":[
        "department"
    ],
    "wof:name":"Amqui Feu Dept",
    "wof:placetype":"venue"
},
  "geometry": {"coordinates":[-67.4341125488,48.4632835388],"type":"Point"}
}