{
  "type": "Feature",
  "properties": {
    "addr:full":"325 Boul Saint-Martin O Laval QC H7M 1Y7",
    "addr:housenumber":"325",
    "addr:postcode":"h7m 1y7",
    "addr:street":"Boul Saint-Martin O",
    "iso:country":"CA",
    "sg:address":"325 Boul Saint-Martin O",
    "sg:city":"Laval",
    "sg:classifiers":[
        {
            "category":"Shopping",
            "subcategory":"Florist",
            "type":"Retail Goods"
        }
    ],
    "sg:phone":"+1 450 669 3597",
    "sg:postcode":"H7M 1Y7",
    "sg:province":"QC",
    "wof:name":"Au Lotus Noir Laval",
    "wof:placetype":"venue"
},
  "geometry": {"coordinates":[-73.710114,45.57885],"type":"Point"}
}