{
  "type": "Feature",
  "properties": {
    "addr:full":"185 Rue Alexandre Sherbrooke QC J1H 4S8",
    "addr:housenumber":"185",
    "addr:postcode":"j1h 4s8",
    "addr:street":"Rue Alexandre",
    "iso:country":"CA",
    "sg:address":"185 Rue Alexandre",
    "sg:city":"Sherbrooke",
    "sg:classifiers":[
        {
            "category":"Restaurant",
            "type":"Food & Drink"
        }
    ],
    "sg:phone":"+1 819 566 7494",
    "sg:postcode":"J1H 4S8",
    "sg:province":"QC",
    "wof:name":"Restaurant Village Vietnamien",
    "wof:placetype":"venue"
},
  "geometry": {"coordinates":[-71.892647,45.397369],"type":"Point"}
}