{
  "type": "Feature",
  "properties": {
    "addr:full":"2151 Rue Fullum Montreal QC H2K 3P1",
    "addr:housenumber":"2151",
    "addr:postcode":"h2k 3p1",
    "addr:street":"Rue Fullum",
    "iso:country":"CA",
    "sg:address":"2151 Rue Fullum",
    "sg:city":"Montreal",
    "sg:classifiers":[
        {
            "category":"Organizations",
            "subcategory":"Religious Organization",
            "type":"Services"
        }
    ],
    "sg:phone":"+1 514 598 7549",
    "sg:postcode":"H2K 3P1",
    "sg:province":"QC",
    "sg:tags":[
        "church"
    ],
    "wof:name":"Cote Pierre Vicaire Episcopal",
    "wof:placetype":"venue"
},
  "geometry": {"coordinates":[-73.5571060181,45.5315093994],"type":"Point"}
}