{
  "type": "Feature",
  "properties": {
    "addr:full":"Granby QC J2G 5G7",
    "addr:postcode":"j2g 5g7",
    "iso:country":"CA",
    "sg:city":"Granby",
    "sg:classifiers":[
        {
            "category":"Health Services",
            "subcategory":"Doctor",
            "type":"Services"
        }
    ],
    "sg:phone":"+1 450 777 3368",
    "sg:postcode":"J2G 5G7",
    "sg:province":"QC",
    "sg:tags":[
        "dentist"
    ],
    "wof:name":"Kyritsis, Georges DDS",
    "wof:placetype":"venue"
},
  "geometry": {"coordinates":[-72.727554,45.404957],"type":"Point"}
}