{
  "type": "Feature",
  "properties": {
    "addr:full":"999 Canada Pl Vancouver BC V6C 3C1",
    "addr:housenumber":"999",
    "addr:postcode":"v6c 3c1",
    "addr:street":"Canada Pl",
    "iso:country":"CA",
    "sg:address":"999 Canada Pl",
    "sg:city":"Vancouver",
    "sg:classifiers":[
        {
            "category":"Parking",
            "type":"Transportation"
        }
    ],
    "sg:phone":"+1 604 684 2251",
    "sg:postcode":"V6C 3C1",
    "sg:province":"BC",
    "sg:tags":[
        "garage"
    ],
    "wof:name":"Citipark",
    "wof:placetype":"venue"
},
  "geometry": {"coordinates":[-123.114898682,49.2880020142],"type":"Point"}
}