{
  "type": "Feature",
  "properties": {
    "addr:full":"Durham ON N0G 1R0",
    "addr:postcode":"n0g 1r0",
    "iso:country":"CA",
    "sg:city":"Durham",
    "sg:classifiers":[
        {
            "category":"Social Services",
            "type":"Services"
        }
    ],
    "sg:phone":"+1 519 369 6774",
    "sg:postcode":"N0G 1R0",
    "sg:province":"ON",
    "sg:tags":[
        "organization",
        "welfare"
    ],
    "wof:name":"Queens Bush Rural Ministries",
    "wof:placetype":"venue"
},
  "geometry": {"coordinates":[-80.7406463623,44.1489067078],"type":"Point"}
}