{
  "type": "Feature",
  "properties": {
    "iso:country":"CA",
    "sg:city":"Victoria",
    "sg:classifiers":[
        {
            "category":"Arts & Performance",
            "subcategory":"Theater",
            "type":"Entertainment"
        }
    ],
    "sg:phone":"+1 250 382 2670",
    "sg:postcode":"V8T 4P7",
    "sg:province":"BC",
    "sg:tags":[
        "talent",
        "agency",
        "casting"
    ],
    "wof:name":"Barbara Coultish Talent-Model",
    "wof:placetype":"venue"
},
  "geometry": {"coordinates":[-123.367576599,48.4362068176],"type":"Point"}
}