{
  "type": "Feature",
  "properties": {
    "addr:full":"125 Forestry Rd Longlac ON P0T 2A0",
    "addr:housenumber":"125",
    "addr:postcode":"p0t 2a0",
    "addr:street":"Forestry Rd",
    "iso:country":"CA",
    "sg:address":"125 Forestry Rd",
    "sg:city":"Longlac",
    "sg:classifiers":[
        {
            "category":"Personal",
            "subcategory":"Beauty Salon",
            "type":"Services"
        }
    ],
    "sg:phone":"+1 807 876 2635",
    "sg:postcode":"P0T 2A0",
    "sg:province":"ON",
    "wof:name":"Liz's Golden Scissors Unisex",
    "wof:placetype":"venue"
},
  "geometry": {"coordinates":[-86.5350570679,49.7795410156],"type":"Point"}
}