{
  "type": "Feature",
  "properties": {
    "addr:full":"1 Rink Rd Twillingate NL A0G 4M0",
    "addr:housenumber":"1",
    "addr:postcode":"a0g 4m0",
    "addr:street":"Rink Rd Twillingate",
    "iso:country":"CA",
    "sg:address":"1 Rink Rd",
    "sg:city":"Twillingate",
    "sg:classifiers":[
        {
            "category":"Banks & Credit Unions",
            "subcategory":"Bank",
            "type":"Services"
        }
    ],
    "sg:phone":"+1 709 884 2704",
    "sg:postcode":"A0G 4M0",
    "sg:province":"NL",
    "wof:name":"Tri-Island Credit Union",
    "wof:placetype":"venue"
},
  "geometry": {"coordinates":[-54.7759742737,49.6569213867],"type":"Point"}
}