{
  "type": "Feature",
  "properties": {
    "addr:full":"10702 Diefenbaker Dr North Battleford SK S9A 4A8",
    "addr:housenumber":"10702",
    "addr:postcode":"s9a 4a8",
    "addr:street":"Diefenbaker Dr",
    "iso:country":"CA",
    "sg:address":"10702 Diefenbaker Dr",
    "sg:city":"North Battleford",
    "sg:classifiers":[
        {
            "category":"Education",
            "subcategory":"School",
            "type":"Public Place"
        }
    ],
    "sg:phone":"+1 306 937 5100",
    "sg:postcode":"S9A 4A8",
    "sg:province":"SK",
    "wof:name":"North West Regional College",
    "wof:placetype":"venue"
},
  "geometry": {"coordinates":[-108.288002014,52.7825431824],"type":"Point"}
}