{
  "type": "Feature",
  "properties": {
    "addr:full":"11214 153 St NW Edmonton AB T5M 1X6",
    "addr:housenumber":"11214",
    "addr:postcode":"t5m 1x6",
    "addr:street":"153 St Nw",
    "iso:country":"CA",
    "sg:address":"11214 153 St NW",
    "sg:city":"Edmonton",
    "sg:classifiers":[
        {
            "category":"Manufacturing",
            "subcategory":"Rubber & Plastics",
            "type":"Manufacturing & Wholesale Goods"
        }
    ],
    "sg:phone":"+1 780 451 1310",
    "sg:postcode":"T5M 1X6",
    "sg:province":"AB",
    "sg:tags":[
        "mold",
        "maker"
    ],
    "wof:name":"Copperfield Plastic Fab Ltd",
    "wof:placetype":"venue"
},
  "geometry": {"coordinates":[-113.584412,53.561153],"type":"Point"}
}