{
  "type": "Feature",
  "properties": {
    "addr:full":"Vancouver BC V6M 4B9",
    "addr:postcode":"v6m 4b9",
    "iso:country":"CA",
    "sg:city":"Vancouver",
    "sg:classifiers":[
        {
            "category":"Wholesale",
            "subcategory":"Medical Equipment & Supplies",
            "type":"Manufacturing & Wholesale Goods"
        }
    ],
    "sg:phone":"+1 604 266 1354",
    "sg:postcode":"V6M 4B9",
    "sg:province":"BC",
    "sg:tags":[
        "physiotherapy"
    ],
    "wof:name":"Paramedic Instrumentation Ltd",
    "wof:placetype":"venue"
},
  "geometry": {"coordinates":[-123.161041,49.234421],"type":"Point"}
}