{
  "type": "Feature",
  "properties": {
    "iso:country":"CA",
    "sg:address":"1265 Upper James St",
    "sg:city":"Hamilton",
    "sg:classifiers":[
        {
            "category":"Home & Garden",
            "subcategory":"Furniture",
            "type":"Retail Goods"
        }
    ],
    "sg:phone":"+1 905 389 9215",
    "sg:postcode":"L9C 3B3",
    "sg:province":"ON",
    "sg:tags":[
        "equipment",
        "kitchen",
        "door",
        "cabinet"
    ],
    "wof:name":"A M Custom Built Kitchen Cbnts",
    "wof:placetype":"venue"
},
  "geometry": {"coordinates":[-79.8879318237,43.2134933472],"type":"Point"}
}