{
  "type": "Feature",
  "properties": {
    "iso:country":"CA",
    "sg:address":"379 59th Ave E",
    "sg:city":"Vancouver",
    "sg:classifiers":[
        {
            "category":"Wholesale",
            "subcategory":"Jewelry",
            "type":"Manufacturing & Wholesale Goods"
        }
    ],
    "sg:phone":"+1 604 327 1847",
    "sg:postcode":"V5X 1X8",
    "sg:province":"BC",
    "sg:tags":[
        "jeweler"
    ],
    "wof:name":"Gosel Imports CO",
    "wof:placetype":"venue"
},
  "geometry": {"coordinates":[-123.098548889,49.2167930603],"type":"Point"}
}