{
  "type": "Feature",
  "properties": {
    "addr:full":"434 Maybank Ave Toronto ON M6N 3S8",
    "addr:housenumber":"434",
    "addr:postcode":"m6n 3s8",
    "addr:street":"Maybank Ave",
    "iso:country":"CA",
    "sg:address":"434 Maybank Ave",
    "sg:city":"Toronto",
    "sg:classifiers":[
        {
            "category":"Retail",
            "subcategory":"Repair Shop",
            "type":"Services"
        }
    ],
    "sg:phone":"+1 416 604 3900",
    "sg:postcode":"M6N 3S8",
    "sg:province":"ON",
    "sg:tags":[
        "upholsterer"
    ],
    "wof:name":"Rho Interiors & Upholstery",
    "wof:placetype":"venue"
},
  "geometry": {"coordinates":[-79.474007,43.677383],"type":"Point"}
}