{
  "type": "Feature",
  "properties": {
    "iso:country":"CA",
    "sg:address":"304 Av Du Mont-Royal E",
    "sg:city":"Montreal",
    "sg:classifiers":[
        {
            "category":"Shopping",
            "subcategory":"Clothing, Apparel, & Fashions",
            "type":"Retail Goods"
        }
    ],
    "sg:phone":"+1 514 843 5151",
    "sg:postcode":"H2T 1P7",
    "sg:province":"QC",
    "sg:tags":[
        "item",
        "boutique"
    ],
    "wof:name":"Artisan Du Mont-Royal",
    "wof:placetype":"venue"
},
  "geometry": {"coordinates":[-73.5836639404,45.5229263306],"type":"Point"}
}