{
  "type": "Feature",
  "properties": {
    "addr:full":"5 Mitchell Dr Sioux Lookout ON P8T 1C7",
    "addr:housenumber":"5",
    "addr:postcode":"p8t 1c7",
    "addr:street":"Mitchell Dr",
    "iso:country":"CA",
    "sg:address":"5 Mitchell Dr",
    "sg:city":"Sioux Lookout",
    "sg:classifiers":[
        {
            "category":"Building & Trades",
            "subcategory":"Construction",
            "type":"Services"
        }
    ],
    "sg:phone":"+1 807 737 2756",
    "sg:postcode":"P8T 1C7",
    "sg:province":"ON",
    "sg:tags":[
        "contractor"
    ],
    "wof:name":"J R Carpentry",
    "wof:placetype":"venue"
},
  "geometry": {"coordinates":[-91.911118,50.089001],"type":"Point"}
}