{
  "type": "Feature",
  "properties": {
    "addr:full":"Etobicoke ON M9C 1C6",
    "addr:postcode":"m9c 1c6",
    "iso:country":"CA",
    "sg:city":"Etobicoke",
    "sg:classifiers":[
        {
            "category":"Personal",
            "subcategory":"Beauty Salon",
            "type":"Services"
        }
    ],
    "sg:phone":"+1 416 622 1565",
    "sg:postcode":"M9C 1C6",
    "sg:province":"ON",
    "wof:name":"Capricci Hair Salon",
    "wof:placetype":"venue"
},
  "geometry": {"coordinates":[-79.5615692139,43.634513855],"type":"Point"}
}