{
  "type": "Feature",
  "properties": {
    "iso:country":"CA",
    "sg:address":"335 Rue Saint-Donat",
    "sg:city":"Saint-Donat-DE-Montcalm",
    "sg:classifiers":[
        {
            "category":"Personal",
            "subcategory":"Beauty Salon",
            "type":"Services"
        }
    ],
    "sg:phone":"+1 819 424 7902",
    "sg:postcode":"J0T 2C0",
    "sg:province":"QC",
    "wof:name":"Salon Influence Coiffure Enr",
    "wof:placetype":"venue"
},
  "geometry": {"coordinates":[-74.224045,46.318493],"type":"Point"}
}