{
  "type": "Feature",
  "properties": {
    "addr:full":"Abbotsford BC V4X 2N3",
    "addr:postcode":"v4x 2n3",
    "iso:country":"CA",
    "sg:city":"Abbotsford",
    "sg:classifiers":[
        {
            "category":"Home & Garden",
            "subcategory":"Home Furnishings",
            "type":"Retail Goods"
        }
    ],
    "sg:phone":"+1 604 850 0556",
    "sg:postcode":"V4X 2N3",
    "sg:province":"BC",
    "sg:tags":[
        "venetian",
        "blind"
    ],
    "wof:name":"Dennis Scott Blinds/Draperies",
    "wof:placetype":"venue"
},
  "geometry": {"coordinates":[-122.38104199999999,49.049873],"type":"Point"}
}