{
  "type": "Feature",
  "properties": {
    "iso:country":"CA",
    "sg:city":"Delisle",
    "sg:classifiers":[
        {
            "category":"Manufacturing",
            "subcategory":"Furniture",
            "type":"Manufacturing & Wholesale Goods"
        }
    ],
    "sg:phone":"+1 306 493 2446",
    "sg:postcode":"S0L 0P0",
    "sg:province":"SK",
    "sg:tags":[
        "woodworker"
    ],
    "wof:name":"Faludi Wood & Crafts",
    "wof:placetype":"venue"
},
  "geometry": {"coordinates":[-107.134941101,51.9238395691],"type":"Point"}
}