{
  "type": "Feature",
  "properties": {
    "iso:country":"CA",
    "sg:address":"2919 Boul Du Cure-Labelle",
    "sg:city":"Prevost",
    "sg:classifiers":[
        {
            "category":"Wholesale",
            "subcategory":"Farm Supplies",
            "type":"Manufacturing & Wholesale Goods"
        }
    ],
    "sg:phone":"+1 450 224 8630",
    "sg:postcode":"J0R 1T0",
    "sg:province":"QC",
    "sg:tags":[
        "feed"
    ],
    "wof:name":"Nourriture & Accessoires Pour",
    "wof:placetype":"venue"
},
  "geometry": {"coordinates":[-74.070274353,45.8614959717],"type":"Point"}
}