{
  "type": "Feature",
  "properties": {
    "addr:full":"624 1st Ave NW Moose Jaw SK S6H 3M6",
    "addr:housenumber":"624",
    "addr:postcode":"s6h 3m6",
    "addr:street":"1St Ave Nw",
    "iso:country":"CA",
    "sg:address":"624 1st Ave NW",
    "sg:city":"Moose Jaw",
    "sg:classifiers":[
        {
            "category":"Health Services",
            "subcategory":"Chiropractor",
            "type":"Services"
        }
    ],
    "sg:phone":"+1 306 691 4040",
    "sg:postcode":"S6H 3M6",
    "sg:province":"SK",
    "wof:name":"Heidinger, Steven DC",
    "wof:placetype":"venue"
},
  "geometry": {"coordinates":[-105.53750599999999,50.39592],"type":"Point"}
}