{
  "type": "Feature",
  "properties": {
    "addr:full":"7220 Kennedy Rd # 3 Markham ON L3R 7P2",
    "addr:housenumber":"7220",
    "addr:postcode":"l3r 7p2",
    "addr:street":"Kennedy Rd # 3",
    "iso:country":"CA",
    "sg:address":"7220 Kennedy Rd # 3",
    "sg:city":"Markham",
    "sg:classifiers":[
        {
            "category":"Food & Beverages",
            "subcategory":"Specialty",
            "type":"Retail Goods"
        }
    ],
    "sg:phone":"+1 905 513 8850",
    "sg:postcode":"L3R 7P2",
    "sg:province":"ON",
    "sg:tags":[
        "herb"
    ],
    "wof:name":"Shun Lee Herbs CO Ltd",
    "wof:placetype":"venue"
},
  "geometry": {"coordinates":[-79.30670928959999,43.8304138184],"type":"Point"}
}