{
  "type": "Feature",
  "properties": {
    "addr:full":"1110 Robson St Vancouver BC V6E 1B2",
    "addr:housenumber":"1110",
    "addr:postcode":"v6e 1b2",
    "addr:street":"Robson St",
    "iso:country":"CA",
    "sg:address":"1110 Robson St",
    "sg:city":"Vancouver",
    "sg:classifiers":[
        {
            "category":"Shopping",
            "subcategory":"Clothing, Apparel, & Fashions",
            "type":"Retail Goods"
        }
    ],
    "sg:phone":"+1 604 684 3251",
    "sg:postcode":"V6E 1B2",
    "sg:province":"BC",
    "wof:name":"Aritzia Clothing CO",
    "wof:placetype":"venue"
},
  "geometry": {"coordinates":[-123.12539700000001,49.284775],"type":"Point"}
}