{
  "type": "Feature",
  "properties": {
    "iso:country":"CA",
    "sg:address":"393 King Ave",
    "sg:city":"Bathurst",
    "sg:classifiers":[
        {
            "category":"Food & Beverages",
            "subcategory":"Groceries & Convenience Stores",
            "type":"Retail Goods"
        }
    ],
    "sg:phone":"+1 506 548 5368",
    "sg:postcode":"E2A 1P4",
    "sg:province":"NB",
    "wof:name":"Baxter's Convenience & Diner",
    "wof:placetype":"venue"
},
  "geometry": {"coordinates":[-65.6525878906,47.6183128357],"type":"Point"}
}