{
  "type": "Feature",
  "properties": {
    "addr:full":"51 Ontario St S Grand Bend ON N0M 1T0",
    "addr:housenumber":"51",
    "addr:postcode":"n0m 1t0",
    "addr:street":"Ontario St S",
    "iso:country":"CA",
    "sg:address":"51 Ontario St S",
    "sg:city":"Grand Bend",
    "sg:classifiers":[
        {
            "category":"Real Estate",
            "subcategory":"Real Estate Agent",
            "type":"Services"
        }
    ],
    "sg:phone":"+1 519 238 7777",
    "sg:postcode":"N0M 1T0",
    "sg:province":"ON",
    "wof:name":"Andrea Ross Real Estate",
    "wof:placetype":"venue"
},
  "geometry": {"coordinates":[-81.75532531739999,43.3136978149],"type":"Point"}
}