{
  "type": "Feature",
  "properties": {
    "addr:full":"2561 Rue Fleury E Montreal QC H2B 1L7",
    "addr:housenumber":"2561",
    "addr:postcode":"h2b 1l7",
    "addr:street":"Rue Fleury E",
    "iso:country":"CA",
    "sg:address":"2561 Rue Fleury E",
    "sg:city":"Montreal",
    "sg:classifiers":[
        {
            "category":"Food & Beverages",
            "subcategory":"Bakery",
            "type":"Retail Goods"
        }
    ],
    "sg:phone":"+1 514 387 3385",
    "sg:postcode":"H2B 1L7",
    "sg:province":"QC",
    "sg:tags":[
        "baker"
    ],
    "wof:name":"Gourmandise Dopo Cena Inc",
    "wof:placetype":"venue"
},
  "geometry": {"coordinates":[-73.646957,45.576462],"type":"Point"}
}