{
  "type": "Feature",
  "properties": {
    "iso:country":"CA",
    "sg:address":"22 Queen St",
    "sg:city":"Bridgetown",
    "sg:classifiers":[
        {
            "category":"Home & Garden",
            "subcategory":"Building Materials",
            "type":"Retail Goods"
        }
    ],
    "sg:phone":"+1 902 665 4359",
    "sg:postcode":"B0S 1C0",
    "sg:province":"NS",
    "sg:tags":[
        "paint"
    ],
    "wof:name":"Bridgetown Home Hardware",
    "wof:placetype":"venue"
},
  "geometry": {"coordinates":[-65.291306,44.840569],"type":"Point"}
}