{
  "type": "Feature",
  "properties": {
    "addr:full":"Red Deer AB T4N 7A6",
    "addr:postcode":"t4n 7a6",
    "iso:country":"CA",
    "sg:city":"Red Deer",
    "sg:classifiers":[
        {
            "category":"Autos & Motor Vehicles",
            "subcategory":"Auto Supplies",
            "type":"Retail Goods"
        }
    ],
    "sg:phone":"+1 403 340 8956",
    "sg:postcode":"T4N 7A6",
    "sg:province":"AB",
    "sg:tags":[
        "automobile",
        "stereo",
        "radio"
    ],
    "wof:name":"X-Plosive Audio",
    "wof:placetype":"venue"
},
  "geometry": {"coordinates":[-113.805809,52.285965],"type":"Point"}
}