{
  "type": "Feature",
  "properties": {
    "addr:full":"Stettler AB T0C 2L0",
    "addr:postcode":"t0c 2l0",
    "iso:country":"CA",
    "sg:city":"Stettler",
    "sg:classifiers":[
        {
            "category":"Retail",
            "subcategory":"Laundry & Dry Cleaning",
            "type":"Services"
        }
    ],
    "sg:phone":"+1 403 742 3089",
    "sg:postcode":"T0C 2L0",
    "sg:province":"AB",
    "sg:tags":[
        "cleaners",
        "rug",
        "carpet"
    ],
    "wof:name":"Fabri-Zone Cleaning Systems",
    "wof:placetype":"venue"
},
  "geometry": {"coordinates":[-112.71101400000001,52.323536],"type":"Point"}
}