{
  "type": "Feature",
  "properties": {
    "iso:country":"CA",
    "sg:address":"260 Sunset Dr",
    "sg:city":"Regina",
    "sg:classifiers":[
        {
            "category":"Health Services",
            "subcategory":"Nursing And Care Facility",
            "type":"Services"
        }
    ],
    "sg:phone":"+1 306 586 3355",
    "sg:postcode":"S4S 2S3",
    "sg:province":"SK",
    "sg:tags":[
        "home",
        "convalescent"
    ],
    "wof:name":"Extendicare/Sunset",
    "wof:placetype":"venue"
},
  "geometry": {"coordinates":[-104.63597106900001,50.4089584351],"type":"Point"}
}