{
  "type": "Feature",
  "properties": {
    "addr:full":"191 Sheppard Ave E North York ON M2N 3A8",
    "addr:housenumber":"191",
    "addr:postcode":"m2n 3a8",
    "addr:street":"Sheppard Ave E",
    "iso:country":"CA",
    "sg:address":"191 Sheppard Ave E",
    "sg:city":"North York",
    "sg:classifiers":[
        {
            "category":"Restaurant",
            "type":"Food & Drink"
        }
    ],
    "sg:phone":"+1 416 224 0630",
    "sg:postcode":"M2N 3A8",
    "sg:province":"ON",
    "wof:name":"Sushi Fish House",
    "wof:placetype":"venue"
},
  "geometry": {"coordinates":[-79.39928399999999,43.76395],"type":"Point"}
}