{
  "type": "Feature",
  "properties": {
    "iso:country":"CA",
    "sg:address":"162 Rte 230 O",
    "sg:city":"Saint-Pascal",
    "sg:classifiers":[
        {
            "category":"Wholesale",
            "subcategory":"Meat",
            "type":"Manufacturing & Wholesale Goods"
        }
    ],
    "sg:phone":"+1 418 492 2128",
    "sg:postcode":"G0L 3Y0",
    "sg:province":"QC",
    "sg:tags":[
        "packer"
    ],
    "wof:name":"Viandes Kamouraska Inc",
    "wof:placetype":"venue"
},
  "geometry": {"coordinates":[-69.825729,47.518761],"type":"Point"}
}