{
  "type": "Feature",
  "properties": {
    "addr:full":"Clear Lake Rd S Kapuskasing ON P5N 2X7",
    "addr:postcode":"p5n 2x7",
    "addr:street":"Clear Lake Rd",
    "iso:country":"CA",
    "sg:address":"Clear Lake Rd S",
    "sg:city":"Kapuskasing",
    "sg:classifiers":[
        {
            "category":"Manufacturing",
            "subcategory":"Lumber",
            "type":"Manufacturing & Wholesale Goods"
        }
    ],
    "sg:phone":"+1 705 335 2885",
    "sg:postcode":"P5N 2X7",
    "sg:province":"ON",
    "sg:tags":[
        "company",
        "logging"
    ],
    "wof:name":"First Nation Timber Ltd",
    "wof:placetype":"venue"
},
  "geometry": {"coordinates":[-82.361244,49.387363],"type":"Point"}
}