{
  "type": "Feature",
  "properties": {
    "addr:full":"1341 Rue Newton Boucherville QC J4B 5H2",
    "addr:housenumber":"1341",
    "addr:postcode":"j4b 5h2",
    "addr:street":"Rue Newton",
    "iso:country":"CA",
    "sg:address":"1341 Rue Newton",
    "sg:city":"Boucherville",
    "sg:classifiers":[
        {
            "category":"Manufacturing",
            "subcategory":"Tools & Machinery",
            "type":"Manufacturing & Wholesale Goods"
        }
    ],
    "sg:phone":"+1 450 641 0887",
    "sg:postcode":"J4B 5H2",
    "sg:province":"QC",
    "sg:tags":[
        "lubricating",
        "supply",
        "automobile",
        "system",
        "devices",
        "parts"
    ],
    "wof:name":"Coventa Inc",
    "wof:placetype":"venue"
},
  "geometry": {"coordinates":[-73.4259719849,45.5657463074],"type":"Point"}
}