{
  "type": "Feature",
  "properties": {
    "iso:country":"CA",
    "sg:address":"361 Algonquin Blvd W",
    "sg:city":"Timmins",
    "sg:classifiers":[
        {
            "category":"Professional",
            "subcategory":"Computer Services",
            "type":"Services"
        }
    ],
    "sg:phone":"+1 705 264 7064",
    "sg:postcode":"P4N 2S3",
    "sg:province":"ON",
    "sg:tags":[
        "internet"
    ],
    "wof:name":"Vianet Internet Access",
    "wof:placetype":"venue"
},
  "geometry": {"coordinates":[-81.346001,48.475868],"type":"Point"}
}