{
  "type": "Feature",
  "properties": {
    "addr:full":"121 Rue Lafontaine Riviere-Du-Loup QC G5R 3A3",
    "addr:housenumber":"121",
    "addr:postcode":"g5r 3a3",
    "addr:street":"Rue Lafontaine",
    "iso:country":"CA",
    "sg:address":"121 Rue Lafontaine",
    "sg:city":"Riviere-Du-Loup",
    "sg:classifiers":[
        {
            "category":"Organizations",
            "subcategory":"Non-profit Organization",
            "type":"Services"
        }
    ],
    "sg:phone":"+1 418 862 0649",
    "sg:postcode":"G5R 3A3",
    "sg:province":"QC",
    "sg:tags":[
        "charitable",
        "salvage",
        "institution",
        "merchandise",
        "surplus"
    ],
    "wof:name":"Conference St-Vincent",
    "wof:placetype":"venue"
},
  "geometry": {"coordinates":[-69.537933,47.836761],"type":"Point"}
}