{
  "type": "Feature",
  "properties": {
    "addr:full":"5850 Av Victoria Montreal QC H3W 2R5",
    "addr:housenumber":"5850",
    "addr:postcode":"h3w 2r5",
    "addr:street":"Av Victoria",
    "iso:country":"CA",
    "sg:address":"5850 Av Victoria",
    "sg:city":"Montreal",
    "sg:classifiers":[
        {
            "category":"Organizations",
            "subcategory":"Religious Organization",
            "type":"Services"
        }
    ],
    "sg:phone":"+1 514 738 1004",
    "sg:postcode":"H3W 2R5",
    "sg:province":"QC",
    "sg:tags":[
        "church"
    ],
    "wof:name":"Grand Rabbinat Du Quebec",
    "wof:placetype":"venue"
},
  "geometry": {"coordinates":[-73.6353302002,45.4931869507],"type":"Point"}
}