{
  "type": "Feature",
  "properties": {
    "addr:full":"470 2nd Line Hagersville ON N0A 1H0",
    "addr:housenumber":"470",
    "addr:postcode":"n0a 1h0",
    "addr:street":"2Nd Line",
    "iso:country":"CA",
    "sg:address":"470 2nd Line",
    "sg:city":"Hagersville",
    "sg:classifiers":[
        {
            "category":"Home & Garden",
            "subcategory":"Garden Supply",
            "type":"Retail Goods"
        }
    ],
    "sg:phone":"+1 519 445 4828",
    "sg:postcode":"N0A 1H0",
    "sg:province":"ON",
    "sg:tags":[
        "nurseryman"
    ],
    "wof:name":"Sweet Grass Gardens",
    "wof:placetype":"venue"
},
  "geometry": {"coordinates":[-79.99420166020001,42.9817810059],"type":"Point"}
}