{
  "type": "Feature",
  "properties": {
    "iso:country":"CA",
    "sg:address":"316 Barton St E",
    "sg:city":"Hamilton",
    "sg:classifiers":[
        {
            "category":"Autos & Motor Vehicles",
            "subcategory":"Automobile Sales",
            "type":"Retail Goods"
        }
    ],
    "sg:phone":"+1 905 528 7776",
    "sg:postcode":"L8L 2X5",
    "sg:province":"ON",
    "sg:tags":[
        "car",
        "dealer"
    ],
    "wof:name":"A & C Car Sales",
    "wof:placetype":"venue"
},
  "geometry": {"coordinates":[-79.8522720337,43.2606315613],"type":"Point"}
}