{
  "type": "Feature",
  "properties": {
    "addr:full":"20202 Industrial Ave Langley BC V3A 4K7",
    "addr:housenumber":"20202",
    "addr:postcode":"v3a 4k7",
    "addr:street":"Industrial Ave",
    "iso:country":"CA",
    "sg:address":"20202 Industrial Ave",
    "sg:city":"Langley",
    "sg:classifiers":[
        {
            "category":"Building & Trades",
            "subcategory":"Plumbing",
            "type":"Services"
        }
    ],
    "sg:phone":"+1 604 534 5555",
    "sg:postcode":"V3A 4K7",
    "sg:province":"BC",
    "sg:tags":[
        "air",
        "conditioning",
        "contractor",
        "system",
        "heating"
    ],
    "wof:name":"Gandy Installations Ltd",
    "wof:placetype":"venue"
},
  "geometry": {"coordinates":[-122.663856506,49.1080856323],"type":"Point"}
}