{
  "type": "Feature",
  "properties": {
    "addr:full":"Lachine QC H8T 1Y5",
    "addr:postcode":"h8t 1y5",
    "iso:country":"CA",
    "sg:city":"Lachine",
    "sg:classifiers":[
        {
            "category":"Real Estate",
            "subcategory":"Real Estate Operator",
            "type":"Services"
        }
    ],
    "sg:phone":"+1 514 634 2491",
    "sg:postcode":"H8T 1Y5",
    "sg:province":"QC",
    "sg:tags":[
        "apartment"
    ],
    "wof:name":"Sacks Enterprises Inc",
    "wof:placetype":"venue"
},
  "geometry": {"coordinates":[-73.6923675537,45.4421386719],"type":"Point"}
}