{
  "type": "Feature",
  "properties": {
    "addr:full":"555 Lakeside Greens Dr Chestermere AB T1X 1C5",
    "addr:housenumber":"555",
    "addr:postcode":"t1x 1c5",
    "addr:street":"Lakeside Greens Dr",
    "iso:country":"CA",
    "sg:address":"555 Lakeside Greens Dr",
    "sg:city":"Chestermere",
    "sg:classifiers":[
        {
            "category":"Recreation",
            "type":"Entertainment"
        }
    ],
    "sg:phone":"+1 403 569 9111",
    "sg:postcode":"T1X 1C5",
    "sg:province":"AB",
    "sg:tags":[
        "range",
        "practice",
        "golf"
    ],
    "wof:name":"Lakeside Greens Golf",
    "wof:placetype":"venue"
},
  "geometry": {"coordinates":[-113.828460693,51.0383110046],"type":"Point"}
}