{
  "type": "Feature",
  "properties": {
    "addr:full":"2284 Av Notre-Dame Sainte-Foy QC G2E 3G5",
    "addr:housenumber":"2284",
    "addr:postcode":"g2e 3g5",
    "addr:street":"Av Notre-Dame",
    "iso:country":"CA",
    "sg:address":"2284 Av Notre-Dame",
    "sg:city":"Sainte-Foy",
    "sg:classifiers":[
        {
            "category":"Retail",
            "subcategory":"Auto Repair",
            "type":"Services"
        }
    ],
    "sg:phone":"+1 418 872 4252",
    "sg:postcode":"G2E 3G5",
    "sg:province":"QC",
    "sg:tags":[
        "body",
        "automobile",
        "painting"
    ],
    "wof:name":"Auto Bcb Inc",
    "wof:placetype":"venue"
},
  "geometry": {"coordinates":[-71.381485,46.814491],"type":"Point"}
}