{
  "type": "Feature",
  "properties": {
    "addr:full":"18 Rue Sanscartier Gatineau QC J8P 4N5",
    "addr:housenumber":"18",
    "addr:postcode":"j8p 4n5",
    "addr:street":"Rue Sanscartier",
    "iso:country":"CA",
    "sg:address":"18 Rue Sanscartier",
    "sg:city":"Gatineau",
    "sg:classifiers":[
        {
            "category":"Recreation",
            "subcategory":"Marina",
            "type":"Entertainment"
        }
    ],
    "sg:phone":"+1 819 663 2603",
    "sg:postcode":"J8P 4N5",
    "sg:province":"QC",
    "sg:tags":[
        "repairing",
        "boat"
    ],
    "wof:name":"Templeton Marine Expert",
    "wof:placetype":"venue"
},
  "geometry": {"coordinates":[-75.6393203735,45.4781723022],"type":"Point"}
}