{
  "type": "Feature",
  "properties": {
    "addr:full":"1000 Gerrard St E Toronto ON M4M 3G6",
    "addr:housenumber":"1000",
    "addr:postcode":"m4m 3g6",
    "addr:street":"Gerrard St E",
    "iso:country":"CA",
    "sg:address":"1000 Gerrard St E",
    "sg:city":"Toronto",
    "sg:classifiers":[
        {
            "category":"Shopping",
            "subcategory":"Jewelry",
            "type":"Retail Goods"
        }
    ],
    "sg:phone":"+1 416 463 2188",
    "sg:postcode":"M4M 3G6",
    "sg:province":"ON",
    "sg:tags":[
        "jeweler"
    ],
    "wof:name":"Goldy Jewellery & Watches",
    "wof:placetype":"venue"
},
  "geometry": {"coordinates":[-79.33850099999999,43.668716],"type":"Point"}
}