{
  "type": "Feature",
  "properties": {
    "addr:full":"5 Linsmore Cres Toronto ON M4J 4J5",
    "addr:housenumber":"5",
    "addr:postcode":"m4j 4j5",
    "addr:street":"Linsmore Cres",
    "iso:country":"CA",
    "sg:address":"5 Linsmore Cres",
    "sg:city":"Toronto",
    "sg:classifiers":[
        {
            "category":"Retail",
            "subcategory":"Laundry & Dry Cleaning",
            "type":"Services"
        }
    ],
    "sg:phone":"+1 416 461 9498",
    "sg:postcode":"M4J 4J5",
    "sg:province":"ON",
    "sg:tags":[
        "cleaners"
    ],
    "wof:name":"Tilton Dry Cleaners",
    "wof:placetype":"venue"
},
  "geometry": {"coordinates":[-79.329697,43.682362],"type":"Point"}
}