{
  "type": "Feature",
  "properties": {
    "iso:country":"CA",
    "sg:address":"44 Anson Dr",
    "sg:city":"Iroquois Falls",
    "sg:classifiers":[
        {
            "category":"Education",
            "subcategory":"School",
            "type":"Public Place"
        }
    ],
    "sg:phone":"+1 705 258 3921",
    "sg:postcode":"P0K 1E0",
    "sg:province":"ON",
    "wof:name":"Iroquois Falls Secondary Schl",
    "wof:placetype":"venue"
},
  "geometry": {"coordinates":[-80.6825866699,48.7688026428],"type":"Point"}
}