{
  "type": "Feature",
  "properties": {
    "addr:full":"91 Rue D'Aston Victoriaville QC G6P 9N9",
    "addr:housenumber":"91",
    "addr:postcode":"g6p 9n9",
    "addr:street":"Rue D'Aston",
    "iso:country":"CA",
    "sg:address":"91 Rue D'Aston",
    "sg:city":"Victoriaville",
    "sg:classifiers":[
        {
            "category":"Social Services",
            "type":"Services"
        }
    ],
    "sg:phone":"+1 819 752 3320",
    "sg:postcode":"G6P 9N9",
    "sg:province":"QC",
    "sg:tags":[
        "youth",
        "organization",
        "center"
    ],
    "wof:name":"Maison Raymond Roy",
    "wof:placetype":"venue"
},
  "geometry": {"coordinates":[-71.993652,46.046085],"type":"Point"}
}