{
  "type": "Feature",
  "properties": {
    "addr:full":"Whitecourt AB T7S 1N8",
    "addr:postcode":"t7s 1n8",
    "iso:country":"CA",
    "sg:city":"Whitecourt",
    "sg:classifiers":[
        {
            "category":"Wholesale",
            "subcategory":"Machinery & Supplies",
            "type":"Manufacturing & Wholesale Goods"
        }
    ],
    "sg:phone":"+1 780 706 2555",
    "sg:postcode":"T7S 1N8",
    "sg:province":"AB",
    "sg:tags":[
        "equipment",
        "oil",
        "well"
    ],
    "wof:name":"Tryton Tool Svc Ltd",
    "wof:placetype":"venue"
},
  "geometry": {"coordinates":[-115.653893,54.127323],"type":"Point"}
}