{
  "type": "Feature",
  "properties": {
    "addr:full":"4149 98 St NW Edmonton AB T6E 5N5",
    "addr:housenumber":"4149",
    "addr:postcode":"t6e 5n5",
    "addr:street":"98 St Nw",
    "iso:country":"CA",
    "sg:address":"4149 98 St NW",
    "sg:city":"Edmonton",
    "sg:classifiers":[
        {
            "category":"Manufacturing",
            "subcategory":"Printing",
            "type":"Manufacturing & Wholesale Goods"
        }
    ],
    "sg:phone":"+1 780 432 9350",
    "sg:postcode":"T6E 5N5",
    "sg:province":"AB",
    "sg:tags":[
        "cards",
        "post"
    ],
    "wof:name":"Alberta Color Productions",
    "wof:placetype":"venue"
},
  "geometry": {"coordinates":[-113.481956,53.477577],"type":"Point"}
}