{
  "type": "Feature",
  "properties": {
    "addr:full":"421 St Clair St Chatham ON N7L 3K4",
    "addr:housenumber":"421",
    "addr:postcode":"n7l 3k4",
    "addr:street":"St Clair St",
    "iso:country":"CA",
    "sg:address":"421 St Clair St",
    "sg:city":"Chatham",
    "sg:classifiers":[
        {
            "category":"Shopping",
            "type":"Retail Goods"
        }
    ],
    "sg:phone":"+1 519 352 2290",
    "sg:postcode":"N7L 3K4",
    "sg:province":"ON",
    "sg:tags":[
        "pet",
        "shop",
        "supply"
    ],
    "wof:name":"Critter Shop",
    "wof:placetype":"venue"
},
  "geometry": {"coordinates":[-82.20089,42.415966],"type":"Point"}
}