{
  "type": "Feature",
  "properties": {
    "iso:country":"CA",
    "sg:city":"Mackenzie",
    "sg:classifiers":[
        {
            "category":"Building & Trades",
            "subcategory":"Construction",
            "type":"Services"
        }
    ],
    "sg:phone":"+1 250 997 6393",
    "sg:postcode":"V0J 2C0",
    "sg:province":"BC",
    "sg:tags":[
        "general",
        "contractor"
    ],
    "wof:name":"Cant Holdings Ltd",
    "wof:placetype":"venue"
},
  "geometry": {"coordinates":[-123.10446167000001,55.3444023132],"type":"Point"}
}