{
  "type": "Feature",
  "properties": {
    "iso:country":"CA",
    "sg:address":"1599 Sedlescomb Dr",
    "sg:city":"Mississauga",
    "sg:classifiers":[
        {
            "category":"Autos & Motor Vehicles",
            "subcategory":"Motorcycle Sales",
            "type":"Retail Goods"
        }
    ],
    "sg:phone":"+1 905 602 8666",
    "sg:postcode":"L4X 1M4",
    "sg:province":"ON",
    "sg:tags":[
        "scooter"
    ],
    "wof:name":"Motorcycle Store",
    "wof:placetype":"venue"
},
  "geometry": {"coordinates":[-79.5824203491,43.6158790588],"type":"Point"}
}