{
  "type": "Feature",
  "properties": {
    "addr:full":"7290 Gray Ave Burnaby BC V5J 3Z2",
    "addr:housenumber":"7290",
    "addr:postcode":"v5j 3z2",
    "addr:street":"Gray Ave",
    "iso:country":"CA",
    "sg:address":"7290 Gray Ave",
    "sg:city":"Burnaby",
    "sg:classifiers":[
        {
            "category":"Mining & Drilling",
            "type":"Manufacturing & Wholesale Goods"
        }
    ],
    "sg:phone":"+1 604 434 8829",
    "sg:postcode":"V5J 3Z2",
    "sg:province":"BC",
    "sg:tags":[
        "company"
    ],
    "wof:name":"Fancamp Exploration Ltd",
    "wof:placetype":"venue"
},
  "geometry": {"coordinates":[-122.999268,49.217628],"type":"Point"}
}