{
  "type": "Feature",
  "properties": {
    "addr:full":"1410 Alberni Hwy Parksville BC V9P 2C9",
    "addr:housenumber":"1410",
    "addr:postcode":"v9p 2c9",
    "addr:street":"Alberni Hwy",
    "iso:country":"CA",
    "sg:address":"1410 Alberni Hwy",
    "sg:city":"Parksville",
    "sg:classifiers":[
        {
            "category":"Retail",
            "subcategory":"Auto Repair",
            "type":"Services"
        }
    ],
    "sg:phone":"+1 250 248 5964",
    "sg:postcode":"V9P 2C9",
    "sg:province":"BC",
    "sg:tags":[
        "body",
        "automobile",
        "painting"
    ],
    "wof:name":"Can DO Collision",
    "wof:placetype":"venue"
},
  "geometry": {"coordinates":[-124.324532,49.307011],"type":"Point"}
}