{
  "type": "Feature",
  "properties": {
    "addr:full":"1031 Autumnwood Dr # 6 Winnipeg MB R2J 1C6",
    "addr:housenumber":"1031",
    "addr:postcode":"r2j 1c6",
    "addr:street":"Autumnwood Dr # 6",
    "iso:country":"CA",
    "sg:address":"1031 Autumnwood Dr # 6",
    "sg:city":"Winnipeg",
    "sg:classifiers":[
        {
            "category":"Health Services",
            "subcategory":"Doctor",
            "type":"Services"
        }
    ],
    "sg:phone":"+1 204 256 0987",
    "sg:postcode":"R2J 1C6",
    "sg:province":"MB",
    "sg:tags":[
        "dentist"
    ],
    "wof:name":"Winestock, Neil DDS",
    "wof:placetype":"venue"
},
  "geometry": {"coordinates":[-97.078163,49.863605],"type":"Point"}
}