{
  "type": "Feature",
  "properties": {
    "addr:full":"1 Av Holiday # 320 Pointe-Claire QC H9R 5N3",
    "addr:postcode":"h9r 5n3",
    "addr:street":"Av Holiday # 320",
    "iso:country":"CA",
    "sg:address":"1 Av Holiday # 320",
    "sg:city":"Pointe-Claire",
    "sg:classifiers":[
        {
            "category":"Real Estate",
            "subcategory":"Real Estate Agent",
            "type":"Services"
        }
    ],
    "sg:phone":"+1 514 428 0071",
    "sg:postcode":"H9R 5N3",
    "sg:province":"QC",
    "sg:tags":[
        "management"
    ],
    "wof:name":"Investissements Morguard Ltee",
    "wof:placetype":"venue"
},
  "geometry": {"coordinates":[-73.82455400000001,45.460564],"type":"Point"}
}