{
  "type": "Feature",
  "properties": {
    "addr:full":"595 Wall St Winnipeg MB R3G 2T5",
    "addr:housenumber":"595",
    "addr:postcode":"r3g 2t5",
    "addr:street":"Wall St",
    "iso:country":"CA",
    "sg:address":"595 Wall St",
    "sg:city":"Winnipeg",
    "sg:classifiers":[
        {
            "category":"Retail",
            "subcategory":"Auto Repair",
            "type":"Services"
        }
    ],
    "sg:phone":"+1 204 786 8595",
    "sg:postcode":"R3G 2T5",
    "sg:province":"MB",
    "sg:tags":[
        "conversion",
        "van",
        "undercoating",
        "automobile",
        "rustproofing",
        "accessory",
        "truck"
    ],
    "wof:name":"Perma-Guard Rustproofing Inc",
    "wof:placetype":"venue"
},
  "geometry": {"coordinates":[-97.1825637817,49.8855438232],"type":"Point"}
}