{
  "type": "Feature",
  "properties": {
    "addr:full":"Magog QC J1X 2R9",
    "addr:postcode":"j1x 2r9",
    "iso:country":"CA",
    "sg:city":"Magog",
    "sg:classifiers":[
        {
            "category":"Health Services",
            "subcategory":"Health Practitioner",
            "type":"Services"
        }
    ],
    "sg:phone":"+1 819 843 2379",
    "sg:postcode":"J1X 2R9",
    "sg:province":"QC",
    "sg:tags":[
        "physiotherapist"
    ],
    "wof:name":"Clinique DE Physiotherapie",
    "wof:placetype":"venue"
},
  "geometry": {"coordinates":[-72.1442947388,45.267616272],"type":"Point"}
}