{
  "type": "Feature",
  "properties": {
    "addr:full":"369 Portugal Cove Pl St. John's NL A1A 4Y5",
    "addr:housenumber":"369",
    "addr:postcode":"a1a 4y5",
    "addr:street":"Portugal Cove Pl",
    "iso:country":"CA",
    "sg:address":"369 Portugal Cove Pl",
    "sg:city":"St. John's",
    "sg:classifiers":[
        {
            "category":"Retail",
            "subcategory":"Auto Repair",
            "type":"Services"
        }
    ],
    "sg:phone":"+1 709 753 5162",
    "sg:postcode":"A1A 4Y5",
    "sg:province":"NL",
    "sg:tags":[
        "transmission",
        "automobile",
        "repairing"
    ],
    "wof:name":"Mr Transmatic",
    "wof:placetype":"venue"
},
  "geometry": {"coordinates":[-52.8507385254,47.6272201538],"type":"Point"}
}