{
  "type": "Feature",
  "properties": {
    "addr:full":"1162 Dundas St W Mississauga ON L5C 1E1",
    "addr:housenumber":"1162",
    "addr:postcode":"l5c 1e1",
    "addr:street":"Dundas St W",
    "iso:country":"CA",
    "sg:address":"1162 Dundas St W",
    "sg:city":"Mississauga",
    "sg:classifiers":[
        {
            "category":"Restaurant",
            "type":"Food & Drink"
        }
    ],
    "sg:phone":"+1 905 270 3431",
    "sg:postcode":"L5C 1E1",
    "sg:province":"ON",
    "wof:name":"Kfc",
    "wof:placetype":"venue"
},
  "geometry": {"coordinates":[-79.644676,43.555592],"type":"Point"}
}