{
  "type": "Feature",
  "properties": {
    "iso:country":"CA",
    "sg:address":"249 Courtland Ave E",
    "sg:city":"Kitchener",
    "sg:classifiers":[
        {
            "category":"Autos & Motor Vehicles",
            "subcategory":"Automobile Sales",
            "type":"Retail Goods"
        }
    ],
    "sg:phone":"+1 519 579 3488",
    "sg:postcode":"N2G 2V6",
    "sg:province":"ON",
    "sg:tags":[
        "car",
        "dealer"
    ],
    "wof:name":"City Auto Sales",
    "wof:placetype":"venue"
},
  "geometry": {"coordinates":[-80.4842834473,43.4409637451],"type":"Point"}
}