{
  "type": "Feature",
  "properties": {
    "addr:full":"Laval QC H7N 3Y6",
    "addr:postcode":"h7n 3y6",
    "iso:country":"CA",
    "sg:city":"Laval",
    "sg:classifiers":[
        {
            "category":"Home & Garden",
            "subcategory":"Building Materials",
            "type":"Retail Goods"
        }
    ],
    "sg:phone":"+1 450 667 6000",
    "sg:postcode":"H7N 3Y6",
    "sg:province":"QC",
    "wof:name":"Marcel Benoit Ltee",
    "wof:placetype":"venue"
},
  "geometry": {"coordinates":[-73.7059631348,45.5557556152],"type":"Point"}
}