{
  "type": "Feature",
  "properties": {
    "iso:country":"CA",
    "sg:address":"Stone Rd",
    "sg:city":"Callander",
    "sg:classifiers":[
        {
            "category":"Recreation",
            "type":"Entertainment"
        }
    ],
    "sg:phone":"+1 705 752 1068",
    "sg:postcode":"P0H 1H0",
    "sg:province":"ON",
    "sg:tags":[
        "party",
        "guide",
        "fishing"
    ],
    "wof:name":"Murdoch Fishing Charters",
    "wof:placetype":"venue"
},
  "geometry": {"coordinates":[-79.36157989500001,46.1928291321],"type":"Point"}
}