{
  "type": "Feature",
  "properties": {
    "iso:country":"CA",
    "sg:address":"1100 Halcomb Rd",
    "sg:city":"Halcomb",
    "sg:classifiers":[
        {
            "category":"Travel",
            "subcategory":"Campground",
            "type":"Entertainment"
        }
    ],
    "sg:phone":"+1 506 836 7452",
    "sg:postcode":"E9E 1X3",
    "sg:province":"NB",
    "sg:tags":[
        "camp",
        "fishing"
    ],
    "wof:name":"Miramichi Inn",
    "wof:placetype":"venue"
},
  "geometry": {"coordinates":[-65.962600708,46.9249687195],"type":"Point"}
}