{
  "type": "Feature",
  "properties": {
    "addr:full":"582 Rue Lindsay Drummondville QC J2B 1H5",
    "addr:housenumber":"582",
    "addr:postcode":"j2b 1h5",
    "addr:street":"Rue Lindsay",
    "iso:country":"CA",
    "sg:address":"582 Rue Lindsay",
    "sg:city":"Drummondville",
    "sg:classifiers":[
        {
            "category":"Personal",
            "subcategory":"Tanning Parlor",
            "type":"Services"
        }
    ],
    "sg:phone":"+1 819 478 4588",
    "sg:postcode":"J2B 1H5",
    "sg:province":"QC",
    "sg:tags":[
        "salon"
    ],
    "wof:name":"Bronzage Carina",
    "wof:placetype":"venue"
},
  "geometry": {"coordinates":[-72.47858428959999,45.877910614],"type":"Point"}
}