{
  "type": "Feature",
  "properties": {
    "addr:full":"Saskatoon SK S7H 1W5",
    "addr:postcode":"s7h 1w5",
    "iso:country":"CA",
    "sg:city":"Saskatoon",
    "sg:classifiers":[
        {
            "category":"Food & Beverages",
            "subcategory":"Groceries & Convenience Stores",
            "type":"Retail Goods"
        }
    ],
    "sg:phone":"+1 306 343 8388",
    "sg:postcode":"S7H 1W5",
    "sg:province":"SK",
    "wof:name":"Mac's Convenience Stores Ltd",
    "wof:placetype":"venue"
},
  "geometry": {"coordinates":[-106.645844,52.107208],"type":"Point"}
}