{
  "type": "Feature",
  "properties": {
    "iso:country":"CA",
    "sg:address":"1520 Lodestar Rd",
    "sg:city":"North York",
    "sg:classifiers":[
        {
            "category":"Building & Trades",
            "subcategory":"Construction",
            "type":"Services"
        }
    ],
    "sg:phone":"+1 416 630 6986",
    "sg:postcode":"M3J 3C1",
    "sg:province":"ON",
    "sg:tags":[
        "plastering",
        "contractor"
    ],
    "wof:name":"Benvenuto Brothers",
    "wof:placetype":"venue"
},
  "geometry": {"coordinates":[-79.46797943120001,43.7614021301],"type":"Point"}
}