{
  "type": "Feature",
  "properties": {
    "addr:full":"Winnipeg MB R3B 1V8",
    "addr:postcode":"r3b 1v8",
    "iso:country":"CA",
    "sg:city":"Winnipeg",
    "sg:classifiers":[
        {
            "category":"Personal",
            "subcategory":"Beauty Salon",
            "type":"Services"
        }
    ],
    "sg:phone":"+1 204 775 2639",
    "sg:postcode":"R3B 1V8",
    "sg:province":"MB",
    "wof:name":"T Fuong Beauty Salon",
    "wof:placetype":"venue"
},
  "geometry": {"coordinates":[-97.15419,49.896236],"type":"Point"}
}