{
  "type": "Feature",
  "properties": {
    "iso:country":"CA",
    "sg:address":"4188 Av DE Courtrai",
    "sg:city":"Montreal",
    "sg:classifiers":[
        {
            "category":"Home & Garden",
            "subcategory":"Home Furnishings",
            "type":"Retail Goods"
        }
    ],
    "sg:phone":"+1 514 341 3326",
    "sg:postcode":"H3S 1C2",
    "sg:province":"QC",
    "sg:tags":[
        "curtain",
        "made",
        "drapery"
    ],
    "wof:name":"Entreprises Decoraph",
    "wof:placetype":"venue"
},
  "geometry": {"coordinates":[-73.6424026489,45.5006256104],"type":"Point"}
}