{
  "type": "Feature",
  "properties": {
    "addr:full":"Brochet MB R0B 0B0",
    "addr:postcode":"r0b 0b0",
    "iso:country":"CA",
    "sg:city":"Brochet",
    "sg:classifiers":[
        {
            "category":"Building & Trades",
            "subcategory":"Construction",
            "type":"Services"
        }
    ],
    "sg:phone":"+1 204 323 2056",
    "sg:postcode":"R0B 0B0",
    "sg:province":"MB",
    "sg:tags":[
        "general",
        "contractor"
    ],
    "wof:name":"Barren Lands Construction CO",
    "wof:placetype":"venue"
},
  "geometry": {"coordinates":[-101.660797,57.889042],"type":"Point"}
}