{
  "type": "Feature",
  "properties": {
    "addr:full":"225 8 Ave SW Calgary AB T2P 1B7",
    "addr:housenumber":"225",
    "addr:postcode":"t2p 1b7",
    "addr:street":"8 Ave Sw",
    "iso:country":"CA",
    "sg:address":"225 8 Ave SW",
    "sg:city":"Calgary",
    "sg:classifiers":[
        {
            "category":"Shopping",
            "subcategory":"Shoes",
            "type":"Retail Goods"
        }
    ],
    "sg:phone":"+1 403 266 2543",
    "sg:postcode":"T2P 1B7",
    "sg:province":"AB",
    "wof:name":"Arnold Churgin Shoes Ltd",
    "wof:placetype":"venue"
},
  "geometry": {"coordinates":[-114.066230774,51.0454826355],"type":"Point"}
}