{
  "type": "Feature",
  "properties": {
    "addr:full":"667 Sammon Ave East York ON M4C 2E3",
    "addr:housenumber":"667",
    "addr:postcode":"m4c 2e3",
    "addr:street":"Sammon Ave",
    "iso:country":"CA",
    "sg:address":"667 Sammon Ave",
    "sg:city":"East York",
    "sg:classifiers":[
        {
            "category":"Food & Beverages",
            "subcategory":"Groceries & Convenience Stores",
            "type":"Retail Goods"
        }
    ],
    "sg:phone":"+1 416 421 6277",
    "sg:postcode":"M4C 2E3",
    "sg:province":"ON",
    "sg:tags":[
        "grocer"
    ],
    "wof:name":"Sammon Grocery",
    "wof:placetype":"venue"
},
  "geometry": {"coordinates":[-79.322968,43.689312],"type":"Point"}
}