{
  "type": "Feature",
  "properties": {
    "addr:full":"620 Main St Swan River MB R0L 1Z0",
    "addr:housenumber":"620",
    "addr:postcode":"r0l 1z0",
    "addr:street":"Main St",
    "iso:country":"CA",
    "sg:address":"620 Main St",
    "sg:city":"Swan River",
    "sg:classifiers":[
        {
            "category":"Shopping",
            "subcategory":"Discount & Variety Stores",
            "type":"Retail Goods"
        }
    ],
    "sg:phone":"+1 204 734 5770",
    "sg:postcode":"R0L 1Z0",
    "sg:province":"MB",
    "sg:tags":[
        "merchandise",
        "general"
    ],
    "wof:name":"Bargain Shop",
    "wof:placetype":"venue"
},
  "geometry": {"coordinates":[-101.267272949,52.105796814],"type":"Point"}
}