{
  "type": "Feature",
  "properties": {
    "iso:country":"CA",
    "sg:address":"2159 Nantes St",
    "sg:city":"Orleans",
    "sg:classifiers":[
        {
            "category":"Social Services",
            "subcategory":"Child Care",
            "type":"Services"
        }
    ],
    "sg:phone":"+1 613 837 9726",
    "sg:postcode":"K4A 4C4",
    "sg:province":"ON",
    "wof:name":"Garderie Coccinelle DE L'Ecole",
    "wof:placetype":"venue"
},
  "geometry": {"coordinates":[-75.4619293213,45.4590339661],"type":"Point"}
}