{
  "type": "Feature",
  "properties": {
    "iso:country":"CA",
    "sg:city":"London",
    "sg:classifiers":[
        {
            "category":"Professional",
            "subcategory":"Lawyer & Legal Services",
            "type":"Services"
        }
    ],
    "sg:phone":"+1 519 672 6240",
    "sg:postcode":"N6A 5P3",
    "sg:province":"ON",
    "sg:tags":[
        "attorney"
    ],
    "wof:name":"Stambler & Mills",
    "wof:placetype":"venue"
},
  "geometry": {"coordinates":[-81.2519,42.98526],"type":"Point"}
}