{
  "type": "Feature",
  "properties": {
    "addr:full":"241 West St N #300 Orillia ON L3V 5C9",
    "addr:housenumber":"241",
    "addr:postcode":"l3v 5c9",
    "addr:street":"West St N # 300",
    "iso:country":"CA",
    "sg:address":"241 West St N #300",
    "sg:city":"Orillia",
    "sg:classifiers":[
        {
            "category":"Professional",
            "subcategory":"Lawyer & Legal Services",
            "type":"Services"
        }
    ],
    "sg:phone":"+1 705 327 6655",
    "sg:postcode":"L3V 5C9",
    "sg:province":"ON",
    "sg:tags":[
        "attorney"
    ],
    "wof:name":"Hacker Gignac Rice",
    "wof:placetype":"venue"
},
  "geometry": {"coordinates":[-79.425995,44.615673],"type":"Point"}
}