{
  "type": "Feature",
  "properties": {
    "iso:country":"CA",
    "sg:city":"St Catharines",
    "sg:classifiers":[
        {
            "category":"Building & Trades",
            "subcategory":"Construction",
            "type":"Services"
        }
    ],
    "sg:phone":"+1 905 688 6677",
    "sg:postcode":"L2R 2Z6",
    "sg:province":"ON",
    "sg:tags":[
        "steel"
    ],
    "wof:name":"Compusteel Detailing Svc",
    "wof:placetype":"venue"
},
  "geometry": {"coordinates":[-79.232315,43.163521],"type":"Point"}
}