{
  "type": "Feature",
  "properties": {
    "iso:country":"CA",
    "sg:address":"4 Patterson Rd",
    "sg:city":"Barrie",
    "sg:classifiers":[
        {
            "category":"Wholesale",
            "subcategory":"Electrical",
            "type":"Manufacturing & Wholesale Goods"
        }
    ],
    "sg:phone":"+1 705 726 0211",
    "sg:postcode":"L4N 5P4",
    "sg:province":"ON",
    "sg:tags":[
        "equipment",
        "electric",
        "supply"
    ],
    "wof:name":"Nedco",
    "wof:placetype":"venue"
},
  "geometry": {"coordinates":[-79.709106,44.370014],"type":"Point"}
}