{
  "type": "Feature",
  "properties": {
    "iso:country":"CA",
    "sg:address":"194 Rue St-Francois",
    "sg:city":"Edmundston",
    "sg:classifiers":[
        {
            "category":"Insurance",
            "subcategory":"Insurance Agent",
            "type":"Services"
        }
    ],
    "sg:phone":"+1 506 735 5549",
    "sg:postcode":"E3V 1E9",
    "sg:province":"NB",
    "sg:tags":[
        "adjuster"
    ],
    "wof:name":"Cunningham Lindsey Canada Ltd",
    "wof:placetype":"venue"
},
  "geometry": {"coordinates":[-68.3359451294,47.3620185852],"type":"Point"}
}