{
  "type": "Feature",
  "properties": {
    "iso:country":"CA",
    "sg:address":"366 Paddington Rd",
    "sg:city":"Winnipeg",
    "sg:classifiers":[
        {
            "category":"Professional",
            "type":"Services"
        }
    ],
    "sg:phone":"+1 204 471 3155",
    "sg:postcode":"R2N 1R1",
    "sg:province":"MB",
    "sg:tags":[
        "school",
        "establishment"
    ],
    "wof:name":"George Mc Dowell School",
    "wof:placetype":"venue"
},
  "geometry": {"coordinates":[-97.108482,49.810337],"type":"Point"}
}