{
  "type": "Feature",
  "properties": {
    "addr:full":"Oshawa ON L1J 2K5",
    "addr:postcode":"l1j 2k5",
    "iso:country":"CA",
    "sg:city":"Oshawa",
    "sg:classifiers":[
        {
            "category":"Health Services",
            "subcategory":"Doctor",
            "type":"Services"
        }
    ],
    "sg:phone":"+1 905 725 9441",
    "sg:postcode":"L1J 2K5",
    "sg:province":"ON",
    "sg:tags":[
        "dentist"
    ],
    "wof:name":"Hergott, Greg J DDS",
    "wof:placetype":"venue"
},
  "geometry": {"coordinates":[-78.880027771,43.8936843872],"type":"Point"}
}