{
  "type": "Feature",
  "properties": {
    "addr:full":"5284 Rue Jonergin Saint-Hubert QC J3Y 2S2",
    "addr:housenumber":"5284",
    "addr:postcode":"j3y 2s2",
    "addr:street":"Rue Jonergin",
    "iso:country":"CA",
    "sg:address":"5284 Rue Jonergin",
    "sg:city":"Saint-Hubert",
    "sg:classifiers":[
        {
            "category":"Manufacturing",
            "subcategory":"Printing",
            "type":"Manufacturing & Wholesale Goods"
        }
    ],
    "sg:phone":"+1 450 443 4492",
    "sg:postcode":"J3Y 2S2",
    "sg:province":"QC",
    "sg:tags":[
        "printer"
    ],
    "wof:name":"Imprimerie Litho Sm Inc",
    "wof:placetype":"venue"
},
  "geometry": {"coordinates":[-73.4315872192,45.4717521667],"type":"Point"}
}