{
  "type": "Feature",
  "properties": {
    "addr:full":"1 Saskatchewan Cres The Pas MB R9A 1K3",
    "addr:housenumber":"1",
    "addr:postcode":"r9a 1k3",
    "addr:street":"Saskatchewan Cres",
    "iso:country":"CA",
    "sg:address":"1 Saskatchewan Cres",
    "sg:city":"The Pas",
    "sg:classifiers":[
        {
            "category":"Organizations",
            "subcategory":"Religious Organization",
            "type":"Services"
        }
    ],
    "sg:phone":"+1 204 623 2119",
    "sg:postcode":"R9A 1K3",
    "sg:province":"MB",
    "sg:tags":[
        "church"
    ],
    "wof:name":"Anglican Church",
    "wof:placetype":"venue"
},
  "geometry": {"coordinates":[-101.25035099999999,53.813435],"type":"Point"}
}