{
  "type": "Feature",
  "properties": {
    "addr:full":"241 Jacqueline Rd Campbell River BC V9W 7L3",
    "addr:housenumber":"241",
    "addr:postcode":"v9w 7l3",
    "addr:street":"Jacqueline Rd",
    "iso:country":"CA",
    "sg:address":"241 Jacqueline Rd",
    "sg:city":"Campbell River",
    "sg:classifiers":[
        {
            "category":"Retail",
            "subcategory":"Laundry & Dry Cleaning",
            "type":"Services"
        }
    ],
    "sg:phone":"+1 250 286 1966",
    "sg:postcode":"V9W 7L3",
    "sg:province":"BC",
    "sg:tags":[
        "cleaners",
        "rug",
        "carpet"
    ],
    "wof:name":"Rite-Way Carpet & Upholstery",
    "wof:placetype":"venue"
},
  "geometry": {"coordinates":[-125.26823400000001,50.003208],"type":"Point"}
}