{
  "type": "Feature",
  "properties": {
    "addr:full":"5329 Driscoll Dr Manotick ON K4M 1E3",
    "addr:housenumber":"5329",
    "addr:postcode":"k4m 1e3",
    "addr:street":"Driscoll Dr",
    "iso:country":"CA",
    "sg:address":"5329 Driscoll Dr",
    "sg:city":"Manotick",
    "sg:classifiers":[
        {
            "category":"Recreation",
            "type":"Entertainment"
        }
    ],
    "sg:phone":"+1 613 692 5224",
    "sg:postcode":"K4M 1E3",
    "sg:province":"ON",
    "sg:tags":[
        "club",
        "curling"
    ],
    "wof:name":"Ottawa Valley Curling Assn",
    "wof:placetype":"venue"
},
  "geometry": {"coordinates":[-75.69496917719999,45.237071991],"type":"Point"}
}