{
  "type": "Feature",
  "properties": {
    "iso:country":"CA",
    "sg:city":"Thornhill",
    "sg:classifiers":[
        {
            "category":"Education",
            "subcategory":"School",
            "type":"Public Place"
        }
    ],
    "sg:phone":"+1 905 889 4445",
    "sg:postcode":"L4J 8J1",
    "sg:province":"ON",
    "sg:tags":[
        "academic",
        "special"
    ],
    "wof:name":"Next Page Education",
    "wof:placetype":"venue"
},
  "geometry": {"coordinates":[-79.422668,43.807644],"type":"Point"}
}