{
  "type": "Feature",
  "properties": {
    "addr:full":"169 Hamilton River Rd Happy Valley-Goose Bay NL A0P 1C0",
    "addr:housenumber":"169",
    "addr:postcode":"a0p 1c0",
    "addr:street":"Hamilton River Rd",
    "iso:country":"CA",
    "sg:address":"169 Hamilton River Rd",
    "sg:city":"Happy Valley-Goose Bay",
    "sg:classifiers":[
        {
            "category":"Professional",
            "subcategory":"Research",
            "type":"Services"
        }
    ],
    "sg:phone":"+1 709 896 4277",
    "sg:postcode":"A0P 1C0",
    "sg:province":"NL",
    "sg:tags":[
        "asbestos",
        "environmental",
        "ecological"
    ],
    "wof:name":"Pinchin Leblanc Environmental",
    "wof:placetype":"venue"
},
  "geometry": {"coordinates":[-60.376701,53.309303],"type":"Point"}
}