{
  "type": "Feature",
  "properties": {
    "addr:full":"43 Scott St W St Catharines ON L2R 1E1",
    "addr:housenumber":"43",
    "addr:postcode":"l2r 1e1",
    "addr:street":"Scott St W",
    "iso:country":"CA",
    "sg:address":"43 Scott St W",
    "sg:city":"St Catharines",
    "sg:classifiers":[
        {
            "category":"Retail",
            "subcategory":"Auto Repair",
            "type":"Services"
        }
    ],
    "sg:phone":"+1 905 682 8788",
    "sg:postcode":"L2R 1E1",
    "sg:province":"ON",
    "sg:tags":[
        "brake"
    ],
    "wof:name":"Doctor Brake's Cmplte Car Care",
    "wof:placetype":"venue"
},
  "geometry": {"coordinates":[-79.2631607056,43.1768531799],"type":"Point"}
}