{
  "type": "Feature",
  "properties": {
    "iso:country":"CA",
    "sg:address":"161 Rang Saint-Charles",
    "sg:city":"Saint-Thomas",
    "sg:classifiers":[
        {
            "category":"Freight",
            "type":"Transportation"
        }
    ],
    "sg:phone":"+1 450 753 3693",
    "sg:postcode":"J0K 3L0",
    "sg:province":"QC",
    "sg:tags":[
        "trucking"
    ],
    "wof:name":"Viateur Goyet & Sons",
    "wof:placetype":"venue"
},
  "geometry": {"coordinates":[-73.3558959961,46.0060119629],"type":"Point"}
}