{
  "type": "Feature",
  "properties": {
    "addr:full":"869 Av Sainte-Therese Beauport QC G1B 1E8",
    "addr:postcode":"g1b 1e8",
    "addr:street":"869 Av Sainte-Therese",
    "iso:country":"CA",
    "sg:address":"869 Av Sainte-Therese",
    "sg:city":"Beauport",
    "sg:classifiers":[
        {
            "category":"Shopping",
            "subcategory":"Clothing, Apparel, & Fashions",
            "type":"Retail Goods"
        }
    ],
    "sg:phone":"+1 418 821 0400",
    "sg:postcode":"G1B 1E8",
    "sg:province":"QC",
    "sg:tags":[
        "dressmaker"
    ],
    "wof:name":"Atelier DE Couture Suzanne",
    "wof:placetype":"venue"
},
  "geometry": {"coordinates":[-71.19324493409999,46.9058570862],"type":"Point"}
}