{
  "type": "Feature",
  "properties": {
    "addr:full":"1920 Como Lake Ave Coquitlam BC V3J 3R3",
    "addr:housenumber":"1920",
    "addr:postcode":"v3j 3r3",
    "addr:street":"Como Lake Ave",
    "iso:country":"CA",
    "sg:address":"1920 Como Lake Ave",
    "sg:city":"Coquitlam",
    "sg:classifiers":[
        {
            "category":"Food & Beverages",
            "subcategory":"Groceries & Convenience Stores",
            "type":"Retail Goods"
        }
    ],
    "sg:phone":"+1 604 939 3721",
    "sg:postcode":"V3J 3R3",
    "sg:province":"BC",
    "sg:tags":[
        "grocer"
    ],
    "wof:name":"Super Valu",
    "wof:placetype":"venue"
},
  "geometry": {"coordinates":[-122.839806,49.263226],"type":"Point"}
}