{
  "type": "Feature",
  "properties": {
    "addr:full":"Calgary AB T2A 4V1",
    "addr:postcode":"t2a 4v1",
    "iso:country":"CA",
    "sg:city":"Calgary",
    "sg:classifiers":[
        {
            "category":"Personal",
            "subcategory":"Beauty Salon",
            "type":"Services"
        }
    ],
    "sg:phone":"+1 403 204 9700",
    "sg:postcode":"T2A 4V1",
    "sg:province":"AB",
    "wof:name":"Hippy Nails",
    "wof:placetype":"venue"
},
  "geometry": {"coordinates":[-113.957573,51.052822],"type":"Point"}
}