{
  "type": "Feature",
  "properties": {
    "addr:full":"25 Main St Grand Valley ON L0N 1G0",
    "addr:housenumber":"25",
    "addr:postcode":"l0n 1g0",
    "addr:street":"Main St",
    "iso:country":"CA",
    "sg:address":"25 Main St",
    "sg:city":"Grand Valley",
    "sg:classifiers":[
        {
            "category":"Real Estate",
            "subcategory":"Real Estate Agent",
            "type":"Services"
        }
    ],
    "sg:phone":"+1 519 928 5723",
    "sg:postcode":"L0N 1G0",
    "sg:province":"ON",
    "wof:name":"Sally Franco Real Estate",
    "wof:placetype":"venue"
},
  "geometry": {"coordinates":[-80.31531524659999,43.8999557495],"type":"Point"}
}