{
  "type": "Feature",
  "properties": {
    "addr:full":"240 Rue Des Pensees Saint-Raymond QC G3L 2B9",
    "addr:housenumber":"240",
    "addr:postcode":"g3l 2b9",
    "addr:street":"Rue Des Pensees",
    "iso:country":"CA",
    "sg:address":"240 Rue Des Pensees",
    "sg:city":"Saint-Raymond",
    "sg:classifiers":[
        {
            "category":"Building & Trades",
            "subcategory":"Construction",
            "type":"Services"
        }
    ],
    "sg:phone":"+1 418 337 6744",
    "sg:postcode":"G3L 2B9",
    "sg:province":"QC",
    "sg:tags":[
        "repairing",
        "remodeling",
        "contractor"
    ],
    "wof:name":"Specialiste Hardy Enr",
    "wof:placetype":"venue"
},
  "geometry": {"coordinates":[-71.83551,46.866913],"type":"Point"}
}