{
  "type": "Feature",
  "properties": {
    "iso:country":"CA",
    "sg:address":"117 Windsor Dr",
    "sg:city":"Brockville",
    "sg:classifiers":[
        {
            "category":"Organizations",
            "subcategory":"Religious Organization",
            "type":"Services"
        }
    ],
    "sg:phone":"+1 613 345 2050",
    "sg:postcode":"K6V 3H7",
    "sg:province":"ON",
    "sg:tags":[
        "church"
    ],
    "wof:name":"Bethel Christian Reformed Chr",
    "wof:placetype":"venue"
},
  "geometry": {"coordinates":[-75.7065582275,44.6083526611],"type":"Point"}
}