{
  "type": "Feature",
  "properties": {
    "addr:full":"211 Ch Des Cascadelles Piedmont QC J0R 1K0",
    "addr:housenumber":"211",
    "addr:postcode":"j0r 1k0",
    "addr:street":"Ch Des Cascadelles",
    "iso:country":"CA",
    "sg:address":"211 Ch Des Cascadelles",
    "sg:city":"Piedmont",
    "sg:classifiers":[
        {
            "category":"Building & Trades",
            "subcategory":"Electrical",
            "type":"Services"
        }
    ],
    "sg:phone":"+1 450 227 6624",
    "sg:postcode":"J0R 1K0",
    "sg:province":"QC",
    "sg:tags":[
        "electric",
        "contractor"
    ],
    "wof:name":"Benmark Enr",
    "wof:placetype":"venue"
},
  "geometry": {"coordinates":[-74.1129455566,45.8895225525],"type":"Point"}
}