{
  "type": "Feature",
  "properties": {
    "iso:country":"CA",
    "sg:city":"Burlington",
    "sg:classifiers":[
        {
            "category":"Shopping",
            "type":"Retail Goods"
        }
    ],
    "sg:phone":"+1 905 335 8414",
    "sg:postcode":"L7P 3N8",
    "sg:province":"ON",
    "sg:tags":[
        "pet",
        "food",
        "supply"
    ],
    "wof:name":"Pet Valu",
    "wof:placetype":"venue"
},
  "geometry": {"coordinates":[-79.841484,43.35556],"type":"Point"}
}