{
  "type": "Feature",
  "properties": {
    "addr:full":"475 Wyandotte St E Windsor ON N9A 3H8",
    "addr:housenumber":"475",
    "addr:postcode":"n9a 3h8",
    "addr:street":"Wyandotte St E",
    "iso:country":"CA",
    "sg:address":"475 Wyandotte St E",
    "sg:city":"Windsor",
    "sg:classifiers":[
        {
            "category":"Home & Garden",
            "subcategory":"Furniture",
            "type":"Retail Goods"
        }
    ],
    "sg:phone":"+1 519 256 9222",
    "sg:postcode":"N9A 3H8",
    "sg:province":"ON",
    "sg:tags":[
        "futon"
    ],
    "wof:name":"Natural Futon Ctr",
    "wof:placetype":"venue"
},
  "geometry": {"coordinates":[-83.03019,42.316338],"type":"Point"}
}