{
  "type": "Feature",
  "properties": {
    "iso:country":"CA",
    "sg:city":"Montreal",
    "sg:classifiers":[
        {
            "category":"Communications",
            "subcategory":"Film & Video Production",
            "type":"Services"
        }
    ],
    "sg:phone":"+1 514 844 1229",
    "sg:postcode":"H2X 2T7",
    "sg:province":"QC",
    "sg:tags":[
        "audio"
    ],
    "wof:name":"Groupe Mediavision Inc",
    "wof:placetype":"venue"
},
  "geometry": {"coordinates":[-73.57193,45.513798],"type":"Point"}
}