{
  "type": "Feature",
  "properties": {
    "addr:full":"1057 Denman St Vancouver BC V6G 2M7",
    "addr:housenumber":"1057",
    "addr:postcode":"v6g 2m7",
    "addr:street":"Denman St",
    "iso:country":"CA",
    "sg:address":"1057 Denman St",
    "sg:city":"Vancouver",
    "sg:classifiers":[
        {
            "category":"Food & Beverages",
            "subcategory":"Fruits & Vegetables",
            "type":"Retail Goods"
        }
    ],
    "sg:phone":"+1 604 685 9716",
    "sg:postcode":"V6G 2M7",
    "sg:province":"BC",
    "sg:tags":[
        "produce"
    ],
    "wof:name":"C South Vancouver Produce CO",
    "wof:placetype":"venue"
},
  "geometry": {"coordinates":[-123.139938355,49.2886428833],"type":"Point"}
}