{
  "type": "Feature",
  "properties": {
    "addr:full":"Athabasca AB T9S 1E7",
    "addr:postcode":"t9s 1e7",
    "iso:country":"CA",
    "sg:city":"Athabasca",
    "sg:classifiers":[
        {
            "category":"Building & Trades",
            "subcategory":"Construction",
            "type":"Services"
        }
    ],
    "sg:phone":"+1 780 675 2155",
    "sg:postcode":"T9S 1E7",
    "sg:province":"AB",
    "sg:tags":[
        "general",
        "contractor"
    ],
    "wof:name":"Pac Construction",
    "wof:placetype":"venue"
},
  "geometry": {"coordinates":[-113.287598,54.719704],"type":"Point"}
}