{
  "type": "Feature",
  "properties": {
    "addr:full":"5112 54 St Redwater AB T0A 2W0",
    "addr:housenumber":"5112",
    "addr:postcode":"t0a 2w0",
    "addr:street":"54 St",
    "iso:country":"CA",
    "sg:address":"5112 54 St",
    "sg:city":"Redwater",
    "sg:classifiers":[
        {
            "category":"Social Services",
            "type":"Services"
        }
    ],
    "sg:phone":"+1 780 942 3704",
    "sg:postcode":"T0A 2W0",
    "sg:province":"AB",
    "sg:tags":[
        "crisis",
        "center"
    ],
    "wof:name":"Redwater & District Victim Svc",
    "wof:placetype":"venue"
},
  "geometry": {"coordinates":[-113.117935,53.952972],"type":"Point"}
}