{
  "type": "Feature",
  "properties": {
    "addr:full":"500 Av Carignan Boisbriand QC J7G 2M9",
    "addr:housenumber":"500",
    "addr:postcode":"j7g 2m9",
    "addr:street":"Av Carignan",
    "iso:country":"CA",
    "sg:address":"500 Av Carignan",
    "sg:city":"Boisbriand",
    "sg:classifiers":[
        {
            "category":"Retail",
            "subcategory":"Repair Shop",
            "type":"Services"
        }
    ],
    "sg:phone":"+1 450 435 2000",
    "sg:postcode":"J7G 2M9",
    "sg:province":"QC",
    "sg:tags":[
        "lock",
        "locksmith"
    ],
    "wof:name":"Serrurier 2000 Inc",
    "wof:placetype":"venue"
},
  "geometry": {"coordinates":[-73.8238449097,45.6133232117],"type":"Point"}
}