{
  "type": "Feature",
  "properties": {
    "addr:full":"1509 2nd St W Cornwall ON K6J 1J5",
    "addr:housenumber":"1509",
    "addr:postcode":"k6j 1j5",
    "addr:street":"2Nd St W",
    "iso:country":"CA",
    "sg:address":"1509 2nd St W",
    "sg:city":"Cornwall",
    "sg:classifiers":[
        {
            "category":"Organizations",
            "subcategory":"Religious Organization",
            "type":"Services"
        }
    ],
    "sg:phone":"+1 613 938 6683",
    "sg:postcode":"K6J 1J5",
    "sg:province":"ON",
    "sg:tags":[
        "church"
    ],
    "wof:name":"St Matthews Lutheran Church",
    "wof:placetype":"venue"
},
  "geometry": {"coordinates":[-74.76508331300001,45.0108261108],"type":"Point"}
}