{
  "type": "Feature",
  "properties": {
    "addr:full":"Stanstead QC J0B 3E2",
    "addr:postcode":"j0b 3e2",
    "iso:country":"CA",
    "sg:city":"Stanstead",
    "sg:classifiers":[
        {
            "category":"Personal",
            "subcategory":"Beauty Salon",
            "type":"Services"
        }
    ],
    "sg:phone":"+1 819 876 5711",
    "sg:postcode":"J0B 3E2",
    "sg:province":"QC",
    "wof:name":"Raymond's Beauty Shop",
    "wof:placetype":"venue"
},
  "geometry": {"coordinates":[-72.0971298218,45.0064277649],"type":"Point"}
}