{
  "type": "Feature",
  "properties": {
    "addr:full":"305 Boul Saint-Luc Saint-Luc QC J2W 1C5",
    "addr:housenumber":"305",
    "addr:postcode":"j2w 1c5",
    "addr:street":"Boul Saint-Luc",
    "iso:country":"CA",
    "sg:address":"305 Boul Saint-Luc",
    "sg:city":"Saint-Luc",
    "sg:classifiers":[
        {
            "category":"Shopping",
            "subcategory":"Florist",
            "type":"Retail Goods"
        }
    ],
    "sg:phone":"+1 450 359 9984",
    "sg:postcode":"J2W 1C5",
    "sg:province":"QC",
    "wof:name":"Fleur D'Art",
    "wof:placetype":"venue"
},
  "geometry": {"coordinates":[-73.2981414795,45.3568992615],"type":"Point"}
}