{
  "type": "Feature",
  "properties": {
    "addr:full":"867 Mcleod Ave Winnipeg MB R2G 0Y4",
    "addr:housenumber":"867",
    "addr:postcode":"r2g 0y4",
    "addr:street":"Mcleod Ave",
    "iso:country":"CA",
    "sg:address":"867 Mcleod Ave",
    "sg:city":"Winnipeg",
    "sg:classifiers":[
        {
            "category":"Home & Garden",
            "subcategory":"Building Materials",
            "type":"Retail Goods"
        }
    ],
    "sg:phone":"+1 204 668 0079",
    "sg:postcode":"R2G 0Y4",
    "sg:province":"MB",
    "wof:name":"Woodland Supply",
    "wof:placetype":"venue"
},
  "geometry": {"coordinates":[-97.0665969849,49.9280967712],"type":"Point"}
}