{
  "type": "Feature",
  "properties": {
    "addr:full":"801 Marine Dr # 100 North Vancouver BC V7P 3K6",
    "addr:housenumber":"801",
    "addr:postcode":"v7p 3k6",
    "addr:street":"Marine Dr # 100",
    "iso:country":"CA",
    "sg:address":"801 Marine Dr # 100",
    "sg:city":"North Vancouver",
    "sg:classifiers":[
        {
            "category":"Restaurant",
            "type":"Food & Drink"
        }
    ],
    "sg:phone":"+1 604 984 4464",
    "sg:postcode":"V7P 3K6",
    "sg:province":"BC",
    "wof:name":"Red Robin Capalano",
    "wof:placetype":"venue"
},
  "geometry": {"coordinates":[-123.095009,49.321091],"type":"Point"}
}