{
  "type": "Feature",
  "properties": {
    "iso:country":"CA",
    "sg:address":"400 Ray Lawson Blvd",
    "sg:city":"Brampton",
    "sg:classifiers":[
        {
            "category":"Health Services",
            "subcategory":"Nursing And Care Facility",
            "type":"Services"
        }
    ],
    "sg:phone":"+1 905 456 3334",
    "sg:postcode":"L6Y 4G4",
    "sg:province":"ON",
    "sg:tags":[
        "home",
        "retirement",
        "community"
    ],
    "wof:name":"Southbrook Lodge Inc",
    "wof:placetype":"venue"
},
  "geometry": {"coordinates":[-79.732002,43.653362],"type":"Point"}
}