{
  "type": "Feature",
  "properties": {
    "addr:full":"400 Ray Lawson Blvd Brampton ON L6Y 4G4",
    "addr:housenumber":"400",
    "addr:postcode":"l6y 4g4",
    "addr:street":"Ray Lawson Blvd",
    "iso:country":"CA",
    "sg:address":"400 Ray Lawson Blvd",
    "sg:city":"Brampton",
    "sg:classifiers":[
        {
            "category":"Health Services",
            "subcategory":"Nursing And Care Facility",
            "type":"Services"
        }
    ],
    "sg:phone":"+1 905 456 3334",
    "sg:postcode":"L6Y 4G4",
    "sg:province":"ON",
    "sg:tags":[
        "home",
        "retirement",
        "community"
    ],
    "wof:name":"Southbrook Lodge Inc",
    "wof:placetype":"venue"
},
  "geometry": {"coordinates":[-79.73200199999999,43.653362],"type":"Point"}
}