{
  "type": "Feature",
  "properties": {
    "addr:full":"3066 Boul Des Forges Trois-Rivieres QC G8Z 1V5",
    "addr:housenumber":"3066",
    "addr:postcode":"g8z 1v5",
    "addr:street":"Boul Des Forges Trois-Rivieres",
    "iso:country":"CA",
    "sg:address":"3066 Boul Des Forges",
    "sg:city":"Trois-Rivieres",
    "sg:classifiers":[
        {
            "category":"Professional",
            "subcategory":"Business Services",
            "type":"Services"
        }
    ],
    "sg:phone":"+1 819 375 6315",
    "sg:postcode":"G8Z 1V5",
    "sg:province":"QC",
    "sg:tags":[
        "inventory"
    ],
    "wof:name":"Service D'Inventaire-Gestion",
    "wof:placetype":"venue"
},
  "geometry": {"coordinates":[-72.570137,46.348557],"type":"Point"}
}