{
  "type": "Feature",
  "properties": {
    "addr:full":"Sainte-Claire QC G0R 2V0",
    "addr:postcode":"g0r 2v0",
    "iso:country":"CA",
    "sg:city":"Sainte-Claire",
    "sg:classifiers":[
        {
            "category":"Building & Trades",
            "subcategory":"Plumbing",
            "type":"Services"
        }
    ],
    "sg:phone":"+1 418 883 3244",
    "sg:postcode":"G0R 2V0",
    "sg:province":"QC",
    "sg:tags":[
        "contractor"
    ],
    "wof:name":"Fournier Gilles Inc",
    "wof:placetype":"venue"
},
  "geometry": {"coordinates":[-70.8535,46.59874],"type":"Point"}
}