{
  "type": "Feature",
  "properties": {
    "addr:full":"Tobermory ON N0H 2R0",
    "addr:postcode":"n0h 2r0",
    "iso:country":"CA",
    "sg:city":"Tobermory",
    "sg:classifiers":[
        {
            "category":"Building & Trades",
            "subcategory":"Construction",
            "type":"Services"
        }
    ],
    "sg:phone":"+1 519 596 8272",
    "sg:postcode":"N0H 2R0",
    "sg:province":"ON",
    "sg:tags":[
        "general",
        "contractor"
    ],
    "wof:name":"Gary's Cement Work",
    "wof:placetype":"venue"
},
  "geometry": {"coordinates":[-81.665092,45.253826],"type":"Point"}
}