{
  "type": "Feature",
  "properties": {
    "iso:country":"CA",
    "sg:address":"5304 Sherbourne Dr",
    "sg:city":"Nanaimo",
    "sg:classifiers":[
        {
            "category":"Recreation",
            "type":"Entertainment"
        }
    ],
    "sg:phone":"+1 250 751 3657",
    "sg:postcode":"V9T 2J8",
    "sg:province":"BC",
    "sg:tags":[
        "martial",
        "arts",
        "instruction"
    ],
    "wof:name":"Tomari School of Karate",
    "wof:placetype":"venue"
},
  "geometry": {"coordinates":[-124.03831481900001,49.2159805298],"type":"Point"}
}