{
  "type": "Feature",
  "properties": {
    "addr:full":"287 Lorne St Sudbury ON P3C 4R1",
    "addr:housenumber":"287",
    "addr:postcode":"p3c 4r1",
    "addr:street":"Lorne St",
    "iso:country":"CA",
    "sg:address":"287 Lorne St",
    "sg:city":"Sudbury",
    "sg:classifiers":[
        {
            "category":"Retail",
            "subcategory":"Auto Repair",
            "type":"Services"
        }
    ],
    "sg:phone":"+1 705 673 8616",
    "sg:postcode":"P3C 4R1",
    "sg:province":"ON",
    "sg:tags":[
        "repairing",
        "automobile"
    ],
    "wof:name":"Tony's Auto Svc",
    "wof:placetype":"venue"
},
  "geometry": {"coordinates":[-81.00578308110001,46.4855003357],"type":"Point"}
}