{
  "type": "Feature",
  "properties": {
    "iso:country":"CA",
    "sg:address":"124 Sydney St S",
    "sg:city":"Kitchener",
    "sg:classifiers":[
        {
            "category":"Building & Trades",
            "subcategory":"Construction",
            "type":"Services"
        }
    ],
    "sg:phone":"+1 519 744 4714",
    "sg:postcode":"N2G 3V2",
    "sg:province":"ON",
    "sg:tags":[
        "painter"
    ],
    "wof:name":"Painters & Allied Trades",
    "wof:placetype":"venue"
},
  "geometry": {"coordinates":[-80.472824,43.438484],"type":"Point"}
}