{
  "type": "Feature",
  "properties": {
    "addr:full":"942 Cole Harbour Rd Dartmouth NS B2V 1E6",
    "addr:housenumber":"942",
    "addr:postcode":"b2v 1e6",
    "addr:street":"Cole Harbour Rd",
    "iso:country":"CA",
    "sg:address":"942 Cole Harbour Rd",
    "sg:city":"Dartmouth",
    "sg:classifiers":[
        {
            "category":"Real Estate",
            "subcategory":"Real Estate Agent",
            "type":"Services"
        }
    ],
    "sg:phone":"+1 902 434 9090",
    "sg:postcode":"B2V 1E6",
    "sg:province":"NS",
    "wof:name":"Century 21 Trident Realty Ltd",
    "wof:placetype":"venue"
},
  "geometry": {"coordinates":[-63.4969215393,44.6710968018],"type":"Point"}
}