{
  "type": "Feature",
  "properties": {
    "addr:full":"Churchbridge SK S0A 0M0",
    "addr:postcode":"s0a 0m0",
    "iso:country":"CA",
    "sg:city":"Churchbridge",
    "sg:classifiers":[
        {
            "category":"Farming",
            "subcategory":"Nursery",
            "type":"Manufacturing & Wholesale Goods"
        }
    ],
    "sg:phone":"+1 306 896 2992",
    "sg:postcode":"S0A 0M0",
    "sg:province":"SK",
    "sg:tags":[
        "greenhouse"
    ],
    "wof:name":"Hillcrest Harmony Flowers",
    "wof:placetype":"venue"
},
  "geometry": {"coordinates":[-101.89769699999999,50.897381],"type":"Point"}
}