{
  "type": "Feature",
  "properties": {
    "addr:full":"190 Henderson Hwy Winnipeg MB R2L 1L6",
    "addr:housenumber":"190",
    "addr:postcode":"r2l 1l6",
    "addr:street":"Henderson Hwy",
    "iso:country":"CA",
    "sg:address":"190 Henderson Hwy",
    "sg:city":"Winnipeg",
    "sg:classifiers":[
        {
            "category":"Restaurant",
            "type":"Food & Drink"
        }
    ],
    "sg:phone":"+1 204 661 3643",
    "sg:postcode":"R2L 1L6",
    "sg:province":"MB",
    "wof:name":"Sonya's Restaurant",
    "wof:placetype":"venue"
},
  "geometry": {"coordinates":[-97.1158752441,49.9132957458],"type":"Point"}
}