{
  "type": "Feature",
  "properties": {
    "addr:full":"314 Main St W Warman SK S0K 4S0",
    "addr:housenumber":"314",
    "addr:postcode":"s0k 4s0",
    "addr:street":"Main St W",
    "iso:country":"CA",
    "sg:address":"314 Main St W",
    "sg:city":"Warman",
    "sg:classifiers":[
        {
            "category":"Health Services",
            "subcategory":"Chiropractor",
            "type":"Services"
        }
    ],
    "sg:phone":"+1 306 956 0860",
    "sg:postcode":"S0K 4S0",
    "sg:province":"SK",
    "wof:name":"Reid Family Chiropractic",
    "wof:placetype":"venue"
},
  "geometry": {"coordinates":[-106.572525,52.318489],"type":"Point"}
}