{
  "type": "Feature",
  "properties": {
    "addr:full":"500 Rue Kennedy Dieppe NB E1A 5Y7",
    "addr:housenumber":"500",
    "addr:postcode":"e1a 5y7",
    "addr:street":"Rue Kennedy",
    "iso:country":"CA",
    "sg:address":"500 Rue Kennedy",
    "sg:city":"Dieppe",
    "sg:classifiers":[
        {
            "category":"Restaurant",
            "type":"Food & Drink"
        }
    ],
    "sg:phone":"+1 506 855 0564",
    "sg:postcode":"E1A 5Y7",
    "sg:province":"NB",
    "wof:name":"Garden Breeze Restaurant",
    "wof:placetype":"venue"
},
  "geometry": {"coordinates":[-64.760391,46.098789],"type":"Point"}
}