{
  "type": "Feature",
  "properties": {
    "iso:country":"CA",
    "sg:address":"63 Dundas St W",
    "sg:city":"Mississauga",
    "sg:classifiers":[
        {
            "category":"Shopping",
            "subcategory":"Shoes",
            "type":"Retail Goods"
        }
    ],
    "sg:phone":"+1 905 277 2526",
    "sg:postcode":"L5B 1H7",
    "sg:province":"ON",
    "wof:name":"Firenze Shoes",
    "wof:placetype":"venue"
},
  "geometry": {"coordinates":[-79.6182556152,43.5788002014],"type":"Point"}
}