{
  "type": "Feature",
  "properties": {
    "addr:full":"4180 Rue Bernard-Pilon Saint-Mathieu-DE-Beloeil QC J3G 4S5",
    "addr:housenumber":"4180",
    "addr:postcode":"j3g 4s5",
    "addr:street":"Rue Bernard-Pilon",
    "iso:country":"CA",
    "sg:address":"4180 Rue Bernard-Pilon",
    "sg:city":"Saint-Mathieu-DE-Beloeil",
    "sg:classifiers":[
        {
            "category":"Travel",
            "subcategory":"Hotels & Motels",
            "type":"Entertainment"
        }
    ],
    "sg:phone":"+1 450 467 1373",
    "sg:postcode":"J3G 4S5",
    "sg:province":"QC",
    "wof:name":"Motel Beloeil Inc",
    "wof:placetype":"venue"
},
  "geometry": {"coordinates":[-73.282471,45.584126],"type":"Point"}
}