{
  "type": "Feature",
  "properties": {
    "addr:full":"11575 Burnaby Rd Wainfleet ON L0S 1V0",
    "addr:housenumber":"11575",
    "addr:postcode":"l0s 1v0",
    "addr:street":"Burnaby Rd",
    "iso:country":"CA",
    "sg:address":"11575 Burnaby Rd",
    "sg:city":"Wainfleet",
    "sg:classifiers":[
        {
            "category":"Wholesale",
            "subcategory":"Metals & Minerals",
            "type":"Manufacturing & Wholesale Goods"
        }
    ],
    "sg:phone":"+1 905 899 2047",
    "sg:postcode":"L0S 1V0",
    "sg:province":"ON",
    "sg:tags":[
        "pipe"
    ],
    "wof:name":"Devron Pipe Sales",
    "wof:placetype":"venue"
},
  "geometry": {"coordinates":[-79.355743,42.88541],"type":"Point"}
}