{
  "type": "Feature",
  "properties": {
    "iso:country":"CA",
    "sg:address":"6110 Ch DE Chambly # 210",
    "sg:city":"Saint-Hubert",
    "sg:classifiers":[
        {
            "category":"Banks & Credit Unions",
            "subcategory":"Investment Brokerage",
            "type":"Services"
        }
    ],
    "sg:phone":"+1 450 443 3347",
    "sg:postcode":"J3Y 3R5",
    "sg:province":"QC",
    "sg:tags":[
        "consultant",
        "planning",
        "financial"
    ],
    "wof:name":"Services Financiers E Gosselin",
    "wof:placetype":"venue"
},
  "geometry": {"coordinates":[-73.4042434692,45.4974250793],"type":"Point"}
}