{
  "type": "Feature",
  "properties": {
    "addr:full":"279 Wellington St Kingston ON K7K 6E1",
    "addr:housenumber":"279",
    "addr:postcode":"k7k 6e1",
    "addr:street":"Wellington St",
    "iso:country":"CA",
    "sg:address":"279 Wellington St",
    "sg:city":"Kingston",
    "sg:classifiers":[
        {
            "category":"Government",
            "subcategory":"Office",
            "type":"Public Place"
        }
    ],
    "sg:phone":"+1 613 547 8557",
    "sg:postcode":"K7K 6E1",
    "sg:province":"ON",
    "sg:tags":[
        "village"
    ],
    "wof:name":"Kingston Provincial Offences",
    "wof:placetype":"venue"
},
  "geometry": {"coordinates":[-76.4814376831,44.2341766357],"type":"Point"}
}