{
  "type": "Feature",
  "properties": {
    "addr:full":"Roquemaure QC J0Z 3K0",
    "addr:postcode":"j0z 3k0",
    "iso:country":"CA",
    "sg:city":"Roquemaure",
    "sg:classifiers":[
        {
            "category":"Manufacturing",
            "subcategory":"Lumber",
            "type":"Manufacturing & Wholesale Goods"
        }
    ],
    "sg:phone":"+1 819 333 7887",
    "sg:postcode":"J0Z 3K0",
    "sg:province":"QC",
    "sg:tags":[
        "syrup",
        "maple",
        "sugar"
    ],
    "wof:name":"Cabane A Sucre Chez Ti-Paul",
    "wof:placetype":"venue"
},
  "geometry": {"coordinates":[-79.405647,48.619801],"type":"Point"}
}