{
  "type": "Feature",
  "properties": {
    "addr:full":"101 King St Stewart Valley SK S0N 2P0",
    "addr:housenumber":"101",
    "addr:postcode":"s0n 2p0",
    "addr:street":"King St",
    "iso:country":"CA",
    "sg:address":"101 King St",
    "sg:city":"Stewart Valley",
    "sg:classifiers":[
        {
            "category":"Government",
            "subcategory":"Office",
            "type":"Public Place"
        }
    ],
    "sg:phone":"+1 306 778 2105",
    "sg:postcode":"S0N 2P0",
    "sg:province":"SK",
    "sg:tags":[
        "municipality"
    ],
    "wof:name":"R M of Sask Landing",
    "wof:placetype":"venue"
},
  "geometry": {"coordinates":[-107.805183,50.594646],"type":"Point"}
}