{
  "type": "Feature",
  "properties": {
    "addr:full":"1054 Centre St Thornhill ON L4J 3M8",
    "addr:housenumber":"1054",
    "addr:postcode":"l4j 3m8",
    "addr:street":"Centre St",
    "iso:country":"CA",
    "sg:address":"1054 Centre St",
    "sg:city":"Thornhill",
    "sg:classifiers":[
        {
            "category":"Retail",
            "subcategory":"Laundry & Dry Cleaning",
            "type":"Services"
        }
    ],
    "sg:phone":"+1 905 764 0169",
    "sg:postcode":"L4J 3M8",
    "sg:province":"ON",
    "sg:tags":[
        "cleaners"
    ],
    "wof:name":"Cadet Cleaners",
    "wof:placetype":"venue"
},
  "geometry": {"coordinates":[-79.45965576170001,43.8090133667],"type":"Point"}
}