{
  "type": "Feature",
  "properties": {
    "addr:full":"950 Rue Saint-Jean Quebec QC G1R 1R5",
    "addr:housenumber":"950",
    "addr:postcode":"g1r 1r5",
    "addr:street":"Rue Saint-Jean",
    "iso:country":"CA",
    "sg:address":"950 Rue Saint-Jean",
    "sg:city":"Quebec",
    "sg:classifiers":[
        {
            "category":"Professional",
            "subcategory":"Computer Services",
            "type":"Services"
        }
    ],
    "sg:phone":"+1 418 694 0051",
    "sg:postcode":"G1R 1R5",
    "sg:province":"QC",
    "sg:tags":[
        "shop",
        "coffee",
        "internet"
    ],
    "wof:name":"Tribune Cafe",
    "wof:placetype":"venue"
},
  "geometry": {"coordinates":[-71.2141952515,46.8126525879],"type":"Point"}
}