{
  "type": "Feature",
  "properties": {
    "addr:full":"811 14 St NW Calgary AB T2N 2A4",
    "addr:housenumber":"14",
    "addr:postcode":"t2n 2a4",
    "addr:street":"811;St Nw",
    "iso:country":"CA",
    "sg:address":"811 14 St NW",
    "sg:city":"Calgary",
    "sg:classifiers":[
        {
            "category":"Organizations",
            "subcategory":"Non-profit Organization",
            "type":"Services"
        }
    ],
    "sg:phone":"+1 403 270 8500",
    "sg:postcode":"T2N 2A4",
    "sg:province":"AB",
    "sg:tags":[
        "charitable",
        "institution",
        "association"
    ],
    "wof:name":"Canadian Down Syndrome Society",
    "wof:placetype":"venue"
},
  "geometry": {"coordinates":[-114.094917,51.059086],"type":"Point"}
}