{
  "type": "Feature",
  "properties": {
    "addr:full":"227 St Andrew St W Fergus ON N1M 1N8",
    "addr:housenumber":"227",
    "addr:postcode":"n1m 1n8",
    "addr:street":"St Andrew St W",
    "iso:country":"CA",
    "sg:address":"227 St Andrew St W",
    "sg:city":"Fergus",
    "sg:classifiers":[
        {
            "category":"Shopping",
            "subcategory":"Department Store",
            "type":"Retail Goods"
        }
    ],
    "sg:phone":"+1 519 843 2161",
    "sg:postcode":"N1M 1N8",
    "sg:province":"ON",
    "wof:name":"James Russell & Sons Ltd",
    "wof:placetype":"venue"
},
  "geometry": {"coordinates":[-80.3790969849,43.704460144],"type":"Point"}
}