{
  "type": "Feature",
  "properties": {
    "addr:full":"1815 Yonge St #200 Toronto ON M4T 2A4",
    "addr:housenumber":"1815",
    "addr:postcode":"m4t 2a4",
    "addr:street":"Yonge St # 200",
    "iso:country":"CA",
    "sg:address":"1815 Yonge St #200",
    "sg:city":"Toronto",
    "sg:classifiers":[
        {
            "category":"Real Estate",
            "subcategory":"Architect",
            "type":"Services"
        }
    ],
    "sg:phone":"+1 416 480 2020",
    "sg:postcode":"M4T 2A4",
    "sg:province":"ON",
    "wof:name":"Reich & Petch Architects Inc",
    "wof:placetype":"venue"
},
  "geometry": {"coordinates":[-79.396095,43.696056],"type":"Point"}
}