{
  "type": "Feature",
  "properties": {
    "addr:full":"434 Sackville Dr Lower Sackville NS B4C 2R8",
    "addr:housenumber":"434",
    "addr:postcode":"b4c 2r8",
    "addr:street":"Sackville Dr",
    "iso:country":"CA",
    "sg:address":"434 Sackville Dr",
    "sg:city":"Lower Sackville",
    "sg:classifiers":[
        {
            "category":"Retail",
            "subcategory":"Car Wash",
            "type":"Services"
        }
    ],
    "sg:phone":"+1 902 456 5513",
    "sg:postcode":"B4C 2R8",
    "sg:province":"NS",
    "sg:tags":[
        "polishing",
        "washing"
    ],
    "wof:name":"Rubber Duck Car Wash",
    "wof:placetype":"venue"
},
  "geometry": {"coordinates":[-63.678436,44.764805],"type":"Point"}
}