{
  "type": "Feature",
  "properties": {
    "iso:country":"CA",
    "sg:address":"1470 Midland Ave",
    "sg:city":"Scarborough",
    "sg:classifiers":[
        {
            "category":"Real Estate",
            "subcategory":"Developer",
            "type":"Services"
        }
    ],
    "sg:phone":"+1 416 750 8262",
    "sg:postcode":"M1P 4Z4",
    "sg:province":"ON",
    "sg:tags":[
        "company",
        "land"
    ],
    "wof:name":"Scarborough Fair Condominiums",
    "wof:placetype":"venue"
},
  "geometry": {"coordinates":[-79.2657546997,43.753036499],"type":"Point"}
}