{
  "type": "Feature",
  "properties": {
    "addr:full":"Swan Hills AB T0G 2C0",
    "addr:postcode":"t0g 2c0",
    "iso:country":"CA",
    "sg:city":"Swan Hills",
    "sg:classifiers":[
        {
            "category":"Mining & Drilling",
            "type":"Manufacturing & Wholesale Goods"
        }
    ],
    "sg:phone":"+1 780 333 2692",
    "sg:postcode":"T0G 2C0",
    "sg:province":"AB",
    "sg:tags":[
        "field",
        "oil"
    ],
    "wof:name":"Weatherford Artiticial Lift",
    "wof:placetype":"venue"
},
  "geometry": {"coordinates":[-115.413177,54.718685],"type":"Point"}
}