{
  "type": "Feature",
  "properties": {
    "addr:full":"207 Mcrae Dr East York ON M4G 1T4",
    "addr:housenumber":"207",
    "addr:postcode":"m4g 1t4",
    "addr:street":"Mcrae Dr",
    "iso:country":"CA",
    "sg:address":"207 Mcrae Dr",
    "sg:city":"East York",
    "sg:classifiers":[
        {
            "category":"Building & Trades",
            "subcategory":"Construction",
            "type":"Services"
        }
    ],
    "sg:phone":"+1 416 489 1776",
    "sg:postcode":"M4G 1T4",
    "sg:province":"ON",
    "sg:tags":[
        "home",
        "general",
        "improvement",
        "contractor"
    ],
    "wof:name":"Belvedere Home Improvements",
    "wof:placetype":"venue"
},
  "geometry": {"coordinates":[-79.3658065796,43.7081832886],"type":"Point"}
}