{
  "type": "Feature",
  "properties": {
    "addr:full":"1 Rue Villeneuve Saint-Andre-Avellin QC J0V 1W0",
    "addr:housenumber":"1",
    "addr:postcode":"j0v 1w0",
    "addr:street":"Rue Villeneuve Saint-Andre-Avellin",
    "iso:country":"CA",
    "sg:address":"1 Rue Villeneuve",
    "sg:city":"Saint-Andre-Avellin",
    "sg:classifiers":[
        {
            "category":"Education",
            "subcategory":"School",
            "type":"Public Place"
        }
    ],
    "sg:phone":"+1 819 983 7315",
    "sg:postcode":"J0V 1W0",
    "sg:province":"QC",
    "wof:name":"Ecole Jm Robert & Providence",
    "wof:placetype":"venue"
},
  "geometry": {"coordinates":[-75.0578613281,45.721446991],"type":"Point"}
}