{
  "type": "Feature",
  "properties": {
    "addr:full":"409 Richview Ave Toronto ON M5P 3G7",
    "addr:housenumber":"409",
    "addr:postcode":"m5p 3g7",
    "addr:street":"Richview Ave",
    "iso:country":"CA",
    "sg:address":"409 Richview Ave",
    "sg:city":"Toronto",
    "sg:classifiers":[
        {
            "category":"Professional",
            "subcategory":"Management & Consulting",
            "type":"Services"
        }
    ],
    "sg:phone":"+1 416 483 5357",
    "sg:postcode":"M5P 3G7",
    "sg:province":"ON",
    "sg:tags":[
        "communications",
        "consultant",
        "marketing"
    ],
    "wof:name":"Rotman & CO Inc",
    "wof:placetype":"venue"
},
  "geometry": {"coordinates":[-79.42282867430001,43.6978378296],"type":"Point"}
}