{
  "type": "Feature",
  "properties": {
    "addr:full":"1626 Lasalle Blvd #B Sudbury ON P3A 1Z7",
    "addr:housenumber":"1626",
    "addr:postcode":"p3a 1z7",
    "addr:street":"Lasalle Blvd # B",
    "iso:country":"CA",
    "sg:address":"1626 Lasalle Blvd #B",
    "sg:city":"Sudbury",
    "sg:classifiers":[
        {
            "category":"Building & Trades",
            "subcategory":"Construction",
            "type":"Services"
        }
    ],
    "sg:phone":"+1 705 524 9405",
    "sg:postcode":"P3A 1Z7",
    "sg:province":"ON",
    "sg:tags":[
        "waterproofing",
        "contractor"
    ],
    "wof:name":"Faggioni Homes",
    "wof:placetype":"venue"
},
  "geometry": {"coordinates":[-80.9378204346,46.522190094],"type":"Point"}
}