{
  "type": "Feature",
  "properties": {
    "addr:full":"1495 Boul Saint-Paul Chicoutimi QC G7J 3Y3",
    "addr:housenumber":"1495",
    "addr:postcode":"g7j 3y3",
    "addr:street":"Boul Saint-Paul",
    "iso:country":"CA",
    "sg:address":"1495 Boul Saint-Paul",
    "sg:city":"Chicoutimi",
    "sg:classifiers":[
        {
            "category":"Food & Beverages",
            "subcategory":"Groceries & Convenience Stores",
            "type":"Retail Goods"
        }
    ],
    "sg:phone":"+1 418 545 0411",
    "sg:postcode":"G7J 3Y3",
    "sg:province":"QC",
    "sg:tags":[
        "grocer"
    ],
    "wof:name":"Couche-Tard",
    "wof:placetype":"venue"
},
  "geometry": {"coordinates":[-71.09642791749999,48.4043769836],"type":"Point"}
}