{
  "type": "Feature",
  "properties": {
    "addr:full":"346 Main St N Markham ON L3P 1Z1",
    "addr:housenumber":"346",
    "addr:postcode":"l3p 1z1",
    "addr:street":"Main St N",
    "iso:country":"CA",
    "sg:address":"346 Main St N",
    "sg:city":"Markham",
    "sg:classifiers":[
        {
            "category":"Personal",
            "subcategory":"Beauty Salon",
            "type":"Services"
        }
    ],
    "sg:phone":"+1 905 471 1084",
    "sg:postcode":"L3P 1Z1",
    "sg:province":"ON",
    "wof:name":"Kids Zone Hair Shop",
    "wof:placetype":"venue"
},
  "geometry": {"coordinates":[-79.2636871338,43.8894615173],"type":"Point"}
}