{
  "type": "Feature",
  "properties": {
    "addr:full":"350 138 Rte Saint-Hilarion QC G0A 3V0",
    "addr:housenumber":"138",
    "addr:postcode":"g0a 3v0",
    "addr:street":"Rte Saint-Hilarion",
    "iso:country":"CA",
    "sg:address":"350 138 Rte",
    "sg:city":"Saint-Hilarion",
    "sg:classifiers":[
        {
            "category":"Building & Trades",
            "subcategory":"Construction",
            "type":"Services"
        }
    ],
    "sg:phone":"+1 418 457 3853",
    "sg:postcode":"G0A 3V0",
    "sg:province":"QC",
    "sg:tags":[
        "general",
        "contractor"
    ],
    "wof:name":"Constructions Ovila Dufour Inc",
    "wof:placetype":"venue"
},
  "geometry": {"coordinates":[-70.4019393921,47.5760421753],"type":"Point"}
}