{
  "type": "Feature",
  "properties": {
    "addr:full":"2052 Rue Lapierre Lasalle QC H8N 2L1",
    "addr:housenumber":"2052",
    "addr:postcode":"h8n 2l1",
    "addr:street":"Rue Lapierre",
    "iso:country":"CA",
    "sg:address":"2052 Rue Lapierre",
    "sg:city":"Lasalle",
    "sg:classifiers":[
        {
            "category":"Home & Garden",
            "subcategory":"Household Appliances",
            "type":"Retail Goods"
        }
    ],
    "sg:phone":"+1 514 365 4622",
    "sg:postcode":"H8N 2L1",
    "sg:province":"QC",
    "sg:tags":[
        "cleaners",
        "vacuum"
    ],
    "wof:name":"Aspirateurs Multi-Choix",
    "wof:placetype":"venue"
},
  "geometry": {"coordinates":[-73.61599,45.436867],"type":"Point"}
}