{
  "type": "Feature",
  "properties": {
    "iso:country":"CA",
    "sg:address":"2440 128 St",
    "sg:city":"Surrey",
    "sg:classifiers":[
        {
            "category":"Education",
            "subcategory":"School",
            "type":"Public Place"
        }
    ],
    "sg:phone":"+1 604 535 9101",
    "sg:postcode":"V4A 3W3",
    "sg:province":"BC",
    "wof:name":"Crescent Park Elementary Schl",
    "wof:placetype":"venue"
},
  "geometry": {"coordinates":[-122.867118835,49.0467987061],"type":"Point"}
}