{
  "type": "Feature",
  "properties": {
    "addr:full":"2440 128 St Surrey BC V4A 3W3",
    "addr:housenumber":"2440",
    "addr:postcode":"v4a 3w3",
    "addr:street":"128 St",
    "iso:country":"CA",
    "sg:address":"2440 128 St",
    "sg:city":"Surrey",
    "sg:classifiers":[
        {
            "category":"Education",
            "subcategory":"School",
            "type":"Public Place"
        }
    ],
    "sg:phone":"+1 604 535 9101",
    "sg:postcode":"V4A 3W3",
    "sg:province":"BC",
    "wof:name":"Crescent Park Elementary Schl",
    "wof:placetype":"venue"
},
  "geometry": {"coordinates":[-122.867118835,49.0467987061],"type":"Point"}
}