{
  "type": "Feature",
  "properties": {
    "iso:country":"CA",
    "sg:address":"628 Wellington St",
    "sg:city":"London",
    "sg:classifiers":[
        {
            "category":"Banks & Credit Unions",
            "subcategory":"Investment Brokerage",
            "type":"Services"
        }
    ],
    "sg:phone":"+1 519 660 1075",
    "sg:postcode":"N6A 3R9",
    "sg:province":"ON",
    "wof:name":"Dardan Capital Corp",
    "wof:placetype":"venue"
},
  "geometry": {"coordinates":[-81.24881,42.992168],"type":"Point"}
}