{
  "type": "Feature",
  "properties": {
    "addr:full":"Drayton Valley AB T7A 1R5",
    "addr:postcode":"t7a 1r5",
    "addr:street":"Drayton",
    "iso:country":"CA",
    "sg:city":"Drayton Valley",
    "sg:classifiers":[
        {
            "category":"Building & Trades",
            "subcategory":"Construction",
            "type":"Services"
        }
    ],
    "sg:phone":"+1 780 542 7441",
    "sg:postcode":"T7A 1R5",
    "sg:province":"AB",
    "sg:tags":[
        "sandblasting",
        "painter"
    ],
    "wof:name":"Artisan Sandblasting & Paintng",
    "wof:placetype":"venue"
},
  "geometry": {"coordinates":[-114.979752,53.206966],"type":"Point"}
}