{
  "type": "Feature",
  "properties": {
    "addr:full":"Prevost QC J0R 1T0",
    "addr:postcode":"j0r 1t0",
    "addr:street":"Prevost",
    "iso:country":"CA",
    "sg:city":"Prevost",
    "sg:classifiers":[
        {
            "category":"Personal",
            "type":"Services"
        }
    ],
    "sg:phone":"+1 450 224 7187",
    "sg:postcode":"J0R 1T0",
    "sg:province":"QC",
    "sg:tags":[
        "therapist",
        "massage"
    ],
    "wof:name":"Centre DE Massotherapie",
    "wof:placetype":"venue"
},
  "geometry": {"coordinates":[-74.0699310303,45.858997345],"type":"Point"}
}