{
  "type": "Feature",
  "properties": {
    "addr:full":"627 Prince Rupert Ave Winnipeg MB R2K 1W1",
    "addr:housenumber":"627",
    "addr:postcode":"r2k 1w1",
    "addr:street":"Prince Rupert Ave",
    "iso:country":"CA",
    "sg:address":"627 Prince Rupert Ave",
    "sg:city":"Winnipeg",
    "sg:classifiers":[
        {
            "category":"Professional",
            "subcategory":"Management & Consulting",
            "type":"Services"
        }
    ],
    "sg:phone":"+1 204 663 2140",
    "sg:postcode":"R2K 1W1",
    "sg:province":"MB",
    "sg:tags":[
        "construction"
    ],
    "wof:name":"Gwh Construction Management",
    "wof:placetype":"venue"
},
  "geometry": {"coordinates":[-97.08554100000001,49.91626],"type":"Point"}
}