{
  "type": "Feature",
  "properties": {
    "addr:full":"1264 Athol St Regina SK S4T 7V3",
    "addr:housenumber":"1264",
    "addr:postcode":"s4t 7v3",
    "addr:street":"Athol St",
    "iso:country":"CA",
    "sg:address":"1264 Athol St",
    "sg:city":"Regina",
    "sg:classifiers":[
        {
            "category":"Government",
            "subcategory":"Office",
            "type":"Public Place"
        }
    ],
    "sg:phone":"+1 306 777 6450",
    "sg:postcode":"S4T 7V3",
    "sg:province":"SK",
    "sg:tags":[
        "department",
        "police",
        "association",
        "village"
    ],
    "wof:name":"North Central Community Assn",
    "wof:placetype":"venue"
},
  "geometry": {"coordinates":[-104.628433227,50.4588737488],"type":"Point"}
}