{
  "type": "Feature",
  "properties": {
    "addr:full":"395 St Albert Rd St Albert AB T8N 5Z9",
    "addr:housenumber":"395",
    "addr:postcode":"t8n 5z9",
    "addr:street":"St Albert Rd St Albert",
    "iso:country":"CA",
    "sg:address":"395 St Albert Rd",
    "sg:city":"St Albert",
    "sg:classifiers":[
        {
            "category":"Restaurant",
            "type":"Food & Drink"
        }
    ],
    "sg:phone":"+1 780 458 3620",
    "sg:postcode":"T8N 5Z9",
    "sg:province":"AB",
    "sg:tags":[
        "grocer",
        "delicatessen"
    ],
    "wof:name":"Canada Safeway Ltd",
    "wof:placetype":"venue"
},
  "geometry": {"coordinates":[-113.625885,53.644066],"type":"Point"}
}