{
  "type": "Feature",
  "properties": {
    "addr:full":"85 Macbeath Ave Moncton NB E1C 6Z3",
    "addr:housenumber":"85",
    "addr:postcode":"e1c 6z3",
    "addr:street":"Macbeath Ave",
    "iso:country":"CA",
    "sg:address":"85 Macbeath Ave",
    "sg:city":"Moncton",
    "sg:classifiers":[
        {
            "category":"Organizations",
            "subcategory":"Religious Organization",
            "type":"Services"
        }
    ],
    "sg:phone":"+1 506 857 4817",
    "sg:postcode":"E1C 6Z3",
    "sg:province":"NB",
    "sg:tags":[
        "church"
    ],
    "wof:name":"Mountain View United Church",
    "wof:placetype":"venue"
},
  "geometry": {"coordinates":[-64.805367,46.102791],"type":"Point"}
}