{
  "type": "Feature",
  "properties": {
    "addr:full":"22 Fisher St King City ON L7B 1G3",
    "addr:housenumber":"22",
    "addr:postcode":"l7b 1g3",
    "addr:street":"Fisher St",
    "iso:country":"CA",
    "sg:address":"22 Fisher St",
    "sg:city":"King City",
    "sg:classifiers":[
        {
            "category":"Professional",
            "subcategory":"Research",
            "type":"Services"
        }
    ],
    "sg:phone":"+1 905 833 1244",
    "sg:postcode":"L7B 1G3",
    "sg:province":"ON",
    "sg:tags":[
        "environmental",
        "ecological"
    ],
    "wof:name":"Lgl Ltd",
    "wof:placetype":"venue"
},
  "geometry": {"coordinates":[-79.52514600000001,43.928703],"type":"Point"}
}