{
  "type": "Feature",
  "properties": {
    "addr:full":"Calgary AB T3E 7L7",
    "addr:postcode":"t3e 7l7",
    "iso:country":"CA",
    "sg:city":"Calgary",
    "sg:classifiers":[
        {
            "category":"Social Services",
            "type":"Services"
        }
    ],
    "sg:phone":"+1 403 275 0258",
    "sg:postcode":"T3E 7L7",
    "sg:province":"AB",
    "sg:tags":[
        "organization",
        "welfare"
    ],
    "wof:name":"Community Kitchen Program",
    "wof:placetype":"venue"
},
  "geometry": {"coordinates":[-114.11779,51.016006],"type":"Point"}
}