{
  "type": "Feature",
  "properties": {
    "addr:full":"Fox Valley SK S0N 0V0",
    "addr:postcode":"s0n 0v0",
    "addr:street":"Fox Valley",
    "iso:country":"CA",
    "sg:city":"Fox Valley",
    "sg:classifiers":[
        {
            "category":"Wholesale",
            "subcategory":"Petroleum",
            "type":"Manufacturing & Wholesale Goods"
        }
    ],
    "sg:phone":"+1 306 666 4434",
    "sg:postcode":"S0N 0V0",
    "sg:province":"SK",
    "sg:tags":[
        "oil"
    ],
    "wof:name":"Petro-Canada Bulk",
    "wof:placetype":"venue"
},
  "geometry": {"coordinates":[-107.80336800000001,50.282124],"type":"Point"}
}