{
  "type": "Feature",
  "properties": {
    "addr:full":"2114 Rang Grand Saint-Charles-Sur-Richelieu QC J0H 2G0",
    "addr:housenumber":"2114",
    "addr:postcode":"j0h 2g0",
    "addr:street":"Rang Grand Saint-Charles-Sur-Richelieu",
    "iso:country":"CA",
    "sg:address":"2114 Rang Grand",
    "sg:city":"Saint-Charles-Sur-Richelieu",
    "sg:classifiers":[
        {
            "category":"Retail",
            "subcategory":"Auto Repair",
            "type":"Services"
        }
    ],
    "sg:phone":"+1 450 584 3962",
    "sg:postcode":"J0H 2G0",
    "sg:province":"QC",
    "sg:tags":[
        "body",
        "automobile",
        "painting"
    ],
    "wof:name":"Benoit Auto Carrosserie Enr",
    "wof:placetype":"venue"
},
  "geometry": {"coordinates":[-73.1184005737,45.6433868408],"type":"Point"}
}