{
  "type": "Feature",
  "properties": {
    "addr:full":"Winnipeg MB R2L 0W8",
    "addr:postcode":"r2l 0w8",
    "iso:country":"CA",
    "sg:city":"Winnipeg",
    "sg:classifiers":[
        {
            "category":"Retail",
            "subcategory":"Auto Repair",
            "type":"Services"
        }
    ],
    "sg:phone":"+1 204 661 1449",
    "sg:postcode":"R2L 0W8",
    "sg:province":"MB",
    "sg:tags":[
        "transmission"
    ],
    "wof:name":"Town Transmission",
    "wof:placetype":"venue"
},
  "geometry": {"coordinates":[-97.1095657349,49.9059371948],"type":"Point"}
}