{
  "type": "Feature",
  "properties": {
    "addr:full":"Brockville ON K6V 5V6",
    "addr:postcode":"k6v 5v6",
    "iso:country":"CA",
    "sg:city":"Brockville",
    "sg:classifiers":[
        {
            "category":"Wholesale",
            "subcategory":"Electrical",
            "type":"Manufacturing & Wholesale Goods"
        }
    ],
    "sg:phone":"+1 613 342 6999",
    "sg:postcode":"K6V 5V6",
    "sg:province":"ON",
    "sg:tags":[
        "sound",
        "equipment",
        "system"
    ],
    "wof:name":"Gerraudio Distribution Inc",
    "wof:placetype":"venue"
},
  "geometry": {"coordinates":[-75.69969940190001,44.6240653992],"type":"Point"}
}