{
  "type": "Feature",
  "properties": {
    "addr:full":"4156 Petrolia Line Petrolia ON N0N 1R0",
    "addr:housenumber":"4156",
    "addr:postcode":"n0n 1r0",
    "addr:street":"Petrolia Line",
    "iso:country":"CA",
    "sg:address":"4156 Petrolia Line",
    "sg:city":"Petrolia",
    "sg:classifiers":[
        {
            "category":"Professional",
            "subcategory":"Management & Consulting",
            "type":"Services"
        }
    ],
    "sg:phone":"+1 519 882 3542",
    "sg:postcode":"N0N 1R0",
    "sg:province":"ON",
    "sg:tags":[
        "consultant",
        "safety"
    ],
    "wof:name":"Environmental Accident Prtctn",
    "wof:placetype":"venue"
},
  "geometry": {"coordinates":[-82.14894099999999,42.882107],"type":"Point"}
}