{
  "type": "Feature",
  "properties": {
    "iso:country":"CA",
    "sg:city":"Blumenort",
    "sg:classifiers":[
        {
            "category":"Retail",
            "subcategory":"Auto Repair",
            "type":"Services"
        }
    ],
    "sg:phone":"+1 204 326 3155",
    "sg:postcode":"R0A 0C0",
    "sg:province":"MB",
    "sg:tags":[
        "truck"
    ],
    "wof:name":"Pbx Truck Svc",
    "wof:placetype":"venue"
},
  "geometry": {"coordinates":[-96.69017028810001,49.6042556763],"type":"Point"}
}