{
  "type": "Feature",
  "properties": {
    "addr:full":"Woodbridge ON L4L 1A6",
    "addr:postcode":"l4l 1a6",
    "iso:country":"CA",
    "sg:city":"Woodbridge",
    "sg:classifiers":[
        {
            "category":"Home & Garden",
            "subcategory":"Home Furnishings",
            "type":"Retail Goods"
        }
    ],
    "sg:phone":"+1 905 856 7979",
    "sg:postcode":"L4L 1A6",
    "sg:province":"ON",
    "sg:tags":[
        "tile",
        "bathroom",
        "fixture"
    ],
    "wof:name":"Canaroma International Inc",
    "wof:placetype":"venue"
},
  "geometry": {"coordinates":[-79.548607,43.794956],"type":"Point"}
}