{
  "type": "Feature",
  "properties": {
    "addr:full":"750 Norquay Dr Winkler MB R6W 4B9",
    "addr:housenumber":"750",
    "addr:postcode":"r6w 4b9",
    "addr:street":"Norquay Dr",
    "iso:country":"CA",
    "sg:address":"750 Norquay Dr",
    "sg:city":"Winkler",
    "sg:classifiers":[
        {
            "category":"Restaurant",
            "type":"Food & Drink"
        }
    ],
    "sg:phone":"+1 204 325 4143",
    "sg:postcode":"R6W 4B9",
    "sg:province":"MB",
    "wof:name":"Mc Donald's",
    "wof:placetype":"venue"
},
  "geometry": {"coordinates":[-97.9314422607,49.1902923584],"type":"Point"}
}