{
  "type": "Feature",
  "properties": {
    "addr:full":"Abbotsford BC V2S 2B1",
    "addr:postcode":"v2s 2b1",
    "iso:country":"CA",
    "sg:city":"Abbotsford",
    "sg:classifiers":[
        {
            "category":"Real Estate",
            "subcategory":"Real Estate Agent",
            "type":"Services"
        }
    ],
    "sg:phone":"+1 604 852 2778",
    "sg:postcode":"V2S 2B1",
    "sg:province":"BC",
    "sg:tags":[
        "management"
    ],
    "wof:name":"Central Valley Property Mgmt",
    "wof:placetype":"venue"
},
  "geometry": {"coordinates":[-122.306106567,49.0507545471],"type":"Point"}
}