{
  "type": "Feature",
  "properties": {
    "addr:full":"5411 Canotek Rd Gloucester ON K1J 9M3",
    "addr:housenumber":"5411",
    "addr:postcode":"k1j 9m3",
    "addr:street":"Canotek Rd",
    "iso:country":"CA",
    "sg:address":"5411 Canotek Rd",
    "sg:city":"Gloucester",
    "sg:classifiers":[
        {
            "category":"Building & Trades",
            "subcategory":"Electrical",
            "type":"Services"
        }
    ],
    "sg:phone":"+1 613 748 1615",
    "sg:postcode":"K1J 9M3",
    "sg:province":"ON",
    "sg:tags":[
        "electric",
        "contractor"
    ],
    "wof:name":"Lights R US",
    "wof:placetype":"venue"
},
  "geometry": {"coordinates":[-75.582184,45.457798],"type":"Point"}
}