{
  "type": "Feature",
  "properties": {
    "iso:country":"CA",
    "sg:address":"334 Rue DE LA Riviere",
    "sg:city":"Cowansville",
    "sg:classifiers":[
        {
            "category":"Retail",
            "subcategory":"Auto Repair",
            "type":"Services"
        }
    ],
    "sg:phone":"+1 450 263 2202",
    "sg:postcode":"J2K 1M8",
    "sg:province":"QC",
    "sg:tags":[
        "repairing",
        "automobile",
        "radiator"
    ],
    "wof:name":"Garage Jean Joachim & Fils",
    "wof:placetype":"venue"
},
  "geometry": {"coordinates":[-72.757774,45.206512],"type":"Point"}
}