{
  "type": "Feature",
  "properties": {
    "addr:full":"Drummondville QC J2B 1W5",
    "addr:postcode":"j2b 1w5",
    "iso:country":"CA",
    "sg:city":"Drummondville",
    "sg:classifiers":[
        {
            "category":"Personal",
            "subcategory":"Barber",
            "type":"Services"
        }
    ],
    "sg:phone":"+1 819 472 5979",
    "sg:postcode":"J2B 1W5",
    "sg:province":"QC",
    "wof:name":"Picotin, Denis",
    "wof:placetype":"venue"
},
  "geometry": {"coordinates":[-72.484207,45.874722],"type":"Point"}
}