{
  "type": "Feature",
  "properties": {
    "addr:full":"Niagara on the Lake ON L0S 1J0",
    "addr:postcode":"l0s 1j0",
    "iso:country":"CA",
    "sg:city":"Niagara on the Lake",
    "sg:classifiers":[
        {
            "category":"Building & Trades",
            "subcategory":"Plumbing",
            "type":"Services"
        }
    ],
    "sg:phone":"+1 905 468 7567",
    "sg:postcode":"L0S 1J0",
    "sg:province":"ON",
    "sg:tags":[
        "septic"
    ],
    "wof:name":"Star Pumping Svc",
    "wof:placetype":"venue"
},
  "geometry": {"coordinates":[-79.093323,43.210945],"type":"Point"}
}