{
  "type": "Feature",
  "properties": {
    "addr:full":"2755 Honey Harbour Rd Honey Harbour ON P0E 1E0",
    "addr:housenumber":"2755",
    "addr:postcode":"p0e 1e0",
    "addr:street":"Honey Harbour Rd",
    "iso:country":"CA",
    "sg:address":"2755 Honey Harbour Rd",
    "sg:city":"Honey Harbour",
    "sg:classifiers":[
        {
            "category":"Recreation",
            "subcategory":"Marina",
            "type":"Entertainment"
        }
    ],
    "sg:phone":"+1 705 756 2432",
    "sg:postcode":"P0E 1E0",
    "sg:province":"ON",
    "wof:name":"Admiral's Marina Inc",
    "wof:placetype":"venue"
},
  "geometry": {"coordinates":[-79.817673,44.870884],"type":"Point"}
}