{
  "type": "Feature",
  "properties": {
    "addr:full":"3815 Rue Saint-Jacques Montreal QC H4C 1H5",
    "addr:housenumber":"3815",
    "addr:postcode":"h4c 1h5",
    "addr:street":"Rue Saint-Jacques",
    "iso:country":"CA",
    "sg:address":"3815 Rue Saint-Jacques",
    "sg:city":"Montreal",
    "sg:classifiers":[
        {
            "category":"Autos & Motor Vehicles",
            "subcategory":"Fuel & Gas Station",
            "type":"Retail Goods"
        }
    ],
    "sg:phone":"+1 514 935 8456",
    "sg:postcode":"H4C 1H5",
    "sg:province":"QC",
    "sg:tags":[
        "repairing",
        "automobile",
        "oil"
    ],
    "wof:name":"George Garage Enr",
    "wof:placetype":"venue"
},
  "geometry": {"coordinates":[-73.58403800000001,45.479958],"type":"Point"}
}