{
  "type": "Feature",
  "properties": {
    "iso:country":"CA",
    "sg:city":"Calgary",
    "sg:classifiers":[
        {
            "category":"Health Services",
            "subcategory":"Doctor",
            "type":"Services"
        }
    ],
    "sg:phone":"+1 403 292 9555",
    "sg:postcode":"T2N 3P7",
    "sg:province":"AB",
    "sg:tags":[
        "physician",
        "surgeon"
    ],
    "wof:name":"Wagner, Garth A MD",
    "wof:placetype":"venue"
},
  "geometry": {"coordinates":[-114.09065246599999,51.0526199341],"type":"Point"}
}