{
  "type": "Feature",
  "properties": {
    "iso:country":"CA",
    "sg:city":"Thunder Bay",
    "sg:classifiers":[
        {
            "category":"Government",
            "subcategory":"Office",
            "type":"Public Place"
        }
    ],
    "sg:phone":"+1 807 684 4444",
    "sg:postcode":"P7B 6C7",
    "sg:province":"ON",
    "sg:tags":[
        "village"
    ],
    "wof:name":"Thunder Bay Community",
    "wof:placetype":"venue"
},
  "geometry": {"coordinates":[-89.24123382569999,48.4217414856],"type":"Point"}
}