{
  "type": "Feature",
  "properties": {
    "iso:country":"CA",
    "sg:city":"Orleans",
    "sg:classifiers":[
        {
            "category":"Health Services",
            "subcategory":"Health Practitioner",
            "type":"Services"
        }
    ],
    "sg:phone":"+1 613 834 9603",
    "sg:postcode":"K1C 1E9",
    "sg:province":"ON",
    "sg:tags":[
        "psychologist"
    ],
    "wof:name":"Orleans Psychological Ctr",
    "wof:placetype":"venue"
},
  "geometry": {"coordinates":[-75.527961731,45.4697952271],"type":"Point"}
}