{
  "type": "Feature",
  "properties": {
    "addr:full":"1220 138 Rte Neuville QC G0A 2R0",
    "addr:housenumber":"1220",
    "addr:postcode":"g0a 2r0",
    "addr:street":"138 Rte",
    "iso:country":"CA",
    "sg:address":"1220 138 Rte",
    "sg:city":"Neuville",
    "sg:classifiers":[
        {
            "category":"Food & Beverages",
            "subcategory":"Groceries & Convenience Stores",
            "type":"Retail Goods"
        }
    ],
    "sg:phone":"+1 418 876 2396",
    "sg:postcode":"G0A 2R0",
    "sg:province":"QC",
    "wof:name":"Depanneur Gaz Bar Sbl",
    "wof:placetype":"venue"
},
  "geometry": {"coordinates":[-71.58532700000001,46.696613],"type":"Point"}
}