{
  "type": "Feature",
  "properties": {
    "iso:country":"CA",
    "sg:address":"2340 Ontario St",
    "sg:city":"Oakville",
    "sg:classifiers":[
        {
            "category":"Recreation",
            "subcategory":"Marina",
            "type":"Entertainment"
        }
    ],
    "sg:phone":"+1 905 827 7575",
    "sg:postcode":"L6L 6P7",
    "sg:province":"ON",
    "wof:name":"Bronte Outer Harbour Marina",
    "wof:placetype":"venue"
},
  "geometry": {"coordinates":[-79.70597839360001,43.395488739],"type":"Point"}
}