{
  "type": "Feature",
  "properties": {
    "addr:full":"1221 Sundowner Rd Midland ON L4R 4K4",
    "addr:housenumber":"1221",
    "addr:postcode":"l4r 4k4",
    "addr:street":"Sundowner Rd",
    "iso:country":"CA",
    "sg:address":"1221 Sundowner Rd",
    "sg:city":"Midland",
    "sg:classifiers":[
        {
            "category":"Autos & Motor Vehicles",
            "subcategory":"Motorcycle Sales",
            "type":"Retail Goods"
        }
    ],
    "sg:phone":"+1 705 526 7500",
    "sg:postcode":"L4R 4K4",
    "sg:province":"ON",
    "sg:tags":[
        "scooter"
    ],
    "wof:name":"Amp Cycle & Sled Svc",
    "wof:placetype":"venue"
},
  "geometry": {"coordinates":[-79.9118652344,44.7341651917],"type":"Point"}
}