{
  "type": "Feature",
  "properties": {
    "addr:full":"2600 Eglinton Ave W York ON M6M 1T5",
    "addr:housenumber":"2600",
    "addr:postcode":"m6m 1t5",
    "addr:street":"Eglinton Ave W",
    "iso:country":"CA",
    "sg:address":"2600 Eglinton Ave W",
    "sg:city":"York",
    "sg:classifiers":[
        {
            "category":"Shopping",
            "subcategory":"Pharmacy",
            "type":"Retail Goods"
        }
    ],
    "sg:phone":"+1 416 651 6511",
    "sg:postcode":"M6M 1T5",
    "sg:province":"ON",
    "wof:name":"Medicine Shoppe",
    "wof:placetype":"venue"
},
  "geometry": {"coordinates":[-79.4733657837,43.6906700134],"type":"Point"}
}