{
  "type": "Feature",
  "properties": {
    "iso:country":"CA",
    "sg:city":"Pelee Island",
    "sg:classifiers":[
        {
            "category":"Travel",
            "subcategory":"Hotels & Motels",
            "type":"Entertainment"
        }
    ],
    "sg:phone":"+1 519 724 9994",
    "sg:postcode":"N0R 1M0",
    "sg:province":"ON",
    "wof:name":"Pelee Island Hotel & Pub",
    "wof:placetype":"venue"
},
  "geometry": {"coordinates":[-82.6893005371,41.7611923218],"type":"Point"}
}