{
  "type": "Feature",
  "properties": {
    "addr:full":"423 Stage Coach East Hill Brome QC J0E 1K0",
    "addr:housenumber":"423",
    "addr:postcode":"j0e 1k0",
    "addr:street":"Stage Coach East Hill",
    "iso:country":"CA",
    "sg:address":"423 Stage Coach East Hill",
    "sg:city":"Brome",
    "sg:classifiers":[
        {
            "category":"Communications",
            "subcategory":"Film & Video Production",
            "type":"Services"
        }
    ],
    "sg:phone":"+1 450 243 0298",
    "sg:postcode":"J0E 1K0",
    "sg:province":"QC",
    "sg:tags":[
        "television",
        "producer"
    ],
    "wof:name":"Productions Claude Godbout",
    "wof:placetype":"venue"
},
  "geometry": {"coordinates":[-72.572067,45.194027],"type":"Point"}
}