{
  "type": "Feature",
  "properties": {
    "addr:full":"100 Bayshore Dr Nepean ON K2B 8C1",
    "addr:housenumber":"100",
    "addr:postcode":"k2b 8c1",
    "addr:street":"Bayshore Dr",
    "iso:country":"CA",
    "sg:address":"100 Bayshore Dr",
    "sg:city":"Nepean",
    "sg:classifiers":[
        {
            "category":"Shopping",
            "subcategory":"Shoes",
            "type":"Retail Goods"
        }
    ],
    "sg:phone":"+1 613 820 2306",
    "sg:postcode":"K2B 8C1",
    "sg:province":"ON",
    "wof:name":"Transit Shoes",
    "wof:placetype":"venue"
},
  "geometry": {"coordinates":[-75.805092,45.349079],"type":"Point"}
}