{
  "type": "Feature",
  "properties": {
    "iso:country":"CA",
    "sg:address":"84 New Cumberland Rd",
    "sg:city":"Pleasantville",
    "sg:classifiers":[
        {
            "category":"Building & Trades",
            "subcategory":"Plumbing",
            "type":"Services"
        }
    ],
    "sg:phone":"+1 902 543 5501",
    "sg:postcode":"B0R 1G0",
    "sg:province":"NS",
    "sg:tags":[
        "contractor"
    ],
    "wof:name":"Dalton Jodrey Plumbing & Htg",
    "wof:placetype":"venue"
},
  "geometry": {"coordinates":[-64.43946800000001,44.333366],"type":"Point"}
}