{
  "type": "Feature",
  "properties": {
    "addr:full":"2530 42E Rue N Aubert-Gallion QC G5Y 5B7",
    "addr:housenumber":"2530",
    "addr:postcode":"g5y 5b7",
    "addr:street":"42E Rue N",
    "iso:country":"CA",
    "sg:address":"2530 42E Rue N",
    "sg:city":"Aubert-Gallion",
    "sg:classifiers":[
        {
            "category":"Home & Garden",
            "subcategory":"Household Appliances",
            "type":"Retail Goods"
        }
    ],
    "sg:phone":"+1 418 227 5345",
    "sg:postcode":"G5Y 5B7",
    "sg:province":"QC",
    "sg:tags":[
        "conditioning",
        "air",
        "system",
        "contractor"
    ],
    "wof:name":"Specialiste DE L'Electro Usage",
    "wof:placetype":"venue"
},
  "geometry": {"coordinates":[-70.71602630620001,46.116859436],"type":"Point"}
}