{
  "type": "Feature",
  "properties": {
    "iso:country":"CA",
    "sg:city":"Red Deer",
    "sg:classifiers":[
        {
            "category":"Retail",
            "subcategory":"Auto Rental",
            "type":"Services"
        }
    ],
    "sg:phone":"+1 403 347 5811",
    "sg:postcode":"T4R 2R1",
    "sg:province":"AB",
    "sg:tags":[
        "renting",
        "automobile",
        "truck"
    ],
    "wof:name":"National Car Rental",
    "wof:placetype":"venue"
},
  "geometry": {"coordinates":[-113.81796300000001,52.245926],"type":"Point"}
}