{
  "type": "Feature",
  "properties": {
    "addr:full":"125 Goulet St Winnipeg MB R2H 0R6",
    "addr:housenumber":"125",
    "addr:postcode":"r2h 0r6",
    "addr:street":"Goulet St",
    "iso:country":"CA",
    "sg:address":"125 Goulet St",
    "sg:city":"Winnipeg",
    "sg:classifiers":[
        {
            "category":"Banks & Credit Unions",
            "subcategory":"Bank",
            "type":"Services"
        }
    ],
    "sg:phone":"+1 204 988 5760",
    "sg:postcode":"R2H 0R6",
    "sg:province":"MB",
    "wof:name":"Royal Bank Financial Group",
    "wof:placetype":"venue"
},
  "geometry": {"coordinates":[-97.12241363530001,49.8824958801],"type":"Point"}
}