{
  "type": "Feature",
  "properties": {
    "iso:country":"CA",
    "sg:address":"7240 Boul Maurice-Duplessis",
    "sg:city":"Montreal",
    "sg:classifiers":[
        {
            "category":"Wholesale",
            "subcategory":"Office Equipment",
            "type":"Manufacturing & Wholesale Goods"
        }
    ],
    "sg:phone":"+1 514 643 3355",
    "sg:postcode":"H1E 4A7",
    "sg:province":"QC",
    "sg:tags":[
        "accounting",
        "bookkeeping",
        "system"
    ],
    "wof:name":"Varano, Vincent",
    "wof:placetype":"venue"
},
  "geometry": {"coordinates":[-73.60218,45.623589],"type":"Point"}
}