{
  "type": "Feature",
  "properties": {
    "addr:full":"Penticton BC V2A 5E9",
    "addr:postcode":"v2a 5e9",
    "iso:country":"CA",
    "sg:city":"Penticton",
    "sg:classifiers":[
        {
            "category":"Government",
            "subcategory":"Post Office",
            "type":"Public Place"
        }
    ],
    "sg:phone":"+1 250 492 8000",
    "sg:postcode":"V2A 5E9",
    "sg:province":"BC",
    "sg:tags":[
        "pharmacy"
    ],
    "wof:name":"Shoppers Drug Mart",
    "wof:placetype":"venue"
},
  "geometry": {"coordinates":[-119.586494,49.484982],"type":"Point"}
}