{
  "type": "Feature",
  "properties": {
    "addr:full":"25 Rue Laurier Hull QC J8X 4C8",
    "addr:housenumber":"25",
    "addr:postcode":"j8x 4c8",
    "addr:street":"Rue Laurier",
    "iso:country":"CA",
    "sg:address":"25 Rue Laurier",
    "sg:city":"Hull",
    "sg:classifiers":[
        {
            "category":"Government",
            "subcategory":"Office",
            "type":"Public Place"
        }
    ],
    "sg:phone":"+1 819 595 2002",
    "sg:postcode":"J8X 4C8",
    "sg:province":"QC",
    "sg:tags":[
        "city",
        "hall"
    ],
    "wof:name":"Hotel DE Ville",
    "wof:placetype":"venue"
},
  "geometry": {"coordinates":[-75.710655,45.427956],"type":"Point"}
}