{
  "type": "Feature",
  "properties": {
    "addr:full":"215 Rue Des Pins Sainte-Sabine QC J0J 2B0",
    "addr:housenumber":"215",
    "addr:postcode":"j0j 2b0",
    "addr:street":"Rue Des Pins",
    "iso:country":"CA",
    "sg:address":"215 Rue Des Pins",
    "sg:city":"Sainte-Sabine",
    "sg:classifiers":[
        {
            "category":"Building & Trades",
            "subcategory":"Landscaping Services",
            "type":"Services"
        }
    ],
    "sg:phone":"+1 450 293 5080",
    "sg:postcode":"J0J 2B0",
    "sg:province":"QC",
    "sg:tags":[
        "landscape",
        "contractor"
    ],
    "wof:name":"Paysagement Harbec Inc",
    "wof:placetype":"venue"
},
  "geometry": {"coordinates":[-72.988907,45.245949],"type":"Point"}
}