{
  "type": "Feature",
  "properties": {
    "addr:full":"2 Corby Rd # 1 Markham ON L3R 8A9",
    "addr:housenumber":"2",
    "addr:postcode":"l3r 8a9",
    "addr:street":"Corby Rd # 1",
    "iso:country":"CA",
    "sg:address":"2 Corby Rd # 1",
    "sg:city":"Markham",
    "sg:classifiers":[
        {
            "category":"Food & Beverages",
            "subcategory":"Groceries & Convenience Stores",
            "type":"Retail Goods"
        }
    ],
    "sg:phone":"+1 905 940 3347",
    "sg:postcode":"L3R 8A9",
    "sg:province":"ON",
    "sg:tags":[
        "grocer"
    ],
    "wof:name":"Grocer Counter",
    "wof:placetype":"venue"
},
  "geometry": {"coordinates":[-79.344833374,43.8604736328],"type":"Point"}
}