{
  "type": "Feature",
  "properties": {
    "iso:country":"CA",
    "sg:address":"102 N Railway Ave",
    "sg:city":"Deloraine",
    "sg:classifiers":[
        {
            "category":"Banks & Credit Unions",
            "subcategory":"Bank",
            "type":"Services"
        }
    ],
    "sg:phone":"+1 204 747 3012",
    "sg:postcode":"R0M 0M0",
    "sg:province":"MB",
    "wof:name":"Royal Bank Financial Group",
    "wof:placetype":"venue"
},
  "geometry": {"coordinates":[-100.497436523,49.1933364868],"type":"Point"}
}