{
  "type": "Feature",
  "properties": {
    "iso:country":"CA",
    "sg:address":"150 Mill St",
    "sg:city":"Durham",
    "sg:classifiers":[
        {
            "category":"Professional",
            "subcategory":"Lawyer & Legal Services",
            "type":"Services"
        }
    ],
    "sg:phone":"+1 519 369 6931",
    "sg:postcode":"N0G 1R0",
    "sg:province":"ON",
    "sg:tags":[
        "attorney"
    ],
    "wof:name":"Dunlop Johnson & Pust",
    "wof:placetype":"venue"
},
  "geometry": {"coordinates":[-80.8176193237,44.1770248413],"type":"Point"}
}