{
  "type": "Feature",
  "properties": {
    "addr:full":"London ON N6A 3E6",
    "addr:postcode":"n6a 3e6",
    "iso:country":"CA",
    "sg:city":"London",
    "sg:classifiers":[
        {
            "category":"Real Estate",
            "subcategory":"Real Estate Agent",
            "type":"Services"
        }
    ],
    "sg:phone":"+1 519 645 6666",
    "sg:postcode":"N6A 3E6",
    "sg:province":"ON",
    "sg:tags":[
        "management"
    ],
    "wof:name":"Farhi Holdings Corp",
    "wof:placetype":"venue"
},
  "geometry": {"coordinates":[-81.250443,42.986206],"type":"Point"}
}