{
  "type": "Feature",
  "properties": {
    "addr:full":"7 Beaufort St London ON N6G 1A5",
    "addr:housenumber":"7",
    "addr:postcode":"n6g 1a5",
    "addr:street":"Beaufort St",
    "iso:country":"CA",
    "sg:address":"7 Beaufort St",
    "sg:city":"London",
    "sg:classifiers":[
        {
            "category":"Education",
            "subcategory":"School",
            "type":"Public Place"
        }
    ],
    "sg:phone":"+1 519 858 8862",
    "sg:postcode":"N6G 1A5",
    "sg:province":"ON",
    "wof:name":"London Waldorf School",
    "wof:placetype":"venue"
},
  "geometry": {"coordinates":[-81.2617034912,42.9955024719],"type":"Point"}
}