{
  "type": "Feature",
  "properties": {
    "addr:full":"2 Boul Tache O Montmagny QC G5V 3A1",
    "addr:housenumber":"2",
    "addr:postcode":"g5v 3a1",
    "addr:street":"Boul Tache O",
    "iso:country":"CA",
    "sg:address":"2 Boul Tache O",
    "sg:city":"Montmagny",
    "sg:classifiers":[
        {
            "category":"Retail",
            "subcategory":"Auto Repair",
            "type":"Services"
        }
    ],
    "sg:phone":"+1 418 248 3634",
    "sg:postcode":"G5V 3A1",
    "sg:province":"QC",
    "sg:tags":[
        "repairing",
        "automobile",
        "wrecker"
    ],
    "wof:name":"Garage Corriveau Esso",
    "wof:placetype":"venue"
},
  "geometry": {"coordinates":[-70.56343099999999,46.981506],"type":"Point"}
}