{
  "type": "Feature",
  "properties": {
    "addr:full":"175 Lahr Dr Belleville ON K8N 5S2",
    "addr:housenumber":"175",
    "addr:postcode":"k8n 5s2",
    "addr:street":"Lahr Dr",
    "iso:country":"CA",
    "sg:address":"175 Lahr Dr",
    "sg:city":"Belleville",
    "sg:classifiers":[
        {
            "category":"Shopping",
            "subcategory":"Computers & Home Electronics",
            "type":"Retail Goods"
        }
    ],
    "sg:phone":"+1 613 966 6321",
    "sg:postcode":"K8N 5S2",
    "sg:province":"ON",
    "sg:tags":[
        "equipment",
        "dealer"
    ],
    "wof:name":"Office Equipment Digital Sltns",
    "wof:placetype":"venue"
},
  "geometry": {"coordinates":[-77.380928,44.193409],"type":"Point"}
}