{
  "type": "Feature",
  "properties": {
    "addr:full":"195 Wellington St # 7 Bracebridge ON P1L 1C2",
    "addr:housenumber":"195",
    "addr:postcode":"p1l 1c2",
    "addr:street":"Wellington St # 7",
    "iso:country":"CA",
    "sg:address":"195 Wellington St # 7",
    "sg:city":"Bracebridge",
    "sg:classifiers":[
        {
            "category":"Home & Garden",
            "subcategory":"Furniture",
            "type":"Retail Goods"
        }
    ],
    "sg:phone":"+1 705 645 8183",
    "sg:postcode":"P1L 1C2",
    "sg:province":"ON",
    "wof:name":"Muskoka Furniture Outlet",
    "wof:placetype":"venue"
},
  "geometry": {"coordinates":[-79.319237,45.039101],"type":"Point"}
}