{
  "type": "Feature",
  "properties": {
    "iso:country":"CA",
    "sg:city":"Georgetown",
    "sg:classifiers":[
        {
            "category":"Personal",
            "subcategory":"Beauty Salon",
            "type":"Services"
        }
    ],
    "sg:phone":"+1 905 873 7960",
    "sg:postcode":"L7G 4G4",
    "sg:province":"ON",
    "wof:name":"Salon Marcel",
    "wof:placetype":"venue"
},
  "geometry": {"coordinates":[-79.89361572270001,43.6423912048],"type":"Point"}
}