{
  "type": "Feature",
  "properties": {
    "addr:full":"19780 Fraser Hwy Langley BC V3A 4C9",
    "addr:housenumber":"19780",
    "addr:postcode":"v3a 4c9",
    "addr:street":"Fraser Hwy",
    "iso:country":"CA",
    "sg:address":"19780 Fraser Hwy",
    "sg:city":"Langley",
    "sg:classifiers":[
        {
            "category":"Restaurant",
            "type":"Food & Drink"
        }
    ],
    "sg:phone":"+1 604 514 1820",
    "sg:postcode":"V3A 4C9",
    "sg:province":"BC",
    "wof:name":"Mc Donald's",
    "wof:placetype":"venue"
},
  "geometry": {"coordinates":[-122.676132,49.112034],"type":"Point"}
}