{
  "type": "Feature",
  "properties": {
    "addr:full":"1185 Lakeshore Rd E Mississauga ON L5E 1G1",
    "addr:housenumber":"1185",
    "addr:postcode":"l5e 1g1",
    "addr:street":"Lakeshore Rd E",
    "iso:country":"CA",
    "sg:address":"1185 Lakeshore Rd E",
    "sg:city":"Mississauga",
    "sg:classifiers":[
        {
            "category":"Building & Trades",
            "subcategory":"Construction",
            "type":"Services"
        }
    ],
    "sg:phone":"+1 905 274 0770",
    "sg:postcode":"L5E 1G1",
    "sg:province":"ON",
    "sg:tags":[
        "contractor"
    ],
    "wof:name":"Napev Construction Ltd",
    "wof:placetype":"venue"
},
  "geometry": {"coordinates":[-79.5550689697,43.5805892944],"type":"Point"}
}