{
  "type": "Feature",
  "properties": {
    "iso:country":"CA",
    "sg:address":"425 Boul Cure-Poirier O",
    "sg:city":"Longueuil",
    "sg:classifiers":[
        {
            "category":"Shopping",
            "subcategory":"Pharmacy",
            "type":"Retail Goods"
        }
    ],
    "sg:phone":"+1 450 679 1296",
    "sg:postcode":"J4J 2H3",
    "sg:province":"QC",
    "wof:name":"Pharmacie Le Thi C",
    "wof:placetype":"venue"
},
  "geometry": {"coordinates":[-73.4793395996,45.5340232849],"type":"Point"}
}