{
  "type": "Feature",
  "properties": {
    "addr:full":"Delta BC V4K 2X7",
    "addr:postcode":"v4k 2x7",
    "iso:country":"CA",
    "sg:city":"Delta",
    "sg:classifiers":[
        {
            "category":"Government",
            "subcategory":"Post Office",
            "type":"Public Place"
        }
    ],
    "sg:phone":"+1 604 946 4555",
    "sg:postcode":"V4K 2X7",
    "sg:province":"BC",
    "wof:name":"Pharmasave",
    "wof:placetype":"venue"
},
  "geometry": {"coordinates":[-123.08367200000001,49.091202],"type":"Point"}
}