{
  "type": "Feature",
  "properties": {
    "addr:full":"2915 Portland Dr Oakville ON L6H 5S4",
    "addr:housenumber":"2915",
    "addr:postcode":"l6h 5s4",
    "addr:street":"Portland Dr",
    "iso:country":"CA",
    "sg:address":"2915 Portland Dr",
    "sg:city":"Oakville",
    "sg:classifiers":[
        {
            "category":"Manufacturing",
            "subcategory":"Tools & Machinery",
            "type":"Manufacturing & Wholesale Goods"
        }
    ],
    "sg:phone":"+1 905 829 0099",
    "sg:postcode":"L6H 5S4",
    "sg:province":"ON",
    "sg:tags":[
        "machine",
        "shop"
    ],
    "wof:name":"Coordinate Industries Ltd",
    "wof:placetype":"venue"
},
  "geometry": {"coordinates":[-79.680519,43.517551],"type":"Point"}
}