{
  "type": "Feature",
  "properties": {
    "addr:full":"Abbotsford BC V2T 1W8",
    "addr:postcode":"v2t 1w8",
    "iso:country":"CA",
    "sg:city":"Abbotsford",
    "sg:classifiers":[
        {
            "category":"Personal",
            "subcategory":"Beauty Salon",
            "type":"Services"
        }
    ],
    "sg:phone":"+1 604 556 5334",
    "sg:postcode":"V2T 1W8",
    "sg:province":"BC",
    "wof:name":"Tip Top Hair Studio",
    "wof:placetype":"venue"
},
  "geometry": {"coordinates":[-122.337455749,49.0495910645],"type":"Point"}
}