{
  "type": "Feature",
  "properties": {
    "addr:full":"251 Cairncroft Rd Oakville ON L6J 4M4",
    "addr:housenumber":"251",
    "addr:postcode":"l6j 4m4",
    "addr:street":"Cairncroft Rd",
    "iso:country":"CA",
    "sg:address":"251 Cairncroft Rd",
    "sg:city":"Oakville",
    "sg:classifiers":[
        {
            "category":"Professional",
            "subcategory":"Management & Consulting",
            "type":"Services"
        }
    ],
    "sg:phone":"+1 905 842 6766",
    "sg:postcode":"L6J 4M4",
    "sg:province":"ON",
    "sg:tags":[
        "advisory",
        "financial",
        "business",
        "consultant"
    ],
    "wof:name":"Network Research Inc",
    "wof:placetype":"venue"
},
  "geometry": {"coordinates":[-79.65509,43.466221],"type":"Point"}
}