{
  "type": "Feature",
  "properties": {
    "addr:full":"198 North St Bridgewater NS B4V 2V6",
    "addr:housenumber":"198",
    "addr:postcode":"b4v 2v6",
    "addr:street":"North St",
    "iso:country":"CA",
    "sg:address":"198 North St",
    "sg:city":"Bridgewater",
    "sg:classifiers":[
        {
            "category":"Home & Garden",
            "subcategory":"Mobile Homes",
            "type":"Retail Goods"
        }
    ],
    "sg:phone":"+1 902 543 9465",
    "sg:postcode":"B4V 2V6",
    "sg:province":"NS",
    "sg:tags":[
        "building"
    ],
    "wof:name":"Kent Homes Ltd",
    "wof:placetype":"venue"
},
  "geometry": {"coordinates":[-64.52209499999999,44.389061],"type":"Point"}
}