{
  "type": "Feature",
  "properties": {
    "iso:country":"CA",
    "sg:city":"Cochrane",
    "sg:classifiers":[
        {
            "category":"Professional",
            "subcategory":"Business Services",
            "type":"Services"
        }
    ],
    "sg:phone":"+1 705 272 2507",
    "sg:postcode":"P0L 1C0",
    "sg:province":"ON",
    "sg:tags":[
        "searcher",
        "record"
    ],
    "wof:name":"Northern Research",
    "wof:placetype":"venue"
},
  "geometry": {"coordinates":[-81.02895355219999,49.0652198792],"type":"Point"}
}