{
  "type": "Feature",
  "properties": {
    "addr:full":"57 Windy Golf Way North York ON M3C 3A6",
    "addr:housenumber":"57",
    "addr:postcode":"m3c 3a6",
    "addr:street":"Golf Way",
    "iso:country":"CA",
    "sg:address":"57 Windy Golf Way",
    "sg:city":"North York",
    "sg:classifiers":[
        {
            "category":"Building & Trades",
            "subcategory":"Electrical",
            "type":"Services"
        }
    ],
    "sg:phone":"+1 416 429 1316",
    "sg:postcode":"M3C 3A6",
    "sg:province":"ON",
    "sg:tags":[
        "electric",
        "contractor"
    ],
    "wof:name":"Stumer Electric Ltd",
    "wof:placetype":"venue"
},
  "geometry": {"coordinates":[-79.325012207,43.7171859741],"type":"Point"}
}