{
  "type": "Feature",
  "properties": {
    "addr:full":"2075 Plessis Rd Winnipeg MB R3W 1S4",
    "addr:housenumber":"2075",
    "addr:postcode":"r3w 1s4",
    "addr:street":"Plessis Rd",
    "iso:country":"CA",
    "sg:address":"2075 Plessis Rd",
    "sg:city":"Winnipeg",
    "sg:classifiers":[
        {
            "category":"Retail",
            "subcategory":"Auto Repair",
            "type":"Services"
        }
    ],
    "sg:phone":"+1 204 222 5313",
    "sg:postcode":"R3W 1S4",
    "sg:province":"MB",
    "sg:tags":[
        "body",
        "automobile",
        "painting"
    ],
    "wof:name":"Litwin Auto Sales & Autobody",
    "wof:placetype":"venue"
},
  "geometry": {"coordinates":[-97.025223,49.91663],"type":"Point"}
}