{
  "type": "Feature",
  "properties": {
    "addr:full":"Vancouver BC V6C 1B4",
    "addr:postcode":"v6c 1b4",
    "iso:country":"CA",
    "sg:city":"Vancouver",
    "sg:classifiers":[
        {
            "category":"Banks & Credit Unions",
            "subcategory":"Bank",
            "type":"Services"
        }
    ],
    "sg:phone":"+1 604 708 7877",
    "sg:postcode":"V6C 1B4",
    "sg:province":"BC",
    "sg:tags":[
        "broker",
        "foreign",
        "dealer",
        "exchange"
    ],
    "wof:name":"Citizens Bank of Canada",
    "wof:placetype":"venue"
},
  "geometry": {"coordinates":[-123.11481475799999,49.2861862183],"type":"Point"}
}