{
  "type": "Feature",
  "properties": {
    "addr:full":"3305 32 St NE Calgary AB T1Y 5X7",
    "addr:housenumber":"3305",
    "addr:postcode":"t1y 5x7",
    "addr:street":"32 St Ne",
    "iso:country":"CA",
    "sg:address":"3305 32 St NE",
    "sg:city":"Calgary",
    "sg:classifiers":[
        {
            "category":"Autos & Motor Vehicles",
            "subcategory":"Automobile Sales",
            "type":"Retail Goods"
        }
    ],
    "sg:phone":"+1 403 291 2111",
    "sg:postcode":"T1Y 5X7",
    "sg:province":"AB",
    "sg:tags":[
        "car",
        "dealer"
    ],
    "wof:name":"Stampede Lexus Toyota",
    "wof:placetype":"venue"
},
  "geometry": {"coordinates":[-113.98882293699999,51.0818099976],"type":"Point"}
}