{
  "type": "Feature",
  "properties": {
    "addr:full":"991 Boul Pierre-Bertrand Vanier QC G1M 2E8",
    "addr:housenumber":"991",
    "addr:postcode":"g1m 2e8",
    "addr:street":"Boul Pierre-Bertrand",
    "iso:country":"CA",
    "sg:address":"991 Boul Pierre-Bertrand",
    "sg:city":"Vanier",
    "sg:classifiers":[
        {
            "category":"Manufacturing",
            "subcategory":"Signs",
            "type":"Manufacturing & Wholesale Goods"
        }
    ],
    "sg:phone":"+1 418 527 2476",
    "sg:postcode":"G1M 2E8",
    "sg:province":"QC",
    "sg:tags":[
        "painter"
    ],
    "wof:name":"Autocollant Imagemo",
    "wof:placetype":"venue"
},
  "geometry": {"coordinates":[-71.275711,46.827316],"type":"Point"}
}