{
  "type": "Feature",
  "properties": {
    "iso:country":"CA",
    "sg:city":"Vancouver",
    "sg:classifiers":[
        {
            "category":"Professional",
            "subcategory":"Management & Consulting",
            "type":"Services"
        }
    ],
    "sg:phone":"+1 604 682 8844",
    "sg:postcode":"V6G 2S6",
    "sg:province":"BC",
    "sg:tags":[
        "consultant",
        "business"
    ],
    "wof:name":"Big Picture Inc",
    "wof:placetype":"venue"
},
  "geometry": {"coordinates":[-123.128471,49.290051],"type":"Point"}
}