{
  "type": "Feature",
  "properties": {
    "addr:full":"110 Boteler St Ottawa ON K1N 8W8",
    "addr:housenumber":"110",
    "addr:postcode":"k1n 8w8",
    "addr:street":"Boteler St",
    "iso:country":"CA",
    "sg:address":"110 Boteler St",
    "sg:city":"Ottawa",
    "sg:classifiers":[
        {
            "category":"Real Estate",
            "subcategory":"Real Estate Operator",
            "type":"Services"
        }
    ],
    "sg:phone":"+1 613 241 5115",
    "sg:postcode":"K1N 8W8",
    "sg:province":"ON",
    "sg:tags":[
        "apartment"
    ],
    "wof:name":"Gatineau View Apartments",
    "wof:placetype":"venue"
},
  "geometry": {"coordinates":[-75.696594,45.434441],"type":"Point"}
}