{
  "type": "Feature",
  "properties": {
    "iso:country":"CA",
    "sg:address":"100 Caroline St S",
    "sg:city":"Waterloo",
    "sg:classifiers":[
        {
            "category":"Personal",
            "subcategory":"Beauty Salon",
            "type":"Services"
        }
    ],
    "sg:phone":"+1 519 743 4093",
    "sg:postcode":"N2L 1X5",
    "sg:province":"ON",
    "wof:name":"House of Elegance",
    "wof:placetype":"venue"
},
  "geometry": {"coordinates":[-80.521805,43.460712],"type":"Point"}
}