{
  "type": "Feature",
  "properties": {
    "addr:full":"3203 97 St NW Edmonton AB T6N 1B7",
    "addr:housenumber":"3203",
    "addr:postcode":"t6n 1b7",
    "addr:street":"97 St Nw",
    "iso:country":"CA",
    "sg:address":"3203 97 St NW",
    "sg:city":"Edmonton",
    "sg:classifiers":[
        {
            "category":"Wholesale",
            "subcategory":"Machinery & Supplies",
            "type":"Manufacturing & Wholesale Goods"
        }
    ],
    "sg:phone":"+1 780 499 1616",
    "sg:postcode":"T6N 1B7",
    "sg:province":"AB",
    "sg:tags":[
        "printer",
        "cartridge",
        "furniture"
    ],
    "wof:name":"Tonerman of Laser Networks",
    "wof:placetype":"venue"
},
  "geometry": {"coordinates":[-113.479446,53.464401],"type":"Point"}
}