{
  "type": "Feature",
  "properties": {
    "addr:full":"480 Rue Lafontaine Riviere-Du-Loup QC G5R 3C4",
    "addr:housenumber":"480",
    "addr:postcode":"g5r 3c4",
    "addr:street":"Rue Lafontaine",
    "iso:country":"CA",
    "sg:address":"480 Rue Lafontaine",
    "sg:city":"Riviere-Du-Loup",
    "sg:classifiers":[
        {
            "category":"Wholesale",
            "subcategory":"Stationery",
            "type":"Manufacturing & Wholesale Goods"
        }
    ],
    "sg:phone":"+1 418 862 6454",
    "sg:postcode":"G5R 3C4",
    "sg:province":"QC",
    "sg:tags":[
        "sanitary",
        "product",
        "supply"
    ],
    "wof:name":"Perscott Sm Inc",
    "wof:placetype":"venue"
},
  "geometry": {"coordinates":[-69.5311508179,47.8280754089],"type":"Point"}
}