{
  "type": "Feature",
  "properties": {
    "addr:full":"654 Rue Farrell Drummondville QC J2C 7Y7",
    "addr:housenumber":"654",
    "addr:postcode":"j2c 7y7",
    "addr:street":"Rue Farrell",
    "iso:country":"CA",
    "sg:address":"654 Rue Farrell",
    "sg:city":"Drummondville",
    "sg:classifiers":[
        {
            "category":"Wholesale",
            "subcategory":"Electrical",
            "type":"Manufacturing & Wholesale Goods"
        }
    ],
    "sg:phone":"+1 819 477 6112",
    "sg:postcode":"J2C 7Y7",
    "sg:province":"QC",
    "sg:tags":[
        "equipment",
        "electric",
        "supply"
    ],
    "wof:name":"Westburne",
    "wof:placetype":"venue"
},
  "geometry": {"coordinates":[-72.52159899999999,45.887604],"type":"Point"}
}