{
  "type": "Feature",
  "properties": {
    "addr:full":"Labelle QC J0T 1H0",
    "addr:postcode":"j0t 1h0",
    "iso:country":"CA",
    "sg:city":"Labelle",
    "sg:classifiers":[
        {
            "category":"Real Estate",
            "subcategory":"Real Estate Agent",
            "type":"Services"
        }
    ],
    "sg:phone":"+1 819 686 2836",
    "sg:postcode":"J0T 1H0",
    "sg:province":"QC",
    "wof:name":"Immeubles Laurentides",
    "wof:placetype":"venue"
},
  "geometry": {"coordinates":[-74.7340927124,46.2802848816],"type":"Point"}
}