{
  "type": "Feature",
  "properties": {
    "addr:full":"Le Gardeur QC J5Z 3B5",
    "addr:postcode":"j5z 3b5",
    "addr:street":"Le Gardeur",
    "iso:country":"CA",
    "sg:city":"Le Gardeur",
    "sg:classifiers":[
        {
            "category":"Insurance",
            "subcategory":"Insurance Agent",
            "type":"Services"
        }
    ],
    "sg:phone":"+1 450 581 5840",
    "sg:postcode":"J5Z 3B5",
    "sg:province":"QC",
    "wof:name":"Jette Picard & Assoc Inc",
    "wof:placetype":"venue"
},
  "geometry": {"coordinates":[-73.4611740112,45.7585067749],"type":"Point"}
}