{
  "type": "Feature",
  "properties": {
    "iso:country":"CA",
    "sg:city":"Bancroft",
    "sg:classifiers":[
        {
            "category":"Building & Trades",
            "subcategory":"Construction",
            "type":"Services"
        }
    ],
    "sg:phone":"+1 613 332 4766",
    "sg:postcode":"K0L 1C0",
    "sg:province":"ON",
    "sg:tags":[
        "contractor"
    ],
    "wof:name":"Designer Kitchen CO",
    "wof:placetype":"venue"
},
  "geometry": {"coordinates":[-77.8866195679,45.0704307556],"type":"Point"}
}