{
  "type": "Feature",
  "properties": {
    "addr:full":"St-Sauveur-Des-Monts QC J0R 1R6",
    "addr:postcode":"j0r 1r6",
    "iso:country":"CA",
    "sg:city":"St-Sauveur-Des-Monts",
    "sg:classifiers":[
        {
            "category":"Restaurant",
            "type":"Food & Drink"
        }
    ],
    "sg:phone":"+1 450 227 4455",
    "sg:postcode":"J0R 1R6",
    "sg:province":"QC",
    "wof:name":"Nettoyeur Des Monts",
    "wof:placetype":"venue"
},
  "geometry": {"coordinates":[-74.154449,45.892063],"type":"Point"}
}