{
  "type": "Feature",
  "properties": {
    "iso:country":"CA",
    "sg:address":"530 Rue Duhamel",
    "sg:city":"Saint-Lazare",
    "sg:classifiers":[
        {
            "category":"Home & Garden",
            "subcategory":"Building Materials",
            "type":"Retail Goods"
        }
    ],
    "sg:phone":"+1 450 424 0551",
    "sg:postcode":"J7T 2A8",
    "sg:province":"QC",
    "sg:tags":[
        "glass",
        "window",
        "plate"
    ],
    "wof:name":"Vitrerie Gms",
    "wof:placetype":"venue"
},
  "geometry": {"coordinates":[-74.0942153931,45.3840637207],"type":"Point"}
}