{
  "type": "Feature",
  "properties": {
    "addr:full":"1150 Park St Regina SK S4N 4Y9",
    "addr:housenumber":"1150",
    "addr:postcode":"s4n 4y9",
    "addr:street":"Park St",
    "iso:country":"CA",
    "sg:address":"1150 Park St",
    "sg:city":"Regina",
    "sg:classifiers":[
        {
            "category":"Wholesale",
            "subcategory":"Construction Materials",
            "type":"Manufacturing & Wholesale Goods"
        }
    ],
    "sg:phone":"+1 306 789 9777",
    "sg:postcode":"S4N 4Y9",
    "sg:province":"SK",
    "sg:tags":[
        "siding",
        "fence",
        "contractor"
    ],
    "wof:name":"Bar-T Constr & Prestainer Ltd",
    "wof:placetype":"venue"
},
  "geometry": {"coordinates":[-104.572525024,50.4604568481],"type":"Point"}
}