{
  "type": "Feature",
  "properties": {
    "iso:country":"CA",
    "sg:city":"St Catharines",
    "sg:classifiers":[
        {
            "category":"Restaurant",
            "type":"Food & Drink"
        }
    ],
    "sg:phone":"+1 905 687 9774",
    "sg:postcode":"L2R 3H7",
    "sg:province":"ON",
    "wof:name":"Cool Moose Cafe",
    "wof:placetype":"venue"
},
  "geometry": {"coordinates":[-79.246429,43.158352],"type":"Point"}
}