{
  "type": "Feature",
  "properties": {
    "addr:full":"St Catharines ON L2R 3H7",
    "addr:postcode":"l2r 3h7",
    "iso:country":"CA",
    "sg:city":"St Catharines",
    "sg:classifiers":[
        {
            "category":"Restaurant",
            "type":"Food & Drink"
        }
    ],
    "sg:phone":"+1 905 687 9774",
    "sg:postcode":"L2R 3H7",
    "sg:province":"ON",
    "wof:name":"Cool Moose Cafe",
    "wof:placetype":"venue"
},
  "geometry": {"coordinates":[-79.24642900000001,43.158352],"type":"Point"}
}