{
  "type": "Feature",
  "properties": {
    "addr:full":"320 Rue Abraham-Martin Quebec QC G1K 8N2",
    "addr:housenumber":"320",
    "addr:postcode":"g1k 8n2",
    "addr:street":"Rue Abraham-Martin",
    "iso:country":"CA",
    "sg:address":"320 Rue Abraham-Martin",
    "sg:city":"Quebec",
    "sg:classifiers":[
        {
            "category":"Shopping",
            "subcategory":"Tobacco",
            "type":"Retail Goods"
        }
    ],
    "sg:phone":"+1 418 525 4850",
    "sg:postcode":"G1K 8N2",
    "sg:province":"QC",
    "sg:tags":[
        "cigarette",
        "cigar",
        "dealer"
    ],
    "wof:name":"Tabatout",
    "wof:placetype":"venue"
},
  "geometry": {"coordinates":[-71.212563,46.817669],"type":"Point"}
}