{
  "type": "Feature",
  "properties": {
    "addr:full":"8255 Av Mountain Sights Montreal QC H4P 2B5",
    "addr:housenumber":"8255",
    "addr:postcode":"h4p 2b5",
    "addr:street":"Av Mountain Sights",
    "iso:country":"CA",
    "sg:address":"8255 Av Mountain Sights",
    "sg:city":"Montreal",
    "sg:classifiers":[
        {
            "category":"Professional",
            "subcategory":"Business Services",
            "type":"Services"
        }
    ],
    "sg:phone":"+1 514 341 2111",
    "sg:postcode":"H4P 2B5",
    "sg:province":"QC",
    "sg:tags":[
        "telemarketing"
    ],
    "wof:name":"Global Paper Supplies",
    "wof:placetype":"venue"
},
  "geometry": {"coordinates":[-73.657951,45.50066],"type":"Point"}
}