{
  "type": "Feature",
  "properties": {
    "iso:country":"CA",
    "sg:address":"140 Christina St N",
    "sg:city":"Sarnia",
    "sg:classifiers":[
        {
            "category":"Home & Garden",
            "subcategory":"Furniture",
            "type":"Retail Goods"
        }
    ],
    "sg:phone":"+1 519 344 1174",
    "sg:postcode":"N7T 5T9",
    "sg:province":"ON",
    "wof:name":"Taylor's Furniture Store Ltd",
    "wof:placetype":"venue"
},
  "geometry": {"coordinates":[-82.407242,42.971958],"type":"Point"}
}