{
  "type": "Feature",
  "properties": {
    "addr:full":"Nanaimo BC V9R 5H9",
    "addr:postcode":"v9r 5h9",
    "iso:country":"CA",
    "sg:city":"Nanaimo",
    "sg:classifiers":[
        {
            "category":"Professional",
            "subcategory":"Lawyer & Legal Services",
            "type":"Services"
        }
    ],
    "sg:phone":"+1 250 753 1891",
    "sg:postcode":"V9R 5H9",
    "sg:province":"BC",
    "sg:tags":[
        "attorney"
    ],
    "wof:name":"Hertzberg, A Peter",
    "wof:placetype":"venue"
},
  "geometry": {"coordinates":[-123.937073,49.16851],"type":"Point"}
}