{
  "type": "Feature",
  "properties": {
    "iso:country":"CA",
    "sg:address":"1337 King St N",
    "sg:city":"St Jacobs",
    "sg:classifiers":[
        {
            "category":"Shopping",
            "subcategory":"Shoes",
            "type":"Retail Goods"
        }
    ],
    "sg:phone":"+1 519 664 3831",
    "sg:postcode":"N0B 2N0",
    "sg:province":"ON",
    "wof:name":"Elaine's Shoes",
    "wof:placetype":"venue"
},
  "geometry": {"coordinates":[-80.5543212891,43.5359992981],"type":"Point"}
}