{
  "type": "Feature",
  "properties": {
    "addr:full":"Calgary AB T2R 1B8",
    "addr:postcode":"t2r 1b8",
    "iso:country":"CA",
    "sg:city":"Calgary",
    "sg:classifiers":[
        {
            "category":"Restaurant",
            "type":"Food & Drink"
        }
    ],
    "sg:phone":"+1 403 229 0999",
    "sg:postcode":"T2R 1B8",
    "sg:province":"AB",
    "sg:tags":[
        "out",
        "pizza"
    ],
    "wof:name":"Big John's Pizza & Donairs",
    "wof:placetype":"venue"
},
  "geometry": {"coordinates":[-114.081818,51.039894],"type":"Point"}
}