{
  "type": "Feature",
  "properties": {
    "addr:full":"3 Rue Des Grands-Ducs Sept-Iles QC G4S 1Z2",
    "addr:housenumber":"3",
    "addr:postcode":"g4s 1z2",
    "addr:street":"Rue Des Grands-Ducs",
    "iso:country":"CA",
    "sg:address":"3 Rue Des Grands-Ducs",
    "sg:city":"Sept-Iles",
    "sg:classifiers":[
        {
            "category":"Recreation",
            "type":"Entertainment"
        }
    ],
    "sg:phone":"+1 418 962 4429",
    "sg:postcode":"G4S 1Z2",
    "sg:province":"QC",
    "sg:tags":[
        "martial",
        "arts",
        "instruction"
    ],
    "wof:name":"Dojo Central Karate Jka Sept-",
    "wof:placetype":"venue"
},
  "geometry": {"coordinates":[-66.429573,50.272987],"type":"Point"}
}