{
  "type": "Feature",
  "properties": {
    "addr:full":"182 Main St S Mount Forest ON N0G 2L0",
    "addr:housenumber":"182",
    "addr:postcode":"n0g 2l0",
    "addr:street":"Main St S Mount",
    "iso:country":"CA",
    "sg:address":"182 Main St S",
    "sg:city":"Mount Forest",
    "sg:classifiers":[
        {
            "category":"Insurance",
            "subcategory":"Insurance Agent",
            "type":"Services"
        }
    ],
    "sg:phone":"+1 519 323 1376",
    "sg:postcode":"N0G 2L0",
    "sg:province":"ON",
    "wof:name":"Secure Insurance Solutions Grp",
    "wof:placetype":"venue"
},
  "geometry": {"coordinates":[-80.7341,43.98093],"type":"Point"}
}