{
  "type": "Feature",
  "properties": {
    "addr:full":"9040 95 Ave NW Edmonton AB T6C 1Z3",
    "addr:housenumber":"9040",
    "addr:postcode":"t6c 1z3",
    "addr:street":"95 Ave Nw",
    "iso:country":"CA",
    "sg:address":"9040 95 Ave NW",
    "sg:city":"Edmonton",
    "sg:classifiers":[
        {
            "category":"Organizations",
            "subcategory":"Religious Organization",
            "type":"Services"
        }
    ],
    "sg:phone":"+1 780 465 6118",
    "sg:postcode":"T6C 1Z3",
    "sg:province":"AB",
    "sg:tags":[
        "church"
    ],
    "wof:name":"Assumption Parish",
    "wof:placetype":"venue"
},
  "geometry": {"coordinates":[-113.466041565,53.5319671631],"type":"Point"}
}