{
  "type": "Feature",
  "properties": {
    "iso:country":"CA",
    "sg:address":"1 Beghin Ave",
    "sg:city":"Winnipeg",
    "sg:classifiers":[
        {
            "category":"Manufacturing",
            "subcategory":"Printing",
            "type":"Manufacturing & Wholesale Goods"
        }
    ],
    "sg:phone":"+1 204 663 9000",
    "sg:postcode":"R2J 3X5",
    "sg:province":"MB",
    "sg:tags":[
        "printer"
    ],
    "wof:name":"Premier Printing Ltd",
    "wof:placetype":"venue"
},
  "geometry": {"coordinates":[-97.04331207280001,49.8854103088],"type":"Point"}
}