{
  "type": "Feature",
  "properties": {
    "iso:country":"CA",
    "sg:address":"2349 Fairview St",
    "sg:city":"Burlington",
    "sg:classifiers":[
        {
            "category":"Organizations",
            "subcategory":"Labor Organization",
            "type":"Services"
        }
    ],
    "sg:phone":"+1 905 631 0494",
    "sg:postcode":"L7R 2E3",
    "sg:province":"ON",
    "wof:name":"Blerctc",
    "wof:placetype":"venue"
},
  "geometry": {"coordinates":[-79.801826,43.344078],"type":"Point"}
}