{
  "type": "Feature",
  "properties": {
    "iso:country":"CA",
    "sg:address":"9453 124 Ave",
    "sg:city":"Grande Prairie",
    "sg:classifiers":[
        {
            "category":"Manufacturing",
            "subcategory":"Printing",
            "type":"Manufacturing & Wholesale Goods"
        }
    ],
    "sg:phone":"+1 780 532 4111",
    "sg:postcode":"T8V 5Y6",
    "sg:province":"AB",
    "sg:tags":[
        "newspaper"
    ],
    "wof:name":"Edmonton Sun",
    "wof:placetype":"venue"
},
  "geometry": {"coordinates":[-118.779098511,55.1928443909],"type":"Point"}
}