{
  "type": "Feature",
  "properties": {
    "addr:full":"1003 1/2 Fennell Ave E Hamilton ON L8T 1R1",
    "addr:housenumber":"1003 1 / 2",
    "addr:postcode":"l8t 1r1",
    "addr:street":"Fennell Ave E",
    "iso:country":"CA",
    "sg:address":"1003 1/2 Fennell Ave E",
    "sg:city":"Hamilton",
    "sg:classifiers":[
        {
            "category":"Retail",
            "subcategory":"Laundry & Dry Cleaning",
            "type":"Services"
        }
    ],
    "sg:phone":"+1 905 383 6664",
    "sg:postcode":"L8T 1R1",
    "sg:province":"ON",
    "sg:tags":[
        "leather",
        "cleaners"
    ],
    "wof:name":"Wright's Cleaners",
    "wof:placetype":"venue"
},
  "geometry": {"coordinates":[-79.836601,43.227512],"type":"Point"}
}