{
  "type": "Feature",
  "properties": {
    "addr:full":"1557 O'Connor Dr East York ON M4B 2V7",
    "addr:housenumber":"1557",
    "addr:postcode":"m4b 2v7",
    "addr:street":"O'Connor Dr",
    "iso:country":"CA",
    "sg:address":"1557 O'Connor Dr",
    "sg:city":"East York",
    "sg:classifiers":[
        {
            "category":"Health Services",
            "subcategory":"Doctor",
            "type":"Services"
        }
    ],
    "sg:phone":"+1 416 288 0080",
    "sg:postcode":"M4B 2V7",
    "sg:province":"ON",
    "sg:tags":[
        "clinic"
    ],
    "wof:name":"East York Denture Clinic",
    "wof:placetype":"venue"
},
  "geometry": {"coordinates":[-79.353554,43.692467],"type":"Point"}
}