{
  "type": "Feature",
  "properties": {
    "addr:full":"860 Boul Saint-Rene O Gatineau QC J8T 8M1",
    "addr:housenumber":"860",
    "addr:postcode":"j8t 8m1",
    "addr:street":"Boul Saint-Rene O",
    "iso:country":"CA",
    "sg:address":"860 Boul Saint-Rene O",
    "sg:city":"Gatineau",
    "sg:classifiers":[
        {
            "category":"Shopping",
            "subcategory":"Pharmacy",
            "type":"Retail Goods"
        }
    ],
    "sg:phone":"+1 819 243 1881",
    "sg:postcode":"J8T 8M1",
    "sg:province":"QC",
    "wof:name":"Jean Coutu",
    "wof:placetype":"venue"
},
  "geometry": {"coordinates":[-75.608574,45.498028],"type":"Point"}
}