{
  "type": "Feature",
  "properties": {
    "addr:full":"204 Rue Jacques-Cartier S Saint-Jean-Sur-Richelieu QC J3B 4J3",
    "addr:housenumber":"204",
    "addr:postcode":"j3b 4j3",
    "addr:street":"Rue Jacques-Cartier S",
    "iso:country":"CA",
    "sg:address":"204 Rue Jacques-Cartier S",
    "sg:city":"Saint-Jean-Sur-Richelieu",
    "sg:classifiers":[
        {
            "category":"Restaurant",
            "type":"Food & Drink"
        }
    ],
    "sg:phone":"+1 450 346 7496",
    "sg:postcode":"J3B 4J3",
    "sg:province":"QC",
    "wof:name":"Restaurant Le Sous-Marin",
    "wof:placetype":"venue"
},
  "geometry": {"coordinates":[-73.257149,45.286091],"type":"Point"}
}