{
  "type": "Feature",
  "properties": {
    "addr:full":"804 York Rd Guelph ON N1E 6A6",
    "addr:housenumber":"804",
    "addr:postcode":"n1e 6a6",
    "addr:street":"York Rd",
    "iso:country":"CA",
    "sg:address":"804 York Rd",
    "sg:city":"Guelph",
    "sg:classifiers":[
        {
            "category":"Shopping",
            "subcategory":"Discount & Variety Stores",
            "type":"Retail Goods"
        }
    ],
    "sg:phone":"+1 519 822 7190",
    "sg:postcode":"N1E 6A6",
    "sg:province":"ON",
    "wof:name":"Publix Super Variety & Gift",
    "wof:placetype":"venue"
},
  "geometry": {"coordinates":[-80.2140426636,43.5592765808],"type":"Point"}
}