{
  "type": "Feature",
  "properties": {
    "addr:full":"1590 Cedar Hill Cross Rd Victoria BC V8P 2P5",
    "addr:housenumber":"1590",
    "addr:postcode":"v8p 2p5",
    "addr:street":"Cedar Hill Cross Rd",
    "iso:country":"CA",
    "sg:address":"1590 Cedar Hill Cross Rd",
    "sg:city":"Victoria",
    "sg:classifiers":[
        {
            "category":"Retail",
            "subcategory":"Laundry & Dry Cleaning",
            "type":"Services"
        }
    ],
    "sg:phone":"+1 250 477 6214",
    "sg:postcode":"V8P 2P5",
    "sg:province":"BC",
    "sg:tags":[
        "cleaners"
    ],
    "wof:name":"Individual Dry Cleaners Ltd",
    "wof:placetype":"venue"
},
  "geometry": {"coordinates":[-123.36451700000001,48.428314],"type":"Point"}
}