{
  "type": "Feature",
  "properties": {
    "iso:country":"CA",
    "sg:address":"902 Dillingham Rd",
    "sg:city":"Pickering",
    "sg:classifiers":[
        {
            "category":"Manufacturing",
            "subcategory":"Tools & Machinery",
            "type":"Manufacturing & Wholesale Goods"
        }
    ],
    "sg:phone":"+1 905 839 5196",
    "sg:postcode":"L1W 1Z6",
    "sg:province":"ON",
    "sg:tags":[
        "equipment",
        "conveyor",
        "conveying"
    ],
    "wof:name":"Allied Conveyors Ltd",
    "wof:placetype":"venue"
},
  "geometry": {"coordinates":[-79.068039,43.826355],"type":"Point"}
}