{
  "type": "Feature",
  "properties": {
    "iso:country":"CA",
    "sg:address":"2509 Rue Boivin",
    "sg:city":"Jonquiere",
    "sg:classifiers":[
        {
            "category":"Building & Trades",
            "subcategory":"Construction",
            "type":"Services"
        }
    ],
    "sg:phone":"+1 418 548 5178",
    "sg:postcode":"G7S 4R1",
    "sg:province":"QC",
    "sg:tags":[
        "general",
        "contractor"
    ],
    "wof:name":"Constructions Jp Frigon",
    "wof:placetype":"venue"
},
  "geometry": {"coordinates":[-71.14757537840001,48.401096344],"type":"Point"}
}