{
  "type": "Feature",
  "properties": {
    "addr:full":"290 Boul Pierre-Boursier Chateauguay QC J6J 4Z2",
    "addr:housenumber":"290",
    "addr:postcode":"j6j 4z2",
    "addr:street":"Boul Pierre-Boursier",
    "iso:country":"CA",
    "sg:address":"290 Boul Pierre-Boursier",
    "sg:city":"Chateauguay",
    "sg:classifiers":[
        {
            "category":"Retail",
            "subcategory":"Auto Repair",
            "type":"Services"
        }
    ],
    "sg:phone":"+1 450 699 1555",
    "sg:postcode":"J6J 4Z2",
    "sg:province":"QC",
    "sg:tags":[
        "repairing",
        "automobile"
    ],
    "wof:name":"Burn's Auto Repair",
    "wof:placetype":"venue"
},
  "geometry": {"coordinates":[-73.6990356445,45.3514060974],"type":"Point"}
}