{
  "type": "Feature",
  "properties": {
    "addr:full":"Notre-Dame-Du-Mont-Carmel QC G0X 3J0",
    "addr:postcode":"g0x 3j0",
    "iso:country":"CA",
    "sg:city":"Notre-Dame-Du-Mont-Carmel",
    "sg:classifiers":[
        {
            "category":"Building & Trades",
            "subcategory":"Construction",
            "type":"Services"
        }
    ],
    "sg:phone":"+1 819 372 9908",
    "sg:postcode":"G0X 3J0",
    "sg:province":"QC",
    "sg:tags":[
        "masonry",
        "contractor"
    ],
    "wof:name":"Maconnerie J-C Cossette & Fils",
    "wof:placetype":"venue"
},
  "geometry": {"coordinates":[-72.676147,46.413673],"type":"Point"}
}