{
  "type": "Feature",
  "properties": {
    "iso:country":"CA",
    "sg:address":"605 Denton St",
    "sg:city":"Coquitlam",
    "sg:classifiers":[
        {
            "category":"Recreation",
            "subcategory":"Marina",
            "type":"Entertainment"
        }
    ],
    "sg:phone":"+1 604 936 1136",
    "sg:postcode":"V3J 3V7",
    "sg:province":"BC",
    "sg:tags":[
        "repairing",
        "boat"
    ],
    "wof:name":"Denton Marine Svc",
    "wof:placetype":"venue"
},
  "geometry": {"coordinates":[-122.887016296,49.2538528442],"type":"Point"}
}