{
  "type": "Feature",
  "properties": {
    "addr:full":"75 Woodland Dr Hay River NT X0E 1G1",
    "addr:housenumber":"75",
    "addr:postcode":"x0e 1g1",
    "addr:street":"Woodland Dr",
    "iso:country":"CA",
    "sg:address":"75 Woodland Dr",
    "sg:city":"Hay River",
    "sg:classifiers":[
        {
            "category":"Education",
            "subcategory":"Library",
            "type":"Public Place"
        }
    ],
    "sg:phone":"+1 867 874 6486",
    "sg:postcode":"X0E 1G1",
    "sg:province":"NT",
    "wof:name":"Nwt Centennial Library",
    "wof:placetype":"venue"
},
  "geometry": {"coordinates":[-115.78892500000001,60.809883],"type":"Point"}
}