{
  "type": "Feature",
  "properties": {
    "addr:full":"Limoges ON K0A 2M0",
    "addr:postcode":"k0a 2m0",
    "iso:country":"CA",
    "sg:city":"Limoges",
    "sg:classifiers":[
        {
            "category":"Freight",
            "type":"Transportation"
        }
    ],
    "sg:phone":"+1 613 443 2826",
    "sg:postcode":"K0A 2M0",
    "sg:province":"ON",
    "sg:tags":[
        "trucking"
    ],
    "wof:name":"Lacroix Trucking and Savings",
    "wof:placetype":"venue"
},
  "geometry": {"coordinates":[-75.252647,45.331104],"type":"Point"}
}