{
  "type": "Feature",
  "properties": {
    "addr:full":"Manning Park BC V0X 1R0",
    "addr:postcode":"v0x 1r0",
    "iso:country":"CA",
    "sg:city":"Manning Park",
    "sg:classifiers":[
        {
            "category":"Autos & Motor Vehicles",
            "subcategory":"Fuel & Gas Station",
            "type":"Retail Goods"
        }
    ],
    "sg:phone":"+1 250 840 8857",
    "sg:postcode":"V0X 1R0",
    "sg:province":"BC",
    "sg:tags":[
        "oil"
    ],
    "wof:name":"East Gate Svc & Towing",
    "wof:placetype":"venue"
},
  "geometry": {"coordinates":[-120.61306,49.138523],"type":"Point"}
}