{
  "type": "Feature",
  "properties": {
    "addr:full":"13 Meadowland Ave Barrie ON L4N 2Y3",
    "addr:housenumber":"13",
    "addr:postcode":"l4n 2y3",
    "addr:street":"Meadowland Ave",
    "iso:country":"CA",
    "sg:address":"13 Meadowland Ave",
    "sg:city":"Barrie",
    "sg:classifiers":[
        {
            "category":"Retail",
            "subcategory":"Repair Shop",
            "type":"Services"
        }
    ],
    "sg:phone":"+1 705 726 4429",
    "sg:postcode":"L4N 2Y3",
    "sg:province":"ON",
    "sg:tags":[
        "lock",
        "locksmith"
    ],
    "wof:name":"Steven Sons Lock Svc",
    "wof:placetype":"venue"
},
  "geometry": {"coordinates":[-79.6805648804,44.3643722534],"type":"Point"}
}