{
  "type": "Feature",
  "properties": {
    "addr:full":"7 Skyline Cres NE Calgary AB T2K 5X2",
    "addr:housenumber":"7",
    "addr:postcode":"t2k 5x2",
    "addr:street":"Skyline Cres Ne",
    "iso:country":"CA",
    "sg:address":"7 Skyline Cres NE",
    "sg:city":"Calgary",
    "sg:classifiers":[
        {
            "category":"Building & Trades",
            "subcategory":"Construction",
            "type":"Services"
        }
    ],
    "sg:phone":"+1 403 516 1110",
    "sg:postcode":"T2K 5X2",
    "sg:province":"AB",
    "sg:tags":[
        "solarium"
    ],
    "wof:name":"Slimline Sunrooms",
    "wof:placetype":"venue"
},
  "geometry": {"coordinates":[-114.046257,51.098476],"type":"Point"}
}