{
  "type": "Feature",
  "properties": {
    "addr:full":"3891 Richmond Rd Nepean ON K2H 5C1",
    "addr:housenumber":"3891",
    "addr:postcode":"k2h 5c1",
    "addr:street":"Richmond Rd",
    "iso:country":"CA",
    "sg:address":"3891 Richmond Rd",
    "sg:city":"Nepean",
    "sg:classifiers":[
        {
            "category":"Organizations",
            "subcategory":"Religious Organization",
            "type":"Services"
        }
    ],
    "sg:phone":"+1 613 828 6720",
    "sg:postcode":"K2H 5C1",
    "sg:province":"ON",
    "sg:tags":[
        "church"
    ],
    "wof:name":"St Martin DE Porres Church",
    "wof:placetype":"venue"
},
  "geometry": {"coordinates":[-75.827164,45.318878],"type":"Point"}
}