{
  "type": "Feature",
  "properties": {
    "iso:country":"CA",
    "sg:address":"75 Rue Frontenac",
    "sg:city":"Riviere-Du-Loup",
    "sg:classifiers":[
        {
            "category":"Organizations",
            "subcategory":"Professional Association",
            "type":"Services"
        }
    ],
    "sg:phone":"+1 418 862 4394",
    "sg:postcode":"G5R 1S6",
    "sg:province":"QC",
    "wof:name":"Federation Quebecoise-Hockey",
    "wof:placetype":"venue"
},
  "geometry": {"coordinates":[-69.538788,47.826122],"type":"Point"}
}