{
  "type": "Feature",
  "properties": {
    "addr:full":"Surrey BC V3W 3V6",
    "addr:postcode":"v3w 3v6",
    "iso:country":"CA",
    "sg:city":"Surrey",
    "sg:classifiers":[
        {
            "category":"Manufacturing",
            "subcategory":"Metals",
            "type":"Manufacturing & Wholesale Goods"
        }
    ],
    "sg:phone":"+1 604 596 4121",
    "sg:postcode":"V3W 3V6",
    "sg:province":"BC",
    "sg:tags":[
        "steel"
    ],
    "wof:name":"Richfab Industries Ltd",
    "wof:placetype":"venue"
},
  "geometry": {"coordinates":[-122.882041931,49.1583328247],"type":"Point"}
}