{
  "type": "Feature",
  "properties": {
    "addr:full":"144 Shorting Rd Scarborough ON M1S 3S6",
    "addr:housenumber":"144",
    "addr:postcode":"m1s 3s6",
    "addr:street":"Shorting Rd",
    "iso:country":"CA",
    "sg:address":"144 Shorting Rd",
    "sg:city":"Scarborough",
    "sg:classifiers":[
        {
            "category":"Manufacturing",
            "subcategory":"Metals",
            "type":"Manufacturing & Wholesale Goods"
        }
    ],
    "sg:phone":"+1 416 293 3200",
    "sg:postcode":"M1S 3S6",
    "sg:province":"ON",
    "sg:tags":[
        "foundry"
    ],
    "wof:name":"Steve's Castings Ltd",
    "wof:placetype":"venue"
},
  "geometry": {"coordinates":[-79.250648,43.795273],"type":"Point"}
}