{
  "type": "Feature",
  "properties": {
    "addr:full":"55 Rue Principale N Saint-Pamphile QC G0R 3X0",
    "addr:housenumber":"55",
    "addr:postcode":"g0r 3x0",
    "addr:street":"Rue Principale N",
    "iso:country":"CA",
    "sg:address":"55 Rue Principale N",
    "sg:city":"Saint-Pamphile",
    "sg:classifiers":[
        {
            "category":"Shopping",
            "subcategory":"Clothing, Apparel, & Fashions",
            "type":"Retail Goods"
        }
    ],
    "sg:phone":"+1 418 356 3115",
    "sg:postcode":"G0R 3X0",
    "sg:province":"QC",
    "sg:tags":[
        "furnishing"
    ],
    "wof:name":"Mercerie Rejean Gauvin Inc",
    "wof:placetype":"venue"
},
  "geometry": {"coordinates":[-69.7797698975,46.9613609314],"type":"Point"}
}