{
  "type": "Feature",
  "properties": {
    "addr:full":"17430 106A Ave NW Edmonton AB T5S 1E6",
    "addr:housenumber":"17430",
    "addr:postcode":"t5s 1e6",
    "addr:street":"106A Ave Nw",
    "iso:country":"CA",
    "sg:address":"17430 106A Ave NW",
    "sg:city":"Edmonton",
    "sg:classifiers":[
        {
            "category":"Building & Trades",
            "subcategory":"Equipment Rental",
            "type":"Services"
        }
    ],
    "sg:phone":"+1 780 489 8787",
    "sg:postcode":"T5S 1E6",
    "sg:province":"AB",
    "sg:tags":[
        "leasing",
        "video"
    ],
    "wof:name":"Matrix Video Communications",
    "wof:placetype":"venue"
},
  "geometry": {"coordinates":[-113.621506,53.552052],"type":"Point"}
}