{
  "type": "Feature",
  "properties": {
    "addr:full":"Coquitlam BC V3J 1S7",
    "addr:postcode":"v3j 1s7",
    "iso:country":"CA",
    "sg:city":"Coquitlam",
    "sg:classifiers":[
        {
            "category":"Wholesale",
            "subcategory":"Construction Materials",
            "type":"Manufacturing & Wholesale Goods"
        }
    ],
    "sg:phone":"+1 604 936 6525",
    "sg:postcode":"V3J 1S7",
    "sg:province":"BC",
    "sg:tags":[
        "importer",
        "lumber"
    ],
    "wof:name":"A Q Timber Inc",
    "wof:placetype":"venue"
},
  "geometry": {"coordinates":[-122.863555908,49.2494506836],"type":"Point"}
}