{
  "type": "Feature",
  "properties": {
    "addr:full":"Montreal QC H2W 1Y9",
    "addr:postcode":"h2w 1y9",
    "iso:country":"CA",
    "sg:city":"Montreal",
    "sg:classifiers":[
        {
            "category":"Professional",
            "subcategory":"Art Services",
            "type":"Services"
        }
    ],
    "sg:phone":"+1 514 843 5088",
    "sg:postcode":"H2W 1Y9",
    "sg:province":"QC",
    "sg:tags":[
        "photographer"
    ],
    "wof:name":"Yves Beaulieu Photography Inc",
    "wof:placetype":"venue"
},
  "geometry": {"coordinates":[-73.580055,45.517143],"type":"Point"}
}