{
  "type": "Feature",
  "properties": {
    "iso:country":"CA",
    "sg:address":"520 Rue Lafontaine",
    "sg:city":"Riviere-Du-Loup",
    "sg:classifiers":[
        {
            "category":"Personal",
            "subcategory":"Beauty Salon",
            "type":"Services"
        }
    ],
    "sg:phone":"+1 418 867 5293",
    "sg:postcode":"G5R 3C4",
    "sg:province":"QC",
    "wof:name":"Salon DE Coiffure Cheveux-Art",
    "wof:placetype":"venue"
},
  "geometry": {"coordinates":[-69.5304260254,47.8276519775],"type":"Point"}
}