{
  "type": "Feature",
  "properties": {
    "addr:full":"8045 Old Waneta Rd Trail BC V1R 4X1",
    "addr:housenumber":"8045",
    "addr:postcode":"bc v1r 4x1",
    "addr:street":"Old Waneta Rd Trail",
    "iso:country":"CA",
    "sg:address":"8045 Old Waneta Rd",
    "sg:city":"Trail",
    "sg:classifiers":[
        {
            "category":"Professional",
            "subcategory":"Business Services",
            "type":"Services"
        }
    ],
    "sg:phone":"+1 250 364 5810",
    "sg:postcode":"V1R 4X1",
    "sg:province":"BC",
    "sg:tags":[
        "paging",
        "answering"
    ],
    "wof:name":"Champion Communications",
    "wof:placetype":"venue"
},
  "geometry": {"coordinates":[-117.638832092,49.090133667],"type":"Point"}
}