{
  "type": "Feature",
  "properties": {
    "addr:full":"1381 Rue Ampere Boucherville QC J4B 5Z5",
    "addr:housenumber":"1381",
    "addr:postcode":"j4b 5z5",
    "addr:street":"Rue Ampere",
    "iso:country":"CA",
    "sg:address":"1381 Rue Ampere",
    "sg:city":"Boucherville",
    "sg:classifiers":[
        {
            "category":"Manufacturing",
            "subcategory":"Food",
            "type":"Manufacturing & Wholesale Goods"
        }
    ],
    "sg:phone":"+1 450 641 2200",
    "sg:postcode":"J4B 5Z5",
    "sg:province":"QC",
    "sg:tags":[
        "grocer",
        "product",
        "manufacturer"
    ],
    "wof:name":"Newlyweds Foods",
    "wof:placetype":"venue"
},
  "geometry": {"coordinates":[-73.427643,45.569359],"type":"Point"}
}