{
  "type": "Feature",
  "properties": {
    "iso:country":"CA",
    "sg:city":"Scarborough",
    "sg:classifiers":[
        {
            "category":"Organizations",
            "subcategory":"Membership Organization",
            "type":"Services"
        }
    ],
    "sg:phone":"+1 416 439 7111",
    "sg:postcode":"M1H 3B7",
    "sg:province":"ON",
    "wof:name":"Scarborough Women's Ctr",
    "wof:placetype":"venue"
},
  "geometry": {"coordinates":[-79.2321548462,43.7764701843],"type":"Point"}
}