{
  "type": "Feature",
  "properties": {
    "iso:country":"CA",
    "sg:address":"SE 3 7 14W",
    "sg:city":"Glenboro",
    "sg:classifiers":[
        {
            "category":"Wholesale",
            "subcategory":"Petroleum",
            "type":"Manufacturing & Wholesale Goods"
        }
    ],
    "sg:phone":"+1 204 827 2296",
    "sg:postcode":"R0K 0X0",
    "sg:province":"MB",
    "sg:tags":[
        "pipe",
        "line",
        "company"
    ],
    "wof:name":"Enbridge Pipelines Inc",
    "wof:placetype":"venue"
},
  "geometry": {"coordinates":[-99.29020690919999,49.5583190918],"type":"Point"}
}