{
  "type": "Feature",
  "properties": {
    "addr:full":"284 Holland St W Bradford ON L3Z 1J1",
    "addr:housenumber":"284",
    "addr:postcode":"l3z 1j1",
    "addr:street":"Holland St W",
    "iso:country":"CA",
    "sg:address":"284 Holland St W",
    "sg:city":"Bradford",
    "sg:classifiers":[
        {
            "category":"Home & Garden",
            "subcategory":"Building Materials",
            "type":"Retail Goods"
        }
    ],
    "sg:phone":"+1 905 775 0526",
    "sg:postcode":"L3Z 1J1",
    "sg:province":"ON",
    "sg:tags":[
        "paint"
    ],
    "wof:name":"Decorator's Edge Paint & Wlpr",
    "wof:placetype":"venue"
},
  "geometry": {"coordinates":[-79.57506600000001,44.111839],"type":"Point"}
}