{
  "type": "Feature",
  "properties": {
    "iso:country":"CA",
    "sg:city":"Delta",
    "sg:classifiers":[
        {
            "category":"Health Services",
            "subcategory":"Doctor",
            "type":"Services"
        }
    ],
    "sg:phone":"+1 604 596 2211",
    "sg:postcode":"V4C 6R2",
    "sg:province":"BC",
    "sg:tags":[
        "physician",
        "surgeon"
    ],
    "wof:name":"Mitchell Family Medical Ctr",
    "wof:placetype":"venue"
},
  "geometry": {"coordinates":[-122.89051055900001,49.1565170288],"type":"Point"}
}