{
  "type": "Feature",
  "properties": {
    "iso:country":"CA",
    "sg:address":"139 Rue DE LA Station",
    "sg:city":"Laurier-Station",
    "sg:classifiers":[
        {
            "category":"Education",
            "subcategory":"School",
            "type":"Public Place"
        }
    ],
    "sg:phone":"+1 418 728 5686",
    "sg:postcode":"G0S 1N0",
    "sg:province":"QC",
    "wof:name":"Ecole LA Source",
    "wof:placetype":"venue"
},
  "geometry": {"coordinates":[-71.62822723390001,46.5406646729],"type":"Point"}
}