{
  "type": "Feature",
  "properties": {
    "iso:country":"CA",
    "sg:address":"Mohawk Dr",
    "sg:city":"Cornwall",
    "sg:classifiers":[
        {
            "category":"Education",
            "subcategory":"School",
            "type":"Public Place"
        }
    ],
    "sg:phone":"+1 613 938 8723",
    "sg:postcode":"K6H 5R6",
    "sg:province":"ON",
    "wof:name":"Child and Family Treatment CT",
    "wof:placetype":"venue"
},
  "geometry": {"coordinates":[-74.7734222412,45.0348777771],"type":"Point"}
}