{
  "type": "Feature",
  "properties": {
    "iso:country":"CA",
    "sg:address":"7782 Boul Levesque E",
    "sg:city":"Laval",
    "sg:classifiers":[
        {
            "category":"Restaurant",
            "type":"Food & Drink"
        }
    ],
    "sg:phone":"+1 450 664 2777",
    "sg:postcode":"H7A 1T3",
    "sg:province":"QC",
    "wof:name":"Sam Sing Restaurant",
    "wof:placetype":"venue"
},
  "geometry": {"coordinates":[-73.5923690796,45.6579666138],"type":"Point"}
}