{
  "type": "Feature",
  "properties": {
    "addr:full":"42 Rexdale Blvd Etobicoke ON M9W 5Z3",
    "addr:housenumber":"42",
    "addr:postcode":"m9w 5z3",
    "addr:street":"Rexdale Blvd",
    "iso:country":"CA",
    "sg:address":"42 Rexdale Blvd",
    "sg:city":"Etobicoke",
    "sg:classifiers":[
        {
            "category":"Restaurant",
            "type":"Food & Drink"
        }
    ],
    "sg:phone":"+1 416 746 4948",
    "sg:postcode":"M9W 5Z3",
    "sg:province":"ON",
    "wof:name":"Faley Restaurant",
    "wof:placetype":"venue"
},
  "geometry": {"coordinates":[-79.55899047849999,43.7137298584],"type":"Point"}
}