{
  "type": "Feature",
  "properties": {
    "iso:country":"CA",
    "sg:address":"171 Mohawk Rd E # 3",
    "sg:city":"Hamilton",
    "sg:classifiers":[
        {
            "category":"Restaurant",
            "type":"Food & Drink"
        }
    ],
    "sg:phone":"+1 905 383 7777",
    "sg:postcode":"L9A 2H4",
    "sg:province":"ON",
    "sg:tags":[
        "out",
        "pizza"
    ],
    "wof:name":"Mario's Pizza & Wings",
    "wof:placetype":"venue"
},
  "geometry": {"coordinates":[-79.87302398680001,43.2267036438],"type":"Point"}
}