{
  "type": "Feature",
  "properties": {
    "iso:country":"CA",
    "sg:address":"7445 Boul Langelier",
    "sg:city":"Saint-Leonard",
    "sg:classifiers":[
        {
            "category":"Shopping",
            "subcategory":"Optical Goods",
            "type":"Retail Goods"
        }
    ],
    "sg:phone":"+1 514 252 8340",
    "sg:postcode":"H1S 1V6",
    "sg:province":"QC",
    "sg:tags":[
        "optician"
    ],
    "wof:name":"Club Lunette Jgg Enr",
    "wof:placetype":"venue"
},
  "geometry": {"coordinates":[-73.572762,45.591663],"type":"Point"}
}