{
  "type": "Feature",
  "properties": {
    "addr:full":"North York ON M2J 1W8",
    "addr:postcode":"m2j 1w8",
    "iso:country":"CA",
    "sg:city":"North York",
    "sg:classifiers":[
        {
            "category":"Organizations",
            "subcategory":"Professional Association",
            "type":"Services"
        }
    ],
    "sg:phone":"+1 416 499 1416",
    "sg:postcode":"M2J 1W8",
    "sg:province":"ON",
    "wof:name":"Canadian Fluid Power Assn",
    "wof:placetype":"venue"
},
  "geometry": {"coordinates":[-79.330444,43.774872],"type":"Point"}
}