{
  "type": "Feature",
  "properties": {
    "iso:country":"CA",
    "sg:address":"18 Boul Des Iles",
    "sg:city":"Port-Cartier",
    "sg:classifiers":[
        {
            "category":"Education",
            "subcategory":"School",
            "type":"Public Place"
        }
    ],
    "sg:phone":"+1 418 766 7171",
    "sg:postcode":"G5B 2N4",
    "sg:province":"QC",
    "wof:name":"Centre Educatif L'Abri",
    "wof:placetype":"venue"
},
  "geometry": {"coordinates":[-66.886169,50.022701],"type":"Point"}
}