{
  "type": "Feature",
  "properties": {
    "addr:full":"82 Victoria St S Port Hope ON L1A 3L6",
    "addr:housenumber":"82",
    "addr:postcode":"l1a 3l6",
    "addr:street":"Victoria St S",
    "iso:country":"CA",
    "sg:address":"82 Victoria St S",
    "sg:city":"Port Hope",
    "sg:classifiers":[
        {
            "category":"Sports & Exercise",
            "subcategory":"Golf",
            "type":"Entertainment"
        }
    ],
    "sg:phone":"+1 905 885 6487",
    "sg:postcode":"L1A 3L6",
    "sg:province":"ON",
    "sg:tags":[
        "course"
    ],
    "wof:name":"Port Hope Golf & Country Club",
    "wof:placetype":"venue"
},
  "geometry": {"coordinates":[-78.305916,43.94611],"type":"Point"}
}