{
  "type": "Feature",
  "properties": {
    "iso:country":"CA",
    "sg:address":"3711 2 Ave SW",
    "sg:city":"Calgary",
    "sg:classifiers":[
        {
            "category":"Professional",
            "subcategory":"Engineering",
            "type":"Services"
        }
    ],
    "sg:phone":"+1 403 232 8990",
    "sg:postcode":"T3C 0A2",
    "sg:province":"AB",
    "sg:tags":[
        "engineer"
    ],
    "wof:name":"Tesla Solutions Group Inc",
    "wof:placetype":"venue"
},
  "geometry": {"coordinates":[-114.139503,51.051052],"type":"Point"}
}