{
  "type": "Feature",
  "properties": {
    "addr:full":"Surrey BC V3W 1E6",
    "addr:postcode":"v3w 1e6",
    "iso:country":"CA",
    "sg:city":"Surrey",
    "sg:classifiers":[
        {
            "category":"Professional",
            "subcategory":"Accounting & Tax Preparation",
            "type":"Services"
        }
    ],
    "sg:phone":"+1 604 502 0777",
    "sg:postcode":"V3W 1E6",
    "sg:province":"BC",
    "sg:tags":[
        "accountant"
    ],
    "wof:name":"Marcus & CO",
    "wof:placetype":"venue"
},
  "geometry": {"coordinates":[-122.86792800000001,49.14106],"type":"Point"}
}