{
  "type": "Feature",
  "properties": {
    "addr:full":"Richmond BC V6X 2A8",
    "addr:postcode":"v6x 2a8",
    "iso:country":"CA",
    "sg:city":"Richmond",
    "sg:classifiers":[
        {
            "category":"Building & Trades",
            "subcategory":"Construction",
            "type":"Services"
        }
    ],
    "sg:phone":"+1 604 241 7667",
    "sg:postcode":"V6X 2A8",
    "sg:province":"BC",
    "sg:tags":[
        "general",
        "contractor"
    ],
    "wof:name":"Counsil of Construction Assoc",
    "wof:placetype":"venue"
},
  "geometry": {"coordinates":[-123.14237199999999,49.173668],"type":"Point"}
}