{
  "type": "Feature",
  "properties": {
    "addr:full":"Tadoussac QC G0T 2A0",
    "addr:postcode":"g0t 2a0",
    "iso:country":"CA",
    "sg:city":"Tadoussac",
    "sg:classifiers":[
        {
            "category":"Wholesale",
            "subcategory":"Groceries",
            "type":"Manufacturing & Wholesale Goods"
        }
    ],
    "sg:phone":"+1 418 235 4752",
    "sg:postcode":"G0T 2A0",
    "sg:province":"QC",
    "sg:tags":[
        "cocoa",
        "chocolate"
    ],
    "wof:name":"Boulangerie Chocolaterie Pain",
    "wof:placetype":"venue"
},
  "geometry": {"coordinates":[-69.7209472656,48.1431274414],"type":"Point"}
}