{
  "type": "Feature",
  "properties": {
    "iso:country":"CA",
    "sg:address":"2007 Rue Gertrude",
    "sg:city":"Carignan",
    "sg:classifiers":[
        {
            "category":"Building & Trades",
            "subcategory":"Construction",
            "type":"Services"
        }
    ],
    "sg:phone":"+1 450 658 5540",
    "sg:postcode":"J3L 4G8",
    "sg:province":"QC",
    "sg:tags":[
        "equipment",
        "kitchen",
        "maker",
        "cabinet"
    ],
    "wof:name":"Atout Meuble Ebenisterie Inc",
    "wof:placetype":"venue"
},
  "geometry": {"coordinates":[-73.3333740234,45.4483451843],"type":"Point"}
}