{
  "type": "Feature",
  "properties": {
    "addr:full":"310 Park Ave Thunder Bay ON P7B 6C8",
    "addr:housenumber":"310",
    "addr:postcode":"p7b 6c8",
    "addr:street":"Park Ave",
    "iso:country":"CA",
    "sg:address":"310 Park Ave",
    "sg:city":"Thunder Bay",
    "sg:classifiers":[
        {
            "category":"Organizations",
            "subcategory":"Religious Organization",
            "type":"Services"
        }
    ],
    "sg:phone":"+1 807 345 3916",
    "sg:postcode":"P7B 6C8",
    "sg:province":"ON",
    "sg:tags":[
        "church"
    ],
    "wof:name":"United Church Cambrian Presby",
    "wof:placetype":"venue"
},
  "geometry": {"coordinates":[-89.22524300000001,48.43615],"type":"Point"}
}