{
  "type": "Feature",
  "properties": {
    "addr:full":"166 Tecumseh Rd W Windsor ON N8X 1E9",
    "addr:housenumber":"166",
    "addr:postcode":"n8x 1e9",
    "addr:street":"Tecumseh Rd W",
    "iso:country":"CA",
    "sg:address":"166 Tecumseh Rd W",
    "sg:city":"Windsor",
    "sg:classifiers":[
        {
            "category":"Organizations",
            "subcategory":"Religious Organization",
            "type":"Services"
        }
    ],
    "sg:phone":"+1 519 973 7240",
    "sg:postcode":"N8X 1E9",
    "sg:province":"ON",
    "sg:tags":[
        "church"
    ],
    "wof:name":"St Peter's Maronite Church",
    "wof:placetype":"venue"
},
  "geometry": {"coordinates":[-83.0271682739,42.2962112427],"type":"Point"}
}