{
  "type": "Feature",
  "properties": {
    "addr:full":"2910 Westbrook Ave Stevensville ON L0S 1S0",
    "addr:housenumber":"2910",
    "addr:postcode":"l0s 1s0",
    "addr:street":"Westbrook Ave",
    "iso:country":"CA",
    "sg:address":"2910 Westbrook Ave",
    "sg:city":"Stevensville",
    "sg:classifiers":[
        {
            "category":"Personal",
            "type":"Services"
        }
    ],
    "sg:phone":"+1 905 382 2645",
    "sg:postcode":"L0S 1S0",
    "sg:province":"ON",
    "sg:tags":[
        "electrolysis"
    ],
    "wof:name":"Advance Computer Electrolysis",
    "wof:placetype":"venue"
},
  "geometry": {"coordinates":[-79.0546722412,42.9437065125],"type":"Point"}
}