{
  "type": "Feature",
  "properties": {
    "addr:full":"450 Hurdman St Mattawa ON P0H 1V0",
    "addr:housenumber":"450",
    "addr:postcode":"p0h 1v0",
    "addr:street":"Hurdman St",
    "iso:country":"CA",
    "sg:address":"450 Hurdman St",
    "sg:city":"Mattawa",
    "sg:classifiers":[
        {
            "category":"Recreation",
            "type":"Entertainment"
        }
    ],
    "sg:phone":"+1 705 744 2311",
    "sg:postcode":"P0H 1V0",
    "sg:province":"ON",
    "sg:tags":[
        "provincial",
        "center",
        "parks"
    ],
    "wof:name":"Mattawa Parks & Recreation",
    "wof:placetype":"venue"
},
  "geometry": {"coordinates":[-78.7022018433,46.3136901855],"type":"Point"}
}