{
  "type": "Feature",
  "properties": {
    "addr:full":"Montreal QC H4N 3H5",
    "addr:postcode":"h4n 3h5",
    "iso:country":"CA",
    "sg:city":"Montreal",
    "sg:classifiers":[
        {
            "category":"Personal",
            "subcategory":"Hair Removal",
            "type":"Services"
        }
    ],
    "sg:phone":"+1 514 383 0123",
    "sg:postcode":"H4N 3H5",
    "sg:province":"QC",
    "sg:tags":[
        "removing"
    ],
    "wof:name":"Eclipse Laser Esthetique",
    "wof:placetype":"venue"
},
  "geometry": {"coordinates":[-73.63369,45.581413],"type":"Point"}
}