{
  "type": "Feature",
  "properties": {
    "addr:full":"65 Brunswick St Fredericton NB E3B 1G5",
    "addr:housenumber":"65",
    "addr:postcode":"e3b 1g5",
    "addr:street":"Brunswick St",
    "iso:country":"CA",
    "sg:address":"65 Brunswick St",
    "sg:city":"Fredericton",
    "sg:classifiers":[
        {
            "category":"Organizations",
            "subcategory":"Professional Association",
            "type":"Services"
        }
    ],
    "sg:phone":"+1 506 451 8414",
    "sg:postcode":"E3B 1G5",
    "sg:province":"NB",
    "wof:name":"Friends & Fellowship Group",
    "wof:placetype":"venue"
},
  "geometry": {"coordinates":[-66.65181,45.964287],"type":"Point"}
}