{
  "type": "Feature",
  "properties": {
    "addr:full":"5530 Bilby St Halifax NS B3K 1V3",
    "addr:housenumber":"5530",
    "addr:postcode":"b3k 1v3",
    "addr:street":"Bilby St",
    "iso:country":"CA",
    "sg:address":"5530 Bilby St",
    "sg:city":"Halifax",
    "sg:classifiers":[
        {
            "category":"Retail",
            "subcategory":"Auto Repair",
            "type":"Services"
        }
    ],
    "sg:phone":"+1 902 455 2102",
    "sg:postcode":"B3K 1V3",
    "sg:province":"NS",
    "sg:tags":[
        "body",
        "automobile",
        "painting"
    ],
    "wof:name":"Bone's Body & Fender",
    "wof:placetype":"venue"
},
  "geometry": {"coordinates":[-63.596039,44.660137],"type":"Point"}
}