{
  "type": "Feature",
  "properties": {
    "iso:country":"CA",
    "sg:address":"2102 Old Dollarton Rd",
    "sg:city":"North Vancouver",
    "sg:classifiers":[
        {
            "category":"Retail",
            "subcategory":"Auto Repair",
            "type":"Services"
        }
    ],
    "sg:phone":"+1 604 929 2717",
    "sg:postcode":"V7H 1A7",
    "sg:province":"BC",
    "sg:tags":[
        "repairing",
        "automobile"
    ],
    "wof:name":"Dollarton Automotive Svc",
    "wof:placetype":"venue"
},
  "geometry": {"coordinates":[-123.01701355,49.3074989319],"type":"Point"}
}