{
  "type": "Feature",
  "properties": {
    "addr:full":"Winkler MB R6W 2S2",
    "addr:postcode":"r6w 2s2",
    "iso:country":"CA",
    "sg:city":"Winkler",
    "sg:classifiers":[
        {
            "category":"Shopping",
            "subcategory":"Clothing, Apparel, & Fashions",
            "type":"Retail Goods"
        }
    ],
    "sg:phone":"+1 204 325 5826",
    "sg:postcode":"R6W 2S2",
    "sg:province":"MB",
    "wof:name":"Reitmans",
    "wof:placetype":"venue"
},
  "geometry": {"coordinates":[-97.93250999999999,49.190529],"type":"Point"}
}