{
  "type": "Feature",
  "properties": {
    "addr:full":"Calgary AB T2P 3Y6",
    "addr:postcode":"t2p 3y6",
    "iso:country":"CA",
    "sg:city":"Calgary",
    "sg:classifiers":[
        {
            "category":"Health Services",
            "subcategory":"Chiropractor",
            "type":"Services"
        }
    ],
    "sg:phone":"+1 403 232 1283",
    "sg:postcode":"T2P 3Y6",
    "sg:province":"AB",
    "wof:name":"Betts, Steve DC",
    "wof:placetype":"venue"
},
  "geometry": {"coordinates":[-114.06338501,51.0482215881],"type":"Point"}
}