{
  "type": "Feature",
  "properties": {
    "iso:country":"CA",
    "sg:address":"1297 Rue Beauvais",
    "sg:city":"Saint-Laurent",
    "sg:classifiers":[
        {
            "category":"Manufacturing",
            "subcategory":"Printing",
            "type":"Manufacturing & Wholesale Goods"
        }
    ],
    "sg:phone":"+1 514 336 7499",
    "sg:postcode":"H4N 1T9",
    "sg:province":"QC",
    "sg:tags":[
        "typesetting"
    ],
    "wof:name":"Optima Creations",
    "wof:placetype":"venue"
},
  "geometry": {"coordinates":[-73.674331665,45.5304374695],"type":"Point"}
}