{
  "type": "Feature",
  "properties": {
    "iso:country":"CA",
    "sg:city":"Markham",
    "sg:classifiers":[
        {
            "category":"Shopping",
            "subcategory":"Florist",
            "type":"Retail Goods"
        }
    ],
    "sg:phone":"+1 905 474 0977",
    "sg:postcode":"L3R 9W6",
    "sg:province":"ON",
    "wof:name":"Flowers By Helen",
    "wof:placetype":"venue"
},
  "geometry": {"coordinates":[-79.31540679930001,43.8599243164],"type":"Point"}
}