{
  "type": "Feature",
  "properties": {
    "addr:full":"640 Dundas St E Belleville ON K8N 1G7",
    "addr:housenumber":"640",
    "addr:postcode":"k8n 1g7",
    "addr:street":"Dundas St E",
    "iso:country":"CA",
    "sg:address":"640 Dundas St E",
    "sg:city":"Belleville",
    "sg:classifiers":[
        {
            "category":"Home & Garden",
            "subcategory":"Building Materials",
            "type":"Retail Goods"
        }
    ],
    "sg:phone":"+1 613 968 3646",
    "sg:postcode":"K8N 1G7",
    "sg:province":"ON",
    "sg:tags":[
        "glass",
        "window",
        "plate"
    ],
    "wof:name":"Belleville City Glass Inc",
    "wof:placetype":"venue"
},
  "geometry": {"coordinates":[-77.3406448364,44.1691169739],"type":"Point"}
}