{
  "type": "Feature",
  "properties": {
    "addr:full":"Fort St James BC V0J 1P0",
    "addr:postcode":"v0j 1p0",
    "addr:street":"Fort St",
    "iso:country":"CA",
    "sg:city":"Fort St James",
    "sg:classifiers":[
        {
            "category":"Arts & Performance",
            "subcategory":"Theater",
            "type":"Entertainment"
        }
    ],
    "sg:phone":"+1 250 996 2246",
    "sg:postcode":"V0J 1P0",
    "sg:province":"BC",
    "sg:tags":[
        "television",
        "station",
        "representative"
    ],
    "wof:name":"Fort St James Tv Society",
    "wof:placetype":"venue"
},
  "geometry": {"coordinates":[-124.250923,54.445839],"type":"Point"}
}