{
  "type": "Feature",
  "properties": {
    "addr:full":"Cambridge ON N1T 1H9",
    "addr:postcode":"n1t 1h9",
    "iso:country":"CA",
    "sg:city":"Cambridge",
    "sg:classifiers":[
        {
            "category":"Shopping",
            "subcategory":"Computers & Home Electronics",
            "type":"Retail Goods"
        }
    ],
    "sg:phone":"+1 519 740 6060",
    "sg:postcode":"N1T 1H9",
    "sg:province":"ON",
    "sg:tags":[
        "parts",
        "supply"
    ],
    "wof:name":"Lazer Depot Inc",
    "wof:placetype":"venue"
},
  "geometry": {"coordinates":[-80.3044433594,43.4042320251],"type":"Point"}
}