{
  "type": "Feature",
  "properties": {
    "addr:full":"17452 103 Ave NW Edmonton AB T5S 2C8",
    "addr:housenumber":"17452",
    "addr:postcode":"t5s 2c8",
    "addr:street":"103 Ave Nw",
    "iso:country":"CA",
    "sg:address":"17452 103 Ave NW",
    "sg:city":"Edmonton",
    "sg:classifiers":[
        {
            "category":"Home & Garden",
            "subcategory":"Household Appliances",
            "type":"Retail Goods"
        }
    ],
    "sg:phone":"+1 780 484 1770",
    "sg:postcode":"T5S 2C8",
    "sg:province":"AB",
    "sg:tags":[
        "cleaners",
        "vacuum"
    ],
    "wof:name":"Rain-Alta Holdings Ltd",
    "wof:placetype":"venue"
},
  "geometry": {"coordinates":[-113.621475,53.545437],"type":"Point"}
}