{
  "type": "Feature",
  "properties": {
    "iso:country":"CA",
    "sg:address":"195 Lambton St E",
    "sg:city":"Durham",
    "sg:classifiers":[
        {
            "category":"Professional",
            "subcategory":"Lawyer & Legal Services",
            "type":"Services"
        }
    ],
    "sg:phone":"+1 519 369 2515",
    "sg:postcode":"N0G 1R0",
    "sg:province":"ON",
    "sg:tags":[
        "attorney"
    ],
    "wof:name":"Fallis Fallis & Mc Millan",
    "wof:placetype":"venue"
},
  "geometry": {"coordinates":[-80.8171920776,44.1763572693],"type":"Point"}
}