{
  "type": "Feature",
  "properties": {
    "addr:full":"4100 3E Av O Charlesbourg QC G1H 6E1",
    "addr:housenumber":"4100",
    "addr:postcode":"g1h 6e1",
    "addr:street":"3E Av O",
    "iso:country":"CA",
    "sg:address":"4100 3E Av O",
    "sg:city":"Charlesbourg",
    "sg:classifiers":[
        {
            "category":"Health Services",
            "subcategory":"Doctor",
            "type":"Services"
        }
    ],
    "sg:phone":"+1 418 622 6696",
    "sg:postcode":"G1H 6E1",
    "sg:province":"QC",
    "sg:tags":[
        "physiotherapist",
        "clinic"
    ],
    "wof:name":"Clinique Georges Morisset",
    "wof:placetype":"venue"
},
  "geometry": {"coordinates":[-71.252205,46.840069],"type":"Point"}
}