{
  "type": "Feature",
  "properties": {
    "addr:full":"404 94 Ave SE Calgary AB T2J 0E8",
    "addr:postcode":"t2j 0e8",
    "addr:street":"404 94 Ave Se",
    "iso:country":"CA",
    "sg:address":"404 94 Ave SE",
    "sg:city":"Calgary",
    "sg:classifiers":[
        {
            "category":"Organizations",
            "subcategory":"Professional Association",
            "type":"Services"
        }
    ],
    "sg:phone":"+1 403 253 2291",
    "sg:postcode":"T2J 0E8",
    "sg:province":"AB",
    "wof:name":"Society For Trtmnt of Autism",
    "wof:placetype":"venue"
},
  "geometry": {"coordinates":[-114.06043200000001,50.968739],"type":"Point"}
}