{
  "type": "Feature",
  "properties": {
    "addr:full":"55 Waterloo St Exeter ON N0M 1S2",
    "addr:housenumber":"55",
    "addr:postcode":"n0m 1s2",
    "addr:street":"Waterloo St",
    "iso:country":"CA",
    "sg:address":"55 Waterloo St",
    "sg:city":"Exeter",
    "sg:classifiers":[
        {
            "category":"Retail",
            "subcategory":"Auto Repair",
            "type":"Services"
        }
    ],
    "sg:phone":"+1 519 235 0411",
    "sg:postcode":"N0M 1S2",
    "sg:province":"ON",
    "sg:tags":[
        "body",
        "automobile",
        "painting"
    ],
    "wof:name":"Exeter Collision Ltd",
    "wof:placetype":"venue"
},
  "geometry": {"coordinates":[-81.481667,43.341301],"type":"Point"}
}