{
  "type": "Feature",
  "properties": {
    "addr:full":"12 Drapeau St #A Balmoral NB E8E 1H2",
    "addr:housenumber":"12",
    "addr:postcode":"e8e 1h2",
    "addr:street":"Drapeau St # A",
    "iso:country":"CA",
    "sg:address":"12 Drapeau St #A",
    "sg:city":"Balmoral",
    "sg:classifiers":[
        {
            "category":"Food & Beverages",
            "subcategory":"Groceries & Convenience Stores",
            "type":"Retail Goods"
        }
    ],
    "sg:phone":"+1 506 826 3485",
    "sg:postcode":"E8E 1H2",
    "sg:province":"NB",
    "sg:tags":[
        "grocer"
    ],
    "wof:name":"Depanneur Guitard Inc",
    "wof:placetype":"venue"
},
  "geometry": {"coordinates":[-66.409126,47.982201],"type":"Point"}
}