{
  "type": "Feature",
  "properties": {
    "addr:full":"20 Queen St W # 102 Toronto ON M5H 3R3",
    "addr:housenumber":"20",
    "addr:postcode":"m5h 3r3",
    "addr:street":"Queen St W # 102",
    "iso:country":"CA",
    "sg:address":"20 Queen St W # 102",
    "sg:city":"Toronto",
    "sg:classifiers":[
        {
            "category":"Restaurant",
            "type":"Food & Drink"
        }
    ],
    "sg:phone":"+1 416 340 7887",
    "sg:postcode":"M5H 3R3",
    "sg:province":"ON",
    "wof:name":"Duke of Richmond Pub",
    "wof:placetype":"venue"
},
  "geometry": {"coordinates":[-79.38004302980001,43.6523780823],"type":"Point"}
}