{
  "type": "Feature",
  "properties": {
    "addr:full":"19 Albert St Elliot Lake ON P5A 2Y7",
    "addr:housenumber":"19",
    "addr:postcode":"p5a 2y7",
    "addr:street":"Albert St",
    "iso:country":"CA",
    "sg:address":"19 Albert St",
    "sg:city":"Elliot Lake",
    "sg:classifiers":[
        {
            "category":"Building & Trades",
            "subcategory":"Construction",
            "type":"Services"
        }
    ],
    "sg:phone":"+1 705 848 7342",
    "sg:postcode":"P5A 2Y7",
    "sg:province":"ON",
    "sg:tags":[
        "painter",
        "contractor"
    ],
    "wof:name":"Jim's Contracting",
    "wof:placetype":"venue"
},
  "geometry": {"coordinates":[-82.624268,46.375378],"type":"Point"}
}