{
  "type": "Feature",
  "properties": {
    "addr:full":"76 Hawkcliff Pl NW Calgary AB T3G 2S1",
    "addr:housenumber":"76",
    "addr:postcode":"t3g 2s1",
    "addr:street":"Hawkcliff Pl Nw",
    "iso:country":"CA",
    "sg:address":"76 Hawkcliff Pl NW",
    "sg:city":"Calgary",
    "sg:classifiers":[
        {
            "category":"Health Services",
            "subcategory":"Doctor",
            "type":"Services"
        }
    ],
    "sg:phone":"+1 403 239 1465",
    "sg:postcode":"T3G 2S1",
    "sg:province":"AB",
    "sg:tags":[
        "dentist"
    ],
    "wof:name":"Calgary & District Dental Scty",
    "wof:placetype":"venue"
},
  "geometry": {"coordinates":[-114.166618347,51.1233062744],"type":"Point"}
}