{
  "type": "Feature",
  "properties": {
    "iso:country":"CA",
    "sg:city":"Mississauga",
    "sg:classifiers":[
        {
            "category":"Shopping",
            "subcategory":"Pharmacy",
            "type":"Retail Goods"
        }
    ],
    "sg:phone":"+1 905 820 2727",
    "sg:postcode":"L5L 3R6",
    "sg:province":"ON",
    "wof:name":"Jenpharm Drug Mart",
    "wof:placetype":"venue"
},
  "geometry": {"coordinates":[-79.682953,43.542343],"type":"Point"}
}