{
  "type": "Feature",
  "properties": {
    "addr:full":"208 Romaine St Peterborough ON K9J 2C4",
    "addr:housenumber":"208",
    "addr:postcode":"k9j 2c4",
    "addr:street":"Romaine St",
    "iso:country":"CA",
    "sg:address":"208 Romaine St",
    "sg:city":"Peterborough",
    "sg:classifiers":[
        {
            "category":"Organizations",
            "subcategory":"Religious Organization",
            "type":"Services"
        }
    ],
    "sg:phone":"+1 705 745 5549",
    "sg:postcode":"K9J 2C4",
    "sg:province":"ON",
    "sg:tags":[
        "church"
    ],
    "wof:name":"Sacred Heart Rectory",
    "wof:placetype":"venue"
},
  "geometry": {"coordinates":[-78.32017500000001,44.291794],"type":"Point"}
}