{
  "type": "Feature",
  "properties": {
    "iso:country":"CA",
    "sg:city":"Grande-Riviere",
    "sg:classifiers":[
        {
            "category":"Shopping",
            "subcategory":"Computers & Home Electronics",
            "type":"Retail Goods"
        }
    ],
    "sg:phone":"+1 418 385 3060",
    "sg:postcode":"G0C 1V0",
    "sg:province":"QC",
    "sg:tags":[
        "television",
        "radio"
    ],
    "wof:name":"Bernard Electronique Enr",
    "wof:placetype":"venue"
},
  "geometry": {"coordinates":[-64.47978973390001,48.4008903503],"type":"Point"}
}