{
  "type": "Feature",
  "properties": {
    "addr:full":"111 Rue Belanger Chateauguay QC J6J 4Z2",
    "addr:housenumber":"111",
    "addr:postcode":"j6j 4z2",
    "addr:street":"Rue Belanger",
    "iso:country":"CA",
    "sg:address":"111 Rue Belanger",
    "sg:city":"Chateauguay",
    "sg:classifiers":[
        {
            "category":"Wholesale",
            "subcategory":"Stationery",
            "type":"Manufacturing & Wholesale Goods"
        }
    ],
    "sg:phone":"+1 450 698 0707",
    "sg:postcode":"J6J 4Z2",
    "sg:province":"QC",
    "sg:tags":[
        "core",
        "tube",
        "paper"
    ],
    "wof:name":"Polyrol Paper Tube Inc",
    "wof:placetype":"venue"
},
  "geometry": {"coordinates":[-73.69637299999999,45.348129],"type":"Point"}
}