{
  "type": "Feature",
  "properties": {
    "addr:full":"105 Strowger Blvd Brockville ON K6V 5K1",
    "addr:housenumber":"105",
    "addr:postcode":"k6v 5k1",
    "addr:street":"Strowger Blvd",
    "iso:country":"CA",
    "sg:address":"105 Strowger Blvd",
    "sg:city":"Brockville",
    "sg:classifiers":[
        {
            "category":"Wholesale",
            "subcategory":"Sporting Goods",
            "type":"Manufacturing & Wholesale Goods"
        }
    ],
    "sg:phone":"+1 613 345 2320",
    "sg:postcode":"K6V 5K1",
    "sg:province":"ON",
    "wof:name":"Leslee Sports Importing",
    "wof:placetype":"venue"
},
  "geometry": {"coordinates":[-75.701263,44.593067],"type":"Point"}
}