{
  "type": "Feature",
  "properties": {
    "addr:full":"10605 135 St Surrey BC V3T 4C8",
    "addr:housenumber":"10605",
    "addr:postcode":"v3t 4c8",
    "addr:street":"135 St",
    "iso:country":"CA",
    "sg:address":"10605 135 St",
    "sg:city":"Surrey",
    "sg:classifiers":[
        {
            "category":"Arena",
            "subcategory":"Sports Club",
            "type":"Entertainment"
        }
    ],
    "sg:phone":"+1 604 930 5466",
    "sg:postcode":"V3T 4C8",
    "sg:province":"BC",
    "sg:tags":[
        "football"
    ],
    "wof:name":"B C Lions Football Club Inc",
    "wof:placetype":"venue"
},
  "geometry": {"coordinates":[-122.847748,49.191639],"type":"Point"}
}