{
  "type": "Feature",
  "properties": {
    "addr:full":"110 Wright Ave Dartmouth NS B3B 1R6",
    "addr:housenumber":"110",
    "addr:postcode":"b3b 1r6",
    "addr:street":"Wright Ave",
    "iso:country":"CA",
    "sg:address":"110 Wright Ave",
    "sg:city":"Dartmouth",
    "sg:classifiers":[
        {
            "category":"Manufacturing",
            "subcategory":"Glass & Minerals",
            "type":"Manufacturing & Wholesale Goods"
        }
    ],
    "sg:phone":"+1 902 468 2884",
    "sg:postcode":"B3B 1R6",
    "sg:province":"NS",
    "sg:tags":[
        "concrete",
        "brick",
        "block",
        "form"
    ],
    "wof:name":"Bird-Stairs",
    "wof:placetype":"venue"
},
  "geometry": {"coordinates":[-63.592026,44.7062],"type":"Point"}
}