{
  "type": "Feature",
  "properties": {
    "addr:full":"870 Hanwell Rd Fredericton NB E3B 6A2",
    "addr:housenumber":"870",
    "addr:postcode":"e3b 6a2",
    "addr:street":"Hanwell Rd",
    "iso:country":"CA",
    "sg:address":"870 Hanwell Rd",
    "sg:city":"Fredericton",
    "sg:classifiers":[
        {
            "category":"Wholesale",
            "subcategory":"Hardware",
            "type":"Manufacturing & Wholesale Goods"
        }
    ],
    "sg:phone":"+1 506 452 8107",
    "sg:postcode":"E3B 6A2",
    "sg:province":"NB",
    "sg:tags":[
        "equipment",
        "fireplace",
        "heating",
        "system"
    ],
    "wof:name":"Sunpoke Energy Systems Ltd",
    "wof:placetype":"venue"
},
  "geometry": {"coordinates":[-66.685822,45.952587],"type":"Point"}
}