{
  "type": "Feature",
  "properties": {
    "addr:full":"St Catharines ON L2R 1C8",
    "addr:postcode":"l2r 1c8",
    "iso:country":"CA",
    "sg:city":"St Catharines",
    "sg:classifiers":[
        {
            "category":"Professional",
            "subcategory":"Engineering",
            "type":"Services"
        }
    ],
    "sg:phone":"+1 905 704 0763",
    "sg:postcode":"L2R 1C8",
    "sg:province":"ON",
    "sg:tags":[
        "engineer"
    ],
    "wof:name":"Synectics",
    "wof:placetype":"venue"
},
  "geometry": {"coordinates":[-79.265007019,43.1780548096],"type":"Point"}
}