{
  "type": "Feature",
  "properties": {
    "addr:full":"321 Summerwood Pl SE Airdrie AB T4B 1W4",
    "addr:housenumber":"321",
    "addr:postcode":"t4b 1w4",
    "addr:street":"Summerwood Pl Se",
    "iso:country":"CA",
    "sg:address":"321 Summerwood Pl SE",
    "sg:city":"Airdrie",
    "sg:classifiers":[
        {
            "category":"Building & Trades",
            "subcategory":"Plumbing",
            "type":"Services"
        }
    ],
    "sg:phone":"+1 403 948 3988",
    "sg:postcode":"T4B 1W4",
    "sg:province":"AB",
    "sg:tags":[
        "refrigeration",
        "contractor"
    ],
    "wof:name":"Airdrie Appliance Svc",
    "wof:placetype":"venue"
},
  "geometry": {"coordinates":[-114.01097106900001,51.2769088745],"type":"Point"}
}