{
  "type": "Feature",
  "properties": {
    "addr:full":"7813 Av Paiement Charlesbourg QC G1H 5P5",
    "addr:housenumber":"7813",
    "addr:postcode":"g1h 5p5",
    "addr:street":"Av Paiement",
    "iso:country":"CA",
    "sg:address":"7813 Av Paiement",
    "sg:city":"Charlesbourg",
    "sg:classifiers":[
        {
            "category":"Shopping",
            "subcategory":"Clothing, Apparel, & Fashions",
            "type":"Retail Goods"
        }
    ],
    "sg:phone":"+1 418 626 7981",
    "sg:postcode":"G1H 5P5",
    "sg:province":"QC",
    "sg:tags":[
        "item",
        "boutique"
    ],
    "wof:name":"Boutique Helene Enr",
    "wof:placetype":"venue"
},
  "geometry": {"coordinates":[-71.27831999999999,46.854183],"type":"Point"}
}