{
  "type": "Feature",
  "properties": {
    "addr:full":"North Rustico PE C0A 1X0",
    "addr:postcode":"c0a 1x0",
    "iso:country":"CA",
    "sg:city":"North Rustico",
    "sg:classifiers":[
        {
            "category":"Food & Beverages",
            "subcategory":"Groceries & Convenience Stores",
            "type":"Retail Goods"
        }
    ],
    "sg:phone":"+1 902 963 2725",
    "sg:postcode":"C0A 1X0",
    "sg:province":"PE",
    "sg:tags":[
        "grocer"
    ],
    "wof:name":"Island Food Ctr",
    "wof:placetype":"venue"
},
  "geometry": {"coordinates":[-63.313205719,46.4581413269],"type":"Point"}
}