{
  "type": "Feature",
  "properties": {
    "addr:full":"19 Main St S Newmarket ON L3Y 3Y1",
    "addr:housenumber":"19",
    "addr:postcode":"l3y 3y1",
    "addr:street":"Main St S",
    "iso:country":"CA",
    "sg:address":"19 Main St S",
    "sg:city":"Newmarket",
    "sg:classifiers":[
        {
            "category":"Personal",
            "subcategory":"Beauty Salon",
            "type":"Services"
        }
    ],
    "sg:phone":"+1 905 895 5632",
    "sg:postcode":"L3Y 3Y1",
    "sg:province":"ON",
    "sg:tags":[
        "barber"
    ],
    "wof:name":"Rocco's Barber Shop",
    "wof:placetype":"venue"
},
  "geometry": {"coordinates":[-79.460739,44.058456],"type":"Point"}
}