{
  "type": "Feature",
  "properties": {
    "addr:full":"1117 101st St North Battleford SK S9A 0Z5",
    "addr:housenumber":"1117",
    "addr:postcode":"s9a 0z5",
    "addr:street":"101St St",
    "iso:country":"CA",
    "sg:address":"1117 101st St",
    "sg:city":"North Battleford",
    "sg:classifiers":[
        {
            "category":"Shopping",
            "subcategory":"Used Merchandise",
            "type":"Retail Goods"
        }
    ],
    "sg:phone":"+1 306 446 2922",
    "sg:postcode":"S9A 0Z5",
    "sg:province":"SK",
    "sg:tags":[
        "second",
        "pawnbroker",
        "store",
        "hand"
    ],
    "wof:name":"Northwest Trading CO",
    "wof:placetype":"venue"
},
  "geometry": {"coordinates":[-108.297791,52.773788],"type":"Point"}
}