{
  "type": "Feature",
  "properties": {
    "addr:full":"Sainte-Foy QC G1V 3W3",
    "addr:postcode":"g1v 3w3",
    "iso:country":"CA",
    "sg:city":"Sainte-Foy",
    "sg:classifiers":[
        {
            "category":"Organizations",
            "subcategory":"Professional Association",
            "type":"Services"
        }
    ],
    "sg:phone":"+1 418 654 3232",
    "sg:postcode":"G1V 3W3",
    "sg:province":"QC",
    "wof:name":"Amdeq",
    "wof:placetype":"venue"
},
  "geometry": {"coordinates":[-71.2917633057,46.7692108154],"type":"Point"}
}