{
  "type": "Feature",
  "properties": {
    "addr:full":"5018 80 Ave SE Calgary AB T2C 2X3",
    "addr:housenumber":"5018",
    "addr:postcode":"t2c 2x3",
    "addr:street":"80 Ave Se",
    "iso:country":"CA",
    "sg:address":"5018 80 Ave SE",
    "sg:city":"Calgary",
    "sg:classifiers":[
        {
            "category":"Manufacturing",
            "subcategory":"Tools & Machinery",
            "type":"Manufacturing & Wholesale Goods"
        }
    ],
    "sg:phone":"+1 403 272 0562",
    "sg:postcode":"T2C 2X3",
    "sg:province":"AB",
    "sg:tags":[
        "equipment",
        "purifying",
        "cleaning",
        "air"
    ],
    "wof:name":"Dexon Canada Mfg Corp",
    "wof:placetype":"venue"
},
  "geometry": {"coordinates":[-113.96188354500001,50.9802284241],"type":"Point"}
}