{
  "type": "Feature",
  "properties": {
    "addr:full":"1816 Broadway W Vancouver BC V6J 1Y9",
    "addr:housenumber":"1816",
    "addr:postcode":"v6j 1y9",
    "addr:street":"Broadway W",
    "iso:country":"CA",
    "sg:address":"1816 Broadway W",
    "sg:city":"Vancouver",
    "sg:classifiers":[
        {
            "category":"Health Services",
            "subcategory":"Doctor",
            "type":"Services"
        }
    ],
    "sg:phone":"+1 604 736 1888",
    "sg:postcode":"V6J 1Y9",
    "sg:province":"BC",
    "sg:tags":[
        "clinic"
    ],
    "wof:name":"Broadway & Burrard Walk-In",
    "wof:placetype":"venue"
},
  "geometry": {"coordinates":[-123.14630099999999,49.263603],"type":"Point"}
}