{
  "type": "Feature",
  "properties": {
    "addr:full":"175 Dundas St London ON N6A 1G4",
    "addr:housenumber":"175",
    "addr:postcode":"n6a 1g4",
    "addr:street":"Dundas St",
    "iso:country":"CA",
    "sg:address":"175 Dundas St",
    "sg:city":"London",
    "sg:classifiers":[
        {
            "category":"Personal",
            "subcategory":"Beauty Salon",
            "type":"Services"
        }
    ],
    "sg:phone":"+1 519 660 6432",
    "sg:postcode":"N6A 1G4",
    "sg:province":"ON",
    "wof:name":"First Choice Hair Cutters",
    "wof:placetype":"venue"
},
  "geometry": {"coordinates":[-81.2489929199,42.9837684631],"type":"Point"}
}