{
  "type": "Feature",
  "properties": {
    "addr:full":"1209 Richmond St #101 London ON N6A 3L7",
    "addr:housenumber":"1209",
    "addr:postcode":"n6a 3l7",
    "addr:street":"Richmond St # 101",
    "iso:country":"CA",
    "sg:address":"1209 Richmond St #101",
    "sg:city":"London",
    "sg:classifiers":[
        {
            "category":"Real Estate",
            "subcategory":"Real Estate Operator",
            "type":"Services"
        }
    ],
    "sg:phone":"+1 519 438 8801",
    "sg:postcode":"N6A 3L7",
    "sg:province":"ON",
    "sg:tags":[
        "apartment"
    ],
    "wof:name":"Somerset Place",
    "wof:placetype":"venue"
},
  "geometry": {"coordinates":[-81.2640304565,43.011505127],"type":"Point"}
}