{
  "type": "Feature",
  "properties": {
    "addr:full":"2495 Arbutus Rd Victoria BC V8N 1V9",
    "addr:housenumber":"2495",
    "addr:postcode":"v8n 1v9",
    "addr:street":"Arbutus Rd",
    "iso:country":"CA",
    "sg:address":"2495 Arbutus Rd",
    "sg:city":"Victoria",
    "sg:classifiers":[
        {
            "category":"Recreation",
            "type":"Entertainment"
        }
    ],
    "sg:phone":"+1 250 477 4401",
    "sg:postcode":"V8N 1V9",
    "sg:province":"BC",
    "sg:tags":[
        "hall",
        "auditorium"
    ],
    "wof:name":"Goward House",
    "wof:placetype":"venue"
},
  "geometry": {"coordinates":[-123.36346399999999,48.415897],"type":"Point"}
}