{
  "type": "Feature",
  "properties": {
    "addr:full":"2914 Danforth Ave Toronto ON M4C 1M1",
    "addr:housenumber":"2914",
    "addr:postcode":"m4c 1m1",
    "addr:street":"Danforth Ave",
    "iso:country":"CA",
    "sg:address":"2914 Danforth Ave",
    "sg:city":"Toronto",
    "sg:classifiers":[
        {
            "category":"Health Services",
            "subcategory":"Doctor",
            "type":"Services"
        }
    ],
    "sg:phone":"+1 416 690 4030",
    "sg:postcode":"M4C 1M1",
    "sg:province":"ON",
    "sg:tags":[
        "dentist"
    ],
    "wof:name":"Walkden, R DDS",
    "wof:placetype":"venue"
},
  "geometry": {"coordinates":[-79.2934799194,43.6901283264],"type":"Point"}
}