{
  "type": "Feature",
  "properties": {
    "addr:full":"3028 Red Bluff Rd Quesnel BC V2J 6C6",
    "addr:housenumber":"3028",
    "addr:postcode":"v2j 6c6",
    "addr:street":"Red Bluff Rd",
    "iso:country":"CA",
    "sg:address":"3028 Red Bluff Rd",
    "sg:city":"Quesnel",
    "sg:classifiers":[
        {
            "category":"Home & Garden",
            "subcategory":"Garden Supply",
            "type":"Retail Goods"
        }
    ],
    "sg:phone":"+1 250 747 2915",
    "sg:postcode":"V2J 6C6",
    "sg:province":"BC",
    "sg:tags":[
        "nurseryman"
    ],
    "wof:name":"Richbar Nursery Ltd",
    "wof:placetype":"venue"
},
  "geometry": {"coordinates":[-122.498245,52.978119],"type":"Point"}
}