{
  "type": "Feature",
  "properties": {
    "addr:full":"365 Rue DE Louvain O Montreal QC H2N 2J1",
    "addr:housenumber":"365",
    "addr:postcode":"h2n 2j1",
    "addr:street":"Rue De Louvain O",
    "iso:country":"CA",
    "sg:address":"365 Rue DE Louvain O",
    "sg:city":"Montreal",
    "sg:classifiers":[
        {
            "category":"Wholesale",
            "subcategory":"Apparel",
            "type":"Manufacturing & Wholesale Goods"
        }
    ],
    "sg:phone":"+1 514 381 1853",
    "sg:postcode":"H2N 2J1",
    "sg:province":"QC",
    "sg:tags":[
        "clothing"
    ],
    "wof:name":"Philhobar Design Canada Ltee",
    "wof:placetype":"venue"
},
  "geometry": {"coordinates":[-73.65798950200001,45.5402030945],"type":"Point"}
}