{
  "type": "Feature",
  "properties": {
    "iso:country":"CA",
    "sg:address":"978 Denman St",
    "sg:city":"Vancouver",
    "sg:classifiers":[
        {
            "category":"Personal",
            "subcategory":"Beauty Salon",
            "type":"Services"
        }
    ],
    "sg:phone":"+1 604 685 6813",
    "sg:postcode":"V6G 2M1",
    "sg:province":"BC",
    "wof:name":"Natasha Hair Design",
    "wof:placetype":"venue"
},
  "geometry": {"coordinates":[-123.138244629,49.2894477844],"type":"Point"}
}