{
  "type": "Feature",
  "properties": {
    "addr:full":"56 Elora St Mildmay ON N0G 2J0",
    "addr:housenumber":"56",
    "addr:postcode":"n0g 2j0",
    "addr:street":"Elora St",
    "iso:country":"CA",
    "sg:address":"56 Elora St",
    "sg:city":"Mildmay",
    "sg:classifiers":[
        {
            "category":"Government",
            "subcategory":"Office",
            "type":"Public Place"
        }
    ],
    "sg:phone":"+1 519 367 5525",
    "sg:postcode":"N0G 2J0",
    "sg:province":"ON",
    "sg:tags":[
        "village"
    ],
    "wof:name":"Mildmay Post Office",
    "wof:placetype":"venue"
},
  "geometry": {"coordinates":[-81.116997,44.041286],"type":"Point"}
}