{
  "type": "Feature",
  "properties": {
    "addr:full":"9155 79 Ave NW Edmonton AB T6C 0R9",
    "addr:housenumber":"9155",
    "addr:postcode":"t6c 0r9",
    "addr:street":"79 Ave Nw",
    "iso:country":"CA",
    "sg:address":"9155 79 Ave NW",
    "sg:city":"Edmonton",
    "sg:classifiers":[
        {
            "category":"Organizations",
            "subcategory":"Religious Organization",
            "type":"Services"
        }
    ],
    "sg:phone":"+1 780 466 5281",
    "sg:postcode":"T6C 0R9",
    "sg:province":"AB",
    "sg:tags":[
        "church"
    ],
    "wof:name":"St Paul's Lutheran Church",
    "wof:placetype":"venue"
},
  "geometry": {"coordinates":[-113.468360901,53.5148925781],"type":"Point"}
}