{
  "type": "Feature",
  "properties": {
    "addr:full":"950 Rue Hall Terrebonne QC J6W 4L5",
    "addr:housenumber":"950",
    "addr:postcode":"j6w 4l5",
    "addr:street":"Rue Hall",
    "iso:country":"CA",
    "sg:address":"950 Rue Hall",
    "sg:city":"Terrebonne",
    "sg:classifiers":[
        {
            "category":"Retail",
            "subcategory":"Auto Rental",
            "type":"Services"
        }
    ],
    "sg:phone":"+1 450 961 4700",
    "sg:postcode":"J6W 4L5",
    "sg:province":"QC",
    "sg:tags":[
        "renting",
        "automobile"
    ],
    "wof:name":"Entreprise Location D'Autos",
    "wof:placetype":"venue"
},
  "geometry": {"coordinates":[-73.632294,45.704674],"type":"Point"}
}