{
  "type": "Feature",
  "properties": {
    "addr:full":"18 Pine St # 307 Kitchener ON N2H 5Z8",
    "addr:housenumber":"18;307",
    "addr:postcode":"n2h 5z8",
    "addr:street":"Pine St #",
    "iso:country":"CA",
    "sg:address":"18 Pine St # 307",
    "sg:city":"Kitchener",
    "sg:classifiers":[
        {
            "category":"Health Services",
            "subcategory":"Medical Lab",
            "type":"Services"
        }
    ],
    "sg:phone":"+1 519 570 3660",
    "sg:postcode":"N2H 5Z8",
    "sg:province":"ON",
    "sg:tags":[
        "x"
    ],
    "wof:name":"Stronell, R",
    "wof:placetype":"venue"
},
  "geometry": {"coordinates":[-80.5112457275,43.457611084],"type":"Point"}
}