{
  "type": "Feature",
  "properties": {
    "addr:full":"RR 1 Lcd 9 Edmonton AB T6H 4N6",
    "addr:housenumber":"9",
    "addr:postcode":"t6h 4n6",
    "addr:street":"Rr 1 Lcd",
    "iso:country":"CA",
    "sg:address":"RR 1 Lcd 9",
    "sg:city":"Edmonton",
    "sg:classifiers":[
        {
            "category":"Recreation",
            "type":"Entertainment"
        }
    ],
    "sg:phone":"+1 780 470 5646",
    "sg:postcode":"T6H 4N6",
    "sg:province":"AB",
    "sg:tags":[
        "center"
    ],
    "wof:name":"Enoch Cree Nation",
    "wof:placetype":"venue"
},
  "geometry": {"coordinates":[-113.49037199999999,53.546219],"type":"Point"}
}