{
  "type": "Feature",
  "properties": {
    "iso:country":"CA",
    "sg:address":"610 Sixth St # 136",
    "sg:city":"New Westminster",
    "sg:classifiers":[
        {
            "category":"Manufacturing",
            "subcategory":"Wood Products",
            "type":"Manufacturing & Wholesale Goods"
        }
    ],
    "sg:phone":"+1 604 540 0175",
    "sg:postcode":"V3L 3C2",
    "sg:province":"BC",
    "sg:tags":[
        "picture",
        "frame"
    ],
    "wof:name":"Regis Pictures & Frames",
    "wof:placetype":"venue"
},
  "geometry": {"coordinates":[-122.920890808,49.2133674622],"type":"Point"}
}