{
  "type": "Feature",
  "properties": {
    "addr:full":"1329 Niakwa Rd E #4 Winnipeg MB R2J 3T4",
    "addr:housenumber":"1329",
    "addr:postcode":"r2j 3t4",
    "addr:street":"Niakwa Rd E # 4",
    "iso:country":"CA",
    "sg:address":"1329 Niakwa Rd E #4",
    "sg:city":"Winnipeg",
    "sg:classifiers":[
        {
            "category":"Wholesale",
            "subcategory":"Sporting Goods",
            "type":"Manufacturing & Wholesale Goods"
        }
    ],
    "sg:phone":"+1 204 253 7499",
    "sg:postcode":"R2J 3T4",
    "sg:province":"MB",
    "sg:tags":[
        "pool",
        "swimming"
    ],
    "wof:name":"Side Lines Distribution",
    "wof:placetype":"venue"
},
  "geometry": {"coordinates":[-97.04613500000001,49.856609],"type":"Point"}
}