{
  "type": "Feature",
  "properties": {
    "addr:full":"7 Rue DE LA Nicolet # A Victoriaville QC G6P 7H2",
    "addr:housenumber":"7",
    "addr:postcode":"g6p 7h2",
    "addr:street":"Rue De La Nicolet # A",
    "iso:country":"CA",
    "sg:address":"7 Rue DE LA Nicolet # A",
    "sg:city":"Victoriaville",
    "sg:classifiers":[
        {
            "category":"Building & Trades",
            "subcategory":"Construction",
            "type":"Services"
        }
    ],
    "sg:phone":"+1 819 752 9966",
    "sg:postcode":"G6P 7H2",
    "sg:province":"QC",
    "sg:tags":[
        "excavating",
        "road",
        "contractor"
    ],
    "wof:name":"Gagne Excavation Ltee",
    "wof:placetype":"venue"
},
  "geometry": {"coordinates":[-71.96120500000001,46.069157],"type":"Point"}
}