{
  "type": "Feature",
  "properties": {
    "addr:full":"6 Main St W Grimsby ON L3M 1R4",
    "addr:housenumber":"6",
    "addr:postcode":"l3m 1r4",
    "addr:street":"Main St W",
    "iso:country":"CA",
    "sg:address":"6 Main St W",
    "sg:city":"Grimsby",
    "sg:classifiers":[
        {
            "category":"Retail",
            "subcategory":"Repair Shop",
            "type":"Services"
        }
    ],
    "sg:phone":"+1 905 945 5134",
    "sg:postcode":"L3M 1R4",
    "sg:province":"ON",
    "sg:tags":[
        "lock",
        "locksmith"
    ],
    "wof:name":"Secure Locksmithing Svc",
    "wof:placetype":"venue"
},
  "geometry": {"coordinates":[-79.56089,43.193348],"type":"Point"}
}