{
  "type": "Feature",
  "properties": {
    "addr:full":"33 Oak St E Leamington ON N8H 2C3",
    "addr:housenumber":"33",
    "addr:postcode":"n8h 2c3",
    "addr:street":"Oak St E",
    "iso:country":"CA",
    "sg:address":"33 Oak St E",
    "sg:city":"Leamington",
    "sg:classifiers":[
        {
            "category":"Food & Beverages",
            "subcategory":"Groceries & Convenience Stores",
            "type":"Retail Goods"
        }
    ],
    "sg:phone":"+1 519 326 9898",
    "sg:postcode":"N8H 2C3",
    "sg:province":"ON",
    "sg:tags":[
        "grocer"
    ],
    "wof:name":"Oak & Victoria Express",
    "wof:placetype":"venue"
},
  "geometry": {"coordinates":[-82.596901,42.046642],"type":"Point"}
}