{
  "type": "Feature",
  "properties": {
    "addr:full":"560 Elmhurst Rd Winnipeg MB R3R 0V1",
    "addr:housenumber":"560",
    "addr:postcode":"r3r 0v1",
    "addr:street":"Elmhurst Rd",
    "iso:country":"CA",
    "sg:address":"560 Elmhurst Rd",
    "sg:city":"Winnipeg",
    "sg:classifiers":[
        {
            "category":"Real Estate",
            "subcategory":"Real Estate Agent",
            "type":"Services"
        }
    ],
    "sg:phone":"+1 204 896 3450",
    "sg:postcode":"R3R 0V1",
    "sg:province":"MB",
    "wof:name":"Wadhwa Realty",
    "wof:placetype":"venue"
},
  "geometry": {"coordinates":[-97.256927,49.856644],"type":"Point"}
}