{
  "type": "Feature",
  "properties": {
    "addr:full":"925 Watt St Winnipeg MB R2K 2T4",
    "addr:housenumber":"925",
    "addr:postcode":"r2k 2t4",
    "addr:street":"Watt St",
    "iso:country":"CA",
    "sg:address":"925 Watt St",
    "sg:city":"Winnipeg",
    "sg:classifiers":[
        {
            "category":"Sports & Exercise",
            "subcategory":"Golf",
            "type":"Entertainment"
        }
    ],
    "sg:phone":"+1 204 988 1535",
    "sg:postcode":"R2K 2T4",
    "sg:province":"MB",
    "sg:tags":[
        "course"
    ],
    "wof:name":"Rossmere Country Club",
    "wof:placetype":"venue"
},
  "geometry": {"coordinates":[-97.08721160890001,49.9283256531],"type":"Point"}
}