{
  "type": "Feature",
  "properties": {
    "addr:full":"Oliver BC V0H 1T0",
    "addr:postcode":"bc v0h 1t0",
    "iso:country":"CA",
    "sg:city":"Oliver",
    "sg:classifiers":[
        {
            "category":"Shopping",
            "subcategory":"Department Store",
            "type":"Retail Goods"
        }
    ],
    "sg:phone":"+1 250 498 4489",
    "sg:postcode":"V0H 1T0",
    "sg:province":"BC",
    "wof:name":"Saan Stores Ltd",
    "wof:placetype":"venue"
},
  "geometry": {"coordinates":[-119.55175800000001,49.178581],"type":"Point"}
}