{
  "type": "Feature",
  "properties": {
    "addr:full":"11 Colonel By Dr Ottawa ON K1N 9H4",
    "addr:housenumber":"11",
    "addr:postcode":"k1n 9h4",
    "addr:street":"Colonel By Dr",
    "iso:country":"CA",
    "sg:address":"11 Colonel By Dr",
    "sg:city":"Ottawa",
    "sg:classifiers":[
        {
            "category":"Travel",
            "subcategory":"Hotels & Motels",
            "type":"Entertainment"
        }
    ],
    "sg:phone":"+1 613 560 7000",
    "sg:postcode":"K1N 9H4",
    "sg:province":"ON",
    "wof:name":"Westin Ottawa",
    "wof:placetype":"venue"
},
  "geometry": {"coordinates":[-75.69264221189999,45.4248733521],"type":"Point"}
}