{
  "type": "Feature",
  "properties": {
    "iso:country":"CA",
    "sg:address":"70 17th St W",
    "sg:city":"Prince Albert",
    "sg:classifiers":[
        {
            "category":"Organizations",
            "subcategory":"Labor Organization",
            "type":"Services"
        }
    ],
    "sg:phone":"+1 306 922 3895",
    "sg:postcode":"S6V 3X3",
    "sg:province":"SK",
    "wof:name":"Cupe",
    "wof:placetype":"venue"
},
  "geometry": {"coordinates":[-105.756187439,53.197883606],"type":"Point"}
}