{
  "type": "Feature",
  "properties": {
    "addr:full":"Moncton NB E1E 4E3",
    "addr:postcode":"e1e 4e3",
    "iso:country":"CA",
    "sg:city":"Moncton",
    "sg:classifiers":[
        {
            "category":"Building & Trades",
            "subcategory":"Plumbing",
            "type":"Services"
        }
    ],
    "sg:phone":"+1 506 857 8890",
    "sg:postcode":"E1E 4E3",
    "sg:province":"NB",
    "sg:tags":[
        "air",
        "conditioning",
        "contractor",
        "system",
        "heating"
    ],
    "wof:name":"Honeywell Limited",
    "wof:placetype":"venue"
},
  "geometry": {"coordinates":[-64.84045399999999,46.088097],"type":"Point"}
}