{
  "type": "Feature",
  "properties": {
    "addr:full":"2 Cottage St Berwick NS B0P 1E0",
    "addr:housenumber":"2",
    "addr:postcode":"b0p 1e0",
    "addr:street":"Cottage St",
    "iso:country":"CA",
    "sg:address":"2 Cottage St",
    "sg:city":"Berwick",
    "sg:classifiers":[
        {
            "category":"Arena",
            "subcategory":"Sports Club",
            "type":"Entertainment"
        }
    ],
    "sg:phone":"+1 902 538 9070",
    "sg:postcode":"B0P 1E0",
    "sg:province":"NS",
    "sg:tags":[
        "athletic",
        "fields",
        "stadium"
    ],
    "wof:name":"Berwick Arena",
    "wof:placetype":"venue"
},
  "geometry": {"coordinates":[-64.726135,45.049469],"type":"Point"}
}