{
  "type": "Feature",
  "properties": {
    "addr:full":"Hamilton ON L8E 2X3",
    "addr:postcode":"l8e 2x3",
    "iso:country":"CA",
    "sg:city":"Hamilton",
    "sg:classifiers":[
        {
            "category":"Food & Beverages",
            "subcategory":"Specialty",
            "type":"Retail Goods"
        }
    ],
    "sg:phone":"+1 905 573 0003",
    "sg:postcode":"L8E 2X3",
    "sg:province":"ON",
    "sg:tags":[
        "water",
        "bulk",
        "company"
    ],
    "wof:name":"Water Source",
    "wof:placetype":"venue"
},
  "geometry": {"coordinates":[-79.76026153559999,43.2378005981],"type":"Point"}
}