{
  "type": "Feature",
  "properties": {
    "addr:full":"Calgary AB T2J 7G9",
    "addr:postcode":"t2j 7g9",
    "iso:country":"CA",
    "sg:city":"Calgary",
    "sg:classifiers":[
        {
            "category":"Shopping",
            "subcategory":"Clothing, Apparel, & Fashions",
            "type":"Retail Goods"
        }
    ],
    "sg:phone":"+1 403 225 9777",
    "sg:postcode":"T2J 7G9",
    "sg:province":"AB",
    "sg:tags":[
        "alteration"
    ],
    "wof:name":"Hanna's Design & Alterations",
    "wof:placetype":"venue"
},
  "geometry": {"coordinates":[-114.06999999999999,50.943905],"type":"Point"}
}