{
  "type": "Feature",
  "properties": {
    "iso:country":"CA",
    "sg:address":"1009 Trim Rd",
    "sg:city":"Orleans",
    "sg:classifiers":[
        {
            "category":"Recreation",
            "subcategory":"Marina",
            "type":"Entertainment"
        }
    ],
    "sg:phone":"+1 613 841 0778",
    "sg:postcode":"K4A 3P4",
    "sg:province":"ON",
    "sg:tags":[
        "bait",
        "fishing"
    ],
    "wof:name":"Petrie Island Bait & Tackle",
    "wof:placetype":"venue"
},
  "geometry": {"coordinates":[-75.48381,45.498512],"type":"Point"}
}