{
  "type": "Feature",
  "properties": {
    "addr:full":"2919 Douglasdale Blvd SE Calgary AB T2Z 2H9",
    "addr:postcode":"2919;t2z 2h9",
    "addr:street":"Douglasdale Blvd Se",
    "iso:country":"CA",
    "sg:address":"2919 Douglasdale Blvd SE",
    "sg:city":"Calgary",
    "sg:classifiers":[
        {
            "category":"Education",
            "subcategory":"School",
            "type":"Public Place"
        }
    ],
    "sg:phone":"+1 403 203 3466",
    "sg:postcode":"T2Z 2H9",
    "sg:province":"AB",
    "wof:name":"Monsignor Js Smith Elementary",
    "wof:placetype":"venue"
},
  "geometry": {"coordinates":[-113.99077606199999,50.940864563],"type":"Point"}
}