{
  "type": "Feature",
  "properties": {
    "iso:country":"CA",
    "sg:address":"129 Mitton St S",
    "sg:city":"Sarnia",
    "sg:classifiers":[
        {
            "category":"Home & Garden",
            "subcategory":"Home Furnishings",
            "type":"Retail Goods"
        }
    ],
    "sg:phone":"+1 519 332 0880",
    "sg:postcode":"N7T 3C5",
    "sg:province":"ON",
    "sg:tags":[
        "utensil",
        "cooking"
    ],
    "wof:name":"Alcove Kitchen Widgets",
    "wof:placetype":"venue"
},
  "geometry": {"coordinates":[-82.3985824585,42.9697380066],"type":"Point"}
}