{
  "type": "Feature",
  "properties": {
    "addr:full":"1155 Kingsway Vancouver BC V5V 3C9",
    "addr:housenumber":"1155",
    "addr:postcode":"v5v 3c9",
    "addr:street":"Kingsway",
    "iso:country":"CA",
    "sg:address":"1155 Kingsway",
    "sg:city":"Vancouver",
    "sg:classifiers":[
        {
            "category":"Travel",
            "subcategory":"Travel Agent",
            "type":"Entertainment"
        }
    ],
    "sg:phone":"+1 604 876 5026",
    "sg:postcode":"V5V 3C9",
    "sg:province":"BC",
    "sg:tags":[
        "agency",
        "bureau"
    ],
    "wof:name":"Han MI Tour & Travel",
    "wof:placetype":"venue"
},
  "geometry": {"coordinates":[-123.080543518,49.2525291443],"type":"Point"}
}