{
  "type": "Feature",
  "properties": {
    "addr:full":"116 Cedar St Woodstock NB E7M 1E9",
    "addr:housenumber":"116",
    "addr:postcode":"e7m 1e9",
    "addr:street":"Cedar St",
    "iso:country":"CA",
    "sg:address":"116 Cedar St",
    "sg:city":"Woodstock",
    "sg:classifiers":[
        {
            "category":"Taxi",
            "type":"Transportation"
        }
    ],
    "sg:phone":"+1 506 328 9581",
    "sg:postcode":"E7M 1E9",
    "sg:province":"NB",
    "sg:tags":[
        "delivery",
        "taxicab"
    ],
    "wof:name":"Mike's Taxi",
    "wof:placetype":"venue"
},
  "geometry": {"coordinates":[-67.5784,46.152672],"type":"Point"}
}