{
  "type": "Feature",
  "properties": {
    "iso:country":"CA",
    "sg:address":"5805 Boul Grande-Allee",
    "sg:city":"Brossard",
    "sg:classifiers":[
        {
            "category":"Real Estate",
            "subcategory":"Real Estate Operator",
            "type":"Services"
        }
    ],
    "sg:phone":"+1 450 676 2272",
    "sg:postcode":"J4Z 3G4",
    "sg:province":"QC",
    "sg:tags":[
        "apartment"
    ],
    "wof:name":"Office Municipal D'Habitation",
    "wof:placetype":"venue"
},
  "geometry": {"coordinates":[-73.437912,45.470833],"type":"Point"}
}