{
  "type": "Feature",
  "properties": {
    "addr:full":"694 Main St Sussex NB E4E 7H9",
    "addr:housenumber":"694",
    "addr:postcode":"e4e 7h9",
    "addr:street":"Main St",
    "iso:country":"CA",
    "sg:address":"694 Main St",
    "sg:city":"Sussex",
    "sg:classifiers":[
        {
            "category":"Professional",
            "subcategory":"Accounting & Tax Preparation",
            "type":"Services"
        }
    ],
    "sg:phone":"+1 506 432 6106",
    "sg:postcode":"E4E 7H9",
    "sg:province":"NB",
    "sg:tags":[
        "accountant"
    ],
    "wof:name":"Skaling, Frank L CA",
    "wof:placetype":"venue"
},
  "geometry": {"coordinates":[-65.505234,45.722935],"type":"Point"}
}