{
  "type": "Feature",
  "properties": {
    "addr:full":"310 76E Rue O Charlesbourg QC G1H 4R6",
    "addr:housenumber":"310",
    "addr:postcode":"g1h 4r6",
    "addr:street":"76E Rue O",
    "iso:country":"CA",
    "sg:address":"310 76E Rue O",
    "sg:city":"Charlesbourg",
    "sg:classifiers":[
        {
            "category":"Wholesale",
            "subcategory":"Machinery & Supplies",
            "type":"Manufacturing & Wholesale Goods"
        }
    ],
    "sg:phone":"+1 418 628 8181",
    "sg:postcode":"G1H 4R6",
    "sg:province":"QC",
    "sg:tags":[
        "salon",
        "tanning",
        "beauty"
    ],
    "wof:name":"Service Plus Alain Thibault",
    "wof:placetype":"venue"
},
  "geometry": {"coordinates":[-71.25118999999999,46.845703],"type":"Point"}
}