{
  "type": "Feature",
  "properties": {
    "addr:full":"Val-Des-Monts QC J8N 2G9",
    "addr:postcode":"j8n 2g9",
    "iso:country":"CA",
    "sg:city":"Val-Des-Monts",
    "sg:classifiers":[
        {
            "category":"Education",
            "subcategory":"School",
            "type":"Public Place"
        }
    ],
    "sg:phone":"+1 819 457 2335",
    "sg:postcode":"J8N 2G9",
    "sg:province":"QC",
    "wof:name":"Poltimore Elementary School",
    "wof:placetype":"venue"
},
  "geometry": {"coordinates":[-75.71249400000001,45.788967],"type":"Point"}
}