{
  "type": "Feature",
  "properties": {
    "addr:full":"970 Dixon Rd Etobicoke ON M9W 1J9",
    "addr:housenumber":"970",
    "addr:postcode":"m9w 1j9",
    "addr:street":"Dixon Rd",
    "iso:country":"CA",
    "sg:address":"970 Dixon Rd",
    "sg:city":"Etobicoke",
    "sg:classifiers":[
        {
            "category":"Retail",
            "subcategory":"Auto Rental",
            "type":"Services"
        }
    ],
    "sg:phone":"+1 416 213 0736",
    "sg:postcode":"M9W 1J9",
    "sg:province":"ON",
    "sg:tags":[
        "renting",
        "automobile"
    ],
    "wof:name":"Thrifty Car Rental",
    "wof:placetype":"venue"
},
  "geometry": {"coordinates":[-79.5980606079,43.686882019],"type":"Point"}
}