{
  "type": "Feature",
  "properties": {
    "addr:full":"3131 Ch D'Oka Sainte-Marthe-Sur-Le-Lac QC J0N 1P0",
    "addr:postcode":"3131;j0n 1p0",
    "addr:street":"Ch D'Oka",
    "iso:country":"CA",
    "sg:address":"3131 Ch D'Oka",
    "sg:city":"Sainte-Marthe-Sur-Le-Lac",
    "sg:classifiers":[
        {
            "category":"Restaurant",
            "type":"Food & Drink"
        }
    ],
    "sg:phone":"+1 450 472 8998",
    "sg:postcode":"J0N 1P0",
    "sg:province":"QC",
    "wof:name":"Restaurant Bj Pizza",
    "wof:placetype":"venue"
},
  "geometry": {"coordinates":[-73.99458300000001,45.501686],"type":"Point"}
}