{
  "type": "Feature",
  "properties": {
    "addr:full":"Concord ON L4K 3X1",
    "addr:postcode":"l4k 3x1",
    "iso:country":"CA",
    "sg:city":"Concord",
    "sg:classifiers":[
        {
            "category":"Manufacturing",
            "subcategory":"Tools & Machinery",
            "type":"Manufacturing & Wholesale Goods"
        }
    ],
    "sg:phone":"+1 905 660 1069",
    "sg:postcode":"L4K 3X1",
    "sg:province":"ON",
    "sg:tags":[
        "machine",
        "shop"
    ],
    "wof:name":"Alpen Machine & Tool Ltd",
    "wof:placetype":"venue"
},
  "geometry": {"coordinates":[-79.53010559080001,43.7987709045],"type":"Point"}
}