{
  "type": "Feature",
  "properties": {
    "addr:full":"3361 Calgary Trail NW Edmonton AB T6J 6V1",
    "addr:housenumber":"3361",
    "addr:postcode":"t6j 6v1",
    "addr:street":"Calgary Trail Nw",
    "iso:country":"CA",
    "sg:address":"3361 Calgary Trail NW",
    "sg:city":"Edmonton",
    "sg:classifiers":[
        {
            "category":"Restaurant",
            "type":"Food & Drink"
        }
    ],
    "sg:phone":"+1 780 439 9142",
    "sg:postcode":"T6J 6V1",
    "sg:province":"AB",
    "sg:tags":[
        "shop",
        "tea",
        "coffee"
    ],
    "wof:name":"Second Cup",
    "wof:placetype":"venue"
},
  "geometry": {"coordinates":[-113.495437622,53.4669532776],"type":"Point"}
}