{
  "type": "Feature",
  "properties": {
    "addr:full":"2541 Boul Du Carmel Trois-Rivieres QC G8Z 3S3",
    "addr:housenumber":"2541",
    "addr:postcode":"g8z 3s3",
    "addr:street":"Boul Du Carmel Trois-Rivieres",
    "iso:country":"CA",
    "sg:address":"2541 Boul Du Carmel",
    "sg:city":"Trois-Rivieres",
    "sg:classifiers":[
        {
            "category":"Health Services",
            "subcategory":"Nursing And Care Facility",
            "type":"Services"
        }
    ],
    "sg:phone":"+1 819 379 6781",
    "sg:postcode":"G8Z 3S3",
    "sg:province":"QC",
    "sg:tags":[
        "home",
        "retirement",
        "community"
    ],
    "wof:name":"Residence Poirier",
    "wof:placetype":"venue"
},
  "geometry": {"coordinates":[-72.562271,46.360142],"type":"Point"}
}