{
  "type": "Feature",
  "properties": {
    "addr:full":"870 Rue Victorin Saint-Charles-DE-Drummond QC J2C 6G1",
    "addr:housenumber":"870",
    "addr:postcode":"j2c 6g1",
    "addr:street":"Rue Victorin",
    "iso:country":"CA",
    "sg:address":"870 Rue Victorin",
    "sg:city":"Saint-Charles-DE-Drummond",
    "sg:classifiers":[
        {
            "category":"Building & Trades",
            "subcategory":"Construction",
            "type":"Services"
        }
    ],
    "sg:phone":"+1 819 474 1825",
    "sg:postcode":"J2C 6G1",
    "sg:province":"QC",
    "sg:tags":[
        "contractor"
    ],
    "wof:name":"Construction M Gauthier",
    "wof:placetype":"venue"
},
  "geometry": {"coordinates":[-72.4748306274,45.9019355774],"type":"Point"}
}