{
  "type": "Feature",
  "properties": {
    "addr:full":"Surrey BC V3R 8X8",
    "addr:postcode":"v3r 8x8",
    "iso:country":"CA",
    "sg:city":"Surrey",
    "sg:classifiers":[
        {
            "category":"Food & Beverages",
            "subcategory":"Groceries & Convenience Stores",
            "type":"Retail Goods"
        }
    ],
    "sg:phone":"+1 604 588 2663",
    "sg:postcode":"V3R 8X8",
    "sg:province":"BC",
    "sg:tags":[
        "grocer"
    ],
    "wof:name":"Mac's Convenience Stores Ltd",
    "wof:placetype":"venue"
},
  "geometry": {"coordinates":[-122.80072784399999,49.1847991943],"type":"Point"}
}