{
  "type": "Feature",
  "properties": {
    "addr:full":"3013 Ch DE Chambly Longueuil QC J4L 1N3",
    "addr:postcode":"3013;j4l 1n3",
    "addr:street":"Ch De Chambly",
    "iso:country":"CA",
    "sg:address":"3013 Ch DE Chambly",
    "sg:city":"Longueuil",
    "sg:classifiers":[
        {
            "category":"Professional",
            "subcategory":"Accounting & Tax Preparation",
            "type":"Services"
        }
    ],
    "sg:phone":"+1 450 646 6098",
    "sg:postcode":"J4L 1N3",
    "sg:province":"QC",
    "sg:tags":[
        "bookkeeping",
        "return",
        "system",
        "filing"
    ],
    "wof:name":"Services DE Secretariat",
    "wof:placetype":"venue"
},
  "geometry": {"coordinates":[-73.4565124512,45.5190963745],"type":"Point"}
}