{
  "type": "Feature",
  "properties": {
    "addr:full":"3395 Bathurst St North York ON M6A 2B8",
    "addr:housenumber":"3395",
    "addr:postcode":"m6a 2b8",
    "addr:street":"Bathurst St",
    "iso:country":"CA",
    "sg:address":"3395 Bathurst St",
    "sg:city":"North York",
    "sg:classifiers":[
        {
            "category":"Wholesale",
            "subcategory":"Electrical",
            "type":"Manufacturing & Wholesale Goods"
        }
    ],
    "sg:phone":"+1 416 789 2931",
    "sg:postcode":"M6A 2B8",
    "sg:province":"ON",
    "sg:tags":[
        "alarm",
        "burglar",
        "system"
    ],
    "wof:name":"Securely Yours",
    "wof:placetype":"venue"
},
  "geometry": {"coordinates":[-79.431183,43.726437],"type":"Point"}
}