{
  "type": "Feature",
  "properties": {
    "addr:full":"351 Rue Roy E Montreal QC H2W 1N1",
    "addr:housenumber":"351",
    "addr:postcode":"h2w 1n1",
    "addr:street":"Rue Roy E",
    "iso:country":"CA",
    "sg:address":"351 Rue Roy E",
    "sg:city":"Montreal",
    "sg:classifiers":[
        {
            "category":"Bars & Pubs",
            "type":"Food & Drink"
        }
    ],
    "sg:phone":"+1 514 849 6467",
    "sg:postcode":"H2W 1N1",
    "sg:province":"QC",
    "wof:name":"Roy Bar",
    "wof:placetype":"venue"
},
  "geometry": {"coordinates":[-73.57312,45.518814],"type":"Point"}
}