{
  "type": "Feature",
  "properties": {
    "addr:full":"Roumieu Rd Burns Lake BC V0J 1E0",
    "addr:postcode":"v0j 1e0",
    "addr:street":"Roumieu Rd",
    "iso:country":"CA",
    "sg:address":"Roumieu Rd",
    "sg:city":"Burns Lake",
    "sg:classifiers":[
        {
            "category":"Freight",
            "type":"Transportation"
        }
    ],
    "sg:phone":"+1 250 692 4280",
    "sg:postcode":"V0J 1E0",
    "sg:province":"BC",
    "sg:tags":[
        "trucking"
    ],
    "wof:name":"Jubinville Enterprises Ltd",
    "wof:placetype":"venue"
},
  "geometry": {"coordinates":[-125.73472595200001,54.2228317261],"type":"Point"}
}