{
  "type": "Feature",
  "properties": {
    "addr:full":"2998 Bradbury Dr Prince Albert SK S6V 7W2",
    "addr:housenumber":"2998",
    "addr:postcode":"s6v 7w2",
    "addr:street":"Bradbury Dr",
    "iso:country":"CA",
    "sg:address":"2998 Bradbury Dr",
    "sg:city":"Prince Albert",
    "sg:classifiers":[
        {
            "category":"Building & Trades",
            "subcategory":"Construction",
            "type":"Services"
        }
    ],
    "sg:phone":"+1 306 763 2805",
    "sg:postcode":"S6V 7W2",
    "sg:province":"SK",
    "sg:tags":[
        "concrete",
        "masonry",
        "contractor"
    ],
    "wof:name":"Naicker's Masonry Concrete",
    "wof:placetype":"venue"
},
  "geometry": {"coordinates":[-105.70193500000001,53.185394],"type":"Point"}
}