{
  "type": "Feature",
  "properties": {
    "iso:country":"CA",
    "sg:address":"1483 Rte 209",
    "sg:city":"Franklin",
    "sg:classifiers":[
        {
            "category":"Retail",
            "subcategory":"Funeral Services",
            "type":"Services"
        }
    ],
    "sg:phone":"+1 450 827 2335",
    "sg:postcode":"J0S 1E0",
    "sg:province":"QC",
    "sg:tags":[
        "director"
    ],
    "wof:name":"J M Sharpe Salon Funeraire",
    "wof:placetype":"venue"
},
  "geometry": {"coordinates":[-73.924621582,45.0284690857],"type":"Point"}
}