{
  "type": "Feature",
  "properties": {
    "iso:country":"CA",
    "sg:address":"103 Milvan Dr",
    "sg:city":"North York",
    "sg:phone":"+1 416 749 6555",
    "sg:postcode":"M9L 1Z7",
    "sg:province":"ON",
    "sg:tags":[
        "oil"
    ],
    "wof:name":"Sayco Distributors Ltd",
    "wof:placetype":"venue"
},
  "geometry": {"coordinates":[-79.5591506958,43.7559623718],"type":"Point"}
}