{
  "type": "Feature",
  "properties": {
    "addr:full":"84 Isabella St Pembroke ON K8A 5S5",
    "addr:housenumber":"84",
    "addr:postcode":"k8a 5s5",
    "addr:street":"Isabella St",
    "iso:country":"CA",
    "sg:address":"84 Isabella St",
    "sg:city":"Pembroke",
    "sg:classifiers":[
        {
            "category":"Insurance",
            "subcategory":"Insurance Agent",
            "type":"Services"
        }
    ],
    "sg:phone":"+1 613 735 0018",
    "sg:postcode":"K8A 5S5",
    "sg:province":"ON",
    "wof:name":"Sun Life Financial",
    "wof:placetype":"venue"
},
  "geometry": {"coordinates":[-77.113602,45.824074],"type":"Point"}
}