{
  "type": "Feature",
  "properties": {
    "addr:full":"44 Grand River St N Paris ON N3L 2M2",
    "addr:housenumber":"44",
    "addr:postcode":"n3l 2m2",
    "addr:street":"Grand;St N",
    "iso:country":"CA",
    "sg:address":"44 Grand River St N",
    "sg:city":"Paris",
    "sg:classifiers":[
        {
            "category":"Restaurant",
            "type":"Food & Drink"
        }
    ],
    "sg:phone":"+1 519 442 6110",
    "sg:postcode":"N3L 2M2",
    "sg:province":"ON",
    "wof:name":"Cafe Europa",
    "wof:placetype":"venue"
},
  "geometry": {"coordinates":[-80.384148,43.193237],"type":"Point"}
}