{
  "type": "Feature",
  "properties": {
    "iso:country":"CA",
    "sg:address":"691 Lilac St",
    "sg:city":"Sudbury",
    "sg:classifiers":[
        {
            "category":"Education",
            "subcategory":"School",
            "type":"Public Place"
        }
    ],
    "sg:phone":"+1 705 674 0701",
    "sg:postcode":"P3E 4E2",
    "sg:province":"ON",
    "wof:name":"St Francis School",
    "wof:placetype":"venue"
},
  "geometry": {"coordinates":[-81.012634,46.47768],"type":"Point"}
}