{
  "type": "Feature",
  "properties": {
    "addr:full":"760 393 Rte Palmarolle QC J0Z 3C0",
    "addr:housenumber":"760 393",
    "addr:postcode":"j0z 3c0",
    "addr:street":"Rte Palmarolle",
    "iso:country":"CA",
    "sg:address":"760 393 Rte",
    "sg:city":"Palmarolle",
    "sg:classifiers":[
        {
            "category":"Building & Trades",
            "subcategory":"Landscaping Services",
            "type":"Services"
        }
    ],
    "sg:phone":"+1 819 787 2944",
    "sg:postcode":"J0Z 3C0",
    "sg:province":"QC",
    "sg:tags":[
        "landscape",
        "contractor"
    ],
    "wof:name":"Amenagement Paysager E Mercier",
    "wof:placetype":"venue"
},
  "geometry": {"coordinates":[-79.200478,48.664425],"type":"Point"}
}