{
  "type": "Feature",
  "properties": {
    "addr:full":"Barrie ON L4M 3C5",
    "addr:postcode":"l4m 3c5",
    "iso:country":"CA",
    "sg:city":"Barrie",
    "sg:classifiers":[
        {
            "category":"Shopping",
            "subcategory":"Clothing, Apparel, & Fashions",
            "type":"Retail Goods"
        }
    ],
    "sg:phone":"+1 705 734 9884",
    "sg:postcode":"L4M 3C5",
    "sg:province":"ON",
    "sg:tags":[
        "furnishing"
    ],
    "wof:name":"Moore's Clothing For Men",
    "wof:placetype":"venue"
},
  "geometry": {"coordinates":[-79.7065200806,44.4084625244],"type":"Point"}
}