{
  "type": "Feature",
  "properties": {
    "addr:full":"925 Rte Marie-Victorin Sorel-Tracy QC J3R 1L2",
    "addr:housenumber":"925",
    "addr:postcode":"j3r 1l2",
    "addr:street":"Rte Marie-Victorin",
    "iso:country":"CA",
    "sg:address":"925 Rte Marie-Victorin",
    "sg:city":"Sorel-Tracy",
    "sg:classifiers":[
        {
            "category":"Restaurant",
            "type":"Food & Drink"
        }
    ],
    "sg:phone":"+1 450 743 5557",
    "sg:postcode":"J3R 1L2",
    "sg:province":"QC",
    "wof:name":"Restaurant LA Petite Chaumiere",
    "wof:placetype":"venue"
},
  "geometry": {"coordinates":[-73.127663,46.040081],"type":"Point"}
}