{
  "type": "Feature",
  "properties": {
    "addr:full":"90 Princess Cres Sault Ste Marie ON P6B 3P5",
    "addr:housenumber":"90",
    "addr:postcode":"p6b 3p5",
    "addr:street":"Princess Cres",
    "iso:country":"CA",
    "sg:address":"90 Princess Cres",
    "sg:city":"Sault Ste Marie",
    "sg:classifiers":[
        {
            "category":"Building & Trades",
            "subcategory":"Construction",
            "type":"Services"
        }
    ],
    "sg:phone":"+1 705 949 0475",
    "sg:postcode":"P6B 3P5",
    "sg:province":"ON",
    "sg:tags":[
        "painter"
    ],
    "wof:name":"Alfie's Painting & Decor Ltd",
    "wof:placetype":"venue"
},
  "geometry": {"coordinates":[-84.306015,46.524773],"type":"Point"}
}