{
  "type": "Feature",
  "properties": {
    "addr:full":"3857 Lake Shore Blvd W Etobicoke ON M8W 1R4",
    "addr:housenumber":"3857",
    "addr:postcode":"m8w 1r4",
    "addr:street":"Lake Shore Blvd W",
    "iso:country":"CA",
    "sg:address":"3857 Lake Shore Blvd W",
    "sg:city":"Etobicoke",
    "sg:classifiers":[
        {
            "category":"Food & Beverages",
            "subcategory":"Bakery",
            "type":"Retail Goods"
        }
    ],
    "sg:phone":"+1 416 251 1339",
    "sg:postcode":"M8W 1R4",
    "sg:province":"ON",
    "sg:tags":[
        "doughnut"
    ],
    "wof:name":"Coffee Time Donuts",
    "wof:placetype":"venue"
},
  "geometry": {"coordinates":[-79.545036,43.590256],"type":"Point"}
}