{
  "type": "Feature",
  "properties": {
    "addr:full":"4381 Rue Saint-Denis Montreal QC H2J 2L2",
    "addr:housenumber":"4381",
    "addr:postcode":"h2j 2l2",
    "addr:street":"Rue Saint-Denis",
    "iso:country":"CA",
    "sg:address":"4381 Rue Saint-Denis",
    "sg:city":"Montreal",
    "sg:classifiers":[
        {
            "category":"Shopping",
            "subcategory":"Clothing, Apparel, & Fashions",
            "type":"Retail Goods"
        }
    ],
    "sg:phone":"+1 514 845 5674",
    "sg:postcode":"H2J 2L2",
    "sg:province":"QC",
    "sg:tags":[
        "designer"
    ],
    "wof:name":"Elles-Toiles",
    "wof:placetype":"venue"
},
  "geometry": {"coordinates":[-73.5810699463,45.5233039856],"type":"Point"}
}