{
  "type": "Feature",
  "properties": {
    "addr:full":"St Catharines ON L2M 6S9",
    "addr:postcode":"l2m 6s9",
    "iso:country":"CA",
    "sg:city":"St Catharines",
    "sg:classifiers":[
        {
            "category":"Wholesale",
            "subcategory":"Metals & Minerals",
            "type":"Manufacturing & Wholesale Goods"
        }
    ],
    "sg:phone":"+1 905 687 8808",
    "sg:postcode":"L2M 6S9",
    "sg:province":"ON",
    "sg:tags":[
        "steel",
        "warehouse"
    ],
    "wof:name":"Metal Supermarkets",
    "wof:placetype":"venue"
},
  "geometry": {"coordinates":[-79.1998138428,43.1726531982],"type":"Point"}
}