{
  "type": "Feature",
  "properties": {
    "addr:full":"25 Kensington Rd Brampton ON L6T 3W8",
    "addr:housenumber":"25",
    "addr:postcode":"l6t 3w8",
    "addr:street":"Kensington Rd",
    "iso:country":"CA",
    "sg:address":"25 Kensington Rd",
    "sg:city":"Brampton",
    "sg:classifiers":[
        {
            "category":"Taxi",
            "type":"Transportation"
        }
    ],
    "sg:phone":"+1 905 458 5858",
    "sg:postcode":"L6T 3W8",
    "sg:province":"ON",
    "sg:tags":[
        "taxicab",
        "airport"
    ],
    "wof:name":"Atlas Taxi Svc Ltd",
    "wof:placetype":"venue"
},
  "geometry": {"coordinates":[-79.717956543,43.7216644287],"type":"Point"}
}