{
  "type": "Feature",
  "properties": {
    "addr:full":"72 Place Bourget N Joliette QC J6E 5E4",
    "addr:housenumber":"72",
    "addr:postcode":"j6e 5e4",
    "addr:street":"Place Bourget N",
    "iso:country":"CA",
    "sg:address":"72 Place Bourget N",
    "sg:city":"Joliette",
    "sg:classifiers":[
        {
            "category":"Health Services",
            "subcategory":"Doctor",
            "type":"Services"
        }
    ],
    "sg:phone":"+1 450 759 1212",
    "sg:postcode":"J6E 5E4",
    "sg:province":"QC",
    "sg:tags":[
        "dentist"
    ],
    "wof:name":"Dion, Jean-Pierre DDS",
    "wof:placetype":"venue"
},
  "geometry": {"coordinates":[-73.4408493042,46.0253639221],"type":"Point"}
}