{
  "type": "Feature",
  "properties": {
    "addr:full":"477 Rue Saint-Francois-Xavier Montreal QC H2Y 2T2",
    "addr:housenumber":"477",
    "addr:postcode":"h2y 2t2",
    "addr:street":"Rue Saint-Francois-Xavier",
    "iso:country":"CA",
    "sg:address":"477 Rue Saint-Francois-Xavier",
    "sg:city":"Montreal",
    "sg:classifiers":[
        {
            "category":"Real Estate",
            "subcategory":"Real Estate Agent",
            "type":"Services"
        }
    ],
    "sg:phone":"+1 514 844 4318",
    "sg:postcode":"H2Y 2T2",
    "sg:province":"QC",
    "sg:tags":[
        "management"
    ],
    "wof:name":"Gestion D'Immeubles Bazinet",
    "wof:placetype":"venue"
},
  "geometry": {"coordinates":[-73.5568161011,45.5037460327],"type":"Point"}
}