{
  "type": "Feature",
  "properties": {
    "addr:full":"191 Rue Leveillee Saint-Francois-Du-Lac QC J0G 1M0",
    "addr:housenumber":"191",
    "addr:postcode":"j0g 1m0",
    "addr:street":"Rue Leveillee Saint-Francois-Du-Lac",
    "iso:country":"CA",
    "sg:address":"191 Rue Leveillee",
    "sg:city":"Saint-Francois-Du-Lac",
    "sg:classifiers":[
        {
            "category":"Banks & Credit Unions",
            "subcategory":"Bank",
            "type":"Services"
        }
    ],
    "sg:phone":"+1 450 568 3108",
    "sg:postcode":"J0G 1M0",
    "sg:province":"QC",
    "wof:name":"Caisse Populaire St-Francois",
    "wof:placetype":"venue"
},
  "geometry": {"coordinates":[-72.828484,46.067211],"type":"Point"}
}