{
  "type": "Feature",
  "properties": {
    "addr:full":"2133 Royal Windsor Dr # 4 Mississauga ON L5J 1K5",
    "addr:housenumber":"2133",
    "addr:postcode":"l5j 1k5",
    "addr:street":"Royal Windsor Dr # 4",
    "iso:country":"CA",
    "sg:address":"2133 Royal Windsor Dr # 4",
    "sg:city":"Mississauga",
    "sg:classifiers":[
        {
            "category":"Professional",
            "type":"Services"
        }
    ],
    "sg:phone":"+1 905 403 4769",
    "sg:postcode":"L5J 1K5",
    "sg:province":"ON",
    "sg:tags":[
        "equipment",
        "hydroponics",
        "supply"
    ],
    "wof:name":"Second Nature Hydroponics",
    "wof:placetype":"venue"
},
  "geometry": {"coordinates":[-79.633026,43.508343],"type":"Point"}
}