{
  "type": "Feature",
  "properties": {
    "addr:full":"79 Ridout St S London ON N6C 3X2",
    "addr:housenumber":"79",
    "addr:postcode":"n6c 3x2",
    "addr:street":"Ridout St S",
    "iso:country":"CA",
    "sg:address":"79 Ridout St S",
    "sg:city":"London",
    "sg:classifiers":[
        {
            "category":"Shopping",
            "subcategory":"Computers & Home Electronics",
            "type":"Retail Goods"
        }
    ],
    "sg:phone":"+1 519 439 6947",
    "sg:postcode":"N6C 3X2",
    "sg:province":"ON",
    "sg:tags":[
        "software"
    ],
    "wof:name":"Alliance Healthcare Group Inc",
    "wof:placetype":"venue"
},
  "geometry": {"coordinates":[-81.249413,42.973194],"type":"Point"}
}