{
  "type": "Feature",
  "properties": {
    "iso:country":"CA",
    "sg:city":"Calgary",
    "sg:classifiers":[
        {
            "category":"Shopping",
            "subcategory":"Computers & Home Electronics",
            "type":"Retail Goods"
        }
    ],
    "sg:phone":"+1 403 538 3270",
    "sg:postcode":"T2E 6Z3",
    "sg:province":"AB",
    "sg:tags":[
        "equipment",
        "dealer"
    ],
    "wof:name":"Techtronics Computer",
    "wof:placetype":"venue"
},
  "geometry": {"coordinates":[-114.006797791,51.081287384],"type":"Point"}
}