{
  "type": "Feature",
  "properties": {
    "addr:full":"Wahnapitae ON P0M 3C0",
    "addr:postcode":"p0m 3c0",
    "iso:country":"CA",
    "sg:city":"Wahnapitae",
    "sg:classifiers":[
        {
            "category":"Recreation",
            "type":"Entertainment"
        }
    ],
    "sg:phone":"+1 705 694 4635",
    "sg:postcode":"P0M 3C0",
    "sg:province":"ON",
    "sg:tags":[
        "government",
        "hall",
        "auditorium"
    ],
    "wof:name":"Wahnapitae Centre Comm",
    "wof:placetype":"venue"
},
  "geometry": {"coordinates":[-80.7842636108,46.4873123169],"type":"Point"}
}