{
  "type": "Feature",
  "properties": {
    "addr:full":"545 Kipawa Rd Temiscaming QC J0Z 3R0",
    "addr:housenumber":"545",
    "addr:postcode":"j0z 3r0",
    "addr:street":"Kipawa Rd",
    "iso:country":"CA",
    "sg:address":"545 Kipawa Rd",
    "sg:city":"Temiscaming",
    "sg:classifiers":[
        {
            "category":"Home & Garden",
            "subcategory":"Furniture",
            "type":"Retail Goods"
        }
    ],
    "sg:phone":"+1 819 627 9700",
    "sg:postcode":"J0Z 3R0",
    "sg:province":"QC",
    "wof:name":"Meubles St Martin Ltee",
    "wof:placetype":"venue"
},
  "geometry": {"coordinates":[-79.0942230225,46.7230300903],"type":"Point"}
}