{
  "type": "Feature",
  "properties": {
    "addr:full":"1056 Ch DE LA Station LA Conception QC J0T 1M0",
    "addr:housenumber":"1056",
    "addr:postcode":"j0t 1m0",
    "addr:street":"Ch De La Station",
    "iso:country":"CA",
    "sg:address":"1056 Ch DE LA Station",
    "sg:city":"LA Conception",
    "sg:classifiers":[
        {
            "category":"Retail",
            "subcategory":"Animal Services",
            "type":"Services"
        }
    ],
    "sg:phone":"+1 819 686 3323",
    "sg:postcode":"J0T 1M0",
    "sg:province":"QC",
    "sg:tags":[
        "breeder",
        "horse"
    ],
    "wof:name":"Waldeck U Lesa Horse Farm",
    "wof:placetype":"venue"
},
  "geometry": {"coordinates":[-74.6833572388,46.2059707642],"type":"Point"}
}