{
  "type": "Feature",
  "properties": {
    "addr:full":"4464 Highway 2 Wellington NS B2T 1A2",
    "addr:housenumber":"4464",
    "addr:postcode":"b2t 1a2",
    "addr:street":"Highway 2",
    "iso:country":"CA",
    "sg:address":"4464 Highway 2",
    "sg:city":"Wellington",
    "sg:classifiers":[
        {
            "category":"Building & Trades",
            "subcategory":"Construction",
            "type":"Services"
        }
    ],
    "sg:phone":"+1 902 861 1510",
    "sg:postcode":"B2T 1A2",
    "sg:province":"NS",
    "sg:tags":[
        "roofing",
        "contractor"
    ],
    "wof:name":"William Sarty Siding CO Ltd",
    "wof:placetype":"venue"
},
  "geometry": {"coordinates":[-63.6181411743,44.8595733643],"type":"Point"}
}