{
  "type": "Feature",
  "properties": {
    "iso:country":"CA",
    "sg:address":"92 Ochterloney St",
    "sg:city":"Dartmouth",
    "sg:classifiers":[
        {
            "category":"Professional",
            "subcategory":"Lawyer & Legal Services",
            "type":"Services"
        }
    ],
    "sg:phone":"+1 902 465 6669",
    "sg:postcode":"B2Y 1C5",
    "sg:province":"NS",
    "sg:tags":[
        "attorney"
    ],
    "wof:name":"Foote, Helen L",
    "wof:placetype":"venue"
},
  "geometry": {"coordinates":[-63.5666809082,44.6679039001],"type":"Point"}
}