{
  "type": "Feature",
  "properties": {
    "addr:full":"Dartmouth NS B2W 2E8",
    "addr:postcode":"b2w 2e8",
    "iso:country":"CA",
    "sg:city":"Dartmouth",
    "sg:classifiers":[
        {
            "category":"Education",
            "subcategory":"Dance Studio",
            "type":"Public Place"
        }
    ],
    "sg:phone":"+1 902 462 0007",
    "sg:postcode":"B2W 2E8",
    "sg:province":"NS",
    "sg:tags":[
        "instruction",
        "dancing"
    ],
    "wof:name":"Belly Dance Basics & Beyond",
    "wof:placetype":"venue"
},
  "geometry": {"coordinates":[-63.515606,44.67627],"type":"Point"}
}