{
  "type": "Feature",
  "properties": {
    "addr:full":"471 Main St W Grimsby ON L3M 1T4",
    "addr:housenumber":"471",
    "addr:postcode":"l3m 1t4",
    "addr:street":"Main St W",
    "iso:country":"CA",
    "sg:address":"471 Main St W",
    "sg:city":"Grimsby",
    "sg:classifiers":[
        {
            "category":"Home & Garden",
            "subcategory":"Garden Supply",
            "type":"Retail Goods"
        }
    ],
    "sg:phone":"+1 905 945 6336",
    "sg:postcode":"L3M 1T4",
    "sg:province":"ON",
    "sg:tags":[
        "center"
    ],
    "wof:name":"Trillium Hill Greenhouses",
    "wof:placetype":"venue"
},
  "geometry": {"coordinates":[-79.611351,43.20166],"type":"Point"}
}