{
  "type": "Feature",
  "properties": {
    "addr:full":"1405 125 Rte Sainte-Julienne QC J0K 2T0",
    "addr:housenumber":"1405",
    "addr:postcode":"j0k 2t0",
    "addr:street":"125 Rte",
    "iso:country":"CA",
    "sg:address":"1405 125 Rte",
    "sg:city":"Sainte-Julienne",
    "sg:classifiers":[
        {
            "category":"Home & Garden",
            "subcategory":"Hardware",
            "type":"Retail Goods"
        }
    ],
    "sg:phone":"+1 450 831 2721",
    "sg:postcode":"J0K 2T0",
    "sg:province":"QC",
    "sg:tags":[
        "building",
        "material"
    ],
    "wof:name":"Materiaux DE Construction",
    "wof:placetype":"venue"
},
  "geometry": {"coordinates":[-73.7074050903,45.9624252319],"type":"Point"}
}