{
  "type": "Feature",
  "properties": {
    "addr:full":"19791 96 Ave Langley BC V1M 3C9",
    "addr:housenumber":"19791",
    "addr:postcode":"v1m 3c9",
    "addr:street":"96 Ave",
    "iso:country":"CA",
    "sg:address":"19791 96 Ave",
    "sg:city":"Langley",
    "sg:classifiers":[
        {
            "category":"Retail",
            "subcategory":"Veterinary Services",
            "type":"Services"
        }
    ],
    "sg:phone":"+1 604 888 2323",
    "sg:postcode":"V1M 3C9",
    "sg:province":"BC",
    "sg:tags":[
        "veterinarian"
    ],
    "wof:name":"Dobson, Marian DVM",
    "wof:placetype":"venue"
},
  "geometry": {"coordinates":[-122.673546,49.177197],"type":"Point"}
}