{
  "type": "Feature",
  "properties": {
    "addr:full":"1861 Ambassador Dr Windsor ON N9C 4B5",
    "addr:housenumber":"1861",
    "addr:postcode":"n9c 4b5",
    "addr:street":"Ambassador Dr",
    "iso:country":"CA",
    "sg:address":"1861 Ambassador Dr",
    "sg:city":"Windsor",
    "sg:classifiers":[
        {
            "category":"Retail",
            "subcategory":"Auto Repair",
            "type":"Services"
        }
    ],
    "sg:phone":"+1 519 250 5475",
    "sg:postcode":"N9C 4B5",
    "sg:province":"ON",
    "sg:tags":[
        "wrecker"
    ],
    "wof:name":"Lil Joe's Towing",
    "wof:placetype":"venue"
},
  "geometry": {"coordinates":[-83.05682400000001,42.281075],"type":"Point"}
}