{
  "type": "Feature",
  "properties": {
    "iso:country":"CA",
    "sg:address":"783 Rue Notre-Dame",
    "sg:city":"Repentigny",
    "sg:classifiers":[
        {
            "category":"Shopping",
            "subcategory":"Pharmacy",
            "type":"Retail Goods"
        }
    ],
    "sg:phone":"+1 450 582 1773",
    "sg:postcode":"J5Y 1B4",
    "sg:province":"QC",
    "wof:name":"Pharmacie Nancy Morissette",
    "wof:placetype":"venue"
},
  "geometry": {"coordinates":[-73.424797,45.760662],"type":"Point"}
}