{
  "type": "Feature",
  "properties": {
    "addr:full":"Nepean ON K2E 7X7",
    "addr:postcode":"k2e 7x7",
    "iso:country":"CA",
    "sg:city":"Nepean",
    "sg:classifiers":[
        {
            "category":"Building & Trades",
            "subcategory":"Construction",
            "type":"Services"
        }
    ],
    "sg:phone":"+1 613 727 6919",
    "sg:postcode":"K2E 7X7",
    "sg:province":"ON",
    "sg:tags":[
        "dry wall",
        "contractor"
    ],
    "wof:name":"Marcantonio Constructors Inc",
    "wof:placetype":"venue"
},
  "geometry": {"coordinates":[-75.710251,45.328941],"type":"Point"}
}