{
  "type": "Feature",
  "properties": {
    "addr:full":"London ON N5V 2E5",
    "addr:postcode":"n5v 2e5",
    "iso:country":"CA",
    "sg:city":"London",
    "sg:classifiers":[
        {
            "category":"Shopping",
            "subcategory":"Discount & Variety Stores",
            "type":"Retail Goods"
        }
    ],
    "sg:phone":"+1 519 452 0200",
    "sg:postcode":"N5V 2E5",
    "sg:province":"ON",
    "wof:name":"Peter's Mini Mart",
    "wof:placetype":"venue"
},
  "geometry": {"coordinates":[-81.2057266235,43.0228652954],"type":"Point"}
}