{
  "type": "Feature",
  "properties": {
    "addr:full":"Maple Ridge BC V2X 3H7",
    "addr:postcode":"v2x 3h7",
    "iso:country":"CA",
    "sg:city":"Maple Ridge",
    "sg:classifiers":[
        {
            "category":"Shopping",
            "subcategory":"Pharmacy",
            "type":"Retail Goods"
        }
    ],
    "sg:phone":"+1 604 467 9100",
    "sg:postcode":"V2X 3H7",
    "sg:province":"BC",
    "wof:name":"Haney Pharmacy",
    "wof:placetype":"venue"
},
  "geometry": {"coordinates":[-122.6073,49.220692],"type":"Point"}
}