{
  "type": "Feature",
  "properties": {
    "addr:full":"986 Tecumseh Rd W Windsor ON N8X 2A8",
    "addr:housenumber":"986",
    "addr:postcode":"n8x 2a8",
    "addr:street":"Tecumseh Rd W",
    "iso:country":"CA",
    "sg:address":"986 Tecumseh Rd W",
    "sg:city":"Windsor",
    "sg:classifiers":[
        {
            "category":"Shopping",
            "type":"Retail Goods"
        }
    ],
    "sg:phone":"+1 519 977 1938",
    "sg:postcode":"N8X 2A8",
    "sg:province":"ON",
    "sg:tags":[
        "chemical"
    ],
    "wof:name":"Canada Colors & Chemicals Ltd",
    "wof:placetype":"venue"
},
  "geometry": {"coordinates":[-83.038872,42.297699],"type":"Point"}
}