{
  "type": "Feature",
  "properties": {
    "addr:full":"139 Prescott St Kemptville ON K0G 1J0",
    "addr:housenumber":"139",
    "addr:postcode":"k0g 1j0",
    "addr:street":"Prescott St",
    "iso:country":"CA",
    "sg:address":"139 Prescott St",
    "sg:city":"Kemptville",
    "sg:classifiers":[
        {
            "category":"Banks & Credit Unions",
            "subcategory":"Bank",
            "type":"Services"
        }
    ],
    "sg:phone":"+1 613 258 5961",
    "sg:postcode":"K0G 1J0",
    "sg:province":"ON",
    "wof:name":"Scotiabank",
    "wof:placetype":"venue"
},
  "geometry": {"coordinates":[-75.64502716059999,45.0157699585],"type":"Point"}
}