{
  "type": "Feature",
  "properties": {
    "addr:full":"Chilliwack BC V2R 1E3",
    "addr:postcode":"v2r 1e3",
    "iso:country":"CA",
    "sg:city":"Chilliwack",
    "sg:classifiers":[
        {
            "category":"Real Estate",
            "subcategory":"Real Estate Agent",
            "type":"Services"
        }
    ],
    "sg:phone":"+1 604 858 7124",
    "sg:postcode":"V2R 1E3",
    "sg:province":"BC",
    "sg:tags":[
        "appraiser"
    ],
    "wof:name":"Fortin Appraisals",
    "wof:placetype":"venue"
},
  "geometry": {"coordinates":[-121.96030399999999,49.130981],"type":"Point"}
}