{
  "type": "Feature",
  "properties": {
    "iso:country":"CA",
    "sg:address":"1005 21st St W",
    "sg:city":"North Vancouver",
    "sg:classifiers":[
        {
            "category":"Autos & Motor Vehicles",
            "subcategory":"Motorcycle Sales",
            "type":"Retail Goods"
        }
    ],
    "sg:phone":"+1 604 988 6852",
    "sg:postcode":"V7P 2C4",
    "sg:province":"BC",
    "sg:tags":[
        "car",
        "golf",
        "cart"
    ],
    "wof:name":"Walker Golf & Ind Cars",
    "wof:placetype":"venue"
},
  "geometry": {"coordinates":[-123.097755,49.328571],"type":"Point"}
}