{
  "type": "Feature",
  "properties": {
    "addr:full":"North York ON M2N 5X2",
    "addr:postcode":"m2n 5x2",
    "iso:country":"CA",
    "sg:city":"North York",
    "sg:classifiers":[
        {
            "category":"Shopping",
            "type":"Retail Goods"
        }
    ],
    "sg:phone":"+1 416 226 9122",
    "sg:postcode":"M2N 5X2",
    "sg:province":"ON",
    "sg:tags":[
        "telephone",
        "cellular"
    ],
    "wof:name":"Bell World",
    "wof:placetype":"venue"
},
  "geometry": {"coordinates":[-79.410843,43.761978],"type":"Point"}
}