{
  "type": "Feature",
  "properties": {
    "addr:full":"10101 2 Ave SW Calgary AB T3B 5T2",
    "addr:housenumber":"10101",
    "addr:postcode":"t3b 5t2",
    "addr:street":"2 Ave Sw",
    "iso:country":"CA",
    "sg:address":"10101 2 Ave SW",
    "sg:city":"Calgary",
    "sg:classifiers":[
        {
            "category":"Education",
            "subcategory":"School",
            "type":"Public Place"
        }
    ],
    "sg:phone":"+1 403 286 5686",
    "sg:postcode":"T3B 5T2",
    "sg:province":"AB",
    "wof:name":"Chinook Winds Adventist Acad",
    "wof:placetype":"venue"
},
  "geometry": {"coordinates":[-114.233238,51.081223],"type":"Point"}
}