{
  "type": "Feature",
  "properties": {
    "addr:full":"7 Rue Notre-Dame Quebec QC G1K 4E9",
    "addr:housenumber":"7",
    "addr:postcode":"g1k 4e9",
    "addr:street":"Rue Notre-Dame",
    "iso:country":"CA",
    "sg:address":"7 Rue Notre-Dame",
    "sg:city":"Quebec",
    "sg:classifiers":[
        {
            "category":"Shopping",
            "subcategory":"Clothing, Apparel, & Fashions",
            "type":"Retail Goods"
        }
    ],
    "sg:phone":"+1 418 692 3030",
    "sg:postcode":"G1K 4E9",
    "sg:province":"QC",
    "sg:tags":[
        "item",
        "boutique"
    ],
    "wof:name":"Boutique Du Lys",
    "wof:placetype":"venue"
},
  "geometry": {"coordinates":[-71.202904,46.812592],"type":"Point"}
}