{
  "type": "Feature",
  "properties": {
    "addr:full":"22301 Fraser Hwy Langley BC V3A 4H5",
    "addr:housenumber":"22301",
    "addr:postcode":"v3a 4h5",
    "addr:street":"Fraser Hwy",
    "iso:country":"CA",
    "sg:address":"22301 Fraser Hwy",
    "sg:city":"Langley",
    "sg:classifiers":[
        {
            "category":"Travel",
            "subcategory":"Campground",
            "type":"Entertainment"
        }
    ],
    "sg:phone":"+1 604 534 5514",
    "sg:postcode":"V3A 4H5",
    "sg:province":"BC",
    "wof:name":"Datwiler's Mobile Home",
    "wof:placetype":"venue"
},
  "geometry": {"coordinates":[-122.60620900000001,49.091194],"type":"Point"}
}