{
  "type": "Feature",
  "properties": {
    "addr:full":"725 College St Toronto ON M6G 1C5",
    "addr:housenumber":"725",
    "addr:postcode":"m6g 1c5",
    "addr:street":"College St",
    "iso:country":"CA",
    "sg:address":"725 College St",
    "sg:city":"Toronto",
    "sg:classifiers":[
        {
            "category":"Cinema",
            "subcategory":"Movie Rental",
            "type":"Entertainment"
        }
    ],
    "sg:phone":"+1 416 535 6078",
    "sg:postcode":"M6G 1C5",
    "sg:province":"ON",
    "sg:tags":[
        "leasing",
        "video",
        "disc",
        "tape"
    ],
    "wof:name":"Rogers Video",
    "wof:placetype":"venue"
},
  "geometry": {"coordinates":[-79.418747,43.655067],"type":"Point"}
}