{
  "type": "Feature",
  "properties": {
    "addr:full":"187 Sutherland Ave Winnipeg MB R2W 3E6",
    "addr:housenumber":"187",
    "addr:postcode":"r2w 3e6",
    "addr:street":"Sutherland Ave",
    "iso:country":"CA",
    "sg:address":"187 Sutherland Ave",
    "sg:city":"Winnipeg",
    "sg:classifiers":[
        {
            "category":"Manufacturing",
            "subcategory":"Tools & Machinery",
            "type":"Manufacturing & Wholesale Goods"
        }
    ],
    "sg:phone":"+1 204 943 9519",
    "sg:postcode":"R2W 3E6",
    "sg:province":"MB",
    "sg:tags":[
        "machine",
        "shop"
    ],
    "wof:name":"Muzeen & Blythe Ltd",
    "wof:placetype":"venue"
},
  "geometry": {"coordinates":[-97.13239299999999,49.906624],"type":"Point"}
}