{
  "type": "Feature",
  "properties": {
    "addr:full":"Victoria BC V8N 6J1",
    "addr:postcode":"v8n 6j1",
    "iso:country":"CA",
    "sg:city":"Victoria",
    "sg:classifiers":[
        {
            "category":"Real Estate",
            "subcategory":"Real Estate Operator",
            "type":"Services"
        }
    ],
    "sg:phone":"+1 250 477 2122",
    "sg:postcode":"V8N 6J1",
    "sg:province":"BC",
    "sg:tags":[
        "mall",
        "shopping",
        "center"
    ],
    "wof:name":"University Heights Shpg Ctr",
    "wof:placetype":"venue"
},
  "geometry": {"coordinates":[-123.333237,48.448151],"type":"Point"}
}