{
  "type": "Feature",
  "properties": {
    "iso:country":"CA",
    "sg:address":"102 Main St",
    "sg:city":"Flin Flon",
    "sg:classifiers":[
        {
            "category":"Retail",
            "subcategory":"Laundry & Dry Cleaning",
            "type":"Services"
        }
    ],
    "sg:phone":"+1 204 687 7289",
    "sg:postcode":"R8A 1K1",
    "sg:province":"MB",
    "sg:tags":[
        "cleaners"
    ],
    "wof:name":"Dry Cleaning Plus",
    "wof:placetype":"venue"
},
  "geometry": {"coordinates":[-101.877159119,54.7671012878],"type":"Point"}
}