{
  "type": "Feature",
  "properties": {
    "addr:full":"Oshawa ON L1G 3V2",
    "addr:postcode":"l1g 3v2",
    "iso:country":"CA",
    "sg:city":"Oshawa",
    "sg:classifiers":[
        {
            "category":"Restaurant",
            "type":"Food & Drink"
        }
    ],
    "sg:phone":"+1 905 432 3147",
    "sg:postcode":"L1G 3V2",
    "sg:province":"ON",
    "wof:name":"Fifth Avenue Fries",
    "wof:placetype":"venue"
},
  "geometry": {"coordinates":[-78.868225,43.935211],"type":"Point"}
}