{
  "type": "Feature",
  "properties": {
    "iso:country":"CA",
    "sg:city":"Coquitlam",
    "sg:classifiers":[
        {
            "category":"Wholesale",
            "subcategory":"Machinery & Supplies",
            "type":"Manufacturing & Wholesale Goods"
        }
    ],
    "sg:phone":"+1 604 464 5579",
    "sg:postcode":"V3K 6H1",
    "sg:province":"BC",
    "sg:tags":[
        "pail"
    ],
    "wof:name":"Icl",
    "wof:placetype":"venue"
},
  "geometry": {"coordinates":[-122.820854,49.231312],"type":"Point"}
}