{
  "type": "Feature",
  "properties": {
    "addr:full":"224 Wallace Ave # 111 Toronto ON M6H 1V7",
    "addr:housenumber":"224",
    "addr:postcode":"m6h 1v7",
    "addr:street":"Wallace Ave # 111",
    "iso:country":"CA",
    "sg:address":"224 Wallace Ave # 111",
    "sg:city":"Toronto",
    "sg:classifiers":[
        {
            "category":"Retail",
            "subcategory":"Repair Shop",
            "type":"Services"
        }
    ],
    "sg:phone":"+1 416 533 1694",
    "sg:postcode":"M6H 1V7",
    "sg:province":"ON",
    "sg:tags":[
        "antique",
        "refinishing"
    ],
    "wof:name":"Maple Leaf Furniture Refinshng",
    "wof:placetype":"venue"
},
  "geometry": {"coordinates":[-79.4459991455,43.6621017456],"type":"Point"}
}