{
  "type": "Feature",
  "properties": {
    "iso:country":"CA",
    "sg:address":"6187 200 St",
    "sg:city":"Langley",
    "sg:classifiers":[
        {
            "category":"Health Services",
            "subcategory":"Doctor",
            "type":"Services"
        }
    ],
    "sg:phone":"+1 604 530 2828",
    "sg:postcode":"V2Y 1A2",
    "sg:province":"BC",
    "sg:tags":[
        "dentist"
    ],
    "wof:name":"Mah, Terry DDS",
    "wof:placetype":"venue"
},
  "geometry": {"coordinates":[-122.66897582999999,49.1149635315],"type":"Point"}
}