{
  "type": "Feature",
  "properties": {
    "addr:full":"Prince George BC V2K 5X5",
    "addr:postcode":"v2k 5x5",
    "iso:country":"CA",
    "sg:city":"Prince George",
    "sg:classifiers":[
        {
            "category":"Retail",
            "subcategory":"Auto Repair",
            "type":"Services"
        }
    ],
    "sg:phone":"+1 250 962 6119",
    "sg:postcode":"V2K 5X5",
    "sg:province":"BC",
    "sg:tags":[
        "repairing",
        "automobile"
    ],
    "wof:name":"North City Automotive",
    "wof:placetype":"venue"
},
  "geometry": {"coordinates":[-122.79978199999999,54.010571],"type":"Point"}
}