{
  "type": "Feature",
  "properties": {
    "iso:country":"CA",
    "sg:address":"16 Brock St W",
    "sg:city":"Tillsonburg",
    "sg:classifiers":[
        {
            "category":"Insurance",
            "subcategory":"Insurance Agent",
            "type":"Services"
        }
    ],
    "sg:phone":"+1 519 842 8465",
    "sg:postcode":"N4G 2A2",
    "sg:province":"ON",
    "wof:name":"O'Grady & Associates",
    "wof:placetype":"venue"
},
  "geometry": {"coordinates":[-80.7279891968,42.8600769043],"type":"Point"}
}