{
  "type": "Feature",
  "properties": {
    "addr:full":"London ON N5Z 3J1",
    "addr:postcode":"n5z 3j1",
    "iso:country":"CA",
    "sg:city":"London",
    "sg:classifiers":[
        {
            "category":"Banks & Credit Unions",
            "subcategory":"Investment Brokerage",
            "type":"Services"
        }
    ],
    "sg:phone":"+1 519 649 2244",
    "sg:postcode":"N5Z 3J1",
    "sg:province":"ON",
    "wof:name":"Edward Jones",
    "wof:placetype":"venue"
},
  "geometry": {"coordinates":[-81.2139511108,42.9596176147],"type":"Point"}
}