{
  "type": "Feature",
  "properties": {
    "addr:full":"2210 Bank St Ottawa ON K1V 1J5",
    "addr:housenumber":"2210",
    "addr:postcode":"k1v 1j5",
    "addr:street":"Bank St",
    "iso:country":"CA",
    "sg:address":"2210 Bank St",
    "sg:city":"Ottawa",
    "sg:classifiers":[
        {
            "category":"Shopping",
            "subcategory":"Books",
            "type":"Retail Goods"
        }
    ],
    "sg:phone":"+1 613 521 9199",
    "sg:postcode":"K1V 1J5",
    "sg:province":"ON",
    "sg:tags":[
        "dealer"
    ],
    "wof:name":"Chapters",
    "wof:placetype":"venue"
},
  "geometry": {"coordinates":[-75.6543502808,45.3574905396],"type":"Point"}
}