{
  "type": "Feature",
  "properties": {
    "addr:full":"Lynden ON L0R 1T0",
    "addr:postcode":"l0r 1t0",
    "iso:country":"CA",
    "sg:city":"Lynden",
    "sg:classifiers":[
        {
            "category":"Retail",
            "subcategory":"Repair Shop",
            "type":"Services"
        }
    ],
    "sg:phone":"+1 519 647 2090",
    "sg:postcode":"L0R 1T0",
    "sg:province":"ON",
    "sg:tags":[
        "ironwork",
        "railing"
    ],
    "wof:name":"Supreme Ornamental Iron Works",
    "wof:placetype":"venue"
},
  "geometry": {"coordinates":[-80.14598846440001,43.2334709167],"type":"Point"}
}