{
  "type": "Feature",
  "properties": {
    "addr:full":"434 East Petpeswick Rd Musquodoboit Harbour NS B0J 2L0",
    "addr:housenumber":"434",
    "addr:postcode":"b0j 2l0",
    "addr:street":"East Petpeswick Rd",
    "iso:country":"CA",
    "sg:address":"434 East Petpeswick Rd",
    "sg:city":"Musquodoboit Harbour",
    "sg:classifiers":[
        {
            "category":"Organizations",
            "subcategory":"Professional Association",
            "type":"Services"
        }
    ],
    "sg:phone":"+1 902 889 2896",
    "sg:postcode":"B0J 2L0",
    "sg:province":"NS",
    "sg:tags":[
        "club"
    ],
    "wof:name":"Petpeswick Yacht Club",
    "wof:placetype":"venue"
},
  "geometry": {"coordinates":[-63.1477241516,44.7835540771],"type":"Point"}
}