{
  "type": "Feature",
  "properties": {
    "addr:full":"Jemseg NB E4C 3K4",
    "addr:postcode":"e4c 3k4",
    "iso:country":"CA",
    "sg:city":"Jemseg",
    "sg:classifiers":[
        {
            "category":"Personal",
            "subcategory":"Beauty Salon",
            "type":"Services"
        }
    ],
    "sg:phone":"+1 506 488 8087",
    "sg:postcode":"E4C 3K4",
    "sg:province":"NB",
    "wof:name":"Susan's Country Hair Care",
    "wof:placetype":"venue"
},
  "geometry": {"coordinates":[-66.108177,45.831924],"type":"Point"}
}