{
  "type": "Feature",
  "properties": {
    "addr:full":"103 Av Du Mont-Royal O Montreal QC H2T 2S9",
    "addr:postcode":"h2t 2s9",
    "addr:street":"103 Av Du Mont-Royal O",
    "iso:country":"CA",
    "sg:address":"103 Av Du Mont-Royal O",
    "sg:city":"Montreal",
    "sg:classifiers":[
        {
            "category":"Food & Beverages",
            "subcategory":"Groceries & Convenience Stores",
            "type":"Retail Goods"
        }
    ],
    "sg:phone":"+1 514 840 8791",
    "sg:postcode":"H2T 2S9",
    "sg:province":"QC",
    "wof:name":"Varietes Plus Du Parc",
    "wof:placetype":"venue"
},
  "geometry": {"coordinates":[-73.585426,45.521229],"type":"Point"}
}