{
  "type": "Feature",
  "properties": {
    "iso:country":"CA",
    "sg:city":"Gloucester",
    "sg:classifiers":[
        {
            "category":"Professional",
            "subcategory":"Business Services",
            "type":"Services"
        }
    ],
    "sg:phone":"+1 613 746 1013",
    "sg:postcode":"K1J 8M8",
    "sg:province":"ON",
    "sg:tags":[
        "drafting"
    ],
    "wof:name":"Brown Custom Design",
    "wof:placetype":"venue"
},
  "geometry": {"coordinates":[-75.59018707280001,45.4492683411],"type":"Point"}
}