{
  "type": "Feature",
  "properties": {
    "addr:full":"PO Box 435 St Marys NL A0B 3B0",
    "addr:housenumber":"po;435",
    "addr:postcode":"a0b 3b0",
    "addr:street":"Box",
    "iso:country":"CA",
    "sg:address":"PO Box 435",
    "sg:city":"St Marys",
    "sg:classifiers":[
        {
            "category":"Organizations",
            "subcategory":"Religious Organization",
            "type":"Services"
        }
    ],
    "sg:phone":"+1 709 525 2310",
    "sg:postcode":"A0B 3B0",
    "sg:province":"NL",
    "sg:tags":[
        "church"
    ],
    "wof:name":"Assumption Parish",
    "wof:placetype":"venue"
},
  "geometry": {"coordinates":[-57.988827,48.957024],"type":"Point"}
}