{
  "type": "Feature",
  "properties": {
    "iso:country":"CA",
    "sg:address":"3770 Montee Saint-Hubert",
    "sg:city":"Saint-Hubert",
    "sg:classifiers":[
        {
            "category":"Personal",
            "type":"Services"
        }
    ],
    "sg:phone":"+1 450 656 1199",
    "sg:postcode":"J3Y 4K1",
    "sg:province":"QC",
    "sg:tags":[
        "electrolysis"
    ],
    "wof:name":"Esthetique & Elctrolyse Karine",
    "wof:placetype":"venue"
},
  "geometry": {"coordinates":[-73.430176,45.492523],"type":"Point"}
}