{
  "type": "Feature",
  "properties": {
    "iso:country":"CA",
    "sg:address":"495 London St",
    "sg:city":"Winnipeg",
    "sg:classifiers":[
        {
            "category":"Personal",
            "subcategory":"Barber",
            "type":"Services"
        }
    ],
    "sg:phone":"+1 204 661 1249",
    "sg:postcode":"R2K 2Z4",
    "sg:province":"MB",
    "wof:name":"Munroe Men's Hairstyling",
    "wof:placetype":"venue"
},
  "geometry": {"coordinates":[-97.081886,49.910858],"type":"Point"}
}