{
  "type": "Feature",
  "properties": {
    "iso:country":"CA",
    "sg:address":"790 Gadwell Crt",
    "sg:city":"Orleans",
    "sg:classifiers":[
        {
            "category":"Building & Trades",
            "subcategory":"Construction",
            "type":"Services"
        }
    ],
    "sg:phone":"+1 613 830 7628",
    "sg:postcode":"K1E 2L1",
    "sg:province":"ON",
    "sg:tags":[
        "painter"
    ],
    "wof:name":"Orleans Painting Inc",
    "wof:placetype":"venue"
},
  "geometry": {"coordinates":[-75.51220703120001,45.4886817932],"type":"Point"}
}