{
  "type": "Feature",
  "properties": {
    "iso:country":"CA",
    "sg:address":"3428 42 St NE",
    "sg:city":"Calgary",
    "sg:classifiers":[
        {
            "category":"Education",
            "subcategory":"School",
            "type":"Public Place"
        }
    ],
    "sg:phone":"+1 403 777 6700",
    "sg:postcode":"T1Y 6A3",
    "sg:province":"AB",
    "wof:name":"Chief Justice Milvain Elmntry",
    "wof:placetype":"venue"
},
  "geometry": {"coordinates":[-113.97306823700001,51.0827713013],"type":"Point"}
}