{
  "type": "Feature",
  "properties": {
    "addr:full":"1135 Rue Decarie Saint-Laurent QC H4L 3M8",
    "addr:housenumber":"1135",
    "addr:postcode":"h4l 3m8",
    "addr:street":"Rue Decarie",
    "iso:country":"CA",
    "sg:address":"1135 Rue Decarie",
    "sg:city":"Saint-Laurent",
    "sg:classifiers":[
        {
            "category":"Shopping",
            "subcategory":"Pharmacy",
            "type":"Retail Goods"
        }
    ],
    "sg:phone":"+1 514 748 7725",
    "sg:postcode":"H4L 3M8",
    "sg:province":"QC",
    "wof:name":"Pharmaprix",
    "wof:placetype":"venue"
},
  "geometry": {"coordinates":[-73.6841812134,45.5154342651],"type":"Point"}
}