{
  "type": "Feature",
  "properties": {
    "addr:full":"4490 Strathcona Rd North Vancouver BC V7G 1G3",
    "addr:housenumber":"4490",
    "addr:postcode":"v7g 1g3",
    "addr:street":"Strathcona Rd",
    "iso:country":"CA",
    "sg:address":"4490 Strathcona Rd",
    "sg:city":"North Vancouver",
    "sg:classifiers":[
        {
            "category":"Wholesale",
            "subcategory":"Groceries",
            "type":"Manufacturing & Wholesale Goods"
        }
    ],
    "sg:phone":"+1 604 929 4383",
    "sg:postcode":"V7G 1G3",
    "sg:province":"BC",
    "sg:tags":[
        "food",
        "broker"
    ],
    "wof:name":"Positive Resulats",
    "wof:placetype":"venue"
},
  "geometry": {"coordinates":[-122.946228,49.318008],"type":"Point"}
}