{
  "type": "Feature",
  "properties": {
    "iso:country":"CA",
    "sg:address":"4124 16 St SE",
    "sg:city":"Calgary",
    "sg:classifiers":[
        {
            "category":"Manufacturing",
            "subcategory":"Tools & Machinery",
            "type":"Manufacturing & Wholesale Goods"
        }
    ],
    "sg:phone":"+1 403 266 6601",
    "sg:postcode":"T2G 3S1",
    "sg:province":"AB",
    "sg:tags":[
        "refrigeration",
        "refrigerating"
    ],
    "wof:name":"All Temp Refrigeration & Ac",
    "wof:placetype":"venue"
},
  "geometry": {"coordinates":[-114.02200317400001,51.0181083679],"type":"Point"}
}