{
  "type": "Feature",
  "properties": {
    "iso:country":"CA",
    "sg:address":"857 3rd St W",
    "sg:city":"North Vancouver",
    "sg:classifiers":[
        {
            "category":"Wholesale",
            "subcategory":"Electrical",
            "type":"Manufacturing & Wholesale Goods"
        }
    ],
    "sg:phone":"+1 604 980 3688",
    "sg:postcode":"V7P 1E3",
    "sg:province":"BC",
    "sg:tags":[
        "instrument"
    ],
    "wof:name":"Southwell Controls Ltd",
    "wof:placetype":"venue"
},
  "geometry": {"coordinates":[-123.097122,49.320007],"type":"Point"}
}