{
  "type": "Feature",
  "properties": {
    "addr:full":"44 Morrow Rd Barrie ON L4N 3V8",
    "addr:housenumber":"44",
    "addr:postcode":"l4n 3v8",
    "addr:street":"Morrow Rd",
    "iso:country":"CA",
    "sg:address":"44 Morrow Rd",
    "sg:city":"Barrie",
    "sg:classifiers":[
        {
            "category":"Retail",
            "subcategory":"Auto Repair",
            "type":"Services"
        }
    ],
    "sg:phone":"+1 705 733 1393",
    "sg:postcode":"L4N 3V8",
    "sg:province":"ON",
    "sg:tags":[
        "machine",
        "automobile",
        "shop"
    ],
    "wof:name":"Al Billes Racing",
    "wof:placetype":"venue"
},
  "geometry": {"coordinates":[-79.702225,44.360935],"type":"Point"}
}