{
  "type": "Feature",
  "properties": {
    "addr:full":"15537 Hebbville Rd Bridgewater NS B4V 2W4",
    "addr:postcode":"15537;b4v 2w4",
    "addr:street":"Hebbville Rd",
    "iso:country":"CA",
    "sg:address":"15537 Hebbville Rd",
    "sg:city":"Bridgewater",
    "sg:classifiers":[
        {
            "category":"Retail",
            "subcategory":"Auto Repair",
            "type":"Services"
        }
    ],
    "sg:phone":"+1 902 543 3878",
    "sg:postcode":"B4V 2W4",
    "sg:province":"NS",
    "sg:tags":[
        "repairing",
        "automobile"
    ],
    "wof:name":"Le Blanc Auto Svc",
    "wof:placetype":"venue"
},
  "geometry": {"coordinates":[-64.523033,44.380497],"type":"Point"}
}