{
  "type": "Feature",
  "properties": {
    "iso:country":"CA",
    "sg:city":"Chetwynd",
    "sg:classifiers":[
        {
            "category":"Shopping",
            "subcategory":"Department Store",
            "type":"Retail Goods"
        }
    ],
    "sg:phone":"+1 250 788 9687",
    "sg:postcode":"V0C 1J0",
    "sg:province":"BC",
    "wof:name":"Saan Stores Ltd",
    "wof:placetype":"venue"
},
  "geometry": {"coordinates":[-121.63749694800001,55.6958465576],"type":"Point"}
}