{
  "type": "Feature",
  "properties": {
    "addr:full":"528 Everglade Cres London ON N6H 2W7",
    "addr:housenumber":"528",
    "addr:postcode":"n6h 2w7",
    "addr:street":"Everglade Cres",
    "iso:country":"CA",
    "sg:address":"528 Everglade Cres",
    "sg:city":"London",
    "sg:classifiers":[
        {
            "category":"Building & Trades",
            "subcategory":"Construction",
            "type":"Services"
        }
    ],
    "sg:phone":"+1 519 471 5163",
    "sg:postcode":"N6H 2W7",
    "sg:province":"ON",
    "sg:tags":[
        "home",
        "improvement"
    ],
    "wof:name":"Amaral Home Improvements",
    "wof:placetype":"venue"
},
  "geometry": {"coordinates":[-81.31253100000001,42.969147],"type":"Point"}
}