{
  "type": "Feature",
  "properties": {
    "addr:full":"70 Madawaska Blvd Arnprior ON K7S 1S5",
    "addr:housenumber":"70",
    "addr:postcode":"k7s 1s5",
    "addr:street":"Madawaska Blvd",
    "iso:country":"CA",
    "sg:address":"70 Madawaska Blvd",
    "sg:city":"Arnprior",
    "sg:classifiers":[
        {
            "category":"Restaurant",
            "type":"Food & Drink"
        }
    ],
    "sg:phone":"+1 613 623 6060",
    "sg:postcode":"K7S 1S5",
    "sg:province":"ON",
    "wof:name":"Elgin Cafe & Pub",
    "wof:placetype":"venue"
},
  "geometry": {"coordinates":[-76.346992,45.434326],"type":"Point"}
}