{
  "type": "Feature",
  "properties": {
    "addr:full":"1010 Rue DE Serigny Longueuil QC J4K 5G7",
    "addr:housenumber":"1010",
    "addr:postcode":"j4k 5g7",
    "addr:street":"Rue De Serigny",
    "iso:country":"CA",
    "sg:address":"1010 Rue DE Serigny",
    "sg:city":"Longueuil",
    "sg:classifiers":[
        {
            "category":"Government",
            "subcategory":"Office",
            "type":"Public Place"
        }
    ],
    "sg:phone":"+1 450 928 5688",
    "sg:postcode":"J4K 5G7",
    "sg:province":"QC",
    "wof:name":"Quebec Investissement",
    "wof:placetype":"venue"
},
  "geometry": {"coordinates":[-73.523712,45.52343],"type":"Point"}
}