{
  "type": "Feature",
  "properties": {
    "addr:full":"1009 Baker St Cranbrook BC V1C 1A6",
    "addr:housenumber":"1009",
    "addr:postcode":"bc v1c 1a6",
    "addr:street":"Baker St",
    "iso:country":"CA",
    "sg:address":"1009 Baker St",
    "sg:city":"Cranbrook",
    "sg:classifiers":[
        {
            "category":"Food & Beverages",
            "subcategory":"Specialty",
            "type":"Retail Goods"
        }
    ],
    "sg:phone":"+1 250 489 4464",
    "sg:postcode":"V1C 1A6",
    "sg:province":"BC",
    "sg:tags":[
        "health",
        "diet"
    ],
    "wof:name":"Kathy's Kitchen",
    "wof:placetype":"venue"
},
  "geometry": {"coordinates":[-115.767319,49.512024],"type":"Point"}
}