{
  "type": "Feature",
  "properties": {
    "iso:country":"CA",
    "sg:address":"120 Main St N",
    "sg:city":"Carman",
    "sg:classifiers":[
        {
            "category":"Retail",
            "subcategory":"Auto Repair",
            "type":"Services"
        }
    ],
    "sg:phone":"+1 204 745 3756",
    "sg:postcode":"R0G 0J0",
    "sg:province":"MB",
    "sg:tags":[
        "body",
        "automobile",
        "painting"
    ],
    "wof:name":"Carman Collision Ctr",
    "wof:placetype":"venue"
},
  "geometry": {"coordinates":[-98.0015945435,49.5092544556],"type":"Point"}
}