{
  "type": "Feature",
  "properties": {
    "addr:full":"1580 Rue Chabanel O Montreal QC H4N 1H4",
    "addr:housenumber":"1580",
    "addr:postcode":"h4n 1h4",
    "addr:street":"Rue Chabanel O",
    "iso:country":"CA",
    "sg:address":"1580 Rue Chabanel O",
    "sg:city":"Montreal",
    "sg:classifiers":[
        {
            "category":"Wholesale",
            "subcategory":"Sporting Goods",
            "type":"Manufacturing & Wholesale Goods"
        }
    ],
    "sg:phone":"+1 514 382 2283",
    "sg:postcode":"H4N 1H4",
    "sg:province":"QC",
    "wof:name":"Landor Trading CO Ltd",
    "wof:placetype":"venue"
},
  "geometry": {"coordinates":[-73.65821099999999,45.531219],"type":"Point"}
}