{
  "type": "Feature",
  "properties": {
    "addr:full":"5349 4E Av Montreal QC H1Y 2V4",
    "addr:housenumber":"5349",
    "addr:postcode":"h1y 2v4",
    "addr:street":"4E Av",
    "iso:country":"CA",
    "sg:address":"5349 4E Av",
    "sg:city":"Montreal",
    "sg:classifiers":[
        {
            "category":"Organizations",
            "subcategory":"Professional Association",
            "type":"Services"
        }
    ],
    "sg:phone":"+1 514 525 4386",
    "sg:postcode":"H1Y 2V4",
    "sg:province":"QC",
    "wof:name":"Promenade Masson Enr",
    "wof:placetype":"venue"
},
  "geometry": {"coordinates":[-73.5746688843,45.5468864441],"type":"Point"}
}