{
  "type": "Feature",
  "properties": {
    "iso:country":"CA",
    "sg:city":"Montreal",
    "sg:classifiers":[
        {
            "category":"Restaurant",
            "type":"Food & Drink"
        }
    ],
    "sg:phone":"+1 514 939 5530",
    "sg:postcode":"H3K 1H7",
    "sg:province":"QC",
    "sg:tags":[
        "delicatessen"
    ],
    "wof:name":"Wayne Delicatessen",
    "wof:placetype":"venue"
},
  "geometry": {"coordinates":[-73.561501,45.483109],"type":"Point"}
}