{
  "type": "Feature",
  "properties": {
    "addr:full":"Montreal QC H3K 1H7",
    "addr:postcode":"h3k 1h7",
    "iso:country":"CA",
    "sg:city":"Montreal",
    "sg:classifiers":[
        {
            "category":"Restaurant",
            "type":"Food & Drink"
        }
    ],
    "sg:phone":"+1 514 939 5530",
    "sg:postcode":"H3K 1H7",
    "sg:province":"QC",
    "sg:tags":[
        "delicatessen"
    ],
    "wof:name":"Wayne Delicatessen",
    "wof:placetype":"venue"
},
  "geometry": {"coordinates":[-73.56150100000001,45.483109],"type":"Point"}
}