{
  "type": "Feature",
  "properties": {
    "addr:full":"Vancouver BC V6J 1X1",
    "addr:postcode":"v6j 1x1",
    "iso:country":"CA",
    "sg:city":"Vancouver",
    "sg:classifiers":[
        {
            "category":"Professional",
            "subcategory":"Accounting & Tax Preparation",
            "type":"Services"
        }
    ],
    "sg:phone":"+1 604 734 7979",
    "sg:postcode":"V6J 1X1",
    "sg:province":"BC",
    "sg:tags":[
        "accountant"
    ],
    "wof:name":"J R Berkson & Assoc Inc",
    "wof:placetype":"venue"
},
  "geometry": {"coordinates":[-123.142532,49.263817],"type":"Point"}
}