{
  "type": "Feature",
  "properties": {
    "iso:country":"CA",
    "sg:city":"Toronto",
    "sg:classifiers":[
        {
            "category":"Professional",
            "subcategory":"Art Services",
            "type":"Services"
        }
    ],
    "sg:phone":"+1 416 368 2442",
    "sg:postcode":"M5A 3X9",
    "sg:province":"ON",
    "sg:tags":[
        "graphic",
        "designer"
    ],
    "wof:name":"Mad Design Inc",
    "wof:placetype":"venue"
},
  "geometry": {"coordinates":[-79.3683013916,43.6523513794],"type":"Point"}
}