{
  "type": "Feature",
  "properties": {
    "addr:full":"113 Byron St N Whitby ON L1N 4M8",
    "addr:housenumber":"113",
    "addr:postcode":"l1n 4m8",
    "addr:street":"Byron St N",
    "iso:country":"CA",
    "sg:address":"113 Byron St N",
    "sg:city":"Whitby",
    "sg:classifiers":[
        {
            "category":"Personal",
            "subcategory":"Beauty Salon",
            "type":"Services"
        }
    ],
    "sg:phone":"+1 905 668 2299",
    "sg:postcode":"L1N 4M8",
    "sg:province":"ON",
    "wof:name":"Byron Classic Salon",
    "wof:placetype":"venue"
},
  "geometry": {"coordinates":[-78.943657,43.880386],"type":"Point"}
}