{
  "type": "Feature",
  "properties": {
    "addr:full":"2100 Rue Louis-Felix Drummondville QC J2C 6E5",
    "addr:housenumber":"2100",
    "addr:postcode":"j2c 6e5",
    "addr:street":"Rue Louis-Felix",
    "iso:country":"CA",
    "sg:address":"2100 Rue Louis-Felix",
    "sg:city":"Drummondville",
    "sg:classifiers":[
        {
            "category":"Utilities",
            "subcategory":"Fuel Oil & Lpg",
            "type":"Services"
        }
    ],
    "sg:phone":"+1 819 472 5428",
    "sg:postcode":"J2C 6E5",
    "sg:province":"QC",
    "wof:name":"Marchand Petroleum Inc",
    "wof:placetype":"venue"
},
  "geometry": {"coordinates":[-72.50670599999999,45.867104],"type":"Point"}
}