{
  "type": "Feature",
  "properties": {
    "addr:full":"1224 Parkway Dr Port Williams NS B0P 1T0",
    "addr:housenumber":"1224",
    "addr:postcode":"b0p 1t0",
    "addr:street":"Parkway Dr",
    "iso:country":"CA",
    "sg:address":"1224 Parkway Dr",
    "sg:city":"Port Williams",
    "sg:classifiers":[
        {
            "category":"Retail",
            "subcategory":"Auto Repair",
            "type":"Services"
        }
    ],
    "sg:phone":"+1 902 542 7867",
    "sg:postcode":"B0P 1T0",
    "sg:province":"NS",
    "sg:tags":[
        "body",
        "automobile",
        "painting"
    ],
    "wof:name":"Brent Gerrits Collision",
    "wof:placetype":"venue"
},
  "geometry": {"coordinates":[-64.403008,45.099335],"type":"Point"}
}