{
  "type": "Feature",
  "properties": {
    "iso:country":"CA",
    "sg:address":"1184 Denman St",
    "sg:city":"Vancouver",
    "sg:classifiers":[
        {
            "category":"Restaurant",
            "type":"Food & Drink"
        }
    ],
    "sg:phone":"+1 604 688 0802",
    "sg:postcode":"V6G 2M9",
    "sg:province":"BC",
    "wof:name":"Subway Sandwiches & Salads",
    "wof:placetype":"venue"
},
  "geometry": {"coordinates":[-123.14147186300001,49.287311554],"type":"Point"}
}