{
  "type": "Feature",
  "properties": {
    "addr:full":"550 Av Crepeau Mascouche QC J7K 3M8",
    "addr:housenumber":"550",
    "addr:postcode":"j7k 3m8",
    "addr:street":"Av Crepeau",
    "iso:country":"CA",
    "sg:address":"550 Av Crepeau",
    "sg:city":"Mascouche",
    "sg:classifiers":[
        {
            "category":"Social Services",
            "subcategory":"Child Care",
            "type":"Services"
        }
    ],
    "sg:phone":"+1 450 474 5599",
    "sg:postcode":"J7K 3M8",
    "sg:province":"QC",
    "wof:name":"Garderie Educative Les Fourmis",
    "wof:placetype":"venue"
},
  "geometry": {"coordinates":[-73.60643,45.731117],"type":"Point"}
}