{
  "type": "Feature",
  "properties": {
    "iso:country":"CA",
    "sg:address":"49 Keil Dr S",
    "sg:city":"Chatham",
    "sg:classifiers":[
        {
            "category":"Restaurant",
            "type":"Food & Drink"
        }
    ],
    "sg:phone":"+1 519 354 0224",
    "sg:postcode":"N7M 3G7",
    "sg:province":"ON",
    "wof:name":"Pranovi's",
    "wof:placetype":"venue"
},
  "geometry": {"coordinates":[-82.208389,42.392952],"type":"Point"}
}