{
  "type": "Feature",
  "properties": {
    "addr:full":"10 Widdicombe Hill Etobicoke ON M9R 1B3",
    "addr:housenumber":"10",
    "addr:postcode":"m9r 1b3",
    "addr:street":"Widdicombe Hill",
    "iso:country":"CA",
    "sg:address":"10 Widdicombe Hill",
    "sg:city":"Etobicoke",
    "sg:classifiers":[
        {
            "category":"Personal",
            "subcategory":"Hair Removal",
            "type":"Services"
        }
    ],
    "sg:phone":"+1 416 738 8842",
    "sg:postcode":"M9R 1B3",
    "sg:province":"ON",
    "sg:tags":[
        "removing",
        "electrolysis"
    ],
    "wof:name":"Head To Toe Electrolysis By",
    "wof:placetype":"venue"
},
  "geometry": {"coordinates":[-79.548286,43.680012],"type":"Point"}
}