{
  "type": "Feature",
  "properties": {
    "iso:country":"CA",
    "sg:address":"250 Rue Hubert",
    "sg:city":"Beloeil",
    "sg:classifiers":[
        {
            "category":"Organizations",
            "subcategory":"Professional Association",
            "type":"Services"
        }
    ],
    "sg:phone":"+1 450 464 2905",
    "sg:postcode":"J3G 2S9",
    "sg:province":"QC",
    "sg:tags":[
        "social",
        "welfare"
    ],
    "wof:name":"Chevaliers DE Colombs Conseil",
    "wof:placetype":"venue"
},
  "geometry": {"coordinates":[-73.204079,45.569286],"type":"Point"}
}