{
  "type": "Feature",
  "properties": {
    "addr:full":"225 King William St Hamilton ON L8R 1B1",
    "addr:housenumber":"225",
    "addr:postcode":"l8r 1b1",
    "addr:street":"King William St",
    "iso:country":"CA",
    "sg:address":"225 King William St",
    "sg:city":"Hamilton",
    "sg:classifiers":[
        {
            "category":"Organizations",
            "subcategory":"Membership Organization",
            "type":"Services"
        }
    ],
    "sg:phone":"+1 905 522 4446",
    "sg:postcode":"L8R 1B1",
    "sg:province":"ON",
    "sg:tags":[
        "correctional",
        "institution"
    ],
    "wof:name":"John Howard Society",
    "wof:placetype":"venue"
},
  "geometry": {"coordinates":[-79.86042785639999,43.255355835],"type":"Point"}
}