{
  "type": "Feature",
  "properties": {
    "addr:full":"200 Main St Melville SK S0A 2P0",
    "addr:housenumber":"200",
    "addr:postcode":"s0a 2p0",
    "addr:street":"Main St",
    "iso:country":"CA",
    "sg:address":"200 Main St",
    "sg:city":"Melville",
    "sg:classifiers":[
        {
            "category":"Organizations",
            "subcategory":"Professional Association",
            "type":"Services"
        }
    ],
    "sg:phone":"+1 306 728 4141",
    "sg:postcode":"S0A 2P0",
    "sg:province":"SK",
    "sg:tags":[
        "club"
    ],
    "wof:name":"Elk's Club",
    "wof:placetype":"venue"
},
  "geometry": {"coordinates":[-102.818237,50.93169],"type":"Point"}
}