{
  "type": "Feature",
  "properties": {
    "addr:full":"8459 Granville St Vancouver BC V6P 4Z9",
    "addr:housenumber":"8459",
    "addr:postcode":"v6p 4z9",
    "addr:street":"Granville St",
    "iso:country":"CA",
    "sg:address":"8459 Granville St",
    "sg:city":"Vancouver",
    "sg:classifiers":[
        {
            "category":"Food & Beverages",
            "subcategory":"Bakery",
            "type":"Retail Goods"
        }
    ],
    "sg:phone":"+1 604 266 9250",
    "sg:postcode":"V6P 4Z9",
    "sg:province":"BC",
    "sg:tags":[
        "baker"
    ],
    "wof:name":"Uppercrust Bakery & Deli",
    "wof:placetype":"venue"
},
  "geometry": {"coordinates":[-123.140693665,49.2098731995],"type":"Point"}
}