{
  "type": "Feature",
  "properties": {
    "addr:full":"297 Trunk Rd Duncan BC V9L 2P3",
    "addr:housenumber":"297",
    "addr:postcode":"v9l 2p3",
    "addr:street":"Trunk Rd",
    "iso:country":"CA",
    "sg:address":"297 Trunk Rd",
    "sg:city":"Duncan",
    "sg:classifiers":[
        {
            "category":"Personal",
            "subcategory":"Beauty Salon",
            "type":"Services"
        }
    ],
    "sg:phone":"+1 250 746 5852",
    "sg:postcode":"V9L 2P3",
    "sg:province":"BC",
    "wof:name":"Lily's Beauty Salon Ltd",
    "wof:placetype":"venue"
},
  "geometry": {"coordinates":[-123.702202,48.776878],"type":"Point"}
}