{
  "type": "Feature",
  "properties": {
    "addr:full":"4605 1E Av Charlesbourg QC G1H 2T1",
    "addr:housenumber":"4605",
    "addr:postcode":"g1h 2t1",
    "addr:street":"1E Av",
    "iso:country":"CA",
    "sg:address":"4605 1E Av",
    "sg:city":"Charlesbourg",
    "sg:classifiers":[
        {
            "category":"Banks & Credit Unions",
            "subcategory":"Bank",
            "type":"Services"
        }
    ],
    "sg:phone":"+1 418 628 1331",
    "sg:postcode":"G1H 2T1",
    "sg:province":"QC",
    "wof:name":"Banque Nationale Du Canada",
    "wof:placetype":"venue"
},
  "geometry": {"coordinates":[-71.25159499999999,46.844727],"type":"Point"}
}