{
  "type": "Feature",
  "properties": {
    "iso:country":"CA",
    "sg:address":"4605 1E Av",
    "sg:city":"Charlesbourg",
    "sg:classifiers":[
        {
            "category":"Banks & Credit Unions",
            "subcategory":"Bank",
            "type":"Services"
        }
    ],
    "sg:phone":"+1 418 628 1331",
    "sg:postcode":"G1H 2T1",
    "sg:province":"QC",
    "wof:name":"Banque Nationale Du Canada",
    "wof:placetype":"venue"
},
  "geometry": {"coordinates":[-71.251595,46.844727],"type":"Point"}
}