{
  "type": "Feature",
  "properties": {
    "addr:full":"896 10th St Hanover ON N4N 3P2",
    "addr:housenumber":"896",
    "addr:postcode":"n4n 3p2",
    "addr:street":"10Th St",
    "iso:country":"CA",
    "sg:address":"896 10th St",
    "sg:city":"Hanover",
    "sg:classifiers":[
        {
            "category":"Autos & Motor Vehicles",
            "subcategory":"Auto Supplies",
            "type":"Retail Goods"
        }
    ],
    "sg:phone":"+1 519 364 5955",
    "sg:postcode":"N4N 3P2",
    "sg:province":"ON",
    "sg:tags":[
        "repairing",
        "automobile",
        "parts"
    ],
    "wof:name":"Canadian Tire",
    "wof:placetype":"venue"
},
  "geometry": {"coordinates":[-81.00643920900001,44.1555328369],"type":"Point"}
}