{
  "type": "Feature",
  "properties": {
    "addr:full":"10444 20 Ave NW Edmonton AB T6J 5A2",
    "addr:housenumber":"10444",
    "addr:postcode":"t6j 5a2",
    "addr:street":"20 Ave Nw",
    "iso:country":"CA",
    "sg:address":"10444 20 Ave NW",
    "sg:city":"Edmonton",
    "sg:classifiers":[
        {
            "category":"Professional",
            "subcategory":"Engineering",
            "type":"Services"
        }
    ],
    "sg:phone":"+1 780 448 9195",
    "sg:postcode":"T6J 5A2",
    "sg:province":"AB",
    "sg:tags":[
        "engineer"
    ],
    "wof:name":"New Paradigm Engineering Ltd",
    "wof:placetype":"venue"
},
  "geometry": {"coordinates":[-113.497055,53.450932],"type":"Point"}
}