{
  "type": "Feature",
  "properties": {
    "addr:full":"800 Sq Victoria # 400 Montreal QC H4Z 1A1",
    "addr:housenumber":"800",
    "addr:postcode":"h4z 1a1",
    "addr:street":"Sq Victoria # 400",
    "iso:country":"CA",
    "sg:address":"800 Sq Victoria # 400",
    "sg:city":"Montreal",
    "sg:classifiers":[
        {
            "category":"Banks & Credit Unions",
            "subcategory":"Investment Brokerage",
            "type":"Services"
        }
    ],
    "sg:phone":"+1 514 871 2424",
    "sg:postcode":"H4Z 1A1",
    "sg:province":"QC",
    "sg:tags":[
        "stock",
        "exchange"
    ],
    "wof:name":"Bourse DE Montreal Inc",
    "wof:placetype":"venue"
},
  "geometry": {"coordinates":[-73.5607757568,45.5009384155],"type":"Point"}
}