{
  "type": "Feature",
  "properties": {
    "addr:full":"43 Main St Stephenville NL A2N 1H7",
    "addr:housenumber":"43",
    "addr:postcode":"a2n 1h7",
    "addr:street":"Main St",
    "iso:country":"CA",
    "sg:address":"43 Main St",
    "sg:city":"Stephenville",
    "sg:classifiers":[
        {
            "category":"Real Estate",
            "subcategory":"Real Estate Agent",
            "type":"Services"
        }
    ],
    "sg:phone":"+1 709 643 2714",
    "sg:postcode":"A2N 1H7",
    "sg:province":"NL",
    "wof:name":"Westmount Real Estate Ltd",
    "wof:placetype":"venue"
},
  "geometry": {"coordinates":[-58.583584,48.547302],"type":"Point"}
}