{
  "type": "Feature",
  "properties": {
    "addr:full":"377 Woodbridge Ave Woodbridge ON L4L 2V7",
    "addr:housenumber":"377",
    "addr:postcode":"l4l 2v7",
    "addr:street":"Woodbridge Ave",
    "iso:country":"CA",
    "sg:address":"377 Woodbridge Ave",
    "sg:city":"Woodbridge",
    "sg:classifiers":[
        {
            "category":"Education",
            "subcategory":"School",
            "type":"Public Place"
        }
    ],
    "sg:phone":"+1 905 851 1772",
    "sg:postcode":"L4L 2V7",
    "sg:province":"ON",
    "wof:name":"Toronto District Christian Hgh",
    "wof:placetype":"venue"
},
  "geometry": {"coordinates":[-79.6012039185,43.7838783264],"type":"Point"}
}