{
  "type": "Feature",
  "properties": {
    "iso:country":"CA",
    "sg:address":"164 Rue Fleury O",
    "sg:city":"Montreal",
    "sg:classifiers":[
        {
            "category":"Personal",
            "subcategory":"Beauty Salon",
            "type":"Services"
        }
    ],
    "sg:phone":"+1 514 382 5158",
    "sg:postcode":"H3L 1T5",
    "sg:province":"QC",
    "wof:name":"Clinique D'Esthetique Fleuries",
    "wof:placetype":"venue"
},
  "geometry": {"coordinates":[-73.664131,45.549519],"type":"Point"}
}