{
  "type": "Feature",
  "properties": {
    "addr:full":"145 Annette St Toronto ON M6P 1P3",
    "addr:housenumber":"145",
    "addr:postcode":"m6p 1p3",
    "addr:street":"Annette St",
    "iso:country":"CA",
    "sg:address":"145 Annette St",
    "sg:city":"Toronto",
    "sg:classifiers":[
        {
            "category":"Education",
            "subcategory":"Library",
            "type":"Public Place"
        }
    ],
    "sg:phone":"+1 416 393 7692",
    "sg:postcode":"M6P 1P3",
    "sg:province":"ON",
    "wof:name":"Annette Branch Public Library",
    "wof:placetype":"venue"
},
  "geometry": {"coordinates":[-79.4661407471,43.6635055542],"type":"Point"}
}