{
  "type": "Feature",
  "properties": {
    "addr:full":"Newdale MB R0J 1J0",
    "addr:postcode":"r0j 1j0",
    "iso:country":"CA",
    "sg:city":"Newdale",
    "sg:classifiers":[
        {
            "category":"Recreation",
            "type":"Entertainment"
        }
    ],
    "sg:phone":"+1 204 849 2283",
    "sg:postcode":"R0J 1J0",
    "sg:province":"MB",
    "sg:tags":[
        "club",
        "curling"
    ],
    "wof:name":"Newdale Curling Club",
    "wof:placetype":"venue"
},
  "geometry": {"coordinates":[-100.203681946,50.3506660461],"type":"Point"}
}