{
  "type": "Feature",
  "properties": {
    "addr:full":"9094 Leslie St # 2 Richmond Hill ON L4B 3L9",
    "addr:housenumber":"9094",
    "addr:postcode":"l4b 3l9",
    "addr:street":"Leslie St # 2",
    "iso:country":"CA",
    "sg:address":"9094 Leslie St # 2",
    "sg:city":"Richmond Hill",
    "sg:classifiers":[
        {
            "category":"Home & Garden",
            "subcategory":"Furniture",
            "type":"Retail Goods"
        }
    ],
    "sg:phone":"+1 905 764 9098",
    "sg:postcode":"L4B 3L9",
    "sg:province":"ON",
    "sg:tags":[
        "mattress"
    ],
    "wof:name":"Pioneer Bedding Ltd",
    "wof:placetype":"venue"
},
  "geometry": {"coordinates":[-79.384979,43.854191],"type":"Point"}
}