{
  "type": "Feature",
  "properties": {
    "addr:full":"770 Rue Notre-Dame Repentigny QC J5Y 1B6",
    "addr:housenumber":"770",
    "addr:postcode":"j5y 1b6",
    "addr:street":"Rue Notre-Dame",
    "iso:country":"CA",
    "sg:address":"770 Rue Notre-Dame",
    "sg:city":"Repentigny",
    "sg:classifiers":[
        {
            "category":"Retail",
            "subcategory":"Auto Repair",
            "type":"Services"
        }
    ],
    "sg:phone":"+1 450 582 2547",
    "sg:postcode":"J5Y 1B6",
    "sg:province":"QC",
    "sg:tags":[
        "repairing",
        "automobile"
    ],
    "wof:name":"A Bouchard & Fils Inc",
    "wof:placetype":"venue"
},
  "geometry": {"coordinates":[-73.42491099999999,45.760029],"type":"Point"}
}