{
  "type": "Feature",
  "properties": {
    "addr:full":"16640 Westminster Hwy Richmond BC V6V 1A8",
    "addr:housenumber":"16640",
    "addr:postcode":"v6v 1a8",
    "addr:street":"Westminster Hwy",
    "iso:country":"CA",
    "sg:address":"16640 Westminster Hwy",
    "sg:city":"Richmond",
    "sg:classifiers":[
        {
            "category":"Retail",
            "subcategory":"Animal Services",
            "type":"Services"
        }
    ],
    "sg:phone":"+1 604 278 7181",
    "sg:postcode":"V6V 1A8",
    "sg:province":"BC",
    "sg:tags":[
        "pet",
        "boarding",
        "sitting"
    ],
    "wof:name":"Rondivills",
    "wof:placetype":"venue"
},
  "geometry": {"coordinates":[-123.03981,49.169788],"type":"Point"}
}