{
  "type": "Feature",
  "properties": {
    "iso:country":"CA",
    "sg:address":"1112 Central Ave",
    "sg:city":"Saskatoon",
    "sg:classifiers":[
        {
            "category":"Recreation",
            "type":"Entertainment"
        }
    ],
    "sg:phone":"+1 306 374 1040",
    "sg:postcode":"S7N 2H1",
    "sg:province":"SK",
    "sg:tags":[
        "hall",
        "auditorium"
    ],
    "wof:name":"Sutherland Hall",
    "wof:placetype":"venue"
},
  "geometry": {"coordinates":[-106.599174499,52.1398925781],"type":"Point"}
}