{
  "type": "Feature",
  "properties": {
    "addr:full":"1734 7 St SW Calgary AB T2T 2W6",
    "addr:housenumber":"1734 7",
    "addr:postcode":"t2t 2w6",
    "addr:street":"St Sw",
    "iso:country":"CA",
    "sg:address":"1734 7 St SW",
    "sg:city":"Calgary",
    "sg:classifiers":[
        {
            "category":"Professional",
            "subcategory":"Art Services",
            "type":"Services"
        }
    ],
    "sg:phone":"+1 403 229 0072",
    "sg:postcode":"T2T 2W6",
    "sg:province":"AB",
    "sg:tags":[
        "graphic",
        "designer"
    ],
    "wof:name":"Lorna Fraser Graphic Designer",
    "wof:placetype":"venue"
},
  "geometry": {"coordinates":[-114.079093933,51.036491394],"type":"Point"}
}