{
  "type": "Feature",
  "properties": {
    "addr:full":"1075 18E Rue Quebec QC G1J 1Y8",
    "addr:housenumber":"1075",
    "addr:postcode":"g1j 1y8",
    "addr:street":"18E Rue Quebec",
    "iso:country":"CA",
    "sg:address":"1075 18E Rue",
    "sg:city":"Quebec",
    "sg:classifiers":[
        {
            "category":"Manufacturing",
            "subcategory":"Metals",
            "type":"Manufacturing & Wholesale Goods"
        }
    ],
    "sg:phone":"+1 418 522 8271",
    "sg:postcode":"G1J 1Y8",
    "sg:province":"QC",
    "sg:tags":[
        "shelter",
        "garage",
        "canopy",
        "temporary",
        "awning"
    ],
    "wof:name":"Auvents W Lecours Inc",
    "wof:placetype":"venue"
},
  "geometry": {"coordinates":[-71.229111,46.834393],"type":"Point"}
}