{
  "type": "Feature",
  "properties": {
    "addr:full":"383 Midpark Blvd SE Calgary AB T2X 3C8",
    "addr:housenumber":"383",
    "addr:postcode":"t2x 3c8",
    "addr:street":"Midpark Blvd Se",
    "iso:country":"CA",
    "sg:address":"383 Midpark Blvd SE",
    "sg:city":"Calgary",
    "sg:classifiers":[
        {
            "category":"Utilities",
            "subcategory":"Natural Gas",
            "type":"Services"
        }
    ],
    "sg:phone":"+1 403 254 6200",
    "sg:postcode":"T2X 3C8",
    "sg:province":"AB",
    "sg:tags":[
        "company"
    ],
    "wof:name":"Atco Gas",
    "wof:placetype":"venue"
},
  "geometry": {"coordinates":[-114.059669,50.907871],"type":"Point"}
}