{
  "type": "Feature",
  "properties": {
    "addr:full":"3307 Bayview Ave North York ON M2K 1G4",
    "addr:housenumber":"3307",
    "addr:postcode":"m2k 1g4",
    "addr:street":"Bayview Ave",
    "iso:country":"CA",
    "sg:address":"3307 Bayview Ave",
    "sg:city":"North York",
    "sg:classifiers":[
        {
            "category":"Wholesale",
            "subcategory":"Electrical",
            "type":"Manufacturing & Wholesale Goods"
        }
    ],
    "sg:phone":"+1 416 250 7398",
    "sg:postcode":"M2K 1G4",
    "sg:province":"ON",
    "sg:tags":[
        "alarm",
        "burglar",
        "system"
    ],
    "wof:name":"Blaze Alarms",
    "wof:placetype":"venue"
},
  "geometry": {"coordinates":[-79.3932876587,43.7917709351],"type":"Point"}
}