{
  "type": "Feature",
  "properties": {
    "addr:full":"142 Centennial Sq Thunder Bay ON P7E 1H3",
    "addr:housenumber":"142",
    "addr:postcode":"p7e 1h3",
    "addr:street":"Centennial Sq",
    "iso:country":"CA",
    "sg:address":"142 Centennial Sq",
    "sg:city":"Thunder Bay",
    "sg:classifiers":[
        {
            "category":"Food & Beverages",
            "subcategory":"Specialty",
            "type":"Retail Goods"
        }
    ],
    "sg:phone":"+1 807 623 4333",
    "sg:postcode":"P7E 1H3",
    "sg:province":"ON",
    "sg:tags":[
        "health",
        "diet"
    ],
    "wof:name":"Nutrition Corner",
    "wof:placetype":"venue"
},
  "geometry": {"coordinates":[-89.193161,48.473419],"type":"Point"}
}