{
  "type": "Feature",
  "properties": {
    "iso:country":"CA",
    "sg:address":"114 Queen St",
    "sg:city":"St Catharines",
    "sg:classifiers":[
        {
            "category":"Health Services",
            "subcategory":"Doctor",
            "type":"Services"
        }
    ],
    "sg:phone":"+1 905 688 3334",
    "sg:postcode":"L2R 5H3",
    "sg:province":"ON",
    "sg:tags":[
        "physician",
        "surgeon"
    ],
    "wof:name":"Roberts, Mark A MD",
    "wof:placetype":"venue"
},
  "geometry": {"coordinates":[-79.251816,43.160011],"type":"Point"}
}