{
  "type": "Feature",
  "properties": {
    "addr:full":"Baie Verte NL A0K 1B0",
    "addr:postcode":"a0k 1b0",
    "iso:country":"CA",
    "sg:city":"Baie Verte",
    "sg:classifiers":[
        {
            "category":"Government",
            "subcategory":"Fire Station",
            "type":"Public Place"
        }
    ],
    "sg:phone":"+1 709 532 4067",
    "sg:postcode":"A0K 1B0",
    "sg:province":"NL",
    "sg:tags":[
        "department"
    ],
    "wof:name":"Newfoundland Wildlife Officers",
    "wof:placetype":"venue"
},
  "geometry": {"coordinates":[-56.19231,49.939465],"type":"Point"}
}