{
  "type": "Feature",
  "properties": {
    "addr:full":"2 Haviland St Charlottetown PE C1A 3S6",
    "addr:housenumber":"2",
    "addr:postcode":"c1a 3s6",
    "addr:street":"Haviland St",
    "iso:country":"CA",
    "sg:address":"2 Haviland St",
    "sg:city":"Charlottetown",
    "sg:classifiers":[
        {
            "category":"Organizations",
            "subcategory":"Professional Association",
            "type":"Services"
        }
    ],
    "sg:phone":"+1 902 894 4421",
    "sg:postcode":"C1A 3S6",
    "sg:province":"PE",
    "sg:tags":[
        "club"
    ],
    "wof:name":"Haviland Club",
    "wof:placetype":"venue"
},
  "geometry": {"coordinates":[-63.127846,46.230373],"type":"Point"}
}