{
  "type": "Feature",
  "properties": {
    "addr:full":"390 Dundas St Woodstock ON N4S 1B7",
    "addr:housenumber":"390",
    "addr:postcode":"n4s 1b7",
    "addr:street":"Dundas St",
    "iso:country":"CA",
    "sg:address":"390 Dundas St",
    "sg:city":"Woodstock",
    "sg:classifiers":[
        {
            "category":"Government",
            "subcategory":"Office",
            "type":"Public Place"
        }
    ],
    "sg:phone":"+1 519 421 2203",
    "sg:postcode":"N4S 1B7",
    "sg:province":"ON",
    "wof:name":"Water & Wastewater Svc",
    "wof:placetype":"venue"
},
  "geometry": {"coordinates":[-80.7606582642,43.1293983459],"type":"Point"}
}