{
  "type": "Feature",
  "properties": {
    "addr:full":"1 Cabot Cres Happy Valley-Goose Bay NL A0P 1E0",
    "addr:housenumber":"1",
    "addr:postcode":"a0p 1e0",
    "addr:street":"Cabot Cres",
    "iso:country":"CA",
    "sg:address":"1 Cabot Cres",
    "sg:city":"Happy Valley-Goose Bay",
    "sg:classifiers":[
        {
            "category":"Organizations",
            "subcategory":"Religious Organization",
            "type":"Services"
        }
    ],
    "sg:phone":"+1 709 896 1171",
    "sg:postcode":"A0P 1E0",
    "sg:province":"NL",
    "sg:tags":[
        "church"
    ],
    "wof:name":"R C Catechetical Ctr",
    "wof:placetype":"venue"
},
  "geometry": {"coordinates":[-60.3029441833,53.3020706177],"type":"Point"}
}