{
  "type": "Feature",
  "properties": {
    "addr:full":"238 Railway Ave E Eston SK S0L 1A0",
    "addr:housenumber":"238",
    "addr:postcode":"s0l 1a0",
    "addr:street":"Railway Ave E Eston",
    "iso:country":"CA",
    "sg:address":"238 Railway Ave E",
    "sg:city":"Eston",
    "sg:classifiers":[
        {
            "category":"Autos & Motor Vehicles",
            "subcategory":"Auto Supplies",
            "type":"Retail Goods"
        }
    ],
    "sg:phone":"+1 306 962 3899",
    "sg:postcode":"S0L 1A0",
    "sg:province":"SK",
    "sg:tags":[
        "tire"
    ],
    "wof:name":"K & S Tire",
    "wof:placetype":"venue"
},
  "geometry": {"coordinates":[-108.753319,51.153858],"type":"Point"}
}