{
  "type": "Feature",
  "properties": {
    "iso:country":"CA",
    "sg:address":"Kruger Rd",
    "sg:city":"Merville",
    "sg:classifiers":[
        {
            "category":"Organizations",
            "subcategory":"Religious Organization",
            "type":"Services"
        }
    ],
    "sg:phone":"+1 604 337 5258",
    "sg:postcode":"V0R 2M0",
    "sg:province":"BC",
    "sg:tags":[
        "church"
    ],
    "wof:name":"Comox Valley S D A Church",
    "wof:placetype":"venue"
},
  "geometry": {"coordinates":[-125.052230835,49.7814064026],"type":"Point"}
}