{
  "type": "Feature",
  "properties": {
    "addr:full":"Oxford Station ON K0G 1T0",
    "addr:postcode":"k0g 1t0",
    "iso:country":"CA",
    "sg:city":"Oxford Station",
    "sg:classifiers":[
        {
            "category":"Travel",
            "subcategory":"Campground",
            "type":"Entertainment"
        }
    ],
    "sg:phone":"+1 613 258 2940",
    "sg:postcode":"K0G 1T0",
    "sg:province":"ON",
    "wof:name":"Wildwood Camp Grounds",
    "wof:placetype":"venue"
},
  "geometry": {"coordinates":[-75.61334991459999,44.9332122803],"type":"Point"}
}