{
  "type": "Feature",
  "properties": {
    "addr:full":"224 3rd St W Kyle SK S0L 1T0",
    "addr:housenumber":"224",
    "addr:postcode":"s0l 1t0",
    "addr:street":"3Rd St W",
    "iso:country":"CA",
    "sg:address":"224 3rd St W",
    "sg:city":"Kyle",
    "sg:classifiers":[
        {
            "category":"Arena",
            "subcategory":"Sports Club",
            "type":"Entertainment"
        }
    ],
    "sg:phone":"+1 306 375 2252",
    "sg:postcode":"S0L 1T0",
    "sg:province":"SK",
    "sg:tags":[
        "skating",
        "athletic",
        "stadium",
        "rink",
        "fields"
    ],
    "wof:name":"Kyle Community Sports Ctr",
    "wof:placetype":"venue"
},
  "geometry": {"coordinates":[-108.03958129900001,50.8342781067],"type":"Point"}
}