{
  "type": "Feature",
  "properties": {
    "iso:country":"CA",
    "sg:city":"Clarenceville",
    "sg:classifiers":[
        {
            "category":"Farming",
            "subcategory":"Farm",
            "type":"Manufacturing & Wholesale Goods"
        }
    ],
    "sg:phone":"+1 450 294 3331",
    "sg:postcode":"J0J 1B0",
    "sg:province":"QC",
    "wof:name":"Ferme Robitaille Lanoue",
    "wof:placetype":"venue"
},
  "geometry": {"coordinates":[-73.172996521,45.0470199585],"type":"Point"}
}