{
  "type": "Feature",
  "properties": {
    "addr:full":"670 Rue Principale Saint-Thomas QC J0K 3L0",
    "addr:housenumber":"670",
    "addr:postcode":"j0k 3l0",
    "addr:street":"Rue Principale",
    "iso:country":"CA",
    "sg:address":"670 Rue Principale",
    "sg:city":"Saint-Thomas",
    "sg:classifiers":[
        {
            "category":"Autos & Motor Vehicles",
            "subcategory":"Fuel & Gas Station",
            "type":"Retail Goods"
        }
    ],
    "sg:phone":"+1 450 756 0411",
    "sg:postcode":"J0K 3L0",
    "sg:province":"QC",
    "sg:tags":[
        "oil"
    ],
    "wof:name":"Station DE Svc Robitaille",
    "wof:placetype":"venue"
},
  "geometry": {"coordinates":[-73.356148,46.012882],"type":"Point"}
}