{
  "type": "Feature",
  "properties": {
    "addr:full":"Terrace BC V8G 2P2",
    "addr:postcode":"v8g 2p2",
    "iso:country":"CA",
    "sg:city":"Terrace",
    "sg:classifiers":[
        {
            "category":"Health Services",
            "subcategory":"Clinic",
            "type":"Services"
        }
    ],
    "sg:phone":"+1 250 635 2194",
    "sg:postcode":"V8G 2P2",
    "sg:province":"BC",
    "wof:name":"Viva Clinic",
    "wof:placetype":"venue"
},
  "geometry": {"coordinates":[-128.58622700000001,54.52317],"type":"Point"}
}