{
  "type": "Feature",
  "properties": {
    "addr:full":"Richmond BC V6X 1Z7",
    "addr:postcode":"v6x 1z7",
    "iso:country":"CA",
    "sg:city":"Richmond",
    "sg:classifiers":[
        {
            "category":"Building & Trades",
            "subcategory":"Equipment Rental",
            "type":"Services"
        }
    ],
    "sg:phone":"+1 604 273 4583",
    "sg:postcode":"V6X 1Z7",
    "sg:province":"BC",
    "sg:tags":[
        "renting",
        "truck",
        "leasing",
        "yard"
    ],
    "wof:name":"U-Haul CO Ltd",
    "wof:placetype":"venue"
},
  "geometry": {"coordinates":[-123.094078,49.196701],"type":"Point"}
}