{
  "type": "Feature",
  "properties": {
    "addr:full":"525 1st Ave Neepawa MB R0J 1H0",
    "addr:housenumber":"525",
    "addr:postcode":"r0j 1h0",
    "addr:street":"1St Ave",
    "iso:country":"CA",
    "sg:address":"525 1st Ave",
    "sg:city":"Neepawa",
    "sg:classifiers":[
        {
            "category":"Health Services",
            "subcategory":"Nursing And Care Facility",
            "type":"Services"
        }
    ],
    "sg:phone":"+1 204 476 2112",
    "sg:postcode":"R0J 1H0",
    "sg:province":"MB",
    "sg:tags":[
        "home",
        "retirement",
        "community"
    ],
    "wof:name":"Elks Manor",
    "wof:placetype":"venue"
},
  "geometry": {"coordinates":[-99.4673461914,50.2347640991],"type":"Point"}
}