{
  "type": "Feature",
  "properties": {
    "addr:full":"Huntsville ON P1H 1G7",
    "addr:postcode":"p1h 1g7",
    "iso:country":"CA",
    "sg:city":"Huntsville",
    "sg:classifiers":[
        {
            "category":"Retail",
            "subcategory":"Laundry & Dry Cleaning",
            "type":"Services"
        }
    ],
    "sg:phone":"+1 705 788 2407",
    "sg:postcode":"P1H 1G7",
    "sg:province":"ON",
    "sg:tags":[
        "cleaners"
    ],
    "wof:name":"Muskoka Laundry & Dry Cleaners",
    "wof:placetype":"venue"
},
  "geometry": {"coordinates":[-79.211761,45.328625],"type":"Point"}
}