{
  "type": "Feature",
  "properties": {
    "addr:full":"Winnipeg MB R3K 2E2",
    "addr:postcode":"r3k 2e2",
    "iso:country":"CA",
    "sg:city":"Winnipeg",
    "sg:classifiers":[
        {
            "category":"Health Services",
            "subcategory":"Doctor",
            "type":"Services"
        }
    ],
    "sg:phone":"+1 204 958 9500",
    "sg:postcode":"R3K 2E2",
    "sg:province":"MB",
    "sg:tags":[
        "dentist"
    ],
    "wof:name":"Kim, Aaron DDS",
    "wof:placetype":"venue"
},
  "geometry": {"coordinates":[-97.28031900000001,49.879913],"type":"Point"}
}