{
  "type": "Feature",
  "properties": {
    "addr:full":"2 Drummond St W Perth ON K7H 2J2",
    "addr:housenumber":"2",
    "addr:postcode":"k7h 2j2",
    "addr:street":"Drummond St W",
    "iso:country":"CA",
    "sg:address":"2 Drummond St W",
    "sg:city":"Perth",
    "sg:classifiers":[
        {
            "category":"Organizations",
            "subcategory":"Labor Organization",
            "type":"Services"
        }
    ],
    "sg:phone":"+1 613 267 7194",
    "sg:postcode":"K7H 2J2",
    "sg:province":"ON",
    "wof:name":"Cupe",
    "wof:placetype":"venue"
},
  "geometry": {"coordinates":[-76.25011444090001,44.9022521973],"type":"Point"}
}