{
  "type": "Feature",
  "properties": {
    "iso:country":"CA",
    "sg:address":"8540 10E Av",
    "sg:city":"Montreal",
    "sg:classifiers":[
        {
            "category":"Retail",
            "subcategory":"Laundry & Dry Cleaning",
            "type":"Services"
        }
    ],
    "sg:phone":"+1 514 725 9898",
    "sg:postcode":"H1Z 3B6",
    "sg:province":"QC",
    "sg:tags":[
        "diaper"
    ],
    "wof:name":"Q J Trading",
    "wof:placetype":"venue"
},
  "geometry": {"coordinates":[-73.617912,45.566467],"type":"Point"}
}