{
  "type": "Feature",
  "properties": {
    "addr:full":"29 Cormorant Bay Winnipeg MB R2J 2V8",
    "addr:housenumber":"29",
    "addr:postcode":"r2j 2v8",
    "addr:street":"Cormorant Bay",
    "iso:country":"CA",
    "sg:address":"29 Cormorant Bay",
    "sg:city":"Winnipeg",
    "sg:classifiers":[
        {
            "category":"Shopping",
            "type":"Retail Goods"
        }
    ],
    "sg:phone":"+1 204 256 7867",
    "sg:postcode":"R2J 2V8",
    "sg:province":"MB",
    "sg:tags":[
        "cosmetic",
        "perfume"
    ],
    "wof:name":"Mary Kay Cosmetics",
    "wof:placetype":"venue"
},
  "geometry": {"coordinates":[-97.07398999999999,49.849148],"type":"Point"}
}