{
  "type": "Feature",
  "properties": {
    "addr:full":"1095 Crawford Ave Windsor ON N9A 5E1",
    "addr:housenumber":"1095",
    "addr:postcode":"n9a 5e1",
    "addr:street":"Crawford Ave",
    "iso:country":"CA",
    "sg:address":"1095 Crawford Ave",
    "sg:city":"Windsor",
    "sg:classifiers":[
        {
            "category":"Building & Trades",
            "subcategory":"Construction",
            "type":"Services"
        }
    ],
    "sg:phone":"+1 519 258 0535",
    "sg:postcode":"N9A 5E1",
    "sg:province":"ON",
    "sg:tags":[
        "caulking",
        "waterproofing",
        "contractor"
    ],
    "wof:name":"London Caulking & Install",
    "wof:placetype":"venue"
},
  "geometry": {"coordinates":[-83.042984,42.303654],"type":"Point"}
}