{
  "type": "Feature",
  "properties": {
    "addr:full":"7665 Boul Lacordaire Saint-Leonard QC H1S 2A7",
    "addr:housenumber":"7665",
    "addr:postcode":"h1s 2a7",
    "addr:street":"Boul Lacordaire",
    "iso:country":"CA",
    "sg:address":"7665 Boul Lacordaire",
    "sg:city":"Saint-Leonard",
    "sg:classifiers":[
        {
            "category":"Autos & Motor Vehicles",
            "subcategory":"Automobile Sales",
            "type":"Retail Goods"
        }
    ],
    "sg:phone":"+1 514 252 1373",
    "sg:postcode":"H1S 2A7",
    "sg:province":"QC",
    "sg:tags":[
        "car",
        "dealer"
    ],
    "wof:name":"St-Leonard Toyota",
    "wof:placetype":"venue"
},
  "geometry": {"coordinates":[-73.5859222412,45.581867218],"type":"Point"}
}