{
  "type": "Feature",
  "properties": {
    "addr:full":"121 Saunders Rd Mcadam NB E6J 1L7",
    "addr:housenumber":"121",
    "addr:postcode":"e6j 1l7",
    "addr:street":"Saunders Rd",
    "iso:country":"CA",
    "sg:address":"121 Saunders Rd",
    "sg:city":"Mcadam",
    "sg:classifiers":[
        {
            "category":"Shopping",
            "subcategory":"Discount & Variety Stores",
            "type":"Retail Goods"
        }
    ],
    "sg:phone":"+1 506 784 2261",
    "sg:postcode":"E6J 1L7",
    "sg:province":"NB",
    "sg:tags":[
        "merchandise",
        "general"
    ],
    "wof:name":"James H Cook & Sons",
    "wof:placetype":"venue"
},
  "geometry": {"coordinates":[-67.327995,45.59248],"type":"Point"}
}