{
  "type": "Feature",
  "properties": {
    "addr:full":"169 Liberty St Toronto ON M6K 3G3",
    "addr:housenumber":"169",
    "addr:postcode":"m6k 3g3",
    "addr:street":"Liberty St",
    "iso:country":"CA",
    "sg:address":"169 Liberty St",
    "sg:city":"Toronto",
    "sg:classifiers":[
        {
            "category":"Home & Garden",
            "subcategory":"Home Furnishings",
            "type":"Retail Goods"
        }
    ],
    "sg:phone":"+1 416 532 4284",
    "sg:postcode":"M6K 3G3",
    "sg:province":"ON",
    "sg:tags":[
        "pottery"
    ],
    "wof:name":"Gangbar Studio",
    "wof:placetype":"venue"
},
  "geometry": {"coordinates":[-79.424744,43.637314],"type":"Point"}
}