{
  "type": "Feature",
  "properties": {
    "iso:country":"CA",
    "sg:address":"100 Ellerslie Ave",
    "sg:city":"North York",
    "sg:classifiers":[
        {
            "category":"Professional",
            "subcategory":"Management & Consulting",
            "type":"Services"
        }
    ],
    "sg:phone":"+1 416 590 9917",
    "sg:postcode":"M2N 1X8",
    "sg:province":"ON",
    "sg:tags":[
        "consultant",
        "business"
    ],
    "wof:name":"Stewart Advantage Consultants",
    "wof:placetype":"venue"
},
  "geometry": {"coordinates":[-79.4182128906,43.7706298828],"type":"Point"}
}