{
  "type": "Feature",
  "properties": {
    "addr:full":"Montreal QC H4A 1G7",
    "addr:postcode":"h4a 1g7",
    "iso:country":"CA",
    "sg:city":"Montreal",
    "sg:classifiers":[
        {
            "category":"Professional",
            "subcategory":"Accounting & Tax Preparation",
            "type":"Services"
        }
    ],
    "sg:phone":"+1 514 484 4600",
    "sg:postcode":"H4A 1G7",
    "sg:province":"QC",
    "sg:tags":[
        "accountant"
    ],
    "wof:name":"Hsi Consultants Enrg",
    "wof:placetype":"venue"
},
  "geometry": {"coordinates":[-73.62610599999999,45.472206],"type":"Point"}
}