{
  "type": "Feature",
  "properties": {
    "iso:country":"CA",
    "sg:address":"680 Wall St",
    "sg:city":"Winnipeg",
    "sg:classifiers":[
        {
            "category":"Manufacturing",
            "subcategory":"Paper Products",
            "type":"Manufacturing & Wholesale Goods"
        }
    ],
    "sg:phone":"+1 204 786 5761",
    "sg:postcode":"R3G 2T8",
    "sg:province":"MB",
    "sg:tags":[
        "corrugated",
        "solid",
        "fiber",
        "box"
    ],
    "wof:name":"Norampac Inc",
    "wof:placetype":"venue"
},
  "geometry": {"coordinates":[-97.1828536987,49.8877296448],"type":"Point"}
}