{
  "type": "Feature",
  "properties": {
    "addr:full":"605 1st Ave SW Ste Rose Du Lac MB R0L 1S0",
    "addr:housenumber":"605",
    "addr:postcode":"r0l 1s0",
    "addr:street":"1St Ave Sw Ste Rose Du Lac",
    "iso:country":"CA",
    "sg:address":"605 1st Ave SW",
    "sg:city":"Ste Rose Du Lac",
    "sg:classifiers":[
        {
            "category":"Home & Garden",
            "subcategory":"Building Materials",
            "type":"Retail Goods"
        }
    ],
    "sg:phone":"+1 204 447 3152",
    "sg:postcode":"R0L 1S0",
    "sg:province":"MB",
    "wof:name":"Mc Munn & Yates DO-It Ctr",
    "wof:placetype":"venue"
},
  "geometry": {"coordinates":[-99.523201,51.059185],"type":"Point"}
}