{
  "type": "Feature",
  "properties": {
    "iso:country":"CA",
    "sg:address":"6119 Main St",
    "sg:city":"Niagara Falls",
    "sg:classifiers":[
        {
            "category":"Restaurant",
            "type":"Food & Drink"
        }
    ],
    "sg:phone":"+1 905 371 2524",
    "sg:postcode":"L2G 6A2",
    "sg:province":"ON",
    "sg:tags":[
        "cafe"
    ],
    "wof:name":"Cool Corner Cafe",
    "wof:placetype":"venue"
},
  "geometry": {"coordinates":[-79.0913238525,43.0861663818],"type":"Point"}
}