{
  "type": "Feature",
  "properties": {
    "addr:full":"North Vancouver BC V7J 2A2",
    "addr:postcode":"v7j 2a2",
    "iso:country":"CA",
    "sg:city":"North Vancouver",
    "sg:classifiers":[
        {
            "category":"Government",
            "subcategory":"Office",
            "type":"Public Place"
        }
    ],
    "sg:phone":"+1 604 666 0585",
    "sg:postcode":"V7J 2A2",
    "sg:province":"BC",
    "wof:name":"Canada Members of Parliament",
    "wof:placetype":"venue"
},
  "geometry": {"coordinates":[-123.04153442400001,49.335521698],"type":"Point"}
}