{
  "type": "Feature",
  "properties": {
    "addr:full":"5 Arthur St S Guelph ON N1E 5K2",
    "addr:housenumber":"5",
    "addr:postcode":"n1e 5k2",
    "addr:street":"Arthur St S",
    "iso:country":"CA",
    "sg:address":"5 Arthur St S",
    "sg:city":"Guelph",
    "sg:classifiers":[
        {
            "category":"Home & Garden",
            "subcategory":"Household Appliances",
            "type":"Retail Goods"
        }
    ],
    "sg:phone":"+1 519 823 9663",
    "sg:postcode":"N1E 5K2",
    "sg:province":"ON",
    "wof:name":"W C Wood CO Ltd Mfg Major",
    "wof:placetype":"venue"
},
  "geometry": {"coordinates":[-80.242531,43.547424],"type":"Point"}
}