{
  "type": "Feature",
  "properties": {
    "addr:full":"416 Ruth Ave North York ON M2M 2J2",
    "addr:housenumber":"416",
    "addr:postcode":"m2m 2j2",
    "addr:street":"Ruth Ave",
    "iso:country":"CA",
    "sg:address":"416 Ruth Ave",
    "sg:city":"North York",
    "sg:classifiers":[
        {
            "category":"Real Estate",
            "subcategory":"Real Estate Agent",
            "type":"Services"
        }
    ],
    "sg:phone":"+1 416 221 8934",
    "sg:postcode":"M2M 2J2",
    "sg:province":"ON",
    "wof:name":"Alltrust Realty Inc",
    "wof:placetype":"venue"
},
  "geometry": {"coordinates":[-79.398544,43.793285],"type":"Point"}
}