{
  "type": "Feature",
  "properties": {
    "addr:full":"320 College St Toronto ON M5T 1S3",
    "addr:housenumber":"320",
    "addr:postcode":"m5t 1s3",
    "addr:street":"College St",
    "iso:country":"CA",
    "sg:address":"320 College St",
    "sg:city":"Toronto",
    "sg:classifiers":[
        {
            "category":"Restaurant",
            "type":"Food & Drink"
        }
    ],
    "sg:phone":"+1 416 967 1078",
    "sg:postcode":"M5T 1S3",
    "sg:province":"ON",
    "wof:name":"Free Times Cafe",
    "wof:placetype":"venue"
},
  "geometry": {"coordinates":[-79.4024963379,43.6576576233],"type":"Point"}
}