{
  "type": "Feature",
  "properties": {
    "addr:full":"1180 Rue John-Martin Saint-Felix-DE-Valois QC J0K 2M0",
    "addr:housenumber":"1180",
    "addr:postcode":"j0k 2m0",
    "addr:street":"Rue John-Martin Saint-Felix-De-Valois",
    "iso:country":"CA",
    "sg:address":"1180 Rue John-Martin",
    "sg:city":"Saint-Felix-DE-Valois",
    "sg:classifiers":[
        {
            "category":"Building & Trades",
            "subcategory":"Electrical",
            "type":"Services"
        }
    ],
    "sg:phone":"+1 450 889 5387",
    "sg:postcode":"J0K 2M0",
    "sg:province":"QC",
    "sg:tags":[
        "electric",
        "contractor"
    ],
    "wof:name":"Denis St-Georges Electrique",
    "wof:placetype":"venue"
},
  "geometry": {"coordinates":[-73.463218689,46.1731262207],"type":"Point"}
}