{
  "type": "Feature",
  "properties": {
    "addr:full":"2195 Av Ekers Mont-Royal QC H3S 1C6",
    "addr:housenumber":"2195",
    "addr:postcode":"h3s 1c6",
    "addr:street":"Av Ekers",
    "iso:country":"CA",
    "sg:address":"2195 Av Ekers",
    "sg:city":"Mont-Royal",
    "sg:classifiers":[
        {
            "category":"Manufacturing",
            "subcategory":"Metals",
            "type":"Manufacturing & Wholesale Goods"
        }
    ],
    "sg:phone":"+1 514 733 4681",
    "sg:postcode":"H3S 1C6",
    "sg:province":"QC",
    "sg:tags":[
        "stamping"
    ],
    "wof:name":"S Baum Tooling Cie Ltee",
    "wof:placetype":"venue"
},
  "geometry": {"coordinates":[-73.6282653809,45.515247345],"type":"Point"}
}