{
  "type": "Feature",
  "properties": {
    "addr:full":"Spirit River AB T0H 3G0",
    "addr:postcode":"t0h 3g0",
    "iso:country":"CA",
    "sg:city":"Spirit River",
    "sg:classifiers":[
        {
            "category":"Wholesale",
            "subcategory":"Machinery & Supplies",
            "type":"Manufacturing & Wholesale Goods"
        }
    ],
    "sg:phone":"+1 780 864 3735",
    "sg:postcode":"T0H 3G0",
    "sg:province":"AB",
    "sg:tags":[
        "spraying",
        "equipment"
    ],
    "wof:name":"Boomspray Canada Inc",
    "wof:placetype":"venue"
},
  "geometry": {"coordinates":[-118.834068,55.779083],"type":"Point"}
}