{
  "type": "Feature",
  "properties": {
    "addr:full":"4791 Rue Du Parc LA Dore QC G8J 1E1",
    "addr:housenumber":"4791",
    "addr:postcode":"g8j 1e1",
    "addr:street":"Rue Du Parc La Dore",
    "iso:country":"CA",
    "sg:address":"4791 Rue Du Parc",
    "sg:city":"LA Dore",
    "sg:classifiers":[
        {
            "category":"Wholesale",
            "subcategory":"Construction Materials",
            "type":"Manufacturing & Wholesale Goods"
        }
    ],
    "sg:phone":"+1 418 256 1235",
    "sg:postcode":"G8J 1E1",
    "sg:province":"QC",
    "sg:tags":[
        "sand",
        "gravel"
    ],
    "wof:name":"Transport Jhl Inc",
    "wof:placetype":"venue"
},
  "geometry": {"coordinates":[-72.645362854,48.7115287781],"type":"Point"}
}