{
  "type": "Feature",
  "properties": {
    "addr:full":"9305 5 St SE Calgary AB T2J 1K4",
    "addr:housenumber":"9305 5",
    "addr:postcode":"t2j 1k4",
    "addr:street":"St Se",
    "iso:country":"CA",
    "sg:address":"9305 5 St SE",
    "sg:city":"Calgary",
    "sg:classifiers":[
        {
            "category":"Organizations",
            "subcategory":"Professional Association",
            "type":"Services"
        }
    ],
    "sg:phone":"+1 403 252 2116",
    "sg:postcode":"T2J 1K4",
    "sg:province":"AB",
    "sg:tags":[
        "club"
    ],
    "wof:name":"Fraternal Order of Eagles 2098",
    "wof:placetype":"venue"
},
  "geometry": {"coordinates":[-114.052925,50.970089],"type":"Point"}
}