{
  "type": "Feature",
  "properties": {
    "addr:full":"2968 Boul Sainte-Anne Beauport QC G1E 3J3",
    "addr:housenumber":"2968",
    "addr:postcode":"qc g1e 3j3",
    "addr:street":"Boul Sainte-Anne",
    "iso:country":"CA",
    "sg:address":"2968 Boul Sainte-Anne",
    "sg:city":"Beauport",
    "sg:classifiers":[
        {
            "category":"Manufacturing",
            "subcategory":"Food",
            "type":"Manufacturing & Wholesale Goods"
        }
    ],
    "sg:phone":"+1 418 666 9577",
    "sg:postcode":"G1E 3J3",
    "sg:province":"QC",
    "sg:tags":[
        "product",
        "manufacturer"
    ],
    "wof:name":"Metro Richelieu Inc",
    "wof:placetype":"venue"
},
  "geometry": {"coordinates":[-71.21118199999999,46.846481],"type":"Point"}
}