{
  "type": "Feature",
  "properties": {
    "addr:full":"5151 Terminal Rd Halifax NS B3J 1A1",
    "addr:housenumber":"5151",
    "addr:postcode":"ns b3j 1a1",
    "addr:street":"Terminal Rd",
    "iso:country":"CA",
    "sg:address":"5151 Terminal Rd",
    "sg:city":"Halifax",
    "sg:classifiers":[
        {
            "category":"Real Estate",
            "subcategory":"Real Estate Operator",
            "type":"Services"
        }
    ],
    "sg:phone":"+1 902 429 4174",
    "sg:postcode":"B3J 1A1",
    "sg:province":"NS",
    "sg:tags":[
        "building",
        "parks"
    ],
    "wof:name":"Terminal Rd Office Building",
    "wof:placetype":"venue"
},
  "geometry": {"coordinates":[-63.568211,44.640987],"type":"Point"}
}