{
  "type": "Feature",
  "properties": {
    "addr:full":"152 Main St Joggins NS B0L 1A0",
    "addr:housenumber":"152",
    "addr:postcode":"b0l 1a0",
    "addr:street":"Main St",
    "iso:country":"CA",
    "sg:address":"152 Main St",
    "sg:city":"Joggins",
    "sg:classifiers":[
        {
            "category":"Food & Beverages",
            "subcategory":"Liquor & Beverages",
            "type":"Retail Goods"
        }
    ],
    "sg:phone":"+1 902 251 2722",
    "sg:postcode":"B0L 1A0",
    "sg:province":"NS",
    "sg:tags":[
        "government"
    ],
    "wof:name":"Nova Scotia Liquor Commission",
    "wof:placetype":"venue"
},
  "geometry": {"coordinates":[-64.4424209595,45.6912345886],"type":"Point"}
}