{
  "type": "Feature",
  "properties": {
    "addr:full":"294 Tremblay Rd Ottawa ON K1G 0A4",
    "addr:housenumber":"294",
    "addr:postcode":"k1g 0a4",
    "addr:street":"Tremblay Rd",
    "iso:country":"CA",
    "sg:address":"294 Tremblay Rd",
    "sg:city":"Ottawa",
    "sg:classifiers":[
        {
            "category":"Restaurant",
            "type":"Food & Drink"
        }
    ],
    "sg:phone":"+1 613 746 7767",
    "sg:postcode":"K1G 0A4",
    "sg:province":"ON",
    "wof:name":"White Horse Restaurant",
    "wof:placetype":"venue"
},
  "geometry": {"coordinates":[-75.64769699999999,45.418491],"type":"Point"}
}