{
  "type": "Feature",
  "properties": {
    "addr:full":"63 Main St N Minnedosa MB R0J 1E0",
    "addr:housenumber":"63",
    "addr:postcode":"r0j 1e0",
    "addr:street":"Main St N",
    "iso:country":"CA",
    "sg:address":"63 Main St N",
    "sg:city":"Minnedosa",
    "sg:classifiers":[
        {
            "category":"Professional",
            "subcategory":"Management & Consulting",
            "type":"Services"
        }
    ],
    "sg:phone":"+1 204 867 2272",
    "sg:postcode":"R0J 1E0",
    "sg:province":"MB",
    "sg:tags":[
        "consultant",
        "recreation",
        "program",
        "hall",
        "auditorium"
    ],
    "wof:name":"Minnedosa Community Conf Ctr",
    "wof:placetype":"venue"
},
  "geometry": {"coordinates":[-99.8387832642,50.253868103],"type":"Point"}
}