{
  "type": "Feature",
  "properties": {
    "addr:full":"540 Sixth St New Westminster BC V3L 3B5",
    "addr:housenumber":"540",
    "addr:postcode":"v3l 3b5",
    "addr:street":"Sixth St",
    "iso:country":"CA",
    "sg:address":"540 Sixth St",
    "sg:city":"New Westminster",
    "sg:classifiers":[
        {
            "category":"Personal",
            "subcategory":"Beauty Salon",
            "type":"Services"
        }
    ],
    "sg:phone":"+1 604 522 6422",
    "sg:postcode":"V3L 3B5",
    "sg:province":"BC",
    "sg:tags":[
        "consultant",
        "health"
    ],
    "wof:name":"Classic Beauty Salon Ltd",
    "wof:placetype":"venue"
},
  "geometry": {"coordinates":[-122.91986799999999,49.212532],"type":"Point"}
}