{
  "type": "Feature",
  "properties": {
    "iso:country":"CA",
    "sg:address":"1210 17 Ave SW",
    "sg:city":"Calgary",
    "sg:classifiers":[
        {
            "category":"Retail",
            "subcategory":"Laundry & Dry Cleaning",
            "type":"Services"
        }
    ],
    "sg:phone":"+1 403 244 9811",
    "sg:postcode":"T2T 0B8",
    "sg:province":"AB",
    "sg:tags":[
        "cleaners"
    ],
    "wof:name":"Royal Cleaners",
    "wof:placetype":"venue"
},
  "geometry": {"coordinates":[-114.08995819099999,51.0378837585],"type":"Point"}
}