{
  "type": "Feature",
  "properties": {
    "iso:country":"CA",
    "sg:address":"31 Conception Bay Hwy",
    "sg:city":"Conception Bay South",
    "sg:classifiers":[
        {
            "category":"Shopping",
            "subcategory":"Pharmacy",
            "type":"Retail Goods"
        }
    ],
    "sg:phone":"+1 709 834 1003",
    "sg:postcode":"A1W 3A3",
    "sg:province":"NL",
    "wof:name":"Sobeys Pharmacy",
    "wof:placetype":"venue"
},
  "geometry": {"coordinates":[-52.9470672607,47.5205459595],"type":"Point"}
}