{
  "type": "Feature",
  "properties": {
    "addr:full":"2077 Arras Ave Windsor ON N8W 1T4",
    "addr:housenumber":"2077",
    "addr:postcode":"n8w 1t4",
    "addr:street":"Arras Ave",
    "iso:country":"CA",
    "sg:address":"2077 Arras Ave",
    "sg:city":"Windsor",
    "sg:classifiers":[
        {
            "category":"Personal",
            "subcategory":"Beauty Salon",
            "type":"Services"
        }
    ],
    "sg:phone":"+1 519 977 5111",
    "sg:postcode":"N8W 1T4",
    "sg:province":"ON",
    "wof:name":"Shapely Styles",
    "wof:placetype":"venue"
},
  "geometry": {"coordinates":[-82.99279,42.294994],"type":"Point"}
}