{
  "type": "Feature",
  "properties": {
    "addr:full":"Cornwall PE C0A 1H0",
    "addr:postcode":"c0a 1h0",
    "iso:country":"CA",
    "sg:city":"Cornwall",
    "sg:classifiers":[
        {
            "category":"Building & Trades",
            "subcategory":"Plumbing",
            "type":"Services"
        }
    ],
    "sg:phone":"+1 902 675 2360",
    "sg:postcode":"C0A 1H0",
    "sg:province":"PE",
    "sg:tags":[
        "heating",
        "well",
        "drilling",
        "contractor"
    ],
    "wof:name":"Mac Donald Watson Well Drill",
    "wof:placetype":"venue"
},
  "geometry": {"coordinates":[-63.2180747986,46.2276802063],"type":"Point"}
}