{
  "type": "Feature",
  "properties": {
    "addr:full":"7105 Rue Saint-Hubert Montreal QC H2S 2N1",
    "addr:housenumber":"7105",
    "addr:postcode":"h2s 2n1",
    "addr:street":"Rue Saint-Hubert",
    "iso:country":"CA",
    "sg:address":"7105 Rue Saint-Hubert",
    "sg:city":"Montreal",
    "sg:classifiers":[
        {
            "category":"Professional",
            "subcategory":"Management & Consulting",
            "type":"Services"
        }
    ],
    "sg:phone":"+1 514 273 5329",
    "sg:postcode":"H2S 2N1",
    "sg:province":"QC",
    "sg:tags":[
        "consultant",
        "educational"
    ],
    "wof:name":"Capefls Inc",
    "wof:placetype":"venue"
},
  "geometry": {"coordinates":[-73.61215199999999,45.540424],"type":"Point"}
}