{
  "type": "Feature",
  "properties": {
    "addr:full":"106 10 St NW # A Calgary AB T2N 1V3",
    "addr:housenumber":"106 10",
    "addr:postcode":"t2n 1v3",
    "addr:street":"St Nw # A",
    "iso:country":"CA",
    "sg:address":"106 10 St NW # A",
    "sg:city":"Calgary",
    "sg:classifiers":[
        {
            "category":"Home & Garden",
            "subcategory":"Home Furnishings",
            "type":"Retail Goods"
        }
    ],
    "sg:phone":"+1 403 283 9992",
    "sg:postcode":"T2N 1V3",
    "sg:province":"AB",
    "sg:tags":[
        "made",
        "drapery",
        "cushion"
    ],
    "wof:name":"Cushy Life",
    "wof:placetype":"venue"
},
  "geometry": {"coordinates":[-114.085724,51.052288],"type":"Point"}
}