{
  "type": "Feature",
  "properties": {
    "addr:full":"Guelph ON N1G 3W8",
    "addr:postcode":"n1g 3w8",
    "iso:country":"CA",
    "sg:city":"Guelph",
    "sg:classifiers":[
        {
            "category":"Food & Beverages",
            "subcategory":"Specialty",
            "type":"Retail Goods"
        }
    ],
    "sg:phone":"+1 519 763 2284",
    "sg:postcode":"N1G 3W8",
    "sg:province":"ON",
    "sg:tags":[
        "gourmet",
        "shop"
    ],
    "wof:name":"Guelph Poultry Market",
    "wof:placetype":"venue"
},
  "geometry": {"coordinates":[-80.231354,43.508366],"type":"Point"}
}