{
  "type": "Feature",
  "properties": {
    "addr:full":"50 Kingston Rd E Ajax ON L1Z 1G1",
    "addr:housenumber":"50",
    "addr:postcode":"l1z 1g1",
    "addr:street":"Kingston Rd E",
    "iso:country":"CA",
    "sg:address":"50 Kingston Rd E",
    "sg:city":"Ajax",
    "sg:classifiers":[
        {
            "category":"Restaurant",
            "type":"Food & Drink"
        }
    ],
    "sg:phone":"+1 905 426 2393",
    "sg:postcode":"L1Z 1G1",
    "sg:province":"ON",
    "wof:name":"Harvey's",
    "wof:placetype":"venue"
},
  "geometry": {"coordinates":[-79.0229263306,43.8620872498],"type":"Point"}
}