{
  "type": "Feature",
  "properties": {
    "addr:full":"2 King St W # 145 Hamilton ON L8P 1A1",
    "addr:housenumber":"2;145",
    "addr:postcode":"l8p 1a1",
    "addr:street":"King St W #",
    "iso:country":"CA",
    "sg:address":"2 King St W # 145",
    "sg:city":"Hamilton",
    "sg:classifiers":[
        {
            "category":"Shopping",
            "subcategory":"Clothing, Apparel, & Fashions",
            "type":"Retail Goods"
        }
    ],
    "sg:phone":"+1 905 528 5443",
    "sg:postcode":"L8P 1A1",
    "sg:province":"ON",
    "wof:name":"Sirens",
    "wof:placetype":"venue"
},
  "geometry": {"coordinates":[-79.86921691889999,43.2568092346],"type":"Point"}
}