{
  "type": "Feature",
  "properties": {
    "addr:full":"280 Centre St E Richmond Hill ON L4C 1A9",
    "addr:housenumber":"280",
    "addr:postcode":"l4c 1a9",
    "addr:street":"Centre St",
    "iso:country":"CA",
    "sg:address":"280 Centre St E",
    "sg:city":"Richmond Hill",
    "sg:classifiers":[
        {
            "category":"Professional",
            "subcategory":"Computer Services",
            "type":"Services"
        }
    ],
    "sg:phone":"+1 905 770 2189",
    "sg:postcode":"L4C 1A9",
    "sg:province":"ON",
    "sg:tags":[
        "repair"
    ],
    "wof:name":"Bigtech Inc",
    "wof:placetype":"venue"
},
  "geometry": {"coordinates":[-79.42551400000001,43.877674],"type":"Point"}
}