{
  "type": "Feature",
  "properties": {
    "iso:country":"CA",
    "sg:address":"2210 Seal Cove Cir",
    "sg:city":"Prince Rupert",
    "sg:classifiers":[
        {
            "category":"Recreation",
            "subcategory":"Marina",
            "type":"Entertainment"
        }
    ],
    "sg:phone":"+1 250 627 8771",
    "sg:postcode":"V8J 2G3",
    "sg:province":"BC",
    "sg:tags":[
        "repairing",
        "repair",
        "marine",
        "boat"
    ],
    "wof:name":"Kello's Marine Svc",
    "wof:placetype":"venue"
},
  "geometry": {"coordinates":[-130.28973388700001,54.330745697],"type":"Point"}
}