{
  "type": "Feature",
  "properties": {
    "addr:full":"298 Gerard D Levesque O Paspebiac QC G0C 2K0",
    "addr:housenumber":"298",
    "addr:postcode":"g0c 2k0",
    "addr:street":"Gerard D Levesque O Paspebiac",
    "iso:country":"CA",
    "sg:address":"298 Gerard D Levesque O",
    "sg:city":"Paspebiac",
    "sg:classifiers":[
        {
            "category":"Building & Trades",
            "subcategory":"Construction",
            "type":"Services"
        }
    ],
    "sg:phone":"+1 418 752 5302",
    "sg:postcode":"G0C 2K0",
    "sg:province":"QC",
    "sg:tags":[
        "equipment",
        "kitchen",
        "maker",
        "cabinet"
    ],
    "wof:name":"Ebenisterie Delarosbil Inc",
    "wof:placetype":"venue"
},
  "geometry": {"coordinates":[-65.227356,48.033669],"type":"Point"}
}