{
  "type": "Feature",
  "properties": {
    "addr:full":"53 Cimarron Way Okotoks AB T1S 1M8",
    "addr:housenumber":"53",
    "addr:postcode":"t1s 1m8",
    "addr:street":"Cimarron Way;Ab",
    "iso:country":"CA",
    "sg:address":"53 Cimarron Way",
    "sg:city":"Okotoks",
    "sg:classifiers":[
        {
            "category":"Education",
            "subcategory":"School",
            "type":"Public Place"
        }
    ],
    "sg:phone":"+1 403 938 4119",
    "sg:postcode":"T1S 1M8",
    "sg:province":"AB",
    "wof:name":"Okotoks Homeschooling Svc",
    "wof:placetype":"venue"
},
  "geometry": {"coordinates":[-113.966697693,50.7160758972],"type":"Point"}
}