{
  "type": "Feature",
  "properties": {
    "addr:full":"7011 104 St NW Edmonton AB T6H 2L8",
    "addr:housenumber":"7011",
    "addr:postcode":"t6h 2l8",
    "addr:street":"104 St Nw",
    "iso:country":"CA",
    "sg:address":"7011 104 St NW",
    "sg:city":"Edmonton",
    "sg:classifiers":[
        {
            "category":"Building & Trades",
            "subcategory":"Construction",
            "type":"Services"
        }
    ],
    "sg:phone":"+1 780 430 7746",
    "sg:postcode":"T6H 2L8",
    "sg:province":"AB",
    "sg:tags":[
        "contractor"
    ],
    "wof:name":"Vinterra Properties Inc",
    "wof:placetype":"venue"
},
  "geometry": {"coordinates":[-113.49754299999999,53.506554],"type":"Point"}
}