{
  "type": "Feature",
  "properties": {
    "addr:full":"83 Galaxy Blvd Etobicoke ON M9W 5X6",
    "addr:housenumber":"83",
    "addr:postcode":"m9w 5x6",
    "addr:street":"Galaxy Blvd",
    "iso:country":"CA",
    "sg:address":"83 Galaxy Blvd",
    "sg:city":"Etobicoke",
    "sg:classifiers":[
        {
            "category":"Professional",
            "subcategory":"Management & Consulting",
            "type":"Services"
        }
    ],
    "sg:phone":"+1 416 798 2929",
    "sg:postcode":"M9W 5X6",
    "sg:province":"ON",
    "sg:tags":[
        "export"
    ],
    "wof:name":"International Trade Corp",
    "wof:placetype":"venue"
},
  "geometry": {"coordinates":[-79.5855255127,43.6797218323],"type":"Point"}
}