{
  "type": "Feature",
  "properties": {
    "addr:full":"282 South Kingsway Toronto ON M6S 3T9",
    "addr:housenumber":"282",
    "addr:postcode":"m6s 3t9",
    "addr:street":"South Kingsway",
    "iso:country":"CA",
    "sg:address":"282 South Kingsway",
    "sg:city":"Toronto",
    "sg:classifiers":[
        {
            "category":"Utilities",
            "subcategory":"Refuse",
            "type":"Services"
        }
    ],
    "sg:phone":"+1 416 761 9292",
    "sg:postcode":"M6S 3T9",
    "sg:province":"ON",
    "sg:tags":[
        "waste",
        "container",
        "garbage",
        "collection"
    ],
    "wof:name":"Four Seasons Disposal Inc",
    "wof:placetype":"venue"
},
  "geometry": {"coordinates":[-79.4843444824,43.6468696594],"type":"Point"}
}