{
  "type": "Feature",
  "properties": {
    "addr:full":"583 Nebo Rd Hannon ON L0R 1P0",
    "addr:housenumber":"583",
    "addr:postcode":"l0r 1p0",
    "addr:street":"Nebo Rd",
    "iso:country":"CA",
    "sg:address":"583 Nebo Rd",
    "sg:city":"Hannon",
    "sg:classifiers":[
        {
            "category":"Home & Garden",
            "subcategory":"Building Materials",
            "type":"Retail Goods"
        }
    ],
    "sg:phone":"+1 905 679 6433",
    "sg:postcode":"L0R 1P0",
    "sg:province":"ON",
    "sg:tags":[
        "mixed",
        "concrete"
    ],
    "wof:name":"Quality Ready Mix Ltd",
    "wof:placetype":"venue"
},
  "geometry": {"coordinates":[-79.839401,43.189289],"type":"Point"}
}