{
  "type": "Feature",
  "properties": {
    "addr:full":"3300 Kennedy Rd Scarborough ON M1V 3S8",
    "addr:housenumber":"3300",
    "addr:postcode":"m1v 3s8",
    "addr:street":"Kennedy Rd",
    "iso:country":"CA",
    "sg:address":"3300 Kennedy Rd",
    "sg:city":"Scarborough",
    "sg:classifiers":[
        {
            "category":"Organizations",
            "subcategory":"Religious Organization",
            "type":"Services"
        }
    ],
    "sg:phone":"+1 416 754 7147",
    "sg:postcode":"M1V 3S8",
    "sg:province":"ON",
    "sg:tags":[
        "church"
    ],
    "wof:name":"Chinese United Church",
    "wof:placetype":"venue"
},
  "geometry": {"coordinates":[-79.30352000000001,43.815132],"type":"Point"}
}