{
  "type": "Feature",
  "properties": {
    "iso:country":"CA",
    "sg:address":"673 Cassells St",
    "sg:city":"North Bay",
    "sg:classifiers":[
        {
            "category":"Personal",
            "subcategory":"Beauty Salon",
            "type":"Services"
        }
    ],
    "sg:phone":"+1 705 476 5148",
    "sg:postcode":"P1B 4A1",
    "sg:province":"ON",
    "wof:name":"New Horizons Hair Team",
    "wof:placetype":"venue"
},
  "geometry": {"coordinates":[-79.46249389650001,46.3150100708],"type":"Point"}
}