{
  "type": "Feature",
  "properties": {
    "iso:country":"CA",
    "sg:address":"George St & Hwy 2",
    "sg:city":"Simpson",
    "sg:classifiers":[
        {
            "category":"Autos & Motor Vehicles",
            "subcategory":"Fuel & Gas Station",
            "type":"Retail Goods"
        }
    ],
    "sg:phone":"+1 306 836 2101",
    "sg:postcode":"S0G 4M0",
    "sg:province":"SK",
    "sg:tags":[
        "oil"
    ],
    "wof:name":"Simpson CO-OP",
    "wof:placetype":"venue"
},
  "geometry": {"coordinates":[-105.444412231,51.4486236572],"type":"Point"}
}