{
  "type": "Feature",
  "properties": {
    "iso:country":"CA",
    "sg:address":"5005 Boul Pierre-Bertrand",
    "sg:city":"Quebec",
    "sg:classifiers":[
        {
            "category":"Government",
            "subcategory":"Police Station",
            "type":"Public Place"
        }
    ],
    "sg:phone":"+1 418 623 6249",
    "sg:postcode":"G2K 1M1",
    "sg:province":"QC",
    "sg:tags":[
        "department"
    ],
    "wof:name":"Quebec Surete Du",
    "wof:placetype":"venue"
},
  "geometry": {"coordinates":[-71.2817001343,46.8338356018],"type":"Point"}
}