{
  "type": "Feature",
  "properties": {
    "addr:full":"Guelph ON N1L 1E3",
    "addr:postcode":"n1l 1e3",
    "iso:country":"CA",
    "sg:city":"Guelph",
    "sg:classifiers":[
        {
            "category":"Manufacturing",
            "subcategory":"Signs",
            "type":"Manufacturing & Wholesale Goods"
        }
    ],
    "sg:phone":"+1 519 763 5650",
    "sg:postcode":"N1L 1E3",
    "sg:province":"ON",
    "wof:name":"Signshop",
    "wof:placetype":"venue"
},
  "geometry": {"coordinates":[-80.205772,43.564598],"type":"Point"}
}