{
  "type": "Feature",
  "properties": {
    "addr:full":"Saint-Felicien QC G8K 1R7",
    "addr:postcode":"g8k 1r7",
    "iso:country":"CA",
    "sg:city":"Saint-Felicien",
    "sg:classifiers":[
        {
            "category":"Personal",
            "subcategory":"Beauty Salon",
            "type":"Services"
        }
    ],
    "sg:phone":"+1 418 679 0477",
    "sg:postcode":"G8K 1R7",
    "sg:province":"QC",
    "wof:name":"Salon DE Coiffure Felicienne",
    "wof:placetype":"venue"
},
  "geometry": {"coordinates":[-72.437111,48.646965],"type":"Point"}
}