{
  "type": "Feature",
  "properties": {
    "iso:country":"CA",
    "sg:address":"62 Airdrie Dr",
    "sg:city":"Woodbridge",
    "sg:classifiers":[
        {
            "category":"Building & Trades",
            "subcategory":"Plumbing",
            "type":"Services"
        }
    ],
    "sg:phone":"+1 905 851 8044",
    "sg:postcode":"L4L 1C6",
    "sg:province":"ON",
    "sg:tags":[
        "heating",
        "contractor"
    ],
    "wof:name":"Westdown Mechanical Inc",
    "wof:placetype":"venue"
},
  "geometry": {"coordinates":[-79.565155,43.804348],"type":"Point"}
}