{
  "type": "Feature",
  "properties": {
    "iso:country":"CA",
    "sg:address":"5570 Av Du Parc",
    "sg:city":"Montreal",
    "sg:classifiers":[
        {
            "category":"Restaurant",
            "type":"Food & Drink"
        }
    ],
    "sg:phone":"+1 514 271 1453",
    "sg:postcode":"H2V 4H1",
    "sg:province":"QC",
    "wof:name":"Restaurant Aux Lilas",
    "wof:placetype":"venue"
},
  "geometry": {"coordinates":[-73.603264,45.522518],"type":"Point"}
}