{
  "type": "Feature",
  "properties": {
    "addr:full":"Marystown NL A0E 2M0",
    "addr:postcode":"a0e 2m0",
    "iso:country":"CA",
    "sg:city":"Marystown",
    "sg:classifiers":[
        {
            "category":"Shopping",
            "subcategory":"Discount & Variety Stores",
            "type":"Retail Goods"
        }
    ],
    "sg:phone":"+1 709 279 5131",
    "sg:postcode":"A0E 2M0",
    "sg:province":"NL",
    "wof:name":"A Buck or Two",
    "wof:placetype":"venue"
},
  "geometry": {"coordinates":[-55.157001,47.16375],"type":"Point"}
}