{
  "type": "Feature",
  "properties": {
    "addr:full":"13 William St Elmvale ON L0L 1P0",
    "addr:housenumber":"13",
    "addr:postcode":"l0l 1p0",
    "addr:street":"William St",
    "iso:country":"CA",
    "sg:address":"13 William St",
    "sg:city":"Elmvale",
    "sg:classifiers":[
        {
            "category":"Manufacturing",
            "subcategory":"Printing",
            "type":"Manufacturing & Wholesale Goods"
        }
    ],
    "sg:phone":"+1 705 322 1822",
    "sg:postcode":"L0L 1P0",
    "sg:province":"ON",
    "sg:tags":[
        "printer"
    ],
    "wof:name":"Bayweb Transcontinental Ptg",
    "wof:placetype":"venue"
},
  "geometry": {"coordinates":[-79.871574,44.587288],"type":"Point"}
}