{
  "type": "Feature",
  "properties": {
    "addr:full":"New Westminster BC V3M 5Z5",
    "addr:postcode":"v3m 5z5",
    "iso:country":"CA",
    "sg:city":"New Westminster",
    "sg:classifiers":[
        {
            "category":"Social Services",
            "subcategory":"Child Care",
            "type":"Services"
        }
    ],
    "sg:phone":"+1 604 527 5632",
    "sg:postcode":"V3M 5Z5",
    "sg:province":"BC",
    "wof:name":"Douglas College Child Care Ctr",
    "wof:placetype":"venue"
},
  "geometry": {"coordinates":[-122.91244500000001,49.204605],"type":"Point"}
}