{
  "type": "Feature",
  "properties": {
    "addr:full":"Richmond Hill ON L4B 1G9",
    "addr:postcode":"l4b 1g9",
    "iso:country":"CA",
    "sg:city":"Richmond Hill",
    "sg:classifiers":[
        {
            "category":"Restaurant",
            "type":"Food & Drink"
        }
    ],
    "sg:phone":"+1 905 882 0772",
    "sg:postcode":"L4B 1G9",
    "sg:province":"ON",
    "wof:name":"Azzurro Cafe",
    "wof:placetype":"venue"
},
  "geometry": {"coordinates":[-79.38324737550001,43.8531646729],"type":"Point"}
}