{
  "type": "Feature",
  "properties": {
    "addr:full":"5295 Boul Des Mille-Iles Laval QC H7J 1B3",
    "addr:housenumber":"5295",
    "addr:postcode":"h7j 1b3",
    "addr:street":"Boul Des Mille-Iles",
    "iso:country":"CA",
    "sg:address":"5295 Boul Des Mille-Iles",
    "sg:city":"Laval",
    "sg:classifiers":[
        {
            "category":"Retail",
            "subcategory":"Animal Services",
            "type":"Services"
        }
    ],
    "sg:phone":"+1 450 666 3107",
    "sg:postcode":"H7J 1B3",
    "sg:province":"QC",
    "sg:tags":[
        "pet",
        "grooming",
        "washing"
    ],
    "wof:name":"Clinique DE Beaute Canine Enr",
    "wof:placetype":"venue"
},
  "geometry": {"coordinates":[-73.6584014893,45.68309021],"type":"Point"}
}