{
  "type": "Feature",
  "properties": {
    "iso:country":"CA",
    "sg:address":"2275 Rue Power",
    "sg:city":"Drummondville",
    "sg:classifiers":[
        {
            "category":"Retail",
            "subcategory":"Repair Shop",
            "type":"Services"
        }
    ],
    "sg:phone":"+1 819 477 5737",
    "sg:postcode":"J2C 6Z5",
    "sg:province":"QC",
    "sg:tags":[
        "welding"
    ],
    "wof:name":"Soudure Specialisee N Hebert",
    "wof:placetype":"venue"
},
  "geometry": {"coordinates":[-72.52351379389999,45.8732414246],"type":"Point"}
}