{
  "type": "Feature",
  "properties": {
    "iso:country":"CA",
    "sg:address":"16455 Rue Napoleon-Brisebois",
    "sg:city":"Montreal",
    "sg:classifiers":[
        {
            "category":"Home & Garden",
            "subcategory":"Building Materials",
            "type":"Retail Goods"
        }
    ],
    "sg:phone":"+1 514 644 5820",
    "sg:postcode":"H1A 5S6",
    "sg:province":"QC",
    "sg:tags":[
        "glass",
        "window",
        "plate"
    ],
    "wof:name":"Vitrerie Chayer",
    "wof:placetype":"venue"
},
  "geometry": {"coordinates":[-73.48891448969999,45.6991043091],"type":"Point"}
}