{
  "type": "Feature",
  "properties": {
    "iso:country":"CA",
    "sg:address":"166 Charlotte St",
    "sg:city":"Peterborough",
    "sg:classifiers":[
        {
            "category":"Restaurant",
            "type":"Food & Drink"
        }
    ],
    "sg:phone":"+1 705 749 2580",
    "sg:postcode":"K9J 2T8",
    "sg:province":"ON",
    "wof:name":"Mc Thirstys Pint",
    "wof:placetype":"venue"
},
  "geometry": {"coordinates":[-78.320640564,44.3035392761],"type":"Point"}
}