{
  "type": "Feature",
  "properties": {
    "addr:full":"Whistler BC V0N 1B4",
    "addr:postcode":"v0n 1b4",
    "iso:country":"CA",
    "sg:city":"Whistler",
    "sg:classifiers":[
        {
            "category":"Shopping",
            "subcategory":"Tobacco",
            "type":"Retail Goods"
        }
    ],
    "sg:phone":"+1 604 932 6099",
    "sg:postcode":"V0N 1B4",
    "sg:province":"BC",
    "sg:tags":[
        "cigarette",
        "cigar",
        "dealer"
    ],
    "wof:name":"A Vancouver Cigar CO",
    "wof:placetype":"venue"
},
  "geometry": {"coordinates":[-122.955879,50.117214],"type":"Point"}
}