{
  "type": "Feature",
  "properties": {
    "addr:full":"3357 Ellesmere Rd Scarborough ON M1C 1H1",
    "addr:housenumber":"3357",
    "addr:postcode":"m1c 1h1",
    "addr:street":"Ellesmere Rd",
    "iso:country":"CA",
    "sg:address":"3357 Ellesmere Rd",
    "sg:city":"Scarborough",
    "sg:classifiers":[
        {
            "category":"Restaurant",
            "type":"Food & Drink"
        }
    ],
    "sg:phone":"+1 416 282 2889",
    "sg:postcode":"M1C 1H1",
    "sg:province":"ON",
    "wof:name":"Highland Fish & Chips",
    "wof:placetype":"venue"
},
  "geometry": {"coordinates":[-79.1843032837,43.7874488831],"type":"Point"}
}