{
  "type": "Feature",
  "properties": {
    "addr:full":"5260 Boul Saint-Laurent Montreal QC H2T 1S1",
    "addr:housenumber":"5260",
    "addr:postcode":"h2t 1s1",
    "addr:street":"Boul Saint-Laurent",
    "iso:country":"CA",
    "sg:address":"5260 Boul Saint-Laurent",
    "sg:city":"Montreal",
    "sg:classifiers":[
        {
            "category":"Restaurant",
            "type":"Food & Drink"
        }
    ],
    "sg:phone":"+1 514 278 8844",
    "sg:postcode":"H2T 1S1",
    "sg:province":"QC",
    "sg:tags":[
        "cafe"
    ],
    "wof:name":"Snack'n Blues",
    "wof:placetype":"venue"
},
  "geometry": {"coordinates":[-73.59564208979999,45.5241737366],"type":"Point"}
}