{
  "type": "Feature",
  "properties": {
    "addr:full":"490 St Clair St Chatham ON N7L 3K8",
    "addr:housenumber":"490",
    "addr:postcode":"n7l 3k8",
    "addr:street":"St Clair St",
    "iso:country":"CA",
    "sg:address":"490 St Clair St",
    "sg:city":"Chatham",
    "sg:classifiers":[
        {
            "category":"Organizations",
            "subcategory":"Religious Organization",
            "type":"Services"
        }
    ],
    "sg:phone":"+1 519 354 4391",
    "sg:postcode":"N7L 3K8",
    "sg:province":"ON",
    "sg:tags":[
        "church"
    ],
    "wof:name":"Our Lady of Victory Church",
    "wof:placetype":"venue"
},
  "geometry": {"coordinates":[-82.20536,42.41917],"type":"Point"}
}