{
  "type": "Feature",
  "properties": {
    "iso:country":"CA",
    "sg:address":"2111 Main St # 135",
    "sg:city":"Penticton",
    "sg:classifiers":[
        {
            "category":"Banks & Credit Unions",
            "subcategory":"Investment Brokerage",
            "type":"Services"
        }
    ],
    "sg:phone":"+1 250 493 3077",
    "sg:postcode":"V2A 6W6",
    "sg:province":"BC",
    "sg:tags":[
        "consultant",
        "planning",
        "financial",
        "advisory"
    ],
    "wof:name":"Valley First Financial Svc Ltd",
    "wof:placetype":"venue"
},
  "geometry": {"coordinates":[-119.583015442,49.4747161865],"type":"Point"}
}