{
  "type": "Feature",
  "properties": {
    "iso:country":"CA",
    "sg:address":"208 Piccadilly St",
    "sg:city":"London",
    "sg:classifiers":[
        {
            "category":"Shopping",
            "subcategory":"Used Merchandise",
            "type":"Retail Goods"
        }
    ],
    "sg:phone":"+1 519 434 6107",
    "sg:postcode":"N6A 1S1",
    "sg:province":"ON",
    "sg:tags":[
        "shop",
        "consignment"
    ],
    "wof:name":"Timeless Boutique Treasures",
    "wof:placetype":"venue"
},
  "geometry": {"coordinates":[-81.253029,42.994408],"type":"Point"}
}