{
  "type": "Feature",
  "properties": {
    "addr:full":"9790 51 Ave NW Edmonton AB T6E 0A6",
    "addr:housenumber":"9790",
    "addr:postcode":"t6e 0a6",
    "addr:street":"51 Ave Nw",
    "iso:country":"CA",
    "sg:address":"9790 51 Ave NW",
    "sg:city":"Edmonton",
    "sg:classifiers":[
        {
            "category":"Manufacturing",
            "subcategory":"Printing",
            "type":"Manufacturing & Wholesale Goods"
        }
    ],
    "sg:phone":"+1 780 435 9394",
    "sg:postcode":"T6E 0A6",
    "sg:province":"AB",
    "sg:tags":[
        "printer"
    ],
    "wof:name":"Alpine Press Ltd",
    "wof:placetype":"venue"
},
  "geometry": {"coordinates":[-113.484711,53.488415],"type":"Point"}
}