{
  "type": "Feature",
  "properties": {
    "addr:full":"5155 Spectrum Way # 15 Mississauga ON L4W 5A1",
    "addr:housenumber":"5155",
    "addr:postcode":"l4w 5a1",
    "addr:street":"Spectrum Way # 15",
    "iso:country":"CA",
    "sg:address":"5155 Spectrum Way # 15",
    "sg:city":"Mississauga",
    "sg:classifiers":[
        {
            "category":"Insurance",
            "subcategory":"Insurance Agent",
            "type":"Services"
        }
    ],
    "sg:phone":"+1 905 238 0022",
    "sg:postcode":"L4W 5A1",
    "sg:province":"ON",
    "sg:tags":[
        "adjuster"
    ],
    "wof:name":"Szypka Welton & Assoc Ins Ltd",
    "wof:placetype":"venue"
},
  "geometry": {"coordinates":[-79.6114807129,43.6503562927],"type":"Point"}
}