{
  "type": "Feature",
  "properties": {
    "addr:full":"788 Rue Cowie Granby QC J2G 3Y1",
    "addr:housenumber":"788",
    "addr:postcode":"j2g 3y1",
    "addr:street":"Rue Cowie",
    "iso:country":"CA",
    "sg:address":"788 Rue Cowie",
    "sg:city":"Granby",
    "sg:classifiers":[
        {
            "category":"Wholesale",
            "subcategory":"Hardware",
            "type":"Manufacturing & Wholesale Goods"
        }
    ],
    "sg:phone":"+1 450 378 7458",
    "sg:postcode":"J2G 3Y1",
    "sg:province":"QC",
    "wof:name":"Specialites En Quincaillerie",
    "wof:placetype":"venue"
},
  "geometry": {"coordinates":[-72.755371,45.394337],"type":"Point"}
}