{
  "type": "Feature",
  "properties": {
    "addr:full":"57 Beaverbank Rd Lower Sackville NS B4E 1V5",
    "addr:housenumber":"57",
    "addr:postcode":"ns b4e 1v5",
    "addr:street":"Beaverbank Rd Lower",
    "iso:country":"CA",
    "sg:address":"57 Beaverbank Rd",
    "sg:city":"Lower Sackville",
    "sg:classifiers":[
        {
            "category":"Restaurant",
            "type":"Food & Drink"
        }
    ],
    "sg:phone":"+1 902 865 2226",
    "sg:postcode":"B4E 1V5",
    "sg:province":"NS",
    "wof:name":"May Garden Chinese Food",
    "wof:placetype":"venue"
},
  "geometry": {"coordinates":[-63.691551,44.782146],"type":"Point"}
}