{
  "type": "Feature",
  "properties": {
    "addr:full":"1 Maliseet Dr Woodstock First Nation NB E7M 4J5",
    "addr:housenumber":"1",
    "addr:postcode":"e7m 4j5",
    "addr:street":"Maliseet Dr",
    "iso:country":"CA",
    "sg:address":"1 Maliseet Dr",
    "sg:city":"Woodstock First Nation",
    "sg:classifiers":[
        {
            "category":"Health Services",
            "subcategory":"Doctor",
            "type":"Services"
        }
    ],
    "sg:phone":"+1 506 328 8813",
    "sg:postcode":"E7M 4J5",
    "sg:province":"NB",
    "sg:tags":[
        "physician",
        "surgeon"
    ],
    "wof:name":"Perley, M P MD",
    "wof:placetype":"venue"
},
  "geometry": {"coordinates":[-67.57395200000001,46.150249],"type":"Point"}
}