{
  "type": "Feature",
  "properties": {
    "addr:full":"500 Brooksbank Ave North Vancouver BC V7J 3S4",
    "addr:housenumber":"500",
    "addr:postcode":"v7j 3s4",
    "addr:street":"Brooksbank Ave",
    "iso:country":"CA",
    "sg:address":"500 Brooksbank Ave",
    "sg:city":"North Vancouver",
    "sg:classifiers":[
        {
            "category":"Professional",
            "subcategory":"Engineering",
            "type":"Services"
        }
    ],
    "sg:phone":"+1 604 980 3421",
    "sg:postcode":"V7J 3S4",
    "sg:province":"BC",
    "sg:tags":[
        "paper",
        "engineer"
    ],
    "wof:name":"Honeywell",
    "wof:placetype":"venue"
},
  "geometry": {"coordinates":[-123.040214539,49.3107452393],"type":"Point"}
}