{
  "type": "Feature",
  "properties": {
    "addr:full":"Winnipeg MB R2V 3C8",
    "addr:postcode":"r2v 3c8",
    "iso:country":"CA",
    "sg:city":"Winnipeg",
    "sg:classifiers":[
        {
            "category":"Professional",
            "subcategory":"Lawyer & Legal Services",
            "type":"Services"
        }
    ],
    "sg:phone":"+1 204 694 5588",
    "sg:postcode":"R2V 3C8",
    "sg:province":"MB",
    "sg:tags":[
        "attorney"
    ],
    "wof:name":"Nickel, Ingrid",
    "wof:placetype":"venue"
},
  "geometry": {"coordinates":[-97.152,49.948757],"type":"Point"}
}