{
  "type": "Feature",
  "properties": {
    "addr:full":"582 North River Rd Charlottetown PE C1E 1K1",
    "addr:housenumber":"582",
    "addr:postcode":"c1e 1k1",
    "addr:street":"North River Rd",
    "iso:country":"CA",
    "sg:address":"582 North River Rd",
    "sg:city":"Charlottetown",
    "sg:classifiers":[
        {
            "category":"Organizations",
            "subcategory":"Non-profit Organization",
            "type":"Services"
        }
    ],
    "sg:phone":"+1 902 892 2367",
    "sg:postcode":"C1E 1K1",
    "sg:province":"PE",
    "sg:tags":[
        "charitable",
        "institution"
    ],
    "wof:name":"Benevolent Irish Society",
    "wof:placetype":"venue"
},
  "geometry": {"coordinates":[-63.156109,46.261475],"type":"Point"}
}