{
  "type": "Feature",
  "properties": {
    "addr:full":"166 Pearl St E Brockville ON K6V 1R4",
    "addr:housenumber":"166",
    "addr:postcode":"k6v 1r4",
    "addr:street":"Pearl St",
    "iso:country":"CA",
    "sg:address":"166 Pearl St E",
    "sg:city":"Brockville",
    "sg:classifiers":[
        {
            "category":"Education",
            "subcategory":"School",
            "type":"Public Place"
        }
    ],
    "sg:phone":"+1 613 345 5031",
    "sg:postcode":"K6V 1R4",
    "sg:province":"ON",
    "wof:name":"Commonwealth Public School",
    "wof:placetype":"venue"
},
  "geometry": {"coordinates":[-75.6793212891,44.5975341797],"type":"Point"}
}