{
  "type": "Feature",
  "properties": {
    "iso:country":"CA",
    "sg:address":"250 Wyse Rd",
    "sg:city":"Dartmouth",
    "sg:classifiers":[
        {
            "category":"Wholesale",
            "subcategory":"Meat",
            "type":"Manufacturing & Wholesale Goods"
        }
    ],
    "sg:phone":"+1 902 464 4777",
    "sg:postcode":"B3A 1N2",
    "sg:province":"NS",
    "sg:tags":[
        "butchering"
    ],
    "wof:name":"Chater Meat Market",
    "wof:placetype":"venue"
},
  "geometry": {"coordinates":[-63.585411,44.675056],"type":"Point"}
}