{
  "type": "Feature",
  "properties": {
    "addr:full":"1592 Ogilvie St S Prince George BC V2N 1W9",
    "addr:housenumber":"1592",
    "addr:postcode":"v2n 1w9",
    "addr:street":"Ogilvie St S",
    "iso:country":"CA",
    "sg:address":"1592 Ogilvie St S",
    "sg:city":"Prince George",
    "sg:classifiers":[
        {
            "category":"Wholesale",
            "subcategory":"Hardware",
            "type":"Manufacturing & Wholesale Goods"
        }
    ],
    "sg:phone":"+1 250 564 8616",
    "sg:postcode":"V2N 1W9",
    "sg:province":"BC",
    "sg:tags":[
        "equipment",
        "heating",
        "system"
    ],
    "wof:name":"Energy Wise Distributors Ltd",
    "wof:placetype":"venue"
},
  "geometry": {"coordinates":[-122.788955688,53.9094581604],"type":"Point"}
}