{
  "type": "Feature",
  "properties": {
    "iso:country":"CA",
    "sg:address":"1049 Mcphee Ave",
    "sg:city":"Courtenay",
    "sg:classifiers":[
        {
            "category":"Home & Garden",
            "subcategory":"Garden Supply",
            "type":"Retail Goods"
        }
    ],
    "sg:phone":"+1 250 334 3678",
    "sg:postcode":"V9N 3A1",
    "sg:province":"BC",
    "sg:tags":[
        "lawn",
        "mower"
    ],
    "wof:name":"Rent-All Equipment Ctr",
    "wof:placetype":"venue"
},
  "geometry": {"coordinates":[-125.00252500000001,49.684399],"type":"Point"}
}