{
  "type": "Feature",
  "properties": {
    "addr:full":"300 Muskoka Rd N Gravenhurst ON P1P 1N8",
    "addr:housenumber":"300",
    "addr:postcode":"p1p 1n8",
    "addr:street":"Muskoka Rd N",
    "iso:country":"CA",
    "sg:address":"300 Muskoka Rd N",
    "sg:city":"Gravenhurst",
    "sg:classifiers":[
        {
            "category":"Health Services",
            "subcategory":"Nursing And Care Facility",
            "type":"Services"
        }
    ],
    "sg:phone":"+1 705 687 3356",
    "sg:postcode":"P1P 1N8",
    "sg:province":"ON",
    "sg:tags":[
        "home",
        "retirement",
        "community"
    ],
    "wof:name":"Gravenhurst Manor",
    "wof:placetype":"venue"
},
  "geometry": {"coordinates":[-79.374741,44.921677],"type":"Point"}
}