{
  "type": "Feature",
  "properties": {
    "addr:full":"1350 Brockchem Rd Maitland ON K0E 1P0",
    "addr:housenumber":"1350",
    "addr:postcode":"k0e 1p0",
    "addr:street":"Brockchem Rd",
    "iso:country":"CA",
    "sg:address":"1350 Brockchem Rd",
    "sg:city":"Maitland",
    "sg:classifiers":[
        {
            "category":"Manufacturing",
            "subcategory":"Chemicals & Compounds",
            "type":"Manufacturing & Wholesale Goods"
        }
    ],
    "sg:phone":"+1 613 348 3743",
    "sg:postcode":"K0E 1P0",
    "sg:province":"ON",
    "wof:name":"Nitrous Oxide of Canada",
    "wof:placetype":"venue"
},
  "geometry": {"coordinates":[-75.593872,44.652397],"type":"Point"}
}