{
  "type": "Feature",
  "properties": {
    "iso:country":"CA",
    "sg:address":"219 Shoemaker St",
    "sg:city":"Kitchener",
    "sg:classifiers":[
        {
            "category":"Manufacturing",
            "subcategory":"Tools & Machinery",
            "type":"Manufacturing & Wholesale Goods"
        }
    ],
    "sg:phone":"+1 519 893 1500",
    "sg:postcode":"N2E 3B3",
    "sg:province":"ON",
    "sg:tags":[
        "lighting",
        "fixture"
    ],
    "wof:name":"Acculite Manufacturing Inc",
    "wof:placetype":"venue"
},
  "geometry": {"coordinates":[-80.46845245359999,43.4060516357],"type":"Point"}
}