{
  "type": "Feature",
  "properties": {
    "addr:full":"165 Front St N Campbellford ON K0L 1L0",
    "addr:housenumber":"165",
    "addr:postcode":"k0l 1l0",
    "addr:street":"Front St N Campbellford",
    "iso:country":"CA",
    "sg:address":"165 Front St N",
    "sg:city":"Campbellford",
    "sg:classifiers":[
        {
            "category":"Taxi",
            "type":"Transportation"
        }
    ],
    "sg:phone":"+1 705 653 4742",
    "sg:postcode":"K0L 1L0",
    "sg:province":"ON",
    "sg:tags":[
        "taxicab"
    ],
    "wof:name":"Cambellford Ellis Taxi",
    "wof:placetype":"venue"
},
  "geometry": {"coordinates":[-77.79350280760001,44.3128204346],"type":"Point"}
}