{
  "type": "Feature",
  "properties": {
    "addr:full":"9903 107 St Westlock AB T7P 2K5",
    "addr:housenumber":"9903",
    "addr:postcode":"t7p 2k5",
    "addr:street":"107 St",
    "iso:country":"CA",
    "sg:address":"9903 107 St",
    "sg:city":"Westlock",
    "sg:classifiers":[
        {
            "category":"Personal",
            "subcategory":"Beauty Salon",
            "type":"Services"
        }
    ],
    "sg:phone":"+1 780 349 5088",
    "sg:postcode":"T7P 2K5",
    "sg:province":"AB",
    "wof:name":"Rendezvous Hair",
    "wof:placetype":"venue"
},
  "geometry": {"coordinates":[-113.864418,54.154716],"type":"Point"}
}