{
  "type": "Feature",
  "properties": {
    "addr:full":"381 Broadview Ave Toronto ON M4K 2M7",
    "addr:housenumber":"381",
    "addr:postcode":"m4k 2m7",
    "addr:street":"Broadview Ave",
    "iso:country":"CA",
    "sg:address":"381 Broadview Ave",
    "sg:city":"Toronto",
    "sg:classifiers":[
        {
            "category":"Health Services",
            "subcategory":"Clinic",
            "type":"Services"
        }
    ],
    "sg:phone":"+1 416 461 2280",
    "sg:postcode":"M4K 2M7",
    "sg:province":"ON",
    "wof:name":"Maximal Functions",
    "wof:placetype":"venue"
},
  "geometry": {"coordinates":[-79.352554,43.66584],"type":"Point"}
}