{
  "type": "Feature",
  "properties": {
    "addr:full":"1250 Brownmiller Rd Quesnel BC V2J 6P5",
    "addr:housenumber":"1250",
    "addr:postcode":"v2j 6p5",
    "addr:street":"Brownmiller Rd",
    "iso:country":"CA",
    "sg:address":"1250 Brownmiller Rd",
    "sg:city":"Quesnel",
    "sg:classifiers":[
        {
            "category":"Manufacturing",
            "subcategory":"Lumber",
            "type":"Manufacturing & Wholesale Goods"
        }
    ],
    "sg:phone":"+1 250 992 9244",
    "sg:postcode":"V2J 6P5",
    "sg:province":"BC",
    "wof:name":"West Fraser Mills Ltd",
    "wof:placetype":"venue"
},
  "geometry": {"coordinates":[-122.50438690199999,52.9948806763],"type":"Point"}
}