{
  "type": "Feature",
  "properties": {
    "addr:full":"135 Gateway Park Dr Kitchener ON N2P 2J9",
    "addr:housenumber":"135",
    "addr:postcode":"n2p 2j9",
    "addr:street":"Gateway Park Dr",
    "iso:country":"CA",
    "sg:address":"135 Gateway Park Dr",
    "sg:city":"Kitchener",
    "sg:classifiers":[
        {
            "category":"Shopping",
            "subcategory":"Books",
            "type":"Retail Goods"
        }
    ],
    "sg:phone":"+1 519 650 2553",
    "sg:postcode":"N2P 2J9",
    "sg:province":"ON",
    "sg:tags":[
        "dealer"
    ],
    "wof:name":"Chapters",
    "wof:placetype":"venue"
},
  "geometry": {"coordinates":[-80.387733,43.406582],"type":"Point"}
}