{
  "type": "Feature",
  "properties": {
    "iso:country":"CA",
    "sg:address":"135 Gateway Park Dr",
    "sg:city":"Kitchener",
    "sg:classifiers":[
        {
            "category":"Shopping",
            "subcategory":"Books",
            "type":"Retail Goods"
        }
    ],
    "sg:phone":"+1 519 650 2553",
    "sg:postcode":"N2P 2J9",
    "sg:province":"ON",
    "sg:tags":[
        "dealer"
    ],
    "wof:name":"Chapters",
    "wof:placetype":"venue"
},
  "geometry": {"coordinates":[-80.387733,43.406582],"type":"Point"}
}