{
  "type": "Feature",
  "properties": {
    "addr:full":"PO Box 90 Sherbrooke NS B0J 3C0",
    "addr:housenumber":"po box 90",
    "addr:postcode":"b0j 3c0",
    "iso:country":"CA",
    "sg:address":"PO Box 90",
    "sg:city":"Sherbrooke",
    "sg:classifiers":[
        {
            "category":"Manufacturing",
            "subcategory":"Printing",
            "type":"Manufacturing & Wholesale Goods"
        }
    ],
    "sg:phone":"+1 902 522 2090",
    "sg:postcode":"B0J 3C0",
    "sg:province":"NS",
    "sg:tags":[
        "publisher"
    ],
    "wof:name":"Nova Satellite Productions Ltd",
    "wof:placetype":"venue"
},
  "geometry": {"coordinates":[-61.9816894531,45.1432151794],"type":"Point"}
}