{
  "type": "Feature",
  "properties": {
    "addr:full":"238 Main St Cambridge ON N1R 1W8",
    "addr:housenumber":"238",
    "addr:postcode":"n1r 1w8",
    "addr:street":"Main St",
    "iso:country":"CA",
    "sg:address":"238 Main St",
    "sg:city":"Cambridge",
    "sg:classifiers":[
        {
            "category":"Health Services",
            "subcategory":"Health Practitioner",
            "type":"Services"
        }
    ],
    "sg:phone":"+1 519 621 3278",
    "sg:postcode":"N1R 1W8",
    "sg:province":"ON",
    "sg:tags":[
        "psychotherapist",
        "counselor",
        "marriage",
        "family"
    ],
    "wof:name":"Seaton Schwarz Counselling",
    "wof:placetype":"venue"
},
  "geometry": {"coordinates":[-80.302711,43.356575],"type":"Point"}
}