{
  "type": "Feature",
  "properties": {
    "iso:country":"CA",
    "sg:address":"4908 Rue Adam",
    "sg:city":"Montreal",
    "sg:classifiers":[
        {
            "category":"Health Services",
            "subcategory":"Nursing And Care Facility",
            "type":"Services"
        }
    ],
    "sg:phone":"+1 514 256 6043",
    "sg:postcode":"H1V 1W3",
    "sg:province":"QC",
    "sg:tags":[
        "home",
        "retirement",
        "community"
    ],
    "wof:name":"Residence St-Clement",
    "wof:placetype":"venue"
},
  "geometry": {"coordinates":[-73.5316543579,45.5573310852],"type":"Point"}
}