{
  "type": "Feature",
  "properties": {
    "addr:full":"1251 4th Ave Prince George BC V2L 3J5",
    "addr:housenumber":"1251",
    "addr:postcode":"v2l 3j5",
    "addr:street":"4Th Ave",
    "iso:country":"CA",
    "sg:address":"1251 4th Ave",
    "sg:city":"Prince George",
    "sg:classifiers":[
        {
            "category":"Restaurant",
            "type":"Food & Drink"
        }
    ],
    "sg:phone":"+1 250 563 4369",
    "sg:postcode":"V2L 3J5",
    "sg:province":"BC",
    "sg:tags":[
        "shop",
        "coffee"
    ],
    "wof:name":"Zoe's Java House",
    "wof:placetype":"venue"
},
  "geometry": {"coordinates":[-122.74600982699999,53.9159011841],"type":"Point"}
}