{
  "type": "Feature",
  "properties": {
    "addr:full":"2 Rue Grande Rue Katevale QC J0B 1W0",
    "addr:housenumber":"2",
    "addr:postcode":"j0b 1w0",
    "addr:street":"Rue Grande Rue Katevale",
    "iso:country":"CA",
    "sg:address":"2 Rue Grande Rue",
    "sg:city":"Katevale",
    "sg:classifiers":[
        {
            "category":"Travel",
            "subcategory":"Hotels & Motels",
            "type":"Entertainment"
        }
    ],
    "sg:phone":"+1 819 868 1212",
    "sg:postcode":"J0B 1W0",
    "sg:province":"QC",
    "sg:tags":[
        "inn"
    ],
    "wof:name":"Auberge Ste-Catherine-Hatley",
    "wof:placetype":"venue"
},
  "geometry": {"coordinates":[-72.0528640747,45.1961708069],"type":"Point"}
}