{
  "type": "Feature",
  "properties": {
    "addr:full":"45643 Lark Rd Chilliwack BC V2R 3N5",
    "addr:housenumber":"45643",
    "addr:postcode":"v2r 3n5",
    "addr:street":"Lark Rd",
    "iso:country":"CA",
    "sg:address":"45643 Lark Rd",
    "sg:city":"Chilliwack",
    "sg:classifiers":[
        {
            "category":"Personal",
            "subcategory":"Beauty Salon",
            "type":"Services"
        }
    ],
    "sg:phone":"+1 604 858 6161",
    "sg:postcode":"V2R 3N5",
    "sg:province":"BC",
    "wof:name":"Christine's the Hair Place",
    "wof:placetype":"venue"
},
  "geometry": {"coordinates":[-121.961372,49.106174],"type":"Point"}
}