{
  "type": "Feature",
  "properties": {
    "iso:country":"CA",
    "sg:address":"825 Rue Lucien-Beaudin",
    "sg:city":"Iberville",
    "sg:classifiers":[
        {
            "category":"Professional",
            "subcategory":"Business Services",
            "type":"Services"
        }
    ],
    "sg:phone":"+1 450 347 6493",
    "sg:postcode":"J2X 5L2",
    "sg:province":"QC",
    "sg:tags":[
        "garbage",
        "collection"
    ],
    "wof:name":"Parc A Conteneurs Iberville",
    "wof:placetype":"venue"
},
  "geometry": {"coordinates":[-73.2416687012,45.3064155579],"type":"Point"}
}