{
  "type": "Feature",
  "properties": {
    "addr:full":"Campbell River BC V9W 3N7",
    "addr:postcode":"v9w 3n7",
    "iso:country":"CA",
    "sg:city":"Campbell River",
    "sg:classifiers":[
        {
            "category":"Wholesale",
            "subcategory":"Machinery & Supplies",
            "type":"Manufacturing & Wholesale Goods"
        }
    ],
    "sg:phone":"+1 250 830 1190",
    "sg:postcode":"V9W 3N7",
    "sg:province":"BC",
    "sg:tags":[
        "janitor"
    ],
    "wof:name":"Samson's Janitorial World",
    "wof:placetype":"venue"
},
  "geometry": {"coordinates":[-125.258606,50.023479],"type":"Point"}
}