{
  "type": "Feature",
  "properties": {
    "addr:full":"307 Central Ave N Swift Current SK S9H 0L5",
    "addr:housenumber":"307",
    "addr:postcode":"s9h 0l5",
    "addr:street":"Central Ave N",
    "iso:country":"CA",
    "sg:address":"307 Central Ave N",
    "sg:city":"Swift Current",
    "sg:classifiers":[
        {
            "category":"Banks & Credit Unions",
            "subcategory":"Bank",
            "type":"Services"
        }
    ],
    "sg:phone":"+1 306 773 3138",
    "sg:postcode":"S9H 0L5",
    "sg:province":"SK",
    "wof:name":"Cibc",
    "wof:placetype":"venue"
},
  "geometry": {"coordinates":[-107.799904,50.286835],"type":"Point"}
}