{
  "type": "Feature",
  "properties": {
    "addr:full":"Fairford MB R0C 0X0",
    "addr:postcode":"r0c 0x0",
    "iso:country":"CA",
    "sg:city":"Fairford",
    "sg:classifiers":[
        {
            "category":"Social Services",
            "type":"Services"
        }
    ],
    "sg:phone":"+1 204 659 5705",
    "sg:postcode":"R0C 0X0",
    "sg:province":"MB",
    "sg:tags":[
        "organization",
        "native",
        "welfare"
    ],
    "wof:name":"Pinaymootang First Nation",
    "wof:placetype":"venue"
},
  "geometry": {"coordinates":[-98.645690918,51.6094207764],"type":"Point"}
}