{
  "type": "Feature",
  "properties": {
    "addr:full":"White Rock BC V4B 2B8",
    "addr:postcode":"v4b 2b8",
    "iso:country":"CA",
    "sg:city":"White Rock",
    "sg:classifiers":[
        {
            "category":"Personal",
            "subcategory":"Beauty Salon",
            "type":"Services"
        }
    ],
    "sg:phone":"+1 604 541 8869",
    "sg:postcode":"V4B 2B8",
    "sg:province":"BC",
    "wof:name":"Making Waves Hair Studio",
    "wof:placetype":"venue"
},
  "geometry": {"coordinates":[-122.802269,49.024975],"type":"Point"}
}