{
  "type": "Feature",
  "properties": {
    "addr:full":"441 Rue Saint-Jacques N Causapscal QC G0J 1J0",
    "addr:housenumber":"441",
    "addr:postcode":"g0j 1j0",
    "addr:street":"Rue Saint-Jacques N",
    "iso:country":"CA",
    "sg:address":"441 Rue Saint-Jacques N",
    "sg:city":"Causapscal",
    "sg:classifiers":[
        {
            "category":"Shopping",
            "subcategory":"Tobacco",
            "type":"Retail Goods"
        }
    ],
    "sg:phone":"+1 418 756 3856",
    "sg:postcode":"G0J 1J0",
    "sg:province":"QC",
    "sg:tags":[
        "cigarette",
        "cigar",
        "dealer"
    ],
    "wof:name":"Depanneur Chez Yolande Inc",
    "wof:placetype":"venue"
},
  "geometry": {"coordinates":[-67.2344741821,48.3663024902],"type":"Point"}
}