{
  "type": "Feature",
  "properties": {
    "iso:country":"CA",
    "sg:city":"Falardeau",
    "sg:classifiers":[
        {
            "category":"Shopping",
            "subcategory":"Used Merchandise",
            "type":"Retail Goods"
        }
    ],
    "sg:phone":"+1 418 673 3776",
    "sg:postcode":"G0V 1C0",
    "sg:province":"QC",
    "sg:tags":[
        "clothing"
    ],
    "wof:name":"Comptoir Multiservice Inc",
    "wof:placetype":"venue"
},
  "geometry": {"coordinates":[-71.11205291749999,48.6212158203],"type":"Point"}
}