{
  "type": "Feature",
  "properties": {
    "iso:country":"CA",
    "sg:address":"12 Beech St",
    "sg:city":"Brampton",
    "sg:classifiers":[
        {
            "category":"Sports & Exercise",
            "subcategory":"Bowling",
            "type":"Entertainment"
        }
    ],
    "sg:phone":"+1 905 459 2711",
    "sg:postcode":"L6V 1V1",
    "sg:province":"ON",
    "sg:tags":[
        "center"
    ],
    "wof:name":"Brampton Bowling Lanes",
    "wof:placetype":"venue"
},
  "geometry": {"coordinates":[-79.75281524659999,43.6944961548],"type":"Point"}
}