{
  "type": "Feature",
  "properties": {
    "addr:full":"534 Lawrence Ave W # 215 North York ON M6A 1A2",
    "addr:housenumber":"534",
    "addr:postcode":"m6a 1a2",
    "addr:street":"Lawrence Ave W # 215",
    "iso:country":"CA",
    "sg:address":"534 Lawrence Ave W # 215",
    "sg:city":"North York",
    "sg:classifiers":[
        {
            "category":"Professional",
            "subcategory":"Accounting & Tax Preparation",
            "type":"Services"
        }
    ],
    "sg:phone":"+1 416 783 2222",
    "sg:postcode":"M6A 1A2",
    "sg:province":"ON",
    "sg:tags":[
        "accountant"
    ],
    "wof:name":"Avp",
    "wof:placetype":"venue"
},
  "geometry": {"coordinates":[-79.432434082,43.7187576294],"type":"Point"}
}