{
  "type": "Feature",
  "properties": {
    "addr:full":"Sainte-Anne-Des-Plaines QC J0N 1H0",
    "addr:postcode":"j0n 1h0",
    "iso:country":"CA",
    "sg:city":"Sainte-Anne-Des-Plaines",
    "sg:classifiers":[
        {
            "category":"Building & Trades",
            "subcategory":"Landscaping Services",
            "type":"Services"
        }
    ],
    "sg:phone":"+1 450 478 8784",
    "sg:postcode":"J0N 1H0",
    "sg:province":"QC",
    "sg:tags":[
        "landscape",
        "contractor"
    ],
    "wof:name":"Entreprises Stephane Simard",
    "wof:placetype":"venue"
},
  "geometry": {"coordinates":[-73.8157653809,45.7632522583],"type":"Point"}
}