{
  "type": "Feature",
  "properties": {
    "addr:full":"402 Allanburg Rd Thorold ON L2V 1A4",
    "addr:housenumber":"402",
    "addr:postcode":"l2v 1a4",
    "addr:street":"Allanburg Rd",
    "iso:country":"CA",
    "sg:address":"402 Allanburg Rd",
    "sg:city":"Thorold",
    "sg:classifiers":[
        {
            "category":"Wholesale",
            "subcategory":"Machinery & Supplies",
            "type":"Manufacturing & Wholesale Goods"
        }
    ],
    "sg:phone":"+1 905 227 3291",
    "sg:postcode":"L2V 1A4",
    "sg:province":"ON",
    "sg:tags":[
        "equipment",
        "material",
        "truck",
        "handling"
    ],
    "wof:name":"Lucas Industrial Tires",
    "wof:placetype":"venue"
},
  "geometry": {"coordinates":[-79.1993103027,43.0987052917],"type":"Point"}
}