{
  "type": "Feature",
  "properties": {
    "addr:full":"60 Rue Albert-Deblois Saint-Anselme QC G0R 2N0",
    "addr:housenumber":"60",
    "addr:postcode":"g0r 2n0",
    "addr:street":"Rue Albert-Deblois",
    "iso:country":"CA",
    "sg:address":"60 Rue Albert-Deblois",
    "sg:city":"Saint-Anselme",
    "sg:classifiers":[
        {
            "category":"Manufacturing",
            "subcategory":"Tools & Machinery",
            "type":"Manufacturing & Wholesale Goods"
        }
    ],
    "sg:phone":"+1 418 885 8214",
    "sg:postcode":"G0R 2N0",
    "sg:province":"QC",
    "sg:tags":[
        "machine",
        "shop"
    ],
    "wof:name":"Usinages G Baillargeon",
    "wof:placetype":"venue"
},
  "geometry": {"coordinates":[-70.98828125,46.6388549805],"type":"Point"}
}