{
  "type": "Feature",
  "properties": {
    "addr:full":"160 Rue Saint-Viateur E Montreal QC H2T 1A8",
    "addr:housenumber":"160",
    "addr:postcode":"h2t 1a8",
    "addr:street":"Rue Saint-Viateur E",
    "iso:country":"CA",
    "sg:address":"160 Rue Saint-Viateur E",
    "sg:city":"Montreal",
    "sg:classifiers":[
        {
            "category":"Professional",
            "subcategory":"Business Services",
            "type":"Services"
        }
    ],
    "sg:phone":"+1 514 276 8477",
    "sg:postcode":"H2T 1A8",
    "sg:province":"QC",
    "sg:tags":[
        "cloth",
        "cutting"
    ],
    "wof:name":"Jma Cutting Contractor",
    "wof:placetype":"venue"
},
  "geometry": {"coordinates":[-73.597359,45.527321],"type":"Point"}
}