{
  "type": "Feature",
  "properties": {
    "addr:full":"4 Parkes Dr Ajax ON L1S 4X1",
    "addr:housenumber":"4",
    "addr:postcode":"l1s 4x1",
    "addr:street":"Parkes Dr",
    "iso:country":"CA",
    "sg:address":"4 Parkes Dr",
    "sg:city":"Ajax",
    "sg:classifiers":[
        {
            "category":"Education",
            "subcategory":"School",
            "type":"Public Place"
        }
    ],
    "sg:phone":"+1 905 686 3014",
    "sg:postcode":"L1S 4X1",
    "sg:province":"ON",
    "wof:name":"Lakeside Public School",
    "wof:placetype":"venue"
},
  "geometry": {"coordinates":[-79.02824401860001,43.8216705322],"type":"Point"}
}