{
  "type": "Feature",
  "properties": {
    "iso:country":"CA",
    "sg:address":"2571 Dorchester Rd",
    "sg:city":"Niagara Falls",
    "sg:classifiers":[
        {
            "category":"Personal",
            "type":"Services"
        }
    ],
    "sg:phone":"+1 905 357 1017",
    "sg:postcode":"L2J 2Y9",
    "sg:province":"ON",
    "sg:tags":[
        "therapist",
        "massage"
    ],
    "wof:name":"Cupolo & Pierini",
    "wof:placetype":"venue"
},
  "geometry": {"coordinates":[-79.11288452150001,43.1349487305],"type":"Point"}
}