{
  "type": "Feature",
  "properties": {
    "addr:full":"36 Burford Delhi Townline Rd Scotland ON N0E 1R0",
    "addr:housenumber":"36",
    "addr:postcode":"n0e 1r0",
    "addr:street":"Burford Delhi Townline Rd",
    "iso:country":"CA",
    "sg:address":"36 Burford Delhi Townline Rd",
    "sg:city":"Scotland",
    "sg:classifiers":[
        {
            "category":"Retail",
            "subcategory":"Animal Services",
            "type":"Services"
        }
    ],
    "sg:phone":"+1 519 446 2995",
    "sg:postcode":"N0E 1R0",
    "sg:province":"ON",
    "sg:tags":[
        "pet",
        "boarding",
        "sitting"
    ],
    "wof:name":"Westmorland Kennels",
    "wof:placetype":"venue"
},
  "geometry": {"coordinates":[-80.3754043579,43.0257759094],"type":"Point"}
}