{
  "type": "Feature",
  "properties": {
    "addr:full":"40 Executive Crt Scarborough ON M1S 4N4",
    "addr:housenumber":"40",
    "addr:postcode":"m1s 4n4",
    "addr:street":"Executive Crt",
    "iso:country":"CA",
    "sg:address":"40 Executive Crt",
    "sg:city":"Scarborough",
    "sg:classifiers":[
        {
            "category":"Wholesale",
            "subcategory":"Machinery & Supplies",
            "type":"Manufacturing & Wholesale Goods"
        }
    ],
    "sg:phone":"+1 416 299 1220",
    "sg:postcode":"M1S 4N4",
    "sg:province":"ON",
    "sg:tags":[
        "bearing"
    ],
    "wof:name":"Skf Canada Ltd",
    "wof:placetype":"venue"
},
  "geometry": {"coordinates":[-79.23956298829999,43.7859649658],"type":"Point"}
}