{
  "type": "Feature",
  "properties": {
    "addr:full":"102 Main St W Atikokan ON P0T 1C0",
    "addr:housenumber":"102",
    "addr:postcode":"p0t 1c0",
    "addr:street":"Main St W Atikokan",
    "iso:country":"CA",
    "sg:address":"102 Main St W",
    "sg:city":"Atikokan",
    "sg:classifiers":[
        {
            "category":"Shopping",
            "subcategory":"Department Store",
            "type":"Retail Goods"
        }
    ],
    "sg:phone":"+1 807 597 6048",
    "sg:postcode":"P0T 1C0",
    "sg:province":"ON",
    "wof:name":"Saan Stores Ltd",
    "wof:placetype":"venue"
},
  "geometry": {"coordinates":[-91.62200900000001,48.757591],"type":"Point"}
}