{
  "type": "Feature",
  "properties": {
    "iso:country":"CA",
    "sg:city":"Etobicoke",
    "sg:classifiers":[
        {
            "category":"Health Services",
            "subcategory":"Doctor",
            "type":"Services"
        }
    ],
    "sg:phone":"+1 416 741 0707",
    "sg:postcode":"M9V 5G4",
    "sg:province":"ON",
    "sg:tags":[
        "physician",
        "surgeon"
    ],
    "wof:name":"Sehgal, Parmila MD",
    "wof:placetype":"venue"
},
  "geometry": {"coordinates":[-79.5993270874,43.7311019897],"type":"Point"}
}