{
  "type": "Feature",
  "properties": {
    "addr:full":"Calgary AB T1Y 3R6",
    "addr:postcode":"t1y 3r6",
    "iso:country":"CA",
    "sg:city":"Calgary",
    "sg:classifiers":[
        {
            "category":"Shopping",
            "subcategory":"Clothing, Apparel, & Fashions",
            "type":"Retail Goods"
        }
    ],
    "sg:phone":"+1 403 293 7468",
    "sg:postcode":"T1Y 3R6",
    "sg:province":"AB",
    "sg:tags":[
        "tailor"
    ],
    "wof:name":"Marie's Tailoring Shop",
    "wof:placetype":"venue"
},
  "geometry": {"coordinates":[-113.95827484100001,51.0755233765],"type":"Point"}
}