{
  "type": "Feature",
  "properties": {
    "iso:country":"CA",
    "sg:address":"402 Scissons Cres",
    "sg:city":"Saskatoon",
    "sg:classifiers":[
        {
            "category":"Building & Trades",
            "subcategory":"Cleaning & Sanitation",
            "type":"Services"
        }
    ],
    "sg:phone":"+1 306 668 0179",
    "sg:postcode":"S7S 1C1",
    "sg:province":"SK",
    "sg:tags":[
        "window"
    ],
    "wof:name":"Presto Window Cleaning",
    "wof:placetype":"venue"
},
  "geometry": {"coordinates":[-106.592697144,52.1560211182],"type":"Point"}
}