{
  "type": "Feature",
  "properties": {
    "addr:full":"Saint-Tite QC G0X 3H0",
    "addr:postcode":"g0x 3h0",
    "iso:country":"CA",
    "sg:city":"Saint-Tite",
    "sg:classifiers":[
        {
            "category":"Manufacturing",
            "subcategory":"Tools & Machinery",
            "type":"Manufacturing & Wholesale Goods"
        }
    ],
    "sg:phone":"+1 418 365 7832",
    "sg:postcode":"G0X 3H0",
    "sg:province":"QC",
    "sg:tags":[
        "machine",
        "shop"
    ],
    "wof:name":"Ateliers Saint-Tite Enr",
    "wof:placetype":"venue"
},
  "geometry": {"coordinates":[-72.5831451416,46.7380905151],"type":"Point"}
}