{
  "type": "Feature",
  "properties": {
    "iso:country":"CA",
    "sg:address":"6045 Ch Saint-Francois",
    "sg:city":"Saint-Laurent",
    "sg:classifiers":[
        {
            "category":"Shopping",
            "subcategory":"Computers & Home Electronics",
            "type":"Retail Goods"
        }
    ],
    "sg:phone":"+1 514 336 0392",
    "sg:postcode":"H4S 1B6",
    "sg:province":"QC",
    "sg:tags":[
        "equipment",
        "electronic"
    ],
    "wof:name":"Interfax Systemes Inc",
    "wof:placetype":"venue"
},
  "geometry": {"coordinates":[-73.7414779663,45.4855003357],"type":"Point"}
}