{
  "type": "Feature",
  "properties": {
    "addr:full":"106 Killarney Cres Fredericton NB E3A 8S9",
    "addr:housenumber":"106",
    "addr:postcode":"e3a 8s9",
    "addr:street":"Killarney Cres",
    "iso:country":"CA",
    "sg:address":"106 Killarney Cres",
    "sg:city":"Fredericton",
    "sg:classifiers":[
        {
            "category":"Retail",
            "subcategory":"Auto Repair",
            "type":"Services"
        }
    ],
    "sg:phone":"+1 506 459 4952",
    "sg:postcode":"E3A 8S9",
    "sg:province":"NB",
    "sg:tags":[
        "repairing",
        "automobile"
    ],
    "wof:name":"Harry Gunther's Auto Repair",
    "wof:placetype":"venue"
},
  "geometry": {"coordinates":[-66.630112,45.997719],"type":"Point"}
}