{
  "type": "Feature",
  "properties": {
    "addr:full":"Airport Rd Sioux Lookout ON P8T 1C1",
    "addr:postcode":"p8t 1c1",
    "addr:street":"Airport Rd",
    "iso:country":"CA",
    "sg:address":"Airport Rd",
    "sg:city":"Sioux Lookout",
    "sg:classifiers":[
        {
            "category":"Airline",
            "type":"Transportation"
        }
    ],
    "sg:phone":"+1 807 737 3473",
    "sg:postcode":"P8T 1C1",
    "sg:province":"ON",
    "sg:tags":[
        "company"
    ],
    "wof:name":"Bearskin Airlines",
    "wof:placetype":"venue"
},
  "geometry": {"coordinates":[-91.901718,50.115475],"type":"Point"}
}