{
  "type": "Feature",
  "properties": {
    "addr:full":"45 Overlea Blvd Toronto ON M4H 1C3",
    "addr:housenumber":"45",
    "addr:postcode":"m4h 1c3",
    "addr:street":"Overlea Blvd",
    "iso:country":"CA",
    "sg:address":"45 Overlea Blvd",
    "sg:city":"Toronto",
    "sg:classifiers":[
        {
            "category":"Shopping",
            "subcategory":"Pharmacy",
            "type":"Retail Goods"
        }
    ],
    "sg:phone":"+1 416 421 5141",
    "sg:postcode":"M4H 1C3",
    "sg:province":"ON",
    "wof:name":"Shoppers Drug Mart",
    "wof:placetype":"venue"
},
  "geometry": {"coordinates":[-79.349304,43.705124],"type":"Point"}
}