{
  "type": "Feature",
  "properties": {
    "addr:full":"4335 Steeles Ave W North York ON M3N 1V7",
    "addr:housenumber":"4335",
    "addr:postcode":"m3n 1v7",
    "addr:street":"Steeles Ave W",
    "iso:country":"CA",
    "sg:address":"4335 Steeles Ave W",
    "sg:city":"North York",
    "sg:classifiers":[
        {
            "category":"Wholesale",
            "subcategory":"Durable Goods & Equipment",
            "type":"Manufacturing & Wholesale Goods"
        }
    ],
    "sg:phone":"+1 416 667 1000",
    "sg:postcode":"M3N 1V7",
    "sg:province":"ON",
    "sg:tags":[
        "positioning",
        "global",
        "radio",
        "system",
        "communication"
    ],
    "wof:name":"Radioworld",
    "wof:placetype":"venue"
},
  "geometry": {"coordinates":[-79.5306091309,43.7734336853],"type":"Point"}
}