{
  "type": "Feature",
  "properties": {
    "addr:full":"2045 Boul Pere-Lelievre Quebec QC G1P 2W8",
    "addr:housenumber":"2045",
    "addr:postcode":"g1p 2w8",
    "addr:street":"Boul Pere-Lelievre",
    "iso:country":"CA",
    "sg:address":"2045 Boul Pere-Lelievre",
    "sg:city":"Quebec",
    "sg:classifiers":[
        {
            "category":"Restaurant",
            "type":"Food & Drink"
        }
    ],
    "sg:phone":"+1 418 686 1818",
    "sg:postcode":"G1P 2W8",
    "sg:province":"QC",
    "wof:name":"Restaurant Valentine",
    "wof:placetype":"venue"
},
  "geometry": {"coordinates":[-71.2949523926,46.8116416931],"type":"Point"}
}