{
  "type": "Feature",
  "properties": {
    "addr:full":"4955 Dundas St W Etobicoke ON M9A 1B6",
    "addr:housenumber":"4955",
    "addr:postcode":"m9a 1b6",
    "addr:street":"Dundas St W",
    "iso:country":"CA",
    "sg:address":"4955 Dundas St W",
    "sg:city":"Etobicoke",
    "sg:classifiers":[
        {
            "category":"Professional",
            "subcategory":"Computer Services",
            "type":"Services"
        }
    ],
    "sg:phone":"+1 416 234 2820",
    "sg:postcode":"M9A 1B6",
    "sg:province":"ON",
    "sg:tags":[
        "internet"
    ],
    "wof:name":"Battle Station",
    "wof:placetype":"venue"
},
  "geometry": {"coordinates":[-79.529312,43.647873],"type":"Point"}
}