{
  "type": "Feature",
  "properties": {
    "addr:full":"82 1st St NW Wadena SK S0A 4J0",
    "addr:housenumber":"82",
    "addr:postcode":"s0a 4j0",
    "addr:street":"1St St Nw",
    "iso:country":"CA",
    "sg:address":"82 1st St NW",
    "sg:city":"Wadena",
    "sg:classifiers":[
        {
            "category":"Manufacturing",
            "subcategory":"Tools & Machinery",
            "type":"Manufacturing & Wholesale Goods"
        }
    ],
    "sg:phone":"+1 306 338 2480",
    "sg:postcode":"S0A 4J0",
    "sg:province":"SK",
    "sg:tags":[
        "pump"
    ],
    "wof:name":"Lloyd's Manufacturing Ltd",
    "wof:placetype":"venue"
},
  "geometry": {"coordinates":[-103.803031921,51.9453659058],"type":"Point"}
}