{
  "type": "Feature",
  "properties": {
    "iso:country":"CA",
    "sg:city":"Cayuga",
    "sg:classifiers":[
        {
            "category":"Restaurant",
            "type":"Food & Drink"
        }
    ],
    "sg:phone":"+1 905 772 1088",
    "sg:postcode":"N0A 1E0",
    "sg:province":"ON",
    "wof:name":"Country Charm",
    "wof:placetype":"venue"
},
  "geometry": {"coordinates":[-79.835899353,42.9552650452],"type":"Point"}
}