{
  "type": "Feature",
  "properties": {
    "addr:full":"401 Rue Des Erables Lachine QC H8S 2P8",
    "addr:housenumber":"401",
    "addr:postcode":"h8s 2p8",
    "addr:street":"Rue Des Erables",
    "iso:country":"CA",
    "sg:address":"401 Rue Des Erables",
    "sg:city":"Lachine",
    "sg:classifiers":[
        {
            "category":"Manufacturing",
            "subcategory":"Printing",
            "type":"Manufacturing & Wholesale Goods"
        }
    ],
    "sg:phone":"+1 514 364 6090",
    "sg:postcode":"H8S 2P8",
    "sg:province":"QC",
    "sg:tags":[
        "publisher",
        "art",
        "dealer"
    ],
    "wof:name":"Artistica Inc",
    "wof:placetype":"venue"
},
  "geometry": {"coordinates":[-73.65362500000001,45.442657],"type":"Point"}
}