{
  "type": "Feature",
  "properties": {
    "addr:full":"1279 Rue DE LA Sapiniere Cap-Rouge QC G1Y 1A7",
    "addr:housenumber":"1279",
    "addr:postcode":"g1y 1a7",
    "addr:street":"Rue De La Sapiniere",
    "iso:country":"CA",
    "sg:address":"1279 Rue DE LA Sapiniere",
    "sg:city":"Cap-Rouge",
    "sg:classifiers":[
        {
            "category":"Professional",
            "type":"Services"
        }
    ],
    "sg:phone":"+1 418 652 1252",
    "sg:postcode":"G1Y 1A7",
    "sg:province":"QC",
    "sg:tags":[
        "arranger",
        "music",
        "composer"
    ],
    "wof:name":"Midi-Plus Consultants Inc",
    "wof:placetype":"venue"
},
  "geometry": {"coordinates":[-71.34405517579999,46.7583618164],"type":"Point"}
}