{
  "type": "Feature",
  "properties": {
    "addr:full":"1080 Kingston Rd Scarborough ON M1N 1N5",
    "addr:housenumber":"1080",
    "addr:postcode":"m1n 1n5",
    "addr:street":"Kingston Rd",
    "iso:country":"CA",
    "sg:address":"1080 Kingston Rd",
    "sg:city":"Scarborough",
    "sg:classifiers":[
        {
            "category":"Utilities",
            "subcategory":"Cable",
            "type":"Services"
        }
    ],
    "sg:phone":"+1 416 691 1171",
    "sg:postcode":"M1N 1N5",
    "sg:province":"ON",
    "sg:tags":[
        "television"
    ],
    "wof:name":"Cantel Inc",
    "wof:placetype":"venue"
},
  "geometry": {"coordinates":[-79.28290557859999,43.6811561584],"type":"Point"}
}