{
  "type": "Feature",
  "properties": {
    "addr:full":"390 Queen St Blyth ON N0M 1H0",
    "addr:housenumber":"390",
    "addr:postcode":"n0m 1h0",
    "addr:street":"Queen St",
    "iso:country":"CA",
    "sg:address":"390 Queen St",
    "sg:city":"Blyth",
    "sg:classifiers":[
        {
            "category":"Home & Garden",
            "subcategory":"Building Materials",
            "type":"Retail Goods"
        }
    ],
    "sg:phone":"+1 519 523 4840",
    "sg:postcode":"N0M 1H0",
    "sg:province":"ON",
    "sg:tags":[
        "paint"
    ],
    "wof:name":"Blyth Decor Shoppe",
    "wof:placetype":"venue"
},
  "geometry": {"coordinates":[-81.429733,43.735695],"type":"Point"}
}