{
  "type": "Feature",
  "properties": {
    "addr:full":"941 Pandora Ave Victoria BC V8V 3P4",
    "addr:housenumber":"941",
    "addr:postcode":"v8v 3p4",
    "addr:street":"Pandora Ave",
    "iso:country":"CA",
    "sg:address":"941 Pandora Ave",
    "sg:city":"Victoria",
    "sg:classifiers":[
        {
            "category":"Social Services",
            "type":"Services"
        }
    ],
    "sg:phone":"+1 250 388 5505",
    "sg:postcode":"V8V 3P4",
    "sg:province":"BC",
    "sg:tags":[
        "organization",
        "welfare"
    ],
    "wof:name":"St John Ambulance",
    "wof:placetype":"venue"
},
  "geometry": {"coordinates":[-123.35763549799999,48.4271316528],"type":"Point"}
}