{
  "type": "Feature",
  "properties": {
    "addr:full":"278 Rang Saint-Jean-Baptiste Amqui QC G5J 3R7",
    "addr:housenumber":"278",
    "addr:postcode":"g5j 3r7",
    "addr:street":"Rang Saint-Jean-Baptiste",
    "iso:country":"CA",
    "sg:address":"278 Rang Saint-Jean-Baptiste",
    "sg:city":"Amqui",
    "sg:classifiers":[
        {
            "category":"Organizations",
            "subcategory":"Professional Association",
            "type":"Services"
        }
    ],
    "sg:phone":"+1 418 629 5867",
    "sg:postcode":"G5J 3R7",
    "sg:province":"QC",
    "wof:name":"Aph DE LA Vallee",
    "wof:placetype":"venue"
},
  "geometry": {"coordinates":[-67.43743133540001,48.4787139893],"type":"Point"}
}