{
  "type": "Feature",
  "properties": {
    "addr:full":"189 Delrex Blvd Georgetown ON L7G 4E4",
    "addr:housenumber":"189",
    "addr:postcode":"l7g 4e4",
    "addr:street":"Delrex Blvd",
    "iso:country":"CA",
    "sg:address":"189 Delrex Blvd",
    "sg:city":"Georgetown",
    "sg:classifiers":[
        {
            "category":"Local Transit",
            "type":"Transportation"
        }
    ],
    "sg:phone":"+1 905 873 4770",
    "sg:postcode":"L7G 4E4",
    "sg:province":"ON",
    "sg:tags":[
        "limousine"
    ],
    "wof:name":"Regal Limousine Svc Inc",
    "wof:placetype":"venue"
},
  "geometry": {"coordinates":[-79.902672,43.643192],"type":"Point"}
}