{
  "type": "Feature",
  "properties": {
    "addr:full":"10404 87 Ave Fort St John BC V1J 5K7",
    "addr:housenumber":"10404",
    "addr:postcode":"v1j 5k7",
    "addr:street":"87 Ave",
    "iso:country":"CA",
    "sg:address":"10404 87 Ave",
    "sg:city":"Fort St John",
    "sg:classifiers":[
        {
            "category":"Local Transit",
            "type":"Transportation"
        }
    ],
    "sg:phone":"+1 250 787 9373",
    "sg:postcode":"V1J 5K7",
    "sg:province":"BC",
    "sg:tags":[
        "bus",
        "line"
    ],
    "wof:name":"Nordbo Services Ltd",
    "wof:placetype":"venue"
},
  "geometry": {"coordinates":[-120.854141235,56.2336616516],"type":"Point"}
}