{
  "type": "Feature",
  "properties": {
    "addr:full":"Sherwood Park AB T8A 3X3",
    "addr:postcode":"t8a 3x3",
    "iso:country":"CA",
    "sg:city":"Sherwood Park",
    "sg:classifiers":[
        {
            "category":"Social Services",
            "subcategory":"Child Care",
            "type":"Services"
        }
    ],
    "sg:phone":"+1 780 464 1440",
    "sg:postcode":"T8A 3X3",
    "sg:province":"AB",
    "wof:name":"Town & Country Child Care Ctr",
    "wof:placetype":"venue"
},
  "geometry": {"coordinates":[-113.295418,53.52747],"type":"Point"}
}