{
  "type": "Feature",
  "properties": {
    "addr:full":"21 2E Av Forestville QC G0T 1E0",
    "addr:housenumber":"21",
    "addr:postcode":"g0t 1e0",
    "addr:street":"2E Av",
    "iso:country":"CA",
    "sg:address":"21 2E Av",
    "sg:city":"Forestville",
    "sg:classifiers":[
        {
            "category":"Sports & Exercise",
            "subcategory":"Gym",
            "type":"Entertainment"
        }
    ],
    "sg:phone":"+1 418 587 4333",
    "sg:postcode":"G0T 1E0",
    "sg:province":"QC",
    "sg:tags":[
        "club",
        "health",
        "studio",
        "gymnasium"
    ],
    "wof:name":"Gym Pro Forme",
    "wof:placetype":"venue"
},
  "geometry": {"coordinates":[-69.0796966553,48.7387504578],"type":"Point"}
}