{
  "type": "Feature",
  "properties": {
    "addr:full":"26 Oakland Blvd Elliot Lake ON P5A 2T1",
    "addr:housenumber":"26",
    "addr:postcode":"p5a 2t1",
    "addr:street":"Oakland Blvd",
    "iso:country":"CA",
    "sg:address":"26 Oakland Blvd",
    "sg:city":"Elliot Lake",
    "sg:classifiers":[
        {
            "category":"Organizations",
            "subcategory":"Professional Association",
            "type":"Services"
        }
    ],
    "sg:phone":"+1 705 848 7938",
    "sg:postcode":"P5A 2T1",
    "sg:province":"ON",
    "wof:name":"Loyal Order of Moose Hall",
    "wof:placetype":"venue"
},
  "geometry": {"coordinates":[-82.63768,46.381428],"type":"Point"}
}