{
  "type": "Feature",
  "properties": {
    "addr:full":"2000 Rue Jolibois Saint-Hyacinthe QC J2T 1J3",
    "addr:housenumber":"2000",
    "addr:postcode":"j2t 1j3",
    "addr:street":"Rue Jolibois",
    "iso:country":"CA",
    "sg:address":"2000 Rue Jolibois",
    "sg:city":"Saint-Hyacinthe",
    "sg:classifiers":[
        {
            "category":"Organizations",
            "subcategory":"Religious Organization",
            "type":"Services"
        }
    ],
    "sg:phone":"+1 450 774 3945",
    "sg:postcode":"J2T 1J3",
    "sg:province":"QC",
    "sg:tags":[
        "home",
        "retirement",
        "community",
        "retreat",
        "house"
    ],
    "wof:name":"Residence Jolibois",
    "wof:placetype":"venue"
},
  "geometry": {"coordinates":[-72.926940918,45.6340751648],"type":"Point"}
}