{
  "type": "Feature",
  "properties": {
    "addr:full":"Edmonton AB T5J 3P4",
    "addr:postcode":"t5j 3p4",
    "iso:country":"CA",
    "sg:city":"Edmonton",
    "sg:classifiers":[
        {
            "category":"Professional",
            "subcategory":"Employment Agencies",
            "type":"Services"
        }
    ],
    "sg:phone":"+1 780 421 1811",
    "sg:postcode":"T5J 3P4",
    "sg:province":"AB",
    "sg:tags":[
        "opportunity"
    ],
    "wof:name":"Personnel Department",
    "wof:placetype":"venue"
},
  "geometry": {"coordinates":[-113.493850708,53.5448875427],"type":"Point"}
}