{
  "type": "Feature",
  "properties": {
    "addr:full":"16686 113 Ave NW Edmonton AB T5M 2X3",
    "addr:housenumber":"16686",
    "addr:postcode":"t5m 2x3",
    "addr:street":"113 Ave Nw",
    "iso:country":"CA",
    "sg:address":"16686 113 Ave NW",
    "sg:city":"Edmonton",
    "sg:classifiers":[
        {
            "category":"Building & Trades",
            "subcategory":"Plumbing",
            "type":"Services"
        }
    ],
    "sg:phone":"+1 780 447 1133",
    "sg:postcode":"T5M 2X3",
    "sg:province":"AB",
    "sg:tags":[
        "fireplace",
        "cleaning",
        "chimney"
    ],
    "wof:name":"Don's Power Vac",
    "wof:placetype":"venue"
},
  "geometry": {"coordinates":[-113.608757,53.561481],"type":"Point"}
}