{
  "type": "Feature",
  "properties": {
    "addr:full":"67 Highway 97A Vernon BC V1B 3S1",
    "addr:housenumber":"67",
    "addr:postcode":"v1b 3s1",
    "addr:street":"Highway 97A",
    "iso:country":"CA",
    "sg:address":"67 Highway 97A",
    "sg:city":"Vernon",
    "sg:classifiers":[
        {
            "category":"Manufacturing",
            "subcategory":"Glass & Minerals",
            "type":"Manufacturing & Wholesale Goods"
        }
    ],
    "sg:phone":"+1 250 558 3946",
    "sg:postcode":"V1B 3S1",
    "sg:province":"BC",
    "sg:tags":[
        "pipe",
        "drain"
    ],
    "wof:name":"Polytubes Inc",
    "wof:placetype":"venue"
},
  "geometry": {"coordinates":[-119.273803711,50.2656860352],"type":"Point"}
}