{
  "type": "Feature",
  "properties": {
    "addr:full":"Brandon MB R7A 0P6",
    "addr:postcode":"r7a 0p6",
    "iso:country":"CA",
    "sg:city":"Brandon",
    "sg:classifiers":[
        {
            "category":"Insurance",
            "subcategory":"Insurance Agent",
            "type":"Services"
        }
    ],
    "sg:phone":"+1 204 728 5433",
    "sg:postcode":"R7A 0P6",
    "sg:province":"MB",
    "wof:name":"Advanced Financial Svc",
    "wof:placetype":"venue"
},
  "geometry": {"coordinates":[-99.95066799999999,49.84671],"type":"Point"}
}