{
  "type": "Feature",
  "properties": {
    "iso:country":"CA",
    "sg:address":"812 Av Des Cedres",
    "sg:city":"Shawinigan",
    "sg:classifiers":[
        {
            "category":"Professional",
            "subcategory":"Management & Consulting",
            "type":"Services"
        }
    ],
    "sg:phone":"+1 819 537 5107",
    "sg:postcode":"G9N 1P2",
    "sg:province":"QC",
    "sg:tags":[
        "development",
        "economic",
        "agency"
    ],
    "wof:name":"Sadc Ctr DE LA Mauricie",
    "wof:placetype":"venue"
},
  "geometry": {"coordinates":[-72.7461242676,46.5430030823],"type":"Point"}
}