{
  "type": "Feature",
  "properties": {
    "addr:full":"Papineauville QC J0V 1R0",
    "addr:postcode":"j0v 1r0",
    "iso:country":"CA",
    "sg:city":"Papineauville",
    "sg:classifiers":[
        {
            "category":"Government",
            "subcategory":"Office",
            "type":"Public Place"
        }
    ],
    "sg:phone":"+1 819 427 8549",
    "sg:postcode":"J0V 1R0",
    "sg:province":"QC",
    "sg:tags":[
        "village"
    ],
    "wof:name":"Plaisance Usine D'Epuration",
    "wof:placetype":"venue"
},
  "geometry": {"coordinates":[-75.0175857544,45.6172332764],"type":"Point"}
}