{
  "type": "Feature",
  "properties": {
    "addr:full":"PO Box 116 Keremeos BC V0X 1N0",
    "addr:housenumber":"po",
    "addr:postcode":"v0x 1n0",
    "addr:street":"Box 116",
    "iso:country":"CA",
    "sg:address":"PO Box 116",
    "sg:city":"Keremeos",
    "sg:classifiers":[
        {
            "category":"Organizations",
            "subcategory":"Religious Organization",
            "type":"Services"
        }
    ],
    "sg:phone":"+1 250 499 2511",
    "sg:postcode":"V0X 1N0",
    "sg:province":"BC",
    "sg:tags":[
        "church"
    ],
    "wof:name":"Similkameen Mennonite Brethren",
    "wof:placetype":"venue"
},
  "geometry": {"coordinates":[-119.824127,49.205139],"type":"Point"}
}