{
  "type": "Feature",
  "properties": {
    "addr:full":"Maple Ridge BC V2X 2V5",
    "addr:postcode":"v2x 2v5",
    "iso:country":"CA",
    "sg:city":"Maple Ridge",
    "sg:classifiers":[
        {
            "category":"Shopping",
            "type":"Retail Goods"
        }
    ],
    "sg:phone":"+1 604 467 2014",
    "sg:postcode":"V2X 2V5",
    "sg:province":"BC",
    "sg:tags":[
        "equipment",
        "wine",
        "supply"
    ],
    "wof:name":"Mixer Shop",
    "wof:placetype":"venue"
},
  "geometry": {"coordinates":[-122.59335299999999,49.217049],"type":"Point"}
}