{
  "type": "Feature",
  "properties": {
    "iso:country":"CA",
    "sg:address":"1450 Hopkins St",
    "sg:city":"Whitby",
    "sg:classifiers":[
        {
            "category":"Personal",
            "type":"Services"
        }
    ],
    "sg:phone":"+1 905 430 5888",
    "sg:postcode":"L1N 2C3",
    "sg:province":"ON",
    "sg:tags":[
        "program",
        "physical",
        "exercise",
        "fitness"
    ],
    "wof:name":"Durham Women's Fitness",
    "wof:placetype":"venue"
},
  "geometry": {"coordinates":[-78.9169082642,43.8709487915],"type":"Point"}
}