{
  "type": "Feature",
  "properties": {
    "iso:country":"CA",
    "sg:address":"15376 Niagara Parkway Rd",
    "sg:city":"Niagara on the Lake",
    "sg:classifiers":[
        {
            "category":"Manufacturing",
            "subcategory":"Food",
            "type":"Manufacturing & Wholesale Goods"
        }
    ],
    "sg:phone":"+1 905 262 0636",
    "sg:postcode":"L0S 1J0",
    "sg:province":"ON",
    "sg:tags":[
        "winery"
    ],
    "wof:name":"Riverview Cellars Winery",
    "wof:placetype":"venue"
},
  "geometry": {"coordinates":[-79.05950900000001,43.206169],"type":"Point"}
}