{
  "type": "Feature",
  "properties": {
    "addr:full":"Nanaimo BC V9V 1N1",
    "addr:postcode":"v9v 1n1",
    "iso:country":"CA",
    "sg:city":"Nanaimo",
    "sg:classifiers":[
        {
            "category":"Real Estate",
            "subcategory":"Real Estate Agent",
            "type":"Services"
        }
    ],
    "sg:phone":"+1 250 390 1215",
    "sg:postcode":"V9V 1N1",
    "sg:province":"BC",
    "sg:tags":[
        "management"
    ],
    "wof:name":"Westcoast Strata Mgmt Svc",
    "wof:placetype":"venue"
},
  "geometry": {"coordinates":[-124.042908,49.235367],"type":"Point"}
}