{
  "type": "Feature",
  "properties": {
    "iso:country":"CA",
    "sg:address":"2744 Rue Mousseau",
    "sg:city":"Montreal",
    "sg:classifiers":[
        {
            "category":"Building & Trades",
            "subcategory":"Construction",
            "type":"Services"
        }
    ],
    "sg:phone":"+1 514 354 4901",
    "sg:postcode":"H1L 4V9",
    "sg:province":"QC",
    "sg:tags":[
        "woodworker"
    ],
    "wof:name":"Arsenault Pierre Enr",
    "wof:placetype":"venue"
},
  "geometry": {"coordinates":[-73.522514,45.602947],"type":"Point"}
}