{
  "type": "Feature",
  "properties": {
    "iso:country":"CA",
    "sg:address":"3602 Rue Wellington",
    "sg:city":"Verdun",
    "sg:classifiers":[
        {
            "category":"Manufacturing",
            "subcategory":"Printing",
            "type":"Manufacturing & Wholesale Goods"
        }
    ],
    "sg:phone":"+1 514 769 2310",
    "sg:postcode":"H4G 1T6",
    "sg:province":"QC",
    "sg:tags":[
        "printer"
    ],
    "wof:name":"Imprimerie Miracle Inc",
    "wof:placetype":"venue"
},
  "geometry": {"coordinates":[-73.5660705566,45.4678344727],"type":"Point"}
}