{
  "type": "Feature",
  "properties": {
    "addr:full":"380 Railway Southampton ON N0H 2L0",
    "addr:housenumber":"380",
    "addr:postcode":"n0h 2l0",
    "addr:street":"Railway",
    "iso:country":"CA",
    "sg:address":"380 Railway",
    "sg:city":"Southampton",
    "sg:classifiers":[
        {
            "category":"Home & Garden",
            "subcategory":"Furniture",
            "type":"Retail Goods"
        }
    ],
    "sg:phone":"+1 519 797 5522",
    "sg:postcode":"N0H 2L0",
    "sg:province":"ON",
    "wof:name":"Galbraith's Used Furniture",
    "wof:placetype":"venue"
},
  "geometry": {"coordinates":[-81.373550415,44.481048584],"type":"Point"}
}