{
  "type": "Feature",
  "properties": {
    "iso:country":"CA",
    "sg:address":"201 Queens Ave",
    "sg:city":"London",
    "sg:classifiers":[
        {
            "category":"Shopping",
            "type":"Retail Goods"
        }
    ],
    "sg:phone":"+1 519 672 7770",
    "sg:postcode":"N6A 1J1",
    "sg:province":"ON",
    "sg:tags":[
        "art",
        "gallery",
        "dealer"
    ],
    "wof:name":"Innuit Gallery",
    "wof:placetype":"venue"
},
  "geometry": {"coordinates":[-81.248955,42.985222],"type":"Point"}
}