{
  "type": "Feature",
  "properties": {
    "addr:full":"38 Station Rd Great Village NS B0M 1L0",
    "addr:housenumber":"38",
    "addr:postcode":"b0m 1l0",
    "addr:street":"Station Rd",
    "iso:country":"CA",
    "sg:address":"38 Station Rd",
    "sg:city":"Great Village",
    "sg:classifiers":[
        {
            "category":"Organizations",
            "subcategory":"Religious Organization",
            "type":"Services"
        }
    ],
    "sg:phone":"+1 902 668 2398",
    "sg:postcode":"B0M 1L0",
    "sg:province":"NS",
    "sg:tags":[
        "church"
    ],
    "wof:name":"Faith Baptist Church",
    "wof:placetype":"venue"
},
  "geometry": {"coordinates":[-63.5978889465,45.4154624939],"type":"Point"}
}