{
  "type": "Feature",
  "properties": {
    "addr:full":"979 Josephine Rd Brentwood Bay BC V8M 1B2",
    "addr:housenumber":"979",
    "addr:postcode":"v8m 1b2",
    "addr:street":"Josephine Rd",
    "iso:country":"CA",
    "sg:address":"979 Josephine Rd",
    "sg:city":"Brentwood Bay",
    "sg:classifiers":[
        {
            "category":"Building & Trades",
            "subcategory":"Cleaning & Sanitation",
            "type":"Services"
        }
    ],
    "sg:phone":"+1 250 652 2162",
    "sg:postcode":"V8M 1B2",
    "sg:province":"BC",
    "sg:tags":[
        "masonry",
        "fireplace",
        "chimney",
        "contractor"
    ],
    "wof:name":"Jet-Vac Ltd",
    "wof:placetype":"venue"
},
  "geometry": {"coordinates":[-123.45863342299999,48.5709381104],"type":"Point"}
}