{
  "type": "Feature",
  "properties": {
    "iso:country":"CA",
    "sg:city":"Newmarket",
    "sg:classifiers":[
        {
            "category":"Social Services",
            "subcategory":"Child Care",
            "type":"Services"
        }
    ],
    "sg:phone":"+1 905 853 0754",
    "sg:postcode":"L3Y 7R8",
    "sg:province":"ON",
    "sg:tags":[
        "organization",
        "welfare"
    ],
    "wof:name":"Ontario Early Years Centre",
    "wof:placetype":"venue"
},
  "geometry": {"coordinates":[-79.479408,44.050003],"type":"Point"}
}