{
  "type": "Feature",
  "properties": {
    "addr:full":"1067 Ontario St Stratford ON N5A 6W6",
    "addr:housenumber":"1067",
    "addr:postcode":"n5a 6w6",
    "addr:street":"Ontario St",
    "iso:country":"CA",
    "sg:address":"1067 Ontario St",
    "sg:city":"Stratford",
    "sg:classifiers":[
        {
            "category":"Shopping",
            "subcategory":"Jewelry",
            "type":"Retail Goods"
        }
    ],
    "sg:phone":"+1 519 271 4159",
    "sg:postcode":"N5A 6W6",
    "sg:province":"ON",
    "sg:tags":[
        "accessory"
    ],
    "wof:name":"Ardene",
    "wof:placetype":"venue"
},
  "geometry": {"coordinates":[-80.94510699999999,43.370636],"type":"Point"}
}