{
  "type": "Feature",
  "properties": {
    "addr:full":"9 Rue William Shannon QC G0A 4N0",
    "addr:housenumber":"9",
    "addr:postcode":"g0a 4n0",
    "addr:street":"Rue William",
    "iso:country":"CA",
    "sg:address":"9 Rue William",
    "sg:city":"Shannon",
    "sg:classifiers":[
        {
            "category":"Wholesale",
            "subcategory":"Machinery & Supplies",
            "type":"Manufacturing & Wholesale Goods"
        }
    ],
    "sg:phone":"+1 418 844 3519",
    "sg:postcode":"G0A 4N0",
    "sg:province":"QC",
    "sg:tags":[
        "compressor",
        "gas"
    ],
    "wof:name":"Pjc Inc",
    "wof:placetype":"venue"
},
  "geometry": {"coordinates":[-71.534576,46.907124],"type":"Point"}
}