{
  "type": "Feature",
  "properties": {
    "addr:full":"21 DE L'Eglise Matapedia QC G0J 1V0",
    "addr:postcode":"g0j 1v0",
    "addr:street":"21 De L'Eglise Matapedia",
    "iso:country":"CA",
    "sg:address":"21 DE L'Eglise",
    "sg:city":"Matapedia",
    "sg:classifiers":[
        {
            "category":"Food & Beverages",
            "subcategory":"Groceries & Convenience Stores",
            "type":"Retail Goods"
        }
    ],
    "sg:phone":"+1 418 865 2915",
    "sg:postcode":"G0J 1V0",
    "sg:province":"QC",
    "sg:tags":[
        "grocer"
    ],
    "wof:name":"Epicerie Bujold Enr",
    "wof:placetype":"venue"
},
  "geometry": {"coordinates":[-66.955421,47.97522],"type":"Point"}
}