{
  "type": "Feature",
  "properties": {
    "addr:full":"Leamington ON N8H 1N8",
    "addr:postcode":"n8h 1n8",
    "iso:country":"CA",
    "sg:city":"Leamington",
    "sg:classifiers":[
        {
            "category":"Retail",
            "subcategory":"Car Wash",
            "type":"Services"
        }
    ],
    "sg:phone":"+1 519 322 1714",
    "sg:postcode":"N8H 1N8",
    "sg:province":"ON",
    "sg:tags":[
        "polishing",
        "automobile",
        "washing",
        "detail",
        "clean"
    ],
    "wof:name":"Dean's Auto Shine",
    "wof:placetype":"venue"
},
  "geometry": {"coordinates":[-82.618134,42.048775],"type":"Point"}
}