{
  "type": "Feature",
  "properties": {
    "iso:country":"CA",
    "sg:city":"Vancouver",
    "sg:classifiers":[
        {
            "category":"Shopping",
            "subcategory":"Computers & Home Electronics",
            "type":"Retail Goods"
        }
    ],
    "sg:phone":"+1 604 685 5381",
    "sg:postcode":"V6Z 1L3",
    "sg:province":"BC",
    "sg:tags":[
        "high",
        "television",
        "stereophonic",
        "fidelity"
    ],
    "wof:name":"Sony Store",
    "wof:placetype":"venue"
},
  "geometry": {"coordinates":[-123.122116089,49.2800674438],"type":"Point"}
}