{
  "type": "Feature",
  "properties": {
    "iso:country":"CA",
    "sg:city":"Calgary",
    "sg:classifiers":[
        {
            "category":"Health Services",
            "subcategory":"Doctor",
            "type":"Services"
        }
    ],
    "sg:phone":"+1 403 640 4000",
    "sg:postcode":"T2W 1E8",
    "sg:province":"AB",
    "sg:tags":[
        "dentist"
    ],
    "wof:name":"Apple Dental Group",
    "wof:placetype":"venue"
},
  "geometry": {"coordinates":[-114.084953308,50.962436676],"type":"Point"}
}