{
  "type": "Feature",
  "properties": {
    "addr:full":"1251 12 Ave SW Calgary AB T3C 3S7",
    "addr:housenumber":"1251",
    "addr:postcode":"t3c 3s7",
    "addr:street":"12 Ave Sw",
    "iso:country":"CA",
    "sg:address":"1251 12 Ave SW",
    "sg:city":"Calgary",
    "sg:classifiers":[
        {
            "category":"Travel",
            "subcategory":"Travel Agent",
            "type":"Entertainment"
        }
    ],
    "sg:phone":"+1 403 245 0003",
    "sg:postcode":"T3C 3S7",
    "sg:province":"AB",
    "sg:tags":[
        "agency",
        "bureau",
        "cruise"
    ],
    "wof:name":"Cruise Holidays",
    "wof:placetype":"venue"
},
  "geometry": {"coordinates":[-114.090157,51.042042],"type":"Point"}
}