{
  "type": "Feature",
  "properties": {
    "addr:full":"167 2Nnd Ave S #B Saskatoon SK S7K 1K6",
    "addr:housenumber":"167",
    "addr:postcode":"s7k 1k6",
    "addr:street":"2Nnd Ave S # B",
    "iso:country":"CA",
    "sg:address":"167 2Nnd Ave S #B",
    "sg:city":"Saskatoon",
    "sg:classifiers":[
        {
            "category":"Shopping",
            "subcategory":"Jewelry",
            "type":"Retail Goods"
        }
    ],
    "sg:phone":"+1 306 665 8665",
    "sg:postcode":"S7K 1K6",
    "sg:province":"SK",
    "sg:tags":[
        "jeweler"
    ],
    "wof:name":"Roset By Reid",
    "wof:placetype":"venue"
},
  "geometry": {"coordinates":[-106.65933200000001,52.130508],"type":"Point"}
}