{
  "type": "Feature",
  "properties": {
    "addr:full":"1957 Montee Harwood Saint-Lazare QC J7T 2N3",
    "addr:housenumber":"1957",
    "addr:postcode":"j7t 2n3",
    "addr:street":"Montee Harwood",
    "iso:country":"CA",
    "sg:address":"1957 Montee Harwood",
    "sg:city":"Saint-Lazare",
    "sg:classifiers":[
        {
            "category":"Mining & Drilling",
            "type":"Manufacturing & Wholesale Goods"
        }
    ],
    "sg:phone":"+1 450 458 7865",
    "sg:postcode":"J7T 2N3",
    "sg:province":"QC",
    "sg:tags":[
        "company"
    ],
    "wof:name":"Raudin Exploration Inc",
    "wof:placetype":"venue"
},
  "geometry": {"coordinates":[-74.212463,45.420841],"type":"Point"}
}