{
  "type": "Feature",
  "properties": {
    "iso:country":"CA",
    "sg:address":"6135 Boul Des Laurentides",
    "sg:city":"Laval",
    "sg:classifiers":[
        {
            "category":"Social Services",
            "type":"Services"
        }
    ],
    "sg:phone":"+1 450 628 3246",
    "sg:postcode":"H7H 2V3",
    "sg:province":"QC",
    "sg:tags":[
        "organization",
        "association",
        "welfare"
    ],
    "wof:name":"Relais Familial D'Auteuil",
    "wof:placetype":"venue"
},
  "geometry": {"coordinates":[-73.75390625,45.6358833313],"type":"Point"}
}