{
  "type": "Feature",
  "properties": {
    "addr:full":"2577 Rue DE Miniac Saint-Laurent QC H4S 1E5",
    "addr:housenumber":"2577",
    "addr:postcode":"h4s 1e5",
    "addr:street":"Rue De Miniac",
    "iso:country":"CA",
    "sg:address":"2577 Rue DE Miniac",
    "sg:city":"Saint-Laurent",
    "sg:classifiers":[
        {
            "category":"Wholesale",
            "subcategory":"Hardware",
            "type":"Manufacturing & Wholesale Goods"
        }
    ],
    "sg:phone":"+1 514 335 3595",
    "sg:postcode":"H4S 1E5",
    "sg:province":"QC",
    "sg:tags":[
        "equipment",
        "energy",
        "solar"
    ],
    "wof:name":"Heliocol Canada",
    "wof:placetype":"venue"
},
  "geometry": {"coordinates":[-73.7460861206,45.4925460815],"type":"Point"}
}