{
  "type": "Feature",
  "properties": {
    "addr:full":"5010 76 Ave NW Edmonton AB T6B 0A6",
    "addr:housenumber":"5010",
    "addr:postcode":"t6b 0a6",
    "addr:street":"76 Ave Nw",
    "iso:country":"CA",
    "sg:address":"5010 76 Ave NW",
    "sg:city":"Edmonton",
    "sg:classifiers":[
        {
            "category":"Utilities",
            "subcategory":"Fuel Oil & Lpg",
            "type":"Services"
        }
    ],
    "sg:phone":"+1 780 466 8410",
    "sg:postcode":"T6B 0A6",
    "sg:province":"AB",
    "sg:tags":[
        "propane",
        "automobile",
        "parts",
        "gas",
        "supply"
    ],
    "wof:name":"Westway Propane/Automotive",
    "wof:placetype":"venue"
},
  "geometry": {"coordinates":[-113.419235,53.512569],"type":"Point"}
}