{
  "type": "Feature",
  "properties": {
    "addr:full":"112 French St Ladysmith BC V9G 1B5",
    "addr:housenumber":"112",
    "addr:postcode":"v9g 1b5",
    "addr:street":"French St",
    "iso:country":"CA",
    "sg:address":"112 French St",
    "sg:city":"Ladysmith",
    "sg:classifiers":[
        {
            "category":"Retail",
            "subcategory":"Funeral Services",
            "type":"Services"
        }
    ],
    "sg:phone":"+1 250 245 5553",
    "sg:postcode":"V9G 1B5",
    "sg:province":"BC",
    "sg:tags":[
        "director"
    ],
    "wof:name":"Telfords Ladysmith Chemainus",
    "wof:placetype":"venue"
},
  "geometry": {"coordinates":[-123.82209,48.99548],"type":"Point"}
}