{
  "type": "Feature",
  "properties": {
    "addr:full":"468 Boul Salaberry Mercier QC J6R 2L1",
    "addr:housenumber":"468",
    "addr:postcode":"j6r 2l1",
    "addr:street":"Boul Salaberry",
    "iso:country":"CA",
    "sg:address":"468 Boul Salaberry",
    "sg:city":"Mercier",
    "sg:classifiers":[
        {
            "category":"Building & Trades",
            "subcategory":"Construction",
            "type":"Services"
        }
    ],
    "sg:phone":"+1 450 691 0738",
    "sg:postcode":"J6R 2L1",
    "sg:province":"QC",
    "sg:tags":[
        "masonry",
        "contractor"
    ],
    "wof:name":"Maconneries Levesque Inc",
    "wof:placetype":"venue"
},
  "geometry": {"coordinates":[-73.7588195801,45.3353118896],"type":"Point"}
}