{
  "type": "Feature",
  "properties": {
    "addr:full":"3330 Keele St North York ON M3J 1L5",
    "addr:housenumber":"3330",
    "addr:postcode":"m3j 1l5",
    "addr:street":"Keele St",
    "iso:country":"CA",
    "sg:address":"3330 Keele St",
    "sg:city":"North York",
    "sg:classifiers":[
        {
            "category":"Autos & Motor Vehicles",
            "subcategory":"Fuel & Gas Station",
            "type":"Retail Goods"
        }
    ],
    "sg:phone":"+1 416 633 7563",
    "sg:postcode":"M3J 1L5",
    "sg:province":"ON",
    "sg:tags":[
        "oil"
    ],
    "wof:name":"Shell Canada Products Ltd",
    "wof:placetype":"venue"
},
  "geometry": {"coordinates":[-79.4867019653,43.7453155518],"type":"Point"}
}