{
  "type": "Feature",
  "properties": {
    "addr:full":"Cambridge ON N1R 6B3",
    "addr:postcode":"n1r 6b3",
    "iso:country":"CA",
    "sg:city":"Cambridge",
    "sg:classifiers":[
        {
            "category":"Shopping",
            "subcategory":"Music",
            "type":"Retail Goods"
        }
    ],
    "sg:phone":"+1 519 624 0228",
    "sg:postcode":"N1R 6B3",
    "sg:province":"ON",
    "sg:tags":[
        "compact",
        "record",
        "disc",
        "tape"
    ],
    "wof:name":"Hmv",
    "wof:placetype":"venue"
},
  "geometry": {"coordinates":[-80.32270050050001,43.3920707703],"type":"Point"}
}