{
  "type": "Feature",
  "properties": {
    "addr:full":"60 Rue DE LA Fabrique Sainte-Claire QC G0R 2V0",
    "addr:housenumber":"60",
    "addr:postcode":"g0r 2v0",
    "addr:street":"Rue De La Fabrique",
    "iso:country":"CA",
    "sg:address":"60 Rue DE LA Fabrique",
    "sg:city":"Sainte-Claire",
    "sg:classifiers":[
        {
            "category":"Education",
            "subcategory":"School",
            "type":"Public Place"
        }
    ],
    "sg:phone":"+1 418 883 3750",
    "sg:postcode":"G0R 2V0",
    "sg:province":"QC",
    "wof:name":"Ecole Morissette",
    "wof:placetype":"venue"
},
  "geometry": {"coordinates":[-70.865875,46.598553],"type":"Point"}
}