{
  "type": "Feature",
  "properties": {
    "addr:full":"564 Crois DE Murano Laval QC H7M 5R5",
    "addr:housenumber":"564",
    "addr:postcode":"h7m 5r5",
    "addr:street":"Crois De Murano",
    "iso:country":"CA",
    "sg:address":"564 Crois DE Murano",
    "sg:city":"Laval",
    "sg:classifiers":[
        {
            "category":"Building & Trades",
            "subcategory":"Landscaping Services",
            "type":"Services"
        }
    ],
    "sg:phone":"+1 450 662 1453",
    "sg:postcode":"H7M 5R5",
    "sg:province":"QC",
    "sg:tags":[
        "paving",
        "landscape",
        "contractor"
    ],
    "wof:name":"Pavage Can-To Inc",
    "wof:placetype":"venue"
},
  "geometry": {"coordinates":[-73.71611,45.616337],"type":"Point"}
}