{
  "type": "Feature",
  "properties": {
    "addr:full":"Rathwell MB R0G 1S0",
    "addr:postcode":"r0g 1s0",
    "iso:country":"CA",
    "sg:city":"Rathwell",
    "sg:classifiers":[
        {
            "category":"Freight",
            "type":"Transportation"
        }
    ],
    "sg:phone":"+1 204 749 2211",
    "sg:postcode":"R0G 1S0",
    "sg:province":"MB",
    "sg:tags":[
        "grain",
        "elevator"
    ],
    "wof:name":"Louis Dreyfus Canada Ltd",
    "wof:placetype":"venue"
},
  "geometry": {"coordinates":[-98.545952,49.647179],"type":"Point"}
}