{
  "type": "Feature",
  "properties": {
    "iso:country":"CA",
    "sg:address":"25 Union St",
    "sg:city":"Sussex",
    "sg:classifiers":[
        {
            "category":"Wholesale",
            "subcategory":"Farm Supplies",
            "type":"Manufacturing & Wholesale Goods"
        }
    ],
    "sg:phone":"+1 506 432 1826",
    "sg:postcode":"E4E 1T5",
    "sg:province":"NB",
    "sg:tags":[
        "equipment",
        "welding"
    ],
    "wof:name":"Sussex CO Op",
    "wof:placetype":"venue"
},
  "geometry": {"coordinates":[-65.5183334351,45.720287323],"type":"Point"}
}