{
  "type": "Feature",
  "properties": {
    "addr:full":"237 Rue Commerciale Cabano QC G0L 1E0",
    "addr:housenumber":"237",
    "addr:postcode":"g0l 1e0",
    "addr:street":"Rue Commerciale",
    "iso:country":"CA",
    "sg:address":"237 Rue Commerciale",
    "sg:city":"Cabano",
    "sg:classifiers":[
        {
            "category":"Food & Beverages",
            "subcategory":"Liquor & Beverages",
            "type":"Retail Goods"
        }
    ],
    "sg:phone":"+1 418 854 2000",
    "sg:postcode":"G0L 1E0",
    "sg:province":"QC",
    "sg:tags":[
        "store"
    ],
    "wof:name":"Quebec Societe Des Alcools",
    "wof:placetype":"venue"
},
  "geometry": {"coordinates":[-68.8706207275,47.6736717224],"type":"Point"}
}