{
  "type": "Feature",
  "properties": {
    "addr:full":"481 Bernard Ave Kelowna BC V1Y 6N8",
    "addr:housenumber":"481",
    "addr:postcode":"v1y 6n8",
    "addr:street":"Bernard Ave",
    "iso:country":"CA",
    "sg:address":"481 Bernard Ave",
    "sg:city":"Kelowna",
    "sg:classifiers":[
        {
            "category":"Shopping",
            "subcategory":"Tobacco",
            "type":"Retail Goods"
        }
    ],
    "sg:phone":"+1 250 762 4737",
    "sg:postcode":"V1Y 6N8",
    "sg:province":"BC",
    "sg:tags":[
        "cigarette",
        "cigar",
        "dealer"
    ],
    "wof:name":"Wigwam Smoke & Gift Shop",
    "wof:placetype":"venue"
},
  "geometry": {"coordinates":[-119.493934631,49.8861732483],"type":"Point"}
}