{
  "type": "Feature",
  "properties": {
    "addr:full":"Levis QC G6V 6C8",
    "addr:postcode":"g6v 6c8",
    "iso:country":"CA",
    "sg:city":"Levis",
    "sg:classifiers":[
        {
            "category":"Retail",
            "subcategory":"Animal Services",
            "type":"Services"
        }
    ],
    "sg:phone":"+1 418 833 2550",
    "sg:postcode":"G6V 6C8",
    "sg:province":"QC",
    "sg:tags":[
        "pet",
        "shop"
    ],
    "wof:name":"Animalerie Dyno",
    "wof:placetype":"venue"
},
  "geometry": {"coordinates":[-71.171761,46.792294],"type":"Point"}
}