{
  "type": "Feature",
  "properties": {
    "addr:full":"348 Lemoyne St Timmins ON P4N 4C2",
    "addr:housenumber":"348",
    "addr:postcode":"p4n 4c2",
    "addr:street":"Lemoyne St",
    "iso:country":"CA",
    "sg:address":"348 Lemoyne St",
    "sg:city":"Timmins",
    "sg:classifiers":[
        {
            "category":"Building & Trades",
            "subcategory":"Construction",
            "type":"Services"
        }
    ],
    "sg:phone":"+1 705 268 5506",
    "sg:postcode":"P4N 4C2",
    "sg:province":"ON",
    "sg:tags":[
        "demolition",
        "contractor"
    ],
    "wof:name":"Remtech Blasting Svc Inc",
    "wof:placetype":"venue"
},
  "geometry": {"coordinates":[-81.3578033447,48.4791717529],"type":"Point"}
}