{
  "type": "Feature",
  "properties": {
    "addr:full":"Raymond AB T0K 2S0",
    "addr:postcode":"t0k 2s0",
    "iso:country":"CA",
    "sg:city":"Raymond",
    "sg:classifiers":[
        {
            "category":"Food & Beverages",
            "subcategory":"Groceries & Convenience Stores",
            "type":"Retail Goods"
        }
    ],
    "sg:phone":"+1 403 752 3057",
    "sg:postcode":"T0K 2S0",
    "sg:province":"AB",
    "sg:tags":[
        "grocer"
    ],
    "wof:name":"Raymond Mercantile CO Ltd",
    "wof:placetype":"venue"
},
  "geometry": {"coordinates":[-112.66252136200001,49.462020874],"type":"Point"}
}