{
  "type": "Feature",
  "properties": {
    "addr:full":"107 Arrow Rd Guelph ON N1K 1S8",
    "addr:housenumber":"107",
    "addr:postcode":"n1k 1s8",
    "addr:street":"Arrow Rd",
    "iso:country":"CA",
    "sg:address":"107 Arrow Rd",
    "sg:city":"Guelph",
    "sg:classifiers":[
        {
            "category":"Wholesale",
            "subcategory":"Metals & Minerals",
            "type":"Manufacturing & Wholesale Goods"
        }
    ],
    "sg:phone":"+1 519 767 6677",
    "sg:postcode":"N1K 1S8",
    "sg:province":"ON",
    "sg:tags":[
        "pipe",
        "warehouse"
    ],
    "wof:name":"Hunter Steel Sales",
    "wof:placetype":"venue"
},
  "geometry": {"coordinates":[-80.2965621948,43.5564727783],"type":"Point"}
}