{
  "type": "Feature",
  "properties": {
    "iso:country":"CA",
    "sg:address":"1960 Gerrard St E",
    "sg:city":"Toronto",
    "sg:classifiers":[
        {
            "category":"Shopping",
            "subcategory":"Florist",
            "type":"Retail Goods"
        }
    ],
    "sg:phone":"+1 416 691 8038",
    "sg:postcode":"M4E 2B1",
    "sg:province":"ON",
    "wof:name":"East of Eliza",
    "wof:placetype":"venue"
},
  "geometry": {"coordinates":[-79.310486,43.681072],"type":"Point"}
}