{
  "type": "Feature",
  "properties": {
    "addr:full":"Etobicoke ON M8Z 5W3",
    "addr:postcode":"m8z 5w3",
    "iso:country":"CA",
    "sg:city":"Etobicoke",
    "sg:classifiers":[
        {
            "category":"Freight",
            "type":"Transportation"
        }
    ],
    "sg:phone":"+1 416 252 5861",
    "sg:postcode":"M8Z 5W3",
    "sg:province":"ON",
    "sg:tags":[
        "broker",
        "customs"
    ],
    "wof:name":"Counselor Customs Brokers Ltd",
    "wof:placetype":"venue"
},
  "geometry": {"coordinates":[-79.546898,43.617889],"type":"Point"}
}