{
  "type": "Feature",
  "properties": {
    "addr:full":"483 Range Lake Rd Yellowknife NT X1A 2N5",
    "addr:housenumber":"483",
    "addr:postcode":"x1a 2n5",
    "addr:street":"Range Lake Rd",
    "iso:country":"CA",
    "sg:address":"483 Range Lake Rd",
    "sg:city":"Yellowknife",
    "sg:classifiers":[
        {
            "category":"Taxi",
            "type":"Transportation"
        }
    ],
    "sg:phone":"+1 867 873 4444",
    "sg:postcode":"X1A 2N5",
    "sg:province":"NT",
    "sg:tags":[
        "taxicab"
    ],
    "wof:name":"City Cab Ltd",
    "wof:placetype":"venue"
},
  "geometry": {"coordinates":[-114.411064,62.445217],"type":"Point"}
}