{
  "type": "Feature",
  "properties": {
    "iso:country":"CA",
    "sg:address":"160 Cidermill Ave",
    "sg:city":"Concord",
    "sg:classifiers":[
        {
            "category":"Building & Trades",
            "subcategory":"Cleaning & Sanitation",
            "type":"Services"
        }
    ],
    "sg:phone":"+1 905 660 7609",
    "sg:postcode":"L4K 4K5",
    "sg:province":"ON",
    "sg:tags":[
        "janitor"
    ],
    "wof:name":"Quality General Maintenance",
    "wof:placetype":"venue"
},
  "geometry": {"coordinates":[-79.5332336426,43.8055229187],"type":"Point"}
}