{
  "type": "Feature",
  "properties": {
    "addr:full":"10894 Route 430 Trout Brook NB E9E 1R3",
    "addr:housenumber":"10894",
    "addr:postcode":"e9e 1r3",
    "addr:street":"Route 430;Brook",
    "iso:country":"CA",
    "sg:address":"10894 Route 430",
    "sg:city":"Trout Brook",
    "sg:classifiers":[
        {
            "category":"Home & Garden",
            "subcategory":"Building Materials",
            "type":"Retail Goods"
        }
    ],
    "sg:phone":"+1 506 622 3146",
    "sg:postcode":"E9E 1R3",
    "sg:province":"NB",
    "sg:tags":[
        "door"
    ],
    "wof:name":"Allison's Manufacturing Ltd",
    "wof:placetype":"venue"
},
  "geometry": {"coordinates":[-65.785866,47.115681],"type":"Point"}
}