{
  "type": "Feature",
  "properties": {
    "addr:full":"118 5th Ave N Saskatoon SK S7K 2N7",
    "addr:housenumber":"118",
    "addr:postcode":"s7k 2n7",
    "addr:street":"5Th Ave N",
    "iso:country":"CA",
    "sg:address":"118 5th Ave N",
    "sg:city":"Saskatoon",
    "sg:classifiers":[
        {
            "category":"Education",
            "subcategory":"School",
            "type":"Public Place"
        }
    ],
    "sg:phone":"+1 306 665 5553",
    "sg:postcode":"S7K 2N7",
    "sg:province":"SK",
    "wof:name":"Yvonne Yuen School of Design",
    "wof:placetype":"venue"
},
  "geometry": {"coordinates":[-106.65825653100001,52.1281852722],"type":"Point"}
}