{
  "type": "Feature",
  "properties": {
    "addr:full":"140 Dunlop Ave Gimli MB R0C 1B0",
    "addr:housenumber":"140",
    "addr:postcode":"r0c 1b0",
    "addr:street":"Dunlop Ave",
    "iso:country":"CA",
    "sg:address":"140 Dunlop Ave",
    "sg:city":"Gimli",
    "sg:classifiers":[
        {
            "category":"Manufacturing",
            "subcategory":"Watercraft",
            "type":"Manufacturing & Wholesale Goods"
        }
    ],
    "sg:phone":"+1 204 642 7972",
    "sg:postcode":"R0C 1B0",
    "sg:province":"MB",
    "sg:tags":[
        "boat"
    ],
    "wof:name":"Lake Winnipeg Boat Works Ltd",
    "wof:placetype":"venue"
},
  "geometry": {"coordinates":[-96.9941864014,50.6368637085],"type":"Point"}
}