{
  "type": "Feature",
  "properties": {
    "addr:full":"396 Conant St Oshawa ON L1H 3S6",
    "addr:housenumber":"396",
    "addr:postcode":"l1h 3s6",
    "addr:street":"Conant St",
    "iso:country":"CA",
    "sg:address":"396 Conant St",
    "sg:city":"Oshawa",
    "sg:classifiers":[
        {
            "category":"Freight",
            "type":"Transportation"
        }
    ],
    "sg:phone":"+1 905 579 1611",
    "sg:postcode":"L1H 3S6",
    "sg:province":"ON",
    "sg:tags":[
        "courier"
    ],
    "wof:name":"S T Express Courier Svc",
    "wof:placetype":"venue"
},
  "geometry": {"coordinates":[-78.8399505615,43.8804664612],"type":"Point"}
}