{
  "type": "Feature",
  "properties": {
    "addr:full":"8271 Keele St Concord ON L4K 1Z1",
    "addr:housenumber":"8271",
    "addr:postcode":"l4k 1z1",
    "addr:street":"Keele St",
    "iso:country":"CA",
    "sg:address":"8271 Keele St",
    "sg:city":"Concord",
    "sg:classifiers":[
        {
            "category":"Manufacturing",
            "subcategory":"Tools & Machinery",
            "type":"Manufacturing & Wholesale Goods"
        }
    ],
    "sg:phone":"+1 905 669 1999",
    "sg:postcode":"L4K 1Z1",
    "sg:province":"ON",
    "sg:tags":[
        "die",
        "maker"
    ],
    "wof:name":"Clover Tool Mfg Ltd",
    "wof:placetype":"venue"
},
  "geometry": {"coordinates":[-79.502365,43.81295],"type":"Point"}
}