{
  "type": "Feature",
  "properties": {
    "addr:full":"Midland ON L4R 2A8",
    "addr:postcode":"l4r 2a8",
    "iso:country":"CA",
    "sg:city":"Midland",
    "sg:classifiers":[
        {
            "category":"Building & Trades",
            "subcategory":"Construction",
            "type":"Services"
        }
    ],
    "sg:phone":"+1 705 527 5777",
    "sg:postcode":"L4R 2A8",
    "sg:province":"ON",
    "sg:tags":[
        "cabinet",
        "maker",
        "furniture"
    ],
    "wof:name":"Tmz Custom Furniture",
    "wof:placetype":"venue"
},
  "geometry": {"coordinates":[-79.8709487915,44.7520446777],"type":"Point"}
}