{
  "type": "Feature",
  "properties": {
    "addr:full":"Queen Charlotte BC V0T 1S0",
    "addr:postcode":"v0t 1s0",
    "iso:country":"CA",
    "sg:city":"Queen Charlotte",
    "sg:classifiers":[
        {
            "category":"Shopping",
            "subcategory":"Gifts & Souvenirs",
            "type":"Retail Goods"
        }
    ],
    "sg:phone":"+1 250 559 4463",
    "sg:postcode":"V0T 1S0",
    "sg:province":"BC",
    "sg:tags":[
        "shop",
        "coffee"
    ],
    "wof:name":"Hanging By A Fibre",
    "wof:placetype":"venue"
},
  "geometry": {"coordinates":[-132.06933599999999,53.25391],"type":"Point"}
}