{
  "type": "Feature",
  "properties": {
    "addr:full":"Delta BC V4K 2T8",
    "addr:postcode":"v4k 2t8",
    "iso:country":"CA",
    "sg:city":"Delta",
    "sg:classifiers":[
        {
            "category":"Professional",
            "subcategory":"Accounting & Tax Preparation",
            "type":"Services"
        }
    ],
    "sg:phone":"+1 604 946 9114",
    "sg:postcode":"V4K 2T8",
    "sg:province":"BC",
    "sg:tags":[
        "accountant"
    ],
    "wof:name":"Cran & Stuart",
    "wof:placetype":"venue"
},
  "geometry": {"coordinates":[-123.08618199999999,49.091675],"type":"Point"}
}