{
  "type": "Feature",
  "properties": {
    "addr:full":"9004 118 Ave NW Edmonton AB T5B 0T8",
    "addr:housenumber":"9004",
    "addr:postcode":"t5b 0t8",
    "addr:street":"118 Ave Nw",
    "iso:country":"CA",
    "sg:address":"9004 118 Ave NW",
    "sg:city":"Edmonton",
    "sg:classifiers":[
        {
            "category":"Building & Trades",
            "subcategory":"Equipment Rental",
            "type":"Services"
        }
    ],
    "sg:phone":"+1 780 477 2727",
    "sg:postcode":"T5B 0T8",
    "sg:province":"AB",
    "sg:tags":[
        "leasing",
        "furniture"
    ],
    "wof:name":"Affordable Rental Ctr",
    "wof:placetype":"venue"
},
  "geometry": {"coordinates":[-113.479927,53.570599],"type":"Point"}
}