{
  "type": "Feature",
  "properties": {
    "addr:full":"1799 Boul Cure-Labelle Laval QC H7T 1L1",
    "addr:housenumber":"1799",
    "addr:postcode":"h7t 1l1",
    "addr:street":"Boul Cure-Labelle",
    "iso:country":"CA",
    "sg:address":"1799 Boul Cure-Labelle",
    "sg:city":"Laval",
    "sg:classifiers":[
        {
            "category":"Shopping",
            "subcategory":"Jewelry",
            "type":"Retail Goods"
        }
    ],
    "sg:phone":"+1 450 681 1363",
    "sg:postcode":"H7T 1L1",
    "sg:province":"QC",
    "sg:tags":[
        "platinum",
        "silver",
        "gold"
    ],
    "wof:name":"Solution Rl",
    "wof:placetype":"venue"
},
  "geometry": {"coordinates":[-73.7612609863,45.5534172058],"type":"Point"}
}