{
  "type": "Feature",
  "properties": {
    "addr:full":"92 Ch Des Patriotes Sorel-Tracy QC J3P 2K7",
    "addr:housenumber":"92",
    "addr:postcode":"j3p 2k7",
    "addr:street":"Ch Des Patriotes",
    "iso:country":"CA",
    "sg:address":"92 Ch Des Patriotes",
    "sg:city":"Sorel-Tracy",
    "sg:classifiers":[
        {
            "category":"Professional",
            "subcategory":"Business Services",
            "type":"Services"
        }
    ],
    "sg:phone":"+1 450 743 0660",
    "sg:postcode":"J3P 2K7",
    "sg:province":"QC",
    "sg:tags":[
        "information",
        "referral"
    ],
    "wof:name":"Reseau Sentier Nature",
    "wof:placetype":"venue"
},
  "geometry": {"coordinates":[-73.11547899999999,46.033409],"type":"Point"}
}