{
  "type": "Feature",
  "properties": {
    "addr:full":"1833 Folkway Dr Mississauga ON L5L 2X1",
    "addr:housenumber":"1833",
    "addr:postcode":"l5l 2x1",
    "addr:street":"Folkway Dr",
    "iso:country":"CA",
    "sg:address":"1833 Folkway Dr",
    "sg:city":"Mississauga",
    "sg:phone":"+1 905 820 7225",
    "sg:postcode":"L5L 2X1",
    "sg:province":"ON",
    "sg:tags":[
        "food",
        "equipment",
        "processing"
    ],
    "wof:name":"Qms Intl",
    "wof:placetype":"venue"
},
  "geometry": {"coordinates":[-79.681038,43.55484],"type":"Point"}
}