{
  "type": "Feature",
  "properties": {
    "iso:country":"CA",
    "sg:address":"10 Westmore Dr",
    "sg:city":"Etobicoke",
    "sg:classifiers":[
        {
            "category":"Food & Beverages",
            "subcategory":"Groceries & Convenience Stores",
            "type":"Retail Goods"
        }
    ],
    "sg:phone":"+1 416 740 3262",
    "sg:postcode":"M9V 3Z7",
    "sg:province":"ON",
    "sg:tags":[
        "grocer"
    ],
    "wof:name":"Asian Food Ctr",
    "wof:placetype":"venue"
},
  "geometry": {"coordinates":[-79.604401,43.742729],"type":"Point"}
}