{
  "type": "Feature",
  "properties": {
    "addr:full":"17858 66 Ave Surrey BC V3S 7X1",
    "addr:housenumber":"17858",
    "addr:postcode":"v3s 7x1",
    "addr:street":"66 Ave",
    "iso:country":"CA",
    "sg:address":"17858 66 Ave",
    "sg:city":"Surrey",
    "sg:classifiers":[
        {
            "category":"Shopping",
            "type":"Retail Goods"
        }
    ],
    "sg:phone":"+1 604 576 5695",
    "sg:postcode":"V3S 7X1",
    "sg:province":"BC",
    "sg:tags":[
        "equipment",
        "wine",
        "supply"
    ],
    "wof:name":"Cellar Craft",
    "wof:placetype":"venue"
},
  "geometry": {"coordinates":[-122.729263,49.122292],"type":"Point"}
}