{
  "type": "Feature",
  "properties": {
    "addr:full":"Saint-Roch-DE-L'Achigan QC J0K 3H0",
    "addr:postcode":"j0k 3h0",
    "iso:country":"CA",
    "sg:city":"Saint-Roch-DE-L'Achigan",
    "sg:classifiers":[
        {
            "category":"Retail",
            "subcategory":"Funeral Services",
            "type":"Services"
        }
    ],
    "sg:phone":"+1 450 588 2554",
    "sg:postcode":"J0K 3H0",
    "sg:province":"QC",
    "sg:tags":[
        "director"
    ],
    "wof:name":"Beauchamp, Jean-Denis",
    "wof:placetype":"venue"
},
  "geometry": {"coordinates":[-72.06829071040001,48.9647254944],"type":"Point"}
}