{
  "type": "Feature",
  "properties": {
    "addr:full":"Hamilton ON L8L 3E4",
    "addr:postcode":"l8l 3e4",
    "iso:country":"CA",
    "sg:city":"Hamilton",
    "sg:classifiers":[
        {
            "category":"Building & Trades",
            "subcategory":"Construction",
            "type":"Services"
        }
    ],
    "sg:phone":"+1 905 548 0166",
    "sg:postcode":"L8L 3E4",
    "sg:province":"ON",
    "sg:tags":[
        "contractor",
        "general"
    ],
    "wof:name":"Baldin & Beltrame Constr CO",
    "wof:placetype":"venue"
},
  "geometry": {"coordinates":[-79.819061,43.252037],"type":"Point"}
}