{
  "type": "Feature",
  "properties": {
    "addr:full":"650 Adams Crt Kelowna BC V1X 7S2",
    "addr:housenumber":"650",
    "addr:postcode":"v1x 7s2",
    "addr:street":"Adams",
    "iso:country":"CA",
    "sg:address":"650 Adams Crt",
    "sg:city":"Kelowna",
    "sg:classifiers":[
        {
            "category":"Home & Garden",
            "subcategory":"Building Materials",
            "type":"Retail Goods"
        }
    ],
    "sg:phone":"+1 250 765 7212",
    "sg:postcode":"V1X 7S2",
    "sg:province":"BC",
    "sg:tags":[
        "hardwood"
    ],
    "wof:name":"Reimer Hardwoods Ltd",
    "wof:placetype":"venue"
},
  "geometry": {"coordinates":[-119.38839,49.929558],"type":"Point"}
}