{
  "type": "Feature",
  "properties": {
    "addr:full":"8220 Bayview Ave Thornhill ON L3T 2S2",
    "addr:housenumber":"8220",
    "addr:postcode":"l3t 2s2",
    "addr:street":"Bayview Ave",
    "iso:country":"CA",
    "sg:address":"8220 Bayview Ave",
    "sg:city":"Thornhill",
    "sg:classifiers":[
        {
            "category":"Food & Beverages",
            "subcategory":"Bakery",
            "type":"Retail Goods"
        }
    ],
    "sg:phone":"+1 905 881 0736",
    "sg:postcode":"L3T 2S2",
    "sg:province":"ON",
    "sg:tags":[
        "doughnut"
    ],
    "wof:name":"Coffee Time Donuts",
    "wof:placetype":"venue"
},
  "geometry": {"coordinates":[-79.40476200000001,43.832401],"type":"Point"}
}