{
  "type": "Feature",
  "properties": {
    "addr:full":"RR 2 Elora ON N0B 1S0",
    "addr:postcode":"n0b 1s0",
    "addr:street":"Rr 2",
    "iso:country":"CA",
    "sg:address":"RR 2",
    "sg:city":"Elora",
    "sg:classifiers":[
        {
            "category":"Wholesale",
            "subcategory":"Electrical",
            "type":"Manufacturing & Wholesale Goods"
        }
    ],
    "sg:phone":"+1 519 846 0540",
    "sg:postcode":"N0B 1S0",
    "sg:province":"ON",
    "sg:tags":[
        "electric",
        "motor"
    ],
    "wof:name":"Rectify Electric Ltd",
    "wof:placetype":"venue"
},
  "geometry": {"coordinates":[-80.429749,43.68158],"type":"Point"}
}