{
  "type": "Feature",
  "properties": {
    "addr:full":"Mississauga ON L4Y 4A2",
    "addr:postcode":"l4y 4a2",
    "iso:country":"CA",
    "sg:city":"Mississauga",
    "sg:classifiers":[
        {
            "category":"Organizations",
            "subcategory":"Religious Organization",
            "type":"Services"
        }
    ],
    "sg:phone":"+1 905 566 1084",
    "sg:postcode":"L4Y 4A2",
    "sg:province":"ON",
    "sg:tags":[
        "church"
    ],
    "wof:name":"Deeper Life Christian Ministr",
    "wof:placetype":"venue"
},
  "geometry": {"coordinates":[-79.587418,43.605919],"type":"Point"}
}