{
  "type": "Feature",
  "properties": {
    "addr:full":"5247 Inga St Peachland BC V0H 1X8",
    "addr:housenumber":"5247",
    "addr:postcode":"v0h 1x8",
    "addr:street":"Inga St",
    "iso:country":"CA",
    "sg:address":"5247 Inga St",
    "sg:city":"Peachland",
    "sg:classifiers":[
        {
            "category":"Travel",
            "subcategory":"Campground",
            "type":"Entertainment"
        }
    ],
    "sg:phone":"+1 250 767 2354",
    "sg:postcode":"V0H 1X8",
    "sg:province":"BC",
    "sg:tags":[
        "camp"
    ],
    "wof:name":"Maple Springs Bible Camp",
    "wof:placetype":"venue"
},
  "geometry": {"coordinates":[-119.77993774399999,49.752281189],"type":"Point"}
}