{
  "type": "Feature",
  "properties": {
    "addr:full":"404 Elizabeth St Guelph ON N1E 2Y1",
    "addr:housenumber":"404",
    "addr:postcode":"n1e 2y1",
    "addr:street":"Elizabeth St",
    "iso:country":"CA",
    "sg:address":"404 Elizabeth St",
    "sg:city":"Guelph",
    "sg:classifiers":[
        {
            "category":"Wholesale",
            "subcategory":"Chemicals & Plastics",
            "type":"Manufacturing & Wholesale Goods"
        }
    ],
    "sg:phone":"+1 519 822 6490",
    "sg:postcode":"N1E 2Y1",
    "sg:province":"ON",
    "sg:tags":[
        "equipment",
        "welding",
        "helium",
        "supply"
    ],
    "wof:name":"Boc Gases",
    "wof:placetype":"venue"
},
  "geometry": {"coordinates":[-80.2275924683,43.5556793213],"type":"Point"}
}