{
  "type": "Feature",
  "properties": {
    "addr:full":"350 Legget Dr Kanata ON K2K 2W7",
    "addr:housenumber":"350",
    "addr:postcode":"k2k 2w7",
    "addr:street":"Legget Dr",
    "iso:country":"CA",
    "sg:address":"350 Legget Dr",
    "sg:city":"Kanata",
    "sg:classifiers":[
        {
            "category":"Shopping",
            "type":"Retail Goods"
        }
    ],
    "sg:phone":"+1 613 592 2122",
    "sg:postcode":"K2K 2W7",
    "sg:province":"ON",
    "sg:tags":[
        "equipment",
        "telephone",
        "supply"
    ],
    "wof:name":"Mitel Networks Corp",
    "wof:placetype":"venue"
},
  "geometry": {"coordinates":[-75.909081,45.340668],"type":"Point"}
}