{
  "type": "Feature",
  "properties": {
    "addr:full":"408 North Railway Killarney MB R0K 1G0",
    "addr:housenumber":"408",
    "addr:postcode":"r0k 1g0",
    "addr:street":"North Railway",
    "iso:country":"CA",
    "sg:address":"408 North Railway",
    "sg:city":"Killarney",
    "sg:classifiers":[
        {
            "category":"Retail",
            "subcategory":"Repair Shop",
            "type":"Services"
        }
    ],
    "sg:phone":"+1 204 523 4255",
    "sg:postcode":"R0K 1G0",
    "sg:province":"MB",
    "sg:tags":[
        "machine",
        "welding"
    ],
    "wof:name":"Kiwi Welding & Machine Shop",
    "wof:placetype":"venue"
},
  "geometry": {"coordinates":[-99.65876,49.184956],"type":"Point"}
}