{
  "type": "Feature",
  "properties": {
    "iso:country":"CA",
    "sg:address":"1624 70 Ave NW",
    "sg:city":"Edmonton",
    "sg:classifiers":[
        {
            "category":"Professional",
            "subcategory":"Engineering",
            "type":"Services"
        }
    ],
    "sg:phone":"+1 780 440 6064",
    "sg:postcode":"T6P 1P5",
    "sg:province":"AB",
    "sg:tags":[
        "engineer"
    ],
    "wof:name":"Thermo Design Engineering Ltd",
    "wof:placetype":"venue"
},
  "geometry": {"coordinates":[-113.36731,53.506809],"type":"Point"}
}