{
  "type": "Feature",
  "properties": {
    "addr:full":"5292 Knott Cres Manotick ON K4M 1C2",
    "addr:housenumber":"5292",
    "addr:postcode":"k4m 1c2",
    "addr:street":"Knott Cres",
    "iso:country":"CA",
    "sg:address":"5292 Knott Cres",
    "sg:city":"Manotick",
    "sg:classifiers":[
        {
            "category":"Wholesale",
            "subcategory":"Electrical",
            "type":"Manufacturing & Wholesale Goods"
        }
    ],
    "sg:phone":"+1 613 692 6622",
    "sg:postcode":"K4M 1C2",
    "sg:province":"ON",
    "sg:tags":[
        "alarm",
        "burglar",
        "system"
    ],
    "wof:name":"Shanalex Alarms",
    "wof:placetype":"venue"
},
  "geometry": {"coordinates":[-75.6859359741,45.2262649536],"type":"Point"}
}