{
  "type": "Feature",
  "properties": {
    "addr:full":"449 10th St E Prince Albert SK S6V 0Z5",
    "addr:housenumber":"449",
    "addr:postcode":"s6v 0z5",
    "addr:street":"10Th St",
    "iso:country":"CA",
    "sg:address":"449 10th St E",
    "sg:city":"Prince Albert",
    "sg:classifiers":[
        {
            "category":"Organizations",
            "subcategory":"Professional Association",
            "type":"Services"
        }
    ],
    "sg:phone":"+1 306 763 0337",
    "sg:postcode":"S6V 0Z5",
    "sg:province":"SK",
    "wof:name":"Societe Canadienne Francaise",
    "wof:placetype":"venue"
},
  "geometry": {"coordinates":[-105.743186951,53.2037467957],"type":"Point"}
}