{
  "type": "Feature",
  "properties": {
    "iso:country":"CA",
    "sg:address":"96 Wallace St",
    "sg:city":"Nanaimo",
    "sg:classifiers":[
        {
            "category":"Professional",
            "subcategory":"Accounting & Tax Preparation",
            "type":"Services"
        }
    ],
    "sg:phone":"+1 250 753 8251",
    "sg:postcode":"V9R 5L5",
    "sg:province":"BC",
    "sg:tags":[
        "accountant"
    ],
    "wof:name":"Fyfe, Chris CA",
    "wof:placetype":"venue"
},
  "geometry": {"coordinates":[-123.941681,49.168732],"type":"Point"}
}