{
  "type": "Feature",
  "properties": {
    "addr:full":"766 Fort St Victoria BC V8W 1H2",
    "addr:housenumber":"766",
    "addr:postcode":"v8w 1h2",
    "addr:street":"Fort St",
    "iso:country":"CA",
    "sg:address":"766 Fort St",
    "sg:city":"Victoria",
    "sg:classifiers":[
        {
            "category":"Shopping",
            "subcategory":"Optical Goods",
            "type":"Retail Goods"
        }
    ],
    "sg:phone":"+1 250 361 2020",
    "sg:postcode":"V8W 1H2",
    "sg:province":"BC",
    "sg:tags":[
        "optician"
    ],
    "wof:name":"Discovery Optical Ltd",
    "wof:placetype":"venue"
},
  "geometry": {"coordinates":[-123.363525,48.424465],"type":"Point"}
}