{
  "type": "Feature",
  "properties": {
    "iso:country":"CA",
    "sg:address":"5300 Bradco Blvd",
    "sg:city":"Mississauga",
    "sg:classifiers":[
        {
            "category":"Manufacturing",
            "subcategory":"Metals",
            "type":"Manufacturing & Wholesale Goods"
        }
    ],
    "sg:phone":"+1 905 624 4910",
    "sg:postcode":"L4W 1G7",
    "sg:province":"ON",
    "sg:tags":[
        "tube",
        "fabricating"
    ],
    "wof:name":"Tci Inc",
    "wof:placetype":"venue"
},
  "geometry": {"coordinates":[-79.6324768066,43.6371765137],"type":"Point"}
}