{
  "type": "Feature",
  "properties": {
    "addr:full":"53 Erickson Dr Red Deer AB T4R 1X8",
    "addr:housenumber":"53",
    "addr:postcode":"t4r 1x8",
    "addr:street":"Erickson Dr",
    "iso:country":"CA",
    "sg:address":"53 Erickson Dr",
    "sg:city":"Red Deer",
    "sg:classifiers":[
        {
            "category":"Travel",
            "subcategory":"Hotels & Motels",
            "type":"Entertainment"
        }
    ],
    "sg:phone":"+1 403 341 3101",
    "sg:postcode":"T4R 1X8",
    "sg:province":"AB",
    "sg:tags":[
        "resort"
    ],
    "wof:name":"Central Alberta Freestyle Club",
    "wof:placetype":"venue"
},
  "geometry": {"coordinates":[-113.770080566,52.2643203735],"type":"Point"}
}