{
  "type": "Feature",
  "properties": {
    "addr:full":"792 Walkem St Quesnel BC V2J 2J9",
    "addr:housenumber":"792",
    "addr:postcode":"v2j 2j9",
    "addr:street":"Walkem St",
    "iso:country":"CA",
    "sg:address":"792 Walkem St",
    "sg:city":"Quesnel",
    "sg:classifiers":[
        {
            "category":"Retail",
            "subcategory":"Animal Services",
            "type":"Services"
        }
    ],
    "sg:phone":"+1 250 992 5912",
    "sg:postcode":"V2J 2J9",
    "sg:province":"BC",
    "sg:tags":[
        "pet",
        "grooming",
        "washing"
    ],
    "wof:name":"Lyn's Pet Grooming",
    "wof:placetype":"venue"
},
  "geometry": {"coordinates":[-122.501098633,52.9858474731],"type":"Point"}
}