{
  "type": "Feature",
  "properties": {
    "addr:full":"Huntsville ON P1H 1Y4",
    "addr:postcode":"p1h 1y4",
    "iso:country":"CA",
    "sg:city":"Huntsville",
    "sg:classifiers":[
        {
            "category":"Building & Trades",
            "subcategory":"Construction",
            "type":"Services"
        }
    ],
    "sg:phone":"+1 705 789 8067",
    "sg:postcode":"P1H 1Y4",
    "sg:province":"ON",
    "sg:tags":[
        "builder",
        "repairer",
        "masonry",
        "chimney",
        "contractor"
    ],
    "wof:name":"Randy Nickason Masonry",
    "wof:placetype":"venue"
},
  "geometry": {"coordinates":[-79.248589,45.313114],"type":"Point"}
}