{
  "type": "Feature",
  "properties": {
    "iso:country":"CA",
    "sg:address":"88 Shawnee Way SW",
    "sg:city":"Calgary",
    "sg:classifiers":[
        {
            "category":"Personal",
            "type":"Services"
        }
    ],
    "sg:phone":"+1 403 254 6088",
    "sg:postcode":"T2Y 2V3",
    "sg:province":"AB",
    "sg:tags":[
        "consultant",
        "miscellaneous",
        "real estate"
    ],
    "wof:name":"North/South Connection Inc",
    "wof:placetype":"venue"
},
  "geometry": {"coordinates":[-114.091773987,50.9218788147],"type":"Point"}
}