{
  "type": "Feature",
  "properties": {
    "addr:full":"1400 1 St SW # 500 Calgary AB T2R 0V8",
    "addr:housenumber":"1400 1",
    "addr:postcode":"t2r 0v8",
    "addr:street":"St Sw # 500",
    "iso:country":"CA",
    "sg:address":"1400 1 St SW # 500",
    "sg:city":"Calgary",
    "sg:classifiers":[
        {
            "category":"Health Services",
            "subcategory":"Clinic",
            "type":"Services"
        }
    ],
    "sg:phone":"+1 403 232 8770",
    "sg:postcode":"T2R 0V8",
    "sg:province":"AB",
    "sg:tags":[
        "home"
    ],
    "wof:name":"Calgary Home Support",
    "wof:placetype":"venue"
},
  "geometry": {"coordinates":[-114.06576538100001,51.0394630432],"type":"Point"}
}