{
  "type": "Feature",
  "properties": {
    "iso:country":"CA",
    "sg:address":"5009 50th Ave",
    "sg:city":"St Paul",
    "sg:classifiers":[
        {
            "category":"Shopping",
            "subcategory":"Stationery & Office Supplies",
            "type":"Retail Goods"
        }
    ],
    "sg:phone":"+1 780 645 4141",
    "sg:postcode":"T0A 3A0",
    "sg:province":"AB",
    "sg:tags":[
        "stationer"
    ],
    "wof:name":"Evergreen Stationers Ltd",
    "wof:placetype":"venue"
},
  "geometry": {"coordinates":[-111.29750824,53.9912605286],"type":"Point"}
}