{
  "type": "Feature",
  "properties": {
    "iso:country":"CA",
    "sg:address":"5 1st Ave NE",
    "sg:city":"Weyburn",
    "sg:classifiers":[
        {
            "category":"Professional",
            "subcategory":"Lawyer & Legal Services",
            "type":"Services"
        }
    ],
    "sg:phone":"+1 306 842 7419",
    "sg:postcode":"S4H 0M6",
    "sg:province":"SK",
    "sg:tags":[
        "attorney"
    ],
    "wof:name":"Holliday & CO",
    "wof:placetype":"venue"
},
  "geometry": {"coordinates":[-103.858109,49.668385],"type":"Point"}
}