{
  "type": "Feature",
  "properties": {
    "addr:full":"1887 Rue Lavoie Laval QC H7M 2N4",
    "addr:housenumber":"1887",
    "addr:postcode":"h7m 2n4",
    "addr:street":"Rue Lavoie",
    "iso:country":"CA",
    "sg:address":"1887 Rue Lavoie",
    "sg:city":"Laval",
    "sg:classifiers":[
        {
            "category":"Building & Trades",
            "subcategory":"Plumbing",
            "type":"Services"
        }
    ],
    "sg:phone":"+1 450 663 7403",
    "sg:postcode":"H7M 2N4",
    "sg:province":"QC",
    "sg:tags":[
        "contractor"
    ],
    "wof:name":"A & L Plomberie Inc",
    "wof:placetype":"venue"
},
  "geometry": {"coordinates":[-73.7273483276,45.6027984619],"type":"Point"}
}