{
  "type": "Feature",
  "properties": {
    "addr:full":"Markham ON L3R 8X4",
    "addr:postcode":"l3r 8x4",
    "iso:country":"CA",
    "sg:city":"Markham",
    "sg:classifiers":[
        {
            "category":"Retail",
            "subcategory":"Laundry & Dry Cleaning",
            "type":"Services"
        }
    ],
    "sg:phone":"+1 905 479 3850",
    "sg:postcode":"L3R 8X4",
    "sg:province":"ON",
    "sg:tags":[
        "cleaners"
    ],
    "wof:name":"Allcare Cleaners",
    "wof:placetype":"venue"
},
  "geometry": {"coordinates":[-79.342880249,43.8711471558],"type":"Point"}
}