{
  "type": "Feature",
  "properties": {
    "addr:full":"7 Riverview Dr Guelph ON N1E 3R6",
    "addr:housenumber":"7",
    "addr:postcode":"n1e 3r6",
    "addr:street":"Riverview Dr",
    "iso:country":"CA",
    "sg:address":"7 Riverview Dr",
    "sg:city":"Guelph",
    "sg:classifiers":[
        {
            "category":"Health Services",
            "subcategory":"Doctor",
            "type":"Services"
        }
    ],
    "sg:phone":"+1 519 824 8250",
    "sg:postcode":"N1E 3R6",
    "sg:province":"ON",
    "sg:tags":[
        "dentist"
    ],
    "wof:name":"Spencer Health Facility Inc",
    "wof:placetype":"venue"
},
  "geometry": {"coordinates":[-80.26563299999999,43.560799],"type":"Point"}
}