{
  "type": "Feature",
  "properties": {
    "addr:full":"117 George St S Toronto ON M5A 4A2",
    "addr:housenumber":"117",
    "addr:postcode":"m5a 4a2",
    "addr:street":"George St S",
    "iso:country":"CA",
    "sg:address":"117 George St S",
    "sg:city":"Toronto",
    "sg:classifiers":[
        {
            "category":"Banks & Credit Unions",
            "subcategory":"Investment Brokerage",
            "type":"Services"
        }
    ],
    "sg:phone":"+1 416 365 0070",
    "sg:postcode":"M5A 4A2",
    "sg:province":"ON",
    "sg:tags":[
        "consultant",
        "planning",
        "financial"
    ],
    "wof:name":"Dinovo, John P",
    "wof:placetype":"venue"
},
  "geometry": {"coordinates":[-79.369812,43.64909],"type":"Point"}
}