{
  "type": "Feature",
  "properties": {
    "addr:full":"235 Rue Thomas-Chapais Sainte-Julie QC J3E 1N4",
    "addr:housenumber":"235",
    "addr:postcode":"j3e 1n4",
    "addr:street":"Rue Thomas-Chapais",
    "iso:country":"CA",
    "sg:address":"235 Rue Thomas-Chapais",
    "sg:city":"Sainte-Julie",
    "sg:classifiers":[
        {
            "category":"Freight",
            "type":"Transportation"
        }
    ],
    "sg:phone":"+1 514 347 3472",
    "sg:postcode":"J3E 1N4",
    "sg:province":"QC",
    "sg:tags":[
        "trucking"
    ],
    "wof:name":"Transport Ajm Proulx Inc",
    "wof:placetype":"venue"
},
  "geometry": {"coordinates":[-73.339851,45.599026],"type":"Point"}
}