{
  "type": "Feature",
  "properties": {
    "addr:full":"Barriere BC V0E 1E0",
    "addr:postcode":"v0e 1e0",
    "iso:country":"CA",
    "sg:city":"Barriere",
    "sg:classifiers":[
        {
            "category":"Personal",
            "subcategory":"Beauty Salon",
            "type":"Services"
        }
    ],
    "sg:phone":"+1 250 672 0101",
    "sg:postcode":"V0E 1E0",
    "sg:province":"BC",
    "wof:name":"Styling By Stevens",
    "wof:placetype":"venue"
},
  "geometry": {"coordinates":[-120.126671,51.188274],"type":"Point"}
}