{
  "type": "Feature",
  "properties": {
    "iso:country":"CA",
    "sg:address":"3984 Victoria Ave",
    "sg:city":"Vineland",
    "sg:classifiers":[
        {
            "category":"Retail",
            "subcategory":"Portrait Studio",
            "type":"Services"
        }
    ],
    "sg:phone":"+1 905 562 6008",
    "sg:postcode":"L0R 2C0",
    "sg:province":"ON",
    "sg:tags":[
        "photographer"
    ],
    "wof:name":"Klic Photographic Design",
    "wof:placetype":"venue"
},
  "geometry": {"coordinates":[-79.3932342529,43.1547393799],"type":"Point"}
}