{
  "type": "Feature",
  "properties": {
    "addr:full":"33 Cedar St S Timmins ON P4N 2G5",
    "addr:housenumber":"33",
    "addr:postcode":"p4n 2g5",
    "addr:street":"Cedar St S",
    "iso:country":"CA",
    "sg:address":"33 Cedar St S",
    "sg:city":"Timmins",
    "sg:classifiers":[
        {
            "category":"Bars & Pubs",
            "type":"Food & Drink"
        }
    ],
    "sg:phone":"+1 705 360 1477",
    "sg:postcode":"P4N 2G5",
    "sg:province":"ON",
    "sg:tags":[
        "club",
        "lounge",
        "cocktail",
        "night"
    ],
    "wof:name":"Amigos",
    "wof:placetype":"venue"
},
  "geometry": {"coordinates":[-81.329712,48.475605],"type":"Point"}
}