{
  "type": "Feature",
  "properties": {
    "iso:country":"CA",
    "sg:address":"175 Boul Saint-Joseph",
    "sg:city":"Hull",
    "sg:classifiers":[
        {
            "category":"Food & Beverages",
            "subcategory":"Groceries & Convenience Stores",
            "type":"Retail Goods"
        }
    ],
    "sg:phone":"+1 819 778 8558",
    "sg:postcode":"J8Y 3X1",
    "sg:province":"QC",
    "wof:name":"Depanneur Cesar",
    "wof:placetype":"venue"
},
  "geometry": {"coordinates":[-75.733353,45.432884],"type":"Point"}
}