{
  "type": "Feature",
  "properties": {
    "addr:full":"531 Queenston Rd Hamilton ON L8K 1J7",
    "addr:housenumber":"531",
    "addr:postcode":"l8k 1j7",
    "addr:street":"Queenston Rd",
    "iso:country":"CA",
    "sg:address":"531 Queenston Rd",
    "sg:city":"Hamilton",
    "sg:classifiers":[
        {
            "category":"Health Services",
            "subcategory":"Doctor",
            "type":"Services"
        }
    ],
    "sg:phone":"+1 905 560 5680",
    "sg:postcode":"L8K 1J7",
    "sg:province":"ON",
    "sg:tags":[
        "physician",
        "surgeon"
    ],
    "wof:name":"Falletta, Joseph MD",
    "wof:placetype":"venue"
},
  "geometry": {"coordinates":[-79.7785568237,43.2312545776],"type":"Point"}
}