{
  "type": "Feature",
  "properties": {
    "addr:full":"Nipigon ON P0T 2J0",
    "addr:postcode":"p0t 2j0",
    "iso:country":"CA",
    "sg:city":"Nipigon",
    "sg:classifiers":[
        {
            "category":"Travel",
            "subcategory":"Hotels & Motels",
            "type":"Entertainment"
        }
    ],
    "sg:phone":"+1 807 887 2815",
    "sg:postcode":"P0T 2J0",
    "sg:province":"ON",
    "wof:name":"Nipigon River Motel Ltd",
    "wof:placetype":"venue"
},
  "geometry": {"coordinates":[-88.28248596189999,49.020198822],"type":"Point"}
}