{
  "type": "Feature",
  "properties": {
    "addr:full":"19779 56 Ave Langley BC V3A 3X8",
    "addr:housenumber":"19779",
    "addr:postcode":"v3a 3x8",
    "addr:street":"56 Ave",
    "iso:country":"CA",
    "sg:address":"19779 56 Ave",
    "sg:city":"Langley",
    "sg:classifiers":[
        {
            "category":"Professional",
            "type":"Services"
        }
    ],
    "sg:phone":"+1 604 533 5769",
    "sg:postcode":"V3A 3X8",
    "sg:province":"BC",
    "sg:tags":[
        "establishment",
        "landscape",
        "contractor"
    ],
    "wof:name":"Nature's Pleasure Watergardens",
    "wof:placetype":"venue"
},
  "geometry": {"coordinates":[-122.67401886,49.1045379639],"type":"Point"}
}