{
  "type": "Feature",
  "properties": {
    "addr:full":"10 Industrial Way Elmsdale NS B2S 2L4",
    "addr:housenumber":"10",
    "addr:postcode":"b2s 2l4",
    "addr:street":"Industrial Way",
    "iso:country":"CA",
    "sg:address":"10 Industrial Way",
    "sg:city":"Elmsdale",
    "sg:classifiers":[
        {
            "category":"Shopping",
            "subcategory":"Clothing, Apparel, & Fashions",
            "type":"Retail Goods"
        }
    ],
    "sg:phone":"+1 902 883 8882",
    "sg:postcode":"B2S 2L4",
    "sg:province":"NS",
    "sg:tags":[
        "salvage",
        "surplus",
        "merchandise"
    ],
    "wof:name":"Highway 102 Surplus",
    "wof:placetype":"venue"
},
  "geometry": {"coordinates":[-63.5046348572,44.9673805237],"type":"Point"}
}