{
  "type": "Feature",
  "properties": {
    "addr:full":"1465 46E Av Lachine QC H8T 3C5",
    "addr:housenumber":"1465",
    "addr:postcode":"h8t 3c5",
    "addr:street":"46E Av",
    "iso:country":"CA",
    "sg:address":"1465 46E Av",
    "sg:city":"Lachine",
    "sg:classifiers":[
        {
            "category":"Manufacturing",
            "subcategory":"Printing",
            "type":"Manufacturing & Wholesale Goods"
        }
    ],
    "sg:phone":"+1 514 637 2494",
    "sg:postcode":"H8T 3C5",
    "sg:province":"QC",
    "sg:tags":[
        "printer"
    ],
    "wof:name":"Imprimerie Comet Inc",
    "wof:placetype":"venue"
},
  "geometry": {"coordinates":[-73.7098312378,45.4527053833],"type":"Point"}
}