{
  "type": "Feature",
  "properties": {
    "iso:country":"CA",
    "sg:address":"269 Jemima St",
    "sg:city":"Selkirk",
    "sg:classifiers":[
        {
            "category":"Organizations",
            "subcategory":"Religious Organization",
            "type":"Services"
        }
    ],
    "sg:phone":"+1 204 482 3422",
    "sg:postcode":"R1A 1W9",
    "sg:province":"MB",
    "sg:tags":[
        "church"
    ],
    "wof:name":"Notre Dame Catholic Church",
    "wof:placetype":"venue"
},
  "geometry": {"coordinates":[-96.8820266724,50.1396865845],"type":"Point"}
}