{
  "type": "Feature",
  "properties": {
    "addr:full":"22519 Dewdney Trunk Rd Maple Ridge BC V2X 7X7",
    "addr:housenumber":"22519",
    "addr:postcode":"v2x 7x7",
    "addr:street":"Dewdney Trunk Rd",
    "iso:country":"CA",
    "sg:address":"22519 Dewdney Trunk Rd",
    "sg:city":"Maple Ridge",
    "sg:classifiers":[
        {
            "category":"Real Estate",
            "subcategory":"Real Estate Agent",
            "type":"Services"
        }
    ],
    "sg:phone":"+1 604 467 9300",
    "sg:postcode":"V2X 7X7",
    "sg:province":"BC",
    "wof:name":"Coldwell Banker Tri-Tel Realty",
    "wof:placetype":"venue"
},
  "geometry": {"coordinates":[-122.598106,49.220642],"type":"Point"}
}