{
  "type": "Feature",
  "properties": {
    "addr:full":"6750 Rue Marquette Montreal QC H2G 2Y8",
    "addr:housenumber":"6750",
    "addr:postcode":"h2g 2y8",
    "addr:street":"Rue Marquette",
    "iso:country":"CA",
    "sg:address":"6750 Rue Marquette",
    "sg:city":"Montreal",
    "sg:classifiers":[
        {
            "category":"Building & Trades",
            "subcategory":"Electrical",
            "type":"Services"
        }
    ],
    "sg:phone":"+1 514 376 9288",
    "sg:postcode":"H2G 2Y8",
    "sg:province":"QC",
    "sg:tags":[
        "electric",
        "contractor"
    ],
    "wof:name":"Alfonso Frattolillo Electric",
    "wof:placetype":"venue"
},
  "geometry": {"coordinates":[-73.601654,45.544479],"type":"Point"}
}