{
  "type": "Feature",
  "properties": {
    "iso:country":"CA",
    "sg:address":"3320 Miles Rd",
    "sg:city":"Mount Hope",
    "sg:classifiers":[
        {
            "category":"Wholesale",
            "subcategory":"Metals & Minerals",
            "type":"Manufacturing & Wholesale Goods"
        }
    ],
    "sg:phone":"+1 905 679 6999",
    "sg:postcode":"L0R 1W0",
    "sg:province":"ON",
    "sg:tags":[
        "pipe",
        "warehouse"
    ],
    "wof:name":"Interpipe Inc",
    "wof:placetype":"venue"
},
  "geometry": {"coordinates":[-79.8879623413,43.1332244873],"type":"Point"}
}