{
  "type": "Feature",
  "properties": {
    "addr:full":"Edmonton AB T6E 2B3",
    "addr:postcode":"t6e 2b3",
    "iso:country":"CA",
    "sg:city":"Edmonton",
    "sg:classifiers":[
        {
            "category":"Health Services",
            "subcategory":"Chiropractor",
            "type":"Services"
        }
    ],
    "sg:phone":"+1 780 433 7791",
    "sg:postcode":"T6E 2B3",
    "sg:province":"AB",
    "wof:name":"Tuck, P A DC",
    "wof:placetype":"venue"
},
  "geometry": {"coordinates":[-113.51011699999999,53.518284],"type":"Point"}
}