{
  "type": "Feature",
  "properties": {
    "addr:full":"505 Steele St Whitehorse YT Y1A 2E1",
    "addr:housenumber":"505",
    "addr:postcode":"y1a 2e1",
    "addr:street":"Steele St",
    "iso:country":"CA",
    "sg:address":"505 Steele St",
    "sg:city":"Whitehorse",
    "sg:classifiers":[
        {
            "category":"Retail",
            "subcategory":"Car Wash",
            "type":"Services"
        }
    ],
    "sg:phone":"+1 867 633 6135",
    "sg:postcode":"Y1A 2E1",
    "sg:province":"YT",
    "sg:tags":[
        "polishing",
        "automobile",
        "washing",
        "detail",
        "clean"
    ],
    "wof:name":"Pristine Auto Care Inc",
    "wof:placetype":"venue"
},
  "geometry": {"coordinates":[-135.05900600000001,60.719215],"type":"Point"}
}