{
  "type": "Feature",
  "properties": {
    "addr:full":"Main St Pukatawagan MB R0B 1G0",
    "addr:postcode":"r0b 1g0",
    "addr:street":"Main St",
    "iso:country":"CA",
    "sg:address":"Main St",
    "sg:city":"Pukatawagan",
    "sg:classifiers":[
        {
            "category":"Food & Beverages",
            "subcategory":"Groceries & Convenience Stores",
            "type":"Retail Goods"
        }
    ],
    "sg:phone":"+1 204 553 2010",
    "sg:postcode":"R0B 1G0",
    "sg:province":"MB",
    "sg:tags":[
        "grocer"
    ],
    "wof:name":"Akochikan Coop Ltd",
    "wof:placetype":"venue"
},
  "geometry": {"coordinates":[-101.31455200000001,55.74271],"type":"Point"}
}