{
  "type": "Feature",
  "properties": {
    "addr:full":"64 Mcintyre St Nairn Centre ON P0M 2L0",
    "addr:housenumber":"64",
    "addr:postcode":"p0m 2l0",
    "addr:street":"Mcintyre St",
    "iso:country":"CA",
    "sg:address":"64 Mcintyre St",
    "sg:city":"Nairn Centre",
    "sg:classifiers":[
        {
            "category":"Recreation",
            "type":"Entertainment"
        }
    ],
    "sg:phone":"+1 705 869 5366",
    "sg:postcode":"P0M 2L0",
    "sg:province":"ON",
    "sg:tags":[
        "government",
        "hall",
        "auditorium"
    ],
    "wof:name":"Nairn Community Ctr",
    "wof:placetype":"venue"
},
  "geometry": {"coordinates":[-81.58214569090001,46.3340835571],"type":"Point"}
}