{
  "type": "Feature",
  "properties": {
    "addr:full":"120 Rue Principale Saint-Elie QC G0X 2N0",
    "addr:housenumber":"120",
    "addr:postcode":"g0x 2n0",
    "addr:street":"Rue Principale",
    "iso:country":"CA",
    "sg:address":"120 Rue Principale",
    "sg:city":"Saint-Elie",
    "sg:classifiers":[
        {
            "category":"Food & Beverages",
            "subcategory":"Groceries & Convenience Stores",
            "type":"Retail Goods"
        }
    ],
    "sg:phone":"+1 819 221 3200",
    "sg:postcode":"G0X 2N0",
    "sg:province":"QC",
    "sg:tags":[
        "grocer"
    ],
    "wof:name":"Alimentation R Audet",
    "wof:placetype":"venue"
},
  "geometry": {"coordinates":[-72.96221160890001,46.4924659729],"type":"Point"}
}