{
  "type": "Feature",
  "properties": {
    "addr:full":"Nanton AB T0L 1R0",
    "addr:postcode":"t0l 1r0",
    "iso:country":"CA",
    "sg:city":"Nanton",
    "sg:classifiers":[
        {
            "category":"Building & Trades",
            "subcategory":"Plumbing",
            "type":"Services"
        }
    ],
    "sg:phone":"+1 403 646 2138",
    "sg:postcode":"T0L 1R0",
    "sg:province":"AB",
    "sg:tags":[
        "contractor"
    ],
    "wof:name":"Stapley Plumbing & Heating",
    "wof:placetype":"venue"
},
  "geometry": {"coordinates":[-113.771309,50.348495],"type":"Point"}
}