{
  "type": "Feature",
  "properties": {
    "addr:full":"11871 Hammersmith Way Richmond BC V7A 5E5",
    "addr:housenumber":"11871",
    "addr:postcode":"v7a 5e5",
    "addr:street":"Hammersmith Way",
    "iso:country":"CA",
    "sg:address":"11871 Hammersmith Way",
    "sg:city":"Richmond",
    "sg:classifiers":[
        {
            "category":"Wholesale",
            "subcategory":"Groceries",
            "type":"Manufacturing & Wholesale Goods"
        }
    ],
    "sg:phone":"+1 604 277 3302",
    "sg:postcode":"V7A 5E5",
    "sg:province":"BC",
    "sg:tags":[
        "food",
        "product",
        "health",
        "manufacturer"
    ],
    "wof:name":"Organika Health Products Inc",
    "wof:placetype":"venue"
},
  "geometry": {"coordinates":[-123.100739,49.127876],"type":"Point"}
}