{
  "type": "Feature",
  "properties": {
    "addr:full":"Langley BC V2Y 2T5",
    "addr:postcode":"v2y 2t5",
    "iso:country":"CA",
    "sg:city":"Langley",
    "sg:classifiers":[
        {
            "category":"Shopping",
            "subcategory":"Stationery & Office Supplies",
            "type":"Retail Goods"
        }
    ],
    "sg:phone":"+1 604 514 2160",
    "sg:postcode":"V2Y 2T5",
    "sg:province":"BC",
    "wof:name":"Staples",
    "wof:placetype":"venue"
},
  "geometry": {"coordinates":[-122.666245,49.11623],"type":"Point"}
}