{
  "type": "Feature",
  "properties": {
    "addr:full":"671 Carter Rd Bowen Island BC V0N 1G0",
    "addr:housenumber":"671",
    "addr:postcode":"v0n 1g0",
    "addr:street":"Carter Rd",
    "iso:country":"CA",
    "sg:address":"671 Carter Rd",
    "sg:city":"Bowen Island",
    "sg:classifiers":[
        {
            "category":"Education",
            "subcategory":"School",
            "type":"Public Place"
        }
    ],
    "sg:phone":"+1 604 947 9311",
    "sg:postcode":"V0N 1G0",
    "sg:province":"BC",
    "wof:name":"Island Pacific School",
    "wof:placetype":"venue"
},
  "geometry": {"coordinates":[-123.350143,49.380955],"type":"Point"}
}