{
  "type": "Feature",
  "properties": {
    "addr:full":"157 Bridge St Carleton Place ON K7C 2V6",
    "addr:housenumber":"157",
    "addr:postcode":"k7c 2v6",
    "addr:street":"Bridge St",
    "iso:country":"CA",
    "sg:address":"157 Bridge St",
    "sg:city":"Carleton Place",
    "sg:classifiers":[
        {
            "category":"Personal",
            "subcategory":"Beauty Salon",
            "type":"Services"
        }
    ],
    "sg:phone":"+1 613 257 3334",
    "sg:postcode":"K7C 2V6",
    "sg:province":"ON",
    "wof:name":"Marg & Don's Hairstylists",
    "wof:placetype":"venue"
},
  "geometry": {"coordinates":[-76.1462173462,45.1401748657],"type":"Point"}
}