{
  "type": "Feature",
  "properties": {
    "iso:country":"CA",
    "sg:address":"404 Vanburen St",
    "sg:city":"Kemptville",
    "sg:classifiers":[
        {
            "category":"Retail",
            "subcategory":"Auto Repair",
            "type":"Services"
        }
    ],
    "sg:phone":"+1 613 258 0592",
    "sg:postcode":"K0G 1J0",
    "sg:province":"ON",
    "sg:tags":[
        "repairing",
        "automobile"
    ],
    "wof:name":"R T's Small Engine Repairs",
    "wof:placetype":"venue"
},
  "geometry": {"coordinates":[-75.6353302002,45.0177612305],"type":"Point"}
}