{
  "type": "Feature",
  "properties": {
    "addr:full":"North York ON M6B 3Y1",
    "addr:postcode":"m6b 3y1",
    "iso:country":"CA",
    "sg:city":"North York",
    "sg:classifiers":[
        {
            "category":"Manufacturing",
            "subcategory":"Apparel",
            "type":"Manufacturing & Wholesale Goods"
        }
    ],
    "sg:phone":"+1 416 782 1015",
    "sg:postcode":"M6B 3Y1",
    "sg:province":"ON",
    "sg:tags":[
        "cap",
        "hat",
        "millinery"
    ],
    "wof:name":"Cap CO",
    "wof:placetype":"venue"
},
  "geometry": {"coordinates":[-79.46490478520001,43.7044181824],"type":"Point"}
}