{
  "type": "Feature",
  "properties": {
    "iso:country":"CA",
    "sg:address":"3236 Av Francis-Hughes",
    "sg:city":"Laval",
    "sg:classifiers":[
        {
            "category":"Professional",
            "type":"Services"
        }
    ],
    "sg:phone":"+1 450 662 1145",
    "sg:postcode":"H7L 5A7",
    "sg:province":"QC",
    "sg:tags":[
        "establishment",
        "furniture"
    ],
    "wof:name":"Creation Andre Labrecque Inc",
    "wof:placetype":"venue"
},
  "geometry": {"coordinates":[-73.73819,45.59343],"type":"Point"}
}