{
  "type": "Feature",
  "properties": {
    "addr:full":"Bobcaygeon ON K0M 1A0",
    "addr:postcode":"k0m 1a0",
    "iso:country":"CA",
    "sg:city":"Bobcaygeon",
    "sg:classifiers":[
        {
            "category":"Travel",
            "subcategory":"Hotels & Motels",
            "type":"Entertainment"
        }
    ],
    "sg:phone":"+1 705 738 3874",
    "sg:postcode":"K0M 1A0",
    "sg:province":"ON",
    "sg:tags":[
        "cottage",
        "cabin"
    ],
    "wof:name":"Cedars",
    "wof:placetype":"venue"
},
  "geometry": {"coordinates":[-78.53755200000001,44.536301],"type":"Point"}
}