{
  "type": "Feature",
  "properties": {
    "addr:full":"631 Johnson St Victoria BC V8W 1M7",
    "addr:housenumber":"631",
    "addr:postcode":"v8w 1m7",
    "addr:street":"Johnson St",
    "iso:country":"CA",
    "sg:address":"631 Johnson St",
    "sg:city":"Victoria",
    "sg:classifiers":[
        {
            "category":"Shopping",
            "subcategory":"Books",
            "type":"Retail Goods"
        }
    ],
    "sg:phone":"+1 250 384 1656",
    "sg:postcode":"V8W 1M7",
    "sg:province":"BC",
    "sg:tags":[
        "comic",
        "dealer"
    ],
    "wof:name":"Curious Comics",
    "wof:placetype":"venue"
},
  "geometry": {"coordinates":[-123.365982,48.427238],"type":"Point"}
}