{
  "type": "Feature",
  "properties": {
    "addr:full":"9401 Hwy 97 Vernon BC V1H 1W9",
    "addr:housenumber":"9401",
    "addr:postcode":"v1h 1w9",
    "addr:street":"Hwy 97",
    "iso:country":"CA",
    "sg:address":"9401 Hwy 97",
    "sg:city":"Vernon",
    "sg:classifiers":[
        {
            "category":"Sports & Exercise",
            "subcategory":"Golf",
            "type":"Entertainment"
        }
    ],
    "sg:phone":"+1 250 545 5824",
    "sg:postcode":"V1H 1W9",
    "sg:province":"BC",
    "sg:tags":[
        "course"
    ],
    "wof:name":"Spallumcheen Golf Shop",
    "wof:placetype":"venue"
},
  "geometry": {"coordinates":[-119.273743,50.25898],"type":"Point"}
}