{
  "type": "Feature",
  "properties": {
    "addr:full":"Montreal QC H2Z 1J6",
    "addr:postcode":"h2z 1j6",
    "iso:country":"CA",
    "sg:city":"Montreal",
    "sg:classifiers":[
        {
            "category":"Retail",
            "subcategory":"Photofinishing",
            "type":"Services"
        }
    ],
    "sg:phone":"+1 514 874 0875",
    "sg:postcode":"H2Z 1J6",
    "sg:province":"QC",
    "sg:tags":[
        "photo",
        "finishing"
    ],
    "wof:name":"Photo Phuong",
    "wof:placetype":"venue"
},
  "geometry": {"coordinates":[-73.560005,45.508324],"type":"Point"}
}