{
  "type": "Feature",
  "properties": {
    "addr:full":"104 2nd Ave NW Geraldton ON P0T 1M0",
    "addr:housenumber":"104",
    "addr:postcode":"p0t 1m0",
    "addr:street":"2Nd Ave Nw",
    "iso:country":"CA",
    "sg:address":"104 2nd Ave NW",
    "sg:city":"Geraldton",
    "sg:classifiers":[
        {
            "category":"Organizations",
            "subcategory":"Religious Organization",
            "type":"Services"
        }
    ],
    "sg:phone":"+1 807 854 0849",
    "sg:postcode":"P0T 1M0",
    "sg:province":"ON",
    "sg:tags":[
        "church"
    ],
    "wof:name":"St Theresa's Parish",
    "wof:placetype":"venue"
},
  "geometry": {"coordinates":[-86.950203,49.727646],"type":"Point"}
}