{
  "type": "Feature",
  "properties": {
    "addr:full":"Saint-Jean-Port-Joli QC G0R 3G0",
    "addr:postcode":"g0r 3g0",
    "iso:country":"CA",
    "sg:city":"Saint-Jean-Port-Joli",
    "sg:classifiers":[
        {
            "category":"Personal",
            "subcategory":"Beauty Salon",
            "type":"Services"
        }
    ],
    "sg:phone":"+1 418 598 6848",
    "sg:postcode":"G0R 3G0",
    "sg:province":"QC",
    "wof:name":"Salon DE Coiffure Bel-Isa",
    "wof:placetype":"venue"
},
  "geometry": {"coordinates":[-70.26518249510001,47.2165374756],"type":"Point"}
}