{
  "type": "Feature",
  "properties": {
    "addr:full":"4367 London Line Wyoming ON N0N 1T0",
    "addr:housenumber":"4367",
    "addr:postcode":"n0n 1t0",
    "addr:street":"London Line",
    "iso:country":"CA",
    "sg:address":"4367 London Line",
    "sg:city":"Wyoming",
    "sg:classifiers":[
        {
            "category":"Autos & Motor Vehicles",
            "subcategory":"Recreational Vehicle Sales",
            "type":"Retail Goods"
        }
    ],
    "sg:phone":"+1 519 845 3925",
    "sg:postcode":"N0N 1T0",
    "sg:province":"ON",
    "wof:name":"Jim White Trailer Sales Inc",
    "wof:placetype":"venue"
},
  "geometry": {"coordinates":[-82.1288757324,42.9797554016],"type":"Point"}
}