{
  "type": "Feature",
  "properties": {
    "addr:full":"438 Rue Mcgill Montreal QC H2Y 2G1",
    "addr:housenumber":"438",
    "addr:postcode":"h2y 2g1",
    "addr:street":"Rue Mcgill",
    "iso:country":"CA",
    "sg:address":"438 Rue Mcgill",
    "sg:city":"Montreal",
    "sg:classifiers":[
        {
            "category":"Professional",
            "subcategory":"Computer Services",
            "type":"Services"
        }
    ],
    "sg:phone":"+1 514 866 3000",
    "sg:postcode":"H2Y 2G1",
    "sg:province":"QC",
    "sg:tags":[
        "information",
        "system",
        "consultant"
    ],
    "wof:name":"Idcad Svc Conseils",
    "wof:placetype":"venue"
},
  "geometry": {"coordinates":[-73.55819700000001,45.500431],"type":"Point"}
}