{
  "type": "Feature",
  "properties": {
    "iso:country":"CA",
    "sg:address":"5040 Av Beaconsfield",
    "sg:city":"Montreal",
    "sg:classifiers":[
        {
            "category":"Professional",
            "subcategory":"Art Services",
            "type":"Services"
        }
    ],
    "sg:phone":"+1 514 487 8512",
    "sg:postcode":"H3X 3R6",
    "sg:province":"QC",
    "sg:tags":[
        "graphic",
        "designer"
    ],
    "wof:name":"Amigraph Design & Illustration",
    "wof:placetype":"venue"
},
  "geometry": {"coordinates":[-73.63748168950001,45.4738273621],"type":"Point"}
}