{
  "type": "Feature",
  "properties": {
    "addr:full":"10145 Rue Lajeunesse Montreal QC H3L 2E3",
    "addr:housenumber":"10145",
    "addr:postcode":"h3l 2e3",
    "addr:street":"Rue Lajeunesse",
    "iso:country":"CA",
    "sg:address":"10145 Rue Lajeunesse",
    "sg:city":"Montreal",
    "sg:classifiers":[
        {
            "category":"Restaurant",
            "type":"Food & Drink"
        }
    ],
    "sg:phone":"+1 514 382 8234",
    "sg:postcode":"H3L 2E3",
    "sg:province":"QC",
    "wof:name":"Fonderie",
    "wof:placetype":"venue"
},
  "geometry": {"coordinates":[-73.659615,45.552891],"type":"Point"}
}