{
  "type": "Feature",
  "properties": {
    "iso:country":"CA",
    "sg:address":"34 Elgin St",
    "sg:city":"St Catharines",
    "sg:classifiers":[
        {
            "category":"Organizations",
            "subcategory":"Religious Organization",
            "type":"Services"
        }
    ],
    "sg:phone":"+1 905 934 1170",
    "sg:postcode":"L2N 5G5",
    "sg:province":"ON",
    "sg:tags":[
        "church"
    ],
    "wof:name":"Star of the Sea Church",
    "wof:placetype":"venue"
},
  "geometry": {"coordinates":[-79.27337646479999,43.1996498108],"type":"Point"}
}