{
  "type": "Feature",
  "properties": {
    "addr:full":"Sioux Narrows ON P0X 1N0",
    "addr:postcode":"p0x 1n0",
    "iso:country":"CA",
    "sg:city":"Sioux Narrows",
    "sg:classifiers":[
        {
            "category":"Social Services",
            "type":"Services"
        }
    ],
    "sg:phone":"+1 807 226 1081",
    "sg:postcode":"P0X 1N0",
    "sg:province":"ON",
    "sg:tags":[
        "organization",
        "welfare"
    ],
    "wof:name":"Sioux Narrows Nursing Station",
    "wof:placetype":"venue"
},
  "geometry": {"coordinates":[-94.096069,49.419025],"type":"Point"}
}