{
  "type": "Feature",
  "properties": {
    "addr:full":"21 Dundas Sq Toronto ON M5B 1B7",
    "addr:housenumber":"21",
    "addr:postcode":"m5b 1b7",
    "addr:street":"Dundas Sq",
    "iso:country":"CA",
    "sg:address":"21 Dundas Sq",
    "sg:city":"Toronto",
    "sg:classifiers":[
        {
            "category":"Shopping",
            "subcategory":"Jewelry",
            "type":"Retail Goods"
        }
    ],
    "sg:phone":"+1 416 363 7073",
    "sg:postcode":"M5B 1B7",
    "sg:province":"ON",
    "sg:tags":[
        "jeweler"
    ],
    "wof:name":"Donald Mac Kay Gemologist",
    "wof:placetype":"venue"
},
  "geometry": {"coordinates":[-79.37989,43.655834],"type":"Point"}
}