{
  "type": "Feature",
  "properties": {
    "iso:country":"CA",
    "sg:address":"430 Bathurst St",
    "sg:city":"Toronto",
    "sg:classifiers":[
        {
            "category":"Retail",
            "subcategory":"Auto Repair",
            "type":"Services"
        }
    ],
    "sg:phone":"+1 416 924 1191",
    "sg:postcode":"M5T 2S6",
    "sg:province":"ON",
    "sg:tags":[
        "body",
        "automobile",
        "painting"
    ],
    "wof:name":"Sunnyside Auto Ltd",
    "wof:placetype":"venue"
},
  "geometry": {"coordinates":[-79.4071807861,43.6546897888],"type":"Point"}
}