{
  "type": "Feature",
  "properties": {
    "addr:full":"1621 Boul Gaboury Mont-Joli QC G5H 3H9",
    "addr:housenumber":"1621",
    "addr:postcode":"g5h 3h9",
    "addr:street":"Boul Gaboury",
    "iso:country":"CA",
    "sg:address":"1621 Boul Gaboury",
    "sg:city":"Mont-Joli",
    "sg:classifiers":[
        {
            "category":"Health Services",
            "subcategory":"Chiropractor",
            "type":"Services"
        }
    ],
    "sg:phone":"+1 418 775 2133",
    "sg:postcode":"G5H 3H9",
    "sg:province":"QC",
    "wof:name":"Clinique Chiropratique",
    "wof:placetype":"venue"
},
  "geometry": {"coordinates":[-68.1913223267,48.5828971863],"type":"Point"}
}