{
  "type": "Feature",
  "properties": {
    "addr:full":"9320 Boul Saint-Laurent Montreal QC H2N 1N7",
    "addr:housenumber":"9320",
    "addr:postcode":"h2n 1n7",
    "addr:street":"Boul Saint-Laurent",
    "iso:country":"CA",
    "sg:address":"9320 Boul Saint-Laurent",
    "sg:city":"Montreal",
    "sg:classifiers":[
        {
            "category":"Manufacturing",
            "subcategory":"Apparel",
            "type":"Manufacturing & Wholesale Goods"
        }
    ],
    "sg:phone":"+1 514 382 7777",
    "sg:postcode":"H2N 1N7",
    "sg:province":"QC",
    "sg:tags":[
        "clothing"
    ],
    "wof:name":"Belle International",
    "wof:placetype":"venue"
},
  "geometry": {"coordinates":[-73.6517410278,45.5444831848],"type":"Point"}
}