{
  "type": "Feature",
  "properties": {
    "iso:country":"CA",
    "sg:city":"Saint-Gervais",
    "sg:classifiers":[
        {
            "category":"Wholesale",
            "subcategory":"Machinery & Supplies",
            "type":"Manufacturing & Wholesale Goods"
        }
    ],
    "sg:phone":"+1 418 887 3307",
    "sg:postcode":"G0R 3C0",
    "sg:province":"QC",
    "sg:tags":[
        "farm",
        "equipment"
    ],
    "wof:name":"Entreprises Martineau Inc",
    "wof:placetype":"venue"
},
  "geometry": {"coordinates":[-70.890625,46.7163200378],"type":"Point"}
}