{
  "type": "Feature",
  "properties": {
    "addr:full":"Calgary AB T3K 2A8",
    "addr:postcode":"t3k 2a8",
    "iso:country":"CA",
    "sg:city":"Calgary",
    "sg:classifiers":[
        {
            "category":"Shopping",
            "subcategory":"Jewelry",
            "type":"Retail Goods"
        }
    ],
    "sg:phone":"+1 403 274 4458",
    "sg:postcode":"T3K 2A8",
    "sg:province":"AB",
    "sg:tags":[
        "jeweler"
    ],
    "wof:name":"T & T Jewellers",
    "wof:placetype":"venue"
},
  "geometry": {"coordinates":[-114.07295227,51.1254081726],"type":"Point"}
}