{
  "type": "Feature",
  "properties": {
    "addr:full":"Prince George BC V2N 4K3",
    "addr:postcode":"v2n 4k3",
    "iso:country":"CA",
    "sg:city":"Prince George",
    "sg:classifiers":[
        {
            "category":"Personal",
            "subcategory":"Tanning Parlor",
            "type":"Services"
        }
    ],
    "sg:phone":"+1 250 563 1010",
    "sg:postcode":"V2N 4K3",
    "sg:province":"BC",
    "sg:tags":[
        "salon"
    ],
    "wof:name":"Awesome Tan",
    "wof:placetype":"venue"
},
  "geometry": {"coordinates":[-122.77977752699999,53.8892326355],"type":"Point"}
}