{
  "type": "Feature",
  "properties": {
    "addr:full":"Chetwynd BC V0C 1J0",
    "addr:postcode":"bc v0c 1j0",
    "iso:country":"CA",
    "sg:city":"Chetwynd",
    "sg:classifiers":[
        {
            "category":"Wholesale",
            "subcategory":"Construction Materials",
            "type":"Manufacturing & Wholesale Goods"
        }
    ],
    "sg:phone":"+1 250 788 9499",
    "sg:postcode":"V0C 1J0",
    "sg:province":"BC",
    "sg:tags":[
        "sand",
        "gravel"
    ],
    "wof:name":"Pine River Holdings Ltd",
    "wof:placetype":"venue"
},
  "geometry": {"coordinates":[-121.615493774,55.7051124573],"type":"Point"}
}