{
  "type": "Feature",
  "properties": {
    "addr:full":"3119 Petawawa Blvd Petawawa ON K8H 1X9",
    "addr:housenumber":"3119",
    "addr:postcode":"k8h 1x9",
    "addr:street":"Petawawa Blvd",
    "iso:country":"CA",
    "sg:address":"3119 Petawawa Blvd",
    "sg:city":"Petawawa",
    "sg:classifiers":[
        {
            "category":"Restaurant",
            "type":"Food & Drink"
        }
    ],
    "sg:phone":"+1 613 687 0841",
    "sg:postcode":"K8H 1X9",
    "sg:province":"ON",
    "wof:name":"Kelsey's",
    "wof:placetype":"venue"
},
  "geometry": {"coordinates":[-77.2660903931,45.8910675049],"type":"Point"}
}