{
  "type": "Feature",
  "properties": {
    "addr:full":"11418 89 Ave Grande Prairie AB T8V 5V8",
    "addr:housenumber":"11418",
    "addr:postcode":"t8v 5v8",
    "addr:street":"89 Ave",
    "iso:country":"CA",
    "sg:address":"11418 89 Ave",
    "sg:city":"Grande Prairie",
    "sg:classifiers":[
        {
            "category":"Mining & Drilling",
            "type":"Manufacturing & Wholesale Goods"
        }
    ],
    "sg:phone":"+1 780 539 5554",
    "sg:postcode":"T8V 5V8",
    "sg:province":"AB",
    "sg:tags":[
        "equipment",
        "field",
        "oil",
        "well",
        "supply"
    ],
    "wof:name":"Smith Services Completion Syst",
    "wof:placetype":"venue"
},
  "geometry": {"coordinates":[-118.840996,55.159176],"type":"Point"}
}