{
  "type": "Feature",
  "properties": {
    "addr:full":"1083 Knottwood Road East NW Edmonton AB T6K 3N5",
    "addr:housenumber":"1083",
    "addr:postcode":"t6k 3n5",
    "addr:street":"Knottwood Road East Nw",
    "iso:country":"CA",
    "sg:address":"1083 Knottwood Road East NW",
    "sg:city":"Edmonton",
    "sg:classifiers":[
        {
            "category":"Food & Beverages",
            "subcategory":"Bakery",
            "type":"Retail Goods"
        }
    ],
    "sg:phone":"+1 780 450 1319",
    "sg:postcode":"T6K 3N5",
    "sg:province":"AB",
    "sg:tags":[
        "baker"
    ],
    "wof:name":"Rolymie Bakery",
    "wof:placetype":"venue"
},
  "geometry": {"coordinates":[-113.442993,53.44487],"type":"Point"}
}