{
  "type": "Feature",
  "properties": {
    "iso:country":"CA",
    "sg:city":"Vernon",
    "sg:classifiers":[
        {
            "category":"Personal",
            "subcategory":"Beauty Salon",
            "type":"Services"
        }
    ],
    "sg:phone":"+1 250 545 0776",
    "sg:postcode":"V1T 7E3",
    "sg:province":"BC",
    "wof:name":"Unicorn Hairdesign",
    "wof:placetype":"venue"
},
  "geometry": {"coordinates":[-119.262809753,50.256313324],"type":"Point"}
}