{
  "type": "Feature",
  "properties": {
    "addr:full":"1235 Cumberland St Cornwall ON K6J 4K6",
    "addr:housenumber":"1235",
    "addr:postcode":"k6j 4k6",
    "addr:street":"Cumberland St",
    "iso:country":"CA",
    "sg:address":"1235 Cumberland St",
    "sg:city":"Cornwall",
    "sg:classifiers":[
        {
            "category":"Manufacturing",
            "subcategory":"Toys & Sporting Goods",
            "type":"Manufacturing & Wholesale Goods"
        }
    ],
    "sg:phone":"+1 613 932 3474",
    "sg:postcode":"K6J 4K6",
    "sg:province":"ON",
    "sg:tags":[
        "tackle",
        "fishing"
    ],
    "wof:name":"Jiggernaut Tackle CO",
    "wof:placetype":"venue"
},
  "geometry": {"coordinates":[-74.745773,45.030033],"type":"Point"}
}