{
  "type": "Feature",
  "properties": {
    "addr:full":"882 Tower St S Fergus ON N1M 3N7",
    "addr:housenumber":"882",
    "addr:postcode":"n1m 3n7",
    "addr:street":"Tower St S",
    "iso:country":"CA",
    "sg:address":"882 Tower St S",
    "sg:city":"Fergus",
    "sg:classifiers":[
        {
            "category":"Shopping",
            "type":"Retail Goods"
        }
    ],
    "sg:phone":"+1 519 843 7997",
    "sg:postcode":"N1M 3N7",
    "sg:province":"ON",
    "sg:tags":[
        "pet",
        "food",
        "supply"
    ],
    "wof:name":"Pet Valu",
    "wof:placetype":"venue"
},
  "geometry": {"coordinates":[-80.363571167,43.6940193176],"type":"Point"}
}