{
  "type": "Feature",
  "properties": {
    "addr:full":"1141 Highbury Ave N London ON N5Y 1A5",
    "addr:housenumber":"1141",
    "addr:postcode":"n5y 1a5",
    "addr:street":"Highbury Ave N",
    "iso:country":"CA",
    "sg:address":"1141 Highbury Ave N",
    "sg:city":"London",
    "sg:classifiers":[
        {
            "category":"Shopping",
            "subcategory":"Photographic Equipment",
            "type":"Retail Goods"
        }
    ],
    "sg:phone":"+1 519 455 3522",
    "sg:postcode":"N5Y 1A5",
    "sg:province":"ON",
    "sg:tags":[
        "photo",
        "finishing"
    ],
    "wof:name":"Fast Photo",
    "wof:placetype":"venue"
},
  "geometry": {"coordinates":[-81.212379,43.013737],"type":"Point"}
}