{
  "type": "Feature",
  "properties": {
    "addr:full":"202 Richmond St Charlottetown PE C1A 1J2",
    "addr:housenumber":"202",
    "addr:postcode":"c1a 1j2",
    "addr:street":"Richmond St",
    "iso:country":"CA",
    "sg:address":"202 Richmond St",
    "sg:city":"Charlottetown",
    "sg:classifiers":[
        {
            "category":"Government",
            "subcategory":"Office",
            "type":"Public Place"
        }
    ],
    "sg:phone":"+1 902 368 4606",
    "sg:postcode":"C1A 1J2",
    "sg:province":"PE",
    "wof:name":"P E Systems & Technology Svc",
    "wof:placetype":"venue"
},
  "geometry": {"coordinates":[-63.124786,46.235008],"type":"Point"}
}