{
  "type": "Feature",
  "properties": {
    "addr:full":"9620 Mcnaughton Line RR 1 Chatham ON N7M 5J1",
    "addr:housenumber":"9620",
    "addr:postcode":"n7m 5j1",
    "addr:street":"Mcnaughton Line Rr 1",
    "iso:country":"CA",
    "sg:address":"9620 Mcnaughton Line RR 1",
    "sg:city":"Chatham",
    "sg:classifiers":[
        {
            "category":"Building & Trades",
            "subcategory":"Landscaping Services",
            "type":"Services"
        }
    ],
    "sg:phone":"+1 519 355 1035",
    "sg:postcode":"N7M 5J1",
    "sg:province":"ON",
    "sg:tags":[
        "lawn",
        "contractor",
        "landscape",
        "maintenance",
        "grounds"
    ],
    "wof:name":"Lawnscapes",
    "wof:placetype":"venue"
},
  "geometry": {"coordinates":[-82.189583,42.404446],"type":"Point"}
}