{
  "type": "Feature",
  "properties": {
    "iso:country":"CA",
    "sg:address":"450 3rd St NW",
    "sg:city":"Portage LA Prairie",
    "sg:classifiers":[
        {
            "category":"Social Services",
            "type":"Services"
        }
    ],
    "sg:phone":"+1 204 857 3091",
    "sg:postcode":"R1N 3Y1",
    "sg:province":"MB",
    "sg:tags":[
        "information",
        "organization",
        "treatment",
        "alcoholism",
        "welfare"
    ],
    "wof:name":"Aa/Alanon",
    "wof:placetype":"venue"
},
  "geometry": {"coordinates":[-98.2937469482,49.9799957275],"type":"Point"}
}