{
  "type": "Feature",
  "properties": {
    "addr:full":"Willow Bunch SK S0H 4K0",
    "addr:postcode":"s0h 4k0",
    "iso:country":"CA",
    "sg:city":"Willow Bunch",
    "sg:classifiers":[
        {
            "category":"Museum",
            "type":"Entertainment"
        }
    ],
    "sg:phone":"+1 306 473 2806",
    "sg:postcode":"S0H 4K0",
    "sg:province":"SK",
    "wof:name":"Willow Bunch Museum & Heritage",
    "wof:placetype":"venue"
},
  "geometry": {"coordinates":[-105.638267517,49.3918151855],"type":"Point"}
}