{
  "type": "Feature",
  "properties": {
    "addr:full":"15 King St E Bowmanville ON L1C 1N1",
    "addr:housenumber":"15",
    "addr:postcode":"l1c 1n1",
    "addr:street":"King St",
    "iso:country":"CA",
    "sg:address":"15 King St E",
    "sg:city":"Bowmanville",
    "sg:classifiers":[
        {
            "category":"Shopping",
            "subcategory":"Gifts & Souvenirs",
            "type":"Retail Goods"
        }
    ],
    "sg:phone":"+1 905 697 5840",
    "sg:postcode":"L1C 1N1",
    "sg:province":"ON",
    "sg:tags":[
        "shop",
        "collectible"
    ],
    "wof:name":"Gift Hunter",
    "wof:placetype":"venue"
},
  "geometry": {"coordinates":[-78.688751,43.912022],"type":"Point"}
}