{
  "type": "Feature",
  "properties": {
    "addr:full":"530 Rue Maurice-Bois Vanier QC G1M 3G3",
    "addr:housenumber":"530",
    "addr:postcode":"g1m 3g3",
    "addr:street":"Rue Maurice-Bois",
    "iso:country":"CA",
    "sg:address":"530 Rue Maurice-Bois",
    "sg:city":"Vanier",
    "sg:classifiers":[
        {
            "category":"Building & Trades",
            "subcategory":"Equipment Rental",
            "type":"Services"
        }
    ],
    "sg:phone":"+1 418 686 1130",
    "sg:postcode":"G1M 3G3",
    "sg:province":"QC",
    "sg:tags":[
        "contractor"
    ],
    "wof:name":"Equipement Manuquip",
    "wof:placetype":"venue"
},
  "geometry": {"coordinates":[-71.278351,46.819897],"type":"Point"}
}