{
  "type": "Feature",
  "properties": {
    "addr:full":"54 Skeena St Kitimat BC V8C 1Y9",
    "addr:housenumber":"54",
    "addr:postcode":"bc v8c 1y9",
    "addr:street":"Skeena St",
    "iso:country":"CA",
    "sg:address":"54 Skeena St",
    "sg:city":"Kitimat",
    "sg:classifiers":[
        {
            "category":"Professional",
            "subcategory":"Business Services",
            "type":"Services"
        }
    ],
    "sg:phone":"+1 250 632 7555",
    "sg:postcode":"V8C 1Y9",
    "sg:province":"BC",
    "wof:name":"Aurora Charters Water Taxi Svc",
    "wof:placetype":"venue"
},
  "geometry": {"coordinates":[-128.65864563,54.0476608276],"type":"Point"}
}