{
  "type": "Feature",
  "properties": {
    "addr:full":"112 Prince Edward St Brighton ON K0K 1H0",
    "addr:housenumber":"112",
    "addr:postcode":"k0k 1h0",
    "addr:street":"Prince Edward St",
    "iso:country":"CA",
    "sg:address":"112 Prince Edward St",
    "sg:city":"Brighton",
    "sg:classifiers":[
        {
            "category":"Home & Garden",
            "subcategory":"Furniture",
            "type":"Retail Goods"
        }
    ],
    "sg:phone":"+1 613 475 0570",
    "sg:postcode":"K0K 1H0",
    "sg:province":"ON",
    "sg:tags":[
        "equipment",
        "kitchen",
        "cabinet"
    ],
    "wof:name":"Greg Peake Wood Products",
    "wof:placetype":"venue"
},
  "geometry": {"coordinates":[-77.734116,44.035496],"type":"Point"}
}