{
  "type": "Feature",
  "properties": {
    "addr:full":"225 Boul Sir-Wilfrid-Laurier Saint-Basile-Le-Grand QC J3N 1M2",
    "addr:housenumber":"225",
    "addr:postcode":"j3n 1m2",
    "addr:street":"Boul Sir-Wilfrid-Laurier",
    "iso:country":"CA",
    "sg:address":"225 Boul Sir-Wilfrid-Laurier",
    "sg:city":"Saint-Basile-Le-Grand",
    "sg:classifiers":[
        {
            "category":"Autos & Motor Vehicles",
            "subcategory":"Automobile Sales",
            "type":"Retail Goods"
        }
    ],
    "sg:phone":"+1 450 653 0114",
    "sg:postcode":"J3N 1M2",
    "sg:province":"QC",
    "sg:tags":[
        "car",
        "dealer"
    ],
    "wof:name":"Garage Dodge-Chrysler Basile",
    "wof:placetype":"venue"
},
  "geometry": {"coordinates":[-73.294167,45.5275],"type":"Point"}
}