{
  "type": "Feature",
  "properties": {
    "iso:country":"CA",
    "sg:address":"196679 19th Line",
    "sg:city":"Lakeside",
    "sg:classifiers":[
        {
            "category":"Wholesale",
            "subcategory":"Machinery & Supplies",
            "type":"Manufacturing & Wholesale Goods"
        }
    ],
    "sg:phone":"+1 519 349 2075",
    "sg:postcode":"N0M 2G0",
    "sg:province":"ON",
    "sg:tags":[
        "farm",
        "equipment"
    ],
    "wof:name":"Sunova Implement Ltd",
    "wof:placetype":"venue"
},
  "geometry": {"coordinates":[-81.024520874,43.2020874023],"type":"Point"}
}