{
  "type": "Feature",
  "properties": {
    "addr:full":"Thetford Mines QC G6G 1J4",
    "addr:postcode":"g6g 1j4",
    "iso:country":"CA",
    "sg:city":"Thetford Mines",
    "sg:classifiers":[
        {
            "category":"Banks & Credit Unions",
            "subcategory":"Bank",
            "type":"Services"
        }
    ],
    "sg:phone":"+1 418 335 7536",
    "sg:postcode":"G6G 1J4",
    "sg:province":"QC",
    "wof:name":"Banque Royale",
    "wof:placetype":"venue"
},
  "geometry": {"coordinates":[-71.30206298829999,46.08934021],"type":"Point"}
}