{
  "type": "Feature",
  "properties": {
    "addr:full":"106 Prudent Cloutier Mont-Saint-Pierre QC G0E 1V0",
    "addr:housenumber":"106",
    "addr:postcode":"g0e 1v0",
    "addr:street":"Prudent Cloutier",
    "iso:country":"CA",
    "sg:address":"106 Prudent Cloutier",
    "sg:city":"Mont-Saint-Pierre",
    "sg:classifiers":[
        {
            "category":"Shopping",
            "subcategory":"Gifts & Souvenirs",
            "type":"Retail Goods"
        }
    ],
    "sg:phone":"+1 418 797 5033",
    "sg:postcode":"G0E 1V0",
    "sg:province":"QC",
    "sg:tags":[
        "shop"
    ],
    "wof:name":"Transports LA Coulombe Inc",
    "wof:placetype":"venue"
},
  "geometry": {"coordinates":[-65.79894299999999,49.223385],"type":"Point"}
}