{
  "type": "Feature",
  "properties": {
    "addr:full":"2189 Weston Rd York ON M9N 1X9",
    "addr:housenumber":"2189",
    "addr:postcode":"m9n 1x9",
    "addr:street":"Weston Rd",
    "iso:country":"CA",
    "sg:address":"2189 Weston Rd",
    "sg:city":"York",
    "sg:classifiers":[
        {
            "category":"Food & Beverages",
            "subcategory":"Groceries & Convenience Stores",
            "type":"Retail Goods"
        }
    ],
    "sg:phone":"+1 416 240 0655",
    "sg:postcode":"M9N 1X9",
    "sg:province":"ON",
    "sg:tags":[
        "grocer"
    ],
    "wof:name":"Parks Supermarket",
    "wof:placetype":"venue"
},
  "geometry": {"coordinates":[-79.525772,43.703358],"type":"Point"}
}