{
  "type": "Feature",
  "properties": {
    "addr:full":"64 St. Peters Rd Charlottetown PE C1A 5N8",
    "addr:housenumber":"64",
    "addr:postcode":"c1a 5n8",
    "addr:street":"St. Peters Rd",
    "iso:country":"CA",
    "sg:address":"64 St. Peters Rd",
    "sg:city":"Charlottetown",
    "sg:classifiers":[
        {
            "category":"Shopping",
            "subcategory":"Stationery & Office Supplies",
            "type":"Retail Goods"
        }
    ],
    "sg:phone":"+1 902 566 9700",
    "sg:postcode":"C1A 5N8",
    "sg:province":"PE",
    "sg:tags":[
        "equipment",
        "furniture",
        "system",
        "filing"
    ],
    "wof:name":"Atlantic Business Interiors",
    "wof:placetype":"venue"
},
  "geometry": {"coordinates":[-63.12151,46.251469],"type":"Point"}
}