{
  "type": "Feature",
  "properties": {
    "addr:full":"North Vancouver BC V7M 3H6",
    "addr:postcode":"v7m 3h6",
    "iso:country":"CA",
    "sg:city":"North Vancouver",
    "sg:classifiers":[
        {
            "category":"Health Services",
            "subcategory":"Doctor",
            "type":"Services"
        }
    ],
    "sg:phone":"+1 604 988 2520",
    "sg:postcode":"V7M 3H6",
    "sg:province":"BC",
    "sg:tags":[
        "physician",
        "surgeon"
    ],
    "wof:name":"Belmond Medical Holdings Ltd",
    "wof:placetype":"venue"
},
  "geometry": {"coordinates":[-123.072296143,49.3190574646],"type":"Point"}
}