{
  "type": "Feature",
  "properties": {
    "addr:full":"5551 Duncan Bay Rd Campbell River BC V9H 1N6",
    "addr:housenumber":"5551",
    "addr:postcode":"v9h 1n6",
    "addr:street":"Duncan Bay Rd",
    "iso:country":"CA",
    "sg:address":"5551 Duncan Bay Rd",
    "sg:city":"Campbell River",
    "sg:classifiers":[
        {
            "category":"Wholesale",
            "subcategory":"Scrap",
            "type":"Manufacturing & Wholesale Goods"
        }
    ],
    "sg:phone":"+1 250 287 8748",
    "sg:postcode":"V9H 1N6",
    "sg:province":"BC",
    "sg:tags":[
        "recycling",
        "center"
    ],
    "wof:name":"Budget Steel Ltd",
    "wof:placetype":"venue"
},
  "geometry": {"coordinates":[-125.31391143800001,50.0802192688],"type":"Point"}
}