{
  "type": "Feature",
  "properties": {
    "addr:full":"1833 Crowchild Trail NW Calgary AB T2M 4S7",
    "addr:housenumber":"1833",
    "addr:postcode":"t2m 4s7",
    "addr:street":"Crowchild Trail Nw",
    "iso:country":"CA",
    "sg:address":"1833 Crowchild Trail NW",
    "sg:city":"Calgary",
    "sg:classifiers":[
        {
            "category":"Professional",
            "subcategory":"Business Services",
            "type":"Services"
        }
    ],
    "sg:phone":"+1 403 220 7101",
    "sg:postcode":"T2M 4S7",
    "sg:province":"AB",
    "sg:tags":[
        "convention",
        "meeting",
        "facility"
    ],
    "wof:name":"Olympic Volunteer Ctr",
    "wof:placetype":"venue"
},
  "geometry": {"coordinates":[-114.118247986,51.0711784363],"type":"Point"}
}