{
  "type": "Feature",
  "properties": {
    "addr:full":"206 Main St Dinsmore SK S0L 0T0",
    "addr:housenumber":"206",
    "addr:postcode":"s0l 0t0",
    "addr:street":"Main St",
    "iso:country":"CA",
    "sg:address":"206 Main St",
    "sg:city":"Dinsmore",
    "sg:classifiers":[
        {
            "category":"Personal",
            "subcategory":"Beauty Salon",
            "type":"Services"
        }
    ],
    "sg:phone":"+1 306 846 2247",
    "sg:postcode":"S0L 0T0",
    "sg:province":"SK",
    "wof:name":"Bev's Hair Ctr",
    "wof:placetype":"venue"
},
  "geometry": {"coordinates":[-107.44826500000001,51.329094],"type":"Point"}
}