{
  "type": "Feature",
  "properties": {
    "addr:full":"329 Moneta Ave Timmins ON P4N 7C9",
    "addr:housenumber":"329",
    "addr:postcode":"p4n 7c9",
    "addr:street":"Moneta Ave",
    "iso:country":"CA",
    "sg:address":"329 Moneta Ave",
    "sg:city":"Timmins",
    "sg:classifiers":[
        {
            "category":"Retail",
            "subcategory":"Auto Repair",
            "type":"Services"
        }
    ],
    "sg:phone":"+1 705 268 0802",
    "sg:postcode":"P4N 7C9",
    "sg:province":"ON",
    "sg:tags":[
        "body",
        "automobile",
        "painting"
    ],
    "wof:name":"Timmins Collision Ctr Ltd",
    "wof:placetype":"venue"
},
  "geometry": {"coordinates":[-81.3271560669,48.4659881592],"type":"Point"}
}