{
  "type": "Feature",
  "properties": {
    "addr:full":"Scarborough ON M1V 5K5",
    "addr:postcode":"m1v 5k5",
    "iso:country":"CA",
    "sg:city":"Scarborough",
    "sg:classifiers":[
        {
            "category":"Home & Garden",
            "subcategory":"Furniture",
            "type":"Retail Goods"
        }
    ],
    "sg:phone":"+1 416 335 0267",
    "sg:postcode":"M1V 5K5",
    "sg:province":"ON",
    "wof:name":"Franco's Furniture",
    "wof:placetype":"venue"
},
  "geometry": {"coordinates":[-79.29410552980001,43.8183403015],"type":"Point"}
}