{
  "type": "Feature",
  "properties": {
    "iso:country":"CA",
    "sg:address":"79 School St",
    "sg:city":"Glace Bay",
    "sg:classifiers":[
        {
            "category":"Bus Charters",
            "type":"Transportation"
        }
    ],
    "sg:phone":"+1 902 842 0441",
    "sg:postcode":"B1A 1J3",
    "sg:province":"NS",
    "sg:tags":[
        "rental"
    ],
    "wof:name":"Island Shuttle",
    "wof:placetype":"venue"
},
  "geometry": {"coordinates":[-59.9583892822,46.184135437],"type":"Point"}
}