{
  "type": "Feature",
  "properties": {
    "addr:full":"541 Rue Frontiere Hemmingford QC J0L 1H0",
    "addr:housenumber":"541",
    "addr:postcode":"j0l 1h0",
    "addr:street":"Rue Frontiere",
    "iso:country":"CA",
    "sg:address":"541 Rue Frontiere",
    "sg:city":"Hemmingford",
    "sg:classifiers":[
        {
            "category":"Organizations",
            "subcategory":"Religious Organization",
            "type":"Services"
        }
    ],
    "sg:phone":"+1 450 247 2055",
    "sg:postcode":"J0L 1H0",
    "sg:province":"QC",
    "sg:tags":[
        "church"
    ],
    "wof:name":"Presbytere St-Romain",
    "wof:placetype":"venue"
},
  "geometry": {"coordinates":[-73.5854263306,45.0517997742],"type":"Point"}
}