{
  "type": "Feature",
  "properties": {
    "addr:full":"Quebec QC G1J 3N5",
    "addr:postcode":"g1j 3n5",
    "iso:country":"CA",
    "sg:city":"Quebec",
    "sg:classifiers":[
        {
            "category":"Organizations",
            "subcategory":"Community Association",
            "type":"Services"
        }
    ],
    "sg:phone":"+1 418 522 0336",
    "sg:postcode":"G1J 3N5",
    "sg:province":"QC",
    "sg:tags":[
        "club"
    ],
    "wof:name":"Club DE Croquet St-Fidele Inc",
    "wof:placetype":"venue"
},
  "geometry": {"coordinates":[-71.2295227051,46.8319511414],"type":"Point"}
}