{
  "type": "Feature",
  "properties": {
    "iso:country":"CA",
    "sg:city":"Mount Pearl",
    "sg:classifiers":[
        {
            "category":"Professional",
            "subcategory":"Accounting & Tax Preparation",
            "type":"Services"
        }
    ],
    "sg:phone":"+1 709 368 2229",
    "sg:postcode":"A1N 1W8",
    "sg:province":"NL",
    "sg:tags":[
        "accountant"
    ],
    "wof:name":"Randell, David L CA",
    "wof:placetype":"venue"
},
  "geometry": {"coordinates":[-52.8049240112,47.5155410767],"type":"Point"}
}