{
  "type": "Feature",
  "properties": {
    "addr:full":"Sylvan Lake AB T4S 1E8",
    "addr:postcode":"t4s 1e8",
    "iso:country":"CA",
    "sg:city":"Sylvan Lake",
    "sg:classifiers":[
        {
            "category":"Travel",
            "subcategory":"Hotels & Motels",
            "type":"Entertainment"
        }
    ],
    "sg:phone":"+1 403 887 0228",
    "sg:postcode":"T4S 1E8",
    "sg:province":"AB",
    "wof:name":"Lost Harbour Inn",
    "wof:placetype":"venue"
},
  "geometry": {"coordinates":[-114.10481299999999,52.310959],"type":"Point"}
}