{
  "type": "Feature",
  "properties": {
    "addr:full":"256 Sheldon Ave Etobicoke ON M8W 4X8",
    "addr:housenumber":"256",
    "addr:postcode":"m8w 4x8",
    "addr:street":"Sheldon Ave",
    "iso:country":"CA",
    "sg:address":"256 Sheldon Ave",
    "sg:city":"Etobicoke",
    "sg:classifiers":[
        {
            "category":"Real Estate",
            "subcategory":"Real Estate Operator",
            "type":"Services"
        }
    ],
    "sg:phone":"+1 416 259 5748",
    "sg:postcode":"M8W 4X8",
    "sg:province":"ON",
    "sg:tags":[
        "home",
        "apartment",
        "rest"
    ],
    "wof:name":"Jubilee Centre",
    "wof:placetype":"venue"
},
  "geometry": {"coordinates":[-79.54560089109999,43.6079521179],"type":"Point"}
}