{
  "type": "Feature",
  "properties": {
    "iso:country":"CA",
    "sg:city":"Winnipeg",
    "sg:classifiers":[
        {
            "category":"Government",
            "subcategory":"Office",
            "type":"Public Place"
        }
    ],
    "sg:phone":"+1 204 945 7309",
    "sg:postcode":"R3C 3L6",
    "sg:province":"MB",
    "wof:name":"Manitoba Adult Corrections",
    "wof:placetype":"venue"
},
  "geometry": {"coordinates":[-97.1451873779,49.8867301941],"type":"Point"}
}