{
  "type": "Feature",
  "properties": {
    "iso:country":"CA",
    "sg:address":"7941 Av Wiseman",
    "sg:city":"Montreal",
    "sg:classifiers":[
        {
            "category":"Education",
            "subcategory":"School",
            "type":"Public Place"
        }
    ],
    "sg:phone":"+1 514 596 4533",
    "sg:postcode":"H3N 2P2",
    "sg:province":"QC",
    "wof:name":"Ecole Barclay",
    "wof:placetype":"venue"
},
  "geometry": {"coordinates":[-73.6345291138,45.5286560059],"type":"Point"}
}