{
  "type": "Feature",
  "properties": {
    "addr:full":"1205 Finch Ave W North York ON M3J 2E8",
    "addr:housenumber":"1205",
    "addr:postcode":"m3j 2e8",
    "addr:street":"Finch Ave W",
    "iso:country":"CA",
    "sg:address":"1205 Finch Ave W",
    "sg:city":"North York",
    "sg:classifiers":[
        {
            "category":"Autos & Motor Vehicles",
            "subcategory":"Automobile Sales",
            "type":"Retail Goods"
        }
    ],
    "sg:phone":"+1 416 739 7262",
    "sg:postcode":"M3J 2E8",
    "sg:province":"ON",
    "sg:tags":[
        "car",
        "dealer"
    ],
    "wof:name":"Autorama",
    "wof:placetype":"venue"
},
  "geometry": {"coordinates":[-79.483131,43.765087],"type":"Point"}
}