{
  "type": "Feature",
  "properties": {
    "addr:full":"139 Riverside Close SE Calgary AB T2C 3N4",
    "addr:housenumber":"139",
    "addr:postcode":"t2c 3n4",
    "addr:street":"Riverside Close Se",
    "iso:country":"CA",
    "sg:address":"139 Riverside Close SE",
    "sg:city":"Calgary",
    "sg:classifiers":[
        {
            "category":"Professional",
            "subcategory":"Accounting & Tax Preparation",
            "type":"Services"
        }
    ],
    "sg:phone":"+1 403 279 7612",
    "sg:postcode":"T2C 3N4",
    "sg:province":"AB",
    "sg:tags":[
        "accountant"
    ],
    "wof:name":"Lmg Accounting Svc",
    "wof:placetype":"venue"
},
  "geometry": {"coordinates":[-114.02827499999999,50.976082],"type":"Point"}
}