{
  "type": "Feature",
  "properties": {
    "addr:full":"780 Steeprock Dr North York ON M3J 2X2",
    "addr:housenumber":"780",
    "addr:postcode":"m3j 2x2",
    "addr:street":"Steeprock Dr",
    "iso:country":"CA",
    "sg:address":"780 Steeprock Dr",
    "sg:city":"North York",
    "sg:classifiers":[
        {
            "category":"Wholesale",
            "subcategory":"Meat",
            "type":"Manufacturing & Wholesale Goods"
        }
    ],
    "sg:phone":"+1 416 762 7331",
    "sg:postcode":"M3J 2X2",
    "sg:province":"ON",
    "sg:tags":[
        "packer"
    ],
    "wof:name":"Paco Meat Products",
    "wof:placetype":"venue"
},
  "geometry": {"coordinates":[-79.466797,43.760727],"type":"Point"}
}