{
  "type": "Feature",
  "properties": {
    "addr:full":"11901 Seux Rd Mission BC V2V 4J1",
    "addr:housenumber":"11901",
    "addr:postcode":"v2v 4j1",
    "addr:street":"Seux Rd",
    "iso:country":"CA",
    "sg:address":"11901 Seux Rd",
    "sg:city":"Mission",
    "sg:classifiers":[
        {
            "category":"Organizations",
            "subcategory":"Professional Association",
            "type":"Services"
        }
    ],
    "sg:phone":"+1 604 826 5776",
    "sg:postcode":"V2V 4J1",
    "sg:province":"BC",
    "wof:name":"Sons of Norway",
    "wof:placetype":"venue"
},
  "geometry": {"coordinates":[-122.28280599999999,49.159996],"type":"Point"}
}