{
  "type": "Feature",
  "properties": {
    "addr:full":"Toronto ON M5G 2C9",
    "addr:postcode":"m5g 2c9",
    "iso:country":"CA",
    "sg:city":"Toronto",
    "sg:classifiers":[
        {
            "category":"Personal",
            "subcategory":"Beauty Salon",
            "type":"Services"
        }
    ],
    "sg:phone":"+1 416 591 6866",
    "sg:postcode":"M5G 2C9",
    "sg:province":"ON",
    "wof:name":"Trinity Men's Hairstyling",
    "wof:placetype":"venue"
},
  "geometry": {"coordinates":[-79.382774353,43.6537971497],"type":"Point"}
}