{
  "type": "Feature",
  "properties": {
    "iso:country":"CA",
    "sg:city":"London",
    "sg:classifiers":[
        {
            "category":"Health Services",
            "subcategory":"Doctor",
            "type":"Services"
        }
    ],
    "sg:phone":"+1 519 663 9200",
    "sg:postcode":"N5X 3V9",
    "sg:province":"ON",
    "sg:tags":[
        "dentist"
    ],
    "wof:name":"Payne, Gordon DDS",
    "wof:placetype":"venue"
},
  "geometry": {"coordinates":[-81.27610778810001,43.0283584595],"type":"Point"}
}