{
  "type": "Feature",
  "properties": {
    "addr:full":"800 Mountain Rd Moncton NB E1C 2R4",
    "addr:housenumber":"800",
    "addr:postcode":"e1c 2r4",
    "addr:street":"Mountain Rd",
    "iso:country":"CA",
    "sg:address":"800 Mountain Rd",
    "sg:city":"Moncton",
    "sg:classifiers":[
        {
            "category":"Shopping",
            "subcategory":"Pharmacy",
            "type":"Retail Goods"
        }
    ],
    "sg:phone":"+1 506 857 9919",
    "sg:postcode":"E1C 2R4",
    "sg:province":"NB",
    "wof:name":"Lawton's Drugs",
    "wof:placetype":"venue"
},
  "geometry": {"coordinates":[-64.8068237305,46.0997314453],"type":"Point"}
}