{
  "type": "Feature",
  "properties": {
    "addr:full":"6046 Rue Jean-Talon E Saint-Leonard QC H1S 3A9",
    "addr:housenumber":"6046",
    "addr:postcode":"h1s 3a9",
    "addr:street":"Rue Jean-Talon E",
    "iso:country":"CA",
    "sg:address":"6046 Rue Jean-Talon E",
    "sg:city":"Saint-Leonard",
    "sg:classifiers":[
        {
            "category":"Personal",
            "subcategory":"Beauty Salon",
            "type":"Services"
        }
    ],
    "sg:phone":"+1 514 259 7556",
    "sg:postcode":"H1S 3A9",
    "sg:province":"QC",
    "wof:name":"Systema Coiffure",
    "wof:placetype":"venue"
},
  "geometry": {"coordinates":[-73.57833100000001,45.587582],"type":"Point"}
}