{
  "type": "Feature",
  "properties": {
    "addr:full":"2624 Eglinton Ave E Scarborough ON M1K 2S3",
    "addr:housenumber":"2624",
    "addr:postcode":"m1k 2s3",
    "addr:street":"Eglinton Ave E",
    "iso:country":"CA",
    "sg:address":"2624 Eglinton Ave E",
    "sg:city":"Scarborough",
    "sg:classifiers":[
        {
            "category":"Restaurant",
            "type":"Food & Drink"
        }
    ],
    "sg:phone":"+1 416 261 6781",
    "sg:postcode":"M1K 2S3",
    "sg:province":"ON",
    "wof:name":"Black Forest Steak House",
    "wof:placetype":"venue"
},
  "geometry": {"coordinates":[-79.25148799999999,43.736141],"type":"Point"}
}