{
  "type": "Feature",
  "properties": {
    "iso:country":"CA",
    "sg:city":"Waterloo",
    "sg:classifiers":[
        {
            "category":"Retail",
            "subcategory":"Auto Repair",
            "type":"Services"
        }
    ],
    "sg:phone":"+1 519 747 3829",
    "sg:postcode":"N2V 1Y9",
    "sg:province":"ON",
    "sg:tags":[
        "repairing",
        "automobile"
    ],
    "wof:name":"Giilck Automotive Svc Inc",
    "wof:placetype":"venue"
},
  "geometry": {"coordinates":[-80.5435409546,43.5075302124],"type":"Point"}
}