{
  "type": "Feature",
  "properties": {
    "addr:full":"602 Grand Ave E Chatham ON N7L 3Z3",
    "addr:housenumber":"602",
    "addr:postcode":"n7l 3z3",
    "addr:street":"Grand Ave E",
    "iso:country":"CA",
    "sg:address":"602 Grand Ave E",
    "sg:city":"Chatham",
    "sg:classifiers":[
        {
            "category":"Home & Garden",
            "subcategory":"Building Materials",
            "type":"Retail Goods"
        }
    ],
    "sg:phone":"+1 519 352 0450",
    "sg:postcode":"N7L 3Z3",
    "sg:province":"ON",
    "wof:name":"Patene Building Supplies Ltd",
    "wof:placetype":"venue"
},
  "geometry": {"coordinates":[-82.16979980470001,42.4209098816],"type":"Point"}
}