{
  "type": "Feature",
  "properties": {
    "iso:country":"CA",
    "sg:address":"2425 Rue Daniel",
    "sg:city":"Sainte-Foy",
    "sg:classifiers":[
        {
            "category":"Building & Trades",
            "subcategory":"Landscaping Services",
            "type":"Services"
        }
    ],
    "sg:phone":"+1 418 872 7255",
    "sg:postcode":"G2G 2P1",
    "sg:province":"QC",
    "sg:tags":[
        "lawn",
        "tree",
        "maintenance",
        "grounds"
    ],
    "wof:name":"Ange Vert Svc Paysagistes",
    "wof:placetype":"venue"
},
  "geometry": {"coordinates":[-71.383186,46.806023],"type":"Point"}
}