{
  "type": "Feature",
  "properties": {
    "addr:full":"704 Main St S Sauble Beach ON N0H 2G0",
    "addr:housenumber":"704",
    "addr:postcode":"n0h 2g0",
    "addr:street":"Main St S Sauble Beach",
    "iso:country":"CA",
    "sg:address":"704 Main St S",
    "sg:city":"Sauble Beach",
    "sg:classifiers":[
        {
            "category":"Food & Beverages",
            "subcategory":"Liquor & Beverages",
            "type":"Retail Goods"
        }
    ],
    "sg:phone":"+1 519 422 1706",
    "sg:postcode":"N0H 2G0",
    "sg:province":"ON",
    "sg:tags":[
        "beer",
        "ale"
    ],
    "wof:name":"Beer Store",
    "wof:placetype":"venue"
},
  "geometry": {"coordinates":[-81.258118,44.629841],"type":"Point"}
}