{
  "type": "Feature",
  "properties": {
    "iso:country":"CA",
    "sg:city":"Waterloo",
    "sg:classifiers":[
        {
            "category":"Professional",
            "subcategory":"Lawyer & Legal Services",
            "type":"Services"
        }
    ],
    "sg:phone":"+1 519 746 0411",
    "sg:postcode":"N2J 4P9",
    "sg:province":"ON",
    "sg:tags":[
        "attorney"
    ],
    "wof:name":"Hicks Morley Hamilton Stewart",
    "wof:placetype":"venue"
},
  "geometry": {"coordinates":[-80.5205383301,43.4632720947],"type":"Point"}
}