{
  "type": "Feature",
  "properties": {
    "addr:full":"Drummondville QC J2C 2B6",
    "addr:postcode":"j2c 2b6",
    "iso:country":"CA",
    "sg:city":"Drummondville",
    "sg:classifiers":[
        {
            "category":"Restaurant",
            "type":"Food & Drink"
        }
    ],
    "sg:phone":"+1 819 474 7375",
    "sg:postcode":"J2C 2B6",
    "sg:province":"QC",
    "wof:name":"Restaurant Eggsquis",
    "wof:placetype":"venue"
},
  "geometry": {"coordinates":[-72.51490800000001,45.893169],"type":"Point"}
}