{
  "type": "Feature",
  "properties": {
    "iso:country":"CA",
    "sg:address":"177 Birch Ave E",
    "sg:city":"Hamiota",
    "sg:classifiers":[
        {
            "category":"Health Services",
            "subcategory":"Hospital",
            "type":"Services"
        }
    ],
    "sg:phone":"+1 204 764 2412",
    "sg:postcode":"R0M 0T0",
    "sg:province":"MB",
    "sg:tags":[
        "personal",
        "home",
        "care"
    ],
    "wof:name":"Hamiota District Health Ctr",
    "wof:placetype":"venue"
},
  "geometry": {"coordinates":[-100.599845886,50.182510376],"type":"Point"}
}