{
  "type": "Feature",
  "properties": {
    "addr:full":"1261 Rue Shearer Montreal QC H3K 3G4",
    "addr:housenumber":"1261",
    "addr:postcode":"h3k 3g4",
    "addr:street":"Rue Shearer",
    "iso:country":"CA",
    "sg:address":"1261 Rue Shearer",
    "sg:city":"Montreal",
    "sg:classifiers":[
        {
            "category":"Wholesale",
            "subcategory":"Medical Equipment & Supplies",
            "type":"Manufacturing & Wholesale Goods"
        }
    ],
    "sg:phone":"+1 514 933 3888",
    "sg:postcode":"H3K 3G4",
    "sg:province":"QC",
    "sg:tags":[
        "therapy",
        "massage",
        "physical"
    ],
    "wof:name":"Cidraf Equipment Inc",
    "wof:placetype":"venue"
},
  "geometry": {"coordinates":[-73.56276699999999,45.483612],"type":"Point"}
}