{
  "type": "Feature",
  "properties": {
    "addr:full":"1246 Oxford St W London ON N6H 1V7",
    "addr:housenumber":"1246",
    "addr:postcode":"n6h 1v7",
    "addr:street":"Oxford St W",
    "iso:country":"CA",
    "sg:address":"1246 Oxford St W",
    "sg:city":"London",
    "sg:classifiers":[
        {
            "category":"Organizations",
            "subcategory":"Religious Organization",
            "type":"Services"
        }
    ],
    "sg:phone":"+1 519 471 1430",
    "sg:postcode":"N6H 1V7",
    "sg:province":"ON",
    "sg:tags":[
        "church"
    ],
    "wof:name":"St Aidan's Anglican Church",
    "wof:placetype":"venue"
},
  "geometry": {"coordinates":[-81.326599,42.973804],"type":"Point"}
}