{
  "type": "Feature",
  "properties": {
    "addr:full":"238 Charlotte St W Saint John NB E2M 1Y3",
    "addr:housenumber":"238",
    "addr:postcode":"e2m 1y3",
    "addr:street":"Charlotte St W",
    "iso:country":"CA",
    "sg:address":"238 Charlotte St W",
    "sg:city":"Saint John",
    "sg:classifiers":[
        {
            "category":"Professional",
            "subcategory":"Accounting & Tax Preparation",
            "type":"Services"
        }
    ],
    "sg:phone":"+1 506 635 1888",
    "sg:postcode":"E2M 1Y3",
    "sg:province":"NB",
    "sg:tags":[
        "accountant"
    ],
    "wof:name":"Five Chimney Assoc",
    "wof:placetype":"venue"
},
  "geometry": {"coordinates":[-66.0732269287,45.2563552856],"type":"Point"}
}