{
  "type": "Feature",
  "properties": {
    "addr:full":"Black Lake QC G6H 1W3",
    "addr:postcode":"g6h 1w3",
    "addr:street":"Black Lake",
    "iso:country":"CA",
    "sg:city":"Black Lake",
    "sg:classifiers":[
        {
            "category":"Building & Trades",
            "subcategory":"Construction",
            "type":"Services"
        }
    ],
    "sg:phone":"+1 418 423 2687",
    "sg:postcode":"G6H 1W3",
    "sg:province":"QC",
    "sg:tags":[
        "painter"
    ],
    "wof:name":"Michel Lafrance Inc",
    "wof:placetype":"venue"
},
  "geometry": {"coordinates":[-71.357292,46.044426],"type":"Point"}
}