{
  "type": "Feature",
  "properties": {
    "addr:full":"171 Willola Beach Rd Fitzroy Harbour ON K0A 1X0",
    "addr:housenumber":"171",
    "addr:postcode":"k0a 1x0",
    "addr:street":"Willola Beach Rd",
    "iso:country":"CA",
    "sg:address":"171 Willola Beach Rd",
    "sg:city":"Fitzroy Harbour",
    "sg:classifiers":[
        {
            "category":"Building & Trades",
            "subcategory":"Construction",
            "type":"Services"
        }
    ],
    "sg:phone":"+1 613 622 7669",
    "sg:postcode":"K0A 1X0",
    "sg:province":"ON",
    "sg:tags":[
        "home",
        "improvement"
    ],
    "wof:name":"Landmark Construction",
    "wof:placetype":"venue"
},
  "geometry": {"coordinates":[-76.22592899999999,45.490555],"type":"Point"}
}