{
  "type": "Feature",
  "properties": {
    "iso:country":"CA",
    "sg:address":"1737 20th Ave",
    "sg:city":"Prince George",
    "sg:classifiers":[
        {
            "category":"Travel",
            "subcategory":"Hotels & Motels",
            "type":"Entertainment"
        }
    ],
    "sg:phone":"+1 250 564 6869",
    "sg:postcode":"V2L 4B9",
    "sg:province":"BC",
    "wof:name":"P G hi-Way Motel",
    "wof:placetype":"venue"
},
  "geometry": {"coordinates":[-122.760818,53.905338],"type":"Point"}
}