{
  "type": "Feature",
  "properties": {
    "addr:full":"Markham ON L3R 9R4",
    "addr:postcode":"l3r 9r4",
    "iso:country":"CA",
    "sg:city":"Markham",
    "sg:classifiers":[
        {
            "category":"Education",
            "subcategory":"School",
            "type":"Public Place"
        }
    ],
    "sg:phone":"+1 905 470 9751",
    "sg:postcode":"L3R 9R4",
    "sg:province":"ON",
    "wof:name":"Wishing Well Montessori Schl",
    "wof:placetype":"venue"
},
  "geometry": {"coordinates":[-79.363838,43.842945],"type":"Point"}
}