{
  "type": "Feature",
  "properties": {
    "addr:full":"720 Robinson St Coquitlam BC V3J 4G1",
    "addr:housenumber":"720",
    "addr:postcode":"v3j 4g1",
    "addr:street":"Robinson St",
    "iso:country":"CA",
    "sg:address":"720 Robinson St",
    "sg:city":"Coquitlam",
    "sg:classifiers":[
        {
            "category":"Travel",
            "subcategory":"Hotels & Motels",
            "type":"Entertainment"
        }
    ],
    "sg:phone":"+1 604 936 6016",
    "sg:postcode":"V3J 4G1",
    "sg:province":"BC",
    "sg:tags":[
        "breakfast",
        "accommodation",
        "bed"
    ],
    "wof:name":"Bed & Breakfast At Tall Cedars",
    "wof:placetype":"venue"
},
  "geometry": {"coordinates":[-122.880157471,49.2613792419],"type":"Point"}
}