{
  "type": "Feature",
  "properties": {
    "addr:full":"250 Front St W Toronto ON M5V 3G5",
    "addr:housenumber":"250",
    "addr:postcode":"m5v 3g5",
    "addr:street":"Front St W",
    "iso:country":"CA",
    "sg:address":"250 Front St W",
    "sg:city":"Toronto",
    "sg:classifiers":[
        {
            "category":"Communications",
            "subcategory":"Radio Station",
            "type":"Services"
        }
    ],
    "sg:phone":"+1 416 205 3311",
    "sg:postcode":"M5V 3G5",
    "sg:province":"ON",
    "sg:tags":[
        "company",
        "broadcasting"
    ],
    "wof:name":"Canadian Broadcasting Corp",
    "wof:placetype":"venue"
},
  "geometry": {"coordinates":[-79.38692474370001,43.6444778442],"type":"Point"}
}