{
  "type": "Feature",
  "properties": {
    "addr:full":"18411 Rue Antoine-Faucon Pierrefonds QC H9K 1M7",
    "addr:housenumber":"18411",
    "addr:postcode":"h9k 1m7",
    "addr:street":"Rue Antoine-Faucon",
    "iso:country":"CA",
    "sg:address":"18411 Rue Antoine-Faucon",
    "sg:city":"Pierrefonds",
    "sg:classifiers":[
        {
            "category":"Retail",
            "subcategory":"Laundry & Dry Cleaning",
            "type":"Services"
        }
    ],
    "sg:phone":"+1 514 624 7924",
    "sg:postcode":"H9K 1M7",
    "sg:province":"QC",
    "sg:tags":[
        "cleaners"
    ],
    "wof:name":"Nettoyeur Guru",
    "wof:placetype":"venue"
},
  "geometry": {"coordinates":[-73.886917,45.452301],"type":"Point"}
}