{
  "type": "Feature",
  "properties": {
    "addr:full":"315 Boul Des Promenades Saint-Bruno QC J3V 6A7",
    "addr:housenumber":"315",
    "addr:postcode":"j3v 6a7",
    "addr:street":"Boul Des Promenades",
    "iso:country":"CA",
    "sg:address":"315 Boul Des Promenades",
    "sg:city":"Saint-Bruno",
    "sg:classifiers":[
        {
            "category":"Shopping",
            "subcategory":"Clothing, Apparel, & Fashions",
            "type":"Retail Goods"
        }
    ],
    "sg:phone":"+1 450 441 9962",
    "sg:postcode":"J3V 6A7",
    "sg:province":"QC",
    "sg:tags":[
        "item",
        "boutique"
    ],
    "wof:name":"Boutique Colori Inc",
    "wof:placetype":"venue"
},
  "geometry": {"coordinates":[-71.675522,48.471771],"type":"Point"}
}