{
  "type": "Feature",
  "properties": {
    "addr:full":"50 Ch Bates Outremont QC H2V 1A8",
    "addr:housenumber":"50",
    "addr:postcode":"h2v 1a8",
    "addr:street":"Ch Bates",
    "iso:country":"CA",
    "sg:address":"50 Ch Bates",
    "sg:city":"Outremont",
    "sg:classifiers":[
        {
            "category":"Professional",
            "subcategory":"Secretarial Services",
            "type":"Services"
        }
    ],
    "sg:phone":"+1 514 735 9578",
    "sg:postcode":"H2V 1A8",
    "sg:province":"QC",
    "sg:tags":[
        "resume"
    ],
    "wof:name":"Secretariat Therese Viau",
    "wof:placetype":"venue"
},
  "geometry": {"coordinates":[-73.6252212524,45.5176506042],"type":"Point"}
}