{
  "type": "Feature",
  "properties": {
    "addr:full":"220 Canterbury Dr SW Calgary AB T2W 1H4",
    "addr:housenumber":"220",
    "addr:postcode":"t2w 1h4",
    "addr:street":"Canterbury Dr Sw",
    "iso:country":"CA",
    "sg:address":"220 Canterbury Dr SW",
    "sg:city":"Calgary",
    "sg:classifiers":[
        {
            "category":"Education",
            "subcategory":"School",
            "type":"Public Place"
        }
    ],
    "sg:phone":"+1 403 281 3366",
    "sg:postcode":"T2W 1H4",
    "sg:province":"AB",
    "wof:name":"E P Scarlett High School",
    "wof:placetype":"venue"
},
  "geometry": {"coordinates":[-114.08719600000001,50.947926],"type":"Point"}
}