{
  "type": "Feature",
  "properties": {
    "addr:full":"114 Harris Dr Marystown NL A0E 2M0",
    "addr:housenumber":"114",
    "addr:postcode":"a0e 2m0",
    "addr:street":"Harris Dr",
    "iso:country":"CA",
    "sg:address":"114 Harris Dr",
    "sg:city":"Marystown",
    "sg:classifiers":[
        {
            "category":"Retail",
            "subcategory":"Repair Shop",
            "type":"Services"
        }
    ],
    "sg:phone":"+1 709 279 3859",
    "sg:postcode":"A0E 2M0",
    "sg:province":"NL",
    "sg:tags":[
        "lock",
        "locksmith"
    ],
    "wof:name":"Lock & Key Svc",
    "wof:placetype":"venue"
},
  "geometry": {"coordinates":[-55.165783,47.165718],"type":"Point"}
}