{
  "type": "Feature",
  "properties": {
    "addr:full":"Saint-Lambert QC J4P 1S7",
    "addr:postcode":"j4p 1s7",
    "iso:country":"CA",
    "sg:city":"Saint-Lambert",
    "sg:classifiers":[
        {
            "category":"Professional",
            "subcategory":"Accounting & Tax Preparation",
            "type":"Services"
        }
    ],
    "sg:phone":"+1 450 923 9336",
    "sg:postcode":"J4P 1S7",
    "sg:province":"QC",
    "sg:tags":[
        "accountant"
    ],
    "wof:name":"Giguere, Mario CA",
    "wof:placetype":"venue"
},
  "geometry": {"coordinates":[-73.5096664429,45.5035591125],"type":"Point"}
}