{
  "type": "Feature",
  "properties": {
    "addr:full":"Edmonton AB T5K 1V4",
    "addr:postcode":"t5k 1v4",
    "iso:country":"CA",
    "sg:city":"Edmonton",
    "sg:classifiers":[
        {
            "category":"Arts & Performance",
            "subcategory":"Theater",
            "type":"Entertainment"
        }
    ],
    "sg:phone":"+1 780 482 3819",
    "sg:postcode":"T5K 1V4",
    "sg:province":"AB",
    "sg:tags":[
        "bureau"
    ],
    "wof:name":"Stars & Legends",
    "wof:placetype":"venue"
},
  "geometry": {"coordinates":[-113.52108800000001,53.539242],"type":"Point"}
}