{
  "type": "Feature",
  "properties": {
    "addr:full":"16 Bateman Mill Rd Shediac Cape NB E4P 2Z2",
    "addr:housenumber":"16",
    "addr:postcode":"e4p 2z2",
    "addr:street":"Bateman Mill Rd",
    "iso:country":"CA",
    "sg:address":"16 Bateman Mill Rd",
    "sg:city":"Shediac Cape",
    "sg:classifiers":[
        {
            "category":"Wholesale",
            "subcategory":"Construction Materials",
            "type":"Manufacturing & Wholesale Goods"
        }
    ],
    "sg:phone":"+1 506 532 3960",
    "sg:postcode":"E4P 2Z2",
    "sg:province":"NB",
    "sg:tags":[
        "fence"
    ],
    "wof:name":"Dean Welling & Sons Fencing",
    "wof:placetype":"venue"
},
  "geometry": {"coordinates":[-64.566681,46.237846],"type":"Point"}
}