{
  "type": "Feature",
  "properties": {
    "addr:full":"435 Canfor Ave New Westminster BC V3L 5H5",
    "addr:housenumber":"435",
    "addr:postcode":"v3l 5h5",
    "addr:street":"Canfor Ave",
    "iso:country":"CA",
    "sg:address":"435 Canfor Ave",
    "sg:city":"New Westminster",
    "sg:classifiers":[
        {
            "category":"Building & Trades",
            "subcategory":"Construction",
            "type":"Services"
        }
    ],
    "sg:phone":"+1 604 521 2110",
    "sg:postcode":"V3L 5H5",
    "sg:province":"BC",
    "sg:tags":[
        "crane",
        "erectors"
    ],
    "wof:name":"Vision Crane",
    "wof:placetype":"venue"
},
  "geometry": {"coordinates":[-122.880096435,49.2282676697],"type":"Point"}
}