{
  "type": "Feature",
  "properties": {
    "addr:full":"5720 Macleod Trail SW # 101 Calgary AB T2H 0J6",
    "addr:housenumber":"5720",
    "addr:postcode":"t2h 0j6",
    "addr:street":"Macleod Trail Sw # 101",
    "iso:country":"CA",
    "sg:address":"5720 Macleod Trail SW # 101",
    "sg:city":"Calgary",
    "sg:classifiers":[
        {
            "category":"Personal",
            "subcategory":"Tanning Parlor",
            "type":"Services"
        }
    ],
    "sg:phone":"+1 403 255 3162",
    "sg:postcode":"T2H 0J6",
    "sg:province":"AB",
    "sg:tags":[
        "salon"
    ],
    "wof:name":"Fabutan Sun Tan Studios",
    "wof:placetype":"venue"
},
  "geometry": {"coordinates":[-114.07081599999999,51.003395],"type":"Point"}
}