{
  "type": "Feature",
  "properties": {
    "addr:full":"Churchill ON L0L 1K0",
    "addr:postcode":"l0l 1k0",
    "iso:country":"CA",
    "sg:city":"Churchill",
    "sg:classifiers":[
        {
            "category":"Building & Trades",
            "subcategory":"Construction",
            "type":"Services"
        }
    ],
    "sg:phone":"+1 705 456 6707",
    "sg:postcode":"L0L 1K0",
    "sg:province":"ON",
    "sg:tags":[
        "designer",
        "dealer",
        "pool",
        "swimming"
    ],
    "wof:name":"York Simcoe Pools",
    "wof:placetype":"venue"
},
  "geometry": {"coordinates":[-79.60395050050001,44.251033783],"type":"Point"}
}