{
  "type": "Feature",
  "properties": {
    "addr:full":"1856 Powell St Vancouver BC V5L 1H9",
    "addr:housenumber":"1856",
    "addr:postcode":"v5l 1h9",
    "addr:street":"Powell St",
    "iso:country":"CA",
    "sg:address":"1856 Powell St",
    "sg:city":"Vancouver",
    "sg:classifiers":[
        {
            "category":"Wholesale",
            "subcategory":"Scrap",
            "type":"Manufacturing & Wholesale Goods"
        }
    ],
    "sg:phone":"+1 604 253 4987",
    "sg:postcode":"V5L 1H9",
    "sg:province":"BC",
    "sg:tags":[
        "recycling",
        "center"
    ],
    "wof:name":"K & J Bottle Depot",
    "wof:placetype":"venue"
},
  "geometry": {"coordinates":[-123.066551,49.284485],"type":"Point"}
}