{
  "type": "Feature",
  "properties": {
    "addr:full":"Buick BC V0C 2R0",
    "addr:postcode":"v0c 2r0",
    "iso:country":"CA",
    "sg:city":"Buick",
    "sg:classifiers":[
        {
            "category":"Education",
            "subcategory":"School",
            "type":"Public Place"
        }
    ],
    "sg:phone":"+1 250 630 2231",
    "sg:postcode":"V0C 2R0",
    "sg:province":"BC",
    "wof:name":"Buick Creek School",
    "wof:placetype":"venue"
},
  "geometry": {"coordinates":[-121.27456665,56.7601966858],"type":"Point"}
}