{
  "type": "Feature",
  "properties": {
    "addr:full":"Saint-Victor QC G0M 2B0",
    "addr:postcode":"g0m 2b0",
    "iso:country":"CA",
    "sg:city":"Saint-Victor",
    "sg:classifiers":[
        {
            "category":"Shopping",
            "subcategory":"Florist",
            "type":"Retail Goods"
        }
    ],
    "sg:phone":"+1 418 588 6362",
    "sg:postcode":"G0M 2B0",
    "sg:province":"QC",
    "wof:name":"Fleuriste Colette Gosselin Enr",
    "wof:placetype":"venue"
},
  "geometry": {"coordinates":[-70.90836299999999,46.149277],"type":"Point"}
}