{
  "type": "Feature",
  "properties": {
    "addr:full":"Saint-Lambert QC J4P 2J6",
    "addr:postcode":"j4p 2j6",
    "iso:country":"CA",
    "sg:city":"Saint-Lambert",
    "sg:classifiers":[
        {
            "category":"Personal",
            "subcategory":"Beauty Salon",
            "type":"Services"
        }
    ],
    "sg:phone":"+1 450 466 5361",
    "sg:postcode":"J4P 2J6",
    "sg:province":"QC",
    "wof:name":"Blitz Coiffure Inc",
    "wof:placetype":"venue"
},
  "geometry": {"coordinates":[-73.509186,45.500694],"type":"Point"}
}