{
  "type": "Feature",
  "properties": {
    "iso:country":"CA",
    "sg:address":"1212 Commercial Dr",
    "sg:city":"Vancouver",
    "sg:classifiers":[
        {
            "category":"Restaurant",
            "type":"Food & Drink"
        }
    ],
    "sg:phone":"+1 604 253 9119",
    "sg:postcode":"V5L 3X4",
    "sg:province":"BC",
    "wof:name":"Havana",
    "wof:placetype":"venue"
},
  "geometry": {"coordinates":[-123.069397,49.273766],"type":"Point"}
}