{
  "type": "Feature",
  "properties": {
    "iso:country":"CA",
    "sg:address":"RR 1",
    "sg:city":"Ellerslie",
    "sg:classifiers":[
        {
            "category":"Autos & Motor Vehicles",
            "subcategory":"Automobile Sales",
            "type":"Retail Goods"
        }
    ],
    "sg:phone":"+1 902 831 3363",
    "sg:postcode":"C0B 1J0",
    "sg:province":"PE",
    "sg:tags":[
        "car",
        "dealer"
    ],
    "wof:name":"D & D Auto Sales",
    "wof:placetype":"venue"
},
  "geometry": {"coordinates":[-63.9497451782,46.6024551392],"type":"Point"}
}