{
  "type": "Feature",
  "properties": {
    "addr:full":"245 Av Saint-Charles Vaudreuil-Dorion QC J7V 2L6",
    "addr:housenumber":"245",
    "addr:postcode":"j7v 2l6",
    "addr:street":"Av Saint-Charles",
    "iso:country":"CA",
    "sg:address":"245 Av Saint-Charles",
    "sg:city":"Vaudreuil-Dorion",
    "sg:classifiers":[
        {
            "category":"Autos & Motor Vehicles",
            "subcategory":"Auto Supplies",
            "type":"Retail Goods"
        }
    ],
    "sg:phone":"+1 450 424 6100",
    "sg:postcode":"J7V 2L6",
    "sg:province":"QC",
    "sg:tags":[
        "automobile",
        "stereo",
        "radio"
    ],
    "wof:name":"Duro Vitre Auto",
    "wof:placetype":"venue"
},
  "geometry": {"coordinates":[-74.0153503418,45.3896179199],"type":"Point"}
}