{
  "type": "Feature",
  "properties": {
    "addr:full":"2574 Broadway W Vancouver BC V6K 2G1",
    "addr:housenumber":"2574",
    "addr:postcode":"v6k 2g1",
    "addr:street":"Broadway W",
    "iso:country":"CA",
    "sg:address":"2574 Broadway W",
    "sg:city":"Vancouver",
    "sg:classifiers":[
        {
            "category":"Banks & Credit Unions",
            "subcategory":"Investment Brokerage",
            "type":"Services"
        }
    ],
    "sg:phone":"+1 604 730 5352",
    "sg:postcode":"V6K 2G1",
    "sg:province":"BC",
    "wof:name":"Edward Jones",
    "wof:placetype":"venue"
},
  "geometry": {"coordinates":[-123.16383399999999,49.263882],"type":"Point"}
}