{
  "type": "Feature",
  "properties": {
    "addr:full":"7147 124 St Surrey BC V3W 3W9",
    "addr:housenumber":"7147",
    "addr:postcode":"v3w 3w9",
    "addr:street":"124 St",
    "iso:country":"CA",
    "sg:address":"7147 124 St",
    "sg:city":"Surrey",
    "sg:classifiers":[
        {
            "category":"Organizations",
            "subcategory":"Religious Organization",
            "type":"Services"
        }
    ],
    "sg:phone":"+1 604 591 8533",
    "sg:postcode":"V3W 3W9",
    "sg:province":"BC",
    "sg:tags":[
        "church"
    ],
    "wof:name":"St Andrew's Newton",
    "wof:placetype":"venue"
},
  "geometry": {"coordinates":[-122.879288,49.132957],"type":"Point"}
}