{
  "type": "Feature",
  "properties": {
    "addr:full":"265 Simcoe Beaverton ON L0K 1A0",
    "addr:housenumber":"265",
    "addr:postcode":"l0k 1a0",
    "addr:street":"Simcoe",
    "iso:country":"CA",
    "sg:address":"265 Simcoe",
    "sg:city":"Beaverton",
    "sg:classifiers":[
        {
            "category":"Professional",
            "subcategory":"Management & Consulting",
            "type":"Services"
        }
    ],
    "sg:phone":"+1 705 426 2181",
    "sg:postcode":"L0K 1A0",
    "sg:province":"ON",
    "sg:tags":[
        "consultant",
        "business"
    ],
    "wof:name":"Atocrates Centre For Research",
    "wof:placetype":"venue"
},
  "geometry": {"coordinates":[-79.157814,44.430164],"type":"Point"}
}