{
  "type": "Feature",
  "properties": {
    "addr:full":"Brockville ON K6V 5T4",
    "addr:postcode":"k6v 5t4",
    "iso:country":"CA",
    "sg:city":"Brockville",
    "sg:classifiers":[
        {
            "category":"Restaurant",
            "type":"Food & Drink"
        }
    ],
    "sg:phone":"+1 613 345 4575",
    "sg:postcode":"K6V 5T4",
    "sg:province":"ON",
    "wof:name":"Tincap Restaurant & Plaza",
    "wof:placetype":"venue"
},
  "geometry": {"coordinates":[-75.734848,44.610859],"type":"Point"}
}