{
  "type": "Feature",
  "properties": {
    "iso:country":"CA",
    "sg:address":"4388 Rue Saint-Denis",
    "sg:city":"Montreal",
    "sg:classifiers":[
        {
            "category":"Organizations",
            "subcategory":"Professional Association",
            "type":"Services"
        }
    ],
    "sg:phone":"+1 514 286 6020",
    "sg:postcode":"H2J 2L1",
    "sg:province":"QC",
    "wof:name":"Communication-Jeunesse",
    "wof:placetype":"venue"
},
  "geometry": {"coordinates":[-73.581375,45.523125],"type":"Point"}
}