{
  "type": "Feature",
  "properties": {
    "iso:country":"CA",
    "sg:address":"3742 Boul Levesque O",
    "sg:city":"Laval",
    "sg:classifiers":[
        {
            "category":"Health Services",
            "subcategory":"Health Practitioner",
            "type":"Services"
        }
    ],
    "sg:phone":"+1 450 978 0737",
    "sg:postcode":"H7V 1E8",
    "sg:province":"QC",
    "sg:tags":[
        "psychologist"
    ],
    "wof:name":"Chapdelaine, Jean",
    "wof:placetype":"venue"
},
  "geometry": {"coordinates":[-73.737099,45.534966],"type":"Point"}
}