{
  "type": "Feature",
  "properties": {
    "addr:full":"10288 Yonge St Richmond Hill ON L4C 3B8",
    "addr:housenumber":"10288",
    "addr:postcode":"l4c 3b8",
    "addr:street":"Yonge St",
    "iso:country":"CA",
    "sg:address":"10288 Yonge St",
    "sg:city":"Richmond Hill",
    "sg:classifiers":[
        {
            "category":"Food & Beverages",
            "subcategory":"Groceries & Convenience Stores",
            "type":"Retail Goods"
        }
    ],
    "sg:phone":"+1 905 770 2856",
    "sg:postcode":"L4C 3B8",
    "sg:province":"ON",
    "sg:tags":[
        "grocer"
    ],
    "wof:name":"Bismillah Grocers Inc",
    "wof:placetype":"venue"
},
  "geometry": {"coordinates":[-79.4390640259,43.8783111572],"type":"Point"}
}