{
  "type": "Feature",
  "properties": {
    "addr:full":"Vancouver BC V6B 1L8",
    "addr:postcode":"v6b 1l8",
    "iso:country":"CA",
    "sg:city":"Vancouver",
    "sg:classifiers":[
        {
            "category":"Retail",
            "subcategory":"Repair Shop",
            "type":"Services"
        }
    ],
    "sg:phone":"+1 604 681 9624",
    "sg:postcode":"V6B 1L8",
    "sg:province":"BC",
    "sg:tags":[
        "jewelry"
    ],
    "wof:name":"Golden Hands Mfg Ltd",
    "wof:placetype":"venue"
},
  "geometry": {"coordinates":[-123.11215199999999,49.284035],"type":"Point"}
}