{
  "type": "Feature",
  "properties": {
    "addr:full":"402 18 St NW Calgary AB T2N 2G5",
    "addr:housenumber":"18",
    "addr:postcode":"t2n 2g5",
    "addr:street":"402;St Nw",
    "iso:country":"CA",
    "sg:address":"402 18 St NW",
    "sg:city":"Calgary",
    "sg:classifiers":[
        {
            "category":"Education",
            "subcategory":"School",
            "type":"Public Place"
        }
    ],
    "sg:phone":"+1 403 777 6789",
    "sg:postcode":"T2N 2G5",
    "sg:province":"AB",
    "wof:name":"Queen Elizabeth Elementary",
    "wof:placetype":"venue"
},
  "geometry": {"coordinates":[-114.10234069800001,51.0554389954],"type":"Point"}
}