{
  "type": "Feature",
  "properties": {
    "addr:full":"1078 Seaford Rd Mansons Landing BC V0P 1K0",
    "addr:housenumber":"1078",
    "addr:postcode":"v0p 1k0",
    "addr:street":"Seaford Rd",
    "iso:country":"CA",
    "sg:address":"1078 Seaford Rd",
    "sg:city":"Mansons Landing",
    "sg:classifiers":[
        {
            "category":"Travel",
            "subcategory":"Hotels & Motels",
            "type":"Entertainment"
        }
    ],
    "sg:phone":"+1 250 935 6363",
    "sg:postcode":"V0P 1K0",
    "sg:province":"BC",
    "wof:name":"Cortes Island Motel",
    "wof:placetype":"venue"
},
  "geometry": {"coordinates":[-124.982956,50.067432],"type":"Point"}
}