{
  "type": "Feature",
  "properties": {
    "iso:country":"CA",
    "sg:address":"13 Rue DE LA Visitation",
    "sg:city":"Saint-Charles-Borromee",
    "sg:classifiers":[
        {
            "category":"Autos & Motor Vehicles",
            "subcategory":"Automobile Sales",
            "type":"Retail Goods"
        }
    ],
    "sg:phone":"+1 450 752 2784",
    "sg:postcode":"J6E 4M9",
    "sg:province":"QC",
    "sg:tags":[
        "car",
        "dealer"
    ],
    "wof:name":"R D Auto",
    "wof:placetype":"venue"
},
  "geometry": {"coordinates":[-73.44403076170001,46.0379066467],"type":"Point"}
}