{
  "type": "Feature",
  "properties": {
    "addr:full":"653 Rue Principale Saint-Ferdinand QC G0N 1N0",
    "addr:housenumber":"653",
    "addr:postcode":"g0n 1n0",
    "addr:street":"Rue Principale",
    "iso:country":"CA",
    "sg:address":"653 Rue Principale",
    "sg:city":"Saint-Ferdinand",
    "sg:classifiers":[
        {
            "category":"Shopping",
            "subcategory":"Shoes",
            "type":"Retail Goods"
        }
    ],
    "sg:phone":"+1 418 428 3436",
    "sg:postcode":"G0N 1N0",
    "sg:province":"QC",
    "wof:name":"Chaussures Juvalu Enr",
    "wof:placetype":"venue"
},
  "geometry": {"coordinates":[-71.57196,46.107372],"type":"Point"}
}