{
  "type": "Feature",
  "properties": {
    "addr:full":"5771 No. 3 Rd # 200 Richmond BC V6X 2C9",
    "addr:housenumber":"200",
    "addr:postcode":"5771;v6x 2c9",
    "addr:street":"3 Rd #",
    "iso:country":"CA",
    "sg:address":"5771 No. 3 Rd # 200",
    "sg:city":"Richmond",
    "sg:classifiers":[
        {
            "category":"Real Estate",
            "subcategory":"Real Estate Agent",
            "type":"Services"
        }
    ],
    "sg:phone":"+1 604 271 3888",
    "sg:postcode":"V6X 2C9",
    "sg:province":"BC",
    "wof:name":"Interlink Realty Corp",
    "wof:placetype":"venue"
},
  "geometry": {"coordinates":[-123.13696299999999,49.172642],"type":"Point"}
}