{
  "type": "Feature",
  "properties": {
    "addr:full":"7275 Rue Honore-Vaillancourt Montreal QC H1E 2R4",
    "addr:housenumber":"7275",
    "addr:postcode":"h1e 2r4",
    "addr:street":"Rue Honore-Vaillancourt",
    "iso:country":"CA",
    "sg:address":"7275 Rue Honore-Vaillancourt",
    "sg:city":"Montreal",
    "sg:classifiers":[
        {
            "category":"Wholesale",
            "subcategory":"Machinery & Supplies",
            "type":"Manufacturing & Wholesale Goods"
        }
    ],
    "sg:phone":"+1 514 494 8386",
    "sg:postcode":"H1E 2R4",
    "sg:province":"QC",
    "sg:tags":[
        "salon",
        "beauty"
    ],
    "wof:name":"Lisap Produits DE Beaute Ltee",
    "wof:placetype":"venue"
},
  "geometry": {"coordinates":[-73.599007,45.620941],"type":"Point"}
}