{
  "type": "Feature",
  "properties": {
    "addr:full":"1594 Kingsway Vancouver BC V5N 2R9",
    "addr:housenumber":"1594",
    "addr:postcode":"v5n 2r9",
    "addr:street":"Kingsway",
    "iso:country":"CA",
    "sg:address":"1594 Kingsway",
    "sg:city":"Vancouver",
    "sg:classifiers":[
        {
            "category":"Shopping",
            "subcategory":"Clothing, Apparel, & Fashions",
            "type":"Retail Goods"
        }
    ],
    "sg:phone":"+1 604 876 5972",
    "sg:postcode":"V5N 2R9",
    "sg:province":"BC",
    "wof:name":"Thanh Truc Fashion",
    "wof:placetype":"venue"
},
  "geometry": {"coordinates":[-123.071472,49.24794],"type":"Point"}
}