{
  "type": "Feature",
  "properties": {
    "addr:full":"2347 Mcintyre St Regina SK S4P 2S3",
    "addr:housenumber":"2347",
    "addr:postcode":"s4p 2s3",
    "addr:street":"Mcintyre St",
    "iso:country":"CA",
    "sg:address":"2347 Mcintyre St",
    "sg:city":"Regina",
    "sg:classifiers":[
        {
            "category":"Shopping",
            "type":"Retail Goods"
        }
    ],
    "sg:phone":"+1 306 757 4323",
    "sg:postcode":"S4P 2S3",
    "sg:province":"SK",
    "sg:tags":[
        "art",
        "gallery",
        "dealer"
    ],
    "wof:name":"Mc Intyre Gallery",
    "wof:placetype":"venue"
},
  "geometry": {"coordinates":[-104.61640199999999,50.441708],"type":"Point"}
}