{
  "type": "Feature",
  "properties": {
    "addr:full":"19 Rue Saint-Philippe Clermont QC G4A 1K3",
    "addr:housenumber":"19",
    "addr:postcode":"g4a 1k3",
    "addr:street":"Rue Saint-Philippe",
    "iso:country":"CA",
    "sg:address":"19 Rue Saint-Philippe",
    "sg:city":"Clermont",
    "sg:classifiers":[
        {
            "category":"Education",
            "subcategory":"School",
            "type":"Public Place"
        }
    ],
    "sg:phone":"+1 418 439 3862",
    "sg:postcode":"G4A 1K3",
    "sg:province":"QC",
    "wof:name":"Ecole Laure-Gaudreault",
    "wof:placetype":"venue"
},
  "geometry": {"coordinates":[-70.221794,47.693668],"type":"Point"}
}