{
  "type": "Feature",
  "properties": {
    "addr:full":"5330 Bradco Blvd Mississauga ON L4W 1G7",
    "addr:postcode":"5330;l4w 1g7",
    "addr:street":"Bradco Blvd",
    "iso:country":"CA",
    "sg:address":"5330 Bradco Blvd",
    "sg:city":"Mississauga",
    "sg:classifiers":[
        {
            "category":"Freight",
            "type":"Transportation"
        }
    ],
    "sg:phone":"+1 905 624 3220",
    "sg:postcode":"L4W 1G7",
    "sg:province":"ON",
    "sg:tags":[
        "mover"
    ],
    "wof:name":"Taylor Moving & Storage Ltd",
    "wof:placetype":"venue"
},
  "geometry": {"coordinates":[-79.63292694090001,43.6375083923],"type":"Point"}
}