{
  "type": "Feature",
  "properties": {
    "addr:full":"Coquitlam BC V3K 3V8",
    "addr:postcode":"v3k 3v8",
    "iso:country":"CA",
    "sg:city":"Coquitlam",
    "sg:classifiers":[
        {
            "category":"Shopping",
            "subcategory":"Jewelry",
            "type":"Retail Goods"
        }
    ],
    "sg:phone":"+1 604 936 5588",
    "sg:postcode":"V3K 3V8",
    "sg:province":"BC",
    "sg:tags":[
        "jeweler"
    ],
    "wof:name":"Terry Mooney Goldsmith",
    "wof:placetype":"venue"
},
  "geometry": {"coordinates":[-122.89241,49.243439],"type":"Point"}
}