{
  "type": "Feature",
  "properties": {
    "addr:full":"116 Hemlock Rd Ingersoll ON N5C 3Z5",
    "addr:housenumber":"116",
    "addr:postcode":"n5c 3z5",
    "addr:street":"Hemlock Rd",
    "iso:country":"CA",
    "sg:address":"116 Hemlock Rd",
    "sg:city":"Ingersoll",
    "sg:classifiers":[
        {
            "category":"Professional",
            "subcategory":"Accounting & Tax Preparation",
            "type":"Services"
        }
    ],
    "sg:phone":"+1 519 425 0157",
    "sg:postcode":"N5C 3Z5",
    "sg:province":"ON",
    "sg:tags":[
        "accountant"
    ],
    "wof:name":"Piron, A G",
    "wof:placetype":"venue"
},
  "geometry": {"coordinates":[-80.88567399999999,43.029762],"type":"Point"}
}