{
  "type": "Feature",
  "properties": {
    "addr:full":"Toronto ON M5V 3P1",
    "addr:postcode":"m5v 3p1",
    "iso:country":"CA",
    "sg:city":"Toronto",
    "sg:classifiers":[
        {
            "category":"Professional",
            "subcategory":"Art Services",
            "type":"Services"
        }
    ],
    "sg:phone":"+1 416 597 0632",
    "sg:postcode":"M5V 3P1",
    "sg:province":"ON",
    "sg:tags":[
        "graphic",
        "designer"
    ],
    "wof:name":"Avi Dunkelman Design Group",
    "wof:placetype":"venue"
},
  "geometry": {"coordinates":[-79.394569397,43.6482391357],"type":"Point"}
}