{
  "type": "Feature",
  "properties": {
    "addr:full":"983 Lakeshore Rd E Mississauga ON L5E 1E5",
    "addr:housenumber":"983",
    "addr:postcode":"l5e 1e5",
    "addr:street":"Lakeshore Rd E",
    "iso:country":"CA",
    "sg:address":"983 Lakeshore Rd E",
    "sg:city":"Mississauga",
    "sg:classifiers":[
        {
            "category":"Building & Trades",
            "subcategory":"Plumbing",
            "type":"Services"
        }
    ],
    "sg:phone":"+1 905 271 6672",
    "sg:postcode":"L5E 1E5",
    "sg:province":"ON",
    "sg:tags":[
        "air",
        "cleaning",
        "contractor",
        "system",
        "conditioning"
    ],
    "wof:name":"Fawn Heating & Cooling",
    "wof:placetype":"venue"
},
  "geometry": {"coordinates":[-79.5597229004,43.5762367249],"type":"Point"}
}