{
  "type": "Feature",
  "properties": {
    "addr:full":"4990 Walnut St Niagara Falls ON L2G 3N3",
    "addr:housenumber":"4990",
    "addr:postcode":"l2g 3n3",
    "addr:street":"Walnut St",
    "iso:country":"CA",
    "sg:address":"4990 Walnut St",
    "sg:city":"Niagara Falls",
    "sg:classifiers":[
        {
            "category":"Cinema",
            "subcategory":"Movie Theater",
            "type":"Entertainment"
        }
    ],
    "sg:phone":"+1 905 356 4953",
    "sg:postcode":"L2G 3N3",
    "sg:province":"ON",
    "wof:name":"Firehall Theatre",
    "wof:placetype":"venue"
},
  "geometry": {"coordinates":[-79.07611799999999,43.095242],"type":"Point"}
}