{
  "type": "Feature",
  "properties": {
    "addr:full":"Scarborough ON M1V 1E7",
    "addr:postcode":"m1v 1e7",
    "iso:country":"CA",
    "sg:city":"Scarborough",
    "sg:classifiers":[
        {
            "category":"Building & Trades",
            "subcategory":"Construction",
            "type":"Services"
        }
    ],
    "sg:phone":"+1 416 291 1561",
    "sg:postcode":"M1V 1E7",
    "sg:province":"ON",
    "sg:tags":[
        "plastering",
        "contractor"
    ],
    "wof:name":"Cesaroni Contracting Ltd",
    "wof:placetype":"venue"
},
  "geometry": {"coordinates":[-79.29974365229999,43.807762146],"type":"Point"}
}