{
  "type": "Feature",
  "properties": {
    "addr:full":"125 Rue Sherbrooke O Montreal QC H2X 1X4",
    "addr:housenumber":"125",
    "addr:postcode":"h2x 1x4",
    "addr:street":"Rue Sherbrooke O",
    "iso:country":"CA",
    "sg:address":"125 Rue Sherbrooke O",
    "sg:city":"Montreal",
    "sg:classifiers":[
        {
            "category":"Government",
            "subcategory":"Office",
            "type":"Public Place"
        }
    ],
    "sg:phone":"+1 514 873 4833",
    "sg:postcode":"H2X 1X4",
    "sg:province":"QC",
    "wof:name":"Quebec Office DE LA Langue",
    "wof:placetype":"venue"
},
  "geometry": {"coordinates":[-73.569061,45.513779],"type":"Point"}
}