{
  "type": "Feature",
  "properties": {
    "addr:full":"Welland ON L3C 5R4",
    "addr:postcode":"l3c 5r4",
    "iso:country":"CA",
    "sg:city":"Welland",
    "sg:classifiers":[
        {
            "category":"Real Estate",
            "subcategory":"Real Estate Operator",
            "type":"Services"
        }
    ],
    "sg:phone":"+1 905 714 3328",
    "sg:postcode":"L3C 5R4",
    "sg:province":"ON",
    "sg:tags":[
        "management",
        "apartment"
    ],
    "wof:name":"Rose City Terrace Apartments",
    "wof:placetype":"venue"
},
  "geometry": {"coordinates":[-79.274147,42.994591],"type":"Point"}
}