{
  "type": "Feature",
  "properties": {
    "addr:full":"2350 Rue Louis-A.-Amos Lachine QC H8T 3K6",
    "addr:housenumber":"2350",
    "addr:postcode":"h8t 3k6",
    "addr:street":"Rue Louis-A.-Amos",
    "iso:country":"CA",
    "sg:address":"2350 Rue Louis-A.-Amos",
    "sg:city":"Lachine",
    "sg:classifiers":[
        {
            "category":"Wholesale",
            "subcategory":"Non-durable Goods",
            "type":"Manufacturing & Wholesale Goods"
        }
    ],
    "sg:phone":"+1 514 631 0691",
    "sg:postcode":"H8T 3K6",
    "sg:province":"QC",
    "sg:tags":[
        "rubber",
        "sponge"
    ],
    "wof:name":"Fabrications Ultra",
    "wof:placetype":"venue"
},
  "geometry": {"coordinates":[-73.700081,45.467186],"type":"Point"}
}