{
  "type": "Feature",
  "properties": {
    "addr:full":"Saint-Esprit QC J0K 2L0",
    "addr:postcode":"j0k 2l0",
    "iso:country":"CA",
    "sg:city":"Saint-Esprit",
    "sg:classifiers":[
        {
            "category":"Restaurant",
            "type":"Food & Drink"
        }
    ],
    "sg:phone":"+1 450 839 2433",
    "sg:postcode":"J0K 2L0",
    "sg:province":"QC",
    "wof:name":"Restaurant 125 Feuille",
    "wof:placetype":"venue"
},
  "geometry": {"coordinates":[-73.699226,45.932888],"type":"Point"}
}