{
  "type": "Feature",
  "properties": {
    "addr:full":"39 Skotoko Pl Okotoks AB T1S 1R5",
    "addr:housenumber":"39",
    "addr:postcode":"t1s 1r5",
    "addr:street":"Skotoko Pl Okotoks Ab",
    "iso:country":"CA",
    "sg:address":"39 Skotoko Pl",
    "sg:city":"Okotoks",
    "sg:classifiers":[
        {
            "category":"Real Estate",
            "subcategory":"Real Estate Agent",
            "type":"Services"
        }
    ],
    "sg:phone":"+1 403 938 5520",
    "sg:postcode":"T1S 1R5",
    "sg:province":"AB",
    "sg:tags":[
        "housing",
        "cooperative"
    ],
    "wof:name":"Skotoko Housing CO-OP Ltd",
    "wof:placetype":"venue"
},
  "geometry": {"coordinates":[-113.958961487,50.726764679],"type":"Point"}
}