{
  "type": "Feature",
  "properties": {
    "addr:full":"5338 51 Ave Lacombe AB T4L 1N5",
    "addr:housenumber":"5338",
    "addr:postcode":"t4l 1n5",
    "addr:street":"51 Ave",
    "iso:country":"CA",
    "sg:address":"5338 51 Ave",
    "sg:city":"Lacombe",
    "sg:classifiers":[
        {
            "category":"Professional",
            "subcategory":"Computer Services",
            "type":"Services"
        }
    ],
    "sg:phone":"+1 403 782 5432",
    "sg:postcode":"T4L 1N5",
    "sg:province":"AB",
    "sg:tags":[
        "consultant"
    ],
    "wof:name":"Thacker Network Technologies",
    "wof:placetype":"venue"
},
  "geometry": {"coordinates":[-113.736969,52.464779],"type":"Point"}
}