{
  "type": "Feature",
  "properties": {
    "iso:country":"CA",
    "sg:city":"Calgary",
    "sg:classifiers":[
        {
            "category":"Home & Garden",
            "subcategory":"Home Furnishings",
            "type":"Retail Goods"
        }
    ],
    "sg:phone":"+1 403 277 4988",
    "sg:postcode":"T2E 1J8",
    "sg:province":"AB",
    "sg:tags":[
        "interior",
        "consultant",
        "design",
        "venetian",
        "decorator"
    ],
    "wof:name":"Sheila's Drapery",
    "wof:placetype":"venue"
},
  "geometry": {"coordinates":[-114.058982849,51.0671005249],"type":"Point"}
}