{
  "type": "Feature",
  "properties": {
    "addr:full":"2445 17th Sideroad King City ON L7B 1A3",
    "addr:housenumber":"2445",
    "addr:postcode":"l7b 1a3",
    "addr:street":"17Th Sideroad",
    "iso:country":"CA",
    "sg:address":"2445 17th Sideroad",
    "sg:city":"King City",
    "sg:classifiers":[
        {
            "category":"Professional",
            "subcategory":"Management & Consulting",
            "type":"Services"
        }
    ],
    "sg:phone":"+1 905 726 9094",
    "sg:postcode":"L7B 1A3",
    "sg:province":"ON",
    "sg:tags":[
        "consultant",
        "business"
    ],
    "wof:name":"Axis Management Svc",
    "wof:placetype":"venue"
},
  "geometry": {"coordinates":[-79.527512,43.926113],"type":"Point"}
}