{
  "type": "Feature",
  "properties": {
    "addr:full":"Burlington ON L7M 3Z5",
    "addr:postcode":"l7m 3z5",
    "iso:country":"CA",
    "sg:city":"Burlington",
    "sg:classifiers":[
        {
            "category":"Personal",
            "subcategory":"Beauty Salon",
            "type":"Services"
        }
    ],
    "sg:phone":"+1 905 332 1050",
    "sg:postcode":"L7M 3Z5",
    "sg:province":"ON",
    "wof:name":"Linea Uno Family Hair",
    "wof:placetype":"venue"
},
  "geometry": {"coordinates":[-79.80912780760001,43.373210907],"type":"Point"}
}