{
  "type": "Feature",
  "properties": {
    "iso:country":"CA",
    "sg:address":"10 Lebrosse St",
    "sg:city":"Moose Creek",
    "sg:classifiers":[
        {
            "category":"Food & Beverages",
            "subcategory":"Groceries & Convenience Stores",
            "type":"Retail Goods"
        }
    ],
    "sg:phone":"+1 613 538 2288",
    "sg:postcode":"K0C 1W0",
    "sg:province":"ON",
    "sg:tags":[
        "grocer"
    ],
    "wof:name":"Provost General Store",
    "wof:placetype":"venue"
},
  "geometry": {"coordinates":[-74.9748535156,45.2593345642],"type":"Point"}
}