{
  "type": "Feature",
  "properties": {
    "addr:full":"1012 Cuddie Cres Prince George BC V2L 4C2",
    "addr:housenumber":"1012",
    "addr:postcode":"v2l 4c2",
    "addr:street":"Cuddie Cres",
    "iso:country":"CA",
    "sg:address":"1012 Cuddie Cres",
    "sg:city":"Prince George",
    "sg:classifiers":[
        {
            "category":"Organizations",
            "subcategory":"Labor Organization",
            "type":"Services"
        }
    ],
    "sg:phone":"+1 250 563 5159",
    "sg:postcode":"V2L 4C2",
    "sg:province":"BC",
    "wof:name":"Communications Energy Union",
    "wof:placetype":"venue"
},
  "geometry": {"coordinates":[-122.74344600000001,53.9053],"type":"Point"}
}