{
  "type": "Feature",
  "properties": {
    "addr:full":"500 Commercial Dr Lanigan SK S0K 2M0",
    "addr:housenumber":"500",
    "addr:postcode":"s0k 2m0",
    "addr:street":"Commercial Dr",
    "iso:country":"CA",
    "sg:address":"500 Commercial Dr",
    "sg:city":"Lanigan",
    "sg:classifiers":[
        {
            "category":"Restaurant",
            "type":"Food & Drink"
        }
    ],
    "sg:phone":"+1 306 365 2535",
    "sg:postcode":"S0K 2M0",
    "sg:province":"SK",
    "wof:name":"Grandpa Sam's Family Rstrnt",
    "wof:placetype":"venue"
},
  "geometry": {"coordinates":[-105.036155701,51.8458061218],"type":"Point"}
}