{
  "type": "Feature",
  "properties": {
    "addr:full":"18 King St E Oshawa ON L1H 1A9",
    "addr:housenumber":"18",
    "addr:postcode":"l1h 1a9",
    "addr:street":"King St E",
    "iso:country":"CA",
    "sg:address":"18 King St E",
    "sg:city":"Oshawa",
    "sg:classifiers":[
        {
            "category":"Shopping",
            "subcategory":"Florist",
            "type":"Retail Goods"
        }
    ],
    "sg:phone":"+1 905 571 3511",
    "sg:postcode":"L1H 1A9",
    "sg:province":"ON",
    "sg:tags":[
        "shop",
        "gift"
    ],
    "wof:name":"Gift House",
    "wof:placetype":"venue"
},
  "geometry": {"coordinates":[-78.862999,43.897854],"type":"Point"}
}