{
  "type": "Feature",
  "properties": {
    "addr:full":"11467 Wellington Cres Surrey BC V3R 9H1",
    "addr:housenumber":"11467",
    "addr:postcode":"v3r 9h1",
    "addr:street":"Wellington Cres",
    "iso:country":"CA",
    "sg:address":"11467 Wellington Cres",
    "sg:city":"Surrey",
    "sg:classifiers":[
        {
            "category":"Building & Trades",
            "subcategory":"Landscaping Services",
            "type":"Services"
        }
    ],
    "sg:phone":"+1 604 589 5323",
    "sg:postcode":"V3R 9H1",
    "sg:province":"BC",
    "sg:tags":[
        "landscape",
        "contractor"
    ],
    "wof:name":"Goldleaf Garden Care Ltd",
    "wof:placetype":"venue"
},
  "geometry": {"coordinates":[-122.815475464,49.2100334167],"type":"Point"}
}