{
  "type": "Feature",
  "properties": {
    "iso:country":"CA",
    "sg:city":"Waterdown",
    "sg:classifiers":[
        {
            "category":"Organizations",
            "subcategory":"Religious Organization",
            "type":"Services"
        }
    ],
    "sg:phone":"+1 905 689 4857",
    "sg:postcode":"L0R 2H0",
    "sg:province":"ON",
    "sg:tags":[
        "church"
    ],
    "wof:name":"St Thomas Church",
    "wof:placetype":"venue"
},
  "geometry": {"coordinates":[-79.892250061,43.331451416],"type":"Point"}
}