{
  "type": "Feature",
  "properties": {
    "addr:full":"Whitecourt AB T7S 1N6",
    "addr:postcode":"t7s 1n6",
    "iso:country":"CA",
    "sg:city":"Whitecourt",
    "sg:classifiers":[
        {
            "category":"Restaurant",
            "type":"Food & Drink"
        }
    ],
    "sg:phone":"+1 780 778 5286",
    "sg:postcode":"T7S 1N6",
    "sg:province":"AB",
    "wof:name":"K G's Sandwich Bar Ltd",
    "wof:placetype":"venue"
},
  "geometry": {"coordinates":[-115.682434082,54.1406974792],"type":"Point"}
}