{
  "type": "Feature",
  "properties": {
    "addr:full":"9135 39 Ave NW Edmonton AB T6E 5Y2",
    "addr:housenumber":"9135",
    "addr:postcode":"t6e 5y2",
    "addr:street":"39 Ave Nw",
    "iso:country":"CA",
    "sg:address":"9135 39 Ave NW",
    "sg:city":"Edmonton",
    "sg:classifiers":[
        {
            "category":"Mining & Drilling",
            "type":"Manufacturing & Wholesale Goods"
        }
    ],
    "sg:phone":"+1 780 437 2032",
    "sg:postcode":"T6E 5Y2",
    "sg:province":"AB",
    "sg:tags":[
        "field",
        "oil"
    ],
    "wof:name":"Petco Oilfield Products & Supl",
    "wof:placetype":"venue"
},
  "geometry": {"coordinates":[-113.468613,53.473923],"type":"Point"}
}