{
  "type": "Feature",
  "properties": {
    "iso:country":"CA",
    "sg:address":"1241 Rue Saint-Hubert",
    "sg:city":"Montreal",
    "sg:classifiers":[
        {
            "category":"Bars & Pubs",
            "type":"Food & Drink"
        }
    ],
    "sg:phone":"+1 514 845 1571",
    "sg:postcode":"H2L 3Y8",
    "sg:province":"QC",
    "sg:tags":[
        "lounge",
        "cocktail"
    ],
    "wof:name":"Bistro Au Vieux St-Hubert",
    "wof:placetype":"venue"
},
  "geometry": {"coordinates":[-73.5575790405,45.5150184631],"type":"Point"}
}