{
  "type": "Feature",
  "properties": {
    "addr:full":"14573 118 Ave NW Edmonton AB T5L 2M7",
    "addr:housenumber":"14573",
    "addr:postcode":"t5l 2m7",
    "addr:street":"118 Ave Nw",
    "iso:country":"CA",
    "sg:address":"14573 118 Ave NW",
    "sg:city":"Edmonton",
    "sg:classifiers":[
        {
            "category":"Shopping",
            "type":"Retail Goods"
        }
    ],
    "sg:phone":"+1 780 453 5708",
    "sg:postcode":"T5L 2M7",
    "sg:province":"AB",
    "sg:tags":[
        "designer",
        "hot",
        "spa",
        "tub",
        "dealer",
        "pool",
        "swimming"
    ],
    "wof:name":"Total Pool & Spa Care Ltd",
    "wof:placetype":"venue"
},
  "geometry": {"coordinates":[-113.572472,53.570183],"type":"Point"}
}