{
  "type": "Feature",
  "properties": {
    "addr:full":"476 Lancaster Ave Saint John NB E2M 2L7",
    "addr:housenumber":"476",
    "addr:postcode":"e2m 2l7",
    "addr:street":"Lancaster Ave",
    "iso:country":"CA",
    "sg:address":"476 Lancaster Ave",
    "sg:city":"Saint John",
    "sg:classifiers":[
        {
            "category":"Organizations",
            "subcategory":"Religious Organization",
            "type":"Services"
        }
    ],
    "sg:phone":"+1 506 635 8000",
    "sg:postcode":"E2M 2L7",
    "sg:province":"NB",
    "sg:tags":[
        "church"
    ],
    "wof:name":"Hillcrest United Baptist Chr",
    "wof:placetype":"venue"
},
  "geometry": {"coordinates":[-66.084068,45.253597],"type":"Point"}
}