{
  "type": "Feature",
  "properties": {
    "iso:country":"CA",
    "sg:address":"1373 Westdel Bourne",
    "sg:city":"London",
    "sg:classifiers":[
        {
            "category":"Health Services",
            "subcategory":"Medical Lab",
            "type":"Services"
        }
    ],
    "sg:phone":"+1 519 672 2219",
    "sg:postcode":"N6K 4R1",
    "sg:province":"ON",
    "sg:tags":[
        "laboratory"
    ],
    "wof:name":"Den Tech Laboratory",
    "wof:placetype":"venue"
},
  "geometry": {"coordinates":[-81.36251068120001,42.9583358765],"type":"Point"}
}