{
  "type": "Feature",
  "properties": {
    "addr:full":"260 Rue Dorval L'Assomption QC J5W 2Z8",
    "addr:housenumber":"260",
    "addr:postcode":"j5w 2z8",
    "addr:street":"Rue Dorval",
    "iso:country":"CA",
    "sg:address":"260 Rue Dorval",
    "sg:city":"L'Assomption",
    "sg:classifiers":[
        {
            "category":"Shopping",
            "subcategory":"Pharmacy",
            "type":"Retail Goods"
        }
    ],
    "sg:phone":"+1 450 589 5659",
    "sg:postcode":"J5W 2Z8",
    "sg:province":"QC",
    "wof:name":"Pharmacie Eve Des Rochers",
    "wof:placetype":"venue"
},
  "geometry": {"coordinates":[-73.42176055909999,45.8300094604],"type":"Point"}
}