{
  "type": "Feature",
  "properties": {
    "iso:country":"CA",
    "sg:address":"40 Queen St",
    "sg:city":"St Catharines",
    "sg:classifiers":[
        {
            "category":"Professional",
            "subcategory":"Lawyer & Legal Services",
            "type":"Services"
        }
    ],
    "sg:phone":"+1 905 688 6655",
    "sg:postcode":"L2R 5G3",
    "sg:province":"ON",
    "sg:tags":[
        "attorney"
    ],
    "wof:name":"Sullivan Mahoney Llp",
    "wof:placetype":"venue"
},
  "geometry": {"coordinates":[-79.24676513670001,43.1574668884],"type":"Point"}
}