{
  "type": "Feature",
  "properties": {
    "addr:full":"PO Box 58 Champion AB T0L 0R0",
    "addr:housenumber":"po box 58",
    "addr:postcode":"t0l 0r0",
    "iso:country":"CA",
    "sg:address":"PO Box 58",
    "sg:city":"Champion",
    "sg:classifiers":[
        {
            "category":"Organizations",
            "subcategory":"Religious Organization",
            "type":"Services"
        }
    ],
    "sg:phone":"+1 403 897 3955",
    "sg:postcode":"T0L 0R0",
    "sg:province":"AB",
    "sg:tags":[
        "church"
    ],
    "wof:name":"St Mary's Church",
    "wof:placetype":"venue"
},
  "geometry": {"coordinates":[-113.147842,50.238773],"type":"Point"}
}