{
  "type": "Feature",
  "properties": {
    "iso:country":"CA",
    "sg:address":"354 Nash Rd N",
    "sg:city":"Hamilton",
    "sg:classifiers":[
        {
            "category":"Retail",
            "subcategory":"Auto Rental",
            "type":"Services"
        }
    ],
    "sg:phone":"+1 905 573 3330",
    "sg:postcode":"L8H 7P5",
    "sg:province":"ON",
    "sg:tags":[
        "renting",
        "truck",
        "leasing"
    ],
    "wof:name":"Ryder Truck Rental Canada Ltd",
    "wof:placetype":"venue"
},
  "geometry": {"coordinates":[-79.76902771,43.2413864136],"type":"Point"}
}