{
  "type": "Feature",
  "properties": {
    "addr:full":"382 Burton Rd NW Edmonton AB T6R 2J4",
    "addr:housenumber":"382",
    "addr:postcode":"t6r 2j4",
    "addr:street":"Burton Rd Nw",
    "iso:country":"CA",
    "sg:address":"382 Burton Rd NW",
    "sg:city":"Edmonton",
    "sg:classifiers":[
        {
            "category":"Building & Trades",
            "subcategory":"Construction",
            "type":"Services"
        }
    ],
    "sg:phone":"+1 780 436 3438",
    "sg:postcode":"T6R 2J4",
    "sg:province":"AB",
    "sg:tags":[
        "tile",
        "dealer"
    ],
    "wof:name":"Tech Tile Inc",
    "wof:placetype":"venue"
},
  "geometry": {"coordinates":[-113.57054100000001,53.478214],"type":"Point"}
}