{
  "type": "Feature",
  "properties": {
    "iso:country":"CA",
    "sg:address":"1048 Midland Ave",
    "sg:city":"Kingston",
    "sg:classifiers":[
        {
            "category":"Retail",
            "subcategory":"Laundry & Dry Cleaning",
            "type":"Services"
        }
    ],
    "sg:phone":"+1 613 389 7701",
    "sg:postcode":"K7P 2X9",
    "sg:province":"ON",
    "sg:tags":[
        "cleaners"
    ],
    "wof:name":"Dry Cleaners",
    "wof:placetype":"venue"
},
  "geometry": {"coordinates":[-76.573944,44.261154],"type":"Point"}
}