{
  "type": "Feature",
  "properties": {
    "iso:country":"CA",
    "sg:address":"91 Rang York",
    "sg:city":"Saint-Barthelemy",
    "sg:classifiers":[
        {
            "category":"Home & Garden",
            "subcategory":"Household Appliances",
            "type":"Retail Goods"
        }
    ],
    "sg:phone":"+1 450 885 3619",
    "sg:postcode":"J0K 1X0",
    "sg:province":"QC",
    "wof:name":"Clement Brissette Svc Enrg",
    "wof:placetype":"venue"
},
  "geometry": {"coordinates":[-73.11274719239999,46.2046928406],"type":"Point"}
}