{
  "type": "Feature",
  "properties": {
    "addr:full":"675 Av Samson Riviere-Beaudette QC J0P 1R0",
    "addr:housenumber":"675",
    "addr:postcode":"j0p 1r0",
    "addr:street":"Av Samson Riviere-Beaudette",
    "iso:country":"CA",
    "sg:address":"675 Av Samson",
    "sg:city":"Riviere-Beaudette",
    "sg:classifiers":[
        {
            "category":"Building & Trades",
            "subcategory":"Construction",
            "type":"Services"
        }
    ],
    "sg:phone":"+1 450 269 2241",
    "sg:postcode":"J0P 1R0",
    "sg:province":"QC",
    "sg:tags":[
        "foundation"
    ],
    "wof:name":"Fondations Jeno Inc",
    "wof:placetype":"venue"
},
  "geometry": {"coordinates":[-74.31649,45.21162],"type":"Point"}
}