{
  "type": "Feature",
  "properties": {
    "addr:full":"299 Rue Saint-Patrice E Magog QC J1X 1T8",
    "addr:housenumber":"299",
    "addr:postcode":"j1x 1t8",
    "addr:street":"Rue Saint-Patrice E",
    "iso:country":"CA",
    "sg:address":"299 Rue Saint-Patrice E",
    "sg:city":"Magog",
    "sg:classifiers":[
        {
            "category":"Food & Beverages",
            "subcategory":"Groceries & Convenience Stores",
            "type":"Retail Goods"
        }
    ],
    "sg:phone":"+1 819 843 4289",
    "sg:postcode":"J1X 1T8",
    "sg:province":"QC",
    "wof:name":"Depanneur Bergeron",
    "wof:placetype":"venue"
},
  "geometry": {"coordinates":[-72.1383895874,45.2643203735],"type":"Point"}
}