{
  "type": "Feature",
  "properties": {
    "addr:full":"Waterloo ON N2L 5W6",
    "addr:postcode":"n2l 5w6",
    "iso:country":"CA",
    "sg:city":"Waterloo",
    "sg:classifiers":[
        {
            "category":"Food & Beverages",
            "subcategory":"Specialty",
            "type":"Retail Goods"
        }
    ],
    "sg:phone":"+1 519 884 5246",
    "sg:postcode":"N2L 5W6",
    "sg:province":"ON",
    "sg:tags":[
        "health",
        "vitamin",
        "diet"
    ],
    "wof:name":"S & H Health Foods",
    "wof:placetype":"venue"
},
  "geometry": {"coordinates":[-80.5301361084,43.4990577698],"type":"Point"}
}