{
  "type": "Feature",
  "properties": {
    "iso:country":"CA",
    "sg:address":"1230 Landor St",
    "sg:city":"London",
    "sg:classifiers":[
        {
            "category":"Shopping",
            "type":"Retail Goods"
        }
    ],
    "sg:phone":"+1 519 457 6773",
    "sg:postcode":"N5Y 3W5",
    "sg:province":"ON",
    "sg:tags":[
        "decoration",
        "light",
        "christmas"
    ],
    "wof:name":"Festive Lighting",
    "wof:placetype":"venue"
},
  "geometry": {"coordinates":[-81.213989,43.012131],"type":"Point"}
}