{
  "type": "Feature",
  "properties": {
    "addr:full":"Newcastle ON L1B 1B9",
    "addr:postcode":"l1b 1b9",
    "iso:country":"CA",
    "sg:city":"Newcastle",
    "sg:classifiers":[
        {
            "category":"Banks & Credit Unions",
            "subcategory":"Bank",
            "type":"Services"
        }
    ],
    "sg:phone":"+1 905 623 1187",
    "sg:postcode":"L1B 1B9",
    "sg:province":"ON",
    "wof:name":"Royal Bank Financial Group",
    "wof:placetype":"venue"
},
  "geometry": {"coordinates":[-78.61623382569999,43.8992996216],"type":"Point"}
}