{
  "type": "Feature",
  "properties": {
    "addr:full":"Clinton ON N0M 1L0",
    "addr:postcode":"n0m 1l0",
    "iso:country":"CA",
    "sg:city":"Clinton",
    "sg:classifiers":[
        {
            "category":"Manufacturing",
            "subcategory":"Motor Vehicles & Parts",
            "type":"Manufacturing & Wholesale Goods"
        }
    ],
    "sg:phone":"+1 519 482 3364",
    "sg:postcode":"N0M 1L0",
    "sg:province":"ON",
    "sg:tags":[
        "propane",
        "equipment",
        "truck",
        "gas"
    ],
    "wof:name":"Tiesma Tarps & Trailors",
    "wof:placetype":"venue"
},
  "geometry": {"coordinates":[-81.53969573969999,43.6176681519],"type":"Point"}
}