{
  "type": "Feature",
  "properties": {
    "iso:country":"CA",
    "sg:city":"Boucherville",
    "sg:classifiers":[
        {
            "category":"Shopping",
            "subcategory":"Florist",
            "type":"Retail Goods"
        }
    ],
    "sg:phone":"+1 450 641 1752",
    "sg:postcode":"J4B 6P5",
    "sg:province":"QC",
    "wof:name":"Aux Fleurs A Soi",
    "wof:placetype":"venue"
},
  "geometry": {"coordinates":[-73.4341201782,45.5898475647],"type":"Point"}
}