{
  "type": "Feature",
  "properties": {
    "addr:full":"Rte 406 Doyles NL A0N 1J0",
    "addr:postcode":"a0n 1j0",
    "addr:street":"Rte 406",
    "iso:country":"CA",
    "sg:address":"Rte 406",
    "sg:city":"Doyles",
    "sg:classifiers":[
        {
            "category":"Autos & Motor Vehicles",
            "subcategory":"Fuel & Gas Station",
            "type":"Retail Goods"
        }
    ],
    "sg:phone":"+1 709 955 2866",
    "sg:postcode":"A0N 1J0",
    "sg:province":"NL",
    "sg:tags":[
        "oil"
    ],
    "wof:name":"Valley Service Station",
    "wof:placetype":"venue"
},
  "geometry": {"coordinates":[-59.2084617615,47.8256721497],"type":"Point"}
}