{
  "type": "Feature",
  "properties": {
    "addr:full":"230 Boul Saint-Joseph O Drummondville QC J2E 1A2",
    "addr:housenumber":"230",
    "addr:postcode":"j2e 1a2",
    "addr:street":"Boul Saint-Joseph O",
    "iso:country":"CA",
    "sg:address":"230 Boul Saint-Joseph O",
    "sg:city":"Drummondville",
    "sg:classifiers":[
        {
            "category":"Freight",
            "type":"Transportation"
        }
    ],
    "sg:phone":"+1 819 477 2202",
    "sg:postcode":"J2E 1A2",
    "sg:province":"QC",
    "sg:tags":[
        "trucking"
    ],
    "wof:name":"Transport Bourret Inc",
    "wof:placetype":"venue"
},
  "geometry": {"coordinates":[-72.520836,45.89719],"type":"Point"}
}