{
  "type": "Feature",
  "properties": {
    "addr:full":"18223 74 Ave Surrey BC V4N 3G5",
    "addr:housenumber":"18223",
    "addr:postcode":"v4n 3g5",
    "addr:street":"74 Ave",
    "iso:country":"CA",
    "sg:address":"18223 74 Ave",
    "sg:city":"Surrey",
    "sg:classifiers":[
        {
            "category":"Building & Trades",
            "subcategory":"Electrical",
            "type":"Services"
        }
    ],
    "sg:phone":"+1 604 576 6098",
    "sg:postcode":"V4N 3G5",
    "sg:province":"BC",
    "sg:tags":[
        "electric",
        "contractor"
    ],
    "wof:name":"Lenneil Installations Ltd",
    "wof:placetype":"venue"
},
  "geometry": {"coordinates":[-122.716995,49.137035],"type":"Point"}
}