{
  "type": "Feature",
  "properties": {
    "addr:full":"5700 Av Kellert Cote Saint-Luc QC H4W 1T4",
    "addr:housenumber":"5700",
    "addr:postcode":"h4w 1t4",
    "addr:street":"Av Kellert Cote",
    "iso:country":"CA",
    "sg:address":"5700 Av Kellert",
    "sg:city":"Cote Saint-Luc",
    "sg:classifiers":[
        {
            "category":"Education",
            "subcategory":"School",
            "type":"Public Place"
        }
    ],
    "sg:phone":"+1 514 489 5321",
    "sg:postcode":"H4W 1T4",
    "sg:province":"QC",
    "wof:name":"Hebrew Academy",
    "wof:placetype":"venue"
},
  "geometry": {"coordinates":[-73.6622543335,45.4734153748],"type":"Point"}
}