{
  "type": "Feature",
  "properties": {
    "addr:full":"6750 Malden Rd Maidstone ON N0R 1K0",
    "addr:housenumber":"6750",
    "addr:postcode":"n0r 1k0",
    "addr:street":"Malden Rd",
    "iso:country":"CA",
    "sg:address":"6750 Malden Rd",
    "sg:city":"Maidstone",
    "sg:classifiers":[
        {
            "category":"Freight",
            "type":"Transportation"
        }
    ],
    "sg:phone":"+1 519 737 1909",
    "sg:postcode":"N0R 1K0",
    "sg:province":"ON",
    "sg:tags":[
        "trucking"
    ],
    "wof:name":"Express Transportation Systems",
    "wof:placetype":"venue"
},
  "geometry": {"coordinates":[-82.90023040769999,42.2008018494],"type":"Point"}
}