{
  "type": "Feature",
  "properties": {
    "iso:country":"CA",
    "sg:city":"Bancroft",
    "sg:classifiers":[
        {
            "category":"Organizations",
            "subcategory":"Religious Organization",
            "type":"Services"
        }
    ],
    "sg:phone":"+1 613 332 6966",
    "sg:postcode":"K0L 1C0",
    "sg:province":"ON",
    "sg:tags":[
        "church"
    ],
    "wof:name":"Bridge Community Church",
    "wof:placetype":"venue"
},
  "geometry": {"coordinates":[-77.80415344239999,45.0239830017],"type":"Point"}
}