{
  "type": "Feature",
  "properties": {
    "iso:country":"CA",
    "sg:address":"32 Rue Saint-Louis",
    "sg:city":"Lemoyne",
    "sg:classifiers":[
        {
            "category":"Education",
            "subcategory":"Special Training",
            "type":"Public Place"
        }
    ],
    "sg:phone":"+1 450 466 0076",
    "sg:postcode":"J4R 2L4",
    "sg:province":"QC",
    "sg:tags":[
        "literacy"
    ],
    "wof:name":"Alphabetisation Iota",
    "wof:placetype":"venue"
},
  "geometry": {"coordinates":[-73.49884,45.495934],"type":"Point"}
}