{
  "type": "Feature",
  "properties": {
    "addr:full":"1782 Regent St Sudbury ON P3E 3Z8",
    "addr:housenumber":"1782",
    "addr:postcode":"p3e 3z8",
    "addr:street":"Regent St",
    "iso:country":"CA",
    "sg:address":"1782 Regent St",
    "sg:city":"Sudbury",
    "sg:classifiers":[
        {
            "category":"Organizations",
            "subcategory":"Political Organization",
            "type":"Services"
        }
    ],
    "sg:phone":"+1 705 522 7770",
    "sg:postcode":"P3E 3Z8",
    "sg:province":"ON",
    "wof:name":"Progressive Conservative Assn",
    "wof:placetype":"venue"
},
  "geometry": {"coordinates":[-81.0053329468,46.4541130066],"type":"Point"}
}