{
  "type": "Feature",
  "properties": {
    "iso:country":"CA",
    "sg:address":"15 Spruce St",
    "sg:city":"Ear Falls",
    "sg:classifiers":[
        {
            "category":"Education",
            "subcategory":"School",
            "type":"Public Place"
        }
    ],
    "sg:phone":"+1 807 222 2413",
    "sg:postcode":"P0V 1T0",
    "sg:province":"ON",
    "wof:name":"Adult Learning Ctr",
    "wof:placetype":"venue"
},
  "geometry": {"coordinates":[-93.239204,50.637161],"type":"Point"}
}