{
  "type": "Feature",
  "properties": {
    "addr:full":"21 Bicentennial Trail Ohsweken ON N0A 1M0",
    "addr:housenumber":"21",
    "addr:postcode":"n0a 1m0",
    "addr:street":"Bicentennial Trail",
    "iso:country":"CA",
    "sg:address":"21 Bicentennial Trail",
    "sg:city":"Ohsweken",
    "sg:classifiers":[
        {
            "category":"Social Services",
            "subcategory":"Child Care",
            "type":"Services"
        }
    ],
    "sg:phone":"+1 519 445 4411",
    "sg:postcode":"N0A 1M0",
    "sg:province":"ON",
    "sg:tags":[
        "organization",
        "welfare"
    ],
    "wof:name":"Six Nations Child Care Ctr",
    "wof:placetype":"venue"
},
  "geometry": {"coordinates":[-80.1202545166,43.0716285706],"type":"Point"}
}