{
  "type": "Feature",
  "properties": {
    "addr:full":"Troy ON L0R 2B0",
    "addr:postcode":"l0r 2b0",
    "iso:country":"CA",
    "sg:city":"Troy",
    "sg:classifiers":[
        {
            "category":"Building & Trades",
            "subcategory":"Plumbing",
            "type":"Services"
        }
    ],
    "sg:phone":"+1 519 647 2230",
    "sg:postcode":"L0R 2B0",
    "sg:province":"ON",
    "sg:tags":[
        "septic"
    ],
    "wof:name":"Big Bear Pumping Inc",
    "wof:placetype":"venue"
},
  "geometry": {"coordinates":[-80.18364699999999,43.261295],"type":"Point"}
}