{
  "type": "Feature",
  "properties": {
    "addr:full":"510 King St E Toronto ON M5A 1M1",
    "addr:housenumber":"510",
    "addr:postcode":"m5a 1m1",
    "addr:street":"King St E",
    "iso:country":"CA",
    "sg:address":"510 King St E",
    "sg:city":"Toronto",
    "sg:classifiers":[
        {
            "category":"Professional",
            "subcategory":"Printing & Photocopies",
            "type":"Services"
        }
    ],
    "sg:phone":"+1 416 363 9311",
    "sg:postcode":"M5A 1M1",
    "sg:province":"ON",
    "sg:tags":[
        "duplicating",
        "copying"
    ],
    "wof:name":"Print in Ltd",
    "wof:placetype":"venue"
},
  "geometry": {"coordinates":[-79.35746,43.656273],"type":"Point"}
}