{
  "type": "Feature",
  "properties": {
    "addr:full":"Ottawa ON K1K 4C5",
    "addr:postcode":"k1k 4c5",
    "iso:country":"CA",
    "sg:city":"Ottawa",
    "sg:classifiers":[
        {
            "category":"Real Estate",
            "subcategory":"Real Estate Operator",
            "type":"Services"
        }
    ],
    "sg:phone":"+1 613 749 6257",
    "sg:postcode":"K1K 4C5",
    "sg:province":"ON",
    "sg:tags":[
        "condominium"
    ],
    "wof:name":"Carleton Condominum Corp 105",
    "wof:placetype":"venue"
},
  "geometry": {"coordinates":[-75.64252500000001,45.443573],"type":"Point"}
}