{
  "type": "Feature",
  "properties": {
    "iso:country":"CA",
    "sg:address":"112 Matheson St S",
    "sg:city":"Kenora",
    "sg:classifiers":[
        {
            "category":"Restaurant",
            "type":"Food & Drink"
        }
    ],
    "sg:phone":"+1 807 468 6813",
    "sg:postcode":"P9N 1T8",
    "sg:province":"ON",
    "wof:name":"Ho Ho Chinese Food",
    "wof:placetype":"venue"
},
  "geometry": {"coordinates":[-94.48886108400001,49.7670593262],"type":"Point"}
}