{
  "type": "Feature",
  "properties": {
    "iso:country":"CA",
    "sg:address":"404 Balsam Rd NE",
    "sg:city":"Slave Lake",
    "sg:classifiers":[
        {
            "category":"Manufacturing",
            "subcategory":"Tools & Machinery",
            "type":"Manufacturing & Wholesale Goods"
        }
    ],
    "sg:phone":"+1 780 849 3768",
    "sg:postcode":"T0G 2A0",
    "sg:province":"AB",
    "sg:tags":[
        "machine",
        "shop",
        "truck"
    ],
    "wof:name":"Heavy Equipment Repair",
    "wof:placetype":"venue"
},
  "geometry": {"coordinates":[-114.762405395,55.2946052551],"type":"Point"}
}