{
  "type": "Feature",
  "properties": {
    "addr:full":"2889 Woodsia Pl Coquitlam BC V3E 2Y2",
    "addr:housenumber":"2889",
    "addr:postcode":"v3e 2y2",
    "addr:street":"Woodsia Pl",
    "iso:country":"CA",
    "sg:address":"2889 Woodsia Pl",
    "sg:city":"Coquitlam",
    "sg:classifiers":[
        {
            "category":"Manufacturing",
            "subcategory":"Printing",
            "type":"Manufacturing & Wholesale Goods"
        }
    ],
    "sg:phone":"+1 604 468 6928",
    "sg:postcode":"V3E 2Y2",
    "sg:province":"BC",
    "sg:tags":[
        "printer",
        "gold",
        "stamping"
    ],
    "wof:name":"Fantastic Printing & Adv",
    "wof:placetype":"venue"
},
  "geometry": {"coordinates":[-122.80807495099999,49.3032073975],"type":"Point"}
}