{
  "type": "Feature",
  "properties": {
    "iso:country":"CA",
    "sg:address":"1168 Drouillard Rd",
    "sg:city":"Windsor",
    "sg:classifiers":[
        {
            "category":"Recreation",
            "type":"Entertainment"
        }
    ],
    "sg:phone":"+1 519 253 7028",
    "sg:postcode":"N8Y 2R1",
    "sg:province":"ON",
    "sg:tags":[
        "government",
        "hall",
        "auditorium"
    ],
    "wof:name":"Gino A Marcus Community Ctr",
    "wof:placetype":"venue"
},
  "geometry": {"coordinates":[-82.998291,42.318962],"type":"Point"}
}