{
  "type": "Feature",
  "properties": {
    "addr:full":"1168 Drouillard Rd Windsor ON N8Y 2R1",
    "addr:housenumber":"1168",
    "addr:postcode":"n8y 2r1",
    "addr:street":"Drouillard Rd",
    "iso:country":"CA",
    "sg:address":"1168 Drouillard Rd",
    "sg:city":"Windsor",
    "sg:classifiers":[
        {
            "category":"Recreation",
            "type":"Entertainment"
        }
    ],
    "sg:phone":"+1 519 253 7028",
    "sg:postcode":"N8Y 2R1",
    "sg:province":"ON",
    "sg:tags":[
        "government",
        "hall",
        "auditorium"
    ],
    "wof:name":"Gino A Marcus Community Ctr",
    "wof:placetype":"venue"
},
  "geometry": {"coordinates":[-82.99829099999999,42.318962],"type":"Point"}
}