{
  "type": "Feature",
  "properties": {
    "iso:country":"CA",
    "sg:address":"2158 Kilbride St",
    "sg:city":"Kilbride",
    "sg:classifiers":[
        {
            "category":"Building & Trades",
            "subcategory":"Electrical",
            "type":"Services"
        }
    ],
    "sg:phone":"+1 905 336 6557",
    "sg:postcode":"L0P 1G0",
    "sg:province":"ON",
    "sg:tags":[
        "electric",
        "contractor"
    ],
    "wof:name":"J & J Electrical Installations",
    "wof:placetype":"venue"
},
  "geometry": {"coordinates":[-79.936539,43.42551],"type":"Point"}
}