{
  "type": "Feature",
  "properties": {
    "addr:full":"Driftwood Rd Smithers BC V0J 2N7",
    "addr:postcode":"v0j 2n7",
    "addr:street":"Driftwood Rd",
    "iso:country":"CA",
    "sg:address":"Driftwood Rd",
    "sg:city":"Smithers",
    "sg:classifiers":[
        {
            "category":"Manufacturing",
            "subcategory":"Buildings",
            "type":"Manufacturing & Wholesale Goods"
        }
    ],
    "sg:phone":"+1 250 847 3207",
    "sg:postcode":"V0J 2N7",
    "sg:province":"BC",
    "sg:tags":[
        "home",
        "log",
        "cabin"
    ],
    "wof:name":"Eco-Log-Homes",
    "wof:placetype":"venue"
},
  "geometry": {"coordinates":[-127.16537475600001,54.7907409668],"type":"Point"}
}