{
  "type": "Feature",
  "properties": {
    "addr:full":"4050 Boul DE Sainte-Adele Sainte-Adele QC J8B 2N7",
    "addr:housenumber":"4050",
    "addr:postcode":"j8b 2n7",
    "addr:street":"Boul De Sainte-Adele Sainte-Adele",
    "iso:country":"CA",
    "sg:address":"4050 Boul DE Sainte-Adele",
    "sg:city":"Sainte-Adele",
    "sg:classifiers":[
        {
            "category":"Bus Charters",
            "type":"Transportation"
        }
    ],
    "sg:phone":"+1 450 326 3114",
    "sg:postcode":"J8B 2N7",
    "sg:province":"QC",
    "sg:tags":[
        "line",
        "rental"
    ],
    "wof:name":"Autobus Scolaires LA Diligence",
    "wof:placetype":"venue"
},
  "geometry": {"coordinates":[-74.13851165769999,45.9543190002],"type":"Point"}
}