{
  "type": "Feature",
  "properties": {
    "addr:full":"255 Main St Fredericton NB E3A 1E1",
    "addr:housenumber":"255",
    "addr:postcode":"e3a 1e1",
    "addr:street":"Main St",
    "iso:country":"CA",
    "sg:address":"255 Main St",
    "sg:city":"Fredericton",
    "sg:classifiers":[
        {
            "category":"Professional",
            "subcategory":"Lawyer & Legal Services",
            "type":"Services"
        }
    ],
    "sg:phone":"+1 506 458 5959",
    "sg:postcode":"E3A 1E1",
    "sg:province":"NB",
    "sg:tags":[
        "attorney"
    ],
    "wof:name":"Mc Crea, K Chipp",
    "wof:placetype":"venue"
},
  "geometry": {"coordinates":[-66.648765564,45.9763412476],"type":"Point"}
}