{
  "type": "Feature",
  "properties": {
    "iso:country":"CA",
    "sg:address":"2 Macintosh Rd",
    "sg:city":"Port Hawkesbury",
    "sg:classifiers":[
        {
            "category":"Professional",
            "subcategory":"Business Services",
            "type":"Services"
        }
    ],
    "sg:phone":"+1 902 625 3090",
    "sg:postcode":"B9A 3K5",
    "sg:province":"NS",
    "wof:name":"Causeway Business Svc",
    "wof:placetype":"venue"
},
  "geometry": {"coordinates":[-61.3412017822,45.6132888794],"type":"Point"}
}