{
  "type": "Feature",
  "properties": {
    "addr:full":"177 132 Rte E Bonaventure QC G0C 1E0",
    "addr:housenumber":"132",
    "addr:postcode":"g0c 1e0",
    "addr:street":"Rte E",
    "iso:country":"CA",
    "sg:address":"177 132 Rte E",
    "sg:city":"Bonaventure",
    "sg:classifiers":[
        {
            "category":"Home & Garden",
            "subcategory":"Garden Supply",
            "type":"Retail Goods"
        }
    ],
    "sg:phone":"+1 418 534 4502",
    "sg:postcode":"G0C 1E0",
    "sg:province":"QC",
    "sg:tags":[
        "wheel",
        "lawn",
        "alignment"
    ],
    "wof:name":"Alignement Bonaventure",
    "wof:placetype":"venue"
},
  "geometry": {"coordinates":[-65.494446,48.045422],"type":"Point"}
}