{
  "type": "Feature",
  "properties": {
    "addr:full":"610 Cote Joyeuse Saint-Raymond QC G3L 4B1",
    "addr:housenumber":"610",
    "addr:postcode":"g3l 4b1",
    "addr:street":"Cote Joyeuse",
    "iso:country":"CA",
    "sg:address":"610 Cote Joyeuse",
    "sg:city":"Saint-Raymond",
    "sg:classifiers":[
        {
            "category":"Building & Trades",
            "subcategory":"Construction",
            "type":"Services"
        }
    ],
    "sg:phone":"+1 418 337 2747",
    "sg:postcode":"G3L 4B1",
    "sg:province":"QC",
    "sg:tags":[
        "roofing",
        "tin",
        "contractor",
        "plate"
    ],
    "wof:name":"Toitures Maurice Bedard Inc",
    "wof:placetype":"venue"
},
  "geometry": {"coordinates":[-71.834808,46.875469],"type":"Point"}
}