{
  "type": "Feature",
  "properties": {
    "addr:full":"Vancouver BC V6P 3S8",
    "addr:postcode":"v6p 3s8",
    "iso:country":"CA",
    "sg:city":"Vancouver",
    "sg:classifiers":[
        {
            "category":"Manufacturing",
            "subcategory":"Printing",
            "type":"Manufacturing & Wholesale Goods"
        }
    ],
    "sg:phone":"+1 604 325 9969",
    "sg:postcode":"V6P 3S8",
    "sg:province":"BC",
    "sg:tags":[
        "screen"
    ],
    "wof:name":"K & T Screen Printing Ltd",
    "wof:placetype":"venue"
},
  "geometry": {"coordinates":[-123.123367,49.206375],"type":"Point"}
}