{
  "type": "Feature",
  "properties": {
    "addr:full":"8311 Fairmount Dr SE Calgary AB T2H 0Y9",
    "addr:housenumber":"8311",
    "addr:postcode":"t2h 0y9",
    "addr:street":"Fairmount Dr Se",
    "iso:country":"CA",
    "sg:address":"8311 Fairmount Dr SE",
    "sg:city":"Calgary",
    "sg:classifiers":[
        {
            "category":"Restaurant",
            "type":"Food & Drink"
        }
    ],
    "sg:phone":"+1 403 252 5277",
    "sg:postcode":"T2H 0Y9",
    "sg:province":"AB",
    "wof:name":"Subway Sandwiches & Salads",
    "wof:placetype":"venue"
},
  "geometry": {"coordinates":[-114.060150147,50.9793167114],"type":"Point"}
}