{
  "type": "Feature",
  "properties": {
    "addr:full":"2675 Rue Saint-Pierre Drummondville QC J2C 7Y2",
    "addr:housenumber":"2675",
    "addr:postcode":"j2c 7y2",
    "addr:street":"Rue Saint-Pierre",
    "iso:country":"CA",
    "sg:address":"2675 Rue Saint-Pierre",
    "sg:city":"Drummondville",
    "sg:classifiers":[
        {
            "category":"Building & Trades",
            "subcategory":"Construction",
            "type":"Services"
        }
    ],
    "sg:phone":"+1 450 778 5554",
    "sg:postcode":"J2C 7Y2",
    "sg:province":"QC",
    "sg:tags":[
        "general",
        "steam",
        "contractor"
    ],
    "wof:name":"Soresto Inc",
    "wof:placetype":"venue"
},
  "geometry": {"coordinates":[-72.523117,45.865948],"type":"Point"}
}