{
  "type": "Feature",
  "properties": {
    "addr:full":"Rouyn-Noranda QC J9X 2H4",
    "addr:postcode":"j9x 2h4",
    "iso:country":"CA",
    "sg:city":"Rouyn-Noranda",
    "sg:classifiers":[
        {
            "category":"Restaurant",
            "type":"Food & Drink"
        }
    ],
    "sg:phone":"+1 819 797 4442",
    "sg:postcode":"J9X 2H4",
    "sg:province":"QC",
    "wof:name":"Restaurant Au Petit Lutin",
    "wof:placetype":"venue"
},
  "geometry": {"coordinates":[-79.0341491699,48.2791862488],"type":"Point"}
}