{
  "type": "Feature",
  "properties": {
    "addr:full":"Vancouver BC V6H 3W7",
    "addr:postcode":"v6h 3w7",
    "iso:country":"CA",
    "sg:city":"Vancouver",
    "sg:classifiers":[
        {
            "category":"Professional",
            "subcategory":"Advertising",
            "type":"Services"
        }
    ],
    "sg:phone":"+1 604 408 0939",
    "sg:postcode":"V6H 3W7",
    "sg:province":"BC",
    "sg:tags":[
        "counselor"
    ],
    "wof:name":"Hotshop Communications Inc",
    "wof:placetype":"venue"
},
  "geometry": {"coordinates":[-123.13610799999999,49.270882],"type":"Point"}
}