{
  "type": "Feature",
  "properties": {
    "addr:full":"1005 Ottawa St N Kitchener ON N2A 1H2",
    "addr:housenumber":"1005",
    "addr:postcode":"n2a 1h2",
    "addr:street":"Ottawa St N",
    "iso:country":"CA",
    "sg:address":"1005 Ottawa St N",
    "sg:city":"Kitchener",
    "sg:classifiers":[
        {
            "category":"Real Estate",
            "subcategory":"Real Estate Operator",
            "type":"Services"
        }
    ],
    "sg:phone":"+1 519 893 7184",
    "sg:postcode":"N2A 1H2",
    "sg:province":"ON",
    "sg:tags":[
        "mall",
        "shopping",
        "center"
    ],
    "wof:name":"Stanley Park Mall",
    "wof:placetype":"venue"
},
  "geometry": {"coordinates":[-80.445549,43.450317],"type":"Point"}
}