{
  "type": "Feature",
  "properties": {
    "addr:full":"London ON N5W 6E5",
    "addr:postcode":"n5w 6e5",
    "iso:country":"CA",
    "sg:city":"London",
    "sg:classifiers":[
        {
            "category":"Home & Garden",
            "subcategory":"Building Materials",
            "type":"Retail Goods"
        }
    ],
    "sg:phone":"+1 519 661 0591",
    "sg:postcode":"N5W 6E5",
    "sg:province":"ON",
    "sg:tags":[
        "lumber"
    ],
    "wof:name":"Png Hardwoods",
    "wof:placetype":"venue"
},
  "geometry": {"coordinates":[-81.220451,42.998215],"type":"Point"}
}