{
  "type": "Feature",
  "properties": {
    "addr:full":"1608 Rue Fleury E Montreal QC H2C 1S8",
    "addr:housenumber":"1608",
    "addr:postcode":"h2c 1s8",
    "addr:street":"Rue Fleury E",
    "iso:country":"CA",
    "sg:address":"1608 Rue Fleury E",
    "sg:city":"Montreal",
    "sg:classifiers":[
        {
            "category":"Shopping",
            "subcategory":"Clothing, Apparel, & Fashions",
            "type":"Retail Goods"
        }
    ],
    "sg:phone":"+1 514 388 9951",
    "sg:postcode":"H2C 1S8",
    "sg:province":"QC",
    "sg:tags":[
        "tailor"
    ],
    "wof:name":"Tailleur Piccione Enr",
    "wof:placetype":"venue"
},
  "geometry": {"coordinates":[-73.655472,45.564049],"type":"Point"}
}