{
  "type": "Feature",
  "properties": {
    "addr:full":"Vanier ON K1L 7H1",
    "addr:postcode":"k1l 7h1",
    "iso:country":"CA",
    "sg:city":"Vanier",
    "sg:classifiers":[
        {
            "category":"Building & Trades",
            "subcategory":"Plumbing",
            "type":"Services"
        }
    ],
    "sg:phone":"+1 613 746 0441",
    "sg:postcode":"K1L 7H1",
    "sg:province":"ON",
    "sg:tags":[
        "contractor"
    ],
    "wof:name":"A M Turpin Plumbing & Heating",
    "wof:placetype":"venue"
},
  "geometry": {"coordinates":[-75.65922500000001,45.43594],"type":"Point"}
}