{
  "type": "Feature",
  "properties": {
    "addr:full":"3024 52nd Ave E Vancouver BC V5S 1T6",
    "addr:housenumber":"3024",
    "addr:postcode":"v5s 1t6",
    "addr:street":"52Nd Ave E",
    "iso:country":"CA",
    "sg:address":"3024 52nd Ave E",
    "sg:city":"Vancouver",
    "sg:classifiers":[
        {
            "category":"Organizations",
            "subcategory":"Religious Organization",
            "type":"Services"
        }
    ],
    "sg:phone":"+1 604 433 7328",
    "sg:postcode":"V5S 1T6",
    "sg:province":"BC",
    "sg:tags":[
        "church"
    ],
    "wof:name":"Jehovah's Witnesses",
    "wof:placetype":"venue"
},
  "geometry": {"coordinates":[-123.042282105,49.2215614319],"type":"Point"}
}