{
  "type": "Feature",
  "properties": {
    "iso:country":"CA",
    "sg:address":"190 Rue Murray",
    "sg:city":"Montreal",
    "sg:classifiers":[
        {
            "category":"Freight",
            "type":"Transportation"
        }
    ],
    "sg:phone":"+1 514 932 8998",
    "sg:postcode":"H3C 2C7",
    "sg:province":"QC",
    "sg:tags":[
        "courier"
    ],
    "wof:name":"Ics Svc DE Courrier",
    "wof:placetype":"venue"
},
  "geometry": {"coordinates":[-73.559143,45.492413],"type":"Point"}
}