{
  "type": "Feature",
  "properties": {
    "iso:country":"CA",
    "sg:address":"109 Redwood Crt",
    "sg:city":"Welland",
    "sg:classifiers":[
        {
            "category":"Building & Trades",
            "subcategory":"Cleaning & Sanitation",
            "type":"Services"
        }
    ],
    "sg:phone":"+1 905 735 0601",
    "sg:postcode":"L3C 7G7",
    "sg:province":"ON",
    "sg:tags":[
        "janitor"
    ],
    "wof:name":"Regional Janitorial Svc Inc",
    "wof:placetype":"venue"
},
  "geometry": {"coordinates":[-79.2587738037,43.0214080811],"type":"Point"}
}