{
  "type": "Feature",
  "properties": {
    "addr:full":"400 Invermere Mica Creek BC V0E 2L0",
    "addr:housenumber":"400",
    "addr:postcode":"bc v0e 2l0",
    "iso:country":"CA",
    "sg:address":"400 Invermere",
    "sg:city":"Mica Creek",
    "sg:classifiers":[
        {
            "category":"Travel",
            "subcategory":"Hotels & Motels",
            "type":"Entertainment"
        }
    ],
    "sg:phone":"+1 250 834 7272",
    "sg:postcode":"V0E 2L0",
    "sg:province":"BC",
    "wof:name":"North of Fifty Inc",
    "wof:placetype":"venue"
},
  "geometry": {"coordinates":[-118.56648300000001,52.006077],"type":"Point"}
}