{
  "type": "Feature",
  "properties": {
    "addr:full":"517 Parliament St Toronto ON M4X 1P3",
    "addr:housenumber":"517",
    "addr:postcode":"m4x 1p3",
    "addr:street":"Parliament St",
    "iso:country":"CA",
    "sg:address":"517 Parliament St",
    "sg:city":"Toronto",
    "sg:classifiers":[
        {
            "category":"Social Services",
            "type":"Services"
        }
    ],
    "sg:phone":"+1 416 966 8595",
    "sg:postcode":"M4X 1P3",
    "sg:province":"ON",
    "sg:tags":[
        "organization",
        "welfare"
    ],
    "wof:name":"Central Neighbourhood House",
    "wof:placetype":"venue"
},
  "geometry": {"coordinates":[-79.368202,43.665314],"type":"Point"}
}