{
  "type": "Feature",
  "properties": {
    "addr:full":"813 Gerrard St E Toronto ON M4M 1Y8",
    "addr:housenumber":"813",
    "addr:postcode":"m4m 1y8",
    "addr:street":"Gerrard St E",
    "iso:country":"CA",
    "sg:address":"813 Gerrard St E",
    "sg:city":"Toronto",
    "sg:classifiers":[
        {
            "category":"Food & Beverages",
            "subcategory":"Groceries & Convenience Stores",
            "type":"Retail Goods"
        }
    ],
    "sg:phone":"+1 416 461 6766",
    "sg:postcode":"M4M 1Y8",
    "sg:province":"ON",
    "wof:name":"Arsema Variety Store",
    "wof:placetype":"venue"
},
  "geometry": {"coordinates":[-79.34468099999999,43.667049],"type":"Point"}
}