{
  "type": "Feature",
  "properties": {
    "addr:full":"119 1st St E North Vancouver BC V7L 1B2",
    "addr:housenumber":"119",
    "addr:postcode":"v7l 1b2",
    "addr:street":"1St St E",
    "iso:country":"CA",
    "sg:address":"119 1st St E",
    "sg:city":"North Vancouver",
    "sg:classifiers":[
        {
            "category":"Wholesale",
            "subcategory":"Apparel",
            "type":"Manufacturing & Wholesale Goods"
        }
    ],
    "sg:phone":"+1 604 987 1175",
    "sg:postcode":"V7L 1B2",
    "sg:province":"BC",
    "wof:name":"Love Nest",
    "wof:placetype":"venue"
},
  "geometry": {"coordinates":[-123.076927185,49.3109817505],"type":"Point"}
}