{
  "type": "Feature",
  "properties": {
    "iso:country":"CA",
    "sg:address":"4 Manitoba St",
    "sg:city":"Bracebridge",
    "sg:classifiers":[
        {
            "category":"Shopping",
            "type":"Retail Goods"
        }
    ],
    "sg:phone":"+1 705 646 2460",
    "sg:postcode":"P1L 1R9",
    "sg:province":"ON",
    "sg:tags":[
        "art",
        "gallery",
        "dealer"
    ],
    "wof:name":"Silver Bridge Gallery",
    "wof:placetype":"venue"
},
  "geometry": {"coordinates":[-79.30896,45.040283],"type":"Point"}
}