{
  "type": "Feature",
  "properties": {
    "addr:full":"Pickle Lake ON P0V 3A0",
    "addr:postcode":"p0v 3a0",
    "iso:country":"CA",
    "sg:city":"Pickle Lake",
    "sg:classifiers":[
        {
            "category":"Autos & Motor Vehicles",
            "subcategory":"Fuel & Gas Station",
            "type":"Retail Goods"
        }
    ],
    "sg:phone":"+1 807 928 2589",
    "sg:postcode":"P0V 3A0",
    "sg:province":"ON",
    "sg:tags":[
        "automobile",
        "oil",
        "dealer"
    ],
    "wof:name":"Patricia Auto Sales & Svc Ltd",
    "wof:placetype":"venue"
},
  "geometry": {"coordinates":[-90.16166699999999,51.479946],"type":"Point"}
}