{
  "type": "Feature",
  "properties": {
    "addr:full":"22 Rue Blais Saint-Basile-Le-Grand QC J3N 1R5",
    "addr:housenumber":"22",
    "addr:postcode":"j3n 1r5",
    "addr:street":"Rue Blais",
    "iso:country":"CA",
    "sg:address":"22 Rue Blais",
    "sg:city":"Saint-Basile-Le-Grand",
    "sg:classifiers":[
        {
            "category":"Health Services",
            "subcategory":"Health Practitioner",
            "type":"Services"
        }
    ],
    "sg:phone":"+1 450 653 6060",
    "sg:postcode":"J3N 1R5",
    "sg:province":"QC",
    "sg:tags":[
        "acupuncture"
    ],
    "wof:name":"Clinique Medicine Traditionnel",
    "wof:placetype":"venue"
},
  "geometry": {"coordinates":[-73.2893829346,45.5339813232],"type":"Point"}
}