{
  "type": "Feature",
  "properties": {
    "addr:full":"2 Chrislea Rd Woodbridge ON L4L 8V1",
    "addr:housenumber":"2",
    "addr:postcode":"l4l 8v1",
    "addr:street":"Chrislea Rd",
    "iso:country":"CA",
    "sg:address":"2 Chrislea Rd",
    "sg:city":"Woodbridge",
    "sg:classifiers":[
        {
            "category":"Home & Garden",
            "subcategory":"Furniture",
            "type":"Retail Goods"
        }
    ],
    "sg:phone":"+1 905 850 6406",
    "sg:postcode":"L4L 8V1",
    "sg:province":"ON",
    "sg:tags":[
        "appliance"
    ],
    "wof:name":"Sears Canada Inc",
    "wof:placetype":"venue"
},
  "geometry": {"coordinates":[-79.54820251460001,43.7931632996],"type":"Point"}
}