{
  "type": "Feature",
  "properties": {
    "addr:full":"70 Rue DE Gatineau Canton-DE-Granby QC J2G 8C8",
    "addr:housenumber":"70",
    "addr:postcode":"j2g 8c8",
    "addr:street":"Rue De Gatineau Canton-De-Granby",
    "iso:country":"CA",
    "sg:address":"70 Rue DE Gatineau",
    "sg:city":"Canton-DE-Granby",
    "sg:classifiers":[
        {
            "category":"Building & Trades",
            "subcategory":"Construction",
            "type":"Services"
        }
    ],
    "sg:phone":"+1 450 378 1623",
    "sg:postcode":"J2G 8C8",
    "sg:province":"QC",
    "sg:tags":[
        "excavating",
        "contractor",
        "general"
    ],
    "wof:name":"Allaire & Gince Ent",
    "wof:placetype":"venue"
},
  "geometry": {"coordinates":[-72.7217712402,45.3979949951],"type":"Point"}
}