{
  "type": "Feature",
  "properties": {
    "addr:full":"Fredericton NB E3B 1B6",
    "addr:postcode":"e3b 1b6",
    "iso:country":"CA",
    "sg:city":"Fredericton",
    "sg:classifiers":[
        {
            "category":"Insurance",
            "subcategory":"Insurance Agent",
            "type":"Services"
        }
    ],
    "sg:phone":"+1 506 452 1506",
    "sg:postcode":"E3B 1B6",
    "sg:province":"NB",
    "sg:tags":[
        "consultant",
        "planning",
        "financial"
    ],
    "wof:name":"Estate Financial Inc",
    "wof:placetype":"venue"
},
  "geometry": {"coordinates":[-66.64115099999999,45.962044],"type":"Point"}
}