{
  "type": "Feature",
  "properties": {
    "addr:full":"1 Place Du Commerce Verdun QC H3E 1A2",
    "addr:housenumber":"1",
    "addr:postcode":"h3e 1a2",
    "addr:street":"Place Du Commerce",
    "iso:country":"CA",
    "sg:address":"1 Place Du Commerce",
    "sg:city":"Verdun",
    "sg:classifiers":[
        {
            "category":"Health Services",
            "subcategory":"Health Practitioner",
            "type":"Services"
        }
    ],
    "sg:phone":"+1 514 768 8857",
    "sg:postcode":"H3E 1A2",
    "sg:province":"QC",
    "sg:tags":[
        "physician"
    ],
    "wof:name":"Centre European DE Medicine",
    "wof:placetype":"venue"
},
  "geometry": {"coordinates":[-73.571762085,45.4590187073],"type":"Point"}
}