{
  "type": "Feature",
  "properties": {
    "addr:full":"3579 Ponytrail Dr Mississauga ON L4X 1V9",
    "addr:housenumber":"3579",
    "addr:postcode":"l4x 1v9",
    "addr:street":"Ponytrail Dr",
    "iso:country":"CA",
    "sg:address":"3579 Ponytrail Dr",
    "sg:city":"Mississauga",
    "sg:classifiers":[
        {
            "category":"Professional",
            "subcategory":"Engineering",
            "type":"Services"
        }
    ],
    "sg:phone":"+1 905 602 0400",
    "sg:postcode":"L4X 1V9",
    "sg:province":"ON",
    "sg:tags":[
        "engineer"
    ],
    "wof:name":"Sigma Engineering Group Ltd",
    "wof:placetype":"venue"
},
  "geometry": {"coordinates":[-79.58783699999999,43.631405],"type":"Point"}
}