{
  "type": "Feature",
  "properties": {
    "iso:country":"CA",
    "sg:address":"1031 Rock Castle Rd",
    "sg:city":"Severn Bridge",
    "sg:classifiers":[
        {
            "category":"Manufacturing",
            "subcategory":"Tools & Machinery",
            "type":"Manufacturing & Wholesale Goods"
        }
    ],
    "sg:phone":"+1 705 689 5022",
    "sg:postcode":"P0E 1N0",
    "sg:province":"ON",
    "sg:tags":[
        "machine",
        "die",
        "maker",
        "shop"
    ],
    "wof:name":"Mc Intyre Tool & Die",
    "wof:placetype":"venue"
},
  "geometry": {"coordinates":[-79.37036895750001,44.7753486633],"type":"Point"}
}