{
  "type": "Feature",
  "properties": {
    "iso:country":"CA",
    "sg:address":"12 Flemington Rd",
    "sg:city":"North York",
    "sg:classifiers":[
        {
            "category":"Health Services",
            "subcategory":"Doctor",
            "type":"Services"
        }
    ],
    "sg:phone":"+1 416 787 1661",
    "sg:postcode":"M6A 2N4",
    "sg:province":"ON",
    "sg:tags":[
        "clinic"
    ],
    "wof:name":"Lawrence Heights Community Ctr",
    "wof:placetype":"venue"
},
  "geometry": {"coordinates":[-79.4447479248,43.7194328308],"type":"Point"}
}