{
  "type": "Feature",
  "properties": {
    "addr:full":"1076 Ogilvie Rd Gloucester ON K1J 7P8",
    "addr:housenumber":"1076",
    "addr:postcode":"k1j 7p8",
    "addr:street":"Ogilvie Rd",
    "iso:country":"CA",
    "sg:address":"1076 Ogilvie Rd",
    "sg:city":"Gloucester",
    "sg:classifiers":[
        {
            "category":"Personal",
            "subcategory":"Beauty Salon",
            "type":"Services"
        }
    ],
    "sg:phone":"+1 613 748 1222",
    "sg:postcode":"K1J 7P8",
    "sg:province":"ON",
    "wof:name":"Clip Joint",
    "wof:placetype":"venue"
},
  "geometry": {"coordinates":[-75.63297300000001,45.425488],"type":"Point"}
}