{
  "type": "Feature",
  "properties": {
    "addr:full":"168 Thames Rd Exeter ON N0M 1S3",
    "addr:housenumber":"168",
    "addr:postcode":"n0m 1s3",
    "addr:street":"Thames Rd",
    "iso:country":"CA",
    "sg:address":"168 Thames Rd",
    "sg:city":"Exeter",
    "sg:classifiers":[
        {
            "category":"Autos & Motor Vehicles",
            "subcategory":"Automobile Sales",
            "type":"Retail Goods"
        }
    ],
    "sg:phone":"+1 519 235 3922",
    "sg:postcode":"N0M 1S3",
    "sg:province":"ON",
    "sg:tags":[
        "car",
        "dealer"
    ],
    "wof:name":"Paul's Auto Marine",
    "wof:placetype":"venue"
},
  "geometry": {"coordinates":[-81.47760009770001,43.3625488281],"type":"Point"}
}