{
  "type": "Feature",
  "properties": {
    "addr:full":"293 Place St Lucknow ON N0G 2H0",
    "addr:housenumber":"293",
    "addr:postcode":"n0g 2h0",
    "addr:street":"Place St",
    "iso:country":"CA",
    "sg:address":"293 Place St",
    "sg:city":"Lucknow",
    "sg:classifiers":[
        {
            "category":"Organizations",
            "subcategory":"Religious Organization",
            "type":"Services"
        }
    ],
    "sg:phone":"+1 519 528 3133",
    "sg:postcode":"N0G 2H0",
    "sg:province":"ON",
    "sg:tags":[
        "church"
    ],
    "wof:name":"Christian Reformed Church",
    "wof:placetype":"venue"
},
  "geometry": {"coordinates":[-81.519524,43.956326],"type":"Point"}
}