{
  "type": "Feature",
  "properties": {
    "iso:country":"CA",
    "sg:address":"768 Lingan Rd",
    "sg:city":"Sydney",
    "sg:classifiers":[
        {
            "category":"Shopping",
            "subcategory":"Clothing, Apparel, & Fashions",
            "type":"Retail Goods"
        }
    ],
    "sg:phone":"+1 902 539 8027",
    "sg:postcode":"B1N 3K6",
    "sg:province":"NS",
    "sg:tags":[
        "salvage",
        "surplus",
        "merchandise"
    ],
    "wof:name":"East Side Auto Salvage Ltd",
    "wof:placetype":"venue"
},
  "geometry": {"coordinates":[-60.160369873,46.1757278442],"type":"Point"}
}