{
  "type": "Feature",
  "properties": {
    "addr:full":"119 Westglen Cres Spruce Grove AB T7X 1V7",
    "addr:housenumber":"119",
    "addr:postcode":"t7x 1v7",
    "addr:street":"Westglen Cres",
    "iso:country":"CA",
    "sg:address":"119 Westglen Cres",
    "sg:city":"Spruce Grove",
    "sg:classifiers":[
        {
            "category":"Shopping",
            "subcategory":"Stationery & Office Supplies",
            "type":"Retail Goods"
        }
    ],
    "sg:phone":"+1 780 487 8533",
    "sg:postcode":"T7X 1V7",
    "sg:province":"AB",
    "sg:tags":[
        "equipment",
        "system",
        "filing"
    ],
    "wof:name":"Dasco Data Products Ltd",
    "wof:placetype":"venue"
},
  "geometry": {"coordinates":[-113.92139400000001,53.544098],"type":"Point"}
}