{
  "type": "Feature",
  "properties": {
    "addr:full":"269 Boul Labelle Rosemere QC J7A 2H3",
    "addr:housenumber":"269",
    "addr:postcode":"j7a 2h3",
    "addr:street":"Boul Labelle",
    "iso:country":"CA",
    "sg:address":"269 Boul Labelle",
    "sg:city":"Rosemere",
    "sg:classifiers":[
        {
            "category":"Wholesale",
            "subcategory":"Construction Materials",
            "type":"Manufacturing & Wholesale Goods"
        }
    ],
    "sg:phone":"+1 450 433 1451",
    "sg:postcode":"J7A 2H3",
    "sg:province":"QC",
    "sg:tags":[
        "floor"
    ],
    "wof:name":"Centre Ceramique Rosemere Enr",
    "wof:placetype":"venue"
},
  "geometry": {"coordinates":[-73.80749511720001,45.6270484924],"type":"Point"}
}