{
  "type": "Feature",
  "properties": {
    "iso:country":"CA",
    "sg:address":"188 Bunting Rd",
    "sg:city":"St Catharines",
    "sg:classifiers":[
        {
            "category":"Manufacturing",
            "subcategory":"Soap",
            "type":"Manufacturing & Wholesale Goods"
        }
    ],
    "sg:phone":"+1 905 682 1808",
    "sg:postcode":"L2M 3Y1",
    "sg:province":"ON",
    "sg:tags":[
        "detergent"
    ],
    "wof:name":"Soap Factory",
    "wof:placetype":"venue"
},
  "geometry": {"coordinates":[-79.20970153810001,43.1706199646],"type":"Point"}
}