{
  "type": "Feature",
  "properties": {
    "addr:full":"5581 Av Royalmount Mont-Royal QC H4P 1J3",
    "addr:housenumber":"5581",
    "addr:postcode":"h4p 1j3",
    "addr:street":"Av Royalmount",
    "iso:country":"CA",
    "sg:address":"5581 Av Royalmount",
    "sg:city":"Mont-Royal",
    "sg:classifiers":[
        {
            "category":"Home & Garden",
            "subcategory":"Building Materials",
            "type":"Retail Goods"
        }
    ],
    "sg:phone":"+1 514 735 1651",
    "sg:postcode":"H4P 1J3",
    "sg:province":"QC",
    "sg:tags":[
        "glass",
        "window",
        "plate"
    ],
    "wof:name":"Housses D'Autos Henri Inc",
    "wof:placetype":"venue"
},
  "geometry": {"coordinates":[-73.666382,45.494511],"type":"Point"}
}