{
  "type": "Feature",
  "properties": {
    "addr:full":"300 Av Duluth E Montreal QC H2W 1H9",
    "addr:postcode":"h2w 1h9",
    "addr:street":"300 Av Duluth E",
    "iso:country":"CA",
    "sg:address":"300 Av Duluth E",
    "sg:city":"Montreal",
    "sg:classifiers":[
        {
            "category":"Restaurant",
            "type":"Food & Drink"
        }
    ],
    "sg:phone":"+1 514 281 6788",
    "sg:postcode":"H2W 1H9",
    "sg:province":"QC",
    "wof:name":"Restaurant Tay DO",
    "wof:placetype":"venue"
},
  "geometry": {"coordinates":[-73.5767440796,45.5197601318],"type":"Point"}
}