{
  "type": "Feature",
  "properties": {
    "iso:country":"CA",
    "sg:address":"3300 Alexis Park Dr",
    "sg:city":"Vernon",
    "sg:classifiers":[
        {
            "category":"Organizations",
            "subcategory":"Religious Organization",
            "type":"Services"
        }
    ],
    "sg:phone":"+1 250 545 0797",
    "sg:postcode":"V1T 6G8",
    "sg:province":"BC",
    "sg:tags":[
        "church"
    ],
    "wof:name":"Trinity United Church",
    "wof:placetype":"venue"
},
  "geometry": {"coordinates":[-119.28457641599999,50.2653007507],"type":"Point"}
}