{
  "type": "Feature",
  "properties": {
    "addr:full":"Nepean ON K2E 7S4",
    "addr:postcode":"k2e 7s4",
    "iso:country":"CA",
    "sg:city":"Nepean",
    "sg:classifiers":[
        {
            "category":"Utilities",
            "subcategory":"Telephone",
            "type":"Services"
        }
    ],
    "sg:phone":"+1 613 274 0606",
    "sg:postcode":"K2E 7S4",
    "sg:province":"ON",
    "sg:tags":[
        "distance",
        "long"
    ],
    "wof:name":"Sussex Long Distance",
    "wof:placetype":"venue"
},
  "geometry": {"coordinates":[-75.70549800000001,45.3437],"type":"Point"}
}