{
  "type": "Feature",
  "properties": {
    "addr:full":"63 1E Av O Amos QC J9T 1T7",
    "addr:housenumber":"63",
    "addr:postcode":"j9t 1t7",
    "addr:street":"1E Av O Amos",
    "iso:country":"CA",
    "sg:address":"63 1E Av O",
    "sg:city":"Amos",
    "sg:classifiers":[
        {
            "category":"Restaurant",
            "type":"Food & Drink"
        }
    ],
    "sg:phone":"+1 819 732 4564",
    "sg:postcode":"J9T 1T7",
    "sg:province":"QC",
    "wof:name":"Restaurant Beau Coq Bar Bq",
    "wof:placetype":"venue"
},
  "geometry": {"coordinates":[-78.114364624,48.572052002],"type":"Point"}
}