{
  "type": "Feature",
  "properties": {
    "iso:country":"CA",
    "sg:address":"3368 Tallman Dr",
    "sg:city":"Vineland",
    "sg:classifiers":[
        {
            "category":"Manufacturing",
            "subcategory":"Signs",
            "type":"Manufacturing & Wholesale Goods"
        }
    ],
    "sg:phone":"+1 905 562 6422",
    "sg:postcode":"L0R 2C0",
    "sg:province":"ON",
    "wof:name":"Peter Junlke Signs",
    "wof:placetype":"venue"
},
  "geometry": {"coordinates":[-79.391494751,43.1512680054],"type":"Point"}
}