{
  "type": "Feature",
  "properties": {
    "iso:country":"CA",
    "sg:address":"2254 Hamilton Dr",
    "sg:city":"Port Alberni",
    "sg:classifiers":[
        {
            "category":"Travel",
            "subcategory":"Hotels & Motels",
            "type":"Entertainment"
        }
    ],
    "sg:phone":"+1 250 723 1000",
    "sg:postcode":"V9Y 1B6",
    "sg:province":"BC",
    "sg:tags":[
        "resort"
    ],
    "wof:name":"Eagle Nook Ocean Wilderness",
    "wof:placetype":"venue"
},
  "geometry": {"coordinates":[-124.804328919,49.2202949524],"type":"Point"}
}