{
  "type": "Feature",
  "properties": {
    "iso:country":"CA",
    "sg:address":"305 Rue Saint-Vallier",
    "sg:city":"Chicoutimi",
    "sg:classifiers":[
        {
            "category":"Health Services",
            "subcategory":"Doctor",
            "type":"Services"
        }
    ],
    "sg:phone":"+1 418 541 1079",
    "sg:postcode":"G7H 5H6",
    "sg:province":"QC",
    "sg:tags":[
        "clinic"
    ],
    "wof:name":"Clinique Unite DE Medicine",
    "wof:placetype":"venue"
},
  "geometry": {"coordinates":[-71.050148,48.426315],"type":"Point"}
}