{
  "type": "Feature",
  "properties": {
    "addr:full":"680 Kingston Ave Kamloops BC V2B 2C8",
    "addr:housenumber":"680",
    "addr:postcode":"bc v2b 2c8",
    "addr:street":"Kingston Ave",
    "iso:country":"CA",
    "sg:address":"680 Kingston Ave",
    "sg:city":"Kamloops",
    "sg:classifiers":[
        {
            "category":"Manufacturing",
            "subcategory":"Building Materials",
            "type":"Manufacturing & Wholesale Goods"
        }
    ],
    "sg:phone":"+1 250 376 8711",
    "sg:postcode":"V2B 2C8",
    "sg:province":"BC",
    "wof:name":"Excel Industries Ltd",
    "wof:placetype":"venue"
},
  "geometry": {"coordinates":[-120.35955800000001,50.711212],"type":"Point"}
}