{
  "type": "Feature",
  "properties": {
    "addr:full":"Drumbo ON N0J 1G0",
    "addr:postcode":"n0j 1g0",
    "iso:country":"CA",
    "sg:city":"Drumbo",
    "sg:classifiers":[
        {
            "category":"Retail",
            "subcategory":"Laundry & Dry Cleaning",
            "type":"Services"
        }
    ],
    "sg:phone":"+1 519 463 5239",
    "sg:postcode":"N0J 1G0",
    "sg:province":"ON",
    "sg:tags":[
        "cleaners",
        "rug",
        "carpet"
    ],
    "wof:name":"Steamatic of Oxford",
    "wof:placetype":"venue"
},
  "geometry": {"coordinates":[-80.5528793335,43.2367553711],"type":"Point"}
}