{
  "type": "Feature",
  "properties": {
    "addr:full":"1403 29 St NW Calgary AB T2N 2T9",
    "addr:housenumber":"1403",
    "addr:postcode":"t2n 2t9",
    "addr:street":"29 St Nw",
    "iso:country":"CA",
    "sg:address":"1403 29 St NW",
    "sg:city":"Calgary",
    "sg:classifiers":[
        {
            "category":"Health Services",
            "subcategory":"Doctor",
            "type":"Services"
        }
    ],
    "sg:phone":"+1 403 944 1571",
    "sg:postcode":"T2N 2T9",
    "sg:province":"AB",
    "sg:tags":[
        "physician",
        "surgeon"
    ],
    "wof:name":"Klassen, John MD",
    "wof:placetype":"venue"
},
  "geometry": {"coordinates":[-114.130821,51.064762],"type":"Point"}
}