{
  "type": "Feature",
  "properties": {
    "addr:full":"1136 Ch Du Grand-Ruisseau St-Sauveur QC J0R 1R2",
    "addr:housenumber":"1136",
    "addr:postcode":"j0r 1r2",
    "addr:street":"Ch Du Grand-Ruisseau St-Sauveur",
    "iso:country":"CA",
    "sg:address":"1136 Ch Du Grand-Ruisseau",
    "sg:city":"St-Sauveur",
    "sg:classifiers":[
        {
            "category":"Building & Trades",
            "subcategory":"Landscaping Services",
            "type":"Services"
        }
    ],
    "sg:phone":"+1 450 227 5876",
    "sg:postcode":"J0R 1R2",
    "sg:province":"QC",
    "sg:tags":[
        "landscape",
        "contractor"
    ],
    "wof:name":"Entretien Paysager Filiatrault",
    "wof:placetype":"venue"
},
  "geometry": {"coordinates":[-74.2017669678,45.8734588623],"type":"Point"}
}