{
  "type": "Feature",
  "properties": {
    "addr:full":"PO Box 10 Conne River NL A0H 1J0",
    "addr:housenumber":"po box 10",
    "addr:postcode":"a0h 1j0",
    "iso:country":"CA",
    "sg:address":"PO Box 10",
    "sg:city":"Conne River",
    "sg:classifiers":[
        {
            "category":"Autos & Motor Vehicles",
            "subcategory":"Fuel & Gas Station",
            "type":"Retail Goods"
        }
    ],
    "sg:phone":"+1 709 882 2731",
    "sg:postcode":"A0H 1J0",
    "sg:province":"NL",
    "sg:tags":[
        "oil"
    ],
    "wof:name":"Conne River Gas Bar",
    "wof:placetype":"venue"
},
  "geometry": {"coordinates":[-55.699203,47.882755],"type":"Point"}
}