{
  "type": "Feature",
  "properties": {
    "addr:full":"Orleans ON K1C 7E2",
    "addr:postcode":"k1c 7e2",
    "iso:country":"CA",
    "sg:city":"Orleans",
    "sg:classifiers":[
        {
            "category":"Banks & Credit Unions",
            "subcategory":"Bank",
            "type":"Services"
        }
    ],
    "sg:phone":"+1 613 834 2029",
    "sg:postcode":"K1C 7E2",
    "sg:province":"ON",
    "wof:name":"Scotiabank",
    "wof:placetype":"venue"
},
  "geometry": {"coordinates":[-75.52509307859999,45.4597663879],"type":"Point"}
}