{
  "type": "Feature",
  "properties": {
    "addr:full":"1619 Henderson Hwy Winnipeg MB R2G 1N8",
    "addr:housenumber":"1619",
    "addr:postcode":"r2g 1n8",
    "addr:street":"Henderson Hwy",
    "iso:country":"CA",
    "sg:address":"1619 Henderson Hwy",
    "sg:city":"Winnipeg",
    "sg:classifiers":[
        {
            "category":"Retail",
            "subcategory":"Laundry & Dry Cleaning",
            "type":"Services"
        }
    ],
    "sg:phone":"+1 204 338 8622",
    "sg:postcode":"R2G 1N8",
    "sg:province":"MB",
    "sg:tags":[
        "diaper"
    ],
    "wof:name":"Tender Touch Diaper Svc",
    "wof:placetype":"venue"
},
  "geometry": {"coordinates":[-97.0818786621,49.9491348267],"type":"Point"}
}