{
  "type": "Feature",
  "properties": {
    "addr:full":"280 Holiday Inn Dr Cambridge ON N3C 1Z4",
    "addr:housenumber":"280",
    "addr:postcode":"n3c 1z4",
    "addr:street":"Holiday Inn Dr",
    "iso:country":"CA",
    "sg:address":"280 Holiday Inn Dr",
    "sg:city":"Cambridge",
    "sg:classifiers":[
        {
            "category":"Manufacturing",
            "subcategory":"Signs",
            "type":"Manufacturing & Wholesale Goods"
        }
    ],
    "sg:phone":"+1 519 220 0505",
    "sg:postcode":"N3C 1Z4",
    "sg:province":"ON",
    "wof:name":"Pride Signs Ltd",
    "wof:placetype":"venue"
},
  "geometry": {"coordinates":[-80.317237854,43.4168815613],"type":"Point"}
}