{
  "type": "Feature",
  "properties": {
    "addr:full":"25 Yorkwoods Gate North York ON M3N 1K1",
    "addr:housenumber":"25",
    "addr:postcode":"m3n 1k1",
    "addr:street":"Yorkwoods Gate",
    "iso:country":"CA",
    "sg:address":"25 Yorkwoods Gate",
    "sg:city":"North York",
    "sg:classifiers":[
        {
            "category":"Education",
            "subcategory":"School",
            "type":"Public Place"
        }
    ],
    "sg:phone":"+1 416 395 2990",
    "sg:postcode":"M3N 1K1",
    "sg:province":"ON",
    "wof:name":"Yorkwoods Public School",
    "wof:placetype":"venue"
},
  "geometry": {"coordinates":[-79.51372499999999,43.751106],"type":"Point"}
}