{
  "type": "Feature",
  "properties": {
    "iso:country":"CA",
    "sg:address":"20 D'Arcy St",
    "sg:city":"Toronto",
    "sg:classifiers":[
        {
            "category":"Communications",
            "subcategory":"Film & Video Production",
            "type":"Services"
        }
    ],
    "sg:phone":"+1 416 595 5794",
    "sg:postcode":"M5T 1J7",
    "sg:province":"ON",
    "sg:tags":[
        "taping"
    ],
    "wof:name":"Canavision Inc",
    "wof:placetype":"venue"
},
  "geometry": {"coordinates":[-79.3853530884,43.6485481262],"type":"Point"}
}