{
  "type": "Feature",
  "properties": {
    "addr:full":"1675 Rue Villeray Montreal QC H2E 1H5",
    "addr:housenumber":"1675",
    "addr:postcode":"h2e 1h5",
    "addr:street":"Rue Villeray",
    "iso:country":"CA",
    "sg:address":"1675 Rue Villeray",
    "sg:city":"Montreal",
    "sg:classifiers":[
        {
            "category":"Shopping",
            "subcategory":"Clothing, Apparel, & Fashions",
            "type":"Retail Goods"
        }
    ],
    "sg:phone":"+1 514 721 9773",
    "sg:postcode":"H2E 1H5",
    "sg:province":"QC",
    "sg:tags":[
        "item",
        "boutique"
    ],
    "wof:name":"Creations Paula",
    "wof:placetype":"venue"
},
  "geometry": {"coordinates":[-73.61515799999999,45.550884],"type":"Point"}
}