{
  "type": "Feature",
  "properties": {
    "addr:full":"14 Dracup Ave N Yorkton SK S3N 3W1",
    "addr:housenumber":"14",
    "addr:postcode":"s3n 3w1",
    "addr:street":"Dracup Ave N",
    "iso:country":"CA",
    "sg:address":"14 Dracup Ave N",
    "sg:city":"Yorkton",
    "sg:classifiers":[
        {
            "category":"Restaurant",
            "type":"Food & Drink"
        }
    ],
    "sg:phone":"+1 306 782 4900",
    "sg:postcode":"S3N 3W1",
    "sg:province":"SK",
    "wof:name":"Smitty's Family Restaurant",
    "wof:placetype":"venue"
},
  "geometry": {"coordinates":[-102.45121765099999,51.2108345032],"type":"Point"}
}