{
  "type": "Feature",
  "properties": {
    "addr:full":"Winnipeg MB R3R 2P9",
    "addr:postcode":"r3r 2p9",
    "iso:country":"CA",
    "sg:city":"Winnipeg",
    "sg:classifiers":[
        {
            "category":"Restaurant",
            "type":"Food & Drink"
        }
    ],
    "sg:phone":"+1 204 949 3229",
    "sg:postcode":"R3R 2P9",
    "sg:province":"MB",
    "wof:name":"Mc Donald's",
    "wof:placetype":"venue"
},
  "geometry": {"coordinates":[-97.31526947019999,49.8633613586],"type":"Point"}
}