{
  "type": "Feature",
  "properties": {
    "addr:full":"Ottawa ON K1Y 2X2",
    "addr:postcode":"k1y 2x2",
    "iso:country":"CA",
    "sg:city":"Ottawa",
    "sg:classifiers":[
        {
            "category":"Retail",
            "subcategory":"Auto Repair",
            "type":"Services"
        }
    ],
    "sg:phone":"+1 613 798 2220",
    "sg:postcode":"K1Y 2X2",
    "sg:province":"ON",
    "sg:tags":[
        "repairing",
        "automobile"
    ],
    "wof:name":"Ike's Auto Ctr",
    "wof:placetype":"venue"
},
  "geometry": {"coordinates":[-75.7407531738,45.3977241516],"type":"Point"}
}