{
  "type": "Feature",
  "properties": {
    "addr:full":"652 Progress Ave Kingston ON K7M 4W9",
    "addr:housenumber":"652",
    "addr:postcode":"k7m 4w9",
    "addr:street":"Progress Ave",
    "iso:country":"CA",
    "sg:address":"652 Progress Ave",
    "sg:city":"Kingston",
    "sg:classifiers":[
        {
            "category":"Education",
            "subcategory":"School",
            "type":"Public Place"
        }
    ],
    "sg:phone":"+1 613 384 9449",
    "sg:postcode":"K7M 4W9",
    "sg:province":"ON",
    "wof:name":"Baybridge Community Education",
    "wof:placetype":"venue"
},
  "geometry": {"coordinates":[-76.56991600000001,44.246758],"type":"Point"}
}