{
  "type": "Feature",
  "properties": {
    "addr:full":"2986 Nanaimo St Vancouver BC V5N 5G3",
    "addr:housenumber":"2986",
    "addr:postcode":"v5n 5g3",
    "addr:street":"Nanaimo St",
    "iso:country":"CA",
    "sg:address":"2986 Nanaimo St",
    "sg:city":"Vancouver",
    "sg:classifiers":[
        {
            "category":"Personal",
            "subcategory":"Beauty Salon",
            "type":"Services"
        }
    ],
    "sg:phone":"+1 604 430 6606",
    "sg:postcode":"V5N 5G3",
    "sg:province":"BC",
    "wof:name":"Lanna Hair Design",
    "wof:placetype":"venue"
},
  "geometry": {"coordinates":[-123.05635833700001,49.2574005127],"type":"Point"}
}