{
  "type": "Feature",
  "properties": {
    "addr:full":"410 Highway 77 Leamington ON N8H 3V6",
    "addr:housenumber":"410",
    "addr:postcode":"n8h 3v6",
    "addr:street":"Highway 77",
    "iso:country":"CA",
    "sg:address":"410 Highway 77",
    "sg:city":"Leamington",
    "sg:classifiers":[
        {
            "category":"Manufacturing",
            "subcategory":"Tools & Machinery",
            "type":"Manufacturing & Wholesale Goods"
        }
    ],
    "sg:phone":"+1 519 326 3261",
    "sg:postcode":"N8H 3V6",
    "sg:province":"ON",
    "sg:tags":[
        "farm",
        "lawn",
        "mower"
    ],
    "wof:name":"Janzen Equipment Ltd",
    "wof:placetype":"venue"
},
  "geometry": {"coordinates":[-82.5997161865,42.0541534424],"type":"Point"}
}