{
  "type": "Feature",
  "properties": {
    "iso:country":"CA",
    "sg:address":"1203 Broad St",
    "sg:city":"Victoria",
    "sg:classifiers":[
        {
            "category":"Shopping",
            "type":"Retail Goods"
        }
    ],
    "sg:phone":"+1 250 388 0009",
    "sg:postcode":"V8W 2A4",
    "sg:province":"BC",
    "sg:tags":[
        "art",
        "gallery",
        "dealer"
    ],
    "wof:name":"West End Gallery",
    "wof:placetype":"venue"
},
  "geometry": {"coordinates":[-123.366394043,48.4257583618],"type":"Point"}
}