{
  "type": "Feature",
  "properties": {
    "addr:full":"167 Sterling Ave Winnipeg MB R2M 2R8",
    "addr:housenumber":"167",
    "addr:postcode":"r2m 2r8",
    "addr:street":"Sterling Ave",
    "iso:country":"CA",
    "sg:address":"167 Sterling Ave",
    "sg:city":"Winnipeg",
    "sg:classifiers":[
        {
            "category":"Building & Trades",
            "subcategory":"Construction",
            "type":"Services"
        }
    ],
    "sg:phone":"+1 204 253 4698",
    "sg:postcode":"R2M 2R8",
    "sg:province":"MB",
    "sg:tags":[
        "concrete",
        "contractor",
        "general"
    ],
    "wof:name":"Anthony's Piling Contractors",
    "wof:placetype":"venue"
},
  "geometry": {"coordinates":[-97.09884643549999,49.8349685669],"type":"Point"}
}