{
  "type": "Feature",
  "properties": {
    "addr:full":"Kelowna BC V1X 3W7",
    "addr:postcode":"v1x 3w7",
    "iso:country":"CA",
    "sg:city":"Kelowna",
    "sg:classifiers":[
        {
            "category":"Retail",
            "subcategory":"Portrait Studio",
            "type":"Services"
        }
    ],
    "sg:phone":"+1 250 868 9529",
    "sg:postcode":"V1X 3W7",
    "sg:province":"BC",
    "sg:tags":[
        "photographer"
    ],
    "wof:name":"Pbk Photographics",
    "wof:placetype":"venue"
},
  "geometry": {"coordinates":[-119.40078699999999,49.876297],"type":"Point"}
}