{
  "type": "Feature",
  "properties": {
    "iso:country":"CA",
    "sg:address":"150 Edmonton Ave",
    "sg:city":"Moncton",
    "sg:classifiers":[
        {
            "category":"Wholesale",
            "subcategory":"Electrical",
            "type":"Manufacturing & Wholesale Goods"
        }
    ],
    "sg:phone":"+1 506 857 9106",
    "sg:postcode":"E1C 3B9",
    "sg:province":"NB",
    "sg:tags":[
        "alarm",
        "burglar",
        "system"
    ],
    "wof:name":"Chubb Security Systems",
    "wof:placetype":"venue"
},
  "geometry": {"coordinates":[-64.80188800000001,46.095451],"type":"Point"}
}