{
  "type": "Feature",
  "properties": {
    "addr:full":"47 Charlotte St Saint John NB E2L 2H8",
    "addr:housenumber":"47",
    "addr:postcode":"nb e2l 2h8",
    "addr:street":"Charlotte St",
    "iso:country":"CA",
    "sg:address":"47 Charlotte St",
    "sg:city":"Saint John",
    "sg:classifiers":[
        {
            "category":"Food & Beverages",
            "subcategory":"Meat & Fish",
            "type":"Retail Goods"
        }
    ],
    "sg:phone":"+1 506 693 7291",
    "sg:postcode":"E2L 2H8",
    "sg:province":"NB",
    "wof:name":"Dean's Meat Stall Ltd",
    "wof:placetype":"venue"
},
  "geometry": {"coordinates":[-66.05909729,45.2740402222],"type":"Point"}
}