{
  "type": "Feature",
  "properties": {
    "addr:full":"245 Le Maire St Winnipeg MB R3V 1M2",
    "addr:housenumber":"245",
    "addr:postcode":"r3v 1m2",
    "addr:street":"Le Maire St",
    "iso:country":"CA",
    "sg:address":"245 Le Maire St",
    "sg:city":"Winnipeg",
    "sg:classifiers":[
        {
            "category":"Education",
            "subcategory":"School",
            "type":"Public Place"
        }
    ],
    "sg:phone":"+1 204 275 5048",
    "sg:postcode":"R3V 1M2",
    "sg:province":"MB",
    "wof:name":"Barriere Crossings School",
    "wof:placetype":"venue"
},
  "geometry": {"coordinates":[-97.16572600000001,49.76775],"type":"Point"}
}