{
  "type": "Feature",
  "properties": {
    "iso:country":"CA",
    "sg:city":"Moose Creek",
    "sg:classifiers":[
        {
            "category":"Personal",
            "subcategory":"Beauty Salon",
            "type":"Services"
        }
    ],
    "sg:phone":"+1 613 538 2950",
    "sg:postcode":"K0C 1W0",
    "sg:province":"ON",
    "wof:name":"Salon Mireille",
    "wof:placetype":"venue"
},
  "geometry": {"coordinates":[-74.9701919556,45.2617721558],"type":"Point"}
}