{
  "type": "Feature",
  "properties": {
    "addr:full":"Winnipeg MB R2H 0G9",
    "addr:postcode":"r2h 0g9",
    "iso:country":"CA",
    "sg:city":"Winnipeg",
    "sg:classifiers":[
        {
            "category":"Organizations",
            "subcategory":"Membership Organization",
            "type":"Services"
        }
    ],
    "sg:phone":"+1 204 235 0670",
    "sg:postcode":"R2H 0G9",
    "sg:province":"MB",
    "sg:tags":[
        "senior",
        "citizen"
    ],
    "wof:name":"Federation Des Aines",
    "wof:placetype":"venue"
},
  "geometry": {"coordinates":[-97.113243,49.894573],"type":"Point"}
}