{
  "type": "Feature",
  "properties": {
    "addr:full":"155 Rue DE Fontenelle Blainville QC J7B 1N9",
    "addr:housenumber":"155",
    "addr:postcode":"j7b 1n9",
    "addr:street":"Rue De Fontenelle",
    "iso:country":"CA",
    "sg:address":"155 Rue DE Fontenelle",
    "sg:city":"Blainville",
    "sg:classifiers":[
        {
            "category":"Freight",
            "type":"Transportation"
        }
    ],
    "sg:phone":"+1 450 437 9343",
    "sg:postcode":"J7B 1N9",
    "sg:province":"QC",
    "sg:tags":[
        "broker",
        "trucking"
    ],
    "wof:name":"A P Intl",
    "wof:placetype":"venue"
},
  "geometry": {"coordinates":[-73.83367200000001,45.658466],"type":"Point"}
}