{
  "type": "Feature",
  "properties": {
    "addr:full":"147 Bank St Ottawa ON K1P 5N7",
    "addr:housenumber":"147",
    "addr:postcode":"k1p 5n7",
    "addr:street":"Bank St",
    "iso:country":"CA",
    "sg:address":"147 Bank St",
    "sg:city":"Ottawa",
    "sg:classifiers":[
        {
            "category":"Shopping",
            "type":"Retail Goods"
        }
    ],
    "sg:phone":"+1 613 236 1690",
    "sg:postcode":"K1P 5N7",
    "sg:province":"ON",
    "sg:tags":[
        "picture",
        "frame"
    ],
    "wof:name":"Images on Bank",
    "wof:placetype":"venue"
},
  "geometry": {"coordinates":[-75.699265,45.418976],"type":"Point"}
}