{
  "type": "Feature",
  "properties": {
    "addr:full":"6565 5th Line Port Hope ON L1A 3V8",
    "addr:housenumber":"6565",
    "addr:postcode":"l1a 3v8",
    "addr:street":"5Th Line",
    "iso:country":"CA",
    "sg:address":"6565 5th Line",
    "sg:city":"Port Hope",
    "sg:classifiers":[
        {
            "category":"Building & Trades",
            "subcategory":"Construction",
            "type":"Services"
        }
    ],
    "sg:phone":"+1 905 885 9092",
    "sg:postcode":"L1A 3V8",
    "sg:province":"ON",
    "sg:tags":[
        "excavating",
        "contractor"
    ],
    "wof:name":"Litz Bobcat Svc",
    "wof:placetype":"venue"
},
  "geometry": {"coordinates":[-78.31382751460001,44.0204200745],"type":"Point"}
}