{
  "type": "Feature",
  "properties": {
    "iso:country":"CA",
    "sg:address":"450 Av Michel-Jasmin",
    "sg:city":"Dorval",
    "sg:classifiers":[
        {
            "category":"Retail",
            "subcategory":"Auto Repair",
            "type":"Services"
        }
    ],
    "sg:phone":"+1 514 631 0462",
    "sg:postcode":"H9P 1C1",
    "sg:province":"QC",
    "sg:tags":[
        "repairing",
        "automobile"
    ],
    "wof:name":"F & H Garage",
    "wof:placetype":"venue"
},
  "geometry": {"coordinates":[-73.73465,45.453758],"type":"Point"}
}