{
  "type": "Feature",
  "properties": {
    "addr:full":"Haliburton ON K0M 1S0",
    "addr:postcode":"k0m 1s0",
    "iso:country":"CA",
    "sg:city":"Haliburton",
    "sg:classifiers":[
        {
            "category":"Health Services",
            "subcategory":"Chiropractor",
            "type":"Services"
        }
    ],
    "sg:phone":"+1 705 457 9895",
    "sg:postcode":"K0M 1S0",
    "sg:province":"ON",
    "wof:name":"Hill Chiropractic & Physio",
    "wof:placetype":"venue"
},
  "geometry": {"coordinates":[-78.509697,45.048401],"type":"Point"}
}