{
  "type": "Feature",
  "properties": {
    "iso:country":"CA",
    "sg:address":"30 Ordnance St",
    "sg:city":"Toronto",
    "sg:classifiers":[
        {
            "category":"Shopping",
            "type":"Retail Goods"
        }
    ],
    "sg:phone":"+1 416 504 2808",
    "sg:postcode":"M6K 1A2",
    "sg:province":"ON",
    "sg:tags":[
        "material",
        "fixture",
        "miscellaneous",
        "store",
        "display"
    ],
    "wof:name":"Display Bank",
    "wof:placetype":"venue"
},
  "geometry": {"coordinates":[-79.4092330933,43.6394271851],"type":"Point"}
}