{
  "type": "Feature",
  "properties": {
    "addr:full":"5010 50 St Yellowknife NT X1A 2N1",
    "addr:housenumber":"5010",
    "addr:postcode":"x1a 2n1",
    "addr:street":"50 St",
    "iso:country":"CA",
    "sg:address":"5010 50 St",
    "sg:city":"Yellowknife",
    "sg:classifiers":[
        {
            "category":"Food & Beverages",
            "subcategory":"Candy",
            "type":"Retail Goods"
        }
    ],
    "sg:phone":"+1 867 873 3640",
    "sg:postcode":"X1A 2N1",
    "sg:province":"NT",
    "sg:tags":[
        "confectionery"
    ],
    "wof:name":"Saigon Smoke Shop",
    "wof:placetype":"venue"
},
  "geometry": {"coordinates":[-114.37146,62.453724],"type":"Point"}
}