{
  "type": "Feature",
  "properties": {
    "addr:full":"Fort Erie ON L2A 3G9",
    "addr:postcode":"l2a 3g9",
    "iso:country":"CA",
    "sg:city":"Fort Erie",
    "sg:classifiers":[
        {
            "category":"Personal",
            "subcategory":"Beauty Salon",
            "type":"Services"
        }
    ],
    "sg:phone":"+1 905 871 2363",
    "sg:postcode":"L2A 3G9",
    "sg:province":"ON",
    "wof:name":"Hairport Unisex",
    "wof:placetype":"venue"
},
  "geometry": {"coordinates":[-78.9100723267,42.9166755676],"type":"Point"}
}