{
  "type": "Feature",
  "properties": {
    "addr:full":"1 Main St Strome AB T0B 4H0",
    "addr:housenumber":"1",
    "addr:postcode":"t0b 4h0",
    "addr:street":"Main St",
    "iso:country":"CA",
    "sg:address":"1 Main St",
    "sg:city":"Strome",
    "sg:classifiers":[
        {
            "category":"Wholesale",
            "subcategory":"Machinery & Supplies",
            "type":"Manufacturing & Wholesale Goods"
        }
    ],
    "sg:phone":"+1 780 376 2200",
    "sg:postcode":"T0B 4H0",
    "sg:province":"AB",
    "sg:tags":[
        "glass",
        "product",
        "fiber"
    ],
    "wof:name":"Quicksilver Manufacturing Ltd",
    "wof:placetype":"venue"
},
  "geometry": {"coordinates":[-112.06509399399999,52.8122253418],"type":"Point"}
}