{
  "type": "Feature",
  "properties": {
    "addr:full":"Richmond BC V6X 2E3",
    "addr:postcode":"v6x 2e3",
    "iso:country":"CA",
    "sg:city":"Richmond",
    "sg:classifiers":[
        {
            "category":"Insurance",
            "subcategory":"Insurance Agent",
            "type":"Services"
        }
    ],
    "sg:phone":"+1 604 273 0232",
    "sg:postcode":"V6X 2E3",
    "sg:province":"BC",
    "wof:name":"Assetplus Financial Svc Inc",
    "wof:placetype":"venue"
},
  "geometry": {"coordinates":[-123.136681,49.1707],"type":"Point"}
}