{
  "type": "Feature",
  "properties": {
    "addr:full":"79 Swanhurst Blvd Mississauga ON L5N 1B8",
    "addr:housenumber":"79",
    "addr:postcode":"l5n 1b8",
    "addr:street":"Swanhurst Blvd",
    "iso:country":"CA",
    "sg:address":"79 Swanhurst Blvd",
    "sg:city":"Mississauga",
    "sg:classifiers":[
        {
            "category":"Organizations",
            "subcategory":"Religious Organization",
            "type":"Services"
        }
    ],
    "sg:phone":"+1 905 812 0452",
    "sg:postcode":"L5N 1B8",
    "sg:province":"ON",
    "sg:tags":[
        "church"
    ],
    "wof:name":"Mississauga Mennonite Fllwshp",
    "wof:placetype":"venue"
},
  "geometry": {"coordinates":[-79.72429700000001,43.592304],"type":"Point"}
}