{
  "type": "Feature",
  "properties": {
    "iso:country":"CA",
    "sg:address":"150 Fernwood Rd",
    "sg:city":"Salt Spring Island",
    "sg:classifiers":[
        {
            "category":"Education",
            "subcategory":"School",
            "type":"Public Place"
        }
    ],
    "sg:phone":"+1 250 537 9332",
    "sg:postcode":"V8K 1C5",
    "sg:province":"BC",
    "wof:name":"Fernwood Elementary School",
    "wof:placetype":"venue"
},
  "geometry": {"coordinates":[-123.538528442,48.9074020386],"type":"Point"}
}