{
  "type": "Feature",
  "properties": {
    "iso:country":"CA",
    "sg:city":"Scarborough",
    "sg:classifiers":[
        {
            "category":"Health Services",
            "subcategory":"Doctor",
            "type":"Services"
        }
    ],
    "sg:phone":"+1 416 298 3232",
    "sg:postcode":"M1S 4V5",
    "sg:province":"ON",
    "sg:tags":[
        "dentist"
    ],
    "wof:name":"Lin, Deborah DDS",
    "wof:placetype":"venue"
},
  "geometry": {"coordinates":[-79.2939758301,43.8020591736],"type":"Point"}
}