{
  "type": "Feature",
  "properties": {
    "addr:full":"985 Mission St Winnipeg MB R2J 0A4",
    "addr:housenumber":"985",
    "addr:postcode":"r2j 0a4",
    "addr:street":"Mission St",
    "iso:country":"CA",
    "sg:address":"985 Mission St",
    "sg:city":"Winnipeg",
    "sg:classifiers":[
        {
            "category":"Building & Trades",
            "subcategory":"Plumbing",
            "type":"Services"
        }
    ],
    "sg:phone":"+1 204 231 5328",
    "sg:postcode":"R2J 0A4",
    "sg:province":"MB",
    "sg:tags":[
        "ventilating",
        "contractor"
    ],
    "wof:name":"Lsm Metal Fabricators Ltd",
    "wof:placetype":"venue"
},
  "geometry": {"coordinates":[-97.08298499999999,49.895035],"type":"Point"}
}