{
  "type": "Feature",
  "properties": {
    "iso:country":"CA",
    "sg:address":"825 Av Tecumseh # A",
    "sg:city":"Pointe-Claire",
    "sg:classifiers":[
        {
            "category":"Manufacturing",
            "subcategory":"Apparel",
            "type":"Manufacturing & Wholesale Goods"
        }
    ],
    "sg:phone":"+1 514 683 5202",
    "sg:postcode":"H9R 4T8",
    "sg:province":"QC",
    "wof:name":"Las Vegas Creations Inc",
    "wof:placetype":"venue"
},
  "geometry": {"coordinates":[-73.8132095337,45.475944519],"type":"Point"}
}