{
  "type": "Feature",
  "properties": {
    "addr:full":"115 4th St Wawanesa MB R0K 2G0",
    "addr:housenumber":"115",
    "addr:postcode":"r0k 2g0",
    "addr:street":"4Th St",
    "iso:country":"CA",
    "sg:address":"115 4th St",
    "sg:city":"Wawanesa",
    "sg:classifiers":[
        {
            "category":"Insurance",
            "subcategory":"Insurance Agent",
            "type":"Services"
        }
    ],
    "sg:phone":"+1 204 824 2012",
    "sg:postcode":"R0K 2G0",
    "sg:province":"MB",
    "wof:name":"Mc Lean Insurance",
    "wof:placetype":"venue"
},
  "geometry": {"coordinates":[-99.68444100000001,49.596924],"type":"Point"}
}