{
  "type": "Feature",
  "properties": {
    "addr:full":"4903 48 Ave Fort Nelson BC V0C 1R0",
    "addr:housenumber":"4903",
    "addr:postcode":"bc v0c 1r0",
    "addr:street":"48 Ave",
    "iso:country":"CA",
    "sg:address":"4903 48 Ave",
    "sg:city":"Fort Nelson",
    "sg:classifiers":[
        {
            "category":"Social Services",
            "type":"Services"
        }
    ],
    "sg:phone":"+1 250 774 3816",
    "sg:postcode":"V0C 1R0",
    "sg:province":"BC",
    "sg:tags":[
        "organization",
        "welfare"
    ],
    "wof:name":"Transients' Hostel",
    "wof:placetype":"venue"
},
  "geometry": {"coordinates":[-122.699516,58.802032],"type":"Point"}
}