{
  "type": "Feature",
  "properties": {
    "addr:full":"145 Traynor St Riverview NB E1B 3B1",
    "addr:housenumber":"145",
    "addr:postcode":"e1b 3b1",
    "addr:street":"Traynor St",
    "iso:country":"CA",
    "sg:address":"145 Traynor St",
    "sg:city":"Riverview",
    "sg:classifiers":[
        {
            "category":"Home & Garden",
            "subcategory":"Building Materials",
            "type":"Retail Goods"
        }
    ],
    "sg:phone":"+1 506 387 4501",
    "sg:postcode":"E1B 3B1",
    "sg:province":"NB",
    "wof:name":"Domac Tim-Br Mart",
    "wof:placetype":"venue"
},
  "geometry": {"coordinates":[-64.81750488279999,46.0572357178],"type":"Point"}
}