{
  "type": "Feature",
  "properties": {
    "iso:country":"CA",
    "sg:address":"203 Rte Larose",
    "sg:city":"Saint-Isidore",
    "sg:classifiers":[
        {
            "category":"Building & Trades",
            "subcategory":"Electrical",
            "type":"Services"
        }
    ],
    "sg:phone":"+1 418 882 5129",
    "sg:postcode":"G0S 2S0",
    "sg:province":"QC",
    "sg:tags":[
        "electric",
        "contractor"
    ],
    "wof:name":"Jean-Louis Gosselin Inc",
    "wof:placetype":"venue"
},
  "geometry": {"coordinates":[-71.12758599999999,46.58736],"type":"Point"}
}