{
  "type": "Feature",
  "properties": {
    "iso:country":"CA",
    "sg:address":"203 River St",
    "sg:city":"Toronto",
    "sg:classifiers":[
        {
            "category":"Organizations",
            "subcategory":"Religious Organization",
            "type":"Services"
        }
    ],
    "sg:phone":"+1 416 944 3297",
    "sg:postcode":"M5A 3P9",
    "sg:province":"ON",
    "sg:tags":[
        "church"
    ],
    "wof:name":"Serbian Orthodox Church",
    "wof:placetype":"venue"
},
  "geometry": {"coordinates":[-79.35912322999999,43.6638755798],"type":"Point"}
}