{
  "type": "Feature",
  "properties": {
    "addr:full":"PO Box 20102 Rpo Brandon South Brandon MB R7A 6Y8",
    "addr:housenumber":"po box",
    "addr:postcode":"20102;r7a 6y8",
    "addr:street":"South",
    "iso:country":"CA",
    "sg:address":"PO Box 20102 Rpo Brandon South",
    "sg:city":"Brandon",
    "sg:classifiers":[
        {
            "category":"Banks & Credit Unions",
            "subcategory":"Investment Brokerage",
            "type":"Services"
        }
    ],
    "sg:phone":"+1 204 728 2708",
    "sg:postcode":"R7A 6Y8",
    "sg:province":"MB",
    "wof:name":"Great Plains Insurance",
    "wof:placetype":"venue"
},
  "geometry": {"coordinates":[-99.961952,49.847698],"type":"Point"}
}