{
  "type": "Feature",
  "properties": {
    "addr:full":"76 Ch Valiquette Gatineau QC J8R 3L8",
    "addr:housenumber":"76",
    "addr:postcode":"j8r 3l8",
    "addr:street":"Ch Valiquette",
    "iso:country":"CA",
    "sg:address":"76 Ch Valiquette",
    "sg:city":"Gatineau",
    "sg:classifiers":[
        {
            "category":"Professional",
            "subcategory":"Business Services",
            "type":"Services"
        }
    ],
    "sg:phone":"+1 819 669 6748",
    "sg:postcode":"J8R 3L8",
    "sg:province":"QC",
    "sg:tags":[
        "translator",
        "interpreter"
    ],
    "wof:name":"Traduction Redaction Louis",
    "wof:placetype":"venue"
},
  "geometry": {"coordinates":[-75.655411,45.541328],"type":"Point"}
}