{
  "type": "Feature",
  "properties": {
    "addr:full":"139 8th St S Humboldt SK S0K 2A0",
    "addr:housenumber":"139",
    "addr:postcode":"s0k 2a0",
    "addr:street":"8Th St S",
    "iso:country":"CA",
    "sg:address":"139 8th St S",
    "sg:city":"Humboldt",
    "sg:classifiers":[
        {
            "category":"Recreation",
            "type":"Entertainment"
        }
    ],
    "sg:phone":"+1 306 682 3941",
    "sg:postcode":"S0K 2A0",
    "sg:province":"SK",
    "sg:tags":[
        "hall",
        "auditorium"
    ],
    "wof:name":"Ukranian Catholic All Saints",
    "wof:placetype":"venue"
},
  "geometry": {"coordinates":[-105.12294799999999,52.205811],"type":"Point"}
}