{
  "type": "Feature",
  "properties": {
    "addr:full":"5025 Willow St Vancouver BC V5Z 3S1",
    "addr:housenumber":"5025",
    "addr:postcode":"v5z 3s1",
    "addr:street":"Willow St",
    "iso:country":"CA",
    "sg:address":"5025 Willow St",
    "sg:city":"Vancouver",
    "sg:classifiers":[
        {
            "category":"Education",
            "subcategory":"School",
            "type":"Public Place"
        }
    ],
    "sg:phone":"+1 604 713 8930",
    "sg:postcode":"V5Z 3S1",
    "sg:province":"BC",
    "wof:name":"Eric Hamber Secondary School",
    "wof:placetype":"venue"
},
  "geometry": {"coordinates":[-123.123817444,49.2389068604],"type":"Point"}
}