{
  "type": "Feature",
  "properties": {
    "addr:full":"St Albert AB T8N 3M5",
    "addr:postcode":"t8n 3m5",
    "iso:country":"CA",
    "sg:city":"St Albert",
    "sg:classifiers":[
        {
            "category":"Social Services",
            "subcategory":"Child Care",
            "type":"Services"
        }
    ],
    "sg:phone":"+1 780 459 2210",
    "sg:postcode":"T8N 3M5",
    "sg:province":"AB",
    "wof:name":"Grandma Gooch Daycare Inc",
    "wof:placetype":"venue"
},
  "geometry": {"coordinates":[-113.606864929,53.6360168457],"type":"Point"}
}