{
  "type": "Feature",
  "properties": {
    "iso:country":"CA",
    "sg:address":"875 Dundas St",
    "sg:city":"Woodstock",
    "sg:classifiers":[
        {
            "category":"Retail",
            "subcategory":"Auto Repair",
            "type":"Services"
        }
    ],
    "sg:phone":"+1 519 539 6101",
    "sg:postcode":"N4S 1G8",
    "sg:province":"ON",
    "sg:tags":[
        "repairing",
        "automobile"
    ],
    "wof:name":"Beattie Automotive",
    "wof:placetype":"venue"
},
  "geometry": {"coordinates":[-80.7387390137,43.1328239441],"type":"Point"}
}