{
  "type": "Feature",
  "properties": {
    "iso:country":"CA",
    "sg:city":"Richmond",
    "sg:classifiers":[
        {
            "category":"Wholesale",
            "subcategory":"Construction Materials",
            "type":"Manufacturing & Wholesale Goods"
        }
    ],
    "sg:phone":"+1 604 273 5441",
    "sg:postcode":"V6V 2W3",
    "sg:province":"BC",
    "sg:tags":[
        "lumber"
    ],
    "wof:name":"Skana Forest Products Ltd",
    "wof:placetype":"venue"
},
  "geometry": {"coordinates":[-122.992622,49.169205],"type":"Point"}
}