{
  "type": "Feature",
  "properties": {
    "addr:full":"1180 Bidwell St Vancouver BC V6G 2K6",
    "addr:housenumber":"1180",
    "addr:postcode":"v6g 2k6",
    "addr:street":"Bidwell St",
    "iso:country":"CA",
    "sg:address":"1180 Bidwell St",
    "sg:city":"Vancouver",
    "sg:classifiers":[
        {
            "category":"Shopping",
            "subcategory":"Clothing, Apparel, & Fashions",
            "type":"Retail Goods"
        }
    ],
    "sg:phone":"+1 604 684 0712",
    "sg:postcode":"V6G 2K6",
    "sg:province":"BC",
    "sg:tags":[
        "tailor"
    ],
    "wof:name":"Vivien's Fashion",
    "wof:placetype":"venue"
},
  "geometry": {"coordinates":[-123.139687,49.286427],"type":"Point"}
}