{
  "type": "Feature",
  "properties": {
    "addr:full":"211 Rue DE LA Gauchetiere O Montreal QC H2Z 1C5",
    "addr:housenumber":"211",
    "addr:postcode":"h2z 1c5",
    "addr:street":"Rue De La Gauchetiere O",
    "iso:country":"CA",
    "sg:address":"211 Rue DE LA Gauchetiere O",
    "sg:city":"Montreal",
    "sg:classifiers":[
        {
            "category":"Organizations",
            "subcategory":"Professional Association",
            "type":"Services"
        }
    ],
    "sg:phone":"+1 514 861 4541",
    "sg:postcode":"H2Z 1C5",
    "sg:province":"QC",
    "wof:name":"Montreal Chinese Community Ctr",
    "wof:placetype":"venue"
},
  "geometry": {"coordinates":[-73.558594,45.510277],"type":"Point"}
}