{
  "type": "Feature",
  "properties": {
    "addr:full":"462 Albert St Waterloo ON N2L 3V4",
    "addr:housenumber":"462",
    "addr:postcode":"n2l 3v4",
    "addr:street":"Albert St",
    "iso:country":"CA",
    "sg:address":"462 Albert St",
    "sg:city":"Waterloo",
    "sg:classifiers":[
        {
            "category":"Food & Beverages",
            "subcategory":"Liquor & Beverages",
            "type":"Retail Goods"
        }
    ],
    "sg:phone":"+1 519 884 4811",
    "sg:postcode":"N2L 3V4",
    "sg:province":"ON",
    "sg:tags":[
        "beer",
        "ale"
    ],
    "wof:name":"Beer Store",
    "wof:placetype":"venue"
},
  "geometry": {"coordinates":[-80.540764,43.485855],"type":"Point"}
}