{
  "type": "Feature",
  "properties": {
    "addr:full":"343 Main St Florenceville NB E7L 3G7",
    "addr:housenumber":"343",
    "addr:postcode":"e7l 3g7",
    "addr:street":"Main St",
    "iso:country":"CA",
    "sg:address":"343 Main St",
    "sg:city":"Florenceville",
    "sg:classifiers":[
        {
            "category":"Restaurant",
            "type":"Food & Drink"
        }
    ],
    "sg:phone":"+1 506 392 1810",
    "sg:postcode":"E7L 3G7",
    "sg:province":"NB",
    "sg:tags":[
        "pizza"
    ],
    "wof:name":"Pizza Delight",
    "wof:placetype":"venue"
},
  "geometry": {"coordinates":[-67.61932400000001,46.440624],"type":"Point"}
}