{
  "type": "Feature",
  "properties": {
    "addr:full":"407 Dollarton Hwy N North Vancouver BC V7G 1M9",
    "addr:housenumber":"407",
    "addr:postcode":"v7g 1m9",
    "addr:street":"Dollarton Hwy N",
    "iso:country":"CA",
    "sg:address":"407 Dollarton Hwy N",
    "sg:city":"North Vancouver",
    "sg:classifiers":[
        {
            "category":"Insurance",
            "subcategory":"Insurance Agent",
            "type":"Services"
        }
    ],
    "sg:phone":"+1 604 924 1251",
    "sg:postcode":"V7G 1M9",
    "sg:province":"BC",
    "wof:name":"Sussex Insurance Inc",
    "wof:placetype":"venue"
},
  "geometry": {"coordinates":[-122.953330994,49.3065299988],"type":"Point"}
}