{
  "type": "Feature",
  "properties": {
    "addr:full":"312 Brownridge Dr Thornhill ON L4J 5X1",
    "addr:housenumber":"312",
    "addr:postcode":"l4j 5x1",
    "addr:street":"Brownridge Dr",
    "iso:country":"CA",
    "sg:address":"312 Brownridge Dr",
    "sg:city":"Thornhill",
    "sg:classifiers":[
        {
            "category":"Manufacturing",
            "subcategory":"Printing",
            "type":"Manufacturing & Wholesale Goods"
        }
    ],
    "sg:phone":"+1 905 738 5005",
    "sg:postcode":"L4J 5X1",
    "sg:province":"ON",
    "sg:tags":[
        "newspaper"
    ],
    "wof:name":"Indo Caribbean World",
    "wof:placetype":"venue"
},
  "geometry": {"coordinates":[-79.4703292847,43.8051834106],"type":"Point"}
}