{
  "type": "Feature",
  "properties": {
    "addr:full":"3280 Highway 97 N Kelowna BC V1X 5C1",
    "addr:housenumber":"3280",
    "addr:postcode":"v1x 5c1",
    "addr:street":"Highway 97 N",
    "iso:country":"CA",
    "sg:address":"3280 Highway 97 N",
    "sg:city":"Kelowna",
    "sg:classifiers":[
        {
            "category":"Retail",
            "subcategory":"Repair Shop",
            "type":"Services"
        }
    ],
    "sg:phone":"+1 250 765 3295",
    "sg:postcode":"V1X 5C1",
    "sg:province":"BC",
    "sg:tags":[
        "upholsterer"
    ],
    "wof:name":"Experts Auto Upholstery",
    "wof:placetype":"venue"
},
  "geometry": {"coordinates":[-119.49659699999999,49.886814],"type":"Point"}
}