{
  "type": "Feature",
  "properties": {
    "addr:full":"20 Oxford Blvd Port Colborne ON L3K 5C9",
    "addr:housenumber":"20",
    "addr:postcode":"l3k 5c9",
    "addr:street":"Oxford Blvd",
    "iso:country":"CA",
    "sg:address":"20 Oxford Blvd",
    "sg:city":"Port Colborne",
    "sg:classifiers":[
        {
            "category":"Health Services",
            "subcategory":"Medical Lab",
            "type":"Services"
        }
    ],
    "sg:phone":"+1 905 835 1532",
    "sg:postcode":"L3K 5C9",
    "sg:province":"ON",
    "sg:tags":[
        "laboratory"
    ],
    "wof:name":"Perfect Smile Entreprises",
    "wof:placetype":"venue"
},
  "geometry": {"coordinates":[-79.2642211914,42.9134864807],"type":"Point"}
}