{
  "type": "Feature",
  "properties": {
    "addr:full":"North York ON M3B 2M5",
    "addr:postcode":"m3b 2m5",
    "iso:country":"CA",
    "sg:city":"North York",
    "sg:classifiers":[
        {
            "category":"Manufacturing",
            "subcategory":"Tools & Machinery",
            "type":"Manufacturing & Wholesale Goods"
        }
    ],
    "sg:phone":"+1 416 445 6886",
    "sg:postcode":"M3B 2M5",
    "sg:province":"ON",
    "sg:tags":[
        "cleaners",
        "household",
        "vacuum"
    ],
    "wof:name":"Vacuflo",
    "wof:placetype":"venue"
},
  "geometry": {"coordinates":[-79.3604507446,43.7558860779],"type":"Point"}
}