{
  "type": "Feature",
  "properties": {
    "iso:country":"CA",
    "sg:city":"London",
    "sg:classifiers":[
        {
            "category":"Food & Beverages",
            "subcategory":"Specialty",
            "type":"Retail Goods"
        }
    ],
    "sg:phone":"+1 519 659 3737",
    "sg:postcode":"N5Y 1A8",
    "sg:province":"ON",
    "sg:tags":[
        "health",
        "diet"
    ],
    "wof:name":"S & H Health Foods",
    "wof:placetype":"venue"
},
  "geometry": {"coordinates":[-81.215469,43.01952],"type":"Point"}
}