{
  "type": "Feature",
  "properties": {
    "addr:full":"3272 Boul Neilson Sainte-Foy QC G1W 2V8",
    "addr:housenumber":"3272",
    "addr:postcode":"g1w 2v8",
    "addr:street":"Boul Neilson",
    "iso:country":"CA",
    "sg:address":"3272 Boul Neilson",
    "sg:city":"Sainte-Foy",
    "sg:classifiers":[
        {
            "category":"Travel",
            "subcategory":"Travel Agent",
            "type":"Entertainment"
        }
    ],
    "sg:phone":"+1 418 653 6222",
    "sg:postcode":"G1W 2V8",
    "sg:province":"QC",
    "sg:tags":[
        "agency",
        "bureau"
    ],
    "wof:name":"Club Voyages Elysee",
    "wof:placetype":"venue"
},
  "geometry": {"coordinates":[-71.3096160889,46.7574043274],"type":"Point"}
}