{
  "type": "Feature",
  "properties": {
    "addr:full":"RR 3 Craigmyle AB T0J 0T0",
    "addr:postcode":"t0j 0t0",
    "addr:street":"Rr 3 Craigmyle",
    "iso:country":"CA",
    "sg:address":"RR 3",
    "sg:city":"Craigmyle",
    "sg:classifiers":[
        {
            "category":"Organizations",
            "subcategory":"Professional Association",
            "type":"Services"
        }
    ],
    "sg:phone":"+1 403 665 2493",
    "sg:postcode":"T0J 0T0",
    "sg:province":"AB",
    "sg:tags":[
        "club"
    ],
    "wof:name":"Hand Hills Lake Club",
    "wof:placetype":"venue"
},
  "geometry": {"coordinates":[-112.24826049799999,51.6694488525],"type":"Point"}
}