{
  "type": "Feature",
  "properties": {
    "addr:full":"8 Purley Cres Scarborough ON M1M 1E8",
    "addr:housenumber":"8",
    "addr:postcode":"m1m 1e8",
    "addr:street":"Purley Cres",
    "iso:country":"CA",
    "sg:address":"8 Purley Cres",
    "sg:city":"Scarborough",
    "sg:classifiers":[
        {
            "category":"Freight",
            "type":"Transportation"
        }
    ],
    "sg:phone":"+1 416 269 5828",
    "sg:postcode":"M1M 1E8",
    "sg:province":"ON",
    "sg:tags":[
        "cartage"
    ],
    "wof:name":"Gundar Cartage & Express",
    "wof:placetype":"venue"
},
  "geometry": {"coordinates":[-79.22904200000001,43.721191],"type":"Point"}
}