{
  "type": "Feature",
  "properties": {
    "iso:country":"CA",
    "sg:address":"8540 Greenall Ave",
    "sg:city":"Burnaby",
    "sg:classifiers":[
        {
            "category":"Government",
            "subcategory":"Police Station",
            "type":"Public Place"
        }
    ],
    "sg:phone":"+1 604 434 2448",
    "sg:postcode":"V5J 3M6",
    "sg:province":"BC",
    "sg:tags":[
        "bailiff"
    ],
    "wof:name":"Active Bailiff Svc Ltd",
    "wof:placetype":"venue"
},
  "geometry": {"coordinates":[-123.017715454,49.2072792053],"type":"Point"}
}