{
  "type": "Feature",
  "properties": {
    "iso:country":"CA",
    "sg:address":"718 Main St",
    "sg:city":"Pincher Creek",
    "sg:classifiers":[
        {
            "category":"Travel",
            "subcategory":"Hotels & Motels",
            "type":"Entertainment"
        }
    ],
    "sg:phone":"+1 403 627 3830",
    "sg:postcode":"T0K 1W0",
    "sg:province":"AB",
    "wof:name":"Alberta Hotel",
    "wof:placetype":"venue"
},
  "geometry": {"coordinates":[-113.94893646200001,49.4855194092],"type":"Point"}
}