{
  "type": "Feature",
  "properties": {
    "addr:full":"7107 120 St Delta BC V4E 2A9",
    "addr:housenumber":"7107",
    "addr:postcode":"v4e 2a9",
    "addr:street":"120 St",
    "iso:country":"CA",
    "sg:address":"7107 120 St",
    "sg:city":"Delta",
    "sg:classifiers":[
        {
            "category":"Shopping",
            "subcategory":"Jewelry",
            "type":"Retail Goods"
        }
    ],
    "sg:phone":"+1 604 596 5444",
    "sg:postcode":"V4E 2A9",
    "sg:province":"BC",
    "sg:tags":[
        "jeweler"
    ],
    "wof:name":"Gold Star Jewellery Belegris",
    "wof:placetype":"venue"
},
  "geometry": {"coordinates":[-122.890556335,49.1322898865],"type":"Point"}
}