{
  "type": "Feature",
  "properties": {
    "addr:full":"10288 Yonge St Richmond Hill ON L4C 3B8",
    "addr:housenumber":"10288",
    "addr:postcode":"l4c 3b8",
    "addr:street":"Yonge St",
    "iso:country":"CA",
    "sg:address":"10288 Yonge St",
    "sg:city":"Richmond Hill",
    "sg:classifiers":[
        {
            "category":"Professional",
            "subcategory":"Management & Consulting",
            "type":"Services"
        }
    ],
    "sg:phone":"+1 905 883 9373",
    "sg:postcode":"L4C 3B8",
    "sg:province":"ON",
    "sg:tags":[
        "party",
        "planning",
        "amusement"
    ],
    "wof:name":"Kiddies Korner Indoor Plygrnd",
    "wof:placetype":"venue"
},
  "geometry": {"coordinates":[-79.439064,43.878311],"type":"Point"}
}