{
  "type": "Feature",
  "properties": {
    "addr:full":"709 Gauthier Larouche QC G0W 1Z0",
    "addr:housenumber":"709",
    "addr:postcode":"g0w 1z0",
    "addr:street":"Gauthier Larouche",
    "iso:country":"CA",
    "sg:address":"709 Gauthier",
    "sg:city":"Larouche",
    "sg:classifiers":[
        {
            "category":"Government",
            "subcategory":"Office",
            "type":"Public Place"
        }
    ],
    "sg:phone":"+1 418 695 2201",
    "sg:postcode":"G0W 1Z0",
    "sg:province":"QC",
    "sg:tags":[
        "village"
    ],
    "wof:name":"Larouche Secretariat",
    "wof:placetype":"venue"
},
  "geometry": {"coordinates":[-71.5252914429,48.4496231079],"type":"Point"}
}