{
  "type": "Feature",
  "properties": {
    "addr:full":"84 Burr Oak Dr Naughton ON P0M 2M0",
    "addr:housenumber":"84",
    "addr:postcode":"p0m 2m0",
    "addr:street":"Burr Oak Dr Naughton",
    "iso:country":"CA",
    "sg:address":"84 Burr Oak Dr",
    "sg:city":"Naughton",
    "sg:classifiers":[
        {
            "category":"Autos & Motor Vehicles",
            "subcategory":"Motorcycle Sales",
            "type":"Retail Goods"
        }
    ],
    "sg:phone":"+1 705 866 1957",
    "sg:postcode":"P0M 2M0",
    "sg:province":"ON",
    "sg:tags":[
        "scooter"
    ],
    "wof:name":"D & J Motorcycle Sales",
    "wof:placetype":"venue"
},
  "geometry": {"coordinates":[-81.19012499999999,46.403126],"type":"Point"}
}