{
  "type": "Feature",
  "properties": {
    "addr:full":"Barrie ON L4N 5R7",
    "addr:postcode":"l4n 5r7",
    "iso:country":"CA",
    "sg:city":"Barrie",
    "sg:classifiers":[
        {
            "category":"Personal",
            "subcategory":"Beauty Salon",
            "type":"Services"
        }
    ],
    "sg:phone":"+1 705 721 5800",
    "sg:postcode":"L4N 5R7",
    "sg:province":"ON",
    "wof:name":"Skinsational",
    "wof:placetype":"venue"
},
  "geometry": {"coordinates":[-79.711967,44.382446],"type":"Point"}
}