{
  "type": "Feature",
  "properties": {
    "addr:full":"266 S River Rd Elora ON N0B 1S0",
    "addr:housenumber":"266",
    "addr:postcode":"n0b 1s0",
    "addr:street":"S River Rd",
    "iso:country":"CA",
    "sg:address":"266 S River Rd",
    "sg:city":"Elora",
    "sg:classifiers":[
        {
            "category":"Manufacturing",
            "subcategory":"Apparel",
            "type":"Manufacturing & Wholesale Goods"
        }
    ],
    "sg:phone":"+1 519 846 0088",
    "sg:postcode":"N0B 1S0",
    "sg:province":"ON",
    "sg:tags":[
        "flag",
        "banner"
    ],
    "wof:name":"Grand Flags",
    "wof:placetype":"venue"
},
  "geometry": {"coordinates":[-80.409554,43.689484],"type":"Point"}
}