{
  "type": "Feature",
  "properties": {
    "addr:full":"500 Rue Des Trinitaires Saint-Jean-Sur-Richelieu QC J3B 2X6",
    "addr:housenumber":"500",
    "addr:postcode":"j3b 2x6",
    "addr:street":"Rue Des Trinitaires",
    "iso:country":"CA",
    "sg:address":"500 Rue Des Trinitaires",
    "sg:city":"Saint-Jean-Sur-Richelieu",
    "sg:classifiers":[
        {
            "category":"Building & Trades",
            "subcategory":"Construction",
            "type":"Services"
        }
    ],
    "sg:phone":"+1 450 347 3304",
    "sg:postcode":"J3B 2X6",
    "sg:province":"QC",
    "sg:tags":[
        "painter"
    ],
    "wof:name":"Peinture Mg",
    "wof:placetype":"venue"
},
  "geometry": {"coordinates":[-73.276482,45.303715],"type":"Point"}
}