{
  "type": "Feature",
  "properties": {
    "addr:full":"6574 Ladner Trunk Rd Delta BC V4K 3N3",
    "addr:housenumber":"6574",
    "addr:postcode":"v4k 3n3",
    "addr:street":"Ladner Trunk Rd",
    "iso:country":"CA",
    "sg:address":"6574 Ladner Trunk Rd",
    "sg:city":"Delta",
    "sg:classifiers":[
        {
            "category":"Travel",
            "subcategory":"Hotels & Motels",
            "type":"Entertainment"
        }
    ],
    "sg:phone":"+1 604 946 4288",
    "sg:postcode":"V4K 3N3",
    "sg:province":"BC",
    "wof:name":"Tsawwassen Motel",
    "wof:placetype":"venue"
},
  "geometry": {"coordinates":[-123.037086487,49.0900917053],"type":"Point"}
}