{
  "type": "Feature",
  "properties": {
    "addr:full":"503 3rd St Kenaston SK S0G 2N0",
    "addr:housenumber":"503",
    "addr:postcode":"s0g 2n0",
    "addr:street":"3Rd St",
    "iso:country":"CA",
    "sg:address":"503 3rd St",
    "sg:city":"Kenaston",
    "sg:classifiers":[
        {
            "category":"Organizations",
            "subcategory":"Religious Organization",
            "type":"Services"
        }
    ],
    "sg:phone":"+1 306 252 2234",
    "sg:postcode":"S0G 2N0",
    "sg:province":"SK",
    "sg:tags":[
        "church"
    ],
    "wof:name":"Evangelical Missionary Church",
    "wof:placetype":"venue"
},
  "geometry": {"coordinates":[-106.276420593,51.5034637451],"type":"Point"}
}