{
  "type": "Feature",
  "properties": {
    "addr:full":"RR 1 Pass Lake ON P0T 2M0",
    "addr:postcode":"p0t 2m0",
    "addr:street":"Rr 1 Pass",
    "iso:country":"CA",
    "sg:address":"RR 1",
    "sg:city":"Pass Lake",
    "sg:classifiers":[
        {
            "category":"Government",
            "subcategory":"Office",
            "type":"Public Place"
        }
    ],
    "sg:phone":"+1 807 977 2526",
    "sg:postcode":"P0T 2M0",
    "sg:province":"ON",
    "wof:name":"Ontario Sleeping Giant Park",
    "wof:placetype":"venue"
},
  "geometry": {"coordinates":[-88.73802947999999,48.5639724731],"type":"Point"}
}