{
  "type": "Feature",
  "properties": {
    "addr:full":"83 Rue Saint-Vincent Sainte-Agathe-Des-Monts QC J8C 2A8",
    "addr:housenumber":"83",
    "addr:postcode":"j8c 2a8",
    "addr:street":"Rue Saint-Vincent",
    "iso:country":"CA",
    "sg:address":"83 Rue Saint-Vincent",
    "sg:city":"Sainte-Agathe-Des-Monts",
    "sg:classifiers":[
        {
            "category":"Education",
            "subcategory":"Library",
            "type":"Public Place"
        }
    ],
    "sg:phone":"+1 819 326 4595",
    "sg:postcode":"J8C 2A8",
    "sg:province":"QC",
    "wof:name":"Bibliotheque Ste-Agathe-Des-MT",
    "wof:placetype":"venue"
},
  "geometry": {"coordinates":[-74.28819300000001,46.048855],"type":"Point"}
}