{
  "type": "Feature",
  "properties": {
    "addr:full":"Montreal QC H3T 1J4",
    "addr:postcode":"h3t 1j4",
    "iso:country":"CA",
    "sg:city":"Montreal",
    "sg:classifiers":[
        {
            "category":"Shopping",
            "subcategory":"Books",
            "type":"Retail Goods"
        }
    ],
    "sg:phone":"+1 514 340 4067",
    "sg:postcode":"H3T 1J4",
    "sg:province":"QC",
    "sg:tags":[
        "dealer"
    ],
    "wof:name":"Librairie Scientifique Ecole",
    "wof:placetype":"venue"
},
  "geometry": {"coordinates":[-73.6185836792,45.5032806396],"type":"Point"}
}