{
  "type": "Feature",
  "properties": {
    "addr:full":"253 Morel Ave Kamouraska QC G0L 1M0",
    "addr:housenumber":"253",
    "addr:postcode":"g0l 1m0",
    "addr:street":"Morel Ave",
    "iso:country":"CA",
    "sg:address":"253 Morel Ave",
    "sg:city":"Kamouraska",
    "sg:classifiers":[
        {
            "category":"Restaurant",
            "type":"Food & Drink"
        }
    ],
    "sg:phone":"+1 418 492 6246",
    "sg:postcode":"G0L 1M0",
    "sg:province":"QC",
    "wof:name":"Au Relais DE Kamouraska",
    "wof:placetype":"venue"
},
  "geometry": {"coordinates":[-69.879699707,47.5515594482],"type":"Point"}
}