{
  "type": "Feature",
  "properties": {
    "iso:country":"CA",
    "sg:city":"Saint-Amable",
    "sg:classifiers":[
        {
            "category":"Recreation",
            "type":"Entertainment"
        }
    ],
    "sg:phone":"+1 450 649 3636",
    "sg:postcode":"J0L 1N0",
    "sg:province":"QC",
    "sg:tags":[
        "center",
        "government"
    ],
    "wof:name":"St Amable Loisirs",
    "wof:placetype":"venue"
},
  "geometry": {"coordinates":[-73.2956542969,45.649066925],"type":"Point"}
}