{
  "type": "Feature",
  "properties": {
    "addr:full":"3375 North Service Rd Burlington ON L7N 3G2",
    "addr:housenumber":"3375",
    "addr:postcode":"l7n 3g2",
    "addr:street":"North Service Rd",
    "iso:country":"CA",
    "sg:address":"3375 North Service Rd",
    "sg:city":"Burlington",
    "sg:classifiers":[
        {
            "category":"Wholesale",
            "subcategory":"Groceries",
            "type":"Manufacturing & Wholesale Goods"
        }
    ],
    "sg:phone":"+1 905 332 5352",
    "sg:postcode":"L7N 3G2",
    "sg:province":"ON",
    "sg:tags":[
        "beverage"
    ],
    "wof:name":"Newco Corp",
    "wof:placetype":"venue"
},
  "geometry": {"coordinates":[-79.792542,43.363121],"type":"Point"}
}