{
  "type": "Feature",
  "properties": {
    "addr:full":"147 Elman Cres Newmarket ON L3Y 7X2",
    "addr:housenumber":"147",
    "addr:postcode":"l3y 7x2",
    "addr:street":"Elman Cres",
    "iso:country":"CA",
    "sg:address":"147 Elman Cres",
    "sg:city":"Newmarket",
    "sg:classifiers":[
        {
            "category":"Building & Trades",
            "subcategory":"Landscaping Services",
            "type":"Services"
        }
    ],
    "sg:phone":"+1 905 830 1995",
    "sg:postcode":"L3Y 7X2",
    "sg:province":"ON",
    "sg:tags":[
        "lawn",
        "maintenance",
        "grounds"
    ],
    "wof:name":"Kevco Property Maintenance",
    "wof:placetype":"venue"
},
  "geometry": {"coordinates":[-79.47440338129999,44.0685081482],"type":"Point"}
}