{
  "type": "Feature",
  "properties": {
    "addr:full":"728 Av Royale Beauport QC G1E 1Z4",
    "addr:postcode":"qc g1e 1z4",
    "addr:street":"728 Av Royale",
    "iso:country":"CA",
    "sg:address":"728 Av Royale",
    "sg:city":"Beauport",
    "sg:classifiers":[
        {
            "category":"Health Services",
            "subcategory":"Doctor",
            "type":"Services"
        }
    ],
    "sg:phone":"+1 418 666 7911",
    "sg:postcode":"G1E 1Z4",
    "sg:province":"QC",
    "sg:tags":[
        "physician",
        "surgeon"
    ],
    "wof:name":"Marineau, Jean-Marie MD",
    "wof:placetype":"venue"
},
  "geometry": {"coordinates":[-71.18869018549999,46.861366272],"type":"Point"}
}