{
  "type": "Feature",
  "properties": {
    "addr:full":"337 Highway Ave N Picture Butte AB T0K 1V0",
    "addr:housenumber":"337",
    "addr:postcode":"t0k 1v0",
    "addr:street":"Highway Ave N Picture",
    "iso:country":"CA",
    "sg:address":"337 Highway Ave N",
    "sg:city":"Picture Butte",
    "sg:classifiers":[
        {
            "category":"Shopping",
            "subcategory":"Florist",
            "type":"Retail Goods"
        }
    ],
    "sg:phone":"+1 403 732 4886",
    "sg:postcode":"T0K 1V0",
    "sg:province":"AB",
    "wof:name":"Flare N' Flowers",
    "wof:placetype":"venue"
},
  "geometry": {"coordinates":[-112.779343,49.877819],"type":"Point"}
}