{
  "type": "Feature",
  "properties": {
    "addr:full":"3901 Macleod Trail SW Calgary AB T2G 2R4",
    "addr:housenumber":"3901",
    "addr:postcode":"t2g 2r4",
    "addr:street":"Macleod Trail Sw",
    "iso:country":"CA",
    "sg:address":"3901 Macleod Trail SW",
    "sg:city":"Calgary",
    "sg:classifiers":[
        {
            "category":"Autos & Motor Vehicles",
            "subcategory":"Automobile Sales",
            "type":"Retail Goods"
        }
    ],
    "sg:phone":"+1 403 287 7886",
    "sg:postcode":"T2G 2R4",
    "sg:province":"AB",
    "sg:tags":[
        "car",
        "dealer"
    ],
    "wof:name":"Daewoo Centaur",
    "wof:placetype":"venue"
},
  "geometry": {"coordinates":[-114.06201900000001,51.020023],"type":"Point"}
}