{
  "type": "Feature",
  "properties": {
    "addr:full":"189 Ch DE LA Grande-Cote Boisbriand QC J7G 1B6",
    "addr:housenumber":"189",
    "addr:postcode":"j7g 1b6",
    "addr:street":"Ch De La Grande-Cote",
    "iso:country":"CA",
    "sg:address":"189 Ch DE LA Grande-Cote",
    "sg:city":"Boisbriand",
    "sg:classifiers":[
        {
            "category":"Health Services",
            "subcategory":"Chiropractor",
            "type":"Services"
        }
    ],
    "sg:phone":"+1 450 434 1819",
    "sg:postcode":"J7G 1B6",
    "sg:province":"QC",
    "wof:name":"Cardinal, Leo DC",
    "wof:placetype":"venue"
},
  "geometry": {"coordinates":[-73.823814,45.613312],"type":"Point"}
}