{
  "type": "Feature",
  "properties": {
    "addr:full":"1735 Kipling Ave Etobicoke ON M9R 2Y8",
    "addr:housenumber":"1735",
    "addr:postcode":"m9r 2y8",
    "addr:street":"Kipling Ave",
    "iso:country":"CA",
    "sg:address":"1735 Kipling Ave",
    "sg:city":"Etobicoke",
    "sg:classifiers":[
        {
            "category":"Social Services",
            "type":"Services"
        }
    ],
    "sg:phone":"+1 416 244 5673",
    "sg:postcode":"M9R 2Y8",
    "sg:province":"ON",
    "sg:tags":[
        "organization",
        "welfare"
    ],
    "wof:name":"Siwa Somali Immigrant Wom",
    "wof:placetype":"venue"
},
  "geometry": {"coordinates":[-79.5583114624,43.6939926147],"type":"Point"}
}