{
  "type": "Feature",
  "properties": {
    "addr:full":"225 2nd Ave W Vancouver BC V5Y 1C7",
    "addr:housenumber":"225",
    "addr:postcode":"v5y 1c7",
    "addr:street":"2Nd Ave W",
    "iso:country":"CA",
    "sg:address":"225 2nd Ave W",
    "sg:city":"Vancouver",
    "sg:classifiers":[
        {
            "category":"Communications",
            "subcategory":"Film & Video Production",
            "type":"Services"
        }
    ],
    "sg:phone":"+1 604 877 7705",
    "sg:postcode":"V5Y 1C7",
    "sg:province":"BC",
    "sg:tags":[
        "motion",
        "picture",
        "studio",
        "producer"
    ],
    "wof:name":"Second Avenue Studios",
    "wof:placetype":"venue"
},
  "geometry": {"coordinates":[-123.11055,49.268921],"type":"Point"}
}