{
  "type": "Feature",
  "properties": {
    "iso:country":"CA",
    "sg:address":"315 Av Des Jasmins S",
    "sg:city":"Alma",
    "sg:classifiers":[
        {
            "category":"Building & Trades",
            "subcategory":"Construction",
            "type":"Services"
        }
    ],
    "sg:phone":"+1 418 668 2413",
    "sg:postcode":"G8B 6X6",
    "sg:province":"QC",
    "sg:tags":[
        "product",
        "paving",
        "asphalt",
        "contractor"
    ],
    "wof:name":"Asphalte Ultra Inc",
    "wof:placetype":"venue"
},
  "geometry": {"coordinates":[-71.653968811,48.5355796814],"type":"Point"}
}