{
  "type": "Feature",
  "properties": {
    "iso:country":"CA",
    "sg:address":"675 Adelaide St N",
    "sg:city":"London",
    "sg:classifiers":[
        {
            "category":"Real Estate",
            "subcategory":"Real Estate Agent",
            "type":"Services"
        }
    ],
    "sg:phone":"+1 519 667 1800",
    "sg:postcode":"N5Y 2L4",
    "sg:province":"ON",
    "wof:name":"Remax City Centre Realty Inc",
    "wof:placetype":"venue"
},
  "geometry": {"coordinates":[-81.23571,42.996956],"type":"Point"}
}