{
  "type": "Feature",
  "properties": {
    "iso:country":"CA",
    "sg:address":"145 Larose Ave",
    "sg:city":"The Pas",
    "sg:classifiers":[
        {
            "category":"Organizations",
            "subcategory":"Professional Association",
            "type":"Services"
        }
    ],
    "sg:phone":"+1 204 627 6864",
    "sg:postcode":"R9A 1L7",
    "sg:province":"MB",
    "sg:tags":[
        "native"
    ],
    "wof:name":"Pas Sweetgrass Head Start Ctr",
    "wof:placetype":"venue"
},
  "geometry": {"coordinates":[-101.251609802,53.8207778931],"type":"Point"}
}