{
  "type": "Feature",
  "properties": {
    "addr:full":"Mississauga ON L4W 5C5",
    "addr:postcode":"l4w 5c5",
    "iso:country":"CA",
    "sg:city":"Mississauga",
    "sg:classifiers":[
        {
            "category":"Education",
            "subcategory":"Dance Studio",
            "type":"Public Place"
        }
    ],
    "sg:phone":"+1 905 602 8890",
    "sg:postcode":"L4W 5C5",
    "sg:province":"ON",
    "sg:tags":[
        "school",
        "instruction",
        "dancing"
    ],
    "wof:name":"Broadway Bound",
    "wof:placetype":"venue"
},
  "geometry": {"coordinates":[-79.635559,43.626465],"type":"Point"}
}