{
  "type": "Feature",
  "properties": {
    "addr:full":"59 Kirby Ave Dundas ON L9H 6P3",
    "addr:housenumber":"59",
    "addr:postcode":"l9h 6p3",
    "addr:street":"Kirby Ave",
    "iso:country":"CA",
    "sg:address":"59 Kirby Ave",
    "sg:city":"Dundas",
    "sg:classifiers":[
        {
            "category":"Education",
            "subcategory":"Library",
            "type":"Public Place"
        }
    ],
    "sg:phone":"+1 905 627 4951",
    "sg:postcode":"L9H 6P3",
    "sg:province":"ON",
    "sg:tags":[
        "government"
    ],
    "wof:name":"Greensville Branch Library",
    "wof:placetype":"venue"
},
  "geometry": {"coordinates":[-79.9523773193,43.2637786865],"type":"Point"}
}