{
  "type": "Feature",
  "properties": {
    "iso:country":"CA",
    "sg:address":"3375 Cassino Ave",
    "sg:city":"Saskatoon",
    "sg:classifiers":[
        {
            "category":"Building & Trades",
            "subcategory":"Electrical",
            "type":"Services"
        }
    ],
    "sg:phone":"+1 306 382 0530",
    "sg:postcode":"S7M 5E8",
    "sg:province":"SK",
    "sg:tags":[
        "electric",
        "contractor"
    ],
    "wof:name":"A C Electric",
    "wof:placetype":"venue"
},
  "geometry": {"coordinates":[-106.733779907,52.1068458557],"type":"Point"}
}