{
  "type": "Feature",
  "properties": {
    "addr:full":"Edmonton AB T5N 1P6",
    "addr:postcode":"t5n 1p6",
    "iso:country":"CA",
    "sg:city":"Edmonton",
    "sg:classifiers":[
        {
            "category":"Real Estate",
            "subcategory":"Real Estate Agent",
            "type":"Services"
        }
    ],
    "sg:phone":"+1 780 452 2829",
    "sg:postcode":"T5N 1P6",
    "sg:province":"AB",
    "sg:tags":[
        "appraiser"
    ],
    "wof:name":"Independent Real Property",
    "wof:placetype":"venue"
},
  "geometry": {"coordinates":[-113.53610999999999,53.541897],"type":"Point"}
}