{
  "type": "Feature",
  "properties": {
    "iso:country":"CA",
    "sg:address":"1116 Victoria Park Ave",
    "sg:city":"East York",
    "sg:classifiers":[
        {
            "category":"Retail",
            "subcategory":"Laundry & Dry Cleaning",
            "type":"Services"
        }
    ],
    "sg:phone":"+1 416 759 5798",
    "sg:postcode":"M4B 2K3",
    "sg:province":"ON",
    "sg:tags":[
        "cleaners"
    ],
    "wof:name":"Professional 1 HR Cleaners",
    "wof:placetype":"venue"
},
  "geometry": {"coordinates":[-79.29577636720001,43.7079162598],"type":"Point"}
}