{
  "type": "Feature",
  "properties": {
    "addr:full":"135 Huron Rd Mitchell ON N0K 1N0",
    "addr:housenumber":"135",
    "addr:postcode":"n0k 1n0",
    "addr:street":"Huron Rd",
    "iso:country":"CA",
    "sg:address":"135 Huron Rd",
    "sg:city":"Mitchell",
    "sg:classifiers":[
        {
            "category":"Wholesale",
            "subcategory":"Farm Supplies",
            "type":"Manufacturing & Wholesale Goods"
        }
    ],
    "sg:phone":"+1 519 348 8752",
    "sg:postcode":"N0K 1N0",
    "sg:province":"ON",
    "sg:tags":[
        "feed"
    ],
    "wof:name":"Mitchell Feed Mill Inc",
    "wof:placetype":"venue"
},
  "geometry": {"coordinates":[-81.210319519,43.4737205505],"type":"Point"}
}