{
  "type": "Feature",
  "properties": {
    "addr:full":"600 14 Ave SE Slave Lake AB T0G 2A3",
    "addr:postcode":"600;t0g 2a3",
    "addr:street":"14 Ave Se",
    "iso:country":"CA",
    "sg:address":"600 14 Ave SE",
    "sg:city":"Slave Lake",
    "sg:classifiers":[
        {
            "category":"Travel",
            "subcategory":"Hotels & Motels",
            "type":"Entertainment"
        }
    ],
    "sg:phone":"+1 780 849 2400",
    "sg:postcode":"T0G 2A3",
    "sg:province":"AB",
    "wof:name":"Highway Motor Inn",
    "wof:placetype":"venue"
},
  "geometry": {"coordinates":[-114.76815000000001,55.269138],"type":"Point"}
}