{
  "type": "Feature",
  "properties": {
    "addr:full":"832 Upper Wentworth St Hamilton ON L9A 4W4",
    "addr:housenumber":"832",
    "addr:postcode":"l9a 4w4",
    "addr:street":"Upper Wentworth St",
    "iso:country":"CA",
    "sg:address":"832 Upper Wentworth St",
    "sg:city":"Hamilton",
    "sg:classifiers":[
        {
            "category":"Shopping",
            "type":"Retail Goods"
        }
    ],
    "sg:phone":"+1 905 575 5555",
    "sg:postcode":"L9A 4W4",
    "sg:province":"ON",
    "sg:tags":[
        "hearing",
        "equipment",
        "supply",
        "impaired"
    ],
    "wof:name":"Audio Dynamics Hearing Aid",
    "wof:placetype":"venue"
},
  "geometry": {"coordinates":[-79.8625946045,43.2226791382],"type":"Point"}
}