{
  "type": "Feature",
  "properties": {
    "iso:country":"CA",
    "sg:address":"877 Exmouth St",
    "sg:city":"Sarnia",
    "sg:classifiers":[
        {
            "category":"Professional",
            "subcategory":"Detective & Security Services",
            "type":"Services"
        }
    ],
    "sg:phone":"+1 519 332 4007",
    "sg:postcode":"N7T 5R3",
    "sg:province":"ON",
    "sg:tags":[
        "supervisory",
        "sprinkler"
    ],
    "wof:name":"Uss",
    "wof:placetype":"venue"
},
  "geometry": {"coordinates":[-82.377335,42.984894],"type":"Point"}
}