{
  "type": "Feature",
  "properties": {
    "iso:country":"CA",
    "sg:address":"131 Campbell Ave",
    "sg:city":"North Bay",
    "sg:classifiers":[
        {
            "category":"Real Estate",
            "subcategory":"Real Estate Agent",
            "type":"Services"
        }
    ],
    "sg:phone":"+1 705 474 8599",
    "sg:postcode":"P1A 1W1",
    "sg:province":"ON",
    "wof:name":"Bain & Bain Agencies Ltd",
    "wof:placetype":"venue"
},
  "geometry": {"coordinates":[-79.4552536011,46.2893943787],"type":"Point"}
}