{
  "type": "Feature",
  "properties": {
    "addr:full":"9627 66 Ave NW Edmonton AB T6E 0M2",
    "addr:housenumber":"9627",
    "addr:postcode":"t6e 0m2",
    "addr:street":"66 Ave Nw",
    "iso:country":"CA",
    "sg:address":"9627 66 Ave NW",
    "sg:city":"Edmonton",
    "sg:classifiers":[
        {
            "category":"Food & Beverages",
            "subcategory":"Bakery",
            "type":"Retail Goods"
        }
    ],
    "sg:phone":"+1 780 435 8484",
    "sg:postcode":"T6E 0M2",
    "sg:province":"AB",
    "sg:tags":[
        "baker"
    ],
    "wof:name":"Hazeldean Bakery",
    "wof:placetype":"venue"
},
  "geometry": {"coordinates":[-113.47740173299999,53.5027503967],"type":"Point"}
}