{
  "type": "Feature",
  "properties": {
    "addr:full":"7575 Boul Viau Saint-Leonard QC H1S 2P4",
    "addr:housenumber":"7575",
    "addr:postcode":"h1s 2p4",
    "addr:street":"Boul Viau",
    "iso:country":"CA",
    "sg:address":"7575 Boul Viau",
    "sg:city":"Saint-Leonard",
    "sg:classifiers":[
        {
            "category":"Real Estate",
            "subcategory":"Real Estate Operator",
            "type":"Services"
        }
    ],
    "sg:phone":"+1 514 725 4698",
    "sg:postcode":"H1S 2P4",
    "sg:province":"QC",
    "sg:tags":[
        "apartment"
    ],
    "wof:name":"Fiducie Provost",
    "wof:placetype":"venue"
},
  "geometry": {"coordinates":[-73.5904388428,45.5750732422],"type":"Point"}
}