{
  "type": "Feature",
  "properties": {
    "iso:country":"CA",
    "sg:address":"15 Astorville Rd",
    "sg:city":"Astorville",
    "sg:classifiers":[
        {
            "category":"Home & Garden",
            "subcategory":"Building Materials",
            "type":"Retail Goods"
        }
    ],
    "sg:phone":"+1 705 752 1360",
    "sg:postcode":"P0H 1B0",
    "sg:province":"ON",
    "wof:name":"Perron's Building Supplies",
    "wof:placetype":"venue"
},
  "geometry": {"coordinates":[-79.2683258057,46.1852264404],"type":"Point"}
}