{
  "type": "Feature",
  "properties": {
    "addr:full":"74 Humber Rd Corner Brook NL A2H 1E8",
    "addr:housenumber":"74",
    "addr:postcode":"a2h 1e8",
    "addr:street":"Humber Rd",
    "iso:country":"CA",
    "sg:address":"74 Humber Rd",
    "sg:city":"Corner Brook",
    "sg:classifiers":[
        {
            "category":"Wholesale",
            "subcategory":"Auto Parts",
            "type":"Manufacturing & Wholesale Goods"
        }
    ],
    "sg:phone":"+1 709 634 4836",
    "sg:postcode":"A2H 1E8",
    "sg:province":"NL",
    "sg:tags":[
        "automobile",
        "supply"
    ],
    "wof:name":"Corner Brook Automotive Ltd",
    "wof:placetype":"venue"
},
  "geometry": {"coordinates":[-57.9332885742,48.9618492126],"type":"Point"}
}