{
  "type": "Feature",
  "properties": {
    "addr:full":"North Vancouver BC V7M 2H1",
    "addr:postcode":"v7m 2h1",
    "iso:country":"CA",
    "sg:city":"North Vancouver",
    "sg:classifiers":[
        {
            "category":"Health Services",
            "subcategory":"Chiropractor",
            "type":"Services"
        }
    ],
    "sg:phone":"+1 604 986 7304",
    "sg:postcode":"V7M 2H1",
    "sg:province":"BC",
    "wof:name":"Morton, Elli DC",
    "wof:placetype":"venue"
},
  "geometry": {"coordinates":[-123.07223500000001,49.318153],"type":"Point"}
}