{
  "type": "Feature",
  "properties": {
    "addr:full":"1998 17th Ave Campbell River BC V9W 4L9",
    "addr:housenumber":"1998",
    "addr:postcode":"v9w 4l9",
    "addr:street":"17Th Ave",
    "iso:country":"CA",
    "sg:address":"1998 17th Ave",
    "sg:city":"Campbell River",
    "sg:classifiers":[
        {
            "category":"Home & Garden",
            "subcategory":"Building Materials",
            "type":"Retail Goods"
        }
    ],
    "sg:phone":"+1 250 287 8396",
    "sg:postcode":"V9W 4L9",
    "sg:province":"BC",
    "sg:tags":[
        "plate",
        "window",
        "product",
        "plastic"
    ],
    "wof:name":"North Island Glass Ltd",
    "wof:placetype":"venue"
},
  "geometry": {"coordinates":[-125.273026,50.032276],"type":"Point"}
}