{
  "type": "Feature",
  "properties": {
    "addr:full":"288 Frederick St Kitchener ON N2H 2N5",
    "addr:housenumber":"288",
    "addr:postcode":"n2h 2n5",
    "addr:street":"Frederick St",
    "iso:country":"CA",
    "sg:address":"288 Frederick St",
    "sg:city":"Kitchener",
    "sg:classifiers":[
        {
            "category":"Personal",
            "subcategory":"Beauty Salon",
            "type":"Services"
        }
    ],
    "sg:phone":"+1 519 576 0244",
    "sg:postcode":"N2H 2N5",
    "sg:province":"ON",
    "wof:name":"New Hair",
    "wof:placetype":"venue"
},
  "geometry": {"coordinates":[-80.4778213501,43.455871582],"type":"Point"}
}