{
  "type": "Feature",
  "properties": {
    "addr:full":"3411 Bathurst St North York ON M6A 2C1",
    "addr:housenumber":"3411",
    "addr:postcode":"m6a 2c1",
    "addr:street":"Bathurst St",
    "iso:country":"CA",
    "sg:address":"3411 Bathurst St",
    "sg:city":"North York",
    "sg:classifiers":[
        {
            "category":"Restaurant",
            "type":"Food & Drink"
        }
    ],
    "sg:phone":"+1 416 789 5023",
    "sg:postcode":"M6A 2C1",
    "sg:province":"ON",
    "wof:name":"Sun Up Barbecue CO",
    "wof:placetype":"venue"
},
  "geometry": {"coordinates":[-79.43135100000001,43.726822],"type":"Point"}
}