{
  "type": "Feature",
  "properties": {
    "addr:full":"56 Cote E Evain QC J0Z 1Y0",
    "addr:housenumber":"56",
    "addr:postcode":"j0z 1y0",
    "addr:street":"Cote E Evain",
    "iso:country":"CA",
    "sg:address":"56 Cote E",
    "sg:city":"Evain",
    "sg:classifiers":[
        {
            "category":"Education",
            "subcategory":"School",
            "type":"Public Place"
        }
    ],
    "sg:phone":"+1 819 768 2890",
    "sg:postcode":"J0Z 1Y0",
    "sg:province":"QC",
    "wof:name":"St-Bernard Ecole",
    "wof:placetype":"venue"
},
  "geometry": {"coordinates":[-79.230698,48.322769],"type":"Point"}
}