{
  "type": "Feature",
  "properties": {
    "addr:full":"1502 11 Ave SW Calgary AB T3C 0M9",
    "addr:housenumber":"1502",
    "addr:postcode":"t3c 0m9",
    "addr:street":"11 Ave Sw",
    "iso:country":"CA",
    "sg:address":"1502 11 Ave SW",
    "sg:city":"Calgary",
    "sg:classifiers":[
        {
            "category":"Autos & Motor Vehicles",
            "subcategory":"Auto Supplies",
            "type":"Retail Goods"
        }
    ],
    "sg:phone":"+1 403 244 3532",
    "sg:postcode":"T3C 0M9",
    "sg:province":"AB",
    "sg:tags":[
        "wheel",
        "alignment"
    ],
    "wof:name":"Globe Steering Clinic Calgary",
    "wof:placetype":"venue"
},
  "geometry": {"coordinates":[-114.09493999999999,51.043396],"type":"Point"}
}