{
  "type": "Feature",
  "properties": {
    "addr:full":"11756 Morris St Maple Ridge BC V2X 5C8",
    "addr:housenumber":"11756",
    "addr:postcode":"v2x 5c8",
    "addr:street":"Morris St",
    "iso:country":"CA",
    "sg:address":"11756 Morris St",
    "sg:city":"Maple Ridge",
    "sg:classifiers":[
        {
            "category":"Retail",
            "subcategory":"Laundry & Dry Cleaning",
            "type":"Services"
        }
    ],
    "sg:phone":"+1 604 463 6619",
    "sg:postcode":"V2X 5C8",
    "sg:province":"BC",
    "sg:tags":[
        "cleaners",
        "rug",
        "carpet"
    ],
    "wof:name":"Ridge Meadows Carpet Care",
    "wof:placetype":"venue"
},
  "geometry": {"coordinates":[-122.627311706,49.2161064148],"type":"Point"}
}