{
  "type": "Feature",
  "properties": {
    "addr:full":"Petrolia ON N0N 1R0",
    "addr:postcode":"n0n 1r0",
    "iso:country":"CA",
    "sg:city":"Petrolia",
    "sg:classifiers":[
        {
            "category":"Government",
            "subcategory":"Police Station",
            "type":"Public Place"
        }
    ],
    "sg:phone":"+1 519 882 1011",
    "sg:postcode":"N0N 1R0",
    "sg:province":"ON",
    "sg:tags":[
        "department"
    ],
    "wof:name":"Ontario Provincial Police",
    "wof:placetype":"venue"
},
  "geometry": {"coordinates":[-82.12368011469999,42.8821716309],"type":"Point"}
}