{
  "type": "Feature",
  "properties": {
    "addr:full":"Hinton AB T7V 1S8",
    "addr:postcode":"t7v 1s8",
    "iso:country":"CA",
    "sg:city":"Hinton",
    "sg:classifiers":[
        {
            "category":"Restaurant",
            "type":"Food & Drink"
        }
    ],
    "sg:phone":"+1 780 817 2400",
    "sg:postcode":"T7V 1S8",
    "sg:province":"AB",
    "wof:name":"Boston Pizza",
    "wof:placetype":"venue"
},
  "geometry": {"coordinates":[-117.60272979699999,53.3957366943],"type":"Point"}
}