{
  "type": "Feature",
  "properties": {
    "addr:full":"7070 Av Somerled Montreal QC H4V 1V9",
    "addr:housenumber":"7070",
    "addr:postcode":"h4v 1v9",
    "addr:street":"Av Somerled",
    "iso:country":"CA",
    "sg:address":"7070 Av Somerled",
    "sg:city":"Montreal",
    "sg:classifiers":[
        {
            "category":"Organizations",
            "subcategory":"Religious Organization",
            "type":"Services"
        }
    ],
    "sg:phone":"+1 514 484 2168",
    "sg:postcode":"H4V 1V9",
    "sg:province":"QC",
    "sg:tags":[
        "church"
    ],
    "wof:name":"Ste Catherine DE Sienne Parois",
    "wof:placetype":"venue"
},
  "geometry": {"coordinates":[-73.64334869379999,45.4610176086],"type":"Point"}
}