{
  "type": "Feature",
  "properties": {
    "addr:full":"806 Vernon St Nelson BC V1L 4G5",
    "addr:housenumber":"806",
    "addr:postcode":"bc v1l 4g5",
    "addr:street":"Vernon St",
    "iso:country":"CA",
    "sg:address":"806 Vernon St",
    "sg:city":"Nelson",
    "sg:classifiers":[
        {
            "category":"Health Services",
            "subcategory":"Medical Lab",
            "type":"Services"
        }
    ],
    "sg:phone":"+1 250 352 9360",
    "sg:postcode":"V1L 4G5",
    "sg:province":"BC",
    "sg:tags":[
        "laboratory"
    ],
    "wof:name":"Mds Metro Laboratory Svc",
    "wof:placetype":"venue"
},
  "geometry": {"coordinates":[-117.29026,49.494301],"type":"Point"}
}