{
  "type": "Feature",
  "properties": {
    "addr:full":"Gatineau QC J8T 2S3",
    "addr:postcode":"j8t 2s3",
    "iso:country":"CA",
    "sg:city":"Gatineau",
    "sg:classifiers":[
        {
            "category":"Building & Trades",
            "subcategory":"Construction",
            "type":"Services"
        }
    ],
    "sg:phone":"+1 819 246 5797",
    "sg:postcode":"J8T 2S3",
    "sg:province":"QC",
    "sg:tags":[
        "dry wall",
        "stucco",
        "contractor"
    ],
    "wof:name":"Systeme Int & Stuc Cardon",
    "wof:placetype":"venue"
},
  "geometry": {"coordinates":[-75.66258999999999,45.483261],"type":"Point"}
}