{
  "type": "Feature",
  "properties": {
    "addr:full":"310 Millway Ave Concord ON L4K 3W3",
    "addr:housenumber":"310",
    "addr:postcode":"l4k 3w3",
    "addr:street":"Millway Ave",
    "iso:country":"CA",
    "sg:address":"310 Millway Ave",
    "sg:city":"Concord",
    "sg:classifiers":[
        {
            "category":"Utilities",
            "subcategory":"Refuse",
            "type":"Services"
        }
    ],
    "sg:phone":"+1 905 739 6248",
    "sg:postcode":"L4K 3W3",
    "sg:province":"ON",
    "sg:tags":[
        "garbage",
        "collection"
    ],
    "wof:name":"Spills Saver Industries Inc",
    "wof:placetype":"venue"
},
  "geometry": {"coordinates":[-79.528831,43.801495],"type":"Point"}
}