{
  "type": "Feature",
  "properties": {
    "addr:full":"1220 Dundas St E Toronto ON M4M 1S3",
    "addr:housenumber":"1220",
    "addr:postcode":"m4m 1s3",
    "addr:street":"Dundas St E",
    "iso:country":"CA",
    "sg:address":"1220 Dundas St E",
    "sg:city":"Toronto",
    "sg:classifiers":[
        {
            "category":"Wholesale",
            "subcategory":"Electrical",
            "type":"Manufacturing & Wholesale Goods"
        }
    ],
    "sg:phone":"+1 416 462 1919",
    "sg:postcode":"M4M 1S3",
    "sg:province":"ON",
    "sg:tags":[
        "control",
        "lock",
        "security",
        "locksmith"
    ],
    "wof:name":"Hardware Agencies Ltd",
    "wof:placetype":"venue"
},
  "geometry": {"coordinates":[-79.3408279419,43.6652030945],"type":"Point"}
}