{
  "type": "Feature",
  "properties": {
    "addr:full":"111 Warwick St Digby NS B0V 1A0",
    "addr:housenumber":"111",
    "addr:postcode":"b0v 1a0",
    "addr:street":"Warwick St",
    "iso:country":"CA",
    "sg:address":"111 Warwick St",
    "sg:city":"Digby",
    "sg:classifiers":[
        {
            "category":"Travel",
            "subcategory":"Hotels & Motels",
            "type":"Entertainment"
        }
    ],
    "sg:phone":"+1 902 245 4747",
    "sg:postcode":"B0V 1A0",
    "sg:province":"NS",
    "wof:name":"Kingfisher Scallop House",
    "wof:placetype":"venue"
},
  "geometry": {"coordinates":[-65.76200900000001,44.61689],"type":"Point"}
}