{
  "type": "Feature",
  "properties": {
    "addr:full":"380 Vansickle Rd St Catharines ON L2R 6P7",
    "addr:housenumber":"380",
    "addr:postcode":"l2r 6p7",
    "addr:street":"Vansickle Rd",
    "iso:country":"CA",
    "sg:address":"380 Vansickle Rd",
    "sg:city":"St Catharines",
    "sg:classifiers":[
        {
            "category":"Food & Beverages",
            "subcategory":"Specialty",
            "type":"Retail Goods"
        }
    ],
    "sg:phone":"+1 905 685 9996",
    "sg:postcode":"L2R 6P7",
    "sg:province":"ON",
    "sg:tags":[
        "water",
        "bulk",
        "company"
    ],
    "wof:name":"Water Depot",
    "wof:placetype":"venue"
},
  "geometry": {"coordinates":[-79.2701950073,43.1489143372],"type":"Point"}
}