{
  "type": "Feature",
  "properties": {
    "addr:full":"Toronto ON M6S 1P1",
    "addr:postcode":"m6s 1p1",
    "iso:country":"CA",
    "sg:city":"Toronto",
    "sg:classifiers":[
        {
            "category":"Professional",
            "subcategory":"Accounting & Tax Preparation",
            "type":"Services"
        }
    ],
    "sg:phone":"+1 416 766 9288",
    "sg:postcode":"M6S 1P1",
    "sg:province":"ON",
    "sg:tags":[
        "accountant"
    ],
    "wof:name":"Strohyj, George CA",
    "wof:placetype":"venue"
},
  "geometry": {"coordinates":[-79.478668,43.650471],"type":"Point"}
}