{
  "type": "Feature",
  "properties": {
    "addr:full":"4050 Bloor St W Etobicoke ON M9B 1M5",
    "addr:housenumber":"4050",
    "addr:postcode":"m9b 1m5",
    "addr:street":"Bloor St W",
    "iso:country":"CA",
    "sg:address":"4050 Bloor St W",
    "sg:city":"Etobicoke",
    "sg:classifiers":[
        {
            "category":"Education",
            "subcategory":"School",
            "type":"Public Place"
        }
    ],
    "sg:phone":"+1 416 394 7140",
    "sg:postcode":"M9B 1M5",
    "sg:province":"ON",
    "wof:name":"Bloorlea Middle School",
    "wof:placetype":"venue"
},
  "geometry": {"coordinates":[-79.556252,43.637177],"type":"Point"}
}