{
  "type": "Feature",
  "properties": {
    "iso:country":"CA",
    "sg:city":"Port Rowan",
    "sg:classifiers":[
        {
            "category":"Social Services",
            "type":"Services"
        }
    ],
    "sg:phone":"+1 519 586 8897",
    "sg:postcode":"N0E 1M0",
    "sg:province":"ON",
    "sg:tags":[
        "organization",
        "welfare"
    ],
    "wof:name":"Mission Food Bank",
    "wof:placetype":"venue"
},
  "geometry": {"coordinates":[-80.45040130620001,42.6270484924],"type":"Point"}
}