{
  "type": "Feature",
  "properties": {
    "addr:full":"27 Sagona Ave Mount Pearl NL A1N 4P8",
    "addr:housenumber":"27",
    "addr:postcode":"a1n 4p8",
    "addr:street":"Sagona Ave",
    "iso:country":"CA",
    "sg:address":"27 Sagona Ave",
    "sg:city":"Mount Pearl",
    "sg:classifiers":[
        {
            "category":"Professional",
            "subcategory":"Accounting & Tax Preparation",
            "type":"Services"
        }
    ],
    "sg:phone":"+1 709 747 0178",
    "sg:postcode":"A1N 4P8",
    "sg:province":"NL",
    "sg:tags":[
        "accountant"
    ],
    "wof:name":"Smith & Assoc",
    "wof:placetype":"venue"
},
  "geometry": {"coordinates":[-52.836529,47.5182],"type":"Point"}
}