{
  "type": "Feature",
  "properties": {
    "iso:country":"CA",
    "sg:address":"31 Muir St",
    "sg:city":"London",
    "sg:classifiers":[
        {
            "category":"Freight",
            "type":"Transportation"
        }
    ],
    "sg:phone":"+1 519 457 2650",
    "sg:postcode":"N5W 4B8",
    "sg:province":"ON",
    "sg:tags":[
        "roofing",
        "contractor",
        "trucking"
    ],
    "wof:name":"Thomas Roofing London Ltd",
    "wof:placetype":"venue"
},
  "geometry": {"coordinates":[-81.2099075317,42.9871520996],"type":"Point"}
}