{
  "type": "Feature",
  "properties": {
    "iso:country":"CA",
    "sg:address":"3446 Rue Saint-Denis",
    "sg:city":"Montreal",
    "sg:classifiers":[
        {
            "category":"Personal",
            "subcategory":"Beauty Salon",
            "type":"Services"
        }
    ],
    "sg:phone":"+1 514 843 4347",
    "sg:postcode":"H2X 3L3",
    "sg:province":"QC",
    "wof:name":"Essentiel A LA Beaute Enr",
    "wof:placetype":"venue"
},
  "geometry": {"coordinates":[-73.56823,45.517136],"type":"Point"}
}