{
  "type": "Feature",
  "properties": {
    "iso:country":"CA",
    "sg:city":"LA Plaine",
    "sg:classifiers":[
        {
            "category":"Personal",
            "subcategory":"Beauty Salon",
            "type":"Services"
        }
    ],
    "sg:phone":"+1 450 478 8119",
    "sg:postcode":"J7M 1V5",
    "sg:province":"QC",
    "sg:tags":[
        "manicuring"
    ],
    "wof:name":"Escalle Beaute",
    "wof:placetype":"venue"
},
  "geometry": {"coordinates":[-73.7665863037,45.7919998169],"type":"Point"}
}