{
  "type": "Feature",
  "properties": {
    "addr:full":"773 Bank St Ottawa ON K1S 3V5",
    "addr:housenumber":"773",
    "addr:postcode":"k1s 3v5",
    "addr:street":"Bank St",
    "iso:country":"CA",
    "sg:address":"773 Bank St",
    "sg:city":"Ottawa",
    "sg:classifiers":[
        {
            "category":"Restaurant",
            "type":"Food & Drink"
        }
    ],
    "sg:phone":"+1 613 232 1015",
    "sg:postcode":"K1S 3V5",
    "sg:province":"ON",
    "sg:tags":[
        "shop",
        "coffee"
    ],
    "wof:name":"Second Cup",
    "wof:placetype":"venue"
},
  "geometry": {"coordinates":[-75.688484,45.403645],"type":"Point"}
}