{
  "type": "Feature",
  "properties": {
    "addr:full":"258 Rue Saint-Joseph # A Sainte-Martine QC J0S 1V0",
    "addr:housenumber":"258",
    "addr:postcode":"j0s 1v0",
    "addr:street":"Rue Saint-Joseph # A Sainte-Martine",
    "iso:country":"CA",
    "sg:address":"258 Rue Saint-Joseph # A",
    "sg:city":"Sainte-Martine",
    "sg:classifiers":[
        {
            "category":"Restaurant",
            "type":"Food & Drink"
        }
    ],
    "sg:phone":"+1 450 427 3267",
    "sg:postcode":"J0S 1V0",
    "sg:province":"QC",
    "sg:tags":[
        "parlor",
        "ice",
        "cream"
    ],
    "wof:name":"Bar Laitier Gregoire",
    "wof:placetype":"venue"
},
  "geometry": {"coordinates":[-73.7980041504,45.2529296875],"type":"Point"}
}