{
  "type": "Feature",
  "properties": {
    "addr:full":"Scarborough ON M1V 4T3",
    "addr:postcode":"m1v 4t3",
    "iso:country":"CA",
    "sg:city":"Scarborough",
    "sg:classifiers":[
        {
            "category":"Manufacturing",
            "subcategory":"Paper Products",
            "type":"Manufacturing & Wholesale Goods"
        }
    ],
    "sg:phone":"+1 416 292 0788",
    "sg:postcode":"M1V 4T3",
    "sg:province":"ON",
    "sg:tags":[
        "bag"
    ],
    "wof:name":"Bestley Enterprises CO",
    "wof:placetype":"venue"
},
  "geometry": {"coordinates":[-79.30281100000001,43.818733],"type":"Point"}
}