{
  "type": "Feature",
  "properties": {
    "addr:full":"100 Wicks Ave Churchbridge SK S0A 0M0",
    "addr:housenumber":"100",
    "addr:postcode":"s0a 0m0",
    "addr:street":"Wicks Ave",
    "iso:country":"CA",
    "sg:address":"100 Wicks Ave",
    "sg:city":"Churchbridge",
    "sg:classifiers":[
        {
            "category":"Recreation",
            "type":"Entertainment"
        }
    ],
    "sg:phone":"+1 306 896 2491",
    "sg:postcode":"S0A 0M0",
    "sg:province":"SK",
    "sg:tags":[
        "pool",
        "swimming"
    ],
    "wof:name":"Churchbridge Swimming Pool",
    "wof:placetype":"venue"
},
  "geometry": {"coordinates":[-101.89769744900001,50.8973846436],"type":"Point"}
}