{
  "type": "Feature",
  "properties": {
    "addr:full":"67 East Main St Welland ON L3B 3W4",
    "addr:housenumber":"67",
    "addr:postcode":"l3b 3w4",
    "addr:street":"East Main St",
    "iso:country":"CA",
    "sg:address":"67 East Main St",
    "sg:city":"Welland",
    "sg:classifiers":[
        {
            "category":"Health Services",
            "subcategory":"Hospital",
            "type":"Services"
        }
    ],
    "sg:phone":"+1 905 788 3010",
    "sg:postcode":"L3B 3W4",
    "sg:province":"ON",
    "sg:tags":[
        "mental"
    ],
    "wof:name":"Oak Centre",
    "wof:placetype":"venue"
},
  "geometry": {"coordinates":[-79.249008,42.991821],"type":"Point"}
}