{
  "type": "Feature",
  "properties": {
    "addr:full":"53 Highway Ave London ON N6C 2K4",
    "addr:housenumber":"53",
    "addr:postcode":"n6c 2k4",
    "addr:street":"Highway Ave",
    "iso:country":"CA",
    "sg:address":"53 Highway Ave",
    "sg:city":"London",
    "sg:classifiers":[
        {
            "category":"Building & Trades",
            "subcategory":"Electrical",
            "type":"Services"
        }
    ],
    "sg:phone":"+1 519 672 5459",
    "sg:postcode":"N6C 2K4",
    "sg:province":"ON",
    "sg:tags":[
        "electric",
        "contractor"
    ],
    "wof:name":"K B Grundy Electrical Contr",
    "wof:placetype":"venue"
},
  "geometry": {"coordinates":[-81.25881195069999,42.9617652893],"type":"Point"}
}