{
  "type": "Feature",
  "properties": {
    "iso:country":"CA",
    "sg:address":"217 3E Av",
    "sg:city":"Iberville",
    "sg:classifiers":[
        {
            "category":"Home & Garden",
            "subcategory":"Building Materials",
            "type":"Retail Goods"
        }
    ],
    "sg:phone":"+1 450 346 0045",
    "sg:postcode":"J2X 1Y2",
    "sg:province":"QC",
    "sg:tags":[
        "glass",
        "window",
        "plate"
    ],
    "wof:name":"Vitrerie",
    "wof:placetype":"venue"
},
  "geometry": {"coordinates":[-73.2388534546,45.3053092957],"type":"Point"}
}