{
  "type": "Feature",
  "properties": {
    "addr:full":"Calgary AB T3G 5H6",
    "addr:postcode":"t3g 5h6",
    "iso:country":"CA",
    "sg:city":"Calgary",
    "sg:classifiers":[
        {
            "category":"Health Services",
            "subcategory":"Doctor",
            "type":"Services"
        }
    ],
    "sg:phone":"+1 403 202 4070",
    "sg:postcode":"T3G 5H6",
    "sg:province":"AB",
    "sg:tags":[
        "dentist"
    ],
    "wof:name":"Rix, Douglas DDS",
    "wof:placetype":"venue"
},
  "geometry": {"coordinates":[-114.20108,51.1292],"type":"Point"}
}