{
  "type": "Feature",
  "properties": {
    "addr:full":"280 Jane St Toronto ON M6S 3Z2",
    "addr:housenumber":"280",
    "addr:postcode":"m6s 3z2",
    "addr:street":"Jane St",
    "iso:country":"CA",
    "sg:address":"280 Jane St",
    "sg:city":"Toronto",
    "sg:classifiers":[
        {
            "category":"Restaurant",
            "type":"Food & Drink"
        }
    ],
    "sg:phone":"+1 416 766 5036",
    "sg:postcode":"M6S 3Z2",
    "sg:province":"ON",
    "sg:tags":[
        "caterer"
    ],
    "wof:name":"Gourmet Catering",
    "wof:placetype":"venue"
},
  "geometry": {"coordinates":[-79.487343,43.655903],"type":"Point"}
}