{
  "type": "Feature",
  "properties": {
    "addr:full":"5 Lisa St Brampton ON L6T 4T4",
    "addr:housenumber":"5",
    "addr:postcode":"l6t 4t4",
    "addr:street":"Lisa St",
    "iso:country":"CA",
    "sg:address":"5 Lisa St",
    "sg:city":"Brampton",
    "sg:classifiers":[
        {
            "category":"Professional",
            "subcategory":"Accounting & Tax Preparation",
            "type":"Services"
        }
    ],
    "sg:phone":"+1 905 450 0567",
    "sg:postcode":"L6T 4T4",
    "sg:province":"ON",
    "sg:tags":[
        "bookkeeping",
        "general"
    ],
    "wof:name":"Bill's Bookkeeping & Tax Svc",
    "wof:placetype":"venue"
},
  "geometry": {"coordinates":[-79.7256240845,43.7107543945],"type":"Point"}
}