{
  "type": "Feature",
  "properties": {
    "addr:full":"35587 Huron Rd Goderich ON N7A 3X8",
    "addr:housenumber":"35587",
    "addr:postcode":"n7a 3x8",
    "addr:street":"Huron Rd",
    "iso:country":"CA",
    "sg:address":"35587 Huron Rd",
    "sg:city":"Goderich",
    "sg:classifiers":[
        {
            "category":"Retail",
            "subcategory":"Auto Repair",
            "type":"Services"
        }
    ],
    "sg:phone":"+1 519 524 2638",
    "sg:postcode":"N7A 3X8",
    "sg:province":"ON",
    "sg:tags":[
        "truck"
    ],
    "wof:name":"Plane Colours",
    "wof:placetype":"venue"
},
  "geometry": {"coordinates":[-81.69174957280001,43.7317581177],"type":"Point"}
}