{
  "type": "Feature",
  "properties": {
    "addr:full":"2201 Broad St Regina SK S4P 1Y7",
    "addr:housenumber":"2201",
    "addr:postcode":"s4p 1y7",
    "addr:street":"Broad St",
    "iso:country":"CA",
    "sg:address":"2201 Broad St",
    "sg:city":"Regina",
    "sg:classifiers":[
        {
            "category":"Restaurant",
            "type":"Food & Drink"
        }
    ],
    "sg:phone":"+1 306 522 5535",
    "sg:postcode":"S4P 1Y7",
    "sg:province":"SK",
    "sg:tags":[
        "shop",
        "doughnut",
        "coffee"
    ],
    "wof:name":"Just Bean Brewed",
    "wof:placetype":"venue"
},
  "geometry": {"coordinates":[-104.606133,50.443783],"type":"Point"}
}