{
  "type": "Feature",
  "properties": {
    "addr:full":"Winnipeg MB R2H 1J9",
    "addr:postcode":"r2h 1j9",
    "iso:country":"CA",
    "sg:city":"Winnipeg",
    "sg:classifiers":[
        {
            "category":"Professional",
            "subcategory":"Lawyer & Legal Services",
            "type":"Services"
        }
    ],
    "sg:phone":"+1 204 957 0520",
    "sg:postcode":"R2H 1J9",
    "sg:province":"MB",
    "sg:tags":[
        "attorney"
    ],
    "wof:name":"Donen, Darrel",
    "wof:placetype":"venue"
},
  "geometry": {"coordinates":[-97.1425628662,49.8903503418],"type":"Point"}
}