{
  "type": "Feature",
  "properties": {
    "addr:full":"3650 Rue Principale Dunham QC J0E 1M0",
    "addr:housenumber":"3650",
    "addr:postcode":"j0e 1m0",
    "addr:street":"Rue Principale",
    "iso:country":"CA",
    "sg:address":"3650 Rue Principale",
    "sg:city":"Dunham",
    "sg:classifiers":[
        {
            "category":"Restaurant",
            "type":"Food & Drink"
        }
    ],
    "sg:phone":"+1 450 295 2323",
    "sg:postcode":"J0E 1M0",
    "sg:province":"QC",
    "wof:name":"Restaurant Des Trefles",
    "wof:placetype":"venue"
},
  "geometry": {"coordinates":[-72.80075100000001,45.134857],"type":"Point"}
}