{
  "type": "Feature",
  "properties": {
    "iso:country":"CA",
    "sg:address":"2 Landry St",
    "sg:city":"Winnipeg",
    "sg:classifiers":[
        {
            "category":"Building & Trades",
            "subcategory":"Construction",
            "type":"Services"
        }
    ],
    "sg:phone":"+1 204 269 0009",
    "sg:postcode":"R3V 1K9",
    "sg:province":"MB",
    "sg:tags":[
        "plastering",
        "contractor"
    ],
    "wof:name":"Morin Stucco Wire",
    "wof:placetype":"venue"
},
  "geometry": {"coordinates":[-97.150208,49.764893],"type":"Point"}
}