{
  "type": "Feature",
  "properties": {
    "iso:country":"CA",
    "sg:address":"60 Horton Lane",
    "sg:city":"Penobsquis",
    "sg:classifiers":[
        {
            "category":"Wholesale",
            "subcategory":"Auto Parts",
            "type":"Manufacturing & Wholesale Goods"
        }
    ],
    "sg:phone":"+1 506 433 3976",
    "sg:postcode":"E4G 2W8",
    "sg:province":"NB",
    "sg:tags":[
        "automobile",
        "rebuilt"
    ],
    "wof:name":"Craig's Auto Salvage",
    "wof:placetype":"venue"
},
  "geometry": {"coordinates":[-65.3874053955,45.7747192383],"type":"Point"}
}