{
  "type": "Feature",
  "properties": {
    "addr:full":"Whistler BC V0N 1B4",
    "addr:postcode":"v0n 1b4",
    "iso:country":"CA",
    "sg:city":"Whistler",
    "sg:classifiers":[
        {
            "category":"Travel",
            "subcategory":"Travel Agent",
            "type":"Entertainment"
        }
    ],
    "sg:phone":"+1 604 935 3445",
    "sg:postcode":"V0N 1B4",
    "sg:province":"BC",
    "sg:tags":[
        "agency",
        "bureau"
    ],
    "wof:name":"Explore Whistler Adventures",
    "wof:placetype":"venue"
},
  "geometry": {"coordinates":[-122.956962585,50.1116104126],"type":"Point"}
}