{
  "type": "Feature",
  "properties": {
    "addr:full":"245 Welton St Sydney NS B1P 5S3",
    "addr:housenumber":"245",
    "addr:postcode":"b1p 5s3",
    "addr:street":"Welton St",
    "iso:country":"CA",
    "sg:address":"245 Welton St",
    "sg:city":"Sydney",
    "sg:classifiers":[
        {
            "category":"Personal",
            "subcategory":"Tanning Parlor",
            "type":"Services"
        }
    ],
    "sg:phone":"+1 902 567 0212",
    "sg:postcode":"B1P 5S3",
    "sg:province":"NS",
    "sg:tags":[
        "salon",
        "program",
        "physical",
        "exercise",
        "fitness"
    ],
    "wof:name":"Sweeney's Gym & Fitness Ctr",
    "wof:placetype":"venue"
},
  "geometry": {"coordinates":[-60.166252,46.143486],"type":"Point"}
}