{
  "type": "Feature",
  "properties": {
    "addr:full":"252 10th St Hanover ON N4N 1N9",
    "addr:housenumber":"252",
    "addr:postcode":"n4n 1n9",
    "addr:street":"10Th St",
    "iso:country":"CA",
    "sg:address":"252 10th St",
    "sg:city":"Hanover",
    "sg:classifiers":[
        {
            "category":"Food & Beverages",
            "subcategory":"Liquor & Beverages",
            "type":"Retail Goods"
        }
    ],
    "sg:phone":"+1 519 364 2980",
    "sg:postcode":"N4N 1N9",
    "sg:province":"ON",
    "sg:tags":[
        "store"
    ],
    "wof:name":"Liquor Control Board of Ont",
    "wof:placetype":"venue"
},
  "geometry": {"coordinates":[-81.02951,44.151928],"type":"Point"}
}