{
  "type": "Feature",
  "properties": {
    "addr:full":"36 Rue Bourbeau Windsor QC J1S 2P6",
    "addr:housenumber":"36",
    "addr:postcode":"j1s 2p6",
    "addr:street":"Rue Bourbeau",
    "iso:country":"CA",
    "sg:address":"36 Rue Bourbeau",
    "sg:city":"Windsor",
    "sg:classifiers":[
        {
            "category":"Building & Trades",
            "subcategory":"Construction",
            "type":"Services"
        }
    ],
    "sg:phone":"+1 819 845 2469",
    "sg:postcode":"J1S 2P6",
    "sg:province":"QC",
    "sg:tags":[
        "general",
        "contractor"
    ],
    "wof:name":"Construction Ade",
    "wof:placetype":"venue"
},
  "geometry": {"coordinates":[-72.01469400000001,45.561176],"type":"Point"}
}