{
  "type": "Feature",
  "properties": {
    "addr:full":"1271 Rue Sainte-Catherine E Montreal QC H2L 2H3",
    "addr:housenumber":"1271",
    "addr:postcode":"h2l 2h3",
    "addr:street":"Rue Sainte-Catherine E",
    "iso:country":"CA",
    "sg:address":"1271 Rue Sainte-Catherine E",
    "sg:city":"Montreal",
    "sg:classifiers":[
        {
            "category":"Food & Beverages",
            "subcategory":"Groceries & Convenience Stores",
            "type":"Retail Goods"
        }
    ],
    "sg:phone":"+1 514 524 3256",
    "sg:postcode":"H2L 2H3",
    "sg:province":"QC",
    "wof:name":"Depanneur Du Village DE Mtl",
    "wof:placetype":"venue"
},
  "geometry": {"coordinates":[-73.55577099999999,45.5191],"type":"Point"}
}