{
  "type": "Feature",
  "properties": {
    "iso:country":"CA",
    "sg:address":"245 Rue Notre-Dame N",
    "sg:city":"Sainte-Marie",
    "sg:classifiers":[
        {
            "category":"Bars & Pubs",
            "type":"Food & Drink"
        }
    ],
    "sg:phone":"+1 418 387 2011",
    "sg:postcode":"G6E 2K5",
    "sg:province":"QC",
    "sg:tags":[
        "lounge",
        "cocktail"
    ],
    "wof:name":"Bar Le Houblon",
    "wof:placetype":"venue"
},
  "geometry": {"coordinates":[-71.0266418457,46.4400215149],"type":"Point"}
}