{
  "type": "Feature",
  "properties": {
    "addr:full":"2424 5th Ave Fort Macleod AB T0L 0Z0",
    "addr:housenumber":"2424",
    "addr:postcode":"t0l 0z0",
    "addr:street":"5Th Ave Fort",
    "iso:country":"CA",
    "sg:address":"2424 5th Ave",
    "sg:city":"Fort Macleod",
    "sg:classifiers":[
        {
            "category":"Retail",
            "subcategory":"Funeral Services",
            "type":"Services"
        }
    ],
    "sg:phone":"+1 403 553 3772",
    "sg:postcode":"T0L 0Z0",
    "sg:province":"AB",
    "sg:tags":[
        "director"
    ],
    "wof:name":"Eden's Funeral Home Ltd",
    "wof:placetype":"venue"
},
  "geometry": {"coordinates":[-113.400192,49.725895],"type":"Point"}
}