{
  "type": "Feature",
  "properties": {
    "addr:full":"772 Hamilton Rd London ON N5Z 1T9",
    "addr:housenumber":"772",
    "addr:postcode":"n5z 1t9",
    "addr:street":"Hamilton Rd",
    "iso:country":"CA",
    "sg:address":"772 Hamilton Rd",
    "sg:city":"London",
    "sg:classifiers":[
        {
            "category":"Food & Beverages",
            "subcategory":"Bakery",
            "type":"Retail Goods"
        }
    ],
    "sg:phone":"+1 519 455 6250",
    "sg:postcode":"N5Z 1T9",
    "sg:province":"ON",
    "sg:tags":[
        "baker"
    ],
    "wof:name":"Klein's Bakery Ltd",
    "wof:placetype":"venue"
},
  "geometry": {"coordinates":[-81.2033615112,42.9791030884],"type":"Point"}
}