{
  "type": "Feature",
  "properties": {
    "addr:full":"2717 Rock Bay Ave Victoria BC V8T 4R8",
    "addr:housenumber":"2717",
    "addr:postcode":"v8t 4r8",
    "addr:street":"Rock Bay Ave",
    "iso:country":"CA",
    "sg:address":"2717 Rock Bay Ave",
    "sg:city":"Victoria",
    "sg:classifiers":[
        {
            "category":"Wholesale",
            "subcategory":"Office Equipment",
            "type":"Manufacturing & Wholesale Goods"
        }
    ],
    "sg:phone":"+1 250 381 1666",
    "sg:postcode":"V8T 4R8",
    "sg:province":"BC",
    "sg:tags":[
        "parts",
        "register",
        "computer",
        "cash",
        "supply"
    ],
    "wof:name":"Riptide Computer Resources Inc",
    "wof:placetype":"venue"
},
  "geometry": {"coordinates":[-123.3697052,48.4379005432],"type":"Point"}
}