{
  "type": "Feature",
  "properties": {
    "iso:country":"CA",
    "sg:address":"11 Durham St E",
    "sg:city":"Walkerton",
    "sg:classifiers":[
        {
            "category":"Shopping",
            "subcategory":"Clothing, Apparel, & Fashions",
            "type":"Retail Goods"
        }
    ],
    "sg:phone":"+1 519 881 2835",
    "sg:postcode":"N0G 2V0",
    "sg:province":"ON",
    "sg:tags":[
        "shop",
        "bridal"
    ],
    "wof:name":"House of Brides",
    "wof:placetype":"venue"
},
  "geometry": {"coordinates":[-81.1532821655,44.1337890625],"type":"Point"}
}