{
  "type": "Feature",
  "properties": {
    "addr:full":"575 Queen St Chatham ON N7M 2J7",
    "addr:housenumber":"575",
    "addr:postcode":"n7m 2j7",
    "addr:street":"Queen St",
    "iso:country":"CA",
    "sg:address":"575 Queen St",
    "sg:city":"Chatham",
    "sg:classifiers":[
        {
            "category":"Health Services",
            "subcategory":"Doctor",
            "type":"Services"
        }
    ],
    "sg:phone":"+1 519 351 0727",
    "sg:postcode":"N7M 2J7",
    "sg:province":"ON",
    "sg:tags":[
        "dentist"
    ],
    "wof:name":"Pucovsky, John DDS",
    "wof:placetype":"venue"
},
  "geometry": {"coordinates":[-82.17255400000001,42.393032],"type":"Point"}
}