{
  "type": "Feature",
  "properties": {
    "addr:full":"3 Vanier Dr Pinawa MB R0E 1L0",
    "addr:housenumber":"3",
    "addr:postcode":"r0e 1l0",
    "addr:street":"Vanier Dr Pinawa",
    "iso:country":"CA",
    "sg:address":"3 Vanier Dr",
    "sg:city":"Pinawa",
    "sg:classifiers":[
        {
            "category":"Shopping",
            "subcategory":"Pharmacy",
            "type":"Retail Goods"
        }
    ],
    "sg:phone":"+1 204 753 2324",
    "sg:postcode":"R0E 1L0",
    "sg:province":"MB",
    "wof:name":"Pinawa Pharmacy",
    "wof:placetype":"venue"
},
  "geometry": {"coordinates":[-95.8785018921,50.1492385864],"type":"Point"}
}