{
  "type": "Feature",
  "properties": {
    "iso:country":"CA",
    "sg:address":"17600 Yonge St",
    "sg:city":"Newmarket",
    "sg:classifiers":[
        {
            "category":"Shopping",
            "subcategory":"Department Store",
            "type":"Retail Goods"
        }
    ],
    "sg:phone":"+1 905 895 1100",
    "sg:postcode":"L3Y 4Z1",
    "sg:province":"ON",
    "wof:name":"Zellers",
    "wof:placetype":"venue"
},
  "geometry": {"coordinates":[-79.48111,44.057056],"type":"Point"}
}