{
  "type": "Feature",
  "properties": {
    "addr:full":"2070 Broad St Regina SK S4P 1Y3",
    "addr:housenumber":"2070",
    "addr:postcode":"s4p 1y3",
    "addr:street":"Broad St",
    "iso:country":"CA",
    "sg:address":"2070 Broad St",
    "sg:city":"Regina",
    "sg:classifiers":[
        {
            "category":"Organizations",
            "subcategory":"Professional Association",
            "type":"Services"
        }
    ],
    "sg:phone":"+1 306 525 6046",
    "sg:postcode":"S4P 1Y3",
    "sg:province":"SK",
    "wof:name":"Pink Triangle Community Svc",
    "wof:placetype":"venue"
},
  "geometry": {"coordinates":[-104.606728,50.446049],"type":"Point"}
}