{
  "type": "Feature",
  "properties": {
    "addr:full":"365 William St Midland ON L4R 2S4",
    "addr:housenumber":"365",
    "addr:postcode":"l4r 2s4",
    "addr:street":"William St",
    "iso:country":"CA",
    "sg:address":"365 William St",
    "sg:city":"Midland",
    "sg:classifiers":[
        {
            "category":"Home & Garden",
            "subcategory":"Home Furnishings",
            "type":"Retail Goods"
        }
    ],
    "sg:phone":"+1 705 527 9663",
    "sg:postcode":"L4R 2S4",
    "sg:province":"ON",
    "sg:tags":[
        "stove",
        "wood",
        "burning"
    ],
    "wof:name":"Woodworks",
    "wof:placetype":"venue"
},
  "geometry": {"coordinates":[-79.871925354,44.7526664734],"type":"Point"}
}