{
  "type": "Feature",
  "properties": {
    "addr:full":"262 Rue Labelle Saint-Jerome QC J7Z 5L1",
    "addr:housenumber":"262",
    "addr:postcode":"j7z 5l1",
    "addr:street":"Rue Labelle Saint-Jerome",
    "iso:country":"CA",
    "sg:address":"262 Rue Labelle",
    "sg:city":"Saint-Jerome",
    "sg:classifiers":[
        {
            "category":"Shopping",
            "subcategory":"Shoes",
            "type":"Retail Goods"
        }
    ],
    "sg:phone":"+1 450 432 4675",
    "sg:postcode":"J7Z 5L1",
    "sg:province":"QC",
    "wof:name":"Theoret R Chaussures Ltee",
    "wof:placetype":"venue"
},
  "geometry": {"coordinates":[-74.00430299999999,45.775028],"type":"Point"}
}