{
  "type": "Feature",
  "properties": {
    "addr:full":"3516 35 Ave SW Calgary AB T3E 1A3",
    "addr:housenumber":"3516",
    "addr:postcode":"t3e 1a3",
    "addr:street":"35 Ave Sw",
    "iso:country":"CA",
    "sg:address":"3516 35 Ave SW",
    "sg:city":"Calgary",
    "sg:classifiers":[
        {
            "category":"Professional",
            "subcategory":"Accounting & Tax Preparation",
            "type":"Services"
        }
    ],
    "sg:phone":"+1 403 240 9245",
    "sg:postcode":"T3E 1A3",
    "sg:province":"AB",
    "sg:tags":[
        "consultant"
    ],
    "wof:name":"Sylvan Tax Svc Ltd",
    "wof:placetype":"venue"
},
  "geometry": {"coordinates":[-114.13593292199999,51.0225067139],"type":"Point"}
}