{
  "type": "Feature",
  "properties": {
    "addr:full":"4710 Rue Saint-Ambroise # 170 Montreal QC H4C 2C7",
    "addr:housenumber":"4710",
    "addr:postcode":"h4c 2c7",
    "addr:street":"Rue Saint-Ambroise # 170",
    "iso:country":"CA",
    "sg:address":"4710 Rue Saint-Ambroise # 170",
    "sg:city":"Montreal",
    "sg:classifiers":[
        {
            "category":"Manufacturing",
            "subcategory":"Printing",
            "type":"Manufacturing & Wholesale Goods"
        }
    ],
    "sg:phone":"+1 514 933 3184",
    "sg:postcode":"H4C 2C7",
    "sg:province":"QC",
    "sg:tags":[
        "screen"
    ],
    "wof:name":"Y Knot Designs",
    "wof:placetype":"venue"
},
  "geometry": {"coordinates":[-73.585503,45.470619],"type":"Point"}
}