{
  "type": "Feature",
  "properties": {
    "iso:country":"CA",
    "sg:address":"5417 Boul Gouin O",
    "sg:city":"Montreal",
    "sg:classifiers":[
        {
            "category":"Personal",
            "subcategory":"Beauty Salon",
            "type":"Services"
        }
    ],
    "sg:phone":"+1 514 334 3035",
    "sg:postcode":"H4J 1C7",
    "sg:province":"QC",
    "wof:name":"Coiffure Mireille",
    "wof:placetype":"venue"
},
  "geometry": {"coordinates":[-73.716454,45.534122],"type":"Point"}
}