{
  "type": "Feature",
  "properties": {
    "addr:full":"24 Elizabeth St Brighton ON K0K 1H0",
    "addr:housenumber":"24",
    "addr:postcode":"k0k 1h0",
    "addr:street":"Elizabeth St",
    "iso:country":"CA",
    "sg:address":"24 Elizabeth St",
    "sg:city":"Brighton",
    "sg:classifiers":[
        {
            "category":"Education",
            "subcategory":"School",
            "type":"Public Place"
        }
    ],
    "sg:phone":"+1 613 475 2814",
    "sg:postcode":"K0K 1H0",
    "sg:province":"ON",
    "wof:name":"Brighton Public School",
    "wof:placetype":"venue"
},
  "geometry": {"coordinates":[-77.73454284669999,44.0422058105],"type":"Point"}
}