{
  "type": "Feature",
  "properties": {
    "addr:full":"120 Govt Road Allowance NW Newdale MB R0J 1J0",
    "addr:housenumber":"120",
    "addr:postcode":"r0j 1j0",
    "addr:street":"Govt Road Allowance Nw",
    "iso:country":"CA",
    "sg:address":"120 Govt Road Allowance NW",
    "sg:city":"Newdale",
    "sg:classifiers":[
        {
            "category":"Retail",
            "subcategory":"Auto Repair",
            "type":"Services"
        }
    ],
    "sg:phone":"+1 204 849 2052",
    "sg:postcode":"R0J 1J0",
    "sg:province":"MB",
    "sg:tags":[
        "repairing",
        "automobile"
    ],
    "wof:name":"Baker's Service",
    "wof:placetype":"venue"
},
  "geometry": {"coordinates":[-100.203681946,50.3506660461],"type":"Point"}
}