{
  "type": "Feature",
  "properties": {
    "iso:country":"CA",
    "sg:address":"95 Falshire Dr NE",
    "sg:city":"Calgary",
    "sg:classifiers":[
        {
            "category":"Organizations",
            "subcategory":"Professional Association",
            "type":"Services"
        }
    ],
    "sg:phone":"+1 403 280 4422",
    "sg:postcode":"T3J 1P7",
    "sg:province":"AB",
    "sg:tags":[
        "montessori",
        "school"
    ],
    "wof:name":"Falconridge/Castleridge Comm",
    "wof:placetype":"venue"
},
  "geometry": {"coordinates":[-113.945984,51.105206],"type":"Point"}
}