{
  "type": "Feature",
  "properties": {
    "addr:full":"49 King St Dryden ON P8N 1B7",
    "addr:housenumber":"49",
    "addr:postcode":"p8n 1b7",
    "addr:street":"King St",
    "iso:country":"CA",
    "sg:address":"49 King St",
    "sg:city":"Dryden",
    "sg:classifiers":[
        {
            "category":"Shopping",
            "subcategory":"Gifts & Souvenirs",
            "type":"Retail Goods"
        }
    ],
    "sg:phone":"+1 807 223 4880",
    "sg:postcode":"P8N 1B7",
    "sg:province":"ON",
    "sg:tags":[
        "shop",
        "art",
        "gallery",
        "dealer"
    ],
    "wof:name":"About Crafts & Art Studio",
    "wof:placetype":"venue"
},
  "geometry": {"coordinates":[-92.8383560181,49.7843818665],"type":"Point"}
}