{
  "type": "Feature",
  "properties": {
    "addr:full":"Edmonton AB T5E 6K1",
    "addr:postcode":"t5e 6k1",
    "iso:country":"CA",
    "sg:city":"Edmonton",
    "sg:classifiers":[
        {
            "category":"Real Estate",
            "subcategory":"Real Estate Agent",
            "type":"Services"
        }
    ],
    "sg:phone":"+1 780 413 4547",
    "sg:postcode":"T5E 6K1",
    "sg:province":"AB",
    "sg:tags":[
        "appraiser"
    ],
    "wof:name":"R E Advisory Svc Ltd",
    "wof:placetype":"venue"
},
  "geometry": {"coordinates":[-113.490371704,53.5462188721],"type":"Point"}
}