{
  "type": "Feature",
  "properties": {
    "iso:country":"CA",
    "sg:address":"33211 N Railway Ave",
    "sg:city":"Mission",
    "sg:classifiers":[
        {
            "category":"Recreation",
            "type":"Entertainment"
        }
    ],
    "sg:phone":"+1 604 820 7429",
    "sg:postcode":"V4S 1E3",
    "sg:province":"BC",
    "sg:tags":[
        "martial",
        "arts",
        "instruction"
    ],
    "wof:name":"Canadian Martial Arts Academy",
    "wof:placetype":"venue"
},
  "geometry": {"coordinates":[-122.304207,49.134048],"type":"Point"}
}