{
  "type": "Feature",
  "properties": {
    "addr:full":"311 Caldari Rd Concord ON L4K 4S9",
    "addr:housenumber":"311",
    "addr:postcode":"l4k 4s9",
    "addr:street":"Caldari Rd",
    "iso:country":"CA",
    "sg:address":"311 Caldari Rd",
    "sg:city":"Concord",
    "sg:classifiers":[
        {
            "category":"Wholesale",
            "subcategory":"Stationery",
            "type":"Manufacturing & Wholesale Goods"
        }
    ],
    "sg:phone":"+1 905 738 7205",
    "sg:postcode":"L4K 4S9",
    "sg:province":"ON",
    "sg:tags":[
        "box",
        "fiber"
    ],
    "wof:name":"Flint Packaging Products Ltd",
    "wof:placetype":"venue"
},
  "geometry": {"coordinates":[-79.529808,43.826233],"type":"Point"}
}