{
  "type": "Feature",
  "properties": {
    "iso:country":"CA",
    "sg:city":"Saskatoon",
    "sg:classifiers":[
        {
            "category":"Building & Trades",
            "subcategory":"Construction",
            "type":"Services"
        }
    ],
    "sg:phone":"+1 306 934 3533",
    "sg:postcode":"S7K 6K1",
    "sg:province":"SK",
    "sg:tags":[
        "concrete",
        "contractor",
        "restoration",
        "cleaning",
        "repair"
    ],
    "wof:name":"Vector Construction Ltd",
    "wof:placetype":"venue"
},
  "geometry": {"coordinates":[-106.664360046,52.1704864502],"type":"Point"}
}