{
  "type": "Feature",
  "properties": {
    "addr:full":"1113 4th Ave Raymore SK S0A 3J0",
    "addr:housenumber":"1113",
    "addr:postcode":"s0a 3j0",
    "addr:street":"4Th Ave",
    "iso:country":"CA",
    "sg:address":"1113 4th Ave",
    "sg:city":"Raymore",
    "sg:classifiers":[
        {
            "category":"Building & Trades",
            "subcategory":"Plumbing",
            "type":"Services"
        }
    ],
    "sg:phone":"+1 306 746 2930",
    "sg:postcode":"S0A 3J0",
    "sg:province":"SK",
    "sg:tags":[
        "contractor"
    ],
    "wof:name":"Sebastian Plumbing & Heating",
    "wof:placetype":"venue"
},
  "geometry": {"coordinates":[-104.538024902,51.4097290039],"type":"Point"}
}