{
  "type": "Feature",
  "properties": {
    "addr:full":"3045 Broadway W Vancouver BC V6K 2G9",
    "addr:housenumber":"3045",
    "addr:postcode":"v6k 2g9",
    "addr:street":"Broadway W",
    "iso:country":"CA",
    "sg:address":"3045 Broadway W",
    "sg:city":"Vancouver",
    "sg:classifiers":[
        {
            "category":"Food & Beverages",
            "subcategory":"Groceries & Convenience Stores",
            "type":"Retail Goods"
        }
    ],
    "sg:phone":"+1 604 733 3398",
    "sg:postcode":"V6K 2G9",
    "sg:province":"BC",
    "sg:tags":[
        "grocer"
    ],
    "wof:name":"Golden Valley Farm Market Ltd",
    "wof:placetype":"venue"
},
  "geometry": {"coordinates":[-123.17278289799999,49.264251709],"type":"Point"}
}