{
  "type": "Feature",
  "properties": {
    "addr:full":"7405 100 Ave Fort St John BC V1J 5T8",
    "addr:housenumber":"7405",
    "addr:postcode":"v1j 5t8",
    "addr:street":"100 Ave",
    "iso:country":"CA",
    "sg:address":"7405 100 Ave",
    "sg:city":"Fort St John",
    "sg:phone":"+1 250 787 0791",
    "sg:postcode":"V1J 5T8",
    "sg:province":"BC",
    "sg:tags":[
        "product",
        "oil",
        "petroleum"
    ],
    "wof:name":"Imperial Oil",
    "wof:placetype":"venue"
},
  "geometry": {"coordinates":[-120.847252,56.221725],"type":"Point"}
}