{
  "type": "Feature",
  "properties": {
    "iso:country":"CA",
    "sg:address":"169 Rue Champlain",
    "sg:city":"Salaberry-DE-Valleyfield",
    "sg:classifiers":[
        {
            "category":"Shopping",
            "subcategory":"Stationery & Office Supplies",
            "type":"Retail Goods"
        }
    ],
    "sg:phone":"+1 450 371 3100",
    "sg:postcode":"J6T 1X6",
    "sg:province":"QC",
    "sg:tags":[
        "stationer"
    ],
    "wof:name":"Association CO-Op-Etudiants",
    "wof:placetype":"venue"
},
  "geometry": {"coordinates":[-74.13246917719999,45.2536354065],"type":"Point"}
}