{
  "type": "Feature",
  "properties": {
    "addr:full":"5201 Duke St Halifax NS B3J 1N9",
    "addr:housenumber":"5201",
    "addr:postcode":"ns b3j 1n9",
    "addr:street":"Duke St",
    "iso:country":"CA",
    "sg:address":"5201 Duke St",
    "sg:city":"Halifax",
    "sg:classifiers":[
        {
            "category":"Shopping",
            "subcategory":"Clothing, Apparel, & Fashions",
            "type":"Retail Goods"
        }
    ],
    "sg:phone":"+1 902 429 7832",
    "sg:postcode":"B3J 1N9",
    "sg:province":"NS",
    "wof:name":"Reitmans",
    "wof:placetype":"venue"
},
  "geometry": {"coordinates":[-63.575165,44.64922],"type":"Point"}
}