{
  "type": "Feature",
  "properties": {
    "addr:full":"20 Market Dr Milton ON L9T 3H5",
    "addr:housenumber":"20",
    "addr:postcode":"l9t 3h5",
    "addr:street":"Market Dr",
    "iso:country":"CA",
    "sg:address":"20 Market Dr",
    "sg:city":"Milton",
    "sg:classifiers":[
        {
            "category":"Autos & Motor Vehicles",
            "subcategory":"Auto Supplies",
            "type":"Retail Goods"
        }
    ],
    "sg:phone":"+1 905 878 2495",
    "sg:postcode":"L9T 3H5",
    "sg:province":"ON",
    "sg:tags":[
        "automobile",
        "parts"
    ],
    "wof:name":"Canadian Tire",
    "wof:placetype":"venue"
},
  "geometry": {"coordinates":[-79.90087127690001,43.5230102539],"type":"Point"}
}