{
  "type": "Feature",
  "properties": {
    "addr:full":"21 Tsse Villebon Repentigny QC J6A 1P4",
    "addr:housenumber":"21",
    "addr:postcode":"j6a 1p4",
    "addr:street":"Tsse Villebon",
    "iso:country":"CA",
    "sg:address":"21 Tsse Villebon",
    "sg:city":"Repentigny",
    "sg:classifiers":[
        {
            "category":"Shopping",
            "subcategory":"Tobacco",
            "type":"Retail Goods"
        }
    ],
    "sg:phone":"+1 514 866 3179",
    "sg:postcode":"J6A 1P4",
    "sg:province":"QC",
    "sg:tags":[
        "cigarette",
        "cigar",
        "dealer"
    ],
    "wof:name":"Entreprises Paul Dussault",
    "wof:placetype":"venue"
},
  "geometry": {"coordinates":[-73.47146606450001,45.7261047363],"type":"Point"}
}