{
  "type": "Feature",
  "properties": {
    "iso:country":"CA",
    "sg:city":"Stittsville",
    "sg:classifiers":[
        {
            "category":"Personal",
            "subcategory":"Beauty Salon",
            "type":"Services"
        }
    ],
    "sg:phone":"+1 613 836 6113",
    "sg:postcode":"K2S 1B1",
    "sg:province":"ON",
    "wof:name":"Shears Hair Design",
    "wof:placetype":"venue"
},
  "geometry": {"coordinates":[-75.9287261963,45.2647247314],"type":"Point"}
}