{
  "type": "Feature",
  "properties": {
    "iso:country":"CA",
    "sg:city":"Mississauga",
    "sg:classifiers":[
        {
            "category":"Communications",
            "subcategory":"Film & Video Production",
            "type":"Services"
        }
    ],
    "sg:phone":"+1 905 602 6977",
    "sg:postcode":"L4W 4T6",
    "sg:province":"ON",
    "sg:tags":[
        "audio"
    ],
    "wof:name":"Van Valkenburg Communications",
    "wof:placetype":"venue"
},
  "geometry": {"coordinates":[-79.6086807251,43.6371765137],"type":"Point"}
}