{
  "type": "Feature",
  "properties": {
    "addr:full":"603 Rue Dufour Laurierville QC G0S 1P0",
    "addr:housenumber":"603",
    "addr:postcode":"g0s 1p0",
    "addr:street":"Rue Dufour",
    "iso:country":"CA",
    "sg:address":"603 Rue Dufour",
    "sg:city":"Laurierville",
    "sg:classifiers":[
        {
            "category":"Manufacturing",
            "subcategory":"Tools & Machinery",
            "type":"Manufacturing & Wholesale Goods"
        }
    ],
    "sg:phone":"+1 819 365 4555",
    "sg:postcode":"G0S 1P0",
    "sg:province":"QC",
    "sg:tags":[
        "pattern",
        "maker"
    ],
    "wof:name":"J M Samson Inc",
    "wof:placetype":"venue"
},
  "geometry": {"coordinates":[-71.65883599999999,46.294693],"type":"Point"}
}