{
  "type": "Feature",
  "properties": {
    "addr:full":"1325 Shawson Dr Mississauga ON L4W 1C4",
    "addr:housenumber":"1325",
    "addr:postcode":"l4w 1c4",
    "addr:street":"Shawson Dr",
    "iso:country":"CA",
    "sg:address":"1325 Shawson Dr",
    "sg:city":"Mississauga",
    "sg:classifiers":[
        {
            "category":"Building & Trades",
            "subcategory":"Construction",
            "type":"Services"
        }
    ],
    "sg:phone":"+1 905 564 1553",
    "sg:postcode":"L4W 1C4",
    "sg:province":"ON",
    "sg:tags":[
        "waterproofing",
        "contractor"
    ],
    "wof:name":"M E Nevins Ltd",
    "wof:placetype":"venue"
},
  "geometry": {"coordinates":[-79.64697265620001,43.6498527527],"type":"Point"}
}