{
  "type": "Feature",
  "properties": {
    "iso:country":"CA",
    "sg:address":"4619 Rue Leckie",
    "sg:city":"Saint-Hubert",
    "sg:classifiers":[
        {
            "category":"Education",
            "subcategory":"School",
            "type":"Public Place"
        }
    ],
    "sg:phone":"+1 450 678 2018",
    "sg:postcode":"J3Y 9E6",
    "sg:province":"QC",
    "wof:name":"Academie Marie-Laurier Inc",
    "wof:placetype":"venue"
},
  "geometry": {"coordinates":[-73.430801,45.518299],"type":"Point"}
}