{
  "type": "Feature",
  "properties": {
    "addr:full":"Mckenzie Rd E Red Deer AB T4N 5E8",
    "addr:postcode":"t4n 5e8",
    "addr:street":"Mckenzie Rd E",
    "iso:country":"CA",
    "sg:address":"Mckenzie Rd E",
    "sg:city":"Red Deer",
    "sg:classifiers":[
        {
            "category":"Organizations",
            "subcategory":"Religious Organization",
            "type":"Services"
        }
    ],
    "sg:phone":"+1 403 886 4123",
    "sg:postcode":"T4N 5E8",
    "sg:province":"AB",
    "sg:tags":[
        "church"
    ],
    "wof:name":"Seventh Day Adventist Church",
    "wof:placetype":"venue"
},
  "geometry": {"coordinates":[-113.790092,52.295841],"type":"Point"}
}