{
  "type": "Feature",
  "properties": {
    "addr:full":"Burnaby BC V5C 2L1",
    "addr:postcode":"v5c 2l1",
    "iso:country":"CA",
    "sg:city":"Burnaby",
    "sg:classifiers":[
        {
            "category":"Insurance",
            "subcategory":"Insurance Agent",
            "type":"Services"
        }
    ],
    "sg:phone":"+1 604 294 4441",
    "sg:postcode":"V5C 2L1",
    "sg:province":"BC",
    "sg:tags":[
        "consultant"
    ],
    "wof:name":"Arm Management Ltd",
    "wof:placetype":"venue"
},
  "geometry": {"coordinates":[-122.994011,49.281055],"type":"Point"}
}