{
  "type": "Feature",
  "properties": {
    "addr:full":"980 Rue Richelieu Quebec QC G1R 1L5",
    "addr:housenumber":"980",
    "addr:postcode":"g1r 1l5",
    "addr:street":"Rue Richelieu",
    "iso:country":"CA",
    "sg:address":"980 Rue Richelieu",
    "sg:city":"Quebec",
    "sg:classifiers":[
        {
            "category":"Education",
            "subcategory":"School",
            "type":"Public Place"
        }
    ],
    "sg:phone":"+1 418 692 1072",
    "sg:postcode":"G1R 1L5",
    "sg:province":"QC",
    "wof:name":"Ecole St-Louis-Gonzague",
    "wof:placetype":"venue"
},
  "geometry": {"coordinates":[-71.21476745610001,46.8135757446],"type":"Point"}
}