{
  "type": "Feature",
  "properties": {
    "iso:country":"CA",
    "sg:city":"Sutton West",
    "sg:classifiers":[
        {
            "category":"Arena",
            "subcategory":"Sports Club",
            "type":"Entertainment"
        }
    ],
    "sg:phone":"+1 905 722 8661",
    "sg:postcode":"L0E 1R0",
    "sg:province":"ON",
    "sg:tags":[
        "athletic",
        "fields",
        "stadium",
        "government"
    ],
    "wof:name":"Sutton Arena",
    "wof:placetype":"venue"
},
  "geometry": {"coordinates":[-79.3537368774,44.3016586304],"type":"Point"}
}