{
  "type": "Feature",
  "properties": {
    "addr:full":"22 Bloomfield Rd South Ohio NS B0W 3E0",
    "addr:housenumber":"22",
    "addr:postcode":"b0w 3e0",
    "addr:street":"Bloomfield Rd",
    "iso:country":"CA",
    "sg:address":"22 Bloomfield Rd",
    "sg:city":"South Ohio",
    "sg:classifiers":[
        {
            "category":"Building & Trades",
            "subcategory":"Cleaning & Sanitation",
            "type":"Services"
        }
    ],
    "sg:phone":"+1 902 761 2452",
    "sg:postcode":"B0W 3E0",
    "sg:province":"NS",
    "wof:name":"Clean-Rite Industrial Cleaners",
    "wof:placetype":"venue"
},
  "geometry": {"coordinates":[-66.0454940796,43.9244766235],"type":"Point"}
}