{
  "type": "Feature",
  "properties": {
    "addr:full":"1289 Highway 54 Caledonia ON N3W 2G9",
    "addr:housenumber":"1289",
    "addr:postcode":"n3w 2g9",
    "addr:street":"Highway 54",
    "iso:country":"CA",
    "sg:address":"1289 Highway 54",
    "sg:city":"Caledonia",
    "sg:classifiers":[
        {
            "category":"Freight",
            "type":"Transportation"
        }
    ],
    "sg:phone":"+1 905 765 0707",
    "sg:postcode":"N3W 2G9",
    "sg:province":"ON",
    "sg:tags":[
        "grain",
        "elevator"
    ],
    "wof:name":"Blaindale Farms Ltd",
    "wof:placetype":"venue"
},
  "geometry": {"coordinates":[-79.95072937010001,43.0735626221],"type":"Point"}
}