{
  "type": "Feature",
  "properties": {
    "addr:full":"Sylvan Lake AB T4S 1J9",
    "addr:postcode":"t4s 1j9",
    "iso:country":"CA",
    "sg:city":"Sylvan Lake",
    "sg:classifiers":[
        {
            "category":"Health Services",
            "subcategory":"Medical Lab",
            "type":"Services"
        }
    ],
    "sg:phone":"+1 403 887 6272",
    "sg:postcode":"T4S 1J9",
    "sg:province":"AB",
    "wof:name":"Sylvan Lake Denture Clinic Ltd",
    "wof:placetype":"venue"
},
  "geometry": {"coordinates":[-114.095932,52.301418],"type":"Point"}
}