{
  "type": "Feature",
  "properties": {
    "addr:full":"Scarborough ON M1P 4R9",
    "addr:postcode":"m1p 4r9",
    "iso:country":"CA",
    "sg:city":"Scarborough",
    "sg:classifiers":[
        {
            "category":"Wholesale",
            "subcategory":"Non-durable Goods",
            "type":"Manufacturing & Wholesale Goods"
        }
    ],
    "sg:phone":"+1 416 335 1400",
    "sg:postcode":"M1P 4R9",
    "sg:province":"ON",
    "sg:tags":[
        "rubber",
        "sponge"
    ],
    "wof:name":"Cushionfoam Supply CO Ltd",
    "wof:placetype":"venue"
},
  "geometry": {"coordinates":[-79.274033,43.774963],"type":"Point"}
}