{
  "type": "Feature",
  "properties": {
    "addr:full":"601 Dundas St W Whitby ON L1N 2N3",
    "addr:housenumber":"601",
    "addr:postcode":"l1n 2n3",
    "addr:street":"Dundas St W",
    "iso:country":"CA",
    "sg:address":"601 Dundas St W",
    "sg:city":"Whitby",
    "sg:classifiers":[
        {
            "category":"Shopping",
            "type":"Retail Goods"
        }
    ],
    "sg:phone":"+1 905 666 8277",
    "sg:postcode":"L1N 2N3",
    "sg:province":"ON",
    "sg:tags":[
        "pet",
        "food",
        "supply"
    ],
    "wof:name":"Pet Valu",
    "wof:placetype":"venue"
},
  "geometry": {"coordinates":[-78.948662,43.878239],"type":"Point"}
}