{
  "type": "Feature",
  "properties": {
    "addr:full":"5485 Tomken Rd Mississauga ON L4W 3Y3",
    "addr:housenumber":"5485",
    "addr:postcode":"l4w 3y3",
    "addr:street":"Tomken Rd",
    "iso:country":"CA",
    "sg:address":"5485 Tomken Rd",
    "sg:city":"Mississauga",
    "sg:classifiers":[
        {
            "category":"Manufacturing",
            "subcategory":"Printing",
            "type":"Manufacturing & Wholesale Goods"
        }
    ],
    "sg:phone":"+1 905 625 1010",
    "sg:postcode":"L4W 3Y3",
    "sg:province":"ON",
    "sg:tags":[
        "printer"
    ],
    "wof:name":"M M & T Packaging CO",
    "wof:placetype":"venue"
},
  "geometry": {"coordinates":[-79.645149,43.636253],"type":"Point"}
}