{
  "type": "Feature",
  "properties": {
    "addr:full":"52 Ashton Cres Waterloo ON N2L 1P9",
    "addr:housenumber":"52",
    "addr:postcode":"n2l 1p9",
    "addr:street":"Ashton Cres",
    "iso:country":"CA",
    "sg:address":"52 Ashton Cres",
    "sg:city":"Waterloo",
    "sg:classifiers":[
        {
            "category":"Professional",
            "subcategory":"Art Services",
            "type":"Services"
        }
    ],
    "sg:phone":"+1 519 883 8797",
    "sg:postcode":"N2L 1P9",
    "sg:province":"ON",
    "sg:tags":[
        "illustrator"
    ],
    "wof:name":"Ian Beveridge Illustration",
    "wof:placetype":"venue"
},
  "geometry": {"coordinates":[-80.5382232666,43.4555549622],"type":"Point"}
}