{
  "type": "Feature",
  "properties": {
    "addr:full":"Laval QC H7P 1V8",
    "addr:postcode":"h7p 1v8",
    "iso:country":"CA",
    "sg:city":"Laval",
    "sg:classifiers":[
        {
            "category":"Personal",
            "subcategory":"Barber",
            "type":"Services"
        }
    ],
    "sg:phone":"+1 450 625 9250",
    "sg:postcode":"H7P 1V8",
    "sg:province":"QC",
    "wof:name":"Salon Tony",
    "wof:placetype":"venue"
},
  "geometry": {"coordinates":[-73.81266021730001,45.5761299133],"type":"Point"}
}