{
  "type": "Feature",
  "properties": {
    "iso:country":"CA",
    "sg:address":"551 Boul Samson",
    "sg:city":"Laval",
    "sg:classifiers":[
        {
            "category":"Recreation",
            "type":"Entertainment"
        }
    ],
    "sg:phone":"+1 450 689 7011",
    "sg:postcode":"H7X 1J5",
    "sg:province":"QC",
    "sg:tags":[
        "martial",
        "arts",
        "instruction"
    ],
    "wof:name":"Karate Sportif Ste-Dorothee",
    "wof:placetype":"venue"
},
  "geometry": {"coordinates":[-73.8114852905,45.5267181396],"type":"Point"}
}