{
  "type": "Feature",
  "properties": {
    "addr:full":"117 Boul Gerard-D.-Levesque O Paspebiac QC G0C 2K0",
    "addr:housenumber":"117",
    "addr:postcode":"g0c 2k0",
    "addr:street":"Boul Gerard-D.-Levesque O Paspebiac",
    "iso:country":"CA",
    "sg:address":"117 Boul Gerard-D.-Levesque O",
    "sg:city":"Paspebiac",
    "sg:classifiers":[
        {
            "category":"Shopping",
            "subcategory":"Department Store",
            "type":"Retail Goods"
        }
    ],
    "sg:phone":"+1 418 752 5512",
    "sg:postcode":"G0C 2K0",
    "sg:province":"QC",
    "wof:name":"Saan Stores Ltd",
    "wof:placetype":"venue"
},
  "geometry": {"coordinates":[-65.23716,48.030605],"type":"Point"}
}