{
  "type": "Feature",
  "properties": {
    "addr:full":"625 Av Marshall Dorval QC H9P 1E1",
    "addr:housenumber":"625",
    "addr:postcode":"h9p 1e1",
    "addr:street":"Av Marshall",
    "iso:country":"CA",
    "sg:address":"625 Av Marshall",
    "sg:city":"Dorval",
    "sg:classifiers":[
        {
            "category":"Retail",
            "subcategory":"Auto Repair",
            "type":"Services"
        }
    ],
    "sg:phone":"+1 514 828 0866",
    "sg:postcode":"H9P 1E1",
    "sg:province":"QC",
    "sg:tags":[
        "repairing",
        "automobile"
    ],
    "wof:name":"Carosserie Marshall",
    "wof:placetype":"venue"
},
  "geometry": {"coordinates":[-73.73606100000001,45.450657],"type":"Point"}
}