{
  "type": "Feature",
  "properties": {
    "addr:full":"208 10th St Hanover ON N4N 1N7",
    "addr:housenumber":"208",
    "addr:postcode":"n4n 1n7",
    "addr:street":"10Th St",
    "iso:country":"CA",
    "sg:address":"208 10th St",
    "sg:city":"Hanover",
    "sg:classifiers":[
        {
            "category":"Real Estate",
            "subcategory":"Real Estate Agent",
            "type":"Services"
        }
    ],
    "sg:phone":"+1 519 364 3711",
    "sg:postcode":"N4N 1N7",
    "sg:province":"ON",
    "wof:name":"Wilfred Mc Intee & CO Ltd",
    "wof:placetype":"venue"
},
  "geometry": {"coordinates":[-81.0313796997,44.1517181396],"type":"Point"}
}