{
  "type": "Feature",
  "properties": {
    "addr:full":"Toronto ON M5V 3H3",
    "addr:postcode":"m5v 3h3",
    "iso:country":"CA",
    "sg:city":"Toronto",
    "sg:classifiers":[
        {
            "category":"Communications",
            "subcategory":"Film & Video Production",
            "type":"Services"
        }
    ],
    "sg:phone":"+1 416 979 7678",
    "sg:postcode":"M5V 3H3",
    "sg:province":"ON",
    "sg:tags":[
        "taping"
    ],
    "wof:name":"Creative Post",
    "wof:placetype":"venue"
},
  "geometry": {"coordinates":[-79.39801,43.641769],"type":"Point"}
}