{
  "type": "Feature",
  "properties": {
    "addr:full":"26 Green Acres Grand Bend ON N0M 1T0",
    "addr:housenumber":"26",
    "addr:postcode":"n0m 1t0",
    "addr:street":"Green Acres",
    "iso:country":"CA",
    "sg:address":"26 Green Acres",
    "sg:city":"Grand Bend",
    "sg:classifiers":[
        {
            "category":"Home & Garden",
            "subcategory":"Building Materials",
            "type":"Retail Goods"
        }
    ],
    "sg:phone":"+1 519 238 6773",
    "sg:postcode":"N0M 1T0",
    "sg:province":"ON",
    "sg:tags":[
        "windows",
        "general",
        "contractor"
    ],
    "wof:name":"Lovie Construction Ltd",
    "wof:placetype":"venue"
},
  "geometry": {"coordinates":[-81.75788879389999,43.3073730469],"type":"Point"}
}