{
  "type": "Feature",
  "properties": {
    "addr:full":"56 Hess St S Hamilton ON L8P 3N3",
    "addr:housenumber":"56",
    "addr:postcode":"l8p 3n3",
    "addr:street":"Hess St S",
    "iso:country":"CA",
    "sg:address":"56 Hess St S",
    "sg:city":"Hamilton",
    "sg:classifiers":[
        {
            "category":"Restaurant",
            "type":"Food & Drink"
        }
    ],
    "sg:phone":"+1 905 540 8888",
    "sg:postcode":"L8P 3N3",
    "sg:province":"ON",
    "wof:name":"Doors Pub & Pizzeria",
    "wof:placetype":"venue"
},
  "geometry": {"coordinates":[-79.878349,43.25724],"type":"Point"}
}