{
  "type": "Feature",
  "properties": {
    "addr:full":"28 Rue Saint-Joseph Maskinonge QC J0K 1N0",
    "addr:housenumber":"28",
    "addr:postcode":"j0k 1n0",
    "addr:street":"Rue Saint-Joseph",
    "iso:country":"CA",
    "sg:address":"28 Rue Saint-Joseph",
    "sg:city":"Maskinonge",
    "sg:classifiers":[
        {
            "category":"Education",
            "subcategory":"School",
            "type":"Public Place"
        }
    ],
    "sg:phone":"+1 819 227 2293",
    "sg:postcode":"J0K 1N0",
    "sg:province":"QC",
    "wof:name":"Ecole Marie-Immaculee",
    "wof:placetype":"venue"
},
  "geometry": {"coordinates":[-73.01501500000001,46.225891],"type":"Point"}
}