{
  "type": "Feature",
  "properties": {
    "addr:full":"Ottawa ON K2P 1X3",
    "addr:postcode":"k2p 1x3",
    "iso:country":"CA",
    "sg:city":"Ottawa",
    "sg:classifiers":[
        {
            "category":"Health Services",
            "subcategory":"Optometrist",
            "type":"Services"
        }
    ],
    "sg:phone":"+1 613 235 1125",
    "sg:postcode":"K2P 1X3",
    "sg:province":"ON",
    "wof:name":"Feeley, Helen OD",
    "wof:placetype":"venue"
},
  "geometry": {"coordinates":[-75.6970367432,45.4163665771],"type":"Point"}
}