{
  "type": "Feature",
  "properties": {
    "addr:full":"1888 Lockyer Rd Roberts Creek BC V0N 2W1",
    "addr:postcode":"1888;v0n 2w1",
    "addr:street":"Lockyer Rd",
    "iso:country":"CA",
    "sg:address":"1888 Lockyer Rd",
    "sg:city":"Roberts Creek",
    "sg:classifiers":[
        {
            "category":"Health Services",
            "subcategory":"Health Practitioner",
            "type":"Services"
        }
    ],
    "sg:phone":"+1 604 885 0648",
    "sg:postcode":"V0N 2W1",
    "sg:province":"BC",
    "sg:tags":[
        "midwife"
    ],
    "wof:name":"St Leger, Anne-Marie",
    "wof:placetype":"venue"
},
  "geometry": {"coordinates":[-123.606461,49.413261],"type":"Point"}
}