{
  "type": "Feature",
  "properties": {
    "addr:full":"1180 20 St SE Salmon Arm BC V1E 2J4",
    "addr:housenumber":"1180",
    "addr:postcode":"v1e 2j4",
    "addr:street":"20 St Se",
    "iso:country":"CA",
    "sg:address":"1180 20 St SE",
    "sg:city":"Salmon Arm",
    "sg:classifiers":[
        {
            "category":"Education",
            "subcategory":"School",
            "type":"Public Place"
        }
    ],
    "sg:phone":"+1 250 832 7195",
    "sg:postcode":"V1E 2J4",
    "sg:province":"BC",
    "wof:name":"Hillcrest School",
    "wof:placetype":"venue"
},
  "geometry": {"coordinates":[-119.26200900000001,50.692017],"type":"Point"}
}