{
  "type": "Feature",
  "properties": {
    "addr:full":"2481 Rue Guenette Saint-Laurent QC H4R 2E9",
    "addr:housenumber":"2481",
    "addr:postcode":"h4r 2e9",
    "addr:street":"Rue Guenette",
    "iso:country":"CA",
    "sg:address":"2481 Rue Guenette",
    "sg:city":"Saint-Laurent",
    "sg:classifiers":[
        {
            "category":"Wholesale",
            "subcategory":"Electrical",
            "type":"Manufacturing & Wholesale Goods"
        }
    ],
    "sg:phone":"+1 514 337 8247",
    "sg:postcode":"H4R 2E9",
    "sg:province":"QC",
    "sg:tags":[
        "control",
        "security",
        "system"
    ],
    "wof:name":"Universal",
    "wof:placetype":"venue"
},
  "geometry": {"coordinates":[-73.72940800000001,45.500885],"type":"Point"}
}