{
  "type": "Feature",
  "properties": {
    "iso:country":"CA",
    "sg:address":"336 Av Gamache",
    "sg:city":"Sept-Iles",
    "sg:classifiers":[
        {
            "category":"Personal",
            "subcategory":"Tanning Parlor",
            "type":"Services"
        }
    ],
    "sg:phone":"+1 418 962 3319",
    "sg:postcode":"G4R 2H7",
    "sg:province":"QC",
    "sg:tags":[
        "salon"
    ],
    "wof:name":"Miami Bronzage",
    "wof:placetype":"venue"
},
  "geometry": {"coordinates":[-66.3765411377,50.206817627],"type":"Point"}
}