{
  "type": "Feature",
  "properties": {
    "addr:full":"11451 95 St NW Edmonton AB T5G 1L3",
    "addr:housenumber":"11451",
    "addr:postcode":"t5g 1l3",
    "addr:street":"95 St Nw",
    "iso:country":"CA",
    "sg:address":"11451 95 St NW",
    "sg:city":"Edmonton",
    "sg:classifiers":[
        {
            "category":"Personal",
            "subcategory":"Beauty Salon",
            "type":"Services"
        }
    ],
    "sg:phone":"+1 780 477 1132",
    "sg:postcode":"T5G 1L3",
    "sg:province":"AB",
    "wof:name":"Stefa's Beauty Shop",
    "wof:placetype":"venue"
},
  "geometry": {"coordinates":[-113.486946,53.565033],"type":"Point"}
}