{
  "type": "Feature",
  "properties": {
    "addr:full":"14 Adelaide St W Toronto ON M5H 1L6",
    "addr:housenumber":"14",
    "addr:postcode":"m5h 1l6",
    "addr:street":"Adelaide St W",
    "iso:country":"CA",
    "sg:address":"14 Adelaide St W",
    "sg:city":"Toronto",
    "sg:classifiers":[
        {
            "category":"Manufacturing",
            "subcategory":"Printing",
            "type":"Manufacturing & Wholesale Goods"
        }
    ],
    "sg:phone":"+1 416 203 7764",
    "sg:postcode":"M5H 1L6",
    "sg:province":"ON",
    "sg:tags":[
        "publisher"
    ],
    "wof:name":"Firefighter Magazine",
    "wof:placetype":"venue"
},
  "geometry": {"coordinates":[-79.378815,43.650463],"type":"Point"}
}