{
  "type": "Feature",
  "properties": {
    "iso:country":"CA",
    "sg:city":"Ottawa",
    "sg:classifiers":[
        {
            "category":"Personal",
            "subcategory":"Beauty Salon",
            "type":"Services"
        }
    ],
    "sg:phone":"+1 613 733 1531",
    "sg:postcode":"K1G 1A4",
    "sg:province":"ON",
    "wof:name":"Elmvale Beauty Salon",
    "wof:placetype":"venue"
},
  "geometry": {"coordinates":[-75.624046,45.400059],"type":"Point"}
}