{
  "type": "Feature",
  "properties": {
    "addr:full":"2095 Wyandotte St E Windsor ON N8Y 4Z3",
    "addr:housenumber":"2095",
    "addr:postcode":"n8y 4z3",
    "addr:street":"Wyandotte St E",
    "iso:country":"CA",
    "sg:address":"2095 Wyandotte St E",
    "sg:city":"Windsor",
    "sg:classifiers":[
        {
            "category":"Health Services",
            "subcategory":"Health Practitioner",
            "type":"Services"
        }
    ],
    "sg:phone":"+1 519 258 1035",
    "sg:postcode":"N8Y 4Z3",
    "sg:province":"ON",
    "sg:tags":[
        "psychologist"
    ],
    "wof:name":"Mc Grory, Jay J",
    "wof:placetype":"venue"
},
  "geometry": {"coordinates":[-83.011101,42.323315],"type":"Point"}
}