{
  "type": "Feature",
  "properties": {
    "addr:full":"800 Rue Sainte-Catherine E Montreal QC H2L 2E2",
    "addr:housenumber":"800",
    "addr:postcode":"h2l 2e2",
    "addr:street":"Rue Sainte-Catherine E",
    "iso:country":"CA",
    "sg:address":"800 Rue Sainte-Catherine E",
    "sg:city":"Montreal",
    "sg:classifiers":[
        {
            "category":"Restaurant",
            "type":"Food & Drink"
        }
    ],
    "sg:phone":"+1 514 287 0040",
    "sg:postcode":"H2L 2E2",
    "sg:province":"QC",
    "sg:tags":[
        "shop",
        "coffee"
    ],
    "wof:name":"Cafe Vienne",
    "wof:placetype":"venue"
},
  "geometry": {"coordinates":[-73.5587768555,45.5154838562],"type":"Point"}
}