{
  "type": "Feature",
  "properties": {
    "addr:full":"5475 Rue Thibault Laval QC H7K 2Z1",
    "addr:housenumber":"5475",
    "addr:postcode":"qc h7k 2z1",
    "addr:street":"Rue Thibault",
    "iso:country":"CA",
    "sg:address":"5475 Rue Thibault",
    "sg:city":"Laval",
    "sg:classifiers":[
        {
            "category":"Professional",
            "subcategory":"Computer Services",
            "type":"Services"
        }
    ],
    "sg:phone":"+1 450 963 0012",
    "sg:postcode":"H7K 2Z1",
    "sg:province":"QC",
    "sg:tags":[
        "repair",
        "dealer",
        "equipment"
    ],
    "wof:name":"Etc Solutions Informatiques",
    "wof:placetype":"venue"
},
  "geometry": {"coordinates":[-73.7558441162,45.6207084656],"type":"Point"}
}