{
  "type": "Feature",
  "properties": {
    "addr:full":"Toronto ON M6K 3C3",
    "addr:postcode":"m6k 3c3",
    "iso:country":"CA",
    "sg:city":"Toronto",
    "sg:classifiers":[
        {
            "category":"Education",
            "subcategory":"Special Training",
            "type":"Public Place"
        }
    ],
    "sg:phone":"+1 416 260 6451",
    "sg:postcode":"M6K 3C3",
    "sg:province":"ON",
    "sg:tags":[
        "instruction",
        "music"
    ],
    "wof:name":"Canadian Bureau For Music",
    "wof:placetype":"venue"
},
  "geometry": {"coordinates":[-79.3853302002,43.648563385],"type":"Point"}
}