{
  "type": "Feature",
  "properties": {
    "addr:full":"276 Macpherson Ave Toronto ON M4V 1A3",
    "addr:housenumber":"276",
    "addr:postcode":"m4v 1a3",
    "addr:street":"Macpherson Ave",
    "iso:country":"CA",
    "sg:address":"276 Macpherson Ave",
    "sg:city":"Toronto",
    "sg:classifiers":[
        {
            "category":"Utilities",
            "subcategory":"Fuel Oil & Lpg",
            "type":"Services"
        }
    ],
    "sg:phone":"+1 416 920 3838",
    "sg:postcode":"M4V 1A3",
    "sg:province":"ON",
    "sg:tags":[
        "firewood"
    ],
    "wof:name":"AAA University Firewood",
    "wof:placetype":"venue"
},
  "geometry": {"coordinates":[-79.40097799999999,43.677429],"type":"Point"}
}