{
  "type": "Feature",
  "properties": {
    "addr:full":"4 Rue Lachapelle Lac-Sainte-Marie QC J0X 1Z0",
    "addr:housenumber":"4",
    "addr:postcode":"j0x 1z0",
    "addr:street":"Rue Lachapelle",
    "iso:country":"CA",
    "sg:address":"4 Rue Lachapelle",
    "sg:city":"Lac-Sainte-Marie",
    "sg:classifiers":[
        {
            "category":"Building & Trades",
            "subcategory":"Construction",
            "type":"Services"
        }
    ],
    "sg:phone":"+1 819 467 2485",
    "sg:postcode":"J0X 1Z0",
    "sg:province":"QC",
    "sg:tags":[
        "excavating",
        "contractor"
    ],
    "wof:name":"Henri Marcel Excavation",
    "wof:placetype":"venue"
},
  "geometry": {"coordinates":[-75.94598388670001,45.9518623352],"type":"Point"}
}