{
  "type": "Feature",
  "properties": {
    "addr:full":"10 Pearson Pl Grand Bank NL A0E 1W0",
    "addr:housenumber":"10",
    "addr:postcode":"a0e 1w0",
    "addr:street":"Pearson Pl",
    "iso:country":"CA",
    "sg:address":"10 Pearson Pl",
    "sg:city":"Grand Bank",
    "sg:classifiers":[
        {
            "category":"Personal",
            "subcategory":"Beauty Salon",
            "type":"Services"
        }
    ],
    "sg:phone":"+1 709 832 1664",
    "sg:postcode":"A0E 1W0",
    "sg:province":"NL",
    "wof:name":"Lois' Hair Techniques-Sun Room",
    "wof:placetype":"venue"
},
  "geometry": {"coordinates":[-55.7579421997,47.0944137573],"type":"Point"}
}