{
  "type": "Feature",
  "properties": {
    "addr:full":"Lorne Ave S & Cartwright St Saskatoon SK S7L 3J8",
    "addr:postcode":"s7l 3j8",
    "addr:street":"Lorne Ave;Cartwright St",
    "iso:country":"CA",
    "sg:address":"Lorne Ave S & Cartwright St",
    "sg:city":"Saskatoon",
    "sg:classifiers":[
        {
            "category":"Recreation",
            "type":"Entertainment"
        }
    ],
    "sg:phone":"+1 306 933 4080",
    "sg:postcode":"S7L 3J8",
    "sg:province":"SK",
    "sg:tags":[
        "skating",
        "rink"
    ],
    "wof:name":"Schroh Arenas Ltd",
    "wof:placetype":"venue"
},
  "geometry": {"coordinates":[-106.670471191,52.1123085022],"type":"Point"}
}