{
  "type": "Feature",
  "properties": {
    "addr:full":"91 Kingsway Vancouver BC V5T 3J1",
    "addr:housenumber":"91",
    "addr:postcode":"v5t 3j1",
    "addr:street":"Kingsway",
    "iso:country":"CA",
    "sg:address":"91 Kingsway",
    "sg:city":"Vancouver",
    "sg:classifiers":[
        {
            "category":"Professional",
            "subcategory":"Accounting & Tax Preparation",
            "type":"Services"
        }
    ],
    "sg:phone":"+1 604 872 7744",
    "sg:postcode":"V5T 3J1",
    "sg:province":"BC",
    "sg:tags":[
        "consultant"
    ],
    "wof:name":"Promptax Services",
    "wof:placetype":"venue"
},
  "geometry": {"coordinates":[-123.09948,49.263126],"type":"Point"}
}