{
  "type": "Feature",
  "properties": {
    "iso:country":"CA",
    "sg:address":"1430 Rue DE Champigny # B",
    "sg:city":"Montreal",
    "sg:classifiers":[
        {
            "category":"Professional",
            "subcategory":"Accounting & Tax Preparation",
            "type":"Services"
        }
    ],
    "sg:phone":"+1 514 761 6012",
    "sg:postcode":"H4E 1L8",
    "sg:province":"QC",
    "sg:tags":[
        "return",
        "filing"
    ],
    "wof:name":"Impot & Administration Ec",
    "wof:placetype":"venue"
},
  "geometry": {"coordinates":[-73.58265686039999,45.4606208801],"type":"Point"}
}