{
  "type": "Feature",
  "properties": {
    "addr:full":"246 Rue Principale E Sainte-Euphemie QC G0R 2Z0",
    "addr:housenumber":"246",
    "addr:postcode":"g0r 2z0",
    "addr:street":"Rue Principale E Sainte-Euphemie",
    "iso:country":"CA",
    "sg:address":"246 Rue Principale E",
    "sg:city":"Sainte-Euphemie",
    "sg:classifiers":[
        {
            "category":"Food & Beverages",
            "subcategory":"Groceries & Convenience Stores",
            "type":"Retail Goods"
        }
    ],
    "sg:phone":"+1 418 469 3039",
    "sg:postcode":"G0R 2Z0",
    "sg:province":"QC",
    "sg:tags":[
        "grocer"
    ],
    "wof:name":"Epicerie Andre Chabot",
    "wof:placetype":"venue"
},
  "geometry": {"coordinates":[-70.456154,46.780643],"type":"Point"}
}