{
  "type": "Feature",
  "properties": {
    "addr:full":"19069 Highway 17 Oxdrift ON P0V 2J0",
    "addr:housenumber":"19069",
    "addr:postcode":"p0v 2j0",
    "addr:street":"Highway 17",
    "iso:country":"CA",
    "sg:address":"19069 Highway 17",
    "sg:city":"Oxdrift",
    "sg:classifiers":[
        {
            "category":"Building & Trades",
            "subcategory":"Landscaping Services",
            "type":"Services"
        }
    ],
    "sg:phone":"+1 807 937 2522",
    "sg:postcode":"P0V 2J0",
    "sg:province":"ON",
    "sg:tags":[
        "tree"
    ],
    "wof:name":"Caren Clearing & Spraying Inc",
    "wof:placetype":"venue"
},
  "geometry": {"coordinates":[-93.016396,49.80135],"type":"Point"}
}