{
  "type": "Feature",
  "properties": {
    "addr:full":"455 Silvercreek Pky N Guelph ON N1H 8M7",
    "addr:housenumber":"455",
    "addr:postcode":"n1h 8m7",
    "addr:street":"Silvercreek Pky N",
    "iso:country":"CA",
    "sg:address":"455 Silvercreek Pky N",
    "sg:city":"Guelph",
    "sg:classifiers":[
        {
            "category":"Building & Trades",
            "subcategory":"Construction",
            "type":"Services"
        }
    ],
    "sg:phone":"+1 519 763 2960",
    "sg:postcode":"N1H 8M7",
    "sg:province":"ON",
    "sg:tags":[
        "railroad",
        "contractor"
    ],
    "wof:name":"Pacific Northern Rail Contrs",
    "wof:placetype":"venue"
},
  "geometry": {"coordinates":[-80.29467,43.550438],"type":"Point"}
}