{
  "type": "Feature",
  "properties": {
    "addr:full":"Verner ON P0H 2M0",
    "addr:postcode":"p0h 2m0",
    "addr:street":"Verner",
    "iso:country":"CA",
    "sg:city":"Verner",
    "sg:classifiers":[
        {
            "category":"Insurance",
            "subcategory":"Insurance Agent",
            "type":"Services"
        }
    ],
    "sg:phone":"+1 705 594 9555",
    "sg:postcode":"P0H 2M0",
    "sg:province":"ON",
    "sg:tags":[
        "investment"
    ],
    "wof:name":"Primerica Financial Svc",
    "wof:placetype":"venue"
},
  "geometry": {"coordinates":[-80.126915,46.411175],"type":"Point"}
}