{
  "type": "Feature",
  "properties": {
    "iso:country":"CA",
    "sg:address":"895 Boul Du Seminaire N # 400",
    "sg:city":"Saint-Jean-Sur-Richelieu",
    "sg:classifiers":[
        {
            "category":"Banks & Credit Unions",
            "subcategory":"Investment Brokerage",
            "type":"Services"
        }
    ],
    "sg:phone":"+1 450 359 0555",
    "sg:postcode":"J3A 1J2",
    "sg:province":"QC",
    "sg:tags":[
        "consultant",
        "planning",
        "financial"
    ],
    "wof:name":"Nationale Banque Financiere",
    "wof:placetype":"venue"
},
  "geometry": {"coordinates":[-73.2673110962,45.3310813904],"type":"Point"}
}