{
  "type": "Feature",
  "properties": {
    "addr:full":"4029 Gordon Head Rd Victoria BC V8N 3X7",
    "addr:housenumber":"4029",
    "addr:postcode":"v8n 3x7",
    "addr:street":"Gordon Head Rd",
    "iso:country":"CA",
    "sg:address":"4029 Gordon Head Rd",
    "sg:city":"Victoria",
    "sg:classifiers":[
        {
            "category":"Retail",
            "subcategory":"Laundry & Dry Cleaning",
            "type":"Services"
        }
    ],
    "sg:phone":"+1 250 477 5770",
    "sg:postcode":"V8N 3X7",
    "sg:province":"BC",
    "sg:tags":[
        "venetian",
        "cleaners",
        "blind"
    ],
    "wof:name":"All So Brite Blind Cleaning",
    "wof:placetype":"venue"
},
  "geometry": {"coordinates":[-123.364517212,48.428314209],"type":"Point"}
}