{
  "type": "Feature",
  "properties": {
    "addr:full":"232 Hay Ave St Andrews MB R1A 3M7",
    "addr:housenumber":"232",
    "addr:postcode":"r1a 3m7",
    "addr:street":"Hay Ave",
    "iso:country":"CA",
    "sg:address":"232 Hay Ave",
    "sg:city":"St Andrews",
    "sg:classifiers":[
        {
            "category":"Health Services",
            "subcategory":"Health Practitioner",
            "type":"Services"
        }
    ],
    "sg:phone":"+1 204 757 2587",
    "sg:postcode":"R1A 3M7",
    "sg:province":"MB",
    "sg:tags":[
        "nurse",
        "registry"
    ],
    "wof:name":"Excellent Health Care Svc",
    "wof:placetype":"venue"
},
  "geometry": {"coordinates":[-96.993668,50.084965],"type":"Point"}
}