{
  "type": "Feature",
  "properties": {
    "addr:full":"169 Av Bedbrook Montreal-Ouest QC H4X 1R7",
    "addr:postcode":"h4x 1r7",
    "addr:street":"169 Av Bedbrook Montreal-Ouest",
    "iso:country":"CA",
    "sg:address":"169 Av Bedbrook",
    "sg:city":"Montreal-Ouest",
    "sg:classifiers":[
        {
            "category":"Wholesale",
            "subcategory":"Durable Goods & Equipment",
            "type":"Manufacturing & Wholesale Goods"
        }
    ],
    "sg:phone":"+1 514 483 5099",
    "sg:postcode":"H4X 1R7",
    "sg:province":"QC",
    "sg:tags":[
        "importer"
    ],
    "wof:name":"Christoffersen Import",
    "wof:placetype":"venue"
},
  "geometry": {"coordinates":[-73.65108499999999,45.452068],"type":"Point"}
}