{
  "type": "Feature",
  "properties": {
    "addr:full":"9 Bruce St London ON N6C 1G3",
    "addr:housenumber":"9",
    "addr:postcode":"n6c 1g3",
    "addr:street":"Bruce St",
    "iso:country":"CA",
    "sg:address":"9 Bruce St",
    "sg:city":"London",
    "sg:classifiers":[
        {
            "category":"Wholesale",
            "subcategory":"Machinery & Supplies",
            "type":"Manufacturing & Wholesale Goods"
        }
    ],
    "sg:phone":"+1 519 432 1330",
    "sg:postcode":"N6C 1G3",
    "sg:province":"ON",
    "sg:tags":[
        "equipment",
        "conveyor",
        "business",
        "conveying"
    ],
    "wof:name":"Ftd Maintenance",
    "wof:placetype":"venue"
},
  "geometry": {"coordinates":[-81.2614440918,42.9716377258],"type":"Point"}
}