{
  "type": "Feature",
  "properties": {
    "addr:full":"139 Water St Pictou NS B0K 1H0",
    "addr:housenumber":"139",
    "addr:postcode":"b0k 1h0",
    "addr:street":"Water St",
    "iso:country":"CA",
    "sg:address":"139 Water St",
    "sg:city":"Pictou",
    "sg:classifiers":[
        {
            "category":"Health Services",
            "subcategory":"Doctor",
            "type":"Services"
        }
    ],
    "sg:phone":"+1 902 485 5377",
    "sg:postcode":"B0K 1H0",
    "sg:province":"NS",
    "sg:tags":[
        "physician",
        "surgeon"
    ],
    "wof:name":"Mac Cara, Shirley MD",
    "wof:placetype":"venue"
},
  "geometry": {"coordinates":[-62.7113990784,45.6761894226],"type":"Point"}
}