{
  "type": "Feature",
  "properties": {
    "addr:full":"117 John St N Hamilton ON L8R 1H7",
    "addr:housenumber":"117",
    "addr:postcode":"l8r 1h7",
    "addr:street":"John St N",
    "iso:country":"CA",
    "sg:address":"117 John St N",
    "sg:city":"Hamilton",
    "sg:classifiers":[
        {
            "category":"Retail",
            "subcategory":"Auto Repair",
            "type":"Services"
        }
    ],
    "sg:phone":"+1 905 528 0714",
    "sg:postcode":"L8R 1H7",
    "sg:province":"ON",
    "sg:tags":[
        "repairing",
        "automobile"
    ],
    "wof:name":"A G Donaldson & Son Auto Svc",
    "wof:placetype":"venue"
},
  "geometry": {"coordinates":[-79.86526499999999,43.259224],"type":"Point"}
}