{
  "type": "Feature",
  "properties": {
    "addr:full":"4316 Stage Coach Rd Sydenham ON K0H 2T0",
    "addr:housenumber":"4316",
    "addr:postcode":"k0h 2t0",
    "addr:street":"Stage Coach Rd",
    "iso:country":"CA",
    "sg:address":"4316 Stage Coach Rd",
    "sg:city":"Sydenham",
    "sg:classifiers":[
        {
            "category":"Professional",
            "subcategory":"Lawyer & Legal Services",
            "type":"Services"
        }
    ],
    "sg:phone":"+1 613 376 3397",
    "sg:postcode":"K0H 2T0",
    "sg:province":"ON",
    "sg:tags":[
        "attorney"
    ],
    "wof:name":"Glassco, John M",
    "wof:placetype":"venue"
},
  "geometry": {"coordinates":[-76.5965805054,44.4086112976],"type":"Point"}
}