{
  "type": "Feature",
  "properties": {
    "addr:full":"106 Bathurst St Toronto ON M5V 3N7",
    "addr:housenumber":"106",
    "addr:postcode":"m5v 3n7",
    "addr:street":"Bathurst St",
    "iso:country":"CA",
    "sg:address":"106 Bathurst St",
    "sg:city":"Toronto",
    "sg:classifiers":[
        {
            "category":"Shopping",
            "subcategory":"Jewelry",
            "type":"Retail Goods"
        }
    ],
    "sg:phone":"+1 416 367 0844",
    "sg:postcode":"M5V 3N7",
    "sg:province":"ON",
    "sg:tags":[
        "diamond"
    ],
    "wof:name":"Artam Diamonds Intl Inc",
    "wof:placetype":"venue"
},
  "geometry": {"coordinates":[-79.40308400000001,43.644402],"type":"Point"}
}