{
  "type": "Feature",
  "properties": {
    "addr:full":"37 Capital Dr Nepean ON K2G 0E7",
    "addr:housenumber":"37",
    "addr:postcode":"k2g 0e7",
    "addr:street":"Capital Dr",
    "iso:country":"CA",
    "sg:address":"37 Capital Dr",
    "sg:city":"Nepean",
    "sg:classifiers":[
        {
            "category":"Building & Trades",
            "subcategory":"Construction",
            "type":"Services"
        }
    ],
    "sg:phone":"+1 613 226 6669",
    "sg:postcode":"K2G 0E7",
    "sg:province":"ON",
    "sg:tags":[
        "insulation",
        "heat",
        "material"
    ],
    "wof:name":"Insulation Store",
    "wof:placetype":"venue"
},
  "geometry": {"coordinates":[-75.7194595337,45.3231391907],"type":"Point"}
}