{
  "type": "Feature",
  "properties": {
    "addr:full":"845 Eglinton Ave E East York ON M4G 4G9",
    "addr:housenumber":"845",
    "addr:postcode":"m4g 4g9",
    "addr:street":"Eglinton Ave E",
    "iso:country":"CA",
    "sg:address":"845 Eglinton Ave E",
    "sg:city":"East York",
    "sg:classifiers":[
        {
            "category":"Home & Garden",
            "subcategory":"Carpets & Floor Coverings",
            "type":"Retail Goods"
        }
    ],
    "sg:phone":"+1 416 467 7072",
    "sg:postcode":"M4G 4G9",
    "sg:province":"ON",
    "sg:tags":[
        "dealer",
        "rug"
    ],
    "wof:name":"Giant Carpet",
    "wof:placetype":"venue"
},
  "geometry": {"coordinates":[-79.362663269,43.7139015198],"type":"Point"}
}