{
  "type": "Feature",
  "properties": {
    "addr:full":"Blainville QC J7C 2K4",
    "addr:postcode":"j7c 2k4",
    "iso:country":"CA",
    "sg:city":"Blainville",
    "sg:classifiers":[
        {
            "category":"Sports & Exercise",
            "subcategory":"Gym",
            "type":"Entertainment"
        }
    ],
    "sg:phone":"+1 450 433 3355",
    "sg:postcode":"J7C 2K4",
    "sg:province":"QC",
    "sg:tags":[
        "club",
        "health",
        "studio",
        "gymnasium"
    ],
    "wof:name":"Nautilus Plus Inc",
    "wof:placetype":"venue"
},
  "geometry": {"coordinates":[-73.8700256348,45.6668014526],"type":"Point"}
}