{
  "type": "Feature",
  "properties": {
    "addr:full":"Pointe-Claire QC H9S 4L1",
    "addr:postcode":"h9s 4l1",
    "iso:country":"CA",
    "sg:city":"Pointe-Claire",
    "sg:classifiers":[
        {
            "category":"Banks & Credit Unions",
            "subcategory":"Financial Services",
            "type":"Services"
        }
    ],
    "sg:phone":"+1 514 426 4994",
    "sg:postcode":"H9S 4L1",
    "sg:province":"QC",
    "sg:tags":[
        "bankruptcy",
        "trustee"
    ],
    "wof:name":"Aberback Lapointe & Associes",
    "wof:placetype":"venue"
},
  "geometry": {"coordinates":[-73.824348,45.429428],"type":"Point"}
}