{
  "type": "Feature",
  "properties": {
    "addr:full":"1177 Robson St Vancouver BC V6E 1B5",
    "addr:housenumber":"1177",
    "addr:postcode":"v6e 1b5",
    "addr:street":"Robson St",
    "iso:country":"CA",
    "sg:address":"1177 Robson St",
    "sg:city":"Vancouver",
    "sg:classifiers":[
        {
            "category":"Shopping",
            "subcategory":"Clothing, Apparel, & Fashions",
            "type":"Retail Goods"
        }
    ],
    "sg:phone":"+1 604 683 7207",
    "sg:postcode":"V6E 1B5",
    "sg:province":"BC",
    "sg:tags":[
        "accessory"
    ],
    "wof:name":"Claire's Boutiques",
    "wof:placetype":"venue"
},
  "geometry": {"coordinates":[-123.126235962,49.2857093811],"type":"Point"}
}