{
  "type": "Feature",
  "properties": {
    "addr:full":"Radisson QC J0Y 2X0",
    "addr:postcode":"j0y 2x0",
    "iso:country":"CA",
    "sg:city":"Radisson",
    "sg:classifiers":[
        {
            "category":"Retail",
            "subcategory":"Auto Repair",
            "type":"Services"
        }
    ],
    "sg:phone":"+1 819 638 7808",
    "sg:postcode":"J0Y 2X0",
    "sg:province":"QC",
    "sg:tags":[
        "repairing",
        "automobile"
    ],
    "wof:name":"Service DE Pneus Emj",
    "wof:placetype":"venue"
},
  "geometry": {"coordinates":[-77.6197433472,53.7948608398],"type":"Point"}
}