{
  "type": "Feature",
  "properties": {
    "iso:country":"CA",
    "sg:address":"1015 Boul Du Jardin",
    "sg:city":"Charlesbourg",
    "sg:classifiers":[
        {
            "category":"Home & Garden",
            "subcategory":"Building Materials",
            "type":"Retail Goods"
        }
    ],
    "sg:phone":"+1 418 627 5555",
    "sg:postcode":"G1G 3X4",
    "sg:province":"QC",
    "sg:tags":[
        "glass",
        "window",
        "plate"
    ],
    "wof:name":"Lebeau Vitres D'Autos",
    "wof:placetype":"venue"
},
  "geometry": {"coordinates":[-71.2782745361,46.8714675903],"type":"Point"}
}