{
  "type": "Feature",
  "properties": {
    "addr:full":"5564 Boul Saint-Laurent Montreal QC H2T 1S8",
    "addr:housenumber":"5564",
    "addr:postcode":"h2t 1s8",
    "addr:street":"Boul Saint-Laurent",
    "iso:country":"CA",
    "sg:address":"5564 Boul Saint-Laurent",
    "sg:city":"Montreal",
    "sg:classifiers":[
        {
            "category":"Retail",
            "subcategory":"Repair Shop",
            "type":"Services"
        }
    ],
    "sg:phone":"+1 514 277 1105",
    "sg:postcode":"H2T 1S8",
    "sg:province":"QC",
    "sg:tags":[
        "lock",
        "locksmith"
    ],
    "wof:name":"J Piche & Fils Inc",
    "wof:placetype":"venue"
},
  "geometry": {"coordinates":[-73.5998,45.526085],"type":"Point"}
}