{
  "type": "Feature",
  "properties": {
    "addr:full":"RR 1 Princeton ON N0J 1V0",
    "addr:postcode":"n0j 1v0",
    "addr:street":"Rr 1",
    "iso:country":"CA",
    "sg:address":"RR 1",
    "sg:city":"Princeton",
    "sg:classifiers":[
        {
            "category":"Organizations",
            "subcategory":"Religious Organization",
            "type":"Services"
        }
    ],
    "sg:phone":"+1 519 458 4763",
    "sg:postcode":"N0J 1V0",
    "sg:province":"ON",
    "sg:tags":[
        "church"
    ],
    "wof:name":"Etonia United Church",
    "wof:placetype":"venue"
},
  "geometry": {"coordinates":[-80.52752700000001,43.172009],"type":"Point"}
}