{
  "type": "Feature",
  "properties": {
    "addr:full":"130 Cedar St Cambridge ON N1S 1W4",
    "addr:housenumber":"130",
    "addr:postcode":"n1s 1w4",
    "addr:street":"Cedar St",
    "iso:country":"CA",
    "sg:address":"130 Cedar St",
    "sg:city":"Cambridge",
    "sg:classifiers":[
        {
            "category":"Home & Garden",
            "subcategory":"Building Materials",
            "type":"Retail Goods"
        }
    ],
    "sg:phone":"+1 519 623 3839",
    "sg:postcode":"N1S 1W4",
    "sg:province":"ON",
    "sg:tags":[
        "paint"
    ],
    "wof:name":"Home Hardware Stores",
    "wof:placetype":"venue"
},
  "geometry": {"coordinates":[-80.32828521730001,43.3517990112],"type":"Point"}
}