{
  "type": "Feature",
  "properties": {
    "addr:full":"15130 Rue Ghislaine Mirabel QC J7N 1W7",
    "addr:housenumber":"15130",
    "addr:postcode":"j7n 1w7",
    "addr:street":"Rue Ghislaine",
    "iso:country":"CA",
    "sg:address":"15130 Rue Ghislaine",
    "sg:city":"Mirabel",
    "sg:classifiers":[
        {
            "category":"Restaurant",
            "type":"Food & Drink"
        }
    ],
    "sg:phone":"+1 450 475 6660",
    "sg:postcode":"J7N 1W7",
    "sg:province":"QC",
    "wof:name":"Fritadan",
    "wof:placetype":"venue"
},
  "geometry": {"coordinates":[-73.98090362550001,45.6285476685],"type":"Point"}
}