{
  "type": "Feature",
  "properties": {
    "addr:full":"1285 Woodbine Ave East York ON M4C 4E8",
    "addr:housenumber":"1285",
    "addr:postcode":"m4c 4e8",
    "addr:street":"Woodbine Ave",
    "iso:country":"CA",
    "sg:address":"1285 Woodbine Ave",
    "sg:city":"East York",
    "sg:classifiers":[
        {
            "category":"Retail",
            "subcategory":"Auto Repair",
            "type":"Services"
        }
    ],
    "sg:phone":"+1 416 423 9161",
    "sg:postcode":"M4C 4E8",
    "sg:province":"ON",
    "sg:tags":[
        "repairing",
        "automobile"
    ],
    "wof:name":"Sure Choice Auto Svc Ctr Ltd",
    "wof:placetype":"venue"
},
  "geometry": {"coordinates":[-79.316444,43.694412],"type":"Point"}
}