{
  "type": "Feature",
  "properties": {
    "addr:full":"6258 Rue Garneau Saint-Emile QC G3E 1P6",
    "addr:housenumber":"6258",
    "addr:postcode":"g3e 1p6",
    "addr:street":"Rue Garneau Saint-Emile",
    "iso:country":"CA",
    "sg:address":"6258 Rue Garneau",
    "sg:city":"Saint-Emile",
    "sg:classifiers":[
        {
            "category":"Building & Trades",
            "subcategory":"Electrical",
            "type":"Services"
        }
    ],
    "sg:phone":"+1 418 847 4419",
    "sg:postcode":"G3E 1P6",
    "sg:province":"QC",
    "sg:tags":[
        "electric",
        "contractor"
    ],
    "wof:name":"Entreprises Volt-Maitre Enr",
    "wof:placetype":"venue"
},
  "geometry": {"coordinates":[-71.3442764282,46.8852462769],"type":"Point"}
}