{
  "type": "Feature",
  "properties": {
    "addr:full":"1310 Rue Sainte-Catherine E Montreal QC H2L 2H5",
    "addr:housenumber":"1310",
    "addr:postcode":"h2l 2h5",
    "addr:street":"Rue Sainte-Catherine E",
    "iso:country":"CA",
    "sg:address":"1310 Rue Sainte-Catherine E",
    "sg:city":"Montreal",
    "sg:classifiers":[
        {
            "category":"Restaurant",
            "type":"Food & Drink"
        }
    ],
    "sg:phone":"+1 514 524 6705",
    "sg:postcode":"H2L 2H5",
    "sg:province":"QC",
    "wof:name":"Bato Thai",
    "wof:placetype":"venue"
},
  "geometry": {"coordinates":[-73.555038,45.519409],"type":"Point"}
}