{
  "type": "Feature",
  "properties": {
    "iso:country":"CA",
    "sg:address":"27 Cindy Lee Cres",
    "sg:city":"Orillia",
    "sg:classifiers":[
        {
            "category":"Building & Trades",
            "subcategory":"Construction",
            "type":"Services"
        }
    ],
    "sg:phone":"+1 705 327 1434",
    "sg:postcode":"L3V 7P3",
    "sg:province":"ON",
    "sg:tags":[
        "dry wall",
        "contractor"
    ],
    "wof:name":"Frontier Drywall",
    "wof:placetype":"venue"
},
  "geometry": {"coordinates":[-79.4313735962,44.5941925049],"type":"Point"}
}