{
  "type": "Feature",
  "properties": {
    "addr:full":"63950 Old Yale Rd Hope BC V0X 1L2",
    "addr:housenumber":"63950",
    "addr:postcode":"v0x 1l2",
    "addr:street":"Old Yale Rd",
    "iso:country":"CA",
    "sg:address":"63950 Old Yale Rd",
    "sg:city":"Hope",
    "sg:classifiers":[
        {
            "category":"Travel",
            "subcategory":"Hotels & Motels",
            "type":"Entertainment"
        }
    ],
    "sg:phone":"+1 604 869 5352",
    "sg:postcode":"V0X 1L2",
    "sg:province":"BC",
    "wof:name":"Holiday Motel",
    "wof:placetype":"venue"
},
  "geometry": {"coordinates":[-121.46023599999999,49.359325],"type":"Point"}
}