{
  "type": "Feature",
  "properties": {
    "addr:full":"51 Front St E Strathroy ON N7G 1Y5",
    "addr:housenumber":"51",
    "addr:postcode":"n7g 1y5",
    "addr:street":"Front St E",
    "iso:country":"CA",
    "sg:address":"51 Front St E",
    "sg:city":"Strathroy",
    "sg:classifiers":[
        {
            "category":"Shopping",
            "subcategory":"Clothing, Apparel, & Fashions",
            "type":"Retail Goods"
        }
    ],
    "sg:phone":"+1 519 245 4930",
    "sg:postcode":"N7G 1Y5",
    "sg:province":"ON",
    "wof:name":"Winston Fashions",
    "wof:placetype":"venue"
},
  "geometry": {"coordinates":[-81.62255859379999,42.9595527649],"type":"Point"}
}