{
  "type": "Feature",
  "properties": {
    "addr:full":"Toronto ON M5R 3M4",
    "addr:postcode":"m5r 3m4",
    "iso:country":"CA",
    "sg:city":"Toronto",
    "sg:classifiers":[
        {
            "category":"Health Services",
            "subcategory":"Nursing And Care Facility",
            "type":"Services"
        }
    ],
    "sg:phone":"+1 416 925 9165",
    "sg:postcode":"M5R 3M4",
    "sg:province":"ON",
    "sg:tags":[
        "home",
        "rest"
    ],
    "wof:name":"Wigwamen Terrace",
    "wof:placetype":"venue"
},
  "geometry": {"coordinates":[-79.40423583979999,43.6671447754],"type":"Point"}
}