{
  "type": "Feature",
  "properties": {
    "addr:full":"830 North Dr Winnipeg MB R3T 0A6",
    "addr:housenumber":"830",
    "addr:postcode":"r3t 0a6",
    "addr:street":"North Dr",
    "iso:country":"CA",
    "sg:address":"830 North Dr",
    "sg:city":"Winnipeg",
    "sg:classifiers":[
        {
            "category":"Organizations",
            "subcategory":"Religious Organization",
            "type":"Services"
        }
    ],
    "sg:phone":"+1 204 475 7549",
    "sg:postcode":"R3T 0A6",
    "sg:province":"MB",
    "sg:tags":[
        "church"
    ],
    "wof:name":"St Paul's Anglican Church",
    "wof:placetype":"venue"
},
  "geometry": {"coordinates":[-97.14709499999999,49.847115],"type":"Point"}
}