{
  "type": "Feature",
  "properties": {
    "addr:full":"263 Argyle St S Caledonia ON N3W 1K7",
    "addr:housenumber":"263",
    "addr:postcode":"n3w 1k7",
    "addr:street":"Argyle St S",
    "iso:country":"CA",
    "sg:address":"263 Argyle St S",
    "sg:city":"Caledonia",
    "sg:classifiers":[
        {
            "category":"Personal",
            "subcategory":"Beauty Salon",
            "type":"Services"
        }
    ],
    "sg:phone":"+1 905 765 0826",
    "sg:postcode":"N3W 1K7",
    "sg:province":"ON",
    "wof:name":"First Choice Haircutters",
    "wof:placetype":"venue"
},
  "geometry": {"coordinates":[-79.95877838129999,43.065120697],"type":"Point"}
}