{
  "type": "Feature",
  "properties": {
    "addr:full":"4894 Sherkston Rd Sherkston ON L0S 1R0",
    "addr:housenumber":"4894",
    "addr:postcode":"l0s 1r0",
    "addr:street":"Sherkston Rd",
    "iso:country":"CA",
    "sg:address":"4894 Sherkston Rd",
    "sg:city":"Sherkston",
    "sg:classifiers":[
        {
            "category":"Freight",
            "type":"Transportation"
        }
    ],
    "sg:phone":"+1 905 894 0933",
    "sg:postcode":"L0S 1R0",
    "sg:province":"ON",
    "sg:tags":[
        "trucking"
    ],
    "wof:name":"Eberly Trucking Ltd",
    "wof:placetype":"venue"
},
  "geometry": {"coordinates":[-79.1241226196,42.8852310181],"type":"Point"}
}