{
  "type": "Feature",
  "properties": {
    "addr:full":"Calgary AB T1Y 5E2",
    "addr:postcode":"t1y 5e2",
    "iso:country":"CA",
    "sg:city":"Calgary",
    "sg:classifiers":[
        {
            "category":"Shopping",
            "subcategory":"Computers & Home Electronics",
            "type":"Retail Goods"
        }
    ],
    "sg:phone":"+1 403 250 3005",
    "sg:postcode":"T1Y 5E2",
    "sg:province":"AB",
    "sg:tags":[
        "equipment",
        "dealer"
    ],
    "wof:name":"Protek Computers Inc",
    "wof:placetype":"venue"
},
  "geometry": {"coordinates":[-113.994606,51.08379],"type":"Point"}
}