{
  "type": "Feature",
  "properties": {
    "addr:full":"Nepean ON K2E 8B9",
    "addr:postcode":"k2e 8b9",
    "iso:country":"CA",
    "sg:city":"Nepean",
    "sg:classifiers":[
        {
            "category":"Building & Trades",
            "subcategory":"Construction",
            "type":"Services"
        }
    ],
    "sg:phone":"+1 613 723 7849",
    "sg:postcode":"K2E 8B9",
    "sg:province":"ON",
    "sg:tags":[
        "paving",
        "contractor"
    ],
    "wof:name":"Canada Paving & Construction",
    "wof:placetype":"venue"
},
  "geometry": {"coordinates":[-75.71360778810001,45.3318786621],"type":"Point"}
}