{
  "type": "Feature",
  "properties": {
    "iso:country":"CA",
    "sg:address":"Main Rd",
    "sg:city":"Goulds",
    "sg:classifiers":[
        {
            "category":"Personal",
            "subcategory":"Beauty Salon",
            "type":"Services"
        }
    ],
    "sg:phone":"+1 709 368 6330",
    "sg:postcode":"A1S 1G9",
    "sg:province":"NL",
    "wof:name":"Guys & Gals Unisex Hair",
    "wof:placetype":"venue"
},
  "geometry": {"coordinates":[-52.7710037231,47.4435653687],"type":"Point"}
}