{
  "type": "Feature",
  "properties": {
    "addr:full":"230 Rue Des Sagueneens Chicoutimi QC G7H 3A2",
    "addr:housenumber":"230",
    "addr:postcode":"g7h 3a2",
    "addr:street":"Rue Des Sagueneens",
    "iso:country":"CA",
    "sg:address":"230 Rue Des Sagueneens",
    "sg:city":"Chicoutimi",
    "sg:classifiers":[
        {
            "category":"Personal",
            "subcategory":"Beauty Salon",
            "type":"Services"
        }
    ],
    "sg:phone":"+1 418 690 1350",
    "sg:postcode":"G7H 3A2",
    "sg:province":"QC",
    "wof:name":"Salon Meche Folle",
    "wof:placetype":"venue"
},
  "geometry": {"coordinates":[-71.064224,48.405678],"type":"Point"}
}