{
  "type": "Feature",
  "properties": {
    "iso:country":"CA",
    "sg:address":"9509 105 Ave",
    "sg:city":"High Level",
    "sg:classifiers":[
        {
            "category":"Building & Trades",
            "subcategory":"Plumbing",
            "type":"Services"
        }
    ],
    "sg:phone":"+1 780 926 3959",
    "sg:postcode":"T0H 1Z0",
    "sg:province":"AB",
    "sg:tags":[
        "contractor",
        "general"
    ],
    "wof:name":"Northern Services",
    "wof:placetype":"venue"
},
  "geometry": {"coordinates":[-117.13092804,58.5112762451],"type":"Point"}
}