{
  "type": "Feature",
  "properties": {
    "addr:full":"322 Consumers Rd North York ON M2J 1P8",
    "addr:housenumber":"322",
    "addr:postcode":"m2j 1p8",
    "addr:street":"Consumers Rd",
    "iso:country":"CA",
    "sg:address":"322 Consumers Rd",
    "sg:city":"North York",
    "sg:classifiers":[
        {
            "category":"Organizations",
            "subcategory":"Professional Association",
            "type":"Services"
        }
    ],
    "sg:phone":"+1 416 490 8844",
    "sg:postcode":"M2J 1P8",
    "sg:province":"ON",
    "wof:name":"Life Saving Society",
    "wof:placetype":"venue"
},
  "geometry": {"coordinates":[-79.329117,43.770699],"type":"Point"}
}