{
  "type": "Feature",
  "properties": {
    "addr:full":"197 Toryork Dr North York ON M9L 1X9",
    "addr:housenumber":"197",
    "addr:postcode":"m9l 1x9",
    "addr:street":"Toryork Dr",
    "iso:country":"CA",
    "sg:address":"197 Toryork Dr",
    "sg:city":"North York",
    "sg:classifiers":[
        {
            "category":"Manufacturing",
            "subcategory":"Metals",
            "type":"Manufacturing & Wholesale Goods"
        }
    ],
    "sg:phone":"+1 416 749 9461",
    "sg:postcode":"M9L 1X9",
    "sg:province":"ON",
    "sg:tags":[
        "product",
        "magnesium"
    ],
    "wof:name":"M & B Magnesium Products Ltd",
    "wof:placetype":"venue"
},
  "geometry": {"coordinates":[-79.559433,43.760399],"type":"Point"}
}