{
  "type": "Feature",
  "properties": {
    "addr:full":"3084 Spring St Port Moody BC V3H 1Z8",
    "addr:housenumber":"3084",
    "addr:postcode":"v3h 1z8",
    "addr:street":"Spring St",
    "iso:country":"CA",
    "sg:address":"3084 Spring St",
    "sg:city":"Port Moody",
    "sg:classifiers":[
        {
            "category":"Retail",
            "subcategory":"Animal Services",
            "type":"Services"
        }
    ],
    "sg:phone":"+1 604 469 4400",
    "sg:postcode":"V3H 1Z8",
    "sg:province":"BC",
    "sg:tags":[
        "pet",
        "grooming",
        "washing"
    ],
    "wof:name":"Port Moody Dog Grooming",
    "wof:placetype":"venue"
},
  "geometry": {"coordinates":[-122.842316,49.277401],"type":"Point"}
}