{
  "type": "Feature",
  "properties": {
    "addr:full":"151 Stradwick Ave Nepean ON K2J 2X9",
    "addr:housenumber":"151",
    "addr:postcode":"k2j 2x9",
    "addr:street":"Stradwick Ave",
    "iso:country":"CA",
    "sg:address":"151 Stradwick Ave",
    "sg:city":"Nepean",
    "sg:classifiers":[
        {
            "category":"Professional",
            "type":"Services"
        }
    ],
    "sg:phone":"+1 613 724 1794",
    "sg:postcode":"K2J 2X9",
    "sg:province":"ON",
    "sg:tags":[
        "establishment",
        "appraiser",
        "real estate"
    ],
    "wof:name":"Kirk & Oswald Appraisal Svc",
    "wof:placetype":"venue"
},
  "geometry": {"coordinates":[-75.769592,45.275021],"type":"Point"}
}