{
  "type": "Feature",
  "properties": {
    "addr:full":"5 Purcell Cres Maple ON L6A 3C4",
    "addr:housenumber":"5",
    "addr:postcode":"l6a 3c4",
    "addr:street":"Purcell Cres",
    "iso:country":"CA",
    "sg:address":"5 Purcell Cres",
    "sg:city":"Maple",
    "sg:classifiers":[
        {
            "category":"Building & Trades",
            "subcategory":"Cleaning & Sanitation",
            "type":"Services"
        }
    ],
    "sg:phone":"+1 905 303 0076",
    "sg:postcode":"L6A 3C4",
    "sg:province":"ON",
    "sg:tags":[
        "house",
        "janitor"
    ],
    "wof:name":"Ginas Maid Svc",
    "wof:placetype":"venue"
},
  "geometry": {"coordinates":[-79.523727417,43.8658752441],"type":"Point"}
}