{
  "type": "Feature",
  "properties": {
    "addr:full":"1075 Bo-DE Lane St Jacobs ON N0B 2N0",
    "addr:housenumber":"1075",
    "addr:postcode":"n0b 2n0",
    "addr:street":"Bo-De Lane St",
    "iso:country":"CA",
    "sg:address":"1075 Bo-DE Lane",
    "sg:city":"St Jacobs",
    "sg:classifiers":[
        {
            "category":"Recreation",
            "type":"Entertainment"
        }
    ],
    "sg:phone":"+1 519 664 2951",
    "sg:postcode":"N0B 2N0",
    "sg:province":"ON",
    "sg:tags":[
        "hall",
        "auditorium"
    ],
    "wof:name":"Waterloo Rod & Gun Club",
    "wof:placetype":"venue"
},
  "geometry": {"coordinates":[-80.553596,43.5392],"type":"Point"}
}