{
  "type": "Feature",
  "properties": {
    "addr:full":"10442 Av Armand-Lavergne Montreal-Nord QC H1H 3N4",
    "addr:postcode":"h1h 3n4",
    "addr:street":"Av Armand-Lavergne",
    "iso:country":"CA",
    "sg:address":"10442 Av Armand-Lavergne",
    "sg:city":"Montreal-Nord",
    "sg:classifiers":[
        {
            "category":"Wholesale",
            "subcategory":"Auto Parts",
            "type":"Manufacturing & Wholesale Goods"
        }
    ],
    "sg:phone":"+1 514 325 6602",
    "sg:postcode":"H1H 3N4",
    "sg:province":"QC",
    "sg:tags":[
        "transmission",
        "manufacturer"
    ],
    "wof:name":"King-O-Matic Les Industries",
    "wof:placetype":"venue"
},
  "geometry": {"coordinates":[-73.6285934448,45.5895004272],"type":"Point"}
}