{
  "type": "Feature",
  "properties": {
    "addr:full":"Calgary AB T2H 1J9",
    "addr:postcode":"t2h 1j9",
    "iso:country":"CA",
    "sg:city":"Calgary",
    "sg:classifiers":[
        {
            "category":"Autos & Motor Vehicles",
            "subcategory":"Motorcycle Sales",
            "type":"Retail Goods"
        }
    ],
    "sg:phone":"+1 403 253 7977",
    "sg:postcode":"T2H 1J9",
    "sg:province":"AB",
    "sg:tags":[
        "scooter"
    ],
    "wof:name":"Speedtwin Performance Cycles",
    "wof:placetype":"venue"
},
  "geometry": {"coordinates":[-114.056869507,51.0046920776],"type":"Point"}
}