{
  "type": "Feature",
  "properties": {
    "addr:full":"1101 Fennell Ave E Hamilton ON L8T 1S1",
    "addr:housenumber":"1101",
    "addr:postcode":"l8t 1s1",
    "addr:street":"Fennell Ave E",
    "iso:country":"CA",
    "sg:address":"1101 Fennell Ave E",
    "sg:city":"Hamilton",
    "sg:classifiers":[
        {
            "category":"Personal",
            "subcategory":"Barber",
            "type":"Services"
        }
    ],
    "sg:phone":"+1 905 385 0477",
    "sg:postcode":"L8T 1S1",
    "sg:province":"ON",
    "wof:name":"Sherwood Men's Hairstyling",
    "wof:placetype":"venue"
},
  "geometry": {"coordinates":[-79.8307342529,43.2260093689],"type":"Point"}
}