{
  "type": "Feature",
  "properties": {
    "addr:full":"455 Rue St-Paul N Saint-Ubalde QC G0A 4L0",
    "addr:housenumber":"455",
    "addr:postcode":"g0a 4l0",
    "addr:street":"Rue St-Paul N",
    "iso:country":"CA",
    "sg:address":"455 Rue St-Paul N",
    "sg:city":"Saint-Ubalde",
    "sg:classifiers":[
        {
            "category":"Retail",
            "subcategory":"Auto Repair",
            "type":"Services"
        }
    ],
    "sg:phone":"+1 418 277 2059",
    "sg:postcode":"G0A 4L0",
    "sg:province":"QC",
    "sg:tags":[
        "repairing",
        "automobile"
    ],
    "wof:name":"Garage Bernard Hardy Inc",
    "wof:placetype":"venue"
},
  "geometry": {"coordinates":[-72.271828,46.756947],"type":"Point"}
}