{
  "type": "Feature",
  "properties": {
    "addr:full":"Joyceville ON K0H 1Y0",
    "addr:postcode":"k0h 1y0",
    "iso:country":"CA",
    "sg:city":"Joyceville",
    "sg:classifiers":[
        {
            "category":"Autos & Motor Vehicles",
            "subcategory":"Fuel & Gas Station",
            "type":"Retail Goods"
        }
    ],
    "sg:phone":"+1 613 542 3468",
    "sg:postcode":"K0H 1Y0",
    "sg:province":"ON",
    "sg:tags":[
        "oil"
    ],
    "wof:name":"Kingston Husky Car/Truck Stop",
    "wof:placetype":"venue"
},
  "geometry": {"coordinates":[-76.33493799999999,44.361469],"type":"Point"}
}