{
  "type": "Feature",
  "properties": {
    "addr:full":"Edmonton AB T5L 2W3",
    "addr:postcode":"t5l 2w3",
    "iso:country":"CA",
    "sg:city":"Edmonton",
    "sg:classifiers":[
        {
            "category":"Social Services",
            "subcategory":"Child Care",
            "type":"Services"
        }
    ],
    "sg:phone":"+1 780 451 5540",
    "sg:postcode":"T5L 2W3",
    "sg:province":"AB",
    "wof:name":"Bamby Day Care Ctr Ltd",
    "wof:placetype":"venue"
},
  "geometry": {"coordinates":[-113.56138610799999,53.5734519958],"type":"Point"}
}