{
  "type": "Feature",
  "properties": {
    "iso:country":"CA",
    "sg:address":"5930 No 6 Rd # 301",
    "sg:city":"Richmond",
    "sg:classifiers":[
        {
            "category":"Autos & Motor Vehicles",
            "subcategory":"Auto Supplies",
            "type":"Retail Goods"
        }
    ],
    "sg:phone":"+1 604 276 8038",
    "sg:postcode":"V6V 1Z1",
    "sg:province":"BC",
    "sg:tags":[
        "automobile",
        "alarm"
    ],
    "wof:name":"Ying Wah Auto Svc Ltd",
    "wof:placetype":"venue"
},
  "geometry": {"coordinates":[-123.06905365,49.1719398499],"type":"Point"}
}