{
  "type": "Feature",
  "properties": {
    "addr:full":"2976 Broadway W Vancouver BC V6K 2G8",
    "addr:housenumber":"2976",
    "addr:postcode":"v6k 2g8",
    "addr:street":"Broadway W",
    "iso:country":"CA",
    "sg:address":"2976 Broadway W",
    "sg:city":"Vancouver",
    "sg:classifiers":[
        {
            "category":"Shopping",
            "subcategory":"Jewelry",
            "type":"Retail Goods"
        }
    ],
    "sg:phone":"+1 604 731 5222",
    "sg:postcode":"V6K 2G8",
    "sg:province":"BC",
    "sg:tags":[
        "jeweler"
    ],
    "wof:name":"Rhodes Jewelers",
    "wof:placetype":"venue"
},
  "geometry": {"coordinates":[-123.171508789,49.2639541626],"type":"Point"}
}