{
  "type": "Feature",
  "properties": {
    "addr:full":"432 275 Rte Ste-Marguerite-DE-Dorchester QC G0S 2X0",
    "addr:housenumber":"275",
    "addr:postcode":"g0s 2x0",
    "addr:street":"Rte Ste-Marguerite-De-Dorchester",
    "iso:country":"CA",
    "sg:address":"432 275 Rte",
    "sg:city":"Ste-Marguerite-DE-Dorchester",
    "sg:classifiers":[
        {
            "category":"Building & Trades",
            "subcategory":"Plumbing",
            "type":"Services"
        }
    ],
    "sg:phone":"+1 418 935 7172",
    "sg:postcode":"G0S 2X0",
    "sg:province":"QC",
    "sg:tags":[
        "plate",
        "tin",
        "heating",
        "contractor"
    ],
    "wof:name":"Ferblanterie Stephanie Boiss",
    "wof:placetype":"venue"
},
  "geometry": {"coordinates":[-70.93868255620001,46.5112991333],"type":"Point"}
}