{
  "type": "Feature",
  "properties": {
    "addr:full":"Truro NS B2N 4Z9",
    "addr:postcode":"b2n 4z9",
    "iso:country":"CA",
    "sg:city":"Truro",
    "sg:classifiers":[
        {
            "category":"Health Services",
            "subcategory":"Doctor",
            "type":"Services"
        }
    ],
    "sg:phone":"+1 902 893 9211",
    "sg:postcode":"B2N 4Z9",
    "sg:province":"NS",
    "sg:tags":[
        "physician",
        "surgeon"
    ],
    "wof:name":"Curtis, Gary M MD",
    "wof:placetype":"venue"
},
  "geometry": {"coordinates":[-63.2913589478,45.358455658],"type":"Point"}
}