{
  "type": "Feature",
  "properties": {
    "addr:full":"287 Ashland Ave London ON N5W 4E3",
    "addr:housenumber":"287",
    "addr:postcode":"n5w 4e3",
    "addr:street":"Ashland Ave",
    "iso:country":"CA",
    "sg:address":"287 Ashland Ave",
    "sg:city":"London",
    "sg:classifiers":[
        {
            "category":"Manufacturing",
            "subcategory":"Printing",
            "type":"Manufacturing & Wholesale Goods"
        }
    ],
    "sg:phone":"+1 519 453 5880",
    "sg:postcode":"N5W 4E3",
    "sg:province":"ON",
    "sg:tags":[
        "printer"
    ],
    "wof:name":"Holiday Print & Promotions Ltd",
    "wof:placetype":"venue"
},
  "geometry": {"coordinates":[-81.2069320679,42.9910812378],"type":"Point"}
}