{
  "type": "Feature",
  "properties": {
    "addr:full":"481 Main St W Port Colborne ON L3K 3W3",
    "addr:housenumber":"481",
    "addr:postcode":"l3k 3w3",
    "addr:street":"Main St W",
    "iso:country":"CA",
    "sg:address":"481 Main St W",
    "sg:city":"Port Colborne",
    "sg:classifiers":[
        {
            "category":"Shopping",
            "subcategory":"Discount & Variety Stores",
            "type":"Retail Goods"
        }
    ],
    "sg:phone":"+1 905 834 6710",
    "sg:postcode":"L3K 3W3",
    "sg:province":"ON",
    "wof:name":"B B's Variety",
    "wof:placetype":"venue"
},
  "geometry": {"coordinates":[-79.26029200000001,42.898823],"type":"Point"}
}