{
  "type": "Feature",
  "properties": {
    "addr:full":"9620 62 Ave NW Edmonton AB T6E 0E2",
    "addr:housenumber":"9620",
    "addr:postcode":"t6e 0e2",
    "addr:street":"62 Ave Nw",
    "iso:country":"CA",
    "sg:address":"9620 62 Ave NW",
    "sg:city":"Edmonton",
    "sg:classifiers":[
        {
            "category":"Retail",
            "subcategory":"Auto Repair",
            "type":"Services"
        }
    ],
    "sg:phone":"+1 780 435 6880",
    "sg:postcode":"T6E 0E2",
    "sg:province":"AB",
    "sg:tags":[
        "transmission"
    ],
    "wof:name":"Bonds Transmissions",
    "wof:placetype":"venue"
},
  "geometry": {"coordinates":[-113.47745500000001,53.498585],"type":"Point"}
}