{
  "type": "Feature",
  "properties": {
    "addr:full":"Seba Beach AB T0E 2B0",
    "addr:postcode":"t0e 2b0",
    "iso:country":"CA",
    "sg:city":"Seba Beach",
    "sg:classifiers":[
        {
            "category":"Organizations",
            "subcategory":"Professional Association",
            "type":"Services"
        }
    ],
    "sg:phone":"+1 780 797 3087",
    "sg:postcode":"T0E 2B0",
    "sg:province":"AB",
    "sg:tags":[
        "club"
    ],
    "wof:name":"Seba Beach Seniors Golden Age",
    "wof:placetype":"venue"
},
  "geometry": {"coordinates":[-114.735595703,53.5598258972],"type":"Point"}
}