{
  "type": "Feature",
  "properties": {
    "addr:full":"6995 Av DE Westbury Montreal QC H3W 2X9",
    "addr:housenumber":"6995",
    "addr:postcode":"h3w 2x9",
    "addr:street":"Av De Westbury",
    "iso:country":"CA",
    "sg:address":"6995 Av DE Westbury",
    "sg:city":"Montreal",
    "sg:classifiers":[
        {
            "category":"Organizations",
            "subcategory":"Membership Organization",
            "type":"Services"
        }
    ],
    "sg:phone":"+1 514 344 8145",
    "sg:postcode":"H3W 2X9",
    "sg:province":"QC",
    "wof:name":"Chai Youth Campus",
    "wof:placetype":"venue"
},
  "geometry": {"coordinates":[-73.64780399999999,45.494759],"type":"Point"}
}