{
  "type": "Feature",
  "properties": {
    "addr:full":"Laval QC H7V 1N8",
    "addr:postcode":"h7v 1n8",
    "iso:country":"CA",
    "sg:city":"Laval",
    "sg:classifiers":[
        {
            "category":"Manufacturing",
            "subcategory":"Food",
            "type":"Manufacturing & Wholesale Goods"
        }
    ],
    "sg:phone":"+1 514 488 2811",
    "sg:postcode":"H7V 1N8",
    "sg:province":"QC",
    "sg:tags":[
        "storage",
        "winery",
        "wine"
    ],
    "wof:name":"St-Laurent Serge Cave A Vins",
    "wof:placetype":"venue"
},
  "geometry": {"coordinates":[-73.7316894531,45.5459365845],"type":"Point"}
}