{
  "type": "Feature",
  "properties": {
    "addr:full":"4905 50 St Vermilion AB T9X 1C3",
    "addr:housenumber":"4905",
    "addr:postcode":"t9x 1c3",
    "addr:street":"50 St",
    "iso:country":"CA",
    "sg:address":"4905 50 St",
    "sg:city":"Vermilion",
    "sg:classifiers":[
        {
            "category":"Food & Beverages",
            "subcategory":"Liquor & Beverages",
            "type":"Retail Goods"
        }
    ],
    "sg:phone":"+1 780 853 5132",
    "sg:postcode":"T9X 1C3",
    "sg:province":"AB",
    "sg:tags":[
        "store"
    ],
    "wof:name":"Lorraines Liquor Store",
    "wof:placetype":"venue"
},
  "geometry": {"coordinates":[-110.852714539,53.3531723022],"type":"Point"}
}