{
  "type": "Feature",
  "properties": {
    "addr:full":"25 Ch DE LA Savane Gatineau QC J8T 8A4",
    "addr:housenumber":"25",
    "addr:postcode":"j8t 8a4",
    "addr:street":"Ch De La Savane",
    "iso:country":"CA",
    "sg:address":"25 Ch DE LA Savane",
    "sg:city":"Gatineau",
    "sg:classifiers":[
        {
            "category":"Restaurant",
            "type":"Food & Drink"
        }
    ],
    "sg:phone":"+1 819 243 7827",
    "sg:postcode":"J8T 8A4",
    "sg:province":"QC",
    "wof:name":"Subway Sandwiches & Salads",
    "wof:placetype":"venue"
},
  "geometry": {"coordinates":[-75.7035293579,45.473865509],"type":"Point"}
}