{
  "type": "Feature",
  "properties": {
    "addr:full":"5024 51st St Provost AB T0B 3S0",
    "addr:housenumber":"5024",
    "addr:postcode":"t0b 3s0",
    "addr:street":"51St St",
    "iso:country":"CA",
    "sg:address":"5024 51st St",
    "sg:city":"Provost",
    "sg:classifiers":[
        {
            "category":"Professional",
            "subcategory":"Business Services",
            "type":"Services"
        }
    ],
    "sg:phone":"+1 780 753 6861",
    "sg:postcode":"T0B 3S0",
    "sg:province":"AB",
    "sg:tags":[
        "paging",
        "answering"
    ],
    "wof:name":"Provost Communications",
    "wof:placetype":"venue"
},
  "geometry": {"coordinates":[-110.266167,52.351906],"type":"Point"}
}