{
  "type": "Feature",
  "properties": {
    "addr:full":"2 Fisherman Dr #2 Brampton ON L7A 1B5",
    "addr:housenumber":"2",
    "addr:postcode":"l7a 1b5",
    "addr:street":"Fisherman Dr # 2",
    "iso:country":"CA",
    "sg:address":"2 Fisherman Dr #2",
    "sg:city":"Brampton",
    "sg:classifiers":[
        {
            "category":"Retail",
            "subcategory":"Auto Repair",
            "type":"Services"
        }
    ],
    "sg:phone":"+1 905 840 5901",
    "sg:postcode":"L7A 1B5",
    "sg:province":"ON",
    "sg:tags":[
        "automobile",
        "lubrication"
    ],
    "wof:name":"Pennzoil 10 Minute Oil Change",
    "wof:placetype":"venue"
},
  "geometry": {"coordinates":[-79.799751,43.715008],"type":"Point"}
}