{
  "type": "Feature",
  "properties": {
    "addr:full":"65 Church St St Stephen NB E3L 1M6",
    "addr:housenumber":"65",
    "addr:postcode":"e3l 1m6",
    "addr:street":"Church St",
    "iso:country":"CA",
    "sg:address":"65 Church St",
    "sg:city":"St Stephen",
    "sg:classifiers":[
        {
            "category":"Health Services",
            "subcategory":"Doctor",
            "type":"Services"
        }
    ],
    "sg:phone":"+1 506 466 3878",
    "sg:postcode":"E3L 1M6",
    "sg:province":"NB",
    "sg:tags":[
        "physician",
        "surgeon"
    ],
    "wof:name":"Acheson, Donald K MD",
    "wof:placetype":"venue"
},
  "geometry": {"coordinates":[-67.30940200000001,45.184341],"type":"Point"}
}