{
  "type": "Feature",
  "properties": {
    "iso:country":"CA",
    "sg:address":"960 Third Line E",
    "sg:city":"Sault Ste Marie",
    "sg:classifiers":[
        {
            "category":"Building & Trades",
            "subcategory":"Construction",
            "type":"Services"
        }
    ],
    "sg:phone":"+1 705 759 6300",
    "sg:postcode":"P6A 6J8",
    "sg:province":"ON",
    "sg:tags":[
        "roofing",
        "contractor"
    ],
    "wof:name":"Continental Roofing Ltd",
    "wof:placetype":"venue"
},
  "geometry": {"coordinates":[-84.303062439,46.553527832],"type":"Point"}
}