{
  "type": "Feature",
  "properties": {
    "addr:full":"Janetville ON L0B 1K0",
    "addr:postcode":"l0b 1k0",
    "iso:country":"CA",
    "sg:city":"Janetville",
    "sg:classifiers":[
        {
            "category":"Organizations",
            "subcategory":"Religious Organization",
            "type":"Services"
        }
    ],
    "sg:phone":"+1 705 324 4006",
    "sg:postcode":"L0B 1K0",
    "sg:province":"ON",
    "sg:tags":[
        "church"
    ],
    "wof:name":"Janetville United Church",
    "wof:placetype":"venue"
},
  "geometry": {"coordinates":[-78.72545599999999,44.214592],"type":"Point"}
}