{
  "type": "Feature",
  "properties": {
    "iso:country":"CA",
    "sg:address":"1345 Rte Marie-Victorin O",
    "sg:city":"Deschaillons-Sur-Saint-Laurent",
    "sg:classifiers":[
        {
            "category":"Restaurant",
            "type":"Food & Drink"
        }
    ],
    "sg:phone":"+1 819 292 2437",
    "sg:postcode":"G0S 1G0",
    "sg:province":"QC",
    "wof:name":"Casse-Croute Capri",
    "wof:placetype":"venue"
},
  "geometry": {"coordinates":[-72.1206893921,46.5545196533],"type":"Point"}
}