{
  "type": "Feature",
  "properties": {
    "addr:full":"1345 Rte Marie-Victorin O Deschaillons-Sur-Saint-Laurent QC G0S 1G0",
    "addr:housenumber":"1345",
    "addr:postcode":"g0s 1g0",
    "addr:street":"Rte Marie-Victorin O",
    "iso:country":"CA",
    "sg:address":"1345 Rte Marie-Victorin O",
    "sg:city":"Deschaillons-Sur-Saint-Laurent",
    "sg:classifiers":[
        {
            "category":"Restaurant",
            "type":"Food & Drink"
        }
    ],
    "sg:phone":"+1 819 292 2437",
    "sg:postcode":"G0S 1G0",
    "sg:province":"QC",
    "wof:name":"Casse-Croute Capri",
    "wof:placetype":"venue"
},
  "geometry": {"coordinates":[-72.1206893921,46.5545196533],"type":"Point"}
}