{
  "type": "Feature",
  "properties": {
    "addr:full":"555 Ch DE LA Riviere S Saint-Eustache QC J7R 4K3",
    "addr:housenumber":"555",
    "addr:postcode":"j7r 4k3",
    "addr:street":"Ch De La Riviere S",
    "iso:country":"CA",
    "sg:address":"555 Ch DE LA Riviere S",
    "sg:city":"Saint-Eustache",
    "sg:classifiers":[
        {
            "category":"Sports & Exercise",
            "subcategory":"Golf",
            "type":"Entertainment"
        }
    ],
    "sg:phone":"+1 450 472 4653",
    "sg:postcode":"J7R 4K3",
    "sg:province":"QC",
    "sg:tags":[
        "hall",
        "auditorium"
    ],
    "wof:name":"Club DE Golf Deux Montagnes",
    "wof:placetype":"venue"
},
  "geometry": {"coordinates":[-73.9312133789,45.5627365112],"type":"Point"}
}