{
  "type": "Feature",
  "properties": {
    "addr:full":"152 Main St Fredericton NB E3A 1C8",
    "addr:housenumber":"152",
    "addr:postcode":"e3a 1c8",
    "addr:street":"Main St",
    "iso:country":"CA",
    "sg:address":"152 Main St",
    "sg:city":"Fredericton",
    "sg:classifiers":[
        {
            "category":"Professional",
            "subcategory":"Accounting & Tax Preparation",
            "type":"Services"
        }
    ],
    "sg:phone":"+1 506 458 9390",
    "sg:postcode":"E3A 1C8",
    "sg:province":"NB",
    "sg:tags":[
        "accountant"
    ],
    "wof:name":"Craig, Ross",
    "wof:placetype":"venue"
},
  "geometry": {"coordinates":[-66.65430499999999,45.978531],"type":"Point"}
}