{
  "type": "Feature",
  "properties": {
    "addr:full":"1251 Rue DE Conde Montreal QC H3K 2E4",
    "addr:housenumber":"1251",
    "addr:postcode":"h3k 2e4",
    "addr:street":"Rue De Conde",
    "iso:country":"CA",
    "sg:address":"1251 Rue DE Conde",
    "sg:city":"Montreal",
    "sg:classifiers":[
        {
            "category":"Manufacturing",
            "subcategory":"Tools & Machinery",
            "type":"Manufacturing & Wholesale Goods"
        }
    ],
    "sg:phone":"+1 514 931 1301",
    "sg:postcode":"H3K 2E4",
    "sg:province":"QC",
    "sg:tags":[
        "equipment",
        "aircraft",
        "parts",
        "supply"
    ],
    "wof:name":"Plasmatec Inc",
    "wof:placetype":"venue"
},
  "geometry": {"coordinates":[-73.559158,45.485954],"type":"Point"}
}