{
  "type": "Feature",
  "properties": {
    "addr:full":"Truro NS B2N 5B4",
    "addr:postcode":"b2n 5b4",
    "iso:country":"CA",
    "sg:city":"Truro",
    "sg:classifiers":[
        {
            "category":"Organizations",
            "subcategory":"Professional Association",
            "type":"Services"
        }
    ],
    "sg:phone":"+1 902 895 7893",
    "sg:postcode":"B2N 5B4",
    "sg:province":"NS",
    "sg:tags":[
        "club"
    ],
    "wof:name":"Truro Horsemens Club",
    "wof:placetype":"venue"
},
  "geometry": {"coordinates":[-63.3042030334,45.3585357666],"type":"Point"}
}