{
  "type": "Feature",
  "properties": {
    "addr:full":"Montreal QC H1T 3X1",
    "addr:postcode":"h1t 3x1",
    "iso:country":"CA",
    "sg:city":"Montreal",
    "sg:classifiers":[
        {
            "category":"Freight",
            "type":"Transportation"
        }
    ],
    "sg:phone":"+1 514 252 5335",
    "sg:postcode":"H1T 3X1",
    "sg:province":"QC",
    "sg:tags":[
        "broker",
        "trucking"
    ],
    "wof:name":"Courtiers En Transport Gj Inc",
    "wof:placetype":"venue"
},
  "geometry": {"coordinates":[-73.552773,45.568336],"type":"Point"}
}