{
  "type": "Feature",
  "properties": {
    "addr:full":"21 Mollard Crt Barrie ON L4N 8Y1",
    "addr:housenumber":"21",
    "addr:postcode":"l4n 8y1",
    "addr:street":"Mollard Crt",
    "iso:country":"CA",
    "sg:address":"21 Mollard Crt",
    "sg:city":"Barrie",
    "sg:classifiers":[
        {
            "category":"Manufacturing",
            "subcategory":"Tools & Machinery",
            "type":"Manufacturing & Wholesale Goods"
        }
    ],
    "sg:phone":"+1 705 733 2810",
    "sg:postcode":"L4N 8Y1",
    "sg:province":"ON",
    "sg:tags":[
        "machine",
        "shop"
    ],
    "wof:name":"Msm Machine & Design Ltd",
    "wof:placetype":"venue"
},
  "geometry": {"coordinates":[-79.68235799999999,44.355667],"type":"Point"}
}