{
  "type": "Feature",
  "properties": {
    "addr:full":"524 Cleveland Cres SE Calgary AB T2G 4A9",
    "addr:housenumber":"524",
    "addr:postcode":"t2g 4a9",
    "addr:street":"Cleveland Cres Se",
    "iso:country":"CA",
    "sg:address":"524 Cleveland Cres SE",
    "sg:city":"Calgary",
    "sg:classifiers":[
        {
            "category":"Wholesale",
            "subcategory":"Machinery & Supplies",
            "type":"Manufacturing & Wholesale Goods"
        }
    ],
    "sg:phone":"+1 403 287 6155",
    "sg:postcode":"T2G 4A9",
    "sg:province":"AB",
    "sg:tags":[
        "instrument",
        "surveying"
    ],
    "wof:name":"am-Tech Canada Precision",
    "wof:placetype":"venue"
},
  "geometry": {"coordinates":[-114.053352356,51.0163002014],"type":"Point"}
}