{
  "type": "Feature",
  "properties": {
    "addr:full":"18 Parkhurst Blvd East York ON M4G 2C6",
    "addr:housenumber":"18",
    "addr:postcode":"m4g 2c6",
    "addr:street":"Parkhurst Blvd",
    "iso:country":"CA",
    "sg:address":"18 Parkhurst Blvd",
    "sg:city":"East York",
    "sg:phone":"+1 416 487 7311",
    "sg:postcode":"M4G 2C6",
    "sg:province":"ON",
    "sg:tags":[
        "oil"
    ],
    "wof:name":"Leader Petroleum Ltd",
    "wof:placetype":"venue"
},
  "geometry": {"coordinates":[-79.374741,43.708965],"type":"Point"}
}