{
  "type": "Feature",
  "properties": {
    "iso:country":"CA",
    "sg:address":"5760 Av Parkhaven",
    "sg:city":"Cote Saint-Luc",
    "sg:classifiers":[
        {
            "category":"Organizations",
            "subcategory":"Labor Organization",
            "type":"Services"
        }
    ],
    "sg:phone":"+1 514 369 6220",
    "sg:postcode":"H4W 1X9",
    "sg:province":"QC",
    "wof:name":"Griffith Mc Connell Worker's",
    "wof:placetype":"venue"
},
  "geometry": {"coordinates":[-73.6668167114,45.4688224792],"type":"Point"}
}