{
  "type": "Feature",
  "properties": {
    "iso:country":"CA",
    "sg:address":"455 South Railway St W",
    "sg:city":"Swift Current",
    "sg:classifiers":[
        {
            "category":"Wholesale",
            "subcategory":"Farm Supplies",
            "type":"Manufacturing & Wholesale Goods"
        }
    ],
    "sg:phone":"+1 306 778 2419",
    "sg:postcode":"S9H 2Z3",
    "sg:province":"SK",
    "sg:tags":[
        "feed"
    ],
    "wof:name":"Bio Earth Works",
    "wof:placetype":"venue"
},
  "geometry": {"coordinates":[-107.804328919,50.2806930542],"type":"Point"}
}