{
  "type": "Feature",
  "properties": {
    "addr:full":"5284 Nauvoo Rd Watford ON N0M 2S0",
    "addr:housenumber":"5284",
    "addr:postcode":"n0m 2s0",
    "addr:street":"Nauvoo Rd",
    "iso:country":"CA",
    "sg:address":"5284 Nauvoo Rd",
    "sg:city":"Watford",
    "sg:classifiers":[
        {
            "category":"Food & Beverages",
            "subcategory":"Bakery",
            "type":"Retail Goods"
        }
    ],
    "sg:phone":"+1 519 876 2925",
    "sg:postcode":"N0M 2S0",
    "sg:province":"ON",
    "sg:tags":[
        "doughnut"
    ],
    "wof:name":"Good Morning Donut Deli",
    "wof:placetype":"venue"
},
  "geometry": {"coordinates":[-81.87988300000001,42.947361],"type":"Point"}
}