{
  "type": "Feature",
  "properties": {
    "iso:country":"CA",
    "sg:city":"Calgary",
    "sg:classifiers":[
        {
            "category":"Shopping",
            "type":"Retail Goods"
        }
    ],
    "sg:phone":"+1 403 252 0911",
    "sg:postcode":"T2H 2G3",
    "sg:province":"AB",
    "sg:tags":[
        "equipment",
        "telephone",
        "supply"
    ],
    "wof:name":"Nine-One-One Communication",
    "wof:placetype":"venue"
},
  "geometry": {"coordinates":[-114.050613403,50.9920387268],"type":"Point"}
}