{
  "type": "Feature",
  "properties": {
    "addr:full":"985 Rue Nouvel Baie-Comeau QC G5C 2C9",
    "addr:housenumber":"985",
    "addr:postcode":"g5c 2c9",
    "addr:street":"Rue Nouvel",
    "iso:country":"CA",
    "sg:address":"985 Rue Nouvel",
    "sg:city":"Baie-Comeau",
    "sg:classifiers":[
        {
            "category":"Government",
            "subcategory":"Office",
            "type":"Public Place"
        }
    ],
    "sg:phone":"+1 418 295 4704",
    "sg:postcode":"G5C 2C9",
    "sg:province":"QC",
    "wof:name":"Quebec Ateliers Mecaniques",
    "wof:placetype":"venue"
},
  "geometry": {"coordinates":[-68.26383972169999,49.1945075989],"type":"Point"}
}