{
  "type": "Feature",
  "properties": {
    "iso:country":"CA",
    "sg:address":"3705 Portage Ave",
    "sg:city":"Winnipeg",
    "sg:classifiers":[
        {
            "category":"Autos & Motor Vehicles",
            "subcategory":"Fuel & Gas Station",
            "type":"Retail Goods"
        }
    ],
    "sg:phone":"+1 204 888 0885",
    "sg:postcode":"R3K 0X4",
    "sg:province":"MB",
    "sg:tags":[
        "oil"
    ],
    "wof:name":"Mohawk Uni-City Svc",
    "wof:placetype":"venue"
},
  "geometry": {"coordinates":[-97.31568145750001,49.8819351196],"type":"Point"}
}