{
  "type": "Feature",
  "properties": {
    "addr:full":"441 Columbia St Kamloops BC V2C 2T3",
    "addr:housenumber":"441",
    "addr:postcode":"bc v2c 2t3",
    "addr:street":"Columbia St",
    "iso:country":"CA",
    "sg:address":"441 Columbia St",
    "sg:city":"Kamloops",
    "sg:classifiers":[
        {
            "category":"Government",
            "subcategory":"Office",
            "type":"Public Place"
        }
    ],
    "sg:phone":"+1 250 371 3780",
    "sg:postcode":"V2C 2T3",
    "sg:province":"BC",
    "wof:name":"BC Training & Employability",
    "wof:placetype":"venue"
},
  "geometry": {"coordinates":[-120.331017,50.671272],"type":"Point"}
}