{
  "type": "Feature",
  "properties": {
    "addr:full":"66 Strathmoor Way Sherwood Park AB T8H 2A5",
    "addr:housenumber":"66",
    "addr:postcode":"t8h 2a5",
    "addr:street":"Strathmoor Way",
    "iso:country":"CA",
    "sg:address":"66 Strathmoor Way",
    "sg:city":"Sherwood Park",
    "sg:classifiers":[
        {
            "category":"Manufacturing",
            "subcategory":"Metals",
            "type":"Manufacturing & Wholesale Goods"
        }
    ],
    "sg:phone":"+1 780 464 1292",
    "sg:postcode":"T8H 2A5",
    "sg:province":"AB",
    "sg:tags":[
        "welding"
    ],
    "wof:name":"Mahon Fabricating & Welding",
    "wof:placetype":"venue"
},
  "geometry": {"coordinates":[-113.323822022,53.5631256104],"type":"Point"}
}