{
  "type": "Feature",
  "properties": {
    "addr:full":"Scarborough ON M1P 4Y4",
    "addr:postcode":"m1p 4y4",
    "iso:country":"CA",
    "sg:city":"Scarborough",
    "sg:classifiers":[
        {
            "category":"Freight",
            "type":"Transportation"
        }
    ],
    "sg:phone":"+1 416 751 8008",
    "sg:postcode":"M1P 4Y4",
    "sg:province":"ON",
    "wof:name":"International Shipping Link",
    "wof:placetype":"venue"
},
  "geometry": {"coordinates":[-79.263176,43.752048],"type":"Point"}
}