{
  "type": "Feature",
  "properties": {
    "addr:full":"181 Liberty St S Bowmanville ON L1C 3Z2",
    "addr:housenumber":"181",
    "addr:postcode":"l1c 3z2",
    "addr:street":"Liberty St S",
    "iso:country":"CA",
    "sg:address":"181 Liberty St S",
    "sg:city":"Bowmanville",
    "sg:classifiers":[
        {
            "category":"Government",
            "subcategory":"Office",
            "type":"Public Place"
        }
    ],
    "sg:phone":"+1 905 623 3106",
    "sg:postcode":"L1C 3Z2",
    "sg:province":"ON",
    "sg:tags":[
        "association",
        "village"
    ],
    "wof:name":"Clarington Board of Trade",
    "wof:placetype":"venue"
},
  "geometry": {"coordinates":[-78.674987793,43.8989067078],"type":"Point"}
}