{
  "type": "Feature",
  "properties": {
    "iso:country":"CA",
    "sg:address":"RR 2",
    "sg:city":"Picton",
    "sg:classifiers":[
        {
            "category":"Wholesale",
            "subcategory":"Farm Supplies",
            "type":"Manufacturing & Wholesale Goods"
        }
    ],
    "sg:phone":"+1 613 476 2952",
    "sg:postcode":"K0K 2T0",
    "sg:province":"ON",
    "sg:tags":[
        "livestock"
    ],
    "wof:name":"Carson Bay Farms",
    "wof:placetype":"venue"
},
  "geometry": {"coordinates":[-77.13897705079999,44.009223938],"type":"Point"}
}