{
  "type": "Feature",
  "properties": {
    "iso:country":"CA",
    "sg:address":"259 Hollywood Ave",
    "sg:city":"North York",
    "sg:classifiers":[
        {
            "category":"Building & Trades",
            "subcategory":"Construction",
            "type":"Services"
        }
    ],
    "sg:phone":"+1 416 221 1804",
    "sg:postcode":"M2N 3K8",
    "sg:province":"ON",
    "sg:tags":[
        "home",
        "improvement"
    ],
    "wof:name":"J T Stewart General Contr Ltd",
    "wof:placetype":"venue"
},
  "geometry": {"coordinates":[-79.3978805542,43.7686347961],"type":"Point"}
}