{
  "type": "Feature",
  "properties": {
    "addr:full":"49562 Chilliwack Central Rd Chilliwack BC V2P 6H3",
    "addr:postcode":"49562;v2p 6h3",
    "addr:street":"Central Rd",
    "iso:country":"CA",
    "sg:address":"49562 Chilliwack Central Rd",
    "sg:city":"Chilliwack",
    "sg:classifiers":[
        {
            "category":"Retail",
            "subcategory":"Auto Repair",
            "type":"Services"
        }
    ],
    "sg:phone":"+1 604 794 7611",
    "sg:postcode":"V2P 6H3",
    "sg:province":"BC",
    "sg:tags":[
        "repairing",
        "automobile"
    ],
    "wof:name":"Agrimotive Repair Svc",
    "wof:placetype":"venue"
},
  "geometry": {"coordinates":[-121.855011,49.161495],"type":"Point"}
}