{
  "type": "Feature",
  "properties": {
    "addr:full":"113 Elmwood Ave Cambridge ON N1R 4Y7",
    "addr:housenumber":"113",
    "addr:postcode":"n1r 4y7",
    "addr:street":"Elmwood Ave",
    "iso:country":"CA",
    "sg:address":"113 Elmwood Ave",
    "sg:city":"Cambridge",
    "sg:classifiers":[
        {
            "category":"Building & Trades",
            "subcategory":"Construction",
            "type":"Services"
        }
    ],
    "sg:phone":"+1 519 621 0617",
    "sg:postcode":"N1R 4Y7",
    "sg:province":"ON",
    "sg:tags":[
        "plastering",
        "contractor"
    ],
    "wof:name":"St Clair Plastering",
    "wof:placetype":"venue"
},
  "geometry": {"coordinates":[-80.31485000000001,43.375309],"type":"Point"}
}