{
  "type": "Feature",
  "properties": {
    "addr:full":"Little Current ON P0P 1K0",
    "addr:postcode":"p0p 1k0",
    "iso:country":"CA",
    "sg:city":"Little Current",
    "sg:classifiers":[
        {
            "category":"Food & Beverages",
            "subcategory":"Groceries & Convenience Stores",
            "type":"Retail Goods"
        }
    ],
    "sg:phone":"+1 705 368 0057",
    "sg:postcode":"P0P 1K0",
    "sg:province":"ON",
    "wof:name":"K & T Corner Store",
    "wof:placetype":"venue"
},
  "geometry": {"coordinates":[-81.931282,45.97887],"type":"Point"}
}