{
  "type": "Feature",
  "properties": {
    "addr:full":"St-Hermenegilde QC J0B 2W0",
    "addr:postcode":"j0b 2w0",
    "iso:country":"CA",
    "sg:city":"St-Hermenegilde",
    "sg:classifiers":[
        {
            "category":"Organizations",
            "subcategory":"Religious Organization",
            "type":"Services"
        }
    ],
    "sg:phone":"+1 819 849 4596",
    "sg:postcode":"J0B 2W0",
    "sg:province":"QC",
    "sg:tags":[
        "church"
    ],
    "wof:name":"Presbytere St Hermenegilde",
    "wof:placetype":"venue"
},
  "geometry": {"coordinates":[-71.673851,45.105549],"type":"Point"}
}