{
  "type": "Feature",
  "properties": {
    "iso:country":"CA",
    "sg:address":"91 John St",
    "sg:city":"Moncton",
    "sg:classifiers":[
        {
            "category":"Health Services",
            "subcategory":"Doctor",
            "type":"Services"
        }
    ],
    "sg:phone":"+1 506 854 1550",
    "sg:postcode":"E1C 2H3",
    "sg:province":"NB",
    "sg:tags":[
        "dentist"
    ],
    "wof:name":"Reid, Gord DDS",
    "wof:placetype":"venue"
},
  "geometry": {"coordinates":[-64.7898025513,46.0939445496],"type":"Point"}
}