{
  "type": "Feature",
  "properties": {
    "addr:full":"PO Box 176 Flesherton ON N0C 1E0",
    "addr:housenumber":"po",
    "addr:postcode":"n0c 1e0",
    "addr:street":"Box 176",
    "iso:country":"CA",
    "sg:address":"PO Box 176",
    "sg:city":"Flesherton",
    "sg:classifiers":[
        {
            "category":"Organizations",
            "subcategory":"Religious Organization",
            "type":"Services"
        }
    ],
    "sg:phone":"+1 905 725 6598",
    "sg:postcode":"N0C 1E0",
    "sg:province":"ON",
    "sg:tags":[
        "church"
    ],
    "wof:name":"Cedarside Baptist Church",
    "wof:placetype":"venue"
},
  "geometry": {"coordinates":[-80.54986599999999,44.261234],"type":"Point"}
}