{
  "type": "Feature",
  "properties": {
    "addr:full":"4635 Rue Sherbrooke O Westmount QC H3Z 1G2",
    "addr:housenumber":"4635",
    "addr:postcode":"h3z 1g2",
    "addr:street":"Rue Sherbrooke O",
    "iso:country":"CA",
    "sg:address":"4635 Rue Sherbrooke O",
    "sg:city":"Westmount",
    "sg:classifiers":[
        {
            "category":"Health Services",
            "subcategory":"Health Practitioner",
            "type":"Services"
        }
    ],
    "sg:phone":"+1 514 939 0053",
    "sg:postcode":"H3Z 1G2",
    "sg:province":"QC",
    "sg:tags":[
        "psychotherapist"
    ],
    "wof:name":"Aronson, Angela",
    "wof:placetype":"venue"
},
  "geometry": {"coordinates":[-73.60071600000001,45.481571],"type":"Point"}
}