{
  "type": "Feature",
  "properties": {
    "addr:full":"Mascouche QC J7L 1M2",
    "addr:postcode":"j7l 1m2",
    "iso:country":"CA",
    "sg:city":"Mascouche",
    "sg:classifiers":[
        {
            "category":"Building & Trades",
            "subcategory":"Construction",
            "type":"Services"
        }
    ],
    "sg:phone":"+1 450 477 2002",
    "sg:postcode":"J7L 1M2",
    "sg:province":"QC",
    "sg:tags":[
        "repairing",
        "contractor",
        "remodeling",
        "general"
    ],
    "wof:name":"Daniel Renovation Plus",
    "wof:placetype":"venue"
},
  "geometry": {"coordinates":[-73.651482,45.74865],"type":"Point"}
}