{
  "type": "Feature",
  "properties": {
    "iso:country":"CA",
    "sg:address":"1 Rue Saint-Antoine",
    "sg:city":"Metabetchouan-Lac-A-LA-Croix",
    "sg:classifiers":[
        {
            "category":"Restaurant",
            "type":"Food & Drink"
        }
    ],
    "sg:phone":"+1 418 349 3645",
    "sg:postcode":"G8G 1G6",
    "sg:province":"QC",
    "wof:name":"Restaurant Coco-Rico",
    "wof:placetype":"venue"
},
  "geometry": {"coordinates":[-71.8688735962,48.4249916077],"type":"Point"}
}