{
  "type": "Feature",
  "properties": {
    "iso:country":"CA",
    "sg:address":"25 John St E",
    "sg:city":"Waterdown",
    "sg:classifiers":[
        {
            "category":"Building & Trades",
            "subcategory":"Plumbing",
            "type":"Services"
        }
    ],
    "sg:phone":"+1 905 689 6420",
    "sg:postcode":"L0R 2H0",
    "sg:province":"ON",
    "sg:tags":[
        "contractor"
    ],
    "wof:name":"Waterdown Plumbing",
    "wof:placetype":"venue"
},
  "geometry": {"coordinates":[-79.896965,43.336559],"type":"Point"}
}