{
  "type": "Feature",
  "properties": {
    "addr:full":"25 John St E Waterdown ON L0R 2H0",
    "addr:housenumber":"25",
    "addr:postcode":"l0r 2h0",
    "addr:street":"John St E",
    "iso:country":"CA",
    "sg:address":"25 John St E",
    "sg:city":"Waterdown",
    "sg:classifiers":[
        {
            "category":"Building & Trades",
            "subcategory":"Plumbing",
            "type":"Services"
        }
    ],
    "sg:phone":"+1 905 689 6420",
    "sg:postcode":"L0R 2H0",
    "sg:province":"ON",
    "sg:tags":[
        "contractor"
    ],
    "wof:name":"Waterdown Plumbing",
    "wof:placetype":"venue"
},
  "geometry": {"coordinates":[-79.89696499999999,43.336559],"type":"Point"}
}