{
  "type": "Feature",
  "properties": {
    "addr:full":"474 Boul Perron Carleton QC G0C 1J0",
    "addr:housenumber":"474",
    "addr:postcode":"g0c 1j0",
    "addr:street":"Boul Perron",
    "iso:country":"CA",
    "sg:address":"474 Boul Perron",
    "sg:city":"Carleton",
    "sg:classifiers":[
        {
            "category":"Travel",
            "subcategory":"Hotels & Motels",
            "type":"Entertainment"
        }
    ],
    "sg:phone":"+1 418 364 3388",
    "sg:postcode":"G0C 1J0",
    "sg:province":"QC",
    "wof:name":"Manoir Belle Plage",
    "wof:placetype":"venue"
},
  "geometry": {"coordinates":[-66.133972,48.108269],"type":"Point"}
}