{
  "type": "Feature",
  "properties": {
    "addr:full":"1613 St Clair Ave W Toronto ON M6E 1C9",
    "addr:housenumber":"1613",
    "addr:postcode":"m6e 1c9",
    "addr:street":"St Clair Ave W",
    "iso:country":"CA",
    "sg:address":"1613 St Clair Ave W",
    "sg:city":"Toronto",
    "sg:classifiers":[
        {
            "category":"Wholesale",
            "subcategory":"Fruits & Vegetables",
            "type":"Manufacturing & Wholesale Goods"
        }
    ],
    "sg:phone":"+1 416 654 7133",
    "sg:postcode":"M6E 1C9",
    "sg:province":"ON",
    "wof:name":"Meschino Banana CO Ltd",
    "wof:placetype":"venue"
},
  "geometry": {"coordinates":[-79.455444,43.675049],"type":"Point"}
}