{
  "type": "Feature",
  "properties": {
    "addr:full":"130 Perth St Brockville ON K6V 5E3",
    "addr:housenumber":"130",
    "addr:postcode":"k6v 5e3",
    "addr:street":"Perth St",
    "iso:country":"CA",
    "sg:address":"130 Perth St",
    "sg:city":"Brockville",
    "sg:classifiers":[
        {
            "category":"Restaurant",
            "type":"Food & Drink"
        }
    ],
    "sg:phone":"+1 613 342 9521",
    "sg:postcode":"K6V 5E3",
    "sg:province":"ON",
    "wof:name":"Jon's Restaurant",
    "wof:placetype":"venue"
},
  "geometry": {"coordinates":[-75.69309997560001,44.5914306641],"type":"Point"}
}