{
  "type": "Feature",
  "properties": {
    "addr:full":"5515 137 Ave NW Edmonton AB T5A 3L4",
    "addr:housenumber":"5515",
    "addr:postcode":"t5a 3l4",
    "addr:street":"137 Ave Nw",
    "iso:country":"CA",
    "sg:address":"5515 137 Ave NW",
    "sg:city":"Edmonton",
    "sg:classifiers":[
        {
            "category":"Restaurant",
            "type":"Food & Drink"
        }
    ],
    "sg:phone":"+1 780 473 6370",
    "sg:postcode":"T5A 3L4",
    "sg:province":"AB",
    "wof:name":"Boston Pizza",
    "wof:placetype":"venue"
},
  "geometry": {"coordinates":[-113.425857544,53.599193573],"type":"Point"}
}