{
  "type": "Feature",
  "properties": {
    "addr:full":"866 Riverside Rd Belliveau Cove NS B0W 1J0",
    "addr:housenumber":"866",
    "addr:postcode":"b0w 1j0",
    "addr:street":"Riverside Rd Belliveau Cove",
    "iso:country":"CA",
    "sg:address":"866 Riverside Rd",
    "sg:city":"Belliveau Cove",
    "sg:classifiers":[
        {
            "category":"Wholesale",
            "subcategory":"Seafood",
            "type":"Manufacturing & Wholesale Goods"
        }
    ],
    "sg:phone":"+1 902 837 5567",
    "sg:postcode":"B0W 1J0",
    "sg:province":"NS",
    "wof:name":"Raymond Seafood",
    "wof:placetype":"venue"
},
  "geometry": {"coordinates":[-66.06134,44.386734],"type":"Point"}
}