{
  "type": "Feature",
  "properties": {
    "addr:full":"6082 32nd Side Rd Acton ON L7J 2L7",
    "addr:housenumber":"6082",
    "addr:postcode":"l7j 2l7",
    "addr:street":"32Nd Side Rd",
    "iso:country":"CA",
    "sg:address":"6082 32nd Side Rd",
    "sg:city":"Acton",
    "sg:classifiers":[
        {
            "category":"Wholesale",
            "subcategory":"Auto Parts",
            "type":"Manufacturing & Wholesale Goods"
        }
    ],
    "sg:phone":"+1 519 853 3100",
    "sg:postcode":"L7J 2L7",
    "sg:province":"ON",
    "sg:tags":[
        "automobile",
        "rebuilt"
    ],
    "wof:name":"Bray Auto/Truck Recyclers Inc",
    "wof:placetype":"venue"
},
  "geometry": {"coordinates":[-80.084526,43.630032],"type":"Point"}
}