{
  "type": "Feature",
  "properties": {
    "iso:country":"CA",
    "sg:city":"Neilburg",
    "sg:classifiers":[
        {
            "category":"Professional",
            "type":"Services"
        }
    ],
    "sg:phone":"+1 306 823 4722",
    "sg:postcode":"S0M 2C0",
    "sg:province":"SK",
    "sg:tags":[
        "establishment",
        "oil",
        "well"
    ],
    "wof:name":"Silverman Oil Field Svc Ltd",
    "wof:placetype":"venue"
},
  "geometry": {"coordinates":[-109.631576538,52.8418159485],"type":"Point"}
}