{
  "type": "Feature",
  "properties": {
    "addr:full":"Edmonton AB T5X 3N5",
    "addr:postcode":"t5x 3n5",
    "iso:country":"CA",
    "sg:city":"Edmonton",
    "sg:classifiers":[
        {
            "category":"Health Services",
            "subcategory":"Doctor",
            "type":"Services"
        }
    ],
    "sg:phone":"+1 780 457 2227",
    "sg:postcode":"T5X 3N5",
    "sg:province":"AB",
    "sg:tags":[
        "dentist"
    ],
    "wof:name":"Ng, Richard S C DDS",
    "wof:placetype":"venue"
},
  "geometry": {"coordinates":[-113.51638,53.613171],"type":"Point"}
}