{
  "type": "Feature",
  "properties": {
    "addr:full":"633 Main St Glace Bay NS B1A 6J3",
    "addr:housenumber":"633",
    "addr:postcode":"b1a 6j3",
    "addr:street":"Main St",
    "iso:country":"CA",
    "sg:address":"633 Main St",
    "sg:city":"Glace Bay",
    "sg:classifiers":[
        {
            "category":"Government",
            "subcategory":"Office",
            "type":"Public Place"
        }
    ],
    "sg:phone":"+1 902 842 2655",
    "sg:postcode":"B1A 6J3",
    "sg:province":"NS",
    "wof:name":"Glace Bay Human Resources Ctr",
    "wof:placetype":"venue"
},
  "geometry": {"coordinates":[-59.95826,46.196754],"type":"Point"}
}