{
  "type": "Feature",
  "properties": {
    "addr:full":"252 North Park St Brantford ON N3R 4L1",
    "addr:housenumber":"252",
    "addr:postcode":"n3r 4l1",
    "addr:street":"North Park St",
    "iso:country":"CA",
    "sg:address":"252 North Park St",
    "sg:city":"Brantford",
    "sg:classifiers":[
        {
            "category":"Organizations",
            "subcategory":"Religious Organization",
            "type":"Services"
        }
    ],
    "sg:phone":"+1 519 759 7362",
    "sg:postcode":"N3R 4L1",
    "sg:province":"ON",
    "sg:tags":[
        "church"
    ],
    "wof:name":"Bethel Park Bible Chapel",
    "wof:placetype":"venue"
},
  "geometry": {"coordinates":[-80.263443,43.166664],"type":"Point"}
}