{
  "type": "Feature",
  "properties": {
    "addr:full":"1310 Rte Marie-Victorin Saint-Nicolas QC G7A 4G1",
    "addr:housenumber":"1310",
    "addr:postcode":"g7a 4g1",
    "addr:street":"Rte Marie-Victorin",
    "iso:country":"CA",
    "sg:address":"1310 Rte Marie-Victorin",
    "sg:city":"Saint-Nicolas",
    "sg:classifiers":[
        {
            "category":"Wholesale",
            "subcategory":"Construction Materials",
            "type":"Manufacturing & Wholesale Goods"
        }
    ],
    "sg:phone":"+1 418 831 1226",
    "sg:postcode":"G7A 4G1",
    "sg:province":"QC",
    "sg:tags":[
        "sand",
        "gravel"
    ],
    "wof:name":"A C Langlois & Freres Inc",
    "wof:placetype":"venue"
},
  "geometry": {"coordinates":[-71.390564,46.702213],"type":"Point"}
}