{
  "type": "Feature",
  "properties": {
    "addr:full":"Surrey BC V3S 8P7",
    "addr:postcode":"v3s 8p7",
    "iso:country":"CA",
    "sg:city":"Surrey",
    "sg:classifiers":[
        {
            "category":"Manufacturing",
            "subcategory":"Signs",
            "type":"Manufacturing & Wholesale Goods"
        }
    ],
    "sg:phone":"+1 604 534 2484",
    "sg:postcode":"V3S 8P7",
    "sg:province":"BC",
    "wof:name":"Signway",
    "wof:placetype":"venue"
},
  "geometry": {"coordinates":[-122.68291473399999,49.1022758484],"type":"Point"}
}