{
  "type": "Feature",
  "properties": {
    "addr:full":"312 Manitoba Schreiber ON P0T 2S0",
    "addr:housenumber":"312",
    "addr:postcode":"p0t 2s0",
    "addr:street":"Manitoba",
    "iso:country":"CA",
    "sg:address":"312 Manitoba",
    "sg:city":"Schreiber",
    "sg:classifiers":[
        {
            "category":"Education",
            "subcategory":"Special Training",
            "type":"Public Place"
        }
    ],
    "sg:phone":"+1 807 824 3164",
    "sg:postcode":"P0T 2S0",
    "sg:province":"ON",
    "sg:tags":[
        "reading",
        "instruction",
        "improvement"
    ],
    "wof:name":"Literacy Program",
    "wof:placetype":"venue"
},
  "geometry": {"coordinates":[-87.266312,48.808399],"type":"Point"}
}