{
  "type": "Feature",
  "properties": {
    "addr:full":"385 Springbank Ave Woodstock ON N4T 1R3",
    "addr:housenumber":"385",
    "addr:postcode":"n4t 1r3",
    "addr:street":"Springbank Ave",
    "iso:country":"CA",
    "sg:address":"385 Springbank Ave",
    "sg:city":"Woodstock",
    "sg:classifiers":[
        {
            "category":"Shopping",
            "type":"Retail Goods"
        }
    ],
    "sg:phone":"+1 519 539 0111",
    "sg:postcode":"N4T 1R3",
    "sg:province":"ON",
    "sg:tags":[
        "pet",
        "food",
        "supply"
    ],
    "wof:name":"Global Pet Foods",
    "wof:placetype":"venue"
},
  "geometry": {"coordinates":[-80.7365188599,43.1470680237],"type":"Point"}
}