{
  "type": "Feature",
  "properties": {
    "addr:full":"15911 110B Ave NW Edmonton AB T5P 1J5",
    "addr:housenumber":"15911",
    "addr:postcode":"t5p 1j5",
    "addr:street":"110B Ave Nw",
    "iso:country":"CA",
    "sg:address":"15911 110B Ave NW",
    "sg:city":"Edmonton",
    "sg:classifiers":[
        {
            "category":"Building & Trades",
            "subcategory":"Construction",
            "type":"Services"
        }
    ],
    "sg:phone":"+1 780 484 9890",
    "sg:postcode":"T5P 1J5",
    "sg:province":"AB",
    "wof:name":"Celestial Building Systems Ltd",
    "wof:placetype":"venue"
},
  "geometry": {"coordinates":[-113.595032,53.558132],"type":"Point"}
}