{
  "type": "Feature",
  "properties": {
    "addr:full":"704 Brealey Dr Peterborough ON K9K 2M7",
    "addr:housenumber":"704",
    "addr:postcode":"k9k 2m7",
    "addr:street":"Brealey Dr",
    "iso:country":"CA",
    "sg:address":"704 Brealey Dr",
    "sg:city":"Peterborough",
    "sg:classifiers":[
        {
            "category":"Shopping",
            "type":"Retail Goods"
        }
    ],
    "sg:phone":"+1 705 749 9778",
    "sg:postcode":"K9K 2M7",
    "sg:province":"ON",
    "sg:tags":[
        "cosmetic",
        "perfume"
    ],
    "wof:name":"Avon Canada Inc",
    "wof:placetype":"venue"
},
  "geometry": {"coordinates":[-78.3690567017,44.2698402405],"type":"Point"}
}