{
  "type": "Feature",
  "properties": {
    "addr:full":"33 Rue Canusa Stanstead QC J0B 3E2",
    "addr:housenumber":"33",
    "addr:postcode":"j0b 3e2",
    "addr:street":"Rue Canusa",
    "iso:country":"CA",
    "sg:address":"33 Rue Canusa",
    "sg:city":"Stanstead",
    "sg:classifiers":[
        {
            "category":"Wholesale",
            "subcategory":"Machinery & Supplies",
            "type":"Manufacturing & Wholesale Goods"
        }
    ],
    "sg:phone":"+1 819 876 2722",
    "sg:postcode":"J0B 3E2",
    "sg:province":"QC",
    "sg:tags":[
        "sandblasting",
        "contractor"
    ],
    "wof:name":"Derusha Supply",
    "wof:placetype":"venue"
},
  "geometry": {"coordinates":[-72.135498,45.005943],"type":"Point"}
}