{
  "type": "Feature",
  "properties": {
    "addr:full":"1459 Regent Ave W Winnipeg MB R2C 3B2",
    "addr:housenumber":"1459",
    "addr:postcode":"r2c 3b2",
    "addr:street":"Regent Ave W",
    "iso:country":"CA",
    "sg:address":"1459 Regent Ave W",
    "sg:city":"Winnipeg",
    "sg:classifiers":[
        {
            "category":"Autos & Motor Vehicles",
            "subcategory":"Automobile Sales",
            "type":"Retail Goods"
        }
    ],
    "sg:phone":"+1 204 661 8181",
    "sg:postcode":"R2C 3B2",
    "sg:province":"MB",
    "sg:tags":[
        "car",
        "dealer"
    ],
    "wof:name":"Park Pontiac Buick Gmc Ltd",
    "wof:placetype":"venue"
},
  "geometry": {"coordinates":[-97.048599,49.895576],"type":"Point"}
}