{
  "type": "Feature",
  "properties": {
    "iso:country":"CA",
    "sg:address":"31 5th Ave E",
    "sg:city":"Vancouver",
    "sg:classifiers":[
        {
            "category":"Retail",
            "subcategory":"Portrait Studio",
            "type":"Services"
        }
    ],
    "sg:phone":"+1 604 873 4454",
    "sg:postcode":"V5T 1G7",
    "sg:province":"BC",
    "sg:tags":[
        "photographer"
    ],
    "wof:name":"Bryan Ward Photography Ltd",
    "wof:placetype":"venue"
},
  "geometry": {"coordinates":[-123.10409545900001,49.2666130066],"type":"Point"}
}