{
  "type": "Feature",
  "properties": {
    "iso:country":"CA",
    "sg:address":"7423 Highway 26",
    "sg:city":"Stayner",
    "sg:classifiers":[
        {
            "category":"Restaurant",
            "type":"Food & Drink"
        }
    ],
    "sg:phone":"+1 705 428 6995",
    "sg:postcode":"L0M 1S0",
    "sg:province":"ON",
    "wof:name":"Stayner Burger Restaurant",
    "wof:placetype":"venue"
},
  "geometry": {"coordinates":[-80.0894699097,44.4197654724],"type":"Point"}
}