{
  "type": "Feature",
  "properties": {
    "addr:full":"66 Rue DE LA Gauchetiere O Montreal QC H2Z 1C1",
    "addr:housenumber":"66",
    "addr:postcode":"h2z 1c1",
    "addr:street":"Rue De La Gauchetiere O",
    "iso:country":"CA",
    "sg:address":"66 Rue DE LA Gauchetiere O",
    "sg:city":"Montreal",
    "sg:classifiers":[
        {
            "category":"Shopping",
            "subcategory":"Books",
            "type":"Retail Goods"
        }
    ],
    "sg:phone":"+1 514 874 1552",
    "sg:postcode":"H2Z 1C1",
    "sg:province":"QC",
    "sg:tags":[
        "dealer"
    ],
    "wof:name":"Tin Tin Holding Inc",
    "wof:placetype":"venue"
},
  "geometry": {"coordinates":[-73.559219,45.508877],"type":"Point"}
}