{
  "type": "Feature",
  "properties": {
    "addr:full":"175 Rue Principale # 29 Cowansville QC J2K 3L9",
    "addr:housenumber":"175",
    "addr:postcode":"j2k 3l9",
    "addr:street":"Rue Principale # 29",
    "iso:country":"CA",
    "sg:address":"175 Rue Principale # 29",
    "sg:city":"Cowansville",
    "sg:classifiers":[
        {
            "category":"Health Services",
            "subcategory":"Optometrist",
            "type":"Services"
        }
    ],
    "sg:phone":"+1 450 263 1162",
    "sg:postcode":"J2K 3L9",
    "sg:province":"QC",
    "wof:name":"Savard, Marc OD",
    "wof:placetype":"venue"
},
  "geometry": {"coordinates":[-72.745193,45.208084],"type":"Point"}
}