{
  "type": "Feature",
  "properties": {
    "addr:full":"300 Henderson Hwy Winnipeg MB R2L 1M6",
    "addr:housenumber":"300",
    "addr:postcode":"r2l 1m6",
    "addr:street":"Henderson Hwy",
    "iso:country":"CA",
    "sg:address":"300 Henderson Hwy",
    "sg:city":"Winnipeg",
    "sg:classifiers":[
        {
            "category":"Health Services",
            "subcategory":"Optometrist",
            "type":"Services"
        }
    ],
    "sg:phone":"+1 204 669 4203",
    "sg:postcode":"R2L 1M6",
    "sg:province":"MB",
    "wof:name":"Sullivan Optical Inc",
    "wof:placetype":"venue"
},
  "geometry": {"coordinates":[-97.114189,49.916512],"type":"Point"}
}