{
  "type": "Feature",
  "properties": {
    "addr:full":"3624 Boul Poirier Saint-Laurent QC H4R 2J5",
    "addr:housenumber":"3624",
    "addr:postcode":"h4r 2j5",
    "addr:street":"Boul Poirier",
    "iso:country":"CA",
    "sg:address":"3624 Boul Poirier",
    "sg:city":"Saint-Laurent",
    "sg:classifiers":[
        {
            "category":"Wholesale",
            "subcategory":"Machinery & Supplies",
            "type":"Manufacturing & Wholesale Goods"
        }
    ],
    "sg:phone":"+1 514 745 7040",
    "sg:postcode":"H4R 2J5",
    "sg:province":"QC",
    "sg:tags":[
        "equipment",
        "plating"
    ],
    "wof:name":"Produits Chimiques Mac Dermid",
    "wof:placetype":"venue"
},
  "geometry": {"coordinates":[-73.7188415527,45.4989738464],"type":"Point"}
}