{
  "type": "Feature",
  "properties": {
    "addr:full":"545 Ch Witty Sainte-Christine QC J0H 1H0",
    "addr:housenumber":"545",
    "addr:postcode":"j0h 1h0",
    "addr:street":"Ch Witty",
    "iso:country":"CA",
    "sg:address":"545 Ch Witty",
    "sg:city":"Sainte-Christine",
    "sg:classifiers":[
        {
            "category":"Shopping",
            "type":"Retail Goods"
        }
    ],
    "sg:phone":"+1 819 858 2795",
    "sg:postcode":"J0H 1H0",
    "sg:province":"QC",
    "sg:tags":[
        "awning",
        "canopy"
    ],
    "wof:name":"Canevas Plus",
    "wof:placetype":"venue"
},
  "geometry": {"coordinates":[-72.39738464360001,45.5962295532],"type":"Point"}
}