{
  "type": "Feature",
  "properties": {
    "iso:country":"CA",
    "sg:address":"6010 50 Ave",
    "sg:city":"Vegreville",
    "sg:classifiers":[
        {
            "category":"Wholesale",
            "subcategory":"Electrical",
            "type":"Manufacturing & Wholesale Goods"
        }
    ],
    "sg:phone":"+1 780 632 6000",
    "sg:postcode":"T9C 1N6",
    "sg:province":"AB",
    "sg:tags":[
        "fire",
        "equipment",
        "protection"
    ],
    "wof:name":"Veg Fire & Safety",
    "wof:placetype":"venue"
},
  "geometry": {"coordinates":[-112.065170288,53.4998016357],"type":"Point"}
}