{
  "type": "Feature",
  "properties": {
    "addr:full":"76 Oakhaven Dr Scarborough ON M1V 1X9",
    "addr:housenumber":"76",
    "addr:postcode":"m1v 1x9",
    "addr:street":"Oakhaven Dr",
    "iso:country":"CA",
    "sg:address":"76 Oakhaven Dr",
    "sg:city":"Scarborough",
    "sg:classifiers":[
        {
            "category":"Home & Garden",
            "subcategory":"Carpets & Floor Coverings",
            "type":"Retail Goods"
        }
    ],
    "sg:phone":"+1 416 321 9782",
    "sg:postcode":"M1V 1X9",
    "sg:province":"ON",
    "sg:tags":[
        "dealer",
        "rug"
    ],
    "wof:name":"Lee's Flooring & Blinds",
    "wof:placetype":"venue"
},
  "geometry": {"coordinates":[-79.283569,43.823376],"type":"Point"}
}