{
  "type": "Feature",
  "properties": {
    "addr:full":"23 Woodward Ave Blind River ON P0R 1B0",
    "addr:housenumber":"23",
    "addr:postcode":"p0r 1b0",
    "addr:street":"Woodward Ave",
    "iso:country":"CA",
    "sg:address":"23 Woodward Ave",
    "sg:city":"Blind River",
    "sg:classifiers":[
        {
            "category":"Shopping",
            "subcategory":"Stationery & Office Supplies",
            "type":"Retail Goods"
        }
    ],
    "sg:phone":"+1 705 356 7424",
    "sg:postcode":"P0R 1B0",
    "sg:province":"ON",
    "sg:tags":[
        "stationer"
    ],
    "wof:name":"Unicorn Stationery & Gifts",
    "wof:placetype":"venue"
},
  "geometry": {"coordinates":[-82.9539260864,46.1866340637],"type":"Point"}
}