{
  "type": "Feature",
  "properties": {
    "addr:full":"592 Niagara St Welland ON L3C 1L8",
    "addr:housenumber":"592",
    "addr:postcode":"l3c 1l8",
    "addr:street":"Niagara St",
    "iso:country":"CA",
    "sg:address":"592 Niagara St",
    "sg:city":"Welland",
    "sg:classifiers":[
        {
            "category":"Autos & Motor Vehicles",
            "subcategory":"Auto Supplies",
            "type":"Retail Goods"
        }
    ],
    "sg:phone":"+1 905 732 2435",
    "sg:postcode":"L3C 1L8",
    "sg:province":"ON",
    "sg:tags":[
        "tire"
    ],
    "wof:name":"Groff Tire & Battery Ltd",
    "wof:placetype":"venue"
},
  "geometry": {"coordinates":[-79.25102200000001,43.007496],"type":"Point"}
}