{
  "type": "Feature",
  "properties": {
    "addr:full":"366 Yorston St Williams Lake BC V2G 4J5",
    "addr:housenumber":"366",
    "addr:postcode":"v2g 4j5",
    "addr:street":"Yorston St",
    "iso:country":"CA",
    "sg:address":"366 Yorston St",
    "sg:city":"Williams Lake",
    "sg:classifiers":[
        {
            "category":"Shopping",
            "subcategory":"Pharmacy",
            "type":"Retail Goods"
        }
    ],
    "sg:phone":"+1 250 398 8177",
    "sg:postcode":"V2G 4J5",
    "sg:province":"BC",
    "wof:name":"Kornak & Hamm's Pharmacy",
    "wof:placetype":"venue"
},
  "geometry": {"coordinates":[-122.14091500000001,52.126743],"type":"Point"}
}