{
  "type": "Feature",
  "properties": {
    "addr:full":"90 Spring St Summerside PE C1N 3E4",
    "addr:housenumber":"90",
    "addr:postcode":"c1n 3e4",
    "addr:street":"Spring St",
    "iso:country":"CA",
    "sg:address":"90 Spring St",
    "sg:city":"Summerside",
    "sg:classifiers":[
        {
            "category":"Organizations",
            "subcategory":"Religious Organization",
            "type":"Services"
        }
    ],
    "sg:phone":"+1 902 436 3155",
    "sg:postcode":"C1N 3E4",
    "sg:province":"PE",
    "sg:tags":[
        "church"
    ],
    "wof:name":"Trinity United Church",
    "wof:placetype":"venue"
},
  "geometry": {"coordinates":[-63.7893066406,46.3944816589],"type":"Point"}
}