{
  "type": "Feature",
  "properties": {
    "addr:full":"636 36 Ave NE Calgary AB T2E 2L7",
    "addr:postcode":"t2e 2l7",
    "addr:street":"636 36 Ave Ne",
    "iso:country":"CA",
    "sg:address":"636 36 Ave NE",
    "sg:city":"Calgary",
    "sg:classifiers":[
        {
            "category":"Manufacturing",
            "subcategory":"Metals",
            "type":"Manufacturing & Wholesale Goods"
        }
    ],
    "sg:phone":"+1 403 295 9676",
    "sg:postcode":"T2E 2L7",
    "sg:province":"AB",
    "sg:tags":[
        "paint"
    ],
    "wof:name":"Bellare Industrial Coatings",
    "wof:placetype":"venue"
},
  "geometry": {"coordinates":[-114.049835,51.085175],"type":"Point"}
}