{
  "type": "Feature",
  "properties": {
    "iso:country":"CA",
    "sg:city":"Peterborough",
    "sg:classifiers":[
        {
            "category":"Real Estate",
            "subcategory":"Real Estate Operator",
            "type":"Services"
        }
    ],
    "sg:phone":"+1 705 745 6887",
    "sg:postcode":"K9J 7G8",
    "sg:province":"ON",
    "sg:tags":[
        "apartment"
    ],
    "wof:name":"Talwood Property Management",
    "wof:placetype":"venue"
},
  "geometry": {"coordinates":[-78.346031189,44.293964386],"type":"Point"}
}