{
  "type": "Feature",
  "properties": {
    "addr:full":"Sainte-Madeleine QC J0H 1S0",
    "addr:postcode":"j0h 1s0",
    "iso:country":"CA",
    "sg:city":"Sainte-Madeleine",
    "sg:classifiers":[
        {
            "category":"Organizations",
            "subcategory":"Religious Organization",
            "type":"Services"
        }
    ],
    "sg:phone":"+1 450 795 3335",
    "sg:postcode":"J0H 1S0",
    "sg:province":"QC",
    "sg:tags":[
        "church"
    ],
    "wof:name":"Presbytere Ste-Madeleine",
    "wof:placetype":"venue"
},
  "geometry": {"coordinates":[-73.059189,45.586239],"type":"Point"}
}