{
  "type": "Feature",
  "properties": {
    "iso:country":"CA",
    "sg:address":"225 Railway Ave",
    "sg:city":"Southey",
    "sg:classifiers":[
        {
            "category":"Retail",
            "subcategory":"Auto Repair",
            "type":"Services"
        }
    ],
    "sg:phone":"+1 306 726 2160",
    "sg:postcode":"S0G 4P0",
    "sg:province":"SK",
    "sg:tags":[
        "repairing",
        "automobile"
    ],
    "wof:name":"D & S General Repair",
    "wof:placetype":"venue"
},
  "geometry": {"coordinates":[-104.496757507,50.9380760193],"type":"Point"}
}