{
  "type": "Feature",
  "properties": {
    "addr:full":"333 Rue Riverside Saint-Lambert QC J4P 1A9",
    "addr:housenumber":"333",
    "addr:postcode":"j4p 1a9",
    "addr:street":"Rue Riverside",
    "iso:country":"CA",
    "sg:address":"333 Rue Riverside",
    "sg:city":"Saint-Lambert",
    "sg:classifiers":[
        {
            "category":"Real Estate",
            "subcategory":"Real Estate Operator",
            "type":"Services"
        }
    ],
    "sg:phone":"+1 450 671 6921",
    "sg:postcode":"J4P 1A9",
    "sg:province":"QC",
    "sg:tags":[
        "apartment"
    ],
    "wof:name":"San Soucy Enr",
    "wof:placetype":"venue"
},
  "geometry": {"coordinates":[-73.517349,45.504017],"type":"Point"}
}