{
  "type": "Feature",
  "properties": {
    "addr:full":"353 Spadina Ave Toronto ON M5T 2G3",
    "addr:housenumber":"353",
    "addr:postcode":"m5t 2g3",
    "addr:street":"Spadina Ave",
    "iso:country":"CA",
    "sg:address":"353 Spadina Ave",
    "sg:city":"Toronto",
    "sg:classifiers":[
        {
            "category":"Restaurant",
            "type":"Food & Drink"
        }
    ],
    "sg:phone":"+1 416 596 8787",
    "sg:postcode":"M5T 2G3",
    "sg:province":"ON",
    "wof:name":"New Sky Garden Restaurant",
    "wof:placetype":"venue"
},
  "geometry": {"coordinates":[-79.39872,43.655418],"type":"Point"}
}