{
  "type": "Feature",
  "properties": {
    "addr:full":"7995 17E Av Montreal QC H1Z 3R2",
    "addr:housenumber":"7995",
    "addr:postcode":"h1z 3r2",
    "addr:street":"17E Av",
    "iso:country":"CA",
    "sg:address":"7995 17E Av",
    "sg:city":"Montreal",
    "sg:classifiers":[
        {
            "category":"Wholesale",
            "subcategory":"Machinery & Supplies",
            "type":"Manufacturing & Wholesale Goods"
        }
    ],
    "sg:phone":"+1 514 376 3050",
    "sg:postcode":"H1Z 3R2",
    "sg:province":"QC",
    "sg:tags":[
        "hoist"
    ],
    "wof:name":"Leger Hoist Equipment Inc",
    "wof:placetype":"venue"
},
  "geometry": {"coordinates":[-73.6048812866,45.5674972534],"type":"Point"}
}