{
  "type": "Feature",
  "properties": {
    "addr:full":"1644 Bayview Ave Toronto ON M4G 3C2",
    "addr:housenumber":"1644",
    "addr:postcode":"m4g 3c2",
    "addr:street":"Bayview Ave",
    "iso:country":"CA",
    "sg:address":"1644 Bayview Ave",
    "sg:city":"Toronto",
    "sg:classifiers":[
        {
            "category":"Personal",
            "type":"Services"
        }
    ],
    "sg:phone":"+1 416 480 9848",
    "sg:postcode":"M4G 3C2",
    "sg:province":"ON",
    "sg:tags":[
        "program",
        "physical",
        "exercise",
        "fitness"
    ],
    "wof:name":"Personal Training Plus",
    "wof:placetype":"venue"
},
  "geometry": {"coordinates":[-79.375839,43.707073],"type":"Point"}
}