{
  "type": "Feature",
  "properties": {
    "addr:full":"178 Rue Saint-Rene Rimouski QC G5L 4V2",
    "addr:housenumber":"178",
    "addr:postcode":"g5l 4v2",
    "addr:street":"Rue Saint-Rene",
    "iso:country":"CA",
    "sg:address":"178 Rue Saint-Rene",
    "sg:city":"Rimouski",
    "sg:classifiers":[
        {
            "category":"Retail",
            "subcategory":"Repair Shop",
            "type":"Services"
        }
    ],
    "sg:phone":"+1 418 724 8819",
    "sg:postcode":"G5L 4V2",
    "sg:province":"QC",
    "sg:tags":[
        "tool",
        "parts"
    ],
    "wof:name":"Service Yves Le Brun Enr",
    "wof:placetype":"venue"
},
  "geometry": {"coordinates":[-68.52544399999999,48.441662],"type":"Point"}
}