{
  "type": "Feature",
  "properties": {
    "iso:country":"CA",
    "sg:address":"423 Donlands Ave",
    "sg:city":"East York",
    "sg:classifiers":[
        {
            "category":"Shopping",
            "subcategory":"Clothing, Apparel, & Fashions",
            "type":"Retail Goods"
        }
    ],
    "sg:phone":"+1 416 422 5472",
    "sg:postcode":"M4J 3S2",
    "sg:province":"ON",
    "sg:tags":[
        "tailor"
    ],
    "wof:name":"Stevens Custom Tailors",
    "wof:placetype":"venue"
},
  "geometry": {"coordinates":[-79.34279632569999,43.694442749],"type":"Point"}
}