{
  "type": "Feature",
  "properties": {
    "addr:full":"Montreal QC H3T 1Y9",
    "addr:postcode":"h3t 1y9",
    "iso:country":"CA",
    "sg:city":"Montreal",
    "sg:classifiers":[
        {
            "category":"Health Services",
            "subcategory":"Doctor",
            "type":"Services"
        }
    ],
    "sg:phone":"+1 514 733 3459",
    "sg:postcode":"H3T 1Y9",
    "sg:province":"QC",
    "sg:tags":[
        "dentist"
    ],
    "wof:name":"Dulude, Josee-Anne DDS",
    "wof:placetype":"venue"
},
  "geometry": {"coordinates":[-73.62464900000001,45.497246],"type":"Point"}
}