{
  "type": "Feature",
  "properties": {
    "addr:full":"3345 Boul Des Entreprises Terrebonne QC J6X 4J9",
    "addr:housenumber":"3345",
    "addr:postcode":"j6x 4j9",
    "addr:street":"Boul Des Entreprises",
    "iso:country":"CA",
    "sg:address":"3345 Boul Des Entreprises",
    "sg:city":"Terrebonne",
    "sg:classifiers":[
        {
            "category":"Manufacturing",
            "subcategory":"Tools & Machinery",
            "type":"Manufacturing & Wholesale Goods"
        }
    ],
    "sg:phone":"+1 450 477 7795",
    "sg:postcode":"J6X 4J9",
    "sg:province":"QC",
    "sg:tags":[
        "electric",
        "cabinet"
    ],
    "wof:name":"Metamax Inc",
    "wof:placetype":"venue"
},
  "geometry": {"coordinates":[-73.687248,45.72575],"type":"Point"}
}