{
  "type": "Feature",
  "properties": {
    "addr:full":"Nanaimo BC V9R 2T5",
    "addr:postcode":"v9r 2t5",
    "iso:country":"CA",
    "sg:city":"Nanaimo",
    "sg:classifiers":[
        {
            "category":"Banks & Credit Unions",
            "subcategory":"Investment Brokerage",
            "type":"Services"
        }
    ],
    "sg:phone":"+1 250 754 8008",
    "sg:postcode":"V9R 2T5",
    "sg:province":"BC",
    "sg:tags":[
        "funds",
        "mutual"
    ],
    "wof:name":"Aic Group of Funds",
    "wof:placetype":"venue"
},
  "geometry": {"coordinates":[-123.94116200000001,49.164806],"type":"Point"}
}