{
  "type": "Feature",
  "properties": {
    "addr:full":"193 Gordon St Smooth Rock Falls ON P0L 2B0",
    "addr:housenumber":"193",
    "addr:postcode":"p0l 2b0",
    "addr:street":"Gordon St",
    "iso:country":"CA",
    "sg:address":"193 Gordon St",
    "sg:city":"Smooth Rock Falls",
    "sg:classifiers":[
        {
            "category":"Organizations",
            "subcategory":"Professional Association",
            "type":"Services"
        }
    ],
    "sg:phone":"+1 705 338 2601",
    "sg:postcode":"P0L 2B0",
    "sg:province":"ON",
    "wof:name":"Chevalier DE Colomb Conseil",
    "wof:placetype":"venue"
},
  "geometry": {"coordinates":[-81.621765,49.278511],"type":"Point"}
}