{
  "type": "Feature",
  "properties": {
    "addr:full":"2176 Victoria Ave E Regina SK S4N 7B9",
    "addr:housenumber":"2176",
    "addr:postcode":"s4n 7b9",
    "addr:street":"Victoria Ave E",
    "iso:country":"CA",
    "sg:address":"2176 Victoria Ave E",
    "sg:city":"Regina",
    "sg:classifiers":[
        {
            "category":"Banks & Credit Unions",
            "subcategory":"Bank",
            "type":"Services"
        }
    ],
    "sg:phone":"+1 306 546 5801",
    "sg:postcode":"S4N 7B9",
    "sg:province":"SK",
    "sg:tags":[
        "loan",
        "real estate"
    ],
    "wof:name":"Citifinancial",
    "wof:placetype":"venue"
},
  "geometry": {"coordinates":[-104.552505493,50.4476852417],"type":"Point"}
}