{
  "type": "Feature",
  "properties": {
    "addr:full":"3344 Boul Henri-Bourassa E Montreal-Nord QC H1H 1H5",
    "addr:housenumber":"3344",
    "addr:postcode":"h1h 1h5",
    "addr:street":"Boul Henri-Bourassa E",
    "iso:country":"CA",
    "sg:address":"3344 Boul Henri-Bourassa E",
    "sg:city":"Montreal-Nord",
    "sg:classifiers":[
        {
            "category":"Professional",
            "subcategory":"Accounting & Tax Preparation",
            "type":"Services"
        }
    ],
    "sg:phone":"+1 514 322 9651",
    "sg:postcode":"H1H 1H5",
    "sg:province":"QC",
    "sg:tags":[
        "bookkeeping",
        "system",
        "general"
    ],
    "wof:name":"Gestion Gc",
    "wof:placetype":"venue"
},
  "geometry": {"coordinates":[-73.649033,45.586212],"type":"Point"}
}