{
  "type": "Feature",
  "properties": {
    "addr:full":"210 Front St Sturgeon Falls ON P2B 2J3",
    "addr:housenumber":"210",
    "addr:postcode":"p2b 2j3",
    "addr:street":"Front St",
    "iso:country":"CA",
    "sg:address":"210 Front St",
    "sg:city":"Sturgeon Falls",
    "sg:classifiers":[
        {
            "category":"Restaurant",
            "type":"Food & Drink"
        }
    ],
    "sg:phone":"+1 705 753 4780",
    "sg:postcode":"P2B 2J3",
    "sg:province":"ON",
    "wof:name":"China House",
    "wof:placetype":"venue"
},
  "geometry": {"coordinates":[-79.916527,46.365814],"type":"Point"}
}