{
  "type": "Feature",
  "properties": {
    "addr:full":"Cap-DE-LA-Madeleine QC G8T 6Y3",
    "addr:postcode":"g8t 6y3",
    "iso:country":"CA",
    "sg:city":"Cap-DE-LA-Madeleine",
    "sg:classifiers":[
        {
            "category":"Retail",
            "subcategory":"Auto Repair",
            "type":"Services"
        }
    ],
    "sg:phone":"+1 819 373 4221",
    "sg:postcode":"G8T 6Y3",
    "sg:province":"QC",
    "sg:tags":[
        "repairing",
        "automobile"
    ],
    "wof:name":"Garage Des Ponts",
    "wof:placetype":"venue"
},
  "geometry": {"coordinates":[-72.5355453491,46.3722801208],"type":"Point"}
}