{
  "type": "Feature",
  "properties": {
    "addr:full":"1742 Centennial Cres North Battleford SK S9A 3J3",
    "addr:housenumber":"1742",
    "addr:postcode":"s9a 3j3",
    "addr:street":"Centennial Cres",
    "iso:country":"CA",
    "sg:address":"1742 Centennial Cres",
    "sg:city":"North Battleford",
    "sg:classifiers":[
        {
            "category":"Freight",
            "type":"Transportation"
        }
    ],
    "sg:phone":"+1 306 445 4604",
    "sg:postcode":"S9A 3J3",
    "sg:province":"SK",
    "sg:tags":[
        "trucking"
    ],
    "wof:name":"Risling Transport",
    "wof:placetype":"venue"
},
  "geometry": {"coordinates":[-108.279945,52.783085],"type":"Point"}
}