{
  "type": "Feature",
  "properties": {
    "addr:full":"10144 100 Ave Fort St John BC V1J 1Y6",
    "addr:housenumber":"10144",
    "addr:postcode":"v1j 1y6",
    "addr:street":"100 Ave",
    "iso:country":"CA",
    "sg:address":"10144 100 Ave",
    "sg:city":"Fort St John",
    "sg:classifiers":[
        {
            "category":"Shopping",
            "subcategory":"Used Merchandise",
            "type":"Retail Goods"
        }
    ],
    "sg:phone":"+1 250 785 6024",
    "sg:postcode":"V1J 1Y6",
    "sg:province":"BC",
    "sg:tags":[
        "second",
        "store",
        "hand"
    ],
    "wof:name":"Girl Guide Thrift Shop",
    "wof:placetype":"venue"
},
  "geometry": {"coordinates":[-120.849845886,56.2467002869],"type":"Point"}
}