{
  "type": "Feature",
  "properties": {
    "addr:full":"General Delivery Grassy Narrows ON P0X 1B0",
    "addr:postcode":"p0x 1b0",
    "addr:street":"Grassy",
    "iso:country":"CA",
    "sg:address":"General Delivery",
    "sg:city":"Grassy Narrows",
    "sg:classifiers":[
        {
            "category":"Organizations",
            "subcategory":"Professional Association",
            "type":"Services"
        }
    ],
    "sg:phone":"+1 807 925 9967",
    "sg:postcode":"P0X 1B0",
    "sg:province":"ON",
    "sg:tags":[
        "native"
    ],
    "wof:name":"Niipawitung Trust Fund",
    "wof:placetype":"venue"
},
  "geometry": {"coordinates":[-93.9481124878,50.1333427429],"type":"Point"}
}