{
  "type": "Feature",
  "properties": {
    "addr:full":"Otterville ON N0J 1R0",
    "addr:postcode":"n0j 1r0",
    "iso:country":"CA",
    "sg:city":"Otterville",
    "sg:classifiers":[
        {
            "category":"Professional",
            "subcategory":"Management & Consulting",
            "type":"Services"
        }
    ],
    "sg:phone":"+1 519 582 4671",
    "sg:postcode":"N0J 1R0",
    "sg:province":"ON",
    "sg:tags":[
        "agricultural",
        "consultant"
    ],
    "wof:name":"Ontario Soil Balancers",
    "wof:placetype":"venue"
},
  "geometry": {"coordinates":[-80.6080780029,42.9257392883],"type":"Point"}
}