{
  "type": "Feature",
  "properties": {
    "iso:country":"CA",
    "sg:address":"1 Water Dr",
    "sg:city":"Fortune",
    "sg:classifiers":[
        {
            "category":"Bars & Pubs",
            "type":"Food & Drink"
        }
    ],
    "sg:phone":"+1 709 832 2621",
    "sg:postcode":"A0E 1P0",
    "sg:province":"NL",
    "sg:tags":[
        "lounge",
        "cocktail"
    ],
    "wof:name":"Charlie's Bar",
    "wof:placetype":"venue"
},
  "geometry": {"coordinates":[-55.825954,47.074135],"type":"Point"}
}