{
  "type": "Feature",
  "properties": {
    "addr:full":"1 Water Dr Fortune NL A0E 1P0",
    "addr:housenumber":"1",
    "addr:postcode":"a0e 1p0",
    "addr:street":"Water Dr",
    "iso:country":"CA",
    "sg:address":"1 Water Dr",
    "sg:city":"Fortune",
    "sg:classifiers":[
        {
            "category":"Bars & Pubs",
            "type":"Food & Drink"
        }
    ],
    "sg:phone":"+1 709 832 2621",
    "sg:postcode":"A0E 1P0",
    "sg:province":"NL",
    "sg:tags":[
        "lounge",
        "cocktail"
    ],
    "wof:name":"Charlie's Bar",
    "wof:placetype":"venue"
},
  "geometry": {"coordinates":[-55.825954,47.074135],"type":"Point"}
}