{
  "type": "Feature",
  "properties": {
    "iso:country":"CA",
    "sg:address":"1512 Regent Ave W",
    "sg:city":"Winnipeg",
    "sg:classifiers":[
        {
            "category":"Restaurant",
            "type":"Food & Drink"
        }
    ],
    "sg:phone":"+1 204 661 6191",
    "sg:postcode":"R2C 3B4",
    "sg:province":"MB",
    "wof:name":"Smitty's",
    "wof:placetype":"venue"
},
  "geometry": {"coordinates":[-97.0557022095,49.8957443237],"type":"Point"}
}