{
  "type": "Feature",
  "properties": {
    "addr:full":"7268 Veyaness Rd Saanichton BC V8M 1M2",
    "addr:housenumber":"7268",
    "addr:postcode":"v8m 1m2",
    "addr:street":"Veyaness Rd",
    "iso:country":"CA",
    "sg:address":"7268 Veyaness Rd",
    "sg:city":"Saanichton",
    "sg:classifiers":[
        {
            "category":"Manufacturing",
            "subcategory":"Food",
            "type":"Manufacturing & Wholesale Goods"
        }
    ],
    "sg:phone":"+1 250 652 8256",
    "sg:postcode":"V8M 1M2",
    "sg:province":"BC",
    "sg:tags":[
        "frozen",
        "dessert",
        "ice",
        "cream"
    ],
    "wof:name":"Shady Creek All Natural Ice",
    "wof:placetype":"venue"
},
  "geometry": {"coordinates":[-123.416893,48.5952],"type":"Point"}
}