{
  "type": "Feature",
  "properties": {
    "addr:full":"48 Rue Laval Hull QC J8X 3G9",
    "addr:housenumber":"48",
    "addr:postcode":"j8x 3g9",
    "addr:street":"Rue Laval",
    "iso:country":"CA",
    "sg:address":"48 Rue Laval",
    "sg:city":"Hull",
    "sg:classifiers":[
        {
            "category":"Bars & Pubs",
            "type":"Food & Drink"
        }
    ],
    "sg:phone":"+1 819 777 6555",
    "sg:postcode":"J8X 3G9",
    "sg:province":"QC",
    "wof:name":"Ou-Quoi",
    "wof:placetype":"venue"
},
  "geometry": {"coordinates":[-75.71611785890001,45.4272117615],"type":"Point"}
}