{
  "type": "Feature",
  "properties": {
    "addr:full":"103 Rue Couture Saint-Odilon QC G0S 3A0",
    "addr:housenumber":"103",
    "addr:postcode":"g0s 3a0",
    "addr:street":"Rue Couture Saint-Odilon",
    "iso:country":"CA",
    "sg:address":"103 Rue Couture",
    "sg:city":"Saint-Odilon",
    "sg:classifiers":[
        {
            "category":"Personal",
            "subcategory":"Beauty Salon",
            "type":"Services"
        }
    ],
    "sg:phone":"+1 418 464 4334",
    "sg:postcode":"G0S 3A0",
    "sg:province":"QC",
    "wof:name":"Salon Claire",
    "wof:placetype":"venue"
},
  "geometry": {"coordinates":[-70.6762008667,46.356174469],"type":"Point"}
}