{
  "type": "Feature",
  "properties": {
    "addr:full":"3803 Calgary Trail NW Edmonton AB T6J 5M8",
    "addr:housenumber":"3803",
    "addr:postcode":"t6j 5m8",
    "addr:street":"Calgary Trail Nw",
    "iso:country":"CA",
    "sg:address":"3803 Calgary Trail NW",
    "sg:city":"Edmonton",
    "sg:classifiers":[
        {
            "category":"Home & Garden",
            "subcategory":"Home Furnishings",
            "type":"Retail Goods"
        }
    ],
    "sg:phone":"+1 780 435 4522",
    "sg:postcode":"T6J 5M8",
    "sg:province":"AB",
    "sg:tags":[
        "utensil",
        "cooking"
    ],
    "wof:name":"Paderno Factory Store",
    "wof:placetype":"venue"
},
  "geometry": {"coordinates":[-113.495429993,53.4734153748],"type":"Point"}
}