{
  "type": "Feature",
  "properties": {
    "addr:full":"24 Amanda St Coniston ON P0M 1M0",
    "addr:housenumber":"24",
    "addr:postcode":"p0m 1m0",
    "addr:street":"Amanda St",
    "iso:country":"CA",
    "sg:address":"24 Amanda St",
    "sg:city":"Coniston",
    "sg:classifiers":[
        {
            "category":"Food & Beverages",
            "subcategory":"Liquor & Beverages",
            "type":"Retail Goods"
        }
    ],
    "sg:phone":"+1 705 694 4542",
    "sg:postcode":"P0M 1M0",
    "sg:province":"ON",
    "sg:tags":[
        "store"
    ],
    "wof:name":"Regie Des Alcools DE L'Ontario",
    "wof:placetype":"venue"
},
  "geometry": {"coordinates":[-80.8469085693,46.4938774109],"type":"Point"}
}