{
  "type": "Feature",
  "properties": {
    "addr:full":"18 School St Waterdown ON L0R 2H0",
    "addr:housenumber":"18",
    "addr:postcode":"l0r 2h0",
    "addr:street":"School St",
    "iso:country":"CA",
    "sg:address":"18 School St",
    "sg:city":"Waterdown",
    "sg:classifiers":[
        {
            "category":"Building & Trades",
            "subcategory":"Construction",
            "type":"Services"
        }
    ],
    "sg:phone":"+1 905 689 7866",
    "sg:postcode":"L0R 2H0",
    "sg:province":"ON",
    "sg:tags":[
        "painter"
    ],
    "wof:name":"Mr Paint & Renovate",
    "wof:placetype":"venue"
},
  "geometry": {"coordinates":[-79.8897018433,43.3303184509],"type":"Point"}
}