{
  "type": "Feature",
  "properties": {
    "addr:full":"Vancouver BC V6T 2G1",
    "addr:postcode":"v6t 2g1",
    "iso:country":"CA",
    "sg:city":"Vancouver",
    "sg:classifiers":[
        {
            "category":"Professional",
            "subcategory":"Management & Consulting",
            "type":"Services"
        }
    ],
    "sg:phone":"+1 604 224 7795",
    "sg:postcode":"V6T 2G1",
    "sg:province":"BC",
    "sg:tags":[
        "consultant",
        "business"
    ],
    "wof:name":"R Turner Inc",
    "wof:placetype":"venue"
},
  "geometry": {"coordinates":[-123.235458374,49.2581214905],"type":"Point"}
}