{
  "type": "Feature",
  "properties": {
    "addr:full":"684 Rue Decarie Sainte-Julie QC J3E 1J9",
    "addr:housenumber":"684",
    "addr:postcode":"j3e 1j9",
    "addr:street":"Rue Decarie",
    "iso:country":"CA",
    "sg:address":"684 Rue Decarie",
    "sg:city":"Sainte-Julie",
    "sg:classifiers":[
        {
            "category":"Building & Trades",
            "subcategory":"Construction",
            "type":"Services"
        }
    ],
    "sg:phone":"+1 450 649 5779",
    "sg:postcode":"J3E 1J9",
    "sg:province":"QC",
    "sg:tags":[
        "elevator"
    ],
    "wof:name":"Ascenseurs Atlantique Ltee",
    "wof:placetype":"venue"
},
  "geometry": {"coordinates":[-73.34683990480001,45.5930328369],"type":"Point"}
}