{
  "type": "Feature",
  "properties": {
    "addr:full":"Brampton ON L6T 5A1",
    "addr:postcode":"l6t 5a1",
    "iso:country":"CA",
    "sg:city":"Brampton",
    "sg:classifiers":[
        {
            "category":"Home & Garden",
            "subcategory":"Furniture",
            "type":"Retail Goods"
        }
    ],
    "sg:phone":"+1 905 790 3246",
    "sg:postcode":"L6T 5A1",
    "sg:province":"ON",
    "sg:tags":[
        "top",
        "counter",
        "kitchen",
        "cabinet"
    ],
    "wof:name":"Megna Countertops Inc",
    "wof:placetype":"venue"
},
  "geometry": {"coordinates":[-79.681595,43.712524],"type":"Point"}
}