{
  "type": "Feature",
  "properties": {
    "addr:full":"742 Erin St Winnipeg MB R3G 2W4",
    "addr:housenumber":"742",
    "addr:postcode":"r3g 2w4",
    "addr:street":"Erin St",
    "iso:country":"CA",
    "sg:address":"742 Erin St",
    "sg:city":"Winnipeg",
    "sg:classifiers":[
        {
            "category":"Home & Garden",
            "subcategory":"Building Materials",
            "type":"Retail Goods"
        }
    ],
    "sg:phone":"+1 204 775 5714",
    "sg:postcode":"R3G 2W4",
    "sg:province":"MB",
    "sg:tags":[
        "windows"
    ],
    "wof:name":"North End Weatherstripping",
    "wof:placetype":"venue"
},
  "geometry": {"coordinates":[-97.185059,49.888332],"type":"Point"}
}