{
  "type": "Feature",
  "properties": {
    "addr:full":"2716 Exshaw Rd NW Calgary AB T2M 4E8",
    "addr:housenumber":"2716",
    "addr:postcode":"t2m 4e8",
    "addr:street":"Exshaw Rd Nw",
    "iso:country":"CA",
    "sg:address":"2716 Exshaw Rd NW",
    "sg:city":"Calgary",
    "sg:classifiers":[
        {
            "category":"Education",
            "subcategory":"Special Training",
            "type":"Public Place"
        }
    ],
    "sg:phone":"+1 403 284 4085",
    "sg:postcode":"T2M 4E8",
    "sg:province":"AB",
    "sg:tags":[
        "instruction",
        "music"
    ],
    "wof:name":"Orff Music For Children",
    "wof:placetype":"venue"
},
  "geometry": {"coordinates":[-114.11158,51.076347],"type":"Point"}
}