{
  "type": "Feature",
  "properties": {
    "addr:full":"41 Rue Du College Pont-Rouge QC G3H 3A4",
    "addr:housenumber":"41",
    "addr:postcode":"g3h 3a4",
    "addr:street":"Rue Du College",
    "iso:country":"CA",
    "sg:address":"41 Rue Du College",
    "sg:city":"Pont-Rouge",
    "sg:classifiers":[
        {
            "category":"Education",
            "subcategory":"Library",
            "type":"Public Place"
        }
    ],
    "sg:phone":"+1 418 873 4067",
    "sg:postcode":"G3H 3A4",
    "sg:province":"QC",
    "wof:name":"Bibliotheque DE Pont-Rouge",
    "wof:placetype":"venue"
},
  "geometry": {"coordinates":[-71.6950378418,46.752456665],"type":"Point"}
}