{
  "type": "Feature",
  "properties": {
    "iso:country":"CA",
    "sg:city":"Dallas",
    "sg:classifiers":[
        {
            "category":"Food & Beverages",
            "subcategory":"Groceries & Convenience Stores",
            "type":"Retail Goods"
        }
    ],
    "sg:phone":"+1 204 645 2683",
    "sg:postcode":"R0C 0S0",
    "sg:province":"MB",
    "sg:tags":[
        "grocer"
    ],
    "wof:name":"Dallas General Store",
    "wof:placetype":"venue"
},
  "geometry": {"coordinates":[-97.4857711792,51.3970336914],"type":"Point"}
}