{
  "type": "Feature",
  "properties": {
    "addr:full":"42 Rue Principal Sainte-Therese-DE-LA-Gatineau QC J0X 2X0",
    "addr:housenumber":"42",
    "addr:postcode":"j0x 2x0",
    "addr:street":"Rue Principal Sainte-Therese-De-La-Gatineau",
    "iso:country":"CA",
    "sg:address":"42 Rue Principal",
    "sg:city":"Sainte-Therese-DE-LA-Gatineau",
    "sg:classifiers":[
        {
            "category":"Food & Beverages",
            "subcategory":"Groceries & Convenience Stores",
            "type":"Retail Goods"
        }
    ],
    "sg:phone":"+1 819 449 7453",
    "sg:postcode":"J0X 2X0",
    "sg:province":"QC",
    "sg:tags":[
        "grocer"
    ],
    "wof:name":"Epicerie 4 Saisons",
    "wof:placetype":"venue"
},
  "geometry": {"coordinates":[-75.7104873657,45.4278526306],"type":"Point"}
}