{
  "type": "Feature",
  "properties": {
    "addr:full":"149 Alfred Ave Winnipeg MB R2W 1X2",
    "addr:housenumber":"149",
    "addr:postcode":"r2w 1x2",
    "addr:street":"Alfred Ave",
    "iso:country":"CA",
    "sg:address":"149 Alfred Ave",
    "sg:city":"Winnipeg",
    "sg:classifiers":[
        {
            "category":"Building & Trades",
            "subcategory":"Construction",
            "type":"Services"
        }
    ],
    "sg:phone":"+1 204 589 1322",
    "sg:postcode":"R2W 1X2",
    "sg:province":"MB",
    "sg:tags":[
        "concrete",
        "contractor"
    ],
    "wof:name":"Banak Paving",
    "wof:placetype":"venue"
},
  "geometry": {"coordinates":[-97.12996699999999,49.915272],"type":"Point"}
}