{
  "type": "Feature",
  "properties": {
    "addr:full":"616 Broadway St Tillsonburg ON N4G 3S9",
    "addr:housenumber":"616",
    "addr:postcode":"n4g 3s9",
    "addr:street":"Broadway St",
    "iso:country":"CA",
    "sg:address":"616 Broadway St",
    "sg:city":"Tillsonburg",
    "sg:classifiers":[
        {
            "category":"Home & Garden",
            "subcategory":"Furniture",
            "type":"Retail Goods"
        }
    ],
    "sg:phone":"+1 519 842 4981",
    "sg:postcode":"N4G 3S9",
    "sg:province":"ON",
    "wof:name":"Stubbe's Countrywide",
    "wof:placetype":"venue"
},
  "geometry": {"coordinates":[-80.74694100000001,42.879078],"type":"Point"}
}