{
  "type": "Feature",
  "properties": {
    "iso:country":"CA",
    "sg:address":"420 Boul Wilfrid-Lavigne",
    "sg:city":"Aylmer",
    "sg:classifiers":[
        {
            "category":"Government",
            "subcategory":"Office",
            "type":"Public Place"
        }
    ],
    "sg:phone":"+1 819 682 0362",
    "sg:postcode":"J9H 6W7",
    "sg:province":"QC",
    "wof:name":"Quebec Centre Local D'Emploi",
    "wof:placetype":"venue"
},
  "geometry": {"coordinates":[-75.8378829956,45.3970870972],"type":"Point"}
}