{
  "type": "Feature",
  "properties": {
    "addr:full":"486 Ester St Sudbury ON P3E 5C4",
    "addr:housenumber":"486",
    "addr:postcode":"p3e 5c4",
    "addr:street":"Ester St",
    "iso:country":"CA",
    "sg:address":"486 Ester St",
    "sg:city":"Sudbury",
    "sg:classifiers":[
        {
            "category":"Organizations",
            "subcategory":"Religious Organization",
            "type":"Services"
        }
    ],
    "sg:phone":"+1 705 522 5181",
    "sg:postcode":"P3E 5C4",
    "sg:province":"ON",
    "sg:tags":[
        "church"
    ],
    "wof:name":"St Nicholas Greek Orthodox",
    "wof:placetype":"venue"
},
  "geometry": {"coordinates":[-81.01171100000001,46.443775],"type":"Point"}
}