{
  "type": "Feature",
  "properties": {
    "addr:full":"RR 1 Thomasburg ON K0K 3H0",
    "addr:postcode":"k0k 3h0",
    "addr:street":"Rr 1",
    "iso:country":"CA",
    "sg:address":"RR 1",
    "sg:city":"Thomasburg",
    "sg:classifiers":[
        {
            "category":"Building & Trades",
            "subcategory":"Construction",
            "type":"Services"
        }
    ],
    "sg:phone":"+1 613 478 5110",
    "sg:postcode":"K0K 3H0",
    "sg:province":"ON",
    "sg:tags":[
        "general",
        "contractor"
    ],
    "wof:name":"D G Brown Construction Ltd",
    "wof:placetype":"venue"
},
  "geometry": {"coordinates":[-77.34586299999999,44.388767],"type":"Point"}
}