{
  "type": "Feature",
  "properties": {
    "iso:country":"CA",
    "sg:city":"Concord",
    "sg:classifiers":[
        {
            "category":"Manufacturing",
            "subcategory":"Printing",
            "type":"Manufacturing & Wholesale Goods"
        }
    ],
    "sg:phone":"+1 905 738 5353",
    "sg:postcode":"L4K 3C8",
    "sg:province":"ON",
    "sg:tags":[
        "printer"
    ],
    "wof:name":"Northview Print & Copy Inc",
    "wof:placetype":"venue"
},
  "geometry": {"coordinates":[-79.5020523071,43.7799072266],"type":"Point"}
}