{
  "type": "Feature",
  "properties": {
    "addr:full":"3908 2nd Ave Smithers BC V0J 2N0",
    "addr:housenumber":"3908",
    "addr:postcode":"v0j 2n0",
    "addr:street":"2Nd Ave",
    "iso:country":"CA",
    "sg:address":"3908 2nd Ave",
    "sg:city":"Smithers",
    "sg:classifiers":[
        {
            "category":"Recreation",
            "type":"Entertainment"
        }
    ],
    "sg:phone":"+1 250 847 9818",
    "sg:postcode":"V0J 2N0",
    "sg:province":"BC",
    "sg:tags":[
        "hall",
        "auditorium"
    ],
    "wof:name":"Elk's Home",
    "wof:placetype":"venue"
},
  "geometry": {"coordinates":[-127.17287399999999,54.78204],"type":"Point"}
}