{
  "type": "Feature",
  "properties": {
    "iso:country":"CA",
    "sg:address":"504 Rue Notre-Dame",
    "sg:city":"Repentigny",
    "sg:classifiers":[
        {
            "category":"Shopping",
            "subcategory":"Pharmacy",
            "type":"Retail Goods"
        }
    ],
    "sg:phone":"+1 450 581 1400",
    "sg:postcode":"J6A 2T8",
    "sg:province":"QC",
    "wof:name":"Famili-Sante Jacques Rioux",
    "wof:placetype":"venue"
},
  "geometry": {"coordinates":[-73.4423446655,45.7414627075],"type":"Point"}
}