{
  "type": "Feature",
  "properties": {
    "iso:country":"CA",
    "sg:address":"8080 Boul Taschereau",
    "sg:city":"Brossard",
    "sg:classifiers":[
        {
            "category":"Health Services",
            "subcategory":"Doctor",
            "type":"Services"
        }
    ],
    "sg:phone":"+1 450 465 5589",
    "sg:postcode":"J4X 1C2",
    "sg:province":"QC",
    "sg:tags":[
        "clinic"
    ],
    "wof:name":"Clinique Medicale Alexandre",
    "wof:placetype":"venue"
},
  "geometry": {"coordinates":[-73.468628,45.449863],"type":"Point"}
}