{
  "type": "Feature",
  "properties": {
    "iso:country":"CA",
    "sg:address":"1001 Av Laurier O",
    "sg:city":"Outremont",
    "sg:classifiers":[
        {
            "category":"Shopping",
            "subcategory":"Clothing, Apparel, & Fashions",
            "type":"Retail Goods"
        }
    ],
    "sg:phone":"+1 514 271 7787",
    "sg:postcode":"H2V 2L1",
    "sg:province":"QC",
    "sg:tags":[
        "item",
        "boutique"
    ],
    "wof:name":"Tristan & Iseut",
    "wof:placetype":"venue"
},
  "geometry": {"coordinates":[-73.59665679930001,45.5185623169],"type":"Point"}
}