{
  "type": "Feature",
  "properties": {
    "addr:full":"1190 Rue Galt E Sherbrooke QC J1G 1Y5",
    "addr:housenumber":"1190",
    "addr:postcode":"j1g 1y5",
    "addr:street":"Rue Galt E",
    "iso:country":"CA",
    "sg:address":"1190 Rue Galt E",
    "sg:city":"Sherbrooke",
    "sg:classifiers":[
        {
            "category":"Manufacturing",
            "subcategory":"Tools & Machinery",
            "type":"Manufacturing & Wholesale Goods"
        }
    ],
    "sg:phone":"+1 819 566 1040",
    "sg:postcode":"J1G 1Y5",
    "sg:province":"QC",
    "sg:tags":[
        "machine",
        "shop"
    ],
    "wof:name":"Engrenages Sherbrooke Inc",
    "wof:placetype":"venue"
},
  "geometry": {"coordinates":[-71.8625793457,45.3969154358],"type":"Point"}
}