{
  "type": "Feature",
  "properties": {
    "addr:full":"777 Clark Dr Vancouver BC V5L 3J3",
    "addr:housenumber":"777",
    "addr:postcode":"v5l 3j3",
    "addr:street":"Clark Dr",
    "iso:country":"CA",
    "sg:address":"777 Clark Dr",
    "sg:city":"Vancouver",
    "sg:classifiers":[
        {
            "category":"Wholesale",
            "subcategory":"Fruits & Vegetables",
            "type":"Manufacturing & Wholesale Goods"
        }
    ],
    "sg:phone":"+1 604 253 6622",
    "sg:postcode":"V5L 3J3",
    "sg:province":"BC",
    "wof:name":"Jim M Koo Wholesale Produce",
    "wof:placetype":"venue"
},
  "geometry": {"coordinates":[-123.077415,49.277916],"type":"Point"}
}