{
  "type": "Feature",
  "properties": {
    "addr:full":"8387 Boul Saint-Michel Montreal QC H1Z 3E7",
    "addr:housenumber":"8387",
    "addr:postcode":"h1z 3e7",
    "addr:street":"Boul Saint-Michel",
    "iso:country":"CA",
    "sg:address":"8387 Boul Saint-Michel",
    "sg:city":"Montreal",
    "sg:classifiers":[
        {
            "category":"Restaurant",
            "type":"Food & Drink"
        }
    ],
    "sg:phone":"+1 514 723 2008",
    "sg:postcode":"H1Z 3E7",
    "sg:province":"QC",
    "wof:name":"Carlouchis Restaurant Enr",
    "wof:placetype":"venue"
},
  "geometry": {"coordinates":[-73.6144332886,45.5661582947],"type":"Point"}
}