{
  "type": "Feature",
  "properties": {
    "addr:full":"1688 Av Du Mont-Royal E Montreal QC H2J 1Z5",
    "addr:housenumber":"1688",
    "addr:postcode":"h2j 1z5",
    "addr:street":"Av Du Mont-Royal E",
    "iso:country":"CA",
    "sg:address":"1688 Av Du Mont-Royal E",
    "sg:city":"Montreal",
    "sg:classifiers":[
        {
            "category":"Sports & Exercise",
            "subcategory":"Bowling",
            "type":"Entertainment"
        }
    ],
    "sg:phone":"+1 514 521 7651",
    "sg:postcode":"H2J 1Z5",
    "sg:province":"QC",
    "sg:tags":[
        "center"
    ],
    "wof:name":"Salle DE Quilles Au Drome Enr",
    "wof:placetype":"venue"
},
  "geometry": {"coordinates":[-73.574783,45.53244],"type":"Point"}
}