{
  "type": "Feature",
  "properties": {
    "addr:full":"1866 Mcara St Regina SK S4N 6C4",
    "addr:housenumber":"1866",
    "addr:postcode":"s4n 6c4",
    "addr:street":"Mcara St",
    "iso:country":"CA",
    "sg:address":"1866 Mcara St",
    "sg:city":"Regina",
    "sg:classifiers":[
        {
            "category":"Organizations",
            "subcategory":"Labor Organization",
            "type":"Services"
        }
    ],
    "sg:phone":"+1 306 525 2336",
    "sg:postcode":"S4N 6C4",
    "sg:province":"SK",
    "wof:name":"Construction Workers Union",
    "wof:placetype":"venue"
},
  "geometry": {"coordinates":[-104.58234405499999,50.4493789673],"type":"Point"}
}