{
  "type": "Feature",
  "properties": {
    "addr:full":"6750 Davand Dr # 9 Mississauga ON L5T 2L8",
    "addr:housenumber":"6750",
    "addr:postcode":"l5t 2l8",
    "addr:street":"Davand Dr # 9",
    "iso:country":"CA",
    "sg:address":"6750 Davand Dr # 9",
    "sg:city":"Mississauga",
    "sg:classifiers":[
        {
            "category":"Retail",
            "subcategory":"Repair Shop",
            "type":"Services"
        }
    ],
    "sg:phone":"+1 905 564 7876",
    "sg:postcode":"L5T 2L8",
    "sg:province":"ON",
    "sg:tags":[
        "equipment",
        "electronic",
        "supply"
    ],
    "wof:name":"Solika Solutions Inc",
    "wof:placetype":"venue"
},
  "geometry": {"coordinates":[-79.66929626460001,43.6688842773],"type":"Point"}
}