{
  "type": "Feature",
  "properties": {
    "addr:full":"56 Celtic Dr Dartmouth NS B2Y 3G6",
    "addr:housenumber":"56",
    "addr:postcode":"b2y 3g6",
    "addr:street":"Celtic Dr",
    "iso:country":"CA",
    "sg:address":"56 Celtic Dr",
    "sg:city":"Dartmouth",
    "sg:classifiers":[
        {
            "category":"Building & Trades",
            "subcategory":"Construction",
            "type":"Services"
        }
    ],
    "sg:phone":"+1 902 469 1032",
    "sg:postcode":"B2Y 3G6",
    "sg:province":"NS",
    "sg:tags":[
        "home",
        "improvement"
    ],
    "wof:name":"A & H Renovations",
    "wof:placetype":"venue"
},
  "geometry": {"coordinates":[-63.5487670898,44.6757164001],"type":"Point"}
}