{
  "type": "Feature",
  "properties": {
    "iso:country":"CA",
    "sg:address":"2067 132 Rte E",
    "sg:city":"Le Bic",
    "sg:classifiers":[
        {
            "category":"Shopping",
            "subcategory":"Used Merchandise",
            "type":"Retail Goods"
        }
    ],
    "sg:phone":"+1 418 736 5141",
    "sg:postcode":"G0L 1B0",
    "sg:province":"QC",
    "sg:tags":[
        "flea",
        "market"
    ],
    "wof:name":"Marche Aux Puces & Comptoir",
    "wof:placetype":"venue"
},
  "geometry": {"coordinates":[-68.7056427002,48.3731918335],"type":"Point"}
}