{
  "type": "Feature",
  "properties": {
    "addr:full":"32 Caribou Lake Rd Loring ON P0H 1S0",
    "addr:housenumber":"32",
    "addr:postcode":"p0h 1s0",
    "addr:street":"Caribou Lake Rd",
    "iso:country":"CA",
    "sg:address":"32 Caribou Lake Rd",
    "sg:city":"Loring",
    "sg:classifiers":[
        {
            "category":"Travel",
            "subcategory":"Hotels & Motels",
            "type":"Entertainment"
        }
    ],
    "sg:phone":"+1 705 757 2713",
    "sg:postcode":"P0H 1S0",
    "sg:province":"ON",
    "sg:tags":[
        "cottage",
        "cabin"
    ],
    "wof:name":"Brooks Cottages",
    "wof:placetype":"venue"
},
  "geometry": {"coordinates":[-79.99749,45.932285],"type":"Point"}
}