{
  "type": "Feature",
  "properties": {
    "iso:country":"CA",
    "sg:address":"1405 St Matthews Ave",
    "sg:city":"Winnipeg",
    "sg:classifiers":[
        {
            "category":"Bars & Pubs",
            "type":"Food & Drink"
        }
    ],
    "sg:phone":"+1 204 775 8791",
    "sg:postcode":"R3G 0K5",
    "sg:province":"MB",
    "sg:tags":[
        "club",
        "night"
    ],
    "wof:name":"Tijuana Yacht Club",
    "wof:placetype":"venue"
},
  "geometry": {"coordinates":[-97.1947174072,49.8909721375],"type":"Point"}
}