{
  "type": "Feature",
  "properties": {
    "addr:full":"858 Merivale Rd Ottawa ON K1Z 5Z6",
    "addr:housenumber":"858",
    "addr:postcode":"k1z 5z6",
    "addr:street":"Merivale Rd",
    "iso:country":"CA",
    "sg:address":"858 Merivale Rd",
    "sg:city":"Ottawa",
    "sg:classifiers":[
        {
            "category":"Restaurant",
            "type":"Food & Drink"
        }
    ],
    "sg:phone":"+1 613 725 2818",
    "sg:postcode":"K1Z 5Z6",
    "sg:province":"ON",
    "wof:name":"Amigo's Restaurant",
    "wof:placetype":"venue"
},
  "geometry": {"coordinates":[-75.73255899999999,45.384872],"type":"Point"}
}