{
  "type": "Feature",
  "properties": {
    "addr:full":"London ON N6L 1E3",
    "addr:postcode":"n6l 1e3",
    "iso:country":"CA",
    "sg:city":"London",
    "sg:classifiers":[
        {
            "category":"Education",
            "subcategory":"School",
            "type":"Public Place"
        }
    ],
    "sg:phone":"+1 519 652 7672",
    "sg:postcode":"N6L 1E3",
    "sg:province":"ON",
    "sg:tags":[
        "instruction",
        "music"
    ],
    "wof:name":"Yamaha Music School",
    "wof:placetype":"venue"
},
  "geometry": {"coordinates":[-81.266403,42.919861],"type":"Point"}
}