{
  "type": "Feature",
  "properties": {
    "addr:full":"468 Mcnicoll Ave North York ON M2H 2E1",
    "addr:housenumber":"468",
    "addr:postcode":"m2h 2e1",
    "addr:street":"Mcnicoll Ave",
    "iso:country":"CA",
    "sg:address":"468 Mcnicoll Ave",
    "sg:city":"North York",
    "sg:classifiers":[
        {
            "category":"Professional",
            "subcategory":"Business Services",
            "type":"Services"
        }
    ],
    "sg:phone":"+1 416 499 9517",
    "sg:postcode":"M2H 2E1",
    "sg:province":"ON",
    "sg:tags":[
        "interior",
        "consultant",
        "design",
        "decorator"
    ],
    "wof:name":"Hylan Interior Svc",
    "wof:placetype":"venue"
},
  "geometry": {"coordinates":[-79.3408660889,43.8037452698],"type":"Point"}
}