{
  "type": "Feature",
  "properties": {
    "addr:full":"7 Grand Ave Kitchener ON N2K 1B2",
    "addr:housenumber":"7",
    "addr:postcode":"n2k 1b2",
    "addr:street":"Grand Ave",
    "iso:country":"CA",
    "sg:address":"7 Grand Ave",
    "sg:city":"Kitchener",
    "sg:classifiers":[
        {
            "category":"Freight",
            "type":"Transportation"
        }
    ],
    "sg:phone":"+1 519 744 3597",
    "sg:postcode":"N2K 1B2",
    "sg:province":"ON",
    "sg:tags":[
        "trucking"
    ],
    "wof:name":"Bell Cartage",
    "wof:placetype":"venue"
},
  "geometry": {"coordinates":[-80.4758300781,43.4799613953],"type":"Point"}
}