{
  "type": "Feature",
  "properties": {
    "iso:country":"CA",
    "sg:address":"11800 Lake Fraser Dr SE",
    "sg:city":"Calgary",
    "sg:classifiers":[
        {
            "category":"Social Services",
            "subcategory":"Adult Care",
            "type":"Services"
        }
    ],
    "sg:phone":"+1 403 258 1849",
    "sg:postcode":"T2J 7G8",
    "sg:province":"AB",
    "sg:tags":[
        "senior",
        "housing",
        "citizen"
    ],
    "wof:name":"Lake Bonavista Village",
    "wof:placetype":"venue"
},
  "geometry": {"coordinates":[-114.067810059,50.9479217529],"type":"Point"}
}