{
  "type": "Feature",
  "properties": {
    "iso:country":"CA",
    "sg:city":"Saint-Pierre-Ile-D'Orleans",
    "sg:classifiers":[
        {
            "category":"Personal",
            "subcategory":"Beauty Salon",
            "type":"Services"
        }
    ],
    "sg:phone":"+1 418 828 0303",
    "sg:postcode":"G0A 4E0",
    "sg:province":"QC",
    "wof:name":"Salon Coup D'Oeil",
    "wof:placetype":"venue"
},
  "geometry": {"coordinates":[-73.36098480219999,45.5325164795],"type":"Point"}
}