{
  "type": "Feature",
  "properties": {
    "addr:full":"2109 Ottawa St Windsor ON N8Y 1R8",
    "addr:housenumber":"2109",
    "addr:postcode":"n8y 1r8",
    "addr:street":"Ottawa St",
    "iso:country":"CA",
    "sg:address":"2109 Ottawa St",
    "sg:city":"Windsor",
    "sg:classifiers":[
        {
            "category":"Shopping",
            "subcategory":"Gifts & Souvenirs",
            "type":"Retail Goods"
        }
    ],
    "sg:phone":"+1 519 977 5362",
    "sg:postcode":"N8Y 1R8",
    "sg:province":"ON",
    "sg:tags":[
        "shop"
    ],
    "wof:name":"Gift Trends",
    "wof:placetype":"venue"
},
  "geometry": {"coordinates":[-83.003868,42.312691],"type":"Point"}
}