{
  "type": "Feature",
  "properties": {
    "addr:full":"7003 Ch DE LA Cote-Des-Neiges Montreal QC H3S 2B6",
    "addr:housenumber":"7003",
    "addr:postcode":"h3s 2b6",
    "addr:street":"Ch De La Cote-Des-Neiges",
    "iso:country":"CA",
    "sg:address":"7003 Ch DE LA Cote-Des-Neiges",
    "sg:city":"Montreal",
    "sg:classifiers":[
        {
            "category":"Building & Trades",
            "subcategory":"Construction",
            "type":"Services"
        }
    ],
    "sg:phone":"+1 514 344 5227",
    "sg:postcode":"H3S 2B6",
    "sg:province":"QC",
    "sg:tags":[
        "general",
        "contractor"
    ],
    "wof:name":"Progest Construction",
    "wof:placetype":"venue"
},
  "geometry": {"coordinates":[-73.639061,45.504284],"type":"Point"}
}