{
  "type": "Feature",
  "properties": {
    "addr:full":"1481 Harmony Rd N Oshawa ON L1H 7K5",
    "addr:housenumber":"1481",
    "addr:postcode":"l1h 7k5",
    "addr:street":"Harmony Rd N",
    "iso:country":"CA",
    "sg:address":"1481 Harmony Rd N",
    "sg:city":"Oshawa",
    "sg:classifiers":[
        {
            "category":"Restaurant",
            "type":"Food & Drink"
        }
    ],
    "sg:phone":"+1 905 725 0245",
    "sg:postcode":"L1H 7K5",
    "sg:province":"ON",
    "wof:name":"Harvey's",
    "wof:placetype":"venue"
},
  "geometry": {"coordinates":[-78.85071600000001,43.942818],"type":"Point"}
}