{
  "type": "Feature",
  "properties": {
    "addr:full":"276 Rue Des Saphirs Boischatel QC G0A 1H0",
    "addr:housenumber":"276",
    "addr:postcode":"g0a 1h0",
    "addr:street":"Rue Des Saphirs",
    "iso:country":"CA",
    "sg:address":"276 Rue Des Saphirs",
    "sg:city":"Boischatel",
    "sg:classifiers":[
        {
            "category":"Building & Trades",
            "subcategory":"Construction",
            "type":"Services"
        }
    ],
    "sg:phone":"+1 418 822 2932",
    "sg:postcode":"G0A 1H0",
    "sg:province":"QC",
    "sg:tags":[
        "concrete",
        "restoration",
        "repair",
        "cleaning",
        "contractor"
    ],
    "wof:name":"Injection Quebec Inc",
    "wof:placetype":"venue"
},
  "geometry": {"coordinates":[-71.156891,46.920658],"type":"Point"}
}