{
  "type": "Feature",
  "properties": {
    "iso:country":"CA",
    "sg:address":"3300 Mavis Rd",
    "sg:city":"Mississauga",
    "sg:classifiers":[
        {
            "category":"Retail",
            "subcategory":"Auto Repair",
            "type":"Services"
        }
    ],
    "sg:phone":"+1 905 275 1996",
    "sg:postcode":"L5C 1T8",
    "sg:province":"ON",
    "sg:tags":[
        "body",
        "automobile",
        "painting"
    ],
    "wof:name":"Adria Autobody",
    "wof:placetype":"venue"
},
  "geometry": {"coordinates":[-79.6417770386,43.5720100403],"type":"Point"}
}