{
  "type": "Feature",
  "properties": {
    "addr:full":"Edmonton AB T5N 1P3",
    "addr:postcode":"t5n 1p3",
    "iso:country":"CA",
    "sg:city":"Edmonton",
    "sg:classifiers":[
        {
            "category":"Personal",
            "subcategory":"Beauty Salon",
            "type":"Services"
        }
    ],
    "sg:phone":"+1 780 488 1155",
    "sg:postcode":"T5N 1P3",
    "sg:province":"AB",
    "wof:name":"European Hair & Tanning Studio",
    "wof:placetype":"venue"
},
  "geometry": {"coordinates":[-113.533905,53.550049],"type":"Point"}
}