{
  "type": "Feature",
  "properties": {
    "addr:full":"Breslau ON N0B 1M0",
    "addr:postcode":"n0b 1m0",
    "iso:country":"CA",
    "sg:city":"Breslau",
    "sg:classifiers":[
        {
            "category":"Manufacturing",
            "subcategory":"Chemicals & Compounds",
            "type":"Manufacturing & Wholesale Goods"
        }
    ],
    "sg:phone":"+1 519 742 8377",
    "sg:postcode":"N0B 1M0",
    "sg:province":"ON",
    "sg:tags":[
        "fertilizer"
    ],
    "wof:name":"Evergreeen Liquid Plant Food",
    "wof:placetype":"venue"
},
  "geometry": {"coordinates":[-80.4139709473,43.4756965637],"type":"Point"}
}