{
  "type": "Feature",
  "properties": {
    "iso:country":"CA",
    "sg:address":"1110 Heritage Rd",
    "sg:city":"Burlington",
    "sg:classifiers":[
        {
            "category":"Wholesale",
            "subcategory":"Machinery & Supplies",
            "type":"Manufacturing & Wholesale Goods"
        }
    ],
    "sg:phone":"+1 905 336 8381",
    "sg:postcode":"L7L 4X9",
    "sg:province":"ON",
    "sg:tags":[
        "valve"
    ],
    "wof:name":"Specialty Valve Sales Ltd",
    "wof:placetype":"venue"
},
  "geometry": {"coordinates":[-79.7847290039,43.3753738403],"type":"Point"}
}