{
  "type": "Feature",
  "properties": {
    "addr:full":"246 Moonstone Rd E Moonstone ON L0K 1N0",
    "addr:housenumber":"246",
    "addr:postcode":"l0k 1n0",
    "addr:street":"Moonstone Rd E Moonstone",
    "iso:country":"CA",
    "sg:address":"246 Moonstone Rd E",
    "sg:city":"Moonstone",
    "sg:classifiers":[
        {
            "category":"Food & Beverages",
            "subcategory":"Groceries & Convenience Stores",
            "type":"Retail Goods"
        }
    ],
    "sg:phone":"+1 705 835 6750",
    "sg:postcode":"L0K 1N0",
    "sg:province":"ON",
    "wof:name":"Tasty Market",
    "wof:placetype":"venue"
},
  "geometry": {"coordinates":[-79.66346,44.655632],"type":"Point"}
}