{
  "type": "Feature",
  "properties": {
    "iso:country":"CA",
    "sg:address":"Oliver Lake Rd E",
    "sg:city":"South Gillies",
    "sg:classifiers":[
        {
            "category":"Professional",
            "subcategory":"Management & Consulting",
            "type":"Services"
        }
    ],
    "sg:phone":"+1 807 475 5630",
    "sg:postcode":"P0T 2V0",
    "sg:province":"ON",
    "sg:tags":[
        "consultant",
        "safety"
    ],
    "wof:name":"Construction Safety Assn",
    "wof:placetype":"venue"
},
  "geometry": {"coordinates":[-89.6999740601,48.2753334045],"type":"Point"}
}