{
  "type": "Feature",
  "properties": {
    "addr:full":"Railway Ave Humboldt SK S0K 2A0",
    "addr:postcode":"s0k 2a0",
    "addr:street":"Railway Ave",
    "iso:country":"CA",
    "sg:address":"Railway Ave",
    "sg:city":"Humboldt",
    "sg:classifiers":[
        {
            "category":"Recreation",
            "type":"Entertainment"
        }
    ],
    "sg:phone":"+1 306 682 2123",
    "sg:postcode":"S0K 2A0",
    "sg:province":"SK",
    "sg:tags":[
        "club",
        "curling",
        "government"
    ],
    "wof:name":"Humboldt Curling Rink",
    "wof:placetype":"venue"
},
  "geometry": {"coordinates":[-105.12146799999999,52.2019],"type":"Point"}
}