{
  "type": "Feature",
  "properties": {
    "iso:country":"CA",
    "sg:city":"Toronto",
    "sg:classifiers":[
        {
            "category":"Professional",
            "subcategory":"Accounting & Tax Preparation",
            "type":"Services"
        }
    ],
    "sg:phone":"+1 416 962 3397",
    "sg:postcode":"M4T 1L9",
    "sg:province":"ON",
    "sg:tags":[
        "accountant"
    ],
    "wof:name":"Cheng, William K C CA",
    "wof:placetype":"venue"
},
  "geometry": {"coordinates":[-79.3927764893,43.6882247925],"type":"Point"}
}