{
  "type": "Feature",
  "properties": {
    "iso:country":"CA",
    "sg:address":"1027 Frost St",
    "sg:city":"North Bay",
    "sg:classifiers":[
        {
            "category":"Retail",
            "subcategory":"Auto Repair",
            "type":"Services"
        }
    ],
    "sg:phone":"+1 705 474 4985",
    "sg:postcode":"P1B 6C8",
    "sg:province":"ON",
    "sg:tags":[
        "repairing",
        "automobile",
        "brake"
    ],
    "wof:name":"Mathews Automotive",
    "wof:placetype":"venue"
},
  "geometry": {"coordinates":[-79.4519729614,46.3280296326],"type":"Point"}
}