{
  "type": "Feature",
  "properties": {
    "iso:country":"CA",
    "sg:address":"166 Timmons St",
    "sg:city":"Collingwood",
    "sg:classifiers":[
        {
            "category":"Manufacturing",
            "subcategory":"Tools & Machinery",
            "type":"Manufacturing & Wholesale Goods"
        }
    ],
    "sg:phone":"+1 705 445 7474",
    "sg:postcode":"L9Y 3Z2",
    "sg:province":"ON",
    "sg:tags":[
        "heating",
        "contractor"
    ],
    "wof:name":"Craigleith Climate Control",
    "wof:placetype":"venue"
},
  "geometry": {"coordinates":[-80.2168273926,44.4998893738],"type":"Point"}
}