{
  "type": "Feature",
  "properties": {
    "addr:full":"5110 Boul Cousineau Saint-Hubert QC J3Y 7G5",
    "addr:housenumber":"5110",
    "addr:postcode":"j3y 7g5",
    "addr:street":"Boul Cousineau",
    "iso:country":"CA",
    "sg:address":"5110 Boul Cousineau",
    "sg:city":"Saint-Hubert",
    "sg:classifiers":[
        {
            "category":"Organizations",
            "subcategory":"Labor Organization",
            "type":"Services"
        }
    ],
    "sg:phone":"+1 450 926 2242",
    "sg:postcode":"J3Y 7G5",
    "sg:province":"QC",
    "wof:name":"Federation DE LA Sante Et Des",
    "wof:placetype":"venue"
},
  "geometry": {"coordinates":[-73.42892500000001,45.503948],"type":"Point"}
}