{
  "type": "Feature",
  "properties": {
    "addr:full":"1800 Rue Leon-Harmel Quebec QC G1N 4R9",
    "addr:housenumber":"1800",
    "addr:postcode":"g1n 4r9",
    "addr:street":"Rue Leon-Harmel",
    "iso:country":"CA",
    "sg:address":"1800 Rue Leon-Harmel",
    "sg:city":"Quebec",
    "sg:classifiers":[
        {
            "category":"Manufacturing",
            "subcategory":"Food",
            "type":"Manufacturing & Wholesale Goods"
        }
    ],
    "sg:phone":"+1 418 527 7999",
    "sg:postcode":"G1N 4R9",
    "sg:province":"QC",
    "sg:tags":[
        "baker",
        "cookie",
        "bakery"
    ],
    "wof:name":"Multi-Marques Inc",
    "wof:placetype":"venue"
},
  "geometry": {"coordinates":[-71.271957,46.79858],"type":"Point"}
}