{
  "type": "Feature",
  "properties": {
    "addr:full":"1425 Boul Rene-Levesque O Montreal QC H3G 1T7",
    "addr:housenumber":"1425",
    "addr:postcode":"h3g 1t7",
    "addr:street":"Boul Rene-Levesque O",
    "iso:country":"CA",
    "sg:address":"1425 Boul Rene-Levesque O",
    "sg:city":"Montreal",
    "sg:classifiers":[
        {
            "category":"Real Estate",
            "subcategory":"Architect",
            "type":"Services"
        }
    ],
    "sg:phone":"+1 514 879 1708",
    "sg:postcode":"H3G 1T7",
    "sg:province":"QC",
    "wof:name":"Duschenes & Fish",
    "wof:placetype":"venue"
},
  "geometry": {"coordinates":[-73.5517959595,45.5195808411],"type":"Point"}
}