{
  "type": "Feature",
  "properties": {
    "iso:country":"CA",
    "sg:address":"50 Boul Taschereau",
    "sg:city":"LA Prairie",
    "sg:classifiers":[
        {
            "category":"Shopping",
            "subcategory":"Stationery & Office Supplies",
            "type":"Retail Goods"
        }
    ],
    "sg:phone":"+1 450 444 5007",
    "sg:postcode":"J5R 4V3",
    "sg:province":"QC",
    "sg:tags":[
        "cigarette",
        "cigar",
        "dealer",
        "tobacco"
    ],
    "wof:name":"Cigarobec",
    "wof:placetype":"venue"
},
  "geometry": {"coordinates":[-73.484116,45.423779],"type":"Point"}
}