{
  "type": "Feature",
  "properties": {
    "iso:country":"CA",
    "sg:city":"Waterdown",
    "sg:classifiers":[
        {
            "category":"Professional",
            "subcategory":"Accounting & Tax Preparation",
            "type":"Services"
        }
    ],
    "sg:phone":"+1 905 689 7823",
    "sg:postcode":"L0R 2H6",
    "sg:province":"ON",
    "sg:tags":[
        "return",
        "filing"
    ],
    "wof:name":"Waterdown Income Tax & Bkpg",
    "wof:placetype":"venue"
},
  "geometry": {"coordinates":[-79.8982086182,43.3290176392],"type":"Point"}
}