{
  "type": "Feature",
  "properties": {
    "addr:full":"8 Huron St Lindsay ON K9V 6K3",
    "addr:housenumber":"8",
    "addr:postcode":"k9v 6k3",
    "addr:street":"Huron St",
    "iso:country":"CA",
    "sg:address":"8 Huron St",
    "sg:city":"Lindsay",
    "sg:classifiers":[
        {
            "category":"Organizations",
            "subcategory":"Religious Organization",
            "type":"Services"
        }
    ],
    "sg:phone":"+1 705 878 8217",
    "sg:postcode":"K9V 6K3",
    "sg:province":"ON",
    "sg:tags":[
        "church"
    ],
    "wof:name":"Guy Mills Court",
    "wof:placetype":"venue"
},
  "geometry": {"coordinates":[-78.730087,44.356213],"type":"Point"}
}