{
  "type": "Feature",
  "properties": {
    "addr:full":"1707 St Laurent Blvd Ottawa ON K1G 3V4",
    "addr:housenumber":"1707",
    "addr:postcode":"k1g 3v4",
    "addr:street":"St Laurent Blvd",
    "iso:country":"CA",
    "sg:address":"1707 St Laurent Blvd",
    "sg:city":"Ottawa",
    "sg:classifiers":[
        {
            "category":"Home & Garden",
            "subcategory":"Home Furnishings",
            "type":"Retail Goods"
        }
    ],
    "sg:phone":"+1 613 733 9927",
    "sg:postcode":"K1G 3V4",
    "sg:province":"ON",
    "sg:tags":[
        "curtain",
        "made",
        "drapery"
    ],
    "wof:name":"Shoppers Drapes & Blinds",
    "wof:placetype":"venue"
},
  "geometry": {"coordinates":[-75.6268463135,45.4059562683],"type":"Point"}
}