{
  "type": "Feature",
  "properties": {
    "addr:full":"2301 Rue Fleury E Montreal QC H2B 1K8",
    "addr:housenumber":"2301",
    "addr:postcode":"h2b 1k8",
    "addr:street":"Rue Fleury E",
    "iso:country":"CA",
    "sg:address":"2301 Rue Fleury E",
    "sg:city":"Montreal",
    "sg:classifiers":[
        {
            "category":"Manufacturing",
            "subcategory":"Paper Products",
            "type":"Manufacturing & Wholesale Goods"
        }
    ],
    "sg:phone":"+1 514 383 5874",
    "sg:postcode":"H2B 1K8",
    "sg:province":"QC",
    "sg:tags":[
        "packaging",
        "material"
    ],
    "wof:name":"Audace Les Emballages Inc",
    "wof:placetype":"venue"
},
  "geometry": {"coordinates":[-73.64916229249999,45.5737571716],"type":"Point"}
}