{
  "type": "Feature",
  "properties": {
    "iso:country":"CA",
    "sg:city":"North York",
    "sg:classifiers":[
        {
            "category":"Wholesale",
            "subcategory":"Apparel",
            "type":"Manufacturing & Wholesale Goods"
        }
    ],
    "sg:phone":"+1 416 351 9942",
    "sg:postcode":"M6B 1P8",
    "sg:province":"ON",
    "wof:name":"Hagerty & Le Messurier Sales",
    "wof:placetype":"venue"
},
  "geometry": {"coordinates":[-79.45729064939999,43.7025909424],"type":"Point"}
}