{
  "type": "Feature",
  "properties": {
    "addr:full":"972 Marine Dr #303 North Vancouver BC V7P 3M9",
    "addr:housenumber":"972",
    "addr:postcode":"v7p 3m9",
    "addr:street":"Marine Dr # 303",
    "iso:country":"CA",
    "sg:address":"972 Marine Dr #303",
    "sg:city":"North Vancouver",
    "sg:classifiers":[
        {
            "category":"Social Services",
            "subcategory":"Child Care",
            "type":"Services"
        }
    ],
    "sg:phone":"+1 604 990 5572",
    "sg:postcode":"V7P 3M9",
    "sg:province":"BC",
    "wof:name":"Park Place Daycare Ltd",
    "wof:placetype":"venue"
},
  "geometry": {"coordinates":[-123.100440979,49.3233261108],"type":"Point"}
}