{
  "type": "Feature",
  "properties": {
    "iso:country":"CA",
    "sg:address":"186 Central St",
    "sg:city":"Chester",
    "sg:classifiers":[
        {
            "category":"Government",
            "subcategory":"Office",
            "type":"Public Place"
        }
    ],
    "sg:phone":"+1 902 275 5840",
    "sg:postcode":"B0J 1J0",
    "sg:province":"NS",
    "sg:tags":[
        "village"
    ],
    "wof:name":"Chester Regional Devel Agency",
    "wof:placetype":"venue"
},
  "geometry": {"coordinates":[-64.2417831421,44.5462760925],"type":"Point"}
}