{
  "type": "Feature",
  "properties": {
    "addr:full":"128 Woolwich St Guelph ON N1H 3V2",
    "addr:housenumber":"128",
    "addr:postcode":"n1h 3v2",
    "addr:street":"Woolwich St",
    "iso:country":"CA",
    "sg:address":"128 Woolwich St",
    "sg:city":"Guelph",
    "sg:classifiers":[
        {
            "category":"Home & Garden",
            "subcategory":"Home Furnishings",
            "type":"Retail Goods"
        }
    ],
    "sg:phone":"+1 519 836 4326",
    "sg:postcode":"N1H 3V2",
    "sg:province":"ON",
    "sg:tags":[
        "pottery"
    ],
    "wof:name":"Stonehouse Pottery",
    "wof:placetype":"venue"
},
  "geometry": {"coordinates":[-80.24973300000001,43.5476],"type":"Point"}
}