{
  "type": "Feature",
  "properties": {
    "addr:full":"311 Columbia St Kamloops BC V2C 2T1",
    "addr:housenumber":"311",
    "addr:postcode":"bc v2c 2t1",
    "addr:street":"Columbia St",
    "iso:country":"CA",
    "sg:address":"311 Columbia St",
    "sg:city":"Kamloops",
    "sg:classifiers":[
        {
            "category":"Health Services",
            "subcategory":"Hospital",
            "type":"Services"
        }
    ],
    "sg:phone":"+1 250 374 5111",
    "sg:postcode":"V2C 2T1",
    "sg:province":"BC",
    "wof:name":"Royal Inland Hospital",
    "wof:placetype":"venue"
},
  "geometry": {"coordinates":[-120.33403015099999,50.6712913513],"type":"Point"}
}