{
  "type": "Feature",
  "properties": {
    "addr:full":"LA Ronge SK S0J 1L0",
    "addr:postcode":"s0j 1l0",
    "iso:country":"CA",
    "sg:city":"LA Ronge",
    "sg:classifiers":[
        {
            "category":"Wholesale",
            "subcategory":"Groceries",
            "type":"Manufacturing & Wholesale Goods"
        }
    ],
    "sg:phone":"+1 306 425 2314",
    "sg:postcode":"S0J 1L0",
    "sg:province":"SK",
    "sg:tags":[
        "grocer"
    ],
    "wof:name":"Riese's Canadian Lake Wild Ric",
    "wof:placetype":"venue"
},
  "geometry": {"coordinates":[-105.295326233,55.1124954224],"type":"Point"}
}