{
  "type": "Feature",
  "properties": {
    "iso:country":"CA",
    "sg:address":"7216 8th Ave",
    "sg:city":"Regina",
    "sg:classifiers":[
        {
            "category":"Building & Trades",
            "subcategory":"Construction",
            "type":"Services"
        }
    ],
    "sg:phone":"+1 306 757 5433",
    "sg:postcode":"S4T 0W9",
    "sg:province":"SK",
    "sg:tags":[
        "general",
        "contractor"
    ],
    "wof:name":"Nortec Enterprises",
    "wof:placetype":"venue"
},
  "geometry": {"coordinates":[-104.68196106000001,50.4572296143],"type":"Point"}
}