{
  "type": "Feature",
  "properties": {
    "addr:full":"1 Commercial Crt Fox Creek AB T0H 1P0",
    "addr:housenumber":"1",
    "addr:postcode":"t0h 1p0",
    "addr:street":"Commercial Crt Fox",
    "iso:country":"CA",
    "sg:address":"1 Commercial Crt",
    "sg:city":"Fox Creek",
    "sg:classifiers":[
        {
            "category":"Travel",
            "subcategory":"Hotels & Motels",
            "type":"Entertainment"
        }
    ],
    "sg:phone":"+1 780 622 3792",
    "sg:postcode":"T0H 1P0",
    "sg:province":"AB",
    "wof:name":"Grizzly Motor Hotel",
    "wof:placetype":"venue"
},
  "geometry": {"coordinates":[-116.804794,54.394127],"type":"Point"}
}