{
  "type": "Feature",
  "properties": {
    "iso:country":"CA",
    "sg:address":"42 Wright St",
    "sg:city":"St Catharines",
    "sg:classifiers":[
        {
            "category":"Wholesale",
            "subcategory":"Hardware",
            "type":"Manufacturing & Wholesale Goods"
        }
    ],
    "sg:phone":"+1 905 687 3583",
    "sg:postcode":"L2P 3J4",
    "sg:province":"ON",
    "sg:tags":[
        "plumbing",
        "purifying",
        "fixture",
        "cleaning",
        "air"
    ],
    "wof:name":"Bardon Supplies",
    "wof:placetype":"venue"
},
  "geometry": {"coordinates":[-79.217293,43.167751],"type":"Point"}
}