{
  "type": "Feature",
  "properties": {
    "iso:country":"CA",
    "sg:address":"245 Rue Saint-Georges",
    "sg:city":"Trois-Rivieres",
    "sg:classifiers":[
        {
            "category":"Health Services",
            "subcategory":"Health Practitioner",
            "type":"Services"
        }
    ],
    "sg:phone":"+1 819 371 2164",
    "sg:postcode":"G9A 2K1",
    "sg:province":"QC",
    "sg:tags":[
        "physiotherapist"
    ],
    "wof:name":"Clinique DE Physiotherapie DE",
    "wof:placetype":"venue"
},
  "geometry": {"coordinates":[-72.542053,46.340302],"type":"Point"}
}