{
  "type": "Feature",
  "properties": {
    "iso:country":"CA",
    "sg:address":"4075 Rhodes Dr",
    "sg:city":"Windsor",
    "sg:classifiers":[
        {
            "category":"Wholesale",
            "subcategory":"Metals & Minerals",
            "type":"Manufacturing & Wholesale Goods"
        }
    ],
    "sg:phone":"+1 519 948 5246",
    "sg:postcode":"N8W 5B5",
    "sg:province":"ON",
    "sg:tags":[
        "pipe"
    ],
    "wof:name":"Crane Supply",
    "wof:placetype":"venue"
},
  "geometry": {"coordinates":[-82.96272999999999,42.283775],"type":"Point"}
}