{
  "type": "Feature",
  "properties": {
    "addr:full":"2222 Rue Ontario E Montreal QC H2K 1V8",
    "addr:housenumber":"2222",
    "addr:postcode":"h2k 1v8",
    "addr:street":"Rue Ontario E",
    "iso:country":"CA",
    "sg:address":"2222 Rue Ontario E",
    "sg:city":"Montreal",
    "sg:classifiers":[
        {
            "category":"Shopping",
            "subcategory":"Musical Instruments",
            "type":"Retail Goods"
        }
    ],
    "sg:phone":"+1 514 526 5969",
    "sg:postcode":"H2K 1V8",
    "sg:province":"QC",
    "wof:name":"Boite A Musique Gl Inc",
    "wof:placetype":"venue"
},
  "geometry": {"coordinates":[-73.555611,45.529629],"type":"Point"}
}