{
  "type": "Feature",
  "properties": {
    "iso:country":"CA",
    "sg:address":"RR 4 STN Main",
    "sg:city":"Kincardine",
    "sg:classifiers":[
        {
            "category":"Building & Trades",
            "subcategory":"Construction",
            "type":"Services"
        }
    ],
    "sg:phone":"+1 519 395 5692",
    "sg:postcode":"N2Z 2X5",
    "sg:province":"ON",
    "sg:tags":[
        "contractor"
    ],
    "wof:name":"Armstrong Carpentry Ltd",
    "wof:placetype":"venue"
},
  "geometry": {"coordinates":[-81.6317367554,44.1816139221],"type":"Point"}
}