{
  "type": "Feature",
  "properties": {
    "addr:full":"103 Weston Ave E Maidstone SK S0M 1M0",
    "addr:housenumber":"103",
    "addr:postcode":"s0m 1m0",
    "addr:street":"Weston Ave E",
    "iso:country":"CA",
    "sg:address":"103 Weston Ave E",
    "sg:city":"Maidstone",
    "sg:classifiers":[
        {
            "category":"Wholesale",
            "subcategory":"Construction Materials",
            "type":"Manufacturing & Wholesale Goods"
        }
    ],
    "sg:phone":"+1 306 893 2662",
    "sg:postcode":"S0M 1M0",
    "sg:province":"SK",
    "sg:tags":[
        "sand",
        "gravel"
    ],
    "wof:name":"Wesco Services Ltd",
    "wof:placetype":"venue"
},
  "geometry": {"coordinates":[-109.296607971,53.0874595642],"type":"Point"}
}