{
  "type": "Feature",
  "properties": {
    "addr:full":"80 Ch Mckee Stoneham QC G0A 4P0",
    "addr:housenumber":"80",
    "addr:postcode":"g0a 4p0",
    "addr:street":"Ch Mckee",
    "iso:country":"CA",
    "sg:address":"80 Ch Mckee",
    "sg:city":"Stoneham",
    "sg:classifiers":[
        {
            "category":"Professional",
            "subcategory":"Art Services",
            "type":"Services"
        }
    ],
    "sg:phone":"+1 418 948 6794",
    "sg:postcode":"G0A 4P0",
    "sg:province":"QC",
    "sg:tags":[
        "photographer"
    ],
    "wof:name":"Soulard, Pierre",
    "wof:placetype":"venue"
},
  "geometry": {"coordinates":[-71.37790679930001,46.9752464294],"type":"Point"}
}