{
  "type": "Feature",
  "properties": {
    "addr:full":"975 Rue Moreau Saint-Hubert QC J3Y 6J9",
    "addr:housenumber":"975",
    "addr:postcode":"j3y 6j9",
    "addr:street":"Rue Moreau",
    "iso:country":"CA",
    "sg:address":"975 Rue Moreau",
    "sg:city":"Saint-Hubert",
    "sg:classifiers":[
        {
            "category":"Professional",
            "subcategory":"Art Services",
            "type":"Services"
        }
    ],
    "sg:phone":"+1 450 462 2518",
    "sg:postcode":"J3Y 6J9",
    "sg:province":"QC",
    "sg:tags":[
        "graphic",
        "designer"
    ],
    "wof:name":"Jacques Poisson's Office",
    "wof:placetype":"venue"
},
  "geometry": {"coordinates":[-73.40743255620001,45.5044326782],"type":"Point"}
}