{
  "type": "Feature",
  "properties": {
    "addr:full":"Dorval QC H9S 1L7",
    "addr:postcode":"h9s 1l7",
    "iso:country":"CA",
    "sg:city":"Dorval",
    "sg:classifiers":[
        {
            "category":"Professional",
            "subcategory":"Business Services",
            "type":"Services"
        }
    ],
    "sg:phone":"+1 514 631 0000",
    "sg:postcode":"H9S 1L7",
    "sg:province":"QC",
    "sg:tags":[
        "telemarketing"
    ],
    "wof:name":"Linton Service D'Appels",
    "wof:placetype":"venue"
},
  "geometry": {"coordinates":[-73.73932600000001,45.444084],"type":"Point"}
}