{
  "type": "Feature",
  "properties": {
    "addr:full":"186 Hurontario St #102 Collingwood ON L9Y 4T4",
    "addr:housenumber":"186",
    "addr:postcode":"l9y 4t4",
    "addr:street":"Hurontario St # 102",
    "iso:country":"CA",
    "sg:address":"186 Hurontario St #102",
    "sg:city":"Collingwood",
    "sg:classifiers":[
        {
            "category":"Professional",
            "subcategory":"Accounting & Tax Preparation",
            "type":"Services"
        }
    ],
    "sg:phone":"+1 705 444 1417",
    "sg:postcode":"L9Y 4T4",
    "sg:province":"ON",
    "sg:tags":[
        "return",
        "filing"
    ],
    "wof:name":"H & R Block Canada Inc",
    "wof:placetype":"venue"
},
  "geometry": {"coordinates":[-80.21668243409999,44.4981842041],"type":"Point"}
}