{
  "type": "Feature",
  "properties": {
    "addr:full":"509 Edward St N #3 Thunder Bay ON P7C 4R1",
    "addr:housenumber":"509",
    "addr:postcode":"p7c 4r1",
    "addr:street":"Edward St N # 3",
    "iso:country":"CA",
    "sg:address":"509 Edward St N #3",
    "sg:city":"Thunder Bay",
    "sg:classifiers":[
        {
            "category":"Personal",
            "subcategory":"Beauty Salon",
            "type":"Services"
        }
    ],
    "sg:phone":"+1 807 475 4444",
    "sg:postcode":"P7C 4R1",
    "sg:province":"ON",
    "wof:name":"Avanti Hair Salon",
    "wof:placetype":"venue"
},
  "geometry": {"coordinates":[-89.2776184082,48.3944282532],"type":"Point"}
}