{
  "type": "Feature",
  "properties": {
    "addr:full":"325 Sixth St New Westminster BC V3L 3A9",
    "addr:housenumber":"325",
    "addr:postcode":"v3l 3a9",
    "addr:street":"Sixth St",
    "iso:country":"CA",
    "sg:address":"325 Sixth St",
    "sg:city":"New Westminster",
    "sg:classifiers":[
        {
            "category":"Organizations",
            "subcategory":"Religious Organization",
            "type":"Services"
        }
    ],
    "sg:phone":"+1 604 521 0363",
    "sg:postcode":"V3L 3A9",
    "sg:province":"BC",
    "sg:tags":[
        "church"
    ],
    "wof:name":"Salvation Army",
    "wof:placetype":"venue"
},
  "geometry": {"coordinates":[-122.915665,49.209606],"type":"Point"}
}