{
  "type": "Feature",
  "properties": {
    "addr:full":"PO Box 123 STN Main Winnipeg MB R3C 2G1",
    "addr:housenumber":"po",
    "addr:postcode":"r3c 2g1",
    "addr:street":"Box 123 Stn",
    "iso:country":"CA",
    "sg:address":"PO Box 123 STN Main",
    "sg:city":"Winnipeg",
    "sg:classifiers":[
        {
            "category":"Shopping",
            "subcategory":"Florist",
            "type":"Retail Goods"
        }
    ],
    "sg:phone":"+1 204 669 9669",
    "sg:postcode":"R3C 2G1",
    "sg:province":"MB",
    "sg:tags":[
        "personal",
        "bureau"
    ],
    "wof:name":"Living Interiors",
    "wof:placetype":"venue"
},
  "geometry": {"coordinates":[-97.140739,49.899426],"type":"Point"}
}