{
  "type": "Feature",
  "properties": {
    "iso:country":"CA",
    "sg:address":"8530 Young Rd",
    "sg:city":"Chilliwack",
    "sg:classifiers":[
        {
            "category":"Government",
            "subcategory":"Fire Station",
            "type":"Public Place"
        }
    ],
    "sg:phone":"+1 604 792 8713",
    "sg:postcode":"V2P 4P1",
    "sg:province":"BC",
    "sg:tags":[
        "department"
    ],
    "wof:name":"Chilliwack Fire Dept",
    "wof:placetype":"venue"
},
  "geometry": {"coordinates":[-121.951332092,49.1569786072],"type":"Point"}
}