{
  "type": "Feature",
  "properties": {
    "addr:full":"1596 Ouellette Ave Windsor ON N8X 1K7",
    "addr:housenumber":"1596",
    "addr:postcode":"n8x 1k7",
    "addr:street":"Ouellette Ave",
    "iso:country":"CA",
    "sg:address":"1596 Ouellette Ave",
    "sg:city":"Windsor",
    "sg:classifiers":[
        {
            "category":"Shopping",
            "subcategory":"Optical Goods",
            "type":"Retail Goods"
        }
    ],
    "sg:phone":"+1 519 254 0252",
    "sg:postcode":"N8X 1K7",
    "sg:province":"ON",
    "sg:tags":[
        "optician"
    ],
    "wof:name":"M L Soulliere Opticians",
    "wof:placetype":"venue"
},
  "geometry": {"coordinates":[-83.02648162840001,42.2982711792],"type":"Point"}
}