{
  "type": "Feature",
  "properties": {
    "addr:full":"506269 Highway 89 Shelburne ON L0N 1S8",
    "addr:housenumber":"506269",
    "addr:postcode":"l0n 1s8",
    "addr:street":"Highway 89",
    "iso:country":"CA",
    "sg:address":"506269 Highway 89",
    "sg:city":"Shelburne",
    "sg:classifiers":[
        {
            "category":"Restaurant",
            "type":"Food & Drink"
        }
    ],
    "sg:phone":"+1 519 925 2810",
    "sg:postcode":"L0N 1S8",
    "sg:province":"ON",
    "wof:name":"Superburger",
    "wof:placetype":"venue"
},
  "geometry": {"coordinates":[-80.20208700000001,44.078785],"type":"Point"}
}