{
  "type": "Feature",
  "properties": {
    "addr:full":"195 Place Du Marche-Du-Nord Montreal QC H2S 1A2",
    "addr:housenumber":"195",
    "addr:postcode":"h2s 1a2",
    "addr:street":"Place Du Marche-Du-Nord",
    "iso:country":"CA",
    "sg:address":"195 Place Du Marche-Du-Nord",
    "sg:city":"Montreal",
    "sg:classifiers":[
        {
            "category":"Food & Beverages",
            "subcategory":"Groceries & Convenience Stores",
            "type":"Retail Goods"
        }
    ],
    "sg:phone":"+1 514 277 8752",
    "sg:postcode":"H2S 1A2",
    "sg:province":"QC",
    "sg:tags":[
        "grocer"
    ],
    "wof:name":"Ultrasruits",
    "wof:placetype":"venue"
},
  "geometry": {"coordinates":[-73.6158752441,45.5362815857],"type":"Point"}
}