{
  "type": "Feature",
  "properties": {
    "iso:country":"CA",
    "sg:address":"798 Boul Henri-Bourassa E",
    "sg:city":"Montreal",
    "sg:classifiers":[
        {
            "category":"Health Services",
            "subcategory":"Chiropractor",
            "type":"Services"
        }
    ],
    "sg:phone":"+1 514 382 3566",
    "sg:postcode":"H2C 1E6",
    "sg:province":"QC",
    "wof:name":"Clinique Chiropratique Caron",
    "wof:placetype":"venue"
},
  "geometry": {"coordinates":[-73.6669998169,45.5581626892],"type":"Point"}
}