{
  "type": "Feature",
  "properties": {
    "addr:full":"Scarborough ON M1G 3V5",
    "addr:postcode":"m1g 3v5",
    "iso:country":"CA",
    "sg:city":"Scarborough",
    "sg:classifiers":[
        {
            "category":"Manufacturing",
            "subcategory":"Tools & Machinery",
            "type":"Manufacturing & Wholesale Goods"
        }
    ],
    "sg:phone":"+1 416 289 8882",
    "sg:postcode":"M1G 3V5",
    "sg:province":"ON",
    "sg:tags":[
        "equipment",
        "purifying",
        "cleaning",
        "air"
    ],
    "wof:name":"Cimatec Environmental Engnrng",
    "wof:placetype":"venue"
},
  "geometry": {"coordinates":[-79.231865,43.783005],"type":"Point"}
}