{
  "type": "Feature",
  "properties": {
    "addr:full":"29 Saint Andrews St Toronto ON M5T 1K7",
    "addr:housenumber":"29",
    "addr:postcode":"m5t 1k7",
    "addr:street":"Saint Andrews St",
    "iso:country":"CA",
    "sg:address":"29 Saint Andrews St",
    "sg:city":"Toronto",
    "sg:classifiers":[
        {
            "category":"Food & Beverages",
            "subcategory":"Specialty",
            "type":"Retail Goods"
        }
    ],
    "sg:phone":"+1 416 593 5238",
    "sg:postcode":"M5T 1K7",
    "sg:province":"ON",
    "sg:tags":[
        "herb",
        "health",
        "diet"
    ],
    "wof:name":"International Herbs CO",
    "wof:placetype":"venue"
},
  "geometry": {"coordinates":[-79.399261,43.654133],"type":"Point"}
}