{
  "type": "Feature",
  "properties": {
    "addr:full":"386 N Albert St Regina SK S4R 3C1",
    "addr:housenumber":"386",
    "addr:postcode":"s4r 3c1",
    "addr:street":"N Albert St",
    "iso:country":"CA",
    "sg:address":"386 N Albert St",
    "sg:city":"Regina",
    "sg:classifiers":[
        {
            "category":"Health Services",
            "subcategory":"Medical Lab",
            "type":"Services"
        }
    ],
    "sg:phone":"+1 306 543 3301",
    "sg:postcode":"S4R 3C1",
    "sg:province":"SK",
    "wof:name":"Northgate Denture Clinic",
    "wof:placetype":"venue"
},
  "geometry": {"coordinates":[-104.618431,50.482037],"type":"Point"}
}