{
  "type": "Feature",
  "properties": {
    "addr:full":"7 Red Bank Dr Chipman NB E4A 2A1",
    "addr:housenumber":"7",
    "addr:postcode":"e4a 2a1",
    "addr:street":"Red Bank Dr",
    "iso:country":"CA",
    "sg:address":"7 Red Bank Dr",
    "sg:city":"Chipman",
    "sg:classifiers":[
        {
            "category":"Restaurant",
            "type":"Food & Drink"
        }
    ],
    "sg:phone":"+1 506 339 5929",
    "sg:postcode":"E4A 2A1",
    "sg:province":"NB",
    "wof:name":"Willa's Country Kitchen Ltd",
    "wof:placetype":"venue"
},
  "geometry": {"coordinates":[-65.8807296753,46.1758956909],"type":"Point"}
}