{
  "type": "Feature",
  "properties": {
    "addr:full":"4490 Conc 7 Windsor ON N9A 6J3",
    "addr:housenumber":"4490;7",
    "addr:postcode":"n9a 6j3",
    "addr:street":"Conc",
    "iso:country":"CA",
    "sg:address":"4490 Conc 7",
    "sg:city":"Windsor",
    "sg:classifiers":[
        {
            "category":"Organizations",
            "subcategory":"Religious Organization",
            "type":"Services"
        }
    ],
    "sg:phone":"+1 519 972 5977",
    "sg:postcode":"N9A 6J3",
    "sg:province":"ON",
    "sg:tags":[
        "church"
    ],
    "wof:name":"Windsor Christian Fellowship",
    "wof:placetype":"venue"
},
  "geometry": {"coordinates":[-82.96247099999999,42.254002],"type":"Point"}
}