{
  "type": "Feature",
  "properties": {
    "iso:country":"CA",
    "sg:city":"Boissevain",
    "sg:classifiers":[
        {
            "category":"Farming",
            "subcategory":"Farm & Veterinary Services",
            "type":"Manufacturing & Wholesale Goods"
        }
    ],
    "sg:phone":"+1 204 534 6692",
    "sg:postcode":"R0K 0E0",
    "sg:province":"MB",
    "sg:tags":[
        "seed",
        "grain",
        "cleaning"
    ],
    "wof:name":"West Gro Seeds Svc Ltd",
    "wof:placetype":"venue"
},
  "geometry": {"coordinates":[-100.059455872,49.2296257019],"type":"Point"}
}