{
  "type": "Feature",
  "properties": {
    "iso:country":"CA",
    "sg:address":"7090 Kingsway",
    "sg:city":"Burnaby",
    "sg:classifiers":[
        {
            "category":"Restaurant",
            "type":"Food & Drink"
        }
    ],
    "sg:phone":"+1 604 526 3712",
    "sg:postcode":"V5E 1E7",
    "sg:province":"BC",
    "wof:name":"Boua Thai Restaurant Ltd",
    "wof:placetype":"venue"
},
  "geometry": {"coordinates":[-122.95783996599999,49.2183151245],"type":"Point"}
}