{
  "type": "Feature",
  "properties": {
    "addr:full":"Ottawa ON K2C 0C7",
    "addr:postcode":"k2c 0c7",
    "iso:country":"CA",
    "sg:city":"Ottawa",
    "sg:classifiers":[
        {
            "category":"Social Services",
            "type":"Services"
        }
    ],
    "sg:phone":"+1 613 274 3214",
    "sg:postcode":"K2C 0C7",
    "sg:province":"ON",
    "sg:tags":[
        "counselor",
        "marriage",
        "family"
    ],
    "wof:name":"Couples Coach",
    "wof:placetype":"venue"
},
  "geometry": {"coordinates":[-75.7585067749,45.3535881042],"type":"Point"}
}