{
  "type": "Feature",
  "properties": {
    "iso:country":"CA",
    "sg:address":"2030 Rue Lottinville",
    "sg:city":"Saint-Paulin",
    "sg:classifiers":[
        {
            "category":"Retail",
            "subcategory":"Auto Repair",
            "type":"Services"
        }
    ],
    "sg:phone":"+1 819 268 2004",
    "sg:postcode":"J0K 3G0",
    "sg:province":"QC",
    "sg:tags":[
        "repairing",
        "automobile"
    ],
    "wof:name":"Garage Daniel & Louis Frappier",
    "wof:placetype":"venue"
},
  "geometry": {"coordinates":[-73.0200500488,46.4189682007],"type":"Point"}
}