{
  "type": "Feature",
  "properties": {
    "addr:full":"Guelph ON N1H 6J2",
    "addr:postcode":"n1h 6j2",
    "iso:country":"CA",
    "sg:city":"Guelph",
    "sg:classifiers":[
        {
            "category":"Manufacturing",
            "subcategory":"Metals",
            "type":"Manufacturing & Wholesale Goods"
        }
    ],
    "sg:phone":"+1 519 823 5110",
    "sg:postcode":"N1H 6J2",
    "sg:province":"ON",
    "sg:tags":[
        "welding"
    ],
    "wof:name":"General Welding",
    "wof:placetype":"venue"
},
  "geometry": {"coordinates":[-80.2478713989,43.5445632935],"type":"Point"}
}