{
  "type": "Feature",
  "properties": {
    "addr:full":"20 Pamcrest Dr North York ON M2M 2M1",
    "addr:housenumber":"20",
    "addr:postcode":"m2m 2m1",
    "addr:street":"Pamcrest Dr",
    "iso:country":"CA",
    "sg:address":"20 Pamcrest Dr",
    "sg:city":"North York",
    "sg:classifiers":[
        {
            "category":"Building & Trades",
            "subcategory":"Landscaping Services",
            "type":"Services"
        }
    ],
    "sg:phone":"+1 416 225 4262",
    "sg:postcode":"M2M 2M1",
    "sg:province":"ON",
    "sg:tags":[
        "sod",
        "sodding"
    ],
    "wof:name":"W Hughes Sodding & Grading",
    "wof:placetype":"venue"
},
  "geometry": {"coordinates":[-79.40678405760001,43.7937850952],"type":"Point"}
}