{
  "type": "Feature",
  "properties": {
    "iso:country":"CA",
    "sg:address":"9281 15E Av",
    "sg:city":"Montreal",
    "sg:classifiers":[
        {
            "category":"Real Estate",
            "subcategory":"Real Estate Operator",
            "type":"Services"
        }
    ],
    "sg:phone":"+1 514 723 3242",
    "sg:postcode":"H1Z 3P4",
    "sg:province":"QC",
    "sg:tags":[
        "apartment"
    ],
    "wof:name":"Centre D'Hebergement Fontaine",
    "wof:placetype":"venue"
},
  "geometry": {"coordinates":[-73.6293716431,45.5757637024],"type":"Point"}
}