{
  "type": "Feature",
  "properties": {
    "addr:full":"21 Keppler Cres Nepean ON K2H 5Y1",
    "addr:housenumber":"21",
    "addr:postcode":"k2h 5y1",
    "addr:street":"Keppler Cres",
    "iso:country":"CA",
    "sg:address":"21 Keppler Cres",
    "sg:city":"Nepean",
    "sg:classifiers":[
        {
            "category":"Shopping",
            "subcategory":"Bicycles & Sporting Goods",
            "type":"Retail Goods"
        }
    ],
    "sg:phone":"+1 613 829 4378",
    "sg:postcode":"K2H 5Y1",
    "sg:province":"ON",
    "sg:tags":[
        "awning",
        "canopy"
    ],
    "wof:name":"Norseman Group",
    "wof:placetype":"venue"
},
  "geometry": {"coordinates":[-75.787216,45.331161],"type":"Point"}
}