{
  "type": "Feature",
  "properties": {
    "addr:full":"2985 Pembina Hwy Winnipeg MB R3T 2H5",
    "addr:housenumber":"2985",
    "addr:postcode":"r3t 2h5",
    "addr:street":"Pembina Hwy",
    "iso:country":"CA",
    "sg:address":"2985 Pembina Hwy",
    "sg:city":"Winnipeg",
    "sg:classifiers":[
        {
            "category":"Restaurant",
            "type":"Food & Drink"
        }
    ],
    "sg:phone":"+1 204 269 4611",
    "sg:postcode":"R3T 2H5",
    "sg:province":"MB",
    "sg:tags":[
        "pizza"
    ],
    "wof:name":"Santa Lucia Pizza Winnipeg Ltd",
    "wof:placetype":"venue"
},
  "geometry": {"coordinates":[-97.157448,49.785011],"type":"Point"}
}