{
  "type": "Feature",
  "properties": {
    "iso:country":"CA",
    "sg:address":"2985 Pembina Hwy",
    "sg:city":"Winnipeg",
    "sg:classifiers":[
        {
            "category":"Restaurant",
            "type":"Food & Drink"
        }
    ],
    "sg:phone":"+1 204 269 4611",
    "sg:postcode":"R3T 2H5",
    "sg:province":"MB",
    "sg:tags":[
        "pizza"
    ],
    "wof:name":"Santa Lucia Pizza Winnipeg Ltd",
    "wof:placetype":"venue"
},
  "geometry": {"coordinates":[-97.157448,49.785011],"type":"Point"}
}