{
  "type": "Feature",
  "properties": {
    "addr:full":"6000 Rue Laurendeau Montreal QC H4E 3X4",
    "addr:housenumber":"6000",
    "addr:postcode":"h4e 3x4",
    "addr:street":"Rue Laurendeau",
    "iso:country":"CA",
    "sg:address":"6000 Rue Laurendeau",
    "sg:city":"Montreal",
    "sg:classifiers":[
        {
            "category":"Food & Beverages",
            "subcategory":"Groceries & Convenience Stores",
            "type":"Retail Goods"
        }
    ],
    "sg:phone":"+1 514 766 7367",
    "sg:postcode":"H4E 3X4",
    "sg:province":"QC",
    "sg:tags":[
        "grocer"
    ],
    "wof:name":"Provigo",
    "wof:placetype":"venue"
},
  "geometry": {"coordinates":[-73.58814239500001,45.4584693909],"type":"Point"}
}