{
  "type": "Feature",
  "properties": {
    "addr:full":"Winnipeg MB R3P 0N5",
    "addr:postcode":"r3p 0n5",
    "iso:country":"CA",
    "sg:city":"Winnipeg",
    "sg:classifiers":[
        {
            "category":"Health Services",
            "subcategory":"Doctor",
            "type":"Services"
        }
    ],
    "sg:phone":"+1 204 488 4564",
    "sg:postcode":"R3P 0N5",
    "sg:province":"MB",
    "sg:tags":[
        "dentist"
    ],
    "wof:name":"Cholakis Dental Group",
    "wof:placetype":"venue"
},
  "geometry": {"coordinates":[-97.21163900000001,49.866642],"type":"Point"}
}