{
  "type": "Feature",
  "properties": {
    "addr:full":"161 Nugget Ave Scarborough ON M1S 3B1",
    "addr:housenumber":"161",
    "addr:postcode":"m1s 3b1",
    "addr:street":"Nugget Ave",
    "iso:country":"CA",
    "sg:address":"161 Nugget Ave",
    "sg:city":"Scarborough",
    "sg:classifiers":[
        {
            "category":"Building & Trades",
            "subcategory":"Construction",
            "type":"Services"
        }
    ],
    "sg:phone":"+1 416 299 5151",
    "sg:postcode":"M1S 3B1",
    "sg:province":"ON",
    "sg:tags":[
        "resurfacing",
        "laying",
        "refinishing",
        "floor"
    ],
    "wof:name":"Woodchuck Flooring Inc",
    "wof:placetype":"venue"
},
  "geometry": {"coordinates":[-79.254608,43.793808],"type":"Point"}
}