{
  "type": "Feature",
  "properties": {
    "addr:full":"17915 Leslie St #13 Newmarket ON L3Y 3E3",
    "addr:housenumber":"17915;13",
    "addr:postcode":"l3y 3e3",
    "addr:street":"Leslie St #",
    "iso:country":"CA",
    "sg:address":"17915 Leslie St #13",
    "sg:city":"Newmarket",
    "sg:classifiers":[
        {
            "category":"Building & Trades",
            "subcategory":"Construction",
            "type":"Services"
        }
    ],
    "sg:phone":"+1 905 836 9636",
    "sg:postcode":"L3Y 3E3",
    "sg:province":"ON",
    "sg:tags":[
        "designer",
        "dealer",
        "pool",
        "swimming"
    ],
    "wof:name":"Pioneer Family Pools",
    "wof:placetype":"venue"
},
  "geometry": {"coordinates":[-79.4342575073,44.0759811401],"type":"Point"}
}