{
  "type": "Feature",
  "properties": {
    "addr:full":"Fort Macleod AB T0L 0Z0",
    "addr:postcode":"t0l 0z0",
    "addr:street":"Fort",
    "iso:country":"CA",
    "sg:city":"Fort Macleod",
    "sg:classifiers":[
        {
            "category":"Building & Trades",
            "subcategory":"Plumbing",
            "type":"Services"
        }
    ],
    "sg:phone":"+1 403 553 3729",
    "sg:postcode":"T0L 0Z0",
    "sg:province":"AB",
    "sg:tags":[
        "heating",
        "contractor"
    ],
    "wof:name":"J W Feltin Heating & Air Cond",
    "wof:placetype":"venue"
},
  "geometry": {"coordinates":[-113.40192399999999,49.721039],"type":"Point"}
}