{
  "type": "Feature",
  "properties": {
    "addr:full":"643 Governors Rd E Paris ON N3L 3E1",
    "addr:housenumber":"643",
    "addr:postcode":"n3l 3e1",
    "addr:street":"Governors Rd E",
    "iso:country":"CA",
    "sg:address":"643 Governors Rd E",
    "sg:city":"Paris",
    "sg:classifiers":[
        {
            "category":"Building & Trades",
            "subcategory":"Construction",
            "type":"Services"
        }
    ],
    "sg:phone":"+1 519 442 7665",
    "sg:postcode":"N3L 3E1",
    "sg:province":"ON",
    "sg:tags":[
        "designer",
        "dealer",
        "pool",
        "swimming"
    ],
    "wof:name":"Tottle Pools",
    "wof:placetype":"venue"
},
  "geometry": {"coordinates":[-80.338943,43.195541],"type":"Point"}
}