{
  "type": "Feature",
  "properties": {
    "addr:full":"993 Doran Rd Pembroke ON K8A 6W7",
    "addr:housenumber":"993",
    "addr:postcode":"k8a 6w7",
    "addr:street":"Doran Rd",
    "iso:country":"CA",
    "sg:address":"993 Doran Rd",
    "sg:city":"Pembroke",
    "sg:classifiers":[
        {
            "category":"Retail",
            "subcategory":"Auto Repair",
            "type":"Services"
        }
    ],
    "sg:phone":"+1 613 687 4664",
    "sg:postcode":"K8A 6W7",
    "sg:province":"ON",
    "sg:tags":[
        "repairing",
        "automobile"
    ],
    "wof:name":"Midway Auto",
    "wof:placetype":"venue"
},
  "geometry": {"coordinates":[-77.120369,45.81839],"type":"Point"}
}