{
  "type": "Feature",
  "properties": {
    "addr:full":"324 Sovereign Rd London ON N6M 1A8",
    "addr:housenumber":"324",
    "addr:postcode":"n6m 1a8",
    "addr:street":"Sovereign Rd",
    "iso:country":"CA",
    "sg:address":"324 Sovereign Rd",
    "sg:city":"London",
    "sg:classifiers":[
        {
            "category":"Wholesale",
            "subcategory":"Machinery & Supplies",
            "type":"Manufacturing & Wholesale Goods"
        }
    ],
    "sg:phone":"+1 519 457 7625",
    "sg:postcode":"N6M 1A8",
    "sg:province":"ON",
    "sg:tags":[
        "equipment",
        "industrial"
    ],
    "wof:name":"Silver Top Supply",
    "wof:placetype":"venue"
},
  "geometry": {"coordinates":[-81.13866400000001,42.989666],"type":"Point"}
}