{
  "type": "Feature",
  "properties": {
    "addr:full":"2763 Ch Sainte-Marie Mascouche QC J7K 1N2",
    "addr:postcode":"2763;j7k 1n2",
    "addr:street":"Ch Sainte-Marie",
    "iso:country":"CA",
    "sg:address":"2763 Ch Sainte-Marie",
    "sg:city":"Mascouche",
    "sg:classifiers":[
        {
            "category":"Shopping",
            "subcategory":"Gifts & Souvenirs",
            "type":"Retail Goods"
        }
    ],
    "sg:phone":"+1 450 966 9299",
    "sg:postcode":"J7K 1N2",
    "sg:province":"QC",
    "sg:tags":[
        "school",
        "balloon",
        "artist"
    ],
    "wof:name":"Tourlou En Fete",
    "wof:placetype":"venue"
},
  "geometry": {"coordinates":[-73.6092,45.750965],"type":"Point"}
}