{
  "type": "Feature",
  "properties": {
    "addr:full":"324 172 Rte W St-Nazaire-Du-Lac-St-Jean QC G0W 2V0",
    "addr:housenumber":"172",
    "addr:postcode":"g0w 2v0",
    "addr:street":"Rte W St-Nazaire-Du-Lac-St-Jean",
    "iso:country":"CA",
    "sg:address":"324 172 Rte W",
    "sg:city":"St-Nazaire-Du-Lac-St-Jean",
    "sg:classifiers":[
        {
            "category":"Building & Trades",
            "subcategory":"Construction",
            "type":"Services"
        }
    ],
    "sg:phone":"+1 418 662 4958",
    "sg:postcode":"G0W 2V0",
    "sg:province":"QC",
    "sg:tags":[
        "excavating",
        "demolition",
        "contractor"
    ],
    "wof:name":"Gercom Construction Inc",
    "wof:placetype":"venue"
},
  "geometry": {"coordinates":[-71.48893,48.575619],"type":"Point"}
}