{
  "type": "Feature",
  "properties": {
    "iso:country":"CA",
    "sg:city":"London",
    "sg:classifiers":[
        {
            "category":"Manufacturing",
            "subcategory":"Metals",
            "type":"Manufacturing & Wholesale Goods"
        }
    ],
    "sg:phone":"+1 519 455 9090",
    "sg:postcode":"N5W 5K8",
    "sg:province":"ON",
    "sg:tags":[
        "finisher"
    ],
    "wof:name":"H & G Powder Painting",
    "wof:placetype":"venue"
},
  "geometry": {"coordinates":[-81.1987,42.985477],"type":"Point"}
}