{
  "type": "Feature",
  "properties": {
    "iso:country":"CA",
    "sg:address":"2425 Av Du Pont S",
    "sg:city":"Alma",
    "sg:classifiers":[
        {
            "category":"Manufacturing",
            "subcategory":"Metals",
            "type":"Manufacturing & Wholesale Goods"
        }
    ],
    "sg:phone":"+1 418 668 2200",
    "sg:postcode":"G8B 5V2",
    "sg:province":"QC",
    "sg:tags":[
        "plate",
        "tin"
    ],
    "wof:name":"Energie Mecanique Enr",
    "wof:placetype":"venue"
},
  "geometry": {"coordinates":[-71.656128,48.516548],"type":"Point"}
}