{
  "type": "Feature",
  "properties": {
    "addr:full":"249 Manitoba Rd Winkler MB R6W 4B3",
    "addr:housenumber":"249",
    "addr:postcode":"r6w 4b3",
    "addr:street":"Manitoba Rd",
    "iso:country":"CA",
    "sg:address":"249 Manitoba Rd",
    "sg:city":"Winkler",
    "sg:classifiers":[
        {
            "category":"Building & Trades",
            "subcategory":"Electrical",
            "type":"Services"
        }
    ],
    "sg:phone":"+1 204 325 9571",
    "sg:postcode":"R6W 4B3",
    "sg:province":"MB",
    "sg:tags":[
        "electric",
        "contractor"
    ],
    "wof:name":"D A Loewen Electric Ltd",
    "wof:placetype":"venue"
},
  "geometry": {"coordinates":[-97.93038199999999,49.17186],"type":"Point"}
}