{
  "type": "Feature",
  "properties": {
    "addr:full":"3509 Portage Rd Niagara Falls ON L2J 2K5",
    "addr:housenumber":"3509",
    "addr:postcode":"l2j 2k5",
    "addr:street":"Portage Rd",
    "iso:country":"CA",
    "sg:address":"3509 Portage Rd",
    "sg:city":"Niagara Falls",
    "sg:classifiers":[
        {
            "category":"Restaurant",
            "type":"Food & Drink"
        }
    ],
    "sg:phone":"+1 905 356 7950",
    "sg:postcode":"L2J 2K5",
    "sg:province":"ON",
    "sg:tags":[
        "parlor",
        "ice",
        "cream"
    ],
    "wof:name":"Dairy Queen",
    "wof:placetype":"venue"
},
  "geometry": {"coordinates":[-79.0997467041,43.1212348938],"type":"Point"}
}