{
  "type": "Feature",
  "properties": {
    "addr:full":"808 Robertson St Kenora ON P9N 1X9",
    "addr:housenumber":"808",
    "addr:postcode":"p9n 1x9",
    "addr:street":"Robertson St",
    "iso:country":"CA",
    "sg:address":"808 Robertson St",
    "sg:city":"Kenora",
    "sg:classifiers":[
        {
            "category":"Government",
            "subcategory":"Office",
            "type":"Public Place"
        }
    ],
    "sg:phone":"+1 807 468 2769",
    "sg:postcode":"P9N 1X9",
    "sg:province":"ON",
    "wof:name":"Ontario Construction Office",
    "wof:placetype":"venue"
},
  "geometry": {"coordinates":[-94.487206,49.756092],"type":"Point"}
}