{
  "type": "Feature",
  "properties": {
    "addr:full":"10 Bayside Dr Saint John NB E2J 1A2",
    "addr:housenumber":"10",
    "addr:postcode":"e2j 1a2",
    "addr:street":"Bayside Dr",
    "iso:country":"CA",
    "sg:address":"10 Bayside Dr",
    "sg:city":"Saint John",
    "sg:classifiers":[
        {
            "category":"Restaurant",
            "type":"Food & Drink"
        }
    ],
    "sg:phone":"+1 506 652 3232",
    "sg:postcode":"E2J 1A2",
    "sg:province":"NB",
    "sg:tags":[
        "pizza"
    ],
    "wof:name":"Pizza Twice Inc",
    "wof:placetype":"venue"
},
  "geometry": {"coordinates":[-66.04247283940001,45.2864952087],"type":"Point"}
}