{
  "type": "Feature",
  "properties": {
    "iso:country":"CA",
    "sg:city":"Fort Mcmurray",
    "sg:classifiers":[
        {
            "category":"Autos & Motor Vehicles",
            "subcategory":"Auto Supplies",
            "type":"Retail Goods"
        }
    ],
    "sg:phone":"+1 780 791 3000",
    "sg:postcode":"T9H 4A2",
    "sg:province":"AB",
    "sg:tags":[
        "automobile",
        "parts"
    ],
    "wof:name":"Uap Napa Auto Parts",
    "wof:placetype":"venue"
},
  "geometry": {"coordinates":[-111.35218811,56.7163887024],"type":"Point"}
}