{
  "type": "Feature",
  "properties": {
    "addr:full":"575 Bridge St Bathurst NB E2A 1W7",
    "addr:housenumber":"575",
    "addr:postcode":"e2a 1w7",
    "addr:street":"Bridge St",
    "iso:country":"CA",
    "sg:address":"575 Bridge St",
    "sg:city":"Bathurst",
    "sg:classifiers":[
        {
            "category":"Building & Trades",
            "subcategory":"Construction",
            "type":"Services"
        }
    ],
    "sg:phone":"+1 506 546 9373",
    "sg:postcode":"E2A 1W7",
    "sg:province":"NB",
    "sg:tags":[
        "sandblasting"
    ],
    "wof:name":"Maritime Steeplejack CO Ltd",
    "wof:placetype":"venue"
},
  "geometry": {"coordinates":[-65.63539900000001,47.612705],"type":"Point"}
}