{
  "type": "Feature",
  "properties": {
    "iso:country":"CA",
    "sg:address":"570 Davie St",
    "sg:city":"Vancouver",
    "sg:classifiers":[
        {
            "category":"Personal",
            "subcategory":"Beauty Salon",
            "type":"Services"
        }
    ],
    "sg:phone":"+1 604 806 0818",
    "sg:postcode":"V6B 2G4",
    "sg:province":"BC",
    "wof:name":"Chemically Addicted Hair",
    "wof:placetype":"venue"
},
  "geometry": {"coordinates":[-123.125068665,49.2762107849],"type":"Point"}
}