{
  "type": "Feature",
  "properties": {
    "addr:full":"457 Boul Dr Albiny-Paquette Mont-Laurier QC J9L 1K7",
    "addr:housenumber":"457",
    "addr:postcode":"j9l 1k7",
    "addr:street":"Boul Dr Albiny-Paquette",
    "iso:country":"CA",
    "sg:address":"457 Boul Dr Albiny-Paquette",
    "sg:city":"Mont-Laurier",
    "sg:classifiers":[
        {
            "category":"Restaurant",
            "type":"Food & Drink"
        }
    ],
    "sg:phone":"+1 819 623 2597",
    "sg:postcode":"J9L 1K7",
    "sg:province":"QC",
    "wof:name":"Place Mont-Laurier Pizzeria",
    "wof:placetype":"venue"
},
  "geometry": {"coordinates":[-75.498634,46.549732],"type":"Point"}
}