{
  "type": "Feature",
  "properties": {
    "addr:full":"Haileybury ON P0J 1K0",
    "addr:postcode":"p0j 1k0",
    "iso:country":"CA",
    "sg:city":"Haileybury",
    "sg:classifiers":[
        {
            "category":"Organizations",
            "subcategory":"Religious Organization",
            "type":"Services"
        }
    ],
    "sg:phone":"+1 705 672 5942",
    "sg:postcode":"P0J 1K0",
    "sg:province":"ON",
    "sg:tags":[
        "church"
    ],
    "wof:name":"St Andrews United Church",
    "wof:placetype":"venue"
},
  "geometry": {"coordinates":[-79.63518500000001,47.450436],"type":"Point"}
}