{
  "type": "Feature",
  "properties": {
    "iso:country":"CA",
    "sg:city":"Montague",
    "sg:classifiers":[
        {
            "category":"Banks & Credit Unions",
            "subcategory":"Bank",
            "type":"Services"
        }
    ],
    "sg:phone":"+1 902 838 3255",
    "sg:postcode":"C0A 1R0",
    "sg:province":"PE",
    "sg:tags":[
        "loan",
        "real estate"
    ],
    "wof:name":"Citifinancial",
    "wof:placetype":"venue"
},
  "geometry": {"coordinates":[-62.6509094238,46.180896759],"type":"Point"}
}