{
  "type": "Feature",
  "properties": {
    "addr:full":"65 Walnut St S Hamilton ON L8N 2L2",
    "addr:housenumber":"65",
    "addr:postcode":"l8n 2l2",
    "addr:street":"Walnut St S",
    "iso:country":"CA",
    "sg:address":"65 Walnut St S",
    "sg:city":"Hamilton",
    "sg:classifiers":[
        {
            "category":"Professional",
            "subcategory":"Lawyer & Legal Services",
            "type":"Services"
        }
    ],
    "sg:phone":"+1 905 528 5150",
    "sg:postcode":"L8N 2L2",
    "sg:province":"ON",
    "sg:tags":[
        "attorney"
    ],
    "wof:name":"Cummins Seto",
    "wof:placetype":"venue"
},
  "geometry": {"coordinates":[-79.8639373779,43.2526931763],"type":"Point"}
}