{
  "type": "Feature",
  "properties": {
    "iso:country":"CA",
    "sg:address":"696 the Kingsway",
    "sg:city":"Peterborough",
    "sg:classifiers":[
        {
            "category":"Building & Trades",
            "subcategory":"Plumbing",
            "type":"Services"
        }
    ],
    "sg:phone":"+1 705 743 6438",
    "sg:postcode":"K9J 6W6",
    "sg:province":"ON",
    "sg:tags":[
        "air",
        "conditioning",
        "contractor",
        "system",
        "heating"
    ],
    "wof:name":"Cidco Heating",
    "wof:placetype":"venue"
},
  "geometry": {"coordinates":[-78.340584,44.277237],"type":"Point"}
}