{
  "type": "Feature",
  "properties": {
    "addr:full":"506 Hanna St E Windsor ON N8X 2N6",
    "addr:housenumber":"506",
    "addr:postcode":"n8x 2n6",
    "addr:street":"Hanna St E",
    "iso:country":"CA",
    "sg:address":"506 Hanna St E",
    "sg:city":"Windsor",
    "sg:classifiers":[
        {
            "category":"Retail",
            "subcategory":"Auto Repair",
            "type":"Services"
        }
    ],
    "sg:phone":"+1 519 253 5166",
    "sg:postcode":"N8X 2N6",
    "sg:province":"ON",
    "sg:tags":[
        "repairing",
        "automobile"
    ],
    "wof:name":"Windsor Auto Clinic",
    "wof:placetype":"venue"
},
  "geometry": {"coordinates":[-83.0185699463,42.3011245728],"type":"Point"}
}