{
  "type": "Feature",
  "properties": {
    "addr:full":"Portage LA Prairie MB R1N 3C2",
    "addr:postcode":"r1n 3c2",
    "iso:country":"CA",
    "sg:city":"Portage LA Prairie",
    "sg:classifiers":[
        {
            "category":"Museum",
            "type":"Entertainment"
        }
    ],
    "sg:phone":"+1 204 857 3259",
    "sg:postcode":"R1N 3C2",
    "sg:province":"MB",
    "wof:name":"Fort Lareine Museum & Trst Bur",
    "wof:placetype":"venue"
},
  "geometry": {"coordinates":[-98.2736358643,49.9545402527],"type":"Point"}
}