{
  "type": "Feature",
  "properties": {
    "addr:full":"98 Mutual St S Ingersoll ON N5C 1S5",
    "addr:postcode":"n5c 1s5",
    "addr:street":"St S",
    "iso:country":"CA",
    "sg:address":"98 Mutual St S",
    "sg:city":"Ingersoll",
    "sg:classifiers":[
        {
            "category":"Autos & Motor Vehicles",
            "subcategory":"Auto Supplies",
            "type":"Retail Goods"
        }
    ],
    "sg:phone":"+1 519 485 3900",
    "sg:postcode":"N5C 1S5",
    "sg:province":"ON",
    "sg:tags":[
        "automobile",
        "parts"
    ],
    "wof:name":"Canadian Tire",
    "wof:placetype":"venue"
},
  "geometry": {"coordinates":[-80.88208770750001,43.0416488647],"type":"Point"}
}