{
  "type": "Feature",
  "properties": {
    "addr:full":"2397 Walker Rd Windsor ON N8W 3P7",
    "addr:housenumber":"2397",
    "addr:postcode":"n8w 3p7",
    "addr:street":"Walker Rd",
    "iso:country":"CA",
    "sg:address":"2397 Walker Rd",
    "sg:city":"Windsor",
    "sg:classifiers":[
        {
            "category":"Professional",
            "subcategory":"Engineering",
            "type":"Services"
        }
    ],
    "sg:phone":"+1 519 254 2551",
    "sg:postcode":"N8W 3P7",
    "sg:province":"ON",
    "sg:tags":[
        "engineer"
    ],
    "wof:name":"Valdez Engineering Ltd",
    "wof:placetype":"venue"
},
  "geometry": {"coordinates":[-82.99160766599999,42.2976112366],"type":"Point"}
}