{
  "type": "Feature",
  "properties": {
    "addr:full":"35 Evesham Cres #42 Brampton ON L6T 3R9",
    "addr:housenumber":"35",
    "addr:postcode":"l6t 3r9",
    "addr:street":"Evesham Cres # 42",
    "iso:country":"CA",
    "sg:address":"35 Evesham Cres #42",
    "sg:city":"Brampton",
    "sg:classifiers":[
        {
            "category":"Manufacturing",
            "subcategory":"Printing",
            "type":"Manufacturing & Wholesale Goods"
        }
    ],
    "sg:phone":"+1 905 789 0372",
    "sg:postcode":"L6T 3R9",
    "sg:province":"ON",
    "sg:tags":[
        "printer"
    ],
    "wof:name":"Kamban Printing Inc",
    "wof:placetype":"venue"
},
  "geometry": {"coordinates":[-79.7012176514,43.7258911133],"type":"Point"}
}