{
  "type": "Feature",
  "properties": {
    "iso:country":"CA",
    "sg:address":"1199 St James St",
    "sg:city":"Winnipeg",
    "sg:classifiers":[
        {
            "category":"Real Estate",
            "subcategory":"Real Estate Agent",
            "type":"Services"
        }
    ],
    "sg:phone":"+1 204 943 2451",
    "sg:postcode":"R3H 0K8",
    "sg:province":"MB",
    "sg:tags":[
        "management",
        "apartment"
    ],
    "wof:name":"Apex Realty",
    "wof:placetype":"venue"
},
  "geometry": {"coordinates":[-97.19989776609999,49.9002418518],"type":"Point"}
}