{
  "type": "Feature",
  "properties": {
    "iso:country":"CA",
    "sg:city":"Canoe Narrows",
    "sg:classifiers":[
        {
            "category":"Education",
            "subcategory":"School",
            "type":"Public Place"
        }
    ],
    "sg:phone":"+1 306 829 4202",
    "sg:postcode":"S0M 0K0",
    "sg:province":"SK",
    "wof:name":"Jans Bay School",
    "wof:placetype":"venue"
},
  "geometry": {"coordinates":[-108.154015,55.167759],"type":"Point"}
}