{
  "type": "Feature",
  "properties": {
    "addr:full":"110 Rue Des Cedres Canton Bedford QC J0J 1A0",
    "addr:housenumber":"110",
    "addr:postcode":"j0j 1a0",
    "addr:street":"Rue Des Cedres Canton",
    "iso:country":"CA",
    "sg:address":"110 Rue Des Cedres",
    "sg:city":"Canton Bedford",
    "sg:classifiers":[
        {
            "category":"Personal",
            "subcategory":"Beauty Salon",
            "type":"Services"
        }
    ],
    "sg:phone":"+1 450 248 2713",
    "sg:postcode":"J0J 1A0",
    "sg:province":"QC",
    "sg:tags":[
        "electrolysis"
    ],
    "wof:name":"Electrolyse & Esthetique Josee",
    "wof:placetype":"venue"
},
  "geometry": {"coordinates":[-72.96463012700001,45.120513916],"type":"Point"}
}