{
  "type": "Feature",
  "properties": {
    "addr:full":"282 Dundas St E Trenton ON K8V 1M2",
    "addr:housenumber":"282",
    "addr:postcode":"k8v 1m2",
    "addr:street":"Dundas St E",
    "iso:country":"CA",
    "sg:address":"282 Dundas St E",
    "sg:city":"Trenton",
    "sg:classifiers":[
        {
            "category":"Personal",
            "subcategory":"Beauty Salon",
            "type":"Services"
        }
    ],
    "sg:phone":"+1 613 394 4185",
    "sg:postcode":"K8V 1M2",
    "sg:province":"ON",
    "wof:name":"Classique Coiffure",
    "wof:placetype":"venue"
},
  "geometry": {"coordinates":[-77.5551147461,44.1050796509],"type":"Point"}
}