{
  "type": "Feature",
  "properties": {
    "iso:country":"CA",
    "sg:address":"104 Main St",
    "sg:city":"Stephenville",
    "sg:classifiers":[
        {
            "category":"Cinema",
            "subcategory":"Movie Rental",
            "type":"Entertainment"
        }
    ],
    "sg:phone":"+1 709 643 5277",
    "sg:postcode":"A2N 1J3",
    "sg:province":"NL",
    "sg:tags":[
        "leasing",
        "video",
        "disc",
        "tape"
    ],
    "wof:name":"Video Shoppe",
    "wof:placetype":"venue"
},
  "geometry": {"coordinates":[-58.5795249939,48.5484352112],"type":"Point"}
}