{
  "type": "Feature",
  "properties": {
    "addr:full":"5095 Av Tour Du Lac Lac-A-LA-Tortue QC G0X 1L0",
    "addr:housenumber":"5095",
    "addr:postcode":"g0x 1l0",
    "addr:street":"Av Tour Du Lac Lac-A-La-Tortue",
    "iso:country":"CA",
    "sg:address":"5095 Av Tour Du Lac",
    "sg:city":"Lac-A-LA-Tortue",
    "sg:classifiers":[
        {
            "category":"Travel",
            "subcategory":"Campground",
            "type":"Entertainment"
        }
    ],
    "sg:phone":"+1 819 538 2159",
    "sg:postcode":"G0X 1L0",
    "sg:province":"QC",
    "wof:name":"Camping Rouillard",
    "wof:placetype":"venue"
},
  "geometry": {"coordinates":[-72.622711,46.610519],"type":"Point"}
}