{
  "type": "Feature",
  "properties": {
    "iso:country":"CA",
    "sg:city":"Montreal",
    "sg:classifiers":[
        {
            "category":"Real Estate",
            "subcategory":"Architect",
            "type":"Services"
        }
    ],
    "sg:phone":"+1 514 843 8069",
    "sg:postcode":"H2Y 2T2",
    "sg:province":"QC",
    "wof:name":"Jean Raymond Architects",
    "wof:placetype":"venue"
},
  "geometry": {"coordinates":[-73.556816,45.503746],"type":"Point"}
}