{
  "type": "Feature",
  "properties": {
    "iso:country":"CA",
    "sg:address":"714 Baker St",
    "sg:city":"Nelson",
    "sg:classifiers":[
        {
            "category":"Retail",
            "subcategory":"Auto Repair",
            "type":"Services"
        }
    ],
    "sg:phone":"+1 250 354 4146",
    "sg:postcode":"V1L 4J6",
    "sg:province":"BC",
    "sg:tags":[
        "repairing",
        "automobile"
    ],
    "wof:name":"Civic Auto Repair",
    "wof:placetype":"venue"
},
  "geometry": {"coordinates":[-117.290847778,49.4930038452],"type":"Point"}
}