{
  "type": "Feature",
  "properties": {
    "addr:full":"26 Fieldway Rd Etobicoke ON M8Z 3L2",
    "addr:housenumber":"26",
    "addr:postcode":"m8z 3l2",
    "addr:street":"Fieldway Rd",
    "iso:country":"CA",
    "sg:address":"26 Fieldway Rd",
    "sg:city":"Etobicoke",
    "sg:classifiers":[
        {
            "category":"Manufacturing",
            "subcategory":"Metals",
            "type":"Manufacturing & Wholesale Goods"
        }
    ],
    "sg:phone":"+1 416 239 3585",
    "sg:postcode":"M8Z 3L2",
    "sg:province":"ON",
    "sg:tags":[
        "casting",
        "jewelry"
    ],
    "wof:name":"Goldcast Jewelry Ltd",
    "wof:placetype":"venue"
},
  "geometry": {"coordinates":[-79.5275726318,43.6422729492],"type":"Point"}
}