{
  "type": "Feature",
  "properties": {
    "addr:full":"Red Lake ON P0V 2M0",
    "addr:postcode":"p0v 2m0",
    "iso:country":"CA",
    "sg:city":"Red Lake",
    "sg:classifiers":[
        {
            "category":"Travel",
            "subcategory":"Campground",
            "type":"Entertainment"
        }
    ],
    "sg:phone":"+1 807 727 2581",
    "sg:postcode":"P0V 2M0",
    "sg:province":"ON",
    "sg:tags":[
        "camp",
        "fishing"
    ],
    "wof:name":"Sportsman's Lodge",
    "wof:placetype":"venue"
},
  "geometry": {"coordinates":[-93.8221664429,51.0190124512],"type":"Point"}
}