{
  "type": "Feature",
  "properties": {
    "addr:full":"162 Rue Principale E Saint-Alphonse-DE-Caplan QC G0C 2V0",
    "addr:housenumber":"162",
    "addr:postcode":"g0c 2v0",
    "addr:street":"Rue Principale E Saint-Alphonse-De-Caplan",
    "iso:country":"CA",
    "sg:address":"162 Rue Principale E",
    "sg:city":"Saint-Alphonse-DE-Caplan",
    "sg:classifiers":[
        {
            "category":"Home & Garden",
            "subcategory":"Hardware",
            "type":"Retail Goods"
        }
    ],
    "sg:phone":"+1 418 388 5238",
    "sg:postcode":"G0C 2V0",
    "sg:province":"QC",
    "wof:name":"Quincaillerie Arseneault",
    "wof:placetype":"venue"
},
  "geometry": {"coordinates":[-65.6277389526,48.1887207031],"type":"Point"}
}