{
  "type": "Feature",
  "properties": {
    "addr:full":"350 Sparks St # 208 Ottawa ON K1R 7S8",
    "addr:housenumber":"350",
    "addr:postcode":"k1r 7s8",
    "addr:street":"Sparks St # 208",
    "iso:country":"CA",
    "sg:address":"350 Sparks St # 208",
    "sg:city":"Ottawa",
    "sg:classifiers":[
        {
            "category":"Professional",
            "subcategory":"Management & Consulting",
            "type":"Services"
        }
    ],
    "sg:phone":"+1 613 233 5474",
    "sg:postcode":"K1R 7S8",
    "sg:province":"ON",
    "sg:tags":[
        "consultant",
        "business"
    ],
    "wof:name":"Prairie Research Assoc",
    "wof:placetype":"venue"
},
  "geometry": {"coordinates":[-75.7057189941,45.4191207886],"type":"Point"}
}