{
  "type": "Feature",
  "properties": {
    "addr:full":"300 W 3rd St Revelstoke BC V0E 2S0",
    "addr:housenumber":"300",
    "addr:postcode":"v0e 2s0",
    "addr:street":"W 3Rd St",
    "iso:country":"CA",
    "sg:address":"300 W 3rd St",
    "sg:city":"Revelstoke",
    "sg:classifiers":[
        {
            "category":"Health Services",
            "subcategory":"Chiropractor",
            "type":"Services"
        }
    ],
    "sg:phone":"+1 250 837 2110",
    "sg:postcode":"V0E 2S0",
    "sg:province":"BC",
    "wof:name":"Viznaugh, Wade DC",
    "wof:placetype":"venue"
},
  "geometry": {"coordinates":[-118.197906,50.998329],"type":"Point"}
}