{
  "type": "Feature",
  "properties": {
    "addr:full":"Calgary AB T2P 3H5",
    "addr:postcode":"t2p 3h5",
    "iso:country":"CA",
    "sg:city":"Calgary",
    "sg:classifiers":[
        {
            "category":"Shopping",
            "subcategory":"Jewelry",
            "type":"Retail Goods"
        }
    ],
    "sg:phone":"+1 403 269 7222",
    "sg:postcode":"T2P 3H5",
    "sg:province":"AB",
    "sg:tags":[
        "jeweler"
    ],
    "wof:name":"Stephen Avenue Jewellery",
    "wof:placetype":"venue"
},
  "geometry": {"coordinates":[-114.073975,51.048546],"type":"Point"}
}