{
  "type": "Feature",
  "properties": {
    "addr:full":"459 Stephen St Morden MB R6M 1T9",
    "addr:housenumber":"459",
    "addr:postcode":"r6m 1t9",
    "addr:street":"Stephen St",
    "iso:country":"CA",
    "sg:address":"459 Stephen St",
    "sg:city":"Morden",
    "sg:classifiers":[
        {
            "category":"Retail",
            "subcategory":"Portrait Studio",
            "type":"Services"
        }
    ],
    "sg:phone":"+1 204 822 4450",
    "sg:postcode":"R6M 1T9",
    "sg:province":"MB",
    "sg:tags":[
        "photographer"
    ],
    "wof:name":"Nikkel Photography",
    "wof:placetype":"venue"
},
  "geometry": {"coordinates":[-98.104462,49.189949],"type":"Point"}
}