{
  "type": "Feature",
  "properties": {
    "iso:country":"CA",
    "sg:city":"Beamsville",
    "sg:classifiers":[
        {
            "category":"Shopping",
            "type":"Retail Goods"
        }
    ],
    "sg:phone":"+1 905 563 5865",
    "sg:postcode":"L0R 1B1",
    "sg:province":"ON",
    "sg:tags":[
        "art",
        "gallery",
        "dealer"
    ],
    "wof:name":"Kramer Sculptures",
    "wof:placetype":"venue"
},
  "geometry": {"coordinates":[-79.46672058110001,43.1816596985],"type":"Point"}
}