{
  "type": "Feature",
  "properties": {
    "addr:full":"Trois-Rivieres QC G8Y 5B8",
    "addr:postcode":"g8y 5b8",
    "iso:country":"CA",
    "sg:city":"Trois-Rivieres",
    "sg:classifiers":[
        {
            "category":"Utilities",
            "subcategory":"Cable",
            "type":"Services"
        }
    ],
    "sg:phone":"+1 819 693 5151",
    "sg:postcode":"G8Y 5B8",
    "sg:province":"QC",
    "sg:tags":[
        "television"
    ],
    "wof:name":"Cogeco Cable Inc",
    "wof:placetype":"venue"
},
  "geometry": {"coordinates":[-72.591339,46.359516],"type":"Point"}
}