{
  "type": "Feature",
  "properties": {
    "addr:full":"2518 Prince Edward St Vancouver BC V5T 4T3",
    "addr:housenumber":"2518",
    "addr:postcode":"v5t 4t3",
    "addr:street":"Prince Edward St",
    "iso:country":"CA",
    "sg:address":"2518 Prince Edward St",
    "sg:city":"Vancouver",
    "sg:classifiers":[
        {
            "category":"Professional",
            "subcategory":"Accounting & Tax Preparation",
            "type":"Services"
        }
    ],
    "sg:phone":"+1 604 871 9889",
    "sg:postcode":"V5T 4T3",
    "sg:province":"BC",
    "sg:tags":[
        "accountant"
    ],
    "wof:name":"Lee, James",
    "wof:placetype":"venue"
},
  "geometry": {"coordinates":[-123.095703125,49.2624015808],"type":"Point"}
}