{
  "type": "Feature",
  "properties": {
    "iso:country":"CA",
    "sg:address":"65 Boul Sainte-Madeleine",
    "sg:city":"Cap-DE-LA-Madeleine",
    "sg:classifiers":[
        {
            "category":"Food & Beverages",
            "subcategory":"Specialty",
            "type":"Retail Goods"
        }
    ],
    "sg:phone":"+1 819 694 4441",
    "sg:postcode":"G8T 3K8",
    "sg:province":"QC",
    "sg:tags":[
        "bulk",
        "grocer",
        "health",
        "diet"
    ],
    "wof:name":"Panier DE Sante",
    "wof:placetype":"venue"
},
  "geometry": {"coordinates":[-72.5134048462,46.3633613586],"type":"Point"}
}