{
  "type": "Feature",
  "properties": {
    "iso:country":"CA",
    "sg:city":"Kahnawake",
    "sg:classifiers":[
        {
            "category":"Health Services",
            "subcategory":"Hospital",
            "type":"Services"
        }
    ],
    "sg:phone":"+1 450 638 3930",
    "sg:postcode":"J0L 1B0",
    "sg:province":"QC",
    "wof:name":"Kateri Memorial Hospital Ctr",
    "wof:placetype":"venue"
},
  "geometry": {"coordinates":[-73.6833572388,45.415802002],"type":"Point"}
}