{
  "type": "Feature",
  "properties": {
    "addr:full":"10518 Jubilee Rd Summerland BC V0H 1Z0",
    "addr:housenumber":"10518",
    "addr:postcode":"v0h 1z0",
    "addr:street":"Jubilee Rd",
    "iso:country":"CA",
    "sg:address":"10518 Jubilee Rd",
    "sg:city":"Summerland",
    "sg:classifiers":[
        {
            "category":"Building & Trades",
            "subcategory":"Construction",
            "type":"Services"
        }
    ],
    "sg:phone":"+1 250 494 2796",
    "sg:postcode":"V0H 1Z0",
    "sg:province":"BC",
    "sg:tags":[
        "excavating",
        "contractor"
    ],
    "wof:name":"Dave Miller Trucking Ltd",
    "wof:placetype":"venue"
},
  "geometry": {"coordinates":[-119.683921814,49.6034393311],"type":"Point"}
}