{
  "type": "Feature",
  "properties": {
    "iso:country":"CA",
    "sg:address":"824 Johnson St",
    "sg:city":"Victoria",
    "sg:classifiers":[
        {
            "category":"Real Estate",
            "subcategory":"Real Estate Agent",
            "type":"Services"
        }
    ],
    "sg:phone":"+1 250 384 4253",
    "sg:postcode":"V8W 1N3",
    "sg:province":"BC",
    "sg:tags":[
        "management"
    ],
    "wof:name":"Skipper Properties Ltd",
    "wof:placetype":"venue"
},
  "geometry": {"coordinates":[-123.360939,48.426956],"type":"Point"}
}