{
  "type": "Feature",
  "properties": {
    "addr:full":"191 Western Ave Schomberg ON L0G 1T0",
    "addr:housenumber":"191",
    "addr:postcode":"l0g 1t0",
    "addr:street":"Western Ave",
    "iso:country":"CA",
    "sg:address":"191 Western Ave",
    "sg:city":"Schomberg",
    "sg:classifiers":[
        {
            "category":"Retail",
            "subcategory":"Veterinary Services",
            "type":"Services"
        }
    ],
    "sg:phone":"+1 905 939 7136",
    "sg:postcode":"L0G 1T0",
    "sg:province":"ON",
    "sg:tags":[
        "veterinarian"
    ],
    "wof:name":"DE Gannes Equine Veterinary",
    "wof:placetype":"venue"
},
  "geometry": {"coordinates":[-79.68789672849999,44.0054473877],"type":"Point"}
}