{
  "type": "Feature",
  "properties": {
    "addr:full":"2 Water St Marystown NL A0E 2M0",
    "addr:housenumber":"2",
    "addr:postcode":"a0e 2m0",
    "addr:street":"Water St",
    "iso:country":"CA",
    "sg:address":"2 Water St",
    "sg:city":"Marystown",
    "sg:classifiers":[
        {
            "category":"Home & Garden",
            "subcategory":"Furniture",
            "type":"Retail Goods"
        }
    ],
    "sg:phone":"+1 709 279 3616",
    "sg:postcode":"A0E 2M0",
    "sg:province":"NL",
    "sg:tags":[
        "equipment",
        "kitchen",
        "cabinet"
    ],
    "wof:name":"Peninsula Kitchens Ltd",
    "wof:placetype":"venue"
},
  "geometry": {"coordinates":[-55.1577987671,47.1586494446],"type":"Point"}
}