{
  "type": "Feature",
  "properties": {
    "addr:full":"180 Boul DE LA Concorde O Laval QC H7N 1H9",
    "addr:housenumber":"180",
    "addr:postcode":"h7n 1h9",
    "addr:street":"Boul De La Concorde O",
    "iso:country":"CA",
    "sg:address":"180 Boul DE LA Concorde O",
    "sg:city":"Laval",
    "sg:classifiers":[
        {
            "category":"Restaurant",
            "type":"Food & Drink"
        }
    ],
    "sg:phone":"+1 450 667 9300",
    "sg:postcode":"H7N 1H9",
    "sg:province":"QC",
    "sg:tags":[
        "cafe"
    ],
    "wof:name":"Cafe Bistro II Momento",
    "wof:placetype":"venue"
},
  "geometry": {"coordinates":[-73.69948599999999,45.566071],"type":"Point"}
}