{
  "type": "Feature",
  "properties": {
    "addr:full":"Compton QC J0B 1L0",
    "addr:postcode":"j0b 1l0",
    "iso:country":"CA",
    "sg:city":"Compton",
    "sg:classifiers":[
        {
            "category":"Autos & Motor Vehicles",
            "subcategory":"Automobile Sales",
            "type":"Retail Goods"
        }
    ],
    "sg:phone":"+1 819 835 5592",
    "sg:postcode":"J0B 1L0",
    "sg:province":"QC",
    "sg:tags":[
        "car",
        "dealer"
    ],
    "wof:name":"Automobiles Denis L Veilleux",
    "wof:placetype":"venue"
},
  "geometry": {"coordinates":[-71.83000946040001,45.2500801086],"type":"Point"}
}