{
  "type": "Feature",
  "properties": {
    "addr:full":"360 Broadway St Winnipeg MB R3C 0T6",
    "addr:housenumber":"360",
    "addr:postcode":"r3c 0t6",
    "addr:street":"Broadway St",
    "iso:country":"CA",
    "sg:address":"360 Broadway St",
    "sg:city":"Winnipeg",
    "sg:classifiers":[
        {
            "category":"Restaurant",
            "type":"Food & Drink"
        }
    ],
    "sg:phone":"+1 204 943 2324",
    "sg:postcode":"R3C 0T6",
    "sg:province":"MB",
    "wof:name":"Subway Sandwiches & Salads",
    "wof:placetype":"venue"
},
  "geometry": {"coordinates":[-97.142838,49.886864],"type":"Point"}
}