{
  "type": "Feature",
  "properties": {
    "iso:country":"CA",
    "sg:city":"Yellowknife",
    "sg:classifiers":[
        {
            "category":"Insurance",
            "subcategory":"Insurance Agent",
            "type":"Services"
        }
    ],
    "sg:phone":"+1 867 873 3414",
    "sg:postcode":"X1A 3S9",
    "sg:province":"NT",
    "wof:name":"Aon Reed Stenhouse Ltd",
    "wof:placetype":"venue"
},
  "geometry": {"coordinates":[-114.37436676,62.4526596069],"type":"Point"}
}