{
  "type": "Feature",
  "properties": {
    "addr:full":"Montreal QC H3L 1N8",
    "addr:postcode":"h3l 1n8",
    "iso:country":"CA",
    "sg:city":"Montreal",
    "sg:classifiers":[
        {
            "category":"Education",
            "subcategory":"Special Training",
            "type":"Public Place"
        }
    ],
    "sg:phone":"+1 514 334 1819",
    "sg:postcode":"H3L 1N8",
    "sg:province":"QC",
    "sg:tags":[
        "school",
        "language"
    ],
    "wof:name":"Institut Medialangue Intl Ltee",
    "wof:placetype":"venue"
},
  "geometry": {"coordinates":[-73.66957855219999,45.5532569885],"type":"Point"}
}