{
  "type": "Feature",
  "properties": {
    "addr:full":"410 Rang Chartier # 104 Mont-Saint-Gregoire QC J0J 1K0",
    "addr:housenumber":"410",
    "addr:postcode":"j0j 1k0",
    "addr:street":"Rang Chartier # 104 Mont-Saint-Gregoire",
    "iso:country":"CA",
    "sg:address":"410 Rang Chartier # 104",
    "sg:city":"Mont-Saint-Gregoire",
    "sg:classifiers":[
        {
            "category":"Building & Trades",
            "subcategory":"Landscaping Services",
            "type":"Services"
        }
    ],
    "sg:phone":"+1 450 346 0484",
    "sg:postcode":"J0J 1K0",
    "sg:province":"QC",
    "sg:tags":[
        "tree",
        "landscape",
        "contractor"
    ],
    "wof:name":"Terrassement Tecnick Enr",
    "wof:placetype":"venue"
},
  "geometry": {"coordinates":[-73.144791,45.32766],"type":"Point"}
}