{
  "type": "Feature",
  "properties": {
    "iso:country":"CA",
    "sg:address":"637 Davis Dr",
    "sg:city":"Newmarket",
    "sg:classifiers":[
        {
            "category":"Health Services",
            "subcategory":"Doctor",
            "type":"Services"
        }
    ],
    "sg:phone":"+1 905 898 7924",
    "sg:postcode":"L3Y 2R2",
    "sg:province":"ON",
    "sg:tags":[
        "physician",
        "surgeon"
    ],
    "wof:name":"York Cardiology Svc",
    "wof:placetype":"venue"
},
  "geometry": {"coordinates":[-79.4510803223,44.0615501404],"type":"Point"}
}