{
  "type": "Feature",
  "properties": {
    "addr:full":"186 W Church St Waterford ON N0E 1Y0",
    "addr:housenumber":"186",
    "addr:postcode":"n0e 1y0",
    "addr:street":"W Church St",
    "iso:country":"CA",
    "sg:address":"186 W Church St",
    "sg:city":"Waterford",
    "sg:classifiers":[
        {
            "category":"Building & Trades",
            "subcategory":"Construction",
            "type":"Services"
        }
    ],
    "sg:phone":"+1 519 443 7872",
    "sg:postcode":"N0E 1Y0",
    "sg:province":"ON",
    "sg:tags":[
        "paving",
        "contractor"
    ],
    "wof:name":"Pursley Paving",
    "wof:placetype":"venue"
},
  "geometry": {"coordinates":[-80.29811100000001,42.929848],"type":"Point"}
}