{
  "type": "Feature",
  "properties": {
    "addr:full":"525 Rte DE L Eglise Saint-Pierre-Baptiste QC G0P 1K0",
    "addr:housenumber":"525",
    "addr:postcode":"g0p 1k0",
    "addr:street":"Rte De L Eglise",
    "iso:country":"CA",
    "sg:address":"525 Rte DE L Eglise",
    "sg:city":"Saint-Pierre-Baptiste",
    "sg:classifiers":[
        {
            "category":"Insurance",
            "subcategory":"Insurance Agent",
            "type":"Services"
        }
    ],
    "sg:phone":"+1 418 453 2166",
    "sg:postcode":"G0P 1K0",
    "sg:province":"QC",
    "wof:name":"Promutuel Appalaches",
    "wof:placetype":"venue"
},
  "geometry": {"coordinates":[-71.6190338135,46.2026901245],"type":"Point"}
}