{
  "type": "Feature",
  "properties": {
    "addr:full":"3215 Jefferson Blvd Windsor ON N8T 2W7",
    "addr:housenumber":"3215",
    "addr:postcode":"n8t 2w7",
    "addr:street":"Jefferson Blvd",
    "iso:country":"CA",
    "sg:address":"3215 Jefferson Blvd",
    "sg:city":"Windsor",
    "sg:classifiers":[
        {
            "category":"Wholesale",
            "subcategory":"Auto Parts",
            "type":"Manufacturing & Wholesale Goods"
        }
    ],
    "sg:phone":"+1 519 945 1133",
    "sg:postcode":"N8T 2W7",
    "sg:province":"ON",
    "sg:tags":[
        "automobile",
        "supply"
    ],
    "wof:name":"Tenneco Automotive",
    "wof:placetype":"venue"
},
  "geometry": {"coordinates":[-82.941475,42.293625],"type":"Point"}
}