{
  "type": "Feature",
  "properties": {
    "addr:full":"31 Cow Bay Rd Eastern Passage NS B3G 1A3",
    "addr:housenumber":"31",
    "addr:postcode":"b3g 1a3",
    "addr:street":"Cow Bay Rd",
    "iso:country":"CA",
    "sg:address":"31 Cow Bay Rd",
    "sg:city":"Eastern Passage",
    "sg:classifiers":[
        {
            "category":"Personal",
            "subcategory":"Beauty Salon",
            "type":"Services"
        }
    ],
    "sg:phone":"+1 902 465 3300",
    "sg:postcode":"B3G 1A3",
    "sg:province":"NS",
    "wof:name":"Impressions Unisex Hair Salon",
    "wof:placetype":"venue"
},
  "geometry": {"coordinates":[-63.492039,44.611984],"type":"Point"}
}