{
  "type": "Feature",
  "properties": {
    "addr:full":"Saskatoon SK S7K 7K3",
    "addr:postcode":"s7k 7k3",
    "iso:country":"CA",
    "sg:city":"Saskatoon",
    "sg:classifiers":[
        {
            "category":"Professional",
            "subcategory":"Business Services",
            "type":"Services"
        }
    ],
    "sg:phone":"+1 306 975 1999",
    "sg:postcode":"S7K 7K3",
    "sg:province":"SK",
    "sg:tags":[
        "water",
        "supply",
        "system",
        "hauling"
    ],
    "wof:name":"Central Water Equipment Svc",
    "wof:placetype":"venue"
},
  "geometry": {"coordinates":[-106.6604,52.173195],"type":"Point"}
}