{
  "type": "Feature",
  "properties": {
    "iso:country":"CA",
    "sg:city":"Vancouver",
    "sg:classifiers":[
        {
            "category":"Shopping",
            "subcategory":"Optical Goods",
            "type":"Retail Goods"
        }
    ],
    "sg:phone":"+1 604 681 1915",
    "sg:postcode":"V6B 6L5",
    "sg:province":"BC",
    "wof:name":"Sarix Enterprises Ltd",
    "wof:placetype":"venue"
},
  "geometry": {"coordinates":[-123.12193298299999,49.2759552002],"type":"Point"}
}