{
  "type": "Feature",
  "properties": {
    "addr:full":"141 Crofton Bay Winnipeg MB R2M 2E4",
    "addr:housenumber":"141",
    "addr:postcode":"r2m 2e4",
    "addr:street":"Crofton Bay",
    "iso:country":"CA",
    "sg:address":"141 Crofton Bay",
    "sg:city":"Winnipeg",
    "sg:classifiers":[
        {
            "category":"Professional",
            "subcategory":"Detective & Security Services",
            "type":"Services"
        }
    ],
    "sg:phone":"+1 204 255 4785",
    "sg:postcode":"R2M 2E4",
    "sg:province":"MB",
    "sg:tags":[
        "consultant",
        "guard",
        "patrol",
        "system"
    ],
    "wof:name":"Holiday Home Check Svc",
    "wof:placetype":"venue"
},
  "geometry": {"coordinates":[-97.1230926514,49.8360137939],"type":"Point"}
}