{
  "type": "Feature",
  "properties": {
    "addr:full":"663 Bathurst St London ON N5Z 1P8",
    "addr:housenumber":"663",
    "addr:postcode":"n5z 1p8",
    "addr:street":"Bathurst St",
    "iso:country":"CA",
    "sg:address":"663 Bathurst St",
    "sg:city":"London",
    "sg:classifiers":[
        {
            "category":"Government",
            "subcategory":"Office",
            "type":"Public Place"
        }
    ],
    "sg:phone":"+1 519 661 4721",
    "sg:postcode":"N5Z 1P8",
    "sg:province":"ON",
    "sg:tags":[
        "village"
    ],
    "wof:name":"London Purchasing Div",
    "wof:placetype":"venue"
},
  "geometry": {"coordinates":[-81.230576,42.984753],"type":"Point"}
}