{
  "type": "Feature",
  "properties": {
    "addr:full":"21 Windsor Court Rd Thornhill ON L3T 4Y4",
    "addr:housenumber":"21",
    "addr:postcode":"l3t 4y4",
    "addr:street":"Windsor Court Rd",
    "iso:country":"CA",
    "sg:address":"21 Windsor Court Rd",
    "sg:city":"Thornhill",
    "sg:classifiers":[
        {
            "category":"Arts & Performance",
            "subcategory":"Theater",
            "type":"Entertainment"
        }
    ],
    "sg:phone":"+1 905 731 1329",
    "sg:postcode":"L3T 4Y4",
    "sg:province":"ON",
    "sg:tags":[
        "television",
        "program",
        "producer"
    ],
    "wof:name":"Super People Production Ltd",
    "wof:placetype":"venue"
},
  "geometry": {"coordinates":[-79.358963,43.815491],"type":"Point"}
}