{
  "type": "Feature",
  "properties": {
    "addr:full":"273 2nd Ave Minitonas MB R0L 1G0",
    "addr:housenumber":"273",
    "addr:postcode":"r0l 1g0",
    "addr:street":"2Nd Ave",
    "iso:country":"CA",
    "sg:address":"273 2nd Ave",
    "sg:city":"Minitonas",
    "sg:classifiers":[
        {
            "category":"Travel",
            "subcategory":"Hotels & Motels",
            "type":"Entertainment"
        }
    ],
    "sg:phone":"+1 204 525 4249",
    "sg:postcode":"R0L 1G0",
    "sg:province":"MB",
    "wof:name":"Minitonas Hotel",
    "wof:placetype":"venue"
},
  "geometry": {"coordinates":[-101.037147522,52.0865859985],"type":"Point"}
}