{
  "type": "Feature",
  "properties": {
    "iso:country":"CA",
    "sg:city":"Vancouver",
    "sg:classifiers":[
        {
            "category":"Mining & Drilling",
            "type":"Manufacturing & Wholesale Goods"
        }
    ],
    "sg:phone":"+1 604 623 3101",
    "sg:postcode":"V6C 1T1",
    "sg:province":"BC",
    "sg:tags":[
        "contractor"
    ],
    "wof:name":"Starfire Minerals Inc",
    "wof:placetype":"venue"
},
  "geometry": {"coordinates":[-123.114449,49.285042],"type":"Point"}
}