{
  "type": "Feature",
  "properties": {
    "iso:country":"CA",
    "sg:address":"9244 County Rd 42",
    "sg:city":"Maidstone",
    "sg:classifiers":[
        {
            "category":"Recreation",
            "type":"Entertainment"
        }
    ],
    "sg:phone":"+1 519 735 5252",
    "sg:postcode":"N0R 1K0",
    "sg:province":"ON",
    "sg:tags":[
        "stable"
    ],
    "wof:name":"Southern Cross Stables",
    "wof:placetype":"venue"
},
  "geometry": {"coordinates":[-82.89051055909999,42.210067749],"type":"Point"}
}