{
  "type": "Feature",
  "properties": {
    "addr:full":"Mississauga ON L4W 2V3",
    "addr:postcode":"l4w 2v3",
    "iso:country":"CA",
    "sg:city":"Mississauga",
    "sg:classifiers":[
        {
            "category":"Food & Beverages",
            "subcategory":"Bakery",
            "type":"Retail Goods"
        }
    ],
    "sg:phone":"+1 905 629 8231",
    "sg:postcode":"L4W 2V3",
    "sg:province":"ON",
    "sg:tags":[
        "doughnut"
    ],
    "wof:name":"Coffee Time Donuts",
    "wof:placetype":"venue"
},
  "geometry": {"coordinates":[-79.641899,43.632999],"type":"Point"}
}