{
  "type": "Feature",
  "properties": {
    "addr:full":"Guelph ON N1H 7N8",
    "addr:postcode":"n1h 7n8",
    "iso:country":"CA",
    "sg:city":"Guelph",
    "sg:classifiers":[
        {
            "category":"Restaurant",
            "type":"Food & Drink"
        }
    ],
    "sg:phone":"+1 519 836 1818",
    "sg:postcode":"N1H 7N8",
    "sg:province":"ON",
    "sg:tags":[
        "pizza"
    ],
    "wof:name":"Jumbo 3 For 1 Pizza & Wings",
    "wof:placetype":"venue"
},
  "geometry": {"coordinates":[-80.265221,43.556374],"type":"Point"}
}