{
  "type": "Feature",
  "properties": {
    "addr:full":"2220 Av Beaconsfield Montreal QC H4A 2G8",
    "addr:housenumber":"2220",
    "addr:postcode":"h4a 2g8",
    "addr:street":"Av Beaconsfield",
    "iso:country":"CA",
    "sg:address":"2220 Av Beaconsfield",
    "sg:city":"Montreal",
    "sg:classifiers":[
        {
            "category":"Freight",
            "type":"Transportation"
        }
    ],
    "sg:phone":"+1 514 482 6095",
    "sg:postcode":"H4A 2G8",
    "sg:province":"QC",
    "sg:tags":[
        "warehouse",
        "mover"
    ],
    "wof:name":"Ramsays Express Reg",
    "wof:placetype":"venue"
},
  "geometry": {"coordinates":[-73.619698,45.46595],"type":"Point"}
}