{
  "type": "Feature",
  "properties": {
    "iso:country":"CA",
    "sg:address":"939 Lawrence Ave E",
    "sg:city":"North York",
    "sg:classifiers":[
        {
            "category":"Food & Beverages",
            "subcategory":"Groceries & Convenience Stores",
            "type":"Retail Goods"
        }
    ],
    "sg:phone":"+1 416 444 7671",
    "sg:postcode":"M3C 1P8",
    "sg:province":"ON",
    "sg:tags":[
        "grocer"
    ],
    "wof:name":"Dominion Stores",
    "wof:placetype":"venue"
},
  "geometry": {"coordinates":[-79.3451766968,43.7366752625],"type":"Point"}
}