{
  "type": "Feature",
  "properties": {
    "addr:full":"534 Union St Fredericton NB E3A 3N2",
    "addr:housenumber":"534",
    "addr:postcode":"e3a 3n2",
    "addr:street":"Union St",
    "iso:country":"CA",
    "sg:address":"534 Union St",
    "sg:city":"Fredericton",
    "sg:classifiers":[
        {
            "category":"Food & Beverages",
            "subcategory":"Bakery",
            "type":"Retail Goods"
        }
    ],
    "sg:phone":"+1 506 462 9958",
    "sg:postcode":"E3A 3N2",
    "sg:province":"NB",
    "sg:tags":[
        "tea",
        "coffee",
        "doughnut"
    ],
    "wof:name":"Tim Hortons",
    "wof:placetype":"venue"
},
  "geometry": {"coordinates":[-66.63316345210001,45.9699363708],"type":"Point"}
}