{
  "type": "Feature",
  "properties": {
    "addr:full":"Thetford Mines QC G6G 6K6",
    "addr:postcode":"g6g 6k6",
    "iso:country":"CA",
    "sg:city":"Thetford Mines",
    "sg:classifiers":[
        {
            "category":"Retail",
            "subcategory":"Auto Repair",
            "type":"Services"
        }
    ],
    "sg:phone":"+1 418 335 5727",
    "sg:postcode":"G6G 6K6",
    "sg:province":"QC",
    "sg:tags":[
        "repairing",
        "automobile"
    ],
    "wof:name":"Donald Baril Garage Enr",
    "wof:placetype":"venue"
},
  "geometry": {"coordinates":[-71.299263,46.090576],"type":"Point"}
}