{
  "type": "Feature",
  "properties": {
    "addr:full":"Cobourg ON K9A 4J9",
    "addr:postcode":"k9a 4j9",
    "iso:country":"CA",
    "sg:city":"Cobourg",
    "sg:classifiers":[
        {
            "category":"Shopping",
            "subcategory":"Gifts & Souvenirs",
            "type":"Retail Goods"
        }
    ],
    "sg:phone":"+1 905 372 9163",
    "sg:postcode":"K9A 4J9",
    "sg:province":"ON",
    "sg:tags":[
        "trophy",
        "shop",
        "medal",
        "award"
    ],
    "wof:name":"Jean's Trophies & Gifts",
    "wof:placetype":"venue"
},
  "geometry": {"coordinates":[-78.167778,43.959606],"type":"Point"}
}