{
  "type": "Feature",
  "properties": {
    "addr:full":"400 Sandwich St S Amherstburg ON N9V 3L4",
    "addr:housenumber":"400",
    "addr:postcode":"n9v 3l4",
    "addr:street":"Sandwich St S",
    "iso:country":"CA",
    "sg:address":"400 Sandwich St S",
    "sg:city":"Amherstburg",
    "sg:classifiers":[
        {
            "category":"Real Estate",
            "subcategory":"Real Estate Operator",
            "type":"Services"
        }
    ],
    "sg:phone":"+1 519 736 6419",
    "sg:postcode":"N9V 3L4",
    "sg:province":"ON",
    "sg:tags":[
        "mall",
        "shopping",
        "center"
    ],
    "wof:name":"White Woods Mall",
    "wof:placetype":"venue"
},
  "geometry": {"coordinates":[-83.10828399659999,42.0971336365],"type":"Point"}
}