{
  "type": "Feature",
  "properties": {
    "addr:full":"2360 Rue Belanger Montreal QC H2G 1E2",
    "addr:housenumber":"2360",
    "addr:postcode":"h2g 1e2",
    "addr:street":"Rue Belanger",
    "iso:country":"CA",
    "sg:address":"2360 Rue Belanger",
    "sg:city":"Montreal",
    "sg:classifiers":[
        {
            "category":"Personal",
            "subcategory":"Beauty Salon",
            "type":"Services"
        }
    ],
    "sg:phone":"+1 514 727 1080",
    "sg:postcode":"H2G 1E2",
    "sg:province":"QC",
    "sg:tags":[
        "school"
    ],
    "wof:name":"Institut Guylaine Enr",
    "wof:placetype":"venue"
},
  "geometry": {"coordinates":[-73.5993652344,45.550945282],"type":"Point"}
}