{
  "type": "Feature",
  "properties": {
    "iso:country":"CA",
    "sg:city":"Montreal",
    "sg:classifiers":[
        {
            "category":"Professional",
            "subcategory":"Business Services",
            "type":"Services"
        }
    ],
    "sg:phone":"+1 514 393 3242",
    "sg:postcode":"H2Z 1S5",
    "sg:province":"QC",
    "sg:tags":[
        "telemarketing"
    ],
    "wof:name":"Hi-Tel",
    "wof:placetype":"venue"
},
  "geometry": {"coordinates":[-73.565308,45.502724],"type":"Point"}
}