{
  "type": "Feature",
  "properties": {
    "addr:full":"9322 90 St NW Edmonton AB T6C 3M4",
    "addr:housenumber":"9322",
    "addr:postcode":"t6c 3m4",
    "addr:street":"90 St Nw",
    "iso:country":"CA",
    "sg:address":"9322 90 St NW",
    "sg:city":"Edmonton",
    "sg:classifiers":[
        {
            "category":"Professional",
            "subcategory":"Business Services",
            "type":"Services"
        }
    ],
    "sg:phone":"+1 780 440 4276",
    "sg:postcode":"T6C 3M4",
    "sg:province":"AB",
    "sg:tags":[
        "inspection"
    ],
    "wof:name":"Spexwest",
    "wof:placetype":"venue"
},
  "geometry": {"coordinates":[-113.46560700000001,53.5294],"type":"Point"}
}