{
  "type": "Feature",
  "properties": {
    "iso:country":"CA",
    "sg:address":"112 Main St N",
    "sg:city":"Newmarket",
    "sg:classifiers":[
        {
            "category":"Real Estate",
            "subcategory":"Developer",
            "type":"Services"
        }
    ],
    "sg:phone":"+1 905 836 5133",
    "sg:postcode":"L3Y 4A1",
    "sg:province":"ON",
    "sg:tags":[
        "cemetery"
    ],
    "wof:name":"Newmarket Cemetery CO",
    "wof:placetype":"venue"
},
  "geometry": {"coordinates":[-79.463081,44.062824],"type":"Point"}
}