{
  "type": "Feature",
  "properties": {
    "addr:full":"Richmond Hill ON L4E 2W1",
    "addr:postcode":"l4e 2w1",
    "iso:country":"CA",
    "sg:city":"Richmond Hill",
    "sg:classifiers":[
        {
            "category":"Personal",
            "subcategory":"Beauty Salon",
            "type":"Services"
        }
    ],
    "sg:phone":"+1 905 773 8258",
    "sg:postcode":"L4E 2W1",
    "sg:province":"ON",
    "wof:name":"Michele Hairstyling",
    "wof:placetype":"venue"
},
  "geometry": {"coordinates":[-79.45723724370001,43.9442176819],"type":"Point"}
}