{
  "type": "Feature",
  "properties": {
    "addr:full":"Mississauga ON L5T 2P7",
    "addr:postcode":"l5t 2p7",
    "iso:country":"CA",
    "sg:city":"Mississauga",
    "sg:classifiers":[
        {
            "category":"Professional",
            "subcategory":"Management & Consulting",
            "type":"Services"
        }
    ],
    "sg:phone":"+1 905 564 7233",
    "sg:postcode":"L5T 2P7",
    "sg:province":"ON",
    "sg:tags":[
        "consultant",
        "educational"
    ],
    "wof:name":"Peel Elementary Teachers Local",
    "wof:placetype":"venue"
},
  "geometry": {"coordinates":[-79.68789672849999,43.6367340088],"type":"Point"}
}