{
  "type": "Feature",
  "properties": {
    "addr:full":"4 Airport Hangar Fort Macleod AB T0L 0Z0",
    "addr:housenumber":"4;hangar",
    "addr:postcode":"t0l 0z0",
    "addr:street":"Fort Macleod",
    "iso:country":"CA",
    "sg:address":"4 Airport Hangar",
    "sg:city":"Fort Macleod",
    "sg:classifiers":[
        {
            "category":"Wholesale",
            "subcategory":"Farm Supplies",
            "type":"Manufacturing & Wholesale Goods"
        }
    ],
    "sg:phone":"+1 403 553 4094",
    "sg:postcode":"T0L 0Z0",
    "sg:province":"AB",
    "sg:tags":[
        "fertilizer"
    ],
    "wof:name":"Agrium Inc",
    "wof:placetype":"venue"
},
  "geometry": {"coordinates":[-113.395584106,49.7260742188],"type":"Point"}
}