{
  "type": "Feature",
  "properties": {
    "addr:full":"1759 Burr Brook Rd RR 8 Kingston ON K7L 4V4",
    "addr:housenumber":"1759",
    "addr:postcode":"k7l 4v4",
    "addr:street":"Burr Brook Rd;8",
    "iso:country":"CA",
    "sg:address":"1759 Burr Brook Rd RR 8",
    "sg:city":"Kingston",
    "sg:classifiers":[
        {
            "category":"Building & Trades",
            "subcategory":"Construction",
            "type":"Services"
        }
    ],
    "sg:phone":"+1 613 546 5311",
    "sg:postcode":"K7L 4V4",
    "sg:province":"ON",
    "sg:tags":[
        "masonry",
        "contractor"
    ],
    "wof:name":"John Harmsen Masonry Contr Ltd",
    "wof:placetype":"venue"
},
  "geometry": {"coordinates":[-76.47933197019999,44.2315368652],"type":"Point"}
}