{
  "type": "Feature",
  "properties": {
    "addr:full":"345 North Rd Coquitlam BC V3K 3V8",
    "addr:housenumber":"345",
    "addr:postcode":"v3k 3v8",
    "addr:street":"North Rd",
    "iso:country":"CA",
    "sg:address":"345 North Rd",
    "sg:city":"Coquitlam",
    "sg:classifiers":[
        {
            "category":"Restaurant",
            "type":"Food & Drink"
        }
    ],
    "sg:phone":"+1 604 931 5500",
    "sg:postcode":"V3K 3V8",
    "sg:province":"BC",
    "sg:tags":[
        "greek",
        "product"
    ],
    "wof:name":"Santorini Taverna",
    "wof:placetype":"venue"
},
  "geometry": {"coordinates":[-122.892456,49.244568],"type":"Point"}
}