{
  "type": "Feature",
  "properties": {
    "iso:country":"CA",
    "sg:address":"600 Lake St",
    "sg:city":"St Catharines",
    "sg:classifiers":[
        {
            "category":"Health Services",
            "subcategory":"Nursing And Care Facility",
            "type":"Services"
        }
    ],
    "sg:phone":"+1 905 935 3344",
    "sg:postcode":"L2N 4J4",
    "sg:province":"ON",
    "sg:tags":[
        "home",
        "retirement",
        "community"
    ],
    "wof:name":"Heidehof Home For the Aged",
    "wof:placetype":"venue"
},
  "geometry": {"coordinates":[-79.25221252439999,43.1980476379],"type":"Point"}
}