{
  "type": "Feature",
  "properties": {
    "iso:country":"CA",
    "sg:address":"562 Sheppard Ave W",
    "sg:city":"North York",
    "sg:classifiers":[
        {
            "category":"Restaurant",
            "type":"Food & Drink"
        }
    ],
    "sg:phone":"+1 416 638 0533",
    "sg:postcode":"M3H 2R9",
    "sg:province":"ON",
    "sg:tags":[
        "delicatessen"
    ],
    "wof:name":"Mark's International Deli",
    "wof:placetype":"venue"
},
  "geometry": {"coordinates":[-79.4377288818,43.7556648254],"type":"Point"}
}