{
  "type": "Feature",
  "properties": {
    "addr:full":"1892 Baseline Rd W Bowmanville ON L1C 3K3",
    "addr:housenumber":"1892",
    "addr:postcode":"l1c 3k3",
    "addr:street":"Baseline Rd W",
    "iso:country":"CA",
    "sg:address":"1892 Baseline Rd W",
    "sg:city":"Bowmanville",
    "sg:classifiers":[
        {
            "category":"Autos & Motor Vehicles",
            "subcategory":"Auto Supplies",
            "type":"Retail Goods"
        }
    ],
    "sg:phone":"+1 905 434 8007",
    "sg:postcode":"L1C 3K3",
    "sg:province":"ON",
    "sg:tags":[
        "bumper",
        "grill",
        "guard",
        "parts",
        "automobile"
    ],
    "wof:name":"Durham Bumper & Fender",
    "wof:placetype":"venue"
},
  "geometry": {"coordinates":[-78.6956863403,43.8966789246],"type":"Point"}
}