{
  "type": "Feature",
  "properties": {
    "addr:full":"204 Ronald Prom Montreal-Ouest QC H4X 1M8",
    "addr:housenumber":"204",
    "addr:postcode":"h4x 1m8",
    "addr:street":"Ronald Prom Montreal-Ouest",
    "iso:country":"CA",
    "sg:address":"204 Ronald Prom",
    "sg:city":"Montreal-Ouest",
    "sg:classifiers":[
        {
            "category":"Manufacturing",
            "subcategory":"Tools & Machinery",
            "type":"Manufacturing & Wholesale Goods"
        }
    ],
    "sg:phone":"+1 514 488 5787",
    "sg:postcode":"H4X 1M8",
    "sg:province":"QC",
    "sg:tags":[
        "mold"
    ],
    "wof:name":"Alumould & Tool Ltd",
    "wof:placetype":"venue"
},
  "geometry": {"coordinates":[-73.6423110962,45.4485855103],"type":"Point"}
}