{
  "type": "Feature",
  "properties": {
    "addr:full":"Quebec QC G1S 2P1",
    "addr:postcode":"g1s 2p1",
    "iso:country":"CA",
    "sg:city":"Quebec",
    "sg:classifiers":[
        {
            "category":"Health Services",
            "subcategory":"Doctor",
            "type":"Services"
        }
    ],
    "sg:phone":"+1 418 682 8484",
    "sg:postcode":"G1S 2P1",
    "sg:province":"QC",
    "sg:tags":[
        "dentist"
    ],
    "wof:name":"Ouellet, Bruno DDS",
    "wof:placetype":"venue"
},
  "geometry": {"coordinates":[-71.25852999999999,46.79269],"type":"Point"}
}