{
  "type": "Feature",
  "properties": {
    "addr:full":"Saskatoon SK S7H 5M7",
    "addr:postcode":"s7h 5m7",
    "iso:country":"CA",
    "sg:city":"Saskatoon",
    "sg:classifiers":[
        {
            "category":"Health Services",
            "subcategory":"Medical Lab",
            "type":"Services"
        }
    ],
    "sg:phone":"+1 306 373 5868",
    "sg:postcode":"S7H 5M7",
    "sg:province":"SK",
    "sg:tags":[
        "x",
        "laboratory"
    ],
    "wof:name":"College Park Mall X-Ray Clinic",
    "wof:placetype":"venue"
},
  "geometry": {"coordinates":[-106.591438294,52.1149215698],"type":"Point"}
}