{
  "type": "Feature",
  "properties": {
    "iso:country":"CA",
    "sg:city":"Calgary",
    "sg:classifiers":[
        {
            "category":"Wholesale",
            "subcategory":"Electrical",
            "type":"Manufacturing & Wholesale Goods"
        }
    ],
    "sg:phone":"+1 403 219 0555",
    "sg:postcode":"T1Y 6Z1",
    "sg:province":"AB",
    "sg:tags":[
        "communications",
        "equipment"
    ],
    "wof:name":"Ntf Communications Inc",
    "wof:placetype":"venue"
},
  "geometry": {"coordinates":[-113.998023987,51.0805435181],"type":"Point"}
}