{
  "type": "Feature",
  "properties": {
    "addr:full":"10028 101st St Peace River AB T8S 1S5",
    "addr:housenumber":"10028",
    "addr:postcode":"t8s 1s5",
    "addr:street":"101St St",
    "iso:country":"CA",
    "sg:address":"10028 101st St",
    "sg:city":"Peace River",
    "sg:classifiers":[
        {
            "category":"Shopping",
            "subcategory":"Department Store",
            "type":"Retail Goods"
        }
    ],
    "sg:phone":"+1 780 624 8008",
    "sg:postcode":"T8S 1S5",
    "sg:province":"AB",
    "sg:tags":[
        "shop"
    ],
    "wof:name":"Liquidation World Inc",
    "wof:placetype":"venue"
},
  "geometry": {"coordinates":[-117.288979,56.23307],"type":"Point"}
}