{
  "type": "Feature",
  "properties": {
    "addr:full":"1 Hamilton St S Waterdown ON L0R 2H0",
    "addr:housenumber":"1",
    "addr:postcode":"l0r 2h0",
    "addr:street":"Hamilton St S",
    "iso:country":"CA",
    "sg:address":"1 Hamilton St S",
    "sg:city":"Waterdown",
    "sg:classifiers":[
        {
            "category":"Real Estate",
            "subcategory":"Real Estate Operator",
            "type":"Services"
        }
    ],
    "sg:phone":"+1 905 689 7341",
    "sg:postcode":"L0R 2H0",
    "sg:province":"ON",
    "sg:tags":[
        "apartment",
        "rental",
        "agency"
    ],
    "wof:name":"Apt Rental Svc Ltd",
    "wof:placetype":"venue"
},
  "geometry": {"coordinates":[-79.895416,43.331001],"type":"Point"}
}