{
  "type": "Feature",
  "properties": {
    "addr:full":"1755 Robson St Vancouver BC V6G 3B7",
    "addr:housenumber":"1755",
    "addr:postcode":"v6g 3b7",
    "addr:street":"Robson St",
    "iso:country":"CA",
    "sg:address":"1755 Robson St",
    "sg:city":"Vancouver",
    "sg:classifiers":[
        {
            "category":"Organizations",
            "subcategory":"Political Organization",
            "type":"Services"
        }
    ],
    "sg:phone":"+1 604 878 1490",
    "sg:postcode":"V6G 3B7",
    "sg:province":"BC",
    "wof:name":"Vancouver Burrard Liberals",
    "wof:placetype":"venue"
},
  "geometry": {"coordinates":[-123.13462800000001,49.291111],"type":"Point"}
}