{
  "type": "Feature",
  "properties": {
    "addr:full":"228 Centre St Assiniboia SK S0H 0B0",
    "addr:housenumber":"228",
    "addr:postcode":"s0h 0b0",
    "addr:street":"Centre St",
    "iso:country":"CA",
    "sg:address":"228 Centre St",
    "sg:city":"Assiniboia",
    "sg:classifiers":[
        {
            "category":"Professional",
            "subcategory":"Lawyer & Legal Services",
            "type":"Services"
        }
    ],
    "sg:phone":"+1 306 642 3543",
    "sg:postcode":"S0H 0B0",
    "sg:province":"SK",
    "sg:tags":[
        "attorney"
    ],
    "wof:name":"Lewans, Paul",
    "wof:placetype":"venue"
},
  "geometry": {"coordinates":[-105.99234,49.632462],"type":"Point"}
}