{
  "type": "Feature",
  "properties": {
    "addr:full":"369 Borebank St Winnipeg MB R3N 1E5",
    "addr:housenumber":"369",
    "addr:postcode":"r3n 1e5",
    "addr:street":"Borebank St",
    "iso:country":"CA",
    "sg:address":"369 Borebank St",
    "sg:city":"Winnipeg",
    "sg:classifiers":[
        {
            "category":"Arts & Performance",
            "subcategory":"Theater",
            "type":"Entertainment"
        }
    ],
    "sg:phone":"+1 204 582 9725",
    "sg:postcode":"R3N 1E5",
    "sg:province":"MB",
    "sg:tags":[
        "bureau"
    ],
    "wof:name":"Cherry Tree Productions",
    "wof:placetype":"venue"
},
  "geometry": {"coordinates":[-97.192307,49.868279],"type":"Point"}
}