{
  "type": "Feature",
  "properties": {
    "addr:full":"7653 Main St Morell PE C0A 1S0",
    "addr:housenumber":"7653",
    "addr:postcode":"c0a 1s0",
    "addr:street":"Main St",
    "iso:country":"CA",
    "sg:address":"7653 Main St",
    "sg:city":"Morell",
    "sg:classifiers":[
        {
            "category":"Food & Beverages",
            "subcategory":"Groceries & Convenience Stores",
            "type":"Retail Goods"
        }
    ],
    "sg:phone":"+1 902 961 2253",
    "sg:postcode":"C0A 1S0",
    "sg:province":"PE",
    "sg:tags":[
        "grocer"
    ],
    "wof:name":"Jay's Clover Farm",
    "wof:placetype":"venue"
},
  "geometry": {"coordinates":[-62.7043571472,46.4161109924],"type":"Point"}
}