{
  "type": "Feature",
  "properties": {
    "addr:full":"9 Brockley Dr Hamilton ON L8E 3C3",
    "addr:housenumber":"9",
    "addr:postcode":"l8e 3c3",
    "addr:street":"Brockley Dr",
    "iso:country":"CA",
    "sg:address":"9 Brockley Dr",
    "sg:city":"Hamilton",
    "sg:classifiers":[
        {
            "category":"Freight",
            "type":"Transportation"
        }
    ],
    "sg:phone":"+1 905 561 1241",
    "sg:postcode":"L8E 3C3",
    "sg:province":"ON",
    "sg:tags":[
        "broker",
        "customs"
    ],
    "wof:name":"Harte & Lyne Ltd",
    "wof:placetype":"venue"
},
  "geometry": {"coordinates":[-79.7462844849,43.2344398499],"type":"Point"}
}