{
  "type": "Feature",
  "properties": {
    "addr:full":"Pointe-Claire QC H9R 4A5",
    "addr:postcode":"h9r 4a5",
    "iso:country":"CA",
    "sg:city":"Pointe-Claire",
    "sg:classifiers":[
        {
            "category":"Manufacturing",
            "subcategory":"Electronics",
            "type":"Manufacturing & Wholesale Goods"
        }
    ],
    "sg:phone":"+1 514 426 5588",
    "sg:postcode":"H9R 4A5",
    "sg:province":"QC",
    "sg:tags":[
        "equipment",
        "electronic",
        "supply"
    ],
    "wof:name":"Mobel Electroniques Inc",
    "wof:placetype":"venue"
},
  "geometry": {"coordinates":[-73.801277,45.46497],"type":"Point"}
}