{
  "type": "Feature",
  "properties": {
    "addr:full":"Saint-Roch-DE-L'Achigan QC J0K 3H0",
    "addr:postcode":"j0k 3h0",
    "iso:country":"CA",
    "sg:city":"Saint-Roch-DE-L'Achigan",
    "sg:classifiers":[
        {
            "category":"Cinema",
            "subcategory":"Movie Rental",
            "type":"Entertainment"
        }
    ],
    "sg:phone":"+1 450 588 5576",
    "sg:postcode":"J0K 3H0",
    "sg:province":"QC",
    "sg:tags":[
        "leasing",
        "video",
        "disc",
        "tape"
    ],
    "wof:name":"Vide 'O' Bout",
    "wof:placetype":"venue"
},
  "geometry": {"coordinates":[-72.07131195069999,48.9631843567],"type":"Point"}
}