{
  "type": "Feature",
  "properties": {
    "addr:full":"114 Purvis Lane Salt Spring Island BC V8K 2S5",
    "addr:housenumber":"114",
    "addr:postcode":"v8k 2s5",
    "addr:street":"Purvis Lane",
    "iso:country":"CA",
    "sg:address":"114 Purvis Lane",
    "sg:city":"Salt Spring Island",
    "sg:classifiers":[
        {
            "category":"Social Services",
            "type":"Services"
        }
    ],
    "sg:phone":"+1 250 537 1522",
    "sg:postcode":"V8K 2S5",
    "sg:province":"BC",
    "sg:tags":[
        "organization",
        "grocer",
        "welfare"
    ],
    "wof:name":"Thrifty Foods",
    "wof:placetype":"venue"
},
  "geometry": {"coordinates":[-123.499641,48.853687],"type":"Point"}
}