{
  "type": "Feature",
  "properties": {
    "addr:full":"91 Bridgeport Rd E Waterloo ON N2J 2K2",
    "addr:housenumber":"91",
    "addr:postcode":"n2j 2k2",
    "addr:street":"Bridgeport Rd E",
    "iso:country":"CA",
    "sg:address":"91 Bridgeport Rd E",
    "sg:city":"Waterloo",
    "sg:classifiers":[
        {
            "category":"Autos & Motor Vehicles",
            "subcategory":"Automobile Sales",
            "type":"Retail Goods"
        }
    ],
    "sg:phone":"+1 519 747 5664",
    "sg:postcode":"N2J 2K2",
    "sg:province":"ON",
    "sg:tags":[
        "car",
        "dealer"
    ],
    "wof:name":"Auto Agency",
    "wof:placetype":"venue"
},
  "geometry": {"coordinates":[-80.5143280029,43.4693183899],"type":"Point"}
}