{
  "type": "Feature",
  "properties": {
    "addr:full":"16830 111 Ave NW Edmonton AB T5M 4E8",
    "addr:housenumber":"16830",
    "addr:postcode":"t5m 4e8",
    "addr:street":"111 Ave Nw",
    "iso:country":"CA",
    "sg:address":"16830 111 Ave NW",
    "sg:city":"Edmonton",
    "sg:classifiers":[
        {
            "category":"Retail",
            "subcategory":"Auto Repair",
            "type":"Services"
        }
    ],
    "sg:phone":"+1 780 482 3818",
    "sg:postcode":"T5M 4E8",
    "sg:province":"AB",
    "sg:tags":[
        "trailer"
    ],
    "wof:name":"Edmonton Trailer Repair Ltd",
    "wof:placetype":"venue"
},
  "geometry": {"coordinates":[-113.611023,53.559662],"type":"Point"}
}