{
  "type": "Feature",
  "properties": {
    "addr:full":"59 Scott Rd Cambridge ON N3C 2X6",
    "addr:housenumber":"59",
    "addr:postcode":"n3c 2x6",
    "addr:street":"Scott Rd",
    "iso:country":"CA",
    "sg:address":"59 Scott Rd",
    "sg:city":"Cambridge",
    "sg:classifiers":[
        {
            "category":"Food & Beverages",
            "subcategory":"Bakery",
            "type":"Retail Goods"
        }
    ],
    "sg:phone":"+1 519 212 2567",
    "sg:postcode":"N3C 2X6",
    "sg:province":"ON",
    "sg:tags":[
        "baker"
    ],
    "wof:name":"Cheesecakes By Christine",
    "wof:placetype":"venue"
},
  "geometry": {"coordinates":[-80.319412,43.433723],"type":"Point"}
}