{
  "type": "Feature",
  "properties": {
    "addr:full":"6584 Deer Lake Ave Burnaby BC V5G 3T7",
    "addr:housenumber":"6584",
    "addr:postcode":"v5g 3t7",
    "addr:street":"Deer Lake Ave",
    "iso:country":"CA",
    "sg:address":"6584 Deer Lake Ave",
    "sg:city":"Burnaby",
    "sg:classifiers":[
        {
            "category":"Arts & Performance",
            "subcategory":"Theater",
            "type":"Entertainment"
        }
    ],
    "sg:phone":"+1 604 299 0412",
    "sg:postcode":"V5G 3T7",
    "sg:province":"BC",
    "wof:name":"Burnaby Lyric Opera Society",
    "wof:placetype":"venue"
},
  "geometry": {"coordinates":[-122.967934,49.238548],"type":"Point"}
}