{
  "type": "Feature",
  "properties": {
    "iso:country":"CA",
    "sg:address":"118 2 Ave W",
    "sg:city":"Cochrane",
    "sg:classifiers":[
        {
            "category":"Shopping",
            "type":"Retail Goods"
        }
    ],
    "sg:phone":"+1 403 932 3030",
    "sg:postcode":"T4C 2E7",
    "sg:province":"AB",
    "sg:tags":[
        "picture",
        "frame",
        "art",
        "gallery",
        "dealer"
    ],
    "wof:name":"Westlands Art Gallery",
    "wof:placetype":"venue"
},
  "geometry": {"coordinates":[-114.469284058,51.1902503967],"type":"Point"}
}