{
  "type": "Feature",
  "properties": {
    "addr:full":"1336 Rue Helene Sainte-Julienne QC J0K 2T0",
    "addr:housenumber":"1336",
    "addr:postcode":"j0k 2t0",
    "addr:street":"Rue Helene",
    "iso:country":"CA",
    "sg:address":"1336 Rue Helene",
    "sg:city":"Sainte-Julienne",
    "sg:classifiers":[
        {
            "category":"Wholesale",
            "subcategory":"Machinery & Supplies",
            "type":"Manufacturing & Wholesale Goods"
        }
    ],
    "sg:phone":"+1 450 831 4510",
    "sg:postcode":"J0K 2T0",
    "sg:province":"QC",
    "sg:tags":[
        "farm",
        "equipment"
    ],
    "wof:name":"Alarme & Securite pm Inc",
    "wof:placetype":"venue"
},
  "geometry": {"coordinates":[-73.704498,45.969059],"type":"Point"}
}