{
  "type": "Feature",
  "properties": {
    "addr:full":"348 Albert St E Sault Ste Marie ON P6A 2J6",
    "addr:housenumber":"348",
    "addr:postcode":"p6a 2j6",
    "addr:street":"Albert St E",
    "iso:country":"CA",
    "sg:address":"348 Albert St E",
    "sg:city":"Sault Ste Marie",
    "sg:classifiers":[
        {
            "category":"Professional",
            "subcategory":"Lawyer & Legal Services",
            "type":"Services"
        }
    ],
    "sg:phone":"+1 705 945 8868",
    "sg:postcode":"P6A 2J6",
    "sg:province":"ON",
    "sg:tags":[
        "attorney"
    ],
    "wof:name":"Mc Cooeye, Eric D",
    "wof:placetype":"venue"
},
  "geometry": {"coordinates":[-84.333313,46.513878],"type":"Point"}
}