{
  "type": "Feature",
  "properties": {
    "addr:full":"52 Hawkcliff Crt NW Calgary AB T3G 2X4",
    "addr:housenumber":"52",
    "addr:postcode":"t3g 2x4",
    "addr:street":"Hawkcliff Crt Nw",
    "iso:country":"CA",
    "sg:address":"52 Hawkcliff Crt NW",
    "sg:city":"Calgary",
    "sg:classifiers":[
        {
            "category":"Wholesale",
            "subcategory":"Electrical",
            "type":"Manufacturing & Wholesale Goods"
        }
    ],
    "sg:phone":"+1 403 547 8118",
    "sg:postcode":"T3G 2X4",
    "sg:province":"AB",
    "sg:tags":[
        "control"
    ],
    "wof:name":"Rednap Design Svc Ltd",
    "wof:placetype":"venue"
},
  "geometry": {"coordinates":[-114.165382385,51.1285667419],"type":"Point"}
}