{
  "type": "Feature",
  "properties": {
    "addr:full":"31 Trider Cres Dartmouth NS B3B 1V6",
    "addr:housenumber":"31",
    "addr:postcode":"b3b 1v6",
    "addr:street":"Trider Cres",
    "iso:country":"CA",
    "sg:address":"31 Trider Cres",
    "sg:city":"Dartmouth",
    "sg:classifiers":[
        {
            "category":"Professional",
            "subcategory":"Testing Lab",
            "type":"Services"
        }
    ],
    "sg:phone":"+1 902 468 3344",
    "sg:postcode":"B3B 1V6",
    "sg:province":"NS",
    "sg:tags":[
        "calibration"
    ],
    "wof:name":"Pylon Atlantic Inc",
    "wof:placetype":"venue"
},
  "geometry": {"coordinates":[-63.58828,44.707359],"type":"Point"}
}