{
  "type": "Feature",
  "properties": {
    "iso:country":"CA",
    "sg:address":"1465 Pembina Hwy",
    "sg:city":"Winnipeg",
    "sg:classifiers":[
        {
            "category":"Food & Beverages",
            "subcategory":"Meat & Fish",
            "type":"Retail Goods"
        }
    ],
    "sg:phone":"+1 204 284 2976",
    "sg:postcode":"R3T 2C5",
    "sg:province":"MB",
    "wof:name":"Webers Meat & Delicatessen",
    "wof:placetype":"venue"
},
  "geometry": {"coordinates":[-97.151054,49.836227],"type":"Point"}
}