{
  "type": "Feature",
  "properties": {
    "addr:full":"209 Drummond St Blyth ON N0M 1H0",
    "addr:housenumber":"209",
    "addr:postcode":"n0m 1h0",
    "addr:street":"Drummond St",
    "iso:country":"CA",
    "sg:address":"209 Drummond St",
    "sg:city":"Blyth",
    "sg:classifiers":[
        {
            "category":"Food & Beverages",
            "subcategory":"Groceries & Convenience Stores",
            "type":"Retail Goods"
        }
    ],
    "sg:phone":"+1 519 523 4551",
    "sg:postcode":"N0M 1H0",
    "sg:province":"ON",
    "sg:tags":[
        "grocer"
    ],
    "wof:name":"Scrimgeour's Food Market",
    "wof:placetype":"venue"
},
  "geometry": {"coordinates":[-81.42823799999999,43.737106],"type":"Point"}
}