{
  "type": "Feature",
  "properties": {
    "addr:full":"Wainwright AB T9W 2R3",
    "addr:postcode":"t9w 2r3",
    "iso:country":"CA",
    "sg:city":"Wainwright",
    "sg:classifiers":[
        {
            "category":"Government",
            "subcategory":"Office",
            "type":"Public Place"
        }
    ],
    "sg:phone":"+1 780 842 6177",
    "sg:postcode":"T9W 2R3",
    "sg:province":"AB",
    "wof:name":"Wainwright Constituency Office",
    "wof:placetype":"venue"
},
  "geometry": {"coordinates":[-110.85936,52.835453],"type":"Point"}
}