{
  "type": "Feature",
  "properties": {
    "addr:full":"2333 Sadler Dr Prince George BC V2K 4N7",
    "addr:housenumber":"2333",
    "addr:postcode":"v2k 4n7",
    "addr:street":"Sadler Dr",
    "iso:country":"CA",
    "sg:address":"2333 Sadler Dr",
    "sg:city":"Prince George",
    "sg:classifiers":[
        {
            "category":"Retail",
            "subcategory":"Portrait Studio",
            "type":"Services"
        }
    ],
    "sg:phone":"+1 250 962 2160",
    "sg:postcode":"V2K 4N7",
    "sg:province":"BC",
    "sg:tags":[
        "photographer"
    ],
    "wof:name":"Memories By Moira",
    "wof:placetype":"venue"
},
  "geometry": {"coordinates":[-122.787109375,53.9634628296],"type":"Point"}
}