{
  "type": "Feature",
  "properties": {
    "addr:full":"Prevost QC J0R 1T0",
    "addr:postcode":"j0r 1t0",
    "addr:street":"Prevost",
    "iso:country":"CA",
    "sg:city":"Prevost",
    "sg:classifiers":[
        {
            "category":"Home & Garden",
            "subcategory":"Garden Supply",
            "type":"Retail Goods"
        }
    ],
    "sg:phone":"+1 450 224 2000",
    "sg:postcode":"J0R 1T0",
    "sg:province":"QC",
    "sg:tags":[
        "nurseryman",
        "center"
    ],
    "wof:name":"Botanix Pepinere G Lorrain",
    "wof:placetype":"venue"
},
  "geometry": {"coordinates":[-74.06905399999999,45.856457],"type":"Point"}
}