{
  "type": "Feature",
  "properties": {
    "addr:full":"7720 69 St NW Edmonton AB T6B 2J7",
    "addr:housenumber":"7720",
    "addr:postcode":"t6b 2j7",
    "addr:street":"69 St Nw",
    "iso:country":"CA",
    "sg:address":"7720 69 St NW",
    "sg:city":"Edmonton",
    "sg:classifiers":[
        {
            "category":"Wholesale",
            "subcategory":"Machinery & Supplies",
            "type":"Manufacturing & Wholesale Goods"
        }
    ],
    "sg:phone":"+1 780 413 1760",
    "sg:postcode":"T6B 2J7",
    "sg:province":"AB",
    "sg:tags":[
        "valve"
    ],
    "wof:name":"D G Valve Systems Inc",
    "wof:placetype":"venue"
},
  "geometry": {"coordinates":[-113.433403015,53.5136756897],"type":"Point"}
}