{
  "type": "Feature",
  "properties": {
    "addr:full":"243 204 Rte E Audet QC G0Y 1A0",
    "addr:housenumber":"204",
    "addr:postcode":"g0y 1a0",
    "addr:street":"Rte E Audet",
    "iso:country":"CA",
    "sg:address":"243 204 Rte E",
    "sg:city":"Audet",
    "sg:classifiers":[
        {
            "category":"Building & Trades",
            "subcategory":"Construction",
            "type":"Services"
        }
    ],
    "sg:phone":"+1 819 583 0150",
    "sg:postcode":"G0Y 1A0",
    "sg:province":"QC",
    "sg:tags":[
        "concrete",
        "excavating",
        "form",
        "contractor"
    ],
    "wof:name":"Construction Patrick Boucher",
    "wof:placetype":"venue"
},
  "geometry": {"coordinates":[-70.7383270264,45.6565818787],"type":"Point"}
}