{
  "type": "Feature",
  "properties": {
    "addr:full":"8530 Rue Champ D'Eau Saint-Leonard QC H1P 1Y3",
    "addr:housenumber":"8530",
    "addr:postcode":"h1p 1y3",
    "addr:street":"Rue Champ D'Eau",
    "iso:country":"CA",
    "sg:address":"8530 Rue Champ D'Eau",
    "sg:city":"Saint-Leonard",
    "sg:classifiers":[
        {
            "category":"Professional",
            "subcategory":"Business Services",
            "type":"Services"
        }
    ],
    "sg:phone":"+1 514 328 9348",
    "sg:postcode":"H1P 1Y3",
    "sg:province":"QC",
    "sg:tags":[
        "recording",
        "studio"
    ],
    "wof:name":"Studio DE Production Cherry",
    "wof:placetype":"venue"
},
  "geometry": {"coordinates":[-73.5953369141,45.589389801],"type":"Point"}
}