{
  "type": "Feature",
  "properties": {
    "addr:full":"223 Main St Ottawa ON K1S 1C4",
    "addr:housenumber":"223",
    "addr:postcode":"k1s 1c4",
    "addr:street":"Main St",
    "iso:country":"CA",
    "sg:address":"223 Main St",
    "sg:city":"Ottawa",
    "sg:classifiers":[
        {
            "category":"Social Services",
            "type":"Services"
        }
    ],
    "sg:phone":"+1 613 782 3022",
    "sg:postcode":"K1S 1C4",
    "sg:province":"ON",
    "sg:tags":[
        "counselor",
        "marriage",
        "family"
    ],
    "wof:name":"Centre DE Counselling L'Univ",
    "wof:placetype":"venue"
},
  "geometry": {"coordinates":[-75.677521,45.408432],"type":"Point"}
}