{
  "type": "Feature",
  "properties": {
    "addr:full":"Saskatoon SK S7H 3K5",
    "addr:postcode":"s7h 3k5",
    "iso:country":"CA",
    "sg:city":"Saskatoon",
    "sg:classifiers":[
        {
            "category":"Personal",
            "subcategory":"Barber",
            "type":"Services"
        }
    ],
    "sg:phone":"+1 306 955 3922",
    "sg:postcode":"S7H 3K5",
    "sg:province":"SK",
    "wof:name":"Shear Creations",
    "wof:placetype":"venue"
},
  "geometry": {"coordinates":[-106.611542,52.108704],"type":"Point"}
}