{
  "type": "Feature",
  "properties": {
    "addr:full":"440 Mcnicoll Ave North York ON M2H 2E1",
    "addr:housenumber":"440",
    "addr:postcode":"m2h 2e1",
    "addr:street":"Mcnicoll Ave",
    "iso:country":"CA",
    "sg:address":"440 Mcnicoll Ave",
    "sg:city":"North York",
    "sg:classifiers":[
        {
            "category":"Restaurant",
            "type":"Food & Drink"
        }
    ],
    "sg:phone":"+1 416 499 1791",
    "sg:postcode":"M2H 2E1",
    "sg:province":"ON",
    "wof:name":"Hickory House Restaurant",
    "wof:placetype":"venue"
},
  "geometry": {"coordinates":[-79.341331,43.80365],"type":"Point"}
}