{
  "type": "Feature",
  "properties": {
    "addr:full":"1375 Boul Monseigneur-Langlois Grande-Ile QC J6S 1C1",
    "addr:housenumber":"1375",
    "addr:postcode":"j6s 1c1",
    "addr:street":"Boul Monseigneur-Langlois Grande-Ile",
    "iso:country":"CA",
    "sg:address":"1375 Boul Monseigneur-Langlois",
    "sg:city":"Grande-Ile",
    "sg:classifiers":[
        {
            "category":"Shopping",
            "subcategory":"Department Store",
            "type":"Retail Goods"
        }
    ],
    "sg:phone":"+1 450 373 7310",
    "sg:postcode":"J6S 1C1",
    "sg:province":"QC",
    "wof:name":"Laubainerie",
    "wof:placetype":"venue"
},
  "geometry": {"coordinates":[-74.132378,45.271164],"type":"Point"}
}