{
  "type": "Feature",
  "properties": {
    "addr:full":"Parry Sound ON P2A 2W9",
    "addr:postcode":"p2a 2w9",
    "iso:country":"CA",
    "sg:city":"Parry Sound",
    "sg:classifiers":[
        {
            "category":"Professional",
            "subcategory":"Computer Services",
            "type":"Services"
        }
    ],
    "sg:phone":"+1 705 746 4485",
    "sg:postcode":"P2A 2W9",
    "sg:province":"ON",
    "wof:name":"Internal Telephone Inc",
    "wof:placetype":"venue"
},
  "geometry": {"coordinates":[-80.022308,45.363766],"type":"Point"}
}