{
  "type": "Feature",
  "properties": {
    "addr:full":"805 Rue Villeray Montreal QC H2R 1J4",
    "addr:housenumber":"805",
    "addr:postcode":"h2r 1j4",
    "addr:street":"Rue Villeray",
    "iso:country":"CA",
    "sg:address":"805 Rue Villeray",
    "sg:city":"Montreal",
    "sg:classifiers":[
        {
            "category":"Professional",
            "type":"Services"
        }
    ],
    "sg:phone":"+1 514 254 5740",
    "sg:postcode":"H2R 1J4",
    "sg:province":"QC",
    "sg:tags":[
        "establishment",
        "counselor",
        "marriage",
        "family"
    ],
    "wof:name":"Sof Montreal",
    "wof:placetype":"venue"
},
  "geometry": {"coordinates":[-73.62097167970001,45.5443572998],"type":"Point"}
}