{
  "type": "Feature",
  "properties": {
    "addr:full":"1460 Stoneybrook Cres London ON N5X 1C4",
    "addr:housenumber":"1460",
    "addr:postcode":"n5x 1c4",
    "addr:street":"Stoneybrook Cres",
    "iso:country":"CA",
    "sg:address":"1460 Stoneybrook Cres",
    "sg:city":"London",
    "sg:classifiers":[
        {
            "category":"Education",
            "subcategory":"School",
            "type":"Public Place"
        }
    ],
    "sg:phone":"+1 519 452 8590",
    "sg:postcode":"N5X 1C4",
    "sg:province":"ON",
    "wof:name":"Stoneybrook School",
    "wof:placetype":"venue"
},
  "geometry": {"coordinates":[-81.2609863281,43.0290641785],"type":"Point"}
}