{
  "type": "Feature",
  "properties": {
    "iso:country":"CA",
    "sg:city":"Laval",
    "sg:classifiers":[
        {
            "category":"Health Services",
            "subcategory":"Hospital",
            "type":"Services"
        }
    ],
    "sg:phone":"+1 450 668 1058",
    "sg:postcode":"H7G 2T2",
    "sg:province":"QC",
    "sg:tags":[
        "mental"
    ],
    "wof:name":"En-Droit",
    "wof:placetype":"venue"
},
  "geometry": {"coordinates":[-73.6838378906,45.5631790161],"type":"Point"}
}