{
  "type": "Feature",
  "properties": {
    "addr:full":"The Pas MB R9A 1K9",
    "addr:postcode":"r9a 1k9",
    "iso:country":"CA",
    "sg:city":"The Pas",
    "sg:classifiers":[
        {
            "category":"Arts & Performance",
            "subcategory":"Theater",
            "type":"Entertainment"
        }
    ],
    "sg:phone":"+1 204 623 6904",
    "sg:postcode":"R9A 1K9",
    "sg:province":"MB",
    "sg:tags":[
        "dance",
        "music",
        "recorded"
    ],
    "wof:name":"Partie Sound Music Svc",
    "wof:placetype":"venue"
},
  "geometry": {"coordinates":[-101.23777771,53.8207931519],"type":"Point"}
}