{
  "type": "Feature",
  "properties": {
    "iso:country":"CA",
    "sg:address":"5554 Av Robinson",
    "sg:city":"Cote Saint-Luc",
    "sg:classifiers":[
        {
            "category":"Organizations",
            "subcategory":"Professional Association",
            "type":"Services"
        }
    ],
    "sg:phone":"+1 514 481 2033",
    "sg:postcode":"H4V 2P8",
    "sg:province":"QC",
    "wof:name":"Merton Home & School Assn",
    "wof:placetype":"venue"
},
  "geometry": {"coordinates":[-73.651199,45.472446],"type":"Point"}
}