{
  "type": "Feature",
  "properties": {
    "addr:full":"220 Av Guthrie Dorval QC H9P 2S8",
    "addr:housenumber":"220",
    "addr:postcode":"h9p 2s8",
    "addr:street":"Av Guthrie",
    "iso:country":"CA",
    "sg:address":"220 Av Guthrie",
    "sg:city":"Dorval",
    "sg:classifiers":[
        {
            "category":"Manufacturing",
            "subcategory":"Tools & Machinery",
            "type":"Manufacturing & Wholesale Goods"
        }
    ],
    "sg:phone":"+1 514 633 8423",
    "sg:postcode":"H9P 2S8",
    "sg:province":"QC",
    "sg:tags":[
        "carpet",
        "cleaning",
        "rug"
    ],
    "wof:name":"Easy-Way Inc",
    "wof:placetype":"venue"
},
  "geometry": {"coordinates":[-73.7270278931,45.4517593384],"type":"Point"}
}