{
  "type": "Feature",
  "properties": {
    "addr:full":"833 Lynn Valley Rd North Vancouver BC V7J 1Z6",
    "addr:housenumber":"833",
    "addr:postcode":"v7j 1z6",
    "addr:street":"Lynn Valley Rd",
    "iso:country":"CA",
    "sg:address":"833 Lynn Valley Rd",
    "sg:city":"North Vancouver",
    "sg:classifiers":[
        {
            "category":"Building & Trades",
            "subcategory":"Construction",
            "type":"Services"
        }
    ],
    "sg:phone":"+1 604 984 6560",
    "sg:postcode":"V7J 1Z6",
    "sg:province":"BC",
    "sg:tags":[
        "roofing",
        "contractor"
    ],
    "wof:name":"Affordable Quality Roofing Ltd",
    "wof:placetype":"venue"
},
  "geometry": {"coordinates":[-123.04964447,49.33070755],"type":"Point"}
}