{
  "type": "Feature",
  "properties": {
    "iso:country":"CA",
    "sg:address":"13235 Jamsyl Dr",
    "sg:city":"Windsor",
    "sg:classifiers":[
        {
            "category":"Professional",
            "subcategory":"Advertising",
            "type":"Services"
        }
    ],
    "sg:phone":"+1 519 979 5626",
    "sg:postcode":"N8N 2L9",
    "sg:province":"ON",
    "sg:tags":[
        "magazine"
    ],
    "wof:name":"Prologix Distribution Svc",
    "wof:placetype":"venue"
},
  "geometry": {"coordinates":[-83.0339126587,42.3178215027],"type":"Point"}
}