{
  "type": "Feature",
  "properties": {
    "addr:full":"710 Crowfoot Cres NW Calgary AB T3G 4S3",
    "addr:housenumber":"710",
    "addr:postcode":"t3g 4s3",
    "addr:street":"Crowfoot Cres Nw",
    "iso:country":"CA",
    "sg:address":"710 Crowfoot Cres NW",
    "sg:city":"Calgary",
    "sg:classifiers":[
        {
            "category":"Autos & Motor Vehicles",
            "subcategory":"Automobile Sales",
            "type":"Retail Goods"
        }
    ],
    "sg:phone":"+1 403 374 3374",
    "sg:postcode":"T3G 4S3",
    "sg:province":"AB",
    "sg:tags":[
        "car",
        "dealer"
    ],
    "wof:name":"Saturn Isuzu of Crowfoot",
    "wof:placetype":"venue"
},
  "geometry": {"coordinates":[-114.20503234900001,51.1278457642],"type":"Point"}
}