{
  "type": "Feature",
  "properties": {
    "addr:full":"319 Rue Victoria Edmundston NB E3V 2J7",
    "addr:housenumber":"319",
    "addr:postcode":"e3v 2j7",
    "addr:street":"Rue Victoria",
    "iso:country":"CA",
    "sg:address":"319 Rue Victoria",
    "sg:city":"Edmundston",
    "sg:classifiers":[
        {
            "category":"Health Services",
            "subcategory":"Chiropractor",
            "type":"Services"
        }
    ],
    "sg:phone":"+1 506 739 5567",
    "sg:postcode":"E3V 2J7",
    "sg:province":"NB",
    "wof:name":"Clinique Chiropractique Michel",
    "wof:placetype":"venue"
},
  "geometry": {"coordinates":[-68.3281555176,47.373626709],"type":"Point"}
}