{
  "type": "Feature",
  "properties": {
    "addr:full":"8415 Rue Saint-Denis Montreal QC H2P 2G9",
    "addr:housenumber":"8415",
    "addr:postcode":"h2p 2g9",
    "addr:street":"Rue Saint-Denis",
    "iso:country":"CA",
    "sg:address":"8415 Rue Saint-Denis",
    "sg:city":"Montreal",
    "sg:classifiers":[
        {
            "category":"Health Services",
            "subcategory":"Health Practitioner",
            "type":"Services"
        }
    ],
    "sg:phone":"+1 514 382 2107",
    "sg:postcode":"H2P 2G9",
    "sg:province":"QC",
    "sg:tags":[
        "dietitian"
    ],
    "wof:name":"DE Keyser Nutrition Allergies",
    "wof:placetype":"venue"
},
  "geometry": {"coordinates":[-73.633949,45.544121],"type":"Point"}
}