{
  "type": "Feature",
  "properties": {
    "addr:full":"163 Rue Drouin Scott QC G0S 3G0",
    "addr:housenumber":"163",
    "addr:postcode":"g0s 3g0",
    "addr:street":"Rue Drouin",
    "iso:country":"CA",
    "sg:address":"163 Rue Drouin",
    "sg:city":"Scott",
    "sg:classifiers":[
        {
            "category":"Shopping",
            "type":"Retail Goods"
        }
    ],
    "sg:phone":"+1 418 387 2425",
    "sg:postcode":"G0S 3G0",
    "sg:province":"QC",
    "sg:tags":[
        "monument"
    ],
    "wof:name":"Monuments Chabot Inc",
    "wof:placetype":"venue"
},
  "geometry": {"coordinates":[-71.04605100000001,46.501438],"type":"Point"}
}