{
  "type": "Feature",
  "properties": {
    "iso:country":"CA",
    "sg:address":"3572 Rue Jean-Talon E",
    "sg:city":"Montreal",
    "sg:classifiers":[
        {
            "category":"Personal",
            "subcategory":"Beauty Salon",
            "type":"Services"
        }
    ],
    "sg:phone":"+1 514 728 0498",
    "sg:postcode":"H2A 1X5",
    "sg:province":"QC",
    "wof:name":"Coiffure Sahara",
    "wof:placetype":"venue"
},
  "geometry": {"coordinates":[-73.595406,45.561928],"type":"Point"}
}