{
  "type": "Feature",
  "properties": {
    "addr:full":"Chilliwack BC V2R 1A2",
    "addr:postcode":"v2r 1a2",
    "iso:country":"CA",
    "sg:city":"Chilliwack",
    "sg:classifiers":[
        {
            "category":"Shopping",
            "subcategory":"Department Store",
            "type":"Retail Goods"
        }
    ],
    "sg:phone":"+1 604 858 5100",
    "sg:postcode":"V2R 1A2",
    "sg:province":"BC",
    "wof:name":"Wal-Mart",
    "wof:placetype":"venue"
},
  "geometry": {"coordinates":[-121.961731,49.140621],"type":"Point"}
}