{
  "type": "Feature",
  "properties": {
    "addr:full":"Surrey BC V3W 6K2",
    "addr:postcode":"v3w 6k2",
    "iso:country":"CA",
    "sg:city":"Surrey",
    "sg:classifiers":[
        {
            "category":"Wholesale",
            "subcategory":"Non-durable Goods",
            "type":"Manufacturing & Wholesale Goods"
        }
    ],
    "sg:phone":"+1 604 591 9122",
    "sg:postcode":"V3W 6K2",
    "sg:province":"BC",
    "sg:tags":[
        "broom"
    ],
    "wof:name":"Kwick Clean & Green Ltd",
    "wof:placetype":"venue"
},
  "geometry": {"coordinates":[-122.86792800000001,49.14106],"type":"Point"}
}