{
  "type": "Feature",
  "properties": {
    "addr:full":"674 Upper James St Hamilton ON L9C 2Z6",
    "addr:housenumber":"674",
    "addr:postcode":"l9c 2z6",
    "addr:street":"Upper James St",
    "iso:country":"CA",
    "sg:address":"674 Upper James St",
    "sg:city":"Hamilton",
    "sg:classifiers":[
        {
            "category":"Shopping",
            "subcategory":"Bicycles & Sporting Goods",
            "type":"Retail Goods"
        }
    ],
    "sg:phone":"+1 905 575 3051",
    "sg:postcode":"L9C 2Z6",
    "sg:province":"ON",
    "wof:name":"Tru Grip Gymnastics",
    "wof:placetype":"venue"
},
  "geometry": {"coordinates":[-79.87938699999999,43.234509],"type":"Point"}
}