{
  "type": "Feature",
  "properties": {
    "addr:full":"5775 Route 335 Saint-Calixte QC J0K 1Z0",
    "addr:housenumber":"5775",
    "addr:postcode":"j0k 1z0",
    "addr:street":"Route 335",
    "iso:country":"CA",
    "sg:address":"5775 Route 335",
    "sg:city":"Saint-Calixte",
    "sg:classifiers":[
        {
            "category":"Building & Trades",
            "subcategory":"Electrical",
            "type":"Services"
        }
    ],
    "sg:phone":"+1 450 222 3698",
    "sg:postcode":"J0K 1Z0",
    "sg:province":"QC",
    "sg:tags":[
        "electric",
        "contractor"
    ],
    "wof:name":"Payette Serge Electricien Inc",
    "wof:placetype":"venue"
},
  "geometry": {"coordinates":[-73.846031,45.945538],"type":"Point"}
}