{
  "type": "Feature",
  "properties": {
    "addr:full":"Toronto ON M4C 4X3",
    "addr:postcode":"m4c 4x3",
    "iso:country":"CA",
    "sg:city":"Toronto",
    "sg:classifiers":[
        {
            "category":"Building & Trades",
            "subcategory":"Construction",
            "type":"Services"
        }
    ],
    "sg:phone":"+1 416 694 7004",
    "sg:postcode":"M4C 4X3",
    "sg:province":"ON",
    "sg:tags":[
        "resurfacing",
        "laying",
        "refinishing",
        "floor"
    ],
    "wof:name":"Minoa Flooring",
    "wof:placetype":"venue"
},
  "geometry": {"coordinates":[-79.30127716059999,43.6874008179],"type":"Point"}
}