{
  "type": "Feature",
  "properties": {
    "addr:full":"5588 Signal Hill Ctr SW Calgary AB T3H 3P8",
    "addr:housenumber":"5588",
    "addr:postcode":"t3h 3p8",
    "addr:street":"Signal Hill Ctr Sw",
    "iso:country":"CA",
    "sg:address":"5588 Signal Hill Ctr SW",
    "sg:city":"Calgary",
    "sg:classifiers":[
        {
            "category":"Shopping",
            "subcategory":"Hobbies, Toys, & Games",
            "type":"Retail Goods"
        }
    ],
    "sg:phone":"+1 403 246 3336",
    "sg:postcode":"T3H 3P8",
    "sg:province":"AB",
    "sg:tags":[
        "craft",
        "supply"
    ],
    "wof:name":"Michaels Arts & Crafts",
    "wof:placetype":"venue"
},
  "geometry": {"coordinates":[-114.167991638,51.0192947388],"type":"Point"}
}