{
  "type": "Feature",
  "properties": {
    "addr:full":"205 Haichert St Warman SK S0K 4S0",
    "addr:housenumber":"205",
    "addr:postcode":"s0k 4s0",
    "addr:street":"Haichert St",
    "iso:country":"CA",
    "sg:address":"205 Haichert St",
    "sg:city":"Warman",
    "sg:classifiers":[
        {
            "category":"Building & Trades",
            "subcategory":"Construction",
            "type":"Services"
        }
    ],
    "sg:phone":"+1 306 668 2866",
    "sg:postcode":"S0K 4S0",
    "sg:province":"SK",
    "sg:tags":[
        "home",
        "builder",
        "general",
        "contractor"
    ],
    "wof:name":"Loewen Concrete",
    "wof:placetype":"venue"
},
  "geometry": {"coordinates":[-106.572525024,52.3184890747],"type":"Point"}
}