{
  "type": "Feature",
  "properties": {
    "addr:full":"5921 87A St NW Edmonton AB T6E 5W6",
    "addr:housenumber":"5921",
    "addr:postcode":"t6e 5w6",
    "addr:street":"87A St Nw",
    "iso:country":"CA",
    "sg:address":"5921 87A St NW",
    "sg:city":"Edmonton",
    "sg:classifiers":[
        {
            "category":"Mining & Drilling",
            "type":"Manufacturing & Wholesale Goods"
        }
    ],
    "sg:phone":"+1 780 465 6006",
    "sg:postcode":"T6E 5W6",
    "sg:province":"AB",
    "sg:tags":[
        "field",
        "oil"
    ],
    "wof:name":"Control Drilling Svc Ltd",
    "wof:placetype":"venue"
},
  "geometry": {"coordinates":[-113.460739136,53.4950752258],"type":"Point"}
}