{
  "type": "Feature",
  "properties": {
    "iso:country":"CA",
    "sg:address":"803 Princess Ave",
    "sg:city":"Brandon",
    "sg:classifiers":[
        {
            "category":"Home & Garden",
            "subcategory":"Garden Supply",
            "type":"Retail Goods"
        }
    ],
    "sg:phone":"+1 204 727 0575",
    "sg:postcode":"R7A 0P5",
    "sg:province":"MB",
    "sg:tags":[
        "bulb",
        "seed"
    ],
    "wof:name":"Lindenberg Seeds Ltd",
    "wof:placetype":"venue"
},
  "geometry": {"coordinates":[-99.948890686,49.8470153809],"type":"Point"}
}