{
  "type": "Feature",
  "properties": {
    "addr:full":"952 Main St E Hamilton ON L8M 1M8",
    "addr:housenumber":"952",
    "addr:postcode":"l8m 1m8",
    "addr:street":"Main St E",
    "iso:country":"CA",
    "sg:address":"952 Main St E",
    "sg:city":"Hamilton",
    "sg:classifiers":[
        {
            "category":"Banks & Credit Unions",
            "subcategory":"Financial Services",
            "type":"Services"
        }
    ],
    "sg:phone":"+1 905 544 6300",
    "sg:postcode":"L8M 1M8",
    "sg:province":"ON",
    "sg:tags":[
        "bankruptcy",
        "trustee"
    ],
    "wof:name":"Hobbs & CO",
    "wof:placetype":"venue"
},
  "geometry": {"coordinates":[-79.831337,43.245293],"type":"Point"}
}