{
  "type": "Feature",
  "properties": {
    "addr:full":"1399 Regent St Fredericton NB E3C 1A3",
    "addr:housenumber":"1399",
    "addr:postcode":"e3c 1a3",
    "addr:street":"Regent St",
    "iso:country":"CA",
    "sg:address":"1399 Regent St",
    "sg:city":"Fredericton",
    "sg:classifiers":[
        {
            "category":"Shopping",
            "subcategory":"Department Store",
            "type":"Retail Goods"
        }
    ],
    "sg:phone":"+1 506 452 1511",
    "sg:postcode":"E3C 1A3",
    "sg:province":"NB",
    "wof:name":"Wal-Mart",
    "wof:placetype":"venue"
},
  "geometry": {"coordinates":[-66.66349,45.932686],"type":"Point"}
}