{
  "type": "Feature",
  "properties": {
    "addr:full":"1301 Front Rd S Amherstburg ON N9V 2M5",
    "addr:housenumber":"1301",
    "addr:postcode":"n9v 2m5",
    "addr:street":"Front Rd S",
    "iso:country":"CA",
    "sg:address":"1301 Front Rd S",
    "sg:city":"Amherstburg",
    "sg:classifiers":[
        {
            "category":"Building & Trades",
            "subcategory":"Landscaping Services",
            "type":"Services"
        }
    ],
    "sg:phone":"+1 519 736 6085",
    "sg:postcode":"N9V 2M5",
    "sg:province":"ON",
    "sg:tags":[
        "lawn",
        "maintenance",
        "grounds"
    ],
    "wof:name":"Laing's Lawn Care & Pest Cntrl",
    "wof:placetype":"venue"
},
  "geometry": {"coordinates":[-83.1160125732,42.0673408508],"type":"Point"}
}