{
  "type": "Feature",
  "properties": {
    "addr:full":"279 Vincent St Stony Mountain MB R0C 3A0",
    "addr:housenumber":"279",
    "addr:postcode":"r0c 3a0",
    "addr:street":"Vincent St",
    "iso:country":"CA",
    "sg:address":"279 Vincent St",
    "sg:city":"Stony Mountain",
    "sg:classifiers":[
        {
            "category":"Mining & Drilling",
            "type":"Manufacturing & Wholesale Goods"
        }
    ],
    "sg:phone":"+1 204 344 5115",
    "sg:postcode":"R0C 3A0",
    "sg:province":"MB",
    "sg:tags":[
        "stone"
    ],
    "wof:name":"Mariash Construction Ltd",
    "wof:placetype":"venue"
},
  "geometry": {"coordinates":[-101.086395,52.38419],"type":"Point"}
}