{
  "type": "Feature",
  "properties": {
    "iso:country":"CA",
    "sg:city":"Berthierville",
    "sg:classifiers":[
        {
            "category":"Building & Trades",
            "subcategory":"Construction",
            "type":"Services"
        }
    ],
    "sg:phone":"+1 450 836 1379",
    "sg:postcode":"J0K 1A0",
    "sg:province":"QC",
    "sg:tags":[
        "masonry",
        "contractor"
    ],
    "wof:name":"Maconnerie S Degrandpre",
    "wof:placetype":"venue"
},
  "geometry": {"coordinates":[-73.1882553101,46.0874481201],"type":"Point"}
}