{
  "type": "Feature",
  "properties": {
    "iso:country":"CA",
    "sg:address":"12036 County Rd 27",
    "sg:city":"Midhurst",
    "sg:classifiers":[
        {
            "category":"Building & Trades",
            "subcategory":"Construction",
            "type":"Services"
        }
    ],
    "sg:phone":"+1 705 726 0199",
    "sg:postcode":"L0L 1X0",
    "sg:province":"ON",
    "sg:tags":[
        "excavating",
        "contractor"
    ],
    "wof:name":"Bruce Beard Bulldozing & Grdng",
    "wof:placetype":"venue"
},
  "geometry": {"coordinates":[-79.7301559448,44.4444961548],"type":"Point"}
}