{
  "type": "Feature",
  "properties": {
    "addr:full":"253 Ch Du Lac-Connelly Saint-Hippolyte QC J8A 1Z8",
    "addr:housenumber":"253",
    "addr:postcode":"j8a 1z8",
    "addr:street":"Ch Du Lac-Connelly",
    "iso:country":"CA",
    "sg:address":"253 Ch Du Lac-Connelly",
    "sg:city":"Saint-Hippolyte",
    "sg:classifiers":[
        {
            "category":"Restaurant",
            "type":"Food & Drink"
        }
    ],
    "sg:phone":"+1 450 563 3228",
    "sg:postcode":"J8A 1Z8",
    "sg:province":"QC",
    "wof:name":"Restaurant Des Nations",
    "wof:placetype":"venue"
},
  "geometry": {"coordinates":[-73.983673,45.905365],"type":"Point"}
}