{
  "type": "Feature",
  "properties": {
    "iso:country":"CA",
    "sg:address":"25 Carn Rd",
    "sg:city":"Inuvik",
    "sg:classifiers":[
        {
            "category":"Building & Trades",
            "subcategory":"Cleaning & Sanitation",
            "type":"Services"
        }
    ],
    "sg:phone":"+1 867 777 3535",
    "sg:postcode":"X0E 0T0",
    "sg:province":"NT",
    "sg:tags":[
        "breakfast",
        "janitor",
        "accommodation",
        "bed"
    ],
    "wof:name":"Krystal Kleen Ltd",
    "wof:placetype":"venue"
},
  "geometry": {"coordinates":[-133.734939575,68.3610534668],"type":"Point"}
}