{
  "type": "Feature",
  "properties": {
    "iso:country":"CA",
    "sg:address":"6525 Boul Decarie",
    "sg:city":"Montreal",
    "sg:classifiers":[
        {
            "category":"Professional",
            "subcategory":"Lawyer & Legal Services",
            "type":"Services"
        }
    ],
    "sg:phone":"+1 514 341 5353",
    "sg:postcode":"H3W 3E3",
    "sg:province":"QC",
    "sg:tags":[
        "attorney"
    ],
    "wof:name":"Gorszman, E Leslie",
    "wof:placetype":"venue"
},
  "geometry": {"coordinates":[-73.645569,45.491379],"type":"Point"}
}