{
  "type": "Feature",
  "properties": {
    "iso:country":"CA",
    "sg:city":"Markham",
    "sg:classifiers":[
        {
            "category":"Wholesale",
            "subcategory":"Machinery & Supplies",
            "type":"Manufacturing & Wholesale Goods"
        }
    ],
    "sg:phone":"+1 905 475 4830",
    "sg:postcode":"L3R 3V9",
    "sg:province":"ON",
    "sg:tags":[
        "packaging"
    ],
    "wof:name":"Pmr Packaging Inc",
    "wof:placetype":"venue"
},
  "geometry": {"coordinates":[-79.359001,43.824188],"type":"Point"}
}