{
  "type": "Feature",
  "properties": {
    "addr:full":"105 Rue DE L'Echo Saint-Eustache QC J7P 3W3",
    "addr:housenumber":"105",
    "addr:postcode":"j7p 3w3",
    "addr:street":"Rue De L'Echo",
    "iso:country":"CA",
    "sg:address":"105 Rue DE L'Echo",
    "sg:city":"Saint-Eustache",
    "sg:classifiers":[
        {
            "category":"Professional",
            "subcategory":"Testing Lab",
            "type":"Services"
        }
    ],
    "sg:phone":"+1 450 974 7252",
    "sg:postcode":"J7P 3W3",
    "sg:province":"QC",
    "sg:tags":[
        "laboratory"
    ],
    "wof:name":"Probioteck Inc",
    "wof:placetype":"venue"
},
  "geometry": {"coordinates":[-73.8888931274,45.5580406189],"type":"Point"}
}