{
  "type": "Feature",
  "properties": {
    "iso:country":"CA",
    "sg:address":"10311 Lonsdale Cres",
    "sg:city":"Windsor",
    "sg:classifiers":[
        {
            "category":"Arts & Performance",
            "subcategory":"Theater",
            "type":"Entertainment"
        }
    ],
    "sg:phone":"+1 519 979 0023",
    "sg:postcode":"N8R 2E2",
    "sg:province":"ON",
    "sg:tags":[
        "music"
    ],
    "wof:name":"Jangles the Magic Clown",
    "wof:placetype":"venue"
},
  "geometry": {"coordinates":[-82.90808868409999,42.2987785339],"type":"Point"}
}