{
  "type": "Feature",
  "properties": {
    "addr:full":"209 Patrick St Springside SK S0A 3V0",
    "addr:housenumber":"209",
    "addr:postcode":"s0a 3v0",
    "addr:street":"Patrick St",
    "iso:country":"CA",
    "sg:address":"209 Patrick St",
    "sg:city":"Springside",
    "sg:classifiers":[
        {
            "category":"Organizations",
            "subcategory":"Religious Organization",
            "type":"Services"
        }
    ],
    "sg:phone":"+1 306 792 2102",
    "sg:postcode":"S0A 3V0",
    "sg:province":"SK",
    "sg:tags":[
        "church"
    ],
    "wof:name":"Springside Baptist Church",
    "wof:placetype":"venue"
},
  "geometry": {"coordinates":[-102.74578099999999,51.345161],"type":"Point"}
}