{
  "type": "Feature",
  "properties": {
    "addr:full":"30 Mcnaughton Ave Wallaceburg ON N8A 1R9",
    "addr:housenumber":"30",
    "addr:postcode":"n8a 1r9",
    "addr:street":"Mcnaughton Ave",
    "iso:country":"CA",
    "sg:address":"30 Mcnaughton Ave",
    "sg:city":"Wallaceburg",
    "sg:classifiers":[
        {
            "category":"Health Services",
            "subcategory":"Doctor",
            "type":"Services"
        }
    ],
    "sg:phone":"+1 519 627 1497",
    "sg:postcode":"N8A 1R9",
    "sg:province":"ON",
    "sg:tags":[
        "physician",
        "surgeon"
    ],
    "wof:name":"Wallaceburg Community Medical",
    "wof:placetype":"venue"
},
  "geometry": {"coordinates":[-82.3852310181,42.5884780884],"type":"Point"}
}