{
  "type": "Feature",
  "properties": {
    "addr:full":"Saint-Come-Liniere QC G0M 1J0",
    "addr:postcode":"g0m 1j0",
    "iso:country":"CA",
    "sg:city":"Saint-Come-Liniere",
    "sg:classifiers":[
        {
            "category":"Manufacturing",
            "subcategory":"Building Materials",
            "type":"Manufacturing & Wholesale Goods"
        }
    ],
    "sg:phone":"+1 418 685 2222",
    "sg:postcode":"G0M 1J0",
    "sg:province":"QC",
    "sg:tags":[
        "lumber"
    ],
    "wof:name":"Inter-Foret 2222 Inc",
    "wof:placetype":"venue"
},
  "geometry": {"coordinates":[-70.514931,46.051098],"type":"Point"}
}