{
  "type": "Feature",
  "properties": {
    "addr:full":"39 St. Clare Ave Stephenville NL A2N 1N8",
    "addr:housenumber":"39",
    "addr:postcode":"a2n 1n8",
    "addr:street":"St. Clare Ave",
    "iso:country":"CA",
    "sg:address":"39 St. Clare Ave",
    "sg:city":"Stephenville",
    "sg:classifiers":[
        {
            "category":"Social Services",
            "type":"Services"
        }
    ],
    "sg:phone":"+1 709 643 4010",
    "sg:postcode":"A2N 1N8",
    "sg:province":"NL",
    "sg:tags":[
        "organization",
        "welfare"
    ],
    "wof:name":"Stephenville Community Food",
    "wof:placetype":"venue"
},
  "geometry": {"coordinates":[-58.584316,48.550854],"type":"Point"}
}