{
  "type": "Feature",
  "properties": {
    "iso:country":"CA",
    "sg:address":"9845 Carleton St",
    "sg:city":"Chilliwack",
    "sg:classifiers":[
        {
            "category":"Organizations",
            "subcategory":"Religious Organization",
            "type":"Services"
        }
    ],
    "sg:phone":"+1 604 792 7811",
    "sg:postcode":"V2P 6E4",
    "sg:province":"BC",
    "sg:tags":[
        "church"
    ],
    "wof:name":"Community of Christ",
    "wof:placetype":"venue"
},
  "geometry": {"coordinates":[-121.928634644,49.1801795959],"type":"Point"}
}