{
  "type": "Feature",
  "properties": {
    "addr:full":"657 139 Rte Roxton Pond QC J0E 1Z0",
    "addr:housenumber":"139",
    "addr:postcode":"j0e 1z0",
    "addr:street":"Rte Roxton Pond",
    "iso:country":"CA",
    "sg:address":"657 139 Rte",
    "sg:city":"Roxton Pond",
    "sg:classifiers":[
        {
            "category":"Building & Trades",
            "subcategory":"Plumbing",
            "type":"Services"
        }
    ],
    "sg:phone":"+1 450 372 7434",
    "sg:postcode":"J0E 1Z0",
    "sg:province":"QC",
    "sg:tags":[
        "disposal",
        "system",
        "sewage",
        "septic"
    ],
    "wof:name":"Fortin Gerard",
    "wof:placetype":"venue"
},
  "geometry": {"coordinates":[-72.662941,45.473156],"type":"Point"}
}