{
  "type": "Feature",
  "properties": {
    "addr:full":"Surrey BC V3W 3E8",
    "addr:postcode":"v3w 3e8",
    "iso:country":"CA",
    "sg:city":"Surrey",
    "sg:classifiers":[
        {
            "category":"Retail",
            "subcategory":"Auto Repair",
            "type":"Services"
        }
    ],
    "sg:phone":"+1 604 599 1223",
    "sg:postcode":"V3W 3E8",
    "sg:province":"BC",
    "sg:tags":[
        "repairing",
        "automobile"
    ],
    "wof:name":"Darcy's Auto Svc Ltd",
    "wof:placetype":"venue"
},
  "geometry": {"coordinates":[-122.876235962,49.1522026062],"type":"Point"}
}