{
  "type": "Feature",
  "properties": {
    "addr:full":"101 Rue Sainte-Marguerite Sainte-Anne-DE-LA-Perade QC G0X 2J0",
    "addr:housenumber":"101",
    "addr:postcode":"g0x 2j0",
    "addr:street":"Rue Sainte-Marguerite Sainte-Anne-De-La-Perade",
    "iso:country":"CA",
    "sg:address":"101 Rue Sainte-Marguerite",
    "sg:city":"Sainte-Anne-DE-LA-Perade",
    "sg:classifiers":[
        {
            "category":"Personal",
            "subcategory":"Beauty Salon",
            "type":"Services"
        }
    ],
    "sg:phone":"+1 418 325 2929",
    "sg:postcode":"G0X 2J0",
    "sg:province":"QC",
    "wof:name":"Salon Coiffure R Lavallee",
    "wof:placetype":"venue"
},
  "geometry": {"coordinates":[-72.2046890259,46.569026947],"type":"Point"}
}