{
  "type": "Feature",
  "properties": {
    "addr:full":"4440 Baseline Rd Sutton West ON L0E 1R0",
    "addr:housenumber":"4440",
    "addr:postcode":"l0e 1r0",
    "addr:street":"Baseline Rd",
    "iso:country":"CA",
    "sg:address":"4440 Baseline Rd",
    "sg:city":"Sutton West",
    "sg:classifiers":[
        {
            "category":"Home & Garden",
            "subcategory":"Building Materials",
            "type":"Retail Goods"
        }
    ],
    "sg:phone":"+1 905 722 3259",
    "sg:postcode":"L0E 1R0",
    "sg:province":"ON",
    "sg:tags":[
        "mixed",
        "concrete",
        "common",
        "face"
    ],
    "wof:name":"Canada Building Materials CO",
    "wof:placetype":"venue"
},
  "geometry": {"coordinates":[-79.3863525391,44.2980384827],"type":"Point"}
}