{
  "type": "Feature",
  "properties": {
    "addr:full":"1348 Rue Beaubien E Montreal QC H2G 1K8",
    "addr:housenumber":"1348",
    "addr:postcode":"h2g 1k8",
    "addr:street":"Rue Beaubien E",
    "iso:country":"CA",
    "sg:address":"1348 Rue Beaubien E",
    "sg:city":"Montreal",
    "sg:classifiers":[
        {
            "category":"Restaurant",
            "type":"Food & Drink"
        }
    ],
    "sg:phone":"+1 514 272 3857",
    "sg:postcode":"H2G 1K8",
    "sg:province":"QC",
    "wof:name":"Restaurant Chez Billy",
    "wof:placetype":"venue"
},
  "geometry": {"coordinates":[-73.5988998413,45.5405654907],"type":"Point"}
}