{
  "type": "Feature",
  "properties": {
    "addr:full":"9066 51 Ave NW Edmonton AB T6E 5X4",
    "addr:housenumber":"9066",
    "addr:postcode":"t6e 5x4",
    "addr:street":"51 Ave Nw",
    "iso:country":"CA",
    "sg:address":"9066 51 Ave NW",
    "sg:city":"Edmonton",
    "sg:classifiers":[
        {
            "category":"Home & Garden",
            "subcategory":"Household Appliances",
            "type":"Retail Goods"
        }
    ],
    "sg:phone":"+1 780 482 3474",
    "sg:postcode":"T6E 5X4",
    "sg:province":"AB",
    "sg:tags":[
        "cleaners",
        "parts",
        "vacuum"
    ],
    "wof:name":"Jiffy Vacuum",
    "wof:placetype":"venue"
},
  "geometry": {"coordinates":[-113.465721,53.4883],"type":"Point"}
}