{
  "type": "Feature",
  "properties": {
    "iso:country":"CA",
    "sg:address":"11 Dogwood Cres",
    "sg:city":"Yorkton",
    "sg:classifiers":[
        {
            "category":"Building & Trades",
            "subcategory":"Electrical",
            "type":"Services"
        }
    ],
    "sg:phone":"+1 306 782 5592",
    "sg:postcode":"S3N 2M6",
    "sg:province":"SK",
    "sg:tags":[
        "electric",
        "contractor"
    ],
    "wof:name":"R H Electric",
    "wof:placetype":"venue"
},
  "geometry": {"coordinates":[-102.488250732,51.2049751282],"type":"Point"}
}