{
  "type": "Feature",
  "properties": {
    "addr:full":"6179 Main St Stouffville ON L4A 4H8",
    "addr:housenumber":"6179",
    "addr:postcode":"l4a 4h8",
    "addr:street":"Main St",
    "iso:country":"CA",
    "sg:address":"6179 Main St",
    "sg:city":"Stouffville",
    "sg:classifiers":[
        {
            "category":"Health Services",
            "subcategory":"Doctor",
            "type":"Services"
        }
    ],
    "sg:phone":"+1 905 640 2300",
    "sg:postcode":"L4A 4H8",
    "sg:province":"ON",
    "sg:tags":[
        "physician",
        "surgeon"
    ],
    "wof:name":"Izso, Peter MD",
    "wof:placetype":"venue"
},
  "geometry": {"coordinates":[-79.2509,43.970306],"type":"Point"}
}