{
  "type": "Feature",
  "properties": {
    "iso:country":"CA",
    "sg:address":"540 Piercey Rd",
    "sg:city":"Bolton",
    "sg:classifiers":[
        {
            "category":"Manufacturing",
            "subcategory":"Metals",
            "type":"Manufacturing & Wholesale Goods"
        }
    ],
    "sg:phone":"+1 905 857 3337",
    "sg:postcode":"L7E 5B4",
    "sg:province":"ON",
    "sg:tags":[
        "gas",
        "burner"
    ],
    "wof:name":"North American Mfg",
    "wof:placetype":"venue"
},
  "geometry": {"coordinates":[-79.72821044920001,43.8648757935],"type":"Point"}
}