{
  "type": "Feature",
  "properties": {
    "addr:full":"348 King George Hwy Miramichi NB E1V 1K9",
    "addr:housenumber":"348",
    "addr:postcode":"e1v 1k9",
    "addr:street":"King George Hwy",
    "iso:country":"CA",
    "sg:address":"348 King George Hwy",
    "sg:city":"Miramichi",
    "sg:classifiers":[
        {
            "category":"Wholesale",
            "subcategory":"Auto Parts",
            "type":"Manufacturing & Wholesale Goods"
        }
    ],
    "sg:phone":"+1 506 622 5388",
    "sg:postcode":"E1V 1K9",
    "sg:province":"NB",
    "sg:tags":[
        "glass",
        "rebuilt",
        "automobile"
    ],
    "wof:name":"Clearsight Auto Glass",
    "wof:placetype":"venue"
},
  "geometry": {"coordinates":[-65.5775299072,46.9865455627],"type":"Point"}
}