{
  "type": "Feature",
  "properties": {
    "addr:full":"Hwy 5 & Hwy 10 W Dauphin MB R7N 2T9",
    "addr:postcode":"r7n 2t9",
    "addr:street":"Hwy 5 & Hwy 10 W",
    "iso:country":"CA",
    "sg:address":"Hwy 5 & Hwy 10 W",
    "sg:city":"Dauphin",
    "sg:classifiers":[
        {
            "category":"Wholesale",
            "subcategory":"Machinery & Supplies",
            "type":"Manufacturing & Wholesale Goods"
        }
    ],
    "sg:phone":"+1 204 638 6443",
    "sg:postcode":"R7N 2T9",
    "sg:province":"MB",
    "sg:tags":[
        "farm",
        "equipment"
    ],
    "wof:name":"Sydor Farm Equipment",
    "wof:placetype":"venue"
},
  "geometry": {"coordinates":[-100.063271,51.134918],"type":"Point"}
}