{
  "type": "Feature",
  "properties": {
    "addr:full":"Toronto ON M5V 1M7",
    "addr:postcode":"m5v 1m7",
    "iso:country":"CA",
    "sg:city":"Toronto",
    "sg:classifiers":[
        {
            "category":"Wholesale",
            "subcategory":"Durable Goods & Equipment",
            "type":"Manufacturing & Wholesale Goods"
        }
    ],
    "sg:phone":"+1 416 504 3113",
    "sg:postcode":"M5V 1M7",
    "sg:province":"ON",
    "sg:tags":[
        "importer"
    ],
    "wof:name":"Fruitrade International Inc",
    "wof:placetype":"venue"
},
  "geometry": {"coordinates":[-79.401123,43.644363],"type":"Point"}
}