{
  "type": "Feature",
  "properties": {
    "addr:full":"3065 Ridgeway Dr #38 Mississauga ON L5L 5M6",
    "addr:housenumber":"3065",
    "addr:postcode":"l5l 5m6",
    "addr:street":"Ridgeway Dr # 38",
    "iso:country":"CA",
    "sg:address":"3065 Ridgeway Dr #38",
    "sg:city":"Mississauga",
    "sg:classifiers":[
        {
            "category":"Real Estate",
            "subcategory":"Real Estate Agent",
            "type":"Services"
        }
    ],
    "sg:phone":"+1 905 828 2520",
    "sg:postcode":"L5L 5M6",
    "sg:province":"ON",
    "sg:tags":[
        "appraiser"
    ],
    "wof:name":"Mississauga Appraisal Svc Inc",
    "wof:placetype":"venue"
},
  "geometry": {"coordinates":[-79.68907900000001,43.518631],"type":"Point"}
}