{
  "type": "Feature",
  "properties": {
    "addr:full":"Windsor ON N9A 7A2",
    "addr:postcode":"n9a 7a2",
    "iso:country":"CA",
    "sg:city":"Windsor",
    "sg:classifiers":[
        {
            "category":"Food & Beverages",
            "subcategory":"Bakery",
            "type":"Retail Goods"
        }
    ],
    "sg:phone":"+1 519 973 1942",
    "sg:postcode":"N9A 7A2",
    "sg:province":"ON",
    "sg:tags":[
        "baker"
    ],
    "wof:name":"Crumbles Muffins Inc",
    "wof:placetype":"venue"
},
  "geometry": {"coordinates":[-83.0398864746,42.3161354065],"type":"Point"}
}