{
  "type": "Feature",
  "properties": {
    "iso:country":"CA",
    "sg:address":"1738 Water St",
    "sg:city":"Miramichi",
    "sg:classifiers":[
        {
            "category":"Shopping",
            "subcategory":"Music",
            "type":"Retail Goods"
        }
    ],
    "sg:phone":"+1 506 773 8010",
    "sg:postcode":"E1N 1B5",
    "sg:province":"NB",
    "sg:tags":[
        "compact",
        "record",
        "disc",
        "tape"
    ],
    "wof:name":"Saltwater Sounds",
    "wof:placetype":"venue"
},
  "geometry": {"coordinates":[-65.46997833250001,47.0299606323],"type":"Point"}
}