{
  "type": "Feature",
  "properties": {
    "iso:country":"CA",
    "sg:city":"Richmond",
    "sg:classifiers":[
        {
            "category":"Professional",
            "subcategory":"Accounting & Tax Preparation",
            "type":"Services"
        }
    ],
    "sg:phone":"+1 604 273 6622",
    "sg:postcode":"V6X 3Z9",
    "sg:province":"BC",
    "sg:tags":[
        "accountant"
    ],
    "wof:name":"Farria Law & CO",
    "wof:placetype":"venue"
},
  "geometry": {"coordinates":[-123.128303528,49.1851272583],"type":"Point"}
}