{
  "type": "Feature",
  "properties": {
    "addr:full":"310 Ridge Rd N Ridgeway ON L0S 1N0",
    "addr:housenumber":"310",
    "addr:postcode":"l0s 1n0",
    "addr:street":"Ridge Rd N",
    "iso:country":"CA",
    "sg:address":"310 Ridge Rd N",
    "sg:city":"Ridgeway",
    "sg:classifiers":[
        {
            "category":"Banks & Credit Unions",
            "subcategory":"Bank",
            "type":"Services"
        }
    ],
    "sg:phone":"+1 905 894 1030",
    "sg:postcode":"L0S 1N0",
    "sg:province":"ON",
    "wof:name":"Cibc",
    "wof:placetype":"venue"
},
  "geometry": {"coordinates":[-79.0517501831,42.8832702637],"type":"Point"}
}