{
  "type": "Feature",
  "properties": {
    "iso:country":"CA",
    "sg:address":"4300 Steeles Ave E",
    "sg:city":"Markham",
    "sg:classifiers":[
        {
            "category":"Shopping",
            "subcategory":"Jewelry",
            "type":"Retail Goods"
        }
    ],
    "sg:phone":"+1 905 944 0883",
    "sg:postcode":"L3R 0Y5",
    "sg:province":"ON",
    "sg:tags":[
        "jeweler"
    ],
    "wof:name":"Sapphire Jewellery Ltd",
    "wof:placetype":"venue"
},
  "geometry": {"coordinates":[-79.3067321777,43.8238983154],"type":"Point"}
}