{
  "type": "Feature",
  "properties": {
    "addr:full":"919 Waterton Ave Pincher Creek AB T0K 1W0",
    "addr:housenumber":"919",
    "addr:postcode":"t0k 1w0",
    "addr:street":"Waterton Ave",
    "iso:country":"CA",
    "sg:address":"919 Waterton Ave",
    "sg:city":"Pincher Creek",
    "sg:classifiers":[
        {
            "category":"Travel",
            "subcategory":"Hotels & Motels",
            "type":"Entertainment"
        }
    ],
    "sg:phone":"+1 403 627 5000",
    "sg:postcode":"T0K 1W0",
    "sg:province":"AB",
    "wof:name":"Heritage Inn",
    "wof:placetype":"venue"
},
  "geometry": {"coordinates":[-113.936447,49.482136],"type":"Point"}
}