{
  "type": "Feature",
  "properties": {
    "addr:full":"173 Simcoe St N Oshawa ON L1G 4S8",
    "addr:housenumber":"173",
    "addr:postcode":"l1g 4s8",
    "addr:street":"Simcoe St N",
    "iso:country":"CA",
    "sg:address":"173 Simcoe St N",
    "sg:city":"Oshawa",
    "sg:classifiers":[
        {
            "category":"Social Services",
            "type":"Services"
        }
    ],
    "sg:phone":"+1 905 404 0265",
    "sg:postcode":"L1G 4S8",
    "sg:province":"ON",
    "sg:tags":[
        "counselor",
        "marriage",
        "family"
    ],
    "wof:name":"Campbell, Carrol",
    "wof:placetype":"venue"
},
  "geometry": {"coordinates":[-78.865639,43.902309],"type":"Point"}
}