{
  "type": "Feature",
  "properties": {
    "addr:full":"3464 89 Hwy Cookstown ON L0L 1L0",
    "addr:housenumber":"3464",
    "addr:postcode":"l0l 1l0",
    "addr:street":"89 Hwy",
    "iso:country":"CA",
    "sg:address":"3464 89 Hwy",
    "sg:city":"Cookstown",
    "sg:classifiers":[
        {
            "category":"Restaurant",
            "type":"Food & Drink"
        }
    ],
    "sg:phone":"+1 705 458 9543",
    "sg:postcode":"L0L 1L0",
    "sg:province":"ON",
    "wof:name":"Mc Donald's",
    "wof:placetype":"venue"
},
  "geometry": {"coordinates":[-79.659904,44.199326],"type":"Point"}
}