{
  "type": "Feature",
  "properties": {
    "iso:country":"CA",
    "sg:address":"1006 Boul Quevillon",
    "sg:city":"Lebel-Sur-Quevillon",
    "sg:classifiers":[
        {
            "category":"Autos & Motor Vehicles",
            "subcategory":"Automobile Sales",
            "type":"Retail Goods"
        }
    ],
    "sg:phone":"+1 819 755 4848",
    "sg:postcode":"J0Y 1X0",
    "sg:province":"QC",
    "sg:tags":[
        "car",
        "dealer"
    ],
    "wof:name":"Senex Pontiac Buick",
    "wof:placetype":"venue"
},
  "geometry": {"coordinates":[-76.9813537598,49.0493850708],"type":"Point"}
}