{
  "type": "Feature",
  "properties": {
    "addr:full":"452 Milltown Blvd St Stephen NB E3L 1K1",
    "addr:housenumber":"452",
    "addr:postcode":"e3l 1k1",
    "addr:street":"Milltown Blvd",
    "iso:country":"CA",
    "sg:address":"452 Milltown Blvd",
    "sg:city":"St Stephen",
    "sg:classifiers":[
        {
            "category":"Organizations",
            "subcategory":"Religious Organization",
            "type":"Services"
        }
    ],
    "sg:phone":"+1 506 466 5232",
    "sg:postcode":"E3L 1K1",
    "sg:province":"NB",
    "sg:tags":[
        "church"
    ],
    "wof:name":"Milltown United Church",
    "wof:placetype":"venue"
},
  "geometry": {"coordinates":[-67.2966,45.173145],"type":"Point"}
}