{
  "type": "Feature",
  "properties": {
    "addr:full":"213 Dundas St Woodstock ON N4S 1A8",
    "addr:housenumber":"213",
    "addr:postcode":"n4s 1a8",
    "addr:street":"Dundas St",
    "iso:country":"CA",
    "sg:address":"213 Dundas St",
    "sg:city":"Woodstock",
    "sg:classifiers":[
        {
            "category":"Retail",
            "subcategory":"Laundry & Dry Cleaning",
            "type":"Services"
        }
    ],
    "sg:phone":"+1 519 539 1208",
    "sg:postcode":"N4S 1A8",
    "sg:province":"ON",
    "sg:tags":[
        "cleaners"
    ],
    "wof:name":"City Wide Cleaners",
    "wof:placetype":"venue"
},
  "geometry": {"coordinates":[-80.76879099999999,43.128513],"type":"Point"}
}