{
  "type": "Feature",
  "properties": {
    "addr:full":"402 Thorne Dr Millbrook ON L0A 1G0",
    "addr:housenumber":"402",
    "addr:postcode":"l0a 1g0",
    "addr:street":"Thorne Dr",
    "iso:country":"CA",
    "sg:address":"402 Thorne Dr",
    "sg:city":"Millbrook",
    "sg:classifiers":[
        {
            "category":"Wholesale",
            "subcategory":"Construction Materials",
            "type":"Manufacturing & Wholesale Goods"
        }
    ],
    "sg:phone":"+1 705 875 0048",
    "sg:postcode":"L0A 1G0",
    "sg:province":"ON",
    "sg:tags":[
        "fence"
    ],
    "wof:name":"Floyd's Sales & Svc",
    "wof:placetype":"venue"
},
  "geometry": {"coordinates":[-78.44803619379999,44.1506500244],"type":"Point"}
}