{
  "type": "Feature",
  "properties": {
    "addr:full":"295 Commercial St Glace Bay NS B1A 3C5",
    "addr:housenumber":"295",
    "addr:postcode":"b1a 3c5",
    "addr:street":"Commercial St",
    "iso:country":"CA",
    "sg:address":"295 Commercial St",
    "sg:city":"Glace Bay",
    "sg:classifiers":[
        {
            "category":"Restaurant",
            "type":"Food & Drink"
        }
    ],
    "sg:phone":"+1 902 842 5050",
    "sg:postcode":"B1A 3C5",
    "sg:province":"NS",
    "wof:name":"Krisley's Diner",
    "wof:placetype":"venue"
},
  "geometry": {"coordinates":[-59.955029,46.194099],"type":"Point"}
}