{
  "type": "Feature",
  "properties": {
    "iso:country":"CA",
    "sg:city":"Toronto",
    "sg:classifiers":[
        {
            "category":"Travel",
            "subcategory":"Travel Agent",
            "type":"Entertainment"
        }
    ],
    "sg:phone":"+1 416 922 3443",
    "sg:postcode":"M4W 1J5",
    "sg:province":"ON",
    "sg:tags":[
        "agency",
        "bureau"
    ],
    "wof:name":"Ernie King Travel",
    "wof:placetype":"venue"
},
  "geometry": {"coordinates":[-79.3874969482,43.6711730957],"type":"Point"}
}