{
  "type": "Feature",
  "properties": {
    "addr:full":"58 Rue Eaton Kirkland QC H9H 3S3",
    "addr:housenumber":"58",
    "addr:postcode":"h9h 3s3",
    "addr:street":"Rue Eaton",
    "iso:country":"CA",
    "sg:address":"58 Rue Eaton",
    "sg:city":"Kirkland",
    "sg:classifiers":[
        {
            "category":"Organizations",
            "subcategory":"Religious Organization",
            "type":"Services"
        }
    ],
    "sg:phone":"+1 514 694 3638",
    "sg:postcode":"H9H 3S3",
    "sg:province":"QC",
    "sg:tags":[
        "church"
    ],
    "wof:name":"Eglise DE Jesus Christ",
    "wof:placetype":"venue"
},
  "geometry": {"coordinates":[-73.84279600000001,45.449341],"type":"Point"}
}