{
  "type": "Feature",
  "properties": {
    "addr:full":"19 Victoria Cres Brampton ON L6T 1E2",
    "addr:housenumber":"19",
    "addr:postcode":"l6t 1e2",
    "addr:street":"Victoria Cres",
    "iso:country":"CA",
    "sg:address":"19 Victoria Cres",
    "sg:city":"Brampton",
    "sg:classifiers":[
        {
            "category":"Manufacturing",
            "subcategory":"Metals",
            "type":"Manufacturing & Wholesale Goods"
        }
    ],
    "sg:phone":"+1 905 792 2828",
    "sg:postcode":"L6T 1E2",
    "sg:province":"ON",
    "sg:tags":[
        "brass",
        "product"
    ],
    "wof:name":"Brascon Architectural Products",
    "wof:placetype":"venue"
},
  "geometry": {"coordinates":[-79.76721999999999,43.691532],"type":"Point"}
}