{
  "type": "Feature",
  "properties": {
    "addr:full":"2500 Campeau Dr Kanata ON K2K 2W3",
    "addr:housenumber":"2500",
    "addr:postcode":"k2k 2w3",
    "addr:street":"Campeau Dr",
    "iso:country":"CA",
    "sg:address":"2500 Campeau Dr",
    "sg:city":"Kanata",
    "sg:classifiers":[
        {
            "category":"Shopping",
            "type":"Retail Goods"
        }
    ],
    "sg:phone":"+1 613 724 4122",
    "sg:postcode":"K2K 2W3",
    "sg:province":"ON",
    "sg:tags":[
        "government",
        "art",
        "dealer",
        "gallery"
    ],
    "wof:name":"Kanata Civic Art Gallery",
    "wof:placetype":"venue"
},
  "geometry": {"coordinates":[-75.895614624,45.3201751709],"type":"Point"}
}