{
  "type": "Feature",
  "properties": {
    "addr:full":"Belleville ON K8N 4Z5",
    "addr:postcode":"k8n 4z5",
    "iso:country":"CA",
    "sg:city":"Belleville",
    "sg:classifiers":[
        {
            "category":"Professional",
            "subcategory":"Computer Services",
            "type":"Services"
        }
    ],
    "sg:phone":"+1 613 969 7093",
    "sg:postcode":"K8N 4Z5",
    "sg:province":"ON",
    "sg:tags":[
        "communication",
        "radio",
        "system"
    ],
    "wof:name":"Quinte Communications Ltd",
    "wof:placetype":"venue"
},
  "geometry": {"coordinates":[-77.396339,44.201347],"type":"Point"}
}