{
  "type": "Feature",
  "properties": {
    "addr:full":"540 Alpha St Victoria BC V8Z 1B2",
    "addr:housenumber":"540",
    "addr:postcode":"v8z 1b2",
    "addr:street":"Alpha St",
    "iso:country":"CA",
    "sg:address":"540 Alpha St",
    "sg:city":"Victoria",
    "sg:classifiers":[
        {
            "category":"Retail",
            "subcategory":"Repair Shop",
            "type":"Services"
        }
    ],
    "sg:phone":"+1 250 385 8683",
    "sg:postcode":"V8Z 1B2",
    "sg:province":"BC",
    "sg:tags":[
        "ironwork"
    ],
    "wof:name":"Fantasy Metal Crafting",
    "wof:placetype":"venue"
},
  "geometry": {"coordinates":[-123.37580871599999,48.4470367432],"type":"Point"}
}