{
  "type": "Feature",
  "properties": {
    "addr:full":"503 14th Ave S Cranbrook BC V1C 2X9",
    "addr:housenumber":"503",
    "addr:postcode":"bc v1c 2x9",
    "addr:street":"14Th Ave S",
    "iso:country":"CA",
    "sg:address":"503 14th Ave S",
    "sg:city":"Cranbrook",
    "sg:classifiers":[
        {
            "category":"Building & Trades",
            "subcategory":"Construction",
            "type":"Services"
        }
    ],
    "sg:phone":"+1 250 426 3835",
    "sg:postcode":"V1C 2X9",
    "sg:province":"BC",
    "sg:tags":[
        "general",
        "road",
        "contractor"
    ],
    "wof:name":"Hebditch Holdings Ltd",
    "wof:placetype":"venue"
},
  "geometry": {"coordinates":[-115.762313843,49.5028190613],"type":"Point"}
}