{
  "type": "Feature",
  "properties": {
    "addr:full":"45 7th Ave S Cranbrook BC V1C 2J2",
    "addr:housenumber":"45",
    "addr:postcode":"bc v1c 2j2",
    "addr:street":"7Th Ave S",
    "iso:country":"CA",
    "sg:address":"45 7th Ave S",
    "sg:city":"Cranbrook",
    "sg:classifiers":[
        {
            "category":"Home & Garden",
            "subcategory":"Building Materials",
            "type":"Retail Goods"
        }
    ],
    "sg:phone":"+1 250 426 4448",
    "sg:postcode":"V1C 2J2",
    "sg:province":"BC",
    "sg:tags":[
        "door"
    ],
    "wof:name":"Kootenay Overhead Door & Glass",
    "wof:placetype":"venue"
},
  "geometry": {"coordinates":[-115.771972656,49.511013031],"type":"Point"}
}