{
  "type": "Feature",
  "properties": {
    "addr:full":"407 5th Rg Sainte-Cecile-DE-Milton QC J0E 2C0",
    "addr:housenumber":"407",
    "addr:postcode":"j0e 2c0",
    "addr:street":"5Th Rg Sainte-Cecile-De-Milton",
    "iso:country":"CA",
    "sg:address":"407 5th Rg",
    "sg:city":"Sainte-Cecile-DE-Milton",
    "sg:classifiers":[
        {
            "category":"Wholesale",
            "subcategory":"Electrical",
            "type":"Manufacturing & Wholesale Goods"
        }
    ],
    "sg:phone":"+1 450 378 6465",
    "sg:postcode":"J0E 2C0",
    "sg:province":"QC",
    "sg:tags":[
        "control",
        "security",
        "greenhouse"
    ],
    "wof:name":"Hol-Ser Inc",
    "wof:placetype":"venue"
},
  "geometry": {"coordinates":[-72.75926200000001,45.480148],"type":"Point"}
}