{
  "type": "Feature",
  "properties": {
    "addr:full":"104 1st Ave NW Dauphin MB R7N 1G9",
    "addr:housenumber":"104",
    "addr:postcode":"dauphin;r7n 1g9",
    "addr:street":"1St Ave Nw",
    "iso:country":"CA",
    "sg:address":"104 1st Ave NW",
    "sg:city":"Dauphin",
    "sg:classifiers":[
        {
            "category":"Shopping",
            "type":"Retail Goods"
        }
    ],
    "sg:phone":"+1 204 638 6231",
    "sg:postcode":"R7N 1G9",
    "sg:province":"MB",
    "sg:tags":[
        "art",
        "gallery",
        "dealer"
    ],
    "wof:name":"Dauphin Allied Arts Council",
    "wof:placetype":"venue"
},
  "geometry": {"coordinates":[-100.05194899999999,51.150795],"type":"Point"}
}