{
  "type": "Feature",
  "properties": {
    "addr:full":"718 Ch D'Aylmer Aylmer QC J9H 5T2",
    "addr:housenumber":"718",
    "addr:postcode":"j9h 5t2",
    "addr:street":"Ch D'Aylmer",
    "iso:country":"CA",
    "sg:address":"718 Ch D'Aylmer",
    "sg:city":"Aylmer",
    "sg:classifiers":[
        {
            "category":"Banks & Credit Unions",
            "subcategory":"Investment Brokerage",
            "type":"Services"
        }
    ],
    "sg:phone":"+1 819 682 4646",
    "sg:postcode":"J9H 5T2",
    "sg:province":"QC",
    "sg:tags":[
        "consultant",
        "planning",
        "financial"
    ],
    "wof:name":"Libertas International",
    "wof:placetype":"venue"
},
  "geometry": {"coordinates":[-75.824608,45.396294],"type":"Point"}
}