{
  "type": "Feature",
  "properties": {
    "addr:full":"795 Boul Everard H Daigle Grand-Sault/Grand Falls NB E3Z 3C7",
    "addr:housenumber":"795",
    "addr:postcode":"e3z 3c7",
    "addr:street":"Boul Everard H Daigle",
    "iso:country":"CA",
    "sg:address":"795 Boul Everard H Daigle",
    "sg:city":"Grand-Sault/Grand Falls",
    "sg:classifiers":[
        {
            "category":"Autos & Motor Vehicles",
            "subcategory":"Automobile Sales",
            "type":"Retail Goods"
        }
    ],
    "sg:phone":"+1 506 473 5000",
    "sg:postcode":"E3Z 3C7",
    "sg:province":"NB",
    "sg:tags":[
        "car",
        "dealer"
    ],
    "wof:name":"Rendez-Vous Chrysler Jeep",
    "wof:placetype":"venue"
},
  "geometry": {"coordinates":[-67.76216100000001,47.044388],"type":"Point"}
}