{
  "type": "Feature",
  "properties": {
    "addr:full":"3235 Rue Ontario E Montreal QC H1W 1P3",
    "addr:housenumber":"3235",
    "addr:postcode":"h1w 1p3",
    "addr:street":"Rue Ontario E",
    "iso:country":"CA",
    "sg:address":"3235 Rue Ontario E",
    "sg:city":"Montreal",
    "sg:classifiers":[
        {
            "category":"Shopping",
            "subcategory":"Bicycles & Sporting Goods",
            "type":"Retail Goods"
        }
    ],
    "sg:phone":"+1 514 525 2737",
    "sg:postcode":"H1W 1P3",
    "sg:province":"QC",
    "wof:name":"Gene Velo Sport",
    "wof:placetype":"venue"
},
  "geometry": {"coordinates":[-73.54727200000001,45.541534],"type":"Point"}
}