{
  "type": "Feature",
  "properties": {
    "addr:full":"3400 Ch Des Quatre-Bourgeois Sainte-Foy QC G1W 2L3",
    "addr:postcode":"3400;g1w 2l3",
    "addr:street":"Ch Des Quatre-Bourgeois",
    "iso:country":"CA",
    "sg:address":"3400 Ch Des Quatre-Bourgeois",
    "sg:city":"Sainte-Foy",
    "sg:classifiers":[
        {
            "category":"Shopping",
            "subcategory":"Tobacco",
            "type":"Retail Goods"
        }
    ],
    "sg:phone":"+1 418 651 6252",
    "sg:postcode":"G1W 2L3",
    "sg:province":"QC",
    "sg:tags":[
        "cigarette",
        "cigar",
        "dealer"
    ],
    "wof:name":"Tabagie Naviles Enr",
    "wof:placetype":"venue"
},
  "geometry": {"coordinates":[-71.3164901733,46.7634353638],"type":"Point"}
}