{
  "type": "Feature",
  "properties": {
    "addr:full":"141 Garrison Rd Fort Erie ON L2A 1M3",
    "addr:housenumber":"141",
    "addr:postcode":"l2a 1m3",
    "addr:street":"Garrison Rd",
    "iso:country":"CA",
    "sg:address":"141 Garrison Rd",
    "sg:city":"Fort Erie",
    "sg:classifiers":[
        {
            "category":"Food & Beverages",
            "subcategory":"Bakery",
            "type":"Retail Goods"
        }
    ],
    "sg:phone":"+1 905 871 1743",
    "sg:postcode":"L2A 1M3",
    "sg:province":"ON",
    "sg:tags":[
        "tea",
        "coffee",
        "doughnut"
    ],
    "wof:name":"Tim Hortons",
    "wof:placetype":"venue"
},
  "geometry": {"coordinates":[-78.917923,42.9058],"type":"Point"}
}