{
  "type": "Feature",
  "properties": {
    "addr:full":"375 Rte 132 RR 1 New Richmond QC G0C 2B0",
    "addr:housenumber":"375;1",
    "addr:postcode":"g0c 2b0",
    "addr:street":"Rte 132 Rr",
    "iso:country":"CA",
    "sg:address":"375 Rte 132 RR 1",
    "sg:city":"New Richmond",
    "sg:classifiers":[
        {
            "category":"Autos & Motor Vehicles",
            "subcategory":"Fuel & Gas Station",
            "type":"Retail Goods"
        }
    ],
    "sg:phone":"+1 418 392 6655",
    "sg:postcode":"G0C 2B0",
    "sg:province":"QC",
    "sg:tags":[
        "oil"
    ],
    "wof:name":"Depanneur Shell",
    "wof:placetype":"venue"
},
  "geometry": {"coordinates":[-65.8950881958,48.2077064514],"type":"Point"}
}