{
  "type": "Feature",
  "properties": {
    "addr:full":"2949 101 St NW Edmonton AB T6N 1A7",
    "addr:housenumber":"2949",
    "addr:postcode":"t6n 1a7",
    "addr:street":"101 St Nw",
    "iso:country":"CA",
    "sg:address":"2949 101 St NW",
    "sg:city":"Edmonton",
    "sg:classifiers":[
        {
            "category":"Building & Trades",
            "subcategory":"Construction",
            "type":"Services"
        }
    ],
    "sg:phone":"+1 780 461 3461",
    "sg:postcode":"T6N 1A7",
    "sg:province":"AB",
    "sg:tags":[
        "downspouts",
        "siding",
        "gutter",
        "contractor"
    ],
    "wof:name":"Rainguard Eavestroughing Ltd",
    "wof:placetype":"venue"
},
  "geometry": {"coordinates":[-113.489403,53.458828],"type":"Point"}
}