{
  "type": "Feature",
  "properties": {
    "iso:country":"CA",
    "sg:city":"Uxbridge",
    "sg:classifiers":[
        {
            "category":"Recreation",
            "type":"Entertainment"
        }
    ],
    "sg:phone":"+1 905 852 7400",
    "sg:postcode":"L9P 1R1",
    "sg:province":"ON",
    "sg:tags":[
        "stable"
    ],
    "wof:name":"Prince Lee Acres",
    "wof:placetype":"venue"
},
  "geometry": {"coordinates":[-79.123863,44.106167],"type":"Point"}
}