{
  "type": "Feature",
  "properties": {
    "addr:full":"277 Sparks St # A Ottawa ON K1R 7X9",
    "addr:housenumber":"277",
    "addr:postcode":"k1r 7x9",
    "addr:street":"Sparks St # A",
    "iso:country":"CA",
    "sg:address":"277 Sparks St # A",
    "sg:city":"Ottawa",
    "sg:classifiers":[
        {
            "category":"Restaurant",
            "type":"Food & Drink"
        }
    ],
    "sg:phone":"+1 613 235 7232",
    "sg:postcode":"K1R 7X9",
    "sg:province":"ON",
    "sg:tags":[
        "delicatessen"
    ],
    "wof:name":"Deli Kat Cafe",
    "wof:placetype":"venue"
},
  "geometry": {"coordinates":[-75.70425400000001,45.420059],"type":"Point"}
}