{
  "type": "Feature",
  "properties": {
    "addr:full":"1622 Rue Roberval Saint-Bruno QC J3V 3P9",
    "addr:housenumber":"1622",
    "addr:postcode":"j3v 3p9",
    "addr:street":"Rue Roberval",
    "iso:country":"CA",
    "sg:address":"1622 Rue Roberval",
    "sg:city":"Saint-Bruno",
    "sg:classifiers":[
        {
            "category":"Organizations",
            "subcategory":"Professional Association",
            "type":"Services"
        }
    ],
    "sg:phone":"+1 450 461 1218",
    "sg:postcode":"J3V 3P9",
    "sg:province":"QC",
    "wof:name":"Royal Canadian Legion Royale",
    "wof:placetype":"venue"
},
  "geometry": {"coordinates":[-71.675522,48.471771],"type":"Point"}
}