{
  "type": "Feature",
  "properties": {
    "addr:full":"Oshawa ON L1H 7K5",
    "addr:postcode":"l1h 7k5",
    "iso:country":"CA",
    "sg:city":"Oshawa",
    "sg:classifiers":[
        {
            "category":"Shopping",
            "subcategory":"Clothing, Apparel, & Fashions",
            "type":"Retail Goods"
        }
    ],
    "sg:phone":"+1 905 571 5992",
    "sg:postcode":"L1H 7K5",
    "sg:province":"ON",
    "sg:tags":[
        "furnishing"
    ],
    "wof:name":"Mark's Work Wearhouse",
    "wof:placetype":"venue"
},
  "geometry": {"coordinates":[-78.8499298096,43.9410362244],"type":"Point"}
}