{
  "type": "Feature",
  "properties": {
    "iso:country":"CA",
    "sg:address":"201 Main St",
    "sg:city":"Balcarres",
    "sg:classifiers":[
        {
            "category":"Restaurant",
            "type":"Food & Drink"
        }
    ],
    "sg:phone":"+1 306 334 2788",
    "sg:postcode":"S0G 0C0",
    "sg:province":"SK",
    "wof:name":"Paulene's Corner Cafe",
    "wof:placetype":"venue"
},
  "geometry": {"coordinates":[-103.542747498,50.8030014038],"type":"Point"}
}