{
  "type": "Feature",
  "properties": {
    "addr:full":"1797 South Cameron Blvd Windsor ON N9B 3P6",
    "addr:housenumber":"1797",
    "addr:postcode":"n9b 3p6",
    "addr:street":"South Cameron Blvd",
    "iso:country":"CA",
    "sg:address":"1797 South Cameron Blvd",
    "sg:city":"Windsor",
    "sg:classifiers":[
        {
            "category":"Building & Trades",
            "subcategory":"Construction",
            "type":"Services"
        }
    ],
    "sg:phone":"+1 519 969 7557",
    "sg:postcode":"N9B 3P6",
    "sg:province":"ON",
    "sg:tags":[
        "home",
        "improvement"
    ],
    "wof:name":"Olivia Construction Homes Inc",
    "wof:placetype":"venue"
},
  "geometry": {"coordinates":[-83.038185,42.289883],"type":"Point"}
}