{
  "type": "Feature",
  "properties": {
    "addr:full":"750 Av Des Diamants Charlesbourg QC G2L 2R2",
    "addr:housenumber":"750",
    "addr:postcode":"g2l 2r2",
    "addr:street":"Av Des Diamants",
    "iso:country":"CA",
    "sg:address":"750 Av Des Diamants",
    "sg:city":"Charlesbourg",
    "sg:classifiers":[
        {
            "category":"Health Services",
            "subcategory":"Nursing And Care Facility",
            "type":"Services"
        }
    ],
    "sg:phone":"+1 418 628 6332",
    "sg:postcode":"G2L 2R2",
    "sg:province":"QC",
    "sg:tags":[
        "home",
        "retirement",
        "community"
    ],
    "wof:name":"Pavillon Des Veterans Inc",
    "wof:placetype":"venue"
},
  "geometry": {"coordinates":[-71.25202899999999,46.876637],"type":"Point"}
}