{
  "type": "Feature",
  "properties": {
    "addr:full":"2524 Main St Westbank BC V4T 2E3",
    "addr:housenumber":"2524",
    "addr:postcode":"v4t 2e3",
    "addr:street":"Main St",
    "iso:country":"CA",
    "sg:address":"2524 Main St",
    "sg:city":"Westbank",
    "sg:classifiers":[
        {
            "category":"Government",
            "subcategory":"Office",
            "type":"Public Place"
        }
    ],
    "sg:phone":"+1 250 768 8426",
    "sg:postcode":"V4T 2E3",
    "sg:province":"BC",
    "wof:name":"B C Members of the Legislative",
    "wof:placetype":"venue"
},
  "geometry": {"coordinates":[-119.63248400000001,49.829426],"type":"Point"}
}