{
  "type": "Feature",
  "properties": {
    "addr:full":"34 Sullivans Loop Pouch Cove NL A0A 3L0",
    "addr:housenumber":"34",
    "addr:postcode":"a0a 3l0",
    "addr:street":"Sullivans Loop",
    "iso:country":"CA",
    "sg:address":"34 Sullivans Loop",
    "sg:city":"Pouch Cove",
    "sg:classifiers":[
        {
            "category":"Travel",
            "subcategory":"Hotels & Motels",
            "type":"Entertainment"
        }
    ],
    "sg:phone":"+1 709 335 8315",
    "sg:postcode":"A0A 3L0",
    "sg:province":"NL",
    "sg:tags":[
        "breakfast",
        "accommodation",
        "bed"
    ],
    "wof:name":"Points East",
    "wof:placetype":"venue"
},
  "geometry": {"coordinates":[-52.7631607056,47.7685966492],"type":"Point"}
}