{
  "type": "Feature",
  "properties": {
    "addr:full":"140 Smith St E Yorkton SK S3N 3Z7",
    "addr:housenumber":"140",
    "addr:postcode":"s3n 3z7",
    "addr:street":"Smith St E",
    "iso:country":"CA",
    "sg:address":"140 Smith St E",
    "sg:city":"Yorkton",
    "sg:classifiers":[
        {
            "category":"Retail",
            "subcategory":"Car Wash",
            "type":"Services"
        }
    ],
    "sg:phone":"+1 306 786 7227",
    "sg:postcode":"S3N 3Z7",
    "sg:province":"SK",
    "sg:tags":[
        "polishing",
        "washing"
    ],
    "wof:name":"Shell Canada Products Ltd",
    "wof:placetype":"venue"
},
  "geometry": {"coordinates":[-102.45365099999999,51.211796],"type":"Point"}
}