{
  "type": "Feature",
  "properties": {
    "iso:country":"CA",
    "sg:address":"140 Smith St E",
    "sg:city":"Yorkton",
    "sg:classifiers":[
        {
            "category":"Retail",
            "subcategory":"Car Wash",
            "type":"Services"
        }
    ],
    "sg:phone":"+1 306 786 7227",
    "sg:postcode":"S3N 3Z7",
    "sg:province":"SK",
    "sg:tags":[
        "polishing",
        "washing"
    ],
    "wof:name":"Shell Canada Products Ltd",
    "wof:placetype":"venue"
},
  "geometry": {"coordinates":[-102.453651,51.211796],"type":"Point"}
}