{
  "type": "Feature",
  "properties": {
    "addr:full":"1246 Two Mile Rd Winnipeg MB R2N 4E6",
    "addr:housenumber":"1246",
    "addr:postcode":"r2n 4e6",
    "addr:street":"Two Mile Rd",
    "iso:country":"CA",
    "sg:address":"1246 Two Mile Rd",
    "sg:city":"Winnipeg",
    "sg:classifiers":[
        {
            "category":"Shopping",
            "subcategory":"Bicycles & Sporting Goods",
            "type":"Retail Goods"
        }
    ],
    "sg:phone":"+1 204 255 5515",
    "sg:postcode":"R2N 4E6",
    "sg:province":"MB",
    "sg:tags":[
        "amusement",
        "devices"
    ],
    "wof:name":"Super-Tramp",
    "wof:placetype":"venue"
},
  "geometry": {"coordinates":[-97.084068,49.786118],"type":"Point"}
}