{
  "type": "Feature",
  "properties": {
    "addr:full":"375 Broadway W Vancouver BC V5Y 1P8",
    "addr:housenumber":"375",
    "addr:postcode":"v5y 1p8",
    "addr:street":"Broadway W",
    "iso:country":"CA",
    "sg:address":"375 Broadway W",
    "sg:city":"Vancouver",
    "sg:classifiers":[
        {
            "category":"Personal",
            "subcategory":"Beauty Salon",
            "type":"Services"
        }
    ],
    "sg:phone":"+1 604 874 3230",
    "sg:postcode":"V5Y 1P8",
    "sg:province":"BC",
    "wof:name":"Vanity Room",
    "wof:placetype":"venue"
},
  "geometry": {"coordinates":[-123.112335,49.263313],"type":"Point"}
}