{
  "type": "Feature",
  "properties": {
    "addr:full":"Brandon MB R7A 5B8",
    "addr:postcode":"r7a 5b8",
    "iso:country":"CA",
    "sg:city":"Brandon",
    "sg:classifiers":[
        {
            "category":"Insurance",
            "subcategory":"Insurance Agent",
            "type":"Services"
        }
    ],
    "sg:phone":"+1 204 729 2000",
    "sg:postcode":"R7A 5B8",
    "sg:province":"MB",
    "sg:tags":[
        "investment"
    ],
    "wof:name":"Investors Group Financial Svc",
    "wof:placetype":"venue"
},
  "geometry": {"coordinates":[-99.96160888670001,49.8367347717],"type":"Point"}
}