{
  "type": "Feature",
  "properties": {
    "addr:full":"Niagara on the Lake ON L0S 1J0",
    "addr:postcode":"l0s 1j0",
    "iso:country":"CA",
    "sg:city":"Niagara on the Lake",
    "sg:classifiers":[
        {
            "category":"Building & Trades",
            "subcategory":"Construction",
            "type":"Services"
        }
    ],
    "sg:phone":"+1 905 468 4981",
    "sg:postcode":"L0S 1J0",
    "sg:province":"ON",
    "sg:tags":[
        "contractor"
    ],
    "wof:name":"Carmel Construction Ltd",
    "wof:placetype":"venue"
},
  "geometry": {"coordinates":[-79.080673,43.23848],"type":"Point"}
}