{
  "type": "Feature",
  "properties": {
    "addr:full":"820 Boul Decarie Saint-Laurent QC H4L 3L9",
    "addr:housenumber":"820",
    "addr:postcode":"h4l 3l9",
    "addr:street":"Boul Decarie",
    "iso:country":"CA",
    "sg:address":"820 Boul Decarie",
    "sg:city":"Saint-Laurent",
    "sg:classifiers":[
        {
            "category":"Personal",
            "subcategory":"Beauty Salon",
            "type":"Services"
        }
    ],
    "sg:phone":"+1 514 747 2291",
    "sg:postcode":"H4L 3L9",
    "sg:province":"QC",
    "wof:name":"May Bo Salon DE Coiffure",
    "wof:placetype":"venue"
},
  "geometry": {"coordinates":[-73.679069519,45.5116729736],"type":"Point"}
}