{
  "type": "Feature",
  "properties": {
    "addr:full":"42 Rue Desrochers Laval QC H7V 1Z8",
    "addr:housenumber":"42",
    "addr:postcode":"h7v 1z8",
    "addr:street":"Rue Desrochers",
    "iso:country":"CA",
    "sg:address":"42 Rue Desrochers",
    "sg:city":"Laval",
    "sg:classifiers":[
        {
            "category":"Manufacturing",
            "subcategory":"Printing",
            "type":"Manufacturing & Wholesale Goods"
        }
    ],
    "sg:phone":"+1 450 681 2202",
    "sg:postcode":"H7V 1Z8",
    "sg:province":"QC",
    "sg:tags":[
        "printer"
    ],
    "wof:name":"Alliance Lafleur Enr",
    "wof:placetype":"venue"
},
  "geometry": {"coordinates":[-73.7165145874,45.5426940918],"type":"Point"}
}