{
  "type": "Feature",
  "properties": {
    "addr:full":"32 Earl Dr Chatham ON N7M 5Z3",
    "addr:housenumber":"32",
    "addr:postcode":"n7m 5z3",
    "addr:street":"Earl Dr",
    "iso:country":"CA",
    "sg:address":"32 Earl Dr",
    "sg:city":"Chatham",
    "sg:classifiers":[
        {
            "category":"Shopping",
            "subcategory":"Clothing, Apparel, & Fashions",
            "type":"Retail Goods"
        }
    ],
    "sg:phone":"+1 519 354 5294",
    "sg:postcode":"N7M 5Z3",
    "sg:province":"ON",
    "sg:tags":[
        "theatrical",
        "costume"
    ],
    "wof:name":"Illusion Costume Rental",
    "wof:placetype":"venue"
},
  "geometry": {"coordinates":[-82.202377,42.395168],"type":"Point"}
}