{
  "type": "Feature",
  "properties": {
    "addr:full":"367 Van Horne St S Cranbrook BC V1C 1Z6",
    "addr:housenumber":"367",
    "addr:postcode":"v1c 1z6",
    "addr:street":"Van Horne St S",
    "iso:country":"CA",
    "sg:address":"367 Van Horne St S",
    "sg:city":"Cranbrook",
    "sg:classifiers":[
        {
            "category":"Food & Beverages",
            "subcategory":"Groceries & Convenience Stores",
            "type":"Retail Goods"
        }
    ],
    "sg:phone":"+1 250 417 0055",
    "sg:postcode":"V1C 1Z6",
    "sg:province":"BC",
    "sg:tags":[
        "grocer"
    ],
    "wof:name":"Kootenay Tree House",
    "wof:placetype":"venue"
},
  "geometry": {"coordinates":[-115.78323399999999,49.505825],"type":"Point"}
}