{
  "type": "Feature",
  "properties": {
    "addr:full":"81 Fyfe Ave Woodstock ON N4S 8Y2",
    "addr:housenumber":"81",
    "addr:postcode":"n4s 8y2",
    "addr:street":"Fyfe Ave",
    "iso:country":"CA",
    "sg:address":"81 Fyfe Ave",
    "sg:city":"Woodstock",
    "sg:classifiers":[
        {
            "category":"Health Services",
            "subcategory":"Nursing And Care Facility",
            "type":"Services"
        }
    ],
    "sg:phone":"+1 519 539 6461",
    "sg:postcode":"N4S 8Y2",
    "sg:province":"ON",
    "sg:tags":[
        "home",
        "convalescent"
    ],
    "wof:name":"Carassant Care Woodstock",
    "wof:placetype":"venue"
},
  "geometry": {"coordinates":[-80.74314117430001,43.1235046387],"type":"Point"}
}