{
  "type": "Feature",
  "properties": {
    "iso:country":"CA",
    "sg:city":"Sainte-Croix",
    "sg:classifiers":[
        {
            "category":"Shopping",
            "subcategory":"Pharmacy",
            "type":"Retail Goods"
        }
    ],
    "sg:phone":"+1 418 926 3201",
    "sg:postcode":"G0S 2H0",
    "sg:province":"QC",
    "wof:name":"Pharmacie Gervais Lemay",
    "wof:placetype":"venue"
},
  "geometry": {"coordinates":[-71.7411117554,46.6229362488],"type":"Point"}
}