{
  "type": "Feature",
  "properties": {
    "addr:full":"151 Oxford St W London ON N6H 1S3",
    "addr:housenumber":"151",
    "addr:postcode":"n6h 1s3",
    "addr:street":"Oxford St W",
    "iso:country":"CA",
    "sg:address":"151 Oxford St W",
    "sg:city":"London",
    "sg:classifiers":[
        {
            "category":"Education",
            "subcategory":"School",
            "type":"Public Place"
        }
    ],
    "sg:phone":"+1 519 679 9920",
    "sg:postcode":"N6H 1S3",
    "sg:province":"ON",
    "wof:name":"London Islamic School",
    "wof:placetype":"venue"
},
  "geometry": {"coordinates":[-81.2699432373,42.9906463623],"type":"Point"}
}