{
  "type": "Feature",
  "properties": {
    "addr:full":"Vancouver BC V6P 3S9",
    "addr:postcode":"v6p 3s9",
    "iso:country":"CA",
    "sg:city":"Vancouver",
    "sg:classifiers":[
        {
            "category":"Travel",
            "subcategory":"Travel Agent",
            "type":"Entertainment"
        }
    ],
    "sg:phone":"+1 604 321 8772",
    "sg:postcode":"V6P 3S9",
    "sg:province":"BC",
    "sg:tags":[
        "tours",
        "promoter"
    ],
    "wof:name":"Nac Tours",
    "wof:placetype":"venue"
},
  "geometry": {"coordinates":[-123.12392425500001,49.2075653076],"type":"Point"}
}