{
  "type": "Feature",
  "properties": {
    "addr:full":"225 Rue Saint-Joseph Mont-Saint-Gregoire QC J0J 1K0",
    "addr:housenumber":"225",
    "addr:postcode":"j0j 1k0",
    "addr:street":"Rue Saint-Joseph Mont-Saint-Gregoire",
    "iso:country":"CA",
    "sg:address":"225 Rue Saint-Joseph",
    "sg:city":"Mont-Saint-Gregoire",
    "sg:classifiers":[
        {
            "category":"Government",
            "subcategory":"Office",
            "type":"Public Place"
        }
    ],
    "sg:phone":"+1 450 347 5376",
    "sg:postcode":"J0J 1K0",
    "sg:province":"QC",
    "sg:tags":[
        "village"
    ],
    "wof:name":"St-Gregoire-Le-Grand Adm Ofc",
    "wof:placetype":"venue"
},
  "geometry": {"coordinates":[-73.159111,45.335915],"type":"Point"}
}