{
  "type": "Feature",
  "properties": {
    "iso:country":"CA",
    "sg:address":"945 Sydenham Rd",
    "sg:city":"Peterborough",
    "sg:classifiers":[
        {
            "category":"Building & Trades",
            "subcategory":"Construction",
            "type":"Services"
        }
    ],
    "sg:phone":"+1 705 742 1250",
    "sg:postcode":"K9J 1K5",
    "sg:province":"ON",
    "sg:tags":[
        "equipment",
        "computer",
        "wiring"
    ],
    "wof:name":"Works Avenue",
    "wof:placetype":"venue"
},
  "geometry": {"coordinates":[-78.30434417719999,44.2864837646],"type":"Point"}
}