{
  "type": "Feature",
  "properties": {
    "addr:full":"35 Teal Ave Stoney Creek ON L8E 3B1",
    "addr:housenumber":"35",
    "addr:postcode":"l8e 3b1",
    "addr:street":"Teal Ave",
    "iso:country":"CA",
    "sg:address":"35 Teal Ave",
    "sg:city":"Stoney Creek",
    "sg:classifiers":[
        {
            "category":"Manufacturing",
            "subcategory":"Metals",
            "type":"Manufacturing & Wholesale Goods"
        }
    ],
    "sg:phone":"+1 905 662 7711",
    "sg:postcode":"L8E 3B1",
    "sg:province":"ON",
    "sg:tags":[
        "valve"
    ],
    "wof:name":"North Port Valves",
    "wof:placetype":"venue"
},
  "geometry": {"coordinates":[-79.73165893549999,43.2387313843],"type":"Point"}
}