{
  "type": "Feature",
  "properties": {
    "addr:full":"200 King St W Dundas ON L9H 1V4",
    "addr:housenumber":"200",
    "addr:postcode":"on l9h 1v4",
    "addr:street":"King St W",
    "iso:country":"CA",
    "sg:address":"200 King St W",
    "sg:city":"Dundas",
    "sg:classifiers":[
        {
            "category":"Retail",
            "subcategory":"Auto Rental",
            "type":"Services"
        }
    ],
    "sg:phone":"+1 905 628 9889",
    "sg:postcode":"L9H 1V4",
    "sg:province":"ON",
    "sg:tags":[
        "renting",
        "automobile"
    ],
    "wof:name":"A Carter Car & Truck Rentals",
    "wof:placetype":"venue"
},
  "geometry": {"coordinates":[-79.962456,43.267365],"type":"Point"}
}