{
  "type": "Feature",
  "properties": {
    "iso:country":"CA",
    "sg:address":"1507 Mardell Pl",
    "sg:city":"London",
    "sg:classifiers":[
        {
            "category":"Manufacturing",
            "subcategory":"Metals",
            "type":"Manufacturing & Wholesale Goods"
        }
    ],
    "sg:phone":"+1 519 455 7366",
    "sg:postcode":"N5V 1X1",
    "sg:province":"ON",
    "sg:tags":[
        "general",
        "contractor"
    ],
    "wof:name":"Henderson Renovations Ltd",
    "wof:placetype":"venue"
},
  "geometry": {"coordinates":[-81.199844,43.008423],"type":"Point"}
}