{
  "type": "Feature",
  "properties": {
    "addr:full":"7181 Rue Beaubien E Anjou QC H1M 2Y2",
    "addr:housenumber":"7181",
    "addr:postcode":"h1m 2y2",
    "addr:street":"Rue Beaubien E",
    "iso:country":"CA",
    "sg:address":"7181 Rue Beaubien E",
    "sg:city":"Anjou",
    "sg:classifiers":[
        {
            "category":"Shopping",
            "subcategory":"Pharmacy",
            "type":"Retail Goods"
        }
    ],
    "sg:phone":"+1 514 355 6465",
    "sg:postcode":"H1M 2Y2",
    "sg:province":"QC",
    "wof:name":"Pharmacie Denis Ruel",
    "wof:placetype":"venue"
},
  "geometry": {"coordinates":[-73.55718231199999,45.5944519043],"type":"Point"}
}