{
  "type": "Feature",
  "properties": {
    "iso:country":"CA",
    "sg:city":"Jacksonville",
    "sg:classifiers":[
        {
            "category":"Wholesale",
            "subcategory":"Auto Parts",
            "type":"Manufacturing & Wholesale Goods"
        }
    ],
    "sg:phone":"+1 506 328 4242",
    "sg:postcode":"E7M 3J8",
    "sg:province":"NB",
    "sg:tags":[
        "automobile",
        "rebuilt",
        "supply"
    ],
    "wof:name":"Parts R US",
    "wof:placetype":"venue"
},
  "geometry": {"coordinates":[-67.6223373413,46.1971588135],"type":"Point"}
}