{
  "type": "Feature",
  "properties": {
    "addr:full":"Calgary AB T2K 1H9",
    "addr:postcode":"t2k 1h9",
    "iso:country":"CA",
    "sg:city":"Calgary",
    "sg:classifiers":[
        {
            "category":"Recreation",
            "type":"Entertainment"
        }
    ],
    "sg:phone":"+1 403 284 2251",
    "sg:postcode":"T2K 1H9",
    "sg:province":"AB",
    "sg:tags":[
        "martial",
        "arts",
        "instruction"
    ],
    "wof:name":"Black Belt of Karate",
    "wof:placetype":"venue"
},
  "geometry": {"coordinates":[-114.094528,51.085083],"type":"Point"}
}