{
  "type": "Feature",
  "properties": {
    "addr:full":"Bromhead SK S0C 0N0",
    "addr:postcode":"s0c 0n0",
    "addr:street":"Bromhead",
    "iso:country":"CA",
    "sg:city":"Bromhead",
    "sg:classifiers":[
        {
            "category":"Organizations",
            "subcategory":"Religious Organization",
            "type":"Services"
        }
    ],
    "sg:phone":"+1 306 456 2533",
    "sg:postcode":"S0C 0N0",
    "sg:province":"SK",
    "sg:tags":[
        "church"
    ],
    "wof:name":"Hamar Lutheran Church",
    "wof:placetype":"venue"
},
  "geometry": {"coordinates":[-103.679321289,49.1823921204],"type":"Point"}
}