{
  "type": "Feature",
  "properties": {
    "addr:full":"Langley BC V3A 4G3",
    "addr:postcode":"v3a 4g3",
    "iso:country":"CA",
    "sg:city":"Langley",
    "sg:classifiers":[
        {
            "category":"Real Estate",
            "subcategory":"Developer",
            "type":"Services"
        }
    ],
    "sg:phone":"+1 604 534 3643",
    "sg:postcode":"V3A 4G3",
    "sg:province":"BC",
    "sg:tags":[
        "company",
        "land"
    ],
    "wof:name":"Resland Development Corp",
    "wof:placetype":"venue"
},
  "geometry": {"coordinates":[-122.65345764200001,49.1041984558],"type":"Point"}
}