{
  "type": "Feature",
  "properties": {
    "iso:country":"CA",
    "sg:address":"247 Rue Saint-Jacques",
    "sg:city":"Saint-Jacques",
    "sg:classifiers":[
        {
            "category":"Wholesale",
            "subcategory":"Metals & Minerals",
            "type":"Manufacturing & Wholesale Goods"
        }
    ],
    "sg:phone":"+1 450 839 2655",
    "sg:postcode":"J0K 2R0",
    "sg:province":"QC",
    "sg:tags":[
        "uniform"
    ],
    "wof:name":"Ipex Inc",
    "wof:placetype":"venue"
},
  "geometry": {"coordinates":[-73.5801239014,45.9545135498],"type":"Point"}
}