{
  "type": "Feature",
  "properties": {
    "addr:full":"41 Breynat St Fort Smith NT X0E 0P0",
    "addr:housenumber":"41",
    "addr:postcode":"x0e 0p0",
    "addr:street":"Breynat St",
    "iso:country":"CA",
    "sg:address":"41 Breynat St",
    "sg:city":"Fort Smith",
    "sg:classifiers":[
        {
            "category":"Shopping",
            "subcategory":"Discount & Variety Stores",
            "type":"Retail Goods"
        }
    ],
    "sg:phone":"+1 867 872 2568",
    "sg:postcode":"X0E 0P0",
    "sg:province":"NT",
    "sg:tags":[
        "department",
        "general"
    ],
    "wof:name":"Northern Store",
    "wof:placetype":"venue"
},
  "geometry": {"coordinates":[-111.902633667,60.0000953674],"type":"Point"}
}