{
  "type": "Feature",
  "properties": {
    "iso:country":"CA",
    "sg:address":"914 Wapiti Ave",
    "sg:city":"Waskesiu Lake",
    "sg:classifiers":[
        {
            "category":"Travel",
            "subcategory":"Hotels & Motels",
            "type":"Entertainment"
        }
    ],
    "sg:phone":"+1 306 663 5556",
    "sg:postcode":"S0J 2Y0",
    "sg:province":"SK",
    "sg:tags":[
        "resort"
    ],
    "wof:name":"Chateau Park Chalets",
    "wof:placetype":"venue"
},
  "geometry": {"coordinates":[-106.0753479,53.9210700989],"type":"Point"}
}