{
  "type": "Feature",
  "properties": {
    "addr:full":"17094 Mc Lean Rd Moose Creek ON K0C 1W0",
    "addr:housenumber":"17094",
    "addr:postcode":"k0c 1w0",
    "addr:street":"Mc Lean Rd",
    "iso:country":"CA",
    "sg:address":"17094 Mc Lean Rd",
    "sg:city":"Moose Creek",
    "sg:classifiers":[
        {
            "category":"Building & Trades",
            "subcategory":"Construction",
            "type":"Services"
        }
    ],
    "sg:phone":"+1 613 538 2305",
    "sg:postcode":"K0C 1W0",
    "sg:province":"ON",
    "sg:tags":[
        "maker",
        "cabinet"
    ],
    "wof:name":"L A Forgues Woodwork",
    "wof:placetype":"venue"
},
  "geometry": {"coordinates":[-74.95856499999999,45.269096],"type":"Point"}
}