{
  "type": "Feature",
  "properties": {
    "addr:full":"1058 Marcelin Desbiens QC G0W 1N0",
    "addr:housenumber":"1058",
    "addr:postcode":"g0w 1n0",
    "addr:street":"Marcelin Desbiens",
    "iso:country":"CA",
    "sg:address":"1058 Marcelin",
    "sg:city":"Desbiens",
    "sg:classifiers":[
        {
            "category":"Organizations",
            "subcategory":"Professional Association",
            "type":"Services"
        }
    ],
    "sg:phone":"+1 418 346 1242",
    "sg:postcode":"G0W 1N0",
    "sg:province":"QC",
    "wof:name":"Societe Recreo-Touristique",
    "wof:placetype":"venue"
},
  "geometry": {"coordinates":[-71.9474563599,48.4180259705],"type":"Point"}
}