{
  "type": "Feature",
  "properties": {
    "addr:full":"26 Main St N Hagersville ON N0A 1H0",
    "addr:housenumber":"26",
    "addr:postcode":"n0a 1h0",
    "addr:street":"Main St N",
    "iso:country":"CA",
    "sg:address":"26 Main St N",
    "sg:city":"Hagersville",
    "sg:classifiers":[
        {
            "category":"Insurance",
            "subcategory":"Insurance Agent",
            "type":"Services"
        }
    ],
    "sg:phone":"+1 905 768 3384",
    "sg:postcode":"N0A 1H0",
    "sg:province":"ON",
    "wof:name":"R A Bennett Insurance",
    "wof:placetype":"venue"
},
  "geometry": {"coordinates":[-80.050873,42.962708],"type":"Point"}
}