{
  "type": "Feature",
  "properties": {
    "addr:full":"206 Queen St S # C Mississauga ON L5M 1L3",
    "addr:housenumber":"206",
    "addr:postcode":"l5m 1l3",
    "addr:street":"Queen St S # C",
    "iso:country":"CA",
    "sg:address":"206 Queen St S # C",
    "sg:city":"Mississauga",
    "sg:classifiers":[
        {
            "category":"Food & Beverages",
            "subcategory":"Bakery",
            "type":"Retail Goods"
        }
    ],
    "sg:phone":"+1 905 821 1166",
    "sg:postcode":"L5M 1L3",
    "sg:province":"ON",
    "sg:tags":[
        "baker"
    ],
    "wof:name":"Town Talk Bakery & Fine Pastry",
    "wof:placetype":"venue"
},
  "geometry": {"coordinates":[-79.59994500000001,43.543491],"type":"Point"}
}