{
  "type": "Feature",
  "properties": {
    "addr:full":"1641 Slater Ave Kamloops BC V2B 4K3",
    "addr:housenumber":"1641",
    "addr:postcode":"bc v2b 4k3",
    "addr:street":"Slater Ave",
    "iso:country":"CA",
    "sg:address":"1641 Slater Ave",
    "sg:city":"Kamloops",
    "sg:classifiers":[
        {
            "category":"Building & Trades",
            "subcategory":"Construction",
            "type":"Services"
        }
    ],
    "sg:phone":"+1 250 554 2719",
    "sg:postcode":"V2B 4K3",
    "sg:province":"BC",
    "sg:tags":[
        "masonry",
        "contractor"
    ],
    "wof:name":"Phil Green Masonry",
    "wof:placetype":"venue"
},
  "geometry": {"coordinates":[-120.386184692,50.7004547119],"type":"Point"}
}