{
  "type": "Feature",
  "properties": {
    "iso:country":"CA",
    "sg:address":"24 Perdue Crt",
    "sg:city":"Markham",
    "sg:classifiers":[
        {
            "category":"Building & Trades",
            "subcategory":"Electrical",
            "type":"Services"
        }
    ],
    "sg:phone":"+1 905 479 7196",
    "sg:postcode":"L3R 8T1",
    "sg:province":"ON",
    "sg:tags":[
        "electric",
        "contractor"
    ],
    "wof:name":"Econ Electric CO Ltd",
    "wof:placetype":"venue"
},
  "geometry": {"coordinates":[-79.294144,43.842155],"type":"Point"}
}