{
  "type": "Feature",
  "properties": {
    "iso:country":"CA",
    "sg:address":"753 Burrard St",
    "sg:city":"Vancouver",
    "sg:classifiers":[
        {
            "category":"Shopping",
            "subcategory":"Clothing, Apparel, & Fashions",
            "type":"Retail Goods"
        }
    ],
    "sg:phone":"+1 604 647 0201",
    "sg:postcode":"V6Z 1X6",
    "sg:province":"BC",
    "wof:name":"Wolford",
    "wof:placetype":"venue"
},
  "geometry": {"coordinates":[-123.122123718,49.2838745117],"type":"Point"}
}