{
  "type": "Feature",
  "properties": {
    "addr:full":"Richmond BC V6X 3P3",
    "addr:postcode":"v6x 3p3",
    "iso:country":"CA",
    "sg:city":"Richmond",
    "sg:classifiers":[
        {
            "category":"Professional",
            "subcategory":"Management & Consulting",
            "type":"Services"
        }
    ],
    "sg:phone":"+1 604 276 2083",
    "sg:postcode":"V6X 3P3",
    "sg:province":"BC",
    "sg:tags":[
        "marketing",
        "consultant"
    ],
    "wof:name":"Brandon Marketing Inc",
    "wof:placetype":"venue"
},
  "geometry": {"coordinates":[-123.130882263,49.1784744263],"type":"Point"}
}