{
  "type": "Feature",
  "properties": {
    "addr:full":"17 Marineside Dr Englee NL A0K 2J0",
    "addr:housenumber":"17",
    "addr:postcode":"a0k 2j0",
    "addr:street":"Marineside Dr",
    "iso:country":"CA",
    "sg:address":"17 Marineside Dr",
    "sg:city":"Englee",
    "sg:classifiers":[
        {
            "category":"Food & Beverages",
            "subcategory":"Groceries & Convenience Stores",
            "type":"Retail Goods"
        }
    ],
    "sg:phone":"+1 709 866 2739",
    "sg:postcode":"A0K 2J0",
    "sg:province":"NL",
    "sg:tags":[
        "grocer"
    ],
    "wof:name":"Breen's Groceries & Confectnry",
    "wof:placetype":"venue"
},
  "geometry": {"coordinates":[-56.1045265198,50.734172821],"type":"Point"}
}