{
  "type": "Feature",
  "properties": {
    "iso:country":"CA",
    "sg:address":"10 Drury St # 312",
    "sg:city":"Kapuskasing",
    "sg:classifiers":[
        {
            "category":"Real Estate",
            "subcategory":"Real Estate Operator",
            "type":"Services"
        }
    ],
    "sg:phone":"+1 705 335 3805",
    "sg:postcode":"P5N 1K9",
    "sg:province":"ON",
    "sg:tags":[
        "apartment"
    ],
    "wof:name":"Drury Place",
    "wof:placetype":"venue"
},
  "geometry": {"coordinates":[-82.4310760498,49.4167861938],"type":"Point"}
}