{
  "type": "Feature",
  "properties": {
    "addr:full":"3169 Boul Masson Quebec QC G1P 1J7",
    "addr:housenumber":"3169",
    "addr:postcode":"g1p 1j7",
    "addr:street":"Boul Masson",
    "iso:country":"CA",
    "sg:address":"3169 Boul Masson",
    "sg:city":"Quebec",
    "sg:classifiers":[
        {
            "category":"Food & Beverages",
            "subcategory":"Groceries & Convenience Stores",
            "type":"Retail Goods"
        }
    ],
    "sg:phone":"+1 418 871 6979",
    "sg:postcode":"G1P 1J7",
    "sg:province":"QC",
    "wof:name":"Marche Les Saules Inc",
    "wof:placetype":"venue"
},
  "geometry": {"coordinates":[-71.32279200000001,46.812298],"type":"Point"}
}