{
  "type": "Feature",
  "properties": {
    "addr:full":"Roberval QC G8H 2K9",
    "addr:postcode":"g8h 2k9",
    "iso:country":"CA",
    "sg:city":"Roberval",
    "sg:classifiers":[
        {
            "category":"Personal",
            "subcategory":"Beauty Salon",
            "type":"Services"
        }
    ],
    "sg:phone":"+1 418 275 3569",
    "sg:postcode":"G8H 2K9",
    "sg:province":"QC",
    "wof:name":"Salon Boucle D'Or",
    "wof:placetype":"venue"
},
  "geometry": {"coordinates":[-72.22007000000001,48.512222],"type":"Point"}
}