{
  "type": "Feature",
  "properties": {
    "addr:full":"11 King St W # 200 Toronto ON M5H 4C7",
    "addr:housenumber":"11",
    "addr:postcode":"m5h 4c7",
    "addr:street":"King St W # 200",
    "iso:country":"CA",
    "sg:address":"11 King St W # 200",
    "sg:city":"Toronto",
    "sg:classifiers":[
        {
            "category":"Health Services",
            "subcategory":"Doctor",
            "type":"Services"
        }
    ],
    "sg:phone":"+1 416 864 0727",
    "sg:postcode":"M5H 4C7",
    "sg:province":"ON",
    "sg:tags":[
        "physician",
        "surgeon"
    ],
    "wof:name":"Au, Susan J MD",
    "wof:placetype":"venue"
},
  "geometry": {"coordinates":[-79.378265,43.648911],"type":"Point"}
}