{
  "type": "Feature",
  "properties": {
    "iso:country":"CA",
    "sg:address":"305 1st St W",
    "sg:city":"Delisle",
    "sg:classifiers":[
        {
            "category":"Health Services",
            "subcategory":"Doctor",
            "type":"Services"
        }
    ],
    "sg:phone":"+1 306 493 2810",
    "sg:postcode":"S0L 0P0",
    "sg:province":"SK",
    "sg:tags":[
        "physician",
        "surgeon"
    ],
    "wof:name":"Delisle Community Health Ctr",
    "wof:placetype":"venue"
},
  "geometry": {"coordinates":[-107.134803772,51.9240837097],"type":"Point"}
}