{
  "type": "Feature",
  "properties": {
    "addr:full":"9 Smith St E Yorkton SK S3N 0H2",
    "addr:housenumber":"9",
    "addr:postcode":"s3n 0h2",
    "addr:street":"Smith St E",
    "iso:country":"CA",
    "sg:address":"9 Smith St E",
    "sg:city":"Yorkton",
    "sg:classifiers":[
        {
            "category":"Government",
            "subcategory":"Fire Station",
            "type":"Public Place"
        }
    ],
    "sg:phone":"+1 306 786 1795",
    "sg:postcode":"S3N 0H2",
    "sg:province":"SK",
    "sg:tags":[
        "department"
    ],
    "wof:name":"Yorkton Fire Hall",
    "wof:placetype":"venue"
},
  "geometry": {"coordinates":[-102.46208190900001,51.2122612],"type":"Point"}
}