{
  "type": "Feature",
  "properties": {
    "addr:full":"276 Talbot St S Essex ON N8M 1B8",
    "addr:housenumber":"276",
    "addr:postcode":"n8m 1b8",
    "addr:street":"Talbot St S",
    "iso:country":"CA",
    "sg:address":"276 Talbot St S",
    "sg:city":"Essex",
    "sg:classifiers":[
        {
            "category":"Organizations",
            "subcategory":"Religious Organization",
            "type":"Services"
        }
    ],
    "sg:phone":"+1 519 776 5071",
    "sg:postcode":"N8M 1B8",
    "sg:province":"ON",
    "sg:tags":[
        "church"
    ],
    "wof:name":"Christian Reformed Church",
    "wof:placetype":"venue"
},
  "geometry": {"coordinates":[-82.811081,42.167404],"type":"Point"}
}