{
  "type": "Feature",
  "properties": {
    "addr:full":"416 Safari Dr Oshawa ON L1K 1B6",
    "addr:housenumber":"416",
    "addr:postcode":"l1k 1b6",
    "addr:street":"Safari Dr",
    "iso:country":"CA",
    "sg:address":"416 Safari Dr",
    "sg:city":"Oshawa",
    "sg:classifiers":[
        {
            "category":"Professional",
            "subcategory":"Testing Lab",
            "type":"Services"
        }
    ],
    "sg:phone":"+1 905 579 5055",
    "sg:postcode":"L1K 1B6",
    "sg:province":"ON",
    "sg:tags":[
        "laboratory"
    ],
    "wof:name":"Canadian Garment Analysis Lab",
    "wof:placetype":"venue"
},
  "geometry": {"coordinates":[-78.826965332,43.9152145386],"type":"Point"}
}