{
  "type": "Feature",
  "properties": {
    "addr:full":"99 Levesque St Sudbury ON P3B 3S8",
    "addr:housenumber":"99",
    "addr:postcode":"p3b 3s8",
    "addr:street":"Levesque St",
    "iso:country":"CA",
    "sg:address":"99 Levesque St",
    "sg:city":"Sudbury",
    "sg:classifiers":[
        {
            "category":"Building & Trades",
            "subcategory":"Cleaning & Sanitation",
            "type":"Services"
        }
    ],
    "sg:phone":"+1 705 524 2395",
    "sg:postcode":"P3B 3S8",
    "sg:province":"ON",
    "sg:tags":[
        "filter"
    ],
    "wof:name":"D & J Cleaners",
    "wof:placetype":"venue"
},
  "geometry": {"coordinates":[-80.910713,46.488426],"type":"Point"}
}