{
  "type": "Feature",
  "properties": {
    "addr:full":"1582 Rue Du Boulevard Laterriere QC G7N 1J8",
    "addr:housenumber":"1582",
    "addr:postcode":"g7n 1j8",
    "addr:street":"Rue Du Boulevard Laterriere",
    "iso:country":"CA",
    "sg:address":"1582 Rue Du Boulevard",
    "sg:city":"Laterriere",
    "sg:classifiers":[
        {
            "category":"Building & Trades",
            "subcategory":"Construction",
            "type":"Services"
        }
    ],
    "sg:phone":"+1 418 678 2502",
    "sg:postcode":"G7N 1J8",
    "sg:province":"QC",
    "sg:tags":[
        "roof",
        "structure",
        "contractor"
    ],
    "wof:name":"St-Gelais Fosses Septiques",
    "wof:placetype":"venue"
},
  "geometry": {"coordinates":[-71.128113,48.315098],"type":"Point"}
}