{
  "type": "Feature",
  "properties": {
    "addr:full":"1944 Queen St E Toronto ON M4L 1H6",
    "addr:housenumber":"1944",
    "addr:postcode":"m4l 1h6",
    "addr:street":"Queen St E",
    "iso:country":"CA",
    "sg:address":"1944 Queen St E",
    "sg:city":"Toronto",
    "sg:classifiers":[
        {
            "category":"Shopping",
            "subcategory":"Optical Goods",
            "type":"Retail Goods"
        }
    ],
    "sg:phone":"+1 416 699 3407",
    "sg:postcode":"M4L 1H6",
    "sg:province":"ON",
    "sg:tags":[
        "optician"
    ],
    "wof:name":"Envy Eyewear",
    "wof:placetype":"venue"
},
  "geometry": {"coordinates":[-79.302925,43.66954],"type":"Point"}
}