{
  "type": "Feature",
  "properties": {
    "addr:full":"1120 Rogers Way Kamloops BC V1S 1N5",
    "addr:housenumber":"1120",
    "addr:postcode":"bc v1s 1n5",
    "addr:street":"Rogers Way",
    "iso:country":"CA",
    "sg:address":"1120 Rogers Way",
    "sg:city":"Kamloops",
    "sg:classifiers":[
        {
            "category":"Autos & Motor Vehicles",
            "subcategory":"Fuel & Gas Station",
            "type":"Retail Goods"
        }
    ],
    "sg:phone":"+1 250 374 3230",
    "sg:postcode":"V1S 1N5",
    "sg:province":"BC",
    "sg:tags":[
        "oil"
    ],
    "wof:name":"Aberdeen Esso",
    "wof:placetype":"venue"
},
  "geometry": {"coordinates":[-120.367599,50.652042],"type":"Point"}
}