{
  "type": "Feature",
  "properties": {
    "addr:full":"3501 Route 113 N Desmaraisville QC J0Y 1H0",
    "addr:housenumber":"3501",
    "addr:postcode":"j0y 1h0",
    "addr:street":"Route 113 N",
    "iso:country":"CA",
    "sg:address":"3501 Route 113 N",
    "sg:city":"Desmaraisville",
    "sg:classifiers":[
        {
            "category":"Bars & Pubs",
            "type":"Food & Drink"
        }
    ],
    "sg:phone":"+1 819 753 2906",
    "sg:postcode":"J0Y 1H0",
    "sg:province":"QC",
    "sg:tags":[
        "lounge",
        "cocktail"
    ],
    "wof:name":"Bar Ti-Cossins",
    "wof:placetype":"venue"
},
  "geometry": {"coordinates":[-76.188255,49.50795],"type":"Point"}
}