{
  "type": "Feature",
  "properties": {
    "iso:country":"CA",
    "sg:address":"2340 Rue DE Salaberry",
    "sg:city":"Montreal",
    "sg:classifiers":[
        {
            "category":"Personal",
            "subcategory":"Beauty Salon",
            "type":"Services"
        }
    ],
    "sg:phone":"+1 514 332 3988",
    "sg:postcode":"H3M 1K9",
    "sg:province":"QC",
    "wof:name":"Salon Gaby Haboury Coiffure",
    "wof:placetype":"venue"
},
  "geometry": {"coordinates":[-73.6980209351,45.5386886597],"type":"Point"}
}