{
  "type": "Feature",
  "properties": {
    "addr:full":"8724 Rue Saint-Denis Montreal QC H2M 1N2",
    "addr:housenumber":"8724",
    "addr:postcode":"h2m 1n2",
    "addr:street":"Rue Saint-Denis",
    "iso:country":"CA",
    "sg:address":"8724 Rue Saint-Denis",
    "sg:city":"Montreal",
    "sg:classifiers":[
        {
            "category":"Shopping",
            "subcategory":"Bicycles & Sporting Goods",
            "type":"Retail Goods"
        }
    ],
    "sg:phone":"+1 514 384 9040",
    "sg:postcode":"H2M 1N2",
    "sg:province":"QC",
    "wof:name":"Laverdure Lucien Inc",
    "wof:placetype":"venue"
},
  "geometry": {"coordinates":[-73.6393661499,45.5454101562],"type":"Point"}
}