{
  "type": "Feature",
  "properties": {
    "addr:full":"35 Ch Victoria O Scotstown QC J0B 3B0",
    "addr:housenumber":"35",
    "addr:postcode":"j0b 3b0",
    "addr:street":"Ch Victoria O",
    "iso:country":"CA",
    "sg:address":"35 Ch Victoria O",
    "sg:city":"Scotstown",
    "sg:classifiers":[
        {
            "category":"Travel",
            "subcategory":"Hotels & Motels",
            "type":"Entertainment"
        }
    ],
    "sg:phone":"+1 819 657 4974",
    "sg:postcode":"J0B 3B0",
    "sg:province":"QC",
    "wof:name":"Hotel Scotstown",
    "wof:placetype":"venue"
},
  "geometry": {"coordinates":[-71.27258300779999,45.5287971497],"type":"Point"}
}