{
  "type": "Feature",
  "properties": {
    "addr:full":"1 Spencer St Picton ON K0K 2T0",
    "addr:housenumber":"1",
    "addr:postcode":"k0k 2t0",
    "addr:street":"Spencer St",
    "iso:country":"CA",
    "sg:address":"1 Spencer St",
    "sg:city":"Picton",
    "sg:classifiers":[
        {
            "category":"Health Services",
            "subcategory":"Doctor",
            "type":"Services"
        }
    ],
    "sg:phone":"+1 613 476 5766",
    "sg:postcode":"K0K 2T0",
    "sg:province":"ON",
    "sg:tags":[
        "physician",
        "surgeon"
    ],
    "wof:name":"Burke, Graham MD",
    "wof:placetype":"venue"
},
  "geometry": {"coordinates":[-77.13585662840001,44.016658783],"type":"Point"}
}