{
  "type": "Feature",
  "properties": {
    "addr:full":"PO Box 810 Fox Creek AB T0H 1P0",
    "addr:housenumber":"po;810",
    "addr:postcode":"ab t0h 1p0",
    "addr:street":"Box;Creek",
    "iso:country":"CA",
    "sg:address":"PO Box 810",
    "sg:city":"Fox Creek",
    "sg:classifiers":[
        {
            "category":"Organizations",
            "subcategory":"Religious Organization",
            "type":"Services"
        }
    ],
    "sg:phone":"+1 403 622 4279",
    "sg:postcode":"T0H 1P0",
    "sg:province":"AB",
    "sg:tags":[
        "church"
    ],
    "wof:name":"Fox Creek Baptist Church",
    "wof:placetype":"venue"
},
  "geometry": {"coordinates":[-116.809898,54.413643],"type":"Point"}
}