{
  "type": "Feature",
  "properties": {
    "addr:full":"226 Upper Lake St Picton ON K0K 2T0",
    "addr:housenumber":"226",
    "addr:postcode":"k0k 2t0",
    "addr:street":"Upper Lake St",
    "iso:country":"CA",
    "sg:address":"226 Upper Lake St",
    "sg:city":"Picton",
    "sg:classifiers":[
        {
            "category":"Home & Garden",
            "subcategory":"Building Materials",
            "type":"Retail Goods"
        }
    ],
    "sg:phone":"+1 613 476 2848",
    "sg:postcode":"K0K 2T0",
    "sg:province":"ON",
    "sg:tags":[
        "mixed",
        "concrete"
    ],
    "wof:name":"Power Concrete Products Ltd",
    "wof:placetype":"venue"
},
  "geometry": {"coordinates":[-77.1567993164,43.9927368164],"type":"Point"}
}