{
  "type": "Feature",
  "properties": {
    "addr:full":"795 Boul Industriel Granby QC J2G 9A1",
    "addr:housenumber":"795",
    "addr:postcode":"j2g 9a1",
    "addr:street":"Boul Industriel",
    "iso:country":"CA",
    "sg:address":"795 Boul Industriel",
    "sg:city":"Granby",
    "sg:classifiers":[
        {
            "category":"Wholesale",
            "subcategory":"Electrical",
            "type":"Manufacturing & Wholesale Goods"
        }
    ],
    "sg:phone":"+1 514 875 5861",
    "sg:postcode":"J2G 9A1",
    "sg:province":"QC",
    "sg:tags":[
        "transformer"
    ],
    "wof:name":"Transformateur Delta Du Canada",
    "wof:placetype":"venue"
},
  "geometry": {"coordinates":[-72.755234,45.389336],"type":"Point"}
}