{
  "type": "Feature",
  "properties": {
    "addr:full":"301 Front St W Toronto ON M5V 2T6",
    "addr:housenumber":"301",
    "addr:postcode":"m5v 2t6",
    "addr:street":"Front St W",
    "iso:country":"CA",
    "sg:address":"301 Front St W",
    "sg:city":"Toronto",
    "sg:classifiers":[
        {
            "category":"Communications",
            "subcategory":"Radio Station",
            "type":"Services"
        }
    ],
    "sg:phone":"+1 416 867 1063",
    "sg:postcode":"M5V 2T6",
    "sg:province":"ON",
    "sg:tags":[
        "company",
        "broadcasting"
    ],
    "wof:name":"Cjez",
    "wof:placetype":"venue"
},
  "geometry": {"coordinates":[-79.388245,43.643925],"type":"Point"}
}