{
  "type": "Feature",
  "properties": {
    "addr:full":"1178 Albert St Regina SK S4R 2R1",
    "addr:housenumber":"1178",
    "addr:postcode":"s4r 2r1",
    "addr:street":"Albert St",
    "iso:country":"CA",
    "sg:address":"1178 Albert St",
    "sg:city":"Regina",
    "sg:classifiers":[
        {
            "category":"Shopping",
            "subcategory":"Used Merchandise",
            "type":"Retail Goods"
        }
    ],
    "sg:phone":"+1 306 757 4265",
    "sg:postcode":"S4R 2R1",
    "sg:province":"SK",
    "sg:tags":[
        "antique"
    ],
    "wof:name":"Affinity's Antiques",
    "wof:placetype":"venue"
},
  "geometry": {"coordinates":[-104.618438721,50.4602661133],"type":"Point"}
}