{
  "type": "Feature",
  "properties": {
    "addr:full":"44816 Harriston Rd Gorrie ON N0G 1X0",
    "addr:postcode":"44816;n0g 1x0",
    "addr:street":"Harriston Rd",
    "iso:country":"CA",
    "sg:address":"44816 Harriston Rd",
    "sg:city":"Gorrie",
    "sg:classifiers":[
        {
            "category":"Government",
            "subcategory":"Office",
            "type":"Public Place"
        }
    ],
    "sg:phone":"+1 519 335 3208",
    "sg:postcode":"N0G 1X0",
    "sg:province":"ON",
    "sg:tags":[
        "municipality"
    ],
    "wof:name":"Howick Municipal Office",
    "wof:placetype":"venue"
},
  "geometry": {"coordinates":[-81.10972595210001,43.8727607727],"type":"Point"}
}