{
  "type": "Feature",
  "properties": {
    "iso:country":"CA",
    "sg:address":"452 Wyandotte St W",
    "sg:city":"Windsor",
    "sg:classifiers":[
        {
            "category":"Cinema",
            "subcategory":"Movie Rental",
            "type":"Entertainment"
        }
    ],
    "sg:phone":"+1 519 252 9988",
    "sg:postcode":"N9A 5X4",
    "sg:province":"ON",
    "sg:tags":[
        "leasing",
        "video",
        "disc",
        "tape"
    ],
    "wof:name":"Asia Fortune Gifts & Video",
    "wof:placetype":"venue"
},
  "geometry": {"coordinates":[-83.0413894653,42.3126449585],"type":"Point"}
}