{
  "type": "Feature",
  "properties": {
    "addr:full":"1019 Nelson St Oshawa ON L1H 7N9",
    "addr:housenumber":"1019",
    "addr:postcode":"l1h 7n9",
    "addr:street":"Nelson St",
    "iso:country":"CA",
    "sg:address":"1019 Nelson St",
    "sg:city":"Oshawa",
    "sg:classifiers":[
        {
            "category":"Wholesale",
            "subcategory":"Machinery & Supplies",
            "type":"Manufacturing & Wholesale Goods"
        }
    ],
    "sg:phone":"+1 905 436 7366",
    "sg:postcode":"L1H 7N9",
    "sg:province":"ON",
    "sg:tags":[
        "pipe",
        "plumbing",
        "fitting",
        "fixture"
    ],
    "wof:name":"Crane Supply",
    "wof:placetype":"venue"
},
  "geometry": {"coordinates":[-78.8369979858,43.8747787476],"type":"Point"}
}