{
  "type": "Feature",
  "properties": {
    "addr:full":"762 Rue Saint-Michel Terrebonne QC J6W 3K3",
    "addr:housenumber":"762",
    "addr:postcode":"j6w 3k3",
    "addr:street":"Rue Saint-Michel",
    "iso:country":"CA",
    "sg:address":"762 Rue Saint-Michel",
    "sg:city":"Terrebonne",
    "sg:classifiers":[
        {
            "category":"Personal",
            "subcategory":"Beauty Salon",
            "type":"Services"
        }
    ],
    "sg:phone":"+1 450 492 4876",
    "sg:postcode":"J6W 3K3",
    "sg:province":"QC",
    "wof:name":"Maison DE LA Coupe Enr",
    "wof:placetype":"venue"
},
  "geometry": {"coordinates":[-73.6424713135,45.6988182068],"type":"Point"}
}