{
  "type": "Feature",
  "properties": {
    "addr:full":"95 Av Horne Rouyn-Noranda QC J9X 4S4",
    "addr:postcode":"j9x 4s4",
    "addr:street":"95 Av Horne",
    "iso:country":"CA",
    "sg:address":"95 Av Horne",
    "sg:city":"Rouyn-Noranda",
    "sg:classifiers":[
        {
            "category":"Travel",
            "subcategory":"Hotels & Motels",
            "type":"Entertainment"
        }
    ],
    "sg:phone":"+1 819 762 0725",
    "sg:postcode":"J9X 4S4",
    "sg:province":"QC",
    "wof:name":"Motel DE Ville",
    "wof:placetype":"venue"
},
  "geometry": {"coordinates":[-79.02108800000001,48.241318],"type":"Point"}
}