{
  "type": "Feature",
  "properties": {
    "addr:full":"8075 Boul Taschereau Brossard QC J4Y 1A4",
    "addr:housenumber":"8075",
    "addr:postcode":"j4y 1a4",
    "addr:street":"Boul Taschereau",
    "iso:country":"CA",
    "sg:address":"8075 Boul Taschereau",
    "sg:city":"Brossard",
    "sg:classifiers":[
        {
            "category":"Social Services",
            "subcategory":"Child Care",
            "type":"Services"
        }
    ],
    "sg:phone":"+1 450 676 4600",
    "sg:postcode":"J4Y 1A4",
    "sg:province":"QC",
    "wof:name":"Garderie Chateau DE Reve",
    "wof:placetype":"venue"
},
  "geometry": {"coordinates":[-73.4680175781,45.4496231079],"type":"Point"}
}