{
  "type": "Feature",
  "properties": {
    "addr:full":"1185 Boul Moody Terrebonne QC J6W 3Z5",
    "addr:housenumber":"1185",
    "addr:postcode":"j6w 3z5",
    "addr:street":"Boul Moody",
    "iso:country":"CA",
    "sg:address":"1185 Boul Moody",
    "sg:city":"Terrebonne",
    "sg:classifiers":[
        {
            "category":"Shopping",
            "type":"Retail Goods"
        }
    ],
    "sg:phone":"+1 450 492 4664",
    "sg:postcode":"J6W 3Z5",
    "sg:province":"QC",
    "sg:tags":[
        "cosmetic",
        "perfume"
    ],
    "wof:name":"Parfumerie Karen",
    "wof:placetype":"venue"
},
  "geometry": {"coordinates":[-73.64804100000001,45.702183],"type":"Point"}
}