{
  "type": "Feature",
  "properties": {
    "addr:full":"227 Rue Saint-Germain E Rimouski QC G5L 1B5",
    "addr:housenumber":"227",
    "addr:postcode":"g5l 1b5",
    "addr:street":"Rue Saint-Germain E",
    "iso:country":"CA",
    "sg:address":"227 Rue Saint-Germain E",
    "sg:city":"Rimouski",
    "sg:classifiers":[
        {
            "category":"Home & Garden",
            "subcategory":"Building Materials",
            "type":"Retail Goods"
        }
    ],
    "sg:phone":"+1 418 723 3230",
    "sg:postcode":"G5L 1B5",
    "sg:province":"QC",
    "sg:tags":[
        "glass",
        "window",
        "plate"
    ],
    "wof:name":"Centre Du Pare-Brise Enr",
    "wof:placetype":"venue"
},
  "geometry": {"coordinates":[-68.518677,48.456078],"type":"Point"}
}