{
  "type": "Feature",
  "properties": {
    "addr:full":"Saint-Guillaume QC J0C 1L0",
    "addr:postcode":"j0c 1l0",
    "iso:country":"CA",
    "sg:city":"Saint-Guillaume",
    "sg:classifiers":[
        {
            "category":"Organizations",
            "subcategory":"Religious Organization",
            "type":"Services"
        }
    ],
    "sg:phone":"+1 819 396 2469",
    "sg:postcode":"J0C 1L0",
    "sg:province":"QC",
    "wof:name":"Freres DE St-Gabriel",
    "wof:placetype":"venue"
},
  "geometry": {"coordinates":[-72.766571,45.881668],"type":"Point"}
}