{
  "type": "Feature",
  "properties": {
    "iso:country":"CA",
    "sg:address":"93 Ch DE LA Riviere",
    "sg:city":"Saint-Etienne-DE-Beauharnois",
    "sg:classifiers":[
        {
            "category":"Building & Trades",
            "subcategory":"Construction",
            "type":"Services"
        }
    ],
    "sg:phone":"+1 450 429 5994",
    "sg:postcode":"J0S 1S0",
    "sg:province":"QC",
    "sg:tags":[
        "concrete",
        "stucco",
        "contractor"
    ],
    "wof:name":"Finitions Mercier Inc",
    "wof:placetype":"venue"
},
  "geometry": {"coordinates":[-73.918159,45.251266],"type":"Point"}
}