{
  "type": "Feature",
  "properties": {
    "addr:full":"32 Beckwith St Carleton Place ON K7C 2T2",
    "addr:housenumber":"32",
    "addr:postcode":"k7c 2t2",
    "addr:street":"Beckwith St",
    "iso:country":"CA",
    "sg:address":"32 Beckwith St",
    "sg:city":"Carleton Place",
    "sg:classifiers":[
        {
            "category":"Professional",
            "subcategory":"Lawyer & Legal Services",
            "type":"Services"
        }
    ],
    "sg:phone":"+1 613 257 1655",
    "sg:postcode":"K7C 2T2",
    "sg:province":"ON",
    "sg:tags":[
        "attorney"
    ],
    "wof:name":"Bennett, Kenneth J",
    "wof:placetype":"venue"
},
  "geometry": {"coordinates":[-76.14241,45.137829],"type":"Point"}
}