{
  "type": "Feature",
  "properties": {
    "addr:full":"1575 Onoadaga Rd Ohsweken ON N0A 1M0",
    "addr:housenumber":"1575",
    "addr:postcode":"n0a 1m0",
    "addr:street":"Onoadaga Rd",
    "iso:country":"CA",
    "sg:address":"1575 Onoadaga Rd",
    "sg:city":"Ohsweken",
    "sg:classifiers":[
        {
            "category":"Education",
            "subcategory":"School",
            "type":"Public Place"
        }
    ],
    "sg:phone":"+1 519 445 4665",
    "sg:postcode":"N0A 1M0",
    "sg:province":"ON",
    "wof:name":"Emily C General Elementary",
    "wof:placetype":"venue"
},
  "geometry": {"coordinates":[-80.11879730219999,43.0690460205],"type":"Point"}
}