{
  "type": "Feature",
  "properties": {
    "addr:full":"1184 Conrad Ave Gull Lake SK S0N 1A0",
    "addr:housenumber":"1184",
    "addr:postcode":"s0n 1a0",
    "addr:street":"Conrad Ave",
    "iso:country":"CA",
    "sg:address":"1184 Conrad Ave",
    "sg:city":"Gull Lake",
    "sg:classifiers":[
        {
            "category":"Government",
            "subcategory":"Office",
            "type":"Public Place"
        }
    ],
    "sg:phone":"+1 306 672 4430",
    "sg:postcode":"S0N 1A0",
    "sg:province":"SK",
    "sg:tags":[
        "municipality"
    ],
    "wof:name":"Rural Municipality-Gull Lake",
    "wof:placetype":"venue"
},
  "geometry": {"coordinates":[-108.48629800000001,50.094341],"type":"Point"}
}