{
  "type": "Feature",
  "properties": {
    "addr:full":"1630 Dundas St London ON N5W 3C4",
    "addr:housenumber":"1630",
    "addr:postcode":"n5w 3c4",
    "addr:street":"Dundas St",
    "iso:country":"CA",
    "sg:address":"1630 Dundas St",
    "sg:city":"London",
    "sg:classifiers":[
        {
            "category":"Shopping",
            "subcategory":"Discount & Variety Stores",
            "type":"Retail Goods"
        }
    ],
    "sg:phone":"+1 519 659 7400",
    "sg:postcode":"N5W 3C4",
    "sg:province":"ON",
    "wof:name":"Canada Variety",
    "wof:placetype":"venue"
},
  "geometry": {"coordinates":[-81.190849,43.000656],"type":"Point"}
}