{
  "type": "Feature",
  "properties": {
    "addr:full":"3881 Boul Saint-Jean Dollard-Des-Ormeaux QC H9G 2V1",
    "addr:housenumber":"3881",
    "addr:postcode":"h9g 2v1",
    "addr:street":"Boul Saint-Jean",
    "iso:country":"CA",
    "sg:address":"3881 Boul Saint-Jean",
    "sg:city":"Dollard-Des-Ormeaux",
    "sg:classifiers":[
        {
            "category":"Health Services",
            "subcategory":"Doctor",
            "type":"Services"
        }
    ],
    "sg:phone":"+1 514 624 0444",
    "sg:postcode":"H9G 2V1",
    "sg:province":"QC",
    "sg:tags":[
        "clinic"
    ],
    "wof:name":"Centre D'Ortopedie & Medicine",
    "wof:placetype":"venue"
},
  "geometry": {"coordinates":[-73.83665466310001,45.4753341675],"type":"Point"}
}