{
  "type": "Feature",
  "properties": {
    "addr:full":"223 Forsyth St N Sarnia ON N7T 6E3",
    "addr:housenumber":"223",
    "addr:postcode":"n7t 6e3",
    "addr:street":"Forsyth St N",
    "iso:country":"CA",
    "sg:address":"223 Forsyth St N",
    "sg:city":"Sarnia",
    "sg:classifiers":[
        {
            "category":"Professional",
            "subcategory":"Business Services",
            "type":"Services"
        }
    ],
    "sg:phone":"+1 519 336 9996",
    "sg:postcode":"N7T 6E3",
    "sg:province":"ON",
    "sg:tags":[
        "arbitration"
    ],
    "wof:name":"Five Arrows Consulting Inc",
    "wof:placetype":"venue"
},
  "geometry": {"coordinates":[-82.400749,42.97451],"type":"Point"}
}