{
  "type": "Feature",
  "properties": {
    "addr:full":"27060 20 Ave Langley BC V4W 2P1",
    "addr:housenumber":"27060",
    "addr:postcode":"v4w 2p1",
    "addr:street":"20 Ave",
    "iso:country":"CA",
    "sg:address":"27060 20 Ave",
    "sg:city":"Langley",
    "sg:classifiers":[
        {
            "category":"Building & Trades",
            "subcategory":"Construction",
            "type":"Services"
        }
    ],
    "sg:phone":"+1 604 607 6654",
    "sg:postcode":"V4W 2P1",
    "sg:province":"BC",
    "sg:tags":[
        "boring",
        "drilling",
        "contractor"
    ],
    "wof:name":"Tds/Trenchless Drilling Svc",
    "wof:placetype":"venue"
},
  "geometry": {"coordinates":[-122.473816,49.03841],"type":"Point"}
}