{
  "type": "Feature",
  "properties": {
    "addr:full":"1413 Edward St S Thunder Bay ON P7E 2J5",
    "addr:housenumber":"1413",
    "addr:postcode":"p7e 2j5",
    "addr:street":"Edward St S",
    "iso:country":"CA",
    "sg:address":"1413 Edward St S",
    "sg:city":"Thunder Bay",
    "sg:classifiers":[
        {
            "category":"Retail",
            "subcategory":"Laundry & Dry Cleaning",
            "type":"Services"
        }
    ],
    "sg:phone":"+1 807 475 7363",
    "sg:postcode":"P7E 2J5",
    "sg:province":"ON",
    "sg:tags":[
        "cleaners"
    ],
    "wof:name":"Westfort Laundromat",
    "wof:placetype":"venue"
},
  "geometry": {"coordinates":[-89.27866363530001,48.3659515381],"type":"Point"}
}