{
  "type": "Feature",
  "properties": {
    "iso:country":"CA",
    "sg:address":"330 Rue Principale",
    "sg:city":"Granby",
    "sg:classifiers":[
        {
            "category":"Recreation",
            "type":"Entertainment"
        }
    ],
    "sg:phone":"+1 450 777 1033",
    "sg:postcode":"J2G 2W4",
    "sg:province":"QC",
    "sg:tags":[
        "lounge",
        "parlor",
        "billiard",
        "cocktail"
    ],
    "wof:name":"Bar Salon Billard DE Granby",
    "wof:placetype":"venue"
},
  "geometry": {"coordinates":[-72.731086731,45.4017295837],"type":"Point"}
}