{
  "type": "Feature",
  "properties": {
    "addr:full":"1100 Commissioners Rd E London ON N5Z 4W8",
    "addr:housenumber":"1100",
    "addr:postcode":"n5z 4w8",
    "addr:street":"Commissioners Rd E",
    "iso:country":"CA",
    "sg:address":"1100 Commissioners Rd E",
    "sg:city":"London",
    "sg:classifiers":[
        {
            "category":"Cinema",
            "subcategory":"Movie Rental",
            "type":"Entertainment"
        }
    ],
    "sg:phone":"+1 519 668 3550",
    "sg:postcode":"N5Z 4W8",
    "sg:province":"ON",
    "sg:tags":[
        "video",
        "game",
        "tape",
        "leasing"
    ],
    "wof:name":"Blockbuster Video",
    "wof:placetype":"venue"
},
  "geometry": {"coordinates":[-81.19951629640001,42.9618492126],"type":"Point"}
}