{
  "type": "Feature",
  "properties": {
    "addr:full":"PO Box 43 Dewdney BC V0M 1H0",
    "addr:housenumber":"po box 43",
    "addr:postcode":"v0m 1h0",
    "iso:country":"CA",
    "sg:address":"PO Box 43",
    "sg:city":"Dewdney",
    "sg:classifiers":[
        {
            "category":"Building & Trades",
            "subcategory":"Construction",
            "type":"Services"
        }
    ],
    "sg:phone":"+1 604 826 6805",
    "sg:postcode":"V0M 1H0",
    "sg:province":"BC",
    "sg:tags":[
        "excavating",
        "contractor"
    ],
    "wof:name":"Brock Enterprises",
    "wof:placetype":"venue"
},
  "geometry": {"coordinates":[-122.20107299999999,49.160866],"type":"Point"}
}