{
  "type": "Feature",
  "properties": {
    "addr:full":"59 Walker St Truro NS B2N 4A8",
    "addr:housenumber":"59",
    "addr:postcode":"b2n 4a8",
    "addr:street":"Walker St",
    "iso:country":"CA",
    "sg:address":"59 Walker St",
    "sg:city":"Truro",
    "sg:classifiers":[
        {
            "category":"Personal",
            "subcategory":"Beauty Salon",
            "type":"Services"
        }
    ],
    "sg:phone":"+1 902 893 2085",
    "sg:postcode":"B2N 4A8",
    "sg:province":"NS",
    "wof:name":"Lenore Beauty Shop",
    "wof:placetype":"venue"
},
  "geometry": {"coordinates":[-63.272572,45.365353],"type":"Point"}
}