{
  "type": "Feature",
  "properties": {
    "addr:full":"276 Av Allard Dorval QC H9S 3B9",
    "addr:housenumber":"276",
    "addr:postcode":"h9s 3b9",
    "addr:street":"Av Allard",
    "iso:country":"CA",
    "sg:address":"276 Av Allard",
    "sg:city":"Dorval",
    "sg:classifiers":[
        {
            "category":"Building & Trades",
            "subcategory":"Construction",
            "type":"Services"
        }
    ],
    "sg:phone":"+1 514 631 5124",
    "sg:postcode":"H9S 3B9",
    "sg:province":"QC",
    "sg:tags":[
        "tennis",
        "court"
    ],
    "wof:name":"Showcourt International Entrps",
    "wof:placetype":"venue"
},
  "geometry": {"coordinates":[-73.751755,45.443932],"type":"Point"}
}