{
  "type": "Feature",
  "properties": {
    "addr:full":"NE 24-12-13W Austin MB R0H 0C0",
    "addr:postcode":"r0h 0c0",
    "addr:street":"Ne 24-12-13W",
    "iso:country":"CA",
    "sg:address":"NE 24-12-13W",
    "sg:city":"Austin",
    "sg:classifiers":[
        {
            "category":"Communications",
            "subcategory":"Film & Video Production",
            "type":"Services"
        }
    ],
    "sg:phone":"+1 204 466 2904",
    "sg:postcode":"R0H 0C0",
    "sg:province":"MB",
    "sg:tags":[
        "taping"
    ],
    "wof:name":"Rural Route Videos",
    "wof:placetype":"venue"
},
  "geometry": {"coordinates":[-98.936348,49.950375],"type":"Point"}
}