{
  "type": "Feature",
  "properties": {
    "iso:country":"CA",
    "sg:address":"3920 35A Ave",
    "sg:city":"Red Deer",
    "sg:classifiers":[
        {
            "category":"Building & Trades",
            "subcategory":"Construction",
            "type":"Services"
        }
    ],
    "sg:phone":"+1 403 341 3524",
    "sg:postcode":"T4N 2S5",
    "sg:province":"AB",
    "sg:tags":[
        "painter"
    ],
    "wof:name":"Roger's Home Decorating",
    "wof:placetype":"venue"
},
  "geometry": {"coordinates":[-113.779388,52.260406],"type":"Point"}
}