{
  "type": "Feature",
  "properties": {
    "iso:country":"CA",
    "sg:address":"1805 Wilson Ave",
    "sg:city":"North York",
    "sg:classifiers":[
        {
            "category":"Shopping",
            "type":"Retail Goods"
        }
    ],
    "sg:phone":"+1 416 742 9332",
    "sg:postcode":"M9M 1A2",
    "sg:province":"ON",
    "sg:tags":[
        "equipment",
        "telephone",
        "supply"
    ],
    "wof:name":"Bci Networks",
    "wof:placetype":"venue"
},
  "geometry": {"coordinates":[-79.522141,43.717777],"type":"Point"}
}