{
  "type": "Feature",
  "properties": {
    "addr:full":"332 Front St Eastend SK S0N 0T0",
    "addr:housenumber":"332",
    "addr:postcode":"s0n 0t0",
    "addr:street":"Front St",
    "iso:country":"CA",
    "sg:address":"332 Front St",
    "sg:city":"Eastend",
    "sg:classifiers":[
        {
            "category":"Recreation",
            "type":"Entertainment"
        }
    ],
    "sg:phone":"+1 306 295 3560",
    "sg:postcode":"S0N 0T0",
    "sg:province":"SK",
    "sg:tags":[
        "center"
    ],
    "wof:name":"Eastend Rink Complex",
    "wof:placetype":"venue"
},
  "geometry": {"coordinates":[-108.828705,49.513657],"type":"Point"}
}