{
  "type": "Feature",
  "properties": {
    "addr:full":"1555 Buffalo Pl Winnipeg MB R3T 1L9",
    "addr:housenumber":"1555",
    "addr:postcode":"r3t 1l9",
    "addr:street":"Buffalo Pl",
    "iso:country":"CA",
    "sg:address":"1555 Buffalo Pl",
    "sg:city":"Winnipeg",
    "sg:classifiers":[
        {
            "category":"Food & Beverages",
            "subcategory":"Liquor & Beverages",
            "type":"Retail Goods"
        }
    ],
    "sg:phone":"+1 204 284 2501",
    "sg:postcode":"R3T 1L9",
    "sg:province":"MB",
    "sg:tags":[
        "store"
    ],
    "wof:name":"Liquor Control Commission",
    "wof:placetype":"venue"
},
  "geometry": {"coordinates":[-97.174538,49.835297],"type":"Point"}
}