{
  "type": "Feature",
  "properties": {
    "addr:full":"798 N Government St Hwy 3 Greenwood BC V0H 1J0",
    "addr:housenumber":"798",
    "addr:postcode":"v0h 1j0",
    "addr:street":"N Government St Hwy 3",
    "iso:country":"CA",
    "sg:address":"798 N Government St Hwy 3",
    "sg:city":"Greenwood",
    "sg:classifiers":[
        {
            "category":"Travel",
            "subcategory":"Hotels & Motels",
            "type":"Entertainment"
        }
    ],
    "sg:phone":"+1 250 445 6733",
    "sg:postcode":"V0H 1J0",
    "sg:province":"BC",
    "wof:name":"Evening Star Motel",
    "wof:placetype":"venue"
},
  "geometry": {"coordinates":[-118.67641399999999,49.106312],"type":"Point"}
}