{
  "type": "Feature",
  "properties": {
    "addr:full":"331 Queenston St St Catharines ON L2P 2X8",
    "addr:housenumber":"331",
    "addr:postcode":"l2p 2x8",
    "addr:street":"Queenston St",
    "iso:country":"CA",
    "sg:address":"331 Queenston St",
    "sg:city":"St Catharines",
    "sg:classifiers":[
        {
            "category":"Travel",
            "subcategory":"Travel Agent",
            "type":"Entertainment"
        }
    ],
    "sg:phone":"+1 905 682 2467",
    "sg:postcode":"L2P 2X8",
    "sg:province":"ON",
    "sg:tags":[
        "agency",
        "bureau"
    ],
    "wof:name":"Agm Travel",
    "wof:placetype":"venue"
},
  "geometry": {"coordinates":[-79.2160644531,43.1592903137],"type":"Point"}
}