{
  "type": "Feature",
  "properties": {
    "addr:full":"209 Allan Ave Saltcoats SK S0A 3R0",
    "addr:housenumber":"209",
    "addr:postcode":"s0a 3r0",
    "addr:street":"Allan Ave",
    "iso:country":"CA",
    "sg:address":"209 Allan Ave",
    "sg:city":"Saltcoats",
    "sg:classifiers":[
        {
            "category":"Retail",
            "subcategory":"Auto Repair",
            "type":"Services"
        }
    ],
    "sg:phone":"+1 306 744 2292",
    "sg:postcode":"S0A 3R0",
    "sg:province":"SK",
    "sg:tags":[
        "repairing",
        "automobile"
    ],
    "wof:name":"Saltcoats Farm & Auto",
    "wof:placetype":"venue"
},
  "geometry": {"coordinates":[-102.169204712,51.041229248],"type":"Point"}
}