{
  "type": "Feature",
  "properties": {
    "addr:full":"1060 Poplar Grove Rd Penticton BC V2A 8T6",
    "addr:housenumber":"1060",
    "addr:postcode":"v2a 8t6",
    "addr:street":"Poplar Grove Rd",
    "iso:country":"CA",
    "sg:address":"1060 Poplar Grove Rd",
    "sg:city":"Penticton",
    "sg:classifiers":[
        {
            "category":"Manufacturing",
            "subcategory":"Food",
            "type":"Manufacturing & Wholesale Goods"
        }
    ],
    "sg:phone":"+1 250 493 9463",
    "sg:postcode":"V2A 8T6",
    "sg:province":"BC",
    "sg:tags":[
        "winery"
    ],
    "wof:name":"Poplar Grove Winery",
    "wof:placetype":"venue"
},
  "geometry": {"coordinates":[-119.56562805199999,49.5330848694],"type":"Point"}
}