{
  "type": "Feature",
  "properties": {
    "addr:full":"748 Upland Hts Coldstream BC V1B 2X9",
    "addr:housenumber":"748",
    "addr:postcode":"bc v1b 2x9",
    "addr:street":"Upland Hts",
    "iso:country":"CA",
    "sg:address":"748 Upland Hts",
    "sg:city":"Coldstream",
    "sg:classifiers":[
        {
            "category":"Building & Trades",
            "subcategory":"Construction",
            "type":"Services"
        }
    ],
    "sg:phone":"+1 250 545 3971",
    "sg:postcode":"V1B 2X9",
    "sg:province":"BC",
    "sg:tags":[
        "general",
        "contractor"
    ],
    "wof:name":"Gavin Parsons Homes",
    "wof:placetype":"venue"
},
  "geometry": {"coordinates":[-119.215553,50.249275],"type":"Point"}
}