{
  "type": "Feature",
  "properties": {
    "iso:country":"CA",
    "sg:city":"Stoney Creek",
    "sg:classifiers":[
        {
            "category":"Home & Garden",
            "subcategory":"Furniture",
            "type":"Retail Goods"
        }
    ],
    "sg:phone":"+1 905 643 9292",
    "sg:postcode":"L8E 5Y7",
    "sg:province":"ON",
    "wof:name":"Leather Sofa Galleria",
    "wof:placetype":"venue"
},
  "geometry": {"coordinates":[-79.6561965942,43.2211112976],"type":"Point"}
}