{
  "type": "Feature",
  "properties": {
    "addr:full":"RR 2 STN Main Acton ON L7J 2L8",
    "addr:postcode":"l7j 2l8",
    "addr:street":"Rr 2 Stn",
    "iso:country":"CA",
    "sg:address":"RR 2 STN Main",
    "sg:city":"Acton",
    "sg:classifiers":[
        {
            "category":"Retail",
            "subcategory":"Animal Services",
            "type":"Services"
        }
    ],
    "sg:phone":"+1 519 833 2693",
    "sg:postcode":"L7J 2L8",
    "sg:province":"ON",
    "sg:tags":[
        "pet",
        "boarding",
        "sitting"
    ],
    "wof:name":"Lo Franco Kennels",
    "wof:placetype":"venue"
},
  "geometry": {"coordinates":[-80.0403289795,43.63073349],"type":"Point"}
}