{
  "type": "Feature",
  "properties": {
    "addr:full":"930 Park Ave Beausejour MB R0E 0C0",
    "addr:housenumber":"930",
    "addr:postcode":"r0e 0c0",
    "addr:street":"Park Ave",
    "iso:country":"CA",
    "sg:address":"930 Park Ave",
    "sg:city":"Beausejour",
    "sg:classifiers":[
        {
            "category":"Travel",
            "subcategory":"Hotels & Motels",
            "type":"Entertainment"
        }
    ],
    "sg:phone":"+1 204 268 1955",
    "sg:postcode":"R0E 0C0",
    "sg:province":"MB",
    "wof:name":"Beausejour Motel",
    "wof:placetype":"venue"
},
  "geometry": {"coordinates":[-96.509697,50.061779],"type":"Point"}
}