{
  "type": "Feature",
  "properties": {
    "addr:full":"1345 Rue Jacques-Cartier S Saint-Jean-Sur-Richelieu QC J3B 6Y8",
    "addr:housenumber":"1345",
    "addr:postcode":"j3b 6y8",
    "addr:street":"Rue Jacques-Cartier S",
    "iso:country":"CA",
    "sg:address":"1345 Rue Jacques-Cartier S",
    "sg:city":"Saint-Jean-Sur-Richelieu",
    "sg:classifiers":[
        {
            "category":"Manufacturing",
            "subcategory":"Metals",
            "type":"Manufacturing & Wholesale Goods"
        }
    ],
    "sg:phone":"+1 450 346 8050",
    "sg:postcode":"J3B 6Y8",
    "sg:province":"QC",
    "sg:tags":[
        "equipment",
        "fireplace"
    ],
    "wof:name":"Foyers Valcourt Inc",
    "wof:placetype":"venue"
},
  "geometry": {"coordinates":[-73.255005,45.237423],"type":"Point"}
}