{
  "type": "Feature",
  "properties": {
    "addr:full":"112 1/2 Osgoode St Ottawa ON K1N 6S2",
    "addr:housenumber":"112 1 / 2",
    "addr:postcode":"k1n 6s2",
    "addr:street":"St",
    "iso:country":"CA",
    "sg:address":"112 1/2 Osgoode St",
    "sg:city":"Ottawa",
    "sg:classifiers":[
        {
            "category":"Restaurant",
            "type":"Food & Drink"
        }
    ],
    "sg:phone":"+1 613 234 1173",
    "sg:postcode":"K1N 6S2",
    "sg:province":"ON",
    "wof:name":"Father & Sons Restaurant",
    "wof:placetype":"venue"
},
  "geometry": {"coordinates":[-75.681023,45.423744],"type":"Point"}
}