{
  "type": "Feature",
  "properties": {
    "addr:full":"698 King St E Hamilton ON L8M 1A3",
    "addr:housenumber":"698",
    "addr:postcode":"l8m 1a3",
    "addr:street":"King St E",
    "iso:country":"CA",
    "sg:address":"698 King St E",
    "sg:city":"Hamilton",
    "sg:classifiers":[
        {
            "category":"Banks & Credit Unions",
            "subcategory":"Bank",
            "type":"Services"
        }
    ],
    "sg:phone":"+1 905 529 9445",
    "sg:postcode":"L8M 1A3",
    "sg:province":"ON",
    "wof:name":"Hamilton Community Cu Ltd",
    "wof:placetype":"venue"
},
  "geometry": {"coordinates":[-79.846992,43.251686],"type":"Point"}
}