{
  "type": "Feature",
  "properties": {
    "addr:full":"1748 Base Line Rd W # 100 Courtice ON L1E 2T1",
    "addr:housenumber":"1748",
    "addr:postcode":"l1e 2t1",
    "addr:street":"Base Line Rd W # 100 Courtice",
    "iso:country":"CA",
    "sg:address":"1748 Base Line Rd W # 100",
    "sg:city":"Courtice",
    "sg:classifiers":[
        {
            "category":"Building & Trades",
            "subcategory":"Construction",
            "type":"Services"
        }
    ],
    "sg:phone":"+1 905 436 2600",
    "sg:postcode":"L1E 2T1",
    "sg:province":"ON",
    "sg:tags":[
        "contractor"
    ],
    "wof:name":"Halminen Homes",
    "wof:placetype":"venue"
},
  "geometry": {"coordinates":[-78.7650756836,43.8814315796],"type":"Point"}
}