{
  "type": "Feature",
  "properties": {
    "iso:country":"CA",
    "sg:address":"382 King St",
    "sg:city":"Midland",
    "sg:classifiers":[
        {
            "category":"Banks & Credit Unions",
            "subcategory":"Financial Services",
            "type":"Services"
        }
    ],
    "sg:phone":"+1 705 528 6988",
    "sg:postcode":"L4R 3M9",
    "sg:province":"ON",
    "sg:tags":[
        "bankruptcy",
        "trustee"
    ],
    "wof:name":"Paddon & Yorke Inc",
    "wof:placetype":"venue"
},
  "geometry": {"coordinates":[-79.8828277588,44.7466087341],"type":"Point"}
}