{
  "type": "Feature",
  "properties": {
    "iso:country":"CA",
    "sg:address":"1611 14 St SW",
    "sg:city":"Calgary",
    "sg:classifiers":[
        {
            "category":"Shopping",
            "subcategory":"Gifts & Souvenirs",
            "type":"Retail Goods"
        }
    ],
    "sg:phone":"+1 403 209 8609",
    "sg:postcode":"T3C 1E3",
    "sg:province":"AB",
    "sg:tags":[
        "basket",
        "shop",
        "parcel"
    ],
    "wof:name":"Dragonfly Creations",
    "wof:placetype":"venue"
},
  "geometry": {"coordinates":[-114.09485599999999,51.038334],"type":"Point"}
}