{
  "type": "Feature",
  "properties": {
    "addr:full":"Longueuil QC J4G 1R3",
    "addr:postcode":"j4g 1r3",
    "iso:country":"CA",
    "sg:city":"Longueuil",
    "sg:classifiers":[
        {
            "category":"Organizations",
            "subcategory":"Professional Association",
            "type":"Services"
        }
    ],
    "sg:phone":"+1 450 442 9966",
    "sg:postcode":"J4G 1R3",
    "sg:province":"QC",
    "wof:name":"Salons DE Quilles Assoc Du QC",
    "wof:placetype":"venue"
},
  "geometry": {"coordinates":[-73.4763793945,45.5627479553],"type":"Point"}
}