{
  "type": "Feature",
  "properties": {
    "addr:full":"400 Boul Magenta E Farnham QC J2N 2S7",
    "addr:housenumber":"400",
    "addr:postcode":"j2n 2s7",
    "addr:street":"Boul Magenta E",
    "iso:country":"CA",
    "sg:address":"400 Boul Magenta E",
    "sg:city":"Farnham",
    "sg:classifiers":[
        {
            "category":"Real Estate",
            "subcategory":"Real Estate Operator",
            "type":"Services"
        }
    ],
    "sg:phone":"+1 450 293 3391",
    "sg:postcode":"J2N 2S7",
    "sg:province":"QC",
    "sg:tags":[
        "boarding",
        "house",
        "retirement",
        "community",
        "home"
    ],
    "wof:name":"Residences Magenta Inc",
    "wof:placetype":"venue"
},
  "geometry": {"coordinates":[-72.9742202759,45.2902412415],"type":"Point"}
}