{
  "type": "Feature",
  "properties": {
    "iso:country":"CA",
    "sg:address":"20 Nashville Ave",
    "sg:city":"York",
    "sg:classifiers":[
        {
            "category":"Professional",
            "subcategory":"Accounting & Tax Preparation",
            "type":"Services"
        }
    ],
    "sg:phone":"+1 416 663 8090",
    "sg:postcode":"M6M 1J1",
    "sg:province":"ON",
    "sg:tags":[
        "return",
        "filing"
    ],
    "wof:name":"Diluca & Assoc Accounting",
    "wof:placetype":"venue"
},
  "geometry": {"coordinates":[-79.475693,43.682926],"type":"Point"}
}