{
  "type": "Feature",
  "properties": {
    "addr:full":"781 Rang Saint-Francois O Lourdes QC G0S 1T0",
    "addr:housenumber":"781",
    "addr:postcode":"g0s 1t0",
    "addr:street":"Rang Saint-Francois O",
    "iso:country":"CA",
    "sg:address":"781 Rang Saint-Francois O",
    "sg:city":"Lourdes",
    "sg:classifiers":[
        {
            "category":"Autos & Motor Vehicles",
            "subcategory":"Automobile Sales",
            "type":"Retail Goods"
        }
    ],
    "sg:phone":"+1 819 385 4422",
    "sg:postcode":"G0S 1T0",
    "sg:province":"QC",
    "sg:tags":[
        "repairing",
        "car"
    ],
    "wof:name":"Garage P Bedard & Fils Inc",
    "wof:placetype":"venue"
},
  "geometry": {"coordinates":[-71.81989299999999,46.326809],"type":"Point"}
}