{
  "type": "Feature",
  "properties": {
    "iso:country":"CA",
    "sg:city":"Calgary",
    "sg:classifiers":[
        {
            "category":"Social Services",
            "subcategory":"Job Training",
            "type":"Services"
        }
    ],
    "sg:phone":"+1 403 266 6690",
    "sg:postcode":"T2P 2V7",
    "sg:province":"AB",
    "sg:tags":[
        "counseling",
        "management",
        "employment",
        "business",
        "consultant"
    ],
    "wof:name":"Right Management Consultants",
    "wof:placetype":"venue"
},
  "geometry": {"coordinates":[-114.065574646,51.0482673645],"type":"Point"}
}