{
  "type": "Feature",
  "properties": {
    "iso:country":"CA",
    "sg:address":"94 Rue Blainville O",
    "sg:city":"Sainte-Therese",
    "sg:classifiers":[
        {
            "category":"Health Services",
            "subcategory":"Doctor",
            "type":"Services"
        }
    ],
    "sg:phone":"+1 450 435 2843",
    "sg:postcode":"J7E 1X7",
    "sg:province":"QC",
    "sg:tags":[
        "physician",
        "surgeon"
    ],
    "wof:name":"Blaizel, Gilbert MD",
    "wof:placetype":"venue"
},
  "geometry": {"coordinates":[-73.834022522,45.6392707825],"type":"Point"}
}