{
  "type": "Feature",
  "properties": {
    "addr:full":"5923 4 Ave Edson AB T7E 1L9",
    "addr:housenumber":"5923",
    "addr:postcode":"t7e 1l9",
    "addr:street":"4 Ave",
    "iso:country":"CA",
    "sg:address":"5923 4 Ave",
    "sg:city":"Edson",
    "sg:classifiers":[
        {
            "category":"Professional",
            "subcategory":"Business Services",
            "type":"Services"
        }
    ],
    "sg:phone":"+1 780 723 7775",
    "sg:postcode":"T7E 1L9",
    "sg:province":"AB",
    "sg:tags":[
        "fire",
        "protection"
    ],
    "wof:name":"Safety Store & More Ltd",
    "wof:placetype":"venue"
},
  "geometry": {"coordinates":[-116.453773498,53.5768470764],"type":"Point"}
}