{
  "type": "Feature",
  "properties": {
    "iso:country":"CA",
    "sg:address":"2620 4 St NW",
    "sg:city":"Calgary",
    "sg:classifiers":[
        {
            "category":"Restaurant",
            "type":"Food & Drink"
        }
    ],
    "sg:phone":"+1 403 277 0096",
    "sg:postcode":"T2M 3A1",
    "sg:province":"AB",
    "sg:tags":[
        "pizza"
    ],
    "wof:name":"Karouzos Pizza Steak House",
    "wof:placetype":"venue"
},
  "geometry": {"coordinates":[-114.07128906200001,51.0753822327],"type":"Point"}
}