{
  "type": "Feature",
  "properties": {
    "addr:full":"121 Vansitmart Ave Hamilton ON L8H 3A6",
    "addr:housenumber":"121",
    "addr:postcode":"l8h 3a6",
    "addr:street":"Vansitmart Ave",
    "iso:country":"CA",
    "sg:address":"121 Vansitmart Ave",
    "sg:city":"Hamilton",
    "sg:classifiers":[
        {
            "category":"Building & Trades",
            "subcategory":"Construction",
            "type":"Services"
        }
    ],
    "sg:phone":"+1 905 547 7715",
    "sg:postcode":"L8H 3A6",
    "sg:province":"ON",
    "sg:tags":[
        "general",
        "contractor"
    ],
    "wof:name":"James Kemp Construction Ltd",
    "wof:placetype":"venue"
},
  "geometry": {"coordinates":[-79.8003997803,43.2493896484],"type":"Point"}
}