{
  "type": "Feature",
  "properties": {
    "addr:full":"44 Rue Du Chateau Saint-Luc QC J2W 1V2",
    "addr:housenumber":"44",
    "addr:postcode":"j2w 1v2",
    "addr:street":"Rue Du Chateau",
    "iso:country":"CA",
    "sg:address":"44 Rue Du Chateau",
    "sg:city":"Saint-Luc",
    "sg:classifiers":[
        {
            "category":"Communications",
            "subcategory":"Film & Video Production",
            "type":"Services"
        }
    ],
    "sg:phone":"+1 450 348 3533",
    "sg:postcode":"J2W 1V2",
    "sg:province":"QC",
    "sg:tags":[
        "taping"
    ],
    "wof:name":"Productions Video Jean Bedard",
    "wof:placetype":"venue"
},
  "geometry": {"coordinates":[-73.3017654419,45.3499641418],"type":"Point"}
}