{
  "type": "Feature",
  "properties": {
    "iso:country":"CA",
    "sg:address":"3 Queen St E",
    "sg:city":"Sault Ste Marie",
    "sg:classifiers":[
        {
            "category":"Insurance",
            "subcategory":"Insurance Agent",
            "type":"Services"
        }
    ],
    "sg:phone":"+1 705 759 9191",
    "sg:postcode":"P6A 1Y4",
    "sg:province":"ON",
    "wof:name":"North Star Brokers Inc",
    "wof:placetype":"venue"
},
  "geometry": {"coordinates":[-84.340965271,46.5174293518],"type":"Point"}
}