{
  "type": "Feature",
  "properties": {
    "addr:full":"103 Main St S Minnedosa MB R0J 1E0",
    "addr:housenumber":"103",
    "addr:postcode":"r0j 1e0",
    "addr:street":"Main St S Minnedosa",
    "iso:country":"CA",
    "sg:address":"103 Main St S",
    "sg:city":"Minnedosa",
    "sg:classifiers":[
        {
            "category":"Government",
            "subcategory":"Office",
            "type":"Public Place"
        }
    ],
    "sg:phone":"+1 204 867 2727",
    "sg:postcode":"R0J 1E0",
    "sg:province":"MB",
    "sg:tags":[
        "village"
    ],
    "wof:name":"Minnedosa Town Ofc",
    "wof:placetype":"venue"
},
  "geometry": {"coordinates":[-99.838768,50.247849],"type":"Point"}
}