{
  "type": "Feature",
  "properties": {
    "addr:full":"335 Seventh Ave S Williams Lake BC V2G 1L4",
    "addr:housenumber":"335",
    "addr:postcode":"v2g 1l4",
    "addr:street":"Seventh Ave S Williams",
    "iso:country":"CA",
    "sg:address":"335 Seventh Ave S",
    "sg:city":"Williams Lake",
    "sg:classifiers":[
        {
            "category":"Retail",
            "subcategory":"Auto Repair",
            "type":"Services"
        }
    ],
    "sg:phone":"+1 250 392 3345",
    "sg:postcode":"V2G 1L4",
    "sg:province":"BC",
    "sg:tags":[
        "repairing",
        "automobile"
    ],
    "wof:name":"North Shore Repair Ltd",
    "wof:placetype":"venue"
},
  "geometry": {"coordinates":[-122.136444,52.122993],"type":"Point"}
}