{
  "type": "Feature",
  "properties": {
    "addr:full":"16238 10 Ave Surrey BC V4A 1B1",
    "addr:housenumber":"16238",
    "addr:postcode":"v4a 1b1",
    "addr:street":"10 Ave",
    "iso:country":"CA",
    "sg:address":"16238 10 Ave",
    "sg:city":"Surrey",
    "sg:classifiers":[
        {
            "category":"Retail",
            "subcategory":"Animal Services",
            "type":"Services"
        }
    ],
    "sg:phone":"+1 604 576 3959",
    "sg:postcode":"V4A 1B1",
    "sg:province":"BC",
    "sg:tags":[
        "pet",
        "boarding",
        "sitting"
    ],
    "wof:name":"Ana Care Kennel & Pet Svc",
    "wof:placetype":"venue"
},
  "geometry": {"coordinates":[-122.772621,49.019966],"type":"Point"}
}