{
  "type": "Feature",
  "properties": {
    "addr:full":"398 Av Rouleau Rimouski QC G5L 5W5",
    "addr:postcode":"g5l 5w5",
    "addr:street":"398 Av Rouleau",
    "iso:country":"CA",
    "sg:address":"398 Av Rouleau",
    "sg:city":"Rimouski",
    "sg:classifiers":[
        {
            "category":"Food & Beverages",
            "subcategory":"Groceries & Convenience Stores",
            "type":"Retail Goods"
        }
    ],
    "sg:phone":"+1 418 724 9494",
    "sg:postcode":"G5L 5W5",
    "sg:province":"QC",
    "wof:name":"Depanneur Du Parc Inc",
    "wof:placetype":"venue"
},
  "geometry": {"coordinates":[-68.519257,48.438763],"type":"Point"}
}