{
  "type": "Feature",
  "properties": {
    "addr:full":"100 Fullarton St London ON N6A 1K1",
    "addr:housenumber":"100",
    "addr:postcode":"n6a 1k1",
    "addr:street":"Fullarton St",
    "iso:country":"CA",
    "sg:address":"100 Fullarton St",
    "sg:city":"London",
    "sg:classifiers":[
        {
            "category":"Professional",
            "subcategory":"Lawyer & Legal Services",
            "type":"Services"
        }
    ],
    "sg:phone":"+1 519 433 3195",
    "sg:postcode":"N6A 1K1",
    "sg:province":"ON",
    "sg:tags":[
        "attorney"
    ],
    "wof:name":"Portis, Mary F",
    "wof:placetype":"venue"
},
  "geometry": {"coordinates":[-81.2532577515,42.9848861694],"type":"Point"}
}