{
  "type": "Feature",
  "properties": {
    "iso:country":"CA",
    "sg:address":"13312 Rue Chelsea",
    "sg:city":"Pierrefonds",
    "sg:classifiers":[
        {
            "category":"Building & Trades",
            "subcategory":"Landscaping Services",
            "type":"Services"
        }
    ],
    "sg:phone":"+1 514 626 8164",
    "sg:postcode":"H9A 1A9",
    "sg:province":"QC",
    "sg:tags":[
        "tree",
        "landscape",
        "contractor"
    ],
    "wof:name":"Arborescence Dufour",
    "wof:placetype":"venue"
},
  "geometry": {"coordinates":[-73.844131,45.495941],"type":"Point"}
}