{
  "type": "Feature",
  "properties": {
    "addr:full":"49 River Rd Arnprior ON K7S 1R3",
    "addr:housenumber":"49",
    "addr:postcode":"k7s 1r3",
    "addr:street":"River Rd",
    "iso:country":"CA",
    "sg:address":"49 River Rd",
    "sg:city":"Arnprior",
    "sg:classifiers":[
        {
            "category":"Shopping",
            "subcategory":"Clothing, Apparel, & Fashions",
            "type":"Retail Goods"
        }
    ],
    "sg:phone":"+1 613 623 5608",
    "sg:postcode":"K7S 1R3",
    "sg:province":"ON",
    "sg:tags":[
        "dressmaker"
    ],
    "wof:name":"Sew on the Go",
    "wof:placetype":"venue"
},
  "geometry": {"coordinates":[-76.354355,45.422966],"type":"Point"}
}