{
  "type": "Feature",
  "properties": {
    "addr:full":"186 Peter St S Bothwell ON N0P 1C0",
    "addr:housenumber":"186",
    "addr:postcode":"n0p 1c0",
    "addr:street":"Peter St S",
    "iso:country":"CA",
    "sg:address":"186 Peter St S",
    "sg:city":"Bothwell",
    "sg:classifiers":[
        {
            "category":"Restaurant",
            "type":"Food & Drink"
        }
    ],
    "sg:phone":"+1 519 695 3400",
    "sg:postcode":"N0P 1C0",
    "sg:province":"ON",
    "wof:name":"L A Roadhouse Restaurant",
    "wof:placetype":"venue"
},
  "geometry": {"coordinates":[-81.866615,42.630817],"type":"Point"}
}