{
  "type": "Feature",
  "properties": {
    "addr:full":"1225 Finch Ave W North York ON M3J 2E8",
    "addr:housenumber":"1225",
    "addr:postcode":"m3j 2e8",
    "addr:street":"Finch Ave W",
    "iso:country":"CA",
    "sg:address":"1225 Finch Ave W",
    "sg:city":"North York",
    "sg:classifiers":[
        {
            "category":"Shopping",
            "subcategory":"Gifts & Souvenirs",
            "type":"Retail Goods"
        }
    ],
    "sg:phone":"+1 416 631 7688",
    "sg:postcode":"M3J 2E8",
    "sg:province":"ON",
    "sg:tags":[
        "party",
        "supply"
    ],
    "wof:name":"Party Packagers",
    "wof:placetype":"venue"
},
  "geometry": {"coordinates":[-79.484336853,43.7648200989],"type":"Point"}
}