{
  "type": "Feature",
  "properties": {
    "iso:country":"CA",
    "sg:city":"Elmvale",
    "sg:classifiers":[
        {
            "category":"Health Services",
            "subcategory":"Doctor",
            "type":"Services"
        }
    ],
    "sg:phone":"+1 705 322 1144",
    "sg:postcode":"L0L 1P0",
    "sg:province":"ON",
    "sg:tags":[
        "dentist"
    ],
    "wof:name":"Cole, Brian W DDS",
    "wof:placetype":"venue"
},
  "geometry": {"coordinates":[-79.8664093018,44.5823478699],"type":"Point"}
}