{
  "type": "Feature",
  "properties": {
    "addr:full":"Spruce Grove AB T7Y 1C3",
    "addr:postcode":"t7y 1c3",
    "iso:country":"CA",
    "sg:city":"Spruce Grove",
    "sg:classifiers":[
        {
            "category":"Recreation",
            "type":"Entertainment"
        }
    ],
    "sg:phone":"+1 780 470 0180",
    "sg:postcode":"T7Y 1C3",
    "sg:province":"AB",
    "sg:tags":[
        "hall",
        "auditorium"
    ],
    "wof:name":"Clymont Community League",
    "wof:placetype":"venue"
},
  "geometry": {"coordinates":[-113.901855,53.544636],"type":"Point"}
}