{
  "type": "Feature",
  "properties": {
    "iso:country":"CA",
    "sg:address":"145 Gill Dr",
    "sg:city":"Neepawa",
    "sg:classifiers":[
        {
            "category":"Building & Trades",
            "subcategory":"Plumbing",
            "type":"Services"
        }
    ],
    "sg:phone":"+1 204 476 3466",
    "sg:postcode":"R0J 1H0",
    "sg:province":"MB",
    "sg:tags":[
        "mechanical",
        "contractor"
    ],
    "wof:name":"Neepawa Plumbing & Heating",
    "wof:placetype":"venue"
},
  "geometry": {"coordinates":[-99.4651794434,50.2262382507],"type":"Point"}
}