{
  "type": "Feature",
  "properties": {
    "addr:full":"425 West St N Orillia ON L3V 7R2",
    "addr:housenumber":"425",
    "addr:postcode":"l3v 7r2",
    "addr:street":"West St N",
    "iso:country":"CA",
    "sg:address":"425 West St N",
    "sg:city":"Orillia",
    "sg:classifiers":[
        {
            "category":"Shopping",
            "subcategory":"Used Merchandise",
            "type":"Retail Goods"
        }
    ],
    "sg:phone":"+1 705 329 2041",
    "sg:postcode":"L3V 7R2",
    "sg:province":"ON",
    "sg:tags":[
        "charitable",
        "second",
        "institution",
        "store",
        "hand"
    ],
    "wof:name":"Goodwill",
    "wof:placetype":"venue"
},
  "geometry": {"coordinates":[-79.431999,44.622883],"type":"Point"}
}