{
  "type": "Feature",
  "properties": {
    "addr:full":"Calgary AB T2P 3E8",
    "addr:postcode":"t2p 3e8",
    "iso:country":"CA",
    "sg:city":"Calgary",
    "sg:classifiers":[
        {
            "category":"Professional",
            "subcategory":"Engineering",
            "type":"Services"
        }
    ],
    "sg:phone":"+1 403 221 8380",
    "sg:postcode":"T2P 3E8",
    "sg:province":"AB",
    "sg:tags":[
        "consultant",
        "oil",
        "gas"
    ],
    "wof:name":"Kinetic Engineering Ltd",
    "wof:placetype":"venue"
},
  "geometry": {"coordinates":[-114.078934,51.049896],"type":"Point"}
}