{
  "type": "Feature",
  "properties": {
    "addr:full":"5521 Boul Bourque Rock Forest QC J1N 1G8",
    "addr:housenumber":"5521",
    "addr:postcode":"j1n 1g8",
    "addr:street":"Boul Bourque",
    "iso:country":"CA",
    "sg:address":"5521 Boul Bourque",
    "sg:city":"Rock Forest",
    "sg:classifiers":[
        {
            "category":"Home & Garden",
            "subcategory":"Building Materials",
            "type":"Retail Goods"
        }
    ],
    "sg:phone":"+1 819 864 7231",
    "sg:postcode":"J1N 1G8",
    "sg:province":"QC",
    "sg:tags":[
        "glass",
        "window",
        "plate"
    ],
    "wof:name":"Boulevard Du Pare-Brise Inc",
    "wof:placetype":"venue"
},
  "geometry": {"coordinates":[-72.00165557859999,45.3640174866],"type":"Point"}
}