{
  "type": "Feature",
  "properties": {
    "addr:full":"1 Pico Cres Thornhill ON L4J 8P4",
    "addr:housenumber":"1",
    "addr:postcode":"l4j 8p4",
    "addr:street":"Pico Cres",
    "iso:country":"CA",
    "sg:address":"1 Pico Cres",
    "sg:city":"Thornhill",
    "sg:classifiers":[
        {
            "category":"Professional",
            "subcategory":"Management & Consulting",
            "type":"Services"
        }
    ],
    "sg:phone":"+1 905 839 0603",
    "sg:postcode":"L4J 8P4",
    "sg:province":"ON",
    "sg:tags":[
        "marketing",
        "consultant"
    ],
    "wof:name":"Techno Planet Productions Inc",
    "wof:placetype":"venue"
},
  "geometry": {"coordinates":[-79.460915,43.820721],"type":"Point"}
}