{
  "type": "Feature",
  "properties": {
    "addr:full":"4800 Rue DE Bullion Montreal QC H2T 1Y8",
    "addr:housenumber":"4800",
    "addr:postcode":"h2t 1y8",
    "addr:street":"Rue De Bullion",
    "iso:country":"CA",
    "sg:address":"4800 Rue DE Bullion",
    "sg:city":"Montreal",
    "sg:classifiers":[
        {
            "category":"Wholesale",
            "subcategory":"Meat",
            "type":"Manufacturing & Wholesale Goods"
        }
    ],
    "sg:phone":"+1 514 288 4188",
    "sg:postcode":"H2T 1Y8",
    "sg:province":"QC",
    "sg:tags":[
        "butchering"
    ],
    "wof:name":"Raphael & Freres",
    "wof:placetype":"venue"
},
  "geometry": {"coordinates":[-73.58799,45.523003],"type":"Point"}
}