{
  "type": "Feature",
  "properties": {
    "addr:full":"425 Av Pie-X Saint-Christophe-D'Arthabaska QC G6P 6S1",
    "addr:housenumber":"425",
    "addr:postcode":"g6p 6s1",
    "addr:street":"Av Pie-X",
    "iso:country":"CA",
    "sg:address":"425 Av Pie-X",
    "sg:city":"Saint-Christophe-D'Arthabaska",
    "sg:classifiers":[
        {
            "category":"Manufacturing",
            "subcategory":"Tools & Machinery",
            "type":"Manufacturing & Wholesale Goods"
        }
    ],
    "sg:phone":"+1 819 357 3560",
    "sg:postcode":"G6P 6S1",
    "sg:province":"QC",
    "sg:tags":[
        "machine",
        "shop"
    ],
    "wof:name":"Usinage Bois-Francs Inc",
    "wof:placetype":"venue"
},
  "geometry": {"coordinates":[-71.93277,46.030239],"type":"Point"}
}