{
  "type": "Feature",
  "properties": {
    "addr:full":"404 4th Ave Bowsman MB R0L 0H0",
    "addr:housenumber":"404",
    "addr:postcode":"r0l 0h0",
    "addr:street":"4Th Ave",
    "iso:country":"CA",
    "sg:address":"404 4th Ave",
    "sg:city":"Bowsman",
    "sg:classifiers":[
        {
            "category":"Education",
            "subcategory":"School",
            "type":"Public Place"
        }
    ],
    "sg:phone":"+1 204 238 4212",
    "sg:postcode":"R0L 0H0",
    "sg:province":"MB",
    "wof:name":"Bowsman School",
    "wof:placetype":"venue"
},
  "geometry": {"coordinates":[-101.21681213399999,52.2358474731],"type":"Point"}
}