{
  "type": "Feature",
  "properties": {
    "addr:full":"8829 Rue Pascal-Gagnon Saint-Leonard QC H1P 1Z4",
    "addr:housenumber":"8829",
    "addr:postcode":"h1p 1z4",
    "addr:street":"Rue Pascal-Gagnon",
    "iso:country":"CA",
    "sg:address":"8829 Rue Pascal-Gagnon",
    "sg:city":"Saint-Leonard",
    "sg:classifiers":[
        {
            "category":"Manufacturing",
            "subcategory":"Tools & Machinery",
            "type":"Manufacturing & Wholesale Goods"
        }
    ],
    "sg:phone":"+1 514 326 1170",
    "sg:postcode":"H1P 1Z4",
    "sg:province":"QC",
    "sg:tags":[
        "machine",
        "shop"
    ],
    "wof:name":"Acadian Industries Inc",
    "wof:placetype":"venue"
},
  "geometry": {"coordinates":[-73.5921325684,45.6040611267],"type":"Point"}
}