{
  "type": "Feature",
  "properties": {
    "addr:full":"Winnipeg MB R3C 0S6",
    "addr:postcode":"r3c 0s6",
    "iso:country":"CA",
    "sg:city":"Winnipeg",
    "sg:classifiers":[
        {
            "category":"Banks & Credit Unions",
            "subcategory":"Bank",
            "type":"Services"
        }
    ],
    "sg:phone":"+1 204 943 1712",
    "sg:postcode":"R3C 0S6",
    "sg:province":"MB",
    "sg:tags":[
        "financing",
        "loan",
        "real estate"
    ],
    "wof:name":"Benchmark Financial Svc",
    "wof:placetype":"venue"
},
  "geometry": {"coordinates":[-97.1402587891,49.8874435425],"type":"Point"}
}