{
  "type": "Feature",
  "properties": {
    "addr:full":"Valemount BC V0E 2Z0",
    "addr:postcode":"v0e 2z0",
    "iso:country":"CA",
    "sg:city":"Valemount",
    "sg:classifiers":[
        {
            "category":"Government",
            "subcategory":"Office",
            "type":"Public Place"
        }
    ],
    "sg:phone":"+1 250 566 4505",
    "sg:postcode":"V0E 2Z0",
    "sg:province":"BC",
    "sg:tags":[
        "village"
    ],
    "wof:name":"Valemount Public Works",
    "wof:placetype":"venue"
},
  "geometry": {"coordinates":[-119.276885986,52.8267211914],"type":"Point"}
}