{
  "type": "Feature",
  "properties": {
    "iso:country":"CA",
    "sg:address":"15483 Yonge St",
    "sg:city":"Aurora",
    "sg:classifiers":[
        {
            "category":"Personal",
            "subcategory":"Beauty Salon",
            "type":"Services"
        }
    ],
    "sg:phone":"+1 905 727 7587",
    "sg:postcode":"L4G 1P3",
    "sg:province":"ON",
    "wof:name":"Leanne Nail's",
    "wof:placetype":"venue"
},
  "geometry": {"coordinates":[-79.4687805176,44.0054664612],"type":"Point"}
}