{
  "type": "Feature",
  "properties": {
    "addr:full":"1389 Seacliff Dr Kingsville ON N9Y 2M4",
    "addr:housenumber":"1389",
    "addr:postcode":"n9y 2m4",
    "addr:street":"Seacliff Dr",
    "iso:country":"CA",
    "sg:address":"1389 Seacliff Dr",
    "sg:city":"Kingsville",
    "sg:classifiers":[
        {
            "category":"Travel",
            "subcategory":"Hotels & Motels",
            "type":"Entertainment"
        }
    ],
    "sg:phone":"+1 519 733 9660",
    "sg:postcode":"N9Y 2M4",
    "sg:province":"ON",
    "sg:tags":[
        "breakfast",
        "accommodation",
        "bed"
    ],
    "wof:name":"Old Farmhouse Bed & Breakfast",
    "wof:placetype":"venue"
},
  "geometry": {"coordinates":[-82.6810913086,42.0388259888],"type":"Point"}
}