{
  "type": "Feature",
  "properties": {
    "addr:full":"130 Rue Notre-Dame L'Epiphanie QC J5X 2V9",
    "addr:housenumber":"130",
    "addr:postcode":"j5x 2v9",
    "addr:street":"Rue Notre-Dame L'Epiphanie",
    "iso:country":"CA",
    "sg:address":"130 Rue Notre-Dame",
    "sg:city":"L'Epiphanie",
    "sg:classifiers":[
        {
            "category":"Personal",
            "subcategory":"Beauty Salon",
            "type":"Services"
        }
    ],
    "sg:phone":"+1 450 588 6544",
    "sg:postcode":"J5X 2V9",
    "sg:province":"QC",
    "wof:name":"Salon DE Coiffure Dix Versions",
    "wof:placetype":"venue"
},
  "geometry": {"coordinates":[-73.48575599999999,45.848484],"type":"Point"}
}