{
  "type": "Feature",
  "properties": {
    "addr:full":"London ON N6L 1G5",
    "addr:postcode":"n6l 1g5",
    "iso:country":"CA",
    "sg:city":"London",
    "sg:classifiers":[
        {
            "category":"Building & Trades",
            "subcategory":"Plumbing",
            "type":"Services"
        }
    ],
    "sg:phone":"+1 519 652 1884",
    "sg:postcode":"N6L 1G5",
    "sg:province":"ON",
    "sg:tags":[
        "heating",
        "contractor"
    ],
    "wof:name":"Radiant Heating & Cooling",
    "wof:placetype":"venue"
},
  "geometry": {"coordinates":[-81.263153,42.918587],"type":"Point"}
}