{
  "type": "Feature",
  "properties": {
    "addr:full":"High Prairie AB T0G 1E0",
    "addr:postcode":"t0g 1e0",
    "iso:country":"CA",
    "sg:city":"High Prairie",
    "sg:classifiers":[
        {
            "category":"Building & Trades",
            "subcategory":"Plumbing",
            "type":"Services"
        }
    ],
    "sg:phone":"+1 780 523 3275",
    "sg:postcode":"T0G 1E0",
    "sg:province":"AB",
    "sg:tags":[
        "contractor"
    ],
    "wof:name":"Gardner Plumbing & Heating Ltd",
    "wof:placetype":"venue"
},
  "geometry": {"coordinates":[-116.499450684,55.4365692139],"type":"Point"}
}