{
  "type": "Feature",
  "properties": {
    "iso:country":"CA",
    "sg:city":"Arichat",
    "sg:classifiers":[
        {
            "category":"Shopping",
            "subcategory":"Pharmacy",
            "type":"Retail Goods"
        }
    ],
    "sg:phone":"+1 902 226 3133",
    "sg:postcode":"B0E 1A0",
    "sg:province":"NS",
    "wof:name":"Dooley Pharmacy",
    "wof:placetype":"venue"
},
  "geometry": {"coordinates":[-61.0165023804,45.5118560791],"type":"Point"}
}