{
  "type": "Feature",
  "properties": {
    "addr:full":"3951 Steveston Hwy Richmond BC V7E 2J9",
    "addr:housenumber":"3951",
    "addr:postcode":"v7e 2j9",
    "addr:street":"Steveston Hwy",
    "iso:country":"CA",
    "sg:address":"3951 Steveston Hwy",
    "sg:city":"Richmond",
    "sg:classifiers":[
        {
            "category":"Health Services",
            "subcategory":"Doctor",
            "type":"Services"
        }
    ],
    "sg:phone":"+1 604 277 1131",
    "sg:postcode":"V7E 2J9",
    "sg:province":"BC",
    "sg:tags":[
        "dentist"
    ],
    "wof:name":"Steveston Dental Group",
    "wof:placetype":"venue"
},
  "geometry": {"coordinates":[-123.181915283,49.1340065002],"type":"Point"}
}