{
  "type": "Feature",
  "properties": {
    "addr:full":"48 Mulock Ave Toronto ON M6N 3C4",
    "addr:housenumber":"48",
    "addr:postcode":"m6n 3c4",
    "addr:street":"Mulock Ave",
    "iso:country":"CA",
    "sg:address":"48 Mulock Ave",
    "sg:city":"Toronto",
    "sg:classifiers":[
        {
            "category":"Wholesale",
            "subcategory":"Non-durable Goods",
            "type":"Manufacturing & Wholesale Goods"
        }
    ],
    "sg:phone":"+1 416 762 7077",
    "sg:postcode":"M6N 3C4",
    "sg:province":"ON",
    "sg:tags":[
        "material",
        "artist"
    ],
    "wof:name":"Modernart Manufacturing Inc",
    "wof:placetype":"venue"
},
  "geometry": {"coordinates":[-79.46505000000001,43.669044],"type":"Point"}
}