{
  "type": "Feature",
  "properties": {
    "addr:full":"128 Sterling Rd Toronto ON M6R 2B7",
    "addr:housenumber":"128",
    "addr:postcode":"m6r 2b7",
    "addr:street":"Sterling Rd",
    "iso:country":"CA",
    "sg:address":"128 Sterling Rd",
    "sg:city":"Toronto",
    "sg:classifiers":[
        {
            "category":"Banks & Credit Unions",
            "subcategory":"Financial Services",
            "type":"Services"
        }
    ],
    "sg:phone":"+1 416 364 8128",
    "sg:postcode":"M6R 2B7",
    "sg:province":"ON",
    "sg:tags":[
        "company",
        "holding"
    ],
    "wof:name":"Dafina Holdings Ltd",
    "wof:placetype":"venue"
},
  "geometry": {"coordinates":[-79.444855,43.653908],"type":"Point"}
}