{
  "type": "Feature",
  "properties": {
    "iso:country":"CA",
    "sg:address":"664 Fennell Ave E",
    "sg:city":"Hamilton",
    "sg:classifiers":[
        {
            "category":"Professional",
            "subcategory":"Accounting & Tax Preparation",
            "type":"Services"
        }
    ],
    "sg:phone":"+1 905 389 5588",
    "sg:postcode":"L8V 1V1",
    "sg:province":"ON",
    "sg:tags":[
        "payroll"
    ],
    "wof:name":"Ctc Payroll Svc",
    "wof:placetype":"venue"
},
  "geometry": {"coordinates":[-79.850563,43.230606],"type":"Point"}
}