{
  "type": "Feature",
  "properties": {
    "addr:full":"6306 55 St Taber AB T1G 2H4",
    "addr:housenumber":"6306",
    "addr:postcode":"t1g 2h4",
    "addr:street":"55 St",
    "iso:country":"CA",
    "sg:address":"6306 55 St",
    "sg:city":"Taber",
    "sg:classifiers":[
        {
            "category":"Retail",
            "subcategory":"Car Wash",
            "type":"Services"
        }
    ],
    "sg:phone":"+1 403 223 0397",
    "sg:postcode":"T1G 2H4",
    "sg:province":"AB",
    "sg:tags":[
        "polishing",
        "washing"
    ],
    "wof:name":"Top Wand Car & Truck Wash",
    "wof:placetype":"venue"
},
  "geometry": {"coordinates":[-112.14186100000001,49.79977],"type":"Point"}
}