{
  "type": "Feature",
  "properties": {
    "addr:full":"123 Fern Ave Toronto ON M6R 1K2",
    "addr:housenumber":"123",
    "addr:postcode":"m6r 1k2",
    "addr:street":"Fern Ave",
    "iso:country":"CA",
    "sg:address":"123 Fern Ave",
    "sg:city":"Toronto",
    "sg:classifiers":[
        {
            "category":"Professional",
            "subcategory":"Art Services",
            "type":"Services"
        }
    ],
    "sg:phone":"+1 416 588 7273",
    "sg:postcode":"M6R 1K2",
    "sg:province":"ON",
    "sg:tags":[
        "marketing",
        "graphic",
        "designer",
        "consultant"
    ],
    "wof:name":"Xrare Corp",
    "wof:placetype":"venue"
},
  "geometry": {"coordinates":[-79.44548,43.64497],"type":"Point"}
}