{
  "type": "Feature",
  "properties": {
    "addr:full":"168 Porter Cove Rd Porter Cove NB E9C 2J6",
    "addr:housenumber":"168",
    "addr:postcode":"e9c 2j6",
    "addr:street":"Porter Cove Rd",
    "iso:country":"CA",
    "sg:address":"168 Porter Cove Rd",
    "sg:city":"Porter Cove",
    "sg:classifiers":[
        {
            "category":"Building & Trades",
            "subcategory":"Electrical",
            "type":"Services"
        }
    ],
    "sg:phone":"+1 506 369 2314",
    "sg:postcode":"E9C 2J6",
    "sg:province":"NB",
    "sg:tags":[
        "electric",
        "contractor"
    ],
    "wof:name":"O'Donnell Line & Electric Ltd",
    "wof:placetype":"venue"
},
  "geometry": {"coordinates":[-66.353493,46.490845],"type":"Point"}
}