{
  "type": "Feature",
  "properties": {
    "addr:full":"422 Queen St N Paisley ON N0G 2N0",
    "addr:housenumber":"422",
    "addr:postcode":"n0g 2n0",
    "addr:street":"Queen St N",
    "iso:country":"CA",
    "sg:address":"422 Queen St N",
    "sg:city":"Paisley",
    "sg:classifiers":[
        {
            "category":"Wholesale",
            "subcategory":"Farm Supplies",
            "type":"Manufacturing & Wholesale Goods"
        }
    ],
    "sg:phone":"+1 519 353 5521",
    "sg:postcode":"N0G 2N0",
    "sg:province":"ON",
    "sg:tags":[
        "feed"
    ],
    "wof:name":"Robinson Feeds",
    "wof:placetype":"venue"
},
  "geometry": {"coordinates":[-81.2740249634,44.3086471558],"type":"Point"}
}