{
  "type": "Feature",
  "properties": {
    "iso:country":"CA",
    "sg:address":"146 Rue Commerciale",
    "sg:city":"Saint-Henri-DE-Levis",
    "sg:classifiers":[
        {
            "category":"Wholesale",
            "subcategory":"Metals & Minerals",
            "type":"Manufacturing & Wholesale Goods"
        }
    ],
    "sg:phone":"+1 418 882 2205",
    "sg:postcode":"G0R 3E0",
    "sg:province":"QC",
    "sg:tags":[
        "pipe",
        "sewer",
        "drain"
    ],
    "wof:name":"Fortier 2000 Ltee",
    "wof:placetype":"venue"
},
  "geometry": {"coordinates":[-71.069480896,46.6942405701],"type":"Point"}
}