{
  "type": "Feature",
  "properties": {
    "addr:full":"385 Viewmount Dr Head of St Margarets Bay NS B3Z 2G4",
    "addr:housenumber":"385",
    "addr:postcode":"b3z 2g4",
    "addr:street":"Viewmount Dr",
    "iso:country":"CA",
    "sg:address":"385 Viewmount Dr",
    "sg:city":"Head of St Margarets Bay",
    "sg:classifiers":[
        {
            "category":"Wholesale",
            "subcategory":"Durable Goods & Equipment",
            "type":"Manufacturing & Wholesale Goods"
        }
    ],
    "sg:phone":"+1 902 826 7457",
    "sg:postcode":"B3Z 2G4",
    "sg:province":"NS",
    "sg:tags":[
        "representative",
        "manufacturer"
    ],
    "wof:name":"Henk M Van Leeuwen Sales Agncy",
    "wof:placetype":"venue"
},
  "geometry": {"coordinates":[-63.9061317444,44.6740913391],"type":"Point"}
}