{
  "type": "Feature",
  "properties": {
    "addr:full":"6701 Rue Sherbrooke O Montreal QC H4B 1P3",
    "addr:housenumber":"6701",
    "addr:postcode":"h4b 1p3",
    "addr:street":"Rue Sherbrooke O",
    "iso:country":"CA",
    "sg:address":"6701 Rue Sherbrooke O",
    "sg:city":"Montreal",
    "sg:classifiers":[
        {
            "category":"Food & Beverages",
            "subcategory":"Groceries & Convenience Stores",
            "type":"Retail Goods"
        }
    ],
    "sg:phone":"+1 514 489 5176",
    "sg:postcode":"H4B 1P3",
    "sg:province":"QC",
    "wof:name":"Depanneur Montclair",
    "wof:placetype":"venue"
},
  "geometry": {"coordinates":[-73.5427856445,45.5837898254],"type":"Point"}
}