{
  "type": "Feature",
  "properties": {
    "addr:full":"Community Ctr Bawlf AB T0B 0J0",
    "addr:postcode":"t0b 0j0",
    "addr:street":"Community",
    "iso:country":"CA",
    "sg:address":"Community Ctr",
    "sg:city":"Bawlf",
    "sg:classifiers":[
        {
            "category":"Recreation",
            "type":"Entertainment"
        }
    ],
    "sg:phone":"+1 780 373 2632",
    "sg:postcode":"T0B 0J0",
    "sg:province":"AB",
    "sg:tags":[
        "club",
        "curling"
    ],
    "wof:name":"Bawlf Curling Club",
    "wof:placetype":"venue"
},
  "geometry": {"coordinates":[-112.46668243400001,52.9201011658],"type":"Point"}
}