{
  "type": "Feature",
  "properties": {
    "addr:full":"1003 11th Ave W Kindersley SK S0L 1S0",
    "addr:housenumber":"1003",
    "addr:postcode":"s0l 1s0",
    "addr:street":"11Th Ave W Kindersley",
    "iso:country":"CA",
    "sg:address":"1003 11th Ave W",
    "sg:city":"Kindersley",
    "sg:classifiers":[
        {
            "category":"Freight",
            "type":"Transportation"
        }
    ],
    "sg:phone":"+1 306 463 2724",
    "sg:postcode":"S0L 1S0",
    "sg:province":"SK",
    "sg:tags":[
        "trucking"
    ],
    "wof:name":"Kindersley Transport Ltd",
    "wof:placetype":"venue"
},
  "geometry": {"coordinates":[-109.18486,51.474411],"type":"Point"}
}