{
  "type": "Feature",
  "properties": {
    "iso:country":"CA",
    "sg:city":"Winnipeg",
    "sg:classifiers":[
        {
            "category":"Professional",
            "subcategory":"Lawyer & Legal Services",
            "type":"Services"
        }
    ],
    "sg:phone":"+1 204 942 2271",
    "sg:postcode":"R3C 4E1",
    "sg:province":"MB",
    "sg:tags":[
        "attorney"
    ],
    "wof:name":"Gripp, Roger D",
    "wof:placetype":"venue"
},
  "geometry": {"coordinates":[-97.142532,49.89035],"type":"Point"}
}