{
  "type": "Feature",
  "properties": {
    "iso:country":"CA",
    "sg:address":"5210 110 St NW",
    "sg:city":"Edmonton",
    "sg:classifiers":[
        {
            "category":"Social Services",
            "subcategory":"Adult Care",
            "type":"Services"
        }
    ],
    "sg:phone":"+1 780 437 7061",
    "sg:postcode":"T6H 5K1",
    "sg:province":"AB",
    "sg:tags":[
        "senior",
        "housing",
        "citizen"
    ],
    "wof:name":"Pleasantview Place",
    "wof:placetype":"venue"
},
  "geometry": {"coordinates":[-113.514137268,53.4897766113],"type":"Point"}
}