{
  "type": "Feature",
  "properties": {
    "addr:full":"10 Wakefield Dr SW Calgary AB T3C 2W7",
    "addr:housenumber":"10",
    "addr:postcode":"t3c 2w7",
    "addr:street":"Wakefield Dr Sw",
    "iso:country":"CA",
    "sg:address":"10 Wakefield Dr SW",
    "sg:city":"Calgary",
    "sg:classifiers":[
        {
            "category":"Building & Trades",
            "subcategory":"Construction",
            "type":"Services"
        }
    ],
    "sg:phone":"+1 403 242 5932",
    "sg:postcode":"T3C 2W7",
    "sg:province":"AB",
    "sg:tags":[
        "repairing",
        "remodeling",
        "contractor"
    ],
    "wof:name":"Vista Home Svc",
    "wof:placetype":"venue"
},
  "geometry": {"coordinates":[-114.160926819,51.0445137024],"type":"Point"}
}