{
  "type": "Feature",
  "properties": {
    "addr:full":"175 Av Du College Beauport QC G1E 2Y9",
    "addr:housenumber":"175",
    "addr:postcode":"qc g1e 2y9",
    "addr:street":"Av Du College",
    "iso:country":"CA",
    "sg:address":"175 Av Du College",
    "sg:city":"Beauport",
    "sg:classifiers":[
        {
            "category":"Building & Trades",
            "subcategory":"Construction",
            "type":"Services"
        }
    ],
    "sg:phone":"+1 418 622 8624",
    "sg:postcode":"G1E 2Y9",
    "sg:province":"QC",
    "sg:tags":[
        "contractor"
    ],
    "wof:name":"Construction Renovation",
    "wof:placetype":"venue"
},
  "geometry": {"coordinates":[-71.17860400000001,46.86211],"type":"Point"}
}