{
  "type": "Feature",
  "properties": {
    "iso:country":"CA",
    "sg:address":"734 Cathcart Blvd",
    "sg:city":"Sarnia",
    "sg:classifiers":[
        {
            "category":"Retail",
            "subcategory":"Portrait Studio",
            "type":"Services"
        }
    ],
    "sg:phone":"+1 519 383 1100",
    "sg:postcode":"N7V 2N5",
    "sg:province":"ON",
    "sg:tags":[
        "photographer"
    ],
    "wof:name":"Impressions Photographic Std",
    "wof:placetype":"venue"
},
  "geometry": {"coordinates":[-82.3851318359,43.0053634644],"type":"Point"}
}