{
  "type": "Feature",
  "properties": {
    "addr:full":"Berwick NS B0P 1E0",
    "addr:postcode":"b0p 1e0",
    "iso:country":"CA",
    "sg:city":"Berwick",
    "sg:classifiers":[
        {
            "category":"Autos & Motor Vehicles",
            "subcategory":"Fuel & Gas Station",
            "type":"Retail Goods"
        }
    ],
    "sg:phone":"+1 902 538 9154",
    "sg:postcode":"B0P 1E0",
    "sg:province":"NS",
    "sg:tags":[
        "oil"
    ],
    "wof:name":"South Berwick Automotive Svc",
    "wof:placetype":"venue"
},
  "geometry": {"coordinates":[-64.7377243042,45.0498161316],"type":"Point"}
}