{
  "type": "Feature",
  "properties": {
    "iso:country":"CA",
    "sg:address":"73 Humber Rd",
    "sg:city":"Corner Brook",
    "sg:classifiers":[
        {
            "category":"Food & Beverages",
            "subcategory":"Groceries & Convenience Stores",
            "type":"Retail Goods"
        }
    ],
    "sg:phone":"+1 709 637 6655",
    "sg:postcode":"A2H 1E9",
    "sg:province":"NL",
    "sg:tags":[
        "grocer"
    ],
    "wof:name":"Colemans Food Ctr Store",
    "wof:placetype":"venue"
},
  "geometry": {"coordinates":[-57.9334945679,48.9620819092],"type":"Point"}
}