{
  "type": "Feature",
  "properties": {
    "addr:full":"Calgary AB T2H 0M2",
    "addr:postcode":"t2h 0m2",
    "iso:country":"CA",
    "sg:city":"Calgary",
    "sg:classifiers":[
        {
            "category":"Professional",
            "subcategory":"Detective & Security Services",
            "type":"Services"
        }
    ],
    "sg:phone":"+1 403 255 7940",
    "sg:postcode":"T2H 0M2",
    "sg:province":"AB",
    "sg:tags":[
        "guard",
        "patrol"
    ],
    "wof:name":"Initial Security Svc",
    "wof:placetype":"venue"
},
  "geometry": {"coordinates":[-114.071929932,50.9739151001],"type":"Point"}
}