{
  "type": "Feature",
  "properties": {
    "addr:full":"1096 Queen St W Toronto ON M6J 1H9",
    "addr:housenumber":"1096",
    "addr:postcode":"m6j 1h9",
    "addr:street":"Queen St W",
    "iso:country":"CA",
    "sg:address":"1096 Queen St W",
    "sg:city":"Toronto",
    "sg:classifiers":[
        {
            "category":"Shopping",
            "type":"Retail Goods"
        }
    ],
    "sg:phone":"+1 416 597 9466",
    "sg:postcode":"M6J 1H9",
    "sg:province":"ON",
    "sg:tags":[
        "art",
        "gallery",
        "dealer"
    ],
    "wof:name":"DE Leon White Gallery",
    "wof:placetype":"venue"
},
  "geometry": {"coordinates":[-79.42272199999999,43.643562],"type":"Point"}
}