{
  "type": "Feature",
  "properties": {
    "iso:country":"CA",
    "sg:city":"Oakville",
    "sg:classifiers":[
        {
            "category":"Wholesale",
            "subcategory":"Electrical",
            "type":"Manufacturing & Wholesale Goods"
        }
    ],
    "sg:phone":"+1 905 829 9922",
    "sg:postcode":"L6H 5S3",
    "sg:province":"ON",
    "sg:tags":[
        "conduit",
        "fitting"
    ],
    "wof:name":"Moltec Trading Group Ltd",
    "wof:placetype":"venue"
},
  "geometry": {"coordinates":[-79.676025,43.516098],"type":"Point"}
}