{
  "type": "Feature",
  "properties": {
    "addr:full":"6087 Island Hwy W Qualicum Beach BC V9K 2E2",
    "addr:housenumber":"6087",
    "addr:postcode":"v9k 2e2",
    "addr:street":"Island Hwy W",
    "iso:country":"CA",
    "sg:address":"6087 Island Hwy W",
    "sg:city":"Qualicum Beach",
    "sg:classifiers":[
        {
            "category":"Restaurant",
            "type":"Food & Drink"
        }
    ],
    "sg:phone":"+1 250 757 9995",
    "sg:postcode":"V9K 2E2",
    "sg:province":"BC",
    "wof:name":"Sandbar Cafe",
    "wof:placetype":"venue"
},
  "geometry": {"coordinates":[-124.475838,49.360474],"type":"Point"}
}