{
  "type": "Feature",
  "properties": {
    "addr:full":"Montreal QC H3A 1P8",
    "addr:postcode":"h3a 1p8",
    "iso:country":"CA",
    "sg:city":"Montreal",
    "sg:classifiers":[
        {
            "category":"Personal",
            "type":"Services"
        }
    ],
    "sg:phone":"+1 514 842 6225",
    "sg:postcode":"H3A 1P8",
    "sg:province":"QC",
    "sg:tags":[
        "electrolysis"
    ],
    "wof:name":"Systeme Gregoire DE Montreal",
    "wof:placetype":"venue"
},
  "geometry": {"coordinates":[-73.57392120359999,45.4993476868],"type":"Point"}
}