{
  "type": "Feature",
  "properties": {
    "iso:country":"CA",
    "sg:address":"877 11 St SE # 2",
    "sg:city":"Medicine Hat",
    "sg:classifiers":[
        {
            "category":"Retail",
            "subcategory":"Animal Services",
            "type":"Services"
        }
    ],
    "sg:phone":"+1 403 527 8779",
    "sg:postcode":"T1A 1T6",
    "sg:province":"AB",
    "sg:tags":[
        "pet",
        "grooming",
        "washing"
    ],
    "wof:name":"Jaws & Paws Dog Grooming",
    "wof:placetype":"venue"
},
  "geometry": {"coordinates":[-110.66501599999999,50.028103],"type":"Point"}
}