{
  "type": "Feature",
  "properties": {
    "addr:full":"1094 Rue Saint-Andre Acton Vale QC J0H 1A0",
    "addr:housenumber":"1094",
    "addr:postcode":"j0h 1a0",
    "addr:street":"Rue Saint-Andre",
    "iso:country":"CA",
    "sg:address":"1094 Rue Saint-Andre",
    "sg:city":"Acton Vale",
    "sg:classifiers":[
        {
            "category":"Shopping",
            "subcategory":"Tobacco",
            "type":"Retail Goods"
        }
    ],
    "sg:phone":"+1 450 546 2753",
    "sg:postcode":"J0H 1A0",
    "sg:province":"QC",
    "sg:tags":[
        "cigarette",
        "cigar",
        "dealer"
    ],
    "wof:name":"Tabagie Acton Varietes",
    "wof:placetype":"venue"
},
  "geometry": {"coordinates":[-72.564713,45.649693],"type":"Point"}
}