{
  "type": "Feature",
  "properties": {
    "addr:full":"109 Rue Saint-Andre Metabetchouan-Lac-A-LA-Croix QC G8G 1V5",
    "addr:housenumber":"109",
    "addr:postcode":"g8g 1v5",
    "addr:street":"Rue Saint-Andre",
    "iso:country":"CA",
    "sg:address":"109 Rue Saint-Andre",
    "sg:city":"Metabetchouan-Lac-A-LA-Croix",
    "sg:classifiers":[
        {
            "category":"Manufacturing",
            "subcategory":"Printing",
            "type":"Manufacturing & Wholesale Goods"
        }
    ],
    "sg:phone":"+1 418 349 8219",
    "sg:postcode":"G8G 1V5",
    "sg:province":"QC",
    "sg:tags":[
        "printer"
    ],
    "wof:name":"Imprimerie Metabetchouan Enr",
    "wof:placetype":"venue"
},
  "geometry": {"coordinates":[-71.87294,48.425892],"type":"Point"}
}