{
  "type": "Feature",
  "properties": {
    "addr:full":"Calgary AB T2M 0K3",
    "addr:postcode":"t2m 0k3",
    "iso:country":"CA",
    "sg:city":"Calgary",
    "sg:classifiers":[
        {
            "category":"Insurance",
            "subcategory":"Insurance Agent",
            "type":"Services"
        }
    ],
    "sg:phone":"+1 403 289 5486",
    "sg:postcode":"T2M 0K3",
    "sg:province":"AB",
    "wof:name":"Wright & CO Insurance",
    "wof:placetype":"venue"
},
  "geometry": {"coordinates":[-114.08165741000001,51.0670814514],"type":"Point"}
}