{
  "type": "Feature",
  "properties": {
    "addr:full":"1505 8th St E Saskatoon SK S7H 0T2",
    "addr:housenumber":"1505",
    "addr:postcode":"s7h 0t2",
    "addr:street":"8Th St E",
    "iso:country":"CA",
    "sg:address":"1505 8th St E",
    "sg:city":"Saskatoon",
    "sg:classifiers":[
        {
            "category":"Cinema",
            "subcategory":"Movie Rental",
            "type":"Entertainment"
        }
    ],
    "sg:phone":"+1 306 343 7475",
    "sg:postcode":"S7H 0T2",
    "sg:province":"SK",
    "sg:tags":[
        "leasing",
        "video",
        "disc",
        "tape"
    ],
    "wof:name":"Blockbuster Video",
    "wof:placetype":"venue"
},
  "geometry": {"coordinates":[-106.63475,52.115078],"type":"Point"}
}