{
  "type": "Feature",
  "properties": {
    "addr:full":"10 Stephen St Pictou NS B0K 1H0",
    "addr:housenumber":"10",
    "addr:postcode":"b0k 1h0",
    "addr:street":"Stephen St",
    "iso:country":"CA",
    "sg:address":"10 Stephen St",
    "sg:city":"Pictou",
    "sg:classifiers":[
        {
            "category":"Organizations",
            "subcategory":"Religious Organization",
            "type":"Services"
        }
    ],
    "sg:phone":"+1 902 485 4112",
    "sg:postcode":"B0K 1H0",
    "sg:province":"NS",
    "sg:tags":[
        "church"
    ],
    "wof:name":"Stella Maris Church",
    "wof:placetype":"venue"
},
  "geometry": {"coordinates":[-62.7070732117,45.6781806946],"type":"Point"}
}