{
  "type": "Feature",
  "properties": {
    "addr:full":"Calgary AB T2G 5M2",
    "addr:postcode":"t2g 5m2",
    "iso:country":"CA",
    "sg:city":"Calgary",
    "sg:classifiers":[
        {
            "category":"Shopping",
            "subcategory":"Stationery & Office Supplies",
            "type":"Retail Goods"
        }
    ],
    "sg:phone":"+1 403 243 4443",
    "sg:postcode":"T2G 5M2",
    "sg:province":"AB",
    "sg:tags":[
        "educational",
        "material"
    ],
    "wof:name":"Canadian Home Education",
    "wof:placetype":"venue"
},
  "geometry": {"coordinates":[-114.034973145,51.0101013184],"type":"Point"}
}