{
  "type": "Feature",
  "properties": {
    "addr:full":"1138 Kensington Rd NW Calgary AB T2N 3P3",
    "addr:housenumber":"1138",
    "addr:postcode":"t2n 3p3",
    "addr:street":"Kensington Rd Nw",
    "iso:country":"CA",
    "sg:address":"1138 Kensington Rd NW",
    "sg:city":"Calgary",
    "sg:classifiers":[
        {
            "category":"Professional",
            "subcategory":"Lawyer & Legal Services",
            "type":"Services"
        }
    ],
    "sg:phone":"+1 403 571 5120",
    "sg:postcode":"T2N 3P3",
    "sg:province":"AB",
    "sg:tags":[
        "attorney"
    ],
    "wof:name":"Sebree, Sandra",
    "wof:placetype":"venue"
},
  "geometry": {"coordinates":[-114.08773803699999,51.052734375],"type":"Point"}
}