{
  "type": "Feature",
  "properties": {
    "addr:full":"723 Rue Saint-Louis Terrebonne QC J6W 1J3",
    "addr:housenumber":"723",
    "addr:postcode":"j6w 1j3",
    "addr:street":"Rue Saint-Louis",
    "iso:country":"CA",
    "sg:address":"723 Rue Saint-Louis",
    "sg:city":"Terrebonne",
    "sg:classifiers":[
        {
            "category":"Health Services",
            "subcategory":"Doctor",
            "type":"Services"
        }
    ],
    "sg:phone":"+1 450 964 1755",
    "sg:postcode":"J6W 1J3",
    "sg:province":"QC",
    "sg:tags":[
        "physician",
        "surgeon"
    ],
    "wof:name":"Clinique Osteopathie DE",
    "wof:placetype":"venue"
},
  "geometry": {"coordinates":[-73.634331,45.695099],"type":"Point"}
}