{
  "type": "Feature",
  "properties": {
    "addr:full":"5525 272 St Langley BC V4W 1P1",
    "addr:housenumber":"5525",
    "addr:postcode":"v4w 1p1",
    "addr:street":"272 St",
    "iso:country":"CA",
    "sg:address":"5525 272 St",
    "sg:city":"Langley",
    "sg:classifiers":[
        {
            "category":"Professional",
            "subcategory":"Management & Consulting",
            "type":"Services"
        }
    ],
    "sg:phone":"+1 604 856 3156",
    "sg:postcode":"V4W 1P1",
    "sg:province":"BC",
    "sg:tags":[
        "development",
        "industrial"
    ],
    "wof:name":"Gloucester Industrial Estates",
    "wof:placetype":"venue"
},
  "geometry": {"coordinates":[-122.471069,49.101856],"type":"Point"}
}