{
  "type": "Feature",
  "properties": {
    "iso:country":"CA",
    "sg:address":"194 Rue Saint-Paul O",
    "sg:city":"Montreal",
    "sg:classifiers":[
        {
            "category":"Freight",
            "type":"Transportation"
        }
    ],
    "sg:phone":"+1 514 848 0448",
    "sg:postcode":"H2Y 1Z8",
    "sg:province":"QC",
    "sg:tags":[
        "shipping",
        "agent"
    ],
    "wof:name":"Sea Projects",
    "wof:placetype":"venue"
},
  "geometry": {"coordinates":[-73.552444,45.50742],"type":"Point"}
}