{
  "type": "Feature",
  "properties": {
    "addr:full":"517 Mountain Ave Carlyle SK S0C 0R0",
    "addr:housenumber":"517",
    "addr:postcode":"s0c 0r0",
    "addr:street":"Mountain Ave",
    "iso:country":"CA",
    "sg:address":"517 Mountain Ave",
    "sg:city":"Carlyle",
    "sg:classifiers":[
        {
            "category":"Retail",
            "subcategory":"Laundry & Dry Cleaning",
            "type":"Services"
        }
    ],
    "sg:phone":"+1 306 453 2707",
    "sg:postcode":"S0C 0R0",
    "sg:province":"SK",
    "sg:tags":[
        "cleaners",
        "rug",
        "carpet"
    ],
    "wof:name":"Royal Touch Carpet & Uphlstry",
    "wof:placetype":"venue"
},
  "geometry": {"coordinates":[-102.265388,49.636585],"type":"Point"}
}