{
  "type": "Feature",
  "properties": {
    "addr:full":"685 5th Ave W Owen Sound ON N4K 5A2",
    "addr:housenumber":"685",
    "addr:postcode":"n4k 5a2",
    "addr:street":"5Th Ave W",
    "iso:country":"CA",
    "sg:address":"685 5th Ave W",
    "sg:city":"Owen Sound",
    "sg:classifiers":[
        {
            "category":"Home & Garden",
            "subcategory":"Home Furnishings",
            "type":"Retail Goods"
        }
    ],
    "sg:phone":"+1 519 376 3992",
    "sg:postcode":"N4K 5A2",
    "sg:province":"ON",
    "sg:tags":[
        "curtain",
        "made",
        "drapery"
    ],
    "wof:name":"Scenic City Drapery",
    "wof:placetype":"venue"
},
  "geometry": {"coordinates":[-80.94919586180001,44.5607376099],"type":"Point"}
}