{
  "type": "Feature",
  "properties": {
    "addr:full":"350 Rue Principale E Saint-Eloi QC G0L 2V0",
    "addr:housenumber":"350",
    "addr:postcode":"g0l 2v0",
    "addr:street":"Rue Principale E Saint-Eloi",
    "iso:country":"CA",
    "sg:address":"350 Rue Principale E",
    "sg:city":"Saint-Eloi",
    "sg:classifiers":[
        {
            "category":"Travel",
            "subcategory":"Hotels & Motels",
            "type":"Entertainment"
        }
    ],
    "sg:phone":"+1 418 898 6147",
    "sg:postcode":"G0L 2V0",
    "sg:province":"QC",
    "sg:tags":[
        "inn"
    ],
    "wof:name":"Auberge Au Vieux Presbytere",
    "wof:placetype":"venue"
},
  "geometry": {"coordinates":[-69.22377,48.040806],"type":"Point"}
}