{
  "type": "Feature",
  "properties": {
    "addr:full":"90 Rue Jean Saint-Luc QC J2W 2C7",
    "addr:housenumber":"90",
    "addr:postcode":"j2w 2c7",
    "addr:street":"Rue Jean",
    "iso:country":"CA",
    "sg:address":"90 Rue Jean",
    "sg:city":"Saint-Luc",
    "sg:classifiers":[
        {
            "category":"Building & Trades",
            "subcategory":"Construction",
            "type":"Services"
        }
    ],
    "sg:phone":"+1 450 348 2915",
    "sg:postcode":"J2W 2C7",
    "sg:province":"QC",
    "sg:tags":[
        "contractor"
    ],
    "wof:name":"C S Construction Renovation",
    "wof:placetype":"venue"
},
  "geometry": {"coordinates":[-73.256607,45.366047],"type":"Point"}
}