{
  "type": "Feature",
  "properties": {
    "addr:full":"12018 102 Ave NW Edmonton AB T5K 0R9",
    "addr:housenumber":"12018",
    "addr:postcode":"t5k 0r9",
    "addr:street":"102 Ave Nw",
    "iso:country":"CA",
    "sg:address":"12018 102 Ave NW",
    "sg:city":"Edmonton",
    "sg:classifiers":[
        {
            "category":"Wholesale",
            "subcategory":"Electrical",
            "type":"Manufacturing & Wholesale Goods"
        }
    ],
    "sg:phone":"+1 780 408 3838",
    "sg:postcode":"T5K 0R9",
    "sg:province":"AB",
    "sg:tags":[
        "control",
        "security",
        "system"
    ],
    "wof:name":"Two-Way Voice Security Inc",
    "wof:placetype":"venue"
},
  "geometry": {"coordinates":[-113.52918200000001,53.543148],"type":"Point"}
}