{
  "type": "Feature",
  "properties": {
    "iso:country":"CA",
    "sg:city":"Winnipeg",
    "sg:classifiers":[
        {
            "category":"Health Services",
            "subcategory":"Doctor",
            "type":"Services"
        }
    ],
    "sg:phone":"+1 204 254 2343",
    "sg:postcode":"R3X 1N7",
    "sg:province":"MB",
    "sg:tags":[
        "dentist"
    ],
    "wof:name":"Raineault, Monique DDS",
    "wof:placetype":"venue"
},
  "geometry": {"coordinates":[-97.065559,49.839836],"type":"Point"}
}