{
  "type": "Feature",
  "properties": {
    "addr:full":"4451 Westminster Hwy Richmond BC V7C 1B6",
    "addr:housenumber":"4451",
    "addr:postcode":"v7c 1b6",
    "addr:street":"Westminster Hwy",
    "iso:country":"CA",
    "sg:address":"4451 Westminster Hwy",
    "sg:city":"Richmond",
    "sg:classifiers":[
        {
            "category":"Shopping",
            "subcategory":"Clothing, Apparel, & Fashions",
            "type":"Retail Goods"
        }
    ],
    "sg:phone":"+1 604 278 6346",
    "sg:postcode":"V7C 1B6",
    "sg:province":"BC",
    "sg:tags":[
        "dressmaker"
    ],
    "wof:name":"Susan Papas Dressmaking",
    "wof:placetype":"venue"
},
  "geometry": {"coordinates":[-123.17653656,49.1703567505],"type":"Point"}
}