{
  "type": "Feature",
  "properties": {
    "addr:full":"Orleans ON K1C 7K3",
    "addr:postcode":"k1c 7k3",
    "iso:country":"CA",
    "sg:city":"Orleans",
    "sg:classifiers":[
        {
            "category":"Health Services",
            "subcategory":"Podiatrist",
            "type":"Services"
        }
    ],
    "sg:phone":"+1 613 841 8500",
    "sg:postcode":"K1C 7K3",
    "sg:province":"ON",
    "wof:name":"Kerbl, David R DPM",
    "wof:placetype":"venue"
},
  "geometry": {"coordinates":[-75.5059432983,45.4832611084],"type":"Point"}
}