{
  "type": "Feature",
  "properties": {
    "addr:full":"Scarborough ON M1S 5H6",
    "addr:postcode":"m1s 5h6",
    "iso:country":"CA",
    "sg:city":"Scarborough",
    "sg:classifiers":[
        {
            "category":"Manufacturing",
            "subcategory":"Printing",
            "type":"Manufacturing & Wholesale Goods"
        }
    ],
    "sg:phone":"+1 416 332 1607",
    "sg:postcode":"M1S 5H6",
    "sg:province":"ON",
    "sg:tags":[
        "printer"
    ],
    "wof:name":"Hannah Production",
    "wof:placetype":"venue"
},
  "geometry": {"coordinates":[-79.288155,43.803486],"type":"Point"}
}