{
  "type": "Feature",
  "properties": {
    "addr:full":"Nanaimo BC V9S 4N2",
    "addr:postcode":"v9s 4n2",
    "iso:country":"CA",
    "sg:city":"Nanaimo",
    "sg:classifiers":[
        {
            "category":"Education",
            "subcategory":"Special Training",
            "type":"Public Place"
        }
    ],
    "sg:phone":"+1 250 756 2575",
    "sg:postcode":"V9S 4N2",
    "sg:province":"BC",
    "sg:tags":[
        "instruction",
        "driving"
    ],
    "wof:name":"Cowichan School of Motoring",
    "wof:placetype":"venue"
},
  "geometry": {"coordinates":[-123.98041499999999,49.196079],"type":"Point"}
}