{
  "type": "Feature",
  "properties": {
    "iso:country":"CA",
    "sg:address":"5749 Tecumseh Rd E",
    "sg:city":"Windsor",
    "sg:classifiers":[
        {
            "category":"Personal",
            "subcategory":"Barber",
            "type":"Services"
        }
    ],
    "sg:phone":"+1 519 948 7114",
    "sg:postcode":"N8T 1E1",
    "sg:province":"ON",
    "wof:name":"Lucio's Barber Shop",
    "wof:placetype":"venue"
},
  "geometry": {"coordinates":[-82.95611572270001,42.3094787598],"type":"Point"}
}