{
  "type": "Feature",
  "properties": {
    "addr:full":"255 Boul DE LA Concorde O # 7 Laval QC H7N 5T1",
    "addr:housenumber":"255",
    "addr:postcode":"h7n 5t1",
    "addr:street":"Boul De La Concorde O # 7",
    "iso:country":"CA",
    "sg:address":"255 Boul DE LA Concorde O # 7",
    "sg:city":"Laval",
    "sg:classifiers":[
        {
            "category":"Retail",
            "subcategory":"Laundry & Dry Cleaning",
            "type":"Services"
        }
    ],
    "sg:phone":"+1 450 669 2111",
    "sg:postcode":"H7N 5T1",
    "sg:province":"QC",
    "sg:tags":[
        "cleaners"
    ],
    "wof:name":"Nettoyeurs Daoust",
    "wof:placetype":"venue"
},
  "geometry": {"coordinates":[-73.70114898680001,45.565700531],"type":"Point"}
}