{
  "type": "Feature",
  "properties": {
    "addr:full":"3262 Tottenham Rd Beeton ON L0G 1A0",
    "addr:housenumber":"3262",
    "addr:postcode":"l0g 1a0",
    "addr:street":"Tottenham Rd",
    "iso:country":"CA",
    "sg:address":"3262 Tottenham Rd",
    "sg:city":"Beeton",
    "sg:classifiers":[
        {
            "category":"Freight",
            "type":"Transportation"
        }
    ],
    "sg:phone":"+1 905 729 3823",
    "sg:postcode":"L0G 1A0",
    "sg:province":"ON",
    "sg:tags":[
        "grain",
        "elevator"
    ],
    "wof:name":"Wayland Farms",
    "wof:placetype":"venue"
},
  "geometry": {"coordinates":[-79.8220748901,44.0855636597],"type":"Point"}
}