{
  "type": "Feature",
  "properties": {
    "addr:full":"5400 Rue Des Tournelles Quebec QC G2J 1E4",
    "addr:housenumber":"5400",
    "addr:postcode":"g2j 1e4",
    "addr:street":"Rue Des Tournelles",
    "iso:country":"CA",
    "sg:address":"5400 Rue Des Tournelles",
    "sg:city":"Quebec",
    "sg:classifiers":[
        {
            "category":"Manufacturing",
            "subcategory":"Tools & Machinery",
            "type":"Manufacturing & Wholesale Goods"
        }
    ],
    "sg:phone":"+1 418 624 4557",
    "sg:postcode":"G2J 1E4",
    "sg:province":"QC",
    "sg:tags":[
        "machine",
        "shop"
    ],
    "wof:name":"Atelier D'Usinage L Dussault",
    "wof:placetype":"venue"
},
  "geometry": {"coordinates":[-71.2812576294,46.8383827209],"type":"Point"}
}