{
  "type": "Feature",
  "properties": {
    "addr:full":"1668 O'Connor Dr North York ON M4A 1W4",
    "addr:housenumber":"1668",
    "addr:postcode":"m4a 1w4",
    "addr:street":"O'Connor Dr",
    "iso:country":"CA",
    "sg:address":"1668 O'Connor Dr",
    "sg:city":"North York",
    "sg:classifiers":[
        {
            "category":"Retail",
            "subcategory":"Auto Repair",
            "type":"Services"
        }
    ],
    "sg:phone":"+1 416 759 3280",
    "sg:postcode":"M4A 1W4",
    "sg:province":"ON",
    "sg:tags":[
        "truck"
    ],
    "wof:name":"Sahlani's General Garage Inc",
    "wof:placetype":"venue"
},
  "geometry": {"coordinates":[-79.353554,43.692467],"type":"Point"}
}