{
  "type": "Feature",
  "properties": {
    "addr:full":"4061 Rue Prieur E Montreal-Nord QC H1H 2M9",
    "addr:housenumber":"4061",
    "addr:postcode":"h1h 2m9",
    "addr:street":"Rue Prieur E",
    "iso:country":"CA",
    "sg:address":"4061 Rue Prieur E",
    "sg:city":"Montreal-Nord",
    "sg:classifiers":[
        {
            "category":"Restaurant",
            "type":"Food & Drink"
        }
    ],
    "sg:phone":"+1 514 321 1246",
    "sg:postcode":"H1H 2M9",
    "sg:province":"QC",
    "sg:tags":[
        "delicatessen"
    ],
    "wof:name":"Charcuterie & Fromagerie",
    "wof:placetype":"venue"
},
  "geometry": {"coordinates":[-73.635254,45.588074],"type":"Point"}
}