{
  "type": "Feature",
  "properties": {
    "iso:country":"CA",
    "sg:city":"Concord",
    "sg:classifiers":[
        {
            "category":"Education",
            "subcategory":"Special Training",
            "type":"Public Place"
        }
    ],
    "sg:phone":"+1 905 761 0372",
    "sg:postcode":"L4K 2L7",
    "sg:province":"ON",
    "sg:tags":[
        "instruction",
        "driving"
    ],
    "wof:name":"Great Canada Driving School",
    "wof:placetype":"venue"
},
  "geometry": {"coordinates":[-79.47747802729999,43.7856674194],"type":"Point"}
}