{
  "type": "Feature",
  "properties": {
    "iso:country":"CA",
    "sg:address":"12140 Vulcan Way",
    "sg:city":"Richmond",
    "sg:classifiers":[
        {
            "category":"Manufacturing",
            "subcategory":"Metals",
            "type":"Manufacturing & Wholesale Goods"
        }
    ],
    "sg:phone":"+1 604 273 6441",
    "sg:postcode":"V6V 1J8",
    "sg:province":"BC",
    "sg:tags":[
        "tank"
    ],
    "wof:name":"Stanco Projects",
    "wof:placetype":"venue"
},
  "geometry": {"coordinates":[-123.08908844,49.1937294006],"type":"Point"}
}