{
  "type": "Feature",
  "properties": {
    "addr:full":"377 Rue Dupuy Quebec QC G1L 1P2",
    "addr:housenumber":"377",
    "addr:postcode":"g1l 1p2",
    "addr:street":"Rue Dupuy",
    "iso:country":"CA",
    "sg:address":"377 Rue Dupuy",
    "sg:city":"Quebec",
    "sg:classifiers":[
        {
            "category":"Manufacturing",
            "subcategory":"Motor Vehicles & Parts",
            "type":"Manufacturing & Wholesale Goods"
        }
    ],
    "sg:phone":"+1 418 626 5276",
    "sg:postcode":"G1L 1P2",
    "sg:province":"QC",
    "sg:tags":[
        "automobile",
        "supply"
    ],
    "wof:name":"Du-So Pieces D'Auto Inc",
    "wof:placetype":"venue"
},
  "geometry": {"coordinates":[-71.253716,46.827999],"type":"Point"}
}