{
  "type": "Feature",
  "properties": {
    "addr:full":"159 Clayte St Thunder Bay ON P7A 6S7",
    "addr:housenumber":"159",
    "addr:postcode":"p7a 6s7",
    "addr:street":"Clayte St",
    "iso:country":"CA",
    "sg:address":"159 Clayte St",
    "sg:city":"Thunder Bay",
    "sg:classifiers":[
        {
            "category":"Education",
            "subcategory":"School",
            "type":"Public Place"
        }
    ],
    "sg:phone":"+1 807 345 4482",
    "sg:postcode":"P7A 6S7",
    "sg:province":"ON",
    "wof:name":"Bishop Gallagher Senior Elem",
    "wof:placetype":"venue"
},
  "geometry": {"coordinates":[-89.2245635986,48.4555625916],"type":"Point"}
}