{
  "type": "Feature",
  "properties": {
    "addr:full":"244 O'Connell Dr Corner Brook NL A2H 5N5",
    "addr:housenumber":"244",
    "addr:postcode":"a2h 5n5",
    "addr:street":"O'Connell Dr",
    "iso:country":"CA",
    "sg:address":"244 O'Connell Dr",
    "sg:city":"Corner Brook",
    "sg:classifiers":[
        {
            "category":"Banks & Credit Unions",
            "subcategory":"Bank",
            "type":"Services"
        }
    ],
    "sg:phone":"+1 709 639 2030",
    "sg:postcode":"A2H 5N5",
    "sg:province":"NL",
    "sg:tags":[
        "cashing",
        "loan",
        "check"
    ],
    "wof:name":"Quick Cash",
    "wof:placetype":"venue"
},
  "geometry": {"coordinates":[-57.9373321533,48.9438247681],"type":"Point"}
}