{
  "type": "Feature",
  "properties": {
    "addr:full":"6550 Island Hwy N Nanaimo BC V9V 1K8",
    "addr:housenumber":"6550",
    "addr:postcode":"v9v 1k8",
    "addr:street":"Island Hwy N",
    "iso:country":"CA",
    "sg:address":"6550 Island Hwy N",
    "sg:city":"Nanaimo",
    "sg:classifiers":[
        {
            "category":"Restaurant",
            "type":"Food & Drink"
        }
    ],
    "sg:phone":"+1 250 390 1227",
    "sg:postcode":"V9V 1K8",
    "sg:province":"BC",
    "wof:name":"Ricky's All Day Grill",
    "wof:placetype":"venue"
},
  "geometry": {"coordinates":[-124.04498291,49.2356185913],"type":"Point"}
}