{
  "type": "Feature",
  "properties": {
    "addr:full":"Calgary AB T2S 0J2",
    "addr:postcode":"t2s 0j2",
    "iso:country":"CA",
    "sg:city":"Calgary",
    "sg:classifiers":[
        {
            "category":"Health Services",
            "subcategory":"Doctor",
            "type":"Services"
        }
    ],
    "sg:phone":"+1 403 228 6904",
    "sg:postcode":"T2S 0J2",
    "sg:province":"AB",
    "sg:tags":[
        "physician",
        "surgeon"
    ],
    "wof:name":"Wheeler, Bruce H MD",
    "wof:placetype":"venue"
},
  "geometry": {"coordinates":[-114.069603,51.032547],"type":"Point"}
}