{
  "type": "Feature",
  "properties": {
    "addr:full":"16 John St Thornhill ON L3T 1X8",
    "addr:housenumber":"16",
    "addr:postcode":"l3t 1x8",
    "addr:street":"John St",
    "iso:country":"CA",
    "sg:address":"16 John St",
    "sg:city":"Thornhill",
    "sg:classifiers":[
        {
            "category":"Professional",
            "subcategory":"Lawyer & Legal Services",
            "type":"Services"
        }
    ],
    "sg:phone":"+1 905 882 2422",
    "sg:postcode":"L3T 1X8",
    "sg:province":"ON",
    "sg:tags":[
        "attorney"
    ],
    "wof:name":"Burlew, Edward L",
    "wof:placetype":"venue"
},
  "geometry": {"coordinates":[-79.422707,43.814732],"type":"Point"}
}