{
  "type": "Feature",
  "properties": {
    "addr:full":"Lac-Etchemin QC G0R 1S0",
    "addr:postcode":"g0r 1s0",
    "iso:country":"CA",
    "sg:city":"Lac-Etchemin",
    "sg:classifiers":[
        {
            "category":"Professional",
            "subcategory":"Computer Services",
            "type":"Services"
        }
    ],
    "sg:phone":"+1 418 625 4271",
    "sg:postcode":"G0R 1S0",
    "sg:province":"QC",
    "sg:tags":[
        "telephone",
        "cellular",
        "internet"
    ],
    "wof:name":"Sogetel Inc",
    "wof:placetype":"venue"
},
  "geometry": {"coordinates":[-70.50953699999999,46.399731],"type":"Point"}
}