{
  "type": "Feature",
  "properties": {
    "addr:full":"Saint-Basile-Le-Grand QC J3N 1M2",
    "addr:postcode":"j3n 1m2",
    "iso:country":"CA",
    "sg:city":"Saint-Basile-Le-Grand",
    "sg:classifiers":[
        {
            "category":"Wholesale",
            "subcategory":"Electrical",
            "type":"Manufacturing & Wholesale Goods"
        }
    ],
    "sg:phone":"+1 450 653 1752",
    "sg:postcode":"J3N 1M2",
    "sg:province":"QC",
    "sg:tags":[
        "equipment",
        "electric",
        "supply"
    ],
    "wof:name":"Beaulieu & Lamoureux Inc",
    "wof:placetype":"venue"
},
  "geometry": {"coordinates":[-73.3035125732,45.5246963501],"type":"Point"}
}