{
  "type": "Feature",
  "properties": {
    "addr:full":"Bridge Lake BC V0K 1E0",
    "addr:postcode":"v0k 1e0",
    "iso:country":"CA",
    "sg:city":"Bridge Lake",
    "sg:classifiers":[
        {
            "category":"Travel",
            "subcategory":"Hotels & Motels",
            "type":"Entertainment"
        }
    ],
    "sg:phone":"+1 250 593 4514",
    "sg:postcode":"V0K 1E0",
    "sg:province":"BC",
    "sg:tags":[
        "ranch",
        "guest"
    ],
    "wof:name":"Double T Guest Ranch",
    "wof:placetype":"venue"
},
  "geometry": {"coordinates":[-120.725845337,51.4768447876],"type":"Point"}
}