{
  "type": "Feature",
  "properties": {
    "addr:full":"5600 Sackville St Halifax NS B3J 1L2",
    "addr:housenumber":"5600",
    "addr:postcode":"ns b3j 1l2",
    "addr:street":"Sackville St",
    "iso:country":"CA",
    "sg:address":"5600 Sackville St",
    "sg:city":"Halifax",
    "sg:classifiers":[
        {
            "category":"Communications",
            "subcategory":"Film & Video Production",
            "type":"Services"
        }
    ],
    "sg:phone":"+1 902 420 4002",
    "sg:postcode":"B3J 1L2",
    "sg:province":"NS",
    "sg:tags":[
        "taping"
    ],
    "wof:name":"Centre For Art Tapes",
    "wof:placetype":"venue"
},
  "geometry": {"coordinates":[-63.580086,44.644592],"type":"Point"}
}