{
  "type": "Feature",
  "properties": {
    "iso:country":"CA",
    "sg:city":"Aurora",
    "sg:classifiers":[
        {
            "category":"Professional",
            "subcategory":"Accounting & Tax Preparation",
            "type":"Services"
        }
    ],
    "sg:phone":"+1 905 713 0055",
    "sg:postcode":"L4G 1H5",
    "sg:province":"ON",
    "sg:tags":[
        "accountant"
    ],
    "wof:name":"Mc Creesh & CO",
    "wof:placetype":"venue"
},
  "geometry": {"coordinates":[-79.466019,44.000118],"type":"Point"}
}