{
  "type": "Feature",
  "properties": {
    "addr:full":"351 Rue DE L'Eglise Sullivan QC J0Y 2N0",
    "addr:housenumber":"351",
    "addr:postcode":"j0y 2n0",
    "addr:street":"Rue De L'Eglise",
    "iso:country":"CA",
    "sg:address":"351 Rue DE L'Eglise",
    "sg:city":"Sullivan",
    "sg:classifiers":[
        {
            "category":"Social Services",
            "subcategory":"Child Care",
            "type":"Services"
        }
    ],
    "sg:phone":"+1 819 825 2275",
    "sg:postcode":"J0Y 2N0",
    "sg:province":"QC",
    "wof:name":"Centre DE LA Petite Enfance",
    "wof:placetype":"venue"
},
  "geometry": {"coordinates":[-77.8282089233,48.1318702698],"type":"Point"}
}