{
  "type": "Feature",
  "properties": {
    "addr:full":"349 3E Rue Quebec QC G1L 2S9",
    "addr:housenumber":"349",
    "addr:postcode":"g1l 2s9",
    "addr:street":"3E Rue Quebec",
    "iso:country":"CA",
    "sg:address":"349 3E Rue",
    "sg:city":"Quebec",
    "sg:classifiers":[
        {
            "category":"Retail",
            "subcategory":"Auto Repair",
            "type":"Services"
        }
    ],
    "sg:phone":"+1 418 521 2886",
    "sg:postcode":"G1L 2S9",
    "sg:province":"QC",
    "sg:tags":[
        "repairing",
        "automobile"
    ],
    "wof:name":"Auto Diagno-Ctr",
    "wof:placetype":"venue"
},
  "geometry": {"coordinates":[-71.22479199999999,46.822521],"type":"Point"}
}