{
  "type": "Feature",
  "properties": {
    "iso:country":"CA",
    "sg:address":"3899 Boul Saint-Laurent",
    "sg:city":"Montreal",
    "sg:classifiers":[
        {
            "category":"Restaurant",
            "type":"Food & Drink"
        }
    ],
    "sg:phone":"+1 514 281 6521",
    "sg:postcode":"H2W 1X9",
    "sg:province":"QC",
    "wof:name":"Mondo Fritz",
    "wof:placetype":"venue"
},
  "geometry": {"coordinates":[-73.577629,45.51635],"type":"Point"}
}