{
  "type": "Feature",
  "properties": {
    "addr:full":"15373 Castle Downs Rd NW # 1B Edmonton AB T5X 6C3",
    "addr:housenumber":"15373;1b",
    "addr:postcode":"t5x 6c3",
    "addr:street":"Castle Downs Rd Nw #",
    "iso:country":"CA",
    "sg:address":"15373 Castle Downs Rd NW # 1B",
    "sg:city":"Edmonton",
    "sg:classifiers":[
        {
            "category":"Shopping",
            "subcategory":"Florist",
            "type":"Retail Goods"
        }
    ],
    "sg:phone":"+1 780 457 5898",
    "sg:postcode":"T5X 6C3",
    "sg:province":"AB",
    "wof:name":"Panda Flowers",
    "wof:placetype":"venue"
},
  "geometry": {"coordinates":[-113.516494751,53.6155433655],"type":"Point"}
}