{
  "type": "Feature",
  "properties": {
    "addr:full":"285 Boul Du Roi-Du-Nord Laval QC H7L 1X6",
    "addr:housenumber":"285",
    "addr:postcode":"h7l 1x6",
    "addr:street":"Boul Du Roi-Du-Nord",
    "iso:country":"CA",
    "sg:address":"285 Boul Du Roi-Du-Nord",
    "sg:city":"Laval",
    "sg:classifiers":[
        {
            "category":"Health Services",
            "subcategory":"Nursing And Care Facility",
            "type":"Services"
        }
    ],
    "sg:phone":"+1 450 622 1738",
    "sg:postcode":"H7L 1X6",
    "sg:province":"QC",
    "sg:tags":[
        "home",
        "retirement",
        "community"
    ],
    "wof:name":"Residence Roi Du Nord",
    "wof:placetype":"venue"
},
  "geometry": {"coordinates":[-73.79019927980001,45.6084938049],"type":"Point"}
}