{
  "type": "Feature",
  "properties": {
    "addr:full":"511 Osborne St Winnipeg MB R3L 2A8",
    "addr:housenumber":"511",
    "addr:postcode":"r3l 2a8",
    "addr:street":"Osborne St",
    "iso:country":"CA",
    "sg:address":"511 Osborne St",
    "sg:city":"Winnipeg",
    "sg:classifiers":[
        {
            "category":"Retail",
            "subcategory":"Laundry & Dry Cleaning",
            "type":"Services"
        }
    ],
    "sg:phone":"+1 204 453 0693",
    "sg:postcode":"R3L 2A8",
    "sg:province":"MB",
    "sg:tags":[
        "cleaners",
        "fur",
        "business"
    ],
    "wof:name":"J M Furs",
    "wof:placetype":"venue"
},
  "geometry": {"coordinates":[-97.135666,49.866528],"type":"Point"}
}