{
  "type": "Feature",
  "properties": {
    "addr:full":"1636 Main St # 130 Penticton BC V2A 5G8",
    "addr:housenumber":"1636",
    "addr:postcode":"v2a 5g8",
    "addr:street":"Main St # 130",
    "iso:country":"CA",
    "sg:address":"1636 Main St # 130",
    "sg:city":"Penticton",
    "sg:classifiers":[
        {
            "category":"Banks & Credit Unions",
            "subcategory":"Investment Brokerage",
            "type":"Services"
        }
    ],
    "sg:phone":"+1 250 770 1475",
    "sg:postcode":"V2A 5G8",
    "sg:province":"BC",
    "wof:name":"Edward Jones",
    "wof:placetype":"venue"
},
  "geometry": {"coordinates":[-119.584480286,49.4802436829],"type":"Point"}
}