{
  "type": "Feature",
  "properties": {
    "addr:full":"1320 8th St E Saskatoon SK S7H 0S8",
    "addr:housenumber":"1320",
    "addr:postcode":"s7h 0s8",
    "addr:street":"8Th St E",
    "iso:country":"CA",
    "sg:address":"1320 8th St E",
    "sg:city":"Saskatoon",
    "sg:classifiers":[
        {
            "category":"Retail",
            "subcategory":"Portrait Studio",
            "type":"Services"
        }
    ],
    "sg:phone":"+1 306 933 3393",
    "sg:postcode":"S7H 0S8",
    "sg:province":"SK",
    "sg:tags":[
        "photography"
    ],
    "wof:name":"Cindy Moleski Photography",
    "wof:placetype":"venue"
},
  "geometry": {"coordinates":[-106.63829800000001,52.114658],"type":"Point"}
}