{
  "type": "Feature",
  "properties": {
    "addr:full":"4679 Marine Ave Powell River BC V8A 2L2",
    "addr:housenumber":"4679",
    "addr:postcode":"v8a 2l2",
    "addr:street":"Marine Ave Powell",
    "iso:country":"CA",
    "sg:address":"4679 Marine Ave",
    "sg:city":"Powell River",
    "sg:classifiers":[
        {
            "category":"Shopping",
            "type":"Retail Goods"
        }
    ],
    "sg:phone":"+1 604 485 6467",
    "sg:postcode":"V8A 2L2",
    "sg:province":"BC",
    "sg:tags":[
        "picture",
        "frame"
    ],
    "wof:name":"Synergy Frame Shop Ltd",
    "wof:placetype":"venue"
},
  "geometry": {"coordinates":[-124.52835082999999,49.8421020508],"type":"Point"}
}