{
  "type": "Feature",
  "properties": {
    "addr:full":"632 Barton St E Hamilton ON L8L 2Z9",
    "addr:housenumber":"632",
    "addr:postcode":"l8l 2z9",
    "addr:street":"Barton St E",
    "iso:country":"CA",
    "sg:address":"632 Barton St E",
    "sg:city":"Hamilton",
    "sg:classifiers":[
        {
            "category":"Bars & Pubs",
            "type":"Food & Drink"
        }
    ],
    "sg:phone":"+1 905 544 5846",
    "sg:postcode":"L8L 2Z9",
    "sg:province":"ON",
    "wof:name":"Zak's",
    "wof:placetype":"venue"
},
  "geometry": {"coordinates":[-79.838303,43.256908],"type":"Point"}
}