{
  "type": "Feature",
  "properties": {
    "addr:full":"4620 16A Ave NW Edmonton AB T6L 2S2",
    "addr:housenumber":"4620",
    "addr:postcode":"t6l 2s2",
    "addr:street":"16A Ave Nw",
    "iso:country":"CA",
    "sg:address":"4620 16A Ave NW",
    "sg:city":"Edmonton",
    "sg:classifiers":[
        {
            "category":"Wholesale",
            "subcategory":"Electrical",
            "type":"Manufacturing & Wholesale Goods"
        }
    ],
    "sg:phone":"+1 780 462 0900",
    "sg:postcode":"T6L 2S2",
    "sg:province":"AB",
    "sg:tags":[
        "appliance"
    ],
    "wof:name":"Crown Appliance & Rfrgrtn",
    "wof:placetype":"venue"
},
  "geometry": {"coordinates":[-113.410232544,53.4448432922],"type":"Point"}
}