{
  "type": "Feature",
  "properties": {
    "addr:full":"162 4E Av Dolbeau-Mistassini QC G8L 2S6",
    "addr:housenumber":"162",
    "addr:postcode":"g8l 2s6",
    "addr:street":"4E Av Dolbeau-Mistassini",
    "iso:country":"CA",
    "sg:address":"162 4E Av",
    "sg:city":"Dolbeau-Mistassini",
    "sg:classifiers":[
        {
            "category":"Social Services",
            "type":"Services"
        }
    ],
    "sg:phone":"+1 418 276 6911",
    "sg:postcode":"G8L 2S6",
    "sg:province":"QC",
    "sg:tags":[
        "handicapped",
        "organization",
        "welfare"
    ],
    "wof:name":"Maison D'Integration Norlac",
    "wof:placetype":"venue"
},
  "geometry": {"coordinates":[-72.2242736816,48.877166748],"type":"Point"}
}