{
  "type": "Feature",
  "properties": {
    "addr:full":"32746 Huntingdon Rd Abbotsford BC V2T 5Z1",
    "addr:postcode":"32746;v2t 5z1",
    "addr:street":"Huntingdon Rd",
    "iso:country":"CA",
    "sg:address":"32746 Huntingdon Rd",
    "sg:city":"Abbotsford",
    "sg:classifiers":[
        {
            "category":"Education",
            "subcategory":"School",
            "type":"Public Place"
        }
    ],
    "sg:phone":"+1 604 853 1845",
    "sg:postcode":"V2T 5Z1",
    "sg:province":"BC",
    "wof:name":"South Poplar Elementary",
    "wof:placetype":"venue"
},
  "geometry": {"coordinates":[-122.317626953,49.0167427063],"type":"Point"}
}