{
  "type": "Feature",
  "properties": {
    "addr:full":"121 Rue Martin Blainville QC J7B 1E9",
    "addr:housenumber":"121",
    "addr:postcode":"j7b 1e9",
    "addr:street":"Rue Martin",
    "iso:country":"CA",
    "sg:address":"121 Rue Martin",
    "sg:city":"Blainville",
    "sg:classifiers":[
        {
            "category":"Professional",
            "subcategory":"Business Services",
            "type":"Services"
        }
    ],
    "sg:phone":"+1 450 430 9633",
    "sg:postcode":"J7B 1E9",
    "sg:province":"QC",
    "wof:name":"Gesstion Rhm",
    "wof:placetype":"venue"
},
  "geometry": {"coordinates":[-73.8158416748,45.6487312317],"type":"Point"}
}