{
  "type": "Feature",
  "properties": {
    "iso:country":"CA",
    "sg:address":"200 King St W",
    "sg:city":"Toronto",
    "sg:classifiers":[
        {
            "category":"Manufacturing",
            "subcategory":"Metals",
            "type":"Manufacturing & Wholesale Goods"
        }
    ],
    "sg:phone":"+1 416 666 0676",
    "sg:postcode":"M5H 3T4",
    "sg:province":"ON",
    "sg:tags":[
        "steel"
    ],
    "wof:name":"Spencer Steel Ltd",
    "wof:placetype":"venue"
},
  "geometry": {"coordinates":[-79.3849868774,43.6476974487],"type":"Point"}
}