{
  "type": "Feature",
  "properties": {
    "addr:full":"4350 Victoria Dr Port Alberni BC V9Y 7L1",
    "addr:housenumber":"4350",
    "addr:postcode":"v9y 7l1",
    "addr:street":"Victoria Dr",
    "iso:country":"CA",
    "sg:address":"4350 Victoria Dr",
    "sg:city":"Port Alberni",
    "sg:classifiers":[
        {
            "category":"Retail",
            "subcategory":"Portrait Studio",
            "type":"Services"
        }
    ],
    "sg:phone":"+1 250 724 2720",
    "sg:postcode":"V9Y 7L1",
    "sg:province":"BC",
    "sg:tags":[
        "photographer"
    ],
    "wof:name":"Nichele Portrait Studio",
    "wof:placetype":"venue"
},
  "geometry": {"coordinates":[-124.779358,49.254177],"type":"Point"}
}