{
  "type": "Feature",
  "properties": {
    "addr:full":"1204 Boul Saint-Laurent Montreal QC H2X 2S5",
    "addr:housenumber":"1204",
    "addr:postcode":"h2x 2s5",
    "addr:street":"Boul Saint-Laurent",
    "iso:country":"CA",
    "sg:address":"1204 Boul Saint-Laurent",
    "sg:city":"Montreal",
    "sg:classifiers":[
        {
            "category":"Restaurant",
            "type":"Food & Drink"
        }
    ],
    "sg:phone":"+1 514 875 8455",
    "sg:postcode":"H2X 2S5",
    "sg:province":"QC",
    "sg:tags":[
        "shop",
        "coffee"
    ],
    "wof:name":"Olio Cafe",
    "wof:placetype":"venue"
},
  "geometry": {"coordinates":[-73.5629196167,45.5093002319],"type":"Point"}
}