{
  "type": "Feature",
  "properties": {
    "addr:full":"580 Errol Rd W Sarnia ON N7V 2C1",
    "addr:housenumber":"580",
    "addr:postcode":"n7v 2c1",
    "addr:street":"Errol Rd W",
    "iso:country":"CA",
    "sg:address":"580 Errol Rd W",
    "sg:city":"Sarnia",
    "sg:classifiers":[
        {
            "category":"Social Services",
            "type":"Services"
        }
    ],
    "sg:phone":"+1 519 337 5998",
    "sg:postcode":"N7V 2C1",
    "sg:province":"ON",
    "sg:tags":[
        "organization",
        "welfare"
    ],
    "wof:name":"Start",
    "wof:placetype":"venue"
},
  "geometry": {"coordinates":[-82.39079284669999,42.9935951233],"type":"Point"}
}