{
  "type": "Feature",
  "properties": {
    "addr:full":"8108 Manning Ave Fort Mcmurray AB T9H 1V7",
    "addr:housenumber":"8108",
    "addr:postcode":"t9h 1v7",
    "addr:street":"Manning Ave",
    "iso:country":"CA",
    "sg:address":"8108 Manning Ave",
    "sg:city":"Fort Mcmurray",
    "sg:classifiers":[
        {
            "category":"Building & Trades",
            "subcategory":"Plumbing",
            "type":"Services"
        }
    ],
    "sg:phone":"+1 780 799 7201",
    "sg:postcode":"T9H 1V7",
    "sg:province":"AB",
    "sg:tags":[
        "contractor"
    ],
    "wof:name":"Action Imperial Plumbing & Htg",
    "wof:placetype":"venue"
},
  "geometry": {"coordinates":[-111.346038818,56.7153129578],"type":"Point"}
}