{
  "type": "Feature",
  "properties": {
    "addr:full":"11 Rue Des Jacinthes Blainville QC J7C 4T3",
    "addr:housenumber":"11",
    "addr:postcode":"j7c 4t3",
    "addr:street":"Rue Des Jacinthes",
    "iso:country":"CA",
    "sg:address":"11 Rue Des Jacinthes",
    "sg:city":"Blainville",
    "sg:classifiers":[
        {
            "category":"Wholesale",
            "subcategory":"Drugs",
            "type":"Manufacturing & Wholesale Goods"
        }
    ],
    "sg:phone":"+1 450 430 4079",
    "sg:postcode":"J7C 4T3",
    "sg:province":"QC",
    "sg:tags":[
        "preparation",
        "toilet"
    ],
    "wof:name":"Laboratoires Redken",
    "wof:placetype":"venue"
},
  "geometry": {"coordinates":[-73.87885300000001,45.660671],"type":"Point"}
}