{
  "type": "Feature",
  "properties": {
    "addr:full":"2520 Calgary Trail NW Edmonton AB T6J 5J6",
    "addr:housenumber":"2520",
    "addr:postcode":"t6j 5j6",
    "addr:street":"Calgary Trail Nw",
    "iso:country":"CA",
    "sg:address":"2520 Calgary Trail NW",
    "sg:city":"Edmonton",
    "sg:phone":"+1 780 434 5747",
    "sg:postcode":"T6J 5J6",
    "sg:province":"AB",
    "sg:tags":[
        "oil"
    ],
    "wof:name":"Dandy Oil Products",
    "wof:placetype":"venue"
},
  "geometry": {"coordinates":[-113.49272918699999,53.4561958313],"type":"Point"}
}