{
  "type": "Feature",
  "properties": {
    "iso:country":"CA",
    "sg:address":"43 Rue Archambault",
    "sg:city":"Charlemagne",
    "sg:classifiers":[
        {
            "category":"Building & Trades",
            "subcategory":"Construction",
            "type":"Services"
        }
    ],
    "sg:phone":"+1 450 581 2155",
    "sg:postcode":"J5Z 1Z9",
    "sg:province":"QC",
    "sg:tags":[
        "siding",
        "contractor"
    ],
    "wof:name":"Revetements Metalliques Jc",
    "wof:placetype":"venue"
},
  "geometry": {"coordinates":[-73.486122,45.728378],"type":"Point"}
}