{
  "type": "Feature",
  "properties": {
    "addr:full":"43 Rue Archambault Charlemagne QC J5Z 1Z9",
    "addr:housenumber":"43",
    "addr:postcode":"j5z 1z9",
    "addr:street":"Rue Archambault",
    "iso:country":"CA",
    "sg:address":"43 Rue Archambault",
    "sg:city":"Charlemagne",
    "sg:classifiers":[
        {
            "category":"Building & Trades",
            "subcategory":"Construction",
            "type":"Services"
        }
    ],
    "sg:phone":"+1 450 581 2155",
    "sg:postcode":"J5Z 1Z9",
    "sg:province":"QC",
    "sg:tags":[
        "siding",
        "contractor"
    ],
    "wof:name":"Revetements Metalliques Jc",
    "wof:placetype":"venue"
},
  "geometry": {"coordinates":[-73.48612199999999,45.728378],"type":"Point"}
}