{
  "type": "Feature",
  "properties": {
    "iso:country":"CA",
    "sg:address":"17 Betts Ave",
    "sg:city":"Yorkton",
    "sg:classifiers":[
        {
            "category":"Shopping",
            "subcategory":"Bicycles & Sporting Goods",
            "type":"Retail Goods"
        }
    ],
    "sg:phone":"+1 306 783 5629",
    "sg:postcode":"S3N 1M1",
    "sg:province":"SK",
    "sg:tags":[
        "apparel",
        "saddlery",
        "harness",
        "western"
    ],
    "wof:name":"Hitching Post",
    "wof:placetype":"venue"
},
  "geometry": {"coordinates":[-102.463852,51.210793],"type":"Point"}
}