{
  "type": "Feature",
  "properties": {
    "addr:full":"451 Centre St N Napanee ON K7R 3S4",
    "addr:housenumber":"451",
    "addr:postcode":"k7r 3s4",
    "addr:street":"Centre St N",
    "iso:country":"CA",
    "sg:address":"451 Centre St N",
    "sg:city":"Napanee",
    "sg:classifiers":[
        {
            "category":"Autos & Motor Vehicles",
            "subcategory":"Automobile Sales",
            "type":"Retail Goods"
        }
    ],
    "sg:phone":"+1 613 354 2134",
    "sg:postcode":"K7R 3S4",
    "sg:province":"ON",
    "sg:tags":[
        "car",
        "dealer"
    ],
    "wof:name":"Pringle Ford",
    "wof:placetype":"venue"
},
  "geometry": {"coordinates":[-76.962227,44.259323],"type":"Point"}
}