{
  "type": "Feature",
  "properties": {
    "iso:country":"CA",
    "sg:address":"413 Coverdale Rd",
    "sg:city":"Riverview",
    "sg:classifiers":[
        {
            "category":"Restaurant",
            "type":"Food & Drink"
        }
    ],
    "sg:phone":"+1 506 387 7710",
    "sg:postcode":"E1B 3K3",
    "sg:province":"NB",
    "wof:name":"Kfc",
    "wof:placetype":"venue"
},
  "geometry": {"coordinates":[-64.799873,46.065559],"type":"Point"}
}