{
  "type": "Feature",
  "properties": {
    "addr:full":"225 Hill St Corunna ON N0N 1G0",
    "addr:housenumber":"225",
    "addr:postcode":"n0n 1g0",
    "addr:street":"Hill St",
    "iso:country":"CA",
    "sg:address":"225 Hill St",
    "sg:city":"Corunna",
    "sg:classifiers":[
        {
            "category":"Shopping",
            "subcategory":"Used Merchandise",
            "type":"Retail Goods"
        }
    ],
    "sg:phone":"+1 519 862 4645",
    "sg:postcode":"N0N 1G0",
    "sg:province":"ON",
    "sg:tags":[
        "antique"
    ],
    "wof:name":"Knight's Second Time Around",
    "wof:placetype":"venue"
},
  "geometry": {"coordinates":[-82.449112,42.88834],"type":"Point"}
}