{
  "type": "Feature",
  "properties": {
    "addr:full":"Toronto ON M6H 4H5",
    "addr:postcode":"m6h 4h5",
    "iso:country":"CA",
    "sg:city":"Toronto",
    "sg:classifiers":[
        {
            "category":"Health Services",
            "subcategory":"Doctor",
            "type":"Services"
        }
    ],
    "sg:phone":"+1 416 652 3540",
    "sg:postcode":"M6H 4H5",
    "sg:province":"ON",
    "sg:tags":[
        "physician",
        "surgeon"
    ],
    "wof:name":"Perez, Eduardo MD",
    "wof:placetype":"venue"
},
  "geometry": {"coordinates":[-79.442635,43.677315],"type":"Point"}
}