{
  "type": "Feature",
  "properties": {
    "addr:full":"758 Dovercourt Rd Toronto ON M6H 2X2",
    "addr:housenumber":"758",
    "addr:postcode":"m6h 2x2",
    "addr:street":"Dovercourt Rd",
    "iso:country":"CA",
    "sg:address":"758 Dovercourt Rd",
    "sg:city":"Toronto",
    "sg:classifiers":[
        {
            "category":"Restaurant",
            "type":"Food & Drink"
        }
    ],
    "sg:phone":"+1 416 531 1474",
    "sg:postcode":"M6H 2X2",
    "sg:province":"ON",
    "wof:name":"Top Taste",
    "wof:placetype":"venue"
},
  "geometry": {"coordinates":[-79.42974853520001,43.6614456177],"type":"Point"}
}