{
  "type": "Feature",
  "properties": {
    "addr:full":"284 132 Rte E Nouvelle QC G0C 2E0",
    "addr:housenumber":"132",
    "addr:postcode":"qc g0c 2e0",
    "addr:street":"Rte E",
    "iso:country":"CA",
    "sg:address":"284 132 Rte E",
    "sg:city":"Nouvelle",
    "sg:classifiers":[
        {
            "category":"Retail",
            "subcategory":"Auto Repair",
            "type":"Services"
        }
    ],
    "sg:phone":"+1 418 794 2743",
    "sg:postcode":"G0C 2E0",
    "sg:province":"QC",
    "sg:tags":[
        "repairing",
        "automobile"
    ],
    "wof:name":"Savoie Donat",
    "wof:placetype":"venue"
},
  "geometry": {"coordinates":[-66.300529,48.130966],"type":"Point"}
}