{
  "type": "Feature",
  "properties": {
    "addr:full":"3088 Gibbins Rd Duncan BC V9L 1E8",
    "addr:housenumber":"3088",
    "addr:postcode":"v9l 1e8",
    "addr:street":"Gibbins Rd",
    "iso:country":"CA",
    "sg:address":"3088 Gibbins Rd",
    "sg:city":"Duncan",
    "sg:classifiers":[
        {
            "category":"Government",
            "subcategory":"Office",
            "type":"Public Place"
        }
    ],
    "sg:phone":"+1 250 709 3040",
    "sg:postcode":"V9L 1E8",
    "sg:province":"BC",
    "wof:name":"B C Mental Health Ctr",
    "wof:placetype":"venue"
},
  "geometry": {"coordinates":[-123.70738220200001,48.779094696],"type":"Point"}
}