{
  "type": "Feature",
  "properties": {
    "addr:full":"100 Legacy Rd Ottawa ON K1G 5T8",
    "addr:housenumber":"100",
    "addr:postcode":"k1g 5t8",
    "addr:street":"Legacy Rd",
    "iso:country":"CA",
    "sg:address":"100 Legacy Rd",
    "sg:city":"Ottawa",
    "sg:classifiers":[
        {
            "category":"Wholesale",
            "subcategory":"Groceries",
            "type":"Manufacturing & Wholesale Goods"
        }
    ],
    "sg:phone":"+1 613 737 7000",
    "sg:postcode":"K1G 5T8",
    "sg:province":"ON",
    "sg:tags":[
        "grocer"
    ],
    "wof:name":"Summit Foods Svc Distr Inc",
    "wof:placetype":"venue"
},
  "geometry": {"coordinates":[-75.60938299999999,45.38295],"type":"Point"}
}