{
  "type": "Feature",
  "properties": {
    "addr:full":"1100 Av Laurier E Montreal QC H2J 1G7",
    "addr:housenumber":"1100",
    "addr:postcode":"h2j 1g7",
    "addr:street":"Av Laurier E",
    "iso:country":"CA",
    "sg:address":"1100 Av Laurier E",
    "sg:city":"Montreal",
    "sg:classifiers":[
        {
            "category":"Shopping",
            "subcategory":"Computers & Home Electronics",
            "type":"Retail Goods"
        }
    ],
    "sg:phone":"+1 514 272 1688",
    "sg:postcode":"H2J 1G7",
    "sg:province":"QC",
    "sg:tags":[
        "parts",
        "supply"
    ],
    "wof:name":"Ordine",
    "wof:placetype":"venue"
},
  "geometry": {"coordinates":[-73.58576965330001,45.5310897827],"type":"Point"}
}