{
  "type": "Feature",
  "properties": {
    "addr:full":"661 Grande Allee E Quebec QC G1R 2K4",
    "addr:housenumber":"661",
    "addr:postcode":"g1r 2k4",
    "addr:street":"Grande Allee E",
    "iso:country":"CA",
    "sg:address":"661 Grande Allee E",
    "sg:city":"Quebec",
    "sg:classifiers":[
        {
            "category":"Travel",
            "subcategory":"Hotels & Motels",
            "type":"Entertainment"
        }
    ],
    "sg:phone":"+1 418 522 2652",
    "sg:postcode":"G1R 2K4",
    "sg:province":"QC",
    "wof:name":"Manoir Lafayette",
    "wof:placetype":"venue"
},
  "geometry": {"coordinates":[-71.21595000000001,46.806499],"type":"Point"}
}