{
  "type": "Feature",
  "properties": {
    "addr:full":"39 Spring Garden Blvd St Catharines ON L2N 3P9",
    "addr:housenumber":"39",
    "addr:postcode":"l2n 3p9",
    "addr:street":"Spring Garden Blvd",
    "iso:country":"CA",
    "sg:address":"39 Spring Garden Blvd",
    "sg:city":"St Catharines",
    "sg:classifiers":[
        {
            "category":"Building & Trades",
            "subcategory":"Construction",
            "type":"Services"
        }
    ],
    "sg:phone":"+1 905 938 7275",
    "sg:postcode":"L2N 3P9",
    "sg:province":"ON",
    "sg:tags":[
        "general",
        "contractor"
    ],
    "wof:name":"Hutchinson & Assoc",
    "wof:placetype":"venue"
},
  "geometry": {"coordinates":[-79.23915100000001,43.210407],"type":"Point"}
}