{
  "type": "Feature",
  "properties": {
    "addr:full":"107 Cooks Point Rd Clarks Harbour NS B0W 1P0",
    "addr:housenumber":"107",
    "addr:postcode":"b0w 1p0",
    "addr:street":"Cooks Point Rd",
    "iso:country":"CA",
    "sg:address":"107 Cooks Point Rd",
    "sg:city":"Clarks Harbour",
    "sg:classifiers":[
        {
            "category":"Food & Beverages",
            "subcategory":"Meat & Fish",
            "type":"Retail Goods"
        }
    ],
    "sg:phone":"+1 902 745 3256",
    "sg:postcode":"B0W 1P0",
    "sg:province":"NS",
    "sg:tags":[
        "lobster"
    ],
    "wof:name":"R & L Fisheries",
    "wof:placetype":"venue"
},
  "geometry": {"coordinates":[-66.1195220947,43.8501434326],"type":"Point"}
}