{
  "type": "Feature",
  "properties": {
    "addr:full":"280 Rue Beaudry N Joliette QC J6E 6A6",
    "addr:housenumber":"280",
    "addr:postcode":"j6e 6a6",
    "addr:street":"Rue Beaudry N",
    "iso:country":"CA",
    "sg:address":"280 Rue Beaudry N",
    "sg:city":"Joliette",
    "sg:classifiers":[
        {
            "category":"Insurance",
            "subcategory":"Insurance Agent",
            "type":"Services"
        }
    ],
    "sg:phone":"+1 450 759 8151",
    "sg:postcode":"J6E 6A6",
    "sg:province":"QC",
    "wof:name":"Assurances Raymond Malo Inc",
    "wof:placetype":"venue"
},
  "geometry": {"coordinates":[-73.453323,46.021709],"type":"Point"}
}