{
  "type": "Feature",
  "properties": {
    "addr:full":"Vulcan AB T0L 2B0",
    "addr:postcode":"t0l 2b0",
    "iso:country":"CA",
    "sg:city":"Vulcan",
    "sg:classifiers":[
        {
            "category":"Government",
            "subcategory":"Office",
            "type":"Public Place"
        }
    ],
    "sg:phone":"+1 403 485 6971",
    "sg:postcode":"T0L 2B0",
    "sg:province":"AB",
    "wof:name":"Alberta Fish & Wildlife Dist",
    "wof:placetype":"venue"
},
  "geometry": {"coordinates":[-113.258178711,50.3973388672],"type":"Point"}
}