{
  "type": "Feature",
  "properties": {
    "addr:full":"Montreal QC H2N 2L1",
    "addr:postcode":"h2n 2l1",
    "iso:country":"CA",
    "sg:city":"Montreal",
    "sg:classifiers":[
        {
            "category":"Wholesale",
            "subcategory":"Apparel",
            "type":"Manufacturing & Wholesale Goods"
        }
    ],
    "sg:phone":"+1 514 381 7575",
    "sg:postcode":"H2N 2L1",
    "sg:province":"QC",
    "sg:tags":[
        "clothing"
    ],
    "wof:name":"Shaker Vasico Intl Inc",
    "wof:placetype":"venue"
},
  "geometry": {"coordinates":[-73.65525100000001,45.537827],"type":"Point"}
}