{
  "type": "Feature",
  "properties": {
    "addr:full":"10203 97 St Westlock AB T7P 2H1",
    "addr:housenumber":"10203",
    "addr:postcode":"t7p 2h1",
    "addr:street":"97 St",
    "iso:country":"CA",
    "sg:address":"10203 97 St",
    "sg:city":"Westlock",
    "sg:classifiers":[
        {
            "category":"Travel",
            "subcategory":"Hotels & Motels",
            "type":"Entertainment"
        }
    ],
    "sg:phone":"+1 780 349 8249",
    "sg:postcode":"T7P 2H1",
    "sg:province":"AB",
    "sg:tags":[
        "housing",
        "senior",
        "citizen"
    ],
    "wof:name":"Smithfield Lodge",
    "wof:placetype":"venue"
},
  "geometry": {"coordinates":[-113.85424,54.149239],"type":"Point"}
}