{
  "type": "Feature",
  "properties": {
    "addr:full":"45916 Wellington Ave Chilliwack BC V2P 2C7",
    "addr:housenumber":"45916",
    "addr:postcode":"v2p 2c7",
    "addr:street":"Wellington Ave",
    "iso:country":"CA",
    "sg:address":"45916 Wellington Ave",
    "sg:city":"Chilliwack",
    "sg:classifiers":[
        {
            "category":"Sports & Exercise",
            "subcategory":"Bowling",
            "type":"Entertainment"
        }
    ],
    "sg:phone":"+1 604 795 2637",
    "sg:postcode":"V2P 2C7",
    "sg:province":"BC",
    "sg:tags":[
        "center"
    ],
    "wof:name":"Chillibowl Lanes Ltd",
    "wof:placetype":"venue"
},
  "geometry": {"coordinates":[-121.95388,49.171238],"type":"Point"}
}