{
  "type": "Feature",
  "properties": {
    "iso:country":"CA",
    "sg:address":"162 Boul Labelle",
    "sg:city":"Rosemere",
    "sg:classifiers":[
        {
            "category":"Restaurant",
            "type":"Food & Drink"
        }
    ],
    "sg:phone":"+1 450 434 9693",
    "sg:postcode":"J7A 2H1",
    "sg:province":"QC",
    "wof:name":"Cafe Depot",
    "wof:placetype":"venue"
},
  "geometry": {"coordinates":[-73.799881,45.622402],"type":"Point"}
}