{
  "type": "Feature",
  "properties": {
    "addr:full":"North York ON M2N 6H7",
    "addr:postcode":"m2n 6h7",
    "iso:country":"CA",
    "sg:city":"North York",
    "sg:classifiers":[
        {
            "category":"Health Services",
            "subcategory":"Doctor",
            "type":"Services"
        }
    ],
    "sg:phone":"+1 416 218 0529",
    "sg:postcode":"M2N 6H7",
    "sg:province":"ON",
    "sg:tags":[
        "physician",
        "surgeon"
    ],
    "wof:name":"Baker, Gordon MD",
    "wof:placetype":"venue"
},
  "geometry": {"coordinates":[-79.38832855219999,43.7666969299],"type":"Point"}
}