{
  "type": "Feature",
  "properties": {
    "iso:country":"CA",
    "sg:address":"120 Collis St",
    "sg:city":"Creston",
    "sg:classifiers":[
        {
            "category":"Retail",
            "subcategory":"Repair Shop",
            "type":"Services"
        }
    ],
    "sg:phone":"+1 250 428 7464",
    "sg:postcode":"V0B 1G6",
    "sg:province":"BC",
    "sg:tags":[
        "machine",
        "welding"
    ],
    "wof:name":"Comfort Welding Ltd",
    "wof:placetype":"venue"
},
  "geometry": {"coordinates":[-116.525611877,49.1171913147],"type":"Point"}
}