{
  "type": "Feature",
  "properties": {
    "iso:country":"CA",
    "sg:city":"Winnipeg",
    "sg:classifiers":[
        {
            "category":"Freight",
            "type":"Transportation"
        }
    ],
    "sg:phone":"+1 204 784 9277",
    "sg:postcode":"R3H 0Z7",
    "sg:province":"MB",
    "sg:tags":[
        "broker",
        "customs"
    ],
    "wof:name":"Affiliated Customs Brokers Ltd",
    "wof:placetype":"venue"
},
  "geometry": {"coordinates":[-97.22290802000001,49.8993759155],"type":"Point"}
}