{
  "type": "Feature",
  "properties": {
    "addr:full":"69 Jamie Ave Nepean ON K2E 7Y6",
    "addr:housenumber":"69",
    "addr:postcode":"k2e 7y6",
    "addr:street":"Jamie Ave",
    "iso:country":"CA",
    "sg:address":"69 Jamie Ave",
    "sg:city":"Nepean",
    "sg:classifiers":[
        {
            "category":"Home & Garden",
            "subcategory":"Building Materials",
            "type":"Retail Goods"
        }
    ],
    "sg:phone":"+1 613 723 7797",
    "sg:postcode":"K2E 7Y6",
    "sg:province":"ON",
    "wof:name":"Baffin Building Systems",
    "wof:placetype":"venue"
},
  "geometry": {"coordinates":[-75.71775100000001,45.335926],"type":"Point"}
}