{
  "type": "Feature",
  "properties": {
    "addr:full":"1708 152 St Surrey BC V4A 4N4",
    "addr:housenumber":"1708",
    "addr:postcode":"v4a 4n4",
    "addr:street":"152 St",
    "iso:country":"CA",
    "sg:address":"1708 152 St",
    "sg:city":"Surrey",
    "sg:classifiers":[
        {
            "category":"Shopping",
            "subcategory":"Bicycles & Sporting Goods",
            "type":"Retail Goods"
        }
    ],
    "sg:phone":"+1 604 531 7879",
    "sg:postcode":"V4A 4N4",
    "sg:province":"BC",
    "wof:name":"Peninsula Runners CO",
    "wof:placetype":"venue"
},
  "geometry": {"coordinates":[-122.801055908,49.0331954956],"type":"Point"}
}