{
  "type": "Feature",
  "properties": {
    "addr:full":"Stirling ON K0K 3E0",
    "addr:postcode":"k0k 3e0",
    "iso:country":"CA",
    "sg:city":"Stirling",
    "sg:classifiers":[
        {
            "category":"Retail",
            "subcategory":"Veterinary Services",
            "type":"Services"
        }
    ],
    "sg:phone":"+1 613 395 3386",
    "sg:postcode":"K0K 3E0",
    "sg:province":"ON",
    "sg:tags":[
        "veterinarian"
    ],
    "wof:name":"Heagle, Robb DVM",
    "wof:placetype":"venue"
},
  "geometry": {"coordinates":[-76.8320007324,44.440700531],"type":"Point"}
}