{
  "type": "Feature",
  "properties": {
    "addr:full":"20 Fountain Head Lane Miramichi NB E1V 4A1",
    "addr:housenumber":"20",
    "addr:postcode":"e1v 4a1",
    "addr:street":"Fountain Head Lane",
    "iso:country":"CA",
    "sg:address":"20 Fountain Head Lane",
    "sg:city":"Miramichi",
    "sg:classifiers":[
        {
            "category":"Restaurant",
            "type":"Food & Drink"
        }
    ],
    "sg:phone":"+1 506 622 3078",
    "sg:postcode":"E1V 4A1",
    "sg:province":"NB",
    "wof:name":"Goodie Shop",
    "wof:placetype":"venue"
},
  "geometry": {"coordinates":[-65.563332,47.002098],"type":"Point"}
}