{
  "type": "Feature",
  "properties": {
    "addr:full":"333 11 Ave SW #1440 Calgary AB T2R 1L9",
    "addr:postcode":"t2r 1l9",
    "addr:street":"333 11 Ave Sw # 1440",
    "iso:country":"CA",
    "sg:address":"333 11 Ave SW #1440",
    "sg:city":"Calgary",
    "sg:classifiers":[
        {
            "category":"Professional",
            "subcategory":"Lawyer & Legal Services",
            "type":"Services"
        }
    ],
    "sg:phone":"+1 403 292 0700",
    "sg:postcode":"T2R 1L9",
    "sg:province":"AB",
    "sg:tags":[
        "attorney"
    ],
    "wof:name":"Joffe, Hal",
    "wof:placetype":"venue"
},
  "geometry": {"coordinates":[-114.068924,51.0424],"type":"Point"}
}