{
  "type": "Feature",
  "properties": {
    "iso:country":"CA",
    "sg:address":"4341 Ontario St",
    "sg:city":"Beamsville",
    "sg:classifiers":[
        {
            "category":"Social Services",
            "subcategory":"Child Care",
            "type":"Services"
        }
    ],
    "sg:phone":"+1 905 563 1841",
    "sg:postcode":"L0R 1B0",
    "sg:province":"ON",
    "wof:name":"Beamsville Coop Nursery School",
    "wof:placetype":"venue"
},
  "geometry": {"coordinates":[-79.47630310060001,43.1680145264],"type":"Point"}
}