{
  "type": "Feature",
  "properties": {
    "addr:full":"162 Gore St # 203S Sault Ste Marie ON P6A 1M2",
    "addr:housenumber":"162",
    "addr:postcode":"p6a 1m2",
    "addr:street":"Gore St # 203S",
    "iso:country":"CA",
    "sg:address":"162 Gore St # 203S",
    "sg:city":"Sault Ste Marie",
    "sg:classifiers":[
        {
            "category":"Professional",
            "subcategory":"Accounting & Tax Preparation",
            "type":"Services"
        }
    ],
    "sg:phone":"+1 705 759 6689",
    "sg:postcode":"P6A 1M2",
    "sg:province":"ON",
    "sg:tags":[
        "bookkeeping",
        "general"
    ],
    "wof:name":"Terry Laird Bookkeeping Svc",
    "wof:placetype":"venue"
},
  "geometry": {"coordinates":[-84.339699,46.519333],"type":"Point"}
}