{
  "type": "Feature",
  "properties": {
    "iso:country":"CA",
    "sg:city":"Willow Bunch",
    "sg:classifiers":[
        {
            "category":"Retail",
            "subcategory":"Auto Repair",
            "type":"Services"
        }
    ],
    "sg:phone":"+1 306 473 2261",
    "sg:postcode":"S0H 4K0",
    "sg:province":"SK",
    "sg:tags":[
        "body",
        "automobile",
        "painting"
    ],
    "wof:name":"Southern Auto Body",
    "wof:placetype":"venue"
},
  "geometry": {"coordinates":[-105.638267517,49.3918151855],"type":"Point"}
}