{
  "type": "Feature",
  "properties": {
    "addr:full":"9 Longworth St Souris PE C0A 2B0",
    "addr:housenumber":"9",
    "addr:postcode":"c0a 2b0",
    "addr:street":"Longworth St",
    "iso:country":"CA",
    "sg:address":"9 Longworth St",
    "sg:city":"Souris",
    "sg:classifiers":[
        {
            "category":"Travel",
            "subcategory":"Hotels & Motels",
            "type":"Entertainment"
        }
    ],
    "sg:phone":"+1 902 687 4626",
    "sg:postcode":"C0A 2B0",
    "sg:province":"PE",
    "sg:tags":[
        "tourist",
        "accommodation"
    ],
    "wof:name":"A Place To Stay",
    "wof:placetype":"venue"
},
  "geometry": {"coordinates":[-62.252228,46.358746],"type":"Point"}
}