{
  "type": "Feature",
  "properties": {
    "addr:full":"391 Campbell St Winnipeg MB R3N 1B6",
    "addr:housenumber":"391",
    "addr:postcode":"r3n 1b6",
    "addr:street":"Campbell St",
    "iso:country":"CA",
    "sg:address":"391 Campbell St",
    "sg:city":"Winnipeg",
    "sg:classifiers":[
        {
            "category":"Wholesale",
            "subcategory":"Durable Goods & Equipment",
            "type":"Manufacturing & Wholesale Goods"
        }
    ],
    "sg:phone":"+1 204 489 1214",
    "sg:postcode":"R3N 1B6",
    "sg:province":"MB",
    "sg:tags":[
        "exporter"
    ],
    "wof:name":"Aquarian Industries Int'l Ltd",
    "wof:placetype":"venue"
},
  "geometry": {"coordinates":[-97.1909408569,49.8677558899],"type":"Point"}
}