{
  "type": "Feature",
  "properties": {
    "iso:country":"CA",
    "sg:address":"99 Duncan Mill Rd",
    "sg:city":"North York",
    "sg:classifiers":[
        {
            "category":"Organizations",
            "subcategory":"Professional Association",
            "type":"Services"
        }
    ],
    "sg:phone":"+1 416 445 9910",
    "sg:postcode":"M3B 1Z2",
    "sg:province":"ON",
    "sg:tags":[
        "real estate"
    ],
    "wof:name":"Ontario Real Estate Assn",
    "wof:placetype":"venue"
},
  "geometry": {"coordinates":[-79.3558807373,43.7614440918],"type":"Point"}
}