{
  "type": "Feature",
  "properties": {
    "addr:full":"Edmonton AB T5S 1J9",
    "addr:postcode":"t5s 1j9",
    "iso:country":"CA",
    "sg:city":"Edmonton",
    "sg:classifiers":[
        {
            "category":"Shopping",
            "subcategory":"Computers & Home Electronics",
            "type":"Retail Goods"
        }
    ],
    "sg:phone":"+1 780 455 9197",
    "sg:postcode":"T5S 1J9",
    "sg:province":"AB",
    "sg:tags":[
        "equipment",
        "dealer",
        "software"
    ],
    "wof:name":"Kanotech Information Systems",
    "wof:placetype":"venue"
},
  "geometry": {"coordinates":[-113.62571,53.545506],"type":"Point"}
}