{
  "type": "Feature",
  "properties": {
    "addr:full":"736 Granville St # 316 Vancouver BC V6Z 1G3",
    "addr:housenumber":"736",
    "addr:postcode":"v6z 1g3",
    "addr:street":"Granville St # 316",
    "iso:country":"CA",
    "sg:address":"736 Granville St # 316",
    "sg:city":"Vancouver",
    "sg:classifiers":[
        {
            "category":"Manufacturing",
            "subcategory":"Jewelry",
            "type":"Manufacturing & Wholesale Goods"
        }
    ],
    "sg:phone":"+1 604 683 5688",
    "sg:postcode":"V6Z 1G3",
    "sg:province":"BC",
    "sg:tags":[
        "jeweler"
    ],
    "wof:name":"Bonds Jewellery Appraisal Lab",
    "wof:placetype":"venue"
},
  "geometry": {"coordinates":[-123.118606567,49.281955719],"type":"Point"}
}