{
  "type": "Feature",
  "properties": {
    "addr:full":"747 Princess Ave Victoria BC V8T 1K5",
    "addr:housenumber":"747",
    "addr:postcode":"v8t 1k5",
    "addr:street":"Princess Ave",
    "iso:country":"CA",
    "sg:address":"747 Princess Ave",
    "sg:city":"Victoria",
    "sg:classifiers":[
        {
            "category":"Manufacturing",
            "subcategory":"Metals",
            "type":"Manufacturing & Wholesale Goods"
        }
    ],
    "sg:phone":"+1 250 381 4747",
    "sg:postcode":"V8T 1K5",
    "sg:province":"BC",
    "sg:tags":[
        "mail",
        "storage"
    ],
    "wof:name":"Target Storage & Mini Wrhse",
    "wof:placetype":"venue"
},
  "geometry": {"coordinates":[-123.36363220200001,48.433265686],"type":"Point"}
}