{
  "type": "Feature",
  "properties": {
    "addr:full":"388 11th St Hanover ON N4N 1S5",
    "addr:housenumber":"388",
    "addr:postcode":"n4n 1s5",
    "addr:street":"11Th St",
    "iso:country":"CA",
    "sg:address":"388 11th St",
    "sg:city":"Hanover",
    "sg:classifiers":[
        {
            "category":"Home & Garden",
            "subcategory":"Building Materials",
            "type":"Retail Goods"
        }
    ],
    "sg:phone":"+1 519 364 3049",
    "sg:postcode":"N4N 1S5",
    "sg:province":"ON",
    "sg:tags":[
        "siding"
    ],
    "wof:name":"Ron Pike Aluminum Products",
    "wof:placetype":"venue"
},
  "geometry": {"coordinates":[-81.02428399999999,44.153801],"type":"Point"}
}