{
  "type": "Feature",
  "properties": {
    "addr:full":"10195 Av Royale Sainte-Anne-DE-Beaupre QC G0A 3C0",
    "addr:housenumber":"10195",
    "addr:postcode":"g0a 3c0",
    "addr:street":"Av Royale",
    "iso:country":"CA",
    "sg:address":"10195 Av Royale",
    "sg:city":"Sainte-Anne-DE-Beaupre",
    "sg:classifiers":[
        {
            "category":"Food & Beverages",
            "subcategory":"Groceries & Convenience Stores",
            "type":"Retail Goods"
        }
    ],
    "sg:phone":"+1 418 827 5136",
    "sg:postcode":"G0A 3C0",
    "sg:province":"QC",
    "sg:tags":[
        "grocer"
    ],
    "wof:name":"Accommodation Ste-Anne Enr",
    "wof:placetype":"venue"
},
  "geometry": {"coordinates":[-70.924454,47.026478],"type":"Point"}
}