{
  "type": "Feature",
  "properties": {
    "addr:full":"1749 Paris St Sudbury ON P3E 4V4",
    "addr:housenumber":"1749",
    "addr:postcode":"p3e 4v4",
    "addr:street":"Paris St",
    "iso:country":"CA",
    "sg:address":"1749 Paris St",
    "sg:city":"Sudbury",
    "sg:classifiers":[
        {
            "category":"Real Estate",
            "subcategory":"Real Estate Operator",
            "type":"Services"
        }
    ],
    "sg:phone":"+1 705 688 6059",
    "sg:postcode":"P3E 4V4",
    "sg:province":"ON",
    "sg:tags":[
        "apartment"
    ],
    "wof:name":"Parkview Apartments",
    "wof:placetype":"venue"
},
  "geometry": {"coordinates":[-81.001442,46.456909],"type":"Point"}
}