{
  "type": "Feature",
  "properties": {
    "addr:full":"75 Federal Rd Welland ON L3B 3P2",
    "addr:housenumber":"75",
    "addr:postcode":"l3b 3p2",
    "addr:street":"Federal Rd",
    "iso:country":"CA",
    "sg:address":"75 Federal Rd",
    "sg:city":"Welland",
    "sg:classifiers":[
        {
            "category":"Bus Charters",
            "type":"Transportation"
        }
    ],
    "sg:phone":"+1 905 732 6844",
    "sg:postcode":"L3B 3P2",
    "sg:province":"ON",
    "sg:tags":[
        "line",
        "rental"
    ],
    "wof:name":"Welland Transit",
    "wof:placetype":"venue"
},
  "geometry": {"coordinates":[-79.25885772709999,42.9660263062],"type":"Point"}
}