{
  "type": "Feature",
  "properties": {
    "iso:country":"CA",
    "sg:address":"923 Wyandotte St E",
    "sg:city":"Windsor",
    "sg:classifiers":[
        {
            "category":"Shopping",
            "subcategory":"Used Merchandise",
            "type":"Retail Goods"
        }
    ],
    "sg:phone":"+1 519 977 7108",
    "sg:postcode":"N9A 3K1",
    "sg:province":"ON",
    "sg:tags":[
        "furniture"
    ],
    "wof:name":"Rivoli Used Furniture",
    "wof:placetype":"venue"
},
  "geometry": {"coordinates":[-83.02346,42.318718],"type":"Point"}
}