{
  "type": "Feature",
  "properties": {
    "iso:country":"CA",
    "sg:address":"106 Eagleson Rd",
    "sg:city":"Kanata",
    "sg:classifiers":[
        {
            "category":"Autos & Motor Vehicles",
            "subcategory":"Fuel & Gas Station",
            "type":"Retail Goods"
        }
    ],
    "sg:phone":"+1 613 592 5613",
    "sg:postcode":"K2L 2P1",
    "sg:province":"ON",
    "sg:tags":[
        "oil"
    ],
    "wof:name":"Shell",
    "wof:placetype":"venue"
},
  "geometry": {"coordinates":[-75.8818893433,45.3126754761],"type":"Point"}
}