{
  "type": "Feature",
  "properties": {
    "iso:country":"CA",
    "sg:city":"Calgary",
    "sg:classifiers":[
        {
            "category":"Insurance",
            "subcategory":"Insurance Agent",
            "type":"Services"
        }
    ],
    "sg:phone":"+1 403 210 3135",
    "sg:postcode":"T2M 4S2",
    "sg:province":"AB",
    "wof:name":"Portage LA Prairie Mutual Ins",
    "wof:placetype":"venue"
},
  "geometry": {"coordinates":[-114.08512878400001,51.0671348572],"type":"Point"}
}