{
  "type": "Feature",
  "properties": {
    "addr:full":"21 Boul Cartier Riviere-Du-Loup QC G5R 5Z3",
    "addr:housenumber":"21",
    "addr:postcode":"g5r 5z3",
    "addr:street":"Boul Cartier Riviere-Du-Loup",
    "iso:country":"CA",
    "sg:address":"21 Boul Cartier",
    "sg:city":"Riviere-Du-Loup",
    "sg:classifiers":[
        {
            "category":"Organizations",
            "subcategory":"Religious Organization",
            "type":"Services"
        }
    ],
    "sg:phone":"+1 418 867 1754",
    "sg:postcode":"G5R 5Z3",
    "sg:province":"QC",
    "sg:tags":[
        "church"
    ],
    "wof:name":"Temoins DE Jehovah",
    "wof:placetype":"venue"
},
  "geometry": {"coordinates":[-69.5489730835,47.8586997986],"type":"Point"}
}