{
  "type": "Feature",
  "properties": {
    "addr:full":"Winnipeg MB R3T 2B6",
    "addr:postcode":"r3t 2b6",
    "iso:country":"CA",
    "sg:city":"Winnipeg",
    "sg:classifiers":[
        {
            "category":"Personal",
            "subcategory":"Barber",
            "type":"Services"
        }
    ],
    "sg:phone":"+1 204 475 0049",
    "sg:postcode":"R3T 2B6",
    "sg:province":"MB",
    "wof:name":"Cec Richards Barber Shop",
    "wof:placetype":"venue"
},
  "geometry": {"coordinates":[-97.152672,49.839817],"type":"Point"}
}