{
  "type": "Feature",
  "properties": {
    "addr:full":"252 Main St S Newmarket ON L3Y 3Z5",
    "addr:housenumber":"252",
    "addr:postcode":"l3y 3z5",
    "addr:street":"Main St S",
    "iso:country":"CA",
    "sg:address":"252 Main St S",
    "sg:city":"Newmarket",
    "sg:classifiers":[
        {
            "category":"Home & Garden",
            "subcategory":"Hardware",
            "type":"Retail Goods"
        }
    ],
    "sg:phone":"+1 905 836 7777",
    "sg:postcode":"L3Y 3Z5",
    "sg:province":"ON",
    "wof:name":"J D Wholesale",
    "wof:placetype":"venue"
},
  "geometry": {"coordinates":[-79.45682499999999,44.052063],"type":"Point"}
}