{
  "type": "Feature",
  "properties": {
    "addr:full":"Saint John NB E2L 2C4",
    "addr:postcode":"e2l 2c4",
    "iso:country":"CA",
    "sg:city":"Saint John",
    "sg:classifiers":[
        {
            "category":"Organizations",
            "subcategory":"Professional Association",
            "type":"Services"
        }
    ],
    "sg:phone":"+1 506 634 0957",
    "sg:postcode":"E2L 2C4",
    "sg:province":"NB",
    "wof:name":"Adanac Association",
    "wof:placetype":"venue"
},
  "geometry": {"coordinates":[-66.061058,45.27256],"type":"Point"}
}