{
  "type": "Feature",
  "properties": {
    "addr:full":"336 Rue Jean-Rioux Trois-Pistoles QC G0L 4K0",
    "addr:housenumber":"336",
    "addr:postcode":"g0l 4k0",
    "addr:street":"Rue Jean-Rioux",
    "iso:country":"CA",
    "sg:address":"336 Rue Jean-Rioux",
    "sg:city":"Trois-Pistoles",
    "sg:classifiers":[
        {
            "category":"Shopping",
            "subcategory":"Jewelry",
            "type":"Retail Goods"
        }
    ],
    "sg:phone":"+1 418 851 1310",
    "sg:postcode":"G0L 4K0",
    "sg:province":"QC",
    "sg:tags":[
        "jeweler"
    ],
    "wof:name":"Bijouterie Ch Rioux Inc",
    "wof:placetype":"venue"
},
  "geometry": {"coordinates":[-69.1738204956,48.1241874695],"type":"Point"}
}