{
  "type": "Feature",
  "properties": {
    "iso:country":"CA",
    "sg:address":"1865 Rue Giroux",
    "sg:city":"Longueuil",
    "sg:classifiers":[
        {
            "category":"Building & Trades",
            "subcategory":"Construction",
            "type":"Services"
        }
    ],
    "sg:phone":"+1 450 468 6680",
    "sg:postcode":"J4N 1K7",
    "sg:province":"QC",
    "sg:tags":[
        "excavating",
        "contractor"
    ],
    "wof:name":"Alain Labrecque Inc",
    "wof:placetype":"venue"
},
  "geometry": {"coordinates":[-73.4611206055,45.5530204773],"type":"Point"}
}