{
  "type": "Feature",
  "properties": {
    "addr:full":"255 Boul DE LA Concorde E Laval QC H7G 2E3",
    "addr:housenumber":"255",
    "addr:postcode":"qc h7g 2e3",
    "addr:street":"Boul De La Concorde E",
    "iso:country":"CA",
    "sg:address":"255 Boul DE LA Concorde E",
    "sg:city":"Laval",
    "sg:classifiers":[
        {
            "category":"Wholesale",
            "subcategory":"Durable Goods & Equipment",
            "type":"Manufacturing & Wholesale Goods"
        }
    ],
    "sg:phone":"+1 450 967 3889",
    "sg:postcode":"H7G 2E3",
    "sg:province":"QC",
    "sg:tags":[
        "representative",
        "manufacturer"
    ],
    "wof:name":"Distributions Denis Fontaine",
    "wof:placetype":"venue"
},
  "geometry": {"coordinates":[-73.68190800000001,45.576462],"type":"Point"}
}