{
  "type": "Feature",
  "properties": {
    "addr:full":"171 Rue Principale Granby QC J2G 2V5",
    "addr:housenumber":"171",
    "addr:postcode":"j2g 2v5",
    "addr:street":"Rue Principale",
    "iso:country":"CA",
    "sg:address":"171 Rue Principale",
    "sg:city":"Granby",
    "sg:classifiers":[
        {
            "category":"Shopping",
            "subcategory":"Jewelry",
            "type":"Retail Goods"
        }
    ],
    "sg:phone":"+1 450 372 7242",
    "sg:postcode":"J2G 2V5",
    "sg:province":"QC",
    "sg:tags":[
        "jeweler"
    ],
    "wof:name":"Bijouterie Brouillette & Fils",
    "wof:placetype":"venue"
},
  "geometry": {"coordinates":[-72.72625732420001,45.3998947144],"type":"Point"}
}