{
  "type": "Feature",
  "properties": {
    "addr:full":"1284 Dundas St W Toronto ON M6J 1X7",
    "addr:housenumber":"1284",
    "addr:postcode":"m6j 1x7",
    "addr:street":"Dundas St W",
    "iso:country":"CA",
    "sg:address":"1284 Dundas St W",
    "sg:city":"Toronto",
    "sg:classifiers":[
        {
            "category":"Insurance",
            "subcategory":"Insurance Agent",
            "type":"Services"
        }
    ],
    "sg:phone":"+1 416 531 4674",
    "sg:postcode":"M6J 1X7",
    "sg:province":"ON",
    "wof:name":"Regional Insurance Svc Inc",
    "wof:placetype":"venue"
},
  "geometry": {"coordinates":[-79.425224,43.649578],"type":"Point"}
}