{
  "type": "Feature",
  "properties": {
    "iso:country":"CA",
    "sg:address":"65 Frank St",
    "sg:city":"Strathroy",
    "sg:classifiers":[
        {
            "category":"Insurance",
            "subcategory":"Insurance Agent",
            "type":"Services"
        }
    ],
    "sg:phone":"+1 519 245 1400",
    "sg:postcode":"N7G 2R3",
    "sg:province":"ON",
    "wof:name":"Kettlewell Insurance & Real",
    "wof:placetype":"venue"
},
  "geometry": {"coordinates":[-81.62445831300001,42.9568061829],"type":"Point"}
}