{
  "type": "Feature",
  "properties": {
    "addr:full":"107 2nd Ave NW Weyburn SK S4H 1P7",
    "addr:housenumber":"107",
    "addr:postcode":"s4h 1p7",
    "addr:street":"2Nd Ave Nw",
    "iso:country":"CA",
    "sg:address":"107 2nd Ave NW",
    "sg:city":"Weyburn",
    "sg:classifiers":[
        {
            "category":"Education",
            "subcategory":"School",
            "type":"Public Place"
        }
    ],
    "sg:phone":"+1 306 842 7494",
    "sg:postcode":"S4H 1P7",
    "sg:province":"SK",
    "wof:name":"Weyburn Comprehensive School",
    "wof:placetype":"venue"
},
  "geometry": {"coordinates":[-103.86322800000001,49.669994],"type":"Point"}
}