{
  "type": "Feature",
  "properties": {
    "iso:country":"CA",
    "sg:address":"6 Duke St E",
    "sg:city":"Kitchener",
    "sg:classifiers":[
        {
            "category":"Shopping",
            "subcategory":"Computers & Home Electronics",
            "type":"Retail Goods"
        }
    ],
    "sg:phone":"+1 519 569 7986",
    "sg:postcode":"N2H 1A3",
    "sg:province":"ON",
    "sg:tags":[
        "equipment",
        "dealer"
    ],
    "wof:name":"Computer Xs",
    "wof:placetype":"venue"
},
  "geometry": {"coordinates":[-80.487991333,43.4508552551],"type":"Point"}
}