{
  "type": "Feature",
  "properties": {
    "addr:full":"2759 Rue Sherbrooke E Montreal QC H2K 1G9",
    "addr:housenumber":"2759",
    "addr:postcode":"h2k 1g9",
    "addr:street":"Rue Sherbrooke E",
    "iso:country":"CA",
    "sg:address":"2759 Rue Sherbrooke E",
    "sg:city":"Montreal",
    "sg:classifiers":[
        {
            "category":"Personal",
            "subcategory":"Barber",
            "type":"Services"
        }
    ],
    "sg:phone":"+1 514 524 1626",
    "sg:postcode":"H2K 1G9",
    "sg:province":"QC",
    "wof:name":"Gauthier Freres",
    "wof:placetype":"venue"
},
  "geometry": {"coordinates":[-73.56005859379999,45.5386543274],"type":"Point"}
}