{
  "type": "Feature",
  "properties": {
    "iso:country":"CA",
    "sg:address":"750 Rue Saint-Vallier O",
    "sg:city":"Quebec",
    "sg:classifiers":[
        {
            "category":"Health Services",
            "subcategory":"Health Practitioner",
            "type":"Services"
        }
    ],
    "sg:phone":"+1 418 683 1492",
    "sg:postcode":"G1N 1E1",
    "sg:province":"QC",
    "sg:tags":[
        "physiotherapist"
    ],
    "wof:name":"Clinique DE Physiotherapie",
    "wof:placetype":"venue"
},
  "geometry": {"coordinates":[-71.218277,46.813805],"type":"Point"}
}