{
  "type": "Feature",
  "properties": {
    "addr:full":"309 Centre St Meadow Lake SK S9X 1L7",
    "addr:housenumber":"309",
    "addr:postcode":"s9x 1l7",
    "addr:street":"Centre St",
    "iso:country":"CA",
    "sg:address":"309 Centre St",
    "sg:city":"Meadow Lake",
    "sg:classifiers":[
        {
            "category":"Insurance",
            "subcategory":"Insurance Agent",
            "type":"Services"
        }
    ],
    "sg:phone":"+1 306 236 6222",
    "sg:postcode":"S9X 1L7",
    "sg:province":"SK",
    "wof:name":"CO-Operators General Insurance",
    "wof:placetype":"venue"
},
  "geometry": {"coordinates":[-108.432197571,54.1199455261],"type":"Point"}
}