{
  "type": "Feature",
  "properties": {
    "addr:full":"1018 Rue Ontario E Montreal QC H2L 1P9",
    "addr:housenumber":"1018",
    "addr:postcode":"h2l 1p9",
    "addr:street":"Rue Ontario E",
    "iso:country":"CA",
    "sg:address":"1018 Rue Ontario E",
    "sg:city":"Montreal",
    "sg:classifiers":[
        {
            "category":"Food & Beverages",
            "subcategory":"Groceries & Convenience Stores",
            "type":"Retail Goods"
        }
    ],
    "sg:phone":"+1 514 598 7369",
    "sg:postcode":"H2L 1P9",
    "sg:province":"QC",
    "sg:tags":[
        "grocer"
    ],
    "wof:name":"Marche Briere",
    "wof:placetype":"venue"
},
  "geometry": {"coordinates":[-73.562988,45.519745],"type":"Point"}
}