{
  "type": "Feature",
  "properties": {
    "addr:full":"6870 Rue DE Marseille Montreal QC H1N 1M7",
    "addr:housenumber":"6870",
    "addr:postcode":"h1n 1m7",
    "addr:street":"Rue De Marseille",
    "iso:country":"CA",
    "sg:address":"6870 Rue DE Marseille",
    "sg:city":"Montreal",
    "sg:classifiers":[
        {
            "category":"Food & Beverages",
            "subcategory":"Groceries & Convenience Stores",
            "type":"Retail Goods"
        }
    ],
    "sg:phone":"+1 514 254 8202",
    "sg:postcode":"H1N 1M7",
    "sg:province":"QC",
    "wof:name":"Depanneur Genois",
    "wof:placetype":"venue"
},
  "geometry": {"coordinates":[-73.53755187989999,45.5841293335],"type":"Point"}
}