{
  "type": "Feature",
  "properties": {
    "addr:full":"17 Division St N Kingsville ON N9Y 1C7",
    "addr:housenumber":"17",
    "addr:postcode":"n9y 1c7",
    "addr:street":"Division St N",
    "iso:country":"CA",
    "sg:address":"17 Division St N",
    "sg:city":"Kingsville",
    "sg:classifiers":[
        {
            "category":"Insurance",
            "subcategory":"Insurance Agent",
            "type":"Services"
        }
    ],
    "sg:phone":"+1 519 733 4121",
    "sg:postcode":"N9Y 1C7",
    "sg:province":"ON",
    "wof:name":"Will Insurance Brokers",
    "wof:placetype":"venue"
},
  "geometry": {"coordinates":[-82.73938,42.038361],"type":"Point"}
}