{
  "type": "Feature",
  "properties": {
    "iso:country":"CA",
    "sg:address":"172 Rue Dollard",
    "sg:city":"Hull",
    "sg:classifiers":[
        {
            "category":"Food & Beverages",
            "subcategory":"Groceries & Convenience Stores",
            "type":"Retail Goods"
        }
    ],
    "sg:phone":"+1 819 770 6554",
    "sg:postcode":"J8X 3M9",
    "sg:province":"QC",
    "wof:name":"Depanneur 172 Dollard",
    "wof:placetype":"venue"
},
  "geometry": {"coordinates":[-75.712852478,45.4357833862],"type":"Point"}
}