{
  "type": "Feature",
  "properties": {
    "iso:country":"CA",
    "sg:address":"276 Stinson Cres",
    "sg:city":"Hamilton",
    "sg:classifiers":[
        {
            "category":"Wholesale",
            "subcategory":"Sporting Goods",
            "type":"Manufacturing & Wholesale Goods"
        }
    ],
    "sg:phone":"+1 905 529 0766",
    "sg:postcode":"L8N 1T7",
    "sg:province":"ON",
    "sg:tags":[
        "pool",
        "swimming"
    ],
    "wof:name":"W C Marketing",
    "wof:placetype":"venue"
},
  "geometry": {"coordinates":[-79.85060882569999,43.2469406128],"type":"Point"}
}