{
  "type": "Feature",
  "properties": {
    "iso:country":"CA",
    "sg:address":"561 Av Victoria",
    "sg:city":"Saint-Lambert",
    "sg:classifiers":[
        {
            "category":"Food & Beverages",
            "subcategory":"Bakery",
            "type":"Retail Goods"
        }
    ],
    "sg:phone":"+1 450 923 3463",
    "sg:postcode":"J4P 3R2",
    "sg:province":"QC",
    "sg:tags":[
        "baker"
    ],
    "wof:name":"Couronne Des Roys Inc",
    "wof:placetype":"venue"
},
  "geometry": {"coordinates":[-73.510429,45.500847],"type":"Point"}
}