{
  "type": "Feature",
  "properties": {
    "addr:full":"40 Midlake Blvd SE Calgary AB T2X 2X7",
    "addr:housenumber":"40",
    "addr:postcode":"t2x 2x7",
    "addr:street":"Midlake Blvd Se",
    "iso:country":"CA",
    "sg:address":"40 Midlake Blvd SE",
    "sg:city":"Calgary",
    "sg:classifiers":[
        {
            "category":"Professional",
            "subcategory":"Business Services",
            "type":"Services"
        }
    ],
    "sg:phone":"+1 403 256 1515",
    "sg:postcode":"T2X 2X7",
    "sg:province":"AB",
    "sg:tags":[
        "appraiser"
    ],
    "wof:name":"Wasslen Appraisal Svc",
    "wof:placetype":"venue"
},
  "geometry": {"coordinates":[-114.06182098399999,50.9149398804],"type":"Point"}
}