{
  "type": "Feature",
  "properties": {
    "addr:full":"356 Line 3 S Bonfield ON P0H 1E0",
    "addr:housenumber":"356",
    "addr:postcode":"p0h 1e0",
    "addr:street":"Line 3 S",
    "iso:country":"CA",
    "sg:address":"356 Line 3 S",
    "sg:city":"Bonfield",
    "sg:classifiers":[
        {
            "category":"Government",
            "subcategory":"Office",
            "type":"Public Place"
        }
    ],
    "sg:phone":"+1 705 776 2659",
    "sg:postcode":"P0H 1E0",
    "sg:province":"ON",
    "sg:tags":[
        "village"
    ],
    "wof:name":"Bonfield Animal Control",
    "wof:placetype":"venue"
},
  "geometry": {"coordinates":[-79.14709499999999,46.238949],"type":"Point"}
}