{
  "type": "Feature",
  "properties": {
    "addr:full":"340 Stafford St Winnipeg MB R3M 2W4",
    "addr:housenumber":"340",
    "addr:postcode":"r3m 2w4",
    "addr:street":"Stafford St",
    "iso:country":"CA",
    "sg:address":"340 Stafford St",
    "sg:city":"Winnipeg",
    "sg:classifiers":[
        {
            "category":"Health Services",
            "subcategory":"Chiropractor",
            "type":"Services"
        }
    ],
    "sg:phone":"+1 204 453 2987",
    "sg:postcode":"R3M 2W4",
    "sg:province":"MB",
    "wof:name":"Kowall Chiropractic Ctr",
    "wof:placetype":"venue"
},
  "geometry": {"coordinates":[-97.1588592529,49.86510849],"type":"Point"}
}