{
  "type": "Feature",
  "properties": {
    "addr:full":"Toronto ON M4S 2A2",
    "addr:postcode":"m4s 2a2",
    "iso:country":"CA",
    "sg:city":"Toronto",
    "sg:classifiers":[
        {
            "category":"Personal",
            "subcategory":"Beauty Salon",
            "type":"Services"
        }
    ],
    "sg:phone":"+1 416 481 6711",
    "sg:postcode":"M4S 2A2",
    "sg:province":"ON",
    "sg:tags":[
        "aromatherapy"
    ],
    "wof:name":"Magda Massage Svc",
    "wof:placetype":"venue"
},
  "geometry": {"coordinates":[-79.3970565796,43.7014198303],"type":"Point"}
}