{
  "type": "Feature",
  "properties": {
    "iso:country":"CA",
    "sg:address":"1692 Eglinton Ave W",
    "sg:city":"York",
    "sg:classifiers":[
        {
            "category":"Personal",
            "subcategory":"Beauty Salon",
            "type":"Services"
        }
    ],
    "sg:phone":"+1 416 789 5142",
    "sg:postcode":"M6E 2H5",
    "sg:province":"ON",
    "wof:name":"Touch of Class Hair Design",
    "wof:placetype":"venue"
},
  "geometry": {"coordinates":[-79.4460449219,43.6967315674],"type":"Point"}
}