{
  "type": "Feature",
  "properties": {
    "addr:full":"Longueuil QC J4H 1C6",
    "addr:postcode":"j4h 1c6",
    "iso:country":"CA",
    "sg:city":"Longueuil",
    "sg:classifiers":[
        {
            "category":"Professional",
            "subcategory":"Lawyer & Legal Services",
            "type":"Services"
        }
    ],
    "sg:phone":"+1 450 928 3232",
    "sg:postcode":"J4H 1C6",
    "sg:province":"QC",
    "sg:tags":[
        "attorney"
    ],
    "wof:name":"Campeau, Jean-Guy",
    "wof:placetype":"venue"
},
  "geometry": {"coordinates":[-73.50769,45.541176],"type":"Point"}
}