{
  "type": "Feature",
  "properties": {
    "iso:country":"CA",
    "sg:address":"1914 Commercial Dr",
    "sg:city":"Vancouver",
    "sg:classifiers":[
        {
            "category":"Restaurant",
            "type":"Food & Drink"
        }
    ],
    "sg:phone":"+1 604 251 5552",
    "sg:postcode":"V5N 4A7",
    "sg:province":"BC",
    "sg:tags":[
        "pizza"
    ],
    "wof:name":"Golden Boys Pizza",
    "wof:placetype":"venue"
},
  "geometry": {"coordinates":[-123.06950378400001,49.2676277161],"type":"Point"}
}