{
  "type": "Feature",
  "properties": {
    "addr:full":"1735 Commercial Dr Vancouver BC V5N 4A4",
    "addr:housenumber":"1735",
    "addr:postcode":"v5n 4a4",
    "addr:street":"Commercial Dr",
    "iso:country":"CA",
    "sg:address":"1735 Commercial Dr",
    "sg:city":"Vancouver",
    "sg:classifiers":[
        {
            "category":"Personal",
            "subcategory":"Beauty Salon",
            "type":"Services"
        }
    ],
    "sg:phone":"+1 604 253 3937",
    "sg:postcode":"V5N 4A4",
    "sg:province":"BC",
    "wof:name":"Pronta Moda",
    "wof:placetype":"venue"
},
  "geometry": {"coordinates":[-123.069901,49.269257],"type":"Point"}
}