{
  "type": "Feature",
  "properties": {
    "addr:full":"227 Dumfries Ave Kitchener ON N2H 2E6",
    "addr:housenumber":"227",
    "addr:postcode":"n2h 2e6",
    "addr:street":"Dumfries Ave",
    "iso:country":"CA",
    "sg:address":"227 Dumfries Ave",
    "sg:city":"Kitchener",
    "sg:classifiers":[
        {
            "category":"Health Services",
            "subcategory":"Chiropractor",
            "type":"Services"
        }
    ],
    "sg:phone":"+1 519 742 4471",
    "sg:postcode":"N2H 2E6",
    "sg:province":"ON",
    "wof:name":"Smith Chiropractic Clinic",
    "wof:placetype":"venue"
},
  "geometry": {"coordinates":[-80.47184753419999,43.4560890198],"type":"Point"}
}