{
  "type": "Feature",
  "properties": {
    "addr:full":"180 Niagara St St Catharines ON L2R 4L9",
    "addr:housenumber":"180",
    "addr:postcode":"l2r 4l9",
    "addr:street":"Niagara St",
    "iso:country":"CA",
    "sg:address":"180 Niagara St",
    "sg:city":"St Catharines",
    "sg:classifiers":[
        {
            "category":"Wholesale",
            "subcategory":"Electrical",
            "type":"Manufacturing & Wholesale Goods"
        }
    ],
    "sg:phone":"+1 905 685 0249",
    "sg:postcode":"L2R 4L9",
    "sg:province":"ON",
    "sg:tags":[
        "control",
        "security",
        "system"
    ],
    "wof:name":"Systems Service",
    "wof:placetype":"venue"
},
  "geometry": {"coordinates":[-79.23252100000001,43.17215],"type":"Point"}
}