{
  "type": "Feature",
  "properties": {
    "iso:country":"CA",
    "sg:address":"382 James St",
    "sg:city":"Delhi",
    "sg:classifiers":[
        {
            "category":"Restaurant",
            "type":"Food & Drink"
        }
    ],
    "sg:phone":"+1 519 582 2530",
    "sg:postcode":"N4B 2B7",
    "sg:province":"ON",
    "wof:name":"Paul's Cafe",
    "wof:placetype":"venue"
},
  "geometry": {"coordinates":[-80.49267578120001,42.8510246277],"type":"Point"}
}