{
  "type": "Feature",
  "properties": {
    "iso:country":"CA",
    "sg:address":"33 Boul Begin",
    "sg:city":"Sainte-Claire",
    "sg:classifiers":[
        {
            "category":"Retail",
            "subcategory":"Auto Repair",
            "type":"Services"
        }
    ],
    "sg:phone":"+1 418 883 2012",
    "sg:postcode":"G0R 2V0",
    "sg:province":"QC",
    "sg:tags":[
        "repairing",
        "automobile"
    ],
    "wof:name":"Mgl Mecanique Inc",
    "wof:placetype":"venue"
},
  "geometry": {"coordinates":[-70.879814,46.598373],"type":"Point"}
}