{
  "type": "Feature",
  "properties": {
    "addr:full":"100 Malden Rd Essex ON N8M 2X5",
    "addr:housenumber":"100",
    "addr:postcode":"n8m 2x5",
    "addr:street":"Malden Rd",
    "iso:country":"CA",
    "sg:address":"100 Malden Rd",
    "sg:city":"Essex",
    "sg:classifiers":[
        {
            "category":"Home & Garden",
            "subcategory":"Furniture",
            "type":"Retail Goods"
        }
    ],
    "sg:phone":"+1 519 776 8676",
    "sg:postcode":"N8M 2X5",
    "sg:province":"ON",
    "wof:name":"Jones Fine Furniture Ltd",
    "wof:placetype":"venue"
},
  "geometry": {"coordinates":[-82.97188568120001,42.1108093262],"type":"Point"}
}