{
  "type": "Feature",
  "properties": {
    "addr:full":"2133 Rue Des Ormes LA Baie QC G7B 3W3",
    "addr:housenumber":"2133",
    "addr:postcode":"g7b 3w3",
    "addr:street":"Rue Des Ormes",
    "iso:country":"CA",
    "sg:address":"2133 Rue Des Ormes",
    "sg:city":"LA Baie",
    "sg:classifiers":[
        {
            "category":"Food & Beverages",
            "subcategory":"Groceries & Convenience Stores",
            "type":"Retail Goods"
        }
    ],
    "sg:phone":"+1 418 544 7513",
    "sg:postcode":"G7B 3W3",
    "sg:province":"QC",
    "sg:tags":[
        "grocer"
    ],
    "wof:name":"Accommodation Des Ormes",
    "wof:placetype":"venue"
},
  "geometry": {"coordinates":[-70.8992843628,48.3434753418],"type":"Point"}
}