{
  "type": "Feature",
  "properties": {
    "iso:country":"CA",
    "sg:city":"Quebec",
    "sg:classifiers":[
        {
            "category":"Social Services",
            "subcategory":"Child Care",
            "type":"Services"
        }
    ],
    "sg:phone":"+1 418 871 2711",
    "sg:postcode":"G1P 1H6",
    "sg:province":"QC",
    "wof:name":"Garderie L'Elephant Rose Enr",
    "wof:placetype":"venue"
},
  "geometry": {"coordinates":[-71.331078,46.82346],"type":"Point"}
}