{
  "type": "Feature",
  "properties": {
    "addr:full":"5945 Airport Rd #210 Mississauga ON L4V 1R9",
    "addr:housenumber":"5945",
    "addr:postcode":"l4v 1r9",
    "addr:street":"Airport Rd # 210",
    "iso:country":"CA",
    "sg:address":"5945 Airport Rd #210",
    "sg:city":"Mississauga",
    "sg:classifiers":[
        {
            "category":"Organizations",
            "subcategory":"Labor Organization",
            "type":"Services"
        }
    ],
    "sg:phone":"+1 905 678 6652",
    "sg:postcode":"L4V 1R9",
    "sg:province":"ON",
    "wof:name":"Teamsters Canada",
    "wof:placetype":"venue"
},
  "geometry": {"coordinates":[-79.60839799999999,43.686085],"type":"Point"}
}