{
  "type": "Feature",
  "properties": {
    "addr:full":"151 Rue Emilie-Gamelin LA Prairie QC J5R 1E4",
    "addr:housenumber":"151",
    "addr:postcode":"j5r 1e4",
    "addr:street":"Rue Emilie-Gamelin",
    "iso:country":"CA",
    "sg:address":"151 Rue Emilie-Gamelin",
    "sg:city":"LA Prairie",
    "sg:classifiers":[
        {
            "category":"Health Services",
            "subcategory":"Nursing And Care Facility",
            "type":"Services"
        }
    ],
    "sg:phone":"+1 450 659 9362",
    "sg:postcode":"J5R 1E4",
    "sg:province":"QC",
    "sg:tags":[
        "home",
        "retirement",
        "community"
    ],
    "wof:name":"Residence LA Belle Epoque",
    "wof:placetype":"venue"
},
  "geometry": {"coordinates":[-73.496109,45.42131],"type":"Point"}
}