{
  "type": "Feature",
  "properties": {
    "iso:country":"CA",
    "sg:address":"858 Brock St N",
    "sg:city":"Whitby",
    "sg:classifiers":[
        {
            "category":"Health Services",
            "subcategory":"Doctor",
            "type":"Services"
        }
    ],
    "sg:phone":"+1 905 668 3884",
    "sg:postcode":"L1N 4J5",
    "sg:province":"ON",
    "sg:tags":[
        "dentist"
    ],
    "wof:name":"Bolshin, Daniel DDS",
    "wof:placetype":"venue"
},
  "geometry": {"coordinates":[-78.94718933110001,43.8913040161],"type":"Point"}
}