{
  "type": "Feature",
  "properties": {
    "iso:country":"CA",
    "sg:address":"3584 Rue DE Chambly",
    "sg:city":"Montreal",
    "sg:classifiers":[
        {
            "category":"Professional",
            "subcategory":"Management & Consulting",
            "type":"Services"
        }
    ],
    "sg:phone":"+1 514 527 2611",
    "sg:postcode":"H1W 3J9",
    "sg:province":"QC",
    "sg:tags":[
        "consultant",
        "educational"
    ],
    "wof:name":"Pacijou",
    "wof:placetype":"venue"
},
  "geometry": {"coordinates":[-73.55754852290001,45.5494651794],"type":"Point"}
}