{
  "type": "Feature",
  "properties": {
    "addr:full":"11718 125 St NW Edmonton AB T5M 0N6",
    "addr:housenumber":"11718",
    "addr:postcode":"t5m 0n6",
    "addr:street":"125 St Nw",
    "iso:country":"CA",
    "sg:address":"11718 125 St NW",
    "sg:city":"Edmonton",
    "sg:classifiers":[
        {
            "category":"Building & Trades",
            "subcategory":"Construction",
            "type":"Services"
        }
    ],
    "sg:phone":"+1 780 455 1186",
    "sg:postcode":"T5M 0N6",
    "sg:province":"AB",
    "sg:tags":[
        "maker",
        "cabinet"
    ],
    "wof:name":"Mike's Woodworking",
    "wof:placetype":"venue"
},
  "geometry": {"coordinates":[-113.537834,53.568905],"type":"Point"}
}