{
  "type": "Feature",
  "properties": {
    "addr:full":"929 Old Derry Rd Mississauga ON L5W 1A1",
    "addr:housenumber":"929",
    "addr:postcode":"l5w 1a1",
    "addr:street":"Old Derry Rd",
    "iso:country":"CA",
    "sg:address":"929 Old Derry Rd",
    "sg:city":"Mississauga",
    "sg:classifiers":[
        {
            "category":"Education",
            "subcategory":"School",
            "type":"Public Place"
        }
    ],
    "sg:phone":"+1 905 565 8707",
    "sg:postcode":"L5W 1A1",
    "sg:province":"ON",
    "wof:name":"Rotherglen School",
    "wof:placetype":"venue"
},
  "geometry": {"coordinates":[-79.727180481,43.6278648376],"type":"Point"}
}