{
  "type": "Feature",
  "properties": {
    "addr:full":"28 Erie St Stratford ON N5A 2M4",
    "addr:housenumber":"28",
    "addr:postcode":"n5a 2m4",
    "addr:street":"Erie St",
    "iso:country":"CA",
    "sg:address":"28 Erie St",
    "sg:city":"Stratford",
    "sg:classifiers":[
        {
            "category":"Restaurant",
            "type":"Food & Drink"
        }
    ],
    "sg:phone":"+1 519 272 0133",
    "sg:postcode":"N5A 2M4",
    "sg:province":"ON",
    "sg:tags":[
        "parlor",
        "ice",
        "cream"
    ],
    "wof:name":"Scooper's",
    "wof:placetype":"venue"
},
  "geometry": {"coordinates":[-80.9834442139,43.3709106445],"type":"Point"}
}