{
  "type": "Feature",
  "properties": {
    "addr:full":"80 Reed Ave St Andrews NB E5B 1A1",
    "addr:housenumber":"80",
    "addr:postcode":"e5b 1a1",
    "addr:street":"Reed Ave",
    "iso:country":"CA",
    "sg:address":"80 Reed Ave",
    "sg:city":"St Andrews",
    "sg:classifiers":[
        {
            "category":"Government",
            "subcategory":"Fire Station",
            "type":"Public Place"
        }
    ],
    "sg:phone":"+1 ",
    "sg:postcode":"E5B 1A1",
    "sg:province":"NB",
    "sg:tags":[
        "department"
    ],
    "wof:name":"St Andrews Fire Dept",
    "wof:placetype":"venue"
},
  "geometry": {"coordinates":[-67.06102,45.082806],"type":"Point"}
}