{
  "type": "Feature",
  "properties": {
    "addr:full":"515 Cape St Mary Rd Yarmouth NS B5A 4A5",
    "addr:housenumber":"515",
    "addr:postcode":"b5a 4a5",
    "addr:street":"Cape St Mary Rd",
    "iso:country":"CA",
    "sg:address":"515 Cape St Mary Rd",
    "sg:city":"Yarmouth",
    "sg:classifiers":[
        {
            "category":"Manufacturing",
            "subcategory":"Watercraft",
            "type":"Manufacturing & Wholesale Goods"
        }
    ],
    "sg:phone":"+1 902 645 2451",
    "sg:postcode":"B5A 4A5",
    "sg:province":"NS",
    "sg:tags":[
        "boat"
    ],
    "wof:name":"Cape St Marys Boat Builders",
    "wof:placetype":"venue"
},
  "geometry": {"coordinates":[-66.11885100000001,43.841282],"type":"Point"}
}