{
  "type": "Feature",
  "properties": {
    "addr:full":"Bay Bulls NL A0A 1C0",
    "addr:postcode":"a0a 1c0",
    "addr:street":"Bay",
    "iso:country":"CA",
    "sg:city":"Bay Bulls",
    "sg:classifiers":[
        {
            "category":"Banks & Credit Unions",
            "subcategory":"Bank",
            "type":"Services"
        }
    ],
    "sg:phone":"+1 709 334 2170",
    "sg:postcode":"A0A 1C0",
    "sg:province":"NL",
    "wof:name":"Community Credit Union",
    "wof:placetype":"venue"
},
  "geometry": {"coordinates":[-52.8186035156,47.3170166016],"type":"Point"}
}