{
  "type": "Feature",
  "properties": {
    "iso:country":"CA",
    "sg:address":"1420 Columbia St",
    "sg:city":"North Vancouver",
    "sg:classifiers":[
        {
            "category":"Home & Garden",
            "subcategory":"Carpets & Floor Coverings",
            "type":"Retail Goods"
        }
    ],
    "sg:phone":"+1 604 984 3666",
    "sg:postcode":"V7J 1A2",
    "sg:province":"BC",
    "sg:tags":[
        "dealer",
        "rug"
    ],
    "wof:name":"Concept One Floors Ltd",
    "wof:placetype":"venue"
},
  "geometry": {"coordinates":[-123.033706665,49.3026237488],"type":"Point"}
}