{
  "type": "Feature",
  "properties": {
    "iso:country":"CA",
    "sg:address":"36 Main St N",
    "sg:city":"Brampton",
    "sg:classifiers":[
        {
            "category":"Shopping",
            "subcategory":"Clothing, Apparel, & Fashions",
            "type":"Retail Goods"
        }
    ],
    "sg:phone":"+1 905 451 7673",
    "sg:postcode":"L6V 1N6",
    "sg:province":"ON",
    "sg:tags":[
        "leather",
        "fur",
        "business"
    ],
    "wof:name":"International Furs Ltd",
    "wof:placetype":"venue"
},
  "geometry": {"coordinates":[-79.76058197019999,43.6865501404],"type":"Point"}
}