{
  "type": "Feature",
  "properties": {
    "addr:full":"432 Rue Jarry E Montreal QC H2P 1V3",
    "addr:housenumber":"432",
    "addr:postcode":"h2p 1v3",
    "addr:street":"Rue Jarry E",
    "iso:country":"CA",
    "sg:address":"432 Rue Jarry E",
    "sg:city":"Montreal",
    "sg:classifiers":[
        {
            "category":"Shopping",
            "subcategory":"Clothing, Apparel, & Fashions",
            "type":"Retail Goods"
        }
    ],
    "sg:phone":"+1 514 382 9827",
    "sg:postcode":"H2P 1V3",
    "sg:province":"QC",
    "sg:tags":[
        "handbag"
    ],
    "wof:name":"J J Cuir",
    "wof:placetype":"venue"
},
  "geometry": {"coordinates":[-73.6288757324,45.5427742004],"type":"Point"}
}