{
  "type": "Feature",
  "properties": {
    "addr:full":"1551 Duranleau St Vancouver BC V6H 3S3",
    "addr:housenumber":"1551",
    "addr:postcode":"v6h 3s3",
    "addr:street":"Duranleau St",
    "iso:country":"CA",
    "sg:address":"1551 Duranleau St",
    "sg:city":"Vancouver",
    "sg:classifiers":[
        {
            "category":"Professional",
            "type":"Services"
        }
    ],
    "sg:phone":"+1 604 669 1551",
    "sg:postcode":"V6H 3S3",
    "sg:province":"BC",
    "sg:tags":[
        "arts",
        "artist"
    ],
    "wof:name":"Island Studio",
    "wof:placetype":"venue"
},
  "geometry": {"coordinates":[-123.13588,49.271278],"type":"Point"}
}