{
  "type": "Feature",
  "properties": {
    "addr:full":"600 Rte Cameron Sainte-Marie QC G6E 1B2",
    "addr:housenumber":"600",
    "addr:postcode":"g6e 1b2",
    "addr:street":"Rte Cameron",
    "iso:country":"CA",
    "sg:address":"600 Rte Cameron",
    "sg:city":"Sainte-Marie",
    "sg:classifiers":[
        {
            "category":"Shopping",
            "type":"Retail Goods"
        }
    ],
    "sg:phone":"+1 418 387 4155",
    "sg:postcode":"G6E 1B2",
    "sg:province":"QC",
    "sg:tags":[
        "whirlpool",
        "equipment",
        "bath",
        "supply"
    ],
    "wof:name":"Maax Inc",
    "wof:placetype":"venue"
},
  "geometry": {"coordinates":[-71.041397,46.466404],"type":"Point"}
}