{
  "type": "Feature",
  "properties": {
    "addr:full":"105 1st Ave Paradise Hill SK S0M 2G0",
    "addr:housenumber":"105",
    "addr:postcode":"s0m 2g0",
    "addr:street":"1St Ave Paradise Hill",
    "iso:country":"CA",
    "sg:address":"105 1st Ave",
    "sg:city":"Paradise Hill",
    "sg:classifiers":[
        {
            "category":"Health Services",
            "subcategory":"Doctor",
            "type":"Services"
        }
    ],
    "sg:phone":"+1 306 344 2255",
    "sg:postcode":"S0M 2G0",
    "sg:province":"SK",
    "sg:tags":[
        "clinic",
        "hospital"
    ],
    "wof:name":"Paradise Hill Hospital",
    "wof:placetype":"venue"
},
  "geometry": {"coordinates":[-109.45829773,53.5379142761],"type":"Point"}
}