{
  "type": "Feature",
  "properties": {
    "addr:full":"405 Montee Lussier Saint-Edouard-DE-Napierville QC J0L 1Y0",
    "addr:housenumber":"405",
    "addr:postcode":"j0l 1y0",
    "addr:street":"Montee Lussier Saint-Edouard-De-Napierville",
    "iso:country":"CA",
    "sg:address":"405 Montee Lussier",
    "sg:city":"Saint-Edouard-DE-Napierville",
    "sg:classifiers":[
        {
            "category":"Food & Beverages",
            "subcategory":"Groceries & Convenience Stores",
            "type":"Retail Goods"
        }
    ],
    "sg:phone":"+1 450 454 2943",
    "sg:postcode":"J0L 1Y0",
    "sg:province":"QC",
    "sg:tags":[
        "grocer"
    ],
    "wof:name":"Marche R Charette Inc",
    "wof:placetype":"venue"
},
  "geometry": {"coordinates":[-73.5115661621,45.2397155762],"type":"Point"}
}