{
  "type": "Feature",
  "properties": {
    "addr:full":"12722 137 Ave NW Edmonton AB T5L 4Y8",
    "addr:housenumber":"12722",
    "addr:postcode":"t5l 4y8",
    "addr:street":"137 Ave Nw",
    "iso:country":"CA",
    "sg:address":"12722 137 Ave NW",
    "sg:city":"Edmonton",
    "sg:classifiers":[
        {
            "category":"Restaurant",
            "type":"Food & Drink"
        }
    ],
    "sg:phone":"+1 780 456 7676",
    "sg:postcode":"T5L 4Y8",
    "sg:province":"AB",
    "wof:name":"House of Quon Restaurant",
    "wof:placetype":"venue"
},
  "geometry": {"coordinates":[-113.543137,53.599724],"type":"Point"}
}