{
  "type": "Feature",
  "properties": {
    "addr:full":"4000 Rue Hickmore Saint-Laurent QC H4T 1K2",
    "addr:housenumber":"4000",
    "addr:postcode":"h4t 1k2",
    "addr:street":"Rue Hickmore",
    "iso:country":"CA",
    "sg:address":"4000 Rue Hickmore",
    "sg:city":"Saint-Laurent",
    "sg:classifiers":[
        {
            "category":"Home & Garden",
            "subcategory":"Building Materials",
            "type":"Retail Goods"
        }
    ],
    "sg:phone":"+1 514 344 1788",
    "sg:postcode":"H4T 1K2",
    "sg:province":"QC",
    "sg:tags":[
        "mixed",
        "concrete"
    ],
    "wof:name":"Lafarge Canada Inc",
    "wof:placetype":"venue"
},
  "geometry": {"coordinates":[-73.693459,45.476784],"type":"Point"}
}