{
  "type": "Feature",
  "properties": {
    "addr:full":"961 Boul Hamel Saint-Felicien QC G8K 2X4",
    "addr:housenumber":"961",
    "addr:postcode":"g8k 2x4",
    "addr:street":"Boul Hamel Saint-Felicien",
    "iso:country":"CA",
    "sg:address":"961 Boul Hamel",
    "sg:city":"Saint-Felicien",
    "sg:classifiers":[
        {
            "category":"Professional",
            "subcategory":"Management & Consulting",
            "type":"Services"
        }
    ],
    "sg:phone":"+1 418 679 1176",
    "sg:postcode":"G8K 2X4",
    "sg:province":"QC",
    "sg:tags":[
        "communication",
        "consultant",
        "radio",
        "system",
        "telecommunication"
    ],
    "wof:name":"Communications Telesignal",
    "wof:placetype":"venue"
},
  "geometry": {"coordinates":[-72.446472168,48.6411247253],"type":"Point"}
}