{
  "type": "Feature",
  "properties": {
    "addr:full":"Camrose AB T4V 3G8",
    "addr:postcode":"t4v 3g8",
    "iso:country":"CA",
    "sg:city":"Camrose",
    "sg:classifiers":[
        {
            "category":"Real Estate",
            "subcategory":"Real Estate Operator",
            "type":"Services"
        }
    ],
    "sg:phone":"+1 780 672 7719",
    "sg:postcode":"T4V 3G8",
    "sg:province":"AB",
    "sg:tags":[
        "mall",
        "shopping",
        "center"
    ],
    "wof:name":"Dugan Mall Shopping Ctr",
    "wof:placetype":"venue"
},
  "geometry": {"coordinates":[-112.85571299999999,53.017796],"type":"Point"}
}