{
  "type": "Feature",
  "properties": {
    "addr:full":"108 Main St W Otterville ON N0J 1R0",
    "addr:housenumber":"108",
    "addr:postcode":"n0j 1r0",
    "addr:street":"Main St W Otterville",
    "iso:country":"CA",
    "sg:address":"108 Main St W",
    "sg:city":"Otterville",
    "sg:classifiers":[
        {
            "category":"Retail",
            "subcategory":"Auto Repair",
            "type":"Services"
        }
    ],
    "sg:phone":"+1 519 879 6574",
    "sg:postcode":"N0J 1R0",
    "sg:province":"ON",
    "sg:tags":[
        "truck"
    ],
    "wof:name":"M & L Svc & Repair",
    "wof:placetype":"venue"
},
  "geometry": {"coordinates":[-80.60343933110001,42.9264907837],"type":"Point"}
}