{
  "type": "Feature",
  "properties": {
    "addr:full":"423 King St E Hamilton ON L8N 1C5",
    "addr:housenumber":"423",
    "addr:postcode":"l8n 1c5",
    "addr:street":"King St E",
    "iso:country":"CA",
    "sg:address":"423 King St E",
    "sg:city":"Hamilton",
    "sg:classifiers":[
        {
            "category":"Organizations",
            "subcategory":"Professional Association",
            "type":"Services"
        }
    ],
    "sg:phone":"+1 905 385 0925",
    "sg:postcode":"L8N 1C5",
    "sg:province":"ON",
    "wof:name":"Afro Canadian Caribbean Assn",
    "wof:placetype":"venue"
},
  "geometry": {"coordinates":[-79.85650634770001,43.2531967163],"type":"Point"}
}