{
  "type": "Feature",
  "properties": {
    "addr:full":"Scarborough ON M1L 2L1",
    "addr:postcode":"m1l 2l1",
    "iso:country":"CA",
    "sg:city":"Scarborough",
    "sg:classifiers":[
        {
            "category":"Shopping",
            "subcategory":"Department Store",
            "type":"Retail Goods"
        }
    ],
    "sg:phone":"+1 416 615 0606",
    "sg:postcode":"M1L 2L1",
    "sg:province":"ON",
    "sg:tags":[
        "shop"
    ],
    "wof:name":"Everything For A Dollar Store",
    "wof:placetype":"venue"
},
  "geometry": {"coordinates":[-79.300522,43.72522],"type":"Point"}
}