{
  "type": "Feature",
  "properties": {
    "addr:full":"5799 Luke Rd Mississauga ON L4W 1T2",
    "addr:housenumber":"5799",
    "addr:postcode":"l4w 1t2",
    "addr:street":"Luke Rd",
    "iso:country":"CA",
    "sg:address":"5799 Luke Rd",
    "sg:city":"Mississauga",
    "sg:classifiers":[
        {
            "category":"Home & Garden",
            "subcategory":"Garden Supply",
            "type":"Retail Goods"
        }
    ],
    "sg:phone":"+1 905 670 2129",
    "sg:postcode":"L4W 1T2",
    "sg:province":"ON",
    "sg:tags":[
        "farm",
        "equipment",
        "lawn"
    ],
    "wof:name":"Luke's Mower & Machine Ltd",
    "wof:placetype":"venue"
},
  "geometry": {"coordinates":[-79.6348724365,43.6619949341],"type":"Point"}
}