{
  "type": "Feature",
  "properties": {
    "iso:country":"CA",
    "sg:address":"1085 F R Nelson Rd",
    "sg:city":"Coldwater",
    "sg:classifiers":[
        {
            "category":"Home & Garden",
            "subcategory":"Furniture",
            "type":"Retail Goods"
        }
    ],
    "sg:phone":"+1 705 686 7491",
    "sg:postcode":"L0K 1E0",
    "sg:province":"ON",
    "wof:name":"Leisure Lawn Products",
    "wof:placetype":"venue"
},
  "geometry": {"coordinates":[-79.644363,44.710224],"type":"Point"}
}