{
  "type": "Feature",
  "properties": {
    "iso:country":"CA",
    "sg:address":"315 Ridge Rd N",
    "sg:city":"Ridgeway",
    "sg:classifiers":[
        {
            "category":"Shopping",
            "subcategory":"Pharmacy",
            "type":"Retail Goods"
        }
    ],
    "sg:phone":"+1 905 894 2520",
    "sg:postcode":"L0S 1N0",
    "sg:province":"ON",
    "wof:name":"Brodie's Drug Store",
    "wof:placetype":"venue"
},
  "geometry": {"coordinates":[-79.0521240234,42.8832702637],"type":"Point"}
}