{
  "type": "Feature",
  "properties": {
    "iso:country":"CA",
    "sg:city":"Cap-DE-LA-Madeleine",
    "sg:classifiers":[
        {
            "category":"Health Services",
            "subcategory":"Doctor",
            "type":"Services"
        }
    ],
    "sg:phone":"+1 819 374 7264",
    "sg:postcode":"G8T 7B2",
    "sg:province":"QC",
    "sg:tags":[
        "physician",
        "surgeon",
        "holistic",
        "practitioner"
    ],
    "wof:name":"Clinique Jean Le Sieur",
    "wof:placetype":"venue"
},
  "geometry": {"coordinates":[-72.553947,46.390205],"type":"Point"}
}