{
  "type": "Feature",
  "properties": {
    "addr:full":"Main St N Montague PE C0A 1R0",
    "addr:postcode":"c0a 1r0",
    "addr:street":"Main St N",
    "iso:country":"CA",
    "sg:address":"Main St N",
    "sg:city":"Montague",
    "sg:classifiers":[
        {
            "category":"Autos & Motor Vehicles",
            "subcategory":"Auto Supplies",
            "type":"Retail Goods"
        }
    ],
    "sg:phone":"+1 902 838 3299",
    "sg:postcode":"C0A 1R0",
    "sg:province":"PE",
    "sg:tags":[
        "automobile",
        "parts"
    ],
    "wof:name":"Kmt Automart Ltd",
    "wof:placetype":"venue"
},
  "geometry": {"coordinates":[-62.6424293518,46.1629333496],"type":"Point"}
}