{
  "type": "Feature",
  "properties": {
    "addr:full":"2500 Chesterfield Ave North Vancouver BC V7N 3M2",
    "addr:housenumber":"2500",
    "addr:postcode":"v7n 3m2",
    "addr:street":"Chesterfield Ave",
    "iso:country":"CA",
    "sg:address":"2500 Chesterfield Ave",
    "sg:city":"North Vancouver",
    "sg:classifiers":[
        {
            "category":"Building & Trades",
            "subcategory":"Construction",
            "type":"Services"
        }
    ],
    "sg:phone":"+1 604 985 8737",
    "sg:postcode":"V7N 3M2",
    "sg:province":"BC",
    "sg:tags":[
        "insulation",
        "heat",
        "contractor"
    ],
    "wof:name":"Canadian Insulation CO",
    "wof:placetype":"venue"
},
  "geometry": {"coordinates":[-123.075073242,49.3324737549],"type":"Point"}
}