{
  "type": "Feature",
  "properties": {
    "addr:full":"3265 264 St Aldergrove BC V4W 3E9",
    "addr:housenumber":"3265",
    "addr:postcode":"v4w 3e9",
    "addr:street":"264 St",
    "iso:country":"CA",
    "sg:address":"3265 264 St",
    "sg:city":"Aldergrove",
    "sg:classifiers":[
        {
            "category":"Autos & Motor Vehicles",
            "subcategory":"Auto Supplies",
            "type":"Retail Goods"
        }
    ],
    "sg:phone":"+1 604 607 0102",
    "sg:postcode":"V4W 3E9",
    "sg:province":"BC",
    "sg:tags":[
        "tire"
    ],
    "wof:name":"Midway Tire Ltd",
    "wof:placetype":"venue"
},
  "geometry": {"coordinates":[-122.49292800000001,49.061634],"type":"Point"}
}