{
  "type": "Feature",
  "properties": {
    "addr:full":"Sainte-Madeleine QC J0H 1S0",
    "addr:postcode":"j0h 1s0",
    "iso:country":"CA",
    "sg:city":"Sainte-Madeleine",
    "sg:classifiers":[
        {
            "category":"Personal",
            "subcategory":"Beauty Salon",
            "type":"Services"
        }
    ],
    "sg:phone":"+1 450 774 7383",
    "sg:postcode":"J0H 1S0",
    "sg:province":"QC",
    "wof:name":"Coiffure 4 Saisons",
    "wof:placetype":"venue"
},
  "geometry": {"coordinates":[-73.001617,45.598808],"type":"Point"}
}