{
  "type": "Feature",
  "properties": {
    "addr:full":"Georgetown ON L7G 4B1",
    "addr:postcode":"l7g 4b1",
    "iso:country":"CA",
    "sg:city":"Georgetown",
    "sg:classifiers":[
        {
            "category":"Government",
            "subcategory":"Office",
            "type":"Public Place"
        }
    ],
    "sg:phone":"+1 905 877 6915",
    "sg:postcode":"L7G 4B1",
    "sg:province":"ON",
    "wof:name":"Ontario Human Resources Devl",
    "wof:placetype":"venue"
},
  "geometry": {"coordinates":[-79.90018499999999,43.649979],"type":"Point"}
}