{
  "type": "Feature",
  "properties": {
    "addr:full":"475 Rue Racine E Chicoutimi QC G7H 1T5",
    "addr:housenumber":"475",
    "addr:postcode":"g7h 1t5",
    "addr:street":"Rue Racine E",
    "iso:country":"CA",
    "sg:address":"475 Rue Racine E",
    "sg:city":"Chicoutimi",
    "sg:classifiers":[
        {
            "category":"Health Services",
            "subcategory":"Doctor",
            "type":"Services"
        }
    ],
    "sg:phone":"+1 418 549 1637",
    "sg:postcode":"G7H 1T5",
    "sg:province":"QC",
    "sg:tags":[
        "dentist"
    ],
    "wof:name":"Tremblay, Guy DDS",
    "wof:placetype":"venue"
},
  "geometry": {"coordinates":[-71.05379499999999,48.428764],"type":"Point"}
}