{
  "type": "Feature",
  "properties": {
    "addr:full":"Fort Nelson BC V0C 1R0",
    "addr:postcode":"bc v0c 1r0",
    "iso:country":"CA",
    "sg:city":"Fort Nelson",
    "sg:classifiers":[
        {
            "category":"Retail",
            "subcategory":"Auto Repair",
            "type":"Services"
        }
    ],
    "sg:phone":"+1 250 774 3054",
    "sg:postcode":"V0C 1R0",
    "sg:province":"BC",
    "sg:tags":[
        "wrecker"
    ],
    "wof:name":"Archie's Auto Wrecking",
    "wof:placetype":"venue"
},
  "geometry": {"coordinates":[-122.711936951,58.8002357483],"type":"Point"}
}