{
  "type": "Feature",
  "properties": {
    "iso:country":"CA",
    "sg:city":"Winnipeg",
    "sg:classifiers":[
        {
            "category":"Health Services",
            "subcategory":"Chiropractor",
            "type":"Services"
        }
    ],
    "sg:phone":"+1 204 831 1122",
    "sg:postcode":"R3J 0P4",
    "sg:province":"MB",
    "wof:name":"Rutherford, Peter DC",
    "wof:placetype":"venue"
},
  "geometry": {"coordinates":[-97.2632141113,49.8756752014],"type":"Point"}
}