{
  "type": "Feature",
  "properties": {
    "addr:full":"189 Davis St Port Colborne ON L3K 5X8",
    "addr:housenumber":"189",
    "addr:postcode":"l3k 5x8",
    "addr:street":"Davis St",
    "iso:country":"CA",
    "sg:address":"189 Davis St",
    "sg:city":"Port Colborne",
    "sg:classifiers":[
        {
            "category":"Social Services",
            "type":"Services"
        }
    ],
    "sg:phone":"+1 905 834 5325",
    "sg:postcode":"L3K 5X8",
    "sg:province":"ON",
    "sg:tags":[
        "mission"
    ],
    "wof:name":"Christianview Fellowship Ctr",
    "wof:placetype":"venue"
},
  "geometry": {"coordinates":[-79.24221799999999,42.883835],"type":"Point"}
}