{
  "type": "Feature",
  "properties": {
    "iso:country":"CA",
    "sg:address":"10136 107 St",
    "sg:city":"Westlock",
    "sg:classifiers":[
        {
            "category":"Home & Garden",
            "subcategory":"Carpets & Floor Coverings",
            "type":"Retail Goods"
        }
    ],
    "sg:phone":"+1 780 349 3319",
    "sg:postcode":"T7P 1X3",
    "sg:province":"AB",
    "sg:tags":[
        "material",
        "rug"
    ],
    "wof:name":"Westlock Decorating Ctr Ltd",
    "wof:placetype":"venue"
},
  "geometry": {"coordinates":[-113.858841,54.1572],"type":"Point"}
}