{
  "type": "Feature",
  "properties": {
    "addr:full":"17 Cambridge Cres Saskatoon SK S7H 3P9",
    "addr:housenumber":"17",
    "addr:postcode":"s7h 3p9",
    "addr:street":"Cambridge Cres",
    "iso:country":"CA",
    "sg:address":"17 Cambridge Cres",
    "sg:city":"Saskatoon",
    "sg:classifiers":[
        {
            "category":"Health Services",
            "subcategory":"Health Practitioner",
            "type":"Services"
        }
    ],
    "sg:phone":"+1 306 244 3040",
    "sg:postcode":"S7H 3P9",
    "sg:province":"SK",
    "sg:tags":[
        "nutritionist",
        "dietitian"
    ],
    "wof:name":"Mac Kenzie's Nutrition Conslng",
    "wof:placetype":"venue"
},
  "geometry": {"coordinates":[-106.600945,52.124619],"type":"Point"}
}