{
  "type": "Feature",
  "properties": {
    "addr:full":"3 Rue Gaston-Miron Blainville QC J7C 4P1",
    "addr:housenumber":"3",
    "addr:postcode":"j7c 4p1",
    "addr:street":"Rue Gaston-Miron",
    "iso:country":"CA",
    "sg:address":"3 Rue Gaston-Miron",
    "sg:city":"Blainville",
    "sg:classifiers":[
        {
            "category":"Manufacturing",
            "subcategory":"Furniture",
            "type":"Manufacturing & Wholesale Goods"
        }
    ],
    "sg:phone":"+1 450 437 0142",
    "sg:postcode":"J7C 4P1",
    "sg:province":"QC",
    "wof:name":"Mobilier Cm",
    "wof:placetype":"venue"
},
  "geometry": {"coordinates":[-73.890625,45.674335],"type":"Point"}
}