{
  "type": "Feature",
  "properties": {
    "addr:full":"25 Cote Du Bic Sainte-Francoise QC G0L 3B0",
    "addr:housenumber":"25",
    "addr:postcode":"g0l 3b0",
    "addr:street":"Cote Du Bic Sainte-Francoise",
    "iso:country":"CA",
    "sg:address":"25 Cote Du Bic",
    "sg:city":"Sainte-Francoise",
    "sg:phone":"+1 418 857 3232",
    "sg:postcode":"G0L 3B0",
    "sg:province":"QC",
    "sg:tags":[
        "vegetable",
        "farm"
    ],
    "wof:name":"Distribution R Rioux",
    "wof:placetype":"venue"
},
  "geometry": {"coordinates":[-71.998367,46.454464],"type":"Point"}
}