{
  "type": "Feature",
  "properties": {
    "addr:full":"124 15 Ave SE # 201 Calgary AB T2G 5A8",
    "addr:postcode":"t2g 5a8",
    "addr:street":"124 15 Ave Se # 201",
    "iso:country":"CA",
    "sg:address":"124 15 Ave SE # 201",
    "sg:city":"Calgary",
    "sg:classifiers":[
        {
            "category":"Social Services",
            "subcategory":"Adult Care",
            "type":"Services"
        }
    ],
    "sg:phone":"+1 403 294 1440",
    "sg:postcode":"T2G 5A8",
    "sg:province":"AB",
    "sg:tags":[
        "senior",
        "housing",
        "citizen"
    ],
    "wof:name":"Gracewood Housing Group Ltd",
    "wof:placetype":"venue"
},
  "geometry": {"coordinates":[-114.062775,51.038677],"type":"Point"}
}