{
  "type": "Feature",
  "properties": {
    "addr:full":"1453 Gerrard St E Toronto ON M4L 1Z9",
    "addr:housenumber":"1453",
    "addr:postcode":"m4l 1z9",
    "addr:street":"Gerrard St E",
    "iso:country":"CA",
    "sg:address":"1453 Gerrard St E",
    "sg:city":"Toronto",
    "sg:classifiers":[
        {
            "category":"Manufacturing",
            "subcategory":"Apparel",
            "type":"Manufacturing & Wholesale Goods"
        }
    ],
    "sg:phone":"+1 416 778 7455",
    "sg:postcode":"M4L 1Z9",
    "sg:province":"ON",
    "sg:tags":[
        "textile",
        "manufacturer"
    ],
    "wof:name":"Neelam Silk",
    "wof:placetype":"venue"
},
  "geometry": {"coordinates":[-79.321388,43.672264],"type":"Point"}
}