{
  "type": "Feature",
  "properties": {
    "addr:full":"Rosemere QC J7A 3T2",
    "addr:postcode":"j7a 3t2",
    "iso:country":"CA",
    "sg:city":"Rosemere",
    "sg:classifiers":[
        {
            "category":"Shopping",
            "subcategory":"Shoes",
            "type":"Retail Goods"
        }
    ],
    "sg:phone":"+1 450 430 3073",
    "sg:postcode":"J7A 3T2",
    "sg:province":"QC",
    "wof:name":"Foot Locker",
    "wof:placetype":"venue"
},
  "geometry": {"coordinates":[-73.817055,45.632904],"type":"Point"}
}