{
  "type": "Feature",
  "properties": {
    "iso:country":"CA",
    "sg:city":"Saint-Romuald",
    "sg:classifiers":[
        {
            "category":"Health Services",
            "subcategory":"Health Practitioner",
            "type":"Services"
        }
    ],
    "sg:phone":"+1 418 834 9266",
    "sg:postcode":"G6W 2S6",
    "sg:province":"QC",
    "sg:tags":[
        "physiotherapist"
    ],
    "wof:name":"Physiotherapie St-Romuald",
    "wof:placetype":"venue"
},
  "geometry": {"coordinates":[-71.237724,46.752796],"type":"Point"}
}