{
  "type": "Feature",
  "properties": {
    "addr:full":"98 Vine St Hamilton ON L8R 2A9",
    "addr:housenumber":"98",
    "addr:postcode":"l8r 2a9",
    "addr:street":"Vine St",
    "iso:country":"CA",
    "sg:address":"98 Vine St",
    "sg:city":"Hamilton",
    "sg:classifiers":[
        {
            "category":"Manufacturing",
            "subcategory":"Tools & Machinery",
            "type":"Manufacturing & Wholesale Goods"
        }
    ],
    "sg:phone":"+1 905 528 8651",
    "sg:postcode":"L8R 2A9",
    "sg:province":"ON",
    "sg:tags":[
        "machine",
        "automobile",
        "shop"
    ],
    "wof:name":"Auto Service & Supply",
    "wof:placetype":"venue"
},
  "geometry": {"coordinates":[-79.87127700000001,43.260719],"type":"Point"}
}