{
  "type": "Feature",
  "properties": {
    "addr:full":"Saint-Bernard-DE-Lacolle QC J0J 1V0",
    "addr:postcode":"j0j 1v0",
    "iso:country":"CA",
    "sg:city":"Saint-Bernard-DE-Lacolle",
    "sg:classifiers":[
        {
            "category":"Building & Trades",
            "subcategory":"Construction",
            "type":"Services"
        }
    ],
    "sg:phone":"+1 450 246 2455",
    "sg:postcode":"J0J 1V0",
    "sg:province":"QC",
    "sg:tags":[
        "cabinet",
        "maker",
        "furniture"
    ],
    "wof:name":"Brosseau Antique",
    "wof:placetype":"venue"
},
  "geometry": {"coordinates":[-73.469154,45.118378],"type":"Point"}
}