{
  "type": "Feature",
  "properties": {
    "addr:full":"1123 Kensington Rd NW Calgary AB T2N 3P2",
    "addr:housenumber":"1123",
    "addr:postcode":"t2n 3p2",
    "addr:street":"Kensington Rd Nw",
    "iso:country":"CA",
    "sg:address":"1123 Kensington Rd NW",
    "sg:city":"Calgary",
    "sg:classifiers":[
        {
            "category":"Food & Beverages",
            "subcategory":"Candy",
            "type":"Retail Goods"
        }
    ],
    "sg:phone":"+1 403 283 5550",
    "sg:postcode":"T2N 3P2",
    "sg:province":"AB",
    "sg:tags":[
        "confectionery"
    ],
    "wof:name":"Chocolaterie Bernard Callebaut",
    "wof:placetype":"venue"
},
  "geometry": {"coordinates":[-114.087524,51.05238],"type":"Point"}
}