{
  "type": "Feature",
  "properties": {
    "iso:country":"CA",
    "sg:city":"Langley",
    "sg:classifiers":[
        {
            "category":"Health Services",
            "subcategory":"Doctor",
            "type":"Services"
        }
    ],
    "sg:phone":"+1 604 534 6711",
    "sg:postcode":"V3A 2C6",
    "sg:province":"BC",
    "sg:tags":[
        "physician",
        "surgeon"
    ],
    "wof:name":"Martin, Brendan MD",
    "wof:placetype":"venue"
},
  "geometry": {"coordinates":[-122.651756,49.102962],"type":"Point"}
}