{
  "type": "Feature",
  "properties": {
    "addr:full":"Langley BC V3A 2C6",
    "addr:postcode":"v3a 2c6",
    "iso:country":"CA",
    "sg:city":"Langley",
    "sg:classifiers":[
        {
            "category":"Health Services",
            "subcategory":"Doctor",
            "type":"Services"
        }
    ],
    "sg:phone":"+1 604 534 6711",
    "sg:postcode":"V3A 2C6",
    "sg:province":"BC",
    "sg:tags":[
        "physician",
        "surgeon"
    ],
    "wof:name":"Martin, Brendan MD",
    "wof:placetype":"venue"
},
  "geometry": {"coordinates":[-122.65175600000001,49.102962],"type":"Point"}
}