{
  "type": "Feature",
  "properties": {
    "addr:full":"131 Av Principale Rouyn-Noranda QC J9X 4P3",
    "addr:postcode":"j9x 4p3",
    "addr:street":"131 Av Principale",
    "iso:country":"CA",
    "sg:address":"131 Av Principale",
    "sg:city":"Rouyn-Noranda",
    "sg:classifiers":[
        {
            "category":"Restaurant",
            "type":"Food & Drink"
        }
    ],
    "sg:phone":"+1 819 764 5646",
    "sg:postcode":"J9X 4P3",
    "sg:province":"QC",
    "wof:name":"Burger King",
    "wof:placetype":"venue"
},
  "geometry": {"coordinates":[-79.0198059082,48.2397460938],"type":"Point"}
}