{
  "type": "Feature",
  "properties": {
    "addr:full":"7245 Rue Alexandra Montreal QC H2R 2Y9",
    "addr:housenumber":"7245",
    "addr:postcode":"h2r 2y9",
    "addr:street":"Rue Alexandra",
    "iso:country":"CA",
    "sg:address":"7245 Rue Alexandra",
    "sg:city":"Montreal",
    "sg:classifiers":[
        {
            "category":"Professional",
            "subcategory":"Art Services",
            "type":"Services"
        }
    ],
    "sg:phone":"+1 514 278 6236",
    "sg:postcode":"H2R 2Y9",
    "sg:province":"QC",
    "sg:tags":[
        "graphic",
        "designer"
    ],
    "wof:name":"Fleury Savard",
    "wof:placetype":"venue"
},
  "geometry": {"coordinates":[-73.62106300000001,45.532928],"type":"Point"}
}