{
  "type": "Feature",
  "properties": {
    "iso:country":"CA",
    "sg:address":"5304 46th Ave",
    "sg:city":"Fort Nelson",
    "sg:classifiers":[
        {
            "category":"Retail",
            "subcategory":"Repair Shop",
            "type":"Services"
        }
    ],
    "sg:phone":"+1 250 774 2002",
    "sg:postcode":"V0C 1R0",
    "sg:province":"BC",
    "sg:tags":[
        "welding"
    ],
    "wof:name":"Derick's Welding Ltd",
    "wof:placetype":"venue"
},
  "geometry": {"coordinates":[-122.706001282,58.8000564575],"type":"Point"}
}