{
  "type": "Feature",
  "properties": {
    "iso:country":"CA",
    "sg:address":"5719 Victoria Ave",
    "sg:city":"Niagara Falls",
    "sg:classifiers":[
        {
            "category":"Restaurant",
            "type":"Food & Drink"
        }
    ],
    "sg:phone":"+1 905 354 7471",
    "sg:postcode":"L2G 3L5",
    "sg:province":"ON",
    "wof:name":"Mama Mia's Original Italian",
    "wof:placetype":"venue"
},
  "geometry": {"coordinates":[-79.0757904053,43.0924034119],"type":"Point"}
}