{
  "type": "Feature",
  "properties": {
    "addr:full":"94 Bridgeport Rd E # 1348 Waterloo ON N2J 2J9",
    "addr:housenumber":"94",
    "addr:postcode":"n2j 2j9",
    "addr:street":"Bridgeport Rd E # 1348",
    "iso:country":"CA",
    "sg:address":"94 Bridgeport Rd E # 1348",
    "sg:city":"Waterloo",
    "sg:classifiers":[
        {
            "category":"Food & Beverages",
            "subcategory":"Specialty",
            "type":"Retail Goods"
        }
    ],
    "sg:phone":"+1 519 747 9478",
    "sg:postcode":"N2J 2J9",
    "sg:province":"ON",
    "sg:tags":[
        "health",
        "diet"
    ],
    "wof:name":"General Nutrition Ctr",
    "wof:placetype":"venue"
},
  "geometry": {"coordinates":[-80.51416,43.469692],"type":"Point"}
}