{
  "type": "Feature",
  "properties": {
    "addr:full":"60 Church St Chalk River ON K0J 1J0",
    "addr:housenumber":"60",
    "addr:postcode":"k0j 1j0",
    "addr:street":"Church St",
    "iso:country":"CA",
    "sg:address":"60 Church St",
    "sg:city":"Chalk River",
    "sg:classifiers":[
        {
            "category":"Shopping",
            "subcategory":"Crafts & Fabrics",
            "type":"Retail Goods"
        }
    ],
    "sg:phone":"+1 613 589 2031",
    "sg:postcode":"K0J 1J0",
    "sg:province":"ON",
    "sg:tags":[
        "shop"
    ],
    "wof:name":"Joy Enterprises",
    "wof:placetype":"venue"
},
  "geometry": {"coordinates":[-77.44963799999999,46.01252],"type":"Point"}
}