{
  "type": "Feature",
  "properties": {
    "addr:full":"309 Grays Rd Hamilton ON L8E 1V6",
    "addr:housenumber":"309",
    "addr:postcode":"l8e 1v6",
    "addr:street":"Grays Rd",
    "iso:country":"CA",
    "sg:address":"309 Grays Rd",
    "sg:city":"Hamilton",
    "sg:classifiers":[
        {
            "category":"Food & Beverages",
            "subcategory":"Groceries & Convenience Stores",
            "type":"Retail Goods"
        }
    ],
    "sg:phone":"+1 905 561 9182",
    "sg:postcode":"L8E 1V6",
    "sg:province":"ON",
    "wof:name":"Grays Convenience Store",
    "wof:placetype":"venue"
},
  "geometry": {"coordinates":[-79.74024199999999,43.232933],"type":"Point"}
}