{
  "type": "Feature",
  "properties": {
    "addr:full":"4565 Wallace St Port Alberni BC V9Y 3Y3",
    "addr:housenumber":"4565",
    "addr:postcode":"v9y 3y3",
    "addr:street":"Wallace St",
    "iso:country":"CA",
    "sg:address":"4565 Wallace St",
    "sg:city":"Port Alberni",
    "sg:classifiers":[
        {
            "category":"Health Services",
            "subcategory":"Doctor",
            "type":"Services"
        }
    ],
    "sg:phone":"+1 250 723 8311",
    "sg:postcode":"V9Y 3Y3",
    "sg:province":"BC",
    "sg:tags":[
        "dentist"
    ],
    "wof:name":"Zens, Peter K DDS",
    "wof:placetype":"venue"
},
  "geometry": {"coordinates":[-124.800857544,49.2507019043],"type":"Point"}
}