{
  "type": "Feature",
  "properties": {
    "addr:full":"1383 Dugald Rd Winnipeg MB R2J 0H3",
    "addr:housenumber":"1383",
    "addr:postcode":"r2j 0h3",
    "addr:street":"Dugald Rd",
    "iso:country":"CA",
    "sg:address":"1383 Dugald Rd",
    "sg:city":"Winnipeg",
    "sg:classifiers":[
        {
            "category":"Building & Trades",
            "subcategory":"Construction",
            "type":"Services"
        }
    ],
    "sg:phone":"+1 204 237 7375",
    "sg:postcode":"R2J 0H3",
    "sg:province":"MB",
    "sg:tags":[
        "general",
        "contractor"
    ],
    "wof:name":"Boretta Construction Ltd",
    "wof:placetype":"venue"
},
  "geometry": {"coordinates":[-97.055649,49.886074],"type":"Point"}
}