{
  "type": "Feature",
  "properties": {
    "addr:full":"255 Thurso St Winnipeg MB R3M 3C7",
    "addr:housenumber":"255",
    "addr:postcode":"r3m 3c7",
    "addr:street":"Thurso St",
    "iso:country":"CA",
    "sg:address":"255 Thurso St",
    "sg:city":"Winnipeg",
    "sg:classifiers":[
        {
            "category":"Professional",
            "subcategory":"Business Services",
            "type":"Services"
        }
    ],
    "sg:phone":"+1 204 478 9994",
    "sg:postcode":"R3M 3C7",
    "sg:province":"MB",
    "sg:tags":[
        "water",
        "treatment"
    ],
    "wof:name":"Nor-Chem Water Treatment",
    "wof:placetype":"venue"
},
  "geometry": {"coordinates":[-97.172302,49.863415],"type":"Point"}
}