{
  "type": "Feature",
  "properties": {
    "addr:full":"117 Rue Du Quebec Sherbrooke QC J1H 3L4",
    "addr:housenumber":"117",
    "addr:postcode":"j1h 3l4",
    "addr:street":"Rue Du Quebec",
    "iso:country":"CA",
    "sg:address":"117 Rue Du Quebec",
    "sg:city":"Sherbrooke",
    "sg:classifiers":[
        {
            "category":"Manufacturing",
            "subcategory":"Buildings",
            "type":"Manufacturing & Wholesale Goods"
        }
    ],
    "sg:phone":"+1 819 569 7991",
    "sg:postcode":"J1H 3L4",
    "sg:province":"QC",
    "sg:tags":[
        "prefab",
        "home",
        "log",
        "cabin"
    ],
    "wof:name":"Batiments Multiconcept Enr",
    "wof:placetype":"venue"
},
  "geometry": {"coordinates":[-71.9049453735,45.4004478455],"type":"Point"}
}