{
  "type": "Feature",
  "properties": {
    "addr:full":"7535 Boul Des Forges Trois-Rivieres QC G8Y 1Z3",
    "addr:housenumber":"7535",
    "addr:postcode":"g8y 1z3",
    "addr:street":"Boul Des Forges Trois-Rivieres",
    "iso:country":"CA",
    "sg:address":"7535 Boul Des Forges",
    "sg:city":"Trois-Rivieres",
    "sg:classifiers":[
        {
            "category":"Autos & Motor Vehicles",
            "subcategory":"Motorcycle Sales",
            "type":"Retail Goods"
        }
    ],
    "sg:phone":"+1 819 379 8288",
    "sg:postcode":"G8Y 1Z3",
    "sg:province":"QC",
    "sg:tags":[
        "scooter"
    ],
    "wof:name":"Clinique DE LA Moto Enr",
    "wof:placetype":"venue"
},
  "geometry": {"coordinates":[-72.6133880615,46.3745727539],"type":"Point"}
}