{
  "type": "Feature",
  "properties": {
    "addr:full":"337 Holyrood Holyrood NL A0A 2R0",
    "addr:housenumber":"337",
    "addr:postcode":"a0a 2r0",
    "addr:street":"Holyrood",
    "iso:country":"CA",
    "sg:address":"337 Holyrood",
    "sg:city":"Holyrood",
    "sg:classifiers":[
        {
            "category":"Health Services",
            "subcategory":"Doctor",
            "type":"Services"
        }
    ],
    "sg:phone":"+1 709 229 7385",
    "sg:postcode":"A0A 2R0",
    "sg:province":"NL",
    "sg:tags":[
        "physician",
        "surgeon"
    ],
    "wof:name":"Holyrood Medical Clinic",
    "wof:placetype":"venue"
},
  "geometry": {"coordinates":[-53.145828,47.381283],"type":"Point"}
}