{
  "type": "Feature",
  "properties": {
    "addr:full":"842 Av Sainte-Croix Saint-Laurent QC H4L 3Y4",
    "addr:postcode":"h4l 3y4",
    "addr:street":"842 Av Sainte-Croix",
    "iso:country":"CA",
    "sg:address":"842 Av Sainte-Croix",
    "sg:city":"Saint-Laurent",
    "sg:classifiers":[
        {
            "category":"Professional",
            "subcategory":"Business Services",
            "type":"Services"
        }
    ],
    "sg:phone":"+1 514 748 9314",
    "sg:postcode":"H4L 3Y4",
    "sg:province":"QC",
    "sg:tags":[
        "notary"
    ],
    "wof:name":"Grou Leduc & Farley",
    "wof:placetype":"venue"
},
  "geometry": {"coordinates":[-73.6767959595,45.5141944885],"type":"Point"}
}