{
  "type": "Feature",
  "properties": {
    "addr:full":"34478 97th St Oliver BC V0H 1T0",
    "addr:housenumber":"34478",
    "addr:postcode":"bc v0h 1t0",
    "addr:street":"97Th St",
    "iso:country":"CA",
    "sg:address":"34478 97th St",
    "sg:city":"Oliver",
    "sg:classifiers":[
        {
            "category":"Health Services",
            "subcategory":"Medical Lab",
            "type":"Services"
        }
    ],
    "sg:phone":"+1 250 498 3858",
    "sg:postcode":"V0H 1T0",
    "sg:province":"BC",
    "wof:name":"Community Denture Ctr",
    "wof:placetype":"venue"
},
  "geometry": {"coordinates":[-119.55310821499999,49.1768836975],"type":"Point"}
}