{
  "type": "Feature",
  "properties": {
    "iso:country":"CA",
    "sg:city":"Edmonton",
    "sg:classifiers":[
        {
            "category":"Health Services",
            "subcategory":"Chiropractor",
            "type":"Services"
        }
    ],
    "sg:phone":"+1 780 422 5477",
    "sg:postcode":"T5J 2Y2",
    "sg:province":"AB",
    "wof:name":"Hurst Enterprises",
    "wof:placetype":"venue"
},
  "geometry": {"coordinates":[-113.502685547,53.5399627686],"type":"Point"}
}