{
  "type": "Feature",
  "properties": {
    "iso:country":"CA",
    "sg:address":"7812 100 Ave",
    "sg:city":"Peace River",
    "sg:classifiers":[
        {
            "category":"Restaurant",
            "type":"Food & Drink"
        }
    ],
    "sg:phone":"+1 780 624 4003",
    "sg:postcode":"T8S 2A3",
    "sg:province":"AB",
    "wof:name":"Mc Donald's",
    "wof:placetype":"venue"
},
  "geometry": {"coordinates":[-117.342529297,56.2332992554],"type":"Point"}
}