{
  "type": "Feature",
  "properties": {
    "addr:full":"1216 River Rd Manotick ON K4M 1B4",
    "addr:housenumber":"1216",
    "addr:postcode":"k4m 1b4",
    "addr:street":"River Rd",
    "iso:country":"CA",
    "sg:address":"1216 River Rd",
    "sg:city":"Manotick",
    "sg:classifiers":[
        {
            "category":"Professional",
            "subcategory":"Art Services",
            "type":"Services"
        }
    ],
    "sg:phone":"+1 613 692 1104",
    "sg:postcode":"K4M 1B4",
    "sg:province":"ON",
    "sg:tags":[
        "production",
        "layout",
        "advertising"
    ],
    "wof:name":"Huggett Music Productions",
    "wof:placetype":"venue"
},
  "geometry": {"coordinates":[-75.66860200000001,45.226463],"type":"Point"}
}