{
  "type": "Feature",
  "properties": {
    "addr:full":"1764 Kelly Douglas Rd Kamloops BC V2C 5S4",
    "addr:housenumber":"1764",
    "addr:postcode":"bc v2c 5s4",
    "addr:street":"Kelly Douglas Rd",
    "iso:country":"CA",
    "sg:address":"1764 Kelly Douglas Rd",
    "sg:city":"Kamloops",
    "sg:classifiers":[
        {
            "category":"Manufacturing",
            "subcategory":"Metals",
            "type":"Manufacturing & Wholesale Goods"
        }
    ],
    "sg:phone":"+1 250 372 9552",
    "sg:postcode":"V2C 5S4",
    "sg:province":"BC",
    "sg:tags":[
        "hose",
        "coupling",
        "contractor"
    ],
    "wof:name":"Finning Canada",
    "wof:placetype":"venue"
},
  "geometry": {"coordinates":[-120.2862854,50.6786193848],"type":"Point"}
}