{
  "type": "Feature",
  "properties": {
    "addr:full":"Toronto ON M4Y 2X6",
    "addr:postcode":"m4y 2x6",
    "iso:country":"CA",
    "sg:city":"Toronto",
    "sg:classifiers":[
        {
            "category":"Food & Beverages",
            "subcategory":"Bakery",
            "type":"Retail Goods"
        }
    ],
    "sg:phone":"+1 416 962 0358",
    "sg:postcode":"M4Y 2X6",
    "sg:province":"ON",
    "sg:tags":[
        "baker"
    ],
    "wof:name":"Sweet City Bakery",
    "wof:placetype":"venue"
},
  "geometry": {"coordinates":[-79.385948,43.664761],"type":"Point"}
}