{
  "type": "Feature",
  "properties": {
    "addr:full":"778 Archibald St Winnipeg MB R2J 0Y4",
    "addr:housenumber":"778",
    "addr:postcode":"r2j 0y4",
    "addr:street":"Archibald St",
    "iso:country":"CA",
    "sg:address":"778 Archibald St",
    "sg:city":"Winnipeg",
    "sg:classifiers":[
        {
            "category":"Organizations",
            "subcategory":"Religious Organization",
            "type":"Services"
        }
    ],
    "sg:phone":"+1 204 237 3068",
    "sg:postcode":"R2J 0Y4",
    "sg:province":"MB",
    "sg:tags":[
        "church"
    ],
    "wof:name":"Holy Family Church",
    "wof:placetype":"venue"
},
  "geometry": {"coordinates":[-97.09599300000001,49.876904],"type":"Point"}
}