{
  "type": "Feature",
  "properties": {
    "addr:full":"524 Darlington Dr Dalhousie NB E8C 1N1",
    "addr:housenumber":"524",
    "addr:postcode":"e8c 1n1",
    "addr:street":"Darlington Dr",
    "iso:country":"CA",
    "sg:address":"524 Darlington Dr",
    "sg:city":"Dalhousie",
    "sg:classifiers":[
        {
            "category":"Wholesale",
            "subcategory":"Scrap",
            "type":"Manufacturing & Wholesale Goods"
        }
    ],
    "sg:phone":"+1 506 684 3285",
    "sg:postcode":"E8C 1N1",
    "sg:province":"NB",
    "sg:tags":[
        "iron",
        "recycling",
        "metal",
        "can",
        "bottle",
        "depot"
    ],
    "wof:name":"Billy's Bottle Exchange",
    "wof:placetype":"venue"
},
  "geometry": {"coordinates":[-66.40007,48.041725],"type":"Point"}
}