{
  "type": "Feature",
  "properties": {
    "addr:full":"Kitchener ON N2E 2L6",
    "addr:postcode":"n2e 2l6",
    "iso:country":"CA",
    "sg:city":"Kitchener",
    "sg:classifiers":[
        {
            "category":"Manufacturing",
            "subcategory":"Tools & Machinery",
            "type":"Manufacturing & Wholesale Goods"
        }
    ],
    "sg:phone":"+1 519 748 4735",
    "sg:postcode":"N2E 2L6",
    "sg:province":"ON",
    "sg:tags":[
        "machine",
        "shop"
    ],
    "wof:name":"Gruhle Manufacturing Ltd",
    "wof:placetype":"venue"
},
  "geometry": {"coordinates":[-80.459412,43.39872],"type":"Point"}
}