{
  "type": "Feature",
  "properties": {
    "addr:full":"North York ON M3J 3K5",
    "addr:postcode":"m3j 3k5",
    "iso:country":"CA",
    "sg:city":"North York",
    "sg:classifiers":[
        {
            "category":"Restaurant",
            "type":"Food & Drink"
        }
    ],
    "sg:phone":"+1 416 739 6651",
    "sg:postcode":"M3J 3K5",
    "sg:province":"ON",
    "sg:tags":[
        "delicatessen"
    ],
    "wof:name":"International Discount Foods",
    "wof:placetype":"venue"
},
  "geometry": {"coordinates":[-79.49095199999999,43.782234],"type":"Point"}
}