{
  "type": "Feature",
  "properties": {
    "addr:full":"19 Victoria St E Alliston ON L9R 1T3",
    "addr:housenumber":"19",
    "addr:postcode":"l9r 1t3",
    "addr:street":"Victoria St E Alliston",
    "iso:country":"CA",
    "sg:address":"19 Victoria St E",
    "sg:city":"Alliston",
    "sg:classifiers":[
        {
            "category":"Cinema",
            "subcategory":"Movie Theater",
            "type":"Entertainment"
        }
    ],
    "sg:phone":"+1 705 435 7631",
    "sg:postcode":"L9R 1T3",
    "sg:province":"ON",
    "wof:name":"Circle Theatre",
    "wof:placetype":"venue"
},
  "geometry": {"coordinates":[-79.8682174683,44.1540527344],"type":"Point"}
}