{
  "type": "Feature",
  "properties": {
    "iso:country":"CA",
    "sg:address":"475 Saskatchewan Ave E",
    "sg:city":"Portage LA Prairie",
    "sg:classifiers":[
        {
            "category":"Building & Trades",
            "subcategory":"Equipment Rental",
            "type":"Services"
        }
    ],
    "sg:phone":"+1 204 239 6088",
    "sg:postcode":"R1N 0L5",
    "sg:province":"MB",
    "sg:tags":[
        "yard"
    ],
    "wof:name":"Linden's Rent-Alls",
    "wof:placetype":"venue"
},
  "geometry": {"coordinates":[-98.28314208979999,49.9725837708],"type":"Point"}
}