{
  "type": "Feature",
  "properties": {
    "addr:full":"171 107 Rte Deleage QC J9E 3A8",
    "addr:housenumber":"107",
    "addr:postcode":"j9e 3a8",
    "addr:street":"Rte Deleage",
    "iso:country":"CA",
    "sg:address":"171 107 Rte",
    "sg:city":"Deleage",
    "sg:classifiers":[
        {
            "category":"Retail",
            "subcategory":"Auto Repair",
            "type":"Services"
        }
    ],
    "sg:phone":"+1 819 449 3608",
    "sg:postcode":"J9E 3A8",
    "sg:province":"QC",
    "sg:tags":[
        "repairing",
        "automobile"
    ],
    "wof:name":"Garage Claude Mantha",
    "wof:placetype":"venue"
},
  "geometry": {"coordinates":[-75.95938110349999,46.3846244812],"type":"Point"}
}