{
  "type": "Feature",
  "properties": {
    "addr:full":"43 3rd Ave E Vancouver BC V5T 1C5",
    "addr:housenumber":"43",
    "addr:postcode":"v5t 1c5",
    "addr:street":"3Rd Ave E",
    "iso:country":"CA",
    "sg:address":"43 3rd Ave E",
    "sg:city":"Vancouver",
    "sg:classifiers":[
        {
            "category":"Manufacturing",
            "subcategory":"Metals",
            "type":"Manufacturing & Wholesale Goods"
        }
    ],
    "sg:phone":"+1 604 879 2901",
    "sg:postcode":"V5T 1C5",
    "sg:province":"BC",
    "sg:tags":[
        "stamping"
    ],
    "wof:name":"Metal & Wood Products Ltd",
    "wof:placetype":"venue"
},
  "geometry": {"coordinates":[-123.10383606000001,49.2684211731],"type":"Point"}
}