{
  "type": "Feature",
  "properties": {
    "iso:country":"CA",
    "sg:city":"Vancouver",
    "sg:classifiers":[
        {
            "category":"Professional",
            "subcategory":"Lawyer & Legal Services",
            "type":"Services"
        }
    ],
    "sg:phone":"+1 604 682 7474",
    "sg:postcode":"V6Z 2K8",
    "sg:province":"BC",
    "sg:tags":[
        "attorney"
    ],
    "wof:name":"Berezowskyj, Stephen J",
    "wof:placetype":"venue"
},
  "geometry": {"coordinates":[-123.126152039,49.2785987854],"type":"Point"}
}