{
  "type": "Feature",
  "properties": {
    "addr:full":"2942 Finch Ave E Scarborough ON M1W 2T4",
    "addr:housenumber":"2942",
    "addr:postcode":"m1w 2t4",
    "addr:street":"Finch Ave E",
    "iso:country":"CA",
    "sg:address":"2942 Finch Ave E",
    "sg:city":"Scarborough",
    "sg:classifiers":[
        {
            "category":"Organizations",
            "subcategory":"Labor Organization",
            "type":"Services"
        }
    ],
    "sg:phone":"+1 416 495 1599",
    "sg:postcode":"M1W 2T4",
    "sg:province":"ON",
    "wof:name":"Ontario Public Svc Employees",
    "wof:placetype":"venue"
},
  "geometry": {"coordinates":[-79.3290557861,43.793800354],"type":"Point"}
}