{
  "type": "Feature",
  "properties": {
    "addr:full":"1150 Boul Saint-Joseph E Montreal QC H2J 1L5",
    "addr:housenumber":"1150",
    "addr:postcode":"h2j 1l5",
    "addr:street":"Boul Saint-Joseph E",
    "iso:country":"CA",
    "sg:address":"1150 Boul Saint-Joseph E",
    "sg:city":"Montreal",
    "sg:classifiers":[
        {
            "category":"Health Services",
            "subcategory":"Doctor",
            "type":"Services"
        }
    ],
    "sg:phone":"+1 514 523 1151",
    "sg:postcode":"H2J 1L5",
    "sg:province":"QC",
    "sg:tags":[
        "physician",
        "surgeon"
    ],
    "wof:name":"Cersf Canada Inc",
    "wof:placetype":"venue"
},
  "geometry": {"coordinates":[-73.5835800171,45.5305519104],"type":"Point"}
}