{
  "type": "Feature",
  "properties": {
    "addr:full":"31 Durham St S Madoc ON K0K 2K0",
    "addr:housenumber":"31",
    "addr:postcode":"k0k 2k0",
    "addr:street":"Durham St S",
    "iso:country":"CA",
    "sg:address":"31 Durham St S",
    "sg:city":"Madoc",
    "sg:classifiers":[
        {
            "category":"Utilities",
            "subcategory":"Cable",
            "type":"Services"
        }
    ],
    "sg:phone":"+1 613 473 2839",
    "sg:postcode":"K0K 2K0",
    "sg:province":"ON",
    "sg:tags":[
        "television"
    ],
    "wof:name":"Hastings Cablevision Ltd",
    "wof:placetype":"venue"
},
  "geometry": {"coordinates":[-77.472374,44.504856],"type":"Point"}
}