{
  "type": "Feature",
  "properties": {
    "addr:full":"1326 Garrison Rd Fort Erie ON L2A 1P1",
    "addr:housenumber":"1326",
    "addr:postcode":"l2a 1p1",
    "addr:street":"Garrison Rd",
    "iso:country":"CA",
    "sg:address":"1326 Garrison Rd",
    "sg:city":"Fort Erie",
    "sg:classifiers":[
        {
            "category":"Autos & Motor Vehicles",
            "subcategory":"Automobile Sales",
            "type":"Retail Goods"
        }
    ],
    "sg:phone":"+1 905 871 1816",
    "sg:postcode":"L2A 1P1",
    "sg:province":"ON",
    "sg:tags":[
        "repairing",
        "car"
    ],
    "wof:name":"Green Acres Svc",
    "wof:placetype":"venue"
},
  "geometry": {"coordinates":[-78.9647445679,42.9048614502],"type":"Point"}
}