{
  "type": "Feature",
  "properties": {
    "addr:full":"5429 Dundas St W #4 Etobicoke ON M9B 1B5",
    "addr:housenumber":"5429",
    "addr:postcode":"m9b 1b5",
    "addr:street":"Dundas St W # 4",
    "iso:country":"CA",
    "sg:address":"5429 Dundas St W #4",
    "sg:city":"Etobicoke",
    "sg:classifiers":[
        {
            "category":"Retail",
            "subcategory":"Auto Rental",
            "type":"Services"
        }
    ],
    "sg:phone":"+1 416 251 2932",
    "sg:postcode":"M9B 1B5",
    "sg:province":"ON",
    "sg:tags":[
        "renting",
        "automobile"
    ],
    "wof:name":"Advantage Car & Truck Rentals",
    "wof:placetype":"venue"
},
  "geometry": {"coordinates":[-79.54280090330001,43.6331825256],"type":"Point"}
}