{
  "type": "Feature",
  "properties": {
    "addr:full":"88 Rue Saint-Andre Metabetchouan-Lac-A-LA-Croix QC G8G 1V3",
    "addr:housenumber":"88",
    "addr:postcode":"g8g 1v3",
    "addr:street":"Rue Saint-Andre",
    "iso:country":"CA",
    "sg:address":"88 Rue Saint-Andre",
    "sg:city":"Metabetchouan-Lac-A-LA-Croix",
    "sg:classifiers":[
        {
            "category":"Organizations",
            "subcategory":"Religious Organization",
            "type":"Services"
        }
    ],
    "sg:phone":"+1 418 349 2121",
    "sg:postcode":"G8G 1V3",
    "sg:province":"QC",
    "sg:tags":[
        "church"
    ],
    "wof:name":"Presbytere St-Jerome",
    "wof:placetype":"venue"
},
  "geometry": {"coordinates":[-72.049026,48.419083],"type":"Point"}
}