{
  "type": "Feature",
  "properties": {
    "addr:full":"Prince Albert SK S6V 3X7",
    "addr:postcode":"s6v 3x7",
    "iso:country":"CA",
    "sg:city":"Prince Albert",
    "sg:classifiers":[
        {
            "category":"Building & Trades",
            "subcategory":"Plumbing",
            "type":"Services"
        }
    ],
    "sg:phone":"+1 306 764 2826",
    "sg:postcode":"S6V 3X7",
    "sg:province":"SK",
    "sg:tags":[
        "mechanical",
        "contractor"
    ],
    "wof:name":"Thermal Metals",
    "wof:placetype":"venue"
},
  "geometry": {"coordinates":[-105.76442,53.197525],"type":"Point"}
}