{
  "type": "Feature",
  "properties": {
    "addr:full":"145 Highbury Ave St Thomas ON N5P 4J4",
    "addr:housenumber":"145",
    "addr:postcode":"n5p 4j4",
    "addr:street":"Highbury Ave",
    "iso:country":"CA",
    "sg:address":"145 Highbury Ave",
    "sg:city":"St Thomas",
    "sg:classifiers":[
        {
            "category":"Manufacturing",
            "subcategory":"Tools & Machinery",
            "type":"Manufacturing & Wholesale Goods"
        }
    ],
    "sg:phone":"+1 519 637 1720",
    "sg:postcode":"N5P 4J4",
    "sg:province":"ON",
    "sg:tags":[
        "alternator",
        "starter"
    ],
    "wof:name":"St Thomas Starter & Alternator",
    "wof:placetype":"venue"
},
  "geometry": {"coordinates":[-81.150093,42.798355],"type":"Point"}
}