{
  "type": "Feature",
  "properties": {
    "addr:full":"86 Charleswood Dr Beaconsfield QC H9W 5N3",
    "addr:housenumber":"86",
    "addr:postcode":"h9w 5n3",
    "addr:street":"Charleswood Dr",
    "iso:country":"CA",
    "sg:address":"86 Charleswood Dr",
    "sg:city":"Beaconsfield",
    "sg:classifiers":[
        {
            "category":"Social Services",
            "subcategory":"Child Care",
            "type":"Services"
        }
    ],
    "sg:phone":"+1 514 695 7148",
    "sg:postcode":"H9W 5N3",
    "sg:province":"QC",
    "sg:tags":[
        "kindergarten",
        "academic",
        "school"
    ],
    "wof:name":"Busy Fours Preschool",
    "wof:placetype":"venue"
},
  "geometry": {"coordinates":[-73.84026299999999,45.433743],"type":"Point"}
}