{
  "type": "Feature",
  "properties": {
    "iso:country":"CA",
    "sg:address":"128 Parkdale Ave N",
    "sg:city":"Hamilton",
    "sg:classifiers":[
        {
            "category":"Restaurant",
            "type":"Food & Drink"
        }
    ],
    "sg:phone":"+1 905 549 1011",
    "sg:postcode":"L8H 5X2",
    "sg:province":"ON",
    "wof:name":"Shuffles Restaurant",
    "wof:placetype":"venue"
},
  "geometry": {"coordinates":[-79.7903518677,43.2399368286],"type":"Point"}
}