{
  "type": "Feature",
  "properties": {
    "addr:full":"24 River Dr Port Dover ON N0A 1N7",
    "addr:housenumber":"24",
    "addr:postcode":"n0a 1n7",
    "addr:street":"River Dr Port Dover",
    "iso:country":"CA",
    "sg:address":"24 River Dr",
    "sg:city":"Port Dover",
    "sg:classifiers":[
        {
            "category":"Recreation",
            "subcategory":"Marina",
            "type":"Entertainment"
        }
    ],
    "sg:phone":"+1 519 583 1611",
    "sg:postcode":"N0A 1N7",
    "sg:province":"ON",
    "wof:name":"Bridge Marine Svc",
    "wof:placetype":"venue"
},
  "geometry": {"coordinates":[-80.197464,42.787193],"type":"Point"}
}