{
  "type": "Feature",
  "properties": {
    "addr:full":"2809 45 Ave Vernon BC V1T 3N5",
    "addr:housenumber":"2809",
    "addr:postcode":"v1t 3n5",
    "addr:street":"45 Ave",
    "iso:country":"CA",
    "sg:address":"2809 45 Ave",
    "sg:city":"Vernon",
    "sg:classifiers":[
        {
            "category":"Home & Garden",
            "subcategory":"Building Materials",
            "type":"Retail Goods"
        }
    ],
    "sg:phone":"+1 250 542 9309",
    "sg:postcode":"V1T 3N5",
    "sg:province":"BC",
    "sg:tags":[
        "glass",
        "window",
        "plate"
    ],
    "wof:name":"H & L Glass Ltd",
    "wof:placetype":"venue"
},
  "geometry": {"coordinates":[-119.268494,50.278023],"type":"Point"}
}