{
  "type": "Feature",
  "properties": {
    "addr:full":"Windsor NS B0N 2T0",
    "addr:postcode":"b0n 2t0",
    "iso:country":"CA",
    "sg:city":"Windsor",
    "sg:classifiers":[
        {
            "category":"Education",
            "subcategory":"Special Training",
            "type":"Public Place"
        }
    ],
    "sg:phone":"+1 902 798 0732",
    "sg:postcode":"B0N 2T0",
    "sg:province":"NS",
    "sg:tags":[
        "instruction",
        "music"
    ],
    "wof:name":"Dorian Hall Academy of Music",
    "wof:placetype":"venue"
},
  "geometry": {"coordinates":[-64.139061,44.994808],"type":"Point"}
}