{
  "type": "Feature",
  "properties": {
    "addr:full":"3005 Boul Pitfield Saint-Laurent QC H4S 1H4",
    "addr:housenumber":"3005",
    "addr:postcode":"h4s 1h4",
    "addr:street":"Boul Pitfield",
    "iso:country":"CA",
    "sg:address":"3005 Boul Pitfield",
    "sg:city":"Saint-Laurent",
    "sg:classifiers":[
        {
            "category":"Manufacturing",
            "subcategory":"Tools & Machinery",
            "type":"Manufacturing & Wholesale Goods"
        }
    ],
    "sg:phone":"+1 514 332 7967",
    "sg:postcode":"H4S 1H4",
    "sg:province":"QC",
    "sg:tags":[
        "fire",
        "equipment",
        "protection"
    ],
    "wof:name":"Protection Incendie Polygon",
    "wof:placetype":"venue"
},
  "geometry": {"coordinates":[-73.74762699999999,45.497883],"type":"Point"}
}