{
  "type": "Feature",
  "properties": {
    "iso:country":"CA",
    "sg:address":"1006 Broadway Ave",
    "sg:city":"Saskatoon",
    "sg:classifiers":[
        {
            "category":"Organizations",
            "subcategory":"Religious Organization",
            "type":"Services"
        }
    ],
    "sg:phone":"+1 306 653 0771",
    "sg:postcode":"S7N 1B9",
    "sg:province":"SK",
    "sg:tags":[
        "church"
    ],
    "wof:name":"St Josephs Parish",
    "wof:placetype":"venue"
},
  "geometry": {"coordinates":[-106.656974792,52.1155319214],"type":"Point"}
}