{
  "type": "Feature",
  "properties": {
    "addr:full":"334 Rue Marie-DE-L'Incarnation Quebec QC G1N 3G6",
    "addr:housenumber":"334",
    "addr:postcode":"g1n 3g6",
    "addr:street":"Rue Marie-De-L'Incarnation",
    "iso:country":"CA",
    "sg:address":"334 Rue Marie-DE-L'Incarnation",
    "sg:city":"Quebec",
    "sg:classifiers":[
        {
            "category":"Restaurant",
            "type":"Food & Drink"
        }
    ],
    "sg:phone":"+1 418 687 0829",
    "sg:postcode":"G1N 3G6",
    "sg:province":"QC",
    "wof:name":"Restaurant Super Club Sandwich",
    "wof:placetype":"venue"
},
  "geometry": {"coordinates":[-71.4194717407,46.858581543],"type":"Point"}
}