{
  "type": "Feature",
  "properties": {
    "addr:full":"500 Rue Saint-Eustache Saint-Eustache QC J7R 7E7",
    "addr:housenumber":"500",
    "addr:postcode":"j7r 7e7",
    "addr:street":"Rue Saint-Eustache",
    "iso:country":"CA",
    "sg:address":"500 Rue Saint-Eustache",
    "sg:city":"Saint-Eustache",
    "sg:classifiers":[
        {
            "category":"Manufacturing",
            "subcategory":"Glass & Minerals",
            "type":"Manufacturing & Wholesale Goods"
        }
    ],
    "sg:phone":"+1 450 491 7800",
    "sg:postcode":"J7R 7E7",
    "sg:province":"QC",
    "sg:tags":[
        "building",
        "material",
        "common"
    ],
    "wof:name":"Transpave Inc",
    "wof:placetype":"venue"
},
  "geometry": {"coordinates":[-73.91831970210001,45.563659668],"type":"Point"}
}