{
  "type": "Feature",
  "properties": {
    "addr:full":"10123 99 St NW # 1720 Edmonton AB T5J 3H1",
    "addr:housenumber":"10123",
    "addr:postcode":"t5j 3h1",
    "addr:street":"99 St Nw # 1720",
    "iso:country":"CA",
    "sg:address":"10123 99 St NW # 1720",
    "sg:city":"Edmonton",
    "sg:classifiers":[
        {
            "category":"Professional",
            "subcategory":"Lawyer & Legal Services",
            "type":"Services"
        }
    ],
    "sg:phone":"+1 780 424 7145",
    "sg:postcode":"T5J 3H1",
    "sg:province":"AB",
    "sg:tags":[
        "attorney"
    ],
    "wof:name":"Caruk, Joseph A",
    "wof:placetype":"venue"
},
  "geometry": {"coordinates":[-113.488495,53.542091],"type":"Point"}
}