{
  "type": "Feature",
  "properties": {
    "addr:full":"258 Wilson Ave North York ON M3H 1S6",
    "addr:housenumber":"258",
    "addr:postcode":"m3h 1s6",
    "addr:street":"Wilson Ave",
    "iso:country":"CA",
    "sg:address":"258 Wilson Ave",
    "sg:city":"North York",
    "sg:classifiers":[
        {
            "category":"Professional",
            "subcategory":"Lawyer & Legal Services",
            "type":"Services"
        }
    ],
    "sg:phone":"+1 416 631 7504",
    "sg:postcode":"M3H 1S6",
    "sg:province":"ON",
    "sg:tags":[
        "attorney"
    ],
    "wof:name":"Greenbaum, Donald QC",
    "wof:placetype":"venue"
},
  "geometry": {"coordinates":[-79.432159,43.73769],"type":"Point"}
}