{
  "type": "Feature",
  "properties": {
    "iso:country":"CA",
    "sg:address":"2695 Rue Charbonneau",
    "sg:city":"Trois-Rivieres-Ouest",
    "sg:classifiers":[
        {
            "category":"Wholesale",
            "subcategory":"Construction Materials",
            "type":"Manufacturing & Wholesale Goods"
        }
    ],
    "sg:phone":"+1 819 377 3627",
    "sg:postcode":"G9A 5C9",
    "sg:province":"QC",
    "sg:tags":[
        "concrete",
        "general",
        "form",
        "contractor"
    ],
    "wof:name":"Coffrages Mauriciens Inc",
    "wof:placetype":"venue"
},
  "geometry": {"coordinates":[-72.59326934809999,46.3322525024],"type":"Point"}
}