{
  "type": "Feature",
  "properties": {
    "addr:full":"Telkwa BC V0J 2X0",
    "addr:postcode":"v0j 2x0",
    "iso:country":"CA",
    "sg:city":"Telkwa",
    "sg:classifiers":[
        {
            "category":"Travel",
            "subcategory":"Campground",
            "type":"Entertainment"
        }
    ],
    "sg:phone":"+1 250 846 5012",
    "sg:postcode":"V0J 2X0",
    "sg:province":"BC",
    "wof:name":"Fort Telkwa Rv Park",
    "wof:placetype":"venue"
},
  "geometry": {"coordinates":[-127.050605774,54.697593689],"type":"Point"}
}