{
  "type": "Feature",
  "properties": {
    "addr:full":"201 Ch Mill Waltham QC J0X 3H0",
    "addr:housenumber":"201",
    "addr:postcode":"j0x 3h0",
    "addr:street":"Ch Mill",
    "iso:country":"CA",
    "sg:address":"201 Ch Mill",
    "sg:city":"Waltham",
    "sg:classifiers":[
        {
            "category":"Wholesale",
            "subcategory":"Construction Materials",
            "type":"Manufacturing & Wholesale Goods"
        }
    ],
    "sg:phone":"+1 819 689 2947",
    "sg:postcode":"J0X 3H0",
    "sg:province":"QC",
    "sg:tags":[
        "lumber"
    ],
    "wof:name":"Sechoirs Waltham",
    "wof:placetype":"venue"
},
  "geometry": {"coordinates":[-76.910149,45.907658],"type":"Point"}
}