{
  "type": "Feature",
  "properties": {
    "addr:full":"607 Colby Dr Waterloo ON N2V 1A1",
    "addr:housenumber":"607",
    "addr:postcode":"n2v 1a1",
    "addr:street":"Colby Dr",
    "iso:country":"CA",
    "sg:address":"607 Colby Dr",
    "sg:city":"Waterloo",
    "sg:classifiers":[
        {
            "category":"Manufacturing",
            "subcategory":"Tools & Machinery",
            "type":"Manufacturing & Wholesale Goods"
        }
    ],
    "sg:phone":"+1 519 746 1516",
    "sg:postcode":"N2V 1A1",
    "sg:province":"ON",
    "sg:tags":[
        "machine",
        "shop"
    ],
    "wof:name":"Baumeier Engineered Products",
    "wof:placetype":"venue"
},
  "geometry": {"coordinates":[-80.5421295166,43.5044517517],"type":"Point"}
}