{
  "type": "Feature",
  "properties": {
    "addr:full":"429 Rue Notre-Dame O Trois-Pistoles QC G0L 4K0",
    "addr:housenumber":"429",
    "addr:postcode":"g0l 4k0",
    "addr:street":"Rue Notre-Dame O",
    "iso:country":"CA",
    "sg:address":"429 Rue Notre-Dame O",
    "sg:city":"Trois-Pistoles",
    "sg:classifiers":[
        {
            "category":"Restaurant",
            "type":"Food & Drink"
        }
    ],
    "sg:phone":"+1 418 851 4022",
    "sg:postcode":"G0L 4K0",
    "sg:province":"QC",
    "wof:name":"Restaurant L'Eclair",
    "wof:placetype":"venue"
},
  "geometry": {"coordinates":[-69.1634674072,48.1315841675],"type":"Point"}
}