{
  "type": "Feature",
  "properties": {
    "addr:full":"1644 York Rd Deseronto ON K0K 1X0",
    "addr:housenumber":"1644",
    "addr:postcode":"k0k 1x0",
    "addr:street":"York Rd",
    "iso:country":"CA",
    "sg:address":"1644 York Rd",
    "sg:city":"Deseronto",
    "sg:classifiers":[
        {
            "category":"Education",
            "subcategory":"Library",
            "type":"Public Place"
        }
    ],
    "sg:phone":"+1 613 967 6264",
    "sg:postcode":"K0K 1X0",
    "sg:province":"ON",
    "wof:name":"Tyendinaga Mohawk Public",
    "wof:placetype":"venue"
},
  "geometry": {"coordinates":[-77.0492935181,44.1945838928],"type":"Point"}
}