{
  "type": "Feature",
  "properties": {
    "iso:country":"CA",
    "sg:address":"2349 Fairview St",
    "sg:city":"Burlington",
    "sg:classifiers":[
        {
            "category":"Social Services",
            "type":"Services"
        }
    ],
    "sg:phone":"+1 905 333 3274",
    "sg:postcode":"L7R 2E3",
    "sg:province":"ON",
    "sg:tags":[
        "counselor",
        "marriage",
        "family"
    ],
    "wof:name":"Garvie, Ken",
    "wof:placetype":"venue"
},
  "geometry": {"coordinates":[-79.801826,43.344078],"type":"Point"}
}