{
  "type": "Feature",
  "properties": {
    "addr:full":"2349 Fairview St Burlington ON L7R 2E3",
    "addr:housenumber":"2349",
    "addr:postcode":"l7r 2e3",
    "addr:street":"Fairview St",
    "iso:country":"CA",
    "sg:address":"2349 Fairview St",
    "sg:city":"Burlington",
    "sg:classifiers":[
        {
            "category":"Social Services",
            "type":"Services"
        }
    ],
    "sg:phone":"+1 905 333 3274",
    "sg:postcode":"L7R 2E3",
    "sg:province":"ON",
    "sg:tags":[
        "counselor",
        "marriage",
        "family"
    ],
    "wof:name":"Garvie, Ken",
    "wof:placetype":"venue"
},
  "geometry": {"coordinates":[-79.80182600000001,43.344078],"type":"Point"}
}