{
  "type": "Feature",
  "properties": {
    "iso:country":"CA",
    "sg:address":"253 Ontario St",
    "sg:city":"Kingston",
    "sg:classifiers":[
        {
            "category":"Recreation",
            "type":"Entertainment"
        }
    ],
    "sg:phone":"+1 613 549 8091",
    "sg:postcode":"K7L 2Z4",
    "sg:province":"ON",
    "sg:tags":[
        "charter",
        "boat"
    ],
    "wof:name":"St Lawrence Cruise Lines Inc",
    "wof:placetype":"venue"
},
  "geometry": {"coordinates":[-76.479393,44.230736],"type":"Point"}
}