{
  "type": "Feature",
  "properties": {
    "iso:country":"CA",
    "sg:address":"1537 Grant Ave",
    "sg:city":"Winnipeg",
    "sg:classifiers":[
        {
            "category":"Health Services",
            "subcategory":"Doctor",
            "type":"Services"
        }
    ],
    "sg:phone":"+1 204 488 7025",
    "sg:postcode":"R3N 0M3",
    "sg:province":"MB",
    "sg:tags":[
        "dentist"
    ],
    "wof:name":"Grant Dental Ctr",
    "wof:placetype":"venue"
},
  "geometry": {"coordinates":[-97.185844,49.856602],"type":"Point"}
}