{
  "type": "Feature",
  "properties": {
    "addr:full":"67 Rue Du Rocher Riviere-Du-Loup QC G5R 1J8",
    "addr:housenumber":"67",
    "addr:postcode":"g5r 1j8",
    "addr:street":"Rue Du Rocher Riviere-Du-Loup",
    "iso:country":"CA",
    "sg:address":"67 Rue Du Rocher",
    "sg:city":"Riviere-Du-Loup",
    "sg:classifiers":[
        {
            "category":"Education",
            "subcategory":"Library",
            "type":"Public Place"
        }
    ],
    "sg:phone":"+1 418 862 4252",
    "sg:postcode":"G5R 1J8",
    "sg:province":"QC",
    "wof:name":"Bibliotheque Municipale",
    "wof:placetype":"venue"
},
  "geometry": {"coordinates":[-69.53626300000001,47.837563],"type":"Point"}
}