{
  "type": "Feature",
  "properties": {
    "addr:full":"613 143 Rte S Windsor QC J1S 2X2",
    "addr:housenumber":"143",
    "addr:postcode":"j1s 2x2",
    "addr:street":"Rte S",
    "iso:country":"CA",
    "sg:address":"613 143 Rte S",
    "sg:city":"Windsor",
    "sg:classifiers":[
        {
            "category":"Home & Garden",
            "subcategory":"Building Materials",
            "type":"Retail Goods"
        }
    ],
    "sg:phone":"+1 819 845 4778",
    "sg:postcode":"J1S 2X2",
    "sg:province":"QC",
    "sg:tags":[
        "paint"
    ],
    "wof:name":"Peinture A-1 Premier Prix",
    "wof:placetype":"venue"
},
  "geometry": {"coordinates":[-72.0065,45.569019],"type":"Point"}
}