{
  "type": "Feature",
  "properties": {
    "iso:country":"CA",
    "sg:address":"5812 Highway 2A",
    "sg:city":"Lacombe",
    "sg:classifiers":[
        {
            "category":"Retail",
            "subcategory":"Auto Repair",
            "type":"Services"
        }
    ],
    "sg:phone":"+1 403 782 6694",
    "sg:postcode":"T4L 2G5",
    "sg:province":"AB",
    "sg:tags":[
        "body",
        "automobile",
        "painting"
    ],
    "wof:name":"Autotech Collision & Frame Ltd",
    "wof:placetype":"venue"
},
  "geometry": {"coordinates":[-113.719139099,52.4723739624],"type":"Point"}
}