{
  "type": "Feature",
  "properties": {
    "addr:full":"85 Main St Stephenville NL A2N 1H9",
    "addr:housenumber":"85",
    "addr:postcode":"a2n 1h9",
    "addr:street":"Main St",
    "iso:country":"CA",
    "sg:address":"85 Main St",
    "sg:city":"Stephenville",
    "sg:classifiers":[
        {
            "category":"Manufacturing",
            "subcategory":"Furniture",
            "type":"Manufacturing & Wholesale Goods"
        }
    ],
    "sg:phone":"+1 709 643 5791",
    "sg:postcode":"A2N 1H9",
    "sg:province":"NL",
    "sg:tags":[
        "supply"
    ],
    "wof:name":"Stephenville Office Supply",
    "wof:placetype":"venue"
},
  "geometry": {"coordinates":[-58.580837,48.548145],"type":"Point"}
}