{
  "type": "Feature",
  "properties": {
    "addr:full":"1175 Stellar Dr Newmarket ON L3Y 7B8",
    "addr:housenumber":"1175",
    "addr:postcode":"l3y 7b8",
    "addr:street":"Stellar Dr",
    "iso:country":"CA",
    "sg:address":"1175 Stellar Dr",
    "sg:city":"Newmarket",
    "sg:classifiers":[
        {
            "category":"Professional",
            "subcategory":"Business Services",
            "type":"Services"
        }
    ],
    "sg:phone":"+1 905 853 0040",
    "sg:postcode":"L3Y 7B8",
    "sg:province":"ON",
    "sg:tags":[
        "water",
        "treatment"
    ],
    "wof:name":"Canadian Water Warehouse",
    "wof:placetype":"venue"
},
  "geometry": {"coordinates":[-79.42948199999999,44.077236],"type":"Point"}
}