{
  "type": "Feature",
  "properties": {
    "addr:full":"Yellowknife NT X1A 3X6",
    "addr:postcode":"x1a 3x6",
    "iso:country":"CA",
    "sg:city":"Yellowknife",
    "sg:classifiers":[
        {
            "category":"Wholesale",
            "subcategory":"Machinery & Supplies",
            "type":"Manufacturing & Wholesale Goods"
        }
    ],
    "sg:phone":"+1 867 920 4175",
    "sg:postcode":"X1A 3X6",
    "sg:province":"NT",
    "sg:tags":[
        "bearing"
    ],
    "wof:name":"Kinecor Inc",
    "wof:placetype":"venue"
},
  "geometry": {"coordinates":[-114.414062,62.464188],"type":"Point"}
}