{
  "type": "Feature",
  "properties": {
    "addr:full":"496 Rue Laviolette Saint-Jerome QC J7Y 2T9",
    "addr:housenumber":"496",
    "addr:postcode":"j7y 2t9",
    "addr:street":"Rue Laviolette",
    "iso:country":"CA",
    "sg:address":"496 Rue Laviolette",
    "sg:city":"Saint-Jerome",
    "sg:classifiers":[
        {
            "category":"Real Estate",
            "subcategory":"Surveying",
            "type":"Services"
        }
    ],
    "sg:phone":"+1 450 436 2888",
    "sg:postcode":"J7Y 2T9",
    "sg:province":"QC",
    "sg:tags":[
        "surveyor"
    ],
    "wof:name":"Richer & Legault",
    "wof:placetype":"venue"
},
  "geometry": {"coordinates":[-74.006889,45.781731],"type":"Point"}
}