{
  "type": "Feature",
  "properties": {
    "addr:full":"52 Scott St W St Catharines ON L2R 1C9",
    "addr:housenumber":"52",
    "addr:postcode":"l2r 1c9",
    "addr:street":"Scott St W",
    "iso:country":"CA",
    "sg:address":"52 Scott St W",
    "sg:city":"St Catharines",
    "sg:classifiers":[
        {
            "category":"Manufacturing",
            "subcategory":"Printing",
            "type":"Manufacturing & Wholesale Goods"
        }
    ],
    "sg:phone":"+1 905 685 5881",
    "sg:postcode":"L2R 1C9",
    "sg:province":"ON",
    "sg:tags":[
        "printer"
    ],
    "wof:name":"J J Lee Printing CO Ltd",
    "wof:placetype":"venue"
},
  "geometry": {"coordinates":[-79.26261901860001,43.1767463684],"type":"Point"}
}