{
  "type": "Feature",
  "properties": {
    "iso:country":"CA",
    "sg:address":"2851 Steeple Hill Cres",
    "sg:city":"Richmond",
    "sg:classifiers":[
        {
            "category":"Retail",
            "subcategory":"Repair Shop",
            "type":"Services"
        }
    ],
    "sg:phone":"+1 613 838 4631",
    "sg:postcode":"K0A 2Z0",
    "sg:province":"ON",
    "sg:tags":[
        "welding"
    ],
    "wof:name":"Mowat Welding",
    "wof:placetype":"venue"
},
  "geometry": {"coordinates":[-75.8365402222,45.1958045959],"type":"Point"}
}