{
  "type": "Feature",
  "properties": {
    "addr:full":"384 Hamilton Rd London ON N5Z 1R5",
    "addr:housenumber":"384",
    "addr:postcode":"n5z 1r5",
    "addr:street":"Hamilton Rd",
    "iso:country":"CA",
    "sg:address":"384 Hamilton Rd",
    "sg:city":"London",
    "sg:classifiers":[
        {
            "category":"Shopping",
            "subcategory":"Bicycles & Sporting Goods",
            "type":"Retail Goods"
        }
    ],
    "sg:phone":"+1 519 672 5487",
    "sg:postcode":"N5Z 1R5",
    "sg:province":"ON",
    "sg:tags":[
        "tackle",
        "fishing"
    ],
    "wof:name":"Jay's Flyshop",
    "wof:placetype":"venue"
},
  "geometry": {"coordinates":[-81.2207946777,42.980846405],"type":"Point"}
}