{
  "type": "Feature",
  "properties": {
    "iso:country":"CA",
    "sg:city":"Perth",
    "sg:classifiers":[
        {
            "category":"Shopping",
            "subcategory":"Computers & Home Electronics",
            "type":"Retail Goods"
        }
    ],
    "sg:phone":"+1 613 264 0777",
    "sg:postcode":"K7H 2M8",
    "sg:province":"ON",
    "sg:tags":[
        "equipment",
        "dealer"
    ],
    "wof:name":"Service Plus",
    "wof:placetype":"venue"
},
  "geometry": {"coordinates":[-76.2535705566,44.9015045166],"type":"Point"}
}