{
  "type": "Feature",
  "properties": {
    "addr:full":"191 Rue Kerouac Coaticook QC J1A 1A2",
    "addr:housenumber":"191",
    "addr:postcode":"j1a 1a2",
    "addr:street":"Rue Kerouac",
    "iso:country":"CA",
    "sg:address":"191 Rue Kerouac",
    "sg:city":"Coaticook",
    "sg:classifiers":[
        {
            "category":"Home & Garden",
            "subcategory":"Building Materials",
            "type":"Retail Goods"
        }
    ],
    "sg:phone":"+1 819 849 2738",
    "sg:postcode":"J1A 1A2",
    "sg:province":"QC",
    "sg:tags":[
        "door"
    ],
    "wof:name":"Marcoux & Frere Enrg",
    "wof:placetype":"venue"
},
  "geometry": {"coordinates":[-71.8062591553,45.1487541199],"type":"Point"}
}