{
  "type": "Feature",
  "properties": {
    "iso:country":"CA",
    "sg:address":"1667 Rue Poirier",
    "sg:city":"Saint-Laurent",
    "sg:classifiers":[
        {
            "category":"Shopping",
            "subcategory":"Pharmacy",
            "type":"Retail Goods"
        }
    ],
    "sg:phone":"+1 514 747 5534",
    "sg:postcode":"H4L 1J2",
    "sg:province":"QC",
    "wof:name":"T T Can Vao Pharmacy",
    "wof:placetype":"venue"
},
  "geometry": {"coordinates":[-73.69735,45.51973],"type":"Point"}
}