{
  "type": "Feature",
  "properties": {
    "addr:full":"3100 Ch Saint-Louis Sainte-Foy QC G1W 1R8",
    "addr:postcode":"3100;g1w 1r8",
    "addr:street":"Ch Saint-Louis",
    "iso:country":"CA",
    "sg:address":"3100 Ch Saint-Louis",
    "sg:city":"Sainte-Foy",
    "sg:classifiers":[
        {
            "category":"Travel",
            "subcategory":"Hotels & Motels",
            "type":"Entertainment"
        }
    ],
    "sg:phone":"+1 418 653 2841",
    "sg:postcode":"G1W 1R8",
    "sg:province":"QC",
    "wof:name":"Hotel Aristocrate Best Western",
    "wof:placetype":"venue"
},
  "geometry": {"coordinates":[-71.29227400000001,46.757149],"type":"Point"}
}