{
  "type": "Feature",
  "properties": {
    "addr:full":"242 Ch Des Patriotes N Mont-Saint-Hilaire QC J3H 3H3",
    "addr:housenumber":"242",
    "addr:postcode":"j3h 3h3",
    "addr:street":"Ch Des Patriotes N Mont-Saint-Hilaire",
    "iso:country":"CA",
    "sg:address":"242 Ch Des Patriotes N",
    "sg:city":"Mont-Saint-Hilaire",
    "sg:classifiers":[
        {
            "category":"Food & Beverages",
            "subcategory":"Groceries & Convenience Stores",
            "type":"Retail Goods"
        }
    ],
    "sg:phone":"+1 450 467 4775",
    "sg:postcode":"J3H 3H3",
    "sg:province":"QC",
    "sg:tags":[
        "grocer"
    ],
    "wof:name":"Marche D'Alimentation Baril",
    "wof:placetype":"venue"
},
  "geometry": {"coordinates":[-73.19533538819999,45.5697937012],"type":"Point"}
}