{
  "type": "Feature",
  "properties": {
    "addr:full":"11 Hillcrest Ave Sackville NB E4L 3X9",
    "addr:housenumber":"11",
    "addr:postcode":"e4l 3x9",
    "addr:street":"Hillcrest Ave",
    "iso:country":"CA",
    "sg:address":"11 Hillcrest Ave",
    "sg:city":"Sackville",
    "sg:classifiers":[
        {
            "category":"Personal",
            "subcategory":"Beauty Salon",
            "type":"Services"
        }
    ],
    "sg:phone":"+1 506 536 1199",
    "sg:postcode":"E4L 3X9",
    "sg:province":"NB",
    "wof:name":"Right Cut",
    "wof:placetype":"venue"
},
  "geometry": {"coordinates":[-64.3761062622,45.8909492493],"type":"Point"}
}