{
  "type": "Feature",
  "properties": {
    "addr:full":"2881 Small St Innisfil ON L9S 1H3",
    "addr:housenumber":"2881",
    "addr:postcode":"l9s 1h3",
    "addr:street":"Small St",
    "iso:country":"CA",
    "sg:address":"2881 Small St",
    "sg:city":"Innisfil",
    "sg:classifiers":[
        {
            "category":"Personal",
            "subcategory":"Beauty Salon",
            "type":"Services"
        }
    ],
    "sg:phone":"+1 705 431 9061",
    "sg:postcode":"L9S 1H3",
    "sg:province":"ON",
    "wof:name":"Cut's & CO",
    "wof:placetype":"venue"
},
  "geometry": {"coordinates":[-79.623245,44.330399],"type":"Point"}
}