{
  "type": "Feature",
  "properties": {
    "iso:country":"CA",
    "sg:city":"Glentworth",
    "sg:classifiers":[
        {
            "category":"Sports & Exercise",
            "subcategory":"Bowling",
            "type":"Entertainment"
        }
    ],
    "sg:phone":"+1 306 266 2148",
    "sg:postcode":"S0H 1V0",
    "sg:province":"SK",
    "sg:tags":[
        "center"
    ],
    "wof:name":"Glentworth Bowling Alley",
    "wof:placetype":"venue"
},
  "geometry": {"coordinates":[-106.680557251,49.4233665466],"type":"Point"}
}