{
  "type": "Feature",
  "properties": {
    "addr:full":"Brampton ON L6T 5K1",
    "addr:postcode":"l6t 5k1",
    "iso:country":"CA",
    "sg:city":"Brampton",
    "sg:classifiers":[
        {
            "category":"Manufacturing",
            "subcategory":"Tools & Machinery",
            "type":"Manufacturing & Wholesale Goods"
        }
    ],
    "sg:phone":"+1 905 793 9184",
    "sg:postcode":"L6T 5K1",
    "sg:province":"ON",
    "sg:tags":[
        "machine",
        "shop"
    ],
    "wof:name":"Alltrim Tool & Die",
    "wof:placetype":"venue"
},
  "geometry": {"coordinates":[-79.67847399999999,43.731045],"type":"Point"}
}