{
  "type": "Feature",
  "properties": {
    "addr:full":"2700 28 Ave Vernon BC V1T 1V7",
    "addr:housenumber":"2700",
    "addr:postcode":"v1t 1v7",
    "addr:street":"28 Ave",
    "iso:country":"CA",
    "sg:address":"2700 28 Ave",
    "sg:city":"Vernon",
    "sg:classifiers":[
        {
            "category":"Education",
            "subcategory":"School",
            "type":"Public Place"
        }
    ],
    "sg:phone":"+1 250 542 4081",
    "sg:postcode":"V1T 1V7",
    "sg:province":"BC",
    "wof:name":"St James Catholic School",
    "wof:placetype":"venue"
},
  "geometry": {"coordinates":[-119.266967773,50.262008667],"type":"Point"}
}