{
  "type": "Feature",
  "properties": {
    "addr:full":"1645 Colborne St Brantford ON N3T 5L4",
    "addr:housenumber":"1645",
    "addr:postcode":"n3t 5l4",
    "addr:street":"Colborne St",
    "iso:country":"CA",
    "sg:address":"1645 Colborne St",
    "sg:city":"Brantford",
    "sg:classifiers":[
        {
            "category":"Travel",
            "subcategory":"Campground",
            "type":"Entertainment"
        }
    ],
    "sg:phone":"+1 519 754 0171",
    "sg:postcode":"N3T 5L4",
    "sg:province":"ON",
    "sg:tags":[
        "camp"
    ],
    "wof:name":"Circle Square Ranch",
    "wof:placetype":"venue"
},
  "geometry": {"coordinates":[-80.24224853520001,43.1401481628],"type":"Point"}
}