{
  "type": "Feature",
  "properties": {
    "addr:full":"58 Hillside Dr East York ON M4K 2M2",
    "addr:housenumber":"58",
    "addr:postcode":"m4k 2m2",
    "addr:street":"Hillside Dr",
    "iso:country":"CA",
    "sg:address":"58 Hillside Dr",
    "sg:city":"East York",
    "sg:classifiers":[
        {
            "category":"Professional",
            "subcategory":"Advertising",
            "type":"Services"
        }
    ],
    "sg:phone":"+1 416 467 1099",
    "sg:postcode":"M4K 2M2",
    "sg:province":"ON",
    "sg:tags":[
        "counselor"
    ],
    "wof:name":"R G Advertising",
    "wof:placetype":"venue"
},
  "geometry": {"coordinates":[-79.356308,43.688599],"type":"Point"}
}