{
  "type": "Feature",
  "properties": {
    "addr:full":"706 17 Ave SW Calgary AB T2S 0B7",
    "addr:postcode":"t2s 0b7",
    "addr:street":"706 17 Ave Sw",
    "iso:country":"CA",
    "sg:address":"706 17 Ave SW",
    "sg:city":"Calgary",
    "sg:classifiers":[
        {
            "category":"Cinema",
            "subcategory":"Movie Rental",
            "type":"Entertainment"
        }
    ],
    "sg:phone":"+1 403 229 2277",
    "sg:postcode":"T2S 0B7",
    "sg:province":"AB",
    "sg:tags":[
        "player",
        "recorder",
        "video",
        "leasing",
        "tape"
    ],
    "wof:name":"Blockbuster Video",
    "wof:placetype":"venue"
},
  "geometry": {"coordinates":[-114.07733917199999,51.0379524231],"type":"Point"}
}