{
  "type": "Feature",
  "properties": {
    "addr:full":"1440 Rue Sainte-Catherine O Montreal QC H3G 1R8",
    "addr:housenumber":"1440",
    "addr:postcode":"h3g 1r8",
    "addr:street":"Rue Sainte-Catherine O",
    "iso:country":"CA",
    "sg:address":"1440 Rue Sainte-Catherine O",
    "sg:city":"Montreal",
    "sg:classifiers":[
        {
            "category":"Professional",
            "subcategory":"Business Services",
            "type":"Services"
        }
    ],
    "sg:phone":"+1 514 333 7473",
    "sg:postcode":"H3G 1R8",
    "sg:province":"QC",
    "sg:tags":[
        "telemarketing"
    ],
    "wof:name":"Strategic Marketing",
    "wof:placetype":"venue"
},
  "geometry": {"coordinates":[-73.5539093018,45.5206298828],"type":"Point"}
}