{
  "type": "Feature",
  "properties": {
    "addr:full":"1878 Torbrook Rd Wilmot Station NS B0P 1W0",
    "addr:housenumber":"1878",
    "addr:postcode":"b0p 1w0",
    "addr:street":"Torbrook Rd",
    "iso:country":"CA",
    "sg:address":"1878 Torbrook Rd",
    "sg:city":"Wilmot Station",
    "sg:classifiers":[
        {
            "category":"Retail",
            "subcategory":"Auto Repair",
            "type":"Services"
        }
    ],
    "sg:phone":"+1 902 765 8161",
    "sg:postcode":"B0P 1W0",
    "sg:province":"NS",
    "sg:tags":[
        "body",
        "automobile",
        "painting"
    ],
    "wof:name":"Dave's Collision Works",
    "wof:placetype":"venue"
},
  "geometry": {"coordinates":[-65.063171,44.975368],"type":"Point"}
}