{
  "type": "Feature",
  "properties": {
    "addr:full":"Osoyoos BC V0H 1V0",
    "addr:postcode":"v0h 1v0",
    "iso:country":"CA",
    "sg:city":"Osoyoos",
    "sg:classifiers":[
        {
            "category":"Retail",
            "subcategory":"Funeral Services",
            "type":"Services"
        }
    ],
    "sg:phone":"+1 250 495 7903",
    "sg:postcode":"V0H 1V0",
    "sg:province":"BC",
    "sg:tags":[
        "director"
    ],
    "wof:name":"Graham Funeral Home Ltd",
    "wof:placetype":"venue"
},
  "geometry": {"coordinates":[-119.46350099999999,49.031406],"type":"Point"}
}