{
  "type": "Feature",
  "properties": {
    "addr:full":"6908 Island Hwy N # 1 Nanaimo BC V9V 1P6",
    "addr:housenumber":"6908",
    "addr:postcode":"v9v 1p6",
    "addr:street":"Island Hwy N # 1",
    "iso:country":"CA",
    "sg:address":"6908 Island Hwy N # 1",
    "sg:city":"Nanaimo",
    "sg:classifiers":[
        {
            "category":"Banks & Credit Unions",
            "subcategory":"Bank",
            "type":"Services"
        }
    ],
    "sg:phone":"+1 250 390 5086",
    "sg:postcode":"V9V 1P6",
    "sg:province":"BC",
    "wof:name":"Bank of Montreal",
    "wof:placetype":"venue"
},
  "geometry": {"coordinates":[-124.05178832999999,49.2397232056],"type":"Point"}
}