{
  "type": "Feature",
  "properties": {
    "addr:full":"637 Rte Des Campagnards Val-Senneville QC J0Y 2P0",
    "addr:housenumber":"637",
    "addr:postcode":"j0y 2p0",
    "addr:street":"Rte Des Campagnards",
    "iso:country":"CA",
    "sg:address":"637 Rte Des Campagnards",
    "sg:city":"Val-Senneville",
    "sg:classifiers":[
        {
            "category":"Restaurant",
            "type":"Food & Drink"
        }
    ],
    "sg:phone":"+1 819 874 4822",
    "sg:postcode":"J0Y 2P0",
    "sg:province":"QC",
    "wof:name":"Bar Casse-Croute Le Villageois",
    "wof:placetype":"venue"
},
  "geometry": {"coordinates":[-77.655914,48.180935],"type":"Point"}
}