{
  "type": "Feature",
  "properties": {
    "addr:full":"North York ON M3J 2V5",
    "addr:postcode":"m3j 2v5",
    "iso:country":"CA",
    "sg:city":"North York",
    "sg:classifiers":[
        {
            "category":"Professional",
            "subcategory":"Lawyer & Legal Services",
            "type":"Services"
        }
    ],
    "sg:phone":"+1 416 630 1801",
    "sg:postcode":"M3J 2V5",
    "sg:province":"ON",
    "sg:tags":[
        "attorney"
    ],
    "wof:name":"Woolfson & Woolfson",
    "wof:placetype":"venue"
},
  "geometry": {"coordinates":[-79.470619,43.768173],"type":"Point"}
}