{
  "type": "Feature",
  "properties": {
    "addr:full":"4008 Pleasant Valley Rd Vernon BC V1T 4M2",
    "addr:housenumber":"4008",
    "addr:postcode":"v1t 4m2",
    "addr:street":"Pleasant Valley Rd",
    "iso:country":"CA",
    "sg:address":"4008 Pleasant Valley Rd",
    "sg:city":"Vernon",
    "sg:classifiers":[
        {
            "category":"Travel",
            "subcategory":"Hotels & Motels",
            "type":"Entertainment"
        }
    ],
    "sg:phone":"+1 250 549 1767",
    "sg:postcode":"V1T 4M2",
    "sg:province":"BC",
    "sg:tags":[
        "breakfast",
        "accommodation",
        "bed"
    ],
    "wof:name":"Richmond House",
    "wof:placetype":"venue"
},
  "geometry": {"coordinates":[-119.256653,50.271523],"type":"Point"}
}