{
  "type": "Feature",
  "properties": {
    "addr:full":"Edmonton AB T6K 4B2",
    "addr:postcode":"t6k 4b2",
    "iso:country":"CA",
    "sg:city":"Edmonton",
    "sg:classifiers":[
        {
            "category":"Health Services",
            "subcategory":"Medical Lab",
            "type":"Services"
        }
    ],
    "sg:phone":"+1 780 461 1399",
    "sg:postcode":"T6K 4B2",
    "sg:province":"AB",
    "sg:tags":[
        "laboratory"
    ],
    "wof:name":"Dynacare Kasper Medical Lab",
    "wof:placetype":"venue"
},
  "geometry": {"coordinates":[-113.43398999999999,53.461136],"type":"Point"}
}