{
  "type": "Feature",
  "properties": {
    "addr:full":"6197 Decker Dr London ON N6P 1J6",
    "addr:housenumber":"6197",
    "addr:postcode":"n6p 1j6",
    "addr:street":"Decker Dr",
    "iso:country":"CA",
    "sg:address":"6197 Decker Dr",
    "sg:city":"London",
    "sg:classifiers":[
        {
            "category":"Retail",
            "subcategory":"Veterinary Services",
            "type":"Services"
        }
    ],
    "sg:phone":"+1 519 652 5412",
    "sg:postcode":"N6P 1J6",
    "sg:province":"ON",
    "sg:tags":[
        "veterinarian"
    ],
    "wof:name":"Ilderton Equine Clinic",
    "wof:placetype":"venue"
},
  "geometry": {"coordinates":[-81.266655,42.878109],"type":"Point"}
}