{
  "type": "Feature",
  "properties": {
    "addr:full":"138 Highway 8 Stoney Creek ON L8G 1C2",
    "addr:housenumber":"138",
    "addr:postcode":"l8g 1c2",
    "addr:street":"Highway 8",
    "iso:country":"CA",
    "sg:address":"138 Highway 8",
    "sg:city":"Stoney Creek",
    "sg:classifiers":[
        {
            "category":"Personal",
            "subcategory":"Beauty Salon",
            "type":"Services"
        }
    ],
    "sg:phone":"+1 905 662 8711",
    "sg:postcode":"L8G 1C2",
    "sg:province":"ON",
    "wof:name":"Vero Salon Ctr",
    "wof:placetype":"venue"
},
  "geometry": {"coordinates":[-79.68988,43.212067],"type":"Point"}
}