{
  "type": "Feature",
  "properties": {
    "addr:full":"Saint-Benoit-Labre QC G0M 1P0",
    "addr:postcode":"g0m 1p0",
    "iso:country":"CA",
    "sg:city":"Saint-Benoit-Labre",
    "sg:classifiers":[
        {
            "category":"Wholesale",
            "subcategory":"Machinery & Supplies",
            "type":"Manufacturing & Wholesale Goods"
        }
    ],
    "sg:phone":"+1 418 228 1449",
    "sg:postcode":"G0M 1P0",
    "sg:province":"QC",
    "sg:tags":[
        "engine"
    ],
    "wof:name":"Garage Donald Boucher",
    "wof:placetype":"venue"
},
  "geometry": {"coordinates":[-70.79961400000001,46.082489],"type":"Point"}
}