{
  "type": "Feature",
  "properties": {
    "addr:full":"Richmond BC V7C 4N1",
    "addr:postcode":"v7c 4n1",
    "iso:country":"CA",
    "sg:city":"Richmond",
    "sg:classifiers":[
        {
            "category":"Restaurant",
            "type":"Food & Drink"
        }
    ],
    "sg:phone":"+1 604 276 0666",
    "sg:postcode":"V7C 4N1",
    "sg:province":"BC",
    "sg:tags":[
        "caterer"
    ],
    "wof:name":"Ifsco Canada Catering Ltd",
    "wof:placetype":"venue"
},
  "geometry": {"coordinates":[-123.150634766,49.1725349426],"type":"Point"}
}