{
  "type": "Feature",
  "properties": {
    "addr:full":"Toronto ON M5J 1A7",
    "addr:postcode":"m5j 1a7",
    "iso:country":"CA",
    "sg:city":"Toronto",
    "sg:classifiers":[
        {
            "category":"Shopping",
            "type":"Retail Goods"
        }
    ],
    "sg:phone":"+1 416 603 7591",
    "sg:postcode":"M5J 1A7",
    "sg:province":"ON",
    "sg:tags":[
        "art",
        "gallery",
        "dealer"
    ],
    "wof:name":"Harris Gallery Fine Inuit Art",
    "wof:placetype":"venue"
},
  "geometry": {"coordinates":[-79.380669,43.639614],"type":"Point"}
}