{
  "type": "Feature",
  "properties": {
    "addr:full":"323 Boul Henri-Bourassa O Montreal QC H3L 1N8",
    "addr:housenumber":"323",
    "addr:postcode":"h3l 1n8",
    "addr:street":"Boul Henri-Bourassa O",
    "iso:country":"CA",
    "sg:address":"323 Boul Henri-Bourassa O",
    "sg:city":"Montreal",
    "sg:classifiers":[
        {
            "category":"Travel",
            "subcategory":"Travel Agent",
            "type":"Entertainment"
        }
    ],
    "sg:phone":"+1 514 337 3727",
    "sg:postcode":"H3L 1N8",
    "sg:province":"QC",
    "sg:tags":[
        "agency",
        "bureau"
    ],
    "wof:name":"Navigair Inc",
    "wof:placetype":"venue"
},
  "geometry": {"coordinates":[-73.669579,45.553257],"type":"Point"}
}