{
  "type": "Feature",
  "properties": {
    "addr:full":"Vancouver BC V6M 1Y9",
    "addr:postcode":"v6m 1y9",
    "iso:country":"CA",
    "sg:city":"Vancouver",
    "sg:classifiers":[
        {
            "category":"Personal",
            "type":"Services"
        }
    ],
    "sg:phone":"+1 604 261 1590",
    "sg:postcode":"V6M 1Y9",
    "sg:province":"BC",
    "sg:tags":[
        "therapist",
        "massage"
    ],
    "wof:name":"David Arscott Massage Therapy",
    "wof:placetype":"venue"
},
  "geometry": {"coordinates":[-123.15458700000001,49.234402],"type":"Point"}
}