{
  "type": "Feature",
  "properties": {
    "addr:full":"3 Cartier Terrace Bay ON P0T 2W0",
    "addr:housenumber":"3",
    "addr:postcode":"p0t 2w0",
    "addr:street":"Cartier",
    "iso:country":"CA",
    "sg:address":"3 Cartier",
    "sg:city":"Terrace Bay",
    "sg:classifiers":[
        {
            "category":"Health Services",
            "subcategory":"Health Practitioner",
            "type":"Services"
        }
    ],
    "sg:phone":"+1 807 825 1418",
    "sg:postcode":"P0T 2W0",
    "sg:province":"ON",
    "sg:tags":[
        "nurse",
        "registry"
    ],
    "wof:name":"Victorian Order of Nurses",
    "wof:placetype":"venue"
},
  "geometry": {"coordinates":[-87.10424041749999,48.7809371948],"type":"Point"}
}