{
  "type": "Feature",
  "properties": {
    "addr:full":"1120 Centre St NE Calgary AB T2E 2R2",
    "addr:housenumber":"1120",
    "addr:postcode":"t2e 2r2",
    "addr:street":"Centre St Ne",
    "iso:country":"CA",
    "sg:address":"1120 Centre St NE",
    "sg:city":"Calgary",
    "sg:classifiers":[
        {
            "category":"Restaurant",
            "type":"Food & Drink"
        }
    ],
    "sg:phone":"+1 403 277 6171",
    "sg:postcode":"T2E 2R2",
    "sg:province":"AB",
    "wof:name":"Imperial Palace Restaurant",
    "wof:placetype":"venue"
},
  "geometry": {"coordinates":[-114.037346,51.052513],"type":"Point"}
}