{
  "type": "Feature",
  "properties": {
    "addr:full":"89 Skymark Dr North York ON M2H 3S6",
    "addr:housenumber":"89",
    "addr:postcode":"m2h 3s6",
    "addr:street":"Skymark Dr",
    "iso:country":"CA",
    "sg:address":"89 Skymark Dr",
    "sg:city":"North York",
    "sg:classifiers":[
        {
            "category":"Shopping",
            "type":"Retail Goods"
        }
    ],
    "sg:phone":"+1 416 492 3706",
    "sg:postcode":"M2H 3S6",
    "sg:province":"ON",
    "sg:tags":[
        "candle"
    ],
    "wof:name":"Apollo Candle Corp",
    "wof:placetype":"venue"
},
  "geometry": {"coordinates":[-79.354378,43.794979],"type":"Point"}
}