{
  "type": "Feature",
  "properties": {
    "addr:full":"1299 Ellesmere Rd Scarborough ON M1P 2Y2",
    "addr:housenumber":"1299",
    "addr:postcode":"m1p 2y2",
    "addr:street":"Ellesmere Rd",
    "iso:country":"CA",
    "sg:address":"1299 Ellesmere Rd",
    "sg:city":"Scarborough",
    "sg:classifiers":[
        {
            "category":"Recreation",
            "type":"Entertainment"
        }
    ],
    "sg:phone":"+1 416 396 4069",
    "sg:postcode":"M1P 2Y2",
    "sg:province":"ON",
    "sg:tags":[
        "government",
        "hall",
        "auditorium"
    ],
    "wof:name":"Birkdale Community Ctr",
    "wof:placetype":"venue"
},
  "geometry": {"coordinates":[-79.26422100000001,43.769325],"type":"Point"}
}