{
  "type": "Feature",
  "properties": {
    "iso:country":"CA",
    "sg:address":"921 Gana Crt",
    "sg:city":"Mississauga",
    "sg:classifiers":[
        {
            "category":"Wholesale",
            "subcategory":"Durable Goods & Equipment",
            "type":"Manufacturing & Wholesale Goods"
        }
    ],
    "sg:phone":"+1 905 564 2255",
    "sg:postcode":"L5S 1N9",
    "sg:province":"ON",
    "sg:tags":[
        "representative",
        "manufacturer"
    ],
    "wof:name":"Pirie Mc Kie & Assoc Inc",
    "wof:placetype":"venue"
},
  "geometry": {"coordinates":[-79.688263,43.665394],"type":"Point"}
}