{
  "type": "Feature",
  "properties": {
    "addr:full":"401 Kent St W Lindsay ON K9V 4Z1",
    "addr:housenumber":"401",
    "addr:postcode":"k9v 4z1",
    "addr:street":"Kent St W",
    "iso:country":"CA",
    "sg:address":"401 Kent St W",
    "sg:city":"Lindsay",
    "sg:classifiers":[
        {
            "category":"Food & Beverages",
            "subcategory":"Specialty",
            "type":"Retail Goods"
        }
    ],
    "sg:phone":"+1 705 878 1530",
    "sg:postcode":"K9V 4Z1",
    "sg:province":"ON",
    "sg:tags":[
        "health",
        "diet"
    ],
    "wof:name":"S & H Health Foods",
    "wof:placetype":"venue"
},
  "geometry": {"coordinates":[-78.759331,44.350052],"type":"Point"}
}