{
  "type": "Feature",
  "properties": {
    "addr:full":"438 Cygnet Dr Enfield NS B2T 1K3",
    "addr:housenumber":"438",
    "addr:postcode":"b2t 1k3",
    "addr:street":"Cygnet Dr",
    "iso:country":"CA",
    "sg:address":"438 Cygnet Dr",
    "sg:city":"Enfield",
    "sg:classifiers":[
        {
            "category":"Airport",
            "type":"Transportation"
        }
    ],
    "sg:phone":"+1 902 873 3543",
    "sg:postcode":"B2T 1K3",
    "sg:province":"NS",
    "sg:tags":[
        "aircraft",
        "maintenance"
    ],
    "wof:name":"Plh Aviation Svc",
    "wof:placetype":"venue"
},
  "geometry": {"coordinates":[-63.5168418884,44.8835868835],"type":"Point"}
}