{
  "type": "Feature",
  "properties": {
    "addr:full":"460 Wismer St Waterloo ON N2K 2K7",
    "addr:housenumber":"460",
    "addr:postcode":"n2k 2k7",
    "addr:street":"Wismer St",
    "iso:country":"CA",
    "sg:address":"460 Wismer St",
    "sg:city":"Waterloo",
    "sg:classifiers":[
        {
            "category":"Wholesale",
            "subcategory":"Meat",
            "type":"Manufacturing & Wholesale Goods"
        }
    ],
    "sg:phone":"+1 519 744 5658",
    "sg:postcode":"N2K 2K7",
    "sg:province":"ON",
    "sg:tags":[
        "product",
        "butchering"
    ],
    "wof:name":"Osogood Meat Products Ltd",
    "wof:placetype":"venue"
},
  "geometry": {"coordinates":[-80.487816,43.497578],"type":"Point"}
}