{
  "type": "Feature",
  "properties": {
    "addr:full":"241 Pictou Rd Truro NS B2N 2S7",
    "addr:housenumber":"241",
    "addr:postcode":"b2n 2s7",
    "addr:street":"Pictou Rd",
    "iso:country":"CA",
    "sg:address":"241 Pictou Rd",
    "sg:city":"Truro",
    "sg:classifiers":[
        {
            "category":"Health Services",
            "subcategory":"Doctor",
            "type":"Services"
        }
    ],
    "sg:phone":"+1 902 895 6300",
    "sg:postcode":"B2N 2S7",
    "sg:province":"NS",
    "sg:tags":[
        "dentist"
    ],
    "wof:name":"Ferguson, Lana DDS",
    "wof:placetype":"venue"
},
  "geometry": {"coordinates":[-63.2890396118,45.3660202026],"type":"Point"}
}