{
  "type": "Feature",
  "properties": {
    "addr:full":"230 Rue Rochette Saint-Pascal QC G0L 3Y0",
    "addr:housenumber":"230",
    "addr:postcode":"g0l 3y0",
    "addr:street":"Rue Rochette",
    "iso:country":"CA",
    "sg:address":"230 Rue Rochette",
    "sg:city":"Saint-Pascal",
    "sg:classifiers":[
        {
            "category":"Real Estate",
            "subcategory":"Real Estate Agent",
            "type":"Services"
        }
    ],
    "sg:phone":"+1 418 492 6343",
    "sg:postcode":"G0L 3Y0",
    "sg:province":"QC",
    "sg:tags":[
        "cooperative"
    ],
    "wof:name":"Centres DE Renovation Dynaco",
    "wof:placetype":"venue"
},
  "geometry": {"coordinates":[-69.819214,47.528622],"type":"Point"}
}