{
  "type": "Feature",
  "properties": {
    "addr:full":"1200 Boul Saint-Luc L'Acadie QC J2Y 1A5",
    "addr:housenumber":"1200",
    "addr:postcode":"j2y 1a5",
    "addr:street":"Boul Saint-Luc",
    "iso:country":"CA",
    "sg:address":"1200 Boul Saint-Luc",
    "sg:city":"L'Acadie",
    "sg:classifiers":[
        {
            "category":"Autos & Motor Vehicles",
            "subcategory":"Recreational Vehicle Sales",
            "type":"Retail Goods"
        }
    ],
    "sg:phone":"+1 450 349 3535",
    "sg:postcode":"J2Y 1A5",
    "sg:province":"QC",
    "wof:name":"Super Marche Du Vr",
    "wof:placetype":"venue"
},
  "geometry": {"coordinates":[-73.372879,45.376907],"type":"Point"}
}