{
  "type": "Feature",
  "properties": {
    "addr:full":"2833 Dufferin St North York ON M6B 3R9",
    "addr:housenumber":"2833",
    "addr:postcode":"m6b 3r9",
    "addr:street":"Dufferin St",
    "iso:country":"CA",
    "sg:address":"2833 Dufferin St",
    "sg:city":"North York",
    "sg:classifiers":[
        {
            "category":"Autos & Motor Vehicles",
            "subcategory":"Auto Supplies",
            "type":"Retail Goods"
        }
    ],
    "sg:phone":"+1 416 783 1225",
    "sg:postcode":"M6B 3R9",
    "sg:province":"ON",
    "sg:tags":[
        "automobile",
        "stereo",
        "radio"
    ],
    "wof:name":"Auto Efx Inc",
    "wof:placetype":"venue"
},
  "geometry": {"coordinates":[-79.45287322999999,43.7060699463],"type":"Point"}
}