{
  "type": "Feature",
  "properties": {
    "addr:full":"6 Rue Du Couvent Saint-Pierre-DE-Broughton QC G0N 1T0",
    "addr:housenumber":"6",
    "addr:postcode":"g0n 1t0",
    "addr:street":"Rue Du Couvent",
    "iso:country":"CA",
    "sg:address":"6 Rue Du Couvent",
    "sg:city":"Saint-Pierre-DE-Broughton",
    "sg:classifiers":[
        {
            "category":"Education",
            "subcategory":"School",
            "type":"Public Place"
        }
    ],
    "sg:phone":"+1 418 424 3450",
    "sg:postcode":"G0N 1T0",
    "sg:province":"QC",
    "wof:name":"Ecole DE LA Pierre-Douce",
    "wof:placetype":"venue"
},
  "geometry": {"coordinates":[-71.206703,46.244602],"type":"Point"}
}