{
  "type": "Feature",
  "properties": {
    "addr:full":"3480 Rue Mctavish Montreal QC H3A 1X9",
    "addr:housenumber":"3480",
    "addr:postcode":"h3a 1x9",
    "addr:street":"Rue Mctavish",
    "iso:country":"CA",
    "sg:address":"3480 Rue Mctavish",
    "sg:city":"Montreal",
    "sg:classifiers":[
        {
            "category":"Travel",
            "subcategory":"Travel Agent",
            "type":"Entertainment"
        }
    ],
    "sg:phone":"+1 514 398 0647",
    "sg:postcode":"H3A 1X9",
    "sg:province":"QC",
    "sg:tags":[
        "agency",
        "bureau"
    ],
    "wof:name":"Voyages Campus",
    "wof:placetype":"venue"
},
  "geometry": {"coordinates":[-73.57777400000001,45.503601],"type":"Point"}
}