{
  "type": "Feature",
  "properties": {
    "addr:full":"4439 Belmont St Hwy 7 Norwood ON K0L 2V0",
    "addr:housenumber":"4439",
    "addr:postcode":"k0l 2v0",
    "addr:street":"Belmont St Hwy 7",
    "iso:country":"CA",
    "sg:address":"4439 Belmont St Hwy 7",
    "sg:city":"Norwood",
    "sg:classifiers":[
        {
            "category":"Manufacturing",
            "subcategory":"Metals",
            "type":"Manufacturing & Wholesale Goods"
        }
    ],
    "sg:phone":"+1 705 639 5925",
    "sg:postcode":"K0L 2V0",
    "sg:province":"ON",
    "sg:tags":[
        "post",
        "fitting",
        "fence"
    ],
    "wof:name":"Lutes Fence City",
    "wof:placetype":"venue"
},
  "geometry": {"coordinates":[-77.979133606,44.3830337524],"type":"Point"}
}