{
  "type": "Feature",
  "properties": {
    "addr:full":"1670 Ross Rd Kelowna BC V1Z 1L9",
    "addr:housenumber":"1670",
    "addr:postcode":"v1z 1l9",
    "addr:street":"Ross Rd",
    "iso:country":"CA",
    "sg:address":"1670 Ross Rd",
    "sg:city":"Kelowna",
    "sg:classifiers":[
        {
            "category":"Organizations",
            "subcategory":"Professional Association",
            "type":"Services"
        }
    ],
    "sg:phone":"+1 250 769 1609",
    "sg:postcode":"V1Z 1L9",
    "sg:province":"BC",
    "sg:tags":[
        "club"
    ],
    "wof:name":"Okanagan Hungarian Society",
    "wof:placetype":"venue"
},
  "geometry": {"coordinates":[-119.584557,49.860962],"type":"Point"}
}