{
  "type": "Feature",
  "properties": {
    "addr:full":"Kitchener ON N2G 1N9",
    "addr:postcode":"n2g 1n9",
    "iso:country":"CA",
    "sg:city":"Kitchener",
    "sg:classifiers":[
        {
            "category":"Health Services",
            "subcategory":"Doctor",
            "type":"Services"
        }
    ],
    "sg:phone":"+1 519 742 6062",
    "sg:postcode":"N2G 1N9",
    "sg:province":"ON",
    "sg:tags":[
        "physician",
        "surgeon"
    ],
    "wof:name":"Fowlis, Ronald A F MD",
    "wof:placetype":"venue"
},
  "geometry": {"coordinates":[-80.5148468018,43.4560852051],"type":"Point"}
}