{
  "type": "Feature",
  "properties": {
    "iso:country":"CA",
    "sg:address":"71 Rue Saint-Eustache",
    "sg:city":"Saint-Eustache",
    "sg:classifiers":[
        {
            "category":"Restaurant",
            "type":"Food & Drink"
        }
    ],
    "sg:phone":"+1 450 473 1515",
    "sg:postcode":"J7R 2L3",
    "sg:province":"QC",
    "wof:name":"Casa Du Gourmet",
    "wof:placetype":"venue"
},
  "geometry": {"coordinates":[-73.8912658691,45.5587272644],"type":"Point"}
}