{
  "type": "Feature",
  "properties": {
    "addr:full":"1355 Artisans Crt Burlington ON L7L 5Y2",
    "addr:housenumber":"1355",
    "addr:postcode":"l7l 5y2",
    "addr:street":"Artisans Crt",
    "iso:country":"CA",
    "sg:address":"1355 Artisans Crt",
    "sg:city":"Burlington",
    "sg:classifiers":[
        {
            "category":"Building & Trades",
            "subcategory":"Construction",
            "type":"Services"
        }
    ],
    "sg:phone":"+1 905 547 5262",
    "sg:postcode":"L7L 5Y2",
    "sg:province":"ON",
    "sg:tags":[
        "siding",
        "contractor"
    ],
    "wof:name":"Desi's Aluminum Ltd",
    "wof:placetype":"venue"
},
  "geometry": {"coordinates":[-79.78430899999999,43.38604],"type":"Point"}
}