{
  "type": "Feature",
  "properties": {
    "addr:full":"Calgary AB T2E 6Y7",
    "addr:postcode":"t2e 6y7",
    "iso:country":"CA",
    "sg:city":"Calgary",
    "sg:classifiers":[
        {
            "category":"Professional",
            "subcategory":"Advertising",
            "type":"Services"
        }
    ],
    "sg:phone":"+1 403 250 6577",
    "sg:postcode":"T2E 6Y7",
    "sg:province":"AB",
    "sg:tags":[
        "transportation"
    ],
    "wof:name":"Pattison Transit Group",
    "wof:placetype":"venue"
},
  "geometry": {"coordinates":[-114.004364014,51.0864753723],"type":"Point"}
}