{
  "type": "Feature",
  "properties": {
    "addr:full":"135 Ch Du Tremblay # K Boucherville QC J4B 7K4",
    "addr:housenumber":"135;# k",
    "addr:postcode":"j4b 7k4",
    "addr:street":"Ch Du Tremblay",
    "iso:country":"CA",
    "sg:address":"135 Ch Du Tremblay # K",
    "sg:city":"Boucherville",
    "sg:classifiers":[
        {
            "category":"Wholesale",
            "subcategory":"Electrical",
            "type":"Manufacturing & Wholesale Goods"
        }
    ],
    "sg:phone":"+1 450 449 1100",
    "sg:postcode":"J4B 7K4",
    "sg:province":"QC",
    "sg:tags":[
        "electric",
        "motor"
    ],
    "wof:name":"Roy Electromecanique Inc",
    "wof:placetype":"venue"
},
  "geometry": {"coordinates":[-73.426903,45.560375],"type":"Point"}
}