{
  "type": "Feature",
  "properties": {
    "addr:full":"404 Roxton Rd Toronto ON M6G 3R2",
    "addr:housenumber":"404",
    "addr:postcode":"m6g 3r2",
    "addr:street":"Roxton Rd",
    "iso:country":"CA",
    "sg:address":"404 Roxton Rd",
    "sg:city":"Toronto",
    "sg:classifiers":[
        {
            "category":"Retail",
            "subcategory":"Auto Repair",
            "type":"Services"
        }
    ],
    "sg:phone":"+1 416 536 1869",
    "sg:postcode":"M6G 3R2",
    "sg:province":"ON",
    "sg:tags":[
        "repairing",
        "automobile",
        "electric"
    ],
    "wof:name":"Mechanical & Electrical Auto",
    "wof:placetype":"venue"
},
  "geometry": {"coordinates":[-79.423119,43.658459],"type":"Point"}
}