{
  "type": "Feature",
  "properties": {
    "addr:full":"PO Box 325 D'Escousse NS B0E 1K0",
    "addr:housenumber":"po",
    "addr:postcode":"b0e 1k0",
    "addr:street":"Box 325",
    "iso:country":"CA",
    "sg:address":"PO Box 325",
    "sg:city":"D'Escousse",
    "sg:classifiers":[
        {
            "category":"Organizations",
            "subcategory":"Professional Association",
            "type":"Services"
        }
    ],
    "sg:phone":"+1 902 226 3463",
    "sg:postcode":"B0E 1K0",
    "sg:province":"NS",
    "sg:tags":[
        "club"
    ],
    "wof:name":"Rocky Bay Athletic Club",
    "wof:placetype":"venue"
},
  "geometry": {"coordinates":[-60.9596710205,45.5859603882],"type":"Point"}
}