{
  "type": "Feature",
  "properties": {
    "iso:country":"CA",
    "sg:city":"New Westminster",
    "sg:classifiers":[
        {
            "category":"Health Services",
            "subcategory":"Doctor",
            "type":"Services"
        }
    ],
    "sg:phone":"+1 604 522 6711",
    "sg:postcode":"V3M 1X4",
    "sg:province":"BC",
    "sg:tags":[
        "physician",
        "surgeon"
    ],
    "wof:name":"Chan, Edward MD",
    "wof:placetype":"venue"
},
  "geometry": {"coordinates":[-122.919113,49.211571],"type":"Point"}
}