{
  "type": "Feature",
  "properties": {
    "iso:country":"CA",
    "sg:address":"48 Rue Allen E",
    "sg:city":"Waterloo",
    "sg:classifiers":[
        {
            "category":"Building & Trades",
            "subcategory":"Construction",
            "type":"Services"
        }
    ],
    "sg:phone":"+1 450 539 1945",
    "sg:postcode":"J0E 2N0",
    "sg:province":"QC",
    "sg:tags":[
        "material",
        "general",
        "contractor"
    ],
    "wof:name":"Materiaux DE Construction Adam",
    "wof:placetype":"venue"
},
  "geometry": {"coordinates":[-72.5117340088,45.3505134583],"type":"Point"}
}