{
  "type": "Feature",
  "properties": {
    "addr:full":"11845 34 St NW Edmonton AB T5W 4Y2",
    "addr:housenumber":"11845",
    "addr:postcode":"t5w 4y2",
    "addr:street":"34 St Nw",
    "iso:country":"CA",
    "sg:address":"11845 34 St NW",
    "sg:city":"Edmonton",
    "sg:classifiers":[
        {
            "category":"Food & Beverages",
            "subcategory":"Liquor & Beverages",
            "type":"Retail Goods"
        }
    ],
    "sg:phone":"+1 780 477 6918",
    "sg:postcode":"T5W 4Y2",
    "sg:province":"AB",
    "sg:tags":[
        "store"
    ],
    "wof:name":"Beverly Hills Liquor Store",
    "wof:placetype":"venue"
},
  "geometry": {"coordinates":[-113.39358520499999,53.5715103149],"type":"Point"}
}