{
  "type": "Feature",
  "properties": {
    "addr:full":"24 Station Rd Thompson MB R8N 0N4",
    "addr:housenumber":"24",
    "addr:postcode":"r8n 0n4",
    "addr:street":"Station Rd",
    "iso:country":"CA",
    "sg:address":"24 Station Rd",
    "sg:city":"Thompson",
    "sg:classifiers":[
        {
            "category":"Autos & Motor Vehicles",
            "subcategory":"Boat Sales",
            "type":"Retail Goods"
        }
    ],
    "sg:phone":"+1 204 677 2952",
    "sg:postcode":"R8N 0N4",
    "sg:province":"MB",
    "sg:tags":[
        "dealer"
    ],
    "wof:name":"Rick's Marine",
    "wof:placetype":"venue"
},
  "geometry": {"coordinates":[-97.8470458984,55.7417831421],"type":"Point"}
}