{
  "type": "Feature",
  "properties": {
    "addr:full":"10404 176 St NW Edmonton AB T5S 1L3",
    "addr:housenumber":"10404",
    "addr:postcode":"t5s 1l3",
    "addr:street":"176 St Nw",
    "iso:country":"CA",
    "sg:address":"10404 176 St NW",
    "sg:city":"Edmonton",
    "sg:classifiers":[
        {
            "category":"Manufacturing",
            "subcategory":"Metals",
            "type":"Manufacturing & Wholesale Goods"
        }
    ],
    "sg:phone":"+1 780 451 5482",
    "sg:postcode":"T5S 1L3",
    "sg:province":"AB",
    "sg:tags":[
        "forming",
        "fabricator"
    ],
    "wof:name":"Lenmak Exterior Innovations",
    "wof:placetype":"venue"
},
  "geometry": {"coordinates":[-113.624130249,53.5470085144],"type":"Point"}
}