{
  "type": "Feature",
  "properties": {
    "addr:full":"543 Front St Quesnel BC V2J 2K7",
    "addr:housenumber":"543",
    "addr:postcode":"v2j 2k7",
    "addr:street":"Front St",
    "iso:country":"CA",
    "sg:address":"543 Front St",
    "sg:city":"Quesnel",
    "sg:classifiers":[
        {
            "category":"Social Services",
            "type":"Services"
        }
    ],
    "sg:phone":"+1 250 992 9414",
    "sg:postcode":"V2J 2K7",
    "sg:province":"BC",
    "sg:tags":[
        "crisis",
        "center"
    ],
    "wof:name":"Crisis Line",
    "wof:placetype":"venue"
},
  "geometry": {"coordinates":[-122.49895477299999,52.9812355042],"type":"Point"}
}