{
  "type": "Feature",
  "properties": {
    "addr:full":"Rimouski QC G5L 8R3",
    "addr:postcode":"g5l 8r3",
    "iso:country":"CA",
    "sg:city":"Rimouski",
    "sg:classifiers":[
        {
            "category":"Professional",
            "subcategory":"Management & Consulting",
            "type":"Services"
        }
    ],
    "sg:phone":"+1 418 723 3366",
    "sg:postcode":"G5L 8R3",
    "sg:province":"QC",
    "sg:tags":[
        "marketing",
        "consultant"
    ],
    "wof:name":"Ddm Marketing",
    "wof:placetype":"venue"
},
  "geometry": {"coordinates":[-68.5129318237,48.4337310791],"type":"Point"}
}