{
  "type": "Feature",
  "properties": {
    "addr:full":"1040 Rang Saint-Pierre Herouxville QC G0X 1J0",
    "addr:housenumber":"1040",
    "addr:postcode":"g0x 1j0",
    "addr:street":"Rang Saint-Pierre Herouxville",
    "iso:country":"CA",
    "sg:address":"1040 Rang Saint-Pierre",
    "sg:city":"Herouxville",
    "sg:classifiers":[
        {
            "category":"Organizations",
            "subcategory":"Community Association",
            "type":"Services"
        }
    ],
    "sg:phone":"+1 418 365 3820",
    "sg:postcode":"G0X 1J0",
    "sg:province":"QC",
    "sg:tags":[
        "club"
    ],
    "wof:name":"Salle DE L'Age D'Or",
    "wof:placetype":"venue"
},
  "geometry": {"coordinates":[-72.6126937866,46.6732063293],"type":"Point"}
}