{
  "type": "Feature",
  "properties": {
    "addr:full":"3039 Howard Ave Windsor ON N8X 3Y9",
    "addr:housenumber":"3039",
    "addr:postcode":"n8x 3y9",
    "addr:street":"Howard Ave",
    "iso:country":"CA",
    "sg:address":"3039 Howard Ave",
    "sg:city":"Windsor",
    "sg:classifiers":[
        {
            "category":"Shopping",
            "subcategory":"Hobbies, Toys, & Games",
            "type":"Retail Goods"
        }
    ],
    "sg:phone":"+1 519 972 8697",
    "sg:postcode":"N8X 3Y9",
    "sg:province":"ON",
    "wof:name":"Toys R US",
    "wof:placetype":"venue"
},
  "geometry": {"coordinates":[-83.006035,42.27504],"type":"Point"}
}