{
  "type": "Feature",
  "properties": {
    "iso:country":"CA",
    "sg:city":"Falher",
    "sg:classifiers":[
        {
            "category":"Retail",
            "subcategory":"Repair Shop",
            "type":"Services"
        }
    ],
    "sg:phone":"+1 780 837 2783",
    "sg:postcode":"T0H 1M0",
    "sg:province":"AB",
    "sg:tags":[
        "lock",
        "locksmith"
    ],
    "wof:name":"Falher Glass & Locksmith",
    "wof:placetype":"venue"
},
  "geometry": {"coordinates":[-117.20516204800001,55.7362976074],"type":"Point"}
}