{
  "type": "Feature",
  "properties": {
    "addr:full":"5058 Aa Mcdonald Hwy Montague PE C0A 1R0",
    "addr:postcode":"5058 aa;c0a 1r0",
    "addr:street":"Mcdonald Hwy",
    "iso:country":"CA",
    "sg:address":"5058 Aa Mcdonald Hwy",
    "sg:city":"Montague",
    "sg:classifiers":[
        {
            "category":"Freight",
            "type":"Transportation"
        }
    ],
    "sg:phone":"+1 902 838 5499",
    "sg:postcode":"C0A 1R0",
    "sg:province":"PE",
    "sg:tags":[
        "commercial",
        "storage"
    ],
    "wof:name":"Brudenell Self Storage",
    "wof:placetype":"venue"
},
  "geometry": {"coordinates":[-62.649719,46.167164],"type":"Point"}
}