{
  "type": "Feature",
  "properties": {
    "addr:full":"827 Denman St Vancouver BC V6G 2L7",
    "addr:housenumber":"827",
    "addr:postcode":"v6g 2l7",
    "addr:street":"Denman St",
    "iso:country":"CA",
    "sg:address":"827 Denman St",
    "sg:city":"Vancouver",
    "sg:classifiers":[
        {
            "category":"Restaurant",
            "type":"Food & Drink"
        }
    ],
    "sg:phone":"+1 604 683 7236",
    "sg:postcode":"V6G 2L7",
    "sg:province":"BC",
    "wof:name":"Poncho's Mexican Restaurant",
    "wof:placetype":"venue"
},
  "geometry": {"coordinates":[-123.136375,49.291077],"type":"Point"}
}