{
  "type": "Feature",
  "properties": {
    "addr:full":"Corner Brook NL A2H 2Y6",
    "addr:postcode":"a2h 2y6",
    "iso:country":"CA",
    "sg:city":"Corner Brook",
    "sg:classifiers":[
        {
            "category":"Professional",
            "subcategory":"Lawyer & Legal Services",
            "type":"Services"
        }
    ],
    "sg:phone":"+1 709 634 8700",
    "sg:postcode":"A2H 2Y6",
    "sg:province":"NL",
    "sg:tags":[
        "attorney"
    ],
    "wof:name":"Sweetland & Burridge",
    "wof:placetype":"venue"
},
  "geometry": {"coordinates":[-57.93977,48.950703],"type":"Point"}
}