{
  "type": "Feature",
  "properties": {
    "addr:full":"3319 North Service Rd Vineland Station ON L0R 2E0",
    "addr:housenumber":"3319",
    "addr:postcode":"l0r 2e0",
    "addr:street":"North Service Rd",
    "iso:country":"CA",
    "sg:address":"3319 North Service Rd",
    "sg:city":"Vineland Station",
    "sg:classifiers":[
        {
            "category":"Shopping",
            "type":"Retail Goods"
        }
    ],
    "sg:phone":"+1 905 562 0005",
    "sg:postcode":"L0R 2E0",
    "sg:province":"ON",
    "sg:tags":[
        "factory",
        "outlet"
    ],
    "wof:name":"Prudhommes Factory Outlet",
    "wof:placetype":"venue"
},
  "geometry": {"coordinates":[-79.392014,43.168785],"type":"Point"}
}