{
  "type": "Feature",
  "properties": {
    "addr:full":"112 Springbank Ave Woodstock ON N4S 7P8",
    "addr:housenumber":"112",
    "addr:postcode":"n4s 7p8",
    "addr:street":"Springbank Ave",
    "iso:country":"CA",
    "sg:address":"112 Springbank Ave",
    "sg:city":"Woodstock",
    "sg:classifiers":[
        {
            "category":"Banks & Credit Unions",
            "subcategory":"Investment Brokerage",
            "type":"Services"
        }
    ],
    "sg:phone":"+1 519 421 3629",
    "sg:postcode":"N4S 7P8",
    "sg:province":"ON",
    "sg:tags":[
        "consultant",
        "planning",
        "financial"
    ],
    "wof:name":"Investment Planning Counsel",
    "wof:placetype":"venue"
},
  "geometry": {"coordinates":[-80.730003,43.138226],"type":"Point"}
}