{
  "type": "Feature",
  "properties": {
    "addr:full":"294 Eglinton Ave W Toronto ON M4R 1B2",
    "addr:housenumber":"294",
    "addr:postcode":"m4r 1b2",
    "addr:street":"Eglinton Ave W",
    "iso:country":"CA",
    "sg:address":"294 Eglinton Ave W",
    "sg:city":"Toronto",
    "sg:classifiers":[
        {
            "category":"Home & Garden",
            "subcategory":"Furniture",
            "type":"Retail Goods"
        }
    ],
    "sg:phone":"+1 416 489 8863",
    "sg:postcode":"M4R 1B2",
    "sg:province":"ON",
    "sg:tags":[
        "builder",
        "custom"
    ],
    "wof:name":"Room Inc",
    "wof:placetype":"venue"
},
  "geometry": {"coordinates":[-79.40785217289999,43.7049026489],"type":"Point"}
}