{
  "type": "Feature",
  "properties": {
    "addr:full":"12 Cheadle St W # 102 Swift Current SK S9H 0A9",
    "addr:housenumber":"12",
    "addr:postcode":"s9h 0a9",
    "addr:street":"Cheadle St W # 102",
    "iso:country":"CA",
    "sg:address":"12 Cheadle St W # 102",
    "sg:city":"Swift Current",
    "sg:classifiers":[
        {
            "category":"Health Services",
            "subcategory":"Chiropractor",
            "type":"Services"
        }
    ],
    "sg:phone":"+1 306 773 3144",
    "sg:postcode":"S9H 0A9",
    "sg:province":"SK",
    "wof:name":"Chiropractic Clinic",
    "wof:placetype":"venue"
},
  "geometry": {"coordinates":[-107.800179,50.283333],"type":"Point"}
}