{
  "type": "Feature",
  "properties": {
    "iso:country":"CA",
    "sg:address":"3046 Route 117",
    "sg:city":"Pointe-Sapin",
    "sg:classifiers":[
        {
            "category":"Manufacturing",
            "subcategory":"Food",
            "type":"Manufacturing & Wholesale Goods"
        }
    ],
    "sg:phone":"+1 506 876 2873",
    "sg:postcode":"E9A 1V1",
    "sg:province":"NB",
    "sg:tags":[
        "product",
        "seafood",
        "fish",
        "prepared"
    ],
    "wof:name":"Crown Seafood Ltd",
    "wof:placetype":"venue"
},
  "geometry": {"coordinates":[-64.8468704224,46.9554290771],"type":"Point"}
}