{
  "type": "Feature",
  "properties": {
    "iso:country":"CA",
    "sg:address":"155 North Front St",
    "sg:city":"Belleville",
    "sg:classifiers":[
        {
            "category":"Building & Trades",
            "subcategory":"Electrical",
            "type":"Services"
        }
    ],
    "sg:phone":"+1 613 968 2756",
    "sg:postcode":"K8P 3B7",
    "sg:province":"ON",
    "sg:tags":[
        "electric",
        "contractor"
    ],
    "wof:name":"Digital Electric Inc",
    "wof:placetype":"venue"
},
  "geometry": {"coordinates":[-77.390625,44.1770172119],"type":"Point"}
}