{
  "type": "Feature",
  "properties": {
    "iso:country":"CA",
    "sg:address":"796 Sargent Ave",
    "sg:city":"Winnipeg",
    "sg:classifiers":[
        {
            "category":"Home & Garden",
            "subcategory":"Household Appliances",
            "type":"Retail Goods"
        }
    ],
    "sg:phone":"+1 204 772 3990",
    "sg:postcode":"R3E 0B8",
    "sg:province":"MB",
    "sg:tags":[
        "cleaners",
        "vacuum"
    ],
    "wof:name":"Pestyk's Vacuum Professionals",
    "wof:placetype":"venue"
},
  "geometry": {"coordinates":[-97.168365,49.896751],"type":"Point"}
}