{
  "type": "Feature",
  "properties": {
    "addr:full":"16947 58 Ave Surrey BC V3S 8P1",
    "addr:housenumber":"16947",
    "addr:postcode":"v3s 8p1",
    "addr:street":"58 Ave",
    "iso:country":"CA",
    "sg:address":"16947 58 Ave",
    "sg:city":"Surrey",
    "sg:classifiers":[
        {
            "category":"Building & Trades",
            "subcategory":"Construction",
            "type":"Services"
        }
    ],
    "sg:phone":"+1 604 574 1747",
    "sg:postcode":"V3S 8P1",
    "sg:province":"BC",
    "sg:tags":[
        "general",
        "drainage",
        "contractor"
    ],
    "wof:name":"R H Contracting Ltd",
    "wof:placetype":"venue"
},
  "geometry": {"coordinates":[-122.753326,49.108002],"type":"Point"}
}