{
  "type": "Feature",
  "properties": {
    "addr:full":"500 Rexdale Blvd # 18 Etobicoke ON M9W 6K5",
    "addr:housenumber":"500",
    "addr:postcode":"m9w 6k5",
    "addr:street":"Rexdale Blvd # 18",
    "iso:country":"CA",
    "sg:address":"500 Rexdale Blvd # 18",
    "sg:city":"Etobicoke",
    "sg:classifiers":[
        {
            "category":"Personal",
            "subcategory":"Beauty Salon",
            "type":"Services"
        }
    ],
    "sg:phone":"+1 416 674 0400",
    "sg:postcode":"M9W 6K5",
    "sg:province":"ON",
    "wof:name":"Ray Daniel Salon & Spa",
    "wof:placetype":"venue"
},
  "geometry": {"coordinates":[-79.597084,43.717823],"type":"Point"}
}