{
  "type": "Feature",
  "properties": {
    "addr:full":"10021 Rue Renaude-Lapointe Anjou QC H1J 2T4",
    "addr:housenumber":"10021",
    "addr:postcode":"h1j 2t4",
    "addr:street":"Rue Renaude-Lapointe",
    "iso:country":"CA",
    "sg:address":"10021 Rue Renaude-Lapointe",
    "sg:city":"Anjou",
    "sg:classifiers":[
        {
            "category":"Manufacturing",
            "subcategory":"Tools & Machinery",
            "type":"Manufacturing & Wholesale Goods"
        }
    ],
    "sg:phone":"+1 514 352 1229",
    "sg:postcode":"H1J 2T4",
    "sg:province":"QC",
    "sg:tags":[
        "electric",
        "motor"
    ],
    "wof:name":"Distributions Mep Inc",
    "wof:placetype":"venue"
},
  "geometry": {"coordinates":[-73.5851593018,45.6101379395],"type":"Point"}
}