{
  "type": "Feature",
  "properties": {
    "addr:full":"120 Lawrence Ave Orangeville ON L9W 1S8",
    "addr:housenumber":"120",
    "addr:postcode":"l9w 1s8",
    "addr:street":"Lawrence Ave",
    "iso:country":"CA",
    "sg:address":"120 Lawrence Ave",
    "sg:city":"Orangeville",
    "sg:classifiers":[
        {
            "category":"Education",
            "subcategory":"School",
            "type":"Public Place"
        }
    ],
    "sg:phone":"+1 519 941 2461",
    "sg:postcode":"L9W 1S8",
    "sg:province":"ON",
    "wof:name":"Parkinson Centennial Public",
    "wof:placetype":"venue"
},
  "geometry": {"coordinates":[-80.102875,43.908619],"type":"Point"}
}