{
  "type": "Feature",
  "properties": {
    "addr:full":"8 Sparklett Cres Brampton ON L6Z 1M8",
    "addr:housenumber":"8",
    "addr:postcode":"l6z 1m8",
    "addr:street":"Sparklett Cres",
    "iso:country":"CA",
    "sg:address":"8 Sparklett Cres",
    "sg:city":"Brampton",
    "sg:classifiers":[
        {
            "category":"Home & Garden",
            "subcategory":"Household Appliances",
            "type":"Retail Goods"
        }
    ],
    "sg:phone":"+1 905 846 9973",
    "sg:postcode":"L6Z 1M8",
    "sg:province":"ON",
    "wof:name":"Altra Appliance Svc",
    "wof:placetype":"venue"
},
  "geometry": {"coordinates":[-79.788651,43.727139],"type":"Point"}
}