{
  "type": "Feature",
  "properties": {
    "addr:full":"88 Harbord St Toronto ON M5S 1G5",
    "addr:housenumber":"88",
    "addr:postcode":"m5s 1g5",
    "addr:street":"Harbord St",
    "iso:country":"CA",
    "sg:address":"88 Harbord St",
    "sg:city":"Toronto",
    "sg:classifiers":[
        {
            "category":"Restaurant",
            "type":"Food & Drink"
        }
    ],
    "sg:phone":"+1 416 929 7788",
    "sg:postcode":"M5S 1G5",
    "sg:province":"ON",
    "wof:name":"Splendido Bar & Grill",
    "wof:placetype":"venue"
},
  "geometry": {"coordinates":[-79.402885,43.663017],"type":"Point"}
}