{
  "type": "Feature",
  "properties": {
    "addr:full":"170 1E Av O Sainte-Anne-Des-Monts QC G4V 1C8",
    "addr:housenumber":"170",
    "addr:postcode":"g4v 1c8",
    "addr:street":"1E Av O",
    "iso:country":"CA",
    "sg:address":"170 1E Av O",
    "sg:city":"Sainte-Anne-Des-Monts",
    "sg:classifiers":[
        {
            "category":"Home & Garden",
            "subcategory":"Hardware",
            "type":"Retail Goods"
        }
    ],
    "sg:phone":"+1 418 763 2345",
    "sg:postcode":"G4V 1C8",
    "sg:province":"QC",
    "wof:name":"J N Keable Inc",
    "wof:placetype":"venue"
},
  "geometry": {"coordinates":[-66.48639678959999,49.1292152405],"type":"Point"}
}