{
  "type": "Feature",
  "properties": {
    "iso:country":"CA",
    "sg:city":"Nanaimo",
    "sg:classifiers":[
        {
            "category":"Shopping",
            "subcategory":"Hobbies, Toys, & Games",
            "type":"Retail Goods"
        }
    ],
    "sg:phone":"+1 250 753 6221",
    "sg:postcode":"V9R 5E2",
    "sg:province":"BC",
    "sg:tags":[
        "model",
        "supply"
    ],
    "wof:name":"Leisure Time Hobbies",
    "wof:placetype":"venue"
},
  "geometry": {"coordinates":[-123.934944153,49.1640930176],"type":"Point"}
}