{
  "type": "Feature",
  "properties": {
    "addr:full":"3 Lindenwood Pl Winnipeg MB R3P 1M3",
    "addr:housenumber":"3",
    "addr:postcode":"r3p 1m3",
    "addr:street":"Lindenwood Pl",
    "iso:country":"CA",
    "sg:address":"3 Lindenwood Pl",
    "sg:city":"Winnipeg",
    "sg:classifiers":[
        {
            "category":"Banks & Credit Unions",
            "subcategory":"Investment Brokerage",
            "type":"Services"
        }
    ],
    "sg:phone":"+1 204 949 1777",
    "sg:postcode":"R3P 1M3",
    "sg:province":"MB",
    "sg:tags":[
        "broker",
        "commodity"
    ],
    "wof:name":"Daex Commodities Inc",
    "wof:placetype":"venue"
},
  "geometry": {"coordinates":[-97.180183,49.838936],"type":"Point"}
}