{
  "type": "Feature",
  "properties": {
    "iso:country":"CA",
    "sg:address":"51 York St",
    "sg:city":"Ottawa",
    "sg:classifiers":[
        {
            "category":"Food & Beverages",
            "subcategory":"Fruits & Vegetables",
            "type":"Retail Goods"
        }
    ],
    "sg:phone":"+1 613 241 4345",
    "sg:postcode":"K1N 9B7",
    "sg:province":"ON",
    "sg:tags":[
        "produce"
    ],
    "wof:name":"Ontario Fruit Dealers Ltd",
    "wof:placetype":"venue"
},
  "geometry": {"coordinates":[-75.692993,45.428177],"type":"Point"}
}