{
  "type": "Feature",
  "properties": {
    "addr:full":"52 Lisa Dr Prince Albert SK S6V 5S5",
    "addr:housenumber":"52",
    "addr:postcode":"s6v 5s5",
    "addr:street":"Lisa Dr",
    "iso:country":"CA",
    "sg:address":"52 Lisa Dr",
    "sg:city":"Prince Albert",
    "sg:classifiers":[
        {
            "category":"Building & Trades",
            "subcategory":"Electrical",
            "type":"Services"
        }
    ],
    "sg:phone":"+1 306 763 4201",
    "sg:postcode":"S6V 5S5",
    "sg:province":"SK",
    "sg:tags":[
        "electric",
        "contractor"
    ],
    "wof:name":"Free-Way Electric Ltd",
    "wof:placetype":"venue"
},
  "geometry": {"coordinates":[-105.752876,53.19944],"type":"Point"}
}