{
  "type": "Feature",
  "properties": {
    "addr:full":"5237 Rue Saint-Denis Montreal QC H2J 2M1",
    "addr:housenumber":"5237",
    "addr:postcode":"h2j 2m1",
    "addr:street":"Rue Saint-Denis",
    "iso:country":"CA",
    "sg:address":"5237 Rue Saint-Denis",
    "sg:city":"Montreal",
    "sg:classifiers":[
        {
            "category":"Restaurant",
            "type":"Food & Drink"
        }
    ],
    "sg:phone":"+1 514 271 2333",
    "sg:postcode":"H2J 2M1",
    "sg:province":"QC",
    "wof:name":"Restaurant Le Bleu Raisin",
    "wof:placetype":"venue"
},
  "geometry": {"coordinates":[-73.59107971189999,45.5278205872],"type":"Point"}
}