{
  "type": "Feature",
  "properties": {
    "addr:full":"609 Hamilton Ave W Melfort SK S0E 1A0",
    "addr:housenumber":"609",
    "addr:postcode":"s0e 1a0",
    "addr:street":"Hamilton Ave W Melfort",
    "iso:country":"CA",
    "sg:address":"609 Hamilton Ave W",
    "sg:city":"Melfort",
    "sg:classifiers":[
        {
            "category":"Wholesale",
            "subcategory":"Scrap",
            "type":"Manufacturing & Wholesale Goods"
        }
    ],
    "sg:phone":"+1 306 752 2531",
    "sg:postcode":"S0E 1A0",
    "sg:province":"SK",
    "sg:tags":[
        "recycling",
        "center"
    ],
    "wof:name":"Sarcan Recycling",
    "wof:placetype":"venue"
},
  "geometry": {"coordinates":[-104.629760742,52.8672904968],"type":"Point"}
}