{
  "type": "Feature",
  "properties": {
    "addr:full":"47 Main St N Rossburn MB R0J 1V0",
    "addr:housenumber":"47",
    "addr:postcode":"r0j 1v0",
    "addr:street":"Main St N Rossburn",
    "iso:country":"CA",
    "sg:address":"47 Main St N",
    "sg:city":"Rossburn",
    "sg:classifiers":[
        {
            "category":"Banks & Credit Unions",
            "subcategory":"Bank",
            "type":"Services"
        }
    ],
    "sg:phone":"+1 204 859 5025",
    "sg:postcode":"R0J 1V0",
    "sg:province":"MB",
    "wof:name":"Vanguard Credit Union Ltd",
    "wof:placetype":"venue"
},
  "geometry": {"coordinates":[-100.810829,50.668968],"type":"Point"}
}