{
  "type": "Feature",
  "properties": {
    "addr:full":"7319 Hwy 23 N Atwood ON N0G 1B0",
    "addr:housenumber":"7319",
    "addr:postcode":"n0g 1b0",
    "addr:street":"Hwy 23 N",
    "iso:country":"CA",
    "sg:address":"7319 Hwy 23 N",
    "sg:city":"Atwood",
    "sg:classifiers":[
        {
            "category":"Manufacturing",
            "subcategory":"Metals",
            "type":"Manufacturing & Wholesale Goods"
        }
    ],
    "sg:phone":"+1 519 356 2802",
    "sg:postcode":"N0G 1B0",
    "sg:province":"ON",
    "sg:tags":[
        "tank"
    ],
    "wof:name":"Smith Steel & Fabrication Inc",
    "wof:placetype":"venue"
},
  "geometry": {"coordinates":[-81.0121002197,43.6767883301],"type":"Point"}
}