{
  "type": "Feature",
  "properties": {
    "addr:full":"6 Sheridan St Brantford ON N3T 2P6",
    "addr:housenumber":"6",
    "addr:postcode":"n3t 2p6",
    "addr:street":"Sheridan St",
    "iso:country":"CA",
    "sg:address":"6 Sheridan St",
    "sg:city":"Brantford",
    "sg:classifiers":[
        {
            "category":"Health Services",
            "subcategory":"Nursing And Care Facility",
            "type":"Services"
        }
    ],
    "sg:phone":"+1 519 759 2070",
    "sg:postcode":"N3T 2P6",
    "sg:province":"ON",
    "sg:tags":[
        "home",
        "retirement",
        "community"
    ],
    "wof:name":"Sheridan Lodge Retirement Home",
    "wof:placetype":"venue"
},
  "geometry": {"coordinates":[-80.266068,43.143932],"type":"Point"}
}