{
  "type": "Feature",
  "properties": {
    "iso:country":"CA",
    "sg:address":"524 Av Crepeau",
    "sg:city":"Mascouche",
    "sg:classifiers":[
        {
            "category":"Health Services",
            "subcategory":"Doctor",
            "type":"Services"
        }
    ],
    "sg:phone":"+1 450 966 9713",
    "sg:postcode":"J7K 3M8",
    "sg:province":"QC",
    "sg:tags":[
        "clinic"
    ],
    "wof:name":"Martigny, Thierry",
    "wof:placetype":"venue"
},
  "geometry": {"coordinates":[-73.60813903810001,45.7311286926],"type":"Point"}
}