{
  "type": "Feature",
  "properties": {
    "iso:country":"CA",
    "sg:address":"2733 Coventry Rd",
    "sg:city":"Oakville",
    "sg:classifiers":[
        {
            "category":"Manufacturing",
            "subcategory":"Food",
            "type":"Manufacturing & Wholesale Goods"
        }
    ],
    "sg:phone":"+1 905 829 2444",
    "sg:postcode":"L6H 5V9",
    "sg:province":"ON",
    "sg:tags":[
        "bakery",
        "prod",
        "product",
        "manufacturer"
    ],
    "wof:name":"Bakery Delite",
    "wof:placetype":"venue"
},
  "geometry": {"coordinates":[-79.682693,43.509197],"type":"Point"}
}