{
  "type": "Feature",
  "properties": {
    "addr:full":"1308 Av Maguire Sillery QC G1T 1Z3",
    "addr:housenumber":"1308",
    "addr:postcode":"g1t 1z3",
    "addr:street":"Av Maguire",
    "iso:country":"CA",
    "sg:address":"1308 Av Maguire",
    "sg:city":"Sillery",
    "sg:classifiers":[
        {
            "category":"Restaurant",
            "type":"Food & Drink"
        }
    ],
    "sg:phone":"+1 418 686 0808",
    "sg:postcode":"G1T 1Z3",
    "sg:province":"QC",
    "wof:name":"Faks Cafe",
    "wof:placetype":"venue"
},
  "geometry": {"coordinates":[-71.251846,46.781471],"type":"Point"}
}