{
  "type": "Feature",
  "properties": {
    "addr:full":"1789 Av Chauveau Quebec QC G2K 1B3",
    "addr:housenumber":"1789",
    "addr:postcode":"g2k 1b3",
    "addr:street":"Av Chauveau",
    "iso:country":"CA",
    "sg:address":"1789 Av Chauveau",
    "sg:city":"Quebec",
    "sg:classifiers":[
        {
            "category":"Building & Trades",
            "subcategory":"Construction",
            "type":"Services"
        }
    ],
    "sg:phone":"+1 418 628 0599",
    "sg:postcode":"G2K 1B3",
    "sg:province":"QC",
    "sg:tags":[
        "contractor"
    ],
    "wof:name":"Trudelle & Bedard Inc",
    "wof:placetype":"venue"
},
  "geometry": {"coordinates":[-71.318855,46.846275],"type":"Point"}
}