{
  "type": "Feature",
  "properties": {
    "iso:country":"CA",
    "sg:city":"Kitchener",
    "sg:classifiers":[
        {
            "category":"Wholesale",
            "subcategory":"Electrical",
            "type":"Manufacturing & Wholesale Goods"
        }
    ],
    "sg:phone":"+1 519 748 5500",
    "sg:postcode":"N2R 1A7",
    "sg:province":"ON",
    "sg:tags":[
        "bearing",
        "electric"
    ],
    "wof:name":"Canadian Bearings Ltd",
    "wof:placetype":"venue"
},
  "geometry": {"coordinates":[-80.471306,43.400547],"type":"Point"}
}