{
  "type": "Feature",
  "properties": {
    "addr:full":"Repentigny QC J6A 3Z3",
    "addr:postcode":"j6a 3z3",
    "iso:country":"CA",
    "sg:city":"Repentigny",
    "sg:classifiers":[
        {
            "category":"Wholesale",
            "subcategory":"Office Equipment",
            "type":"Manufacturing & Wholesale Goods"
        }
    ],
    "sg:phone":"+1 450 654 4994",
    "sg:postcode":"J6A 3Z3",
    "sg:province":"QC",
    "sg:tags":[
        "accounting",
        "bookkeeping",
        "system"
    ],
    "wof:name":"Gagnon, Jerome",
    "wof:placetype":"venue"
},
  "geometry": {"coordinates":[-73.4608535767,45.7311897278],"type":"Point"}
}