{
  "type": "Feature",
  "properties": {
    "iso:country":"CA",
    "sg:address":"551 Machray Ave",
    "sg:city":"Winnipeg",
    "sg:classifiers":[
        {
            "category":"Museum",
            "type":"Entertainment"
        }
    ],
    "sg:phone":"+1 204 586 6298",
    "sg:postcode":"R2W 1A8",
    "sg:province":"MB",
    "wof:name":"Fort Garry Horse Museum",
    "wof:placetype":"venue"
},
  "geometry": {"coordinates":[-97.1399841309,49.9276199341],"type":"Point"}
}