{
  "type": "Feature",
  "properties": {
    "addr:full":"230 Ecclestone Dr Bracebridge ON P1L 1G4",
    "addr:housenumber":"230",
    "addr:postcode":"p1l 1g4",
    "addr:street":"Ecclestone Dr",
    "iso:country":"CA",
    "sg:address":"230 Ecclestone Dr",
    "sg:city":"Bracebridge",
    "sg:classifiers":[
        {
            "category":"Shopping",
            "subcategory":"Bicycles & Sporting Goods",
            "type":"Retail Goods"
        }
    ],
    "sg:phone":"+1 705 645 1166",
    "sg:postcode":"P1L 1G4",
    "sg:province":"ON",
    "wof:name":"Ecclestone Cycle CO",
    "wof:placetype":"venue"
},
  "geometry": {"coordinates":[-79.312759,45.032124],"type":"Point"}
}