{
  "type": "Feature",
  "properties": {
    "addr:full":"3 Sultan St Toronto ON M5S 1L6",
    "addr:housenumber":"3",
    "addr:postcode":"m5s 1l6",
    "addr:street":"Sultan St",
    "iso:country":"CA",
    "sg:address":"3 Sultan St",
    "sg:city":"Toronto",
    "sg:classifiers":[
        {
            "category":"Wholesale",
            "subcategory":"Non-durable Goods",
            "type":"Manufacturing & Wholesale Goods"
        }
    ],
    "sg:phone":"+1 416 924 8220",
    "sg:postcode":"M5S 1L6",
    "sg:province":"ON",
    "sg:tags":[
        "advertising"
    ],
    "wof:name":"Givn'r Promotions Group Inc",
    "wof:placetype":"venue"
},
  "geometry": {"coordinates":[-79.3901596069,43.6686058044],"type":"Point"}
}