{
  "type": "Feature",
  "properties": {
    "addr:full":"27 Rue Marie-DE-L'Incarnation # A Quebec QC G1N 3E5",
    "addr:housenumber":"27",
    "addr:postcode":"g1n 3e5",
    "addr:street":"Rue Marie-De-L'Incarnation # A",
    "iso:country":"CA",
    "sg:address":"27 Rue Marie-DE-L'Incarnation # A",
    "sg:city":"Quebec",
    "sg:classifiers":[
        {
            "category":"Professional",
            "subcategory":"Business Services",
            "type":"Services"
        }
    ],
    "sg:phone":"+1 418 682 0777",
    "sg:postcode":"G1N 3E5",
    "sg:province":"QC",
    "sg:tags":[
        "auctioneer"
    ],
    "wof:name":"Encan FL Inc",
    "wof:placetype":"venue"
},
  "geometry": {"coordinates":[-71.4194717407,46.858581543],"type":"Point"}
}