{
  "type": "Feature",
  "properties": {
    "addr:full":"242 Brooke Ave North York ON M5M 2K8",
    "addr:housenumber":"242",
    "addr:postcode":"m5m 2k8",
    "addr:street":"Brooke Ave",
    "iso:country":"CA",
    "sg:address":"242 Brooke Ave",
    "sg:city":"North York",
    "sg:classifiers":[
        {
            "category":"Shopping",
            "subcategory":"Computers & Home Electronics",
            "type":"Retail Goods"
        }
    ],
    "sg:phone":"+1 416 789 7297",
    "sg:postcode":"M5M 2K8",
    "sg:province":"ON",
    "sg:tags":[
        "radio",
        "television",
        "video",
        "equipment"
    ],
    "wof:name":"Star Tv & Audio Svc Ctr",
    "wof:placetype":"venue"
},
  "geometry": {"coordinates":[-79.41986083979999,43.7332725525],"type":"Point"}
}