{
  "type": "Feature",
  "properties": {
    "addr:full":"554 Sheppard Ave W North York ON M3H 2R9",
    "addr:housenumber":"554",
    "addr:postcode":"m3h 2r9",
    "addr:street":"Sheppard Ave W",
    "iso:country":"CA",
    "sg:address":"554 Sheppard Ave W",
    "sg:city":"North York",
    "sg:classifiers":[
        {
            "category":"Restaurant",
            "type":"Food & Drink"
        }
    ],
    "sg:phone":"+1 416 636 1632",
    "sg:postcode":"M3H 2R9",
    "sg:province":"ON",
    "wof:name":"China Court Restaurant",
    "wof:placetype":"venue"
},
  "geometry": {"coordinates":[-79.437431,43.755726],"type":"Point"}
}