{
  "type": "Feature",
  "properties": {
    "addr:full":"Newmarket ON L3Y 3E3",
    "addr:postcode":"l3y 3e3",
    "iso:country":"CA",
    "sg:city":"Newmarket",
    "sg:classifiers":[
        {
            "category":"Building & Trades",
            "subcategory":"Equipment Rental",
            "type":"Services"
        }
    ],
    "sg:phone":"+1 905 895 9500",
    "sg:postcode":"L3Y 3E3",
    "sg:province":"ON",
    "sg:tags":[
        "yard"
    ],
    "wof:name":"Neighbourhood Rental Ctr",
    "wof:placetype":"venue"
},
  "geometry": {"coordinates":[-79.4329986572,44.0708694458],"type":"Point"}
}