{
  "type": "Feature",
  "properties": {
    "addr:full":"254 10th St Hanover ON N4N 1N9",
    "addr:housenumber":"254",
    "addr:postcode":"n4n 1n9",
    "addr:street":"10Th St",
    "iso:country":"CA",
    "sg:address":"254 10th St",
    "sg:city":"Hanover",
    "sg:classifiers":[
        {
            "category":"Shopping",
            "subcategory":"Gifts & Souvenirs",
            "type":"Retail Goods"
        }
    ],
    "sg:phone":"+1 519 364 4456",
    "sg:postcode":"N4N 1N9",
    "sg:province":"ON",
    "sg:tags":[
        "shop"
    ],
    "wof:name":"Candles Delight",
    "wof:placetype":"venue"
},
  "geometry": {"coordinates":[-81.0294342041,44.1519393921],"type":"Point"}
}