{
  "type": "Feature",
  "properties": {
    "addr:full":"1 Rue LA Plaza-DE-Mauricie Shawinigan QC G9N 7C1",
    "addr:housenumber":"1",
    "addr:postcode":"g9n 7c1",
    "addr:street":"Rue La Plaza-De-Mauricie",
    "iso:country":"CA",
    "sg:address":"1 Rue LA Plaza-DE-Mauricie",
    "sg:city":"Shawinigan",
    "sg:classifiers":[
        {
            "category":"Recreation",
            "type":"Entertainment"
        }
    ],
    "sg:phone":"+1 819 539 1198",
    "sg:postcode":"G9N 7C1",
    "sg:province":"QC",
    "sg:tags":[
        "lottery",
        "agent"
    ],
    "wof:name":"Kiosque Loto-Quebec",
    "wof:placetype":"venue"
},
  "geometry": {"coordinates":[-72.7405014038,46.5639610291],"type":"Point"}
}