{
  "type": "Feature",
  "properties": {
    "iso:country":"CA",
    "sg:address":"42 Falling Brook Dr",
    "sg:city":"Barrie",
    "sg:classifiers":[
        {
            "category":"Shopping",
            "subcategory":"Computers & Home Electronics",
            "type":"Retail Goods"
        }
    ],
    "sg:phone":"+1 705 721 5228",
    "sg:postcode":"L4N 7E9",
    "sg:province":"ON",
    "sg:tags":[
        "equipment",
        "dealer"
    ],
    "wof:name":"D & D Advanced Computing Inc",
    "wof:placetype":"venue"
},
  "geometry": {"coordinates":[-79.63958,44.361988],"type":"Point"}
}