{
  "type": "Feature",
  "properties": {
    "addr:full":"1401 O'Connor Dr East York ON M4B 2V5",
    "addr:housenumber":"1401",
    "addr:postcode":"m4b 2v5",
    "addr:street":"O'Connor Dr",
    "iso:country":"CA",
    "sg:address":"1401 O'Connor Dr",
    "sg:city":"East York",
    "sg:classifiers":[
        {
            "category":"Sports & Exercise",
            "subcategory":"Bowling",
            "type":"Entertainment"
        }
    ],
    "sg:phone":"+1 416 755 1231",
    "sg:postcode":"M4B 2V5",
    "sg:province":"ON",
    "sg:tags":[
        "center"
    ],
    "wof:name":"O'Connor Bowl",
    "wof:placetype":"venue"
},
  "geometry": {"coordinates":[-79.353554,43.692467],"type":"Point"}
}