{
  "type": "Feature",
  "properties": {
    "addr:full":"113 Main St Unity SK S0K 4L0",
    "addr:housenumber":"113",
    "addr:postcode":"s0k 4l0",
    "addr:street":"Main St",
    "iso:country":"CA",
    "sg:address":"113 Main St",
    "sg:city":"Unity",
    "sg:classifiers":[
        {
            "category":"Shopping",
            "subcategory":"Crafts & Fabrics",
            "type":"Retail Goods"
        }
    ],
    "sg:phone":"+1 306 228 7273",
    "sg:postcode":"S0K 4L0",
    "sg:province":"SK",
    "sg:tags":[
        "shop"
    ],
    "wof:name":"Stitch By Stitch",
    "wof:placetype":"venue"
},
  "geometry": {"coordinates":[-109.159538,52.441868],"type":"Point"}
}