{
  "type": "Feature",
  "properties": {
    "addr:full":"320 Westridge Rd NW Edmonton AB T5T 1C5",
    "addr:housenumber":"320",
    "addr:postcode":"t5t 1c5",
    "addr:street":"Westridge Rd Nw",
    "iso:country":"CA",
    "sg:address":"320 Westridge Rd NW",
    "sg:city":"Edmonton",
    "sg:classifiers":[
        {
            "category":"Real Estate",
            "subcategory":"Developer",
            "type":"Services"
        }
    ],
    "sg:phone":"+1 780 487 9341",
    "sg:postcode":"T5T 1C5",
    "sg:province":"AB",
    "wof:name":"First Industrial Developments",
    "wof:placetype":"venue"
},
  "geometry": {"coordinates":[-113.606476,53.507969],"type":"Point"}
}