{
  "type": "Feature",
  "properties": {
    "addr:full":"1634 Winhara Rd Gravenhurst ON P1P 1R1",
    "addr:housenumber":"1634",
    "addr:postcode":"p1p 1r1",
    "addr:street":"Winhara Rd",
    "iso:country":"CA",
    "sg:address":"1634 Winhara Rd",
    "sg:city":"Gravenhurst",
    "sg:classifiers":[
        {
            "category":"Home & Garden",
            "subcategory":"Building Materials",
            "type":"Retail Goods"
        }
    ],
    "sg:phone":"+1 705 687 2061",
    "sg:postcode":"P1P 1R1",
    "sg:province":"ON",
    "sg:tags":[
        "mixed",
        "concrete"
    ],
    "wof:name":"Lafarge Canada Inc",
    "wof:placetype":"venue"
},
  "geometry": {"coordinates":[-79.314644,44.985542],"type":"Point"}
}