{
  "type": "Feature",
  "properties": {
    "addr:full":"99 111 Rte W LA Sarre QC J9Z 3K4",
    "addr:housenumber":"111",
    "addr:postcode":"j9z 3k4",
    "addr:street":"99;Rte W La Sarre",
    "iso:country":"CA",
    "sg:address":"99 111 Rte W",
    "sg:city":"LA Sarre",
    "sg:classifiers":[
        {
            "category":"Retail",
            "subcategory":"Auto Repair",
            "type":"Services"
        }
    ],
    "sg:phone":"+1 819 333 5550",
    "sg:postcode":"J9Z 3K4",
    "sg:province":"QC",
    "sg:tags":[
        "repairing",
        "automobile"
    ],
    "wof:name":"Mecanique Generale Enr",
    "wof:placetype":"venue"
},
  "geometry": {"coordinates":[-79.20031738279999,48.7975616455],"type":"Point"}
}