{
  "type": "Feature",
  "properties": {
    "addr:full":"PO Box 628 Bon Accord AB T0A 0K0",
    "addr:housenumber":"po",
    "addr:postcode":"t0a 0k0",
    "addr:street":"Box 628",
    "iso:country":"CA",
    "sg:address":"PO Box 628",
    "sg:city":"Bon Accord",
    "sg:classifiers":[
        {
            "category":"Manufacturing",
            "subcategory":"Apparel",
            "type":"Manufacturing & Wholesale Goods"
        }
    ],
    "sg:phone":"+1 780 921 3001",
    "sg:postcode":"T0A 0K0",
    "sg:province":"AB",
    "sg:tags":[
        "upholsterer"
    ],
    "wof:name":"Lone Wolf Custom Canvass Ltd",
    "wof:placetype":"venue"
},
  "geometry": {"coordinates":[-113.410797,53.837276],"type":"Point"}
}