{
  "type": "Feature",
  "properties": {
    "addr:full":"795 Rue Cormier Drummondville QC J2C 6P7",
    "addr:housenumber":"795",
    "addr:postcode":"j2c 6p7",
    "addr:street":"Rue Cormier",
    "iso:country":"CA",
    "sg:address":"795 Rue Cormier",
    "sg:city":"Drummondville",
    "sg:classifiers":[
        {
            "category":"Wholesale",
            "subcategory":"Apparel",
            "type":"Manufacturing & Wholesale Goods"
        }
    ],
    "sg:phone":"+1 819 474 3995",
    "sg:postcode":"J2C 6P7",
    "sg:province":"QC",
    "sg:tags":[
        "thread"
    ],
    "wof:name":"Fibre Ventek Ltd",
    "wof:placetype":"venue"
},
  "geometry": {"coordinates":[-72.5144042969,45.887512207],"type":"Point"}
}