{
  "type": "Feature",
  "properties": {
    "addr:full":"1222 Ch Des Hauteurs Saint-Hippolyte QC J8A 1Y4",
    "addr:housenumber":"1222",
    "addr:postcode":"j8a 1y4",
    "addr:street":"Ch Des Hauteurs",
    "iso:country":"CA",
    "sg:address":"1222 Ch Des Hauteurs",
    "sg:city":"Saint-Hippolyte",
    "sg:classifiers":[
        {
            "category":"Real Estate",
            "subcategory":"Architect",
            "type":"Services"
        }
    ],
    "sg:phone":"+1 450 224 8082",
    "sg:postcode":"J8A 1Y4",
    "sg:province":"QC",
    "wof:name":"Adam, Jean-Marie",
    "wof:placetype":"venue"
},
  "geometry": {"coordinates":[-74.006142,45.886242],"type":"Point"}
}