{
  "type": "Feature",
  "properties": {
    "addr:full":"68 Capri Ave NW Calgary AB T2L 0H1",
    "addr:housenumber":"68",
    "addr:postcode":"t2l 0h1",
    "addr:street":"Capri Ave Nw",
    "iso:country":"CA",
    "sg:address":"68 Capri Ave NW",
    "sg:city":"Calgary",
    "sg:classifiers":[
        {
            "category":"Building & Trades",
            "subcategory":"Plumbing",
            "type":"Services"
        }
    ],
    "sg:phone":"+1 403 289 0050",
    "sg:postcode":"T2L 0H1",
    "sg:province":"AB",
    "sg:tags":[
        "cleaning",
        "boiler"
    ],
    "wof:name":"Fire Rite Mechanical Ltd",
    "wof:placetype":"venue"
},
  "geometry": {"coordinates":[-114.105896,51.089466],"type":"Point"}
}