{
  "type": "Feature",
  "properties": {
    "addr:full":"1550 Kimball Side Rd Courtright ON N0N 1H0",
    "addr:housenumber":"1550",
    "addr:postcode":"n0n 1h0",
    "addr:street":"Kimball Side Rd",
    "iso:country":"CA",
    "sg:address":"1550 Kimball Side Rd",
    "sg:city":"Courtright",
    "sg:classifiers":[
        {
            "category":"Government",
            "subcategory":"Fire Station",
            "type":"Public Place"
        }
    ],
    "sg:phone":"+1 ",
    "sg:postcode":"N0N 1H0",
    "sg:province":"ON",
    "sg:tags":[
        "department"
    ],
    "wof:name":"Courtright Fire Hall Personnel",
    "wof:placetype":"venue"
},
  "geometry": {"coordinates":[-82.4742279053,42.8188858032],"type":"Point"}
}