{
  "type": "Feature",
  "properties": {
    "addr:full":"6027 103A St NW Edmonton AB T6H 2J7",
    "addr:housenumber":"6027",
    "addr:postcode":"t6h 2j7",
    "addr:street":"103A St Nw",
    "iso:country":"CA",
    "sg:address":"6027 103A St NW",
    "sg:city":"Edmonton",
    "sg:classifiers":[
        {
            "category":"Wholesale",
            "subcategory":"Furniture",
            "type":"Manufacturing & Wholesale Goods"
        }
    ],
    "sg:phone":"+1 780 436 7335",
    "sg:postcode":"T6H 2J7",
    "sg:province":"AB",
    "sg:tags":[
        "equipment",
        "library",
        "supply"
    ],
    "wof:name":"Warwood Office Furnishings Ltd",
    "wof:placetype":"venue"
},
  "geometry": {"coordinates":[-113.49479700000001,53.497322],"type":"Point"}
}