{
  "type": "Feature",
  "properties": {
    "addr:full":"1302 Ch DE L'Eglise Remigny QC J0Z 3H0",
    "addr:housenumber":"1302",
    "addr:postcode":"j0z 3h0",
    "addr:street":"Ch De L'Eglise",
    "iso:country":"CA",
    "sg:address":"1302 Ch DE L'Eglise",
    "sg:city":"Remigny",
    "sg:classifiers":[
        {
            "category":"Manufacturing",
            "subcategory":"Lumber",
            "type":"Manufacturing & Wholesale Goods"
        }
    ],
    "sg:phone":"+1 819 761 2128",
    "sg:postcode":"J0Z 3H0",
    "sg:province":"QC",
    "sg:tags":[
        "forester"
    ],
    "wof:name":"Foresterie Des Quinze",
    "wof:placetype":"venue"
},
  "geometry": {"coordinates":[-79.22814200000001,47.75423],"type":"Point"}
}