{
  "type": "Feature",
  "properties": {
    "iso:country":"CA",
    "sg:address":"30 Mcnaughton Ave",
    "sg:city":"Wallaceburg",
    "sg:classifiers":[
        {
            "category":"Food & Beverages",
            "subcategory":"Meat & Fish",
            "type":"Retail Goods"
        }
    ],
    "sg:phone":"+1 519 627 4545",
    "sg:postcode":"N8A 1R9",
    "sg:province":"ON",
    "sg:tags":[
        "frozen"
    ],
    "wof:name":"M & M Meat Shop",
    "wof:placetype":"venue"
},
  "geometry": {"coordinates":[-82.3852310181,42.5884780884],"type":"Point"}
}