{
  "type": "Feature",
  "properties": {
    "iso:country":"CA",
    "sg:city":"Mississauga",
    "sg:classifiers":[
        {
            "category":"Shopping",
            "subcategory":"Computers & Home Electronics",
            "type":"Retail Goods"
        }
    ],
    "sg:phone":"+1 905 273 9550",
    "sg:postcode":"L4Z 1V3",
    "sg:province":"ON",
    "sg:tags":[
        "software"
    ],
    "wof:name":"Quatro Group Software Systems",
    "wof:placetype":"venue"
},
  "geometry": {"coordinates":[-79.640556,43.600727],"type":"Point"}
}