{
  "type": "Feature",
  "properties": {
    "addr:full":"64 3E Av Windsor QC J1S 1X9",
    "addr:housenumber":"64",
    "addr:postcode":"j1s 1x9",
    "addr:street":"3E Av",
    "iso:country":"CA",
    "sg:address":"64 3E Av",
    "sg:city":"Windsor",
    "sg:classifiers":[
        {
            "category":"Retail",
            "subcategory":"Funeral Services",
            "type":"Services"
        }
    ],
    "sg:phone":"+1 819 565 7646",
    "sg:postcode":"J1S 1X9",
    "sg:province":"QC",
    "sg:tags":[
        "director"
    ],
    "wof:name":"Maison A Bouvert",
    "wof:placetype":"venue"
},
  "geometry": {"coordinates":[-72.0004196167,45.5717124939],"type":"Point"}
}