{
  "type": "Feature",
  "properties": {
    "addr:full":"Verdun QC H3E 1R2",
    "addr:postcode":"h3e 1r2",
    "iso:country":"CA",
    "sg:city":"Verdun",
    "sg:classifiers":[
        {
            "category":"Professional",
            "subcategory":"Advertising",
            "type":"Services"
        }
    ],
    "sg:phone":"+1 514 954 0477",
    "sg:postcode":"H3E 1R2",
    "sg:province":"QC",
    "wof:name":"Visuel Corp",
    "wof:placetype":"venue"
},
  "geometry": {"coordinates":[-73.57176200000001,45.459019],"type":"Point"}
}