{
  "type": "Feature",
  "properties": {
    "addr:full":"Toronto ON M6H 4A9",
    "addr:postcode":"m6h 4a9",
    "iso:country":"CA",
    "sg:city":"Toronto",
    "sg:classifiers":[
        {
            "category":"Shopping",
            "subcategory":"Clothing, Apparel, & Fashions",
            "type":"Retail Goods"
        }
    ],
    "sg:phone":"+1 416 532 5242",
    "sg:postcode":"M6H 4A9",
    "sg:province":"ON",
    "wof:name":"Suzy Shier",
    "wof:placetype":"venue"
},
  "geometry": {"coordinates":[-79.43435700000001,43.656773],"type":"Point"}
}