{
  "type": "Feature",
  "properties": {
    "iso:country":"CA",
    "sg:address":"1170 Boul Lebourgneuf # 300",
    "sg:city":"Quebec",
    "sg:classifiers":[
        {
            "category":"Restaurant",
            "type":"Food & Drink"
        }
    ],
    "sg:phone":"+1 418 624 3339",
    "sg:postcode":"G2K 2E3",
    "sg:province":"QC",
    "wof:name":"Restaurant Extreme",
    "wof:placetype":"venue"
},
  "geometry": {"coordinates":[-71.2939453125,46.8360748291],"type":"Point"}
}