{
  "type": "Feature",
  "properties": {
    "addr:full":"1170 Boul Lebourgneuf # 300 Quebec QC G2K 2E3",
    "addr:housenumber":"1170",
    "addr:postcode":"g2k 2e3",
    "addr:street":"Boul Lebourgneuf # 300",
    "iso:country":"CA",
    "sg:address":"1170 Boul Lebourgneuf # 300",
    "sg:city":"Quebec",
    "sg:classifiers":[
        {
            "category":"Restaurant",
            "type":"Food & Drink"
        }
    ],
    "sg:phone":"+1 418 624 3339",
    "sg:postcode":"G2K 2E3",
    "sg:province":"QC",
    "wof:name":"Restaurant Extreme",
    "wof:placetype":"venue"
},
  "geometry": {"coordinates":[-71.2939453125,46.8360748291],"type":"Point"}
}