{
  "type": "Feature",
  "properties": {
    "addr:full":"Surrey BC V4A 5A4",
    "addr:postcode":"v4a 5a4",
    "iso:country":"CA",
    "sg:city":"Surrey",
    "sg:classifiers":[
        {
            "category":"Professional",
            "subcategory":"Employment Agencies",
            "type":"Services"
        }
    ],
    "sg:phone":"+1 604 538 2079",
    "sg:postcode":"V4A 5A4",
    "sg:province":"BC",
    "sg:tags":[
        "exporter",
        "help"
    ],
    "wof:name":"Far West Group",
    "wof:placetype":"venue"
},
  "geometry": {"coordinates":[-122.79334258999999,49.0451583862],"type":"Point"}
}