{
  "type": "Feature",
  "properties": {
    "addr:full":"111 9E Rue Rouyn-Noranda QC J9X 2B7",
    "addr:housenumber":"111",
    "addr:postcode":"j9x 2b7",
    "addr:street":"9E Rue",
    "iso:country":"CA",
    "sg:address":"111 9E Rue",
    "sg:city":"Rouyn-Noranda",
    "sg:classifiers":[
        {
            "category":"Government",
            "subcategory":"Fire Station",
            "type":"Public Place"
        }
    ],
    "sg:phone":"+1 819 797 7124",
    "sg:postcode":"J9X 2B7",
    "sg:province":"QC",
    "sg:tags":[
        "department"
    ],
    "wof:name":"Rouyn-Noranda Incendies-Adm",
    "wof:placetype":"venue"
},
  "geometry": {"coordinates":[-79.019356,48.247295],"type":"Point"}
}