{
  "type": "Feature",
  "properties": {
    "addr:full":"312 Rue Lindsay Drummondville QC J2B 1G5",
    "addr:housenumber":"312",
    "addr:postcode":"j2b 1g5",
    "addr:street":"Rue Lindsay",
    "iso:country":"CA",
    "sg:address":"312 Rue Lindsay",
    "sg:city":"Drummondville",
    "sg:classifiers":[
        {
            "category":"Home & Garden",
            "subcategory":"Furniture",
            "type":"Retail Goods"
        }
    ],
    "sg:phone":"+1 819 478 4149",
    "sg:postcode":"J2B 1G5",
    "sg:province":"QC",
    "wof:name":"Setlakwe Meubles",
    "wof:placetype":"venue"
},
  "geometry": {"coordinates":[-72.485657,45.881851],"type":"Point"}
}