{
  "type": "Feature",
  "properties": {
    "addr:full":"371 Salter Ave # 800 Windsor ON N9A 5C1",
    "addr:housenumber":"371",
    "addr:postcode":"n9a 5c1",
    "addr:street":"Salter Ave # 800",
    "iso:country":"CA",
    "sg:address":"371 Salter Ave # 800",
    "sg:city":"Windsor",
    "sg:classifiers":[
        {
            "category":"Wholesale",
            "subcategory":"Electrical",
            "type":"Manufacturing & Wholesale Goods"
        }
    ],
    "sg:phone":"+1 519 977 7800",
    "sg:postcode":"N9A 5C1",
    "sg:province":"ON",
    "sg:tags":[
        "equipment",
        "audio",
        "lighting",
        "system"
    ],
    "wof:name":"Allied Production Group",
    "wof:placetype":"venue"
},
  "geometry": {"coordinates":[-83.04811096189999,42.3143119812],"type":"Point"}
}