{
  "type": "Feature",
  "properties": {
    "addr:full":"Hamilton ON L8S 2H8",
    "addr:postcode":"l8s 2h8",
    "iso:country":"CA",
    "sg:city":"Hamilton",
    "sg:classifiers":[
        {
            "category":"Retail",
            "subcategory":"Self-service Laundry",
            "type":"Services"
        }
    ],
    "sg:phone":"+1 905 308 8437",
    "sg:postcode":"L8S 2H8",
    "sg:province":"ON",
    "wof:name":"Super Wash World",
    "wof:placetype":"venue"
},
  "geometry": {"coordinates":[-79.938126,43.251434],"type":"Point"}
}