{
  "type": "Feature",
  "properties": {
    "iso:country":"CA",
    "sg:address":"167 Country Rd",
    "sg:city":"Corner Brook",
    "sg:classifiers":[
        {
            "category":"Retail",
            "subcategory":"Funeral Services",
            "type":"Services"
        }
    ],
    "sg:phone":"+1 709 634 2500",
    "sg:postcode":"A2H 4M5",
    "sg:province":"NL",
    "sg:tags":[
        "director"
    ],
    "wof:name":"Country Haven",
    "wof:placetype":"venue"
},
  "geometry": {"coordinates":[-57.9746818542,48.9428634644],"type":"Point"}
}