{
  "type": "Feature",
  "properties": {
    "addr:full":"Toronto ON M5A 1N1",
    "addr:postcode":"m5a 1n1",
    "iso:country":"CA",
    "sg:city":"Toronto",
    "sg:classifiers":[
        {
            "category":"Wholesale",
            "subcategory":"Durable Goods & Equipment",
            "type":"Manufacturing & Wholesale Goods"
        }
    ],
    "sg:phone":"+1 416 494 2562",
    "sg:postcode":"M5A 1N1",
    "sg:province":"ON",
    "sg:tags":[
        "compact",
        "record",
        "disc",
        "tape"
    ],
    "wof:name":"Alma Records",
    "wof:placetype":"venue"
},
  "geometry": {"coordinates":[-79.370803833,43.6517868042],"type":"Point"}
}