{
  "type": "Feature",
  "properties": {
    "addr:full":"47 Madison Ave S Kitchener ON N2G 3M4",
    "addr:housenumber":"47",
    "addr:postcode":"n2g 3m4",
    "addr:street":"Madison Ave S",
    "iso:country":"CA",
    "sg:address":"47 Madison Ave S",
    "sg:city":"Kitchener",
    "sg:classifiers":[
        {
            "category":"Organizations",
            "subcategory":"Professional Association",
            "type":"Services"
        }
    ],
    "sg:phone":"+1 519 741 8881",
    "sg:postcode":"N2G 3M4",
    "sg:province":"ON",
    "wof:name":"Hope Harbour",
    "wof:placetype":"venue"
},
  "geometry": {"coordinates":[-80.482788,43.445473],"type":"Point"}
}