{
  "type": "Feature",
  "properties": {
    "addr:full":"3241 Ch Sainte-Foy Sainte-Foy QC G1X 1R8",
    "addr:postcode":"3241;g1x 1r8",
    "addr:street":"Ch Sainte-Foy",
    "iso:country":"CA",
    "sg:address":"3241 Ch Sainte-Foy",
    "sg:city":"Sainte-Foy",
    "sg:classifiers":[
        {
            "category":"Retail",
            "subcategory":"Auto Repair",
            "type":"Services"
        }
    ],
    "sg:phone":"+1 418 653 0344",
    "sg:postcode":"G1X 1R8",
    "sg:province":"QC",
    "sg:tags":[
        "repairing",
        "automobile"
    ],
    "wof:name":"Service B Ouellet Inc",
    "wof:placetype":"venue"
},
  "geometry": {"coordinates":[-71.2917633057,46.7692108154],"type":"Point"}
}