{
  "type": "Feature",
  "properties": {
    "addr:full":"8980 Douglas St Richmond BC V6X 1V3",
    "addr:housenumber":"8980",
    "addr:postcode":"v6x 1v3",
    "addr:street":"Douglas St",
    "iso:country":"CA",
    "sg:address":"8980 Douglas St",
    "sg:city":"Richmond",
    "sg:classifiers":[
        {
            "category":"Building & Trades",
            "subcategory":"Construction",
            "type":"Services"
        }
    ],
    "sg:phone":"+1 604 278 7663",
    "sg:postcode":"V6X 1V3",
    "sg:province":"BC",
    "sg:tags":[
        "roofing",
        "contractor"
    ],
    "wof:name":"O B Roofing Ltd",
    "wof:placetype":"venue"
},
  "geometry": {"coordinates":[-123.126251221,49.1927871704],"type":"Point"}
}