{
  "type": "Feature",
  "properties": {
    "addr:full":"556 Christina St N Sarnia ON N7T 5W6",
    "addr:housenumber":"556",
    "addr:postcode":"n7t 5w6",
    "addr:street":"Christina St N",
    "iso:country":"CA",
    "sg:address":"556 Christina St N",
    "sg:city":"Sarnia",
    "sg:classifiers":[
        {
            "category":"Government",
            "subcategory":"Office",
            "type":"Public Place"
        }
    ],
    "sg:phone":"+1 519 344 7715",
    "sg:postcode":"N7T 5W6",
    "sg:province":"ON",
    "wof:name":"Motor Vehicle Licence Bureau",
    "wof:placetype":"venue"
},
  "geometry": {"coordinates":[-82.400719,42.983921],"type":"Point"}
}