{
  "type": "Feature",
  "properties": {
    "addr:full":"23 Glenthorn Ave Charlottetown PE C1A 8K7",
    "addr:housenumber":"23",
    "addr:postcode":"c1a 8k7",
    "addr:street":"Glenthorn Ave",
    "iso:country":"CA",
    "sg:address":"23 Glenthorn Ave",
    "sg:city":"Charlottetown",
    "sg:classifiers":[
        {
            "category":"Building & Trades",
            "subcategory":"Cleaning & Sanitation",
            "type":"Services"
        }
    ],
    "sg:phone":"+1 902 368 7444",
    "sg:postcode":"C1A 8K7",
    "sg:province":"PE",
    "sg:tags":[
        "janitor"
    ],
    "wof:name":"A-1 Building Cleaning Ltd",
    "wof:placetype":"venue"
},
  "geometry": {"coordinates":[-63.107174,46.265388],"type":"Point"}
}