{
  "type": "Feature",
  "properties": {
    "addr:full":"1 1st St Moosonee ON P0L 1Y0",
    "addr:housenumber":"1",
    "addr:postcode":"p0l 1y0",
    "addr:street":"1St St",
    "iso:country":"CA",
    "sg:address":"1 1st St",
    "sg:city":"Moosonee",
    "sg:classifiers":[
        {
            "category":"Railroad",
            "type":"Transportation"
        }
    ],
    "sg:phone":"+1 705 336 2931",
    "sg:postcode":"P0L 1Y0",
    "sg:province":"ON",
    "wof:name":"Ontario Northland Express Svc",
    "wof:placetype":"venue"
},
  "geometry": {"coordinates":[-80.6458740234,51.2741317749],"type":"Point"}
}