{
  "type": "Feature",
  "properties": {
    "addr:full":"446 Newfoundland Dr St. John's NL A1A 4G7",
    "addr:housenumber":"446",
    "addr:postcode":"a1a 4g7",
    "addr:street":"Newfoundland Dr",
    "iso:country":"CA",
    "sg:address":"446 Newfoundland Dr",
    "sg:city":"St. John's",
    "sg:classifiers":[
        {
            "category":"Building & Trades",
            "subcategory":"Construction",
            "type":"Services"
        }
    ],
    "sg:phone":"+1 709 754 0077",
    "sg:postcode":"A1A 4G7",
    "sg:province":"NL",
    "sg:tags":[
        "paving",
        "contractor"
    ],
    "wof:name":"Provincial Paving Ltd",
    "wof:placetype":"venue"
},
  "geometry": {"coordinates":[-52.7079582214,47.600982666],"type":"Point"}
}