{
  "type": "Feature",
  "properties": {
    "addr:full":"193 Elizabeth Ave St. John's NL A1B 1S9",
    "addr:housenumber":"193",
    "addr:postcode":"a1b 1s9",
    "addr:street":"Elizabeth Ave",
    "iso:country":"CA",
    "sg:address":"193 Elizabeth Ave",
    "sg:city":"St. John's",
    "sg:classifiers":[
        {
            "category":"Health Services",
            "subcategory":"Doctor",
            "type":"Services"
        }
    ],
    "sg:phone":"+1 709 726 4667",
    "sg:postcode":"A1B 1S9",
    "sg:province":"NL",
    "sg:tags":[
        "physician",
        "surgeon"
    ],
    "wof:name":"O'Leary, Sean MD",
    "wof:placetype":"venue"
},
  "geometry": {"coordinates":[-52.724937439,47.5741767883],"type":"Point"}
}