{
  "type": "Feature",
  "properties": {
    "addr:full":"12 33E Av Bois-Des-Filion QC J6Z 2B8",
    "addr:housenumber":"12",
    "addr:postcode":"j6z 2b8",
    "addr:street":"33E Av Bois-Des-Filion",
    "iso:country":"CA",
    "sg:address":"12 33E Av",
    "sg:city":"Bois-Des-Filion",
    "sg:classifiers":[
        {
            "category":"Building & Trades",
            "subcategory":"Construction",
            "type":"Services"
        }
    ],
    "sg:phone":"+1 450 621 8857",
    "sg:postcode":"J6Z 2B8",
    "sg:province":"QC",
    "sg:tags":[
        "repairing",
        "remodeling",
        "contractor"
    ],
    "wof:name":"Constructions Jomar Inc",
    "wof:placetype":"venue"
},
  "geometry": {"coordinates":[-73.75635528559999,45.6687965393],"type":"Point"}
}