{
  "type": "Feature",
  "properties": {
    "addr:full":"9415 98 Ave High Level AB T0H 1Z0",
    "addr:housenumber":"9415",
    "addr:postcode":"t0h 1z0",
    "addr:street":"98 Ave",
    "iso:country":"CA",
    "sg:address":"9415 98 Ave",
    "sg:city":"High Level",
    "sg:classifiers":[
        {
            "category":"Building & Trades",
            "subcategory":"Construction",
            "type":"Services"
        }
    ],
    "sg:phone":"+1 780 926 3208",
    "sg:postcode":"T0H 1Z0",
    "sg:province":"AB",
    "sg:tags":[
        "general",
        "contractor"
    ],
    "wof:name":"LA Prairie Group Contractors",
    "wof:placetype":"venue"
},
  "geometry": {"coordinates":[-117.131607,58.52058],"type":"Point"}
}