{
  "type": "Feature",
  "properties": {
    "addr:full":"Maria QC G0C 1Y0",
    "addr:postcode":"g0c 1y0",
    "addr:street":"Maria",
    "iso:country":"CA",
    "sg:city":"Maria",
    "sg:classifiers":[
        {
            "category":"Manufacturing",
            "subcategory":"Lumber",
            "type":"Manufacturing & Wholesale Goods"
        }
    ],
    "sg:phone":"+1 418 759 3284",
    "sg:postcode":"G0C 1Y0",
    "sg:province":"QC",
    "sg:tags":[
        "forester"
    ],
    "wof:name":"Entrepreneur Forestier",
    "wof:placetype":"venue"
},
  "geometry": {"coordinates":[-65.9848861694,48.180606842],"type":"Point"}
}