{
  "type": "Feature",
  "properties": {
    "iso:country":"CA",
    "sg:address":"329 Rothesay Ave",
    "sg:city":"Saint John",
    "sg:classifiers":[
        {
            "category":"Manufacturing",
            "subcategory":"Signs",
            "type":"Manufacturing & Wholesale Goods"
        }
    ],
    "sg:phone":"+1 506 657 8746",
    "sg:postcode":"E2J 2C3",
    "sg:province":"NB",
    "sg:tags":[
        "automobile",
        "customizing"
    ],
    "wof:name":"Trim Line of Saint John",
    "wof:placetype":"venue"
},
  "geometry": {"coordinates":[-66.04058074949999,45.2963447571],"type":"Point"}
}