{
  "type": "Feature",
  "properties": {
    "addr:full":"Peterborough ON K9J 6W9",
    "addr:postcode":"k9j 6w9",
    "iso:country":"CA",
    "sg:city":"Peterborough",
    "sg:classifiers":[
        {
            "category":"Freight",
            "type":"Transportation"
        }
    ],
    "sg:phone":"+1 705 876 6772",
    "sg:postcode":"K9J 6W9",
    "sg:province":"ON",
    "sg:tags":[
        "delivery",
        "courier"
    ],
    "wof:name":"C J's Courier",
    "wof:placetype":"venue"
},
  "geometry": {"coordinates":[-78.3449707031,44.278678894],"type":"Point"}
}