{
  "type": "Feature",
  "properties": {
    "addr:full":"Scarborough ON M1N 4C3",
    "addr:postcode":"m1n 4c3",
    "iso:country":"CA",
    "sg:city":"Scarborough",
    "sg:classifiers":[
        {
            "category":"Restaurant",
            "type":"Food & Drink"
        }
    ],
    "sg:phone":"+1 416 690 3658",
    "sg:postcode":"M1N 4C3",
    "sg:province":"ON",
    "wof:name":"Mc Donald's",
    "wof:placetype":"venue"
},
  "geometry": {"coordinates":[-79.2859039307,43.6871681213],"type":"Point"}
}