{
  "type": "Feature",
  "properties": {
    "addr:full":"53 Saint-Charles Station Rd Upper Rexton NB E4W 3E1",
    "addr:housenumber":"53",
    "addr:postcode":"e4w 3e1",
    "addr:street":"Saint-Charles Station Rd",
    "iso:country":"CA",
    "sg:address":"53 Saint-Charles Station Rd",
    "sg:city":"Upper Rexton",
    "sg:classifiers":[
        {
            "category":"Building & Trades",
            "subcategory":"Plumbing",
            "type":"Services"
        }
    ],
    "sg:phone":"+1 506 523 4501",
    "sg:postcode":"E4W 3E1",
    "sg:province":"NB",
    "sg:tags":[
        "contractor"
    ],
    "wof:name":"E Johnson Plumbing & Htg Reg's",
    "wof:placetype":"venue"
},
  "geometry": {"coordinates":[-64.8701095581,46.6425704956],"type":"Point"}
}