{
  "type": "Feature",
  "properties": {
    "iso:country":"CA",
    "sg:city":"Kelowna",
    "sg:classifiers":[
        {
            "category":"Manufacturing",
            "subcategory":"Printing",
            "type":"Manufacturing & Wholesale Goods"
        }
    ],
    "sg:phone":"+1 604 882 5115",
    "sg:postcode":"V1X 5C3",
    "sg:province":"BC",
    "sg:tags":[
        "printer"
    ],
    "wof:name":"Speedpro Systems Inc",
    "wof:placetype":"venue"
},
  "geometry": {"coordinates":[-119.496597,49.886814],"type":"Point"}
}