{
  "type": "Feature",
  "properties": {
    "iso:country":"CA",
    "sg:city":"Ottawa",
    "sg:classifiers":[
        {
            "category":"Autos & Motor Vehicles",
            "subcategory":"Auto Supplies",
            "type":"Retail Goods"
        }
    ],
    "sg:phone":"+1 613 746 1000",
    "sg:postcode":"K1B 3T4",
    "sg:province":"ON",
    "sg:tags":[
        "automobile",
        "stereo",
        "parts",
        "radio"
    ],
    "wof:name":"Ottawa's Auto Sound Plus",
    "wof:placetype":"venue"
},
  "geometry": {"coordinates":[-75.62641143800001,45.4119148254],"type":"Point"}
}