{
  "type": "Feature",
  "properties": {
    "addr:full":"850 Oliver St Williams Lake BC V2G 3W1",
    "addr:housenumber":"850",
    "addr:postcode":"v2g 3w1",
    "addr:street":"Oliver St",
    "iso:country":"CA",
    "sg:address":"850 Oliver St",
    "sg:city":"Williams Lake",
    "sg:classifiers":[
        {
            "category":"Shopping",
            "subcategory":"Department Store",
            "type":"Retail Goods"
        }
    ],
    "sg:phone":"+1 250 398 8430",
    "sg:postcode":"V2G 3W1",
    "sg:province":"BC",
    "wof:name":"Zellers",
    "wof:placetype":"venue"
},
  "geometry": {"coordinates":[-122.131927,52.12854],"type":"Point"}
}