{
  "type": "Feature",
  "properties": {
    "iso:country":"CA",
    "sg:address":"6425 Fraser St",
    "sg:city":"Vancouver",
    "sg:classifiers":[
        {
            "category":"Shopping",
            "subcategory":"Discount & Variety Stores",
            "type":"Retail Goods"
        }
    ],
    "sg:phone":"+1 604 323 8474",
    "sg:postcode":"V5W 3A6",
    "sg:province":"BC",
    "sg:tags":[
        "shop",
        "gift"
    ],
    "wof:name":"Dollar Store Express",
    "wof:placetype":"venue"
},
  "geometry": {"coordinates":[-123.090904236,49.2262687683],"type":"Point"}
}