{
  "type": "Feature",
  "properties": {
    "addr:full":"151 Rue Lindsay Drummondville QC J2C 1N7",
    "addr:housenumber":"151",
    "addr:postcode":"j2c 1n7",
    "addr:street":"Rue Lindsay",
    "iso:country":"CA",
    "sg:address":"151 Rue Lindsay",
    "sg:city":"Drummondville",
    "sg:classifiers":[
        {
            "category":"Personal",
            "subcategory":"Beauty Salon",
            "type":"Services"
        }
    ],
    "sg:phone":"+1 819 477 2220",
    "sg:postcode":"J2C 1N7",
    "sg:province":"QC",
    "wof:name":"Salon D'Esthetique Laurence",
    "wof:placetype":"venue"
},
  "geometry": {"coordinates":[-72.4920578003,45.8850517273],"type":"Point"}
}