{
  "type": "Feature",
  "properties": {
    "addr:full":"940 Winston Churchill Blvd Oakville ON L6J 7X5",
    "addr:housenumber":"940",
    "addr:postcode":"l6j 7x5",
    "addr:street":"Winston Churchill Blvd",
    "iso:country":"CA",
    "sg:address":"940 Winston Churchill Blvd",
    "sg:city":"Oakville",
    "sg:classifiers":[
        {
            "category":"Retail",
            "subcategory":"Repair Shop",
            "type":"Services"
        }
    ],
    "sg:phone":"+1 905 337 7710",
    "sg:postcode":"L6J 7X5",
    "sg:province":"ON",
    "sg:tags":[
        "steel",
        "welding"
    ],
    "wof:name":"George Seehaver Welding",
    "wof:placetype":"venue"
},
  "geometry": {"coordinates":[-79.6444320679,43.4953727722],"type":"Point"}
}