{
  "type": "Feature",
  "properties": {
    "addr:full":"Mansonville QC J0E 1X0",
    "addr:postcode":"j0e 1x0",
    "iso:country":"CA",
    "sg:city":"Mansonville",
    "sg:classifiers":[
        {
            "category":"Organizations",
            "subcategory":"Professional Association",
            "type":"Services"
        }
    ],
    "sg:phone":"+1 450 292 3114",
    "sg:postcode":"J0E 1X0",
    "sg:province":"QC",
    "wof:name":"Citizen Advocacy-Mountain Vly",
    "wof:placetype":"venue"
},
  "geometry": {"coordinates":[-72.39213562010001,45.0525474548],"type":"Point"}
}