{
  "type": "Feature",
  "properties": {
    "addr:full":"166 Rue Principale E Farnham QC J2N 1L4",
    "addr:housenumber":"166",
    "addr:postcode":"j2n 1l4",
    "addr:street":"Rue Principale E",
    "iso:country":"CA",
    "sg:address":"166 Rue Principale E",
    "sg:city":"Farnham",
    "sg:classifiers":[
        {
            "category":"Personal",
            "subcategory":"Beauty Salon",
            "type":"Services"
        }
    ],
    "sg:phone":"+1 450 293 7161",
    "sg:postcode":"J2N 1L4",
    "sg:province":"QC",
    "wof:name":"Salon Liane Enr",
    "wof:placetype":"venue"
},
  "geometry": {"coordinates":[-72.97872924799999,45.284828186],"type":"Point"}
}