{
  "type": "Feature",
  "properties": {
    "addr:full":"136 Central Ave Montmartre SK S0G 3M0",
    "addr:housenumber":"136",
    "addr:postcode":"s0g 3m0",
    "addr:street":"Central Ave",
    "iso:country":"CA",
    "sg:address":"136 Central Ave",
    "sg:city":"Montmartre",
    "sg:classifiers":[
        {
            "category":"Government",
            "subcategory":"Office",
            "type":"Public Place"
        }
    ],
    "sg:phone":"+1 306 424 2040",
    "sg:postcode":"S0G 3M0",
    "sg:province":"SK",
    "sg:tags":[
        "village"
    ],
    "wof:name":"Montmartre Village Office",
    "wof:placetype":"venue"
},
  "geometry": {"coordinates":[-103.44969940199999,50.2201309204],"type":"Point"}
}