{
  "type": "Feature",
  "properties": {
    "addr:full":"37 Victoria St Udora ON L0C 1L0",
    "addr:housenumber":"37",
    "addr:postcode":"l0c 1l0",
    "addr:street":"Victoria St",
    "iso:country":"CA",
    "sg:address":"37 Victoria St",
    "sg:city":"Udora",
    "sg:classifiers":[
        {
            "category":"Wholesale",
            "subcategory":"Construction Materials",
            "type":"Manufacturing & Wholesale Goods"
        }
    ],
    "sg:phone":"+1 705 228 8393",
    "sg:postcode":"L0C 1L0",
    "sg:province":"ON",
    "sg:tags":[
        "pet",
        "fence"
    ],
    "wof:name":"Hidden Fence of SE Ontario",
    "wof:placetype":"venue"
},
  "geometry": {"coordinates":[-79.1844177246,44.2590370178],"type":"Point"}
}