{
  "type": "Feature",
  "properties": {
    "addr:full":"72 Commercial Ave Ajax ON L1S 2H5",
    "addr:housenumber":"72",
    "addr:postcode":"l1s 2h5",
    "addr:street":"Commercial Ave",
    "iso:country":"CA",
    "sg:address":"72 Commercial Ave",
    "sg:city":"Ajax",
    "sg:classifiers":[
        {
            "category":"Personal",
            "subcategory":"Beauty Salon",
            "type":"Services"
        }
    ],
    "sg:phone":"+1 905 426 6649",
    "sg:postcode":"L1S 2H5",
    "sg:province":"ON",
    "wof:name":"Sincerely P Hair Studio",
    "wof:placetype":"venue"
},
  "geometry": {"coordinates":[-79.023315,43.849396],"type":"Point"}
}