{
  "type": "Feature",
  "properties": {
    "addr:full":"3083 32 St S Lethbridge AB T1K 7B1",
    "addr:housenumber":"3083",
    "addr:postcode":"t1k 7b1",
    "addr:street":"32 St S",
    "iso:country":"CA",
    "sg:address":"3083 32 St S",
    "sg:city":"Lethbridge",
    "sg:classifiers":[
        {
            "category":"Home & Garden",
            "subcategory":"Furniture",
            "type":"Retail Goods"
        }
    ],
    "sg:phone":"+1 403 327 4447",
    "sg:postcode":"T1K 7B1",
    "sg:province":"AB",
    "sg:tags":[
        "mattress"
    ],
    "wof:name":"Mattress Mattress Inc",
    "wof:placetype":"venue"
},
  "geometry": {"coordinates":[-112.796318,49.663013],"type":"Point"}
}