{
  "type": "Feature",
  "properties": {
    "addr:full":"Sherwood Park AB T8A 2G4",
    "addr:postcode":"t8a 2g4",
    "iso:country":"CA",
    "sg:city":"Sherwood Park",
    "sg:classifiers":[
        {
            "category":"Food & Beverages",
            "subcategory":"Liquor & Beverages",
            "type":"Retail Goods"
        }
    ],
    "sg:phone":"+1 780 449 5555",
    "sg:postcode":"T8A 2G4",
    "sg:province":"AB",
    "sg:tags":[
        "store"
    ],
    "wof:name":"Liquor World",
    "wof:placetype":"venue"
},
  "geometry": {"coordinates":[-113.31979370099999,53.5130271912],"type":"Point"}
}