{
  "type": "Feature",
  "properties": {
    "addr:full":"2605 17 Ave SW Calgary AB T3E 0A4",
    "addr:housenumber":"2605",
    "addr:postcode":"t3e 0a4",
    "addr:street":"17 Ave Sw",
    "iso:country":"CA",
    "sg:address":"2605 17 Ave SW",
    "sg:city":"Calgary",
    "sg:classifiers":[
        {
            "category":"Autos & Motor Vehicles",
            "subcategory":"Automobile Sales",
            "type":"Retail Goods"
        }
    ],
    "sg:phone":"+1 403 246 0001",
    "sg:postcode":"T3E 0A4",
    "sg:province":"AB",
    "sg:tags":[
        "car",
        "dealer"
    ],
    "wof:name":"Stampede Auto Sales",
    "wof:placetype":"venue"
},
  "geometry": {"coordinates":[-114.121162415,51.0376777649],"type":"Point"}
}