{
  "type": "Feature",
  "properties": {
    "addr:full":"Mississauga ON L5N 2X4",
    "addr:postcode":"l5n 2x4",
    "iso:country":"CA",
    "sg:city":"Mississauga",
    "sg:classifiers":[
        {
            "category":"Education",
            "subcategory":"Special Training",
            "type":"Public Place"
        }
    ],
    "sg:phone":"+1 905 826 7300",
    "sg:postcode":"L5N 2X4",
    "sg:province":"ON",
    "sg:tags":[
        "management"
    ],
    "wof:name":"Dale Carnegie Training",
    "wof:placetype":"venue"
},
  "geometry": {"coordinates":[-79.74284400000001,43.597809],"type":"Point"}
}