{
  "type": "Feature",
  "properties": {
    "iso:country":"CA",
    "sg:address":"4320 Rue Sainte-Bernadette",
    "sg:city":"Rock Forest",
    "sg:classifiers":[
        {
            "category":"Social Services",
            "subcategory":"Child Care",
            "type":"Services"
        }
    ],
    "sg:phone":"+1 819 823 0095",
    "sg:postcode":"J1N 1S6",
    "sg:province":"QC",
    "wof:name":"Transition Petite Enfance",
    "wof:placetype":"venue"
},
  "geometry": {"coordinates":[-71.97244262700001,45.3819046021],"type":"Point"}
}