{
  "type": "Feature",
  "properties": {
    "addr:full":"Montreal QC H3K 1J5",
    "addr:postcode":"h3k 1j5",
    "iso:country":"CA",
    "sg:city":"Montreal",
    "sg:classifiers":[
        {
            "category":"Organizations",
            "subcategory":"Religious Organization",
            "type":"Services"
        }
    ],
    "sg:phone":"+1 514 932 5335",
    "sg:postcode":"H3K 1J5",
    "sg:province":"QC",
    "sg:tags":[
        "church"
    ],
    "wof:name":"St Charles Church",
    "wof:placetype":"venue"
},
  "geometry": {"coordinates":[-73.56494140620001,45.4813613892],"type":"Point"}
}