{
  "type": "Feature",
  "properties": {
    "addr:full":"2535 Av T.-D.-Bouchard Saint-Hyacinthe QC J2S 7N9",
    "addr:postcode":"2535;j2s 7n9",
    "addr:street":"Av T.-D.-Bouchard",
    "iso:country":"CA",
    "sg:address":"2535 Av T.-D.-Bouchard",
    "sg:city":"Saint-Hyacinthe",
    "sg:classifiers":[
        {
            "category":"Health Services",
            "subcategory":"Medical Lab",
            "type":"Services"
        }
    ],
    "sg:phone":"+1 450 774 8022",
    "sg:postcode":"J2S 7N9",
    "sg:province":"QC",
    "sg:tags":[
        "laboratory"
    ],
    "wof:name":"Laboratoire Dentaire Mondor",
    "wof:placetype":"venue"
},
  "geometry": {"coordinates":[-72.94852400000001,45.639572],"type":"Point"}
}