{
  "type": "Feature",
  "properties": {
    "addr:full":"27 Haas Rd Etobicoke ON M9W 3A1",
    "addr:housenumber":"27",
    "addr:postcode":"m9w 3a1",
    "addr:street":"Haas Rd",
    "iso:country":"CA",
    "sg:address":"27 Haas Rd",
    "sg:city":"Etobicoke",
    "sg:classifiers":[
        {
            "category":"Retail",
            "subcategory":"Auto Repair",
            "type":"Services"
        }
    ],
    "sg:phone":"+1 416 747 8022",
    "sg:postcode":"M9W 3A1",
    "sg:province":"ON",
    "sg:tags":[
        "body",
        "automobile",
        "painting"
    ],
    "wof:name":"Kalsi Automotive Collision",
    "wof:placetype":"venue"
},
  "geometry": {"coordinates":[-79.57427978520001,43.7169494629],"type":"Point"}
}