{
  "type": "Feature",
  "properties": {
    "addr:full":"12 George St Wawa ON P0S 1K0",
    "addr:housenumber":"12",
    "addr:postcode":"p0s 1k0",
    "addr:street":"George St",
    "iso:country":"CA",
    "sg:address":"12 George St",
    "sg:city":"Wawa",
    "sg:classifiers":[
        {
            "category":"Building & Trades",
            "subcategory":"Plumbing",
            "type":"Services"
        }
    ],
    "sg:phone":"+1 705 856 1686",
    "sg:postcode":"P0S 1K0",
    "sg:province":"ON",
    "sg:tags":[
        "furnace",
        "contractor"
    ],
    "wof:name":"A & A Furnace Repair",
    "wof:placetype":"venue"
},
  "geometry": {"coordinates":[-84.773308,47.992031],"type":"Point"}
}