{
  "type": "Feature",
  "properties": {
    "addr:full":"3672 St Clair Ave E Scarborough ON M1M 1T2",
    "addr:housenumber":"3672",
    "addr:postcode":"m1m 1t2",
    "addr:street":"St Clair Ave E",
    "iso:country":"CA",
    "sg:address":"3672 St Clair Ave E",
    "sg:city":"Scarborough",
    "sg:classifiers":[
        {
            "category":"Autos & Motor Vehicles",
            "subcategory":"Automobile Sales",
            "type":"Retail Goods"
        }
    ],
    "sg:phone":"+1 416 266 7550",
    "sg:postcode":"M1M 1T2",
    "sg:province":"ON",
    "sg:tags":[
        "car",
        "dealer"
    ],
    "wof:name":"Delta Auto Sales",
    "wof:placetype":"venue"
},
  "geometry": {"coordinates":[-79.2499694824,43.719165802],"type":"Point"}
}