{
  "type": "Feature",
  "properties": {
    "addr:full":"1021 Bracken Rd St Andrews MB R1A 4H8",
    "addr:housenumber":"1021",
    "addr:postcode":"r1a 4h8",
    "addr:street":"Bracken Rd",
    "iso:country":"CA",
    "sg:address":"1021 Bracken Rd",
    "sg:city":"St Andrews",
    "sg:classifiers":[
        {
            "category":"Building & Trades",
            "subcategory":"Construction",
            "type":"Services"
        }
    ],
    "sg:phone":"+1 204 482 7886",
    "sg:postcode":"R1A 4H8",
    "sg:province":"MB",
    "sg:tags":[
        "water",
        "boring",
        "well",
        "drilling",
        "contractor"
    ],
    "wof:name":"Selkirk Drillers",
    "wof:placetype":"venue"
},
  "geometry": {"coordinates":[-97.032715,50.388145],"type":"Point"}
}