{
  "type": "Feature",
  "properties": {
    "addr:full":"1406 8th Ave N Saskatoon SK S7K 2X7",
    "addr:housenumber":"1406",
    "addr:postcode":"s7k 2x7",
    "addr:street":"8Th Ave N",
    "iso:country":"CA",
    "sg:address":"1406 8th Ave N",
    "sg:city":"Saskatoon",
    "sg:classifiers":[
        {
            "category":"Organizations",
            "subcategory":"Religious Organization",
            "type":"Services"
        }
    ],
    "sg:phone":"+1 306 653 4140",
    "sg:postcode":"S7K 2X7",
    "sg:province":"SK",
    "sg:tags":[
        "church"
    ],
    "wof:name":"St Mark's Anglican Church",
    "wof:placetype":"venue"
},
  "geometry": {"coordinates":[-106.650184631,52.1460456848],"type":"Point"}
}