{
  "type": "Feature",
  "properties": {
    "addr:full":"129 George #12 Ailsa Craig ON N0M 1A0",
    "addr:housenumber":"129;# 12",
    "addr:postcode":"n0m 1a0",
    "addr:street":"George;Ailsa Craig",
    "iso:country":"CA",
    "sg:address":"129 George #12",
    "sg:city":"Ailsa Craig",
    "sg:classifiers":[
        {
            "category":"Retail",
            "subcategory":"Portrait Studio",
            "type":"Services"
        }
    ],
    "sg:phone":"+1 519 293 1047",
    "sg:postcode":"N0M 1A0",
    "sg:province":"ON",
    "sg:tags":[
        "photographer"
    ],
    "wof:name":"Photography By Nigel",
    "wof:placetype":"venue"
},
  "geometry": {"coordinates":[-81.538307,43.146698],"type":"Point"}
}