{
  "type": "Feature",
  "properties": {
    "addr:full":"4456 1st Ave Prince George BC V2M 1C8",
    "addr:housenumber":"4456",
    "addr:postcode":"v2m 1c8",
    "addr:street":"1St Ave",
    "iso:country":"CA",
    "sg:address":"4456 1st Ave",
    "sg:city":"Prince George",
    "sg:classifiers":[
        {
            "category":"Professional",
            "subcategory":"Accounting & Tax Preparation",
            "type":"Services"
        }
    ],
    "sg:phone":"+1 250 612 3846",
    "sg:postcode":"V2M 1C8",
    "sg:province":"BC",
    "sg:tags":[
        "accountant"
    ],
    "wof:name":"Spruce City Accounting & Fncl",
    "wof:placetype":"venue"
},
  "geometry": {"coordinates":[-122.808464,53.927895],"type":"Point"}
}