{
  "type": "Feature",
  "properties": {
    "addr:full":"58 Broadway St Tillsonburg ON N4G 3P3",
    "addr:housenumber":"58",
    "addr:postcode":"n4g 3p3",
    "addr:street":"Broadway St",
    "iso:country":"CA",
    "sg:address":"58 Broadway St",
    "sg:city":"Tillsonburg",
    "sg:classifiers":[
        {
            "category":"Freight",
            "type":"Transportation"
        }
    ],
    "sg:phone":"+1 519 688 3464",
    "sg:postcode":"N4G 3P3",
    "sg:province":"ON",
    "sg:tags":[
        "courier"
    ],
    "wof:name":"Home Sweet Home",
    "wof:placetype":"venue"
},
  "geometry": {"coordinates":[-80.72576100000001,42.858898],"type":"Point"}
}