{
  "type": "Feature",
  "properties": {
    "addr:full":"1031 Toy Ave Pickering ON L1W 3N9",
    "addr:housenumber":"1031",
    "addr:postcode":"l1w 3n9",
    "addr:street":"Toy Ave",
    "iso:country":"CA",
    "sg:address":"1031 Toy Ave",
    "sg:city":"Pickering",
    "sg:classifiers":[
        {
            "category":"Retail",
            "subcategory":"Auto Repair",
            "type":"Services"
        }
    ],
    "sg:phone":"+1 905 428 9007",
    "sg:postcode":"L1W 3N9",
    "sg:province":"ON",
    "sg:tags":[
        "repairing",
        "automobile"
    ],
    "wof:name":"Amogenx Auto Inc",
    "wof:placetype":"venue"
},
  "geometry": {"coordinates":[-79.06547500000001,43.835243],"type":"Point"}
}