{
  "type": "Feature",
  "properties": {
    "addr:full":"221 Av Laurier O Montreal QC H2T 2N9",
    "addr:housenumber":"221",
    "addr:postcode":"h2t 2n9",
    "addr:street":"Av Laurier O",
    "iso:country":"CA",
    "sg:address":"221 Av Laurier O",
    "sg:city":"Montreal",
    "sg:classifiers":[
        {
            "category":"Personal",
            "subcategory":"Beauty Salon",
            "type":"Services"
        }
    ],
    "sg:phone":"+1 514 271 6333",
    "sg:postcode":"H2T 2N9",
    "sg:province":"QC",
    "wof:name":"Orbite Coupe Beaute Cosmetique",
    "wof:placetype":"venue"
},
  "geometry": {"coordinates":[-73.59098815919999,45.5253944397],"type":"Point"}
}