{
  "type": "Feature",
  "properties": {
    "addr:full":"Timmins ON P4N 7C3",
    "addr:postcode":"p4n 7c3",
    "iso:country":"CA",
    "sg:city":"Timmins",
    "sg:classifiers":[
        {
            "category":"Building & Trades",
            "subcategory":"Electrical",
            "type":"Services"
        }
    ],
    "sg:phone":"+1 705 267 7694",
    "sg:postcode":"P4N 7C3",
    "sg:province":"ON",
    "sg:tags":[
        "electric",
        "contractor"
    ],
    "wof:name":"Accurate Electric",
    "wof:placetype":"venue"
},
  "geometry": {"coordinates":[-81.31004299999999,48.523438],"type":"Point"}
}