{
  "type": "Feature",
  "properties": {
    "iso:country":"CA",
    "sg:address":"6405 Knight St",
    "sg:city":"Vancouver",
    "sg:classifiers":[
        {
            "category":"Health Services",
            "subcategory":"Doctor",
            "type":"Services"
        }
    ],
    "sg:phone":"+1 604 301 2227",
    "sg:postcode":"V5P 2V9",
    "sg:province":"BC",
    "sg:tags":[
        "clinic"
    ],
    "wof:name":"Knight Street Youth Clinic",
    "wof:placetype":"venue"
},
  "geometry": {"coordinates":[-123.077453613,49.2263183594],"type":"Point"}
}