{
  "type": "Feature",
  "properties": {
    "addr:full":"402 Brady St Sudbury ON P3B 2P6",
    "addr:housenumber":"402",
    "addr:postcode":"p3b 2p6",
    "addr:street":"Brady St",
    "iso:country":"CA",
    "sg:address":"402 Brady St",
    "sg:city":"Sudbury",
    "sg:classifiers":[
        {
            "category":"Social Services",
            "type":"Services"
        }
    ],
    "sg:phone":"+1 705 675 1179",
    "sg:postcode":"P3B 2P6",
    "sg:province":"ON",
    "sg:tags":[
        "organization",
        "welfare"
    ],
    "wof:name":"Rockhaven",
    "wof:placetype":"venue"
},
  "geometry": {"coordinates":[-80.9859924316,46.4922866821],"type":"Point"}
}