{
  "type": "Feature",
  "properties": {
    "iso:country":"CA",
    "sg:address":"45 Rue Principale",
    "sg:city":"Frelighsburg",
    "sg:classifiers":[
        {
            "category":"Retail",
            "subcategory":"Auto Repair",
            "type":"Services"
        }
    ],
    "sg:phone":"+1 450 298 5236",
    "sg:postcode":"J0J 1C0",
    "sg:province":"QC",
    "sg:tags":[
        "repairing",
        "automobile"
    ],
    "wof:name":"Garage Daniel Bessette",
    "wof:placetype":"venue"
},
  "geometry": {"coordinates":[-72.83858499999999,45.053238],"type":"Point"}
}