{
  "type": "Feature",
  "properties": {
    "addr:full":"828 Rue Le Premont Sainte-Foy QC G1X 3B2",
    "addr:housenumber":"828",
    "addr:postcode":"g1x 3b2",
    "addr:street":"Rue Le Premont",
    "iso:country":"CA",
    "sg:address":"828 Rue Le Premont",
    "sg:city":"Sainte-Foy",
    "sg:classifiers":[
        {
            "category":"Banks & Credit Unions",
            "subcategory":"Bank",
            "type":"Services"
        }
    ],
    "sg:phone":"+1 418 564 3472",
    "sg:postcode":"G1X 3B2",
    "sg:province":"QC",
    "sg:tags":[
        "loan",
        "real estate"
    ],
    "wof:name":"Stastny Zdenek",
    "wof:placetype":"venue"
},
  "geometry": {"coordinates":[-71.31652800000001,46.771156],"type":"Point"}
}