{
  "type": "Feature",
  "properties": {
    "iso:country":"CA",
    "sg:address":"828 Rue Le Premont",
    "sg:city":"Sainte-Foy",
    "sg:classifiers":[
        {
            "category":"Banks & Credit Unions",
            "subcategory":"Bank",
            "type":"Services"
        }
    ],
    "sg:phone":"+1 418 564 3472",
    "sg:postcode":"G1X 3B2",
    "sg:province":"QC",
    "sg:tags":[
        "loan",
        "real estate"
    ],
    "wof:name":"Stastny Zdenek",
    "wof:placetype":"venue"
},
  "geometry": {"coordinates":[-71.316528,46.771156],"type":"Point"}
}