{
  "type": "Feature",
  "properties": {
    "addr:full":"595 Frederick St Kitchener ON N2B 2A8",
    "addr:housenumber":"595",
    "addr:postcode":"n2b 2a8",
    "addr:street":"Frederick St",
    "iso:country":"CA",
    "sg:address":"595 Frederick St",
    "sg:city":"Kitchener",
    "sg:classifiers":[
        {
            "category":"Shopping",
            "subcategory":"Gifts & Souvenirs",
            "type":"Retail Goods"
        }
    ],
    "sg:phone":"+1 519 570 3232",
    "sg:postcode":"N2B 2A8",
    "sg:province":"ON",
    "sg:tags":[
        "equipment",
        "party",
        "camping",
        "supply"
    ],
    "wof:name":"Tent Works",
    "wof:placetype":"venue"
},
  "geometry": {"coordinates":[-80.467438,43.459965],"type":"Point"}
}