{
  "type": "Feature",
  "properties": {
    "addr:full":"4879 Main St Vancouver BC V5V 3R9",
    "addr:housenumber":"4879",
    "addr:postcode":"v5v 3r9",
    "addr:street":"Main St",
    "iso:country":"CA",
    "sg:address":"4879 Main St",
    "sg:city":"Vancouver",
    "sg:classifiers":[
        {
            "category":"Retail",
            "subcategory":"Repair Shop",
            "type":"Services"
        }
    ],
    "sg:phone":"+1 604 874 5600",
    "sg:postcode":"V5V 3R9",
    "sg:province":"BC",
    "sg:tags":[
        "appliance"
    ],
    "wof:name":"Amco Appliance Svc",
    "wof:placetype":"venue"
},
  "geometry": {"coordinates":[-123.101585,49.240929],"type":"Point"}
}