{
  "type": "Feature",
  "properties": {
    "addr:full":"1935 Whittington Dr Peterborough ON K9J 6X4",
    "addr:housenumber":"1935",
    "addr:postcode":"k9j 6x4",
    "addr:street":"Whittington Dr",
    "iso:country":"CA",
    "sg:address":"1935 Whittington Dr",
    "sg:city":"Peterborough",
    "sg:classifiers":[
        {
            "category":"Professional",
            "subcategory":"Business Services",
            "type":"Services"
        }
    ],
    "sg:phone":"+1 705 742 7839",
    "sg:postcode":"K9J 6X4",
    "sg:province":"ON",
    "sg:tags":[
        "recording",
        "studio"
    ],
    "wof:name":"Haggarty Sound Studio",
    "wof:placetype":"venue"
},
  "geometry": {"coordinates":[-78.3659210205,44.2635917664],"type":"Point"}
}