{
  "type": "Feature",
  "properties": {
    "addr:full":"Langley BC V2Y 2E3",
    "addr:postcode":"v2y 2e3",
    "iso:country":"CA",
    "sg:city":"Langley",
    "sg:classifiers":[
        {
            "category":"Food & Beverages",
            "subcategory":"Fruits & Vegetables",
            "type":"Retail Goods"
        }
    ],
    "sg:phone":"+1 604 533 8828",
    "sg:postcode":"V2Y 2E3",
    "sg:province":"BC",
    "sg:tags":[
        "produce"
    ],
    "wof:name":"Willowbrook Produce Ltd",
    "wof:placetype":"venue"
},
  "geometry": {"coordinates":[-122.67482,49.117805],"type":"Point"}
}