{
  "type": "Feature",
  "properties": {
    "addr:full":"4795 Rue Sainte-Catherine O # 203 Westmount QC H3Z 1S8",
    "addr:housenumber":"4795",
    "addr:postcode":"h3z 1s8",
    "addr:street":"Rue Sainte-Catherine O # 203",
    "iso:country":"CA",
    "sg:address":"4795 Rue Sainte-Catherine O # 203",
    "sg:city":"Westmount",
    "sg:classifiers":[
        {
            "category":"Manufacturing",
            "subcategory":"Printing",
            "type":"Manufacturing & Wholesale Goods"
        }
    ],
    "sg:phone":"+1 514 931 1114",
    "sg:postcode":"H3Z 1S8",
    "sg:province":"QC",
    "sg:tags":[
        "production",
        "video",
        "multimedia",
        "taping"
    ],
    "wof:name":"Video Activ Productions Inc",
    "wof:placetype":"venue"
},
  "geometry": {"coordinates":[-73.597595,45.47802],"type":"Point"}
}