{
  "type": "Feature",
  "properties": {
    "addr:full":"55 Corley Ave Toronto ON M4E 1T8",
    "addr:housenumber":"55",
    "addr:postcode":"m4e 1t8",
    "addr:street":"Corley Ave",
    "iso:country":"CA",
    "sg:address":"55 Corley Ave",
    "sg:city":"Toronto",
    "sg:classifiers":[
        {
            "category":"Education",
            "subcategory":"School",
            "type":"Public Place"
        }
    ],
    "sg:phone":"+1 416 393 1700",
    "sg:postcode":"M4E 1T8",
    "sg:province":"ON",
    "wof:name":"Norway Junior Public School",
    "wof:placetype":"venue"
},
  "geometry": {"coordinates":[-79.3054275513,43.6770744324],"type":"Point"}
}