{
  "type": "Feature",
  "properties": {
    "addr:full":"3114 Cornwallis Cres Coldbrook NS B4R 1A2",
    "addr:housenumber":"3114",
    "addr:postcode":"b4r 1a2",
    "addr:street":"Cornwallis Cres",
    "iso:country":"CA",
    "sg:address":"3114 Cornwallis Cres",
    "sg:city":"Coldbrook",
    "sg:classifiers":[
        {
            "category":"Wholesale",
            "subcategory":"Construction Materials",
            "type":"Manufacturing & Wholesale Goods"
        }
    ],
    "sg:phone":"+1 902 679 1958",
    "sg:postcode":"B4R 1A2",
    "sg:province":"NS",
    "sg:tags":[
        "fence"
    ],
    "wof:name":"Annic Enterprises",
    "wof:placetype":"venue"
},
  "geometry": {"coordinates":[-64.56662,45.069038],"type":"Point"}
}