{
  "type": "Feature",
  "properties": {
    "addr:full":"78 Mason Beach Rd Lunenburg NS B0J 2C0",
    "addr:housenumber":"78",
    "addr:postcode":"b0j 2c0",
    "addr:street":"Mason Beach Rd",
    "iso:country":"CA",
    "sg:address":"78 Mason Beach Rd",
    "sg:city":"Lunenburg",
    "sg:classifiers":[
        {
            "category":"Health Services",
            "subcategory":"Doctor",
            "type":"Services"
        }
    ],
    "sg:phone":"+1 902 634 1951",
    "sg:postcode":"B0J 2C0",
    "sg:province":"NS",
    "sg:tags":[
        "physician",
        "surgeon"
    ],
    "wof:name":"Wilson, Diane MD",
    "wof:placetype":"venue"
},
  "geometry": {"coordinates":[-64.3172,44.371071],"type":"Point"}
}