{
  "type": "Feature",
  "properties": {
    "addr:full":"3131 Lake Shore Blvd W Etobicoke ON M8V 3W8",
    "addr:housenumber":"3131",
    "addr:postcode":"m8v 3w8",
    "addr:street":"Lake Shore Blvd W",
    "iso:country":"CA",
    "sg:address":"3131 Lake Shore Blvd W",
    "sg:city":"Etobicoke",
    "sg:classifiers":[
        {
            "category":"Social Services",
            "type":"Services"
        }
    ],
    "sg:phone":"+1 416 255 5900",
    "sg:postcode":"M8V 3W8",
    "sg:province":"ON",
    "sg:tags":[
        "assault",
        "abuse",
        "welfare",
        "organization",
        "sexual",
        "crisis"
    ],
    "wof:name":"Gatehouse",
    "wof:placetype":"venue"
},
  "geometry": {"coordinates":[-79.51512146,43.5985145569],"type":"Point"}
}