{
  "type": "Feature",
  "properties": {
    "addr:full":"33 Densley Ave North York ON M6M 2P5",
    "addr:housenumber":"33",
    "addr:postcode":"m6m 2p5",
    "addr:street":"Densley Ave",
    "iso:country":"CA",
    "sg:address":"33 Densley Ave",
    "sg:city":"North York",
    "sg:classifiers":[
        {
            "category":"Building & Trades",
            "subcategory":"Construction",
            "type":"Services"
        }
    ],
    "sg:phone":"+1 416 245 1800",
    "sg:postcode":"M6M 2P5",
    "sg:province":"ON",
    "sg:tags":[
        "woodworker"
    ],
    "wof:name":"Maia Custom Woodwork",
    "wof:placetype":"venue"
},
  "geometry": {"coordinates":[-79.4734954834,43.7034873962],"type":"Point"}
}