{
  "type": "Feature",
  "properties": {
    "iso:country":"CA",
    "sg:city":"Thompson",
    "sg:classifiers":[
        {
            "category":"Cinema",
            "subcategory":"Movie Rental",
            "type":"Entertainment"
        }
    ],
    "sg:phone":"+1 204 677 3174",
    "sg:postcode":"R8N 0M7",
    "sg:province":"MB",
    "sg:tags":[
        "video",
        "game",
        "tape",
        "leasing"
    ],
    "wof:name":"Blockbuster Video Canada Ltd",
    "wof:placetype":"venue"
},
  "geometry": {"coordinates":[-97.85433197019999,55.7419013977],"type":"Point"}
}