{
  "type": "Feature",
  "properties": {
    "addr:full":"123 King St W Hamilton ON L8P 4S8",
    "addr:housenumber":"123",
    "addr:postcode":"l8p 4s8",
    "addr:street":"King St W",
    "iso:country":"CA",
    "sg:address":"123 King St W",
    "sg:city":"Hamilton",
    "sg:classifiers":[
        {
            "category":"Museum",
            "type":"Entertainment"
        }
    ],
    "sg:phone":"+1 905 527 6610",
    "sg:postcode":"L8P 4S8",
    "sg:province":"ON",
    "sg:tags":[
        "art",
        "gallery",
        "dealer"
    ],
    "wof:name":"Art Gallery of Hamilton",
    "wof:placetype":"venue"
},
  "geometry": {"coordinates":[-79.872383,43.257427],"type":"Point"}
}