{
  "type": "Feature",
  "properties": {
    "addr:full":"1505 Ch Gascon Terrebonne QC J6X 2Z6",
    "addr:housenumber":"1505",
    "addr:postcode":"j6x 2z6",
    "addr:street":"Ch Gascon",
    "iso:country":"CA",
    "sg:address":"1505 Ch Gascon",
    "sg:city":"Terrebonne",
    "sg:classifiers":[
        {
            "category":"Sports & Exercise",
            "subcategory":"Gym",
            "type":"Entertainment"
        }
    ],
    "sg:phone":"+1 450 964 7177",
    "sg:postcode":"J6X 2Z6",
    "sg:province":"QC",
    "sg:tags":[
        "club",
        "health",
        "studio",
        "gymnasium"
    ],
    "wof:name":"Nautilus Plus Inc",
    "wof:placetype":"venue"
},
  "geometry": {"coordinates":[-73.65303,45.712162],"type":"Point"}
}