{
  "type": "Feature",
  "properties": {
    "iso:country":"CA",
    "sg:address":"780 Lahakas Blvd S",
    "sg:city":"Kitimat",
    "sg:classifiers":[
        {
            "category":"Retail",
            "subcategory":"Auto Repair",
            "type":"Services"
        }
    ],
    "sg:phone":"+1 250 632 7388",
    "sg:postcode":"V8C 1T9",
    "sg:province":"BC",
    "sg:tags":[
        "fuel",
        "automobile",
        "conversion"
    ],
    "wof:name":"Farwest Fuels",
    "wof:placetype":"venue"
},
  "geometry": {"coordinates":[-128.65623474099999,54.0535392761],"type":"Point"}
}