{
  "type": "Feature",
  "properties": {
    "addr:full":"Scarborough ON M1P 3B3",
    "addr:postcode":"m1p 3b3",
    "iso:country":"CA",
    "sg:city":"Scarborough",
    "sg:classifiers":[
        {
            "category":"Manufacturing",
            "subcategory":"Tools & Machinery",
            "type":"Manufacturing & Wholesale Goods"
        }
    ],
    "sg:phone":"+1 416 750 0222",
    "sg:postcode":"M1P 3B3",
    "sg:province":"ON",
    "sg:tags":[
        "machine",
        "shop"
    ],
    "wof:name":"Eme Technologies Inc",
    "wof:placetype":"venue"
},
  "geometry": {"coordinates":[-79.269424,43.756439],"type":"Point"}
}