{
  "type": "Feature",
  "properties": {
    "addr:full":"58 Second Ave Grand Falls-Windsor NL A2B 1B5",
    "addr:housenumber":"58",
    "addr:postcode":"a2b 1b5",
    "addr:street":"Second Ave",
    "iso:country":"CA",
    "sg:address":"58 Second Ave",
    "sg:city":"Grand Falls-Windsor",
    "sg:classifiers":[
        {
            "category":"Organizations",
            "subcategory":"Religious Organization",
            "type":"Services"
        }
    ],
    "sg:phone":"+1 709 489 6855",
    "sg:postcode":"A2B 1B5",
    "sg:province":"NL",
    "sg:tags":[
        "church"
    ],
    "wof:name":"Church of Jesus Christ-Lds",
    "wof:placetype":"venue"
},
  "geometry": {"coordinates":[-55.6728744507,48.9522895813],"type":"Point"}
}