{
  "type": "Feature",
  "properties": {
    "addr:full":"540 5 Ave SW #1600 Calgary AB T2P 0M2",
    "addr:housenumber":"540",
    "addr:postcode":"t2p 0m2",
    "addr:street":"5 Ave Sw # 1600",
    "iso:country":"CA",
    "sg:address":"540 5 Ave SW #1600",
    "sg:city":"Calgary",
    "sg:classifiers":[
        {
            "category":"Mining & Drilling",
            "type":"Manufacturing & Wholesale Goods"
        }
    ],
    "sg:phone":"+1 403 264 4020",
    "sg:postcode":"T2P 0M2",
    "sg:province":"AB",
    "sg:tags":[
        "field",
        "oil"
    ],
    "wof:name":"Den-Ray Rat Hole Drilling Ltd",
    "wof:placetype":"venue"
},
  "geometry": {"coordinates":[-114.072364807,51.0487632751],"type":"Point"}
}