{
  "type": "Feature",
  "properties": {
    "addr:full":"91 Clairmont St Mahone Bay NS B0J 2E0",
    "addr:housenumber":"91",
    "addr:postcode":"b0j 2e0",
    "addr:street":"Clairmont St",
    "iso:country":"CA",
    "sg:address":"91 Clairmont St",
    "sg:city":"Mahone Bay",
    "sg:classifiers":[
        {
            "category":"Recreation",
            "type":"Entertainment"
        }
    ],
    "sg:phone":"+1 902 624 6193",
    "sg:postcode":"B0J 2E0",
    "sg:province":"NS",
    "sg:tags":[
        "pool",
        "swimming"
    ],
    "wof:name":"Mahone Bay Swimming Pool",
    "wof:placetype":"venue"
},
  "geometry": {"coordinates":[-64.38215599999999,44.448479],"type":"Point"}
}