{
  "type": "Feature",
  "properties": {
    "iso:country":"CA",
    "sg:city":"Haliburton",
    "sg:classifiers":[
        {
            "category":"Building & Trades",
            "subcategory":"Construction",
            "type":"Services"
        }
    ],
    "sg:phone":"+1 705 457 3837",
    "sg:postcode":"K0M 1S0",
    "sg:province":"ON",
    "sg:tags":[
        "home",
        "improvement"
    ],
    "wof:name":"G J Burtch Construction Ltd",
    "wof:placetype":"venue"
},
  "geometry": {"coordinates":[-78.4982757568,45.0487785339],"type":"Point"}
}