{
  "type": "Feature",
  "properties": {
    "addr:full":"290 Laura St Winnipeg MB R3A 1C5",
    "addr:housenumber":"290",
    "addr:postcode":"r3a 1c5",
    "addr:street":"Laura St",
    "iso:country":"CA",
    "sg:address":"290 Laura St",
    "sg:city":"Winnipeg",
    "sg:classifiers":[
        {
            "category":"Building & Trades",
            "subcategory":"Construction",
            "type":"Services"
        }
    ],
    "sg:phone":"+1 204 943 2120",
    "sg:postcode":"R3A 1C5",
    "sg:province":"MB",
    "sg:tags":[
        "elevator"
    ],
    "wof:name":"Inter-City Elevator Inc",
    "wof:placetype":"venue"
},
  "geometry": {"coordinates":[-97.1442565918,49.9054450989],"type":"Point"}
}