{
  "type": "Feature",
  "properties": {
    "addr:full":"208 John St Belleville ON K8N 3G1",
    "addr:housenumber":"208",
    "addr:postcode":"k8n 3g1",
    "addr:street":"John St",
    "iso:country":"CA",
    "sg:address":"208 John St",
    "sg:city":"Belleville",
    "sg:classifiers":[
        {
            "category":"Health Services",
            "subcategory":"Health Practitioner",
            "type":"Services"
        }
    ],
    "sg:phone":"+1 613 966 4262",
    "sg:postcode":"K8N 3G1",
    "sg:province":"ON",
    "sg:tags":[
        "psychologist",
        "counselor",
        "marriage",
        "family"
    ],
    "wof:name":"Mourelatos, Eva PhD",
    "wof:placetype":"venue"
},
  "geometry": {"coordinates":[-77.3797988892,44.1648674011],"type":"Point"}
}