{
  "type": "Feature",
  "properties": {
    "addr:full":"100 Pender St W # 200 Vancouver BC V6B 1R8",
    "addr:housenumber":"100",
    "addr:postcode":"v6b 1r8",
    "addr:street":"Pender St W # 200",
    "iso:country":"CA",
    "sg:address":"100 Pender St W # 200",
    "sg:city":"Vancouver",
    "sg:classifiers":[
        {
            "category":"Professional",
            "subcategory":"Lawyer & Legal Services",
            "type":"Services"
        }
    ],
    "sg:phone":"+1 604 688 8588",
    "sg:postcode":"V6B 1R8",
    "sg:province":"BC",
    "sg:tags":[
        "attorney"
    ],
    "wof:name":"Brian E Mickelson Law Corp",
    "wof:placetype":"venue"
},
  "geometry": {"coordinates":[-123.10779599999999,49.281048],"type":"Point"}
}