{
  "type": "Feature",
  "properties": {
    "iso:country":"CA",
    "sg:city":"Oakville",
    "sg:classifiers":[
        {
            "category":"Professional",
            "subcategory":"Business Services",
            "type":"Services"
        }
    ],
    "sg:phone":"+1 905 815 1272",
    "sg:postcode":"L6K 3L1",
    "sg:province":"ON",
    "sg:tags":[
        "fund",
        "promotion",
        "marketing",
        "raising",
        "consultant"
    ],
    "wof:name":"P M Promo",
    "wof:placetype":"venue"
},
  "geometry": {"coordinates":[-79.67683410639999,43.4447021484],"type":"Point"}
}