{
  "type": "Feature",
  "properties": {
    "addr:full":"11440 5E Av Montreal QC H1E 1R1",
    "addr:housenumber":"11440",
    "addr:postcode":"h1e 1r1",
    "addr:street":"5E Av",
    "iso:country":"CA",
    "sg:address":"11440 5E Av",
    "sg:city":"Montreal",
    "sg:classifiers":[
        {
            "category":"Retail",
            "subcategory":"Auto Repair",
            "type":"Services"
        }
    ],
    "sg:phone":"+1 514 881 1702",
    "sg:postcode":"H1E 1R1",
    "sg:province":"QC",
    "sg:tags":[
        "repairing",
        "automobile"
    ],
    "wof:name":"Garage Hispano Enr",
    "wof:placetype":"venue"
},
  "geometry": {"coordinates":[-73.597122,45.618763],"type":"Point"}
}