{
  "type": "Feature",
  "properties": {
    "addr:full":"50 Wanaki Mikan Ch Maniwaki QC J9E 3B3",
    "addr:housenumber":"50",
    "addr:postcode":"j9e 3b3",
    "addr:street":"Wanaki Mikan Ch",
    "iso:country":"CA",
    "sg:address":"50 Wanaki Mikan Ch",
    "sg:city":"Maniwaki",
    "sg:classifiers":[
        {
            "category":"Organizations",
            "subcategory":"Non-profit Organization",
            "type":"Services"
        }
    ],
    "sg:phone":"+1 819 449 7000",
    "sg:postcode":"J9E 3B3",
    "sg:province":"QC",
    "sg:tags":[
        "info",
        "addiction",
        "abuse",
        "treatment",
        "drug"
    ],
    "wof:name":"Wanaki Center",
    "wof:placetype":"venue"
},
  "geometry": {"coordinates":[-75.9815979004,46.3746795654],"type":"Point"}
}