{
  "type": "Feature",
  "properties": {
    "addr:full":"37 Ch Laurier Saint-Norbert-D'Arthabaska QC G0P 1B0",
    "addr:housenumber":"37",
    "addr:postcode":"g0p 1b0",
    "addr:street":"Ch Laurier",
    "iso:country":"CA",
    "sg:address":"37 Ch Laurier",
    "sg:city":"Saint-Norbert-D'Arthabaska",
    "sg:classifiers":[
        {
            "category":"Autos & Motor Vehicles",
            "subcategory":"Automobile Sales",
            "type":"Retail Goods"
        }
    ],
    "sg:phone":"+1 819 369 9309",
    "sg:postcode":"G0P 1B0",
    "sg:province":"QC",
    "sg:tags":[
        "car",
        "dealer"
    ],
    "wof:name":"Garage Jean Louis Martel Inc",
    "wof:placetype":"venue"
},
  "geometry": {"coordinates":[-71.88677199999999,46.066605],"type":"Point"}
}