{
  "type": "Feature",
  "properties": {
    "addr:full":"4955 Av DE Courtrai Montreal QC H3W 1A6",
    "addr:housenumber":"4955",
    "addr:postcode":"h3w 1a6",
    "addr:street":"Av De Courtrai",
    "iso:country":"CA",
    "sg:address":"4955 Av DE Courtrai",
    "sg:city":"Montreal",
    "sg:classifiers":[
        {
            "category":"Manufacturing",
            "subcategory":"Tools & Machinery",
            "type":"Manufacturing & Wholesale Goods"
        }
    ],
    "sg:phone":"+1 514 871 9999",
    "sg:postcode":"H3W 1A6",
    "sg:province":"QC",
    "sg:tags":[
        "ventilating",
        "fan"
    ],
    "wof:name":"M K Plastics Corp",
    "wof:placetype":"venue"
},
  "geometry": {"coordinates":[-73.64724699999999,45.495869],"type":"Point"}
}