{
  "type": "Feature",
  "properties": {
    "iso:country":"CA",
    "sg:address":"4955 Av DE Courtrai",
    "sg:city":"Montreal",
    "sg:classifiers":[
        {
            "category":"Manufacturing",
            "subcategory":"Tools & Machinery",
            "type":"Manufacturing & Wholesale Goods"
        }
    ],
    "sg:phone":"+1 514 871 9999",
    "sg:postcode":"H3W 1A6",
    "sg:province":"QC",
    "sg:tags":[
        "ventilating",
        "fan"
    ],
    "wof:name":"M K Plastics Corp",
    "wof:placetype":"venue"
},
  "geometry": {"coordinates":[-73.647247,45.495869],"type":"Point"}
}