{
  "type": "Feature",
  "properties": {
    "addr:full":"4365 Blue Grouse Rd Duncan BC V9L 6M3",
    "addr:housenumber":"4365",
    "addr:postcode":"v9l 6m3",
    "addr:street":"Blue Grouse Rd",
    "iso:country":"CA",
    "sg:address":"4365 Blue Grouse Rd",
    "sg:city":"Duncan",
    "sg:classifiers":[
        {
            "category":"Manufacturing",
            "subcategory":"Food",
            "type":"Manufacturing & Wholesale Goods"
        }
    ],
    "sg:phone":"+1 250 743 3834",
    "sg:postcode":"V9L 6M3",
    "sg:province":"BC",
    "sg:tags":[
        "winery"
    ],
    "wof:name":"Blue Grouse Vineyards",
    "wof:placetype":"venue"
},
  "geometry": {"coordinates":[-123.707382,48.779095],"type":"Point"}
}