{
  "type": "Feature",
  "properties": {
    "addr:full":"23 Foresthill Rd Corner Brook NL A2H 6G1",
    "addr:housenumber":"23",
    "addr:postcode":"a2h 6g1",
    "addr:street":"Foresthill Rd",
    "iso:country":"CA",
    "sg:address":"23 Foresthill Rd",
    "sg:city":"Corner Brook",
    "sg:classifiers":[
        {
            "category":"Wholesale",
            "subcategory":"Auto Parts",
            "type":"Manufacturing & Wholesale Goods"
        }
    ],
    "sg:phone":"+1 709 634 0044",
    "sg:postcode":"A2H 6G1",
    "sg:province":"NL",
    "sg:tags":[
        "equipment",
        "truck"
    ],
    "wof:name":"Parts For Trucks Inc",
    "wof:placetype":"venue"
},
  "geometry": {"coordinates":[-57.9196243286,48.9537506104],"type":"Point"}
}