{
  "type": "Feature",
  "properties": {
    "addr:full":"2 Rue DE L'Entente Levis QC G6V 1R2",
    "addr:housenumber":"2",
    "addr:postcode":"g6v 1r2",
    "addr:street":"Rue De L'Entente",
    "iso:country":"CA",
    "sg:address":"2 Rue DE L'Entente",
    "sg:city":"Levis",
    "sg:classifiers":[
        {
            "category":"Education",
            "subcategory":"School",
            "type":"Public Place"
        }
    ],
    "sg:phone":"+1 418 838 8545",
    "sg:postcode":"G6V 1R2",
    "sg:province":"QC",
    "wof:name":"St Dominique Ecoles Primaires",
    "wof:placetype":"venue"
},
  "geometry": {"coordinates":[-71.17673499999999,46.817554],"type":"Point"}
}