{
  "type": "Feature",
  "properties": {
    "iso:country":"CA",
    "sg:address":"2 Rue DE L'Entente",
    "sg:city":"Levis",
    "sg:classifiers":[
        {
            "category":"Education",
            "subcategory":"School",
            "type":"Public Place"
        }
    ],
    "sg:phone":"+1 418 838 8545",
    "sg:postcode":"G6V 1R2",
    "sg:province":"QC",
    "wof:name":"St Dominique Ecoles Primaires",
    "wof:placetype":"venue"
},
  "geometry": {"coordinates":[-71.176735,46.817554],"type":"Point"}
}