{
  "type": "Feature",
  "properties": {
    "addr:full":"47 Main St Flin Flon MB R8A 1J7",
    "addr:housenumber":"47",
    "addr:postcode":"r8a 1j7",
    "addr:street":"Main St",
    "iso:country":"CA",
    "sg:address":"47 Main St",
    "sg:city":"Flin Flon",
    "sg:classifiers":[
        {
            "category":"Professional",
            "subcategory":"Lawyer & Legal Services",
            "type":"Services"
        }
    ],
    "sg:phone":"+1 204 687 8208",
    "sg:postcode":"R8A 1J7",
    "sg:province":"MB",
    "sg:tags":[
        "attorney"
    ],
    "wof:name":"Ginnell Bauman & Watt",
    "wof:placetype":"venue"
},
  "geometry": {"coordinates":[-101.875412,54.764946],"type":"Point"}
}