{
  "type": "Feature",
  "properties": {
    "addr:full":"1905 Danforth Ave Toronto ON M4C 1J5",
    "addr:housenumber":"1905",
    "addr:postcode":"m4c 1j5",
    "addr:street":"Danforth Ave",
    "iso:country":"CA",
    "sg:address":"1905 Danforth Ave",
    "sg:city":"Toronto",
    "sg:classifiers":[
        {
            "category":"Retail",
            "subcategory":"Veterinary Services",
            "type":"Services"
        }
    ],
    "sg:phone":"+1 416 699 1175",
    "sg:postcode":"M4C 1J5",
    "sg:province":"ON",
    "sg:tags":[
        "veterinarian"
    ],
    "wof:name":"Woodbine Animal Clinic",
    "wof:placetype":"venue"
},
  "geometry": {"coordinates":[-79.3164978027,43.6847381592],"type":"Point"}
}