{
  "type": "Feature",
  "properties": {
    "addr:full":"3674 Rue Principale Tracadie-Sheila NB E1X 1E2",
    "addr:housenumber":"3674",
    "addr:postcode":"e1x 1e2",
    "addr:street":"Rue Principale",
    "iso:country":"CA",
    "sg:address":"3674 Rue Principale",
    "sg:city":"Tracadie-Sheila",
    "sg:classifiers":[
        {
            "category":"Professional",
            "subcategory":"Lawyer & Legal Services",
            "type":"Services"
        }
    ],
    "sg:phone":"+1 506 395 0044",
    "sg:postcode":"E1X 1E2",
    "sg:province":"NB",
    "sg:tags":[
        "attorney"
    ],
    "wof:name":"Le Bouthillier, Euclide",
    "wof:placetype":"venue"
},
  "geometry": {"coordinates":[-64.9176864624,47.4913406372],"type":"Point"}
}