{
  "type": "Feature",
  "properties": {
    "iso:country":"CA",
    "sg:address":"11140 River Rd",
    "sg:city":"Richmond",
    "sg:classifiers":[
        {
            "category":"Manufacturing",
            "subcategory":"Building Materials",
            "type":"Manufacturing & Wholesale Goods"
        }
    ],
    "sg:phone":"+1 604 276 2855",
    "sg:postcode":"V6X 1Z5",
    "sg:province":"BC",
    "wof:name":"Trident Millwork & Display Ltd",
    "wof:placetype":"venue"
},
  "geometry": {"coordinates":[-123.10071563699999,49.1974906921],"type":"Point"}
}