{
  "type": "Feature",
  "properties": {
    "iso:country":"CA",
    "sg:address":"116 4th Ave SW",
    "sg:city":"Manning",
    "sg:classifiers":[
        {
            "category":"Professional",
            "subcategory":"Management & Consulting",
            "type":"Services"
        }
    ],
    "sg:phone":"+1 780 836 3354",
    "sg:postcode":"T0H 2M0",
    "sg:province":"AB",
    "sg:tags":[
        "agricultural",
        "consultant"
    ],
    "wof:name":"North Peace Applied Research",
    "wof:placetype":"venue"
},
  "geometry": {"coordinates":[-117.631576538,56.9214096069],"type":"Point"}
}