{
  "type": "Feature",
  "properties": {
    "addr:full":"34 Birch St E Chapleau ON P0M 1K0",
    "addr:housenumber":"34",
    "addr:postcode":"p0m 1k0",
    "addr:street":"Birch St E",
    "iso:country":"CA",
    "sg:address":"34 Birch St E",
    "sg:city":"Chapleau",
    "sg:classifiers":[
        {
            "category":"Banks & Credit Unions",
            "subcategory":"Bank",
            "type":"Services"
        }
    ],
    "sg:phone":"+1 705 864 1841",
    "sg:postcode":"P0M 1K0",
    "sg:province":"ON",
    "wof:name":"Northern Credit Union Ltd",
    "wof:placetype":"venue"
},
  "geometry": {"coordinates":[-83.40016199999999,47.843288],"type":"Point"}
}