{
  "type": "Feature",
  "properties": {
    "iso:country":"CA",
    "sg:city":"Mississauga",
    "sg:classifiers":[
        {
            "category":"Retail",
            "subcategory":"Repair Shop",
            "type":"Services"
        }
    ],
    "sg:phone":"+1 905 696 9244",
    "sg:postcode":"L5T 1K8",
    "sg:province":"ON",
    "sg:tags":[
        "pump"
    ],
    "wof:name":"Isoflow Engineered Products",
    "wof:placetype":"venue"
},
  "geometry": {"coordinates":[-79.6644287109,43.6513786316],"type":"Point"}
}