{
  "type": "Feature",
  "properties": {
    "addr:full":"514 Maryland St Winnipeg MB R3G 1M5",
    "addr:housenumber":"514",
    "addr:postcode":"r3g 1m5",
    "addr:street":"Maryland St",
    "iso:country":"CA",
    "sg:address":"514 Maryland St",
    "sg:city":"Winnipeg",
    "sg:classifiers":[
        {
            "category":"Organizations",
            "subcategory":"Religious Organization",
            "type":"Services"
        }
    ],
    "sg:phone":"+1 204 775 4929",
    "sg:postcode":"R3G 1M5",
    "sg:province":"MB",
    "sg:tags":[
        "church"
    ],
    "wof:name":"New Life Ministries",
    "wof:placetype":"venue"
},
  "geometry": {"coordinates":[-97.16027800000001,49.894478],"type":"Point"}
}