{
  "type": "Feature",
  "properties": {
    "addr:full":"99 Mapleview Dr W Barrie ON L4N 9H7",
    "addr:housenumber":"99",
    "addr:postcode":"l4n 9h7",
    "addr:street":"Mapleview Dr W",
    "iso:country":"CA",
    "sg:address":"99 Mapleview Dr W",
    "sg:city":"Barrie",
    "sg:classifiers":[
        {
            "category":"Banks & Credit Unions",
            "subcategory":"Bank",
            "type":"Services"
        }
    ],
    "sg:phone":"+1 705 725 7830",
    "sg:postcode":"L4N 9H7",
    "sg:province":"ON",
    "wof:name":"Royal Bank Financial Group",
    "wof:placetype":"venue"
},
  "geometry": {"coordinates":[-79.69528961180001,44.3328781128],"type":"Point"}
}