{
  "type": "Feature",
  "properties": {
    "addr:full":"North Battleford SK S9A 3G4",
    "addr:postcode":"s9a 3g4",
    "iso:country":"CA",
    "sg:city":"North Battleford",
    "sg:classifiers":[
        {
            "category":"Real Estate",
            "subcategory":"Real Estate Operator",
            "type":"Services"
        }
    ],
    "sg:phone":"+1 306 445 8778",
    "sg:postcode":"S9A 3G4",
    "sg:province":"SK",
    "sg:tags":[
        "mobile",
        "home",
        "community"
    ],
    "wof:name":"North Battleford Heritage Ests",
    "wof:placetype":"venue"
},
  "geometry": {"coordinates":[-108.278030395,52.7765083313],"type":"Point"}
}