{
  "type": "Feature",
  "properties": {
    "addr:full":"100 3rd Ave E Shellbrook SK S0J 2E0",
    "addr:housenumber":"100",
    "addr:postcode":"s0j 2e0",
    "addr:street":"3Rd Ave E Shellbrook",
    "iso:country":"CA",
    "sg:address":"100 3rd Ave E",
    "sg:city":"Shellbrook",
    "sg:classifiers":[
        {
            "category":"Education",
            "subcategory":"School",
            "type":"Public Place"
        }
    ],
    "sg:phone":"+1 306 747 2588",
    "sg:postcode":"S0J 2E0",
    "sg:province":"SK",
    "wof:name":"Shellbrook Elementary School",
    "wof:placetype":"venue"
},
  "geometry": {"coordinates":[-106.379082,53.221207],"type":"Point"}
}