{
  "type": "Feature",
  "properties": {
    "addr:full":"293 Londonderry Mall NW # 4M Edmonton AB T5C 3C8",
    "addr:housenumber":"293;4m",
    "addr:postcode":"t5c 3c8",
    "addr:street":"Londonderry Mall Nw #",
    "iso:country":"CA",
    "sg:address":"293 Londonderry Mall NW # 4M",
    "sg:city":"Edmonton",
    "sg:classifiers":[
        {
            "category":"Shopping",
            "subcategory":"Clothing, Apparel, & Fashions",
            "type":"Retail Goods"
        }
    ],
    "sg:phone":"+1 780 476 3927",
    "sg:postcode":"T5C 3C8",
    "sg:province":"AB",
    "wof:name":"Garage Clothing CO",
    "wof:placetype":"venue"
},
  "geometry": {"coordinates":[-113.490371704,53.5462188721],"type":"Point"}
}