{
  "type": "Feature",
  "properties": {
    "addr:full":"Etobicoke ON M8X 1Y4",
    "addr:postcode":"m8x 1y4",
    "iso:country":"CA",
    "sg:city":"Etobicoke",
    "sg:classifiers":[
        {
            "category":"Insurance",
            "subcategory":"Insurance Agent",
            "type":"Services"
        }
    ],
    "sg:phone":"+1 416 234 8000",
    "sg:postcode":"M8X 1Y4",
    "sg:province":"ON",
    "wof:name":"State Farm Insurance CO",
    "wof:placetype":"venue"
},
  "geometry": {"coordinates":[-79.51084899999999,43.660343],"type":"Point"}
}