{
  "type": "Feature",
  "properties": {
    "addr:full":"17710 Rue Beaupre Becancour QC G9H 1V5",
    "addr:housenumber":"17710",
    "addr:postcode":"g9h 1v5",
    "addr:street":"Rue Beaupre Becancour",
    "iso:country":"CA",
    "sg:address":"17710 Rue Beaupre",
    "sg:city":"Becancour",
    "sg:classifiers":[
        {
            "category":"Professional",
            "subcategory":"Business Services",
            "type":"Services"
        }
    ],
    "sg:phone":"+1 819 233 9833",
    "sg:postcode":"G9H 1V5",
    "sg:province":"QC",
    "wof:name":"Griffe Originale Enr",
    "wof:placetype":"venue"
},
  "geometry": {"coordinates":[-72.53564453120001,46.2965011597],"type":"Point"}
}