{
  "type": "Feature",
  "properties": {
    "addr:full":"3337 Boul Taschereau Greenfield Park QC J4V 2H5",
    "addr:housenumber":"3337",
    "addr:postcode":"j4v 2h5",
    "addr:street":"Boul Taschereau",
    "iso:country":"CA",
    "sg:address":"3337 Boul Taschereau",
    "sg:city":"Greenfield Park",
    "sg:classifiers":[
        {
            "category":"Autos & Motor Vehicles",
            "subcategory":"Fuel & Gas Station",
            "type":"Retail Goods"
        }
    ],
    "sg:phone":"+1 450 926 3401",
    "sg:postcode":"J4V 2H5",
    "sg:province":"QC",
    "sg:tags":[
        "oil"
    ],
    "wof:name":"Shell Canada Ltee",
    "wof:placetype":"venue"
},
  "geometry": {"coordinates":[-73.48751068120001,45.5007972717],"type":"Point"}
}