{
  "type": "Feature",
  "properties": {
    "addr:full":"138 10th Ave N Creston BC V0B 1G0",
    "addr:housenumber":"138",
    "addr:postcode":"bc v0b 1g0",
    "addr:street":"10Th Ave N",
    "iso:country":"CA",
    "sg:address":"138 10th Ave N",
    "sg:city":"Creston",
    "sg:classifiers":[
        {
            "category":"Government",
            "subcategory":"Office",
            "type":"Public Place"
        }
    ],
    "sg:phone":"+1 250 428 3553",
    "sg:postcode":"V0B 1G0",
    "sg:province":"BC",
    "sg:tags":[
        "information",
        "treatment",
        "alcoholism"
    ],
    "wof:name":"Alcohol & Drug Counselling",
    "wof:placetype":"venue"
},
  "geometry": {"coordinates":[-116.51325199999999,49.095993],"type":"Point"}
}