{
  "type": "Feature",
  "properties": {
    "addr:full":"134 1st Ave E Ponteix SK S0N 1Z0",
    "addr:housenumber":"134",
    "addr:postcode":"s0n 1z0",
    "addr:street":"1St Ave E Ponteix",
    "iso:country":"CA",
    "sg:address":"134 1st Ave E",
    "sg:city":"Ponteix",
    "sg:classifiers":[
        {
            "category":"Education",
            "subcategory":"Library",
            "type":"Public Place"
        }
    ],
    "sg:phone":"+1 306 625 3353",
    "sg:postcode":"S0N 1Z0",
    "sg:province":"SK",
    "wof:name":"Chinook Regional Library",
    "wof:placetype":"venue"
},
  "geometry": {"coordinates":[-107.493972778,49.7460632324],"type":"Point"}
}