{
  "type": "Feature",
  "properties": {
    "addr:full":"41 Rivalda Rd North York ON M9M 2M4",
    "addr:housenumber":"41",
    "addr:postcode":"m9m 2m4",
    "addr:street":"Rivalda Rd",
    "iso:country":"CA",
    "sg:address":"41 Rivalda Rd",
    "sg:city":"North York",
    "sg:classifiers":[
        {
            "category":"Wholesale",
            "subcategory":"Electrical",
            "type":"Manufacturing & Wholesale Goods"
        }
    ],
    "sg:phone":"+1 416 742 6911",
    "sg:postcode":"M9M 2M4",
    "sg:province":"ON",
    "sg:tags":[
        "equipment",
        "electric"
    ],
    "wof:name":"Lineman's Testing Labs",
    "wof:placetype":"venue"
},
  "geometry": {"coordinates":[-79.53478200000001,43.737576],"type":"Point"}
}