{
  "type": "Feature",
  "properties": {
    "addr:full":"605 Hespeler Rd Cambridge ON N1R 6J3",
    "addr:housenumber":"605",
    "addr:postcode":"n1r 6j3",
    "addr:street":"Hespeler Rd",
    "iso:country":"CA",
    "sg:address":"605 Hespeler Rd",
    "sg:city":"Cambridge",
    "sg:classifiers":[
        {
            "category":"Restaurant",
            "type":"Food & Drink"
        }
    ],
    "sg:phone":"+1 519 621 9191",
    "sg:postcode":"N1R 6J3",
    "sg:province":"ON",
    "wof:name":"Archie's Bar & Grill",
    "wof:placetype":"venue"
},
  "geometry": {"coordinates":[-80.3266830444,43.4044113159],"type":"Point"}
}