{
  "type": "Feature",
  "properties": {
    "addr:full":"Thornbury ON N0H 2P0",
    "addr:postcode":"n0h 2p0",
    "iso:country":"CA",
    "sg:city":"Thornbury",
    "sg:classifiers":[
        {
            "category":"Retail",
            "subcategory":"Portrait Studio",
            "type":"Services"
        }
    ],
    "sg:phone":"+1 519 599 6195",
    "sg:postcode":"N0H 2P0",
    "sg:province":"ON",
    "sg:tags":[
        "photographer"
    ],
    "wof:name":"Robert Burcher Photography",
    "wof:placetype":"venue"
},
  "geometry": {"coordinates":[-80.450699,44.561565],"type":"Point"}
}