{
  "type": "Feature",
  "properties": {
    "addr:full":"Val-Barrette QC J0W 1Y0",
    "addr:postcode":"j0w 1y0",
    "iso:country":"CA",
    "sg:city":"Val-Barrette",
    "sg:classifiers":[
        {
            "category":"Restaurant",
            "type":"Food & Drink"
        }
    ],
    "sg:phone":"+1 819 585 2142",
    "sg:postcode":"J0W 1Y0",
    "sg:province":"QC",
    "wof:name":"Patate Frite Val Barrette",
    "wof:placetype":"venue"
},
  "geometry": {"coordinates":[-75.355484,46.507858],"type":"Point"}
}