{
  "type": "Feature",
  "properties": {
    "addr:full":"7328 Main St Louisbourg NS B1C 1P5",
    "addr:housenumber":"7328",
    "addr:postcode":"b1c 1p5",
    "addr:street":"Main St",
    "iso:country":"CA",
    "sg:address":"7328 Main St",
    "sg:city":"Louisbourg",
    "sg:classifiers":[
        {
            "category":"Travel",
            "subcategory":"Hotels & Motels",
            "type":"Entertainment"
        }
    ],
    "sg:phone":"+1 902 733 2122",
    "sg:postcode":"B1C 1P5",
    "sg:province":"NS",
    "sg:tags":[
        "cottage",
        "tours",
        "cabin",
        "sightseeing"
    ],
    "wof:name":"Lupine Tours",
    "wof:placetype":"venue"
},
  "geometry": {"coordinates":[-59.961338,45.926147],"type":"Point"}
}