{
  "type": "Feature",
  "properties": {
    "addr:full":"5315 50th Ave S Fort Nelson BC V0C 1R0",
    "addr:housenumber":"5315",
    "addr:postcode":"bc v0c 1r0",
    "addr:street":"50Th Ave S",
    "iso:country":"CA",
    "sg:address":"5315 50th Ave S",
    "sg:city":"Fort Nelson",
    "sg:classifiers":[
        {
            "category":"Education",
            "subcategory":"Library",
            "type":"Public Place"
        }
    ],
    "sg:phone":"+1 250 774 6777",
    "sg:postcode":"V0C 1R0",
    "sg:province":"BC",
    "wof:name":"Fort Nelson Public Library",
    "wof:placetype":"venue"
},
  "geometry": {"coordinates":[-122.706154,58.804295],"type":"Point"}
}