{
  "type": "Feature",
  "properties": {
    "iso:country":"CA",
    "sg:address":"Cedar",
    "sg:city":"Thorne",
    "sg:classifiers":[
        {
            "category":"Health Services",
            "subcategory":"Doctor",
            "type":"Services"
        }
    ],
    "sg:phone":"+1 705 981 9334",
    "sg:postcode":"P0H 2J0",
    "sg:province":"ON",
    "sg:tags":[
        "clinic"
    ],
    "wof:name":"Thorne Nursing Station",
    "wof:placetype":"venue"
},
  "geometry": {"coordinates":[-79.1020202637,46.7001533508],"type":"Point"}
}