{
  "type": "Feature",
  "properties": {
    "addr:full":"449 Norton Ave W Miami MB R0G 1H0",
    "addr:housenumber":"449",
    "addr:postcode":"r0g 1h0",
    "addr:street":"Norton Ave W",
    "iso:country":"CA",
    "sg:address":"449 Norton Ave W",
    "sg:city":"Miami",
    "sg:classifiers":[
        {
            "category":"Banks & Credit Unions",
            "subcategory":"Bank",
            "type":"Services"
        }
    ],
    "sg:phone":"+1 204 435 2468",
    "sg:postcode":"R0G 1H0",
    "sg:province":"MB",
    "wof:name":"Cibc",
    "wof:placetype":"venue"
},
  "geometry": {"coordinates":[-98.24341583250001,49.3710861206],"type":"Point"}
}