{
  "type": "Feature",
  "properties": {
    "addr:full":"223 St Clair Ave W Toronto ON M4V 1R3",
    "addr:housenumber":"223",
    "addr:postcode":"m4v 1r3",
    "addr:street":"St Clair Ave W",
    "iso:country":"CA",
    "sg:address":"223 St Clair Ave W",
    "sg:city":"Toronto",
    "sg:classifiers":[
        {
            "category":"Health Services",
            "subcategory":"Clinic",
            "type":"Services"
        }
    ],
    "sg:phone":"+1 416 960 1415",
    "sg:postcode":"M4V 1R3",
    "sg:province":"ON",
    "wof:name":"Izenberg, S O",
    "wof:placetype":"venue"
},
  "geometry": {"coordinates":[-79.40441894529999,43.68592453],"type":"Point"}
}