{
  "type": "Feature",
  "properties": {
    "iso:country":"CA",
    "sg:address":"SE 8 25 23",
    "sg:city":"Grandview",
    "sg:classifiers":[
        {
            "category":"Organizations",
            "subcategory":"Religious Organization",
            "type":"Services"
        }
    ],
    "sg:phone":"+1 204 546 2423",
    "sg:postcode":"R0L 0Y0",
    "sg:province":"MB",
    "sg:tags":[
        "church"
    ],
    "wof:name":"Grandview Mennonite Church",
    "wof:placetype":"venue"
},
  "geometry": {"coordinates":[-100.69960021999999,51.1684112549],"type":"Point"}
}