{
  "type": "Feature",
  "properties": {
    "addr:full":"17 Stanley St Miramichi NB E1N 2S7",
    "addr:housenumber":"17",
    "addr:postcode":"e1n 2s7",
    "addr:street":"Stanley St",
    "iso:country":"CA",
    "sg:address":"17 Stanley St",
    "sg:city":"Miramichi",
    "sg:classifiers":[
        {
            "category":"Building & Trades",
            "subcategory":"Construction",
            "type":"Services"
        }
    ],
    "sg:phone":"+1 506 622 8010",
    "sg:postcode":"E1N 2S7",
    "sg:province":"NB",
    "sg:tags":[
        "home",
        "improvement"
    ],
    "wof:name":"A-1 Siding",
    "wof:placetype":"venue"
},
  "geometry": {"coordinates":[-65.46645355219999,47.0281066895],"type":"Point"}
}