{
  "type": "Feature",
  "properties": {
    "addr:full":"6483 Kingston Rd Scarborough ON M1C 1L5",
    "addr:housenumber":"6483",
    "addr:postcode":"m1c 1l5",
    "addr:street":"Kingston Rd",
    "iso:country":"CA",
    "sg:address":"6483 Kingston Rd",
    "sg:city":"Scarborough",
    "sg:classifiers":[
        {
            "category":"Autos & Motor Vehicles",
            "subcategory":"Automobile Sales",
            "type":"Retail Goods"
        }
    ],
    "sg:phone":"+1 416 284 3581",
    "sg:postcode":"M1C 1L5",
    "sg:province":"ON",
    "sg:tags":[
        "car",
        "dealer"
    ],
    "wof:name":"Abram Motors",
    "wof:placetype":"venue"
},
  "geometry": {"coordinates":[-79.15615099999999,43.792419],"type":"Point"}
}