{
  "type": "Feature",
  "properties": {
    "addr:full":"382 Bear Point Rd Shelburne NS B0T 1W0",
    "addr:housenumber":"382",
    "addr:postcode":"b0t 1w0",
    "addr:street":"Bear Point Rd",
    "iso:country":"CA",
    "sg:address":"382 Bear Point Rd",
    "sg:city":"Shelburne",
    "sg:classifiers":[
        {
            "category":"Wholesale",
            "subcategory":"Seafood",
            "type":"Manufacturing & Wholesale Goods"
        }
    ],
    "sg:phone":"+1 902 723 0055",
    "sg:postcode":"B0T 1W0",
    "sg:province":"NS",
    "wof:name":"Corner Fisheries Ltd",
    "wof:placetype":"venue"
},
  "geometry": {"coordinates":[-65.31564299999999,43.765659],"type":"Point"}
}