{
  "type": "Feature",
  "properties": {
    "iso:country":"CA",
    "sg:address":"70 Rue DE LA Barre # 703",
    "sg:city":"Longueuil",
    "sg:classifiers":[
        {
            "category":"Professional",
            "subcategory":"Management & Consulting",
            "type":"Services"
        }
    ],
    "sg:phone":"+1 450 674 1589",
    "sg:postcode":"J4K 5J3",
    "sg:province":"QC",
    "sg:tags":[
        "communications",
        "consultant"
    ],
    "wof:name":"Andre Debray & Assoc Inc",
    "wof:placetype":"venue"
},
  "geometry": {"coordinates":[-73.52298,45.527645],"type":"Point"}
}