{
  "type": "Feature",
  "properties": {
    "addr:full":"970 Av Bombardier N Alma QC G8B 7A1",
    "addr:housenumber":"970",
    "addr:postcode":"g8b 7a1",
    "addr:street":"Av Bombardier N",
    "iso:country":"CA",
    "sg:address":"970 Av Bombardier N",
    "sg:city":"Alma",
    "sg:classifiers":[
        {
            "category":"Retail",
            "subcategory":"Auto Repair",
            "type":"Services"
        }
    ],
    "sg:phone":"+1 418 668 4501",
    "sg:postcode":"G8B 7A1",
    "sg:province":"QC",
    "sg:tags":[
        "spring"
    ],
    "wof:name":"Suspension Turcotte Alma Inc",
    "wof:placetype":"venue"
},
  "geometry": {"coordinates":[-71.649292,48.570114],"type":"Point"}
}