{
  "type": "Feature",
  "properties": {
    "addr:full":"2001 5 St Nisku AB T9E 7X4",
    "addr:housenumber":"2001 5",
    "addr:postcode":"t9e 7x4",
    "addr:street":"St",
    "iso:country":"CA",
    "sg:address":"2001 5 St",
    "sg:city":"Nisku",
    "sg:classifiers":[
        {
            "category":"Restaurant",
            "type":"Food & Drink"
        }
    ],
    "sg:phone":"+1 780 955 3605",
    "sg:postcode":"T9E 7X4",
    "sg:province":"AB",
    "wof:name":"Pipeline Alley Cafe",
    "wof:placetype":"venue"
},
  "geometry": {"coordinates":[-113.531051636,53.3384475708],"type":"Point"}
}