{
  "type": "Feature",
  "properties": {
    "addr:full":"Mississauga ON L5L 5M5",
    "addr:postcode":"l5l 5m5",
    "iso:country":"CA",
    "sg:city":"Mississauga",
    "sg:classifiers":[
        {
            "category":"Manufacturing",
            "subcategory":"Printing",
            "type":"Manufacturing & Wholesale Goods"
        }
    ],
    "sg:phone":"+1 905 608 2195",
    "sg:postcode":"L5L 5M5",
    "sg:province":"ON",
    "sg:tags":[
        "printer"
    ],
    "wof:name":"Z R Printing & Graphics",
    "wof:placetype":"venue"
},
  "geometry": {"coordinates":[-79.691002,43.518375],"type":"Point"}
}