{
  "type": "Feature",
  "properties": {
    "addr:full":"988 Rue Du Federal Sherbrooke QC J1H 5A7",
    "addr:housenumber":"988",
    "addr:postcode":"j1h 5a7",
    "addr:street":"Rue Du Federal",
    "iso:country":"CA",
    "sg:address":"988 Rue Du Federal",
    "sg:city":"Sherbrooke",
    "sg:classifiers":[
        {
            "category":"Personal",
            "subcategory":"Beauty Salon",
            "type":"Services"
        }
    ],
    "sg:phone":"+1 819 564 7892",
    "sg:postcode":"J1H 5A7",
    "sg:province":"QC",
    "wof:name":"Salon St-Colomban Enr",
    "wof:placetype":"venue"
},
  "geometry": {"coordinates":[-71.8857498169,45.3914871216],"type":"Point"}
}