{
  "type": "Feature",
  "properties": {
    "addr:full":"5407 Hwy 60 Douglas ON K0J 1S0",
    "addr:housenumber":"5407",
    "addr:postcode":"k0j 1s0",
    "addr:street":"Hwy 60",
    "iso:country":"CA",
    "sg:address":"5407 Hwy 60",
    "sg:city":"Douglas",
    "sg:classifiers":[
        {
            "category":"Retail",
            "subcategory":"Auto Repair",
            "type":"Services"
        }
    ],
    "sg:phone":"+1 613 649 2402",
    "sg:postcode":"K0J 1S0",
    "sg:province":"ON",
    "sg:tags":[
        "repairing",
        "automobile"
    ],
    "wof:name":"Buch's Garage",
    "wof:placetype":"venue"
},
  "geometry": {"coordinates":[-76.944458,45.513401],"type":"Point"}
}