{
  "type": "Feature",
  "properties": {
    "addr:full":"18 Torrington Pl Ottawa ON K1S 4E3",
    "addr:housenumber":"18",
    "addr:postcode":"k1s 4e3",
    "addr:street":"Torrington Pl",
    "iso:country":"CA",
    "sg:address":"18 Torrington Pl",
    "sg:city":"Ottawa",
    "sg:classifiers":[
        {
            "category":"Professional",
            "subcategory":"Management & Consulting",
            "type":"Services"
        }
    ],
    "sg:phone":"+1 613 230 9978",
    "sg:postcode":"K1S 4E3",
    "sg:province":"ON",
    "sg:tags":[
        "consultant",
        "educational"
    ],
    "wof:name":"Spectra Interactive Learning",
    "wof:placetype":"venue"
},
  "geometry": {"coordinates":[-75.693649292,45.395904541],"type":"Point"}
}