{
  "type": "Feature",
  "properties": {
    "addr:full":"Etobicoke ON M9W 6P3",
    "addr:postcode":"m9w 6p3",
    "iso:country":"CA",
    "sg:city":"Etobicoke",
    "sg:classifiers":[
        {
            "category":"Wholesale",
            "subcategory":"Groceries",
            "type":"Manufacturing & Wholesale Goods"
        }
    ],
    "sg:phone":"+1 416 674 0606",
    "sg:postcode":"M9W 6P3",
    "sg:province":"ON",
    "sg:tags":[
        "baker"
    ],
    "wof:name":"Wow Factor Desserts",
    "wof:placetype":"venue"
},
  "geometry": {"coordinates":[-79.63325500489999,43.7459144592],"type":"Point"}
}