{
  "type": "Feature",
  "properties": {
    "addr:full":"Teulon MB R0C 3B0",
    "addr:postcode":"r0c 3b0",
    "iso:country":"CA",
    "sg:city":"Teulon",
    "sg:classifiers":[
        {
            "category":"Government",
            "subcategory":"Office",
            "type":"Public Place"
        }
    ],
    "sg:phone":"+1 204 886 4406",
    "sg:postcode":"R0C 3B0",
    "sg:province":"MB",
    "wof:name":"Manitoba Livestock Technician",
    "wof:placetype":"venue"
},
  "geometry": {"coordinates":[-97.26309204099999,50.3857460022],"type":"Point"}
}