{
  "type": "Feature",
  "properties": {
    "iso:country":"CA",
    "sg:address":"114 Forsythe St",
    "sg:city":"Oakville",
    "sg:classifiers":[
        {
            "category":"Professional",
            "subcategory":"Management & Consulting",
            "type":"Services"
        }
    ],
    "sg:phone":"+1 905 844 8998",
    "sg:postcode":"L6K 3T3",
    "sg:province":"ON",
    "sg:tags":[
        "employee",
        "consultant",
        "benefit"
    ],
    "wof:name":"Gps Consulting Group Inc",
    "wof:placetype":"venue"
},
  "geometry": {"coordinates":[-79.6726989746,43.4424057007],"type":"Point"}
}