{
  "type": "Feature",
  "properties": {
    "addr:full":"136 Main St S Kenora ON P9N 1S9",
    "addr:housenumber":"136",
    "addr:postcode":"p9n 1s9",
    "addr:street":"Main St S",
    "iso:country":"CA",
    "sg:address":"136 Main St S",
    "sg:city":"Kenora",
    "sg:classifiers":[
        {
            "category":"Government",
            "subcategory":"Office",
            "type":"Public Place"
        }
    ],
    "sg:phone":"+1 807 468 2857",
    "sg:postcode":"P9N 1S9",
    "sg:province":"ON",
    "wof:name":"Ontario Probation & Parole",
    "wof:placetype":"venue"
},
  "geometry": {"coordinates":[-94.4906158447,49.7672538757],"type":"Point"}
}