{
  "type": "Feature",
  "properties": {
    "addr:full":"Onoway AB T0E 1V0",
    "addr:postcode":"t0e 1v0",
    "iso:country":"CA",
    "sg:city":"Onoway",
    "sg:classifiers":[
        {
            "category":"Building & Trades",
            "subcategory":"Construction",
            "type":"Services"
        }
    ],
    "sg:phone":"+1 780 967 2232",
    "sg:postcode":"T0E 1V0",
    "sg:province":"AB",
    "sg:tags":[
        "excavating",
        "contractor",
        "general"
    ],
    "wof:name":"Simpson Construction",
    "wof:placetype":"venue"
},
  "geometry": {"coordinates":[-114.173439,53.70715],"type":"Point"}
}