{
  "type": "Feature",
  "properties": {
    "addr:full":"Saint-Jean-Baptiste-DE-Nicolet QC J3T 1T7",
    "addr:postcode":"j3t 1t7",
    "iso:country":"CA",
    "sg:city":"Saint-Jean-Baptiste-DE-Nicolet",
    "sg:classifiers":[
        {
            "category":"Health Services",
            "subcategory":"Health Practitioner",
            "type":"Services"
        }
    ],
    "sg:phone":"+1 819 293 2876",
    "sg:postcode":"J3T 1T7",
    "sg:province":"QC",
    "sg:tags":[
        "medicine",
        "orthopedic"
    ],
    "wof:name":"Clinique D'Orthotherapie Jean",
    "wof:placetype":"venue"
},
  "geometry": {"coordinates":[-72.616028,46.22855],"type":"Point"}
}