{
  "type": "Feature",
  "properties": {
    "addr:full":"PO Box 790 Carnduff SK S0C 0S0",
    "addr:housenumber":"po",
    "addr:postcode":"s0c 0s0",
    "addr:street":"Box 790",
    "iso:country":"CA",
    "sg:address":"PO Box 790",
    "sg:city":"Carnduff",
    "sg:classifiers":[
        {
            "category":"Mining & Drilling",
            "type":"Manufacturing & Wholesale Goods"
        }
    ],
    "sg:phone":"+1 306 928 2226",
    "sg:postcode":"S0C 0S0",
    "sg:province":"SK",
    "sg:tags":[
        "company",
        "oil"
    ],
    "wof:name":"Arc Resources Ltd",
    "wof:placetype":"venue"
},
  "geometry": {"coordinates":[-101.799049,49.177223],"type":"Point"}
}