{
  "type": "Feature",
  "properties": {
    "addr:full":"519 Finlay St E Killarney MB R0K 1G0",
    "addr:housenumber":"519",
    "addr:postcode":"r0k 1g0",
    "addr:street":"Finlay St E",
    "iso:country":"CA",
    "sg:address":"519 Finlay St E",
    "sg:city":"Killarney",
    "sg:classifiers":[
        {
            "category":"Wholesale",
            "subcategory":"Machinery & Supplies",
            "type":"Manufacturing & Wholesale Goods"
        }
    ],
    "sg:phone":"+1 204 523 4888",
    "sg:postcode":"R0K 1G0",
    "sg:province":"MB",
    "sg:tags":[
        "farm",
        "equipment"
    ],
    "wof:name":"Killarney Farm Supplies",
    "wof:placetype":"venue"
},
  "geometry": {"coordinates":[-99.669296,49.18457],"type":"Point"}
}