{
  "type": "Feature",
  "properties": {
    "addr:full":"4 Patton St Grimsby ON L3M 3M5",
    "addr:housenumber":"4",
    "addr:postcode":"l3m 3m5",
    "addr:street":"Patton St",
    "iso:country":"CA",
    "sg:address":"4 Patton St",
    "sg:city":"Grimsby",
    "sg:classifiers":[
        {
            "category":"Manufacturing",
            "subcategory":"Tools & Machinery",
            "type":"Manufacturing & Wholesale Goods"
        }
    ],
    "sg:phone":"+1 905 945 1050",
    "sg:postcode":"L3M 3M5",
    "sg:province":"ON",
    "sg:tags":[
        "control"
    ],
    "wof:name":"Frs Instrumentation & Ctrls",
    "wof:placetype":"venue"
},
  "geometry": {"coordinates":[-79.5640869141,43.1952400208],"type":"Point"}
}