{
  "type": "Feature",
  "properties": {
    "iso:country":"CA",
    "sg:city":"Sainte-Claire",
    "sg:classifiers":[
        {
            "category":"Shopping",
            "subcategory":"Florist",
            "type":"Retail Goods"
        }
    ],
    "sg:phone":"+1 418 883 3353",
    "sg:postcode":"G0R 2V0",
    "sg:province":"QC",
    "wof:name":"Renee Fleuriste Enr",
    "wof:placetype":"venue"
},
  "geometry": {"coordinates":[-70.86539459230001,46.6013145447],"type":"Point"}
}