{
  "type": "Feature",
  "properties": {
    "addr:full":"140 Bell Farm Rd Barrie ON L4M 5K5",
    "addr:housenumber":"140",
    "addr:postcode":"l4m 5k5",
    "addr:street":"Bell Farm Rd",
    "iso:country":"CA",
    "sg:address":"140 Bell Farm Rd",
    "sg:city":"Barrie",
    "sg:classifiers":[
        {
            "category":"Travel",
            "subcategory":"Hotels & Motels",
            "type":"Entertainment"
        }
    ],
    "sg:phone":"+1 705 735 0772",
    "sg:postcode":"L4M 5K5",
    "sg:province":"ON",
    "sg:tags":[
        "tourist",
        "accommodation"
    ],
    "wof:name":"Georgian Green Summer Hostel",
    "wof:placetype":"venue"
},
  "geometry": {"coordinates":[-79.67627,44.410786],"type":"Point"}
}