{
  "type": "Feature",
  "properties": {
    "addr:full":"Victoria BC V8W 3M9",
    "addr:postcode":"v8w 3m9",
    "iso:country":"CA",
    "sg:city":"Victoria",
    "sg:classifiers":[
        {
            "category":"Shopping",
            "subcategory":"Optical Goods",
            "type":"Retail Goods"
        }
    ],
    "sg:phone":"+1 250 361 1977",
    "sg:postcode":"V8W 3M9",
    "sg:province":"BC",
    "sg:tags":[
        "optician"
    ],
    "wof:name":"Lenscrafters",
    "wof:placetype":"venue"
},
  "geometry": {"coordinates":[-123.065826,49.220127],"type":"Point"}
}