{
  "type": "Feature",
  "properties": {
    "addr:full":"Buckingham QC J8L 3P5",
    "addr:postcode":"j8l 3p5",
    "iso:country":"CA",
    "sg:city":"Buckingham",
    "sg:classifiers":[
        {
            "category":"Professional",
            "subcategory":"Art Services",
            "type":"Services"
        }
    ],
    "sg:phone":"+1 819 986 7708",
    "sg:postcode":"J8L 3P5",
    "sg:province":"QC",
    "sg:tags":[
        "graphic",
        "designer"
    ],
    "wof:name":"Groupe Concept",
    "wof:placetype":"venue"
},
  "geometry": {"coordinates":[-75.432723999,45.5702667236],"type":"Point"}
}