{
  "type": "Feature",
  "properties": {
    "iso:country":"CA",
    "sg:address":"776 Gordon Baker Rd",
    "sg:city":"North York",
    "sg:classifiers":[
        {
            "category":"Wholesale",
            "subcategory":"Machinery & Supplies",
            "type":"Manufacturing & Wholesale Goods"
        }
    ],
    "sg:phone":"+1 416 499 9300",
    "sg:postcode":"M2H 3B4",
    "sg:province":"ON",
    "sg:tags":[
        "equipment",
        "industrial"
    ],
    "wof:name":"Integrated Machinery Inc",
    "wof:placetype":"venue"
},
  "geometry": {"coordinates":[-79.34613800050001,43.8089256287],"type":"Point"}
}