{
  "type": "Feature",
  "properties": {
    "addr:full":"Kitimat BC V8C 2H4",
    "addr:postcode":"bc v8c 2h4",
    "iso:country":"CA",
    "sg:city":"Kitimat",
    "sg:classifiers":[
        {
            "category":"Building & Trades",
            "subcategory":"Electrical",
            "type":"Services"
        }
    ],
    "sg:phone":"+1 250 632 6601",
    "sg:postcode":"V8C 2H4",
    "sg:province":"BC",
    "sg:tags":[
        "electric",
        "contractor"
    ],
    "wof:name":"Pereira Electric Ltd",
    "wof:placetype":"venue"
},
  "geometry": {"coordinates":[-128.68424999999999,54.061138],"type":"Point"}
}