{
  "type": "Feature",
  "properties": {
    "addr:full":"11 Ch DE LA Randonnee Stoneham QC G0A 4P0",
    "addr:housenumber":"11",
    "addr:postcode":"g0a 4p0",
    "addr:street":"Ch De La Randonnee",
    "iso:country":"CA",
    "sg:address":"11 Ch DE LA Randonnee",
    "sg:city":"Stoneham",
    "sg:classifiers":[
        {
            "category":"Professional",
            "subcategory":"Art Services",
            "type":"Services"
        }
    ],
    "sg:phone":"+1 418 848 2416",
    "sg:postcode":"G0A 4P0",
    "sg:province":"QC",
    "sg:tags":[
        "graphic",
        "designer"
    ],
    "wof:name":"Alainshe Enr",
    "wof:placetype":"venue"
},
  "geometry": {"coordinates":[-71.350517,47.008472],"type":"Point"}
}