{
  "type": "Feature",
  "properties": {
    "addr:full":"Kirkland QC H9H 5B9",
    "addr:postcode":"h9h 5b9",
    "iso:country":"CA",
    "sg:city":"Kirkland",
    "sg:classifiers":[
        {
            "category":"Wholesale",
            "subcategory":"Electrical",
            "type":"Manufacturing & Wholesale Goods"
        }
    ],
    "sg:phone":"+1 514 693 9776",
    "sg:postcode":"H9H 5B9",
    "sg:province":"QC",
    "sg:tags":[
        "equipment",
        "electric",
        "supply"
    ],
    "wof:name":"Imexcom Canada Inc",
    "wof:placetype":"venue"
},
  "geometry": {"coordinates":[-73.862335,45.456436],"type":"Point"}
}