{
  "type": "Feature",
  "properties": {
    "addr:full":"Matapedia QC G0J 1V0",
    "addr:postcode":"g0j 1v0",
    "iso:country":"CA",
    "sg:city":"Matapedia",
    "sg:classifiers":[
        {
            "category":"Health Services",
            "subcategory":"Doctor",
            "type":"Services"
        }
    ],
    "sg:phone":"+1 418 865 2175",
    "sg:postcode":"G0J 1V0",
    "sg:province":"QC",
    "sg:tags":[
        "physician",
        "surgeon"
    ],
    "wof:name":"Le Blanc, Paul MD",
    "wof:placetype":"venue"
},
  "geometry": {"coordinates":[-66.955978,47.975296],"type":"Point"}
}