{
  "type": "Feature",
  "properties": {
    "addr:full":"161 St. Peters Rd Charlottetown PE C1A 5P6",
    "addr:housenumber":"161",
    "addr:postcode":"c1a 5p6",
    "addr:street":"St. Peters Rd",
    "iso:country":"CA",
    "sg:address":"161 St. Peters Rd",
    "sg:city":"Charlottetown",
    "sg:classifiers":[
        {
            "category":"Personal",
            "subcategory":"Beauty Salon",
            "type":"Services"
        }
    ],
    "sg:phone":"+1 902 892 2334",
    "sg:postcode":"C1A 5P6",
    "sg:province":"PE",
    "wof:name":"Sherwood Styling Salon",
    "wof:placetype":"venue"
},
  "geometry": {"coordinates":[-63.1187705994,46.2610778809],"type":"Point"}
}