{
  "type": "Feature",
  "properties": {
    "addr:full":"2010 Rue Saint-Denis Montreal QC H2X 3K7",
    "addr:housenumber":"2010",
    "addr:postcode":"h2x 3k7",
    "addr:street":"Rue Saint-Denis",
    "iso:country":"CA",
    "sg:address":"2010 Rue Saint-Denis",
    "sg:city":"Montreal",
    "sg:classifiers":[
        {
            "category":"Shopping",
            "subcategory":"Clothing, Apparel, & Fashions",
            "type":"Retail Goods"
        }
    ],
    "sg:phone":"+1 514 847 0006",
    "sg:postcode":"H2X 3K7",
    "sg:province":"QC",
    "wof:name":"Modes 2010",
    "wof:placetype":"venue"
},
  "geometry": {"coordinates":[-73.56564331049999,45.5159492493],"type":"Point"}
}