{
  "type": "Feature",
  "properties": {
    "addr:full":"32 Church St Amherst NS B4H 3A8",
    "addr:housenumber":"32",
    "addr:postcode":"b4h 3a8",
    "addr:street":"Church St",
    "iso:country":"CA",
    "sg:address":"32 Church St",
    "sg:city":"Amherst",
    "sg:classifiers":[
        {
            "category":"Banks & Credit Unions",
            "subcategory":"Bank",
            "type":"Services"
        }
    ],
    "sg:phone":"+1 902 667 3376",
    "sg:postcode":"B4H 3A8",
    "sg:province":"NS",
    "wof:name":"Cibc",
    "wof:placetype":"venue"
},
  "geometry": {"coordinates":[-64.2116317749,45.8329734802],"type":"Point"}
}