{
  "type": "Feature",
  "properties": {
    "iso:country":"CA",
    "sg:city":"New Richmond",
    "sg:classifiers":[
        {
            "category":"Manufacturing",
            "subcategory":"Lumber",
            "type":"Manufacturing & Wholesale Goods"
        }
    ],
    "sg:phone":"+1 418 392 4435",
    "sg:postcode":"G0C 2B0",
    "sg:province":"QC",
    "sg:tags":[
        "sawmill"
    ],
    "wof:name":"Pabaced Gds Inc",
    "wof:placetype":"venue"
},
  "geometry": {"coordinates":[-65.7964172363,48.1657104492],"type":"Point"}
}