{
  "type": "Feature",
  "properties": {
    "addr:full":"2032 First St Louth St Catharines ON L2R 6P9",
    "addr:housenumber":"2032",
    "addr:postcode":"l2r 6p9",
    "addr:street":"First St Louth",
    "iso:country":"CA",
    "sg:address":"2032 First St Louth",
    "sg:city":"St Catharines",
    "sg:classifiers":[
        {
            "category":"Manufacturing",
            "subcategory":"Motor Vehicles & Parts",
            "type":"Manufacturing & Wholesale Goods"
        }
    ],
    "sg:phone":"+1 905 641 9110",
    "sg:postcode":"L2R 6P9",
    "sg:province":"ON",
    "sg:tags":[
        "automobile",
        "supply"
    ],
    "wof:name":"Venest Industries Inc",
    "wof:placetype":"venue"
},
  "geometry": {"coordinates":[-79.248672,43.156334],"type":"Point"}
}