{
  "type": "Feature",
  "properties": {
    "addr:full":"14 Yonge St S Elmvale ON L0L 1P0",
    "addr:housenumber":"14",
    "addr:postcode":"l0l 1p0",
    "addr:street":"Yonge St S",
    "iso:country":"CA",
    "sg:address":"14 Yonge St S",
    "sg:city":"Elmvale",
    "sg:classifiers":[
        {
            "category":"Food & Beverages",
            "subcategory":"Groceries & Convenience Stores",
            "type":"Retail Goods"
        }
    ],
    "sg:phone":"+1 705 322 2261",
    "sg:postcode":"L0L 1P0",
    "sg:province":"ON",
    "sg:tags":[
        "grocer"
    ],
    "wof:name":"Iga",
    "wof:placetype":"venue"
},
  "geometry": {"coordinates":[-79.86535600000001,44.582443],"type":"Point"}
}