{
  "type": "Feature",
  "properties": {
    "iso:country":"CA",
    "sg:address":"727 Courtney St",
    "sg:city":"Victoria",
    "sg:classifiers":[
        {
            "category":"Retail",
            "subcategory":"Auto Rental",
            "type":"Services"
        }
    ],
    "sg:phone":"+1 250 953 5300",
    "sg:postcode":"V8W 1C3",
    "sg:province":"BC",
    "sg:tags":[
        "renting",
        "automobile"
    ],
    "wof:name":"Budget Car & Truck Rental",
    "wof:placetype":"venue"
},
  "geometry": {"coordinates":[-123.364838,48.422756],"type":"Point"}
}