{
  "type": "Feature",
  "properties": {
    "addr:full":"14435 124 Ave NW Edmonton AB T5L 3B2",
    "addr:housenumber":"14435",
    "addr:postcode":"t5l 3b2",
    "addr:street":"124 Ave Nw",
    "iso:country":"CA",
    "sg:address":"14435 124 Ave NW",
    "sg:city":"Edmonton",
    "sg:phone":"+1 780 451 4373",
    "sg:postcode":"T5L 3B2",
    "sg:province":"AB",
    "sg:tags":[
        "lubricant",
        "oil",
        "grease"
    ],
    "wof:name":"Chris Page & Assoc Ltd",
    "wof:placetype":"venue"
},
  "geometry": {"coordinates":[-113.570640564,53.5788459778],"type":"Point"}
}