{
  "type": "Feature",
  "properties": {
    "addr:full":"124 Main St Woodstock ON N4S 1S9",
    "addr:housenumber":"124",
    "addr:postcode":"n4s 1s9",
    "addr:street":"Main St",
    "iso:country":"CA",
    "sg:address":"124 Main St",
    "sg:city":"Woodstock",
    "sg:classifiers":[
        {
            "category":"Manufacturing",
            "subcategory":"Metals",
            "type":"Manufacturing & Wholesale Goods"
        }
    ],
    "sg:phone":"+1 519 421 0742",
    "sg:postcode":"N4S 1S9",
    "sg:province":"ON",
    "sg:tags":[
        "stamping"
    ],
    "wof:name":"Forestdale Metal Products Inc",
    "wof:placetype":"venue"
},
  "geometry": {"coordinates":[-80.770943,43.125423],"type":"Point"}
}