{
  "type": "Feature",
  "properties": {
    "addr:full":"Highway 2 & 5 Meacham SK S0K 2V0",
    "addr:postcode":"s0k 2v0",
    "addr:street":"Highway 2 & 5 Meacham",
    "iso:country":"CA",
    "sg:address":"Highway 2 & 5",
    "sg:city":"Meacham",
    "sg:classifiers":[
        {
            "category":"Restaurant",
            "type":"Food & Drink"
        }
    ],
    "sg:phone":"+1 306 376 2211",
    "sg:postcode":"S0K 2V0",
    "sg:province":"SK",
    "sg:tags":[
        "hall",
        "auditorium"
    ],
    "wof:name":"D M Junction 2 & 5",
    "wof:placetype":"venue"
},
  "geometry": {"coordinates":[-105.758911,52.107155],"type":"Point"}
}