{
  "type": "Feature",
  "properties": {
    "addr:full":"122 Queen St Stephenville NL A2N 2N7",
    "addr:housenumber":"122",
    "addr:postcode":"a2n 2n7",
    "addr:street":"Queen St",
    "iso:country":"CA",
    "sg:address":"122 Queen St",
    "sg:city":"Stephenville",
    "sg:classifiers":[
        {
            "category":"Food & Beverages",
            "subcategory":"Groceries & Convenience Stores",
            "type":"Retail Goods"
        }
    ],
    "sg:phone":"+1 709 643 3812",
    "sg:postcode":"A2N 2N7",
    "sg:province":"NL",
    "wof:name":"Sweet Shop",
    "wof:placetype":"venue"
},
  "geometry": {"coordinates":[-58.576141,48.550232],"type":"Point"}
}