{
  "type": "Feature",
  "properties": {
    "addr:full":"173 Rue DE Liverpool Saint-Augustin-DE-Desmaures QC G3A 2C8",
    "addr:housenumber":"173",
    "addr:postcode":"g3a 2c8",
    "addr:street":"Rue De Liverpool",
    "iso:country":"CA",
    "sg:address":"173 Rue DE Liverpool",
    "sg:city":"Saint-Augustin-DE-Desmaures",
    "sg:classifiers":[
        {
            "category":"Wholesale",
            "subcategory":"Metals & Minerals",
            "type":"Manufacturing & Wholesale Goods"
        }
    ],
    "sg:phone":"+1 418 878 5711",
    "sg:postcode":"G3A 2C8",
    "sg:province":"QC",
    "sg:tags":[
        "steel",
        "warehouse",
        "reinforcing",
        "supply"
    ],
    "wof:name":"Acier Hydraulique Inc",
    "wof:placetype":"venue"
},
  "geometry": {"coordinates":[-71.4422454834,46.7513046265],"type":"Point"}
}