{
  "type": "Feature",
  "properties": {
    "addr:full":"1180 Rue Du Sud Cowansville QC J2K 2Y8",
    "addr:housenumber":"1180",
    "addr:postcode":"j2k 2y8",
    "addr:street":"Rue Du Sud",
    "iso:country":"CA",
    "sg:address":"1180 Rue Du Sud",
    "sg:city":"Cowansville",
    "sg:classifiers":[
        {
            "category":"Health Services",
            "subcategory":"Doctor",
            "type":"Services"
        }
    ],
    "sg:phone":"+1 450 263 3902",
    "sg:postcode":"J2K 2Y8",
    "sg:province":"QC",
    "sg:tags":[
        "clinic"
    ],
    "wof:name":"Cere, Pierre",
    "wof:placetype":"venue"
},
  "geometry": {"coordinates":[-72.75048828120001,45.196559906],"type":"Point"}
}