{
  "type": "Feature",
  "properties": {
    "addr:full":"Timmins ON P4N 7H1",
    "addr:postcode":"p4n 7h1",
    "iso:country":"CA",
    "sg:city":"Timmins",
    "sg:classifiers":[
        {
            "category":"Building & Trades",
            "subcategory":"Construction",
            "type":"Services"
        }
    ],
    "sg:phone":"+1 705 264 6820",
    "sg:postcode":"P4N 7H1",
    "sg:province":"ON",
    "sg:tags":[
        "sand",
        "gravel",
        "general",
        "contractor"
    ],
    "wof:name":"Paul Guiho Trucking & Constr",
    "wof:placetype":"venue"
},
  "geometry": {"coordinates":[-81.328957,48.476074],"type":"Point"}
}