{
  "type": "Feature",
  "properties": {
    "addr:full":"Scarborough ON M1R 2Z2",
    "addr:postcode":"m1r 2z2",
    "iso:country":"CA",
    "sg:city":"Scarborough",
    "sg:classifiers":[
        {
            "category":"Restaurant",
            "type":"Food & Drink"
        }
    ],
    "sg:phone":"+1 416 751 4278",
    "sg:postcode":"M1R 2Z2",
    "sg:province":"ON",
    "wof:name":"Saghar Restaurant Inc",
    "wof:placetype":"venue"
},
  "geometry": {"coordinates":[-79.295486,43.745094],"type":"Point"}
}