{
  "type": "Feature",
  "properties": {
    "addr:full":"1086 Gladstone Ave Ottawa ON K1Y 3G9",
    "addr:housenumber":"1086",
    "addr:postcode":"k1y 3g9",
    "addr:street":"Gladstone Ave",
    "iso:country":"CA",
    "sg:address":"1086 Gladstone Ave",
    "sg:city":"Ottawa",
    "sg:classifiers":[
        {
            "category":"Retail",
            "subcategory":"Auto Repair",
            "type":"Services"
        }
    ],
    "sg:phone":"+1 613 729 6000",
    "sg:postcode":"K1Y 3G9",
    "sg:province":"ON",
    "sg:tags":[
        "transmission",
        "automobile",
        "repairing"
    ],
    "wof:name":"B & N Transmission",
    "wof:placetype":"venue"
},
  "geometry": {"coordinates":[-75.722748,45.400959],"type":"Point"}
}