{
  "type": "Feature",
  "properties": {
    "addr:full":"36654 Hart Hwy Bear Lake BC V0J 3G0",
    "addr:housenumber":"36654",
    "addr:postcode":"v0j 3g0",
    "addr:street":"Hart Hwy",
    "iso:country":"CA",
    "sg:address":"36654 Hart Hwy",
    "sg:city":"Bear Lake",
    "sg:classifiers":[
        {
            "category":"Manufacturing",
            "subcategory":"Lumber",
            "type":"Manufacturing & Wholesale Goods"
        }
    ],
    "sg:phone":"+1 250 972 4700",
    "sg:postcode":"V0J 3G0",
    "sg:province":"BC",
    "wof:name":"Canadian Forest Products Ltd",
    "wof:placetype":"venue"
},
  "geometry": {"coordinates":[-122.689018,54.50116],"type":"Point"}
}