{
  "type": "Feature",
  "properties": {
    "iso:country":"CA",
    "sg:city":"Quebec",
    "sg:classifiers":[
        {
            "category":"Communications",
            "subcategory":"Television Station",
            "type":"Services"
        }
    ],
    "sg:phone":"+1 418 847 0183",
    "sg:postcode":"G2C 1S9",
    "sg:province":"QC",
    "sg:tags":[
        "broadcasting",
        "co"
    ],
    "wof:name":"Tele Mag 24 Inc",
    "wof:placetype":"venue"
},
  "geometry": {"coordinates":[-71.3137588501,46.8208885193],"type":"Point"}
}