{
  "type": "Feature",
  "properties": {
    "addr:full":"295 Main St Landmark MB R0A 0X0",
    "addr:housenumber":"295",
    "addr:postcode":"r0a 0x0",
    "addr:street":"Main St",
    "iso:country":"CA",
    "sg:address":"295 Main St",
    "sg:city":"Landmark",
    "sg:classifiers":[
        {
            "category":"Building & Trades",
            "subcategory":"Construction",
            "type":"Services"
        }
    ],
    "sg:phone":"+1 204 355 4617",
    "sg:postcode":"R0A 0X0",
    "sg:province":"MB",
    "sg:tags":[
        "dry wall",
        "contractor"
    ],
    "wof:name":"Landville Drywall Ltd",
    "wof:placetype":"venue"
},
  "geometry": {"coordinates":[-96.81996917719999,49.6641654968],"type":"Point"}
}