{
  "type": "Feature",
  "properties": {
    "addr:full":"215 Pine St Stayner ON L0M 1S0",
    "addr:housenumber":"215",
    "addr:postcode":"l0m 1s0",
    "addr:street":"Pine St",
    "iso:country":"CA",
    "sg:address":"215 Pine St",
    "sg:city":"Stayner",
    "sg:classifiers":[
        {
            "category":"Organizations",
            "subcategory":"Religious Organization",
            "type":"Services"
        }
    ],
    "sg:phone":"+1 705 428 2124",
    "sg:postcode":"L0M 1S0",
    "sg:province":"ON",
    "sg:tags":[
        "church"
    ],
    "wof:name":"St Patrick's Roman Catholic",
    "wof:placetype":"venue"
},
  "geometry": {"coordinates":[-80.091537,44.416897],"type":"Point"}
}