{
  "type": "Feature",
  "properties": {
    "iso:country":"CA",
    "sg:address":"528 2 St SE",
    "sg:city":"Medicine Hat",
    "sg:classifiers":[
        {
            "category":"Shopping",
            "subcategory":"Used Merchandise",
            "type":"Retail Goods"
        }
    ],
    "sg:phone":"+1 403 529 9366",
    "sg:postcode":"T1A 0C6",
    "sg:province":"AB",
    "sg:tags":[
        "shop",
        "consignment"
    ],
    "wof:name":"Phase II Boutique",
    "wof:placetype":"venue"
},
  "geometry": {"coordinates":[-110.677864,50.040203],"type":"Point"}
}