{
  "type": "Feature",
  "properties": {
    "iso:country":"CA",
    "sg:address":"4960 13 St SE",
    "sg:city":"Calgary",
    "sg:classifiers":[
        {
            "category":"Professional",
            "subcategory":"Advertising",
            "type":"Services"
        }
    ],
    "sg:phone":"+1 403 244 4200",
    "sg:postcode":"T2G 5M9",
    "sg:province":"AB",
    "sg:tags":[
        "counselor"
    ],
    "wof:name":"Gold Group Inc",
    "wof:placetype":"venue"
},
  "geometry": {"coordinates":[-114.032745361,51.0081329346],"type":"Point"}
}