{
  "type": "Feature",
  "properties": {
    "iso:country":"CA",
    "sg:city":"Vancouver",
    "sg:classifiers":[
        {
            "category":"Real Estate",
            "subcategory":"Real Estate Agent",
            "type":"Services"
        }
    ],
    "sg:phone":"+1 604 683 2033",
    "sg:postcode":"V6E 4G7",
    "sg:province":"BC",
    "sg:tags":[
        "cooperative"
    ],
    "wof:name":"Pacific Heights Housing CO-OP",
    "wof:placetype":"venue"
},
  "geometry": {"coordinates":[-123.13285827599999,49.2774200439],"type":"Point"}
}