{
  "type": "Feature",
  "properties": {
    "addr:full":"1472 St Clair Ave W Toronto ON M6E 1C6",
    "addr:housenumber":"1472",
    "addr:postcode":"m6e 1c6",
    "addr:street":"St Clair Ave W",
    "iso:country":"CA",
    "sg:address":"1472 St Clair Ave W",
    "sg:city":"Toronto",
    "sg:classifiers":[
        {
            "category":"Personal",
            "subcategory":"Beauty Salon",
            "type":"Services"
        }
    ],
    "sg:phone":"+1 416 653 1102",
    "sg:postcode":"M6E 1C6",
    "sg:province":"ON",
    "wof:name":"Classic Cuts",
    "wof:placetype":"venue"
},
  "geometry": {"coordinates":[-79.45339199999999,43.675735],"type":"Point"}
}