{
  "type": "Feature",
  "properties": {
    "iso:country":"CA",
    "sg:address":"PO Box 178",
    "sg:city":"Baie Verte",
    "sg:classifiers":[
        {
            "category":"Education",
            "subcategory":"Library",
            "type":"Public Place"
        }
    ],
    "sg:phone":"+1 709 532 8361",
    "sg:postcode":"A0K 1B0",
    "sg:province":"NL",
    "wof:name":"Baie Verta Public Library",
    "wof:placetype":"venue"
},
  "geometry": {"coordinates":[-56.1923103333,49.9394645691],"type":"Point"}
}