{
  "type": "Feature",
  "properties": {
    "addr:full":"16 Eastwood St Hamilton ON L8H 6R7",
    "addr:housenumber":"16",
    "addr:postcode":"l8h 6r7",
    "addr:street":"Eastwood St",
    "iso:country":"CA",
    "sg:address":"16 Eastwood St",
    "sg:city":"Hamilton",
    "sg:classifiers":[
        {
            "category":"Social Services",
            "type":"Services"
        }
    ],
    "sg:phone":"+1 905 545 0565",
    "sg:postcode":"L8H 6R7",
    "sg:province":"ON",
    "sg:tags":[
        "organization",
        "welfare"
    ],
    "wof:name":"Roxborough Parc Ctr",
    "wof:placetype":"venue"
},
  "geometry": {"coordinates":[-79.778519,43.238911],"type":"Point"}
}