{
  "type": "Feature",
  "properties": {
    "addr:full":"Cap-Chat QC G0J 1E0",
    "addr:postcode":"g0j 1e0",
    "iso:country":"CA",
    "sg:city":"Cap-Chat",
    "sg:classifiers":[
        {
            "category":"Recreation",
            "type":"Entertainment"
        }
    ],
    "sg:phone":"+1 418 786 2620",
    "sg:postcode":"G0J 1E0",
    "sg:province":"QC",
    "sg:tags":[
        "stable"
    ],
    "wof:name":"Ranch M & M Inc",
    "wof:placetype":"venue"
},
  "geometry": {"coordinates":[-66.733253479,49.086894989],"type":"Point"}
}