{
  "type": "Feature",
  "properties": {
    "addr:full":"3075 Wild Rose Blvd Nanoose Bay BC V9P 9E4",
    "addr:housenumber":"3075",
    "addr:postcode":"v9p 9e4",
    "addr:street":"Wild Rose Blvd",
    "iso:country":"CA",
    "sg:address":"3075 Wild Rose Blvd",
    "sg:city":"Nanoose Bay",
    "sg:classifiers":[
        {
            "category":"Professional",
            "subcategory":"Management & Consulting",
            "type":"Services"
        }
    ],
    "sg:phone":"+1 250 468 5505",
    "sg:postcode":"V9P 9E4",
    "sg:province":"BC",
    "sg:tags":[
        "counselor",
        "public",
        "relations"
    ],
    "wof:name":"Pamela Bottomley Public Rltns",
    "wof:placetype":"venue"
},
  "geometry": {"coordinates":[-124.183769,49.252571],"type":"Point"}
}