{
  "type": "Feature",
  "properties": {
    "addr:full":"171 Av Dalcourt Louiseville QC J5V 1A6",
    "addr:postcode":"j5v 1a6",
    "addr:street":"171 Av Dalcourt",
    "iso:country":"CA",
    "sg:address":"171 Av Dalcourt",
    "sg:city":"Louiseville",
    "sg:classifiers":[
        {
            "category":"Home & Garden",
            "subcategory":"Hardware",
            "type":"Retail Goods"
        }
    ],
    "sg:phone":"+1 819 228 2753",
    "sg:postcode":"J5V 1A6",
    "sg:province":"QC",
    "wof:name":"Caron & Gagnon Ltee",
    "wof:placetype":"venue"
},
  "geometry": {"coordinates":[-72.94383999999999,46.261482],"type":"Point"}
}