{
  "type": "Feature",
  "properties": {
    "iso:country":"CA",
    "sg:address":"1720 Rupert St",
    "sg:city":"Vancouver",
    "sg:classifiers":[
        {
            "category":"Autos & Motor Vehicles",
            "subcategory":"Fuel & Gas Station",
            "type":"Retail Goods"
        }
    ],
    "sg:phone":"+1 604 251 5925",
    "sg:postcode":"V5M 3S3",
    "sg:province":"BC",
    "sg:tags":[
        "oil"
    ],
    "wof:name":"First & Rupert Town Pantry",
    "wof:placetype":"venue"
},
  "geometry": {"coordinates":[-123.03345489500001,49.269153595],"type":"Point"}
}