{
  "type": "Feature",
  "properties": {
    "addr:full":"205 Main St Dartmouth NS B2X 1S4",
    "addr:housenumber":"205",
    "addr:postcode":"b2x 1s4",
    "addr:street":"Main St",
    "iso:country":"CA",
    "sg:address":"205 Main St",
    "sg:city":"Dartmouth",
    "sg:classifiers":[
        {
            "category":"Building & Trades",
            "subcategory":"Construction",
            "type":"Services"
        }
    ],
    "sg:phone":"+1 902 434 8976",
    "sg:postcode":"B2X 1S4",
    "sg:province":"NS",
    "sg:tags":[
        "roofing",
        "siding",
        "contractor"
    ],
    "wof:name":"Safeway Window Specialists",
    "wof:placetype":"venue"
},
  "geometry": {"coordinates":[-63.5293579102,44.6844482422],"type":"Point"}
}