{
  "type": "Feature",
  "properties": {
    "addr:full":"84 Rue Principale E Sainte-Agathe-Des-Monts QC J8C 1J7",
    "addr:housenumber":"84",
    "addr:postcode":"j8c 1j7",
    "addr:street":"Rue Principale E Sainte-Agathe-Des-Monts",
    "iso:country":"CA",
    "sg:address":"84 Rue Principale E",
    "sg:city":"Sainte-Agathe-Des-Monts",
    "sg:classifiers":[
        {
            "category":"Restaurant",
            "type":"Food & Drink"
        }
    ],
    "sg:phone":"+1 819 326 7055",
    "sg:postcode":"J8C 1J7",
    "sg:province":"QC",
    "wof:name":"Au Petit Creux",
    "wof:placetype":"venue"
},
  "geometry": {"coordinates":[-74.284431,46.046623],"type":"Point"}
}