{
  "type": "Feature",
  "properties": {
    "addr:full":"43 Crow Bay Hgts Campbellford ON K0L 1L0",
    "addr:housenumber":"43",
    "addr:postcode":"k0l 1l0",
    "addr:street":"Crow Bay",
    "iso:country":"CA",
    "sg:address":"43 Crow Bay Hgts",
    "sg:city":"Campbellford",
    "sg:classifiers":[
        {
            "category":"Arts & Performance",
            "subcategory":"Theater",
            "type":"Entertainment"
        }
    ],
    "sg:phone":"+1 705 653 2403",
    "sg:postcode":"K0L 1L0",
    "sg:province":"ON",
    "sg:tags":[
        "live",
        "music"
    ],
    "wof:name":"Wilson Instrument",
    "wof:placetype":"venue"
},
  "geometry": {"coordinates":[-77.769974,44.337116],"type":"Point"}
}