{
  "type": "Feature",
  "properties": {
    "addr:full":"2119 Ch Des Mesanges Nominingue QC J0W 1R0",
    "addr:housenumber":"2119",
    "addr:postcode":"j0w 1r0",
    "addr:street":"Ch Des Mesanges",
    "iso:country":"CA",
    "sg:address":"2119 Ch Des Mesanges",
    "sg:city":"Nominingue",
    "sg:classifiers":[
        {
            "category":"Home & Garden",
            "subcategory":"Hardware",
            "type":"Retail Goods"
        }
    ],
    "sg:phone":"+1 819 278 3709",
    "sg:postcode":"J0W 1R0",
    "sg:province":"QC",
    "sg:tags":[
        "paint"
    ],
    "wof:name":"Cooperative Agricole",
    "wof:placetype":"venue"
},
  "geometry": {"coordinates":[-75.028587,46.385715],"type":"Point"}
}