{
  "type": "Feature",
  "properties": {
    "addr:full":"5500 North Service Rd E Windsor ON N8T 3P3",
    "addr:housenumber":"5500",
    "addr:postcode":"n8t 3p3",
    "addr:street":"North Service Rd E",
    "iso:country":"CA",
    "sg:address":"5500 North Service Rd E",
    "sg:city":"Windsor",
    "sg:classifiers":[
        {
            "category":"Professional",
            "subcategory":"Business Services",
            "type":"Services"
        }
    ],
    "sg:phone":"+1 519 945 6338",
    "sg:postcode":"N8T 3P3",
    "sg:province":"ON",
    "sg:tags":[
        "inspection"
    ],
    "wof:name":"Intermodal Transportation Svc",
    "wof:placetype":"venue"
},
  "geometry": {"coordinates":[-82.94451100000001,42.290096],"type":"Point"}
}