{
  "type": "Feature",
  "properties": {
    "iso:country":"CA",
    "sg:address":"520 Plains Rd",
    "sg:city":"East York",
    "sg:classifiers":[
        {
            "category":"Social Services",
            "subcategory":"Child Care",
            "type":"Services"
        }
    ],
    "sg:phone":"+1 416 421 2273",
    "sg:postcode":"M4C 2Z1",
    "sg:province":"ON",
    "wof:name":"Plains Rd Child Care Inc",
    "wof:placetype":"venue"
},
  "geometry": {"coordinates":[-79.3192977905,43.6980476379],"type":"Point"}
}