{
  "type": "Feature",
  "properties": {
    "addr:full":"667 Elgin Mills Rd W Richmond Hill ON L4C 4M3",
    "addr:housenumber":"667",
    "addr:postcode":"l4c 4m3",
    "addr:street":"Elgin Mills Rd W",
    "iso:country":"CA",
    "sg:address":"667 Elgin Mills Rd W",
    "sg:city":"Richmond Hill",
    "sg:classifiers":[
        {
            "category":"Wholesale",
            "subcategory":"Machinery & Supplies",
            "type":"Manufacturing & Wholesale Goods"
        }
    ],
    "sg:phone":"+1 905 884 5438",
    "sg:postcode":"L4C 4M3",
    "sg:province":"ON",
    "sg:tags":[
        "farm",
        "equipment"
    ],
    "wof:name":"Zir Importing",
    "wof:placetype":"venue"
},
  "geometry": {"coordinates":[-79.464676,43.884525],"type":"Point"}
}