{
  "type": "Feature",
  "properties": {
    "iso:country":"CA",
    "sg:address":"999 Av Mceachran",
    "sg:city":"Outremont",
    "sg:classifiers":[
        {
            "category":"Education",
            "subcategory":"Library",
            "type":"Public Place"
        }
    ],
    "sg:phone":"+1 514 495 6231",
    "sg:postcode":"H2V 3E6",
    "sg:province":"QC",
    "sg:tags":[
        "government"
    ],
    "wof:name":"Outremont Patinoire",
    "wof:placetype":"venue"
},
  "geometry": {"coordinates":[-73.619156,45.519478],"type":"Point"}
}