{
  "type": "Feature",
  "properties": {
    "iso:country":"CA",
    "sg:city":"Laval",
    "sg:classifiers":[
        {
            "category":"Retail",
            "subcategory":"Self-service Laundry",
            "type":"Services"
        }
    ],
    "sg:phone":"+1 450 663 7181",
    "sg:postcode":"H7N 1J1",
    "sg:province":"QC",
    "wof:name":"Lavoir Plus",
    "wof:placetype":"venue"
},
  "geometry": {"coordinates":[-73.7010345459,45.565284729],"type":"Point"}
}