{
  "type": "Feature",
  "properties": {
    "addr:full":"16 Westminster Ave Toronto ON M6R 1N4",
    "addr:housenumber":"16",
    "addr:postcode":"m6r 1n4",
    "addr:street":"Westminster Ave",
    "iso:country":"CA",
    "sg:address":"16 Westminster Ave",
    "sg:city":"Toronto",
    "sg:classifiers":[
        {
            "category":"Professional",
            "subcategory":"Lawyer & Legal Services",
            "type":"Services"
        }
    ],
    "sg:phone":"+1 416 537 2424",
    "sg:postcode":"M6R 1N4",
    "sg:province":"ON",
    "sg:tags":[
        "attorney"
    ],
    "wof:name":"Boorne, Steven",
    "wof:placetype":"venue"
},
  "geometry": {"coordinates":[-79.4453430176,43.6481399536],"type":"Point"}
}