{
  "type": "Feature",
  "properties": {
    "addr:full":"8 Leonard Dr Sussex NB E4E 5S1",
    "addr:housenumber":"8",
    "addr:postcode":"e4e 5s1",
    "addr:street":"Leonard Dr",
    "iso:country":"CA",
    "sg:address":"8 Leonard Dr",
    "sg:city":"Sussex",
    "sg:classifiers":[
        {
            "category":"Organizations",
            "subcategory":"Professional Association",
            "type":"Services"
        }
    ],
    "sg:phone":"+1 506 432 9535",
    "sg:postcode":"E4E 5S1",
    "sg:province":"NB",
    "wof:name":"Kings County Soccer Assn",
    "wof:placetype":"venue"
},
  "geometry": {"coordinates":[-65.4966583252,45.7247390747],"type":"Point"}
}