{
  "type": "Feature",
  "properties": {
    "addr:full":"Victoria BC V9B 1V9",
    "addr:postcode":"v9b 1v9",
    "iso:country":"CA",
    "sg:city":"Victoria",
    "sg:classifiers":[
        {
            "category":"Retail",
            "subcategory":"Repair Shop",
            "type":"Services"
        }
    ],
    "sg:phone":"+1 250 478 9709",
    "sg:postcode":"V9B 1V9",
    "sg:province":"BC",
    "sg:tags":[
        "lock",
        "safe",
        "locksmith",
        "vault"
    ],
    "wof:name":"Acme Safe Ltd",
    "wof:placetype":"venue"
},
  "geometry": {"coordinates":[-123.364517212,48.428314209],"type":"Point"}
}