{
  "type": "Feature",
  "properties": {
    "addr:full":"Labrador City NL A2V 1L1",
    "addr:postcode":"a2v 1l1",
    "iso:country":"CA",
    "sg:city":"Labrador City",
    "sg:classifiers":[
        {
            "category":"Shopping",
            "subcategory":"Gifts & Souvenirs",
            "type":"Retail Goods"
        }
    ],
    "sg:phone":"+1 709 944 3012",
    "sg:postcode":"A2V 1L1",
    "sg:province":"NL",
    "sg:tags":[
        "shop",
        "pharmacy"
    ],
    "wof:name":"Manstan Drugs",
    "wof:placetype":"venue"
},
  "geometry": {"coordinates":[-66.9095916748,52.9431266785],"type":"Point"}
}