{
  "type": "Feature",
  "properties": {
    "addr:full":"1125 St Clair Ave W Toronto ON M6E 1B1",
    "addr:housenumber":"1125",
    "addr:postcode":"m6e 1b1",
    "addr:street":"St Clair Ave W",
    "iso:country":"CA",
    "sg:address":"1125 St Clair Ave W",
    "sg:city":"Toronto",
    "sg:classifiers":[
        {
            "category":"Shopping",
            "subcategory":"Discount & Variety Stores",
            "type":"Retail Goods"
        }
    ],
    "sg:phone":"+1 416 654 7048",
    "sg:postcode":"M6E 1B1",
    "sg:province":"ON",
    "wof:name":"Tony's Variety",
    "wof:placetype":"venue"
},
  "geometry": {"coordinates":[-79.441467,43.67815],"type":"Point"}
}