{
  "type": "Feature",
  "properties": {
    "addr:full":"1525 Beryl St Quesnel BC V2J 4L8",
    "addr:housenumber":"1525",
    "addr:postcode":"v2j 4l8",
    "addr:street":"Beryl St",
    "iso:country":"CA",
    "sg:address":"1525 Beryl St",
    "sg:city":"Quesnel",
    "sg:classifiers":[
        {
            "category":"Education",
            "subcategory":"School",
            "type":"Public Place"
        }
    ],
    "sg:phone":"+1 250 747 2009",
    "sg:postcode":"V2J 4L8",
    "sg:province":"BC",
    "wof:name":"Lakeview Elementary School",
    "wof:placetype":"venue"
},
  "geometry": {"coordinates":[-122.498245,52.978119],"type":"Point"}
}