{
  "type": "Feature",
  "properties": {
    "addr:full":"Edmonton AB T5J 3N6",
    "addr:postcode":"t5j 3n6",
    "iso:country":"CA",
    "sg:city":"Edmonton",
    "sg:classifiers":[
        {
            "category":"Professional",
            "subcategory":"Accounting & Tax Preparation",
            "type":"Services"
        }
    ],
    "sg:phone":"+1 780 424 8833",
    "sg:postcode":"T5J 3N6",
    "sg:province":"AB",
    "sg:tags":[
        "accountant"
    ],
    "wof:name":"Durocher, Jackie M CA",
    "wof:placetype":"venue"
},
  "geometry": {"coordinates":[-113.49763488799999,53.5407485962],"type":"Point"}
}