{
  "type": "Feature",
  "properties": {
    "addr:full":"1200 Bay St Toronto ON M5R 2A5",
    "addr:housenumber":"1200",
    "addr:postcode":"m5r 2a5",
    "addr:street":"Bay St",
    "iso:country":"CA",
    "sg:address":"1200 Bay St",
    "sg:city":"Toronto",
    "sg:classifiers":[
        {
            "category":"Professional",
            "subcategory":"Employment Agencies",
            "type":"Services"
        }
    ],
    "sg:phone":"+1 416 961 6100",
    "sg:postcode":"M5R 2A5",
    "sg:province":"ON",
    "sg:tags":[
        "consultant",
        "search",
        "executive"
    ],
    "wof:name":"Management One Consultants",
    "wof:placetype":"venue"
},
  "geometry": {"coordinates":[-79.38962554930001,43.6697387695],"type":"Point"}
}