{
  "type": "Feature",
  "properties": {
    "addr:full":"Mont-Royal QC H4T 1M4",
    "addr:postcode":"h4t 1m4",
    "iso:country":"CA",
    "sg:city":"Mont-Royal",
    "sg:classifiers":[
        {
            "category":"Professional",
            "subcategory":"Business Services",
            "type":"Services"
        }
    ],
    "sg:phone":"+1 514 736 0576",
    "sg:postcode":"H4T 1M4",
    "sg:province":"QC",
    "sg:tags":[
        "packaging"
    ],
    "wof:name":"Reparation & Installation",
    "wof:placetype":"venue"
},
  "geometry": {"coordinates":[-73.680603,45.4893],"type":"Point"}
}