{
  "type": "Feature",
  "properties": {
    "addr:full":"1594 Nicholson St S Prince George BC V2N 1V6",
    "addr:housenumber":"1594",
    "addr:postcode":"v2n 1v6",
    "addr:street":"Nicholson St S",
    "iso:country":"CA",
    "sg:address":"1594 Nicholson St S",
    "sg:city":"Prince George",
    "sg:classifiers":[
        {
            "category":"Wholesale",
            "subcategory":"Auto Parts",
            "type":"Manufacturing & Wholesale Goods"
        }
    ],
    "sg:phone":"+1 250 562 4979",
    "sg:postcode":"V2N 1V6",
    "sg:province":"BC",
    "sg:tags":[
        "fabricator",
        "truck",
        "aluminum",
        "accessory"
    ],
    "wof:name":"Interior Offroad Equipment Ltd",
    "wof:placetype":"venue"
},
  "geometry": {"coordinates":[-122.786705,53.908989],"type":"Point"}
}