{
  "type": "Feature",
  "properties": {
    "addr:full":"3765 Boul Saint-Martin O Laval QC H7T 1A7",
    "addr:housenumber":"3765",
    "addr:postcode":"h7t 1a7",
    "addr:street":"Boul Saint-Martin O",
    "iso:country":"CA",
    "sg:address":"3765 Boul Saint-Martin O",
    "sg:city":"Laval",
    "sg:classifiers":[
        {
            "category":"Autos & Motor Vehicles",
            "subcategory":"Fuel & Gas Station",
            "type":"Retail Goods"
        }
    ],
    "sg:phone":"+1 450 681 2122",
    "sg:postcode":"H7T 1A7",
    "sg:province":"QC",
    "sg:tags":[
        "oil"
    ],
    "wof:name":"Libre Service Shell N Lube",
    "wof:placetype":"venue"
},
  "geometry": {"coordinates":[-73.757378,45.552971],"type":"Point"}
}