{
  "type": "Feature",
  "properties": {
    "iso:country":"CA",
    "sg:city":"Montreal",
    "sg:classifiers":[
        {
            "category":"Insurance",
            "subcategory":"Insurance Agent",
            "type":"Services"
        }
    ],
    "sg:phone":"+1 514 274 3551",
    "sg:postcode":"H3N 1X1",
    "sg:province":"QC",
    "sg:tags":[
        "adjuster"
    ],
    "wof:name":"Bureau D'Ajustement Cntntl Ltd",
    "wof:placetype":"venue"
},
  "geometry": {"coordinates":[-73.619835,45.529636],"type":"Point"}
}