{
  "type": "Feature",
  "properties": {
    "addr:full":"7 Toffee Crt Etobicoke ON M8V 3B9",
    "addr:housenumber":"7",
    "addr:postcode":"m8v 3b9",
    "addr:street":"Toffee Crt",
    "iso:country":"CA",
    "sg:address":"7 Toffee Crt",
    "sg:city":"Etobicoke",
    "sg:classifiers":[
        {
            "category":"Manufacturing",
            "subcategory":"Printing",
            "type":"Manufacturing & Wholesale Goods"
        }
    ],
    "sg:phone":"+1 416 252 3307",
    "sg:postcode":"M8V 3B9",
    "sg:province":"ON",
    "sg:tags":[
        "printer"
    ],
    "wof:name":"Allforms Service Printing Ltd",
    "wof:placetype":"venue"
},
  "geometry": {"coordinates":[-79.50709500000001,43.605698],"type":"Point"}
}