{
  "type": "Feature",
  "properties": {
    "addr:full":"50 Rte Du Golf Le Bic QC G0L 1B0",
    "addr:housenumber":"50",
    "addr:postcode":"g0l 1b0",
    "addr:street":"Rte Du Golf Le Bic",
    "iso:country":"CA",
    "sg:address":"50 Rte Du Golf",
    "sg:city":"Le Bic",
    "sg:classifiers":[
        {
            "category":"Cinema",
            "subcategory":"Movie Theater",
            "type":"Entertainment"
        }
    ],
    "sg:phone":"+1 418 736 4141",
    "sg:postcode":"G0L 1B0",
    "sg:province":"QC",
    "sg:tags":[
        "equipment",
        "theatrical",
        "supply"
    ],
    "wof:name":"Theatre Les Gens D'En Bas",
    "wof:placetype":"venue"
},
  "geometry": {"coordinates":[-68.7069320679,48.3737983704],"type":"Point"}
}