{
  "type": "Feature",
  "properties": {
    "addr:full":"Chilliwack BC V2R 3M7",
    "addr:postcode":"v2r 3m7",
    "iso:country":"CA",
    "sg:city":"Chilliwack",
    "sg:classifiers":[
        {
            "category":"Health Services",
            "subcategory":"Doctor",
            "type":"Services"
        }
    ],
    "sg:phone":"+1 604 858 4441",
    "sg:postcode":"V2R 3M7",
    "sg:province":"BC",
    "sg:tags":[
        "dentist"
    ],
    "wof:name":"Liem, Miriam DDS",
    "wof:placetype":"venue"
},
  "geometry": {"coordinates":[-121.961868,49.105007],"type":"Point"}
}