{
  "type": "Feature",
  "properties": {
    "iso:country":"CA",
    "sg:address":"RR 2",
    "sg:city":"Thorndale",
    "sg:classifiers":[
        {
            "category":"Professional",
            "subcategory":"Computer Services",
            "type":"Services"
        }
    ],
    "sg:phone":"+1 519 670 6152",
    "sg:postcode":"N0M 2P0",
    "sg:province":"ON",
    "sg:tags":[
        "consultant"
    ],
    "wof:name":"Computer Hand Inc",
    "wof:placetype":"venue"
},
  "geometry": {"coordinates":[-81.1411819458,43.1051330566],"type":"Point"}
}