{
  "type": "Feature",
  "properties": {
    "addr:full":"292 Rue Duquette O Gatineau QC J8P 2Z9",
    "addr:housenumber":"292",
    "addr:postcode":"j8p 2z9",
    "addr:street":"Rue Duquette O",
    "iso:country":"CA",
    "sg:address":"292 Rue Duquette O",
    "sg:city":"Gatineau",
    "sg:classifiers":[
        {
            "category":"Personal",
            "subcategory":"Beauty Salon",
            "type":"Services"
        }
    ],
    "sg:phone":"+1 819 663 3347",
    "sg:postcode":"J8P 2Z9",
    "sg:province":"QC",
    "wof:name":"Salon Passe-Partout Enr",
    "wof:placetype":"venue"
},
  "geometry": {"coordinates":[-75.659019,45.49015],"type":"Point"}
}