{
  "type": "Feature",
  "properties": {
    "addr:full":"Notre-Dame-Du-Lac QC G0L 1X0",
    "addr:postcode":"g0l 1x0",
    "iso:country":"CA",
    "sg:city":"Notre-Dame-Du-Lac",
    "sg:classifiers":[
        {
            "category":"Building & Trades",
            "subcategory":"Construction",
            "type":"Services"
        }
    ],
    "sg:phone":"+1 418 899 0904",
    "sg:postcode":"G0L 1X0",
    "sg:province":"QC",
    "sg:tags":[
        "maker",
        "cabinet"
    ],
    "wof:name":"Ebenisterie Michel Ferland",
    "wof:placetype":"venue"
},
  "geometry": {"coordinates":[-68.796081543,47.6108055115],"type":"Point"}
}