{
  "type": "Feature",
  "properties": {
    "addr:full":"Surrey BC V3W 1E6",
    "addr:postcode":"v3w 1e6",
    "iso:country":"CA",
    "sg:city":"Surrey",
    "sg:classifiers":[
        {
            "category":"Home & Garden",
            "subcategory":"Building Materials",
            "type":"Retail Goods"
        }
    ],
    "sg:phone":"+1 604 590 0106",
    "sg:postcode":"V3W 1E6",
    "sg:province":"BC",
    "sg:tags":[
        "windows"
    ],
    "wof:name":"Easi-Serv Products Inc",
    "wof:placetype":"venue"
},
  "geometry": {"coordinates":[-122.86792755099999,49.1410598755],"type":"Point"}
}