{
  "type": "Feature",
  "properties": {
    "addr:full":"15330 24 Ave Surrey BC V4A 2J1",
    "addr:housenumber":"15330",
    "addr:postcode":"v4a 2j1",
    "addr:street":"24 Ave",
    "iso:country":"CA",
    "sg:address":"15330 24 Ave",
    "sg:city":"Surrey",
    "sg:classifiers":[
        {
            "category":"Shopping",
            "subcategory":"Clothing, Apparel, & Fashions",
            "type":"Retail Goods"
        }
    ],
    "sg:phone":"+1 604 536 9640",
    "sg:postcode":"V4A 2J1",
    "sg:province":"BC",
    "sg:tags":[
        "tailor"
    ],
    "wof:name":"Lena's Tailors",
    "wof:placetype":"venue"
},
  "geometry": {"coordinates":[-122.79750799999999,49.045422],"type":"Point"}
}