{
  "type": "Feature",
  "properties": {
    "addr:full":"25 Main St Grand Bend ON N0M 1T0",
    "addr:housenumber":"25",
    "addr:postcode":"n0m 1t0",
    "addr:street":"Main St",
    "iso:country":"CA",
    "sg:address":"25 Main St",
    "sg:city":"Grand Bend",
    "sg:classifiers":[
        {
            "category":"Organizations",
            "subcategory":"Religious Organization",
            "type":"Services"
        }
    ],
    "sg:phone":"+1 519 238 2402",
    "sg:postcode":"N0M 1T0",
    "sg:province":"ON",
    "sg:tags":[
        "church"
    ],
    "wof:name":"Grand Bend United Church",
    "wof:placetype":"venue"
},
  "geometry": {"coordinates":[-81.7587966919,43.3133850098],"type":"Point"}
}