{
  "type": "Feature",
  "properties": {
    "addr:full":"46 Rue Principale Aylmer QC J9H 3L3",
    "addr:housenumber":"46",
    "addr:postcode":"j9h 3l3",
    "addr:street":"Rue Principale",
    "iso:country":"CA",
    "sg:address":"46 Rue Principale",
    "sg:city":"Aylmer",
    "sg:classifiers":[
        {
            "category":"Home & Garden",
            "subcategory":"Building Materials",
            "type":"Retail Goods"
        }
    ],
    "sg:phone":"+1 819 684 1212",
    "sg:postcode":"J9H 3L3",
    "sg:province":"QC",
    "sg:tags":[
        "glass",
        "door"
    ],
    "wof:name":"Vitrerie Jean-Pierre",
    "wof:placetype":"venue"
},
  "geometry": {"coordinates":[-75.8500289917,45.3945007324],"type":"Point"}
}