{
  "type": "Feature",
  "properties": {
    "iso:country":"CA",
    "sg:address":"30 Saint Regis Cres N",
    "sg:city":"North York",
    "sg:classifiers":[
        {
            "category":"Autos & Motor Vehicles",
            "subcategory":"Auto Supplies",
            "type":"Retail Goods"
        }
    ],
    "sg:phone":"+1 416 630 4531",
    "sg:postcode":"M3J 1Z2",
    "sg:province":"ON",
    "sg:tags":[
        "equipment",
        "air",
        "conditioning",
        "automobile"
    ],
    "wof:name":"Cars Complete Automotive",
    "wof:placetype":"venue"
},
  "geometry": {"coordinates":[-79.485275,43.756275],"type":"Point"}
}