{
  "type": "Feature",
  "properties": {
    "addr:full":"1300 Boul Saint-Jean-Baptiste Pointe-Aux-Trembles QC H1B 4A4",
    "addr:housenumber":"1300",
    "addr:postcode":"h1b 4a4",
    "addr:street":"Boul Saint-Jean-Baptiste",
    "iso:country":"CA",
    "sg:address":"1300 Boul Saint-Jean-Baptiste",
    "sg:city":"Pointe-Aux-Trembles",
    "sg:classifiers":[
        {
            "category":"Cinema",
            "subcategory":"Movie Rental",
            "type":"Entertainment"
        }
    ],
    "sg:phone":"+1 514 640 1300",
    "sg:postcode":"H1B 4A4",
    "sg:province":"QC",
    "sg:tags":[
        "leasing",
        "video",
        "disc",
        "tape"
    ],
    "wof:name":"Superclub Videotron",
    "wof:placetype":"venue"
},
  "geometry": {"coordinates":[-73.501999,45.641743],"type":"Point"}
}