{
  "type": "Feature",
  "properties": {
    "iso:country":"CA",
    "sg:city":"Sundre",
    "sg:classifiers":[
        {
            "category":"Social Services",
            "subcategory":"Adult Care",
            "type":"Services"
        }
    ],
    "sg:phone":"+1 403 638 4833",
    "sg:postcode":"T0M 1X0",
    "sg:province":"AB",
    "sg:tags":[
        "senior",
        "housing",
        "citizen"
    ],
    "wof:name":"Foothills Lodge",
    "wof:placetype":"venue"
},
  "geometry": {"coordinates":[-114.640861511,51.7985572815],"type":"Point"}
}