{
  "type": "Feature",
  "properties": {
    "addr:full":"8815 92 St NW Edmonton AB T6C 3P9",
    "addr:housenumber":"8815",
    "addr:postcode":"t6c 3p9",
    "addr:street":"92 St Nw",
    "iso:country":"CA",
    "sg:address":"8815 92 St NW",
    "sg:city":"Edmonton",
    "sg:classifiers":[
        {
            "category":"Personal",
            "subcategory":"Beauty Salon",
            "type":"Services"
        }
    ],
    "sg:phone":"+1 780 469 8103",
    "sg:postcode":"T6C 3P9",
    "sg:province":"AB",
    "wof:name":"Exalte Le Salon Ltd",
    "wof:placetype":"venue"
},
  "geometry": {"coordinates":[-113.46809399999999,53.523884],"type":"Point"}
}