{
  "type": "Feature",
  "properties": {
    "addr:full":"Scarborough ON M1S 3L1",
    "addr:postcode":"m1s 3l1",
    "iso:country":"CA",
    "sg:city":"Scarborough",
    "sg:classifiers":[
        {
            "category":"Wholesale",
            "subcategory":"Non-durable Goods",
            "type":"Manufacturing & Wholesale Goods"
        }
    ],
    "sg:phone":"+1 416 646 1175",
    "sg:postcode":"M1S 3L1",
    "sg:province":"ON",
    "sg:tags":[
        "advertising"
    ],
    "wof:name":"Neurasa Limited",
    "wof:placetype":"venue"
},
  "geometry": {"coordinates":[-79.257217,43.792564],"type":"Point"}
}