{
  "type": "Feature",
  "properties": {
    "addr:full":"460 Dawes Rd East York ON M4B 2E9",
    "addr:housenumber":"460",
    "addr:postcode":"m4b 2e9",
    "addr:street":"Dawes Rd",
    "iso:country":"CA",
    "sg:address":"460 Dawes Rd",
    "sg:city":"East York",
    "sg:classifiers":[
        {
            "category":"Personal",
            "subcategory":"Beauty Salon",
            "type":"Services"
        }
    ],
    "sg:phone":"+1 416 750 0465",
    "sg:postcode":"M4B 2E9",
    "sg:province":"ON",
    "wof:name":"Urban Image Hair Studio",
    "wof:placetype":"venue"
},
  "geometry": {"coordinates":[-79.2970504761,43.7029838562],"type":"Point"}
}