{
  "type": "Feature",
  "properties": {
    "addr:full":"9082 Clarkson Ave Black Creek BC V9J 1B3",
    "addr:housenumber":"9082",
    "addr:postcode":"v9j 1b3",
    "addr:street":"Clarkson Ave",
    "iso:country":"CA",
    "sg:address":"9082 Clarkson Ave",
    "sg:city":"Black Creek",
    "sg:classifiers":[
        {
            "category":"Utilities",
            "subcategory":"Water",
            "type":"Services"
        }
    ],
    "sg:phone":"+1 250 337 5979",
    "sg:postcode":"V9J 1B3",
    "sg:province":"BC",
    "sg:tags":[
        "company",
        "sewage"
    ],
    "wof:name":"Watutco Enterprises Ltd",
    "wof:placetype":"venue"
},
  "geometry": {"coordinates":[-125.135002,49.843006],"type":"Point"}
}