{
  "type": "Feature",
  "properties": {
    "iso:country":"CA",
    "sg:address":"RR 2 Box 3633",
    "sg:city":"Corner Brook",
    "sg:classifiers":[
        {
            "category":"Cinema",
            "subcategory":"Movie Rental",
            "type":"Entertainment"
        }
    ],
    "sg:phone":"+1 709 783 3000",
    "sg:postcode":"A2H 6B9",
    "sg:province":"NL",
    "sg:tags":[
        "leasing",
        "video",
        "disc",
        "tape"
    ],
    "wof:name":"Meadows Home Entertainment",
    "wof:placetype":"venue"
},
  "geometry": {"coordinates":[-57.94947052,48.9501991272],"type":"Point"}
}