{
  "type": "Feature",
  "properties": {
    "iso:country":"CA",
    "sg:address":"4 Crannberry Crt",
    "sg:city":"Halifax",
    "sg:classifiers":[
        {
            "category":"Organizations",
            "subcategory":"Professional Association",
            "type":"Services"
        }
    ],
    "sg:phone":"+1 902 446 3130",
    "sg:postcode":"B3R 2E5",
    "sg:province":"NS",
    "wof:name":"Greystone Drive Tenants Assn",
    "wof:placetype":"venue"
},
  "geometry": {"coordinates":[-63.6129074097,44.5998458862],"type":"Point"}
}