{
  "type": "Feature",
  "properties": {
    "addr:full":"132 Woolwich St N Kitchener ON N2K 1S4",
    "addr:housenumber":"132",
    "addr:postcode":"n2k 1s4",
    "addr:street":"Woolwich St N",
    "iso:country":"CA",
    "sg:address":"132 Woolwich St N",
    "sg:city":"Kitchener",
    "sg:classifiers":[
        {
            "category":"Local Transit",
            "type":"Transportation"
        }
    ],
    "sg:phone":"+1 519 742 0805",
    "sg:postcode":"N2K 1S4",
    "sg:province":"ON",
    "sg:tags":[
        "airport"
    ],
    "wof:name":"Alternative Airport Svc",
    "wof:placetype":"venue"
},
  "geometry": {"coordinates":[-80.48273500000001,43.486958],"type":"Point"}
}