{
  "type": "Feature",
  "properties": {
    "addr:full":"3277 Westfield Rd Saint John NB E2M 7B5",
    "addr:housenumber":"3277",
    "addr:postcode":"e2m 7b5",
    "addr:street":"Westfield Rd",
    "iso:country":"CA",
    "sg:address":"3277 Westfield Rd",
    "sg:city":"Saint John",
    "sg:classifiers":[
        {
            "category":"Health Services",
            "subcategory":"Nursing And Care Facility",
            "type":"Services"
        }
    ],
    "sg:phone":"+1 506 738 2917",
    "sg:postcode":"E2M 7B5",
    "sg:province":"NB",
    "sg:tags":[
        "home",
        "rest"
    ],
    "wof:name":"Seely Lodge For Seniors",
    "wof:placetype":"venue"
},
  "geometry": {"coordinates":[-66.192818,45.289108],"type":"Point"}
}