{
  "type": "Feature",
  "properties": {
    "iso:country":"CA",
    "sg:address":"1085 Princess St",
    "sg:city":"Kingston",
    "sg:classifiers":[
        {
            "category":"Professional",
            "type":"Services"
        }
    ],
    "sg:phone":"+1 613 531 8053",
    "sg:postcode":"K7L 1H3",
    "sg:province":"ON",
    "sg:tags":[
        "fire",
        "restoration",
        "establishment",
        "damage"
    ],
    "wof:name":"Signature Professional Clng",
    "wof:placetype":"venue"
},
  "geometry": {"coordinates":[-76.5174331665,44.2440795898],"type":"Point"}
}