{
  "type": "Feature",
  "properties": {
    "iso:country":"CA",
    "sg:city":"Calgary",
    "sg:classifiers":[
        {
            "category":"Manufacturing",
            "subcategory":"Metals",
            "type":"Manufacturing & Wholesale Goods"
        }
    ],
    "sg:phone":"+1 403 269 1870",
    "sg:postcode":"T2G 1P5",
    "sg:province":"AB",
    "sg:tags":[
        "steel"
    ],
    "wof:name":"Plains Fabrication & Supply",
    "wof:placetype":"venue"
},
  "geometry": {"coordinates":[-114.043212891,51.031993866],"type":"Point"}
}