{
  "type": "Feature",
  "properties": {
    "addr:full":"74 Facer St St Catharines ON L2M 5J2",
    "addr:housenumber":"74",
    "addr:postcode":"l2m 5j2",
    "addr:street":"Facer St",
    "iso:country":"CA",
    "sg:address":"74 Facer St",
    "sg:city":"St Catharines",
    "sg:classifiers":[
        {
            "category":"Personal",
            "subcategory":"Beauty Salon",
            "type":"Services"
        }
    ],
    "sg:phone":"+1 905 646 1464",
    "sg:postcode":"L2M 5J2",
    "sg:province":"ON",
    "wof:name":"Deby's Hair Biz",
    "wof:placetype":"venue"
},
  "geometry": {"coordinates":[-79.2231826782,43.1764526367],"type":"Point"}
}