{
  "type": "Feature",
  "properties": {
    "addr:full":"4003 34E Av Shawinigan QC G9N 7J1",
    "addr:housenumber":"4003",
    "addr:postcode":"g9n 7j1",
    "addr:street":"34E Av",
    "iso:country":"CA",
    "sg:address":"4003 34E Av",
    "sg:city":"Shawinigan",
    "sg:classifiers":[
        {
            "category":"Organizations",
            "subcategory":"Professional Association",
            "type":"Services"
        }
    ],
    "sg:phone":"+1 819 539 3549",
    "sg:postcode":"G9N 7J1",
    "sg:province":"QC",
    "wof:name":"Loisirs Assomption",
    "wof:placetype":"venue"
},
  "geometry": {"coordinates":[-72.7474746704,46.5754356384],"type":"Point"}
}