{
  "type": "Feature",
  "properties": {
    "addr:full":"Winnipeg MB R3J 0H2",
    "addr:postcode":"r3j 0h2",
    "iso:country":"CA",
    "sg:city":"Winnipeg",
    "sg:classifiers":[
        {
            "category":"Personal",
            "subcategory":"Beauty Salon",
            "type":"Services"
        }
    ],
    "sg:phone":"+1 204 774 8146",
    "sg:postcode":"R3J 0H2",
    "sg:province":"MB",
    "sg:tags":[
        "manicuring"
    ],
    "wof:name":"Hollywood Nails",
    "wof:placetype":"venue"
},
  "geometry": {"coordinates":[-97.218262,49.878445],"type":"Point"}
}