{
  "type": "Feature",
  "properties": {
    "addr:full":"115 Avenue B E Wynyard SK S0A 4T0",
    "addr:housenumber":"115",
    "addr:postcode":"s0a 4t0",
    "addr:street":"Avenue B E Wynyard",
    "iso:country":"CA",
    "sg:address":"115 Avenue B E",
    "sg:city":"Wynyard",
    "sg:classifiers":[
        {
            "category":"Professional",
            "subcategory":"Lawyer & Legal Services",
            "type":"Services"
        }
    ],
    "sg:phone":"+1 306 554 2523",
    "sg:postcode":"S0A 4T0",
    "sg:province":"SK",
    "sg:tags":[
        "attorney"
    ],
    "wof:name":"Klebeck Law Office",
    "wof:placetype":"venue"
},
  "geometry": {"coordinates":[-104.170417786,51.7707633972],"type":"Point"}
}