{
  "type": "Feature",
  "properties": {
    "addr:full":"Rl 41 8 13 E Hadashville MB R0E 0X0",
    "addr:housenumber":"41;13 e",
    "addr:postcode":"r0e 0x0",
    "addr:street":"8;Hadashville",
    "iso:country":"CA",
    "sg:address":"Rl 41 8 13 E",
    "sg:city":"Hadashville",
    "sg:classifiers":[
        {
            "category":"Travel",
            "subcategory":"Hotels & Motels",
            "type":"Entertainment"
        }
    ],
    "sg:phone":"+1 204 426 2104",
    "sg:postcode":"R0E 0X0",
    "sg:province":"MB",
    "wof:name":"Mc Munn Motor Hotel",
    "wof:placetype":"venue"
},
  "geometry": {"coordinates":[-95.9069900513,49.6847076416],"type":"Point"}
}