{
  "type": "Feature",
  "properties": {
    "addr:full":"6612 Rue Saint-Hubert Montreal QC H2S 2M3",
    "addr:housenumber":"6612",
    "addr:postcode":"h2s 2m3",
    "addr:street":"Rue Saint-Hubert",
    "iso:country":"CA",
    "sg:address":"6612 Rue Saint-Hubert",
    "sg:city":"Montreal",
    "sg:classifiers":[
        {
            "category":"Home & Garden",
            "subcategory":"Home Furnishings",
            "type":"Retail Goods"
        }
    ],
    "sg:phone":"+1 514 277 9515",
    "sg:postcode":"H2S 2M3",
    "sg:province":"QC",
    "sg:tags":[
        "curtain",
        "made",
        "drapery"
    ],
    "wof:name":"Draperies Rayons Bleus Inc",
    "wof:placetype":"venue"
},
  "geometry": {"coordinates":[-73.605042,45.5369],"type":"Point"}
}