{
  "type": "Feature",
  "properties": {
    "addr:full":"3640 Weston Rd # 4 North York ON M9L 1W2",
    "addr:housenumber":"3640",
    "addr:postcode":"m9l 1w2",
    "addr:street":"Weston Rd # 4",
    "iso:country":"CA",
    "sg:address":"3640 Weston Rd # 4",
    "sg:city":"North York",
    "sg:classifiers":[
        {
            "category":"Home & Garden",
            "subcategory":"Building Materials",
            "type":"Retail Goods"
        }
    ],
    "sg:phone":"+1 416 748 1333",
    "sg:postcode":"M9L 1W2",
    "sg:province":"ON",
    "sg:tags":[
        "shutter"
    ],
    "wof:name":"Mastercraft Shutters",
    "wof:placetype":"venue"
},
  "geometry": {"coordinates":[-79.54435700000001,43.759434],"type":"Point"}
}