{
  "type": "Feature",
  "properties": {
    "addr:full":"1697 Melwood Dr Kerwood ON N0M 2B0",
    "addr:housenumber":"1697",
    "addr:postcode":"n0m 2b0",
    "addr:street":"Melwood Dr",
    "iso:country":"CA",
    "sg:address":"1697 Melwood Dr",
    "sg:city":"Kerwood",
    "sg:classifiers":[
        {
            "category":"Organizations",
            "subcategory":"Religious Organization",
            "type":"Services"
        }
    ],
    "sg:phone":"+1 519 247 1117",
    "sg:postcode":"N0M 2B0",
    "sg:province":"ON",
    "sg:tags":[
        "church"
    ],
    "wof:name":"Church in Metcalfe",
    "wof:placetype":"venue"
},
  "geometry": {"coordinates":[-81.7437667847,42.9438934326],"type":"Point"}
}