{
  "type": "Feature",
  "properties": {
    "iso:country":"CA",
    "sg:address":"1103 Victoria Park Ave",
    "sg:city":"Scarborough",
    "sg:classifiers":[
        {
            "category":"Shopping",
            "subcategory":"Discount & Variety Stores",
            "type":"Retail Goods"
        }
    ],
    "sg:phone":"+1 416 759 4093",
    "sg:postcode":"M4B 2K2",
    "sg:province":"ON",
    "wof:name":"V P St Clair Variety",
    "wof:placetype":"venue"
},
  "geometry": {"coordinates":[-79.295624,43.708328],"type":"Point"}
}