{
  "type": "Feature",
  "properties": {
    "iso:country":"CA",
    "sg:city":"New Westminster",
    "sg:classifiers":[
        {
            "category":"Social Services",
            "type":"Services"
        }
    ],
    "sg:phone":"+1 604 520 0009",
    "sg:postcode":"V3M 2J3",
    "sg:province":"BC",
    "sg:tags":[
        "organization",
        "welfare"
    ],
    "wof:name":"Cameray Centre",
    "wof:placetype":"venue"
},
  "geometry": {"coordinates":[-122.922210693,49.2141456604],"type":"Point"}
}