{
  "type": "Feature",
  "properties": {
    "addr:full":"401 Pido Rd Peterborough ON K9J 6X7",
    "addr:housenumber":"401",
    "addr:postcode":"k9j 6x7",
    "addr:street":"Pido Rd",
    "iso:country":"CA",
    "sg:address":"401 Pido Rd",
    "sg:city":"Peterborough",
    "sg:classifiers":[
        {
            "category":"Professional",
            "subcategory":"Engineering",
            "type":"Services"
        }
    ],
    "sg:phone":"+1 705 876 0226",
    "sg:postcode":"K9J 6X7",
    "sg:province":"ON",
    "sg:tags":[
        "amusement",
        "devices",
        "engineer"
    ],
    "wof:name":"Jesler Enterprises Inc",
    "wof:placetype":"venue"
},
  "geometry": {"coordinates":[-78.293503,44.276733],"type":"Point"}
}