{
  "type": "Feature",
  "properties": {
    "addr:full":"1650 Av Alexandre-Le-Grand Boisbriand QC J7G 3K1",
    "addr:housenumber":"1650",
    "addr:postcode":"j7g 3k1",
    "addr:street":"Av Alexandre-Le-Grand",
    "iso:country":"CA",
    "sg:address":"1650 Av Alexandre-Le-Grand",
    "sg:city":"Boisbriand",
    "sg:classifiers":[
        {
            "category":"Education",
            "subcategory":"School",
            "type":"Public Place"
        }
    ],
    "sg:phone":"+1 450 433 5514",
    "sg:postcode":"J7G 3K1",
    "sg:province":"QC",
    "wof:name":"Des Grands-Chemins Ecole",
    "wof:placetype":"venue"
},
  "geometry": {"coordinates":[-73.844902,45.621281],"type":"Point"}
}