{
  "type": "Feature",
  "properties": {
    "addr:full":"3480 Fairview St Burlington ON L7N 2R5",
    "addr:housenumber":"3480",
    "addr:postcode":"l7n 2r5",
    "addr:street":"Fairview St",
    "iso:country":"CA",
    "sg:address":"3480 Fairview St",
    "sg:city":"Burlington",
    "sg:classifiers":[
        {
            "category":"Insurance",
            "subcategory":"Insurance Agent",
            "type":"Services"
        }
    ],
    "sg:phone":"+1 905 632 6772",
    "sg:postcode":"L7N 2R5",
    "sg:province":"ON",
    "sg:tags":[
        "travel",
        "agency",
        "bureau"
    ],
    "wof:name":"Caa South Central Ontario",
    "wof:placetype":"venue"
},
  "geometry": {"coordinates":[-79.78141784669999,43.3578605652],"type":"Point"}
}