{
  "type": "Feature",
  "properties": {
    "addr:full":"147 Albion St S Amherst NS B4H 2X2",
    "addr:housenumber":"147",
    "addr:postcode":"b4h 2x2",
    "addr:street":"Albion St S",
    "iso:country":"CA",
    "sg:address":"147 Albion St S",
    "sg:city":"Amherst",
    "sg:classifiers":[
        {
            "category":"Real Estate",
            "subcategory":"Real Estate Operator",
            "type":"Services"
        }
    ],
    "sg:phone":"+1 902 661 1515",
    "sg:postcode":"B4H 2X2",
    "sg:province":"NS",
    "sg:tags":[
        "mall",
        "shopping",
        "center"
    ],
    "wof:name":"Amherst Town Square",
    "wof:placetype":"venue"
},
  "geometry": {"coordinates":[-64.204399,45.815651],"type":"Point"}
}