{
  "type": "Feature",
  "properties": {
    "addr:full":"816 Queen St Saskatoon SK S7K 0N1",
    "addr:housenumber":"816",
    "addr:postcode":"s7k 0n1",
    "addr:street":"Queen St",
    "iso:country":"CA",
    "sg:address":"816 Queen St",
    "sg:city":"Saskatoon",
    "sg:classifiers":[
        {
            "category":"Organizations",
            "subcategory":"Religious Organization",
            "type":"Services"
        }
    ],
    "sg:phone":"+1 306 652 9138",
    "sg:postcode":"S7K 0N1",
    "sg:province":"SK",
    "sg:tags":[
        "church"
    ],
    "wof:name":"Jehovah's Witnesses",
    "wof:placetype":"venue"
},
  "geometry": {"coordinates":[-106.65030670199999,52.1367683411],"type":"Point"}
}