{
  "type": "Feature",
  "properties": {
    "iso:country":"CA",
    "sg:address":"106 Strickland St",
    "sg:city":"Whitehorse",
    "sg:classifiers":[
        {
            "category":"Building & Trades",
            "subcategory":"Construction",
            "type":"Services"
        }
    ],
    "sg:phone":"+1 867 668 7332",
    "sg:postcode":"Y1A 2J5",
    "sg:province":"YT",
    "sg:tags":[
        "wallpaper",
        "painter"
    ],
    "wof:name":"Raymar Painting Contractor",
    "wof:placetype":"venue"
},
  "geometry": {"coordinates":[-135.05305480999999,60.7232055664],"type":"Point"}
}