{
  "type": "Feature",
  "properties": {
    "addr:full":"105 Ominica St W Moose Jaw SK S6H 1X1",
    "addr:housenumber":"105",
    "addr:postcode":"s6h 1x1",
    "addr:street":"Ominica St W",
    "iso:country":"CA",
    "sg:address":"105 Ominica St W",
    "sg:city":"Moose Jaw",
    "sg:classifiers":[
        {
            "category":"Home & Garden",
            "subcategory":"Building Materials",
            "type":"Retail Goods"
        }
    ],
    "sg:phone":"+1 306 693 0400",
    "sg:postcode":"S6H 1X1",
    "sg:province":"SK",
    "sg:tags":[
        "paint"
    ],
    "wof:name":"General Paint Ltd",
    "wof:placetype":"venue"
},
  "geometry": {"coordinates":[-105.537689,50.393353],"type":"Point"}
}