{
  "type": "Feature",
  "properties": {
    "addr:full":"390 Rue Notre-Dame-DE-Fatima Laval QC H7G 3Z3",
    "addr:housenumber":"390",
    "addr:postcode":"qc h7g 3z3",
    "addr:street":"Rue Notre-Dame-De-Fatima",
    "iso:country":"CA",
    "sg:address":"390 Rue Notre-Dame-DE-Fatima",
    "sg:city":"Laval",
    "sg:classifiers":[
        {
            "category":"Manufacturing",
            "subcategory":"Signs",
            "type":"Manufacturing & Wholesale Goods"
        }
    ],
    "sg:phone":"+1 514 327 1682",
    "sg:postcode":"H7G 3Z3",
    "sg:province":"QC",
    "wof:name":"Enseignes Mivicom Inc",
    "wof:placetype":"venue"
},
  "geometry": {"coordinates":[-73.67975616459999,45.577381134],"type":"Point"}
}