{
  "type": "Feature",
  "properties": {
    "addr:full":"Foxwarren MB R0J 0R0",
    "addr:postcode":"r0j 0r0",
    "iso:country":"CA",
    "sg:city":"Foxwarren",
    "sg:classifiers":[
        {
            "category":"Home & Garden",
            "subcategory":"Building Materials",
            "type":"Retail Goods"
        }
    ],
    "sg:phone":"+1 204 847 2331",
    "sg:postcode":"R0J 0R0",
    "sg:province":"MB",
    "sg:tags":[
        "mixed",
        "concrete"
    ],
    "wof:name":"Prairie Concrete",
    "wof:placetype":"venue"
},
  "geometry": {"coordinates":[-101.150894165,50.5207366943],"type":"Point"}
}