{
  "type": "Feature",
  "properties": {
    "addr:full":"York PE C0A 1P0",
    "addr:postcode":"c0a 1p0",
    "iso:country":"CA",
    "sg:city":"York",
    "sg:classifiers":[
        {
            "category":"Farming",
            "subcategory":"Nursery",
            "type":"Manufacturing & Wholesale Goods"
        }
    ],
    "sg:phone":"+1 902 566 1503",
    "sg:postcode":"C0A 1P0",
    "sg:province":"PE",
    "sg:tags":[
        "center",
        "greenhouse",
        "garden"
    ],
    "wof:name":"York Greenhouses & Garden Ctr",
    "wof:placetype":"venue"
},
  "geometry": {"coordinates":[-63.095089,46.310341],"type":"Point"}
}