{
  "type": "Feature",
  "properties": {
    "addr:full":"84 Second Line W Sault Ste Marie ON P6C 2H9",
    "addr:housenumber":"84",
    "addr:postcode":"p6c 2h9",
    "addr:street":"Second Line W",
    "iso:country":"CA",
    "sg:address":"84 Second Line W",
    "sg:city":"Sault Ste Marie",
    "sg:classifiers":[
        {
            "category":"Wholesale",
            "subcategory":"Meat",
            "type":"Manufacturing & Wholesale Goods"
        }
    ],
    "sg:phone":"+1 705 942 1215",
    "sg:postcode":"P6C 2H9",
    "sg:province":"ON",
    "sg:tags":[
        "butchering"
    ],
    "wof:name":"Bruni's Butcher's Block",
    "wof:placetype":"venue"
},
  "geometry": {"coordinates":[-84.3542709351,46.5377388],"type":"Point"}
}