{
  "type": "Feature",
  "properties": {
    "addr:full":"Vancouver BC V6A 1P3",
    "addr:postcode":"v6a 1p3",
    "iso:country":"CA",
    "sg:city":"Vancouver",
    "sg:classifiers":[
        {
            "category":"Social Services",
            "type":"Services"
        }
    ],
    "sg:phone":"+1 604 685 5548",
    "sg:postcode":"V6A 1P3",
    "sg:province":"BC",
    "sg:tags":[
        "organization",
        "welfare"
    ],
    "wof:name":"Lotus Light Charity Society",
    "wof:placetype":"venue"
},
  "geometry": {"coordinates":[-123.096222,49.281391],"type":"Point"}
}