{
  "type": "Feature",
  "properties": {
    "addr:full":"535 Barton St E Hamilton ON L8L 2Y9",
    "addr:housenumber":"535",
    "addr:postcode":"l8l 2y9",
    "addr:street":"Barton St E",
    "iso:country":"CA",
    "sg:address":"535 Barton St E",
    "sg:city":"Hamilton",
    "sg:classifiers":[
        {
            "category":"Retail",
            "subcategory":"Auto Repair",
            "type":"Services"
        }
    ],
    "sg:phone":"+1 905 561 5823",
    "sg:postcode":"L8L 2Y9",
    "sg:province":"ON",
    "sg:tags":[
        "automobile",
        "lubrication"
    ],
    "wof:name":"Denny's Lube Ctr",
    "wof:placetype":"venue"
},
  "geometry": {"coordinates":[-79.842812,43.258411],"type":"Point"}
}