{
  "type": "Feature",
  "properties": {
    "addr:full":"3603 Boul Des Hetres Shawinigan QC G9N 4T7",
    "addr:housenumber":"3603",
    "addr:postcode":"g9n 4t7",
    "addr:street":"Boul Des Hetres",
    "iso:country":"CA",
    "sg:address":"3603 Boul Des Hetres",
    "sg:city":"Shawinigan",
    "sg:classifiers":[
        {
            "category":"Professional",
            "subcategory":"Art Services",
            "type":"Services"
        }
    ],
    "sg:phone":"+1 819 539 9415",
    "sg:postcode":"G9N 4T7",
    "sg:province":"QC",
    "sg:tags":[
        "graphic",
        "printer",
        "designer"
    ],
    "wof:name":"Imprimerie Shawinigan Enr",
    "wof:placetype":"venue"
},
  "geometry": {"coordinates":[-72.73820499999999,46.565697],"type":"Point"}
}