{
  "type": "Feature",
  "properties": {
    "addr:full":"331 East Victoria St Amherst NS B4H 3Y2",
    "addr:housenumber":"331",
    "addr:postcode":"b4h 3y2",
    "addr:street":"East Victoria St",
    "iso:country":"CA",
    "sg:address":"331 East Victoria St",
    "sg:city":"Amherst",
    "sg:classifiers":[
        {
            "category":"Food & Beverages",
            "subcategory":"Groceries & Convenience Stores",
            "type":"Retail Goods"
        }
    ],
    "sg:phone":"+1 902 667 1640",
    "sg:postcode":"B4H 3Y2",
    "sg:province":"NS",
    "wof:name":"Steamboats Convenience Ctr",
    "wof:placetype":"venue"
},
  "geometry": {"coordinates":[-64.193817,45.843781],"type":"Point"}
}