{
  "type": "Feature",
  "properties": {
    "iso:country":"CA",
    "sg:address":"1086 Trafalgar St",
    "sg:city":"London",
    "sg:classifiers":[
        {
            "category":"Food & Beverages",
            "subcategory":"Bakery",
            "type":"Retail Goods"
        }
    ],
    "sg:phone":"+1 519 451 1521",
    "sg:postcode":"N5Z 1G7",
    "sg:province":"ON",
    "sg:tags":[
        "baker"
    ],
    "wof:name":"Morning Star Bakery",
    "wof:placetype":"venue"
},
  "geometry": {"coordinates":[-81.208656,42.98143],"type":"Point"}
}