{
  "type": "Feature",
  "properties": {
    "addr:full":"Toronto ON M5V 1G1",
    "addr:postcode":"m5v 1g1",
    "iso:country":"CA",
    "sg:city":"Toronto",
    "sg:classifiers":[
        {
            "category":"Real Estate",
            "subcategory":"Architect",
            "type":"Services"
        }
    ],
    "sg:phone":"+1 416 979 5813",
    "sg:postcode":"M5V 1G1",
    "sg:province":"ON",
    "wof:name":"Fan & Dutra Architects Inc",
    "wof:placetype":"venue"
},
  "geometry": {"coordinates":[-79.399147,43.642944],"type":"Point"}
}