{
  "type": "Feature",
  "properties": {
    "addr:full":"242 Rue Principale Vallee-Jonction QC G0S 3J0",
    "addr:housenumber":"242",
    "addr:postcode":"g0s 3j0",
    "addr:street":"Rue Principale",
    "iso:country":"CA",
    "sg:address":"242 Rue Principale",
    "sg:city":"Vallee-Jonction",
    "sg:classifiers":[
        {
            "category":"Restaurant",
            "type":"Food & Drink"
        }
    ],
    "sg:phone":"+1 418 253 6133",
    "sg:postcode":"G0S 3J0",
    "sg:province":"QC",
    "wof:name":"Restaurant Feuille D'Erable",
    "wof:placetype":"venue"
},
  "geometry": {"coordinates":[-70.9250946045,46.3768348694],"type":"Point"}
}