{
  "type": "Feature",
  "properties": {
    "addr:full":"77 Bloor St W Toronto ON M5S 1M2",
    "addr:housenumber":"77",
    "addr:postcode":"m5s 1m2",
    "addr:street":"Bloor St W",
    "iso:country":"CA",
    "sg:address":"77 Bloor St W",
    "sg:city":"Toronto",
    "sg:classifiers":[
        {
            "category":"Restaurant",
            "type":"Food & Drink"
        }
    ],
    "sg:phone":"+1 416 926 1002",
    "sg:postcode":"M5S 1M2",
    "sg:province":"ON",
    "sg:tags":[
        "delicatessen"
    ],
    "wof:name":"Urban X Cape Cafe",
    "wof:placetype":"venue"
},
  "geometry": {"coordinates":[-79.3898468018,43.6694412231],"type":"Point"}
}