{
  "type": "Feature",
  "properties": {
    "addr:full":"4726 50 Ave Calmar AB T0C 0V0",
    "addr:housenumber":"4726",
    "addr:postcode":"t0c 0v0",
    "addr:street":"50 Ave",
    "iso:country":"CA",
    "sg:address":"4726 50 Ave",
    "sg:city":"Calmar",
    "sg:classifiers":[
        {
            "category":"Restaurant",
            "type":"Food & Drink"
        }
    ],
    "sg:phone":"+1 780 985 2273",
    "sg:postcode":"T0C 0V0",
    "sg:province":"AB",
    "wof:name":"Skip's Sports Bar",
    "wof:placetype":"venue"
},
  "geometry": {"coordinates":[-113.80117,53.265171],"type":"Point"}
}