{
  "type": "Feature",
  "properties": {
    "addr:full":"Saanichton BC V8M 2B3",
    "addr:postcode":"v8m 2b3",
    "iso:country":"CA",
    "sg:city":"Saanichton",
    "sg:classifiers":[
        {
            "category":"Cinema",
            "subcategory":"Movie Rental",
            "type":"Entertainment"
        }
    ],
    "sg:phone":"+1 250 652 7634",
    "sg:postcode":"V8M 2B3",
    "sg:province":"BC",
    "sg:tags":[
        "leasing",
        "video",
        "disc",
        "tape"
    ],
    "wof:name":"Xanavision Video",
    "wof:placetype":"venue"
},
  "geometry": {"coordinates":[-123.417106628,48.5947341919],"type":"Point"}
}