{
  "type": "Feature",
  "properties": {
    "iso:country":"CA",
    "sg:address":"205 10th Ave E",
    "sg:city":"Prince Albert",
    "sg:classifiers":[
        {
            "category":"Social Services",
            "subcategory":"Child Care",
            "type":"Services"
        }
    ],
    "sg:phone":"+1 306 763 8465",
    "sg:postcode":"S6V 5T3",
    "sg:province":"SK",
    "wof:name":"Small World Day Care CO-OP",
    "wof:placetype":"venue"
},
  "geometry": {"coordinates":[-105.722328186,53.2092666626],"type":"Point"}
}