{
  "type": "Feature",
  "properties": {
    "addr:full":"Victoriaville QC G6P 4C4",
    "addr:postcode":"g6p 4c4",
    "iso:country":"CA",
    "sg:city":"Victoriaville",
    "sg:classifiers":[
        {
            "category":"Building & Trades",
            "subcategory":"Construction",
            "type":"Services"
        }
    ],
    "sg:phone":"+1 819 751 2213",
    "sg:postcode":"G6P 4C4",
    "sg:province":"QC",
    "sg:tags":[
        "water",
        "well",
        "drilling"
    ],
    "wof:name":"A & G Pusatiers Expert",
    "wof:placetype":"venue"
},
  "geometry": {"coordinates":[-71.959022522,46.0551376343],"type":"Point"}
}