{
  "type": "Feature",
  "properties": {
    "addr:full":"436 Ch Des Pionniers O L'Islet QC G0R 2B0",
    "addr:housenumber":"436",
    "addr:postcode":"g0r 2b0",
    "addr:street":"Ch Des Pionniers O",
    "iso:country":"CA",
    "sg:address":"436 Ch Des Pionniers O",
    "sg:city":"L'Islet",
    "sg:classifiers":[
        {
            "category":"Building & Trades",
            "subcategory":"Construction",
            "type":"Services"
        }
    ],
    "sg:phone":"+1 418 247 3218",
    "sg:postcode":"G0R 2B0",
    "sg:province":"QC",
    "sg:tags":[
        "general",
        "contractor"
    ],
    "wof:name":"Construction Renovation Paul",
    "wof:placetype":"venue"
},
  "geometry": {"coordinates":[-70.33153533940001,47.0898017883],"type":"Point"}
}