{
  "type": "Feature",
  "properties": {
    "addr:full":"1460 Rue Ferland O Alma QC G8C 1C2",
    "addr:housenumber":"1460",
    "addr:postcode":"g8c 1c2",
    "addr:street":"Rue Ferland O",
    "iso:country":"CA",
    "sg:address":"1460 Rue Ferland O",
    "sg:city":"Alma",
    "sg:classifiers":[
        {
            "category":"Building & Trades",
            "subcategory":"Construction",
            "type":"Services"
        }
    ],
    "sg:phone":"+1 418 668 4244",
    "sg:postcode":"G8C 1C2",
    "sg:province":"QC",
    "sg:tags":[
        "general",
        "contractor"
    ],
    "wof:name":"Constructions Rm",
    "wof:placetype":"venue"
},
  "geometry": {"coordinates":[-71.670174,48.5452],"type":"Point"}
}