{
  "type": "Feature",
  "properties": {
    "addr:full":"910 Northmount Dr NW Calgary AB T2L 0A9",
    "addr:housenumber":"910",
    "addr:postcode":"t2l 0a9",
    "addr:street":"Northmount Dr Nw",
    "iso:country":"CA",
    "sg:address":"910 Northmount Dr NW",
    "sg:city":"Calgary",
    "sg:classifiers":[
        {
            "category":"Retail",
            "subcategory":"Auto Repair",
            "type":"Services"
        }
    ],
    "sg:phone":"+1 403 284 9542",
    "sg:postcode":"T2L 0A9",
    "sg:province":"AB",
    "sg:tags":[
        "repairing",
        "automobile"
    ],
    "wof:name":"Northmount Auto Svc",
    "wof:placetype":"venue"
},
  "geometry": {"coordinates":[-114.10295105,51.0863647461],"type":"Point"}
}