{
  "type": "Feature",
  "properties": {
    "iso:country":"CA",
    "sg:address":"435 Balmoral St",
    "sg:city":"Thunder Bay",
    "sg:classifiers":[
        {
            "category":"Organizations",
            "subcategory":"Professional Association",
            "type":"Services"
        }
    ],
    "sg:phone":"+1 807 622 9741",
    "sg:postcode":"P7C 5N4",
    "sg:province":"ON",
    "wof:name":"Learning Disabilities Assn",
    "wof:placetype":"venue"
},
  "geometry": {"coordinates":[-89.2583770752,48.3921775818],"type":"Point"}
}