{
  "type": "Feature",
  "properties": {
    "addr:full":"Dorval QC H9P 1G9",
    "addr:postcode":"h9p 1g9",
    "iso:country":"CA",
    "sg:city":"Dorval",
    "sg:classifiers":[
        {
            "category":"Wholesale",
            "subcategory":"Office Equipment",
            "type":"Manufacturing & Wholesale Goods"
        }
    ],
    "sg:phone":"+1 514 633 0845",
    "sg:postcode":"H9P 1G9",
    "sg:province":"QC",
    "sg:tags":[
        "accounting",
        "bookkeeping",
        "system"
    ],
    "wof:name":"Jonmac Services Inc",
    "wof:placetype":"venue"
},
  "geometry": {"coordinates":[-73.72180899999999,45.452271],"type":"Point"}
}