{
  "type": "Feature",
  "properties": {
    "addr:full":"5239 Av Du Parc Montreal QC H2V 4G9",
    "addr:housenumber":"5239",
    "addr:postcode":"h2v 4g9",
    "addr:street":"Av Du Parc",
    "iso:country":"CA",
    "sg:address":"5239 Av Du Parc",
    "sg:city":"Montreal",
    "sg:classifiers":[
        {
            "category":"Shopping",
            "subcategory":"Clothing, Apparel, & Fashions",
            "type":"Retail Goods"
        }
    ],
    "sg:phone":"+1 514 948 2702",
    "sg:postcode":"H2V 4G9",
    "sg:province":"QC",
    "wof:name":"Silk Master Fashions Ltd",
    "wof:placetype":"venue"
},
  "geometry": {"coordinates":[-73.598602,45.520836],"type":"Point"}
}