{
  "type": "Feature",
  "properties": {
    "iso:country":"CA",
    "sg:address":"416 St Clair St",
    "sg:city":"Chatham",
    "sg:classifiers":[
        {
            "category":"Professional",
            "subcategory":"Business Services",
            "type":"Services"
        }
    ],
    "sg:phone":"+1 519 358 1061",
    "sg:postcode":"N7L 3K5",
    "sg:province":"ON",
    "sg:tags":[
        "process",
        "bailiff",
        "server"
    ],
    "wof:name":"Fred Boersma Bailiff Svc",
    "wof:placetype":"venue"
},
  "geometry": {"coordinates":[-82.2007141113,42.4154243469],"type":"Point"}
}