{
  "type": "Feature",
  "properties": {
    "addr:full":"2270 Boul Mercure Drummondville QC J2B 3R5",
    "addr:housenumber":"2270",
    "addr:postcode":"j2b 3r5",
    "addr:street":"Boul Mercure",
    "iso:country":"CA",
    "sg:address":"2270 Boul Mercure",
    "sg:city":"Drummondville",
    "sg:classifiers":[
        {
            "category":"Shopping",
            "subcategory":"Clothing, Apparel, & Fashions",
            "type":"Retail Goods"
        }
    ],
    "sg:phone":"+1 819 478 0904",
    "sg:postcode":"J2B 3R5",
    "sg:province":"QC",
    "sg:tags":[
        "boutique",
        "shoes"
    ],
    "wof:name":"Mercerie Denis Enrg",
    "wof:placetype":"venue"
},
  "geometry": {"coordinates":[-72.456261,45.852737],"type":"Point"}
}