{
  "type": "Feature",
  "properties": {
    "addr:full":"Calgary AB T2E 7A1",
    "addr:postcode":"t2e 7a1",
    "iso:country":"CA",
    "sg:city":"Calgary",
    "sg:classifiers":[
        {
            "category":"Manufacturing",
            "subcategory":"Printing",
            "type":"Manufacturing & Wholesale Goods"
        }
    ],
    "sg:phone":"+1 403 250 2525",
    "sg:postcode":"T2E 7A1",
    "sg:province":"AB",
    "sg:tags":[
        "printer"
    ],
    "wof:name":"Makeda Press",
    "wof:placetype":"venue"
},
  "geometry": {"coordinates":[-114.032440185,51.0916175842],"type":"Point"}
}