{
  "type": "Feature",
  "properties": {
    "addr:full":"Val-Des-Lacs QC J0T 2P0",
    "addr:postcode":"j0t 2p0",
    "iso:country":"CA",
    "sg:city":"Val-Des-Lacs",
    "sg:classifiers":[
        {
            "category":"Travel",
            "subcategory":"Campground",
            "type":"Entertainment"
        }
    ],
    "sg:phone":"+1 819 326 4488",
    "sg:postcode":"J0T 2P0",
    "sg:province":"QC",
    "sg:tags":[
        "camp"
    ],
    "wof:name":"Camp Maromac Inc",
    "wof:placetype":"venue"
},
  "geometry": {"coordinates":[-74.3710479736,46.1732940674],"type":"Point"}
}