{
  "type": "Feature",
  "properties": {
    "addr:full":"8255 Boul Henri-Bourassa Charlesbourg QC G1G 4C8",
    "addr:housenumber":"8255",
    "addr:postcode":"g1g 4c8",
    "addr:street":"Boul Henri-Bourassa",
    "iso:country":"CA",
    "sg:address":"8255 Boul Henri-Bourassa",
    "sg:city":"Charlesbourg",
    "sg:classifiers":[
        {
            "category":"Personal",
            "subcategory":"Tanning Parlor",
            "type":"Services"
        }
    ],
    "sg:phone":"+1 418 622 9982",
    "sg:postcode":"G1G 4C8",
    "sg:province":"QC",
    "sg:tags":[
        "salon"
    ],
    "wof:name":"Sante Bronzage",
    "wof:placetype":"venue"
},
  "geometry": {"coordinates":[-71.2694473267,46.8635635376],"type":"Point"}
}