{
  "type": "Feature",
  "properties": {
    "addr:full":"Gloucester ON K1J 9L1",
    "addr:postcode":"k1j 9l1",
    "iso:country":"CA",
    "sg:city":"Gloucester",
    "sg:classifiers":[
        {
            "category":"Manufacturing",
            "subcategory":"Tools & Machinery",
            "type":"Manufacturing & Wholesale Goods"
        }
    ],
    "sg:phone":"+1 613 747 0193",
    "sg:postcode":"K1J 9L1",
    "sg:province":"ON",
    "sg:tags":[
        "machine",
        "shop"
    ],
    "wof:name":"Dominis Engineering Ltd",
    "wof:placetype":"venue"
},
  "geometry": {"coordinates":[-75.5839767456,45.4571304321],"type":"Point"}
}