{
  "type": "Feature",
  "properties": {
    "iso:country":"CA",
    "sg:city":"Maple",
    "sg:classifiers":[
        {
            "category":"Professional",
            "subcategory":"Lawyer & Legal Services",
            "type":"Services"
        }
    ],
    "sg:phone":"+1 905 832 2611",
    "sg:postcode":"L6A 1C6",
    "sg:province":"ON",
    "sg:tags":[
        "attorney"
    ],
    "wof:name":"Walsh Mc Luskie & Doyle",
    "wof:placetype":"venue"
},
  "geometry": {"coordinates":[-79.521797,43.852806],"type":"Point"}
}