{
  "type": "Feature",
  "properties": {
    "addr:full":"Quigleys Line Bell Island NL A0A 4H0",
    "addr:postcode":"a0a 4h0",
    "addr:street":"Line Bell",
    "iso:country":"CA",
    "sg:address":"Quigleys Line",
    "sg:city":"Bell Island",
    "sg:classifiers":[
        {
            "category":"Organizations",
            "subcategory":"Community Association",
            "type":"Services"
        }
    ],
    "sg:phone":"+1 709 488 2072",
    "sg:postcode":"A0A 4H0",
    "sg:province":"NL",
    "sg:tags":[
        "club"
    ],
    "wof:name":"Royal Canadian Legion",
    "wof:placetype":"venue"
},
  "geometry": {"coordinates":[-52.9490699768,47.6229782104],"type":"Point"}
}