{
  "type": "Feature",
  "properties": {
    "addr:full":"2061 Ch Du Lac-Sauvage Saint-Faustin-Lac-Carre QC J0T 1J2",
    "addr:housenumber":"2061",
    "addr:postcode":"j0t 1j2",
    "addr:street":"Ch Du Lac-Sauvage",
    "iso:country":"CA",
    "sg:address":"2061 Ch Du Lac-Sauvage",
    "sg:city":"Saint-Faustin-Lac-Carre",
    "sg:classifiers":[
        {
            "category":"Travel",
            "subcategory":"Campground",
            "type":"Entertainment"
        }
    ],
    "sg:phone":"+1 819 425 3556",
    "sg:postcode":"J0T 1J2",
    "sg:province":"QC",
    "sg:tags":[
        "camp"
    ],
    "wof:name":"Base DE Plein Air Laurentides",
    "wof:placetype":"venue"
},
  "geometry": {"coordinates":[-74.518524,46.053326],"type":"Point"}
}