{
  "type": "Feature",
  "properties": {
    "addr:full":"Ottawa ON K1H 6X9",
    "addr:postcode":"k1h 6x9",
    "iso:country":"CA",
    "sg:city":"Ottawa",
    "sg:classifiers":[
        {
            "category":"Food & Beverages",
            "subcategory":"Specialty",
            "type":"Retail Goods"
        }
    ],
    "sg:phone":"+1 613 737 6043",
    "sg:postcode":"K1H 6X9",
    "sg:province":"ON",
    "sg:tags":[
        "supplement",
        "vitamin"
    ],
    "wof:name":"Shaklee Independent Distr",
    "wof:placetype":"venue"
},
  "geometry": {"coordinates":[-75.6369018555,45.3813362122],"type":"Point"}
}