{
  "type": "Feature",
  "properties": {
    "addr:full":"North York ON M3J 3K3",
    "addr:postcode":"m3j 3k3",
    "iso:country":"CA",
    "sg:city":"North York",
    "sg:classifiers":[
        {
            "category":"Home & Garden",
            "subcategory":"Home Furnishings",
            "type":"Retail Goods"
        }
    ],
    "sg:phone":"+1 416 667 0139",
    "sg:postcode":"M3J 3K3",
    "sg:province":"ON",
    "sg:tags":[
        "curtain",
        "made",
        "drapery"
    ],
    "wof:name":"Riviera Drapery",
    "wof:placetype":"venue"
},
  "geometry": {"coordinates":[-79.4887924194,43.7641029358],"type":"Point"}
}