{
  "type": "Feature",
  "properties": {
    "addr:full":"Surrey BC V3W 3V6",
    "addr:postcode":"v3w 3v6",
    "iso:country":"CA",
    "sg:city":"Surrey",
    "sg:classifiers":[
        {
            "category":"Retail",
            "subcategory":"Auto Repair",
            "type":"Services"
        }
    ],
    "sg:phone":"+1 604 590 2405",
    "sg:postcode":"V3W 3V6",
    "sg:province":"BC",
    "sg:tags":[
        "truck"
    ],
    "wof:name":"Pro Frame & Welding Ltd",
    "wof:placetype":"venue"
},
  "geometry": {"coordinates":[-122.882019043,49.1589813232],"type":"Point"}
}