{
  "type": "Feature",
  "properties": {
    "addr:full":"32958 Twelfth Ave Mission BC V2V 2M8",
    "addr:postcode":"32958;v2v 2m8",
    "addr:street":"Twelfth Ave",
    "iso:country":"CA",
    "sg:address":"32958 Twelfth Ave",
    "sg:city":"Mission",
    "sg:classifiers":[
        {
            "category":"Professional",
            "subcategory":"Lawyer & Legal Services",
            "type":"Services"
        }
    ],
    "sg:phone":"+1 604 820 4143",
    "sg:postcode":"V2V 2M8",
    "sg:province":"BC",
    "sg:tags":[
        "attorney"
    ],
    "wof:name":"Pratt, Janet L",
    "wof:placetype":"venue"
},
  "geometry": {"coordinates":[-122.311439514,49.1448745728],"type":"Point"}
}