{
  "type": "Feature",
  "properties": {
    "addr:full":"700 Apex Ave North Vancouver BC V7H 2R5",
    "addr:housenumber":"700",
    "addr:postcode":"v7h 2r5",
    "addr:street":"Apex Ave",
    "iso:country":"CA",
    "sg:address":"700 Apex Ave",
    "sg:city":"North Vancouver",
    "sg:classifiers":[
        {
            "category":"Recreation",
            "type":"Entertainment"
        }
    ],
    "sg:phone":"+1 604 929 6672",
    "sg:postcode":"V7H 2R5",
    "sg:province":"BC",
    "sg:tags":[
        "range",
        "practice",
        "golf"
    ],
    "wof:name":"Takaya Golf Ctr",
    "wof:placetype":"venue"
},
  "geometry": {"coordinates":[-122.98107899999999,49.312382],"type":"Point"}
}