{
  "type": "Feature",
  "properties": {
    "iso:country":"CA",
    "sg:address":"700 Apex Ave",
    "sg:city":"North Vancouver",
    "sg:classifiers":[
        {
            "category":"Recreation",
            "type":"Entertainment"
        }
    ],
    "sg:phone":"+1 604 929 6672",
    "sg:postcode":"V7H 2R5",
    "sg:province":"BC",
    "sg:tags":[
        "range",
        "practice",
        "golf"
    ],
    "wof:name":"Takaya Golf Ctr",
    "wof:placetype":"venue"
},
  "geometry": {"coordinates":[-122.981079,49.312382],"type":"Point"}
}