{
  "type": "Feature",
  "properties": {
    "addr:full":"307 33rd St W Saskatoon SK S7L 0V3",
    "addr:housenumber":"307",
    "addr:postcode":"s7l 0v3",
    "addr:street":"33Rd St W",
    "iso:country":"CA",
    "sg:address":"307 33rd St W",
    "sg:city":"Saskatoon",
    "sg:classifiers":[
        {
            "category":"Shopping",
            "subcategory":"Used Merchandise",
            "type":"Retail Goods"
        }
    ],
    "sg:phone":"+1 306 652 2975",
    "sg:postcode":"S7L 0V3",
    "sg:province":"SK",
    "sg:tags":[
        "antique"
    ],
    "wof:name":"Penn's Antiques",
    "wof:placetype":"venue"
},
  "geometry": {"coordinates":[-106.673995972,52.1437225342],"type":"Point"}
}