{
  "type": "Feature",
  "properties": {
    "addr:full":"180 2 Rang Saint-Louis-DE-Blandford QC G0Z 1B0",
    "addr:housenumber":"180 2",
    "addr:postcode":"g0z 1b0",
    "addr:street":"Rang Saint-Louis-De-Blandford",
    "iso:country":"CA",
    "sg:address":"180 2 Rang",
    "sg:city":"Saint-Louis-DE-Blandford",
    "sg:classifiers":[
        {
            "category":"Building & Trades",
            "subcategory":"Cleaning & Sanitation",
            "type":"Services"
        }
    ],
    "sg:phone":"+1 819 364 7342",
    "sg:postcode":"G0Z 1B0",
    "sg:province":"QC",
    "sg:tags":[
        "snow",
        "removal"
    ],
    "wof:name":"Bois-Net Pepin Inc",
    "wof:placetype":"venue"
},
  "geometry": {"coordinates":[-72.02321600000001,46.264816],"type":"Point"}
}