{
  "type": "Feature",
  "properties": {
    "addr:full":"Drayton Valley AB T7A 1S4",
    "addr:postcode":"t7a 1s4",
    "addr:street":"Drayton",
    "iso:country":"CA",
    "sg:city":"Drayton Valley",
    "sg:classifiers":[
        {
            "category":"Travel",
            "subcategory":"Hotels & Motels",
            "type":"Entertainment"
        }
    ],
    "sg:phone":"+1 780 542 9122",
    "sg:postcode":"T7A 1S4",
    "sg:province":"AB",
    "wof:name":"Super 8 Motel Drayton Valley",
    "wof:placetype":"venue"
},
  "geometry": {"coordinates":[-114.97615051299999,53.2098083496],"type":"Point"}
}