{
  "type": "Feature",
  "properties": {
    "addr:full":"Toronto ON M5V 2M5",
    "addr:postcode":"m5v 2m5",
    "iso:country":"CA",
    "sg:city":"Toronto",
    "sg:classifiers":[
        {
            "category":"Manufacturing",
            "subcategory":"Apparel",
            "type":"Manufacturing & Wholesale Goods"
        }
    ],
    "sg:phone":"+1 416 504 9298",
    "sg:postcode":"M5V 2M5",
    "sg:province":"ON",
    "wof:name":"Mai Aru Studio",
    "wof:placetype":"venue"
},
  "geometry": {"coordinates":[-79.39954400000001,43.646275],"type":"Point"}
}