{
  "type": "Feature",
  "properties": {
    "addr:full":"464 Rue Saint-Jean Montreal QC H2Y 2S1",
    "addr:housenumber":"464",
    "addr:postcode":"h2y 2s1",
    "addr:street":"Rue Saint-Jean",
    "iso:country":"CA",
    "sg:address":"464 Rue Saint-Jean",
    "sg:city":"Montreal",
    "sg:classifiers":[
        {
            "category":"Building & Trades",
            "subcategory":"Construction",
            "type":"Services"
        }
    ],
    "sg:phone":"+1 514 285 2033",
    "sg:postcode":"H2Y 2S1",
    "sg:province":"QC",
    "sg:tags":[
        "insulation",
        "heat",
        "contractor"
    ],
    "wof:name":"Isolation L'Ere 2000",
    "wof:placetype":"venue"
},
  "geometry": {"coordinates":[-73.5574874878,45.5025405884],"type":"Point"}
}