{
  "type": "Feature",
  "properties": {
    "addr:full":"223 Welsford Pictou NS B0K 1H0",
    "addr:housenumber":"223",
    "addr:postcode":"b0k 1h0",
    "addr:street":"Welsford",
    "iso:country":"CA",
    "sg:address":"223 Welsford",
    "sg:city":"Pictou",
    "sg:classifiers":[
        {
            "category":"Health Services",
            "subcategory":"Medical Lab",
            "type":"Services"
        }
    ],
    "sg:phone":"+1 902 485 1997",
    "sg:postcode":"B0K 1H0",
    "sg:province":"NS",
    "wof:name":"Shiretown Denture Clinic",
    "wof:placetype":"venue"
},
  "geometry": {"coordinates":[-62.70393,45.680069],"type":"Point"}
}