{
  "type": "Feature",
  "properties": {
    "iso:country":"CA",
    "sg:address":"336 Clearwater Vlg",
    "sg:city":"Clearwater",
    "sg:classifiers":[
        {
            "category":"Organizations",
            "subcategory":"Religious Organization",
            "type":"Services"
        }
    ],
    "sg:phone":"+1 250 674 2691",
    "sg:postcode":"V0E 1N0",
    "sg:province":"BC",
    "sg:tags":[
        "church"
    ],
    "wof:name":"Clearwater Catholic Church",
    "wof:placetype":"venue"
},
  "geometry": {"coordinates":[-120.043907166,51.6443824768],"type":"Point"}
}