{
  "type": "Feature",
  "properties": {
    "addr:full":"Chateauguay QC J6K 1C5",
    "addr:postcode":"j6k 1c5",
    "iso:country":"CA",
    "sg:city":"Chateauguay",
    "sg:classifiers":[
        {
            "category":"Personal",
            "subcategory":"Beauty Salon",
            "type":"Services"
        }
    ],
    "sg:phone":"+1 450 691 2114",
    "sg:postcode":"J6K 1C5",
    "sg:province":"QC",
    "wof:name":"Chateauguay DE Luxe Barber",
    "wof:placetype":"venue"
},
  "geometry": {"coordinates":[-73.716446,45.359043],"type":"Point"}
}