{
  "type": "Feature",
  "properties": {
    "addr:full":"112 Adelaide St E Toronto ON M5C 1K9",
    "addr:housenumber":"112",
    "addr:postcode":"m5c 1k9",
    "addr:street":"Adelaide St E",
    "iso:country":"CA",
    "sg:address":"112 Adelaide St E",
    "sg:city":"Toronto",
    "sg:classifiers":[
        {
            "category":"Professional",
            "subcategory":"Lawyer & Legal Services",
            "type":"Services"
        }
    ],
    "sg:phone":"+1 416 307 0003",
    "sg:postcode":"M5C 1K9",
    "sg:province":"ON",
    "sg:tags":[
        "attorney"
    ],
    "wof:name":"Feld, Lisa",
    "wof:placetype":"venue"
},
  "geometry": {"coordinates":[-79.373062,43.65163],"type":"Point"}
}