{
  "type": "Feature",
  "properties": {
    "addr:full":"11760 Woodbine Ave Gormley ON L0H 1G0",
    "addr:housenumber":"11760",
    "addr:postcode":"l0h 1g0",
    "addr:street":"Woodbine Ave",
    "iso:country":"CA",
    "sg:address":"11760 Woodbine Ave",
    "sg:city":"Gormley",
    "sg:classifiers":[
        {
            "category":"Organizations",
            "subcategory":"Religious Organization",
            "type":"Services"
        }
    ],
    "sg:phone":"+1 905 887 5489",
    "sg:postcode":"L0H 1G0",
    "sg:province":"ON",
    "sg:tags":[
        "church"
    ],
    "wof:name":"Heise Hill Brethren in Christ",
    "wof:placetype":"venue"
},
  "geometry": {"coordinates":[-79.378502,43.930477],"type":"Point"}
}