{
  "type": "Feature",
  "properties": {
    "addr:full":"215 Union St Saint John NB E2L 1A9",
    "addr:housenumber":"215",
    "addr:postcode":"nb e2l 1a9",
    "addr:street":"Union St",
    "iso:country":"CA",
    "sg:address":"215 Union St",
    "sg:city":"Saint John",
    "sg:classifiers":[
        {
            "category":"Restaurant",
            "type":"Food & Drink"
        }
    ],
    "sg:phone":"+1 506 634 0505",
    "sg:postcode":"E2L 1A9",
    "sg:province":"NB",
    "wof:name":"Top's Pizza & Restaurant",
    "wof:placetype":"venue"
},
  "geometry": {"coordinates":[-66.05789900000001,45.275394],"type":"Point"}
}