{
  "type": "Feature",
  "properties": {
    "iso:country":"CA",
    "sg:address":"3030 Dundas St W",
    "sg:city":"Toronto",
    "sg:phone":"+1 416 762 3356",
    "sg:postcode":"M6P 1Z3",
    "sg:province":"ON",
    "sg:tags":[
        "equipment",
        "supply"
    ],
    "wof:name":"Jtd Intl Food Equipment Ltd",
    "wof:placetype":"venue"
},
  "geometry": {"coordinates":[-79.47016906739999,43.6655960083],"type":"Point"}
}