{
  "type": "Feature",
  "properties": {
    "iso:country":"CA",
    "sg:address":"1010 Av Saint-Louis",
    "sg:city":"Plessisville",
    "sg:classifiers":[
        {
            "category":"Restaurant",
            "type":"Food & Drink"
        }
    ],
    "sg:phone":"+1 819 362 2895",
    "sg:postcode":"G6L 2M3",
    "sg:province":"QC",
    "wof:name":"Restaurant Pizza-Ville",
    "wof:placetype":"venue"
},
  "geometry": {"coordinates":[-71.7644729614,46.2143669128],"type":"Point"}
}