{
  "type": "Feature",
  "properties": {
    "addr:full":"209 Van Horne St S Cranbrook BC V1C 6R9",
    "addr:housenumber":"209",
    "addr:postcode":"v1c 6r9",
    "addr:street":"Van Horne St S",
    "iso:country":"CA",
    "sg:address":"209 Van Horne St S",
    "sg:city":"Cranbrook",
    "sg:classifiers":[
        {
            "category":"Personal",
            "subcategory":"Beauty Salon",
            "type":"Services"
        }
    ],
    "sg:phone":"+1 250 489 3963",
    "sg:postcode":"V1C 6R9",
    "sg:province":"BC",
    "wof:name":"Kutters Korner Family Styling",
    "wof:placetype":"venue"
},
  "geometry": {"coordinates":[-115.777687073,49.5082893372],"type":"Point"}
}