{
  "type": "Feature",
  "properties": {
    "iso:country":"CA",
    "sg:city":"Quebec",
    "sg:classifiers":[
        {
            "category":"Building & Trades",
            "subcategory":"Construction",
            "type":"Services"
        }
    ],
    "sg:phone":"+1 418 666 9840",
    "sg:postcode":"G1J 2C2",
    "sg:province":"QC",
    "sg:tags":[
        "roofing",
        "contractor",
        "consultant"
    ],
    "wof:name":"Toitures Bernier & Fils",
    "wof:placetype":"venue"
},
  "geometry": {"coordinates":[-71.224915,46.831276],"type":"Point"}
}