{
  "type": "Feature",
  "properties": {
    "addr:full":"525 Boul Wilfrid-Hamel Quebec QC G1M 2S8",
    "addr:housenumber":"525",
    "addr:postcode":"g1m 2s8",
    "addr:street":"Boul Wilfrid-Hamel",
    "iso:country":"CA",
    "sg:address":"525 Boul Wilfrid-Hamel",
    "sg:city":"Quebec",
    "sg:classifiers":[
        {
            "category":"Recreation",
            "type":"Entertainment"
        }
    ],
    "sg:phone":"+1 418 529 9238",
    "sg:postcode":"G1M 2S8",
    "sg:province":"QC",
    "sg:tags":[
        "club",
        "instruction",
        "gymnasium",
        "health",
        "studio",
        "swimming"
    ],
    "wof:name":"Acti-Forme",
    "wof:placetype":"venue"
},
  "geometry": {"coordinates":[-71.2484588623,46.8202056885],"type":"Point"}
}