{
  "type": "Feature",
  "properties": {
    "addr:full":"Kamloops BC V2H 1B7",
    "addr:postcode":"kamloops bc v2h 1b7",
    "iso:country":"CA",
    "sg:city":"Kamloops",
    "sg:classifiers":[
        {
            "category":"Wholesale",
            "subcategory":"Electrical",
            "type":"Manufacturing & Wholesale Goods"
        }
    ],
    "sg:phone":"+1 250 374 2494",
    "sg:postcode":"V2H 1B7",
    "sg:province":"BC",
    "sg:tags":[
        "communication",
        "communications",
        "radio",
        "consultant"
    ],
    "wof:name":"Province-Wide Comms Ltd",
    "wof:placetype":"venue"
},
  "geometry": {"coordinates":[-120.324257,50.693905],"type":"Point"}
}