{
  "type": "Feature",
  "properties": {
    "addr:full":"413 Rue Saint-Laurent Saint-Eustache QC J7P 1R8",
    "addr:housenumber":"413",
    "addr:postcode":"j7p 1r8",
    "addr:street":"Rue Saint-Laurent",
    "iso:country":"CA",
    "sg:address":"413 Rue Saint-Laurent",
    "sg:city":"Saint-Eustache",
    "sg:classifiers":[
        {
            "category":"Personal",
            "subcategory":"Beauty Salon",
            "type":"Services"
        }
    ],
    "sg:phone":"+1 450 472 3276",
    "sg:postcode":"J7P 1R8",
    "sg:province":"QC",
    "wof:name":"Salon Huguette Gamache",
    "wof:placetype":"venue"
},
  "geometry": {"coordinates":[-73.86144299999999,45.584167],"type":"Point"}
}