{
  "type": "Feature",
  "properties": {
    "addr:full":"1280 Av Du Chanoine-Morel Sillery QC G1S 4B2",
    "addr:housenumber":"1280",
    "addr:postcode":"g1s 4b2",
    "addr:street":"Av Du Chanoine-Morel",
    "iso:country":"CA",
    "sg:address":"1280 Av Du Chanoine-Morel",
    "sg:city":"Sillery",
    "sg:classifiers":[
        {
            "category":"Home & Garden",
            "subcategory":"Carpets & Floor Coverings",
            "type":"Retail Goods"
        }
    ],
    "sg:phone":"+1 418 683 2383",
    "sg:postcode":"G1S 4B2",
    "sg:province":"QC",
    "sg:tags":[
        "dealer",
        "rug"
    ],
    "wof:name":"Tapis Decor Sillery Inc",
    "wof:placetype":"venue"
},
  "geometry": {"coordinates":[-71.24751999999999,46.784241],"type":"Point"}
}