{
  "type": "Feature",
  "properties": {
    "addr:full":"6837 Rue Saint-Hubert Montreal QC H2S 2M7",
    "addr:housenumber":"6837",
    "addr:postcode":"h2s 2m7",
    "addr:street":"Rue Saint-Hubert",
    "iso:country":"CA",
    "sg:address":"6837 Rue Saint-Hubert",
    "sg:city":"Montreal",
    "sg:classifiers":[
        {
            "category":"Shopping",
            "subcategory":"Clothing, Apparel, & Fashions",
            "type":"Retail Goods"
        }
    ],
    "sg:phone":"+1 514 278 1668",
    "sg:postcode":"H2S 2M7",
    "sg:province":"QC",
    "sg:tags":[
        "item",
        "boutique"
    ],
    "wof:name":"Hkr Collections Inc",
    "wof:placetype":"venue"
},
  "geometry": {"coordinates":[-73.608261,45.538658],"type":"Point"}
}