{
  "type": "Feature",
  "properties": {
    "addr:full":"311 20th St E Saskatoon SK S7K 0A9",
    "addr:housenumber":"311",
    "addr:postcode":"s7k 0a9",
    "addr:street":"20Th St E",
    "iso:country":"CA",
    "sg:address":"311 20th St E",
    "sg:city":"Saskatoon",
    "sg:classifiers":[
        {
            "category":"Social Services",
            "type":"Services"
        }
    ],
    "sg:phone":"+1 306 655 4900",
    "sg:postcode":"S7K 0A9",
    "sg:province":"SK",
    "sg:tags":[
        "organization",
        "health",
        "welfare"
    ],
    "wof:name":"Saskatoon Mental Health Svc",
    "wof:placetype":"venue"
},
  "geometry": {"coordinates":[-106.663315,52.125122],"type":"Point"}
}