{
  "type": "Feature",
  "properties": {
    "addr:full":"3333 Highway 16 E Thornhill BC V8G 4P3",
    "addr:housenumber":"3333",
    "addr:postcode":"v8g 4p3",
    "addr:street":"Highway 16 E",
    "iso:country":"CA",
    "sg:address":"3333 Highway 16 E",
    "sg:city":"Thornhill",
    "sg:classifiers":[
        {
            "category":"Retail",
            "subcategory":"Veterinary Services",
            "type":"Services"
        }
    ],
    "sg:phone":"+1 250 635 6491",
    "sg:postcode":"V8G 4P3",
    "sg:province":"BC",
    "sg:tags":[
        "veterinarian"
    ],
    "wof:name":"Skeena Animal Hospital",
    "wof:placetype":"venue"
},
  "geometry": {"coordinates":[-128.54469299300001,54.512424469],"type":"Point"}
}