{
  "type": "Feature",
  "properties": {
    "addr:full":"4 Dominion Bay Thompson MB R8N 1L3",
    "addr:housenumber":"4",
    "addr:postcode":"r8n 1l3",
    "addr:street":"Dominion Bay",
    "iso:country":"CA",
    "sg:address":"4 Dominion Bay",
    "sg:city":"Thompson",
    "sg:classifiers":[
        {
            "category":"Retail",
            "subcategory":"Portrait Studio",
            "type":"Services"
        }
    ],
    "sg:phone":"+1 204 677 8177",
    "sg:postcode":"R8N 1L3",
    "sg:province":"MB",
    "sg:tags":[
        "photographer"
    ],
    "wof:name":"Chris Sundevic Photography",
    "wof:placetype":"venue"
},
  "geometry": {"coordinates":[-97.8615112305,55.7346382141],"type":"Point"}
}