{
  "type": "Feature",
  "properties": {
    "iso:country":"CA",
    "sg:city":"Vancouver",
    "sg:classifiers":[
        {
            "category":"Real Estate",
            "subcategory":"Architect",
            "type":"Services"
        }
    ],
    "sg:phone":"+1 604 228 1247",
    "sg:postcode":"V6H 3W7",
    "sg:province":"BC",
    "wof:name":"Brunhoff, Stefan",
    "wof:placetype":"venue"
},
  "geometry": {"coordinates":[-123.136108398,49.2708816528],"type":"Point"}
}