{
  "type": "Feature",
  "properties": {
    "addr:full":"Edmonton AB T5K 1W8",
    "addr:postcode":"t5k 1w8",
    "iso:country":"CA",
    "sg:city":"Edmonton",
    "sg:classifiers":[
        {
            "category":"Health Services",
            "subcategory":"Health Practitioner",
            "type":"Services"
        }
    ],
    "sg:phone":"+1 780 482 5232",
    "sg:postcode":"T5K 1W8",
    "sg:province":"AB",
    "sg:tags":[
        "acupuncture"
    ],
    "wof:name":"Peking Acutherapy Clinic",
    "wof:placetype":"venue"
},
  "geometry": {"coordinates":[-113.52301,53.539974],"type":"Point"}
}