{
  "type": "Feature",
  "properties": {
    "addr:full":"300 Eagleson Rd Kanata ON K2M 1C9",
    "addr:housenumber":"300",
    "addr:postcode":"k2m 1c9",
    "addr:street":"Eagleson Rd",
    "iso:country":"CA",
    "sg:address":"300 Eagleson Rd",
    "sg:city":"Kanata",
    "sg:classifiers":[
        {
            "category":"Shopping",
            "subcategory":"Pharmacy",
            "type":"Retail Goods"
        }
    ],
    "sg:phone":"+1 613 592 3109",
    "sg:postcode":"K2M 1C9",
    "sg:province":"ON",
    "wof:name":"Pharma Plus Drugmart",
    "wof:placetype":"venue"
},
  "geometry": {"coordinates":[-75.87627410890001,45.302646637],"type":"Point"}
}