{
  "type": "Feature",
  "properties": {
    "addr:full":"1451 Boul Pere-Lelievre Quebec QC G1M 1N8",
    "addr:housenumber":"1451",
    "addr:postcode":"g1m 1n8",
    "addr:street":"Boul Pere-Lelievre",
    "iso:country":"CA",
    "sg:address":"1451 Boul Pere-Lelievre",
    "sg:city":"Quebec",
    "sg:classifiers":[
        {
            "category":"Health Services",
            "subcategory":"Nursing And Care Facility",
            "type":"Services"
        }
    ],
    "sg:phone":"+1 418 683 2516",
    "sg:postcode":"G1M 1N8",
    "sg:province":"QC",
    "sg:tags":[
        "social",
        "home",
        "welfare",
        "rest",
        "organization"
    ],
    "wof:name":"Chsld Residence St-Antoine",
    "wof:placetype":"venue"
},
  "geometry": {"coordinates":[-71.278572,46.810345],"type":"Point"}
}