{
  "type": "Feature",
  "properties": {
    "addr:full":"240 Willingdon Ave Burnaby BC V5C 5E9",
    "addr:housenumber":"240",
    "addr:postcode":"v5c 5e9",
    "addr:street":"Willingdon Ave",
    "iso:country":"CA",
    "sg:address":"240 Willingdon Ave",
    "sg:city":"Burnaby",
    "sg:classifiers":[
        {
            "category":"Recreation",
            "type":"Entertainment"
        }
    ],
    "sg:phone":"+1 604 298 7946",
    "sg:postcode":"V5C 5E9",
    "sg:province":"BC",
    "sg:tags":[
        "pool",
        "swimming"
    ],
    "wof:name":"Eileen Dailly Leisure Pool",
    "wof:placetype":"venue"
},
  "geometry": {"coordinates":[-123.00290699999999,49.282387],"type":"Point"}
}