{
  "type": "Feature",
  "properties": {
    "iso:country":"CA",
    "sg:address":"123 Rue Wellington N",
    "sg:city":"Sherbrooke",
    "sg:classifiers":[
        {
            "category":"Restaurant",
            "type":"Food & Drink"
        }
    ],
    "sg:phone":"+1 819 565 8404",
    "sg:postcode":"J1H 5B9",
    "sg:province":"QC",
    "wof:name":"Restaurant Baladi",
    "wof:placetype":"venue"
},
  "geometry": {"coordinates":[-71.8917312622,45.4033355713],"type":"Point"}
}