{
  "type": "Feature",
  "properties": {
    "addr:full":"New Liskeard ON P0J 1P0",
    "addr:postcode":"p0j 1p0",
    "iso:country":"CA",
    "sg:city":"New Liskeard",
    "sg:classifiers":[
        {
            "category":"Building & Trades",
            "subcategory":"Construction",
            "type":"Services"
        }
    ],
    "sg:phone":"+1 705 647 5499",
    "sg:postcode":"P0J 1P0",
    "sg:province":"ON",
    "sg:tags":[
        "welding",
        "general",
        "contractor"
    ],
    "wof:name":"Gilbert's Welding",
    "wof:placetype":"venue"
},
  "geometry": {"coordinates":[-79.699455,47.504883],"type":"Point"}
}