{
  "type": "Feature",
  "properties": {
    "addr:full":"218 River Valley Dr Grand Bay-Westfield NB E5K 1A4",
    "addr:housenumber":"218",
    "addr:postcode":"e5k 1a4",
    "addr:street":"River Valley Dr",
    "iso:country":"CA",
    "sg:address":"218 River Valley Dr",
    "sg:city":"Grand Bay-Westfield",
    "sg:classifiers":[
        {
            "category":"Building & Trades",
            "subcategory":"Plumbing",
            "type":"Services"
        }
    ],
    "sg:phone":"+1 506 738 8161",
    "sg:postcode":"E5K 1A4",
    "sg:province":"NB",
    "sg:tags":[
        "conditioning",
        "air",
        "system",
        "contractor"
    ],
    "wof:name":"Mike O'Brien Refrigeration",
    "wof:placetype":"venue"
},
  "geometry": {"coordinates":[-66.19483184809999,45.3031768799],"type":"Point"}
}