{
  "type": "Feature",
  "properties": {
    "addr:full":"62 17th St W Prince Albert SK S6V 3X3",
    "addr:housenumber":"62",
    "addr:postcode":"s6v 3x3",
    "addr:street":"17Th St",
    "iso:country":"CA",
    "sg:address":"62 17th St W",
    "sg:city":"Prince Albert",
    "sg:classifiers":[
        {
            "category":"Building & Trades",
            "subcategory":"Construction",
            "type":"Services"
        }
    ],
    "sg:phone":"+1 306 763 3700",
    "sg:postcode":"S6V 3X3",
    "sg:province":"SK",
    "sg:tags":[
        "general",
        "contractor"
    ],
    "wof:name":"Rnf Ventures",
    "wof:placetype":"venue"
},
  "geometry": {"coordinates":[-105.756004,53.197884],"type":"Point"}
}