{
  "type": "Feature",
  "properties": {
    "addr:full":"281 Rue Notre-Dame Repentigny QC J6A 2R8",
    "addr:housenumber":"281",
    "addr:postcode":"j6a 2r8",
    "addr:street":"Rue Notre-Dame",
    "iso:country":"CA",
    "sg:address":"281 Rue Notre-Dame",
    "sg:city":"Repentigny",
    "sg:classifiers":[
        {
            "category":"Education",
            "subcategory":"School",
            "type":"Public Place"
        }
    ],
    "sg:phone":"+1 450 585 3492",
    "sg:postcode":"J6A 2R8",
    "sg:province":"QC",
    "sg:tags":[
        "academic",
        "instruction",
        "special",
        "dancing"
    ],
    "wof:name":"Ecole DE Ballet Notre Dame",
    "wof:placetype":"venue"
},
  "geometry": {"coordinates":[-73.458046,45.726639],"type":"Point"}
}