{
  "type": "Feature",
  "properties": {
    "addr:full":"4980 Boul Decarie Montreal QC H3X 2H7",
    "addr:housenumber":"4980",
    "addr:postcode":"h3x 2h7",
    "addr:street":"Boul Decarie",
    "iso:country":"CA",
    "sg:address":"4980 Boul Decarie",
    "sg:city":"Montreal",
    "sg:classifiers":[
        {
            "category":"Personal",
            "subcategory":"Beauty Salon",
            "type":"Services"
        }
    ],
    "sg:phone":"+1 514 489 7173",
    "sg:postcode":"H3X 2H7",
    "sg:province":"QC",
    "wof:name":"Jasu Beauty Salon",
    "wof:placetype":"venue"
},
  "geometry": {"coordinates":[-73.627945,45.482708],"type":"Point"}
}