{
  "type": "Feature",
  "properties": {
    "addr:full":"1168 Clyde Crt Kingston ON K7P 2E4",
    "addr:housenumber":"1168",
    "addr:postcode":"k7p 2e4",
    "addr:street":"Clyde Crt",
    "iso:country":"CA",
    "sg:address":"1168 Clyde Crt",
    "sg:city":"Kingston",
    "sg:classifiers":[
        {
            "category":"Manufacturing",
            "subcategory":"Signs",
            "type":"Manufacturing & Wholesale Goods"
        }
    ],
    "sg:phone":"+1 613 389 9932",
    "sg:postcode":"K7P 2E4",
    "sg:province":"ON",
    "wof:name":"Celebrity Sign Rentals",
    "wof:placetype":"venue"
},
  "geometry": {"coordinates":[-76.563171,44.267494],"type":"Point"}
}