{
  "type": "Feature",
  "properties": {
    "iso:country":"CA",
    "sg:address":"425 Rue Saint-Louis",
    "sg:city":"Saint-Jean-Sur-Richelieu",
    "sg:classifiers":[
        {
            "category":"Wholesale",
            "subcategory":"Electrical",
            "type":"Manufacturing & Wholesale Goods"
        }
    ],
    "sg:phone":"+1 450 359 6721",
    "sg:postcode":"J3B 1Y6",
    "sg:province":"QC",
    "sg:tags":[
        "equipment",
        "wire",
        "electric"
    ],
    "wof:name":"Pirelli Cables Inc",
    "wof:placetype":"venue"
},
  "geometry": {"coordinates":[-73.2717590332,45.3127708435],"type":"Point"}
}