{
  "type": "Feature",
  "properties": {
    "iso:country":"CA",
    "sg:address":"1312 4th St",
    "sg:city":"Estevan",
    "sg:classifiers":[
        {
            "category":"Professional",
            "subcategory":"Lawyer & Legal Services",
            "type":"Services"
        }
    ],
    "sg:phone":"+1 306 634 3631",
    "sg:postcode":"S4A 0X2",
    "sg:province":"SK",
    "sg:tags":[
        "attorney"
    ],
    "wof:name":"Mc Geough, Tim",
    "wof:placetype":"venue"
},
  "geometry": {"coordinates":[-102.99749799999999,49.141243],"type":"Point"}
}