{
  "type": "Feature",
  "properties": {
    "addr:full":"150 Rue Robert-Bernard Drummondville QC J2C 8N1",
    "addr:housenumber":"150",
    "addr:postcode":"j2c 8n1",
    "addr:street":"Rue Robert-Bernard",
    "iso:country":"CA",
    "sg:address":"150 Rue Robert-Bernard",
    "sg:city":"Drummondville",
    "sg:classifiers":[
        {
            "category":"Wholesale",
            "subcategory":"Machinery & Supplies",
            "type":"Manufacturing & Wholesale Goods"
        }
    ],
    "sg:phone":"+1 819 474 0002",
    "sg:postcode":"J2C 8N1",
    "sg:province":"QC",
    "sg:tags":[
        "farm",
        "equipment"
    ],
    "wof:name":"Agritex Drummondville Inc",
    "wof:placetype":"venue"
},
  "geometry": {"coordinates":[-72.51123800000001,45.909988],"type":"Point"}
}