{
  "type": "Feature",
  "properties": {
    "addr:full":"Hwy 30 Altona MB R0G 0B0",
    "addr:postcode":"r0g 0b0",
    "addr:street":"Hwy 30",
    "iso:country":"CA",
    "sg:address":"Hwy 30",
    "sg:city":"Altona",
    "sg:classifiers":[
        {
            "category":"Building & Trades",
            "subcategory":"Construction",
            "type":"Services"
        }
    ],
    "sg:phone":"+1 204 324 5477",
    "sg:postcode":"R0G 0B0",
    "sg:province":"MB",
    "sg:tags":[
        "excavating",
        "sewer",
        "contractor"
    ],
    "wof:name":"Let Construction Ltd",
    "wof:placetype":"venue"
},
  "geometry": {"coordinates":[-97.549621582,49.1226463318],"type":"Point"}
}