{
  "type": "Feature",
  "properties": {
    "iso:country":"CA",
    "sg:address":"2581 Springfield Rd",
    "sg:city":"Kelowna",
    "sg:classifiers":[
        {
            "category":"Travel",
            "subcategory":"Hotels & Motels",
            "type":"Entertainment"
        }
    ],
    "sg:phone":"+1 250 762 8505",
    "sg:postcode":"V1X 1C3",
    "sg:province":"BC",
    "sg:tags":[
        "breakfast",
        "accommodation",
        "bed"
    ],
    "wof:name":"Bilodeau Bed & Breakfast",
    "wof:placetype":"venue"
},
  "geometry": {"coordinates":[-119.41607666,49.8803138733],"type":"Point"}
}