{
  "type": "Feature",
  "properties": {
    "addr:full":"10 Midland St Winnipeg MB R3E 2Y6",
    "addr:housenumber":"10",
    "addr:postcode":"r3e 2y6",
    "addr:street":"Midland St",
    "iso:country":"CA",
    "sg:address":"10 Midland St",
    "sg:city":"Winnipeg",
    "sg:classifiers":[
        {
            "category":"Government",
            "subcategory":"Office",
            "type":"Public Place"
        }
    ],
    "sg:phone":"+1 204 945 3278",
    "sg:postcode":"R3E 2Y6",
    "sg:province":"MB",
    "wof:name":"Manitoba Community Release Ctr",
    "wof:placetype":"venue"
},
  "geometry": {"coordinates":[-97.19003295900001,49.907245636],"type":"Point"}
}