{
  "type": "Feature",
  "properties": {
    "addr:full":"RR 6 STN Main Lindsay ON K9V 4R6",
    "addr:postcode":"k9v 4r6",
    "addr:street":"Rr 6 Stn",
    "iso:country":"CA",
    "sg:address":"RR 6 STN Main",
    "sg:city":"Lindsay",
    "sg:classifiers":[
        {
            "category":"Travel",
            "subcategory":"Hotels & Motels",
            "type":"Entertainment"
        }
    ],
    "sg:phone":"+1 705 793 2032",
    "sg:postcode":"K9V 4R6",
    "sg:province":"ON",
    "sg:tags":[
        "cottage",
        "cabin"
    ],
    "wof:name":"Rustic Bay Cottages",
    "wof:placetype":"venue"
},
  "geometry": {"coordinates":[-78.74006652830001,44.3542861938],"type":"Point"}
}