{
  "type": "Feature",
  "properties": {
    "addr:full":"1414 Vineland St Kelowna BC V1Y 3Y6",
    "addr:housenumber":"1414",
    "addr:postcode":"v1y 3y6",
    "addr:street":"Vineland St",
    "iso:country":"CA",
    "sg:address":"1414 Vineland St",
    "sg:city":"Kelowna",
    "sg:classifiers":[
        {
            "category":"Utilities",
            "type":"Services"
        }
    ],
    "sg:phone":"+1 250 868 1232",
    "sg:postcode":"V1Y 3Y6",
    "sg:province":"BC",
    "sg:tags":[
        "sweeping",
        "marking",
        "maintenance",
        "parking"
    ],
    "wof:name":"Dun-Rite Sweeping Svc",
    "wof:placetype":"venue"
},
  "geometry": {"coordinates":[-119.45985400000001,49.888863],"type":"Point"}
}