{
  "type": "Feature",
  "properties": {
    "addr:full":"Railway St Togo SK S0A 4E0",
    "addr:postcode":"s0a 4e0",
    "addr:street":"Railway St",
    "iso:country":"CA",
    "sg:address":"Railway St",
    "sg:city":"Togo",
    "sg:classifiers":[
        {
            "category":"Travel",
            "subcategory":"Hotels & Motels",
            "type":"Entertainment"
        }
    ],
    "sg:phone":"+1 306 597 2141",
    "sg:postcode":"S0A 4E0",
    "sg:province":"SK",
    "wof:name":"Empress Hotel",
    "wof:placetype":"venue"
},
  "geometry": {"coordinates":[-101.587982,51.404514],"type":"Point"}
}