{
  "type": "Feature",
  "properties": {
    "iso:country":"CA",
    "sg:address":"22 Rue Melancon E",
    "sg:city":"Alma",
    "sg:classifiers":[
        {
            "category":"Health Services",
            "subcategory":"Doctor",
            "type":"Services"
        }
    ],
    "sg:phone":"+1 418 668 2377",
    "sg:postcode":"G8B 6W3",
    "sg:province":"QC",
    "sg:tags":[
        "clinic"
    ],
    "wof:name":"Clinique DE Medicine Generale",
    "wof:placetype":"venue"
},
  "geometry": {"coordinates":[-71.6382827759,48.5566215515],"type":"Point"}
}