{
  "type": "Feature",
  "properties": {
    "addr:full":"1144 Rue Boulay Acton Vale QC J0H 1A0",
    "addr:housenumber":"1144",
    "addr:postcode":"j0h 1a0",
    "addr:street":"Rue Boulay",
    "iso:country":"CA",
    "sg:address":"1144 Rue Boulay",
    "sg:city":"Acton Vale",
    "sg:classifiers":[
        {
            "category":"Autos & Motor Vehicles",
            "subcategory":"Fuel & Gas Station",
            "type":"Retail Goods"
        }
    ],
    "sg:phone":"+1 450 546 2616",
    "sg:postcode":"J0H 1A0",
    "sg:province":"QC",
    "sg:tags":[
        "furnace"
    ],
    "wof:name":"Dupont Paul & Fils Inc",
    "wof:placetype":"venue"
},
  "geometry": {"coordinates":[-72.56684112550001,45.6476974487],"type":"Point"}
}