{
  "type": "Feature",
  "properties": {
    "addr:full":"360 Colony St Winnipeg MB R3B 2P3",
    "addr:housenumber":"360",
    "addr:postcode":"r3b 2p3",
    "addr:street":"Colony St",
    "iso:country":"CA",
    "sg:address":"360 Colony St",
    "sg:city":"Winnipeg",
    "sg:classifiers":[
        {
            "category":"Travel",
            "subcategory":"Hotels & Motels",
            "type":"Entertainment"
        }
    ],
    "sg:phone":"+1 204 786 7011",
    "sg:postcode":"R3B 2P3",
    "sg:province":"MB",
    "wof:name":"Holiday Inn Hotel & Suites",
    "wof:placetype":"venue"
},
  "geometry": {"coordinates":[-97.151253,49.891182],"type":"Point"}
}