{
  "type": "Feature",
  "properties": {
    "addr:full":"214 Princes St S Kincardine ON N2Z 2T2",
    "addr:housenumber":"214",
    "addr:postcode":"n2z 2t2",
    "addr:street":"Princes St S",
    "iso:country":"CA",
    "sg:address":"214 Princes St S",
    "sg:city":"Kincardine",
    "sg:classifiers":[
        {
            "category":"Retail",
            "subcategory":"Repair Shop",
            "type":"Services"
        }
    ],
    "sg:phone":"+1 519 396 8652",
    "sg:postcode":"N2Z 2T2",
    "sg:province":"ON",
    "sg:tags":[
        "water",
        "equipment",
        "softening"
    ],
    "wof:name":"R D's Water Conditioning",
    "wof:placetype":"venue"
},
  "geometry": {"coordinates":[-81.643799,44.163143],"type":"Point"}
}