{
  "type": "Feature",
  "properties": {
    "addr:full":"22 Pine St Pine Falls MB R0E 1M0",
    "addr:housenumber":"22",
    "addr:postcode":"r0e 1m0",
    "addr:street":"Pine St",
    "iso:country":"CA",
    "sg:address":"22 Pine St",
    "sg:city":"Pine Falls",
    "sg:classifiers":[
        {
            "category":"Shopping",
            "subcategory":"Pharmacy",
            "type":"Retail Goods"
        }
    ],
    "sg:phone":"+1 204 367 2517",
    "sg:postcode":"R0E 1M0",
    "sg:province":"MB",
    "wof:name":"Pine Pharmacy",
    "wof:placetype":"venue"
},
  "geometry": {"coordinates":[-96.2175750732,50.5673561096],"type":"Point"}
}