{
  "type": "Feature",
  "properties": {
    "iso:country":"CA",
    "sg:address":"5102 46 Ave",
    "sg:city":"Olds",
    "sg:classifiers":[
        {
            "category":"Restaurant",
            "type":"Food & Drink"
        }
    ],
    "sg:phone":"+1 403 556 8656",
    "sg:postcode":"T4H 1E6",
    "sg:province":"AB",
    "wof:name":"South China Sea",
    "wof:placetype":"venue"
},
  "geometry": {"coordinates":[-114.104515076,51.7951316833],"type":"Point"}
}