{
  "type": "Feature",
  "properties": {
    "addr:full":"Kamloops BC V2E 2N1",
    "addr:postcode":"bc v2e 2n1",
    "iso:country":"CA",
    "sg:city":"Kamloops",
    "sg:classifiers":[
        {
            "category":"Banks & Credit Unions",
            "subcategory":"Investment Brokerage",
            "type":"Services"
        }
    ],
    "sg:phone":"+1 250 851 2054",
    "sg:postcode":"V2E 2N1",
    "sg:province":"BC",
    "wof:name":"Edwards Jones",
    "wof:placetype":"venue"
},
  "geometry": {"coordinates":[-120.36998,50.661716],"type":"Point"}
}