{
  "type": "Feature",
  "properties": {
    "addr:full":"20 Rue Saint-Germain E Rimouski QC G5L 1A2",
    "addr:housenumber":"20",
    "addr:postcode":"g5l 1a2",
    "addr:street":"Rue Saint-Germain E",
    "iso:country":"CA",
    "sg:address":"20 Rue Saint-Germain E",
    "sg:city":"Rimouski",
    "sg:classifiers":[
        {
            "category":"Shopping",
            "subcategory":"Books",
            "type":"Retail Goods"
        }
    ],
    "sg:phone":"+1 418 721 3669",
    "sg:postcode":"G5L 1A2",
    "sg:province":"QC",
    "sg:tags":[
        "dealer"
    ],
    "wof:name":"Fou Du Roi",
    "wof:placetype":"venue"
},
  "geometry": {"coordinates":[-68.5269622803,48.4517784119],"type":"Point"}
}