{
  "type": "Feature",
  "properties": {
    "addr:full":"29 Casewood Dr Hanwell NB E3C 2L6",
    "addr:housenumber":"29",
    "addr:postcode":"e3c 2l6",
    "addr:street":"Casewood Dr",
    "iso:country":"CA",
    "sg:address":"29 Casewood Dr",
    "sg:city":"Hanwell",
    "sg:classifiers":[
        {
            "category":"Wholesale",
            "subcategory":"Sporting Goods",
            "type":"Manufacturing & Wholesale Goods"
        }
    ],
    "sg:phone":"+1 506 454 7333",
    "sg:postcode":"E3C 2L6",
    "sg:province":"NB",
    "sg:tags":[
        "course",
        "golf",
        "equipment"
    ],
    "wof:name":"Maritime Turf Supplies Ltd",
    "wof:placetype":"venue"
},
  "geometry": {"coordinates":[-66.795441,45.868484],"type":"Point"}
}