{
  "type": "Feature",
  "properties": {
    "addr:full":"Fort Mcmurray AB T9H 1L2",
    "addr:postcode":"t9h 1l2",
    "iso:country":"CA",
    "sg:city":"Fort Mcmurray",
    "sg:classifiers":[
        {
            "category":"Health Services",
            "subcategory":"Doctor",
            "type":"Services"
        }
    ],
    "sg:phone":"+1 780 791 0779",
    "sg:postcode":"T9H 1L2",
    "sg:province":"AB",
    "sg:tags":[
        "dentist"
    ],
    "wof:name":"Northern Lights Dental Ctr",
    "wof:placetype":"venue"
},
  "geometry": {"coordinates":[-111.380966187,56.7248878479],"type":"Point"}
}