{
  "type": "Feature",
  "properties": {
    "addr:full":"Kelowna BC V1X 7C5",
    "addr:postcode":"v1x 7c5",
    "iso:country":"CA",
    "sg:city":"Kelowna",
    "sg:classifiers":[
        {
            "category":"Building & Trades",
            "subcategory":"Plumbing",
            "type":"Services"
        }
    ],
    "sg:phone":"+1 250 762 7288",
    "sg:postcode":"V1X 7C5",
    "sg:province":"BC",
    "sg:tags":[
        "sheet",
        "work",
        "metal",
        "contractor"
    ],
    "wof:name":"G W Industries",
    "wof:placetype":"venue"
},
  "geometry": {"coordinates":[-119.432373047,49.8865127563],"type":"Point"}
}