{
  "type": "Feature",
  "properties": {
    "addr:full":"1072 Queen St W Toronto ON M6J 1H8",
    "addr:housenumber":"1072",
    "addr:postcode":"m6j 1h8",
    "addr:street":"Queen St W",
    "iso:country":"CA",
    "sg:address":"1072 Queen St W",
    "sg:city":"Toronto",
    "sg:classifiers":[
        {
            "category":"Home & Garden",
            "subcategory":"Household Appliances",
            "type":"Retail Goods"
        }
    ],
    "sg:phone":"+1 416 533 9903",
    "sg:postcode":"M6J 1H8",
    "sg:province":"ON",
    "wof:name":"Royal Appliances",
    "wof:placetype":"venue"
},
  "geometry": {"coordinates":[-79.421738,43.643753],"type":"Point"}
}