{
  "type": "Feature",
  "properties": {
    "addr:full":"920 Memorial Ave Thunder Bay ON P7B 3Z9",
    "addr:housenumber":"920",
    "addr:postcode":"p7b 3z9",
    "addr:street":"Memorial Ave",
    "iso:country":"CA",
    "sg:address":"920 Memorial Ave",
    "sg:city":"Thunder Bay",
    "sg:classifiers":[
        {
            "category":"Shopping",
            "subcategory":"Books",
            "type":"Retail Goods"
        }
    ],
    "sg:phone":"+1 807 345 1159",
    "sg:postcode":"P7B 3Z9",
    "sg:province":"ON",
    "sg:tags":[
        "dealer"
    ],
    "wof:name":"Book Shelf",
    "wof:placetype":"venue"
},
  "geometry": {"coordinates":[-89.2456436157,48.4103355408],"type":"Point"}
}