{
  "type": "Feature",
  "properties": {
    "iso:country":"CA",
    "sg:address":"10164 Yonge St",
    "sg:city":"Richmond Hill",
    "sg:classifiers":[
        {
            "category":"Personal",
            "subcategory":"Beauty Salon",
            "type":"Services"
        }
    ],
    "sg:phone":"+1 905 884 3545",
    "sg:postcode":"L4C 1T6",
    "sg:province":"ON",
    "sg:tags":[
        "school"
    ],
    "wof:name":"International Academy of Hair",
    "wof:placetype":"venue"
},
  "geometry": {"coordinates":[-79.4382858276,43.8751983643],"type":"Point"}
}