{
  "type": "Feature",
  "properties": {
    "addr:full":"5006 50 St Camrose AB T4V 1R2",
    "addr:housenumber":"5006",
    "addr:postcode":"t4v 1r2",
    "addr:street":"50 St",
    "iso:country":"CA",
    "sg:address":"5006 50 St",
    "sg:city":"Camrose",
    "sg:classifiers":[
        {
            "category":"Retail",
            "subcategory":"Portrait Studio",
            "type":"Services"
        }
    ],
    "sg:phone":"+1 780 672 5547",
    "sg:postcode":"T4V 1R2",
    "sg:province":"AB",
    "sg:tags":[
        "photographer"
    ],
    "wof:name":"Lyseng Studios",
    "wof:placetype":"venue"
},
  "geometry": {"coordinates":[-112.825012207,53.022480011],"type":"Point"}
}