{
  "type": "Feature",
  "properties": {
    "iso:country":"CA",
    "sg:address":"4018 New St",
    "sg:city":"Burlington",
    "sg:classifiers":[
        {
            "category":"Personal",
            "subcategory":"Beauty Salon",
            "type":"Services"
        }
    ],
    "sg:phone":"+1 905 333 4958",
    "sg:postcode":"L7L 1S7",
    "sg:province":"ON",
    "wof:name":"Bozena's Aesthetics",
    "wof:placetype":"venue"
},
  "geometry": {"coordinates":[-79.768898,43.353214],"type":"Point"}
}