{
  "type": "Feature",
  "properties": {
    "addr:full":"4018 New St Burlington ON L7L 1S7",
    "addr:housenumber":"4018",
    "addr:postcode":"l7l 1s7",
    "addr:street":"New St",
    "iso:country":"CA",
    "sg:address":"4018 New St",
    "sg:city":"Burlington",
    "sg:classifiers":[
        {
            "category":"Personal",
            "subcategory":"Beauty Salon",
            "type":"Services"
        }
    ],
    "sg:phone":"+1 905 333 4958",
    "sg:postcode":"L7L 1S7",
    "sg:province":"ON",
    "wof:name":"Bozena's Aesthetics",
    "wof:placetype":"venue"
},
  "geometry": {"coordinates":[-79.76889799999999,43.353214],"type":"Point"}
}