{
  "type": "Feature",
  "properties": {
    "addr:full":"Kitchener ON N2H 5Z8",
    "addr:postcode":"n2h 5z8",
    "iso:country":"CA",
    "sg:city":"Kitchener",
    "sg:classifiers":[
        {
            "category":"Health Services",
            "subcategory":"Doctor",
            "type":"Services"
        }
    ],
    "sg:phone":"+1 519 741 5252",
    "sg:postcode":"N2H 5Z8",
    "sg:province":"ON",
    "sg:tags":[
        "physician",
        "surgeon"
    ],
    "wof:name":"Cardio Pulmonary Svc",
    "wof:placetype":"venue"
},
  "geometry": {"coordinates":[-80.5112457275,43.457611084],"type":"Point"}
}