{
  "type": "Feature",
  "properties": {
    "addr:full":"190 3rd Ave Cochrane ON P0L 1C0",
    "addr:housenumber":"190",
    "addr:postcode":"p0l 1c0",
    "addr:street":"3Rd Ave",
    "iso:country":"CA",
    "sg:address":"190 3rd Ave",
    "sg:city":"Cochrane",
    "sg:classifiers":[
        {
            "category":"Social Services",
            "type":"Services"
        }
    ],
    "sg:phone":"+1 705 272 4497",
    "sg:postcode":"P0L 1C0",
    "sg:province":"ON",
    "sg:tags":[
        "organization",
        "association",
        "welfare"
    ],
    "wof:name":"Ininew Friendship Ctr",
    "wof:placetype":"venue"
},
  "geometry": {"coordinates":[-81.029549,49.063763],"type":"Point"}
}