{
  "type": "Feature",
  "properties": {
    "addr:full":"St Albert AB T8N 2X4",
    "addr:postcode":"t8n 2x4",
    "iso:country":"CA",
    "sg:city":"St Albert",
    "sg:classifiers":[
        {
            "category":"Social Services",
            "type":"Services"
        }
    ],
    "sg:phone":"+1 780 460 1113",
    "sg:postcode":"T8N 2X4",
    "sg:province":"AB",
    "sg:tags":[
        "counseling"
    ],
    "wof:name":"Donnelly, Carolyn",
    "wof:placetype":"venue"
},
  "geometry": {"coordinates":[-113.626205,53.634941],"type":"Point"}
}