{
  "type": "Feature",
  "properties": {
    "addr:full":"10127 145 St NW Edmonton AB T5N 2X6",
    "addr:housenumber":"10127",
    "addr:postcode":"t5n 2x6",
    "addr:street":"145 St Nw",
    "iso:country":"CA",
    "sg:address":"10127 145 St NW",
    "sg:city":"Edmonton",
    "sg:classifiers":[
        {
            "category":"Organizations",
            "subcategory":"Religious Organization",
            "type":"Services"
        }
    ],
    "sg:phone":"+1 780 455 0771",
    "sg:postcode":"T5N 2X6",
    "sg:province":"AB",
    "sg:tags":[
        "church"
    ],
    "wof:name":"St Paul's Anglican Church",
    "wof:placetype":"venue"
},
  "geometry": {"coordinates":[-113.570640564,53.5419082642],"type":"Point"}
}