{
  "type": "Feature",
  "properties": {
    "addr:full":"Black Point LA Loche SK S0M 1G0",
    "addr:postcode":"s0m 1g0",
    "iso:country":"CA",
    "sg:address":"Black Point",
    "sg:city":"LA Loche",
    "sg:classifiers":[
        {
            "category":"Government",
            "subcategory":"Office",
            "type":"Public Place"
        }
    ],
    "sg:phone":"+1 306 822 2727",
    "sg:postcode":"S0M 1G0",
    "sg:province":"SK",
    "sg:tags":[
        "municipality"
    ],
    "wof:name":"Northern Settlement-Black Pnt",
    "wof:placetype":"venue"
},
  "geometry": {"coordinates":[-109.436096191,56.482334137],"type":"Point"}
}