{
  "type": "Feature",
  "properties": {
    "addr:full":"776 Victoria St Kamloops BC V2C 2B6",
    "addr:housenumber":"776",
    "addr:postcode":"bc v2c 2b6",
    "addr:street":"Victoria St",
    "iso:country":"CA",
    "sg:address":"776 Victoria St",
    "sg:city":"Kamloops",
    "sg:classifiers":[
        {
            "category":"Retail",
            "subcategory":"Repair Shop",
            "type":"Services"
        }
    ],
    "sg:phone":"+1 250 374 5305",
    "sg:postcode":"V2C 2B6",
    "sg:province":"BC",
    "sg:tags":[
        "automobile",
        "top",
        "upholstery",
        "upholsterer"
    ],
    "wof:name":"Wallace Upholstery & Drapery",
    "wof:placetype":"venue"
},
  "geometry": {"coordinates":[-120.32225800000001,50.676006],"type":"Point"}
}