{
  "type": "Feature",
  "properties": {
    "addr:full":"3 First St Elmsdale NS B2S 2L5",
    "addr:housenumber":"3",
    "addr:postcode":"b2s 2l5",
    "addr:street":"First St",
    "iso:country":"CA",
    "sg:address":"3 First St",
    "sg:city":"Elmsdale",
    "sg:classifiers":[
        {
            "category":"Utilities",
            "subcategory":"Refuse",
            "type":"Services"
        }
    ],
    "sg:phone":"+1 902 883 4561",
    "sg:postcode":"B2S 2L5",
    "sg:province":"NS",
    "sg:tags":[
        "garbage",
        "collection"
    ],
    "wof:name":"Miller Waste Systems",
    "wof:placetype":"venue"
},
  "geometry": {"coordinates":[-63.5046348572,44.9673805237],"type":"Point"}
}