{
  "type": "Feature",
  "properties": {
    "addr:full":"1770 Ch Gomin Sillery QC G1S 1P2",
    "addr:housenumber":"1770",
    "addr:postcode":"g1s 1p2",
    "addr:street":"Ch Gomin",
    "iso:country":"CA",
    "sg:address":"1770 Ch Gomin",
    "sg:city":"Sillery",
    "sg:classifiers":[
        {
            "category":"Home & Garden",
            "subcategory":"Building Materials",
            "type":"Retail Goods"
        }
    ],
    "sg:phone":"+1 418 527 7444",
    "sg:postcode":"G1S 1P2",
    "sg:province":"QC",
    "sg:tags":[
        "glass",
        "leaded"
    ],
    "wof:name":"Atelier in Vitraux",
    "wof:placetype":"venue"
},
  "geometry": {"coordinates":[-71.25402800000001,46.787491],"type":"Point"}
}