{
  "type": "Feature",
  "properties": {
    "addr:full":"404 Vernon St Nelson BC V1L 4E5",
    "addr:housenumber":"404",
    "addr:postcode":"bc v1l 4e5",
    "addr:street":"Vernon St",
    "iso:country":"CA",
    "sg:address":"404 Vernon St",
    "sg:city":"Nelson",
    "sg:classifiers":[
        {
            "category":"Professional",
            "subcategory":"Printing & Photocopies",
            "type":"Services"
        }
    ],
    "sg:phone":"+1 250 352 5371",
    "sg:postcode":"V1L 4E5",
    "sg:province":"BC",
    "sg:tags":[
        "blueprinting"
    ],
    "wof:name":"Fairbank Reproductions",
    "wof:placetype":"venue"
},
  "geometry": {"coordinates":[-117.29576900000001,49.49221],"type":"Point"}
}