{
  "type": "Feature",
  "properties": {
    "addr:full":"5221 48 Ave Taber AB T1G 1S8",
    "addr:housenumber":"5221",
    "addr:postcode":"t1g 1s8",
    "addr:street":"48 Ave Taber",
    "iso:country":"CA",
    "sg:address":"5221 48 Ave",
    "sg:city":"Taber",
    "sg:classifiers":[
        {
            "category":"Shopping",
            "subcategory":"Clothing, Apparel, & Fashions",
            "type":"Retail Goods"
        }
    ],
    "sg:phone":"+1 403 223 2497",
    "sg:postcode":"T1G 1S8",
    "sg:province":"AB",
    "wof:name":"Great Garb Boutique Ltd",
    "wof:placetype":"venue"
},
  "geometry": {"coordinates":[-112.14630099999999,49.784512],"type":"Point"}
}