{
  "type": "Feature",
  "properties": {
    "addr:full":"Richmond BC V7E 3A7",
    "addr:postcode":"v7e 3a7",
    "iso:country":"CA",
    "sg:city":"Richmond",
    "sg:classifiers":[
        {
            "category":"Shopping",
            "subcategory":"Gifts & Souvenirs",
            "type":"Retail Goods"
        }
    ],
    "sg:phone":"+1 604 277 6866",
    "sg:postcode":"V7E 3A7",
    "sg:province":"BC",
    "sg:tags":[
        "shop",
        "confectionery",
        "candy"
    ],
    "wof:name":"Candy Bouquet",
    "wof:placetype":"venue"
},
  "geometry": {"coordinates":[-123.18192291299999,49.1253852844],"type":"Point"}
}