{
  "type": "Feature",
  "properties": {
    "addr:full":"Chevery QC G0G 1G0",
    "addr:postcode":"g0g 1g0",
    "iso:country":"CA",
    "sg:city":"Chevery",
    "sg:classifiers":[
        {
            "category":"Airport",
            "type":"Transportation"
        }
    ],
    "sg:phone":"+1 418 787 2215",
    "sg:postcode":"G0G 1G0",
    "sg:province":"QC",
    "wof:name":"Aeroport DE Chevery",
    "wof:placetype":"venue"
},
  "geometry": {"coordinates":[-59.2439994812,50.6828918457],"type":"Point"}
}