{
  "type": "Feature",
  "properties": {
    "addr:full":"140 Mount Albion Rd Hamilton ON L8K 5S8",
    "addr:housenumber":"140",
    "addr:postcode":"l8k 5s8",
    "addr:street":"Mount Albion Rd",
    "iso:country":"CA",
    "sg:address":"140 Mount Albion Rd",
    "sg:city":"Hamilton",
    "sg:classifiers":[
        {
            "category":"Shopping",
            "subcategory":"Musical Instruments",
            "type":"Retail Goods"
        }
    ],
    "sg:phone":"+1 905 561 1331",
    "sg:postcode":"L8K 5S8",
    "sg:province":"ON",
    "sg:tags":[
        "organs"
    ],
    "wof:name":"R A Denton & Son",
    "wof:placetype":"venue"
},
  "geometry": {"coordinates":[-79.793167,43.220379],"type":"Point"}
}