{
  "type": "Feature",
  "properties": {
    "addr:full":"10353 Hwy 221 Canning NS B0P 1H0",
    "addr:housenumber":"10353",
    "addr:postcode":"b0p 1h0",
    "addr:street":"Hwy 221",
    "iso:country":"CA",
    "sg:address":"10353 Hwy 221",
    "sg:city":"Canning",
    "sg:classifiers":[
        {
            "category":"Building & Trades",
            "subcategory":"Construction",
            "type":"Services"
        }
    ],
    "sg:phone":"+1 902 582 3809",
    "sg:postcode":"B0P 1H0",
    "sg:province":"NS",
    "sg:tags":[
        "roofing",
        "contractor"
    ],
    "wof:name":"Acadia Roofing & Contracting",
    "wof:placetype":"venue"
},
  "geometry": {"coordinates":[-64.4206695557,45.1574134827],"type":"Point"}
}