{
  "type": "Feature",
  "properties": {
    "addr:full":"107 Lansdowne St E Callander ON P0H 1H0",
    "addr:housenumber":"107",
    "addr:postcode":"p0h 1h0",
    "addr:street":"Lansdowne St E",
    "iso:country":"CA",
    "sg:address":"107 Lansdowne St E",
    "sg:city":"Callander",
    "sg:classifiers":[
        {
            "category":"Museum",
            "type":"Entertainment"
        }
    ],
    "sg:phone":"+1 705 752 2282",
    "sg:postcode":"P0H 1H0",
    "sg:province":"ON",
    "wof:name":"Callander Bay Heritage Museum",
    "wof:placetype":"venue"
},
  "geometry": {"coordinates":[-79.362556,46.223103],"type":"Point"}
}