{
  "type": "Feature",
  "properties": {
    "addr:full":"42003 Mackenzie Hwy Hay River NT X0E 0R9",
    "addr:housenumber":"42003",
    "addr:postcode":"x0e 0r9",
    "addr:street":"Mackenzie Hwy",
    "iso:country":"CA",
    "sg:address":"42003 Mackenzie Hwy",
    "sg:city":"Hay River",
    "sg:classifiers":[
        {
            "category":"Manufacturing",
            "subcategory":"Tools & Machinery",
            "type":"Manufacturing & Wholesale Goods"
        }
    ],
    "sg:phone":"+1 867 874 5170",
    "sg:postcode":"X0E 0R9",
    "sg:province":"NT",
    "sg:tags":[
        "machine",
        "shop",
        "trucking"
    ],
    "wof:name":"Northern Transportation CO Ltd",
    "wof:placetype":"venue"
},
  "geometry": {"coordinates":[-115.782166,60.82058],"type":"Point"}
}