{
  "type": "Feature",
  "properties": {
    "addr:full":"327 Rue Lafontaine Riviere-Du-Loup QC G5R 3B2",
    "addr:housenumber":"327",
    "addr:postcode":"g5r 3b2",
    "addr:street":"Rue Lafontaine",
    "iso:country":"CA",
    "sg:address":"327 Rue Lafontaine",
    "sg:city":"Riviere-Du-Loup",
    "sg:classifiers":[
        {
            "category":"Professional",
            "subcategory":"Business Services",
            "type":"Services"
        }
    ],
    "sg:phone":"+1 418 862 3535",
    "sg:postcode":"G5R 3B2",
    "sg:province":"QC",
    "sg:tags":[
        "consultant",
        "rug",
        "design",
        "interior",
        "dealer",
        "decorator",
        "carpet"
    ],
    "wof:name":"Decoration Gl Inc",
    "wof:placetype":"venue"
},
  "geometry": {"coordinates":[-69.53639200000001,47.832066],"type":"Point"}
}