{
  "type": "Feature",
  "properties": {
    "iso:country":"CA",
    "sg:address":"151 First Line",
    "sg:city":"Elora",
    "sg:classifiers":[
        {
            "category":"Building & Trades",
            "subcategory":"Construction",
            "type":"Services"
        }
    ],
    "sg:phone":"+1 519 846 5587",
    "sg:postcode":"N0B 1S0",
    "sg:province":"ON",
    "sg:tags":[
        "excavating",
        "contractor"
    ],
    "wof:name":"Brian Green Construction Ltd",
    "wof:placetype":"venue"
},
  "geometry": {"coordinates":[-80.40770721440001,43.679233551],"type":"Point"}
}