{
  "type": "Feature",
  "properties": {
    "addr:full":"2541 Yonge St Toronto ON M4P 2H9",
    "addr:housenumber":"2541",
    "addr:postcode":"m4p 2h9",
    "addr:street":"Yonge St",
    "iso:country":"CA",
    "sg:address":"2541 Yonge St",
    "sg:city":"Toronto",
    "sg:classifiers":[
        {
            "category":"Shopping",
            "subcategory":"Clothing, Apparel, & Fashions",
            "type":"Retail Goods"
        }
    ],
    "sg:phone":"+1 416 481 1074",
    "sg:postcode":"M4P 2H9",
    "sg:province":"ON",
    "wof:name":"Casual Way Ltd",
    "wof:placetype":"venue"
},
  "geometry": {"coordinates":[-79.399582,43.713127],"type":"Point"}
}