{
  "type": "Feature",
  "properties": {
    "addr:full":"300 Wallace St Nanaimo BC V9R 5B5",
    "addr:housenumber":"300",
    "addr:postcode":"v9r 5b5",
    "addr:street":"Wallace St",
    "iso:country":"CA",
    "sg:address":"300 Wallace St",
    "sg:city":"Nanaimo",
    "sg:classifiers":[
        {
            "category":"Retail",
            "subcategory":"Auto Repair",
            "type":"Services"
        }
    ],
    "sg:phone":"+1 250 754 6421",
    "sg:postcode":"V9R 5B5",
    "sg:province":"BC",
    "sg:tags":[
        "repairing",
        "automobile",
        "brake"
    ],
    "wof:name":"Gold Automotive",
    "wof:placetype":"venue"
},
  "geometry": {"coordinates":[-123.939499,49.16581],"type":"Point"}
}