{
  "type": "Feature",
  "properties": {
    "addr:full":"Granby QC J2G 8E9",
    "addr:postcode":"j2g 8e9",
    "iso:country":"CA",
    "sg:city":"Granby",
    "sg:classifiers":[
        {
            "category":"Organizations",
            "subcategory":"Religious Organization",
            "type":"Services"
        }
    ],
    "sg:phone":"+1 450 378 7732",
    "sg:postcode":"J2G 8E9",
    "sg:province":"QC",
    "wof:name":"Peres Du Verbe Divin",
    "wof:placetype":"venue"
},
  "geometry": {"coordinates":[-72.771767,45.394726],"type":"Point"}
}