{
  "type": "Feature",
  "properties": {
    "iso:country":"CA",
    "sg:address":"16850 Montee Guenette",
    "sg:city":"Mirabel",
    "sg:classifiers":[
        {
            "category":"Building & Trades",
            "subcategory":"Construction",
            "type":"Services"
        }
    ],
    "sg:phone":"+1 450 436 2880",
    "sg:postcode":"J7J 2E2",
    "sg:province":"QC",
    "sg:tags":[
        "builder",
        "gazebo"
    ],
    "wof:name":"Gazebos Du Nord Inc",
    "wof:placetype":"venue"
},
  "geometry": {"coordinates":[-73.9985961914,45.7448005676],"type":"Point"}
}