{
  "type": "Feature",
  "properties": {
    "addr:full":"Langley BC V1M 3E1",
    "addr:postcode":"v1m 3e1",
    "iso:country":"CA",
    "sg:city":"Langley",
    "sg:classifiers":[
        {
            "category":"Retail",
            "subcategory":"Auto Repair",
            "type":"Services"
        }
    ],
    "sg:phone":"+1 604 881 2075",
    "sg:postcode":"V1M 3E1",
    "sg:province":"BC",
    "sg:tags":[
        "truck"
    ],
    "wof:name":"G T Mechanical",
    "wof:placetype":"venue"
},
  "geometry": {"coordinates":[-122.676574707,49.1771965027],"type":"Point"}
}