{
  "type": "Feature",
  "properties": {
    "addr:full":"651 Highway 6 Caledonia ON N3W 1M3",
    "addr:housenumber":"651",
    "addr:postcode":"n3w 1m3",
    "addr:street":"Highway 6",
    "iso:country":"CA",
    "sg:address":"651 Highway 6",
    "sg:city":"Caledonia",
    "sg:classifiers":[
        {
            "category":"Manufacturing",
            "subcategory":"Wood Products",
            "type":"Manufacturing & Wholesale Goods"
        }
    ],
    "sg:phone":"+1 905 765 2736",
    "sg:postcode":"N3W 1M3",
    "sg:province":"ON",
    "sg:tags":[
        "pallet",
        "skid"
    ],
    "wof:name":"James Gordon & Sons Lumber",
    "wof:placetype":"venue"
},
  "geometry": {"coordinates":[-79.95072937010001,43.0735626221],"type":"Point"}
}