{
  "type": "Feature",
  "properties": {
    "addr:full":"16 Kingfisher Cres Cambridge ON N1T 1P9",
    "addr:housenumber":"16",
    "addr:postcode":"n1t 1p9",
    "addr:street":"Kingfisher Cres",
    "iso:country":"CA",
    "sg:address":"16 Kingfisher Cres",
    "sg:city":"Cambridge",
    "sg:classifiers":[
        {
            "category":"Manufacturing",
            "subcategory":"Printing",
            "type":"Manufacturing & Wholesale Goods"
        }
    ],
    "sg:phone":"+1 519 620 1265",
    "sg:postcode":"N1T 1P9",
    "sg:province":"ON",
    "sg:tags":[
        "printer",
        "broker"
    ],
    "wof:name":"Crossroads Print & Promotions",
    "wof:placetype":"venue"
},
  "geometry": {"coordinates":[-80.28270000000001,43.394001],"type":"Point"}
}