{
  "type": "Feature",
  "properties": {
    "addr:full":"362 Rue Salaberry Mont-Laurier QC J9L 1N7",
    "addr:housenumber":"362",
    "addr:postcode":"j9l 1n7",
    "addr:street":"Rue Salaberry",
    "iso:country":"CA",
    "sg:address":"362 Rue Salaberry",
    "sg:city":"Mont-Laurier",
    "sg:classifiers":[
        {
            "category":"Organizations",
            "subcategory":"Professional Association",
            "type":"Services"
        }
    ],
    "sg:phone":"+1 819 623 7215",
    "sg:postcode":"J9L 1N7",
    "sg:province":"QC",
    "wof:name":"Centre DE LA Famille",
    "wof:placetype":"venue"
},
  "geometry": {"coordinates":[-75.501389,46.549381],"type":"Point"}
}