{
  "type": "Feature",
  "properties": {
    "addr:full":"9696 Curry Rd Wallacetown ON N0L 2M0",
    "addr:housenumber":"9696",
    "addr:postcode":"n0l 2m0",
    "addr:street":"Curry Rd",
    "iso:country":"CA",
    "sg:address":"9696 Curry Rd",
    "sg:city":"Wallacetown",
    "sg:classifiers":[
        {
            "category":"Manufacturing",
            "subcategory":"Wood Products",
            "type":"Manufacturing & Wholesale Goods"
        }
    ],
    "sg:phone":"+1 519 762 2404",
    "sg:postcode":"N0L 2M0",
    "sg:province":"ON",
    "sg:tags":[
        "pallet",
        "skid"
    ],
    "wof:name":"Shelley's Sawmill Inc",
    "wof:placetype":"venue"
},
  "geometry": {"coordinates":[-81.4699172974,42.6383361816],"type":"Point"}
}