{
  "type": "Feature",
  "properties": {
    "iso:country":"CA",
    "sg:address":"35 Melnick Rd",
    "sg:city":"Winnipeg",
    "sg:classifiers":[
        {
            "category":"Wholesale",
            "subcategory":"Machinery & Supplies",
            "type":"Manufacturing & Wholesale Goods"
        }
    ],
    "sg:phone":"+1 204 255 0260",
    "sg:postcode":"R3X 1V5",
    "sg:province":"MB",
    "sg:tags":[
        "contractor"
    ],
    "wof:name":"Guertin Equipment Ltd",
    "wof:placetype":"venue"
},
  "geometry": {"coordinates":[-97.05632799999999,49.812996],"type":"Point"}
}