{
  "type": "Feature",
  "properties": {
    "addr:full":"PO Box 59 Wonowon BC V0C 2N0",
    "addr:housenumber":"po box 59",
    "addr:postcode":"bc v0c 2n0",
    "iso:country":"CA",
    "sg:address":"PO Box 59",
    "sg:city":"Wonowon",
    "sg:classifiers":[
        {
            "category":"Building & Trades",
            "subcategory":"Construction",
            "type":"Services"
        }
    ],
    "sg:phone":"+1 250 772 5404",
    "sg:postcode":"V0C 2N0",
    "sg:province":"BC",
    "sg:tags":[
        "general",
        "contractor"
    ],
    "wof:name":"Halfway Daneza Enterprises Ltd",
    "wof:placetype":"venue"
},
  "geometry": {"coordinates":[-121.81315600000001,56.731262],"type":"Point"}
}