{
  "type": "Feature",
  "properties": {
    "addr:full":"187 Garry St Winnipeg MB R3C 1G7",
    "addr:housenumber":"187",
    "addr:postcode":"r3c 1g7",
    "addr:street":"Garry St",
    "iso:country":"CA",
    "sg:address":"187 Garry St",
    "sg:city":"Winnipeg",
    "sg:classifiers":[
        {
            "category":"Travel",
            "subcategory":"Hotels & Motels",
            "type":"Entertainment"
        }
    ],
    "sg:phone":"+1 204 942 7528",
    "sg:postcode":"R3C 1G7",
    "sg:province":"MB",
    "wof:name":"Windsor Hotel",
    "wof:placetype":"venue"
},
  "geometry": {"coordinates":[-97.1387786865,49.8908576965],"type":"Point"}
}