{
  "type": "Feature",
  "properties": {
    "addr:full":"1545 Mcara St # D Regina SK S4N 6H4",
    "addr:housenumber":"1545",
    "addr:postcode":"s4n 6h4",
    "addr:street":"Mcara St # D",
    "iso:country":"CA",
    "sg:address":"1545 Mcara St # D",
    "sg:city":"Regina",
    "sg:classifiers":[
        {
            "category":"Building & Trades",
            "subcategory":"Construction",
            "type":"Services"
        }
    ],
    "sg:phone":"+1 306 761 5400",
    "sg:postcode":"S4N 6H4",
    "sg:province":"SK",
    "sg:tags":[
        "general",
        "contractor"
    ],
    "wof:name":"Artistic Masonry & Stucco",
    "wof:placetype":"venue"
},
  "geometry": {"coordinates":[-104.58197,50.454365],"type":"Point"}
}