{
  "type": "Feature",
  "properties": {
    "addr:full":"541A North Railway St SE Medicine Hat AB T1A 2Z5",
    "addr:housenumber":"541a",
    "addr:postcode":"t1a 2z5",
    "addr:street":"North Railway St Se",
    "iso:country":"CA",
    "sg:address":"541A North Railway St SE",
    "sg:city":"Medicine Hat",
    "sg:classifiers":[
        {
            "category":"Home & Garden",
            "subcategory":"Garden Supply",
            "type":"Retail Goods"
        }
    ],
    "sg:phone":"+1 403 526 6131",
    "sg:postcode":"T1A 2Z5",
    "sg:province":"AB",
    "sg:tags":[
        "lawn",
        "mower"
    ],
    "wof:name":"Zark Repair",
    "wof:placetype":"venue"
},
  "geometry": {"coordinates":[-110.669914246,50.0386734009],"type":"Point"}
}