{
  "type": "Feature",
  "properties": {
    "addr:full":"200 Queen St N Hamilton ON L8R 2W3",
    "addr:housenumber":"200",
    "addr:postcode":"l8r 2w3",
    "addr:street":"Queen St N",
    "iso:country":"CA",
    "sg:address":"200 Queen St N",
    "sg:city":"Hamilton",
    "sg:classifiers":[
        {
            "category":"Building & Trades",
            "subcategory":"Plumbing",
            "type":"Services"
        }
    ],
    "sg:phone":"+1 905 634 4697",
    "sg:postcode":"L8R 2W3",
    "sg:province":"ON",
    "sg:tags":[
        "air",
        "conditioning",
        "contractor",
        "system",
        "heating"
    ],
    "wof:name":"Hamco Heating & Cooling Ltd",
    "wof:placetype":"venue"
},
  "geometry": {"coordinates":[-79.8759841919,43.2654533386],"type":"Point"}
}