{
  "type": "Feature",
  "properties": {
    "addr:full":"6516 Wicks Rd Duncan BC V9L 5V2",
    "addr:housenumber":"6516",
    "addr:postcode":"v9l 5v2",
    "addr:street":"Wicks Rd",
    "iso:country":"CA",
    "sg:address":"6516 Wicks Rd",
    "sg:city":"Duncan",
    "sg:classifiers":[
        {
            "category":"Personal",
            "type":"Services"
        }
    ],
    "sg:phone":"+1 250 748 5678",
    "sg:postcode":"V9L 5V2",
    "sg:province":"BC",
    "sg:tags":[
        "electrolysis"
    ],
    "wof:name":"Carol's Electrolysis",
    "wof:placetype":"venue"
},
  "geometry": {"coordinates":[-123.70738220200001,48.779094696],"type":"Point"}
}