{
  "type": "Feature",
  "properties": {
    "iso:country":"CA",
    "sg:city":"Grande Prairie",
    "sg:classifiers":[
        {
            "category":"Retail",
            "subcategory":"Portrait Studio",
            "type":"Services"
        }
    ],
    "sg:phone":"+1 780 532 5051",
    "sg:postcode":"T8V 0T9",
    "sg:province":"AB",
    "sg:tags":[
        "photo",
        "finishing"
    ],
    "wof:name":"Snapshot 1 HR Photo & Gallery",
    "wof:placetype":"venue"
},
  "geometry": {"coordinates":[-118.792198181,55.1708717346],"type":"Point"}
}