{
  "type": "Feature",
  "properties": {
    "addr:full":"341 Weber St N Waterloo ON N2J 3H8",
    "addr:housenumber":"341",
    "addr:postcode":"n2j 3h8",
    "addr:street":"Weber St N",
    "iso:country":"CA",
    "sg:address":"341 Weber St N",
    "sg:city":"Waterloo",
    "sg:classifiers":[
        {
            "category":"Local Transit",
            "type":"Transportation"
        }
    ],
    "sg:phone":"+1 519 886 8090",
    "sg:postcode":"N2J 3H8",
    "sg:province":"ON",
    "sg:tags":[
        "limousine"
    ],
    "wof:name":"Boulevard Limousine",
    "wof:placetype":"venue"
},
  "geometry": {"coordinates":[-80.52327699999999,43.481812],"type":"Point"}
}