{
  "type": "Feature",
  "properties": {
    "addr:full":"300 Albert St Port Moody BC V3H 2M5",
    "addr:housenumber":"300",
    "addr:postcode":"v3h 2m5",
    "addr:street":"Albert St",
    "iso:country":"CA",
    "sg:address":"300 Albert St",
    "sg:city":"Port Moody",
    "sg:classifiers":[
        {
            "category":"Education",
            "subcategory":"School",
            "type":"Public Place"
        }
    ],
    "sg:phone":"+1 604 939 6656",
    "sg:postcode":"V3H 2M5",
    "sg:province":"BC",
    "wof:name":"Port Moody Senior Secondary",
    "wof:placetype":"venue"
},
  "geometry": {"coordinates":[-122.866753,49.274673],"type":"Point"}
}