{
  "type": "Feature",
  "properties": {
    "addr:full":"Barraute QC J0Y 1A0",
    "addr:postcode":"j0y 1a0",
    "iso:country":"CA",
    "sg:city":"Barraute",
    "sg:classifiers":[
        {
            "category":"Freight",
            "type":"Transportation"
        }
    ],
    "sg:phone":"+1 819 734 6787",
    "sg:postcode":"J0Y 1A0",
    "sg:province":"QC",
    "sg:tags":[
        "trucking"
    ],
    "wof:name":"Julien Omer Transport",
    "wof:placetype":"venue"
},
  "geometry": {"coordinates":[-77.6286239624,48.4369506836],"type":"Point"}
}