{
  "type": "Feature",
  "properties": {
    "addr:full":"Souris PE C0A 2B0",
    "addr:postcode":"c0a 2b0",
    "iso:country":"CA",
    "sg:city":"Souris",
    "sg:classifiers":[
        {
            "category":"Home & Garden",
            "subcategory":"Carpets & Floor Coverings",
            "type":"Retail Goods"
        }
    ],
    "sg:phone":"+1 902 687 3512",
    "sg:postcode":"C0A 2B0",
    "sg:province":"PE",
    "sg:tags":[
        "material"
    ],
    "wof:name":"Floor Store",
    "wof:placetype":"venue"
},
  "geometry": {"coordinates":[-62.2537,46.35379],"type":"Point"}
}