{
  "type": "Feature",
  "properties": {
    "addr:full":"699 Haney St Winnipeg MB R3R 0Y7",
    "addr:housenumber":"699",
    "addr:postcode":"r3r 0y7",
    "addr:street":"Haney St",
    "iso:country":"CA",
    "sg:address":"699 Haney St",
    "sg:city":"Winnipeg",
    "sg:classifiers":[
        {
            "category":"Organizations",
            "subcategory":"Religious Organization",
            "type":"Services"
        }
    ],
    "sg:phone":"+1 204 837 7982",
    "sg:postcode":"R3R 0Y7",
    "sg:province":"MB",
    "sg:tags":[
        "church"
    ],
    "wof:name":"Charleswood Mennonite Church",
    "wof:placetype":"venue"
},
  "geometry": {"coordinates":[-97.26611328120001,49.8522071838],"type":"Point"}
}