{
  "type": "Feature",
  "properties": {
    "addr:full":"3 Century Blvd Millbrook ON L0A 1G0",
    "addr:housenumber":"3",
    "addr:postcode":"l0a 1g0",
    "addr:street":"Century Blvd",
    "iso:country":"CA",
    "sg:address":"3 Century Blvd",
    "sg:city":"Millbrook",
    "sg:classifiers":[
        {
            "category":"Retail",
            "subcategory":"Animal Services",
            "type":"Services"
        }
    ],
    "sg:phone":"+1 705 932 2628",
    "sg:postcode":"L0A 1G0",
    "sg:province":"ON",
    "sg:tags":[
        "pet",
        "grooming",
        "washing"
    ],
    "wof:name":"A & D Grooming Professionals",
    "wof:placetype":"venue"
},
  "geometry": {"coordinates":[-78.4459686279,44.1563224792],"type":"Point"}
}