{
  "type": "Feature",
  "properties": {
    "iso:country":"CA",
    "sg:city":"Midland",
    "sg:classifiers":[
        {
            "category":"Home & Garden",
            "subcategory":"Household Appliances",
            "type":"Retail Goods"
        }
    ],
    "sg:phone":"+1 705 526 9381",
    "sg:postcode":"L4R 4K4",
    "sg:province":"ON",
    "wof:name":"Sears Canada Inc",
    "wof:placetype":"venue"
},
  "geometry": {"coordinates":[-79.88851165769999,44.7499046326],"type":"Point"}
}