{
  "type": "Feature",
  "properties": {
    "addr:full":"4637 Macleod Trail SW Calgary AB T2G 5C1",
    "addr:housenumber":"4637",
    "addr:postcode":"t2g 5c1",
    "addr:street":"Macleod Trail Sw",
    "iso:country":"CA",
    "sg:address":"4637 Macleod Trail SW",
    "sg:city":"Calgary",
    "sg:classifiers":[
        {
            "category":"Real Estate",
            "subcategory":"Real Estate Agent",
            "type":"Services"
        }
    ],
    "sg:phone":"+1 403 287 1957",
    "sg:postcode":"T2G 5C1",
    "sg:province":"AB",
    "sg:tags":[
        "management"
    ],
    "wof:name":"Stanley Park Place",
    "wof:placetype":"venue"
},
  "geometry": {"coordinates":[-114.066429138,51.0122909546],"type":"Point"}
}