{
  "type": "Feature",
  "properties": {
    "addr:full":"5011 50 Ave Stettler AB T0C 2L2",
    "addr:housenumber":"5011",
    "addr:postcode":"t0c 2l2",
    "addr:street":"50 Ave",
    "iso:country":"CA",
    "sg:address":"5011 50 Ave",
    "sg:city":"Stettler",
    "sg:classifiers":[
        {
            "category":"Manufacturing",
            "subcategory":"Printing",
            "type":"Manufacturing & Wholesale Goods"
        }
    ],
    "sg:phone":"+1 403 742 8858",
    "sg:postcode":"T0C 2L2",
    "sg:province":"AB",
    "sg:tags":[
        "printer"
    ],
    "wof:name":"Heartland Promotions Inc",
    "wof:placetype":"venue"
},
  "geometry": {"coordinates":[-112.705521,52.325829],"type":"Point"}
}