{
  "type": "Feature",
  "properties": {
    "addr:full":"Calgary AB T2B 0B1",
    "addr:postcode":"t2b 0b1",
    "iso:country":"CA",
    "sg:city":"Calgary",
    "sg:classifiers":[
        {
            "category":"Restaurant",
            "type":"Food & Drink"
        }
    ],
    "sg:phone":"+1 403 272 8008",
    "sg:postcode":"T2B 0B1",
    "sg:province":"AB",
    "wof:name":"Sinclair's Diner",
    "wof:placetype":"venue"
},
  "geometry": {"coordinates":[-113.959946,51.035397],"type":"Point"}
}