{
  "type": "Feature",
  "properties": {
    "addr:full":"North York ON M3J 2E9",
    "addr:postcode":"m3j 2e9",
    "iso:country":"CA",
    "sg:city":"North York",
    "sg:classifiers":[
        {
            "category":"Wholesale",
            "subcategory":"Machinery & Supplies",
            "type":"Manufacturing & Wholesale Goods"
        }
    ],
    "sg:phone":"+1 416 667 1761",
    "sg:postcode":"M3J 2E9",
    "sg:province":"ON",
    "sg:tags":[
        "janitor"
    ],
    "wof:name":"National Cleaning & Maintenanc",
    "wof:placetype":"venue"
},
  "geometry": {"coordinates":[-79.481453,43.765453],"type":"Point"}
}