{
  "type": "Feature",
  "properties": {
    "addr:full":"325 Vulcan Ave Sydney NS B1P 5X1",
    "addr:housenumber":"325",
    "addr:postcode":"b1p 5x1",
    "addr:street":"Vulcan Ave",
    "iso:country":"CA",
    "sg:address":"325 Vulcan Ave",
    "sg:city":"Sydney",
    "sg:classifiers":[
        {
            "category":"Professional",
            "subcategory":"Business Services",
            "type":"Services"
        }
    ],
    "sg:phone":"+1 902 563 9050",
    "sg:postcode":"B1P 5X1",
    "sg:province":"NS",
    "sg:tags":[
        "telemarketing"
    ],
    "wof:name":"Ict Canada Marketing Inc",
    "wof:placetype":"venue"
},
  "geometry": {"coordinates":[-60.165005,46.145576],"type":"Point"}
}