{
  "type": "Feature",
  "properties": {
    "addr:full":"Saskatoon SK S7K 1N4",
    "addr:postcode":"s7k 1n4",
    "iso:country":"CA",
    "sg:city":"Saskatoon",
    "sg:classifiers":[
        {
            "category":"Health Services",
            "subcategory":"Doctor",
            "type":"Services"
        }
    ],
    "sg:phone":"+1 306 665 0777",
    "sg:postcode":"S7K 1N4",
    "sg:province":"SK",
    "sg:tags":[
        "dentist"
    ],
    "wof:name":"Wall Street Dental Clinic",
    "wof:placetype":"venue"
},
  "geometry": {"coordinates":[-106.66910553,52.1302490234],"type":"Point"}
}