{
  "type": "Feature",
  "properties": {
    "iso:country":"CA",
    "sg:address":"911 Rue Jean-Talon E",
    "sg:city":"Montreal",
    "sg:classifiers":[
        {
            "category":"Education",
            "subcategory":"School",
            "type":"Public Place"
        }
    ],
    "sg:phone":"+1 514 270 1336",
    "sg:postcode":"H2R 1V5",
    "sg:province":"QC",
    "sg:tags":[
        "academic",
        "special"
    ],
    "wof:name":"Centre Des Metiers Du Cuir",
    "wof:placetype":"venue"
},
  "geometry": {"coordinates":[-73.6130142212,45.5412559509],"type":"Point"}
}