{
  "type": "Feature",
  "properties": {
    "addr:full":"129 Rte DE St-Alphonse Saint-Alphonse-DE-Caplan QC G0C 2V0",
    "addr:housenumber":"129",
    "addr:postcode":"g0c 2v0",
    "addr:street":"Rte De St-Alphonse Saint-Alphonse-De-Caplan",
    "iso:country":"CA",
    "sg:address":"129 Rte DE St-Alphonse",
    "sg:city":"Saint-Alphonse-DE-Caplan",
    "sg:classifiers":[
        {
            "category":"Food & Beverages",
            "subcategory":"Groceries & Convenience Stores",
            "type":"Retail Goods"
        }
    ],
    "sg:phone":"+1 418 388 5558",
    "sg:postcode":"G0C 2V0",
    "sg:province":"QC",
    "wof:name":"Depanneur Le Duo Enr",
    "wof:placetype":"venue"
},
  "geometry": {"coordinates":[-65.67924499999999,48.101181],"type":"Point"}
}