{
  "type": "Feature",
  "properties": {
    "addr:full":"1787 Drew Rd Mississauga ON L5S 1J5",
    "addr:housenumber":"1787",
    "addr:postcode":"l5s 1j5",
    "addr:street":"Drew Rd",
    "iso:country":"CA",
    "sg:address":"1787 Drew Rd",
    "sg:city":"Mississauga",
    "sg:classifiers":[
        {
            "category":"Wholesale",
            "subcategory":"Construction Materials",
            "type":"Manufacturing & Wholesale Goods"
        }
    ],
    "sg:phone":"+1 905 672 2020",
    "sg:postcode":"L5S 1J5",
    "sg:province":"ON",
    "sg:tags":[
        "waterproofing"
    ],
    "wof:name":"Gemite Products Inc",
    "wof:placetype":"venue"
},
  "geometry": {"coordinates":[-79.6747207642,43.6860389709],"type":"Point"}
}