{
  "type": "Feature",
  "properties": {
    "iso:country":"CA",
    "sg:address":"184 Rue Des Pins",
    "sg:city":"Saint-Lambert-DE-Lauzon",
    "sg:classifiers":[
        {
            "category":"Building & Trades",
            "subcategory":"Construction",
            "type":"Services"
        }
    ],
    "sg:phone":"+1 418 889 8866",
    "sg:postcode":"G0S 2W0",
    "sg:province":"QC",
    "sg:tags":[
        "general",
        "contractor"
    ],
    "wof:name":"Constructions Den Mer Inc",
    "wof:placetype":"venue"
},
  "geometry": {"coordinates":[-71.2300491333,46.6132164001],"type":"Point"}
}