{
  "type": "Feature",
  "properties": {
    "addr:full":"1813 2 Ave Cold Lake AB T9M 1E3",
    "addr:housenumber":"1813",
    "addr:postcode":"t9m 1e3",
    "addr:street":"2 Ave",
    "iso:country":"CA",
    "sg:address":"1813 2 Ave",
    "sg:city":"Cold Lake",
    "sg:classifiers":[
        {
            "category":"Building & Trades",
            "subcategory":"Construction",
            "type":"Services"
        }
    ],
    "sg:phone":"+1 780 639 3224",
    "sg:postcode":"T9M 1E3",
    "sg:province":"AB",
    "sg:tags":[
        "concrete",
        "contractor"
    ],
    "wof:name":"Clearcut Construction",
    "wof:placetype":"venue"
},
  "geometry": {"coordinates":[-110.186279,54.470291],"type":"Point"}
}