{
  "type": "Feature",
  "properties": {
    "addr:full":"229 Rang Charlotte Saint-Liboire QC J0H 1R0",
    "addr:housenumber":"229",
    "addr:postcode":"j0h 1r0",
    "addr:street":"Rang Charlotte",
    "iso:country":"CA",
    "sg:address":"229 Rang Charlotte",
    "sg:city":"Saint-Liboire",
    "sg:classifiers":[
        {
            "category":"Building & Trades",
            "subcategory":"Equipment Rental",
            "type":"Services"
        }
    ],
    "sg:phone":"+1 450 793 4710",
    "sg:postcode":"J0H 1R0",
    "sg:province":"QC",
    "sg:tags":[
        "excavating",
        "contractor"
    ],
    "wof:name":"Drainage Lazure Inc",
    "wof:placetype":"venue"
},
  "geometry": {"coordinates":[-72.728241,45.665638],"type":"Point"}
}