{
  "type": "Feature",
  "properties": {
    "addr:full":"73 Montee Gagnon Bois-Des-Filion QC J6Z 4H3",
    "addr:housenumber":"73",
    "addr:postcode":"j6z 4h3",
    "addr:street":"Montee Gagnon",
    "iso:country":"CA",
    "sg:address":"73 Montee Gagnon",
    "sg:city":"Bois-Des-Filion",
    "sg:classifiers":[
        {
            "category":"Autos & Motor Vehicles",
            "subcategory":"Auto Supplies",
            "type":"Retail Goods"
        }
    ],
    "sg:phone":"+1 450 965 4284",
    "sg:postcode":"J6Z 4H3",
    "sg:province":"QC",
    "sg:tags":[
        "automobile",
        "parts"
    ],
    "wof:name":"Pieces D'Auto Rj",
    "wof:placetype":"venue"
},
  "geometry": {"coordinates":[-73.7614440918,45.6656112671],"type":"Point"}
}