{
  "type": "Feature",
  "properties": {
    "iso:country":"CA",
    "sg:address":"5017 42 St",
    "sg:city":"St Paul",
    "sg:classifiers":[
        {
            "category":"Shopping",
            "subcategory":"Clothing, Apparel, & Fashions",
            "type":"Retail Goods"
        }
    ],
    "sg:phone":"+1 780 645 3378",
    "sg:postcode":"T0A 3A2",
    "sg:province":"AB",
    "wof:name":"Fields Stores",
    "wof:placetype":"venue"
},
  "geometry": {"coordinates":[-111.27318572999999,53.9923248291],"type":"Point"}
}