{
  "type": "Feature",
  "properties": {
    "addr:full":"790 Tennyson Ave Trail BC V1R 2E3",
    "addr:housenumber":"790",
    "addr:postcode":"bc v1r 2e3",
    "addr:street":"Tennyson Ave Trail",
    "iso:country":"CA",
    "sg:address":"790 Tennyson Ave",
    "sg:city":"Trail",
    "sg:classifiers":[
        {
            "category":"Shopping",
            "type":"Retail Goods"
        }
    ],
    "sg:phone":"+1 250 368 6865",
    "sg:postcode":"V1R 2E3",
    "sg:province":"BC",
    "sg:tags":[
        "spa",
        "hot",
        "tub"
    ],
    "wof:name":"Lyle's Hot Tubs Inc",
    "wof:placetype":"venue"
},
  "geometry": {"coordinates":[-117.71221199999999,49.096451],"type":"Point"}
}