{
  "type": "Feature",
  "properties": {
    "iso:country":"CA",
    "sg:address":"350 Allegretto Cres",
    "sg:city":"Saskatoon",
    "sg:classifiers":[
        {
            "category":"Wholesale",
            "subcategory":"Machinery & Supplies",
            "type":"Manufacturing & Wholesale Goods"
        }
    ],
    "sg:phone":"+1 306 242 3666",
    "sg:postcode":"S7K 6R5",
    "sg:province":"SK",
    "sg:tags":[
        "equipment",
        "welding"
    ],
    "wof:name":"E T Welding Supplies Ltd",
    "wof:placetype":"venue"
},
  "geometry": {"coordinates":[-106.637451172,52.176158905],"type":"Point"}
}