{
  "type": "Feature",
  "properties": {
    "addr:full":"28 Westlake Dr Spruce Grove AB T7X 1S5",
    "addr:housenumber":"28",
    "addr:postcode":"t7x 1s5",
    "addr:street":"Westlake Dr",
    "iso:country":"CA",
    "sg:address":"28 Westlake Dr",
    "sg:city":"Spruce Grove",
    "sg:classifiers":[
        {
            "category":"Wholesale",
            "subcategory":"Photographic Equipment",
            "type":"Manufacturing & Wholesale Goods"
        }
    ],
    "sg:phone":"+1 780 960 3522",
    "sg:postcode":"T7X 1S5",
    "sg:province":"AB",
    "sg:tags":[
        "audio"
    ],
    "wof:name":"Tandberg Canada Inc",
    "wof:placetype":"venue"
},
  "geometry": {"coordinates":[-113.92377500000001,53.546303],"type":"Point"}
}