{
  "type": "Feature",
  "properties": {
    "iso:country":"CA",
    "sg:address":"299 Dunraven Rd",
    "sg:city":"L'Ile-Du-Grand-Calumet",
    "sg:classifiers":[
        {
            "category":"Wholesale",
            "subcategory":"Construction Materials",
            "type":"Manufacturing & Wholesale Goods"
        }
    ],
    "sg:phone":"+1 819 648 2555",
    "sg:postcode":"J0X 1J0",
    "sg:province":"QC",
    "sg:tags":[
        "fence"
    ],
    "wof:name":"Dumouchel Fence Inc",
    "wof:placetype":"venue"
},
  "geometry": {"coordinates":[-76.60981750489999,45.7190628052],"type":"Point"}
}