{
  "type": "Feature",
  "properties": {
    "iso:country":"CA",
    "sg:city":"Montmagny",
    "sg:classifiers":[
        {
            "category":"Real Estate",
            "subcategory":"Real Estate Agent",
            "type":"Services"
        }
    ],
    "sg:phone":"+1 418 248 7006",
    "sg:postcode":"G5V 1B6",
    "sg:province":"QC",
    "sg:tags":[
        "loan",
        "appraiser"
    ],
    "wof:name":"Evalim Inc",
    "wof:placetype":"venue"
},
  "geometry": {"coordinates":[-70.563591,46.981754],"type":"Point"}
}