{
  "type": "Feature",
  "properties": {
    "addr:full":"10 Toronto St South River ON P0A 1X0",
    "addr:housenumber":"10",
    "addr:postcode":"p0a 1x0",
    "addr:street":"Toronto St",
    "iso:country":"CA",
    "sg:address":"10 Toronto St",
    "sg:city":"South River",
    "sg:classifiers":[
        {
            "category":"Shopping",
            "subcategory":"Crafts & Fabrics",
            "type":"Retail Goods"
        }
    ],
    "sg:phone":"+1 705 386 0388",
    "sg:postcode":"P0A 1X0",
    "sg:province":"ON",
    "sg:tags":[
        "shop"
    ],
    "wof:name":"South River Books & Crafts",
    "wof:placetype":"venue"
},
  "geometry": {"coordinates":[-79.37705200000001,45.839775],"type":"Point"}
}