{
  "type": "Feature",
  "properties": {
    "addr:full":"300 18th St N Brandon MB R7A 7P3",
    "addr:housenumber":"300",
    "addr:postcode":"r7a 7p3",
    "addr:street":"18Th St N",
    "iso:country":"CA",
    "sg:address":"300 18th St N",
    "sg:city":"Brandon",
    "sg:classifiers":[
        {
            "category":"Travel",
            "subcategory":"Hotels & Motels",
            "type":"Entertainment"
        }
    ],
    "sg:phone":"+1 204 728 7230",
    "sg:postcode":"R7A 7P3",
    "sg:province":"MB",
    "wof:name":"Rodeway Inn Motel",
    "wof:placetype":"venue"
},
  "geometry": {"coordinates":[-99.962082,49.855652],"type":"Point"}
}