{
  "type": "Feature",
  "properties": {
    "addr:full":"140 Algonquin Blvd W Timmins ON P4N 8M2",
    "addr:housenumber":"140",
    "addr:postcode":"p4n 8m2",
    "addr:street":"Algonquin Blvd W",
    "iso:country":"CA",
    "sg:address":"140 Algonquin Blvd W",
    "sg:city":"Timmins",
    "sg:classifiers":[
        {
            "category":"Food & Beverages",
            "subcategory":"Groceries & Convenience Stores",
            "type":"Retail Goods"
        }
    ],
    "sg:phone":"+1 705 268 5481",
    "sg:postcode":"P4N 8M2",
    "sg:province":"ON",
    "sg:tags":[
        "grocer"
    ],
    "wof:name":"A & P Food Stores Ltd",
    "wof:placetype":"venue"
},
  "geometry": {"coordinates":[-81.339653,48.476223],"type":"Point"}
}