{
  "type": "Feature",
  "properties": {
    "iso:country":"CA",
    "sg:address":"566 College St",
    "sg:city":"Toronto",
    "sg:classifiers":[
        {
            "category":"Shopping",
            "subcategory":"Pharmacy",
            "type":"Retail Goods"
        }
    ],
    "sg:phone":"+1 416 924 2134",
    "sg:postcode":"M6G 1B1",
    "sg:province":"ON",
    "wof:name":"Liberman's Drug Store",
    "wof:placetype":"venue"
},
  "geometry": {"coordinates":[-79.412483,43.655605],"type":"Point"}
}