{
  "type": "Feature",
  "properties": {
    "addr:full":"6579 Dalrymple Way NW Calgary AB T3A 1S1",
    "addr:housenumber":"6579",
    "addr:postcode":"t3a 1s1",
    "addr:street":"Dalrymple Way Nw",
    "iso:country":"CA",
    "sg:address":"6579 Dalrymple Way NW",
    "sg:city":"Calgary",
    "sg:classifiers":[
        {
            "category":"Building & Trades",
            "subcategory":"Plumbing",
            "type":"Services"
        }
    ],
    "sg:phone":"+1 403 288 5600",
    "sg:postcode":"T3A 1S1",
    "sg:province":"AB",
    "sg:tags":[
        "heating",
        "contractor"
    ],
    "wof:name":"Abel Sheet Metal Ltd",
    "wof:placetype":"venue"
},
  "geometry": {"coordinates":[-114.163651,51.111969],"type":"Point"}
}