{
  "type": "Feature",
  "properties": {
    "iso:country":"CA",
    "sg:city":"Mississauga",
    "sg:classifiers":[
        {
            "category":"Shopping",
            "subcategory":"Gifts & Souvenirs",
            "type":"Retail Goods"
        }
    ],
    "sg:phone":"+1 905 822 5914",
    "sg:postcode":"L5K 1T9",
    "sg:province":"ON",
    "sg:tags":[
        "cards",
        "shop",
        "greeting"
    ],
    "wof:name":"Hallmark Cards",
    "wof:placetype":"venue"
},
  "geometry": {"coordinates":[-79.654442,43.529037],"type":"Point"}
}