{
  "type": "Feature",
  "properties": {
    "addr:full":"129 Moran Pl Lillooet BC V0K 1V0",
    "addr:housenumber":"129",
    "addr:postcode":"v0k 1v0",
    "addr:street":"Moran Pl",
    "iso:country":"CA",
    "sg:address":"129 Moran Pl",
    "sg:city":"Lillooet",
    "sg:classifiers":[
        {
            "category":"Freight",
            "type":"Transportation"
        }
    ],
    "sg:phone":"+1 250 256 4828",
    "sg:postcode":"V0K 1V0",
    "sg:province":"BC",
    "sg:tags":[
        "trucking"
    ],
    "wof:name":"HI-Ro Enterprise Ltd",
    "wof:placetype":"venue"
},
  "geometry": {"coordinates":[-121.924744,50.704269],"type":"Point"}
}