{
  "type": "Feature",
  "properties": {
    "addr:full":"921 2nd Ave E Owen Sound ON N4K 2H5",
    "addr:housenumber":"921",
    "addr:postcode":"n4k 2h5",
    "addr:street":"2Nd Ave E",
    "iso:country":"CA",
    "sg:address":"921 2nd Ave E",
    "sg:city":"Owen Sound",
    "sg:classifiers":[
        {
            "category":"Shopping",
            "subcategory":"Jewelry",
            "type":"Retail Goods"
        }
    ],
    "sg:phone":"+1 519 376 5536",
    "sg:postcode":"N4K 2H5",
    "sg:province":"ON",
    "sg:tags":[
        "jeweler"
    ],
    "wof:name":"Buzza Brothers Jewellers",
    "wof:placetype":"venue"
},
  "geometry": {"coordinates":[-80.942757,44.566357],"type":"Point"}
}