{
  "type": "Feature",
  "properties": {
    "addr:full":"6411 Carlton Ave Niagara Falls ON L2G 5K1",
    "addr:housenumber":"6411",
    "addr:postcode":"l2g 5k1",
    "addr:street":"Carlton Ave",
    "iso:country":"CA",
    "sg:address":"6411 Carlton Ave",
    "sg:city":"Niagara Falls",
    "sg:classifiers":[
        {
            "category":"Retail",
            "subcategory":"Repair Shop",
            "type":"Services"
        }
    ],
    "sg:phone":"+1 905 371 3644",
    "sg:postcode":"L2G 5K1",
    "sg:province":"ON",
    "sg:tags":[
        "appliance"
    ],
    "wof:name":"Brian's Low Cost Repair",
    "wof:placetype":"venue"
},
  "geometry": {"coordinates":[-79.10581999999999,43.082249],"type":"Point"}
}