{
  "type": "Feature",
  "properties": {
    "addr:full":"Hwy 13 & Hwy 36 Killam AB T0B 2L0",
    "addr:postcode":"t0b 2l0",
    "addr:street":"Hwy 13 & Hwy 36",
    "iso:country":"CA",
    "sg:address":"Hwy 13 & Hwy 36",
    "sg:city":"Killam",
    "sg:classifiers":[
        {
            "category":"Wholesale",
            "subcategory":"Farm Supplies",
            "type":"Manufacturing & Wholesale Goods"
        }
    ],
    "sg:phone":"+1 780 385 2426",
    "sg:postcode":"T0B 2L0",
    "sg:province":"AB",
    "sg:tags":[
        "chemical",
        "agricultural",
        "fertilizer"
    ],
    "wof:name":"Agricore United",
    "wof:placetype":"venue"
},
  "geometry": {"coordinates":[-111.842072,52.792191],"type":"Point"}
}