{
  "type": "Feature",
  "properties": {
    "addr:full":"Toronto ON M5A 1M3",
    "addr:postcode":"m5a 1m3",
    "iso:country":"CA",
    "sg:city":"Toronto",
    "sg:classifiers":[
        {
            "category":"Manufacturing",
            "subcategory":"Metals",
            "type":"Manufacturing & Wholesale Goods"
        }
    ],
    "sg:phone":"+1 416 861 0544",
    "sg:postcode":"M5A 1M3",
    "sg:province":"ON",
    "sg:tags":[
        "picture",
        "frame"
    ],
    "wof:name":"Custom Arts Concepts Ltd",
    "wof:placetype":"venue"
},
  "geometry": {"coordinates":[-79.35947400000001,43.654823],"type":"Point"}
}