{
  "type": "Feature",
  "properties": {
    "iso:country":"CA",
    "sg:city":"Alonsa",
    "sg:classifiers":[
        {
            "category":"Restaurant",
            "type":"Food & Drink"
        }
    ],
    "sg:phone":"+1 204 767 2090",
    "sg:postcode":"R0H 0A0",
    "sg:province":"MB",
    "wof:name":"Rancher's Bar & Grill",
    "wof:placetype":"venue"
},
  "geometry": {"coordinates":[-99.0846710205,50.8791427612],"type":"Point"}
}