{
  "type": "Feature",
  "properties": {
    "iso:country":"CA",
    "sg:address":"261 Christina St N",
    "sg:city":"Sarnia",
    "sg:classifiers":[
        {
            "category":"Organizations",
            "subcategory":"Religious Organization",
            "type":"Services"
        }
    ],
    "sg:phone":"+1 519 332 2662",
    "sg:postcode":"N7T 5V4",
    "sg:province":"ON",
    "sg:tags":[
        "church"
    ],
    "wof:name":"St Andrew's Presbyterian Chr",
    "wof:placetype":"venue"
},
  "geometry": {"coordinates":[-82.4063491821,42.975025177],"type":"Point"}
}