{
  "type": "Feature",
  "properties": {
    "addr:full":"279 Boul Rosemere Rosemere QC J7A 2T1",
    "addr:housenumber":"279",
    "addr:postcode":"j7a 2t1",
    "addr:street":"Boul Rosemere Rosemere",
    "iso:country":"CA",
    "sg:address":"279 Boul Rosemere",
    "sg:city":"Rosemere",
    "sg:classifiers":[
        {
            "category":"Professional",
            "subcategory":"Employment Agencies",
            "type":"Services"
        }
    ],
    "sg:phone":"+1 450 965 1441",
    "sg:postcode":"J7A 2T1",
    "sg:province":"QC",
    "sg:tags":[
        "consultant",
        "search",
        "executive"
    ],
    "wof:name":"Lacoste Recherche DE Cadres",
    "wof:placetype":"venue"
},
  "geometry": {"coordinates":[-73.799751,45.636585],"type":"Point"}
}