{
  "type": "Feature",
  "properties": {
    "addr:full":"Sudbury ON P3A 3T4",
    "addr:postcode":"p3a 3t4",
    "iso:country":"CA",
    "sg:city":"Sudbury",
    "sg:classifiers":[
        {
            "category":"Communications",
            "subcategory":"Radio Station",
            "type":"Services"
        }
    ],
    "sg:phone":"+1 705 560 8323",
    "sg:postcode":"P3A 3T4",
    "sg:province":"ON",
    "sg:tags":[
        "company",
        "broadcasting"
    ],
    "wof:name":"Chyc",
    "wof:placetype":"venue"
},
  "geometry": {"coordinates":[-80.94435900000001,46.507595],"type":"Point"}
}