{
  "type": "Feature",
  "properties": {
    "addr:full":"1647 Rue Davidson Montreal QC H1W 2Y4",
    "addr:housenumber":"1647",
    "addr:postcode":"h1w 2y4",
    "addr:street":"Rue Davidson",
    "iso:country":"CA",
    "sg:address":"1647 Rue Davidson",
    "sg:city":"Montreal",
    "sg:classifiers":[
        {
            "category":"Building & Trades",
            "subcategory":"Landscaping Services",
            "type":"Services"
        }
    ],
    "sg:phone":"+1 514 524 0220",
    "sg:postcode":"H1W 2Y4",
    "sg:province":"QC",
    "sg:tags":[
        "landscape",
        "contractor"
    ],
    "wof:name":"Jardins DE Capucinne",
    "wof:placetype":"venue"
},
  "geometry": {"coordinates":[-73.54322814939999,45.5422668457],"type":"Point"}
}