{
  "type": "Feature",
  "properties": {
    "addr:full":"8325 Rue Notre-Dame E Montreal QC H1L 3L2",
    "addr:housenumber":"8325",
    "addr:postcode":"h1l 3l2",
    "addr:street":"Rue Notre-Dame E",
    "iso:country":"CA",
    "sg:address":"8325 Rue Notre-Dame E",
    "sg:city":"Montreal",
    "sg:classifiers":[
        {
            "category":"Shopping",
            "subcategory":"Pharmacy",
            "type":"Retail Goods"
        }
    ],
    "sg:phone":"+1 514 353 2010",
    "sg:postcode":"H1L 3L2",
    "sg:province":"QC",
    "wof:name":"Uniprix",
    "wof:placetype":"venue"
},
  "geometry": {"coordinates":[-73.51122283940001,45.5938110352],"type":"Point"}
}