{
  "type": "Feature",
  "properties": {
    "addr:full":"342 Rue Saint-Francois Saint-Germain-DE-Grantham QC J0C 1K0",
    "addr:housenumber":"342",
    "addr:postcode":"j0c 1k0",
    "addr:street":"Rue Saint-Francois",
    "iso:country":"CA",
    "sg:address":"342 Rue Saint-Francois",
    "sg:city":"Saint-Germain-DE-Grantham",
    "sg:classifiers":[
        {
            "category":"Building & Trades",
            "subcategory":"Construction",
            "type":"Services"
        }
    ],
    "sg:phone":"+1 819 395 4363",
    "sg:postcode":"J0C 1K0",
    "sg:province":"QC",
    "sg:tags":[
        "general",
        "contractor"
    ],
    "wof:name":"Construction Bi-Bo Inc",
    "wof:placetype":"venue"
},
  "geometry": {"coordinates":[-72.572029,45.840248],"type":"Point"}
}