{
  "type": "Feature",
  "properties": {
    "iso:country":"CA",
    "sg:address":"126 Limestone Cres",
    "sg:city":"North York",
    "sg:classifiers":[
        {
            "category":"Professional",
            "subcategory":"Printing & Photocopies",
            "type":"Services"
        }
    ],
    "sg:phone":"+1 416 736 7890",
    "sg:postcode":"M3J 2S4",
    "sg:province":"ON",
    "sg:tags":[
        "machine",
        "duplicating",
        "copying"
    ],
    "wof:name":"Atcom Office Solutions Inc",
    "wof:placetype":"venue"
},
  "geometry": {"coordinates":[-79.4881439209,43.7803611755],"type":"Point"}
}