{
  "type": "Feature",
  "properties": {
    "addr:full":"Chapleau ON P0M 1K0",
    "addr:postcode":"p0m 1k0",
    "iso:country":"CA",
    "sg:city":"Chapleau",
    "sg:classifiers":[
        {
            "category":"Travel",
            "subcategory":"Campground",
            "type":"Entertainment"
        }
    ],
    "sg:phone":"+1 705 864 0201",
    "sg:postcode":"P0M 1K0",
    "sg:province":"ON",
    "sg:tags":[
        "camp",
        "fishing"
    ],
    "wof:name":"Five Mile Lake Lodge",
    "wof:placetype":"venue"
},
  "geometry": {"coordinates":[-83.4048995972,47.8424758911],"type":"Point"}
}