{
  "type": "Feature",
  "properties": {
    "addr:full":"29 Fallingbrook St Whitby ON L1R 1M7",
    "addr:housenumber":"29",
    "addr:postcode":"l1r 1m7",
    "addr:street":"Fallingbrook St",
    "iso:country":"CA",
    "sg:address":"29 Fallingbrook St",
    "sg:city":"Whitby",
    "sg:classifiers":[
        {
            "category":"Social Services",
            "subcategory":"Child Care",
            "type":"Services"
        }
    ],
    "sg:phone":"+1 905 430 1898",
    "sg:postcode":"L1R 1M7",
    "sg:province":"ON",
    "wof:name":"Schoolhouse Playcare Ctr",
    "wof:placetype":"venue"
},
  "geometry": {"coordinates":[-78.93478399999999,43.904453],"type":"Point"}
}