{
  "type": "Feature",
  "properties": {
    "addr:full":"Surrey BC V3S 1X7",
    "addr:postcode":"v3s 1x7",
    "iso:country":"CA",
    "sg:city":"Surrey",
    "sg:classifiers":[
        {
            "category":"Wholesale",
            "subcategory":"Jewelry",
            "type":"Manufacturing & Wholesale Goods"
        }
    ],
    "sg:phone":"+1 604 590 4060",
    "sg:postcode":"V3S 1X7",
    "sg:province":"BC",
    "sg:tags":[
        "platinum",
        "silver",
        "gold"
    ],
    "wof:name":"Rand Refining Ltd",
    "wof:placetype":"venue"
},
  "geometry": {"coordinates":[-122.814453125,49.1189689636],"type":"Point"}
}