{
  "type": "Feature",
  "properties": {
    "addr:full":"3490 21E Av Laval QC H7R 3G7",
    "addr:housenumber":"3490",
    "addr:postcode":"h7r 3g7",
    "addr:street":"21E Av",
    "iso:country":"CA",
    "sg:address":"3490 21E Av",
    "sg:city":"Laval",
    "sg:classifiers":[
        {
            "category":"Building & Trades",
            "subcategory":"Construction",
            "type":"Services"
        }
    ],
    "sg:phone":"+1 450 962 0823",
    "sg:postcode":"H7R 3G7",
    "sg:province":"QC",
    "sg:tags":[
        "concrete",
        "contractor"
    ],
    "wof:name":"Pro-Solage Inc",
    "wof:placetype":"venue"
},
  "geometry": {"coordinates":[-73.87455,45.544243],"type":"Point"}
}