{
  "type": "Feature",
  "properties": {
    "addr:full":"4933 Boul Royal Shawinigan QC G9N 8G5",
    "addr:housenumber":"4933",
    "addr:postcode":"g9n 8g5",
    "addr:street":"Boul Royal",
    "iso:country":"CA",
    "sg:address":"4933 Boul Royal",
    "sg:city":"Shawinigan",
    "sg:classifiers":[
        {
            "category":"Home & Garden",
            "subcategory":"Household Appliances",
            "type":"Retail Goods"
        }
    ],
    "sg:phone":"+1 819 539 8315",
    "sg:postcode":"G9N 8G5",
    "sg:province":"QC",
    "wof:name":"Champagne Pieces Electromenage",
    "wof:placetype":"venue"
},
  "geometry": {"coordinates":[-72.7275238037,46.5688056946],"type":"Point"}
}