{
  "type": "Feature",
  "properties": {
    "addr:full":"137 W Stewart St # A Vanderhoof BC V0J 3A0",
    "addr:housenumber":"137",
    "addr:postcode":"v0j 3a0",
    "addr:street":"W Stewart St # A",
    "iso:country":"CA",
    "sg:address":"137 W Stewart St # A",
    "sg:city":"Vanderhoof",
    "sg:classifiers":[
        {
            "category":"Restaurant",
            "type":"Food & Drink"
        }
    ],
    "sg:phone":"+1 250 567 5154",
    "sg:postcode":"V0J 3A0",
    "sg:province":"BC",
    "sg:tags":[
        "pizza"
    ],
    "wof:name":"Pizza Man Pizza",
    "wof:placetype":"venue"
},
  "geometry": {"coordinates":[-124.010345,54.016014],"type":"Point"}
}