{
  "type": "Feature",
  "properties": {
    "iso:country":"CA",
    "sg:city":"Bedeque",
    "sg:classifiers":[
        {
            "category":"Government",
            "subcategory":"Office",
            "type":"Public Place"
        }
    ],
    "sg:phone":"+1 902 887 7382",
    "sg:postcode":"C0B 1C0",
    "sg:province":"PE",
    "wof:name":"P E Access Kinkora",
    "wof:placetype":"venue"
},
  "geometry": {"coordinates":[-63.7250747681,46.3378982544],"type":"Point"}
}