{
  "type": "Feature",
  "properties": {
    "addr:full":"50 John St E Waterloo ON N2J 1E8",
    "addr:housenumber":"50",
    "addr:postcode":"n2j 1e8",
    "addr:street":"John St E",
    "iso:country":"CA",
    "sg:address":"50 John St E",
    "sg:city":"Waterloo",
    "sg:classifiers":[
        {
            "category":"Health Services",
            "subcategory":"Health Practitioner",
            "type":"Services"
        }
    ],
    "sg:phone":"+1 519 742 8589",
    "sg:postcode":"N2J 1E8",
    "sg:province":"ON",
    "sg:tags":[
        "psychologist"
    ],
    "wof:name":"Ross, Christopher PhD",
    "wof:placetype":"venue"
},
  "geometry": {"coordinates":[-80.51546478269999,43.4615364075],"type":"Point"}
}