{
  "type": "Feature",
  "properties": {
    "iso:country":"CA",
    "sg:city":"Grande Prairie",
    "sg:classifiers":[
        {
            "category":"Real Estate",
            "subcategory":"Developer",
            "type":"Services"
        }
    ],
    "sg:phone":"+1 780 532 0510",
    "sg:postcode":"T8V 2V4",
    "sg:province":"AB",
    "sg:tags":[
        "mobile",
        "home"
    ],
    "wof:name":"Silver Pointe Village Inc",
    "wof:placetype":"venue"
},
  "geometry": {"coordinates":[-118.801124573,55.1699523926],"type":"Point"}
}