{
  "type": "Feature",
  "properties": {
    "addr:full":"86 Young St Clearwater BC V0E 1N0",
    "addr:housenumber":"86",
    "addr:postcode":"v0e 1n0",
    "addr:street":"Young St",
    "iso:country":"CA",
    "sg:address":"86 Young St",
    "sg:city":"Clearwater",
    "sg:classifiers":[
        {
            "category":"Personal",
            "subcategory":"Beauty Salon",
            "type":"Services"
        }
    ],
    "sg:phone":"+1 250 674 3320",
    "sg:postcode":"V0E 1N0",
    "sg:province":"BC",
    "wof:name":"Natural Hair",
    "wof:placetype":"venue"
},
  "geometry": {"coordinates":[-120.034820557,51.6509246826],"type":"Point"}
}