{
  "type": "Feature",
  "properties": {
    "addr:full":"1045 Mcnicoll Ave Scarborough ON M1W 3W6",
    "addr:housenumber":"1045",
    "addr:postcode":"m1w 3w6",
    "addr:street":"Mcnicoll Ave",
    "iso:country":"CA",
    "sg:address":"1045 Mcnicoll Ave",
    "sg:city":"Scarborough",
    "sg:classifiers":[
        {
            "category":"Social Services",
            "type":"Services"
        }
    ],
    "sg:phone":"+1 416 750 9885",
    "sg:postcode":"M1W 3W6",
    "sg:province":"ON",
    "sg:tags":[
        "organization",
        "welfare"
    ],
    "wof:name":"Scarborough Support Svc",
    "wof:placetype":"venue"
},
  "geometry": {"coordinates":[-79.33274841310001,43.8038139343],"type":"Point"}
}