{
  "type": "Feature",
  "properties": {
    "iso:country":"CA",
    "sg:address":"16532 111 Ave NW",
    "sg:city":"Edmonton",
    "sg:classifiers":[
        {
            "category":"Wholesale",
            "subcategory":"Machinery & Supplies",
            "type":"Manufacturing & Wholesale Goods"
        }
    ],
    "sg:phone":"+1 780 483 7775",
    "sg:postcode":"T5M 3V8",
    "sg:province":"AB",
    "sg:tags":[
        "bearing"
    ],
    "wof:name":"Commercial Bearing Svc Ltd",
    "wof:placetype":"venue"
},
  "geometry": {"coordinates":[-113.60610199,53.5595321655],"type":"Point"}
}