{
  "type": "Feature",
  "properties": {
    "addr:full":"Winnipeg MB R3B 3H6",
    "addr:postcode":"r3b 3h6",
    "iso:country":"CA",
    "sg:city":"Winnipeg",
    "sg:classifiers":[
        {
            "category":"Food & Beverages",
            "subcategory":"Groceries & Convenience Stores",
            "type":"Retail Goods"
        }
    ],
    "sg:phone":"+1 204 942 8605",
    "sg:postcode":"R3B 3H6",
    "sg:province":"MB",
    "sg:tags":[
        "grocer"
    ],
    "wof:name":"Global Fine Foods",
    "wof:placetype":"venue"
},
  "geometry": {"coordinates":[-97.14814800000001,49.892204],"type":"Point"}
}