{
  "type": "Feature",
  "properties": {
    "addr:full":"NE 8 68 17W Snow Lake MB R0B 1M0",
    "addr:housenumber":"68 17w",
    "addr:postcode":"r0b 1m0",
    "addr:street":"Ne 8;Snow Lake",
    "iso:country":"CA",
    "sg:address":"NE 8 68 17W",
    "sg:city":"Snow Lake",
    "sg:classifiers":[
        {
            "category":"Recreation",
            "type":"Entertainment"
        }
    ],
    "sg:phone":"+1 204 358 2744",
    "sg:postcode":"R0B 1M0",
    "sg:province":"MB",
    "sg:tags":[
        "course",
        "golf"
    ],
    "wof:name":"Snow Lake Golf Club",
    "wof:placetype":"venue"
},
  "geometry": {"coordinates":[-100.015022,54.874523],"type":"Point"}
}