{
  "type": "Feature",
  "properties": {
    "addr:full":"Riverton MB R0C 2R0",
    "addr:postcode":"r0c 2r0",
    "iso:country":"CA",
    "sg:city":"Riverton",
    "sg:classifiers":[
        {
            "category":"Building & Trades",
            "subcategory":"Equipment Rental",
            "type":"Services"
        }
    ],
    "sg:phone":"+1 204 378 5244",
    "sg:postcode":"R0C 2R0",
    "sg:province":"MB",
    "sg:tags":[
        "aircraft",
        "leasing",
        "charter"
    ],
    "wof:name":"Riverton Airways",
    "wof:placetype":"venue"
},
  "geometry": {"coordinates":[-96.96832999999999,50.306469],"type":"Point"}
}