{
  "type": "Feature",
  "properties": {
    "addr:full":"318 Williams Ave Killarney MB R0K 1G0",
    "addr:housenumber":"318",
    "addr:postcode":"r0k 1g0",
    "addr:street":"Williams Ave",
    "iso:country":"CA",
    "sg:address":"318 Williams Ave",
    "sg:city":"Killarney",
    "sg:classifiers":[
        {
            "category":"Education",
            "subcategory":"Library",
            "type":"Public Place"
        }
    ],
    "sg:phone":"+1 204 523 4949",
    "sg:postcode":"R0K 1G0",
    "sg:province":"MB",
    "wof:name":"Lakeland Regional Library",
    "wof:placetype":"venue"
},
  "geometry": {"coordinates":[-99.666946,49.180901],"type":"Point"}
}