{
  "type": "Feature",
  "properties": {
    "addr:full":"219 Rue Saint-Georges Beloeil QC J3G 4N4",
    "addr:housenumber":"219",
    "addr:postcode":"j3g 4n4",
    "addr:street":"Rue Saint-Georges",
    "iso:country":"CA",
    "sg:address":"219 Rue Saint-Georges",
    "sg:city":"Beloeil",
    "sg:classifiers":[
        {
            "category":"Manufacturing",
            "subcategory":"Glass & Minerals",
            "type":"Manufacturing & Wholesale Goods"
        }
    ],
    "sg:phone":"+1 450 467 8611",
    "sg:postcode":"J3G 4N4",
    "sg:province":"QC",
    "sg:tags":[
        "conversion",
        "fiber",
        "van",
        "accessory",
        "truck",
        "fabricator"
    ],
    "wof:name":"Fibrocap Inc",
    "wof:placetype":"venue"
},
  "geometry": {"coordinates":[-73.21556099999999,45.548107],"type":"Point"}
}