{
  "type": "Feature",
  "properties": {
    "iso:country":"CA",
    "sg:address":"4054 Pender St",
    "sg:city":"Burnaby",
    "sg:classifiers":[
        {
            "category":"Professional",
            "subcategory":"Business Services",
            "type":"Services"
        }
    ],
    "sg:phone":"+1 604 434 4433",
    "sg:postcode":"V5C 2L8",
    "sg:province":"BC",
    "sg:tags":[
        "convention",
        "meeting",
        "facility"
    ],
    "wof:name":"Can-West Display Svc Ltd",
    "wof:placetype":"venue"
},
  "geometry": {"coordinates":[-123.015060425,49.2801017761],"type":"Point"}
}