{
  "type": "Feature",
  "properties": {
    "addr:full":"885 Main St W Listowel ON N4W 1B4",
    "addr:housenumber":"885",
    "addr:postcode":"n4w 1b4",
    "addr:street":"Main St W",
    "iso:country":"CA",
    "sg:address":"885 Main St W",
    "sg:city":"Listowel",
    "sg:classifiers":[
        {
            "category":"Freight",
            "type":"Transportation"
        }
    ],
    "sg:phone":"+1 519 291 4700",
    "sg:postcode":"N4W 1B4",
    "sg:province":"ON",
    "sg:tags":[
        "trucking"
    ],
    "wof:name":"Manitoulin Transport Inc",
    "wof:placetype":"venue"
},
  "geometry": {"coordinates":[-80.9641494751,43.7362327576],"type":"Point"}
}