{
  "type": "Feature",
  "properties": {
    "addr:full":"Farm Paradise Hill SK S0M 2G0",
    "addr:postcode":"s0m 2g0",
    "addr:street":"Hill",
    "iso:country":"CA",
    "sg:address":"Farm",
    "sg:city":"Paradise Hill",
    "sg:classifiers":[
        {
            "category":"Wholesale",
            "subcategory":"Construction Materials",
            "type":"Manufacturing & Wholesale Goods"
        }
    ],
    "sg:phone":"+1 306 344 4891",
    "sg:postcode":"S0M 2G0",
    "sg:province":"SK",
    "sg:tags":[
        "fence"
    ],
    "wof:name":"Hardes Fencing",
    "wof:placetype":"venue"
},
  "geometry": {"coordinates":[-109.45829000000001,53.539154],"type":"Point"}
}