{
  "type": "Feature",
  "properties": {
    "addr:full":"Winnipeg MB R3K 1G4",
    "addr:postcode":"r3k 1g4",
    "iso:country":"CA",
    "sg:city":"Winnipeg",
    "sg:classifiers":[
        {
            "category":"Real Estate",
            "subcategory":"Real Estate Operator",
            "type":"Services"
        }
    ],
    "sg:phone":"+1 204 832 5140",
    "sg:postcode":"R3K 1G4",
    "sg:province":"MB",
    "sg:tags":[
        "condominium"
    ],
    "wof:name":"Village West",
    "wof:placetype":"venue"
},
  "geometry": {"coordinates":[-97.293221,49.877644],"type":"Point"}
}