{
  "type": "Feature",
  "properties": {
    "addr:full":"295 Bridge Dr W Lethbridge AB T1J 4S5",
    "addr:housenumber":"295",
    "addr:postcode":"t1j 4s5",
    "addr:street":"Bridge Dr W",
    "iso:country":"CA",
    "sg:address":"295 Bridge Dr W",
    "sg:city":"Lethbridge",
    "sg:classifiers":[
        {
            "category":"Building & Trades",
            "subcategory":"Construction",
            "type":"Services"
        }
    ],
    "sg:phone":"+1 403 381 6452",
    "sg:postcode":"T1J 4S5",
    "sg:province":"AB",
    "sg:tags":[
        "general",
        "contractor"
    ],
    "wof:name":"Willow Creek Sand & Gravel Ltd",
    "wof:placetype":"venue"
},
  "geometry": {"coordinates":[-112.873199,49.705582],"type":"Point"}
}