{
  "type": "Feature",
  "properties": {
    "addr:full":"Hwy 21 S Port Elgin ON N0H 2C0",
    "addr:postcode":"n0h 2c0",
    "addr:street":"Hwy 21 S",
    "iso:country":"CA",
    "sg:address":"Hwy 21 S",
    "sg:city":"Port Elgin",
    "sg:classifiers":[
        {
            "category":"Travel",
            "subcategory":"Hotels & Motels",
            "type":"Entertainment"
        }
    ],
    "sg:phone":"+1 519 832 2058",
    "sg:postcode":"N0H 2C0",
    "sg:province":"ON",
    "wof:name":"Port Elgin Super 8 Motel",
    "wof:placetype":"venue"
},
  "geometry": {"coordinates":[-81.390114,44.434662],"type":"Point"}
}