{
  "type": "Feature",
  "properties": {
    "addr:full":"211 Victoria Ave Belleville ON K8N 2C2",
    "addr:housenumber":"211",
    "addr:postcode":"k8n 2c2",
    "addr:street":"Victoria Ave",
    "iso:country":"CA",
    "sg:address":"211 Victoria Ave",
    "sg:city":"Belleville",
    "sg:classifiers":[
        {
            "category":"Organizations",
            "subcategory":"Religious Organization",
            "type":"Services"
        }
    ],
    "sg:phone":"+1 613 962 1433",
    "sg:postcode":"K8N 2C2",
    "sg:province":"ON",
    "sg:tags":[
        "synagogue"
    ],
    "wof:name":"Sons of Jacob Congregation",
    "wof:placetype":"venue"
},
  "geometry": {"coordinates":[-77.3709564209,44.1696891785],"type":"Point"}
}