{
  "type": "Feature",
  "properties": {
    "iso:country":"CA",
    "sg:address":"12811 96 Ave",
    "sg:city":"Surrey",
    "sg:classifiers":[
        {
            "category":"Cinema",
            "subcategory":"Movie Rental",
            "type":"Entertainment"
        }
    ],
    "sg:phone":"+1 604 585 1029",
    "sg:postcode":"V3V 6V9",
    "sg:province":"BC",
    "sg:tags":[
        "leasing",
        "video",
        "disc",
        "tape"
    ],
    "wof:name":"Ten To Nine Video Ltd",
    "wof:placetype":"venue"
},
  "geometry": {"coordinates":[-122.867393494,49.1773223877],"type":"Point"}
}