{
  "type": "Feature",
  "properties": {
    "addr:full":"530 Av Brochu Sept-Iles QC G4R 2X3",
    "addr:postcode":"g4r 2x3",
    "addr:street":"530 Av Brochu Sept-Iles",
    "iso:country":"CA",
    "sg:address":"530 Av Brochu",
    "sg:city":"Sept-Iles",
    "sg:classifiers":[
        {
            "category":"Education",
            "subcategory":"School",
            "type":"Public Place"
        }
    ],
    "sg:phone":"+1 418 968 9804",
    "sg:postcode":"G4R 2X3",
    "sg:province":"QC",
    "wof:name":"Eastern Shores School Board",
    "wof:placetype":"venue"
},
  "geometry": {"coordinates":[-66.38763400000001,50.208382],"type":"Point"}
}