{
  "type": "Feature",
  "properties": {
    "addr:full":"1358 Cornwall St Regina SK S4R 2H5",
    "addr:housenumber":"1358",
    "addr:postcode":"s4r 2h5",
    "addr:street":"Cornwall St",
    "iso:country":"CA",
    "sg:address":"1358 Cornwall St",
    "sg:city":"Regina",
    "sg:classifiers":[
        {
            "category":"Shopping",
            "subcategory":"Stationery & Office Supplies",
            "type":"Retail Goods"
        }
    ],
    "sg:phone":"+1 306 522 2856",
    "sg:postcode":"S4R 2H5",
    "sg:province":"SK",
    "sg:tags":[
        "rubber",
        "stamp",
        "marking",
        "devices",
        "plastic"
    ],
    "wof:name":"O K Marking Devices Ltd",
    "wof:placetype":"venue"
},
  "geometry": {"coordinates":[-104.61247299999999,50.457409],"type":"Point"}
}