{
  "type": "Feature",
  "properties": {
    "addr:full":"134 Felbrigg Ave North York ON M5M 2M5",
    "addr:housenumber":"134",
    "addr:postcode":"m5m 2m5",
    "addr:street":"Felbrigg Ave",
    "iso:country":"CA",
    "sg:address":"134 Felbrigg Ave",
    "sg:city":"North York",
    "sg:classifiers":[
        {
            "category":"Retail",
            "subcategory":"Animal Services",
            "type":"Services"
        }
    ],
    "sg:phone":"+1 416 932 0181",
    "sg:postcode":"M5M 2M5",
    "sg:province":"ON",
    "sg:tags":[
        "pet",
        "grooming",
        "washing"
    ],
    "wof:name":"Chien Elegant",
    "wof:placetype":"venue"
},
  "geometry": {"coordinates":[-79.418167,43.734589],"type":"Point"}
}