{
  "type": "Feature",
  "properties": {
    "addr:full":"7340 Sidaway Rd Richmond BC V6W 1B8",
    "addr:housenumber":"7340",
    "addr:postcode":"v6w 1b8",
    "addr:street":"Sidaway Rd",
    "iso:country":"CA",
    "sg:address":"7340 Sidaway Rd",
    "sg:city":"Richmond",
    "sg:classifiers":[
        {
            "category":"Organizations",
            "subcategory":"Community Association",
            "type":"Services"
        }
    ],
    "sg:phone":"+1 604 278 0832",
    "sg:postcode":"V6W 1B8",
    "sg:province":"BC",
    "sg:tags":[
        "club"
    ],
    "wof:name":"Vancouver Gun Club",
    "wof:placetype":"venue"
},
  "geometry": {"coordinates":[-123.08029174799999,49.1607704163],"type":"Point"}
}