{
  "type": "Feature",
  "properties": {
    "iso:country":"CA",
    "sg:address":"1817 Fremont Rd",
    "sg:city":"Nanaimo",
    "sg:classifiers":[
        {
            "category":"Home & Garden",
            "subcategory":"Building Materials",
            "type":"Retail Goods"
        }
    ],
    "sg:phone":"+1 250 758 1985",
    "sg:postcode":"V9S 3H3",
    "sg:province":"BC",
    "sg:tags":[
        "glass",
        "window",
        "plate"
    ],
    "wof:name":"Hub City Glass Ltd",
    "wof:placetype":"venue"
},
  "geometry": {"coordinates":[-123.981925964,49.1938667297],"type":"Point"}
}