{
  "type": "Feature",
  "properties": {
    "addr:full":"26 Forbes St Cambridge ON N3C 2E2",
    "addr:housenumber":"26",
    "addr:postcode":"n3c 2e2",
    "addr:street":"Forbes St",
    "iso:country":"CA",
    "sg:address":"26 Forbes St",
    "sg:city":"Cambridge",
    "sg:classifiers":[
        {
            "category":"Health Services",
            "subcategory":"Doctor",
            "type":"Services"
        }
    ],
    "sg:phone":"+1 519 658 4615",
    "sg:postcode":"N3C 2E2",
    "sg:province":"ON",
    "sg:tags":[
        "physician",
        "surgeon"
    ],
    "wof:name":"Hespeler Clinic",
    "wof:placetype":"venue"
},
  "geometry": {"coordinates":[-80.307266,43.429951],"type":"Point"}
}