{
  "type": "Feature",
  "properties": {
    "addr:full":"Westmount QC H3Z 2P9",
    "addr:postcode":"h3z 2p9",
    "iso:country":"CA",
    "sg:city":"Westmount",
    "sg:classifiers":[
        {
            "category":"Insurance",
            "subcategory":"Insurance Agent",
            "type":"Services"
        }
    ],
    "sg:phone":"+1 514 867 1703",
    "sg:postcode":"H3Z 2P9",
    "sg:province":"QC",
    "wof:name":"Di Stasio Financial Inc",
    "wof:placetype":"venue"
},
  "geometry": {"coordinates":[-73.5875091553,45.4867591858],"type":"Point"}
}