{
  "type": "Feature",
  "properties": {
    "addr:full":"4025 90 Ave SE Calgary AB T2C 2S5",
    "addr:housenumber":"4025",
    "addr:postcode":"t2c 2s5",
    "addr:street":"90 Ave Se",
    "iso:country":"CA",
    "sg:address":"4025 90 Ave SE",
    "sg:city":"Calgary",
    "sg:classifiers":[
        {
            "category":"Wholesale",
            "subcategory":"Scrap",
            "type":"Manufacturing & Wholesale Goods"
        }
    ],
    "sg:phone":"+1 403 720 5970",
    "sg:postcode":"T2C 2S5",
    "sg:province":"AB",
    "sg:tags":[
        "metal",
        "iron"
    ],
    "wof:name":"Blackfoot Metals Ltd",
    "wof:placetype":"venue"
},
  "geometry": {"coordinates":[-113.98156,50.972187],"type":"Point"}
}