{
  "type": "Feature",
  "properties": {
    "addr:full":"145 Boul Lorrain Gatineau QC J8P 2G1",
    "addr:housenumber":"145",
    "addr:postcode":"j8p 2g1",
    "addr:street":"Boul Lorrain",
    "iso:country":"CA",
    "sg:address":"145 Boul Lorrain",
    "sg:city":"Gatineau",
    "sg:classifiers":[
        {
            "category":"Food & Beverages",
            "subcategory":"Groceries & Convenience Stores",
            "type":"Retail Goods"
        }
    ],
    "sg:phone":"+1 819 663 5533",
    "sg:postcode":"J8P 2G1",
    "sg:province":"QC",
    "sg:tags":[
        "grocer"
    ],
    "wof:name":"Marche Daniel",
    "wof:placetype":"venue"
},
  "geometry": {"coordinates":[-75.608276,45.498375],"type":"Point"}
}