{
  "type": "Feature",
  "properties": {
    "iso:country":"CA",
    "sg:address":"3850 Kimatouche Rd",
    "sg:city":"Kelowna",
    "sg:classifiers":[
        {
            "category":"Building & Trades",
            "subcategory":"Landscaping Services",
            "type":"Services"
        }
    ],
    "sg:phone":"+1 250 861 1058",
    "sg:postcode":"V1W 4E7",
    "sg:province":"BC",
    "sg:tags":[
        "lawn",
        "maintenance",
        "grounds"
    ],
    "wof:name":"Hegion Garden Svc",
    "wof:placetype":"venue"
},
  "geometry": {"coordinates":[-119.394058227,49.841217041],"type":"Point"}
}