{
  "type": "Feature",
  "properties": {
    "addr:full":"62 Rue Des Oblats N Ville-Marie QC J9V 1J6",
    "addr:housenumber":"62",
    "addr:postcode":"j9v 1j6",
    "addr:street":"Rue Des Oblats N",
    "iso:country":"CA",
    "sg:address":"62 Rue Des Oblats N",
    "sg:city":"Ville-Marie",
    "sg:classifiers":[
        {
            "category":"Shopping",
            "subcategory":"Catalog Store",
            "type":"Retail Goods"
        }
    ],
    "sg:phone":"+1 819 629 2343",
    "sg:postcode":"J9V 1J6",
    "sg:province":"QC",
    "sg:tags":[
        "mail",
        "order",
        "internet"
    ],
    "wof:name":"Sears Canada Inc",
    "wof:placetype":"venue"
},
  "geometry": {"coordinates":[-79.436829,47.337719],"type":"Point"}
}