{
  "type": "Feature",
  "properties": {
    "addr:full":"3269 Portage Ave Winnipeg MB R3K 0W6",
    "addr:housenumber":"3269",
    "addr:postcode":"r3k 0w6",
    "addr:street":"Portage Ave",
    "iso:country":"CA",
    "sg:address":"3269 Portage Ave",
    "sg:city":"Winnipeg",
    "sg:classifiers":[
        {
            "category":"Shopping",
            "type":"Retail Goods"
        }
    ],
    "sg:phone":"+1 204 837 4698",
    "sg:postcode":"R3K 0W6",
    "sg:province":"MB",
    "sg:tags":[
        "picture",
        "frame"
    ],
    "wof:name":"Instaframe Galleries",
    "wof:placetype":"venue"
},
  "geometry": {"coordinates":[-97.2928771973,49.8818397522],"type":"Point"}
}