{
  "type": "Feature",
  "properties": {
    "iso:country":"CA",
    "sg:city":"Montreal",
    "sg:classifiers":[
        {
            "category":"Real Estate",
            "subcategory":"Real Estate Agent",
            "type":"Services"
        }
    ],
    "sg:phone":"+1 514 899 0017",
    "sg:postcode":"H1T 2E6",
    "sg:province":"QC",
    "wof:name":"Immeubles Cote & Assoc Inc",
    "wof:placetype":"venue"
},
  "geometry": {"coordinates":[-73.566864,45.568851],"type":"Point"}
}