{
  "type": "Feature",
  "properties": {
    "iso:country":"CA",
    "sg:address":"5674 Vedder Rd",
    "sg:city":"Chilliwack",
    "sg:classifiers":[
        {
            "category":"Home & Garden",
            "subcategory":"Hardware",
            "type":"Retail Goods"
        }
    ],
    "sg:phone":"+1 604 858 5289",
    "sg:postcode":"V2R 3N2",
    "sg:province":"BC",
    "wof:name":"Fortin's Home Hardware",
    "wof:placetype":"venue"
},
  "geometry": {"coordinates":[-121.96065521200001,49.1060600281],"type":"Point"}
}