{
  "type": "Feature",
  "properties": {
    "iso:country":"CA",
    "sg:address":"9475 180 St",
    "sg:city":"Surrey",
    "sg:classifiers":[
        {
            "category":"Home & Garden",
            "subcategory":"Furniture",
            "type":"Retail Goods"
        }
    ],
    "sg:phone":"+1 604 882 1254",
    "sg:postcode":"V4N 3V6",
    "sg:province":"BC",
    "sg:tags":[
        "equipment",
        "kitchen",
        "cabinet"
    ],
    "wof:name":"Zanrosso Manufacturing Ltd",
    "wof:placetype":"venue"
},
  "geometry": {"coordinates":[-122.72382354699999,49.1751785278],"type":"Point"}
}