{
  "type": "Feature",
  "properties": {
    "addr:full":"12917 53 St NW Edmonton AB T5A 2E7",
    "addr:housenumber":"12917",
    "addr:postcode":"t5a 2e7",
    "addr:street":"53 St Nw",
    "iso:country":"CA",
    "sg:address":"12917 53 St NW",
    "sg:city":"Edmonton",
    "sg:classifiers":[
        {
            "category":"Wholesale",
            "subcategory":"Scrap",
            "type":"Manufacturing & Wholesale Goods"
        }
    ],
    "sg:phone":"+1 780 476 1066",
    "sg:postcode":"T5A 2E7",
    "sg:province":"AB",
    "sg:tags":[
        "repairing",
        "automobile",
        "crushing"
    ],
    "wof:name":"Kendale Truck Parts Ltd",
    "wof:placetype":"venue"
},
  "geometry": {"coordinates":[-113.422843933,53.588142395],"type":"Point"}
}