{
  "type": "Feature",
  "properties": {
    "addr:full":"23 Rue Sainte-Catherine O Montreal QC H2X 1Z5",
    "addr:housenumber":"23",
    "addr:postcode":"h2x 1z5",
    "addr:street":"Rue Sainte-Catherine O",
    "iso:country":"CA",
    "sg:address":"23 Rue Sainte-Catherine O",
    "sg:city":"Montreal",
    "sg:classifiers":[
        {
            "category":"Personal",
            "subcategory":"Tattoo Parlor",
            "type":"Services"
        }
    ],
    "sg:phone":"+1 514 288 6225",
    "sg:postcode":"H2X 1Z5",
    "sg:province":"QC",
    "sg:tags":[
        "tattooing"
    ],
    "wof:name":"Superock Inc",
    "wof:placetype":"venue"
},
  "geometry": {"coordinates":[-73.590836,45.516144],"type":"Point"}
}