{
  "type": "Feature",
  "properties": {
    "iso:country":"CA",
    "sg:address":"400 Bayfield St",
    "sg:city":"Barrie",
    "sg:classifiers":[
        {
            "category":"Banks & Credit Unions",
            "subcategory":"Investment Brokerage",
            "type":"Services"
        }
    ],
    "sg:phone":"+1 705 730 7598",
    "sg:postcode":"L4M 5A1",
    "sg:province":"ON",
    "sg:tags":[
        "consultant",
        "planning",
        "financial"
    ],
    "wof:name":"Dunbrook Associates",
    "wof:placetype":"venue"
},
  "geometry": {"coordinates":[-79.704346,44.40538],"type":"Point"}
}