{
  "type": "Feature",
  "properties": {
    "addr:full":"182 Ontario St Burks Falls ON P0A 1C0",
    "addr:housenumber":"182",
    "addr:postcode":"p0a 1c0",
    "addr:street":"Ontario St",
    "iso:country":"CA",
    "sg:address":"182 Ontario St",
    "sg:city":"Burks Falls",
    "sg:classifiers":[
        {
            "category":"Home & Garden",
            "subcategory":"Household Appliances",
            "type":"Retail Goods"
        }
    ],
    "sg:phone":"+1 705 382 2726",
    "sg:postcode":"P0A 1C0",
    "sg:province":"ON",
    "wof:name":"Burk's Falls Radio & Tv Svc",
    "wof:placetype":"venue"
},
  "geometry": {"coordinates":[-83.56378173829999,46.2565841675],"type":"Point"}
}