{
  "type": "Feature",
  "properties": {
    "addr:full":"513 20 Ave SW # 3 Calgary AB T2S 0E7",
    "addr:housenumber":"513",
    "addr:postcode":"t2s 0e7",
    "addr:street":"20 Ave Sw # 3",
    "iso:country":"CA",
    "sg:address":"513 20 Ave SW # 3",
    "sg:city":"Calgary",
    "sg:classifiers":[
        {
            "category":"Building & Trades",
            "subcategory":"Construction",
            "type":"Services"
        }
    ],
    "sg:phone":"+1 403 228 9174",
    "sg:postcode":"T2S 0E7",
    "sg:province":"AB",
    "sg:tags":[
        "communications",
        "contractor",
        "consultant"
    ],
    "wof:name":"Montana Creative",
    "wof:placetype":"venue"
},
  "geometry": {"coordinates":[-114.072044373,51.0349998474],"type":"Point"}
}