{
  "type": "Feature",
  "properties": {
    "addr:full":"Desboro ON N0H 1K0",
    "addr:postcode":"n0h 1k0",
    "iso:country":"CA",
    "sg:city":"Desboro",
    "sg:classifiers":[
        {
            "category":"Building & Trades",
            "subcategory":"Landscaping Services",
            "type":"Services"
        }
    ],
    "sg:phone":"+1 519 794 2737",
    "sg:postcode":"N0H 1K0",
    "sg:province":"ON",
    "sg:tags":[
        "designer",
        "landscape"
    ],
    "wof:name":"Northwood Associates Landscape",
    "wof:placetype":"venue"
},
  "geometry": {"coordinates":[-80.954643,44.391685],"type":"Point"}
}