{
  "type": "Feature",
  "properties": {
    "addr:full":"201 Wilfred St Wawota SK S0G 5A0",
    "addr:housenumber":"201",
    "addr:postcode":"s0g 5a0",
    "addr:street":"Wilfred St",
    "iso:country":"CA",
    "sg:address":"201 Wilfred St",
    "sg:city":"Wawota",
    "sg:classifiers":[
        {
            "category":"Health Services",
            "subcategory":"Nursing And Care Facility",
            "type":"Services"
        }
    ],
    "sg:phone":"+1 306 739 2533",
    "sg:postcode":"S0G 5A0",
    "sg:province":"SK",
    "sg:tags":[
        "home",
        "convalescent"
    ],
    "wof:name":"Wawota & Dist Special Care Hm",
    "wof:placetype":"venue"
},
  "geometry": {"coordinates":[-102.028183,49.90321],"type":"Point"}
}