{
  "type": "Feature",
  "properties": {
    "addr:full":"40388 Tantalus Way Garibaldi Highlands BC V0N 1T0",
    "addr:housenumber":"40388",
    "addr:postcode":"v0n 1t0",
    "addr:street":"Tantalus Way",
    "iso:country":"CA",
    "sg:address":"40388 Tantalus Way",
    "sg:city":"Garibaldi Highlands",
    "sg:classifiers":[
        {
            "category":"Cinema",
            "subcategory":"Movie Rental",
            "type":"Entertainment"
        }
    ],
    "sg:phone":"+1 604 898 9525",
    "sg:postcode":"V0N 1T0",
    "sg:province":"BC",
    "sg:tags":[
        "leasing",
        "video",
        "disc",
        "tape"
    ],
    "wof:name":"Highland Video",
    "wof:placetype":"venue"
},
  "geometry": {"coordinates":[-123.13254499999999,49.740482],"type":"Point"}
}