{
  "type": "Feature",
  "properties": {
    "addr:full":"295 Shuswap St Chase BC V0E 1M0",
    "addr:housenumber":"295",
    "addr:postcode":"v0e 1m0",
    "addr:street":"Shuswap St",
    "iso:country":"CA",
    "sg:address":"295 Shuswap St",
    "sg:city":"Chase",
    "sg:classifiers":[
        {
            "category":"Organizations",
            "subcategory":"Religious Organization",
            "type":"Services"
        }
    ],
    "sg:phone":"+1 250 679 3626",
    "sg:postcode":"V0E 1M0",
    "sg:province":"BC",
    "sg:tags":[
        "church"
    ],
    "wof:name":"Evangelical Free Church",
    "wof:placetype":"venue"
},
  "geometry": {"coordinates":[-119.694771,50.813839],"type":"Point"}
}