{
  "type": "Feature",
  "properties": {
    "addr:full":"586 Mount Pleasant Rd Toronto ON M4S 2M8",
    "addr:housenumber":"586",
    "addr:postcode":"m4s 2m8",
    "addr:street":"Mount Pleasant Rd",
    "iso:country":"CA",
    "sg:address":"586 Mount Pleasant Rd",
    "sg:city":"Toronto",
    "sg:classifiers":[
        {
            "category":"Personal",
            "subcategory":"Beauty Salon",
            "type":"Services"
        }
    ],
    "sg:phone":"+1 416 485 1583",
    "sg:postcode":"M4S 2M8",
    "sg:province":"ON",
    "wof:name":"Seringa Skin Care",
    "wof:placetype":"venue"
},
  "geometry": {"coordinates":[-79.3884048462,43.7035217285],"type":"Point"}
}