{
  "type": "Feature",
  "properties": {
    "addr:full":"1837 Lansdowne St W # 9B Peterborough ON K9K 1R4",
    "addr:housenumber":"1837",
    "addr:postcode":"k9k 1r4",
    "addr:street":"Lansdowne St W # 9B",
    "iso:country":"CA",
    "sg:address":"1837 Lansdowne St W # 9B",
    "sg:city":"Peterborough",
    "sg:classifiers":[
        {
            "category":"Restaurant",
            "type":"Food & Drink"
        }
    ],
    "sg:phone":"+1 705 748 2282",
    "sg:postcode":"K9K 1R4",
    "sg:province":"ON",
    "sg:tags":[
        "pizza"
    ],
    "wof:name":"Alba Pizzeria",
    "wof:placetype":"venue"
},
  "geometry": {"coordinates":[-78.37350499999999,44.275036],"type":"Point"}
}