{
  "type": "Feature",
  "properties": {
    "iso:country":"CA",
    "sg:address":"1837 Lansdowne St W # 9B",
    "sg:city":"Peterborough",
    "sg:classifiers":[
        {
            "category":"Restaurant",
            "type":"Food & Drink"
        }
    ],
    "sg:phone":"+1 705 748 2282",
    "sg:postcode":"K9K 1R4",
    "sg:province":"ON",
    "sg:tags":[
        "pizza"
    ],
    "wof:name":"Alba Pizzeria",
    "wof:placetype":"venue"
},
  "geometry": {"coordinates":[-78.373505,44.275036],"type":"Point"}
}