{
  "type": "Feature",
  "properties": {
    "iso:country":"CA",
    "sg:address":"82 Charterhouse Cres",
    "sg:city":"London",
    "sg:classifiers":[
        {
            "category":"Manufacturing",
            "subcategory":"Motor Vehicles & Parts",
            "type":"Manufacturing & Wholesale Goods"
        }
    ],
    "sg:phone":"+1 519 451 0417",
    "sg:postcode":"N5W 5V5",
    "sg:province":"ON",
    "sg:tags":[
        "automobile",
        "wrecking"
    ],
    "wof:name":"Tommy's Quick Cash",
    "wof:placetype":"venue"
},
  "geometry": {"coordinates":[-81.169907,42.989422],"type":"Point"}
}