{
  "type": "Feature",
  "properties": {
    "iso:country":"CA",
    "sg:city":"Richmond",
    "sg:classifiers":[
        {
            "category":"Insurance",
            "subcategory":"Insurance Agent",
            "type":"Services"
        }
    ],
    "sg:phone":"+1 604 448 9196",
    "sg:postcode":"V7E 3R8",
    "sg:province":"BC",
    "wof:name":"Nesika Insurance Svc",
    "wof:placetype":"venue"
},
  "geometry": {"coordinates":[-123.164299011,49.1210136414],"type":"Point"}
}