{
  "type": "Feature",
  "properties": {
    "addr:full":"3592 Bluestream Cres Mississauga ON L4Y 3S6",
    "addr:housenumber":"3592",
    "addr:postcode":"l4y 3s6",
    "addr:street":"Bluestream Cres",
    "iso:country":"CA",
    "sg:address":"3592 Bluestream Cres",
    "sg:city":"Mississauga",
    "sg:classifiers":[
        {
            "category":"Wholesale",
            "subcategory":"Electrical",
            "type":"Manufacturing & Wholesale Goods"
        }
    ],
    "sg:phone":"+1 905 276 5801",
    "sg:postcode":"L4Y 3S6",
    "sg:province":"ON",
    "sg:tags":[
        "equipment",
        "electronic",
        "supply"
    ],
    "wof:name":"Larcon Electronics Ltd",
    "wof:placetype":"venue"
},
  "geometry": {"coordinates":[-79.607254,43.615307],"type":"Point"}
}