{
  "type": "Feature",
  "properties": {
    "addr:full":"Chatham ON N7M 6A9",
    "addr:postcode":"n7m 6a9",
    "iso:country":"CA",
    "sg:city":"Chatham",
    "sg:classifiers":[
        {
            "category":"Shopping",
            "subcategory":"Clothing, Apparel, & Fashions",
            "type":"Retail Goods"
        }
    ],
    "sg:phone":"+1 519 352 1702",
    "sg:postcode":"N7M 6A9",
    "sg:province":"ON",
    "wof:name":"Fairweather",
    "wof:placetype":"venue"
},
  "geometry": {"coordinates":[-82.18264000000001,42.404991],"type":"Point"}
}