{
  "type": "Feature",
  "properties": {
    "addr:full":"Winnipeg MB R2J 3W7",
    "addr:postcode":"r2j 3w7",
    "iso:country":"CA",
    "sg:city":"Winnipeg",
    "sg:classifiers":[
        {
            "category":"Food & Beverages",
            "subcategory":"Liquor & Beverages",
            "type":"Retail Goods"
        }
    ],
    "sg:phone":"+1 204 987 4043",
    "sg:postcode":"R2J 3W7",
    "sg:province":"MB",
    "sg:tags":[
        "store"
    ],
    "wof:name":"Manitoba Liquor Control Comm",
    "wof:placetype":"venue"
},
  "geometry": {"coordinates":[-97.07400512700001,49.8540687561],"type":"Point"}
}