{
  "type": "Feature",
  "properties": {
    "addr:full":"50 Eglinton Sq Scarborough ON M1L 2K1",
    "addr:housenumber":"50",
    "addr:postcode":"m1l 2k1",
    "addr:street":"Eglinton Sq",
    "iso:country":"CA",
    "sg:address":"50 Eglinton Sq",
    "sg:city":"Scarborough",
    "sg:classifiers":[
        {
            "category":"Education",
            "subcategory":"Library",
            "type":"Public Place"
        }
    ],
    "sg:phone":"+1 416 396 8920",
    "sg:postcode":"M1L 2K1",
    "sg:province":"ON",
    "wof:name":"Edlinton Sq Branch Library",
    "wof:placetype":"venue"
},
  "geometry": {"coordinates":[-79.3015213013,43.7235412598],"type":"Point"}
}