{
  "type": "Feature",
  "properties": {
    "addr:full":"39 Ormond St Brockville ON K6V 2K3",
    "addr:housenumber":"39",
    "addr:postcode":"k6v 2k3",
    "addr:street":"Ormond St",
    "iso:country":"CA",
    "sg:address":"39 Ormond St",
    "sg:city":"Brockville",
    "sg:classifiers":[
        {
            "category":"Shopping",
            "subcategory":"Hobbies, Toys, & Games",
            "type":"Retail Goods"
        }
    ],
    "sg:phone":"+1 613 342 8667",
    "sg:postcode":"K6V 2K3",
    "sg:province":"ON",
    "sg:tags":[
        "craft",
        "supply"
    ],
    "wof:name":"Needleworks",
    "wof:placetype":"venue"
},
  "geometry": {"coordinates":[-75.67948199999999,44.594379],"type":"Point"}
}