{
  "type": "Feature",
  "properties": {
    "iso:country":"CA",
    "sg:address":"222 Lesmill Rd",
    "sg:city":"North York",
    "sg:classifiers":[
        {
            "category":"Building & Trades",
            "subcategory":"Construction",
            "type":"Services"
        }
    ],
    "sg:phone":"+1 416 445 8552",
    "sg:postcode":"M3B 2T5",
    "sg:province":"ON",
    "sg:tags":[
        "general",
        "contractor"
    ],
    "wof:name":"Senator Homes Ltd",
    "wof:placetype":"venue"
},
  "geometry": {"coordinates":[-79.3590545654,43.7610588074],"type":"Point"}
}