{
  "type": "Feature",
  "properties": {
    "addr:full":"6615 Ch DE LA Cote-DE-Liesse Saint-Laurent QC H4T 1E5",
    "addr:housenumber":"6615",
    "addr:postcode":"h4t 1e5",
    "addr:street":"Ch De La Cote-De-Liesse",
    "iso:country":"CA",
    "sg:address":"6615 Ch DE LA Cote-DE-Liesse",
    "sg:city":"Saint-Laurent",
    "sg:classifiers":[
        {
            "category":"Bars & Pubs",
            "type":"Food & Drink"
        }
    ],
    "sg:phone":"+1 514 341 1011",
    "sg:postcode":"H4T 1E5",
    "sg:province":"QC",
    "wof:name":"Chez L'Pere Gedeon",
    "wof:placetype":"venue"
},
  "geometry": {"coordinates":[-73.693359375,45.4848175049],"type":"Point"}
}