{
  "type": "Feature",
  "properties": {
    "addr:full":"92 Rue Saint-Pierre Saint-Constant QC J5A 1G3",
    "addr:housenumber":"92",
    "addr:postcode":"j5a 1g3",
    "addr:street":"Rue Saint-Pierre",
    "iso:country":"CA",
    "sg:address":"92 Rue Saint-Pierre",
    "sg:city":"Saint-Constant",
    "sg:classifiers":[
        {
            "category":"Home & Garden",
            "subcategory":"Building Materials",
            "type":"Retail Goods"
        }
    ],
    "sg:phone":"+1 450 638 0184",
    "sg:postcode":"J5A 1G3",
    "sg:province":"QC",
    "sg:tags":[
        "glass",
        "window",
        "plate"
    ],
    "wof:name":"Vitro Plus St Constant",
    "wof:placetype":"venue"
},
  "geometry": {"coordinates":[-73.5646820068,45.3777351379],"type":"Point"}
}