{
  "type": "Feature",
  "properties": {
    "addr:full":"142 Anne St Thedford ON N0M 2N0",
    "addr:housenumber":"142",
    "addr:postcode":"n0m 2n0",
    "addr:street":"Anne St",
    "iso:country":"CA",
    "sg:address":"142 Anne St",
    "sg:city":"Thedford",
    "sg:classifiers":[
        {
            "category":"Building & Trades",
            "subcategory":"Construction",
            "type":"Services"
        }
    ],
    "sg:phone":"+1 519 296 5579",
    "sg:postcode":"N0M 2N0",
    "sg:province":"ON",
    "sg:tags":[
        "general",
        "contractor"
    ],
    "wof:name":"Bob Hamilton Heating & General",
    "wof:placetype":"venue"
},
  "geometry": {"coordinates":[-81.85251617430001,43.1639328003],"type":"Point"}
}