{
  "type": "Feature",
  "properties": {
    "iso:country":"CA",
    "sg:city":"Markham",
    "sg:classifiers":[
        {
            "category":"Manufacturing",
            "subcategory":"Printing",
            "type":"Manufacturing & Wholesale Goods"
        }
    ],
    "sg:phone":"+1 905 201 6994",
    "sg:postcode":"L3P 5E5",
    "sg:province":"ON",
    "sg:tags":[
        "printer"
    ],
    "wof:name":"Print Three",
    "wof:placetype":"venue"
},
  "geometry": {"coordinates":[-79.284538,43.868008],"type":"Point"}
}