{
  "type": "Feature",
  "properties": {
    "addr:full":"89 Ch Larocque Salaberry-DE-Valleyfield QC J6T 4A6",
    "addr:housenumber":"89",
    "addr:postcode":"j6t 4a6",
    "addr:street":"Ch Larocque",
    "iso:country":"CA",
    "sg:address":"89 Ch Larocque",
    "sg:city":"Salaberry-DE-Valleyfield",
    "sg:classifiers":[
        {
            "category":"Personal",
            "subcategory":"Beauty Salon",
            "type":"Services"
        }
    ],
    "sg:phone":"+1 450 377 8501",
    "sg:postcode":"J6T 4A6",
    "sg:province":"QC",
    "wof:name":"Coiffure Allure Mode",
    "wof:placetype":"venue"
},
  "geometry": {"coordinates":[-74.1350326538,45.2527732849],"type":"Point"}
}