{
  "type": "Feature",
  "properties": {
    "addr:full":"46 Fox St Essex ON N8M 2S2",
    "addr:housenumber":"46",
    "addr:postcode":"n8m 2s2",
    "addr:street":"Fox St",
    "iso:country":"CA",
    "sg:address":"46 Fox St",
    "sg:city":"Essex",
    "sg:classifiers":[
        {
            "category":"Government",
            "subcategory":"Office",
            "type":"Public Place"
        }
    ],
    "sg:phone":"+1 519 776 5272",
    "sg:postcode":"N8M 2S2",
    "sg:province":"ON",
    "wof:name":"Susan Whelan Constituency",
    "wof:placetype":"venue"
},
  "geometry": {"coordinates":[-82.821541,42.175358],"type":"Point"}
}