{
  "type": "Feature",
  "properties": {
    "addr:full":"21160 Vanneck Rd London ON N6H 5L2",
    "addr:housenumber":"21160",
    "addr:postcode":"n6h 5l2",
    "addr:street":"Vanneck Rd",
    "iso:country":"CA",
    "sg:address":"21160 Vanneck Rd",
    "sg:city":"London",
    "sg:classifiers":[
        {
            "category":"Retail",
            "subcategory":"Auto Repair",
            "type":"Services"
        }
    ],
    "sg:phone":"+1 519 471 0347",
    "sg:postcode":"N6H 5L2",
    "sg:province":"ON",
    "sg:tags":[
        "wrecker"
    ],
    "wof:name":"Collver Towing",
    "wof:placetype":"venue"
},
  "geometry": {"coordinates":[-81.24621582029999,42.9868965149],"type":"Point"}
}