{
  "type": "Feature",
  "properties": {
    "addr:full":"Vancouver BC V6H 1N8",
    "addr:postcode":"v6h 1n8",
    "iso:country":"CA",
    "sg:city":"Vancouver",
    "sg:classifiers":[
        {
            "category":"Manufacturing",
            "subcategory":"Paper Products",
            "type":"Manufacturing & Wholesale Goods"
        }
    ],
    "sg:phone":"+1 604 682 5106",
    "sg:postcode":"V6H 1N8",
    "sg:province":"BC",
    "sg:tags":[
        "label"
    ],
    "wof:name":"Superseal Tape & Label",
    "wof:placetype":"venue"
},
  "geometry": {"coordinates":[-123.134964,49.259659],"type":"Point"}
}