{
  "type": "Feature",
  "properties": {
    "iso:country":"CA",
    "sg:city":"St Catharines",
    "sg:classifiers":[
        {
            "category":"Recreation",
            "type":"Entertainment"
        }
    ],
    "sg:phone":"+1 905 704 0446",
    "sg:postcode":"L2T 3B2",
    "sg:province":"ON",
    "sg:tags":[
        "club",
        "bridge"
    ],
    "wof:name":"Bridge Centre of Niagara",
    "wof:placetype":"venue"
},
  "geometry": {"coordinates":[-79.224159,43.13298],"type":"Point"}
}