{
  "type": "Feature",
  "properties": {
    "addr:full":"501 Serviceberry Trail Rockyford AB T0J 2R0",
    "addr:housenumber":"501",
    "addr:postcode":"t0j 2r0",
    "addr:street":"Serviceberry Trail",
    "iso:country":"CA",
    "sg:address":"501 Serviceberry Trail",
    "sg:city":"Rockyford",
    "sg:classifiers":[
        {
            "category":"Retail",
            "subcategory":"Auto Repair",
            "type":"Services"
        }
    ],
    "sg:phone":"+1 403 533 3959",
    "sg:postcode":"T0J 2R0",
    "sg:province":"AB",
    "sg:tags":[
        "repairing",
        "automobile"
    ],
    "wof:name":"Southland Transportation Ltd",
    "wof:placetype":"venue"
},
  "geometry": {"coordinates":[-113.144485,51.233616],"type":"Point"}
}