{
  "type": "Feature",
  "properties": {
    "iso:country":"CA",
    "sg:address":"4056 New St",
    "sg:city":"Burlington",
    "sg:classifiers":[
        {
            "category":"Education",
            "subcategory":"School",
            "type":"Public Place"
        }
    ],
    "sg:phone":"+1 905 637 3810",
    "sg:postcode":"L7L 1S9",
    "sg:province":"ON",
    "wof:name":"St Raphael's School",
    "wof:placetype":"venue"
},
  "geometry": {"coordinates":[-79.767838,43.354156],"type":"Point"}
}