{
  "type": "Feature",
  "properties": {
    "addr:full":"25914 Hwy 48 Sutton West ON L0E 1R0",
    "addr:housenumber":"25914",
    "addr:postcode":"l0e 1r0",
    "addr:street":"Hwy 48",
    "iso:country":"CA",
    "sg:address":"25914 Hwy 48",
    "sg:city":"Sutton West",
    "sg:classifiers":[
        {
            "category":"Retail",
            "subcategory":"Veterinary Services",
            "type":"Services"
        }
    ],
    "sg:phone":"+1 905 722 6571",
    "sg:postcode":"L0E 1R0",
    "sg:province":"ON",
    "sg:tags":[
        "veterinarian"
    ],
    "wof:name":"Georgina Veterinary Clinic",
    "wof:placetype":"venue"
},
  "geometry": {"coordinates":[-79.35105900000001,44.295826],"type":"Point"}
}