{
  "type": "Feature",
  "properties": {
    "addr:full":"5322 118 Ave NW Edmonton AB T5W 1C4",
    "addr:housenumber":"5322",
    "addr:postcode":"t5w 1c4",
    "addr:street":"118 Ave Nw",
    "iso:country":"CA",
    "sg:address":"5322 118 Ave NW",
    "sg:city":"Edmonton",
    "sg:classifiers":[
        {
            "category":"Building & Trades",
            "subcategory":"Construction",
            "type":"Services"
        }
    ],
    "sg:phone":"+1 780 447 5343",
    "sg:postcode":"T5W 1C4",
    "sg:province":"AB",
    "sg:tags":[
        "resurfacing",
        "material",
        "laying",
        "refinishing",
        "floor"
    ],
    "wof:name":"Contract Interiors",
    "wof:placetype":"venue"
},
  "geometry": {"coordinates":[-113.423492432,53.5704574585],"type":"Point"}
}