{
  "type": "Feature",
  "properties": {
    "addr:full":"165 Boul Coakley Asbestos QC J1T 1A4",
    "addr:housenumber":"165",
    "addr:postcode":"j1t 1a4",
    "addr:street":"Boul Coakley",
    "iso:country":"CA",
    "sg:address":"165 Boul Coakley",
    "sg:city":"Asbestos",
    "sg:classifiers":[
        {
            "category":"Building & Trades",
            "subcategory":"Construction",
            "type":"Services"
        }
    ],
    "sg:phone":"+1 819 879 2188",
    "sg:postcode":"J1T 1A4",
    "sg:province":"QC",
    "sg:tags":[
        "concrete",
        "pumping"
    ],
    "wof:name":"Pompage DE Beton Asbestos",
    "wof:placetype":"venue"
},
  "geometry": {"coordinates":[-71.916336,45.78281],"type":"Point"}
}