{
  "type": "Feature",
  "properties": {
    "addr:full":"10755 Av Edger #A Montreal-Nord QC H1G 4Z7",
    "addr:postcode":"h1g 4z7",
    "addr:street":"Av Edger # A",
    "iso:country":"CA",
    "sg:address":"10755 Av Edger #A",
    "sg:city":"Montreal-Nord",
    "sg:classifiers":[
        {
            "category":"Manufacturing",
            "subcategory":"Tools & Machinery",
            "type":"Manufacturing & Wholesale Goods"
        }
    ],
    "sg:phone":"+1 514 327 1886",
    "sg:postcode":"H1G 4Z7",
    "sg:province":"QC",
    "sg:tags":[
        "machine",
        "shop"
    ],
    "wof:name":"S L Precision Erosion Inc",
    "wof:placetype":"venue"
},
  "geometry": {"coordinates":[-73.620552,45.59787],"type":"Point"}
}