{
  "type": "Feature",
  "properties": {
    "addr:full":"12144 Northpark Cres Surrey BC V3X 2B2",
    "addr:housenumber":"12144",
    "addr:postcode":"v3x 2b2",
    "addr:street":"Northpark Cres",
    "iso:country":"CA",
    "sg:address":"12144 Northpark Cres",
    "sg:city":"Surrey",
    "sg:classifiers":[
        {
            "category":"Manufacturing",
            "subcategory":"Rubber & Plastics",
            "type":"Manufacturing & Wholesale Goods"
        }
    ],
    "sg:phone":"+1 604 501 9644",
    "sg:postcode":"V3X 2B2",
    "sg:province":"BC",
    "sg:tags":[
        "seal"
    ],
    "wof:name":"Brit Bar Security Products",
    "wof:placetype":"venue"
},
  "geometry": {"coordinates":[-122.884804,49.112873],"type":"Point"}
}