{
  "type": "Feature",
  "properties": {
    "iso:country":"CA",
    "sg:city":"Lac LA Biche",
    "sg:classifiers":[
        {
            "category":"Personal",
            "subcategory":"Beauty Salon",
            "type":"Services"
        }
    ],
    "sg:phone":"+1 780 623 2235",
    "sg:postcode":"T0A 2C0",
    "sg:province":"AB",
    "wof:name":"Black Knight Hair Styling",
    "wof:placetype":"venue"
},
  "geometry": {"coordinates":[-111.97793579099999,54.7711296082],"type":"Point"}
}