{
  "type": "Feature",
  "properties": {
    "addr:full":"7 Belle Ave Souris PE C0A 2B0",
    "addr:housenumber":"7",
    "addr:postcode":"c0a 2b0",
    "addr:street":"Belle Ave",
    "iso:country":"CA",
    "sg:address":"7 Belle Ave",
    "sg:city":"Souris",
    "sg:classifiers":[
        {
            "category":"Personal",
            "subcategory":"Beauty Salon",
            "type":"Services"
        }
    ],
    "sg:phone":"+1 902 687 2562",
    "sg:postcode":"C0A 2B0",
    "sg:province":"PE",
    "wof:name":"Julie's Place Hair Salon",
    "wof:placetype":"venue"
},
  "geometry": {"coordinates":[-62.25248,46.353855],"type":"Point"}
}