{
  "type": "Feature",
  "properties": {
    "iso:country":"CA",
    "sg:address":"7712 Kent Blvd",
    "sg:city":"Brockville",
    "sg:classifiers":[
        {
            "category":"Shopping",
            "subcategory":"Florist",
            "type":"Retail Goods"
        }
    ],
    "sg:phone":"+1 613 345 1337",
    "sg:postcode":"K6V 7H6",
    "sg:province":"ON",
    "wof:name":"Flowers Brockville",
    "wof:placetype":"venue"
},
  "geometry": {"coordinates":[-75.7066268921,44.5994682312],"type":"Point"}
}