{
  "type": "Feature",
  "properties": {
    "addr:full":"3506 Tudor Glen St Albert AB T8N 3V4",
    "addr:housenumber":"3506",
    "addr:postcode":"t8n 3v4",
    "addr:street":"Tudor Glen",
    "iso:country":"CA",
    "sg:address":"3506 Tudor Glen",
    "sg:city":"St Albert",
    "sg:classifiers":[
        {
            "category":"Restaurant",
            "type":"Food & Drink"
        }
    ],
    "sg:phone":"+1 780 459 5089",
    "sg:postcode":"T8N 3V4",
    "sg:province":"AB",
    "wof:name":"Joey's Only Seafood Restaurant",
    "wof:placetype":"venue"
},
  "geometry": {"coordinates":[-113.62735000000001,53.633518],"type":"Point"}
}