{
  "type": "Feature",
  "properties": {
    "addr:full":"Ottawa ON K1P 6A9",
    "addr:postcode":"k1p 6a9",
    "iso:country":"CA",
    "sg:city":"Ottawa",
    "sg:classifiers":[
        {
            "category":"Professional",
            "subcategory":"Computer Services",
            "type":"Services"
        }
    ],
    "sg:phone":"+1 613 566 7027",
    "sg:postcode":"K1P 6A9",
    "sg:province":"ON",
    "sg:tags":[
        "internet"
    ],
    "wof:name":"Iline Entertainment Inc",
    "wof:placetype":"venue"
},
  "geometry": {"coordinates":[-75.70072937010001,45.4199295044],"type":"Point"}
}