{
  "type": "Feature",
  "properties": {
    "iso:country":"CA",
    "sg:address":"2860 Des Quatre-Bourgeois Ch",
    "sg:city":"Sainte-Foy",
    "sg:classifiers":[
        {
            "category":"Professional",
            "subcategory":"Accounting & Tax Preparation",
            "type":"Services"
        }
    ],
    "sg:phone":"+1 418 656 6062",
    "sg:postcode":"G1V 1Y3",
    "sg:province":"QC",
    "sg:tags":[
        "accountant"
    ],
    "wof:name":"Turgeon, Rene",
    "wof:placetype":"venue"
},
  "geometry": {"coordinates":[-71.299385,46.774506],"type":"Point"}
}