{
  "type": "Feature",
  "properties": {
    "iso:country":"CA",
    "sg:address":"4288 5th Ave",
    "sg:city":"Prince George",
    "sg:classifiers":[
        {
            "category":"Restaurant",
            "type":"Food & Drink"
        }
    ],
    "sg:phone":"+1 250 564 2828",
    "sg:postcode":"V2M 7A2",
    "sg:province":"BC",
    "wof:name":"China Sail Restaurant",
    "wof:placetype":"venue"
},
  "geometry": {"coordinates":[-122.804504395,53.9207878113],"type":"Point"}
}