{
  "type": "Feature",
  "properties": {
    "addr:full":"7354 Ch DE LA Cote-Saint-Luc Montreal QC H4W 1P7",
    "addr:postcode":"7354;h4w 1p7",
    "addr:street":"Ch De La Cote-Saint-Luc",
    "iso:country":"CA",
    "sg:address":"7354 Ch DE LA Cote-Saint-Luc",
    "sg:city":"Montreal",
    "sg:classifiers":[
        {
            "category":"Restaurant",
            "type":"Food & Drink"
        }
    ],
    "sg:phone":"+1 514 485 8818",
    "sg:postcode":"H4W 1P7",
    "sg:province":"QC",
    "sg:tags":[
        "caterer"
    ],
    "wof:name":"Solly the Caterer",
    "wof:placetype":"venue"
},
  "geometry": {"coordinates":[-73.656509,45.462254],"type":"Point"}
}