{
  "type": "Feature",
  "properties": {
    "iso:country":"CA",
    "sg:address":"488 Rue DE L'Ecole",
    "sg:city":"Saint-Marcel-DE-Richelieu",
    "sg:classifiers":[
        {
            "category":"Education",
            "subcategory":"School",
            "type":"Public Place"
        }
    ],
    "sg:phone":"+1 450 773 5081",
    "sg:postcode":"J0H 1T0",
    "sg:province":"QC",
    "wof:name":"Saint-Marcel Ecole",
    "wof:placetype":"venue"
},
  "geometry": {"coordinates":[-72.8987197876,45.8603401184],"type":"Point"}
}