{
  "type": "Feature",
  "properties": {
    "addr:full":"Calgary AB T2T 4H4",
    "addr:postcode":"t2t 4h4",
    "iso:country":"CA",
    "sg:city":"Calgary",
    "sg:classifiers":[
        {
            "category":"Building & Trades",
            "subcategory":"Construction",
            "type":"Services"
        }
    ],
    "sg:phone":"+1 403 243 7038",
    "sg:postcode":"T2T 4H4",
    "sg:province":"AB",
    "sg:tags":[
        "contractor",
        "general"
    ],
    "wof:name":"Design Factor Homes",
    "wof:placetype":"venue"
},
  "geometry": {"coordinates":[-114.100265503,51.0190353394],"type":"Point"}
}