{
  "type": "Feature",
  "properties": {
    "addr:full":"425 Lansdowne St Kamloops BC V2C 1Y2",
    "addr:housenumber":"425",
    "addr:postcode":"bc v2c 1y2",
    "addr:street":"Lansdowne St",
    "iso:country":"CA",
    "sg:address":"425 Lansdowne St",
    "sg:city":"Kamloops",
    "sg:classifiers":[
        {
            "category":"Organizations",
            "subcategory":"Community Association",
            "type":"Services"
        }
    ],
    "sg:phone":"+1 250 374 1742",
    "sg:postcode":"V2C 1Y2",
    "sg:province":"BC",
    "sg:tags":[
        "club"
    ],
    "wof:name":"Royal Canadian Legion",
    "wof:placetype":"venue"
},
  "geometry": {"coordinates":[-120.331260681,50.6765403748],"type":"Point"}
}