{
  "type": "Feature",
  "properties": {
    "addr:full":"1185 8th Ave Valemount BC V0E 2Z0",
    "addr:housenumber":"1185",
    "addr:postcode":"v0e 2z0",
    "addr:street":"8Th Ave",
    "iso:country":"CA",
    "sg:address":"1185 8th Ave",
    "sg:city":"Valemount",
    "sg:classifiers":[
        {
            "category":"Building & Trades",
            "subcategory":"Plumbing",
            "type":"Services"
        }
    ],
    "sg:phone":"+1 250 566 4520",
    "sg:postcode":"V0E 2Z0",
    "sg:province":"BC",
    "sg:tags":[
        "contractor"
    ],
    "wof:name":"Valemount Plumbing & Heating",
    "wof:placetype":"venue"
},
  "geometry": {"coordinates":[-119.259834,52.82946],"type":"Point"}
}