{
  "type": "Feature",
  "properties": {
    "addr:full":"Milton ON L9T 4R3",
    "addr:postcode":"l9t 4r3",
    "iso:country":"CA",
    "sg:city":"Milton",
    "sg:classifiers":[
        {
            "category":"Personal",
            "subcategory":"Beauty Salon",
            "type":"Services"
        }
    ],
    "sg:phone":"+1 905 876 1337",
    "sg:postcode":"L9T 4R3",
    "sg:province":"ON",
    "wof:name":"Hi 5 Hair Designers",
    "wof:placetype":"venue"
},
  "geometry": {"coordinates":[-79.86199999999999,43.509026],"type":"Point"}
}