{
  "type": "Feature",
  "properties": {
    "addr:full":"2150 Av Laurier E Montreal QC H2H 1C2",
    "addr:housenumber":"2150",
    "addr:postcode":"h2h 1c2",
    "addr:street":"Av Laurier E",
    "iso:country":"CA",
    "sg:address":"2150 Av Laurier E",
    "sg:city":"Montreal",
    "sg:classifiers":[
        {
            "category":"Retail",
            "subcategory":"Self-service Laundry",
            "type":"Services"
        }
    ],
    "sg:phone":"+1 514 525 1704",
    "sg:postcode":"H2H 1C2",
    "sg:province":"QC",
    "wof:name":"Lavoir Laurier",
    "wof:placetype":"venue"
},
  "geometry": {"coordinates":[-73.57769,45.538631],"type":"Point"}
}