{
  "type": "Feature",
  "properties": {
    "addr:full":"6549 Wildmare Access Rd S Chetwynd BC V0C 1J0",
    "addr:housenumber":"6549",
    "addr:postcode":"bc v0c 1j0",
    "addr:street":"Wildmare Access Rd",
    "iso:country":"CA",
    "sg:address":"6549 Wildmare Access Rd S",
    "sg:city":"Chetwynd",
    "sg:classifiers":[
        {
            "category":"Real Estate",
            "subcategory":"Real Estate Operator",
            "type":"Services"
        }
    ],
    "sg:phone":"+1 250 788 9676",
    "sg:postcode":"V0C 1J0",
    "sg:province":"BC",
    "sg:tags":[
        "mobile",
        "home",
        "community"
    ],
    "wof:name":"Aspen Mobile Home Estates",
    "wof:placetype":"venue"
},
  "geometry": {"coordinates":[-121.627747,55.697533],"type":"Point"}
}