{
  "type": "Feature",
  "properties": {
    "addr:full":"Bldg 953 Iqaluit NU X0A 0H0",
    "addr:postcode":"x0a 0h0",
    "iso:country":"CA",
    "sg:address":"Bldg 953",
    "sg:city":"Iqaluit",
    "sg:classifiers":[
        {
            "category":"Food & Beverages",
            "subcategory":"Meat & Fish",
            "type":"Retail Goods"
        }
    ],
    "sg:phone":"+1 867 979 5563",
    "sg:postcode":"X0A 0H0",
    "sg:province":"NU",
    "wof:name":"Nunavut Fish & Meat Processing",
    "wof:placetype":"venue"
},
  "geometry": {"coordinates":[-68.5190200806,63.7514762878],"type":"Point"}
}