{
  "type": "Feature",
  "properties": {
    "addr:full":"294 Josephine St Wingham ON N0G 2W0",
    "addr:housenumber":"294",
    "addr:postcode":"n0g 2w0",
    "addr:street":"Josephine St",
    "iso:country":"CA",
    "sg:address":"294 Josephine St",
    "sg:city":"Wingham",
    "sg:classifiers":[
        {
            "category":"Personal",
            "subcategory":"Beauty Salon",
            "type":"Services"
        }
    ],
    "sg:phone":"+1 519 357 1337",
    "sg:postcode":"N0G 2W0",
    "sg:province":"ON",
    "wof:name":"Heads Up",
    "wof:placetype":"venue"
},
  "geometry": {"coordinates":[-81.31212600000001,43.887581],"type":"Point"}
}