{
  "type": "Feature",
  "properties": {
    "addr:full":"North Battleford SK S9A 0X3",
    "addr:postcode":"s9a 0x3",
    "iso:country":"CA",
    "sg:city":"North Battleford",
    "sg:classifiers":[
        {
            "category":"Home & Garden",
            "subcategory":"Household Appliances",
            "type":"Retail Goods"
        }
    ],
    "sg:phone":"+1 306 446 0000",
    "sg:postcode":"S9A 0X3",
    "sg:province":"SK",
    "sg:tags":[
        "cleaners",
        "vacuum"
    ],
    "wof:name":"Battleford's Allmake Vacuums",
    "wof:placetype":"venue"
},
  "geometry": {"coordinates":[-108.298751831,52.7858543396],"type":"Point"}
}