{
  "type": "Feature",
  "properties": {
    "addr:full":"70 Chatham St W Windsor ON N9A 5M6",
    "addr:housenumber":"70",
    "addr:postcode":"n9a 5m6",
    "addr:street":"Chatham St W",
    "iso:country":"CA",
    "sg:address":"70 Chatham St W",
    "sg:city":"Windsor",
    "sg:classifiers":[
        {
            "category":"Shopping",
            "subcategory":"Clothing, Apparel, & Fashions",
            "type":"Retail Goods"
        }
    ],
    "sg:phone":"+1 519 258 2930",
    "sg:postcode":"N9A 5M6",
    "sg:province":"ON",
    "sg:tags":[
        "furnishing"
    ],
    "wof:name":"Lou Myles Disegnatore",
    "wof:placetype":"venue"
},
  "geometry": {"coordinates":[-83.04016113279999,42.3181610107],"type":"Point"}
}