{
  "type": "Feature",
  "properties": {
    "addr:full":"143 Av Saint-Laurent Louiseville QC J5V 1J6",
    "addr:postcode":"j5v 1j6",
    "addr:street":"143 Av Saint-Laurent",
    "iso:country":"CA",
    "sg:address":"143 Av Saint-Laurent",
    "sg:city":"Louiseville",
    "sg:classifiers":[
        {
            "category":"Restaurant",
            "type":"Food & Drink"
        }
    ],
    "sg:phone":"+1 819 228 2141",
    "sg:postcode":"J5V 1J6",
    "sg:province":"QC",
    "wof:name":"Restaurant El Greco Pizzeria",
    "wof:placetype":"venue"
},
  "geometry": {"coordinates":[-72.943169,46.25581],"type":"Point"}
}