{
  "type": "Feature",
  "properties": {
    "addr:full":"Kelowna BC V1Y 1W1",
    "addr:postcode":"v1y 1w1",
    "iso:country":"CA",
    "sg:city":"Kelowna",
    "sg:classifiers":[
        {
            "category":"Shopping",
            "subcategory":"Gifts & Souvenirs",
            "type":"Retail Goods"
        }
    ],
    "sg:phone":"+1 250 763 8479",
    "sg:postcode":"V1Y 1W1",
    "sg:province":"BC",
    "sg:tags":[
        "shop"
    ],
    "wof:name":"Wine Art & Other Delights",
    "wof:placetype":"venue"
},
  "geometry": {"coordinates":[-119.491035,49.864372],"type":"Point"}
}