{
  "type": "Feature",
  "properties": {
    "addr:full":"802 Main St Dartmouth NS B2W 3V1",
    "addr:housenumber":"802",
    "addr:postcode":"b2w 3v1",
    "addr:street":"Main St",
    "iso:country":"CA",
    "sg:address":"802 Main St",
    "sg:city":"Dartmouth",
    "sg:classifiers":[
        {
            "category":"Shopping",
            "subcategory":"Hobbies, Toys, & Games",
            "type":"Retail Goods"
        }
    ],
    "sg:phone":"+1 902 434 0268",
    "sg:postcode":"B2W 3V1",
    "sg:province":"NS",
    "sg:tags":[
        "model",
        "supply"
    ],
    "wof:name":"George's Model Trains",
    "wof:placetype":"venue"
},
  "geometry": {"coordinates":[-63.4898376465,44.6981773376],"type":"Point"}
}