{
  "type": "Feature",
  "properties": {
    "addr:full":"Sainte-Martine QC J0S 1V0",
    "addr:postcode":"j0s 1v0",
    "iso:country":"CA",
    "sg:city":"Sainte-Martine",
    "sg:classifiers":[
        {
            "category":"Restaurant",
            "type":"Food & Drink"
        }
    ],
    "sg:phone":"+1 450 427 2180",
    "sg:postcode":"J0S 1V0",
    "sg:province":"QC",
    "sg:tags":[
        "caterer"
    ],
    "wof:name":"Buffet Double Delice Enr",
    "wof:placetype":"venue"
},
  "geometry": {"coordinates":[-73.7876205444,45.262462616],"type":"Point"}
}