{
  "type": "Feature",
  "properties": {
    "addr:full":"9725 62 Ave NW Edmonton AB T6E 0E4",
    "addr:housenumber":"9725",
    "addr:postcode":"t6e 0e4",
    "addr:street":"62 Ave Nw",
    "iso:country":"CA",
    "sg:address":"9725 62 Ave NW",
    "sg:city":"Edmonton",
    "sg:classifiers":[
        {
            "category":"Wholesale",
            "subcategory":"Machinery & Supplies",
            "type":"Manufacturing & Wholesale Goods"
        }
    ],
    "sg:phone":"+1 780 437 1260",
    "sg:postcode":"T6E 0E4",
    "sg:province":"AB",
    "sg:tags":[
        "fitting",
        "hose",
        "coupling",
        "plastic"
    ],
    "wof:name":"Goodall Rubber CO",
    "wof:placetype":"venue"
},
  "geometry": {"coordinates":[-113.480712891,53.4982223511],"type":"Point"}
}