{
  "type": "Feature",
  "properties": {
    "addr:full":"9385 120 St Delta BC V4C 6R9",
    "addr:housenumber":"9385",
    "addr:postcode":"v4c 6r9",
    "addr:street":"120 St",
    "iso:country":"CA",
    "sg:address":"9385 120 St",
    "sg:city":"Delta",
    "sg:classifiers":[
        {
            "category":"Banks & Credit Unions",
            "subcategory":"Bank",
            "type":"Services"
        }
    ],
    "sg:phone":"+1 604 585 9992",
    "sg:postcode":"V4C 6R9",
    "sg:province":"BC",
    "sg:tags":[
        "broker",
        "foreign",
        "dealer",
        "exchange"
    ],
    "wof:name":"A One Currency Exchange",
    "wof:placetype":"venue"
},
  "geometry": {"coordinates":[-122.890426636,49.1736984253],"type":"Point"}
}