{
  "type": "Feature",
  "properties": {
    "addr:full":"191 Church St Toronto ON M5B 1Y7",
    "addr:housenumber":"191",
    "addr:postcode":"m5b 1y7",
    "addr:street":"Church St",
    "iso:country":"CA",
    "sg:address":"191 Church St",
    "sg:city":"Toronto",
    "sg:classifiers":[
        {
            "category":"Insurance",
            "subcategory":"Insurance Agent",
            "type":"Services"
        }
    ],
    "sg:phone":"+1 416 367 5291",
    "sg:postcode":"M5B 1Y7",
    "sg:province":"ON",
    "wof:name":"Creaghan Mc Connell Group",
    "wof:placetype":"venue"
},
  "geometry": {"coordinates":[-79.376419,43.65527],"type":"Point"}
}