{
  "type": "Feature",
  "properties": {
    "addr:full":"3150 1 Ave NE Salmon Arm BC V1E 2B1",
    "addr:housenumber":"3150",
    "addr:postcode":"v1e 2b1",
    "addr:street":"1 Ave Ne",
    "iso:country":"CA",
    "sg:address":"3150 1 Ave NE",
    "sg:city":"Salmon Arm",
    "sg:classifiers":[
        {
            "category":"Building & Trades",
            "subcategory":"Construction",
            "type":"Services"
        }
    ],
    "sg:phone":"+1 250 832 4078",
    "sg:postcode":"V1E 2B1",
    "sg:province":"BC",
    "sg:tags":[
        "dry wall",
        "contractor"
    ],
    "wof:name":"Lorne Plett Drywall Contr",
    "wof:placetype":"venue"
},
  "geometry": {"coordinates":[-119.246917725,50.7006149292],"type":"Point"}
}