{
  "type": "Feature",
  "properties": {
    "addr:full":"25 Doxsee Ave S Campbellford ON K0L 1L0",
    "addr:housenumber":"25",
    "addr:postcode":"k0l 1l0",
    "addr:street":"Doxsee Ave S Campbellford",
    "iso:country":"CA",
    "sg:address":"25 Doxsee Ave S",
    "sg:city":"Campbellford",
    "sg:classifiers":[
        {
            "category":"Restaurant",
            "type":"Food & Drink"
        }
    ],
    "sg:phone":"+1 705 653 0385",
    "sg:postcode":"K0L 1L0",
    "sg:province":"ON",
    "wof:name":"Subway Sandwiches & Salads",
    "wof:placetype":"venue"
},
  "geometry": {"coordinates":[-77.79639400000001,44.307289],"type":"Point"}
}