{
  "type": "Feature",
  "properties": {
    "addr:full":"466 Ch DE LA Grande-Ligne Rigaud QC J0P 1P0",
    "addr:housenumber":"466",
    "addr:postcode":"j0p 1p0",
    "addr:street":"Ch De La Grande-Ligne",
    "iso:country":"CA",
    "sg:address":"466 Ch DE LA Grande-Ligne",
    "sg:city":"Rigaud",
    "sg:classifiers":[
        {
            "category":"Food & Beverages",
            "subcategory":"Groceries & Convenience Stores",
            "type":"Retail Goods"
        }
    ],
    "sg:phone":"+1 450 451 0520",
    "sg:postcode":"J0P 1P0",
    "sg:province":"QC",
    "sg:tags":[
        "grocer"
    ],
    "wof:name":"Marche Rigaud Metro",
    "wof:placetype":"venue"
},
  "geometry": {"coordinates":[-74.282982,45.479904],"type":"Point"}
}