{
  "type": "Feature",
  "properties": {
    "addr:full":"262 Dundas St London ON N6A 1H3",
    "addr:housenumber":"262",
    "addr:postcode":"n6a 1h3",
    "addr:street":"Dundas St",
    "iso:country":"CA",
    "sg:address":"262 Dundas St",
    "sg:city":"London",
    "sg:classifiers":[
        {
            "category":"Shopping",
            "subcategory":"News",
            "type":"Retail Goods"
        }
    ],
    "sg:phone":"+1 519 438 7374",
    "sg:postcode":"N6A 1H3",
    "sg:province":"ON",
    "sg:tags":[
        "store",
        "variety"
    ],
    "wof:name":"News Depot",
    "wof:placetype":"venue"
},
  "geometry": {"coordinates":[-81.2458648682,42.984916687],"type":"Point"}
}