{
  "type": "Feature",
  "properties": {
    "iso:country":"CA",
    "sg:address":"8720 Rue Hochelaga",
    "sg:city":"Montreal",
    "sg:classifiers":[
        {
            "category":"Cinema",
            "subcategory":"Movie Rental",
            "type":"Entertainment"
        }
    ],
    "sg:phone":"+1 514 353 8525",
    "sg:postcode":"H1L 2M7",
    "sg:province":"QC",
    "sg:tags":[
        "leasing",
        "video",
        "disc",
        "tape"
    ],
    "wof:name":"Video Super 3D",
    "wof:placetype":"venue"
},
  "geometry": {"coordinates":[-73.51950836180001,45.6016845703],"type":"Point"}
}