{
  "type": "Feature",
  "properties": {
    "iso:country":"CA",
    "sg:city":"Brampton",
    "sg:classifiers":[
        {
            "category":"Professional",
            "subcategory":"Lawyer & Legal Services",
            "type":"Services"
        }
    ],
    "sg:phone":"+1 905 791 6262",
    "sg:postcode":"L6T 4B5",
    "sg:province":"ON",
    "sg:tags":[
        "attorney"
    ],
    "wof:name":"Speigel Nichols Fox",
    "wof:placetype":"venue"
},
  "geometry": {"coordinates":[-79.7242889404,43.7168426514],"type":"Point"}
}