{
  "type": "Feature",
  "properties": {
    "addr:full":"2374 Yonge St Toronto ON M4P 2E6",
    "addr:housenumber":"2374",
    "addr:postcode":"m4p 2e6",
    "addr:street":"Yonge St",
    "iso:country":"CA",
    "sg:address":"2374 Yonge St",
    "sg:city":"Toronto",
    "sg:classifiers":[
        {
            "category":"Shopping",
            "subcategory":"Computers & Home Electronics",
            "type":"Retail Goods"
        }
    ],
    "sg:phone":"+1 416 486 6875",
    "sg:postcode":"M4P 2E6",
    "sg:province":"ON",
    "sg:tags":[
        "game",
        "video",
        "supply"
    ],
    "wof:name":"Electronics Boutique",
    "wof:placetype":"venue"
},
  "geometry": {"coordinates":[-79.3989639282,43.7088279724],"type":"Point"}
}