{
  "type": "Feature",
  "properties": {
    "iso:country":"CA",
    "sg:address":"900 Rue Saint-Charles E",
    "sg:city":"Longueuil",
    "sg:classifiers":[
        {
            "category":"Travel",
            "subcategory":"Hotels & Motels",
            "type":"Entertainment"
        }
    ],
    "sg:phone":"+1 450 646 8100",
    "sg:postcode":"J4H 3Y2",
    "sg:province":"QC",
    "wof:name":"Holiday Inn Longueuil",
    "wof:placetype":"venue"
},
  "geometry": {"coordinates":[-73.4988021851,45.5519104004],"type":"Point"}
}