{
  "type": "Feature",
  "properties": {
    "iso:country":"CA",
    "sg:address":"361 Mcrae Ave",
    "sg:city":"Ottawa",
    "sg:classifiers":[
        {
            "category":"Professional",
            "subcategory":"Art Services",
            "type":"Services"
        }
    ],
    "sg:phone":"+1 613 722 1414",
    "sg:postcode":"K1Z 8P4",
    "sg:province":"ON",
    "sg:tags":[
        "graphic",
        "advertising",
        "designer"
    ],
    "wof:name":"Mantle & Overall Comms",
    "wof:placetype":"venue"
},
  "geometry": {"coordinates":[-75.749557,45.395367],"type":"Point"}
}