{
  "type": "Feature",
  "properties": {
    "addr:full":"1827 36 St SE Calgary AB T2B 0X5",
    "addr:housenumber":"1827",
    "addr:postcode":"t2b 0x5",
    "addr:street":"36 St Se",
    "iso:country":"CA",
    "sg:address":"1827 36 St SE",
    "sg:city":"Calgary",
    "sg:classifiers":[
        {
            "category":"Autos & Motor Vehicles",
            "subcategory":"Automobile Sales",
            "type":"Retail Goods"
        }
    ],
    "sg:phone":"+1 403 248 5882",
    "sg:postcode":"T2B 0X5",
    "sg:province":"AB",
    "sg:tags":[
        "car",
        "dealer"
    ],
    "wof:name":"Corral Auto Mart",
    "wof:placetype":"venue"
},
  "geometry": {"coordinates":[-113.981819,51.037231],"type":"Point"}
}