{
  "type": "Feature",
  "properties": {
    "iso:country":"CA",
    "sg:address":"386 66E Rue O",
    "sg:city":"Charlesbourg",
    "sg:classifiers":[
        {
            "category":"Professional",
            "subcategory":"Art Services",
            "type":"Services"
        }
    ],
    "sg:phone":"+1 418 627 5266",
    "sg:postcode":"G1H 7G1",
    "sg:province":"QC",
    "sg:tags":[
        "graphic",
        "designer"
    ],
    "wof:name":"Etincelles Communications Enr",
    "wof:placetype":"venue"
},
  "geometry": {"coordinates":[-71.25127410890001,46.8456726074],"type":"Point"}
}