{
  "type": "Feature",
  "properties": {
    "addr:full":"812 Edmonton Trail NE Calgary AB T2E 3J6",
    "addr:housenumber":"812",
    "addr:postcode":"t2e 3j6",
    "addr:street":"Edmonton Trail Ne",
    "iso:country":"CA",
    "sg:address":"812 Edmonton Trail NE",
    "sg:city":"Calgary",
    "sg:classifiers":[
        {
            "category":"Real Estate",
            "subcategory":"Real Estate Agent",
            "type":"Services"
        }
    ],
    "sg:phone":"+1 403 230 8927",
    "sg:postcode":"T2E 3J6",
    "sg:province":"AB",
    "wof:name":"Xymet Management Ltd",
    "wof:placetype":"venue"
},
  "geometry": {"coordinates":[-114.054253,51.058945],"type":"Point"}
}