{
  "type": "Feature",
  "properties": {
    "iso:country":"CA",
    "sg:address":"37 Rue St-Cajetan",
    "sg:city":"Armagh",
    "sg:classifiers":[
        {
            "category":"Personal",
            "subcategory":"Beauty Salon",
            "type":"Services"
        }
    ],
    "sg:phone":"+1 418 466 2828",
    "sg:postcode":"G0R 1A0",
    "sg:province":"QC",
    "wof:name":"Salon Pierrette",
    "wof:placetype":"venue"
},
  "geometry": {"coordinates":[-70.5869293213,46.7419013977],"type":"Point"}
}