{
  "type": "Feature",
  "properties": {
    "addr:full":"5268 Marlborough Dr NE Calgary AB T2A 5L5",
    "addr:housenumber":"5268",
    "addr:postcode":"t2a 5l5",
    "addr:street":"Marlborough Dr Ne",
    "iso:country":"CA",
    "sg:address":"5268 Marlborough Dr NE",
    "sg:city":"Calgary",
    "sg:classifiers":[
        {
            "category":"Education",
            "subcategory":"Special Training",
            "type":"Public Place"
        }
    ],
    "sg:phone":"+1 403 273 7332",
    "sg:postcode":"T2A 5L5",
    "sg:province":"AB",
    "sg:tags":[
        "instruction",
        "driving"
    ],
    "wof:name":"Prepared Driving School",
    "wof:placetype":"venue"
},
  "geometry": {"coordinates":[-113.95926666299999,51.0602035522],"type":"Point"}
}