{
  "type": "Feature",
  "properties": {
    "addr:full":"738 Rue Victoria Edmundston NB E3V 3S9",
    "addr:housenumber":"738",
    "addr:postcode":"e3v 3s9",
    "addr:street":"Rue Victoria",
    "iso:country":"CA",
    "sg:address":"738 Rue Victoria",
    "sg:city":"Edmundston",
    "sg:classifiers":[
        {
            "category":"Wholesale",
            "subcategory":"Apparel",
            "type":"Manufacturing & Wholesale Goods"
        }
    ],
    "sg:phone":"+1 506 737 1800",
    "sg:postcode":"E3V 3S9",
    "sg:province":"NB",
    "sg:tags":[
        "label"
    ],
    "wof:name":"Whk Woven Labels Ltd",
    "wof:placetype":"venue"
},
  "geometry": {"coordinates":[-68.3426895142,47.3907775879],"type":"Point"}
}