{
  "type": "Feature",
  "properties": {
    "addr:full":"5312 114 Ave SE Calgary AB T2C 4T9",
    "addr:housenumber":"5312",
    "addr:postcode":"t2c 4t9",
    "addr:street":"114 Ave Se",
    "iso:country":"CA",
    "sg:address":"5312 114 Ave SE",
    "sg:city":"Calgary",
    "sg:classifiers":[
        {
            "category":"Freight",
            "type":"Transportation"
        }
    ],
    "sg:phone":"+1 403 203 7352",
    "sg:postcode":"T2C 4T9",
    "sg:province":"AB",
    "sg:tags":[
        "trucking"
    ],
    "wof:name":"Goliath Tractor Svc",
    "wof:placetype":"venue"
},
  "geometry": {"coordinates":[-113.955849,50.950703],"type":"Point"}
}