{
  "type": "Feature",
  "properties": {
    "iso:country":"CA",
    "sg:address":"2780 Jane St # Ll4",
    "sg:city":"North York",
    "sg:classifiers":[
        {
            "category":"Health Services",
            "subcategory":"Medical Lab",
            "type":"Services"
        }
    ],
    "sg:phone":"+1 416 740 7588",
    "sg:postcode":"M3N 2J2",
    "sg:province":"ON",
    "sg:tags":[
        "laboratory"
    ],
    "wof:name":"Canadian Medical Laboratories",
    "wof:placetype":"venue"
},
  "geometry": {"coordinates":[-79.515488,43.747826],"type":"Point"}
}