{
  "type": "Feature",
  "properties": {
    "addr:full":"320 Speers Rd Oakville ON L6K 3R9",
    "addr:housenumber":"320",
    "addr:postcode":"l6k 3r9",
    "addr:street":"Speers Rd",
    "iso:country":"CA",
    "sg:address":"320 Speers Rd",
    "sg:city":"Oakville",
    "sg:classifiers":[
        {
            "category":"Banks & Credit Unions",
            "subcategory":"Bank",
            "type":"Services"
        }
    ],
    "sg:phone":"+1 905 338 5222",
    "sg:postcode":"L6K 3R9",
    "sg:province":"ON",
    "wof:name":"Scotiabank",
    "wof:placetype":"venue"
},
  "geometry": {"coordinates":[-79.6927871704,43.4409561157],"type":"Point"}
}