{
  "type": "Feature",
  "properties": {
    "addr:full":"627 Rue Dalpe Saint-Amable QC J0L 1N0",
    "addr:housenumber":"627",
    "addr:postcode":"j0l 1n0",
    "addr:street":"Rue Dalpe",
    "iso:country":"CA",
    "sg:address":"627 Rue Dalpe",
    "sg:city":"Saint-Amable",
    "sg:classifiers":[
        {
            "category":"Professional",
            "type":"Services"
        }
    ],
    "sg:phone":"+1 450 922 6197",
    "sg:postcode":"J0L 1N0",
    "sg:province":"QC",
    "sg:tags":[
        "establishment",
        "salon",
        "tanning",
        "supply"
    ],
    "wof:name":"Bronze Tech Inc",
    "wof:placetype":"venue"
},
  "geometry": {"coordinates":[-73.309944,45.646858],"type":"Point"}
}