{
  "type": "Feature",
  "properties": {
    "addr:full":"Thornhill ON L4J 8H9",
    "addr:postcode":"l4j 8h9",
    "iso:country":"CA",
    "sg:city":"Thornhill",
    "sg:classifiers":[
        {
            "category":"Travel",
            "subcategory":"Travel Agent",
            "type":"Entertainment"
        }
    ],
    "sg:phone":"+1 905 762 0700",
    "sg:postcode":"L4J 8H9",
    "sg:province":"ON",
    "sg:tags":[
        "agency",
        "bureau"
    ],
    "wof:name":"Pars Tours",
    "wof:placetype":"venue"
},
  "geometry": {"coordinates":[-79.4225845337,43.8073272705],"type":"Point"}
}