{
  "type": "Feature",
  "properties": {
    "addr:full":"765 Boul Laval Laval QC H7S 2K4",
    "addr:housenumber":"765",
    "addr:postcode":"h7s 2k4",
    "addr:street":"Boul Laval",
    "iso:country":"CA",
    "sg:address":"765 Boul Laval",
    "sg:city":"Laval",
    "sg:classifiers":[
        {
            "category":"Organizations",
            "subcategory":"Religious Organization",
            "type":"Services"
        }
    ],
    "sg:phone":"+1 450 669 4631",
    "sg:postcode":"H7S 2K4",
    "sg:province":"QC",
    "sg:tags":[
        "church"
    ],
    "wof:name":"Eglise DE L'Ile Jesus",
    "wof:placetype":"venue"
},
  "geometry": {"coordinates":[-73.71968099999999,45.567242],"type":"Point"}
}