{
  "type": "Feature",
  "properties": {
    "addr:full":"901 8 St NW Slave Lake AB T0G 2A1",
    "addr:housenumber":"901 8",
    "addr:postcode":"t0g 2a1",
    "addr:street":"St Nw",
    "iso:country":"CA",
    "sg:address":"901 8 St NW",
    "sg:city":"Slave Lake",
    "sg:classifiers":[
        {
            "category":"Freight",
            "type":"Transportation"
        }
    ],
    "sg:phone":"+1 780 849 4360",
    "sg:postcode":"T0G 2A1",
    "sg:province":"AB",
    "sg:tags":[
        "field",
        "oil"
    ],
    "wof:name":"Baron Transport",
    "wof:placetype":"venue"
},
  "geometry": {"coordinates":[-114.782814,55.289902],"type":"Point"}
}