{
  "type": "Feature",
  "properties": {
    "addr:full":"110 Concord St S Ottawa ON K1S 0Z1",
    "addr:housenumber":"110",
    "addr:postcode":"k1s 0z1",
    "addr:street":"Concord St S",
    "iso:country":"CA",
    "sg:address":"110 Concord St S",
    "sg:city":"Ottawa",
    "sg:classifiers":[
        {
            "category":"Building & Trades",
            "subcategory":"Landscaping Services",
            "type":"Services"
        }
    ],
    "sg:phone":"+1 613 230 2131",
    "sg:postcode":"K1S 0Z1",
    "sg:province":"ON",
    "sg:tags":[
        "landscape",
        "contractor"
    ],
    "wof:name":"Abboud & Sons",
    "wof:placetype":"venue"
},
  "geometry": {"coordinates":[-75.677406,45.414085],"type":"Point"}
}