{
  "type": "Feature",
  "properties": {
    "iso:country":"CA",
    "sg:address":"943 Landslide Rd",
    "sg:city":"Sault Ste Marie",
    "sg:classifiers":[
        {
            "category":"Recreation",
            "type":"Entertainment"
        }
    ],
    "sg:phone":"+1 705 253 4712",
    "sg:postcode":"P6A 6J8",
    "sg:province":"ON",
    "sg:tags":[
        "amusement"
    ],
    "wof:name":"Mockingbird Hill Farm",
    "wof:placetype":"venue"
},
  "geometry": {"coordinates":[-84.2803649902,46.5945167542],"type":"Point"}
}