{
  "type": "Feature",
  "properties": {
    "addr:full":"22 Bebonang St M'Chigeeng ON P0P 1G0",
    "addr:housenumber":"22",
    "addr:postcode":"p0p 1g0",
    "addr:street":"Bebonang St",
    "iso:country":"CA",
    "sg:address":"22 Bebonang St",
    "sg:city":"M'Chigeeng",
    "sg:classifiers":[
        {
            "category":"Education",
            "subcategory":"Special Training",
            "type":"Public Place"
        }
    ],
    "sg:phone":"+1 705 377 5611",
    "sg:postcode":"P0P 1G0",
    "sg:province":"ON",
    "sg:tags":[
        "reading",
        "instruction",
        "improvement"
    ],
    "wof:name":"M'Chigeeng First Nation Edctn",
    "wof:placetype":"venue"
},
  "geometry": {"coordinates":[-82.162392,45.828045],"type":"Point"}
}