{
  "type": "Feature",
  "properties": {
    "addr:full":"Toronto ON M6P 1B3",
    "addr:postcode":"m6p 1b3",
    "iso:country":"CA",
    "sg:city":"Toronto",
    "sg:classifiers":[
        {
            "category":"Restaurant",
            "type":"Food & Drink"
        }
    ],
    "sg:phone":"+1 416 762 5511",
    "sg:postcode":"M6P 1B3",
    "sg:province":"ON",
    "sg:tags":[
        "out"
    ],
    "wof:name":"Krzystof Jozwik",
    "wof:placetype":"venue"
},
  "geometry": {"coordinates":[-79.459,43.655041],"type":"Point"}
}