{
  "type": "Feature",
  "properties": {
    "addr:full":"2056 Columbia Rossland BC V0G 1Y0",
    "addr:housenumber":"2056",
    "addr:postcode":"v0g 1y0",
    "addr:street":"Columbia",
    "iso:country":"CA",
    "sg:address":"2056 Columbia",
    "sg:city":"Rossland",
    "sg:classifiers":[
        {
            "category":"Organizations",
            "subcategory":"Community Association",
            "type":"Services"
        }
    ],
    "sg:phone":"+1 250 362 7785",
    "sg:postcode":"V0G 1Y0",
    "sg:province":"BC",
    "sg:tags":[
        "fraternal"
    ],
    "wof:name":"Fraternal Order of Eagle",
    "wof:placetype":"venue"
},
  "geometry": {"coordinates":[-117.79924800000001,49.077061],"type":"Point"}
}