{
  "type": "Feature",
  "properties": {
    "iso:country":"CA",
    "sg:address":"154 Rue Saint-Louis",
    "sg:city":"Saint-Eustache",
    "sg:classifiers":[
        {
            "category":"Health Services",
            "subcategory":"Nursing And Care Facility",
            "type":"Services"
        }
    ],
    "sg:phone":"+1 450 472 9002",
    "sg:postcode":"J7R 1Y2",
    "sg:province":"QC",
    "sg:tags":[
        "home",
        "retirement",
        "community"
    ],
    "wof:name":"Pavillon St-Louis Inc",
    "wof:placetype":"venue"
},
  "geometry": {"coordinates":[-73.8889083862,45.5582809448],"type":"Point"}
}