{
  "type": "Feature",
  "properties": {
    "addr:full":"Neepawa MB R0J 1H0",
    "addr:postcode":"r0j 1h0",
    "iso:country":"CA",
    "sg:city":"Neepawa",
    "sg:classifiers":[
        {
            "category":"Personal",
            "type":"Services"
        }
    ],
    "sg:phone":"+1 204 476 5928",
    "sg:postcode":"R0J 1H0",
    "sg:province":"MB",
    "sg:tags":[
        "therapist",
        "massage"
    ],
    "wof:name":"Darlene's Massage & Hydrothrpy",
    "wof:placetype":"venue"
},
  "geometry": {"coordinates":[-99.465065,50.228504],"type":"Point"}
}