{
  "type": "Feature",
  "properties": {
    "addr:full":"9305 Jubilee Rd Summerland BC V0H 1Z0",
    "addr:housenumber":"9305",
    "addr:postcode":"v0h 1z0",
    "addr:street":"Jubilee Rd",
    "iso:country":"CA",
    "sg:address":"9305 Jubilee Rd",
    "sg:city":"Summerland",
    "sg:classifiers":[
        {
            "category":"Retail",
            "subcategory":"Auto Repair",
            "type":"Services"
        }
    ],
    "sg:phone":"+1 250 494 7471",
    "sg:postcode":"V0H 1Z0",
    "sg:province":"BC",
    "sg:tags":[
        "repairing",
        "automobile"
    ],
    "wof:name":"Big O Tires",
    "wof:placetype":"venue"
},
  "geometry": {"coordinates":[-119.676575,49.603123],"type":"Point"}
}