{
  "type": "Feature",
  "properties": {
    "addr:full":"6 Rue Saint-Michel Vaudreuil-Dorion QC J7V 1E7",
    "addr:housenumber":"6",
    "addr:postcode":"j7v 1e7",
    "addr:street":"Rue Saint-Michel",
    "iso:country":"CA",
    "sg:address":"6 Rue Saint-Michel",
    "sg:city":"Vaudreuil-Dorion",
    "sg:classifiers":[
        {
            "category":"Building & Trades",
            "subcategory":"Construction",
            "type":"Services"
        }
    ],
    "sg:phone":"+1 450 424 2425",
    "sg:postcode":"J7V 1E7",
    "sg:province":"QC",
    "sg:tags":[
        "contractor"
    ],
    "wof:name":"Habitations Raymond",
    "wof:placetype":"venue"
},
  "geometry": {"coordinates":[-74.02578,45.399258],"type":"Point"}
}