{
  "type": "Feature",
  "properties": {
    "addr:full":"445 Av Marconi Sainte-Foy QC G1N 4A7",
    "addr:housenumber":"445",
    "addr:postcode":"g1n 4a7",
    "addr:street":"Av Marconi",
    "iso:country":"CA",
    "sg:address":"445 Av Marconi",
    "sg:city":"Sainte-Foy",
    "sg:classifiers":[
        {
            "category":"Manufacturing",
            "subcategory":"Rubber & Plastics",
            "type":"Manufacturing & Wholesale Goods"
        }
    ],
    "sg:phone":"+1 418 683 1724",
    "sg:postcode":"G1N 4A7",
    "sg:province":"QC",
    "sg:tags":[
        "pulley",
        "covering"
    ],
    "wof:name":"Electro Mecanik Playford",
    "wof:placetype":"venue"
},
  "geometry": {"coordinates":[-71.276619,46.797127],"type":"Point"}
}