{
  "type": "Feature",
  "properties": {
    "iso:country":"CA",
    "sg:address":"2203 Rue Harmony",
    "sg:city":"Montreal",
    "sg:classifiers":[
        {
            "category":"Retail",
            "subcategory":"Auto Repair",
            "type":"Services"
        }
    ],
    "sg:phone":"+1 514 526 2151",
    "sg:postcode":"H2K 3R1",
    "sg:province":"QC",
    "sg:tags":[
        "body",
        "automobile",
        "painting"
    ],
    "wof:name":"Jean Claude Auto Reparations",
    "wof:placetype":"venue"
},
  "geometry": {"coordinates":[-73.557404,45.531242],"type":"Point"}
}