{
  "type": "Feature",
  "properties": {
    "addr:full":"St Catharines ON L2P 3Y1",
    "addr:postcode":"l2p 3y1",
    "iso:country":"CA",
    "sg:city":"St Catharines",
    "sg:classifiers":[
        {
            "category":"Building & Trades",
            "subcategory":"Construction",
            "type":"Services"
        }
    ],
    "sg:phone":"+1 905 680 6000",
    "sg:postcode":"L2P 3Y1",
    "sg:province":"ON",
    "sg:tags":[
        "general",
        "contractor"
    ],
    "wof:name":"Silvergate Homes Ltd",
    "wof:placetype":"venue"
},
  "geometry": {"coordinates":[-79.20593261720001,43.1401863098],"type":"Point"}
}