{
  "type": "Feature",
  "properties": {
    "addr:full":"PO Box 32 L'Anse Au Loup NL A0K 3L0",
    "addr:housenumber":"po box 32",
    "addr:postcode":"a0k 3l0",
    "addr:street":"Au Loup",
    "iso:country":"CA",
    "sg:address":"PO Box 32",
    "sg:city":"L'Anse Au Loup",
    "sg:classifiers":[
        {
            "category":"Organizations",
            "subcategory":"Religious Organization",
            "type":"Services"
        }
    ],
    "sg:phone":"+1 709 927 5204",
    "sg:postcode":"A0K 3L0",
    "sg:province":"NL",
    "sg:tags":[
        "church"
    ],
    "wof:name":"Gospel Hall",
    "wof:placetype":"venue"
},
  "geometry": {"coordinates":[-56.8312301636,51.5265693665],"type":"Point"}
}