{
  "type": "Feature",
  "properties": {
    "addr:full":"770 Boul Industriel Granby QC J2G 9J5",
    "addr:housenumber":"770",
    "addr:postcode":"j2g 9j5",
    "addr:street":"Boul Industriel",
    "iso:country":"CA",
    "sg:address":"770 Boul Industriel",
    "sg:city":"Granby",
    "sg:classifiers":[
        {
            "category":"Retail",
            "subcategory":"Repair Shop",
            "type":"Services"
        }
    ],
    "sg:phone":"+1 450 777 1471",
    "sg:postcode":"J2G 9J5",
    "sg:province":"QC",
    "sg:tags":[
        "steel",
        "welding"
    ],
    "wof:name":"Industries Prometal",
    "wof:placetype":"venue"
},
  "geometry": {"coordinates":[-72.7540512085,45.3889770508],"type":"Point"}
}