{
  "type": "Feature",
  "properties": {
    "addr:full":"Burns Lake BC V0J 1E0",
    "addr:postcode":"bc v0j 1e0",
    "addr:street":"Burns Lake",
    "iso:country":"CA",
    "sg:city":"Burns Lake",
    "sg:classifiers":[
        {
            "category":"Professional",
            "subcategory":"Computer Services",
            "type":"Services"
        }
    ],
    "sg:phone":"+1 250 692 3201",
    "sg:postcode":"V0J 1E0",
    "sg:province":"BC",
    "sg:tags":[
        "repair",
        "dealer",
        "equipment"
    ],
    "wof:name":"Computers Etcetera",
    "wof:placetype":"venue"
},
  "geometry": {"coordinates":[-125.75868199999999,54.226593],"type":"Point"}
}