{
  "type": "Feature",
  "properties": {
    "addr:full":"664 Front St Quesnel BC V2J 2K8",
    "addr:housenumber":"664",
    "addr:postcode":"v2j 2k8",
    "addr:street":"Front St",
    "iso:country":"CA",
    "sg:address":"664 Front St",
    "sg:city":"Quesnel",
    "sg:classifiers":[
        {
            "category":"Shopping",
            "subcategory":"Pharmacy",
            "type":"Retail Goods"
        }
    ],
    "sg:phone":"+1 250 991 5155",
    "sg:postcode":"V2J 2K8",
    "sg:province":"BC",
    "wof:name":"Good Healh Pharmacy Ltd",
    "wof:placetype":"venue"
},
  "geometry": {"coordinates":[-122.498833,52.983418],"type":"Point"}
}