{
  "type": "Feature",
  "properties": {
    "addr:full":"5 Walnut St # A Pine Falls MB R0E 1M0",
    "addr:housenumber":"5",
    "addr:postcode":"r0e 1m0",
    "addr:street":"Walnut St # A Pine",
    "iso:country":"CA",
    "sg:address":"5 Walnut St # A",
    "sg:city":"Pine Falls",
    "sg:classifiers":[
        {
            "category":"Social Services",
            "subcategory":"Child Care",
            "type":"Services"
        }
    ],
    "sg:phone":"+1 204 367 2601",
    "sg:postcode":"R0E 1M0",
    "sg:province":"MB",
    "wof:name":"Happy Tots Place",
    "wof:placetype":"venue"
},
  "geometry": {"coordinates":[-96.217575,50.567356],"type":"Point"}
}