{
  "type": "Feature",
  "properties": {
    "addr:full":"21 Clements St Yarmouth NS B5A 2B9",
    "addr:housenumber":"21",
    "addr:postcode":"b5a 2b9",
    "addr:street":"Clements St",
    "iso:country":"CA",
    "sg:address":"21 Clements St",
    "sg:city":"Yarmouth",
    "sg:classifiers":[
        {
            "category":"Travel",
            "subcategory":"Hotels & Motels",
            "type":"Entertainment"
        }
    ],
    "sg:phone":"+1 902 742 0079",
    "sg:postcode":"B5A 2B9",
    "sg:province":"NS",
    "sg:tags":[
        "breakfast",
        "accommodation",
        "bed"
    ],
    "wof:name":"Clementines Bed & Breakfast",
    "wof:placetype":"venue"
},
  "geometry": {"coordinates":[-66.1141662598,43.8357505798],"type":"Point"}
}