{
  "type": "Feature",
  "properties": {
    "addr:full":"Buffalo Head Prairie AB T0H 4A0",
    "addr:postcode":"t0h 4a0",
    "iso:country":"CA",
    "sg:city":"Buffalo Head Prairie",
    "sg:classifiers":[
        {
            "category":"Retail",
            "subcategory":"Auto Repair",
            "type":"Services"
        }
    ],
    "sg:phone":"+1 780 928 2602",
    "sg:postcode":"T0H 4A0",
    "sg:province":"AB",
    "sg:tags":[
        "repairing",
        "automobile"
    ],
    "wof:name":"Tompkins Mobile Svc",
    "wof:placetype":"venue"
},
  "geometry": {"coordinates":[-116.34927399999999,58.04937],"type":"Point"}
}