{
  "type": "Feature",
  "properties": {
    "addr:full":"Rouyn-Noranda QC J9X 2A5",
    "addr:postcode":"j9x 2a5",
    "iso:country":"CA",
    "sg:city":"Rouyn-Noranda",
    "sg:classifiers":[
        {
            "category":"Professional",
            "subcategory":"Business Services",
            "type":"Services"
        }
    ],
    "sg:phone":"+1 819 762 6333",
    "sg:postcode":"J9X 2A5",
    "sg:province":"QC",
    "wof:name":"Congesis Abitibi-Temiscamingue",
    "wof:placetype":"venue"
},
  "geometry": {"coordinates":[-79.017899,48.247494],"type":"Point"}
}