{
  "type": "Feature",
  "properties": {
    "addr:full":"140 Milner Ave Scarborough ON M1S 3R3",
    "addr:housenumber":"140",
    "addr:postcode":"m1s 3r3",
    "addr:street":"Milner Ave",
    "iso:country":"CA",
    "sg:address":"140 Milner Ave",
    "sg:city":"Scarborough",
    "sg:classifiers":[
        {
            "category":"Wholesale",
            "subcategory":"Seafood",
            "type":"Manufacturing & Wholesale Goods"
        }
    ],
    "sg:phone":"+1 416 292 5565",
    "sg:postcode":"M1S 3R3",
    "sg:province":"ON",
    "sg:tags":[
        "equipment",
        "supply"
    ],
    "wof:name":"Great Lake Seafood CO",
    "wof:placetype":"venue"
},
  "geometry": {"coordinates":[-79.246315,43.785439],"type":"Point"}
}