{
  "type": "Feature",
  "properties": {
    "addr:full":"4719 48th Ave Redwater AB T0A 2W0",
    "addr:housenumber":"4719",
    "addr:postcode":"t0a 2w0",
    "addr:street":"48Th Ave",
    "iso:country":"CA",
    "sg:address":"4719 48th Ave",
    "sg:city":"Redwater",
    "sg:classifiers":[
        {
            "category":"Organizations",
            "subcategory":"Professional Association",
            "type":"Services"
        }
    ],
    "sg:phone":"+1 780 942 3482",
    "sg:postcode":"T0A 2W0",
    "sg:province":"AB",
    "sg:tags":[
        "club"
    ],
    "wof:name":"Derick Hall",
    "wof:placetype":"venue"
},
  "geometry": {"coordinates":[-113.105011,53.948822],"type":"Point"}
}