{
  "type": "Feature",
  "properties": {
    "addr:full":"4731 Burke Rd Port Alberni BC V9Y 5P1",
    "addr:housenumber":"4731",
    "addr:postcode":"v9y 5p1",
    "addr:street":"Burke Rd",
    "iso:country":"CA",
    "sg:address":"4731 Burke Rd",
    "sg:city":"Port Alberni",
    "sg:classifiers":[
        {
            "category":"Organizations",
            "subcategory":"Religious Organization",
            "type":"Services"
        }
    ],
    "sg:phone":"+1 250 723 8912",
    "sg:postcode":"V9Y 5P1",
    "sg:province":"BC",
    "sg:tags":[
        "church"
    ],
    "wof:name":"Holy Family & Notre Dame",
    "wof:placetype":"venue"
},
  "geometry": {"coordinates":[-124.809822,49.260887],"type":"Point"}
}