{
  "type": "Feature",
  "properties": {
    "addr:full":"1051 Main St Hampton NB E5N 6E9",
    "addr:housenumber":"1051",
    "addr:postcode":"e5n 6e9",
    "addr:street":"Main St",
    "iso:country":"CA",
    "sg:address":"1051 Main St",
    "sg:city":"Hampton",
    "sg:classifiers":[
        {
            "category":"Restaurant",
            "type":"Food & Drink"
        }
    ],
    "sg:phone":"+1 506 832 3153",
    "sg:postcode":"E5N 6E9",
    "sg:province":"NB",
    "wof:name":"Kozy Korner Restaurant",
    "wof:placetype":"venue"
},
  "geometry": {"coordinates":[-65.8361587524,45.5415496826],"type":"Point"}
}