{
  "type": "Feature",
  "properties": {
    "iso:country":"CA",
    "sg:address":"1325 3rd Ave",
    "sg:city":"Dawson",
    "sg:classifiers":[
        {
            "category":"Building & Trades",
            "subcategory":"Construction",
            "type":"Services"
        }
    ],
    "sg:phone":"+1 867 993 5716",
    "sg:postcode":"Y0B 1G0",
    "sg:province":"YT",
    "sg:tags":[
        "woodworker"
    ],
    "wof:name":"Williams Construction",
    "wof:placetype":"venue"
},
  "geometry": {"coordinates":[-139.427276611,64.065284729],"type":"Point"}
}