{
  "type": "Feature",
  "properties": {
    "iso:country":"CA",
    "sg:address":"637 King St E",
    "sg:city":"Cambridge",
    "sg:classifiers":[
        {
            "category":"Banks & Credit Unions",
            "subcategory":"Bank",
            "type":"Services"
        }
    ],
    "sg:phone":"+1 519 653 2388",
    "sg:postcode":"N3H 3N7",
    "sg:province":"ON",
    "wof:name":"Royal Bank Financial Group",
    "wof:placetype":"venue"
},
  "geometry": {"coordinates":[-80.359085,43.396381],"type":"Point"}
}