{
  "type": "Feature",
  "properties": {
    "addr:full":"169 Daniel Ave Ottawa ON K1Y 0E1",
    "addr:housenumber":"169",
    "addr:postcode":"k1y 0e1",
    "addr:street":"Daniel Ave",
    "iso:country":"CA",
    "sg:address":"169 Daniel Ave",
    "sg:city":"Ottawa",
    "sg:classifiers":[
        {
            "category":"Professional",
            "subcategory":"Management & Consulting",
            "type":"Services"
        }
    ],
    "sg:phone":"+1 613 722 8707",
    "sg:postcode":"K1Y 0E1",
    "sg:province":"ON",
    "sg:tags":[
        "consultant",
        "business"
    ],
    "wof:name":"Process Inc",
    "wof:placetype":"venue"
},
  "geometry": {"coordinates":[-75.747314,45.402946],"type":"Point"}
}