{
  "type": "Feature",
  "properties": {
    "addr:full":"4920 Victoria Dr Vancouver BC V5P 3T6",
    "addr:housenumber":"4920",
    "addr:postcode":"v5p 3t6",
    "addr:street":"Victoria Dr",
    "iso:country":"CA",
    "sg:address":"4920 Victoria Dr",
    "sg:city":"Vancouver",
    "sg:classifiers":[
        {
            "category":"Wholesale",
            "subcategory":"Furniture",
            "type":"Manufacturing & Wholesale Goods"
        }
    ],
    "sg:phone":"+1 604 323 0233",
    "sg:postcode":"V5P 3T6",
    "sg:province":"BC",
    "sg:tags":[
        "mattress"
    ],
    "wof:name":"D & K Mfg Distributing",
    "wof:placetype":"venue"
},
  "geometry": {"coordinates":[-123.06509399399999,49.239730835],"type":"Point"}
}