{
  "type": "Feature",
  "properties": {
    "addr:full":"3950 Biggs Rd Nanaimo BC V9T 5P9",
    "addr:housenumber":"3950",
    "addr:postcode":"v9t 5p9",
    "addr:street":"Biggs Rd",
    "iso:country":"CA",
    "sg:address":"3950 Biggs Rd",
    "sg:city":"Nanaimo",
    "sg:classifiers":[
        {
            "category":"Real Estate",
            "subcategory":"Real Estate Operator",
            "type":"Services"
        }
    ],
    "sg:phone":"+1 250 751 3048",
    "sg:postcode":"V9T 5P9",
    "sg:province":"BC",
    "sg:tags":[
        "mobile",
        "home",
        "community"
    ],
    "wof:name":"Deerwood Place Estates Ltd",
    "wof:placetype":"venue"
},
  "geometry": {"coordinates":[-124.04483,49.206833],"type":"Point"}
}