{
  "type": "Feature",
  "properties": {
    "addr:full":"5445 West Blvd Vancouver BC V6M 3W5",
    "addr:housenumber":"5445",
    "addr:postcode":"v6m 3w5",
    "addr:street":"West Blvd",
    "iso:country":"CA",
    "sg:address":"5445 West Blvd",
    "sg:city":"Vancouver",
    "sg:classifiers":[
        {
            "category":"Building & Trades",
            "subcategory":"Plumbing",
            "type":"Services"
        }
    ],
    "sg:phone":"+1 604 266 2720",
    "sg:postcode":"V6M 3W5",
    "sg:province":"BC",
    "sg:tags":[
        "sheet",
        "work",
        "metal",
        "contractor"
    ],
    "wof:name":"Kerrisdale Heating & Sheet Mtl",
    "wof:placetype":"venue"
},
  "geometry": {"coordinates":[-123.15570831300001,49.2370147705],"type":"Point"}
}