{
  "type": "Feature",
  "properties": {
    "addr:full":"930 Rue Aubry Saint-Jean-Sur-Richelieu QC J3B 2H9",
    "addr:housenumber":"930",
    "addr:postcode":"j3b 2h9",
    "addr:street":"Rue Aubry",
    "iso:country":"CA",
    "sg:address":"930 Rue Aubry",
    "sg:city":"Saint-Jean-Sur-Richelieu",
    "sg:classifiers":[
        {
            "category":"Building & Trades",
            "subcategory":"Plumbing",
            "type":"Services"
        }
    ],
    "sg:phone":"+1 450 346 5526",
    "sg:postcode":"J3B 2H9",
    "sg:province":"QC",
    "sg:tags":[
        "conditioning",
        "air",
        "refrigeration",
        "system",
        "contractor"
    ],
    "wof:name":"Dugre & Bonneau",
    "wof:placetype":"venue"
},
  "geometry": {"coordinates":[-73.2911148071,45.3091201782],"type":"Point"}
}