{
  "type": "Feature",
  "properties": {
    "addr:full":"Toronto ON M4P 2C6",
    "addr:postcode":"m4p 2c6",
    "iso:country":"CA",
    "sg:city":"Toronto",
    "sg:classifiers":[
        {
            "category":"Health Services",
            "subcategory":"Doctor",
            "type":"Services"
        }
    ],
    "sg:phone":"+1 416 486 1136",
    "sg:postcode":"M4P 2C6",
    "sg:province":"ON",
    "sg:tags":[
        "dentist"
    ],
    "wof:name":"Belman, Noah DDS",
    "wof:placetype":"venue"
},
  "geometry": {"coordinates":[-79.398293,43.707249],"type":"Point"}
}