{
  "type": "Feature",
  "properties": {
    "addr:full":"21 Harvard Cres Saskatoon SK S7H 3R2",
    "addr:housenumber":"21",
    "addr:postcode":"s7h 3r2",
    "addr:street":"Harvard Cres",
    "iso:country":"CA",
    "sg:address":"21 Harvard Cres",
    "sg:city":"Saskatoon",
    "sg:classifiers":[
        {
            "category":"Professional",
            "subcategory":"Management & Consulting",
            "type":"Services"
        }
    ],
    "sg:phone":"+1 306 477 1076",
    "sg:postcode":"S7H 3R2",
    "sg:province":"SK",
    "sg:tags":[
        "consultant",
        "business"
    ],
    "wof:name":"Hiebert Group",
    "wof:placetype":"venue"
},
  "geometry": {"coordinates":[-106.601601,52.12532],"type":"Point"}
}