{
  "type": "Feature",
  "properties": {
    "addr:full":"Rosedale Point Geraldton ON P0T 1M0",
    "addr:postcode":"p0t 1m0",
    "addr:street":"Rosedale",
    "iso:country":"CA",
    "sg:address":"Rosedale Point",
    "sg:city":"Geraldton",
    "sg:classifiers":[
        {
            "category":"Freight",
            "type":"Transportation"
        }
    ],
    "sg:phone":"+1 807 854 0711",
    "sg:postcode":"P0T 1M0",
    "sg:province":"ON",
    "sg:tags":[
        "trucking"
    ],
    "wof:name":"Manitoulin Transport Inc",
    "wof:placetype":"venue"
},
  "geometry": {"coordinates":[-86.95001999999999,49.719582],"type":"Point"}
}