{
  "type": "Feature",
  "properties": {
    "addr:full":"174 Clement St Papineauville QC J0V 1R0",
    "addr:housenumber":"174",
    "addr:postcode":"j0v 1r0",
    "addr:street":"Clement St",
    "iso:country":"CA",
    "sg:address":"174 Clement St",
    "sg:city":"Papineauville",
    "sg:classifiers":[
        {
            "category":"Building & Trades",
            "subcategory":"Construction",
            "type":"Services"
        }
    ],
    "sg:phone":"+1 819 427 5532",
    "sg:postcode":"J0V 1R0",
    "sg:province":"QC",
    "sg:tags":[
        "excavating",
        "contractor"
    ],
    "wof:name":"Emilio Seguin Ltee",
    "wof:placetype":"venue"
},
  "geometry": {"coordinates":[-75.021614,45.618641],"type":"Point"}
}