{
  "type": "Feature",
  "properties": {
    "addr:full":"2411 Eglinton Ave W York ON M6M 1S8",
    "addr:housenumber":"2411",
    "addr:postcode":"m6m 1s8",
    "addr:street":"Eglinton Ave W",
    "iso:country":"CA",
    "sg:address":"2411 Eglinton Ave W",
    "sg:city":"York",
    "sg:classifiers":[
        {
            "category":"Real Estate",
            "subcategory":"Real Estate Agent",
            "type":"Services"
        }
    ],
    "sg:phone":"+1 416 244 6413",
    "sg:postcode":"M6M 1S8",
    "sg:province":"ON",
    "wof:name":"Seneca Real Estate Ltd",
    "wof:placetype":"venue"
},
  "geometry": {"coordinates":[-79.46569824220001,43.6917533875],"type":"Point"}
}