{
  "type": "Feature",
  "properties": {
    "iso:country":"CA",
    "sg:address":"12311 55 St NW",
    "sg:city":"Edmonton",
    "sg:classifiers":[
        {
            "category":"Organizations",
            "subcategory":"Religious Organization",
            "type":"Services"
        }
    ],
    "sg:phone":"+1 780 474 2805",
    "sg:postcode":"T5W 5G1",
    "sg:province":"AB",
    "sg:tags":[
        "church"
    ],
    "wof:name":"Our Lady of Fatima Catholic",
    "wof:placetype":"venue"
},
  "geometry": {"coordinates":[-113.425857544,53.5786399841],"type":"Point"}
}