{
  "type": "Feature",
  "properties": {
    "iso:country":"CA",
    "sg:address":"30 Main St S",
    "sg:city":"Kenora",
    "sg:classifiers":[
        {
            "category":"Health Services",
            "subcategory":"Optometrist",
            "type":"Services"
        }
    ],
    "sg:phone":"+1 807 468 7047",
    "sg:postcode":"P9N 1S7",
    "sg:province":"ON",
    "wof:name":"Girard, M J OD",
    "wof:placetype":"venue"
},
  "geometry": {"coordinates":[-94.48989105219999,49.7682342529],"type":"Point"}
}