{
  "type": "Feature",
  "properties": {
    "addr:full":"Bon-Conseil QC J0C 1A0",
    "addr:postcode":"j0c 1a0",
    "addr:street":"Bon-Conseil",
    "iso:country":"CA",
    "sg:city":"Bon-Conseil",
    "sg:classifiers":[
        {
            "category":"Wholesale",
            "subcategory":"Farm Supplies",
            "type":"Manufacturing & Wholesale Goods"
        }
    ],
    "sg:phone":"+1 819 336 5700",
    "sg:postcode":"J0C 1A0",
    "sg:province":"QC",
    "wof:name":"Premix DE LA Ferme Enr",
    "wof:placetype":"venue"
},
  "geometry": {"coordinates":[-72.373665,45.975559],"type":"Point"}
}