{
  "type": "Feature",
  "properties": {
    "iso:country":"CA",
    "sg:city":"Garden Bay",
    "sg:classifiers":[
        {
            "category":"Manufacturing",
            "subcategory":"Petroleum Products",
            "type":"Manufacturing & Wholesale Goods"
        }
    ],
    "sg:phone":"+1 604 883 9910",
    "sg:postcode":"V0N 1S0",
    "sg:province":"BC",
    "sg:tags":[
        "oil",
        "recovery"
    ],
    "wof:name":"Roosendal Farms",
    "wof:placetype":"venue"
},
  "geometry": {"coordinates":[-123.97167968799999,49.6389694214],"type":"Point"}
}