{
  "type": "Feature",
  "properties": {
    "addr:full":"Edmonton AB T6E 5L1",
    "addr:postcode":"t6e 5l1",
    "iso:country":"CA",
    "sg:city":"Edmonton",
    "sg:classifiers":[
        {
            "category":"Real Estate",
            "subcategory":"Architect",
            "type":"Services"
        }
    ],
    "sg:phone":"+1 780 465 5654",
    "sg:postcode":"T6E 5L1",
    "sg:province":"AB",
    "wof:name":"Lam Matichuk Architects",
    "wof:placetype":"venue"
},
  "geometry": {"coordinates":[-113.458298,53.485085],"type":"Point"}
}