{
  "type": "Feature",
  "properties": {
    "addr:full":"11177 Rue Hamon Montreal QC H3M 3E4",
    "addr:housenumber":"11177",
    "addr:postcode":"h3m 3e4",
    "addr:street":"Rue Hamon",
    "iso:country":"CA",
    "sg:address":"11177 Rue Hamon",
    "sg:city":"Montreal",
    "sg:classifiers":[
        {
            "category":"Wholesale",
            "subcategory":"Drugs",
            "type":"Manufacturing & Wholesale Goods"
        }
    ],
    "sg:phone":"+1 514 335 0310",
    "sg:postcode":"H3M 3E4",
    "sg:province":"QC",
    "sg:tags":[
        "pharmaceutical",
        "product"
    ],
    "wof:name":"Laboratoires Omega Ltee",
    "wof:placetype":"venue"
},
  "geometry": {"coordinates":[-73.68182400000001,45.540642],"type":"Point"}
}