{
  "type": "Feature",
  "properties": {
    "iso:country":"CA",
    "sg:city":"Mississauga",
    "sg:classifiers":[
        {
            "category":"Retail",
            "subcategory":"Auto Repair",
            "type":"Services"
        }
    ],
    "sg:phone":"+1 905 678 8364",
    "sg:postcode":"L5S 1K4",
    "sg:province":"ON",
    "sg:tags":[
        "repairing",
        "automobile"
    ],
    "wof:name":"Conti Automotive & Equipment",
    "wof:placetype":"venue"
},
  "geometry": {"coordinates":[-79.673538,43.689747],"type":"Point"}
}