{
  "type": "Feature",
  "properties": {
    "addr:full":"54 Alice St Waterford ON N0E 1Y0",
    "addr:housenumber":"54",
    "addr:postcode":"n0e 1y0",
    "addr:street":"Alice St",
    "iso:country":"CA",
    "sg:address":"54 Alice St",
    "sg:city":"Waterford",
    "sg:classifiers":[
        {
            "category":"Sports & Exercise",
            "subcategory":"Bowling",
            "type":"Entertainment"
        }
    ],
    "sg:phone":"+1 519 443 5341",
    "sg:postcode":"N0E 1Y0",
    "sg:province":"ON",
    "sg:tags":[
        "center"
    ],
    "wof:name":"Waterford Bowl & Pizzeria",
    "wof:placetype":"venue"
},
  "geometry": {"coordinates":[-80.29302978520001,42.9342765808],"type":"Point"}
}