{
  "type": "Feature",
  "properties": {
    "iso:country":"CA",
    "sg:address":"616 Main St",
    "sg:city":"Gravelbourg",
    "sg:classifiers":[
        {
            "category":"Food & Beverages",
            "subcategory":"Liquor & Beverages",
            "type":"Retail Goods"
        }
    ],
    "sg:phone":"+1 306 648 4412",
    "sg:postcode":"S0H 1X0",
    "sg:province":"SK",
    "sg:tags":[
        "government"
    ],
    "wof:name":"Liquor Board Store",
    "wof:placetype":"venue"
},
  "geometry": {"coordinates":[-106.55741882300001,49.8748703003],"type":"Point"}
}