{
  "type": "Feature",
  "properties": {
    "addr:full":"3329 Forrestdale Cir Mississauga ON L5N 6X5",
    "addr:housenumber":"3329",
    "addr:postcode":"l5n 6x5",
    "addr:street":"Forrestdale Cir",
    "iso:country":"CA",
    "sg:address":"3329 Forrestdale Cir",
    "sg:city":"Mississauga",
    "sg:classifiers":[
        {
            "category":"Wholesale",
            "subcategory":"Furniture",
            "type":"Manufacturing & Wholesale Goods"
        }
    ],
    "sg:phone":"+1 905 824 6575",
    "sg:postcode":"L5N 6X5",
    "sg:province":"ON",
    "wof:name":"Pech Consulting",
    "wof:placetype":"venue"
},
  "geometry": {"coordinates":[-79.773712,43.578472],"type":"Point"}
}