{
  "type": "Feature",
  "properties": {
    "addr:full":"Toronto ON M4W 1H4",
    "addr:postcode":"m4w 1h4",
    "iso:country":"CA",
    "sg:city":"Toronto",
    "sg:classifiers":[
        {
            "category":"Personal",
            "subcategory":"Beauty Salon",
            "type":"Services"
        }
    ],
    "sg:phone":"+1 416 969 8932",
    "sg:postcode":"M4W 1H4",
    "sg:province":"ON",
    "wof:name":"Off the Top Hair Salon",
    "wof:placetype":"venue"
},
  "geometry": {"coordinates":[-79.3782501221,43.6721992493],"type":"Point"}
}