{
  "type": "Feature",
  "properties": {
    "addr:full":"6146 Malden Rd Windsor ON N9H 1S8",
    "addr:housenumber":"6146",
    "addr:postcode":"n9h 1s8",
    "addr:street":"Malden Rd",
    "iso:country":"CA",
    "sg:address":"6146 Malden Rd",
    "sg:city":"Windsor",
    "sg:classifiers":[
        {
            "category":"Home & Garden",
            "subcategory":"Home Furnishings",
            "type":"Retail Goods"
        }
    ],
    "sg:phone":"+1 519 734 8937",
    "sg:postcode":"N9H 1S8",
    "sg:province":"ON",
    "sg:tags":[
        "venetian",
        "blind",
        "made",
        "drapery"
    ],
    "wof:name":"Luna Custom Draperies",
    "wof:placetype":"venue"
},
  "geometry": {"coordinates":[-83.060508728,42.2527389526],"type":"Point"}
}