{
  "type": "Feature",
  "properties": {
    "addr:full":"597 Bernard Ave Kelowna BC V1Y 6N9",
    "addr:housenumber":"597",
    "addr:postcode":"v1y 6n9",
    "addr:street":"Bernard Ave",
    "iso:country":"CA",
    "sg:address":"597 Bernard Ave",
    "sg:city":"Kelowna",
    "sg:classifiers":[
        {
            "category":"Shopping",
            "subcategory":"Pharmacy",
            "type":"Retail Goods"
        }
    ],
    "sg:phone":"+1 250 763 1232",
    "sg:postcode":"V1Y 6N9",
    "sg:province":"BC",
    "wof:name":"Shoppers Drug Mart",
    "wof:placetype":"venue"
},
  "geometry": {"coordinates":[-119.490067,49.88623],"type":"Point"}
}