{
  "type": "Feature",
  "properties": {
    "addr:full":"5171 Airport Rd S Richmond BC V7B 1B5",
    "addr:housenumber":"5171",
    "addr:postcode":"v7b 1b5",
    "addr:street":"Airport Rd",
    "iso:country":"CA",
    "sg:address":"5171 Airport Rd S",
    "sg:city":"Richmond",
    "sg:classifiers":[
        {
            "category":"Autos & Motor Vehicles",
            "subcategory":"Automobile Sales",
            "type":"Retail Goods"
        }
    ],
    "sg:phone":"+1 604 244 1669",
    "sg:postcode":"V7B 1B5",
    "sg:province":"BC",
    "sg:tags":[
        "equipment",
        "aircraft",
        "parts",
        "supply"
    ],
    "wof:name":"Eurocopter Canada Inc",
    "wof:placetype":"venue"
},
  "geometry": {"coordinates":[-123.16732788100001,49.1802978516],"type":"Point"}
}