{
  "type": "Feature",
  "properties": {
    "iso:country":"CA",
    "sg:city":"Vancouver",
    "sg:classifiers":[
        {
            "category":"Travel",
            "subcategory":"Travel Agent",
            "type":"Entertainment"
        }
    ],
    "sg:phone":"+1 604 688 3551",
    "sg:postcode":"V6G 2Z4",
    "sg:province":"BC",
    "sg:tags":[
        "agency",
        "bureau"
    ],
    "wof:name":"Uniglobe Advance Travel Ltd",
    "wof:placetype":"venue"
},
  "geometry": {"coordinates":[-123.129898071,49.2892227173],"type":"Point"}
}