{
  "type": "Feature",
  "properties": {
    "addr:full":"6587 Ch Saint-Francois Saint-Laurent QC H4S 1B6",
    "addr:housenumber":"6587",
    "addr:postcode":"h4s 1b6",
    "addr:street":"Ch Saint-Francois",
    "iso:country":"CA",
    "sg:address":"6587 Ch Saint-Francois",
    "sg:city":"Saint-Laurent",
    "sg:classifiers":[
        {
            "category":"Professional",
            "subcategory":"Business Services",
            "type":"Services"
        }
    ],
    "sg:phone":"+1 514 335 3256",
    "sg:postcode":"H4S 1B6",
    "sg:province":"QC",
    "wof:name":"Grimko Reparation Vente & Loc",
    "wof:placetype":"venue"
},
  "geometry": {"coordinates":[-73.74603271479999,45.481880188],"type":"Point"}
}