{
  "type": "Feature",
  "properties": {
    "iso:country":"CA",
    "sg:address":"847 Fort St",
    "sg:city":"Victoria",
    "sg:classifiers":[
        {
            "category":"Manufacturing",
            "subcategory":"Metals",
            "type":"Manufacturing & Wholesale Goods"
        }
    ],
    "sg:phone":"+1 250 384 5942",
    "sg:postcode":"V8W 1H6",
    "sg:province":"BC",
    "sg:tags":[
        "closer",
        "lock",
        "door",
        "locksmith"
    ],
    "wof:name":"Victoria Mobile Locksmiths",
    "wof:placetype":"venue"
},
  "geometry": {"coordinates":[-123.361190796,48.423992157],"type":"Point"}
}