{
  "type": "Feature",
  "properties": {
    "iso:country":"CA",
    "sg:city":"London",
    "sg:classifiers":[
        {
            "category":"Real Estate",
            "subcategory":"Developer",
            "type":"Services"
        }
    ],
    "sg:phone":"+1 519 673 4000",
    "sg:postcode":"N6A 5P6",
    "sg:province":"ON",
    "sg:tags":[
        "company",
        "land"
    ],
    "wof:name":"Charcomp Developments Inc",
    "wof:placetype":"venue"
},
  "geometry": {"coordinates":[-81.249924,42.993019],"type":"Point"}
}