{
  "type": "Feature",
  "properties": {
    "addr:full":"London ON N6A 5P6",
    "addr:postcode":"n6a 5p6",
    "iso:country":"CA",
    "sg:city":"London",
    "sg:classifiers":[
        {
            "category":"Real Estate",
            "subcategory":"Developer",
            "type":"Services"
        }
    ],
    "sg:phone":"+1 519 673 4000",
    "sg:postcode":"N6A 5P6",
    "sg:province":"ON",
    "sg:tags":[
        "company",
        "land"
    ],
    "wof:name":"Charcomp Developments Inc",
    "wof:placetype":"venue"
},
  "geometry": {"coordinates":[-81.24992399999999,42.993019],"type":"Point"}
}