{
  "type": "Feature",
  "properties": {
    "addr:full":"1466 Dundas St W Toronto ON M6J 1Y6",
    "addr:housenumber":"1466",
    "addr:postcode":"m6j 1y6",
    "addr:street":"Dundas St W",
    "iso:country":"CA",
    "sg:address":"1466 Dundas St W",
    "sg:city":"Toronto",
    "sg:classifiers":[
        {
            "category":"Personal",
            "subcategory":"Beauty Salon",
            "type":"Services"
        }
    ],
    "sg:phone":"+1 416 536 0600",
    "sg:postcode":"M6J 1Y6",
    "sg:province":"ON",
    "wof:name":"Lucinda Beauty Salon",
    "wof:placetype":"venue"
},
  "geometry": {"coordinates":[-79.4307556152,43.6496734619],"type":"Point"}
}