{
  "type": "Feature",
  "properties": {
    "addr:full":"North Vancouver BC V7M 1R5",
    "addr:postcode":"v7m 1r5",
    "iso:country":"CA",
    "sg:city":"North Vancouver",
    "sg:classifiers":[
        {
            "category":"Insurance",
            "subcategory":"Insurance Agent",
            "type":"Services"
        }
    ],
    "sg:phone":"+1 604 980 3655",
    "sg:postcode":"V7M 1R5",
    "sg:province":"BC",
    "wof:name":"Davis, Patrick",
    "wof:placetype":"venue"
},
  "geometry": {"coordinates":[-123.073692322,49.3222236633],"type":"Point"}
}