{
  "type": "Feature",
  "properties": {
    "addr:full":"610 Boul Cure-Labelle Laval QC H7V 2T7",
    "addr:housenumber":"610",
    "addr:postcode":"h7v 2t7",
    "addr:street":"Boul Cure-Labelle",
    "iso:country":"CA",
    "sg:address":"610 Boul Cure-Labelle",
    "sg:city":"Laval",
    "sg:classifiers":[
        {
            "category":"Health Services",
            "subcategory":"Doctor",
            "type":"Services"
        }
    ],
    "sg:phone":"+1 450 687 4146",
    "sg:postcode":"H7V 2T7",
    "sg:province":"QC",
    "sg:tags":[
        "clinic"
    ],
    "wof:name":"Clinique DE Radiologie",
    "wof:placetype":"venue"
},
  "geometry": {"coordinates":[-73.74226400000001,45.536949],"type":"Point"}
}