{
  "type": "Feature",
  "properties": {
    "addr:full":"172 King St Parrsboro NS B0M 1S0",
    "addr:housenumber":"172",
    "addr:postcode":"b0m 1s0",
    "addr:street":"King St",
    "iso:country":"CA",
    "sg:address":"172 King St",
    "sg:city":"Parrsboro",
    "sg:classifiers":[
        {
            "category":"Education",
            "subcategory":"School",
            "type":"Public Place"
        }
    ],
    "sg:phone":"+1 902 254 5600",
    "sg:postcode":"B0M 1S0",
    "sg:province":"NS",
    "wof:name":"Parrsboro Regional High",
    "wof:placetype":"venue"
},
  "geometry": {"coordinates":[-64.325943,45.406155],"type":"Point"}
}