{
  "type": "Feature",
  "properties": {
    "addr:full":"50 Canada Ch Edmundston NB E3V 1V3",
    "addr:housenumber":"50",
    "addr:postcode":"e3v 1v3",
    "iso:country":"CA",
    "sg:address":"50 Canada Ch",
    "sg:city":"Edmundston",
    "sg:classifiers":[
        {
            "category":"Banks & Credit Unions",
            "subcategory":"Bank",
            "type":"Services"
        }
    ],
    "sg:phone":"+1 506 735 3374",
    "sg:postcode":"E3V 1V3",
    "sg:province":"NB",
    "wof:name":"Bank of Montreal",
    "wof:placetype":"venue"
},
  "geometry": {"coordinates":[-68.32972700000001,47.36404],"type":"Point"}
}