{
  "type": "Feature",
  "properties": {
    "addr:full":"159 Henri Dunant St Moncton NB E1E 1E4",
    "addr:housenumber":"159",
    "addr:postcode":"e1e 1e4",
    "addr:street":"Henri Dunant St",
    "iso:country":"CA",
    "sg:address":"159 Henri Dunant St",
    "sg:city":"Moncton",
    "sg:classifiers":[
        {
            "category":"Wholesale",
            "subcategory":"Hardware",
            "type":"Manufacturing & Wholesale Goods"
        }
    ],
    "sg:phone":"+1 506 857 8658",
    "sg:postcode":"E1E 1E4",
    "sg:province":"NB",
    "sg:tags":[
        "fastener"
    ],
    "wof:name":"H Paulin & CO Ltd",
    "wof:placetype":"venue"
},
  "geometry": {"coordinates":[-64.8277587891,46.0786819458],"type":"Point"}
}