{
  "type": "Feature",
  "properties": {
    "addr:full":"Richibucto NB E4W 3W7",
    "addr:postcode":"e4w 3w7",
    "iso:country":"CA",
    "sg:city":"Richibucto",
    "sg:classifiers":[
        {
            "category":"Shopping",
            "subcategory":"Pharmacy",
            "type":"Retail Goods"
        }
    ],
    "sg:phone":"+1 506 523 4801",
    "sg:postcode":"E4W 3W7",
    "sg:province":"NB",
    "wof:name":"Shoppers Drug Mart",
    "wof:placetype":"venue"
},
  "geometry": {"coordinates":[-64.87339019780001,46.6743965149],"type":"Point"}
}