{
  "type": "Feature",
  "properties": {
    "iso:country":"CA",
    "sg:address":"5850 Av Baldwin",
    "sg:city":"Anjou",
    "sg:classifiers":[
        {
            "category":"Shopping",
            "subcategory":"Computers & Home Electronics",
            "type":"Retail Goods"
        }
    ],
    "sg:phone":"+1 514 353 3882",
    "sg:postcode":"H1K 3C3",
    "sg:province":"QC",
    "sg:tags":[
        "television",
        "radio"
    ],
    "wof:name":"Electronique Jacques Martin",
    "wof:placetype":"venue"
},
  "geometry": {"coordinates":[-73.54287,45.60767],"type":"Point"}
}