{
  "type": "Feature",
  "properties": {
    "addr:full":"1335 Johnston Rd White Rock BC V4B 3Z3",
    "addr:housenumber":"1335",
    "addr:postcode":"v4b 3z3",
    "addr:street":"Johnston Rd",
    "iso:country":"CA",
    "sg:address":"1335 Johnston Rd",
    "sg:city":"White Rock",
    "sg:classifiers":[
        {
            "category":"Shopping",
            "subcategory":"Musical Instruments",
            "type":"Retail Goods"
        }
    ],
    "sg:phone":"+1 604 538 0906",
    "sg:postcode":"V4B 3Z3",
    "sg:province":"BC",
    "sg:tags":[
        "music",
        "dealer"
    ],
    "wof:name":"Tapestry Music",
    "wof:placetype":"venue"
},
  "geometry": {"coordinates":[-122.801376,49.026512],"type":"Point"}
}