{
  "type": "Feature",
  "properties": {
    "addr:full":"9192 Rue Sherbrooke E Montreal QC H1L 1E5",
    "addr:housenumber":"9192",
    "addr:postcode":"h1l 1e5",
    "addr:street":"Rue Sherbrooke E",
    "iso:country":"CA",
    "sg:address":"9192 Rue Sherbrooke E",
    "sg:city":"Montreal",
    "sg:classifiers":[
        {
            "category":"Restaurant",
            "type":"Food & Drink"
        }
    ],
    "sg:phone":"+1 514 352 2011",
    "sg:postcode":"H1L 1E5",
    "sg:province":"QC",
    "wof:name":"Restaurant Le Cupidon D'Or",
    "wof:placetype":"venue"
},
  "geometry": {"coordinates":[-73.5271911621,45.6093025208],"type":"Point"}
}