{
  "type": "Feature",
  "properties": {
    "addr:full":"1200 Douglas St Victoria BC V8W 2E5",
    "addr:housenumber":"1200",
    "addr:postcode":"v8w 2e5",
    "addr:street":"Douglas St",
    "iso:country":"CA",
    "sg:address":"1200 Douglas St",
    "sg:city":"Victoria",
    "sg:classifiers":[
        {
            "category":"Restaurant",
            "type":"Food & Drink"
        }
    ],
    "sg:phone":"+1 250 952 3600",
    "sg:postcode":"V8W 2E5",
    "sg:province":"BC",
    "wof:name":"Mc Donald's",
    "wof:placetype":"venue"
},
  "geometry": {"coordinates":[-123.36528015099999,48.4255867004],"type":"Point"}
}