{
  "type": "Feature",
  "properties": {
    "iso:country":"CA",
    "sg:address":"625 Rte Cameron",
    "sg:city":"Sainte-Marie",
    "sg:classifiers":[
        {
            "category":"Autos & Motor Vehicles",
            "subcategory":"Automobile Sales",
            "type":"Retail Goods"
        }
    ],
    "sg:phone":"+1 418 387 1625",
    "sg:postcode":"G6E 1B1",
    "sg:province":"QC",
    "sg:tags":[
        "car",
        "dealer"
    ],
    "wof:name":"Autos Mars Inc",
    "wof:placetype":"venue"
},
  "geometry": {"coordinates":[-71.03954315190001,46.4679908752],"type":"Point"}
}