{
  "type": "Feature",
  "properties": {
    "addr:full":"4063 Hamilton Rd Dorchester ON N0L 1G2",
    "addr:housenumber":"4063",
    "addr:postcode":"n0l 1g2",
    "addr:street":"Hamilton Rd",
    "iso:country":"CA",
    "sg:address":"4063 Hamilton Rd",
    "sg:city":"Dorchester",
    "sg:classifiers":[
        {
            "category":"Restaurant",
            "type":"Food & Drink"
        }
    ],
    "sg:phone":"+1 519 268 6668",
    "sg:postcode":"N0L 1G2",
    "sg:province":"ON",
    "wof:name":"Godfather Pizza",
    "wof:placetype":"venue"
},
  "geometry": {"coordinates":[-81.057869,42.988384],"type":"Point"}
}