{
  "type": "Feature",
  "properties": {
    "addr:full":"290 St Clair Ave W Toronto ON M4V 1S3",
    "addr:housenumber":"290",
    "addr:postcode":"m4v 1s3",
    "addr:street":"St Clair Ave W",
    "iso:country":"CA",
    "sg:address":"290 St Clair Ave W",
    "sg:city":"Toronto",
    "sg:classifiers":[
        {
            "category":"Health Services",
            "subcategory":"Health Practitioner",
            "type":"Services"
        }
    ],
    "sg:phone":"+1 416 967 1827",
    "sg:postcode":"M4V 1S3",
    "sg:province":"ON",
    "sg:tags":[
        "psychologist",
        "counselor",
        "marriage",
        "family"
    ],
    "wof:name":"Kaffko, K",
    "wof:placetype":"venue"
},
  "geometry": {"coordinates":[-79.410141,43.684971],"type":"Point"}
}