{
  "type": "Feature",
  "properties": {
    "iso:country":"CA",
    "sg:address":"323 Queen St W #2",
    "sg:city":"Toronto",
    "sg:classifiers":[
        {
            "category":"Shopping",
            "subcategory":"Bicycles & Sporting Goods",
            "type":"Retail Goods"
        }
    ],
    "sg:phone":"+1 416 971 6901",
    "sg:postcode":"M5V 2A4",
    "sg:province":"ON",
    "sg:tags":[
        "equipment",
        "snowboard",
        "skateboard"
    ],
    "wof:name":"So Hip It Hurts",
    "wof:placetype":"venue"
},
  "geometry": {"coordinates":[-79.391685,43.649628],"type":"Point"}
}