{
  "type": "Feature",
  "properties": {
    "addr:full":"34120 Laxton Ave Mission BC V2V 6B2",
    "addr:postcode":"34120;v2v 6b2",
    "addr:street":"Laxton Ave",
    "iso:country":"CA",
    "sg:address":"34120 Laxton Ave",
    "sg:city":"Mission",
    "sg:classifiers":[
        {
            "category":"Retail",
            "subcategory":"Repair Shop",
            "type":"Services"
        }
    ],
    "sg:phone":"+1 604 826 3855",
    "sg:postcode":"V2V 6B2",
    "sg:province":"BC",
    "sg:tags":[
        "pump"
    ],
    "wof:name":"Murray's Wellpoint & Pump Svc",
    "wof:placetype":"venue"
},
  "geometry": {"coordinates":[-122.279533,49.165287],"type":"Point"}
}