{
  "type": "Feature",
  "properties": {
    "addr:full":"45 Lothian Ave Etobicoke ON M8Z 4K2",
    "addr:housenumber":"45",
    "addr:postcode":"m8z 4k2",
    "addr:street":"Lothian Ave",
    "iso:country":"CA",
    "sg:address":"45 Lothian Ave",
    "sg:city":"Etobicoke",
    "sg:classifiers":[
        {
            "category":"Retail",
            "subcategory":"Repair Shop",
            "type":"Services"
        }
    ],
    "sg:phone":"+1 416 259 8863",
    "sg:postcode":"M8Z 4K2",
    "sg:province":"ON",
    "sg:tags":[
        "instrument",
        "musical"
    ],
    "wof:name":"Allied Piano Svc",
    "wof:placetype":"venue"
},
  "geometry": {"coordinates":[-79.51979064939999,43.64245224],"type":"Point"}
}