{
  "type": "Feature",
  "properties": {
    "iso:country":"CA",
    "sg:address":"15 Rue Du Rivage",
    "sg:city":"Lameque",
    "sg:classifiers":[
        {
            "category":"Personal",
            "type":"Services"
        }
    ],
    "sg:phone":"+1 506 344 5842",
    "sg:postcode":"E8T 1L6",
    "sg:province":"NB",
    "sg:tags":[
        "therapist",
        "massage"
    ],
    "wof:name":"Clinique Sante & Beaute Chez",
    "wof:placetype":"venue"
},
  "geometry": {"coordinates":[-64.6489028931,47.7918701172],"type":"Point"}
}