{
  "type": "Feature",
  "properties": {
    "iso:country":"CA",
    "sg:address":"1048 Balmoral St",
    "sg:city":"Thunder Bay",
    "sg:classifiers":[
        {
            "category":"Freight",
            "type":"Transportation"
        }
    ],
    "sg:phone":"+1 807 624 2129",
    "sg:postcode":"P7B 5T9",
    "sg:province":"ON",
    "sg:tags":[
        "courier"
    ],
    "wof:name":"Gofer Courier & Messenger Svc",
    "wof:placetype":"venue"
},
  "geometry": {"coordinates":[-89.2580108643,48.4041786194],"type":"Point"}
}