{
  "type": "Feature",
  "properties": {
    "addr:full":"Vancouver BC V6B 2K4",
    "addr:postcode":"v6b 2k4",
    "iso:country":"CA",
    "sg:city":"Vancouver",
    "sg:classifiers":[
        {
            "category":"Professional",
            "subcategory":"Lawyer & Legal Services",
            "type":"Services"
        }
    ],
    "sg:phone":"+1 604 689 5444",
    "sg:postcode":"V6B 2K4",
    "sg:province":"BC",
    "sg:tags":[
        "attorney"
    ],
    "wof:name":"Sas, Catherine A",
    "wof:placetype":"venue"
},
  "geometry": {"coordinates":[-123.10610200000001,49.284122],"type":"Point"}
}