{
  "type": "Feature",
  "properties": {
    "iso:country":"CA",
    "sg:address":"85 Boul Sainte-Anne",
    "sg:city":"Pointe-Au-Pere",
    "sg:classifiers":[
        {
            "category":"Home & Garden",
            "subcategory":"Carpets & Floor Coverings",
            "type":"Retail Goods"
        }
    ],
    "sg:phone":"+1 418 723 6446",
    "sg:postcode":"G5M 1C2",
    "sg:province":"QC",
    "sg:tags":[
        "dealer",
        "rug"
    ],
    "wof:name":"Tapis Ouellet Inc",
    "wof:placetype":"venue"
},
  "geometry": {"coordinates":[-68.4919586182,48.4875793457],"type":"Point"}
}