{
  "type": "Feature",
  "properties": {
    "addr:full":"2455 Mansfield Dr Courtenay BC V9N 2M2",
    "addr:housenumber":"2455",
    "addr:postcode":"v9n 2m2",
    "addr:street":"Mansfield Dr",
    "iso:country":"CA",
    "sg:address":"2455 Mansfield Dr",
    "sg:city":"Courtenay",
    "sg:classifiers":[
        {
            "category":"Government",
            "subcategory":"Office",
            "type":"Public Place"
        }
    ],
    "sg:phone":"+1 250 334 5820",
    "sg:postcode":"V9N 2M2",
    "sg:province":"BC",
    "wof:name":"BC Family & Children's Svc",
    "wof:placetype":"venue"
},
  "geometry": {"coordinates":[-124.980515,49.677357],"type":"Point"}
}