{
  "type": "Feature",
  "properties": {
    "addr:full":"918 6 Ave SW Calgary AB T2P 0V5",
    "addr:housenumber":"918",
    "addr:postcode":"t2p 0v5",
    "addr:street":"6 Ave Sw",
    "iso:country":"CA",
    "sg:address":"918 6 Ave SW",
    "sg:city":"Calgary",
    "sg:classifiers":[
        {
            "category":"Professional",
            "subcategory":"Employment Agencies",
            "type":"Services"
        }
    ],
    "sg:phone":"+1 403 265 7886",
    "sg:postcode":"T2P 0V5",
    "sg:province":"AB",
    "sg:tags":[
        "opportunity"
    ],
    "wof:name":"Paragon Personnel Svc Ltd",
    "wof:placetype":"venue"
},
  "geometry": {"coordinates":[-114.08177947999999,51.0481071472],"type":"Point"}
}