{
  "type": "Feature",
  "properties": {
    "iso:country":"CA",
    "sg:city":"Winnipeg",
    "sg:classifiers":[
        {
            "category":"Real Estate",
            "subcategory":"Real Estate Operator",
            "type":"Services"
        }
    ],
    "sg:phone":"+1 204 269 1649",
    "sg:postcode":"R3T 4W3",
    "sg:province":"MB",
    "sg:tags":[
        "apartment"
    ],
    "wof:name":"Richmond Village",
    "wof:placetype":"venue"
},
  "geometry": {"coordinates":[-97.152222,49.794331],"type":"Point"}
}