{
  "type": "Feature",
  "properties": {
    "addr:full":"760 Rue Belanger Saint-Jerome QC J7Z 1A5",
    "addr:housenumber":"760",
    "addr:postcode":"j7z 1a5",
    "addr:street":"Rue Belanger Saint-Jerome",
    "iso:country":"CA",
    "sg:address":"760 Rue Belanger",
    "sg:city":"Saint-Jerome",
    "sg:classifiers":[
        {
            "category":"Food & Beverages",
            "subcategory":"Groceries & Convenience Stores",
            "type":"Retail Goods"
        }
    ],
    "sg:phone":"+1 450 432 8615",
    "sg:postcode":"J7Z 1A5",
    "sg:province":"QC",
    "wof:name":"Couche-Tard",
    "wof:placetype":"venue"
},
  "geometry": {"coordinates":[-73.99543,45.795601],"type":"Point"}
}