{
  "type": "Feature",
  "properties": {
    "addr:full":"4524 81 Ave NW Edmonton AB T6B 2M2",
    "addr:housenumber":"4524",
    "addr:postcode":"t6b 2m2",
    "addr:street":"81 Ave Nw",
    "iso:country":"CA",
    "sg:address":"4524 81 Ave NW",
    "sg:city":"Edmonton",
    "sg:classifiers":[
        {
            "category":"Professional",
            "subcategory":"Art Services",
            "type":"Services"
        }
    ],
    "sg:phone":"+1 780 469 9191",
    "sg:postcode":"T6B 2M2",
    "sg:province":"AB",
    "sg:tags":[
        "graphic",
        "printer",
        "designer"
    ],
    "wof:name":"Swarm Enterprises",
    "wof:placetype":"venue"
},
  "geometry": {"coordinates":[-113.410599,53.51609],"type":"Point"}
}