{
  "type": "Feature",
  "properties": {
    "addr:full":"4730 Spring Rd Victoria BC V9E 2B5",
    "addr:housenumber":"4730",
    "addr:postcode":"v9e 2b5",
    "addr:street":"Spring Rd",
    "iso:country":"CA",
    "sg:address":"4730 Spring Rd",
    "sg:city":"Victoria",
    "sg:classifiers":[
        {
            "category":"Professional",
            "subcategory":"Management & Consulting",
            "type":"Services"
        }
    ],
    "sg:phone":"+1 250 744 1443",
    "sg:postcode":"V9E 2B5",
    "sg:province":"BC",
    "sg:tags":[
        "consultant",
        "business"
    ],
    "wof:name":"Osprey Consulting Ltd",
    "wof:placetype":"venue"
},
  "geometry": {"coordinates":[-123.34741200000001,48.433708],"type":"Point"}
}