{
  "type": "Feature",
  "properties": {
    "addr:full":"Upper Gagetown NB E5M 1N3",
    "addr:postcode":"e5m 1n3",
    "addr:street":"Upper Gagetown",
    "iso:country":"CA",
    "sg:city":"Upper Gagetown",
    "sg:classifiers":[
        {
            "category":"Travel",
            "subcategory":"Campground",
            "type":"Entertainment"
        }
    ],
    "sg:phone":"+1 506 488 2567",
    "sg:postcode":"E5M 1N3",
    "sg:province":"NB",
    "wof:name":"Gagetown Camping",
    "wof:placetype":"venue"
},
  "geometry": {"coordinates":[-66.15239,45.778137],"type":"Point"}
}