{
  "type": "Feature",
  "properties": {
    "addr:full":"177 Ontario St Brighton ON K0K 1H0",
    "addr:housenumber":"177",
    "addr:postcode":"k0k 1h0",
    "addr:street":"Ontario St",
    "iso:country":"CA",
    "sg:address":"177 Ontario St",
    "sg:city":"Brighton",
    "sg:classifiers":[
        {
            "category":"Building & Trades",
            "subcategory":"Construction",
            "type":"Services"
        }
    ],
    "sg:phone":"+1 613 475 3058",
    "sg:postcode":"K0K 1H0",
    "sg:province":"ON",
    "sg:tags":[
        "painter"
    ],
    "wof:name":"Alex Hamilton Painting",
    "wof:placetype":"venue"
},
  "geometry": {"coordinates":[-77.73954000000001,44.024441],"type":"Point"}
}