{
  "type": "Feature",
  "properties": {
    "addr:full":"270 3 Rang Saint-Jules QC G0N 1R0",
    "addr:housenumber":"270 3",
    "addr:postcode":"g0n 1r0",
    "addr:street":"Rang Saint-Jules",
    "iso:country":"CA",
    "sg:address":"270 3 Rang",
    "sg:city":"Saint-Jules",
    "sg:classifiers":[
        {
            "category":"Personal",
            "subcategory":"Beauty Salon",
            "type":"Services"
        }
    ],
    "sg:phone":"+1 418 426 2159",
    "sg:postcode":"G0N 1R0",
    "sg:province":"QC",
    "wof:name":"Salon Esther",
    "wof:placetype":"venue"
},
  "geometry": {"coordinates":[-70.980446,46.21365],"type":"Point"}
}