{
  "type": "Feature",
  "properties": {
    "addr:full":"1804 Crowchild Trail NW Calgary AB T2M 3Y7",
    "addr:housenumber":"1804",
    "addr:postcode":"t2m 3y7",
    "addr:street":"Crowchild Trail Nw",
    "iso:country":"CA",
    "sg:address":"1804 Crowchild Trail NW",
    "sg:city":"Calgary",
    "sg:classifiers":[
        {
            "category":"Restaurant",
            "type":"Food & Drink"
        }
    ],
    "sg:phone":"+1 403 289 0241",
    "sg:postcode":"T2M 3Y7",
    "sg:province":"AB",
    "wof:name":"Courtyard Cafe & Restaurant",
    "wof:placetype":"venue"
},
  "geometry": {"coordinates":[-114.11730957,51.0677452087],"type":"Point"}
}