{
  "type": "Feature",
  "properties": {
    "iso:country":"CA",
    "sg:address":"380 Albert St",
    "sg:city":"Strathroy",
    "sg:classifiers":[
        {
            "category":"Shopping",
            "type":"Retail Goods"
        }
    ],
    "sg:phone":"+1 519 245 2200",
    "sg:postcode":"N7G 1W7",
    "sg:province":"ON",
    "sg:tags":[
        "orthopedic",
        "appliance"
    ],
    "wof:name":"Footworx",
    "wof:placetype":"venue"
},
  "geometry": {"coordinates":[-81.6363143921,42.9553642273],"type":"Point"}
}