{
  "type": "Feature",
  "properties": {
    "iso:country":"CA",
    "sg:city":"Sarnia",
    "sg:classifiers":[
        {
            "category":"Health Services",
            "subcategory":"Doctor",
            "type":"Services"
        }
    ],
    "sg:phone":"+1 519 344 4868",
    "sg:postcode":"N7T 7W5",
    "sg:province":"ON",
    "sg:tags":[
        "physician",
        "surgeon"
    ],
    "wof:name":"Lacroix, Thomas B MD",
    "wof:placetype":"venue"
},
  "geometry": {"coordinates":[-82.407181,42.972176],"type":"Point"}
}