{
  "type": "Feature",
  "properties": {
    "addr:full":"39 Queen St W Cambridge ON N3C 1G2",
    "addr:housenumber":"39",
    "addr:postcode":"n3c 1g2",
    "addr:street":"Queen St W",
    "iso:country":"CA",
    "sg:address":"39 Queen St W",
    "sg:city":"Cambridge",
    "sg:classifiers":[
        {
            "category":"Professional",
            "subcategory":"Lawyer & Legal Services",
            "type":"Services"
        }
    ],
    "sg:phone":"+1 519 658 6341",
    "sg:postcode":"N3C 1G2",
    "sg:province":"ON",
    "sg:tags":[
        "attorney"
    ],
    "wof:name":"Hilborn & Konduros",
    "wof:placetype":"venue"
},
  "geometry": {"coordinates":[-80.3124923706,43.4306488037],"type":"Point"}
}