{
  "type": "Feature",
  "properties": {
    "addr:full":"93 George St Lanark ON K0G 1K0",
    "addr:housenumber":"93",
    "addr:postcode":"k0g 1k0",
    "addr:street":"George St",
    "iso:country":"CA",
    "sg:address":"93 George St",
    "sg:city":"Lanark",
    "sg:classifiers":[
        {
            "category":"Shopping",
            "subcategory":"Florist",
            "type":"Retail Goods"
        }
    ],
    "sg:phone":"+1 613 259 2340",
    "sg:postcode":"K0G 1K0",
    "sg:province":"ON",
    "wof:name":"Trailling Foliage",
    "wof:placetype":"venue"
},
  "geometry": {"coordinates":[-76.366272,45.019199],"type":"Point"}
}