{
  "type": "Feature",
  "properties": {
    "addr:full":"Lincolnville Rd Monastery NS B0H 1W0",
    "addr:postcode":"b0h 1w0",
    "addr:street":"Lincolnville Rd",
    "iso:country":"CA",
    "sg:address":"Lincolnville Rd",
    "sg:city":"Monastery",
    "sg:classifiers":[
        {
            "category":"Recreation",
            "type":"Entertainment"
        }
    ],
    "sg:phone":"+1 902 232 2282",
    "sg:postcode":"B0H 1W0",
    "sg:province":"NS",
    "sg:tags":[
        "center"
    ],
    "wof:name":"Lincolnville Access Committee",
    "wof:placetype":"venue"
},
  "geometry": {"coordinates":[-61.6138534546,45.6078491211],"type":"Point"}
}