{
  "type": "Feature",
  "properties": {
    "addr:full":"434 John St Port Lambton ON N0P 2B0",
    "addr:housenumber":"434",
    "addr:postcode":"n0p 2b0",
    "addr:street":"John St",
    "iso:country":"CA",
    "sg:address":"434 John St",
    "sg:city":"Port Lambton",
    "sg:classifiers":[
        {
            "category":"Education",
            "subcategory":"School",
            "type":"Public Place"
        }
    ],
    "sg:phone":"+1 519 677 5391",
    "sg:postcode":"N0P 2B0",
    "sg:province":"ON",
    "wof:name":"Sacred Heart School",
    "wof:placetype":"venue"
},
  "geometry": {"coordinates":[-82.50072479249999,42.6575622559],"type":"Point"}
}