{
  "type": "Feature",
  "properties": {
    "addr:full":"4479 Concession 2 Stouffville ON L4A 7X4",
    "addr:housenumber":"4479",
    "addr:postcode":"l4a 7x4",
    "addr:street":"Concession 2",
    "iso:country":"CA",
    "sg:address":"4479 Concession 2",
    "sg:city":"Stouffville",
    "sg:classifiers":[
        {
            "category":"Home & Garden",
            "subcategory":"Garden Supply",
            "type":"Retail Goods"
        }
    ],
    "sg:phone":"+1 905 640 1325",
    "sg:postcode":"L4A 7X4",
    "sg:province":"ON",
    "sg:tags":[
        "tree",
        "christmas"
    ],
    "wof:name":"Taylor Tree Farms Ltd",
    "wof:placetype":"venue"
},
  "geometry": {"coordinates":[-79.2559509277,43.9700813293],"type":"Point"}
}