{
  "type": "Feature",
  "properties": {
    "addr:full":"3102 Laurier Dr Saskatoon SK S7L 5J7",
    "addr:housenumber":"3102",
    "addr:postcode":"s7l 5j7",
    "addr:street":"Laurier Dr",
    "iso:country":"CA",
    "sg:address":"3102 Laurier Dr",
    "sg:city":"Saskatoon",
    "sg:classifiers":[
        {
            "category":"Organizations",
            "subcategory":"Religious Organization",
            "type":"Services"
        }
    ],
    "sg:phone":"+1 306 384 4643",
    "sg:postcode":"S7L 5J7",
    "sg:province":"SK",
    "sg:tags":[
        "church"
    ],
    "wof:name":"Evangelical Free Church",
    "wof:placetype":"venue"
},
  "geometry": {"coordinates":[-106.717918,52.134678],"type":"Point"}
}