{
  "type": "Feature",
  "properties": {
    "addr:full":"1070 4th Ave Prince George BC V2L 3J1",
    "addr:housenumber":"1070",
    "addr:postcode":"v2l 3j1",
    "addr:street":"4Th Ave",
    "iso:country":"CA",
    "sg:address":"1070 4th Ave",
    "sg:city":"Prince George",
    "sg:classifiers":[
        {
            "category":"Organizations",
            "subcategory":"Labor Organization",
            "type":"Services"
        }
    ],
    "sg:phone":"+1 250 563 1116",
    "sg:postcode":"V2L 3J1",
    "sg:province":"BC",
    "wof:name":"B C Government & Svc Employees",
    "wof:placetype":"venue"
},
  "geometry": {"coordinates":[-122.742675781,53.9152755737],"type":"Point"}
}