{
  "type": "Feature",
  "properties": {
    "addr:full":"610 Ch Royal Saint-Pierre-Ile-D'Orleans QC G0A 4E0",
    "addr:housenumber":"610",
    "addr:postcode":"g0a 4e0",
    "addr:street":"Ch Royal Saint-Pierre-Ile-D'Orleans",
    "iso:country":"CA",
    "sg:address":"610 Ch Royal",
    "sg:city":"Saint-Pierre-Ile-D'Orleans",
    "sg:classifiers":[
        {
            "category":"Restaurant",
            "type":"Food & Drink"
        }
    ],
    "sg:phone":"+1 418 828 0555",
    "sg:postcode":"G0A 4E0",
    "sg:province":"QC",
    "wof:name":"Restaurant Chez Magy",
    "wof:placetype":"venue"
},
  "geometry": {"coordinates":[-70.93113700000001,46.904354],"type":"Point"}
}