{
  "type": "Feature",
  "properties": {
    "addr:full":"5574 Rue Saint-Georges Levis QC G6V 4M6",
    "addr:housenumber":"5574",
    "addr:postcode":"g6v 4m6",
    "addr:street":"Rue Saint-Georges",
    "iso:country":"CA",
    "sg:address":"5574 Rue Saint-Georges",
    "sg:city":"Levis",
    "sg:classifiers":[
        {
            "category":"Recreation",
            "type":"Entertainment"
        }
    ],
    "sg:phone":"+1 418 837 5564",
    "sg:postcode":"G6V 4M6",
    "sg:province":"QC",
    "sg:tags":[
        "supply",
        "equipment",
        "arts",
        "instruction",
        "martial"
    ],
    "wof:name":"Studios Unis D'Auto Defense",
    "wof:placetype":"venue"
},
  "geometry": {"coordinates":[-71.182114,46.799065],"type":"Point"}
}