{
  "type": "Feature",
  "properties": {
    "iso:country":"CA",
    "sg:address":"9210 118 Ave NW",
    "sg:city":"Edmonton",
    "sg:classifiers":[
        {
            "category":"Organizations",
            "subcategory":"Community Association",
            "type":"Services"
        }
    ],
    "sg:phone":"+1 780 477 2773",
    "sg:postcode":"T5G 0N2",
    "sg:province":"AB",
    "sg:tags":[
        "club"
    ],
    "wof:name":"Alberta Ave Community League",
    "wof:placetype":"venue"
},
  "geometry": {"coordinates":[-113.48299408,53.5706481934],"type":"Point"}
}