{
  "type": "Feature",
  "properties": {
    "addr:full":"2 Thiessen Cres Kanata ON K2L 2M3",
    "addr:housenumber":"2",
    "addr:postcode":"k2l 2m3",
    "addr:street":"Thiessen Cres",
    "iso:country":"CA",
    "sg:address":"2 Thiessen Cres",
    "sg:city":"Kanata",
    "sg:classifiers":[
        {
            "category":"Professional",
            "subcategory":"Accounting & Tax Preparation",
            "type":"Services"
        }
    ],
    "sg:phone":"+1 613 591 6061",
    "sg:postcode":"K2L 2M3",
    "sg:province":"ON",
    "sg:tags":[
        "consultant",
        "sales"
    ],
    "wof:name":"Lamb & Assoc",
    "wof:placetype":"venue"
},
  "geometry": {"coordinates":[-75.8991928101,45.3047599792],"type":"Point"}
}