{
  "type": "Feature",
  "properties": {
    "addr:full":"180 Cooper St Ottawa ON K2P 2L5",
    "addr:housenumber":"180",
    "addr:postcode":"k2p 2l5",
    "addr:street":"Cooper St",
    "iso:country":"CA",
    "sg:address":"180 Cooper St",
    "sg:city":"Ottawa",
    "sg:classifiers":[
        {
            "category":"Travel",
            "subcategory":"Hotels & Motels",
            "type":"Entertainment"
        }
    ],
    "sg:phone":"+1 613 236 5000",
    "sg:postcode":"K2P 2L5",
    "sg:province":"ON",
    "wof:name":"Cartier Place Suite Hotel",
    "wof:placetype":"venue"
},
  "geometry": {"coordinates":[-75.690071,45.418736],"type":"Point"}
}