{
  "type": "Feature",
  "properties": {
    "addr:full":"1199 Lansing Ave Sudbury ON P3A 4C4",
    "addr:housenumber":"1199",
    "addr:postcode":"p3a 4c4",
    "addr:street":"Lansing Ave",
    "iso:country":"CA",
    "sg:address":"1199 Lansing Ave",
    "sg:city":"Sudbury",
    "sg:classifiers":[
        {
            "category":"Organizations",
            "subcategory":"Religious Organization",
            "type":"Services"
        }
    ],
    "sg:phone":"+1 705 566 0853",
    "sg:postcode":"P3A 4C4",
    "sg:province":"ON",
    "sg:tags":[
        "church"
    ],
    "wof:name":"Redeemer Lutheran Church",
    "wof:placetype":"venue"
},
  "geometry": {"coordinates":[-80.92924499510001,46.5238990784],"type":"Point"}
}