{
  "type": "Feature",
  "properties": {
    "addr:full":"2526 Leitrim Rd Gloucester ON K1T 3V3",
    "addr:housenumber":"2526",
    "addr:postcode":"k1t 3v3",
    "addr:street":"Leitrim Rd",
    "iso:country":"CA",
    "sg:address":"2526 Leitrim Rd",
    "sg:city":"Gloucester",
    "sg:classifiers":[
        {
            "category":"Manufacturing",
            "subcategory":"Leather Goods",
            "type":"Manufacturing & Wholesale Goods"
        }
    ],
    "sg:phone":"+1 613 822 0620",
    "sg:postcode":"K1T 3V3",
    "sg:province":"ON",
    "sg:tags":[
        "case"
    ],
    "wof:name":"Custom Case CO",
    "wof:placetype":"venue"
},
  "geometry": {"coordinates":[-75.6297988892,45.3174781799],"type":"Point"}
}