{
  "type": "Feature",
  "properties": {
    "addr:full":"13680 Bridgeport Rd # 3 Richmond BC V6V 1V3",
    "addr:housenumber":"13680",
    "addr:postcode":"v6v 1v3",
    "addr:street":"Bridgeport Rd # 3",
    "iso:country":"CA",
    "sg:address":"13680 Bridgeport Rd # 3",
    "sg:city":"Richmond",
    "sg:classifiers":[
        {
            "category":"Wholesale",
            "subcategory":"Electrical",
            "type":"Manufacturing & Wholesale Goods"
        }
    ],
    "sg:phone":"+1 604 231 7730",
    "sg:postcode":"V6V 1V3",
    "sg:province":"BC",
    "sg:tags":[
        "electric",
        "motor"
    ],
    "wof:name":"Action Bearings & Drives",
    "wof:placetype":"venue"
},
  "geometry": {"coordinates":[-123.072929,49.191883],"type":"Point"}
}