{
  "type": "Feature",
  "properties": {
    "addr:full":"309 Avenue B N Saskatoon SK S7L 1E3",
    "addr:housenumber":"309",
    "addr:postcode":"s7l 1e3",
    "addr:street":"Avenue B N",
    "iso:country":"CA",
    "sg:address":"309 Avenue B N",
    "sg:city":"Saskatoon",
    "sg:classifiers":[
        {
            "category":"Manufacturing",
            "subcategory":"Tools & Machinery",
            "type":"Manufacturing & Wholesale Goods"
        }
    ],
    "sg:phone":"+1 306 652 3223",
    "sg:postcode":"S7L 1E3",
    "sg:province":"SK",
    "sg:tags":[
        "machine",
        "shop",
        "trailer"
    ],
    "wof:name":"Fleet-Guide Truck & Trailer",
    "wof:placetype":"venue"
},
  "geometry": {"coordinates":[-106.672050476,52.1326713562],"type":"Point"}
}