{
  "type": "Feature",
  "properties": {
    "addr:full":"2330 Highway 97 Westbank BC V4T 2P3",
    "addr:housenumber":"2330",
    "addr:postcode":"v4t 2p3",
    "addr:street":"Highway 97",
    "iso:country":"CA",
    "sg:address":"2330 Highway 97",
    "sg:city":"Westbank",
    "sg:classifiers":[
        {
            "category":"Restaurant",
            "type":"Food & Drink"
        }
    ],
    "sg:phone":"+1 250 707 3300",
    "sg:postcode":"V4T 2P3",
    "sg:province":"BC",
    "sg:tags":[
        "sandwich"
    ],
    "wof:name":"Quiznos Subs",
    "wof:placetype":"venue"
},
  "geometry": {"coordinates":[-119.629616,49.829571],"type":"Point"}
}