{
  "type": "Feature",
  "properties": {
    "addr:full":"1480 Av Charles-Huot Sillery QC G1T 2M3",
    "addr:housenumber":"1480",
    "addr:postcode":"g1t 2m3",
    "addr:street":"Av Charles-Huot",
    "iso:country":"CA",
    "sg:address":"1480 Av Charles-Huot",
    "sg:city":"Sillery",
    "sg:classifiers":[
        {
            "category":"Personal",
            "subcategory":"Beauty Salon",
            "type":"Services"
        }
    ],
    "sg:phone":"+1 418 659 1480",
    "sg:postcode":"G1T 2M3",
    "sg:province":"QC",
    "wof:name":"Coiffure Le 1480 Enr",
    "wof:placetype":"venue"
},
  "geometry": {"coordinates":[-71.266708374,46.7694664001],"type":"Point"}
}