{
  "type": "Feature",
  "properties": {
    "addr:full":"Vancouver BC V6A 4C1",
    "addr:postcode":"v6a 4c1",
    "iso:country":"CA",
    "sg:city":"Vancouver",
    "sg:classifiers":[
        {
            "category":"Education",
            "subcategory":"Vocational School",
            "type":"Public Place"
        }
    ],
    "sg:phone":"+1 604 684 4255",
    "sg:postcode":"V6A 4C1",
    "sg:province":"BC",
    "sg:tags":[
        "technical",
        "trade"
    ],
    "wof:name":"Canadian Multicultural Ctr",
    "wof:placetype":"venue"
},
  "geometry": {"coordinates":[-123.096313477,49.2724075317],"type":"Point"}
}