{
  "type": "Feature",
  "properties": {
    "iso:country":"CA",
    "sg:address":"69 Biddington Ave",
    "sg:city":"Lakeville-Westmorland",
    "sg:classifiers":[
        {
            "category":"Real Estate",
            "subcategory":"Real Estate Operator",
            "type":"Services"
        }
    ],
    "sg:phone":"+1 506 858 0181",
    "sg:postcode":"E1H 1C2",
    "sg:province":"NB",
    "sg:tags":[
        "mobile",
        "home",
        "community"
    ],
    "wof:name":"Lakeside Estates Ltd",
    "wof:placetype":"venue"
},
  "geometry": {"coordinates":[-64.6772155762,46.152961731],"type":"Point"}
}