{
  "type": "Feature",
  "properties": {
    "addr:full":"33 Perth St Brockville ON K6V 5C3",
    "addr:housenumber":"33",
    "addr:postcode":"k6v 5c3",
    "addr:street":"Perth St",
    "iso:country":"CA",
    "sg:address":"33 Perth St",
    "sg:city":"Brockville",
    "sg:classifiers":[
        {
            "category":"Real Estate",
            "subcategory":"Surveying",
            "type":"Services"
        }
    ],
    "sg:phone":"+1 613 342 7525",
    "sg:postcode":"K6V 5C3",
    "sg:province":"ON",
    "sg:tags":[
        "surveyor"
    ],
    "wof:name":"Jordan & Wiseman Surveying Ltd",
    "wof:placetype":"venue"
},
  "geometry": {"coordinates":[-75.68989562989999,44.5881080627],"type":"Point"}
}