{
  "type": "Feature",
  "properties": {
    "addr:full":"46 Racine Rd Etobicoke ON M9W 2Z3",
    "addr:housenumber":"46",
    "addr:postcode":"m9w 2z3",
    "addr:street":"Racine Rd",
    "iso:country":"CA",
    "sg:address":"46 Racine Rd",
    "sg:city":"Etobicoke",
    "sg:classifiers":[
        {
            "category":"Retail",
            "subcategory":"Auto Repair",
            "type":"Services"
        }
    ],
    "sg:phone":"+1 416 745 7745",
    "sg:postcode":"M9W 2Z3",
    "sg:province":"ON",
    "sg:tags":[
        "repairing",
        "automobile"
    ],
    "wof:name":"B & B Auto Repair",
    "wof:placetype":"venue"
},
  "geometry": {"coordinates":[-79.577057,43.71645],"type":"Point"}
}