{
  "type": "Feature",
  "properties": {
    "addr:full":"2073 Piper Lane London ON N5V 3S5",
    "addr:housenumber":"2073",
    "addr:postcode":"n5v 3s5",
    "addr:street":"Piper Lane",
    "iso:country":"CA",
    "sg:address":"2073 Piper Lane",
    "sg:city":"London",
    "sg:classifiers":[
        {
            "category":"Building & Trades",
            "subcategory":"Cleaning & Sanitation",
            "type":"Services"
        }
    ],
    "sg:phone":"+1 519 451 4349",
    "sg:postcode":"N5V 3S5",
    "sg:province":"ON",
    "sg:tags":[
        "snow",
        "removal"
    ],
    "wof:name":"Doug's Luxury Lawn Maintenance",
    "wof:placetype":"venue"
},
  "geometry": {"coordinates":[-81.16690800000001,43.024296],"type":"Point"}
}