{
  "type": "Feature",
  "properties": {
    "addr:full":"SE 2-10-1E Oak Bluff MB R0G 1N0",
    "addr:housenumber":"2-10-1e",
    "addr:postcode":"r0g 1n0",
    "addr:street":"Se;Bluff",
    "iso:country":"CA",
    "sg:address":"SE 2-10-1E",
    "sg:city":"Oak Bluff",
    "sg:classifiers":[
        {
            "category":"Freight",
            "type":"Transportation"
        }
    ],
    "sg:phone":"+1 204 895 8441",
    "sg:postcode":"R0G 1N0",
    "sg:province":"MB",
    "sg:tags":[
        "mobile",
        "home"
    ],
    "wof:name":"Ken Klassen A-1 Trucking",
    "wof:placetype":"venue"
},
  "geometry": {"coordinates":[-97.32415,49.773743],"type":"Point"}
}