{
  "type": "Feature",
  "properties": {
    "addr:full":"Vancouver BC V6Z 2L2",
    "addr:postcode":"v6z 2l2",
    "iso:country":"CA",
    "sg:city":"Vancouver",
    "sg:classifiers":[
        {
            "category":"Shopping",
            "subcategory":"Clothing, Apparel, & Fashions",
            "type":"Retail Goods"
        }
    ],
    "sg:phone":"+1 604 688 2030",
    "sg:postcode":"V6Z 2L2",
    "sg:province":"BC",
    "sg:tags":[
        "swimwear",
        "accessory"
    ],
    "wof:name":"Just Cruisin' Shoppe",
    "wof:placetype":"venue"
},
  "geometry": {"coordinates":[-123.12153600000001,49.281254],"type":"Point"}
}