{
  "type": "Feature",
  "properties": {
    "addr:full":"RR 2 STN A Brampton ON L6V 1A1",
    "addr:postcode":"l6v 1a1",
    "addr:street":"Rr 2 Stn A",
    "iso:country":"CA",
    "sg:address":"RR 2 STN A",
    "sg:city":"Brampton",
    "sg:classifiers":[
        {
            "category":"Travel",
            "subcategory":"Hotels & Motels",
            "type":"Entertainment"
        }
    ],
    "sg:phone":"+1 905 451 0707",
    "sg:postcode":"L6V 1A1",
    "sg:province":"ON",
    "wof:name":"Flowertown Motel",
    "wof:placetype":"venue"
},
  "geometry": {"coordinates":[-79.75872802729999,43.6843032837],"type":"Point"}
}