{
  "type": "Feature",
  "properties": {
    "addr:full":"310 Jessop Ave Saskatoon SK S7N 1Y6",
    "addr:housenumber":"310",
    "addr:postcode":"s7n 1y6",
    "addr:street":"Jessop Ave",
    "iso:country":"CA",
    "sg:address":"310 Jessop Ave",
    "sg:city":"Saskatoon",
    "sg:classifiers":[
        {
            "category":"Retail",
            "subcategory":"Animal Services",
            "type":"Services"
        }
    ],
    "sg:phone":"+1 306 955 7297",
    "sg:postcode":"S7N 1Y6",
    "sg:province":"SK",
    "sg:tags":[
        "pet",
        "grooming",
        "washing"
    ],
    "wof:name":"Paws Awhile Pet Hotel Ltd",
    "wof:placetype":"venue"
},
  "geometry": {"coordinates":[-106.593223572,52.1299095154],"type":"Point"}
}