{
  "type": "Feature",
  "properties": {
    "addr:full":"6955 Frontenac St Vancouver BC V5S 3T4",
    "addr:housenumber":"6955",
    "addr:postcode":"v5s 3t4",
    "addr:street":"Frontenac St",
    "iso:country":"CA",
    "sg:address":"6955 Frontenac St",
    "sg:city":"Vancouver",
    "sg:classifiers":[
        {
            "category":"Education",
            "subcategory":"School",
            "type":"Public Place"
        }
    ],
    "sg:phone":"+1 604 713 4760",
    "sg:postcode":"V5S 3T4",
    "sg:province":"BC",
    "wof:name":"Champlain Heights Elementary",
    "wof:placetype":"venue"
},
  "geometry": {"coordinates":[-123.026932,49.220493],"type":"Point"}
}