{
  "type": "Feature",
  "properties": {
    "addr:full":"3755 Portage Ave Winnipeg MB R3K 0X5",
    "addr:housenumber":"3755",
    "addr:postcode":"r3k 0x5",
    "addr:street":"Portage Ave",
    "iso:country":"CA",
    "sg:address":"3755 Portage Ave",
    "sg:city":"Winnipeg",
    "sg:classifiers":[
        {
            "category":"Autos & Motor Vehicles",
            "subcategory":"Fuel & Gas Station",
            "type":"Retail Goods"
        }
    ],
    "sg:phone":"+1 204 837 7451",
    "sg:postcode":"R3K 0X5",
    "sg:province":"MB",
    "sg:tags":[
        "oil"
    ],
    "wof:name":"Red River CO-Operative Ltd",
    "wof:placetype":"venue"
},
  "geometry": {"coordinates":[-97.3184127808,49.8816108704],"type":"Point"}
}