{
  "type": "Feature",
  "properties": {
    "addr:full":"Montreal QC H2Z 1X4",
    "addr:postcode":"h2z 1x4",
    "iso:country":"CA",
    "sg:city":"Montreal",
    "sg:classifiers":[
        {
            "category":"Manufacturing",
            "subcategory":"Printing",
            "type":"Manufacturing & Wholesale Goods"
        }
    ],
    "sg:phone":"+1 514 842 8024",
    "sg:postcode":"H2Z 1X4",
    "sg:province":"QC",
    "sg:tags":[
        "newspaper"
    ],
    "wof:name":"Nouvelles Chinoises",
    "wof:placetype":"venue"
},
  "geometry": {"coordinates":[-73.55976099999999,45.510715],"type":"Point"}
}