{
  "type": "Feature",
  "properties": {
    "addr:full":"213 Tudhope St Espanola ON P5E 1A2",
    "addr:housenumber":"213",
    "addr:postcode":"p5e 1a2",
    "addr:street":"Tudhope St",
    "iso:country":"CA",
    "sg:address":"213 Tudhope St",
    "sg:city":"Espanola",
    "sg:classifiers":[
        {
            "category":"Organizations",
            "subcategory":"Religious Organization",
            "type":"Services"
        }
    ],
    "sg:phone":"+1 705 869 1244",
    "sg:postcode":"P5E 1A2",
    "sg:province":"ON",
    "sg:tags":[
        "church"
    ],
    "wof:name":"Anglican Church St George",
    "wof:placetype":"venue"
},
  "geometry": {"coordinates":[-81.773872,46.263905],"type":"Point"}
}