{
  "type": "Feature",
  "properties": {
    "addr:full":"8523 Eacrett Rd Radium Hot Springs BC V0A 1M0",
    "addr:postcode":"8523;v0a 1m0",
    "addr:street":"Eacrett Rd",
    "iso:country":"CA",
    "sg:address":"8523 Eacrett Rd",
    "sg:city":"Radium Hot Springs",
    "sg:classifiers":[
        {
            "category":"Travel",
            "subcategory":"Campground",
            "type":"Entertainment"
        }
    ],
    "sg:phone":"+1 250 347 9095",
    "sg:postcode":"V0A 1M0",
    "sg:province":"BC",
    "wof:name":"Mountain Shadows Resort Ltd",
    "wof:placetype":"venue"
},
  "geometry": {"coordinates":[-116.071266174,50.6213645935],"type":"Point"}
}