{
  "type": "Feature",
  "properties": {
    "addr:full":"484 Plains Rd E Burlington ON L7T 2E1",
    "addr:housenumber":"484",
    "addr:postcode":"l7t 2e1",
    "addr:street":"Plains Rd E",
    "iso:country":"CA",
    "sg:address":"484 Plains Rd E",
    "sg:city":"Burlington",
    "sg:classifiers":[
        {
            "category":"Home & Garden",
            "subcategory":"Hardware",
            "type":"Retail Goods"
        }
    ],
    "sg:phone":"+1 905 639 5270",
    "sg:postcode":"L7T 2E1",
    "sg:province":"ON",
    "wof:name":"Aldershot Home Hardware",
    "wof:placetype":"venue"
},
  "geometry": {"coordinates":[-79.83659400000001,43.318699],"type":"Point"}
}