{
  "type": "Feature",
  "properties": {
    "addr:full":"1149 Boul Saint-Luc Saint-Luc QC J2W 1B2",
    "addr:housenumber":"1149",
    "addr:postcode":"j2w 1b2",
    "addr:street":"Boul Saint-Luc",
    "iso:country":"CA",
    "sg:address":"1149 Boul Saint-Luc",
    "sg:city":"Saint-Luc",
    "sg:classifiers":[
        {
            "category":"Food & Beverages",
            "subcategory":"Groceries & Convenience Stores",
            "type":"Retail Goods"
        }
    ],
    "sg:phone":"+1 450 348 1877",
    "sg:postcode":"J2W 1B2",
    "sg:province":"QC",
    "wof:name":"Depanneur St-Luc Enr",
    "wof:placetype":"venue"
},
  "geometry": {"coordinates":[-73.3726806641,45.3773574829],"type":"Point"}
}