{
  "type": "Feature",
  "properties": {
    "iso:country":"CA",
    "sg:address":"29 Muir Rd",
    "sg:city":"Winnipeg",
    "sg:classifiers":[
        {
            "category":"Wholesale",
            "subcategory":"Machinery & Supplies",
            "type":"Manufacturing & Wholesale Goods"
        }
    ],
    "sg:phone":"+1 204 632 9771",
    "sg:postcode":"R2X 2X7",
    "sg:province":"MB",
    "sg:tags":[
        "director",
        "funeral"
    ],
    "wof:name":"Colonial Caskets Ltd",
    "wof:placetype":"venue"
},
  "geometry": {"coordinates":[-97.1913528442,49.9422302246],"type":"Point"}
}