{
  "type": "Feature",
  "properties": {
    "addr:full":"116633 Grey Rd 3 Desboro ON N0H 1K0",
    "addr:housenumber":"116633",
    "addr:postcode":"n0h 1k0",
    "addr:street":"Grey Rd 3",
    "iso:country":"CA",
    "sg:address":"116633 Grey Rd 3",
    "sg:city":"Desboro",
    "sg:classifiers":[
        {
            "category":"Manufacturing",
            "subcategory":"Building Materials",
            "type":"Manufacturing & Wholesale Goods"
        }
    ],
    "sg:phone":"+1 519 794 3132",
    "sg:postcode":"N0H 1K0",
    "sg:province":"ON",
    "sg:tags":[
        "maker",
        "cabinet"
    ],
    "wof:name":"Durnin's Cabinets & Millwork",
    "wof:placetype":"venue"
},
  "geometry": {"coordinates":[-80.99191999999999,44.406384],"type":"Point"}
}