{
  "type": "Feature",
  "properties": {
    "addr:full":"1st Ave W Central Butte SK S0H 0T0",
    "addr:postcode":"s0h 0t0",
    "addr:street":"1St Ave W Central",
    "iso:country":"CA",
    "sg:address":"1st Ave W",
    "sg:city":"Central Butte",
    "sg:classifiers":[
        {
            "category":"Wholesale",
            "subcategory":"Farm Supplies",
            "type":"Manufacturing & Wholesale Goods"
        }
    ],
    "sg:phone":"+1 306 796 4490",
    "sg:postcode":"S0H 0T0",
    "sg:province":"SK",
    "sg:tags":[
        "feed"
    ],
    "wof:name":"Central Butte Feeds",
    "wof:placetype":"venue"
},
  "geometry": {"coordinates":[-106.51249694800001,50.7961540222],"type":"Point"}
}