{
  "type": "Feature",
  "properties": {
    "addr:full":"Vernon BC V1T 2C2",
    "addr:postcode":"v1t 2c2",
    "iso:country":"CA",
    "sg:city":"Vernon",
    "sg:classifiers":[
        {
            "category":"Government",
            "subcategory":"Office",
            "type":"Public Place"
        }
    ],
    "sg:phone":"+1 250 549 5460",
    "sg:postcode":"V1T 2C2",
    "sg:province":"BC",
    "wof:name":"British Columbia Alcohol Clnc",
    "wof:placetype":"venue"
},
  "geometry": {"coordinates":[-119.272407532,50.263671875],"type":"Point"}
}