{
  "type": "Feature",
  "properties": {
    "addr:full":"17 Robson Rd Leamington ON N8H 2M8",
    "addr:housenumber":"17",
    "addr:postcode":"n8h 2m8",
    "addr:street":"Robson Rd",
    "iso:country":"CA",
    "sg:address":"17 Robson Rd",
    "sg:city":"Leamington",
    "sg:classifiers":[
        {
            "category":"Restaurant",
            "type":"Food & Drink"
        }
    ],
    "sg:phone":"+1 519 322 5940",
    "sg:postcode":"N8H 2M8",
    "sg:province":"ON",
    "wof:name":"Ray's Ribhouse",
    "wof:placetype":"venue"
},
  "geometry": {"coordinates":[-82.600365,42.029869],"type":"Point"}
}