{
  "type": "Feature",
  "properties": {
    "iso:country":"CA",
    "sg:address":"51 Forest Hills Pky",
    "sg:city":"Dartmouth",
    "sg:classifiers":[
        {
            "category":"Organizations",
            "subcategory":"Non-profit Organization",
            "type":"Services"
        }
    ],
    "sg:phone":"+1 902 462 5706",
    "sg:postcode":"B2W 6C6",
    "sg:province":"NS",
    "sg:tags":[
        "charitable",
        "institution"
    ],
    "wof:name":"Cole Harbour Parks & Trails",
    "wof:placetype":"venue"
},
  "geometry": {"coordinates":[-63.4908676147,44.6827468872],"type":"Point"}
}