{
  "type": "Feature",
  "properties": {
    "addr:full":"41 Mill St W Leamington ON N8H 1S7",
    "addr:housenumber":"41",
    "addr:postcode":"n8h 1s7",
    "addr:street":"Mill St W",
    "iso:country":"CA",
    "sg:address":"41 Mill St W",
    "sg:city":"Leamington",
    "sg:classifiers":[
        {
            "category":"Professional",
            "subcategory":"Accounting & Tax Preparation",
            "type":"Services"
        }
    ],
    "sg:phone":"+1 519 326 8671",
    "sg:postcode":"N8H 1S7",
    "sg:province":"ON",
    "sg:tags":[
        "accountant"
    ],
    "wof:name":"Shilson, Murray CA",
    "wof:placetype":"venue"
},
  "geometry": {"coordinates":[-82.60149383540001,42.0523986816],"type":"Point"}
}