{
  "type": "Feature",
  "properties": {
    "addr:full":"951 Roselawn Ave York ON M6B 1B6",
    "addr:housenumber":"951",
    "addr:postcode":"m6b 1b6",
    "addr:street":"Roselawn Ave",
    "iso:country":"CA",
    "sg:address":"951 Roselawn Ave",
    "sg:city":"York",
    "sg:classifiers":[
        {
            "category":"Autos & Motor Vehicles",
            "subcategory":"Auto Supplies",
            "type":"Retail Goods"
        }
    ],
    "sg:phone":"+1 416 787 1278",
    "sg:postcode":"M6B 1B6",
    "sg:province":"ON",
    "sg:tags":[
        "tire"
    ],
    "wof:name":"G & M Wholesale Tire Distr",
    "wof:placetype":"venue"
},
  "geometry": {"coordinates":[-79.444229126,43.7014465332],"type":"Point"}
}