{
  "type": "Feature",
  "properties": {
    "addr:full":"15 Rte Maritime Baie-Comeau QC G4Z 2L6",
    "addr:housenumber":"15",
    "addr:postcode":"g4z 2l6",
    "addr:street":"Rte Maritime",
    "iso:country":"CA",
    "sg:address":"15 Rte Maritime",
    "sg:city":"Baie-Comeau",
    "sg:classifiers":[
        {
            "category":"Professional",
            "subcategory":"Business Services",
            "type":"Services"
        }
    ],
    "sg:phone":"+1 418 296 6637",
    "sg:postcode":"G4Z 2L6",
    "sg:province":"QC",
    "sg:tags":[
        "consultant",
        "oil",
        "petroleum"
    ],
    "wof:name":"Petroles Paul Larouche Inc",
    "wof:placetype":"venue"
},
  "geometry": {"coordinates":[-68.134438,49.240479],"type":"Point"}
}