{
  "type": "Feature",
  "properties": {
    "addr:full":"905 Rue DE Nemours #223 Charlesbourg QC G1H 6Z5",
    "addr:housenumber":"905",
    "addr:postcode":"g1h 6z5",
    "addr:street":"Rue De Nemours # 223",
    "iso:country":"CA",
    "sg:address":"905 Rue DE Nemours #223",
    "sg:city":"Charlesbourg",
    "sg:classifiers":[
        {
            "category":"Shopping",
            "type":"Retail Goods"
        }
    ],
    "sg:phone":"+1 418 624 1329",
    "sg:postcode":"G1H 6Z5",
    "sg:province":"QC",
    "sg:tags":[
        "furniture",
        "typewriter"
    ],
    "wof:name":"Machines DE Bureau Expert",
    "wof:placetype":"venue"
},
  "geometry": {"coordinates":[-71.2402267456,46.850818634],"type":"Point"}
}