{
  "type": "Feature",
  "properties": {
    "addr:full":"9002 Oak St Vancouver BC V6P 4B9",
    "addr:housenumber":"9002",
    "addr:postcode":"v6p 4b9",
    "addr:street":"Oak St",
    "iso:country":"CA",
    "sg:address":"9002 Oak St",
    "sg:city":"Vancouver",
    "sg:classifiers":[
        {
            "category":"Building & Trades",
            "subcategory":"Plumbing",
            "type":"Services"
        }
    ],
    "sg:phone":"+1 604 324 7717",
    "sg:postcode":"V6P 4B9",
    "sg:province":"BC",
    "sg:tags":[
        "conditioning",
        "air",
        "system",
        "contractor"
    ],
    "wof:name":"Billco Industries Ltd",
    "wof:placetype":"venue"
},
  "geometry": {"coordinates":[-123.13005065900001,49.2029037476],"type":"Point"}
}