{
  "type": "Feature",
  "properties": {
    "addr:full":"3405 South Millway Mississauga ON L5L 3R1",
    "addr:housenumber":"3405",
    "addr:postcode":"l5l 3r1",
    "addr:street":"South Millway",
    "iso:country":"CA",
    "sg:address":"3405 South Millway",
    "sg:city":"Mississauga",
    "sg:classifiers":[
        {
            "category":"Health Services",
            "subcategory":"Doctor",
            "type":"Services"
        }
    ],
    "sg:phone":"+1 905 607 9997",
    "sg:postcode":"L5L 3R1",
    "sg:province":"ON",
    "sg:tags":[
        "dentist"
    ],
    "wof:name":"Sawmill Valley Dental",
    "wof:placetype":"venue"
},
  "geometry": {"coordinates":[-79.67682600000001,43.544365],"type":"Point"}
}