{
  "type": "Feature",
  "properties": {
    "addr:full":"225 Rue Mill North Hatley QC J0B 2C0",
    "addr:housenumber":"225",
    "addr:postcode":"j0b 2c0",
    "addr:street":"Rue Mill",
    "iso:country":"CA",
    "sg:address":"225 Rue Mill",
    "sg:city":"North Hatley",
    "sg:classifiers":[
        {
            "category":"Travel",
            "subcategory":"Hotels & Motels",
            "type":"Entertainment"
        }
    ],
    "sg:phone":"+1 819 842 2380",
    "sg:postcode":"J0B 2C0",
    "sg:province":"QC",
    "wof:name":"Moulin DE North Hatley",
    "wof:placetype":"venue"
},
  "geometry": {"coordinates":[-71.97379302980001,45.2768249512],"type":"Point"}
}