{
  "type": "Feature",
  "properties": {
    "addr:full":"Pl Daviault Fermont QC G0G 1J0",
    "addr:postcode":"g0g 1j0",
    "addr:street":"Pl Daviault",
    "iso:country":"CA",
    "sg:address":"Pl Daviault",
    "sg:city":"Fermont",
    "sg:classifiers":[
        {
            "category":"Mining & Drilling",
            "type":"Manufacturing & Wholesale Goods"
        }
    ],
    "sg:phone":"+1 418 287 5475",
    "sg:postcode":"G0G 1J0",
    "sg:province":"QC",
    "sg:tags":[
        "company"
    ],
    "wof:name":"Compagnie Miniere Quebec Cart",
    "wof:placetype":"venue"
},
  "geometry": {"coordinates":[-67.09191894529999,52.8022956848],"type":"Point"}
}