{
  "type": "Feature",
  "properties": {
    "addr:full":"474 Island Hwy Victoria BC V9B 1H5",
    "addr:housenumber":"474",
    "addr:postcode":"v9b 1h5",
    "addr:street":"Island Hwy",
    "iso:country":"CA",
    "sg:address":"474 Island Hwy",
    "sg:city":"Victoria",
    "sg:classifiers":[
        {
            "category":"Retail",
            "subcategory":"Auto Repair",
            "type":"Services"
        }
    ],
    "sg:phone":"+1 250 478 5922",
    "sg:postcode":"V9B 1H5",
    "sg:province":"BC",
    "sg:tags":[
        "repairing",
        "automobile"
    ],
    "wof:name":"Starr Automotive",
    "wof:placetype":"venue"
},
  "geometry": {"coordinates":[-123.364517212,48.428314209],"type":"Point"}
}