{
  "type": "Feature",
  "properties": {
    "iso:country":"CA",
    "sg:city":"Quebec",
    "sg:classifiers":[
        {
            "category":"Manufacturing",
            "subcategory":"Printing",
            "type":"Manufacturing & Wholesale Goods"
        }
    ],
    "sg:phone":"+1 418 687 1319",
    "sg:postcode":"G1N 4L2",
    "sg:province":"QC",
    "sg:tags":[
        "printer"
    ],
    "wof:name":"Club Imprimerie Inc",
    "wof:placetype":"venue"
},
  "geometry": {"coordinates":[-71.282448,46.800095],"type":"Point"}
}