{
  "type": "Feature",
  "properties": {
    "addr:full":"321 Rue Saint-Jean Drummondville QC J2B 5L5",
    "addr:housenumber":"321",
    "addr:postcode":"j2b 5l5",
    "addr:street":"Rue Saint-Jean",
    "iso:country":"CA",
    "sg:address":"321 Rue Saint-Jean",
    "sg:city":"Drummondville",
    "sg:classifiers":[
        {
            "category":"Professional",
            "subcategory":"Business Services",
            "type":"Services"
        }
    ],
    "sg:phone":"+1 819 474 7717",
    "sg:postcode":"J2B 5L5",
    "sg:province":"QC",
    "sg:tags":[
        "interior",
        "consultant",
        "design",
        "decorator"
    ],
    "wof:name":"Draperies Marchand Inc",
    "wof:placetype":"venue"
},
  "geometry": {"coordinates":[-72.484077,45.876999],"type":"Point"}
}