{
  "type": "Feature",
  "properties": {
    "addr:full":"Sechelt BC V0N 3A0",
    "addr:postcode":"v0n 3a0",
    "iso:country":"CA",
    "sg:city":"Sechelt",
    "sg:classifiers":[
        {
            "category":"Home & Garden",
            "subcategory":"Furniture",
            "type":"Retail Goods"
        }
    ],
    "sg:phone":"+1 604 740 0894",
    "sg:postcode":"V0N 3A0",
    "sg:province":"BC",
    "sg:tags":[
        "mattress"
    ],
    "wof:name":"Spencers Furniture",
    "wof:placetype":"venue"
},
  "geometry": {"coordinates":[-123.754868,49.4716],"type":"Point"}
}