{
  "type": "Feature",
  "properties": {
    "iso:country":"CA",
    "sg:address":"240 Victoria St",
    "sg:city":"Tweed",
    "sg:classifiers":[
        {
            "category":"Restaurant",
            "type":"Food & Drink"
        }
    ],
    "sg:phone":"+1 613 478 2374",
    "sg:postcode":"K0K 3J0",
    "sg:province":"ON",
    "sg:tags":[
        "caterer"
    ],
    "wof:name":"Duffer's Chuckwagon",
    "wof:placetype":"venue"
},
  "geometry": {"coordinates":[-77.3126068115,44.4768218994],"type":"Point"}
}