{
  "type": "Feature",
  "properties": {
    "iso:country":"CA",
    "sg:address":"106 Colonnade Rd #220",
    "sg:city":"Nepean",
    "sg:classifiers":[
        {
            "category":"Insurance",
            "subcategory":"Insurance Agent",
            "type":"Services"
        }
    ],
    "sg:phone":"+1 613 723 4730",
    "sg:postcode":"K2E 7L6",
    "sg:province":"ON",
    "wof:name":"Taylor Group of CO",
    "wof:placetype":"venue"
},
  "geometry": {"coordinates":[-75.7059707642,45.3466491699],"type":"Point"}
}