{
  "type": "Feature",
  "properties": {
    "addr:full":"347 Durham St Walkerton ON N0G 2V0",
    "addr:housenumber":"347",
    "addr:postcode":"n0g 2v0",
    "addr:street":"Durham St",
    "iso:country":"CA",
    "sg:address":"347 Durham St",
    "sg:city":"Walkerton",
    "sg:classifiers":[
        {
            "category":"Personal",
            "subcategory":"Beauty Salon",
            "type":"Services"
        }
    ],
    "sg:phone":"+1 519 881 0842",
    "sg:postcode":"N0G 2V0",
    "sg:province":"ON",
    "wof:name":"Creative Illusions Unisex",
    "wof:placetype":"venue"
},
  "geometry": {"coordinates":[-81.147896,44.13287],"type":"Point"}
}