{
  "type": "Feature",
  "properties": {
    "addr:full":"1252 Lawrence Ave E North York ON M3A 1C3",
    "addr:housenumber":"1252",
    "addr:postcode":"m3a 1c3",
    "addr:street":"Lawrence Ave E",
    "iso:country":"CA",
    "sg:address":"1252 Lawrence Ave E",
    "sg:city":"North York",
    "sg:classifiers":[
        {
            "category":"Restaurant",
            "type":"Food & Drink"
        }
    ],
    "sg:phone":"+1 416 443 3376",
    "sg:postcode":"M3A 1C3",
    "sg:province":"ON",
    "wof:name":"Triple Crown Bar & Grill",
    "wof:placetype":"venue"
},
  "geometry": {"coordinates":[-79.31881,43.741364],"type":"Point"}
}