{
  "type": "Feature",
  "properties": {
    "addr:full":"Laval QC H7K 3G4",
    "addr:postcode":"qc h7k 3g4",
    "iso:country":"CA",
    "sg:city":"Laval",
    "sg:classifiers":[
        {
            "category":"Personal",
            "subcategory":"Beauty Salon",
            "type":"Services"
        }
    ],
    "sg:phone":"+1 450 669 1362",
    "sg:postcode":"H7K 3G4",
    "sg:province":"QC",
    "wof:name":"Josee Esthetique Elle Et Lui",
    "wof:placetype":"venue"
},
  "geometry": {"coordinates":[-73.7409667969,45.6165275574],"type":"Point"}
}