{
  "type": "Feature",
  "properties": {
    "addr:full":"4910 47 Ave St Paul AB T0A 3A4",
    "addr:housenumber":"4910",
    "addr:postcode":"t0a 3a4",
    "addr:street":"47 Ave",
    "iso:country":"CA",
    "sg:address":"4910 47 Ave",
    "sg:city":"St Paul",
    "sg:classifiers":[
        {
            "category":"Health Services",
            "subcategory":"Clinic",
            "type":"Services"
        }
    ],
    "sg:phone":"+1 780 645 7798",
    "sg:postcode":"T0A 3A4",
    "sg:province":"AB",
    "wof:name":"Behavior Outreach Svc",
    "wof:placetype":"venue"
},
  "geometry": {"coordinates":[-111.29486846899999,53.988483429],"type":"Point"}
}