{
  "type": "Feature",
  "properties": {
    "iso:country":"CA",
    "sg:address":"52 Brentwood Blvd",
    "sg:city":"Sherwood Park",
    "sg:classifiers":[
        {
            "category":"Insurance",
            "subcategory":"Insurance Agent",
            "type":"Services"
        }
    ],
    "sg:phone":"+1 780 467 2122",
    "sg:postcode":"T8A 2H6",
    "sg:province":"AB",
    "wof:name":"Tailor Made Insurance Svc",
    "wof:placetype":"venue"
},
  "geometry": {"coordinates":[-113.295249939,53.5148963928],"type":"Point"}
}