{
  "type": "Feature",
  "properties": {
    "addr:full":"9325 Main St Chilliwack BC V2P 4M3",
    "addr:housenumber":"9325",
    "addr:postcode":"v2p 4m3",
    "addr:street":"Main St",
    "iso:country":"CA",
    "sg:address":"9325 Main St",
    "sg:city":"Chilliwack",
    "sg:classifiers":[
        {
            "category":"Shopping",
            "subcategory":"Department Store",
            "type":"Retail Goods"
        }
    ],
    "sg:phone":"+1 604 792 7111",
    "sg:postcode":"V2P 4M3",
    "sg:province":"BC",
    "sg:tags":[
        "shop"
    ],
    "wof:name":"Liquidation World Inc",
    "wof:placetype":"venue"
},
  "geometry": {"coordinates":[-121.955513001,49.1713142395],"type":"Point"}
}