{
  "type": "Feature",
  "properties": {
    "addr:full":"Timmins ON P4R 1A1",
    "addr:postcode":"p4r 1a1",
    "iso:country":"CA",
    "sg:city":"Timmins",
    "sg:classifiers":[
        {
            "category":"Shopping",
            "subcategory":"Luggage & Leather Goods",
            "type":"Retail Goods"
        }
    ],
    "sg:phone":"+1 705 268 4905",
    "sg:postcode":"P4R 1A1",
    "sg:province":"ON",
    "sg:tags":[
        "travel",
        "accessory"
    ],
    "wof:name":"Bentley Leather",
    "wof:placetype":"venue"
},
  "geometry": {"coordinates":[-81.381744,48.472622],"type":"Point"}
}