{
  "type": "Feature",
  "properties": {
    "addr:full":"752 Sackville Dr Lower Sackville NS B4E 1R7",
    "addr:housenumber":"752",
    "addr:postcode":"b4e 1r7",
    "addr:street":"Sackville Dr",
    "iso:country":"CA",
    "sg:address":"752 Sackville Dr",
    "sg:city":"Lower Sackville",
    "sg:classifiers":[
        {
            "category":"Shopping",
            "subcategory":"Pharmacy",
            "type":"Retail Goods"
        }
    ],
    "sg:phone":"+1 902 865 5820",
    "sg:postcode":"B4E 1R7",
    "sg:province":"NS",
    "wof:name":"Sobeys Pharmacy",
    "wof:placetype":"venue"
},
  "geometry": {"coordinates":[-63.6919898987,44.7725105286],"type":"Point"}
}