{
  "type": "Feature",
  "properties": {
    "addr:full":"1142 Rue Notre-Dame Lachine QC H8S 2C4",
    "addr:housenumber":"1142",
    "addr:postcode":"h8s 2c4",
    "addr:street":"Rue Notre-Dame",
    "iso:country":"CA",
    "sg:address":"1142 Rue Notre-Dame",
    "sg:city":"Lachine",
    "sg:classifiers":[
        {
            "category":"Health Services",
            "subcategory":"Chiropractor",
            "type":"Services"
        }
    ],
    "sg:phone":"+1 514 637 3652",
    "sg:postcode":"H8S 2C4",
    "sg:province":"QC",
    "wof:name":"Lalonde, Richard E DC",
    "wof:placetype":"venue"
},
  "geometry": {"coordinates":[-73.6740112305,45.4350585938],"type":"Point"}
}