{
  "type": "Feature",
  "properties": {
    "addr:full":"Calgary AB T2E 6N4",
    "addr:postcode":"t2e 6n4",
    "iso:country":"CA",
    "sg:city":"Calgary",
    "sg:classifiers":[
        {
            "category":"Professional",
            "subcategory":"Lawyer & Legal Services",
            "type":"Services"
        }
    ],
    "sg:phone":"+1 403 262 7141",
    "sg:postcode":"T2E 6N4",
    "sg:province":"AB",
    "sg:tags":[
        "attorney"
    ],
    "wof:name":"Muszynski Law Office",
    "wof:placetype":"venue"
},
  "geometry": {"coordinates":[-114.032646,51.083424],"type":"Point"}
}