{
  "type": "Feature",
  "properties": {
    "iso:country":"CA",
    "sg:address":"619 Rue Emilien",
    "sg:city":"Charlesbourg",
    "sg:classifiers":[
        {
            "category":"Wholesale",
            "subcategory":"Hardware",
            "type":"Manufacturing & Wholesale Goods"
        }
    ],
    "sg:phone":"+1 418 622 7524",
    "sg:postcode":"G2L 2H6",
    "sg:province":"QC",
    "sg:tags":[
        "tool"
    ],
    "wof:name":"Outillage Ser-Pro Enr",
    "wof:placetype":"venue"
},
  "geometry": {"coordinates":[-71.234612,46.881035],"type":"Point"}
}