{
  "type": "Feature",
  "properties": {
    "addr:full":"5750 Cedarbridge Way Richmond BC V6X 2A7",
    "addr:housenumber":"5750",
    "addr:postcode":"v6x 2a7",
    "addr:street":"Cedarbridge Way",
    "iso:country":"CA",
    "sg:address":"5750 Cedarbridge Way",
    "sg:city":"Richmond",
    "sg:classifiers":[
        {
            "category":"Autos & Motor Vehicles",
            "subcategory":"Automobile Sales",
            "type":"Retail Goods"
        }
    ],
    "sg:phone":"+1 604 278 9688",
    "sg:postcode":"V6X 2A7",
    "sg:province":"BC",
    "sg:tags":[
        "equipment",
        "aircraft",
        "parts",
        "supply"
    ],
    "wof:name":"Sil Industries Ltd",
    "wof:placetype":"venue"
},
  "geometry": {"coordinates":[-123.141960144,49.1736602783],"type":"Point"}
}