{
  "type": "Feature",
  "properties": {
    "addr:full":"5705 Av Westluke Cote Saint-Luc QC H4W 2N5",
    "addr:housenumber":"5705",
    "addr:postcode":"h4w 2n5",
    "addr:street":"Av Westluke Cote",
    "iso:country":"CA",
    "sg:address":"5705 Av Westluke",
    "sg:city":"Cote Saint-Luc",
    "sg:classifiers":[
        {
            "category":"Wholesale",
            "subcategory":"Machinery & Supplies",
            "type":"Manufacturing & Wholesale Goods"
        }
    ],
    "sg:phone":"+1 514 489 2595",
    "sg:postcode":"H4W 2N5",
    "sg:province":"QC",
    "sg:tags":[
        "tool"
    ],
    "wof:name":"Di Fede Import Inc",
    "wof:placetype":"venue"
},
  "geometry": {"coordinates":[-73.670258,45.45966],"type":"Point"}
}