{
  "type": "Feature",
  "properties": {
    "iso:country":"CA",
    "sg:address":"20800 Westminster Hwy # 2113",
    "sg:city":"Richmond",
    "sg:classifiers":[
        {
            "category":"Building & Trades",
            "subcategory":"Electrical",
            "type":"Services"
        }
    ],
    "sg:phone":"+1 604 244 7161",
    "sg:postcode":"V6V 2W3",
    "sg:province":"BC",
    "sg:tags":[
        "electric",
        "contractor"
    ],
    "wof:name":"Dodds & Wright Consulting Ltd",
    "wof:placetype":"venue"
},
  "geometry": {"coordinates":[-122.992622376,49.1692047119],"type":"Point"}
}