{
  "type": "Feature",
  "properties": {
    "addr:full":"2136 Huron Church Rd Windsor ON N9C 2L7",
    "addr:housenumber":"2136",
    "addr:postcode":"n9c 2l7",
    "addr:street":"Huron Church Rd",
    "iso:country":"CA",
    "sg:address":"2136 Huron Church Rd",
    "sg:city":"Windsor",
    "sg:classifiers":[
        {
            "category":"Manufacturing",
            "subcategory":"Metals",
            "type":"Manufacturing & Wholesale Goods"
        }
    ],
    "sg:phone":"+1 519 969 5711",
    "sg:postcode":"N9C 2L7",
    "sg:province":"ON",
    "sg:tags":[
        "plate",
        "name"
    ],
    "wof:name":"Altus Manufacturing",
    "wof:placetype":"venue"
},
  "geometry": {"coordinates":[-83.0511016846,42.2767829895],"type":"Point"}
}