{
  "type": "Feature",
  "properties": {
    "addr:full":"1415 Main St N Callander ON P0H 1H0",
    "addr:housenumber":"1415",
    "addr:postcode":"p0h 1h0",
    "addr:street":"Main St N",
    "iso:country":"CA",
    "sg:address":"1415 Main St N",
    "sg:city":"Callander",
    "sg:classifiers":[
        {
            "category":"Professional",
            "subcategory":"Business Services",
            "type":"Services"
        }
    ],
    "sg:phone":"+1 705 752 1312",
    "sg:postcode":"P0H 1H0",
    "sg:province":"ON",
    "sg:tags":[
        "embroidery"
    ],
    "wof:name":"Wrightway Sportswear",
    "wof:placetype":"venue"
},
  "geometry": {"coordinates":[-79.362877,46.22316],"type":"Point"}
}