{
  "type": "Feature",
  "properties": {
    "addr:full":"59 Mearns Ave Bowmanville ON L1C 3L3",
    "addr:housenumber":"59",
    "addr:postcode":"l1c 3l3",
    "addr:street":"Mearns Ave",
    "iso:country":"CA",
    "sg:address":"59 Mearns Ave",
    "sg:city":"Bowmanville",
    "sg:classifiers":[
        {
            "category":"Wholesale",
            "subcategory":"Durable Goods & Equipment",
            "type":"Manufacturing & Wholesale Goods"
        }
    ],
    "sg:phone":"+1 905 623 2394",
    "sg:postcode":"L1C 3L3",
    "sg:province":"ON",
    "sg:tags":[
        "representative",
        "manufacturer"
    ],
    "wof:name":"Rlm Manufacturing",
    "wof:placetype":"venue"
},
  "geometry": {"coordinates":[-78.6669769287,43.9054031372],"type":"Point"}
}