{
  "type": "Feature",
  "properties": {
    "addr:full":"1663 7th Ave W Vancouver BC V6J 1S4",
    "addr:housenumber":"1663",
    "addr:postcode":"v6j 1s4",
    "addr:street":"7Th Ave W",
    "iso:country":"CA",
    "sg:address":"1663 7th Ave W",
    "sg:city":"Vancouver",
    "sg:classifiers":[
        {
            "category":"Professional",
            "subcategory":"Business Services",
            "type":"Services"
        }
    ],
    "sg:phone":"+1 604 734 3663",
    "sg:postcode":"V6J 1S4",
    "sg:province":"BC",
    "sg:tags":[
        "lecture",
        "bureau",
        "seminar"
    ],
    "wof:name":"National Speakers' Bureau",
    "wof:placetype":"venue"
},
  "geometry": {"coordinates":[-123.14238739,49.2655715942],"type":"Point"}
}