{
  "type": "Feature",
  "properties": {
    "addr:full":"Montreal QC H2J 3J5",
    "addr:postcode":"h2j 3j5",
    "iso:country":"CA",
    "sg:city":"Montreal",
    "sg:classifiers":[
        {
            "category":"Building & Trades",
            "subcategory":"Construction",
            "type":"Services"
        }
    ],
    "sg:phone":"+1 514 523 3600",
    "sg:postcode":"H2J 3J5",
    "sg:province":"QC",
    "sg:tags":[
        "maker",
        "cabinet"
    ],
    "wof:name":"Artebois",
    "wof:placetype":"venue"
},
  "geometry": {"coordinates":[-73.579697,45.529449],"type":"Point"}
}