{
  "type": "Feature",
  "properties": {
    "addr:full":"191 Samuelson St Cambridge ON N1R 1K2",
    "addr:housenumber":"191",
    "addr:postcode":"n1r 1k2",
    "addr:street":"Samuelson St",
    "iso:country":"CA",
    "sg:address":"191 Samuelson St",
    "sg:city":"Cambridge",
    "sg:classifiers":[
        {
            "category":"Manufacturing",
            "subcategory":"Lumber",
            "type":"Manufacturing & Wholesale Goods"
        }
    ],
    "sg:phone":"+1 905 796 5111",
    "sg:postcode":"N1R 1K2",
    "sg:province":"ON",
    "sg:tags":[
        "wood"
    ],
    "wof:name":"Jcr Woodworking CO",
    "wof:placetype":"venue"
},
  "geometry": {"coordinates":[-80.3044052124,43.3701591492],"type":"Point"}
}