{
  "type": "Feature",
  "properties": {
    "addr:full":"815 Rue Muir Saint-Laurent QC H4L 5H9",
    "addr:housenumber":"815",
    "addr:postcode":"h4l 5h9",
    "addr:street":"Rue Muir",
    "iso:country":"CA",
    "sg:address":"815 Rue Muir",
    "sg:city":"Saint-Laurent",
    "sg:classifiers":[
        {
            "category":"Wholesale",
            "subcategory":"Durable Goods & Equipment",
            "type":"Manufacturing & Wholesale Goods"
        }
    ],
    "sg:phone":"+1 514 748 0068",
    "sg:postcode":"H4L 5H9",
    "sg:province":"QC",
    "sg:tags":[
        "exporter"
    ],
    "wof:name":"Pexim-O Import-Export Ltee",
    "wof:placetype":"venue"
},
  "geometry": {"coordinates":[-73.67026519780001,45.5224113464],"type":"Point"}
}