{
  "type": "Feature",
  "properties": {
    "addr:full":"Highway 1 Elkhorn MB R0M 0N0",
    "addr:postcode":"r0m 0n0",
    "addr:street":"Highway 1",
    "iso:country":"CA",
    "sg:address":"Highway 1",
    "sg:city":"Elkhorn",
    "sg:classifiers":[
        {
            "category":"Museum",
            "type":"Entertainment"
        }
    ],
    "sg:phone":"+1 204 845 2604",
    "sg:postcode":"R0M 0N0",
    "sg:province":"MB",
    "wof:name":"Elkhorn Automobile Museum",
    "wof:placetype":"venue"
},
  "geometry": {"coordinates":[-101.230705,49.977234],"type":"Point"}
}