{
  "type": "Feature",
  "properties": {
    "iso:country":"CA",
    "sg:address":"232 King St",
    "sg:city":"Midland",
    "sg:classifiers":[
        {
            "category":"Home & Garden",
            "subcategory":"Garden Supply",
            "type":"Retail Goods"
        }
    ],
    "sg:phone":"+1 705 528 1333",
    "sg:postcode":"L4R 3M2",
    "sg:province":"ON",
    "sg:tags":[
        "center"
    ],
    "wof:name":"Shelley's Flower & Feed",
    "wof:placetype":"venue"
},
  "geometry": {"coordinates":[-79.886627,44.751137],"type":"Point"}
}