{
  "type": "Feature",
  "properties": {
    "iso:country":"CA",
    "sg:address":"1910 Ontario St",
    "sg:city":"Vancouver",
    "sg:classifiers":[
        {
            "category":"Wholesale",
            "subcategory":"Photographic Equipment",
            "type":"Manufacturing & Wholesale Goods"
        }
    ],
    "sg:phone":"+1 604 877 8558",
    "sg:postcode":"V5T 4G6",
    "sg:province":"BC",
    "sg:tags":[
        "audio"
    ],
    "wof:name":"Clark's Audio Visual Svc Ltd",
    "wof:placetype":"venue"
},
  "geometry": {"coordinates":[-123.104507446,49.2681312561],"type":"Point"}
}