{
  "type": "Feature",
  "properties": {
    "addr:full":"5875 Rue Belanger Saint-Leonard QC H1T 1G5",
    "addr:housenumber":"5875",
    "addr:postcode":"h1t 1g5",
    "addr:street":"Rue Belanger",
    "iso:country":"CA",
    "sg:address":"5875 Rue Belanger",
    "sg:city":"Saint-Leonard",
    "sg:classifiers":[
        {
            "category":"Retail",
            "subcategory":"Auto Repair",
            "type":"Services"
        }
    ],
    "sg:phone":"+1 514 721 9631",
    "sg:postcode":"H1T 1G5",
    "sg:province":"QC",
    "sg:tags":[
        "repairing",
        "automobile"
    ],
    "wof:name":"Levesque Turcotte Inc",
    "wof:placetype":"venue"
},
  "geometry": {"coordinates":[-73.572968,45.58252],"type":"Point"}
}