{
  "type": "Feature",
  "properties": {
    "iso:country":"CA",
    "sg:address":"190 Rue Saint-Charles O",
    "sg:city":"Longueuil",
    "sg:classifiers":[
        {
            "category":"Banks & Credit Unions",
            "subcategory":"Bank",
            "type":"Services"
        }
    ],
    "sg:phone":"+1 450 677 2867",
    "sg:postcode":"J4H 1C9",
    "sg:province":"QC",
    "wof:name":"Cibc",
    "wof:placetype":"venue"
},
  "geometry": {"coordinates":[-73.50658416749999,45.5428085327],"type":"Point"}
}