{
  "type": "Feature",
  "properties": {
    "addr:full":"1642 Main St Val Caron ON P3N 1R8",
    "addr:housenumber":"1642",
    "addr:postcode":"p3n 1r8",
    "addr:street":"Main St",
    "iso:country":"CA",
    "sg:address":"1642 Main St",
    "sg:city":"Val Caron",
    "sg:classifiers":[
        {
            "category":"Restaurant",
            "type":"Food & Drink"
        }
    ],
    "sg:phone":"+1 705 897 2586",
    "sg:postcode":"P3N 1R8",
    "sg:province":"ON",
    "wof:name":"Garlum Restaurant",
    "wof:placetype":"venue"
},
  "geometry": {"coordinates":[-81.00885,46.610577],"type":"Point"}
}