{
  "type": "Feature",
  "properties": {
    "addr:full":"1860 Bayview Ave North York ON M4G 3C8",
    "addr:housenumber":"1860",
    "addr:postcode":"m4g 3c8",
    "addr:street":"Bayview Ave",
    "iso:country":"CA",
    "sg:address":"1860 Bayview Ave",
    "sg:city":"North York",
    "sg:classifiers":[
        {
            "category":"Autos & Motor Vehicles",
            "subcategory":"Automobile Sales",
            "type":"Retail Goods"
        }
    ],
    "sg:phone":"+1 416 485 0350",
    "sg:postcode":"M4G 3C8",
    "sg:province":"ON",
    "sg:tags":[
        "car",
        "dealer"
    ],
    "wof:name":"Brennan Pontiac Buick Gmc Ltd",
    "wof:placetype":"venue"
},
  "geometry": {"coordinates":[-79.377876,43.714378],"type":"Point"}
}