{
  "type": "Feature",
  "properties": {
    "addr:full":"1190 Wallace Ave N Listowel ON N4W 1M5",
    "addr:housenumber":"1190",
    "addr:postcode":"n4w 1m5",
    "addr:street":"Wallace Ave N",
    "iso:country":"CA",
    "sg:address":"1190 Wallace Ave N",
    "sg:city":"Listowel",
    "sg:classifiers":[
        {
            "category":"Building & Trades",
            "subcategory":"Landscaping Services",
            "type":"Services"
        }
    ],
    "sg:phone":"+1 519 291 3267",
    "sg:postcode":"N4W 1M5",
    "sg:province":"ON",
    "sg:tags":[
        "landscape",
        "contractor"
    ],
    "wof:name":"Fletcher's Landscaping Inc",
    "wof:placetype":"venue"
},
  "geometry": {"coordinates":[-80.945168,43.741394],"type":"Point"}
}