{
  "type": "Feature",
  "properties": {
    "iso:country":"CA",
    "sg:address":"7419 82 Ave NW",
    "sg:city":"Edmonton",
    "sg:classifiers":[
        {
            "category":"Restaurant",
            "type":"Food & Drink"
        }
    ],
    "sg:phone":"+1 780 414 8460",
    "sg:postcode":"T6B 0G3",
    "sg:province":"AB",
    "wof:name":"Mc Donald's",
    "wof:placetype":"venue"
},
  "geometry": {"coordinates":[-113.440795898,53.5178375244],"type":"Point"}
}