{
  "type": "Feature",
  "properties": {
    "iso:country":"CA",
    "sg:city":"Hinton",
    "sg:classifiers":[
        {
            "category":"Real Estate",
            "subcategory":"Real Estate Operator",
            "type":"Services"
        }
    ],
    "sg:phone":"+1 780 865 3200",
    "sg:postcode":"T7V 1W2",
    "sg:province":"AB",
    "sg:tags":[
        "apartment"
    ],
    "wof:name":"Balsam Court Apts",
    "wof:placetype":"venue"
},
  "geometry": {"coordinates":[-117.545532227,53.4183731079],"type":"Point"}
}