{
  "type": "Feature",
  "properties": {
    "addr:full":"4926 50th St Sedgewick AB T0B 4C0",
    "addr:housenumber":"4926",
    "addr:postcode":"t0b 4c0",
    "addr:street":"50Th St",
    "iso:country":"CA",
    "sg:address":"4926 50th St",
    "sg:city":"Sedgewick",
    "sg:classifiers":[
        {
            "category":"Organizations",
            "subcategory":"Religious Organization",
            "type":"Services"
        }
    ],
    "sg:phone":"+1 780 384 3805",
    "sg:postcode":"T0B 4C0",
    "sg:province":"AB",
    "sg:tags":[
        "church"
    ],
    "wof:name":"Anglican Church St Edmund's",
    "wof:placetype":"venue"
},
  "geometry": {"coordinates":[-111.696830749,52.775844574],"type":"Point"}
}