{
  "type": "Feature",
  "properties": {
    "addr:full":"510 Fort St Victoria BC V8W 1E6",
    "addr:housenumber":"510",
    "addr:postcode":"v8w 1e6",
    "addr:street":"Fort St",
    "iso:country":"CA",
    "sg:address":"510 Fort St",
    "sg:city":"Victoria",
    "sg:classifiers":[
        {
            "category":"Restaurant",
            "type":"Food & Drink"
        }
    ],
    "sg:phone":"+1 250 382 1514",
    "sg:postcode":"V8W 1E6",
    "sg:province":"BC",
    "wof:name":"Koto Japanese Restaurants Ltd",
    "wof:placetype":"venue"
},
  "geometry": {"coordinates":[-123.369598389,48.4250793457],"type":"Point"}
}