{
  "type": "Feature",
  "properties": {
    "addr:full":"6390 Northwest Dr Mississauga ON L4V 1S1",
    "addr:housenumber":"6390",
    "addr:postcode":"l4v 1s1",
    "addr:street":"Northwest Dr",
    "iso:country":"CA",
    "sg:address":"6390 Northwest Dr",
    "sg:city":"Mississauga",
    "sg:classifiers":[
        {
            "category":"Freight",
            "type":"Transportation"
        }
    ],
    "sg:phone":"+1 905 678 2220",
    "sg:postcode":"L4V 1S1",
    "sg:province":"ON",
    "wof:name":"Good Hope Intl Inc",
    "wof:placetype":"venue"
},
  "geometry": {"coordinates":[-79.6183166504,43.7010536194],"type":"Point"}
}