{
  "type": "Feature",
  "properties": {
    "addr:full":"Richmond Hill ON L4B 3A9",
    "addr:postcode":"l4b 3a9",
    "iso:country":"CA",
    "sg:city":"Richmond Hill",
    "sg:classifiers":[
        {
            "category":"Professional",
            "subcategory":"Research",
            "type":"Services"
        }
    ],
    "sg:phone":"+1 905 709 0055",
    "sg:postcode":"L4B 3A9",
    "sg:province":"ON",
    "sg:tags":[
        "market",
        "analysis"
    ],
    "wof:name":"Rqa Inc",
    "wof:placetype":"venue"
},
  "geometry": {"coordinates":[-79.38492599999999,43.848057],"type":"Point"}
}