{
  "type": "Feature",
  "properties": {
    "addr:full":"260 Elk Valley Industrial Rd 1 Sparwood BC V0B 2G0",
    "addr:housenumber":"260",
    "addr:postcode":"bc v0b 2g0",
    "addr:street":"Elk Valley Industrial Rd 1",
    "iso:country":"CA",
    "sg:address":"260 Elk Valley Industrial Rd 1",
    "sg:city":"Sparwood",
    "sg:classifiers":[
        {
            "category":"Wholesale",
            "subcategory":"Auto Parts",
            "type":"Manufacturing & Wholesale Goods"
        }
    ],
    "sg:phone":"+1 250 425 2538",
    "sg:postcode":"V0B 2G0",
    "sg:province":"BC",
    "sg:tags":[
        "brakes"
    ],
    "wof:name":"Morgan Brake & Clutch CO",
    "wof:placetype":"venue"
},
  "geometry": {"coordinates":[-114.888908,49.724892],"type":"Point"}
}