{
  "type": "Feature",
  "properties": {
    "addr:full":"194 Av Joseph Saint-Joseph-Du-Lac QC J0N 1M0",
    "addr:postcode":"j0n 1m0",
    "addr:street":"194 Av Joseph",
    "iso:country":"CA",
    "sg:address":"194 Av Joseph",
    "sg:city":"Saint-Joseph-Du-Lac",
    "sg:classifiers":[
        {
            "category":"Manufacturing",
            "subcategory":"Chemicals & Compounds",
            "type":"Manufacturing & Wholesale Goods"
        }
    ],
    "sg:phone":"+1 450 473 6171",
    "sg:postcode":"J0N 1M0",
    "sg:province":"QC",
    "sg:tags":[
        "firework"
    ],
    "wof:name":"Dragon-Pyrotechniques",
    "wof:placetype":"venue"
},
  "geometry": {"coordinates":[-73.96678199999999,45.51527],"type":"Point"}
}