{
  "type": "Feature",
  "properties": {
    "addr:full":"4646 Rue Sherbrooke O Westmount QC H3Z 2Z8",
    "addr:housenumber":"4646",
    "addr:postcode":"h3z 2z8",
    "addr:street":"Rue Sherbrooke O",
    "iso:country":"CA",
    "sg:address":"4646 Rue Sherbrooke O",
    "sg:city":"Westmount",
    "sg:classifiers":[
        {
            "category":"Health Services",
            "subcategory":"Nursing And Care Facility",
            "type":"Services"
        }
    ],
    "sg:phone":"+1 514 937 3943",
    "sg:postcode":"H3Z 2Z8",
    "sg:province":"QC",
    "sg:tags":[
        "home",
        "retirement",
        "community"
    ],
    "wof:name":"Manoir Westmount",
    "wof:placetype":"venue"
},
  "geometry": {"coordinates":[-73.60090599999999,45.481003],"type":"Point"}
}