{
  "type": "Feature",
  "properties": {
    "iso:country":"CA",
    "sg:address":"2480 Rue Roy",
    "sg:city":"Sherbrooke",
    "sg:classifiers":[
        {
            "category":"Shopping",
            "subcategory":"Used Merchandise",
            "type":"Retail Goods"
        }
    ],
    "sg:phone":"+1 819 823 9495",
    "sg:postcode":"J1K 1C1",
    "sg:province":"QC",
    "sg:tags":[
        "fixture",
        "store"
    ],
    "wof:name":"Les Equipements DE Bureau Bob",
    "wof:placetype":"venue"
},
  "geometry": {"coordinates":[-71.934685,45.390343],"type":"Point"}
}