{
  "type": "Feature",
  "properties": {
    "addr:full":"1156 Fort St Victoria BC V8V 3K8",
    "addr:housenumber":"1156",
    "addr:postcode":"v8v 3k8",
    "addr:street":"Fort St",
    "iso:country":"CA",
    "sg:address":"1156 Fort St",
    "sg:city":"Victoria",
    "sg:classifiers":[
        {
            "category":"Shopping",
            "subcategory":"Used Merchandise",
            "type":"Retail Goods"
        }
    ],
    "sg:phone":"+1 250 383 0121",
    "sg:postcode":"V8V 3K8",
    "sg:province":"BC",
    "sg:tags":[
        "antique"
    ],
    "wof:name":"Faith Grant the Connoisseur",
    "wof:placetype":"venue"
},
  "geometry": {"coordinates":[-123.351570129,48.4232444763],"type":"Point"}
}