{
  "type": "Feature",
  "properties": {
    "addr:full":"Hwy 361 W Lampman SK S0C 1N0",
    "addr:postcode":"s0c 1n0",
    "addr:street":"Hwy 361 W Lampman",
    "iso:country":"CA",
    "sg:address":"Hwy 361 W",
    "sg:city":"Lampman",
    "sg:classifiers":[
        {
            "category":"Wholesale",
            "subcategory":"Machinery & Supplies",
            "type":"Manufacturing & Wholesale Goods"
        }
    ],
    "sg:phone":"+1 306 487 2525",
    "sg:postcode":"S0C 1N0",
    "sg:province":"SK",
    "sg:tags":[
        "equipment",
        "oil",
        "well"
    ],
    "wof:name":"Grimes Sales & Svc CO Ltd",
    "wof:placetype":"venue"
},
  "geometry": {"coordinates":[-102.752685547,49.3772697449],"type":"Point"}
}