{
  "type": "Feature",
  "properties": {
    "addr:full":"75 Rue Rheaume Verdun QC H4G 3C1",
    "addr:housenumber":"75",
    "addr:postcode":"h4g 3c1",
    "addr:street":"Rue Rheaume",
    "iso:country":"CA",
    "sg:address":"75 Rue Rheaume",
    "sg:city":"Verdun",
    "sg:classifiers":[
        {
            "category":"Education",
            "subcategory":"School",
            "type":"Public Place"
        }
    ],
    "sg:phone":"+1 514 765 7666",
    "sg:postcode":"H4G 3C1",
    "sg:province":"QC",
    "wof:name":"Ecole Secondaire Mgr Richard",
    "wof:placetype":"venue"
},
  "geometry": {"coordinates":[-73.564133,45.4678],"type":"Point"}
}