{
  "type": "Feature",
  "properties": {
    "addr:full":"150 Rue St-Catherine O Montreal QC H5B 1B3",
    "addr:housenumber":"150",
    "addr:postcode":"h5b 1b3",
    "addr:street":"Rue St-Catherine O",
    "iso:country":"CA",
    "sg:address":"150 Rue St-Catherine O",
    "sg:city":"Montreal",
    "sg:classifiers":[
        {
            "category":"Shopping",
            "subcategory":"Shoes",
            "type":"Retail Goods"
        }
    ],
    "sg:phone":"+1 514 285 6355",
    "sg:postcode":"H5B 1B3",
    "sg:province":"QC",
    "wof:name":"Sabotier Enrg",
    "wof:placetype":"venue"
},
  "geometry": {"coordinates":[-73.56255299999999,45.511166],"type":"Point"}
}