{
  "type": "Feature",
  "properties": {
    "addr:full":"London ON N6L 1G3",
    "addr:postcode":"n6l 1g3",
    "iso:country":"CA",
    "sg:city":"London",
    "sg:classifiers":[
        {
            "category":"Wholesale",
            "subcategory":"Electrical",
            "type":"Manufacturing & Wholesale Goods"
        }
    ],
    "sg:phone":"+1 519 652 3550",
    "sg:postcode":"N6L 1G3",
    "sg:province":"ON",
    "sg:tags":[
        "lighting",
        "fixture"
    ],
    "wof:name":"Litemor Distributors Ltd",
    "wof:placetype":"venue"
},
  "geometry": {"coordinates":[-81.25160200000001,42.92276],"type":"Point"}
}