{
  "type": "Feature",
  "properties": {
    "addr:full":"1101 Rue Clark Montreal QC H2Z 1K3",
    "addr:housenumber":"1101",
    "addr:postcode":"h2z 1k3",
    "addr:street":"Rue Clark",
    "iso:country":"CA",
    "sg:address":"1101 Rue Clark",
    "sg:city":"Montreal",
    "sg:classifiers":[
        {
            "category":"Organizations",
            "subcategory":"Professional Association",
            "type":"Services"
        }
    ],
    "sg:phone":"+1 514 861 5382",
    "sg:postcode":"H2Z 1K3",
    "sg:province":"QC",
    "wof:name":"Chinese Nationalist League",
    "wof:placetype":"venue"
},
  "geometry": {"coordinates":[-73.560867,45.508175],"type":"Point"}
}