{
  "type": "Feature",
  "properties": {
    "iso:country":"CA",
    "sg:address":"1101 Rue Clark",
    "sg:city":"Montreal",
    "sg:classifiers":[
        {
            "category":"Organizations",
            "subcategory":"Professional Association",
            "type":"Services"
        }
    ],
    "sg:phone":"+1 514 861 5382",
    "sg:postcode":"H2Z 1K3",
    "sg:province":"QC",
    "wof:name":"Chinese Nationalist League",
    "wof:placetype":"venue"
},
  "geometry": {"coordinates":[-73.560867,45.508175],"type":"Point"}
}