{
  "type": "Feature",
  "properties": {
    "addr:full":"32 Largo Cres #A Nepean ON K2G 3C7",
    "addr:housenumber":"32",
    "addr:postcode":"k2g 3c7",
    "addr:street":"Largo Cres # A",
    "iso:country":"CA",
    "sg:address":"32 Largo Cres #A",
    "sg:city":"Nepean",
    "sg:classifiers":[
        {
            "category":"Social Services",
            "type":"Services"
        }
    ],
    "sg:phone":"+1 613 226 9505",
    "sg:postcode":"K2G 3C7",
    "sg:province":"ON",
    "sg:tags":[
        "organization",
        "welfare"
    ],
    "wof:name":"Teen Challenge",
    "wof:placetype":"venue"
},
  "geometry": {"coordinates":[-75.73632000000001,45.342079],"type":"Point"}
}