{
  "type": "Feature",
  "properties": {
    "addr:full":"120 1st St Hague SK S0K 1X0",
    "addr:housenumber":"120",
    "addr:postcode":"s0k 1x0",
    "addr:street":"1St St",
    "iso:country":"CA",
    "sg:address":"120 1st St",
    "sg:city":"Hague",
    "sg:classifiers":[
        {
            "category":"Organizations",
            "subcategory":"Religious Organization",
            "type":"Services"
        }
    ],
    "sg:phone":"+1 306 225 4554",
    "sg:postcode":"S0K 1X0",
    "sg:province":"SK",
    "sg:tags":[
        "church"
    ],
    "wof:name":"Zion Ev Lutheran Church",
    "wof:placetype":"venue"
},
  "geometry": {"coordinates":[-106.417519,52.513191],"type":"Point"}
}