{
  "type": "Feature",
  "properties": {
    "addr:full":"190 Main St Ottawa ON K1S 1C2",
    "addr:housenumber":"190",
    "addr:postcode":"k1s 1c2",
    "addr:street":"Main St",
    "iso:country":"CA",
    "sg:address":"190 Main St",
    "sg:city":"Ottawa",
    "sg:classifiers":[
        {
            "category":"Health Services",
            "subcategory":"Doctor",
            "type":"Services"
        }
    ],
    "sg:phone":"+1 613 521 5991",
    "sg:postcode":"K1S 1C2",
    "sg:province":"ON",
    "sg:tags":[
        "physician",
        "surgeon"
    ],
    "wof:name":"Dawson, John MD",
    "wof:placetype":"venue"
},
  "geometry": {"coordinates":[-75.678078,45.408688],"type":"Point"}
}