{
  "type": "Feature",
  "properties": {
    "addr:full":"1133 Rue Notre-Dame Saint-Felicien QC G8K 1Z7",
    "addr:housenumber":"1133",
    "addr:postcode":"g8k 1z7",
    "addr:street":"Rue Notre-Dame Saint-Felicien",
    "iso:country":"CA",
    "sg:address":"1133 Rue Notre-Dame",
    "sg:city":"Saint-Felicien",
    "sg:classifiers":[
        {
            "category":"Professional",
            "subcategory":"Accounting & Tax Preparation",
            "type":"Services"
        }
    ],
    "sg:phone":"+1 418 679 4711",
    "sg:postcode":"G8K 1Z7",
    "sg:province":"QC",
    "sg:tags":[
        "accountant"
    ],
    "wof:name":"Samson Belair-Deloitte Touche",
    "wof:placetype":"venue"
},
  "geometry": {"coordinates":[-72.44403839109999,48.6497879028],"type":"Point"}
}