{
  "type": "Feature",
  "properties": {
    "addr:full":"6490 Van Deemter Crt Mississauga ON L5T 1S1",
    "addr:housenumber":"6490",
    "addr:postcode":"l5t 1s1",
    "addr:street":"Van Deemter Crt",
    "iso:country":"CA",
    "sg:address":"6490 Van Deemter Crt",
    "sg:city":"Mississauga",
    "sg:classifiers":[
        {
            "category":"Manufacturing",
            "subcategory":"Tools & Machinery",
            "type":"Manufacturing & Wholesale Goods"
        }
    ],
    "sg:phone":"+1 905 696 8000",
    "sg:postcode":"L5T 1S1",
    "sg:province":"ON",
    "sg:tags":[
        "machine",
        "shop"
    ],
    "wof:name":"Trio Tech Inc",
    "wof:placetype":"venue"
},
  "geometry": {"coordinates":[-79.655518,43.666634],"type":"Point"}
}