{
  "type": "Feature",
  "properties": {
    "addr:full":"100 Dundas St E Paris ON N3L 3H6",
    "addr:housenumber":"100",
    "addr:postcode":"n3l 3h6",
    "addr:street":"Dundas St E",
    "iso:country":"CA",
    "sg:address":"100 Dundas St E",
    "sg:city":"Paris",
    "sg:classifiers":[
        {
            "category":"Manufacturing",
            "subcategory":"Toys & Sporting Goods",
            "type":"Manufacturing & Wholesale Goods"
        }
    ],
    "sg:phone":"+1 519 442 4423",
    "sg:postcode":"N3L 3H6",
    "sg:province":"ON",
    "sg:tags":[
        "athletic"
    ],
    "wof:name":"Darby Sportswear CO Ltd",
    "wof:placetype":"venue"
},
  "geometry": {"coordinates":[-80.368103,43.19046],"type":"Point"}
}