{
  "type": "Feature",
  "properties": {
    "addr:full":"New Liskeard ON P0J 1P0",
    "addr:postcode":"p0j 1p0",
    "iso:country":"CA",
    "sg:city":"New Liskeard",
    "sg:classifiers":[
        {
            "category":"Health Services",
            "subcategory":"Doctor",
            "type":"Services"
        }
    ],
    "sg:phone":"+1 705 647 3000",
    "sg:postcode":"P0J 1P0",
    "sg:province":"ON",
    "sg:tags":[
        "physician",
        "surgeon"
    ],
    "wof:name":"Percy, G MD",
    "wof:placetype":"venue"
},
  "geometry": {"coordinates":[-79.68026733400001,47.5087280273],"type":"Point"}
}