{
  "type": "Feature",
  "properties": {
    "addr:full":"Saskatoon SK S7K 7Z1",
    "addr:postcode":"s7k 7z1",
    "iso:country":"CA",
    "sg:city":"Saskatoon",
    "sg:classifiers":[
        {
            "category":"Professional",
            "subcategory":"Management & Consulting",
            "type":"Services"
        }
    ],
    "sg:phone":"+1 306 242 6077",
    "sg:postcode":"S7K 7Z1",
    "sg:province":"SK",
    "sg:tags":[
        "break",
        "coffee",
        "supply"
    ],
    "wof:name":"Mc Quarrie's Maher Coffee Svc",
    "wof:placetype":"venue"
},
  "geometry": {"coordinates":[-106.657898,52.182705],"type":"Point"}
}