{
  "type": "Feature",
  "properties": {
    "addr:full":"781 Prince St Truro NS B2N 1G7",
    "addr:housenumber":"781",
    "addr:postcode":"b2n 1g7",
    "addr:street":"Prince St",
    "iso:country":"CA",
    "sg:address":"781 Prince St",
    "sg:city":"Truro",
    "sg:classifiers":[
        {
            "category":"Shopping",
            "subcategory":"Hobbies, Toys, & Games",
            "type":"Retail Goods"
        }
    ],
    "sg:phone":"+1 902 893 0159",
    "sg:postcode":"B2N 1G7",
    "sg:province":"NS",
    "sg:tags":[
        "craft",
        "supply"
    ],
    "wof:name":"Alderberry Village Craft Coop",
    "wof:placetype":"venue"
},
  "geometry": {"coordinates":[-63.277496,45.364819],"type":"Point"}
}