{
  "type": "Feature",
  "properties": {
    "addr:full":"938 Av Duluth E Montreal QC H2L 1B6",
    "addr:postcode":"h2l 1b6",
    "addr:street":"938 Av Duluth E",
    "iso:country":"CA",
    "sg:address":"938 Av Duluth E",
    "sg:city":"Montreal",
    "sg:classifiers":[
        {
            "category":"Building & Trades",
            "subcategory":"Plumbing",
            "type":"Services"
        }
    ],
    "sg:phone":"+1 514 523 5040",
    "sg:postcode":"H2L 1B6",
    "sg:province":"QC",
    "sg:tags":[
        "contractor"
    ],
    "wof:name":"Metayer Lacombe Plomberie Inc",
    "wof:placetype":"venue"
},
  "geometry": {"coordinates":[-73.5730133057,45.5236053467],"type":"Point"}
}