{
  "type": "Feature",
  "properties": {
    "iso:country":"CA",
    "sg:city":"Surrey",
    "sg:classifiers":[
        {
            "category":"Manufacturing",
            "subcategory":"Tools & Machinery",
            "type":"Manufacturing & Wholesale Goods"
        }
    ],
    "sg:phone":"+1 604 599 1311",
    "sg:postcode":"V3W 9E9",
    "sg:province":"BC",
    "sg:tags":[
        "equipment",
        "safety",
        "clothing"
    ],
    "wof:name":"Custom Protect-Ear Inc",
    "wof:placetype":"venue"
},
  "geometry": {"coordinates":[-122.85131072999999,49.1441993713],"type":"Point"}
}