{
  "type": "Feature",
  "properties": {
    "addr:full":"10319 97 St NW Edmonton AB T5J 0M1",
    "addr:housenumber":"10319",
    "addr:postcode":"t5j 0m1",
    "addr:street":"97 St Nw",
    "iso:country":"CA",
    "sg:address":"10319 97 St NW",
    "sg:city":"Edmonton",
    "sg:classifiers":[
        {
            "category":"Shopping",
            "subcategory":"Used Merchandise",
            "type":"Retail Goods"
        }
    ],
    "sg:phone":"+1 780 422 2088",
    "sg:postcode":"T5J 0M1",
    "sg:province":"AB",
    "sg:tags":[
        "second",
        "hand",
        "store",
        "jeweler"
    ],
    "wof:name":"Uncle Ed's Exchange Ltd",
    "wof:placetype":"venue"
},
  "geometry": {"coordinates":[-113.48683929400001,53.5461807251],"type":"Point"}
}