{
  "type": "Feature",
  "properties": {
    "addr:full":"3605 15th Ave Prince George BC V2N 1A3",
    "addr:housenumber":"3605",
    "addr:postcode":"v2n 1a3",
    "addr:street":"15Th Ave",
    "iso:country":"CA",
    "sg:address":"3605 15th Ave",
    "sg:city":"Prince George",
    "sg:classifiers":[
        {
            "category":"Autos & Motor Vehicles",
            "subcategory":"Auto Supplies",
            "type":"Retail Goods"
        }
    ],
    "sg:phone":"+1 250 564 3224",
    "sg:postcode":"V2N 1A3",
    "sg:province":"BC",
    "sg:tags":[
        "automobile",
        "parts"
    ],
    "wof:name":"Auto Magic Parts Store",
    "wof:placetype":"venue"
},
  "geometry": {"coordinates":[-122.787155,53.910049],"type":"Point"}
}