{
  "type": "Feature",
  "properties": {
    "iso:country":"CA",
    "sg:city":"Teeswater",
    "sg:classifiers":[
        {
            "category":"Building & Trades",
            "subcategory":"Electrical",
            "type":"Services"
        }
    ],
    "sg:phone":"+1 519 392 6893",
    "sg:postcode":"N0G 2S0",
    "sg:province":"ON",
    "sg:tags":[
        "electric",
        "contractor"
    ],
    "wof:name":"Fred Lorch Electric",
    "wof:placetype":"venue"
},
  "geometry": {"coordinates":[-81.28717041020001,43.9999351501],"type":"Point"}
}