{
  "type": "Feature",
  "properties": {
    "addr:full":"Bon-Conseil QC J0C 1A0",
    "addr:postcode":"j0c 1a0",
    "addr:street":"Bon-Conseil",
    "iso:country":"CA",
    "sg:city":"Bon-Conseil",
    "sg:classifiers":[
        {
            "category":"Retail",
            "subcategory":"Auto Repair",
            "type":"Services"
        }
    ],
    "sg:phone":"+1 819 336 5727",
    "sg:postcode":"J0C 1A0",
    "sg:province":"QC",
    "sg:tags":[
        "repairing",
        "automobile"
    ],
    "wof:name":"Garage Landry Enr",
    "wof:placetype":"venue"
},
  "geometry": {"coordinates":[-72.3430023193,46.001121521],"type":"Point"}
}