{
  "type": "Feature",
  "properties": {
    "addr:full":"410 King St N Waterloo ON N2J 2Z3",
    "addr:housenumber":"410",
    "addr:postcode":"n2j 2z3",
    "addr:street":"King St N",
    "iso:country":"CA",
    "sg:address":"410 King St N",
    "sg:city":"Waterloo",
    "sg:classifiers":[
        {
            "category":"Restaurant",
            "type":"Food & Drink"
        }
    ],
    "sg:phone":"+1 519 725 9194",
    "sg:postcode":"N2J 2Z3",
    "sg:province":"ON",
    "wof:name":"Harvey's",
    "wof:placetype":"venue"
},
  "geometry": {"coordinates":[-80.526505,43.484451],"type":"Point"}
}