{
  "type": "Feature",
  "properties": {
    "addr:full":"RR 1 STN Main Okotoks AB T1S 1A1",
    "addr:postcode":"t1s 1a1",
    "addr:street":"Rr 1 Stn Main Okotoks Ab",
    "iso:country":"CA",
    "sg:address":"RR 1 STN Main",
    "sg:city":"Okotoks",
    "sg:classifiers":[
        {
            "category":"Building & Trades",
            "subcategory":"Plumbing",
            "type":"Services"
        }
    ],
    "sg:phone":"+1 403 938 0466",
    "sg:postcode":"T1S 1A1",
    "sg:province":"AB",
    "sg:tags":[
        "contractor"
    ],
    "wof:name":"Ray Minue Plumbing",
    "wof:placetype":"venue"
},
  "geometry": {"coordinates":[-113.974937439,50.7258911133],"type":"Point"}
}