{
  "type": "Feature",
  "properties": {
    "addr:full":"4203 50 St Innisfail AB T4G 1V6",
    "addr:housenumber":"4203",
    "addr:postcode":"t4g 1v6",
    "addr:street":"50 St",
    "iso:country":"CA",
    "sg:address":"4203 50 St",
    "sg:city":"Innisfail",
    "sg:classifiers":[
        {
            "category":"Restaurant",
            "type":"Food & Drink"
        }
    ],
    "sg:phone":"+1 403 227 2800",
    "sg:postcode":"T4G 1V6",
    "sg:province":"AB",
    "wof:name":"Mc Donald's",
    "wof:placetype":"venue"
},
  "geometry": {"coordinates":[-113.93470001199999,52.0274200439],"type":"Point"}
}