{
  "type": "Feature",
  "properties": {
    "iso:country":"CA",
    "sg:city":"Sherrington",
    "sg:classifiers":[
        {
            "category":"Government",
            "subcategory":"Office",
            "type":"Public Place"
        }
    ],
    "sg:phone":"+1 450 454 4959",
    "sg:postcode":"J0L 2N0",
    "sg:province":"QC",
    "sg:tags":[
        "village"
    ],
    "wof:name":"Sherrington Hotel DE Ville",
    "wof:placetype":"venue"
},
  "geometry": {"coordinates":[-73.5228271484,45.1728286743],"type":"Point"}
}