{
  "type": "Feature",
  "properties": {
    "addr:full":"1903 Mount Newton Cross Rd Saanichton BC V8M 2A9",
    "addr:housenumber":"1903",
    "addr:postcode":"v8m 2a9",
    "addr:street":"Mount Newton Cross Rd",
    "iso:country":"CA",
    "sg:address":"1903 Mount Newton Cross Rd",
    "sg:city":"Saanichton",
    "sg:classifiers":[
        {
            "category":"Government",
            "subcategory":"Police Station",
            "type":"Public Place"
        }
    ],
    "sg:phone":"+1 250 652 4441",
    "sg:postcode":"V8M 2A9",
    "sg:province":"BC",
    "sg:tags":[
        "department"
    ],
    "wof:name":"Saanich Police",
    "wof:placetype":"venue"
},
  "geometry": {"coordinates":[-123.420890808,48.5951728821],"type":"Point"}
}