{
  "type": "Feature",
  "properties": {
    "addr:full":"3334 Danforth Ave Scarborough ON M1L 1C6",
    "addr:housenumber":"3334",
    "addr:postcode":"m1l 1c6",
    "addr:street":"Danforth Ave",
    "iso:country":"CA",
    "sg:address":"3334 Danforth Ave",
    "sg:city":"Scarborough",
    "sg:classifiers":[
        {
            "category":"Organizations",
            "subcategory":"Religious Organization",
            "type":"Services"
        }
    ],
    "sg:phone":"+1 416 686 3037",
    "sg:postcode":"M1L 1C6",
    "sg:province":"ON",
    "wof:name":"Baitul Mukarram Islamic Societ",
    "wof:placetype":"venue"
},
  "geometry": {"coordinates":[-79.27808400000001,43.693569],"type":"Point"}
}