{
  "type": "Feature",
  "properties": {
    "iso:country":"CA",
    "sg:address":"102 Laclie St",
    "sg:city":"Orillia",
    "sg:classifiers":[
        {
            "category":"Real Estate",
            "subcategory":"Architect",
            "type":"Services"
        }
    ],
    "sg:phone":"+1 705 325 0761",
    "sg:postcode":"L3V 4M8",
    "sg:province":"ON",
    "wof:name":"Young, Roderick H",
    "wof:placetype":"venue"
},
  "geometry": {"coordinates":[-79.4162063599,44.6139640808],"type":"Point"}
}