{
  "type": "Feature",
  "properties": {
    "iso:country":"CA",
    "sg:address":"105 Sand Rd",
    "sg:city":"Holland Landing",
    "sg:classifiers":[
        {
            "category":"Health Services",
            "subcategory":"Nursing And Care Facility",
            "type":"Services"
        }
    ],
    "sg:phone":"+1 905 836 4215",
    "sg:postcode":"L9N 1H9",
    "sg:province":"ON",
    "sg:tags":[
        "home",
        "rest"
    ],
    "wof:name":"Gordon's Residential Homes",
    "wof:placetype":"venue"
},
  "geometry": {"coordinates":[-79.5046844482,44.1150970459],"type":"Point"}
}