{
  "type": "Feature",
  "properties": {
    "addr:full":"Delta BC V3M 6L2",
    "addr:postcode":"v3m 6l2",
    "iso:country":"CA",
    "sg:city":"Delta",
    "sg:classifiers":[
        {
            "category":"Manufacturing",
            "subcategory":"Tools & Machinery",
            "type":"Manufacturing & Wholesale Goods"
        }
    ],
    "sg:phone":"+1 604 521 2188",
    "sg:postcode":"V3M 6L2",
    "sg:province":"BC",
    "sg:tags":[
        "pattern",
        "maker"
    ],
    "wof:name":"Patterns & Prototypes",
    "wof:placetype":"venue"
},
  "geometry": {"coordinates":[-122.96586600000001,49.165489],"type":"Point"}
}