{
  "type": "Feature",
  "properties": {
    "addr:full":"650 Boul Saint-Joseph O Drummondville QC J2E 1H5",
    "addr:housenumber":"650",
    "addr:postcode":"j2e 1h5",
    "addr:street":"Boul Saint-Joseph O",
    "iso:country":"CA",
    "sg:address":"650 Boul Saint-Joseph O",
    "sg:city":"Drummondville",
    "sg:classifiers":[
        {
            "category":"Bars & Pubs",
            "type":"Food & Drink"
        }
    ],
    "sg:phone":"+1 819 477 9475",
    "sg:postcode":"J2E 1H5",
    "sg:province":"QC",
    "sg:tags":[
        "lounge",
        "cocktail"
    ],
    "wof:name":"Bar Chez Zim-Bar",
    "wof:placetype":"venue"
},
  "geometry": {"coordinates":[-72.51313781739999,45.8926429749],"type":"Point"}
}