{
  "type": "Feature",
  "properties": {
    "addr:full":"8700 8E Av Montreal QC H1Z 2W9",
    "addr:housenumber":"8700",
    "addr:postcode":"h1z 2w9",
    "addr:street":"8E Av",
    "iso:country":"CA",
    "sg:address":"8700 8E Av",
    "sg:city":"Montreal",
    "sg:classifiers":[
        {
            "category":"Manufacturing",
            "subcategory":"Furniture",
            "type":"Manufacturing & Wholesale Goods"
        }
    ],
    "sg:phone":"+1 514 376 7575",
    "sg:postcode":"H1Z 2W9",
    "sg:province":"QC",
    "sg:tags":[
        "chair"
    ],
    "wof:name":"Meubles Paramount Mfg",
    "wof:placetype":"venue"
},
  "geometry": {"coordinates":[-73.6228942871,45.5668907166],"type":"Point"}
}