{
  "type": "Feature",
  "properties": {
    "addr:full":"Sept-Iles QC G4R 3B3",
    "addr:postcode":"g4r 3b3",
    "iso:country":"CA",
    "sg:city":"Sept-Iles",
    "sg:classifiers":[
        {
            "category":"Professional",
            "subcategory":"Accounting & Tax Preparation",
            "type":"Services"
        }
    ],
    "sg:phone":"+1 418 962 2513",
    "sg:postcode":"G4R 3B3",
    "sg:province":"QC",
    "sg:tags":[
        "accountant"
    ],
    "wof:name":"Samson Belair Deloitte",
    "wof:placetype":"venue"
},
  "geometry": {"coordinates":[-66.386612,50.204376],"type":"Point"}
}