{
  "type": "Feature",
  "properties": {
    "addr:full":"1341 Town Line Tottenham ON L0G 1W0",
    "addr:housenumber":"1341",
    "addr:postcode":"l0g 1w0",
    "addr:street":"Town Line",
    "iso:country":"CA",
    "sg:address":"1341 Town Line",
    "sg:city":"Tottenham",
    "sg:classifiers":[
        {
            "category":"Personal",
            "type":"Services"
        }
    ],
    "sg:phone":"+1 905 936 2910",
    "sg:postcode":"L0G 1W0",
    "sg:province":"ON",
    "sg:tags":[
        "control",
        "weight"
    ],
    "wof:name":"Gail's Fitness Studio",
    "wof:placetype":"venue"
},
  "geometry": {"coordinates":[-79.80578613279999,44.0228767395],"type":"Point"}
}