{
  "type": "Feature",
  "properties": {
    "addr:full":"8305 122A St Surrey BC V3W 9P8",
    "addr:housenumber":"8305",
    "addr:postcode":"v3w 9p8",
    "addr:street":"122A St",
    "iso:country":"CA",
    "sg:address":"8305 122A St",
    "sg:city":"Surrey",
    "sg:classifiers":[
        {
            "category":"Education",
            "subcategory":"School",
            "type":"Public Place"
        }
    ],
    "sg:phone":"+1 604 590 1198",
    "sg:postcode":"V3W 9P8",
    "sg:province":"BC",
    "wof:name":"Kennedy Trail Elementary",
    "wof:placetype":"venue"
},
  "geometry": {"coordinates":[-122.830215,49.105179],"type":"Point"}
}