{
  "type": "Feature",
  "properties": {
    "addr:full":"612 Dalhousie Dr Winnipeg MB R3T 3Z5",
    "addr:housenumber":"612",
    "addr:postcode":"r3t 3z5",
    "addr:street":"Dalhousie Dr",
    "iso:country":"CA",
    "sg:address":"612 Dalhousie Dr",
    "sg:city":"Winnipeg",
    "sg:classifiers":[
        {
            "category":"Real Estate",
            "subcategory":"Real Estate Agent",
            "type":"Services"
        }
    ],
    "sg:phone":"+1 204 275 1419",
    "sg:postcode":"R3T 3Z5",
    "sg:province":"MB",
    "wof:name":"R & J Realty",
    "wof:placetype":"venue"
},
  "geometry": {"coordinates":[-97.150047,49.784412],"type":"Point"}
}