{
  "type": "Feature",
  "properties": {
    "addr:full":"Langley BC V2Y 1A2",
    "addr:postcode":"v2y 1a2",
    "iso:country":"CA",
    "sg:city":"Langley",
    "sg:classifiers":[
        {
            "category":"Shopping",
            "type":"Retail Goods"
        }
    ],
    "sg:phone":"+1 604 530 1640",
    "sg:postcode":"V2Y 1A2",
    "sg:province":"BC",
    "sg:tags":[
        "hearing",
        "equipment",
        "supply",
        "impaired"
    ],
    "wof:name":"Advanced Hearing Solutions Inc",
    "wof:placetype":"venue"
},
  "geometry": {"coordinates":[-122.66874694800001,49.1179466248],"type":"Point"}
}