{
  "type": "Feature",
  "properties": {
    "addr:full":"Norwich ON N0J 1P0",
    "addr:postcode":"n0j 1p0",
    "iso:country":"CA",
    "sg:city":"Norwich",
    "sg:classifiers":[
        {
            "category":"Building & Trades",
            "subcategory":"Electrical",
            "type":"Services"
        }
    ],
    "sg:phone":"+1 519 863 2206",
    "sg:postcode":"N0J 1P0",
    "sg:province":"ON",
    "sg:tags":[
        "electric",
        "contractor"
    ],
    "wof:name":"M A Hughes Electric Ltd",
    "wof:placetype":"venue"
},
  "geometry": {"coordinates":[-80.596947,42.987686],"type":"Point"}
}