{
  "type": "Feature",
  "properties": {
    "iso:country":"CA",
    "sg:city":"Deseronto",
    "sg:classifiers":[
        {
            "category":"Building & Trades",
            "subcategory":"Construction",
            "type":"Services"
        }
    ],
    "sg:phone":"+1 613 396 2666",
    "sg:postcode":"K0K 1X0",
    "sg:province":"ON",
    "sg:tags":[
        "contractor"
    ],
    "wof:name":"Earl Silver Construction",
    "wof:placetype":"venue"
},
  "geometry": {"coordinates":[-77.04750823969999,44.199092865],"type":"Point"}
}