{
  "type": "Feature",
  "properties": {
    "addr:full":"578 Rue DE LA Riviere Cowansville QC J2K 3G6",
    "addr:housenumber":"578",
    "addr:postcode":"j2k 3g6",
    "addr:street":"Rue De La Riviere",
    "iso:country":"CA",
    "sg:address":"578 Rue DE LA Riviere",
    "sg:city":"Cowansville",
    "sg:classifiers":[
        {
            "category":"Manufacturing",
            "subcategory":"Lumber",
            "type":"Manufacturing & Wholesale Goods"
        }
    ],
    "sg:phone":"+1 450 263 7120",
    "sg:postcode":"J2K 3G6",
    "sg:province":"QC",
    "sg:tags":[
        "company",
        "logging",
        "forester"
    ],
    "wof:name":"Groupement Forestier Du Haut",
    "wof:placetype":"venue"
},
  "geometry": {"coordinates":[-72.796989,45.210651],"type":"Point"}
}