{
  "type": "Feature",
  "properties": {
    "iso:country":"CA",
    "sg:address":"21 Market St",
    "sg:city":"Fenelon Falls",
    "sg:classifiers":[
        {
            "category":"Education",
            "subcategory":"Library",
            "type":"Public Place"
        }
    ],
    "sg:phone":"+1 705 887 6300",
    "sg:postcode":"K0M 1N0",
    "sg:province":"ON",
    "wof:name":"Fenelon Falls Public Library",
    "wof:placetype":"venue"
},
  "geometry": {"coordinates":[-78.73802947999999,44.5380783081],"type":"Point"}
}