{
  "type": "Feature",
  "properties": {
    "addr:full":"2020 Trafalgar Rd Oakville ON L6H 7H1",
    "addr:housenumber":"2020",
    "addr:postcode":"l6h 7h1",
    "addr:street":"Trafalgar Rd",
    "iso:country":"CA",
    "sg:address":"2020 Trafalgar Rd",
    "sg:city":"Oakville",
    "sg:classifiers":[
        {
            "category":"Autos & Motor Vehicles",
            "subcategory":"Fuel & Gas Station",
            "type":"Retail Goods"
        }
    ],
    "sg:phone":"+1 905 337 9548",
    "sg:postcode":"L6H 7H1",
    "sg:province":"ON",
    "sg:tags":[
        "oil"
    ],
    "wof:name":"Trafalgar Oakville Shell",
    "wof:placetype":"venue"
},
  "geometry": {"coordinates":[-79.70296478269999,43.4755325317],"type":"Point"}
}