{
  "type": "Feature",
  "properties": {
    "addr:full":"4221 Comeau Rd Quesnel BC V2J 6W8",
    "addr:postcode":"4221;v2j 6w8",
    "addr:street":"Comeau Rd",
    "iso:country":"CA",
    "sg:address":"4221 Comeau Rd",
    "sg:city":"Quesnel",
    "sg:classifiers":[
        {
            "category":"Manufacturing",
            "subcategory":"Lumber",
            "type":"Manufacturing & Wholesale Goods"
        }
    ],
    "sg:phone":"+1 250 992 9696",
    "sg:postcode":"V2J 6W8",
    "sg:province":"BC",
    "sg:tags":[
        "company",
        "logging",
        "log",
        "hauling"
    ],
    "wof:name":"Specialty Logging Ltd",
    "wof:placetype":"venue"
},
  "geometry": {"coordinates":[-122.498245,52.978119],"type":"Point"}
}