{
  "type": "Feature",
  "properties": {
    "addr:full":"1379 Rue Provancher Cap-Rouge QC G1Y 1R7",
    "addr:housenumber":"1379",
    "addr:postcode":"g1y 1r7",
    "addr:street":"Rue Provancher",
    "iso:country":"CA",
    "sg:address":"1379 Rue Provancher",
    "sg:city":"Cap-Rouge",
    "sg:classifiers":[
        {
            "category":"Shopping",
            "type":"Retail Goods"
        }
    ],
    "sg:phone":"+1 418 650 0499",
    "sg:postcode":"G1Y 1R7",
    "sg:province":"QC",
    "sg:tags":[
        "picture",
        "frame"
    ],
    "wof:name":"Atelier D'Yves & Valo",
    "wof:placetype":"venue"
},
  "geometry": {"coordinates":[-71.344162,46.75325],"type":"Point"}
}