{
  "type": "Feature",
  "properties": {
    "addr:full":"404 4th St Reston MB R0M 1X0",
    "addr:housenumber":"404",
    "addr:postcode":"r0m 1x0",
    "addr:street":"4Th St",
    "iso:country":"CA",
    "sg:address":"404 4th St",
    "sg:city":"Reston",
    "sg:classifiers":[
        {
            "category":"Organizations",
            "subcategory":"Community Association",
            "type":"Services"
        }
    ],
    "sg:phone":"+1 204 877 3020",
    "sg:postcode":"R0M 1X0",
    "sg:province":"MB",
    "sg:tags":[
        "environmental",
        "org"
    ],
    "wof:name":"West Souris River Conservation",
    "wof:placetype":"venue"
},
  "geometry": {"coordinates":[-101.094970703,49.5622596741],"type":"Point"}
}