{
  "type": "Feature",
  "properties": {
    "addr:full":"232 Scott St Fort Frances ON P9A 1G7",
    "addr:housenumber":"232",
    "addr:postcode":"p9a 1g7",
    "addr:street":"Scott St",
    "iso:country":"CA",
    "sg:address":"232 Scott St",
    "sg:city":"Fort Frances",
    "sg:classifiers":[
        {
            "category":"Restaurant",
            "type":"Food & Drink"
        }
    ],
    "sg:phone":"+1 807 274 1143",
    "sg:postcode":"P9A 1G7",
    "sg:province":"ON",
    "wof:name":"Flambee",
    "wof:placetype":"venue"
},
  "geometry": {"coordinates":[-93.3975448608,48.6101150513],"type":"Point"}
}