{
  "type": "Feature",
  "properties": {
    "addr:full":"84695 Road 173 Atwood ON N0G 1B0",
    "addr:housenumber":"84695",
    "addr:postcode":"n0g 1b0",
    "addr:street":"Road 173",
    "iso:country":"CA",
    "sg:address":"84695 Road 173",
    "sg:city":"Atwood",
    "sg:classifiers":[
        {
            "category":"Freight",
            "type":"Transportation"
        }
    ],
    "sg:phone":"+1 519 356 2550",
    "sg:postcode":"N0G 1B0",
    "sg:province":"ON",
    "sg:tags":[
        "trucking"
    ],
    "wof:name":"Lloyd Hurst Transport",
    "wof:placetype":"venue"
},
  "geometry": {"coordinates":[-81.017471,43.669922],"type":"Point"}
}