{
  "type": "Feature",
  "properties": {
    "iso:country":"CA",
    "sg:city":"Toronto",
    "sg:classifiers":[
        {
            "category":"Manufacturing",
            "subcategory":"Printing",
            "type":"Manufacturing & Wholesale Goods"
        }
    ],
    "sg:phone":"+1 416 922 7223",
    "sg:postcode":"M4Y 1Z4",
    "sg:province":"ON",
    "sg:tags":[
        "publisher"
    ],
    "wof:name":"Performance Racing News",
    "wof:placetype":"venue"
},
  "geometry": {"coordinates":[-79.38497161870001,43.6661643982],"type":"Point"}
}