{
  "type": "Feature",
  "properties": {
    "addr:full":"3941 Rue Sainte-Emilie Montreal QC H4C 2A2",
    "addr:housenumber":"3941",
    "addr:postcode":"h4c 2a2",
    "addr:street":"Rue Sainte-Emilie",
    "iso:country":"CA",
    "sg:address":"3941 Rue Sainte-Emilie",
    "sg:city":"Montreal",
    "sg:classifiers":[
        {
            "category":"Retail",
            "subcategory":"Auto Repair",
            "type":"Services"
        }
    ],
    "sg:phone":"+1 514 932 3130",
    "sg:postcode":"H4C 2A2",
    "sg:province":"QC",
    "sg:tags":[
        "machine",
        "automobile",
        "repairing",
        "shop"
    ],
    "wof:name":"Lachapelle, Pierre",
    "wof:placetype":"venue"
},
  "geometry": {"coordinates":[-73.580963,45.477364],"type":"Point"}
}