{
  "type": "Feature",
  "properties": {
    "addr:full":"105 Durham St Sudbury ON P3E 3M9",
    "addr:housenumber":"105",
    "addr:postcode":"p3e 3m9",
    "addr:street":"Durham St",
    "iso:country":"CA",
    "sg:address":"105 Durham St",
    "sg:city":"Sudbury",
    "sg:classifiers":[
        {
            "category":"Shopping",
            "subcategory":"Used Merchandise",
            "type":"Retail Goods"
        }
    ],
    "sg:phone":"+1 705 669 1482",
    "sg:postcode":"P3E 3M9",
    "sg:province":"ON",
    "sg:tags":[
        "second",
        "store",
        "hand"
    ],
    "wof:name":"Jarrett Value 2",
    "wof:placetype":"venue"
},
  "geometry": {"coordinates":[-80.995239,46.491089],"type":"Point"}
}