{
  "type": "Feature",
  "properties": {
    "addr:full":"700 Paris St Sudbury ON P3E 3B5",
    "addr:housenumber":"700",
    "addr:postcode":"p3e 3b5",
    "addr:street":"Paris St",
    "iso:country":"CA",
    "sg:address":"700 Paris St",
    "sg:city":"Sudbury",
    "sg:classifiers":[
        {
            "category":"Health Services",
            "subcategory":"Hospital",
            "type":"Services"
        }
    ],
    "sg:phone":"+1 705 523 7100",
    "sg:postcode":"P3E 3B5",
    "sg:province":"ON",
    "wof:name":"Sudbury Regional Hospital",
    "wof:placetype":"venue"
},
  "geometry": {"coordinates":[-80.99140199999999,46.479046],"type":"Point"}
}