{
  "type": "Feature",
  "properties": {
    "iso:country":"CA",
    "sg:address":"225 Douglas Woods Pl SE",
    "sg:city":"Calgary",
    "sg:classifiers":[
        {
            "category":"Professional",
            "subcategory":"Engineering",
            "type":"Services"
        }
    ],
    "sg:phone":"+1 403 279 7740",
    "sg:postcode":"T2Z 1K6",
    "sg:province":"AB",
    "sg:tags":[
        "engineer"
    ],
    "wof:name":"Compu Stress Engineering Ltd",
    "wof:placetype":"venue"
},
  "geometry": {"coordinates":[-114.001747131,50.9448623657],"type":"Point"}
}