{
  "type": "Feature",
  "properties": {
    "addr:full":"3511 Kennedy Rd Scarborough ON M1V 4Y3",
    "addr:housenumber":"3511",
    "addr:postcode":"m1v 4y3",
    "addr:street":"Kennedy Rd",
    "iso:country":"CA",
    "sg:address":"3511 Kennedy Rd",
    "sg:city":"Scarborough",
    "sg:classifiers":[
        {
            "category":"Retail",
            "subcategory":"Auto Repair",
            "type":"Services"
        }
    ],
    "sg:phone":"+1 416 298 9939",
    "sg:postcode":"M1V 4Y3",
    "sg:province":"ON",
    "sg:tags":[
        "repairing",
        "automobile"
    ],
    "wof:name":"Wong's Auto & Trading CO",
    "wof:placetype":"venue"
},
  "geometry": {"coordinates":[-79.305809021,43.8213119507],"type":"Point"}
}