{
  "type": "Feature",
  "properties": {
    "addr:full":"47 Temperance St Bowmanville ON L1C 3A7",
    "addr:housenumber":"47",
    "addr:postcode":"l1c 3a7",
    "addr:street":"Temperance St",
    "iso:country":"CA",
    "sg:address":"47 Temperance St",
    "sg:city":"Bowmanville",
    "sg:classifiers":[
        {
            "category":"Organizations",
            "subcategory":"Religious Organization",
            "type":"Services"
        }
    ],
    "sg:phone":"+1 905 623 3432",
    "sg:postcode":"L1C 3A7",
    "sg:province":"ON",
    "sg:tags":[
        "church"
    ],
    "wof:name":"St Andrews Presbyterian",
    "wof:placetype":"venue"
},
  "geometry": {"coordinates":[-78.68845399999999,43.913498],"type":"Point"}
}