{
  "type": "Feature",
  "properties": {
    "iso:country":"CA",
    "sg:address":"15 Varden Cres",
    "sg:city":"Barrie",
    "sg:classifiers":[
        {
            "category":"Building & Trades",
            "subcategory":"Construction",
            "type":"Services"
        }
    ],
    "sg:phone":"+1 705 726 9358",
    "sg:postcode":"L4M 4N8",
    "sg:province":"ON",
    "sg:tags":[
        "general",
        "contractor"
    ],
    "wof:name":"Morris Builder & Contracting",
    "wof:placetype":"venue"
},
  "geometry": {"coordinates":[-79.65873,44.397362],"type":"Point"}
}