{
  "type": "Feature",
  "properties": {
    "addr:full":"418 Fitzwilliam St # 8 Nanaimo BC V9R 3A7",
    "addr:housenumber":"418",
    "addr:postcode":"v9r 3a7",
    "addr:street":"Fitzwilliam St # 8",
    "iso:country":"CA",
    "sg:address":"418 Fitzwilliam St # 8",
    "sg:city":"Nanaimo",
    "sg:classifiers":[
        {
            "category":"Insurance",
            "subcategory":"Insurance Agent",
            "type":"Services"
        }
    ],
    "sg:phone":"+1 250 754 8787",
    "sg:postcode":"V9R 3A7",
    "sg:province":"BC",
    "wof:name":"Zorkin Insurance Brokers",
    "wof:placetype":"venue"
},
  "geometry": {"coordinates":[-123.942024,49.165512],"type":"Point"}
}