{
  "type": "Feature",
  "properties": {
    "addr:full":"Toronto ON M4P 3A1",
    "addr:postcode":"m4p 3a1",
    "iso:country":"CA",
    "sg:city":"Toronto",
    "sg:classifiers":[
        {
            "category":"Health Services",
            "subcategory":"Optometrist",
            "type":"Services"
        }
    ],
    "sg:phone":"+1 416 488 4904",
    "sg:postcode":"M4P 3A1",
    "sg:province":"ON",
    "wof:name":"Leo, Pasquale P OD",
    "wof:placetype":"venue"
},
  "geometry": {"coordinates":[-79.398147583,43.7066497803],"type":"Point"}
}