{
  "type": "Feature",
  "properties": {
    "addr:full":"Winnipeg MB R3G 0T3",
    "addr:postcode":"r3g 0t3",
    "iso:country":"CA",
    "sg:city":"Winnipeg",
    "sg:classifiers":[
        {
            "category":"Government",
            "subcategory":"Office",
            "type":"Public Place"
        }
    ],
    "sg:phone":"+1 204 945 7912",
    "sg:postcode":"R3G 0T3",
    "sg:province":"MB",
    "wof:name":"Manitoba Program & Student Svc",
    "wof:placetype":"venue"
},
  "geometry": {"coordinates":[-97.18373099999999,49.883648],"type":"Point"}
}