{
  "type": "Feature",
  "properties": {
    "iso:country":"CA",
    "sg:city":"Laval",
    "sg:classifiers":[
        {
            "category":"Building & Trades",
            "subcategory":"Construction",
            "type":"Services"
        }
    ],
    "sg:phone":"+1 450 963 4343",
    "sg:postcode":"H7P 1T1",
    "sg:province":"QC",
    "sg:tags":[
        "general",
        "contractor"
    ],
    "wof:name":"Mgb Associes",
    "wof:placetype":"venue"
},
  "geometry": {"coordinates":[-73.786072,45.579842],"type":"Point"}
}