{
  "type": "Feature",
  "properties": {
    "addr:full":"999 Boul DE Maisonneuve O # 750 Montreal QC H3A 3L4",
    "addr:housenumber":"999",
    "addr:postcode":"h3a 3l4",
    "addr:street":"Boul De Maisonneuve O # 750",
    "iso:country":"CA",
    "sg:address":"999 Boul DE Maisonneuve O # 750",
    "sg:city":"Montreal",
    "sg:classifiers":[
        {
            "category":"Professional",
            "subcategory":"Employment Agencies",
            "type":"Services"
        }
    ],
    "sg:phone":"+1 514 849 5493",
    "sg:postcode":"H3A 3L4",
    "sg:province":"QC",
    "sg:tags":[
        "opportunity"
    ],
    "wof:name":"Option 10-10 Inc",
    "wof:placetype":"venue"
},
  "geometry": {"coordinates":[-73.5590133667,45.5176773071],"type":"Point"}
}