{
  "type": "Feature",
  "properties": {
    "addr:full":"340 Main St W North Bay ON P1B 9V1",
    "addr:housenumber":"340",
    "addr:postcode":"p1b 9v1",
    "addr:street":"Main St W",
    "iso:country":"CA",
    "sg:address":"340 Main St W",
    "sg:city":"North Bay",
    "sg:classifiers":[
        {
            "category":"Travel",
            "subcategory":"Hotels & Motels",
            "type":"Entertainment"
        }
    ],
    "sg:phone":"+1 705 495 6461",
    "sg:postcode":"P1B 9V1",
    "sg:province":"ON",
    "wof:name":"Inn on the Bay",
    "wof:placetype":"venue"
},
  "geometry": {"coordinates":[-79.466568,46.313606],"type":"Point"}
}