{
  "type": "Feature",
  "properties": {
    "addr:full":"3236 Weston Rd North York ON M9M 2T8",
    "addr:housenumber":"3236",
    "addr:postcode":"m9m 2t8",
    "addr:street":"Weston Rd",
    "iso:country":"CA",
    "sg:address":"3236 Weston Rd",
    "sg:city":"North York",
    "sg:classifiers":[
        {
            "category":"Shopping",
            "subcategory":"Pharmacy",
            "type":"Retail Goods"
        }
    ],
    "sg:phone":"+1 416 742 7307",
    "sg:postcode":"M9M 2T8",
    "sg:province":"ON",
    "wof:name":"Woodview Medical Pharmacy",
    "wof:placetype":"venue"
},
  "geometry": {"coordinates":[-79.539742,43.739273],"type":"Point"}
}