{
  "type": "Feature",
  "properties": {
    "addr:full":"420 Mill St #C Nelson BC V1L 4R9",
    "addr:housenumber":"420",
    "addr:postcode":"bc v1l 4r9",
    "addr:street":"Mill St # C",
    "iso:country":"CA",
    "sg:address":"420 Mill St #C",
    "sg:city":"Nelson",
    "sg:classifiers":[
        {
            "category":"Organizations",
            "subcategory":"Membership Organization",
            "type":"Services"
        }
    ],
    "sg:phone":"+1 250 352 9916",
    "sg:postcode":"V1L 4R9",
    "sg:province":"BC",
    "wof:name":"Nelson Women's Ctr",
    "wof:placetype":"venue"
},
  "geometry": {"coordinates":[-117.292168,49.488407],"type":"Point"}
}