{
  "type": "Feature",
  "properties": {
    "addr:full":"180 College St #C202 Sudbury ON P3C 5T2",
    "addr:housenumber":"180",
    "addr:postcode":"p3c 5t2",
    "addr:street":"College St # C202",
    "iso:country":"CA",
    "sg:address":"180 College St #C202",
    "sg:city":"Sudbury",
    "sg:classifiers":[
        {
            "category":"Education",
            "subcategory":"School",
            "type":"Public Place"
        }
    ],
    "sg:phone":"+1 705 675 5481",
    "sg:postcode":"P3C 5T2",
    "sg:province":"ON",
    "wof:name":"Adult Education Ctr",
    "wof:placetype":"venue"
},
  "geometry": {"coordinates":[-80.999771,46.496181],"type":"Point"}
}