{
  "type": "Feature",
  "properties": {
    "addr:full":"PO Box 59 Wabasca AB T0G 2K0",
    "addr:housenumber":"po box 59",
    "addr:postcode":"t0g 2k0",
    "addr:street":"Wabasca Ab",
    "iso:country":"CA",
    "sg:address":"PO Box 59",
    "sg:city":"Wabasca",
    "sg:classifiers":[
        {
            "category":"Social Services",
            "subcategory":"Child Care",
            "type":"Services"
        }
    ],
    "sg:phone":"+1 780 891 3988",
    "sg:postcode":"T0G 2K0",
    "sg:province":"AB",
    "sg:tags":[
        "kindergarten",
        "academic",
        "school",
        "montessori"
    ],
    "wof:name":"Children's Place Playschool",
    "wof:placetype":"venue"
},
  "geometry": {"coordinates":[-113.823402405,55.948551178],"type":"Point"}
}