{
  "type": "Feature",
  "properties": {
    "addr:full":"279 Rang Lepage Sainte-Anne-Des-Plaines QC J0N 1H0",
    "addr:housenumber":"279",
    "addr:postcode":"j0n 1h0",
    "addr:street":"Rang Lepage",
    "iso:country":"CA",
    "sg:address":"279 Rang Lepage",
    "sg:city":"Sainte-Anne-Des-Plaines",
    "sg:classifiers":[
        {
            "category":"Wholesale",
            "subcategory":"Machinery & Supplies",
            "type":"Manufacturing & Wholesale Goods"
        }
    ],
    "sg:phone":"+1 450 478 2491",
    "sg:postcode":"J0N 1H0",
    "sg:province":"QC",
    "sg:tags":[
        "ladder"
    ],
    "wof:name":"Echellex Enr",
    "wof:placetype":"venue"
},
  "geometry": {"coordinates":[-73.807388,45.73111],"type":"Point"}
}