{
  "type": "Feature",
  "properties": {
    "addr:full":"219 8 Ave SW Calgary AB T2P 1B7",
    "addr:housenumber":"219",
    "addr:postcode":"t2p 1b7",
    "addr:street":"8 Ave Sw",
    "iso:country":"CA",
    "sg:address":"219 8 Ave SW",
    "sg:city":"Calgary",
    "sg:classifiers":[
        {
            "category":"Bars & Pubs",
            "type":"Food & Drink"
        }
    ],
    "sg:phone":"+1 403 263 9980",
    "sg:postcode":"T2P 1B7",
    "sg:province":"AB",
    "sg:tags":[
        "club",
        "night"
    ],
    "wof:name":"Palace Night Club",
    "wof:placetype":"venue"
},
  "geometry": {"coordinates":[-114.066108704,51.0454788208],"type":"Point"}
}