{
  "type": "Feature",
  "properties": {
    "addr:full":"110 9th Ave E Kindersley SK S0L 1S0",
    "addr:housenumber":"110",
    "addr:postcode":"s0l 1s0",
    "addr:street":"9Th Ave E Kindersley",
    "iso:country":"CA",
    "sg:address":"110 9th Ave E",
    "sg:city":"Kindersley",
    "sg:classifiers":[
        {
            "category":"Building & Trades",
            "subcategory":"Electrical",
            "type":"Services"
        }
    ],
    "sg:phone":"+1 306 463 2511",
    "sg:postcode":"S0L 1S0",
    "sg:province":"SK",
    "sg:tags":[
        "electric",
        "contractor"
    ],
    "wof:name":"Tarnes Electric Ltd",
    "wof:placetype":"venue"
},
  "geometry": {"coordinates":[-109.15994262700001,51.4729309082],"type":"Point"}
}