{
  "type": "Feature",
  "properties": {
    "addr:full":"109 Railway Ave S Rockglen SK S0H 3R0",
    "addr:housenumber":"109",
    "addr:postcode":"s0h 3r0",
    "addr:street":"Railway Ave S Rockglen",
    "iso:country":"CA",
    "sg:address":"109 Railway Ave S",
    "sg:city":"Rockglen",
    "sg:classifiers":[
        {
            "category":"Personal",
            "subcategory":"Beauty Salon",
            "type":"Services"
        }
    ],
    "sg:phone":"+1 306 476 2378",
    "sg:postcode":"S0H 3R0",
    "sg:province":"SK",
    "wof:name":"Fawn's Salon",
    "wof:placetype":"venue"
},
  "geometry": {"coordinates":[-105.950256348,49.180015564],"type":"Point"}
}