{
  "type": "Feature",
  "properties": {
    "addr:full":"1240 St Charles Rd N Lethbridge AB T1H 4M4",
    "addr:housenumber":"1240",
    "addr:postcode":"t1h 4m4",
    "addr:street":"St Charles Rd N",
    "iso:country":"CA",
    "sg:address":"1240 St Charles Rd N",
    "sg:city":"Lethbridge",
    "sg:classifiers":[
        {
            "category":"Building & Trades",
            "subcategory":"Construction",
            "type":"Services"
        }
    ],
    "sg:phone":"+1 403 380 6052",
    "sg:postcode":"T1H 4M4",
    "sg:province":"AB",
    "sg:tags":[
        "repairing",
        "remodeling",
        "contractor"
    ],
    "wof:name":"Al Janzen Home Renovations",
    "wof:placetype":"venue"
},
  "geometry": {"coordinates":[-112.827713,49.718262],"type":"Point"}
}