{
  "type": "Feature",
  "properties": {
    "addr:full":"1382 Rue Provancher Cap-Rouge QC G1Y 1R6",
    "addr:housenumber":"1382",
    "addr:postcode":"g1y 1r6",
    "addr:street":"Rue Provancher",
    "iso:country":"CA",
    "sg:address":"1382 Rue Provancher",
    "sg:city":"Cap-Rouge",
    "sg:classifiers":[
        {
            "category":"Shopping",
            "type":"Retail Goods"
        }
    ],
    "sg:phone":"+1 418 651 5962",
    "sg:postcode":"G1Y 1R6",
    "sg:province":"QC",
    "sg:tags":[
        "art",
        "gallery",
        "dealer"
    ],
    "wof:name":"Atelier Du Vieux Cap-Rouge",
    "wof:placetype":"venue"
},
  "geometry": {"coordinates":[-71.3442687988,46.7525062561],"type":"Point"}
}