{
  "type": "Feature",
  "properties": {
    "addr:full":"33 Memorial Dr # 101 Brantford ON N3R 5R8",
    "addr:housenumber":"33",
    "addr:postcode":"n3r 5r8",
    "addr:street":"Memorial Dr # 101",
    "iso:country":"CA",
    "sg:address":"33 Memorial Dr # 101",
    "sg:city":"Brantford",
    "sg:classifiers":[
        {
            "category":"Real Estate",
            "subcategory":"Developer",
            "type":"Services"
        }
    ],
    "sg:phone":"+1 519 752 0557",
    "sg:postcode":"N3R 5R8",
    "sg:province":"ON",
    "sg:tags":[
        "company",
        "land"
    ],
    "wof:name":"Award Construction Ltd",
    "wof:placetype":"venue"
},
  "geometry": {"coordinates":[-80.2581481934,43.1719436646],"type":"Point"}
}