{
  "type": "Feature",
  "properties": {
    "addr:full":"Flowers Cove NL A0K 2N0",
    "addr:postcode":"a0k 2n0",
    "addr:street":"Cove",
    "iso:country":"CA",
    "sg:city":"Flowers Cove",
    "sg:classifiers":[
        {
            "category":"Food & Beverages",
            "subcategory":"Groceries & Convenience Stores",
            "type":"Retail Goods"
        }
    ],
    "sg:phone":"+1 709 456 2492",
    "sg:postcode":"A0K 2N0",
    "sg:province":"NL",
    "sg:tags":[
        "grocer"
    ],
    "wof:name":"St Barbe Consumers CO-OP Soc",
    "wof:placetype":"venue"
},
  "geometry": {"coordinates":[-56.729759,51.297535],"type":"Point"}
}