{
  "type": "Feature",
  "properties": {
    "addr:full":"4th Ave Leroy SK S0K 2P0",
    "addr:postcode":"s0k 2p0",
    "addr:street":"4Th Ave",
    "iso:country":"CA",
    "sg:address":"4th Ave",
    "sg:city":"Leroy",
    "sg:classifiers":[
        {
            "category":"Education",
            "subcategory":"School",
            "type":"Public Place"
        }
    ],
    "sg:phone":"+1 306 286 3313",
    "sg:postcode":"S0K 2P0",
    "sg:province":"SK",
    "wof:name":"Leroy School",
    "wof:placetype":"venue"
},
  "geometry": {"coordinates":[-104.744072,52.003365],"type":"Point"}
}