{
  "type": "Feature",
  "properties": {
    "iso:country":"CA",
    "sg:address":"924 7 Ave SW",
    "sg:city":"Calgary",
    "sg:classifiers":[
        {
            "category":"Restaurant",
            "type":"Food & Drink"
        }
    ],
    "sg:phone":"+1 403 262 5445",
    "sg:postcode":"T2P 1A4",
    "sg:province":"AB",
    "sg:tags":[
        "shop",
        "coffee"
    ],
    "wof:name":"Cappuccino CO",
    "wof:placetype":"venue"
},
  "geometry": {"coordinates":[-114.081893921,51.0471763611],"type":"Point"}
}