{
  "type": "Feature",
  "properties": {
    "addr:full":"1635 Lawrence Ave W #202 North York ON M6L 3C9",
    "addr:housenumber":"1635",
    "addr:postcode":"m6l 3c9",
    "addr:street":"Lawrence Ave W # 202",
    "iso:country":"CA",
    "sg:address":"1635 Lawrence Ave W #202",
    "sg:city":"North York",
    "sg:classifiers":[
        {
            "category":"Health Services",
            "subcategory":"Doctor",
            "type":"Services"
        }
    ],
    "sg:phone":"+1 416 243 3300",
    "sg:postcode":"M6L 3C9",
    "sg:province":"ON",
    "sg:tags":[
        "physician",
        "surgeon"
    ],
    "wof:name":"Giddens, J David MD",
    "wof:placetype":"venue"
},
  "geometry": {"coordinates":[-79.49205000000001,43.705273],"type":"Point"}
}