{
  "type": "Feature",
  "properties": {
    "addr:full":"Lunenburg NS B0J 2C0",
    "addr:postcode":"b0j 2c0",
    "iso:country":"CA",
    "sg:city":"Lunenburg",
    "sg:classifiers":[
        {
            "category":"Government",
            "subcategory":"Office",
            "type":"Public Place"
        }
    ],
    "sg:phone":"+1 902 541 1344",
    "sg:postcode":"B0J 2C0",
    "sg:province":"NS",
    "sg:tags":[
        "village"
    ],
    "wof:name":"Lunenburg Recreation Program",
    "wof:placetype":"venue"
},
  "geometry": {"coordinates":[-64.318443,44.377213],"type":"Point"}
}