{
  "type": "Feature",
  "properties": {
    "addr:full":"7912 99 Ave Fort St John BC V1J 6K4",
    "addr:housenumber":"7912",
    "addr:postcode":"v1j 6k4",
    "addr:street":"99 Ave",
    "iso:country":"CA",
    "sg:address":"7912 99 Ave",
    "sg:city":"Fort St John",
    "sg:classifiers":[
        {
            "category":"Shopping",
            "subcategory":"Bicycles & Sporting Goods",
            "type":"Retail Goods"
        }
    ],
    "sg:phone":"+1 250 785 6503",
    "sg:postcode":"V1J 6K4",
    "sg:province":"BC",
    "sg:tags":[
        "saddlery",
        "harness"
    ],
    "wof:name":"Pokiak Plastics",
    "wof:placetype":"venue"
},
  "geometry": {"coordinates":[-120.80846405,56.2456130981],"type":"Point"}
}