{
  "type": "Feature",
  "properties": {
    "addr:full":"8576 Rue Saint-Denis Montreal QC H2P 2H2",
    "addr:housenumber":"8576",
    "addr:postcode":"h2p 2h2",
    "addr:street":"Rue Saint-Denis",
    "iso:country":"CA",
    "sg:address":"8576 Rue Saint-Denis",
    "sg:city":"Montreal",
    "sg:classifiers":[
        {
            "category":"Personal",
            "subcategory":"Beauty Salon",
            "type":"Services"
        }
    ],
    "sg:phone":"+1 514 387 2393",
    "sg:postcode":"H2P 2H2",
    "sg:province":"QC",
    "wof:name":"Gy-Zel Coiffure",
    "wof:placetype":"venue"
},
  "geometry": {"coordinates":[-73.636719,45.544643],"type":"Point"}
}