{
  "type": "Feature",
  "properties": {
    "addr:full":"38 Mckillop Crt Brampton ON L6Y 3J2",
    "addr:housenumber":"38",
    "addr:postcode":"l6y 3j2",
    "addr:street":"Mckillop Crt",
    "iso:country":"CA",
    "sg:address":"38 Mckillop Crt",
    "sg:city":"Brampton",
    "sg:classifiers":[
        {
            "category":"Home & Garden",
            "subcategory":"Building Materials",
            "type":"Retail Goods"
        }
    ],
    "sg:phone":"+1 905 451 1870",
    "sg:postcode":"L6Y 3J2",
    "sg:province":"ON",
    "sg:tags":[
        "metal"
    ],
    "wof:name":"Metal Design Systems Intl",
    "wof:placetype":"venue"
},
  "geometry": {"coordinates":[-79.743172,43.667168],"type":"Point"}
}