{
  "type": "Feature",
  "properties": {
    "addr:full":"1077 Rue Clark Montreal QC H2Z 1K3",
    "addr:housenumber":"1077",
    "addr:postcode":"h2z 1k3",
    "addr:street":"Rue Clark",
    "iso:country":"CA",
    "sg:address":"1077 Rue Clark",
    "sg:city":"Montreal",
    "sg:classifiers":[
        {
            "category":"Restaurant",
            "type":"Food & Drink"
        }
    ],
    "sg:phone":"+1 514 861 1943",
    "sg:postcode":"H2Z 1K3",
    "sg:province":"QC",
    "wof:name":"Maison Vip",
    "wof:placetype":"venue"
},
  "geometry": {"coordinates":[-73.56060791020001,45.5080528259],"type":"Point"}
}