{
  "type": "Feature",
  "properties": {
    "iso:country":"CA",
    "sg:address":"325 138 Rte",
    "sg:city":"Saint-Augustin-DE-Desmaures",
    "sg:classifiers":[
        {
            "category":"Organizations",
            "subcategory":"Religious Organization",
            "type":"Services"
        }
    ],
    "sg:phone":"+1 418 878 2140",
    "sg:postcode":"G3A 1G7",
    "sg:province":"QC",
    "sg:tags":[
        "church"
    ],
    "wof:name":"Presbytere St-Augustin",
    "wof:placetype":"venue"
},
  "geometry": {"coordinates":[-71.384727,46.749176],"type":"Point"}
}