{
  "type": "Feature",
  "properties": {
    "addr:full":"6897 Av Somerled Montreal QC H4V 1V2",
    "addr:housenumber":"6897",
    "addr:postcode":"h4v 1v2",
    "addr:street":"Av Somerled",
    "iso:country":"CA",
    "sg:address":"6897 Av Somerled",
    "sg:city":"Montreal",
    "sg:classifiers":[
        {
            "category":"Organizations",
            "subcategory":"Religious Organization",
            "type":"Services"
        }
    ],
    "sg:phone":"+1 514 484 2750",
    "sg:postcode":"H4V 1V2",
    "sg:province":"QC",
    "sg:tags":[
        "church"
    ],
    "wof:name":"St Thomas Church",
    "wof:placetype":"venue"
},
  "geometry": {"coordinates":[-73.64183,45.463425],"type":"Point"}
}