{
  "type": "Feature",
  "properties": {
    "addr:full":"6003 92 St NW Edmonton AB T6E 3A5",
    "addr:housenumber":"6003",
    "addr:postcode":"t6e 3a5",
    "addr:street":"92 St Nw",
    "iso:country":"CA",
    "sg:address":"6003 92 St NW",
    "sg:city":"Edmonton",
    "sg:classifiers":[
        {
            "category":"Wholesale",
            "subcategory":"Groceries",
            "type":"Manufacturing & Wholesale Goods"
        }
    ],
    "sg:phone":"+1 780 436 9650",
    "sg:postcode":"T6E 3A5",
    "sg:province":"AB",
    "sg:tags":[
        "baker"
    ],
    "wof:name":"Special D Baking Ltd",
    "wof:placetype":"venue"
},
  "geometry": {"coordinates":[-113.468628,53.495918],"type":"Point"}
}