{
  "type": "Feature",
  "properties": {
    "addr:full":"30 Huntley Crt NE Medicine Hat AB T1C 1W3",
    "addr:housenumber":"30",
    "addr:postcode":"t1c 1w3",
    "addr:street":"Huntley Crt Ne",
    "iso:country":"CA",
    "sg:address":"30 Huntley Crt NE",
    "sg:city":"Medicine Hat",
    "sg:classifiers":[
        {
            "category":"Mining & Drilling",
            "type":"Manufacturing & Wholesale Goods"
        }
    ],
    "sg:phone":"+1 403 504 4456",
    "sg:postcode":"T1C 1W3",
    "sg:province":"AB",
    "sg:tags":[
        "consultant",
        "oil",
        "gas"
    ],
    "wof:name":"Doehring Consulting Ltd",
    "wof:placetype":"venue"
},
  "geometry": {"coordinates":[-110.678863525,50.0618553162],"type":"Point"}
}