{
  "type": "Feature",
  "properties": {
    "addr:full":"10288 Yonge St Richmond Hill ON L4C 3B8",
    "addr:housenumber":"10288",
    "addr:postcode":"l4c 3b8",
    "addr:street":"Yonge St",
    "iso:country":"CA",
    "sg:address":"10288 Yonge St",
    "sg:city":"Richmond Hill",
    "sg:classifiers":[
        {
            "category":"Professional",
            "subcategory":"Employment Agencies",
            "type":"Services"
        }
    ],
    "sg:phone":"+1 905 884 4800",
    "sg:postcode":"L4C 3B8",
    "sg:province":"ON",
    "sg:tags":[
        "co",
        "fraternal"
    ],
    "wof:name":"Employment Resource Ctr",
    "wof:placetype":"venue"
},
  "geometry": {"coordinates":[-79.439064,43.878311],"type":"Point"}
}