{
  "type": "Feature",
  "properties": {
    "addr:full":"8800 Boul Henri-Bourassa O Saint-Laurent QC H4S 1P4",
    "addr:housenumber":"8800",
    "addr:postcode":"h4s 1p4",
    "addr:street":"Boul Henri-Bourassa O",
    "iso:country":"CA",
    "sg:address":"8800 Boul Henri-Bourassa O",
    "sg:city":"Saint-Laurent",
    "sg:classifiers":[
        {
            "category":"Wholesale",
            "subcategory":"Durable Goods & Equipment",
            "type":"Manufacturing & Wholesale Goods"
        }
    ],
    "sg:phone":"+1 514 335 1500",
    "sg:postcode":"H4S 1P4",
    "sg:province":"QC",
    "sg:tags":[
        "importer"
    ],
    "wof:name":"Glazers Inc",
    "wof:placetype":"venue"
},
  "geometry": {"coordinates":[-73.7456207275,45.5013961792],"type":"Point"}
}