{
  "type": "Feature",
  "properties": {
    "addr:full":"228 Boul Perron E Saint-Simeon-DE-Bonaventure QC G0C 3A0",
    "addr:housenumber":"228",
    "addr:postcode":"g0c 3a0",
    "addr:street":"Boul Perron E Saint-Simeon-De-Bonaventure",
    "iso:country":"CA",
    "sg:address":"228 Boul Perron E",
    "sg:city":"Saint-Simeon-DE-Bonaventure",
    "sg:classifiers":[
        {
            "category":"Building & Trades",
            "subcategory":"Electrical",
            "type":"Services"
        }
    ],
    "sg:phone":"+1 418 534 2553",
    "sg:postcode":"G0C 3A0",
    "sg:province":"QC",
    "sg:tags":[
        "electric",
        "contractor"
    ],
    "wof:name":"Renaud Poirier Enr",
    "wof:placetype":"venue"
},
  "geometry": {"coordinates":[-65.571381,48.070709],"type":"Point"}
}