{
  "type": "Feature",
  "properties": {
    "addr:full":"3969 Hamilton Rd Dorchester ON N0L 1G2",
    "addr:housenumber":"3969",
    "addr:postcode":"n0l 1g2",
    "addr:street":"Hamilton Rd",
    "iso:country":"CA",
    "sg:address":"3969 Hamilton Rd",
    "sg:city":"Dorchester",
    "sg:classifiers":[
        {
            "category":"Building & Trades",
            "subcategory":"Construction",
            "type":"Services"
        }
    ],
    "sg:phone":"+1 519 268 2995",
    "sg:postcode":"N0L 1G2",
    "sg:province":"ON",
    "sg:tags":[
        "drafting",
        "general",
        "contractor"
    ],
    "wof:name":"Barry Wade Design Construction",
    "wof:placetype":"venue"
},
  "geometry": {"coordinates":[-81.060883,42.988392],"type":"Point"}
}