{
  "type": "Feature",
  "properties": {
    "addr:full":"Railway Ave Fosston SK S0E 0V0",
    "addr:postcode":"s0e 0v0",
    "addr:street":"Railway Ave",
    "iso:country":"CA",
    "sg:address":"Railway Ave",
    "sg:city":"Fosston",
    "sg:classifiers":[
        {
            "category":"Food & Beverages",
            "subcategory":"Groceries & Convenience Stores",
            "type":"Retail Goods"
        }
    ],
    "sg:phone":"+1 306 322 4565",
    "sg:postcode":"S0E 0V0",
    "sg:province":"SK",
    "sg:tags":[
        "grocer"
    ],
    "wof:name":"Fosston Grocery",
    "wof:placetype":"venue"
},
  "geometry": {"coordinates":[-103.812477112,52.1934318542],"type":"Point"}
}