{
  "type": "Feature",
  "properties": {
    "addr:full":"215 Rue Saint-Jacques Montreal QC H2Y 1M6",
    "addr:housenumber":"215",
    "addr:postcode":"h2y 1m6",
    "addr:street":"Rue Saint-Jacques",
    "iso:country":"CA",
    "sg:address":"215 Rue Saint-Jacques",
    "sg:city":"Montreal",
    "sg:classifiers":[
        {
            "category":"Professional",
            "subcategory":"Business Services",
            "type":"Services"
        }
    ],
    "sg:phone":"+1 514 287 0339",
    "sg:postcode":"H2Y 1M6",
    "sg:province":"QC",
    "sg:tags":[
        "paralegal"
    ],
    "wof:name":"Quicklaw",
    "wof:placetype":"venue"
},
  "geometry": {"coordinates":[-73.55858600000001,45.503963],"type":"Point"}
}