{
  "type": "Feature",
  "properties": {
    "addr:full":"145 Wayne St Abbey SK S0N 0A0",
    "addr:housenumber":"145",
    "addr:postcode":"s0n 0a0",
    "addr:street":"Wayne St",
    "iso:country":"CA",
    "sg:address":"145 Wayne St",
    "sg:city":"Abbey",
    "sg:classifiers":[
        {
            "category":"Insurance",
            "subcategory":"Insurance Agent",
            "type":"Services"
        }
    ],
    "sg:phone":"+1 306 689 2227",
    "sg:postcode":"S0N 0A0",
    "sg:province":"SK",
    "wof:name":"Sgi",
    "wof:placetype":"venue"
},
  "geometry": {"coordinates":[-108.760628,50.733795],"type":"Point"}
}