{
  "type": "Feature",
  "properties": {
    "addr:full":"391 Dundas St W Trenton ON K8V 3S4",
    "addr:housenumber":"391",
    "addr:postcode":"k8v 3s4",
    "addr:street":"Dundas St W",
    "iso:country":"CA",
    "sg:address":"391 Dundas St W",
    "sg:city":"Trenton",
    "sg:classifiers":[
        {
            "category":"Food & Beverages",
            "subcategory":"Groceries & Convenience Stores",
            "type":"Retail Goods"
        }
    ],
    "sg:phone":"+1 613 394 1649",
    "sg:postcode":"K8V 3S4",
    "sg:province":"ON",
    "wof:name":"Busy Bee Convenience",
    "wof:placetype":"venue"
},
  "geometry": {"coordinates":[-77.591759,44.095943],"type":"Point"}
}