{
  "type": "Feature",
  "properties": {
    "addr:full":"820 Rue Sainte-Catherine E Montreal QC H2L 2E2",
    "addr:housenumber":"820",
    "addr:postcode":"h2l 2e2",
    "addr:street":"Rue Sainte-Catherine E",
    "iso:country":"CA",
    "sg:address":"820 Rue Sainte-Catherine E",
    "sg:city":"Montreal",
    "sg:classifiers":[
        {
            "category":"Shopping",
            "subcategory":"Clothing, Apparel, & Fashions",
            "type":"Retail Goods"
        }
    ],
    "sg:phone":"+1 514 845 3377",
    "sg:postcode":"H2L 2E2",
    "sg:province":"QC",
    "sg:tags":[
        "furnishing"
    ],
    "wof:name":"Ernest",
    "wof:placetype":"venue"
},
  "geometry": {"coordinates":[-73.55871582029999,45.5154953003],"type":"Point"}
}