{
  "type": "Feature",
  "properties": {
    "iso:country":"CA",
    "sg:address":"229 41 Ave NE",
    "sg:city":"Calgary",
    "sg:classifiers":[
        {
            "category":"Autos & Motor Vehicles",
            "subcategory":"Auto Supplies",
            "type":"Retail Goods"
        }
    ],
    "sg:phone":"+1 403 276 2998",
    "sg:postcode":"T2E 2N4",
    "sg:province":"AB",
    "sg:tags":[
        "alternator",
        "generator"
    ],
    "wof:name":"Import Alternators & Starters",
    "wof:placetype":"venue"
},
  "geometry": {"coordinates":[-114.060638428,51.0890274048],"type":"Point"}
}