{
  "type": "Feature",
  "properties": {
    "addr:full":"North York ON M3K 1Z3",
    "addr:postcode":"m3k 1z3",
    "iso:country":"CA",
    "sg:city":"North York",
    "sg:classifiers":[
        {
            "category":"Real Estate",
            "subcategory":"Real Estate Agent",
            "type":"Services"
        }
    ],
    "sg:phone":"+1 416 636 3616",
    "sg:postcode":"M3K 1Z3",
    "sg:province":"ON",
    "sg:tags":[
        "consultant",
        "review",
        "rent"
    ],
    "wof:name":"Andrade Consulting Group",
    "wof:placetype":"venue"
},
  "geometry": {"coordinates":[-79.46021270750001,43.7321014404],"type":"Point"}
}