{
  "type": "Feature",
  "properties": {
    "iso:country":"CA",
    "sg:address":"21 Armstrong St S",
    "sg:city":"New Liskeard",
    "sg:classifiers":[
        {
            "category":"Education",
            "subcategory":"School",
            "type":"Public Place"
        }
    ],
    "sg:phone":"+1 705 647 7304",
    "sg:postcode":"P0J 1P0",
    "sg:province":"ON",
    "wof:name":"Conseil Scolaire Catholique",
    "wof:placetype":"venue"
},
  "geometry": {"coordinates":[-79.6713562012,47.5089797974],"type":"Point"}
}