{
  "type": "Feature",
  "properties": {
    "addr:full":"60 Crockford Blvd Scarborough ON M1R 3C3",
    "addr:housenumber":"60",
    "addr:postcode":"m1r 3c3",
    "addr:street":"Crockford Blvd",
    "iso:country":"CA",
    "sg:address":"60 Crockford Blvd",
    "sg:city":"Scarborough",
    "sg:classifiers":[
        {
            "category":"Manufacturing",
            "subcategory":"Printing",
            "type":"Manufacturing & Wholesale Goods"
        }
    ],
    "sg:phone":"+1 416 750 4233",
    "sg:postcode":"M1R 3C3",
    "sg:province":"ON",
    "sg:tags":[
        "printer"
    ],
    "wof:name":"Good Impressions Graphics",
    "wof:placetype":"venue"
},
  "geometry": {"coordinates":[-79.28849,43.739525],"type":"Point"}
}