{
  "type": "Feature",
  "properties": {
    "addr:full":"North Vancouver BC V7J 3V3",
    "addr:postcode":"v7j 3v3",
    "iso:country":"CA",
    "sg:city":"North Vancouver",
    "sg:classifiers":[
        {
            "category":"Personal",
            "subcategory":"Barber",
            "type":"Services"
        }
    ],
    "sg:phone":"+1 604 987 1717",
    "sg:postcode":"V7J 3V3",
    "sg:province":"BC",
    "sg:tags":[
        "salon",
        "beauty"
    ],
    "wof:name":"Kirby's Hair Designs",
    "wof:placetype":"venue"
},
  "geometry": {"coordinates":[-123.03225707999999,49.3059997559],"type":"Point"}
}