{
  "type": "Feature",
  "properties": {
    "addr:full":"215 Eugenie St W # 170 Windsor ON N8X 2X7",
    "addr:housenumber":"215",
    "addr:postcode":"n8x 2x7",
    "addr:street":"Eugenie St W # 170",
    "iso:country":"CA",
    "sg:address":"215 Eugenie St W # 170",
    "sg:city":"Windsor",
    "sg:classifiers":[
        {
            "category":"Insurance",
            "subcategory":"Insurance Agent",
            "type":"Services"
        }
    ],
    "sg:phone":"+1 519 967 1180",
    "sg:postcode":"N8X 2X7",
    "sg:province":"ON",
    "sg:tags":[
        "consultant",
        "planning",
        "financial"
    ],
    "wof:name":"Freedom 55 Financial",
    "wof:placetype":"venue"
},
  "geometry": {"coordinates":[-83.0201721191,42.2855873108],"type":"Point"}
}