{
  "type": "Feature",
  "properties": {
    "addr:full":"Ajax ON L1S 2J5",
    "addr:postcode":"l1s 2j5",
    "iso:country":"CA",
    "sg:city":"Ajax",
    "sg:classifiers":[
        {
            "category":"Shopping",
            "subcategory":"Pharmacy",
            "type":"Retail Goods"
        }
    ],
    "sg:phone":"+1 905 427 2484",
    "sg:postcode":"L1S 2J5",
    "sg:province":"ON",
    "wof:name":"Medical Place Pharmacy",
    "wof:placetype":"venue"
},
  "geometry": {"coordinates":[-79.01533499999999,43.83773],"type":"Point"}
}