{
  "type": "Feature",
  "properties": {
    "addr:full":"1611 Valmont Way Richmond BC V6V 1Y3",
    "addr:housenumber":"1611",
    "addr:postcode":"v6v 1y3",
    "addr:street":"Valmont Way",
    "iso:country":"CA",
    "sg:address":"1611 Valmont Way",
    "sg:city":"Richmond",
    "sg:classifiers":[
        {
            "category":"Wholesale",
            "subcategory":"Machinery & Supplies",
            "type":"Manufacturing & Wholesale Goods"
        }
    ],
    "sg:phone":"+1 604 278 4481",
    "sg:postcode":"V6V 1Y3",
    "sg:province":"BC",
    "sg:tags":[
        "equipment",
        "hydraulic"
    ],
    "wof:name":"Psi Fluid Power Ltd",
    "wof:placetype":"venue"
},
  "geometry": {"coordinates":[-123.062065,49.200596],"type":"Point"}
}