{
  "type": "Feature",
  "properties": {
    "iso:country":"CA",
    "sg:address":"2158 Boul Des Ruisseaux",
    "sg:city":"Mont-Laurier",
    "sg:classifiers":[
        {
            "category":"Retail",
            "subcategory":"Auto Repair",
            "type":"Services"
        }
    ],
    "sg:phone":"+1 819 623 6805",
    "sg:postcode":"J9L 3G6",
    "sg:province":"QC",
    "sg:tags":[
        "repairing",
        "automobile"
    ],
    "wof:name":"Garage Auto Superieure Enr",
    "wof:placetype":"venue"
},
  "geometry": {"coordinates":[-75.6300582886,46.5605773926],"type":"Point"}
}