{
  "type": "Feature",
  "properties": {
    "addr:full":"11835 102 Ave NW Edmonton AB T5K 0R6",
    "addr:housenumber":"11835",
    "addr:postcode":"t5k 0r6",
    "addr:street":"102 Ave Nw",
    "iso:country":"CA",
    "sg:address":"11835 102 Ave NW",
    "sg:city":"Edmonton",
    "sg:classifiers":[
        {
            "category":"Professional",
            "subcategory":"Lawyer & Legal Services",
            "type":"Services"
        }
    ],
    "sg:phone":"+1 780 482 2888",
    "sg:postcode":"T5K 0R6",
    "sg:province":"AB",
    "sg:tags":[
        "attorney"
    ],
    "wof:name":"Miller Boileau Family Law Grp",
    "wof:placetype":"venue"
},
  "geometry": {"coordinates":[-113.525665283,53.5427932739],"type":"Point"}
}