{
  "type": "Feature",
  "properties": {
    "addr:full":"4443 Keith Ave Terrace BC V8G 1J7",
    "addr:housenumber":"4443",
    "addr:postcode":"v8g 1j7",
    "addr:street":"Keith Ave",
    "iso:country":"CA",
    "sg:address":"4443 Keith Ave",
    "sg:city":"Terrace",
    "sg:classifiers":[
        {
            "category":"Retail",
            "subcategory":"Repair Shop",
            "type":"Services"
        }
    ],
    "sg:phone":"+1 250 638 6030",
    "sg:postcode":"V8G 1J7",
    "sg:province":"BC",
    "sg:tags":[
        "lock",
        "locksmith"
    ],
    "wof:name":"Tolsec Lock & Key",
    "wof:placetype":"venue"
},
  "geometry": {"coordinates":[-128.57835388199999,54.5129356384],"type":"Point"}
}