{
  "type": "Feature",
  "properties": {
    "addr:full":"10243 100 St Fort St John BC V1J 3Y8",
    "addr:housenumber":"10243",
    "addr:postcode":"v1j 3y8",
    "addr:street":"100 St",
    "iso:country":"CA",
    "sg:address":"10243 100 St",
    "sg:city":"Fort St John",
    "sg:classifiers":[
        {
            "category":"Banks & Credit Unions",
            "subcategory":"Bank",
            "type":"Services"
        }
    ],
    "sg:phone":"+1 250 787 8811",
    "sg:postcode":"V1J 3Y8",
    "sg:province":"BC",
    "sg:tags":[
        "loan"
    ],
    "wof:name":"Cash Factory Loans Inc",
    "wof:placetype":"venue"
},
  "geometry": {"coordinates":[-120.84734344500001,56.2487640381],"type":"Point"}
}