{
  "type": "Feature",
  "properties": {
    "addr:full":"Toronto ON M4K 1N8",
    "addr:postcode":"m4k 1n8",
    "iso:country":"CA",
    "sg:city":"Toronto",
    "sg:classifiers":[
        {
            "category":"Personal",
            "type":"Services"
        }
    ],
    "sg:phone":"+1 416 465 7594",
    "sg:postcode":"M4K 1N8",
    "sg:province":"ON",
    "sg:tags":[
        "therapist",
        "massage"
    ],
    "wof:name":"Chester Avenue Massage Therapy",
    "wof:placetype":"venue"
},
  "geometry": {"coordinates":[-79.3526916504,43.6774482727],"type":"Point"}
}