{
  "type": "Feature",
  "properties": {
    "addr:full":"869 Cote D'Abraham Quebec QC G1R 1A4",
    "addr:housenumber":"869",
    "addr:postcode":"g1r 1a4",
    "addr:street":"Cote D'Abraham",
    "iso:country":"CA",
    "sg:address":"869 Cote D'Abraham",
    "sg:city":"Quebec",
    "sg:classifiers":[
        {
            "category":"Restaurant",
            "type":"Food & Drink"
        }
    ],
    "sg:phone":"+1 418 524 0572",
    "sg:postcode":"G1R 1A4",
    "sg:province":"QC",
    "wof:name":"Restaurant Thang Long",
    "wof:placetype":"venue"
},
  "geometry": {"coordinates":[-71.2890167236,46.8064956665],"type":"Point"}
}