{
  "type": "Feature",
  "properties": {
    "addr:full":"5395 Ch DE LA Cote-Saint-Luc Montreal QC H3X 2C3",
    "addr:housenumber":"5395",
    "addr:postcode":"h3x 2c3",
    "addr:street":"Ch De La Cote-Saint-Luc",
    "iso:country":"CA",
    "sg:address":"5395 Ch DE LA Cote-Saint-Luc",
    "sg:city":"Montreal",
    "sg:classifiers":[
        {
            "category":"Building & Trades",
            "subcategory":"Construction",
            "type":"Services"
        }
    ],
    "sg:phone":"+1 514 484 7973",
    "sg:postcode":"H3X 2C3",
    "sg:province":"QC",
    "sg:tags":[
        "excavating",
        "contractor"
    ],
    "wof:name":"Excavations Royal Enr",
    "wof:placetype":"venue"
},
  "geometry": {"coordinates":[-73.62408447270001,45.4796524048],"type":"Point"}
}