{
  "type": "Feature",
  "properties": {
    "addr:full":"Calgary AB T2S 1R9",
    "addr:postcode":"t2s 1r9",
    "iso:country":"CA",
    "sg:city":"Calgary",
    "sg:classifiers":[
        {
            "category":"Professional",
            "subcategory":"Advertising",
            "type":"Services"
        }
    ],
    "sg:phone":"+1 403 228 9526",
    "sg:postcode":"T2S 1R9",
    "sg:province":"AB",
    "sg:tags":[
        "counselor",
        "graphic",
        "designer"
    ],
    "wof:name":"Tandem Marketing Design",
    "wof:placetype":"venue"
},
  "geometry": {"coordinates":[-114.068389893,51.0368347168],"type":"Point"}
}