{
  "type": "Feature",
  "properties": {
    "iso:country":"CA",
    "sg:address":"2605 Westgate Cres",
    "sg:city":"Brights Grove",
    "sg:classifiers":[
        {
            "category":"Building & Trades",
            "subcategory":"Construction",
            "type":"Services"
        }
    ],
    "sg:phone":"+1 519 869 2686",
    "sg:postcode":"N0N 1C0",
    "sg:province":"ON",
    "sg:tags":[
        "general",
        "contractor"
    ],
    "wof:name":"Pez Nelvis Drywall",
    "wof:placetype":"venue"
},
  "geometry": {"coordinates":[-82.2588272095,43.031578064],"type":"Point"}
}