{
  "type": "Feature",
  "properties": {
    "addr:full":"13260 108 Ave Surrey BC V3T 2J6",
    "addr:housenumber":"13260",
    "addr:postcode":"v3t 2j6",
    "addr:street":"108 Ave",
    "iso:country":"CA",
    "sg:address":"13260 108 Ave",
    "sg:city":"Surrey",
    "sg:classifiers":[
        {
            "category":"Organizations",
            "subcategory":"Religious Organization",
            "type":"Services"
        }
    ],
    "sg:phone":"+1 604 951 8651",
    "sg:postcode":"V3T 2J6",
    "sg:province":"BC",
    "sg:tags":[
        "church"
    ],
    "wof:name":"Lighthouse Baptist Church",
    "wof:placetype":"venue"
},
  "geometry": {"coordinates":[-122.854644775,49.1988182068],"type":"Point"}
}