{
  "type": "Feature",
  "properties": {
    "addr:full":"98 Queen St W Brampton ON L6X 1A4",
    "addr:housenumber":"98",
    "addr:postcode":"l6x 1a4",
    "addr:street":"Queen St W",
    "iso:country":"CA",
    "sg:address":"98 Queen St W",
    "sg:city":"Brampton",
    "sg:classifiers":[
        {
            "category":"Banks & Credit Unions",
            "subcategory":"Investment Brokerage",
            "type":"Services"
        }
    ],
    "sg:phone":"+1 905 595 1414",
    "sg:postcode":"L6X 1A4",
    "sg:province":"ON",
    "sg:tags":[
        "consultant",
        "planning",
        "financial",
        "advisory"
    ],
    "wof:name":"Investment Planning Counsel",
    "wof:placetype":"venue"
},
  "geometry": {"coordinates":[-79.761864,43.684155],"type":"Point"}
}