{
  "type": "Feature",
  "properties": {
    "addr:full":"Oshawa ON L1H 3V8",
    "addr:postcode":"l1h 3v8",
    "iso:country":"CA",
    "sg:city":"Oshawa",
    "sg:classifiers":[
        {
            "category":"Home & Garden",
            "subcategory":"Home Furnishings",
            "type":"Retail Goods"
        }
    ],
    "sg:phone":"+1 905 434 3878",
    "sg:postcode":"L1H 3V8",
    "sg:province":"ON",
    "sg:tags":[
        "fireplace"
    ],
    "wof:name":"Fire Brass & Patio House Inc",
    "wof:placetype":"venue"
},
  "geometry": {"coordinates":[-78.830544,43.878448],"type":"Point"}
}