{
  "type": "Feature",
  "properties": {
    "addr:full":"Grand Forks BC V0H 1H0",
    "addr:postcode":"v0h 1h0",
    "iso:country":"CA",
    "sg:city":"Grand Forks",
    "sg:classifiers":[
        {
            "category":"Home & Garden",
            "subcategory":"Carpets & Floor Coverings",
            "type":"Retail Goods"
        }
    ],
    "sg:phone":"+1 250 442 2517",
    "sg:postcode":"V0H 1H0",
    "sg:province":"BC",
    "sg:tags":[
        "dealer",
        "rug"
    ],
    "wof:name":"Gordon Wall Floor Coverings",
    "wof:placetype":"venue"
},
  "geometry": {"coordinates":[-118.437995911,49.0311317444],"type":"Point"}
}