{
  "type": "Feature",
  "properties": {
    "iso:country":"CA",
    "sg:city":"Lougheed",
    "sg:classifiers":[
        {
            "category":"Food & Beverages",
            "subcategory":"Groceries & Convenience Stores",
            "type":"Retail Goods"
        }
    ],
    "sg:phone":"+1 780 386 3739",
    "sg:postcode":"T0B 2V0",
    "sg:province":"AB",
    "sg:tags":[
        "grocer"
    ],
    "wof:name":"Lougheed Food Town",
    "wof:placetype":"venue"
},
  "geometry": {"coordinates":[-111.54434204099999,52.744846344],"type":"Point"}
}