{
  "type": "Feature",
  "properties": {
    "iso:country":"CA",
    "sg:address":"3506 1Re Rue",
    "sg:city":"Saint-Hubert",
    "sg:classifiers":[
        {
            "category":"Professional",
            "subcategory":"Management & Consulting",
            "type":"Services"
        }
    ],
    "sg:phone":"+1 450 443 3030",
    "sg:postcode":"J3Y 8Y5",
    "sg:province":"QC",
    "sg:tags":[
        "construction",
        "general",
        "contractor"
    ],
    "wof:name":"Constructions Brault & Fils",
    "wof:placetype":"venue"
},
  "geometry": {"coordinates":[-73.393143,45.475273],"type":"Point"}
}