{
  "type": "Feature",
  "properties": {
    "addr:full":"485 Boul St-Pierre O Caraquet NB E1W 1A3",
    "addr:housenumber":"485",
    "addr:postcode":"e1w 1a3",
    "addr:street":"Boul St-Pierre O",
    "iso:country":"CA",
    "sg:address":"485 Boul St-Pierre O",
    "sg:city":"Caraquet",
    "sg:classifiers":[
        {
            "category":"Retail",
            "subcategory":"Auto Repair",
            "type":"Services"
        }
    ],
    "sg:phone":"+1 506 727 3366",
    "sg:postcode":"E1W 1A3",
    "sg:province":"NB",
    "sg:tags":[
        "repairing",
        "automobile"
    ],
    "wof:name":"Garage Bertrand Lanteigne",
    "wof:placetype":"venue"
},
  "geometry": {"coordinates":[-64.9970169067,47.7741508484],"type":"Point"}
}