{
  "type": "Feature",
  "properties": {
    "addr:full":"Oakville ON L6H 5V1",
    "addr:postcode":"l6h 5v1",
    "iso:country":"CA",
    "sg:city":"Oakville",
    "sg:classifiers":[
        {
            "category":"Manufacturing",
            "subcategory":"Petroleum Products",
            "type":"Manufacturing & Wholesale Goods"
        }
    ],
    "sg:phone":"+1 905 829 4826",
    "sg:postcode":"L6H 5V1",
    "sg:province":"ON",
    "sg:tags":[
        "lubricant"
    ],
    "wof:name":"Metalon Products",
    "wof:placetype":"venue"
},
  "geometry": {"coordinates":[-79.67334700000001,43.509209],"type":"Point"}
}