{
  "type": "Feature",
  "properties": {
    "iso:country":"CA",
    "sg:address":"2792 Norland Ave",
    "sg:city":"Burnaby",
    "sg:classifiers":[
        {
            "category":"Building & Trades",
            "subcategory":"Construction",
            "type":"Services"
        }
    ],
    "sg:phone":"+1 604 299 7969",
    "sg:postcode":"V5B 3A6",
    "sg:province":"BC",
    "sg:tags":[
        "steel",
        "erectors"
    ],
    "wof:name":"Kwh Constructors Corp",
    "wof:placetype":"venue"
},
  "geometry": {"coordinates":[-122.98135376,49.2593536377],"type":"Point"}
}