{
  "type": "Feature",
  "properties": {
    "iso:country":"CA",
    "sg:address":"2475 139 Rte",
    "sg:city":"Saint-Nicephore",
    "sg:classifiers":[
        {
            "category":"Manufacturing",
            "subcategory":"Metals",
            "type":"Manufacturing & Wholesale Goods"
        }
    ],
    "sg:phone":"+1 819 472 5248",
    "sg:postcode":"J2A 1Z1",
    "sg:province":"QC",
    "sg:tags":[
        "galvanizing"
    ],
    "wof:name":"Chrome Drummond Inc",
    "wof:placetype":"venue"
},
  "geometry": {"coordinates":[-72.4263916016,45.8238487244],"type":"Point"}
}