{
  "type": "Feature",
  "properties": {
    "addr:full":"570 Parliament St Toronto ON M4X 1P8",
    "addr:housenumber":"570",
    "addr:postcode":"m4x 1p8",
    "addr:street":"Parliament St",
    "iso:country":"CA",
    "sg:address":"570 Parliament St",
    "sg:city":"Toronto",
    "sg:classifiers":[
        {
            "category":"Health Services",
            "subcategory":"Doctor",
            "type":"Services"
        }
    ],
    "sg:phone":"+1 416 927 7600",
    "sg:postcode":"M4X 1P8",
    "sg:province":"ON",
    "sg:tags":[
        "dentist"
    ],
    "wof:name":"St Jamestown Dental Ctr",
    "wof:placetype":"venue"
},
  "geometry": {"coordinates":[-79.36948394780001,43.6675071716],"type":"Point"}
}