{
  "type": "Feature",
  "properties": {
    "addr:full":"4335 Hastings St Burnaby BC V5C 2J7",
    "addr:housenumber":"4335",
    "addr:postcode":"v5c 2j7",
    "addr:street":"Hastings St",
    "iso:country":"CA",
    "sg:address":"4335 Hastings St",
    "sg:city":"Burnaby",
    "sg:classifiers":[
        {
            "category":"Personal",
            "subcategory":"Barber",
            "type":"Services"
        }
    ],
    "sg:phone":"+1 604 677 9234",
    "sg:postcode":"V5C 2J7",
    "sg:province":"BC",
    "wof:name":"Alfredo Barber Shop",
    "wof:placetype":"venue"
},
  "geometry": {"coordinates":[-123.007583618,49.281162262],"type":"Point"}
}