{
  "type": "Feature",
  "properties": {
    "addr:full":"Brampton ON L6T 4Z5",
    "addr:postcode":"l6t 4z5",
    "iso:country":"CA",
    "sg:city":"Brampton",
    "sg:classifiers":[
        {
            "category":"Building & Trades",
            "subcategory":"Construction",
            "type":"Services"
        }
    ],
    "sg:phone":"+1 905 453 9729",
    "sg:postcode":"L6T 4Z5",
    "sg:province":"ON",
    "sg:tags":[
        "general",
        "contractor"
    ],
    "wof:name":"Dema Woodwork Industries Ltd",
    "wof:placetype":"venue"
},
  "geometry": {"coordinates":[-79.6985549927,43.6908493042],"type":"Point"}
}