{
  "type": "Feature",
  "properties": {
    "iso:country":"CA",
    "sg:address":"194 Rue Vaillancourt",
    "sg:city":"Saint-Jerome",
    "sg:classifiers":[
        {
            "category":"Autos & Motor Vehicles",
            "subcategory":"Automobile Sales",
            "type":"Retail Goods"
        }
    ],
    "sg:phone":"+1 450 431 2775",
    "sg:postcode":"J7Z 1G6",
    "sg:province":"QC",
    "sg:tags":[
        "dealer",
        "classic"
    ],
    "wof:name":"Auto Performance Pr",
    "wof:placetype":"venue"
},
  "geometry": {"coordinates":[-74.0048294067,45.789440155],"type":"Point"}
}