{
  "type": "Feature",
  "properties": {
    "addr:full":"70 Mcleod Ave # 109 Spruce Grove AB T7X 3C7",
    "addr:housenumber":"70",
    "addr:postcode":"t7x 3c7",
    "addr:street":"Mcleod Ave # 109",
    "iso:country":"CA",
    "sg:address":"70 Mcleod Ave # 109",
    "sg:city":"Spruce Grove",
    "sg:classifiers":[
        {
            "category":"Restaurant",
            "type":"Food & Drink"
        }
    ],
    "sg:phone":"+1 780 962 6090",
    "sg:postcode":"T7X 3C7",
    "sg:province":"AB",
    "sg:tags":[
        "caterer"
    ],
    "wof:name":"Grandma Lee's",
    "wof:placetype":"venue"
},
  "geometry": {"coordinates":[-113.913757324,53.5429916382],"type":"Point"}
}