{
  "type": "Feature",
  "properties": {
    "addr:full":"885 Lipton St Winnipeg MB R3E 2L4",
    "addr:housenumber":"885",
    "addr:postcode":"r3e 2l4",
    "addr:street":"Lipton St",
    "iso:country":"CA",
    "sg:address":"885 Lipton St",
    "sg:city":"Winnipeg",
    "sg:classifiers":[
        {
            "category":"Food & Beverages",
            "subcategory":"Groceries & Convenience Stores",
            "type":"Retail Goods"
        }
    ],
    "sg:phone":"+1 204 774 3144",
    "sg:postcode":"R3E 2L4",
    "sg:province":"MB",
    "sg:tags":[
        "grocer"
    ],
    "wof:name":"West-End Grocery",
    "wof:placetype":"venue"
},
  "geometry": {"coordinates":[-97.172203,49.902092],"type":"Point"}
}