{
  "type": "Feature",
  "properties": {
    "addr:full":"8550 Oakwood Dr RR 2 Niagara Falls ON L2E 6S5",
    "addr:housenumber":"8550",
    "addr:postcode":"l2e 6s5",
    "addr:street":"Oakwood Dr Rr 2",
    "iso:country":"CA",
    "sg:address":"8550 Oakwood Dr RR 2",
    "sg:city":"Niagara Falls",
    "sg:classifiers":[
        {
            "category":"Building & Trades",
            "subcategory":"Construction",
            "type":"Services"
        }
    ],
    "sg:phone":"+1 905 354 2519",
    "sg:postcode":"L2E 6S5",
    "sg:province":"ON",
    "sg:tags":[
        "excavating",
        "contractor"
    ],
    "wof:name":"Montgomery Brothers Constr",
    "wof:placetype":"venue"
},
  "geometry": {"coordinates":[-79.12162780760001,43.0559921265],"type":"Point"}
}