{
  "type": "Feature",
  "properties": {
    "addr:full":"809 High St W Moose Jaw SK S6H 6L7",
    "addr:housenumber":"809",
    "addr:postcode":"s6h 6l7",
    "addr:street":"High St W",
    "iso:country":"CA",
    "sg:address":"809 High St W",
    "sg:city":"Moose Jaw",
    "sg:classifiers":[
        {
            "category":"Manufacturing",
            "subcategory":"Metals",
            "type":"Manufacturing & Wholesale Goods"
        }
    ],
    "sg:phone":"+1 306 693 5244",
    "sg:postcode":"S6H 6L7",
    "sg:province":"SK",
    "sg:tags":[
        "steel"
    ],
    "wof:name":"Five Star Steel",
    "wof:placetype":"venue"
},
  "geometry": {"coordinates":[-105.55490112299999,50.3913993835],"type":"Point"}
}