{
  "type": "Feature",
  "properties": {
    "addr:full":"Saint-Hyacinthe QC J2S 4Z5",
    "addr:postcode":"j2s 4z5",
    "iso:country":"CA",
    "sg:city":"Saint-Hyacinthe",
    "sg:classifiers":[
        {
            "category":"Shopping",
            "subcategory":"Shoes",
            "type":"Retail Goods"
        }
    ],
    "sg:phone":"+1 450 261 8642",
    "sg:postcode":"J2S 4Z5",
    "sg:province":"QC",
    "wof:name":"Naturalizer",
    "wof:placetype":"venue"
},
  "geometry": {"coordinates":[-72.967308,45.636738],"type":"Point"}
}