{
  "type": "Feature",
  "properties": {
    "addr:full":"North York ON M3N 2Z4",
    "addr:postcode":"m3n 2z4",
    "iso:country":"CA",
    "sg:city":"North York",
    "sg:classifiers":[
        {
            "category":"Home & Garden",
            "subcategory":"Household Appliances",
            "type":"Retail Goods"
        }
    ],
    "sg:phone":"+1 416 743 4181",
    "sg:postcode":"M3N 2Z4",
    "sg:province":"ON",
    "wof:name":"Accord Appliance Svc Ctr",
    "wof:placetype":"venue"
},
  "geometry": {"coordinates":[-79.5240325928,43.7546653748],"type":"Point"}
}