{
  "type": "Feature",
  "properties": {
    "iso:country":"CA",
    "sg:address":"28 Main St",
    "sg:city":"Shellbrook",
    "sg:classifiers":[
        {
            "category":"Food & Beverages",
            "subcategory":"Groceries & Convenience Stores",
            "type":"Retail Goods"
        }
    ],
    "sg:phone":"+1 306 747 3623",
    "sg:postcode":"S0J 2E0",
    "sg:province":"SK",
    "sg:tags":[
        "grocer"
    ],
    "wof:name":"Bigway Foods",
    "wof:placetype":"venue"
},
  "geometry": {"coordinates":[-106.388313294,53.2205848694],"type":"Point"}
}