{
  "type": "Feature",
  "properties": {
    "addr:full":"300 Manning Cross NW Edmonton AB T5A 5A1",
    "addr:housenumber":"300",
    "addr:postcode":"t5a 5a1",
    "addr:street":"Manning Cross Nw",
    "iso:country":"CA",
    "sg:address":"300 Manning Cross NW",
    "sg:city":"Edmonton",
    "sg:classifiers":[
        {
            "category":"Restaurant",
            "type":"Food & Drink"
        }
    ],
    "sg:phone":"+1 780 413 8806",
    "sg:postcode":"T5A 5A1",
    "sg:province":"AB",
    "wof:name":"Joey's Only Seafood Restaurant",
    "wof:placetype":"venue"
},
  "geometry": {"coordinates":[-113.421021,53.600044],"type":"Point"}
}