{
  "type": "Feature",
  "properties": {
    "addr:full":"107 Dawes Rd East York ON M4C 5B7",
    "addr:housenumber":"107",
    "addr:postcode":"m4c 5b7",
    "addr:street":"Dawes Rd",
    "iso:country":"CA",
    "sg:address":"107 Dawes Rd",
    "sg:city":"East York",
    "sg:classifiers":[
        {
            "category":"Organizations",
            "subcategory":"Religious Organization",
            "type":"Services"
        }
    ],
    "sg:phone":"+1 416 694 2095",
    "sg:postcode":"M4C 5B7",
    "sg:province":"ON",
    "sg:tags":[
        "church"
    ],
    "wof:name":"Dentonia Park United Church",
    "wof:placetype":"venue"
},
  "geometry": {"coordinates":[-79.296921,43.691967],"type":"Point"}
}