{
  "type": "Feature",
  "properties": {
    "iso:country":"CA",
    "sg:address":"89 Bowes St",
    "sg:city":"Parry Sound",
    "sg:classifiers":[
        {
            "category":"Retail",
            "subcategory":"Funeral Services",
            "type":"Services"
        }
    ],
    "sg:phone":"+1 705 746 4664",
    "sg:postcode":"P2A 2L8",
    "sg:province":"ON",
    "sg:tags":[
        "director",
        "plan"
    ],
    "wof:name":"Torrance Funeral Home & Chapel",
    "wof:placetype":"venue"
},
  "geometry": {"coordinates":[-80.017349,45.342575],"type":"Point"}
}