{
  "type": "Feature",
  "properties": {
    "iso:country":"CA",
    "sg:address":"90 Billy Bishop Way",
    "sg:city":"North York",
    "sg:classifiers":[
        {
            "category":"Building & Trades",
            "subcategory":"Construction",
            "type":"Services"
        }
    ],
    "sg:phone":"+1 416 373 6001",
    "sg:postcode":"M3K 2C8",
    "sg:province":"ON",
    "sg:tags":[
        "hardware",
        "home",
        "improvement"
    ],
    "wof:name":"Home Depot",
    "wof:placetype":"venue"
},
  "geometry": {"coordinates":[-79.4537200928,43.7301368713],"type":"Point"}
}