{
  "type": "Feature",
  "properties": {
    "addr:full":"4278 Jesse Thompson Rd Stouffville ON L4A 7X5",
    "addr:housenumber":"4278",
    "addr:postcode":"l4a 7x5",
    "addr:street":"Jesse Thompson Rd",
    "iso:country":"CA",
    "sg:address":"4278 Jesse Thompson Rd",
    "sg:city":"Stouffville",
    "sg:classifiers":[
        {
            "category":"Wholesale",
            "subcategory":"Plants",
            "type":"Manufacturing & Wholesale Goods"
        }
    ],
    "sg:phone":"+1 905 642 5453",
    "sg:postcode":"L4A 7X5",
    "sg:province":"ON",
    "wof:name":"Strait's Tropical Interiors",
    "wof:placetype":"venue"
},
  "geometry": {"coordinates":[-79.327507,44.025326],"type":"Point"}
}