{
  "type": "Feature",
  "properties": {
    "addr:full":"67 Main St Thedford ON N0M 2N0",
    "addr:housenumber":"67",
    "addr:postcode":"n0m 2n0",
    "addr:street":"Main St",
    "iso:country":"CA",
    "sg:address":"67 Main St",
    "sg:city":"Thedford",
    "sg:classifiers":[
        {
            "category":"Insurance",
            "subcategory":"Insurance Agent",
            "type":"Services"
        }
    ],
    "sg:phone":"+1 519 296 5593",
    "sg:postcode":"N0M 2N0",
    "sg:province":"ON",
    "wof:name":"Mac Lachlan Insurance Brokers",
    "wof:placetype":"venue"
},
  "geometry": {"coordinates":[-81.8558502197,43.1634788513],"type":"Point"}
}