{
  "type": "Feature",
  "properties": {
    "addr:full":"1718 Argyle St Halifax NS B3J 2B6",
    "addr:housenumber":"1718",
    "addr:postcode":"ns b3j 2b6",
    "addr:street":"Argyle St",
    "iso:country":"CA",
    "sg:address":"1718 Argyle St",
    "sg:city":"Halifax",
    "sg:classifiers":[
        {
            "category":"Government",
            "subcategory":"Office",
            "type":"Public Place"
        }
    ],
    "sg:phone":"+1 902 420 8800",
    "sg:postcode":"B3J 2B6",
    "sg:province":"NS",
    "wof:name":"Nova Scotia Resources Ltd",
    "wof:placetype":"venue"
},
  "geometry": {"coordinates":[-63.575104,44.647278],"type":"Point"}
}