{
  "type": "Feature",
  "properties": {
    "addr:full":"10741 Av Racette Montreal-Nord QC H1G 5H5",
    "addr:postcode":"h1g 5h5",
    "addr:street":"Av Racette",
    "iso:country":"CA",
    "sg:address":"10741 Av Racette",
    "sg:city":"Montreal-Nord",
    "sg:classifiers":[
        {
            "category":"Manufacturing",
            "subcategory":"Food",
            "type":"Manufacturing & Wholesale Goods"
        }
    ],
    "sg:phone":"+1 514 327 8990",
    "sg:postcode":"H1G 5H5",
    "sg:province":"QC",
    "sg:tags":[
        "olive",
        "oil"
    ],
    "wof:name":"Symbio Import Export Inc",
    "wof:placetype":"venue"
},
  "geometry": {"coordinates":[-73.622643,45.596684],"type":"Point"}
}