{
  "type": "Feature",
  "properties": {
    "addr:full":"75 Milburn Rd Hamilton ON L8E 3A3",
    "addr:housenumber":"75",
    "addr:postcode":"l8e 3a3",
    "addr:street":"Milburn Rd",
    "iso:country":"CA",
    "sg:address":"75 Milburn Rd",
    "sg:city":"Hamilton",
    "sg:classifiers":[
        {
            "category":"Wholesale",
            "subcategory":"Construction Materials",
            "type":"Manufacturing & Wholesale Goods"
        }
    ],
    "sg:phone":"+1 905 560 5520",
    "sg:postcode":"L8E 3A3",
    "sg:province":"ON",
    "sg:tags":[
        "tile"
    ],
    "wof:name":"Olympia Tile Intl Inc",
    "wof:placetype":"venue"
},
  "geometry": {"coordinates":[-79.741592,43.234951],"type":"Point"}
}