{
  "type": "Feature",
  "properties": {
    "iso:country":"CA",
    "sg:address":"560 Commissioners St",
    "sg:city":"Toronto",
    "sg:classifiers":[
        {
            "category":"Home & Garden",
            "subcategory":"Building Materials",
            "type":"Retail Goods"
        }
    ],
    "sg:phone":"+1 416 461 8122",
    "sg:postcode":"M4M 1A7",
    "sg:province":"ON",
    "sg:tags":[
        "roofing"
    ],
    "wof:name":"Can Roof Corp Inc",
    "wof:placetype":"venue"
},
  "geometry": {"coordinates":[-79.3325500488,43.6540679932],"type":"Point"}
}