{
  "type": "Feature",
  "properties": {
    "addr:full":"469 Talbot St St Thomas ON N5P 1C1",
    "addr:housenumber":"469",
    "addr:postcode":"n5p 1c1",
    "addr:street":"Talbot St",
    "iso:country":"CA",
    "sg:address":"469 Talbot St",
    "sg:city":"St Thomas",
    "sg:classifiers":[
        {
            "category":"Personal",
            "subcategory":"Beauty Salon",
            "type":"Services"
        }
    ],
    "sg:phone":"+1 519 637 1336",
    "sg:postcode":"N5P 1C1",
    "sg:province":"ON",
    "wof:name":"Hair Ideas",
    "wof:placetype":"venue"
},
  "geometry": {"coordinates":[-81.19510699999999,42.779118],"type":"Point"}
}