{
  "type": "Feature",
  "properties": {
    "addr:full":"20400 Hwy 522 Britt ON P0G 1A0",
    "addr:housenumber":"20400",
    "addr:postcode":"p0g 1a0",
    "addr:street":"Hwy 522",
    "iso:country":"CA",
    "sg:address":"20400 Hwy 522",
    "sg:city":"Britt",
    "sg:classifiers":[
        {
            "category":"Government",
            "subcategory":"Office",
            "type":"Public Place"
        }
    ],
    "sg:phone":"+1 705 383 2369",
    "sg:postcode":"P0G 1A0",
    "sg:province":"ON",
    "sg:tags":[
        "provincial",
        "parks"
    ],
    "wof:name":"Grundy Lake Provincial Park",
    "wof:placetype":"venue"
},
  "geometry": {"coordinates":[-80.55501599999999,45.776779],"type":"Point"}
}