{
  "type": "Feature",
  "properties": {
    "addr:full":"9800 Boul Cavendish # 500 Saint-Laurent QC H4M 2V9",
    "addr:housenumber":"9800",
    "addr:postcode":"h4m 2v9",
    "addr:street":"Boul Cavendish # 500",
    "iso:country":"CA",
    "sg:address":"9800 Boul Cavendish # 500",
    "sg:city":"Saint-Laurent",
    "sg:classifiers":[
        {
            "category":"Wholesale",
            "subcategory":"Electrical",
            "type":"Manufacturing & Wholesale Goods"
        }
    ],
    "sg:phone":"+1 514 745 5500",
    "sg:postcode":"H4M 2V9",
    "sg:province":"QC",
    "sg:tags":[
        "equipment",
        "electronic",
        "supply"
    ],
    "wof:name":"Eicon Networks Corp",
    "wof:placetype":"venue"
},
  "geometry": {"coordinates":[-73.699562,45.49559],"type":"Point"}
}