{
  "type": "Feature",
  "properties": {
    "addr:full":"1268 10E Rang Wickham QC J0C 1S0",
    "addr:housenumber":"1268",
    "addr:postcode":"j0c 1s0",
    "addr:street":"10E Rang",
    "iso:country":"CA",
    "sg:address":"1268 10E Rang",
    "sg:city":"Wickham",
    "sg:classifiers":[
        {
            "category":"Retail",
            "subcategory":"Repair Shop",
            "type":"Services"
        }
    ],
    "sg:phone":"+1 819 398 6600",
    "sg:postcode":"J0C 1S0",
    "sg:province":"QC",
    "sg:tags":[
        "sandblasting"
    ],
    "wof:name":"Sablage Au Jet & Peinture MB",
    "wof:placetype":"venue"
},
  "geometry": {"coordinates":[-72.55484800000001,45.787903],"type":"Point"}
}