{
  "type": "Feature",
  "properties": {
    "addr:full":"5906 45 St Leduc AB T9E 7B4",
    "addr:housenumber":"5906",
    "addr:postcode":"t9e 7b4",
    "addr:street":"45 St",
    "iso:country":"CA",
    "sg:address":"5906 45 St",
    "sg:city":"Leduc",
    "sg:classifiers":[
        {
            "category":"Retail",
            "subcategory":"Auto Repair",
            "type":"Services"
        }
    ],
    "sg:phone":"+1 780 986 0979",
    "sg:postcode":"T9E 7B4",
    "sg:province":"AB",
    "sg:tags":[
        "repairing",
        "automobile",
        "muffler",
        "system",
        "exhaust"
    ],
    "wof:name":"Tim's Muffler Inc",
    "wof:placetype":"venue"
},
  "geometry": {"coordinates":[-113.54239699999999,53.272923],"type":"Point"}
}