{
  "type": "Feature",
  "properties": {
    "iso:country":"CA",
    "sg:address":"233 Delrex Blvd",
    "sg:city":"Georgetown",
    "sg:classifiers":[
        {
            "category":"Education",
            "subcategory":"School",
            "type":"Public Place"
        }
    ],
    "sg:phone":"+1 905 877 6976",
    "sg:postcode":"L7G 4G1",
    "sg:province":"ON",
    "wof:name":"Centennial School",
    "wof:placetype":"venue"
},
  "geometry": {"coordinates":[-79.8983306885,43.6430358887],"type":"Point"}
}