{
  "type": "Feature",
  "properties": {
    "addr:full":"885 Des Pionniers Ch Remigny QC J0Z 3H0",
    "addr:housenumber":"885",
    "addr:postcode":"j0z 3h0",
    "addr:street":"Des Pionniers Ch Remigny",
    "iso:country":"CA",
    "sg:address":"885 Des Pionniers Ch",
    "sg:city":"Remigny",
    "sg:classifiers":[
        {
            "category":"Insurance",
            "subcategory":"Insurance Agent",
            "type":"Services"
        }
    ],
    "sg:phone":"+1 819 761 5201",
    "sg:postcode":"J0Z 3H0",
    "sg:province":"QC",
    "wof:name":"Tremblay, Paul Henri",
    "wof:placetype":"venue"
},
  "geometry": {"coordinates":[-79.19858600000001,47.793282],"type":"Point"}
}