{
  "type": "Feature",
  "properties": {
    "addr:full":"Vancouver BC V6A 3X1",
    "addr:postcode":"v6a 3x1",
    "iso:country":"CA",
    "sg:city":"Vancouver",
    "sg:classifiers":[
        {
            "category":"Real Estate",
            "subcategory":"Real Estate Agent",
            "type":"Services"
        }
    ],
    "sg:phone":"+1 604 253 4720",
    "sg:postcode":"V6A 3X1",
    "sg:province":"BC",
    "sg:tags":[
        "authorities",
        "housing"
    ],
    "wof:name":"First United Church Social",
    "wof:placetype":"venue"
},
  "geometry": {"coordinates":[-123.09310913100001,49.2815322876],"type":"Point"}
}