{
  "type": "Feature",
  "properties": {
    "addr:full":"190 Baker St Sudbury ON P3C 2G1",
    "addr:housenumber":"190",
    "addr:postcode":"p3c 2g1",
    "addr:street":"Baker St",
    "iso:country":"CA",
    "sg:address":"190 Baker St",
    "sg:city":"Sudbury",
    "sg:classifiers":[
        {
            "category":"Organizations",
            "subcategory":"Religious Organization",
            "type":"Services"
        }
    ],
    "sg:phone":"+1 705 673 2403",
    "sg:postcode":"P3C 2G1",
    "sg:province":"ON",
    "sg:tags":[
        "church"
    ],
    "wof:name":"Ukrainian Greek Orthodox Chr",
    "wof:placetype":"venue"
},
  "geometry": {"coordinates":[-81.0028457642,46.4978218079],"type":"Point"}
}