{
  "type": "Feature",
  "properties": {
    "iso:country":"CA",
    "sg:address":"600 Av Belvedere",
    "sg:city":"Quebec",
    "sg:classifiers":[
        {
            "category":"Professional",
            "subcategory":"Art Services",
            "type":"Services"
        }
    ],
    "sg:phone":"+1 418 688 7052",
    "sg:postcode":"G1S 3E5",
    "sg:province":"QC",
    "sg:tags":[
        "graphic",
        "designer"
    ],
    "wof:name":"Productions Sadefil Inc",
    "wof:placetype":"venue"
},
  "geometry": {"coordinates":[-71.24448394780001,46.80128479],"type":"Point"}
}