{
  "type": "Feature",
  "properties": {
    "addr:full":"8 Ch Jenness Chelsea QC J9B 2L9",
    "addr:housenumber":"8",
    "addr:postcode":"qc j9b 2l9",
    "addr:street":"Ch Jenness",
    "iso:country":"CA",
    "sg:address":"8 Ch Jenness",
    "sg:city":"Chelsea",
    "sg:classifiers":[
        {
            "category":"Professional",
            "subcategory":"Art Services",
            "type":"Services"
        }
    ],
    "sg:phone":"+1 819 827 9062",
    "sg:postcode":"J9B 2L9",
    "sg:province":"QC",
    "sg:tags":[
        "photographer"
    ],
    "wof:name":"Marshall-Maruska Aerial Images",
    "wof:placetype":"venue"
},
  "geometry": {"coordinates":[-75.87167358400001,45.5834732056],"type":"Point"}
}