{
  "type": "Feature",
  "properties": {
    "iso:country":"CA",
    "sg:address":"148 George St",
    "sg:city":"Arthur",
    "sg:classifiers":[
        {
            "category":"Health Services",
            "subcategory":"Chiropractor",
            "type":"Services"
        }
    ],
    "sg:phone":"+1 519 848 2451",
    "sg:postcode":"N0G 1A0",
    "sg:province":"ON",
    "wof:name":"Gohn, David W DC",
    "wof:placetype":"venue"
},
  "geometry": {"coordinates":[-80.5367889404,43.8315658569],"type":"Point"}
}