{
  "type": "Feature",
  "properties": {
    "addr:full":"53 Goulet St Winnipeg MB R2H 0R5",
    "addr:housenumber":"53",
    "addr:postcode":"r2h 0r5",
    "addr:street":"Goulet St",
    "iso:country":"CA",
    "sg:address":"53 Goulet St",
    "sg:city":"Winnipeg",
    "sg:classifiers":[
        {
            "category":"Professional",
            "subcategory":"Accounting & Tax Preparation",
            "type":"Services"
        }
    ],
    "sg:phone":"+1 204 949 4110",
    "sg:postcode":"R2H 0R5",
    "sg:province":"MB",
    "sg:tags":[
        "return",
        "filing"
    ],
    "wof:name":"H & R Block Canada Inc",
    "wof:placetype":"venue"
},
  "geometry": {"coordinates":[-97.125869751,49.8816490173],"type":"Point"}
}