{
  "type": "Feature",
  "properties": {
    "addr:full":"Saint-Charles-DE-Bellechasse QC G0R 2T0",
    "addr:postcode":"g0r 2t0",
    "iso:country":"CA",
    "sg:city":"Saint-Charles-DE-Bellechasse",
    "sg:classifiers":[
        {
            "category":"Retail",
            "subcategory":"Auto Repair",
            "type":"Services"
        }
    ],
    "sg:phone":"+1 418 887 6922",
    "sg:postcode":"G0R 2T0",
    "sg:province":"QC",
    "sg:tags":[
        "repairing",
        "automobile"
    ],
    "wof:name":"Garage Bernard Cote",
    "wof:placetype":"venue"
},
  "geometry": {"coordinates":[-70.937164,46.780674],"type":"Point"}
}