{
  "type": "Feature",
  "properties": {
    "iso:country":"CA",
    "sg:address":"72199 Regional Road 27",
    "sg:city":"Fenwick",
    "sg:classifiers":[
        {
            "category":"Retail",
            "subcategory":"Animal Services",
            "type":"Services"
        }
    ],
    "sg:phone":"+1 905 386 6993",
    "sg:postcode":"L0S 1C0",
    "sg:province":"ON",
    "sg:tags":[
        "pet",
        "breeder",
        "dog"
    ],
    "wof:name":"Committed To Canine",
    "wof:placetype":"venue"
},
  "geometry": {"coordinates":[-79.3574523926,43.0261611938],"type":"Point"}
}