{
  "type": "Feature",
  "properties": {
    "addr:full":"5799 Yonge St #1107 North York ON M2M 3V3",
    "addr:housenumber":"5799",
    "addr:postcode":"m2m 3v3",
    "addr:street":"Yonge St # 1107",
    "iso:country":"CA",
    "sg:address":"5799 Yonge St #1107",
    "sg:city":"North York",
    "sg:classifiers":[
        {
            "category":"Health Services",
            "subcategory":"Doctor",
            "type":"Services"
        }
    ],
    "sg:phone":"+1 416 222 0880",
    "sg:postcode":"M2M 3V3",
    "sg:province":"ON",
    "sg:tags":[
        "physician",
        "surgeon"
    ],
    "wof:name":"Ravikovich, F MD",
    "wof:placetype":"venue"
},
  "geometry": {"coordinates":[-79.4164733887,43.784324646],"type":"Point"}
}