{
  "type": "Feature",
  "properties": {
    "iso:country":"CA",
    "sg:address":"61 Rue Sainte-Catherine E",
    "sg:city":"Montreal",
    "sg:classifiers":[
        {
            "category":"Shopping",
            "subcategory":"Clothing, Apparel, & Fashions",
            "type":"Retail Goods"
        }
    ],
    "sg:phone":"+1 514 284 1118",
    "sg:postcode":"H2X 1K5",
    "sg:province":"QC",
    "sg:tags":[
        "accessory"
    ],
    "wof:name":"Super Style",
    "wof:placetype":"venue"
},
  "geometry": {"coordinates":[-73.5633010864,45.5107078552],"type":"Point"}
}