{
  "type": "Feature",
  "properties": {
    "addr:full":"Vancouver BC V6J 1S4",
    "addr:postcode":"v6j 1s4",
    "iso:country":"CA",
    "sg:city":"Vancouver",
    "sg:classifiers":[
        {
            "category":"Health Services",
            "subcategory":"Clinic",
            "type":"Services"
        }
    ],
    "sg:phone":"+1 604 714 5550",
    "sg:postcode":"V6J 1S4",
    "sg:province":"BC",
    "sg:tags":[
        "agency",
        "welfare"
    ],
    "wof:name":"Arthritis Society BC & Yukon",
    "wof:placetype":"venue"
},
  "geometry": {"coordinates":[-123.142044067,49.2655677795],"type":"Point"}
}