{
  "type": "Feature",
  "properties": {
    "addr:full":"Warwick QC J0A 1M0",
    "addr:postcode":"j0a 1m0",
    "iso:country":"CA",
    "sg:city":"Warwick",
    "sg:classifiers":[
        {
            "category":"Recreation",
            "type":"Entertainment"
        }
    ],
    "sg:phone":"+1 819 358 5051",
    "sg:postcode":"J0A 1M0",
    "sg:province":"QC",
    "sg:tags":[
        "pool",
        "swimming"
    ],
    "wof:name":"Centre Multi-Sports Desjardins",
    "wof:placetype":"venue"
},
  "geometry": {"coordinates":[-71.996689,45.949211],"type":"Point"}
}