{
  "type": "Feature",
  "properties": {
    "addr:full":"400 Towerlane Dr Airdrie AB T4B 2K7",
    "addr:housenumber":"400",
    "addr:postcode":"t4b 2k7",
    "addr:street":"Towerlane Dr",
    "iso:country":"CA",
    "sg:address":"400 Towerlane Dr",
    "sg:city":"Airdrie",
    "sg:classifiers":[
        {
            "category":"Real Estate",
            "subcategory":"Real Estate Operator",
            "type":"Services"
        }
    ],
    "sg:phone":"+1 403 912 3401",
    "sg:postcode":"T4B 2K7",
    "sg:province":"AB",
    "sg:tags":[
        "apartment"
    ],
    "wof:name":"Boardwalk Realty Ltd",
    "wof:placetype":"venue"
},
  "geometry": {"coordinates":[-114.017776,51.289635],"type":"Point"}
}