{
  "type": "Feature",
  "properties": {
    "iso:country":"CA",
    "sg:address":"19980 Bathurst St",
    "sg:city":"Holland Landing",
    "sg:classifiers":[
        {
            "category":"Building & Trades",
            "subcategory":"Landscaping Services",
            "type":"Services"
        }
    ],
    "sg:phone":"+1 905 836 7612",
    "sg:postcode":"L9N 1P5",
    "sg:province":"ON",
    "sg:tags":[
        "lawn",
        "contractor",
        "landscape",
        "maintenance",
        "grounds"
    ],
    "wof:name":"Star Gardening Ltd",
    "wof:placetype":"venue"
},
  "geometry": {"coordinates":[-79.4923629761,44.1046333313],"type":"Point"}
}