{
  "type": "Feature",
  "properties": {
    "addr:full":"219 Paris Rd Brantford ON N3R 1J2",
    "addr:housenumber":"219",
    "addr:postcode":"n3r 1j2",
    "addr:street":"Paris Rd",
    "iso:country":"CA",
    "sg:address":"219 Paris Rd",
    "sg:city":"Brantford",
    "sg:classifiers":[
        {
            "category":"Retail",
            "subcategory":"Auto Repair",
            "type":"Services"
        }
    ],
    "sg:phone":"+1 519 759 8375",
    "sg:postcode":"N3R 1J2",
    "sg:province":"ON",
    "sg:tags":[
        "wrecker"
    ],
    "wof:name":"Jarret Towing",
    "wof:placetype":"venue"
},
  "geometry": {"coordinates":[-80.297211,43.167896],"type":"Point"}
}