{
  "type": "Feature",
  "properties": {
    "iso:country":"CA",
    "sg:address":"6363 Rte Transcanadienne",
    "sg:city":"Saint-Laurent",
    "sg:classifiers":[
        {
            "category":"Wholesale",
            "subcategory":"Office Equipment",
            "type":"Manufacturing & Wholesale Goods"
        }
    ],
    "sg:phone":"+1 514 747 7728",
    "sg:postcode":"H4T 1Z9",
    "sg:province":"QC",
    "sg:tags":[
        "scanning",
        "code",
        "bar"
    ],
    "wof:name":"Symbol Technologies Canada Inc",
    "wof:placetype":"venue"
},
  "geometry": {"coordinates":[-73.687843,45.49511],"type":"Point"}
}