{
  "type": "Feature",
  "properties": {
    "iso:country":"CA",
    "sg:address":"1399 Buffalo Pl",
    "sg:city":"Winnipeg",
    "sg:classifiers":[
        {
            "category":"Professional",
            "subcategory":"Computer Services",
            "type":"Services"
        }
    ],
    "sg:phone":"+1 204 474 0982",
    "sg:postcode":"R3T 1L6",
    "sg:province":"MB",
    "sg:tags":[
        "consultant"
    ],
    "wof:name":"Automated Design Systems Ltd",
    "wof:placetype":"venue"
},
  "geometry": {"coordinates":[-97.168518,49.837303],"type":"Point"}
}