{
  "type": "Feature",
  "properties": {
    "addr:full":"37 Wells St Guelph ON N1E 6B7",
    "addr:housenumber":"37",
    "addr:postcode":"n1e 6b7",
    "addr:street":"Wells St",
    "iso:country":"CA",
    "sg:address":"37 Wells St",
    "sg:city":"Guelph",
    "sg:classifiers":[
        {
            "category":"Freight",
            "type":"Transportation"
        }
    ],
    "sg:phone":"+1 519 763 0243",
    "sg:postcode":"N1E 6B7",
    "sg:province":"ON",
    "sg:tags":[
        "mover"
    ],
    "wof:name":"Larry's Moving & Storage",
    "wof:placetype":"venue"
},
  "geometry": {"coordinates":[-80.22207641599999,43.5543746948],"type":"Point"}
}