{
  "type": "Feature",
  "properties": {
    "addr:full":"50 Norfinch Dr North York ON M3N 1X1",
    "addr:housenumber":"50",
    "addr:postcode":"m3n 1x1",
    "addr:street":"Norfinch Dr",
    "iso:country":"CA",
    "sg:address":"50 Norfinch Dr",
    "sg:city":"North York",
    "sg:classifiers":[
        {
            "category":"Travel",
            "subcategory":"Hotels & Motels",
            "type":"Entertainment"
        }
    ],
    "sg:phone":"+1 416 663 9500",
    "sg:postcode":"M3N 1X1",
    "sg:province":"ON",
    "wof:name":"Travelodge Toronto North",
    "wof:placetype":"venue"
},
  "geometry": {"coordinates":[-79.5280838013,43.7572898865],"type":"Point"}
}