{
  "type": "Feature",
  "properties": {
    "addr:full":"Nominingue QC J0W 1R0",
    "addr:postcode":"j0w 1r0",
    "iso:country":"CA",
    "sg:city":"Nominingue",
    "sg:classifiers":[
        {
            "category":"Sports & Exercise",
            "subcategory":"Golf",
            "type":"Entertainment"
        }
    ],
    "sg:phone":"+1 819 278 3836",
    "sg:postcode":"J0W 1R0",
    "sg:province":"QC",
    "sg:tags":[
        "course"
    ],
    "wof:name":"Hotel Du Golf Nominigue Inc",
    "wof:placetype":"venue"
},
  "geometry": {"coordinates":[-75.0287857056,46.3909759521],"type":"Point"}
}