{
  "type": "Feature",
  "properties": {
    "addr:full":"620 Camelot Dr Sudbury ON P3B 3N1",
    "addr:housenumber":"620",
    "addr:postcode":"p3b 3n1",
    "addr:street":"Camelot Dr",
    "iso:country":"CA",
    "sg:address":"620 Camelot Dr",
    "sg:city":"Sudbury",
    "sg:classifiers":[
        {
            "category":"Organizations",
            "subcategory":"Religious Organization",
            "type":"Services"
        }
    ],
    "sg:phone":"+1 705 560 4947",
    "sg:postcode":"P3B 3N1",
    "sg:province":"ON",
    "sg:tags":[
        "church"
    ],
    "wof:name":"Salvation Army",
    "wof:placetype":"venue"
},
  "geometry": {"coordinates":[-80.934082,46.500637],"type":"Point"}
}