{
  "type": "Feature",
  "properties": {
    "iso:country":"CA",
    "sg:city":"Montreal",
    "sg:classifiers":[
        {
            "category":"Wholesale",
            "subcategory":"Furniture",
            "type":"Manufacturing & Wholesale Goods"
        }
    ],
    "sg:phone":"+1 514 528 8687",
    "sg:postcode":"H2H 2S5",
    "sg:province":"QC",
    "sg:tags":[
        "equipment",
        "school"
    ],
    "wof:name":"Ecole Quebecoise Du Meuble",
    "wof:placetype":"venue"
},
  "geometry": {"coordinates":[-73.58223,45.539967],"type":"Point"}
}