{
  "type": "Feature",
  "properties": {
    "addr:full":"251 Davenport Rd Toronto ON M5R 1J9",
    "addr:housenumber":"251",
    "addr:postcode":"m5r 1j9",
    "addr:street":"Davenport Rd",
    "iso:country":"CA",
    "sg:address":"251 Davenport Rd",
    "sg:city":"Toronto",
    "sg:classifiers":[
        {
            "category":"Health Services",
            "subcategory":"Health Practitioner",
            "type":"Services"
        }
    ],
    "sg:phone":"+1 416 923 5557",
    "sg:postcode":"M5R 1J9",
    "sg:province":"ON",
    "sg:tags":[
        "physiotherapist"
    ],
    "wof:name":"Body Works",
    "wof:placetype":"venue"
},
  "geometry": {"coordinates":[-79.39774300000001,43.674362],"type":"Point"}
}