{
  "type": "Feature",
  "properties": {
    "addr:full":"2406 11 Ave S Lethbridge AB T1K 0K8",
    "addr:housenumber":"2406",
    "addr:postcode":"t1k 0k8",
    "addr:street":"11 Ave S",
    "iso:country":"CA",
    "sg:address":"2406 11 Ave S",
    "sg:city":"Lethbridge",
    "sg:classifiers":[
        {
            "category":"Organizations",
            "subcategory":"Religious Organization",
            "type":"Services"
        }
    ],
    "sg:phone":"+1 403 328 3445",
    "sg:postcode":"T1K 0K8",
    "sg:province":"AB",
    "sg:tags":[
        "church"
    ],
    "wof:name":"Lutheran Church of the Good",
    "wof:placetype":"venue"
},
  "geometry": {"coordinates":[-112.807174683,49.6817741394],"type":"Point"}
}