{
  "type": "Feature",
  "properties": {
    "iso:country":"CA",
    "sg:address":"156 Alice St",
    "sg:city":"Brantford",
    "sg:classifiers":[
        {
            "category":"Retail",
            "subcategory":"Laundry & Dry Cleaning",
            "type":"Services"
        }
    ],
    "sg:phone":"+1 519 752 5846",
    "sg:postcode":"N3S 5B8",
    "sg:province":"ON",
    "sg:tags":[
        "cleaners",
        "rug",
        "carpet"
    ],
    "wof:name":"Perfection Plus",
    "wof:placetype":"venue"
},
  "geometry": {"coordinates":[-80.250977,43.151344],"type":"Point"}
}