{
  "type": "Feature",
  "properties": {
    "addr:full":"West Vancouver BC V7T 2W4",
    "addr:postcode":"v7t 2w4",
    "iso:country":"CA",
    "sg:city":"West Vancouver",
    "sg:classifiers":[
        {
            "category":"Shopping",
            "subcategory":"Clothing, Apparel, & Fashions",
            "type":"Retail Goods"
        }
    ],
    "sg:phone":"+1 604 922 4111",
    "sg:postcode":"V7T 2W4",
    "sg:province":"BC",
    "sg:tags":[
        "infant",
        "wear"
    ],
    "wof:name":"Please Mum",
    "wof:placetype":"venue"
},
  "geometry": {"coordinates":[-123.140137,49.324551],"type":"Point"}
}