{
  "type": "Feature",
  "properties": {
    "addr:full":"Etobicoke ON M9B 1L1",
    "addr:postcode":"m9b 1l1",
    "iso:country":"CA",
    "sg:city":"Etobicoke",
    "sg:classifiers":[
        {
            "category":"Personal",
            "subcategory":"Beauty Salon",
            "type":"Services"
        }
    ],
    "sg:phone":"+1 416 233 4406",
    "sg:postcode":"M9B 1L1",
    "sg:province":"ON",
    "wof:name":"Carmin Unisex Hair Salon",
    "wof:placetype":"venue"
},
  "geometry": {"coordinates":[-79.539238,43.641087],"type":"Point"}
}