{
  "type": "Feature",
  "properties": {
    "addr:full":"1060 Rue Westmount Ayer's Cliff QC J0B 1C0",
    "addr:housenumber":"1060",
    "addr:postcode":"j0b 1c0",
    "addr:street":"Rue Westmount",
    "iso:country":"CA",
    "sg:address":"1060 Rue Westmount",
    "sg:city":"Ayer's Cliff",
    "sg:classifiers":[
        {
            "category":"Sports & Exercise",
            "subcategory":"Bowling",
            "type":"Entertainment"
        }
    ],
    "sg:phone":"+1 819 838 4121",
    "sg:postcode":"J0B 1C0",
    "sg:province":"QC",
    "sg:tags":[
        "center"
    ],
    "wof:name":"Salon DE Quilles Massawippi",
    "wof:placetype":"venue"
},
  "geometry": {"coordinates":[-72.037842,45.172253],"type":"Point"}
}