{
  "type": "Feature",
  "properties": {
    "addr:full":"1152 Boul Saint-Laurent Montreal QC H2X 2S5",
    "addr:housenumber":"1152",
    "addr:postcode":"h2x 2s5",
    "addr:street":"Boul Saint-Laurent",
    "iso:country":"CA",
    "sg:address":"1152 Boul Saint-Laurent",
    "sg:city":"Montreal",
    "sg:classifiers":[
        {
            "category":"Shopping",
            "subcategory":"Photographic Equipment",
            "type":"Retail Goods"
        }
    ],
    "sg:phone":"+1 514 866 5545",
    "sg:postcode":"H2X 2S5",
    "sg:province":"QC",
    "sg:tags":[
        "supply"
    ],
    "wof:name":"Davidson Image & Son-Multi",
    "wof:placetype":"venue"
},
  "geometry": {"coordinates":[-73.5618591309,45.5088806152],"type":"Point"}
}