{
  "type": "Feature",
  "properties": {
    "addr:full":"Igloolik NU X0A 0L0",
    "addr:postcode":"x0a 0l0",
    "iso:country":"CA",
    "sg:city":"Igloolik",
    "sg:classifiers":[
        {
            "category":"Government",
            "subcategory":"Office",
            "type":"Public Place"
        }
    ],
    "sg:phone":"+1 867 934 2001",
    "sg:postcode":"X0A 0L0",
    "sg:province":"NU",
    "wof:name":"Nwt Public Works & Svc",
    "wof:placetype":"venue"
},
  "geometry": {"coordinates":[-81.7945327759,69.3772354126],"type":"Point"}
}