{
  "type": "Feature",
  "properties": {
    "addr:full":"2805 Hwy 2 E Bowmanville ON L1C 3K5",
    "addr:housenumber":"2805",
    "addr:postcode":"l1c 3k5",
    "addr:street":"Hwy 2 E",
    "iso:country":"CA",
    "sg:address":"2805 Hwy 2 E",
    "sg:city":"Bowmanville",
    "sg:classifiers":[
        {
            "category":"Organizations",
            "subcategory":"Religious Organization",
            "type":"Services"
        }
    ],
    "sg:phone":"+1 905 623 2192",
    "sg:postcode":"L1C 3K5",
    "sg:province":"ON",
    "sg:tags":[
        "church"
    ],
    "wof:name":"Maranatha Christian Reformed",
    "wof:placetype":"venue"
},
  "geometry": {"coordinates":[-78.6636428833,43.9120025635],"type":"Point"}
}