{
  "type": "Feature",
  "properties": {
    "iso:country":"CA",
    "sg:address":"550 Main St N",
    "sg:city":"Moose Jaw",
    "sg:classifiers":[
        {
            "category":"Health Services",
            "subcategory":"Doctor",
            "type":"Services"
        }
    ],
    "sg:phone":"+1 306 694 2082",
    "sg:postcode":"S6H 3K3",
    "sg:province":"SK",
    "sg:tags":[
        "physician",
        "surgeon"
    ],
    "wof:name":"Professional Medical Assoc",
    "wof:placetype":"venue"
},
  "geometry": {"coordinates":[-105.534988403,50.3948898315],"type":"Point"}
}