{
  "type": "Feature",
  "properties": {
    "addr:full":"Sutton QC J0E 2K0",
    "addr:postcode":"j0e 2k0",
    "iso:country":"CA",
    "sg:city":"Sutton",
    "sg:classifiers":[
        {
            "category":"Government",
            "subcategory":"Office",
            "type":"Public Place"
        }
    ],
    "sg:phone":"+1 450 538 2290",
    "sg:postcode":"J0E 2K0",
    "sg:province":"QC",
    "sg:tags":[
        "municipality"
    ],
    "wof:name":"Sutton Hotel DE Ville",
    "wof:placetype":"venue"
},
  "geometry": {"coordinates":[-72.61531100000001,45.106121],"type":"Point"}
}