{
  "type": "Feature",
  "properties": {
    "addr:full":"1706 Queen St W Toronto ON M6R 1B3",
    "addr:housenumber":"1706",
    "addr:postcode":"m6r 1b3",
    "addr:street":"Queen St W",
    "iso:country":"CA",
    "sg:address":"1706 Queen St W",
    "sg:city":"Toronto",
    "sg:classifiers":[
        {
            "category":"Home & Garden",
            "subcategory":"Hardware",
            "type":"Retail Goods"
        }
    ],
    "sg:phone":"+1 416 534 5301",
    "sg:postcode":"M6R 1B3",
    "sg:province":"ON",
    "wof:name":"Sunnyside Hardware & Paint",
    "wof:placetype":"venue"
},
  "geometry": {"coordinates":[-79.445198,43.639034],"type":"Point"}
}