{
  "type": "Feature",
  "properties": {
    "addr:full":"584 Willies Way Bowen Island BC V0N 1G0",
    "addr:housenumber":"584",
    "addr:postcode":"v0n 1g0",
    "addr:street":"Willies Way",
    "iso:country":"CA",
    "sg:address":"584 Willies Way",
    "sg:city":"Bowen Island",
    "sg:classifiers":[
        {
            "category":"Health Services",
            "subcategory":"Clinic",
            "type":"Services"
        }
    ],
    "sg:phone":"+1 604 947 2555",
    "sg:postcode":"V0N 1G0",
    "sg:province":"BC",
    "wof:name":"North American Medical Svc Inc",
    "wof:placetype":"venue"
},
  "geometry": {"coordinates":[-123.38415500000001,49.360878],"type":"Point"}
}