{
  "type": "Feature",
  "properties": {
    "addr:full":"100 City Centre Dr Mississauga ON L5B 2C9",
    "addr:housenumber":"100",
    "addr:postcode":"l5b 2c9",
    "addr:street":"City Centre Dr",
    "iso:country":"CA",
    "sg:address":"100 City Centre Dr",
    "sg:city":"Mississauga",
    "sg:classifiers":[
        {
            "category":"Personal",
            "subcategory":"Beauty Salon",
            "type":"Services"
        }
    ],
    "sg:phone":"+1 905 896 1907",
    "sg:postcode":"L5B 2C9",
    "sg:province":"ON",
    "sg:tags":[
        "electrolysis"
    ],
    "wof:name":"Aesthetics By Tantastic",
    "wof:placetype":"venue"
},
  "geometry": {"coordinates":[-79.6395111084,43.5920944214],"type":"Point"}
}