{
  "type": "Feature",
  "properties": {
    "iso:country":"CA",
    "sg:city":"Sainte-Agathe-Des-Monts",
    "sg:classifiers":[
        {
            "category":"Shopping",
            "subcategory":"Shoes",
            "type":"Retail Goods"
        }
    ],
    "sg:phone":"+1 819 326 8082",
    "sg:postcode":"J8C 1J8",
    "sg:province":"QC",
    "wof:name":"Chaussures Yellow",
    "wof:placetype":"venue"
},
  "geometry": {"coordinates":[-74.284034729,46.0465545654],"type":"Point"}
}