{
  "type": "Feature",
  "properties": {
    "addr:full":"91 Mcinnis Cres Regina SK S4R 3E9",
    "addr:housenumber":"91",
    "addr:postcode":"s4r 3e9",
    "addr:street":"Mcinnis Cres",
    "iso:country":"CA",
    "sg:address":"91 Mcinnis Cres",
    "sg:city":"Regina",
    "sg:classifiers":[
        {
            "category":"Personal",
            "subcategory":"Beauty Salon",
            "type":"Services"
        }
    ],
    "sg:phone":"+1 306 924 1077",
    "sg:postcode":"S4R 3E9",
    "sg:province":"SK",
    "wof:name":"Marj's Beauty Salon",
    "wof:placetype":"venue"
},
  "geometry": {"coordinates":[-104.631515503,50.4834136963],"type":"Point"}
}