{
  "type": "Feature",
  "properties": {
    "iso:country":"CA",
    "sg:address":"135 Rue Notre Dame",
    "sg:city":"Oka",
    "sg:classifiers":[
        {
            "category":"Shopping",
            "subcategory":"Pharmacy",
            "type":"Retail Goods"
        }
    ],
    "sg:phone":"+1 450 479 8448",
    "sg:postcode":"J0N 1E0",
    "sg:province":"QC",
    "wof:name":"Pierre Belisle Pharmacy",
    "wof:placetype":"venue"
},
  "geometry": {"coordinates":[-74.087272644,45.4616127014],"type":"Point"}
}