{
  "type": "Feature",
  "properties": {
    "addr:full":"Napierville QC J0J 1L0",
    "addr:postcode":"j0j 1l0",
    "iso:country":"CA",
    "sg:city":"Napierville",
    "sg:classifiers":[
        {
            "category":"Government",
            "subcategory":"Office",
            "type":"Public Place"
        }
    ],
    "sg:phone":"+1 450 245 7551",
    "sg:postcode":"J0J 1L0",
    "sg:province":"QC",
    "sg:tags":[
        "village"
    ],
    "wof:name":"Napierville Station-Pompage",
    "wof:placetype":"venue"
},
  "geometry": {"coordinates":[-73.39632415769999,45.1941146851],"type":"Point"}
}