{
  "type": "Feature",
  "properties": {
    "addr:full":"289 Spadina Ave Toronto ON M5T 2E6",
    "addr:housenumber":"289",
    "addr:postcode":"m5t 2e6",
    "addr:street":"Spadina Ave",
    "iso:country":"CA",
    "sg:address":"289 Spadina Ave",
    "sg:city":"Toronto",
    "sg:classifiers":[
        {
            "category":"Personal",
            "subcategory":"Beauty Salon",
            "type":"Services"
        }
    ],
    "sg:phone":"+1 416 599 0828",
    "sg:postcode":"M5T 2E6",
    "sg:province":"ON",
    "wof:name":"Good Choice Hair Design",
    "wof:placetype":"venue"
},
  "geometry": {"coordinates":[-79.3978424072,43.6532096863],"type":"Point"}
}