{
  "type": "Feature",
  "properties": {
    "iso:country":"CA",
    "sg:address":"314 Conception Bay Hwy",
    "sg:city":"Bay Roberts",
    "sg:classifiers":[
        {
            "category":"Home & Garden",
            "subcategory":"Garden Supply",
            "type":"Retail Goods"
        }
    ],
    "sg:phone":"+1 709 786 7717",
    "sg:postcode":"A0A 1G0",
    "sg:province":"NL",
    "sg:tags":[
        "lawn",
        "mower",
        "terrain",
        "all",
        "vehicle"
    ],
    "wof:name":"Recreational Parts & Acces",
    "wof:placetype":"venue"
},
  "geometry": {"coordinates":[-53.2855644226,47.5738220215],"type":"Point"}
}