{
  "type": "Feature",
  "properties": {
    "addr:full":"Montreal-Nord QC H1G 1K9",
    "addr:postcode":"h1g 1k9",
    "iso:country":"CA",
    "sg:city":"Montreal-Nord",
    "sg:classifiers":[
        {
            "category":"Health Services",
            "subcategory":"Doctor",
            "type":"Services"
        }
    ],
    "sg:phone":"+1 514 325 7440",
    "sg:postcode":"H1G 1K9",
    "sg:province":"QC",
    "sg:tags":[
        "physician",
        "clinic",
        "surgeon"
    ],
    "wof:name":"Clinique Pediatrique Montreal",
    "wof:placetype":"venue"
},
  "geometry": {"coordinates":[-73.62808990480001,45.6180267334],"type":"Point"}
}