{
  "type": "Feature",
  "properties": {
    "iso:country":"CA",
    "sg:address":"10 Louisa St",
    "sg:city":"Orangeville",
    "sg:classifiers":[
        {
            "category":"Government",
            "subcategory":"Office",
            "type":"Public Place"
        }
    ],
    "sg:phone":"+1 519 941 5802",
    "sg:postcode":"L9W 3P9",
    "sg:province":"ON",
    "sg:tags":[
        "village"
    ],
    "wof:name":"Dufferin Provincial Div",
    "wof:placetype":"venue"
},
  "geometry": {"coordinates":[-80.102219,43.91935],"type":"Point"}
}