{
  "type": "Feature",
  "properties": {
    "addr:full":"20 Rue Monseigneur-Tessier O Rouyn-Noranda QC J9X 2S4",
    "addr:housenumber":"20",
    "addr:postcode":"j9x 2s4",
    "addr:street":"Rue Monseigneur-Tessier O",
    "iso:country":"CA",
    "sg:address":"20 Rue Monseigneur-Tessier O",
    "sg:city":"Rouyn-Noranda",
    "sg:classifiers":[
        {
            "category":"Organizations",
            "subcategory":"Professional Association",
            "type":"Services"
        }
    ],
    "sg:phone":"+1 819 762 1359",
    "sg:postcode":"J9X 2S4",
    "sg:province":"QC",
    "wof:name":"Canadian Legion Branch No 188",
    "wof:placetype":"venue"
},
  "geometry": {"coordinates":[-79.014511,48.237076],"type":"Point"}
}