{
  "type": "Feature",
  "properties": {
    "addr:full":"2436 Gideon Dr Delaware ON N0L 1E0",
    "addr:housenumber":"2436",
    "addr:postcode":"n0l 1e0",
    "addr:street":"Gideon Dr",
    "iso:country":"CA",
    "sg:address":"2436 Gideon Dr",
    "sg:city":"Delaware",
    "sg:classifiers":[
        {
            "category":"Education",
            "subcategory":"School",
            "type":"Public Place"
        }
    ],
    "sg:phone":"+1 519 652 5631",
    "sg:postcode":"N0L 1E0",
    "sg:province":"ON",
    "wof:name":"Our Lady of Lourdes School",
    "wof:placetype":"venue"
},
  "geometry": {"coordinates":[-81.427193,42.915722],"type":"Point"}
}