{
  "type": "Feature",
  "properties": {
    "addr:full":"1 Coad Rd Trenton ON K8V 5W6",
    "addr:housenumber":"1",
    "addr:postcode":"k8v 5w6",
    "addr:street":"Coad Rd",
    "iso:country":"CA",
    "sg:address":"1 Coad Rd",
    "sg:city":"Trenton",
    "sg:classifiers":[
        {
            "category":"Building & Trades",
            "subcategory":"Equipment Rental",
            "type":"Services"
        }
    ],
    "sg:phone":"+1 613 392 9278",
    "sg:postcode":"K8V 5W6",
    "sg:province":"ON",
    "sg:tags":[
        "yard",
        "contractor"
    ],
    "wof:name":"Battlefield Equipment Rentals",
    "wof:placetype":"venue"
},
  "geometry": {"coordinates":[-77.57630899999999,44.101139],"type":"Point"}
}