{
  "type": "Feature",
  "properties": {
    "addr:full":"211 Royal St Imperial SK S0G 2J0",
    "addr:housenumber":"211",
    "addr:postcode":"s0g 2j0",
    "addr:street":"Royal St",
    "iso:country":"CA",
    "sg:address":"211 Royal St",
    "sg:city":"Imperial",
    "sg:classifiers":[
        {
            "category":"Personal",
            "subcategory":"Beauty Salon",
            "type":"Services"
        }
    ],
    "sg:phone":"+1 306 963 2476",
    "sg:postcode":"S0G 2J0",
    "sg:province":"SK",
    "wof:name":"One on One Hair Studio",
    "wof:placetype":"venue"
},
  "geometry": {"coordinates":[-105.439575195,51.3461418152],"type":"Point"}
}