{
  "type": "Feature",
  "properties": {
    "addr:full":"205 10 St S Lethbridge AB T1J 2M5",
    "addr:housenumber":"205 10",
    "addr:postcode":"t1j 2m5",
    "addr:street":"St",
    "iso:country":"CA",
    "sg:address":"205 10 St S",
    "sg:city":"Lethbridge",
    "sg:classifiers":[
        {
            "category":"Autos & Motor Vehicles",
            "subcategory":"Auto Supplies",
            "type":"Retail Goods"
        }
    ],
    "sg:phone":"+1 403 327 8587",
    "sg:postcode":"T1J 2M5",
    "sg:province":"AB",
    "sg:tags":[
        "automobile",
        "parts"
    ],
    "wof:name":"Uap Napa Auto Parts",
    "wof:placetype":"venue"
},
  "geometry": {"coordinates":[-112.832314,49.697033],"type":"Point"}
}