{
  "type": "Feature",
  "properties": {
    "addr:full":"6741 Columbus Rd Mississauga ON L5T 2G9",
    "addr:housenumber":"6741",
    "addr:postcode":"l5t 2g9",
    "addr:street":"Columbus Rd",
    "iso:country":"CA",
    "sg:address":"6741 Columbus Rd",
    "sg:city":"Mississauga",
    "sg:classifiers":[
        {
            "category":"Health Services",
            "subcategory":"Medical Lab",
            "type":"Services"
        }
    ],
    "sg:phone":"+1 905 564 2953",
    "sg:postcode":"L5T 2G9",
    "sg:province":"ON",
    "sg:tags":[
        "laboratory"
    ],
    "wof:name":"Kanti Labs Ltd",
    "wof:placetype":"venue"
},
  "geometry": {"coordinates":[-79.67231750489999,43.6672782898],"type":"Point"}
}