{
  "type": "Feature",
  "properties": {
    "iso:country":"CA",
    "sg:address":"565 Lorne St",
    "sg:city":"Sudbury",
    "sg:classifiers":[
        {
            "category":"Shopping",
            "type":"Retail Goods"
        }
    ],
    "sg:phone":"+1 705 675 7243",
    "sg:postcode":"P3C 4R3",
    "sg:province":"ON",
    "sg:tags":[
        "trophy",
        "medal",
        "award"
    ],
    "wof:name":"First Goal Trophies",
    "wof:placetype":"venue"
},
  "geometry": {"coordinates":[-81.01049,46.481033],"type":"Point"}
}