{
  "type": "Feature",
  "properties": {
    "iso:country":"CA",
    "sg:address":"4733 50 St",
    "sg:city":"St Paul",
    "sg:classifiers":[
        {
            "category":"Shopping",
            "subcategory":"Department Store",
            "type":"Retail Goods"
        }
    ],
    "sg:phone":"+1 780 645 6006",
    "sg:postcode":"T0A 3A4",
    "sg:province":"AB",
    "sg:tags":[
        "shop"
    ],
    "wof:name":"Liquidation World Inc",
    "wof:placetype":"venue"
},
  "geometry": {"coordinates":[-111.296936035,53.9887123108],"type":"Point"}
}