{
  "type": "Feature",
  "properties": {
    "addr:full":"24 Milford Ave North York ON M6M 2V8",
    "addr:housenumber":"24",
    "addr:postcode":"m6m 2v8",
    "addr:street":"Milford Ave",
    "iso:country":"CA",
    "sg:address":"24 Milford Ave",
    "sg:city":"North York",
    "sg:classifiers":[
        {
            "category":"Building & Trades",
            "subcategory":"Construction",
            "type":"Services"
        }
    ],
    "sg:phone":"+1 416 242 5502",
    "sg:postcode":"M6M 2V8",
    "sg:province":"ON",
    "sg:tags":[
        "home",
        "improvement",
        "furniture"
    ],
    "wof:name":"Carelli Custom Interiors",
    "wof:placetype":"venue"
},
  "geometry": {"coordinates":[-79.47584500000001,43.704872],"type":"Point"}
}