{
  "type": "Feature",
  "properties": {
    "addr:full":"672 Henry St Woodstock ON N4S 1Y3",
    "addr:housenumber":"672",
    "addr:postcode":"n4s 1y3",
    "addr:street":"Henry St",
    "iso:country":"CA",
    "sg:address":"672 Henry St",
    "sg:city":"Woodstock",
    "sg:classifiers":[
        {
            "category":"Retail",
            "subcategory":"Repair Shop",
            "type":"Services"
        }
    ],
    "sg:phone":"+1 519 421 1855",
    "sg:postcode":"N4S 1Y3",
    "sg:province":"ON",
    "sg:tags":[
        "tool",
        "parts"
    ],
    "wof:name":"Woodstock Power Tool Repair",
    "wof:placetype":"venue"
},
  "geometry": {"coordinates":[-80.747215271,43.1263923645],"type":"Point"}
}