{
  "type": "Feature",
  "properties": {
    "addr:full":"1885 Boul Lionel-Bertrand Boisbriand QC J7H 1N8",
    "addr:housenumber":"1885",
    "addr:postcode":"j7h 1n8",
    "addr:street":"Boul Lionel-Bertrand",
    "iso:country":"CA",
    "sg:address":"1885 Boul Lionel-Bertrand",
    "sg:city":"Boisbriand",
    "sg:classifiers":[
        {
            "category":"Manufacturing",
            "subcategory":"Rubber & Plastics",
            "type":"Manufacturing & Wholesale Goods"
        }
    ],
    "sg:phone":"+1 450 434 2744",
    "sg:postcode":"J7H 1N8",
    "sg:province":"QC",
    "sg:tags":[
        "product"
    ],
    "wof:name":"Elasto Proxy",
    "wof:placetype":"venue"
},
  "geometry": {"coordinates":[-73.855667,45.609619],"type":"Point"}
}