{
  "type": "Feature",
  "properties": {
    "addr:full":"15811 26 Ave Surrey BC V3S 0B7",
    "addr:housenumber":"15811",
    "addr:postcode":"v3s 0b7",
    "addr:street":"26 Ave",
    "iso:country":"CA",
    "sg:address":"15811 26 Ave",
    "sg:city":"Surrey",
    "sg:classifiers":[
        {
            "category":"Home & Garden",
            "subcategory":"Garden Supply",
            "type":"Retail Goods"
        }
    ],
    "sg:phone":"+1 604 536 6553",
    "sg:postcode":"V3S 0B7",
    "sg:province":"BC",
    "sg:tags":[
        "equipment",
        "irrigation",
        "system"
    ],
    "wof:name":"Challoner Irrigation",
    "wof:placetype":"venue"
},
  "geometry": {"coordinates":[-122.783607,49.049351],"type":"Point"}
}