{
  "type": "Feature",
  "properties": {
    "iso:country":"CA",
    "sg:address":"16320 95 Ave NW",
    "sg:city":"Edmonton",
    "sg:classifiers":[
        {
            "category":"Restaurant",
            "type":"Food & Drink"
        }
    ],
    "sg:phone":"+1 780 484 6160",
    "sg:postcode":"T5P 0A9",
    "sg:province":"AB",
    "sg:tags":[
        "parlor",
        "ice",
        "cream"
    ],
    "wof:name":"Pa Peterson Ice Cream",
    "wof:placetype":"venue"
},
  "geometry": {"coordinates":[-113.603088379,53.5317459106],"type":"Point"}
}