{
  "type": "Feature",
  "properties": {
    "iso:country":"CA",
    "sg:address":"393 Boul Des Laurentides",
    "sg:city":"Saint-Jerome",
    "sg:classifiers":[
        {
            "category":"Retail",
            "subcategory":"Veterinary Services",
            "type":"Services"
        }
    ],
    "sg:phone":"+1 450 565 5665",
    "sg:postcode":"J7Z 4L9",
    "sg:province":"QC",
    "sg:tags":[
        "veterinarian"
    ],
    "wof:name":"Hopital Veterinaire St-Antoine",
    "wof:placetype":"venue"
},
  "geometry": {"coordinates":[-73.9944992065,45.7639312744],"type":"Point"}
}