{
  "type": "Feature",
  "properties": {
    "addr:full":"Brampton ON L6T 2T9",
    "addr:postcode":"l6t 2t9",
    "iso:country":"CA",
    "sg:city":"Brampton",
    "sg:classifiers":[
        {
            "category":"Social Services",
            "type":"Services"
        }
    ],
    "sg:phone":"+1 905 790 8482",
    "sg:postcode":"L6T 2T9",
    "sg:province":"ON",
    "sg:tags":[
        "organization",
        "welfare"
    ],
    "wof:name":"Brampton Multicultural Ctr",
    "wof:placetype":"venue"
},
  "geometry": {"coordinates":[-79.7180480957,43.7178764343],"type":"Point"}
}