{
  "type": "Feature",
  "properties": {
    "addr:full":"821 Queen St Kincardine ON N2Z 2Y2",
    "addr:housenumber":"821",
    "addr:postcode":"n2z 2y2",
    "addr:street":"Queen St",
    "iso:country":"CA",
    "sg:address":"821 Queen St",
    "sg:city":"Kincardine",
    "sg:classifiers":[
        {
            "category":"Real Estate",
            "subcategory":"Real Estate Agent",
            "type":"Services"
        }
    ],
    "sg:phone":"+1 519 396 3396",
    "sg:postcode":"N2Z 2Y2",
    "sg:province":"ON",
    "wof:name":"Royal Le Page",
    "wof:placetype":"venue"
},
  "geometry": {"coordinates":[-81.634727478,44.177406311],"type":"Point"}
}