{
  "type": "Feature",
  "properties": {
    "addr:full":"630 Boul Rene-Levesque O Montreal QC H3B 1S6",
    "addr:housenumber":"630",
    "addr:postcode":"h3b 1s6",
    "addr:street":"Boul Rene-Levesque O",
    "iso:country":"CA",
    "sg:address":"630 Boul Rene-Levesque O",
    "sg:city":"Montreal",
    "sg:classifiers":[
        {
            "category":"Government",
            "subcategory":"Office",
            "type":"Public Place"
        }
    ],
    "sg:phone":"+1 514 861 6340",
    "sg:postcode":"H3B 1S6",
    "sg:province":"QC",
    "sg:tags":[
        "federal",
        "affairs"
    ],
    "wof:name":"Commercial Office of Egyptian",
    "wof:placetype":"venue"
},
  "geometry": {"coordinates":[-73.566711,45.502335],"type":"Point"}
}