{
  "type": "Feature",
  "properties": {
    "addr:full":"Quebec QC G1S 1C1",
    "addr:postcode":"g1s 1c1",
    "iso:country":"CA",
    "sg:city":"Quebec",
    "sg:classifiers":[
        {
            "category":"Professional",
            "subcategory":"Lawyer & Legal Services",
            "type":"Services"
        }
    ],
    "sg:phone":"+1 418 688 5000",
    "sg:postcode":"G1S 1C1",
    "sg:province":"QC",
    "sg:tags":[
        "attorney"
    ],
    "wof:name":"Lavery DE Billy",
    "wof:placetype":"venue"
},
  "geometry": {"coordinates":[-71.339996,46.749989],"type":"Point"}
}