{
  "type": "Feature",
  "properties": {
    "addr:full":"2228 54th Ave E Vancouver BC V5P 1Y7",
    "addr:housenumber":"2228",
    "addr:postcode":"v5p 1y7",
    "addr:street":"54Th Ave E",
    "iso:country":"CA",
    "sg:address":"2228 54th Ave E",
    "sg:city":"Vancouver",
    "sg:classifiers":[
        {
            "category":"Professional",
            "subcategory":"Business Services",
            "type":"Services"
        }
    ],
    "sg:phone":"+1 604 322 8754",
    "sg:postcode":"V5P 1Y7",
    "sg:province":"BC",
    "sg:tags":[
        "notary"
    ],
    "wof:name":"Gupta, Sudershan",
    "wof:placetype":"venue"
},
  "geometry": {"coordinates":[-123.06193500000001,49.220123],"type":"Point"}
}