{
  "type": "Feature",
  "properties": {
    "addr:full":"395 Rue Notre-Dame O Montreal QC H2Y 1V2",
    "addr:housenumber":"395",
    "addr:postcode":"h2y 1v2",
    "addr:street":"Rue Notre-Dame O",
    "iso:country":"CA",
    "sg:address":"395 Rue Notre-Dame O",
    "sg:city":"Montreal",
    "sg:classifiers":[
        {
            "category":"Shopping",
            "subcategory":"Clothing, Apparel, & Fashions",
            "type":"Retail Goods"
        }
    ],
    "sg:phone":"+1 514 287 8979",
    "sg:postcode":"H2Y 1V2",
    "sg:province":"QC",
    "wof:name":"Boutique Annie",
    "wof:placetype":"venue"
},
  "geometry": {"coordinates":[-73.552803,45.510052],"type":"Point"}
}