{
  "type": "Feature",
  "properties": {
    "addr:full":"Brampton ON L6S 5N9",
    "addr:postcode":"l6s 5n9",
    "iso:country":"CA",
    "sg:city":"Brampton",
    "sg:classifiers":[
        {
            "category":"Manufacturing",
            "subcategory":"Printing",
            "type":"Manufacturing & Wholesale Goods"
        }
    ],
    "sg:phone":"+1 905 792 9595",
    "sg:postcode":"L6S 5N9",
    "sg:province":"ON",
    "sg:tags":[
        "screen"
    ],
    "wof:name":"Hammerhead Creations",
    "wof:placetype":"venue"
},
  "geometry": {"coordinates":[-79.71133399999999,43.758102],"type":"Point"}
}