{
  "type": "Feature",
  "properties": {
    "addr:full":"430 Main St Melville SK S0A 2P0",
    "addr:housenumber":"430",
    "addr:postcode":"s0a 2p0",
    "addr:street":"Main St",
    "iso:country":"CA",
    "sg:address":"430 Main St",
    "sg:city":"Melville",
    "sg:classifiers":[
        {
            "category":"Government",
            "subcategory":"Office",
            "type":"Public Place"
        }
    ],
    "sg:phone":"+1 306 728 6840",
    "sg:postcode":"S0A 2P0",
    "sg:province":"SK",
    "sg:tags":[
        "village"
    ],
    "wof:name":"Melville City Manager",
    "wof:placetype":"venue"
},
  "geometry": {"coordinates":[-102.804665,50.929844],"type":"Point"}
}