{
  "type": "Feature",
  "properties": {
    "addr:full":"Abbotsford BC V2S 2C7",
    "addr:postcode":"v2s 2c7",
    "iso:country":"CA",
    "sg:city":"Abbotsford",
    "sg:classifiers":[
        {
            "category":"Cinema",
            "subcategory":"Movie Rental",
            "type":"Entertainment"
        }
    ],
    "sg:phone":"+1 604 852 5863",
    "sg:postcode":"V2S 2C7",
    "sg:province":"BC",
    "sg:tags":[
        "leasing",
        "video",
        "disc",
        "tape"
    ],
    "wof:name":"Rogers Video",
    "wof:placetype":"venue"
},
  "geometry": {"coordinates":[-122.267944,49.037434],"type":"Point"}
}