{
  "type": "Feature",
  "properties": {
    "addr:full":"2041 Hamilton St Regina SK S4P 2E2",
    "addr:housenumber":"2041",
    "addr:postcode":"s4p 2e2",
    "addr:street":"Hamilton St",
    "iso:country":"CA",
    "sg:address":"2041 Hamilton St",
    "sg:city":"Regina",
    "sg:classifiers":[
        {
            "category":"Government",
            "subcategory":"Office",
            "type":"Public Place"
        }
    ],
    "sg:phone":"+1 306 787 3340",
    "sg:postcode":"S4P 2E2",
    "sg:province":"SK",
    "wof:name":"Saskatchewan Transportation CO",
    "wof:placetype":"venue"
},
  "geometry": {"coordinates":[-104.609261,50.446438],"type":"Point"}
}