{
  "type": "Feature",
  "properties": {
    "iso:country":"CA",
    "sg:address":"1370 Ch Saint-Ignace",
    "sg:city":"Saint-Ignace",
    "sg:classifiers":[
        {
            "category":"Food & Beverages",
            "subcategory":"Groceries & Convenience Stores",
            "type":"Retail Goods"
        }
    ],
    "sg:phone":"+1 506 876 2083",
    "sg:postcode":"E4X 2J7",
    "sg:province":"NB",
    "sg:tags":[
        "grocer"
    ],
    "wof:name":"Tex Groceries",
    "wof:placetype":"venue"
},
  "geometry": {"coordinates":[-65.08093261720001,46.7005386353],"type":"Point"}
}