{
  "type": "Feature",
  "properties": {
    "addr:full":"Toronto ON M5T 2E6",
    "addr:postcode":"m5t 2e6",
    "iso:country":"CA",
    "sg:city":"Toronto",
    "sg:classifiers":[
        {
            "category":"Shopping",
            "subcategory":"Jewelry",
            "type":"Retail Goods"
        }
    ],
    "sg:phone":"+1 416 599 9719",
    "sg:postcode":"M5T 2E6",
    "sg:province":"ON",
    "sg:tags":[
        "jeweler"
    ],
    "wof:name":"Ngoc Chau Jewellery",
    "wof:placetype":"venue"
},
  "geometry": {"coordinates":[-79.397964,43.653515],"type":"Point"}
}