{
  "type": "Feature",
  "properties": {
    "iso:country":"CA",
    "sg:address":"1899 Algonquin Ave",
    "sg:city":"North Bay",
    "sg:classifiers":[
        {
            "category":"Shopping",
            "subcategory":"Department Store",
            "type":"Retail Goods"
        }
    ],
    "sg:phone":"+1 705 472 9400",
    "sg:postcode":"P1B 4Y8",
    "sg:province":"ON",
    "wof:name":"Zellers",
    "wof:placetype":"venue"
},
  "geometry": {"coordinates":[-79.46616400000001,46.332394],"type":"Point"}
}