{
  "type": "Feature",
  "properties": {
    "addr:full":"1227 Carmil Blvd Kingston ON K7M 5Z1",
    "addr:housenumber":"1227",
    "addr:postcode":"k7m 5z1",
    "addr:street":"Carmil Blvd",
    "iso:country":"CA",
    "sg:address":"1227 Carmil Blvd",
    "sg:city":"Kingston",
    "sg:classifiers":[
        {
            "category":"Professional",
            "subcategory":"Computer Services",
            "type":"Services"
        }
    ],
    "sg:phone":"+1 613 389 0969",
    "sg:postcode":"K7M 5Z1",
    "sg:province":"ON",
    "sg:tags":[
        "consultant"
    ],
    "wof:name":"Reid's Leading Edge Technology",
    "wof:placetype":"venue"
},
  "geometry": {"coordinates":[-76.60702499999999,44.24963],"type":"Point"}
}