{
  "type": "Feature",
  "properties": {
    "addr:full":"290 Sovereign Rd London ON N6M 1B3",
    "addr:housenumber":"290",
    "addr:postcode":"n6m 1b3",
    "addr:street":"Sovereign Rd",
    "iso:country":"CA",
    "sg:address":"290 Sovereign Rd",
    "sg:city":"London",
    "sg:classifiers":[
        {
            "category":"Wholesale",
            "subcategory":"Machinery & Supplies",
            "type":"Manufacturing & Wholesale Goods"
        }
    ],
    "sg:phone":"+1 519 659 2771",
    "sg:postcode":"N6M 1B3",
    "sg:province":"ON",
    "sg:tags":[
        "farm",
        "equipment"
    ],
    "wof:name":"Hardi Inc",
    "wof:placetype":"venue"
},
  "geometry": {"coordinates":[-81.1369857788,42.9878044128],"type":"Point"}
}