{
  "type": "Feature",
  "properties": {
    "addr:full":"127 Imperial St Toronto ON M5P 1C7",
    "addr:housenumber":"127",
    "addr:postcode":"m5p 1c7",
    "addr:street":"Imperial St",
    "iso:country":"CA",
    "sg:address":"127 Imperial St",
    "sg:city":"Toronto",
    "sg:classifiers":[
        {
            "category":"Wholesale",
            "subcategory":"Office Equipment",
            "type":"Manufacturing & Wholesale Goods"
        }
    ],
    "sg:phone":"+1 416 486 8000",
    "sg:postcode":"M5P 1C7",
    "sg:province":"ON",
    "sg:tags":[
        "machine",
        "duplicating",
        "copying"
    ],
    "wof:name":"Better Office Equipment Inc",
    "wof:placetype":"venue"
},
  "geometry": {"coordinates":[-79.401611,43.698666],"type":"Point"}
}