{
  "type": "Feature",
  "properties": {
    "iso:country":"CA",
    "sg:address":"1129 Queens Ave",
    "sg:city":"Brandon",
    "sg:classifiers":[
        {
            "category":"Government",
            "subcategory":"Office",
            "type":"Public Place"
        }
    ],
    "sg:phone":"+1 204 724 0896",
    "sg:postcode":"R7A 1L9",
    "sg:province":"MB",
    "wof:name":"Manitoba Booking/Reservations",
    "wof:placetype":"venue"
},
  "geometry": {"coordinates":[-99.9522476196,49.830329895],"type":"Point"}
}