{
  "type": "Feature",
  "properties": {
    "addr:full":"712 Fortalice Cres SE Calgary AB T2A 2E1",
    "addr:housenumber":"712",
    "addr:postcode":"t2a 2e1",
    "addr:street":"Fortalice Cres Se",
    "iso:country":"CA",
    "sg:address":"712 Fortalice Cres SE",
    "sg:city":"Calgary",
    "sg:classifiers":[
        {
            "category":"Education",
            "subcategory":"School",
            "type":"Public Place"
        }
    ],
    "sg:phone":"+1 403 248 3664",
    "sg:postcode":"T2A 2E1",
    "sg:province":"AB",
    "wof:name":"St John Bosco Private School",
    "wof:placetype":"venue"
},
  "geometry": {"coordinates":[-113.95966339100001,51.0465812683],"type":"Point"}
}