{
  "type": "Feature",
  "properties": {
    "iso:country":"CA",
    "sg:city":"Coquitlam",
    "sg:classifiers":[
        {
            "category":"Restaurant",
            "type":"Food & Drink"
        }
    ],
    "sg:phone":"+1 604 931 4494",
    "sg:postcode":"V3K 3P1",
    "sg:province":"BC",
    "sg:tags":[
        "delicatessen"
    ],
    "wof:name":"Mr B's Corner Store & Deli",
    "wof:placetype":"venue"
},
  "geometry": {"coordinates":[-122.865852356,49.2488441467],"type":"Point"}
}