{
  "type": "Feature",
  "properties": {
    "addr:full":"Surrey BC V3W 0N6",
    "addr:postcode":"v3w 0n6",
    "iso:country":"CA",
    "sg:city":"Surrey",
    "sg:classifiers":[
        {
            "category":"Home & Garden",
            "subcategory":"Furniture",
            "type":"Retail Goods"
        }
    ],
    "sg:phone":"+1 604 596 5455",
    "sg:postcode":"V3W 0N6",
    "sg:province":"BC",
    "wof:name":"Knock on Wood Furniture Gllry",
    "wof:placetype":"venue"
},
  "geometry": {"coordinates":[-122.848526001,49.139339447],"type":"Point"}
}