{
  "type": "Feature",
  "properties": {
    "iso:country":"CA",
    "sg:address":"7 Walter St",
    "sg:city":"Oakland",
    "sg:classifiers":[
        {
            "category":"Health Services",
            "subcategory":"Health Practitioner",
            "type":"Services"
        }
    ],
    "sg:phone":"+1 519 446 0042",
    "sg:postcode":"N0E 1L0",
    "sg:province":"ON",
    "sg:tags":[
        "nurse",
        "registry"
    ],
    "wof:name":"Alternative Care",
    "wof:placetype":"venue"
},
  "geometry": {"coordinates":[-80.3290176392,43.0308647156],"type":"Point"}
}