{
  "type": "Feature",
  "properties": {
    "iso:country":"CA",
    "sg:address":"46001 Fifth Ave",
    "sg:city":"Chilliwack",
    "sg:classifiers":[
        {
            "category":"Personal",
            "subcategory":"Beauty Salon",
            "type":"Services"
        }
    ],
    "sg:phone":"+1 604 792 2222",
    "sg:postcode":"V2P 1M6",
    "sg:province":"BC",
    "wof:name":"Dna Hair Team",
    "wof:placetype":"venue"
},
  "geometry": {"coordinates":[-121.952156067,49.1652755737],"type":"Point"}
}