{
  "type": "Feature",
  "properties": {
    "iso:country":"CA",
    "sg:address":"6018 48 Ave",
    "sg:city":"Camrose",
    "sg:classifiers":[
        {
            "category":"Health Services",
            "subcategory":"Chiropractor",
            "type":"Services"
        }
    ],
    "sg:phone":"+1 780 679 0961",
    "sg:postcode":"T4V 0K3",
    "sg:province":"AB",
    "wof:name":"Lynes Chiropractic Ctr",
    "wof:placetype":"venue"
},
  "geometry": {"coordinates":[-112.84296417199999,53.0181617737],"type":"Point"}
}