{
  "type": "Feature",
  "properties": {
    "addr:full":"1371 Rue DE LA Manic Chicoutimi QC G7K 1G7",
    "addr:housenumber":"1371",
    "addr:postcode":"g7k 1g7",
    "addr:street":"Rue De La Manic",
    "iso:country":"CA",
    "sg:address":"1371 Rue DE LA Manic",
    "sg:city":"Chicoutimi",
    "sg:classifiers":[
        {
            "category":"Home & Garden",
            "subcategory":"Household Appliances",
            "type":"Retail Goods"
        }
    ],
    "sg:phone":"+1 418 696 1212",
    "sg:postcode":"G7K 1G7",
    "sg:province":"QC",
    "sg:tags":[
        "gas"
    ],
    "wof:name":"Poly Gaz Saguenay Inc",
    "wof:placetype":"venue"
},
  "geometry": {"coordinates":[-71.114929,48.399879],"type":"Point"}
}