{
  "type": "Feature",
  "properties": {
    "addr:full":"Laval QC H7K 3G4",
    "addr:postcode":"qc h7k 3g4",
    "iso:country":"CA",
    "sg:city":"Laval",
    "sg:classifiers":[
        {
            "category":"Health Services",
            "subcategory":"Doctor",
            "type":"Services"
        }
    ],
    "sg:phone":"+1 450 629 4441",
    "sg:postcode":"H7K 3G4",
    "sg:province":"QC",
    "sg:tags":[
        "dentist"
    ],
    "wof:name":"Clinique Dentaire Bastien Inc",
    "wof:placetype":"venue"
},
  "geometry": {"coordinates":[-73.740623,45.616192],"type":"Point"}
}