{
  "type": "Feature",
  "properties": {
    "iso:country":"CA",
    "sg:address":"224 N 10th Ave",
    "sg:city":"Creston",
    "sg:classifiers":[
        {
            "category":"Government",
            "subcategory":"Jail",
            "type":"Public Place"
        }
    ],
    "sg:phone":"+1 250 428 3222",
    "sg:postcode":"V0B 1G0",
    "sg:province":"BC",
    "sg:tags":[
        "provincial",
        "institution"
    ],
    "wof:name":"BC Corrections-Probation Svc",
    "wof:placetype":"venue"
},
  "geometry": {"coordinates":[-116.513214111,49.0970802307],"type":"Point"}
}