{
  "type": "Feature",
  "properties": {
    "addr:full":"207 Main St E Milton ON L9T 1N7",
    "addr:housenumber":"207",
    "addr:postcode":"l9t 1n7",
    "addr:street":"Main St E",
    "iso:country":"CA",
    "sg:address":"207 Main St E",
    "sg:city":"Milton",
    "sg:classifiers":[
        {
            "category":"Building & Trades",
            "subcategory":"Electrical",
            "type":"Services"
        }
    ],
    "sg:phone":"+1 905 878 8348",
    "sg:postcode":"L9T 1N7",
    "sg:province":"ON",
    "sg:tags":[
        "electric",
        "contractor"
    ],
    "wof:name":"Cam Electric",
    "wof:placetype":"venue"
},
  "geometry": {"coordinates":[-79.88362100000001,43.512928],"type":"Point"}
}