{
  "type": "Feature",
  "properties": {
    "addr:full":"131 Esplanade St Truro NS B2N 2K5",
    "addr:housenumber":"131",
    "addr:postcode":"b2n 2k5",
    "addr:street":"Esplanade St",
    "iso:country":"CA",
    "sg:address":"131 Esplanade St",
    "sg:city":"Truro",
    "sg:classifiers":[
        {
            "category":"Bars & Pubs",
            "type":"Food & Drink"
        }
    ],
    "sg:phone":"+1 902 897 0009",
    "sg:postcode":"B2N 2K5",
    "sg:province":"NS",
    "sg:tags":[
        "lounge",
        "cocktail"
    ],
    "wof:name":"Hero's Pub",
    "wof:placetype":"venue"
},
  "geometry": {"coordinates":[-63.2751274109,45.3631896973],"type":"Point"}
}