{
  "type": "Feature",
  "properties": {
    "iso:country":"CA",
    "sg:address":"354 138 Rte",
    "sg:city":"Saint-Augustin-DE-Desmaures",
    "sg:classifiers":[
        {
            "category":"Retail",
            "subcategory":"Funeral Services",
            "type":"Services"
        }
    ],
    "sg:phone":"+1 418 878 2607",
    "sg:postcode":"G3A 1G8",
    "sg:province":"QC",
    "sg:tags":[
        "director"
    ],
    "wof:name":"Rochette, Jacques",
    "wof:placetype":"venue"
},
  "geometry": {"coordinates":[-71.384727,46.749176],"type":"Point"}
}