{
  "type": "Feature",
  "properties": {
    "addr:full":"2073 17 St SE Medicine Hat AB T1A 2B4",
    "addr:housenumber":"2073",
    "addr:postcode":"t1a 2b4",
    "addr:street":"17 St Se",
    "iso:country":"CA",
    "sg:address":"2073 17 St SE",
    "sg:city":"Medicine Hat",
    "sg:classifiers":[
        {
            "category":"Building & Trades",
            "subcategory":"Construction",
            "type":"Services"
        }
    ],
    "sg:phone":"+1 403 529 2744",
    "sg:postcode":"T1A 2B4",
    "sg:province":"AB",
    "sg:tags":[
        "concrete",
        "contractor"
    ],
    "wof:name":"Hcf",
    "wof:placetype":"venue"
},
  "geometry": {"coordinates":[-110.65341949499999,50.023273468],"type":"Point"}
}