{
  "type": "Feature",
  "properties": {
    "addr:full":"7595 Lowland Dr Burnaby BC V5J 5L1",
    "addr:housenumber":"7595",
    "addr:postcode":"v5j 5l1",
    "addr:street":"Lowland Dr",
    "iso:country":"CA",
    "sg:address":"7595 Lowland Dr",
    "sg:city":"Burnaby",
    "sg:classifiers":[
        {
            "category":"Freight",
            "type":"Transportation"
        }
    ],
    "sg:phone":"+1 604 320 0554",
    "sg:postcode":"V5J 5L1",
    "sg:province":"BC",
    "sg:tags":[
        "warehouse",
        "public"
    ],
    "wof:name":"Comet Warehousing & Distr Svc",
    "wof:placetype":"venue"
},
  "geometry": {"coordinates":[-122.99191999999999,49.188667],"type":"Point"}
}