{
  "type": "Feature",
  "properties": {
    "iso:country":"CA",
    "sg:address":"131 Charlotte St",
    "sg:city":"Peterborough",
    "sg:classifiers":[
        {
            "category":"Health Services",
            "subcategory":"Nursing And Care Facility",
            "type":"Services"
        }
    ],
    "sg:phone":"+1 705 876 1314",
    "sg:postcode":"K9J 2T6",
    "sg:province":"ON",
    "sg:tags":[
        "home",
        "retirement",
        "community"
    ],
    "wof:name":"Empress Gardens",
    "wof:placetype":"venue"
},
  "geometry": {"coordinates":[-78.318878,44.30341],"type":"Point"}
}