{
  "type": "Feature",
  "properties": {
    "addr:full":"1166 Place Henri-Dunant Joliette QC J6E 3T5",
    "addr:housenumber":"1166",
    "addr:postcode":"j6e 3t5",
    "addr:street":"Place Henri-Dunant",
    "iso:country":"CA",
    "sg:address":"1166 Place Henri-Dunant",
    "sg:city":"Joliette",
    "sg:classifiers":[
        {
            "category":"Building & Trades",
            "subcategory":"Construction",
            "type":"Services"
        }
    ],
    "sg:phone":"+1 450 759 6954",
    "sg:postcode":"J6E 3T5",
    "sg:province":"QC",
    "sg:tags":[
        "masonry",
        "contractor"
    ],
    "wof:name":"Maconnerie Mc",
    "wof:placetype":"venue"
},
  "geometry": {"coordinates":[-73.447914,46.014038],"type":"Point"}
}