{
  "type": "Feature",
  "properties": {
    "addr:full":"732 St. Andrews Rd Sudbury ON P3A 3W5",
    "addr:housenumber":"732",
    "addr:postcode":"p3a 3w5",
    "addr:street":"St. Andrews Rd",
    "iso:country":"CA",
    "sg:address":"732 St. Andrews Rd",
    "sg:city":"Sudbury",
    "sg:classifiers":[
        {
            "category":"Social Services",
            "type":"Services"
        }
    ],
    "sg:phone":"+1 705 560 6993",
    "sg:postcode":"P3A 3W5",
    "sg:province":"ON",
    "sg:tags":[
        "organization",
        "welfare"
    ],
    "wof:name":"Christian Horizons",
    "wof:placetype":"venue"
},
  "geometry": {"coordinates":[-80.9427032471,46.512840271],"type":"Point"}
}