{
  "type": "Feature",
  "properties": {
    "addr:full":"1 Union St Elmira ON N3B 3J9",
    "addr:housenumber":"1",
    "addr:postcode":"n3b 3j9",
    "addr:street":"Union St",
    "iso:country":"CA",
    "sg:address":"1 Union St",
    "sg:city":"Elmira",
    "sg:classifiers":[
        {
            "category":"Wholesale",
            "subcategory":"Non-durable Goods",
            "type":"Manufacturing & Wholesale Goods"
        }
    ],
    "sg:phone":"+1 519 669 1531",
    "sg:postcode":"N3B 3J9",
    "sg:province":"ON",
    "wof:name":"Edenborough Limited",
    "wof:placetype":"venue"
},
  "geometry": {"coordinates":[-80.552834,43.596512],"type":"Point"}
}