{
  "type": "Feature",
  "properties": {
    "addr:full":"7020 Tecumseh Rd E Windsor ON N8T 1E6",
    "addr:housenumber":"7020",
    "addr:postcode":"n8t 1e6",
    "addr:street":"Tecumseh Rd E",
    "iso:country":"CA",
    "sg:address":"7020 Tecumseh Rd E",
    "sg:city":"Windsor",
    "sg:classifiers":[
        {
            "category":"Retail",
            "subcategory":"Auto Repair",
            "type":"Services"
        }
    ],
    "sg:phone":"+1 519 798 3036",
    "sg:postcode":"N8T 1E6",
    "sg:province":"ON",
    "sg:tags":[
        "repairing",
        "automobile"
    ],
    "wof:name":"Quenneville Service Garage",
    "wof:placetype":"venue"
},
  "geometry": {"coordinates":[-82.942604,42.312325],"type":"Point"}
}