{
  "type": "Feature",
  "properties": {
    "addr:full":"580 Denison St Markham ON L3R 1B9",
    "addr:housenumber":"580",
    "addr:postcode":"l3r 1b9",
    "addr:street":"Denison St",
    "iso:country":"CA",
    "sg:address":"580 Denison St",
    "sg:city":"Markham",
    "sg:classifiers":[
        {
            "category":"Freight",
            "type":"Transportation"
        }
    ],
    "sg:phone":"+1 905 940 0923",
    "sg:postcode":"L3R 1B9",
    "sg:province":"ON",
    "sg:tags":[
        "cartage"
    ],
    "wof:name":"D & M Delivery",
    "wof:placetype":"venue"
},
  "geometry": {"coordinates":[-79.34256000000001,43.823921],"type":"Point"}
}