{
  "type": "Feature",
  "properties": {
    "iso:country":"CA",
    "sg:address":"99 High St",
    "sg:city":"Bridgewater",
    "sg:classifiers":[
        {
            "category":"Government",
            "subcategory":"Office",
            "type":"Public Place"
        }
    ],
    "sg:phone":"+1 902 543 5000",
    "sg:postcode":"B4V 1V8",
    "sg:province":"NS",
    "wof:name":"Nova Scotia Sports & Rec",
    "wof:placetype":"venue"
},
  "geometry": {"coordinates":[-64.5285873413,44.3719062805],"type":"Point"}
}