{
  "type": "Feature",
  "properties": {
    "addr:full":"19594 96 Ave Surrey BC V4N 4C3",
    "addr:housenumber":"19594",
    "addr:postcode":"v4n 4c3",
    "addr:street":"96 Ave",
    "iso:country":"CA",
    "sg:address":"19594 96 Ave",
    "sg:city":"Surrey",
    "sg:classifiers":[
        {
            "category":"Manufacturing",
            "subcategory":"Motor Vehicles & Parts",
            "type":"Manufacturing & Wholesale Goods"
        }
    ],
    "sg:phone":"+1 604 882 0183",
    "sg:postcode":"V4N 4C3",
    "sg:province":"BC",
    "sg:tags":[
        "equipment",
        "truck"
    ],
    "wof:name":"Pacbrake Manufacturing",
    "wof:placetype":"venue"
},
  "geometry": {"coordinates":[-122.67974100000001,49.176857],"type":"Point"}
}