{
  "type": "Feature",
  "properties": {
    "iso:country":"CA",
    "sg:address":"92 Bond St W",
    "sg:city":"Oshawa",
    "sg:classifiers":[
        {
            "category":"Personal",
            "subcategory":"Beauty Salon",
            "type":"Services"
        }
    ],
    "sg:phone":"+1 905 576 3558",
    "sg:postcode":"L1G 1A5",
    "sg:province":"ON",
    "sg:tags":[
        "school"
    ],
    "wof:name":"Career School of Hairstyling",
    "wof:placetype":"venue"
},
  "geometry": {"coordinates":[-78.86753082280001,43.8977890015],"type":"Point"}
}