{
  "type": "Feature",
  "properties": {
    "addr:full":"1359 Davenport Rd Toronto ON M6H 2H5",
    "addr:housenumber":"1359",
    "addr:postcode":"m6h 2h5",
    "addr:street":"Davenport Rd",
    "iso:country":"CA",
    "sg:address":"1359 Davenport Rd",
    "sg:city":"Toronto",
    "sg:classifiers":[
        {
            "category":"Government",
            "subcategory":"Office",
            "type":"Public Place"
        }
    ],
    "sg:phone":"+1 416 535 3158",
    "sg:postcode":"M6H 2H5",
    "sg:province":"ON",
    "wof:name":"Ontario Provincial Parliament",
    "wof:placetype":"venue"
},
  "geometry": {"coordinates":[-79.440155,43.673016],"type":"Point"}
}