{
  "type": "Feature",
  "properties": {
    "iso:country":"CA",
    "sg:city":"Northbrook",
    "sg:classifiers":[
        {
            "category":"Organizations",
            "subcategory":"Professional Association",
            "type":"Services"
        }
    ],
    "sg:phone":"+1 613 336 9707",
    "sg:postcode":"K0H 2G0",
    "sg:province":"ON",
    "wof:name":"Henderson Ucw Hall",
    "wof:placetype":"venue"
},
  "geometry": {"coordinates":[-77.1590881348,44.7334365845],"type":"Point"}
}