{
  "type": "Feature",
  "properties": {
    "addr:full":"15 Bold St Hamilton ON L8P 1T3",
    "addr:housenumber":"15",
    "addr:postcode":"l8p 1t3",
    "addr:street":"Bold St",
    "iso:country":"CA",
    "sg:address":"15 Bold St",
    "sg:city":"Hamilton",
    "sg:classifiers":[
        {
            "category":"Professional",
            "subcategory":"Lawyer & Legal Services",
            "type":"Services"
        }
    ],
    "sg:phone":"+1 905 522 0040",
    "sg:postcode":"L8P 1T3",
    "sg:province":"ON",
    "sg:tags":[
        "attorney"
    ],
    "wof:name":"Katz, Howard",
    "wof:placetype":"venue"
},
  "geometry": {"coordinates":[-79.8716430664,43.252620697],"type":"Point"}
}