{
  "type": "Feature",
  "properties": {
    "addr:full":"Sudbury ON P3A 2A3",
    "addr:postcode":"p3a 2a3",
    "iso:country":"CA",
    "sg:city":"Sudbury",
    "sg:classifiers":[
        {
            "category":"Insurance",
            "subcategory":"Insurance Agent",
            "type":"Services"
        }
    ],
    "sg:phone":"+1 705 524 2700",
    "sg:postcode":"P3A 2A3",
    "sg:province":"ON",
    "wof:name":"Nexus Canada Inc",
    "wof:placetype":"venue"
},
  "geometry": {"coordinates":[-80.919624,46.5219],"type":"Point"}
}