{
  "type": "Feature",
  "properties": {
    "addr:full":"41924 Yarrow Central Rd Chilliwack BC V2R 5E7",
    "addr:postcode":"41924;v2r 5e7",
    "addr:street":"Central Rd",
    "iso:country":"CA",
    "sg:address":"41924 Yarrow Central Rd",
    "sg:city":"Chilliwack",
    "sg:classifiers":[
        {
            "category":"Home & Garden",
            "subcategory":"Building Materials",
            "type":"Retail Goods"
        }
    ],
    "sg:phone":"+1 604 823 6534",
    "sg:postcode":"V2R 5E7",
    "sg:province":"BC",
    "wof:name":"Yarrow Building Supplies Ltd",
    "wof:placetype":"venue"
},
  "geometry": {"coordinates":[-122.06426239,49.0818862915],"type":"Point"}
}