{
  "type": "Feature",
  "properties": {
    "addr:full":"Richmond BC V6V 2V4",
    "addr:postcode":"v6v 2v4",
    "iso:country":"CA",
    "sg:city":"Richmond",
    "sg:classifiers":[
        {
            "category":"Manufacturing",
            "subcategory":"Tools & Machinery",
            "type":"Manufacturing & Wholesale Goods"
        }
    ],
    "sg:phone":"+1 604 278 5000",
    "sg:postcode":"V6V 2V4",
    "sg:province":"BC",
    "sg:tags":[
        "equipment",
        "hospital",
        "surgeon",
        "physician"
    ],
    "wof:name":"Xillix Technologies Corp",
    "wof:placetype":"venue"
},
  "geometry": {"coordinates":[-123.071442,49.17635],"type":"Point"}
}