{
  "type": "Feature",
  "properties": {
    "addr:full":"21 Antares Dr # 101 Nepean ON K2E 7T8",
    "addr:housenumber":"21;101",
    "addr:postcode":"k2e 7t8",
    "addr:street":"Antares Dr #",
    "iso:country":"CA",
    "sg:address":"21 Antares Dr # 101",
    "sg:city":"Nepean",
    "sg:classifiers":[
        {
            "category":"Professional",
            "subcategory":"Engineering",
            "type":"Services"
        }
    ],
    "sg:phone":"+1 613 224 8556",
    "sg:postcode":"K2E 7T8",
    "sg:province":"ON",
    "sg:tags":[
        "fiber",
        "optics",
        "engineer"
    ],
    "wof:name":"Darchi Systems Ltd",
    "wof:placetype":"venue"
},
  "geometry": {"coordinates":[-75.708023,45.334366],"type":"Point"}
}