{
  "type": "Feature",
  "properties": {
    "addr:full":"6832 Rue Saint-Hubert Montreal QC H2S 2M6",
    "addr:housenumber":"6832",
    "addr:postcode":"h2s 2m6",
    "addr:street":"Rue Saint-Hubert",
    "iso:country":"CA",
    "sg:address":"6832 Rue Saint-Hubert",
    "sg:city":"Montreal",
    "sg:classifiers":[
        {
            "category":"Shopping",
            "subcategory":"Clothing, Apparel, & Fashions",
            "type":"Retail Goods"
        }
    ],
    "sg:phone":"+1 514 273 3334",
    "sg:postcode":"H2S 2M6",
    "sg:province":"QC",
    "sg:tags":[
        "shop",
        "bridal"
    ],
    "wof:name":"Pronuptia B France",
    "wof:placetype":"venue"
},
  "geometry": {"coordinates":[-73.60842100000001,45.53841],"type":"Point"}
}