{
  "type": "Feature",
  "properties": {
    "iso:country":"CA",
    "sg:address":"5495 Rang 5 O",
    "sg:city":"L'Ascension-DE-Notre-Seigneur",
    "sg:classifiers":[
        {
            "category":"Home & Garden",
            "subcategory":"Garden Supply",
            "type":"Retail Goods"
        }
    ],
    "sg:phone":"+1 418 347 4355",
    "sg:postcode":"G0W 1Y0",
    "sg:province":"QC",
    "sg:tags":[
        "peat",
        "moss"
    ],
    "wof:name":"Tourbiere Lambert Inc",
    "wof:placetype":"venue"
},
  "geometry": {"coordinates":[-71.7026138306,48.7280502319],"type":"Point"}
}