{
  "type": "Feature",
  "properties": {
    "addr:full":"1726 Avenue H N Saskatoon SK S7L 5A2",
    "addr:housenumber":"1726",
    "addr:postcode":"s7l 5a2",
    "addr:street":"Avenue H N",
    "iso:country":"CA",
    "sg:address":"1726 Avenue H N",
    "sg:city":"Saskatoon",
    "sg:classifiers":[
        {
            "category":"Personal",
            "type":"Services"
        }
    ],
    "sg:phone":"+1 306 242 6185",
    "sg:postcode":"S7L 5A2",
    "sg:province":"SK",
    "sg:tags":[
        "therapist",
        "massage"
    ],
    "wof:name":"Deanna Wells Massage Therapy",
    "wof:placetype":"venue"
},
  "geometry": {"coordinates":[-106.680343628,52.1518096924],"type":"Point"}
}