{
  "type": "Feature",
  "properties": {
    "addr:full":"1444 Rue Notre-Dame L'Ancienne-Lorette QC G2E 3A7",
    "addr:housenumber":"1444",
    "addr:postcode":"g2e 3a7",
    "addr:street":"Rue Notre-Dame",
    "iso:country":"CA",
    "sg:address":"1444 Rue Notre-Dame",
    "sg:city":"L'Ancienne-Lorette",
    "sg:classifiers":[
        {
            "category":"Food & Beverages",
            "subcategory":"Groceries & Convenience Stores",
            "type":"Retail Goods"
        }
    ],
    "sg:phone":"+1 418 872 4069",
    "sg:postcode":"G2E 3A7",
    "sg:province":"QC",
    "sg:tags":[
        "grocer"
    ],
    "wof:name":"Alimentation J Paradis",
    "wof:placetype":"venue"
},
  "geometry": {"coordinates":[-71.3562164307,46.7958145142],"type":"Point"}
}