{
  "type": "Feature",
  "properties": {
    "addr:full":"505 Highway 7 E # Ph501 Thornhill ON L3T 7T1",
    "addr:housenumber":"505",
    "addr:postcode":"l3t 7t1",
    "addr:street":"Highway 7 E # Ph501",
    "iso:country":"CA",
    "sg:address":"505 Highway 7 E # Ph501",
    "sg:city":"Thornhill",
    "sg:classifiers":[
        {
            "category":"Real Estate",
            "subcategory":"Real Estate Agent",
            "type":"Services"
        }
    ],
    "sg:phone":"+1 905 709 8688",
    "sg:postcode":"L3T 7T1",
    "sg:province":"ON",
    "wof:name":"Jardine Hills Realty Inc",
    "wof:placetype":"venue"
},
  "geometry": {"coordinates":[-79.4235534668,43.8155250549],"type":"Point"}
}