{
  "type": "Feature",
  "properties": {
    "addr:full":"146 Main St S Mount Forest ON N0G 2L0",
    "addr:housenumber":"146",
    "addr:postcode":"n0g 2l0",
    "addr:street":"Main St S Mount",
    "iso:country":"CA",
    "sg:address":"146 Main St S",
    "sg:city":"Mount Forest",
    "sg:classifiers":[
        {
            "category":"Shopping",
            "type":"Retail Goods"
        }
    ],
    "sg:phone":"+1 519 323 1410",
    "sg:postcode":"N0G 2L0",
    "sg:province":"ON",
    "sg:tags":[
        "shop",
        "wedding",
        "gift",
        "supply"
    ],
    "wof:name":"Tickle Your Fancy",
    "wof:placetype":"venue"
},
  "geometry": {"coordinates":[-80.7345962524,43.9812812805],"type":"Point"}
}