{
  "type": "Feature",
  "properties": {
    "addr:full":"2059 Carron Dr Bathurst NB E2A 5Z7",
    "addr:housenumber":"2059",
    "addr:postcode":"e2a 5z7",
    "addr:street":"Carron Dr",
    "iso:country":"CA",
    "sg:address":"2059 Carron Dr",
    "sg:city":"Bathurst",
    "sg:classifiers":[
        {
            "category":"Professional",
            "subcategory":"Engineering",
            "type":"Services"
        }
    ],
    "sg:phone":"+1 506 546 6888",
    "sg:postcode":"E2A 5Z7",
    "sg:province":"NB",
    "sg:tags":[
        "engineer"
    ],
    "wof:name":"Cda Engineering",
    "wof:placetype":"venue"
},
  "geometry": {"coordinates":[-65.60874200000001,47.637924],"type":"Point"}
}