{
  "type": "Feature",
  "properties": {
    "addr:full":"Edmonton AB T5K 0L4",
    "addr:postcode":"t5k 0l4",
    "iso:country":"CA",
    "sg:city":"Edmonton",
    "sg:classifiers":[
        {
            "category":"Organizations",
            "subcategory":"Professional Association",
            "type":"Services"
        }
    ],
    "sg:phone":"+1 780 482 8993",
    "sg:postcode":"T5K 0L4",
    "sg:province":"AB",
    "wof:name":"Parkinson's Society of Alberta",
    "wof:placetype":"venue"
},
  "geometry": {"coordinates":[-113.51239776600001,53.5408287048],"type":"Point"}
}