{
  "type": "Feature",
  "properties": {
    "addr:full":"1042 Gerrard St E Toronto ON M4M 1Z5",
    "addr:housenumber":"1042",
    "addr:postcode":"m4m 1z5",
    "addr:street":"Gerrard St E",
    "iso:country":"CA",
    "sg:address":"1042 Gerrard St E",
    "sg:city":"Toronto",
    "sg:classifiers":[
        {
            "category":"Shopping",
            "subcategory":"Discount & Variety Stores",
            "type":"Retail Goods"
        }
    ],
    "sg:phone":"+1 416 461 5242",
    "sg:postcode":"M4M 1Z5",
    "sg:province":"ON",
    "wof:name":"Martin's Variety Store",
    "wof:placetype":"venue"
},
  "geometry": {"coordinates":[-79.33672300000001,43.669056],"type":"Point"}
}