{
  "type": "Feature",
  "properties": {
    "addr:full":"4162 Portage Rd Niagara Falls ON L2E 6A4",
    "addr:housenumber":"4162",
    "addr:postcode":"l2e 6a4",
    "addr:street":"Portage Rd",
    "iso:country":"CA",
    "sg:address":"4162 Portage Rd",
    "sg:city":"Niagara Falls",
    "sg:classifiers":[
        {
            "category":"Professional",
            "subcategory":"Accounting & Tax Preparation",
            "type":"Services"
        }
    ],
    "sg:phone":"+1 905 357 5931",
    "sg:postcode":"L2E 6A4",
    "sg:province":"ON",
    "sg:tags":[
        "accountant"
    ],
    "wof:name":"Fast, David J CA",
    "wof:placetype":"venue"
},
  "geometry": {"coordinates":[-79.0978393555,43.1132392883],"type":"Point"}
}