{
  "type": "Feature",
  "properties": {
    "addr:full":"5550 Boul Sainte-Anne Boischatel QC G0A 1H0",
    "addr:housenumber":"5550",
    "addr:postcode":"g0a 1h0",
    "addr:street":"Boul Sainte-Anne",
    "iso:country":"CA",
    "sg:address":"5550 Boul Sainte-Anne",
    "sg:city":"Boischatel",
    "sg:classifiers":[
        {
            "category":"Restaurant",
            "type":"Food & Drink"
        }
    ],
    "sg:phone":"+1 418 822 3886",
    "sg:postcode":"G0A 1H0",
    "sg:province":"QC",
    "wof:name":"Subway Sandwiches & Salads",
    "wof:placetype":"venue"
},
  "geometry": {"coordinates":[-71.125869751,46.8966255188],"type":"Point"}
}