{
  "type": "Feature",
  "properties": {
    "addr:full":"1302 8th St Estevan SK S4A 1H6",
    "addr:housenumber":"1302",
    "addr:postcode":"s4a 1h6",
    "addr:street":"8Th St",
    "iso:country":"CA",
    "sg:address":"1302 8th St",
    "sg:city":"Estevan",
    "sg:classifiers":[
        {
            "category":"Organizations",
            "subcategory":"Religious Organization",
            "type":"Services"
        }
    ],
    "sg:phone":"+1 306 634 3116",
    "sg:postcode":"S4A 1H6",
    "sg:province":"SK",
    "sg:tags":[
        "church"
    ],
    "wof:name":"Church of Christ",
    "wof:placetype":"venue"
},
  "geometry": {"coordinates":[-102.994545,49.144398],"type":"Point"}
}