{
  "type": "Feature",
  "properties": {
    "addr:full":"42713 Mill Rd Seaforth ON N0K 1W0",
    "addr:housenumber":"42713",
    "addr:postcode":"n0k 1w0",
    "addr:street":"Mill Rd",
    "iso:country":"CA",
    "sg:address":"42713 Mill Rd",
    "sg:city":"Seaforth",
    "sg:classifiers":[
        {
            "category":"Wholesale",
            "subcategory":"Farm Supplies",
            "type":"Manufacturing & Wholesale Goods"
        }
    ],
    "sg:phone":"+1 519 522 0608",
    "sg:postcode":"N0K 1W0",
    "sg:province":"ON",
    "wof:name":"Milton J Dietz Ltd",
    "wof:placetype":"venue"
},
  "geometry": {"coordinates":[-81.3937072754,43.5530433655],"type":"Point"}
}