{
  "type": "Feature",
  "properties": {
    "addr:full":"11390 Av Arthur-Nantel Montreal QC H1E 6V2",
    "addr:housenumber":"11390",
    "addr:postcode":"h1e 6v2",
    "addr:street":"Av Arthur-Nantel",
    "iso:country":"CA",
    "sg:address":"11390 Av Arthur-Nantel",
    "sg:city":"Montreal",
    "sg:classifiers":[
        {
            "category":"Autos & Motor Vehicles",
            "subcategory":"Auto Supplies",
            "type":"Retail Goods"
        }
    ],
    "sg:phone":"+1 514 494 7393",
    "sg:postcode":"H1E 6V2",
    "sg:province":"QC",
    "sg:tags":[
        "equipment",
        "air",
        "conditioning",
        "automobile"
    ],
    "wof:name":"Entreprises Climauto Ltee",
    "wof:placetype":"venue"
},
  "geometry": {"coordinates":[-73.58782958979999,45.62266922],"type":"Point"}
}