{
  "type": "Feature",
  "properties": {
    "addr:full":"5114 46th St Elk Point AB T0A 1A0",
    "addr:housenumber":"5114",
    "addr:postcode":"t0a 1a0",
    "addr:street":"46Th St",
    "iso:country":"CA",
    "sg:address":"5114 46th St",
    "sg:city":"Elk Point",
    "sg:classifiers":[
        {
            "category":"Mining & Drilling",
            "type":"Manufacturing & Wholesale Goods"
        }
    ],
    "sg:phone":"+1 780 724 2910",
    "sg:postcode":"T0A 1A0",
    "sg:province":"AB",
    "sg:tags":[
        "field",
        "oil"
    ],
    "wof:name":"Kudu Industries Inc",
    "wof:placetype":"venue"
},
  "geometry": {"coordinates":[-110.893005,53.898582],"type":"Point"}
}