{
  "type": "Feature",
  "properties": {
    "iso:country":"CA",
    "sg:address":"2255 Boul Des Chutes",
    "sg:city":"Beauport",
    "sg:classifiers":[
        {
            "category":"Insurance",
            "subcategory":"Insurance Agent",
            "type":"Services"
        }
    ],
    "sg:phone":"+1 418 667 8550",
    "sg:postcode":"G1C 1X1",
    "sg:province":"QC",
    "wof:name":"Paul Eugene Chabot Enr",
    "wof:placetype":"venue"
},
  "geometry": {"coordinates":[-71.159645,46.882145],"type":"Point"}
}