{
  "type": "Feature",
  "properties": {
    "addr:full":"56691 Eden Line 44 Eden ON N0J 1H0",
    "addr:housenumber":"56691;44",
    "addr:postcode":"n0j 1h0",
    "addr:street":"Eden Line",
    "iso:country":"CA",
    "sg:address":"56691 Eden Line 44",
    "sg:city":"Eden",
    "sg:classifiers":[
        {
            "category":"Building & Trades",
            "subcategory":"Construction",
            "type":"Services"
        }
    ],
    "sg:phone":"+1 519 866 5416",
    "sg:postcode":"N0J 1H0",
    "sg:province":"ON",
    "sg:tags":[
        "woodworker"
    ],
    "wof:name":"Krahn's Woodworking",
    "wof:placetype":"venue"
},
  "geometry": {"coordinates":[-80.75798034669999,42.7945976257],"type":"Point"}
}