{
  "type": "Feature",
  "properties": {
    "addr:full":"401 Sunset Ave Windsor ON N9B 3A8",
    "addr:housenumber":"401",
    "addr:postcode":"n9b 3a8",
    "addr:street":"Sunset Ave",
    "iso:country":"CA",
    "sg:address":"401 Sunset Ave",
    "sg:city":"Windsor",
    "sg:classifiers":[
        {
            "category":"Communications",
            "subcategory":"Radio Station",
            "type":"Services"
        }
    ],
    "sg:phone":"+1 519 971 3630",
    "sg:postcode":"N9B 3A8",
    "sg:province":"ON",
    "sg:tags":[
        "academic",
        "school",
        "broadcasting",
        "college",
        "company"
    ],
    "wof:name":"University of Windsor Mdtn Svc",
    "wof:placetype":"venue"
},
  "geometry": {"coordinates":[-83.065941,42.30645],"type":"Point"}
}