{
  "type": "Feature",
  "properties": {
    "addr:full":"3500 Carling Ave Nepean ON K2H 8E9",
    "addr:housenumber":"3500",
    "addr:postcode":"k2h 8e9",
    "addr:street":"Carling Ave",
    "iso:country":"CA",
    "sg:address":"3500 Carling Ave",
    "sg:city":"Nepean",
    "sg:classifiers":[
        {
            "category":"Shopping",
            "type":"Retail Goods"
        }
    ],
    "sg:phone":"+1 613 763 2211",
    "sg:postcode":"K2H 8E9",
    "sg:province":"ON",
    "sg:tags":[
        "equipment",
        "telephone",
        "supply"
    ],
    "wof:name":"Nortel Networks",
    "wof:placetype":"venue"
},
  "geometry": {"coordinates":[-75.849907,45.354454],"type":"Point"}
}