{
  "type": "Feature",
  "properties": {
    "addr:full":"297 Greenwood Dr Fredericton NB E3A 7G7",
    "addr:housenumber":"297",
    "addr:postcode":"e3a 7g7",
    "addr:street":"Greenwood Dr",
    "iso:country":"CA",
    "sg:address":"297 Greenwood Dr",
    "sg:city":"Fredericton",
    "sg:classifiers":[
        {
            "category":"Retail",
            "subcategory":"Portrait Studio",
            "type":"Services"
        }
    ],
    "sg:phone":"+1 506 454 1830",
    "sg:postcode":"E3A 7G7",
    "sg:province":"NB",
    "sg:tags":[
        "photographer"
    ],
    "wof:name":"William Demerchant Photography",
    "wof:placetype":"venue"
},
  "geometry": {"coordinates":[-66.594673,45.953117],"type":"Point"}
}