{
  "type": "Feature",
  "properties": {
    "addr:full":"1265 Rue Des Artisans Quebec QC G1N 4T8",
    "addr:housenumber":"1265",
    "addr:postcode":"g1n 4t8",
    "addr:street":"Rue Des Artisans",
    "iso:country":"CA",
    "sg:address":"1265 Rue Des Artisans",
    "sg:city":"Quebec",
    "sg:classifiers":[
        {
            "category":"Home & Garden",
            "subcategory":"Furniture",
            "type":"Retail Goods"
        }
    ],
    "sg:phone":"+1 418 527 6367",
    "sg:postcode":"G1N 4T8",
    "sg:province":"QC",
    "sg:tags":[
        "futon"
    ],
    "wof:name":"Futon Etcetera",
    "wof:placetype":"venue"
},
  "geometry": {"coordinates":[-71.25933074949999,46.8027648926],"type":"Point"}
}