{
  "type": "Feature",
  "properties": {
    "addr:full":"2371 25 Sideroad Innisfil ON L9S 2G3",
    "addr:housenumber":"2371",
    "addr:postcode":"l9s 2g3",
    "addr:street":"25 Sideroad",
    "iso:country":"CA",
    "sg:address":"2371 25 Sideroad",
    "sg:city":"Innisfil",
    "sg:classifiers":[
        {
            "category":"Cinema",
            "subcategory":"Movie Rental",
            "type":"Entertainment"
        }
    ],
    "sg:phone":"+1 705 436 5424",
    "sg:postcode":"L9S 2G3",
    "sg:province":"ON",
    "sg:tags":[
        "leasing",
        "video",
        "disc",
        "tape"
    ],
    "wof:name":"Video 99",
    "wof:placetype":"venue"
},
  "geometry": {"coordinates":[-79.59571099999999,44.30402],"type":"Point"}
}