{
  "type": "Feature",
  "properties": {
    "addr:full":"101 Boul Cartier Riviere-Du-Loup QC G5R 2N3",
    "addr:housenumber":"101",
    "addr:postcode":"g5r 2n3",
    "addr:street":"Boul Cartier Riviere-Du-Loup",
    "iso:country":"CA",
    "sg:address":"101 Boul Cartier",
    "sg:city":"Riviere-Du-Loup",
    "sg:classifiers":[
        {
            "category":"Food & Beverages",
            "subcategory":"Meat & Fish",
            "type":"Retail Goods"
        }
    ],
    "sg:phone":"+1 418 863 6748",
    "sg:postcode":"G5R 2N3",
    "sg:province":"QC",
    "sg:tags":[
        "seafood"
    ],
    "wof:name":"Camion DE Poisson",
    "wof:placetype":"venue"
},
  "geometry": {"coordinates":[-69.5385131836,47.8489112854],"type":"Point"}
}