{
  "type": "Feature",
  "properties": {
    "addr:full":"6735 Ellen Pl Nanaimo BC V9V 1A2",
    "addr:housenumber":"6735",
    "addr:postcode":"v9v 1a2",
    "addr:street":"Ellen Pl",
    "iso:country":"CA",
    "sg:address":"6735 Ellen Pl",
    "sg:city":"Nanaimo",
    "sg:classifiers":[
        {
            "category":"Building & Trades",
            "subcategory":"Electrical",
            "type":"Services"
        }
    ],
    "sg:phone":"+1 250 390 4033",
    "sg:postcode":"V9V 1A2",
    "sg:province":"BC",
    "sg:tags":[
        "electric",
        "contractor"
    ],
    "wof:name":"J Koster Electric CO Ltd",
    "wof:placetype":"venue"
},
  "geometry": {"coordinates":[-124.05497,49.245876],"type":"Point"}
}