{
  "type": "Feature",
  "properties": {
    "addr:full":"10 Ch Lamoureux Grand-Remous QC J0W 1E0",
    "addr:housenumber":"10",
    "addr:postcode":"ch;j0w 1e0",
    "addr:street":"Lamoureux",
    "iso:country":"CA",
    "sg:address":"10 Ch Lamoureux",
    "sg:city":"Grand-Remous",
    "sg:classifiers":[
        {
            "category":"Wholesale",
            "subcategory":"Scrap",
            "type":"Manufacturing & Wholesale Goods"
        }
    ],
    "sg:phone":"+1 819 438 3355",
    "sg:postcode":"J0W 1E0",
    "sg:province":"QC",
    "sg:tags":[
        "steel",
        "metal",
        "iron"
    ],
    "wof:name":"Aciers & Rebuts Ouellette",
    "wof:placetype":"venue"
},
  "geometry": {"coordinates":[-75.905083,46.619305],"type":"Point"}
}