{
  "type": "Feature",
  "properties": {
    "addr:full":"Mississauga ON L5N 7K2",
    "addr:postcode":"l5n 7k2",
    "iso:country":"CA",
    "sg:city":"Mississauga",
    "sg:classifiers":[
        {
            "category":"Real Estate",
            "subcategory":"Developer",
            "type":"Services"
        }
    ],
    "sg:phone":"+1 905 567 3431",
    "sg:postcode":"L5N 7K2",
    "sg:province":"ON",
    "wof:name":"Matthews Southwest",
    "wof:placetype":"venue"
},
  "geometry": {"coordinates":[-79.7440109253,43.6007766724],"type":"Point"}
}