{
  "type": "Feature",
  "properties": {
    "addr:full":"105 Broadway Ave Regina SK S4N 1B2",
    "addr:housenumber":"105",
    "addr:postcode":"s4n 1b2",
    "addr:street":"Broadway Ave",
    "iso:country":"CA",
    "sg:address":"105 Broadway Ave",
    "sg:city":"Regina",
    "sg:classifiers":[
        {
            "category":"Organizations",
            "subcategory":"Religious Organization",
            "type":"Services"
        }
    ],
    "sg:phone":"+1 306 352 1526",
    "sg:postcode":"S4N 1B2",
    "sg:province":"SK",
    "sg:tags":[
        "church"
    ],
    "wof:name":"Broadway United Church",
    "wof:placetype":"venue"
},
  "geometry": {"coordinates":[-104.58238220200001,50.4375305176],"type":"Point"}
}