{
  "type": "Feature",
  "properties": {
    "iso:country":"CA",
    "sg:city":"North York",
    "sg:classifiers":[
        {
            "category":"Communications",
            "subcategory":"Film & Video Production",
            "type":"Services"
        }
    ],
    "sg:phone":"+1 416 445 0200",
    "sg:postcode":"M3B 3K9",
    "sg:province":"ON",
    "sg:tags":[
        "multimedia",
        "taping"
    ],
    "wof:name":"Armsworth Multimedia Prods Ltd",
    "wof:placetype":"venue"
},
  "geometry": {"coordinates":[-79.35182189939999,43.7615585327],"type":"Point"}
}