{
  "type": "Feature",
  "properties": {
    "addr:full":"42 Queen St Stephenville NL A2N 3A7",
    "addr:housenumber":"42",
    "addr:postcode":"a2n 3a7",
    "addr:street":"Queen St",
    "iso:country":"CA",
    "sg:address":"42 Queen St",
    "sg:city":"Stephenville",
    "sg:classifiers":[
        {
            "category":"Shopping",
            "subcategory":"Jewelry",
            "type":"Retail Goods"
        }
    ],
    "sg:phone":"+1 709 643 5514",
    "sg:postcode":"A2N 3A7",
    "sg:province":"NL",
    "sg:tags":[
        "jeweler"
    ],
    "wof:name":"Charm Diamond Ctr",
    "wof:placetype":"venue"
},
  "geometry": {"coordinates":[-58.5751686096,48.5459594727],"type":"Point"}
}