{
  "type": "Feature",
  "properties": {
    "iso:country":"CA",
    "sg:city":"Campbell River",
    "sg:classifiers":[
        {
            "category":"Communications",
            "subcategory":"Radio Station",
            "type":"Services"
        }
    ],
    "sg:phone":"+1 250 830 1080",
    "sg:postcode":"V9W 6R4",
    "sg:province":"BC",
    "sg:tags":[
        "company",
        "broadcasting"
    ],
    "wof:name":"Eagle Cklr",
    "wof:placetype":"venue"
},
  "geometry": {"coordinates":[-125.247802734,49.996887207],"type":"Point"}
}