{
  "type": "Feature",
  "properties": {
    "addr:full":"Vancouver BC V6B 5A1",
    "addr:postcode":"v6b 5a1",
    "iso:country":"CA",
    "sg:city":"Vancouver",
    "sg:classifiers":[
        {
            "category":"Insurance",
            "subcategory":"Insurance Agent",
            "type":"Services"
        }
    ],
    "sg:phone":"+1 604 718 4410",
    "sg:postcode":"V6B 5A1",
    "sg:province":"BC",
    "wof:name":"Desjardins Financial Security",
    "wof:placetype":"venue"
},
  "geometry": {"coordinates":[-123.11512,49.280712],"type":"Point"}
}