{
  "type": "Feature",
  "properties": {
    "addr:full":"295 Montreal Rd Vanier ON K1L 6B8",
    "addr:housenumber":"295",
    "addr:postcode":"k1l 6b8",
    "addr:street":"Montreal Rd",
    "iso:country":"CA",
    "sg:address":"295 Montreal Rd",
    "sg:city":"Vanier",
    "sg:classifiers":[
        {
            "category":"Insurance",
            "subcategory":"Insurance Agent",
            "type":"Services"
        }
    ],
    "sg:phone":"+1 613 746 1450",
    "sg:postcode":"K1L 6B8",
    "sg:province":"ON",
    "sg:tags":[
        "consultant"
    ],
    "wof:name":"Mantha Insurance Brokers Ltd",
    "wof:placetype":"venue"
},
  "geometry": {"coordinates":[-75.659126,45.43721],"type":"Point"}
}