{
  "type": "Feature",
  "properties": {
    "addr:full":"Crilly Rd Fort Frances ON P9A 3M7",
    "addr:postcode":"p9a 3m7",
    "addr:street":"Crilly Rd",
    "iso:country":"CA",
    "sg:address":"Crilly Rd",
    "sg:city":"Fort Frances",
    "sg:classifiers":[
        {
            "category":"Wholesale",
            "subcategory":"Construction Materials",
            "type":"Manufacturing & Wholesale Goods"
        }
    ],
    "sg:phone":"+1 807 947 2326",
    "sg:postcode":"P9A 3M7",
    "sg:province":"ON",
    "sg:tags":[
        "timberland",
        "company",
        "timber"
    ],
    "wof:name":"Seine River Tourist & Timber",
    "wof:placetype":"venue"
},
  "geometry": {"coordinates":[-93.39110599999999,48.610016],"type":"Point"}
}