{
  "type": "Feature",
  "properties": {
    "addr:full":"2520 Division Rd N Kingsville ON N9Y 2E5",
    "addr:housenumber":"2520",
    "addr:postcode":"n9y 2e5",
    "addr:street":"Division Rd N",
    "iso:country":"CA",
    "sg:address":"2520 Division Rd N",
    "sg:city":"Kingsville",
    "sg:classifiers":[
        {
            "category":"Building & Trades",
            "subcategory":"Construction",
            "type":"Services"
        }
    ],
    "sg:phone":"+1 519 733 3135",
    "sg:postcode":"N9Y 2E5",
    "sg:province":"ON",
    "sg:tags":[
        "masonry",
        "contractor"
    ],
    "wof:name":"Martin's Masonry Contractor",
    "wof:placetype":"venue"
},
  "geometry": {"coordinates":[-82.7367095947,42.0739326477],"type":"Point"}
}