{
  "type": "Feature",
  "properties": {
    "addr:full":"PO Box 681 STN Main Brooks AB T1R 1B6",
    "addr:housenumber":"po;681",
    "addr:postcode":"ab t1r 1b6",
    "addr:street":"Box;Stn Main Brooks",
    "iso:country":"CA",
    "sg:address":"PO Box 681 STN Main",
    "sg:city":"Brooks",
    "sg:classifiers":[
        {
            "category":"Mining & Drilling",
            "type":"Manufacturing & Wholesale Goods"
        }
    ],
    "sg:phone":"+1 403 362 8105",
    "sg:postcode":"T1R 1B6",
    "sg:province":"AB",
    "sg:tags":[
        "field",
        "oil"
    ],
    "wof:name":"Big S Vacuum Svc",
    "wof:placetype":"venue"
},
  "geometry": {"coordinates":[-111.89849100000001,50.565853],"type":"Point"}
}