{
  "type": "Feature",
  "properties": {
    "addr:full":"Burnaby BC V5B 1S2",
    "addr:postcode":"v5b 1s2",
    "iso:country":"CA",
    "sg:city":"Burnaby",
    "sg:classifiers":[
        {
            "category":"Health Services",
            "subcategory":"Doctor",
            "type":"Services"
        }
    ],
    "sg:phone":"+1 604 298 5595",
    "sg:postcode":"V5B 1S2",
    "sg:province":"BC",
    "sg:tags":[
        "dentist"
    ],
    "wof:name":"Giancarlo Moro Inc",
    "wof:placetype":"venue"
},
  "geometry": {"coordinates":[-122.96835299999999,49.280128],"type":"Point"}
}