{
  "type": "Feature",
  "properties": {
    "addr:full":"1039 Pacific Ave Winnipeg MB R3E 1G5",
    "addr:housenumber":"1039",
    "addr:postcode":"r3e 1g5",
    "addr:street":"Pacific Ave",
    "iso:country":"CA",
    "sg:address":"1039 Pacific Ave",
    "sg:city":"Winnipeg",
    "sg:classifiers":[
        {
            "category":"Manufacturing",
            "subcategory":"Building Materials",
            "type":"Manufacturing & Wholesale Goods"
        }
    ],
    "sg:phone":"+1 204 783 7599",
    "sg:postcode":"R3E 1G5",
    "sg:province":"MB",
    "wof:name":"Felix Woodworking Ltd",
    "wof:placetype":"venue"
},
  "geometry": {"coordinates":[-97.1688156128,49.9114570618],"type":"Point"}
}