{
  "type": "Feature",
  "properties": {
    "addr:full":"Saint-Nicolas QC G7A 1B1",
    "addr:postcode":"g7a 1b1",
    "iso:country":"CA",
    "sg:city":"Saint-Nicolas",
    "sg:classifiers":[
        {
            "category":"Building & Trades",
            "subcategory":"Construction",
            "type":"Services"
        }
    ],
    "sg:phone":"+1 418 836 5333",
    "sg:postcode":"G7A 1B1",
    "sg:province":"QC",
    "sg:tags":[
        "resurfacing",
        "laying",
        "refinishing",
        "floor"
    ],
    "wof:name":"Sylvavision",
    "wof:placetype":"venue"
},
  "geometry": {"coordinates":[-71.3409042358,46.6760978699],"type":"Point"}
}