{
  "type": "Feature",
  "properties": {
    "iso:country":"CA",
    "sg:address":"11429 Rue Notre-Dame E",
    "sg:city":"Montreal-Est",
    "sg:classifiers":[
        {
            "category":"Retail",
            "subcategory":"Auto Repair",
            "type":"Services"
        }
    ],
    "sg:phone":"+1 514 645 7222",
    "sg:postcode":"H1B 2W7",
    "sg:province":"QC",
    "sg:tags":[
        "body",
        "automobile",
        "painting"
    ],
    "wof:name":"Jo'S'Ma",
    "wof:placetype":"venue"
},
  "geometry": {"coordinates":[-73.495354,45.632107],"type":"Point"}
}