{
  "type": "Feature",
  "properties": {
    "addr:full":"Cp 69 Port-Menier QC G0G 2Y0",
    "addr:housenumber":"69",
    "addr:postcode":"g0g 2y0",
    "addr:street":"Cp",
    "iso:country":"CA",
    "sg:address":"Cp 69",
    "sg:city":"Port-Menier",
    "sg:classifiers":[
        {
            "category":"Travel",
            "subcategory":"Campground",
            "type":"Entertainment"
        }
    ],
    "sg:phone":"+1 418 535 0294",
    "sg:postcode":"G0G 2Y0",
    "sg:province":"QC",
    "sg:tags":[
        "camp",
        "fishing"
    ],
    "wof:name":"Pourvoirie Du Lac Genevieve",
    "wof:placetype":"venue"
},
  "geometry": {"coordinates":[-64.368454,49.826405],"type":"Point"}
}