{
  "type": "Feature",
  "properties": {
    "addr:full":"9902 97 Ave Peace River AB T8S 1H6",
    "addr:housenumber":"9902",
    "addr:postcode":"t8s 1h6",
    "addr:street":"97 Ave",
    "iso:country":"CA",
    "sg:address":"9902 97 Ave",
    "sg:city":"Peace River",
    "sg:classifiers":[
        {
            "category":"Professional",
            "subcategory":"Lawyer & Legal Services",
            "type":"Services"
        }
    ],
    "sg:phone":"+1 780 624 4860",
    "sg:postcode":"T8S 1H6",
    "sg:province":"AB",
    "sg:tags":[
        "attorney"
    ],
    "wof:name":"Lorne G Mann Law Firm",
    "wof:placetype":"venue"
},
  "geometry": {"coordinates":[-117.292084,56.236538],"type":"Point"}
}