{
  "type": "Feature",
  "properties": {
    "addr:full":"1208 Railway St Crossfield AB T0M 0S0",
    "addr:housenumber":"1208",
    "addr:postcode":"t0m 0s0",
    "addr:street":"Railway St",
    "iso:country":"CA",
    "sg:address":"1208 Railway St",
    "sg:city":"Crossfield",
    "sg:classifiers":[
        {
            "category":"Restaurant",
            "type":"Food & Drink"
        }
    ],
    "sg:phone":"+1 403 946 5000",
    "sg:postcode":"T0M 0S0",
    "sg:province":"AB",
    "wof:name":"Enjoy Garden Restaurant",
    "wof:placetype":"venue"
},
  "geometry": {"coordinates":[-114.028358,51.427608],"type":"Point"}
}