{
  "type": "Feature",
  "properties": {
    "addr:full":"5500 Admiral Blvd Delta BC V4K 5B7",
    "addr:housenumber":"5500",
    "addr:postcode":"v4k 5b7",
    "addr:street":"Admiral Blvd",
    "iso:country":"CA",
    "sg:address":"5500 Admiral Blvd",
    "sg:city":"Delta",
    "sg:classifiers":[
        {
            "category":"Education",
            "subcategory":"School",
            "type":"Public Place"
        }
    ],
    "sg:phone":"+1 604 940 4468",
    "sg:postcode":"V4K 5B7",
    "sg:province":"BC",
    "wof:name":"Neilson Grove Elementary",
    "wof:placetype":"venue"
},
  "geometry": {"coordinates":[-123.073265076,49.1049995422],"type":"Point"}
}