{
  "type": "Feature",
  "properties": {
    "iso:country":"CA",
    "sg:address":"1708 Grey Nuns Dr",
    "sg:city":"Orleans",
    "sg:classifiers":[
        {
            "category":"Education",
            "subcategory":"School",
            "type":"Public Place"
        }
    ],
    "sg:phone":"+1 613 824 8177",
    "sg:postcode":"K1C 1C1",
    "sg:province":"ON",
    "wof:name":"Convent Glen Elementary School",
    "wof:placetype":"venue"
},
  "geometry": {"coordinates":[-75.5369796753,45.4694976807],"type":"Point"}
}