{
  "type": "Feature",
  "properties": {
    "iso:country":"CA",
    "sg:address":"209 Rue Child",
    "sg:city":"Coaticook",
    "sg:classifiers":[
        {
            "category":"Bars & Pubs",
            "type":"Food & Drink"
        }
    ],
    "sg:phone":"+1 819 849 9099",
    "sg:postcode":"J1A 2B5",
    "sg:province":"QC",
    "sg:tags":[
        "lounge",
        "cocktail"
    ],
    "wof:name":"Bar-Salon Les Quatre'As",
    "wof:placetype":"venue"
},
  "geometry": {"coordinates":[-71.80452728269999,45.1352806091],"type":"Point"}
}