{
  "type": "Feature",
  "properties": {
    "addr:full":"768 James St N Thunder Bay ON P7C 5N3",
    "addr:housenumber":"768",
    "addr:postcode":"p7c 5n3",
    "addr:street":"James St N",
    "iso:country":"CA",
    "sg:address":"768 James St N",
    "sg:city":"Thunder Bay",
    "sg:classifiers":[
        {
            "category":"Food & Beverages",
            "subcategory":"Groceries & Convenience Stores",
            "type":"Retail Goods"
        }
    ],
    "sg:phone":"+1 807 475 3601",
    "sg:postcode":"P7C 5N3",
    "sg:province":"ON",
    "wof:name":"College Park Variety",
    "wof:placetype":"venue"
},
  "geometry": {"coordinates":[-89.279343,48.400364],"type":"Point"}
}