{
  "type": "Feature",
  "properties": {
    "addr:full":"6796 Boul Temiscamingue Rouyn-Noranda QC J9Y 1N1",
    "addr:housenumber":"6796",
    "addr:postcode":"j9y 1n1",
    "addr:street":"Boul Temiscamingue",
    "iso:country":"CA",
    "sg:address":"6796 Boul Temiscamingue",
    "sg:city":"Rouyn-Noranda",
    "sg:classifiers":[
        {
            "category":"Food & Beverages",
            "subcategory":"Groceries & Convenience Stores",
            "type":"Retail Goods"
        }
    ],
    "sg:phone":"+1 819 797 5555",
    "sg:postcode":"J9Y 1N1",
    "sg:province":"QC",
    "sg:tags":[
        "grocer"
    ],
    "wof:name":"Epicerie Rivard Enr",
    "wof:placetype":"venue"
},
  "geometry": {"coordinates":[-79.1511459351,48.0929832458],"type":"Point"}
}