{
  "type": "Feature",
  "properties": {
    "addr:full":"653 Fennell Ave E Hamilton ON L8V 1T9",
    "addr:housenumber":"653",
    "addr:postcode":"l8v 1t9",
    "addr:street":"Fennell Ave E",
    "iso:country":"CA",
    "sg:address":"653 Fennell Ave E",
    "sg:city":"Hamilton",
    "sg:classifiers":[
        {
            "category":"Restaurant",
            "type":"Food & Drink"
        }
    ],
    "sg:phone":"+1 905 318 6818",
    "sg:postcode":"L8V 1T9",
    "sg:province":"ON",
    "wof:name":"Kwong Hing Restaurant",
    "wof:placetype":"venue"
},
  "geometry": {"coordinates":[-79.851067,43.231003],"type":"Point"}
}