{
  "type": "Feature",
  "properties": {
    "addr:full":"Upper Tantallon NS B3Z 1E3",
    "addr:postcode":"b3z 1e3",
    "iso:country":"CA",
    "sg:city":"Upper Tantallon",
    "sg:classifiers":[
        {
            "category":"Shopping",
            "subcategory":"Used Merchandise",
            "type":"Retail Goods"
        }
    ],
    "sg:phone":"+1 902 826 1565",
    "sg:postcode":"B3Z 1E3",
    "sg:province":"NS",
    "sg:tags":[
        "book",
        "rare",
        "dealer"
    ],
    "wof:name":"Books Galore & More",
    "wof:placetype":"venue"
},
  "geometry": {"coordinates":[-63.878632,44.688263],"type":"Point"}
}