{
  "type": "Feature",
  "properties": {
    "addr:full":"Browns Flat NB E5M 2P1",
    "addr:postcode":"e5m 2p1",
    "addr:street":"Nb",
    "iso:country":"CA",
    "sg:city":"Browns Flat",
    "sg:classifiers":[
        {
            "category":"Food & Beverages",
            "subcategory":"Groceries & Convenience Stores",
            "type":"Retail Goods"
        }
    ],
    "sg:phone":"+1 506 468 2200",
    "sg:postcode":"E5M 2P1",
    "sg:province":"NB",
    "wof:name":"Browns Flat Mainway",
    "wof:placetype":"venue"
},
  "geometry": {"coordinates":[-66.13275899999999,45.473072],"type":"Point"}
}