{
  "type": "Feature",
  "properties": {
    "addr:full":"89 Don St Clinton ON N0M 1L0",
    "addr:housenumber":"89",
    "addr:postcode":"n0m 1l0",
    "addr:street":"Don St",
    "iso:country":"CA",
    "sg:address":"89 Don St",
    "sg:city":"Clinton",
    "sg:classifiers":[
        {
            "category":"Freight",
            "type":"Transportation"
        }
    ],
    "sg:phone":"+1 519 482 3579",
    "sg:postcode":"N0M 1L0",
    "sg:province":"ON",
    "sg:tags":[
        "courier"
    ],
    "wof:name":"Shipco International Inc",
    "wof:placetype":"venue"
},
  "geometry": {"coordinates":[-81.5438461304,43.6238975525],"type":"Point"}
}