{
  "type": "Feature",
  "properties": {
    "iso:country":"CA",
    "sg:address":"10 Colborne St",
    "sg:city":"Fenelon Falls",
    "sg:classifiers":[
        {
            "category":"Cinema",
            "subcategory":"Movie Rental",
            "type":"Entertainment"
        }
    ],
    "sg:phone":"+1 705 887 3000",
    "sg:postcode":"K0M 1N0",
    "sg:province":"ON",
    "sg:tags":[
        "leasing",
        "video",
        "disc",
        "tape"
    ],
    "wof:name":"Video Image",
    "wof:placetype":"venue"
},
  "geometry": {"coordinates":[-78.73621368409999,44.5368804932],"type":"Point"}
}