{
  "type": "Feature",
  "properties": {
    "addr:full":"5011 137 Ave NW Edmonton AB T5A 5C5",
    "addr:housenumber":"5011",
    "addr:postcode":"t5a 5c5",
    "addr:street":"137 Ave Nw",
    "iso:country":"CA",
    "sg:address":"5011 137 Ave NW",
    "sg:city":"Edmonton",
    "sg:classifiers":[
        {
            "category":"Shopping",
            "subcategory":"Florist",
            "type":"Retail Goods"
        }
    ],
    "sg:phone":"+1 780 406 1073",
    "sg:postcode":"T5A 5C5",
    "sg:province":"AB",
    "wof:name":"Petals For Less Ltd",
    "wof:placetype":"venue"
},
  "geometry": {"coordinates":[-113.41658,53.597225],"type":"Point"}
}