{
  "type": "Feature",
  "properties": {
    "iso:country":"CA",
    "sg:address":"930 17 Ave SW",
    "sg:city":"Calgary",
    "sg:classifiers":[
        {
            "category":"Shopping",
            "subcategory":"Bicycles & Sporting Goods",
            "type":"Retail Goods"
        }
    ],
    "sg:phone":"+1 403 228 9112",
    "sg:postcode":"T2T 0A2",
    "sg:province":"AB",
    "sg:tags":[
        "equipment",
        "snowboard",
        "skateboard"
    ],
    "wof:name":"Source",
    "wof:placetype":"venue"
},
  "geometry": {"coordinates":[-114.082649231,51.0379371643],"type":"Point"}
}