{
  "type": "Feature",
  "properties": {
    "iso:country":"CA",
    "sg:address":"3520 Petawawa Blvd",
    "sg:city":"Petawawa",
    "sg:classifiers":[
        {
            "category":"Food & Beverages",
            "subcategory":"Groceries & Convenience Stores",
            "type":"Retail Goods"
        }
    ],
    "sg:phone":"+1 613 687 6940",
    "sg:postcode":"K8H 1W9",
    "sg:province":"ON",
    "sg:tags":[
        "grocer"
    ],
    "wof:name":"Pronto Food Mart",
    "wof:placetype":"venue"
},
  "geometry": {"coordinates":[-77.2846069336,45.9014625549],"type":"Point"}
}