{
  "type": "Feature",
  "properties": {
    "addr:full":"3078 Renfrew St Vancouver BC V5M 3K6",
    "addr:housenumber":"3078",
    "addr:postcode":"v5m 3k6",
    "addr:street":"Renfrew St",
    "iso:country":"CA",
    "sg:address":"3078 Renfrew St",
    "sg:city":"Vancouver",
    "sg:classifiers":[
        {
            "category":"Organizations",
            "subcategory":"Religious Organization",
            "type":"Services"
        }
    ],
    "sg:phone":"+1 604 434 6700",
    "sg:postcode":"V5M 3K6",
    "sg:province":"BC",
    "sg:tags":[
        "church"
    ],
    "wof:name":"St Jude's Parish & Shrine",
    "wof:placetype":"venue"
},
  "geometry": {"coordinates":[-123.044121,49.256569],"type":"Point"}
}