{
  "type": "Feature",
  "properties": {
    "addr:full":"3625 Montee Saint-Hubert Saint-Hubert QC J3Y 4J8",
    "addr:housenumber":"3625",
    "addr:postcode":"j3y 4j8",
    "addr:street":"Montee Saint-Hubert",
    "iso:country":"CA",
    "sg:address":"3625 Montee Saint-Hubert",
    "sg:city":"Saint-Hubert",
    "sg:classifiers":[
        {
            "category":"Education",
            "subcategory":"Library",
            "type":"Public Place"
        }
    ],
    "sg:phone":"+1 450 678 6038",
    "sg:postcode":"J3Y 4J8",
    "sg:province":"QC",
    "sg:tags":[
        "association"
    ],
    "wof:name":"Joujoutheque Parents-Secours",
    "wof:placetype":"venue"
},
  "geometry": {"coordinates":[-73.4287567139,45.4940109253],"type":"Point"}
}