{
  "type": "Feature",
  "properties": {
    "addr:full":"3441 Fieldgate Dr Mississauga ON L4X 2J4",
    "addr:housenumber":"3441",
    "addr:postcode":"l4x 2j4",
    "addr:street":"Fieldgate Dr",
    "iso:country":"CA",
    "sg:address":"3441 Fieldgate Dr",
    "sg:city":"Mississauga",
    "sg:classifiers":[
        {
            "category":"Shopping",
            "subcategory":"Discount & Variety Stores",
            "type":"Retail Goods"
        }
    ],
    "sg:phone":"+1 905 282 9226",
    "sg:postcode":"L4X 2J4",
    "sg:province":"ON",
    "wof:name":"Fieldgate Convenience",
    "wof:placetype":"venue"
},
  "geometry": {"coordinates":[-79.588943,43.623932],"type":"Point"}
}