{
  "type": "Feature",
  "properties": {
    "addr:full":"Montreal QC H2H 2S6",
    "addr:postcode":"h2h 2s6",
    "iso:country":"CA",
    "sg:city":"Montreal",
    "sg:classifiers":[
        {
            "category":"Professional",
            "subcategory":"Research",
            "type":"Services"
        }
    ],
    "sg:phone":"+1 514 529 5870",
    "sg:postcode":"H2H 2S6",
    "sg:province":"QC",
    "sg:tags":[
        "environmental",
        "ecological"
    ],
    "wof:name":"Groupe Gesfor Poirier Pinchin",
    "wof:placetype":"venue"
},
  "geometry": {"coordinates":[-73.217377,45.281342],"type":"Point"}
}