{
  "type": "Feature",
  "properties": {
    "iso:country":"CA",
    "sg:address":"1318 Boul Mont-Royal",
    "sg:city":"Outremont",
    "sg:classifiers":[
        {
            "category":"Food & Beverages",
            "subcategory":"Specialty",
            "type":"Retail Goods"
        }
    ],
    "sg:phone":"+1 514 526 1116",
    "sg:postcode":"H2V 2J1",
    "sg:province":"QC",
    "sg:tags":[
        "gourmet",
        "shop"
    ],
    "wof:name":"Saum-Mom",
    "wof:placetype":"venue"
},
  "geometry": {"coordinates":[-73.603409,45.511753],"type":"Point"}
}