{
  "type": "Feature",
  "properties": {
    "addr:full":"1056 Bloor St W Toronto ON M6H 1M3",
    "addr:housenumber":"1056",
    "addr:postcode":"m6h 1m3",
    "addr:street":"Bloor St W",
    "iso:country":"CA",
    "sg:address":"1056 Bloor St W",
    "sg:city":"Toronto",
    "sg:classifiers":[
        {
            "category":"Education",
            "subcategory":"Dance Studio",
            "type":"Public Place"
        }
    ],
    "sg:phone":"+1 416 537 4415",
    "sg:postcode":"M6H 1M3",
    "sg:province":"ON",
    "sg:tags":[
        "instruction",
        "dancing"
    ],
    "wof:name":"Strickly Salsa",
    "wof:placetype":"venue"
},
  "geometry": {"coordinates":[-79.432709,43.660545],"type":"Point"}
}