{
  "type": "Feature",
  "properties": {
    "addr:full":"PO Box 117 Ernfold SK S0H 1K0",
    "addr:housenumber":"po",
    "addr:postcode":"s0h 1k0",
    "addr:street":"Box 117",
    "iso:country":"CA",
    "sg:address":"PO Box 117",
    "sg:city":"Ernfold",
    "sg:classifiers":[
        {
            "category":"Building & Trades",
            "subcategory":"Plumbing",
            "type":"Services"
        }
    ],
    "sg:phone":"+1 306 629 3292",
    "sg:postcode":"S0H 1K0",
    "sg:province":"SK",
    "sg:tags":[
        "tank",
        "septic",
        "contractor"
    ],
    "wof:name":"Gene Bauck Enterprises",
    "wof:placetype":"venue"
},
  "geometry": {"coordinates":[-106.89563751199999,50.4466590881],"type":"Point"}
}