{
  "type": "Feature",
  "properties": {
    "addr:full":"Sainte-Foy QC G1X 4Y5",
    "addr:postcode":"g1x 4y5",
    "iso:country":"CA",
    "sg:city":"Sainte-Foy",
    "sg:classifiers":[
        {
            "category":"Travel",
            "subcategory":"Travel Agent",
            "type":"Entertainment"
        }
    ],
    "sg:phone":"+1 418 877 8070",
    "sg:postcode":"G1X 4Y5",
    "sg:province":"QC",
    "sg:tags":[
        "agency",
        "bureau"
    ],
    "wof:name":"Agence DE Voyages Fleury Inc",
    "wof:placetype":"venue"
},
  "geometry": {"coordinates":[-71.3688735962,46.7657165527],"type":"Point"}
}