{
  "type": "Feature",
  "properties": {
    "addr:full":"3160 Alps Rd Ayr ON N0B 1E0",
    "addr:housenumber":"3160",
    "addr:postcode":"n0b 1e0",
    "addr:street":"Alps Rd",
    "iso:country":"CA",
    "sg:address":"3160 Alps Rd",
    "sg:city":"Ayr",
    "sg:classifiers":[
        {
            "category":"Manufacturing",
            "subcategory":"Tools & Machinery",
            "type":"Manufacturing & Wholesale Goods"
        }
    ],
    "sg:phone":"+1 519 632 8998",
    "sg:postcode":"N0B 1E0",
    "sg:province":"ON",
    "sg:tags":[
        "farm",
        "equipment"
    ],
    "wof:name":"Agraturf Equipment Svc Inc",
    "wof:placetype":"venue"
},
  "geometry": {"coordinates":[-80.4689254761,43.3128356934],"type":"Point"}
}