{
  "type": "Feature",
  "properties": {
    "iso:country":"CA",
    "sg:address":"1385 Rue Du Grand-Bourg",
    "sg:city":"Val-Belair",
    "sg:classifiers":[
        {
            "category":"Taxi",
            "type":"Transportation"
        }
    ],
    "sg:phone":"+1 418 845 4178",
    "sg:postcode":"G3J 1J3",
    "sg:province":"QC",
    "sg:tags":[
        "taxicab"
    ],
    "wof:name":"Taxi Concept Enr",
    "wof:placetype":"venue"
},
  "geometry": {"coordinates":[-71.436836,46.863079],"type":"Point"}
}