{
  "type": "Feature",
  "properties": {
    "addr:full":"3885 Boul Marie-Victorin Nicolet QC J3T 1T7",
    "addr:housenumber":"3885",
    "addr:postcode":"j3t 1t7",
    "addr:street":"Boul Marie-Victorin",
    "iso:country":"CA",
    "sg:address":"3885 Boul Marie-Victorin",
    "sg:city":"Nicolet",
    "sg:classifiers":[
        {
            "category":"Building & Trades",
            "subcategory":"Construction",
            "type":"Services"
        }
    ],
    "sg:phone":"+1 819 293 6921",
    "sg:postcode":"J3T 1T7",
    "sg:province":"QC",
    "sg:tags":[
        "general",
        "contractor"
    ],
    "wof:name":"Construction G Therrien Inc",
    "wof:placetype":"venue"
},
  "geometry": {"coordinates":[-72.65934799999999,46.182579],"type":"Point"}
}