{
  "type": "Feature",
  "properties": {
    "addr:full":"50 Levendale Rd Richmond Hill ON L4C 4H2",
    "addr:housenumber":"50",
    "addr:postcode":"l4c 4h2",
    "addr:street":"Levendale Rd",
    "iso:country":"CA",
    "sg:address":"50 Levendale Rd",
    "sg:city":"Richmond Hill",
    "sg:classifiers":[
        {
            "category":"Wholesale",
            "subcategory":"Electrical",
            "type":"Manufacturing & Wholesale Goods"
        }
    ],
    "sg:phone":"+1 905 737 0212",
    "sg:postcode":"L4C 4H2",
    "sg:province":"ON",
    "sg:tags":[
        "control",
        "security",
        "system"
    ],
    "wof:name":"Bilco Alarms",
    "wof:placetype":"venue"
},
  "geometry": {"coordinates":[-79.4421157837,43.8820724487],"type":"Point"}
}