{
  "type": "Feature",
  "properties": {
    "addr:full":"5455 Boul Decarie Montreal QC H3W 3C6",
    "addr:housenumber":"5455",
    "addr:postcode":"h3w 3c6",
    "addr:street":"Boul Decarie",
    "iso:country":"CA",
    "sg:address":"5455 Boul Decarie",
    "sg:city":"Montreal",
    "sg:classifiers":[
        {
            "category":"Autos & Motor Vehicles",
            "subcategory":"Fuel & Gas Station",
            "type":"Retail Goods"
        }
    ],
    "sg:phone":"+1 514 483 0061",
    "sg:postcode":"H3W 3C6",
    "sg:province":"QC",
    "sg:tags":[
        "oil"
    ],
    "wof:name":"Ultramar",
    "wof:placetype":"venue"
},
  "geometry": {"coordinates":[-73.63427,45.486271],"type":"Point"}
}