{
  "type": "Feature",
  "properties": {
    "iso:country":"CA",
    "sg:city":"Contrecoeur",
    "sg:classifiers":[
        {
            "category":"Food & Beverages",
            "subcategory":"Bakery",
            "type":"Retail Goods"
        }
    ],
    "sg:phone":"+1 450 587 8225",
    "sg:postcode":"J0L 1C0",
    "sg:province":"QC",
    "sg:tags":[
        "baker"
    ],
    "wof:name":"Patisserie Ann Enr",
    "wof:placetype":"venue"
},
  "geometry": {"coordinates":[-73.2386627197,45.8577957153],"type":"Point"}
}