{
  "type": "Feature",
  "properties": {
    "addr:full":"8731 118 Ave NW Edmonton AB T5B 0T2",
    "addr:housenumber":"8731",
    "addr:postcode":"t5b 0t2",
    "addr:street":"118 Ave Nw",
    "iso:country":"CA",
    "sg:address":"8731 118 Ave NW",
    "sg:city":"Edmonton",
    "sg:classifiers":[
        {
            "category":"Retail",
            "subcategory":"Auto Repair",
            "type":"Services"
        }
    ],
    "sg:phone":"+1 780 477 1089",
    "sg:postcode":"T5B 0T2",
    "sg:province":"AB",
    "sg:tags":[
        "repairing",
        "automobile",
        "parts",
        "supply"
    ],
    "wof:name":"E C Automotive Machining Ltd",
    "wof:placetype":"venue"
},
  "geometry": {"coordinates":[-113.47590599999999,53.570293],"type":"Point"}
}