{
  "type": "Feature",
  "properties": {
    "addr:full":"Kakabeka Falls ON P0T 1W0",
    "addr:postcode":"p0t 1w0",
    "addr:street":"Kakabeka Falls",
    "iso:country":"CA",
    "sg:city":"Kakabeka Falls",
    "sg:classifiers":[
        {
            "category":"Retail",
            "subcategory":"Auto Repair",
            "type":"Services"
        }
    ],
    "sg:phone":"+1 807 473 9172",
    "sg:postcode":"P0T 1W0",
    "sg:province":"ON",
    "sg:tags":[
        "repairing",
        "automobile"
    ],
    "wof:name":"Kakabeka Esso",
    "wof:placetype":"venue"
},
  "geometry": {"coordinates":[-89.614586,48.401608],"type":"Point"}
}