{
  "type": "Feature",
  "properties": {
    "addr:full":"1701 Rue Principale Saint-Jean-Des-Piles QC G0X 2V0",
    "addr:housenumber":"1701",
    "addr:postcode":"g0x 2v0",
    "addr:street":"Rue Principale",
    "iso:country":"CA",
    "sg:address":"1701 Rue Principale",
    "sg:city":"Saint-Jean-Des-Piles",
    "sg:classifiers":[
        {
            "category":"Travel",
            "subcategory":"Hotels & Motels",
            "type":"Entertainment"
        }
    ],
    "sg:phone":"+1 819 538 9883",
    "sg:postcode":"G0X 2V0",
    "sg:province":"QC",
    "wof:name":"Restaurant LA Maison Cadorette",
    "wof:placetype":"venue"
},
  "geometry": {"coordinates":[-72.74215700000001,46.693363],"type":"Point"}
}