{
  "type": "Feature",
  "properties": {
    "addr:full":"109 Mtee Lortie Beaux-Rivages QC J0W 1H0",
    "addr:housenumber":"109",
    "addr:postcode":"j0w 1h0",
    "addr:street":"Mtee Lortie Beaux-Rivages",
    "iso:country":"CA",
    "sg:address":"109 Mtee Lortie",
    "sg:city":"Beaux-Rivages",
    "sg:classifiers":[
        {
            "category":"Home & Garden",
            "subcategory":"Carpets & Floor Coverings",
            "type":"Retail Goods"
        }
    ],
    "sg:phone":"+1 819 585 4655",
    "sg:postcode":"J0W 1H0",
    "sg:province":"QC",
    "sg:tags":[
        "dealer",
        "rug"
    ],
    "wof:name":"L'Entreprise Pere & Fils",
    "wof:placetype":"venue"
},
  "geometry": {"coordinates":[-75.3573303223,46.555896759],"type":"Point"}
}