{
  "type": "Feature",
  "properties": {
    "addr:full":"1102 Fort St Victoria BC V8V 3K8",
    "addr:housenumber":"1102",
    "addr:postcode":"v8v 3k8",
    "addr:street":"Fort St",
    "iso:country":"CA",
    "sg:address":"1102 Fort St",
    "sg:city":"Victoria",
    "sg:classifiers":[
        {
            "category":"Parking",
            "type":"Transportation"
        }
    ],
    "sg:phone":"+1 250 382 4411",
    "sg:postcode":"V8V 3K8",
    "sg:province":"BC",
    "sg:tags":[
        "garage"
    ],
    "wof:name":"Robbins Parking Svc Ltd",
    "wof:placetype":"venue"
},
  "geometry": {"coordinates":[-123.353614807,48.4234771729],"type":"Point"}
}