{
  "type": "Feature",
  "properties": {
    "iso:country":"CA",
    "sg:address":"22 Rue Des Flandres",
    "sg:city":"Gatineau",
    "sg:classifiers":[
        {
            "category":"Shopping",
            "subcategory":"Tobacco",
            "type":"Retail Goods"
        }
    ],
    "sg:phone":"+1 819 568 5050",
    "sg:postcode":"J8T 4R7",
    "sg:province":"QC",
    "sg:tags":[
        "cigarette",
        "cigar",
        "dealer"
    ],
    "wof:name":"Tabagie Riviera",
    "wof:placetype":"venue"
},
  "geometry": {"coordinates":[-75.7190246582,45.4708518982],"type":"Point"}
}