{
  "type": "Feature",
  "properties": {
    "addr:full":"19569 Fraser Hwy Surrey BC V3S 6K7",
    "addr:housenumber":"19569",
    "addr:postcode":"v3s 6k7",
    "addr:street":"Fraser Hwy",
    "iso:country":"CA",
    "sg:address":"19569 Fraser Hwy",
    "sg:city":"Surrey",
    "sg:classifiers":[
        {
            "category":"Personal",
            "subcategory":"Beauty Salon",
            "type":"Services"
        }
    ],
    "sg:phone":"+1 604 533 4441",
    "sg:postcode":"V3S 6K7",
    "sg:province":"BC",
    "wof:name":"Colour Tech II Hair Studio",
    "wof:placetype":"venue"
},
  "geometry": {"coordinates":[-122.680381775,49.1143264771],"type":"Point"}
}