{
  "type": "Feature",
  "properties": {
    "addr:full":"Winnipeg MB R3H 0X4",
    "addr:postcode":"r3h 0x4",
    "iso:country":"CA",
    "sg:city":"Winnipeg",
    "sg:classifiers":[
        {
            "category":"Wholesale",
            "subcategory":"Scrap",
            "type":"Manufacturing & Wholesale Goods"
        }
    ],
    "sg:phone":"+1 204 632 5255",
    "sg:postcode":"R3H 0X4",
    "sg:province":"MB",
    "sg:tags":[
        "recycling",
        "center"
    ],
    "wof:name":"Manitoba Association For Rsrc",
    "wof:placetype":"venue"
},
  "geometry": {"coordinates":[-97.2014007568,49.9110298157],"type":"Point"}
}