{
  "type": "Feature",
  "properties": {
    "addr:full":"4010 Loyalist Dr Mississauga ON L5L 3Y6",
    "addr:housenumber":"4010",
    "addr:postcode":"l5l 3y6",
    "addr:street":"Loyalist Dr",
    "iso:country":"CA",
    "sg:address":"4010 Loyalist Dr",
    "sg:city":"Mississauga",
    "sg:classifiers":[
        {
            "category":"Organizations",
            "subcategory":"Religious Organization",
            "type":"Services"
        }
    ],
    "sg:phone":"+1 905 569 3800",
    "sg:postcode":"L5L 3Y6",
    "sg:province":"ON",
    "sg:tags":[
        "church"
    ],
    "wof:name":"Iglesia Ni Cristo",
    "wof:placetype":"venue"
},
  "geometry": {"coordinates":[-79.70471999999999,43.533432],"type":"Point"}
}