{
  "type": "Feature",
  "properties": {
    "addr:full":"26 3rd St S Weyburn SK S4H 2B8",
    "addr:housenumber":"26",
    "addr:postcode":"s4h 2b8",
    "addr:street":"3Rd St S",
    "iso:country":"CA",
    "sg:address":"26 3rd St S",
    "sg:city":"Weyburn",
    "sg:classifiers":[
        {
            "category":"Wholesale",
            "subcategory":"Farm Supplies",
            "type":"Manufacturing & Wholesale Goods"
        }
    ],
    "sg:phone":"+1 306 842 5476",
    "sg:postcode":"S4H 2B8",
    "sg:province":"SK",
    "sg:tags":[
        "feed"
    ],
    "wof:name":"CO-OP Feeds Ltd",
    "wof:placetype":"venue"
},
  "geometry": {"coordinates":[-103.85456085200001,49.6582260132],"type":"Point"}
}