{
  "type": "Feature",
  "properties": {
    "addr:full":"1843 Paris St Sudbury ON P3E 3C5",
    "addr:housenumber":"1843",
    "addr:postcode":"p3e 3c5",
    "addr:street":"Paris St",
    "iso:country":"CA",
    "sg:address":"1843 Paris St",
    "sg:city":"Sudbury",
    "sg:classifiers":[
        {
            "category":"Organizations",
            "subcategory":"Religious Organization",
            "type":"Services"
        }
    ],
    "sg:phone":"+1 705 522 2164",
    "sg:postcode":"P3E 3C5",
    "sg:province":"ON",
    "sg:tags":[
        "church"
    ],
    "wof:name":"Finnish Pentecostal Church",
    "wof:placetype":"venue"
},
  "geometry": {"coordinates":[-81.0020065308,46.4544944763],"type":"Point"}
}