{
  "type": "Feature",
  "properties": {
    "addr:full":"383 St Laurent Ave Quesnel BC V2J 2E1",
    "addr:housenumber":"383",
    "addr:postcode":"v2j 2e1",
    "addr:street":"St Laurent Ave",
    "iso:country":"CA",
    "sg:address":"383 St Laurent Ave",
    "sg:city":"Quesnel",
    "sg:classifiers":[
        {
            "category":"Travel",
            "subcategory":"Hotels & Motels",
            "type":"Entertainment"
        }
    ],
    "sg:phone":"+1 250 992 5575",
    "sg:postcode":"V2J 2E1",
    "sg:province":"BC",
    "sg:tags":[
        "resort"
    ],
    "wof:name":"Ramada Limited",
    "wof:placetype":"venue"
},
  "geometry": {"coordinates":[-122.49412536600001,52.9792404175],"type":"Point"}
}