{
  "type": "Feature",
  "properties": {
    "addr:full":"39 Kennedy Rd N Brampton ON L6V 1X6",
    "addr:housenumber":"39",
    "addr:postcode":"l6v 1x6",
    "addr:street":"Kennedy Rd N",
    "iso:country":"CA",
    "sg:address":"39 Kennedy Rd N",
    "sg:city":"Brampton",
    "sg:classifiers":[
        {
            "category":"Wholesale",
            "subcategory":"Machinery & Supplies",
            "type":"Manufacturing & Wholesale Goods"
        }
    ],
    "sg:phone":"+1 905 455 8042",
    "sg:postcode":"L6V 1X6",
    "sg:province":"ON",
    "sg:tags":[
        "salon",
        "beauty"
    ],
    "wof:name":"Afro Beauty Supplies Inc",
    "wof:placetype":"venue"
},
  "geometry": {"coordinates":[-79.75148799999999,43.696938],"type":"Point"}
}