{
  "type": "Feature",
  "properties": {
    "addr:full":"PO Box 74036 Rpo Pepper Tree Edmonton AB T5K 2S7",
    "addr:housenumber":"po box",
    "addr:postcode":"74036;t5k 2s7",
    "iso:country":"CA",
    "sg:address":"PO Box 74036 Rpo Pepper Tree",
    "sg:city":"Edmonton",
    "sg:classifiers":[
        {
            "category":"Organizations",
            "subcategory":"Professional Association",
            "type":"Services"
        }
    ],
    "sg:phone":"+1 780 463 0892",
    "sg:postcode":"T5K 2S7",
    "sg:province":"AB",
    "wof:name":"Gamblers Anonymous",
    "wof:placetype":"venue"
},
  "geometry": {"coordinates":[-113.490371704,53.5462188721],"type":"Point"}
}