{
  "type": "Feature",
  "properties": {
    "addr:full":"5680 Fraser St Vancouver BC V5W 2Z4",
    "addr:housenumber":"5680",
    "addr:postcode":"v5w 2z4",
    "addr:street":"Fraser St",
    "iso:country":"CA",
    "sg:address":"5680 Fraser St",
    "sg:city":"Vancouver",
    "sg:classifiers":[
        {
            "category":"Food & Beverages",
            "subcategory":"Groceries & Convenience Stores",
            "type":"Retail Goods"
        }
    ],
    "sg:phone":"+1 604 324 2473",
    "sg:postcode":"V5W 2Z4",
    "sg:province":"BC",
    "sg:tags":[
        "grocer"
    ],
    "wof:name":"Early Bird Foodmart",
    "wof:placetype":"venue"
},
  "geometry": {"coordinates":[-123.090332,49.233261],"type":"Point"}
}