{
  "type": "Feature",
  "properties": {
    "addr:full":"10445 1E Av Saint-Georges QC G5Y 6X8",
    "addr:housenumber":"10445",
    "addr:postcode":"g5y 6x8",
    "addr:street":"1E Av",
    "iso:country":"CA",
    "sg:address":"10445 1E Av",
    "sg:city":"Saint-Georges",
    "sg:classifiers":[
        {
            "category":"Health Services",
            "subcategory":"Doctor",
            "type":"Services"
        }
    ],
    "sg:phone":"+1 418 228 2899",
    "sg:postcode":"G5Y 6X8",
    "sg:province":"QC",
    "sg:tags":[
        "clinic"
    ],
    "wof:name":"Clinique DE Chirurgie Orthoped",
    "wof:placetype":"venue"
},
  "geometry": {"coordinates":[-70.67115020750001,46.1233482361],"type":"Point"}
}