{
  "type": "Feature",
  "properties": {
    "addr:full":"4400 Boul Kimber Saint-Hubert QC J3Y 8L4",
    "addr:housenumber":"4400",
    "addr:postcode":"j3y 8l4",
    "addr:street":"Boul Kimber",
    "iso:country":"CA",
    "sg:address":"4400 Boul Kimber",
    "sg:city":"Saint-Hubert",
    "sg:classifiers":[
        {
            "category":"Wholesale",
            "subcategory":"Machinery & Supplies",
            "type":"Manufacturing & Wholesale Goods"
        }
    ],
    "sg:phone":"+1 450 678 3231",
    "sg:postcode":"J3Y 8L4",
    "sg:province":"QC",
    "sg:tags":[
        "equipment",
        "cosmetic",
        "manicure"
    ],
    "wof:name":"Summum Beaute Intl Inc",
    "wof:placetype":"venue"
},
  "geometry": {"coordinates":[-73.4482955933,45.4988250732],"type":"Point"}
}