{
  "type": "Feature",
  "properties": {
    "addr:full":"Crapaud PE C0A 1J0",
    "addr:postcode":"c0a 1j0",
    "iso:country":"CA",
    "sg:city":"Crapaud",
    "sg:classifiers":[
        {
            "category":"Building & Trades",
            "subcategory":"Plumbing",
            "type":"Services"
        }
    ],
    "sg:phone":"+1 902 658 2152",
    "sg:postcode":"C0A 1J0",
    "sg:province":"PE",
    "sg:tags":[
        "contractor"
    ],
    "wof:name":"Mac Kinnon's Quality Plumbing",
    "wof:placetype":"venue"
},
  "geometry": {"coordinates":[-63.500244,46.239925],"type":"Point"}
}