{
  "type": "Feature",
  "properties": {
    "addr:full":"120 5 St SW Turner Valley AB T0L 2A0",
    "addr:housenumber":"120 5",
    "addr:postcode":"t0l 2a0",
    "addr:street":"St Sw",
    "iso:country":"CA",
    "sg:address":"120 5 St SW",
    "sg:city":"Turner Valley",
    "sg:classifiers":[
        {
            "category":"Government",
            "subcategory":"Fire Station",
            "type":"Public Place"
        }
    ],
    "sg:phone":"+1 403 933 9111",
    "sg:postcode":"T0L 2A0",
    "sg:province":"AB",
    "sg:tags":[
        "department"
    ],
    "wof:name":"Black Diamond Fire Alarm",
    "wof:placetype":"venue"
},
  "geometry": {"coordinates":[-114.27887725799999,50.6748161316],"type":"Point"}
}