{
  "type": "Feature",
  "properties": {
    "addr:full":"Gloucester ON K1B 5R2",
    "addr:postcode":"k1b 5r2",
    "iso:country":"CA",
    "sg:city":"Gloucester",
    "sg:classifiers":[
        {
            "category":"Freight",
            "type":"Transportation"
        }
    ],
    "sg:phone":"+1 613 824 0431",
    "sg:postcode":"K1B 5R2",
    "sg:province":"ON",
    "sg:tags":[
        "commercial",
        "storage"
    ],
    "wof:name":"Orleans Storage Inc",
    "wof:placetype":"venue"
},
  "geometry": {"coordinates":[-75.565361,45.432835],"type":"Point"}
}