{
  "type": "Feature",
  "properties": {
    "iso:country":"CA",
    "sg:address":"5670 Timberlea Blvd",
    "sg:city":"Mississauga",
    "sg:classifiers":[
        {
            "category":"Retail",
            "subcategory":"Auto Repair",
            "type":"Services"
        }
    ],
    "sg:phone":"+1 905 502 9882",
    "sg:postcode":"L4W 4M6",
    "sg:province":"ON",
    "sg:tags":[
        "automobile",
        "customizing"
    ],
    "wof:name":"Dealer Extras Mobile Svc",
    "wof:placetype":"venue"
},
  "geometry": {"coordinates":[-79.651222229,43.6370544434],"type":"Point"}
}