{
  "type": "Feature",
  "properties": {
    "iso:country":"CA",
    "sg:address":"4227 Sheppard Ave E",
    "sg:city":"Scarborough",
    "sg:classifiers":[
        {
            "category":"Travel",
            "subcategory":"Travel Agent",
            "type":"Entertainment"
        }
    ],
    "sg:phone":"+1 416 292 2887",
    "sg:postcode":"M1S 5H5",
    "sg:province":"ON",
    "sg:tags":[
        "agency",
        "bureau"
    ],
    "wof:name":"Confidence Travel",
    "wof:placetype":"venue"
},
  "geometry": {"coordinates":[-79.2779159546,43.7853431702],"type":"Point"}
}