{
  "type": "Feature",
  "properties": {
    "addr:full":"2455 Av Letourneux Montreal QC H1V 2N9",
    "addr:housenumber":"2455",
    "addr:postcode":"h1v 2n9",
    "addr:street":"Av Letourneux",
    "iso:country":"CA",
    "sg:address":"2455 Av Letourneux",
    "sg:city":"Montreal",
    "sg:classifiers":[
        {
            "category":"Education",
            "subcategory":"School",
            "type":"Public Place"
        }
    ],
    "sg:phone":"+1 514 596 4949",
    "sg:postcode":"H1V 2N9",
    "sg:province":"QC",
    "wof:name":"Ecole Eulalie-Durocher",
    "wof:placetype":"venue"
},
  "geometry": {"coordinates":[-73.5464172363,45.554813385],"type":"Point"}
}