{
  "type": "Feature",
  "properties": {
    "addr:full":"287 Rue Victoria Thurso QC J0X 3B0",
    "addr:housenumber":"287",
    "addr:postcode":"j0x 3b0",
    "addr:street":"Rue Victoria",
    "iso:country":"CA",
    "sg:address":"287 Rue Victoria",
    "sg:city":"Thurso",
    "sg:classifiers":[
        {
            "category":"Personal",
            "subcategory":"Shoe Repair & Shine",
            "type":"Services"
        }
    ],
    "sg:phone":"+1 819 985 0325",
    "sg:postcode":"J0X 3B0",
    "sg:province":"QC",
    "sg:tags":[
        "repairing",
        "boot"
    ],
    "wof:name":"Cordonnerie LA Bottine Enr",
    "wof:placetype":"venue"
},
  "geometry": {"coordinates":[-75.240807,45.597435],"type":"Point"}
}