{
  "type": "Feature",
  "properties": {
    "addr:full":"72 Brant Ave Brantford ON N3T 5Z8",
    "addr:housenumber":"72",
    "addr:postcode":"n3t 5z8",
    "addr:street":"Brant Ave",
    "iso:country":"CA",
    "sg:address":"72 Brant Ave",
    "sg:city":"Brantford",
    "sg:classifiers":[
        {
            "category":"Health Services",
            "subcategory":"Medical Lab",
            "type":"Services"
        }
    ],
    "sg:phone":"+1 519 759 7460",
    "sg:postcode":"N3T 5Z8",
    "sg:province":"ON",
    "sg:tags":[
        "laboratory"
    ],
    "wof:name":"Canadian Medical Laboratories",
    "wof:placetype":"venue"
},
  "geometry": {"coordinates":[-80.2714309692,43.1410942078],"type":"Point"}
}