{
  "type": "Feature",
  "properties": {
    "iso:country":"CA",
    "sg:address":"185-911 Yates St. Suite 358",
    "sg:city":"Victoria, BC",
    "sg:classifiers":[
        {
            "category":"Professional",
            "subcategory":"Computer Services",
            "type":"Services"
        }
    ],
    "sg:postcode":"V8V 4Y9",
    "sg:website":"http://www.devicedoctor.com",
    "wof:name":"Device Doctor Software",
    "wof:placetype":"venue"
},
  "geometry": {"coordinates":[-123.35897900000001,48.4256221],"type":"Point"}
}