{
  "type": "Feature",
  "properties": {
    "addr:full":"261 Fischer Ave The Pas MB R9A 1L3",
    "addr:housenumber":"261",
    "addr:postcode":"r9a 1l3",
    "addr:street":"Fischer Ave",
    "iso:country":"CA",
    "sg:address":"261 Fischer Ave",
    "sg:city":"The Pas",
    "sg:classifiers":[
        {
            "category":"Banks & Credit Unions",
            "subcategory":"Bank",
            "type":"Services"
        }
    ],
    "sg:phone":"+1 204 627 6300",
    "sg:postcode":"R9A 1L3",
    "sg:province":"MB",
    "wof:name":"Westoba Credit Union Ltd",
    "wof:placetype":"venue"
},
  "geometry": {"coordinates":[-101.2526474,53.8233184814],"type":"Point"}
}