{
  "type": "Feature",
  "properties": {
    "addr:full":"65 6th Ave Englehart ON P0J 1H0",
    "addr:housenumber":"65",
    "addr:postcode":"p0j 1h0",
    "addr:street":"6Th Ave",
    "iso:country":"CA",
    "sg:address":"65 6th Ave",
    "sg:city":"Englehart",
    "sg:classifiers":[
        {
            "category":"Government",
            "subcategory":"Office",
            "type":"Public Place"
        }
    ],
    "sg:phone":"+1 705 563 2062",
    "sg:postcode":"P0J 1H0",
    "sg:province":"ON",
    "sg:tags":[
        "village"
    ],
    "wof:name":"Ontario Logement Dept",
    "wof:placetype":"venue"
},
  "geometry": {"coordinates":[-79.87488555909999,47.8237915039],"type":"Point"}
}