{
  "type": "Feature",
  "properties": {
    "addr:full":"4728 50th Ave Redwater AB T0A 2W0",
    "addr:housenumber":"4728",
    "addr:postcode":"t0a 2w0",
    "addr:street":"50Th Ave",
    "iso:country":"CA",
    "sg:address":"4728 50th Ave",
    "sg:city":"Redwater",
    "sg:classifiers":[
        {
            "category":"Professional",
            "subcategory":"Lawyer & Legal Services",
            "type":"Services"
        }
    ],
    "sg:phone":"+1 780 942 2880",
    "sg:postcode":"T0A 2W0",
    "sg:province":"AB",
    "sg:tags":[
        "attorney"
    ],
    "wof:name":"Biamonte Cairo & Shortreed",
    "wof:placetype":"venue"
},
  "geometry": {"coordinates":[-113.107460022,53.9523200989],"type":"Point"}
}