{
  "type": "Feature",
  "properties": {
    "addr:full":"159 Ottawa Ave W Morris MB R0G 1K0",
    "addr:housenumber":"159",
    "addr:postcode":"r0g 1k0",
    "addr:street":"Ottawa Ave W",
    "iso:country":"CA",
    "sg:address":"159 Ottawa Ave W",
    "sg:city":"Morris",
    "sg:classifiers":[
        {
            "category":"Organizations",
            "subcategory":"Religious Organization",
            "type":"Services"
        }
    ],
    "sg:phone":"+1 204 746 2508",
    "sg:postcode":"R0G 1K0",
    "sg:province":"MB",
    "sg:tags":[
        "church"
    ],
    "wof:name":"Morris Mennonite Church",
    "wof:placetype":"venue"
},
  "geometry": {"coordinates":[-97.366043,49.353733],"type":"Point"}
}