{
  "type": "Feature",
  "properties": {
    "addr:full":"60 Halifax St Moncton NB E1C 9R9",
    "addr:housenumber":"60",
    "addr:postcode":"e1c 9r9",
    "addr:street":"Halifax St",
    "iso:country":"CA",
    "sg:address":"60 Halifax St",
    "sg:city":"Moncton",
    "sg:classifiers":[
        {
            "category":"Manufacturing",
            "subcategory":"Signs",
            "type":"Manufacturing & Wholesale Goods"
        }
    ],
    "sg:phone":"+1 506 859 7600",
    "sg:postcode":"E1C 9R9",
    "sg:province":"NB",
    "wof:name":"Hansen Signs",
    "wof:placetype":"venue"
},
  "geometry": {"coordinates":[-64.80480194090001,46.0951499939],"type":"Point"}
}