{
  "type": "Feature",
  "properties": {
    "iso:country":"CA",
    "sg:address":"700 Place Leigh-Capreol",
    "sg:city":"Dorval",
    "sg:classifiers":[
        {
            "category":"Professional",
            "subcategory":"Management & Consulting",
            "type":"Services"
        }
    ],
    "sg:phone":"+1 514 636 5207",
    "sg:postcode":"H4Y 1G7",
    "sg:province":"QC",
    "sg:tags":[
        "food"
    ],
    "wof:name":"Laliberte & Assoc Inc",
    "wof:placetype":"venue"
},
  "geometry": {"coordinates":[-73.751396,45.454407],"type":"Point"}
}