{
  "type": "Feature",
  "properties": {
    "addr:full":"7 Rue DE LA Mary Gaspe QC G4X 5E9",
    "addr:housenumber":"7",
    "addr:postcode":"g4x 5e9",
    "addr:street":"Rue De La Mary",
    "iso:country":"CA",
    "sg:address":"7 Rue DE LA Mary",
    "sg:city":"Gaspe",
    "sg:classifiers":[
        {
            "category":"Recreation",
            "subcategory":"Marina",
            "type":"Entertainment"
        }
    ],
    "sg:phone":"+1 418 269 3222",
    "sg:postcode":"G4X 5E9",
    "sg:province":"QC",
    "sg:tags":[
        "repairing",
        "boat"
    ],
    "wof:name":"Electro Demarreur",
    "wof:placetype":"venue"
},
  "geometry": {"coordinates":[-64.3836517334,48.9940071106],"type":"Point"}
}