{
  "type": "Feature",
  "properties": {
    "addr:full":"4540 Manilla Rd SE Calgary AB T2G 4B7",
    "addr:postcode":"4540;t2g 4b7",
    "addr:street":"Manilla Rd Se",
    "iso:country":"CA",
    "sg:address":"4540 Manilla Rd SE",
    "sg:city":"Calgary",
    "sg:classifiers":[
        {
            "category":"Manufacturing",
            "subcategory":"Printing",
            "type":"Manufacturing & Wholesale Goods"
        }
    ],
    "sg:phone":"+1 403 287 2996",
    "sg:postcode":"T2G 4B7",
    "sg:province":"AB",
    "sg:tags":[
        "printer"
    ],
    "wof:name":"Percy's Printing Ltd",
    "wof:placetype":"venue"
},
  "geometry": {"coordinates":[-114.051125,51.013664],"type":"Point"}
}