{
  "type": "Feature",
  "properties": {
    "addr:full":"Saint-Hubert QC J3Y 8Y9",
    "addr:postcode":"j3y 8y9",
    "iso:country":"CA",
    "sg:city":"Saint-Hubert",
    "sg:classifiers":[
        {
            "category":"Airport",
            "type":"Transportation"
        }
    ],
    "sg:phone":"+1 450 656 7880",
    "sg:postcode":"J3Y 8Y9",
    "sg:province":"QC",
    "sg:tags":[
        "aircraft",
        "maintenance"
    ],
    "wof:name":"Petro Air Svc",
    "wof:placetype":"venue"
},
  "geometry": {"coordinates":[-73.4249572754,45.5019836426],"type":"Point"}
}