{
  "type": "Feature",
  "properties": {
    "addr:full":"290 Sandwich St S Amherstburg ON N9V 2A8",
    "addr:housenumber":"290",
    "addr:postcode":"n9v 2a8",
    "addr:street":"Sandwich St S",
    "iso:country":"CA",
    "sg:address":"290 Sandwich St S",
    "sg:city":"Amherstburg",
    "sg:classifiers":[
        {
            "category":"Shopping",
            "subcategory":"Pharmacy",
            "type":"Retail Goods"
        }
    ],
    "sg:phone":"+1 519 736 0979",
    "sg:postcode":"N9V 2A8",
    "sg:province":"ON",
    "wof:name":"Emanuele's Family Pharmacy",
    "wof:placetype":"venue"
},
  "geometry": {"coordinates":[-83.10865020750001,42.1008033752],"type":"Point"}
}