{
  "type": "Feature",
  "properties": {
    "addr:full":"RR 4 STN Main Sherwood Park AB T8A 3K4",
    "addr:postcode":"t8a 3k4",
    "addr:street":"Rr 4 Stn Main;Park",
    "iso:country":"CA",
    "sg:address":"RR 4 STN Main",
    "sg:city":"Sherwood Park",
    "sg:classifiers":[
        {
            "category":"Organizations",
            "subcategory":"Religious Organization",
            "type":"Services"
        }
    ],
    "sg:phone":"+1 780 467 0968",
    "sg:postcode":"T8A 3K4",
    "sg:province":"AB",
    "sg:tags":[
        "church"
    ],
    "wof:name":"Wyecliff Bible Chapel",
    "wof:placetype":"venue"
},
  "geometry": {"coordinates":[-113.29573822,53.5264015198],"type":"Point"}
}