{
  "type": "Feature",
  "properties": {
    "addr:full":"59 Rue Moise Cap-Pele NB E4N 1X5",
    "addr:housenumber":"59",
    "addr:postcode":"e4n 1x5",
    "addr:street":"Rue Moise",
    "iso:country":"CA",
    "sg:address":"59 Rue Moise",
    "sg:city":"Cap-Pele",
    "sg:classifiers":[
        {
            "category":"Personal",
            "subcategory":"Beauty Salon",
            "type":"Services"
        }
    ],
    "sg:phone":"+1 506 577 6633",
    "sg:postcode":"E4N 1X5",
    "sg:province":"NB",
    "wof:name":"Suzanne Salon DE Beaute",
    "wof:placetype":"venue"
},
  "geometry": {"coordinates":[-64.28621699999999,46.229473],"type":"Point"}
}