{
  "type": "Feature",
  "properties": {
    "addr:full":"33 White St St Thomas ON N5R 3T5",
    "addr:housenumber":"33",
    "addr:postcode":"n5r 3t5",
    "addr:street":"White St",
    "iso:country":"CA",
    "sg:address":"33 White St",
    "sg:city":"St Thomas",
    "sg:classifiers":[
        {
            "category":"Health Services",
            "subcategory":"Doctor",
            "type":"Services"
        }
    ],
    "sg:phone":"+1 519 633 2410",
    "sg:postcode":"N5R 3T5",
    "sg:province":"ON",
    "sg:tags":[
        "dentist"
    ],
    "wof:name":"Wakulich, Candice DDS",
    "wof:placetype":"venue"
},
  "geometry": {"coordinates":[-81.193169,42.777576],"type":"Point"}
}