{
  "type": "Feature",
  "properties": {
    "addr:full":"Etobicoke ON M9P 3B6",
    "addr:postcode":"m9p 3b6",
    "iso:country":"CA",
    "sg:city":"Etobicoke",
    "sg:classifiers":[
        {
            "category":"Travel",
            "subcategory":"Travel Agent",
            "type":"Entertainment"
        }
    ],
    "sg:phone":"+1 416 249 7710",
    "sg:postcode":"M9P 3B6",
    "sg:province":"ON",
    "sg:tags":[
        "agency",
        "bureau"
    ],
    "wof:name":"Best Way To Travel Inc",
    "wof:placetype":"venue"
},
  "geometry": {"coordinates":[-79.5305633545,43.6909103394],"type":"Point"}
}