{
  "type": "Feature",
  "properties": {
    "addr:full":"151 Rue Denison E Granby QC J2G 4C4",
    "addr:housenumber":"151",
    "addr:postcode":"j2g 4c4",
    "addr:street":"Rue Denison E",
    "iso:country":"CA",
    "sg:address":"151 Rue Denison E",
    "sg:city":"Granby",
    "sg:classifiers":[
        {
            "category":"Sports & Exercise",
            "subcategory":"Bowling",
            "type":"Entertainment"
        }
    ],
    "sg:phone":"+1 450 372 7211",
    "sg:postcode":"J2G 4C4",
    "sg:province":"QC",
    "sg:tags":[
        "center"
    ],
    "wof:name":"Royaume Des Quilles Dgd Inc",
    "wof:placetype":"venue"
},
  "geometry": {"coordinates":[-72.7122955322,45.3949813843],"type":"Point"}
}