{
  "type": "Feature",
  "properties": {
    "addr:full":"10780 Rue Laverdure Montreal QC H3L 2L9",
    "addr:housenumber":"10780",
    "addr:postcode":"h3l 2l9",
    "addr:street":"Rue Laverdure",
    "iso:country":"CA",
    "sg:address":"10780 Rue Laverdure",
    "sg:city":"Montreal",
    "sg:classifiers":[
        {
            "category":"Manufacturing",
            "subcategory":"Printing",
            "type":"Manufacturing & Wholesale Goods"
        }
    ],
    "sg:phone":"+1 514 389 1603",
    "sg:postcode":"H3L 2L9",
    "sg:province":"QC",
    "sg:tags":[
        "newspaper"
    ],
    "wof:name":"Medialfa",
    "wof:placetype":"venue"
},
  "geometry": {"coordinates":[-73.67158499999999,45.552376],"type":"Point"}
}