{
  "type": "Feature",
  "properties": {
    "addr:full":"1108 Webbwood Dr Sudbury ON P3C 3B7",
    "addr:housenumber":"1108",
    "addr:postcode":"p3c 3b7",
    "addr:street":"Webbwood Dr",
    "iso:country":"CA",
    "sg:address":"1108 Webbwood Dr",
    "sg:city":"Sudbury",
    "sg:classifiers":[
        {
            "category":"Wholesale",
            "subcategory":"Electrical",
            "type":"Manufacturing & Wholesale Goods"
        }
    ],
    "sg:phone":"+1 705 670 8545",
    "sg:postcode":"P3C 3B7",
    "sg:province":"ON",
    "sg:tags":[
        "electric",
        "motor"
    ],
    "wof:name":"Central Electric Motor Svc",
    "wof:placetype":"venue"
},
  "geometry": {"coordinates":[-81.02977752690001,46.4709663391],"type":"Point"}
}