{
  "type": "Feature",
  "properties": {
    "addr:full":"Toronto ON M5E 1E5",
    "addr:postcode":"m5e 1e5",
    "iso:country":"CA",
    "sg:city":"Toronto",
    "sg:classifiers":[
        {
            "category":"Shopping",
            "subcategory":"Tobacco",
            "type":"Retail Goods"
        }
    ],
    "sg:phone":"+1 416 863 0999",
    "sg:postcode":"M5E 1E5",
    "sg:province":"ON",
    "sg:tags":[
        "cigarette",
        "cigar",
        "dealer"
    ],
    "wof:name":"Olympia Gift Shoppe",
    "wof:placetype":"venue"
},
  "geometry": {"coordinates":[-79.3745803833,43.6420516968],"type":"Point"}
}