{
  "type": "Feature",
  "properties": {
    "iso:country":"CA",
    "sg:address":"1708 Lasalle Blvd",
    "sg:city":"Sudbury",
    "sg:classifiers":[
        {
            "category":"Health Services",
            "subcategory":"Chiropractor",
            "type":"Services"
        }
    ],
    "sg:phone":"+1 705 560 4090",
    "sg:postcode":"P3A 2A1",
    "sg:province":"ON",
    "wof:name":"Fantin, J V DC",
    "wof:placetype":"venue"
},
  "geometry": {"coordinates":[-80.934952,46.522213],"type":"Point"}
}