{
  "type": "Feature",
  "properties": {
    "iso:country":"CA",
    "sg:address":"76 Townsend St",
    "sg:city":"Sydney",
    "sg:classifiers":[
        {
            "category":"Bars & Pubs",
            "type":"Food & Drink"
        }
    ],
    "sg:phone":"+1 902 539 7759",
    "sg:postcode":"B1P 5C8",
    "sg:province":"NS",
    "sg:tags":[
        "lounge",
        "cocktail"
    ],
    "wof:name":"Black Diamond Bar & Grill",
    "wof:placetype":"venue"
},
  "geometry": {"coordinates":[-60.193027,46.134575],"type":"Point"}
}