{
  "type": "Feature",
  "properties": {
    "addr:full":"244 Dunkirk Rd St Catharines ON L2R 7K6",
    "addr:housenumber":"244",
    "addr:postcode":"l2r 7k6",
    "addr:street":"Dunkirk Rd",
    "iso:country":"CA",
    "sg:address":"244 Dunkirk Rd",
    "sg:city":"St Catharines",
    "sg:classifiers":[
        {
            "category":"Retail",
            "subcategory":"Auto Repair",
            "type":"Services"
        }
    ],
    "sg:phone":"+1 905 687 7031",
    "sg:postcode":"L2R 7K6",
    "sg:province":"ON",
    "sg:tags":[
        "truck"
    ],
    "wof:name":"Nick's New Used Truck Parts",
    "wof:placetype":"venue"
},
  "geometry": {"coordinates":[-79.2040557861,43.1661720276],"type":"Point"}
}