{
  "type": "Feature",
  "properties": {
    "addr:full":"1496 Kingston Rd Scarborough ON M1N 1R6",
    "addr:housenumber":"1496",
    "addr:postcode":"m1n 1r6",
    "addr:street":"Kingston Rd",
    "iso:country":"CA",
    "sg:address":"1496 Kingston Rd",
    "sg:city":"Scarborough",
    "sg:classifiers":[
        {
            "category":"Restaurant",
            "type":"Food & Drink"
        }
    ],
    "sg:phone":"+1 416 694 1557",
    "sg:postcode":"M1N 1R6",
    "sg:province":"ON",
    "wof:name":"Wimpy's Diner",
    "wof:placetype":"venue"
},
  "geometry": {"coordinates":[-79.269592,43.68885],"type":"Point"}
}