{
  "type": "Feature",
  "properties": {
    "addr:full":"Eddystone MB R0L 0S0",
    "addr:postcode":"r0l 0s0",
    "iso:country":"CA",
    "sg:city":"Eddystone",
    "sg:classifiers":[
        {
            "category":"Education",
            "subcategory":"School",
            "type":"Public Place"
        }
    ],
    "sg:phone":"+1 204 448 2012",
    "sg:postcode":"R0L 0S0",
    "sg:province":"MB",
    "wof:name":"Ebb & Flow School",
    "wof:placetype":"venue"
},
  "geometry": {"coordinates":[-99.1494979858,51.0949554443],"type":"Point"}
}