{
  "type": "Feature",
  "properties": {
    "addr:full":"151 East Lake Blvd NE # 201B Airdrie AB T4A 2G1",
    "addr:housenumber":"151",
    "addr:postcode":"t4a 2g1",
    "addr:street":"East Lake Blvd Ne # 201B",
    "iso:country":"CA",
    "sg:address":"151 East Lake Blvd NE # 201B",
    "sg:city":"Airdrie",
    "sg:classifiers":[
        {
            "category":"Shopping",
            "subcategory":"Stationery & Office Supplies",
            "type":"Retail Goods"
        }
    ],
    "sg:phone":"+1 403 912 5658",
    "sg:postcode":"T4A 2G1",
    "sg:province":"AB",
    "wof:name":"Airdrie Office Supplies Ltd",
    "wof:placetype":"venue"
},
  "geometry": {"coordinates":[-113.990089416,51.2929344177],"type":"Point"}
}