{
  "type": "Feature",
  "properties": {
    "iso:country":"CA",
    "sg:address":"158 Hurontario St",
    "sg:city":"Collingwood",
    "sg:classifiers":[
        {
            "category":"Insurance",
            "subcategory":"Insurance Agent",
            "type":"Services"
        }
    ],
    "sg:phone":"+1 705 444 0309",
    "sg:postcode":"L9Y 2M2",
    "sg:province":"ON",
    "sg:tags":[
        "consultant",
        "planning",
        "financial"
    ],
    "wof:name":"Rba Financial Group",
    "wof:placetype":"venue"
},
  "geometry": {"coordinates":[-80.216766,44.498669],"type":"Point"}
}