{
  "type": "Feature",
  "properties": {
    "addr:full":"5718 Burbank Cres SE Calgary AB T2H 1Z6",
    "addr:housenumber":"5718",
    "addr:postcode":"t2h 1z6",
    "addr:street":"Burbank Cres Se",
    "iso:country":"CA",
    "sg:address":"5718 Burbank Cres SE",
    "sg:city":"Calgary",
    "sg:classifiers":[
        {
            "category":"Wholesale",
            "subcategory":"Machinery & Supplies",
            "type":"Manufacturing & Wholesale Goods"
        }
    ],
    "sg:phone":"+1 403 253 3113",
    "sg:postcode":"T2H 1Z6",
    "sg:province":"AB",
    "sg:tags":[
        "salon",
        "beauty"
    ],
    "wof:name":"Hi Tech Beauty Supplies Ltd",
    "wof:placetype":"venue"
},
  "geometry": {"coordinates":[-114.048317,51.003567],"type":"Point"}
}