{
  "type": "Feature",
  "properties": {
    "addr:full":"132 Jackson St E Hamilton ON L8N 1L3",
    "addr:housenumber":"132",
    "addr:postcode":"l8n 1l3",
    "addr:street":"Jackson St E",
    "iso:country":"CA",
    "sg:address":"132 Jackson St E",
    "sg:city":"Hamilton",
    "sg:classifiers":[
        {
            "category":"Insurance",
            "subcategory":"Insurance Agent",
            "type":"Services"
        }
    ],
    "sg:phone":"+1 905 523 4593",
    "sg:postcode":"L8N 1L3",
    "sg:province":"ON",
    "sg:tags":[
        "consultant"
    ],
    "wof:name":"Vince Agro Insurance",
    "wof:placetype":"venue"
},
  "geometry": {"coordinates":[-79.86498260499999,43.2530403137],"type":"Point"}
}