{
  "type": "Feature",
  "properties": {
    "addr:full":"Toronto ON M5G 1Z6",
    "addr:postcode":"m5g 1z6",
    "iso:country":"CA",
    "sg:city":"Toronto",
    "sg:classifiers":[
        {
            "category":"Organizations",
            "subcategory":"Professional Association",
            "type":"Services"
        }
    ],
    "sg:phone":"+1 416 593 6060",
    "sg:postcode":"M5G 1Z6",
    "sg:province":"ON",
    "wof:name":"Sing Fai Sports Club",
    "wof:placetype":"venue"
},
  "geometry": {"coordinates":[-79.3849639893,43.6582374573],"type":"Point"}
}