{
  "type": "Feature",
  "properties": {
    "addr:full":"745 Montee Sainte-Julie Sainte-Julie QC J3E 1W9",
    "addr:housenumber":"745",
    "addr:postcode":"j3e 1w9",
    "addr:street":"Montee Sainte-Julie",
    "iso:country":"CA",
    "sg:address":"745 Montee Sainte-Julie",
    "sg:city":"Sainte-Julie",
    "sg:classifiers":[
        {
            "category":"Retail",
            "subcategory":"Laundry & Dry Cleaning",
            "type":"Services"
        }
    ],
    "sg:phone":"+1 450 649 4480",
    "sg:postcode":"J3E 1W9",
    "sg:province":"QC",
    "sg:tags":[
        "cleaners"
    ],
    "wof:name":"Nettoyeur Le Baron",
    "wof:placetype":"venue"
},
  "geometry": {"coordinates":[-73.33921100000001,45.59359],"type":"Point"}
}