{
  "type": "Feature",
  "properties": {
    "addr:full":"1726 152 St Surrey BC V4A 4N4",
    "addr:housenumber":"1726",
    "addr:postcode":"v4a 4n4",
    "addr:street":"152 St",
    "iso:country":"CA",
    "sg:address":"1726 152 St",
    "sg:city":"Surrey",
    "sg:classifiers":[
        {
            "category":"Restaurant",
            "type":"Food & Drink"
        }
    ],
    "sg:phone":"+1 604 541 6477",
    "sg:postcode":"V4A 4N4",
    "sg:province":"BC",
    "wof:name":"Wrap Zone",
    "wof:placetype":"venue"
},
  "geometry": {"coordinates":[-122.801056,49.033459],"type":"Point"}
}