{
  "type": "Feature",
  "properties": {
    "iso:country":"CA",
    "sg:address":"22 Guelph St",
    "sg:city":"Georgetown",
    "sg:classifiers":[
        {
            "category":"Health Services",
            "subcategory":"Doctor",
            "type":"Services"
        }
    ],
    "sg:phone":"+1 905 877 4371",
    "sg:postcode":"L7G 3Z4",
    "sg:province":"ON",
    "sg:tags":[
        "dentist"
    ],
    "wof:name":"Greig, H A DDS",
    "wof:placetype":"venue"
},
  "geometry": {"coordinates":[-79.925453186,43.6512260437],"type":"Point"}
}