{
  "type": "Feature",
  "properties": {
    "addr:full":"Windsor ON N8X 4W2",
    "addr:postcode":"n8x 4w2",
    "iso:country":"CA",
    "sg:city":"Windsor",
    "sg:classifiers":[
        {
            "category":"Health Services",
            "subcategory":"Doctor",
            "type":"Services"
        }
    ],
    "sg:phone":"+1 519 256 6839",
    "sg:postcode":"N8X 4W2",
    "sg:province":"ON",
    "sg:tags":[
        "clinic"
    ],
    "wof:name":"Vein Treatment Ctr",
    "wof:placetype":"venue"
},
  "geometry": {"coordinates":[-83.015221,42.298504],"type":"Point"}
}