{
  "type": "Feature",
  "properties": {
    "addr:full":"9267 50 St NW Edmonton AB T6B 3B6",
    "addr:housenumber":"9267",
    "addr:postcode":"t6b 3b6",
    "addr:street":"50 St Nw",
    "iso:country":"CA",
    "sg:address":"9267 50 St NW",
    "sg:city":"Edmonton",
    "sg:classifiers":[
        {
            "category":"Building & Trades",
            "subcategory":"Construction",
            "type":"Services"
        }
    ],
    "sg:phone":"+1 780 910 2028",
    "sg:postcode":"T6B 3B6",
    "sg:province":"AB",
    "sg:tags":[
        "general",
        "contractor"
    ],
    "wof:name":"Alberta General Contractors",
    "wof:placetype":"venue"
},
  "geometry": {"coordinates":[-113.41792297400001,53.5290374756],"type":"Point"}
}