{
  "type": "Feature",
  "properties": {
    "iso:country":"CA",
    "sg:address":"1355 Rue Du Pont",
    "sg:city":"Shawinigan",
    "sg:classifiers":[
        {
            "category":"Airline",
            "type":"Transportation"
        }
    ],
    "sg:phone":"+1 819 536 5353",
    "sg:postcode":"G9N 8G9",
    "sg:province":"QC",
    "sg:tags":[
        "company"
    ],
    "wof:name":"Aeronautique Explorer Inc",
    "wof:placetype":"venue"
},
  "geometry": {"coordinates":[-72.7509231567,46.5524330139],"type":"Point"}
}