{
  "type": "Feature",
  "properties": {
    "addr:full":"24018 Woodbine Ave Keswick ON L4P 3E9",
    "addr:housenumber":"24018",
    "addr:postcode":"l4p 3e9",
    "addr:street":"Woodbine Ave",
    "iso:country":"CA",
    "sg:address":"24018 Woodbine Ave",
    "sg:city":"Keswick",
    "sg:classifiers":[
        {
            "category":"Shopping",
            "subcategory":"Florist",
            "type":"Retail Goods"
        }
    ],
    "sg:phone":"+1 905 476 1318",
    "sg:postcode":"L4P 3E9",
    "sg:province":"ON",
    "sg:tags":[
        "grocer"
    ],
    "wof:name":"Zehrs Markets",
    "wof:placetype":"venue"
},
  "geometry": {"coordinates":[-79.447594,44.228603],"type":"Point"}
}