{
  "type": "Feature",
  "properties": {
    "addr:full":"245 Kent St W Lindsay ON K9V 2Z3",
    "addr:housenumber":"245",
    "addr:postcode":"k9v 2z3",
    "addr:street":"Kent St W",
    "iso:country":"CA",
    "sg:address":"245 Kent St W",
    "sg:city":"Lindsay",
    "sg:classifiers":[
        {
            "category":"Professional",
            "subcategory":"Accounting & Tax Preparation",
            "type":"Services"
        }
    ],
    "sg:phone":"+1 705 324 2006",
    "sg:postcode":"K9V 2Z3",
    "sg:province":"ON",
    "sg:tags":[
        "accountant"
    ],
    "wof:name":"Phoenix Accounting Svc",
    "wof:placetype":"venue"
},
  "geometry": {"coordinates":[-78.74575042719999,44.352809906],"type":"Point"}
}