{
  "type": "Feature",
  "properties": {
    "addr:full":"60 Overlea Blvd Toronto ON M4H 1B6",
    "addr:housenumber":"60",
    "addr:postcode":"m4h 1b6",
    "addr:street":"Overlea Blvd",
    "iso:country":"CA",
    "sg:address":"60 Overlea Blvd",
    "sg:city":"Toronto",
    "sg:classifiers":[
        {
            "category":"Shopping",
            "subcategory":"Used Merchandise",
            "type":"Retail Goods"
        }
    ],
    "sg:phone":"+1 416 422 0998",
    "sg:postcode":"M4H 1B6",
    "sg:province":"ON",
    "sg:tags":[
        "second",
        "store",
        "hand"
    ],
    "wof:name":"Goodwill Industries of Toronto",
    "wof:placetype":"venue"
},
  "geometry": {"coordinates":[-79.344032,43.707577],"type":"Point"}
}