{
  "type": "Feature",
  "properties": {
    "addr:full":"1435 Mountain Rd #400 Moncton NB E1G 1A3",
    "addr:housenumber":"1435",
    "addr:postcode":"e1g 1a3",
    "addr:street":"Mountain Rd # 400",
    "iso:country":"CA",
    "sg:address":"1435 Mountain Rd #400",
    "sg:city":"Moncton",
    "sg:classifiers":[
        {
            "category":"Health Services",
            "subcategory":"Doctor",
            "type":"Services"
        }
    ],
    "sg:phone":"+1 506 859 7200",
    "sg:postcode":"E1G 1A3",
    "sg:province":"NB",
    "sg:tags":[
        "dentist"
    ],
    "wof:name":"Smith, Brian H DDS",
    "wof:placetype":"venue"
},
  "geometry": {"coordinates":[-64.83616600000001,46.113731],"type":"Point"}
}