{
  "type": "Feature",
  "properties": {
    "addr:full":"5 Victoria St W Alliston ON L9R 1S9",
    "addr:housenumber":"5",
    "addr:postcode":"l9r 1s9",
    "addr:street":"Victoria St W Alliston",
    "iso:country":"CA",
    "sg:address":"5 Victoria St W",
    "sg:city":"Alliston",
    "sg:classifiers":[
        {
            "category":"Banks & Credit Unions",
            "subcategory":"Bank",
            "type":"Services"
        }
    ],
    "sg:phone":"+1 705 435 2816",
    "sg:postcode":"L9R 1S9",
    "sg:province":"ON",
    "wof:name":"National Bank",
    "wof:placetype":"venue"
},
  "geometry": {"coordinates":[-79.86943817140001,44.1537895203],"type":"Point"}
}