{
  "type": "Feature",
  "properties": {
    "addr:full":"346 Parkinson Rd Woodstock ON N4S 2N6",
    "addr:housenumber":"346",
    "addr:postcode":"n4s 2n6",
    "addr:street":"Parkinson Rd",
    "iso:country":"CA",
    "sg:address":"346 Parkinson Rd",
    "sg:city":"Woodstock",
    "sg:classifiers":[
        {
            "category":"Education",
            "subcategory":"School",
            "type":"Public Place"
        }
    ],
    "sg:phone":"+1 519 537 8233",
    "sg:postcode":"N4S 2N6",
    "sg:province":"ON",
    "wof:name":"St Patrick's School",
    "wof:placetype":"venue"
},
  "geometry": {"coordinates":[-80.757927,43.117275],"type":"Point"}
}