{
  "type": "Feature",
  "properties": {
    "addr:full":"224 Bridge St Princeton BC V0X 1W0",
    "addr:housenumber":"224",
    "addr:postcode":"v0x 1w0",
    "addr:street":"Bridge St",
    "iso:country":"CA",
    "sg:address":"224 Bridge St",
    "sg:city":"Princeton",
    "sg:classifiers":[
        {
            "category":"Personal",
            "subcategory":"Beauty Salon",
            "type":"Services"
        }
    ],
    "sg:phone":"+1 250 295 7612",
    "sg:postcode":"V0X 1W0",
    "sg:province":"BC",
    "wof:name":"Cut Above Hairstyling",
    "wof:placetype":"venue"
},
  "geometry": {"coordinates":[-120.508872986,49.4606933594],"type":"Point"}
}