{
  "type": "Feature",
  "properties": {
    "iso:country":"CA",
    "sg:address":"796 Rue Victoria",
    "sg:city":"Edmundston",
    "sg:classifiers":[
        {
            "category":"Personal",
            "subcategory":"Beauty Salon",
            "type":"Services"
        }
    ],
    "sg:phone":"+1 506 739 6336",
    "sg:postcode":"E3V 3S9",
    "sg:province":"NB",
    "wof:name":"Salon Lisa Unisex",
    "wof:placetype":"venue"
},
  "geometry": {"coordinates":[-68.344619751,47.394077301],"type":"Point"}
}