{
  "type": "Feature",
  "properties": {
    "iso:country":"CA",
    "sg:city":"Mississauga",
    "sg:classifiers":[
        {
            "category":"Real Estate",
            "subcategory":"Real Estate Agent",
            "type":"Services"
        }
    ],
    "sg:phone":"+1 905 602 0401",
    "sg:postcode":"L4W 5A8",
    "sg:province":"ON",
    "sg:tags":[
        "appraiser"
    ],
    "wof:name":"Leonard Mc Coubrey & Assoc",
    "wof:placetype":"venue"
},
  "geometry": {"coordinates":[-79.6014175415,43.6597480774],"type":"Point"}
}