{
  "type": "Feature",
  "properties": {
    "iso:country":"CA",
    "sg:address":"1385 California Ave",
    "sg:city":"Brockville",
    "sg:classifiers":[
        {
            "category":"Wholesale",
            "subcategory":"Machinery & Supplies",
            "type":"Manufacturing & Wholesale Goods"
        }
    ],
    "sg:phone":"+1 613 342 4408",
    "sg:postcode":"K6V 5V5",
    "sg:province":"ON",
    "sg:tags":[
        "equipment",
        "industrial"
    ],
    "wof:name":"Hansler Smith Ltd",
    "wof:placetype":"venue"
},
  "geometry": {"coordinates":[-75.69622802729999,44.6211166382],"type":"Point"}
}