{
  "type": "Feature",
  "properties": {
    "addr:full":"1421 Victoria Park Ave Scarborough ON M4A 2M5",
    "addr:housenumber":"1421",
    "addr:postcode":"m4a 2m5",
    "addr:street":"Victoria Park Ave",
    "iso:country":"CA",
    "sg:address":"1421 Victoria Park Ave",
    "sg:city":"Scarborough",
    "sg:classifiers":[
        {
            "category":"Building & Trades",
            "subcategory":"Construction",
            "type":"Services"
        }
    ],
    "sg:phone":"+1 416 755 9888",
    "sg:postcode":"M4A 2M5",
    "sg:province":"ON",
    "sg:tags":[
        "drainage",
        "contractor"
    ],
    "wof:name":"Ready Rooter Plumbing & Drain",
    "wof:placetype":"venue"
},
  "geometry": {"coordinates":[-79.300934,43.721073],"type":"Point"}
}