{
  "type": "Feature",
  "properties": {
    "addr:full":"5349 Rue Ferrier Montreal QC H4P 1M1",
    "addr:housenumber":"5349",
    "addr:postcode":"h4p 1m1",
    "addr:street":"Rue Ferrier",
    "iso:country":"CA",
    "sg:address":"5349 Rue Ferrier",
    "sg:city":"Montreal",
    "sg:classifiers":[
        {
            "category":"Shopping",
            "subcategory":"Computers & Home Electronics",
            "type":"Retail Goods"
        }
    ],
    "sg:phone":"+1 514 731 7441",
    "sg:postcode":"H4P 1M1",
    "sg:province":"QC",
    "sg:tags":[
        "equipment",
        "electronic",
        "supply"
    ],
    "wof:name":"Active Electronique",
    "wof:placetype":"venue"
},
  "geometry": {"coordinates":[-73.659302,45.496349],"type":"Point"}
}