{
  "type": "Feature",
  "properties": {
    "addr:full":"696 Brunswick St Prince George BC V2L 2C1",
    "addr:housenumber":"696",
    "addr:postcode":"v2l 2c1",
    "addr:street":"Brunswick St",
    "iso:country":"CA",
    "sg:address":"696 Brunswick St",
    "sg:city":"Prince George",
    "sg:classifiers":[
        {
            "category":"Banks & Credit Unions",
            "subcategory":"Investment Brokerage",
            "type":"Services"
        }
    ],
    "sg:phone":"+1 250 564 2310",
    "sg:postcode":"V2L 2C1",
    "sg:province":"BC",
    "sg:tags":[
        "consultant",
        "planning",
        "financial"
    ],
    "wof:name":"Investors Group",
    "wof:placetype":"venue"
},
  "geometry": {"coordinates":[-122.749771,53.914425],"type":"Point"}
}