{
  "type": "Feature",
  "properties": {
    "addr:full":"226 Wabalisla Bella Bella BC V0T 1B0",
    "addr:housenumber":"226",
    "addr:postcode":"v0t 1b0",
    "addr:street":"Wabalisla Bella",
    "iso:country":"CA",
    "sg:address":"226 Wabalisla",
    "sg:city":"Bella Bella",
    "sg:classifiers":[
        {
            "category":"Organizations",
            "subcategory":"Professional Association",
            "type":"Services"
        }
    ],
    "sg:phone":"+1 250 957 2602",
    "sg:postcode":"V0T 1B0",
    "sg:province":"BC",
    "wof:name":"Heiltsuk Waste Water Treatment",
    "wof:placetype":"venue"
},
  "geometry": {"coordinates":[-128.145859,52.1665],"type":"Point"}
}