{
  "type": "Feature",
  "properties": {
    "iso:country":"CA",
    "sg:address":"282 Rue Principale #A",
    "sg:city":"St-Sauveur-Des-Monts",
    "sg:classifiers":[
        {
            "category":"Shopping",
            "subcategory":"Gifts & Souvenirs",
            "type":"Retail Goods"
        }
    ],
    "sg:phone":"+1 450 227 7486",
    "sg:postcode":"J0R 1R0",
    "sg:province":"QC",
    "sg:tags":[
        "party",
        "supply"
    ],
    "wof:name":"Literie Lunedor",
    "wof:placetype":"venue"
},
  "geometry": {"coordinates":[-74.1582489014,45.8930206299],"type":"Point"}
}