{
  "type": "Feature",
  "properties": {
    "addr:full":"29 Citadel Rd Grand Bank NL A0E 1W0",
    "addr:housenumber":"29",
    "addr:postcode":"a0e 1w0",
    "addr:street":"Citadel Rd",
    "iso:country":"CA",
    "sg:address":"29 Citadel Rd",
    "sg:city":"Grand Bank",
    "sg:classifiers":[
        {
            "category":"Organizations",
            "subcategory":"Religious Organization",
            "type":"Services"
        }
    ],
    "sg:phone":"+1 709 832 1470",
    "sg:postcode":"A0E 1W0",
    "sg:province":"NL",
    "sg:tags":[
        "church"
    ],
    "wof:name":"Salvation Army Citadel",
    "wof:placetype":"venue"
},
  "geometry": {"coordinates":[-55.757942,47.094414],"type":"Point"}
}