{
  "type": "Feature",
  "properties": {
    "iso:country":"CA",
    "sg:address":"2067 Rue Sainte-Catherine O",
    "sg:city":"Montreal",
    "sg:classifiers":[
        {
            "category":"Shopping",
            "type":"Retail Goods"
        }
    ],
    "sg:phone":"+1 514 933 8366",
    "sg:postcode":"H3H 1M6",
    "sg:province":"QC",
    "sg:tags":[
        "miscellaneous",
        "store"
    ],
    "wof:name":"Boutique DE Sexe-Maxi-Mag",
    "wof:placetype":"venue"
},
  "geometry": {"coordinates":[-73.550789,45.524536],"type":"Point"}
}