{
  "type": "Feature",
  "properties": {
    "addr:full":"50 Boul Taschereau # M8 LA Prairie QC J5R 4V3",
    "addr:housenumber":"50;# m8",
    "addr:postcode":"j5r 4v3",
    "addr:street":"Boul Taschereau",
    "iso:country":"CA",
    "sg:address":"50 Boul Taschereau # M8",
    "sg:city":"LA Prairie",
    "sg:classifiers":[
        {
            "category":"Health Services",
            "subcategory":"Health Practitioner",
            "type":"Services"
        }
    ],
    "sg:phone":"+1 450 659 3171",
    "sg:postcode":"J5R 4V3",
    "sg:province":"QC",
    "sg:tags":[
        "psychologist"
    ],
    "wof:name":"Landreville, Denis",
    "wof:placetype":"venue"
},
  "geometry": {"coordinates":[-73.484116,45.423779],"type":"Point"}
}