{
  "type": "Feature",
  "properties": {
    "addr:full":"Scarborough ON M1P 2X8",
    "addr:postcode":"m1p 2x8",
    "iso:country":"CA",
    "sg:city":"Scarborough",
    "sg:classifiers":[
        {
            "category":"Food & Beverages",
            "subcategory":"Meat & Fish",
            "type":"Retail Goods"
        }
    ],
    "sg:phone":"+1 416 285 8558",
    "sg:postcode":"M1P 2X8",
    "sg:province":"ON",
    "sg:tags":[
        "seafood"
    ],
    "wof:name":"Ellesmere Fish & Meat Market",
    "wof:placetype":"venue"
},
  "geometry": {"coordinates":[-79.266319,43.768906],"type":"Point"}
}