{
  "type": "Feature",
  "properties": {
    "iso:country":"CA",
    "sg:address":"65 Rue Sherbrooke E",
    "sg:city":"Montreal",
    "sg:classifiers":[
        {
            "category":"Freight",
            "type":"Transportation"
        }
    ],
    "sg:phone":"+1 514 284 2099",
    "sg:postcode":"H2X 1C4",
    "sg:province":"QC",
    "wof:name":"Allegro Freight Svc",
    "wof:placetype":"venue"
},
  "geometry": {"coordinates":[-73.56926,45.513222],"type":"Point"}
}