{
  "type": "Feature",
  "properties": {
    "iso:country":"CA",
    "sg:address":"183 Rue Louis-Bazinet",
    "sg:city":"Saint-Charles-Borromee",
    "sg:classifiers":[
        {
            "category":"Wholesale",
            "subcategory":"Furniture",
            "type":"Manufacturing & Wholesale Goods"
        }
    ],
    "sg:phone":"+1 450 752 0864",
    "sg:postcode":"J6E 7J4",
    "sg:province":"QC",
    "wof:name":"Robert Gauthier Fournitures",
    "wof:placetype":"venue"
},
  "geometry": {"coordinates":[-73.44251300000001,46.044041],"type":"Point"}
}