{
  "type": "Feature",
  "properties": {
    "addr:full":"18 Lakeport Rd St Catharines ON L2N 4P5",
    "addr:housenumber":"18",
    "addr:postcode":"l2n 4p5",
    "addr:street":"Lakeport Rd",
    "iso:country":"CA",
    "sg:address":"18 Lakeport Rd",
    "sg:city":"St Catharines",
    "sg:classifiers":[
        {
            "category":"Shopping",
            "subcategory":"Clothing, Apparel, & Fashions",
            "type":"Retail Goods"
        }
    ],
    "sg:phone":"+1 905 934 9099",
    "sg:postcode":"L2N 4P5",
    "sg:province":"ON",
    "wof:name":"Magic Mountain Trading CO",
    "wof:placetype":"venue"
},
  "geometry": {"coordinates":[-79.2655334473,43.202419281],"type":"Point"}
}