{
  "type": "Feature",
  "properties": {
    "iso:country":"CA",
    "sg:address":"288 Rexdale Blvd",
    "sg:city":"Etobicoke",
    "sg:classifiers":[
        {
            "category":"Autos & Motor Vehicles",
            "subcategory":"Fuel & Gas Station",
            "type":"Retail Goods"
        }
    ],
    "sg:phone":"+1 416 740 0054",
    "sg:postcode":"M9W 1R6",
    "sg:province":"ON",
    "sg:tags":[
        "oil"
    ],
    "wof:name":"Sunoco",
    "wof:placetype":"venue"
},
  "geometry": {"coordinates":[-79.58224487299999,43.7142562866],"type":"Point"}
}