{
  "type": "Feature",
  "properties": {
    "addr:full":"492 Rue Labbe Thetford Mines QC G6G 1Z6",
    "addr:housenumber":"492",
    "addr:postcode":"g6g 1z6",
    "addr:street":"Rue Labbe",
    "iso:country":"CA",
    "sg:address":"492 Rue Labbe",
    "sg:city":"Thetford Mines",
    "sg:classifiers":[
        {
            "category":"Personal",
            "subcategory":"Beauty Salon",
            "type":"Services"
        }
    ],
    "sg:phone":"+1 418 335 3303",
    "sg:postcode":"G6G 1Z6",
    "sg:province":"QC",
    "wof:name":"Salon Janot Enr",
    "wof:placetype":"venue"
},
  "geometry": {"coordinates":[-71.295586,46.099361],"type":"Point"}
}