{
  "type": "Feature",
  "properties": {
    "iso:country":"CA",
    "sg:address":"321 Josephine St",
    "sg:city":"Wingham",
    "sg:classifiers":[
        {
            "category":"Restaurant",
            "type":"Food & Drink"
        }
    ],
    "sg:phone":"+1 519 357 2332",
    "sg:postcode":"N0G 2W0",
    "sg:province":"ON",
    "sg:tags":[
        "pizza"
    ],
    "wof:name":"Godfather Pizza",
    "wof:placetype":"venue"
},
  "geometry": {"coordinates":[-81.31071472169999,43.888885498],"type":"Point"}
}