{
  "type": "Feature",
  "properties": {
    "addr:full":"4420 Guildwood Way Mississauga ON L5R 2B1",
    "addr:housenumber":"4420",
    "addr:postcode":"l5r 2b1",
    "addr:street":"Guildwood Way",
    "iso:country":"CA",
    "sg:address":"4420 Guildwood Way",
    "sg:city":"Mississauga",
    "sg:classifiers":[
        {
            "category":"Wholesale",
            "subcategory":"Chemicals & Plastics",
            "type":"Manufacturing & Wholesale Goods"
        }
    ],
    "sg:phone":"+1 905 568 3394",
    "sg:postcode":"L5R 2B1",
    "sg:province":"ON",
    "wof:name":"Refined Specialty Chemical Inc",
    "wof:placetype":"venue"
},
  "geometry": {"coordinates":[-79.662109,43.589138],"type":"Point"}
}