{
  "type": "Feature",
  "properties": {
    "addr:full":"3650 Victoria Park Ave # 103 North York ON M2H 3P7",
    "addr:housenumber":"3650",
    "addr:postcode":"m2h 3p7",
    "addr:street":"Victoria Park Ave # 103",
    "iso:country":"CA",
    "sg:address":"3650 Victoria Park Ave # 103",
    "sg:city":"North York",
    "sg:classifiers":[
        {
            "category":"Professional",
            "subcategory":"Accounting & Tax Preparation",
            "type":"Services"
        }
    ],
    "sg:phone":"+1 905 731 7388",
    "sg:postcode":"M2H 3P7",
    "sg:province":"ON",
    "sg:tags":[
        "accountant"
    ],
    "wof:name":"Wong, Sharon",
    "wof:placetype":"venue"
},
  "geometry": {"coordinates":[-79.338165,43.807796],"type":"Point"}
}