{
  "type": "Feature",
  "properties": {
    "addr:full":"806 Av Duluth E Montreal QC H2L 1B3",
    "addr:postcode":"h2l 1b3",
    "addr:street":"806 Av Duluth E",
    "iso:country":"CA",
    "sg:address":"806 Av Duluth E",
    "sg:city":"Montreal",
    "sg:classifiers":[
        {
            "category":"Health Services",
            "subcategory":"Health Practitioner",
            "type":"Services"
        }
    ],
    "sg:phone":"+1 514 526 9817",
    "sg:postcode":"H2L 1B3",
    "sg:province":"QC",
    "sg:tags":[
        "psychologist"
    ],
    "wof:name":"Grau, Marie C",
    "wof:placetype":"venue"
},
  "geometry": {"coordinates":[-73.57405853269999,45.5225486755],"type":"Point"}
}