{
  "type": "Feature",
  "properties": {
    "addr:full":"Yellowknife NT X1A 3S8",
    "addr:postcode":"x1a 3s8",
    "iso:country":"CA",
    "sg:city":"Yellowknife",
    "sg:classifiers":[
        {
            "category":"Banks & Credit Unions",
            "subcategory":"Investment Brokerage",
            "type":"Services"
        }
    ],
    "sg:phone":"+1 867 873 3000",
    "sg:postcode":"X1A 3S8",
    "sg:province":"NT",
    "sg:tags":[
        "consultant",
        "planning",
        "financial",
        "advisory"
    ],
    "wof:name":"Investors Group Financial Svc",
    "wof:placetype":"venue"
},
  "geometry": {"coordinates":[-114.373336792,62.4534645081],"type":"Point"}
}