{
  "type": "Feature",
  "properties": {
    "addr:full":"260 Bell St Ingersoll ON N5C 2P3",
    "addr:housenumber":"260",
    "addr:postcode":"n5c 2p3",
    "addr:street":"Bell St",
    "iso:country":"CA",
    "sg:address":"260 Bell St",
    "sg:city":"Ingersoll",
    "sg:classifiers":[
        {
            "category":"Building & Trades",
            "subcategory":"Electrical",
            "type":"Services"
        }
    ],
    "sg:phone":"+1 519 425 4224",
    "sg:postcode":"N5C 2P3",
    "sg:province":"ON",
    "sg:tags":[
        "electric",
        "contractor"
    ],
    "wof:name":"Rosco Electric",
    "wof:placetype":"venue"
},
  "geometry": {"coordinates":[-80.896698,43.040623],"type":"Point"}
}