{
  "type": "Feature",
  "properties": {
    "addr:full":"400 Diamond Ave Spruce Grove AB T7X 4C8",
    "addr:housenumber":"400",
    "addr:postcode":"t7x 4c8",
    "addr:street":"Diamond Ave",
    "iso:country":"CA",
    "sg:address":"400 Diamond Ave",
    "sg:city":"Spruce Grove",
    "sg:classifiers":[
        {
            "category":"Recreation",
            "type":"Entertainment"
        }
    ],
    "sg:phone":"+1 780 962 9322",
    "sg:postcode":"T7X 4C8",
    "sg:province":"AB",
    "sg:tags":[
        "hall",
        "auditorium"
    ],
    "wof:name":"Spruce Grove Elks Social Hall",
    "wof:placetype":"venue"
},
  "geometry": {"coordinates":[-113.89729309099999,53.5365562439],"type":"Point"}
}