{
  "type": "Feature",
  "properties": {
    "addr:full":"887 Carnarvon St New Westminster BC V3M 1G2",
    "addr:housenumber":"887",
    "addr:postcode":"v3m 1g2",
    "addr:street":"Carnarvon St",
    "iso:country":"CA",
    "sg:address":"887 Carnarvon St",
    "sg:city":"New Westminster",
    "sg:classifiers":[
        {
            "category":"Food & Beverages",
            "subcategory":"Groceries & Convenience Stores",
            "type":"Retail Goods"
        }
    ],
    "sg:phone":"+1 604 527 8393",
    "sg:postcode":"V3M 1G2",
    "sg:province":"BC",
    "sg:tags":[
        "grocer"
    ],
    "wof:name":"Hockey Fans Convenience",
    "wof:placetype":"venue"
},
  "geometry": {"coordinates":[-122.915344238,49.2007789612],"type":"Point"}
}