{
  "type": "Feature",
  "properties": {
    "addr:full":"427 Fulford-Ganges Rd Salt Spring Island BC V8K 2K1",
    "addr:housenumber":"427",
    "addr:postcode":"v8k 2k1",
    "addr:street":"Fulford-Ganges Rd",
    "iso:country":"CA",
    "sg:address":"427 Fulford-Ganges Rd",
    "sg:city":"Salt Spring Island",
    "sg:classifiers":[
        {
            "category":"Retail",
            "subcategory":"Auto Repair",
            "type":"Services"
        }
    ],
    "sg:phone":"+1 250 537 4559",
    "sg:postcode":"V8K 2K1",
    "sg:province":"BC",
    "sg:tags":[
        "repairing",
        "automobile"
    ],
    "wof:name":"Harold Harkema Repairs",
    "wof:placetype":"venue"
},
  "geometry": {"coordinates":[-123.49600982699999,48.8422622681],"type":"Point"}
}