{
  "type": "Feature",
  "properties": {
    "addr:full":"163 Argyle St S Renfrew ON K7V 1T6",
    "addr:housenumber":"163",
    "addr:postcode":"k7v 1t6",
    "addr:street":"Argyle St S",
    "iso:country":"CA",
    "sg:address":"163 Argyle St S",
    "sg:city":"Renfrew",
    "sg:classifiers":[
        {
            "category":"Social Services",
            "type":"Services"
        }
    ],
    "sg:phone":"+1 613 432 9574",
    "sg:postcode":"K7V 1T6",
    "sg:province":"ON",
    "sg:tags":[
        "organization",
        "welfare"
    ],
    "wof:name":"Renfrew & District Food Bank",
    "wof:placetype":"venue"
},
  "geometry": {"coordinates":[-76.6852340698,45.4718971252],"type":"Point"}
}