{
  "type": "Feature",
  "properties": {
    "iso:country":"CA",
    "sg:city":"Gloucester",
    "sg:classifiers":[
        {
            "category":"Health Services",
            "subcategory":"Doctor",
            "type":"Services"
        }
    ],
    "sg:phone":"+1 613 746 6223",
    "sg:postcode":"K1J 9M2",
    "sg:province":"ON",
    "sg:tags":[
        "physician",
        "clinic",
        "surgeon"
    ],
    "wof:name":"Queensway Medical Ctr",
    "wof:placetype":"venue"
},
  "geometry": {"coordinates":[-75.588417,45.452522],"type":"Point"}
}