{
  "type": "Feature",
  "properties": {
    "addr:full":"101 Rue Maurault Pierreville QC J0G 1J0",
    "addr:housenumber":"101",
    "addr:postcode":"j0g 1j0",
    "addr:street":"Rue Maurault",
    "iso:country":"CA",
    "sg:address":"101 Rue Maurault",
    "sg:city":"Pierreville",
    "sg:classifiers":[
        {
            "category":"Personal",
            "subcategory":"Beauty Salon",
            "type":"Services"
        }
    ],
    "sg:phone":"+1 450 568 3558",
    "sg:postcode":"J0G 1J0",
    "sg:province":"QC",
    "wof:name":"Coiffure Leblanc Enr",
    "wof:placetype":"venue"
},
  "geometry": {"coordinates":[-72.810546875,46.071937561],"type":"Point"}
}