{
  "type": "Feature",
  "properties": {
    "addr:full":"866 the Queensway Etobicoke ON M8Z 1N7",
    "addr:housenumber":"866",
    "addr:postcode":"m8z 1n7",
    "addr:street":"The Queensway",
    "iso:country":"CA",
    "sg:address":"866 the Queensway",
    "sg:city":"Etobicoke",
    "sg:classifiers":[
        {
            "category":"Professional",
            "subcategory":"Accounting & Tax Preparation",
            "type":"Services"
        }
    ],
    "sg:phone":"+1 416 259 1461",
    "sg:postcode":"M8Z 1N7",
    "sg:province":"ON",
    "sg:tags":[
        "accountant"
    ],
    "wof:name":"Alfa Management Svc",
    "wof:placetype":"venue"
},
  "geometry": {"coordinates":[-79.51018500000001,43.624763],"type":"Point"}
}