{
  "type": "Feature",
  "properties": {
    "addr:full":"1122 Islington Ave Etobicoke ON M8Z 4S2",
    "addr:housenumber":"1122",
    "addr:postcode":"m8z 4s2",
    "addr:street":"Islington Ave",
    "iso:country":"CA",
    "sg:address":"1122 Islington Ave",
    "sg:city":"Etobicoke",
    "sg:classifiers":[
        {
            "category":"Health Services",
            "subcategory":"Doctor",
            "type":"Services"
        }
    ],
    "sg:phone":"+1 416 231 3077",
    "sg:postcode":"M8Z 4S2",
    "sg:province":"ON",
    "sg:tags":[
        "physician",
        "surgeon"
    ],
    "wof:name":"Stroz, Edward S MD",
    "wof:placetype":"venue"
},
  "geometry": {"coordinates":[-79.5207824707,43.6380882263],"type":"Point"}
}