{
  "type": "Feature",
  "properties": {
    "iso:country":"CA",
    "sg:address":"63 Main St E",
    "sg:city":"Markdale",
    "sg:classifiers":[
        {
            "category":"Retail",
            "subcategory":"Funeral Services",
            "type":"Services"
        }
    ],
    "sg:phone":"+1 519 986 3310",
    "sg:postcode":"N0C 1H0",
    "sg:province":"ON",
    "sg:tags":[
        "director"
    ],
    "wof:name":"May Funeral Home",
    "wof:placetype":"venue"
},
  "geometry": {"coordinates":[-80.64640808110001,44.3198699951],"type":"Point"}
}