{
  "type": "Feature",
  "properties": {
    "addr:full":"North Vancouver BC V7L 2L3",
    "addr:postcode":"v7l 2l3",
    "iso:country":"CA",
    "sg:city":"North Vancouver",
    "sg:classifiers":[
        {
            "category":"Health Services",
            "subcategory":"Doctor",
            "type":"Services"
        }
    ],
    "sg:phone":"+1 604 987 7722",
    "sg:postcode":"V7L 2L3",
    "sg:province":"BC",
    "sg:tags":[
        "physician",
        "surgeon"
    ],
    "wof:name":"Warren, Donald P MD",
    "wof:placetype":"venue"
},
  "geometry": {"coordinates":[-123.07144928,49.319858551],"type":"Point"}
}