{
  "type": "Feature",
  "properties": {
    "addr:full":"RR 1 Warburg AB T0C 2T0",
    "addr:postcode":"t0c 2t0",
    "addr:street":"Rr 1",
    "iso:country":"CA",
    "sg:address":"RR 1",
    "sg:city":"Warburg",
    "sg:classifiers":[
        {
            "category":"Organizations",
            "subcategory":"Religious Organization",
            "type":"Services"
        }
    ],
    "sg:phone":"+1 403 848 7712",
    "sg:postcode":"T0C 2T0",
    "sg:province":"AB",
    "sg:tags":[
        "church"
    ],
    "wof:name":"First Baptist Church",
    "wof:placetype":"venue"
},
  "geometry": {"coordinates":[-114.318642,53.181034],"type":"Point"}
}