{
  "type": "Feature",
  "properties": {
    "addr:full":"2751 Cliffe Ave #1200 Courtenay BC V9N 2L8",
    "addr:housenumber":"2751",
    "addr:postcode":"v9n 2l8",
    "addr:street":"Cliffe Ave # 1200",
    "iso:country":"CA",
    "sg:address":"2751 Cliffe Ave #1200",
    "sg:city":"Courtenay",
    "sg:classifiers":[
        {
            "category":"Food & Beverages",
            "subcategory":"Specialty",
            "type":"Retail Goods"
        }
    ],
    "sg:phone":"+1 250 334 6192",
    "sg:postcode":"V9N 2L8",
    "sg:province":"BC",
    "sg:tags":[
        "health",
        "diet"
    ],
    "wof:name":"General Nutrition Ctr",
    "wof:placetype":"venue"
},
  "geometry": {"coordinates":[-124.98133900000001,49.673447],"type":"Point"}
}