{
  "type": "Feature",
  "properties": {
    "addr:full":"Toronto ON M5S 3A2",
    "addr:postcode":"m5s 3a2",
    "iso:country":"CA",
    "sg:city":"Toronto",
    "sg:classifiers":[
        {
            "category":"Health Services",
            "subcategory":"Doctor",
            "type":"Services"
        }
    ],
    "sg:phone":"+1 416 924 7100",
    "sg:postcode":"M5S 3A2",
    "sg:province":"ON",
    "sg:tags":[
        "physician",
        "surgeon"
    ],
    "wof:name":"Zaltz, A MD",
    "wof:placetype":"venue"
},
  "geometry": {"coordinates":[-79.38711499999999,43.661186],"type":"Point"}
}