{
  "type": "Feature",
  "properties": {
    "iso:country":"CA",
    "sg:address":"4705 Boul Saint-Jean",
    "sg:city":"Pierrefonds",
    "sg:classifiers":[
        {
            "category":"Restaurant",
            "type":"Food & Drink"
        }
    ],
    "sg:phone":"+1 514 626 6803",
    "sg:postcode":"H9H 2A9",
    "sg:province":"QC",
    "wof:name":"Brasserie LA Residence Inc",
    "wof:placetype":"venue"
},
  "geometry": {"coordinates":[-73.85183,45.491959],"type":"Point"}
}