{
  "type": "Feature",
  "properties": {
    "addr:full":"359 Rue Laberge Saint-Jean-Sur-Richelieu QC J3A 1S1",
    "addr:housenumber":"359",
    "addr:postcode":"j3a 1s1",
    "addr:street":"Rue Laberge",
    "iso:country":"CA",
    "sg:address":"359 Rue Laberge",
    "sg:city":"Saint-Jean-Sur-Richelieu",
    "sg:classifiers":[
        {
            "category":"Autos & Motor Vehicles",
            "subcategory":"Automobile Sales",
            "type":"Retail Goods"
        }
    ],
    "sg:phone":"+1 450 348 6816",
    "sg:postcode":"J3A 1S1",
    "sg:province":"QC",
    "sg:tags":[
        "car",
        "dealer"
    ],
    "wof:name":"Automobiles Cloginor Inc",
    "wof:placetype":"venue"
},
  "geometry": {"coordinates":[-73.267906,45.329109],"type":"Point"}
}