{
  "type": "Feature",
  "properties": {
    "addr:full":"Bolton ON L7E 5A6",
    "addr:postcode":"l7e 5a6",
    "iso:country":"CA",
    "sg:city":"Bolton",
    "sg:classifiers":[
        {
            "category":"Retail",
            "subcategory":"Auto Repair",
            "type":"Services"
        }
    ],
    "sg:phone":"+1 905 857 0997",
    "sg:postcode":"L7E 5A6",
    "sg:province":"ON",
    "sg:tags":[
        "automobile",
        "rustproofing",
        "undercoating",
        "customizing"
    ],
    "wof:name":"Krown Rust Control System",
    "wof:placetype":"venue"
},
  "geometry": {"coordinates":[-79.71923065190001,43.8627357483],"type":"Point"}
}