{
  "type": "Feature",
  "properties": {
    "addr:full":"166 Elmhurst Ave North York ON M2N 1S1",
    "addr:housenumber":"166",
    "addr:postcode":"m2n 1s1",
    "addr:street":"Elmhurst Ave",
    "iso:country":"CA",
    "sg:address":"166 Elmhurst Ave",
    "sg:city":"North York",
    "sg:classifiers":[
        {
            "category":"Professional",
            "subcategory":"Computer Services",
            "type":"Services"
        }
    ],
    "sg:phone":"+1 416 223 8382",
    "sg:postcode":"M2N 1S1",
    "sg:province":"ON",
    "sg:tags":[
        "consultant"
    ],
    "wof:name":"Softrite",
    "wof:placetype":"venue"
},
  "geometry": {"coordinates":[-79.41975402830001,43.7614326477],"type":"Point"}
}