{
  "type": "Feature",
  "properties": {
    "addr:full":"NE 28-7-4E Niverville MB R0A 1E0",
    "addr:housenumber":"28-7-4e",
    "addr:postcode":"r0a 1e0",
    "addr:street":"Ne",
    "iso:country":"CA",
    "sg:address":"NE 28-7-4E",
    "sg:city":"Niverville",
    "sg:classifiers":[
        {
            "category":"Freight",
            "type":"Transportation"
        }
    ],
    "sg:phone":"+1 204 388 6705",
    "sg:postcode":"R0A 1E0",
    "sg:province":"MB",
    "sg:tags":[
        "trucking"
    ],
    "wof:name":"Garelan Transport Ltd",
    "wof:placetype":"venue"
},
  "geometry": {"coordinates":[-97.0414428711,49.6059188843],"type":"Point"}
}