{
  "type": "Feature",
  "properties": {
    "addr:full":"6066 East St Cardinal ON K0E 1E0",
    "addr:housenumber":"6066",
    "addr:postcode":"k0e 1e0",
    "addr:street":"East St",
    "iso:country":"CA",
    "sg:address":"6066 East St",
    "sg:city":"Cardinal",
    "sg:classifiers":[
        {
            "category":"Organizations",
            "subcategory":"Religious Organization",
            "type":"Services"
        }
    ],
    "sg:phone":"+1 613 657 3072",
    "sg:postcode":"K0E 1E0",
    "sg:province":"ON",
    "sg:tags":[
        "church"
    ],
    "wof:name":"Sacred Heart of Jesus Cath Ch",
    "wof:placetype":"venue"
},
  "geometry": {"coordinates":[-75.3747787476,44.7883491516],"type":"Point"}
}