{
  "type": "Feature",
  "properties": {
    "iso:country":"CA",
    "sg:address":"315 23rd Ave E",
    "sg:city":"Vancouver",
    "sg:classifiers":[
        {
            "category":"Education",
            "subcategory":"School",
            "type":"Public Place"
        }
    ],
    "sg:phone":"+1 604 713 4985",
    "sg:postcode":"V5V 1X6",
    "sg:province":"BC",
    "wof:name":"David Livingston Elementary",
    "wof:placetype":"venue"
},
  "geometry": {"coordinates":[-123.098121643,49.2503890991],"type":"Point"}
}