{
  "type": "Feature",
  "properties": {
    "iso:country":"CA",
    "sg:city":"Quebec",
    "sg:classifiers":[
        {
            "category":"Retail",
            "subcategory":"Animal Services",
            "type":"Services"
        }
    ],
    "sg:phone":"+1 418 524 5554",
    "sg:postcode":"G1M 3E5",
    "sg:province":"QC",
    "sg:tags":[
        "pet",
        "shop"
    ],
    "wof:name":"Animalerie Dyno",
    "wof:placetype":"venue"
},
  "geometry": {"coordinates":[-71.248924,46.820335],"type":"Point"}
}