{
  "type": "Feature",
  "properties": {
    "addr:full":"Cote Saint-Luc QC H4W 2T5",
    "addr:postcode":"h4w 2t5",
    "addr:street":"Cote Saint-Luc",
    "iso:country":"CA",
    "sg:city":"Cote Saint-Luc",
    "sg:classifiers":[
        {
            "category":"Real Estate",
            "subcategory":"Real Estate Agent",
            "type":"Services"
        }
    ],
    "sg:phone":"+1 514 483 5503",
    "sg:postcode":"H4W 2T5",
    "sg:province":"QC",
    "sg:tags":[
        "management"
    ],
    "wof:name":"Richard & Roy Salomon Inc",
    "wof:placetype":"venue"
},
  "geometry": {"coordinates":[-73.66176605219999,45.4759483337],"type":"Point"}
}