{
  "type": "Feature",
  "properties": {
    "addr:full":"2155 Ferry Ave Prince George BC V2N 5E8",
    "addr:housenumber":"2155",
    "addr:postcode":"v2n 5e8",
    "addr:street":"Ferry Ave",
    "iso:country":"CA",
    "sg:address":"2155 Ferry Ave",
    "sg:city":"Prince George",
    "sg:classifiers":[
        {
            "category":"Insurance",
            "subcategory":"Insurance Agent",
            "type":"Services"
        }
    ],
    "sg:phone":"+1 250 562 6337",
    "sg:postcode":"V2N 5E8",
    "sg:province":"BC",
    "wof:name":"Sussex Insurance",
    "wof:placetype":"venue"
},
  "geometry": {"coordinates":[-122.768394,53.888542],"type":"Point"}
}