{
  "type": "Feature",
  "properties": {
    "addr:full":"1345 Boul Moody Terrebonne QC J6W 3L1",
    "addr:housenumber":"1345",
    "addr:postcode":"j6w 3l1",
    "addr:street":"Boul Moody",
    "iso:country":"CA",
    "sg:address":"1345 Boul Moody",
    "sg:city":"Terrebonne",
    "sg:classifiers":[
        {
            "category":"Food & Beverages",
            "subcategory":"Groceries & Convenience Stores",
            "type":"Retail Goods"
        }
    ],
    "sg:phone":"+1 450 471 1009",
    "sg:postcode":"J6W 3L1",
    "sg:province":"QC",
    "sg:tags":[
        "grocer"
    ],
    "wof:name":"Maxi",
    "wof:placetype":"venue"
},
  "geometry": {"coordinates":[-73.64868927000001,45.7034912109],"type":"Point"}
}