{
  "type": "Feature",
  "properties": {
    "iso:country":"CA",
    "sg:address":"7118 Boul Saint-Laurent",
    "sg:city":"Montreal",
    "sg:classifiers":[
        {
            "category":"Travel",
            "subcategory":"Travel Agent",
            "type":"Entertainment"
        }
    ],
    "sg:phone":"+1 514 270 6222",
    "sg:postcode":"H2S 3E2",
    "sg:province":"QC",
    "sg:tags":[
        "agency",
        "bureau"
    ],
    "wof:name":"Place DE LA Croisiere Inc",
    "wof:placetype":"venue"
},
  "geometry": {"coordinates":[-73.617218,45.534042],"type":"Point"}
}