{
  "type": "Feature",
  "properties": {
    "iso:country":"CA",
    "sg:city":"Montreal",
    "sg:classifiers":[
        {
            "category":"Banks & Credit Unions",
            "subcategory":"Investment Brokerage",
            "type":"Services"
        }
    ],
    "sg:phone":"+1 514 399 9897",
    "sg:postcode":"H3B 1X9",
    "sg:province":"QC",
    "sg:tags":[
        "consultant",
        "financing"
    ],
    "wof:name":"Global Financial Svc",
    "wof:placetype":"venue"
},
  "geometry": {"coordinates":[-73.556435,45.514412],"type":"Point"}
}