{
  "type": "Feature",
  "properties": {
    "addr:full":"10102 Fraser Ave Fort Mcmurray AB T9H 5C2",
    "addr:housenumber":"10102",
    "addr:postcode":"t9h 5c2",
    "addr:street":"Fraser Ave",
    "iso:country":"CA",
    "sg:address":"10102 Fraser Ave",
    "sg:city":"Fort Mcmurray",
    "sg:classifiers":[
        {
            "category":"Travel",
            "subcategory":"Hotels & Motels",
            "type":"Entertainment"
        }
    ],
    "sg:phone":"+1 780 790 2367",
    "sg:postcode":"T9H 5C2",
    "sg:province":"AB",
    "sg:tags":[
        "breakfast",
        "accommodation",
        "bed"
    ],
    "wof:name":"Chez Dube Country Inn",
    "wof:placetype":"venue"
},
  "geometry": {"coordinates":[-111.382347107,56.7305717468],"type":"Point"}
}