{
  "type": "Feature",
  "properties": {
    "addr:full":"232 Main St S Newmarket ON L3Y 3Z5",
    "addr:housenumber":"232",
    "addr:postcode":"l3y 3z5",
    "addr:street":"Main St S",
    "iso:country":"CA",
    "sg:address":"232 Main St S",
    "sg:city":"Newmarket",
    "sg:classifiers":[
        {
            "category":"Personal",
            "subcategory":"Beauty Salon",
            "type":"Services"
        }
    ],
    "sg:phone":"+1 905 953 5427",
    "sg:postcode":"L3Y 3Z5",
    "sg:province":"ON",
    "wof:name":"Hair CO",
    "wof:placetype":"venue"
},
  "geometry": {"coordinates":[-79.45695495610001,44.0523033142],"type":"Point"}
}