{
  "type": "Feature",
  "properties": {
    "addr:full":"87 Wilson Ave Timmins ON P4N 2S8",
    "addr:housenumber":"87",
    "addr:postcode":"p4n 2s8",
    "addr:street":"Wilson Ave",
    "iso:country":"CA",
    "sg:address":"87 Wilson Ave",
    "sg:city":"Timmins",
    "sg:classifiers":[
        {
            "category":"Real Estate",
            "subcategory":"Real Estate Operator",
            "type":"Services"
        }
    ],
    "sg:phone":"+1 705 264 1172",
    "sg:postcode":"P4N 2S8",
    "sg:province":"ON",
    "sg:tags":[
        "building",
        "parks"
    ],
    "wof:name":"G R Belanger Enterprises Ltd",
    "wof:placetype":"venue"
},
  "geometry": {"coordinates":[-81.33775300000001,48.475216],"type":"Point"}
}