{
  "type": "Feature",
  "properties": {
    "addr:full":"4707 51 St Lamont AB T0B 2R0",
    "addr:housenumber":"4707",
    "addr:postcode":"t0b 2r0",
    "addr:street":"51 St",
    "iso:country":"CA",
    "sg:address":"4707 51 St",
    "sg:city":"Lamont",
    "sg:classifiers":[
        {
            "category":"Banks & Credit Unions",
            "subcategory":"Bank",
            "type":"Services"
        }
    ],
    "sg:phone":"+1 780 895 5920",
    "sg:postcode":"T0B 2R0",
    "sg:province":"AB",
    "wof:name":"Capital City Savings & Cu",
    "wof:placetype":"venue"
},
  "geometry": {"coordinates":[-112.779388428,53.7608718872],"type":"Point"}
}