{
  "type": "Feature",
  "properties": {
    "addr:full":"3510 48 Ave Athabasca AB T9S 1T9",
    "addr:housenumber":"3510",
    "addr:postcode":"t9s 1t9",
    "addr:street":"48 Ave",
    "iso:country":"CA",
    "sg:address":"3510 48 Ave",
    "sg:city":"Athabasca",
    "sg:classifiers":[
        {
            "category":"Organizations",
            "subcategory":"Religious Organization",
            "type":"Services"
        }
    ],
    "sg:phone":"+1 780 675 2333",
    "sg:postcode":"T9S 1T9",
    "sg:province":"AB",
    "sg:tags":[
        "church"
    ],
    "wof:name":"Riverview Community Church",
    "wof:placetype":"venue"
},
  "geometry": {"coordinates":[-113.25984200000001,54.716942],"type":"Point"}
}