{
  "type": "Feature",
  "properties": {
    "addr:full":"Eston SK S0L 1A0",
    "addr:postcode":"s0l 1a0",
    "addr:street":"Eston",
    "iso:country":"CA",
    "sg:city":"Eston",
    "sg:classifiers":[
        {
            "category":"Freight",
            "type":"Transportation"
        }
    ],
    "sg:phone":"+1 306 962 4348",
    "sg:postcode":"S0L 1A0",
    "sg:province":"SK",
    "sg:tags":[
        "grain",
        "elevator"
    ],
    "wof:name":"Agra Enterprises Ltd",
    "wof:placetype":"venue"
},
  "geometry": {"coordinates":[-108.754707336,51.1537055969],"type":"Point"}
}