{
  "type": "Feature",
  "properties": {
    "addr:full":"1035 Wharncliffe Rd S London ON N6L 1J9",
    "addr:housenumber":"1035",
    "addr:postcode":"n6l 1j9",
    "addr:street":"Wharncliffe Rd",
    "iso:country":"CA",
    "sg:address":"1035 Wharncliffe Rd S",
    "sg:city":"London",
    "sg:classifiers":[
        {
            "category":"Autos & Motor Vehicles",
            "subcategory":"Automobile Sales",
            "type":"Retail Goods"
        }
    ],
    "sg:phone":"+1 519 690 1600",
    "sg:postcode":"N6L 1J9",
    "sg:province":"ON",
    "sg:tags":[
        "car",
        "dealer"
    ],
    "wof:name":"Volvo of London",
    "wof:placetype":"venue"
},
  "geometry": {"coordinates":[-81.260498,42.937878],"type":"Point"}
}