{
  "type": "Feature",
  "properties": {
    "iso:country":"CA",
    "sg:address":"30 Boul Don-Quichotte",
    "sg:city":"L'Ile-Perrot",
    "sg:classifiers":[
        {
            "category":"Autos & Motor Vehicles",
            "subcategory":"Automobile Sales",
            "type":"Retail Goods"
        }
    ],
    "sg:phone":"+1 514 990 0204",
    "sg:postcode":"J7V 6N5",
    "sg:province":"QC",
    "sg:tags":[
        "car",
        "dealer"
    ],
    "wof:name":"Avantage Ford Inc",
    "wof:placetype":"venue"
},
  "geometry": {"coordinates":[-73.9656677246,45.3899421692],"type":"Point"}
}