{
  "type": "Feature",
  "properties": {
    "addr:full":"North York ON M3L 1S5",
    "addr:postcode":"m3l 1s5",
    "iso:country":"CA",
    "sg:city":"North York",
    "sg:classifiers":[
        {
            "category":"Health Services",
            "subcategory":"Health Practitioner",
            "type":"Services"
        }
    ],
    "sg:phone":"+1 416 742 3767",
    "sg:postcode":"M3L 1S5",
    "sg:province":"ON",
    "sg:tags":[
        "physiotherapist"
    ],
    "wof:name":"Genesis Rehabilitation",
    "wof:placetype":"venue"
},
  "geometry": {"coordinates":[-79.5140075684,43.7418403625],"type":"Point"}
}