{
  "type": "Feature",
  "properties": {
    "addr:full":"79 Halibut St Kitimat BC V8C 2K6",
    "addr:housenumber":"79",
    "addr:postcode":"bc v8c 2k6",
    "addr:street":"Halibut St",
    "iso:country":"CA",
    "sg:address":"79 Halibut St",
    "sg:city":"Kitimat",
    "sg:classifiers":[
        {
            "category":"Personal",
            "subcategory":"Beauty Salon",
            "type":"Services"
        }
    ],
    "sg:phone":"+1 250 632 3300",
    "sg:postcode":"V8C 2K6",
    "sg:province":"BC",
    "wof:name":"Sunflower Esthetics",
    "wof:placetype":"venue"
},
  "geometry": {"coordinates":[-128.60548399999999,54.089653],"type":"Point"}
}