{
  "type": "Feature",
  "properties": {
    "addr:full":"Toronto ON M5H 2Y2",
    "addr:postcode":"m5h 2y2",
    "iso:country":"CA",
    "sg:city":"Toronto",
    "sg:classifiers":[
        {
            "category":"Professional",
            "subcategory":"Lawyer & Legal Services",
            "type":"Services"
        }
    ],
    "sg:phone":"+1 416 368 4666",
    "sg:postcode":"M5H 2Y2",
    "sg:province":"ON",
    "sg:tags":[
        "attorney"
    ],
    "wof:name":"Munroe, Andrew",
    "wof:placetype":"venue"
},
  "geometry": {"coordinates":[-79.381676,43.651512],"type":"Point"}
}