{
  "type": "Feature",
  "properties": {
    "addr:full":"34 Anne St S Barrie ON L4N 4S8",
    "addr:housenumber":"34",
    "addr:postcode":"l4n 4s8",
    "addr:street":"Anne St S",
    "iso:country":"CA",
    "sg:address":"34 Anne St S",
    "sg:city":"Barrie",
    "sg:classifiers":[
        {
            "category":"Retail",
            "subcategory":"Auto Repair",
            "type":"Services"
        }
    ],
    "sg:phone":"+1 705 726 6443",
    "sg:postcode":"L4N 4S8",
    "sg:province":"ON",
    "sg:tags":[
        "repairing",
        "automobile",
        "tire"
    ],
    "wof:name":"Harper Tire Ltd",
    "wof:placetype":"venue"
},
  "geometry": {"coordinates":[-79.7035827637,44.3802833557],"type":"Point"}
}