{
  "type": "Feature",
  "properties": {
    "addr:full":"100 Du Couvent Armagh QC G0R 1A0",
    "addr:housenumber":"100",
    "addr:postcode":"g0r 1a0",
    "addr:street":"Du Couvent",
    "iso:country":"CA",
    "sg:address":"100 Du Couvent",
    "sg:city":"Armagh",
    "sg:classifiers":[
        {
            "category":"Sports & Exercise",
            "subcategory":"Bowling",
            "type":"Entertainment"
        }
    ],
    "sg:phone":"+1 418 466 2450",
    "sg:postcode":"G0R 1A0",
    "sg:province":"QC",
    "sg:tags":[
        "center"
    ],
    "wof:name":"Salon DE Quilles Le Sommet",
    "wof:placetype":"venue"
},
  "geometry": {"coordinates":[-70.58879899999999,46.744251],"type":"Point"}
}