{
  "type": "Feature",
  "properties": {
    "addr:full":"123 Robin Cres Saskatoon SK S7L 6M3",
    "addr:housenumber":"123",
    "addr:postcode":"s7l 6m3",
    "addr:street":"Robin Cres",
    "iso:country":"CA",
    "sg:address":"123 Robin Cres",
    "sg:city":"Saskatoon",
    "sg:classifiers":[
        {
            "category":"Retail",
            "subcategory":"Auto Repair",
            "type":"Services"
        }
    ],
    "sg:phone":"+1 306 244 8070",
    "sg:postcode":"S7L 6M3",
    "sg:province":"SK",
    "sg:tags":[
        "repairing",
        "automobile"
    ],
    "wof:name":"Empire Tire & Auto Ltd",
    "wof:placetype":"venue"
},
  "geometry": {"coordinates":[-106.67957305900001,52.1580734253],"type":"Point"}
}