{
  "type": "Feature",
  "properties": {
    "addr:full":"521 11th Ave Hanover ON N4N 2S3",
    "addr:housenumber":"521",
    "addr:postcode":"n4n 2s3",
    "addr:street":"11Th Ave",
    "iso:country":"CA",
    "sg:address":"521 11th Ave",
    "sg:city":"Hanover",
    "sg:classifiers":[
        {
            "category":"Organizations",
            "subcategory":"Non-profit Organization",
            "type":"Services"
        }
    ],
    "sg:phone":"+1 519 364 6100",
    "sg:postcode":"N4N 2S3",
    "sg:province":"ON",
    "sg:tags":[
        "disability"
    ],
    "wof:name":"Harc Inc",
    "wof:placetype":"venue"
},
  "geometry": {"coordinates":[-81.02538300000001,44.154156],"type":"Point"}
}