{
  "type": "Feature",
  "properties": {
    "iso:country":"CA",
    "sg:address":"630 Rue Poisson",
    "sg:city":"Trois-Rivieres",
    "sg:classifiers":[
        {
            "category":"Organizations",
            "subcategory":"Professional Association",
            "type":"Services"
        }
    ],
    "sg:phone":"+1 819 371 7778",
    "sg:postcode":"G9A 2V5",
    "sg:province":"QC",
    "wof:name":"Moisson Mauricie",
    "wof:placetype":"venue"
},
  "geometry": {"coordinates":[-72.5511703491,46.3346214294],"type":"Point"}
}