{
  "type": "Feature",
  "properties": {
    "addr:full":"1585 Dundas St W Toronto ON M6K 1T9",
    "addr:housenumber":"1585",
    "addr:postcode":"m6k 1t9",
    "addr:street":"Dundas St W",
    "iso:country":"CA",
    "sg:address":"1585 Dundas St W",
    "sg:city":"Toronto",
    "sg:classifiers":[
        {
            "category":"Restaurant",
            "type":"Food & Drink"
        }
    ],
    "sg:phone":"+1 416 588 0307",
    "sg:postcode":"M6K 1T9",
    "sg:province":"ON",
    "wof:name":"Lula Lounge",
    "wof:placetype":"venue"
},
  "geometry": {"coordinates":[-79.43469238279999,43.6496963501],"type":"Point"}
}