{
  "type": "Feature",
  "properties": {
    "iso:country":"CA",
    "sg:address":"1585 Dundas St W",
    "sg:city":"Toronto",
    "sg:classifiers":[
        {
            "category":"Restaurant",
            "type":"Food & Drink"
        }
    ],
    "sg:phone":"+1 416 588 0307",
    "sg:postcode":"M6K 1T9",
    "sg:province":"ON",
    "wof:name":"Lula Lounge",
    "wof:placetype":"venue"
},
  "geometry": {"coordinates":[-79.43469238279999,43.6496963501],"type":"Point"}
}