{
  "type": "Feature",
  "properties": {
    "addr:full":"7600 Boul Marie-Victorin Brossard QC J4W 1B2",
    "addr:housenumber":"7600",
    "addr:postcode":"j4w 1b2",
    "addr:street":"Boul Marie-Victorin",
    "iso:country":"CA",
    "sg:address":"7600 Boul Marie-Victorin",
    "sg:city":"Brossard",
    "sg:classifiers":[
        {
            "category":"Travel",
            "subcategory":"Hotels & Motels",
            "type":"Entertainment"
        }
    ],
    "sg:phone":"+1 450 671 2299",
    "sg:postcode":"J4W 1B2",
    "sg:province":"QC",
    "wof:name":"Motel Champlain",
    "wof:placetype":"venue"
},
  "geometry": {"coordinates":[-73.4935379028,45.4604415894],"type":"Point"}
}