{
  "type": "Feature",
  "properties": {
    "addr:full":"6649 Maple Rd Egmont BC V0N 1N0",
    "addr:housenumber":"6649",
    "addr:postcode":"v0n 1n0",
    "addr:street":"Maple Rd",
    "iso:country":"CA",
    "sg:address":"6649 Maple Rd",
    "sg:city":"Egmont",
    "sg:classifiers":[
        {
            "category":"Travel",
            "subcategory":"Campground",
            "type":"Entertainment"
        }
    ],
    "sg:phone":"+1 604 883 3667",
    "sg:postcode":"V0N 1N0",
    "sg:province":"BC",
    "sg:tags":[
        "camp"
    ],
    "wof:name":"West Coast Wilderness Lodge",
    "wof:placetype":"venue"
},
  "geometry": {"coordinates":[-123.956375122,49.7602958679],"type":"Point"}
}