{
  "type": "Feature",
  "properties": {
    "addr:full":"123 Av Frontenac Pointe-Claire QC H9R 4Z7",
    "addr:postcode":"h9r 4z7",
    "addr:street":"123 Av Frontenac",
    "iso:country":"CA",
    "sg:address":"123 Av Frontenac",
    "sg:city":"Pointe-Claire",
    "sg:classifiers":[
        {
            "category":"Real Estate",
            "subcategory":"Real Estate Agent",
            "type":"Services"
        }
    ],
    "sg:phone":"+1 514 426 9595",
    "sg:postcode":"H9R 4Z7",
    "sg:province":"QC",
    "wof:name":"Sutton Groupe Performer Inc",
    "wof:placetype":"venue"
},
  "geometry": {"coordinates":[-73.827698,45.468819],"type":"Point"}
}