{
  "type": "Feature",
  "properties": {
    "addr:full":"3 Alberta Ave Toronto ON M6H 2R5",
    "addr:housenumber":"3",
    "addr:postcode":"m6h 2r5",
    "addr:street":"Alberta Ave",
    "iso:country":"CA",
    "sg:address":"3 Alberta Ave",
    "sg:city":"Toronto",
    "sg:classifiers":[
        {
            "category":"Retail",
            "subcategory":"Veterinary Services",
            "type":"Services"
        }
    ],
    "sg:phone":"+1 416 651 1357",
    "sg:postcode":"M6H 2R5",
    "sg:province":"ON",
    "sg:tags":[
        "veterinarian"
    ],
    "wof:name":"Alberta Veterinary Svc",
    "wof:placetype":"venue"
},
  "geometry": {"coordinates":[-79.4313964844,43.6749649048],"type":"Point"}
}