{
  "type": "Feature",
  "properties": {
    "addr:full":"95 Main St S Bayfield ON N0M 1G0",
    "addr:housenumber":"95",
    "addr:postcode":"n0m 1g0",
    "addr:street":"Main St S",
    "iso:country":"CA",
    "sg:address":"95 Main St S",
    "sg:city":"Bayfield",
    "sg:classifiers":[
        {
            "category":"Real Estate",
            "subcategory":"Real Estate Agent",
            "type":"Services"
        }
    ],
    "sg:phone":"+1 519 565 2020",
    "sg:postcode":"N0M 1G0",
    "sg:province":"ON",
    "wof:name":"Re/Max Bluewater Realty Inc",
    "wof:placetype":"venue"
},
  "geometry": {"coordinates":[-81.691154,43.55685],"type":"Point"}
}