{
  "type": "Feature",
  "properties": {
    "addr:full":"1 King St W Harrow ON N0R 1G0",
    "addr:housenumber":"1",
    "addr:postcode":"n0r 1g0",
    "addr:street":"King St W",
    "iso:country":"CA",
    "sg:address":"1 King St W",
    "sg:city":"Harrow",
    "sg:classifiers":[
        {
            "category":"Food & Beverages",
            "subcategory":"Liquor & Beverages",
            "type":"Retail Goods"
        }
    ],
    "sg:phone":"+1 519 738 4344",
    "sg:postcode":"N0R 1G0",
    "sg:province":"ON",
    "sg:tags":[
        "beer",
        "ale"
    ],
    "wof:name":"Beer Store",
    "wof:placetype":"venue"
},
  "geometry": {"coordinates":[-82.91900634770001,42.0355682373],"type":"Point"}
}