{
  "type": "Feature",
  "properties": {
    "addr:full":"700 Harwood Ave S Ajax ON L1S 3Y9",
    "addr:housenumber":"700",
    "addr:postcode":"l1s 3y9",
    "addr:street":"Harwood Ave S",
    "iso:country":"CA",
    "sg:address":"700 Harwood Ave S",
    "sg:city":"Ajax",
    "sg:classifiers":[
        {
            "category":"Bars & Pubs",
            "type":"Food & Drink"
        }
    ],
    "sg:phone":"+1 905 428 1815",
    "sg:postcode":"L1S 3Y9",
    "sg:province":"ON",
    "wof:name":"Tudor Rose",
    "wof:placetype":"venue"
},
  "geometry": {"coordinates":[-79.0153808594,43.8344116211],"type":"Point"}
}