{
  "type": "Feature",
  "properties": {
    "addr:full":"46 Rue Blainville O Sainte-Therese QC J7E 1X3",
    "addr:housenumber":"46",
    "addr:postcode":"j7e 1x3",
    "addr:street":"Rue Blainville O Sainte-Therese",
    "iso:country":"CA",
    "sg:address":"46 Rue Blainville O",
    "sg:city":"Sainte-Therese",
    "sg:classifiers":[
        {
            "category":"Education",
            "subcategory":"School",
            "type":"Public Place"
        }
    ],
    "sg:phone":"+1 450 433 5505",
    "sg:postcode":"J7E 1X3",
    "sg:province":"QC",
    "wof:name":"Ecole Mgr Philippe Labelle",
    "wof:placetype":"venue"
},
  "geometry": {"coordinates":[-73.83669999999999,45.639126],"type":"Point"}
}