{
  "type": "Feature",
  "properties": {
    "addr:full":"428 Rue Principale Saint-Donat-DE-Montcalm QC J0T 2C0",
    "addr:housenumber":"428",
    "addr:postcode":"j0t 2c0",
    "addr:street":"Rue Principale",
    "iso:country":"CA",
    "sg:address":"428 Rue Principale",
    "sg:city":"Saint-Donat-DE-Montcalm",
    "sg:classifiers":[
        {
            "category":"Shopping",
            "subcategory":"Clothing, Apparel, & Fashions",
            "type":"Retail Goods"
        }
    ],
    "sg:phone":"+1 819 424 2444",
    "sg:postcode":"J0T 2C0",
    "sg:province":"QC",
    "wof:name":"Boutique Clau an",
    "wof:placetype":"venue"
},
  "geometry": {"coordinates":[-74.22266399999999,46.318993],"type":"Point"}
}