{
  "type": "Feature",
  "properties": {
    "addr:full":"1082 Jutland Pl Oakville ON L6H 2V3",
    "addr:housenumber":"1082",
    "addr:postcode":"l6h 2v3",
    "addr:street":"Jutland Pl",
    "iso:country":"CA",
    "sg:address":"1082 Jutland Pl",
    "sg:city":"Oakville",
    "sg:classifiers":[
        {
            "category":"Health Services",
            "subcategory":"Health Practitioner",
            "type":"Services"
        }
    ],
    "sg:phone":"+1 905 844 0077",
    "sg:postcode":"L6H 2V3",
    "sg:province":"ON",
    "sg:tags":[
        "psychotherapist"
    ],
    "wof:name":"New Beginnings Counselling Svc",
    "wof:placetype":"venue"
},
  "geometry": {"coordinates":[-79.68940000000001,43.479626],"type":"Point"}
}