{
  "type": "Feature",
  "properties": {
    "iso:country":"CA",
    "sg:address":"47 Ch DE LA Riviere",
    "sg:city":"Grand-Remous",
    "sg:classifiers":[
        {
            "category":"Building & Trades",
            "subcategory":"Construction",
            "type":"Services"
        }
    ],
    "sg:phone":"+1 819 438 2979",
    "sg:postcode":"J0W 1E0",
    "sg:province":"QC",
    "sg:tags":[
        "excavating",
        "contractor"
    ],
    "wof:name":"Yvon Ycm Coulombe Enr Excvtn",
    "wof:placetype":"venue"
},
  "geometry": {"coordinates":[-75.9120101929,46.5965614319],"type":"Point"}
}