{
  "type": "Feature",
  "properties": {
    "addr:full":"888 Rue Berlier Laval QC H7L 4K5",
    "addr:housenumber":"888",
    "addr:postcode":"h7l 4k5",
    "addr:street":"Rue Berlier",
    "iso:country":"CA",
    "sg:address":"888 Rue Berlier",
    "sg:city":"Laval",
    "sg:classifiers":[
        {
            "category":"Insurance",
            "subcategory":"Hazard Insurance",
            "type":"Services"
        }
    ],
    "sg:phone":"+1 514 856 1087",
    "sg:postcode":"H7L 4K5",
    "sg:province":"QC",
    "sg:tags":[
        "warranty",
        "automobile",
        "program",
        "processing"
    ],
    "wof:name":"Garanties Nationales Mrwv",
    "wof:placetype":"venue"
},
  "geometry": {"coordinates":[-73.740524292,45.5870704651],"type":"Point"}
}