{
  "type": "Feature",
  "properties": {
    "addr:full":"782 Diltz Rd Dunnville ON N1A 2W2",
    "addr:housenumber":"782",
    "addr:postcode":"n1a 2w2",
    "addr:street":"Diltz Rd",
    "iso:country":"CA",
    "sg:address":"782 Diltz Rd",
    "sg:city":"Dunnville",
    "sg:classifiers":[
        {
            "category":"Wholesale",
            "subcategory":"Plants",
            "type":"Manufacturing & Wholesale Goods"
        }
    ],
    "sg:phone":"+1 905 774 3328",
    "sg:postcode":"N1A 2W2",
    "sg:province":"ON",
    "sg:tags":[
        "florist"
    ],
    "wof:name":"Pine Ridge Gardens",
    "wof:placetype":"venue"
},
  "geometry": {"coordinates":[-79.5825958252,42.9556655884],"type":"Point"}
}