{
  "type": "Feature",
  "properties": {
    "addr:full":"747 Glenforest St Oshawa ON L1J 5E9",
    "addr:housenumber":"747",
    "addr:postcode":"l1j 5e9",
    "addr:street":"Glenforest St",
    "iso:country":"CA",
    "sg:address":"747 Glenforest St",
    "sg:city":"Oshawa",
    "sg:classifiers":[
        {
            "category":"Wholesale",
            "subcategory":"Groceries",
            "type":"Manufacturing & Wholesale Goods"
        }
    ],
    "sg:phone":"+1 905 728 2338",
    "sg:postcode":"L1J 5E9",
    "sg:province":"ON",
    "sg:tags":[
        "food",
        "product"
    ],
    "wof:name":"Watkins Products",
    "wof:placetype":"venue"
},
  "geometry": {"coordinates":[-78.888519,43.913441],"type":"Point"}
}