{
  "type": "Feature",
  "properties": {
    "iso:country":"CA",
    "sg:address":"55 Rue DE L'Eglise",
    "sg:city":"Verdun",
    "sg:classifiers":[
        {
            "category":"Health Services",
            "subcategory":"Doctor",
            "type":"Services"
        }
    ],
    "sg:phone":"+1 514 766 8700",
    "sg:postcode":"H4G 3E7",
    "sg:province":"QC",
    "sg:tags":[
        "clinic"
    ],
    "wof:name":"Dauphin Savard Et Assoc",
    "wof:placetype":"venue"
},
  "geometry": {"coordinates":[-73.5642776489,45.4628410339],"type":"Point"}
}