{
  "type": "Feature",
  "properties": {
    "addr:full":"1497 5E Av Shawinigan-Sud QC G9P 1M4",
    "addr:housenumber":"1497",
    "addr:postcode":"g9p 1m4",
    "addr:street":"5E Av Shawinigan-Sud",
    "iso:country":"CA",
    "sg:address":"1497 5E Av",
    "sg:city":"Shawinigan-Sud",
    "sg:classifiers":[
        {
            "category":"Banks & Credit Unions",
            "subcategory":"Bank",
            "type":"Services"
        }
    ],
    "sg:phone":"+1 819 536 4451",
    "sg:postcode":"G9P 1M4",
    "sg:province":"QC",
    "wof:name":"Cibc",
    "wof:placetype":"venue"
},
  "geometry": {"coordinates":[-72.74949599999999,46.523163],"type":"Point"}
}