{
  "type": "Feature",
  "properties": {
    "iso:country":"CA",
    "sg:address":"2400 Rue Bauman",
    "sg:city":"Jonquiere",
    "sg:classifiers":[
        {
            "category":"Freight",
            "type":"Transportation"
        }
    ],
    "sg:phone":"+1 418 548 7202",
    "sg:postcode":"G7S 4S4",
    "sg:province":"QC",
    "sg:tags":[
        "trucking"
    ],
    "wof:name":"Transport Nolicam Inc",
    "wof:placetype":"venue"
},
  "geometry": {"coordinates":[-71.1624221802,48.4051895142],"type":"Point"}
}