{
  "type": "Feature",
  "properties": {
    "addr:full":"4852 Highway 12 Kentville NS B4N 3V8",
    "addr:housenumber":"4852",
    "addr:postcode":"b4n 3v8",
    "addr:street":"Highway 12",
    "iso:country":"CA",
    "sg:address":"4852 Highway 12",
    "sg:city":"Kentville",
    "sg:classifiers":[
        {
            "category":"Food & Beverages",
            "subcategory":"Fruits & Vegetables",
            "type":"Retail Goods"
        }
    ],
    "sg:phone":"+1 902 678 1206",
    "sg:postcode":"B4N 3V8",
    "sg:province":"NS",
    "sg:tags":[
        "farm",
        "produce",
        "market"
    ],
    "wof:name":"Doyle's Farm Market",
    "wof:placetype":"venue"
},
  "geometry": {"coordinates":[-64.494438,45.07692],"type":"Point"}
}