{
  "type": "Feature",
  "properties": {
    "addr:full":"292 King St W Dundas ON L9H 1W4",
    "addr:housenumber":"292",
    "addr:postcode":"l9h 1w4",
    "addr:street":"King St W",
    "iso:country":"CA",
    "sg:address":"292 King St W",
    "sg:city":"Dundas",
    "sg:classifiers":[
        {
            "category":"Shopping",
            "subcategory":"Discount & Variety Stores",
            "type":"Retail Goods"
        }
    ],
    "sg:phone":"+1 905 627 0901",
    "sg:postcode":"L9H 1W4",
    "sg:province":"ON",
    "wof:name":"Blair's Variety",
    "wof:placetype":"venue"
},
  "geometry": {"coordinates":[-79.967361,43.269527],"type":"Point"}
}