{
  "type": "Feature",
  "properties": {
    "iso:country":"CA",
    "sg:address":"1965 14th Ave W",
    "sg:city":"Vancouver",
    "sg:classifiers":[
        {
            "category":"Wholesale",
            "subcategory":"Furniture",
            "type":"Manufacturing & Wholesale Goods"
        }
    ],
    "sg:phone":"+1 604 736 7617",
    "sg:postcode":"V6J 2K1",
    "sg:province":"BC",
    "wof:name":"Jan Spitzner Agencies",
    "wof:placetype":"venue"
},
  "geometry": {"coordinates":[-123.149719238,49.2592735291],"type":"Point"}
}