{
  "type": "Feature",
  "properties": {
    "addr:full":"52 Place Holtham Hampstead QC H3X 3N5",
    "addr:housenumber":"52",
    "addr:postcode":"h3x 3n5",
    "addr:street":"Place Holtham",
    "iso:country":"CA",
    "sg:address":"52 Place Holtham",
    "sg:city":"Hampstead",
    "sg:classifiers":[
        {
            "category":"Real Estate",
            "subcategory":"Real Estate Agent",
            "type":"Services"
        }
    ],
    "sg:phone":"+1 514 486 2845",
    "sg:postcode":"H3X 3N5",
    "sg:province":"QC",
    "wof:name":"Immeubles Anita Glazer",
    "wof:placetype":"venue"
},
  "geometry": {"coordinates":[-73.64774300000001,45.475624],"type":"Point"}
}