{
  "type": "Feature",
  "properties": {
    "iso:country":"CA",
    "sg:address":"142 East St N",
    "sg:city":"Sarnia",
    "sg:classifiers":[
        {
            "category":"Shopping",
            "subcategory":"Discount & Variety Stores",
            "type":"Retail Goods"
        }
    ],
    "sg:phone":"+1 519 344 7112",
    "sg:postcode":"N7T 6X2",
    "sg:province":"ON",
    "wof:name":"Peter's Variety",
    "wof:placetype":"venue"
},
  "geometry": {"coordinates":[-82.38655853269999,42.9716033936],"type":"Point"}
}