{
  "type": "Feature",
  "properties": {
    "iso:country":"CA",
    "sg:city":"Mississauga",
    "sg:classifiers":[
        {
            "category":"Professional",
            "subcategory":"Advertising",
            "type":"Services"
        }
    ],
    "sg:phone":"+1 905 542 0225",
    "sg:postcode":"L5N 5M3",
    "sg:province":"ON",
    "sg:tags":[
        "designer",
        "display",
        "producer"
    ],
    "wof:name":"Generation 3 Exhibits Inc",
    "wof:placetype":"venue"
},
  "geometry": {"coordinates":[-79.736473,43.606407],"type":"Point"}
}