{
  "type": "Feature",
  "properties": {
    "addr:full":"2430 Finch Ave W North York ON M9M 2E1",
    "addr:housenumber":"2430",
    "addr:postcode":"m9m 2e1",
    "addr:street":"Finch Ave W",
    "iso:country":"CA",
    "sg:address":"2430 Finch Ave W",
    "sg:city":"North York",
    "sg:classifiers":[
        {
            "category":"Autos & Motor Vehicles",
            "subcategory":"Auto Supplies",
            "type":"Retail Goods"
        }
    ],
    "sg:phone":"+1 416 746 2585",
    "sg:postcode":"M9M 2E1",
    "sg:province":"ON",
    "sg:tags":[
        "tire"
    ],
    "wof:name":"Fast'n Tire & Auto Ctr",
    "wof:placetype":"venue"
},
  "geometry": {"coordinates":[-79.55101000000001,43.750374],"type":"Point"}
}