{
  "type": "Feature",
  "properties": {
    "addr:full":"PO Box 23 Harbour Grace NL A0A 2M0",
    "addr:housenumber":"po box 23",
    "addr:postcode":"a0a 2m0",
    "iso:country":"CA",
    "sg:address":"PO Box 23",
    "sg:city":"Harbour Grace",
    "sg:classifiers":[
        {
            "category":"Organizations",
            "subcategory":"Professional Association",
            "type":"Services"
        }
    ],
    "sg:phone":"+1 709 596 6176",
    "sg:postcode":"A0A 2M0",
    "sg:province":"NL",
    "sg:tags":[
        "club"
    ],
    "wof:name":"Daltonian Club",
    "wof:placetype":"venue"
},
  "geometry": {"coordinates":[-53.244015,47.681667],"type":"Point"}
}