{
  "type": "Feature",
  "properties": {
    "addr:full":"1610 St Gabriel Cres Windsor ON N9E 1P1",
    "addr:housenumber":"1610",
    "addr:postcode":"n9e 1p1",
    "addr:street":"St Gabriel Cres",
    "iso:country":"CA",
    "sg:address":"1610 St Gabriel Cres",
    "sg:city":"Windsor",
    "sg:classifiers":[
        {
            "category":"Shopping",
            "type":"Retail Goods"
        }
    ],
    "sg:phone":"+1 519 969 4996",
    "sg:postcode":"N9E 1P1",
    "sg:province":"ON",
    "sg:tags":[
        "cosmetic",
        "perfume"
    ],
    "wof:name":"Mary Kay Cosmetics",
    "wof:placetype":"venue"
},
  "geometry": {"coordinates":[-83.02237700000001,42.256729],"type":"Point"}
}