{
  "type": "Feature",
  "properties": {
    "addr:full":"10 Rue Giguere Levis QC G6V 1N6",
    "addr:housenumber":"10",
    "addr:postcode":"g6v 1n6",
    "addr:street":"Rue Giguere",
    "iso:country":"CA",
    "sg:address":"10 Rue Giguere",
    "sg:city":"Levis",
    "sg:classifiers":[
        {
            "category":"Organizations",
            "subcategory":"Non-profit Organization",
            "type":"Services"
        }
    ],
    "sg:phone":"+1 418 838 4922",
    "sg:postcode":"G6V 1N6",
    "sg:province":"QC",
    "sg:tags":[
        "handicapped"
    ],
    "wof:name":"Personnes Handicappees-Action",
    "wof:placetype":"venue"
},
  "geometry": {"coordinates":[-71.171059,46.82452],"type":"Point"}
}