{
  "type": "Feature",
  "properties": {
    "addr:full":"567 Lawrence Ave W North York ON M6A 1A5",
    "addr:housenumber":"567",
    "addr:postcode":"m6a 1a5",
    "addr:street":"Lawrence Ave W",
    "iso:country":"CA",
    "sg:address":"567 Lawrence Ave W",
    "sg:city":"North York",
    "sg:classifiers":[
        {
            "category":"Organizations",
            "subcategory":"Religious Organization",
            "type":"Services"
        }
    ],
    "sg:phone":"+1 416 789 1891",
    "sg:postcode":"M6A 1A5",
    "sg:province":"ON",
    "sg:tags":[
        "church"
    ],
    "wof:name":"Yeshive Yesodel Hatorah",
    "wof:placetype":"venue"
},
  "geometry": {"coordinates":[-79.435371,43.717831],"type":"Point"}
}