{
  "type": "Feature",
  "properties": {
    "iso:country":"CA",
    "sg:address":"102 DE LA Fabrique",
    "sg:city":"Saint-Marc-Sur-Richelieu",
    "sg:classifiers":[
        {
            "category":"Government",
            "subcategory":"Office",
            "type":"Public Place"
        }
    ],
    "sg:phone":"+1 450 584 2258",
    "sg:postcode":"J0L 2E0",
    "sg:province":"QC",
    "sg:tags":[
        "village"
    ],
    "wof:name":"St Marc Sur Richelieu",
    "wof:placetype":"venue"
},
  "geometry": {"coordinates":[-73.19519042970001,45.6781959534],"type":"Point"}
}