{
  "type": "Feature",
  "properties": {
    "addr:full":"862 Ch Du Vieux-Fort Duhamel-Ouest QC J9V 1N7",
    "addr:housenumber":"862",
    "addr:postcode":"j9v 1n7",
    "addr:street":"Ch Du Vieux-Fort",
    "iso:country":"CA",
    "sg:address":"862 Ch Du Vieux-Fort",
    "sg:city":"Duhamel-Ouest",
    "sg:classifiers":[
        {
            "category":"Restaurant",
            "type":"Food & Drink"
        }
    ],
    "sg:phone":"+1 819 622 0922",
    "sg:postcode":"J9V 1N7",
    "sg:province":"QC",
    "wof:name":"Camping Fort-Temiscamingue",
    "wof:placetype":"venue"
},
  "geometry": {"coordinates":[-79.45483400000001,47.290379],"type":"Point"}
}