{
  "type": "Feature",
  "properties": {
    "addr:full":"Richmond BC V6X 2R2",
    "addr:postcode":"v6x 2r2",
    "iso:country":"CA",
    "sg:city":"Richmond",
    "sg:classifiers":[
        {
            "category":"Shopping",
            "type":"Retail Goods"
        }
    ],
    "sg:phone":"+1 604 273 6262",
    "sg:postcode":"V6X 2R2",
    "sg:province":"BC",
    "sg:tags":[
        "picture",
        "frame"
    ],
    "wof:name":"Framecraft Industry Corp",
    "wof:placetype":"venue"
},
  "geometry": {"coordinates":[-123.099174,49.192913],"type":"Point"}
}