{
  "type": "Feature",
  "properties": {
    "addr:full":"50 Beurling Cres Saskatoon SK S7H 4V7",
    "addr:housenumber":"50",
    "addr:postcode":"s7h 4v7",
    "addr:street":"Beurling Cres",
    "iso:country":"CA",
    "sg:address":"50 Beurling Cres",
    "sg:city":"Saskatoon",
    "sg:classifiers":[
        {
            "category":"Wholesale",
            "subcategory":"Books, Periodicals, & Newspapers",
            "type":"Manufacturing & Wholesale Goods"
        }
    ],
    "sg:phone":"+1 306 955 0225",
    "sg:postcode":"S7H 4V7",
    "sg:province":"SK",
    "sg:tags":[
        "dealer"
    ],
    "wof:name":"National Book Svc",
    "wof:placetype":"venue"
},
  "geometry": {"coordinates":[-106.595505,52.110573],"type":"Point"}
}