{
  "type": "Feature",
  "properties": {
    "addr:full":"8 Queen St E Sault Ste Marie ON P6A 1Y3",
    "addr:housenumber":"8",
    "addr:postcode":"p6a 1y3",
    "addr:street":"Queen St E",
    "iso:country":"CA",
    "sg:address":"8 Queen St E",
    "sg:city":"Sault Ste Marie",
    "sg:classifiers":[
        {
            "category":"Professional",
            "subcategory":"Engineering",
            "type":"Services"
        }
    ],
    "sg:phone":"+1 705 942 6628",
    "sg:postcode":"P6A 1Y3",
    "sg:province":"ON",
    "sg:tags":[
        "engineer"
    ],
    "wof:name":"Stem Engineering Group Inc",
    "wof:placetype":"venue"
},
  "geometry": {"coordinates":[-84.34081999999999,46.517681],"type":"Point"}
}