{
  "type": "Feature",
  "properties": {
    "iso:country":"CA",
    "sg:address":"147 Wallace Heights Dr",
    "sg:city":"North Bay",
    "sg:classifiers":[
        {
            "category":"Building & Trades",
            "subcategory":"Landscaping Services",
            "type":"Services"
        }
    ],
    "sg:phone":"+1 705 476 5518",
    "sg:postcode":"P1C 1E7",
    "sg:province":"ON",
    "sg:tags":[
        "landscape",
        "contractor"
    ],
    "wof:name":"Dlf Landscaping",
    "wof:placetype":"venue"
},
  "geometry": {"coordinates":[-79.439163208,46.3382873535],"type":"Point"}
}