{
  "type": "Feature",
  "properties": {
    "addr:full":"40 King St W Millbrook ON L0A 1G0",
    "addr:housenumber":"40",
    "addr:postcode":"l0a 1g0",
    "addr:street":"King St W",
    "iso:country":"CA",
    "sg:address":"40 King St W",
    "sg:city":"Millbrook",
    "sg:classifiers":[
        {
            "category":"Shopping",
            "subcategory":"Gifts & Souvenirs",
            "type":"Retail Goods"
        }
    ],
    "sg:phone":"+1 705 932 2850",
    "sg:postcode":"L0A 1G0",
    "sg:province":"ON",
    "sg:tags":[
        "shop"
    ],
    "wof:name":"Bear Essentials",
    "wof:placetype":"venue"
},
  "geometry": {"coordinates":[-78.4478302002,44.1508369446],"type":"Point"}
}