{
  "type": "Feature",
  "properties": {
    "addr:full":"1238 1st St Brandon MB R7A 2Y6",
    "addr:housenumber":"1238",
    "addr:postcode":"r7a 2y6",
    "addr:street":"1St St",
    "iso:country":"CA",
    "sg:address":"1238 1st St",
    "sg:city":"Brandon",
    "sg:classifiers":[
        {
            "category":"Building & Trades",
            "subcategory":"Cleaning & Sanitation",
            "type":"Services"
        }
    ],
    "sg:phone":"+1 204 725 2301",
    "sg:postcode":"R7A 2Y6",
    "sg:province":"MB",
    "sg:tags":[
        "fireplace",
        "chimney"
    ],
    "wof:name":"K C Chimney Sweeps",
    "wof:placetype":"venue"
},
  "geometry": {"coordinates":[-99.939301,49.831043],"type":"Point"}
}