{
  "type": "Feature",
  "properties": {
    "addr:full":"90 Rue Bernard Saint-Charles-Borromee QC J6E 2C3",
    "addr:housenumber":"90",
    "addr:postcode":"j6e 2c3",
    "addr:street":"Rue Bernard Saint-Charles-Borromee",
    "iso:country":"CA",
    "sg:address":"90 Rue Bernard",
    "sg:city":"Saint-Charles-Borromee",
    "sg:classifiers":[
        {
            "category":"Health Services",
            "subcategory":"Doctor",
            "type":"Services"
        }
    ],
    "sg:phone":"+1 450 752 6667",
    "sg:postcode":"J6E 2C3",
    "sg:province":"QC",
    "sg:tags":[
        "clinic"
    ],
    "wof:name":"Clinique DE Gastroenterologie",
    "wof:placetype":"venue"
},
  "geometry": {"coordinates":[-73.44859313960001,46.0391921997],"type":"Point"}
}