{
  "type": "Feature",
  "properties": {
    "addr:full":"5620 Grant St Burnaby BC V5B 2K3",
    "addr:housenumber":"5620",
    "addr:postcode":"bc v5b 2k3",
    "addr:street":"Grant St",
    "iso:country":"CA",
    "sg:address":"5620 Grant St",
    "sg:city":"Burnaby",
    "sg:classifiers":[
        {
            "category":"Real Estate",
            "subcategory":"Real Estate Agent",
            "type":"Services"
        }
    ],
    "sg:phone":"+1 604 298 3866",
    "sg:postcode":"V5B 2K3",
    "sg:province":"BC",
    "sg:tags":[
        "management"
    ],
    "wof:name":"Pkp Management Inc",
    "wof:placetype":"venue"
},
  "geometry": {"coordinates":[-122.98197937,49.2702140808],"type":"Point"}
}