{
  "type": "Feature",
  "properties": {
    "addr:full":"50 10 St SW Salmon Arm BC V1E 1E4",
    "addr:housenumber":"10",
    "addr:postcode":"v1e 1e4",
    "addr:street":"St Sw",
    "iso:country":"CA",
    "sg:address":"50 10 St SW",
    "sg:city":"Salmon Arm",
    "sg:classifiers":[
        {
            "category":"Freight",
            "type":"Transportation"
        }
    ],
    "sg:phone":"+1 250 832 3131",
    "sg:postcode":"V1E 1E4",
    "sg:province":"BC",
    "sg:tags":[
        "delivery"
    ],
    "wof:name":"V & C Courier",
    "wof:placetype":"venue"
},
  "geometry": {"coordinates":[-119.296806,50.697521],"type":"Point"}
}