{
  "type": "Feature",
  "properties": {
    "addr:full":"145 Beaconwood Pl Fort Mcmurray AB T9H 2S9",
    "addr:housenumber":"145",
    "addr:postcode":"t9h 2s9",
    "addr:street":"Beaconwood Pl",
    "iso:country":"CA",
    "sg:address":"145 Beaconwood Pl",
    "sg:city":"Fort Mcmurray",
    "sg:classifiers":[
        {
            "category":"Organizations",
            "subcategory":"Religious Organization",
            "type":"Services"
        }
    ],
    "sg:phone":"+1 780 791 2191",
    "sg:postcode":"T9H 2S9",
    "sg:province":"AB",
    "sg:tags":[
        "church"
    ],
    "wof:name":"Church of Jesus Christ-Lds",
    "wof:placetype":"venue"
},
  "geometry": {"coordinates":[-111.35922241199999,56.7010574341],"type":"Point"}
}