{
  "type": "Feature",
  "properties": {
    "iso:country":"CA",
    "sg:city":"Vancouver",
    "sg:classifiers":[
        {
            "category":"Banks & Credit Unions",
            "subcategory":"Investment Brokerage",
            "type":"Services"
        }
    ],
    "sg:phone":"+1 604 681 9695",
    "sg:postcode":"V6B 1N2",
    "sg:province":"BC",
    "sg:tags":[
        "consultant",
        "planning",
        "financial"
    ],
    "wof:name":"Tfp Corp",
    "wof:placetype":"venue"
},
  "geometry": {"coordinates":[-123.11333500000001,49.285206],"type":"Point"}
}