{
  "type": "Feature",
  "properties": {
    "addr:full":"272 Callaghan Cres Oakville ON L6H 5H8",
    "addr:housenumber":"272",
    "addr:postcode":"l6h 5h8",
    "addr:street":"Callaghan Cres",
    "iso:country":"CA",
    "sg:address":"272 Callaghan Cres",
    "sg:city":"Oakville",
    "sg:classifiers":[
        {
            "category":"Professional",
            "subcategory":"Management & Consulting",
            "type":"Services"
        }
    ],
    "sg:phone":"+1 905 257 6033",
    "sg:postcode":"L6H 5H8",
    "sg:province":"ON",
    "sg:tags":[
        "communications",
        "consultant"
    ],
    "wof:name":"Crane Communications",
    "wof:placetype":"venue"
},
  "geometry": {"coordinates":[-79.730919,43.466858],"type":"Point"}
}