{
  "type": "Feature",
  "properties": {
    "addr:full":"3335 Rue Felix-Leclerc Vaudreuil-Dorion QC J7V 8W5",
    "addr:housenumber":"3335",
    "addr:postcode":"j7v 8w5",
    "addr:street":"Rue Felix-Leclerc",
    "iso:country":"CA",
    "sg:address":"3335 Rue Felix-Leclerc",
    "sg:city":"Vaudreuil-Dorion",
    "sg:classifiers":[
        {
            "category":"Professional",
            "subcategory":"Computer Services",
            "type":"Services"
        }
    ],
    "sg:phone":"+1 450 424 0126",
    "sg:postcode":"J7V 8W5",
    "sg:province":"QC",
    "sg:tags":[
        "information",
        "training",
        "system",
        "consultant"
    ],
    "wof:name":"College Info-Technique",
    "wof:placetype":"venue"
},
  "geometry": {"coordinates":[-74.198296,45.443237],"type":"Point"}
}