{
  "type": "Feature",
  "properties": {
    "addr:full":"219 18 St NW Calgary AB T2N 2G4",
    "addr:housenumber":"18",
    "addr:postcode":"t2n 2g4",
    "addr:street":"219;St Nw",
    "iso:country":"CA",
    "sg:address":"219 18 St NW",
    "sg:city":"Calgary",
    "sg:classifiers":[
        {
            "category":"Professional",
            "subcategory":"Computer Services",
            "type":"Services"
        }
    ],
    "sg:phone":"+1 403 282 5330",
    "sg:postcode":"T2N 2G4",
    "sg:province":"AB",
    "sg:tags":[
        "consultant"
    ],
    "wof:name":"Micro Assistance Inc",
    "wof:placetype":"venue"
},
  "geometry": {"coordinates":[-114.102714539,51.0537071228],"type":"Point"}
}