{
  "type": "Feature",
  "properties": {
    "addr:full":"Edmonton AB T6E 1Z5",
    "addr:postcode":"t6e 1z5",
    "iso:country":"CA",
    "sg:city":"Edmonton",
    "sg:classifiers":[
        {
            "category":"Retail",
            "subcategory":"Portrait Studio",
            "type":"Services"
        }
    ],
    "sg:phone":"+1 780 944 0800",
    "sg:postcode":"T6E 1Z5",
    "sg:province":"AB",
    "sg:tags":[
        "photographer"
    ],
    "wof:name":"Smart Photography",
    "wof:placetype":"venue"
},
  "geometry": {"coordinates":[-113.491958618,53.5178794861],"type":"Point"}
}