{
  "type": "Feature",
  "properties": {
    "addr:full":"1541 Chaplin St W Swift Current SK S9H 0H1",
    "addr:housenumber":"1541",
    "addr:postcode":"s9h 0h1",
    "addr:street":"Chaplin St W",
    "iso:country":"CA",
    "sg:address":"1541 Chaplin St W",
    "sg:city":"Swift Current",
    "sg:classifiers":[
        {
            "category":"Manufacturing",
            "subcategory":"Signs",
            "type":"Manufacturing & Wholesale Goods"
        }
    ],
    "sg:phone":"+1 306 773 8800",
    "sg:postcode":"S9H 0H1",
    "sg:province":"SK",
    "sg:tags":[
        "advertising"
    ],
    "wof:name":"Signs 'N Such",
    "wof:placetype":"venue"
},
  "geometry": {"coordinates":[-107.821273804,50.2849121094],"type":"Point"}
}