{
  "type": "Feature",
  "properties": {
    "addr:full":"7005 Av Du Major-Beaudet Sorel-Tracy QC J3R 4X9",
    "addr:housenumber":"7005",
    "addr:postcode":"j3r 4x9",
    "addr:street":"Av Du Major-Beaudet",
    "iso:country":"CA",
    "sg:address":"7005 Av Du Major-Beaudet",
    "sg:city":"Sorel-Tracy",
    "sg:classifiers":[
        {
            "category":"Wholesale",
            "subcategory":"Hardware",
            "type":"Manufacturing & Wholesale Goods"
        }
    ],
    "sg:phone":"+1 450 742 3734",
    "sg:postcode":"J3R 4X9",
    "sg:province":"QC",
    "sg:tags":[
        "fastener"
    ],
    "wof:name":"L V Equipements Quincaillerie",
    "wof:placetype":"venue"
},
  "geometry": {"coordinates":[-73.1552658081,46.0188217163],"type":"Point"}
}