{
  "type": "Feature",
  "properties": {
    "addr:full":"24 Trowbridge St W #7 Meaford ON N4L 1Y1",
    "addr:housenumber":"24",
    "addr:postcode":"n4l 1y1",
    "addr:street":"Trowbridge St W # 7",
    "iso:country":"CA",
    "sg:address":"24 Trowbridge St W #7",
    "sg:city":"Meaford",
    "sg:classifiers":[
        {
            "category":"Retail",
            "subcategory":"Laundry & Dry Cleaning",
            "type":"Services"
        }
    ],
    "sg:phone":"+1 519 538 4044",
    "sg:postcode":"N4L 1Y1",
    "sg:province":"ON",
    "sg:tags":[
        "cleaners"
    ],
    "wof:name":"Trowbridge Cleaning Ctr",
    "wof:placetype":"venue"
},
  "geometry": {"coordinates":[-80.59265136720001,44.6068344116],"type":"Point"}
}