{
  "type": "Feature",
  "properties": {
    "addr:full":"82 Industrial Rd Inuvik NT X0E 0T0",
    "addr:housenumber":"82",
    "addr:postcode":"x0e 0t0",
    "addr:street":"Industrial Rd",
    "iso:country":"CA",
    "sg:address":"82 Industrial Rd",
    "sg:city":"Inuvik",
    "sg:classifiers":[
        {
            "category":"Building & Trades",
            "subcategory":"Construction",
            "type":"Services"
        }
    ],
    "sg:phone":"+1 867 777 3182",
    "sg:postcode":"X0E 0T0",
    "sg:province":"NT",
    "sg:tags":[
        "general",
        "contractor"
    ],
    "wof:name":"D & R Ranson Construction Ltd",
    "wof:placetype":"venue"
},
  "geometry": {"coordinates":[-133.73493999999999,68.361053],"type":"Point"}
}