{
  "type": "Feature",
  "properties": {
    "iso:country":"CA",
    "sg:address":"7476 Prospect St",
    "sg:city":"Pemberton",
    "sg:classifiers":[
        {
            "category":"Recreation",
            "type":"Entertainment"
        }
    ],
    "sg:phone":"+1 604 894 6269",
    "sg:postcode":"V0N 2L0",
    "sg:province":"BC",
    "sg:tags":[
        "amusement"
    ],
    "wof:name":"Adventures on Horseback",
    "wof:placetype":"venue"
},
  "geometry": {"coordinates":[-122.807044983,50.3244094849],"type":"Point"}
}