{
  "type": "Feature",
  "properties": {
    "addr:full":"11770 Boul DE LA Riviere-Des-P Montreal QC H1C 1P9",
    "addr:housenumber":"11770",
    "addr:postcode":"h1c 1p9",
    "addr:street":"Boul De La Riviere-Des-P",
    "iso:country":"CA",
    "sg:address":"11770 Boul DE LA Riviere-Des-P",
    "sg:city":"Montreal",
    "sg:classifiers":[
        {
            "category":"Home & Garden",
            "subcategory":"Building Materials",
            "type":"Retail Goods"
        }
    ],
    "sg:phone":"+1 514 648 9020",
    "sg:postcode":"H1C 1P9",
    "sg:province":"QC",
    "sg:tags":[
        "plate",
        "window",
        "mirror"
    ],
    "wof:name":"Vitrerie Michelois Inc",
    "wof:placetype":"venue"
},
  "geometry": {"coordinates":[-73.560005,45.649101],"type":"Point"}
}