{
  "type": "Feature",
  "properties": {
    "addr:full":"PO Box 239 North Hatley QC J0B 2C0",
    "addr:housenumber":"po",
    "addr:postcode":"j0b 2c0",
    "addr:street":"Box 239",
    "iso:country":"CA",
    "sg:address":"PO Box 239",
    "sg:city":"North Hatley",
    "sg:classifiers":[
        {
            "category":"Organizations",
            "subcategory":"Religious Organization",
            "type":"Services"
        }
    ],
    "sg:phone":"+1 418 842 2686",
    "sg:postcode":"J0B 2C0",
    "sg:province":"QC",
    "sg:tags":[
        "church"
    ],
    "wof:name":"Anglican Parish",
    "wof:placetype":"venue"
},
  "geometry": {"coordinates":[-71.98941000000001,45.182217],"type":"Point"}
}