{
  "type": "Feature",
  "properties": {
    "addr:full":"575 Rue Montplaisir Saint-Charles-DE-Drummond QC J2B 7T5",
    "addr:housenumber":"575",
    "addr:postcode":"j2b 7t5",
    "addr:street":"Rue Montplaisir",
    "iso:country":"CA",
    "sg:address":"575 Rue Montplaisir",
    "sg:city":"Saint-Charles-DE-Drummond",
    "sg:classifiers":[
        {
            "category":"Government",
            "subcategory":"Office",
            "type":"Public Place"
        }
    ],
    "sg:phone":"+1 819 477 1360",
    "sg:postcode":"J2B 7T5",
    "sg:province":"QC",
    "wof:name":"Camping Des Voltigeurs",
    "wof:placetype":"venue"
},
  "geometry": {"coordinates":[-72.4881286621,45.9059486389],"type":"Point"}
}