{
  "type": "Feature",
  "properties": {
    "addr:full":"5690 176A St Surrey BC V3S 4H1",
    "addr:housenumber":"5690",
    "addr:postcode":"v3s 4h1",
    "addr:street":"176A St",
    "iso:country":"CA",
    "sg:address":"5690 176A St",
    "sg:city":"Surrey",
    "sg:classifiers":[
        {
            "category":"Professional",
            "subcategory":"Lawyer & Legal Services",
            "type":"Services"
        }
    ],
    "sg:phone":"+1 604 574 7431",
    "sg:postcode":"V3S 4H1",
    "sg:province":"BC",
    "sg:tags":[
        "attorney"
    ],
    "wof:name":"Mac Kay, Robert W",
    "wof:placetype":"venue"
},
  "geometry": {"coordinates":[-122.830215454,49.105178833],"type":"Point"}
}