{
  "type": "Feature",
  "properties": {
    "iso:country":"CA",
    "sg:address":"74 Provincial Rd 205 E",
    "sg:city":"Rosenort",
    "sg:classifiers":[
        {
            "category":"Manufacturing",
            "subcategory":"Tools & Machinery",
            "type":"Manufacturing & Wholesale Goods"
        }
    ],
    "sg:phone":"+1 204 746 2396",
    "sg:postcode":"R0G 1W0",
    "sg:province":"MB",
    "sg:tags":[
        "farm",
        "equipment"
    ],
    "wof:name":"Westfield Industries Ltd",
    "wof:placetype":"venue"
},
  "geometry": {"coordinates":[-97.4346160889,49.464805603],"type":"Point"}
}