{
  "type": "Feature",
  "properties": {
    "iso:country":"CA",
    "sg:address":"1224 Ch DE Chambly",
    "sg:city":"Longueuil",
    "sg:classifiers":[
        {
            "category":"Personal",
            "subcategory":"Beauty Salon",
            "type":"Services"
        }
    ],
    "sg:phone":"+1 450 679 6366",
    "sg:postcode":"J4J 3W6",
    "sg:province":"QC",
    "wof:name":"Salon DE Coiffure Costa",
    "wof:placetype":"venue"
},
  "geometry": {"coordinates":[-73.4894866943,45.5325698853],"type":"Point"}
}