{
  "type": "Feature",
  "properties": {
    "addr:full":"15 Banbury Crt Aurora ON L4G 3M8",
    "addr:housenumber":"15",
    "addr:postcode":"l4g 3m8",
    "addr:street":"Banbury Crt",
    "iso:country":"CA",
    "sg:address":"15 Banbury Crt",
    "sg:city":"Aurora",
    "sg:classifiers":[
        {
            "category":"Freight",
            "type":"Transportation"
        }
    ],
    "sg:phone":"+1 905 751 0535",
    "sg:postcode":"L4G 3M8",
    "sg:province":"ON",
    "sg:tags":[
        "trucking"
    ],
    "wof:name":"Camston Transportation Inc",
    "wof:placetype":"venue"
},
  "geometry": {"coordinates":[-79.468216,43.988636],"type":"Point"}
}