{
  "type": "Feature",
  "properties": {
    "iso:country":"CA",
    "sg:city":"Vancouver",
    "sg:classifiers":[
        {
            "category":"Banks & Credit Unions",
            "subcategory":"Bank",
            "type":"Services"
        }
    ],
    "sg:phone":"+1 604 734 0322",
    "sg:postcode":"V6J 1X2",
    "sg:province":"BC",
    "sg:tags":[
        "loan",
        "real estate"
    ],
    "wof:name":"Ronald Niven & Assoc Mortgage",
    "wof:placetype":"venue"
},
  "geometry": {"coordinates":[-123.14295196499999,49.2638206482],"type":"Point"}
}