{
  "type": "Feature",
  "properties": {
    "addr:full":"137 Mahood Johnston Dr Kincardine ON N2Z 3A2",
    "addr:housenumber":"137",
    "addr:postcode":"n2z 3a2",
    "addr:street":"Mahood Johnston Dr",
    "iso:country":"CA",
    "sg:address":"137 Mahood Johnston Dr",
    "sg:city":"Kincardine",
    "sg:classifiers":[
        {
            "category":"Organizations",
            "subcategory":"Religious Organization",
            "type":"Services"
        }
    ],
    "sg:phone":"+1 519 396 3338",
    "sg:postcode":"N2Z 3A2",
    "sg:province":"ON",
    "sg:tags":[
        "church"
    ],
    "wof:name":"Lighthouse Fellowship Baptist",
    "wof:placetype":"venue"
},
  "geometry": {"coordinates":[-81.649597168,44.162311554],"type":"Point"}
}