{
  "type": "Feature",
  "properties": {
    "addr:full":"902 Pineview Kaleden BC V0H 1K0",
    "addr:housenumber":"902",
    "addr:postcode":"v0h 1k0",
    "addr:street":"Pineview Kaleden",
    "iso:country":"CA",
    "sg:address":"902 Pineview",
    "sg:city":"Kaleden",
    "sg:classifiers":[
        {
            "category":"Restaurant",
            "type":"Food & Drink"
        }
    ],
    "sg:phone":"+1 250 497 8808",
    "sg:postcode":"V0H 1K0",
    "sg:province":"BC",
    "sg:tags":[
        "caterer"
    ],
    "wof:name":"Okanagan Herb CO & Catering",
    "wof:placetype":"venue"
},
  "geometry": {"coordinates":[-119.601181,49.40332],"type":"Point"}
}