{
  "type": "Feature",
  "properties": {
    "addr:full":"354 Rue DE Castelnau E Montreal QC H2R 1P9",
    "addr:housenumber":"354",
    "addr:postcode":"h2r 1p9",
    "addr:street":"Rue De Castelnau E",
    "iso:country":"CA",
    "sg:address":"354 Rue DE Castelnau E",
    "sg:city":"Montreal",
    "sg:classifiers":[
        {
            "category":"Personal",
            "subcategory":"Beauty Salon",
            "type":"Services"
        }
    ],
    "sg:phone":"+1 514 495 4319",
    "sg:postcode":"H2R 1P9",
    "sg:province":"QC",
    "wof:name":"Salon DE Beaute Dep",
    "wof:placetype":"venue"
},
  "geometry": {"coordinates":[-73.61747699999999,45.538555],"type":"Point"}
}