{
  "type": "Feature",
  "properties": {
    "addr:full":"10 Elm St # 37 Sudbury ON P3C 5N3",
    "addr:housenumber":"10",
    "addr:postcode":"p3c 5n3",
    "addr:street":"Elm St # 37",
    "iso:country":"CA",
    "sg:address":"10 Elm St # 37",
    "sg:city":"Sudbury",
    "sg:classifiers":[
        {
            "category":"Shopping",
            "subcategory":"Clothing, Apparel, & Fashions",
            "type":"Retail Goods"
        }
    ],
    "sg:phone":"+1 705 673 2278",
    "sg:postcode":"P3C 5N3",
    "sg:province":"ON",
    "wof:name":"Bottega Mia",
    "wof:placetype":"venue"
},
  "geometry": {"coordinates":[-80.991158,46.493248],"type":"Point"}
}