{
  "type": "Feature",
  "properties": {
    "iso:country":"CA",
    "sg:address":"333 Rue Saint-Antoine E # 600",
    "sg:city":"Montreal",
    "sg:classifiers":[
        {
            "category":"Government",
            "subcategory":"Office",
            "type":"Public Place"
        }
    ],
    "sg:phone":"+1 514 872 9387",
    "sg:postcode":"H2X 1R9",
    "sg:province":"QC",
    "sg:tags":[
        "village"
    ],
    "wof:name":"Montreal Conseils DE Quartier",
    "wof:placetype":"venue"
},
  "geometry": {"coordinates":[-73.554993,45.510338],"type":"Point"}
}