{
  "type": "Feature",
  "properties": {
    "addr:full":"1922 Skead Rd Garson ON P3L 1V5",
    "addr:housenumber":"1922",
    "addr:postcode":"p3l 1v5",
    "addr:street":"Skead Rd",
    "iso:country":"CA",
    "sg:address":"1922 Skead Rd",
    "sg:city":"Garson",
    "sg:classifiers":[
        {
            "category":"Health Services",
            "subcategory":"Nursing And Care Facility",
            "type":"Services"
        }
    ],
    "sg:phone":"+1 705 693 5666",
    "sg:postcode":"P3L 1V5",
    "sg:province":"ON",
    "sg:tags":[
        "home",
        "rest"
    ],
    "wof:name":"Goodfellow S Residential Home",
    "wof:placetype":"venue"
},
  "geometry": {"coordinates":[-80.82371500000001,46.602119],"type":"Point"}
}