{
  "type": "Feature",
  "properties": {
    "addr:full":"112 107th St W Saskatoon SK S7N 1N8",
    "addr:housenumber":"112",
    "addr:postcode":"s7n 1n8",
    "addr:street":"107Th St W",
    "iso:country":"CA",
    "sg:address":"112 107th St W",
    "sg:city":"Saskatoon",
    "sg:classifiers":[
        {
            "category":"Professional",
            "subcategory":"Art Services",
            "type":"Services"
        }
    ],
    "sg:phone":"+1 306 374 4484",
    "sg:postcode":"S7N 1N8",
    "sg:province":"SK",
    "sg:tags":[
        "graphic",
        "designer",
        "artist"
    ],
    "wof:name":"Eyecatcher Graphics & Design",
    "wof:placetype":"venue"
},
  "geometry": {"coordinates":[-106.600769043,52.135799408],"type":"Point"}
}