{
  "type": "Feature",
  "properties": {
    "addr:full":"2250 Rue Cartier Longueuil QC J4K 4E9",
    "addr:housenumber":"2250",
    "addr:postcode":"j4k 4e9",
    "addr:street":"Rue Cartier",
    "iso:country":"CA",
    "sg:address":"2250 Rue Cartier",
    "sg:city":"Longueuil",
    "sg:classifiers":[
        {
            "category":"Health Services",
            "subcategory":"Hospital",
            "type":"Services"
        }
    ],
    "sg:phone":"+1 450 646 5381",
    "sg:postcode":"J4K 4E9",
    "sg:province":"QC",
    "sg:tags":[
        "mental"
    ],
    "wof:name":"Maison Jacques-Ferron",
    "wof:placetype":"venue"
},
  "geometry": {"coordinates":[-73.48204,45.514561],"type":"Point"}
}