{
  "type": "Feature",
  "properties": {
    "addr:full":"3333 Boul Gouin O Montreal QC H3M 1B5",
    "addr:housenumber":"3333",
    "addr:postcode":"h3m 1b5",
    "addr:street":"Boul Gouin O",
    "iso:country":"CA",
    "sg:address":"3333 Boul Gouin O",
    "sg:city":"Montreal",
    "sg:classifiers":[
        {
            "category":"Personal",
            "subcategory":"Beauty Salon",
            "type":"Services"
        }
    ],
    "sg:phone":"+1 514 327 1263",
    "sg:postcode":"H3M 1B5",
    "sg:province":"QC",
    "wof:name":"Salon DE Coiffure Rosaire",
    "wof:placetype":"venue"
},
  "geometry": {"coordinates":[-73.70826721189999,45.5407333374],"type":"Point"}
}