{
  "type": "Feature",
  "properties": {
    "iso:country":"CA",
    "sg:city":"Courtenay",
    "sg:classifiers":[
        {
            "category":"Food & Beverages",
            "subcategory":"Meat & Fish",
            "type":"Retail Goods"
        }
    ],
    "sg:phone":"+1 250 338 5900",
    "sg:postcode":"V9N 9V7",
    "sg:province":"BC",
    "sg:tags":[
        "butchering"
    ],
    "wof:name":"Comox Valley Meats",
    "wof:placetype":"venue"
},
  "geometry": {"coordinates":[-124.982788086,49.7020111084],"type":"Point"}
}