{
  "type": "Feature",
  "properties": {
    "addr:full":"410 Rue Du Sud Cowansville QC J2K 2X7",
    "addr:housenumber":"410",
    "addr:postcode":"j2k 2x7",
    "addr:street":"Rue Du Sud",
    "iso:country":"CA",
    "sg:address":"410 Rue Du Sud",
    "sg:city":"Cowansville",
    "sg:classifiers":[
        {
            "category":"Restaurant",
            "type":"Food & Drink"
        }
    ],
    "sg:phone":"+1 450 263 8488",
    "sg:postcode":"J2K 2X7",
    "sg:province":"QC",
    "sg:tags":[
        "parlor",
        "ice",
        "cream"
    ],
    "wof:name":"Bar Laitier Nord-Sud",
    "wof:placetype":"venue"
},
  "geometry": {"coordinates":[-72.74685700000001,45.204716],"type":"Point"}
}