{
  "type": "Feature",
  "properties": {
    "addr:full":"4355 Av Old Orchard Montreal QC H4A 3B5",
    "addr:housenumber":"4355",
    "addr:postcode":"h4a 3b5",
    "addr:street":"Av Old Orchard",
    "iso:country":"CA",
    "sg:address":"4355 Av Old Orchard",
    "sg:city":"Montreal",
    "sg:classifiers":[
        {
            "category":"Health Services",
            "subcategory":"Medical Lab",
            "type":"Services"
        }
    ],
    "sg:phone":"+1 514 482 4728",
    "sg:postcode":"H4A 3B5",
    "sg:province":"QC",
    "sg:tags":[
        "laboratory"
    ],
    "wof:name":"Lab One Canada Inc",
    "wof:placetype":"venue"
},
  "geometry": {"coordinates":[-73.623046875,45.4769134521],"type":"Point"}
}