{
  "type": "Feature",
  "properties": {
    "addr:full":"3026 Maplewood Crt Coquitlam BC V3E 3P3",
    "addr:housenumber":"3026",
    "addr:postcode":"v3e 3p3",
    "addr:street":"Maplewood Crt",
    "iso:country":"CA",
    "sg:address":"3026 Maplewood Crt",
    "sg:city":"Coquitlam",
    "sg:classifiers":[
        {
            "category":"Building & Trades",
            "subcategory":"Construction",
            "type":"Services"
        }
    ],
    "sg:phone":"+1 604 945 0921",
    "sg:postcode":"V3E 3P3",
    "sg:province":"BC",
    "sg:tags":[
        "painter"
    ],
    "wof:name":"Express Painting & Wallcover",
    "wof:placetype":"venue"
},
  "geometry": {"coordinates":[-122.793655,49.305412],"type":"Point"}
}