{
  "type": "Feature",
  "properties": {
    "addr:full":"Edmonton AB T5R 5W9",
    "addr:postcode":"t5r 5w9",
    "iso:country":"CA",
    "sg:city":"Edmonton",
    "sg:classifiers":[
        {
            "category":"Health Services",
            "subcategory":"Doctor",
            "type":"Services"
        }
    ],
    "sg:phone":"+1 780 428 9516",
    "sg:postcode":"T5R 5W9",
    "sg:province":"AB",
    "sg:tags":[
        "physician",
        "surgeon"
    ],
    "wof:name":"Lieberman, Murray MD",
    "wof:placetype":"venue"
},
  "geometry": {"coordinates":[-113.490371704,53.5462188721],"type":"Point"}
}