{
  "type": "Feature",
  "properties": {
    "addr:full":"13087 116 Ave Surrey BC V3R 2S8",
    "addr:housenumber":"13087",
    "addr:postcode":"v3r 2s8",
    "addr:street":"116 Ave",
    "iso:country":"CA",
    "sg:address":"13087 116 Ave",
    "sg:city":"Surrey",
    "sg:classifiers":[
        {
            "category":"Building & Trades",
            "subcategory":"Construction",
            "type":"Services"
        }
    ],
    "sg:phone":"+1 604 580 5884",
    "sg:postcode":"V3R 2S8",
    "sg:province":"BC",
    "sg:tags":[
        "resurfacing",
        "laying",
        "refinishing",
        "floor"
    ],
    "wof:name":"MD Sales & Marketing Ltd",
    "wof:placetype":"venue"
},
  "geometry": {"coordinates":[-122.85936700000001,49.213676],"type":"Point"}
}