{
  "type": "Feature",
  "properties": {
    "addr:full":"6600 Rte Louis S.st-Laurent Compton QC J0B 1L0",
    "addr:housenumber":"6600",
    "addr:postcode":"j0b 1l0",
    "addr:street":"Rte Louis S.St-Laurent",
    "iso:country":"CA",
    "sg:address":"6600 Rte Louis S.st-Laurent",
    "sg:city":"Compton",
    "sg:classifiers":[
        {
            "category":"Organizations",
            "subcategory":"Professional Association",
            "type":"Services"
        }
    ],
    "sg:phone":"+1 819 835 9321",
    "sg:postcode":"J0B 1L0",
    "sg:province":"QC",
    "wof:name":"Chevaliers DE Colomb Conseil",
    "wof:placetype":"venue"
},
  "geometry": {"coordinates":[-71.829208374,45.2474517822],"type":"Point"}
}