{
  "type": "Feature",
  "properties": {
    "addr:full":"Winnipeg MB R2H 0R8",
    "addr:postcode":"r2h 0r8",
    "iso:country":"CA",
    "sg:city":"Winnipeg",
    "sg:classifiers":[
        {
            "category":"Health Services",
            "subcategory":"Health Practitioner",
            "type":"Services"
        }
    ],
    "sg:phone":"+1 204 231 2284",
    "sg:postcode":"R2H 0R8",
    "sg:province":"MB",
    "sg:tags":[
        "psychologist"
    ],
    "wof:name":"Kaokis, George",
    "wof:placetype":"venue"
},
  "geometry": {"coordinates":[-97.11920166020001,49.8823471069],"type":"Point"}
}