{
  "type": "Feature",
  "properties": {
    "addr:full":"228 High St Fort Erie ON L2A 3R3",
    "addr:housenumber":"228",
    "addr:postcode":"l2a 3r3",
    "addr:street":"High St",
    "iso:country":"CA",
    "sg:address":"228 High St",
    "sg:city":"Fort Erie",
    "sg:classifiers":[
        {
            "category":"Professional",
            "subcategory":"Accounting & Tax Preparation",
            "type":"Services"
        }
    ],
    "sg:phone":"+1 905 871 3123",
    "sg:postcode":"L2A 3R3",
    "sg:province":"ON",
    "sg:tags":[
        "accountant"
    ],
    "wof:name":"Mantle, Dave",
    "wof:placetype":"venue"
},
  "geometry": {"coordinates":[-78.9160308838,42.9113578796],"type":"Point"}
}