{
  "type": "Feature",
  "properties": {
    "iso:country":"CA",
    "sg:address":"228 High St",
    "sg:city":"Fort Erie",
    "sg:classifiers":[
        {
            "category":"Professional",
            "subcategory":"Accounting & Tax Preparation",
            "type":"Services"
        }
    ],
    "sg:phone":"+1 905 871 3123",
    "sg:postcode":"L2A 3R3",
    "sg:province":"ON",
    "sg:tags":[
        "accountant"
    ],
    "wof:name":"Mantle, Dave",
    "wof:placetype":"venue"
},
  "geometry": {"coordinates":[-78.9160308838,42.9113578796],"type":"Point"}
}