{
  "type": "Feature",
  "properties": {
    "addr:full":"555 George St N Peterborough ON K9H 3S1",
    "addr:housenumber":"555",
    "addr:postcode":"k9h 3s1",
    "addr:street":"George St N",
    "iso:country":"CA",
    "sg:address":"555 George St N",
    "sg:city":"Peterborough",
    "sg:classifiers":[
        {
            "category":"Health Services",
            "subcategory":"Health Practitioner",
            "type":"Services"
        }
    ],
    "sg:phone":"+1 705 741 2284",
    "sg:postcode":"K9H 3S1",
    "sg:province":"ON",
    "sg:tags":[
        "physiotherapist"
    ],
    "wof:name":"Peterborough Physiotherapy",
    "wof:placetype":"venue"
},
  "geometry": {"coordinates":[-78.320572,44.310619],"type":"Point"}
}