{
  "type": "Feature",
  "properties": {
    "iso:country":"CA",
    "sg:address":"2042 Rue Jacques-Cartier",
    "sg:city":"Riviere-Pentecote",
    "sg:classifiers":[
        {
            "category":"Food & Beverages",
            "subcategory":"Groceries & Convenience Stores",
            "type":"Retail Goods"
        }
    ],
    "sg:phone":"+1 418 799 2561",
    "sg:postcode":"G0H 1R0",
    "sg:province":"QC",
    "wof:name":"Servi Pointe Ltee",
    "wof:placetype":"venue"
},
  "geometry": {"coordinates":[-67.16882324220001,49.6768798828],"type":"Point"}
}