{
  "type": "Feature",
  "properties": {
    "addr:full":"698 Tecumseh St Dresden ON N0P 1M0",
    "addr:housenumber":"698",
    "addr:postcode":"n0p 1m0",
    "addr:street":"Tecumseh St",
    "iso:country":"CA",
    "sg:address":"698 Tecumseh St",
    "sg:city":"Dresden",
    "sg:classifiers":[
        {
            "category":"Organizations",
            "subcategory":"Religious Organization",
            "type":"Services"
        }
    ],
    "sg:phone":"+1 519 683 6178",
    "sg:postcode":"N0P 1M0",
    "sg:province":"ON",
    "sg:tags":[
        "church"
    ],
    "wof:name":"St Michael's Church Hall",
    "wof:placetype":"venue"
},
  "geometry": {"coordinates":[-82.177887,42.588005],"type":"Point"}
}