{
  "type": "Feature",
  "properties": {
    "addr:full":"9096 Hwy 11 RR 3 Orillia ON L3V 6H3",
    "addr:housenumber":"9096",
    "addr:postcode":"l3v 6h3",
    "addr:street":"Hwy 11 Rr 3",
    "iso:country":"CA",
    "sg:address":"9096 Hwy 11 RR 3",
    "sg:city":"Orillia",
    "sg:classifiers":[
        {
            "category":"Manufacturing",
            "subcategory":"Metals",
            "type":"Manufacturing & Wholesale Goods"
        }
    ],
    "sg:phone":"+1 705 689 8099",
    "sg:postcode":"L3V 6H3",
    "sg:province":"ON",
    "sg:tags":[
        "fabricator",
        "aluminum"
    ],
    "wof:name":"Rollo's Welding & Creations",
    "wof:placetype":"venue"
},
  "geometry": {"coordinates":[-79.41822814939999,44.606590271],"type":"Point"}
}