{
  "type": "Feature",
  "properties": {
    "addr:full":"557 Southdale Rd E London ON N6E 1A2",
    "addr:housenumber":"557",
    "addr:postcode":"n6e 1a2",
    "addr:street":"Southdale Rd E",
    "iso:country":"CA",
    "sg:address":"557 Southdale Rd E",
    "sg:city":"London",
    "sg:classifiers":[
        {
            "category":"Personal",
            "type":"Services"
        }
    ],
    "sg:phone":"+1 519 668 1911",
    "sg:postcode":"N6E 1A2",
    "sg:province":"ON",
    "sg:tags":[
        "electrolysis"
    ],
    "wof:name":"Southdale Electrolysis",
    "wof:placetype":"venue"
},
  "geometry": {"coordinates":[-81.2341918945,42.9426002502],"type":"Point"}
}