{
  "type": "Feature",
  "properties": {
    "addr:full":"109 Centre Ave E Black Diamond AB T0L 0H0",
    "addr:housenumber":"109",
    "addr:postcode":"t0l 0h0",
    "addr:street":"Centre Ave E",
    "iso:country":"CA",
    "sg:address":"109 Centre Ave E",
    "sg:city":"Black Diamond",
    "sg:classifiers":[
        {
            "category":"Shopping",
            "type":"Retail Goods"
        }
    ],
    "sg:phone":"+1 403 933 5524",
    "sg:postcode":"T0L 0H0",
    "sg:province":"AB",
    "sg:tags":[
        "art",
        "gallery",
        "dealer"
    ],
    "wof:name":"Maryanne's Eden",
    "wof:placetype":"venue"
},
  "geometry": {"coordinates":[-114.23296356199999,50.6882667542],"type":"Point"}
}