{
  "type": "Feature",
  "properties": {
    "iso:country":"CA",
    "sg:address":"926 160 St",
    "sg:city":"Surrey",
    "sg:classifiers":[
        {
            "category":"Travel",
            "subcategory":"Hotels & Motels",
            "type":"Entertainment"
        }
    ],
    "sg:phone":"+1 604 531 4973",
    "sg:postcode":"V4A 4W5",
    "sg:province":"BC",
    "wof:name":"Cedar Lane Motel",
    "wof:placetype":"venue"
},
  "geometry": {"coordinates":[-122.778992,49.018978],"type":"Point"}
}