{
  "type": "Feature",
  "properties": {
    "addr:full":"Bear Island ON P0H 1C0",
    "addr:postcode":"p0h 1c0",
    "addr:street":"Bear",
    "iso:country":"CA",
    "sg:city":"Bear Island",
    "sg:classifiers":[
        {
            "category":"Organizations",
            "subcategory":"Professional Association",
            "type":"Services"
        }
    ],
    "sg:phone":"+1 705 237 8627",
    "sg:postcode":"P0H 1C0",
    "sg:province":"ON",
    "sg:tags":[
        "native"
    ],
    "wof:name":"N'Daki Menan Negotiation Ofc",
    "wof:placetype":"venue"
},
  "geometry": {"coordinates":[-80.0689697266,46.980670929],"type":"Point"}
}