{
  "type": "Feature",
  "properties": {
    "addr:full":"264906 Maple Dell Rd Norwich ON N0J 1P0",
    "addr:housenumber":"264906",
    "addr:postcode":"n0j 1p0",
    "addr:street":"Maple Dell Rd",
    "iso:country":"CA",
    "sg:address":"264906 Maple Dell Rd",
    "sg:city":"Norwich",
    "sg:classifiers":[
        {
            "category":"Building & Trades",
            "subcategory":"Construction",
            "type":"Services"
        }
    ],
    "sg:phone":"+1 519 842 8146",
    "sg:postcode":"N0J 1P0",
    "sg:province":"ON",
    "sg:tags":[
        "concrete",
        "contractor"
    ],
    "wof:name":"Form 'N' Pour Concrete",
    "wof:placetype":"venue"
},
  "geometry": {"coordinates":[-80.69253500000001,42.943138],"type":"Point"}
}