{
  "type": "Feature",
  "properties": {
    "iso:country":"CA",
    "sg:address":"166 Rue Sainte-Genevieve",
    "sg:city":"Saint-Isidore",
    "sg:classifiers":[
        {
            "category":"Retail",
            "subcategory":"Funeral Services",
            "type":"Services"
        }
    ],
    "sg:phone":"+1 418 882 5658",
    "sg:postcode":"G0S 2S0",
    "sg:province":"QC",
    "sg:tags":[
        "director"
    ],
    "wof:name":"Valois Gonzague & Fils Inc",
    "wof:placetype":"venue"
},
  "geometry": {"coordinates":[-71.0896987915,46.5843696594],"type":"Point"}
}