{
  "type": "Feature",
  "properties": {
    "addr:full":"22 Paris St Alliston ON L9R 1T6",
    "addr:housenumber":"22",
    "addr:postcode":"l9r 1t6",
    "addr:street":"Paris St",
    "iso:country":"CA",
    "sg:address":"22 Paris St",
    "sg:city":"Alliston",
    "sg:classifiers":[
        {
            "category":"Shopping",
            "type":"Retail Goods"
        }
    ],
    "sg:phone":"+1 705 435 9572",
    "sg:postcode":"L9R 1T6",
    "sg:province":"ON",
    "sg:tags":[
        "art",
        "gallery",
        "dealer"
    ],
    "wof:name":"Millpond Gallery",
    "wof:placetype":"venue"
},
  "geometry": {"coordinates":[-79.872108,44.152908],"type":"Point"}
}