{
  "type": "Feature",
  "properties": {
    "iso:country":"CA",
    "sg:address":"1573 Ch Saint-Louis",
    "sg:city":"Sillery",
    "sg:classifiers":[
        {
            "category":"Health Services",
            "subcategory":"Nursing And Care Facility",
            "type":"Services"
        }
    ],
    "sg:phone":"+1 418 687 9444",
    "sg:postcode":"G1S 1G4",
    "sg:province":"QC",
    "sg:tags":[
        "social",
        "home",
        "welfare",
        "rest",
        "organization"
    ],
    "wof:name":"Villa Du Bois DE Coulonge Inc",
    "wof:placetype":"venue"
},
  "geometry": {"coordinates":[-71.247154,46.787643],"type":"Point"}
}