{
  "type": "Feature",
  "properties": {
    "addr:full":"1408 Forest Valley Dr Orleans ON K1C 5M7",
    "addr:housenumber":"1408",
    "addr:postcode":"k1c 5m7",
    "addr:street":"Forest Valley Dr",
    "iso:country":"CA",
    "sg:address":"1408 Forest Valley Dr",
    "sg:city":"Orleans",
    "sg:classifiers":[
        {
            "category":"Building & Trades",
            "subcategory":"Landscaping Services",
            "type":"Services"
        }
    ],
    "sg:phone":"+1 613 830 4983",
    "sg:postcode":"K1C 5M7",
    "sg:province":"ON",
    "sg:tags":[
        "landscape",
        "contractor"
    ],
    "wof:name":"Prebbel Inc",
    "wof:placetype":"venue"
},
  "geometry": {"coordinates":[-75.5445480347,45.45860672],"type":"Point"}
}