{
  "type": "Feature",
  "properties": {
    "addr:full":"321 21st St E Saskatoon SK S7K 0C1",
    "addr:housenumber":"321",
    "addr:postcode":"s7k 0c1",
    "addr:street":"21St St E",
    "iso:country":"CA",
    "sg:address":"321 21st St E",
    "sg:city":"Saskatoon",
    "sg:classifiers":[
        {
            "category":"Banks & Credit Unions",
            "subcategory":"Investment Brokerage",
            "type":"Services"
        }
    ],
    "sg:phone":"+1 306 249 6610",
    "sg:postcode":"S7K 0C1",
    "sg:province":"SK",
    "wof:name":"Hsbc Securities Inc",
    "wof:placetype":"venue"
},
  "geometry": {"coordinates":[-106.66244500000001,52.126682],"type":"Point"}
}