{
  "type": "Feature",
  "properties": {
    "addr:full":"1148 Rue Saint-Jean Quebec QC G1R 1S4",
    "addr:housenumber":"1148",
    "addr:postcode":"g1r 1s4",
    "addr:street":"Rue Saint-Jean",
    "iso:country":"CA",
    "sg:address":"1148 Rue Saint-Jean",
    "sg:city":"Quebec",
    "sg:classifiers":[
        {
            "category":"Shopping",
            "subcategory":"Shoes",
            "type":"Retail Goods"
        }
    ],
    "sg:phone":"+1 418 692 4724",
    "sg:postcode":"G1R 1S4",
    "sg:province":"QC",
    "wof:name":"Chaussures Nero Bianco",
    "wof:placetype":"venue"
},
  "geometry": {"coordinates":[-71.21019699999999,46.814224],"type":"Point"}
}