{
  "type": "Feature",
  "properties": {
    "iso:country":"CA",
    "sg:address":"34 Haas Rd",
    "sg:city":"Etobicoke",
    "sg:classifiers":[
        {
            "category":"Manufacturing",
            "subcategory":"Textiles",
            "type":"Manufacturing & Wholesale Goods"
        }
    ],
    "sg:phone":"+1 416 746 7821",
    "sg:postcode":"M9W 3A2",
    "sg:province":"ON",
    "sg:tags":[
        "knitted",
        "fabric"
    ],
    "wof:name":"Finetex Knitting Mill Inc",
    "wof:placetype":"venue"
},
  "geometry": {"coordinates":[-79.5744552612,43.7172698975],"type":"Point"}
}