{
  "type": "Feature",
  "properties": {
    "iso:country":"CA",
    "sg:address":"2 Princess Anne Cres",
    "sg:city":"Etobicoke",
    "sg:classifiers":[
        {
            "category":"Building & Trades",
            "subcategory":"Electrical",
            "type":"Services"
        }
    ],
    "sg:phone":"+1 416 234 9006",
    "sg:postcode":"M9A 2N8",
    "sg:province":"ON",
    "sg:tags":[
        "electric",
        "contractor"
    ],
    "wof:name":"Croatian Electric",
    "wof:placetype":"venue"
},
  "geometry": {"coordinates":[-79.5368881226,43.671836853],"type":"Point"}
}