{
  "type": "Feature",
  "properties": {
    "addr:full":"400 Base Line Rd W London ON N6J 1W1",
    "addr:housenumber":"400",
    "addr:postcode":"n6j 1w1",
    "addr:street":"Base Line Rd W",
    "iso:country":"CA",
    "sg:address":"400 Base Line Rd W",
    "sg:city":"London",
    "sg:classifiers":[
        {
            "category":"Education",
            "subcategory":"School",
            "type":"Public Place"
        }
    ],
    "sg:phone":"+1 519 471 6680",
    "sg:postcode":"N6J 1W1",
    "sg:province":"ON",
    "wof:name":"Ecole Frere Andre",
    "wof:placetype":"venue"
},
  "geometry": {"coordinates":[-81.2793045044,42.9630851746],"type":"Point"}
}