{
  "type": "Feature",
  "properties": {
    "addr:full":"Toronto ON M4G 3V9",
    "addr:postcode":"m4g 3v9",
    "iso:country":"CA",
    "sg:city":"Toronto",
    "sg:classifiers":[
        {
            "category":"Health Services",
            "subcategory":"Hospital",
            "type":"Services"
        }
    ],
    "sg:phone":"+1 416 597 3422",
    "sg:postcode":"M4G 3V9",
    "sg:province":"ON",
    "wof:name":"Toronto Rehabilitation Inst",
    "wof:placetype":"venue"
},
  "geometry": {"coordinates":[-79.369415,43.718452],"type":"Point"}
}