{
  "type": "Feature",
  "properties": {
    "addr:full":"45762 Kipp Ave Chilliwack BC V2P 1Y4",
    "addr:housenumber":"45762",
    "addr:postcode":"v2p 1y4",
    "addr:street":"Kipp Ave",
    "iso:country":"CA",
    "sg:address":"45762 Kipp Ave",
    "sg:city":"Chilliwack",
    "sg:classifiers":[
        {
            "category":"Retail",
            "subcategory":"Laundry & Dry Cleaning",
            "type":"Services"
        }
    ],
    "sg:phone":"+1 604 792 2277",
    "sg:postcode":"V2P 1Y4",
    "sg:province":"BC",
    "sg:tags":[
        "cleaners"
    ],
    "wof:name":"One Stop Cleaning Ctr",
    "wof:placetype":"venue"
},
  "geometry": {"coordinates":[-121.957413,49.170547],"type":"Point"}
}