{
  "type": "Feature",
  "properties": {
    "iso:country":"CA",
    "sg:address":"6409 Beresford St",
    "sg:city":"Burnaby",
    "sg:classifiers":[
        {
            "category":"Building & Trades",
            "subcategory":"Electrical",
            "type":"Services"
        }
    ],
    "sg:phone":"+1 604 430 1202",
    "sg:postcode":"V5E 1B5",
    "sg:province":"BC",
    "sg:tags":[
        "electric",
        "contractor"
    ],
    "wof:name":"Western Integrated Electrical",
    "wof:placetype":"venue"
},
  "geometry": {"coordinates":[-122.97088623,49.2175865173],"type":"Point"}
}