{
  "type": "Feature",
  "properties": {
    "addr:full":"191 Parliament St Toronto ON M5A 2Z4",
    "addr:housenumber":"191",
    "addr:postcode":"m5a 2z4",
    "addr:street":"Parliament St",
    "iso:country":"CA",
    "sg:address":"191 Parliament St",
    "sg:city":"Toronto",
    "sg:classifiers":[
        {
            "category":"Retail",
            "subcategory":"Auto Rental",
            "type":"Services"
        }
    ],
    "sg:phone":"+1 416 868 0350",
    "sg:postcode":"M5A 2Z4",
    "sg:province":"ON",
    "sg:tags":[
        "renting",
        "automobile"
    ],
    "wof:name":"Thrifty Car Rental",
    "wof:placetype":"venue"
},
  "geometry": {"coordinates":[-79.364479,43.656181],"type":"Point"}
}