{
  "type": "Feature",
  "properties": {
    "iso:country":"CA",
    "sg:address":"109 Mccaul St # 38",
    "sg:city":"Toronto",
    "sg:classifiers":[
        {
            "category":"Restaurant",
            "type":"Food & Drink"
        }
    ],
    "sg:phone":"+1 416 596 0339",
    "sg:postcode":"M5T 3K5",
    "sg:province":"ON",
    "wof:name":"Sate Sate",
    "wof:placetype":"venue"
},
  "geometry": {"coordinates":[-79.3910293579,43.6538124084],"type":"Point"}
}