{
  "type": "Feature",
  "properties": {
    "addr:full":"2161 Proton Ave Gull Lake SK S0N 1A0",
    "addr:housenumber":"2161",
    "addr:postcode":"s0n 1a0",
    "addr:street":"Proton Ave",
    "iso:country":"CA",
    "sg:address":"2161 Proton Ave",
    "sg:city":"Gull Lake",
    "sg:classifiers":[
        {
            "category":"Retail",
            "subcategory":"Auto Repair",
            "type":"Services"
        }
    ],
    "sg:phone":"+1 306 672 3206",
    "sg:postcode":"S0N 1A0",
    "sg:province":"SK",
    "sg:tags":[
        "body",
        "automobile",
        "painting"
    ],
    "wof:name":"Horn & Gedny Auto Body",
    "wof:placetype":"venue"
},
  "geometry": {"coordinates":[-108.483924866,50.0979690552],"type":"Point"}
}