{
  "type": "Feature",
  "properties": {
    "addr:full":"287 Simmons Rd Odessa ON K0H 2H0",
    "addr:housenumber":"287",
    "addr:postcode":"k0h 2h0",
    "addr:street":"Simmons Rd",
    "iso:country":"CA",
    "sg:address":"287 Simmons Rd",
    "sg:city":"Odessa",
    "sg:classifiers":[
        {
            "category":"Food & Beverages",
            "subcategory":"Dairy",
            "type":"Retail Goods"
        }
    ],
    "sg:phone":"+1 613 386 7314",
    "sg:postcode":"K0H 2H0",
    "sg:province":"ON",
    "sg:tags":[
        "cheese"
    ],
    "wof:name":"Wilton Cheese Factory",
    "wof:placetype":"venue"
},
  "geometry": {"coordinates":[-76.718918,44.276974],"type":"Point"}
}