{
  "type": "Feature",
  "properties": {
    "addr:full":"11660 Bridgeport Rd Richmond BC V6X 1T2",
    "addr:housenumber":"11660",
    "addr:postcode":"v6x 1t2",
    "addr:street":"Bridgeport Rd",
    "iso:country":"CA",
    "sg:address":"11660 Bridgeport Rd",
    "sg:city":"Richmond",
    "sg:classifiers":[
        {
            "category":"Shopping",
            "subcategory":"Bicycles & Sporting Goods",
            "type":"Retail Goods"
        }
    ],
    "sg:phone":"+1 604 278 5100",
    "sg:postcode":"V6X 1T2",
    "sg:province":"BC",
    "wof:name":"Bridgeport Sports Club Ltd",
    "wof:placetype":"venue"
},
  "geometry": {"coordinates":[-123.09487900000001,49.191784],"type":"Point"}
}