{
  "type": "Feature",
  "properties": {
    "addr:full":"8360 8th Concession Moorefield ON N0G 2K0",
    "addr:housenumber":"8360",
    "addr:postcode":"n0g 2k0",
    "addr:street":"8Th Concession Moorefield",
    "iso:country":"CA",
    "sg:address":"8360 8th Concession",
    "sg:city":"Moorefield",
    "sg:classifiers":[
        {
            "category":"Autos & Motor Vehicles",
            "subcategory":"Auto Supplies",
            "type":"Retail Goods"
        }
    ],
    "sg:phone":"+1 519 638 3413",
    "sg:postcode":"N0G 2K0",
    "sg:province":"ON",
    "sg:tags":[
        "tire"
    ],
    "wof:name":"Moorefield Tires",
    "wof:placetype":"venue"
},
  "geometry": {"coordinates":[-80.752098,43.760754],"type":"Point"}
}