{
  "type": "Feature",
  "properties": {
    "addr:full":"329 Cumberland Ave Winnipeg MB R3B 1T2",
    "addr:housenumber":"329",
    "addr:postcode":"r3b 1t2",
    "addr:street":"Cumberland Ave",
    "iso:country":"CA",
    "sg:address":"329 Cumberland Ave",
    "sg:city":"Winnipeg",
    "sg:classifiers":[
        {
            "category":"Building & Trades",
            "subcategory":"Landscaping Services",
            "type":"Services"
        }
    ],
    "sg:phone":"+1 204 956 4375",
    "sg:postcode":"R3B 1T2",
    "sg:province":"MB",
    "sg:tags":[
        "landscape",
        "contractor"
    ],
    "wof:name":"Swiss Alpine Landscaping",
    "wof:placetype":"venue"
},
  "geometry": {"coordinates":[-97.145203,49.896118],"type":"Point"}
}