{
  "type": "Feature",
  "properties": {
    "addr:full":"197 Rue Principale Bedford QC J0J 1A0",
    "addr:housenumber":"197",
    "addr:postcode":"j0j 1a0",
    "addr:street":"Rue Principale",
    "iso:country":"CA",
    "sg:address":"197 Rue Principale",
    "sg:city":"Bedford",
    "sg:classifiers":[
        {
            "category":"Insurance",
            "subcategory":"Insurance Agent",
            "type":"Services"
        }
    ],
    "sg:phone":"+1 450 248 4367",
    "sg:postcode":"J0J 1A0",
    "sg:province":"QC",
    "wof:name":"Assurances Lanoue & Ouellet",
    "wof:placetype":"venue"
},
  "geometry": {"coordinates":[-72.996323,45.122177],"type":"Point"}
}