{
  "type": "Feature",
  "properties": {
    "iso:country":"CA",
    "sg:address":"7080 Pacific Cir",
    "sg:city":"Mississauga",
    "sg:classifiers":[
        {
            "category":"Shopping",
            "subcategory":"Clothing, Apparel, & Fashions",
            "type":"Retail Goods"
        }
    ],
    "sg:phone":"+1 905 564 1850",
    "sg:postcode":"L5T 2A7",
    "sg:province":"ON",
    "wof:name":"Active Sewing & Cresting",
    "wof:placetype":"venue"
},
  "geometry": {"coordinates":[-79.684334,43.660397],"type":"Point"}
}