{
  "type": "Feature",
  "properties": {
    "addr:full":"Labelle QC J0T 1H0",
    "addr:postcode":"j0t 1h0",
    "iso:country":"CA",
    "sg:city":"Labelle",
    "sg:classifiers":[
        {
            "category":"Recreation",
            "type":"Entertainment"
        }
    ],
    "sg:phone":"+1 819 686 1351",
    "sg:postcode":"J0T 1H0",
    "sg:province":"QC",
    "sg:tags":[
        "government",
        "hall",
        "auditorium"
    ],
    "wof:name":"Centre Communautiare DE Labell",
    "wof:placetype":"venue"
},
  "geometry": {"coordinates":[-74.73509216310001,46.2785148621],"type":"Point"}
}