{
  "type": "Feature",
  "properties": {
    "addr:full":"2010 Rue Annie Ascot QC J1H 6E3",
    "addr:housenumber":"2010",
    "addr:postcode":"j1h 6e3",
    "addr:street":"Rue Annie",
    "iso:country":"CA",
    "sg:address":"2010 Rue Annie",
    "sg:city":"Ascot",
    "sg:classifiers":[
        {
            "category":"Wholesale",
            "subcategory":"Machinery & Supplies",
            "type":"Manufacturing & Wholesale Goods"
        }
    ],
    "sg:phone":"+1 819 822 2869",
    "sg:postcode":"J1H 6E3",
    "sg:province":"QC",
    "sg:tags":[
        "cleaning"
    ],
    "wof:name":"Entretiens Squidly",
    "wof:placetype":"venue"
},
  "geometry": {"coordinates":[-71.8894042969,45.3726501465],"type":"Point"}
}