{
  "type": "Feature",
  "properties": {
    "iso:country":"CA",
    "sg:address":"363 Howden Blvd",
    "sg:city":"Brampton",
    "sg:classifiers":[
        {
            "category":"Organizations",
            "subcategory":"Religious Organization",
            "type":"Services"
        }
    ],
    "sg:phone":"+1 905 450 8003",
    "sg:postcode":"L6S 4L6",
    "sg:province":"ON",
    "sg:tags":[
        "church"
    ],
    "wof:name":"North Bramalea United Church",
    "wof:placetype":"venue"
},
  "geometry": {"coordinates":[-79.74197387700001,43.7170944214],"type":"Point"}
}