{
  "type": "Feature",
  "properties": {
    "addr:full":"250 Queens Quay W #11 Toronto ON M5J 2N2",
    "addr:housenumber":"250",
    "addr:postcode":"m5j 2n2",
    "addr:street":"Queens Quay W # 11",
    "iso:country":"CA",
    "sg:address":"250 Queens Quay W #11",
    "sg:city":"Toronto",
    "sg:classifiers":[
        {
            "category":"Restaurant",
            "type":"Food & Drink"
        }
    ],
    "sg:phone":"+1 416 598 0600",
    "sg:postcode":"M5J 2N2",
    "sg:province":"ON",
    "wof:name":"Spice Thai Cafe",
    "wof:placetype":"venue"
},
  "geometry": {"coordinates":[-79.3846740723,43.6393661499],"type":"Point"}
}