{
  "type": "Feature",
  "properties": {
    "addr:full":"1802 Bayview Ave Toronto ON M4G 3C7",
    "addr:housenumber":"1802",
    "addr:postcode":"m4g 3c7",
    "addr:street":"Bayview Ave",
    "iso:country":"CA",
    "sg:address":"1802 Bayview Ave",
    "sg:city":"Toronto",
    "sg:classifiers":[
        {
            "category":"Retail",
            "subcategory":"Car Wash",
            "type":"Services"
        }
    ],
    "sg:phone":"+1 416 483 1262",
    "sg:postcode":"M4G 3C7",
    "sg:province":"ON",
    "sg:tags":[
        "polishing",
        "washing"
    ],
    "wof:name":"Bayview Car Wash",
    "wof:placetype":"venue"
},
  "geometry": {"coordinates":[-79.377335,43.712078],"type":"Point"}
}