{
  "type": "Feature",
  "properties": {
    "addr:full":"7951 Talbot Trail Blenheim ON N0P 1A0",
    "addr:housenumber":"7951",
    "addr:postcode":"n0p 1a0",
    "addr:street":"Talbot Trail",
    "iso:country":"CA",
    "sg:address":"7951 Talbot Trail",
    "sg:city":"Blenheim",
    "sg:classifiers":[
        {
            "category":"Food & Beverages",
            "subcategory":"Fruits & Vegetables",
            "type":"Retail Goods"
        }
    ],
    "sg:phone":"+1 519 676 2008",
    "sg:postcode":"N0P 1A0",
    "sg:province":"ON",
    "sg:tags":[
        "produce"
    ],
    "wof:name":"Pardo's Berrie Farm",
    "wof:placetype":"venue"
},
  "geometry": {"coordinates":[-82.00760699999999,42.323719],"type":"Point"}
}