{
  "type": "Feature",
  "properties": {
    "iso:country":"CA",
    "sg:address":"28358 Myrtle Ave",
    "sg:city":"Abbotsford",
    "sg:classifiers":[
        {
            "category":"Freight",
            "type":"Transportation"
        }
    ],
    "sg:phone":"+1 604 856 0365",
    "sg:postcode":"V4X 2P4",
    "sg:province":"BC",
    "sg:tags":[
        "trucking"
    ],
    "wof:name":"Banner Transport Ltd",
    "wof:placetype":"venue"
},
  "geometry": {"coordinates":[-122.438171387,49.0989646912],"type":"Point"}
}