{
  "type": "Feature",
  "properties": {
    "iso:country":"CA",
    "sg:city":"Mississauga",
    "sg:classifiers":[
        {
            "category":"Organizations",
            "subcategory":"Professional Association",
            "type":"Services"
        }
    ],
    "sg:phone":"+1 905 890 5161",
    "sg:postcode":"L4Z 3L5",
    "sg:province":"ON",
    "wof:name":"Canadian Cosmetic Toiletry",
    "wof:placetype":"venue"
},
  "geometry": {"coordinates":[-79.6683578491,43.6329498291],"type":"Point"}
}