{
  "type": "Feature",
  "properties": {
    "iso:country":"CA",
    "sg:address":"1500 2 Ave S",
    "sg:city":"Lethbridge",
    "sg:classifiers":[
        {
            "category":"Autos & Motor Vehicles",
            "subcategory":"Auto Supplies",
            "type":"Retail Goods"
        }
    ],
    "sg:phone":"+1 403 328 2244",
    "sg:postcode":"T1J 0G1",
    "sg:province":"AB",
    "sg:tags":[
        "automobile",
        "parts"
    ],
    "wof:name":"Off Shore Auto Body Supplies",
    "wof:placetype":"venue"
},
  "geometry": {"coordinates":[-112.820747376,49.6973838806],"type":"Point"}
}