{
  "type": "Feature",
  "properties": {
    "addr:full":"Saint John NB E2L 1G3",
    "addr:postcode":"e2l 1g3",
    "iso:country":"CA",
    "sg:city":"Saint John",
    "sg:classifiers":[
        {
            "category":"Health Services",
            "subcategory":"Doctor",
            "type":"Services"
        }
    ],
    "sg:phone":"+1 506 634 7772",
    "sg:postcode":"E2L 1G3",
    "sg:province":"NB",
    "sg:tags":[
        "physician",
        "surgeon"
    ],
    "wof:name":"Mac Callum, Margaret MD",
    "wof:placetype":"venue"
},
  "geometry": {"coordinates":[-66.0610656738,45.2729377747],"type":"Point"}
}