{
  "type": "Feature",
  "properties": {
    "addr:full":"1601 St Clair Ave W Toronto ON M6E 1C9",
    "addr:housenumber":"1601",
    "addr:postcode":"m6e 1c9",
    "addr:street":"St Clair Ave W",
    "iso:country":"CA",
    "sg:address":"1601 St Clair Ave W",
    "sg:city":"Toronto",
    "sg:classifiers":[
        {
            "category":"Restaurant",
            "type":"Food & Drink"
        }
    ],
    "sg:phone":"+1 416 654 7764",
    "sg:postcode":"M6E 1C9",
    "sg:province":"ON",
    "wof:name":"Dairy Freezer",
    "wof:placetype":"venue"
},
  "geometry": {"coordinates":[-79.4548873901,43.6752052307],"type":"Point"}
}