{
  "type": "Feature",
  "properties": {
    "addr:full":"1120 Mcdonald St Regina SK S4N 4X3",
    "addr:housenumber":"1120",
    "addr:postcode":"s4n 4x3",
    "addr:street":"Mcdonald St",
    "iso:country":"CA",
    "sg:address":"1120 Mcdonald St",
    "sg:city":"Regina",
    "sg:classifiers":[
        {
            "category":"Wholesale",
            "subcategory":"Machinery & Supplies",
            "type":"Manufacturing & Wholesale Goods"
        }
    ],
    "sg:phone":"+1 306 569 2781",
    "sg:postcode":"S4N 4X3",
    "sg:province":"SK",
    "sg:tags":[
        "equipment",
        "steam",
        "cleaning"
    ],
    "wof:name":"Excalibur Industrial",
    "wof:placetype":"venue"
},
  "geometry": {"coordinates":[-104.583824158,50.4609794617],"type":"Point"}
}