{
  "type": "Feature",
  "properties": {
    "addr:full":"9912 Lougheed Hwy Burnaby BC V3J 1N3",
    "addr:housenumber":"9912",
    "addr:postcode":"v3j 1n3",
    "addr:street":"Lougheed Hwy",
    "iso:country":"CA",
    "sg:address":"9912 Lougheed Hwy",
    "sg:city":"Burnaby",
    "sg:classifiers":[
        {
            "category":"Professional",
            "subcategory":"Lawyer & Legal Services",
            "type":"Services"
        }
    ],
    "sg:phone":"+1 604 682 6121",
    "sg:postcode":"V3J 1N3",
    "sg:province":"BC",
    "sg:tags":[
        "attorney"
    ],
    "wof:name":"Fox Mc Kellar",
    "wof:placetype":"venue"
},
  "geometry": {"coordinates":[-122.893913269,49.2463378906],"type":"Point"}
}