{
  "type": "Feature",
  "properties": {
    "addr:full":"PO Box 8473 STN T Csc Ottawa ON K1G 3H9",
    "addr:housenumber":"po",
    "addr:postcode":"k1g 3h9",
    "addr:street":"Box 8473 Stn T Csc",
    "iso:country":"CA",
    "sg:address":"PO Box 8473 STN T Csc",
    "sg:city":"Ottawa",
    "sg:classifiers":[
        {
            "category":"Government",
            "subcategory":"Police Station",
            "type":"Public Place"
        }
    ],
    "sg:phone":"+1 613 748 6919",
    "sg:postcode":"K1G 3H9",
    "sg:province":"ON",
    "sg:tags":[
        "bailiff"
    ],
    "wof:name":"Card Bailiffs & Adjustments",
    "wof:placetype":"venue"
},
  "geometry": {"coordinates":[-75.691895,45.421501],"type":"Point"}
}