{
  "type": "Feature",
  "properties": {
    "addr:full":"Smiths Falls ON K7A 4Z6",
    "addr:postcode":"k7a 4z6",
    "iso:country":"CA",
    "sg:city":"Smiths Falls",
    "sg:classifiers":[
        {
            "category":"Real Estate",
            "subcategory":"Real Estate Operator",
            "type":"Services"
        }
    ],
    "sg:phone":"+1 613 283 2418",
    "sg:postcode":"K7A 4Z6",
    "sg:province":"ON",
    "sg:tags":[
        "mall",
        "shopping",
        "center"
    ],
    "wof:name":"County Fair Mall",
    "wof:placetype":"venue"
},
  "geometry": {"coordinates":[-76.0149154663,44.8798942566],"type":"Point"}
}