{
  "type": "Feature",
  "properties": {
    "addr:full":"60 James St Parry Sound ON P2A 1T5",
    "addr:housenumber":"60",
    "addr:postcode":"p2a 1t5",
    "addr:street":"James St",
    "iso:country":"CA",
    "sg:address":"60 James St",
    "sg:city":"Parry Sound",
    "sg:classifiers":[
        {
            "category":"Real Estate",
            "subcategory":"Real Estate Operator",
            "type":"Services"
        }
    ],
    "sg:phone":"+1 705 746 4595",
    "sg:postcode":"P2A 1T5",
    "sg:province":"ON",
    "sg:tags":[
        "building",
        "parks"
    ],
    "wof:name":"Logan & Logan",
    "wof:placetype":"venue"
},
  "geometry": {"coordinates":[-80.033981,45.344925],"type":"Point"}
}