{
  "type": "Feature",
  "properties": {
    "addr:full":"23 Colonization Emo ON P0W 1E0",
    "addr:housenumber":"23",
    "addr:postcode":"p0w 1e0",
    "addr:street":"Colonization Emo",
    "iso:country":"CA",
    "sg:address":"23 Colonization",
    "sg:city":"Emo",
    "sg:classifiers":[
        {
            "category":"Organizations",
            "subcategory":"Religious Organization",
            "type":"Services"
        }
    ],
    "sg:phone":"+1 807 482 2700",
    "sg:postcode":"P0W 1E0",
    "sg:province":"ON",
    "sg:tags":[
        "church"
    ],
    "wof:name":"Anglican Church St George's",
    "wof:placetype":"venue"
},
  "geometry": {"coordinates":[-93.83562499999999,48.632481],"type":"Point"}
}