{
  "type": "Feature",
  "properties": {
    "addr:full":"106 Clark St Clarksburg ON N0H 1J0",
    "addr:housenumber":"106",
    "addr:postcode":"n0h 1j0",
    "addr:street":"Clark St",
    "iso:country":"CA",
    "sg:address":"106 Clark St",
    "sg:city":"Clarksburg",
    "sg:classifiers":[
        {
            "category":"Building & Trades",
            "subcategory":"Construction",
            "type":"Services"
        }
    ],
    "sg:phone":"+1 519 599 7913",
    "sg:postcode":"N0H 1J0",
    "sg:province":"ON",
    "sg:tags":[
        "contractor"
    ],
    "wof:name":"Paragon Carpentry",
    "wof:placetype":"venue"
},
  "geometry": {"coordinates":[-80.466499,44.544785],"type":"Point"}
}