{
  "type": "Feature",
  "properties": {
    "iso:country":"CA",
    "sg:address":"2 Mcmurray St",
    "sg:city":"Parry Sound",
    "sg:classifiers":[
        {
            "category":"Autos & Motor Vehicles",
            "subcategory":"Automobile Sales",
            "type":"Retail Goods"
        }
    ],
    "sg:phone":"+1 705 746 2135",
    "sg:postcode":"P2A 1E7",
    "sg:province":"ON",
    "sg:tags":[
        "car",
        "dealer"
    ],
    "wof:name":"L & H Motors Ltd",
    "wof:placetype":"venue"
},
  "geometry": {"coordinates":[-80.03532409669999,45.3461952209],"type":"Point"}
}