{
  "type": "Feature",
  "properties": {
    "addr:full":"Fort Mcmurray AB T9H 4N6",
    "addr:postcode":"t9h 4n6",
    "iso:country":"CA",
    "sg:city":"Fort Mcmurray",
    "sg:classifiers":[
        {
            "category":"Health Services",
            "subcategory":"Doctor",
            "type":"Services"
        }
    ],
    "sg:phone":"+1 780 791 7737",
    "sg:postcode":"T9H 4N6",
    "sg:province":"AB",
    "sg:tags":[
        "dentist"
    ],
    "wof:name":"Aurora Dental Clinic",
    "wof:placetype":"venue"
},
  "geometry": {"coordinates":[-111.427368,56.732548],"type":"Point"}
}