{
  "type": "Feature",
  "properties": {
    "addr:full":"Red Deer AB T4P 1M8",
    "addr:postcode":"t4p 1m8",
    "iso:country":"CA",
    "sg:city":"Red Deer",
    "sg:classifiers":[
        {
            "category":"Building & Trades",
            "subcategory":"Construction",
            "type":"Services"
        }
    ],
    "sg:phone":"+1 403 346 5050",
    "sg:postcode":"T4P 1M8",
    "sg:province":"AB",
    "sg:tags":[
        "paving",
        "contractor"
    ],
    "wof:name":"Central City Asphalt Ltd",
    "wof:placetype":"venue"
},
  "geometry": {"coordinates":[-113.813614,52.310436],"type":"Point"}
}