{
  "type": "Feature",
  "properties": {
    "addr:full":"116 London Rd Hensall ON N0M 1X0",
    "addr:housenumber":"116",
    "addr:postcode":"n0m 1x0",
    "addr:street":"London Rd",
    "iso:country":"CA",
    "sg:address":"116 London Rd",
    "sg:city":"Hensall",
    "sg:classifiers":[
        {
            "category":"Building & Trades",
            "subcategory":"Construction",
            "type":"Services"
        }
    ],
    "sg:phone":"+1 519 263 3245",
    "sg:postcode":"N0M 1X0",
    "sg:province":"ON",
    "sg:tags":[
        "general",
        "contractor"
    ],
    "wof:name":"Jeffery Butler Construction",
    "wof:placetype":"venue"
},
  "geometry": {"coordinates":[-81.498138,43.431293],"type":"Point"}
}