{
  "type": "Feature",
  "properties": {
    "addr:full":"525 Bidwell Rd Manitowaning ON P0P 1N0",
    "addr:housenumber":"525",
    "addr:postcode":"p0p 1n0",
    "addr:street":"Bidwell Rd",
    "iso:country":"CA",
    "sg:address":"525 Bidwell Rd",
    "sg:city":"Manitowaning",
    "sg:classifiers":[
        {
            "category":"Retail",
            "subcategory":"Animal Services",
            "type":"Services"
        }
    ],
    "sg:phone":"+1 705 859 1150",
    "sg:postcode":"P0P 1N0",
    "sg:province":"ON",
    "sg:tags":[
        "pet",
        "grooming",
        "washing"
    ],
    "wof:name":"Head To Tail Mobile Grooming",
    "wof:placetype":"venue"
},
  "geometry": {"coordinates":[-81.829308,45.748837],"type":"Point"}
}