{
  "type": "Feature",
  "properties": {
    "addr:full":"Brampton ON L6T 4L2",
    "addr:postcode":"l6t 4l2",
    "iso:country":"CA",
    "sg:city":"Brampton",
    "sg:classifiers":[
        {
            "category":"Wholesale",
            "subcategory":"Electrical",
            "type":"Manufacturing & Wholesale Goods"
        }
    ],
    "sg:phone":"+1 905 458 2255",
    "sg:postcode":"L6T 4L2",
    "sg:province":"ON",
    "sg:tags":[
        "electric",
        "motor"
    ],
    "wof:name":"A & A Rewinds Ltd",
    "wof:placetype":"venue"
},
  "geometry": {"coordinates":[-79.68245697019999,43.709148407],"type":"Point"}
}