{
  "type": "Feature",
  "properties": {
    "addr:full":"4407 Rue DE Charleroi Montreal-Nord QC H1H 1T6",
    "addr:housenumber":"4407",
    "addr:postcode":"h1h 1t6",
    "addr:street":"Rue De Charleroi",
    "iso:country":"CA",
    "sg:address":"4407 Rue DE Charleroi",
    "sg:city":"Montreal-Nord",
    "sg:classifiers":[
        {
            "category":"Wholesale",
            "subcategory":"Electrical",
            "type":"Manufacturing & Wholesale Goods"
        }
    ],
    "sg:phone":"+1 514 329 3242",
    "sg:postcode":"H1H 1T6",
    "sg:province":"QC",
    "sg:tags":[
        "instrument",
        "electronic"
    ],
    "wof:name":"Primo Instruments Inc",
    "wof:placetype":"venue"
},
  "geometry": {"coordinates":[-73.63568115229999,45.5947113037],"type":"Point"}
}