{
  "type": "Feature",
  "properties": {
    "addr:full":"4669 Rue Jarry E Saint-Leonard QC H1R 1X6",
    "addr:housenumber":"4669",
    "addr:postcode":"h1r 1x6",
    "addr:street":"Rue Jarry E",
    "iso:country":"CA",
    "sg:address":"4669 Rue Jarry E",
    "sg:city":"Saint-Leonard",
    "sg:classifiers":[
        {
            "category":"Shopping",
            "subcategory":"Department Store",
            "type":"Retail Goods"
        }
    ],
    "sg:phone":"+1 514 721 3645",
    "sg:postcode":"H1R 1X6",
    "sg:province":"QC",
    "sg:tags":[
        "shop"
    ],
    "wof:name":"Tech Seng",
    "wof:placetype":"venue"
},
  "geometry": {"coordinates":[-73.5978393555,45.5772476196],"type":"Point"}
}