{
  "type": "Feature",
  "properties": {
    "addr:full":"1665 Rue Antonio-Barbeau Laval QC H7M 4C8",
    "addr:housenumber":"1665",
    "addr:postcode":"h7m 4c8",
    "addr:street":"Rue Antonio-Barbeau",
    "iso:country":"CA",
    "sg:address":"1665 Rue Antonio-Barbeau",
    "sg:city":"Laval",
    "sg:classifiers":[
        {
            "category":"Health Services",
            "subcategory":"Podiatrist",
            "type":"Services"
        }
    ],
    "sg:phone":"+1 450 669 3772",
    "sg:postcode":"H7M 4C8",
    "sg:province":"QC",
    "wof:name":"Clinique Podiatrique DE Laval",
    "wof:placetype":"venue"
},
  "geometry": {"coordinates":[-73.708885,45.606495],"type":"Point"}
}