{
  "type": "Feature",
  "properties": {
    "addr:full":"350 Rue Guizot E Montreal QC H2P 1M6",
    "addr:housenumber":"350",
    "addr:postcode":"h2p 1m6",
    "addr:street":"Rue Guizot E",
    "iso:country":"CA",
    "sg:address":"350 Rue Guizot E",
    "sg:city":"Montreal",
    "sg:classifiers":[
        {
            "category":"Personal",
            "subcategory":"Beauty Salon",
            "type":"Services"
        }
    ],
    "sg:phone":"+1 514 388 0455",
    "sg:postcode":"H2P 1M6",
    "sg:province":"QC",
    "wof:name":"Salon Jocelyn",
    "wof:placetype":"venue"
},
  "geometry": {"coordinates":[-73.63256800000001,45.5429],"type":"Point"}
}