{
  "type": "Feature",
  "properties": {
    "iso:country":"CA",
    "sg:address":"751 14th St W",
    "sg:city":"Prince Albert",
    "sg:classifiers":[
        {
            "category":"Organizations",
            "subcategory":"Religious Organization",
            "type":"Services"
        }
    ],
    "sg:phone":"+1 306 763 3645",
    "sg:postcode":"S6V 3L9",
    "sg:province":"SK",
    "sg:tags":[
        "church"
    ],
    "wof:name":"Ulkrainian Catholic Rectory",
    "wof:placetype":"venue"
},
  "geometry": {"coordinates":[-105.774436951,53.2000541687],"type":"Point"}
}