{
  "type": "Feature",
  "properties": {
    "iso:country":"CA",
    "sg:city":"Calgary",
    "sg:classifiers":[
        {
            "category":"Health Services",
            "subcategory":"Doctor",
            "type":"Services"
        }
    ],
    "sg:phone":"+1 403 281 4266",
    "sg:postcode":"T2V 4J8",
    "sg:province":"AB",
    "sg:tags":[
        "dentist"
    ],
    "wof:name":"Doody, G W DDS",
    "wof:placetype":"venue"
},
  "geometry": {"coordinates":[-114.121002197,50.9610977173],"type":"Point"}
}