{
  "type": "Feature",
  "properties": {
    "addr:full":"2327 2 Ave N Lethbridge AB T1H 0C1",
    "addr:housenumber":"2327",
    "addr:postcode":"t1h 0c1",
    "addr:street":"2 Ave N",
    "iso:country":"CA",
    "sg:address":"2327 2 Ave N",
    "sg:city":"Lethbridge",
    "sg:classifiers":[
        {
            "category":"Freight",
            "type":"Transportation"
        }
    ],
    "sg:phone":"+1 403 328 3280",
    "sg:postcode":"T1H 0C1",
    "sg:province":"AB",
    "sg:tags":[
        "delivery",
        "trucking"
    ],
    "wof:name":"Rcs Cartage Ltd",
    "wof:placetype":"venue"
},
  "geometry": {"coordinates":[-112.80798299999999,49.700344],"type":"Point"}
}