{
  "type": "Feature",
  "properties": {
    "addr:full":"35 Browning Ave Toronto ON M4K 1V8",
    "addr:housenumber":"35",
    "addr:postcode":"m4k 1v8",
    "addr:street":"Browning Ave",
    "iso:country":"CA",
    "sg:address":"35 Browning Ave",
    "sg:city":"Toronto",
    "sg:classifiers":[
        {
            "category":"Professional",
            "subcategory":"Research",
            "type":"Services"
        }
    ],
    "sg:phone":"+1 416 463 1661",
    "sg:postcode":"M4K 1V8",
    "sg:province":"ON",
    "sg:tags":[
        "consultant",
        "social"
    ],
    "wof:name":"Jim Ward Assoc",
    "wof:placetype":"venue"
},
  "geometry": {"coordinates":[-79.355705,43.681236],"type":"Point"}
}