{
  "type": "Feature",
  "properties": {
    "addr:full":"485 Ch Village St-Pierre N Joliette QC J6E 3Z1",
    "addr:housenumber":"485",
    "addr:postcode":"j6e 3z1",
    "addr:street":"Ch Village St-Pierre N",
    "iso:country":"CA",
    "sg:address":"485 Ch Village St-Pierre N",
    "sg:city":"Joliette",
    "sg:classifiers":[
        {
            "category":"Government",
            "subcategory":"Office",
            "type":"Public Place"
        }
    ],
    "sg:phone":"+1 450 756 2592",
    "sg:postcode":"J6E 3Z1",
    "sg:province":"QC",
    "sg:tags":[
        "village"
    ],
    "wof:name":"St Pierre Municipalite",
    "wof:placetype":"venue"
},
  "geometry": {"coordinates":[-73.441956,46.023571],"type":"Point"}
}