{
  "type": "Feature",
  "properties": {
    "addr:full":"3855 Rue Saint-Denis Montreal QC H2W 2M4",
    "addr:housenumber":"3855",
    "addr:postcode":"h2w 2m4",
    "addr:street":"Rue Saint-Denis",
    "iso:country":"CA",
    "sg:address":"3855 Rue Saint-Denis",
    "sg:city":"Montreal",
    "sg:classifiers":[
        {
            "category":"Home & Garden",
            "subcategory":"Furniture",
            "type":"Retail Goods"
        }
    ],
    "sg:phone":"+1 514 499 0438",
    "sg:postcode":"H2W 2M4",
    "sg:province":"QC",
    "sg:tags":[
        "futon"
    ],
    "wof:name":"Futon D'Or",
    "wof:placetype":"venue"
},
  "geometry": {"coordinates":[-73.57331085209999,45.51978302],"type":"Point"}
}