{
  "type": "Feature",
  "properties": {
    "addr:full":"26 Rayborn Cres St Albert AB T8N 5B8",
    "addr:housenumber":"26",
    "addr:postcode":"t8n 5b8",
    "addr:street":"Rayborn Cres",
    "iso:country":"CA",
    "sg:address":"26 Rayborn Cres",
    "sg:city":"St Albert",
    "sg:classifiers":[
        {
            "category":"Building & Trades",
            "subcategory":"Construction",
            "type":"Services"
        }
    ],
    "sg:phone":"+1 780 458 1309",
    "sg:postcode":"T8N 5B8",
    "sg:province":"AB",
    "sg:tags":[
        "concrete",
        "brick",
        "contractor"
    ],
    "wof:name":"Com-Con Paving Stone Ltd",
    "wof:placetype":"venue"
},
  "geometry": {"coordinates":[-113.643066,53.622139],"type":"Point"}
}