{
  "type": "Feature",
  "properties": {
    "iso:country":"CA",
    "sg:address":"520 Simcoe St S",
    "sg:city":"Oshawa",
    "sg:classifiers":[
        {
            "category":"Restaurant",
            "type":"Food & Drink"
        }
    ],
    "sg:phone":"+1 905 579 7577",
    "sg:postcode":"L1H 4J8",
    "sg:province":"ON",
    "sg:tags":[
        "sandwich"
    ],
    "wof:name":"2 For 1 Subs",
    "wof:placetype":"venue"
},
  "geometry": {"coordinates":[-78.857498,43.88401],"type":"Point"}
}