{
  "type": "Feature",
  "properties": {
    "addr:full":"3064 Glen Dr Coquitlam BC V3B 2P9",
    "addr:housenumber":"3064",
    "addr:postcode":"v3b 2p9",
    "addr:street":"Glen Dr",
    "iso:country":"CA",
    "sg:address":"3064 Glen Dr",
    "sg:city":"Coquitlam",
    "sg:classifiers":[
        {
            "category":"Education",
            "subcategory":"School",
            "type":"Public Place"
        }
    ],
    "sg:phone":"+1 604 464 6608",
    "sg:postcode":"V3B 2P9",
    "sg:province":"BC",
    "wof:name":"Glen Elementary School",
    "wof:placetype":"venue"
},
  "geometry": {"coordinates":[-122.789833069,49.2824325562],"type":"Point"}
}