{
  "type": "Feature",
  "properties": {
    "addr:full":"1730 Burrard St Vancouver BC V6J 3G7",
    "addr:housenumber":"1730",
    "addr:postcode":"v6j 3g7",
    "addr:street":"Burrard St",
    "iso:country":"CA",
    "sg:address":"1730 Burrard St",
    "sg:city":"Vancouver",
    "sg:classifiers":[
        {
            "category":"Manufacturing",
            "subcategory":"Motor Vehicles & Parts",
            "type":"Manufacturing & Wholesale Goods"
        }
    ],
    "sg:phone":"+1 604 736 3631",
    "sg:postcode":"V6J 3G7",
    "sg:province":"BC",
    "sg:tags":[
        "repairing",
        "automobile"
    ],
    "wof:name":"Mcl Motor Cars Inc",
    "wof:placetype":"venue"
},
  "geometry": {"coordinates":[-123.14531700000001,49.270344],"type":"Point"}
}