{
  "type": "Feature",
  "properties": {
    "addr:full":"3607 1 St NW Calgary AB T2K 0W7",
    "addr:housenumber":"3607 1",
    "addr:postcode":"t2k 0w7",
    "addr:street":"St Nw",
    "iso:country":"CA",
    "sg:address":"3607 1 St NW",
    "sg:city":"Calgary",
    "sg:classifiers":[
        {
            "category":"Building & Trades",
            "subcategory":"Plumbing",
            "type":"Services"
        }
    ],
    "sg:phone":"+1 403 274 8834",
    "sg:postcode":"T2K 0W7",
    "sg:province":"AB",
    "sg:tags":[
        "contractor"
    ],
    "wof:name":"Premier Plumbing & Heating Ltd",
    "wof:placetype":"venue"
},
  "geometry": {"coordinates":[-114.065552,51.084167],"type":"Point"}
}