{
  "type": "Feature",
  "properties": {
    "iso:country":"CA",
    "sg:address":"268 Ridley Blvd",
    "sg:city":"Toronto",
    "sg:classifiers":[
        {
            "category":"Retail",
            "subcategory":"Repair Shop",
            "type":"Services"
        }
    ],
    "sg:phone":"+1 416 489 5449",
    "sg:postcode":"M5M 4N3",
    "sg:province":"ON",
    "sg:tags":[
        "upholsterer",
        "furniture"
    ],
    "wof:name":"Spring Upholstering CO",
    "wof:placetype":"venue"
},
  "geometry": {"coordinates":[-79.42394256590001,43.7397003174],"type":"Point"}
}