{
  "type": "Feature",
  "properties": {
    "addr:full":"71 Main St N Exeter ON N0M 1S3",
    "addr:housenumber":"71",
    "addr:postcode":"n0m 1s3",
    "addr:street":"Main St N",
    "iso:country":"CA",
    "sg:address":"71 Main St N",
    "sg:city":"Exeter",
    "sg:classifiers":[
        {
            "category":"Professional",
            "subcategory":"Accounting & Tax Preparation",
            "type":"Services"
        }
    ],
    "sg:phone":"+1 519 235 3863",
    "sg:postcode":"N0M 1S3",
    "sg:province":"ON",
    "sg:tags":[
        "accountant"
    ],
    "wof:name":"Homuth, Stu CA",
    "wof:placetype":"venue"
},
  "geometry": {"coordinates":[-81.48303199999999,43.358433],"type":"Point"}
}