{
  "type": "Feature",
  "properties": {
    "addr:full":"Kitchener ON N2A 3Y7",
    "addr:postcode":"n2a 3y7",
    "iso:country":"CA",
    "sg:city":"Kitchener",
    "sg:classifiers":[
        {
            "category":"Retail",
            "subcategory":"Laundry & Dry Cleaning",
            "type":"Services"
        }
    ],
    "sg:phone":"+1 519 894 8288",
    "sg:postcode":"N2A 3Y7",
    "sg:province":"ON",
    "sg:tags":[
        "cleaners"
    ],
    "wof:name":"Sketchley Cleaners",
    "wof:placetype":"venue"
},
  "geometry": {"coordinates":[-80.4404830933,43.432975769],"type":"Point"}
}