{
  "type": "Feature",
  "properties": {
    "addr:full":"720 3 St NW Calgary AB T2N 1N9",
    "addr:housenumber":"720 3",
    "addr:postcode":"t2n 1n9",
    "addr:street":"St Nw",
    "iso:country":"CA",
    "sg:address":"720 3 St NW",
    "sg:city":"Calgary",
    "sg:classifiers":[
        {
            "category":"Shopping",
            "subcategory":"Bicycles & Sporting Goods",
            "type":"Retail Goods"
        }
    ],
    "sg:phone":"+1 403 270 0220",
    "sg:postcode":"T2N 1N9",
    "sg:province":"AB",
    "sg:tags":[
        "equipment",
        "curling",
        "supply"
    ],
    "wof:name":"Curlers Corner",
    "wof:placetype":"venue"
},
  "geometry": {"coordinates":[-114.069733,51.058041],"type":"Point"}
}