{
  "type": "Feature",
  "properties": {
    "iso:country":"CA",
    "sg:address":"186 Charing Cross St",
    "sg:city":"Brantford",
    "sg:classifiers":[
        {
            "category":"Autos & Motor Vehicles",
            "subcategory":"Automobile Sales",
            "type":"Retail Goods"
        }
    ],
    "sg:phone":"+1 519 752 7880",
    "sg:postcode":"N3R 2J5",
    "sg:province":"ON",
    "sg:tags":[
        "car",
        "dealer"
    ],
    "wof:name":"J Partridge Motor Cars",
    "wof:placetype":"venue"
},
  "geometry": {"coordinates":[-80.2603683472,43.1575126648],"type":"Point"}
}