{
  "type": "Feature",
  "properties": {
    "addr:full":"11440 54 St SE Calgary AB T2C 4Y6",
    "addr:housenumber":"11440",
    "addr:postcode":"t2c 4y6",
    "addr:street":"54 St Se",
    "iso:country":"CA",
    "sg:address":"11440 54 St SE",
    "sg:city":"Calgary",
    "sg:classifiers":[
        {
            "category":"Freight",
            "type":"Transportation"
        }
    ],
    "sg:phone":"+1 403 262 9464",
    "sg:postcode":"T2C 4Y6",
    "sg:province":"AB",
    "sg:tags":[
        "trucking"
    ],
    "wof:name":"Consolidated Fastfrate Inc",
    "wof:placetype":"venue"
},
  "geometry": {"coordinates":[-113.955009,50.952511],"type":"Point"}
}