{
  "type": "Feature",
  "properties": {
    "addr:full":"2008 14 St NW Calgary AB T2M 3N3",
    "addr:housenumber":"2008",
    "addr:postcode":"t2m 3n3",
    "addr:street":"14 St Nw",
    "iso:country":"CA",
    "sg:address":"2008 14 St NW",
    "sg:city":"Calgary",
    "sg:classifiers":[
        {
            "category":"Shopping",
            "subcategory":"Pharmacy",
            "type":"Retail Goods"
        }
    ],
    "sg:phone":"+1 403 289 5505",
    "sg:postcode":"T2M 3N3",
    "sg:province":"AB",
    "wof:name":"Sunbow Professional Phrmcy",
    "wof:placetype":"venue"
},
  "geometry": {"coordinates":[-114.10817,51.065346],"type":"Point"}
}