{
  "type": "Feature",
  "properties": {
    "addr:full":"250 Fifth St Balmertown ON P0V 1C0",
    "addr:housenumber":"250",
    "addr:postcode":"p0v 1c0",
    "addr:street":"Fifth St",
    "iso:country":"CA",
    "sg:address":"250 Fifth St",
    "sg:city":"Balmertown",
    "sg:classifiers":[
        {
            "category":"Food & Beverages",
            "subcategory":"Groceries & Convenience Stores",
            "type":"Retail Goods"
        }
    ],
    "sg:phone":"+1 807 735 2515",
    "sg:postcode":"P0V 1C0",
    "sg:province":"ON",
    "wof:name":"Balmer Video",
    "wof:placetype":"venue"
},
  "geometry": {"coordinates":[-93.744057,51.056973],"type":"Point"}
}