{
  "type": "Feature",
  "properties": {
    "iso:country":"CA",
    "sg:city":"Victoria",
    "sg:classifiers":[
        {
            "category":"Health Services",
            "subcategory":"Doctor",
            "type":"Services"
        }
    ],
    "sg:phone":"+1 250 383 4442",
    "sg:postcode":"V8V 3P5",
    "sg:province":"BC",
    "sg:tags":[
        "physician",
        "surgeon"
    ],
    "wof:name":"Kelly, John L MD",
    "wof:placetype":"venue"
},
  "geometry": {"coordinates":[-123.35495758099999,48.4273757935],"type":"Point"}
}