{
  "type": "Feature",
  "properties": {
    "iso:country":"CA",
    "sg:address":"553 Boul Du Seminaire N",
    "sg:city":"Saint-Jean-Sur-Richelieu",
    "sg:classifiers":[
        {
            "category":"Personal",
            "subcategory":"Beauty Salon",
            "type":"Services"
        }
    ],
    "sg:phone":"+1 450 359 6660",
    "sg:postcode":"J3B 7C9",
    "sg:province":"QC",
    "wof:name":"Concept Fk Coiffure",
    "wof:placetype":"venue"
},
  "geometry": {"coordinates":[-73.26383972169999,45.3177528381],"type":"Point"}
}