{
  "type": "Feature",
  "properties": {
    "addr:full":"197 2nd Ave W Minitonas MB R0L 1G0",
    "addr:housenumber":"197",
    "addr:postcode":"r0l 1g0",
    "addr:street":"2Nd Ave W Minitonas",
    "iso:country":"CA",
    "sg:address":"197 2nd Ave W",
    "sg:city":"Minitonas",
    "sg:classifiers":[
        {
            "category":"Recreation",
            "type":"Entertainment"
        }
    ],
    "sg:phone":"+1 204 525 4405",
    "sg:postcode":"R0L 1G0",
    "sg:province":"MB",
    "sg:tags":[
        "guide"
    ],
    "wof:name":"Duck Mountain Outfitters",
    "wof:placetype":"venue"
},
  "geometry": {"coordinates":[-101.037147522,52.0865859985],"type":"Point"}
}