{
  "type": "Feature",
  "properties": {
    "addr:full":"Calgary AB T2T 0B6",
    "addr:postcode":"t2t 0b6",
    "iso:country":"CA",
    "sg:city":"Calgary",
    "sg:classifiers":[
        {
            "category":"Professional",
            "subcategory":"Lawyer & Legal Services",
            "type":"Services"
        }
    ],
    "sg:phone":"+1 403 244 5515",
    "sg:postcode":"T2T 0B6",
    "sg:province":"AB",
    "sg:tags":[
        "attorney"
    ],
    "wof:name":"Gorman Gorman Burns & Watson",
    "wof:placetype":"venue"
},
  "geometry": {"coordinates":[-114.089111328,51.0377044678],"type":"Point"}
}