{
  "type": "Feature",
  "properties": {
    "addr:full":"667 Enfield Rd Burlington ON L7T 2X9",
    "addr:housenumber":"667",
    "addr:postcode":"l7t 2x9",
    "addr:street":"Enfield Rd",
    "iso:country":"CA",
    "sg:address":"667 Enfield Rd",
    "sg:city":"Burlington",
    "sg:classifiers":[
        {
            "category":"Retail",
            "subcategory":"Auto Repair",
            "type":"Services"
        }
    ],
    "sg:phone":"+1 905 632 4882",
    "sg:postcode":"L7T 2X9",
    "sg:province":"ON",
    "sg:tags":[
        "repairing",
        "automobile"
    ],
    "wof:name":"D Car Doctor",
    "wof:placetype":"venue"
},
  "geometry": {"coordinates":[-79.834343,43.324768],"type":"Point"}
}