{
  "type": "Feature",
  "properties": {
    "addr:full":"Angus ON L0M 1B0",
    "addr:postcode":"l0m 1b0",
    "iso:country":"CA",
    "sg:city":"Angus",
    "sg:classifiers":[
        {
            "category":"Restaurant",
            "type":"Food & Drink"
        }
    ],
    "sg:phone":"+1 705 424 1234",
    "sg:postcode":"L0M 1B0",
    "sg:province":"ON",
    "sg:tags":[
        "pizza"
    ],
    "wof:name":"Mario's Pizza",
    "wof:placetype":"venue"
},
  "geometry": {"coordinates":[-79.8852386475,44.3146286011],"type":"Point"}
}