{
  "type": "Feature",
  "properties": {
    "addr:full":"Calgary AB T2T 5R6",
    "addr:postcode":"t2t 5r6",
    "iso:country":"CA",
    "sg:city":"Calgary",
    "sg:classifiers":[
        {
            "category":"Professional",
            "subcategory":"Lawyer & Legal Services",
            "type":"Services"
        }
    ],
    "sg:phone":"+1 403 245 3666",
    "sg:postcode":"T2T 5R6",
    "sg:province":"AB",
    "sg:tags":[
        "attorney"
    ],
    "wof:name":"Quigley, Gerald F",
    "wof:placetype":"venue"
},
  "geometry": {"coordinates":[-114.082687378,51.0376663208],"type":"Point"}
}