{
  "type": "Feature",
  "properties": {
    "addr:full":"111 Avenue Rd Toronto ON M5R 3J8",
    "addr:housenumber":"111",
    "addr:postcode":"m5r 3j8",
    "addr:street":"Avenue Rd",
    "iso:country":"CA",
    "sg:address":"111 Avenue Rd",
    "sg:city":"Toronto",
    "sg:classifiers":[
        {
            "category":"Health Services",
            "subcategory":"Nursing And Care Facility",
            "type":"Services"
        }
    ],
    "sg:phone":"+1 416 928 0111",
    "sg:postcode":"M5R 3J8",
    "sg:province":"ON",
    "sg:tags":[
        "home",
        "retirement",
        "community"
    ],
    "wof:name":"Hazelton Place",
    "wof:placetype":"venue"
},
  "geometry": {"coordinates":[-79.395729,43.673103],"type":"Point"}
}