{
  "type": "Feature",
  "properties": {
    "addr:full":"2666 Lindholm Cres Mississauga ON L5M 4P4",
    "addr:housenumber":"2666",
    "addr:postcode":"l5m 4p4",
    "addr:street":"Lindholm Cres",
    "iso:country":"CA",
    "sg:address":"2666 Lindholm Cres",
    "sg:city":"Mississauga",
    "sg:classifiers":[
        {
            "category":"Building & Trades",
            "subcategory":"Electrical",
            "type":"Services"
        }
    ],
    "sg:phone":"+1 905 569 2448",
    "sg:postcode":"L5M 4P4",
    "sg:province":"ON",
    "sg:tags":[
        "electric",
        "contractor"
    ],
    "wof:name":"Peel Electrical Contractors",
    "wof:placetype":"venue"
},
  "geometry": {"coordinates":[-79.7147521973,43.5479354858],"type":"Point"}
}