{
  "type": "Feature",
  "properties": {
    "iso:country":"CA",
    "sg:address":"1448 Ryan St",
    "sg:city":"Victoria",
    "sg:classifiers":[
        {
            "category":"Building & Trades",
            "subcategory":"Construction",
            "type":"Services"
        }
    ],
    "sg:phone":"+1 250 595 5547",
    "sg:postcode":"V8R 2X1",
    "sg:province":"BC",
    "sg:tags":[
        "repairing",
        "remodeling",
        "contractor"
    ],
    "wof:name":"W L Restoration",
    "wof:placetype":"venue"
},
  "geometry": {"coordinates":[-123.341331,48.440178],"type":"Point"}
}