{
  "type": "Feature",
  "properties": {
    "iso:country":"CA",
    "sg:city":"Burnaby",
    "sg:classifiers":[
        {
            "category":"Personal",
            "subcategory":"Beauty Salon",
            "type":"Services"
        }
    ],
    "sg:phone":"+1 604 520 1020",
    "sg:postcode":"V3N 1B3",
    "sg:province":"BC",
    "wof:name":"Designs Haircare",
    "wof:placetype":"venue"
},
  "geometry": {"coordinates":[-122.945618,49.221779],"type":"Point"}
}