{
  "type": "Feature",
  "properties": {
    "addr:full":"283 Montee Saint-Charles Saint-Eustache QC J7R 4K3",
    "addr:housenumber":"283",
    "addr:postcode":"j7r 4k3",
    "addr:street":"Montee Saint-Charles",
    "iso:country":"CA",
    "sg:address":"283 Montee Saint-Charles",
    "sg:city":"Saint-Eustache",
    "sg:classifiers":[
        {
            "category":"Manufacturing",
            "subcategory":"Tools & Machinery",
            "type":"Manufacturing & Wholesale Goods"
        }
    ],
    "sg:phone":"+1 450 473 1531",
    "sg:postcode":"J7R 4K3",
    "sg:province":"QC",
    "sg:tags":[
        "development",
        "electronic",
        "research"
    ],
    "wof:name":"Electronique D'Interface Enr",
    "wof:placetype":"venue"
},
  "geometry": {"coordinates":[-73.91668701170001,45.6032600403],"type":"Point"}
}