{
  "type": "Feature",
  "properties": {
    "addr:full":"Toronto ON M5C 2B8",
    "addr:postcode":"m5c 2b8",
    "iso:country":"CA",
    "sg:city":"Toronto",
    "sg:classifiers":[
        {
            "category":"Mining & Drilling",
            "type":"Manufacturing & Wholesale Goods"
        }
    ],
    "sg:phone":"+1 416 703 3751",
    "sg:postcode":"M5C 2B8",
    "sg:province":"ON",
    "sg:tags":[
        "company",
        "contractor"
    ],
    "wof:name":"Moydow Mines Intl Inc",
    "wof:placetype":"venue"
},
  "geometry": {"coordinates":[-79.376289,43.650208],"type":"Point"}
}