{
  "type": "Feature",
  "properties": {
    "addr:full":"1314 Rue Ontario E Montreal QC H2L 1R9",
    "addr:housenumber":"1314",
    "addr:postcode":"h2l 1r9",
    "addr:street":"Rue Ontario E",
    "iso:country":"CA",
    "sg:address":"1314 Rue Ontario E",
    "sg:city":"Montreal",
    "sg:classifiers":[
        {
            "category":"Restaurant",
            "type":"Food & Drink"
        }
    ],
    "sg:phone":"+1 514 527 8581",
    "sg:postcode":"H2L 1R9",
    "sg:province":"QC",
    "wof:name":"Palais Montcalm Restaurant",
    "wof:placetype":"venue"
},
  "geometry": {"coordinates":[-73.5613708496,45.5224113464],"type":"Point"}
}