{
  "type": "Feature",
  "properties": {
    "iso:country":"CA",
    "sg:address":"2057 Rue Commerciale",
    "sg:city":"Saint-Francois-DE-Madawaska",
    "sg:classifiers":[
        {
            "category":"Food & Beverages",
            "subcategory":"Groceries & Convenience Stores",
            "type":"Retail Goods"
        }
    ],
    "sg:phone":"+1 506 992 2281",
    "sg:postcode":"E7A 1B3",
    "sg:province":"NB",
    "wof:name":"Depanneur Monique",
    "wof:placetype":"venue"
},
  "geometry": {"coordinates":[-68.7097625732,47.2437973022],"type":"Point"}
}