{
  "type": "Feature",
  "properties": {
    "addr:full":"330 Scott St Fort Frances ON P9A 1G9",
    "addr:housenumber":"330",
    "addr:postcode":"p9a 1g9",
    "addr:street":"Scott St",
    "iso:country":"CA",
    "sg:address":"330 Scott St",
    "sg:city":"Fort Frances",
    "sg:classifiers":[
        {
            "category":"Shopping",
            "subcategory":"Crafts & Fabrics",
            "type":"Retail Goods"
        }
    ],
    "sg:phone":"+1 807 274 6665",
    "sg:postcode":"P9A 1G9",
    "sg:province":"ON",
    "sg:tags":[
        "shop"
    ],
    "wof:name":"Crazy Ladies Fabrics",
    "wof:placetype":"venue"
},
  "geometry": {"coordinates":[-93.39456199999999,48.610203],"type":"Point"}
}