{
  "type": "Feature",
  "properties": {
    "addr:full":"8763 Bayview Ave #A Richmond Hill ON L4B 3V1",
    "addr:housenumber":"8763",
    "addr:postcode":"l4b 3v1",
    "addr:street":"Bayview Ave # A",
    "iso:country":"CA",
    "sg:address":"8763 Bayview Ave #A",
    "sg:city":"Richmond Hill",
    "sg:classifiers":[
        {
            "category":"Shopping",
            "subcategory":"Computers & Home Electronics",
            "type":"Retail Goods"
        }
    ],
    "sg:phone":"+1 905 881 7109",
    "sg:postcode":"L4B 3V1",
    "sg:province":"ON",
    "sg:tags":[
        "high",
        "fidelity",
        "stereophonic"
    ],
    "wof:name":"Audio Excellence Inc",
    "wof:placetype":"venue"
},
  "geometry": {"coordinates":[-79.407578,43.845051],"type":"Point"}
}