{
  "type": "Feature",
  "properties": {
    "iso:country":"CA",
    "sg:address":"33 King St W",
    "sg:city":"Forest",
    "sg:classifiers":[
        {
            "category":"Insurance",
            "subcategory":"Insurance Agent",
            "type":"Services"
        }
    ],
    "sg:phone":"+1 519 786 2101",
    "sg:postcode":"N0N 1J0",
    "sg:province":"ON",
    "wof:name":"Gamble & Assoc Insurance Ltd",
    "wof:placetype":"venue"
},
  "geometry": {"coordinates":[-82.0019683838,43.0966796875],"type":"Point"}
}