{
  "type": "Feature",
  "properties": {
    "addr:full":"635 19 St S Lethbridge AB T1J 3G8",
    "addr:housenumber":"635 19",
    "addr:postcode":"t1j 3g8",
    "addr:street":"St S",
    "iso:country":"CA",
    "sg:address":"635 19 St S",
    "sg:city":"Lethbridge",
    "sg:classifiers":[
        {
            "category":"Insurance",
            "subcategory":"Insurance Agent",
            "type":"Services"
        }
    ],
    "sg:phone":"+1 403 327 6826",
    "sg:postcode":"T1J 3G8",
    "sg:province":"AB",
    "sg:tags":[
        "adjuster"
    ],
    "wof:name":"Carbert Adjusters Ltd",
    "wof:placetype":"venue"
},
  "geometry": {"coordinates":[-112.814438,49.690807],"type":"Point"}
}