{
  "type": "Feature",
  "properties": {
    "addr:full":"1348 Old Cariboo Rd Cache Creek BC V0K 1H0",
    "addr:housenumber":"1348",
    "addr:postcode":"v0k 1h0",
    "addr:street":"Old Cariboo Rd",
    "iso:country":"CA",
    "sg:address":"1348 Old Cariboo Rd",
    "sg:city":"Cache Creek",
    "sg:classifiers":[
        {
            "category":"Retail",
            "subcategory":"Veterinary Services",
            "type":"Services"
        }
    ],
    "sg:phone":"+1 250 457 6203",
    "sg:postcode":"V0K 1H0",
    "sg:province":"BC",
    "sg:tags":[
        "veterinarian"
    ],
    "wof:name":"Cache Creek Vet Hospital",
    "wof:placetype":"venue"
},
  "geometry": {"coordinates":[-121.326813,50.805397],"type":"Point"}
}