{
  "type": "Feature",
  "properties": {
    "addr:full":"36 Mccurdy Dr Gander NL A1V 1A2",
    "addr:housenumber":"36",
    "addr:postcode":"a1v 1a2",
    "addr:street":"Mccurdy Dr",
    "iso:country":"CA",
    "sg:address":"36 Mccurdy Dr",
    "sg:city":"Gander",
    "sg:classifiers":[
        {
            "category":"Organizations",
            "subcategory":"Membership Organization",
            "type":"Services"
        }
    ],
    "sg:phone":"+1 709 651 3002",
    "sg:postcode":"A1V 1A2",
    "sg:province":"NL",
    "sg:tags":[
        "protection",
        "animal"
    ],
    "wof:name":"Spca",
    "wof:placetype":"venue"
},
  "geometry": {"coordinates":[-54.623146,48.963852],"type":"Point"}
}