{
  "type": "Feature",
  "properties": {
    "iso:country":"CA",
    "sg:city":"Coldbrook",
    "sg:classifiers":[
        {
            "category":"Food & Beverages",
            "subcategory":"Specialty",
            "type":"Retail Goods"
        }
    ],
    "sg:phone":"+1 902 678 1110",
    "sg:postcode":"B4R 1A2",
    "sg:province":"NS",
    "sg:tags":[
        "health",
        "diet"
    ],
    "wof:name":"Maria's Health Foods",
    "wof:placetype":"venue"
},
  "geometry": {"coordinates":[-64.59893798829999,45.0615615845],"type":"Point"}
}