{
  "type": "Feature",
  "properties": {
    "addr:full":"2040 Moncrief Rd Peterborough ON K9K 1N8",
    "addr:housenumber":"2040",
    "addr:postcode":"k9k 1n8",
    "addr:street":"Moncrief Rd",
    "iso:country":"CA",
    "sg:address":"2040 Moncrief Rd",
    "sg:city":"Peterborough",
    "sg:classifiers":[
        {
            "category":"Building & Trades",
            "subcategory":"Plumbing",
            "type":"Services"
        }
    ],
    "sg:phone":"+1 705 740 9436",
    "sg:postcode":"K9K 1N8",
    "sg:province":"ON",
    "sg:tags":[
        "conditioning",
        "air",
        "system",
        "contractor"
    ],
    "wof:name":"Intergrated Air",
    "wof:placetype":"venue"
},
  "geometry": {"coordinates":[-78.368477,44.281342],"type":"Point"}
}