{
  "type": "Feature",
  "properties": {
    "addr:full":"Calgary AB T2V 4J8",
    "addr:postcode":"t2v 4j8",
    "iso:country":"CA",
    "sg:city":"Calgary",
    "sg:classifiers":[
        {
            "category":"Shopping",
            "subcategory":"Clothing, Apparel, & Fashions",
            "type":"Retail Goods"
        }
    ],
    "sg:phone":"+1 403 251 6103",
    "sg:postcode":"T2V 4J8",
    "sg:province":"AB",
    "sg:tags":[
        "repairing",
        "boot",
        "shoe"
    ],
    "wof:name":"Express Shoe Repair & Fantasy",
    "wof:placetype":"venue"
},
  "geometry": {"coordinates":[-114.121002197,50.9610977173],"type":"Point"}
}