{
  "type": "Feature",
  "properties": {
    "iso:country":"CA",
    "sg:address":"377 Dalhousie",
    "sg:city":"Ottawa",
    "sg:classifiers":[
        {
            "category":"Professional",
            "subcategory":"Computer Services",
            "type":"Services"
        }
    ],
    "sg:postcode":"K1N 7G2",
    "sg:tags":[
        "travel",
        "blog",
        "community",
        "social-network",
        "blogging"
    ],
    "sg:website":"http://www.travelpod.com",
    "wof:name":"TravelPod",
    "wof:placetype":"venue"
},
  "geometry": {"coordinates":[-75.6898711,45.4273982],"type":"Point"}
}