{
  "type": "Feature",
  "properties": {
    "addr:full":"Castlegar BC V1N 2W9",
    "addr:postcode":"v1n 2w9",
    "iso:country":"CA",
    "sg:city":"Castlegar",
    "sg:classifiers":[
        {
            "category":"Real Estate",
            "subcategory":"Real Estate Operator",
            "type":"Services"
        }
    ],
    "sg:phone":"+1 250 365 3034",
    "sg:postcode":"V1N 2W9",
    "sg:province":"BC",
    "sg:tags":[
        "apartment"
    ],
    "wof:name":"Selkirk Manor",
    "wof:placetype":"venue"
},
  "geometry": {"coordinates":[-117.651481628,49.2931137085],"type":"Point"}
}