{
  "type": "Feature",
  "properties": {
    "addr:full":"Sainte-Madeleine QC J0H 1S0",
    "addr:postcode":"j0h 1s0",
    "iso:country":"CA",
    "sg:city":"Sainte-Madeleine",
    "sg:classifiers":[
        {
            "category":"Retail",
            "subcategory":"Auto Repair",
            "type":"Services"
        }
    ],
    "sg:phone":"+1 450 795 3183",
    "sg:postcode":"J0H 1S0",
    "sg:province":"QC",
    "sg:tags":[
        "body",
        "automobile",
        "painting"
    ],
    "wof:name":"Carosseries Plus Enr",
    "wof:placetype":"venue"
},
  "geometry": {"coordinates":[-73.102242,45.601967],"type":"Point"}
}