{
  "type": "Feature",
  "properties": {
    "addr:full":"52 Forest Circle Crt Woodbridge ON L4L 1N9",
    "addr:housenumber":"52",
    "addr:postcode":"l4l 1n9",
    "addr:street":"Forest Circle Crt",
    "iso:country":"CA",
    "sg:address":"52 Forest Circle Crt",
    "sg:city":"Woodbridge",
    "sg:classifiers":[
        {
            "category":"Building & Trades",
            "subcategory":"Construction",
            "type":"Services"
        }
    ],
    "sg:phone":"+1 905 851 4855",
    "sg:postcode":"L4L 1N9",
    "sg:province":"ON",
    "sg:tags":[
        "general",
        "contractor"
    ],
    "wof:name":"Expert Concrete Floors Ltd",
    "wof:placetype":"venue"
},
  "geometry": {"coordinates":[-79.586685,43.782375],"type":"Point"}
}