{
  "type": "Feature",
  "properties": {
    "addr:full":"3033 King George Hwy # 9 Surrey BC V4P 1B8",
    "addr:housenumber":"3033;hwy",
    "addr:postcode":"v4p 1b8",
    "addr:street":"King George;# 9",
    "iso:country":"CA",
    "sg:address":"3033 King George Hwy # 9",
    "sg:city":"Surrey",
    "sg:classifiers":[
        {
            "category":"Freight",
            "type":"Transportation"
        }
    ],
    "sg:phone":"+1 604 538 2959",
    "sg:postcode":"V4P 1B8",
    "sg:province":"BC",
    "sg:tags":[
        "delivery",
        "courier"
    ],
    "wof:name":"White Rock Courier Ltd",
    "wof:placetype":"venue"
},
  "geometry": {"coordinates":[-122.80798299999999,49.057056],"type":"Point"}
}