{
  "type": "Feature",
  "properties": {
    "iso:country":"CA",
    "sg:address":"21 Rue Comeau",
    "sg:city":"Sept-Iles",
    "sg:classifiers":[
        {
            "category":"Organizations",
            "subcategory":"Professional Association",
            "type":"Services"
        }
    ],
    "sg:phone":"+1 418 962 2809",
    "sg:postcode":"G4R 1J1",
    "sg:province":"QC",
    "sg:tags":[
        "club"
    ],
    "wof:name":"Club DE Curling DE Sept-Iles",
    "wof:placetype":"venue"
},
  "geometry": {"coordinates":[-66.36684417719999,50.2170257568],"type":"Point"}
}