{
  "type": "Feature",
  "properties": {
    "addr:full":"6424 54 St NE Calgary AB T3J 1Z5",
    "addr:housenumber":"6424",
    "addr:postcode":"t3j 1z5",
    "addr:street":"54 St Ne",
    "iso:country":"CA",
    "sg:address":"6424 54 St NE",
    "sg:city":"Calgary",
    "sg:classifiers":[
        {
            "category":"Building & Trades",
            "subcategory":"Construction",
            "type":"Services"
        }
    ],
    "sg:phone":"+1 403 285 5180",
    "sg:postcode":"T3J 1Z5",
    "sg:province":"AB",
    "sg:tags":[
        "general",
        "painter",
        "contractor"
    ],
    "wof:name":"Creative Contracting",
    "wof:placetype":"venue"
},
  "geometry": {"coordinates":[-113.955803,51.108818],"type":"Point"}
}