{
  "type": "Feature",
  "properties": {
    "addr:full":"1325 Rue Wellington S Sherbrooke QC J1H 5E8",
    "addr:housenumber":"1325",
    "addr:postcode":"j1h 5e8",
    "addr:street":"Rue Wellington S",
    "iso:country":"CA",
    "sg:address":"1325 Rue Wellington S",
    "sg:city":"Sherbrooke",
    "sg:classifiers":[
        {
            "category":"Retail",
            "subcategory":"Car Wash",
            "type":"Services"
        }
    ],
    "sg:phone":"+1 819 821 4447",
    "sg:postcode":"J1H 5E8",
    "sg:province":"QC",
    "sg:tags":[
        "polishing",
        "washing"
    ],
    "wof:name":"Lave-Auto Wellington",
    "wof:placetype":"venue"
},
  "geometry": {"coordinates":[-71.8824539185,45.3877754211],"type":"Point"}
}