{
  "type": "Feature",
  "properties": {
    "addr:full":"8468 County Rd No 7 Addison ON K0E 1A0",
    "addr:housenumber":"8468;7",
    "addr:postcode":"k0e 1a0",
    "addr:street":"County Rd No",
    "iso:country":"CA",
    "sg:address":"8468 County Rd No 7",
    "sg:city":"Addison",
    "sg:classifiers":[
        {
            "category":"Government",
            "subcategory":"Office",
            "type":"Public Place"
        }
    ],
    "sg:phone":"+1 613 924 9934",
    "sg:postcode":"K0E 1A0",
    "sg:province":"ON",
    "sg:tags":[
        "village"
    ],
    "wof:name":"Elizabethtown Waste Disposal",
    "wof:placetype":"venue"
},
  "geometry": {"coordinates":[-75.882835,44.660774],"type":"Point"}
}