{
  "type": "Feature",
  "properties": {
    "addr:full":"80 Rue Des Erables Saint-Thomas QC J0K 3L0",
    "addr:housenumber":"80",
    "addr:postcode":"j0k 3l0",
    "addr:street":"Rue Des Erables",
    "iso:country":"CA",
    "sg:address":"80 Rue Des Erables",
    "sg:city":"Saint-Thomas",
    "sg:classifiers":[
        {
            "category":"Wholesale",
            "subcategory":"Chemicals & Plastics",
            "type":"Manufacturing & Wholesale Goods"
        }
    ],
    "sg:phone":"+1 450 759 4700",
    "sg:postcode":"J0K 3L0",
    "sg:province":"QC",
    "wof:name":"Semico Inc",
    "wof:placetype":"venue"
},
  "geometry": {"coordinates":[-73.35056304930001,46.0132522583],"type":"Point"}
}