{
  "type": "Feature",
  "properties": {
    "addr:full":"5003 51 St Lougheed AB T0B 2V0",
    "addr:housenumber":"5003",
    "addr:postcode":"t0b 2v0",
    "addr:street":"51 St",
    "iso:country":"CA",
    "sg:address":"5003 51 St",
    "sg:city":"Lougheed",
    "sg:classifiers":[
        {
            "category":"Building & Trades",
            "subcategory":"Construction",
            "type":"Services"
        }
    ],
    "sg:phone":"+1 780 386 3915",
    "sg:postcode":"T0B 2V0",
    "sg:province":"AB",
    "sg:tags":[
        "water",
        "well",
        "drilling"
    ],
    "wof:name":"Chris's Waterwell Svc",
    "wof:placetype":"venue"
},
  "geometry": {"coordinates":[-111.546775818,52.7442436218],"type":"Point"}
}