{
  "type": "Feature",
  "properties": {
    "addr:full":"345 117 Rte Mont-Tremblant QC J8E 2X4",
    "addr:housenumber":"117",
    "addr:postcode":"j8e 2x4",
    "addr:street":"Rte Mont-Tremblant",
    "iso:country":"CA",
    "sg:address":"345 117 Rte",
    "sg:city":"Mont-Tremblant",
    "sg:classifiers":[
        {
            "category":"Autos & Motor Vehicles",
            "subcategory":"Automobile Sales",
            "type":"Retail Goods"
        }
    ],
    "sg:phone":"+1 819 425 3718",
    "sg:postcode":"J8E 2X4",
    "sg:province":"QC",
    "sg:tags":[
        "car",
        "dealer"
    ],
    "wof:name":"Les Sommets Pontiac Buick",
    "wof:placetype":"venue"
},
  "geometry": {"coordinates":[-74.567841,46.116135],"type":"Point"}
}