{
  "type": "Feature",
  "properties": {
    "addr:full":"160 Saunders Rd Barrie ON L4N 9A4",
    "addr:housenumber":"160",
    "addr:postcode":"l4n 9a4",
    "addr:street":"Saunders Rd",
    "iso:country":"CA",
    "sg:address":"160 Saunders Rd",
    "sg:city":"Barrie",
    "sg:classifiers":[
        {
            "category":"Wholesale",
            "subcategory":"Machinery & Supplies",
            "type":"Manufacturing & Wholesale Goods"
        }
    ],
    "sg:phone":"+1 705 739 3500",
    "sg:postcode":"L4N 9A4",
    "sg:province":"ON",
    "sg:tags":[
        "equipment",
        "pneumatic",
        "component"
    ],
    "wof:name":"Delta Fluid Air Inc",
    "wof:placetype":"venue"
},
  "geometry": {"coordinates":[-79.67645263670001,44.3325614929],"type":"Point"}
}