{
  "type": "Feature",
  "properties": {
    "addr:full":"505 53 Ave SE Calgary AB T2H 0N5",
    "addr:postcode":"t2h 0n5",
    "addr:street":"505 53 Ave Se",
    "iso:country":"CA",
    "sg:address":"505 53 Ave SE",
    "sg:city":"Calgary",
    "sg:classifiers":[
        {
            "category":"Wholesale",
            "subcategory":"Auto Parts",
            "type":"Manufacturing & Wholesale Goods"
        }
    ],
    "sg:phone":"+1 403 258 2909",
    "sg:postcode":"T2H 0N5",
    "sg:province":"AB",
    "sg:tags":[
        "speedometer"
    ],
    "wof:name":"Mr Speedometer",
    "wof:placetype":"venue"
},
  "geometry": {"coordinates":[-114.053566,51.005848],"type":"Point"}
}