{
  "type": "Feature",
  "properties": {
    "iso:country":"CA",
    "sg:city":"Winlaw",
    "sg:classifiers":[
        {
            "category":"Shopping",
            "subcategory":"Books",
            "type":"Retail Goods"
        }
    ],
    "sg:phone":"+1 250 226 7265",
    "sg:postcode":"V0G 2J0",
    "sg:province":"BC",
    "sg:tags":[
        "dealer"
    ],
    "wof:name":"Earth Spirit Metaphysical Bks",
    "wof:placetype":"venue"
},
  "geometry": {"coordinates":[-117.498512268,49.6750488281],"type":"Point"}
}