{
  "type": "Feature",
  "properties": {
    "addr:full":"32 Rue DE L'Artisan Victoriaville QC G6P 7E3",
    "addr:housenumber":"32",
    "addr:postcode":"g6p 7e3",
    "addr:street":"Rue De L'Artisan",
    "iso:country":"CA",
    "sg:address":"32 Rue DE L'Artisan",
    "sg:city":"Victoriaville",
    "sg:classifiers":[
        {
            "category":"Manufacturing",
            "subcategory":"Furniture",
            "type":"Manufacturing & Wholesale Goods"
        }
    ],
    "sg:phone":"+1 819 758 3739",
    "sg:postcode":"G6P 7E3",
    "sg:province":"QC",
    "wof:name":"Alphavic Inc",
    "wof:placetype":"venue"
},
  "geometry": {"coordinates":[-71.9602508545,46.0712738037],"type":"Point"}
}