{
  "type": "Feature",
  "properties": {
    "addr:full":"Mont-Royal QC H3P 3E9",
    "addr:postcode":"h3p 3e9",
    "iso:country":"CA",
    "sg:city":"Mont-Royal",
    "sg:classifiers":[
        {
            "category":"Shopping",
            "subcategory":"Shoes",
            "type":"Retail Goods"
        }
    ],
    "sg:phone":"+1 514 342 0897",
    "sg:postcode":"H3P 3E9",
    "sg:province":"QC",
    "wof:name":"Foot Locker",
    "wof:placetype":"venue"
},
  "geometry": {"coordinates":[-73.648483,45.52673],"type":"Point"}
}