{
  "type": "Feature",
  "properties": {
    "addr:full":"870 Upper James St Hamilton ON L9C 3A4",
    "addr:housenumber":"870",
    "addr:postcode":"l9c 3a4",
    "addr:street":"Upper James St",
    "iso:country":"CA",
    "sg:address":"870 Upper James St",
    "sg:city":"Hamilton",
    "sg:classifiers":[
        {
            "category":"Restaurant",
            "type":"Food & Drink"
        }
    ],
    "sg:phone":"+1 905 388 8864",
    "sg:postcode":"L9C 3A4",
    "sg:province":"ON",
    "wof:name":"Tarboosh Restaurant",
    "wof:placetype":"venue"
},
  "geometry": {"coordinates":[-79.882645,43.226936],"type":"Point"}
}