{
  "type": "Feature",
  "properties": {
    "addr:full":"395 Mulock Dr Newmarket ON L3Y 8P3",
    "addr:housenumber":"395",
    "addr:postcode":"l3y 8p3",
    "addr:street":"Mulock Dr",
    "iso:country":"CA",
    "sg:address":"395 Mulock Dr",
    "sg:city":"Newmarket",
    "sg:classifiers":[
        {
            "category":"Government",
            "subcategory":"Office",
            "type":"Public Place"
        }
    ],
    "sg:phone":"+1 905 895 5193",
    "sg:postcode":"L3Y 8P3",
    "sg:province":"ON",
    "sg:tags":[
        "village"
    ],
    "wof:name":"Newmarket Mayor's Office",
    "wof:placetype":"venue"
},
  "geometry": {"coordinates":[-79.45845031739999,44.0403442383],"type":"Point"}
}