{
  "type": "Feature",
  "properties": {
    "addr:full":"129 S Railway St Balgonie SK S0G 0E0",
    "addr:housenumber":"129",
    "addr:postcode":"s0g 0e0",
    "addr:street":"S Railway St",
    "iso:country":"CA",
    "sg:address":"129 S Railway St",
    "sg:city":"Balgonie",
    "sg:classifiers":[
        {
            "category":"Education",
            "subcategory":"Library",
            "type":"Public Place"
        }
    ],
    "sg:phone":"+1 306 771 2332",
    "sg:postcode":"S0G 0E0",
    "sg:province":"SK",
    "wof:name":"Balgonie Branch Library",
    "wof:placetype":"venue"
},
  "geometry": {"coordinates":[-104.27420044,50.4896736145],"type":"Point"}
}