{
  "type": "Feature",
  "properties": {
    "addr:full":"St Louis SK S0J 2C0",
    "addr:postcode":"s0j 2c0",
    "iso:country":"CA",
    "sg:city":"St Louis",
    "sg:classifiers":[
        {
            "category":"Insurance",
            "subcategory":"Insurance Agent",
            "type":"Services"
        }
    ],
    "sg:phone":"+1 306 422 8525",
    "sg:postcode":"S0J 2C0",
    "sg:province":"SK",
    "wof:name":"Riverside Agencies",
    "wof:placetype":"venue"
},
  "geometry": {"coordinates":[-105.804626465,52.9227828979],"type":"Point"}
}