{
  "type": "Feature",
  "properties": {
    "addr:full":"Forest ON N0N 1J0",
    "addr:postcode":"n0n 1j0",
    "iso:country":"CA",
    "sg:city":"Forest",
    "sg:classifiers":[
        {
            "category":"Organizations",
            "subcategory":"Religious Organization",
            "type":"Services"
        }
    ],
    "sg:phone":"+1 519 786 5243",
    "sg:postcode":"N0N 1J0",
    "sg:province":"ON",
    "sg:tags":[
        "church"
    ],
    "wof:name":"St Christopher's Roman",
    "wof:placetype":"venue"
},
  "geometry": {"coordinates":[-82.0005264282,43.1004219055],"type":"Point"}
}