{
  "type": "Feature",
  "properties": {
    "addr:full":"5653 Rue Saint-Georges Levis QC G6V 4L9",
    "addr:housenumber":"5653",
    "addr:postcode":"g6v 4l9",
    "addr:street":"Rue Saint-Georges",
    "iso:country":"CA",
    "sg:address":"5653 Rue Saint-Georges",
    "sg:city":"Levis",
    "sg:classifiers":[
        {
            "category":"Shopping",
            "subcategory":"Clothing, Apparel, & Fashions",
            "type":"Retail Goods"
        }
    ],
    "sg:phone":"+1 418 835 6226",
    "sg:postcode":"G6V 4L9",
    "sg:province":"QC",
    "sg:tags":[
        "tailor"
    ],
    "wof:name":"Ma Couturiere Enr",
    "wof:placetype":"venue"
},
  "geometry": {"coordinates":[-71.181679,46.80032],"type":"Point"}
}