{
  "type": "Feature",
  "properties": {
    "addr:full":"Winnipeg MB R3L 2W2",
    "addr:postcode":"r3l 2w2",
    "iso:country":"CA",
    "sg:city":"Winnipeg",
    "sg:classifiers":[
        {
            "category":"Professional",
            "subcategory":"Research",
            "type":"Services"
        }
    ],
    "sg:phone":"+1 204 453 1835",
    "sg:postcode":"R3L 2W2",
    "sg:province":"MB",
    "sg:tags":[
        "market",
        "analysis"
    ],
    "wof:name":"Hill Top Research Inc",
    "wof:placetype":"venue"
},
  "geometry": {"coordinates":[-97.1421966553,49.8750686646],"type":"Point"}
}