{
  "type": "Feature",
  "properties": {
    "addr:full":"45 Mcmorran Cres Thornhill ON L4J 2T4",
    "addr:housenumber":"45",
    "addr:postcode":"l4j 2t4",
    "addr:street":"Mcmorran Cres",
    "iso:country":"CA",
    "sg:address":"45 Mcmorran Cres",
    "sg:city":"Thornhill",
    "sg:classifiers":[
        {
            "category":"Social Services",
            "type":"Services"
        }
    ],
    "sg:phone":"+1 905 731 0942",
    "sg:postcode":"L4J 2T4",
    "sg:province":"ON",
    "sg:tags":[
        "counselor",
        "marriage",
        "family"
    ],
    "wof:name":"Cooper, Gail",
    "wof:placetype":"venue"
},
  "geometry": {"coordinates":[-79.449256897,43.7997322083],"type":"Point"}
}