{
  "type": "Feature",
  "properties": {
    "addr:full":"Monte Lake BC V0E 2N0",
    "addr:postcode":"bc v0e 2n0",
    "addr:street":"Monte Lake",
    "iso:country":"CA",
    "sg:city":"Monte Lake",
    "sg:classifiers":[
        {
            "category":"Real Estate",
            "subcategory":"Real Estate Operator",
            "type":"Services"
        }
    ],
    "sg:phone":"+1 250 375 2434",
    "sg:postcode":"V0E 2N0",
    "sg:province":"BC",
    "sg:tags":[
        "mobile",
        "campground",
        "community"
    ],
    "wof:name":"Heritage Campsite & Rv Park",
    "wof:placetype":"venue"
},
  "geometry": {"coordinates":[-119.835281372,50.5233154297],"type":"Point"}
}