{
  "type": "Feature",
  "properties": {
    "iso:country":"CA",
    "sg:address":"Hwy 88",
    "sg:city":"Slave Lake",
    "sg:classifiers":[
        {
            "category":"Travel",
            "subcategory":"Hotels & Motels",
            "type":"Entertainment"
        }
    ],
    "sg:phone":"+1 780 849 2688",
    "sg:postcode":"T0G 2A0",
    "sg:province":"AB",
    "sg:tags":[
        "resort",
        "tourist",
        "accommodation"
    ],
    "wof:name":"Nash's Cabins",
    "wof:placetype":"venue"
},
  "geometry": {"coordinates":[-114.759208679,55.2976036072],"type":"Point"}
}