{
  "type": "Feature",
  "properties": {
    "addr:full":"3839 Ogden Rd SE Calgary AB T2G 4N6",
    "addr:housenumber":"3839",
    "addr:postcode":"t2g 4n6",
    "addr:street":"Ogden Rd Se",
    "iso:country":"CA",
    "sg:address":"3839 Ogden Rd SE",
    "sg:city":"Calgary",
    "sg:classifiers":[
        {
            "category":"Freight",
            "type":"Transportation"
        }
    ],
    "sg:phone":"+1 403 216 5650",
    "sg:postcode":"T2G 4N6",
    "sg:province":"AB",
    "sg:tags":[
        "warehouse",
        "storage"
    ],
    "wof:name":"Versacold Group Calgary",
    "wof:placetype":"venue"
},
  "geometry": {"coordinates":[-114.030708,51.020756],"type":"Point"}
}