{
  "type": "Feature",
  "properties": {
    "addr:full":"259 Brunswick St Fredericton NB E3B 1G8",
    "addr:housenumber":"259",
    "addr:postcode":"e3b 1g8",
    "addr:street":"Brunswick St",
    "iso:country":"CA",
    "sg:address":"259 Brunswick St",
    "sg:city":"Fredericton",
    "sg:classifiers":[
        {
            "category":"Health Services",
            "subcategory":"Health Practitioner",
            "type":"Services"
        }
    ],
    "sg:phone":"+1 506 450 1107",
    "sg:postcode":"E3B 1G8",
    "sg:province":"NB",
    "sg:tags":[
        "psychologist"
    ],
    "wof:name":"Mc Cormack, Peter",
    "wof:placetype":"venue"
},
  "geometry": {"coordinates":[-66.64785766599999,45.9625892639],"type":"Point"}
}