{
  "type": "Feature",
  "properties": {
    "addr:full":"1500 Rue Janelle Drummondville QC J2C 3E5",
    "addr:housenumber":"1500",
    "addr:postcode":"j2c 3e5",
    "addr:street":"Rue Janelle",
    "iso:country":"CA",
    "sg:address":"1500 Rue Janelle",
    "sg:city":"Drummondville",
    "sg:classifiers":[
        {
            "category":"Manufacturing",
            "subcategory":"Tools & Machinery",
            "type":"Manufacturing & Wholesale Goods"
        }
    ],
    "sg:phone":"+1 819 472 1155",
    "sg:postcode":"J2C 3E5",
    "sg:province":"QC",
    "sg:tags":[
        "equipment",
        "electric"
    ],
    "wof:name":"Siemens Au Canada",
    "wof:placetype":"venue"
},
  "geometry": {"coordinates":[-72.5192565918,45.8855895996],"type":"Point"}
}