{
  "type": "Feature",
  "properties": {
    "addr:full":"Waterloo ON N2V 2B7",
    "addr:postcode":"n2v 2b7",
    "iso:country":"CA",
    "sg:city":"Waterloo",
    "sg:classifiers":[
        {
            "category":"Building & Trades",
            "subcategory":"Landscaping Services",
            "type":"Services"
        }
    ],
    "sg:phone":"+1 519 746 8333",
    "sg:postcode":"N2V 2B7",
    "sg:province":"ON",
    "sg:tags":[
        "control",
        "lawn",
        "weed",
        "maintenance",
        "grounds"
    ],
    "wof:name":"Weed Man",
    "wof:placetype":"venue"
},
  "geometry": {"coordinates":[-80.530921936,43.510761261],"type":"Point"}
}