{
  "type": "Feature",
  "properties": {
    "addr:full":"444 Gatesway Ave #A Edwardsville NS B2A 4V1",
    "addr:housenumber":"444",
    "addr:postcode":"b2a 4v1",
    "addr:street":"Gatesway Ave # A",
    "iso:country":"CA",
    "sg:address":"444 Gatesway Ave #A",
    "sg:city":"Edwardsville",
    "sg:classifiers":[
        {
            "category":"Wholesale",
            "subcategory":"Furniture",
            "type":"Manufacturing & Wholesale Goods"
        }
    ],
    "sg:phone":"+1 902 567 2900",
    "sg:postcode":"B2A 4V1",
    "sg:province":"NS",
    "wof:name":"Preferred Office Environments",
    "wof:placetype":"venue"
},
  "geometry": {"coordinates":[-60.229713,46.156395],"type":"Point"}
}