{
  "type": "Feature",
  "properties": {
    "iso:country":"CA",
    "sg:address":"101 2nd St",
    "sg:city":"Thorhild",
    "sg:classifiers":[
        {
            "category":"Autos & Motor Vehicles",
            "subcategory":"Automobile Sales",
            "type":"Retail Goods"
        }
    ],
    "sg:phone":"+1 780 398 3517",
    "sg:postcode":"T0A 3J0",
    "sg:province":"AB",
    "sg:tags":[
        "car",
        "dealer"
    ],
    "wof:name":"Thorhild Service Garage CO Ltd",
    "wof:placetype":"venue"
},
  "geometry": {"coordinates":[-113.125495911,54.1522064209],"type":"Point"}
}