{
  "type": "Feature",
  "properties": {
    "addr:full":"8 Hwy 540A Gore Bay ON P0P 1H0",
    "addr:postcode":"p0p 1h0",
    "addr:street":"8 Hwy 540A",
    "iso:country":"CA",
    "sg:address":"8 Hwy 540A",
    "sg:city":"Gore Bay",
    "sg:classifiers":[
        {
            "category":"Wholesale",
            "subcategory":"Farm Supplies",
            "type":"Manufacturing & Wholesale Goods"
        }
    ],
    "sg:phone":"+1 705 282 1508",
    "sg:postcode":"P0P 1H0",
    "sg:province":"ON",
    "wof:name":"Northland Agromart",
    "wof:placetype":"venue"
},
  "geometry": {"coordinates":[-82.47086299999999,45.903069],"type":"Point"}
}