{
  "type": "Feature",
  "properties": {
    "addr:full":"135 York Hill Blvd Thornhill ON L4J 2P5",
    "addr:housenumber":"135",
    "addr:postcode":"l4j 2p5",
    "addr:street":"York Hill Blvd",
    "iso:country":"CA",
    "sg:address":"135 York Hill Blvd",
    "sg:city":"Thornhill",
    "sg:classifiers":[
        {
            "category":"Restaurant",
            "type":"Food & Drink"
        }
    ],
    "sg:phone":"+1 905 886 3352",
    "sg:postcode":"L4J 2P5",
    "sg:province":"ON",
    "wof:name":"J P Oyster Ltd",
    "wof:placetype":"venue"
},
  "geometry": {"coordinates":[-79.4449081421,43.8008537292],"type":"Point"}
}