{
  "type": "Feature",
  "properties": {
    "addr:full":"12525 125 St NW Edmonton AB T5L 0T4",
    "addr:housenumber":"12525",
    "addr:postcode":"t5l 0t4",
    "addr:street":"125 St Nw",
    "iso:country":"CA",
    "sg:address":"12525 125 St NW",
    "sg:city":"Edmonton",
    "sg:classifiers":[
        {
            "category":"Building & Trades",
            "subcategory":"Plumbing",
            "type":"Services"
        }
    ],
    "sg:phone":"+1 780 453 3257",
    "sg:postcode":"T5L 0T4",
    "sg:province":"AB",
    "sg:tags":[
        "contractor"
    ],
    "wof:name":"Natik Projects Inc",
    "wof:placetype":"venue"
},
  "geometry": {"coordinates":[-113.53750599999999,53.581299],"type":"Point"}
}