{
  "type": "Feature",
  "properties": {
    "iso:country":"CA",
    "sg:address":"1013 Rue Daigneault",
    "sg:city":"Acton Vale",
    "sg:classifiers":[
        {
            "category":"Retail",
            "subcategory":"Auto Repair",
            "type":"Services"
        }
    ],
    "sg:phone":"+1 450 546 2313",
    "sg:postcode":"J0H 1A0",
    "sg:province":"QC",
    "sg:tags":[
        "repairing",
        "automobile"
    ],
    "wof:name":"Garage Fontaine Dores",
    "wof:placetype":"venue"
},
  "geometry": {"coordinates":[-72.5649032593,45.6468963623],"type":"Point"}
}