{
  "type": "Feature",
  "properties": {
    "addr:full":"Saint-Andre-Avellin QC J0V 1W0",
    "addr:postcode":"j0v 1w0",
    "iso:country":"CA",
    "sg:city":"Saint-Andre-Avellin",
    "sg:classifiers":[
        {
            "category":"Social Services",
            "type":"Services"
        }
    ],
    "sg:phone":"+1 819 983 4519",
    "sg:postcode":"J0V 1W0",
    "sg:province":"QC",
    "sg:tags":[
        "youth",
        "organization",
        "jean",
        "center"
    ],
    "wof:name":"Maison Des Jeunes D'Avellin",
    "wof:placetype":"venue"
},
  "geometry": {"coordinates":[-75.046188,45.724834],"type":"Point"}
}