{
  "type": "Feature",
  "properties": {
    "addr:full":"3300 Cadboro Bay Rd Victoria BC V8R 5K5",
    "addr:housenumber":"3300",
    "addr:postcode":"v8r 5k5",
    "addr:street":"Cadboro Bay Rd",
    "iso:country":"CA",
    "sg:address":"3300 Cadboro Bay Rd",
    "sg:city":"Victoria",
    "sg:classifiers":[
        {
            "category":"Recreation",
            "type":"Entertainment"
        }
    ],
    "sg:phone":"+1 250 592 7313",
    "sg:postcode":"V8R 5K5",
    "sg:province":"BC",
    "sg:tags":[
        "course",
        "golf"
    ],
    "wof:name":"Uplands Golf Club",
    "wof:placetype":"venue"
},
  "geometry": {"coordinates":[-123.364517212,48.428314209],"type":"Point"}
}