{
  "type": "Feature",
  "properties": {
    "addr:full":"Ottawa ON K1V 1A4",
    "addr:postcode":"k1v 1a4",
    "iso:country":"CA",
    "sg:city":"Ottawa",
    "sg:classifiers":[
        {
            "category":"Shopping",
            "subcategory":"Optical Goods",
            "type":"Retail Goods"
        }
    ],
    "sg:phone":"+1 613 521 8884",
    "sg:postcode":"K1V 1A4",
    "sg:province":"ON",
    "sg:tags":[
        "optician"
    ],
    "wof:name":"Laurier Optical",
    "wof:placetype":"venue"
},
  "geometry": {"coordinates":[-75.6464920044,45.3534927368],"type":"Point"}
}