{
  "type": "Feature",
  "properties": {
    "addr:full":"10 Factory Lane # 100 St. John's NL A1C 6H5",
    "addr:housenumber":"10",
    "addr:postcode":"a1c 6h5",
    "addr:street":"Factory Lane # 100",
    "iso:country":"CA",
    "sg:address":"10 Factory Lane # 100",
    "sg:city":"St. John's",
    "sg:classifiers":[
        {
            "category":"Building & Trades",
            "subcategory":"Equipment Rental",
            "type":"Services"
        }
    ],
    "sg:phone":"+1 709 739 3948",
    "sg:postcode":"A1C 6H5",
    "sg:province":"NL",
    "sg:tags":[
        "leasing"
    ],
    "wof:name":"East Coast Capital",
    "wof:placetype":"venue"
},
  "geometry": {"coordinates":[-52.699104,47.572346],"type":"Point"}
}