{
  "type": "Feature",
  "properties": {
    "iso:country":"CA",
    "sg:address":"5635 Mintie Rd",
    "sg:city":"Halfmoon Bay",
    "sg:classifiers":[
        {
            "category":"Travel",
            "subcategory":"Hotels & Motels",
            "type":"Entertainment"
        }
    ],
    "sg:phone":"+1 604 885 4771",
    "sg:postcode":"V0N 1Y2",
    "sg:province":"BC",
    "sg:tags":[
        "breakfast",
        "accommodation",
        "bed"
    ],
    "wof:name":"Loghouse",
    "wof:placetype":"venue"
},
  "geometry": {"coordinates":[-123.91037799999999,49.511734],"type":"Point"}
}