{
  "type": "Feature",
  "properties": {
    "addr:full":"9030 132 Ave NW Edmonton AB T5E 0Y2",
    "addr:housenumber":"9030",
    "addr:postcode":"t5e 0y2",
    "addr:street":"132 Ave Nw",
    "iso:country":"CA",
    "sg:address":"9030 132 Ave NW",
    "sg:city":"Edmonton",
    "sg:classifiers":[
        {
            "category":"Food & Beverages",
            "subcategory":"Groceries & Convenience Stores",
            "type":"Retail Goods"
        }
    ],
    "sg:phone":"+1 780 473 1888",
    "sg:postcode":"T5E 0Y2",
    "sg:province":"AB",
    "sg:tags":[
        "grocer"
    ],
    "wof:name":"Glengarry Food Store",
    "wof:placetype":"venue"
},
  "geometry": {"coordinates":[-113.480904,53.592506],"type":"Point"}
}