{
  "type": "Feature",
  "properties": {
    "iso:country":"CA",
    "sg:address":"7 Anne St S",
    "sg:city":"Barrie",
    "sg:classifiers":[
        {
            "category":"Cinema",
            "subcategory":"Movie Rental",
            "type":"Entertainment"
        }
    ],
    "sg:phone":"+1 705 728 8611",
    "sg:postcode":"L4N 2C4",
    "sg:province":"ON",
    "sg:tags":[
        "leasing",
        "video",
        "disc",
        "tape"
    ],
    "wof:name":"Blockbuster Video",
    "wof:placetype":"venue"
},
  "geometry": {"coordinates":[-79.704697,44.382107],"type":"Point"}
}