{
  "type": "Feature",
  "properties": {
    "addr:full":"Vancouver BC V6H 3S7",
    "addr:postcode":"v6h 3s7",
    "iso:country":"CA",
    "sg:city":"Vancouver",
    "sg:classifiers":[
        {
            "category":"Health Services",
            "subcategory":"Doctor",
            "type":"Services"
        }
    ],
    "sg:phone":"+1 604 738 5033",
    "sg:postcode":"V6H 3S7",
    "sg:province":"BC",
    "sg:tags":[
        "dentist"
    ],
    "wof:name":"J S Diggens Inc",
    "wof:placetype":"venue"
},
  "geometry": {"coordinates":[-123.126815796,49.2640571594],"type":"Point"}
}