{
  "type": "Feature",
  "properties": {
    "addr:full":"PO Box 245 Sandy Lake ON P0V 1V0",
    "addr:housenumber":"po",
    "addr:postcode":"p0v 1v0",
    "addr:street":"Box 245",
    "iso:country":"CA",
    "sg:address":"PO Box 245",
    "sg:city":"Sandy Lake",
    "sg:classifiers":[
        {
            "category":"Building & Trades",
            "subcategory":"Equipment Rental",
            "type":"Services"
        }
    ],
    "sg:phone":"+1 807 774 1219",
    "sg:postcode":"P0V 1V0",
    "sg:province":"ON",
    "sg:tags":[
        "aircraft",
        "leasing",
        "charter"
    ],
    "wof:name":"Sandy Lake Seaplane Svc Ltd",
    "wof:placetype":"venue"
},
  "geometry": {"coordinates":[-93.33332799999999,53.05022],"type":"Point"}
}