{
  "type": "Feature",
  "properties": {
    "addr:full":"5 Rue Mitesh Betsiamites QC G0H 1B0",
    "addr:housenumber":"5",
    "addr:postcode":"g0h 1b0",
    "addr:street":"Rue Mitesh",
    "iso:country":"CA",
    "sg:address":"5 Rue Mitesh",
    "sg:city":"Betsiamites",
    "sg:classifiers":[
        {
            "category":"Home & Garden",
            "subcategory":"Hardware",
            "type":"Retail Goods"
        }
    ],
    "sg:phone":"+1 418 567 8368",
    "sg:postcode":"G0H 1B0",
    "sg:province":"QC",
    "wof:name":"Quincaillerie Meshtuk Enr",
    "wof:placetype":"venue"
},
  "geometry": {"coordinates":[-68.6477432251,48.9437561035],"type":"Point"}
}