{
  "type": "Feature",
  "properties": {
    "iso:country":"CA",
    "sg:address":"1228 Lands End Rd",
    "sg:city":"North Saanich",
    "sg:classifiers":[
        {
            "category":"Building & Trades",
            "subcategory":"Construction",
            "type":"Services"
        }
    ],
    "sg:phone":"+1 250 656 3611",
    "sg:postcode":"V8L 5K2",
    "sg:province":"BC",
    "sg:tags":[
        "roofing",
        "contractor"
    ],
    "wof:name":"Grist Slate & Tile Roofing",
    "wof:placetype":"venue"
},
  "geometry": {"coordinates":[-123.448364258,48.6967544556],"type":"Point"}
}