{
  "type": "Feature",
  "properties": {
    "addr:full":"126 Rue Saint-Antoine Gatineau QC J8T 3M4",
    "addr:housenumber":"126",
    "addr:postcode":"j8t 3m4",
    "addr:street":"Rue Saint-Antoine",
    "iso:country":"CA",
    "sg:address":"126 Rue Saint-Antoine",
    "sg:city":"Gatineau",
    "sg:classifiers":[
        {
            "category":"Organizations",
            "subcategory":"Membership Organization",
            "type":"Services"
        }
    ],
    "sg:phone":"+1 819 568 4710",
    "sg:postcode":"J8T 3M4",
    "sg:province":"QC",
    "wof:name":"Maison Unies-Vers-Femmes",
    "wof:placetype":"venue"
},
  "geometry": {"coordinates":[-75.699135,45.463802],"type":"Point"}
}