{
  "type": "Feature",
  "properties": {
    "iso:country":"CA",
    "sg:address":"4791 Ch DE LA Savane",
    "sg:city":"Saint-Hubert",
    "sg:classifiers":[
        {
            "category":"Manufacturing",
            "subcategory":"Metals",
            "type":"Manufacturing & Wholesale Goods"
        }
    ],
    "sg:phone":"+1 450 678 9488",
    "sg:postcode":"J3Y 9G1",
    "sg:province":"QC",
    "sg:tags":[
        "spinning"
    ],
    "wof:name":"Hard & Soft Metal Work",
    "wof:placetype":"venue"
},
  "geometry": {"coordinates":[-73.4270477295,45.5209655762],"type":"Point"}
}