{
  "type": "Feature",
  "properties": {
    "addr:full":"36 Bergen Cres NW Calgary AB T3K 1J3",
    "addr:housenumber":"36",
    "addr:postcode":"t3k 1j3",
    "addr:street":"Bergen Cres Nw",
    "iso:country":"CA",
    "sg:address":"36 Bergen Cres NW",
    "sg:city":"Calgary",
    "sg:classifiers":[
        {
            "category":"Mining & Drilling",
            "type":"Manufacturing & Wholesale Goods"
        }
    ],
    "sg:phone":"+1 403 275 0274",
    "sg:postcode":"T3K 1J3",
    "sg:province":"AB",
    "sg:tags":[
        "field",
        "oil"
    ],
    "wof:name":"Bec-Con Testing Ltd",
    "wof:placetype":"venue"
},
  "geometry": {"coordinates":[-114.072968,51.132069],"type":"Point"}
}