{
  "type": "Feature",
  "properties": {
    "addr:full":"3639 Broadway W Vancouver BC V6R 2B8",
    "addr:housenumber":"3639",
    "addr:postcode":"v6r 2b8",
    "addr:street":"Broadway W",
    "iso:country":"CA",
    "sg:address":"3639 Broadway W",
    "sg:city":"Vancouver",
    "sg:classifiers":[
        {
            "category":"Shopping",
            "subcategory":"Clothing, Apparel, & Fashions",
            "type":"Retail Goods"
        }
    ],
    "sg:phone":"+1 604 736 9970",
    "sg:postcode":"V6R 2B8",
    "sg:province":"BC",
    "sg:tags":[
        "tailor"
    ],
    "wof:name":"Paradise Fashion Studio",
    "wof:placetype":"venue"
},
  "geometry": {"coordinates":[-123.184532,49.264431],"type":"Point"}
}