{
  "type": "Feature",
  "properties": {
    "addr:full":"5908 50 Ave Red Deer AB T4N 4C3",
    "addr:housenumber":"5908",
    "addr:postcode":"t4n 4c3",
    "addr:street":"50 Ave",
    "iso:country":"CA",
    "sg:address":"5908 50 Ave",
    "sg:city":"Red Deer",
    "sg:classifiers":[
        {
            "category":"Autos & Motor Vehicles",
            "subcategory":"Auto Supplies",
            "type":"Retail Goods"
        }
    ],
    "sg:phone":"+1 403 343 2243",
    "sg:postcode":"T4N 4C3",
    "sg:province":"AB",
    "sg:tags":[
        "automobile",
        "parts"
    ],
    "wof:name":"Canadian Tire Gas Bar",
    "wof:placetype":"venue"
},
  "geometry": {"coordinates":[-113.814086914,52.278553009],"type":"Point"}
}