{
  "type": "Feature",
  "properties": {
    "iso:country":"CA",
    "sg:address":"33 City Centre Dr # 544",
    "sg:city":"Mississauga",
    "sg:classifiers":[
        {
            "category":"Professional",
            "subcategory":"Lawyer & Legal Services",
            "type":"Services"
        }
    ],
    "sg:phone":"+1 905 275 2588",
    "sg:postcode":"L5B 2N5",
    "sg:province":"ON",
    "sg:tags":[
        "attorney"
    ],
    "wof:name":"Silvester, John",
    "wof:placetype":"venue"
},
  "geometry": {"coordinates":[-79.63913,43.594429],"type":"Point"}
}