{
  "type": "Feature",
  "properties": {
    "addr:full":"Brampton ON L6T 4P7",
    "addr:postcode":"l6t 4p7",
    "iso:country":"CA",
    "sg:city":"Brampton",
    "sg:classifiers":[
        {
            "category":"Home & Garden",
            "subcategory":"Carpets & Floor Coverings",
            "type":"Retail Goods"
        }
    ],
    "sg:phone":"+1 905 793 3737",
    "sg:postcode":"L6T 4P7",
    "sg:province":"ON",
    "sg:tags":[
        "dealer",
        "rug"
    ],
    "wof:name":"Dixie Carpet & Furniture Distr",
    "wof:placetype":"venue"
},
  "geometry": {"coordinates":[-79.6959686279,43.6933822632],"type":"Point"}
}