{
  "type": "Feature",
  "properties": {
    "addr:full":"Bainsville ON K0C 1E0",
    "addr:postcode":"k0c 1e0",
    "iso:country":"CA",
    "sg:city":"Bainsville",
    "sg:classifiers":[
        {
            "category":"Professional",
            "subcategory":"Management & Consulting",
            "type":"Services"
        }
    ],
    "sg:phone":"+1 613 347 3466",
    "sg:postcode":"K0C 1E0",
    "sg:province":"ON",
    "sg:tags":[
        "agricultural",
        "consultant"
    ],
    "wof:name":"H Crochet Distribution Inc",
    "wof:placetype":"venue"
},
  "geometry": {"coordinates":[-74.42421,45.167557],"type":"Point"}
}