{
  "type": "Feature",
  "properties": {
    "addr:full":"13 Birmingham Ave Bowmanville ON L1C 4Z6",
    "addr:housenumber":"13",
    "addr:postcode":"l1c 4z6",
    "addr:street":"Birmingham Ave",
    "iso:country":"CA",
    "sg:address":"13 Birmingham Ave",
    "sg:city":"Bowmanville",
    "sg:classifiers":[
        {
            "category":"Education",
            "subcategory":"Special Training",
            "type":"Public Place"
        }
    ],
    "sg:phone":"+1 905 623 4641",
    "sg:postcode":"L1C 4Z6",
    "sg:province":"ON",
    "sg:tags":[
        "instruction",
        "driving"
    ],
    "wof:name":"Bowmanville Driving School",
    "wof:placetype":"venue"
},
  "geometry": {"coordinates":[-78.69565582280001,43.9282569885],"type":"Point"}
}