{
  "type": "Feature",
  "properties": {
    "addr:full":"2829 Dundas St W Toronto ON M6P 1Y6",
    "addr:housenumber":"2829",
    "addr:postcode":"m6p 1y6",
    "addr:street":"Dundas St W",
    "iso:country":"CA",
    "sg:address":"2829 Dundas St W",
    "sg:city":"Toronto",
    "sg:classifiers":[
        {
            "category":"Shopping",
            "type":"Retail Goods"
        }
    ],
    "sg:phone":"+1 416 766 6800",
    "sg:postcode":"M6P 1Y6",
    "sg:province":"ON",
    "sg:tags":[
        "orthopedic",
        "appliance"
    ],
    "wof:name":"Toronto Orthopedic Appliance",
    "wof:placetype":"venue"
},
  "geometry": {"coordinates":[-79.463684,43.665215],"type":"Point"}
}