{
  "type": "Feature",
  "properties": {
    "addr:full":"2275 Boul Industriel Chambly QC J3L 4W3",
    "addr:housenumber":"2275",
    "addr:postcode":"j3l 4w3",
    "addr:street":"Boul Industriel",
    "iso:country":"CA",
    "sg:address":"2275 Boul Industriel",
    "sg:city":"Chambly",
    "sg:classifiers":[
        {
            "category":"Building & Trades",
            "subcategory":"Cleaning & Sanitation",
            "type":"Services"
        }
    ],
    "sg:phone":"+1 450 658 5015",
    "sg:postcode":"J3L 4W3",
    "sg:province":"QC",
    "sg:tags":[
        "awning",
        "canopy"
    ],
    "wof:name":"J Brisbois Inc",
    "wof:placetype":"venue"
},
  "geometry": {"coordinates":[-73.274742,45.432861],"type":"Point"}
}