{
  "type": "Feature",
  "properties": {
    "iso:country":"CA",
    "sg:address":"2275 Boul Industriel",
    "sg:city":"Chambly",
    "sg:classifiers":[
        {
            "category":"Building & Trades",
            "subcategory":"Cleaning & Sanitation",
            "type":"Services"
        }
    ],
    "sg:phone":"+1 450 658 5015",
    "sg:postcode":"J3L 4W3",
    "sg:province":"QC",
    "sg:tags":[
        "awning",
        "canopy"
    ],
    "wof:name":"J Brisbois Inc",
    "wof:placetype":"venue"
},
  "geometry": {"coordinates":[-73.274742,45.432861],"type":"Point"}
}