{
  "type": "Feature",
  "properties": {
    "iso:country":"CA",
    "sg:address":"2877 Ch DE Chambly",
    "sg:city":"Longueuil",
    "sg:classifiers":[
        {
            "category":"Shopping",
            "subcategory":"Gifts & Souvenirs",
            "type":"Retail Goods"
        }
    ],
    "sg:phone":"+1 450 674 6353",
    "sg:postcode":"J4L 1M8",
    "sg:province":"QC",
    "sg:tags":[
        "shop"
    ],
    "wof:name":"Idee Cadeaux",
    "wof:placetype":"venue"
},
  "geometry": {"coordinates":[-73.4606628418,45.5208282471],"type":"Point"}
}