{
  "type": "Feature",
  "properties": {
    "iso:country":"CA",
    "sg:address":"1168 Dakota St",
    "sg:city":"Winnipeg",
    "sg:classifiers":[
        {
            "category":"Education",
            "subcategory":"Library",
            "type":"Public Place"
        }
    ],
    "sg:phone":"+1 204 986 4573",
    "sg:postcode":"R2N 3T8",
    "sg:province":"MB",
    "wof:name":"Louis Riel Branch Library",
    "wof:placetype":"venue"
},
  "geometry": {"coordinates":[-97.0994262695,49.8206520081],"type":"Point"}
}