{
  "type": "Feature",
  "properties": {
    "addr:full":"Etobicoke ON M9W 6W2",
    "addr:postcode":"m9w 6w2",
    "iso:country":"CA",
    "sg:city":"Etobicoke",
    "sg:classifiers":[
        {
            "category":"Manufacturing",
            "subcategory":"Motor Vehicles & Parts",
            "type":"Manufacturing & Wholesale Goods"
        }
    ],
    "sg:phone":"+1 416 674 7000",
    "sg:postcode":"M9W 6W2",
    "sg:province":"ON",
    "sg:tags":[
        "transmission"
    ],
    "wof:name":"Converter Man Ltd",
    "wof:placetype":"venue"
},
  "geometry": {"coordinates":[-79.58963775629999,43.7032852173],"type":"Point"}
}