{
  "type": "Feature",
  "properties": {
    "iso:country":"CA",
    "sg:address":"3063 Walker Rd",
    "sg:city":"Windsor",
    "sg:classifiers":[
        {
            "category":"Insurance",
            "subcategory":"Insurance Agent",
            "type":"Services"
        }
    ],
    "sg:phone":"+1 519 966 2600",
    "sg:postcode":"N8W 3R4",
    "sg:province":"ON",
    "wof:name":"Newton, Herb",
    "wof:placetype":"venue"
},
  "geometry": {"coordinates":[-82.983162,42.284683],"type":"Point"}
}