{
  "type": "Feature",
  "properties": {
    "iso:country":"CA",
    "sg:city":"Killarney",
    "sg:classifiers":[
        {
            "category":"Recreation",
            "type":"Entertainment"
        }
    ],
    "sg:phone":"+1 204 523 4862",
    "sg:postcode":"R0K 1G0",
    "sg:province":"MB",
    "sg:tags":[
        "center"
    ],
    "wof:name":"Killarney New Facility",
    "wof:placetype":"venue"
},
  "geometry": {"coordinates":[-99.66584777830001,49.180305481],"type":"Point"}
}