{
  "type": "Feature",
  "properties": {
    "addr:full":"1125 Boul Roland-Therrien Longueuil QC J4J 4V9",
    "addr:housenumber":"1125",
    "addr:postcode":"j4j 4v9",
    "addr:street":"Boul Roland-Therrien",
    "iso:country":"CA",
    "sg:address":"1125 Boul Roland-Therrien",
    "sg:city":"Longueuil",
    "sg:classifiers":[
        {
            "category":"Building & Trades",
            "subcategory":"Electrical",
            "type":"Services"
        }
    ],
    "sg:phone":"+1 450 670 7722",
    "sg:postcode":"J4J 4V9",
    "sg:province":"QC",
    "sg:tags":[
        "electric",
        "contractor"
    ],
    "wof:name":"Labillois Electrique Inc",
    "wof:placetype":"venue"
},
  "geometry": {"coordinates":[-73.485497,45.540096],"type":"Point"}
}