{
  "type": "Feature",
  "properties": {
    "addr:full":"4123 Wellington Rd Nanaimo BC V9T 2H2",
    "addr:housenumber":"4123",
    "addr:postcode":"v9t 2h2",
    "addr:street":"Wellington Rd",
    "iso:country":"CA",
    "sg:address":"4123 Wellington Rd",
    "sg:city":"Nanaimo",
    "sg:classifiers":[
        {
            "category":"Autos & Motor Vehicles",
            "subcategory":"Automobile Sales",
            "type":"Retail Goods"
        }
    ],
    "sg:phone":"+1 250 758 6585",
    "sg:postcode":"V9T 2H2",
    "sg:province":"BC",
    "sg:tags":[
        "car",
        "dealer"
    ],
    "wof:name":"Jim Pattison Hyundai",
    "wof:placetype":"venue"
},
  "geometry": {"coordinates":[-124.018638611,49.2067642212],"type":"Point"}
}