{
  "type": "Feature",
  "properties": {
    "iso:country":"CA",
    "sg:city":"Toronto",
    "sg:classifiers":[
        {
            "category":"Manufacturing",
            "subcategory":"Jewelry",
            "type":"Manufacturing & Wholesale Goods"
        }
    ],
    "sg:phone":"+1 416 363 4283",
    "sg:postcode":"M5B 1Y4",
    "sg:province":"ON",
    "sg:tags":[
        "product",
        "silversmith",
        "hand",
        "second",
        "goldsmith",
        "store"
    ],
    "wof:name":"Five Star Exchange",
    "wof:placetype":"venue"
},
  "geometry": {"coordinates":[-79.3760299683,43.6543121338],"type":"Point"}
}