{
  "type": "Feature",
  "properties": {
    "iso:country":"CA",
    "sg:address":"1602 Maier Rd",
    "sg:city":"Sicamous",
    "sg:classifiers":[
        {
            "category":"Retail",
            "subcategory":"Car Wash",
            "type":"Services"
        }
    ],
    "sg:phone":"+1 250 836 4460",
    "sg:postcode":"V0E 2V0",
    "sg:province":"BC",
    "sg:tags":[
        "polishing",
        "washing",
        "cleaning"
    ],
    "wof:name":"Sicamous Car & Truck Wash",
    "wof:placetype":"venue"
},
  "geometry": {"coordinates":[-118.95847320599999,50.8425140381],"type":"Point"}
}