{
  "type": "Feature",
  "properties": {
    "iso:country":"CA",
    "sg:address":"38 Albert St",
    "sg:city":"Stratford",
    "sg:classifiers":[
        {
            "category":"Real Estate",
            "subcategory":"Developer",
            "type":"Services"
        }
    ],
    "sg:phone":"+1 519 271 0250",
    "sg:postcode":"N5A 3K3",
    "sg:province":"ON",
    "sg:tags":[
        "cemetery"
    ],
    "wof:name":"Recreation Office",
    "wof:placetype":"venue"
},
  "geometry": {"coordinates":[-80.9812088013,43.3706588745],"type":"Point"}
}