{
  "type": "Feature",
  "properties": {
    "addr:full":"1801 Yukon Dr Stewart BC V0T 1W0",
    "addr:housenumber":"1801",
    "addr:postcode":"v0t 1w0",
    "addr:street":"Yukon Dr",
    "iso:country":"CA",
    "sg:address":"1801 Yukon Dr",
    "sg:city":"Stewart",
    "sg:classifiers":[
        {
            "category":"Professional",
            "subcategory":"Accounting & Tax Preparation",
            "type":"Services"
        }
    ],
    "sg:phone":"+1 250 636 9029",
    "sg:postcode":"V0T 1W0",
    "sg:province":"BC",
    "sg:tags":[
        "accountant"
    ],
    "wof:name":"B Belcher Accounting",
    "wof:placetype":"venue"
},
  "geometry": {"coordinates":[-129.98355100000001,55.947449],"type":"Point"}
}