{
  "type": "Feature",
  "properties": {
    "addr:full":"281 Rue King O Sherbrooke QC J1H 1R2",
    "addr:housenumber":"281",
    "addr:postcode":"j1h 1r2",
    "addr:street":"Rue King O",
    "iso:country":"CA",
    "sg:address":"281 Rue King O",
    "sg:city":"Sherbrooke",
    "sg:classifiers":[
        {
            "category":"Bars & Pubs",
            "type":"Food & Drink"
        }
    ],
    "sg:phone":"+1 819 564 8207",
    "sg:postcode":"J1H 1R2",
    "sg:province":"QC",
    "sg:tags":[
        "lounge",
        "cocktail"
    ],
    "wof:name":"Bar Rock & Bert Enr",
    "wof:placetype":"venue"
},
  "geometry": {"coordinates":[-71.882919,45.406532],"type":"Point"}
}