{
  "type": "Feature",
  "properties": {
    "addr:full":"Gloucester ON K1J 7T2",
    "addr:postcode":"k1j 7t2",
    "iso:country":"CA",
    "sg:city":"Gloucester",
    "sg:classifiers":[
        {
            "category":"Banks & Credit Unions",
            "subcategory":"Investment Brokerage",
            "type":"Services"
        }
    ],
    "sg:phone":"+1 613 742 8018",
    "sg:postcode":"K1J 7T2",
    "sg:province":"ON",
    "sg:tags":[
        "consultant",
        "planning",
        "financial"
    ],
    "wof:name":"Investors Group Financial Svc",
    "wof:placetype":"venue"
},
  "geometry": {"coordinates":[-75.63191999999999,45.421963],"type":"Point"}
}