{
  "type": "Feature",
  "properties": {
    "iso:country":"CA",
    "sg:address":"948 King Edward Ave W",
    "sg:city":"Vancouver",
    "sg:classifiers":[
        {
            "category":"Shopping",
            "subcategory":"Optical Goods",
            "type":"Retail Goods"
        }
    ],
    "sg:phone":"+1 604 730 7100",
    "sg:postcode":"V5Z 2E2",
    "sg:province":"BC",
    "sg:tags":[
        "contact",
        "lense",
        "optician"
    ],
    "wof:name":"Winthrope Contact Lenses",
    "wof:placetype":"venue"
},
  "geometry": {"coordinates":[-123.125969,49.24902],"type":"Point"}
}