{
  "type": "Feature",
  "properties": {
    "addr:full":"2776 Broadway E Vancouver BC V5M 1Y8",
    "addr:housenumber":"2776",
    "addr:postcode":"v5m 1y8",
    "addr:street":"Broadway E",
    "iso:country":"CA",
    "sg:address":"2776 Broadway E",
    "sg:city":"Vancouver",
    "sg:classifiers":[
        {
            "category":"Organizations",
            "subcategory":"Community Association",
            "type":"Services"
        }
    ],
    "sg:phone":"+1 604 255 2564",
    "sg:postcode":"V5M 1Y8",
    "sg:province":"BC",
    "sg:tags":[
        "club"
    ],
    "wof:name":"Vancouver Bridge Ctr Ltd",
    "wof:placetype":"venue"
},
  "geometry": {"coordinates":[-123.047737122,49.2618789673],"type":"Point"}
}