{
  "type": "Feature",
  "properties": {
    "addr:full":"62 Boul Valcartier Loretteville QC G2A 2M5",
    "addr:housenumber":"62",
    "addr:postcode":"g2a 2m5",
    "addr:street":"Boul Valcartier",
    "iso:country":"CA",
    "sg:address":"62 Boul Valcartier",
    "sg:city":"Loretteville",
    "sg:classifiers":[
        {
            "category":"Social Services",
            "type":"Services"
        }
    ],
    "sg:phone":"+1 418 843 3001",
    "sg:postcode":"G2A 2M5",
    "sg:province":"QC",
    "sg:tags":[
        "organization",
        "welfare"
    ],
    "wof:name":"Clsc DE LA Jacques-Cartier",
    "wof:placetype":"venue"
},
  "geometry": {"coordinates":[-71.35958100000001,46.85355],"type":"Point"}
}