{
  "type": "Feature",
  "properties": {
    "addr:full":"Isle-Aux-Coudres QC G0A 1X0",
    "addr:postcode":"g0a 1x0",
    "iso:country":"CA",
    "sg:city":"Isle-Aux-Coudres",
    "sg:classifiers":[
        {
            "category":"Travel",
            "subcategory":"Hotels & Motels",
            "type":"Entertainment"
        }
    ],
    "sg:phone":"+1 418 438 2734",
    "sg:postcode":"G0A 1X0",
    "sg:province":"QC",
    "sg:tags":[
        "inn"
    ],
    "wof:name":"Hotel Motel LA Roche Pleureuse",
    "wof:placetype":"venue"
},
  "geometry": {"coordinates":[-70.337563,47.411591],"type":"Point"}
}