{
  "type": "Feature",
  "properties": {
    "addr:full":"108 Elk Run Blvd Canmore AB T1W 1L1",
    "addr:housenumber":"108",
    "addr:postcode":"t1w 1l1",
    "addr:street":"Elk Run Blvd",
    "iso:country":"CA",
    "sg:address":"108 Elk Run Blvd",
    "sg:city":"Canmore",
    "sg:classifiers":[
        {
            "category":"Manufacturing",
            "subcategory":"Metals",
            "type":"Manufacturing & Wholesale Goods"
        }
    ],
    "sg:phone":"+1 403 678 5722",
    "sg:postcode":"T1W 1L1",
    "sg:province":"AB",
    "sg:tags":[
        "rental"
    ],
    "wof:name":"R Joy Rentals",
    "wof:placetype":"venue"
},
  "geometry": {"coordinates":[-115.32141900000001,51.078472],"type":"Point"}
}