{
  "type": "Feature",
  "properties": {
    "addr:full":"153 King St Burford ON N0E 1A0",
    "addr:housenumber":"153",
    "addr:postcode":"n0e 1a0",
    "addr:street":"King St",
    "iso:country":"CA",
    "sg:address":"153 King St",
    "sg:city":"Burford",
    "sg:classifiers":[
        {
            "category":"Retail",
            "subcategory":"Auto Repair",
            "type":"Services"
        }
    ],
    "sg:phone":"+1 519 449 2703",
    "sg:postcode":"N0E 1A0",
    "sg:province":"ON",
    "sg:tags":[
        "body",
        "automobile",
        "painting"
    ],
    "wof:name":"Sutor Auto Body",
    "wof:placetype":"venue"
},
  "geometry": {"coordinates":[-80.4325332642,43.1025733948],"type":"Point"}
}