{
  "type": "Feature",
  "properties": {
    "iso:country":"CA",
    "sg:address":"18 Lockwood Dr",
    "sg:city":"St Catharines",
    "sg:classifiers":[
        {
            "category":"Retail",
            "subcategory":"Portrait Studio",
            "type":"Services"
        }
    ],
    "sg:phone":"+1 905 935 8282",
    "sg:postcode":"L2M 4M4",
    "sg:province":"ON",
    "sg:tags":[
        "photographer"
    ],
    "wof:name":"Avalon Photography",
    "wof:placetype":"venue"
},
  "geometry": {"coordinates":[-79.214485,43.188454],"type":"Point"}
}