{
  "type": "Feature",
  "properties": {
    "iso:country":"CA",
    "sg:address":"58 Kenmount Rd",
    "sg:city":"St. John's",
    "sg:classifiers":[
        {
            "category":"Professional",
            "subcategory":"Management & Consulting",
            "type":"Services"
        }
    ],
    "sg:phone":"+1 709 576 7707",
    "sg:postcode":"A1B 1W2",
    "sg:province":"NL",
    "sg:tags":[
        "consultant",
        "telecommunication"
    ],
    "wof:name":"Cantel Regional Office",
    "wof:placetype":"venue"
},
  "geometry": {"coordinates":[-52.7544403076,47.5586853027],"type":"Point"}
}