{
  "type": "Feature",
  "properties": {
    "addr:full":"194 Robertson Rd # 20 Nepean ON K2H 9J5",
    "addr:housenumber":"194;20",
    "addr:postcode":"k2h 9j5",
    "addr:street":"Robertson Rd #",
    "iso:country":"CA",
    "sg:address":"194 Robertson Rd # 20",
    "sg:city":"Nepean",
    "sg:classifiers":[
        {
            "category":"Restaurant",
            "type":"Food & Drink"
        }
    ],
    "sg:phone":"+1 613 820 1700",
    "sg:postcode":"K2H 9J5",
    "sg:province":"ON",
    "wof:name":"Haveli Indian Restaurant",
    "wof:placetype":"venue"
},
  "geometry": {"coordinates":[-75.84137,45.318615],"type":"Point"}
}