{
  "type": "Feature",
  "properties": {
    "addr:full":"1664 Av Dollard Lasalle QC H8N 1T8",
    "addr:housenumber":"1664",
    "addr:postcode":"h8n 1t8",
    "addr:street":"Av Dollard",
    "iso:country":"CA",
    "sg:address":"1664 Av Dollard",
    "sg:city":"Lasalle",
    "sg:classifiers":[
        {
            "category":"Social Services",
            "type":"Services"
        }
    ],
    "sg:phone":"+1 514 364 5454",
    "sg:postcode":"H8N 1T8",
    "sg:province":"QC",
    "sg:tags":[
        "counseling"
    ],
    "wof:name":"Gold Telecommunications Inc",
    "wof:placetype":"venue"
},
  "geometry": {"coordinates":[-73.630424,45.428303],"type":"Point"}
}