{
  "type": "Feature",
  "properties": {
    "addr:full":"162 2nd Ave NW Swift Current SK S9H 0P2",
    "addr:housenumber":"162",
    "addr:postcode":"s9h 0p2",
    "addr:street":"2Nd Ave Nw",
    "iso:country":"CA",
    "sg:address":"162 2nd Ave NW",
    "sg:city":"Swift Current",
    "sg:classifiers":[
        {
            "category":"Retail",
            "subcategory":"Repair Shop",
            "type":"Services"
        }
    ],
    "sg:phone":"+1 306 773 1860",
    "sg:postcode":"S9H 0P2",
    "sg:province":"SK",
    "sg:tags":[
        "lock",
        "locksmith"
    ],
    "wof:name":"Gee Vee Lock & Key",
    "wof:placetype":"venue"
},
  "geometry": {"coordinates":[-107.802902222,50.2843589783],"type":"Point"}
}