{
  "type": "Feature",
  "properties": {
    "addr:full":"800 Wilson Ave North York ON M3K 1E5",
    "addr:housenumber":"800",
    "addr:postcode":"m3k 1e5",
    "addr:street":"Wilson Ave",
    "iso:country":"CA",
    "sg:address":"800 Wilson Ave",
    "sg:city":"North York",
    "sg:classifiers":[
        {
            "category":"Health Services",
            "subcategory":"Doctor",
            "type":"Services"
        }
    ],
    "sg:phone":"+1 416 633 2433",
    "sg:postcode":"M3K 1E5",
    "sg:province":"ON",
    "sg:tags":[
        "dentist"
    ],
    "wof:name":"Abacan, Ruth DDS",
    "wof:placetype":"venue"
},
  "geometry": {"coordinates":[-79.46584300000001,43.730995],"type":"Point"}
}