{
  "type": "Feature",
  "properties": {
    "addr:full":"Calgary AB T2E 7A2",
    "addr:postcode":"t2e 7a2",
    "iso:country":"CA",
    "sg:city":"Calgary",
    "sg:classifiers":[
        {
            "category":"Wholesale",
            "subcategory":"Office Equipment",
            "type":"Manufacturing & Wholesale Goods"
        }
    ],
    "sg:phone":"+1 403 543 3933",
    "sg:postcode":"T2E 7A2",
    "sg:province":"AB",
    "sg:tags":[
        "register",
        "cash",
        "supply"
    ],
    "wof:name":"Accurate Business Systems Ltd",
    "wof:placetype":"venue"
},
  "geometry": {"coordinates":[-114.011887,51.078457],"type":"Point"}
}