{
  "type": "Feature",
  "properties": {
    "addr:full":"290 Kempenfelt Dr Barrie ON L4M 1C5",
    "addr:housenumber":"290",
    "addr:postcode":"l4m 1c5",
    "addr:street":"Kempenfelt Dr",
    "iso:country":"CA",
    "sg:address":"290 Kempenfelt Dr",
    "sg:city":"Barrie",
    "sg:classifiers":[
        {
            "category":"Building & Trades",
            "subcategory":"Plumbing",
            "type":"Services"
        }
    ],
    "sg:phone":"+1 705 726 6024",
    "sg:postcode":"L4M 1C5",
    "sg:province":"ON",
    "sg:tags":[
        "contractor",
        "mechanical"
    ],
    "wof:name":"Carlmor Mechanical Ltd",
    "wof:placetype":"venue"
},
  "geometry": {"coordinates":[-79.6648101807,44.3941917419],"type":"Point"}
}