{
  "type": "Feature",
  "properties": {
    "addr:full":"68 Floral Pky North York ON M6L 2B9",
    "addr:housenumber":"68",
    "addr:postcode":"m6l 2b9",
    "addr:street":"Floral Pky",
    "iso:country":"CA",
    "sg:address":"68 Floral Pky",
    "sg:city":"North York",
    "sg:classifiers":[
        {
            "category":"Retail",
            "subcategory":"Animal Services",
            "type":"Services"
        }
    ],
    "sg:phone":"+1 416 241 4697",
    "sg:postcode":"M6L 2B9",
    "sg:province":"ON",
    "sg:tags":[
        "pet",
        "boarding",
        "sitting"
    ],
    "wof:name":"Parker Pet Care",
    "wof:placetype":"venue"
},
  "geometry": {"coordinates":[-79.47495269780001,43.7230682373],"type":"Point"}
}