{
  "type": "Feature",
  "properties": {
    "addr:full":"98 Rue Des Equipements Riviere-Du-Loup QC G5R 5W9",
    "addr:housenumber":"98",
    "addr:postcode":"g5r 5w9",
    "addr:street":"Rue Des Equipements Riviere-Du-Loup",
    "iso:country":"CA",
    "sg:address":"98 Rue Des Equipements",
    "sg:city":"Riviere-Du-Loup",
    "sg:classifiers":[
        {
            "category":"Manufacturing",
            "subcategory":"Petroleum Products",
            "type":"Manufacturing & Wholesale Goods"
        }
    ],
    "sg:phone":"+1 418 867 8577",
    "sg:postcode":"G5R 5W9",
    "sg:province":"QC",
    "sg:tags":[
        "environmental",
        "ecological",
        "oil"
    ],
    "wof:name":"Campor Inc",
    "wof:placetype":"venue"
},
  "geometry": {"coordinates":[-69.50569915769999,47.8366279602],"type":"Point"}
}