{
  "type": "Feature",
  "properties": {
    "addr:full":"318 Broadway Orangeville ON L9W 1L3",
    "addr:housenumber":"318",
    "addr:postcode":"l9w 1l3",
    "addr:street":"Broadway",
    "iso:country":"CA",
    "sg:address":"318 Broadway",
    "sg:city":"Orangeville",
    "sg:classifiers":[
        {
            "category":"Shopping",
            "subcategory":"Computers & Home Electronics",
            "type":"Retail Goods"
        }
    ],
    "sg:phone":"+1 519 941 3530",
    "sg:postcode":"L9W 1L3",
    "sg:province":"ON",
    "sg:tags":[
        "high",
        "fidelity",
        "stereophonic"
    ],
    "wof:name":"Channels International",
    "wof:placetype":"venue"
},
  "geometry": {"coordinates":[-80.113922,43.915478],"type":"Point"}
}