{
  "type": "Feature",
  "properties": {
    "addr:full":"5571 Hwy 9 St Andrews MB R1A 2X8",
    "addr:housenumber":"5571",
    "addr:postcode":"r1a 2x8",
    "addr:street":"Hwy 9",
    "iso:country":"CA",
    "sg:address":"5571 Hwy 9",
    "sg:city":"St Andrews",
    "sg:classifiers":[
        {
            "category":"Food & Beverages",
            "subcategory":"Groceries & Convenience Stores",
            "type":"Retail Goods"
        }
    ],
    "sg:phone":"+1 204 338 7538",
    "sg:postcode":"R1A 2X8",
    "sg:province":"MB",
    "sg:tags":[
        "grocer"
    ],
    "wof:name":"Harry's Foods North",
    "wof:placetype":"venue"
},
  "geometry": {"coordinates":[-96.940567,50.136848],"type":"Point"}
}