{
  "type": "Feature",
  "properties": {
    "addr:full":"31 Wilkin Rd NW Edmonton AB T6M 2K4",
    "addr:housenumber":"31",
    "addr:postcode":"t6m 2k4",
    "addr:street":"Wilkin Rd Nw",
    "iso:country":"CA",
    "sg:address":"31 Wilkin Rd NW",
    "sg:city":"Edmonton",
    "sg:classifiers":[
        {
            "category":"Professional",
            "subcategory":"Accounting & Tax Preparation",
            "type":"Services"
        }
    ],
    "sg:phone":"+1 780 413 0196",
    "sg:postcode":"T6M 2K4",
    "sg:province":"AB",
    "sg:tags":[
        "accountant"
    ],
    "wof:name":"Verbeke, Donald B",
    "wof:placetype":"venue"
},
  "geometry": {"coordinates":[-113.60689499999999,53.491058],"type":"Point"}
}