{
  "type": "Feature",
  "properties": {
    "addr:full":"34492 Blatchford Way Abbotsford BC V2S 5J8",
    "addr:postcode":"34492;v2s 5j8",
    "addr:street":"Blatchford Way",
    "iso:country":"CA",
    "sg:address":"34492 Blatchford Way",
    "sg:city":"Abbotsford",
    "sg:classifiers":[
        {
            "category":"Social Services",
            "type":"Services"
        }
    ],
    "sg:phone":"+1 604 556 2428",
    "sg:postcode":"V2S 5J8",
    "sg:province":"BC",
    "sg:tags":[
        "psychologist",
        "counselor"
    ],
    "wof:name":"Paragon Professional Group",
    "wof:placetype":"venue"
},
  "geometry": {"coordinates":[-122.26752471899999,49.0422554016],"type":"Point"}
}