{
  "type": "Feature",
  "properties": {
    "addr:full":"2138 Harris Cres Burlington ON L7R 1G4",
    "addr:housenumber":"2138",
    "addr:postcode":"l7r 1g4",
    "addr:street":"Harris Cres",
    "iso:country":"CA",
    "sg:address":"2138 Harris Cres",
    "sg:city":"Burlington",
    "sg:classifiers":[
        {
            "category":"Building & Trades",
            "subcategory":"Construction",
            "type":"Services"
        }
    ],
    "sg:phone":"+1 905 633 8195",
    "sg:postcode":"L7R 1G4",
    "sg:province":"ON",
    "sg:tags":[
        "roofing",
        "contractor"
    ],
    "wof:name":"Lakeshore Roofing",
    "wof:placetype":"venue"
},
  "geometry": {"coordinates":[-79.79212200000001,43.328484],"type":"Point"}
}