{
  "type": "Feature",
  "properties": {
    "addr:full":"127 Everett Dr # 7 Berens River MB R0B 0A0",
    "addr:housenumber":"127",
    "addr:postcode":"r0b 0a0",
    "addr:street":"Everett Dr # 7 Berens",
    "iso:country":"CA",
    "sg:address":"127 Everett Dr # 7",
    "sg:city":"Berens River",
    "sg:classifiers":[
        {
            "category":"Home & Garden",
            "subcategory":"Building Materials",
            "type":"Retail Goods"
        }
    ],
    "sg:phone":"+1 204 382 2016",
    "sg:postcode":"R0B 0A0",
    "sg:province":"MB",
    "wof:name":"Oshetoon Building Supplies",
    "wof:placetype":"venue"
},
  "geometry": {"coordinates":[-100.23764,50.029285],"type":"Point"}
}