{
  "type": "Feature",
  "properties": {
    "addr:full":"102 Main St Arborfield SK S0E 0A0",
    "addr:housenumber":"102",
    "addr:postcode":"s0e 0a0",
    "addr:street":"Main St",
    "iso:country":"CA",
    "sg:address":"102 Main St",
    "sg:city":"Arborfield",
    "sg:classifiers":[
        {
            "category":"Travel",
            "subcategory":"Hotels & Motels",
            "type":"Entertainment"
        }
    ],
    "sg:phone":"+1 306 769 8627",
    "sg:postcode":"S0E 0A0",
    "sg:province":"SK",
    "wof:name":"Royal Hotel",
    "wof:placetype":"venue"
},
  "geometry": {"coordinates":[-103.66078949,53.1037483215],"type":"Point"}
}