{
  "type": "Feature",
  "properties": {
    "addr:full":"Stewart Valley SK S0N 2P0",
    "addr:postcode":"s0n 2p0",
    "addr:street":"Stewart Valley",
    "iso:country":"CA",
    "sg:city":"Stewart Valley",
    "sg:classifiers":[
        {
            "category":"Freight",
            "type":"Transportation"
        }
    ],
    "sg:phone":"+1 306 773 7495",
    "sg:postcode":"S0N 2P0",
    "sg:province":"SK",
    "sg:tags":[
        "trucking"
    ],
    "wof:name":"Dinius Enterprises Inc",
    "wof:placetype":"venue"
},
  "geometry": {"coordinates":[-107.805183,50.594646],"type":"Point"}
}