{
  "type": "Feature",
  "properties": {
    "addr:full":"1083 Rangeview Rd Mississauga ON L5E 1H2",
    "addr:housenumber":"1083",
    "addr:postcode":"l5e 1h2",
    "addr:street":"Rangeview Rd",
    "iso:country":"CA",
    "sg:address":"1083 Rangeview Rd",
    "sg:city":"Mississauga",
    "sg:classifiers":[
        {
            "category":"Professional",
            "subcategory":"Computer Services",
            "type":"Services"
        }
    ],
    "sg:phone":"+1 905 278 7700",
    "sg:postcode":"L5E 1H2",
    "sg:province":"ON",
    "sg:tags":[
        "consultant",
        "management",
        "business"
    ],
    "wof:name":"Systemgroup Management",
    "wof:placetype":"venue"
},
  "geometry": {"coordinates":[-79.5556182861,43.576675415],"type":"Point"}
}