{
  "type": "Feature",
  "properties": {
    "addr:full":"4782 Wyandotte St E Windsor ON N8Y 1H7",
    "addr:housenumber":"4782",
    "addr:postcode":"n8y 1h7",
    "addr:street":"Wyandotte St E",
    "iso:country":"CA",
    "sg:address":"4782 Wyandotte St E",
    "sg:city":"Windsor",
    "sg:classifiers":[
        {
            "category":"Retail",
            "subcategory":"Repair Shop",
            "type":"Services"
        }
    ],
    "sg:phone":"+1 519 945 6323",
    "sg:postcode":"N8Y 1H7",
    "sg:province":"ON",
    "sg:tags":[
        "appliance"
    ],
    "wof:name":"Demers Appliance Svc",
    "wof:placetype":"venue"
},
  "geometry": {"coordinates":[-82.97951500000001,42.326607],"type":"Point"}
}