{
  "type": "Feature",
  "properties": {
    "addr:full":"479 Rue Saint-Alexis Montreal QC H2Y 2N7",
    "addr:housenumber":"479",
    "addr:postcode":"h2y 2n7",
    "addr:street":"Rue Saint-Alexis",
    "iso:country":"CA",
    "sg:address":"479 Rue Saint-Alexis",
    "sg:city":"Montreal",
    "sg:classifiers":[
        {
            "category":"Restaurant",
            "type":"Food & Drink"
        }
    ],
    "sg:phone":"+1 514 284 2195",
    "sg:postcode":"H2Y 2N7",
    "sg:province":"QC",
    "wof:name":"Restaurant Le Medi-Medi",
    "wof:placetype":"venue"
},
  "geometry": {"coordinates":[-73.557968,45.502628],"type":"Point"}
}