{
  "type": "Feature",
  "properties": {
    "iso:country":"CA",
    "sg:address":"1585 Mississauga Valley Blvd",
    "sg:city":"Mississauga",
    "sg:classifiers":[
        {
            "category":"Shopping",
            "subcategory":"Pharmacy",
            "type":"Retail Goods"
        }
    ],
    "sg:phone":"+1 905 272 1100",
    "sg:postcode":"L5A 3W9",
    "sg:province":"ON",
    "wof:name":"Shoppers Drug Mart",
    "wof:placetype":"venue"
},
  "geometry": {"coordinates":[-79.626923,43.591614],"type":"Point"}
}