{
  "type": "Feature",
  "properties": {
    "addr:full":"1410 Highway 56 Hannon ON L0R 1P0",
    "addr:housenumber":"1410",
    "addr:postcode":"l0r 1p0",
    "addr:street":"Highway 56",
    "iso:country":"CA",
    "sg:address":"1410 Highway 56",
    "sg:city":"Hannon",
    "sg:classifiers":[
        {
            "category":"Building & Trades",
            "subcategory":"Construction",
            "type":"Services"
        }
    ],
    "sg:phone":"+1 905 692 9447",
    "sg:postcode":"L0R 1P0",
    "sg:province":"ON",
    "sg:tags":[
        "equipment",
        "computer",
        "rooms"
    ],
    "wof:name":"Piller Canada",
    "wof:placetype":"venue"
},
  "geometry": {"coordinates":[-79.8377380371,43.1985397339],"type":"Point"}
}