{
  "type": "Feature",
  "properties": {
    "iso:country":"CA",
    "sg:address":"4371 Boul Des Grandes-Prairies",
    "sg:city":"Saint-Leonard",
    "sg:classifiers":[
        {
            "category":"Restaurant",
            "type":"Food & Drink"
        }
    ],
    "sg:phone":"+1 514 326 6080",
    "sg:postcode":"H1R 3G8",
    "sg:province":"QC",
    "sg:tags":[
        "caterer"
    ],
    "wof:name":"Buffet Santanna",
    "wof:placetype":"venue"
},
  "geometry": {"coordinates":[-73.623336792,45.5843505859],"type":"Point"}
}