{
  "type": "Feature",
  "properties": {
    "addr:full":"13743 119 Ave NW Edmonton AB T5L 2N5",
    "addr:housenumber":"13743",
    "addr:postcode":"t5l 2n5",
    "addr:street":"119 Ave Nw",
    "iso:country":"CA",
    "sg:address":"13743 119 Ave NW",
    "sg:city":"Edmonton",
    "sg:classifiers":[
        {
            "category":"Building & Trades",
            "subcategory":"Plumbing",
            "type":"Services"
        }
    ],
    "sg:phone":"+1 780 455 0406",
    "sg:postcode":"T5L 2N5",
    "sg:province":"AB",
    "sg:tags":[
        "contractor"
    ],
    "wof:name":"Plumbing Works",
    "wof:placetype":"venue"
},
  "geometry": {"coordinates":[-113.559883,53.571796],"type":"Point"}
}