{
  "type": "Feature",
  "properties": {
    "addr:full":"Saskatoon SK S7H 4Z8",
    "addr:postcode":"s7h 4z8",
    "iso:country":"CA",
    "sg:city":"Saskatoon",
    "sg:classifiers":[
        {
            "category":"Bars & Pubs",
            "type":"Food & Drink"
        }
    ],
    "sg:phone":"+1 306 477 7000",
    "sg:postcode":"S7H 4Z8",
    "sg:province":"SK",
    "sg:tags":[
        "club",
        "night"
    ],
    "wof:name":"Double Deuce Bar & Grill",
    "wof:placetype":"venue"
},
  "geometry": {"coordinates":[-106.597167969,52.1144866943],"type":"Point"}
}