{
  "type": "Feature",
  "properties": {
    "addr:full":"Victoria BC V8Z 3B8",
    "addr:postcode":"v8z 3b8",
    "iso:country":"CA",
    "sg:city":"Victoria",
    "sg:classifiers":[
        {
            "category":"Home & Garden",
            "subcategory":"Building Materials",
            "type":"Retail Goods"
        }
    ],
    "sg:phone":"+1 250 727 6811",
    "sg:postcode":"V8Z 3B8",
    "sg:province":"BC",
    "sg:tags":[
        "type",
        "truck"
    ],
    "wof:name":"Tedford Overhead Door Ltd",
    "wof:placetype":"venue"
},
  "geometry": {"coordinates":[-123.364517212,48.428314209],"type":"Point"}
}