{
  "type": "Feature",
  "properties": {
    "addr:full":"9156 Rue Boivin Lasalle QC H8R 2E7",
    "addr:housenumber":"9156",
    "addr:postcode":"h8r 2e7",
    "addr:street":"Rue Boivin",
    "iso:country":"CA",
    "sg:address":"9156 Rue Boivin",
    "sg:city":"Lasalle",
    "sg:classifiers":[
        {
            "category":"Building & Trades",
            "subcategory":"Construction",
            "type":"Services"
        }
    ],
    "sg:phone":"+1 514 366 3616",
    "sg:postcode":"H8R 2E7",
    "sg:province":"QC",
    "sg:tags":[
        "paving",
        "contractor"
    ],
    "wof:name":"Entretien Intl DE Batiments",
    "wof:placetype":"venue"
},
  "geometry": {"coordinates":[-73.6357269287,45.4227256775],"type":"Point"}
}