{
  "type": "Feature",
  "properties": {
    "addr:full":"Brandon MB R7A 0L2",
    "addr:postcode":"r7a 0l2",
    "iso:country":"CA",
    "sg:city":"Brandon",
    "sg:classifiers":[
        {
            "category":"Shopping",
            "subcategory":"Tobacco",
            "type":"Retail Goods"
        }
    ],
    "sg:phone":"+1 204 727 5284",
    "sg:postcode":"R7A 0L2",
    "sg:province":"MB",
    "sg:tags":[
        "cigarette",
        "cigar",
        "dealer"
    ],
    "wof:name":"United Cigar Stores",
    "wof:placetype":"venue"
},
  "geometry": {"coordinates":[-99.9488296509,49.8483467102],"type":"Point"}
}