{
  "type": "Feature",
  "properties": {
    "addr:full":"891 Rowntree Dairy Rd Woodbridge ON L4L 5W3",
    "addr:housenumber":"891",
    "addr:postcode":"l4l 5w3",
    "addr:street":"Rowntree Dairy Rd",
    "iso:country":"CA",
    "sg:address":"891 Rowntree Dairy Rd",
    "sg:city":"Woodbridge",
    "sg:classifiers":[
        {
            "category":"Manufacturing",
            "subcategory":"Tools & Machinery",
            "type":"Manufacturing & Wholesale Goods"
        }
    ],
    "sg:phone":"+1 905 264 0541",
    "sg:postcode":"L4L 5W3",
    "sg:province":"ON",
    "sg:tags":[
        "equipment",
        "baker"
    ],
    "wof:name":"Global Bakery & Food Equipment",
    "wof:placetype":"venue"
},
  "geometry": {"coordinates":[-79.57062500000001,43.781788],"type":"Point"}
}