{
  "type": "Feature",
  "properties": {
    "addr:full":"4400 32 St # 800 Vernon BC V1T 9H2",
    "addr:housenumber":"4400",
    "addr:postcode":"v1t 9h2",
    "addr:street":"32 St # 800",
    "iso:country":"CA",
    "sg:address":"4400 32 St # 800",
    "sg:city":"Vernon",
    "sg:classifiers":[
        {
            "category":"Restaurant",
            "type":"Food & Drink"
        }
    ],
    "sg:phone":"+1 250 545 7119",
    "sg:postcode":"V1T 9H2",
    "sg:province":"BC",
    "wof:name":"White Spot Restaurant",
    "wof:placetype":"venue"
},
  "geometry": {"coordinates":[-119.274216,50.276657],"type":"Point"}
}