{
  "type": "Feature",
  "properties": {
    "addr:full":"87 Toronto Rd Port Hope ON L1A 3S3",
    "addr:housenumber":"87",
    "addr:postcode":"l1a 3s3",
    "addr:street":"Toronto Rd",
    "iso:country":"CA",
    "sg:address":"87 Toronto Rd",
    "sg:city":"Port Hope",
    "sg:classifiers":[
        {
            "category":"Retail",
            "subcategory":"Auto Repair",
            "type":"Services"
        }
    ],
    "sg:phone":"+1 905 885 5327",
    "sg:postcode":"L1A 3S3",
    "sg:province":"ON",
    "sg:tags":[
        "repairing",
        "automobile"
    ],
    "wof:name":"Williams Auto Repair",
    "wof:placetype":"venue"
},
  "geometry": {"coordinates":[-78.315102,43.955219],"type":"Point"}
}