{
  "type": "Feature",
  "properties": {
    "iso:country":"CA",
    "sg:city":"Georgetown",
    "sg:classifiers":[
        {
            "category":"Manufacturing",
            "subcategory":"Tools & Machinery",
            "type":"Manufacturing & Wholesale Goods"
        }
    ],
    "sg:phone":"+1 905 877 8023",
    "sg:postcode":"L7G 4S1",
    "sg:province":"ON",
    "sg:tags":[
        "heating",
        "contractor"
    ],
    "wof:name":"Asbuilt Climatecare",
    "wof:placetype":"venue"
},
  "geometry": {"coordinates":[-79.9066238403,43.6549301147],"type":"Point"}
}