{
  "type": "Feature",
  "properties": {
    "addr:full":"Knowlton QC J0E 1V0",
    "addr:postcode":"j0e 1v0",
    "addr:street":"Knowlton",
    "iso:country":"CA",
    "sg:city":"Knowlton",
    "sg:classifiers":[
        {
            "category":"Shopping",
            "subcategory":"Computers & Home Electronics",
            "type":"Retail Goods"
        }
    ],
    "sg:phone":"+1 450 243 0895",
    "sg:postcode":"J0E 1V0",
    "sg:province":"QC",
    "sg:tags":[
        "equipment",
        "satellite",
        "system"
    ],
    "wof:name":"Installations Phil",
    "wof:placetype":"venue"
},
  "geometry": {"coordinates":[-72.52769499999999,45.214237],"type":"Point"}
}