{
  "type": "Feature",
  "properties": {
    "addr:full":"314 Edwards Ave The Pas MB R9A 1K6",
    "addr:housenumber":"314",
    "addr:postcode":"r9a 1k6",
    "addr:street":"Edwards Ave",
    "iso:country":"CA",
    "sg:address":"314 Edwards Ave",
    "sg:city":"The Pas",
    "sg:classifiers":[
        {
            "category":"Travel",
            "subcategory":"Travel Agent",
            "type":"Entertainment"
        }
    ],
    "sg:phone":"+1 204 623 3414",
    "sg:postcode":"R9A 1K6",
    "sg:province":"MB",
    "sg:tags":[
        "agency",
        "bureau"
    ],
    "wof:name":"Huskie Travel Svc Ltd",
    "wof:placetype":"venue"
},
  "geometry": {"coordinates":[-101.25118999999999,53.82349],"type":"Point"}
}