{
  "type": "Feature",
  "properties": {
    "addr:full":"5499 Line 34 Mitchell ON N0K 1N0",
    "addr:housenumber":"5499",
    "addr:postcode":"n0k 1n0",
    "addr:street":"Line 34",
    "iso:country":"CA",
    "sg:address":"5499 Line 34",
    "sg:city":"Mitchell",
    "sg:classifiers":[
        {
            "category":"Shopping",
            "subcategory":"Computers & Home Electronics",
            "type":"Retail Goods"
        }
    ],
    "sg:phone":"+1 519 348 4001",
    "sg:postcode":"N0K 1N0",
    "sg:province":"ON",
    "sg:tags":[
        "equipment",
        "television",
        "radio",
        "satellite"
    ],
    "wof:name":"Shorty's Electronics",
    "wof:placetype":"venue"
},
  "geometry": {"coordinates":[-81.168091,43.433311],"type":"Point"}
}