{
  "type": "Feature",
  "properties": {
    "iso:country":"CA",
    "sg:address":"123 Main St N",
    "sg:city":"Wadena",
    "sg:classifiers":[
        {
            "category":"Home & Garden",
            "subcategory":"Hardware",
            "type":"Retail Goods"
        }
    ],
    "sg:phone":"+1 306 338 2343",
    "sg:postcode":"S0A 4J0",
    "sg:province":"SK",
    "wof:name":"Wadena CO-OP Hardware",
    "wof:placetype":"venue"
},
  "geometry": {"coordinates":[-103.801643372,51.9455299377],"type":"Point"}
}