{
  "type": "Feature",
  "properties": {
    "addr:full":"7071 Bayers Rd Halifax NS B3L 2C2",
    "addr:postcode":"7071;b3l 2c2",
    "addr:street":"Bayers Rd",
    "iso:country":"CA",
    "sg:address":"7071 Bayers Rd",
    "sg:city":"Halifax",
    "sg:classifiers":[
        {
            "category":"Education",
            "subcategory":"Special Training",
            "type":"Public Place"
        }
    ],
    "sg:phone":"+1 902 429 3636",
    "sg:postcode":"B3L 2C2",
    "sg:province":"NS",
    "sg:tags":[
        "school",
        "language"
    ],
    "wof:name":"International Language Inst",
    "wof:placetype":"venue"
},
  "geometry": {"coordinates":[-63.62727,44.653709],"type":"Point"}
}