{
  "type": "Feature",
  "properties": {
    "addr:full":"1 Mount Bernard Ave Corner Brook NL A2H 6Y5",
    "addr:housenumber":"1",
    "addr:postcode":"a2h 6y5",
    "addr:street":"Mount Bernard Ave",
    "iso:country":"CA",
    "sg:address":"1 Mount Bernard Ave",
    "sg:city":"Corner Brook",
    "sg:classifiers":[
        {
            "category":"Real Estate",
            "subcategory":"Real Estate Operator",
            "type":"Services"
        }
    ],
    "sg:phone":"+1 709 634 2626",
    "sg:postcode":"A2H 6Y5",
    "sg:province":"NL",
    "sg:tags":[
        "mall",
        "shopping",
        "center"
    ],
    "wof:name":"Valley Mall Admin Office",
    "wof:placetype":"venue"
},
  "geometry": {"coordinates":[-57.949966,48.95116],"type":"Point"}
}