{
  "type": "Feature",
  "properties": {
    "addr:full":"80 Behnke Cres Pembroke ON K8A 6W7",
    "addr:housenumber":"80",
    "addr:postcode":"k8a 6w7",
    "addr:street":"Behnke Cres",
    "iso:country":"CA",
    "sg:address":"80 Behnke Cres",
    "sg:city":"Pembroke",
    "sg:classifiers":[
        {
            "category":"Manufacturing",
            "subcategory":"Lumber",
            "type":"Manufacturing & Wholesale Goods"
        }
    ],
    "sg:phone":"+1 613 687 0727",
    "sg:postcode":"K8A 6W7",
    "sg:province":"ON",
    "sg:tags":[
        "company",
        "logging"
    ],
    "wof:name":"Behnke Logging & Trucking Ltd",
    "wof:placetype":"venue"
},
  "geometry": {"coordinates":[-77.1122131348,45.8264808655],"type":"Point"}
}