{
  "type": "Feature",
  "properties": {
    "addr:full":"816 Boul Saint-Joseph Roberval QC G8H 2L5",
    "addr:housenumber":"816",
    "addr:postcode":"g8h 2l5",
    "addr:street":"Boul Saint-Joseph",
    "iso:country":"CA",
    "sg:address":"816 Boul Saint-Joseph",
    "sg:city":"Roberval",
    "sg:classifiers":[
        {
            "category":"Retail",
            "subcategory":"Funeral Services",
            "type":"Services"
        }
    ],
    "sg:phone":"+1 418 275 0375",
    "sg:postcode":"G8H 2L5",
    "sg:province":"QC",
    "sg:tags":[
        "director"
    ],
    "wof:name":"Maison Funeraire Harvey Ltee",
    "wof:placetype":"venue"
},
  "geometry": {"coordinates":[-72.22113,48.517258],"type":"Point"}
}