{
  "type": "Feature",
  "properties": {
    "addr:full":"22 Price St Petitcodiac NB E4Z 4R3",
    "addr:housenumber":"22",
    "addr:postcode":"e4z 4r3",
    "addr:street":"Price St",
    "iso:country":"CA",
    "sg:address":"22 Price St",
    "sg:city":"Petitcodiac",
    "sg:classifiers":[
        {
            "category":"Organizations",
            "subcategory":"Religious Organization",
            "type":"Services"
        }
    ],
    "sg:phone":"+1 506 756 8138",
    "sg:postcode":"E4Z 4R3",
    "sg:province":"NB",
    "sg:tags":[
        "church"
    ],
    "wof:name":"St James United Church",
    "wof:placetype":"venue"
},
  "geometry": {"coordinates":[-65.171875,45.929787],"type":"Point"}
}