{
  "type": "Feature",
  "properties": {
    "iso:country":"CA",
    "sg:address":"3109 Edgemont Blvd",
    "sg:city":"North Vancouver",
    "sg:classifiers":[
        {
            "category":"Food & Beverages",
            "subcategory":"Meat & Fish",
            "type":"Retail Goods"
        }
    ],
    "sg:phone":"+1 604 988 6328",
    "sg:postcode":"V7R 2N7",
    "sg:province":"BC",
    "wof:name":"Edgemont Gourmet Meats",
    "wof:placetype":"venue"
},
  "geometry": {"coordinates":[-123.102234,49.337563],"type":"Point"}
}