{
  "type": "Feature",
  "properties": {
    "addr:full":"738 Rue Shefford Bromont QC J2L 1C1",
    "addr:housenumber":"738",
    "addr:postcode":"j2l 1c1",
    "addr:street":"Rue Shefford",
    "iso:country":"CA",
    "sg:address":"738 Rue Shefford",
    "sg:city":"Bromont",
    "sg:classifiers":[
        {
            "category":"Real Estate",
            "subcategory":"Real Estate Agent",
            "type":"Services"
        }
    ],
    "sg:phone":"+1 450 534 3600",
    "sg:postcode":"J2L 1C1",
    "sg:province":"QC",
    "wof:name":"Royal Le Page Action",
    "wof:placetype":"venue"
},
  "geometry": {"coordinates":[-72.65587600000001,45.318371],"type":"Point"}
}