{
  "type": "Feature",
  "properties": {
    "addr:full":"99 Cornish Ave Winnipeg MB R3C 1A2",
    "addr:housenumber":"99",
    "addr:postcode":"r3c 1a2",
    "addr:street":"Cornish Ave",
    "iso:country":"CA",
    "sg:address":"99 Cornish Ave",
    "sg:city":"Winnipeg",
    "sg:classifiers":[
        {
            "category":"Health Services",
            "subcategory":"Hospital",
            "type":"Services"
        }
    ],
    "sg:phone":"+1 204 788 8200",
    "sg:postcode":"R3C 1A2",
    "sg:province":"MB",
    "wof:name":"Misericordia Health Ctr",
    "wof:placetype":"venue"
},
  "geometry": {"coordinates":[-97.160454,49.878895],"type":"Point"}
}