{
  "type": "Feature",
  "properties": {
    "addr:full":"16L29 Lakeshore Rd Wainfleet ON L0S 1V0",
    "addr:housenumber":"16l29",
    "addr:postcode":"l0s 1v0",
    "addr:street":"Lakeshore Rd",
    "iso:country":"CA",
    "sg:address":"16L29 Lakeshore Rd",
    "sg:city":"Wainfleet",
    "sg:classifiers":[
        {
            "category":"Building & Trades",
            "subcategory":"Construction",
            "type":"Services"
        }
    ],
    "sg:phone":"+1 905 899 1700",
    "sg:postcode":"L0S 1V0",
    "sg:province":"ON",
    "sg:tags":[
        "masonry",
        "contractor"
    ],
    "wof:name":"Mann Masonry Ltd",
    "wof:placetype":"venue"
},
  "geometry": {"coordinates":[-79.280266,42.873859],"type":"Point"}
}