{
  "type": "Feature",
  "properties": {
    "iso:country":"CA",
    "sg:address":"3 Marsh Lane",
    "sg:city":"Ajax",
    "sg:classifiers":[
        {
            "category":"Building & Trades",
            "subcategory":"Cleaning & Sanitation",
            "type":"Services"
        }
    ],
    "sg:phone":"+1 905 619 2690",
    "sg:postcode":"L1T 3W4",
    "sg:province":"ON",
    "sg:tags":[
        "janitor"
    ],
    "wof:name":"Immaculate Building Mtnce",
    "wof:placetype":"venue"
},
  "geometry": {"coordinates":[-79.055824,43.874084],"type":"Point"}
}