{
  "type": "Feature",
  "properties": {
    "addr:full":"2676 Gladys Ave Abbotsford BC V2S 3X8",
    "addr:housenumber":"2676",
    "addr:postcode":"v2s 3x8",
    "addr:street":"Gladys Ave",
    "iso:country":"CA",
    "sg:address":"2676 Gladys Ave",
    "sg:city":"Abbotsford",
    "sg:classifiers":[
        {
            "category":"Social Services",
            "subcategory":"Job Training",
            "type":"Services"
        }
    ],
    "sg:phone":"+1 604 850 1235",
    "sg:postcode":"V2S 3X8",
    "sg:province":"BC",
    "sg:tags":[
        "rehabilitation"
    ],
    "wof:name":"Abby House",
    "wof:placetype":"venue"
},
  "geometry": {"coordinates":[-122.287476,49.050819],"type":"Point"}
}