{
  "type": "Feature",
  "properties": {
    "iso:country":"CA",
    "sg:address":"3200 Rue Dandurand",
    "sg:city":"Montreal",
    "sg:classifiers":[
        {
            "category":"Retail",
            "subcategory":"Self-service Laundry",
            "type":"Services"
        }
    ],
    "sg:phone":"+1 514 727 1305",
    "sg:postcode":"H1Y 1V5",
    "sg:province":"QC",
    "wof:name":"Buanderette Martin",
    "wof:placetype":"venue"
},
  "geometry": {"coordinates":[-73.5765,45.551308],"type":"Point"}
}