{
  "type": "Feature",
  "properties": {
    "addr:full":"1411 16th St E Owen Sound ON N4K 1Z4",
    "addr:housenumber":"1411",
    "addr:postcode":"n4k 1z4",
    "addr:street":"16Th St E",
    "iso:country":"CA",
    "sg:address":"1411 16th St E",
    "sg:city":"Owen Sound",
    "sg:classifiers":[
        {
            "category":"Restaurant",
            "type":"Food & Drink"
        }
    ],
    "sg:phone":"+1 519 371 2979",
    "sg:postcode":"N4K 1Z4",
    "sg:province":"ON",
    "wof:name":"Wendy's",
    "wof:placetype":"venue"
},
  "geometry": {"coordinates":[-80.92134900000001,44.574066],"type":"Point"}
}