{
  "type": "Feature",
  "properties": {
    "addr:full":"802 9 Hwy S Drumheller AB T0J 0Y0",
    "addr:housenumber":"802",
    "addr:postcode":"t0j 0y0",
    "addr:street":"9 Hwy S Drumheller",
    "iso:country":"CA",
    "sg:address":"802 9 Hwy S",
    "sg:city":"Drumheller",
    "sg:classifiers":[
        {
            "category":"Building & Trades",
            "subcategory":"Construction",
            "type":"Services"
        }
    ],
    "sg:phone":"+1 403 823 5535",
    "sg:postcode":"T0J 0Y0",
    "sg:province":"AB",
    "sg:tags":[
        "glass"
    ],
    "wof:name":"Badlands Glass & Windshield",
    "wof:placetype":"venue"
},
  "geometry": {"coordinates":[-112.700515747,51.4560127258],"type":"Point"}
}