{
  "type": "Feature",
  "properties": {
    "iso:country":"CA",
    "sg:address":"5500 Boul DE LA Rive-Sud # 235",
    "sg:city":"Levis",
    "sg:classifiers":[
        {
            "category":"Wholesale",
            "subcategory":"Office Equipment",
            "type":"Manufacturing & Wholesale Goods"
        }
    ],
    "sg:phone":"+1 418 833 5062",
    "sg:postcode":"G6V 4Z2",
    "sg:province":"QC",
    "sg:tags":[
        "accounting",
        "bookkeeping",
        "system"
    ],
    "wof:name":"Vallieres, Pascale",
    "wof:placetype":"venue"
},
  "geometry": {"coordinates":[-71.17724609379999,46.7948722839],"type":"Point"}
}