{
  "type": "Feature",
  "properties": {
    "addr:full":"116 Rue Prudent-Cloutier Mont-Saint-Pierre QC G0E 1V0",
    "addr:housenumber":"116",
    "addr:postcode":"g0e 1v0",
    "addr:street":"Rue Prudent-Cloutier",
    "iso:country":"CA",
    "sg:address":"116 Rue Prudent-Cloutier",
    "sg:city":"Mont-Saint-Pierre",
    "sg:classifiers":[
        {
            "category":"Government",
            "subcategory":"Office",
            "type":"Public Place"
        }
    ],
    "sg:phone":"+1 418 797 5214",
    "sg:postcode":"G0E 1V0",
    "sg:province":"QC",
    "wof:name":"Reserve Faunique Des Chics",
    "wof:placetype":"venue"
},
  "geometry": {"coordinates":[-65.7970199585,49.2237472534],"type":"Point"}
}