{
  "type": "Feature",
  "properties": {
    "addr:full":"254 Rue Richelieu Saint-Jean-Sur-Richelieu QC J3B 6X8",
    "addr:housenumber":"254",
    "addr:postcode":"j3b 6x8",
    "addr:street":"Rue Richelieu",
    "iso:country":"CA",
    "sg:address":"254 Rue Richelieu",
    "sg:city":"Saint-Jean-Sur-Richelieu",
    "sg:classifiers":[
        {
            "category":"Shopping",
            "subcategory":"Clothing, Apparel, & Fashions",
            "type":"Retail Goods"
        }
    ],
    "sg:phone":"+1 450 347 4757",
    "sg:postcode":"J3B 6X8",
    "sg:province":"QC",
    "sg:tags":[
        "boutique",
        "furnishing"
    ],
    "wof:name":"Roger Galipeau Inc",
    "wof:placetype":"venue"
},
  "geometry": {"coordinates":[-73.250923,45.307266],"type":"Point"}
}