{
  "type": "Feature",
  "properties": {
    "addr:full":"Uxbridge ON L9P 1R2",
    "addr:postcode":"l9p 1r2",
    "iso:country":"CA",
    "sg:city":"Uxbridge",
    "sg:classifiers":[
        {
            "category":"Building & Trades",
            "subcategory":"Construction",
            "type":"Services"
        }
    ],
    "sg:phone":"+1 905 852 3915",
    "sg:postcode":"L9P 1R2",
    "sg:province":"ON",
    "sg:tags":[
        "masonry",
        "contractor"
    ],
    "wof:name":"Harper Masonry",
    "wof:placetype":"venue"
},
  "geometry": {"coordinates":[-79.123863,44.106167],"type":"Point"}
}