{
  "type": "Feature",
  "properties": {
    "addr:full":"5383 Yonge St North York ON M2N 5R6",
    "addr:housenumber":"5383",
    "addr:postcode":"m2n 5r6",
    "addr:street":"Yonge St",
    "iso:country":"CA",
    "sg:address":"5383 Yonge St",
    "sg:city":"North York",
    "sg:classifiers":[
        {
            "category":"Food & Beverages",
            "subcategory":"Bakery",
            "type":"Retail Goods"
        }
    ],
    "sg:phone":"+1 416 229 1581",
    "sg:postcode":"M2N 5R6",
    "sg:province":"ON",
    "sg:tags":[
        "shop",
        "doughnut",
        "coffee"
    ],
    "wof:name":"Tim Hortons",
    "wof:placetype":"venue"
},
  "geometry": {"coordinates":[-79.4140777588,43.7747268677],"type":"Point"}
}