{
  "type": "Feature",
  "properties": {
    "addr:full":"Binbrook ON L0R 1C0",
    "addr:postcode":"l0r 1c0",
    "iso:country":"CA",
    "sg:city":"Binbrook",
    "sg:phone":"+1 905 692 4003",
    "sg:postcode":"L0R 1C0",
    "sg:province":"ON",
    "sg:tags":[
        "agricultural",
        "product",
        "hall",
        "auditorium"
    ],
    "wof:name":"Binbrook Agricultural Society",
    "wof:placetype":"venue"
},
  "geometry": {"coordinates":[-79.80384100000001,43.123165],"type":"Point"}
}