{
  "type": "Feature",
  "properties": {
    "iso:country":"CA",
    "sg:address":"76 Place Livingston",
    "sg:city":"Sept-Iles",
    "sg:classifiers":[
        {
            "category":"Building & Trades",
            "subcategory":"Construction",
            "type":"Services"
        }
    ],
    "sg:phone":"+1 418 968 3569",
    "sg:postcode":"G4R 4C1",
    "sg:province":"QC",
    "sg:tags":[
        "resurfacing",
        "laying",
        "refinishing",
        "floor"
    ],
    "wof:name":"Signe St-Laurent",
    "wof:placetype":"venue"
},
  "geometry": {"coordinates":[-66.3935241699,50.2172546387],"type":"Point"}
}