{
  "type": "Feature",
  "properties": {
    "addr:full":"685 Plains Rd E Burlington ON L7T 2E8",
    "addr:housenumber":"685",
    "addr:postcode":"l7t 2e8",
    "addr:street":"Plains Rd E",
    "iso:country":"CA",
    "sg:address":"685 Plains Rd E",
    "sg:city":"Burlington",
    "sg:classifiers":[
        {
            "category":"Health Services",
            "subcategory":"Doctor",
            "type":"Services"
        }
    ],
    "sg:phone":"+1 905 681 9200",
    "sg:postcode":"L7T 2E8",
    "sg:province":"ON",
    "sg:tags":[
        "physician",
        "surgeon"
    ],
    "wof:name":"Pracsovics, Anthony MD",
    "wof:placetype":"venue"
},
  "geometry": {"coordinates":[-79.83001708979999,43.3239212036],"type":"Point"}
}