{
  "type": "Feature",
  "properties": {
    "addr:full":"Victoriaville QC G6S 1C1",
    "addr:postcode":"g6s 1c1",
    "iso:country":"CA",
    "sg:city":"Victoriaville",
    "sg:classifiers":[
        {
            "category":"Shopping",
            "subcategory":"Clothing, Apparel, & Fashions",
            "type":"Retail Goods"
        }
    ],
    "sg:phone":"+1 819 357 3239",
    "sg:postcode":"G6S 1C1",
    "sg:province":"QC",
    "wof:name":"Boutique Marise Petite",
    "wof:placetype":"venue"
},
  "geometry": {"coordinates":[-71.92882537840001,46.0626182556],"type":"Point"}
}