{
  "type": "Feature",
  "properties": {
    "addr:full":"RR 8 STN Main Owen Sound ON N4K 5W4",
    "addr:postcode":"n4k 5w4",
    "addr:street":"Rr 8 Stn Main",
    "iso:country":"CA",
    "sg:address":"RR 8 STN Main",
    "sg:city":"Owen Sound",
    "sg:classifiers":[
        {
            "category":"Organizations",
            "subcategory":"Religious Organization",
            "type":"Services"
        }
    ],
    "sg:phone":"+1 519 376 3516",
    "sg:postcode":"N4K 5W4",
    "sg:province":"ON",
    "wof:name":"Word of Life Fellowship Canada",
    "wof:placetype":"venue"
},
  "geometry": {"coordinates":[-80.942604,44.564877],"type":"Point"}
}