{
  "type": "Feature",
  "properties": {
    "addr:full":"Barr Rd Desbarats ON P0R 1E0",
    "addr:postcode":"p0r 1e0",
    "addr:street":"Barr Rd",
    "iso:country":"CA",
    "sg:address":"Barr Rd",
    "sg:city":"Desbarats",
    "sg:classifiers":[
        {
            "category":"Government",
            "subcategory":"Office",
            "type":"Public Place"
        }
    ],
    "sg:phone":"+1 705 782 6341",
    "sg:postcode":"P0R 1E0",
    "sg:province":"ON",
    "sg:tags":[
        "village"
    ],
    "wof:name":"Tarbutt Municipal Garage",
    "wof:placetype":"venue"
},
  "geometry": {"coordinates":[-83.927605,46.342766],"type":"Point"}
}