{
  "type": "Feature",
  "properties": {
    "addr:full":"1904 Davenport Rd Toronto ON M6N 1B7",
    "addr:housenumber":"1904",
    "addr:postcode":"m6n 1b7",
    "addr:street":"Davenport Rd",
    "iso:country":"CA",
    "sg:address":"1904 Davenport Rd",
    "sg:city":"Toronto",
    "sg:classifiers":[
        {
            "category":"Organizations",
            "subcategory":"Religious Organization",
            "type":"Services"
        }
    ],
    "sg:phone":"+1 416 656 1606",
    "sg:postcode":"M6N 1B7",
    "sg:province":"ON",
    "sg:tags":[
        "church"
    ],
    "wof:name":"Davenport Perth Community Chr",
    "wof:placetype":"venue"
},
  "geometry": {"coordinates":[-79.454742,43.670605],"type":"Point"}
}