{
  "type": "Feature",
  "properties": {
    "addr:full":"390 Bank St Ottawa ON K2P 1Y5",
    "addr:housenumber":"390",
    "addr:postcode":"k2p 1y5",
    "addr:street":"Bank St",
    "iso:country":"CA",
    "sg:address":"390 Bank St",
    "sg:city":"Ottawa",
    "sg:classifiers":[
        {
            "category":"Restaurant",
            "type":"Food & Drink"
        }
    ],
    "sg:phone":"+1 613 563 4700",
    "sg:postcode":"K2P 1Y5",
    "sg:province":"ON",
    "wof:name":"James Street Feed CO",
    "wof:placetype":"venue"
},
  "geometry": {"coordinates":[-75.694733,45.41325],"type":"Point"}
}