{
  "type": "Feature",
  "properties": {
    "addr:full":"1351 Hwy 129 Chapleau ON P0M 1K0",
    "addr:housenumber":"1351",
    "addr:postcode":"p0m 1k0",
    "addr:street":"Hwy 129",
    "iso:country":"CA",
    "sg:address":"1351 Hwy 129",
    "sg:city":"Chapleau",
    "sg:classifiers":[
        {
            "category":"Utilities",
            "subcategory":"Refuse",
            "type":"Services"
        }
    ],
    "sg:phone":"+1 705 864 0351",
    "sg:postcode":"P0M 1K0",
    "sg:province":"ON",
    "sg:tags":[
        "landfill"
    ],
    "wof:name":"Chapleau Municipal Landfill",
    "wof:placetype":"venue"
},
  "geometry": {"coordinates":[-83.398438,47.819649],"type":"Point"}
}