{
  "type": "Feature",
  "properties": {
    "addr:full":"Vernon BC V1T 9R1",
    "addr:postcode":"v1t 9r1",
    "iso:country":"CA",
    "sg:city":"Vernon",
    "sg:classifiers":[
        {
            "category":"Restaurant",
            "type":"Food & Drink"
        }
    ],
    "sg:phone":"+1 250 260 1182",
    "sg:postcode":"V1T 9R1",
    "sg:province":"BC",
    "wof:name":"Mc Donald's",
    "wof:placetype":"venue"
},
  "geometry": {"coordinates":[-119.30574,50.256149],"type":"Point"}
}