{
  "type": "Feature",
  "properties": {
    "addr:full":"1856 Arlington St Winnipeg MB R2X 1W6",
    "addr:housenumber":"1856",
    "addr:postcode":"r2x 1w6",
    "addr:street":"Arlington St",
    "iso:country":"CA",
    "sg:address":"1856 Arlington St",
    "sg:city":"Winnipeg",
    "sg:classifiers":[
        {
            "category":"Retail",
            "subcategory":"Animal Services",
            "type":"Services"
        }
    ],
    "sg:phone":"+1 204 632 4689",
    "sg:postcode":"R2X 1W6",
    "sg:province":"MB",
    "sg:tags":[
        "pet",
        "grooming",
        "washing"
    ],
    "wof:name":"Val's Magic Groom",
    "wof:placetype":"venue"
},
  "geometry": {"coordinates":[-97.1456985474,49.9336662292],"type":"Point"}
}