{
  "type": "Feature",
  "properties": {
    "addr:full":"75 Elgin St W Arnprior ON K7S 3T9",
    "addr:housenumber":"75",
    "addr:postcode":"k7s 3t9",
    "addr:street":"Elgin St W",
    "iso:country":"CA",
    "sg:address":"75 Elgin St W",
    "sg:city":"Arnprior",
    "sg:classifiers":[
        {
            "category":"Banks & Credit Unions",
            "subcategory":"Bank",
            "type":"Services"
        }
    ],
    "sg:phone":"+1 613 623 4248",
    "sg:postcode":"K7S 3T9",
    "sg:province":"ON",
    "wof:name":"Cibc",
    "wof:placetype":"venue"
},
  "geometry": {"coordinates":[-76.35516357420001,45.4339981079],"type":"Point"}
}