{
  "type": "Feature",
  "properties": {
    "iso:country":"CA",
    "sg:address":"22 Roseberry St",
    "sg:city":"Campbellton",
    "sg:classifiers":[
        {
            "category":"Retail",
            "subcategory":"Car Wash",
            "type":"Services"
        }
    ],
    "sg:phone":"+1 506 789 1985",
    "sg:postcode":"E3N 2G2",
    "sg:province":"NB",
    "sg:tags":[
        "polishing",
        "washing"
    ],
    "wof:name":"Shine Factory",
    "wof:placetype":"venue"
},
  "geometry": {"coordinates":[-66.674492,48.004902],"type":"Point"}
}