{
  "type": "Feature",
  "properties": {
    "addr:full":"67 Rue Saint-Jean-Baptiste E Montmagny QC G5V 1J9",
    "addr:housenumber":"67",
    "addr:postcode":"g5v 1j9",
    "addr:street":"Rue Saint-Jean-Baptiste E",
    "iso:country":"CA",
    "sg:address":"67 Rue Saint-Jean-Baptiste E",
    "sg:city":"Montmagny",
    "sg:classifiers":[
        {
            "category":"Shopping",
            "subcategory":"Computers & Home Electronics",
            "type":"Retail Goods"
        }
    ],
    "sg:phone":"+1 418 248 0074",
    "sg:postcode":"G5V 1J9",
    "sg:province":"QC",
    "sg:tags":[
        "equipment",
        "dealer"
    ],
    "wof:name":"Microplus Cote-Sud",
    "wof:placetype":"venue"
},
  "geometry": {"coordinates":[-70.55969238279999,46.9799003601],"type":"Point"}
}