{
  "type": "Feature",
  "properties": {
    "addr:full":"1654 Rue Alfred L'Ancienne-Lorette QC G2E 3J1",
    "addr:housenumber":"1654",
    "addr:postcode":"g2e 3j1",
    "addr:street":"Rue Alfred",
    "iso:country":"CA",
    "sg:address":"1654 Rue Alfred",
    "sg:city":"L'Ancienne-Lorette",
    "sg:classifiers":[
        {
            "category":"Building & Trades",
            "subcategory":"Plumbing",
            "type":"Services"
        }
    ],
    "sg:phone":"+1 418 871 7375",
    "sg:postcode":"G2E 3J1",
    "sg:province":"QC",
    "sg:tags":[
        "contractor"
    ],
    "wof:name":"Services D Drolet",
    "wof:placetype":"venue"
},
  "geometry": {"coordinates":[-71.36494399999999,46.800938],"type":"Point"}
}