{
  "type": "Feature",
  "properties": {
    "iso:country":"CA",
    "sg:address":"1654 Rue Alfred",
    "sg:city":"L'Ancienne-Lorette",
    "sg:classifiers":[
        {
            "category":"Building & Trades",
            "subcategory":"Plumbing",
            "type":"Services"
        }
    ],
    "sg:phone":"+1 418 871 7375",
    "sg:postcode":"G2E 3J1",
    "sg:province":"QC",
    "sg:tags":[
        "contractor"
    ],
    "wof:name":"Services D Drolet",
    "wof:placetype":"venue"
},
  "geometry": {"coordinates":[-71.364944,46.800938],"type":"Point"}
}