{
  "type": "Feature",
  "properties": {
    "iso:country":"CA",
    "sg:city":"Quebec",
    "sg:classifiers":[
        {
            "category":"Organizations",
            "subcategory":"Political Organization",
            "type":"Services"
        }
    ],
    "sg:phone":"+1 418 523 6666",
    "sg:postcode":"G1K 8G5",
    "sg:province":"QC",
    "wof:name":"Gagnon, Christiane",
    "wof:placetype":"venue"
},
  "geometry": {"coordinates":[-71.226097,46.813866],"type":"Point"}
}