{
  "type": "Feature",
  "properties": {
    "addr:full":"395 Woodstock Rd Fredericton NB E3B 2H9",
    "addr:housenumber":"395",
    "addr:postcode":"e3b 2h9",
    "addr:street":"Woodstock Rd",
    "iso:country":"CA",
    "sg:address":"395 Woodstock Rd",
    "sg:city":"Fredericton",
    "sg:classifiers":[
        {
            "category":"Real Estate",
            "subcategory":"Developer",
            "type":"Services"
        }
    ],
    "sg:phone":"+1 506 455 7377",
    "sg:postcode":"E3B 2H9",
    "sg:province":"NB",
    "sg:tags":[
        "cemetery"
    ],
    "wof:name":"Wilmot Rural Cemetery",
    "wof:placetype":"venue"
},
  "geometry": {"coordinates":[-66.668892,45.962551],"type":"Point"}
}