{
  "type": "Feature",
  "properties": {
    "addr:full":"5525 Ferry St Niagara Falls ON L2G 1S3",
    "addr:housenumber":"5525",
    "addr:postcode":"l2g 1s3",
    "addr:street":"Ferry St",
    "iso:country":"CA",
    "sg:address":"5525 Ferry St",
    "sg:city":"Niagara Falls",
    "sg:classifiers":[
        {
            "category":"Travel",
            "subcategory":"Hotels & Motels",
            "type":"Entertainment"
        }
    ],
    "sg:phone":"+1 905 356 1233",
    "sg:postcode":"L2G 1S3",
    "sg:province":"ON",
    "wof:name":"Kings Inn Motor Lodge",
    "wof:placetype":"venue"
},
  "geometry": {"coordinates":[-79.087189,43.089653],"type":"Point"}
}