{
  "type": "Feature",
  "properties": {
    "addr:full":"40 Beverly Hills Dr North York ON M3L 1A1",
    "addr:housenumber":"40",
    "addr:postcode":"m3l 1a1",
    "addr:street":"Beverly Hills Dr",
    "iso:country":"CA",
    "sg:address":"40 Beverly Hills Dr",
    "sg:city":"North York",
    "sg:classifiers":[
        {
            "category":"Wholesale",
            "subcategory":"Meat",
            "type":"Manufacturing & Wholesale Goods"
        }
    ],
    "sg:phone":"+1 416 248 2808",
    "sg:postcode":"M3L 1A1",
    "sg:province":"ON",
    "sg:tags":[
        "butchering"
    ],
    "wof:name":"Juan Meat Market",
    "wof:placetype":"venue"
},
  "geometry": {"coordinates":[-79.5121841431,43.7182807922],"type":"Point"}
}