{
  "type": "Feature",
  "properties": {
    "addr:full":"7390 50th St NE Canoe BC V0E 1K0",
    "addr:housenumber":"7390",
    "addr:postcode":"v0e 1k0",
    "addr:street":"50Th St Ne",
    "iso:country":"CA",
    "sg:address":"7390 50th St NE",
    "sg:city":"Canoe",
    "sg:classifiers":[
        {
            "category":"Food & Beverages",
            "subcategory":"Groceries & Convenience Stores",
            "type":"Retail Goods"
        }
    ],
    "sg:phone":"+1 250 804 4800",
    "sg:postcode":"V0E 1K0",
    "sg:province":"BC",
    "sg:tags":[
        "grocer"
    ],
    "wof:name":"Canoe General Store",
    "wof:placetype":"venue"
},
  "geometry": {"coordinates":[-119.07890319800001,50.7899589539],"type":"Point"}
}