{
  "type": "Feature",
  "properties": {
    "addr:full":"4430 W Saanich Rd # 102 Victoria BC V8Z 3E9",
    "addr:housenumber":"4430",
    "addr:postcode":"v8z 3e9",
    "addr:street":"W Saanich Rd # 102",
    "iso:country":"CA",
    "sg:address":"4430 W Saanich Rd # 102",
    "sg:city":"Victoria",
    "sg:classifiers":[
        {
            "category":"Personal",
            "type":"Services"
        }
    ],
    "sg:phone":"+1 250 479 7702",
    "sg:postcode":"V8Z 3E9",
    "sg:province":"BC",
    "sg:tags":[
        "control",
        "weight"
    ],
    "wof:name":"Sureslim",
    "wof:placetype":"venue"
},
  "geometry": {"coordinates":[-123.364517212,48.428314209],"type":"Point"}
}