{
  "type": "Feature",
  "properties": {
    "addr:full":"6235 Rue Saint-Hubert Montreal QC H2S 2L9",
    "addr:housenumber":"6235",
    "addr:postcode":"h2s 2l9",
    "addr:street":"Rue Saint-Hubert",
    "iso:country":"CA",
    "sg:address":"6235 Rue Saint-Hubert",
    "sg:city":"Montreal",
    "sg:classifiers":[
        {
            "category":"Home & Garden",
            "subcategory":"Furniture",
            "type":"Retail Goods"
        }
    ],
    "sg:phone":"+1 514 271 5200",
    "sg:postcode":"H2S 2L9",
    "sg:province":"QC",
    "wof:name":"Bebe-Plus",
    "wof:placetype":"venue"
},
  "geometry": {"coordinates":[-73.600388,45.53511],"type":"Point"}
}