{
  "type": "Feature",
  "properties": {
    "addr:full":"65 Guise St E Hamilton ON L8L 8B4",
    "addr:housenumber":"65",
    "addr:postcode":"l8l 8b4",
    "addr:street":"Guise St E",
    "iso:country":"CA",
    "sg:address":"65 Guise St E",
    "sg:city":"Hamilton",
    "sg:classifiers":[
        {
            "category":"Recreation",
            "type":"Entertainment"
        }
    ],
    "sg:phone":"+1 905 529 1082",
    "sg:postcode":"L8L 8B4",
    "sg:province":"ON",
    "sg:tags":[
        "boating",
        "instruction"
    ],
    "wof:name":"Ontario Boating Forum",
    "wof:placetype":"venue"
},
  "geometry": {"coordinates":[-79.858566,43.274696],"type":"Point"}
}