{
  "type": "Feature",
  "properties": {
    "addr:full":"Saskatoon SK S7H 0W5",
    "addr:postcode":"s7h 0w5",
    "iso:country":"CA",
    "sg:city":"Saskatoon",
    "sg:classifiers":[
        {
            "category":"Home & Garden",
            "subcategory":"Furniture",
            "type":"Retail Goods"
        }
    ],
    "sg:phone":"+1 306 384 5455",
    "sg:postcode":"S7H 0W5",
    "sg:province":"SK",
    "wof:name":"Mattress Mattress Inc",
    "wof:placetype":"venue"
},
  "geometry": {"coordinates":[-106.598426819,52.114906311],"type":"Point"}
}