{
  "type": "Feature",
  "properties": {
    "addr:full":"Sainte-Cecile-DE-Milton QC J0E 2C0",
    "addr:postcode":"j0e 2c0",
    "iso:country":"CA",
    "sg:city":"Sainte-Cecile-DE-Milton",
    "sg:classifiers":[
        {
            "category":"Building & Trades",
            "subcategory":"Construction",
            "type":"Services"
        }
    ],
    "sg:phone":"+1 450 378 8782",
    "sg:postcode":"J0E 2C0",
    "sg:province":"QC",
    "sg:tags":[
        "door",
        "woodworker"
    ],
    "wof:name":"Menuiserie Roger Lussier Inc",
    "wof:placetype":"venue"
},
  "geometry": {"coordinates":[-72.759262085,45.4801483154],"type":"Point"}
}