{
  "type": "Feature",
  "properties": {
    "iso:country":"CA",
    "sg:address":"171 Central Ave N",
    "sg:city":"Swift Current",
    "sg:classifiers":[
        {
            "category":"Building & Trades",
            "subcategory":"Equipment Rental",
            "type":"Services"
        }
    ],
    "sg:phone":"+1 306 778 9155",
    "sg:postcode":"S9H 0K9",
    "sg:province":"SK",
    "sg:tags":[
        "player",
        "recorder",
        "video"
    ],
    "wof:name":"Family Great Tymes Ctr",
    "wof:placetype":"venue"
},
  "geometry": {"coordinates":[-107.799781799,50.2845344543],"type":"Point"}
}