{
  "type": "Feature",
  "properties": {
    "iso:country":"CA",
    "sg:address":"3 Brakes Heights Rd",
    "sg:city":"Corner Brook",
    "sg:classifiers":[
        {
            "category":"Health Services",
            "subcategory":"Nursing And Care Facility",
            "type":"Services"
        }
    ],
    "sg:phone":"+1 709 783 2019",
    "sg:postcode":"A2H 6B9",
    "sg:province":"NL",
    "sg:tags":[
        "home",
        "rest"
    ],
    "wof:name":"Mountain View House",
    "wof:placetype":"venue"
},
  "geometry": {"coordinates":[-57.94947052,48.9501991272],"type":"Point"}
}