{
  "type": "Feature",
  "properties": {
    "addr:full":"3131 2nd Ave W Prince Albert SK S6V 5E7",
    "addr:housenumber":"3131",
    "addr:postcode":"s6v 5e7",
    "addr:street":"2Nd Ave W",
    "iso:country":"CA",
    "sg:address":"3131 2nd Ave W",
    "sg:city":"Prince Albert",
    "sg:classifiers":[
        {
            "category":"Autos & Motor Vehicles",
            "subcategory":"Fuel & Gas Station",
            "type":"Retail Goods"
        }
    ],
    "sg:phone":"+1 306 763 2298",
    "sg:postcode":"S6V 5E7",
    "sg:province":"SK",
    "sg:tags":[
        "oil"
    ],
    "wof:name":"P A South Hill Svc",
    "wof:placetype":"venue"
},
  "geometry": {"coordinates":[-105.760544,53.184643],"type":"Point"}
}