{
  "type": "Feature",
  "properties": {
    "addr:full":"1457 Ch DE LA Source Remigny QC J0Z 3H0",
    "addr:housenumber":"1457",
    "addr:postcode":"j0z 3h0",
    "addr:street":"Ch De La Source",
    "iso:country":"CA",
    "sg:address":"1457 Ch DE LA Source",
    "sg:city":"Remigny",
    "sg:classifiers":[
        {
            "category":"Manufacturing",
            "subcategory":"Lumber",
            "type":"Manufacturing & Wholesale Goods"
        }
    ],
    "sg:phone":"+1 819 761 4101",
    "sg:postcode":"J0Z 3H0",
    "sg:province":"QC",
    "sg:tags":[
        "forester"
    ],
    "wof:name":"Cooperative Forestiere-Remigny",
    "wof:placetype":"venue"
},
  "geometry": {"coordinates":[-79.1934661865,47.784160614],"type":"Point"}
}