{
  "type": "Feature",
  "properties": {
    "addr:full":"53 Rue Saint-Lambert Sainte-Therese QC J7E 3J9",
    "addr:housenumber":"53",
    "addr:postcode":"j7e 3j9",
    "addr:street":"Rue Saint-Lambert Sainte-Therese",
    "iso:country":"CA",
    "sg:address":"53 Rue Saint-Lambert",
    "sg:city":"Sainte-Therese",
    "sg:classifiers":[
        {
            "category":"Social Services",
            "type":"Services"
        }
    ],
    "sg:phone":"+1 450 437 0320",
    "sg:postcode":"J7E 3J9",
    "sg:province":"QC",
    "sg:tags":[
        "organization",
        "welfare"
    ],
    "wof:name":"Maison Des Jeunes Des Basses",
    "wof:placetype":"venue"
},
  "geometry": {"coordinates":[-73.84689299999999,45.642719],"type":"Point"}
}