{
  "type": "Feature",
  "properties": {
    "addr:full":"Lorette MB R0A 0Y0",
    "addr:postcode":"r0a 0y0",
    "iso:country":"CA",
    "sg:city":"Lorette",
    "sg:classifiers":[
        {
            "category":"Cinema",
            "subcategory":"Movie Rental",
            "type":"Entertainment"
        }
    ],
    "sg:phone":"+1 204 878 9978",
    "sg:postcode":"R0A 0Y0",
    "sg:province":"MB",
    "sg:tags":[
        "video",
        "game",
        "leasing"
    ],
    "wof:name":"Jay's Video",
    "wof:placetype":"venue"
},
  "geometry": {"coordinates":[-96.87470245359999,49.7397232056],"type":"Point"}
}