{
  "type": "Feature",
  "properties": {
    "iso:country":"CA",
    "sg:address":"11620 104 Ave NW",
    "sg:city":"Edmonton",
    "sg:classifiers":[
        {
            "category":"Restaurant",
            "type":"Food & Drink"
        }
    ],
    "sg:phone":"+1 780 482 4677",
    "sg:postcode":"T5K 2T7",
    "sg:province":"AB",
    "wof:name":"Brewsters Brewing CO & Rstrnt",
    "wof:placetype":"venue"
},
  "geometry": {"coordinates":[-113.52176666299999,53.5464477539],"type":"Point"}
}