{
  "type": "Feature",
  "properties": {
    "addr:full":"Calgary AB T2E 7E4",
    "addr:postcode":"t2e 7e4",
    "iso:country":"CA",
    "sg:city":"Calgary",
    "sg:classifiers":[
        {
            "category":"Building & Trades",
            "subcategory":"Construction",
            "type":"Services"
        }
    ],
    "sg:phone":"+1 403 291 4385",
    "sg:postcode":"T2E 7E4",
    "sg:province":"AB",
    "sg:tags":[
        "cabling",
        "computer",
        "wiring",
        "telecommunication"
    ],
    "wof:name":"Cardinal Communications Ltd",
    "wof:placetype":"venue"
},
  "geometry": {"coordinates":[-114.010238648,51.0766944885],"type":"Point"}
}