{
  "type": "Feature",
  "properties": {
    "addr:full":"Spruce Grove AB T7X 3N4",
    "addr:postcode":"t7x 3n4",
    "iso:country":"CA",
    "sg:city":"Spruce Grove",
    "sg:classifiers":[
        {
            "category":"Restaurant",
            "type":"Food & Drink"
        }
    ],
    "sg:phone":"+1 780 960 6871",
    "sg:postcode":"T7X 3N4",
    "sg:province":"AB",
    "sg:tags":[
        "pizza"
    ],
    "wof:name":"2 For 1 Parkland Pizza",
    "wof:placetype":"venue"
},
  "geometry": {"coordinates":[-113.885468,53.562889],"type":"Point"}
}