{
  "type": "Feature",
  "properties": {
    "addr:full":"12730 82 St NW Edmonton AB T5E 2T1",
    "addr:housenumber":"12730",
    "addr:postcode":"t5e 2t1",
    "addr:street":"82 St Nw",
    "iso:country":"CA",
    "sg:address":"12730 82 St NW",
    "sg:city":"Edmonton",
    "sg:classifiers":[
        {
            "category":"Restaurant",
            "type":"Food & Drink"
        }
    ],
    "sg:phone":"+1 780 478 9797",
    "sg:postcode":"T5E 2T1",
    "sg:province":"AB",
    "wof:name":"Wok N Roll Restaurant",
    "wof:placetype":"venue"
},
  "geometry": {"coordinates":[-113.46748352,53.5853118896],"type":"Point"}
}