{
  "type": "Feature",
  "properties": {
    "addr:full":"3150 Lake City Way Burnaby BC V5A 3A4",
    "addr:housenumber":"3150",
    "addr:postcode":"v5a 3a4",
    "addr:street":"Lake City Way",
    "iso:country":"CA",
    "sg:address":"3150 Lake City Way",
    "sg:city":"Burnaby",
    "sg:classifiers":[
        {
            "category":"Wholesale",
            "subcategory":"Construction Materials",
            "type":"Manufacturing & Wholesale Goods"
        }
    ],
    "sg:phone":"+1 604 420 9599",
    "sg:postcode":"V5A 3A4",
    "sg:province":"BC",
    "sg:tags":[
        "building"
    ],
    "wof:name":"E Roko Distributors Ltd",
    "wof:placetype":"venue"
},
  "geometry": {"coordinates":[-122.937592,49.256542],"type":"Point"}
}