{
  "type": "Feature",
  "properties": {
    "addr:full":"5108 49 Ave Rycroft AB T0H 3A0",
    "addr:housenumber":"5108",
    "addr:postcode":"t0h 3a0",
    "addr:street":"49 Ave",
    "iso:country":"CA",
    "sg:address":"5108 49 Ave",
    "sg:city":"Rycroft",
    "sg:classifiers":[
        {
            "category":"Building & Trades",
            "subcategory":"Construction",
            "type":"Services"
        }
    ],
    "sg:phone":"+1 780 765 2559",
    "sg:postcode":"T0H 3A0",
    "sg:province":"AB",
    "sg:tags":[
        "pile",
        "driving"
    ],
    "wof:name":"Dfi",
    "wof:placetype":"venue"
},
  "geometry": {"coordinates":[-118.71096799999999,55.758774],"type":"Point"}
}