{
  "type": "Feature",
  "properties": {
    "addr:full":"107 Connie Cres Concord ON L4K 1L3",
    "addr:housenumber":"107",
    "addr:postcode":"l4k 1l3",
    "addr:street":"Connie Cres",
    "iso:country":"CA",
    "sg:address":"107 Connie Cres",
    "sg:city":"Concord",
    "sg:classifiers":[
        {
            "category":"Wholesale",
            "subcategory":"Electrical",
            "type":"Manufacturing & Wholesale Goods"
        }
    ],
    "sg:phone":"+1 905 660 6234",
    "sg:postcode":"L4K 1L3",
    "sg:province":"ON",
    "sg:tags":[
        "high",
        "fidelity",
        "stereophonic"
    ],
    "wof:name":"Precor Limited",
    "wof:placetype":"venue"
},
  "geometry": {"coordinates":[-79.488991,43.818863],"type":"Point"}
}