{
  "type": "Feature",
  "properties": {
    "addr:full":"303 Highland Rd W Kitchener ON N2M 3C6",
    "addr:housenumber":"303",
    "addr:postcode":"n2m 3c6",
    "addr:street":"Highland Rd W",
    "iso:country":"CA",
    "sg:address":"303 Highland Rd W",
    "sg:city":"Kitchener",
    "sg:classifiers":[
        {
            "category":"Retail",
            "subcategory":"Portrait Studio",
            "type":"Services"
        }
    ],
    "sg:phone":"+1 519 742 1997",
    "sg:postcode":"N2M 3C6",
    "sg:province":"ON",
    "sg:tags":[
        "photographer"
    ],
    "wof:name":"Dennis Peter Photography",
    "wof:placetype":"venue"
},
  "geometry": {"coordinates":[-80.5088729858,43.4387702942],"type":"Point"}
}