{
  "type": "Feature",
  "properties": {
    "addr:full":"1905 Lonsdale Ave North Vancouver BC V7M 2K3",
    "addr:housenumber":"1905",
    "addr:postcode":"v7m 2k3",
    "addr:street":"Lonsdale Ave",
    "iso:country":"CA",
    "sg:address":"1905 Lonsdale Ave",
    "sg:city":"North Vancouver",
    "sg:classifiers":[
        {
            "category":"Cinema",
            "subcategory":"Movie Rental",
            "type":"Entertainment"
        }
    ],
    "sg:phone":"+1 604 987 1800",
    "sg:postcode":"V7M 2K3",
    "sg:province":"BC",
    "sg:tags":[
        "leasing",
        "video",
        "disc",
        "tape"
    ],
    "wof:name":"Blockbuster Video",
    "wof:placetype":"venue"
},
  "geometry": {"coordinates":[-123.072372,49.326366],"type":"Point"}
}