{
  "type": "Feature",
  "properties": {
    "addr:full":"3482 Lawrence Ave E # 101 Scarborough ON M1H 3E5",
    "addr:housenumber":"3482",
    "addr:postcode":"m1h 3e5",
    "addr:street":"Lawrence Ave E # 101",
    "iso:country":"CA",
    "sg:address":"3482 Lawrence Ave E # 101",
    "sg:city":"Scarborough",
    "sg:classifiers":[
        {
            "category":"Bars & Pubs",
            "type":"Food & Drink"
        }
    ],
    "sg:phone":"+1 416 439 0100",
    "sg:postcode":"M1H 3E5",
    "sg:province":"ON",
    "wof:name":"Smilin Jack's Bar & Grill",
    "wof:placetype":"venue"
},
  "geometry": {"coordinates":[-79.229309,43.759106],"type":"Point"}
}