{
  "type": "Feature",
  "properties": {
    "addr:full":"583472 West Rd Haileybury ON P0J 1K0",
    "addr:housenumber":"583472",
    "addr:postcode":"p0j 1k0",
    "addr:street":"West Rd",
    "iso:country":"CA",
    "sg:address":"583472 West Rd",
    "sg:city":"Haileybury",
    "sg:classifiers":[
        {
            "category":"Organizations",
            "subcategory":"Religious Organization",
            "type":"Services"
        }
    ],
    "sg:phone":"+1 705 672 2020",
    "sg:postcode":"P0J 1K0",
    "sg:province":"ON",
    "sg:tags":[
        "church"
    ],
    "wof:name":"Haileybury Pentecostal Assembl",
    "wof:placetype":"venue"
},
  "geometry": {"coordinates":[-79.6376647949,47.4494094849],"type":"Point"}
}