{
  "type": "Feature",
  "properties": {
    "addr:full":"2008 36 St SE Calgary AB T2B 0X8",
    "addr:housenumber":"2008",
    "addr:postcode":"t2b 0x8",
    "addr:street":"36 St Se",
    "iso:country":"CA",
    "sg:address":"2008 36 St SE",
    "sg:city":"Calgary",
    "sg:classifiers":[
        {
            "category":"Personal",
            "subcategory":"Beauty Salon",
            "type":"Services"
        }
    ],
    "sg:phone":"+1 403 235 5543",
    "sg:postcode":"T2B 0X8",
    "sg:province":"AB",
    "wof:name":"Beautiful You Salon",
    "wof:placetype":"venue"
},
  "geometry": {"coordinates":[-113.98142199999999,51.035645],"type":"Point"}
}