{
  "type": "Feature",
  "properties": {
    "addr:full":"3825 Richmond Rd # 25 Nepean ON K2H 1A5",
    "addr:housenumber":"3825;25",
    "addr:postcode":"k2h 1a5",
    "addr:street":"Richmond Rd #",
    "iso:country":"CA",
    "sg:address":"3825 Richmond Rd # 25",
    "sg:city":"Nepean",
    "sg:classifiers":[
        {
            "category":"Restaurant",
            "type":"Food & Drink"
        }
    ],
    "sg:phone":"+1 613 596 2828",
    "sg:postcode":"K2H 1A5",
    "sg:province":"ON",
    "wof:name":"Easy Garden Chinese Buffet",
    "wof:placetype":"venue"
},
  "geometry": {"coordinates":[-75.8266906738,45.3241958618],"type":"Point"}
}