{
  "type": "Feature",
  "properties": {
    "addr:full":"Cochrane AB T4C 2B5",
    "addr:postcode":"t4c 2b5",
    "iso:country":"CA",
    "sg:city":"Cochrane",
    "sg:classifiers":[
        {
            "category":"Freight",
            "type":"Transportation"
        }
    ],
    "sg:phone":"+1 403 932 4776",
    "sg:postcode":"T4C 2B5",
    "sg:province":"AB",
    "sg:tags":[
        "bus",
        "line",
        "courier"
    ],
    "wof:name":"Greyhound Canada",
    "wof:placetype":"venue"
},
  "geometry": {"coordinates":[-114.46488952599999,51.1872062683],"type":"Point"}
}