{
  "type": "Feature",
  "properties": {
    "addr:full":"3200 Spit Campbell River BC V9W 5C5",
    "addr:housenumber":"3200",
    "addr:postcode":"v9w 5c5",
    "addr:street":"Spit",
    "iso:country":"CA",
    "sg:address":"3200 Spit",
    "sg:city":"Campbell River",
    "sg:classifiers":[
        {
            "category":"Travel",
            "subcategory":"Hotels & Motels",
            "type":"Entertainment"
        }
    ],
    "sg:phone":"+1 250 287 3223",
    "sg:postcode":"V9W 5C5",
    "sg:province":"BC",
    "sg:tags":[
        "resort"
    ],
    "wof:name":"Tyee Resort Ltd",
    "wof:placetype":"venue"
},
  "geometry": {"coordinates":[-125.25458500000001,50.047222],"type":"Point"}
}