{
  "type": "Feature",
  "properties": {
    "addr:full":"15722 Boul DE Pierrefonds Pierrefonds QC H9H 3P6",
    "addr:housenumber":"15722",
    "addr:postcode":"h9h 3p6",
    "addr:street":"Boul De Pierrefonds",
    "iso:country":"CA",
    "sg:address":"15722 Boul DE Pierrefonds",
    "sg:city":"Pierrefonds",
    "sg:classifiers":[
        {
            "category":"Personal",
            "subcategory":"Barber",
            "type":"Services"
        }
    ],
    "sg:phone":"+1 514 626 2220",
    "sg:postcode":"H9H 3P6",
    "sg:province":"QC",
    "wof:name":"Salon Jean-Jacques",
    "wof:placetype":"venue"
},
  "geometry": {"coordinates":[-73.865692,45.479584],"type":"Point"}
}