{
  "type": "Feature",
  "properties": {
    "addr:full":"9955 Av Lausanne Montreal-Nord QC H1H 5A6",
    "addr:housenumber":"9955",
    "addr:postcode":"h1h 5a6",
    "addr:street":"Av Lausanne",
    "iso:country":"CA",
    "sg:address":"9955 Av Lausanne",
    "sg:city":"Montreal-Nord",
    "sg:classifiers":[
        {
            "category":"Wholesale",
            "subcategory":"Home Furnishings",
            "type":"Manufacturing & Wholesale Goods"
        }
    ],
    "sg:phone":"+1 514 322 6299",
    "sg:postcode":"H1H 5A6",
    "sg:province":"QC",
    "sg:tags":[
        "blind",
        "venetian"
    ],
    "wof:name":"Trans Uv Inc",
    "wof:placetype":"venue"
},
  "geometry": {"coordinates":[-73.638367,45.578014],"type":"Point"}
}