{
  "type": "Feature",
  "properties": {
    "addr:full":"25 Sunset Cres Morell PE C0A 1S0",
    "addr:housenumber":"25",
    "addr:postcode":"c0a 1s0",
    "addr:street":"Sunset Cres",
    "iso:country":"CA",
    "sg:address":"25 Sunset Cres",
    "sg:city":"Morell",
    "sg:classifiers":[
        {
            "category":"Health Services",
            "subcategory":"Doctor",
            "type":"Services"
        }
    ],
    "sg:phone":"+1 902 961 2787",
    "sg:postcode":"C0A 1S0",
    "sg:province":"PE",
    "sg:tags":[
        "dentist"
    ],
    "wof:name":"Coady, Maurice A DDS",
    "wof:placetype":"venue"
},
  "geometry": {"coordinates":[-62.7061805725,46.4156913757],"type":"Point"}
}