{
  "type": "Feature",
  "properties": {
    "addr:full":"3841 Hwy 118 W Port Carling ON P0B 1J0",
    "addr:housenumber":"3841",
    "addr:postcode":"p0b 1j0",
    "addr:street":"Hwy 118 W",
    "iso:country":"CA",
    "sg:address":"3841 Hwy 118 W",
    "sg:city":"Port Carling",
    "sg:classifiers":[
        {
            "category":"Wholesale",
            "subcategory":"Construction Materials",
            "type":"Manufacturing & Wholesale Goods"
        }
    ],
    "sg:phone":"+1 705 765 6447",
    "sg:postcode":"P0B 1J0",
    "sg:province":"ON",
    "sg:tags":[
        "sand",
        "gravel"
    ],
    "wof:name":"Brent Quarry",
    "wof:placetype":"venue"
},
  "geometry": {"coordinates":[-79.605774,45.098156],"type":"Point"}
}