{
  "type": "Feature",
  "properties": {
    "iso:country":"CA",
    "sg:address":"Graham Rd",
    "sg:city":"Thunder Bay",
    "sg:classifiers":[
        {
            "category":"Manufacturing",
            "subcategory":"Lumber",
            "type":"Manufacturing & Wholesale Goods"
        }
    ],
    "sg:phone":"+1 807 986 2371",
    "sg:postcode":"P7B 6B9",
    "sg:province":"ON",
    "sg:tags":[
        "company",
        "logging"
    ],
    "wof:name":"Buchanan Forest Products Ltd",
    "wof:placetype":"venue"
},
  "geometry": {"coordinates":[-90.61763000000001,49.206345],"type":"Point"}
}