{
  "type": "Feature",
  "properties": {
    "addr:full":"10135 Hwy 7 Head of Jeddore NS B0J 1P0",
    "addr:housenumber":"10135",
    "addr:postcode":"b0j 1p0",
    "addr:street":"Hwy 7",
    "iso:country":"CA",
    "sg:address":"10135 Hwy 7",
    "sg:city":"Head of Jeddore",
    "sg:classifiers":[
        {
            "category":"Manufacturing",
            "subcategory":"Printing",
            "type":"Manufacturing & Wholesale Goods"
        }
    ],
    "sg:phone":"+1 902 889 3676",
    "sg:postcode":"B0J 1P0",
    "sg:province":"NS",
    "sg:tags":[
        "printer"
    ],
    "wof:name":"Shore Print",
    "wof:placetype":"venue"
},
  "geometry": {"coordinates":[-63.0611495972,44.7782287598],"type":"Point"}
}