{
  "type": "Feature",
  "properties": {
    "addr:full":"234 41 Ave NE Calgary AB T2E 2N3",
    "addr:housenumber":"234",
    "addr:postcode":"t2e 2n3",
    "addr:street":"41 Ave Ne",
    "iso:country":"CA",
    "sg:address":"234 41 Ave NE",
    "sg:city":"Calgary",
    "sg:classifiers":[
        {
            "category":"Retail",
            "subcategory":"Auto Repair",
            "type":"Services"
        }
    ],
    "sg:phone":"+1 403 520 2008",
    "sg:postcode":"T2E 2N3",
    "sg:province":"AB",
    "sg:tags":[
        "repairing",
        "automobile"
    ],
    "wof:name":"Hks Auto Svc Ctr",
    "wof:placetype":"venue"
},
  "geometry": {"coordinates":[-114.06086000000001,51.089268],"type":"Point"}
}