{
  "type": "Feature",
  "properties": {
    "addr:full":"Peace River AB T8S 1E8",
    "addr:postcode":"t8s 1e8",
    "iso:country":"CA",
    "sg:city":"Peace River",
    "sg:classifiers":[
        {
            "category":"Personal",
            "subcategory":"Barber",
            "type":"Services"
        }
    ],
    "sg:phone":"+1 780 624 1237",
    "sg:postcode":"T8S 1E8",
    "sg:province":"AB",
    "wof:name":"Don's Barber Shop",
    "wof:placetype":"venue"
},
  "geometry": {"coordinates":[-117.29232,56.233421],"type":"Point"}
}