{
  "type": "Feature",
  "properties": {
    "addr:full":"6000 Kingston Rd Scarborough ON M1C 1K3",
    "addr:housenumber":"6000",
    "addr:postcode":"m1c 1k3",
    "addr:street":"Kingston Rd",
    "iso:country":"CA",
    "sg:address":"6000 Kingston Rd",
    "sg:city":"Scarborough",
    "sg:classifiers":[
        {
            "category":"Retail",
            "subcategory":"Auto Repair",
            "type":"Services"
        }
    ],
    "sg:phone":"+1 416 282 7758",
    "sg:postcode":"M1C 1K3",
    "sg:province":"ON",
    "sg:tags":[
        "repairing",
        "automobile"
    ],
    "wof:name":"Campbell's Service Ctr",
    "wof:placetype":"venue"
},
  "geometry": {"coordinates":[-79.169617,43.782661],"type":"Point"}
}