{
  "type": "Feature",
  "properties": {
    "iso:country":"CA",
    "sg:address":"1830 Av Jeanne-D'Arc",
    "sg:city":"Montreal",
    "sg:classifiers":[
        {
            "category":"Building & Trades",
            "subcategory":"Construction",
            "type":"Services"
        }
    ],
    "sg:phone":"+1 514 523 0388",
    "sg:postcode":"H1W 3V1",
    "sg:province":"QC",
    "sg:tags":[
        "masonry",
        "contractor"
    ],
    "wof:name":"Construction Rheaume Ltee",
    "wof:placetype":"venue"
},
  "geometry": {"coordinates":[-73.540306,45.54895],"type":"Point"}
}