{
  "type": "Feature",
  "properties": {
    "iso:country":"CA",
    "sg:city":"Newmarket",
    "sg:classifiers":[
        {
            "category":"Personal",
            "type":"Services"
        }
    ],
    "sg:phone":"+1 905 836 9505",
    "sg:postcode":"L3Y 8C6",
    "sg:province":"ON",
    "sg:tags":[
        "therapist",
        "massage"
    ],
    "wof:name":"Hands on Health Care",
    "wof:placetype":"venue"
},
  "geometry": {"coordinates":[-79.433617,44.073376],"type":"Point"}
}