{
  "type": "Feature",
  "properties": {
    "addr:full":"3612 Burnsland Rd SE Calgary AB T2G 3Z2",
    "addr:housenumber":"3612",
    "addr:postcode":"t2g 3z2",
    "addr:street":"Burnsland Rd Se",
    "iso:country":"CA",
    "sg:address":"3612 Burnsland Rd SE",
    "sg:city":"Calgary",
    "sg:classifiers":[
        {
            "category":"Retail",
            "subcategory":"Repair Shop",
            "type":"Services"
        }
    ],
    "sg:phone":"+1 403 243 4171",
    "sg:postcode":"T2G 3Z2",
    "sg:province":"AB",
    "sg:tags":[
        "upholsterer"
    ],
    "wof:name":"Mac Leod Trail Upholstery",
    "wof:placetype":"venue"
},
  "geometry": {"coordinates":[-114.057701111,51.0227813721],"type":"Point"}
}