{
  "type": "Feature",
  "properties": {
    "addr:full":"Fort Erie ON L2A 6M4",
    "addr:postcode":"l2a 6m4",
    "iso:country":"CA",
    "sg:city":"Fort Erie",
    "sg:classifiers":[
        {
            "category":"Freight",
            "type":"Transportation"
        }
    ],
    "sg:phone":"+1 905 871 9575",
    "sg:postcode":"L2A 6M4",
    "sg:province":"ON",
    "sg:tags":[
        "broker",
        "customs"
    ],
    "wof:name":"Nippon Express Canada Ltd",
    "wof:placetype":"venue"
},
  "geometry": {"coordinates":[-78.909966,42.909386],"type":"Point"}
}