{
  "type": "Feature",
  "properties": {
    "addr:full":"180 Bethridge Rd Etobicoke ON M9W 1N3",
    "addr:housenumber":"180",
    "addr:postcode":"m9w 1n3",
    "addr:street":"Bethridge Rd",
    "iso:country":"CA",
    "sg:address":"180 Bethridge Rd",
    "sg:city":"Etobicoke",
    "sg:classifiers":[
        {
            "category":"Home & Garden",
            "subcategory":"Building Materials",
            "type":"Retail Goods"
        }
    ],
    "sg:phone":"+1 416 741 5402",
    "sg:postcode":"M9W 1N3",
    "sg:province":"ON",
    "sg:tags":[
        "insulation",
        "roofing",
        "heat"
    ],
    "wof:name":"Convoy Supply Ltd",
    "wof:placetype":"venue"
},
  "geometry": {"coordinates":[-79.5848770142,43.7086372375],"type":"Point"}
}