{
  "type": "Feature",
  "properties": {
    "iso:country":"CA",
    "sg:address":"445 3rd St",
    "sg:city":"Kamsack",
    "sg:classifiers":[
        {
            "category":"Building & Trades",
            "subcategory":"Plumbing",
            "type":"Services"
        }
    ],
    "sg:phone":"+1 306 542 4411",
    "sg:postcode":"S0A 1S0",
    "sg:province":"SK",
    "sg:tags":[
        "heating",
        "contractor"
    ],
    "wof:name":"A & L Plumbing & Heating Ltd",
    "wof:placetype":"venue"
},
  "geometry": {"coordinates":[-101.90032959,51.5645523071],"type":"Point"}
}