{
  "type": "Feature",
  "properties": {
    "addr:full":"Mississauga ON L5S 1E7",
    "addr:postcode":"l5s 1e7",
    "iso:country":"CA",
    "sg:city":"Mississauga",
    "sg:classifiers":[
        {
            "category":"Retail",
            "subcategory":"Repair Shop",
            "type":"Services"
        }
    ],
    "sg:phone":"+1 905 673 9251",
    "sg:postcode":"L5S 1E7",
    "sg:province":"ON",
    "sg:tags":[
        "appliance"
    ],
    "wof:name":"Lomatic Appliance Ctr",
    "wof:placetype":"venue"
},
  "geometry": {"coordinates":[-79.66426800000001,43.700661],"type":"Point"}
}