{
  "type": "Feature",
  "properties": {
    "addr:full":"Abbotsford BC V2T 4W7",
    "addr:postcode":"v2t 4w7",
    "iso:country":"CA",
    "sg:city":"Abbotsford",
    "sg:classifiers":[
        {
            "category":"Professional",
            "subcategory":"Accounting & Tax Preparation",
            "type":"Services"
        }
    ],
    "sg:phone":"+1 604 853 8682",
    "sg:postcode":"V2T 4W7",
    "sg:province":"BC",
    "sg:tags":[
        "credit",
        "accountant",
        "debt",
        "counseling"
    ],
    "wof:name":"Bdo Dunwoody Ltd",
    "wof:placetype":"venue"
},
  "geometry": {"coordinates":[-122.321335,49.054573],"type":"Point"}
}