{
  "type": "Feature",
  "properties": {
    "addr:full":"189 King St E Kitchener ON N2G 2K8",
    "addr:housenumber":"189",
    "addr:postcode":"n2g 2k8",
    "addr:street":"King St E",
    "iso:country":"CA",
    "sg:address":"189 King St E",
    "sg:city":"Kitchener",
    "sg:classifiers":[
        {
            "category":"Real Estate",
            "subcategory":"Real Estate Agent",
            "type":"Services"
        }
    ],
    "sg:phone":"+1 519 742 4477",
    "sg:postcode":"N2G 2K8",
    "sg:province":"ON",
    "wof:name":"Margaret Schiketanz Real Est",
    "wof:placetype":"venue"
},
  "geometry": {"coordinates":[-80.48607635499999,43.4482688904],"type":"Point"}
}