{
  "type": "Feature",
  "properties": {
    "addr:full":"4565 Av Du Parc Montreal QC H2V 4E4",
    "addr:housenumber":"4565",
    "addr:postcode":"h2v 4e4",
    "addr:street":"Av Du Parc",
    "iso:country":"CA",
    "sg:address":"4565 Av Du Parc",
    "sg:city":"Montreal",
    "sg:phone":"+1 514 842 1421",
    "sg:postcode":"H2V 4E4",
    "sg:province":"QC",
    "sg:tags":[
        "equipment",
        "motel",
        "hotel",
        "supply"
    ],
    "wof:name":"Monas & CO Ltd",
    "wof:placetype":"venue"
},
  "geometry": {"coordinates":[-73.5902938843,45.5173454285],"type":"Point"}
}