{
  "type": "Feature",
  "properties": {
    "iso:country":"CA",
    "sg:address":"3023 Town Line Rd",
    "sg:city":"Coldwater",
    "sg:classifiers":[
        {
            "category":"Retail",
            "subcategory":"Auto Repair",
            "type":"Services"
        }
    ],
    "sg:phone":"+1 705 325 0845",
    "sg:postcode":"L0K 1E0",
    "sg:province":"ON",
    "sg:tags":[
        "body",
        "automobile",
        "painting"
    ],
    "wof:name":"Body By Biggs",
    "wof:placetype":"venue"
},
  "geometry": {"coordinates":[-79.64436340330001,44.7102241516],"type":"Point"}
}