{
  "type": "Feature",
  "properties": {
    "addr:full":"25 Huron Deep River ON K0J 1P0",
    "addr:housenumber":"25",
    "addr:postcode":"k0j 1p0",
    "addr:street":"Huron",
    "iso:country":"CA",
    "sg:address":"25 Huron",
    "sg:city":"Deep River",
    "sg:classifiers":[
        {
            "category":"Shopping",
            "subcategory":"Bicycles & Sporting Goods",
            "type":"Retail Goods"
        }
    ],
    "sg:phone":"+1 613 584 1728",
    "sg:postcode":"K0J 1P0",
    "sg:province":"ON",
    "wof:name":"Golfsoft Software",
    "wof:placetype":"venue"
},
  "geometry": {"coordinates":[-77.49323272709999,46.1013450623],"type":"Point"}
}