{
  "type": "Feature",
  "properties": {
    "iso:country":"CA",
    "sg:city":"Calgary",
    "sg:classifiers":[
        {
            "category":"Health Services",
            "subcategory":"Doctor",
            "type":"Services"
        }
    ],
    "sg:phone":"+1 403 220 5077",
    "sg:postcode":"T2N 1N4",
    "sg:province":"AB",
    "sg:tags":[
        "physician",
        "surgeon"
    ],
    "wof:name":"Hollinshead, Robert M MD",
    "wof:placetype":"venue"
},
  "geometry": {"coordinates":[-114.13243866000001,51.0785827637],"type":"Point"}
}