{
  "type": "Feature",
  "properties": {
    "iso:country":"CA",
    "sg:city":"Rouyn-Noranda",
    "sg:classifiers":[
        {
            "category":"Freight",
            "type":"Transportation"
        }
    ],
    "sg:phone":"+1 819 797 5043",
    "sg:postcode":"J9X 5A3",
    "sg:province":"QC",
    "sg:tags":[
        "trucking"
    ],
    "wof:name":"Transport Nord-Ouest Inc",
    "wof:placetype":"venue"
},
  "geometry": {"coordinates":[-79.04066467289999,48.2971801758],"type":"Point"}
}