{
  "type": "Feature",
  "properties": {
    "addr:full":"PO Box 14 Port Borden PE C0B 1X0",
    "addr:housenumber":"po box 14",
    "addr:postcode":"c0b 1x0",
    "iso:country":"CA",
    "sg:address":"PO Box 14",
    "sg:city":"Port Borden",
    "sg:classifiers":[
        {
            "category":"Social Services",
            "subcategory":"Child Care",
            "type":"Services"
        }
    ],
    "sg:phone":"+1 902 855 3007",
    "sg:postcode":"C0B 1X0",
    "sg:province":"PE",
    "sg:tags":[
        "kindergarten",
        "academic",
        "school"
    ],
    "wof:name":"Humpty Dumpty Kindergarten",
    "wof:placetype":"venue"
},
  "geometry": {"coordinates":[-63.6927261353,46.2540435791],"type":"Point"}
}