{
  "type": "Feature",
  "properties": {
    "addr:full":"28 Rue Saint-Paul E Montreal QC H2Y 1G3",
    "addr:housenumber":"28",
    "addr:postcode":"h2y 1g3",
    "addr:street":"Rue Saint-Paul E",
    "iso:country":"CA",
    "sg:address":"28 Rue Saint-Paul E",
    "sg:city":"Montreal",
    "sg:classifiers":[
        {
            "category":"Professional",
            "subcategory":"Art Services",
            "type":"Services"
        }
    ],
    "sg:phone":"+1 514 875 1012",
    "sg:postcode":"H2Y 1G3",
    "sg:province":"QC",
    "sg:tags":[
        "graphic",
        "designer"
    ],
    "wof:name":"Langevin & Turcotte",
    "wof:placetype":"venue"
},
  "geometry": {"coordinates":[-73.5533065796,45.5059776306],"type":"Point"}
}