{
  "type": "Feature",
  "properties": {
    "iso:country":"CA",
    "sg:address":"12 Melvyn Ave",
    "sg:city":"Lively",
    "sg:classifiers":[
        {
            "category":"Building & Trades",
            "subcategory":"Construction",
            "type":"Services"
        }
    ],
    "sg:phone":"+1 705 692 5557",
    "sg:postcode":"P3Y 1A8",
    "sg:province":"ON",
    "sg:tags":[
        "home",
        "improvement"
    ],
    "wof:name":"Ontario Wide Home Improvements",
    "wof:placetype":"venue"
},
  "geometry": {"coordinates":[-81.1248703003,46.4228668213],"type":"Point"}
}