{
  "type": "Feature",
  "properties": {
    "addr:full":"5130 Brenton-Page Rd Ladysmith BC V9G 1L6",
    "addr:housenumber":"5130",
    "addr:postcode":"v9g 1l6",
    "addr:street":"Brenton-Page Rd",
    "iso:country":"CA",
    "sg:address":"5130 Brenton-Page Rd",
    "sg:city":"Ladysmith",
    "sg:classifiers":[
        {
            "category":"Travel",
            "subcategory":"Hotels & Motels",
            "type":"Entertainment"
        }
    ],
    "sg:phone":"+1 250 245 8051",
    "sg:postcode":"V9G 1L6",
    "sg:province":"BC",
    "sg:tags":[
        "breakfast",
        "accommodation",
        "bed"
    ],
    "wof:name":"Kiwi Cove Lodge",
    "wof:placetype":"venue"
},
  "geometry": {"coordinates":[-123.82054100000001,48.997356],"type":"Point"}
}