{
  "type": "Feature",
  "properties": {
    "addr:full":"Sidney BC V8L 2X1",
    "addr:postcode":"v8l 2x1",
    "iso:country":"CA",
    "sg:city":"Sidney",
    "sg:classifiers":[
        {
            "category":"Shopping",
            "subcategory":"Stationery & Office Supplies",
            "type":"Retail Goods"
        }
    ],
    "sg:phone":"+1 250 655 3888",
    "sg:postcode":"V8L 2X1",
    "sg:province":"BC",
    "sg:tags":[
        "post"
    ],
    "wof:name":"Monk Office Supply Ltd",
    "wof:placetype":"venue"
},
  "geometry": {"coordinates":[-123.400093,48.648174],"type":"Point"}
}