{
  "type": "Feature",
  "properties": {
    "iso:country":"CA",
    "sg:address":"1983 Queen St E",
    "sg:city":"Toronto",
    "sg:classifiers":[
        {
            "category":"Shopping",
            "subcategory":"Clothing, Apparel, & Fashions",
            "type":"Retail Goods"
        }
    ],
    "sg:phone":"+1 416 698 2799",
    "sg:postcode":"M4L 1J1",
    "sg:province":"ON",
    "wof:name":"Pony Club Fashion For Men",
    "wof:placetype":"venue"
},
  "geometry": {"coordinates":[-79.3004150391,43.6698188782],"type":"Point"}
}