{
  "type": "Feature",
  "properties": {
    "addr:full":"157 Seventh St Kitimat BC V8C 2C4",
    "addr:housenumber":"157",
    "addr:postcode":"bc v8c 2c4",
    "addr:street":"Seventh St",
    "iso:country":"CA",
    "sg:address":"157 Seventh St",
    "sg:city":"Kitimat",
    "sg:classifiers":[
        {
            "category":"Autos & Motor Vehicles",
            "subcategory":"Auto Supplies",
            "type":"Retail Goods"
        }
    ],
    "sg:phone":"+1 250 632 2107",
    "sg:postcode":"V8C 2C4",
    "sg:province":"BC",
    "sg:tags":[
        "automobile",
        "parts"
    ],
    "wof:name":"Daval Automotive & Ind Supply",
    "wof:placetype":"venue"
},
  "geometry": {"coordinates":[-128.68545499999999,54.061241],"type":"Point"}
}