{
  "type": "Feature",
  "properties": {
    "iso:country":"CA",
    "sg:address":"6898 Lesley Cres",
    "sg:city":"Powell River",
    "sg:classifiers":[
        {
            "category":"Building & Trades",
            "subcategory":"Construction",
            "type":"Services"
        }
    ],
    "sg:phone":"+1 604 485 5035",
    "sg:postcode":"V8A 5K2",
    "sg:province":"BC",
    "sg:tags":[
        "roofing",
        "contractor",
        "general"
    ],
    "wof:name":"R & R Roofing",
    "wof:placetype":"venue"
},
  "geometry": {"coordinates":[-124.52497863799999,49.8470497131],"type":"Point"}
}