{
  "type": "Feature",
  "properties": {
    "addr:full":"2555 Rue Paul-Pau Montreal QC H1L 4L5",
    "addr:housenumber":"2555",
    "addr:postcode":"h1l 4l5",
    "addr:street":"Rue Paul-Pau",
    "iso:country":"CA",
    "sg:address":"2555 Rue Paul-Pau",
    "sg:city":"Montreal",
    "sg:classifiers":[
        {
            "category":"Building & Trades",
            "subcategory":"Construction",
            "type":"Services"
        }
    ],
    "sg:phone":"+1 514 493 6467",
    "sg:postcode":"H1L 4L5",
    "sg:province":"QC",
    "sg:tags":[
        "insulation",
        "heat",
        "contractor"
    ],
    "wof:name":"Isolation Dynamo Inc",
    "wof:placetype":"venue"
},
  "geometry": {"coordinates":[-73.51801300050001,45.6060333252],"type":"Point"}
}