{
  "type": "Feature",
  "properties": {
    "addr:full":"114 St David St Mitchell ON N0K 1N0",
    "addr:housenumber":"114",
    "addr:postcode":"n0k 1n0",
    "addr:street":"St David St",
    "iso:country":"CA",
    "sg:address":"114 St David St",
    "sg:city":"Mitchell",
    "sg:classifiers":[
        {
            "category":"Organizations",
            "subcategory":"Religious Organization",
            "type":"Services"
        }
    ],
    "sg:phone":"+1 519 348 9082",
    "sg:postcode":"N0K 1N0",
    "sg:province":"ON",
    "sg:tags":[
        "church"
    ],
    "wof:name":"Grace Lutheran Church",
    "wof:placetype":"venue"
},
  "geometry": {"coordinates":[-81.194641,43.465935],"type":"Point"}
}