{
  "type": "Feature",
  "properties": {
    "addr:full":"9 Winsloe Rd Charlottetown PE C1E 1Z3",
    "addr:housenumber":"9",
    "addr:postcode":"c1e 1z3",
    "addr:street":"Winsloe Rd",
    "iso:country":"CA",
    "sg:address":"9 Winsloe Rd",
    "sg:city":"Charlottetown",
    "sg:classifiers":[
        {
            "category":"Food & Beverages",
            "subcategory":"Groceries & Convenience Stores",
            "type":"Retail Goods"
        }
    ],
    "sg:phone":"+1 902 672 2039",
    "sg:postcode":"C1E 1Z3",
    "sg:province":"PE",
    "sg:tags":[
        "grocer"
    ],
    "wof:name":"Mac Kenzie's Grocery",
    "wof:placetype":"venue"
},
  "geometry": {"coordinates":[-63.172764,46.292484],"type":"Point"}
}