{
  "type": "Feature",
  "properties": {
    "addr:full":"6 Forest St Chatham ON N7L 1Z7",
    "addr:housenumber":"6",
    "addr:postcode":"n7l 1z7",
    "addr:street":"Forest St",
    "iso:country":"CA",
    "sg:address":"6 Forest St",
    "sg:city":"Chatham",
    "sg:classifiers":[
        {
            "category":"Travel",
            "subcategory":"Hotels & Motels",
            "type":"Entertainment"
        }
    ],
    "sg:phone":"+1 519 352 8982",
    "sg:postcode":"N7L 1Z7",
    "sg:province":"ON",
    "sg:tags":[
        "antique",
        "breakfast",
        "accommodation",
        "bed"
    ],
    "wof:name":"Theresa's Wood Shed",
    "wof:placetype":"venue"
},
  "geometry": {"coordinates":[-82.192604,42.409393],"type":"Point"}
}