{
  "type": "Feature",
  "properties": {
    "addr:full":"52 Lakeport Rd St Catharines ON L2N 4P7",
    "addr:housenumber":"52",
    "addr:postcode":"l2n 4p7",
    "addr:street":"Lakeport Rd",
    "iso:country":"CA",
    "sg:address":"52 Lakeport Rd",
    "sg:city":"St Catharines",
    "sg:classifiers":[
        {
            "category":"Food & Beverages",
            "subcategory":"Bakery",
            "type":"Retail Goods"
        }
    ],
    "sg:phone":"+1 905 937 3109",
    "sg:postcode":"L2N 4P7",
    "sg:province":"ON",
    "sg:tags":[
        "doughnut"
    ],
    "wof:name":"Tim Hortons",
    "wof:placetype":"venue"
},
  "geometry": {"coordinates":[-79.266006,43.201012],"type":"Point"}
}