{
  "type": "Feature",
  "properties": {
    "addr:full":"1284 Wellington St W Ottawa ON K1Y 3A9",
    "addr:housenumber":"1284",
    "addr:postcode":"k1y 3a9",
    "addr:street":"Wellington St W",
    "iso:country":"CA",
    "sg:address":"1284 Wellington St W",
    "sg:city":"Ottawa",
    "sg:classifiers":[
        {
            "category":"Real Estate",
            "subcategory":"Real Estate Operator",
            "type":"Services"
        }
    ],
    "sg:phone":"+1 613 729 0656",
    "sg:postcode":"K1Y 3A9",
    "sg:province":"ON",
    "sg:tags":[
        "apartment"
    ],
    "wof:name":"Osgoode Properties Ltd",
    "wof:placetype":"venue"
},
  "geometry": {"coordinates":[-75.73514556879999,45.3989105225],"type":"Point"}
}