{
  "type": "Feature",
  "properties": {
    "addr:full":"1250 Rue Saint-Alexandre Montreal QC H3B 3H5",
    "addr:housenumber":"1250",
    "addr:postcode":"h3b 3h5",
    "addr:street":"Rue Saint-Alexandre",
    "iso:country":"CA",
    "sg:address":"1250 Rue Saint-Alexandre",
    "sg:city":"Montreal",
    "sg:classifiers":[
        {
            "category":"Manufacturing",
            "subcategory":"Apparel",
            "type":"Manufacturing & Wholesale Goods"
        }
    ],
    "sg:phone":"+1 514 866 4891",
    "sg:postcode":"H3B 3H5",
    "sg:province":"QC",
    "sg:tags":[
        "clothing"
    ],
    "wof:name":"Jack Victor Ltd",
    "wof:placetype":"venue"
},
  "geometry": {"coordinates":[-73.5671463013,45.5049362183],"type":"Point"}
}