{
  "type": "Feature",
  "properties": {
    "iso:country":"CA",
    "sg:city":"Montreal",
    "sg:classifiers":[
        {
            "category":"Travel",
            "subcategory":"Travel Agent",
            "type":"Entertainment"
        }
    ],
    "sg:phone":"+1 514 849 1419",
    "sg:postcode":"H2W 2M5",
    "sg:province":"QC",
    "sg:tags":[
        "agency",
        "bureau"
    ],
    "wof:name":"Octopus Voyages Inc",
    "wof:placetype":"venue"
},
  "geometry": {"coordinates":[-73.5771484375,45.5211868286],"type":"Point"}
}