{
  "type": "Feature",
  "properties": {
    "addr:full":"1721 Rue Meloche Saint-Luc QC J2W 1Z9",
    "addr:housenumber":"1721",
    "addr:postcode":"j2w 1z9",
    "addr:street":"Rue Meloche",
    "iso:country":"CA",
    "sg:address":"1721 Rue Meloche",
    "sg:city":"Saint-Luc",
    "sg:classifiers":[
        {
            "category":"Professional",
            "subcategory":"Business Services",
            "type":"Services"
        }
    ],
    "sg:phone":"+1 450 349 6231",
    "sg:postcode":"J2W 1Z9",
    "sg:province":"QC",
    "sg:tags":[
        "pool",
        "swimming"
    ],
    "wof:name":"Clinique DE Piscine Bruno",
    "wof:placetype":"venue"
},
  "geometry": {"coordinates":[-73.2526473999,45.3791007996],"type":"Point"}
}