{
  "type": "Feature",
  "properties": {
    "addr:full":"329 Cumberland Ave # 202 Winnipeg MB R3B 1T2",
    "addr:housenumber":"329",
    "addr:postcode":"r3b 1t2",
    "addr:street":"Cumberland Ave # 202",
    "iso:country":"CA",
    "sg:address":"329 Cumberland Ave # 202",
    "sg:city":"Winnipeg",
    "sg:classifiers":[
        {
            "category":"Home & Garden",
            "subcategory":"Furniture",
            "type":"Retail Goods"
        }
    ],
    "sg:phone":"+1 204 944 8222",
    "sg:postcode":"R3B 1T2",
    "sg:province":"MB",
    "sg:tags":[
        "equipment",
        "kitchen",
        "cabinet"
    ],
    "wof:name":"Kitchen Designs By Decor",
    "wof:placetype":"venue"
},
  "geometry": {"coordinates":[-97.145203,49.896118],"type":"Point"}
}