{
  "type": "Feature",
  "properties": {
    "addr:full":"13335 146 St NW Edmonton AB T5L 4S8",
    "addr:housenumber":"13335",
    "addr:postcode":"t5l 4s8",
    "addr:street":"146 St Nw",
    "iso:country":"CA",
    "sg:address":"13335 146 St NW",
    "sg:city":"Edmonton",
    "sg:classifiers":[
        {
            "category":"Home & Garden",
            "subcategory":"Furniture",
            "type":"Retail Goods"
        }
    ],
    "sg:phone":"+1 780 482 2331",
    "sg:postcode":"T5L 4S8",
    "sg:province":"AB",
    "wof:name":"Furniture Alley",
    "wof:placetype":"venue"
},
  "geometry": {"coordinates":[-113.572067,53.593002],"type":"Point"}
}