{
  "type": "Feature",
  "properties": {
    "addr:full":"48 Ch DE LA Grande-Carriere Louiseville QC J5V 2J7",
    "addr:housenumber":"48",
    "addr:postcode":"j5v 2j7",
    "addr:street":"Ch De La Grande-Carriere",
    "iso:country":"CA",
    "sg:address":"48 Ch DE LA Grande-Carriere",
    "sg:city":"Louiseville",
    "sg:classifiers":[
        {
            "category":"Home & Garden",
            "subcategory":"Building Materials",
            "type":"Retail Goods"
        }
    ],
    "sg:phone":"+1 819 228 1888",
    "sg:postcode":"J5V 2J7",
    "sg:province":"QC",
    "sg:tags":[
        "glass",
        "window",
        "plate"
    ],
    "wof:name":"Lebeau Vitres D'Autos",
    "wof:placetype":"venue"
},
  "geometry": {"coordinates":[-72.9553909302,46.2567558289],"type":"Point"}
}