{
  "type": "Feature",
  "properties": {
    "iso:country":"CA",
    "sg:city":"Sherwood Park",
    "sg:classifiers":[
        {
            "category":"Professional",
            "subcategory":"Employment Agencies",
            "type":"Services"
        }
    ],
    "sg:phone":"+1 780 416 4100",
    "sg:postcode":"T8A 6H2",
    "sg:province":"AB",
    "sg:tags":[
        "opportunity"
    ],
    "wof:name":"L P Kurach & Assoc",
    "wof:placetype":"venue"
},
  "geometry": {"coordinates":[-113.320930481,53.5362892151],"type":"Point"}
}