{
  "type": "Feature",
  "properties": {
    "addr:full":"201 Church St Toronto ON M5B 1Y7",
    "addr:housenumber":"201",
    "addr:postcode":"m5b 1y7",
    "addr:street":"Church St",
    "iso:country":"CA",
    "sg:address":"201 Church St",
    "sg:city":"Toronto",
    "sg:classifiers":[
        {
            "category":"Manufacturing",
            "subcategory":"Musical Instruments",
            "type":"Manufacturing & Wholesale Goods"
        }
    ],
    "sg:phone":"+1 416 363 0093",
    "sg:postcode":"M5B 1Y7",
    "sg:province":"ON",
    "sg:tags":[
        "violin",
        "maker"
    ],
    "wof:name":"George Heinl & CO Ltd",
    "wof:placetype":"venue"
},
  "geometry": {"coordinates":[-79.37651062010001,43.6554908752],"type":"Point"}
}