{
  "type": "Feature",
  "properties": {
    "addr:full":"1285 Montclair Dr Oakville ON L6H 1Z3",
    "addr:housenumber":"1285",
    "addr:postcode":"l6h 1z3",
    "addr:street":"Montclair Dr",
    "iso:country":"CA",
    "sg:address":"1285 Montclair Dr",
    "sg:city":"Oakville",
    "sg:classifiers":[
        {
            "category":"Education",
            "subcategory":"School",
            "type":"Public Place"
        }
    ],
    "sg:phone":"+1 905 845 9590",
    "sg:postcode":"L6H 1Z3",
    "sg:province":"ON",
    "wof:name":"Montclair Elementary School",
    "wof:placetype":"venue"
},
  "geometry": {"coordinates":[-79.699417,43.463043],"type":"Point"}
}