{
  "type": "Feature",
  "properties": {
    "addr:full":"Brampton ON L6W 4P6",
    "addr:postcode":"l6w 4p6",
    "iso:country":"CA",
    "sg:city":"Brampton",
    "sg:classifiers":[
        {
            "category":"Professional",
            "subcategory":"Lawyer & Legal Services",
            "type":"Services"
        }
    ],
    "sg:phone":"+1 905 459 8281",
    "sg:postcode":"L6W 4P6",
    "sg:province":"ON",
    "sg:tags":[
        "attorney"
    ],
    "wof:name":"Kelday, Eric M",
    "wof:placetype":"venue"
},
  "geometry": {"coordinates":[-79.72058105470001,43.6618347168],"type":"Point"}
}