{
  "type": "Feature",
  "properties": {
    "addr:full":"85 York St London ON N6A 1A6",
    "addr:housenumber":"85",
    "addr:postcode":"n6a 1a6",
    "addr:street":"York St",
    "iso:country":"CA",
    "sg:address":"85 York St",
    "sg:city":"London",
    "sg:classifiers":[
        {
            "category":"Manufacturing",
            "subcategory":"Printing",
            "type":"Manufacturing & Wholesale Goods"
        }
    ],
    "sg:phone":"+1 519 673 1002",
    "sg:postcode":"N6A 1A6",
    "sg:province":"ON",
    "sg:tags":[
        "printer"
    ],
    "wof:name":"Print Three",
    "wof:placetype":"venue"
},
  "geometry": {"coordinates":[-81.2515792847,42.9803199768],"type":"Point"}
}