{
  "type": "Feature",
  "properties": {
    "addr:full":"640 King St E Oshawa ON L1H 1G5",
    "addr:housenumber":"640",
    "addr:postcode":"l1h 1g5",
    "addr:street":"King St E",
    "iso:country":"CA",
    "sg:address":"640 King St E",
    "sg:city":"Oshawa",
    "sg:classifiers":[
        {
            "category":"Manufacturing",
            "subcategory":"Printing",
            "type":"Manufacturing & Wholesale Goods"
        }
    ],
    "sg:phone":"+1 905 579 4071",
    "sg:postcode":"L1H 1G5",
    "sg:province":"ON",
    "sg:tags":[
        "printer"
    ],
    "wof:name":"Skali Print",
    "wof:placetype":"venue"
},
  "geometry": {"coordinates":[-78.8407821655,43.903011322],"type":"Point"}
}