{
  "type": "Feature",
  "properties": {
    "addr:full":"12625 Rue Sherbrooke O Pointe-Aux-Trembles QC H1B 1C8",
    "addr:housenumber":"12625",
    "addr:postcode":"h1b 1c8",
    "addr:street":"Rue Sherbrooke O",
    "iso:country":"CA",
    "sg:address":"12625 Rue Sherbrooke O",
    "sg:city":"Pointe-Aux-Trembles",
    "sg:classifiers":[
        {
            "category":"Autos & Motor Vehicles",
            "subcategory":"Auto Supplies",
            "type":"Retail Goods"
        }
    ],
    "sg:phone":"+1 514 645 2761",
    "sg:postcode":"H1B 1C8",
    "sg:province":"QC",
    "sg:tags":[
        "repairing",
        "exhaust",
        "automobile",
        "system",
        "parts",
        "muffler"
    ],
    "wof:name":"Canadian Tire",
    "wof:placetype":"venue"
},
  "geometry": {"coordinates":[-73.5113525391,45.651927948],"type":"Point"}
}