{
  "type": "Feature",
  "properties": {
    "addr:full":"Woodbridge ON L4L 6C9",
    "addr:postcode":"l4l 6c9",
    "iso:country":"CA",
    "sg:city":"Woodbridge",
    "sg:classifiers":[
        {
            "category":"Retail",
            "subcategory":"Car Wash",
            "type":"Services"
        }
    ],
    "sg:phone":"+1 905 265 2314",
    "sg:postcode":"L4L 6C9",
    "sg:province":"ON",
    "sg:tags":[
        "automobile",
        "detail",
        "clean"
    ],
    "wof:name":"Sparkles Auto Salon Inc",
    "wof:placetype":"venue"
},
  "geometry": {"coordinates":[-79.5523986816,43.7850990295],"type":"Point"}
}