{
  "type": "Feature",
  "properties": {
    "addr:full":"33 Newcastle St Etobicoke ON M8Y 1A2",
    "addr:housenumber":"33",
    "addr:postcode":"m8y 1a2",
    "addr:street":"Newcastle St",
    "iso:country":"CA",
    "sg:address":"33 Newcastle St",
    "sg:city":"Etobicoke",
    "sg:classifiers":[
        {
            "category":"Retail",
            "subcategory":"Auto Repair",
            "type":"Services"
        }
    ],
    "sg:phone":"+1 416 251 4488",
    "sg:postcode":"M8Y 1A2",
    "sg:province":"ON",
    "sg:tags":[
        "body",
        "automobile",
        "painting"
    ],
    "wof:name":"Maple & Palm Body Shop",
    "wof:placetype":"venue"
},
  "geometry": {"coordinates":[-79.49663543699999,43.6178665161],"type":"Point"}
}