{
  "type": "Feature",
  "properties": {
    "addr:full":"904 Rue Sainte-Julie Trois-Rivieres QC G9A 1Y2",
    "addr:housenumber":"904",
    "addr:postcode":"g9a 1y2",
    "addr:street":"Rue Sainte-Julie Trois-Rivieres",
    "iso:country":"CA",
    "sg:address":"904 Rue Sainte-Julie",
    "sg:city":"Trois-Rivieres",
    "sg:classifiers":[
        {
            "category":"Health Services",
            "subcategory":"Nursing And Care Facility",
            "type":"Services"
        }
    ],
    "sg:phone":"+1 819 370 4993",
    "sg:postcode":"G9A 1Y2",
    "sg:province":"QC",
    "sg:tags":[
        "home",
        "retirement",
        "community"
    ],
    "wof:name":"Residences Ste Julie Inc",
    "wof:placetype":"venue"
},
  "geometry": {"coordinates":[-72.5467300415,46.348651886],"type":"Point"}
}