{
  "type": "Feature",
  "properties": {
    "addr:full":"1303 73 Ave SW Calgary AB T2V 0R9",
    "addr:housenumber":"1303",
    "addr:postcode":"t2v 0r9",
    "addr:street":"73 Ave Sw",
    "iso:country":"CA",
    "sg:address":"1303 73 Ave SW",
    "sg:city":"Calgary",
    "sg:classifiers":[
        {
            "category":"Mining & Drilling",
            "type":"Manufacturing & Wholesale Goods"
        }
    ],
    "sg:phone":"+1 403 252 2091",
    "sg:postcode":"T2V 0R9",
    "sg:province":"AB",
    "sg:tags":[
        "development",
        "gas",
        "oil",
        "exploration"
    ],
    "wof:name":"Wigham Resources Ltd",
    "wof:placetype":"venue"
},
  "geometry": {"coordinates":[-114.090828,50.987282],"type":"Point"}
}