{
  "type": "Feature",
  "properties": {
    "addr:full":"47280 Thornton Rd Chilliwack BC V2R 4S9",
    "addr:housenumber":"47280",
    "addr:postcode":"v2r 4s9",
    "addr:street":"Thornton Rd",
    "iso:country":"CA",
    "sg:address":"47280 Thornton Rd",
    "sg:city":"Chilliwack",
    "sg:classifiers":[
        {
            "category":"Building & Trades",
            "subcategory":"Construction",
            "type":"Services"
        }
    ],
    "sg:phone":"+1 604 858 3899",
    "sg:postcode":"V2R 4S9",
    "sg:province":"BC",
    "sg:tags":[
        "general",
        "contractor"
    ],
    "wof:name":"Meeres Brothers Construction",
    "wof:placetype":"venue"
},
  "geometry": {"coordinates":[-121.91653442400001,49.0956916809],"type":"Point"}
}