{
  "type": "Feature",
  "properties": {
    "addr:full":"7295 Av Bloomfield Montreal QC H3N 2H1",
    "addr:housenumber":"7295",
    "addr:postcode":"h3n 2h1",
    "addr:street":"Av Bloomfield",
    "iso:country":"CA",
    "sg:address":"7295 Av Bloomfield",
    "sg:city":"Montreal",
    "sg:classifiers":[
        {
            "category":"Bars & Pubs",
            "type":"Food & Drink"
        }
    ],
    "sg:phone":"+1 514 274 9168",
    "sg:postcode":"H3N 2H1",
    "sg:province":"QC",
    "sg:tags":[
        "lounge",
        "cocktail"
    ],
    "wof:name":"New Akropolis Cafe",
    "wof:placetype":"venue"
},
  "geometry": {"coordinates":[-73.625336,45.527912],"type":"Point"}
}