{
  "type": "Feature",
  "properties": {
    "addr:full":"Toronto ON M5B 2H9",
    "addr:postcode":"m5b 2h9",
    "iso:country":"CA",
    "sg:city":"Toronto",
    "sg:classifiers":[
        {
            "category":"Restaurant",
            "type":"Food & Drink"
        }
    ],
    "sg:phone":"+1 416 595 1569",
    "sg:postcode":"M5B 2H9",
    "sg:province":"ON",
    "wof:name":"Subway Sandwiches & Salads",
    "wof:placetype":"venue"
},
  "geometry": {"coordinates":[-79.38069915769999,43.6614227295],"type":"Point"}
}