{
  "type": "Feature",
  "properties": {
    "iso:country":"CA",
    "sg:address":"20 Pineway Blvd",
    "sg:city":"North York",
    "sg:classifiers":[
        {
            "category":"Real Estate",
            "subcategory":"Architect",
            "type":"Services"
        }
    ],
    "sg:phone":"+1 416 222 2639",
    "sg:postcode":"M2H 1A1",
    "sg:province":"ON",
    "wof:name":"Takvor, Hopyan",
    "wof:placetype":"venue"
},
  "geometry": {"coordinates":[-79.3736572266,43.7908821106],"type":"Point"}
}