{
  "type": "Feature",
  "properties": {
    "addr:full":"580 Woodville Rd Woodville ON K0M 2T0",
    "addr:housenumber":"580",
    "addr:postcode":"k0m 2t0",
    "addr:street":"Woodville Rd",
    "iso:country":"CA",
    "sg:address":"580 Woodville Rd",
    "sg:city":"Woodville",
    "sg:classifiers":[
        {
            "category":"Wholesale",
            "subcategory":"Farm Supplies",
            "type":"Manufacturing & Wholesale Goods"
        }
    ],
    "sg:phone":"+1 705 439 4444",
    "sg:postcode":"K0M 2T0",
    "sg:province":"ON",
    "sg:tags":[
        "livestock"
    ],
    "wof:name":"Kawartha Lakes Cooperative Inc",
    "wof:placetype":"venue"
},
  "geometry": {"coordinates":[-78.956703,44.405941],"type":"Point"}
}