{
  "type": "Feature",
  "properties": {
    "addr:full":"581 Mcgeachie Dr Milton ON L9T 3L5",
    "addr:housenumber":"581",
    "addr:postcode":"l9t 3l5",
    "addr:street":"Mcgeachie Dr",
    "iso:country":"CA",
    "sg:address":"581 Mcgeachie Dr",
    "sg:city":"Milton",
    "sg:classifiers":[
        {
            "category":"Wholesale",
            "subcategory":"Durable Goods & Equipment",
            "type":"Manufacturing & Wholesale Goods"
        }
    ],
    "sg:phone":"+1 905 878 8860",
    "sg:postcode":"L9T 3L5",
    "sg:province":"ON",
    "sg:tags":[
        "importer"
    ],
    "wof:name":"Mdm Sales Ltd",
    "wof:placetype":"venue"
},
  "geometry": {"coordinates":[-79.889977,43.530102],"type":"Point"}
}