{
  "type": "Feature",
  "properties": {
    "iso:country":"CA",
    "sg:address":"6240 Portland St",
    "sg:city":"Burnaby",
    "sg:classifiers":[
        {
            "category":"Home & Garden",
            "subcategory":"Carpets & Floor Coverings",
            "type":"Retail Goods"
        }
    ],
    "sg:phone":"+1 604 419 4441",
    "sg:postcode":"V5J 2S2",
    "sg:province":"BC",
    "sg:tags":[
        "dealer",
        "rug"
    ],
    "wof:name":"Global Rugs",
    "wof:placetype":"venue"
},
  "geometry": {"coordinates":[-122.972854614,49.211807251],"type":"Point"}
}