{
  "type": "Feature",
  "properties": {
    "addr:full":"5682 Ch DE Chambly Saint-Hubert QC J3Y 3P7",
    "addr:postcode":"5682;j3y 3p7",
    "addr:street":"Ch De Chambly",
    "iso:country":"CA",
    "sg:address":"5682 Ch DE Chambly",
    "sg:city":"Saint-Hubert",
    "sg:classifiers":[
        {
            "category":"Education",
            "subcategory":"Dance Studio",
            "type":"Public Place"
        }
    ],
    "sg:phone":"+1 450 926 0122",
    "sg:postcode":"J3Y 3P7",
    "sg:province":"QC",
    "sg:tags":[
        "instruction",
        "dancing"
    ],
    "wof:name":"Ecole DE Sanse Qualogic",
    "wof:placetype":"venue"
},
  "geometry": {"coordinates":[-73.41351299999999,45.500988],"type":"Point"}
}