{
  "type": "Feature",
  "properties": {
    "addr:full":"15160 Boul Lacroix Saint-Georges QC G5Y 1R7",
    "addr:housenumber":"15160",
    "addr:postcode":"g5y 1r7",
    "addr:street":"Boul Lacroix",
    "iso:country":"CA",
    "sg:address":"15160 Boul Lacroix",
    "sg:city":"Saint-Georges",
    "sg:classifiers":[
        {
            "category":"Manufacturing",
            "subcategory":"Tools & Machinery",
            "type":"Manufacturing & Wholesale Goods"
        }
    ],
    "sg:phone":"+1 418 228 5512",
    "sg:postcode":"G5Y 1R7",
    "sg:province":"QC",
    "sg:tags":[
        "bearing"
    ],
    "wof:name":"Roulement A Billes Morin Inc",
    "wof:placetype":"venue"
},
  "geometry": {"coordinates":[-70.655304,46.10688],"type":"Point"}
}