{
  "type": "Feature",
  "properties": {
    "addr:full":"201 Deacon St Pembroke ON K8A 2J6",
    "addr:housenumber":"201",
    "addr:postcode":"k8a 2j6",
    "addr:street":"Deacon St",
    "iso:country":"CA",
    "sg:address":"201 Deacon St",
    "sg:city":"Pembroke",
    "sg:classifiers":[
        {
            "category":"Shopping",
            "subcategory":"Pharmacy",
            "type":"Retail Goods"
        }
    ],
    "sg:phone":"+1 613 735 0161",
    "sg:postcode":"K8A 2J6",
    "sg:province":"ON",
    "wof:name":"Mulvihill Drug Mart",
    "wof:placetype":"venue"
},
  "geometry": {"coordinates":[-77.107201,45.813793],"type":"Point"}
}