{
  "type": "Feature",
  "properties": {
    "addr:full":"Gloucester ON K1V 0R4",
    "addr:postcode":"k1v 0r4",
    "iso:country":"CA",
    "sg:city":"Gloucester",
    "sg:classifiers":[
        {
            "category":"Real Estate",
            "subcategory":"Real Estate Agent",
            "type":"Services"
        }
    ],
    "sg:phone":"+1 613 248 8256",
    "sg:postcode":"K1V 0R4",
    "sg:province":"ON",
    "sg:tags":[
        "management"
    ],
    "wof:name":"Aero Term",
    "wof:placetype":"venue"
},
  "geometry": {"coordinates":[-75.6520614624,45.3266906738],"type":"Point"}
}