{
  "type": "Feature",
  "properties": {
    "addr:full":"55 Rue Du Firmament Hull QC J9A 3J1",
    "addr:housenumber":"55",
    "addr:postcode":"j9a 3j1",
    "addr:street":"Rue Du Firmament",
    "iso:country":"CA",
    "sg:address":"55 Rue Du Firmament",
    "sg:city":"Hull",
    "sg:classifiers":[
        {
            "category":"Food & Beverages",
            "subcategory":"Specialty",
            "type":"Retail Goods"
        }
    ],
    "sg:phone":"+1 819 595 9308",
    "sg:postcode":"J9A 3J1",
    "sg:province":"QC",
    "sg:tags":[
        "game",
        "venison",
        "bird"
    ],
    "wof:name":"Diament Gastronomie",
    "wof:placetype":"venue"
},
  "geometry": {"coordinates":[-75.78546142579999,45.4392318726],"type":"Point"}
}