{
  "type": "Feature",
  "properties": {
    "addr:full":"15585 24 Ave # 201 Surrey BC V4A 2J4",
    "addr:housenumber":"15585",
    "addr:postcode":"v4a 2j4",
    "addr:street":"24 Ave # 201",
    "iso:country":"CA",
    "sg:address":"15585 24 Ave # 201",
    "sg:city":"Surrey",
    "sg:classifiers":[
        {
            "category":"Professional",
            "subcategory":"Engineering",
            "type":"Services"
        }
    ],
    "sg:phone":"+1 604 538 0764",
    "sg:postcode":"V4A 2J4",
    "sg:province":"BC",
    "sg:tags":[
        "engineer"
    ],
    "wof:name":"Jade West Engineering CO",
    "wof:placetype":"venue"
},
  "geometry": {"coordinates":[-122.79083300000001,49.045723],"type":"Point"}
}