{
  "type": "Feature",
  "properties": {
    "iso:country":"CA",
    "sg:address":"5789 Perth St",
    "sg:city":"Richmond",
    "sg:classifiers":[
        {
            "category":"Autos & Motor Vehicles",
            "subcategory":"Fuel & Gas Station",
            "type":"Retail Goods"
        }
    ],
    "sg:phone":"+1 613 838 4291",
    "sg:postcode":"K0A 2Z0",
    "sg:province":"ON",
    "sg:tags":[
        "oil"
    ],
    "wof:name":"Drummond's Gas",
    "wof:placetype":"venue"
},
  "geometry": {"coordinates":[-75.8249130249,45.203453064],"type":"Point"}
}