{
  "type": "Feature",
  "properties": {
    "addr:full":"PO Box 4519 STN Main Ponoka AB T4J 1S1",
    "addr:housenumber":"po",
    "addr:postcode":"4519;t4j 1s1",
    "addr:street":"Box;Stn Main",
    "iso:country":"CA",
    "sg:address":"PO Box 4519 STN Main",
    "sg:city":"Ponoka",
    "sg:classifiers":[
        {
            "category":"Manufacturing",
            "subcategory":"Building Materials",
            "type":"Manufacturing & Wholesale Goods"
        }
    ],
    "sg:phone":"+1 403 783 5950",
    "sg:postcode":"T4J 1S1",
    "sg:province":"AB",
    "wof:name":"Blessing & Sons Distributors",
    "wof:placetype":"venue"
},
  "geometry": {"coordinates":[-113.59097300000001,52.676075],"type":"Point"}
}