{
  "type": "Feature",
  "properties": {
    "addr:full":"PO Box 766 Provost AB T0B 3S0",
    "addr:housenumber":"po;766;ab",
    "addr:postcode":"t0b 3s0",
    "addr:street":"Box;Provost",
    "iso:country":"CA",
    "sg:address":"PO Box 766",
    "sg:city":"Provost",
    "sg:classifiers":[
        {
            "category":"Mining & Drilling",
            "type":"Manufacturing & Wholesale Goods"
        }
    ],
    "sg:phone":"+1 780 753 2569",
    "sg:postcode":"T0B 3S0",
    "sg:province":"AB",
    "sg:tags":[
        "field",
        "oil"
    ],
    "wof:name":"Al's Truck Svc Ltd",
    "wof:placetype":"venue"
},
  "geometry": {"coordinates":[-110.268295288,52.3611373901],"type":"Point"}
}