{
  "type": "Feature",
  "properties": {
    "addr:full":"1114 12 Ave SW Calgary AB T2R 0J7",
    "addr:housenumber":"1114",
    "addr:postcode":"t2r 0j7",
    "addr:street":"12 Ave Sw",
    "iso:country":"CA",
    "sg:address":"1114 12 Ave SW",
    "sg:city":"Calgary",
    "sg:classifiers":[
        {
            "category":"Professional",
            "subcategory":"Art Services",
            "type":"Services"
        }
    ],
    "sg:phone":"+1 403 228 1445",
    "sg:postcode":"T2R 0J7",
    "sg:province":"AB",
    "sg:tags":[
        "graphic",
        "designer"
    ],
    "wof:name":"Metrographics",
    "wof:placetype":"venue"
},
  "geometry": {"coordinates":[-114.086967,51.042221],"type":"Point"}
}