{
  "type": "Feature",
  "properties": {
    "addr:full":"793 Boul Quebec Rouyn-Noranda QC J9X 7B2",
    "addr:housenumber":"793",
    "addr:postcode":"j9x 7b2",
    "addr:street":"Boul Quebec",
    "iso:country":"CA",
    "sg:address":"793 Boul Quebec",
    "sg:city":"Rouyn-Noranda",
    "sg:classifiers":[
        {
            "category":"Home & Garden",
            "subcategory":"Building Materials",
            "type":"Retail Goods"
        }
    ],
    "sg:phone":"+1 819 797 2336",
    "sg:postcode":"J9X 7B2",
    "sg:province":"QC",
    "sg:tags":[
        "glass",
        "window",
        "plate"
    ],
    "wof:name":"Duro Vitres & Acces D'Autos",
    "wof:placetype":"venue"
},
  "geometry": {"coordinates":[-79.02536000000001,48.221851],"type":"Point"}
}