{
  "type": "Feature",
  "properties": {
    "addr:full":"1640 Fanshawe Park Rd W London ON N6H 5K9",
    "addr:housenumber":"1640",
    "addr:postcode":"n6h 5k9",
    "addr:street":"Fanshawe Park Rd W",
    "iso:country":"CA",
    "sg:address":"1640 Fanshawe Park Rd W",
    "sg:city":"London",
    "sg:classifiers":[
        {
            "category":"Home & Garden",
            "subcategory":"Building Materials",
            "type":"Retail Goods"
        }
    ],
    "sg:phone":"+1 519 472 3648",
    "sg:postcode":"N6H 5K9",
    "sg:province":"ON",
    "wof:name":"Copp's Buildall",
    "wof:placetype":"venue"
},
  "geometry": {"coordinates":[-81.34446699999999,43.008446],"type":"Point"}
}