{
  "type": "Feature",
  "properties": {
    "iso:country":"CA",
    "sg:address":"1640 Fanshawe Park Rd W",
    "sg:city":"London",
    "sg:classifiers":[
        {
            "category":"Home & Garden",
            "subcategory":"Building Materials",
            "type":"Retail Goods"
        }
    ],
    "sg:phone":"+1 519 472 3648",
    "sg:postcode":"N6H 5K9",
    "sg:province":"ON",
    "wof:name":"Copp's Buildall",
    "wof:placetype":"venue"
},
  "geometry": {"coordinates":[-81.344467,43.008446],"type":"Point"}
}