{
  "type": "Feature",
  "properties": {
    "iso:country":"CA",
    "sg:city":"Windsor",
    "sg:classifiers":[
        {
            "category":"Manufacturing",
            "subcategory":"Rubber & Plastics",
            "type":"Manufacturing & Wholesale Goods"
        }
    ],
    "sg:phone":"+1 519 251 0532",
    "sg:postcode":"N8W 5X2",
    "sg:province":"ON",
    "wof:name":"Dix Plastix",
    "wof:placetype":"venue"
},
  "geometry": {"coordinates":[-82.96472930909999,42.2862892151],"type":"Point"}
}