{
  "type": "Feature",
  "properties": {
    "addr:full":"Winnipeg MB R3C 1L8",
    "addr:postcode":"r3c 1l8",
    "iso:country":"CA",
    "sg:city":"Winnipeg",
    "sg:classifiers":[
        {
            "category":"Social Services",
            "type":"Services"
        }
    ],
    "sg:phone":"+1 204 943 3741",
    "sg:postcode":"R3C 1L8",
    "sg:province":"MB",
    "sg:tags":[
        "counselor",
        "marriage",
        "family"
    ],
    "wof:name":"Steinbart, Murray",
    "wof:placetype":"venue"
},
  "geometry": {"coordinates":[-97.1391983032,49.8860931396],"type":"Point"}
}