{
  "type": "Feature",
  "properties": {
    "addr:full":"37 Stover St S Norwich ON N0J 1P0",
    "addr:housenumber":"37",
    "addr:postcode":"n0j 1p0",
    "addr:street":"Stover St S",
    "iso:country":"CA",
    "sg:address":"37 Stover St S",
    "sg:city":"Norwich",
    "sg:classifiers":[
        {
            "category":"Shopping",
            "subcategory":"Florist",
            "type":"Retail Goods"
        }
    ],
    "sg:phone":"+1 519 863 3704",
    "sg:postcode":"N0J 1P0",
    "sg:province":"ON",
    "wof:name":"Jack's Flowers & Shrubs",
    "wof:placetype":"venue"
},
  "geometry": {"coordinates":[-80.596283,42.984127],"type":"Point"}
}