{
  "type": "Feature",
  "properties": {
    "addr:full":"3095 Regional Rd 5 Ashburn ON L0B 1A0",
    "addr:housenumber":"3095",
    "addr:postcode":"l0b 1a0",
    "addr:street":"Regional Rd 5",
    "iso:country":"CA",
    "sg:address":"3095 Regional Rd 5",
    "sg:city":"Ashburn",
    "sg:classifiers":[
        {
            "category":"Manufacturing",
            "subcategory":"Metals",
            "type":"Manufacturing & Wholesale Goods"
        }
    ],
    "sg:phone":"+1 905 649 3340",
    "sg:postcode":"L0B 1A0",
    "sg:province":"ON",
    "sg:tags":[
        "gates"
    ],
    "wof:name":"Jordan Iron Dreams",
    "wof:placetype":"venue"
},
  "geometry": {"coordinates":[-79.0022735596,44.0168113708],"type":"Point"}
}