{
  "type": "Feature",
  "properties": {
    "addr:full":"517 Richmond St E Toronto ON M5A 1R4",
    "addr:housenumber":"517",
    "addr:postcode":"m5a 1r4",
    "addr:street":"Richmond St E",
    "iso:country":"CA",
    "sg:address":"517 Richmond St E",
    "sg:city":"Toronto",
    "sg:classifiers":[
        {
            "category":"Manufacturing",
            "subcategory":"Printing",
            "type":"Manufacturing & Wholesale Goods"
        }
    ],
    "sg:phone":"+1 416 368 9483",
    "sg:postcode":"M5A 1R4",
    "sg:province":"ON",
    "sg:tags":[
        "printer"
    ],
    "wof:name":"Foster Printing & Digital Comm",
    "wof:placetype":"venue"
},
  "geometry": {"coordinates":[-79.36441000000001,43.654308],"type":"Point"}
}