{
  "type": "Feature",
  "properties": {
    "addr:full":"39 South Station St York ON M9N 2B2",
    "addr:housenumber":"39",
    "addr:postcode":"m9n 2b2",
    "addr:street":"South Station St",
    "iso:country":"CA",
    "sg:address":"39 South Station St",
    "sg:city":"York",
    "sg:classifiers":[
        {
            "category":"Personal",
            "subcategory":"Beauty Salon",
            "type":"Services"
        }
    ],
    "sg:phone":"+1 416 245 0106",
    "sg:postcode":"M9N 2B2",
    "sg:province":"ON",
    "wof:name":"Lina's Unisex Top Line Haircut",
    "wof:placetype":"venue"
},
  "geometry": {"coordinates":[-79.51577,43.701115],"type":"Point"}
}