{
  "type": "Feature",
  "properties": {
    "addr:full":"577 Kingston Rd Toronto ON M4E 1R3",
    "addr:housenumber":"577",
    "addr:postcode":"m4e 1r3",
    "addr:street":"Kingston Rd",
    "iso:country":"CA",
    "sg:address":"577 Kingston Rd",
    "sg:city":"Toronto",
    "sg:classifiers":[
        {
            "category":"Professional",
            "subcategory":"Art Services",
            "type":"Services"
        }
    ],
    "sg:phone":"+1 416 691 6229",
    "sg:postcode":"M4E 1R3",
    "sg:province":"ON",
    "sg:tags":[
        "graphic",
        "designer"
    ],
    "wof:name":"Vigeon Design & Assoc",
    "wof:placetype":"venue"
},
  "geometry": {"coordinates":[-79.299469,43.678463],"type":"Point"}
}