{
  "type": "Feature",
  "properties": {
    "addr:full":"5304 1A St SE Calgary AB T2H 1J2",
    "addr:housenumber":"5304",
    "addr:postcode":"t2h 1j2",
    "addr:street":"1A St Se",
    "iso:country":"CA",
    "sg:address":"5304 1A St SE",
    "sg:city":"Calgary",
    "sg:classifiers":[
        {
            "category":"Retail",
            "subcategory":"Auto Repair",
            "type":"Services"
        }
    ],
    "sg:phone":"+1 403 253 7867",
    "sg:postcode":"T2H 1J2",
    "sg:province":"AB",
    "sg:tags":[
        "body",
        "automobile",
        "painting"
    ],
    "wof:name":"A-1 Auto Body Ltd",
    "wof:placetype":"venue"
},
  "geometry": {"coordinates":[-114.06120300000001,51.007008],"type":"Point"}
}