{
  "type": "Feature",
  "properties": {
    "addr:full":"Montreal QC H3A 1G8",
    "addr:postcode":"h3a 1g8",
    "iso:country":"CA",
    "sg:city":"Montreal",
    "sg:classifiers":[
        {
            "category":"Wholesale",
            "subcategory":"Groceries",
            "type":"Manufacturing & Wholesale Goods"
        }
    ],
    "sg:phone":"+1 514 842 4052",
    "sg:postcode":"H3A 1G8",
    "sg:province":"QC",
    "sg:tags":[
        "food",
        "broker"
    ],
    "wof:name":"G A Wagner Marketing Inc",
    "wof:placetype":"venue"
},
  "geometry": {"coordinates":[-73.5653839111,45.5215377808],"type":"Point"}
}