{
  "type": "Feature",
  "properties": {
    "addr:full":"100 Rue Richelieu Saint-Jean-Sur-Richelieu QC J3B 6X3",
    "addr:housenumber":"100",
    "addr:postcode":"j3b 6x3",
    "addr:street":"Rue Richelieu",
    "iso:country":"CA",
    "sg:address":"100 Rue Richelieu",
    "sg:city":"Saint-Jean-Sur-Richelieu",
    "sg:classifiers":[
        {
            "category":"Government",
            "subcategory":"Office",
            "type":"Public Place"
        }
    ],
    "sg:phone":"+1 450 346 1468",
    "sg:postcode":"J3B 6X3",
    "sg:province":"QC",
    "wof:name":"Quebec Culture Et Comms",
    "wof:placetype":"venue"
},
  "geometry": {"coordinates":[-73.2509460449,45.3038406372],"type":"Point"}
}