{
  "type": "Feature",
  "properties": {
    "addr:full":"89 Bridge St Sackville NB E4L 3P1",
    "addr:housenumber":"89",
    "addr:postcode":"e4l 3p1",
    "addr:street":"Bridge St",
    "iso:country":"CA",
    "sg:address":"89 Bridge St",
    "sg:city":"Sackville",
    "sg:classifiers":[
        {
            "category":"Retail",
            "subcategory":"Funeral Services",
            "type":"Services"
        }
    ],
    "sg:phone":"+1 506 364 8188",
    "sg:postcode":"E4L 3P1",
    "sg:province":"NB",
    "sg:tags":[
        "director"
    ],
    "wof:name":"Campbell's Funeral Home",
    "wof:placetype":"venue"
},
  "geometry": {"coordinates":[-64.359375,45.896393],"type":"Point"}
}