{
  "type": "Feature",
  "properties": {
    "addr:full":"Saint-Eustache QC J7P 4X4",
    "addr:postcode":"j7p 4x4",
    "iso:country":"CA",
    "sg:city":"Saint-Eustache",
    "sg:classifiers":[
        {
            "category":"Shopping",
            "type":"Retail Goods"
        }
    ],
    "sg:phone":"+1 450 472 8023",
    "sg:postcode":"J7P 4X4",
    "sg:province":"QC",
    "sg:tags":[
        "picture",
        "frame"
    ],
    "wof:name":"Encadrement St-Eustache",
    "wof:placetype":"venue"
},
  "geometry": {"coordinates":[-73.912125,45.571999],"type":"Point"}
}