{
  "type": "Feature",
  "properties": {
    "addr:full":"Ancaster ON L9G 4V5",
    "addr:postcode":"l9g 4v5",
    "iso:country":"CA",
    "sg:city":"Ancaster",
    "sg:classifiers":[
        {
            "category":"Manufacturing",
            "subcategory":"Tools & Machinery",
            "type":"Manufacturing & Wholesale Goods"
        }
    ],
    "sg:phone":"+1 905 648 9262",
    "sg:postcode":"L9G 4V5",
    "sg:province":"ON",
    "sg:tags":[
        "turbine"
    ],
    "wof:name":"Bwd Turbines Ltd",
    "wof:placetype":"venue"
},
  "geometry": {"coordinates":[-80.0302886963,43.1903266907],"type":"Point"}
}