{
  "type": "Feature",
  "properties": {
    "addr:full":"Scarborough ON M1S 1S9",
    "addr:postcode":"m1s 1s9",
    "iso:country":"CA",
    "sg:city":"Scarborough",
    "sg:classifiers":[
        {
            "category":"Restaurant",
            "type":"Food & Drink"
        }
    ],
    "sg:phone":"+1 416 299 9322",
    "sg:postcode":"M1S 1S9",
    "sg:province":"ON",
    "wof:name":"Pearl Vegetarian Ltd",
    "wof:placetype":"venue"
},
  "geometry": {"coordinates":[-79.284431,43.784233],"type":"Point"}
}