{
  "type": "Feature",
  "properties": {
    "iso:country":"CA",
    "sg:city":"Calgary",
    "sg:classifiers":[
        {
            "category":"Manufacturing",
            "subcategory":"Printing",
            "type":"Manufacturing & Wholesale Goods"
        }
    ],
    "sg:phone":"+1 403 219 8579",
    "sg:postcode":"T2E 6L6",
    "sg:province":"AB",
    "sg:tags":[
        "printer"
    ],
    "wof:name":"Northwest Printing & Litho Ltd",
    "wof:placetype":"venue"
},
  "geometry": {"coordinates":[-114.03289032000001,51.0918922424],"type":"Point"}
}