{
  "type": "Feature",
  "properties": {
    "iso:country":"CA",
    "sg:city":"Calgary",
    "sg:classifiers":[
        {
            "category":"Shopping",
            "subcategory":"Stationery & Office Supplies",
            "type":"Retail Goods"
        }
    ],
    "sg:phone":"+1 403 274 1780",
    "sg:postcode":"T2E 7P4",
    "sg:province":"AB",
    "wof:name":"Grand & Toy",
    "wof:placetype":"venue"
},
  "geometry": {"coordinates":[-114.041114807,51.1103439331],"type":"Point"}
}