{
  "type": "Feature",
  "properties": {
    "iso:country":"CA",
    "sg:city":"Holland Centre",
    "sg:classifiers":[
        {
            "category":"Government",
            "subcategory":"Office",
            "type":"Public Place"
        }
    ],
    "sg:phone":"+1 519 794 2313",
    "sg:postcode":"N0H 1R0",
    "sg:province":"ON",
    "sg:tags":[
        "village"
    ],
    "wof:name":"Holland Township Roads Dept",
    "wof:placetype":"venue"
},
  "geometry": {"coordinates":[-80.7940750122,44.3931846619],"type":"Point"}
}