{
  "type": "Feature",
  "properties": {
    "addr:full":"6380 2nd Line Tottenham ON L0G 1W0",
    "addr:housenumber":"6380",
    "addr:postcode":"l0g 1w0",
    "addr:street":"2Nd Line",
    "iso:country":"CA",
    "sg:address":"6380 2nd Line",
    "sg:city":"Tottenham",
    "sg:classifiers":[
        {
            "category":"Home & Garden",
            "subcategory":"Home Furnishings",
            "type":"Retail Goods"
        }
    ],
    "sg:phone":"+1 905 936 6000",
    "sg:postcode":"L0G 1W0",
    "sg:province":"ON",
    "sg:tags":[
        "curtain",
        "made",
        "drapery"
    ],
    "wof:name":"Drapery Den",
    "wof:placetype":"venue"
},
  "geometry": {"coordinates":[-79.805786,44.022877],"type":"Point"}
}