{
  "type": "Feature",
  "properties": {
    "addr:full":"3700 Rue Richelieu Saint-Hubert QC J3Y 7B1",
    "addr:housenumber":"3700",
    "addr:postcode":"j3y 7b1",
    "addr:street":"Rue Richelieu",
    "iso:country":"CA",
    "sg:address":"3700 Rue Richelieu",
    "sg:city":"Saint-Hubert",
    "sg:classifiers":[
        {
            "category":"Building & Trades",
            "subcategory":"Construction",
            "type":"Services"
        }
    ],
    "sg:phone":"+1 450 443 4412",
    "sg:postcode":"J3Y 7B1",
    "sg:province":"QC",
    "sg:tags":[
        "maker",
        "cabinet"
    ],
    "wof:name":"Ebenisterie Dn",
    "wof:placetype":"venue"
},
  "geometry": {"coordinates":[-73.44593,45.500744],"type":"Point"}
}