{
  "type": "Feature",
  "properties": {
    "addr:full":"1113 Rue Victoria LA Baie QC G7B 3N2",
    "addr:housenumber":"1113",
    "addr:postcode":"g7b 3n2",
    "addr:street":"Rue Victoria",
    "iso:country":"CA",
    "sg:address":"1113 Rue Victoria",
    "sg:city":"LA Baie",
    "sg:classifiers":[
        {
            "category":"Food & Beverages",
            "subcategory":"Groceries & Convenience Stores",
            "type":"Retail Goods"
        }
    ],
    "sg:phone":"+1 418 544 2225",
    "sg:postcode":"G7B 3N2",
    "sg:province":"QC",
    "sg:tags":[
        "grocer"
    ],
    "wof:name":"Super Sagamie Baieriverain",
    "wof:placetype":"venue"
},
  "geometry": {"coordinates":[-70.88209533689999,48.3456687927],"type":"Point"}
}