{
  "type": "Feature",
  "properties": {
    "iso:country":"CA",
    "sg:city":"Verdun",
    "sg:classifiers":[
        {
            "category":"Education",
            "subcategory":"School",
            "type":"Public Place"
        }
    ],
    "sg:phone":"+1 514 765 7595",
    "sg:postcode":"H4G 2Z1",
    "sg:province":"QC",
    "wof:name":"Ecole Notre-Dame-DE-Lourdes",
    "wof:placetype":"venue"
},
  "geometry": {"coordinates":[-73.570602417,45.4560813904],"type":"Point"}
}