{
  "type": "Feature",
  "properties": {
    "addr:full":"3049 Jefferson Dr Brockville ON K6V 6N7",
    "addr:housenumber":"3049",
    "addr:postcode":"k6v 6n7",
    "addr:street":"Jefferson Dr",
    "iso:country":"CA",
    "sg:address":"3049 Jefferson Dr",
    "sg:city":"Brockville",
    "sg:classifiers":[
        {
            "category":"Food & Beverages",
            "subcategory":"Groceries & Convenience Stores",
            "type":"Retail Goods"
        }
    ],
    "sg:phone":"+1 613 345 0272",
    "sg:postcode":"K6V 6N7",
    "sg:province":"ON",
    "sg:tags":[
        "grocer"
    ],
    "wof:name":"A & P Food Stores Ltd",
    "wof:placetype":"venue"
},
  "geometry": {"coordinates":[-75.704453,44.599472],"type":"Point"}
}