{
  "type": "Feature",
  "properties": {
    "addr:full":"190 Victoria St N Kitchener ON N2H 5C6",
    "addr:housenumber":"190",
    "addr:postcode":"n2h 5c6",
    "addr:street":"Victoria St N",
    "iso:country":"CA",
    "sg:address":"190 Victoria St N",
    "sg:city":"Kitchener",
    "sg:classifiers":[
        {
            "category":"Building & Trades",
            "subcategory":"Pest Control",
            "type":"Services"
        }
    ],
    "sg:phone":"+1 519 744 9674",
    "sg:postcode":"N2H 5C6",
    "sg:province":"ON",
    "wof:name":"Marshall Pest Control Ltd",
    "wof:placetype":"venue"
},
  "geometry": {"coordinates":[-80.489861,43.456284],"type":"Point"}
}