{
  "type": "Feature",
  "properties": {
    "iso:country":"CA",
    "sg:address":"1401 Boul Talbot",
    "sg:city":"Chicoutimi",
    "sg:classifiers":[
        {
            "category":"Banks & Credit Unions",
            "subcategory":"Investment Brokerage",
            "type":"Services"
        }
    ],
    "sg:phone":"+1 418 543 1377",
    "sg:postcode":"G7H 4C1",
    "sg:province":"QC",
    "sg:tags":[
        "return",
        "consultant",
        "tax",
        "preparation",
        "planning",
        "financial",
        "filing"
    ],
    "wof:name":"Solution Select",
    "wof:placetype":"venue"
},
  "geometry": {"coordinates":[-71.057808,48.404797],"type":"Point"}
}