{
  "type": "Feature",
  "properties": {
    "addr:full":"2604 Kensington Rd NW Calgary AB T2N 3S5",
    "addr:housenumber":"2604",
    "addr:postcode":"t2n 3s5",
    "addr:street":"Kensington Rd Nw",
    "iso:country":"CA",
    "sg:address":"2604 Kensington Rd NW",
    "sg:city":"Calgary",
    "sg:classifiers":[
        {
            "category":"Organizations",
            "subcategory":"Religious Organization",
            "type":"Services"
        }
    ],
    "sg:phone":"+1 403 541 8250",
    "sg:postcode":"T2N 3S5",
    "sg:province":"AB",
    "sg:tags":[
        "church"
    ],
    "wof:name":"Evangel Alliance Church",
    "wof:placetype":"venue"
},
  "geometry": {"coordinates":[-114.120529,51.052521],"type":"Point"}
}