{
  "type": "Feature",
  "properties": {
    "addr:full":"1212 Rue DE L'Eglise Saint-Felix-DE-Kingsey QC J0B 2T0",
    "addr:housenumber":"1212",
    "addr:postcode":"j0b 2t0",
    "addr:street":"Rue De L'Eglise Saint-Felix-De-Kingsey",
    "iso:country":"CA",
    "sg:address":"1212 Rue DE L'Eglise",
    "sg:city":"Saint-Felix-DE-Kingsey",
    "sg:classifiers":[
        {
            "category":"Banks & Credit Unions",
            "subcategory":"Bank",
            "type":"Services"
        }
    ],
    "sg:phone":"+1 819 848 2367",
    "sg:postcode":"J0B 2T0",
    "sg:province":"QC",
    "wof:name":"Caisses Desjardins-St-Felix",
    "wof:placetype":"venue"
},
  "geometry": {"coordinates":[-72.2296829224,45.1519813538],"type":"Point"}
}