{
  "type": "Feature",
  "properties": {
    "addr:full":"4562 Queensway Dr # B Thornhill BC V8G 3X6",
    "addr:housenumber":"4562",
    "addr:postcode":"v8g 3x6",
    "addr:street":"Queensway Dr # B",
    "iso:country":"CA",
    "sg:address":"4562 Queensway Dr # B",
    "sg:city":"Thornhill",
    "sg:classifiers":[
        {
            "category":"Communications",
            "subcategory":"Radio Station",
            "type":"Services"
        }
    ],
    "sg:phone":"+1 250 638 8137",
    "sg:postcode":"V8G 3X6",
    "sg:province":"BC",
    "sg:tags":[
        "company",
        "broadcasting"
    ],
    "wof:name":"Northern Native Broadcasting",
    "wof:placetype":"venue"
},
  "geometry": {"coordinates":[-128.562286,54.511154],"type":"Point"}
}