{
  "type": "Feature",
  "properties": {
    "addr:full":"80 Rue Belleville Drummondville QC J2C 5T1",
    "addr:housenumber":"80",
    "addr:postcode":"j2c 5t1",
    "addr:street":"Rue Belleville",
    "iso:country":"CA",
    "sg:address":"80 Rue Belleville",
    "sg:city":"Drummondville",
    "sg:classifiers":[
        {
            "category":"Government",
            "subcategory":"Office",
            "type":"Public Place"
        }
    ],
    "sg:phone":"+1 819 475 8479",
    "sg:postcode":"J2C 5T1",
    "sg:province":"QC",
    "wof:name":"Societe DE L'Assurance Automob",
    "wof:placetype":"venue"
},
  "geometry": {"coordinates":[-72.522972,45.899387],"type":"Point"}
}