{
  "type": "Feature",
  "properties": {
    "addr:full":"3260 Princess St Kingston ON K7L 4V2",
    "addr:housenumber":"3260",
    "addr:postcode":"k7l 4v2",
    "addr:street":"Princess St",
    "iso:country":"CA",
    "sg:address":"3260 Princess St",
    "sg:city":"Kingston",
    "sg:classifiers":[
        {
            "category":"Organizations",
            "subcategory":"Professional Association",
            "type":"Services"
        }
    ],
    "sg:phone":"+1 613 384 9554",
    "sg:postcode":"K7L 4V2",
    "sg:province":"ON",
    "sg:tags":[
        "club"
    ],
    "wof:name":"Kingston District Shrine Club",
    "wof:placetype":"venue"
},
  "geometry": {"coordinates":[-76.60580400000001,44.26329],"type":"Point"}
}