{
  "type": "Feature",
  "properties": {
    "iso:country":"CA",
    "sg:address":"2555 Arbutus St",
    "sg:city":"Vancouver",
    "sg:classifiers":[
        {
            "category":"Home & Garden",
            "subcategory":"Building Materials",
            "type":"Retail Goods"
        }
    ],
    "sg:phone":"+1 604 731 6505",
    "sg:postcode":"V6J 4S2",
    "sg:province":"BC",
    "sg:tags":[
        "paint"
    ],
    "wof:name":"General Paint Ltd",
    "wof:placetype":"venue"
},
  "geometry": {"coordinates":[-123.15312957800001,49.2633323669],"type":"Point"}
}