{
  "type": "Feature",
  "properties": {
    "addr:full":"616 Main St Humboldt SK S0K 2A0",
    "addr:housenumber":"616",
    "addr:postcode":"s0k 2a0",
    "addr:street":"Main St",
    "iso:country":"CA",
    "sg:address":"616 Main St",
    "sg:city":"Humboldt",
    "sg:classifiers":[
        {
            "category":"Shopping",
            "subcategory":"Florist",
            "type":"Retail Goods"
        }
    ],
    "sg:phone":"+1 306 682 3861",
    "sg:postcode":"S0K 2A0",
    "sg:province":"SK",
    "wof:name":"Humboldt Florist Ltd",
    "wof:placetype":"venue"
},
  "geometry": {"coordinates":[-105.122711,52.199184],"type":"Point"}
}