{
  "type": "Feature",
  "properties": {
    "addr:full":"Richmond BC V7A 4S5",
    "addr:postcode":"v7a 4s5",
    "iso:country":"CA",
    "sg:city":"Richmond",
    "sg:classifiers":[
        {
            "category":"Professional",
            "type":"Services"
        }
    ],
    "sg:phone":"+1 604 275 6500",
    "sg:postcode":"V7A 4S5",
    "sg:province":"BC",
    "sg:tags":[
        "engine",
        "aircraft",
        "establishment"
    ],
    "wof:name":"Aero Turbines Support Ltd",
    "wof:placetype":"venue"
},
  "geometry": {"coordinates":[-123.096085,49.130283],"type":"Point"}
}