{
  "type": "Feature",
  "properties": {
    "iso:country":"CA",
    "sg:address":"945 Rue Etienne-Parent",
    "sg:city":"Laval",
    "sg:classifiers":[
        {
            "category":"Arts & Performance",
            "subcategory":"Theater",
            "type":"Entertainment"
        }
    ],
    "sg:phone":"+1 450 661 9660",
    "sg:postcode":"H7E 3A2",
    "sg:province":"QC",
    "sg:tags":[
        "bureau"
    ],
    "wof:name":"Productions Yves Yanne",
    "wof:placetype":"venue"
},
  "geometry": {"coordinates":[-73.66873931879999,45.60338974],"type":"Point"}
}