{
  "type": "Feature",
  "properties": {
    "addr:full":"83 Rte Grand-Capsa Ste-Catherine-DE-LA-J-Cartier QC G0A 3M0",
    "addr:housenumber":"83",
    "addr:postcode":"g0a 3m0",
    "addr:street":"Rte Grand-Capsa Ste-Catherine-De-La-J-Cartier",
    "iso:country":"CA",
    "sg:address":"83 Rte Grand-Capsa",
    "sg:city":"Ste-Catherine-DE-LA-J-Cartier",
    "sg:classifiers":[
        {
            "category":"Travel",
            "subcategory":"Campground",
            "type":"Entertainment"
        }
    ],
    "sg:phone":"+1 418 875 2583",
    "sg:postcode":"G0A 3M0",
    "sg:province":"QC",
    "sg:tags":[
        "camp"
    ],
    "wof:name":"Domaine Notre Dame Inc",
    "wof:placetype":"venue"
},
  "geometry": {"coordinates":[-71.552071,46.784744],"type":"Point"}
}