{
  "type": "Feature",
  "properties": {
    "addr:full":"Concord ON L4K 4J3",
    "addr:postcode":"l4k 4j3",
    "iso:country":"CA",
    "sg:city":"Concord",
    "sg:classifiers":[
        {
            "category":"Shopping",
            "subcategory":"Gifts & Souvenirs",
            "type":"Retail Goods"
        }
    ],
    "sg:phone":"+1 905 660 1655",
    "sg:postcode":"L4K 4J3",
    "sg:province":"ON",
    "sg:tags":[
        "shop"
    ],
    "wof:name":"Kitco",
    "wof:placetype":"venue"
},
  "geometry": {"coordinates":[-79.5387039185,43.8047523499],"type":"Point"}
}