{
  "type": "Feature",
  "properties": {
    "addr:full":"728 Grandin Dr Morinville AB T8R 1K2",
    "addr:housenumber":"728",
    "addr:postcode":"t8r 1k2",
    "addr:street":"Grandin Dr",
    "iso:country":"CA",
    "sg:address":"728 Grandin Dr",
    "sg:city":"Morinville",
    "sg:classifiers":[
        {
            "category":"Manufacturing",
            "subcategory":"Signs",
            "type":"Manufacturing & Wholesale Goods"
        }
    ],
    "sg:phone":"+1 780 939 2891",
    "sg:postcode":"T8R 1K2",
    "sg:province":"AB",
    "wof:name":"Abcor Signs & Graphics Inc",
    "wof:placetype":"venue"
},
  "geometry": {"coordinates":[-113.629798889,53.8021354675],"type":"Point"}
}