{
  "type": "Feature",
  "properties": {
    "addr:full":"97 Ontario St Stratford ON N5A 3H1",
    "addr:housenumber":"97",
    "addr:postcode":"n5a 3h1",
    "addr:street":"Ontario St",
    "iso:country":"CA",
    "sg:address":"97 Ontario St",
    "sg:city":"Stratford",
    "sg:classifiers":[
        {
            "category":"Professional",
            "subcategory":"Printing & Photocopies",
            "type":"Services"
        }
    ],
    "sg:phone":"+1 519 271 9270",
    "sg:postcode":"N5A 3H1",
    "sg:province":"ON",
    "sg:tags":[
        "duplicating",
        "copying"
    ],
    "wof:name":"H H Delea & CO",
    "wof:placetype":"venue"
},
  "geometry": {"coordinates":[-80.98149100000001,43.371284],"type":"Point"}
}