{
  "type": "Feature",
  "properties": {
    "addr:full":"3535 Ch Gascon Mascouche QC J7L 3X6",
    "addr:postcode":"3535;j7l 3x6",
    "addr:street":"Ch Gascon",
    "iso:country":"CA",
    "sg:address":"3535 Ch Gascon",
    "sg:city":"Mascouche",
    "sg:classifiers":[
        {
            "category":"Retail",
            "subcategory":"Auto Repair",
            "type":"Services"
        }
    ],
    "sg:phone":"+1 450 477 0112",
    "sg:postcode":"J7L 3X6",
    "sg:province":"QC",
    "sg:tags":[
        "repairing",
        "automobile"
    ],
    "wof:name":"Crisci & Freres Inc",
    "wof:placetype":"venue"
},
  "geometry": {"coordinates":[-73.6815338135,45.7353286743],"type":"Point"}
}