{
  "type": "Feature",
  "properties": {
    "addr:full":"12979 80 Ave Surrey BC V3W 3B1",
    "addr:housenumber":"12979",
    "addr:postcode":"v3w 3b1",
    "addr:street":"80 Ave",
    "iso:country":"CA",
    "sg:address":"12979 80 Ave",
    "sg:city":"Surrey",
    "sg:classifiers":[
        {
            "category":"Building & Trades",
            "subcategory":"Electrical",
            "type":"Services"
        }
    ],
    "sg:phone":"+1 604 590 4555",
    "sg:postcode":"V3W 3B1",
    "sg:province":"BC",
    "sg:tags":[
        "electric",
        "contractor"
    ],
    "wof:name":"Can-Tec Electrical Svc Ltd",
    "wof:placetype":"venue"
},
  "geometry": {"coordinates":[-122.862983704,49.1483001709],"type":"Point"}
}