{
  "type": "Feature",
  "properties": {
    "iso:country":"CA",
    "sg:address":"82 Boul St-Pierre O",
    "sg:city":"Caraquet",
    "sg:classifiers":[
        {
            "category":"Banks & Credit Unions",
            "subcategory":"Bank",
            "type":"Services"
        }
    ],
    "sg:phone":"+1 506 726 1133",
    "sg:postcode":"E1W 1B6",
    "sg:province":"NB",
    "wof:name":"Caisse Populaire DE Caraquet",
    "wof:placetype":"venue"
},
  "geometry": {"coordinates":[-64.92520141599999,47.7938919067],"type":"Point"}
}