{
  "type": "Feature",
  "properties": {
    "addr:full":"Woodbridge ON L4L 1T5",
    "addr:postcode":"l4l 1t5",
    "iso:country":"CA",
    "sg:city":"Woodbridge",
    "sg:classifiers":[
        {
            "category":"Retail",
            "subcategory":"Auto Repair",
            "type":"Services"
        }
    ],
    "sg:phone":"+1 905 851 0529",
    "sg:postcode":"L4L 1T5",
    "sg:province":"ON",
    "sg:tags":[
        "body",
        "automobile",
        "painting"
    ],
    "wof:name":"International Auto Collision",
    "wof:placetype":"venue"
},
  "geometry": {"coordinates":[-79.60785675050001,43.7760848999],"type":"Point"}
}