{
  "type": "Feature",
  "properties": {
    "addr:full":"52697 Talbot St E Aylmer ON N5H 2R1",
    "addr:housenumber":"52697",
    "addr:postcode":"n5h 2r1",
    "addr:street":"Talbot St E",
    "iso:country":"CA",
    "sg:address":"52697 Talbot St E",
    "sg:city":"Aylmer",
    "sg:classifiers":[
        {
            "category":"Manufacturing",
            "subcategory":"Food",
            "type":"Manufacturing & Wholesale Goods"
        }
    ],
    "sg:phone":"+1 519 773 9764",
    "sg:postcode":"N5H 2R1",
    "sg:province":"ON",
    "sg:tags":[
        "confectionery",
        "candy"
    ],
    "wof:name":"Terry's Candy Caravan",
    "wof:placetype":"venue"
},
  "geometry": {"coordinates":[-80.97283899999999,42.772781],"type":"Point"}
}