{
  "type": "Feature",
  "properties": {
    "addr:full":"167 Rue DE LA Canipco Gatineau QC J8P 4A9",
    "addr:housenumber":"167",
    "addr:postcode":"j8p 4a9",
    "addr:street":"Rue De La Canipco",
    "iso:country":"CA",
    "sg:address":"167 Rue DE LA Canipco",
    "sg:city":"Gatineau",
    "sg:classifiers":[
        {
            "category":"Social Services",
            "subcategory":"Child Care",
            "type":"Services"
        }
    ],
    "sg:phone":"+1 819 663 7337",
    "sg:postcode":"J8P 4A9",
    "sg:province":"QC",
    "wof:name":"Cpe LA Ciboulette",
    "wof:placetype":"venue"
},
  "geometry": {"coordinates":[-75.6497268677,45.4790992737],"type":"Point"}
}