{
  "type": "Feature",
  "properties": {
    "addr:full":"1250 Stittsville Main St #C14 Stittsville ON K2S 1S9",
    "addr:housenumber":"1250",
    "addr:postcode":"k2s 1s9",
    "addr:street":"Stittsville Main St # C14",
    "iso:country":"CA",
    "sg:address":"1250 Stittsville Main St #C14",
    "sg:city":"Stittsville",
    "sg:classifiers":[
        {
            "category":"Health Services",
            "subcategory":"Doctor",
            "type":"Services"
        }
    ],
    "sg:phone":"+1 613 831 2266",
    "sg:postcode":"K2S 1S9",
    "sg:province":"ON",
    "sg:tags":[
        "dentist"
    ],
    "wof:name":"Khedmat, Gozar M DDS",
    "wof:placetype":"venue"
},
  "geometry": {"coordinates":[-75.930466,45.26886],"type":"Point"}
}