{
  "type": "Feature",
  "properties": {
    "addr:full":"298 Concord Ave Toronto ON M6H 2P6",
    "addr:housenumber":"298",
    "addr:postcode":"m6h 2p6",
    "addr:street":"Concord Ave",
    "iso:country":"CA",
    "sg:address":"298 Concord Ave",
    "sg:city":"Toronto",
    "sg:classifiers":[
        {
            "category":"Personal",
            "subcategory":"Beauty Salon",
            "type":"Services"
        }
    ],
    "sg:phone":"+1 416 536 1701",
    "sg:postcode":"M6H 2P6",
    "sg:province":"ON",
    "sg:tags":[
        "barber"
    ],
    "wof:name":"Angra Barber Shop",
    "wof:placetype":"venue"
},
  "geometry": {"coordinates":[-79.427155,43.662018],"type":"Point"}
}