{
  "type": "Feature",
  "properties": {
    "addr:full":"35 Godfrey St Larder Lake ON P0K 1L0",
    "addr:housenumber":"35",
    "addr:postcode":"p0k 1l0",
    "addr:street":"Godfrey St",
    "iso:country":"CA",
    "sg:address":"35 Godfrey St",
    "sg:city":"Larder Lake",
    "sg:classifiers":[
        {
            "category":"Bars & Pubs",
            "type":"Food & Drink"
        }
    ],
    "sg:phone":"+1 705 643 2113",
    "sg:postcode":"P0K 1L0",
    "sg:province":"ON",
    "wof:name":"Windsor Tavern",
    "wof:placetype":"venue"
},
  "geometry": {"coordinates":[-79.712097,48.0989],"type":"Point"}
}