{
  "type": "Feature",
  "properties": {
    "addr:full":"72 Crosthwaite Ave N Hamilton ON L8H 4V2",
    "addr:housenumber":"72",
    "addr:postcode":"l8h 4v2",
    "addr:street":"Crosthwaite Ave N",
    "iso:country":"CA",
    "sg:address":"72 Crosthwaite Ave N",
    "sg:city":"Hamilton",
    "sg:classifiers":[
        {
            "category":"Building & Trades",
            "subcategory":"Construction",
            "type":"Services"
        }
    ],
    "sg:phone":"+1 905 634 0917",
    "sg:postcode":"L8H 4V2",
    "sg:province":"ON",
    "sg:tags":[
        "painter"
    ],
    "wof:name":"Casey Painting & Decorating",
    "wof:placetype":"venue"
},
  "geometry": {"coordinates":[-79.807907,43.242321],"type":"Point"}
}