{
  "type": "Feature",
  "properties": {
    "addr:full":"6 Government Rd W Kirkland Lake ON P2N 2E1",
    "addr:housenumber":"6",
    "addr:postcode":"p2n 2e1",
    "addr:street":"Rd W",
    "iso:country":"CA",
    "sg:address":"6 Government Rd W",
    "sg:city":"Kirkland Lake",
    "sg:classifiers":[
        {
            "category":"Professional",
            "subcategory":"Lawyer & Legal Services",
            "type":"Services"
        }
    ],
    "sg:phone":"+1 705 567 3301",
    "sg:postcode":"P2N 2E1",
    "sg:province":"ON",
    "sg:tags":[
        "attorney"
    ],
    "wof:name":"Ellies, Murray N QC",
    "wof:placetype":"venue"
},
  "geometry": {"coordinates":[-80.033661,48.150856],"type":"Point"}
}