{
  "type": "Feature",
  "properties": {
    "iso:country":"CA",
    "sg:address":"1333 Rg Ste-Anne",
    "sg:city":"Notre-Dame-DE-Stanbridge",
    "sg:classifiers":[
        {
            "category":"Organizations",
            "subcategory":"Membership Organization",
            "type":"Services"
        }
    ],
    "sg:phone":"+1 450 296 4219",
    "sg:postcode":"J0J 1M0",
    "sg:province":"QC",
    "sg:tags":[
        "protection",
        "animal"
    ],
    "wof:name":"Chaumiere Pour Quatre Pattes",
    "wof:placetype":"venue"
},
  "geometry": {"coordinates":[-73.02281188960001,45.1998062134],"type":"Point"}
}