{
  "type": "Feature",
  "properties": {
    "addr:full":"Fort Mcmurray AB T9H 2J9",
    "addr:postcode":"t9h 2j9",
    "iso:country":"CA",
    "sg:city":"Fort Mcmurray",
    "sg:classifiers":[
        {
            "category":"Mining & Drilling",
            "type":"Manufacturing & Wholesale Goods"
        }
    ],
    "sg:phone":"+1 780 714 6161",
    "sg:postcode":"T9H 2J9",
    "sg:province":"AB",
    "sg:tags":[
        "company",
        "oil"
    ],
    "wof:name":"Canadian Natural Resources Ltd",
    "wof:placetype":"venue"
},
  "geometry": {"coordinates":[-111.371506,56.72401],"type":"Point"}
}