{
  "type": "Feature",
  "properties": {
    "iso:country":"CA",
    "sg:address":"430 Trans Canada Hwy",
    "sg:city":"Duncan",
    "sg:classifiers":[
        {
            "category":"Food & Beverages",
            "subcategory":"Meat & Fish",
            "type":"Retail Goods"
        }
    ],
    "sg:phone":"+1 250 748 6377",
    "sg:postcode":"V9L 3R6",
    "sg:province":"BC",
    "wof:name":"Duncan Butcher Shop",
    "wof:placetype":"venue"
},
  "geometry": {"coordinates":[-123.69867706300001,48.7791366577],"type":"Point"}
}