{
  "type": "Feature",
  "properties": {
    "iso:country":"CA",
    "sg:address":"1080 Stacey Crt",
    "sg:city":"Mississauga",
    "sg:classifiers":[
        {
            "category":"Manufacturing",
            "subcategory":"Food",
            "type":"Manufacturing & Wholesale Goods"
        }
    ],
    "sg:phone":"+1 905 624 3321",
    "sg:postcode":"L4W 2X8",
    "sg:province":"ON",
    "sg:tags":[
        "tea",
        "coffee",
        "mills"
    ],
    "wof:name":"Athans Group Coffee CO Ltd",
    "wof:placetype":"venue"
},
  "geometry": {"coordinates":[-79.63795471189999,43.6329498291],"type":"Point"}
}