{
  "type": "Feature",
  "properties": {
    "addr:full":"7330 Goreway Dr # 15 Mississauga ON L4T 4J2",
    "addr:housenumber":"7330",
    "addr:postcode":"l4t 4j2",
    "addr:street":"Goreway Dr # 15",
    "iso:country":"CA",
    "sg:address":"7330 Goreway Dr # 15",
    "sg:city":"Mississauga",
    "sg:classifiers":[
        {
            "category":"Shopping",
            "subcategory":"Optical Goods",
            "type":"Retail Goods"
        }
    ],
    "sg:phone":"+1 905 677 5337",
    "sg:postcode":"L4T 4J2",
    "sg:province":"ON",
    "sg:tags":[
        "optician"
    ],
    "wof:name":"Next Optical",
    "wof:placetype":"venue"
},
  "geometry": {"coordinates":[-79.640282,43.719704],"type":"Point"}
}