{
  "type": "Feature",
  "properties": {
    "addr:full":"29 Shannon Rd Mount Albert ON L0G 1M0",
    "addr:housenumber":"29",
    "addr:postcode":"l0g 1m0",
    "addr:street":"Shannon Rd",
    "iso:country":"CA",
    "sg:address":"29 Shannon Rd",
    "sg:city":"Mount Albert",
    "sg:classifiers":[
        {
            "category":"Building & Trades",
            "subcategory":"Equipment Rental",
            "type":"Services"
        }
    ],
    "sg:phone":"+1 905 473 9805",
    "sg:postcode":"L0G 1M0",
    "sg:province":"ON",
    "sg:tags":[
        "crane"
    ],
    "wof:name":"Babcock Crane Svc",
    "wof:placetype":"venue"
},
  "geometry": {"coordinates":[-79.311806,44.136604],"type":"Point"}
}