{
  "type": "Feature",
  "properties": {
    "addr:full":"525 Jasmine Cres Campbell River BC V9W 7G8",
    "addr:housenumber":"525",
    "addr:postcode":"v9w 7g8",
    "addr:street":"Jasmine Cres",
    "iso:country":"CA",
    "sg:address":"525 Jasmine Cres",
    "sg:city":"Campbell River",
    "sg:classifiers":[
        {
            "category":"Wholesale",
            "subcategory":"Machinery & Supplies",
            "type":"Manufacturing & Wholesale Goods"
        }
    ],
    "sg:phone":"+1 250 923 6279",
    "sg:postcode":"V9W 7G8",
    "sg:province":"BC",
    "sg:tags":[
        "compressor",
        "gas"
    ],
    "wof:name":"Aquatech West",
    "wof:placetype":"venue"
},
  "geometry": {"coordinates":[-125.23893700000001,49.979202],"type":"Point"}
}