{
  "type": "Feature",
  "properties": {
    "addr:full":"685 Rue Bondville Foster QC J0E 1R0",
    "addr:housenumber":"685",
    "addr:postcode":"j0e 1r0",
    "addr:street":"Rue Bondville",
    "iso:country":"CA",
    "sg:address":"685 Rue Bondville",
    "sg:city":"Foster",
    "sg:classifiers":[
        {
            "category":"Food & Beverages",
            "subcategory":"Groceries & Convenience Stores",
            "type":"Retail Goods"
        }
    ],
    "sg:phone":"+1 450 242 2888",
    "sg:postcode":"J0E 1R0",
    "sg:province":"QC",
    "wof:name":"Depanneur Des Erables",
    "wof:placetype":"venue"
},
  "geometry": {"coordinates":[-72.50146484379999,45.2944641113],"type":"Point"}
}