{
  "type": "Feature",
  "properties": {
    "addr:full":"Hamilton ON L8V 1B1",
    "addr:postcode":"l8v 1b1",
    "iso:country":"CA",
    "sg:city":"Hamilton",
    "sg:classifiers":[
        {
            "category":"Shopping",
            "subcategory":"Used Merchandise",
            "type":"Retail Goods"
        }
    ],
    "sg:phone":"+1 905 387 2693",
    "sg:postcode":"L8V 1B1",
    "sg:province":"ON",
    "sg:tags":[
        "second",
        "store",
        "hand"
    ],
    "wof:name":"One More Time",
    "wof:placetype":"venue"
},
  "geometry": {"coordinates":[-79.851883,43.240757],"type":"Point"}
}