{
  "type": "Feature",
  "properties": {
    "addr:full":"985 Prince St Truro NS B2N 1H7",
    "addr:housenumber":"985",
    "addr:postcode":"b2n 1h7",
    "addr:street":"Prince St",
    "iso:country":"CA",
    "sg:address":"985 Prince St",
    "sg:city":"Truro",
    "sg:classifiers":[
        {
            "category":"Food & Beverages",
            "subcategory":"Liquor & Beverages",
            "type":"Retail Goods"
        }
    ],
    "sg:phone":"+1 902 893 2963",
    "sg:postcode":"B2N 1H7",
    "sg:province":"NS",
    "sg:tags":[
        "store"
    ],
    "wof:name":"Nova Scotia Liquor Commission",
    "wof:placetype":"venue"
},
  "geometry": {"coordinates":[-63.271767,45.364269],"type":"Point"}
}