{
  "type": "Feature",
  "properties": {
    "iso:country":"CA",
    "sg:address":"910 Upper Sherman Ave",
    "sg:city":"Hamilton",
    "sg:classifiers":[
        {
            "category":"Organizations",
            "subcategory":"Religious Organization",
            "type":"Services"
        }
    ],
    "sg:phone":"+1 905 389 6981",
    "sg:postcode":"L8V 3N3",
    "sg:province":"ON",
    "sg:tags":[
        "church"
    ],
    "wof:name":"Mountain Church of Nazarene",
    "wof:placetype":"venue"
},
  "geometry": {"coordinates":[-79.853142,43.219105],"type":"Point"}
}