{
  "type": "Feature",
  "properties": {
    "addr:full":"4606 Rue Sainte-Catherine O Westmount QC H3Z 1S3",
    "addr:housenumber":"4606",
    "addr:postcode":"h3z 1s3",
    "addr:street":"Rue Sainte-Catherine O",
    "iso:country":"CA",
    "sg:address":"4606 Rue Sainte-Catherine O",
    "sg:city":"Westmount",
    "sg:classifiers":[
        {
            "category":"Health Services",
            "subcategory":"Doctor",
            "type":"Services"
        }
    ],
    "sg:phone":"+1 514 846 3327",
    "sg:postcode":"H3Z 1S3",
    "sg:province":"QC",
    "sg:tags":[
        "physician",
        "surgeon"
    ],
    "wof:name":"Katz, Max MD",
    "wof:placetype":"venue"
},
  "geometry": {"coordinates":[-73.5949630737,45.4795150757],"type":"Point"}
}