{
  "type": "Feature",
  "properties": {
    "addr:full":"Toronto ON M5R 2A7",
    "addr:postcode":"m5r 2a7",
    "iso:country":"CA",
    "sg:city":"Toronto",
    "sg:classifiers":[
        {
            "category":"Organizations",
            "subcategory":"Professional Association",
            "type":"Services"
        }
    ],
    "sg:phone":"+1 416 960 4930",
    "sg:postcode":"M5R 2A7",
    "sg:province":"ON",
    "wof:name":"Canadian Resort Development",
    "wof:placetype":"venue"
},
  "geometry": {"coordinates":[-79.389893,43.670403],"type":"Point"}
}