{
  "type": "Feature",
  "properties": {
    "addr:full":"1058 Rue Levis Lachenaie QC J6W 4L1",
    "addr:housenumber":"1058",
    "addr:postcode":"j6w 4l1",
    "addr:street":"Rue Levis",
    "iso:country":"CA",
    "sg:address":"1058 Rue Levis",
    "sg:city":"Lachenaie",
    "sg:classifiers":[
        {
            "category":"Retail",
            "subcategory":"Repair Shop",
            "type":"Services"
        }
    ],
    "sg:phone":"+1 450 492 6784",
    "sg:postcode":"J6W 4L1",
    "sg:province":"QC",
    "sg:tags":[
        "welding"
    ],
    "wof:name":"Acier Terrebonne Inc",
    "wof:placetype":"venue"
},
  "geometry": {"coordinates":[-73.62496899999999,45.712566],"type":"Point"}
}