{
  "type": "Feature",
  "properties": {
    "addr:full":"317 Greenwood Ave Winnipeg MB R2M 4J5",
    "addr:housenumber":"317",
    "addr:postcode":"r2m 4j5",
    "addr:street":"Greenwood Ave",
    "iso:country":"CA",
    "sg:address":"317 Greenwood Ave",
    "sg:city":"Winnipeg",
    "sg:phone":"+1 204 253 5330",
    "sg:postcode":"R2M 4J5",
    "sg:province":"MB",
    "sg:tags":[
        "equipment",
        "station"
    ],
    "wof:name":"Hofmann Balancing Techniques",
    "wof:placetype":"venue"
},
  "geometry": {"coordinates":[-97.0979,49.828644],"type":"Point"}
}