{
  "type": "Feature",
  "properties": {
    "addr:full":"Sherbrooke QC J1H 4J6",
    "addr:postcode":"j1h 4j6",
    "iso:country":"CA",
    "sg:city":"Sherbrooke",
    "sg:classifiers":[
        {
            "category":"Health Services",
            "subcategory":"Health Practitioner",
            "type":"Services"
        }
    ],
    "sg:phone":"+1 819 822 3424",
    "sg:postcode":"J1H 4J6",
    "sg:province":"QC",
    "sg:tags":[
        "psychologist"
    ],
    "wof:name":"Bolduc, Marc",
    "wof:placetype":"venue"
},
  "geometry": {"coordinates":[-71.89432499999999,45.398006],"type":"Point"}
}