{
  "type": "Feature",
  "properties": {
    "addr:full":"6568 Longwoods Rd Melbourne ON N0L 1T0",
    "addr:housenumber":"6568",
    "addr:postcode":"n0l 1t0",
    "addr:street":"Longwoods Rd",
    "iso:country":"CA",
    "sg:address":"6568 Longwoods Rd",
    "sg:city":"Melbourne",
    "sg:classifiers":[
        {
            "category":"Manufacturing",
            "subcategory":"Tools & Machinery",
            "type":"Manufacturing & Wholesale Goods"
        }
    ],
    "sg:phone":"+1 519 289 2150",
    "sg:postcode":"N0L 1T0",
    "sg:province":"ON",
    "sg:tags":[
        "machine",
        "shop"
    ],
    "wof:name":"Wolfe Equipment Ltd",
    "wof:placetype":"venue"
},
  "geometry": {"coordinates":[-81.55302399999999,42.81638],"type":"Point"}
}