{
  "type": "Feature",
  "properties": {
    "addr:full":"Westmount QC H3Z 1B8",
    "addr:postcode":"h3z 1b8",
    "iso:country":"CA",
    "sg:city":"Westmount",
    "sg:classifiers":[
        {
            "category":"Manufacturing",
            "subcategory":"Printing",
            "type":"Manufacturing & Wholesale Goods"
        }
    ],
    "sg:phone":"+1 514 931 7261",
    "sg:postcode":"H3Z 1B8",
    "sg:province":"QC",
    "sg:tags":[
        "publisher"
    ],
    "wof:name":"Developpements Iberville Ltee",
    "wof:placetype":"venue"
},
  "geometry": {"coordinates":[-73.5913467407,45.4884490967],"type":"Point"}
}