{
  "type": "Feature",
  "properties": {
    "addr:full":"Mississauga ON L5N 5M2",
    "addr:postcode":"l5n 5m2",
    "iso:country":"CA",
    "sg:city":"Mississauga",
    "sg:classifiers":[
        {
            "category":"Manufacturing",
            "subcategory":"Signs",
            "type":"Manufacturing & Wholesale Goods"
        }
    ],
    "sg:phone":"+1 905 821 8093",
    "sg:postcode":"L5N 5M2",
    "sg:province":"ON",
    "wof:name":"D & G Craft Signs Ltd",
    "wof:placetype":"venue"
},
  "geometry": {"coordinates":[-79.73659499999999,43.606335],"type":"Point"}
}