{
  "type": "Feature",
  "properties": {
    "iso:country":"CA",
    "sg:address":"603 Avila Ave",
    "sg:city":"Winnipeg",
    "sg:classifiers":[
        {
            "category":"Retail",
            "subcategory":"Repair Shop",
            "type":"Services"
        }
    ],
    "sg:phone":"+1 204 269 4070",
    "sg:postcode":"R3T 3A5",
    "sg:province":"MB",
    "sg:tags":[
        "repairing",
        "piano",
        "refinishing"
    ],
    "wof:name":"DE Smet, Henri",
    "wof:placetype":"venue"
},
  "geometry": {"coordinates":[-97.13274383540001,49.8001747131],"type":"Point"}
}