{
  "type": "Feature",
  "properties": {
    "addr:full":"Morden MB R6M 2B5",
    "addr:postcode":"r6m 2b5",
    "iso:country":"CA",
    "sg:city":"Morden",
    "sg:classifiers":[
        {
            "category":"Personal",
            "subcategory":"Barber",
            "type":"Services"
        }
    ],
    "sg:phone":"+1 204 822 5676",
    "sg:postcode":"R6M 2B5",
    "sg:province":"MB",
    "wof:name":"Jimmie's Barber & Hair Styling",
    "wof:placetype":"venue"
},
  "geometry": {"coordinates":[-98.0994262695,49.189781189],"type":"Point"}
}