{
  "type": "Feature",
  "properties": {
    "addr:full":"Trois-Pistoles QC G0L 4K0",
    "addr:postcode":"g0l 4k0",
    "iso:country":"CA",
    "sg:city":"Trois-Pistoles",
    "sg:classifiers":[
        {
            "category":"Professional",
            "subcategory":"Business Services",
            "type":"Services"
        }
    ],
    "sg:phone":"+1 418 851 1366",
    "sg:postcode":"G0L 4K0",
    "sg:province":"QC",
    "wof:name":"Recuperation Des Basques Inc",
    "wof:placetype":"venue"
},
  "geometry": {"coordinates":[-69.17585800000001,48.118481],"type":"Point"}
}