{
  "type": "Feature",
  "properties": {
    "addr:full":"514 South Service Rd E Oakville ON L6J 2X6",
    "addr:housenumber":"514",
    "addr:postcode":"l6j 2x6",
    "addr:street":"South Service Rd E",
    "iso:country":"CA",
    "sg:address":"514 South Service Rd E",
    "sg:city":"Oakville",
    "sg:classifiers":[
        {
            "category":"Manufacturing",
            "subcategory":"Motor Vehicles & Parts",
            "type":"Manufacturing & Wholesale Goods"
        }
    ],
    "sg:phone":"+1 905 845 6657",
    "sg:postcode":"L6J 2X6",
    "sg:province":"ON",
    "sg:tags":[
        "insulation",
        "automotive",
        "findings",
        "contractor"
    ],
    "wof:name":"Schlegel Canada Inc",
    "wof:placetype":"venue"
},
  "geometry": {"coordinates":[-79.67961120610001,43.4643821716],"type":"Point"}
}