{
  "type": "Feature",
  "properties": {
    "addr:full":"Vancouver BC V6C 3P6",
    "addr:postcode":"v6c 3p6",
    "iso:country":"CA",
    "sg:city":"Vancouver",
    "sg:classifiers":[
        {
            "category":"Shopping",
            "subcategory":"Computers & Home Electronics",
            "type":"Retail Goods"
        }
    ],
    "sg:phone":"+1 604 662 7424",
    "sg:postcode":"V6C 3P6",
    "sg:province":"BC",
    "sg:tags":[
        "software"
    ],
    "wof:name":"Sybase Canada",
    "wof:placetype":"venue"
},
  "geometry": {"coordinates":[-123.11982727,49.2851448059],"type":"Point"}
}