{
  "type": "Feature",
  "properties": {
    "addr:full":"Edmundston NB E3V 1E5",
    "addr:postcode":"e3v 1e5",
    "iso:country":"CA",
    "sg:city":"Edmundston",
    "sg:classifiers":[
        {
            "category":"Health Services",
            "subcategory":"Optometrist",
            "type":"Services"
        }
    ],
    "sg:phone":"+1 506 735 4488",
    "sg:postcode":"E3V 1E5",
    "sg:province":"NB",
    "wof:name":"Boulay, Linda OD",
    "wof:placetype":"venue"
},
  "geometry": {"coordinates":[-68.329781,47.362148],"type":"Point"}
}