{
  "type": "Feature",
  "properties": {
    "addr:full":"560 Montreal Rd Ottawa ON K1K 0T9",
    "addr:housenumber":"560",
    "addr:postcode":"k1k 0t9",
    "addr:street":"Montreal Rd",
    "iso:country":"CA",
    "sg:address":"560 Montreal Rd",
    "sg:city":"Ottawa",
    "sg:classifiers":[
        {
            "category":"Home & Garden",
            "subcategory":"Furniture",
            "type":"Retail Goods"
        }
    ],
    "sg:phone":"+1 613 741 5000",
    "sg:postcode":"K1K 0T9",
    "sg:province":"ON",
    "sg:tags":[
        "linen",
        "bedding"
    ],
    "wof:name":"Beddington's Bed & Bath",
    "wof:placetype":"venue"
},
  "geometry": {"coordinates":[-75.64426400000001,45.441811],"type":"Point"}
}