{
  "type": "Feature",
  "properties": {
    "iso:country":"CA",
    "sg:city":"Westmount",
    "sg:classifiers":[
        {
            "category":"Banks & Credit Unions",
            "subcategory":"Bank",
            "type":"Services"
        }
    ],
    "sg:phone":"+1 514 487 8172",
    "sg:postcode":"H3Z 1N1",
    "sg:province":"QC",
    "sg:tags":[
        "loan",
        "real estate"
    ],
    "wof:name":"Morness Investment Inc",
    "wof:placetype":"venue"
},
  "geometry": {"coordinates":[-73.60125,45.476456],"type":"Point"}
}