{
  "type": "Feature",
  "properties": {
    "addr:full":"50 Av Mgr-Plourde Edmundston NB E3V 4M2",
    "addr:postcode":"e3v 4m2",
    "addr:street":"50 Av Mgr-Plourde",
    "iso:country":"CA",
    "sg:address":"50 Av Mgr-Plourde",
    "sg:city":"Edmundston",
    "sg:classifiers":[
        {
            "category":"Utilities",
            "subcategory":"Mobile Phone",
            "type":"Services"
        }
    ],
    "sg:phone":"+1 506 735 6704",
    "sg:postcode":"E3V 4M2",
    "sg:province":"NB",
    "sg:tags":[
        "equipment",
        "computer",
        "dealer",
        "cellular",
        "telephone"
    ],
    "wof:name":"Dumoulin Electronique/Info",
    "wof:placetype":"venue"
},
  "geometry": {"coordinates":[-68.3338546753,47.3817863464],"type":"Point"}
}