{
  "type": "Feature",
  "properties": {
    "addr:full":"3302 27 St Vernon BC V1T 4W7",
    "addr:housenumber":"3302",
    "addr:postcode":"v1t 4w7",
    "addr:street":"27 St",
    "iso:country":"CA",
    "sg:address":"3302 27 St",
    "sg:city":"Vernon",
    "sg:classifiers":[
        {
            "category":"Education",
            "subcategory":"School",
            "type":"Public Place"
        }
    ],
    "sg:phone":"+1 250 542 1388",
    "sg:postcode":"V1T 4W7",
    "sg:province":"BC",
    "wof:name":"Beairsto Elementary",
    "wof:placetype":"venue"
},
  "geometry": {"coordinates":[-119.266929627,50.2661094666],"type":"Point"}
}