{
  "type": "Feature",
  "properties": {
    "addr:full":"9700 113th St Fairview AB T0H 1L0",
    "addr:housenumber":"9700",
    "addr:postcode":"t0h 1l0",
    "addr:street":"113Th St",
    "iso:country":"CA",
    "sg:address":"9700 113th St",
    "sg:city":"Fairview",
    "sg:classifiers":[
        {
            "category":"Autos & Motor Vehicles",
            "subcategory":"Auto Supplies",
            "type":"Retail Goods"
        }
    ],
    "sg:phone":"+1 780 835 5115",
    "sg:postcode":"T0H 1L0",
    "sg:province":"AB",
    "sg:tags":[
        "automobile",
        "parts"
    ],
    "wof:name":"Gregg Distributors",
    "wof:placetype":"venue"
},
  "geometry": {"coordinates":[-118.39199829099999,56.0649299622],"type":"Point"}
}