{
  "type": "Feature",
  "properties": {
    "addr:full":"Regina SK S4P 2V5",
    "addr:postcode":"s4p 2v5",
    "iso:country":"CA",
    "sg:city":"Regina",
    "sg:classifiers":[
        {
            "category":"Professional",
            "subcategory":"Lawyer & Legal Services",
            "type":"Services"
        }
    ],
    "sg:phone":"+1 306 359 0202",
    "sg:postcode":"S4P 2V5",
    "sg:province":"SK",
    "sg:tags":[
        "attorney"
    ],
    "wof:name":"Sauer, Reginald E",
    "wof:placetype":"venue"
},
  "geometry": {"coordinates":[-104.61777499999999,50.443172],"type":"Point"}
}