{
  "type": "Feature",
  "properties": {
    "addr:full":"2202 8 St Nisku AB T9E 7Y9",
    "addr:housenumber":"2202 8",
    "addr:postcode":"t9e 7y9",
    "addr:street":"St",
    "iso:country":"CA",
    "sg:address":"2202 8 St",
    "sg:city":"Nisku",
    "sg:classifiers":[
        {
            "category":"Wholesale",
            "subcategory":"Machinery & Supplies",
            "type":"Manufacturing & Wholesale Goods"
        }
    ],
    "sg:phone":"+1 780 955 5111",
    "sg:postcode":"T9E 7Y9",
    "sg:province":"AB",
    "sg:tags":[
        "equipment",
        "mining",
        "contractor"
    ],
    "wof:name":"Procon Equipment",
    "wof:placetype":"venue"
},
  "geometry": {"coordinates":[-113.516289,53.34174],"type":"Point"}
}