{
  "type": "Feature",
  "properties": {
    "addr:full":"11 Rue Letourneau Victoriaville QC G6P 4M5",
    "addr:housenumber":"11",
    "addr:postcode":"g6p 4m5",
    "addr:street":"Rue Letourneau",
    "iso:country":"CA",
    "sg:address":"11 Rue Letourneau",
    "sg:city":"Victoriaville",
    "sg:classifiers":[
        {
            "category":"Professional",
            "subcategory":"Lawyer & Legal Services",
            "type":"Services"
        }
    ],
    "sg:phone":"+1 819 795 4900",
    "sg:postcode":"G6P 4M5",
    "sg:province":"QC",
    "sg:tags":[
        "arbitration",
        "attorney"
    ],
    "wof:name":"Mailhot, Normand",
    "wof:placetype":"venue"
},
  "geometry": {"coordinates":[-71.95298,46.051186],"type":"Point"}
}