{
  "type": "Feature",
  "properties": {
    "iso:country":"CA",
    "sg:address":"2505 Rue Saint-Hubert",
    "sg:city":"Jonquiere",
    "sg:classifiers":[
        {
            "category":"Education",
            "subcategory":"College",
            "type":"Public Place"
        }
    ],
    "sg:phone":"+1 418 547 2191",
    "sg:postcode":"G7X 5M4",
    "sg:province":"QC",
    "sg:tags":[
        "academic",
        "school"
    ],
    "wof:name":"Cegep DE Jonquiere",
    "wof:placetype":"venue"
},
  "geometry": {"coordinates":[-71.24890136720001,48.4057731628],"type":"Point"}
}