{
  "type": "Feature",
  "properties": {
    "iso:country":"CA",
    "sg:address":"3545 Pitch Pine Cres",
    "sg:city":"Mississauga",
    "sg:phone":"+1 905 569 3333",
    "sg:postcode":"L5L 1P9",
    "sg:province":"ON",
    "sg:tags":[
        "equipment",
        "supply"
    ],
    "wof:name":"S L Crawford & Assoc Ltd",
    "wof:placetype":"venue"
},
  "geometry": {"coordinates":[-79.694702,43.535248],"type":"Point"}
}