{
  "type": "Feature",
  "properties": {
    "addr:full":"3545 Pitch Pine Cres Mississauga ON L5L 1P9",
    "addr:housenumber":"3545",
    "addr:postcode":"l5l 1p9",
    "addr:street":"Pitch Pine Cres",
    "iso:country":"CA",
    "sg:address":"3545 Pitch Pine Cres",
    "sg:city":"Mississauga",
    "sg:phone":"+1 905 569 3333",
    "sg:postcode":"L5L 1P9",
    "sg:province":"ON",
    "sg:tags":[
        "equipment",
        "supply"
    ],
    "wof:name":"S L Crawford & Assoc Ltd",
    "wof:placetype":"venue"
},
  "geometry": {"coordinates":[-79.69470200000001,43.535248],"type":"Point"}
}