{
  "type": "Feature",
  "properties": {
    "addr:full":"London ON N5V 3B1",
    "addr:postcode":"n5v 3b1",
    "iso:country":"CA",
    "sg:city":"London",
    "sg:classifiers":[
        {
            "category":"Professional",
            "subcategory":"Advertising",
            "type":"Services"
        }
    ],
    "sg:phone":"+1 519 455 8600",
    "sg:postcode":"N5V 3B1",
    "sg:province":"ON",
    "sg:tags":[
        "mail"
    ],
    "wof:name":"Absolute Mail Solutions",
    "wof:placetype":"venue"
},
  "geometry": {"coordinates":[-81.184746,43.022411],"type":"Point"}
}