{
  "type": "Feature",
  "properties": {
    "addr:full":"1725 Market St Halifax NS B3J 3N9",
    "addr:housenumber":"1725",
    "addr:postcode":"ns b3j 3n9",
    "addr:street":"Market St",
    "iso:country":"CA",
    "sg:address":"1725 Market St",
    "sg:city":"Halifax",
    "sg:classifiers":[
        {
            "category":"Travel",
            "subcategory":"Hotels & Motels",
            "type":"Entertainment"
        }
    ],
    "sg:phone":"+1 902 425 1986",
    "sg:postcode":"B3J 3N9",
    "sg:province":"NS",
    "wof:name":"Prince George Hotel",
    "wof:placetype":"venue"
},
  "geometry": {"coordinates":[-63.575962,44.646881],"type":"Point"}
}