{
  "type": "Feature",
  "properties": {
    "addr:full":"6 Main St E Hamilton ON L8N 1E8",
    "addr:housenumber":"6",
    "addr:postcode":"l8n 1e8",
    "addr:street":"Main St E",
    "iso:country":"CA",
    "sg:address":"6 Main St E",
    "sg:city":"Hamilton",
    "sg:classifiers":[
        {
            "category":"Organizations",
            "subcategory":"Community Association",
            "type":"Services"
        }
    ],
    "sg:phone":"+1 905 522 4675",
    "sg:postcode":"L8N 1E8",
    "sg:province":"ON",
    "sg:tags":[
        "club"
    ],
    "wof:name":"Hamilton Club",
    "wof:placetype":"venue"
},
  "geometry": {"coordinates":[-79.869446,43.255177],"type":"Point"}
}