{
  "type": "Feature",
  "properties": {
    "addr:full":"2188 Queen St E Toronto ON M4E 1E6",
    "addr:housenumber":"2188",
    "addr:postcode":"m4e 1e6",
    "addr:street":"Queen St E",
    "iso:country":"CA",
    "sg:address":"2188 Queen St E",
    "sg:city":"Toronto",
    "sg:classifiers":[
        {
            "category":"Education",
            "subcategory":"Special Training",
            "type":"Public Place"
        }
    ],
    "sg:phone":"+1 416 686 0960",
    "sg:postcode":"M4E 1E6",
    "sg:province":"ON",
    "sg:tags":[
        "school",
        "instruction",
        "art"
    ],
    "wof:name":"Art Garage",
    "wof:placetype":"venue"
},
  "geometry": {"coordinates":[-79.290436,43.672207],"type":"Point"}
}