{
  "type": "Feature",
  "properties": {
    "addr:full":"377 Mill Rd S Boissevain MB R0K 0E0",
    "addr:housenumber":"377",
    "addr:postcode":"r0k 0e0",
    "addr:street":"Mill Rd S Boissevain",
    "iso:country":"CA",
    "sg:address":"377 Mill Rd S",
    "sg:city":"Boissevain",
    "sg:classifiers":[
        {
            "category":"Freight",
            "type":"Transportation"
        }
    ],
    "sg:phone":"+1 204 534 6514",
    "sg:postcode":"R0K 0E0",
    "sg:province":"MB",
    "sg:tags":[
        "trucking"
    ],
    "wof:name":"Boissevain Transport Ltd",
    "wof:placetype":"venue"
},
  "geometry": {"coordinates":[-100.05753300000001,49.22683],"type":"Point"}
}