{
  "type": "Feature",
  "properties": {
    "addr:full":"32 Rue Saint-Vincent Sainte-Agathe-Des-Monts QC J8C 2A6",
    "addr:housenumber":"32",
    "addr:postcode":"j8c 2a6",
    "addr:street":"Rue Saint-Vincent",
    "iso:country":"CA",
    "sg:address":"32 Rue Saint-Vincent",
    "sg:city":"Sainte-Agathe-Des-Monts",
    "sg:classifiers":[
        {
            "category":"Shopping",
            "subcategory":"Shoes",
            "type":"Retail Goods"
        }
    ],
    "sg:phone":"+1 819 326 4143",
    "sg:postcode":"J8C 2A6",
    "sg:province":"QC",
    "wof:name":"Chaussures Populaires",
    "wof:placetype":"venue"
},
  "geometry": {"coordinates":[-74.2887802124,46.0475196838],"type":"Point"}
}