{
  "type": "Feature",
  "properties": {
    "addr:full":"1360 Kingston Rd #9 Pickering ON L1V 3B4",
    "addr:housenumber":"1360",
    "addr:postcode":"l1v 3b4",
    "addr:street":"Kingston Rd # 9",
    "iso:country":"CA",
    "sg:address":"1360 Kingston Rd #9",
    "sg:city":"Pickering",
    "sg:classifiers":[
        {
            "category":"Shopping",
            "subcategory":"Optical Goods",
            "type":"Retail Goods"
        }
    ],
    "sg:phone":"+1 905 839 9244",
    "sg:postcode":"L1V 3B4",
    "sg:province":"ON",
    "sg:tags":[
        "optician"
    ],
    "wof:name":"Pickering Optical",
    "wof:placetype":"venue"
},
  "geometry": {"coordinates":[-79.08725699999999,43.838348],"type":"Point"}
}