{
  "type": "Feature",
  "properties": {
    "iso:country":"CA",
    "sg:address":"722 9th St E",
    "sg:city":"Owen Sound",
    "sg:classifiers":[
        {
            "category":"Manufacturing",
            "subcategory":"Building Materials",
            "type":"Manufacturing & Wholesale Goods"
        }
    ],
    "sg:phone":"+1 519 371 1593",
    "sg:postcode":"N4K 1R1",
    "sg:province":"ON",
    "sg:tags":[
        "molding"
    ],
    "wof:name":"Wood & Wallworks",
    "wof:placetype":"venue"
},
  "geometry": {"coordinates":[-80.9319610596,44.5671844482],"type":"Point"}
}