{
  "type": "Feature",
  "properties": {
    "addr:full":"1286 Alexander Ave Winnipeg MB R3E 1L1",
    "addr:housenumber":"1286",
    "addr:postcode":"r3e 1l1",
    "addr:street":"Alexander Ave",
    "iso:country":"CA",
    "sg:address":"1286 Alexander Ave",
    "sg:city":"Winnipeg",
    "sg:classifiers":[
        {
            "category":"Retail",
            "subcategory":"Laundry & Dry Cleaning",
            "type":"Services"
        }
    ],
    "sg:phone":"+1 204 788 0870",
    "sg:postcode":"R3E 1L1",
    "sg:province":"MB",
    "sg:tags":[
        "cleaners",
        "rug",
        "carpet"
    ],
    "wof:name":"Enviro-Steem",
    "wof:placetype":"venue"
},
  "geometry": {"coordinates":[-97.178566,49.915318],"type":"Point"}
}