{
  "type": "Feature",
  "properties": {
    "iso:country":"CA",
    "sg:address":"691 Golspie St",
    "sg:city":"Winnipeg",
    "sg:classifiers":[
        {
            "category":"Manufacturing",
            "subcategory":"Tools & Machinery",
            "type":"Manufacturing & Wholesale Goods"
        }
    ],
    "sg:phone":"+1 204 956 6301",
    "sg:postcode":"R2K 2V3",
    "sg:province":"MB",
    "sg:tags":[
        "machine",
        "shop"
    ],
    "wof:name":"Standard Manufacturers Svc",
    "wof:placetype":"venue"
},
  "geometry": {"coordinates":[-97.0877,49.920345],"type":"Point"}
}