{
  "type": "Feature",
  "properties": {
    "addr:full":"457 King St London ON N6B 1S8",
    "addr:housenumber":"457",
    "addr:postcode":"n6b 1s8",
    "addr:street":"King St",
    "iso:country":"CA",
    "sg:address":"457 King St",
    "sg:city":"London",
    "sg:classifiers":[
        {
            "category":"Building & Trades",
            "subcategory":"Construction",
            "type":"Services"
        }
    ],
    "sg:phone":"+1 519 439 3881",
    "sg:postcode":"N6B 1S8",
    "sg:province":"ON",
    "sg:tags":[
        "contractor"
    ],
    "wof:name":"Domus Development London Inc",
    "wof:placetype":"venue"
},
  "geometry": {"coordinates":[-81.23681640620001,42.9857521057],"type":"Point"}
}