{
  "type": "Feature",
  "properties": {
    "addr:full":"99 Rue Principale LA Sarre QC J9Z 1X5",
    "addr:housenumber":"99",
    "addr:postcode":"j9z 1x5",
    "addr:street":"Rue Principale La Sarre",
    "iso:country":"CA",
    "sg:address":"99 Rue Principale",
    "sg:city":"LA Sarre",
    "sg:classifiers":[
        {
            "category":"Organizations",
            "subcategory":"Professional Association",
            "type":"Services"
        }
    ],
    "sg:phone":"+1 819 333 4280",
    "sg:postcode":"J9Z 1X5",
    "sg:province":"QC",
    "wof:name":"Unite Domremy LA Sarre Inc",
    "wof:placetype":"venue"
},
  "geometry": {"coordinates":[-79.205078,48.810478],"type":"Point"}
}