{
  "type": "Feature",
  "properties": {
    "addr:full":"780 Fort St Victoria BC V8W 1H2",
    "addr:housenumber":"780",
    "addr:postcode":"v8w 1h2",
    "addr:street":"Fort St",
    "iso:country":"CA",
    "sg:address":"780 Fort St",
    "sg:city":"Victoria",
    "sg:classifiers":[
        {
            "category":"Manufacturing",
            "subcategory":"Printing",
            "type":"Manufacturing & Wholesale Goods"
        }
    ],
    "sg:phone":"+1 250 385 0642",
    "sg:postcode":"V8W 1H2",
    "sg:province":"BC",
    "sg:tags":[
        "production",
        "video",
        "multimedia",
        "taping"
    ],
    "wof:name":"Roan Sound Productions Ltd",
    "wof:placetype":"venue"
},
  "geometry": {"coordinates":[-123.36319,48.424431],"type":"Point"}
}