{
  "type": "Feature",
  "properties": {
    "addr:full":"5133 Radcliffe Rd Sechelt BC V0N 3A2",
    "addr:housenumber":"5133",
    "addr:postcode":"v0n 3a2",
    "addr:street":"Radcliffe Rd",
    "iso:country":"CA",
    "sg:address":"5133 Radcliffe Rd",
    "sg:city":"Sechelt",
    "sg:classifiers":[
        {
            "category":"Professional",
            "subcategory":"Computer Services",
            "type":"Services"
        }
    ],
    "sg:phone":"+1 604 886 3435",
    "sg:postcode":"V0N 3A2",
    "sg:province":"BC",
    "sg:tags":[
        "repair",
        "dealer",
        "equipment"
    ],
    "wof:name":"Coast Computers",
    "wof:placetype":"venue"
},
  "geometry": {"coordinates":[-123.735237,49.458855],"type":"Point"}
}