{
  "type": "Feature",
  "properties": {
    "addr:full":"Calgary AB T3H 2Z9",
    "addr:postcode":"t3h 2z9",
    "iso:country":"CA",
    "sg:city":"Calgary",
    "sg:classifiers":[
        {
            "category":"Travel",
            "subcategory":"Travel Agent",
            "type":"Entertainment"
        }
    ],
    "sg:phone":"+1 403 240 1331",
    "sg:postcode":"T3H 2Z9",
    "sg:province":"AB",
    "sg:tags":[
        "agency",
        "bureau"
    ],
    "wof:name":"Uniglobe Strathcona Travel",
    "wof:placetype":"venue"
},
  "geometry": {"coordinates":[-114.18431099999999,51.049423],"type":"Point"}
}