{
  "type": "Feature",
  "properties": {
    "iso:country":"CA",
    "sg:address":"255 Boul D'Anjou",
    "sg:city":"Chateauguay",
    "sg:classifiers":[
        {
            "category":"Health Services",
            "subcategory":"Doctor",
            "type":"Services"
        }
    ],
    "sg:phone":"+1 450 691 4321",
    "sg:postcode":"J6J 2R4",
    "sg:province":"QC",
    "sg:tags":[
        "dentist"
    ],
    "wof:name":"Polychuck, Lise DDS",
    "wof:placetype":"venue"
},
  "geometry": {"coordinates":[-73.74011230470001,45.3614845276],"type":"Point"}
}