{
  "type": "Feature",
  "properties": {
    "addr:full":"Toronto ON M5R 3M8",
    "addr:postcode":"m5r 3m8",
    "iso:country":"CA",
    "sg:city":"Toronto",
    "sg:classifiers":[
        {
            "category":"Health Services",
            "subcategory":"Doctor",
            "type":"Services"
        }
    ],
    "sg:phone":"+1 416 534 6313",
    "sg:postcode":"M5R 3M8",
    "sg:province":"ON",
    "sg:tags":[
        "physician",
        "surgeon"
    ],
    "wof:name":"Jussaume, Richard MD",
    "wof:placetype":"venue"
},
  "geometry": {"coordinates":[-79.4115066528,43.6654319763],"type":"Point"}
}