{
  "type": "Feature",
  "properties": {
    "iso:country":"CA",
    "sg:city":"Guelph",
    "sg:classifiers":[
        {
            "category":"Retail",
            "subcategory":"Car Wash",
            "type":"Services"
        }
    ],
    "sg:phone":"+1 519 837 3931",
    "sg:postcode":"N1H 3T9",
    "sg:province":"ON",
    "sg:tags":[
        "polishing",
        "washing"
    ],
    "wof:name":"Supreme Full Svc Car Wash",
    "wof:placetype":"venue"
},
  "geometry": {"coordinates":[-80.24514,43.547138],"type":"Point"}
}