{
  "type": "Feature",
  "properties": {
    "addr:full":"Vernon BC V1H 1R9",
    "addr:postcode":"v1h 1r9",
    "iso:country":"CA",
    "sg:city":"Vernon",
    "sg:classifiers":[
        {
            "category":"Home & Garden",
            "subcategory":"Mobile Homes",
            "type":"Retail Goods"
        }
    ],
    "sg:phone":"+1 250 260 1155",
    "sg:postcode":"V1H 1R9",
    "sg:province":"BC",
    "sg:tags":[
        "building",
        "contractor"
    ],
    "wof:name":"Lakepoint",
    "wof:placetype":"venue"
},
  "geometry": {"coordinates":[-119.273804,50.265686],"type":"Point"}
}