{
  "type": "Feature",
  "properties": {
    "iso:country":"CA",
    "sg:address":"305 Main St",
    "sg:city":"Whitehorse",
    "sg:classifiers":[
        {
            "category":"Real Estate",
            "subcategory":"Real Estate Operator",
            "type":"Services"
        }
    ],
    "sg:phone":"+1 867 667 4222",
    "sg:postcode":"Y1A 2B4",
    "sg:province":"YT",
    "sg:tags":[
        "mall",
        "shopping",
        "center"
    ],
    "wof:name":"Hougen Centre",
    "wof:placetype":"venue"
},
  "geometry": {"coordinates":[-135.05445861800001,60.719165802],"type":"Point"}
}