{
  "type": "Feature",
  "properties": {
    "addr:full":"1003 4 Ave S # 9B Lethbridge AB T1J 0P7",
    "addr:housenumber":"1003;9b",
    "addr:postcode":"t1j 0p7",
    "addr:street":"4 Ave S #",
    "iso:country":"CA",
    "sg:address":"1003 4 Ave S # 9B",
    "sg:city":"Lethbridge",
    "sg:classifiers":[
        {
            "category":"Health Services",
            "subcategory":"Health Practitioner",
            "type":"Services"
        }
    ],
    "sg:phone":"+1 403 381 1700",
    "sg:postcode":"T1J 0P7",
    "sg:province":"AB",
    "sg:tags":[
        "psychologist"
    ],
    "wof:name":"Bernes, Kerry",
    "wof:placetype":"venue"
},
  "geometry": {"coordinates":[-112.832092,49.694752],"type":"Point"}
}