{
  "type": "Feature",
  "properties": {
    "addr:full":"127 Rue Vallilee Chute-Aux-Outardes QC G0H 1C0",
    "addr:housenumber":"127",
    "addr:postcode":"g0h 1c0",
    "addr:street":"Rue Vallilee",
    "iso:country":"CA",
    "sg:address":"127 Rue Vallilee",
    "sg:city":"Chute-Aux-Outardes",
    "sg:classifiers":[
        {
            "category":"Home & Garden",
            "subcategory":"Carpets & Floor Coverings",
            "type":"Retail Goods"
        }
    ],
    "sg:phone":"+1 418 567 2251",
    "sg:postcode":"G0H 1C0",
    "sg:province":"QC",
    "sg:tags":[
        "building",
        "material",
        "rug"
    ],
    "wof:name":"Sylvain Beaulieu Inc",
    "wof:placetype":"venue"
},
  "geometry": {"coordinates":[-68.3933258057,49.1279525757],"type":"Point"}
}