{
  "type": "Feature",
  "properties": {
    "addr:full":"Montreal QC H2N 1P4",
    "addr:postcode":"h2n 1p4",
    "iso:country":"CA",
    "sg:city":"Montreal",
    "sg:classifiers":[
        {
            "category":"Manufacturing",
            "subcategory":"Apparel",
            "type":"Manufacturing & Wholesale Goods"
        }
    ],
    "sg:phone":"+1 514 382 9235",
    "sg:postcode":"H2N 1P4",
    "sg:province":"QC",
    "sg:tags":[
        "clothing"
    ],
    "wof:name":"Sport Collection Paris Inc",
    "wof:placetype":"venue"
},
  "geometry": {"coordinates":[-73.654296875,45.5452651978],"type":"Point"}
}