{
  "type": "Feature",
  "properties": {
    "addr:full":"12 Sierra Morena Way SW Calgary AB T3H 3E4",
    "addr:housenumber":"12",
    "addr:postcode":"t3h 3e4",
    "addr:street":"Sierra Morena Way Sw",
    "iso:country":"CA",
    "sg:address":"12 Sierra Morena Way SW",
    "sg:city":"Calgary",
    "sg:classifiers":[
        {
            "category":"Shopping",
            "subcategory":"Computers & Home Electronics",
            "type":"Retail Goods"
        }
    ],
    "sg:phone":"+1 403 290 1913",
    "sg:postcode":"T3H 3E4",
    "sg:province":"AB",
    "sg:tags":[
        "publishing"
    ],
    "wof:name":"Color Lazer Products",
    "wof:placetype":"venue"
},
  "geometry": {"coordinates":[-114.186073303,51.0200881958],"type":"Point"}
}