{
  "type": "Feature",
  "properties": {
    "addr:full":"515 Rue Dorion Granby QC J2G 1A4",
    "addr:housenumber":"515",
    "addr:postcode":"j2g 1a4",
    "addr:street":"Rue Dorion",
    "iso:country":"CA",
    "sg:address":"515 Rue Dorion",
    "sg:city":"Granby",
    "sg:classifiers":[
        {
            "category":"Professional",
            "subcategory":"Accounting & Tax Preparation",
            "type":"Services"
        }
    ],
    "sg:phone":"+1 450 375 3944",
    "sg:postcode":"J2G 1A4",
    "sg:province":"QC",
    "sg:tags":[
        "accountant"
    ],
    "wof:name":"Residence Langlois",
    "wof:placetype":"venue"
},
  "geometry": {"coordinates":[-72.735626,45.421181],"type":"Point"}
}