{
  "type": "Feature",
  "properties": {
    "addr:full":"313 Lambton St Kincardine ON N2Z 2Y1",
    "addr:housenumber":"313",
    "addr:postcode":"n2z 2y1",
    "addr:street":"Lambton St",
    "iso:country":"CA",
    "sg:address":"313 Lambton St",
    "sg:city":"Kincardine",
    "sg:classifiers":[
        {
            "category":"Professional",
            "subcategory":"Lawyer & Legal Services",
            "type":"Services"
        }
    ],
    "sg:phone":"+1 519 396 8144",
    "sg:postcode":"N2Z 2Y1",
    "sg:province":"ON",
    "sg:tags":[
        "attorney"
    ],
    "wof:name":"Mahood & Darcy",
    "wof:placetype":"venue"
},
  "geometry": {"coordinates":[-81.634186,44.177532],"type":"Point"}
}