{
  "type": "Feature",
  "properties": {
    "iso:country":"CA",
    "sg:address":"5555 Av DE Gaspe",
    "sg:city":"Montreal",
    "sg:classifiers":[
        {
            "category":"Shopping",
            "type":"Retail Goods"
        }
    ],
    "sg:phone":"+1 514 276 5141",
    "sg:postcode":"H2T 2A3",
    "sg:province":"QC",
    "sg:tags":[
        "candle"
    ],
    "wof:name":"Lerner Candles & Kosher Soap",
    "wof:placetype":"venue"
},
  "geometry": {"coordinates":[-73.597717,45.528004],"type":"Point"}
}