{
  "type": "Feature",
  "properties": {
    "addr:full":"390 Highway 311 Truro NS B2N 5B4",
    "addr:housenumber":"390",
    "addr:postcode":"b2n 5b4",
    "addr:street":"Highway 311",
    "iso:country":"CA",
    "sg:address":"390 Highway 311",
    "sg:city":"Truro",
    "sg:classifiers":[
        {
            "category":"Autos & Motor Vehicles",
            "subcategory":"Automobile Sales",
            "type":"Retail Goods"
        }
    ],
    "sg:phone":"+1 902 895 2528",
    "sg:postcode":"B2N 5B4",
    "sg:province":"NS",
    "sg:tags":[
        "car",
        "dealer"
    ],
    "wof:name":"Winston Black Auto Sales",
    "wof:placetype":"venue"
},
  "geometry": {"coordinates":[-63.2890396118,45.3660202026],"type":"Point"}
}