{
  "type": "Feature",
  "properties": {
    "addr:full":"20568 56 Ave Langley BC V3A 3Y8",
    "addr:housenumber":"20568",
    "addr:postcode":"v3a 3y8",
    "addr:street":"56 Ave",
    "iso:country":"CA",
    "sg:address":"20568 56 Ave",
    "sg:city":"Langley",
    "sg:classifiers":[
        {
            "category":"Retail",
            "subcategory":"Portrait Studio",
            "type":"Services"
        }
    ],
    "sg:phone":"+1 604 533 2263",
    "sg:postcode":"V3A 3Y8",
    "sg:province":"BC",
    "sg:tags":[
        "photographer"
    ],
    "wof:name":"Just Say Cheeze Photography",
    "wof:placetype":"venue"
},
  "geometry": {"coordinates":[-122.65278600000001,49.104675],"type":"Point"}
}