{
  "type": "Feature",
  "properties": {
    "addr:full":"451 10th Ave Hanover ON N4N 2P1",
    "addr:housenumber":"451",
    "addr:postcode":"n4n 2p1",
    "addr:street":"10Th Ave",
    "iso:country":"CA",
    "sg:address":"451 10th Ave",
    "sg:city":"Hanover",
    "sg:classifiers":[
        {
            "category":"Education",
            "subcategory":"Library",
            "type":"Public Place"
        }
    ],
    "sg:phone":"+1 519 364 1420",
    "sg:postcode":"N4N 2P1",
    "sg:province":"ON",
    "wof:name":"Hanover Public Library",
    "wof:placetype":"venue"
},
  "geometry": {"coordinates":[-81.0263214111,44.1521682739],"type":"Point"}
}