{
  "type": "Feature",
  "properties": {
    "addr:full":"Park Ave & Main St Mallaig AB T0A 2K0",
    "addr:postcode":"t0a 2k0",
    "addr:street":"St",
    "iso:country":"CA",
    "sg:address":"Park Ave & Main St",
    "sg:city":"Mallaig",
    "sg:classifiers":[
        {
            "category":"Home & Garden",
            "subcategory":"Building Materials",
            "type":"Retail Goods"
        }
    ],
    "sg:phone":"+1 780 635 3799",
    "sg:postcode":"T0A 2K0",
    "sg:province":"AB",
    "wof:name":"St Arnault Lumber Ltd",
    "wof:placetype":"venue"
},
  "geometry": {"coordinates":[-111.36090900000001,54.209518],"type":"Point"}
}