{
  "type": "Feature",
  "properties": {
    "addr:full":"11899 L'Heureux Rd Valemount BC V0E 2Z0",
    "addr:housenumber":"11899",
    "addr:postcode":"v0e 2z0",
    "addr:street":"L'Heureux Rd",
    "iso:country":"CA",
    "sg:address":"11899 L'Heureux Rd",
    "sg:city":"Valemount",
    "sg:classifiers":[
        {
            "category":"Building & Trades",
            "subcategory":"Electrical",
            "type":"Services"
        }
    ],
    "sg:phone":"+1 250 566 9194",
    "sg:postcode":"V0E 2Z0",
    "sg:province":"BC",
    "sg:tags":[
        "electric",
        "contractor"
    ],
    "wof:name":"Blackman Controls",
    "wof:placetype":"venue"
},
  "geometry": {"coordinates":[-119.276871,52.826729],"type":"Point"}
}