{
  "type": "Feature",
  "properties": {
    "addr:full":"1609A 26th Ave Nanton AB T0L 1R0",
    "addr:housenumber":"1609a",
    "addr:postcode":"t0l 1r0",
    "addr:street":"26Th Ave",
    "iso:country":"CA",
    "sg:address":"1609A 26th Ave",
    "sg:city":"Nanton",
    "sg:classifiers":[
        {
            "category":"Building & Trades",
            "subcategory":"Construction",
            "type":"Services"
        }
    ],
    "sg:phone":"+1 403 646 3099",
    "sg:postcode":"T0L 1R0",
    "sg:province":"AB",
    "sg:tags":[
        "general",
        "contractor"
    ],
    "wof:name":"John's Construction",
    "wof:placetype":"venue"
},
  "geometry": {"coordinates":[-113.78203600000001,50.348392],"type":"Point"}
}