{
  "type": "Feature",
  "properties": {
    "addr:full":"751 Pape Ave Toronto ON M4K 3T1",
    "addr:housenumber":"751",
    "addr:postcode":"m4k 3t1",
    "addr:street":"Pape Ave",
    "iso:country":"CA",
    "sg:address":"751 Pape Ave",
    "sg:city":"Toronto",
    "sg:classifiers":[
        {
            "category":"Health Services",
            "subcategory":"Doctor",
            "type":"Services"
        }
    ],
    "sg:phone":"+1 416 461 1822",
    "sg:postcode":"M4K 3T1",
    "sg:province":"ON",
    "sg:tags":[
        "physician",
        "surgeon"
    ],
    "wof:name":"Razack, Jameel MD",
    "wof:placetype":"venue"
},
  "geometry": {"coordinates":[-79.345116,43.680153],"type":"Point"}
}