{
  "type": "Feature",
  "properties": {
    "iso:country":"CA",
    "sg:address":"16910 128A Ave NW",
    "sg:city":"Edmonton",
    "sg:classifiers":[
        {
            "category":"Retail",
            "subcategory":"Auto Repair",
            "type":"Services"
        }
    ],
    "sg:phone":"+1 780 450 1258",
    "sg:postcode":"T5V 1K7",
    "sg:province":"AB",
    "sg:tags":[
        "repairing",
        "tire"
    ],
    "wof:name":"Canadian Treads",
    "wof:placetype":"venue"
},
  "geometry": {"coordinates":[-113.612976074,53.5858802795],"type":"Point"}
}