{
  "type": "Feature",
  "properties": {
    "addr:full":"12585 Av Nicolas-Joly Montreal QC H1E 1V1",
    "addr:housenumber":"12585",
    "addr:postcode":"h1e 1v1",
    "addr:street":"Av Nicolas-Joly",
    "iso:country":"CA",
    "sg:address":"12585 Av Nicolas-Joly",
    "sg:city":"Montreal",
    "sg:classifiers":[
        {
            "category":"Social Services",
            "type":"Services"
        }
    ],
    "sg:phone":"+1 514 494 0434",
    "sg:postcode":"H1E 1V1",
    "sg:province":"QC",
    "sg:tags":[
        "organization",
        "welfare"
    ],
    "wof:name":"Centre Communautaire Le Phare",
    "wof:placetype":"venue"
},
  "geometry": {"coordinates":[-73.600677,45.637501],"type":"Point"}
}