{
  "type": "Feature",
  "properties": {
    "iso:country":"CA",
    "sg:city":"Barrie",
    "sg:classifiers":[
        {
            "category":"Health Services",
            "subcategory":"Chiropractor",
            "type":"Services"
        }
    ],
    "sg:phone":"+1 705 725 8282",
    "sg:postcode":"L4N 5G5",
    "sg:province":"ON",
    "wof:name":"Leacock Family Chiropractic",
    "wof:placetype":"venue"
},
  "geometry": {"coordinates":[-79.72240447999999,44.391166687],"type":"Point"}
}