{
  "type": "Feature",
  "properties": {
    "iso:country":"CA",
    "sg:city":"Ottawa",
    "sg:classifiers":[
        {
            "category":"Communications",
            "subcategory":"News Services",
            "type":"Services"
        }
    ],
    "sg:phone":"+1 613 231 8401",
    "sg:postcode":"K1P 5A4",
    "sg:province":"ON",
    "wof:name":"Mac Lean's Magazine News",
    "wof:placetype":"venue"
},
  "geometry": {"coordinates":[-75.700249,45.422337],"type":"Point"}
}