{
  "type": "Feature",
  "properties": {
    "iso:country":"CA",
    "sg:address":"41 Broadway St W # 60",
    "sg:city":"Yorkton",
    "sg:classifiers":[
        {
            "category":"Health Services",
            "subcategory":"Chiropractor",
            "type":"Services"
        }
    ],
    "sg:phone":"+1 306 783 3722",
    "sg:postcode":"S3N 0L6",
    "sg:province":"SK",
    "wof:name":"Howlett, James D DC",
    "wof:placetype":"venue"
},
  "geometry": {"coordinates":[-102.46568298299999,51.2103309631],"type":"Point"}
}