{
  "type": "Feature",
  "properties": {
    "addr:full":"3675 Boul DE LA Grande-Baie N LA Baie QC G7B 3N8",
    "addr:housenumber":"3675",
    "addr:postcode":"g7b 3n8",
    "addr:street":"Boul De La Grande-Baie N",
    "iso:country":"CA",
    "sg:address":"3675 Boul DE LA Grande-Baie N",
    "sg:city":"LA Baie",
    "sg:classifiers":[
        {
            "category":"Retail",
            "subcategory":"Auto Repair",
            "type":"Services"
        }
    ],
    "sg:phone":"+1 418 549 0589",
    "sg:postcode":"G7B 3N8",
    "sg:province":"QC",
    "sg:tags":[
        "repairing",
        "automobile",
        "radiator"
    ],
    "wof:name":"Radiateur Serge Tremblay Inc",
    "wof:placetype":"venue"
},
  "geometry": {"coordinates":[-70.9449462891,48.372467041],"type":"Point"}
}