{
  "type": "Feature",
  "properties": {
    "addr:full":"357 Oakwood Ave York ON M6E 2W1",
    "addr:housenumber":"357",
    "addr:postcode":"m6e 2w1",
    "addr:street":"Oakwood Ave",
    "iso:country":"CA",
    "sg:address":"357 Oakwood Ave",
    "sg:city":"York",
    "sg:classifiers":[
        {
            "category":"Manufacturing",
            "subcategory":"Printing",
            "type":"Manufacturing & Wholesale Goods"
        }
    ],
    "sg:phone":"+1 416 656 4968",
    "sg:postcode":"M6E 2W1",
    "sg:province":"ON",
    "sg:tags":[
        "printer"
    ],
    "wof:name":"Goldings Graphic Ctr",
    "wof:placetype":"venue"
},
  "geometry": {"coordinates":[-79.4384,43.68689],"type":"Point"}
}