{
  "type": "Feature",
  "properties": {
    "addr:full":"833 Fifth Ave Bassano AB T0J 0B0",
    "addr:housenumber":"833",
    "addr:postcode":"t0j 0b0",
    "addr:street":"Fifth Ave",
    "iso:country":"CA",
    "sg:address":"833 Fifth Ave",
    "sg:city":"Bassano",
    "sg:classifiers":[
        {
            "category":"Freight",
            "type":"Transportation"
        }
    ],
    "sg:phone":"+1 403 641 3655",
    "sg:postcode":"T0J 0B0",
    "sg:province":"AB",
    "sg:tags":[
        "sand",
        "gravel",
        "trucking"
    ],
    "wof:name":"Zibell Trucking",
    "wof:placetype":"venue"
},
  "geometry": {"coordinates":[-112.45761108400001,50.7887916565],"type":"Point"}
}