{
  "type": "Feature",
  "properties": {
    "addr:full":"3270 Berry Rd Winfield BC V4V 1T8",
    "addr:housenumber":"3270",
    "addr:postcode":"v4v 1t8",
    "addr:street":"Berry Rd",
    "iso:country":"CA",
    "sg:address":"3270 Berry Rd",
    "sg:city":"Winfield",
    "sg:classifiers":[
        {
            "category":"Recreation",
            "type":"Entertainment"
        }
    ],
    "sg:phone":"+1 250 766 4131",
    "sg:postcode":"V4V 1T8",
    "sg:province":"BC",
    "sg:tags":[
        "hall",
        "auditorium"
    ],
    "wof:name":"Winfield Memorial Hall Assn",
    "wof:placetype":"venue"
},
  "geometry": {"coordinates":[-119.402275,50.029621],"type":"Point"}
}