{
  "type": "Feature",
  "properties": {
    "addr:full":"30 Heritage Rd Markham ON L3P 1M4",
    "addr:housenumber":"30",
    "addr:postcode":"l3p 1m4",
    "addr:street":"Heritage Rd",
    "iso:country":"CA",
    "sg:address":"30 Heritage Rd",
    "sg:city":"Markham",
    "sg:classifiers":[
        {
            "category":"Wholesale",
            "subcategory":"Motor Vehicles",
            "type":"Manufacturing & Wholesale Goods"
        }
    ],
    "sg:phone":"+1 905 294 5607",
    "sg:postcode":"L3P 1M4",
    "sg:province":"ON",
    "sg:tags":[
        "bus",
        "line",
        "rental"
    ],
    "wof:name":"Laidlaw Transit Ltd",
    "wof:placetype":"venue"
},
  "geometry": {"coordinates":[-79.280518,43.871067],"type":"Point"}
}