{
  "type": "Feature",
  "properties": {
    "addr:full":"Duncan BC V9L 2P2",
    "addr:postcode":"v9l 2p2",
    "iso:country":"CA",
    "sg:city":"Duncan",
    "sg:classifiers":[
        {
            "category":"Shopping",
            "subcategory":"Luggage & Leather Goods",
            "type":"Retail Goods"
        }
    ],
    "sg:phone":"+1 250 748 8009",
    "sg:postcode":"V9L 2P2",
    "sg:province":"BC",
    "wof:name":"Pack Your Bags",
    "wof:placetype":"venue"
},
  "geometry": {"coordinates":[-123.703423,48.776711],"type":"Point"}
}