{
  "type": "Feature",
  "properties": {
    "addr:full":"1862 Vernon St Lumby BC V0E 2G0",
    "addr:housenumber":"1862",
    "addr:postcode":"v0e 2g0",
    "addr:street":"Vernon St",
    "iso:country":"CA",
    "sg:address":"1862 Vernon St",
    "sg:city":"Lumby",
    "sg:classifiers":[
        {
            "category":"Building & Trades",
            "subcategory":"Equipment Rental",
            "type":"Services"
        }
    ],
    "sg:phone":"+1 250 547 9317",
    "sg:postcode":"V0E 2G0",
    "sg:province":"BC",
    "sg:tags":[
        "yard"
    ],
    "wof:name":"Lumby Rental",
    "wof:placetype":"venue"
},
  "geometry": {"coordinates":[-118.966888428,50.2472686768],"type":"Point"}
}