{
  "type": "Feature",
  "properties": {
    "addr:full":"927 Boul Saint-Germain Rimouski QC G5L 3V1",
    "addr:housenumber":"927",
    "addr:postcode":"g5l 3v1",
    "addr:street":"Boul Saint-Germain",
    "iso:country":"CA",
    "sg:address":"927 Boul Saint-Germain",
    "sg:city":"Rimouski",
    "sg:classifiers":[
        {
            "category":"Building & Trades",
            "subcategory":"Landscaping Services",
            "type":"Services"
        }
    ],
    "sg:phone":"+1 418 722 4948",
    "sg:postcode":"G5L 3V1",
    "sg:province":"QC",
    "sg:tags":[
        "horticultural",
        "consultant"
    ],
    "wof:name":"Serres DE Sacre-Coeur Inc",
    "wof:placetype":"venue"
},
  "geometry": {"coordinates":[-68.596046,48.42519],"type":"Point"}
}