{
  "type": "Feature",
  "properties": {
    "addr:full":"2035 Winston Park Dr Oakville ON L6H 6P5",
    "addr:housenumber":"2035",
    "addr:postcode":"l6h 6p5",
    "addr:street":"Winston Park Dr",
    "iso:country":"CA",
    "sg:address":"2035 Winston Park Dr",
    "sg:city":"Oakville",
    "sg:classifiers":[
        {
            "category":"Restaurant",
            "type":"Food & Drink"
        }
    ],
    "sg:phone":"+1 905 829 3233",
    "sg:postcode":"L6H 6P5",
    "sg:province":"ON",
    "wof:name":"East Side Mario's",
    "wof:placetype":"venue"
},
  "geometry": {"coordinates":[-79.668457,43.508102],"type":"Point"}
}