{
  "type": "Feature",
  "properties": {
    "addr:full":"300 Lincoln St Welland ON L3B 4N4",
    "addr:housenumber":"300",
    "addr:postcode":"l3b 4n4",
    "addr:street":"Lincoln St",
    "iso:country":"CA",
    "sg:address":"300 Lincoln St",
    "sg:city":"Welland",
    "sg:classifiers":[
        {
            "category":"Shopping",
            "subcategory":"Shoes",
            "type":"Retail Goods"
        }
    ],
    "sg:phone":"+1 905 735 1957",
    "sg:postcode":"L3B 4N4",
    "sg:province":"ON",
    "wof:name":"Caesar Imports Shoes & Leather",
    "wof:placetype":"venue"
},
  "geometry": {"coordinates":[-79.2400970459,42.9841651917],"type":"Point"}
}