{
  "type": "Feature",
  "properties": {
    "addr:full":"814 14th St Fort Macleod AB T0L 0Z0",
    "addr:housenumber":"814",
    "addr:postcode":"t0l 0z0",
    "addr:street":"14Th St",
    "iso:country":"CA",
    "sg:address":"814 14th St",
    "sg:city":"Fort Macleod",
    "sg:classifiers":[
        {
            "category":"Freight",
            "type":"Transportation"
        }
    ],
    "sg:phone":"+1 403 553 3775",
    "sg:postcode":"T0L 0Z0",
    "sg:province":"AB",
    "sg:tags":[
        "trucking"
    ],
    "wof:name":"Boot Trucking Ltd",
    "wof:placetype":"venue"
},
  "geometry": {"coordinates":[-113.391197205,49.7177238464],"type":"Point"}
}