{
  "type": "Feature",
  "properties": {
    "addr:full":"Toronto ON M4S 2B4",
    "addr:postcode":"m4s 2b4",
    "iso:country":"CA",
    "sg:city":"Toronto",
    "sg:classifiers":[
        {
            "category":"Social Services",
            "subcategory":"Job Training",
            "type":"Services"
        }
    ],
    "sg:phone":"+1 416 486 0605",
    "sg:postcode":"M4S 2B4",
    "sg:province":"ON",
    "sg:tags":[
        "employment"
    ],
    "wof:name":"Career Essentials",
    "wof:placetype":"venue"
},
  "geometry": {"coordinates":[-79.39799499510001,43.7058105469],"type":"Point"}
}