{
  "type": "Feature",
  "properties": {
    "addr:full":"59 Hunt Cres NE Medicine Hat AB T1C 1X8",
    "addr:housenumber":"59",
    "addr:postcode":"t1c 1x8",
    "addr:street":"Hunt Cres Ne",
    "iso:country":"CA",
    "sg:address":"59 Hunt Cres NE",
    "sg:city":"Medicine Hat",
    "sg:classifiers":[
        {
            "category":"Building & Trades",
            "subcategory":"Construction",
            "type":"Services"
        }
    ],
    "sg:phone":"+1 403 527 2522",
    "sg:postcode":"T1C 1X8",
    "sg:province":"AB",
    "sg:tags":[
        "excavating",
        "contractor"
    ],
    "wof:name":"Gas City Ditching",
    "wof:placetype":"venue"
},
  "geometry": {"coordinates":[-110.67378234900001,50.0659828186],"type":"Point"}
}