{
  "type": "Feature",
  "properties": {
    "addr:full":"Dundas ON L9H 5E1",
    "addr:postcode":"l9h 5e1",
    "iso:country":"CA",
    "sg:city":"Dundas",
    "sg:classifiers":[
        {
            "category":"Shopping",
            "subcategory":"Gifts & Souvenirs",
            "type":"Retail Goods"
        }
    ],
    "sg:phone":"+1 905 627 1304",
    "sg:postcode":"L9H 5E1",
    "sg:province":"ON",
    "sg:tags":[
        "shop"
    ],
    "wof:name":"Site of the Green",
    "wof:placetype":"venue"
},
  "geometry": {"coordinates":[-79.952377,43.263779],"type":"Point"}
}