{
  "type": "Feature",
  "properties": {
    "addr:full":"1221 Boul Rene-Levesque O Montreal QC H3G 1T1",
    "addr:housenumber":"1221",
    "addr:postcode":"h3g 1t1",
    "addr:street":"Boul Rene-Levesque O",
    "iso:country":"CA",
    "sg:address":"1221 Boul Rene-Levesque O",
    "sg:city":"Montreal",
    "sg:classifiers":[
        {
            "category":"Restaurant",
            "type":"Food & Drink"
        }
    ],
    "sg:phone":"+1 514 390 0090",
    "sg:postcode":"H3G 1T1",
    "sg:province":"QC",
    "wof:name":"Queue DE Cheval Restaurant",
    "wof:placetype":"venue"
},
  "geometry": {"coordinates":[-73.553833,45.517601],"type":"Point"}
}