{
  "type": "Feature",
  "properties": {
    "addr:full":"73 Falkland St Lunenburg NS B0J 2C0",
    "addr:housenumber":"73",
    "addr:postcode":"b0j 2c0",
    "addr:street":"Falkland St",
    "iso:country":"CA",
    "sg:address":"73 Falkland St",
    "sg:city":"Lunenburg",
    "sg:phone":"+1 902 634 3835",
    "sg:postcode":"B0J 2C0",
    "sg:province":"NS",
    "sg:tags":[
        "oil"
    ],
    "wof:name":"West Nova Fuels Ltd",
    "wof:placetype":"venue"
},
  "geometry": {"coordinates":[-64.3196716309,44.3760490417],"type":"Point"}
}