{
  "type": "Feature",
  "properties": {
    "addr:full":"8006 Wellington Rd # 109 Arthur ON N0G 1A0",
    "addr:housenumber":"8006",
    "addr:postcode":"n0g 1a0",
    "addr:street":"Wellington Rd # 109 Arthur",
    "iso:country":"CA",
    "sg:address":"8006 Wellington Rd # 109",
    "sg:city":"Arthur",
    "sg:classifiers":[
        {
            "category":"Autos & Motor Vehicles",
            "subcategory":"Fuel & Gas Station",
            "type":"Retail Goods"
        }
    ],
    "sg:phone":"+1 519 848 6804",
    "sg:postcode":"N0G 1A0",
    "sg:province":"ON",
    "sg:tags":[
        "oil"
    ],
    "wof:name":"Pioneer Petroleum Inc",
    "wof:placetype":"venue"
},
  "geometry": {"coordinates":[-80.52967099999999,43.828156],"type":"Point"}
}