{
  "type": "Feature",
  "properties": {
    "addr:full":"443 Boul Bourque Omerville QC J1X 4G3",
    "addr:housenumber":"443",
    "addr:postcode":"j1x 4g3",
    "addr:street":"Boul Bourque",
    "iso:country":"CA",
    "sg:address":"443 Boul Bourque",
    "sg:city":"Omerville",
    "sg:classifiers":[
        {
            "category":"Wholesale",
            "subcategory":"Machinery & Supplies",
            "type":"Manufacturing & Wholesale Goods"
        }
    ],
    "sg:phone":"+1 819 843 7744",
    "sg:postcode":"J1X 4G3",
    "sg:province":"QC",
    "sg:tags":[
        "engine"
    ],
    "wof:name":"Brodeur & Simard Enr",
    "wof:placetype":"venue"
},
  "geometry": {"coordinates":[-72.110298,45.291695],"type":"Point"}
}