{
  "type": "Feature",
  "properties": {
    "addr:full":"2318 Loughborough View Dr Battersea ON K0H 1H0",
    "addr:housenumber":"2318",
    "addr:postcode":"k0h 1h0",
    "addr:street":"Loughborough View Dr",
    "iso:country":"CA",
    "sg:address":"2318 Loughborough View Dr",
    "sg:city":"Battersea",
    "sg:classifiers":[
        {
            "category":"Recreation",
            "subcategory":"Marina",
            "type":"Entertainment"
        }
    ],
    "sg:phone":"+1 613 353 6205",
    "sg:postcode":"K0H 1H0",
    "sg:province":"ON",
    "wof:name":"Loughborough Lake Marina",
    "wof:placetype":"venue"
},
  "geometry": {"coordinates":[-76.383461,44.432175],"type":"Point"}
}