{
  "type": "Feature",
  "properties": {
    "addr:full":"4430 Bathurst St North York ON M3H 3S3",
    "addr:housenumber":"4430",
    "addr:postcode":"m3h 3s3",
    "addr:street":"Bathurst St",
    "iso:country":"CA",
    "sg:address":"4430 Bathurst St",
    "sg:city":"North York",
    "sg:classifiers":[
        {
            "category":"Health Services",
            "subcategory":"Health Practitioner",
            "type":"Services"
        }
    ],
    "sg:phone":"+1 416 633 9152",
    "sg:postcode":"M3H 3S3",
    "sg:province":"ON",
    "sg:tags":[
        "psychotherapist"
    ],
    "wof:name":"Pupko, H",
    "wof:placetype":"venue"
},
  "geometry": {"coordinates":[-79.4390869141,43.757270813],"type":"Point"}
}