{
  "type": "Feature",
  "properties": {
    "addr:full":"8653 River Rd S Dewdney BC V0M 1H0",
    "addr:housenumber":"8653",
    "addr:postcode":"v0m 1h0",
    "addr:street":"River Rd",
    "iso:country":"CA",
    "sg:address":"8653 River Rd S",
    "sg:city":"Dewdney",
    "sg:classifiers":[
        {
            "category":"Home & Garden",
            "subcategory":"Building Materials",
            "type":"Retail Goods"
        }
    ],
    "sg:phone":"+1 604 826 6277",
    "sg:postcode":"V0M 1H0",
    "sg:province":"BC",
    "wof:name":"Stave Lake Cedar Mills Inc",
    "wof:placetype":"venue"
},
  "geometry": {"coordinates":[-122.201072693,49.1608657837],"type":"Point"}
}