{
  "type": "Feature",
  "properties": {
    "addr:full":"11900 80 Ave Delta BC V4C 1Y2",
    "addr:housenumber":"11900",
    "addr:postcode":"v4c 1y2",
    "addr:street":"80 Ave",
    "iso:country":"CA",
    "sg:address":"11900 80 Ave",
    "sg:city":"Delta",
    "sg:classifiers":[
        {
            "category":"Health Services",
            "subcategory":"Chiropractor",
            "type":"Services"
        }
    ],
    "sg:phone":"+1 604 596 7355",
    "sg:postcode":"V4C 1Y2",
    "sg:province":"BC",
    "wof:name":"Peter Douwes Chiropractic Corp",
    "wof:placetype":"venue"
},
  "geometry": {"coordinates":[-122.893493652,49.1485481262],"type":"Point"}
}