{
  "type": "Feature",
  "properties": {
    "addr:full":"5134 Rue Frontenac Lac-Megantic QC G6B 1H3",
    "addr:housenumber":"5134",
    "addr:postcode":"g6b 1h3",
    "addr:street":"Rue Frontenac Lac-Megantic",
    "iso:country":"CA",
    "sg:address":"5134 Rue Frontenac",
    "sg:city":"Lac-Megantic",
    "sg:classifiers":[
        {
            "category":"Shopping",
            "subcategory":"Shoes",
            "type":"Retail Goods"
        }
    ],
    "sg:phone":"+1 819 583 1450",
    "sg:postcode":"G6B 1H3",
    "sg:province":"QC",
    "wof:name":"Chaussures Pop",
    "wof:placetype":"venue"
},
  "geometry": {"coordinates":[-70.883957,45.576946],"type":"Point"}
}