{
  "type": "Feature",
  "properties": {
    "addr:full":"80 Frobisher Dr Waterloo ON N2V 2A1",
    "addr:housenumber":"80",
    "addr:postcode":"n2v 2a1",
    "addr:street":"Frobisher Dr",
    "iso:country":"CA",
    "sg:address":"80 Frobisher Dr",
    "sg:city":"Waterloo",
    "sg:classifiers":[
        {
            "category":"Retail",
            "subcategory":"Auto Repair",
            "type":"Services"
        }
    ],
    "sg:phone":"+1 519 888 6630",
    "sg:postcode":"N2V 2A1",
    "sg:province":"ON",
    "sg:tags":[
        "repairing",
        "automobile"
    ],
    "wof:name":"Petersen Auto Electric Ltd",
    "wof:placetype":"venue"
},
  "geometry": {"coordinates":[-80.531639,43.503864],"type":"Point"}
}