{
  "type": "Feature",
  "properties": {
    "addr:full":"Westmount QC H3Z 1N1",
    "addr:postcode":"h3z 1n1",
    "iso:country":"CA",
    "sg:city":"Westmount",
    "sg:classifiers":[
        {
            "category":"Professional",
            "subcategory":"Advertising",
            "type":"Services"
        }
    ],
    "sg:phone":"+1 514 489 5359",
    "sg:postcode":"H3Z 1N1",
    "sg:province":"QC",
    "wof:name":"Ppac Apoc",
    "wof:placetype":"venue"
},
  "geometry": {"coordinates":[-73.6012496948,45.4764556885],"type":"Point"}
}