{
  "type": "Feature",
  "properties": {
    "addr:full":"15 Shaw St S Herbert SK S0H 2A0",
    "addr:housenumber":"15",
    "addr:postcode":"s0h 2a0",
    "addr:street":"Shaw St S Herbert",
    "iso:country":"CA",
    "sg:address":"15 Shaw St S",
    "sg:city":"Herbert",
    "sg:classifiers":[
        {
            "category":"Retail",
            "subcategory":"Auto Repair",
            "type":"Services"
        }
    ],
    "sg:phone":"+1 306 784 3104",
    "sg:postcode":"S0H 2A0",
    "sg:province":"SK",
    "sg:tags":[
        "repairing",
        "automobile"
    ],
    "wof:name":"Wiens Auto Svc",
    "wof:placetype":"venue"
},
  "geometry": {"coordinates":[-107.21916198700001,50.4309844971],"type":"Point"}
}