{
  "type": "Feature",
  "properties": {
    "addr:full":"1037 Pinecrest Rd Ottawa ON K2B 6B6",
    "addr:housenumber":"1037",
    "addr:postcode":"k2b 6b6",
    "addr:street":"Pinecrest Rd",
    "iso:country":"CA",
    "sg:address":"1037 Pinecrest Rd",
    "sg:city":"Ottawa",
    "sg:classifiers":[
        {
            "category":"Retail",
            "subcategory":"Auto Repair",
            "type":"Services"
        }
    ],
    "sg:phone":"+1 613 828 3213",
    "sg:postcode":"K2B 6B6",
    "sg:province":"ON",
    "sg:tags":[
        "repairing",
        "automobile"
    ],
    "wof:name":"Roy Rump & Sons Automotive",
    "wof:placetype":"venue"
},
  "geometry": {"coordinates":[-75.791039,45.351913],"type":"Point"}
}