{
  "type": "Feature",
  "properties": {
    "addr:full":"202 10th St Beaverlodge AB T0H 0C0",
    "addr:housenumber":"202",
    "addr:postcode":"t0h 0c0",
    "addr:street":"10Th St",
    "iso:country":"CA",
    "sg:address":"202 10th St",
    "sg:city":"Beaverlodge",
    "sg:classifiers":[
        {
            "category":"Autos & Motor Vehicles",
            "subcategory":"Automobile Sales",
            "type":"Retail Goods"
        }
    ],
    "sg:phone":"+1 780 354 2241",
    "sg:postcode":"T0H 0C0",
    "sg:province":"AB",
    "sg:tags":[
        "car",
        "dealer"
    ],
    "wof:name":"Tartan Ford",
    "wof:placetype":"venue"
},
  "geometry": {"coordinates":[-119.428482,55.210022],"type":"Point"}
}