{
  "type": "Feature",
  "properties": {
    "addr:full":"1735 Rue Saint-Denis Montreal QC H2X 3K4",
    "addr:housenumber":"1735",
    "addr:postcode":"h2x 3k4",
    "addr:street":"Rue Saint-Denis",
    "iso:country":"CA",
    "sg:address":"1735 Rue Saint-Denis",
    "sg:city":"Montreal",
    "sg:classifiers":[
        {
            "category":"Restaurant",
            "type":"Food & Drink"
        }
    ],
    "sg:phone":"+1 514 844 5542",
    "sg:postcode":"H2X 3K4",
    "sg:province":"QC",
    "wof:name":"Aux Delices DE Szechuan",
    "wof:placetype":"venue"
},
  "geometry": {"coordinates":[-73.563835,45.51545],"type":"Point"}
}