{
  "type": "Feature",
  "properties": {
    "addr:full":"2706 Boul DE LA Concorde E Laval QC H7E 2B4",
    "addr:housenumber":"2706",
    "addr:postcode":"h7e 2b4",
    "addr:street":"Boul De La Concorde E",
    "iso:country":"CA",
    "sg:address":"2706 Boul DE LA Concorde E",
    "sg:city":"Laval",
    "sg:classifiers":[
        {
            "category":"Education",
            "subcategory":"Special Training",
            "type":"Public Place"
        }
    ],
    "sg:phone":"+1 450 667 4526",
    "sg:postcode":"H7E 2B4",
    "sg:province":"QC",
    "sg:tags":[
        "instruction",
        "music"
    ],
    "wof:name":"Ecole DE Piano F Chopin Enr",
    "wof:placetype":"venue"
},
  "geometry": {"coordinates":[-73.670647,45.589767],"type":"Point"}
}