{
  "type": "Feature",
  "properties": {
    "addr:full":"15341 Sequoia Dr Surrey BC V3S 8N4",
    "addr:housenumber":"15341",
    "addr:postcode":"v3s 8n4",
    "addr:street":"Sequoia Dr",
    "iso:country":"CA",
    "sg:address":"15341 Sequoia Dr",
    "sg:city":"Surrey",
    "sg:classifiers":[
        {
            "category":"Wholesale",
            "subcategory":"Groceries",
            "type":"Manufacturing & Wholesale Goods"
        }
    ],
    "sg:phone":"+1 604 575 6218",
    "sg:postcode":"V3S 8N4",
    "sg:province":"BC",
    "sg:tags":[
        "grocer"
    ],
    "wof:name":"Plumrose",
    "wof:placetype":"venue"
},
  "geometry": {"coordinates":[-122.796844482,49.1465530396],"type":"Point"}
}