{
  "type": "Feature",
  "properties": {
    "addr:full":"550 King St E Kitchener ON N2G 2L8",
    "addr:housenumber":"550",
    "addr:postcode":"n2g 2l8",
    "addr:street":"King St E",
    "iso:country":"CA",
    "sg:address":"550 King St E",
    "sg:city":"Kitchener",
    "sg:classifiers":[
        {
            "category":"Personal",
            "subcategory":"Beauty Salon",
            "type":"Services"
        }
    ],
    "sg:phone":"+1 519 886 5020",
    "sg:postcode":"N2G 2L8",
    "sg:province":"ON",
    "wof:name":"Creative Image",
    "wof:placetype":"venue"
},
  "geometry": {"coordinates":[-80.47998046879999,43.445728302],"type":"Point"}
}