{
  "type": "Feature",
  "properties": {
    "addr:full":"473 Queen St E Toronto ON M5A 1T9",
    "addr:housenumber":"473",
    "addr:postcode":"m5a 1t9",
    "addr:street":"Queen St E",
    "iso:country":"CA",
    "sg:address":"473 Queen St E",
    "sg:city":"Toronto",
    "sg:classifiers":[
        {
            "category":"Professional",
            "subcategory":"Research",
            "type":"Services"
        }
    ],
    "sg:phone":"+1 416 363 2287",
    "sg:postcode":"M5A 1T9",
    "sg:province":"ON",
    "sg:tags":[
        "market",
        "analysis"
    ],
    "wof:name":"Informa Market Research CO Ltd",
    "wof:placetype":"venue"
},
  "geometry": {"coordinates":[-79.3592834473,43.6566009521],"type":"Point"}
}