{
  "type": "Feature",
  "properties": {
    "addr:full":"2859 Howard Ave Windsor ON N8X 3Y4",
    "addr:housenumber":"2859",
    "addr:postcode":"n8x 3y4",
    "addr:street":"Howard Ave",
    "iso:country":"CA",
    "sg:address":"2859 Howard Ave",
    "sg:city":"Windsor",
    "sg:classifiers":[
        {
            "category":"Home & Garden",
            "subcategory":"Furniture",
            "type":"Retail Goods"
        }
    ],
    "sg:phone":"+1 519 966 7003",
    "sg:postcode":"N8X 3Y4",
    "sg:province":"ON",
    "wof:name":"Barbecue Shoppe",
    "wof:placetype":"venue"
},
  "geometry": {"coordinates":[-83.0093154907,42.2803382874],"type":"Point"}
}