{
  "type": "Feature",
  "properties": {
    "addr:full":"Cabano QC G0L 1E0",
    "addr:postcode":"g0l 1e0",
    "iso:country":"CA",
    "sg:city":"Cabano",
    "sg:classifiers":[
        {
            "category":"Professional",
            "subcategory":"Accounting & Tax Preparation",
            "type":"Services"
        }
    ],
    "sg:phone":"+1 418 854 2122",
    "sg:postcode":"G0L 1E0",
    "sg:province":"QC",
    "sg:tags":[
        "accountant"
    ],
    "wof:name":"Raymond Chabot Grant Thornton",
    "wof:placetype":"venue"
},
  "geometry": {"coordinates":[-68.8793334961,47.6837081909],"type":"Point"}
}