{
  "type": "Feature",
  "properties": {
    "iso:country":"CA",
    "sg:address":"297 Dundas St E",
    "sg:city":"Waterdown",
    "sg:classifiers":[
        {
            "category":"Restaurant",
            "type":"Food & Drink"
        }
    ],
    "sg:phone":"+1 905 690 9987",
    "sg:postcode":"L0R 2H0",
    "sg:province":"ON",
    "sg:tags":[
        "tea",
        "rooms"
    ],
    "wof:name":"Tea At the White House",
    "wof:placetype":"venue"
},
  "geometry": {"coordinates":[-79.894089,43.332539],"type":"Point"}
}