{
  "type": "Feature",
  "properties": {
    "iso:country":"CA",
    "sg:address":"90 Emerald St S",
    "sg:city":"Hamilton",
    "sg:classifiers":[
        {
            "category":"Health Services",
            "subcategory":"Clinic",
            "type":"Services"
        }
    ],
    "sg:phone":"+1 905 523 5055",
    "sg:postcode":"L8N 2V3",
    "sg:province":"ON",
    "sg:tags":[
        "mental"
    ],
    "wof:name":"St Patrick's Lodge",
    "wof:placetype":"venue"
},
  "geometry": {"coordinates":[-79.8556594849,43.2503852844],"type":"Point"}
}