{
  "type": "Feature",
  "properties": {
    "iso:country":"CA",
    "sg:address":"20 Wellington St",
    "sg:city":"Brantford",
    "sg:classifiers":[
        {
            "category":"Professional",
            "subcategory":"Lawyer & Legal Services",
            "type":"Services"
        }
    ],
    "sg:phone":"+1 519 759 6220",
    "sg:postcode":"N3T 2L4",
    "sg:province":"ON",
    "sg:tags":[
        "attorney"
    ],
    "wof:name":"Hitchon, James A",
    "wof:placetype":"venue"
},
  "geometry": {"coordinates":[-80.266968,43.141148],"type":"Point"}
}