{
  "type": "Feature",
  "properties": {
    "addr:full":"869 Highway 60 Huntsville ON P1H 1B2",
    "addr:housenumber":"869",
    "addr:postcode":"p1h 1b2",
    "addr:street":"Highway 60",
    "iso:country":"CA",
    "sg:address":"869 Highway 60",
    "sg:city":"Huntsville",
    "sg:classifiers":[
        {
            "category":"Retail",
            "subcategory":"Veterinary Services",
            "type":"Services"
        }
    ],
    "sg:phone":"+1 705 789 5181",
    "sg:postcode":"P1H 1B2",
    "sg:province":"ON",
    "sg:tags":[
        "veterinarian"
    ],
    "wof:name":"Algonquin Animal Hospital",
    "wof:placetype":"venue"
},
  "geometry": {"coordinates":[-79.218002,45.326565],"type":"Point"}
}