{
  "type": "Feature",
  "properties": {
    "addr:full":"Etobicoke ON M9P 3B6",
    "addr:postcode":"m9p 3b6",
    "iso:country":"CA",
    "sg:city":"Etobicoke",
    "sg:classifiers":[
        {
            "category":"Shopping",
            "subcategory":"Clothing, Apparel, & Fashions",
            "type":"Retail Goods"
        }
    ],
    "sg:phone":"+1 416 247 9821",
    "sg:postcode":"M9P 3B6",
    "sg:province":"ON",
    "wof:name":"Chic Casuals",
    "wof:placetype":"venue"
},
  "geometry": {"coordinates":[-79.5305633545,43.6909103394],"type":"Point"}
}