{
  "type": "Feature",
  "properties": {
    "addr:full":"37 Melody Rd North York ON M9M 1C9",
    "addr:housenumber":"37",
    "addr:postcode":"m9m 1c9",
    "addr:street":"Melody Rd",
    "iso:country":"CA",
    "sg:address":"37 Melody Rd",
    "sg:city":"North York",
    "sg:classifiers":[
        {
            "category":"Freight",
            "type":"Transportation"
        }
    ],
    "sg:phone":"+1 416 744 7455",
    "sg:postcode":"M9M 1C9",
    "sg:province":"ON",
    "sg:tags":[
        "trucking"
    ],
    "wof:name":"Cross Border Logistics",
    "wof:placetype":"venue"
},
  "geometry": {"coordinates":[-79.53087600000001,43.719215],"type":"Point"}
}