{
  "type": "Feature",
  "properties": {
    "addr:full":"83 Westwood Ave East York ON M4K 2A7",
    "addr:housenumber":"83",
    "addr:postcode":"m4k 2a7",
    "addr:street":"Westwood Ave",
    "iso:country":"CA",
    "sg:address":"83 Westwood Ave",
    "sg:city":"East York",
    "sg:classifiers":[
        {
            "category":"Recreation",
            "type":"Entertainment"
        }
    ],
    "sg:phone":"+1 416 429 7200",
    "sg:postcode":"M4K 2A7",
    "sg:province":"ON",
    "sg:tags":[
        "ticket"
    ],
    "wof:name":"Special Ticket Entertainment",
    "wof:placetype":"venue"
},
  "geometry": {"coordinates":[-79.35243199999999,43.685539],"type":"Point"}
}