{
  "type": "Feature",
  "properties": {
    "addr:full":"8408 Elbow Dr SW Calgary AB T2V 1K7",
    "addr:housenumber":"8408",
    "addr:postcode":"t2v 1k7",
    "addr:street":"Elbow Dr Sw",
    "iso:country":"CA",
    "sg:address":"8408 Elbow Dr SW",
    "sg:city":"Calgary",
    "sg:classifiers":[
        {
            "category":"Organizations",
            "subcategory":"Political Organization",
            "type":"Services"
        }
    ],
    "sg:phone":"+1 403 253 9068",
    "sg:postcode":"T2V 1K7",
    "sg:province":"AB",
    "wof:name":"Liberal Centre",
    "wof:placetype":"venue"
},
  "geometry": {"coordinates":[-114.08296199999999,50.979309],"type":"Point"}
}