{
  "type": "Feature",
  "properties": {
    "addr:full":"304 Railway Ave E Eatonia SK S0L 0Y0",
    "addr:housenumber":"304",
    "addr:postcode":"s0l 0y0",
    "addr:street":"Railway Ave E Eatonia",
    "iso:country":"CA",
    "sg:address":"304 Railway Ave E",
    "sg:city":"Eatonia",
    "sg:classifiers":[
        {
            "category":"Wholesale",
            "subcategory":"Farm Supplies",
            "type":"Manufacturing & Wholesale Goods"
        }
    ],
    "sg:phone":"+1 306 967 2211",
    "sg:postcode":"S0L 0Y0",
    "sg:province":"SK",
    "sg:tags":[
        "fertilizer"
    ],
    "wof:name":"G Macs Ag Team",
    "wof:placetype":"venue"
},
  "geometry": {"coordinates":[-109.389266968,51.2211494446],"type":"Point"}
}