{
  "type": "Feature",
  "properties": {
    "addr:full":"104 Main Ave E Sundre AB T0M 1X0",
    "addr:housenumber":"104",
    "addr:postcode":"t0m 1x0",
    "addr:street":"Main Ave E",
    "iso:country":"CA",
    "sg:address":"104 Main Ave E",
    "sg:city":"Sundre",
    "sg:classifiers":[
        {
            "category":"Autos & Motor Vehicles",
            "subcategory":"Automobile Sales",
            "type":"Retail Goods"
        }
    ],
    "sg:phone":"+1 403 638 3502",
    "sg:postcode":"T0M 1X0",
    "sg:province":"AB",
    "sg:tags":[
        "car",
        "dealer"
    ],
    "wof:name":"Sundre Motors Ltd",
    "wof:placetype":"venue"
},
  "geometry": {"coordinates":[-114.63904571499999,51.7971954346],"type":"Point"}
}