{
  "type": "Feature",
  "properties": {
    "addr:full":"2686 Fortress Dr Port Coquitlam BC V3C 6E3",
    "addr:postcode":"2686;v3c 6e3",
    "addr:street":"Fortress Dr",
    "iso:country":"CA",
    "sg:address":"2686 Fortress Dr",
    "sg:city":"Port Coquitlam",
    "sg:classifiers":[
        {
            "category":"Wholesale",
            "subcategory":"Painting Supplies",
            "type":"Manufacturing & Wholesale Goods"
        }
    ],
    "sg:phone":"+1 604 944 2922",
    "sg:postcode":"V3C 6E3",
    "sg:province":"BC",
    "sg:tags":[
        "wallpaper"
    ],
    "wof:name":"Design Source Intl Inc",
    "wof:placetype":"venue"
},
  "geometry": {"coordinates":[-122.78939800000001,49.229675],"type":"Point"}
}