{
  "type": "Feature",
  "properties": {
    "iso:country":"CA",
    "sg:city":"Saint John",
    "sg:classifiers":[
        {
            "category":"Banks & Credit Unions",
            "subcategory":"Bank",
            "type":"Services"
        }
    ],
    "sg:phone":"+1 506 633 7750",
    "sg:postcode":"E2J 3T3",
    "sg:province":"NB",
    "wof:name":"Cibc",
    "wof:placetype":"venue"
},
  "geometry": {"coordinates":[-66.0149307251,45.3108520508],"type":"Point"}
}