{
  "type": "Feature",
  "properties": {
    "iso:country":"CA",
    "sg:address":"6 Massey St",
    "sg:city":"Angus",
    "sg:classifiers":[
        {
            "category":"Home & Garden",
            "subcategory":"Furniture",
            "type":"Retail Goods"
        }
    ],
    "sg:phone":"+1 705 429 1679",
    "sg:postcode":"L0M 1B0",
    "sg:province":"ON",
    "wof:name":"George's Furniture & Aplliance",
    "wof:placetype":"venue"
},
  "geometry": {"coordinates":[-79.885208,44.314632],"type":"Point"}
}