{
  "type": "Feature",
  "properties": {
    "addr:full":"507 36 Ave SE Calgary AB T2G 1W5",
    "addr:postcode":"t2g 1w5",
    "addr:street":"507 36 Ave Se",
    "iso:country":"CA",
    "sg:address":"507 36 Ave SE",
    "sg:city":"Calgary",
    "sg:classifiers":[
        {
            "category":"Recreation",
            "type":"Entertainment"
        }
    ],
    "sg:phone":"+1 403 243 9880",
    "sg:postcode":"T2G 1W5",
    "sg:province":"AB",
    "sg:tags":[
        "martial",
        "arts",
        "instruction"
    ],
    "wof:name":"Calgary Aikikai",
    "wof:placetype":"venue"
},
  "geometry": {"coordinates":[-114.053283691,51.0212554932],"type":"Point"}
}