{
  "type": "Feature",
  "properties": {
    "addr:full":"318 Painted Post Dr Scarborough ON M1G 2M3",
    "addr:housenumber":"318",
    "addr:postcode":"m1g 2m3",
    "addr:street":"Painted Post Dr",
    "iso:country":"CA",
    "sg:address":"318 Painted Post Dr",
    "sg:city":"Scarborough",
    "sg:classifiers":[
        {
            "category":"Shopping",
            "type":"Retail Goods"
        }
    ],
    "sg:phone":"+1 416 431 6898",
    "sg:postcode":"M1G 2M3",
    "sg:province":"ON",
    "sg:tags":[
        "communications",
        "cellular",
        "consultant"
    ],
    "wof:name":"Suantec Inc",
    "wof:placetype":"venue"
},
  "geometry": {"coordinates":[-79.227051,43.768082],"type":"Point"}
}