{
  "type": "Feature",
  "properties": {
    "addr:full":"3589 Bleams Rd New Hamburg ON N3A 2J1",
    "addr:housenumber":"3589",
    "addr:postcode":"n3a 2j1",
    "addr:street":"Bleams Rd",
    "iso:country":"CA",
    "sg:address":"3589 Bleams Rd",
    "sg:city":"New Hamburg",
    "sg:classifiers":[
        {
            "category":"Real Estate",
            "subcategory":"Real Estate Operator",
            "type":"Services"
        }
    ],
    "sg:phone":"+1 519 662 4852",
    "sg:postcode":"N3A 2J1",
    "sg:province":"ON",
    "sg:tags":[
        "mall",
        "shopping",
        "center"
    ],
    "wof:name":"Countryside Shopping Ctr",
    "wof:placetype":"venue"
},
  "geometry": {"coordinates":[-80.693817,43.376369],"type":"Point"}
}