{
  "type": "Feature",
  "properties": {
    "addr:full":"775 Rue Principale Ile-Aux-Noix QC J0J 1G0",
    "addr:housenumber":"775",
    "addr:postcode":"j0j 1g0",
    "addr:street":"Rue Principale",
    "iso:country":"CA",
    "sg:address":"775 Rue Principale",
    "sg:city":"Ile-Aux-Noix",
    "sg:classifiers":[
        {
            "category":"Personal",
            "subcategory":"Beauty Salon",
            "type":"Services"
        }
    ],
    "sg:phone":"+1 450 291 3557",
    "sg:postcode":"J0J 1G0",
    "sg:province":"QC",
    "wof:name":"Institut DE Beaute Profil Enr",
    "wof:placetype":"venue"
},
  "geometry": {"coordinates":[-73.29394499999999,45.114899],"type":"Point"}
}