{
  "type": "Feature",
  "properties": {
    "addr:full":"34817 97 St Oliver BC V0H 1T0",
    "addr:housenumber":"34817",
    "addr:postcode":"bc v0h 1t0",
    "addr:street":"97 St",
    "iso:country":"CA",
    "sg:address":"34817 97 St",
    "sg:city":"Oliver",
    "sg:classifiers":[
        {
            "category":"Autos & Motor Vehicles",
            "subcategory":"Fuel & Gas Station",
            "type":"Retail Goods"
        }
    ],
    "sg:phone":"+1 250 498 0806",
    "sg:postcode":"V0H 1T0",
    "sg:province":"BC",
    "sg:tags":[
        "confectionery",
        "candy",
        "oil"
    ],
    "wof:name":"Oliver Town Pantry",
    "wof:placetype":"venue"
},
  "geometry": {"coordinates":[-119.55088000000001,49.180267],"type":"Point"}
}