{
  "type": "Feature",
  "properties": {
    "addr:full":"125 Queensway E Simcoe ON N3Y 4M5",
    "addr:housenumber":"125",
    "addr:postcode":"n3y 4m5",
    "addr:street":"Queensway E",
    "iso:country":"CA",
    "sg:address":"125 Queensway E",
    "sg:city":"Simcoe",
    "sg:classifiers":[
        {
            "category":"Shopping",
            "subcategory":"Pharmacy",
            "type":"Retail Goods"
        }
    ],
    "sg:phone":"+1 519 426 1032",
    "sg:postcode":"N3Y 4M5",
    "sg:province":"ON",
    "wof:name":"Drugstore Pharmacy",
    "wof:placetype":"venue"
},
  "geometry": {"coordinates":[-80.294037,42.848251],"type":"Point"}
}