{
  "type": "Feature",
  "properties": {
    "addr:full":"142 Rue Saint-Damien Drummondville QC J2B 5R9",
    "addr:housenumber":"142",
    "addr:postcode":"j2b 5r9",
    "addr:street":"Rue Saint-Damien",
    "iso:country":"CA",
    "sg:address":"142 Rue Saint-Damien",
    "sg:city":"Drummondville",
    "sg:classifiers":[
        {
            "category":"Autos & Motor Vehicles",
            "subcategory":"Automobile Sales",
            "type":"Retail Goods"
        }
    ],
    "sg:phone":"+1 819 478 8181",
    "sg:postcode":"J2B 5R9",
    "sg:province":"QC",
    "sg:tags":[
        "car",
        "dealer"
    ],
    "wof:name":"Parent Suzuki Automobiles",
    "wof:placetype":"venue"
},
  "geometry": {"coordinates":[-72.48335299999999,45.872765],"type":"Point"}
}