{
  "type": "Feature",
  "properties": {
    "addr:full":"Nisku AB T9E 7Y3",
    "addr:postcode":"t9e 7y3",
    "iso:country":"CA",
    "sg:city":"Nisku",
    "sg:classifiers":[
        {
            "category":"Wholesale",
            "subcategory":"Machinery & Supplies",
            "type":"Manufacturing & Wholesale Goods"
        }
    ],
    "sg:phone":"+1 780 955 3878",
    "sg:postcode":"T9E 7Y3",
    "sg:province":"AB",
    "sg:tags":[
        "crane",
        "derrick",
        "welding"
    ],
    "wof:name":"6 S Industries Inc",
    "wof:placetype":"venue"
},
  "geometry": {"coordinates":[-113.521019,53.339325],"type":"Point"}
}