{
  "type": "Feature",
  "properties": {
    "addr:full":"5247 Boul Decarie Montreal QC H3W 3C2",
    "addr:housenumber":"5247",
    "addr:postcode":"h3w 3c2",
    "addr:street":"Boul Decarie",
    "iso:country":"CA",
    "sg:address":"5247 Boul Decarie",
    "sg:city":"Montreal",
    "sg:classifiers":[
        {
            "category":"Shopping",
            "subcategory":"Optical Goods",
            "type":"Retail Goods"
        }
    ],
    "sg:phone":"+1 514 481 2368",
    "sg:postcode":"H3W 3C2",
    "sg:province":"QC",
    "sg:tags":[
        "optician"
    ],
    "wof:name":"E Jim Litresits Dispencing Opt",
    "wof:placetype":"venue"
},
  "geometry": {"coordinates":[-73.6311721802,45.4849357605],"type":"Point"}
}