{
  "type": "Feature",
  "properties": {
    "addr:full":"2924 Centre Rd St Catharines ON L2R 6P7",
    "addr:housenumber":"2924",
    "addr:postcode":"l2r 6p7",
    "addr:street":"Centre Rd",
    "iso:country":"CA",
    "sg:address":"2924 Centre Rd",
    "sg:city":"St Catharines",
    "sg:classifiers":[
        {
            "category":"Building & Trades",
            "subcategory":"Plumbing",
            "type":"Services"
        }
    ],
    "sg:phone":"+1 905 641 5204",
    "sg:postcode":"L2R 6P7",
    "sg:province":"ON",
    "sg:tags":[
        "septic"
    ],
    "wof:name":"Alf Hill & Son Plumbing",
    "wof:placetype":"venue"
},
  "geometry": {"coordinates":[-79.240112,43.162479],"type":"Point"}
}