{
  "type": "Feature",
  "properties": {
    "addr:full":"22 Bluesky Cres Richmond Hill ON L4C 8H9",
    "addr:housenumber":"22",
    "addr:postcode":"l4c 8h9",
    "addr:street":"Bluesky Cres",
    "iso:country":"CA",
    "sg:address":"22 Bluesky Cres",
    "sg:city":"Richmond Hill",
    "sg:classifiers":[
        {
            "category":"Building & Trades",
            "subcategory":"Pest Control",
            "type":"Services"
        }
    ],
    "sg:phone":"+1 905 508 5621",
    "sg:postcode":"L4C 8H9",
    "sg:province":"ON",
    "sg:tags":[
        "insect",
        "devices"
    ],
    "wof:name":"Bluesky Distributing",
    "wof:placetype":"venue"
},
  "geometry": {"coordinates":[-79.429726,43.861965],"type":"Point"}
}