{
  "type": "Feature",
  "properties": {
    "iso:country":"CA",
    "sg:address":"165 Augusta Dr",
    "sg:city":"Winnipeg",
    "sg:classifiers":[
        {
            "category":"Building & Trades",
            "subcategory":"Plumbing",
            "type":"Services"
        }
    ],
    "sg:phone":"+1 204 261 4805",
    "sg:postcode":"R3T 4H3",
    "sg:province":"MB",
    "sg:tags":[
        "contractor"
    ],
    "wof:name":"Condie Plumbing & Heating Ltd",
    "wof:placetype":"venue"
},
  "geometry": {"coordinates":[-97.1667633057,49.8076477051],"type":"Point"}
}