{
  "type": "Feature",
  "properties": {
    "addr:full":"800 Rue Drouin Poularies QC J0Z 3E0",
    "addr:housenumber":"800",
    "addr:postcode":"j0z 3e0",
    "addr:street":"Rue Drouin",
    "iso:country":"CA",
    "sg:address":"800 Rue Drouin",
    "sg:city":"Poularies",
    "sg:classifiers":[
        {
            "category":"Education",
            "subcategory":"School",
            "type":"Public Place"
        }
    ],
    "sg:phone":"+1 819 782 5150",
    "sg:postcode":"J0Z 3E0",
    "sg:province":"QC",
    "wof:name":"Pavillon DE Poularies",
    "wof:placetype":"venue"
},
  "geometry": {"coordinates":[-78.986839,48.661701],"type":"Point"}
}