{
  "type": "Feature",
  "properties": {
    "addr:full":"8685 Rue Pascal-Gagnon Saint-Leonard QC H1P 1Y5",
    "addr:housenumber":"8685",
    "addr:postcode":"h1p 1y5",
    "addr:street":"Rue Pascal-Gagnon",
    "iso:country":"CA",
    "sg:address":"8685 Rue Pascal-Gagnon",
    "sg:city":"Saint-Leonard",
    "sg:classifiers":[
        {
            "category":"Building & Trades",
            "subcategory":"Construction",
            "type":"Services"
        }
    ],
    "sg:phone":"+1 514 993 8860",
    "sg:postcode":"H1P 1Y5",
    "sg:province":"QC",
    "sg:tags":[
        "repairing",
        "cabinet",
        "remodeling",
        "maker",
        "contractor"
    ],
    "wof:name":"Entrepreneur General Specialse",
    "wof:placetype":"venue"
},
  "geometry": {"coordinates":[-73.589043,45.602718],"type":"Point"}
}