{
  "type": "Feature",
  "properties": {
    "addr:full":"4435 Boul DE Hauteville Terrebonne QC J6X 2Y6",
    "addr:housenumber":"4435",
    "addr:postcode":"j6x 2y6",
    "addr:street":"Boul De Hauteville",
    "iso:country":"CA",
    "sg:address":"4435 Boul DE Hauteville",
    "sg:city":"Terrebonne",
    "sg:classifiers":[
        {
            "category":"Health Services",
            "subcategory":"Doctor",
            "type":"Services"
        }
    ],
    "sg:phone":"+1 450 492 3153",
    "sg:postcode":"J6X 2Y6",
    "sg:province":"QC",
    "sg:tags":[
        "clinic"
    ],
    "wof:name":"Clinique Medicale-Hauteville",
    "wof:placetype":"venue"
},
  "geometry": {"coordinates":[-73.66378,45.709656],"type":"Point"}
}