{
  "type": "Feature",
  "properties": {
    "addr:full":"7635 Martin Grove Rd Woodbridge ON L4L 2C5",
    "addr:housenumber":"7635",
    "addr:postcode":"l4l 2c5",
    "addr:street":"Martin Grove Rd",
    "iso:country":"CA",
    "sg:address":"7635 Martin Grove Rd",
    "sg:city":"Woodbridge",
    "sg:classifiers":[
        {
            "category":"Autos & Motor Vehicles",
            "subcategory":"Automobile Sales",
            "type":"Retail Goods"
        }
    ],
    "sg:phone":"+1 905 850 8111",
    "sg:postcode":"L4L 2C5",
    "sg:province":"ON",
    "sg:tags":[
        "car",
        "dealer"
    ],
    "wof:name":"Prima Mazda",
    "wof:placetype":"venue"
},
  "geometry": {"coordinates":[-79.60865800000001,43.773716],"type":"Point"}
}