{
  "type": "Feature",
  "properties": {
    "addr:full":"402 Main St Selkirk MB R1A 1V1",
    "addr:housenumber":"402",
    "addr:postcode":"r1a 1v1",
    "addr:street":"Main St",
    "iso:country":"CA",
    "sg:address":"402 Main St",
    "sg:city":"Selkirk",
    "sg:classifiers":[
        {
            "category":"Home & Garden",
            "subcategory":"Carpets & Floor Coverings",
            "type":"Retail Goods"
        }
    ],
    "sg:phone":"+1 204 482 6161",
    "sg:postcode":"R1A 1V1",
    "sg:province":"MB",
    "sg:tags":[
        "paint",
        "rug"
    ],
    "wof:name":"Daerwood Decorating",
    "wof:placetype":"venue"
},
  "geometry": {"coordinates":[-96.8727798462,50.1446418762],"type":"Point"}
}