{
  "type": "Feature",
  "properties": {
    "addr:full":"33458 Harbour Ave Mission BC V2V 2W4",
    "addr:housenumber":"33458",
    "addr:postcode":"v2v 2w4",
    "addr:street":"Harbour Ave",
    "iso:country":"CA",
    "sg:address":"33458 Harbour Ave",
    "sg:city":"Mission",
    "sg:classifiers":[
        {
            "category":"Manufacturing",
            "subcategory":"Lumber",
            "type":"Manufacturing & Wholesale Goods"
        }
    ],
    "sg:phone":"+1 604 856 9729",
    "sg:postcode":"V2V 2W4",
    "sg:province":"BC",
    "sg:tags":[
        "shingles",
        "company",
        "logging"
    ],
    "wof:name":"Meeker Log & Timber Ltd",
    "wof:placetype":"venue"
},
  "geometry": {"coordinates":[-122.29883599999999,49.130138],"type":"Point"}
}