{
  "type": "Feature",
  "properties": {
    "addr:full":"PO Box 124 Holden AB T0B 2C0",
    "addr:housenumber":"po",
    "addr:postcode":"t0b 2c0",
    "addr:street":"Box 124",
    "iso:country":"CA",
    "sg:address":"PO Box 124",
    "sg:city":"Holden",
    "sg:classifiers":[
        {
            "category":"Organizations",
            "subcategory":"Religious Organization",
            "type":"Services"
        }
    ],
    "sg:phone":"+1 403 688 3994",
    "sg:postcode":"T0B 2C0",
    "sg:province":"AB",
    "sg:tags":[
        "church"
    ],
    "wof:name":"St Gregory Catholic Church",
    "wof:placetype":"venue"
},
  "geometry": {"coordinates":[-112.235367,53.232712],"type":"Point"}
}