{
  "type": "Feature",
  "properties": {
    "addr:full":"124 Waddell Ave E Dominion City MB R0A 0H0",
    "addr:housenumber":"124",
    "addr:postcode":"r0a 0h0",
    "addr:street":"Waddell Ave E",
    "iso:country":"CA",
    "sg:address":"124 Waddell Ave E",
    "sg:city":"Dominion City",
    "sg:classifiers":[
        {
            "category":"Insurance",
            "subcategory":"Insurance Agent",
            "type":"Services"
        }
    ],
    "sg:phone":"+1 204 427 2651",
    "sg:postcode":"R0A 0H0",
    "sg:province":"MB",
    "wof:name":"Barnabe & Saurette Insurance",
    "wof:placetype":"venue"
},
  "geometry": {"coordinates":[-97.16224699999999,49.133465],"type":"Point"}
}