{
  "type": "Feature",
  "properties": {
    "addr:full":"134 49 Ave W Claresholm AB T0L 0T0",
    "addr:postcode":"t0l 0t0",
    "addr:street":"134 49 Ave W Claresholm",
    "iso:country":"CA",
    "sg:address":"134 49 Ave W",
    "sg:city":"Claresholm",
    "sg:classifiers":[
        {
            "category":"Personal",
            "subcategory":"Beauty Salon",
            "type":"Services"
        }
    ],
    "sg:phone":"+1 403 625 2959",
    "sg:postcode":"T0L 0T0",
    "sg:province":"AB",
    "wof:name":"Roostertails Hair Salon",
    "wof:placetype":"venue"
},
  "geometry": {"coordinates":[-113.58373260499999,50.0250511169],"type":"Point"}
}