{
  "type": "Feature",
  "properties": {
    "addr:full":"63 Tacoma Dr Dartmouth NS B2W 3E7",
    "addr:housenumber":"63",
    "addr:postcode":"b2w 3e7",
    "addr:street":"Tacoma Dr",
    "iso:country":"CA",
    "sg:address":"63 Tacoma Dr",
    "sg:city":"Dartmouth",
    "sg:classifiers":[
        {
            "category":"Education",
            "subcategory":"School",
            "type":"Public Place"
        }
    ],
    "sg:phone":"+1 902 434 1668",
    "sg:postcode":"B2W 3E7",
    "sg:province":"NS",
    "sg:tags":[
        "instruction",
        "driving"
    ],
    "wof:name":"Ha's Driving School",
    "wof:placetype":"venue"
},
  "geometry": {"coordinates":[-63.538155,44.680866],"type":"Point"}
}