{
  "type": "Feature",
  "properties": {
    "addr:full":"365 Windermere Ave Toronto ON M6S 3L2",
    "addr:housenumber":"365",
    "addr:postcode":"m6s 3l2",
    "addr:street":"Windermere Ave",
    "iso:country":"CA",
    "sg:address":"365 Windermere Ave",
    "sg:city":"Toronto",
    "sg:classifiers":[
        {
            "category":"Personal",
            "subcategory":"Beauty Salon",
            "type":"Services"
        }
    ],
    "sg:phone":"+1 416 766 4490",
    "sg:postcode":"M6S 3L2",
    "sg:province":"ON",
    "wof:name":"Sandro & Maria Hairstyling Ctr",
    "wof:placetype":"venue"
},
  "geometry": {"coordinates":[-79.48007200000001,43.649696],"type":"Point"}
}