{
  "type": "Feature",
  "properties": {
    "addr:full":"5 Trowbridge St W Meaford ON N4L 1V4",
    "addr:housenumber":"5",
    "addr:postcode":"n4l 1v4",
    "addr:street":"Trowbridge St W",
    "iso:country":"CA",
    "sg:address":"5 Trowbridge St W",
    "sg:city":"Meaford",
    "sg:classifiers":[
        {
            "category":"Banks & Credit Unions",
            "subcategory":"Bank",
            "type":"Services"
        }
    ],
    "sg:phone":"+1 519 538 2060",
    "sg:postcode":"N4L 1V4",
    "sg:province":"ON",
    "wof:name":"Scotiabank",
    "wof:placetype":"venue"
},
  "geometry": {"coordinates":[-80.59204099999999,44.606678],"type":"Point"}
}