{
  "type": "Feature",
  "properties": {
    "addr:full":"130 Louisa St Kitchener ON N2H 5M3",
    "addr:housenumber":"130",
    "addr:postcode":"n2h 5m3",
    "addr:street":"Louisa St",
    "iso:country":"CA",
    "sg:address":"130 Louisa St",
    "sg:city":"Kitchener",
    "sg:classifiers":[
        {
            "category":"Building & Trades",
            "subcategory":"Construction",
            "type":"Services"
        }
    ],
    "sg:phone":"+1 519 579 7718",
    "sg:postcode":"N2H 5M3",
    "sg:province":"ON",
    "sg:tags":[
        "painter"
    ],
    "wof:name":"Two Star Past Midnight",
    "wof:placetype":"venue"
},
  "geometry": {"coordinates":[-80.49854999999999,43.456963],"type":"Point"}
}