{
  "type": "Feature",
  "properties": {
    "addr:full":"6991 Buller Ave Burnaby BC V5J 4S1",
    "addr:housenumber":"6991",
    "addr:postcode":"v5j 4s1",
    "addr:street":"Buller Ave",
    "iso:country":"CA",
    "sg:address":"6991 Buller Ave",
    "sg:city":"Burnaby",
    "sg:classifiers":[
        {
            "category":"Retail",
            "subcategory":"Auto Repair",
            "type":"Services"
        }
    ],
    "sg:phone":"+1 604 439 6733",
    "sg:postcode":"V5J 4S1",
    "sg:province":"BC",
    "sg:tags":[
        "repairing",
        "automobile"
    ],
    "wof:name":"J's Auto Repair",
    "wof:placetype":"venue"
},
  "geometry": {"coordinates":[-122.977615356,49.2200126648],"type":"Point"}
}