{
  "type": "Feature",
  "properties": {
    "addr:full":"Montreal QC H1L 6P1",
    "addr:postcode":"h1l 6p1",
    "iso:country":"CA",
    "sg:city":"Montreal",
    "sg:classifiers":[
        {
            "category":"Health Services",
            "subcategory":"Nursing And Care Facility",
            "type":"Services"
        }
    ],
    "sg:phone":"+1 514 353 9533",
    "sg:postcode":"H1L 6P1",
    "sg:province":"QC",
    "sg:tags":[
        "home",
        "retirement",
        "community"
    ],
    "wof:name":"Residence 2552 Lebrun",
    "wof:placetype":"venue"
},
  "geometry": {"coordinates":[-73.52201843260001,45.5995559692],"type":"Point"}
}