{
  "type": "Feature",
  "properties": {
    "addr:full":"11 Riverside Dr Corner Brook NL A2H 2N2",
    "addr:housenumber":"11",
    "addr:postcode":"a2h 2n2",
    "addr:street":"Riverside Dr",
    "iso:country":"CA",
    "sg:address":"11 Riverside Dr",
    "sg:city":"Corner Brook",
    "sg:classifiers":[
        {
            "category":"Freight",
            "type":"Transportation"
        }
    ],
    "sg:phone":"+1 709 634 2079",
    "sg:postcode":"A2H 2N2",
    "sg:province":"NL",
    "sg:tags":[
        "trucking"
    ],
    "wof:name":"Oceanex Inc",
    "wof:placetype":"venue"
},
  "geometry": {"coordinates":[-57.943081,48.956161],"type":"Point"}
}