{
  "type": "Feature",
  "properties": {
    "addr:full":"2455 Boul Chomedey Laval QC H7T 2W5",
    "addr:housenumber":"2455",
    "addr:postcode":"h7t 2w5",
    "addr:street":"Boul Chomedey",
    "iso:country":"CA",
    "sg:address":"2455 Boul Chomedey",
    "sg:city":"Laval",
    "sg:classifiers":[
        {
            "category":"Autos & Motor Vehicles",
            "subcategory":"Automobile Sales",
            "type":"Retail Goods"
        }
    ],
    "sg:phone":"+1 514 990 9943",
    "sg:postcode":"H7T 2W5",
    "sg:province":"QC",
    "sg:tags":[
        "car",
        "dealer"
    ],
    "wof:name":"Lauzon",
    "wof:placetype":"venue"
},
  "geometry": {"coordinates":[-73.76004,45.56422],"type":"Point"}
}