{
  "type": "Feature",
  "properties": {
    "addr:full":"Portage LA Prairie MB R1N 3B2",
    "addr:postcode":"r1n 3b2",
    "iso:country":"CA",
    "sg:city":"Portage LA Prairie",
    "sg:classifiers":[
        {
            "category":"Farming",
            "subcategory":"Farm & Veterinary Services",
            "type":"Manufacturing & Wholesale Goods"
        }
    ],
    "sg:phone":"+1 204 857 4151",
    "sg:postcode":"R1N 3B2",
    "sg:province":"MB",
    "sg:tags":[
        "aerial",
        "applicator"
    ],
    "wof:name":"John Bodie Aerial Applicator",
    "wof:placetype":"venue"
},
  "geometry": {"coordinates":[-98.2905654907,49.9730834961],"type":"Point"}
}