{
  "type": "Feature",
  "properties": {
    "iso:country":"CA",
    "sg:address":"161 Queen Elizabeth Blvd W",
    "sg:city":"Kamsack",
    "sg:classifiers":[
        {
            "category":"Wholesale",
            "subcategory":"Scrap",
            "type":"Manufacturing & Wholesale Goods"
        }
    ],
    "sg:phone":"+1 306 542 3858",
    "sg:postcode":"S0A 1S0",
    "sg:province":"SK",
    "sg:tags":[
        "recycling",
        "center"
    ],
    "wof:name":"Sarcan Recycle-Kamsack",
    "wof:placetype":"venue"
},
  "geometry": {"coordinates":[-101.898651,51.56496],"type":"Point"}
}