{
  "type": "Feature",
  "properties": {
    "iso:country":"CA",
    "sg:city":"Dorval",
    "sg:classifiers":[
        {
            "category":"Building & Trades",
            "subcategory":"Landscaping Services",
            "type":"Services"
        }
    ],
    "sg:phone":"+1 514 421 3981",
    "sg:postcode":"H9P 1K3",
    "sg:province":"QC",
    "sg:tags":[
        "lawn",
        "maintenance",
        "grounds"
    ],
    "wof:name":"West End Building & Mntnc",
    "wof:placetype":"venue"
},
  "geometry": {"coordinates":[-73.78243255620001,45.4759559631],"type":"Point"}
}