{
  "type": "Feature",
  "properties": {
    "addr:full":"5528 Ann St Manotick ON K4M 1A2",
    "addr:housenumber":"5528",
    "addr:postcode":"k4m 1a2",
    "addr:street":"Ann St",
    "iso:country":"CA",
    "sg:address":"5528 Ann St",
    "sg:city":"Manotick",
    "sg:classifiers":[
        {
            "category":"Health Services",
            "subcategory":"Doctor",
            "type":"Services"
        }
    ],
    "sg:phone":"+1 613 692 1764",
    "sg:postcode":"K4M 1A2",
    "sg:province":"ON",
    "sg:tags":[
        "physician",
        "surgeon"
    ],
    "wof:name":"Ann Street Medical",
    "wof:placetype":"venue"
},
  "geometry": {"coordinates":[-75.6857299805,45.2250480652],"type":"Point"}
}