{
  "type": "Feature",
  "properties": {
    "iso:country":"CA",
    "sg:address":"180 College Ave N",
    "sg:city":"Sarnia",
    "sg:classifiers":[
        {
            "category":"Social Services",
            "type":"Services"
        }
    ],
    "sg:phone":"+1 519 344 2841",
    "sg:postcode":"N7T 7X2",
    "sg:province":"ON",
    "sg:tags":[
        "youth",
        "organization",
        "center"
    ],
    "wof:name":"Rebound A Program For Youths",
    "wof:placetype":"venue"
},
  "geometry": {"coordinates":[-82.401512146,42.9734687805],"type":"Point"}
}