{
  "type": "Feature",
  "properties": {
    "iso:country":"CA",
    "sg:city":"St Catharines",
    "sg:classifiers":[
        {
            "category":"Government",
            "subcategory":"Office",
            "type":"Public Place"
        }
    ],
    "sg:phone":"+1 905 935 0018",
    "sg:postcode":"L2N 1K8",
    "sg:province":"ON",
    "wof:name":"Ontario Memebers of Parliament",
    "wof:placetype":"venue"
},
  "geometry": {"coordinates":[-79.247246,43.183178],"type":"Point"}
}