{
  "type": "Feature",
  "properties": {
    "addr:full":"2141 Deer Run Ave Burlington ON L7M 4C7",
    "addr:housenumber":"2141",
    "addr:postcode":"l7m 4c7",
    "addr:street":"Deer Run Ave",
    "iso:country":"CA",
    "sg:address":"2141 Deer Run Ave",
    "sg:city":"Burlington",
    "sg:classifiers":[
        {
            "category":"Education",
            "subcategory":"School",
            "type":"Public Place"
        }
    ],
    "sg:phone":"+1 905 332 5253",
    "sg:postcode":"L7M 4C7",
    "sg:province":"ON",
    "wof:name":"St Timothy's Roman Catholic",
    "wof:placetype":"venue"
},
  "geometry": {"coordinates":[-79.82451629640001,43.3753814697],"type":"Point"}
}