{
  "type": "Feature",
  "properties": {
    "addr:full":"739 Montreal Rd Cornwall ON K6H 1C5",
    "addr:housenumber":"739",
    "addr:postcode":"k6h 1c5",
    "addr:street":"Montreal Rd",
    "iso:country":"CA",
    "sg:address":"739 Montreal Rd",
    "sg:city":"Cornwall",
    "sg:classifiers":[
        {
            "category":"Home & Garden",
            "subcategory":"Furniture",
            "type":"Retail Goods"
        }
    ],
    "sg:phone":"+1 613 932 2337",
    "sg:postcode":"K6H 1C5",
    "sg:province":"ON",
    "sg:tags":[
        "mattress"
    ],
    "wof:name":"Mattress World",
    "wof:placetype":"venue"
},
  "geometry": {"coordinates":[-74.70618399999999,45.018311],"type":"Point"}
}