{
  "type": "Feature",
  "properties": {
    "addr:full":"10 Howard St Toronto ON M4X 1J5",
    "addr:housenumber":"10",
    "addr:postcode":"m4x 1j5",
    "addr:street":"Howard St",
    "iso:country":"CA",
    "sg:address":"10 Howard St",
    "sg:city":"Toronto",
    "sg:classifiers":[
        {
            "category":"Travel",
            "subcategory":"Travel Agent",
            "type":"Entertainment"
        }
    ],
    "sg:phone":"+1 416 929 8607",
    "sg:postcode":"M4X 1J5",
    "sg:province":"ON",
    "sg:tags":[
        "agency",
        "bureau"
    ],
    "wof:name":"Sunbreeze Travel & Tourist",
    "wof:placetype":"venue"
},
  "geometry": {"coordinates":[-79.3753204346,43.6713523865],"type":"Point"}
}