{
  "type": "Feature",
  "properties": {
    "addr:full":"1139 Hastings St E Vancouver BC V6A 1S3",
    "addr:housenumber":"1139",
    "addr:postcode":"v6a 1s3",
    "addr:street":"Hastings St E",
    "iso:country":"CA",
    "sg:address":"1139 Hastings St E",
    "sg:city":"Vancouver",
    "sg:classifiers":[
        {
            "category":"Professional",
            "subcategory":"Computer Services",
            "type":"Services"
        }
    ],
    "sg:phone":"+1 604 253 2070",
    "sg:postcode":"V6A 1S3",
    "sg:province":"BC",
    "sg:tags":[
        "repair"
    ],
    "wof:name":"Kinetic Electronics Inc",
    "wof:placetype":"venue"
},
  "geometry": {"coordinates":[-123.080399,49.281124],"type":"Point"}
}