{
  "type": "Feature",
  "properties": {
    "addr:full":"Vancouver BC V5Z 3J8",
    "addr:postcode":"v5z 3j8",
    "iso:country":"CA",
    "sg:city":"Vancouver",
    "sg:classifiers":[
        {
            "category":"Shopping",
            "subcategory":"Used Merchandise",
            "type":"Retail Goods"
        }
    ],
    "sg:phone":"+1 604 266 4857",
    "sg:postcode":"V5Z 3J8",
    "sg:province":"BC",
    "sg:tags":[
        "book",
        "rare",
        "dealer"
    ],
    "wof:name":"Narnia Books",
    "wof:placetype":"venue"
},
  "geometry": {"coordinates":[-123.119705,49.259109],"type":"Point"}
}