{
  "type": "Feature",
  "properties": {
    "addr:full":"589 Rue Basque Tracadie-Sheila NB E1X 1B1",
    "addr:housenumber":"589",
    "addr:postcode":"e1x 1b1",
    "addr:street":"Rue Basque",
    "iso:country":"CA",
    "sg:address":"589 Rue Basque",
    "sg:city":"Tracadie-Sheila",
    "sg:classifiers":[
        {
            "category":"Personal",
            "subcategory":"Beauty Salon",
            "type":"Services"
        }
    ],
    "sg:phone":"+1 506 395 9300",
    "sg:postcode":"E1X 1B1",
    "sg:province":"NB",
    "wof:name":"Salon Chez Danielle",
    "wof:placetype":"venue"
},
  "geometry": {"coordinates":[-64.919106,47.509575],"type":"Point"}
}