{
  "type": "Feature",
  "properties": {
    "addr:full":"746 Chester Rd Delta BC V3M 6J1",
    "addr:housenumber":"746",
    "addr:postcode":"v3m 6j1",
    "addr:street":"Chester Rd",
    "iso:country":"CA",
    "sg:address":"746 Chester Rd",
    "sg:city":"Delta",
    "sg:classifiers":[
        {
            "category":"Wholesale",
            "subcategory":"Machinery & Supplies",
            "type":"Manufacturing & Wholesale Goods"
        }
    ],
    "sg:phone":"+1 604 523 2356",
    "sg:postcode":"V3M 6J1",
    "sg:province":"BC",
    "sg:tags":[
        "bearing"
    ],
    "wof:name":"Kaman Industrial Tech Ltd",
    "wof:placetype":"venue"
},
  "geometry": {"coordinates":[-122.948493958,49.1733512878],"type":"Point"}
}