{
  "type": "Feature",
  "properties": {
    "iso:country":"CA",
    "sg:address":"299 Connell St",
    "sg:city":"Woodstock",
    "sg:classifiers":[
        {
            "category":"Real Estate",
            "subcategory":"Real Estate Agent",
            "type":"Services"
        }
    ],
    "sg:phone":"+1 506 324 8888",
    "sg:postcode":"E7M 1L3",
    "sg:province":"NB",
    "wof:name":"Remax Hartford Realty Inc",
    "wof:placetype":"venue"
},
  "geometry": {"coordinates":[-67.593018,46.160839],"type":"Point"}
}