{
  "type": "Feature",
  "properties": {
    "addr:full":"109 King St W Bowmanville ON L1C 3Z9",
    "addr:housenumber":"109",
    "addr:postcode":"l1c 3z9",
    "addr:street":"King St W",
    "iso:country":"CA",
    "sg:address":"109 King St W",
    "sg:city":"Bowmanville",
    "sg:classifiers":[
        {
            "category":"Personal",
            "type":"Services"
        }
    ],
    "sg:phone":"+1 905 623 4887",
    "sg:postcode":"L1C 3Z9",
    "sg:province":"ON",
    "sg:tags":[
        "program",
        "physical",
        "exercise",
        "fitness"
    ],
    "wof:name":"Bottom Line",
    "wof:placetype":"venue"
},
  "geometry": {"coordinates":[-78.692848,43.912804],"type":"Point"}
}