{
  "type": "Feature",
  "properties": {
    "addr:full":"130 Barton St E # 101 Hamilton ON L8L 2W4",
    "addr:housenumber":"130;101",
    "addr:postcode":"l8l 2w4",
    "addr:street":"Barton St E #",
    "iso:country":"CA",
    "sg:address":"130 Barton St E # 101",
    "sg:city":"Hamilton",
    "sg:classifiers":[
        {
            "category":"Organizations",
            "subcategory":"Religious Organization",
            "type":"Services"
        }
    ],
    "sg:phone":"+1 905 529 1213",
    "sg:postcode":"L8L 2W4",
    "sg:province":"ON",
    "sg:tags":[
        "church"
    ],
    "wof:name":"St Stephen's Hungarian Rc Ch",
    "wof:placetype":"venue"
},
  "geometry": {"coordinates":[-79.860603,43.262703],"type":"Point"}
}