{
  "type": "Feature",
  "properties": {
    "iso:country":"CA",
    "sg:address":"730 Nanoose Ave",
    "sg:city":"Parksville",
    "sg:classifiers":[
        {
            "category":"Building & Trades",
            "subcategory":"Plumbing",
            "type":"Services"
        }
    ],
    "sg:phone":"+1 250 248 4260",
    "sg:postcode":"V9P 1E9",
    "sg:province":"BC",
    "sg:tags":[
        "sheet",
        "work",
        "metal",
        "contractor"
    ],
    "wof:name":"Clayton Sheet Metal",
    "wof:placetype":"venue"
},
  "geometry": {"coordinates":[-124.339767456,49.3205223083],"type":"Point"}
}