{
  "type": "Feature",
  "properties": {
    "addr:full":"695 Yonge St Toronto ON M4Y 2B2",
    "addr:housenumber":"695",
    "addr:postcode":"m4y 2b2",
    "addr:street":"Yonge St",
    "iso:country":"CA",
    "sg:address":"695 Yonge St",
    "sg:city":"Toronto",
    "sg:classifiers":[
        {
            "category":"Restaurant",
            "type":"Food & Drink"
        }
    ],
    "sg:phone":"+1 416 966 2424",
    "sg:postcode":"M4Y 2B2",
    "sg:province":"ON",
    "wof:name":"Ginger Restaurant",
    "wof:placetype":"venue"
},
  "geometry": {"coordinates":[-79.38610799999999,43.669144],"type":"Point"}
}