{
  "type": "Feature",
  "properties": {
    "addr:full":"4695 Saint Lawrence Ave Niagara Falls ON L2E 3X6",
    "addr:housenumber":"4695",
    "addr:postcode":"l2e 3x6",
    "addr:street":"Saint Lawrence Ave",
    "iso:country":"CA",
    "sg:address":"4695 Saint Lawrence Ave",
    "sg:city":"Niagara Falls",
    "sg:classifiers":[
        {
            "category":"Government",
            "subcategory":"Office",
            "type":"Public Place"
        }
    ],
    "sg:phone":"+1 905 357 4279",
    "sg:postcode":"L2E 3X6",
    "sg:province":"ON",
    "sg:tags":[
        "member",
        "legislative",
        "assembly"
    ],
    "wof:name":"Pillitteri, Gary",
    "wof:placetype":"venue"
},
  "geometry": {"coordinates":[-79.070274353,43.1057815552],"type":"Point"}
}