{
  "type": "Feature",
  "properties": {
    "addr:full":"Calgary AB T2G 2B9",
    "addr:postcode":"t2g 2b9",
    "iso:country":"CA",
    "sg:city":"Calgary",
    "sg:classifiers":[
        {
            "category":"Health Services",
            "subcategory":"Doctor",
            "type":"Services"
        }
    ],
    "sg:phone":"+1 403 290 0303",
    "sg:postcode":"T2G 2B9",
    "sg:province":"AB",
    "sg:tags":[
        "clinic",
        "dentist"
    ],
    "wof:name":"Centre Street Dental Clinic",
    "wof:placetype":"venue"
},
  "geometry": {"coordinates":[-114.062927,51.050102],"type":"Point"}
}