{
  "type": "Feature",
  "properties": {
    "iso:country":"CA",
    "sg:address":"927 Matheson Blvd E",
    "sg:city":"Mississauga",
    "sg:classifiers":[
        {
            "category":"Wholesale",
            "subcategory":"Machinery & Supplies",
            "type":"Manufacturing & Wholesale Goods"
        }
    ],
    "sg:phone":"+1 905 602 4400",
    "sg:postcode":"L4W 2R7",
    "sg:province":"ON",
    "sg:tags":[
        "belting"
    ],
    "wof:name":"Jason Industrial Canada Ltd",
    "wof:placetype":"venue"
},
  "geometry": {"coordinates":[-79.64366912840001,43.6321105957],"type":"Point"}
}