{
  "type": "Feature",
  "properties": {
    "addr:full":"9170 Highway 93 Midland ON L4R 4K4",
    "addr:housenumber":"9170",
    "addr:postcode":"l4r 4k4",
    "addr:street":"Highway 93",
    "iso:country":"CA",
    "sg:address":"9170 Highway 93",
    "sg:city":"Midland",
    "sg:classifiers":[
        {
            "category":"Manufacturing",
            "subcategory":"Printing",
            "type":"Manufacturing & Wholesale Goods"
        }
    ],
    "sg:phone":"+1 705 527 5500",
    "sg:postcode":"L4R 4K4",
    "sg:province":"ON",
    "sg:tags":[
        "newspaper"
    ],
    "wof:name":"Mirror",
    "wof:placetype":"venue"
},
  "geometry": {"coordinates":[-79.88851165769999,44.7499046326],"type":"Point"}
}