{
  "type": "Feature",
  "properties": {
    "iso:country":"CA",
    "sg:address":"6651 Boul Saint-Laurent",
    "sg:city":"Montreal",
    "sg:classifiers":[
        {
            "category":"Social Services",
            "type":"Services"
        }
    ],
    "sg:phone":"+1 514 272 7507",
    "sg:postcode":"H2S 3C5",
    "sg:province":"QC",
    "sg:tags":[
        "organization",
        "association",
        "welfare"
    ],
    "wof:name":"Maisonnette Des Parents Inc",
    "wof:placetype":"venue"
},
  "geometry": {"coordinates":[-73.610909,45.531494],"type":"Point"}
}