{
  "type": "Feature",
  "properties": {
    "addr:full":"6651 Boul Saint-Laurent Montreal QC H2S 3C5",
    "addr:housenumber":"6651",
    "addr:postcode":"h2s 3c5",
    "addr:street":"Boul Saint-Laurent",
    "iso:country":"CA",
    "sg:address":"6651 Boul Saint-Laurent",
    "sg:city":"Montreal",
    "sg:classifiers":[
        {
            "category":"Social Services",
            "type":"Services"
        }
    ],
    "sg:phone":"+1 514 272 7507",
    "sg:postcode":"H2S 3C5",
    "sg:province":"QC",
    "sg:tags":[
        "organization",
        "association",
        "welfare"
    ],
    "wof:name":"Maisonnette Des Parents Inc",
    "wof:placetype":"venue"
},
  "geometry": {"coordinates":[-73.61090900000001,45.531494],"type":"Point"}
}