{
  "type": "Feature",
  "properties": {
    "addr:full":"7135 Rue Marconi Montreal QC H2S 3K4",
    "addr:housenumber":"7135",
    "addr:postcode":"h2s 3k4",
    "addr:street":"Rue Marconi",
    "iso:country":"CA",
    "sg:address":"7135 Rue Marconi",
    "sg:city":"Montreal",
    "sg:classifiers":[
        {
            "category":"Retail",
            "subcategory":"Auto Repair",
            "type":"Services"
        }
    ],
    "sg:phone":"+1 514 274 2111",
    "sg:postcode":"H2S 3K4",
    "sg:province":"QC",
    "sg:tags":[
        "repairing",
        "automobile"
    ],
    "wof:name":"P K Autos",
    "wof:placetype":"venue"
},
  "geometry": {"coordinates":[-73.619766,45.531544],"type":"Point"}
}