{
  "type": "Feature",
  "properties": {
    "addr:full":"455 Av Duclos Saint-Hyacinthe QC J2S 8V1",
    "addr:postcode":"j2s 8v1",
    "addr:street":"455 Av Duclos",
    "iso:country":"CA",
    "sg:address":"455 Av Duclos",
    "sg:city":"Saint-Hyacinthe",
    "sg:classifiers":[
        {
            "category":"Recreation",
            "type":"Entertainment"
        }
    ],
    "sg:phone":"+1 450 261 0193",
    "sg:postcode":"J2S 8V1",
    "sg:province":"QC",
    "sg:tags":[
        "bingo",
        "game"
    ],
    "wof:name":"Maison Du Bingo Maskoutaine",
    "wof:placetype":"venue"
},
  "geometry": {"coordinates":[-72.9437484741,45.6248588562],"type":"Point"}
}