{
  "type": "Feature",
  "properties": {
    "addr:full":"4111 16 St SE Calgary AB T2G 3R9",
    "addr:housenumber":"4111",
    "addr:postcode":"t2g 3r9",
    "addr:street":"16 St Se",
    "iso:country":"CA",
    "sg:address":"4111 16 St SE",
    "sg:city":"Calgary",
    "sg:classifiers":[
        {
            "category":"Autos & Motor Vehicles",
            "subcategory":"Automobile Sales",
            "type":"Retail Goods"
        }
    ],
    "sg:phone":"+1 403 232 8338",
    "sg:postcode":"T2G 3R9",
    "sg:province":"AB",
    "sg:tags":[
        "truck"
    ],
    "wof:name":"Foothills Equipment Sales",
    "wof:placetype":"venue"
},
  "geometry": {"coordinates":[-114.02227020300001,51.0182762146],"type":"Point"}
}