{
  "type": "Feature",
  "properties": {
    "iso:country":"CA",
    "sg:address":"393 Marion St",
    "sg:city":"Winnipeg",
    "sg:classifiers":[
        {
            "category":"Restaurant",
            "type":"Food & Drink"
        }
    ],
    "sg:phone":"+1 204 231 4520",
    "sg:postcode":"R2H 0V4",
    "sg:province":"MB",
    "wof:name":"Polonez Restaurant",
    "wof:placetype":"venue"
},
  "geometry": {"coordinates":[-97.1090164185,49.8821182251],"type":"Point"}
}