{
  "type": "Feature",
  "properties": {
    "addr:full":"York ON M6M 2C1",
    "addr:postcode":"m6m 2c1",
    "iso:country":"CA",
    "sg:city":"York",
    "sg:classifiers":[
        {
            "category":"Banks & Credit Unions",
            "subcategory":"Financial Services",
            "type":"Services"
        }
    ],
    "sg:phone":"+1 416 368 7561",
    "sg:postcode":"M6M 2C1",
    "sg:province":"ON",
    "sg:tags":[
        "company",
        "holding"
    ],
    "wof:name":"Cotrelle, J E",
    "wof:placetype":"venue"
},
  "geometry": {"coordinates":[-79.4953994751,43.6900215149],"type":"Point"}
}