{
  "type": "Feature",
  "properties": {
    "addr:full":"250 Rue Masson Sainte-Thecle QC G0X 3G0",
    "addr:housenumber":"250",
    "addr:postcode":"g0x 3g0",
    "addr:street":"Rue Masson Sainte-Thecle",
    "iso:country":"CA",
    "sg:address":"250 Rue Masson",
    "sg:city":"Sainte-Thecle",
    "sg:classifiers":[
        {
            "category":"Banks & Credit Unions",
            "subcategory":"Bank",
            "type":"Services"
        }
    ],
    "sg:phone":"+1 418 289 2972",
    "sg:postcode":"G0X 3G0",
    "sg:province":"QC",
    "wof:name":"Caisses Desjardins",
    "wof:placetype":"venue"
},
  "geometry": {"coordinates":[-72.507271,46.818153],"type":"Point"}
}