{
  "type": "Feature",
  "properties": {
    "addr:full":"28 Chapel St Parrsboro NS B0M 1S0",
    "addr:housenumber":"28",
    "addr:postcode":"b0m 1s0",
    "addr:street":"Chapel St",
    "iso:country":"CA",
    "sg:address":"28 Chapel St",
    "sg:city":"Parrsboro",
    "sg:classifiers":[
        {
            "category":"Organizations",
            "subcategory":"Religious Organization",
            "type":"Services"
        }
    ],
    "sg:phone":"+1 902 254 2318",
    "sg:postcode":"B0M 1S0",
    "sg:province":"NS",
    "sg:tags":[
        "church"
    ],
    "wof:name":"United Church Manse",
    "wof:placetype":"venue"
},
  "geometry": {"coordinates":[-64.3259429932,45.4061546326],"type":"Point"}
}