{
  "type": "Feature",
  "properties": {
    "addr:full":"1985 Bollinger Rd Nanaimo BC V9S 5W9",
    "addr:housenumber":"1985",
    "addr:postcode":"v9s 5w9",
    "addr:street":"Bollinger Rd",
    "iso:country":"CA",
    "sg:address":"1985 Bollinger Rd",
    "sg:city":"Nanaimo",
    "sg:classifiers":[
        {
            "category":"Utilities",
            "type":"Services"
        }
    ],
    "sg:phone":"+1 250 753 4772",
    "sg:postcode":"V9S 5W9",
    "sg:province":"BC",
    "sg:tags":[
        "locating"
    ],
    "wof:name":"One Call Locators Canada Ltd",
    "wof:placetype":"venue"
},
  "geometry": {"coordinates":[-123.98730468799999,49.1865234375],"type":"Point"}
}