{
  "type": "Feature",
  "properties": {
    "addr:full":"16 West Concession 7 Jarvis ON N0A 1J0",
    "addr:housenumber":"16",
    "addr:postcode":"n0a 1j0",
    "addr:street":"West Concession 7 Jarvis",
    "iso:country":"CA",
    "sg:address":"16 West Concession 7",
    "sg:city":"Jarvis",
    "sg:classifiers":[
        {
            "category":"Sports & Exercise",
            "subcategory":"Golf",
            "type":"Entertainment"
        }
    ],
    "sg:phone":"+1 519 587 3030",
    "sg:postcode":"N0A 1J0",
    "sg:province":"ON",
    "sg:tags":[
        "range",
        "practice"
    ],
    "wof:name":"Town Line Driving Range",
    "wof:placetype":"venue"
},
  "geometry": {"coordinates":[-80.1351470947,42.8814811707],"type":"Point"}
}