{
  "type": "Feature",
  "properties": {
    "addr:full":"544 King St W Toronto ON M5V 1M3",
    "addr:housenumber":"544",
    "addr:postcode":"m5v 1m3",
    "addr:street":"King St W",
    "iso:country":"CA",
    "sg:address":"544 King St W",
    "sg:city":"Toronto",
    "sg:classifiers":[
        {
            "category":"Autos & Motor Vehicles",
            "subcategory":"Boat Sales",
            "type":"Retail Goods"
        }
    ],
    "sg:phone":"+1 416 504 2891",
    "sg:postcode":"M5V 1M3",
    "sg:province":"ON",
    "sg:tags":[
        "equipment",
        "marine",
        "supply"
    ],
    "wof:name":"Genco Marine Ltd",
    "wof:placetype":"venue"
},
  "geometry": {"coordinates":[-79.3980712891,43.6450080872],"type":"Point"}
}