{
  "type": "Feature",
  "properties": {
    "addr:full":"Winnipeg MB R2M 1G2",
    "addr:postcode":"r2m 1g2",
    "iso:country":"CA",
    "sg:city":"Winnipeg",
    "sg:classifiers":[
        {
            "category":"Real Estate",
            "subcategory":"Real Estate Operator",
            "type":"Services"
        }
    ],
    "sg:phone":"+1 204 940 3476",
    "sg:postcode":"R2M 1G2",
    "sg:province":"MB",
    "sg:tags":[
        "apartment"
    ],
    "wof:name":"River Gardens",
    "wof:placetype":"venue"
},
  "geometry": {"coordinates":[-97.09828948969999,49.8501243591],"type":"Point"}
}