{
  "type": "Feature",
  "properties": {
    "addr:full":"6340 Dewdney Ave Regina SK S4T 1E3",
    "addr:housenumber":"6340",
    "addr:postcode":"s4t 1e3",
    "addr:street":"Dewdney Ave",
    "iso:country":"CA",
    "sg:address":"6340 Dewdney Ave",
    "sg:city":"Regina",
    "sg:classifiers":[
        {
            "category":"Restaurant",
            "type":"Food & Drink"
        }
    ],
    "sg:phone":"+1 306 543 6999",
    "sg:postcode":"S4T 1E3",
    "sg:province":"SK",
    "wof:name":"Mc Carthy Garden Chinese Food",
    "wof:placetype":"venue"
},
  "geometry": {"coordinates":[-104.671768,50.455368],"type":"Point"}
}