{
  "type": "Feature",
  "properties": {
    "addr:full":"1274 Commissioners Rd W London ON N6K 1E1",
    "addr:housenumber":"1274",
    "addr:postcode":"n6k 1e1",
    "addr:street":"Commissioners Rd W",
    "iso:country":"CA",
    "sg:address":"1274 Commissioners Rd W",
    "sg:city":"London",
    "sg:classifiers":[
        {
            "category":"Shopping",
            "subcategory":"Florist",
            "type":"Retail Goods"
        }
    ],
    "sg:phone":"+1 519 471 3900",
    "sg:postcode":"N6K 1E1",
    "sg:province":"ON",
    "wof:name":"Murree Flowers",
    "wof:placetype":"venue"
},
  "geometry": {"coordinates":[-81.33321380620001,42.9596862793],"type":"Point"}
}