{
  "type": "Feature",
  "properties": {
    "addr:full":"289 Rue Laurier Disraeli QC G0N 1E0",
    "addr:housenumber":"289",
    "addr:postcode":"g0n 1e0",
    "addr:street":"Rue Laurier",
    "iso:country":"CA",
    "sg:address":"289 Rue Laurier",
    "sg:city":"Disraeli",
    "sg:classifiers":[
        {
            "category":"Food & Beverages",
            "subcategory":"Groceries & Convenience Stores",
            "type":"Retail Goods"
        }
    ],
    "sg:phone":"+1 418 449 2424",
    "sg:postcode":"G0N 1E0",
    "sg:province":"QC",
    "sg:tags":[
        "butchering"
    ],
    "wof:name":"Inter Marche Enr",
    "wof:placetype":"venue"
},
  "geometry": {"coordinates":[-71.3592224121,45.9040641785],"type":"Point"}
}