{
  "type": "Feature",
  "properties": {
    "iso:country":"CA",
    "sg:city":"Okotoks",
    "sg:classifiers":[
        {
            "category":"Food & Beverages",
            "subcategory":"Specialty",
            "type":"Retail Goods"
        }
    ],
    "sg:phone":"+1 403 938 1740",
    "sg:postcode":"T1S 1Z6",
    "sg:province":"AB",
    "sg:tags":[
        "health",
        "diet"
    ],
    "wof:name":"Nutter's Bulk & Natural Foods",
    "wof:placetype":"venue"
},
  "geometry": {"coordinates":[-113.983032227,50.7185401917],"type":"Point"}
}