{
  "type": "Feature",
  "properties": {
    "addr:full":"105 Simmonds Dr Dartmouth NS B3B 1N7",
    "addr:housenumber":"105",
    "addr:postcode":"b3b 1n7",
    "addr:street":"Simmonds Dr",
    "iso:country":"CA",
    "sg:address":"105 Simmonds Dr",
    "sg:city":"Dartmouth",
    "sg:classifiers":[
        {
            "category":"Manufacturing",
            "subcategory":"Motor Vehicles & Parts",
            "type":"Manufacturing & Wholesale Goods"
        }
    ],
    "sg:phone":"+1 902 468 5800",
    "sg:postcode":"B3B 1N7",
    "sg:province":"NS",
    "sg:tags":[
        "automobile",
        "supply"
    ],
    "wof:name":"Diesel & Auto Electric Ltd",
    "wof:placetype":"venue"
},
  "geometry": {"coordinates":[-63.601643,44.716259],"type":"Point"}
}