{
  "type": "Feature",
  "properties": {
    "addr:full":"1550 Bedford Hwy Bedford NS B4A 1E6",
    "addr:housenumber":"1550",
    "addr:postcode":"b4a 1e6",
    "addr:street":"Bedford Hwy",
    "iso:country":"CA",
    "sg:address":"1550 Bedford Hwy",
    "sg:city":"Bedford",
    "sg:classifiers":[
        {
            "category":"Health Services",
            "subcategory":"Doctor",
            "type":"Services"
        }
    ],
    "sg:phone":"+1 902 835 4598",
    "sg:postcode":"B4A 1E6",
    "sg:province":"NS",
    "sg:tags":[
        "physician",
        "surgeon"
    ],
    "wof:name":"Birnie, William A MD",
    "wof:placetype":"venue"
},
  "geometry": {"coordinates":[-63.657475,44.731945],"type":"Point"}
}