{
  "type": "Feature",
  "properties": {
    "addr:full":"8 White's Rd Carbonear NL A1Y 1A4",
    "addr:housenumber":"8",
    "addr:postcode":"a1y 1a4",
    "addr:street":"White'S Rd",
    "iso:country":"CA",
    "sg:address":"8 White's Rd",
    "sg:city":"Carbonear",
    "sg:classifiers":[
        {
            "category":"Professional",
            "type":"Services"
        }
    ],
    "sg:phone":"+1 709 596 2270",
    "sg:postcode":"A1Y 1A4",
    "sg:province":"NL",
    "wof:name":"Kiex Consulting Ltd",
    "wof:placetype":"venue"
},
  "geometry": {"coordinates":[-53.2295,47.736382],"type":"Point"}
}