{
  "type": "Feature",
  "properties": {
    "addr:full":"122 Charing Cross St Brantford ON N3R 2J1",
    "addr:housenumber":"122",
    "addr:postcode":"n3r 2j1",
    "addr:street":"Charing Cross St",
    "iso:country":"CA",
    "sg:address":"122 Charing Cross St",
    "sg:city":"Brantford",
    "sg:classifiers":[
        {
            "category":"Health Services",
            "subcategory":"Podiatrist",
            "type":"Services"
        }
    ],
    "sg:phone":"+1 519 751 2900",
    "sg:postcode":"N3R 2J1",
    "sg:province":"ON",
    "wof:name":"Bradley, Marilyn DPM",
    "wof:placetype":"venue"
},
  "geometry": {"coordinates":[-80.264289856,43.1589851379],"type":"Point"}
}