{
  "type": "Feature",
  "properties": {
    "iso:country":"CA",
    "sg:address":"8228 93A Ave NW",
    "sg:city":"Edmonton",
    "sg:classifiers":[
        {
            "category":"Real Estate",
            "subcategory":"Real Estate Agent",
            "type":"Services"
        }
    ],
    "sg:phone":"+1 780 468 4060",
    "sg:postcode":"T6C 1V6",
    "sg:province":"AB",
    "wof:name":"Homelife Guaranteed Realty",
    "wof:placetype":"venue"
},
  "geometry": {"coordinates":[-113.452888489,53.5298194885],"type":"Point"}
}