{
  "type": "Feature",
  "properties": {
    "addr:full":"740 Scott St Fort Frances ON P9A 1H8",
    "addr:housenumber":"740",
    "addr:postcode":"p9a 1h8",
    "addr:street":"Scott St",
    "iso:country":"CA",
    "sg:address":"740 Scott St",
    "sg:city":"Fort Frances",
    "sg:classifiers":[
        {
            "category":"Government",
            "subcategory":"Office",
            "type":"Public Place"
        }
    ],
    "sg:phone":"+1 807 274 4561",
    "sg:postcode":"P9A 1H8",
    "sg:province":"ON",
    "sg:tags":[
        "village"
    ],
    "wof:name":"Memorial Sports Ctr",
    "wof:placetype":"venue"
},
  "geometry": {"coordinates":[-93.3824310303,48.6101570129],"type":"Point"}
}