{
  "type": "Feature",
  "properties": {
    "addr:full":"1599 Woodstock Rd Fredericton NB E3C 1P2",
    "addr:housenumber":"1599",
    "addr:postcode":"e3c 1p2",
    "addr:street":"Woodstock Rd",
    "iso:country":"CA",
    "sg:address":"1599 Woodstock Rd",
    "sg:city":"Fredericton",
    "sg:classifiers":[
        {
            "category":"Shopping",
            "type":"Retail Goods"
        }
    ],
    "sg:phone":"+1 506 450 4233",
    "sg:postcode":"E3C 1P2",
    "sg:province":"NB",
    "sg:tags":[
        "picture",
        "art",
        "gallery",
        "dealer"
    ],
    "wof:name":"Birch Cres Gallery By Dale",
    "wof:placetype":"venue"
},
  "geometry": {"coordinates":[-66.7193603516,45.967414856],"type":"Point"}
}