{
  "type": "Feature",
  "properties": {
    "iso:country":"CA",
    "sg:city":"Williams Lake",
    "sg:classifiers":[
        {
            "category":"Health Services",
            "subcategory":"Doctor",
            "type":"Services"
        }
    ],
    "sg:phone":"+1 250 398 8242",
    "sg:postcode":"V2G 1J8",
    "sg:province":"BC",
    "sg:tags":[
        "clinic"
    ],
    "wof:name":"Yorston Medical Clinic",
    "wof:placetype":"venue"
},
  "geometry": {"coordinates":[-122.141052246,52.126209259],"type":"Point"}
}