{
  "type": "Feature",
  "properties": {
    "addr:full":"105 Rue Principale St-Sauveur-Des-Monts QC J0R 1R6",
    "addr:housenumber":"105",
    "addr:postcode":"j0r 1r6",
    "addr:street":"Rue Principale",
    "iso:country":"CA",
    "sg:address":"105 Rue Principale",
    "sg:city":"St-Sauveur-Des-Monts",
    "sg:classifiers":[
        {
            "category":"Health Services",
            "subcategory":"Health Practitioner",
            "type":"Services"
        }
    ],
    "sg:phone":"+1 450 227 0227",
    "sg:postcode":"J0R 1R6",
    "sg:province":"QC",
    "sg:tags":[
        "psychologist"
    ],
    "wof:name":"Approche Globale",
    "wof:placetype":"venue"
},
  "geometry": {"coordinates":[-74.1500549316,45.8982696533],"type":"Point"}
}