{
  "type": "Feature",
  "properties": {
    "addr:full":"Cowansville QC J2K 2X2",
    "addr:postcode":"j2k 2x2",
    "iso:country":"CA",
    "sg:city":"Cowansville",
    "sg:classifiers":[
        {
            "category":"Wholesale",
            "subcategory":"Office Equipment",
            "type":"Manufacturing & Wholesale Goods"
        }
    ],
    "sg:phone":"+1 450 263 7501",
    "sg:postcode":"J2K 2X2",
    "sg:province":"QC",
    "sg:tags":[
        "court",
        "reporting",
        "system",
        "accounting",
        "bookkeeping",
        "secretarial"
    ],
    "wof:name":"Gestion Informatique Gth Inc",
    "wof:placetype":"venue"
},
  "geometry": {"coordinates":[-72.747925,45.206882],"type":"Point"}
}