{
  "type": "Feature",
  "properties": {
    "iso:country":"CA",
    "sg:address":"1150 Birchview Dr",
    "sg:city":"Mississauga",
    "sg:classifiers":[
        {
            "category":"Personal",
            "subcategory":"Beauty Salon",
            "type":"Services"
        }
    ],
    "sg:phone":"+1 905 278 8770",
    "sg:postcode":"L5H 3C8",
    "sg:province":"ON",
    "sg:tags":[
        "day"
    ],
    "wof:name":"Ivy Garden Spa",
    "wof:placetype":"venue"
},
  "geometry": {"coordinates":[-79.61437988279999,43.5320625305],"type":"Point"}
}