{
  "type": "Feature",
  "properties": {
    "addr:full":"114 3 Ave SW Calgary AB T2P 0E7",
    "addr:housenumber":"114",
    "addr:postcode":"t2p 0e7",
    "addr:street":"3 Ave Sw",
    "iso:country":"CA",
    "sg:address":"114 3 Ave SW",
    "sg:city":"Calgary",
    "sg:classifiers":[
        {
            "category":"Organizations",
            "subcategory":"Professional Association",
            "type":"Services"
        }
    ],
    "sg:phone":"+1 403 237 7988",
    "sg:postcode":"T2P 0E7",
    "sg:province":"AB",
    "wof:name":"Calgary Tsung Tsin Assn",
    "wof:placetype":"venue"
},
  "geometry": {"coordinates":[-114.063278,51.050354],"type":"Point"}
}