{
  "type": "Feature",
  "properties": {
    "addr:full":"Cornwall ON K6H 6B9",
    "addr:postcode":"k6h 6b9",
    "iso:country":"CA",
    "sg:city":"Cornwall",
    "sg:classifiers":[
        {
            "category":"Wholesale",
            "subcategory":"Durable Goods & Equipment",
            "type":"Manufacturing & Wholesale Goods"
        }
    ],
    "sg:phone":"+1 613 937 3473",
    "sg:postcode":"K6H 6B9",
    "sg:province":"ON",
    "sg:tags":[
        "fire",
        "extinguisher"
    ],
    "wof:name":"Pyropro Fire Protection System",
    "wof:placetype":"venue"
},
  "geometry": {"coordinates":[-74.71672058110001,45.0342445374],"type":"Point"}
}