{
  "type": "Feature",
  "properties": {
    "addr:full":"276 Elizabeth St Neepawa MB R0J 1H0",
    "addr:housenumber":"276",
    "addr:postcode":"r0j 1h0",
    "addr:street":"Elizabeth St",
    "iso:country":"CA",
    "sg:address":"276 Elizabeth St",
    "sg:city":"Neepawa",
    "sg:classifiers":[
        {
            "category":"Organizations",
            "subcategory":"Religious Organization",
            "type":"Services"
        }
    ],
    "sg:phone":"+1 204 476 3857",
    "sg:postcode":"R0J 1H0",
    "sg:province":"MB",
    "sg:tags":[
        "church"
    ],
    "wof:name":"St John's Ukrainian Catholic",
    "wof:placetype":"venue"
},
  "geometry": {"coordinates":[-99.4657897949,50.2369689941],"type":"Point"}
}