{
  "type": "Feature",
  "properties": {
    "addr:full":"500 Rue Victorin Saint-Roch-DE-Richelieu QC J0L 2M0",
    "addr:housenumber":"500",
    "addr:postcode":"j0l 2m0",
    "addr:street":"Rue Victorin",
    "iso:country":"CA",
    "sg:address":"500 Rue Victorin",
    "sg:city":"Saint-Roch-DE-Richelieu",
    "sg:classifiers":[
        {
            "category":"Building & Trades",
            "subcategory":"Construction",
            "type":"Services"
        }
    ],
    "sg:phone":"+1 450 785 2260",
    "sg:postcode":"J0L 2M0",
    "sg:province":"QC",
    "sg:tags":[
        "house",
        "mover",
        "general",
        "contractor"
    ],
    "wof:name":"Pichard Excavation Inc",
    "wof:placetype":"venue"
},
  "geometry": {"coordinates":[-73.15561676030001,45.901676178],"type":"Point"}
}