{
  "type": "Feature",
  "properties": {
    "addr:full":"10 Rue Browning Dollard-Des-Ormeaux QC H9G 2K4",
    "addr:housenumber":"10",
    "addr:postcode":"h9g 2k4",
    "addr:street":"Rue Browning",
    "iso:country":"CA",
    "sg:address":"10 Rue Browning",
    "sg:city":"Dollard-Des-Ormeaux",
    "sg:classifiers":[
        {
            "category":"Professional",
            "type":"Services"
        }
    ],
    "sg:phone":"+1 514 626 4234",
    "sg:postcode":"H9G 2K4",
    "sg:province":"QC",
    "sg:tags":[
        "establishment",
        "advertising"
    ],
    "wof:name":"Daniel Advertising & Promotion",
    "wof:placetype":"venue"
},
  "geometry": {"coordinates":[-73.8339767456,45.480304718],"type":"Point"}
}