{
  "type": "Feature",
  "properties": {
    "iso:country":"CA",
    "sg:city":"Elko",
    "sg:classifiers":[
        {
            "category":"Autos & Motor Vehicles",
            "subcategory":"Fuel & Gas Station",
            "type":"Retail Goods"
        }
    ],
    "sg:phone":"+1 250 529 7445",
    "sg:postcode":"V0B 1J0",
    "sg:province":"BC",
    "sg:tags":[
        "oil"
    ],
    "wof:name":"Elko Enterprises Ltd",
    "wof:placetype":"venue"
},
  "geometry": {"coordinates":[-115.11491393999999,49.3018188477],"type":"Point"}
}