{
  "type": "Feature",
  "properties": {
    "addr:full":"700 Rue Bernier LA Prairie QC J5R 5W6",
    "addr:housenumber":"700",
    "addr:postcode":"j5r 5w6",
    "addr:street":"Rue Bernier",
    "iso:country":"CA",
    "sg:address":"700 Rue Bernier",
    "sg:city":"LA Prairie",
    "sg:classifiers":[
        {
            "category":"Wholesale",
            "subcategory":"Hardware",
            "type":"Manufacturing & Wholesale Goods"
        }
    ],
    "sg:phone":"+1 450 444 7864",
    "sg:postcode":"J5R 5W6",
    "sg:province":"QC",
    "sg:tags":[
        "dust",
        "collecting",
        "system"
    ],
    "wof:name":"Spec-Air Depoussiereurs Inc",
    "wof:placetype":"venue"
},
  "geometry": {"coordinates":[-73.494438,45.399311],"type":"Point"}
}