{
  "type": "Feature",
  "properties": {
    "addr:full":"Langley BC V3A 5E8",
    "addr:postcode":"v3a 5e8",
    "iso:country":"CA",
    "sg:city":"Langley",
    "sg:classifiers":[
        {
            "category":"Manufacturing",
            "subcategory":"Metals",
            "type":"Manufacturing & Wholesale Goods"
        }
    ],
    "sg:phone":"+1 604 530 9492",
    "sg:postcode":"V3A 5E8",
    "sg:province":"BC",
    "sg:tags":[
        "equipment",
        "conveyor",
        "conveying"
    ],
    "wof:name":"Canvey Equipment Erectors Inc",
    "wof:placetype":"venue"
},
  "geometry": {"coordinates":[-122.650589,49.113266],"type":"Point"}
}