{
  "type": "Feature",
  "properties": {
    "addr:full":"216 38 Ave NE Calgary AB T2E 2M2",
    "addr:postcode":"t2e 2m2",
    "addr:street":"216 38 Ave Ne",
    "iso:country":"CA",
    "sg:address":"216 38 Ave NE",
    "sg:city":"Calgary",
    "sg:classifiers":[
        {
            "category":"Retail",
            "subcategory":"Auto Repair",
            "type":"Services"
        }
    ],
    "sg:phone":"+1 403 276 3460",
    "sg:postcode":"T2E 2M2",
    "sg:province":"AB",
    "sg:tags":[
        "automobile",
        "restoration",
        "classic"
    ],
    "wof:name":"Donz' Wheels of Time Rstrtn",
    "wof:placetype":"venue"
},
  "geometry": {"coordinates":[-114.059288025,51.0869598389],"type":"Point"}
}