{
  "type": "Feature",
  "properties": {
    "addr:full":"1244 Rue Belvedere S Sherbrooke QC J1H 4C7",
    "addr:housenumber":"1244",
    "addr:postcode":"j1h 4c7",
    "addr:street":"Rue Belvedere S",
    "iso:country":"CA",
    "sg:address":"1244 Rue Belvedere S",
    "sg:city":"Sherbrooke",
    "sg:classifiers":[
        {
            "category":"Education",
            "subcategory":"School",
            "type":"Public Place"
        }
    ],
    "sg:phone":"+1 819 562 2020",
    "sg:postcode":"J1H 4C7",
    "sg:province":"QC",
    "sg:tags":[
        "glass",
        "special",
        "academic"
    ],
    "wof:name":"Centre Du Vitrail",
    "wof:placetype":"venue"
},
  "geometry": {"coordinates":[-71.89621699999999,45.38755],"type":"Point"}
}