{
  "type": "Feature",
  "properties": {
    "addr:full":"2921 Murray St Port Moody BC V3H 1X3",
    "addr:housenumber":"2921",
    "addr:postcode":"v3h 1x3",
    "addr:street":"Murray St",
    "iso:country":"CA",
    "sg:address":"2921 Murray St",
    "sg:city":"Port Moody",
    "sg:classifiers":[
        {
            "category":"Manufacturing",
            "subcategory":"Tools & Machinery",
            "type":"Manufacturing & Wholesale Goods"
        }
    ],
    "sg:phone":"+1 604 469 8711",
    "sg:postcode":"V3H 1X3",
    "sg:province":"BC",
    "sg:tags":[
        "machine",
        "shop"
    ],
    "wof:name":"Amaco Machinery Ltd",
    "wof:placetype":"venue"
},
  "geometry": {"coordinates":[-122.845451,49.278713],"type":"Point"}
}