{
  "type": "Feature",
  "properties": {
    "addr:full":"470 Rue Irene-Couture Sherbrooke QC J1L 1J4",
    "addr:housenumber":"470",
    "addr:postcode":"j1l 1j4",
    "addr:street":"Rue Irene-Couture",
    "iso:country":"CA",
    "sg:address":"470 Rue Irene-Couture",
    "sg:city":"Sherbrooke",
    "sg:classifiers":[
        {
            "category":"Professional",
            "type":"Services"
        }
    ],
    "sg:phone":"+1 819 346 7588",
    "sg:postcode":"J1L 1J4",
    "sg:province":"QC",
    "sg:tags":[
        "laboratory",
        "consulting"
    ],
    "wof:name":"Inotel Inc",
    "wof:placetype":"venue"
},
  "geometry": {"coordinates":[-71.9378738403,45.406162262],"type":"Point"}
}