{
  "type": "Feature",
  "properties": {
    "addr:full":"258 County Rd 8 Douro ON K0L 1S0",
    "addr:housenumber":"258;8",
    "addr:postcode":"k0l 1s0",
    "addr:street":"County Rd",
    "iso:country":"CA",
    "sg:address":"258 County Rd 8",
    "sg:city":"Douro",
    "sg:classifiers":[
        {
            "category":"Wholesale",
            "subcategory":"Auto Parts",
            "type":"Manufacturing & Wholesale Goods"
        }
    ],
    "sg:phone":"+1 705 652 3338",
    "sg:postcode":"K0L 1S0",
    "sg:province":"ON",
    "sg:tags":[
        "automobile",
        "wrecking"
    ],
    "wof:name":"Ray Cranley Auto Wreckers Ltd",
    "wof:placetype":"venue"
},
  "geometry": {"coordinates":[-78.1877288818,44.3771896362],"type":"Point"}
}