{
  "type": "Feature",
  "properties": {
    "addr:full":"1196 Danforth Ave Toronto ON M4J 1M6",
    "addr:housenumber":"1196",
    "addr:postcode":"m4j 1m6",
    "addr:street":"Danforth Ave",
    "iso:country":"CA",
    "sg:address":"1196 Danforth Ave",
    "sg:city":"Toronto",
    "sg:classifiers":[
        {
            "category":"Home & Garden",
            "subcategory":"Building Materials",
            "type":"Retail Goods"
        }
    ],
    "sg:phone":"+1 416 461 5815",
    "sg:postcode":"M4J 1M6",
    "sg:province":"ON",
    "sg:tags":[
        "paint"
    ],
    "wof:name":"Decor Paints & Wallpaper",
    "wof:placetype":"venue"
},
  "geometry": {"coordinates":[-79.33219099999999,43.681637],"type":"Point"}
}