{
  "type": "Feature",
  "properties": {
    "addr:full":"3760 Old Clayburn Rd Abbotsford BC V3G 1H8",
    "addr:housenumber":"3760",
    "addr:postcode":"v3g 1h8",
    "addr:street":"Old Clayburn Rd",
    "iso:country":"CA",
    "sg:address":"3760 Old Clayburn Rd",
    "sg:city":"Abbotsford",
    "sg:classifiers":[
        {
            "category":"Shopping",
            "subcategory":"Crafts & Fabrics",
            "type":"Retail Goods"
        }
    ],
    "sg:phone":"+1 604 853 9132",
    "sg:postcode":"V3G 1H8",
    "sg:province":"BC",
    "sg:tags":[
        "shop"
    ],
    "wof:name":"Labours of Love Heirloom Supls",
    "wof:placetype":"venue"
},
  "geometry": {"coordinates":[-122.249137878,49.0703659058],"type":"Point"}
}