{
  "type": "Feature",
  "properties": {
    "iso:country":"CA",
    "sg:address":"1496 Rupert St",
    "sg:city":"North Vancouver",
    "sg:classifiers":[
        {
            "category":"Autos & Motor Vehicles",
            "subcategory":"Motorcycle Sales",
            "type":"Retail Goods"
        }
    ],
    "sg:phone":"+1 604 983 8435",
    "sg:postcode":"V7J 1E9",
    "sg:province":"BC",
    "sg:tags":[
        "scooter"
    ],
    "wof:name":"Diamond Dave's Custom Cycles",
    "wof:placetype":"venue"
},
  "geometry": {"coordinates":[-123.033478,49.271519],"type":"Point"}
}