{
  "type": "Feature",
  "properties": {
    "addr:full":"Ottawa ON K1N 5S7",
    "addr:postcode":"k1n 5s7",
    "iso:country":"CA",
    "sg:city":"Ottawa",
    "sg:classifiers":[
        {
            "category":"Building & Trades",
            "subcategory":"Construction",
            "type":"Services"
        }
    ],
    "sg:phone":"+1 613 241 9344",
    "sg:postcode":"K1N 5S7",
    "sg:province":"ON",
    "sg:tags":[
        "general",
        "contractor"
    ],
    "wof:name":"Dan Tanguay Construction",
    "wof:placetype":"venue"
},
  "geometry": {"coordinates":[-75.6944274902,45.4277763367],"type":"Point"}
}