{
  "type": "Feature",
  "properties": {
    "addr:full":"5145 Satellite Dr Mississauga ON L4W 5B6",
    "addr:housenumber":"5145",
    "addr:postcode":"l4w 5b6",
    "addr:street":"Satellite Dr",
    "iso:country":"CA",
    "sg:address":"5145 Satellite Dr",
    "sg:city":"Mississauga",
    "sg:classifiers":[
        {
            "category":"Manufacturing",
            "subcategory":"Printing",
            "type":"Manufacturing & Wholesale Goods"
        }
    ],
    "sg:phone":"+1 905 625 1323",
    "sg:postcode":"L4W 5B6",
    "sg:province":"ON",
    "sg:tags":[
        "decal"
    ],
    "wof:name":"Holland & Crosby",
    "wof:placetype":"venue"
},
  "geometry": {"coordinates":[-79.60607899999999,43.654125],"type":"Point"}
}