{
  "type": "Feature",
  "properties": {
    "addr:full":"8090 Plaza Dr Dundas ON L9H 4H4",
    "addr:housenumber":"8090",
    "addr:postcode":"l9h 4h4",
    "addr:street":"Plaza Dr",
    "iso:country":"CA",
    "sg:address":"8090 Plaza Dr",
    "sg:city":"Dundas",
    "sg:classifiers":[
        {
            "category":"Retail",
            "subcategory":"Auto Repair",
            "type":"Services"
        }
    ],
    "sg:phone":"+1 905 628 9758",
    "sg:postcode":"L9H 4H4",
    "sg:province":"ON",
    "sg:tags":[
        "brake"
    ],
    "wof:name":"Beverly Tire",
    "wof:placetype":"venue"
},
  "geometry": {"coordinates":[-79.9414901733,43.2590103149],"type":"Point"}
}