{
  "type": "Feature",
  "properties": {
    "addr:full":"97 Hamilton River Rd Happy Valley-Goose Bay NL A0P 1E0",
    "addr:housenumber":"97",
    "addr:postcode":"a0p 1e0",
    "addr:street":"Hamilton River Rd",
    "iso:country":"CA",
    "sg:address":"97 Hamilton River Rd",
    "sg:city":"Happy Valley-Goose Bay",
    "sg:classifiers":[
        {
            "category":"Restaurant",
            "type":"Food & Drink"
        }
    ],
    "sg:phone":"+1 709 896 3585",
    "sg:postcode":"A0P 1E0",
    "sg:province":"NL",
    "wof:name":"Bentley's",
    "wof:placetype":"venue"
},
  "geometry": {"coordinates":[-60.3742980957,53.3064537048],"type":"Point"}
}