{
  "type": "Feature",
  "properties": {
    "addr:full":"4155 Craig Rd Port Alberni BC V9Y 5Y4",
    "addr:housenumber":"4155",
    "addr:postcode":"v9y 5y4",
    "addr:street":"Craig Rd",
    "iso:country":"CA",
    "sg:address":"4155 Craig Rd",
    "sg:city":"Port Alberni",
    "sg:classifiers":[
        {
            "category":"Building & Trades",
            "subcategory":"Plumbing",
            "type":"Services"
        }
    ],
    "sg:phone":"+1 250 724 4314",
    "sg:postcode":"V9Y 5Y4",
    "sg:province":"BC",
    "sg:tags":[
        "contractor"
    ],
    "wof:name":"Carmanah Pacific Plumbing",
    "wof:placetype":"venue"
},
  "geometry": {"coordinates":[-124.797798,49.267059],"type":"Point"}
}