{
  "type": "Feature",
  "properties": {
    "addr:full":"Vancouver BC V6P 4Z4",
    "addr:postcode":"v6p 4z4",
    "iso:country":"CA",
    "sg:city":"Vancouver",
    "sg:classifiers":[
        {
            "category":"Social Services",
            "type":"Services"
        }
    ],
    "sg:phone":"+1 604 323 0901",
    "sg:postcode":"V6P 4Z4",
    "sg:province":"BC",
    "sg:tags":[
        "organization",
        "welfare"
    ],
    "wof:name":"Mandarin Service Ctr",
    "wof:placetype":"venue"
},
  "geometry": {"coordinates":[-123.140244,49.211521],"type":"Point"}
}