{
  "type": "Feature",
  "properties": {
    "addr:full":"250 Rue Saint-Louis Loretteville QC G2B 1L4",
    "addr:housenumber":"250",
    "addr:postcode":"g2b 1l4",
    "addr:street":"Rue Saint-Louis",
    "iso:country":"CA",
    "sg:address":"250 Rue Saint-Louis",
    "sg:city":"Loretteville",
    "sg:classifiers":[
        {
            "category":"Shopping",
            "subcategory":"Clothing, Apparel, & Fashions",
            "type":"Retail Goods"
        }
    ],
    "sg:phone":"+1 418 843 8168",
    "sg:postcode":"G2B 1L4",
    "sg:province":"QC",
    "sg:tags":[
        "dressmaker"
    ],
    "wof:name":"Atelier Couture Fernande",
    "wof:placetype":"venue"
},
  "geometry": {"coordinates":[-71.3585968018,46.8523597717],"type":"Point"}
}