{
  "type": "Feature",
  "properties": {
    "addr:full":"1835 Carrigan Dr Orleans ON K4A 2V4",
    "addr:housenumber":"1835",
    "addr:postcode":"k4a 2v4",
    "addr:street":"Carrigan Dr",
    "iso:country":"CA",
    "sg:address":"1835 Carrigan Dr",
    "sg:city":"Orleans",
    "sg:classifiers":[
        {
            "category":"Social Services",
            "type":"Services"
        }
    ],
    "sg:phone":"+1 613 834 0889",
    "sg:postcode":"K4A 2V4",
    "sg:province":"ON",
    "sg:tags":[
        "organization",
        "welfare"
    ],
    "wof:name":"Christian Horizons",
    "wof:placetype":"venue"
},
  "geometry": {"coordinates":[-75.47879,45.473461],"type":"Point"}
}