{
  "type": "Feature",
  "properties": {
    "addr:full":"1646 Ch Saint-Louis Sillery QC G1S 1G8",
    "addr:postcode":"1646;g1s 1g8",
    "addr:street":"Ch Saint-Louis",
    "iso:country":"CA",
    "sg:address":"1646 Ch Saint-Louis",
    "sg:city":"Sillery",
    "sg:classifiers":[
        {
            "category":"Food & Beverages",
            "subcategory":"Bakery",
            "type":"Retail Goods"
        }
    ],
    "sg:phone":"+1 418 684 0200",
    "sg:postcode":"G1S 1G8",
    "sg:province":"QC",
    "sg:tags":[
        "baker"
    ],
    "wof:name":"Boulangerie Paul",
    "wof:placetype":"venue"
},
  "geometry": {"coordinates":[-71.2462463379,46.7838439941],"type":"Point"}
}