{
  "type": "Feature",
  "properties": {
    "iso:country":"CA",
    "sg:address":"576 Foxwood Trail",
    "sg:city":"Pickering",
    "sg:classifiers":[
        {
            "category":"Building & Trades",
            "subcategory":"Plumbing",
            "type":"Services"
        }
    ],
    "sg:phone":"+1 905 837 2014",
    "sg:postcode":"L1V 4P7",
    "sg:province":"ON",
    "sg:tags":[
        "contractor"
    ],
    "wof:name":"Conmar Plumbing & Drains",
    "wof:placetype":"venue"
},
  "geometry": {"coordinates":[-79.1269683838,43.8234825134],"type":"Point"}
}