{
  "type": "Feature",
  "properties": {
    "addr:full":"Brampton ON L6Y 1T8",
    "addr:postcode":"l6y 1t8",
    "iso:country":"CA",
    "sg:city":"Brampton",
    "sg:classifiers":[
        {
            "category":"Real Estate",
            "subcategory":"Real Estate Operator",
            "type":"Services"
        }
    ],
    "sg:phone":"+1 905 459 4990",
    "sg:postcode":"L6Y 1T8",
    "sg:province":"ON",
    "sg:tags":[
        "apartment"
    ],
    "wof:name":"Palazzo Towers",
    "wof:placetype":"venue"
},
  "geometry": {"coordinates":[-79.749847,43.674736],"type":"Point"}
}