{
  "type": "Feature",
  "properties": {
    "addr:full":"355 Jane St Toronto ON M6S 3Z3",
    "addr:housenumber":"355",
    "addr:postcode":"m6s 3z3",
    "addr:street":"Jane St",
    "iso:country":"CA",
    "sg:address":"355 Jane St",
    "sg:city":"Toronto",
    "sg:classifiers":[
        {
            "category":"Shopping",
            "type":"Retail Goods"
        }
    ],
    "sg:phone":"+1 416 766 2982",
    "sg:postcode":"M6S 3Z3",
    "sg:province":"ON",
    "sg:tags":[
        "art",
        "gallery",
        "dealer"
    ],
    "wof:name":"Roach Tackle Folk Art",
    "wof:placetype":"venue"
},
  "geometry": {"coordinates":[-79.487602,43.657459],"type":"Point"}
}