{
  "type": "Feature",
  "properties": {
    "addr:full":"3149 Kingsway Ave Port Alberni BC V9Y 3B2",
    "addr:housenumber":"3149",
    "addr:postcode":"v9y 3b2",
    "addr:street":"Kingsway Ave",
    "iso:country":"CA",
    "sg:address":"3149 Kingsway Ave",
    "sg:city":"Port Alberni",
    "sg:classifiers":[
        {
            "category":"Shopping",
            "subcategory":"Bicycles & Sporting Goods",
            "type":"Retail Goods"
        }
    ],
    "sg:phone":"+1 250 724 5766",
    "sg:postcode":"V9Y 3B2",
    "sg:province":"BC",
    "sg:tags":[
        "dealer",
        "boat",
        "sales"
    ],
    "wof:name":"Alberni Industrial Marine Supl",
    "wof:placetype":"venue"
},
  "geometry": {"coordinates":[-124.811462402,49.2353363037],"type":"Point"}
}