{
  "type": "Feature",
  "properties": {
    "addr:full":"54 Clark St Welland ON L3B 5W6",
    "addr:housenumber":"54",
    "addr:postcode":"l3b 5w6",
    "addr:street":"Clark St",
    "iso:country":"CA",
    "sg:address":"54 Clark St",
    "sg:city":"Welland",
    "sg:classifiers":[
        {
            "category":"Wholesale",
            "subcategory":"Machinery & Supplies",
            "type":"Manufacturing & Wholesale Goods"
        }
    ],
    "sg:phone":"+1 905 788 3305",
    "sg:postcode":"L3B 5W6",
    "sg:province":"ON",
    "sg:tags":[
        "engine"
    ],
    "wof:name":"Premier Engines",
    "wof:placetype":"venue"
},
  "geometry": {"coordinates":[-79.260223,42.963921],"type":"Point"}
}