{
  "type": "Feature",
  "properties": {
    "addr:full":"509 Boul Arthur-Sauve Saint-Eustache QC J7P 4X4",
    "addr:housenumber":"509",
    "addr:postcode":"j7p 4x4",
    "addr:street":"Boul Arthur-Sauve",
    "iso:country":"CA",
    "sg:address":"509 Boul Arthur-Sauve",
    "sg:city":"Saint-Eustache",
    "sg:classifiers":[
        {
            "category":"Shopping",
            "subcategory":"Pharmacy",
            "type":"Retail Goods"
        }
    ],
    "sg:phone":"+1 450 473 4169",
    "sg:postcode":"J7P 4X4",
    "sg:province":"QC",
    "wof:name":"Uniprix Granger & Pinel",
    "wof:placetype":"venue"
},
  "geometry": {"coordinates":[-73.9119644165,45.5717964172],"type":"Point"}
}