{
  "type": "Feature",
  "properties": {
    "addr:full":"22 Buchanan St Cobourg ON K9A 1Y9",
    "addr:housenumber":"22",
    "addr:postcode":"k9a 1y9",
    "addr:street":"Buchanan St",
    "iso:country":"CA",
    "sg:address":"22 Buchanan St",
    "sg:city":"Cobourg",
    "sg:classifiers":[
        {
            "category":"Manufacturing",
            "subcategory":"Tools & Machinery",
            "type":"Manufacturing & Wholesale Goods"
        }
    ],
    "sg:phone":"+1 905 372 1632",
    "sg:postcode":"K9A 1Y9",
    "sg:province":"ON",
    "sg:tags":[
        "refrigeration",
        "contractor"
    ],
    "wof:name":"Wayne Simpson Refrigeration",
    "wof:placetype":"venue"
},
  "geometry": {"coordinates":[-78.17083740229999,43.9694213867],"type":"Point"}
}