{
  "type": "Feature",
  "properties": {
    "addr:full":"1171 3E Av Grand-Mere QC G9T 2W1",
    "addr:housenumber":"1171",
    "addr:postcode":"g9t 2w1",
    "addr:street":"3E Av Grand-Mere",
    "iso:country":"CA",
    "sg:address":"1171 3E Av",
    "sg:city":"Grand-Mere",
    "sg:classifiers":[
        {
            "category":"Building & Trades",
            "subcategory":"Equipment Rental",
            "type":"Services"
        }
    ],
    "sg:phone":"+1 819 533 3841",
    "sg:postcode":"G9T 2W1",
    "sg:province":"QC",
    "sg:tags":[
        "leasing",
        "production",
        "video",
        "taping"
    ],
    "wof:name":"Productions Novel Inc",
    "wof:placetype":"venue"
},
  "geometry": {"coordinates":[-72.69647999999999,46.607849],"type":"Point"}
}