{
  "type": "Feature",
  "properties": {
    "addr:full":"2020 Oak Bay Ave Victoria BC V8R 1E4",
    "addr:housenumber":"2020",
    "addr:postcode":"v8r 1e4",
    "addr:street":"Oak Bay Ave",
    "iso:country":"CA",
    "sg:address":"2020 Oak Bay Ave",
    "sg:city":"Victoria",
    "sg:classifiers":[
        {
            "category":"Restaurant",
            "type":"Food & Drink"
        }
    ],
    "sg:phone":"+1 250 595 3151",
    "sg:postcode":"V8R 1E4",
    "sg:province":"BC",
    "sg:tags":[
        "delicatessen"
    ],
    "wof:name":"Chef on the Run",
    "wof:placetype":"venue"
},
  "geometry": {"coordinates":[-123.322669983,48.4264183044],"type":"Point"}
}