{
  "type": "Feature",
  "properties": {
    "addr:full":"10585 115 St NW Edmonton AB T5H 3K4",
    "addr:housenumber":"10585",
    "addr:postcode":"t5h 3k4",
    "addr:street":"115 St Nw",
    "iso:country":"CA",
    "sg:address":"10585 115 St NW",
    "sg:city":"Edmonton",
    "sg:classifiers":[
        {
            "category":"Organizations",
            "subcategory":"Professional Association",
            "type":"Services"
        }
    ],
    "sg:phone":"+1 780 421 1615",
    "sg:postcode":"T5H 3K4",
    "sg:province":"AB",
    "wof:name":"Ethiopian Community Assn",
    "wof:placetype":"venue"
},
  "geometry": {"coordinates":[-113.519241333,53.5494613647],"type":"Point"}
}