{
  "type": "Feature",
  "properties": {
    "addr:full":"1 Av Des Erables Clair NB E7A 2B4",
    "addr:postcode":"e7a 2b4",
    "addr:street":"Av Des Erables",
    "iso:country":"CA",
    "sg:address":"1 Av Des Erables",
    "sg:city":"Clair",
    "sg:classifiers":[
        {
            "category":"Home & Garden",
            "subcategory":"Hardware",
            "type":"Retail Goods"
        }
    ],
    "sg:phone":"+1 506 992 2600",
    "sg:postcode":"E7A 2B4",
    "sg:province":"NB",
    "wof:name":"Home Hardware",
    "wof:placetype":"venue"
},
  "geometry": {"coordinates":[-68.603447,47.253017],"type":"Point"}
}