{
  "type": "Feature",
  "properties": {
    "addr:full":"7719 69 St NW Edmonton AB T6B 1V4",
    "addr:housenumber":"7719",
    "addr:postcode":"t6b 1v4",
    "addr:street":"69 St Nw",
    "iso:country":"CA",
    "sg:address":"7719 69 St NW",
    "sg:city":"Edmonton",
    "sg:classifiers":[
        {
            "category":"Manufacturing",
            "subcategory":"Tools & Machinery",
            "type":"Manufacturing & Wholesale Goods"
        }
    ],
    "sg:phone":"+1 780 440 5064",
    "sg:postcode":"T6B 1V4",
    "sg:province":"AB",
    "sg:tags":[
        "field",
        "oil",
        "equipment"
    ],
    "wof:name":"Lotech Manufacturing Inc",
    "wof:placetype":"venue"
},
  "geometry": {"coordinates":[-113.43306699999999,53.513496],"type":"Point"}
}