{
  "type": "Feature",
  "properties": {
    "addr:full":"121 Thirtieth St Etobicoke ON M8W 3C1",
    "addr:housenumber":"121",
    "addr:postcode":"m8w 3c1",
    "addr:street":"Thirtieth St",
    "iso:country":"CA",
    "sg:address":"121 Thirtieth St",
    "sg:city":"Etobicoke",
    "sg:classifiers":[
        {
            "category":"Home & Garden",
            "subcategory":"Carpets & Floor Coverings",
            "type":"Retail Goods"
        }
    ],
    "sg:phone":"+1 416 255 1111",
    "sg:postcode":"M8W 3C1",
    "sg:province":"ON",
    "sg:tags":[
        "material"
    ],
    "wof:name":"Flextile Limited",
    "wof:placetype":"venue"
},
  "geometry": {"coordinates":[-79.531532,43.599827],"type":"Point"}
}