{
  "type": "Feature",
  "properties": {
    "addr:full":"499 Rue Principale Saint-Sebastien-DE-Frontenac QC G0Y 1M0",
    "addr:housenumber":"499",
    "addr:postcode":"g0y 1m0",
    "addr:street":"Rue Principale",
    "iso:country":"CA",
    "sg:address":"499 Rue Principale",
    "sg:city":"Saint-Sebastien-DE-Frontenac",
    "sg:classifiers":[
        {
            "category":"Retail",
            "subcategory":"Auto Repair",
            "type":"Services"
        }
    ],
    "sg:phone":"+1 819 652 2100",
    "sg:postcode":"G0Y 1M0",
    "sg:province":"QC",
    "sg:tags":[
        "repairing",
        "automobile"
    ],
    "wof:name":"Garage Bernier",
    "wof:placetype":"venue"
},
  "geometry": {"coordinates":[-70.974609375,45.7842254639],"type":"Point"}
}