{
  "type": "Feature",
  "properties": {
    "iso:country":"CA",
    "sg:address":"1551 22E Rue",
    "sg:city":"Saint-Come-Liniere",
    "sg:classifiers":[
        {
            "category":"Manufacturing",
            "subcategory":"Tools & Machinery",
            "type":"Manufacturing & Wholesale Goods"
        }
    ],
    "sg:phone":"+1 418 685 3244",
    "sg:postcode":"G0M 1J0",
    "sg:province":"QC",
    "sg:tags":[
        "machine",
        "shop"
    ],
    "wof:name":"Usinage F Lacasse",
    "wof:placetype":"venue"
},
  "geometry": {"coordinates":[-70.52057647709999,46.0611000061],"type":"Point"}
}