{
  "type": "Feature",
  "properties": {
    "addr:full":"161 Rue Des Pins Lac-Des-Ecorces QC J0W 1H0",
    "addr:housenumber":"161",
    "addr:postcode":"j0w 1h0",
    "addr:street":"Rue Des Pins Lac-Des-Ecorces",
    "iso:country":"CA",
    "sg:address":"161 Rue Des Pins",
    "sg:city":"Lac-Des-Ecorces",
    "sg:classifiers":[
        {
            "category":"Food & Beverages",
            "subcategory":"Bakery",
            "type":"Retail Goods"
        }
    ],
    "sg:phone":"+1 819 585 2264",
    "sg:postcode":"J0W 1H0",
    "sg:province":"QC",
    "sg:tags":[
        "baker"
    ],
    "wof:name":"Tarte Brault Enr",
    "wof:placetype":"venue"
},
  "geometry": {"coordinates":[-75.364349,46.554932],"type":"Point"}
}