{
  "type": "Feature",
  "properties": {
    "addr:full":"58 Av Begin Levis QC G6V 4C2",
    "addr:postcode":"g6v 4c2",
    "addr:street":"58 Av Begin",
    "iso:country":"CA",
    "sg:address":"58 Av Begin",
    "sg:city":"Levis",
    "sg:classifiers":[
        {
            "category":"Retail",
            "subcategory":"Funeral Services",
            "type":"Services"
        }
    ],
    "sg:phone":"+1 418 837 4757",
    "sg:postcode":"G6V 4C2",
    "sg:province":"QC",
    "sg:tags":[
        "director"
    ],
    "wof:name":"Gilbert & Turgeon Ltee",
    "wof:placetype":"venue"
},
  "geometry": {"coordinates":[-71.180977,46.808216],"type":"Point"}
}