{
  "type": "Feature",
  "properties": {
    "addr:full":"29 Memorial Ave Elmira ON N3B 2R3",
    "addr:housenumber":"29",
    "addr:postcode":"n3b 2r3",
    "addr:street":"Memorial Ave",
    "iso:country":"CA",
    "sg:address":"29 Memorial Ave",
    "sg:city":"Elmira",
    "sg:classifiers":[
        {
            "category":"Health Services",
            "subcategory":"Health Practitioner",
            "type":"Services"
        }
    ],
    "sg:phone":"+1 519 669 8181",
    "sg:postcode":"N3B 2R3",
    "sg:province":"ON",
    "sg:tags":[
        "therapist",
        "physical"
    ],
    "wof:name":"Elmira Massage Therapy",
    "wof:placetype":"venue"
},
  "geometry": {"coordinates":[-80.5583648682,43.5969657898],"type":"Point"}
}