{
  "type": "Feature",
  "properties": {
    "iso:country":"CA",
    "sg:address":"447 Selkirk Ave",
    "sg:city":"Winnipeg",
    "sg:classifiers":[
        {
            "category":"Retail",
            "subcategory":"Funeral Services",
            "type":"Services"
        }
    ],
    "sg:phone":"+1 204 582 0929",
    "sg:postcode":"R2W 2M4",
    "sg:province":"MB",
    "sg:tags":[
        "director"
    ],
    "wof:name":"Wereschuk Funeral Chapel",
    "wof:placetype":"venue"
},
  "geometry": {"coordinates":[-97.142891,49.915154],"type":"Point"}
}