{
  "type": "Feature",
  "properties": {
    "addr:full":"1702 Foy St Abbotsford BC V2T 6B1",
    "addr:housenumber":"1702",
    "addr:postcode":"v2t 6b1",
    "addr:street":"Foy St",
    "iso:country":"CA",
    "sg:address":"1702 Foy St",
    "sg:city":"Abbotsford",
    "sg:classifiers":[
        {
            "category":"Wholesale",
            "subcategory":"Construction Materials",
            "type":"Manufacturing & Wholesale Goods"
        }
    ],
    "sg:phone":"+1 604 850 0220",
    "sg:postcode":"V2T 6B1",
    "sg:province":"BC",
    "sg:tags":[
        "lumber",
        "broker"
    ],
    "wof:name":"North American Forest Products",
    "wof:placetype":"venue"
},
  "geometry": {"coordinates":[-122.32885,49.051575],"type":"Point"}
}