{
  "type": "Feature",
  "properties": {
    "addr:full":"Wetaskiwin AB T9A 2V6",
    "addr:postcode":"t9a 2v6",
    "iso:country":"CA",
    "sg:city":"Wetaskiwin",
    "sg:classifiers":[
        {
            "category":"Shopping",
            "subcategory":"Gifts & Souvenirs",
            "type":"Retail Goods"
        }
    ],
    "sg:phone":"+1 780 352 5377",
    "sg:postcode":"T9A 2V6",
    "sg:province":"AB",
    "sg:tags":[
        "cards",
        "greeting"
    ],
    "wof:name":"Carlton Cards Ltd",
    "wof:placetype":"venue"
},
  "geometry": {"coordinates":[-113.389854431,52.9549751282],"type":"Point"}
}