{
  "type": "Feature",
  "properties": {
    "iso:country":"CA",
    "sg:address":"285 Boul Saint-Luc",
    "sg:city":"Saint-Luc",
    "sg:classifiers":[
        {
            "category":"Building & Trades",
            "subcategory":"Construction",
            "type":"Services"
        }
    ],
    "sg:phone":"+1 450 349 3330",
    "sg:postcode":"J2W 1C5",
    "sg:province":"QC",
    "sg:tags":[
        "excavating",
        "contractor"
    ],
    "wof:name":"Construction Beaudin Inc",
    "wof:placetype":"venue"
},
  "geometry": {"coordinates":[-73.2973480225,45.3562011719],"type":"Point"}
}