{
  "type": "Feature",
  "properties": {
    "iso:country":"CA",
    "sg:city":"Chestermere",
    "sg:classifiers":[
        {
            "category":"Personal",
            "subcategory":"Beauty Salon",
            "type":"Services"
        }
    ],
    "sg:phone":"+1 403 569 9480",
    "sg:postcode":"T1X 1L6",
    "sg:province":"AB",
    "wof:name":"Purple Dove Hair Salon",
    "wof:placetype":"venue"
},
  "geometry": {"coordinates":[-113.842041016,51.0362510681],"type":"Point"}
}