{
  "type": "Feature",
  "properties": {
    "addr:full":"Campbell River BC V9W 2C2",
    "addr:postcode":"v9w 2c2",
    "iso:country":"CA",
    "sg:city":"Campbell River",
    "sg:classifiers":[
        {
            "category":"Banks & Credit Unions",
            "subcategory":"Bank",
            "type":"Services"
        }
    ],
    "sg:phone":"+1 250 850 3500",
    "sg:postcode":"V9W 2C2",
    "sg:province":"BC",
    "sg:tags":[
        "cashing",
        "loan",
        "check"
    ],
    "wof:name":"Instaloans Financial Solutions",
    "wof:placetype":"venue"
},
  "geometry": {"coordinates":[-125.240021,50.023663],"type":"Point"}
}