{
  "type": "Feature",
  "properties": {
    "addr:full":"Bois-Des-Filion QC J6Z 1H9",
    "addr:postcode":"j6z 1h9",
    "iso:country":"CA",
    "sg:city":"Bois-Des-Filion",
    "sg:classifiers":[
        {
            "category":"Health Services",
            "subcategory":"Doctor",
            "type":"Services"
        }
    ],
    "sg:phone":"+1 450 621 7266",
    "sg:postcode":"J6Z 1H9",
    "sg:province":"QC",
    "sg:tags":[
        "dentist"
    ],
    "wof:name":"Tanguay, Natalie DDS",
    "wof:placetype":"venue"
},
  "geometry": {"coordinates":[-73.758545,45.666412],"type":"Point"}
}