{
  "type": "Feature",
  "properties": {
    "addr:full":"4115 Sheppard Ave E Scarborough ON M1S 1T1",
    "addr:housenumber":"4115",
    "addr:postcode":"m1s 1t1",
    "addr:street":"Sheppard Ave E",
    "iso:country":"CA",
    "sg:address":"4115 Sheppard Ave E",
    "sg:city":"Scarborough",
    "sg:classifiers":[
        {
            "category":"Autos & Motor Vehicles",
            "subcategory":"Automobile Sales",
            "type":"Retail Goods"
        }
    ],
    "sg:phone":"+1 416 292 7528",
    "sg:postcode":"M1S 1T1",
    "sg:province":"ON",
    "sg:tags":[
        "car",
        "dealer"
    ],
    "wof:name":"Cantan Used Car Sales",
    "wof:placetype":"venue"
},
  "geometry": {"coordinates":[-79.28310399999999,43.784271],"type":"Point"}
}