{
  "type": "Feature",
  "properties": {
    "addr:full":"Victoria BC V8W 3B9",
    "addr:postcode":"v8w 3b9",
    "iso:country":"CA",
    "sg:city":"Victoria",
    "sg:classifiers":[
        {
            "category":"Freight",
            "type":"Transportation"
        }
    ],
    "sg:phone":"+1 250 384 1174",
    "sg:postcode":"V8W 3B9",
    "sg:province":"BC",
    "sg:tags":[
        "broker",
        "customs"
    ],
    "wof:name":"King Brothers Ltd",
    "wof:placetype":"venue"
},
  "geometry": {"coordinates":[-123.37025451700001,48.4261169434],"type":"Point"}
}