{
  "type": "Feature",
  "properties": {
    "addr:full":"525 Lees Rd North Bay ON P1B 8G2",
    "addr:housenumber":"525",
    "addr:postcode":"p1b 8g2",
    "addr:street":"Lees Rd",
    "iso:country":"CA",
    "sg:address":"525 Lees Rd",
    "sg:city":"North Bay",
    "sg:classifiers":[
        {
            "category":"Building & Trades",
            "subcategory":"Landscaping Services",
            "type":"Services"
        }
    ],
    "sg:phone":"+1 705 472 7788",
    "sg:postcode":"P1B 8G2",
    "sg:province":"ON",
    "sg:tags":[
        "landscape",
        "contractor"
    ],
    "wof:name":"Northern Tree Svc",
    "wof:placetype":"venue"
},
  "geometry": {"coordinates":[-79.399361,46.344322],"type":"Point"}
}