{
  "type": "Feature",
  "properties": {
    "addr:full":"115 Glen Scarlett Rd Toronto ON M6N 1P5",
    "addr:housenumber":"115",
    "addr:postcode":"m6n 1p5",
    "addr:street":"Glen Scarlett Rd",
    "iso:country":"CA",
    "sg:address":"115 Glen Scarlett Rd",
    "sg:city":"Toronto",
    "sg:classifiers":[
        {
            "category":"Manufacturing",
            "subcategory":"Retail Goods",
            "type":"Manufacturing & Wholesale Goods"
        }
    ],
    "sg:phone":"+1 416 766 4142",
    "sg:postcode":"M6N 1P5",
    "sg:province":"ON",
    "sg:tags":[
        "feather"
    ],
    "wof:name":"Feather Industries Canada Ltd",
    "wof:placetype":"venue"
},
  "geometry": {"coordinates":[-79.47737100000001,43.673584],"type":"Point"}
}