{
  "type": "Feature",
  "properties": {
    "addr:full":"206 Centre Line Westwood ON K0L 3B0",
    "addr:housenumber":"206",
    "addr:postcode":"k0l 3b0",
    "addr:street":"Centre Line",
    "iso:country":"CA",
    "sg:address":"206 Centre Line",
    "sg:city":"Westwood",
    "sg:classifiers":[
        {
            "category":"Shopping",
            "subcategory":"Stationery & Office Supplies",
            "type":"Retail Goods"
        }
    ],
    "sg:phone":"+1 705 696 1544",
    "sg:postcode":"K0L 3B0",
    "sg:province":"ON",
    "wof:name":"Complete Business Technologies",
    "wof:placetype":"venue"
},
  "geometry": {"coordinates":[-78.070374,44.3204],"type":"Point"}
}