{
  "type": "Feature",
  "properties": {
    "addr:full":"91 Plymouth St Winnipeg MB R2X 2V5",
    "addr:housenumber":"91",
    "addr:postcode":"r2x 2v5",
    "addr:street":"Plymouth St",
    "iso:country":"CA",
    "sg:address":"91 Plymouth St",
    "sg:city":"Winnipeg",
    "sg:classifiers":[
        {
            "category":"Wholesale",
            "subcategory":"Vending Machines",
            "type":"Manufacturing & Wholesale Goods"
        }
    ],
    "sg:phone":"+1 204 633 2405",
    "sg:postcode":"R2X 2V5",
    "sg:province":"MB",
    "wof:name":"Quality Vending & Coffee Svc",
    "wof:placetype":"venue"
},
  "geometry": {"coordinates":[-97.1884460449,49.9401321411],"type":"Point"}
}