{
  "type": "Feature",
  "properties": {
    "addr:full":"10528 100 Ave Westlock AB T7P 2J9",
    "addr:housenumber":"10528",
    "addr:postcode":"t7p 2j9",
    "addr:street":"100 Ave",
    "iso:country":"CA",
    "sg:address":"10528 100 Ave",
    "sg:city":"Westlock",
    "sg:classifiers":[
        {
            "category":"Personal",
            "subcategory":"Beauty Salon",
            "type":"Services"
        }
    ],
    "sg:phone":"+1 780 349 3140",
    "sg:postcode":"T7P 2J9",
    "sg:province":"AB",
    "wof:name":"Debbie Beauty & Barber",
    "wof:placetype":"venue"
},
  "geometry": {"coordinates":[-113.860855,54.154297],"type":"Point"}
}