{
  "type": "Feature",
  "properties": {
    "addr:full":"23 12th St Brandon MB R7A 4L6",
    "addr:housenumber":"23",
    "addr:postcode":"r7a 4l6",
    "addr:street":"12Th St",
    "iso:country":"CA",
    "sg:address":"23 12th St",
    "sg:city":"Brandon",
    "sg:classifiers":[
        {
            "category":"Social Services",
            "type":"Services"
        }
    ],
    "sg:phone":"+1 204 727 5425",
    "sg:postcode":"R7A 4L6",
    "sg:province":"MB",
    "sg:tags":[
        "organization",
        "association",
        "welfare"
    ],
    "wof:name":"Canadian Mental Health Assn",
    "wof:placetype":"venue"
},
  "geometry": {"coordinates":[-99.954033,49.848972],"type":"Point"}
}