{
  "type": "Feature",
  "properties": {
    "addr:full":"102 101E Rue Beauceville QC G5X 2M6",
    "addr:housenumber":"102",
    "addr:postcode":"g5x 2m6",
    "addr:street":"101E Rue",
    "iso:country":"CA",
    "sg:address":"102 101E Rue",
    "sg:city":"Beauceville",
    "sg:classifiers":[
        {
            "category":"Building & Trades",
            "subcategory":"Construction",
            "type":"Services"
        }
    ],
    "sg:phone":"+1 418 774 9638",
    "sg:postcode":"G5X 2M6",
    "sg:province":"QC",
    "sg:tags":[
        "masonry",
        "contractor"
    ],
    "wof:name":"Brique Gaston Poulin Inc",
    "wof:placetype":"venue"
},
  "geometry": {"coordinates":[-70.76892100000001,46.206646],"type":"Point"}
}