{
  "type": "Feature",
  "properties": {
    "addr:full":"442 Mill St Blyth ON N0M 1H0",
    "addr:housenumber":"442",
    "addr:postcode":"n0m 1h0",
    "addr:street":"Mill St",
    "iso:country":"CA",
    "sg:address":"442 Mill St",
    "sg:city":"Blyth",
    "sg:classifiers":[
        {
            "category":"Organizations",
            "subcategory":"Religious Organization",
            "type":"Services"
        }
    ],
    "sg:phone":"+1 519 523 4224",
    "sg:postcode":"N0M 1H0",
    "sg:province":"ON",
    "sg:tags":[
        "church"
    ],
    "wof:name":"Blyth United Church",
    "wof:placetype":"venue"
},
  "geometry": {"coordinates":[-81.427155,43.736122],"type":"Point"}
}