{
  "type": "Feature",
  "properties": {
    "iso:country":"CA",
    "sg:address":"7310 Woodbine Ave # 1B",
    "sg:city":"Markham",
    "sg:classifiers":[
        {
            "category":"Home & Garden",
            "subcategory":"Building Materials",
            "type":"Retail Goods"
        }
    ],
    "sg:phone":"+1 905 475 1984",
    "sg:postcode":"L3R 1A4",
    "sg:province":"ON",
    "sg:tags":[
        "type",
        "door"
    ],
    "wof:name":"J Adams Overhead Garage Ltd",
    "wof:placetype":"venue"
},
  "geometry": {"coordinates":[-79.3508071899,43.8214263916],"type":"Point"}
}