{
  "type": "Feature",
  "properties": {
    "iso:country":"CA",
    "sg:city":"Gloucester",
    "sg:classifiers":[
        {
            "category":"Freight",
            "type":"Transportation"
        }
    ],
    "sg:phone":"+1 613 738 3329",
    "sg:postcode":"K1V 0R4",
    "sg:province":"ON",
    "sg:tags":[
        "broker",
        "customs"
    ],
    "wof:name":"Glover Customs Brokers Inc",
    "wof:placetype":"venue"
},
  "geometry": {"coordinates":[-75.6520614624,45.3266906738],"type":"Point"}
}