{
  "type": "Feature",
  "properties": {
    "addr:full":"Sainte-Julie QC J3E 1W6",
    "addr:postcode":"j3e 1w6",
    "iso:country":"CA",
    "sg:city":"Sainte-Julie",
    "sg:classifiers":[
        {
            "category":"Shopping",
            "subcategory":"Computers & Home Electronics",
            "type":"Retail Goods"
        }
    ],
    "sg:phone":"+1 450 922 9607",
    "sg:postcode":"J3E 1W6",
    "sg:province":"QC",
    "sg:tags":[
        "television",
        "radio"
    ],
    "wof:name":"Pro-Centre Electronique",
    "wof:placetype":"venue"
},
  "geometry": {"coordinates":[-73.33551,45.59388],"type":"Point"}
}