{
  "type": "Feature",
  "properties": {
    "addr:full":"North York ON M3A 1B2",
    "addr:postcode":"m3a 1b2",
    "iso:country":"CA",
    "sg:city":"North York",
    "sg:classifiers":[
        {
            "category":"Professional",
            "subcategory":"Accounting & Tax Preparation",
            "type":"Services"
        }
    ],
    "sg:phone":"+1 416 441 6357",
    "sg:postcode":"M3A 1B2",
    "sg:province":"ON",
    "sg:tags":[
        "accountant"
    ],
    "wof:name":"Sharp Edmonds Sharp",
    "wof:placetype":"venue"
},
  "geometry": {"coordinates":[-79.32484436039999,43.7355728149],"type":"Point"}
}