{
  "type": "Feature",
  "properties": {
    "iso:country":"CA",
    "sg:address":"5207 Bank St",
    "sg:city":"Gloucester",
    "sg:classifiers":[
        {
            "category":"Building & Trades",
            "subcategory":"Plumbing",
            "type":"Services"
        }
    ],
    "sg:phone":"+1 613 822 6253",
    "sg:postcode":"K1X 1H2",
    "sg:province":"ON",
    "sg:tags":[
        "contractor"
    ],
    "wof:name":"Exner Plumbing & Heating",
    "wof:placetype":"venue"
},
  "geometry": {"coordinates":[-75.576294,45.29071],"type":"Point"}
}