{
  "type": "Feature",
  "properties": {
    "addr:full":"4111 6 St NE Calgary AB T2E 6V5",
    "addr:housenumber":"4111 6",
    "addr:postcode":"t2e 6v5",
    "addr:street":"St Ne",
    "iso:country":"CA",
    "sg:address":"4111 6 St NE",
    "sg:city":"Calgary",
    "sg:classifiers":[
        {
            "category":"Autos & Motor Vehicles",
            "subcategory":"Motorcycle Sales",
            "type":"Retail Goods"
        }
    ],
    "sg:phone":"+1 403 265 4833",
    "sg:postcode":"T2E 6V5",
    "sg:province":"AB",
    "sg:tags":[
        "scooter"
    ],
    "wof:name":"Bike Exchange",
    "wof:placetype":"venue"
},
  "geometry": {"coordinates":[-114.04844665500001,51.088886261],"type":"Point"}
}