{
  "type": "Feature",
  "properties": {
    "addr:full":"100 Village Dr Lake Louise AB T0L 1E0",
    "addr:housenumber":"100",
    "addr:postcode":"t0l 1e0",
    "addr:street":"Village Dr",
    "iso:country":"CA",
    "sg:address":"100 Village Dr",
    "sg:city":"Lake Louise",
    "sg:classifiers":[
        {
            "category":"Shopping",
            "type":"Retail Goods"
        }
    ],
    "sg:phone":"+1 403 522 2038",
    "sg:postcode":"T0L 1E0",
    "sg:province":"AB",
    "sg:tags":[
        "art",
        "gallery",
        "dealer"
    ],
    "wof:name":"Northern Art Impressions",
    "wof:placetype":"venue"
},
  "geometry": {"coordinates":[-116.17731499999999,51.425865],"type":"Point"}
}