{
  "type": "Feature",
  "properties": {
    "addr:full":"406 1st St Shippagan NB E8S 3E1",
    "addr:housenumber":"406",
    "addr:postcode":"e8s 3e1",
    "addr:street":"1St St",
    "iso:country":"CA",
    "sg:address":"406 1st St",
    "sg:city":"Shippagan",
    "sg:classifiers":[
        {
            "category":"Health Services",
            "subcategory":"Doctor",
            "type":"Services"
        }
    ],
    "sg:phone":"+1 506 336 4939",
    "sg:postcode":"E8S 3E1",
    "sg:province":"NB",
    "sg:tags":[
        "dentist"
    ],
    "wof:name":"St Laurent, Chantal DDS",
    "wof:placetype":"venue"
},
  "geometry": {"coordinates":[-64.711258,47.744629],"type":"Point"}
}