{
  "type": "Feature",
  "properties": {
    "iso:country":"CA",
    "sg:address":"6015 Boul Robert",
    "sg:city":"Saint-Leonard",
    "sg:classifiers":[
        {
            "category":"Shopping",
            "subcategory":"Florist",
            "type":"Retail Goods"
        }
    ],
    "sg:phone":"+1 514 721 7673",
    "sg:postcode":"H1P 1M9",
    "sg:province":"QC",
    "wof:name":"Fleuriste & Cadeaux Secret",
    "wof:placetype":"venue"
},
  "geometry": {"coordinates":[-73.5916137695,45.5929222107],"type":"Point"}
}