{
  "type": "Feature",
  "properties": {
    "addr:full":"138 Anderson Ave # 11 Markham ON L6E 1A4",
    "addr:housenumber":"138",
    "addr:postcode":"l6e 1a4",
    "addr:street":"Anderson Ave # 11",
    "iso:country":"CA",
    "sg:address":"138 Anderson Ave # 11",
    "sg:city":"Markham",
    "sg:classifiers":[
        {
            "category":"Manufacturing",
            "subcategory":"Tools & Machinery",
            "type":"Manufacturing & Wholesale Goods"
        }
    ],
    "sg:phone":"+1 905 471 8283",
    "sg:postcode":"L6E 1A4",
    "sg:province":"ON",
    "sg:tags":[
        "machine",
        "shop"
    ],
    "wof:name":"Irm Ltd",
    "wof:placetype":"venue"
},
  "geometry": {"coordinates":[-79.264725,43.903217],"type":"Point"}
}