{
  "type": "Feature",
  "properties": {
    "addr:full":"502 Marsh St Maple Creek SK S0N 1N0",
    "addr:housenumber":"502",
    "addr:postcode":"s0n 1n0",
    "addr:street":"Marsh St",
    "iso:country":"CA",
    "sg:address":"502 Marsh St",
    "sg:city":"Maple Creek",
    "sg:classifiers":[
        {
            "category":"Social Services",
            "subcategory":"Child Care",
            "type":"Services"
        }
    ],
    "sg:phone":"+1 306 662 3784",
    "sg:postcode":"S0N 1N0",
    "sg:province":"SK",
    "wof:name":"Jack & Jill CO-Operative Schl",
    "wof:placetype":"venue"
},
  "geometry": {"coordinates":[-109.480407715,49.9065856934],"type":"Point"}
}