{
  "type": "Feature",
  "properties": {
    "addr:full":"235 Cameron Rd SE Medicine Hat AB T1B 2Z2",
    "addr:housenumber":"235",
    "addr:postcode":"t1b 2z2",
    "addr:street":"Cameron Rd Se",
    "iso:country":"CA",
    "sg:address":"235 Cameron Rd SE",
    "sg:city":"Medicine Hat",
    "sg:classifiers":[
        {
            "category":"Education",
            "subcategory":"School",
            "type":"Public Place"
        }
    ],
    "sg:phone":"+1 403 529 2000",
    "sg:postcode":"T1B 2Z2",
    "sg:province":"AB",
    "wof:name":"Mother Teresa School",
    "wof:placetype":"venue"
},
  "geometry": {"coordinates":[-110.635780334,50.0096855164],"type":"Point"}
}