{
  "type": "Feature",
  "properties": {
    "addr:full":"3870 216 St Langley BC V3A 8P2",
    "addr:housenumber":"3870",
    "addr:postcode":"v3a 8p2",
    "addr:street":"216 St",
    "iso:country":"CA",
    "sg:address":"3870 216 St",
    "sg:city":"Langley",
    "sg:classifiers":[
        {
            "category":"Building & Trades",
            "subcategory":"Construction",
            "type":"Services"
        }
    ],
    "sg:phone":"+1 604 534 5783",
    "sg:postcode":"V3A 8P2",
    "sg:province":"BC",
    "sg:tags":[
        "excavating",
        "contractor"
    ],
    "wof:name":"Valley Custom Jackhammer Svc",
    "wof:placetype":"venue"
},
  "geometry": {"coordinates":[-122.624633789,49.0722503662],"type":"Point"}
}