{
  "type": "Feature",
  "properties": {
    "addr:full":"East Angus QC J0B 1R0",
    "addr:postcode":"j0b 1r0",
    "iso:country":"CA",
    "sg:city":"East Angus",
    "sg:classifiers":[
        {
            "category":"Professional",
            "subcategory":"Business Services",
            "type":"Services"
        }
    ],
    "sg:phone":"+1 819 832 4656",
    "sg:postcode":"J0B 1R0",
    "sg:province":"QC",
    "wof:name":"Recuperation Faber Moore Inc",
    "wof:placetype":"venue"
},
  "geometry": {"coordinates":[-71.6622619629,45.4879798889],"type":"Point"}
}