{
  "type": "Feature",
  "properties": {
    "iso:country":"CA",
    "sg:address":"60 Renfrew Dr",
    "sg:city":"Markham",
    "sg:classifiers":[
        {
            "category":"Banks & Credit Unions",
            "subcategory":"Investment Brokerage",
            "type":"Services"
        }
    ],
    "sg:phone":"+1 905 474 5617",
    "sg:postcode":"L3R 0E1",
    "sg:province":"ON",
    "sg:tags":[
        "consultant",
        "planning",
        "financial"
    ],
    "wof:name":"New Cap Financial Inc",
    "wof:placetype":"venue"
},
  "geometry": {"coordinates":[-79.36223602290001,43.8578453064],"type":"Point"}
}