{
  "type": "Feature",
  "properties": {
    "addr:full":"Hwy 209 Kenosee Lake SK S0C 2S0",
    "addr:postcode":"s0c 2s0",
    "addr:street":"Hwy 209 Kenosee",
    "iso:country":"CA",
    "sg:address":"Hwy 209",
    "sg:city":"Kenosee Lake",
    "sg:classifiers":[
        {
            "category":"Food & Beverages",
            "subcategory":"Groceries & Convenience Stores",
            "type":"Retail Goods"
        }
    ],
    "sg:phone":"+1 306 577 2234",
    "sg:postcode":"S0C 2S0",
    "sg:province":"SK",
    "sg:tags":[
        "grocer"
    ],
    "wof:name":"Allison Store Ltd",
    "wof:placetype":"venue"
},
  "geometry": {"coordinates":[-102.28563690199999,49.8320007324],"type":"Point"}
}