{
  "type": "Feature",
  "properties": {
    "addr:full":"River Denys NS B0E 2Y0",
    "addr:postcode":"b0e 2y0",
    "iso:country":"CA",
    "sg:city":"River Denys",
    "sg:classifiers":[
        {
            "category":"Building & Trades",
            "subcategory":"Construction",
            "type":"Services"
        }
    ],
    "sg:phone":"+1 902 756 3030",
    "sg:postcode":"B0E 2Y0",
    "sg:province":"NS",
    "sg:tags":[
        "culvert"
    ],
    "wof:name":"Fred N Bird Water & Sewerage",
    "wof:placetype":"venue"
},
  "geometry": {"coordinates":[-61.176071167,45.831905365],"type":"Point"}
}