{
  "type": "Feature",
  "properties": {
    "addr:full":"343 Victoria St E Alliston ON L9R 1J7",
    "addr:housenumber":"343",
    "addr:postcode":"l9r 1j7",
    "addr:street":"Victoria St E Alliston",
    "iso:country":"CA",
    "sg:address":"343 Victoria St E",
    "sg:city":"Alliston",
    "sg:classifiers":[
        {
            "category":"Retail",
            "subcategory":"Portrait Studio",
            "type":"Services"
        }
    ],
    "sg:phone":"+1 705 434 9797",
    "sg:postcode":"L9R 1J7",
    "sg:province":"ON",
    "sg:tags":[
        "photographer"
    ],
    "wof:name":"Charles Bryant Photography",
    "wof:placetype":"venue"
},
  "geometry": {"coordinates":[-79.853233,44.157253],"type":"Point"}
}