{
  "type": "Feature",
  "properties": {
    "addr:full":"115 Gillam Dr Gillam MB R0B 0L0",
    "addr:housenumber":"115",
    "addr:postcode":"r0b 0l0",
    "addr:street":"Gillam Dr",
    "iso:country":"CA",
    "sg:address":"115 Gillam Dr",
    "sg:city":"Gillam",
    "sg:classifiers":[
        {
            "category":"Health Services",
            "subcategory":"Hospital",
            "type":"Services"
        }
    ],
    "sg:phone":"+1 204 652 2600",
    "sg:postcode":"R0B 0L0",
    "sg:province":"MB",
    "wof:name":"Gillam Hospital Inc",
    "wof:placetype":"venue"
},
  "geometry": {"coordinates":[-94.7089309692,56.3494224548],"type":"Point"}
}