{
  "type": "Feature",
  "properties": {
    "addr:full":"1045 Main St Winnipeg MB R2W 3R2",
    "addr:housenumber":"1045",
    "addr:postcode":"r2w 3r2",
    "addr:street":"Main St",
    "iso:country":"CA",
    "sg:address":"1045 Main St",
    "sg:city":"Winnipeg",
    "sg:classifiers":[
        {
            "category":"Personal",
            "subcategory":"Beauty Salon",
            "type":"Services"
        }
    ],
    "sg:phone":"+1 204 586 4664",
    "sg:postcode":"R2W 3R2",
    "sg:province":"MB",
    "wof:name":"Joy Beauty Shop",
    "wof:placetype":"venue"
},
  "geometry": {"coordinates":[-97.1316452026,49.9143943787],"type":"Point"}
}