{
  "type": "Feature",
  "properties": {
    "addr:full":"50 East Wilmot St Richmond Hill ON L4B 3Z3",
    "addr:housenumber":"50",
    "addr:postcode":"l4b 3z3",
    "addr:street":"East Wilmot St",
    "iso:country":"CA",
    "sg:address":"50 East Wilmot St",
    "sg:city":"Richmond Hill",
    "sg:classifiers":[
        {
            "category":"Wholesale",
            "subcategory":"Stationery",
            "type":"Manufacturing & Wholesale Goods"
        }
    ],
    "sg:phone":"+1 905 771 4000",
    "sg:postcode":"L4B 3Z3",
    "sg:province":"ON",
    "sg:tags":[
        "printing",
        "product",
        "paper",
        "supply"
    ],
    "wof:name":"Unisource Canada Inc",
    "wof:placetype":"venue"
},
  "geometry": {"coordinates":[-79.38074493409999,43.8537063599],"type":"Point"}
}