{
  "type": "Feature",
  "properties": {
    "iso:country":"CA",
    "sg:address":"117 Broadway St",
    "sg:city":"Carnduff",
    "sg:classifiers":[
        {
            "category":"Shopping",
            "subcategory":"Computers & Home Electronics",
            "type":"Retail Goods"
        }
    ],
    "sg:phone":"+1 306 482 4004",
    "sg:postcode":"S0C 0S0",
    "sg:province":"SK",
    "sg:tags":[
        "equipment",
        "dealer"
    ],
    "wof:name":"Itcomputes",
    "wof:placetype":"venue"
},
  "geometry": {"coordinates":[-101.799049377,49.1772232056],"type":"Point"}
}