{
  "type": "Feature",
  "properties": {
    "addr:full":"Dickenson Rd Balmertown ON P0V 1C0",
    "addr:postcode":"p0v 1c0",
    "addr:street":"Dickenson Rd",
    "iso:country":"CA",
    "sg:address":"Dickenson Rd",
    "sg:city":"Balmertown",
    "sg:classifiers":[
        {
            "category":"Mining & Drilling",
            "type":"Manufacturing & Wholesale Goods"
        }
    ],
    "sg:phone":"+1 807 735 2077",
    "sg:postcode":"P0V 1C0",
    "sg:province":"ON",
    "sg:tags":[
        "company"
    ],
    "wof:name":"Goldcorp Inc",
    "wof:placetype":"venue"
},
  "geometry": {"coordinates":[-93.7379455566,51.0584716797],"type":"Point"}
}