{
  "type": "Feature",
  "properties": {
    "addr:full":"15537 Boul Gouin O Sainte-Genevieve QC H9H 1C2",
    "addr:housenumber":"15537",
    "addr:postcode":"h9h 1c2",
    "addr:street":"Boul Gouin O Sainte-Genevieve",
    "iso:country":"CA",
    "sg:address":"15537 Boul Gouin O",
    "sg:city":"Sainte-Genevieve",
    "sg:classifiers":[
        {
            "category":"Shopping",
            "subcategory":"Used Merchandise",
            "type":"Retail Goods"
        }
    ],
    "sg:phone":"+1 514 620 3653",
    "sg:postcode":"H9H 1C2",
    "sg:province":"QC",
    "sg:tags":[
        "antique"
    ],
    "wof:name":"Penela Enr",
    "wof:placetype":"venue"
},
  "geometry": {"coordinates":[-73.867119,45.483894],"type":"Point"}
}