{
  "type": "Feature",
  "properties": {
    "addr:full":"1725 16th Ave Richmond Hill ON L4B 4C6",
    "addr:housenumber":"1725",
    "addr:postcode":"l4b 4c6",
    "addr:street":"16Th Ave",
    "iso:country":"CA",
    "sg:address":"1725 16th Ave",
    "sg:city":"Richmond Hill",
    "sg:classifiers":[
        {
            "category":"Wholesale",
            "subcategory":"Apparel",
            "type":"Manufacturing & Wholesale Goods"
        }
    ],
    "sg:phone":"+1 905 763 4400",
    "sg:postcode":"L4B 4C6",
    "sg:province":"ON",
    "sg:tags":[
        "clothing"
    ],
    "wof:name":"Levi Strauss & CO Inc",
    "wof:placetype":"venue"
},
  "geometry": {"coordinates":[-79.38033299999999,43.863865],"type":"Point"}
}