{
  "type": "Feature",
  "properties": {
    "addr:full":"630 4 Ave SW #300 Calgary AB T2P 0J9",
    "addr:housenumber":"630",
    "addr:postcode":"t2p 0j9",
    "addr:street":"4 Ave Sw # 300",
    "iso:country":"CA",
    "sg:address":"630 4 Ave SW #300",
    "sg:city":"Calgary",
    "sg:classifiers":[
        {
            "category":"Professional",
            "type":"Services"
        }
    ],
    "sg:phone":"+1 403 263 2915",
    "sg:postcode":"T2P 0J9",
    "sg:province":"AB",
    "sg:tags":[
        "computer",
        "establishment",
        "software"
    ],
    "wof:name":"Peloton Computer Enterprises",
    "wof:placetype":"venue"
},
  "geometry": {"coordinates":[-114.074394,51.049763],"type":"Point"}
}