{
  "type": "Feature",
  "properties": {
    "addr:full":"Montreal QC H3H 2B8",
    "addr:postcode":"h3h 2b8",
    "iso:country":"CA",
    "sg:city":"Montreal",
    "sg:classifiers":[
        {
            "category":"Communications",
            "subcategory":"Film & Video Production",
            "type":"Services"
        }
    ],
    "sg:phone":"+1 514 939 1442",
    "sg:postcode":"H3H 2B8",
    "sg:province":"QC",
    "sg:tags":[
        "motion",
        "picture",
        "casting"
    ],
    "wof:name":"Ginette D'Amico Casting",
    "wof:placetype":"venue"
},
  "geometry": {"coordinates":[-73.579971,45.491203],"type":"Point"}
}