{
  "type": "Feature",
  "properties": {
    "iso:country":"CA",
    "sg:address":"105 Rue L'Ecuyer",
    "sg:city":"Repentigny",
    "sg:classifiers":[
        {
            "category":"Taxi",
            "type":"Transportation"
        }
    ],
    "sg:phone":"+1 450 581 2220",
    "sg:postcode":"J6A 8C5",
    "sg:province":"QC",
    "sg:tags":[
        "taxicab"
    ],
    "wof:name":"Taxi Rive-Nord",
    "wof:placetype":"venue"
},
  "geometry": {"coordinates":[-73.444061,45.75544],"type":"Point"}
}