{
  "type": "Feature",
  "properties": {
    "addr:full":"708 Rideau St N Kemptville ON K0G 1J0",
    "addr:housenumber":"708",
    "addr:postcode":"k0g 1j0",
    "addr:street":"Rideau St N",
    "iso:country":"CA",
    "sg:address":"708 Rideau St N",
    "sg:city":"Kemptville",
    "sg:classifiers":[
        {
            "category":"Shopping",
            "subcategory":"Florist",
            "type":"Retail Goods"
        }
    ],
    "sg:phone":"+1 613 258 7454",
    "sg:postcode":"K0G 1J0",
    "sg:province":"ON",
    "wof:name":"Kemptville Florist",
    "wof:placetype":"venue"
},
  "geometry": {"coordinates":[-75.6525344849,45.0207290649],"type":"Point"}
}