{
  "type": "Feature",
  "properties": {
    "iso:country":"CA",
    "sg:address":"450 Beta St",
    "sg:city":"Victoria",
    "sg:classifiers":[
        {
            "category":"Restaurant",
            "type":"Food & Drink"
        }
    ],
    "sg:phone":"+1 250 381 6646",
    "sg:postcode":"V8Z 1B1",
    "sg:province":"BC",
    "sg:tags":[
        "caterer"
    ],
    "wof:name":"Casa Antiga Cafe",
    "wof:placetype":"venue"
},
  "geometry": {"coordinates":[-123.375953674,48.4463233948],"type":"Point"}
}