{
  "type": "Feature",
  "properties": {
    "addr:full":"PO Box 422 Temagami ON P0H 2H0",
    "addr:housenumber":"po",
    "addr:postcode":"p0h 2h0",
    "addr:street":"Box 422 Temagami",
    "iso:country":"CA",
    "sg:address":"PO Box 422",
    "sg:city":"Temagami",
    "sg:classifiers":[
        {
            "category":"Home & Garden",
            "subcategory":"Furniture",
            "type":"Retail Goods"
        }
    ],
    "sg:phone":"+1 705 569 2700",
    "sg:postcode":"P0H 2H0",
    "sg:province":"ON",
    "wof:name":"Temagami Log Furniture CO",
    "wof:placetype":"venue"
},
  "geometry": {"coordinates":[-79.789551,47.065605],"type":"Point"}
}