{
  "type": "Feature",
  "properties": {
    "addr:full":"370 William St Wiarton ON N0H 2T0",
    "addr:housenumber":"370",
    "addr:postcode":"n0h 2t0",
    "addr:street":"William St",
    "iso:country":"CA",
    "sg:address":"370 William St",
    "sg:city":"Wiarton",
    "sg:classifiers":[
        {
            "category":"Food & Beverages",
            "subcategory":"Groceries & Convenience Stores",
            "type":"Retail Goods"
        }
    ],
    "sg:phone":"+1 519 534 0760",
    "sg:postcode":"N0H 2T0",
    "sg:province":"ON",
    "sg:tags":[
        "grocer"
    ],
    "wof:name":"Solway's Food Market",
    "wof:placetype":"venue"
},
  "geometry": {"coordinates":[-81.139259,44.743893],"type":"Point"}
}