{
  "type": "Feature",
  "properties": {
    "addr:full":"7 Rue Buttonwood Dollard-Des-Ormeaux QC H9A 2N1",
    "addr:housenumber":"7",
    "addr:postcode":"h9a 2n1",
    "addr:street":"Rue Buttonwood",
    "iso:country":"CA",
    "sg:address":"7 Rue Buttonwood",
    "sg:city":"Dollard-Des-Ormeaux",
    "sg:classifiers":[
        {
            "category":"Real Estate",
            "subcategory":"Real Estate Agent",
            "type":"Services"
        }
    ],
    "sg:phone":"+1 514 684 8441",
    "sg:postcode":"H9A 2N1",
    "sg:province":"QC",
    "sg:tags":[
        "agency",
        "rental"
    ],
    "wof:name":"Equipements Luri Inc",
    "wof:placetype":"venue"
},
  "geometry": {"coordinates":[-73.82912399999999,45.495712],"type":"Point"}
}