{
  "type": "Feature",
  "properties": {
    "addr:full":"Chilliwack BC V2P 4H7",
    "addr:postcode":"v2p 4h7",
    "iso:country":"CA",
    "sg:city":"Chilliwack",
    "sg:classifiers":[
        {
            "category":"Health Services",
            "subcategory":"Doctor",
            "type":"Services"
        }
    ],
    "sg:phone":"+1 604 795 5800",
    "sg:postcode":"V2P 4H7",
    "sg:province":"BC",
    "sg:tags":[
        "physician",
        "surgeon"
    ],
    "wof:name":"John C Chow Inc",
    "wof:placetype":"venue"
},
  "geometry": {"coordinates":[-121.96071600000001,49.167915],"type":"Point"}
}