{
  "type": "Feature",
  "properties": {
    "addr:full":"84 Royal Rd Guelph ON N1H 1G3",
    "addr:housenumber":"84",
    "addr:postcode":"n1h 1g3",
    "addr:street":"Royal Rd",
    "iso:country":"CA",
    "sg:address":"84 Royal Rd",
    "sg:city":"Guelph",
    "sg:classifiers":[
        {
            "category":"Autos & Motor Vehicles",
            "subcategory":"Auto Supplies",
            "type":"Retail Goods"
        }
    ],
    "sg:phone":"+1 519 823 1092",
    "sg:postcode":"N1H 1G3",
    "sg:province":"ON",
    "sg:tags":[
        "filter",
        "gas"
    ],
    "wof:name":"Maddocks Engineering Ltd",
    "wof:placetype":"venue"
},
  "geometry": {"coordinates":[-80.3006744385,43.5443840027],"type":"Point"}
}