{
  "type": "Feature",
  "properties": {
    "addr:full":"39 Chambers St Smiths Falls ON K7A 2Y3",
    "addr:housenumber":"39",
    "addr:postcode":"k7a 2y3",
    "addr:street":"Chambers St",
    "iso:country":"CA",
    "sg:address":"39 Chambers St",
    "sg:city":"Smiths Falls",
    "sg:classifiers":[
        {
            "category":"Sports & Exercise",
            "subcategory":"Bowling",
            "type":"Entertainment"
        }
    ],
    "sg:phone":"+1 613 283 6200",
    "sg:postcode":"K7A 2Y3",
    "sg:province":"ON",
    "sg:tags":[
        "center"
    ],
    "wof:name":"Smiths Falls Gratton Lanes",
    "wof:placetype":"venue"
},
  "geometry": {"coordinates":[-76.01907300000001,44.898724],"type":"Point"}
}