{
  "type": "Feature",
  "properties": {
    "addr:full":"Saint-Alexis-Des-Monts QC J0K 1V0",
    "addr:postcode":"j0k 1v0",
    "iso:country":"CA",
    "sg:city":"Saint-Alexis-Des-Monts",
    "sg:classifiers":[
        {
            "category":"Personal",
            "subcategory":"Beauty Salon",
            "type":"Services"
        }
    ],
    "sg:phone":"+1 819 265 2720",
    "sg:postcode":"J0K 1V0",
    "sg:province":"QC",
    "wof:name":"Salon Eve",
    "wof:placetype":"venue"
},
  "geometry": {"coordinates":[-73.14386,46.461151],"type":"Point"}
}