{
  "type": "Feature",
  "properties": {
    "addr:full":"Montreal QC H2J 1E6",
    "addr:postcode":"h2j 1e6",
    "iso:country":"CA",
    "sg:city":"Montreal",
    "sg:classifiers":[
        {
            "category":"Travel",
            "subcategory":"Travel Agent",
            "type":"Entertainment"
        }
    ],
    "sg:phone":"+1 514 844 1210",
    "sg:postcode":"H2J 1E6",
    "sg:province":"QC",
    "sg:tags":[
        "agency",
        "bureau"
    ],
    "wof:name":"Services DE Voyages Inter",
    "wof:placetype":"venue"
},
  "geometry": {"coordinates":[-73.5926742554,45.523475647],"type":"Point"}
}