{
  "type": "Feature",
  "properties": {
    "addr:full":"Oakville ON L6L 6M5",
    "addr:postcode":"l6l 6m5",
    "iso:country":"CA",
    "sg:city":"Oakville",
    "sg:classifiers":[
        {
            "category":"Professional",
            "subcategory":"Computer Services",
            "type":"Services"
        }
    ],
    "sg:phone":"+1 905 847 2996",
    "sg:postcode":"L6L 6M5",
    "sg:province":"ON",
    "sg:tags":[
        "consultant"
    ],
    "wof:name":"Integrity Technology Conslnts",
    "wof:placetype":"venue"
},
  "geometry": {"coordinates":[-79.73474899999999,43.41275],"type":"Point"}
}