{
  "type": "Feature",
  "properties": {
    "addr:full":"117 Main St N Dauphin MB R7N 1C1",
    "addr:housenumber":"117",
    "addr:postcode":"r7n 1c1",
    "addr:street":"Main St N Dauphin",
    "iso:country":"CA",
    "sg:address":"117 Main St N",
    "sg:city":"Dauphin",
    "sg:classifiers":[
        {
            "category":"Professional",
            "subcategory":"Business Services",
            "type":"Services"
        }
    ],
    "sg:phone":"+1 204 638 4001",
    "sg:postcode":"R7N 1C1",
    "sg:province":"MB",
    "sg:tags":[
        "embroidery"
    ],
    "wof:name":"Bay's & the Denim Wall",
    "wof:placetype":"venue"
},
  "geometry": {"coordinates":[-100.04986599999999,51.149918],"type":"Point"}
}