{
  "type": "Feature",
  "properties": {
    "addr:full":"725 Warden Ave Scarborough ON M1L 4R7",
    "addr:housenumber":"725",
    "addr:postcode":"m1l 4r7",
    "addr:street":"Warden Ave",
    "iso:country":"CA",
    "sg:address":"725 Warden Ave",
    "sg:city":"Scarborough",
    "sg:classifiers":[
        {
            "category":"Food & Beverages",
            "subcategory":"Bakery",
            "type":"Retail Goods"
        }
    ],
    "sg:phone":"+1 416 751 6616",
    "sg:postcode":"M1L 4R7",
    "sg:province":"ON",
    "sg:tags":[
        "doughnut"
    ],
    "wof:name":"Tim Hortons",
    "wof:placetype":"venue"
},
  "geometry": {"coordinates":[-79.281128,43.712822],"type":"Point"}
}