{
  "type": "Feature",
  "properties": {
    "addr:full":"2801 13 Ave SE # A Medicine Hat AB T1A 3R1",
    "addr:housenumber":"2801",
    "addr:postcode":"t1a 3r1",
    "addr:street":"13 Ave Se # A",
    "iso:country":"CA",
    "sg:address":"2801 13 Ave SE # A",
    "sg:city":"Medicine Hat",
    "sg:classifiers":[
        {
            "category":"Personal",
            "subcategory":"Beauty Salon",
            "type":"Services"
        }
    ],
    "sg:phone":"+1 403 528 3113",
    "sg:postcode":"T1A 3R1",
    "sg:province":"AB",
    "wof:name":"Hair Village",
    "wof:placetype":"venue"
},
  "geometry": {"coordinates":[-110.664154,50.01297],"type":"Point"}
}