{
  "type": "Feature",
  "properties": {
    "addr:full":"2065 Rue Jacques-Cartier Terrebonne QC J6X 2T2",
    "addr:housenumber":"2065",
    "addr:postcode":"j6x 2t2",
    "addr:street":"Rue Jacques-Cartier",
    "iso:country":"CA",
    "sg:address":"2065 Rue Jacques-Cartier",
    "sg:city":"Terrebonne",
    "sg:classifiers":[
        {
            "category":"Organizations",
            "subcategory":"Religious Organization",
            "type":"Services"
        }
    ],
    "sg:phone":"+1 450 471 9412",
    "sg:postcode":"J6X 2T2",
    "sg:province":"QC",
    "sg:tags":[
        "church"
    ],
    "wof:name":"Paroisses Catholiques-Parishes",
    "wof:placetype":"venue"
},
  "geometry": {"coordinates":[-73.6676101685,45.7238960266],"type":"Point"}
}