{
  "type": "Feature",
  "properties": {
    "addr:full":"8 King St E Toronto ON M5C 1B5",
    "addr:housenumber":"8",
    "addr:postcode":"m5c 1b5",
    "addr:street":"King St E",
    "iso:country":"CA",
    "sg:address":"8 King St E",
    "sg:city":"Toronto",
    "sg:classifiers":[
        {
            "category":"Banks & Credit Unions",
            "subcategory":"Investment Brokerage",
            "type":"Services"
        }
    ],
    "sg:phone":"+1 416 364 8323",
    "sg:postcode":"M5C 1B5",
    "sg:province":"ON",
    "sg:tags":[
        "consultant",
        "planning",
        "financial"
    ],
    "wof:name":"Simon, Robert P",
    "wof:placetype":"venue"
},
  "geometry": {"coordinates":[-79.3775939941,43.6493225098],"type":"Point"}
}