{
  "type": "Feature",
  "properties": {
    "addr:full":"149 3rd St Cochrane ON P0L 1C0",
    "addr:housenumber":"149",
    "addr:postcode":"p0l 1c0",
    "addr:street":"3Rd St",
    "iso:country":"CA",
    "sg:address":"149 3rd St",
    "sg:city":"Cochrane",
    "sg:classifiers":[
        {
            "category":"Retail",
            "subcategory":"Funeral Services",
            "type":"Services"
        }
    ],
    "sg:phone":"+1 705 272 3239",
    "sg:postcode":"P0L 1C0",
    "sg:province":"ON",
    "sg:tags":[
        "director"
    ],
    "wof:name":"Irvine & Irvine Funeral Drctrs",
    "wof:placetype":"venue"
},
  "geometry": {"coordinates":[-81.0258636475,49.0620918274],"type":"Point"}
}