{
  "type": "Feature",
  "properties": {
    "iso:country":"CA",
    "sg:address":"2155 Ch Sainte-Foy",
    "sg:city":"Sainte-Foy",
    "sg:classifiers":[
        {
            "category":"Food & Beverages",
            "subcategory":"Groceries & Convenience Stores",
            "type":"Retail Goods"
        }
    ],
    "sg:phone":"+1 418 683 9705",
    "sg:postcode":"G1V 1S1",
    "sg:province":"QC",
    "wof:name":"Provi-Soir Couche-Tard",
    "wof:placetype":"venue"
},
  "geometry": {"coordinates":[-71.2917633057,46.7692108154],"type":"Point"}
}