{
  "type": "Feature",
  "properties": {
    "iso:country":"CA",
    "sg:city":"Richmond Hill",
    "sg:classifiers":[
        {
            "category":"Professional",
            "subcategory":"Engineering",
            "type":"Services"
        }
    ],
    "sg:phone":"+1 905 764 9380",
    "sg:postcode":"L4B 3N4",
    "sg:province":"ON",
    "sg:tags":[
        "engineer"
    ],
    "wof:name":"Senes Consultants Ltd",
    "wof:placetype":"venue"
},
  "geometry": {"coordinates":[-79.3881149292,43.8578872681],"type":"Point"}
}