{
  "type": "Feature",
  "properties": {
    "addr:full":"220 Yonge St Toronto ON M5B 2H1",
    "addr:housenumber":"220",
    "addr:postcode":"m5b 2h1",
    "addr:street":"Yonge St",
    "iso:country":"CA",
    "sg:address":"220 Yonge St",
    "sg:city":"Toronto",
    "sg:classifiers":[
        {
            "category":"Shopping",
            "subcategory":"Clothing, Apparel, & Fashions",
            "type":"Retail Goods"
        }
    ],
    "sg:phone":"+1 416 593 2551",
    "sg:postcode":"M5B 2H1",
    "sg:province":"ON",
    "wof:name":"Old Navy",
    "wof:placetype":"venue"
},
  "geometry": {"coordinates":[-79.37980651860001,43.6532020569],"type":"Point"}
}