{
  "type": "Feature",
  "properties": {
    "addr:full":"Bridgewater Hwy Block House NS B0J 1E0",
    "addr:postcode":"ns b0j 1e0",
    "addr:street":"Bridgewater Hwy Block",
    "iso:country":"CA",
    "sg:address":"Bridgewater Hwy",
    "sg:city":"Block House",
    "sg:classifiers":[
        {
            "category":"Building & Trades",
            "subcategory":"Construction",
            "type":"Services"
        }
    ],
    "sg:phone":"+1 902 624 8781",
    "sg:postcode":"B0J 1E0",
    "sg:province":"NS",
    "sg:tags":[
        "painter"
    ],
    "wof:name":"Young & Mader Painting",
    "wof:placetype":"venue"
},
  "geometry": {"coordinates":[-64.523033,44.380489],"type":"Point"}
}