{
  "type": "Feature",
  "properties": {
    "addr:full":"68 Main St S Waterford ON N0E 1Y0",
    "addr:housenumber":"68",
    "addr:postcode":"n0e 1y0",
    "addr:street":"Main St S",
    "iso:country":"CA",
    "sg:address":"68 Main St S",
    "sg:city":"Waterford",
    "sg:classifiers":[
        {
            "category":"Organizations",
            "subcategory":"Religious Organization",
            "type":"Services"
        }
    ],
    "sg:phone":"+1 519 443 7351",
    "sg:postcode":"N0E 1Y0",
    "sg:province":"ON",
    "sg:tags":[
        "church"
    ],
    "wof:name":"Waterford Baptist Church",
    "wof:placetype":"venue"
},
  "geometry": {"coordinates":[-80.290314,42.9333],"type":"Point"}
}