{
  "type": "Feature",
  "properties": {
    "iso:country":"CA",
    "sg:city":"Kitchener",
    "sg:classifiers":[
        {
            "category":"Shopping",
            "subcategory":"Shoes",
            "type":"Retail Goods"
        }
    ],
    "sg:phone":"+1 519 571 1891",
    "sg:postcode":"N2H 6M8",
    "sg:province":"ON",
    "wof:name":"Athletic Direct",
    "wof:placetype":"venue"
},
  "geometry": {"coordinates":[-80.487274,43.449753],"type":"Point"}
}