{
  "type": "Feature",
  "properties": {
    "addr:full":"490 Rue DE L'Argon Charlesbourg QC G2N 2C9",
    "addr:housenumber":"490",
    "addr:postcode":"g2n 2c9",
    "addr:street":"Rue De L'Argon",
    "iso:country":"CA",
    "sg:address":"490 Rue DE L'Argon",
    "sg:city":"Charlesbourg",
    "sg:classifiers":[
        {
            "category":"Manufacturing",
            "subcategory":"Metals",
            "type":"Manufacturing & Wholesale Goods"
        }
    ],
    "sg:phone":"+1 418 849 8095",
    "sg:postcode":"G2N 2C9",
    "sg:province":"QC",
    "sg:tags":[
        "coal",
        "stove"
    ],
    "wof:name":"J A Roby Inc",
    "wof:placetype":"venue"
},
  "geometry": {"coordinates":[-71.317855835,46.8936691284],"type":"Point"}
}