{
  "type": "Feature",
  "properties": {
    "iso:country":"CA",
    "sg:city":"Newmarket",
    "sg:classifiers":[
        {
            "category":"Personal",
            "subcategory":"Beauty Salon",
            "type":"Services"
        }
    ],
    "sg:phone":"+1 905 836 7880",
    "sg:postcode":"L3Y 7C1",
    "sg:province":"ON",
    "sg:tags":[
        "manicuring"
    ],
    "wof:name":"Crystal Nails Salon",
    "wof:placetype":"venue"
},
  "geometry": {"coordinates":[-79.48138427729999,44.0597305298],"type":"Point"}
}