{
  "type": "Feature",
  "properties": {
    "addr:full":"2121 Caroline St Burlington ON L7R 1L7",
    "addr:housenumber":"2121",
    "addr:postcode":"l7r 1l7",
    "addr:street":"Caroline St",
    "iso:country":"CA",
    "sg:address":"2121 Caroline St",
    "sg:city":"Burlington",
    "sg:classifiers":[
        {
            "category":"Organizations",
            "subcategory":"Religious Organization",
            "type":"Services"
        }
    ],
    "sg:phone":"+1 905 634 1849",
    "sg:postcode":"L7R 1L7",
    "sg:province":"ON",
    "sg:tags":[
        "church"
    ],
    "wof:name":"Wellington Square United Chr",
    "wof:placetype":"venue"
},
  "geometry": {"coordinates":[-79.7966537476,43.3308448792],"type":"Point"}
}