{
  "type": "Feature",
  "properties": {
    "addr:full":"20 3 St S # 306 Lethbridge AB T1J 4P1",
    "addr:postcode":"t1j 4p1",
    "addr:street":"20 3 St S # 306",
    "iso:country":"CA",
    "sg:address":"20 3 St S # 306",
    "sg:city":"Lethbridge",
    "sg:classifiers":[
        {
            "category":"Real Estate",
            "subcategory":"Real Estate Operator",
            "type":"Services"
        }
    ],
    "sg:phone":"+1 403 327 0725",
    "sg:postcode":"T1J 4P1",
    "sg:province":"AB",
    "sg:tags":[
        "condominium"
    ],
    "wof:name":"Grandview Village",
    "wof:placetype":"venue"
},
  "geometry": {"coordinates":[-112.84384900000001,49.69746],"type":"Point"}
}