{
  "type": "Feature",
  "properties": {
    "addr:full":"152 S Alberni Hwy Parksville BC V9P 2G5",
    "addr:housenumber":"152",
    "addr:postcode":"v9p 2g5",
    "addr:street":"S Alberni Hwy",
    "iso:country":"CA",
    "sg:address":"152 S Alberni Hwy",
    "sg:city":"Parksville",
    "sg:classifiers":[
        {
            "category":"Banks & Credit Unions",
            "subcategory":"Investment Brokerage",
            "type":"Services"
        }
    ],
    "sg:phone":"+1 250 248 2104",
    "sg:postcode":"V9P 2G5",
    "sg:province":"BC",
    "wof:name":"Rbc Dominion Securities Inc",
    "wof:placetype":"venue"
},
  "geometry": {"coordinates":[-124.31353799999999,49.319241],"type":"Point"}
}