{
  "type": "Feature",
  "properties": {
    "addr:full":"Surrey BC V3W 3K3",
    "addr:postcode":"v3w 3k3",
    "iso:country":"CA",
    "sg:city":"Surrey",
    "sg:classifiers":[
        {
            "category":"Autos & Motor Vehicles",
            "subcategory":"Auto Supplies",
            "type":"Retail Goods"
        }
    ],
    "sg:phone":"+1 604 572 5585",
    "sg:postcode":"V3W 3K3",
    "sg:province":"BC",
    "sg:tags":[
        "automobile",
        "stereo",
        "appliance",
        "radio"
    ],
    "wof:name":"Alpha Audio-Video Svc Ltd",
    "wof:placetype":"venue"
},
  "geometry": {"coordinates":[-122.858718872,49.1624946594],"type":"Point"}
}