{
  "type": "Feature",
  "properties": {
    "addr:full":"Fort Mcmurray AB T9H 4B1",
    "addr:postcode":"t9h 4b1",
    "iso:country":"CA",
    "sg:city":"Fort Mcmurray",
    "sg:classifiers":[
        {
            "category":"Wholesale",
            "subcategory":"Electrical",
            "type":"Manufacturing & Wholesale Goods"
        }
    ],
    "sg:phone":"+1 780 743 8342",
    "sg:postcode":"T9H 4B1",
    "sg:province":"AB",
    "sg:tags":[
        "equipment",
        "electric",
        "supply"
    ],
    "wof:name":"Gescan Division-Sonepar Distr",
    "wof:placetype":"venue"
},
  "geometry": {"coordinates":[-111.344376,56.66785],"type":"Point"}
}