{
  "type": "Feature",
  "properties": {
    "addr:full":"Calgary AB T2K 5X8",
    "addr:postcode":"t2k 5x8",
    "iso:country":"CA",
    "sg:city":"Calgary",
    "sg:classifiers":[
        {
            "category":"Restaurant",
            "type":"Food & Drink"
        }
    ],
    "sg:phone":"+1 403 295 8797",
    "sg:postcode":"T2K 5X8",
    "sg:province":"AB",
    "wof:name":"Mr Sub",
    "wof:placetype":"venue"
},
  "geometry": {"coordinates":[-114.053604126,51.0963516235],"type":"Point"}
}