{
  "type": "Feature",
  "properties": {
    "addr:full":"279 Covehaven View NE Calgary AB T3K 5S4",
    "addr:housenumber":"279",
    "addr:postcode":"t3k 5s4",
    "addr:street":"Covehaven View Ne",
    "iso:country":"CA",
    "sg:address":"279 Covehaven View NE",
    "sg:city":"Calgary",
    "sg:classifiers":[
        {
            "category":"Real Estate",
            "subcategory":"Real Estate Agent",
            "type":"Services"
        }
    ],
    "sg:phone":"+1 403 289 1598",
    "sg:postcode":"T3K 5S4",
    "sg:province":"AB",
    "wof:name":"Edgepark Realty & Management",
    "wof:placetype":"venue"
},
  "geometry": {"coordinates":[-114.05796051,51.1632919312],"type":"Point"}
}