{
  "type": "Feature",
  "properties": {
    "addr:full":"Abbotsford BC V2T 6J6",
    "addr:postcode":"v2t 6j6",
    "iso:country":"CA",
    "sg:city":"Abbotsford",
    "sg:classifiers":[
        {
            "category":"Manufacturing",
            "subcategory":"Glass & Minerals",
            "type":"Manufacturing & Wholesale Goods"
        }
    ],
    "sg:phone":"+1 604 850 6988",
    "sg:postcode":"V2T 6J6",
    "sg:province":"BC",
    "sg:tags":[
        "mirror"
    ],
    "wof:name":"Nostalgia",
    "wof:placetype":"venue"
},
  "geometry": {"coordinates":[-122.367401,49.044094],"type":"Point"}
}