{
  "type": "Feature",
  "properties": {
    "addr:full":"4934 49 Ave Vermilion AB T9X 1C6",
    "addr:housenumber":"4934",
    "addr:postcode":"t9x 1c6",
    "addr:street":"49 Ave",
    "iso:country":"CA",
    "sg:address":"4934 49 Ave",
    "sg:city":"Vermilion",
    "sg:classifiers":[
        {
            "category":"Retail",
            "subcategory":"Laundry & Dry Cleaning",
            "type":"Services"
        }
    ],
    "sg:phone":"+1 780 853 5153",
    "sg:postcode":"T9X 1C6",
    "sg:province":"AB",
    "sg:tags":[
        "cleaners"
    ],
    "wof:name":"Sam's Cleaners",
    "wof:placetype":"venue"
},
  "geometry": {"coordinates":[-110.851311,53.353264],"type":"Point"}
}