{
  "type": "Feature",
  "properties": {
    "iso:country":"CA",
    "sg:address":"69 Cow Bay Rd # 1",
    "sg:city":"Eastern Passage",
    "sg:classifiers":[
        {
            "category":"Food & Beverages",
            "subcategory":"Liquor & Beverages",
            "type":"Retail Goods"
        }
    ],
    "sg:phone":"+1 902 465 8175",
    "sg:postcode":"B3G 1A2",
    "sg:province":"NS",
    "sg:tags":[
        "store"
    ],
    "wof:name":"Nova Scotia Liquor Store",
    "wof:placetype":"venue"
},
  "geometry": {"coordinates":[-63.4902420044,44.6123199463],"type":"Point"}
}