{
  "type": "Feature",
  "properties": {
    "addr:full":"Thunder Bay ON P7C 3P1",
    "addr:postcode":"p7c 3p1",
    "iso:country":"CA",
    "sg:city":"Thunder Bay",
    "sg:classifiers":[
        {
            "category":"Health Services",
            "subcategory":"Doctor",
            "type":"Services"
        }
    ],
    "sg:phone":"+1 807 623 2900",
    "sg:postcode":"P7C 3P1",
    "sg:province":"ON",
    "sg:tags":[
        "dentist"
    ],
    "wof:name":"Mercer, Reginald G DDS",
    "wof:placetype":"venue"
},
  "geometry": {"coordinates":[-89.24528503419999,48.3847236633],"type":"Point"}
}