{
  "type": "Feature",
  "properties": {
    "addr:full":"Edmonton AB T5K 2A2",
    "addr:postcode":"t5k 2a2",
    "iso:country":"CA",
    "sg:city":"Edmonton",
    "sg:classifiers":[
        {
            "category":"Health Services",
            "subcategory":"Health Practitioner",
            "type":"Services"
        }
    ],
    "sg:phone":"+1 780 488 8582",
    "sg:postcode":"T5K 2A2",
    "sg:province":"AB",
    "sg:tags":[
        "therapist",
        "physical"
    ],
    "wof:name":"Morrow, Brent",
    "wof:placetype":"venue"
},
  "geometry": {"coordinates":[-113.528412,53.542053],"type":"Point"}
}