{
  "type": "Feature",
  "properties": {
    "addr:full":"4995 Boul Leger Montreal-Nord QC H1G 1J7",
    "addr:housenumber":"4995",
    "addr:postcode":"h1g 1j7",
    "addr:street":"Boul Leger",
    "iso:country":"CA",
    "sg:address":"4995 Boul Leger",
    "sg:city":"Montreal-Nord",
    "sg:classifiers":[
        {
            "category":"Personal",
            "subcategory":"Tanning Parlor",
            "type":"Services"
        }
    ],
    "sg:phone":"+1 514 955 5353",
    "sg:postcode":"H1G 1J7",
    "sg:province":"QC",
    "sg:tags":[
        "salon"
    ],
    "wof:name":"Bronzage Oasis Soleil Enr",
    "wof:placetype":"venue"
},
  "geometry": {"coordinates":[-73.635895,45.605812],"type":"Point"}
}