{
  "type": "Feature",
  "properties": {
    "iso:country":"CA",
    "sg:city":"Edmonton",
    "sg:classifiers":[
        {
            "category":"Manufacturing",
            "subcategory":"Printing",
            "type":"Manufacturing & Wholesale Goods"
        }
    ],
    "sg:phone":"+1 780 429 1073",
    "sg:postcode":"T5H 2X6",
    "sg:province":"AB",
    "sg:tags":[
        "publisher"
    ],
    "wof:name":"Armadale Publications Inc",
    "wof:placetype":"venue"
},
  "geometry": {"coordinates":[-113.503044,53.548702],"type":"Point"}
}