{
  "type": "Feature",
  "properties": {
    "addr:full":"119 Talbot St E Aylmer ON N5H 1H3",
    "addr:housenumber":"119",
    "addr:postcode":"n5h 1h3",
    "addr:street":"Talbot St E",
    "iso:country":"CA",
    "sg:address":"119 Talbot St E",
    "sg:city":"Aylmer",
    "sg:classifiers":[
        {
            "category":"Retail",
            "subcategory":"Funeral Services",
            "type":"Services"
        }
    ],
    "sg:phone":"+1 519 773 8400",
    "sg:postcode":"N5H 1H3",
    "sg:province":"ON",
    "sg:tags":[
        "director"
    ],
    "wof:name":"H A Kebbel Funeral Home Ltd",
    "wof:placetype":"venue"
},
  "geometry": {"coordinates":[-80.980644,42.773106],"type":"Point"}
}