{
  "type": "Feature",
  "properties": {
    "addr:full":"120 Lower Ganges Rd Salt Spring Island BC V8K 2S8",
    "addr:housenumber":"120",
    "addr:postcode":"v8k 2s8",
    "addr:street":"Lower Ganges Rd",
    "iso:country":"CA",
    "sg:address":"120 Lower Ganges Rd",
    "sg:city":"Salt Spring Island",
    "sg:classifiers":[
        {
            "category":"Travel",
            "subcategory":"Travel Agent",
            "type":"Entertainment"
        }
    ],
    "sg:phone":"+1 250 537 5523",
    "sg:postcode":"V8K 2S8",
    "sg:province":"BC",
    "sg:tags":[
        "agency",
        "bureau"
    ],
    "wof:name":"Uniglobe Pacific Travel",
    "wof:placetype":"venue"
},
  "geometry": {"coordinates":[-123.500046,48.853127],"type":"Point"}
}