{
  "type": "Feature",
  "properties": {
    "addr:full":"531 Rue Papineau Boisbriand QC J7G 2B7",
    "addr:housenumber":"531",
    "addr:postcode":"j7g 2b7",
    "addr:street":"Rue Papineau",
    "iso:country":"CA",
    "sg:address":"531 Rue Papineau",
    "sg:city":"Boisbriand",
    "sg:classifiers":[
        {
            "category":"Manufacturing",
            "subcategory":"Metals",
            "type":"Manufacturing & Wholesale Goods"
        }
    ],
    "sg:phone":"+1 450 430 3521",
    "sg:postcode":"J7G 2B7",
    "sg:province":"QC",
    "sg:tags":[
        "steel"
    ],
    "wof:name":"Aciers Modernes Inc",
    "wof:placetype":"venue"
},
  "geometry": {"coordinates":[-73.82540899999999,45.622704],"type":"Point"}
}