{
  "type": "Feature",
  "properties": {
    "addr:full":"641 Boul Samson Laval QC H7X 1J9",
    "addr:housenumber":"641",
    "addr:postcode":"h7x 1j9",
    "addr:street":"Boul Samson",
    "iso:country":"CA",
    "sg:address":"641 Boul Samson",
    "sg:city":"Laval",
    "sg:classifiers":[
        {
            "category":"Health Services",
            "subcategory":"Chiropractor",
            "type":"Services"
        }
    ],
    "sg:phone":"+1 450 689 7361",
    "sg:postcode":"H7X 1J9",
    "sg:province":"QC",
    "wof:name":"Centre Chiropratique Morin",
    "wof:placetype":"venue"
},
  "geometry": {"coordinates":[-73.81682600000001,45.524593],"type":"Point"}
}