{
  "type": "Feature",
  "properties": {
    "iso:country":"CA",
    "sg:address":"641 Boul Samson",
    "sg:city":"Laval",
    "sg:classifiers":[
        {
            "category":"Health Services",
            "subcategory":"Chiropractor",
            "type":"Services"
        }
    ],
    "sg:phone":"+1 450 689 7361",
    "sg:postcode":"H7X 1J9",
    "sg:province":"QC",
    "wof:name":"Centre Chiropratique Morin",
    "wof:placetype":"venue"
},
  "geometry": {"coordinates":[-73.816826,45.524593],"type":"Point"}
}