{
  "type": "Feature",
  "properties": {
    "addr:full":"171 Collier St Barrie ON L4M 1H6",
    "addr:housenumber":"171",
    "addr:postcode":"l4m 1h6",
    "addr:street":"Collier St",
    "iso:country":"CA",
    "sg:address":"171 Collier St",
    "sg:city":"Barrie",
    "sg:classifiers":[
        {
            "category":"Real Estate",
            "subcategory":"Real Estate Operator",
            "type":"Services"
        }
    ],
    "sg:phone":"+1 705 726 0300",
    "sg:postcode":"L4M 1H6",
    "sg:province":"ON",
    "sg:tags":[
        "apartment"
    ],
    "wof:name":"Mark English Properties",
    "wof:placetype":"venue"
},
  "geometry": {"coordinates":[-79.679725647,44.3908691406],"type":"Point"}
}