{
  "type": "Feature",
  "properties": {
    "addr:full":"1530 Markham Rd Scarborough ON M1B 3G4",
    "addr:housenumber":"1530",
    "addr:postcode":"m1b 3g4",
    "addr:street":"Markham Rd",
    "iso:country":"CA",
    "sg:address":"1530 Markham Rd",
    "sg:city":"Scarborough",
    "sg:classifiers":[
        {
            "category":"Government",
            "subcategory":"Office",
            "type":"Public Place"
        }
    ],
    "sg:phone":"+1 416 338 7720",
    "sg:postcode":"M1B 3G4",
    "sg:province":"ON",
    "sg:tags":[
        "village"
    ],
    "wof:name":"Toronto Court Svc",
    "wof:placetype":"venue"
},
  "geometry": {"coordinates":[-79.237404,43.789997],"type":"Point"}
}