{
  "type": "Feature",
  "properties": {
    "addr:full":"271 Garafraxa St Chatsworth ON N0H 1G0",
    "addr:housenumber":"271",
    "addr:postcode":"n0h 1g0",
    "addr:street":"Garafraxa St",
    "iso:country":"CA",
    "sg:address":"271 Garafraxa St",
    "sg:city":"Chatsworth",
    "sg:classifiers":[
        {
            "category":"Autos & Motor Vehicles",
            "subcategory":"Automobile Sales",
            "type":"Retail Goods"
        }
    ],
    "sg:phone":"+1 519 794 2765",
    "sg:postcode":"N0H 1G0",
    "sg:province":"ON",
    "sg:tags":[
        "car",
        "dealer"
    ],
    "wof:name":"Paul Evans Auto Sales",
    "wof:placetype":"venue"
},
  "geometry": {"coordinates":[-80.89671300000001,44.451843],"type":"Point"}
}