{
  "type": "Feature",
  "properties": {
    "addr:full":"433 St Mary's Rd Winnipeg MB R2M 3K7",
    "addr:housenumber":"433",
    "addr:postcode":"r2m 3k7",
    "addr:street":"St Mary'S Rd",
    "iso:country":"CA",
    "sg:address":"433 St Mary's Rd",
    "sg:city":"Winnipeg",
    "sg:classifiers":[
        {
            "category":"Wholesale",
            "subcategory":"Home Furnishings",
            "type":"Manufacturing & Wholesale Goods"
        }
    ],
    "sg:phone":"+1 204 235 1122",
    "sg:postcode":"R2M 3K7",
    "sg:province":"MB",
    "sg:tags":[
        "rug",
        "carpet"
    ],
    "wof:name":"E-Z Cut Inc",
    "wof:placetype":"venue"
},
  "geometry": {"coordinates":[-97.1489944458,49.8891448975],"type":"Point"}
}