{
  "type": "Feature",
  "properties": {
    "addr:full":"462 Birchmount Rd Scarborough ON M1K 1N8",
    "addr:housenumber":"462",
    "addr:postcode":"m1k 1n8",
    "addr:street":"Birchmount Rd",
    "iso:country":"CA",
    "sg:address":"462 Birchmount Rd",
    "sg:city":"Scarborough",
    "sg:classifiers":[
        {
            "category":"Government",
            "subcategory":"Post Office",
            "type":"Public Place"
        }
    ],
    "sg:phone":"+1 416 698 1616",
    "sg:postcode":"M1K 1N8",
    "sg:province":"ON",
    "wof:name":"Pharmasave",
    "wof:placetype":"venue"
},
  "geometry": {"coordinates":[-79.26838684080001,43.7072486877],"type":"Point"}
}