{
  "type": "Feature",
  "properties": {
    "addr:full":"300 Cabana Rd E Windsor ON N9G 1A3",
    "addr:housenumber":"300",
    "addr:postcode":"n9g 1a3",
    "addr:street":"Cabana Rd E",
    "iso:country":"CA",
    "sg:address":"300 Cabana Rd E",
    "sg:city":"Windsor",
    "sg:classifiers":[
        {
            "category":"Real Estate",
            "subcategory":"Real Estate Agent",
            "type":"Services"
        }
    ],
    "sg:phone":"+1 519 966 3750",
    "sg:postcode":"N9G 1A3",
    "sg:province":"ON",
    "wof:name":"Bob Pedler Real Estate Ltd",
    "wof:placetype":"venue"
},
  "geometry": {"coordinates":[-82.99743700000001,42.258518],"type":"Point"}
}