{
  "type": "Feature",
  "properties": {
    "iso:country":"CA",
    "sg:city":"Thunder Bay",
    "sg:classifiers":[
        {
            "category":"Health Services",
            "subcategory":"Health Practitioner",
            "type":"Services"
        }
    ],
    "sg:phone":"+1 807 344 0012",
    "sg:postcode":"P7B 1A6",
    "sg:province":"ON",
    "sg:tags":[
        "home",
        "nurse",
        "registry"
    ],
    "wof:name":"Victorian Order of Nurses",
    "wof:placetype":"venue"
},
  "geometry": {"coordinates":[-89.2205581665,48.4352722168],"type":"Point"}
}