{
  "type": "Feature",
  "properties": {
    "iso:country":"CA",
    "sg:city":"Montreal",
    "sg:classifiers":[
        {
            "category":"Health Services",
            "subcategory":"Doctor",
            "type":"Services"
        }
    ],
    "sg:phone":"+1 514 737 7751",
    "sg:postcode":"H3S 2C3",
    "sg:province":"QC",
    "sg:tags":[
        "physician",
        "surgeon"
    ],
    "wof:name":"Kiteala, John MD",
    "wof:placetype":"venue"
},
  "geometry": {"coordinates":[-73.626274,45.501068],"type":"Point"}
}