{
  "type": "Feature",
  "properties": {
    "addr:full":"2525 36 St NE Calgary AB T1Y 5T4",
    "addr:housenumber":"2525",
    "addr:postcode":"t1y 5t4",
    "addr:street":"36 St Ne",
    "iso:country":"CA",
    "sg:address":"2525 36 St NE",
    "sg:city":"Calgary",
    "sg:classifiers":[
        {
            "category":"Sports & Exercise",
            "subcategory":"Gym",
            "type":"Entertainment"
        }
    ],
    "sg:phone":"+1 403 285 5822",
    "sg:postcode":"T1Y 5T4",
    "sg:province":"AB",
    "sg:tags":[
        "club",
        "health",
        "studio",
        "gymnasium"
    ],
    "wof:name":"Exclusively Women's Fitness",
    "wof:placetype":"venue"
},
  "geometry": {"coordinates":[-113.982177734,51.0741271973],"type":"Point"}
}