{
  "type": "Feature",
  "properties": {
    "addr:full":"202 Churchill St Hudson Bay SK S0E 0Y0",
    "addr:housenumber":"202",
    "addr:postcode":"s0e 0y0",
    "addr:street":"Churchill St",
    "iso:country":"CA",
    "sg:address":"202 Churchill St",
    "sg:city":"Hudson Bay",
    "sg:classifiers":[
        {
            "category":"Home & Garden",
            "subcategory":"Hardware",
            "type":"Retail Goods"
        }
    ],
    "sg:phone":"+1 306 865 2401",
    "sg:postcode":"S0E 0Y0",
    "sg:province":"SK",
    "wof:name":"Mac Leods True Value Hardware",
    "wof:placetype":"venue"
},
  "geometry": {"coordinates":[-102.38938899999999,52.860977],"type":"Point"}
}