{
  "type": "Feature",
  "properties": {
    "iso:country":"CA",
    "sg:address":"130 Lochiel St",
    "sg:city":"Sarnia",
    "sg:classifiers":[
        {
            "category":"Restaurant",
            "type":"Food & Drink"
        }
    ],
    "sg:phone":"+1 519 337 3239",
    "sg:postcode":"N7T 4C1",
    "sg:province":"ON",
    "sg:tags":[
        "caterer"
    ],
    "wof:name":"New Trish in Edition",
    "wof:placetype":"venue"
},
  "geometry": {"coordinates":[-82.40780639650001,42.9734764099],"type":"Point"}
}