{
  "type": "Feature",
  "properties": {
    "iso:country":"CA",
    "sg:address":"1500 Boul Holy Cross",
    "sg:city":"Cornwall",
    "sg:classifiers":[
        {
            "category":"Social Services",
            "subcategory":"Child Care",
            "type":"Services"
        }
    ],
    "sg:phone":"+1 613 938 6598",
    "sg:postcode":"K6H 2X1",
    "sg:province":"ON",
    "wof:name":"Service DE Recreation Marie",
    "wof:placetype":"venue"
},
  "geometry": {"coordinates":[-74.6995544434,45.0359039307],"type":"Point"}
}