{
  "type": "Feature",
  "properties": {
    "addr:full":"PO Box 95 Beiseker AB T0M 0G0",
    "addr:housenumber":"po box 95",
    "addr:postcode":"t0m 0g0",
    "iso:country":"CA",
    "sg:address":"PO Box 95",
    "sg:city":"Beiseker",
    "sg:classifiers":[
        {
            "category":"Organizations",
            "subcategory":"Religious Organization",
            "type":"Services"
        }
    ],
    "sg:phone":"+1 403 947 3775",
    "sg:postcode":"T0M 0G0",
    "sg:province":"AB",
    "sg:tags":[
        "church"
    ],
    "wof:name":"St Marys Catholic Church",
    "wof:placetype":"venue"
},
  "geometry": {"coordinates":[-113.52265930199999,51.3869285583],"type":"Point"}
}