{
  "type": "Feature",
  "properties": {
    "addr:full":"Bedford NS B4A 3Y4",
    "addr:postcode":"b4a 3y4",
    "iso:country":"CA",
    "sg:city":"Bedford",
    "sg:classifiers":[
        {
            "category":"Shopping",
            "subcategory":"Gifts & Souvenirs",
            "type":"Retail Goods"
        }
    ],
    "sg:phone":"+1 902 835 8678",
    "sg:postcode":"B4A 3Y4",
    "sg:province":"NS",
    "sg:tags":[
        "shop"
    ],
    "wof:name":"Pumpkin Village",
    "wof:placetype":"venue"
},
  "geometry": {"coordinates":[-63.6559715271,44.7327804565],"type":"Point"}
}