{
  "type": "Feature",
  "properties": {
    "addr:full":"47245 Greenhill Rd Chilliwack BC V2R 4T2",
    "addr:housenumber":"47245",
    "addr:postcode":"v2r 4t2",
    "addr:street":"Greenhill Rd",
    "iso:country":"CA",
    "sg:address":"47245 Greenhill Rd",
    "sg:city":"Chilliwack",
    "sg:classifiers":[
        {
            "category":"Building & Trades",
            "subcategory":"Construction",
            "type":"Services"
        }
    ],
    "sg:phone":"+1 604 795 6851",
    "sg:postcode":"V2R 4T2",
    "sg:province":"BC",
    "sg:tags":[
        "insulation",
        "heat",
        "contractor"
    ],
    "wof:name":"M & C Insulators Ltd",
    "wof:placetype":"venue"
},
  "geometry": {"coordinates":[-121.918006897,49.0922813416],"type":"Point"}
}