{
  "type": "Feature",
  "properties": {
    "iso:country":"CA",
    "sg:address":"7900 Boul Taschereau # 202A",
    "sg:city":"Brossard",
    "sg:classifiers":[
        {
            "category":"Wholesale",
            "subcategory":"Chemicals & Plastics",
            "type":"Manufacturing & Wholesale Goods"
        }
    ],
    "sg:phone":"+1 450 466 7764",
    "sg:postcode":"J4X 1C2",
    "sg:province":"QC",
    "wof:name":"Rohm & Haas Canada Inc",
    "wof:placetype":"venue"
},
  "geometry": {"coordinates":[-73.46743011469999,45.4517555237],"type":"Point"}
}