{
  "type": "Feature",
  "properties": {
    "addr:full":"23 Sackville Dr SW Calgary AB T2W 0W3",
    "addr:housenumber":"23",
    "addr:postcode":"t2w 0w3",
    "addr:street":"Sackville Dr Sw",
    "iso:country":"CA",
    "sg:address":"23 Sackville Dr SW",
    "sg:city":"Calgary",
    "sg:classifiers":[
        {
            "category":"Education",
            "subcategory":"School",
            "type":"Public Place"
        }
    ],
    "sg:phone":"+1 403 777 7890",
    "sg:postcode":"T2W 0W3",
    "sg:province":"AB",
    "wof:name":"Harold Panabaker Jr High Schl",
    "wof:placetype":"venue"
},
  "geometry": {"coordinates":[-114.086212,50.957619],"type":"Point"}
}