{
  "type": "Feature",
  "properties": {
    "addr:full":"Vancouver BC V6J 1R3",
    "addr:postcode":"v6j 1r3",
    "iso:country":"CA",
    "sg:city":"Vancouver",
    "sg:classifiers":[
        {
            "category":"Real Estate",
            "subcategory":"Real Estate Agent",
            "type":"Services"
        }
    ],
    "sg:phone":"+1 604 685 2722",
    "sg:postcode":"V6J 1R3",
    "sg:province":"BC",
    "sg:tags":[
        "management"
    ],
    "wof:name":"Mc Gavin Properties Ltd",
    "wof:placetype":"venue"
},
  "geometry": {"coordinates":[-123.141151428,49.2661018372],"type":"Point"}
}