{
  "type": "Feature",
  "properties": {
    "iso:country":"CA",
    "sg:address":"1680 Richmond St # 22",
    "sg:city":"London",
    "sg:classifiers":[
        {
            "category":"Shopping",
            "subcategory":"Luggage & Leather Goods",
            "type":"Retail Goods"
        }
    ],
    "sg:phone":"+1 519 850 7633",
    "sg:postcode":"N6G 3Y9",
    "sg:province":"ON",
    "wof:name":"Danier Leather",
    "wof:placetype":"venue"
},
  "geometry": {"coordinates":[-81.281708,43.025272],"type":"Point"}
}