{
  "type": "Feature",
  "properties": {
    "addr:full":"70 Rue Saint-Paul Quebec QC G1K 3V9",
    "addr:housenumber":"70",
    "addr:postcode":"g1k 3v9",
    "addr:street":"Rue Saint-Paul",
    "iso:country":"CA",
    "sg:address":"70 Rue Saint-Paul",
    "sg:city":"Quebec",
    "sg:classifiers":[
        {
            "category":"Professional",
            "subcategory":"Research",
            "type":"Services"
        }
    ],
    "sg:phone":"+1 418 692 4828",
    "sg:postcode":"G1K 3V9",
    "sg:province":"QC",
    "sg:tags":[
        "environmental",
        "ecological"
    ],
    "wof:name":"Foramec Inc",
    "wof:placetype":"venue"
},
  "geometry": {"coordinates":[-71.2038650513,46.8163795471],"type":"Point"}
}