{
  "type": "Feature",
  "properties": {
    "addr:full":"2300 Pharmacy Ave Scarborough ON M1W 1H8",
    "addr:housenumber":"2300",
    "addr:postcode":"m1w 1h8",
    "addr:street":"Pharmacy Ave",
    "iso:country":"CA",
    "sg:address":"2300 Pharmacy Ave",
    "sg:city":"Scarborough",
    "sg:classifiers":[
        {
            "category":"Education",
            "subcategory":"School",
            "type":"Public Place"
        }
    ],
    "sg:phone":"+1 416 396 6793",
    "sg:postcode":"M1W 1H8",
    "sg:province":"ON",
    "wof:name":"Sir John A Mac Donald Clgt",
    "wof:placetype":"venue"
},
  "geometry": {"coordinates":[-79.3221588135,43.7858276367],"type":"Point"}
}