{
  "type": "Feature",
  "properties": {
    "iso:country":"CA",
    "sg:address":"350 Rue Fraserville",
    "sg:city":"Riviere-Du-Loup",
    "sg:classifiers":[
        {
            "category":"Manufacturing",
            "subcategory":"Tools & Machinery",
            "type":"Manufacturing & Wholesale Goods"
        }
    ],
    "sg:phone":"+1 418 867 3285",
    "sg:postcode":"G5R 5M6",
    "sg:province":"QC",
    "sg:tags":[
        "equipment",
        "refrigeration",
        "electric",
        "supply"
    ],
    "wof:name":"Equipements Yves Landry Inc",
    "wof:placetype":"venue"
},
  "geometry": {"coordinates":[-69.55842590330001,47.7955245972],"type":"Point"}
}