{
  "type": "Feature",
  "properties": {
    "addr:full":"33 Rookwood Ave Fredericton NB E3B 2L8",
    "addr:housenumber":"33",
    "addr:postcode":"e3b 2l8",
    "addr:street":"Rookwood Ave",
    "iso:country":"CA",
    "sg:address":"33 Rookwood Ave",
    "sg:city":"Fredericton",
    "sg:classifiers":[
        {
            "category":"Shopping",
            "type":"Retail Goods"
        }
    ],
    "sg:phone":"+1 506 458 8988",
    "sg:postcode":"E3B 2L8",
    "sg:province":"NB",
    "sg:tags":[
        "limb",
        "home",
        "health",
        "artificial"
    ],
    "wof:name":"A R Menzies & Sons Ltd",
    "wof:placetype":"venue"
},
  "geometry": {"coordinates":[-66.65897369379999,45.9642868042],"type":"Point"}
}