{
  "type": "Feature",
  "properties": {
    "addr:full":"10026 164 St NW Edmonton AB T5P 4Y3",
    "addr:housenumber":"10026",
    "addr:postcode":"t5p 4y3",
    "addr:street":"164 St Nw",
    "iso:country":"CA",
    "sg:address":"10026 164 St NW",
    "sg:city":"Edmonton",
    "sg:classifiers":[
        {
            "category":"Travel",
            "subcategory":"Travel Agent",
            "type":"Entertainment"
        }
    ],
    "sg:phone":"+1 780 489 7669",
    "sg:postcode":"T5P 4Y3",
    "sg:province":"AB",
    "sg:tags":[
        "tours",
        "agency",
        "bureau",
        "skiing"
    ],
    "wof:name":"Downhill Riders Ski & Travel",
    "wof:placetype":"venue"
},
  "geometry": {"coordinates":[-113.604766846,53.5399093628],"type":"Point"}
}