{
  "type": "Feature",
  "properties": {
    "addr:full":"894 King St E Hamilton ON L8M 1B6",
    "addr:housenumber":"894",
    "addr:postcode":"l8m 1b6",
    "addr:street":"King St E",
    "iso:country":"CA",
    "sg:address":"894 King St E",
    "sg:city":"Hamilton",
    "sg:classifiers":[
        {
            "category":"Shopping",
            "subcategory":"Hobbies, Toys, & Games",
            "type":"Retail Goods"
        }
    ],
    "sg:phone":"+1 905 547 7280",
    "sg:postcode":"L8M 1B6",
    "sg:province":"ON",
    "wof:name":"Kool Stuff Toys & Collectibles",
    "wof:placetype":"venue"
},
  "geometry": {"coordinates":[-79.839752,43.25116],"type":"Point"}
}