{
  "type": "Feature",
  "properties": {
    "addr:full":"Route 148 Shawville QC J0X 2Y0",
    "addr:postcode":"j0x 2y0",
    "addr:street":"Route 148",
    "iso:country":"CA",
    "sg:address":"Route 148",
    "sg:city":"Shawville",
    "sg:classifiers":[
        {
            "category":"Social Services",
            "type":"Services"
        }
    ],
    "sg:phone":"+1 819 647 2578",
    "sg:postcode":"J0X 2Y0",
    "sg:province":"QC",
    "sg:tags":[
        "organization",
        "welfare"
    ],
    "wof:name":"Agence Tebizinan",
    "wof:placetype":"venue"
},
  "geometry": {"coordinates":[-76.490326,45.59845],"type":"Point"}
}