{
  "type": "Feature",
  "properties": {
    "addr:full":"Scarborough ON M1S 3A7",
    "addr:postcode":"m1s 3a7",
    "iso:country":"CA",
    "sg:city":"Scarborough",
    "sg:classifiers":[
        {
            "category":"Shopping",
            "type":"Retail Goods"
        }
    ],
    "sg:phone":"+1 416 292 3118",
    "sg:postcode":"M1S 3A7",
    "sg:province":"ON",
    "sg:tags":[
        "ice"
    ],
    "wof:name":"Crystal Ice Mfg CO",
    "wof:placetype":"venue"
},
  "geometry": {"coordinates":[-79.2563095093,43.7933082581],"type":"Point"}
}