{
  "type": "Feature",
  "properties": {
    "addr:full":"207 Rue Heriot Drummondville QC J2C 1J9",
    "addr:housenumber":"207",
    "addr:postcode":"j2c 1j9",
    "addr:street":"Rue Heriot",
    "iso:country":"CA",
    "sg:address":"207 Rue Heriot",
    "sg:city":"Drummondville",
    "sg:classifiers":[
        {
            "category":"Shopping",
            "subcategory":"Luggage & Leather Goods",
            "type":"Retail Goods"
        }
    ],
    "sg:phone":"+1 819 472 6837",
    "sg:postcode":"J2C 1J9",
    "sg:province":"QC",
    "wof:name":"H P Drouin Entreprises Inc",
    "wof:placetype":"venue"
},
  "geometry": {"coordinates":[-72.489502,45.885368],"type":"Point"}
}