{
  "type": "Feature",
  "properties": {
    "iso:country":"CA",
    "sg:address":"18 Martin St",
    "sg:city":"Milton",
    "sg:classifiers":[
        {
            "category":"Health Services",
            "subcategory":"Health Practitioner",
            "type":"Services"
        }
    ],
    "sg:phone":"+1 905 693 3546",
    "sg:postcode":"L9T 2P9",
    "sg:province":"ON",
    "sg:tags":[
        "acupuncture"
    ],
    "wof:name":"Logan, Alice",
    "wof:placetype":"venue"
},
  "geometry": {"coordinates":[-79.883453,43.51366],"type":"Point"}
}