{
  "type": "Feature",
  "properties": {
    "iso:country":"CA",
    "sg:address":"214 Boul Grand",
    "sg:city":"L'Ile-Perrot",
    "sg:classifiers":[
        {
            "category":"Personal",
            "subcategory":"Tanning Parlor",
            "type":"Services"
        }
    ],
    "sg:phone":"+1 514 453 3326",
    "sg:postcode":"J7V 4X1",
    "sg:province":"QC",
    "sg:tags":[
        "salon"
    ],
    "wof:name":"Sante Soleil Enrg",
    "wof:placetype":"venue"
},
  "geometry": {"coordinates":[-73.95890808110001,45.3938865662],"type":"Point"}
}