{
  "type": "Feature",
  "properties": {
    "addr:full":"2297 St Joseph Blvd Orleans ON K1C 1E7",
    "addr:housenumber":"2297",
    "addr:postcode":"k1c 1e7",
    "addr:street":"St Joseph Blvd",
    "iso:country":"CA",
    "sg:address":"2297 St Joseph Blvd",
    "sg:city":"Orleans",
    "sg:classifiers":[
        {
            "category":"Shopping",
            "subcategory":"Musical Instruments",
            "type":"Retail Goods"
        }
    ],
    "sg:phone":"+1 613 837 0124",
    "sg:postcode":"K1C 1E7",
    "sg:province":"ON",
    "sg:tags":[
        "instruction",
        "music",
        "dealer"
    ],
    "wof:name":"Domenic's Academy of Music",
    "wof:placetype":"venue"
},
  "geometry": {"coordinates":[-75.5313873291,45.4682846069],"type":"Point"}
}