{
  "type": "Feature",
  "properties": {
    "addr:full":"PO Box 120 Aylesford NS B0P 1C0",
    "addr:housenumber":"po",
    "addr:postcode":"b0p 1c0",
    "addr:street":"Box 120",
    "iso:country":"CA",
    "sg:address":"PO Box 120",
    "sg:city":"Aylesford",
    "sg:classifiers":[
        {
            "category":"Organizations",
            "subcategory":"Religious Organization",
            "type":"Services"
        }
    ],
    "sg:phone":"+1 902 847 9545",
    "sg:postcode":"B0P 1C0",
    "sg:province":"NS",
    "sg:tags":[
        "church"
    ],
    "wof:name":"Baptist Church",
    "wof:placetype":"venue"
},
  "geometry": {"coordinates":[-64.8375244141,45.0277938843],"type":"Point"}
}