{
  "type": "Feature",
  "properties": {
    "addr:full":"Fox Point Rd Dwight ON P0A 1H0",
    "addr:postcode":"p0a 1h0",
    "addr:street":"Fox Point Rd",
    "iso:country":"CA",
    "sg:address":"Fox Point Rd",
    "sg:city":"Dwight",
    "sg:classifiers":[
        {
            "category":"Building & Trades",
            "subcategory":"Landscaping Services",
            "type":"Services"
        }
    ],
    "sg:phone":"+1 705 635 1148",
    "sg:postcode":"P0A 1H0",
    "sg:province":"ON",
    "sg:tags":[
        "landscape",
        "contractor"
    ],
    "wof:name":"Lakeside Landscaping",
    "wof:placetype":"venue"
},
  "geometry": {"coordinates":[-79.014915,45.297039],"type":"Point"}
}