{
  "type": "Feature",
  "properties": {
    "addr:full":"15 Ropewalk Lane St. John's NL A1E 4P1",
    "addr:housenumber":"15",
    "addr:postcode":"a1e 4p1",
    "addr:street":"Ropewalk Lane",
    "iso:country":"CA",
    "sg:address":"15 Ropewalk Lane",
    "sg:city":"St. John's",
    "sg:classifiers":[
        {
            "category":"Food & Beverages",
            "subcategory":"Specialty",
            "type":"Retail Goods"
        }
    ],
    "sg:phone":"+1 709 579 4116",
    "sg:postcode":"A1E 4P1",
    "sg:province":"NL",
    "sg:tags":[
        "water",
        "bulk",
        "company"
    ],
    "wof:name":"Viking Beverages",
    "wof:placetype":"venue"
},
  "geometry": {"coordinates":[-52.735142,47.554958],"type":"Point"}
}