{
  "type": "Feature",
  "properties": {
    "addr:full":"5116 Elbow Dr SW Calgary AB T2V 1H1",
    "addr:housenumber":"5116",
    "addr:postcode":"t2v 1h1",
    "addr:street":"Elbow Dr Sw",
    "iso:country":"CA",
    "sg:address":"5116 Elbow Dr SW",
    "sg:city":"Calgary",
    "sg:classifiers":[
        {
            "category":"Personal",
            "type":"Services"
        }
    ],
    "sg:phone":"+1 403 259 6798",
    "sg:postcode":"T2V 1H1",
    "sg:province":"AB",
    "sg:tags":[
        "hair",
        "replacement"
    ],
    "wof:name":"Gillespie Clinic",
    "wof:placetype":"venue"
},
  "geometry": {"coordinates":[-114.08118399999999,51.008469],"type":"Point"}
}