{
  "type": "Feature",
  "properties": {
    "addr:full":"5446 Upper Canada Rd Morrisburg ON K0C 1X0",
    "addr:housenumber":"5446",
    "addr:postcode":"k0c 1x0",
    "addr:street":"Upper Canada Rd",
    "iso:country":"CA",
    "sg:address":"5446 Upper Canada Rd",
    "sg:city":"Morrisburg",
    "sg:classifiers":[
        {
            "category":"Recreation",
            "type":"Entertainment"
        }
    ],
    "sg:phone":"+1 613 543 2503",
    "sg:postcode":"K0C 1X0",
    "sg:province":"ON",
    "sg:tags":[
        "attraction",
        "tourist"
    ],
    "wof:name":"Prehistoric World",
    "wof:placetype":"venue"
},
  "geometry": {"coordinates":[-75.103584,44.946625],"type":"Point"}
}