{
  "type": "Feature",
  "properties": {
    "addr:full":"2145 Carmen Rd Nanaimo BC V9S 5L7",
    "addr:housenumber":"2145",
    "addr:postcode":"v9s 5l7",
    "addr:street":"Carmen Rd",
    "iso:country":"CA",
    "sg:address":"2145 Carmen Rd",
    "sg:city":"Nanaimo",
    "sg:classifiers":[
        {
            "category":"Freight",
            "type":"Transportation"
        }
    ],
    "sg:phone":"+1 250 758 2677",
    "sg:postcode":"V9S 5L7",
    "sg:province":"BC",
    "sg:tags":[
        "trucking"
    ],
    "wof:name":"Stan Wood Trucking Ltd",
    "wof:placetype":"venue"
},
  "geometry": {"coordinates":[-123.979972839,49.1900482178],"type":"Point"}
}