{
  "type": "Feature",
  "properties": {
    "iso:country":"CA",
    "sg:address":"1500 Fisher St",
    "sg:city":"North Bay",
    "sg:classifiers":[
        {
            "category":"Shopping",
            "subcategory":"Clothing, Apparel, & Fashions",
            "type":"Retail Goods"
        }
    ],
    "sg:phone":"+1 705 476 5741",
    "sg:postcode":"P1B 2H3",
    "sg:province":"ON",
    "sg:tags":[
        "jean"
    ],
    "wof:name":"Bluenotes",
    "wof:placetype":"venue"
},
  "geometry": {"coordinates":[-79.4432067871,46.3128318787],"type":"Point"}
}