{
  "type": "Feature",
  "properties": {
    "addr:full":"1075 Eglinton Ave W Mississauga ON L5V 2W3",
    "addr:housenumber":"1075",
    "addr:postcode":"l5v 2w3",
    "addr:street":"Eglinton Ave W",
    "iso:country":"CA",
    "sg:address":"1075 Eglinton Ave W",
    "sg:city":"Mississauga",
    "sg:classifiers":[
        {
            "category":"Organizations",
            "subcategory":"Religious Organization",
            "type":"Services"
        }
    ],
    "sg:phone":"+1 905 826 8581",
    "sg:postcode":"L5V 2W3",
    "sg:province":"ON",
    "sg:tags":[
        "church"
    ],
    "wof:name":"City Centre Baptist Church",
    "wof:placetype":"venue"
},
  "geometry": {"coordinates":[-79.67832900000001,43.584351],"type":"Point"}
}