{
  "type": "Feature",
  "properties": {
    "addr:full":"Levis QC G6V 1J5",
    "addr:postcode":"g6v 1j5",
    "iso:country":"CA",
    "sg:city":"Levis",
    "sg:classifiers":[
        {
            "category":"Insurance",
            "subcategory":"Insurance Agent",
            "type":"Services"
        }
    ],
    "sg:phone":"+1 418 833 8371",
    "sg:postcode":"G6V 1J5",
    "sg:province":"QC",
    "wof:name":"Brulotte Regent Svc Financiers",
    "wof:placetype":"venue"
},
  "geometry": {"coordinates":[-71.140266,46.826313],"type":"Point"}
}