{
  "type": "Feature",
  "properties": {
    "addr:full":"101 College St.  MaRS Ste.  227 Toronto, ON M5G 1L7",
    "addr:housenumber":"101",
    "addr:postcode":"m5g 1l7",
    "addr:street":"College St.;Ste. 227",
    "iso:country":"CA",
    "sg:address":"101 College St.  MaRS Ste.  227",
    "sg:city":"Toronto, ON",
    "sg:classifiers":[
        {
            "category":"Professional",
            "subcategory":"Research",
            "type":"Services"
        }
    ],
    "sg:postcode":"M5G 1L7",
    "sg:tags":[
        "traffic",
        "summit-at-stanford-09"
    ],
    "sg:website":"http://www.skymetercorp.com",
    "wof:name":"Skymeter",
    "wof:placetype":"venue"
},
  "geometry": {"coordinates":[-79.388696,43.65992],"type":"Point"}
}