{
  "type": "Feature",
  "properties": {
    "iso:country":"CA",
    "sg:address":"11541 Av Salk",
    "sg:city":"Montreal-Nord",
    "sg:classifiers":[
        {
            "category":"Building & Trades",
            "subcategory":"Construction",
            "type":"Services"
        }
    ],
    "sg:phone":"+1 514 327 2923",
    "sg:postcode":"H1G 4Y7",
    "sg:province":"QC",
    "sg:tags":[
        "excavating",
        "contractor"
    ],
    "wof:name":"Entreprises Poyg Inc",
    "wof:placetype":"venue"
},
  "geometry": {"coordinates":[-73.627182,45.605133],"type":"Point"}
}