{
  "type": "Feature",
  "properties": {
    "addr:full":"19 Caradoc St S Strathroy ON N7G 2N3",
    "addr:housenumber":"19",
    "addr:postcode":"n7g 2n3",
    "addr:street":"Caradoc St S",
    "iso:country":"CA",
    "sg:address":"19 Caradoc St S",
    "sg:city":"Strathroy",
    "sg:classifiers":[
        {
            "category":"Health Services",
            "subcategory":"Doctor",
            "type":"Services"
        }
    ],
    "sg:phone":"+1 519 246 1240",
    "sg:postcode":"N7G 2N3",
    "sg:province":"ON",
    "sg:tags":[
        "dentist"
    ],
    "wof:name":"Watt, David DDS",
    "wof:placetype":"venue"
},
  "geometry": {"coordinates":[-81.62103271479999,42.9559783936],"type":"Point"}
}