{
  "type": "Feature",
  "properties": {
    "addr:full":"3 Millside Dr SW Calgary AB T2Y 2P1",
    "addr:housenumber":"3",
    "addr:postcode":"t2y 2p1",
    "addr:street":"Millside Dr Sw",
    "iso:country":"CA",
    "sg:address":"3 Millside Dr SW",
    "sg:city":"Calgary",
    "sg:classifiers":[
        {
            "category":"Social Services",
            "subcategory":"Child Care",
            "type":"Services"
        }
    ],
    "sg:phone":"+1 403 256 3003",
    "sg:postcode":"T2Y 2P1",
    "sg:province":"AB",
    "wof:name":"Millrise Child Ctr",
    "wof:placetype":"venue"
},
  "geometry": {"coordinates":[-114.080696,50.919899],"type":"Point"}
}