{
  "type": "Feature",
  "properties": {
    "addr:full":"222 Bonny Bay Dryden ON P8N 2Y4",
    "addr:housenumber":"222",
    "addr:postcode":"p8n 2y4",
    "addr:street":"Bonny Bay",
    "iso:country":"CA",
    "sg:address":"222 Bonny Bay",
    "sg:city":"Dryden",
    "sg:classifiers":[
        {
            "category":"Travel",
            "subcategory":"Campground",
            "type":"Entertainment"
        }
    ],
    "sg:phone":"+1 807 938 6696",
    "sg:postcode":"P8N 2Y4",
    "sg:province":"ON",
    "sg:tags":[
        "camp"
    ],
    "wof:name":"Bonny Bay Camp",
    "wof:placetype":"venue"
},
  "geometry": {"coordinates":[-92.6673965454,49.7521820068],"type":"Point"}
}