{
  "type": "Feature",
  "properties": {
    "addr:full":"Toronto ON M5S 2V1",
    "addr:postcode":"m5s 2v1",
    "iso:country":"CA",
    "sg:city":"Toronto",
    "sg:classifiers":[
        {
            "category":"Professional",
            "subcategory":"Research",
            "type":"Services"
        }
    ],
    "sg:phone":"+1 416 923 1166",
    "sg:postcode":"M5S 2V1",
    "sg:province":"ON",
    "sg:tags":[
        "economic",
        "analysis"
    ],
    "wof:name":"Charles River Assoc Intl",
    "wof:placetype":"venue"
},
  "geometry": {"coordinates":[-79.3904037476,43.6696090698],"type":"Point"}
}