{
  "type": "Feature",
  "properties": {
    "addr:full":"5275 Rue Jean-Talon E Saint-Leonard QC H1S 1L2",
    "addr:housenumber":"5275",
    "addr:postcode":"h1s 1l2",
    "addr:street":"Rue Jean-Talon E",
    "iso:country":"CA",
    "sg:address":"5275 Rue Jean-Talon E",
    "sg:city":"Saint-Leonard",
    "sg:classifiers":[
        {
            "category":"Health Services",
            "subcategory":"Doctor",
            "type":"Services"
        }
    ],
    "sg:phone":"+1 514 721 8100",
    "sg:postcode":"H1S 1L2",
    "sg:province":"QC",
    "sg:tags":[
        "dentist"
    ],
    "wof:name":"Venneri, Carlo DDS",
    "wof:placetype":"venue"
},
  "geometry": {"coordinates":[-73.58253499999999,45.578651],"type":"Point"}
}