{
  "type": "Feature",
  "properties": {
    "addr:full":"103 Fourth Ave SW Geraldton ON P0T 1M0",
    "addr:housenumber":"103",
    "addr:postcode":"p0t 1m0",
    "addr:street":"Fourth Ave Sw",
    "iso:country":"CA",
    "sg:address":"103 Fourth Ave SW",
    "sg:city":"Geraldton",
    "sg:classifiers":[
        {
            "category":"Personal",
            "subcategory":"Beauty Salon",
            "type":"Services"
        }
    ],
    "sg:phone":"+1 807 854 1444",
    "sg:postcode":"P0T 1M0",
    "sg:province":"ON",
    "wof:name":"His & Hers Hairstyling",
    "wof:placetype":"venue"
},
  "geometry": {"coordinates":[-86.9465332031,49.7234306335],"type":"Point"}
}