{
  "type": "Feature",
  "properties": {
    "iso:country":"CA",
    "sg:address":"1305 Boul Saint-Joseph",
    "sg:city":"Quebec",
    "sg:classifiers":[
        {
            "category":"Personal",
            "subcategory":"Beauty Salon",
            "type":"Services"
        }
    ],
    "sg:phone":"+1 418 628 6400",
    "sg:postcode":"G2K 1G3",
    "sg:province":"QC",
    "wof:name":"Coupe Herman Enr",
    "wof:placetype":"venue"
},
  "geometry": {"coordinates":[-71.28369903559999,46.8534698486],"type":"Point"}
}