{
  "type": "Feature",
  "properties": {
    "addr:full":"Goderich ON N7A 3X8",
    "addr:postcode":"n7a 3x8",
    "iso:country":"CA",
    "sg:city":"Goderich",
    "sg:classifiers":[
        {
            "category":"Home & Garden",
            "subcategory":"Furniture",
            "type":"Retail Goods"
        }
    ],
    "sg:phone":"+1 519 524 7231",
    "sg:postcode":"N7A 3X8",
    "sg:province":"ON",
    "wof:name":"C & E New & Used Furniture",
    "wof:placetype":"venue"
},
  "geometry": {"coordinates":[-81.7128372192,43.7223930359],"type":"Point"}
}