{
  "type": "Feature",
  "properties": {
    "addr:full":"25 Edilcan Dr # 1 Concord ON L4K 3S4",
    "addr:housenumber":"25",
    "addr:postcode":"l4k 3s4",
    "addr:street":"Edilcan Dr # 1",
    "iso:country":"CA",
    "sg:address":"25 Edilcan Dr # 1",
    "sg:city":"Concord",
    "sg:classifiers":[
        {
            "category":"Manufacturing",
            "subcategory":"Printing",
            "type":"Manufacturing & Wholesale Goods"
        }
    ],
    "sg:phone":"+1 905 738 5004",
    "sg:postcode":"L4K 3S4",
    "sg:province":"ON",
    "sg:tags":[
        "printer",
        "publishing"
    ],
    "wof:name":"Graphic Lounge Inc",
    "wof:placetype":"venue"
},
  "geometry": {"coordinates":[-79.527855,43.815205],"type":"Point"}
}