{
  "type": "Feature",
  "properties": {
    "iso:country":"CA",
    "sg:city":"Mcauley",
    "sg:classifiers":[
        {
            "category":"Personal",
            "subcategory":"Beauty Salon",
            "type":"Services"
        }
    ],
    "sg:phone":"+1 204 722 2217",
    "sg:postcode":"R0M 1H0",
    "sg:province":"MB",
    "wof:name":"Scissors & Sun",
    "wof:placetype":"venue"
},
  "geometry": {"coordinates":[-101.384269714,50.2632217407],"type":"Point"}
}