{
  "type": "Feature",
  "properties": {
    "iso:country":"CA",
    "sg:address":"2200 Queen St E #3",
    "sg:city":"Brampton",
    "sg:classifiers":[
        {
            "category":"Retail",
            "subcategory":"Portrait Studio",
            "type":"Services"
        }
    ],
    "sg:phone":"+1 905 791 5539",
    "sg:postcode":"L6S 4G9",
    "sg:province":"ON",
    "sg:tags":[
        "photographer"
    ],
    "wof:name":"Photoland",
    "wof:placetype":"venue"
},
  "geometry": {"coordinates":[-79.706741,43.734081],"type":"Point"}
}