{
  "type": "Feature",
  "properties": {
    "addr:full":"2200 Queen St E #3 Brampton ON L6S 4G9",
    "addr:housenumber":"2200",
    "addr:postcode":"l6s 4g9",
    "addr:street":"Queen St E # 3",
    "iso:country":"CA",
    "sg:address":"2200 Queen St E #3",
    "sg:city":"Brampton",
    "sg:classifiers":[
        {
            "category":"Retail",
            "subcategory":"Portrait Studio",
            "type":"Services"
        }
    ],
    "sg:phone":"+1 905 791 5539",
    "sg:postcode":"L6S 4G9",
    "sg:province":"ON",
    "sg:tags":[
        "photographer"
    ],
    "wof:name":"Photoland",
    "wof:placetype":"venue"
},
  "geometry": {"coordinates":[-79.70674099999999,43.734081],"type":"Point"}
}