{
  "type": "Feature",
  "properties": {
    "iso:country":"CA",
    "sg:city":"Barrie",
    "sg:classifiers":[
        {
            "category":"Manufacturing",
            "subcategory":"Metals",
            "type":"Manufacturing & Wholesale Goods"
        }
    ],
    "sg:phone":"+1 705 721 6800",
    "sg:postcode":"L4M 5A5",
    "sg:province":"ON",
    "sg:tags":[
        "fiber",
        "telemarketing",
        "system"
    ],
    "wof:name":"Cti",
    "wof:placetype":"venue"
},
  "geometry": {"coordinates":[-79.684479,44.408836],"type":"Point"}
}