{
  "type": "Feature",
  "properties": {
    "addr:full":"Alliston ON L9R 1R2",
    "addr:postcode":"l9r 1r2",
    "addr:street":"Alliston",
    "iso:country":"CA",
    "sg:city":"Alliston",
    "sg:classifiers":[
        {
            "category":"Shopping",
            "subcategory":"Books",
            "type":"Retail Goods"
        }
    ],
    "sg:phone":"+1 705 435 2183",
    "sg:postcode":"L9R 1R2",
    "sg:province":"ON",
    "sg:tags":[
        "dealer"
    ],
    "wof:name":"Beacon Book & Gift Shop",
    "wof:placetype":"venue"
},
  "geometry": {"coordinates":[-79.86618804930001,44.1546974182],"type":"Point"}
}