{
  "type": "Feature",
  "properties": {
    "iso:country":"CA",
    "sg:city":"Halifax",
    "sg:classifiers":[
        {
            "category":"Organizations",
            "subcategory":"Non-profit Organization",
            "type":"Services"
        }
    ],
    "sg:phone":"+1 902 455 7225",
    "sg:postcode":"B3K 5L2",
    "sg:province":"NS",
    "sg:tags":[
        "fund",
        "counselor",
        "raising"
    ],
    "wof:name":"Atlantic Fund Raising Svc Ltd",
    "wof:placetype":"venue"
},
  "geometry": {"coordinates":[-63.6035728455,44.658531189],"type":"Point"}
}