{
  "type": "Feature",
  "properties": {
    "addr:full":"176 Blandford St Innerkip ON N0J 1M0",
    "addr:housenumber":"176",
    "addr:postcode":"n0j 1m0",
    "addr:street":"Blandford St",
    "iso:country":"CA",
    "sg:address":"176 Blandford St",
    "sg:city":"Innerkip",
    "sg:classifiers":[
        {
            "category":"Restaurant",
            "type":"Food & Drink"
        }
    ],
    "sg:phone":"+1 519 469 3624",
    "sg:postcode":"N0J 1M0",
    "sg:province":"ON",
    "sg:tags":[
        "caterer"
    ],
    "wof:name":"Buzzy's Bakery & Catering",
    "wof:placetype":"venue"
},
  "geometry": {"coordinates":[-80.697327,43.208363],"type":"Point"}
}