{
  "type": "Feature",
  "properties": {
    "addr:full":"9060 212 St Langley BC V1M 2B7",
    "addr:housenumber":"9060",
    "addr:postcode":"v1m 2b7",
    "addr:street":"212 St",
    "iso:country":"CA",
    "sg:address":"9060 212 St",
    "sg:city":"Langley",
    "sg:classifiers":[
        {
            "category":"Education",
            "subcategory":"School",
            "type":"Public Place"
        }
    ],
    "sg:phone":"+1 604 888 5257",
    "sg:postcode":"V1M 2B7",
    "sg:province":"BC",
    "wof:name":"James Kennedy Elementary",
    "wof:placetype":"venue"
},
  "geometry": {"coordinates":[-122.634773,49.167236],"type":"Point"}
}