{
  "type": "Feature",
  "properties": {
    "addr:full":"115 Avenue Laurier O. Montreal QC Canada",
    "addr:phone":"514-276-4282",
    "iso:country":"CA",
    "name:eng_x_preferred":[
        "Henrietta"
    ],
    "wof:name":"Henrietta",
    "wof:placetype":"venue"
},
  "geometry": {"coordinates":[-73.594311,45.521646],"type":"Point"}
}