{
  "type": "Feature",
  "properties": {
    "addr:full":"114 Waldron Ave Okotoks AB T1S 1C8",
    "addr:housenumber":"114",
    "addr:postcode":"t1s 1c8",
    "addr:street":"Waldron Ave;Ab",
    "iso:country":"CA",
    "sg:address":"114 Waldron Ave",
    "sg:city":"Okotoks",
    "sg:classifiers":[
        {
            "category":"Organizations",
            "subcategory":"Religious Organization",
            "type":"Services"
        }
    ],
    "sg:phone":"+1 403 938 3515",
    "sg:postcode":"T1S 1C8",
    "sg:province":"AB",
    "sg:tags":[
        "church"
    ],
    "wof:name":"Grace Lutheran Church",
    "wof:placetype":"venue"
},
  "geometry": {"coordinates":[-113.967422,50.733727],"type":"Point"}
}