{
  "type": "Feature",
  "properties": {
    "iso:country":"CA",
    "sg:address":"20 Rue Mahikan",
    "sg:city":"Mashteuiatsh",
    "sg:classifiers":[
        {
            "category":"Home & Garden",
            "subcategory":"Hardware",
            "type":"Retail Goods"
        }
    ],
    "sg:phone":"+1 418 275 1400",
    "sg:postcode":"G0W 2H0",
    "sg:province":"QC",
    "wof:name":"Quincaillerie Mashteuiatsh Enr",
    "wof:placetype":"venue"
},
  "geometry": {"coordinates":[-74.39385223390001,47.2242164612],"type":"Point"}
}