{
  "type": "Feature",
  "properties": {
    "iso:country":"CA",
    "sg:address":"1101 Rue Saint-Alexandre",
    "sg:city":"Montreal",
    "sg:classifiers":[
        {
            "category":"Professional",
            "subcategory":"Business Services",
            "type":"Services"
        }
    ],
    "sg:phone":"+1 514 878 0587",
    "sg:postcode":"H2Z 1P8",
    "sg:province":"QC",
    "sg:tags":[
        "interior",
        "consultant",
        "design",
        "decorator"
    ],
    "wof:name":"Joannidis Design & Concept",
    "wof:placetype":"venue"
},
  "geometry": {"coordinates":[-73.5644836426,45.5039672852],"type":"Point"}
}