{
  "type": "Feature",
  "properties": {
    "iso:country":"CA",
    "sg:address":"2376 Royal Windsor Dr",
    "sg:city":"Oakville",
    "sg:classifiers":[
        {
            "category":"Building & Trades",
            "subcategory":"Landscaping Services",
            "type":"Services"
        }
    ],
    "sg:phone":"+1 905 257 8795",
    "sg:postcode":"L6J 7Y2",
    "sg:province":"ON",
    "sg:tags":[
        "contractor",
        "sodding",
        "landscape",
        "sod"
    ],
    "wof:name":"Ontario Sod",
    "wof:placetype":"venue"
},
  "geometry": {"coordinates":[-79.64999389650001,43.4922332764],"type":"Point"}
}