{
  "type": "Feature",
  "properties": {
    "addr:full":"436 Rue Des Adirondacks Beauport QC G1C 7E8",
    "addr:housenumber":"436",
    "addr:postcode":"qc g1c 7e8",
    "addr:street":"Rue Des Adirondacks",
    "iso:country":"CA",
    "sg:address":"436 Rue Des Adirondacks",
    "sg:city":"Beauport",
    "sg:classifiers":[
        {
            "category":"Wholesale",
            "subcategory":"Construction Materials",
            "type":"Manufacturing & Wholesale Goods"
        }
    ],
    "sg:phone":"+1 418 660 4060",
    "sg:postcode":"G1C 7E8",
    "sg:province":"QC",
    "sg:tags":[
        "sand",
        "gravel",
        "landscape",
        "contractor"
    ],
    "wof:name":"Entreprises Paradis Paysagiste",
    "wof:placetype":"venue"
},
  "geometry": {"coordinates":[-71.190727,46.881107],"type":"Point"}
}