{
  "type": "Feature",
  "properties": {
    "iso:country":"CA",
    "sg:address":"43 Saskatoon Ave",
    "sg:city":"Halifax",
    "sg:classifiers":[
        {
            "category":"Wholesale",
            "subcategory":"Medical Equipment & Supplies",
            "type":"Manufacturing & Wholesale Goods"
        }
    ],
    "sg:phone":"+1 902 457 8388",
    "sg:postcode":"B3M 3H8",
    "sg:province":"NS",
    "sg:tags":[
        "physician",
        "hospital",
        "surgeon"
    ],
    "wof:name":"Vf/Vt Distributors Inc",
    "wof:placetype":"venue"
},
  "geometry": {"coordinates":[-63.688938,44.689632],"type":"Point"}
}