{
  "type": "Feature",
  "properties": {
    "addr:full":"5502 46 St Camrose AB T4V 1X4",
    "addr:housenumber":"5502",
    "addr:postcode":"t4v 1x4",
    "addr:street":"46 St",
    "iso:country":"CA",
    "sg:address":"5502 46 St",
    "sg:city":"Camrose",
    "sg:classifiers":[
        {
            "category":"Organizations",
            "subcategory":"Professional Association",
            "type":"Services"
        }
    ],
    "sg:phone":"+1 780 672 9995",
    "sg:postcode":"T4V 1X4",
    "sg:province":"AB",
    "wof:name":"Centra Cam Vocational Training",
    "wof:placetype":"venue"
},
  "geometry": {"coordinates":[-112.818665,53.032169],"type":"Point"}
}