{
  "type": "Feature",
  "properties": {
    "addr:full":"115 George St Hamilton ON L8P 1E3",
    "addr:housenumber":"115",
    "addr:postcode":"l8p 1e3",
    "addr:street":"George St",
    "iso:country":"CA",
    "sg:address":"115 George St",
    "sg:city":"Hamilton",
    "sg:classifiers":[
        {
            "category":"Restaurant",
            "type":"Food & Drink"
        }
    ],
    "sg:phone":"+1 905 524 5111",
    "sg:postcode":"L8P 1E3",
    "sg:province":"ON",
    "wof:name":"Funky Munkey Rib House",
    "wof:placetype":"venue"
},
  "geometry": {"coordinates":[-79.8788757324,43.2582473755],"type":"Point"}
}