{
  "type": "Feature",
  "properties": {
    "addr:full":"442 Boul Sainte-Anne Sainte-Anne-Des-Plaines QC J0N 1H0",
    "addr:housenumber":"442",
    "addr:postcode":"j0n 1h0",
    "addr:street":"Boul Sainte-Anne",
    "iso:country":"CA",
    "sg:address":"442 Boul Sainte-Anne",
    "sg:city":"Sainte-Anne-Des-Plaines",
    "sg:classifiers":[
        {
            "category":"Health Services",
            "subcategory":"Doctor",
            "type":"Services"
        }
    ],
    "sg:phone":"+1 450 478 4737",
    "sg:postcode":"J0N 1H0",
    "sg:province":"QC",
    "sg:tags":[
        "clinic"
    ],
    "wof:name":"Centre Medical",
    "wof:placetype":"venue"
},
  "geometry": {"coordinates":[-73.81444500000001,45.760204],"type":"Point"}
}