{
  "type": "Feature",
  "properties": {
    "addr:full":"Langley BC V2Y 1A5",
    "addr:postcode":"v2y 1a5",
    "iso:country":"CA",
    "sg:city":"Langley",
    "sg:classifiers":[
        {
            "category":"Personal",
            "subcategory":"Tanning Parlor",
            "type":"Services"
        }
    ],
    "sg:phone":"+1 604 539 0899",
    "sg:postcode":"V2Y 1A5",
    "sg:province":"BC",
    "sg:tags":[
        "salon"
    ],
    "wof:name":"Sun Shop Tanning Studios",
    "wof:placetype":"venue"
},
  "geometry": {"coordinates":[-122.678756714,49.1155929565],"type":"Point"}
}