{
  "type": "Feature",
  "properties": {
    "addr:full":"13 Woodward Blind River ON P0R 1B0",
    "addr:housenumber":"13",
    "addr:postcode":"p0r 1b0",
    "addr:street":"Woodward",
    "iso:country":"CA",
    "sg:address":"13 Woodward",
    "sg:city":"Blind River",
    "sg:classifiers":[
        {
            "category":"Professional",
            "subcategory":"Accounting & Tax Preparation",
            "type":"Services"
        }
    ],
    "sg:phone":"+1 705 356 7453",
    "sg:postcode":"P0R 1B0",
    "sg:province":"ON",
    "sg:tags":[
        "accountant"
    ],
    "wof:name":"Phillips, E A Ted CA",
    "wof:placetype":"venue"
},
  "geometry": {"coordinates":[-82.9545288086,46.1861724854],"type":"Point"}
}