{
  "type": "Feature",
  "properties": {
    "addr:full":"7250 Rue Clark Montreal QC H2R 2Y3",
    "addr:housenumber":"7250",
    "addr:postcode":"h2r 2y3",
    "addr:street":"Rue Clark",
    "iso:country":"CA",
    "sg:address":"7250 Rue Clark",
    "sg:city":"Montreal",
    "sg:classifiers":[
        {
            "category":"Wholesale",
            "subcategory":"Apparel",
            "type":"Manufacturing & Wholesale Goods"
        }
    ],
    "sg:phone":"+1 514 271 2495",
    "sg:postcode":"H2R 2Y3",
    "sg:province":"QC",
    "sg:tags":[
        "textile"
    ],
    "wof:name":"Elgo Textiles Ltd",
    "wof:placetype":"venue"
},
  "geometry": {"coordinates":[-73.61986541749999,45.5343856812],"type":"Point"}
}