{
  "type": "Feature",
  "properties": {
    "addr:full":"Kanata ON K2T 1B8",
    "addr:postcode":"k2t 1b8",
    "iso:country":"CA",
    "sg:city":"Kanata",
    "sg:classifiers":[
        {
            "category":"Shopping",
            "type":"Retail Goods"
        }
    ],
    "sg:phone":"+1 613 599 7009",
    "sg:postcode":"K2T 1B8",
    "sg:province":"ON",
    "sg:tags":[
        "picture",
        "frame",
        "art",
        "gallery",
        "dealer"
    ],
    "wof:name":"Framing & Art Ctr",
    "wof:placetype":"venue"
},
  "geometry": {"coordinates":[-75.91231500000001,45.309914],"type":"Point"}
}