{
  "type": "Feature",
  "properties": {
    "addr:full":"1214 Route 255 Saint-Felix-DE-Kingsey QC J0B 2T0",
    "addr:housenumber":"1214",
    "addr:postcode":"j0b 2t0",
    "addr:street":"Route 255 Saint-Felix-De-Kingsey",
    "iso:country":"CA",
    "sg:address":"1214 Route 255",
    "sg:city":"Saint-Felix-DE-Kingsey",
    "sg:classifiers":[
        {
            "category":"Freight",
            "type":"Transportation"
        }
    ],
    "sg:phone":"+1 819 848 2042",
    "sg:postcode":"J0B 2T0",
    "sg:province":"QC",
    "sg:tags":[
        "trucking"
    ],
    "wof:name":"Durocher Transit Inc",
    "wof:placetype":"venue"
},
  "geometry": {"coordinates":[-72.19266500000001,45.795597],"type":"Point"}
}