{
  "type": "Feature",
  "properties": {
    "addr:full":"200 John St W Oshawa ON L1J 2B4",
    "addr:housenumber":"200",
    "addr:postcode":"l1j 2b4",
    "addr:street":"John St W",
    "iso:country":"CA",
    "sg:address":"200 John St W",
    "sg:city":"Oshawa",
    "sg:classifiers":[
        {
            "category":"Real Estate",
            "subcategory":"Real Estate Operator",
            "type":"Services"
        }
    ],
    "sg:phone":"+1 905 723 5933",
    "sg:postcode":"L1J 2B4",
    "sg:province":"ON",
    "sg:tags":[
        "mall",
        "shopping",
        "center"
    ],
    "wof:name":"Midtown Mall Shopping Ctr",
    "wof:placetype":"venue"
},
  "geometry": {"coordinates":[-78.86823272709999,43.892780304],"type":"Point"}
}