{
  "type": "Feature",
  "properties": {
    "iso:country":"CA",
    "sg:address":"8610 111 St",
    "sg:city":"Fort Saskatchewan",
    "sg:classifiers":[
        {
            "category":"Building & Trades",
            "subcategory":"Construction",
            "type":"Services"
        }
    ],
    "sg:phone":"+1 780 992 0007",
    "sg:postcode":"T8L 3T4",
    "sg:province":"AB",
    "sg:tags":[
        "field",
        "oil",
        "pile",
        "driving"
    ],
    "wof:name":"Peace Land Piling Ltd",
    "wof:placetype":"venue"
},
  "geometry": {"coordinates":[-113.19585418699999,53.7037353516],"type":"Point"}
}