{
  "type": "Feature",
  "properties": {
    "addr:full":"Midland ON L4R 4L2",
    "addr:postcode":"l4r 4l2",
    "iso:country":"CA",
    "sg:city":"Midland",
    "sg:classifiers":[
        {
            "category":"Personal",
            "subcategory":"Beauty Salon",
            "type":"Services"
        }
    ],
    "sg:phone":"+1 705 527 4691",
    "sg:postcode":"L4R 4L2",
    "sg:province":"ON",
    "wof:name":"Magicuts",
    "wof:placetype":"venue"
},
  "geometry": {"coordinates":[-79.906166,44.735603],"type":"Point"}
}