{
  "type": "Feature",
  "properties": {
    "iso:country":"CA",
    "sg:address":"1110 Victoria St",
    "sg:city":"Kamloops",
    "sg:classifiers":[
        {
            "category":"Home & Garden",
            "subcategory":"Building Materials",
            "type":"Retail Goods"
        }
    ],
    "sg:phone":"+1 250 374 1274",
    "sg:postcode":"V2C 2C5",
    "sg:province":"BC",
    "sg:tags":[
        "glass",
        "window"
    ],
    "wof:name":"Century Glass Ltd",
    "wof:placetype":"venue"
},
  "geometry": {"coordinates":[-120.31364440900001,50.6735916138],"type":"Point"}
}