{
  "type": "Feature",
  "properties": {
    "addr:full":"RR 1 Finch ON K0C 1K0",
    "addr:postcode":"k0c 1k0",
    "addr:street":"Rr 1",
    "iso:country":"CA",
    "sg:address":"RR 1",
    "sg:city":"Finch",
    "sg:classifiers":[
        {
            "category":"Building & Trades",
            "subcategory":"Plumbing",
            "type":"Services"
        }
    ],
    "sg:phone":"+1 613 984 2363",
    "sg:postcode":"K0C 1K0",
    "sg:province":"ON",
    "sg:tags":[
        "tank",
        "septic"
    ],
    "wof:name":"Ted Moran & Sons Ltd",
    "wof:placetype":"venue"
},
  "geometry": {"coordinates":[-75.085975647,45.1436691284],"type":"Point"}
}