{
  "type": "Feature",
  "properties": {
    "addr:full":"Ashcroft BC V0K 1A0",
    "addr:postcode":"v0k 1a0",
    "iso:country":"CA",
    "sg:city":"Ashcroft",
    "sg:classifiers":[
        {
            "category":"Food & Beverages",
            "subcategory":"Liquor & Beverages",
            "type":"Retail Goods"
        }
    ],
    "sg:phone":"+1 250 453 2542",
    "sg:postcode":"V0K 1A0",
    "sg:province":"BC",
    "sg:tags":[
        "store"
    ],
    "wof:name":"Liquor Store-Government",
    "wof:placetype":"venue"
},
  "geometry": {"coordinates":[-121.282730102,50.7242851257],"type":"Point"}
}