{
  "type": "Feature",
  "properties": {
    "addr:full":"8010 50th Ave Drayton Valley AB T7A 1S4",
    "addr:housenumber":"8010",
    "addr:postcode":"t7a 1s4",
    "addr:street":"50Th Ave",
    "iso:country":"CA",
    "sg:address":"8010 50th Ave",
    "sg:city":"Drayton Valley",
    "sg:classifiers":[
        {
            "category":"Mining & Drilling",
            "type":"Manufacturing & Wholesale Goods"
        }
    ],
    "sg:phone":"+1 780 542 4258",
    "sg:postcode":"T7A 1S4",
    "sg:province":"AB",
    "sg:tags":[
        "field",
        "oil"
    ],
    "wof:name":"R & L Pumpjack Svc Ltd",
    "wof:placetype":"venue"
},
  "geometry": {"coordinates":[-115.001122,53.221588],"type":"Point"}
}