{
  "type": "Feature",
  "properties": {
    "iso:country":"CA",
    "sg:address":"525 Welland Ave",
    "sg:city":"St Catharines",
    "sg:classifiers":[
        {
            "category":"Travel",
            "subcategory":"Travel Agent",
            "type":"Entertainment"
        }
    ],
    "sg:phone":"+1 905 704 1234",
    "sg:postcode":"L2M 6P3",
    "sg:province":"ON",
    "sg:tags":[
        "agency",
        "bureau"
    ],
    "wof:name":"Marlin Travel",
    "wof:placetype":"venue"
},
  "geometry": {"coordinates":[-79.2119216919,43.1761016846],"type":"Point"}
}