{
  "type": "Feature",
  "properties": {
    "addr:full":"19301 Av Clark-Graham Baie-D'Urfe QC H9X 3P5",
    "addr:housenumber":"19301",
    "addr:postcode":"h9x 3p5",
    "addr:street":"Av Clark-Graham Baie-D'Urfe",
    "iso:country":"CA",
    "sg:address":"19301 Av Clark-Graham",
    "sg:city":"Baie-D'Urfe",
    "sg:classifiers":[
        {
            "category":"Wholesale",
            "subcategory":"Groceries",
            "type":"Manufacturing & Wholesale Goods"
        }
    ],
    "sg:phone":"+1 514 457 8585",
    "sg:postcode":"H9X 3P5",
    "sg:province":"QC",
    "sg:tags":[
        "food",
        "product"
    ],
    "wof:name":"Best Foods Canada Inc",
    "wof:placetype":"venue"
},
  "geometry": {"coordinates":[-71.495659,46.980713],"type":"Point"}
}