{
  "type": "Feature",
  "properties": {
    "addr:full":"46 138 Rte Baie-Trinite QC G0H 1A0",
    "addr:housenumber":"138",
    "addr:postcode":"g0h 1a0",
    "addr:street":"46;Rte Baie-Trinite",
    "iso:country":"CA",
    "sg:address":"46 138 Rte",
    "sg:city":"Baie-Trinite",
    "sg:classifiers":[
        {
            "category":"Food & Beverages",
            "subcategory":"Groceries & Convenience Stores",
            "type":"Retail Goods"
        }
    ],
    "sg:phone":"+1 418 939 2286",
    "sg:postcode":"G0H 1A0",
    "sg:province":"QC",
    "sg:tags":[
        "grocer"
    ],
    "wof:name":"Epicerie Boucherie Chiasson",
    "wof:placetype":"venue"
},
  "geometry": {"coordinates":[-67.30259700000001,49.421322],"type":"Point"}
}