{
  "type": "Feature",
  "properties": {
    "addr:full":"Scarborough ON M1S 4Z5",
    "addr:postcode":"m1s 4z5",
    "iso:country":"CA",
    "sg:city":"Scarborough",
    "sg:classifiers":[
        {
            "category":"Banks & Credit Unions",
            "subcategory":"Bank",
            "type":"Services"
        }
    ],
    "sg:phone":"+1 416 412 4445",
    "sg:postcode":"M1S 4Z5",
    "sg:province":"ON",
    "sg:tags":[
        "loan",
        "real estate"
    ],
    "wof:name":"Jat Financial",
    "wof:placetype":"venue"
},
  "geometry": {"coordinates":[-79.25721,43.810101],"type":"Point"}
}