{
  "type": "Feature",
  "properties": {
    "addr:full":"3030 Line 8 Bradford ON L3Z 2A5",
    "addr:housenumber":"3030",
    "addr:postcode":"l3z 2a5",
    "addr:street":"Line 8",
    "iso:country":"CA",
    "sg:address":"3030 Line 8",
    "sg:city":"Bradford",
    "sg:classifiers":[
        {
            "category":"Retail",
            "subcategory":"Auto Repair",
            "type":"Services"
        }
    ],
    "sg:phone":"+1 905 775 3801",
    "sg:postcode":"L3Z 2A5",
    "sg:province":"ON",
    "sg:tags":[
        "transmission"
    ],
    "wof:name":"S M Racing Components",
    "wof:placetype":"venue"
},
  "geometry": {"coordinates":[-79.56366,44.114552],"type":"Point"}
}