{
  "type": "Feature",
  "properties": {
    "addr:full":"Saint-Quentin NB E8A 1X9",
    "addr:postcode":"e8a 1x9",
    "iso:country":"CA",
    "sg:city":"Saint-Quentin",
    "sg:classifiers":[
        {
            "category":"Health Services",
            "subcategory":"Hospital",
            "type":"Services"
        }
    ],
    "sg:phone":"+1 506 235 9165",
    "sg:postcode":"E8A 1X9",
    "sg:province":"NB",
    "sg:tags":[
        "mental"
    ],
    "wof:name":"Centre D'Activites LA Ressourc",
    "wof:placetype":"venue"
},
  "geometry": {"coordinates":[-67.39656066889999,47.509311676],"type":"Point"}
}