{
  "type": "Feature",
  "properties": {
    "iso:country":"CA",
    "sg:address":"139 Rue Principale",
    "sg:city":"Lambton",
    "sg:classifiers":[
        {
            "category":"Wholesale",
            "subcategory":"Meat",
            "type":"Manufacturing & Wholesale Goods"
        }
    ],
    "sg:phone":"+1 418 486 2770",
    "sg:postcode":"G0M 1H0",
    "sg:province":"QC",
    "sg:tags":[
        "butchering"
    ],
    "wof:name":"Boucherie Gaulin",
    "wof:placetype":"venue"
},
  "geometry": {"coordinates":[-71.0881271362,45.8424072266],"type":"Point"}
}