{
  "type": "Feature",
  "properties": {
    "addr:full":"Calgary AB T2A 7X6",
    "addr:postcode":"t2a 7x6",
    "iso:country":"CA",
    "sg:city":"Calgary",
    "sg:classifiers":[
        {
            "category":"Shopping",
            "subcategory":"Clothing, Apparel, & Fashions",
            "type":"Retail Goods"
        }
    ],
    "sg:phone":"+1 403 295 8386",
    "sg:postcode":"T2A 7X6",
    "sg:province":"AB",
    "sg:tags":[
        "handbag",
        "shoes"
    ],
    "wof:name":"Jolly Shoes",
    "wof:placetype":"venue"
},
  "geometry": {"coordinates":[-113.982094,51.062008],"type":"Point"}
}