{
  "type": "Feature",
  "properties": {
    "addr:full":"Thornhill ON L4J 8H9",
    "addr:postcode":"l4j 8h9",
    "iso:country":"CA",
    "sg:city":"Thornhill",
    "sg:classifiers":[
        {
            "category":"Professional",
            "subcategory":"Accounting & Tax Preparation",
            "type":"Services"
        }
    ],
    "sg:phone":"+1 905 771 5212",
    "sg:postcode":"L4J 8H9",
    "sg:province":"ON",
    "sg:tags":[
        "accountant",
        "dentist"
    ],
    "wof:name":"Khazak Group Consulting Corp",
    "wof:placetype":"venue"
},
  "geometry": {"coordinates":[-79.4226760864,43.8074836731],"type":"Point"}
}