{
  "type": "Feature",
  "properties": {
    "addr:full":"5300 26 St Vernon BC V1T 8G3",
    "addr:housenumber":"5300",
    "addr:postcode":"v1t 8g3",
    "addr:street":"26 St",
    "iso:country":"CA",
    "sg:address":"5300 26 St",
    "sg:city":"Vernon",
    "sg:classifiers":[
        {
            "category":"Health Services",
            "subcategory":"Chiropractor",
            "type":"Services"
        }
    ],
    "sg:phone":"+1 250 549 1400",
    "sg:postcode":"V1T 8G3",
    "sg:province":"BC",
    "wof:name":"Salmon, Michael DC",
    "wof:placetype":"venue"
},
  "geometry": {"coordinates":[-119.26615099999999,50.285378],"type":"Point"}
}