{
  "type": "Feature",
  "properties": {
    "addr:full":"59 Lampman Lane Barrie ON L4N 5G4",
    "addr:housenumber":"59",
    "addr:postcode":"l4n 5g4",
    "addr:street":"Lampman Lane",
    "iso:country":"CA",
    "sg:address":"59 Lampman Lane",
    "sg:city":"Barrie",
    "sg:classifiers":[
        {
            "category":"Recreation",
            "type":"Entertainment"
        }
    ],
    "sg:phone":"+1 705 739 4224",
    "sg:postcode":"L4N 5G4",
    "sg:province":"ON",
    "sg:tags":[
        "government",
        "hall",
        "auditorium"
    ],
    "wof:name":"Barrie Lampman Lane Comm Ctr",
    "wof:placetype":"venue"
},
  "geometry": {"coordinates":[-79.72605900000001,44.39135],"type":"Point"}
}