{
  "type": "Feature",
  "properties": {
    "addr:full":"17 Phillip Dr Deer Lake NL A8A 1Y7",
    "addr:housenumber":"17",
    "addr:postcode":"a8a 1y7",
    "addr:street":"Phillip Dr Deer",
    "iso:country":"CA",
    "sg:address":"17 Phillip Dr",
    "sg:city":"Deer Lake",
    "sg:classifiers":[
        {
            "category":"Travel",
            "subcategory":"Hotels & Motels",
            "type":"Entertainment"
        }
    ],
    "sg:phone":"+1 709 635 3723",
    "sg:postcode":"A8A 1Y7",
    "sg:province":"NL",
    "sg:tags":[
        "breakfast",
        "accommodation",
        "bed"
    ],
    "wof:name":"Watkins House Bed & Breakfast",
    "wof:placetype":"venue"
},
  "geometry": {"coordinates":[-57.423664093,49.1753387451],"type":"Point"}
}