{
  "type": "Feature",
  "properties": {
    "addr:full":"PO Box 1 Stanbridge East QC J0J 2H0",
    "addr:housenumber":"po;1",
    "addr:postcode":"j0j 2h0",
    "addr:street":"Box",
    "iso:country":"CA",
    "sg:address":"PO Box 1",
    "sg:city":"Stanbridge East",
    "sg:classifiers":[
        {
            "category":"Organizations",
            "subcategory":"Religious Organization",
            "type":"Services"
        }
    ],
    "sg:phone":"+1 514 248 3257",
    "sg:postcode":"J0J 2H0",
    "sg:province":"QC",
    "sg:tags":[
        "church"
    ],
    "wof:name":"St James the Apostle Church",
    "wof:placetype":"venue"
},
  "geometry": {"coordinates":[-72.912537,45.117504],"type":"Point"}
}