{
  "type": "Feature",
  "properties": {
    "addr:full":"3761 Navatanee Dr Kamloops BC V2H 1S1",
    "addr:housenumber":"3761",
    "addr:postcode":"bc v2h 1s1",
    "addr:street":"Navatanee Dr",
    "iso:country":"CA",
    "sg:address":"3761 Navatanee Dr",
    "sg:city":"Kamloops",
    "sg:classifiers":[
        {
            "category":"Building & Trades",
            "subcategory":"Plumbing",
            "type":"Services"
        }
    ],
    "sg:phone":"+1 250 573 3273",
    "sg:postcode":"V2H 1S1",
    "sg:province":"BC",
    "sg:tags":[
        "air",
        "conditioning",
        "contractor",
        "system",
        "heating"
    ],
    "wof:name":"Geothermal Heating Specialties",
    "wof:placetype":"venue"
},
  "geometry": {"coordinates":[-120.337891,50.676125],"type":"Point"}
}