{
  "type": "Feature",
  "properties": {
    "addr:full":"402 3rd Ave S Kamsack SK S0A 1S0",
    "addr:housenumber":"402",
    "addr:postcode":"s0a 1s0",
    "addr:street":"3Rd Ave S Kamsack",
    "iso:country":"CA",
    "sg:address":"402 3rd Ave S",
    "sg:city":"Kamsack",
    "sg:classifiers":[
        {
            "category":"Insurance",
            "subcategory":"Insurance Agent",
            "type":"Services"
        }
    ],
    "sg:phone":"+1 306 542 2565",
    "sg:postcode":"S0A 1S0",
    "sg:province":"SK",
    "wof:name":"Cottenie & Gardner Inc",
    "wof:placetype":"venue"
},
  "geometry": {"coordinates":[-101.89911651600001,51.5672531128],"type":"Point"}
}