{
  "type": "Feature",
  "properties": {
    "iso:country":"CA",
    "sg:city":"Toronto",
    "sg:classifiers":[
        {
            "category":"Health Services",
            "subcategory":"Health Practitioner",
            "type":"Services"
        }
    ],
    "sg:phone":"+1 416 924 0757",
    "sg:postcode":"M4V 1R1",
    "sg:province":"ON",
    "sg:tags":[
        "psychotherapist"
    ],
    "wof:name":"Simms, Joel",
    "wof:placetype":"venue"
},
  "geometry": {"coordinates":[-79.402672,43.686531],"type":"Point"}
}