{
  "type": "Feature",
  "properties": {
    "iso:country":"CA",
    "sg:address":"146 Rte Du President-Kennedy",
    "sg:city":"Levis",
    "sg:classifiers":[
        {
            "category":"Restaurant",
            "type":"Food & Drink"
        }
    ],
    "sg:phone":"+1 418 833 2221",
    "sg:postcode":"G6V 6C9",
    "sg:province":"QC",
    "wof:name":"Restaurant Pizza Delice",
    "wof:placetype":"venue"
},
  "geometry": {"coordinates":[-71.164390564,46.7867698669],"type":"Point"}
}