{
  "type": "Feature",
  "properties": {
    "addr:full":"1068 St Clair Ave W Toronto ON M6E 1A5",
    "addr:housenumber":"1068",
    "addr:postcode":"m6e 1a5",
    "addr:street":"St Clair Ave W",
    "iso:country":"CA",
    "sg:address":"1068 St Clair Ave W",
    "sg:city":"Toronto",
    "sg:classifiers":[
        {
            "category":"Shopping",
            "subcategory":"Florist",
            "type":"Retail Goods"
        }
    ],
    "sg:phone":"+1 416 651 3810",
    "sg:postcode":"M6E 1A5",
    "sg:province":"ON",
    "wof:name":"Sina Flowers",
    "wof:placetype":"venue"
},
  "geometry": {"coordinates":[-79.43946800000001,43.678883],"type":"Point"}
}