{
  "type": "Feature",
  "properties": {
    "addr:full":"482 Boundary Rd E Pembroke ON K8A 6L5",
    "addr:housenumber":"482",
    "addr:postcode":"k8a 6l5",
    "addr:street":"Boundary Rd E",
    "iso:country":"CA",
    "sg:address":"482 Boundary Rd E",
    "sg:city":"Pembroke",
    "sg:classifiers":[
        {
            "category":"Freight",
            "type":"Transportation"
        }
    ],
    "sg:phone":"+1 613 635 7350",
    "sg:postcode":"K8A 6L5",
    "sg:province":"ON",
    "sg:tags":[
        "delivery"
    ],
    "wof:name":"Tom's Delivery",
    "wof:placetype":"venue"
},
  "geometry": {"coordinates":[-77.1266784668,45.8127174377],"type":"Point"}
}