{
  "type": "Feature",
  "properties": {
    "addr:full":"977 Golf Links Rd Ancaster ON L9K 1K1",
    "addr:housenumber":"977",
    "addr:postcode":"l9k 1k1",
    "addr:street":"Golf Links Rd",
    "iso:country":"CA",
    "sg:address":"977 Golf Links Rd",
    "sg:city":"Ancaster",
    "sg:classifiers":[
        {
            "category":"Food & Beverages",
            "subcategory":"Bakery",
            "type":"Retail Goods"
        }
    ],
    "sg:phone":"+1 905 304 3355",
    "sg:postcode":"L9K 1K1",
    "sg:province":"ON",
    "sg:tags":[
        "doughnut"
    ],
    "wof:name":"Tim Hortons",
    "wof:placetype":"venue"
},
  "geometry": {"coordinates":[-79.94201700000001,43.227646],"type":"Point"}
}