{
  "type": "Feature",
  "properties": {
    "addr:full":"11415 Boul DE LA Riviere-Des-P Montreal QC H1C 1P8",
    "addr:housenumber":"11415",
    "addr:postcode":"h1c 1p8",
    "addr:street":"Boul De La Riviere-Des-P",
    "iso:country":"CA",
    "sg:address":"11415 Boul DE LA Riviere-Des-P",
    "sg:city":"Montreal",
    "sg:classifiers":[
        {
            "category":"Building & Trades",
            "subcategory":"Electrical",
            "type":"Services"
        }
    ],
    "sg:phone":"+1 514 648 2409",
    "sg:postcode":"H1C 1P8",
    "sg:province":"QC",
    "sg:tags":[
        "electric",
        "contractor"
    ],
    "wof:name":"Salvitec Electrique Cie Ltee",
    "wof:placetype":"venue"
},
  "geometry": {"coordinates":[-73.55439,45.512287],"type":"Point"}
}