{
  "type": "Feature",
  "properties": {
    "addr:full":"201 Leslie St Toronto ON M4M 3C6",
    "addr:housenumber":"201",
    "addr:postcode":"m4m 3c6",
    "addr:street":"Leslie St",
    "iso:country":"CA",
    "sg:address":"201 Leslie St",
    "sg:city":"Toronto",
    "sg:classifiers":[
        {
            "category":"Manufacturing",
            "subcategory":"Printing",
            "type":"Manufacturing & Wholesale Goods"
        }
    ],
    "sg:phone":"+1 416 465 7554",
    "sg:postcode":"M4M 3C6",
    "sg:province":"ON",
    "sg:tags":[
        "newspaper"
    ],
    "wof:name":"Etc Community News",
    "wof:placetype":"venue"
},
  "geometry": {"coordinates":[-79.3287124634,43.6594047546],"type":"Point"}
}