{
  "type": "Feature",
  "properties": {
    "addr:full":"1026 N Muldrew Lake Rd Gravenhurst ON P1P 1T8",
    "addr:housenumber":"1026",
    "addr:postcode":"p1p 1t8",
    "addr:street":"N Muldrew Lake Rd",
    "iso:country":"CA",
    "sg:address":"1026 N Muldrew Lake Rd",
    "sg:city":"Gravenhurst",
    "sg:classifiers":[
        {
            "category":"Home & Garden",
            "subcategory":"Home Furnishings",
            "type":"Retail Goods"
        }
    ],
    "sg:phone":"+1 705 687 7890",
    "sg:postcode":"P1P 1T8",
    "sg:province":"ON",
    "sg:tags":[
        "pottery"
    ],
    "wof:name":"Muskoka Bay Pottery",
    "wof:placetype":"venue"
},
  "geometry": {"coordinates":[-79.3913116455,44.9151420593],"type":"Point"}
}