{
  "type": "Feature",
  "properties": {
    "iso:country":"CA",
    "sg:address":"42 Cabot Cres",
    "sg:city":"Lower Sackville",
    "sg:classifiers":[
        {
            "category":"Social Services",
            "type":"Services"
        }
    ],
    "sg:phone":"+1 902 865 7872",
    "sg:postcode":"B4C 3L3",
    "sg:province":"NS",
    "sg:tags":[
        "organization",
        "welfare"
    ],
    "wof:name":"Sackville United Soccor Assn",
    "wof:placetype":"venue"
},
  "geometry": {"coordinates":[-63.6577072144,44.7742042542],"type":"Point"}
}