{
  "type": "Feature",
  "properties": {
    "addr:full":"218 Church St Comox BC V9M 2G3",
    "addr:housenumber":"218",
    "addr:postcode":"v9m 2g3",
    "addr:street":"Church St",
    "iso:country":"CA",
    "sg:address":"218 Church St",
    "sg:city":"Comox",
    "sg:classifiers":[
        {
            "category":"Organizations",
            "subcategory":"Religious Organization",
            "type":"Services"
        }
    ],
    "sg:phone":"+1 250 339 1212",
    "sg:postcode":"V9M 2G3",
    "sg:province":"BC",
    "sg:tags":[
        "church"
    ],
    "wof:name":"Africa Community Technical Svc",
    "wof:placetype":"venue"
},
  "geometry": {"coordinates":[-124.927085877,49.674823761],"type":"Point"}
}