{
  "type": "Feature",
  "properties": {
    "addr:full":"950 Parkinson Rd Woodstock ON N4S 7W3",
    "addr:housenumber":"950",
    "addr:postcode":"n4s 7w3",
    "addr:street":"Parkinson Rd",
    "iso:country":"CA",
    "sg:address":"950 Parkinson Rd",
    "sg:city":"Woodstock",
    "sg:classifiers":[
        {
            "category":"Building & Trades",
            "subcategory":"Electrical",
            "type":"Services"
        }
    ],
    "sg:phone":"+1 519 537 7622",
    "sg:postcode":"N4S 7W3",
    "sg:province":"ON",
    "sg:tags":[
        "electric",
        "contractor"
    ],
    "wof:name":"Denby Electric Ltd",
    "wof:placetype":"venue"
},
  "geometry": {"coordinates":[-80.731064,43.121284],"type":"Point"}
}