{
  "type": "Feature",
  "properties": {
    "addr:full":"475 107E Rue Shawinigan-Sud QC G9P 2K3",
    "addr:housenumber":"475",
    "addr:postcode":"g9p 2k3",
    "addr:street":"107E Rue Shawinigan-Sud",
    "iso:country":"CA",
    "sg:address":"475 107E Rue",
    "sg:city":"Shawinigan-Sud",
    "sg:classifiers":[
        {
            "category":"Building & Trades",
            "subcategory":"Construction",
            "type":"Services"
        }
    ],
    "sg:phone":"+1 819 537 5003",
    "sg:postcode":"G9P 2K3",
    "sg:province":"QC",
    "sg:tags":[
        "general",
        "contractor"
    ],
    "wof:name":"Fondations Serge Robitaille",
    "wof:placetype":"venue"
},
  "geometry": {"coordinates":[-72.7559432983,46.5268592834],"type":"Point"}
}