{
  "type": "Feature",
  "properties": {
    "iso:country":"CA",
    "sg:address":"154 Rue Saint-Jacques O",
    "sg:city":"Princeville",
    "sg:classifiers":[
        {
            "category":"Shopping",
            "subcategory":"Florist",
            "type":"Retail Goods"
        }
    ],
    "sg:phone":"+1 819 364 3331",
    "sg:postcode":"G6L 4Y6",
    "sg:province":"QC",
    "wof:name":"Fleuriste Rousseau Enr",
    "wof:placetype":"venue"
},
  "geometry": {"coordinates":[-71.8730545044,46.1738815308],"type":"Point"}
}