{
  "type": "Feature",
  "properties": {
    "iso:country":"CA",
    "sg:address":"100 Battery Point",
    "sg:city":"Lunenburg",
    "sg:classifiers":[
        {
            "category":"Manufacturing",
            "subcategory":"Food",
            "type":"Manufacturing & Wholesale Goods"
        }
    ],
    "sg:phone":"+1 902 634 8811",
    "sg:postcode":"B0J 2C0",
    "sg:province":"NS",
    "sg:tags":[
        "packer",
        "fish"
    ],
    "wof:name":"High Liner Foods Inc",
    "wof:placetype":"venue"
},
  "geometry": {"coordinates":[-64.3184432983,44.3772125244],"type":"Point"}
}