{
  "type": "Feature",
  "properties": {
    "addr:full":"75 Urquhart Ave Moncton NB E1H 2R4",
    "addr:housenumber":"75",
    "addr:postcode":"e1h 2r4",
    "addr:street":"Urquhart Ave",
    "iso:country":"CA",
    "sg:address":"75 Urquhart Ave",
    "sg:city":"Moncton",
    "sg:classifiers":[
        {
            "category":"Retail",
            "subcategory":"Auto Rental",
            "type":"Services"
        }
    ],
    "sg:phone":"+1 506 854 2225",
    "sg:postcode":"E1H 2R4",
    "sg:province":"NB",
    "sg:tags":[
        "renting",
        "leasing",
        "trailer"
    ],
    "wof:name":"Trans East Trailers Ltd",
    "wof:placetype":"venue"
},
  "geometry": {"coordinates":[-64.755745,46.129063],"type":"Point"}
}