{
  "type": "Feature",
  "properties": {
    "addr:full":"Montreal QC H2T 1X3",
    "addr:postcode":"h2t 1x3",
    "iso:country":"CA",
    "sg:city":"Montreal",
    "sg:classifiers":[
        {
            "category":"Professional",
            "type":"Services"
        }
    ],
    "sg:phone":"+1 514 289 8572",
    "sg:postcode":"H2T 1X3",
    "sg:province":"QC",
    "sg:tags":[
        "arts",
        "artist"
    ],
    "wof:name":"Rosie Godbout Enrg",
    "wof:placetype":"venue"
},
  "geometry": {"coordinates":[-73.595268,45.526089],"type":"Point"}
}