{
  "type": "Feature",
  "properties": {
    "iso:country":"CA",
    "sg:address":"275 Boul Sainte-Rose",
    "sg:city":"Laval",
    "sg:classifiers":[
        {
            "category":"Personal",
            "subcategory":"Beauty Salon",
            "type":"Services"
        }
    ],
    "sg:phone":"+1 450 625 6007",
    "sg:postcode":"H7L 3X7",
    "sg:province":"QC",
    "wof:name":"Salon Du Manoir",
    "wof:placetype":"venue"
},
  "geometry": {"coordinates":[-73.74463653559999,45.5515670776],"type":"Point"}
}