{
  "type": "Feature",
  "properties": {
    "addr:full":"5013 50 St Red Deer AB T4N 1Y2",
    "addr:housenumber":"5013",
    "addr:postcode":"t4n 1y2",
    "addr:street":"50 St",
    "iso:country":"CA",
    "sg:address":"5013 50 St",
    "sg:city":"Red Deer",
    "sg:classifiers":[
        {
            "category":"Shopping",
            "subcategory":"Clothing, Apparel, & Fashions",
            "type":"Retail Goods"
        }
    ],
    "sg:phone":"+1 403 346 2291",
    "sg:postcode":"T4N 1Y2",
    "sg:province":"AB",
    "sg:tags":[
        "fur",
        "business"
    ],
    "wof:name":"Sisson Furs Ltd",
    "wof:placetype":"venue"
},
  "geometry": {"coordinates":[-113.816062927,52.2688674927],"type":"Point"}
}