{
  "type": "Feature",
  "properties": {
    "addr:full":"6282 Spooner Rd Likely BC V0L 1N0",
    "addr:housenumber":"6282",
    "addr:postcode":"v0l 1n0",
    "addr:street":"Spooner Rd",
    "iso:country":"CA",
    "sg:address":"6282 Spooner Rd",
    "sg:city":"Likely",
    "sg:classifiers":[
        {
            "category":"Building & Trades",
            "subcategory":"Construction",
            "type":"Services"
        }
    ],
    "sg:phone":"+1 250 790 2458",
    "sg:postcode":"V0L 1N0",
    "sg:province":"BC",
    "sg:tags":[
        "general",
        "contractor"
    ],
    "wof:name":"Sherwood Forest Contracting",
    "wof:placetype":"venue"
},
  "geometry": {"coordinates":[-121.569847,52.617023],"type":"Point"}
}