{
  "type": "Feature",
  "properties": {
    "addr:full":"22 Lavinia St Fort Erie ON L2A 2C5",
    "addr:housenumber":"22",
    "addr:postcode":"l2a 2c5",
    "addr:street":"Lavinia St",
    "iso:country":"CA",
    "sg:address":"22 Lavinia St",
    "sg:city":"Fort Erie",
    "sg:classifiers":[
        {
            "category":"Retail",
            "subcategory":"Auto Repair",
            "type":"Services"
        }
    ],
    "sg:phone":"+1 905 871 5512",
    "sg:postcode":"L2A 2C5",
    "sg:province":"ON",
    "sg:tags":[
        "body",
        "automobile",
        "painting"
    ],
    "wof:name":"2 Guys Auto Body",
    "wof:placetype":"venue"
},
  "geometry": {"coordinates":[-78.910622,42.915691],"type":"Point"}
}