{
  "type": "Feature",
  "properties": {
    "addr:full":"28525 Dewdney Trunk Rd Maple Ridge BC V2W 1M1",
    "addr:housenumber":"28525",
    "addr:postcode":"v2w 1m1",
    "addr:street":"Dewdney Trunk Rd",
    "iso:country":"CA",
    "sg:address":"28525 Dewdney Trunk Rd",
    "sg:city":"Maple Ridge",
    "sg:classifiers":[
        {
            "category":"Building & Trades",
            "subcategory":"Construction",
            "type":"Services"
        }
    ],
    "sg:phone":"+1 604 462 1683",
    "sg:postcode":"V2W 1M1",
    "sg:province":"BC",
    "sg:tags":[
        "painter"
    ],
    "wof:name":"Iron Mountain Painting Ltd",
    "wof:placetype":"venue"
},
  "geometry": {"coordinates":[-122.431107,49.220146],"type":"Point"}
}