{
  "type": "Feature",
  "properties": {
    "addr:full":"Brigus NL A0A 1K0",
    "addr:postcode":"a0a 1k0",
    "iso:country":"CA",
    "sg:city":"Brigus",
    "sg:classifiers":[
        {
            "category":"Retail",
            "subcategory":"Funeral Services",
            "type":"Services"
        }
    ],
    "sg:phone":"+1 709 528 4821",
    "sg:postcode":"A0A 1K0",
    "sg:province":"NL",
    "sg:tags":[
        "director"
    ],
    "wof:name":"Broughton's Funeral Home",
    "wof:placetype":"venue"
},
  "geometry": {"coordinates":[-53.232132,47.530632],"type":"Point"}
}