{
  "type": "Feature",
  "properties": {
    "iso:country":"CA",
    "sg:city":"Brampton",
    "sg:classifiers":[
        {
            "category":"Retail",
            "subcategory":"Auto Repair",
            "type":"Services"
        }
    ],
    "sg:phone":"+1 905 799 6364",
    "sg:postcode":"L6T 4Z6",
    "sg:province":"ON",
    "sg:tags":[
        "muffler",
        "exhaust",
        "system"
    ],
    "wof:name":"Ksvg Ganesh Exhaust Inc",
    "wof:placetype":"venue"
},
  "geometry": {"coordinates":[-79.692917,43.693207],"type":"Point"}
}