{
  "type": "Feature",
  "properties": {
    "addr:full":"111 Sun Row Dr Etobicoke ON M9P 3J3",
    "addr:housenumber":"111",
    "addr:postcode":"m9p 3j3",
    "addr:street":"Sun Row Dr",
    "iso:country":"CA",
    "sg:address":"111 Sun Row Dr",
    "sg:city":"Etobicoke",
    "sg:classifiers":[
        {
            "category":"Education",
            "subcategory":"School",
            "type":"Public Place"
        }
    ],
    "sg:phone":"+1 416 393 5391",
    "sg:postcode":"M9P 3J3",
    "sg:province":"ON",
    "wof:name":"Father Serra School",
    "wof:placetype":"venue"
},
  "geometry": {"coordinates":[-79.53729199999999,43.685478],"type":"Point"}
}