{
  "type": "Feature",
  "properties": {
    "addr:full":"Sainte-Paule QC G0J 3C0",
    "addr:postcode":"g0j 3c0",
    "iso:country":"CA",
    "sg:city":"Sainte-Paule",
    "sg:classifiers":[
        {
            "category":"Government",
            "subcategory":"Office",
            "type":"Public Place"
        }
    ],
    "sg:phone":"+1 418 737 4591",
    "sg:postcode":"G0J 3C0",
    "sg:province":"QC",
    "sg:tags":[
        "village"
    ],
    "wof:name":"Ste-Paule Garage",
    "wof:placetype":"venue"
},
  "geometry": {"coordinates":[-67.55052947999999,48.6666793823],"type":"Point"}
}