{
  "type": "Feature",
  "properties": {
    "addr:full":"Sainte-Henedine QC G0S 2R0",
    "addr:postcode":"g0s 2r0",
    "iso:country":"CA",
    "sg:city":"Sainte-Henedine",
    "sg:classifiers":[
        {
            "category":"Organizations",
            "subcategory":"Professional Association",
            "type":"Services"
        }
    ],
    "sg:phone":"+1 418 935 3531",
    "sg:postcode":"G0S 2R0",
    "sg:province":"QC",
    "sg:tags":[
        "club"
    ],
    "wof:name":"Club DE Fertilisation Inc",
    "wof:placetype":"venue"
},
  "geometry": {"coordinates":[-70.9851226807,46.5578842163],"type":"Point"}
}