{
  "type": "Feature",
  "properties": {
    "addr:full":"Montreal QC H2X 2S6",
    "addr:postcode":"h2x 2s6",
    "iso:country":"CA",
    "sg:city":"Montreal",
    "sg:classifiers":[
        {
            "category":"Real Estate",
            "subcategory":"Real Estate Agent",
            "type":"Services"
        }
    ],
    "sg:phone":"+1 514 875 1545",
    "sg:postcode":"H2X 2S6",
    "sg:province":"QC",
    "sg:tags":[
        "management"
    ],
    "wof:name":"9096-5971 Quebec Inc",
    "wof:placetype":"venue"
},
  "geometry": {"coordinates":[-73.562614,45.509514],"type":"Point"}
}