{
  "type": "Feature",
  "properties": {
    "addr:full":"Calgary AB T2P 4X2",
    "addr:postcode":"t2p 4x2",
    "iso:country":"CA",
    "sg:city":"Calgary",
    "sg:classifiers":[
        {
            "category":"Professional",
            "type":"Services"
        }
    ],
    "sg:phone":"+1 403 262 5247",
    "sg:postcode":"T2P 4X2",
    "sg:province":"AB",
    "sg:tags":[
        "geophysical"
    ],
    "wof:name":"Integrated Geophysical Cnsltnt",
    "wof:placetype":"venue"
},
  "geometry": {"coordinates":[-114.07147999999999,51.052341],"type":"Point"}
}