{
  "type": "Feature",
  "properties": {
    "addr:full":"321 Royale St Malartic QC J0Y 1Z0",
    "addr:housenumber":"321",
    "addr:postcode":"j0y 1z0",
    "addr:street":"Royale St",
    "iso:country":"CA",
    "sg:address":"321 Royale St",
    "sg:city":"Malartic",
    "sg:classifiers":[
        {
            "category":"Wholesale",
            "subcategory":"Machinery & Supplies",
            "type":"Manufacturing & Wholesale Goods"
        }
    ],
    "sg:phone":"+1 819 757 3225",
    "sg:postcode":"J0Y 1Z0",
    "sg:province":"QC",
    "sg:tags":[
        "equipment",
        "mining"
    ],
    "wof:name":"Trahan International",
    "wof:placetype":"venue"
},
  "geometry": {"coordinates":[-78.1118469238,48.1321220398],"type":"Point"}
}