{
  "type": "Feature",
  "properties": {
    "addr:full":"Montreal QC H1N 1C7",
    "addr:postcode":"h1n 1c7",
    "iso:country":"CA",
    "sg:city":"Montreal",
    "sg:classifiers":[
        {
            "category":"Health Services",
            "subcategory":"Doctor",
            "type":"Services"
        }
    ],
    "sg:phone":"+1 514 255 8320",
    "sg:postcode":"H1N 1C7",
    "sg:province":"QC",
    "sg:tags":[
        "dentist"
    ],
    "wof:name":"Tremblay, Robert DDS",
    "wof:placetype":"venue"
},
  "geometry": {"coordinates":[-73.54310599999999,45.58305],"type":"Point"}
}