{
  "type": "Feature",
  "properties": {
    "addr:full":"1658 Hwy 2 Milford Station NS B0N 1Y0",
    "addr:housenumber":"1658",
    "addr:postcode":"b0n 1y0",
    "addr:street":"Hwy 2 Milford",
    "iso:country":"CA",
    "sg:address":"1658 Hwy 2",
    "sg:city":"Milford Station",
    "sg:classifiers":[
        {
            "category":"Building & Trades",
            "subcategory":"Electrical",
            "type":"Services"
        }
    ],
    "sg:phone":"+1 902 758 3273",
    "sg:postcode":"B0N 1Y0",
    "sg:province":"NS",
    "sg:tags":[
        "electric",
        "contractor"
    ],
    "wof:name":"George Bergman Electric CO Ltd",
    "wof:placetype":"venue"
},
  "geometry": {"coordinates":[-63.43364,45.051144],"type":"Point"}
}