{
  "type": "Feature",
  "properties": {
    "addr:full":"764 Rue DE Saint-Jovite Mont-Tremblant QC J8E 3J8",
    "addr:housenumber":"764",
    "addr:postcode":"j8e 3j8",
    "addr:street":"Rue De Saint-Jovite",
    "iso:country":"CA",
    "sg:address":"764 Rue DE Saint-Jovite",
    "sg:city":"Mont-Tremblant",
    "sg:classifiers":[
        {
            "category":"Shopping",
            "subcategory":"Hobbies, Toys, & Games",
            "type":"Retail Goods"
        }
    ],
    "sg:phone":"+1 819 425 3270",
    "sg:postcode":"J8E 3J8",
    "sg:province":"QC",
    "wof:name":"Temps Libres Jeu & Hobby",
    "wof:placetype":"venue"
},
  "geometry": {"coordinates":[-74.5894393921,46.1185379028],"type":"Point"}
}