{
  "type": "Feature",
  "properties": {
    "addr:full":"4721 47 Ave Leduc AB T9E 7J4",
    "addr:housenumber":"4721",
    "addr:postcode":"t9e 7j4",
    "addr:street":"47 Ave",
    "iso:country":"CA",
    "sg:address":"4721 47 Ave",
    "sg:city":"Leduc",
    "sg:classifiers":[
        {
            "category":"Health Services",
            "subcategory":"Doctor",
            "type":"Services"
        }
    ],
    "sg:phone":"+1 780 986 1400",
    "sg:postcode":"T9E 7J4",
    "sg:province":"AB",
    "sg:tags":[
        "physician",
        "surgeon"
    ],
    "wof:name":"Leduc Medical Arts Clinic",
    "wof:placetype":"venue"
},
  "geometry": {"coordinates":[-113.545959473,53.2622108459],"type":"Point"}
}