{
  "type": "Feature",
  "properties": {
    "addr:full":"3235 Boul Saint-Martin E Laval QC H7E 5G8",
    "addr:housenumber":"3235",
    "addr:postcode":"h7e 5g8",
    "addr:street":"Boul Saint-Martin E",
    "iso:country":"CA",
    "sg:address":"3235 Boul Saint-Martin E",
    "sg:city":"Laval",
    "sg:classifiers":[
        {
            "category":"Organizations",
            "subcategory":"Professional Association",
            "type":"Services"
        }
    ],
    "sg:phone":"+1 450 664 4718",
    "sg:postcode":"H7E 5G8",
    "sg:province":"QC",
    "sg:tags":[
        "club"
    ],
    "wof:name":"Club D'Observateurs D'Oiseaux",
    "wof:placetype":"venue"
},
  "geometry": {"coordinates":[-73.67756652830001,45.6049728394],"type":"Point"}
}