{
  "type": "Feature",
  "properties": {
    "addr:full":"4800 Dundas St W #100 Etobicoke ON M9A 1B1",
    "addr:housenumber":"4800",
    "addr:postcode":"m9a 1b1",
    "addr:street":"Dundas St W # 100",
    "iso:country":"CA",
    "sg:address":"4800 Dundas St W #100",
    "sg:city":"Etobicoke",
    "sg:classifiers":[
        {
            "category":"Restaurant",
            "type":"Food & Drink"
        }
    ],
    "sg:phone":"+1 416 231 6701",
    "sg:postcode":"M9A 1B1",
    "sg:province":"ON",
    "wof:name":"Pinocchio Dining Lounge",
    "wof:placetype":"venue"
},
  "geometry": {"coordinates":[-79.526459,43.651367],"type":"Point"}
}