{
  "type": "Feature",
  "properties": {
    "addr:full":"56 Route 776 Grand Manan NB E5G 1A1",
    "addr:housenumber":"56",
    "addr:postcode":"e5g 1a1",
    "addr:street":"Route 776",
    "iso:country":"CA",
    "sg:address":"56 Route 776",
    "sg:city":"Grand Manan",
    "sg:classifiers":[
        {
            "category":"Shopping",
            "subcategory":"Hobbies, Toys, & Games",
            "type":"Retail Goods"
        }
    ],
    "sg:phone":"+1 506 662 3625",
    "sg:postcode":"E5G 1A1",
    "sg:province":"NB",
    "sg:tags":[
        "craft",
        "supply"
    ],
    "wof:name":"Island Arts",
    "wof:placetype":"venue"
},
  "geometry": {"coordinates":[-66.84721399999999,44.648453],"type":"Point"}
}