{
  "type": "Feature",
  "properties": {
    "iso:country":"CA",
    "sg:city":"Calgary",
    "sg:classifiers":[
        {
            "category":"Wholesale",
            "subcategory":"Stationery",
            "type":"Manufacturing & Wholesale Goods"
        }
    ],
    "sg:phone":"+1 403 253 3466",
    "sg:postcode":"T2H 2J7",
    "sg:province":"AB",
    "sg:tags":[
        "school",
        "supply"
    ],
    "wof:name":"Christies Office & School Supl",
    "wof:placetype":"venue"
},
  "geometry": {"coordinates":[-114.037933,50.995171],"type":"Point"}
}