{
  "type": "Feature",
  "properties": {
    "iso:country":"CA",
    "sg:address":"2382 Proton Ave",
    "sg:city":"Gull Lake",
    "sg:classifiers":[
        {
            "category":"Professional",
            "subcategory":"Lawyer & Legal Services",
            "type":"Services"
        }
    ],
    "sg:phone":"+1 306 672 4404",
    "sg:postcode":"S0N 1A0",
    "sg:province":"SK",
    "sg:tags":[
        "attorney"
    ],
    "wof:name":"Mac Bean Tessem",
    "wof:placetype":"venue"
},
  "geometry": {"coordinates":[-108.483924866,50.0979690552],"type":"Point"}
}