{
  "type": "Feature",
  "properties": {
    "iso:country":"CA",
    "sg:address":"700 University Ave",
    "sg:city":"Toronto",
    "sg:classifiers":[
        {
            "category":"Professional",
            "subcategory":"Printing & Photocopies",
            "type":"Services"
        }
    ],
    "sg:phone":"+1 416 323 8080",
    "sg:postcode":"M5G 1Z5",
    "sg:province":"ON",
    "sg:tags":[
        "duplicating",
        "copying"
    ],
    "wof:name":"Printing House",
    "wof:placetype":"venue"
},
  "geometry": {"coordinates":[-79.39036560060001,43.6587524414],"type":"Point"}
}