{
  "type": "Feature",
  "properties": {
    "addr:full":"1425 Boul Saint-Joseph Drummondville QC J2C 2E5",
    "addr:housenumber":"1425",
    "addr:postcode":"j2c 2e5",
    "addr:street":"Boul Saint-Joseph",
    "iso:country":"CA",
    "sg:address":"1425 Boul Saint-Joseph",
    "sg:city":"Drummondville",
    "sg:classifiers":[
        {
            "category":"Home & Garden",
            "subcategory":"Home Furnishings",
            "type":"Retail Goods"
        }
    ],
    "sg:phone":"+1 819 478 4983",
    "sg:postcode":"J2C 2E5",
    "sg:province":"QC",
    "sg:tags":[
        "window",
        "covering"
    ],
    "wof:name":"Marche Du Store",
    "wof:placetype":"venue"
},
  "geometry": {"coordinates":[-72.499725,45.884411],"type":"Point"}
}