{
  "type": "Feature",
  "properties": {
    "addr:full":"1837 Lansdowne St W # 2 Peterborough ON K9K 1R4",
    "addr:housenumber":"1837",
    "addr:postcode":"k9k 1r4",
    "addr:street":"Lansdowne St W # 2",
    "iso:country":"CA",
    "sg:address":"1837 Lansdowne St W # 2",
    "sg:city":"Peterborough",
    "sg:classifiers":[
        {
            "category":"Home & Garden",
            "subcategory":"Household Appliances",
            "type":"Retail Goods"
        }
    ],
    "sg:phone":"+1 705 876 1818",
    "sg:postcode":"K9K 1R4",
    "sg:province":"ON",
    "wof:name":"Quan Tv & Appliances",
    "wof:placetype":"venue"
},
  "geometry": {"coordinates":[-78.3735046387,44.2750358582],"type":"Point"}
}