{
  "type": "Feature",
  "properties": {
    "iso:country":"CA",
    "sg:address":"599 Rue Le Breton",
    "sg:city":"Longueuil",
    "sg:classifiers":[
        {
            "category":"Building & Trades",
            "subcategory":"Construction",
            "type":"Services"
        }
    ],
    "sg:phone":"+1 450 679 6034",
    "sg:postcode":"J4G 1R9",
    "sg:province":"QC",
    "sg:tags":[
        "concrete",
        "contractor"
    ],
    "wof:name":"Aubert Yvon Construction Inc",
    "wof:placetype":"venue"
},
  "geometry": {"coordinates":[-73.4715957642,45.5671730042],"type":"Point"}
}