{
  "type": "Feature",
  "properties": {
    "addr:full":"33 Glen Cameron Rd # 1 Thornhill ON L3T 1N9",
    "addr:housenumber":"33",
    "addr:postcode":"l3t 1n9",
    "addr:street":"Glen Cameron Rd # 1",
    "iso:country":"CA",
    "sg:address":"33 Glen Cameron Rd # 1",
    "sg:city":"Thornhill",
    "sg:classifiers":[
        {
            "category":"Building & Trades",
            "subcategory":"Construction",
            "type":"Services"
        }
    ],
    "sg:phone":"+1 905 771 1791",
    "sg:postcode":"L3T 1N9",
    "sg:province":"ON",
    "sg:tags":[
        "general",
        "contractor"
    ],
    "wof:name":"Toram Contracting Inc",
    "wof:placetype":"venue"
},
  "geometry": {"coordinates":[-79.4192657471,43.8057823181],"type":"Point"}
}