{
  "type": "Feature",
  "properties": {
    "addr:full":"88 Rue Bernard O Montreal QC H2T 2J8",
    "addr:housenumber":"88",
    "addr:postcode":"h2t 2j8",
    "addr:street":"Rue Bernard O",
    "iso:country":"CA",
    "sg:address":"88 Rue Bernard O",
    "sg:city":"Montreal",
    "sg:classifiers":[
        {
            "category":"Restaurant",
            "type":"Food & Drink"
        }
    ],
    "sg:phone":"+1 514 271 6733",
    "sg:postcode":"H2T 2J8",
    "sg:province":"QC",
    "wof:name":"Restaurant Thailande",
    "wof:placetype":"venue"
},
  "geometry": {"coordinates":[-73.600533,45.528076],"type":"Point"}
}