{
  "type": "Feature",
  "properties": {
    "addr:full":"Desray Cres RR 2 Paradise NL A1L 1C2",
    "addr:housenumber":"2",
    "addr:postcode":"a1l 1c2",
    "addr:street":"Desray Cres Rr",
    "iso:country":"CA",
    "sg:address":"Desray Cres RR 2",
    "sg:city":"Paradise",
    "sg:classifiers":[
        {
            "category":"Wholesale",
            "subcategory":"Medical Equipment & Supplies",
            "type":"Manufacturing & Wholesale Goods"
        }
    ],
    "sg:phone":"+1 709 781 0181",
    "sg:postcode":"A1L 1C2",
    "sg:province":"NL",
    "sg:tags":[
        "hospital"
    ],
    "wof:name":"Lifescan Canada Ltd",
    "wof:placetype":"venue"
},
  "geometry": {"coordinates":[-52.8864746094,47.5268859863],"type":"Point"}
}