{
  "type": "Feature",
  "properties": {
    "addr:full":"603 Carlton Trail North Battleford SK S9A 4A9",
    "addr:housenumber":"603",
    "addr:postcode":"s9a 4a9",
    "addr:street":"Carlton Trail",
    "iso:country":"CA",
    "sg:address":"603 Carlton Trail",
    "sg:city":"North Battleford",
    "sg:classifiers":[
        {
            "category":"Shopping",
            "subcategory":"Shoes",
            "type":"Retail Goods"
        }
    ],
    "sg:phone":"+1 306 445 2015",
    "sg:postcode":"S9A 4A9",
    "sg:province":"SK",
    "wof:name":"Payless Shoe Source",
    "wof:placetype":"venue"
},
  "geometry": {"coordinates":[-108.272621155,52.7625541687],"type":"Point"}
}