{
  "type": "Feature",
  "properties": {
    "addr:full":"1749 Nanaimo St Vancouver BC V5N 5C1",
    "addr:housenumber":"1749",
    "addr:postcode":"v5n 5c1",
    "addr:street":"Nanaimo St",
    "iso:country":"CA",
    "sg:address":"1749 Nanaimo St",
    "sg:city":"Vancouver",
    "sg:classifiers":[
        {
            "category":"Retail",
            "subcategory":"Repair Shop",
            "type":"Services"
        }
    ],
    "sg:phone":"+1 604 251 9989",
    "sg:postcode":"V5N 5C1",
    "sg:province":"BC",
    "sg:tags":[
        "television",
        "radio"
    ],
    "wof:name":"A-Tech Electronics Svc Ltd",
    "wof:placetype":"venue"
},
  "geometry": {"coordinates":[-123.056725,49.2691],"type":"Point"}
}