{
  "type": "Feature",
  "properties": {
    "addr:full":"11 Railway Ave Moosehorn MB R0C 2E0",
    "addr:housenumber":"11",
    "addr:postcode":"r0c 2e0",
    "addr:street":"Railway Ave",
    "iso:country":"CA",
    "sg:address":"11 Railway Ave",
    "sg:city":"Moosehorn",
    "sg:classifiers":[
        {
            "category":"Banks & Credit Unions",
            "subcategory":"Bank",
            "type":"Services"
        }
    ],
    "sg:phone":"+1 204 768 2437",
    "sg:postcode":"R0C 2E0",
    "sg:province":"MB",
    "wof:name":"Eriksdale Credit Union Ltd",
    "wof:placetype":"venue"
},
  "geometry": {"coordinates":[-98.42506408689999,51.2915687561],"type":"Point"}
}