{
  "type": "Feature",
  "properties": {
    "addr:full":"4081 Rue Saint-Denis Montreal QC H2W 2M7",
    "addr:housenumber":"4081",
    "addr:postcode":"h2w 2m7",
    "addr:street":"Rue Saint-Denis",
    "iso:country":"CA",
    "sg:address":"4081 Rue Saint-Denis",
    "sg:city":"Montreal",
    "sg:classifiers":[
        {
            "category":"Shopping",
            "subcategory":"Optical Goods",
            "type":"Retail Goods"
        }
    ],
    "sg:phone":"+1 514 286 4200",
    "sg:postcode":"H2W 2M7",
    "sg:province":"QC",
    "sg:tags":[
        "optician"
    ],
    "wof:name":"Optix Sport",
    "wof:placetype":"venue"
},
  "geometry": {"coordinates":[-73.57628631590001,45.5211181641],"type":"Point"}
}