{
  "type": "Feature",
  "properties": {
    "iso:country":"CA",
    "sg:address":"753 View St",
    "sg:city":"Victoria",
    "sg:classifiers":[
        {
            "category":"Organizations",
            "subcategory":"Professional Association",
            "type":"Services"
        }
    ],
    "sg:phone":"+1 250 383 4955",
    "sg:postcode":"V8W 1J9",
    "sg:province":"BC",
    "sg:tags":[
        "club"
    ],
    "wof:name":"Army Navy & Air Force Veterans",
    "wof:placetype":"venue"
},
  "geometry": {"coordinates":[-123.36369323700001,48.4251823425],"type":"Point"}
}