{
  "type": "Feature",
  "properties": {
    "addr:full":"868 Merivale Rd Ottawa ON K1Z 5Z6",
    "addr:housenumber":"868",
    "addr:postcode":"k1z 5z6",
    "addr:street":"Merivale Rd",
    "iso:country":"CA",
    "sg:address":"868 Merivale Rd",
    "sg:city":"Ottawa",
    "sg:classifiers":[
        {
            "category":"Organizations",
            "subcategory":"Non-profit Organization",
            "type":"Services"
        }
    ],
    "sg:phone":"+1 613 722 9996",
    "sg:postcode":"K1Z 5Z6",
    "sg:province":"ON",
    "sg:tags":[
        "fund",
        "counselor",
        "raising"
    ],
    "wof:name":"Sixth Chord Productions Inc",
    "wof:placetype":"venue"
},
  "geometry": {"coordinates":[-75.73260500000001,45.384666],"type":"Point"}
}