{
  "type": "Feature",
  "properties": {
    "addr:full":"2457 Beta Ave Burnaby BC V5C 5N1",
    "addr:housenumber":"2457",
    "addr:postcode":"v5c 5n1",
    "addr:street":"Beta Ave",
    "iso:country":"CA",
    "sg:address":"2457 Beta Ave",
    "sg:city":"Burnaby",
    "sg:classifiers":[
        {
            "category":"Manufacturing",
            "subcategory":"Printing",
            "type":"Manufacturing & Wholesale Goods"
        }
    ],
    "sg:phone":"+1 604 294 5456",
    "sg:postcode":"V5C 5N1",
    "sg:province":"BC",
    "sg:tags":[
        "printer"
    ],
    "wof:name":"Mountain Printing & Graphics",
    "wof:placetype":"venue"
},
  "geometry": {"coordinates":[-122.997826,49.263477],"type":"Point"}
}