{
  "type": "Feature",
  "properties": {
    "addr:full":"1800 Argyle St Halifax NS B3J 3N8",
    "addr:housenumber":"1800",
    "addr:postcode":"ns b3j 3n8",
    "addr:street":"Argyle St",
    "iso:country":"CA",
    "sg:address":"1800 Argyle St",
    "sg:city":"Halifax",
    "sg:classifiers":[
        {
            "category":"Restaurant",
            "type":"Food & Drink"
        }
    ],
    "sg:phone":"+1 902 422 2751",
    "sg:postcode":"B3J 3N8",
    "sg:province":"NS",
    "sg:tags":[
        "shop",
        "coffee"
    ],
    "wof:name":"Coffee Corner",
    "wof:placetype":"venue"
},
  "geometry": {"coordinates":[-63.575474,44.648106],"type":"Point"}
}