{
  "type": "Feature",
  "properties": {
    "iso:country":"CA",
    "sg:address":"16 Rue Saint-Francois",
    "sg:city":"Hull",
    "sg:classifiers":[
        {
            "category":"Social Services",
            "subcategory":"Child Care",
            "type":"Services"
        }
    ],
    "sg:phone":"+1 819 778 3312",
    "sg:postcode":"J9A 1A8",
    "sg:province":"QC",
    "wof:name":"Montessori-Programme",
    "wof:placetype":"venue"
},
  "geometry": {"coordinates":[-75.747475,45.422615],"type":"Point"}
}