{
  "type": "Feature",
  "properties": {
    "addr:full":"438 Rue John-Egan Aylmer QC J9H 3V7",
    "addr:housenumber":"438",
    "addr:postcode":"j9h 3v7",
    "addr:street":"Rue John-Egan",
    "iso:country":"CA",
    "sg:address":"438 Rue John-Egan",
    "sg:city":"Aylmer",
    "sg:classifiers":[
        {
            "category":"Personal",
            "subcategory":"Beauty Salon",
            "type":"Services"
        }
    ],
    "sg:phone":"+1 819 685 0559",
    "sg:postcode":"J9H 3V7",
    "sg:province":"QC",
    "wof:name":"Salon Boulevard DE LA Coupe",
    "wof:placetype":"venue"
},
  "geometry": {"coordinates":[-75.8366851807,45.4002571106],"type":"Point"}
}