{
  "type": "Feature",
  "properties": {
    "iso:country":"CA",
    "sg:address":"425 Av Meloche",
    "sg:city":"Dorval",
    "sg:classifiers":[
        {
            "category":"Wholesale",
            "subcategory":"Groceries",
            "type":"Manufacturing & Wholesale Goods"
        }
    ],
    "sg:phone":"+1 514 631 5775",
    "sg:postcode":"H9P 2W2",
    "sg:province":"QC",
    "sg:tags":[
        "food",
        "natural"
    ],
    "wof:name":"Satau Inc",
    "wof:placetype":"venue"
},
  "geometry": {"coordinates":[-73.7269744873,45.4500236511],"type":"Point"}
}