{
  "type": "Feature",
  "properties": {
    "addr:full":"5768 Chabot St Montreal QC H2G 2S7",
    "addr:housenumber":"5768",
    "addr:postcode":"h2g 2s7",
    "addr:street":"Chabot St",
    "iso:country":"CA",
    "sg:address":"5768 Chabot St",
    "sg:city":"Montreal",
    "sg:classifiers":[
        {
            "category":"Communications",
            "subcategory":"Film & Video Production",
            "type":"Services"
        }
    ],
    "sg:phone":"+1 514 388 0482",
    "sg:postcode":"H2G 2S7",
    "sg:province":"QC",
    "sg:tags":[
        "motion",
        "picture",
        "studio",
        "producer"
    ],
    "wof:name":"Productions Du Rapide-Blanc",
    "wof:placetype":"venue"
},
  "geometry": {"coordinates":[-73.588432,45.540764],"type":"Point"}
}