{
  "type": "Feature",
  "properties": {
    "addr:full":"Blenheim ON N0P 1A0",
    "addr:postcode":"n0p 1a0",
    "iso:country":"CA",
    "sg:city":"Blenheim",
    "sg:classifiers":[
        {
            "category":"Retail",
            "subcategory":"Animal Services",
            "type":"Services"
        }
    ],
    "sg:phone":"+1 519 676 6565",
    "sg:postcode":"N0P 1A0",
    "sg:province":"ON",
    "sg:tags":[
        "pet",
        "grooming",
        "washing"
    ],
    "wof:name":"Perfect Pooch Dog Grooming",
    "wof:placetype":"venue"
},
  "geometry": {"coordinates":[-81.986076,42.343338],"type":"Point"}
}