{
  "type": "Feature",
  "properties": {
    "addr:full":"1885 Boul Saint-Joseph Drummondville QC J2B 1R4",
    "addr:housenumber":"1885",
    "addr:postcode":"j2b 1r4",
    "addr:street":"Boul Saint-Joseph",
    "iso:country":"CA",
    "sg:address":"1885 Boul Saint-Joseph",
    "sg:city":"Drummondville",
    "sg:classifiers":[
        {
            "category":"Shopping",
            "subcategory":"Computers & Home Electronics",
            "type":"Retail Goods"
        }
    ],
    "sg:phone":"+1 819 479 7400",
    "sg:postcode":"J2B 1R4",
    "sg:province":"QC",
    "sg:tags":[
        "equipment",
        "dealer"
    ],
    "wof:name":"Etc Informatique Inc",
    "wof:placetype":"venue"
},
  "geometry": {"coordinates":[-72.48834991459999,45.8780670166],"type":"Point"}
}