{
  "type": "Feature",
  "properties": {
    "addr:full":"1427 Rue Saint-Aime Drummondville QC J2B 2S9",
    "addr:housenumber":"1427",
    "addr:postcode":"j2b 2s9",
    "addr:street":"Rue Saint-Aime",
    "iso:country":"CA",
    "sg:address":"1427 Rue Saint-Aime",
    "sg:city":"Drummondville",
    "sg:classifiers":[
        {
            "category":"Wholesale",
            "subcategory":"Electrical",
            "type":"Manufacturing & Wholesale Goods"
        }
    ],
    "sg:phone":"+1 819 477 3077",
    "sg:postcode":"J2B 2S9",
    "sg:province":"QC",
    "sg:tags":[
        "communication",
        "radio",
        "dealer"
    ],
    "wof:name":"Communications Michel Radio",
    "wof:placetype":"venue"
},
  "geometry": {"coordinates":[-72.472168,45.861462],"type":"Point"}
}