{
  "type": "Feature",
  "properties": {
    "iso:country":"CA",
    "sg:address":"64 Golfdale Cres #10",
    "sg:city":"London",
    "sg:classifiers":[
        {
            "category":"Restaurant",
            "type":"Food & Drink"
        }
    ],
    "sg:phone":"+1 519 680 7136",
    "sg:postcode":"N6C 5P4",
    "sg:province":"ON",
    "sg:tags":[
        "caterer"
    ],
    "wof:name":"Sun Sweet Catering",
    "wof:placetype":"venue"
},
  "geometry": {"coordinates":[-81.2487487793,42.9448280334],"type":"Point"}
}