{
  "type": "Feature",
  "properties": {
    "addr:full":"3625 1st St Naramata BC V0H 1N0",
    "addr:housenumber":"3625",
    "addr:postcode":"v0h 1n0",
    "addr:street":"1St St",
    "iso:country":"CA",
    "sg:address":"3625 1st St",
    "sg:city":"Naramata",
    "sg:classifiers":[
        {
            "category":"Travel",
            "subcategory":"Hotels & Motels",
            "type":"Entertainment"
        }
    ],
    "sg:phone":"+1 250 496 5063",
    "sg:postcode":"V0H 1N0",
    "sg:province":"BC",
    "sg:tags":[
        "resort"
    ],
    "wof:name":"Naramata Heritage Inn & Spa",
    "wof:placetype":"venue"
},
  "geometry": {"coordinates":[-119.60319518999999,49.5972061157],"type":"Point"}
}