{
  "type": "Feature",
  "properties": {
    "addr:full":"34 Sunnyside Dr Sussex NB E4E 1C8",
    "addr:housenumber":"34",
    "addr:postcode":"e4e 1c8",
    "addr:street":"Sunnyside Dr",
    "iso:country":"CA",
    "sg:address":"34 Sunnyside Dr",
    "sg:city":"Sussex",
    "sg:classifiers":[
        {
            "category":"Retail",
            "subcategory":"Funeral Services",
            "type":"Services"
        }
    ],
    "sg:phone":"+1 506 433 1176",
    "sg:postcode":"E4E 1C8",
    "sg:province":"NB",
    "sg:tags":[
        "director"
    ],
    "wof:name":"Wallace Funeral Home Ltd",
    "wof:placetype":"venue"
},
  "geometry": {"coordinates":[-65.521271,45.7257],"type":"Point"}
}