{
  "type": "Feature",
  "properties": {
    "addr:full":"Igloolik NU X0A 0L0",
    "addr:postcode":"x0a 0l0",
    "iso:country":"CA",
    "sg:city":"Igloolik",
    "sg:classifiers":[
        {
            "category":"Government",
            "subcategory":"Office",
            "type":"Public Place"
        }
    ],
    "sg:phone":"+1 867 934 8722",
    "sg:postcode":"X0A 0L0",
    "sg:province":"NU",
    "sg:tags":[
        "village"
    ],
    "wof:name":"Igloolik Community Wellness",
    "wof:placetype":"venue"
},
  "geometry": {"coordinates":[-81.794533,69.377235],"type":"Point"}
}