{
  "type": "Feature",
  "properties": {
    "addr:full":"North Vancouver BC V7M 3G8",
    "addr:postcode":"v7m 3g8",
    "iso:country":"CA",
    "sg:city":"North Vancouver",
    "sg:classifiers":[
        {
            "category":"Social Services",
            "subcategory":"Job Training",
            "type":"Services"
        }
    ],
    "sg:phone":"+1 604 984 4567",
    "sg:postcode":"V7M 3G8",
    "sg:province":"BC",
    "sg:tags":[
        "career",
        "counseling",
        "vocational"
    ],
    "wof:name":"North Shore Compass Ctr",
    "wof:placetype":"venue"
},
  "geometry": {"coordinates":[-123.08366393999999,49.3138694763],"type":"Point"}
}