{
  "type": "Feature",
  "properties": {
    "addr:full":"611 Tecumseh Rd E Windsor ON N8X 2S1",
    "addr:housenumber":"611",
    "addr:postcode":"n8x 2s1",
    "addr:street":"Tecumseh Rd E",
    "iso:country":"CA",
    "sg:address":"611 Tecumseh Rd E",
    "sg:city":"Windsor",
    "sg:classifiers":[
        {
            "category":"Manufacturing",
            "subcategory":"Furniture",
            "type":"Manufacturing & Wholesale Goods"
        }
    ],
    "sg:phone":"+1 519 972 7679",
    "sg:postcode":"N8X 2S1",
    "sg:province":"ON",
    "sg:tags":[
        "curtain",
        "drapery"
    ],
    "wof:name":"Draperies By Shezi",
    "wof:placetype":"venue"
},
  "geometry": {"coordinates":[-83.0153808594,42.2981948853],"type":"Point"}
}