{
  "type": "Feature",
  "properties": {
    "addr:full":"14 Shamrock Pl Conception Bay South NL A1W 5C3",
    "addr:housenumber":"14",
    "addr:postcode":"a1w 5c3",
    "addr:street":"Shamrock Pl",
    "iso:country":"CA",
    "sg:address":"14 Shamrock Pl",
    "sg:city":"Conception Bay South",
    "sg:classifiers":[
        {
            "category":"Building & Trades",
            "subcategory":"Construction",
            "type":"Services"
        }
    ],
    "sg:phone":"+1 709 834 4384",
    "sg:postcode":"A1W 5C3",
    "sg:province":"NL",
    "sg:tags":[
        "excavating",
        "contractor"
    ],
    "wof:name":"Jim Butler Ltd",
    "wof:placetype":"venue"
},
  "geometry": {"coordinates":[-52.964931488,47.5005722046],"type":"Point"}
}