{
  "type": "Feature",
  "properties": {
    "addr:full":"1295 26th Ave W Vancouver BC V6H 2A8",
    "addr:housenumber":"1295",
    "addr:postcode":"v6h 2a8",
    "addr:street":"26Th Ave W",
    "iso:country":"CA",
    "sg:address":"1295 26th Ave W",
    "sg:city":"Vancouver",
    "sg:classifiers":[
        {
            "category":"Travel",
            "subcategory":"Hotels & Motels",
            "type":"Entertainment"
        }
    ],
    "sg:phone":"+1 604 731 2621",
    "sg:postcode":"V6H 2A8",
    "sg:province":"BC",
    "sg:tags":[
        "breakfast",
        "accommodation",
        "bed"
    ],
    "wof:name":"Bed & Breakfast By Schneider's",
    "wof:placetype":"venue"
},
  "geometry": {"coordinates":[-123.13397999999999,49.248451],"type":"Point"}
}