{
  "type": "Feature",
  "properties": {
    "iso:country":"CA",
    "sg:city":"Miller Lake",
    "sg:classifiers":[
        {
            "category":"Shopping",
            "subcategory":"Discount & Variety Stores",
            "type":"Retail Goods"
        }
    ],
    "sg:phone":"+1 519 795 7744",
    "sg:postcode":"N0H 1Z0",
    "sg:province":"ON",
    "sg:tags":[
        "merchandise",
        "general"
    ],
    "wof:name":"Drift in General Store",
    "wof:placetype":"venue"
},
  "geometry": {"coordinates":[-81.44310760499999,45.1025695801],"type":"Point"}
}