{
  "type": "Feature",
  "properties": {
    "addr:full":"1220 Rue Des Saules Prevost QC J0R 1T0",
    "addr:housenumber":"1220",
    "addr:postcode":"j0r 1t0",
    "addr:street":"Rue Des Saules",
    "iso:country":"CA",
    "sg:address":"1220 Rue Des Saules",
    "sg:city":"Prevost",
    "sg:classifiers":[
        {
            "category":"Restaurant",
            "type":"Food & Drink"
        }
    ],
    "sg:phone":"+1 450 432 1173",
    "sg:postcode":"J0R 1T0",
    "sg:province":"QC",
    "sg:tags":[
        "caterer"
    ],
    "wof:name":"Buffet Du Domaine Inc",
    "wof:placetype":"venue"
},
  "geometry": {"coordinates":[-74.04933200000001,45.82674],"type":"Point"}
}