{
  "type": "Feature",
  "properties": {
    "addr:full":"12537 21st Ave Blairmore AB T0K 0E0",
    "addr:housenumber":"12537",
    "addr:postcode":"t0k 0e0",
    "addr:street":"21St Ave",
    "iso:country":"CA",
    "sg:address":"12537 21st Ave",
    "sg:city":"Blairmore",
    "sg:classifiers":[
        {
            "category":"Professional",
            "subcategory":"Lawyer & Legal Services",
            "type":"Services"
        }
    ],
    "sg:phone":"+1 403 562 2900",
    "sg:postcode":"T0K 0E0",
    "sg:province":"AB",
    "sg:tags":[
        "attorney"
    ],
    "wof:name":"Douglas G Young Law Office",
    "wof:placetype":"venue"
},
  "geometry": {"coordinates":[-114.441689,49.609257],"type":"Point"}
}