{
  "type": "Feature",
  "properties": {
    "addr:full":"216 Metcalf St Saint John NB E2K 1K6",
    "addr:housenumber":"216",
    "addr:postcode":"e2k 1k6",
    "addr:street":"Metcalf St",
    "iso:country":"CA",
    "sg:address":"216 Metcalf St",
    "sg:city":"Saint John",
    "sg:classifiers":[
        {
            "category":"Manufacturing",
            "subcategory":"Metals",
            "type":"Manufacturing & Wholesale Goods"
        }
    ],
    "sg:phone":"+1 506 648 1009",
    "sg:postcode":"E2K 1K6",
    "sg:province":"NB",
    "sg:tags":[
        "windows"
    ],
    "wof:name":"Metcalf Glass Ltd",
    "wof:placetype":"venue"
},
  "geometry": {"coordinates":[-66.07958221440001,45.2760238647],"type":"Point"}
}