{
  "type": "Feature",
  "properties": {
    "addr:full":"1573 Laperriere Ave Ottawa ON K1Z 7T3",
    "addr:housenumber":"1573",
    "addr:postcode":"k1z 7t3",
    "addr:street":"Laperriere Ave",
    "iso:country":"CA",
    "sg:address":"1573 Laperriere Ave",
    "sg:city":"Ottawa",
    "sg:classifiers":[
        {
            "category":"Wholesale",
            "subcategory":"Durable Goods & Equipment",
            "type":"Manufacturing & Wholesale Goods"
        }
    ],
    "sg:phone":"+1 613 725 3704",
    "sg:postcode":"K1Z 7T3",
    "sg:province":"ON",
    "sg:tags":[
        "electronic",
        "representative"
    ],
    "wof:name":"Cantec Representatives Inc",
    "wof:placetype":"venue"
},
  "geometry": {"coordinates":[-75.74535400000001,45.376762],"type":"Point"}
}