{
  "type": "Feature",
  "properties": {
    "addr:full":"319 Prescott St Kemptville ON K0G 1J0",
    "addr:housenumber":"319",
    "addr:postcode":"k0g 1j0",
    "addr:street":"Prescott St",
    "iso:country":"CA",
    "sg:address":"319 Prescott St",
    "sg:city":"Kemptville",
    "sg:classifiers":[
        {
            "category":"Organizations",
            "subcategory":"Religious Organization",
            "type":"Services"
        }
    ],
    "sg:phone":"+1 613 258 4136",
    "sg:postcode":"K0G 1J0",
    "sg:province":"ON",
    "sg:tags":[
        "church"
    ],
    "wof:name":"St Paul's Presbyterian Church",
    "wof:placetype":"venue"
},
  "geometry": {"coordinates":[-75.6429672241,45.0146827698],"type":"Point"}
}