{
  "type": "Feature",
  "properties": {
    "addr:full":"5074 130 Ave NW Edmonton AB T5A 5A9",
    "addr:housenumber":"5074",
    "addr:postcode":"t5a 5a9",
    "addr:street":"130 Ave Nw",
    "iso:country":"CA",
    "sg:address":"5074 130 Ave NW",
    "sg:city":"Edmonton",
    "sg:classifiers":[
        {
            "category":"Cinema",
            "subcategory":"Movie Theater",
            "type":"Entertainment"
        }
    ],
    "sg:phone":"+1 780 472 9779",
    "sg:postcode":"T5A 5A9",
    "sg:province":"AB",
    "wof:name":"Movies 12",
    "wof:placetype":"venue"
},
  "geometry": {"coordinates":[-113.420258,53.590034],"type":"Point"}
}