{
  "type": "Feature",
  "properties": {
    "addr:full":"16 Main St Lucky Lake SK S0L 1Z0",
    "addr:housenumber":"16",
    "addr:postcode":"s0l 1z0",
    "addr:street":"Main St",
    "iso:country":"CA",
    "sg:address":"16 Main St",
    "sg:city":"Lucky Lake",
    "sg:classifiers":[
        {
            "category":"Shopping",
            "subcategory":"Catalog Store",
            "type":"Retail Goods"
        }
    ],
    "sg:phone":"+1 306 858 2929",
    "sg:postcode":"S0L 1Z0",
    "sg:province":"SK",
    "sg:tags":[
        "mail",
        "order",
        "internet"
    ],
    "wof:name":"Sears Canada Inc",
    "wof:placetype":"venue"
},
  "geometry": {"coordinates":[-107.135559082,50.9799461365],"type":"Point"}
}