{
  "type": "Feature",
  "properties": {
    "addr:full":"175 9E Av Iberville QC J2X 1J7",
    "addr:housenumber":"175",
    "addr:postcode":"j2x 1j7",
    "addr:street":"9E Av",
    "iso:country":"CA",
    "sg:address":"175 9E Av",
    "sg:city":"Iberville",
    "sg:classifiers":[
        {
            "category":"Organizations",
            "subcategory":"Religious Organization",
            "type":"Services"
        }
    ],
    "sg:phone":"+1 450 358 3946",
    "sg:postcode":"J2X 1J7",
    "sg:province":"QC",
    "sg:tags":[
        "house",
        "retreat",
        "rest",
        "home"
    ],
    "wof:name":"Residence St-Athanase",
    "wof:placetype":"venue"
},
  "geometry": {"coordinates":[-73.2414779663,45.309753418],"type":"Point"}
}