{
  "type": "Feature",
  "properties": {
    "addr:full":"Oshawa ON L1G 3R5",
    "addr:postcode":"l1g 3r5",
    "iso:country":"CA",
    "sg:city":"Oshawa",
    "sg:classifiers":[
        {
            "category":"Retail",
            "subcategory":"Auto Repair",
            "type":"Services"
        }
    ],
    "sg:phone":"+1 905 576 5406",
    "sg:postcode":"L1G 3R5",
    "sg:province":"ON",
    "sg:tags":[
        "repairing",
        "automobile"
    ],
    "wof:name":"Durham Auto Works",
    "wof:placetype":"venue"
},
  "geometry": {"coordinates":[-78.879341,43.930508],"type":"Point"}
}