{
  "type": "Feature",
  "properties": {
    "addr:full":"12222 137 Ave NW Edmonton AB T5L 4X5",
    "addr:housenumber":"12222",
    "addr:postcode":"t5l 4x5",
    "addr:street":"137 Ave Nw",
    "iso:country":"CA",
    "sg:address":"12222 137 Ave NW",
    "sg:city":"Edmonton",
    "sg:classifiers":[
        {
            "category":"Restaurant",
            "type":"Food & Drink"
        }
    ],
    "sg:phone":"+1 780 457 7610",
    "sg:postcode":"T5L 4X5",
    "sg:province":"AB",
    "wof:name":"A & W Family Restaurant",
    "wof:placetype":"venue"
},
  "geometry": {"coordinates":[-113.532265,53.599735],"type":"Point"}
}