{
  "type": "Feature",
  "properties": {
    "addr:full":"6815 177 St NW Edmonton AB T5T 4K3",
    "addr:housenumber":"6815",
    "addr:postcode":"t5t 4k3",
    "addr:street":"177 St Nw",
    "iso:country":"CA",
    "sg:address":"6815 177 St NW",
    "sg:city":"Edmonton",
    "sg:classifiers":[
        {
            "category":"Personal",
            "subcategory":"Beauty Salon",
            "type":"Services"
        }
    ],
    "sg:phone":"+1 780 481 1360",
    "sg:postcode":"T5T 4K3",
    "sg:province":"AB",
    "wof:name":"Singleton's Hair Care",
    "wof:placetype":"venue"
},
  "geometry": {"coordinates":[-113.627037,53.502563],"type":"Point"}
}