{
  "type": "Feature",
  "properties": {
    "addr:full":"109 Rue Saint-Vincent Sainte-Agathe-Des-Monts QC J8C 2A8",
    "addr:housenumber":"109",
    "addr:postcode":"j8c 2a8",
    "addr:street":"Rue Saint-Vincent",
    "iso:country":"CA",
    "sg:address":"109 Rue Saint-Vincent",
    "sg:city":"Sainte-Agathe-Des-Monts",
    "sg:classifiers":[
        {
            "category":"Professional",
            "subcategory":"Business Services",
            "type":"Services"
        }
    ],
    "sg:phone":"+1 819 326 6321",
    "sg:postcode":"J8C 2A8",
    "sg:province":"QC",
    "sg:tags":[
        "notary"
    ],
    "wof:name":"Leonard Page & Assocs",
    "wof:placetype":"venue"
},
  "geometry": {"coordinates":[-74.288055,46.04966],"type":"Point"}
}