{
  "type": "Feature",
  "properties": {
    "addr:full":"81 Grand River St N Paris ON N3L 2M3",
    "addr:housenumber":"81",
    "addr:postcode":"n3l 2m3",
    "addr:street":"Grand;St N",
    "iso:country":"CA",
    "sg:address":"81 Grand River St N",
    "sg:city":"Paris",
    "sg:classifiers":[
        {
            "category":"Food & Beverages",
            "subcategory":"Bakery",
            "type":"Retail Goods"
        }
    ],
    "sg:phone":"+1 519 442 6010",
    "sg:postcode":"N3L 2M3",
    "sg:province":"ON",
    "sg:tags":[
        "baker"
    ],
    "wof:name":"Paris Bakery",
    "wof:placetype":"venue"
},
  "geometry": {"coordinates":[-80.38402600000001,43.19368],"type":"Point"}
}