{
  "type": "Feature",
  "properties": {
    "addr:full":"354 Rexdale Blvd Etobicoke ON M9W 1R6",
    "addr:housenumber":"354",
    "addr:postcode":"m9w 1r6",
    "addr:street":"Rexdale Blvd",
    "iso:country":"CA",
    "sg:address":"354 Rexdale Blvd",
    "sg:city":"Etobicoke",
    "sg:classifiers":[
        {
            "category":"Home & Garden",
            "subcategory":"Building Materials",
            "type":"Retail Goods"
        }
    ],
    "sg:phone":"+1 416 745 1234",
    "sg:postcode":"M9W 1R6",
    "sg:province":"ON",
    "sg:tags":[
        "glass",
        "window",
        "plate"
    ],
    "wof:name":"A Arash Windshield",
    "wof:placetype":"venue"
},
  "geometry": {"coordinates":[-79.588577,43.715714],"type":"Point"}
}