{
  "type": "Feature",
  "properties": {
    "addr:full":"9403 Rue Sherbrooke E Montreal QC H1L 6P2",
    "addr:housenumber":"9403",
    "addr:postcode":"h1l 6p2",
    "addr:street":"Rue Sherbrooke E",
    "iso:country":"CA",
    "sg:address":"9403 Rue Sherbrooke E",
    "sg:city":"Montreal",
    "sg:classifiers":[
        {
            "category":"Social Services",
            "type":"Services"
        }
    ],
    "sg:phone":"+1 514 356 2572",
    "sg:postcode":"H1L 6P2",
    "sg:province":"QC",
    "sg:tags":[
        "organization",
        "welfare"
    ],
    "wof:name":"Clsc Mercier-Est Anjou",
    "wof:placetype":"venue"
},
  "geometry": {"coordinates":[-73.52684021,45.6108436584],"type":"Point"}
}