{
  "type": "Feature",
  "properties": {
    "addr:full":"245 Stewart St Peterborough ON K9J 3M8",
    "addr:housenumber":"245",
    "addr:postcode":"k9j 3m8",
    "addr:street":"Stewart St",
    "iso:country":"CA",
    "sg:address":"245 Stewart St",
    "sg:city":"Peterborough",
    "sg:classifiers":[
        {
            "category":"Retail",
            "subcategory":"Animal Services",
            "type":"Services"
        }
    ],
    "sg:phone":"+1 705 740 0168",
    "sg:postcode":"K9J 3M8",
    "sg:province":"ON",
    "sg:tags":[
        "pet",
        "grooming",
        "washing"
    ],
    "wof:name":"Angel's Pet Salon",
    "wof:placetype":"venue"
},
  "geometry": {"coordinates":[-78.32544708250001,44.3007965088],"type":"Point"}
}