{
  "type": "Feature",
  "properties": {
    "addr:full":"159 Boul Dion Matane QC G4W 4B6",
    "addr:housenumber":"159",
    "addr:postcode":"g4w 4b6",
    "addr:street":"Boul Dion",
    "iso:country":"CA",
    "sg:address":"159 Boul Dion",
    "sg:city":"Matane",
    "sg:classifiers":[
        {
            "category":"Personal",
            "subcategory":"Beauty Salon",
            "type":"Services"
        }
    ],
    "sg:phone":"+1 418 566 2615",
    "sg:postcode":"G4W 4B6",
    "sg:province":"QC",
    "wof:name":"Salon Eden",
    "wof:placetype":"venue"
},
  "geometry": {"coordinates":[-67.546043396,48.845867157],"type":"Point"}
}