{
  "type": "Feature",
  "properties": {
    "addr:full":"89 Boul Saint-Raymond Hull QC J8Y 1S6",
    "addr:housenumber":"89",
    "addr:postcode":"j8y 1s6",
    "addr:street":"Boul Saint-Raymond",
    "iso:country":"CA",
    "sg:address":"89 Boul Saint-Raymond",
    "sg:city":"Hull",
    "sg:classifiers":[
        {
            "category":"Education",
            "subcategory":"Special Training",
            "type":"Public Place"
        }
    ],
    "sg:phone":"+1 819 777 8555",
    "sg:postcode":"J8Y 1S6",
    "sg:province":"QC",
    "sg:tags":[
        "instruction",
        "driving"
    ],
    "wof:name":"Ecole Du Conduite R Sarault",
    "wof:placetype":"venue"
},
  "geometry": {"coordinates":[-75.741837,45.446857],"type":"Point"}
}