{
  "type": "Feature",
  "properties": {
    "iso:country":"CA",
    "sg:address":"7510 Bath Rd",
    "sg:city":"Mississauga",
    "sg:classifiers":[
        {
            "category":"Utilities",
            "subcategory":"Telephone",
            "type":"Services"
        }
    ],
    "sg:phone":"+1 905 677 6500",
    "sg:postcode":"L4T 1L2",
    "sg:province":"ON",
    "sg:tags":[
        "communications",
        "datum",
        "communication"
    ],
    "wof:name":"Altecon Data Communications",
    "wof:placetype":"venue"
},
  "geometry": {"coordinates":[-79.656288,43.7108],"type":"Point"}
}