{
  "type": "Feature",
  "properties": {
    "addr:full":"204 Water St St Andrews NB E5B 1B4",
    "addr:housenumber":"204",
    "addr:postcode":"e5b 1b4",
    "addr:street":"Water St",
    "iso:country":"CA",
    "sg:address":"204 Water St",
    "sg:city":"St Andrews",
    "sg:classifiers":[
        {
            "category":"Banks & Credit Unions",
            "subcategory":"Bank",
            "type":"Services"
        }
    ],
    "sg:phone":"+1 506 529 1140",
    "sg:postcode":"E5B 1B4",
    "sg:province":"NB",
    "wof:name":"Scotiabank",
    "wof:placetype":"venue"
},
  "geometry": {"coordinates":[-67.052818,45.073792],"type":"Point"}
}