{
  "type": "Feature",
  "properties": {
    "addr:full":"1590 Av Du Docteur-Penfield Montreal QC H3G 1C5",
    "addr:housenumber":"1590",
    "addr:postcode":"h3g 1c5",
    "addr:street":"Av Du Docteur-Penfield",
    "iso:country":"CA",
    "sg:address":"1590 Av Du Docteur-Penfield",
    "sg:city":"Montreal",
    "sg:classifiers":[
        {
            "category":"Organizations",
            "subcategory":"Professional Association",
            "type":"Services"
        }
    ],
    "sg:phone":"+1 514 931 7531",
    "sg:postcode":"H3G 1C5",
    "sg:province":"QC",
    "wof:name":"Canadian Jewish Congress",
    "wof:placetype":"venue"
},
  "geometry": {"coordinates":[-73.5861282349,45.4967384338],"type":"Point"}
}