{
  "type": "Feature",
  "properties": {
    "addr:full":"40 Rupert St Amherst NS B4H 3R6",
    "addr:housenumber":"40",
    "addr:postcode":"b4h 3r6",
    "addr:street":"Rupert St",
    "iso:country":"CA",
    "sg:address":"40 Rupert St",
    "sg:city":"Amherst",
    "sg:classifiers":[
        {
            "category":"Wholesale",
            "subcategory":"Construction Materials",
            "type":"Manufacturing & Wholesale Goods"
        }
    ],
    "sg:phone":"+1 902 667 5525",
    "sg:postcode":"B4H 3R6",
    "sg:province":"NS",
    "sg:tags":[
        "lumber"
    ],
    "wof:name":"Atlantic Warehousing Ltd",
    "wof:placetype":"venue"
},
  "geometry": {"coordinates":[-64.20365099999999,45.834267],"type":"Point"}
}