{
  "type": "Feature",
  "properties": {
    "addr:full":"Kingston ON K7L 3G4",
    "addr:postcode":"k7l 3g4",
    "iso:country":"CA",
    "sg:city":"Kingston",
    "sg:classifiers":[
        {
            "category":"Health Services",
            "subcategory":"Nursing And Care Facility",
            "type":"Services"
        }
    ],
    "sg:phone":"+1 613 548 8770",
    "sg:postcode":"K7L 3G4",
    "sg:province":"ON",
    "sg:tags":[
        "retirement",
        "financial",
        "consultant",
        "community",
        "planning",
        "home"
    ],
    "wof:name":"M D Management",
    "wof:placetype":"venue"
},
  "geometry": {"coordinates":[-76.484161,44.231422],"type":"Point"}
}