{
  "type": "Feature",
  "properties": {
    "iso:country":"CA",
    "sg:city":"Boucherville",
    "sg:classifiers":[
        {
            "category":"Professional",
            "subcategory":"Computer Services",
            "type":"Services"
        }
    ],
    "sg:phone":"+1 450 449 1622",
    "sg:postcode":"J4B 7K1",
    "sg:province":"QC",
    "sg:tags":[
        "information",
        "system",
        "consultant"
    ],
    "wof:name":"Conseillers En Informatique",
    "wof:placetype":"venue"
},
  "geometry": {"coordinates":[-73.431678772,45.5720481873],"type":"Point"}
}