{
  "type": "Feature",
  "properties": {
    "iso:country":"CA",
    "sg:address":"345 Fairview Rd W",
    "sg:city":"Mississauga",
    "sg:classifiers":[
        {
            "category":"Education",
            "subcategory":"School",
            "type":"Public Place"
        }
    ],
    "sg:phone":"+1 905 306 8420",
    "sg:postcode":"L5B 3W5",
    "sg:province":"ON",
    "wof:name":"St Philip School",
    "wof:placetype":"venue"
},
  "geometry": {"coordinates":[-79.631943,43.579098],"type":"Point"}
}