{
  "type": "Feature",
  "properties": {
    "addr:full":"Brackendale BC V0N 1H0",
    "addr:postcode":"v0n 1h0",
    "iso:country":"CA",
    "sg:city":"Brackendale",
    "sg:classifiers":[
        {
            "category":"Building & Trades",
            "subcategory":"Construction",
            "type":"Services"
        }
    ],
    "sg:phone":"+1 604 898 2389",
    "sg:postcode":"V0N 1H0",
    "sg:province":"BC",
    "sg:tags":[
        "masonry",
        "contractor"
    ],
    "wof:name":"Spitzer Contracting",
    "wof:placetype":"venue"
},
  "geometry": {"coordinates":[-123.130302429,49.7417373657],"type":"Point"}
}