{
  "type": "Feature",
  "properties": {
    "iso:country":"CA",
    "sg:address":"75 7E Av",
    "sg:city":"Terrasse-Vaudreuil",
    "sg:classifiers":[
        {
            "category":"Education",
            "subcategory":"School",
            "type":"Public Place"
        }
    ],
    "sg:phone":"+1 514 453 8201",
    "sg:postcode":"J7V 3N2",
    "sg:province":"QC",
    "wof:name":"Ecole Jose-Maria",
    "wof:placetype":"venue"
},
  "geometry": {"coordinates":[-73.9865264893,45.3901596069],"type":"Point"}
}