{
  "type": "Feature",
  "properties": {
    "addr:full":"5003 20 St SW Calgary AB T2T 5A5",
    "addr:housenumber":"5003",
    "addr:postcode":"t2t 5a5",
    "addr:street":"20 St Sw",
    "iso:country":"CA",
    "sg:address":"5003 20 St SW",
    "sg:city":"Calgary",
    "sg:classifiers":[
        {
            "category":"Education",
            "subcategory":"School",
            "type":"Public Place"
        }
    ],
    "sg:phone":"+1 403 777 7730",
    "sg:postcode":"T2T 5A5",
    "sg:province":"AB",
    "wof:name":"Alternative High School",
    "wof:placetype":"venue"
},
  "geometry": {"coordinates":[-114.10948944099999,51.0095939636],"type":"Point"}
}