{
  "type": "Feature",
  "properties": {
    "addr:full":"Milverton ON N0K 1M0",
    "addr:postcode":"n0k 1m0",
    "iso:country":"CA",
    "sg:city":"Milverton",
    "sg:classifiers":[
        {
            "category":"Recreation",
            "type":"Entertainment"
        }
    ],
    "sg:phone":"+1 519 595 8375",
    "sg:postcode":"N0K 1M0",
    "sg:province":"ON",
    "sg:tags":[
        "skating",
        "rink"
    ],
    "wof:name":"Milverton Arena",
    "wof:placetype":"venue"
},
  "geometry": {"coordinates":[-80.92012,43.565022],"type":"Point"}
}