{
  "type": "Feature",
  "properties": {
    "addr:full":"8 Church St Moose Creek ON K0C 1W0",
    "addr:housenumber":"8",
    "addr:postcode":"k0c 1w0",
    "addr:street":"Church St",
    "iso:country":"CA",
    "sg:address":"8 Church St",
    "sg:city":"Moose Creek",
    "sg:classifiers":[
        {
            "category":"Organizations",
            "subcategory":"Religious Organization",
            "type":"Services"
        }
    ],
    "sg:phone":"+1 613 538 2348",
    "sg:postcode":"K0C 1W0",
    "sg:province":"ON",
    "sg:tags":[
        "church"
    ],
    "wof:name":"Notre Dame Des Anges Cath Ch",
    "wof:placetype":"venue"
},
  "geometry": {"coordinates":[-74.971496582,45.2604217529],"type":"Point"}
}