{
  "type": "Feature",
  "properties": {
    "addr:full":"2246 Spring St Castleton ON K0K 1M0",
    "addr:housenumber":"2246",
    "addr:postcode":"k0k 1m0",
    "addr:street":"Spring St",
    "iso:country":"CA",
    "sg:address":"2246 Spring St",
    "sg:city":"Castleton",
    "sg:classifiers":[
        {
            "category":"Education",
            "subcategory":"School",
            "type":"Public Place"
        }
    ],
    "sg:phone":"+1 905 344 7361",
    "sg:postcode":"K0K 1M0",
    "sg:province":"ON",
    "wof:name":"Castleton Public School",
    "wof:placetype":"venue"
},
  "geometry": {"coordinates":[-77.9354171753,44.0949859619],"type":"Point"}
}