{
  "type": "Feature",
  "properties": {
    "addr:full":"852 Tamarack Dr Labrador City NL A2V 2V6",
    "addr:housenumber":"852",
    "addr:postcode":"a2v 2v6",
    "addr:street":"Tamarack Dr",
    "iso:country":"CA",
    "sg:address":"852 Tamarack Dr",
    "sg:city":"Labrador City",
    "sg:classifiers":[
        {
            "category":"Travel",
            "subcategory":"Hotels & Motels",
            "type":"Entertainment"
        }
    ],
    "sg:phone":"+1 709 944 6002",
    "sg:postcode":"A2V 2V6",
    "sg:province":"NL",
    "sg:tags":[
        "breakfast",
        "accommodation",
        "bed"
    ],
    "wof:name":"Tamarack Bed & Breakfast",
    "wof:placetype":"venue"
},
  "geometry": {"coordinates":[-66.91859436039999,52.9309883118],"type":"Point"}
}