{
  "type": "Feature",
  "properties": {
    "addr:full":"8450 Highway 17 Bruce Mines ON P0R 1C0",
    "addr:housenumber":"8450",
    "addr:postcode":"p0r 1c0",
    "addr:street":"Highway 17",
    "iso:country":"CA",
    "sg:address":"8450 Highway 17",
    "sg:city":"Bruce Mines",
    "sg:classifiers":[
        {
            "category":"Home & Garden",
            "subcategory":"Garden Supply",
            "type":"Retail Goods"
        }
    ],
    "sg:phone":"+1 705 785 9928",
    "sg:postcode":"P0R 1C0",
    "sg:province":"ON",
    "sg:tags":[
        "center"
    ],
    "wof:name":"Greenthumb Greenhouse",
    "wof:placetype":"venue"
},
  "geometry": {"coordinates":[-83.7941436768,46.3002090454],"type":"Point"}
}