{
  "type": "Feature",
  "properties": {
    "addr:full":"8305 Rue Lafrenaie Saint-Leonard QC H1P 2B1",
    "addr:housenumber":"8305",
    "addr:postcode":"h1p 2b1",
    "addr:street":"Rue Lafrenaie",
    "iso:country":"CA",
    "sg:address":"8305 Rue Lafrenaie",
    "sg:city":"Saint-Leonard",
    "sg:classifiers":[
        {
            "category":"Building & Trades",
            "subcategory":"Construction",
            "type":"Services"
        }
    ],
    "sg:phone":"+1 514 329 3399",
    "sg:postcode":"H1P 2B1",
    "sg:province":"QC",
    "sg:tags":[
        "masonry",
        "contractor"
    ],
    "wof:name":"L M Sauve Ltd",
    "wof:placetype":"venue"
},
  "geometry": {"coordinates":[-73.584969,45.597824],"type":"Point"}
}