{
  "type": "Feature",
  "properties": {
    "addr:full":"570 Alden Rd # 4 Markham ON L3R 8N5",
    "addr:housenumber":"570",
    "addr:postcode":"l3r 8n5",
    "addr:street":"Alden Rd # 4",
    "iso:country":"CA",
    "sg:address":"570 Alden Rd # 4",
    "sg:city":"Markham",
    "sg:classifiers":[
        {
            "category":"Wholesale",
            "subcategory":"Durable Goods & Equipment",
            "type":"Manufacturing & Wholesale Goods"
        }
    ],
    "sg:phone":"+1 905 479 4070",
    "sg:postcode":"L3R 8N5",
    "sg:province":"ON",
    "sg:tags":[
        "laser"
    ],
    "wof:name":"Production Design Intl Inc",
    "wof:placetype":"venue"
},
  "geometry": {"coordinates":[-79.331856,43.836926],"type":"Point"}
}