{
  "type": "Feature",
  "properties": {
    "iso:country":"CA",
    "sg:address":"1072 Tanglewood Crt",
    "sg:city":"Oakville",
    "sg:classifiers":[
        {
            "category":"Social Services",
            "subcategory":"Child Care",
            "type":"Services"
        }
    ],
    "sg:phone":"+1 905 849 3614",
    "sg:postcode":"L6L 5H7",
    "sg:province":"ON",
    "wof:name":"Century Child Care Inc",
    "wof:placetype":"venue"
},
  "geometry": {"coordinates":[-79.6903762817,43.4213829041],"type":"Point"}
}