{
  "type": "Feature",
  "properties": {
    "addr:full":"Winnipeg MB R2X 2G8",
    "addr:postcode":"r2x 2g8",
    "iso:country":"CA",
    "sg:city":"Winnipeg",
    "sg:classifiers":[
        {
            "category":"Manufacturing",
            "subcategory":"Metals",
            "type":"Manufacturing & Wholesale Goods"
        }
    ],
    "sg:phone":"+1 204 934 4307",
    "sg:postcode":"R2X 2G8",
    "sg:province":"MB",
    "sg:tags":[
        "steel",
        "treating",
        "heat"
    ],
    "wof:name":"Progress Rail Transcanada Corp",
    "wof:placetype":"venue"
},
  "geometry": {"coordinates":[-97.1702880859,49.9187965393],"type":"Point"}
}