{
  "type": "Feature",
  "properties": {
    "addr:full":"Brossard QC J4W 3H2",
    "addr:postcode":"j4w 3h2",
    "iso:country":"CA",
    "sg:city":"Brossard",
    "sg:classifiers":[
        {
            "category":"Insurance",
            "subcategory":"Insurance Agent",
            "type":"Services"
        }
    ],
    "sg:phone":"+1 450 656 4505",
    "sg:postcode":"J4W 3H2",
    "sg:province":"QC",
    "wof:name":"Services Paul LA Chapelle",
    "wof:placetype":"venue"
},
  "geometry": {"coordinates":[-73.4746017456,45.4738960266],"type":"Point"}
}