{
  "type": "Feature",
  "properties": {
    "addr:full":"Burlington ON L7M 4H2",
    "addr:postcode":"l7m 4h2",
    "iso:country":"CA",
    "sg:city":"Burlington",
    "sg:classifiers":[
        {
            "category":"Food & Beverages",
            "subcategory":"Specialty",
            "type":"Retail Goods"
        }
    ],
    "sg:phone":"+1 905 332 0181",
    "sg:postcode":"L7M 4H2",
    "sg:province":"ON",
    "sg:tags":[
        "health",
        "diet"
    ],
    "wof:name":"Shaklee Independent Distr",
    "wof:placetype":"venue"
},
  "geometry": {"coordinates":[-79.8231582642,43.3891143799],"type":"Point"}
}