{
  "type": "Feature",
  "properties": {
    "iso:country":"CA",
    "sg:address":"1041 Boul Lionel-Boulet",
    "sg:city":"Varennes",
    "sg:classifiers":[
        {
            "category":"Manufacturing",
            "subcategory":"Tools & Machinery",
            "type":"Manufacturing & Wholesale Goods"
        }
    ],
    "sg:phone":"+1 450 929 3131",
    "sg:postcode":"J3X 1P7",
    "sg:province":"QC",
    "sg:tags":[
        "mold"
    ],
    "wof:name":"Conceptions Sn Vena Inc",
    "wof:placetype":"venue"
},
  "geometry": {"coordinates":[-73.4098358154,45.6471595764],"type":"Point"}
}