{
  "type": "Feature",
  "properties": {
    "addr:full":"2129 Ch Gascon Lachenaie QC J6X 4H2",
    "addr:housenumber":"2129",
    "addr:postcode":"j6x 4h2",
    "addr:street":"Ch Gascon",
    "iso:country":"CA",
    "sg:address":"2129 Ch Gascon",
    "sg:city":"Lachenaie",
    "sg:classifiers":[
        {
            "category":"Personal",
            "subcategory":"Beauty Salon",
            "type":"Services"
        }
    ],
    "sg:phone":"+1 450 471 8516",
    "sg:postcode":"J6X 4H2",
    "sg:province":"QC",
    "wof:name":"Salon Fema Elle & Lui Inc",
    "wof:placetype":"venue"
},
  "geometry": {"coordinates":[-73.6626586914,45.7224884033],"type":"Point"}
}