{
  "type": "Feature",
  "properties": {
    "addr:full":"1122 Castlefield Ave York ON M6B 1E9",
    "addr:housenumber":"1122",
    "addr:postcode":"m6b 1e9",
    "addr:street":"Castlefield Ave",
    "iso:country":"CA",
    "sg:address":"1122 Castlefield Ave",
    "sg:city":"York",
    "sg:classifiers":[
        {
            "category":"Wholesale",
            "subcategory":"Electrical",
            "type":"Manufacturing & Wholesale Goods"
        }
    ],
    "sg:phone":"+1 416 785 6565",
    "sg:postcode":"M6B 1E9",
    "sg:province":"ON",
    "sg:tags":[
        "television"
    ],
    "wof:name":"Master Video Inc",
    "wof:placetype":"venue"
},
  "geometry": {"coordinates":[-79.45224,43.700775],"type":"Point"}
}