{
  "type": "Feature",
  "properties": {
    "addr:full":"Calgary AB T2N 1V8",
    "addr:postcode":"t2n 1v8",
    "iso:country":"CA",
    "sg:city":"Calgary",
    "sg:classifiers":[
        {
            "category":"Personal",
            "subcategory":"Beauty Salon",
            "type":"Services"
        }
    ],
    "sg:phone":"+1 403 270 7754",
    "sg:postcode":"T2N 1V8",
    "sg:province":"AB",
    "wof:name":"Kolor Twist Hair CO",
    "wof:placetype":"venue"
},
  "geometry": {"coordinates":[-114.085716248,51.0547065735],"type":"Point"}
}