{
  "type": "Feature",
  "properties": {
    "iso:country":"CA",
    "sg:address":"1 Simcoe St S",
    "sg:city":"Oshawa",
    "sg:classifiers":[
        {
            "category":"Shopping",
            "subcategory":"Discount & Variety Stores",
            "type":"Retail Goods"
        }
    ],
    "sg:phone":"+1 905 404 5499",
    "sg:postcode":"L1H 4G1",
    "sg:province":"ON",
    "wof:name":"Smoke Time Corner Store",
    "wof:placetype":"venue"
},
  "geometry": {"coordinates":[-78.863426,43.897495],"type":"Point"}
}