{
  "type": "Feature",
  "properties": {
    "addr:full":"8016 County Rd 7 Moorefield ON N0G 2K0",
    "addr:housenumber":"8016",
    "addr:postcode":"n0g 2k0",
    "addr:street":"County Rd 7 Moorefield",
    "iso:country":"CA",
    "sg:address":"8016 County Rd 7",
    "sg:city":"Moorefield",
    "sg:classifiers":[
        {
            "category":"Wholesale",
            "subcategory":"Machinery & Supplies",
            "type":"Manufacturing & Wholesale Goods"
        }
    ],
    "sg:phone":"+1 519 638 8941",
    "sg:postcode":"N0G 2K0",
    "sg:province":"ON",
    "sg:tags":[
        "farm",
        "equipment",
        "conditioning",
        "air"
    ],
    "wof:name":"Country Air & Repair",
    "wof:placetype":"venue"
},
  "geometry": {"coordinates":[-80.74730700000001,43.759525],"type":"Point"}
}