{
  "type": "Feature",
  "properties": {
    "addr:full":"Saskatoon SK S7J 2G2",
    "addr:postcode":"s7j 2g2",
    "iso:country":"CA",
    "sg:city":"Saskatoon",
    "sg:classifiers":[
        {
            "category":"Personal",
            "subcategory":"Beauty Salon",
            "type":"Services"
        }
    ],
    "sg:phone":"+1 306 955 2223",
    "sg:postcode":"S7J 2G2",
    "sg:province":"SK",
    "sg:tags":[
        "cosmetic",
        "perfume"
    ],
    "wof:name":"Merle Norman Cosmetics",
    "wof:placetype":"venue"
},
  "geometry": {"coordinates":[-106.62247467,52.1013145447],"type":"Point"}
}