{
  "type": "Feature",
  "properties": {
    "addr:full":"14 St Andrews St Cambridge ON N1S 1M3",
    "addr:housenumber":"14",
    "addr:postcode":"n1s 1m3",
    "addr:street":"St Andrews St",
    "iso:country":"CA",
    "sg:address":"14 St Andrews St",
    "sg:city":"Cambridge",
    "sg:classifiers":[
        {
            "category":"Professional",
            "subcategory":"Advertising",
            "type":"Services"
        }
    ],
    "sg:phone":"+1 519 740 0247",
    "sg:postcode":"N1S 1M3",
    "sg:province":"ON",
    "sg:tags":[
        "counselor"
    ],
    "wof:name":"Advertech Design Communication",
    "wof:placetype":"venue"
},
  "geometry": {"coordinates":[-80.318527,43.356647],"type":"Point"}
}