{
  "type": "Feature",
  "properties": {
    "iso:country":"CA",
    "sg:address":"3261 Mainshore Rd",
    "sg:city":"Port Maitland",
    "sg:classifiers":[
        {
            "category":"Manufacturing",
            "subcategory":"Food",
            "type":"Manufacturing & Wholesale Goods"
        }
    ],
    "sg:phone":"+1 902 649 2088",
    "sg:postcode":"B0W 2V0",
    "sg:province":"NS",
    "sg:tags":[
        "seafood",
        "product",
        "lobster",
        "fish",
        "prepared"
    ],
    "wof:name":"Ocean Mist Seafoods Inc",
    "wof:placetype":"venue"
},
  "geometry": {"coordinates":[-66.1486587524,43.9824714661],"type":"Point"}
}