{
  "type": "Feature",
  "properties": {
    "addr:full":"Etobicoke ON M9W 4N9",
    "addr:postcode":"m9w 4n9",
    "iso:country":"CA",
    "sg:city":"Etobicoke",
    "sg:classifiers":[
        {
            "category":"Shopping",
            "type":"Retail Goods"
        }
    ],
    "sg:phone":"+1 416 744 3344",
    "sg:postcode":"M9W 4N9",
    "sg:province":"ON",
    "sg:tags":[
        "cards",
        "collectible",
        "sport",
        "baseball",
        "memorabilia"
    ],
    "wof:name":"Grosnor Sports Cards Inc",
    "wof:placetype":"venue"
},
  "geometry": {"coordinates":[-79.574158,43.721058],"type":"Point"}
}