{
  "type": "Feature",
  "properties": {
    "iso:country":"CA",
    "sg:address":"2392 Boul Wallberg",
    "sg:city":"Dolbeau-Mistassini",
    "sg:classifiers":[
        {
            "category":"Shopping",
            "subcategory":"Clothing, Apparel, & Fashions",
            "type":"Retail Goods"
        }
    ],
    "sg:phone":"+1 418 239 0026",
    "sg:postcode":"G8L 1K7",
    "sg:province":"QC",
    "sg:tags":[
        "shop",
        "bridal"
    ],
    "wof:name":"Friperie Pourquoi Pas",
    "wof:placetype":"venue"
},
  "geometry": {"coordinates":[-72.2559967041,48.8832397461],"type":"Point"}
}