{
  "type": "Feature",
  "properties": {
    "addr:full":"12617 101 St Grande Prairie AB T8V 5S1",
    "addr:housenumber":"12617",
    "addr:postcode":"t8v 5s1",
    "addr:street":"101 St",
    "iso:country":"CA",
    "sg:address":"12617 101 St",
    "sg:city":"Grande Prairie",
    "sg:classifiers":[
        {
            "category":"Retail",
            "subcategory":"Auto Repair",
            "type":"Services"
        }
    ],
    "sg:phone":"+1 780 539 9775",
    "sg:postcode":"T8V 5S1",
    "sg:province":"AB",
    "sg:tags":[
        "body",
        "automobile",
        "painting"
    ],
    "wof:name":"Complete Automotive",
    "wof:placetype":"venue"
},
  "geometry": {"coordinates":[-118.797783,55.194813],"type":"Point"}
}