{
  "type": "Feature",
  "properties": {
    "iso:country":"CA",
    "sg:address":"26 Procee Cir",
    "sg:city":"Barrie",
    "sg:classifiers":[
        {
            "category":"Home & Garden",
            "subcategory":"Home Furnishings",
            "type":"Retail Goods"
        }
    ],
    "sg:phone":"+1 705 722 8760",
    "sg:postcode":"L4M 4Y8",
    "sg:province":"ON",
    "sg:tags":[
        "curtain",
        "made",
        "drapery"
    ],
    "wof:name":"Country Interior & Gifts",
    "wof:placetype":"venue"
},
  "geometry": {"coordinates":[-79.686325,44.389301],"type":"Point"}
}