{
  "type": "Feature",
  "properties": {
    "addr:full":"211 Rue Sainte-Anne Chicoutimi QC G7J 2L9",
    "addr:housenumber":"211",
    "addr:postcode":"g7j 2l9",
    "addr:street":"Rue Sainte-Anne",
    "iso:country":"CA",
    "sg:address":"211 Rue Sainte-Anne",
    "sg:city":"Chicoutimi",
    "sg:classifiers":[
        {
            "category":"Retail",
            "subcategory":"Auto Repair",
            "type":"Services"
        }
    ],
    "sg:phone":"+1 418 543 7282",
    "sg:postcode":"G7J 2L9",
    "sg:province":"QC",
    "sg:tags":[
        "repairing",
        "automobile",
        "tank"
    ],
    "wof:name":"Saguenay Radiateur",
    "wof:placetype":"venue"
},
  "geometry": {"coordinates":[-71.068054,48.429325],"type":"Point"}
}