{
  "type": "Feature",
  "properties": {
    "iso:country":"CA",
    "sg:address":"346 King St",
    "sg:city":"Welland",
    "sg:classifiers":[
        {
            "category":"Restaurant",
            "type":"Food & Drink"
        }
    ],
    "sg:phone":"+1 905 734 4752",
    "sg:postcode":"L3B 3K3",
    "sg:province":"ON",
    "wof:name":"Rex Hotel Ltd",
    "wof:placetype":"venue"
},
  "geometry": {"coordinates":[-79.2509384155,42.9841995239],"type":"Point"}
}