{
  "type": "Feature",
  "properties": {
    "addr:full":"659 Mount Pleasant Rd Toronto ON M4S 2N2",
    "addr:housenumber":"659",
    "addr:postcode":"m4s 2n2",
    "addr:street":"Mount Pleasant Rd",
    "iso:country":"CA",
    "sg:address":"659 Mount Pleasant Rd",
    "sg:city":"Toronto",
    "sg:classifiers":[
        {
            "category":"Retail",
            "subcategory":"Portrait Studio",
            "type":"Services"
        }
    ],
    "sg:phone":"+1 416 322 6855",
    "sg:postcode":"M4S 2N2",
    "sg:province":"ON",
    "sg:tags":[
        "photographer"
    ],
    "wof:name":"Steve Stober Photography",
    "wof:placetype":"venue"
},
  "geometry": {"coordinates":[-79.388824,43.705502],"type":"Point"}
}