{
  "type": "Feature",
  "properties": {
    "iso:country":"CA",
    "sg:city":"Temagami",
    "sg:classifiers":[
        {
            "category":"Recreation",
            "subcategory":"Marina",
            "type":"Entertainment"
        }
    ],
    "sg:phone":"+1 705 569 3321",
    "sg:postcode":"P0H 2H0",
    "sg:province":"ON",
    "wof:name":"Temagami Boat Livery",
    "wof:placetype":"venue"
},
  "geometry": {"coordinates":[-79.7810668945,47.0657348633],"type":"Point"}
}