{
  "type": "Feature",
  "properties": {
    "iso:country":"CA",
    "sg:address":"1950 Fort St # A",
    "sg:city":"Victoria",
    "sg:classifiers":[
        {
            "category":"Personal",
            "subcategory":"Tanning Parlor",
            "type":"Services"
        }
    ],
    "sg:phone":"+1 250 598 0661",
    "sg:postcode":"V8R 1K3",
    "sg:province":"BC",
    "sg:tags":[
        "salon"
    ],
    "wof:name":"Texas Heat Tanning",
    "wof:placetype":"venue"
},
  "geometry": {"coordinates":[-123.32453155499999,48.4318580627],"type":"Point"}
}