{
  "type": "Feature",
  "properties": {
    "addr:full":"118 Grey St Brantford ON N3S 4V9",
    "addr:housenumber":"118",
    "addr:postcode":"n3s 4v9",
    "addr:street":"Grey St",
    "iso:country":"CA",
    "sg:address":"118 Grey St",
    "sg:city":"Brantford",
    "sg:classifiers":[
        {
            "category":"Manufacturing",
            "subcategory":"Metals",
            "type":"Manufacturing & Wholesale Goods"
        }
    ],
    "sg:phone":"+1 519 759 0550",
    "sg:postcode":"N3S 4V9",
    "sg:province":"ON",
    "sg:tags":[
        "steel"
    ],
    "wof:name":"Oakes Welding Ltd",
    "wof:placetype":"venue"
},
  "geometry": {"coordinates":[-80.25649300000001,43.146408],"type":"Point"}
}