{
  "type": "Feature",
  "properties": {
    "addr:full":"19100 Third St Tilbury ON N0P 2L0",
    "addr:housenumber":"19100",
    "addr:postcode":"n0p 2l0",
    "addr:street":"Third St",
    "iso:country":"CA",
    "sg:address":"19100 Third St",
    "sg:city":"Tilbury",
    "sg:classifiers":[
        {
            "category":"Retail",
            "subcategory":"Repair Shop",
            "type":"Services"
        }
    ],
    "sg:phone":"+1 519 682 0418",
    "sg:postcode":"N0P 2L0",
    "sg:province":"ON",
    "sg:tags":[
        "welding"
    ],
    "wof:name":"Maurice Derynck & Sons Ltd",
    "wof:placetype":"venue"
},
  "geometry": {"coordinates":[-82.431442,42.267284],"type":"Point"}
}