{
  "type": "Feature",
  "properties": {
    "iso:country":"CA",
    "sg:city":"Barrie",
    "sg:classifiers":[
        {
            "category":"Professional",
            "subcategory":"Detective & Security Services",
            "type":"Services"
        }
    ],
    "sg:phone":"+1 705 728 7777",
    "sg:postcode":"L4N 5W4",
    "sg:province":"ON",
    "sg:tags":[
        "guard",
        "patrol"
    ],
    "wof:name":"Securitas",
    "wof:placetype":"venue"
},
  "geometry": {"coordinates":[-79.675095,44.370953],"type":"Point"}
}