{
  "type": "Feature",
  "properties": {
    "addr:full":"208 Taylor St Thorold ON L2V 1C3",
    "addr:housenumber":"208",
    "addr:postcode":"l2v 1c3",
    "addr:street":"Taylor St",
    "iso:country":"CA",
    "sg:address":"208 Taylor St",
    "sg:city":"Thorold",
    "sg:classifiers":[
        {
            "category":"Organizations",
            "subcategory":"Religious Organization",
            "type":"Services"
        }
    ],
    "sg:phone":"+1 905 227 1635",
    "sg:postcode":"L2V 1C3",
    "sg:province":"ON",
    "sg:tags":[
        "church"
    ],
    "wof:name":"Thorold South United Church",
    "wof:placetype":"venue"
},
  "geometry": {"coordinates":[-79.196983,43.102608],"type":"Point"}
}