{
  "type": "Feature",
  "properties": {
    "addr:full":"Horseshoe Lake Rd Parry Sound ON P2A 2W8",
    "addr:postcode":"p2a 2w8",
    "addr:street":"Horseshoe Lake Rd",
    "iso:country":"CA",
    "sg:address":"Horseshoe Lake Rd",
    "sg:city":"Parry Sound",
    "sg:classifiers":[
        {
            "category":"Building & Trades",
            "subcategory":"Construction",
            "type":"Services"
        }
    ],
    "sg:phone":"+1 705 378 2998",
    "sg:postcode":"P2A 2W8",
    "sg:province":"ON",
    "sg:tags":[
        "general",
        "contractor"
    ],
    "wof:name":"Dyck Drywall Contracting",
    "wof:placetype":"venue"
},
  "geometry": {"coordinates":[-80.036362,45.344769],"type":"Point"}
}