{
  "type": "Feature",
  "properties": {
    "addr:full":"5710 Rue Notre-Dame O Montreal QC H4C 1V2",
    "addr:housenumber":"5710",
    "addr:postcode":"h4c 1v2",
    "addr:street":"Rue Notre-Dame O",
    "iso:country":"CA",
    "sg:address":"5710 Rue Notre-Dame O",
    "sg:city":"Montreal",
    "sg:classifiers":[
        {
            "category":"Manufacturing",
            "subcategory":"Rubber & Plastics",
            "type":"Manufacturing & Wholesale Goods"
        }
    ],
    "sg:phone":"+1 514 935 5710",
    "sg:postcode":"H4C 1V2",
    "sg:province":"QC",
    "sg:tags":[
        "producer"
    ],
    "wof:name":"Imaflex Inc",
    "wof:placetype":"venue"
},
  "geometry": {"coordinates":[-73.523544,45.564804],"type":"Point"}
}