{
  "type": "Feature",
  "properties": {
    "addr:full":"Saint-Simeon QC G0T 1X0",
    "addr:postcode":"g0t 1x0",
    "iso:country":"CA",
    "sg:city":"Saint-Simeon",
    "sg:classifiers":[
        {
            "category":"Home & Garden",
            "subcategory":"Home Furnishings",
            "type":"Retail Goods"
        }
    ],
    "sg:phone":"+1 418 638 2349",
    "sg:postcode":"G0T 1X0",
    "sg:province":"QC",
    "sg:tags":[
        "pottery"
    ],
    "wof:name":"Poterie DE Port-Au-Persil",
    "wof:placetype":"venue"
},
  "geometry": {"coordinates":[-69.893845,47.822075],"type":"Point"}
}