{
  "type": "Feature",
  "properties": {
    "addr:full":"1377 the Queensway Etobicoke ON M8Z 1T1",
    "addr:housenumber":"1377",
    "addr:postcode":"m8z 1t1",
    "addr:street":"The Queensway",
    "iso:country":"CA",
    "sg:address":"1377 the Queensway",
    "sg:city":"Etobicoke",
    "sg:classifiers":[
        {
            "category":"Wholesale",
            "subcategory":"Groceries",
            "type":"Manufacturing & Wholesale Goods"
        }
    ],
    "sg:phone":"+1 416 253 4955",
    "sg:postcode":"M8Z 1T1",
    "sg:province":"ON",
    "sg:tags":[
        "food",
        "broker"
    ],
    "wof:name":"Uni Foods",
    "wof:placetype":"venue"
},
  "geometry": {"coordinates":[-79.52941131590001,43.6201667786],"type":"Point"}
}