{
  "type": "Feature",
  "properties": {
    "addr:full":"Mississauga ON L4W 2W5",
    "addr:postcode":"l4w 2w5",
    "iso:country":"CA",
    "sg:city":"Mississauga",
    "sg:classifiers":[
        {
            "category":"Manufacturing",
            "subcategory":"Tools & Machinery",
            "type":"Manufacturing & Wholesale Goods"
        }
    ],
    "sg:phone":"+1 905 625 6093",
    "sg:postcode":"L4W 2W5",
    "sg:province":"ON",
    "sg:tags":[
        "equipment",
        "system",
        "automation"
    ],
    "wof:name":"Promation Engineering Ltd",
    "wof:placetype":"venue"
},
  "geometry": {"coordinates":[-79.642487,43.639851],"type":"Point"}
}