{
  "type": "Feature",
  "properties": {
    "addr:full":"1 Legion Rd Red Lake ON P0V 2M0",
    "addr:housenumber":"1",
    "addr:postcode":"p0v 2m0",
    "addr:street":"Legion Rd",
    "iso:country":"CA",
    "sg:address":"1 Legion Rd",
    "sg:city":"Red Lake",
    "sg:classifiers":[
        {
            "category":"Organizations",
            "subcategory":"Professional Association",
            "type":"Services"
        }
    ],
    "sg:phone":"+1 807 727 2847",
    "sg:postcode":"P0V 2M0",
    "sg:province":"ON",
    "wof:name":"Red Lake Indian Friendship Ctr",
    "wof:placetype":"venue"
},
  "geometry": {"coordinates":[-93.822166,51.019012],"type":"Point"}
}