{
  "type": "Feature",
  "properties": {
    "iso:country":"CA",
    "sg:address":"220 Rue Grande-Allee",
    "sg:city":"Terrebonne",
    "sg:classifiers":[
        {
            "category":"Manufacturing",
            "subcategory":"Signs",
            "type":"Manufacturing & Wholesale Goods"
        }
    ],
    "sg:phone":"+1 450 492 5557",
    "sg:postcode":"J6W 4R9",
    "sg:province":"QC",
    "wof:name":"Lettrage Ft Enr",
    "wof:placetype":"venue"
},
  "geometry": {"coordinates":[-73.6586074829,45.6932106018],"type":"Point"}
}