{
  "type": "Feature",
  "properties": {
    "addr:full":"Saint-Malachie QC G0R 3N0",
    "addr:postcode":"g0r 3n0",
    "iso:country":"CA",
    "sg:city":"Saint-Malachie",
    "sg:classifiers":[
        {
            "category":"Autos & Motor Vehicles",
            "subcategory":"Automobile Sales",
            "type":"Retail Goods"
        }
    ],
    "sg:phone":"+1 418 642 2855",
    "sg:postcode":"G0R 3N0",
    "sg:province":"QC",
    "sg:tags":[
        "car",
        "dealer"
    ],
    "wof:name":"Daniel Pare Dodge Chrysler Inc",
    "wof:placetype":"venue"
},
  "geometry": {"coordinates":[-70.784072876,46.5358047485],"type":"Point"}
}