{
  "type": "Feature",
  "properties": {
    "iso:country":"CA",
    "sg:city":"Kamloops",
    "sg:classifiers":[
        {
            "category":"Health Services",
            "subcategory":"Doctor",
            "type":"Services"
        }
    ],
    "sg:phone":"+1 250 828 6755",
    "sg:postcode":"V2C 6L1",
    "sg:province":"BC",
    "sg:tags":[
        "physician",
        "surgeon"
    ],
    "wof:name":"David Stewart Inc",
    "wof:placetype":"venue"
},
  "geometry": {"coordinates":[-120.334220886,50.6715621948],"type":"Point"}
}