{
  "type": "Feature",
  "properties": {
    "addr:full":"46117 New Sarum Line St Thomas ON N5P 3S7",
    "addr:housenumber":"46117",
    "addr:postcode":"n5p 3s7",
    "addr:street":"New Sarum Line",
    "iso:country":"CA",
    "sg:address":"46117 New Sarum Line",
    "sg:city":"St Thomas",
    "sg:classifiers":[
        {
            "category":"Arts & Performance",
            "subcategory":"Theater",
            "type":"Entertainment"
        }
    ],
    "sg:phone":"+1 519 773 2685",
    "sg:postcode":"N5P 3S7",
    "sg:province":"ON",
    "sg:tags":[
        "live",
        "music"
    ],
    "wof:name":"A & M Sounds Disc Jockey Svc",
    "wof:placetype":"venue"
},
  "geometry": {"coordinates":[-81.193146,42.778938],"type":"Point"}
}