{
  "type": "Feature",
  "properties": {
    "addr:full":"Ottawa ON K1Z 5G7",
    "addr:postcode":"k1z 5g7",
    "iso:country":"CA",
    "sg:city":"Ottawa",
    "sg:classifiers":[
        {
            "category":"Health Services",
            "subcategory":"Health Practitioner",
            "type":"Services"
        }
    ],
    "sg:phone":"+1 613 729 4173",
    "sg:postcode":"K1Z 5G7",
    "sg:province":"ON",
    "sg:tags":[
        "psychologist"
    ],
    "wof:name":"Rosenburg, Truda PhD",
    "wof:placetype":"venue"
},
  "geometry": {"coordinates":[-75.74720000000001,45.381237],"type":"Point"}
}