{
  "type": "Feature",
  "properties": {
    "addr:full":"74 Ainslie St S Cambridge ON N1R 3K5",
    "addr:housenumber":"74",
    "addr:postcode":"n1r 3k5",
    "addr:street":"Ainslie St S",
    "iso:country":"CA",
    "sg:address":"74 Ainslie St S",
    "sg:city":"Cambridge",
    "sg:classifiers":[
        {
            "category":"Retail",
            "subcategory":"Veterinary Services",
            "type":"Services"
        }
    ],
    "sg:phone":"+1 519 623 2711",
    "sg:postcode":"N1R 3K5",
    "sg:province":"ON",
    "sg:tags":[
        "veterinarian"
    ],
    "wof:name":"Ainslie Animal Hospital",
    "wof:placetype":"venue"
},
  "geometry": {"coordinates":[-80.314171,43.355606],"type":"Point"}
}