{
  "type": "Feature",
  "properties": {
    "addr:full":"Victoria BC V8W 1C4",
    "addr:postcode":"v8w 1c4",
    "iso:country":"CA",
    "sg:city":"Victoria",
    "sg:classifiers":[
        {
            "category":"Professional",
            "subcategory":"Management & Consulting",
            "type":"Services"
        }
    ],
    "sg:phone":"+1 250 380 6765",
    "sg:postcode":"V8W 1C4",
    "sg:province":"BC",
    "sg:tags":[
        "consultant",
        "educational"
    ],
    "wof:name":"Junior Achievement Student",
    "wof:placetype":"venue"
},
  "geometry": {"coordinates":[-123.36148071300001,48.4226493835],"type":"Point"}
}