{
  "type": "Feature",
  "properties": {
    "addr:full":"2125 Columbia Ave Rossland BC V0G 1Y0",
    "addr:housenumber":"2125",
    "addr:postcode":"v0g 1y0",
    "addr:street":"Columbia Ave",
    "iso:country":"CA",
    "sg:address":"2125 Columbia Ave",
    "sg:city":"Rossland",
    "sg:classifiers":[
        {
            "category":"Travel",
            "subcategory":"Hotels & Motels",
            "type":"Entertainment"
        }
    ],
    "sg:phone":"+1 250 362 7160",
    "sg:postcode":"V0G 1Y0",
    "sg:province":"BC",
    "wof:name":"Mountain Shadow Hostel",
    "wof:placetype":"venue"
},
  "geometry": {"coordinates":[-117.79804229699999,49.0767402649],"type":"Point"}
}