{
  "type": "Feature",
  "properties": {
    "iso:country":"CA",
    "sg:address":"6 Cheritan Crt",
    "sg:city":"St Catharines",
    "sg:classifiers":[
        {
            "category":"Professional",
            "subcategory":"Computer Services",
            "type":"Services"
        }
    ],
    "sg:phone":"+1 905 938 2444",
    "sg:postcode":"L2N 7J7",
    "sg:province":"ON",
    "sg:tags":[
        "consultant"
    ],
    "wof:name":"Quick Solutions Inc",
    "wof:placetype":"venue"
},
  "geometry": {"coordinates":[-79.2862167358,43.191783905],"type":"Point"}
}