{
  "type": "Feature",
  "properties": {
    "addr:full":"1737 Dewdney Ave Regina SK S4R 1G5",
    "addr:housenumber":"1737",
    "addr:postcode":"s4r 1g5",
    "addr:street":"Dewdney Ave",
    "iso:country":"CA",
    "sg:address":"1737 Dewdney Ave",
    "sg:city":"Regina",
    "sg:classifiers":[
        {
            "category":"Home & Garden",
            "subcategory":"Building Materials",
            "type":"Retail Goods"
        }
    ],
    "sg:phone":"+1 306 525 2791",
    "sg:postcode":"S4R 1G5",
    "sg:province":"SK",
    "sg:tags":[
        "lumber"
    ],
    "wof:name":"Fries Tallman Lumber Ltd",
    "wof:placetype":"venue"
},
  "geometry": {"coordinates":[-104.605164,50.454987],"type":"Point"}
}