{
  "type": "Feature",
  "properties": {
    "addr:full":"4290 Dunbar St Vancouver BC V6S 2E9",
    "addr:housenumber":"4290",
    "addr:postcode":"v6s 2e9",
    "addr:street":"Dunbar St",
    "iso:country":"CA",
    "sg:address":"4290 Dunbar St",
    "sg:city":"Vancouver",
    "sg:classifiers":[
        {
            "category":"Shopping",
            "type":"Retail Goods"
        }
    ],
    "sg:phone":"+1 604 732 6778",
    "sg:postcode":"V6S 2E9",
    "sg:province":"BC",
    "sg:tags":[
        "picture",
        "frame",
        "art",
        "gallery",
        "dealer"
    ],
    "wof:name":"Omega Custom Framing & Gallery",
    "wof:placetype":"venue"
},
  "geometry": {"coordinates":[-123.184997559,49.2482337952],"type":"Point"}
}