{
  "type": "Feature",
  "properties": {
    "addr:full":"9814 44 Ave NW Edmonton AB T6E 5E5",
    "addr:housenumber":"9814",
    "addr:postcode":"t6e 5e5",
    "addr:street":"44 Ave Nw",
    "iso:country":"CA",
    "sg:address":"9814 44 Ave NW",
    "sg:city":"Edmonton",
    "sg:classifiers":[
        {
            "category":"Building & Trades",
            "subcategory":"Plumbing",
            "type":"Services"
        }
    ],
    "sg:phone":"+1 780 496 9479",
    "sg:postcode":"T6E 5E5",
    "sg:province":"AB",
    "sg:tags":[
        "contractor"
    ],
    "wof:name":"Web Mechanical Svc Ltd",
    "wof:placetype":"venue"
},
  "geometry": {"coordinates":[-113.484978,53.482063],"type":"Point"}
}