{
  "type": "Feature",
  "properties": {
    "addr:full":"90 Front St Sioux Lookout ON P8T 1B2",
    "addr:housenumber":"90",
    "addr:postcode":"p8t 1b2",
    "addr:street":"Front St",
    "iso:country":"CA",
    "sg:address":"90 Front St",
    "sg:city":"Sioux Lookout",
    "sg:classifiers":[
        {
            "category":"Personal",
            "subcategory":"Beauty Salon",
            "type":"Services"
        }
    ],
    "sg:phone":"+1 807 737 2736",
    "sg:postcode":"P8T 1B2",
    "sg:province":"ON",
    "wof:name":"Shear Pleasure Hair Design",
    "wof:placetype":"venue"
},
  "geometry": {"coordinates":[-91.9228668213,50.0980377197],"type":"Point"}
}