{
  "type": "Feature",
  "properties": {
    "addr:full":"1225 Rue Crescent Montreal QC H3G 2B1",
    "addr:housenumber":"1225",
    "addr:postcode":"h3g 2b1",
    "addr:street":"Rue Crescent",
    "iso:country":"CA",
    "sg:address":"1225 Rue Crescent",
    "sg:city":"Montreal",
    "sg:classifiers":[
        {
            "category":"Bars & Pubs",
            "type":"Food & Drink"
        }
    ],
    "sg:phone":"+1 514 861 4111",
    "sg:postcode":"H3G 2B1",
    "sg:province":"QC",
    "wof:name":"Hurley Irish Pub",
    "wof:placetype":"venue"
},
  "geometry": {"coordinates":[-73.574532,45.496796],"type":"Point"}
}