{
  "type": "Feature",
  "properties": {
    "addr:full":"15 Julian Ave Ottawa ON K1Y 0S6",
    "addr:housenumber":"15",
    "addr:postcode":"k1y 0s6",
    "addr:street":"Julian Ave",
    "iso:country":"CA",
    "sg:address":"15 Julian Ave",
    "sg:city":"Ottawa",
    "sg:classifiers":[
        {
            "category":"Organizations",
            "subcategory":"Professional Association",
            "type":"Services"
        }
    ],
    "sg:phone":"+1 613 729 2102",
    "sg:postcode":"K1Y 0S6",
    "sg:province":"ON",
    "wof:name":"Health Care Public Relations",
    "wof:placetype":"venue"
},
  "geometry": {"coordinates":[-75.734634,45.398685],"type":"Point"}
}