{
  "type": "Feature",
  "properties": {
    "addr:full":"220 Boul DE LA Montagne Saint-Casimir QC G0A 3L0",
    "addr:housenumber":"220",
    "addr:postcode":"g0a 3l0",
    "addr:street":"Boul De La Montagne",
    "iso:country":"CA",
    "sg:address":"220 Boul DE LA Montagne",
    "sg:city":"Saint-Casimir",
    "sg:classifiers":[
        {
            "category":"Government",
            "subcategory":"Office",
            "type":"Public Place"
        }
    ],
    "sg:phone":"+1 418 339 2543",
    "sg:postcode":"G0A 3L0",
    "sg:province":"QC",
    "sg:tags":[
        "village"
    ],
    "wof:name":"St-Casimir Secretariat",
    "wof:placetype":"venue"
},
  "geometry": {"coordinates":[-72.14110599999999,46.656254],"type":"Point"}
}