{
  "type": "Feature",
  "properties": {
    "addr:full":"Edmonton AB T5K 1Y4",
    "addr:postcode":"t5k 1y4",
    "iso:country":"CA",
    "sg:city":"Edmonton",
    "sg:classifiers":[
        {
            "category":"Personal",
            "subcategory":"Beauty Salon",
            "type":"Services"
        }
    ],
    "sg:phone":"+1 780 482 5838",
    "sg:postcode":"T5K 1Y4",
    "sg:province":"AB",
    "wof:name":"Networks Hair & Body Studio",
    "wof:placetype":"venue"
},
  "geometry": {"coordinates":[-113.5252,53.541664],"type":"Point"}
}