{
  "type": "Feature",
  "properties": {
    "addr:full":"14 Pacific Lane Brampton ON L6S 3V1",
    "addr:housenumber":"14",
    "addr:postcode":"l6s 3v1",
    "addr:street":"Pacific Lane",
    "iso:country":"CA",
    "sg:address":"14 Pacific Lane",
    "sg:city":"Brampton",
    "sg:classifiers":[
        {
            "category":"Wholesale",
            "subcategory":"Groceries",
            "type":"Manufacturing & Wholesale Goods"
        }
    ],
    "sg:phone":"+1 905 793 1210",
    "sg:postcode":"L6S 3V1",
    "sg:province":"ON",
    "sg:tags":[
        "grocer"
    ],
    "wof:name":"Ach Food CO Canada",
    "wof:placetype":"venue"
},
  "geometry": {"coordinates":[-79.7385635376,43.7479934692],"type":"Point"}
}