{
  "type": "Feature",
  "properties": {
    "addr:full":"1797 Huron Church Rd Windsor ON N9C 2L3",
    "addr:housenumber":"1797",
    "addr:postcode":"n9c 2l3",
    "addr:street":"Huron Church Rd",
    "iso:country":"CA",
    "sg:address":"1797 Huron Church Rd",
    "sg:city":"Windsor",
    "sg:classifiers":[
        {
            "category":"Restaurant",
            "type":"Food & Drink"
        }
    ],
    "sg:phone":"+1 519 254 9779",
    "sg:postcode":"N9C 2L3",
    "sg:province":"ON",
    "wof:name":"Kfc",
    "wof:placetype":"venue"
},
  "geometry": {"coordinates":[-83.055595,42.282883],"type":"Point"}
}