{
  "type": "Feature",
  "properties": {
    "addr:full":"15 Ch Fisher Austin QC J0B 1B0",
    "addr:housenumber":"15",
    "addr:postcode":"j0b 1b0",
    "addr:street":"Ch Fisher",
    "iso:country":"CA",
    "sg:address":"15 Ch Fisher",
    "sg:city":"Austin",
    "sg:classifiers":[
        {
            "category":"Travel",
            "subcategory":"Hotels & Motels",
            "type":"Entertainment"
        }
    ],
    "sg:phone":"+1 819 843 1398",
    "sg:postcode":"J0B 1B0",
    "sg:province":"QC",
    "sg:tags":[
        "breakfast",
        "accommodation",
        "bed"
    ],
    "wof:name":"L'Echappee Belle",
    "wof:placetype":"venue"
},
  "geometry": {"coordinates":[-72.278587,45.179256],"type":"Point"}
}