{
  "type": "Feature",
  "properties": {
    "addr:full":"1309 Yonge St S Walkerton ON N0G 2V0",
    "addr:housenumber":"1309",
    "addr:postcode":"n0g 2v0",
    "addr:street":"Yonge St S Walkerton",
    "iso:country":"CA",
    "sg:address":"1309 Yonge St S",
    "sg:city":"Walkerton",
    "sg:classifiers":[
        {
            "category":"Health Services",
            "subcategory":"Doctor",
            "type":"Services"
        }
    ],
    "sg:phone":"+1 519 881 1200",
    "sg:postcode":"N0G 2V0",
    "sg:province":"ON",
    "sg:tags":[
        "physician",
        "surgeon"
    ],
    "wof:name":"Ponesse, David MD",
    "wof:placetype":"venue"
},
  "geometry": {"coordinates":[-81.1495513916,44.1177062988],"type":"Point"}
}