{
  "type": "Feature",
  "properties": {
    "addr:full":"4094 Rue Laval Lac-Megantic QC G6B 1B2",
    "addr:housenumber":"4094",
    "addr:postcode":"g6b 1b2",
    "addr:street":"Rue Laval Lac-Megantic",
    "iso:country":"CA",
    "sg:address":"4094 Rue Laval",
    "sg:city":"Lac-Megantic",
    "sg:classifiers":[
        {
            "category":"Retail",
            "subcategory":"Auto Repair",
            "type":"Services"
        }
    ],
    "sg:phone":"+1 819 583 3005",
    "sg:postcode":"G6B 1B2",
    "sg:province":"QC",
    "sg:tags":[
        "repairing",
        "automobile"
    ],
    "wof:name":"Y Turmel Auto Electric",
    "wof:placetype":"venue"
},
  "geometry": {"coordinates":[-70.89711,45.584858],"type":"Point"}
}