{
  "type": "Feature",
  "properties": {
    "iso:country":"CA",
    "sg:address":"1111 Flint Rd",
    "sg:city":"North York",
    "sg:classifiers":[
        {
            "category":"Autos & Motor Vehicles",
            "subcategory":"Auto Supplies",
            "type":"Retail Goods"
        }
    ],
    "sg:phone":"+1 416 665 9999",
    "sg:postcode":"M3J 3C7",
    "sg:province":"ON",
    "sg:tags":[
        "tire"
    ],
    "wof:name":"Canada Tire & Supply",
    "wof:placetype":"venue"
},
  "geometry": {"coordinates":[-79.481331,43.778057],"type":"Point"}
}