{
  "type": "Feature",
  "properties": {
    "addr:full":"49 Richard Way SW Calgary AB T3E 7M8",
    "addr:housenumber":"49",
    "addr:postcode":"t3e 7m8",
    "addr:street":"Richard Way Sw",
    "iso:country":"CA",
    "sg:address":"49 Richard Way SW",
    "sg:city":"Calgary",
    "sg:classifiers":[
        {
            "category":"Health Services",
            "subcategory":"Clinic",
            "type":"Services"
        }
    ],
    "sg:phone":"+1 403 247 3337",
    "sg:postcode":"T3E 7M8",
    "sg:province":"AB",
    "sg:tags":[
        "information",
        "program",
        "referral"
    ],
    "wof:name":"Eye To Eye Imaging Inc",
    "wof:placetype":"venue"
},
  "geometry": {"coordinates":[-114.131561279,51.0064353943],"type":"Point"}
}