{
  "type": "Feature",
  "properties": {
    "addr:full":"755 Ch Du Sablon Laval QC H7W 4H5",
    "addr:housenumber":"755",
    "addr:postcode":"h7w 4h5",
    "addr:street":"Ch Du Sablon",
    "iso:country":"CA",
    "sg:address":"755 Ch Du Sablon",
    "sg:city":"Laval",
    "sg:classifiers":[
        {
            "category":"Recreation",
            "type":"Entertainment"
        }
    ],
    "sg:phone":"+1 450 688 8961",
    "sg:postcode":"H7W 4H5",
    "sg:province":"QC",
    "sg:tags":[
        "center",
        "hall",
        "auditorium"
    ],
    "wof:name":"Centre DE Sablon",
    "wof:placetype":"venue"
},
  "geometry": {"coordinates":[-73.7685546875,45.5320205688],"type":"Point"}
}