{
  "type": "Feature",
  "properties": {
    "addr:full":"665 Jones St Qualicum Beach BC V9K 1H1",
    "addr:housenumber":"665",
    "addr:postcode":"v9k 1h1",
    "addr:street":"Jones St",
    "iso:country":"CA",
    "sg:address":"665 Jones St",
    "sg:city":"Qualicum Beach",
    "sg:classifiers":[
        {
            "category":"Recreation",
            "type":"Entertainment"
        }
    ],
    "sg:phone":"+1 250 752 3341",
    "sg:postcode":"V9K 1H1",
    "sg:province":"BC",
    "sg:tags":[
        "amusement"
    ],
    "wof:name":"Qualicum Beach Lawn Bowling",
    "wof:placetype":"venue"
},
  "geometry": {"coordinates":[-124.449326,49.348122],"type":"Point"}
}