{
  "type": "Feature",
  "properties": {
    "addr:full":"302 Centre St Cremona AB T0M 0R0",
    "addr:housenumber":"302",
    "addr:postcode":"t0m 0r0",
    "addr:street":"Centre St",
    "iso:country":"CA",
    "sg:address":"302 Centre St",
    "sg:city":"Cremona",
    "sg:classifiers":[
        {
            "category":"Recreation",
            "type":"Entertainment"
        }
    ],
    "sg:phone":"+1 403 637 2763",
    "sg:postcode":"T0M 0R0",
    "sg:province":"AB",
    "sg:tags":[
        "hall",
        "auditorium"
    ],
    "wof:name":"Cremona Community Hall",
    "wof:placetype":"venue"
},
  "geometry": {"coordinates":[-114.489075,51.546272],"type":"Point"}
}