{
  "type": "Feature",
  "properties": {
    "addr:full":"4784 Hwy 1 Granville Ferry NS B0S 1K0",
    "addr:housenumber":"4784",
    "addr:postcode":"b0s 1k0",
    "addr:street":"Hwy 1",
    "iso:country":"CA",
    "sg:address":"4784 Hwy 1",
    "sg:city":"Granville Ferry",
    "sg:classifiers":[
        {
            "category":"Restaurant",
            "type":"Food & Drink"
        }
    ],
    "sg:phone":"+1 902 532 0909",
    "sg:postcode":"B0S 1K0",
    "sg:province":"NS",
    "wof:name":"Sweet Secret Restaurants",
    "wof:placetype":"venue"
},
  "geometry": {"coordinates":[-65.5221328735,44.7518539429],"type":"Point"}
}