{
  "type": "Feature",
  "properties": {
    "addr:full":"4510 Hwy 6 Miller Lake ON N0H 1Z0",
    "addr:housenumber":"4510",
    "addr:postcode":"n0h 1z0",
    "addr:street":"Hwy 6",
    "iso:country":"CA",
    "sg:address":"4510 Hwy 6",
    "sg:city":"Miller Lake",
    "sg:classifiers":[
        {
            "category":"Travel",
            "subcategory":"Campground",
            "type":"Entertainment"
        }
    ],
    "sg:phone":"+1 519 795 7575",
    "sg:postcode":"N0H 1Z0",
    "sg:province":"ON",
    "wof:name":"Maple Ridge Family Campground",
    "wof:placetype":"venue"
},
  "geometry": {"coordinates":[-81.443016,45.101711],"type":"Point"}
}