{
  "type": "Feature",
  "properties": {
    "addr:full":"243 Church St St Catharines ON L2R 3E8",
    "addr:housenumber":"243",
    "addr:postcode":"l2r 3e8",
    "addr:street":"Church St",
    "iso:country":"CA",
    "sg:address":"243 Church St",
    "sg:city":"St Catharines",
    "sg:classifiers":[
        {
            "category":"Professional",
            "subcategory":"Detective & Security Services",
            "type":"Services"
        }
    ],
    "sg:phone":"+1 905 688 9222",
    "sg:postcode":"L2R 3E8",
    "sg:province":"ON",
    "sg:tags":[
        "investigator"
    ],
    "wof:name":"Urquhart Investigation & Rsrch",
    "wof:placetype":"venue"
},
  "geometry": {"coordinates":[-79.236214,43.163872],"type":"Point"}
}