{
  "type": "Feature",
  "properties": {
    "addr:full":"255 Commercial St Berwick NS B0P 1E0",
    "addr:housenumber":"255",
    "addr:postcode":"b0p 1e0",
    "addr:street":"Commercial St",
    "iso:country":"CA",
    "sg:address":"255 Commercial St",
    "sg:city":"Berwick",
    "sg:classifiers":[
        {
            "category":"Health Services",
            "subcategory":"Nursing And Care Facility",
            "type":"Services"
        }
    ],
    "sg:phone":"+1 902 538 9579",
    "sg:postcode":"B0P 1E0",
    "sg:province":"NS",
    "sg:tags":[
        "home",
        "convalescent"
    ],
    "wof:name":"New Vision Special Care Homes",
    "wof:placetype":"venue"
},
  "geometry": {"coordinates":[-64.735367,45.043308],"type":"Point"}
}