{
  "type": "Feature",
  "properties": {
    "iso:country":"CA",
    "sg:address":"9094 148 St",
    "sg:city":"Surrey",
    "sg:classifiers":[
        {
            "category":"Building & Trades",
            "subcategory":"Construction",
            "type":"Services"
        }
    ],
    "sg:phone":"+1 604 951 0890",
    "sg:postcode":"V3R 3W6",
    "sg:province":"BC",
    "sg:tags":[
        "general",
        "contractor"
    ],
    "wof:name":"Ed's Construction Ltd",
    "wof:placetype":"venue"
},
  "geometry": {"coordinates":[-122.81217956499999,49.1682052612],"type":"Point"}
}