{
  "type": "Feature",
  "properties": {
    "addr:full":"782 York St London ON N5W 2S9",
    "addr:housenumber":"782",
    "addr:postcode":"n5w 2s9",
    "addr:street":"York St",
    "iso:country":"CA",
    "sg:address":"782 York St",
    "sg:city":"London",
    "sg:classifiers":[
        {
            "category":"Building & Trades",
            "subcategory":"Construction",
            "type":"Services"
        }
    ],
    "sg:phone":"+1 519 438 0522",
    "sg:postcode":"N5W 2S9",
    "sg:province":"ON",
    "sg:tags":[
        "resurfacing",
        "laying",
        "refinishing",
        "floor"
    ],
    "wof:name":"Huron Flooring Ltd",
    "wof:placetype":"venue"
},
  "geometry": {"coordinates":[-81.224358,42.988068],"type":"Point"}
}