{
  "type": "Feature",
  "properties": {
    "addr:full":"126 York St Ottawa ON K1N 5T5",
    "addr:housenumber":"126",
    "addr:postcode":"k1n 5t5",
    "addr:street":"York St",
    "iso:country":"CA",
    "sg:address":"126 York St",
    "sg:city":"Ottawa",
    "sg:classifiers":[
        {
            "category":"Manufacturing",
            "subcategory":"Printing",
            "type":"Manufacturing & Wholesale Goods"
        }
    ],
    "sg:phone":"+1 613 244 8280",
    "sg:postcode":"K1N 5T5",
    "sg:province":"ON",
    "sg:tags":[
        "publisher"
    ],
    "wof:name":"Aviation Publishers CO Ltd",
    "wof:placetype":"venue"
},
  "geometry": {"coordinates":[-75.6901855469,45.4291381836],"type":"Point"}
}