{
  "type": "Feature",
  "properties": {
    "addr:full":"15 St. Peters Rd Charlottetown PE C1A 5N1",
    "addr:housenumber":"15",
    "addr:postcode":"c1a 5n1",
    "addr:street":"St. Peters Rd",
    "iso:country":"CA",
    "sg:address":"15 St. Peters Rd",
    "sg:city":"Charlottetown",
    "sg:classifiers":[
        {
            "category":"Shopping",
            "subcategory":"Used Merchandise",
            "type":"Retail Goods"
        }
    ],
    "sg:phone":"+1 902 367 3065",
    "sg:postcode":"C1A 5N1",
    "sg:province":"PE",
    "sg:tags":[
        "pawnbroker"
    ],
    "wof:name":"Island Collateral & Sales Inc",
    "wof:placetype":"venue"
},
  "geometry": {"coordinates":[-63.123291,46.247135],"type":"Point"}
}