{
  "type": "Feature",
  "properties": {
    "addr:full":"3814 Rue Masson Montreal QC H1X 1S8",
    "addr:housenumber":"3814",
    "addr:postcode":"h1x 1s8",
    "addr:street":"Rue Masson",
    "iso:country":"CA",
    "sg:address":"3814 Rue Masson",
    "sg:city":"Montreal",
    "sg:classifiers":[
        {
            "category":"Manufacturing",
            "subcategory":"Printing",
            "type":"Manufacturing & Wholesale Goods"
        }
    ],
    "sg:phone":"+1 514 272 6818",
    "sg:postcode":"H1X 1S8",
    "sg:province":"QC",
    "sg:tags":[
        "printer"
    ],
    "wof:name":"Impression Production Lb",
    "wof:placetype":"venue"
},
  "geometry": {"coordinates":[-73.5700683594,45.5561752319],"type":"Point"}
}