{
  "type": "Feature",
  "properties": {
    "addr:full":"86 Rue Principale Sainte-Angele-DE-Monnoir QC J0L 1P0",
    "addr:housenumber":"86",
    "addr:postcode":"j0l 1p0",
    "addr:street":"Rue Principale",
    "iso:country":"CA",
    "sg:address":"86 Rue Principale",
    "sg:city":"Sainte-Angele-DE-Monnoir",
    "sg:classifiers":[
        {
            "category":"Wholesale",
            "subcategory":"Meat",
            "type":"Manufacturing & Wholesale Goods"
        }
    ],
    "sg:phone":"+1 450 460 3069",
    "sg:postcode":"J0L 1P0",
    "sg:province":"QC",
    "sg:tags":[
        "butchering"
    ],
    "wof:name":"Marche D'Auteuil Enr",
    "wof:placetype":"venue"
},
  "geometry": {"coordinates":[-73.10720825200001,45.3905181885],"type":"Point"}
}