{
  "type": "Feature",
  "properties": {
    "iso:country":"CA",
    "sg:address":"772 Boul Lionel-Boulet",
    "sg:city":"Varennes",
    "sg:classifiers":[
        {
            "category":"Building & Trades",
            "subcategory":"Electrical",
            "type":"Services"
        }
    ],
    "sg:phone":"+1 450 652 5909",
    "sg:postcode":"J3X 1P7",
    "sg:province":"QC",
    "sg:tags":[
        "electric",
        "contractor"
    ],
    "wof:name":"Entreprises D'Electricite",
    "wof:placetype":"venue"
},
  "geometry": {"coordinates":[-73.4143295288,45.6502532959],"type":"Point"}
}