{
  "type": "Feature",
  "properties": {
    "addr:full":"Bala ON P0C 1A0",
    "addr:postcode":"p0c 1a0",
    "iso:country":"CA",
    "sg:city":"Bala",
    "sg:classifiers":[
        {
            "category":"Manufacturing",
            "subcategory":"Tools & Machinery",
            "type":"Manufacturing & Wholesale Goods"
        }
    ],
    "sg:phone":"+1 705 762 3440",
    "sg:postcode":"P0C 1A0",
    "sg:province":"ON",
    "sg:tags":[
        "contractor",
        "heating",
        "electric"
    ],
    "wof:name":"Muskoka Rural Electric Contrs",
    "wof:placetype":"venue"
},
  "geometry": {"coordinates":[-79.617676,45.017582],"type":"Point"}
}