{
  "type": "Feature",
  "properties": {
    "addr:full":"5893 Route 340 Haut-Paquetville NB E8R 1S9",
    "addr:housenumber":"5893",
    "addr:postcode":"e8r 1s9",
    "addr:street":"Route 340",
    "iso:country":"CA",
    "sg:address":"5893 Route 340",
    "sg:city":"Haut-Paquetville",
    "sg:classifiers":[
        {
            "category":"Building & Trades",
            "subcategory":"Landscaping Services",
            "type":"Services"
        }
    ],
    "sg:phone":"+1 506 764 5391",
    "sg:postcode":"E8R 1S9",
    "sg:province":"NB",
    "sg:tags":[
        "landscape",
        "contractor"
    ],
    "wof:name":"Paysagiste Beau-Gazon Enr",
    "wof:placetype":"venue"
},
  "geometry": {"coordinates":[-65.114304,47.666782],"type":"Point"}
}