{
  "type": "Feature",
  "properties": {
    "addr:full":"68 Healey Rd Bolton ON L7E 5A4",
    "addr:housenumber":"68",
    "addr:postcode":"l7e 5a4",
    "addr:street":"Healey Rd",
    "iso:country":"CA",
    "sg:address":"68 Healey Rd",
    "sg:city":"Bolton",
    "sg:classifiers":[
        {
            "category":"Wholesale",
            "subcategory":"Machinery & Supplies",
            "type":"Manufacturing & Wholesale Goods"
        }
    ],
    "sg:phone":"+1 905 951 8000",
    "sg:postcode":"L7E 5A4",
    "sg:province":"ON",
    "sg:tags":[
        "valve"
    ],
    "wof:name":"Syntec Process Equipment Ltd",
    "wof:placetype":"venue"
},
  "geometry": {"coordinates":[-79.7197113037,43.8629264832],"type":"Point"}
}