{
  "type": "Feature",
  "properties": {
    "iso:country":"CA",
    "sg:address":"11703 Groat Rd NW",
    "sg:city":"Edmonton",
    "sg:classifiers":[
        {
            "category":"Autos & Motor Vehicles",
            "subcategory":"Auto Supplies",
            "type":"Retail Goods"
        }
    ],
    "sg:phone":"+1 780 455 0848",
    "sg:postcode":"T5M 3K6",
    "sg:province":"AB",
    "sg:tags":[
        "tire"
    ],
    "wof:name":"OK Tire Stores",
    "wof:placetype":"venue"
},
  "geometry": {"coordinates":[-113.549149,53.568573],"type":"Point"}
}