{
  "type": "Feature",
  "properties": {
    "addr:full":"6424 Norwood St Halifax NS B3H 2L3",
    "addr:housenumber":"6424",
    "addr:postcode":"b3h 2l3",
    "addr:street":"Norwood St",
    "iso:country":"CA",
    "sg:address":"6424 Norwood St",
    "sg:city":"Halifax",
    "sg:classifiers":[
        {
            "category":"Professional",
            "subcategory":"Computer Services",
            "type":"Services"
        }
    ],
    "sg:phone":"+1 902 422 6378",
    "sg:postcode":"B3H 2L3",
    "sg:province":"NS",
    "sg:tags":[
        "consultant"
    ],
    "wof:name":"Evans Computer Applications",
    "wof:placetype":"venue"
},
  "geometry": {"coordinates":[-63.600033,44.64241],"type":"Point"}
}