{
  "type": "Feature",
  "properties": {
    "iso:country":"CA",
    "sg:address":"1270 Av William",
    "sg:city":"Sillery",
    "sg:classifiers":[
        {
            "category":"Health Services",
            "subcategory":"Doctor",
            "type":"Services"
        }
    ],
    "sg:phone":"+1 418 688 5018",
    "sg:postcode":"G1S 4G1",
    "sg:province":"QC",
    "sg:tags":[
        "physician",
        "surgeon"
    ],
    "wof:name":"Blair, Duane MD",
    "wof:placetype":"venue"
},
  "geometry": {"coordinates":[-71.249489,46.783424],"type":"Point"}
}