{
  "type": "Feature",
  "properties": {
    "addr:full":"1270 Av William Sillery QC G1S 4G1",
    "addr:housenumber":"1270",
    "addr:postcode":"g1s 4g1",
    "addr:street":"Av William",
    "iso:country":"CA",
    "sg:address":"1270 Av William",
    "sg:city":"Sillery",
    "sg:classifiers":[
        {
            "category":"Health Services",
            "subcategory":"Doctor",
            "type":"Services"
        }
    ],
    "sg:phone":"+1 418 688 5018",
    "sg:postcode":"G1S 4G1",
    "sg:province":"QC",
    "sg:tags":[
        "physician",
        "surgeon"
    ],
    "wof:name":"Blair, Duane MD",
    "wof:placetype":"venue"
},
  "geometry": {"coordinates":[-71.249489,46.783424],"type":"Point"}
}