{
  "type": "Feature",
  "properties": {
    "addr:full":"73 Roncesvalles Ave Toronto ON M6R 2K6",
    "addr:housenumber":"73",
    "addr:postcode":"m6r 2k6",
    "addr:street":"Roncesvalles Ave",
    "iso:country":"CA",
    "sg:address":"73 Roncesvalles Ave",
    "sg:city":"Toronto",
    "sg:classifiers":[
        {
            "category":"Cinema",
            "subcategory":"Movie Rental",
            "type":"Entertainment"
        }
    ],
    "sg:phone":"+1 416 534 7078",
    "sg:postcode":"M6R 2K6",
    "sg:province":"ON",
    "sg:tags":[
        "leasing",
        "video",
        "disc",
        "tape"
    ],
    "wof:name":"Filmbuff",
    "wof:placetype":"venue"
},
  "geometry": {"coordinates":[-79.44696807859999,43.6414222717],"type":"Point"}
}