{
  "type": "Feature",
  "properties": {
    "addr:full":"223 6th St Weyburn SK S4H 1B3",
    "addr:housenumber":"223",
    "addr:postcode":"s4h 1b3",
    "addr:street":"6Th St",
    "iso:country":"CA",
    "sg:address":"223 6th St",
    "sg:city":"Weyburn",
    "sg:classifiers":[
        {
            "category":"Professional",
            "subcategory":"Lawyer & Legal Services",
            "type":"Services"
        }
    ],
    "sg:phone":"+1 306 842 0261",
    "sg:postcode":"S4H 1B3",
    "sg:province":"SK",
    "sg:tags":[
        "attorney"
    ],
    "wof:name":"Bogar Laidlaw Law Firm",
    "wof:placetype":"venue"
},
  "geometry": {"coordinates":[-103.849327,49.663204],"type":"Point"}
}