{
  "type": "Feature",
  "properties": {
    "addr:full":"Montreal QC H4N 1L8",
    "addr:postcode":"h4n 1l8",
    "iso:country":"CA",
    "sg:city":"Montreal",
    "sg:classifiers":[
        {
            "category":"Health Services",
            "subcategory":"Doctor",
            "type":"Services"
        }
    ],
    "sg:phone":"+1 514 383 3632",
    "sg:postcode":"H4N 1L8",
    "sg:province":"QC",
    "sg:tags":[
        "dentist"
    ],
    "wof:name":"Abouabdallah, Raymond DDS",
    "wof:placetype":"venue"
},
  "geometry": {"coordinates":[-73.63369,45.581413],"type":"Point"}
}