{
  "type": "Feature",
  "properties": {
    "addr:full":"314 Frederick St Kitchener ON N2H 2N7",
    "addr:housenumber":"314",
    "addr:postcode":"n2h 2n7",
    "addr:street":"Frederick St",
    "iso:country":"CA",
    "sg:address":"314 Frederick St",
    "sg:city":"Kitchener",
    "sg:classifiers":[
        {
            "category":"Professional",
            "subcategory":"Lawyer & Legal Services",
            "type":"Services"
        }
    ],
    "sg:phone":"+1 519 578 9660",
    "sg:postcode":"N2H 2N7",
    "sg:province":"ON",
    "sg:tags":[
        "attorney"
    ],
    "wof:name":"Judith E Phipps Barristers",
    "wof:placetype":"venue"
},
  "geometry": {"coordinates":[-80.476845,43.45639],"type":"Point"}
}