{
  "type": "Feature",
  "properties": {
    "addr:full":"161 Rue Du Prince Sorel-Tracy QC J3P 4K6",
    "addr:housenumber":"161",
    "addr:postcode":"j3p 4k6",
    "addr:street":"Rue Du Prince",
    "iso:country":"CA",
    "sg:address":"161 Rue Du Prince",
    "sg:city":"Sorel-Tracy",
    "sg:classifiers":[
        {
            "category":"Organizations",
            "subcategory":"Religious Organization",
            "type":"Services"
        }
    ],
    "sg:phone":"+1 450 746 8607",
    "sg:postcode":"J3P 4K6",
    "sg:province":"QC",
    "sg:tags":[
        "church"
    ],
    "wof:name":"Presbytere Notre Dame",
    "wof:placetype":"venue"
},
  "geometry": {"coordinates":[-73.1126251221,46.0405731201],"type":"Point"}
}