{
  "type": "Feature",
  "properties": {
    "addr:full":"5050 Boul Wilfrid-Hamel Quebec QC G2E 5X5",
    "addr:housenumber":"5050",
    "addr:postcode":"g2e 5x5",
    "addr:street":"Boul Wilfrid-Hamel",
    "iso:country":"CA",
    "sg:address":"5050 Boul Wilfrid-Hamel",
    "sg:city":"Quebec",
    "sg:classifiers":[
        {
            "category":"Personal",
            "subcategory":"Tanning Parlor",
            "type":"Services"
        }
    ],
    "sg:phone":"+1 418 871 6677",
    "sg:postcode":"G2E 5X5",
    "sg:province":"QC",
    "sg:tags":[
        "salon"
    ],
    "wof:name":"Salon DE Bronzage D'Azur",
    "wof:placetype":"venue"
},
  "geometry": {"coordinates":[-71.33058200000001,46.803379],"type":"Point"}
}