{
  "type": "Feature",
  "properties": {
    "addr:full":"10036 Av Plaza Montreal-Nord QC H1H 4L6",
    "addr:housenumber":"10036",
    "addr:postcode":"h1h 4l6",
    "addr:street":"Av Plaza",
    "iso:country":"CA",
    "sg:address":"10036 Av Plaza",
    "sg:city":"Montreal-Nord",
    "sg:classifiers":[
        {
            "category":"Retail",
            "subcategory":"Auto Repair",
            "type":"Services"
        }
    ],
    "sg:phone":"+1 514 326 0107",
    "sg:postcode":"H1H 4L6",
    "sg:province":"QC",
    "sg:tags":[
        "repairing",
        "automobile"
    ],
    "wof:name":"Feriste Auto Mecanique",
    "wof:placetype":"venue"
},
  "geometry": {"coordinates":[-73.63413199999999,45.581566],"type":"Point"}
}