{
  "type": "Feature",
  "properties": {
    "addr:full":"795 Boul Decarie Saint-Laurent QC H4L 3L3",
    "addr:housenumber":"795",
    "addr:postcode":"h4l 3l3",
    "addr:street":"Boul Decarie",
    "iso:country":"CA",
    "sg:address":"795 Boul Decarie",
    "sg:city":"Saint-Laurent",
    "sg:classifiers":[
        {
            "category":"Food & Beverages",
            "subcategory":"Groceries & Convenience Stores",
            "type":"Retail Goods"
        }
    ],
    "sg:phone":"+1 514 748 4992",
    "sg:postcode":"H4L 3L3",
    "sg:province":"QC",
    "wof:name":"Couche-Tard",
    "wof:placetype":"venue"
},
  "geometry": {"coordinates":[-73.678032,45.511513],"type":"Point"}
}