{
  "type": "Feature",
  "properties": {
    "addr:full":"60 Quarry Edge Dr Brampton ON L6V 4K2",
    "addr:housenumber":"60",
    "addr:postcode":"l6v 4k2",
    "addr:street":"Quarry Edge Dr",
    "iso:country":"CA",
    "sg:address":"60 Quarry Edge Dr",
    "sg:city":"Brampton",
    "sg:classifiers":[
        {
            "category":"Retail",
            "subcategory":"Laundry & Dry Cleaning",
            "type":"Services"
        }
    ],
    "sg:phone":"+1 905 456 1226",
    "sg:postcode":"L6V 4K2",
    "sg:province":"ON",
    "sg:tags":[
        "cleaners"
    ],
    "wof:name":"Capital M Cleaners",
    "wof:placetype":"venue"
},
  "geometry": {"coordinates":[-79.78237900000001,43.705685],"type":"Point"}
}