{
  "type": "Feature",
  "properties": {
    "iso:country":"CA",
    "sg:address":"60 Quarry Edge Dr",
    "sg:city":"Brampton",
    "sg:classifiers":[
        {
            "category":"Retail",
            "subcategory":"Laundry & Dry Cleaning",
            "type":"Services"
        }
    ],
    "sg:phone":"+1 905 456 1226",
    "sg:postcode":"L6V 4K2",
    "sg:province":"ON",
    "sg:tags":[
        "cleaners"
    ],
    "wof:name":"Capital M Cleaners",
    "wof:placetype":"venue"
},
  "geometry": {"coordinates":[-79.782379,43.705685],"type":"Point"}
}