{
  "type": "Feature",
  "properties": {
    "iso:country":"CA",
    "sg:address":"639 Eramosa Rd",
    "sg:city":"Guelph",
    "sg:classifiers":[
        {
            "category":"Organizations",
            "subcategory":"Religious Organization",
            "type":"Services"
        }
    ],
    "sg:phone":"+1 519 836 0520",
    "sg:postcode":"N1E 2N7",
    "sg:province":"ON",
    "sg:tags":[
        "church"
    ],
    "wof:name":"Jehovah's Witnesses",
    "wof:placetype":"venue"
},
  "geometry": {"coordinates":[-80.247101,43.571693],"type":"Point"}
}