{
  "type": "Feature",
  "properties": {
    "addr:full":"1300 8E Av Quebec QC G1J 5L5",
    "addr:housenumber":"1300",
    "addr:postcode":"g1j 5l5",
    "addr:street":"8E Av",
    "iso:country":"CA",
    "sg:address":"1300 8E Av",
    "sg:city":"Quebec",
    "sg:classifiers":[
        {
            "category":"Education",
            "subcategory":"College",
            "type":"Public Place"
        }
    ],
    "sg:phone":"+1 418 647 6600",
    "sg:postcode":"G1J 5L5",
    "sg:province":"QC",
    "sg:tags":[
        "academic",
        "school"
    ],
    "wof:name":"Cegep DE Limoilou",
    "wof:placetype":"venue"
},
  "geometry": {"coordinates":[-71.2278213501,46.8299560547],"type":"Point"}
}