{
  "type": "Feature",
  "properties": {
    "addr:full":"29 Elora S Harriston ON N0G 1Z0",
    "addr:housenumber":"29",
    "addr:postcode":"n0g 1z0",
    "addr:street":"Elora S",
    "iso:country":"CA",
    "sg:address":"29 Elora S",
    "sg:city":"Harriston",
    "sg:classifiers":[
        {
            "category":"Social Services",
            "type":"Services"
        }
    ],
    "sg:phone":"+1 519 338 5932",
    "sg:postcode":"N0G 1Z0",
    "sg:province":"ON",
    "sg:tags":[
        "youth",
        "organization",
        "center"
    ],
    "wof:name":"Minto Yfc Upper Deck",
    "wof:placetype":"venue"
},
  "geometry": {"coordinates":[-80.87043799999999,43.912895],"type":"Point"}
}