{
  "type": "Feature",
  "properties": {
    "addr:full":"80 Glendale Ave Deep River ON K0J 1P0",
    "addr:housenumber":"80",
    "addr:postcode":"k0j 1p0",
    "addr:street":"Glendale Ave",
    "iso:country":"CA",
    "sg:address":"80 Glendale Ave",
    "sg:city":"Deep River",
    "sg:classifiers":[
        {
            "category":"Organizations",
            "subcategory":"Religious Organization",
            "type":"Services"
        }
    ],
    "sg:phone":"+1 613 584 4131",
    "sg:postcode":"K0J 1P0",
    "sg:province":"ON",
    "sg:tags":[
        "church"
    ],
    "wof:name":"St Barnabas Anglican Church",
    "wof:placetype":"venue"
},
  "geometry": {"coordinates":[-77.4866943359,46.0976905823],"type":"Point"}
}