{
  "type": "Feature",
  "properties": {
    "addr:full":"Huntsville ON P1H 1X7",
    "addr:postcode":"p1h 1x7",
    "iso:country":"CA",
    "sg:city":"Huntsville",
    "sg:classifiers":[
        {
            "category":"Retail",
            "subcategory":"Auto Repair",
            "type":"Services"
        }
    ],
    "sg:phone":"+1 705 789 5711",
    "sg:postcode":"P1H 1X7",
    "sg:province":"ON",
    "sg:tags":[
        "truck"
    ],
    "wof:name":"Turner's Garage",
    "wof:placetype":"venue"
},
  "geometry": {"coordinates":[-79.24256099999999,45.317822],"type":"Point"}
}