{
  "type": "Feature",
  "properties": {
    "addr:full":"1219 Guildford Town Ctr Surrey BC V3R 7B7",
    "addr:housenumber":"1219",
    "addr:postcode":"v3r 7b7",
    "addr:street":"Guildford Town Ctr",
    "iso:country":"CA",
    "sg:address":"1219 Guildford Town Ctr",
    "sg:city":"Surrey",
    "sg:classifiers":[
        {
            "category":"Shopping",
            "subcategory":"Clothing, Apparel, & Fashions",
            "type":"Retail Goods"
        }
    ],
    "sg:phone":"+1 604 589 7542",
    "sg:postcode":"V3R 7B7",
    "sg:province":"BC",
    "sg:tags":[
        "accessory"
    ],
    "wof:name":"Claire's Boutiques",
    "wof:placetype":"venue"
},
  "geometry": {"coordinates":[-122.801704,49.188522],"type":"Point"}
}