{
  "type": "Feature",
  "properties": {
    "iso:country":"CA",
    "sg:city":"Didsbury",
    "sg:classifiers":[
        {
            "category":"Health Services",
            "subcategory":"Doctor",
            "type":"Services"
        }
    ],
    "sg:phone":"+1 403 335 3855",
    "sg:postcode":"T0M 0W0",
    "sg:province":"AB",
    "sg:tags":[
        "dentist"
    ],
    "wof:name":"Didsbury Dental Ctr",
    "wof:placetype":"venue"
},
  "geometry": {"coordinates":[-114.137443542,51.6636734009],"type":"Point"}
}