{
  "type": "Feature",
  "properties": {
    "addr:full":"333 St Mary Ave # 84 Winnipeg MB R3C 4A5",
    "addr:housenumber":"333",
    "addr:postcode":"r3c 4a5",
    "addr:street":"St Mary Ave # 84",
    "iso:country":"CA",
    "sg:address":"333 St Mary Ave # 84",
    "sg:city":"Winnipeg",
    "sg:classifiers":[
        {
            "category":"Health Services",
            "subcategory":"Doctor",
            "type":"Services"
        }
    ],
    "sg:phone":"+1 204 943 7573",
    "sg:postcode":"R3C 4A5",
    "sg:province":"MB",
    "sg:tags":[
        "dentist"
    ],
    "wof:name":"Sullivan, Dan J DDS",
    "wof:placetype":"venue"
},
  "geometry": {"coordinates":[-97.142715,49.890591],"type":"Point"}
}