{
  "type": "Feature",
  "properties": {
    "addr:full":"5918 Main St Niagara Falls ON L2G 5Z8",
    "addr:housenumber":"5918",
    "addr:postcode":"l2g 5z8",
    "addr:street":"Main St",
    "iso:country":"CA",
    "sg:address":"5918 Main St",
    "sg:city":"Niagara Falls",
    "sg:classifiers":[
        {
            "category":"Shopping",
            "subcategory":"Florist",
            "type":"Retail Goods"
        }
    ],
    "sg:phone":"+1 905 356 6325",
    "sg:postcode":"L2G 5Z8",
    "sg:province":"ON",
    "wof:name":"Corby's Flowers",
    "wof:placetype":"venue"
},
  "geometry": {"coordinates":[-79.09227752690001,43.088809967],"type":"Point"}
}