{
  "type": "Feature",
  "properties": {
    "addr:full":"500 Boul Des Laurentides Saint-Jerome QC J7Z 4M2",
    "addr:housenumber":"500",
    "addr:postcode":"j7z 4m2",
    "addr:street":"Boul Des Laurentides",
    "iso:country":"CA",
    "sg:address":"500 Boul Des Laurentides",
    "sg:city":"Saint-Jerome",
    "sg:classifiers":[
        {
            "category":"Shopping",
            "subcategory":"Clothing, Apparel, & Fashions",
            "type":"Retail Goods"
        }
    ],
    "sg:phone":"+1 450 565 3048",
    "sg:postcode":"J7Z 4M2",
    "sg:province":"QC",
    "sg:tags":[
        "lingerie"
    ],
    "wof:name":"Lingerie Alicia",
    "wof:placetype":"venue"
},
  "geometry": {"coordinates":[-73.9930343628,45.7626266479],"type":"Point"}
}