{
  "type": "Feature",
  "properties": {
    "iso:country":"CA",
    "sg:address":"991 Av Ogilvy",
    "sg:city":"Montreal",
    "sg:classifiers":[
        {
            "category":"Restaurant",
            "type":"Food & Drink"
        }
    ],
    "sg:phone":"+1 514 270 9636",
    "sg:postcode":"H3N 1P3",
    "sg:province":"QC",
    "wof:name":"Restaurant Nouveau Hellas",
    "wof:placetype":"venue"
},
  "geometry": {"coordinates":[-73.62753295900001,45.5254554749],"type":"Point"}
}