{
  "type": "Feature",
  "properties": {
    "addr:full":"7730 Boul Des Forges Trois-Rivieres QC G8Y 1Y9",
    "addr:housenumber":"7730",
    "addr:postcode":"g8y 1y9",
    "addr:street":"Boul Des Forges Trois-Rivieres",
    "iso:country":"CA",
    "sg:address":"7730 Boul Des Forges",
    "sg:city":"Trois-Rivieres",
    "sg:classifiers":[
        {
            "category":"Utilities",
            "type":"Services"
        }
    ],
    "sg:phone":"+1 819 693 9990",
    "sg:postcode":"G8Y 1Y9",
    "sg:province":"QC",
    "sg:tags":[
        "sweeping"
    ],
    "wof:name":"A-1 Balai Electro-Hydraulique",
    "wof:placetype":"venue"
},
  "geometry": {"coordinates":[-72.615685,46.376442],"type":"Point"}
}