{
  "type": "Feature",
  "properties": {
    "addr:full":"Regina SK S4W 1A3",
    "addr:postcode":"s4w 1a3",
    "iso:country":"CA",
    "sg:city":"Regina",
    "sg:classifiers":[
        {
            "category":"Autos & Motor Vehicles",
            "subcategory":"Automobile Sales",
            "type":"Retail Goods"
        }
    ],
    "sg:phone":"+1 306 791 4600",
    "sg:postcode":"S4W 1A3",
    "sg:province":"SK",
    "sg:tags":[
        "aircraft"
    ],
    "wof:name":"Prairie Aircraft Sales Ltd",
    "wof:placetype":"venue"
},
  "geometry": {"coordinates":[-104.651672,50.437645],"type":"Point"}
}