{
  "type": "Feature",
  "properties": {
    "addr:full":"9877 Coalburn Rd New Glasgow NS B2H 5C7",
    "addr:housenumber":"9877",
    "addr:postcode":"b2h 5c7",
    "addr:street":"Coalburn Rd",
    "iso:country":"CA",
    "sg:address":"9877 Coalburn Rd",
    "sg:city":"New Glasgow",
    "sg:classifiers":[
        {
            "category":"Building & Trades",
            "subcategory":"Construction",
            "type":"Services"
        }
    ],
    "sg:phone":"+1 902 922 2470",
    "sg:postcode":"B2H 5C7",
    "sg:province":"NS",
    "sg:tags":[
        "excavating",
        "contractor"
    ],
    "wof:name":"C & W Mac Dougall's Bulldozing",
    "wof:placetype":"venue"
},
  "geometry": {"coordinates":[-62.6434135437,45.5918388367],"type":"Point"}
}