{
  "type": "Feature",
  "properties": {
    "addr:full":"2210 Boul Henri-Bourassa E # 101 Montreal QC H2B 1T3",
    "addr:housenumber":"2210",
    "addr:postcode":"h2b 1t3",
    "addr:street":"Boul Henri-Bourassa E # 101",
    "iso:country":"CA",
    "sg:address":"2210 Boul Henri-Bourassa E # 101",
    "sg:city":"Montreal",
    "sg:classifiers":[
        {
            "category":"Professional",
            "subcategory":"Business Services",
            "type":"Services"
        }
    ],
    "sg:phone":"+1 514 381 1019",
    "sg:postcode":"H2B 1T3",
    "sg:province":"QC",
    "sg:tags":[
        "arbitration",
        "attorney"
    ],
    "wof:name":"Tremblay, Robert",
    "wof:placetype":"venue"
},
  "geometry": {"coordinates":[-73.655456543,45.5750045776],"type":"Point"}
}