{
  "type": "Feature",
  "properties": {
    "addr:full":"640 Eby Crest Rd Waterloo ON N2J 4G8",
    "addr:housenumber":"640",
    "addr:postcode":"n2j 4g8",
    "addr:street":"Eby Crest Rd",
    "iso:country":"CA",
    "sg:address":"640 Eby Crest Rd",
    "sg:city":"Waterloo",
    "sg:classifiers":[
        {
            "category":"Building & Trades",
            "subcategory":"Plumbing",
            "type":"Services"
        }
    ],
    "sg:phone":"+1 519 745 4963",
    "sg:postcode":"N2J 4G8",
    "sg:province":"ON",
    "sg:tags":[
        "contractor"
    ],
    "wof:name":"Butler Plumbing & Heating",
    "wof:placetype":"venue"
},
  "geometry": {"coordinates":[-80.520690918,43.4631385803],"type":"Point"}
}