{
  "type": "Feature",
  "properties": {
    "addr:full":"1220 Rue Mantha Rouyn-Noranda QC J9X 5B7",
    "addr:housenumber":"1220",
    "addr:postcode":"j9x 5b7",
    "addr:street":"Rue Mantha",
    "iso:country":"CA",
    "sg:address":"1220 Rue Mantha",
    "sg:city":"Rouyn-Noranda",
    "sg:classifiers":[
        {
            "category":"Building & Trades",
            "subcategory":"Construction",
            "type":"Services"
        }
    ],
    "sg:phone":"+1 819 797 9156",
    "sg:postcode":"J9X 5B7",
    "sg:province":"QC",
    "sg:tags":[
        "material",
        "roof",
        "structure"
    ],
    "wof:name":"Chevrons Rouyn-Noranda Inc",
    "wof:placetype":"venue"
},
  "geometry": {"coordinates":[-79.014511,48.237076],"type":"Point"}
}