{
  "type": "Feature",
  "properties": {
    "addr:full":"312 Boul Morin Asbestos QC J1T 3B9",
    "addr:housenumber":"312",
    "addr:postcode":"j1t 3b9",
    "addr:street":"Boul Morin",
    "iso:country":"CA",
    "sg:address":"312 Boul Morin",
    "sg:city":"Asbestos",
    "sg:classifiers":[
        {
            "category":"Organizations",
            "subcategory":"Community Association",
            "type":"Services"
        }
    ],
    "sg:phone":"+1 819 879 6275",
    "sg:postcode":"J1T 3B9",
    "sg:province":"QC",
    "sg:tags":[
        "club"
    ],
    "wof:name":"Comptoir Familial",
    "wof:placetype":"venue"
},
  "geometry": {"coordinates":[-71.9320144653,45.7729759216],"type":"Point"}
}