{
  "type": "Feature",
  "properties": {
    "addr:full":"Montreal QC H3W 1H9",
    "addr:postcode":"h3w 1h9",
    "iso:country":"CA",
    "sg:city":"Montreal",
    "sg:classifiers":[
        {
            "category":"Professional",
            "subcategory":"Accounting & Tax Preparation",
            "type":"Services"
        }
    ],
    "sg:phone":"+1 514 737 8888",
    "sg:postcode":"H3W 1H9",
    "sg:province":"QC",
    "sg:tags":[
        "accountant"
    ],
    "wof:name":"David S Haimovitch & CO",
    "wof:placetype":"venue"
},
  "geometry": {"coordinates":[-73.636589,45.495762],"type":"Point"}
}