{
  "type": "Feature",
  "properties": {
    "iso:country":"CA",
    "sg:address":"300 Rue Mederic-Dufresne",
    "sg:city":"Trois-Rivieres",
    "sg:classifiers":[
        {
            "category":"Building & Trades",
            "subcategory":"Construction",
            "type":"Services"
        }
    ],
    "sg:phone":"+1 819 371 1242",
    "sg:postcode":"G8Z 4H4",
    "sg:province":"QC",
    "sg:tags":[
        "excavating",
        "contractor"
    ],
    "wof:name":"J P Doyon Ltee",
    "wof:placetype":"venue"
},
  "geometry": {"coordinates":[-72.5736618042,46.3396339417],"type":"Point"}
}