{
  "type": "Feature",
  "properties": {
    "iso:country":"CA",
    "sg:address":"660 51st Ave E",
    "sg:city":"Vancouver",
    "sg:classifiers":[
        {
            "category":"Professional",
            "subcategory":"Lawyer & Legal Services",
            "type":"Services"
        }
    ],
    "sg:phone":"+1 604 325 5524",
    "sg:postcode":"V5X 1C9",
    "sg:province":"BC",
    "sg:tags":[
        "naturalization",
        "immigration"
    ],
    "wof:name":"Mcc Refugee Office",
    "wof:placetype":"venue"
},
  "geometry": {"coordinates":[-123.091598511,49.2234992981],"type":"Point"}
}