{
  "type": "Feature",
  "properties": {
    "iso:country":"CA",
    "sg:address":"605 Industrial Ave #200",
    "sg:city":"Ottawa",
    "sg:classifiers":[
        {
            "category":"Professional",
            "type":"Services"
        }
    ],
    "sg:phone":"+1 613 739 7189",
    "sg:postcode":"K1G 0Z1",
    "sg:province":"ON",
    "sg:tags":[
        "establishment",
        "market",
        "analysis",
        "research"
    ],
    "wof:name":"Canadian Research & Consulting",
    "wof:placetype":"venue"
},
  "geometry": {"coordinates":[-75.6415100098,45.411075592],"type":"Point"}
}