{
  "type": "Feature",
  "properties": {
    "addr:full":"24 Rue Mainville Sainte-Therese QC J7E 4V6",
    "addr:housenumber":"24",
    "addr:postcode":"j7e 4v6",
    "addr:street":"Rue Mainville Sainte-Therese",
    "iso:country":"CA",
    "sg:address":"24 Rue Mainville",
    "sg:city":"Sainte-Therese",
    "sg:classifiers":[
        {
            "category":"Real Estate",
            "subcategory":"Real Estate Agent",
            "type":"Services"
        }
    ],
    "sg:phone":"+1 450 434 2356",
    "sg:postcode":"J7E 4V6",
    "sg:province":"QC",
    "sg:tags":[
        "cooperative"
    ],
    "wof:name":"Cooperative Concept",
    "wof:placetype":"venue"
},
  "geometry": {"coordinates":[-73.82391357420001,45.6381568909],"type":"Point"}
}