{
  "type": "Feature",
  "properties": {
    "addr:full":"212 2nd Ave W Hanna AB T0J 1P0",
    "addr:housenumber":"212",
    "addr:postcode":"t0j 1p0",
    "addr:street":"2Nd Ave W",
    "iso:country":"CA",
    "sg:address":"212 2nd Ave W",
    "sg:city":"Hanna",
    "sg:classifiers":[
        {
            "category":"Government",
            "subcategory":"Office",
            "type":"Public Place"
        }
    ],
    "sg:phone":"+1 403 854 5600",
    "sg:postcode":"T0J 1P0",
    "sg:province":"AB",
    "wof:name":"Alberta Special Areas Board",
    "wof:placetype":"venue"
},
  "geometry": {"coordinates":[-111.929153,51.64299],"type":"Point"}
}