{
  "type": "Feature",
  "properties": {
    "addr:full":"100 Oak Point Hwy Winnipeg MB R2R 1T8",
    "addr:housenumber":"100",
    "addr:postcode":"r2r 1t8",
    "addr:street":"Oak Point Hwy",
    "iso:country":"CA",
    "sg:address":"100 Oak Point Hwy",
    "sg:city":"Winnipeg",
    "sg:classifiers":[
        {
            "category":"Autos & Motor Vehicles",
            "subcategory":"Fuel & Gas Station",
            "type":"Retail Goods"
        }
    ],
    "sg:phone":"+1 204 694 4559",
    "sg:postcode":"R2R 1T8",
    "sg:province":"MB",
    "sg:tags":[
        "oil"
    ],
    "wof:name":"Esso Imperial Oil",
    "wof:placetype":"venue"
},
  "geometry": {"coordinates":[-97.2121582031,49.9309272766],"type":"Point"}
}