{
  "type": "Feature",
  "properties": {
    "addr:full":"1194 Kennedy Rd Scarborough ON M1P 2L1",
    "addr:housenumber":"1194",
    "addr:postcode":"m1p 2l1",
    "addr:street":"Kennedy Rd",
    "iso:country":"CA",
    "sg:address":"1194 Kennedy Rd",
    "sg:city":"Scarborough",
    "sg:classifiers":[
        {
            "category":"Shopping",
            "subcategory":"Computers & Home Electronics",
            "type":"Retail Goods"
        }
    ],
    "sg:phone":"+1 416 759 7909",
    "sg:postcode":"M1P 2L1",
    "sg:province":"ON",
    "sg:tags":[
        "equipment",
        "electronic",
        "supply"
    ],
    "wof:name":"Electronic Connection",
    "wof:placetype":"venue"
},
  "geometry": {"coordinates":[-79.27675600000001,43.753933],"type":"Point"}
}