{
  "type": "Feature",
  "properties": {
    "addr:full":"1020 Princess Ave Brandon MB R7A 0P8",
    "addr:housenumber":"1020",
    "addr:postcode":"r7a 0p8",
    "addr:street":"Princess Ave",
    "iso:country":"CA",
    "sg:address":"1020 Princess Ave",
    "sg:city":"Brandon",
    "sg:classifiers":[
        {
            "category":"Banks & Credit Unions",
            "subcategory":"Bank",
            "type":"Services"
        }
    ],
    "sg:phone":"+1 204 729 2060",
    "sg:postcode":"R7A 0P8",
    "sg:province":"MB",
    "wof:name":"Westoba Credit Union Ltd",
    "wof:placetype":"venue"
},
  "geometry": {"coordinates":[-99.951797,49.846786],"type":"Point"}
}