{
  "type": "Feature",
  "properties": {
    "addr:full":"4475 Rue Bannantyne Verdun QC H4G 1E2",
    "addr:housenumber":"4475",
    "addr:postcode":"h4g 1e2",
    "addr:street":"Rue Bannantyne",
    "iso:country":"CA",
    "sg:address":"4475 Rue Bannantyne",
    "sg:city":"Verdun",
    "sg:classifiers":[
        {
            "category":"Recreation",
            "type":"Entertainment"
        }
    ],
    "sg:phone":"+1 514 768 2481",
    "sg:postcode":"H4G 1E2",
    "sg:province":"QC",
    "sg:tags":[
        "bingo",
        "game"
    ],
    "wof:name":"Bingodrome Enr",
    "wof:placetype":"venue"
},
  "geometry": {"coordinates":[-73.576210022,45.4598846436],"type":"Point"}
}