{
  "type": "Feature",
  "properties": {
    "addr:full":"4079 St Nicholas Rd Miscouche PE C0B 1T0",
    "addr:housenumber":"4079",
    "addr:postcode":"c0b 1t0",
    "addr:street":"St Nicholas Rd",
    "iso:country":"CA",
    "sg:address":"4079 St Nicholas Rd",
    "sg:city":"Miscouche",
    "sg:classifiers":[
        {
            "category":"Building & Trades",
            "subcategory":"Construction",
            "type":"Services"
        }
    ],
    "sg:phone":"+1 902 854 8000",
    "sg:postcode":"C0B 1T0",
    "sg:province":"PE",
    "sg:tags":[
        "insulation",
        "heat",
        "contractor"
    ],
    "wof:name":"Arnie's Insulation",
    "wof:placetype":"venue"
},
  "geometry": {"coordinates":[-63.862068,46.431465],"type":"Point"}
}