{
  "type": "Feature",
  "properties": {
    "addr:full":"2000 Blackacre Dr Oldcastle ON N0R 1L0",
    "addr:housenumber":"2000",
    "addr:postcode":"n0r 1l0",
    "addr:street":"Blackacre Dr",
    "iso:country":"CA",
    "sg:address":"2000 Blackacre Dr",
    "sg:city":"Oldcastle",
    "sg:classifiers":[
        {
            "category":"Manufacturing",
            "subcategory":"Tools & Machinery",
            "type":"Manufacturing & Wholesale Goods"
        }
    ],
    "sg:phone":"+1 519 737 6493",
    "sg:postcode":"N0R 1L0",
    "sg:province":"ON",
    "sg:tags":[
        "die",
        "maker"
    ],
    "wof:name":"Rezmin Tool & Die Inc",
    "wof:placetype":"venue"
},
  "geometry": {"coordinates":[-82.971283,42.233925],"type":"Point"}
}