{
  "type": "Feature",
  "properties": {
    "addr:full":"Whitby ON L1P 1G8",
    "addr:postcode":"l1p 1g8",
    "iso:country":"CA",
    "sg:city":"Whitby",
    "sg:classifiers":[
        {
            "category":"Government",
            "subcategory":"Office",
            "type":"Public Place"
        }
    ],
    "sg:phone":"+1 905 665 8182",
    "sg:postcode":"L1P 1G8",
    "sg:province":"ON",
    "wof:name":"Longfield, Judi",
    "wof:placetype":"venue"
},
  "geometry": {"coordinates":[-78.96235656739999,43.8751831055],"type":"Point"}
}