{
  "type": "Feature",
  "properties": {
    "addr:full":"Surrey BC V3W 1L3",
    "addr:postcode":"v3w 1l3",
    "iso:country":"CA",
    "sg:city":"Surrey",
    "sg:classifiers":[
        {
            "category":"Wholesale",
            "subcategory":"Metals & Minerals",
            "type":"Manufacturing & Wholesale Goods"
        }
    ],
    "sg:phone":"+1 604 543 4666",
    "sg:postcode":"V3W 1L3",
    "sg:province":"BC",
    "sg:tags":[
        "aluminum",
        "railing"
    ],
    "wof:name":"Contemporary Aluminum Railings",
    "wof:placetype":"venue"
},
  "geometry": {"coordinates":[-122.867744,49.143444],"type":"Point"}
}