{
  "type": "Feature",
  "properties": {
    "addr:full":"1314 Henderson Hwy Winnipeg MB R2G 1M4",
    "addr:housenumber":"1314",
    "addr:postcode":"r2g 1m4",
    "addr:street":"Henderson Hwy",
    "iso:country":"CA",
    "sg:address":"1314 Henderson Hwy",
    "sg:city":"Winnipeg",
    "sg:classifiers":[
        {
            "category":"Organizations",
            "subcategory":"Religious Organization",
            "type":"Services"
        }
    ],
    "sg:phone":"+1 204 334 4782",
    "sg:postcode":"R2G 1M4",
    "sg:province":"MB",
    "sg:tags":[
        "church"
    ],
    "wof:name":"Seventh-Day Adventist Church",
    "wof:placetype":"venue"
},
  "geometry": {"coordinates":[-97.0891952515,49.942363739],"type":"Point"}
}