{
  "type": "Feature",
  "properties": {
    "addr:full":"31 Ch Pointe-Du-Chene Shediac NB E4P 2L9",
    "addr:housenumber":"31",
    "addr:postcode":"e4p 2l9",
    "addr:street":"Ch Pointe-Du-Chene",
    "iso:country":"CA",
    "sg:address":"31 Ch Pointe-Du-Chene",
    "sg:city":"Shediac",
    "sg:classifiers":[
        {
            "category":"Building & Trades",
            "subcategory":"Construction",
            "type":"Services"
        }
    ],
    "sg:phone":"+1 506 532 4287",
    "sg:postcode":"E4P 2L9",
    "sg:province":"NB",
    "sg:tags":[
        "roofing",
        "contractor"
    ],
    "wof:name":"E & C Construction Ltd",
    "wof:placetype":"venue"
},
  "geometry": {"coordinates":[-64.515427,46.227104],"type":"Point"}
}