{
  "type": "Feature",
  "properties": {
    "addr:full":"3473 Walker Rd Windsor ON N8W 3S2",
    "addr:housenumber":"3473",
    "addr:postcode":"n8w 3s2",
    "addr:street":"Walker Rd",
    "iso:country":"CA",
    "sg:address":"3473 Walker Rd",
    "sg:city":"Windsor",
    "sg:classifiers":[
        {
            "category":"Building & Trades",
            "subcategory":"Construction",
            "type":"Services"
        }
    ],
    "sg:phone":"+1 519 969 4020",
    "sg:postcode":"N8W 3S2",
    "sg:province":"ON",
    "sg:tags":[
        "general",
        "contractor"
    ],
    "wof:name":"Vince Ferro Construction",
    "wof:placetype":"venue"
},
  "geometry": {"coordinates":[-82.976883,42.274708],"type":"Point"}
}