{
  "type": "Feature",
  "properties": {
    "addr:full":"Notre-Dame-Du-Mont-Carmel QC G0X 3J0",
    "addr:postcode":"g0x 3j0",
    "iso:country":"CA",
    "sg:city":"Notre-Dame-Du-Mont-Carmel",
    "sg:classifiers":[
        {
            "category":"Personal",
            "subcategory":"Beauty Salon",
            "type":"Services"
        }
    ],
    "sg:phone":"+1 819 376 1510",
    "sg:postcode":"G0X 3J0",
    "sg:province":"QC",
    "wof:name":"Salon Martine Enr",
    "wof:placetype":"venue"
},
  "geometry": {"coordinates":[-72.67672,46.470219],"type":"Point"}
}