{
  "type": "Feature",
  "properties": {
    "addr:full":"Calgary AB T2G 2G8",
    "addr:postcode":"t2g 2g8",
    "iso:country":"CA",
    "sg:city":"Calgary",
    "sg:classifiers":[
        {
            "category":"Banks & Credit Unions",
            "subcategory":"Investment Brokerage",
            "type":"Services"
        }
    ],
    "sg:phone":"+1 403 233 9352",
    "sg:postcode":"T2G 2G8",
    "sg:province":"AB",
    "wof:name":"First Capital Management Ltd",
    "wof:placetype":"venue"
},
  "geometry": {"coordinates":[-114.060265,51.046177],"type":"Point"}
}