{
  "type": "Feature",
  "properties": {
    "addr:full":"23 Thorold Rd E Welland ON L3C 3T3",
    "addr:housenumber":"23",
    "addr:postcode":"l3c 3t3",
    "addr:street":"Thorold Rd E",
    "iso:country":"CA",
    "sg:address":"23 Thorold Rd E",
    "sg:city":"Welland",
    "sg:classifiers":[
        {
            "category":"Food & Beverages",
            "subcategory":"Liquor & Beverages",
            "type":"Retail Goods"
        }
    ],
    "sg:phone":"+1 905 734 7826",
    "sg:postcode":"L3C 3T3",
    "sg:province":"ON",
    "sg:tags":[
        "beer",
        "ale"
    ],
    "wof:name":"Beer Store",
    "wof:placetype":"venue"
},
  "geometry": {"coordinates":[-79.245537,43.003601],"type":"Point"}
}