{
  "type": "Feature",
  "properties": {
    "addr:full":"Etobicoke ON M9W 6R6",
    "addr:postcode":"m9w 6r6",
    "iso:country":"CA",
    "sg:city":"Etobicoke",
    "sg:classifiers":[
        {
            "category":"Bus Charters",
            "type":"Transportation"
        }
    ],
    "sg:phone":"+1 416 675 0077",
    "sg:postcode":"M9W 6R6",
    "sg:province":"ON",
    "sg:tags":[
        "rental"
    ],
    "wof:name":"Executive Coach Svc",
    "wof:placetype":"venue"
},
  "geometry": {"coordinates":[-79.63423899999999,43.745895],"type":"Point"}
}