{
  "type": "Feature",
  "properties": {
    "iso:country":"CA",
    "sg:address":"42 Dunlop St E",
    "sg:city":"Barrie",
    "sg:classifiers":[
        {
            "category":"Shopping",
            "subcategory":"Bicycles & Sporting Goods",
            "type":"Retail Goods"
        }
    ],
    "sg:phone":"+1 705 725 8888",
    "sg:postcode":"L4M 1A3",
    "sg:province":"ON",
    "wof:name":"Tropical North",
    "wof:placetype":"venue"
},
  "geometry": {"coordinates":[-79.68863677980001,44.3893890381],"type":"Point"}
}