{
  "type": "Feature",
  "properties": {
    "addr:full":"5710 Ch DE Saint-Jean Saint-Felix-DE-Valois QC J0K 2M0",
    "addr:postcode":"5710;j0k 2m0",
    "addr:street":"Ch De Saint-Jean Saint-Felix-De-Valois",
    "iso:country":"CA",
    "sg:address":"5710 Ch DE Saint-Jean",
    "sg:city":"Saint-Felix-DE-Valois",
    "sg:classifiers":[
        {
            "category":"Autos & Motor Vehicles",
            "subcategory":"Auto Supplies",
            "type":"Retail Goods"
        }
    ],
    "sg:phone":"+1 450 889 2898",
    "sg:postcode":"J0K 2M0",
    "sg:province":"QC",
    "sg:tags":[
        "tire"
    ],
    "wof:name":"Service DE Pneus Yl Inc",
    "wof:placetype":"venue"
},
  "geometry": {"coordinates":[-73.454071,46.168213],"type":"Point"}
}