{
  "type": "Feature",
  "properties": {
    "addr:full":"1867 Yonge St Toronto ON M4S 1Y5",
    "addr:housenumber":"1867",
    "addr:postcode":"m4s 1y5",
    "addr:street":"Yonge St",
    "iso:country":"CA",
    "sg:address":"1867 Yonge St",
    "sg:city":"Toronto",
    "sg:classifiers":[
        {
            "category":"Insurance",
            "subcategory":"Insurance Agent",
            "type":"Services"
        }
    ],
    "sg:phone":"+1 416 486 1617",
    "sg:postcode":"M4S 1Y5",
    "sg:province":"ON",
    "sg:tags":[
        "consultant"
    ],
    "wof:name":"Firstbrook Insurance Group",
    "wof:placetype":"venue"
},
  "geometry": {"coordinates":[-79.396202,43.697102],"type":"Point"}
}