{
  "type": "Feature",
  "properties": {
    "addr:full":"20859 Hwy 2 Shubenacadie NS B0N 2H0",
    "addr:housenumber":"20859",
    "addr:postcode":"b0n 2h0",
    "addr:street":"Hwy 2",
    "iso:country":"CA",
    "sg:address":"20859 Hwy 2",
    "sg:city":"Shubenacadie",
    "sg:phone":"+1 902 883 9930",
    "sg:postcode":"B0N 2H0",
    "sg:province":"NS",
    "sg:tags":[
        "oil"
    ],
    "wof:name":"Ultramar",
    "wof:placetype":"venue"
},
  "geometry": {"coordinates":[-63.4000434875,45.0809326172],"type":"Point"}
}