{
  "type": "Feature",
  "properties": {
    "addr:full":"Yarmouth NS B5A 2P5",
    "addr:postcode":"b5a 2p5",
    "iso:country":"CA",
    "sg:city":"Yarmouth",
    "sg:classifiers":[
        {
            "category":"Health Services",
            "subcategory":"Doctor",
            "type":"Services"
        }
    ],
    "sg:phone":"+1 902 742 4044",
    "sg:postcode":"B5A 2P5",
    "sg:province":"NS",
    "sg:tags":[
        "physician",
        "surgeon"
    ],
    "wof:name":"Madhvani, Ash K MD",
    "wof:placetype":"venue"
},
  "geometry": {"coordinates":[-66.121498,43.851707],"type":"Point"}
}