{
  "type": "Feature",
  "properties": {
    "iso:country":"CA",
    "sg:address":"735 Gillard",
    "sg:city":"Wallaceburg",
    "sg:classifiers":[
        {
            "category":"Freight",
            "type":"Transportation"
        }
    ],
    "sg:phone":"+1 519 627 5848",
    "sg:postcode":"N8A 5G7",
    "sg:province":"ON",
    "sg:tags":[
        "trucking"
    ],
    "wof:name":"Travelers Transportation Svc",
    "wof:placetype":"venue"
},
  "geometry": {"coordinates":[-82.389755,42.583168],"type":"Point"}
}