{
  "type": "Feature",
  "properties": {
    "iso:country":"CA",
    "sg:address":"254 Lakeshore Rd E",
    "sg:city":"Mississauga",
    "sg:classifiers":[
        {
            "category":"Retail",
            "subcategory":"Repair Shop",
            "type":"Services"
        }
    ],
    "sg:phone":"+1 905 891 6960",
    "sg:postcode":"L5G 1G9",
    "sg:province":"ON",
    "sg:tags":[
        "equipment",
        "photographic"
    ],
    "wof:name":"Camera Repair Canada",
    "wof:placetype":"venue"
},
  "geometry": {"coordinates":[-79.5771179199,43.5597991943],"type":"Point"}
}