{
  "type": "Feature",
  "properties": {
    "addr:full":"3517 Howard Ave Windsor ON N9E 3N6",
    "addr:housenumber":"3517",
    "addr:postcode":"n9e 3n6",
    "addr:street":"Howard Ave",
    "iso:country":"CA",
    "sg:address":"3517 Howard Ave",
    "sg:city":"Windsor",
    "sg:classifiers":[
        {
            "category":"Building & Trades",
            "subcategory":"Construction",
            "type":"Services"
        }
    ],
    "sg:phone":"+1 519 972 7164",
    "sg:postcode":"N9E 3N6",
    "sg:province":"ON",
    "sg:tags":[
        "contractor"
    ],
    "wof:name":"Scy Infinity Homes Ltd",
    "wof:placetype":"venue"
},
  "geometry": {"coordinates":[-83.000359,42.266113],"type":"Point"}
}