{
  "type": "Feature",
  "properties": {
    "iso:country":"CA",
    "sg:address":"1018 Fall River Rd",
    "sg:city":"Fall River",
    "sg:classifiers":[
        {
            "category":"Social Services",
            "subcategory":"Child Care",
            "type":"Services"
        }
    ],
    "sg:phone":"+1 902 861 2999",
    "sg:postcode":"B2T 1E9",
    "sg:province":"NS",
    "wof:name":"Peter Rabbit Preschool",
    "wof:placetype":"venue"
},
  "geometry": {"coordinates":[-63.6293182373,44.8073768616],"type":"Point"}
}