{
  "type": "Feature",
  "properties": {
    "addr:full":"507 Ouellette Ave Windsor ON N9A 4J3",
    "addr:housenumber":"507",
    "addr:postcode":"n9a 4j3",
    "addr:street":"Ouellette Ave",
    "iso:country":"CA",
    "sg:address":"507 Ouellette Ave",
    "sg:city":"Windsor",
    "sg:classifiers":[
        {
            "category":"Restaurant",
            "type":"Food & Drink"
        }
    ],
    "sg:phone":"+1 519 252 8683",
    "sg:postcode":"N9A 4J3",
    "sg:province":"ON",
    "wof:name":"Bistro 507",
    "wof:placetype":"venue"
},
  "geometry": {"coordinates":[-83.0373382568,42.3146972656],"type":"Point"}
}