{
  "type": "Feature",
  "properties": {
    "addr:full":"36 Rue Du Marche Salaberry-DE-Valleyfield QC J6T 1P4",
    "addr:housenumber":"36",
    "addr:postcode":"j6t 1p4",
    "addr:street":"Rue Du Marche",
    "iso:country":"CA",
    "sg:address":"36 Rue Du Marche",
    "sg:city":"Salaberry-DE-Valleyfield",
    "sg:classifiers":[
        {
            "category":"Food & Beverages",
            "subcategory":"Groceries & Convenience Stores",
            "type":"Retail Goods"
        }
    ],
    "sg:phone":"+1 450 373 9981",
    "sg:postcode":"J6T 1P4",
    "sg:province":"QC",
    "sg:tags":[
        "grocer"
    ],
    "wof:name":"Marche Daoust Inc",
    "wof:placetype":"venue"
},
  "geometry": {"coordinates":[-74.133369,45.254745],"type":"Point"}
}