{
  "type": "Feature",
  "properties": {
    "iso:country":"CA",
    "sg:city":"Scarborough",
    "sg:classifiers":[
        {
            "category":"Retail",
            "subcategory":"Auto Repair",
            "type":"Services"
        }
    ],
    "sg:phone":"+1 416 293 2245",
    "sg:postcode":"M1V 4W1",
    "sg:province":"ON",
    "sg:tags":[
        "repairing",
        "automobile"
    ],
    "wof:name":"Chuen Wai Auto",
    "wof:placetype":"venue"
},
  "geometry": {"coordinates":[-79.2913360596,43.8062744141],"type":"Point"}
}