{
  "type": "Feature",
  "properties": {
    "addr:full":"Victoria BC V8T 4S9",
    "addr:postcode":"v8t 4s9",
    "iso:country":"CA",
    "sg:city":"Victoria",
    "sg:classifiers":[
        {
            "category":"Retail",
            "subcategory":"Repair Shop",
            "type":"Services"
        }
    ],
    "sg:phone":"+1 250 474 4861",
    "sg:postcode":"V8T 4S9",
    "sg:province":"BC",
    "sg:tags":[
        "refinishing",
        "furniture"
    ],
    "wof:name":"Barley Twist Refinishing CO",
    "wof:placetype":"venue"
},
  "geometry": {"coordinates":[-123.373268127,48.4363136292],"type":"Point"}
}