{
  "type": "Feature",
  "properties": {
    "iso:country":"CA",
    "sg:address":"Mooswa Dr",
    "sg:city":"Wasagaming",
    "sg:classifiers":[
        {
            "category":"Travel",
            "subcategory":"Hotels & Motels",
            "type":"Entertainment"
        }
    ],
    "sg:phone":"+1 204 848 2533",
    "sg:postcode":"R0J 2H0",
    "sg:province":"MB",
    "sg:tags":[
        "resort"
    ],
    "wof:name":"Mooswa Resorts & Confernce Ctr",
    "wof:placetype":"venue"
},
  "geometry": {"coordinates":[-99.97207641599999,50.6510734558],"type":"Point"}
}