{
  "type": "Feature",
  "properties": {
    "addr:full":"Sillery QC G1T 1P1",
    "addr:postcode":"g1t 1p1",
    "iso:country":"CA",
    "sg:city":"Sillery",
    "sg:classifiers":[
        {
            "category":"Personal",
            "type":"Services"
        }
    ],
    "sg:phone":"+1 418 683 5154",
    "sg:postcode":"G1T 1P1",
    "sg:province":"QC",
    "sg:tags":[
        "electrolysis"
    ],
    "wof:name":"Salon Esthetique Isa Belle",
    "wof:placetype":"venue"
},
  "geometry": {"coordinates":[-71.249977,46.779167],"type":"Point"}
}