{
  "type": "Feature",
  "properties": {
    "iso:country":"CA",
    "sg:address":"20 Jacob Keffer Pky",
    "sg:city":"Concord",
    "sg:classifiers":[
        {
            "category":"Shopping",
            "subcategory":"Discount & Variety Stores",
            "type":"Retail Goods"
        }
    ],
    "sg:phone":"+1 905 303 7370",
    "sg:postcode":"L4K 5E3",
    "sg:province":"ON",
    "wof:name":"Vaughan Convenience",
    "wof:placetype":"venue"
},
  "geometry": {"coordinates":[-79.505951,43.836113],"type":"Point"}
}