{
  "type": "Feature",
  "properties": {
    "iso:country":"CA",
    "sg:address":"2020 40th Ave",
    "sg:city":"Red Deer",
    "sg:classifiers":[
        {
            "category":"Organizations",
            "subcategory":"Religious Organization",
            "type":"Services"
        }
    ],
    "sg:phone":"+1 403 347 7311",
    "sg:postcode":"T4N 5E3",
    "sg:province":"AB",
    "sg:tags":[
        "church"
    ],
    "wof:name":"Living Stones Church",
    "wof:placetype":"venue"
},
  "geometry": {"coordinates":[-113.79044342,52.2334594727],"type":"Point"}
}