{
  "type": "Feature",
  "properties": {
    "iso:country":"CA",
    "sg:city":"Montreal",
    "sg:classifiers":[
        {
            "category":"Manufacturing",
            "subcategory":"Apparel",
            "type":"Manufacturing & Wholesale Goods"
        }
    ],
    "sg:phone":"+1 514 342 5893",
    "sg:postcode":"H3S 1C3",
    "sg:province":"QC",
    "sg:tags":[
        "coat",
        "suit"
    ],
    "wof:name":"Ecogold",
    "wof:placetype":"venue"
},
  "geometry": {"coordinates":[-73.64237213129999,45.5006523132],"type":"Point"}
}