{
  "type": "Feature",
  "properties": {
    "iso:country":"CA",
    "sg:address":"495 Mcnicoll Ave",
    "sg:city":"North York",
    "sg:classifiers":[
        {
            "category":"Education",
            "subcategory":"School",
            "type":"Public Place"
        }
    ],
    "sg:phone":"+1 416 491 2522",
    "sg:postcode":"M2H 2C9",
    "sg:province":"ON",
    "sg:tags":[
        "instruction",
        "dancing"
    ],
    "wof:name":"Dennis Moore Theatre School",
    "wof:placetype":"venue"
},
  "geometry": {"coordinates":[-79.340324,43.803581],"type":"Point"}
}