{
  "type": "Feature",
  "properties": {
    "iso:country":"CA",
    "sg:city":"Vancouver",
    "sg:classifiers":[
        {
            "category":"Professional",
            "subcategory":"Lawyer & Legal Services",
            "type":"Services"
        }
    ],
    "sg:phone":"+1 604 632 9940",
    "sg:postcode":"V6B 5A1",
    "sg:province":"BC",
    "sg:tags":[
        "attorney"
    ],
    "wof:name":"Hain, Neil J",
    "wof:placetype":"venue"
},
  "geometry": {"coordinates":[-123.11512,49.280712],"type":"Point"}
}