{
  "type": "Feature",
  "properties": {
    "addr:full":"2350 Rue Dickson Montreal QC H1N 3T1",
    "addr:housenumber":"2350",
    "addr:postcode":"h1n 3t1",
    "addr:street":"Rue Dickson",
    "iso:country":"CA",
    "sg:address":"2350 Rue Dickson",
    "sg:city":"Montreal",
    "sg:classifiers":[
        {
            "category":"Education",
            "subcategory":"School",
            "type":"Public Place"
        }
    ],
    "sg:phone":"+1 514 899 5000",
    "sg:postcode":"H1N 3T1",
    "sg:province":"QC",
    "sg:tags":[
        "recreation",
        "amusement"
    ],
    "wof:name":"Centre D'Escalade Horizon Roc",
    "wof:placetype":"venue"
},
  "geometry": {"coordinates":[-73.535698,45.568676],"type":"Point"}
}