{
  "type": "Feature",
  "properties": {
    "addr:full":"Richmond ON K0A 2Z0",
    "addr:postcode":"k0a 2z0",
    "iso:country":"CA",
    "sg:city":"Richmond",
    "sg:classifiers":[
        {
            "category":"Restaurant",
            "type":"Food & Drink"
        }
    ],
    "sg:phone":"+1 613 838 4334",
    "sg:postcode":"K0A 2Z0",
    "sg:province":"ON",
    "sg:tags":[
        "pizza"
    ],
    "wof:name":"Milano Pizzeria",
    "wof:placetype":"venue"
},
  "geometry": {"coordinates":[-75.83963799999999,45.193089],"type":"Point"}
}