{
  "type": "Feature",
  "properties": {
    "addr:full":"81 Arkell St Hamilton ON L8S 1N6",
    "addr:housenumber":"81",
    "addr:postcode":"l8s 1n6",
    "addr:street":"Arkell St",
    "iso:country":"CA",
    "sg:address":"81 Arkell St",
    "sg:city":"Hamilton",
    "sg:classifiers":[
        {
            "category":"Social Services",
            "type":"Services"
        }
    ],
    "sg:phone":"+1 905 527 8536",
    "sg:postcode":"L8S 1N6",
    "sg:province":"ON",
    "sg:tags":[
        "organization",
        "welfare"
    ],
    "wof:name":"Beth Tikvah",
    "wof:placetype":"venue"
},
  "geometry": {"coordinates":[-79.9061660767,43.2591781616],"type":"Point"}
}