{
  "type": "Feature",
  "properties": {
    "addr:full":"82 Lake St St Catharines ON L2R 5X4",
    "addr:housenumber":"82",
    "addr:postcode":"l2r 5x4",
    "addr:street":"Lake St",
    "iso:country":"CA",
    "sg:address":"82 Lake St",
    "sg:city":"St Catharines",
    "sg:classifiers":[
        {
            "category":"Banks & Credit Unions",
            "subcategory":"Investment Brokerage",
            "type":"Services"
        }
    ],
    "sg:phone":"+1 905 688 4965",
    "sg:postcode":"L2R 5X4",
    "sg:province":"ON",
    "wof:name":"Credential Securities",
    "wof:placetype":"venue"
},
  "geometry": {"coordinates":[-79.250359,43.16272],"type":"Point"}
}