{
  "type": "Feature",
  "properties": {
    "addr:full":"Ottawa ON K1N 9J7",
    "addr:postcode":"k1n 9j7",
    "iso:country":"CA",
    "sg:city":"Ottawa",
    "sg:classifiers":[
        {
            "category":"Shopping",
            "subcategory":"Clothing, Apparel, & Fashions",
            "type":"Retail Goods"
        }
    ],
    "sg:phone":"+1 613 569 1488",
    "sg:postcode":"K1N 9J7",
    "sg:province":"ON",
    "wof:name":"Cleo",
    "wof:placetype":"venue"
},
  "geometry": {"coordinates":[-75.6917648315,45.4444313049],"type":"Point"}
}