{
  "type": "Feature",
  "properties": {
    "addr:full":"136 Richmond St Charlottetown PE C1A 1H9",
    "addr:housenumber":"136",
    "addr:postcode":"c1a 1h9",
    "addr:street":"Richmond St",
    "iso:country":"CA",
    "sg:address":"136 Richmond St",
    "sg:city":"Charlottetown",
    "sg:classifiers":[
        {
            "category":"Restaurant",
            "type":"Food & Drink"
        }
    ],
    "sg:phone":"+1 902 628 6569",
    "sg:postcode":"C1A 1H9",
    "sg:province":"PE",
    "wof:name":"Fishbones Oyster Bar & Seafood",
    "wof:placetype":"venue"
},
  "geometry": {"coordinates":[-63.126347,46.233948],"type":"Point"}
}