{
  "type": "Feature",
  "properties": {
    "addr:full":"325 132 Rte Chandler QC G0C 1K0",
    "addr:housenumber":"132",
    "addr:postcode":"g0c 1k0",
    "addr:street":"Rte Chandler",
    "iso:country":"CA",
    "sg:address":"325 132 Rte",
    "sg:city":"Chandler",
    "sg:classifiers":[
        {
            "category":"Travel",
            "subcategory":"Hotels & Motels",
            "type":"Entertainment"
        }
    ],
    "sg:phone":"+1 418 689 2281",
    "sg:postcode":"G0C 1K0",
    "sg:province":"QC",
    "wof:name":"Motel Fraser Inc",
    "wof:placetype":"venue"
},
  "geometry": {"coordinates":[-64.68017578120001,48.3490104675],"type":"Point"}
}