{
  "type": "Feature",
  "properties": {
    "addr:full":"3302 Ferguson Rd Cobourg ON K9A 4J9",
    "addr:housenumber":"3302",
    "addr:postcode":"k9a 4j9",
    "addr:street":"Ferguson Rd",
    "iso:country":"CA",
    "sg:address":"3302 Ferguson Rd",
    "sg:city":"Cobourg",
    "sg:classifiers":[
        {
            "category":"Recreation",
            "type":"Entertainment"
        }
    ],
    "sg:phone":"+1 905 342 3265",
    "sg:postcode":"K9A 4J9",
    "sg:province":"ON",
    "sg:tags":[
        "stable"
    ],
    "wof:name":"Adanac Horse Farm",
    "wof:placetype":"venue"
},
  "geometry": {"coordinates":[-78.167778,43.959606],"type":"Point"}
}