{
  "type": "Feature",
  "properties": {
    "addr:full":"5651 Rue Hadley Montreal QC H4E 3N1",
    "addr:housenumber":"5651",
    "addr:postcode":"h4e 3n1",
    "addr:street":"Rue Hadley",
    "iso:country":"CA",
    "sg:address":"5651 Rue Hadley",
    "sg:city":"Montreal",
    "sg:classifiers":[
        {
            "category":"Food & Beverages",
            "subcategory":"Groceries & Convenience Stores",
            "type":"Retail Goods"
        }
    ],
    "sg:phone":"+1 514 766 2377",
    "sg:postcode":"H4E 3N1",
    "sg:province":"QC",
    "wof:name":"Epicerie Robert Villeneuve Enr",
    "wof:placetype":"venue"
},
  "geometry": {"coordinates":[-73.592545,45.462025],"type":"Point"}
}