{
  "type": "Feature",
  "properties": {
    "addr:full":"4 Centennial Dr Windsor NS B0N 2T0",
    "addr:housenumber":"4",
    "addr:postcode":"b0n 2t0",
    "addr:street":"Centennial Dr",
    "iso:country":"CA",
    "sg:address":"4 Centennial Dr",
    "sg:city":"Windsor",
    "sg:classifiers":[
        {
            "category":"Wholesale",
            "subcategory":"Electrical",
            "type":"Manufacturing & Wholesale Goods"
        }
    ],
    "sg:phone":"+1 902 798 4003",
    "sg:postcode":"B0N 2T0",
    "sg:province":"NS",
    "sg:tags":[
        "electric",
        "motor"
    ],
    "wof:name":"Anthony's Electric Motor Rpr",
    "wof:placetype":"venue"
},
  "geometry": {"coordinates":[-64.119141,44.9902],"type":"Point"}
}