{
  "type": "Feature",
  "properties": {
    "iso:country":"CA",
    "sg:address":"1580 Bloor St W",
    "sg:city":"Toronto",
    "sg:classifiers":[
        {
            "category":"Shopping",
            "subcategory":"Discount & Variety Stores",
            "type":"Retail Goods"
        }
    ],
    "sg:phone":"+1 416 535 9996",
    "sg:postcode":"M6P 1A4",
    "sg:province":"ON",
    "wof:name":"Scotty's Variety",
    "wof:placetype":"venue"
},
  "geometry": {"coordinates":[-79.4542312622,43.6560592651],"type":"Point"}
}