{
  "type": "Feature",
  "properties": {
    "addr:full":"1709 Bloor St W # 200 Toronto ON M6P 4E5",
    "addr:housenumber":"1709",
    "addr:postcode":"m6p 4e5",
    "addr:street":"Bloor St W # 200",
    "iso:country":"CA",
    "sg:address":"1709 Bloor St W # 200",
    "sg:city":"Toronto",
    "sg:classifiers":[
        {
            "category":"Professional",
            "subcategory":"Computer Services",
            "type":"Services"
        }
    ],
    "sg:phone":"+1 416 762 0032",
    "sg:postcode":"M6P 4E5",
    "sg:province":"ON",
    "sg:tags":[
        "consultant",
        "software"
    ],
    "wof:name":"Intelliware Development Inc",
    "wof:placetype":"venue"
},
  "geometry": {"coordinates":[-79.4590301514,43.6547889709],"type":"Point"}
}