{
  "type": "Feature",
  "properties": {
    "iso:country":"CA",
    "sg:address":"875 Ch Murray",
    "sg:city":"Saint-Antoine Sud",
    "sg:classifiers":[
        {
            "category":"Food & Beverages",
            "subcategory":"Fruits & Vegetables",
            "type":"Retail Goods"
        }
    ],
    "sg:phone":"+1 506 525 2376",
    "sg:postcode":"E4V 2Y3",
    "sg:province":"NB",
    "sg:tags":[
        "produce"
    ],
    "wof:name":"Uris Williams & Sons Ltd",
    "wof:placetype":"venue"
},
  "geometry": {"coordinates":[-64.7523117065,46.3625106812],"type":"Point"}
}