{
  "type": "Feature",
  "properties": {
    "addr:full":"268 College St Toronto ON M5T 1S1",
    "addr:housenumber":"268",
    "addr:postcode":"m5t 1s1",
    "addr:street":"College St",
    "iso:country":"CA",
    "sg:address":"268 College St",
    "sg:city":"Toronto",
    "sg:classifiers":[
        {
            "category":"Banks & Credit Unions",
            "subcategory":"Bank",
            "type":"Services"
        }
    ],
    "sg:phone":"+1 416 861 3730",
    "sg:postcode":"M5T 1S1",
    "sg:province":"ON",
    "wof:name":"Cibc",
    "wof:placetype":"venue"
},
  "geometry": {"coordinates":[-79.400612,43.657986],"type":"Point"}
}