{
  "type": "Feature",
  "properties": {
    "addr:full":"5426 329 Rte S Sainte-Agathe-Nord QC J8C 2Z7",
    "addr:housenumber":"5426",
    "addr:postcode":"j8c 2z7",
    "addr:street":"329 Rte S Sainte-Agathe-Nord",
    "iso:country":"CA",
    "sg:address":"5426 329 Rte S",
    "sg:city":"Sainte-Agathe-Nord",
    "sg:classifiers":[
        {
            "category":"Autos & Motor Vehicles",
            "subcategory":"Fuel & Gas Station",
            "type":"Retail Goods"
        }
    ],
    "sg:phone":"+1 819 326 1646",
    "sg:postcode":"J8C 2Z7",
    "sg:province":"QC",
    "sg:tags":[
        "oil"
    ],
    "wof:name":"Groupe Petrolier Olco Inc",
    "wof:placetype":"venue"
},
  "geometry": {"coordinates":[-74.2838516235,46.0744743347],"type":"Point"}
}