{
  "type": "Feature",
  "properties": {
    "addr:full":"1660 Rosslyn Rd Thunder Bay ON P7K 1J3",
    "addr:housenumber":"1660",
    "addr:postcode":"p7k 1j3",
    "addr:street":"Rosslyn Rd",
    "iso:country":"CA",
    "sg:address":"1660 Rosslyn Rd",
    "sg:city":"Thunder Bay",
    "sg:classifiers":[
        {
            "category":"Professional",
            "subcategory":"Management & Consulting",
            "type":"Services"
        }
    ],
    "sg:phone":"+1 807 577 7929",
    "sg:postcode":"P7K 1J3",
    "sg:province":"ON",
    "sg:tags":[
        "consultant"
    ],
    "wof:name":"Waste Control Systems",
    "wof:placetype":"venue"
},
  "geometry": {"coordinates":[-89.336952,48.3624],"type":"Point"}
}