{
  "type": "Feature",
  "properties": {
    "iso:country":"CA",
    "sg:address":"2945 Rue Diab",
    "sg:city":"Saint-Laurent",
    "sg:classifiers":[
        {
            "category":"Autos & Motor Vehicles",
            "subcategory":"Auto Supplies",
            "type":"Retail Goods"
        }
    ],
    "sg:phone":"+1 514 339 5722",
    "sg:postcode":"H4S 1M1",
    "sg:province":"QC",
    "sg:tags":[
        "automobile",
        "parts",
        "racing",
        "car",
        "equipment"
    ],
    "wof:name":"Rmr Autosport Inc",
    "wof:placetype":"venue"
},
  "geometry": {"coordinates":[-73.7497787476,45.4962310791],"type":"Point"}
}