{
  "type": "Feature",
  "properties": {
    "addr:full":"2440 Rue DE Rouen Montreal QC H2K 1M2",
    "addr:housenumber":"2440",
    "addr:postcode":"h2k 1m2",
    "addr:street":"Rue De Rouen",
    "iso:country":"CA",
    "sg:address":"2440 Rue DE Rouen",
    "sg:city":"Montreal",
    "sg:classifiers":[
        {
            "category":"Food & Beverages",
            "subcategory":"Groceries & Convenience Stores",
            "type":"Retail Goods"
        }
    ],
    "sg:phone":"+1 514 522 4280",
    "sg:postcode":"H2K 1M2",
    "sg:province":"QC",
    "sg:tags":[
        "grocer"
    ],
    "wof:name":"Depanneur Frais",
    "wof:placetype":"venue"
},
  "geometry": {"coordinates":[-73.55718231199999,45.533416748],"type":"Point"}
}