{
  "type": "Feature",
  "properties": {
    "addr:full":"11051 Rue Mirabeau Anjou QC H1J 2S2",
    "addr:housenumber":"11051",
    "addr:postcode":"h1j 2s2",
    "addr:street":"Rue Mirabeau",
    "iso:country":"CA",
    "sg:address":"11051 Rue Mirabeau",
    "sg:city":"Anjou",
    "sg:classifiers":[
        {
            "category":"Wholesale",
            "subcategory":"Machinery & Supplies",
            "type":"Manufacturing & Wholesale Goods"
        }
    ],
    "sg:phone":"+1 514 353 2005",
    "sg:postcode":"H1J 2S2",
    "sg:province":"QC",
    "sg:tags":[
        "equipment",
        "butcher"
    ],
    "wof:name":"Qualite Naturelle Champlain",
    "wof:placetype":"venue"
},
  "geometry": {"coordinates":[-73.58554100000001,45.617477],"type":"Point"}
}