{
  "type": "Feature",
  "properties": {
    "iso:country":"CA",
    "sg:address":"1910 Yonge St",
    "sg:city":"Toronto",
    "sg:classifiers":[
        {
            "category":"Food & Beverages",
            "subcategory":"Bakery",
            "type":"Retail Goods"
        }
    ],
    "sg:phone":"+1 416 481 0209",
    "sg:postcode":"M4S 3B2",
    "sg:province":"ON",
    "sg:tags":[
        "doughnut"
    ],
    "wof:name":"Tim Hortons",
    "wof:placetype":"venue"
},
  "geometry": {"coordinates":[-79.39679,43.698421],"type":"Point"}
}