{
  "type": "Feature",
  "properties": {
    "iso:country":"CA",
    "sg:address":"891 Gustavus St",
    "sg:city":"Port Elgin",
    "sg:classifiers":[
        {
            "category":"Retail",
            "subcategory":"Auto Repair",
            "type":"Services"
        }
    ],
    "sg:phone":"+1 519 832 2087",
    "sg:postcode":"N0H 2C4",
    "sg:province":"ON",
    "sg:tags":[
        "body",
        "automobile",
        "painting"
    ],
    "wof:name":"Maurer's Collision Port Elgin",
    "wof:placetype":"venue"
},
  "geometry": {"coordinates":[-81.37916564939999,44.4319763184],"type":"Point"}
}