{
  "type": "Feature",
  "properties": {
    "addr:full":"914 Murphy Rd Sarnia ON N7S 5C4",
    "addr:housenumber":"914",
    "addr:postcode":"n7s 5c4",
    "addr:street":"Murphy Rd",
    "iso:country":"CA",
    "sg:address":"914 Murphy Rd",
    "sg:city":"Sarnia",
    "sg:classifiers":[
        {
            "category":"Health Services",
            "subcategory":"Doctor",
            "type":"Services"
        }
    ],
    "sg:phone":"+1 519 542 3459",
    "sg:postcode":"N7S 5C4",
    "sg:province":"ON",
    "sg:tags":[
        "dentist"
    ],
    "wof:name":"Mac Kinlay, F S DDS",
    "wof:placetype":"venue"
},
  "geometry": {"coordinates":[-82.366035,42.987881],"type":"Point"}
}