{
  "type": "Feature",
  "properties": {
    "addr:full":"225 Terminal Ave Vancouver BC V6A 2L7",
    "addr:housenumber":"225",
    "addr:postcode":"v6a 2l7",
    "addr:street":"Terminal Ave",
    "iso:country":"CA",
    "sg:address":"225 Terminal Ave",
    "sg:city":"Vancouver",
    "sg:classifiers":[
        {
            "category":"Home & Garden",
            "subcategory":"Building Materials",
            "type":"Retail Goods"
        }
    ],
    "sg:phone":"+1 604 689 4414",
    "sg:postcode":"V6A 2L7",
    "sg:province":"BC",
    "sg:tags":[
        "paint"
    ],
    "wof:name":"Cloverdale Paint",
    "wof:placetype":"venue"
},
  "geometry": {"coordinates":[-123.097672,49.27264],"type":"Point"}
}