{
  "type": "Feature",
  "properties": {
    "addr:full":"Vancouver BC V6C 1G8",
    "addr:postcode":"v6c 1g8",
    "iso:country":"CA",
    "sg:city":"Vancouver",
    "sg:classifiers":[
        {
            "category":"Banks & Credit Unions",
            "subcategory":"Bank",
            "type":"Services"
        }
    ],
    "sg:phone":"+1 604 684 8806",
    "sg:postcode":"V6C 1G8",
    "sg:province":"BC",
    "sg:tags":[
        "machine",
        "teller",
        "automated"
    ],
    "wof:name":"E Station Network Svc",
    "wof:placetype":"venue"
},
  "geometry": {"coordinates":[-123.11483800000001,49.284649],"type":"Point"}
}