{
  "type": "Feature",
  "properties": {
    "iso:country":"CA",
    "sg:address":"190 Queen St E",
    "sg:city":"Brampton",
    "sg:classifiers":[
        {
            "category":"Restaurant",
            "type":"Food & Drink"
        }
    ],
    "sg:phone":"+1 905 457 7422",
    "sg:postcode":"L6V 1B3",
    "sg:province":"ON",
    "wof:name":"Kfc",
    "wof:placetype":"venue"
},
  "geometry": {"coordinates":[-79.75225067140001,43.6933441162],"type":"Point"}
}