{
  "type": "Feature",
  "properties": {
    "addr:full":"6 Clinton St S Teeswater ON N0G 2S0",
    "addr:housenumber":"6",
    "addr:postcode":"n0g 2s0",
    "addr:street":"Clinton St S Teeswater",
    "iso:country":"CA",
    "sg:address":"6 Clinton St S",
    "sg:city":"Teeswater",
    "sg:classifiers":[
        {
            "category":"Home & Garden",
            "subcategory":"Hardware",
            "type":"Retail Goods"
        }
    ],
    "sg:phone":"+1 519 392 6044",
    "sg:postcode":"N0G 2S0",
    "sg:province":"ON",
    "wof:name":"Sillick Pro Hardware",
    "wof:placetype":"venue"
},
  "geometry": {"coordinates":[-81.287025,43.998661],"type":"Point"}
}