{
  "type": "Feature",
  "properties": {
    "addr:full":"10810 54 Ave NW Edmonton AB T6H 0T9",
    "addr:housenumber":"10810",
    "addr:postcode":"t6h 0t9",
    "addr:street":"54 Ave Nw",
    "iso:country":"CA",
    "sg:address":"10810 54 Ave NW",
    "sg:city":"Edmonton",
    "sg:classifiers":[
        {
            "category":"Recreation",
            "type":"Entertainment"
        }
    ],
    "sg:phone":"+1 780 469 2149",
    "sg:postcode":"T6H 0T9",
    "sg:province":"AB",
    "sg:tags":[
        "tennis",
        "court",
        "hall",
        "auditorium"
    ],
    "wof:name":"Capilano Community League",
    "wof:placetype":"venue"
},
  "geometry": {"coordinates":[-113.509979,53.491657],"type":"Point"}
}