{
  "type": "Feature",
  "properties": {
    "addr:full":"1383 Dominion Rd Fort Erie ON L2A 1J6",
    "addr:housenumber":"1383",
    "addr:postcode":"l2a 1j6",
    "addr:street":"Dominion Rd",
    "iso:country":"CA",
    "sg:address":"1383 Dominion Rd",
    "sg:city":"Fort Erie",
    "sg:classifiers":[
        {
            "category":"Building & Trades",
            "subcategory":"Electrical",
            "type":"Services"
        }
    ],
    "sg:phone":"+1 905 871 2591",
    "sg:postcode":"L2A 1J6",
    "sg:province":"ON",
    "sg:tags":[
        "electric",
        "contractor"
    ],
    "wof:name":"Dan's Electrical Svc Ltd",
    "wof:placetype":"venue"
},
  "geometry": {"coordinates":[-78.9666900635,42.8860015869],"type":"Point"}
}