{
  "type": "Feature",
  "properties": {
    "addr:full":"Langley BC V1M 2Y2",
    "addr:postcode":"v1m 2y2",
    "iso:country":"CA",
    "sg:city":"Langley",
    "sg:classifiers":[
        {
            "category":"Shopping",
            "subcategory":"Gifts & Souvenirs",
            "type":"Retail Goods"
        }
    ],
    "sg:phone":"+1 604 882 0632",
    "sg:postcode":"V1M 2Y2",
    "sg:province":"BC",
    "sg:tags":[
        "shop"
    ],
    "wof:name":"Beach Basket Giftware",
    "wof:placetype":"venue"
},
  "geometry": {"coordinates":[-122.63745900000001,49.163078],"type":"Point"}
}