{
  "type": "Feature",
  "properties": {
    "addr:full":"Pth 16 W Gladstone MB R0J 0T0",
    "addr:postcode":"r0j 0t0",
    "addr:street":"Pth 16 W",
    "iso:country":"CA",
    "sg:address":"Pth 16 W",
    "sg:city":"Gladstone",
    "sg:classifiers":[
        {
            "category":"Autos & Motor Vehicles",
            "subcategory":"Fuel & Gas Station",
            "type":"Retail Goods"
        }
    ],
    "sg:phone":"+1 204 385 2855",
    "sg:postcode":"R0J 0T0",
    "sg:province":"MB",
    "sg:tags":[
        "oil"
    ],
    "wof:name":"B & E Svc",
    "wof:placetype":"venue"
},
  "geometry": {"coordinates":[-98.9507522583,50.2254219055],"type":"Point"}
}