{
  "type": "Feature",
  "properties": {
    "addr:full":"Drummondville QC J2B 7T5",
    "addr:postcode":"j2b 7t5",
    "iso:country":"CA",
    "sg:city":"Drummondville",
    "sg:classifiers":[
        {
            "category":"Recreation",
            "type":"Entertainment"
        }
    ],
    "sg:phone":"+1 819 475 2206",
    "sg:postcode":"J2B 7T5",
    "sg:province":"QC",
    "sg:tags":[
        "tennis",
        "court"
    ],
    "wof:name":"Tennis Interieur Drummond Inc",
    "wof:placetype":"venue"
},
  "geometry": {"coordinates":[-72.485497,45.890419],"type":"Point"}
}