{
  "type": "Feature",
  "properties": {
    "addr:full":"7652 Winston St Burnaby BC V5A 2H4",
    "addr:housenumber":"7652",
    "addr:postcode":"v5a 2h4",
    "addr:street":"Winston St",
    "iso:country":"CA",
    "sg:address":"7652 Winston St",
    "sg:city":"Burnaby",
    "sg:classifiers":[
        {
            "category":"Wholesale",
            "subcategory":"Hardware",
            "type":"Manufacturing & Wholesale Goods"
        }
    ],
    "sg:phone":"+1 604 421 3344",
    "sg:postcode":"V5A 2H4",
    "sg:province":"BC",
    "sg:tags":[
        "nut",
        "bolt"
    ],
    "wof:name":"Cascade Distributors Ltd",
    "wof:placetype":"venue"
},
  "geometry": {"coordinates":[-122.94065856900001,49.2480697632],"type":"Point"}
}