{
  "type": "Feature",
  "properties": {
    "addr:full":"131 River St Sunderland ON L0C 1H0",
    "addr:housenumber":"131",
    "addr:postcode":"l0c 1h0",
    "addr:street":"River St",
    "iso:country":"CA",
    "sg:address":"131 River St",
    "sg:city":"Sunderland",
    "sg:classifiers":[
        {
            "category":"Insurance",
            "subcategory":"Insurance Agent",
            "type":"Services"
        }
    ],
    "sg:phone":"+1 705 357 3916",
    "sg:postcode":"L0C 1H0",
    "sg:province":"ON",
    "wof:name":"Brown & Brethour Insurance",
    "wof:placetype":"venue"
},
  "geometry": {"coordinates":[-79.0688705444,44.2621688843],"type":"Point"}
}