{
  "type": "Feature",
  "properties": {
    "addr:full":"23 Coburg St Saint John NB E2L 3J4",
    "addr:housenumber":"23",
    "addr:postcode":"nb e2l 3j4",
    "addr:street":"Coburg St",
    "iso:country":"CA",
    "sg:address":"23 Coburg St",
    "sg:city":"Saint John",
    "sg:classifiers":[
        {
            "category":"Health Services",
            "subcategory":"Doctor",
            "type":"Services"
        }
    ],
    "sg:phone":"+1 506 634 8061",
    "sg:postcode":"E2L 3J4",
    "sg:province":"NB",
    "sg:tags":[
        "dentist"
    ],
    "wof:name":"Fitzpatrick, Donald A DDS",
    "wof:placetype":"venue"
},
  "geometry": {"coordinates":[-66.059837,45.275803],"type":"Point"}
}