{
  "type": "Feature",
  "properties": {
    "addr:full":"1988 Water St Miramichi NB E1N 1C2",
    "addr:housenumber":"1988",
    "addr:postcode":"e1n 1c2",
    "addr:street":"Water St",
    "iso:country":"CA",
    "sg:address":"1988 Water St",
    "sg:city":"Miramichi",
    "sg:classifiers":[
        {
            "category":"Home & Garden",
            "subcategory":"Building Materials",
            "type":"Retail Goods"
        }
    ],
    "sg:phone":"+1 506 773 5150",
    "sg:postcode":"E1N 1C2",
    "sg:province":"NB",
    "wof:name":"Le Gresley Building Supply Ltd",
    "wof:placetype":"venue"
},
  "geometry": {"coordinates":[-65.46472199999999,47.036343],"type":"Point"}
}