{
  "type": "Feature",
  "properties": {
    "iso:country":"CA",
    "sg:address":"54 Crockford Blvd",
    "sg:city":"Scarborough",
    "sg:classifiers":[
        {
            "category":"Manufacturing",
            "subcategory":"Tools & Machinery",
            "type":"Manufacturing & Wholesale Goods"
        }
    ],
    "sg:phone":"+1 416 751 7307",
    "sg:postcode":"M1R 3C3",
    "sg:province":"ON",
    "sg:tags":[
        "equipment",
        "safety",
        "clothing"
    ],
    "wof:name":"Cleanwear Products",
    "wof:placetype":"venue"
},
  "geometry": {"coordinates":[-79.28839111329999,43.739276886],"type":"Point"}
}