{
  "type": "Feature",
  "properties": {
    "addr:full":"56 Cumber Ave Scarborough ON M1E 1T3",
    "addr:housenumber":"56",
    "addr:postcode":"m1e 1t3",
    "addr:street":"Cumber Ave",
    "iso:country":"CA",
    "sg:address":"56 Cumber Ave",
    "sg:city":"Scarborough",
    "sg:classifiers":[
        {
            "category":"Professional",
            "subcategory":"Computer Services",
            "type":"Services"
        }
    ],
    "sg:phone":"+1 416 208 7847",
    "sg:postcode":"M1E 1T3",
    "sg:province":"ON",
    "sg:tags":[
        "consultant"
    ],
    "wof:name":"Starsoft Inc",
    "wof:placetype":"venue"
},
  "geometry": {"coordinates":[-79.18195299999999,43.754574],"type":"Point"}
}