{
  "type": "Feature",
  "properties": {
    "iso:country":"CA",
    "sg:city":"Old Perlican",
    "sg:classifiers":[
        {
            "category":"Education",
            "subcategory":"Library",
            "type":"Public Place"
        }
    ],
    "sg:phone":"+1 709 587 2639",
    "sg:postcode":"A0A 3G0",
    "sg:province":"NL",
    "wof:name":"Old Perlican Public Library",
    "wof:placetype":"venue"
},
  "geometry": {"coordinates":[-53.0059585571,48.0817947388],"type":"Point"}
}