{
  "type": "Feature",
  "properties": {
    "iso:country":"CA",
    "sg:address":"1331 Kingsway",
    "sg:city":"Vancouver",
    "sg:classifiers":[
        {
            "category":"Wholesale",
            "subcategory":"Machinery & Supplies",
            "type":"Manufacturing & Wholesale Goods"
        }
    ],
    "sg:phone":"+1 604 876 8888",
    "sg:postcode":"V5V 3E3",
    "sg:province":"BC",
    "sg:tags":[
        "salon",
        "beauty"
    ],
    "wof:name":"Secret Nail & Beauty Supply",
    "wof:placetype":"venue"
},
  "geometry": {"coordinates":[-123.077156067,49.2508735657],"type":"Point"}
}