{
  "type": "Feature",
  "properties": {
    "addr:full":"22 Ellen St W Kitchener ON N2H 4K3",
    "addr:housenumber":"22",
    "addr:postcode":"n2h 4k3",
    "addr:street":"Ellen St W",
    "iso:country":"CA",
    "sg:address":"22 Ellen St W",
    "sg:city":"Kitchener",
    "sg:classifiers":[
        {
            "category":"Travel",
            "subcategory":"Hotels & Motels",
            "type":"Entertainment"
        }
    ],
    "sg:phone":"+1 519 743 1553",
    "sg:postcode":"N2H 4K3",
    "sg:province":"ON",
    "sg:tags":[
        "breakfast",
        "accommodation",
        "bed"
    ],
    "wof:name":"Claddagh House",
    "wof:placetype":"venue"
},
  "geometry": {"coordinates":[-80.4856262207,43.455947876],"type":"Point"}
}