{
  "type": "Feature",
  "properties": {
    "addr:full":"5075 Yonge St # 401 North York ON M2N 6C6",
    "addr:housenumber":"5075",
    "addr:postcode":"m2n 6c6",
    "addr:street":"Yonge St # 401",
    "iso:country":"CA",
    "sg:address":"5075 Yonge St # 401",
    "sg:city":"North York",
    "sg:classifiers":[
        {
            "category":"Banks & Credit Unions",
            "subcategory":"Bank",
            "type":"Services"
        }
    ],
    "sg:phone":"+1 416 250 8661",
    "sg:postcode":"M2N 6C6",
    "sg:province":"ON",
    "sg:tags":[
        "cashing",
        "money",
        "check",
        "transfer"
    ],
    "wof:name":"Unicash Franchising Inc",
    "wof:placetype":"venue"
},
  "geometry": {"coordinates":[-79.41229199999999,43.767654],"type":"Point"}
}