{
  "type": "Feature",
  "properties": {
    "addr:full":"309 Jarvis St Whitehorse YT Y1A 2H3",
    "addr:housenumber":"309",
    "addr:postcode":"y1a 2h3",
    "addr:street":"Jarvis St",
    "iso:country":"CA",
    "sg:address":"309 Jarvis St",
    "sg:city":"Whitehorse",
    "sg:classifiers":[
        {
            "category":"Restaurant",
            "type":"Food & Drink"
        }
    ],
    "sg:phone":"+1 867 668 2899",
    "sg:postcode":"Y1A 2H3",
    "sg:province":"YT",
    "wof:name":"China Garden Restaurant",
    "wof:placetype":"venue"
},
  "geometry": {"coordinates":[-135.056274414,60.7214660645],"type":"Point"}
}