{
  "type": "Feature",
  "properties": {
    "iso:country":"CA",
    "sg:address":"36 Boul Rene-Levesque E",
    "sg:city":"Quebec",
    "sg:classifiers":[
        {
            "category":"Personal",
            "type":"Services"
        }
    ],
    "sg:phone":"+1 418 522 4922",
    "sg:postcode":"G1R 2B1",
    "sg:province":"QC",
    "sg:tags":[
        "therapist",
        "massage"
    ],
    "wof:name":"Centre DE Sante Beaute Izba",
    "wof:placetype":"venue"
},
  "geometry": {"coordinates":[-71.225075,46.805374],"type":"Point"}
}