{
  "type": "Feature",
  "properties": {
    "addr:full":"1275 Main St W North Bay ON P1B 2W7",
    "addr:housenumber":"1275",
    "addr:postcode":"p1b 2w7",
    "addr:street":"Main St W",
    "iso:country":"CA",
    "sg:address":"1275 Main St W",
    "sg:city":"North Bay",
    "sg:classifiers":[
        {
            "category":"Real Estate",
            "subcategory":"Architect",
            "type":"Services"
        }
    ],
    "sg:phone":"+1 705 476 8466",
    "sg:postcode":"P1B 2W7",
    "sg:province":"ON",
    "wof:name":"Osburn Associates Architect",
    "wof:placetype":"venue"
},
  "geometry": {"coordinates":[-79.48054500000001,46.321014],"type":"Point"}
}