{
  "type": "Feature",
  "properties": {
    "iso:country":"CA",
    "sg:city":"Kelowna",
    "sg:classifiers":[
        {
            "category":"Professional",
            "subcategory":"Lawyer & Legal Services",
            "type":"Services"
        }
    ],
    "sg:phone":"+1 250 862 3004",
    "sg:postcode":"V1Y 6L8",
    "sg:province":"BC",
    "sg:tags":[
        "attorney"
    ],
    "wof:name":"Johnson, Donald J",
    "wof:placetype":"venue"
},
  "geometry": {"coordinates":[-119.491920471,49.8852157593],"type":"Point"}
}