{
  "type": "Feature",
  "properties": {
    "addr:full":"Toronto ON M5E 1W7",
    "addr:postcode":"m5e 1w7",
    "iso:country":"CA",
    "sg:city":"Toronto",
    "sg:classifiers":[
        {
            "category":"Wholesale",
            "subcategory":"Jewelry",
            "type":"Manufacturing & Wholesale Goods"
        }
    ],
    "sg:phone":"+1 416 214 4299",
    "sg:postcode":"M5E 1W7",
    "sg:province":"ON",
    "sg:tags":[
        "platinum",
        "silver",
        "gold"
    ],
    "wof:name":"Advanced Precious Metals Corp",
    "wof:placetype":"venue"
},
  "geometry": {"coordinates":[-79.37457999999999,43.642052],"type":"Point"}
}