{
  "type": "Feature",
  "properties": {
    "iso:country":"CA",
    "sg:address":"540 Rue Notre-Dame",
    "sg:city":"Saint-Alexis-Des-Monts",
    "sg:classifiers":[
        {
            "category":"Travel",
            "subcategory":"Hotels & Motels",
            "type":"Entertainment"
        }
    ],
    "sg:phone":"+1 819 265 3225",
    "sg:postcode":"J0K 1V0",
    "sg:province":"QC",
    "wof:name":"Motel Resto Du Jardin",
    "wof:placetype":"venue"
},
  "geometry": {"coordinates":[-73.1487503052,46.4511871338],"type":"Point"}
}