{
  "type": "Feature",
  "properties": {
    "addr:full":"1349 Ch Des Patriotes Sorel-Tracy QC J3P 6C1",
    "addr:housenumber":"1349",
    "addr:postcode":"j3p 6c1",
    "addr:street":"Ch Des Patriotes",
    "iso:country":"CA",
    "sg:address":"1349 Ch Des Patriotes",
    "sg:city":"Sorel-Tracy",
    "sg:classifiers":[
        {
            "category":"Retail",
            "subcategory":"Repair Shop",
            "type":"Services"
        }
    ],
    "sg:phone":"+1 450 742 0825",
    "sg:postcode":"J3P 6C1",
    "sg:province":"QC",
    "sg:tags":[
        "refinishing",
        "furniture"
    ],
    "wof:name":"Jocelyn Parenteau Enr",
    "wof:placetype":"venue"
},
  "geometry": {"coordinates":[-73.13586425779999,45.9990692139],"type":"Point"}
}