{
  "type": "Feature",
  "properties": {
    "addr:full":"101 Cherryhill Blvd #115 London ON N6H 4S4",
    "addr:housenumber":"101",
    "addr:postcode":"n6h 4s4",
    "addr:street":"Cherryhill Blvd # 115",
    "iso:country":"CA",
    "sg:address":"101 Cherryhill Blvd #115",
    "sg:city":"London",
    "sg:classifiers":[
        {
            "category":"Organizations",
            "subcategory":"Religious Organization",
            "type":"Services"
        }
    ],
    "sg:phone":"+1 519 432 5723",
    "sg:postcode":"N6H 4S4",
    "sg:province":"ON",
    "wof:name":"Reinhard Bonnke Ministries",
    "wof:placetype":"venue"
},
  "geometry": {"coordinates":[-81.27629852290001,42.9887580872],"type":"Point"}
}