{
  "type": "Feature",
  "properties": {
    "addr:full":"Quebec QC G2E 5E8",
    "addr:postcode":"qc g2e 5e8",
    "iso:country":"CA",
    "sg:city":"Quebec",
    "sg:classifiers":[
        {
            "category":"Professional",
            "subcategory":"Management & Consulting",
            "type":"Services"
        }
    ],
    "sg:phone":"+1 418 872 2223",
    "sg:postcode":"G2E 5E8",
    "sg:province":"QC",
    "sg:tags":[
        "marketing",
        "consultant"
    ],
    "wof:name":"Propage Communications Grphqs",
    "wof:placetype":"venue"
},
  "geometry": {"coordinates":[-71.3277206421,46.8010635376],"type":"Point"}
}