{
  "type": "Feature",
  "properties": {
    "addr:full":"Peterborough ON K9J 3G9",
    "addr:postcode":"k9j 3g9",
    "iso:country":"CA",
    "sg:city":"Peterborough",
    "sg:classifiers":[
        {
            "category":"Professional",
            "subcategory":"Employment Agencies",
            "type":"Services"
        }
    ],
    "sg:phone":"+1 705 749 1919",
    "sg:postcode":"K9J 3G9",
    "sg:province":"ON",
    "sg:tags":[
        "opportunity"
    ],
    "wof:name":"Level A Inc",
    "wof:placetype":"venue"
},
  "geometry": {"coordinates":[-78.3199386597,44.3018341064],"type":"Point"}
}