{
  "type": "Feature",
  "properties": {
    "addr:full":"Green Valley ON K0C 1L0",
    "addr:postcode":"k0c 1l0",
    "iso:country":"CA",
    "sg:city":"Green Valley",
    "sg:classifiers":[
        {
            "category":"Manufacturing",
            "subcategory":"Signs",
            "type":"Manufacturing & Wholesale Goods"
        }
    ],
    "sg:phone":"+1 613 525 5863",
    "sg:postcode":"K0C 1L0",
    "sg:province":"ON",
    "wof:name":"Sonne Signs",
    "wof:placetype":"venue"
},
  "geometry": {"coordinates":[-74.61041299999999,45.222652],"type":"Point"}
}