{
  "type": "Feature",
  "properties": {
    "addr:full":"Farm Abbey SK S0N 0A0",
    "addr:postcode":"s0n 0a0",
    "addr:street":"Abbey",
    "iso:country":"CA",
    "sg:address":"Farm",
    "sg:city":"Abbey",
    "sg:classifiers":[
        {
            "category":"Wholesale",
            "subcategory":"Machinery & Supplies",
            "type":"Manufacturing & Wholesale Goods"
        }
    ],
    "sg:phone":"+1 306 689 2574",
    "sg:postcode":"S0N 0A0",
    "sg:province":"SK",
    "sg:tags":[
        "agricultural",
        "implement"
    ],
    "wof:name":"Heard's Combine Salvage",
    "wof:placetype":"venue"
},
  "geometry": {"coordinates":[-108.756691,50.736141],"type":"Point"}
}