{
  "type": "Feature",
  "properties": {
    "iso:country":"CA",
    "sg:address":"37 Myrtle Ave",
    "sg:city":"Yorkton",
    "sg:classifiers":[
        {
            "category":"Professional",
            "subcategory":"Computer Services",
            "type":"Services"
        }
    ],
    "sg:phone":"+1 306 782 0000",
    "sg:postcode":"S3N 1P6",
    "sg:province":"SK",
    "sg:tags":[
        "internet"
    ],
    "wof:name":"Becquet's Custom Programming",
    "wof:placetype":"venue"
},
  "geometry": {"coordinates":[-102.46525573700001,51.2112541199],"type":"Point"}
}