{
  "type": "Feature",
  "properties": {
    "iso:country":"CA",
    "sg:address":"2211 Granville St",
    "sg:city":"Vancouver",
    "sg:classifiers":[
        {
            "category":"Restaurant",
            "type":"Food & Drink"
        }
    ],
    "sg:phone":"+1 604 737 2857",
    "sg:postcode":"V6H 3G1",
    "sg:province":"BC",
    "wof:name":"Paul's Place Restaurant",
    "wof:placetype":"venue"
},
  "geometry": {"coordinates":[-123.138687,49.266041],"type":"Point"}
}