{
  "type": "Feature",
  "properties": {
    "iso:country":"CA",
    "sg:address":"297 323 Rte",
    "sg:city":"Namur",
    "sg:classifiers":[
        {
            "category":"Manufacturing",
            "subcategory":"Tools & Machinery",
            "type":"Manufacturing & Wholesale Goods"
        }
    ],
    "sg:phone":"+1 819 426 2702",
    "sg:postcode":"J0V 1N0",
    "sg:province":"QC",
    "sg:tags":[
        "machine",
        "shop"
    ],
    "wof:name":"Atelier D'Usinage Gg",
    "wof:placetype":"venue"
},
  "geometry": {"coordinates":[-74.92668914790001,45.8969764709],"type":"Point"}
}