{
  "type": "Feature",
  "properties": {
    "addr:full":"PO Box 28 Trochu AB T0M 2C0",
    "addr:housenumber":"po box 28",
    "addr:postcode":"t0m 2c0",
    "iso:country":"CA",
    "sg:address":"PO Box 28",
    "sg:city":"Trochu",
    "sg:classifiers":[
        {
            "category":"Organizations",
            "subcategory":"Religious Organization",
            "type":"Services"
        }
    ],
    "sg:phone":"+1 403 442 3858",
    "sg:postcode":"T0M 2C0",
    "sg:province":"AB",
    "sg:tags":[
        "church"
    ],
    "wof:name":"Trochu United Church",
    "wof:placetype":"venue"
},
  "geometry": {"coordinates":[-113.237633,51.823704],"type":"Point"}
}