{
  "type": "Feature",
  "properties": {
    "iso:country":"CA",
    "sg:city":"Pasadena",
    "sg:classifiers":[
        {
            "category":"Freight",
            "type":"Transportation"
        }
    ],
    "sg:phone":"+1 709 686 5773",
    "sg:postcode":"A0L 1K0",
    "sg:province":"NL",
    "sg:tags":[
        "commercial",
        "cleaning"
    ],
    "wof:name":"Newfoundland Jet Blast Svc",
    "wof:placetype":"venue"
},
  "geometry": {"coordinates":[-57.5958518982,49.0205917358],"type":"Point"}
}