{
  "type": "Feature",
  "properties": {
    "addr:full":"14730 102 St Grande Prairie AB T8V 7E1",
    "addr:housenumber":"14730",
    "addr:postcode":"t8v 7e1",
    "addr:street":"102 St",
    "iso:country":"CA",
    "sg:address":"14730 102 St",
    "sg:city":"Grande Prairie",
    "sg:classifiers":[
        {
            "category":"Freight",
            "type":"Transportation"
        }
    ],
    "sg:phone":"+1 780 539 0037",
    "sg:postcode":"T8V 7E1",
    "sg:province":"AB",
    "sg:tags":[
        "field",
        "oil"
    ],
    "wof:name":"Swanberg Brothers Trucking Ltd",
    "wof:placetype":"venue"
},
  "geometry": {"coordinates":[-118.80126199999999,55.199623],"type":"Point"}
}