{
  "type": "Feature",
  "properties": {
    "iso:country":"CA",
    "sg:address":"304 Rue Deland",
    "sg:city":"L'Acadie",
    "sg:classifiers":[
        {
            "category":"Building & Trades",
            "subcategory":"Electrical",
            "type":"Services"
        }
    ],
    "sg:phone":"+1 450 347 0076",
    "sg:postcode":"J2Y 1A6",
    "sg:province":"QC",
    "sg:tags":[
        "electric",
        "contractor"
    ],
    "wof:name":"Y L Electrique Inc",
    "wof:placetype":"venue"
},
  "geometry": {"coordinates":[-73.315201,45.316349],"type":"Point"}
}