{
  "type": "Feature",
  "properties": {
    "iso:country":"CA",
    "sg:address":"350 Palladium Dr",
    "sg:city":"Kanata",
    "sg:classifiers":[
        {
            "category":"Health Services",
            "subcategory":"Doctor",
            "type":"Services"
        }
    ],
    "sg:phone":"+1 613 592 1707",
    "sg:postcode":"K2V 1A8",
    "sg:province":"ON",
    "sg:tags":[
        "physician",
        "surgeon"
    ],
    "wof:name":"Viner, Norman MD",
    "wof:placetype":"venue"
},
  "geometry": {"coordinates":[-75.9102096558,45.2996406555],"type":"Point"}
}