{
  "type": "Feature",
  "properties": {
    "iso:country":"CA",
    "sg:address":"1525 Seymour St",
    "sg:city":"North Bay",
    "sg:classifiers":[
        {
            "category":"Travel",
            "subcategory":"Hotels & Motels",
            "type":"Entertainment"
        }
    ],
    "sg:phone":"+1 705 495 1133",
    "sg:postcode":"P1B 8G4",
    "sg:province":"ON",
    "wof:name":"Travelodge Airport North Bay",
    "wof:placetype":"venue"
},
  "geometry": {"coordinates":[-79.4387664795,46.3091888428],"type":"Point"}
}