{
  "type": "Feature",
  "properties": {
    "addr:full":"Kitchener ON N2B 3C3",
    "addr:postcode":"n2b 3c3",
    "iso:country":"CA",
    "sg:city":"Kitchener",
    "sg:classifiers":[
        {
            "category":"Shopping",
            "subcategory":"Computers & Home Electronics",
            "type":"Retail Goods"
        }
    ],
    "sg:phone":"+1 519 742 9821",
    "sg:postcode":"N2B 3C3",
    "sg:province":"ON",
    "sg:tags":[
        "equipment",
        "dealer"
    ],
    "wof:name":"Neutron Computers Inc",
    "wof:placetype":"venue"
},
  "geometry": {"coordinates":[-80.468788147,43.4626846313],"type":"Point"}
}