{
  "type": "Feature",
  "properties": {
    "iso:country":"CA",
    "sg:city":"London",
    "sg:classifiers":[
        {
            "category":"Social Services",
            "type":"Services"
        }
    ],
    "sg:phone":"+1 519 641 3006",
    "sg:postcode":"N6K 4L4",
    "sg:province":"ON",
    "sg:tags":[
        "organization",
        "welfare"
    ],
    "wof:name":"Community Homes Ltd",
    "wof:placetype":"venue"
},
  "geometry": {"coordinates":[-81.29737091059999,42.9524116516],"type":"Point"}
}