{
  "type": "Feature",
  "properties": {
    "iso:country":"CA",
    "sg:address":"1005 Boul Laure",
    "sg:city":"Sept-Iles",
    "sg:classifiers":[
        {
            "category":"Food & Beverages",
            "subcategory":"Groceries & Convenience Stores",
            "type":"Retail Goods"
        }
    ],
    "sg:phone":"+1 418 968 1213",
    "sg:postcode":"G4R 4S6",
    "sg:province":"QC",
    "sg:tags":[
        "grocer"
    ],
    "wof:name":"Maxi",
    "wof:placetype":"venue"
},
  "geometry": {"coordinates":[-66.39180755620001,50.2270050049],"type":"Point"}
}