{
  "type": "Feature",
  "properties": {
    "addr:full":"11660 95 St NW Edmonton AB T5G 1L8",
    "addr:housenumber":"11660",
    "addr:postcode":"t5g 1l8",
    "addr:street":"95 St Nw",
    "iso:country":"CA",
    "sg:address":"11660 95 St NW",
    "sg:city":"Edmonton",
    "sg:classifiers":[
        {
            "category":"Health Services",
            "subcategory":"Doctor",
            "type":"Services"
        }
    ],
    "sg:phone":"+1 780 474 2456",
    "sg:postcode":"T5G 1L8",
    "sg:province":"AB",
    "sg:tags":[
        "dentist"
    ],
    "wof:name":"Norwood Dental Assoc",
    "wof:placetype":"venue"
},
  "geometry": {"coordinates":[-113.487442,53.56823],"type":"Point"}
}