{
  "type": "Feature",
  "properties": {
    "addr:full":"825 Av Tanguay N Alma QC G8B 5Y2",
    "addr:housenumber":"825",
    "addr:postcode":"g8b 5y2",
    "addr:street":"Av Tanguay N",
    "iso:country":"CA",
    "sg:address":"825 Av Tanguay N",
    "sg:city":"Alma",
    "sg:classifiers":[
        {
            "category":"Farming",
            "subcategory":"Farm & Veterinary Services",
            "type":"Manufacturing & Wholesale Goods"
        }
    ],
    "sg:phone":"+1 418 480 1677",
    "sg:postcode":"G8B 5Y2",
    "sg:province":"QC",
    "wof:name":"Agriforfait",
    "wof:placetype":"venue"
},
  "geometry": {"coordinates":[-71.642448,48.566616],"type":"Point"}
}