{
  "type": "Feature",
  "properties": {
    "iso:country":"CA",
    "sg:address":"150 Victoria St E",
    "sg:city":"Amherst",
    "sg:classifiers":[
        {
            "category":"Travel",
            "subcategory":"Hotels & Motels",
            "type":"Entertainment"
        }
    ],
    "sg:phone":"+1 902 667 7211",
    "sg:postcode":"B4H 1Y3",
    "sg:province":"NS",
    "wof:name":"Victorian Motel",
    "wof:placetype":"venue"
},
  "geometry": {"coordinates":[-64.21066999999999,45.836372],"type":"Point"}
}