{
  "type": "Feature",
  "properties": {
    "iso:country":"CA",
    "sg:city":"Winnipeg",
    "sg:classifiers":[
        {
            "category":"Shopping",
            "subcategory":"Gifts & Souvenirs",
            "type":"Retail Goods"
        }
    ],
    "sg:phone":"+1 204 989 2160",
    "sg:postcode":"R3C 4S8",
    "sg:province":"MB",
    "sg:tags":[
        "shop"
    ],
    "wof:name":"Cricklewood & CO",
    "wof:placetype":"venue"
},
  "geometry": {"coordinates":[-97.129517,49.887482],"type":"Point"}
}