{
  "type": "Feature",
  "properties": {
    "addr:full":"Devon AB T9G 1G2",
    "addr:postcode":"t9g 1g2",
    "iso:country":"CA",
    "sg:city":"Devon",
    "sg:classifiers":[
        {
            "category":"Insurance",
            "subcategory":"Insurance Agent",
            "type":"Services"
        }
    ],
    "sg:phone":"+1 780 987 5296",
    "sg:postcode":"T9G 1G2",
    "sg:province":"AB",
    "wof:name":"Drake Insurance",
    "wof:placetype":"venue"
},
  "geometry": {"coordinates":[-113.729034,53.365955],"type":"Point"}
}