{
  "type": "Feature",
  "properties": {
    "addr:full":"715 Boul Provencher Brossard QC J4W 1Y5",
    "addr:housenumber":"715",
    "addr:postcode":"j4w 1y5",
    "addr:street":"Boul Provencher",
    "iso:country":"CA",
    "sg:address":"715 Boul Provencher",
    "sg:city":"Brossard",
    "sg:classifiers":[
        {
            "category":"Organizations",
            "subcategory":"Religious Organization",
            "type":"Services"
        }
    ],
    "sg:phone":"+1 450 672 7948",
    "sg:postcode":"J4W 1Y5",
    "sg:province":"QC",
    "sg:tags":[
        "church"
    ],
    "wof:name":"Assoc Bouddhique Vietnamienne",
    "wof:placetype":"venue"
},
  "geometry": {"coordinates":[-73.49077606199999,45.4711837769],"type":"Point"}
}