{
  "type": "Feature",
  "properties": {
    "addr:full":"1039 Durham Ave SW Calgary AB T2T 0P8",
    "addr:housenumber":"1039",
    "addr:postcode":"t2t 0p8",
    "addr:street":"Durham Ave Sw",
    "iso:country":"CA",
    "sg:address":"1039 Durham Ave SW",
    "sg:city":"Calgary",
    "sg:classifiers":[
        {
            "category":"Mining & Drilling",
            "type":"Manufacturing & Wholesale Goods"
        }
    ],
    "sg:phone":"+1 403 245 4788",
    "sg:postcode":"T2T 0P8",
    "sg:province":"AB",
    "sg:tags":[
        "consultant",
        "oil",
        "gas"
    ],
    "wof:name":"Mungan Petroleum Consultants",
    "wof:placetype":"venue"
},
  "geometry": {"coordinates":[-114.084602356,51.0342216492],"type":"Point"}
}