{
  "type": "Feature",
  "properties": {
    "iso:country":"CA",
    "sg:address":"30 Ridgewood Rd",
    "sg:city":"St Catharines",
    "sg:classifiers":[
        {
            "category":"Building & Trades",
            "subcategory":"Construction",
            "type":"Services"
        }
    ],
    "sg:phone":"+1 905 685 6006",
    "sg:postcode":"L2R 3S5",
    "sg:province":"ON",
    "sg:tags":[
        "designer",
        "marine",
        "contractor"
    ],
    "wof:name":"All Fast Marine Inc",
    "wof:placetype":"venue"
},
  "geometry": {"coordinates":[-79.23597,43.150276],"type":"Point"}
}