{
  "type": "Feature",
  "properties": {
    "addr:full":"6860 Ch DE LA Cote-Saint-Luc Montreal QC H4V 1H5",
    "addr:housenumber":"6860",
    "addr:postcode":"h4v 1h5",
    "addr:street":"Ch De La Cote-Saint-Luc",
    "iso:country":"CA",
    "sg:address":"6860 Ch DE LA Cote-Saint-Luc",
    "sg:city":"Montreal",
    "sg:classifiers":[
        {
            "category":"Restaurant",
            "type":"Food & Drink"
        }
    ],
    "sg:phone":"+1 514 489 7575",
    "sg:postcode":"H4V 1H5",
    "sg:province":"QC",
    "wof:name":"Carveli Restaurant",
    "wof:placetype":"venue"
},
  "geometry": {"coordinates":[-73.6512832642,45.4679718018],"type":"Point"}
}