{
  "type": "Feature",
  "properties": {
    "addr:full":"111 Villarboit Cres Concord ON L4K 4K2",
    "addr:housenumber":"111",
    "addr:postcode":"l4k 4k2",
    "addr:street":"Villarboit Cres",
    "iso:country":"CA",
    "sg:address":"111 Villarboit Cres",
    "sg:city":"Concord",
    "sg:classifiers":[
        {
            "category":"Wholesale",
            "subcategory":"Non-durable Goods",
            "type":"Manufacturing & Wholesale Goods"
        }
    ],
    "sg:phone":"+1 905 669 2247",
    "sg:postcode":"L4K 4K2",
    "sg:province":"ON",
    "sg:tags":[
        "bag",
        "canvas",
        "cotton"
    ],
    "wof:name":"Debco Bag Distributors Ltd",
    "wof:placetype":"venue"
},
  "geometry": {"coordinates":[-79.49514007569999,43.8267784119],"type":"Point"}
}