{
  "type": "Feature",
  "properties": {
    "addr:full":"662 Henry St Woodstock ON N4S 1Y1",
    "addr:housenumber":"662",
    "addr:postcode":"n4s 1y1",
    "addr:street":"Henry St",
    "iso:country":"CA",
    "sg:address":"662 Henry St",
    "sg:city":"Woodstock",
    "sg:classifiers":[
        {
            "category":"Shopping",
            "subcategory":"Discount & Variety Stores",
            "type":"Retail Goods"
        }
    ],
    "sg:phone":"+1 519 539 0021",
    "sg:postcode":"N4S 1Y1",
    "sg:province":"ON",
    "wof:name":"Southside Mini Market",
    "wof:placetype":"venue"
},
  "geometry": {"coordinates":[-80.74799299999999,43.126251],"type":"Point"}
}