{
  "type": "Feature",
  "properties": {
    "iso:country":"CA",
    "sg:address":"3664 60 Ave SE",
    "sg:city":"Calgary",
    "sg:classifiers":[
        {
            "category":"Wholesale",
            "subcategory":"Groceries",
            "type":"Manufacturing & Wholesale Goods"
        }
    ],
    "sg:phone":"+1 403 236 3773",
    "sg:postcode":"T2C 2C7",
    "sg:province":"AB",
    "sg:tags":[
        "food",
        "product"
    ],
    "wof:name":"Institutional Food Supply Ltd",
    "wof:placetype":"venue"
},
  "geometry": {"coordinates":[-113.982391357,51.0001525879],"type":"Point"}
}