{
  "type": "Feature",
  "properties": {
    "iso:country":"CA",
    "sg:address":"3350 South Service Rd",
    "sg:city":"Burlington",
    "sg:classifiers":[
        {
            "category":"Building & Trades",
            "subcategory":"Landscaping Services",
            "type":"Services"
        }
    ],
    "sg:phone":"+1 905 333 1034",
    "sg:postcode":"L7N 3M6",
    "sg:province":"ON",
    "sg:tags":[
        "tree"
    ],
    "wof:name":"Davey Tree Corp Office",
    "wof:placetype":"venue"
},
  "geometry": {"coordinates":[-79.793205,43.360977],"type":"Point"}
}