{
  "type": "Feature",
  "properties": {
    "addr:full":"624 Rue Principale O Farnham QC J2N 1K9",
    "addr:housenumber":"624",
    "addr:postcode":"j2n 1k9",
    "addr:street":"Rue Principale O",
    "iso:country":"CA",
    "sg:address":"624 Rue Principale O",
    "sg:city":"Farnham",
    "sg:classifiers":[
        {
            "category":"Retail",
            "subcategory":"Auto Repair",
            "type":"Services"
        }
    ],
    "sg:phone":"+1 450 293 3161",
    "sg:postcode":"J2N 1K9",
    "sg:province":"QC",
    "sg:tags":[
        "repairing",
        "automobile"
    ],
    "wof:name":"Carrefour Pneus Mecanique",
    "wof:placetype":"venue"
},
  "geometry": {"coordinates":[-72.97211456300001,45.2824287415],"type":"Point"}
}