{
  "type": "Feature",
  "properties": {
    "addr:full":"Sydney NS B1S 1A9",
    "addr:postcode":"b1s 1a9",
    "iso:country":"CA",
    "sg:city":"Sydney",
    "sg:classifiers":[
        {
            "category":"Health Services",
            "subcategory":"Doctor",
            "type":"Services"
        }
    ],
    "sg:phone":"+1 902 539 1903",
    "sg:postcode":"B1S 1A9",
    "sg:province":"NS",
    "sg:tags":[
        "physician",
        "surgeon"
    ],
    "wof:name":"Boyd, George MD",
    "wof:placetype":"venue"
},
  "geometry": {"coordinates":[-60.1999702454,46.1245002747],"type":"Point"}
}