{
  "type": "Feature",
  "properties": {
    "iso:country":"CA",
    "sg:address":"12831 Horseshoe Pl",
    "sg:city":"Richmond",
    "sg:classifiers":[
        {
            "category":"Shopping",
            "subcategory":"Pharmacy",
            "type":"Retail Goods"
        }
    ],
    "sg:phone":"+1 604 272 7400",
    "sg:postcode":"V7A 4X5",
    "sg:province":"BC",
    "wof:name":"London Drugs Ltd",
    "wof:placetype":"venue"
},
  "geometry": {"coordinates":[-123.10006,49.121857],"type":"Point"}
}