{
  "type": "Feature",
  "properties": {
    "addr:full":"Brampton ON L6W 3M5",
    "addr:postcode":"l6w 3m5",
    "iso:country":"CA",
    "sg:city":"Brampton",
    "sg:classifiers":[
        {
            "category":"Professional",
            "subcategory":"Business Services",
            "type":"Services"
        }
    ],
    "sg:phone":"+1 905 454 5557",
    "sg:postcode":"L6W 3M5",
    "sg:province":"ON",
    "sg:tags":[
        "packaging"
    ],
    "wof:name":"Rsi Refurbishing Specialists",
    "wof:placetype":"venue"
},
  "geometry": {"coordinates":[-79.71693399999999,43.685585],"type":"Point"}
}