{
  "type": "Feature",
  "properties": {
    "addr:full":"270 Boul DE L'Ile Pincourt QC J7V 3R9",
    "addr:housenumber":"270",
    "addr:postcode":"j7v 3r9",
    "addr:street":"Boul De L'Ile",
    "iso:country":"CA",
    "sg:address":"270 Boul DE L'Ile",
    "sg:city":"Pincourt",
    "sg:classifiers":[
        {
            "category":"Social Services",
            "subcategory":"Child Care",
            "type":"Services"
        }
    ],
    "sg:phone":"+1 514 453 6687",
    "sg:postcode":"J7V 3R9",
    "sg:province":"QC",
    "wof:name":"Centre DE LA Petite Enfance",
    "wof:placetype":"venue"
},
  "geometry": {"coordinates":[-74.02986900000001,45.429287],"type":"Point"}
}