{
  "type": "Feature",
  "properties": {
    "addr:full":"109 3rd St N Geraldton ON P0T 1M0",
    "addr:housenumber":"109",
    "addr:postcode":"p0t 1m0",
    "addr:street":"3Rd St N",
    "iso:country":"CA",
    "sg:address":"109 3rd St N",
    "sg:city":"Geraldton",
    "sg:classifiers":[
        {
            "category":"Shopping",
            "subcategory":"Gifts & Souvenirs",
            "type":"Retail Goods"
        }
    ],
    "sg:phone":"+1 807 854 1348",
    "sg:postcode":"P0T 1M0",
    "sg:province":"ON",
    "sg:tags":[
        "shop"
    ],
    "wof:name":"Nicole's Variety & Gifts",
    "wof:placetype":"venue"
},
  "geometry": {"coordinates":[-86.9469985962,49.7271957397],"type":"Point"}
}