{
  "type": "Feature",
  "properties": {
    "addr:full":"Vancouver BC V6C 3K4",
    "addr:postcode":"v6c 3k4",
    "iso:country":"CA",
    "sg:city":"Vancouver",
    "sg:classifiers":[
        {
            "category":"Building & Trades",
            "subcategory":"Equipment Rental",
            "type":"Services"
        }
    ],
    "sg:phone":"+1 604 641 1994",
    "sg:postcode":"V6C 3K4",
    "sg:province":"BC",
    "sg:tags":[
        "leasing"
    ],
    "wof:name":"Hsbc Leasing",
    "wof:placetype":"venue"
},
  "geometry": {"coordinates":[-123.118202209,49.2846603394],"type":"Point"}
}