{
  "type": "Feature",
  "properties": {
    "addr:full":"Orleans ON K1C 6E7",
    "addr:postcode":"k1c 6e7",
    "iso:country":"CA",
    "sg:city":"Orleans",
    "sg:classifiers":[
        {
            "category":"Shopping",
            "subcategory":"Hobbies, Toys, & Games",
            "type":"Retail Goods"
        }
    ],
    "sg:phone":"+1 613 830 2373",
    "sg:postcode":"K1C 6E7",
    "sg:province":"ON",
    "sg:tags":[
        "model",
        "supply"
    ],
    "wof:name":"Discount Hobbies",
    "wof:placetype":"venue"
},
  "geometry": {"coordinates":[-75.5472488403,45.4618682861],"type":"Point"}
}