{
  "type": "Feature",
  "properties": {
    "addr:full":"780 Av Gamache Sept-Iles QC G4R 2J7",
    "addr:housenumber":"780",
    "addr:postcode":"g4r 2j7",
    "addr:street":"Av Gamache Sept-Iles",
    "iso:country":"CA",
    "sg:address":"780 Av Gamache",
    "sg:city":"Sept-Iles",
    "sg:classifiers":[
        {
            "category":"Building & Trades",
            "subcategory":"Construction",
            "type":"Services"
        }
    ],
    "sg:phone":"+1 418 968 4560",
    "sg:postcode":"G4R 2J7",
    "sg:province":"QC",
    "sg:tags":[
        "painter"
    ],
    "wof:name":"E Blanchard & Fils Peinture",
    "wof:placetype":"venue"
},
  "geometry": {"coordinates":[-66.38952636720001,50.218372345],"type":"Point"}
}