{
  "type": "Feature",
  "properties": {
    "iso:country":"CA",
    "sg:city":"Campbellville",
    "sg:classifiers":[
        {
            "category":"Sports & Exercise",
            "subcategory":"Golf",
            "type":"Entertainment"
        }
    ],
    "sg:phone":"+1 905 335 6028",
    "sg:postcode":"L0P 1B0",
    "sg:province":"ON",
    "sg:tags":[
        "course"
    ],
    "wof:name":"Camisle Golf",
    "wof:placetype":"venue"
},
  "geometry": {"coordinates":[-79.98304748539999,43.487739563],"type":"Point"}
}