{
  "type": "Feature",
  "properties": {
    "addr:full":"Saint-Apollinaire QC G0S 2E0",
    "addr:postcode":"g0s 2e0",
    "iso:country":"CA",
    "sg:city":"Saint-Apollinaire",
    "sg:classifiers":[
        {
            "category":"Shopping",
            "subcategory":"Shoes",
            "type":"Retail Goods"
        }
    ],
    "sg:phone":"+1 418 881 2356",
    "sg:postcode":"G0S 2E0",
    "sg:province":"QC",
    "wof:name":"Cordonnerie Touche-A-Tout",
    "wof:placetype":"venue"
},
  "geometry": {"coordinates":[-71.5077972412,46.6160469055],"type":"Point"}
}