{
  "type": "Feature",
  "properties": {
    "addr:full":"1510 Boul Jacques-Cartier E Longueuil QC J4M 1B3",
    "addr:housenumber":"1510",
    "addr:postcode":"j4m 1b3",
    "addr:street":"Boul Jacques-Cartier E",
    "iso:country":"CA",
    "sg:address":"1510 Boul Jacques-Cartier E",
    "sg:city":"Longueuil",
    "sg:classifiers":[
        {
            "category":"Autos & Motor Vehicles",
            "subcategory":"Fuel & Gas Station",
            "type":"Retail Goods"
        }
    ],
    "sg:phone":"+1 450 448 1124",
    "sg:postcode":"J4M 1B3",
    "sg:province":"QC",
    "sg:tags":[
        "oil"
    ],
    "wof:name":"Shell Canada Ltee",
    "wof:placetype":"venue"
},
  "geometry": {"coordinates":[-73.4562,45.538437],"type":"Point"}
}