{
  "type": "Feature",
  "properties": {
    "addr:full":"Sudbury ON P3A 4S4",
    "addr:postcode":"p3a 4s4",
    "iso:country":"CA",
    "sg:city":"Sudbury",
    "sg:classifiers":[
        {
            "category":"Freight",
            "type":"Transportation"
        }
    ],
    "sg:phone":"+1 705 560 2000",
    "sg:postcode":"P3A 4S4",
    "sg:province":"ON",
    "sg:tags":[
        "mover"
    ],
    "wof:name":"Harris Movers & Storage",
    "wof:placetype":"venue"
},
  "geometry": {"coordinates":[-80.9896621704,46.4895896912],"type":"Point"}
}