{
  "type": "Feature",
  "properties": {
    "iso:country":"CA",
    "sg:address":"1606 7 St SW",
    "sg:city":"Calgary",
    "sg:classifiers":[
        {
            "category":"Shopping",
            "subcategory":"Jewelry",
            "type":"Retail Goods"
        }
    ],
    "sg:phone":"+1 403 245 1562",
    "sg:postcode":"T2R 1A7",
    "sg:province":"AB",
    "sg:tags":[
        "beads"
    ],
    "wof:name":"Beadles Beads & Designer Jwlry",
    "wof:placetype":"venue"
},
  "geometry": {"coordinates":[-114.079292,51.038013],"type":"Point"}
}