{
  "type": "Feature",
  "properties": {
    "addr:full":"1 Cedar Dr Orangeville ON L9W 2X5",
    "addr:housenumber":"1",
    "addr:postcode":"l9w 2x5",
    "addr:street":"Cedar Dr",
    "iso:country":"CA",
    "sg:address":"1 Cedar Dr",
    "sg:city":"Orangeville",
    "sg:classifiers":[
        {
            "category":"Building & Trades",
            "subcategory":"Plumbing",
            "type":"Services"
        }
    ],
    "sg:phone":"+1 519 941 1177",
    "sg:postcode":"L9W 2X5",
    "sg:province":"ON",
    "sg:tags":[
        "septic"
    ],
    "wof:name":"Terry Hunter Septic Pumps",
    "wof:placetype":"venue"
},
  "geometry": {"coordinates":[-80.1008605957,43.9079475403],"type":"Point"}
}