{
  "type": "Feature",
  "properties": {
    "addr:full":"Railway Ave N Clanwilliam MB R0J 0K0",
    "addr:postcode":"r0j 0k0",
    "addr:street":"Railway Ave N",
    "iso:country":"CA",
    "sg:address":"Railway Ave N",
    "sg:city":"Clanwilliam",
    "sg:classifiers":[
        {
            "category":"Recreation",
            "type":"Entertainment"
        }
    ],
    "sg:phone":"+1 204 865 2481",
    "sg:postcode":"R0J 0K0",
    "sg:province":"MB",
    "sg:tags":[
        "club",
        "curling"
    ],
    "wof:name":"Clanwilliam Curling Club",
    "wof:placetype":"venue"
},
  "geometry": {"coordinates":[-99.8151931763,50.4908981323],"type":"Point"}
}