{
  "type": "Feature",
  "properties": {
    "addr:full":"Pointe-Claire QC H9R 5N8",
    "addr:postcode":"h9r 5n8",
    "iso:country":"CA",
    "sg:city":"Pointe-Claire",
    "sg:classifiers":[
        {
            "category":"Shopping",
            "subcategory":"Hobbies, Toys, & Games",
            "type":"Retail Goods"
        }
    ],
    "sg:phone":"+1 514 697 7550",
    "sg:postcode":"H9R 5N8",
    "sg:province":"QC",
    "wof:name":"Jouets Choo-Choo",
    "wof:placetype":"venue"
},
  "geometry": {"coordinates":[-73.830376,45.468391],"type":"Point"}
}