{
  "type": "Feature",
  "properties": {
    "iso:country":"CA",
    "sg:address":"5 Humphrey St",
    "sg:city":"Moncton",
    "sg:classifiers":[
        {
            "category":"Personal",
            "subcategory":"Beauty Salon",
            "type":"Services"
        }
    ],
    "sg:phone":"+1 506 856 9008",
    "sg:postcode":"E1C 6N8",
    "sg:province":"NB",
    "wof:name":"Fancy Image Hair Care",
    "wof:placetype":"venue"
},
  "geometry": {"coordinates":[-64.798042,46.098408],"type":"Point"}
}