{
  "type": "Feature",
  "properties": {
    "addr:full":"14011 Boul Du Cure-Labelle Mirabel QC J7J 1M3",
    "addr:housenumber":"14011",
    "addr:postcode":"j7j 1m3",
    "addr:street":"Boul Du Cure-Labelle",
    "iso:country":"CA",
    "sg:address":"14011 Boul Du Cure-Labelle",
    "sg:city":"Mirabel",
    "sg:classifiers":[
        {
            "category":"Professional",
            "subcategory":"Accounting & Tax Preparation",
            "type":"Services"
        }
    ],
    "sg:phone":"+1 450 434 1484",
    "sg:postcode":"J7J 1M3",
    "sg:province":"QC",
    "sg:tags":[
        "accountant"
    ],
    "wof:name":"Belisle, Alain CA",
    "wof:placetype":"venue"
},
  "geometry": {"coordinates":[-73.932152,45.707253],"type":"Point"}
}