{
  "type": "Feature",
  "properties": {
    "addr:full":"PO Box 3097 STN Main Wainwright AB T9W 1T1",
    "addr:housenumber":"po",
    "addr:postcode":"t9w 1t1",
    "addr:street":"Box 3097 Stn Main",
    "iso:country":"CA",
    "sg:address":"PO Box 3097 STN Main",
    "sg:city":"Wainwright",
    "sg:classifiers":[
        {
            "category":"Freight",
            "type":"Transportation"
        }
    ],
    "sg:phone":"+1 780 842 4273",
    "sg:postcode":"T9W 1T1",
    "sg:province":"AB",
    "sg:tags":[
        "trucking"
    ],
    "wof:name":"Shopland Trucklines Ltd",
    "wof:placetype":"venue"
},
  "geometry": {"coordinates":[-110.85202,52.843384],"type":"Point"}
}