{
  "type": "Feature",
  "properties": {
    "iso:country":"CA",
    "sg:city":"Owen Sound",
    "sg:classifiers":[
        {
            "category":"Retail",
            "subcategory":"Auto Repair",
            "type":"Services"
        }
    ],
    "sg:phone":"+1 519 371 9600",
    "sg:postcode":"N4K 5N7",
    "sg:province":"ON",
    "sg:tags":[
        "repairing",
        "automobile"
    ],
    "wof:name":"Georgian Bay Motors",
    "wof:placetype":"venue"
},
  "geometry": {"coordinates":[-80.9426040649,44.5648765564],"type":"Point"}
}