{
  "type": "Feature",
  "properties": {
    "addr:full":"Belleville ON K8N 5H5",
    "addr:postcode":"k8n 5h5",
    "iso:country":"CA",
    "sg:city":"Belleville",
    "sg:classifiers":[
        {
            "category":"Professional",
            "subcategory":"Lawyer & Legal Services",
            "type":"Services"
        }
    ],
    "sg:phone":"+1 613 966 1123",
    "sg:postcode":"K8N 5H5",
    "sg:province":"ON",
    "sg:tags":[
        "attorney"
    ],
    "wof:name":"Ketcheson, Richard R",
    "wof:placetype":"venue"
},
  "geometry": {"coordinates":[-77.38391900000001,44.163548],"type":"Point"}
}