{
  "type": "Feature",
  "properties": {
    "addr:full":"Meteghan River NS B0W 2L0",
    "addr:postcode":"b0w 2l0",
    "iso:country":"CA",
    "sg:city":"Meteghan River",
    "sg:classifiers":[
        {
            "category":"Wholesale",
            "subcategory":"Seafood",
            "type":"Manufacturing & Wholesale Goods"
        }
    ],
    "sg:phone":"+1 902 645 2238",
    "sg:postcode":"B0W 2L0",
    "sg:province":"NS",
    "wof:name":"Miss Lisanne Fisheries Ltd",
    "wof:placetype":"venue"
},
  "geometry": {"coordinates":[-66.13762699999999,44.223942],"type":"Point"}
}