{
  "type": "Feature",
  "properties": {
    "addr:full":"334 Boundary Rd E Pembroke ON K8A 6W5",
    "addr:housenumber":"334",
    "addr:postcode":"k8a 6w5",
    "addr:street":"Boundary Rd E",
    "iso:country":"CA",
    "sg:address":"334 Boundary Rd E",
    "sg:city":"Pembroke",
    "sg:classifiers":[
        {
            "category":"Autos & Motor Vehicles",
            "subcategory":"Automobile Sales",
            "type":"Retail Goods"
        }
    ],
    "sg:phone":"+1 613 735 7217",
    "sg:postcode":"K8A 6W5",
    "sg:province":"ON",
    "sg:tags":[
        "car",
        "dealer"
    ],
    "wof:name":"Pembroke Auto Sales",
    "wof:placetype":"venue"
},
  "geometry": {"coordinates":[-77.11745500000001,45.805325],"type":"Point"}
}