{
  "type": "Feature",
  "properties": {
    "addr:full":"6871 Trans Canada Hwy NW Salmon Arm BC V1E 3A2",
    "addr:housenumber":"6871",
    "addr:postcode":"v1e 3a2",
    "addr:street":"Trans Canada Hwy Nw",
    "iso:country":"CA",
    "sg:address":"6871 Trans Canada Hwy NW",
    "sg:city":"Salmon Arm",
    "sg:classifiers":[
        {
            "category":"Travel",
            "subcategory":"Hotels & Motels",
            "type":"Entertainment"
        }
    ],
    "sg:phone":"+1 250 832 2833",
    "sg:postcode":"V1E 3A2",
    "sg:province":"BC",
    "wof:name":"View Point Motel",
    "wof:placetype":"venue"
},
  "geometry": {"coordinates":[-119.32496643099999,50.7496261597],"type":"Point"}
}