{
  "type": "Feature",
  "properties": {
    "addr:full":"47 Sunmills Dr SE Calgary AB T2X 2G6",
    "addr:housenumber":"47",
    "addr:postcode":"t2x 2g6",
    "addr:street":"Sunmills Dr Se",
    "iso:country":"CA",
    "sg:address":"47 Sunmills Dr SE",
    "sg:city":"Calgary",
    "sg:classifiers":[
        {
            "category":"Health Services",
            "subcategory":"Chiropractor",
            "type":"Services"
        }
    ],
    "sg:phone":"+1 403 873 2077",
    "sg:postcode":"T2X 2G6",
    "sg:province":"AB",
    "wof:name":"Adjust To Life Chiropractic",
    "wof:placetype":"venue"
},
  "geometry": {"coordinates":[-114.047805786,50.9048919678],"type":"Point"}
}