{
  "type": "Feature",
  "properties": {
    "iso:country":"CA",
    "sg:address":"269 Memorial Ave",
    "sg:city":"Orillia",
    "sg:classifiers":[
        {
            "category":"Restaurant",
            "type":"Food & Drink"
        }
    ],
    "sg:phone":"+1 705 327 8626",
    "sg:postcode":"L3V 5X9",
    "sg:province":"ON",
    "wof:name":"Burger King",
    "wof:placetype":"venue"
},
  "geometry": {"coordinates":[-79.42432403559999,44.5962104797],"type":"Point"}
}