{
  "type": "Feature",
  "properties": {
    "addr:full":"1059 Plains Rd E Burlington ON L7T 4K1",
    "addr:housenumber":"1059",
    "addr:postcode":"l7t 4k1",
    "addr:street":"Plains Rd E",
    "iso:country":"CA",
    "sg:address":"1059 Plains Rd E",
    "sg:city":"Burlington",
    "sg:classifiers":[
        {
            "category":"Manufacturing",
            "subcategory":"Food",
            "type":"Manufacturing & Wholesale Goods"
        }
    ],
    "sg:phone":"+1 905 333 6806",
    "sg:postcode":"L7T 4K1",
    "sg:province":"ON",
    "sg:tags":[
        "winery"
    ],
    "wof:name":"Colio Estate Wines",
    "wof:placetype":"venue"
},
  "geometry": {"coordinates":[-79.82777404789999,43.3262405396],"type":"Point"}
}