{
  "type": "Feature",
  "properties": {
    "iso:country":"CA",
    "sg:address":"132 Centre St",
    "sg:city":"St Thomas",
    "sg:classifiers":[
        {
            "category":"Health Services",
            "subcategory":"Doctor",
            "type":"Services"
        }
    ],
    "sg:phone":"+1 519 631 5525",
    "sg:postcode":"N5R 3A2",
    "sg:province":"ON",
    "sg:tags":[
        "dentist"
    ],
    "wof:name":"Nolan, Daniel R DDS",
    "wof:placetype":"venue"
},
  "geometry": {"coordinates":[-81.19821929930001,42.7777328491],"type":"Point"}
}