{
  "type": "Feature",
  "properties": {
    "addr:full":"2333 Boul Saint-Paul Chicoutimi QC G7K 1E5",
    "addr:housenumber":"2333",
    "addr:postcode":"g7k 1e5",
    "addr:street":"Boul Saint-Paul",
    "iso:country":"CA",
    "sg:address":"2333 Boul Saint-Paul",
    "sg:city":"Chicoutimi",
    "sg:classifiers":[
        {
            "category":"Manufacturing",
            "subcategory":"Motor Vehicles & Parts",
            "type":"Manufacturing & Wholesale Goods"
        }
    ],
    "sg:phone":"+1 418 549 8830",
    "sg:postcode":"G7K 1E5",
    "sg:province":"QC",
    "sg:tags":[
        "equipment",
        "truck"
    ],
    "wof:name":"Camions International 170 Ltee",
    "wof:placetype":"venue"
},
  "geometry": {"coordinates":[-71.114143,48.388344],"type":"Point"}
}