{
  "type": "Feature",
  "properties": {
    "addr:full":"4011 Richmond Rd SW Calgary AB T3E 4P2",
    "addr:housenumber":"4011",
    "addr:postcode":"t3e 4p2",
    "addr:street":"Richmond Rd Sw",
    "iso:country":"CA",
    "sg:address":"4011 Richmond Rd SW",
    "sg:city":"Calgary",
    "sg:classifiers":[
        {
            "category":"Retail",
            "subcategory":"Car Wash",
            "type":"Services"
        }
    ],
    "sg:phone":"+1 403 246 2266",
    "sg:postcode":"T3E 4P2",
    "sg:province":"AB",
    "sg:tags":[
        "polishing",
        "washing"
    ],
    "wof:name":"Western Pride Car Wash",
    "wof:placetype":"venue"
},
  "geometry": {"coordinates":[-114.143814087,51.0213470459],"type":"Point"}
}