{
  "type": "Feature",
  "properties": {
    "iso:country":"CA",
    "sg:city":"Dartmouth",
    "sg:classifiers":[
        {
            "category":"Wholesale",
            "subcategory":"Machinery & Supplies",
            "type":"Manufacturing & Wholesale Goods"
        }
    ],
    "sg:phone":"+1 902 468 5406",
    "sg:postcode":"B3B 1S9",
    "sg:province":"NS",
    "sg:tags":[
        "printer",
        "printing",
        "cartridge"
    ],
    "wof:name":"Sun Chemical Gpi",
    "wof:placetype":"venue"
},
  "geometry": {"coordinates":[-63.5833625793,44.6950492859],"type":"Point"}
}