{
  "type": "Feature",
  "properties": {
    "addr:full":"Richmond BC V6X 3A5",
    "addr:postcode":"v6x 3a5",
    "iso:country":"CA",
    "sg:city":"Richmond",
    "sg:classifiers":[
        {
            "category":"Real Estate",
            "subcategory":"Developer",
            "type":"Services"
        }
    ],
    "sg:phone":"+1 604 278 3378",
    "sg:postcode":"V6X 3A5",
    "sg:province":"BC",
    "sg:tags":[
        "company",
        "land"
    ],
    "wof:name":"Bogner Developments Ltd",
    "wof:placetype":"venue"
},
  "geometry": {"coordinates":[-123.136177,49.177933],"type":"Point"}
}