{
  "type": "Feature",
  "properties": {
    "addr:full":"324 Dombroskie Rd Haley Station ON K0J 1Y0",
    "addr:housenumber":"324",
    "addr:postcode":"k0j 1y0",
    "addr:street":"Dombroskie Rd",
    "iso:country":"CA",
    "sg:address":"324 Dombroskie Rd",
    "sg:city":"Haley Station",
    "sg:classifiers":[
        {
            "category":"Home & Garden",
            "subcategory":"Building Materials",
            "type":"Retail Goods"
        }
    ],
    "sg:phone":"+1 613 432 6207",
    "sg:postcode":"K0J 1Y0",
    "sg:province":"ON",
    "sg:tags":[
        "lumber"
    ],
    "wof:name":"Dombroskie Sylvester Forest",
    "wof:placetype":"venue"
},
  "geometry": {"coordinates":[-76.777756,45.562916],"type":"Point"}
}