{
  "type": "Feature",
  "properties": {
    "iso:country":"CA",
    "sg:address":"2751 Thamesgate Dr",
    "sg:city":"Mississauga",
    "sg:classifiers":[
        {
            "category":"Arena",
            "subcategory":"Sports Club",
            "type":"Entertainment"
        }
    ],
    "sg:phone":"+1 905 677 0431",
    "sg:postcode":"L4T 1G5",
    "sg:province":"ON",
    "sg:tags":[
        "soccer"
    ],
    "wof:name":"Malton Soccer Club",
    "wof:placetype":"venue"
},
  "geometry": {"coordinates":[-79.657272,43.714771],"type":"Point"}
}