{
  "type": "Feature",
  "properties": {
    "addr:full":"2751 Thamesgate Dr Mississauga ON L4T 1G5",
    "addr:housenumber":"2751",
    "addr:postcode":"l4t 1g5",
    "addr:street":"Thamesgate Dr",
    "iso:country":"CA",
    "sg:address":"2751 Thamesgate Dr",
    "sg:city":"Mississauga",
    "sg:classifiers":[
        {
            "category":"Arena",
            "subcategory":"Sports Club",
            "type":"Entertainment"
        }
    ],
    "sg:phone":"+1 905 677 0431",
    "sg:postcode":"L4T 1G5",
    "sg:province":"ON",
    "sg:tags":[
        "soccer"
    ],
    "wof:name":"Malton Soccer Club",
    "wof:placetype":"venue"
},
  "geometry": {"coordinates":[-79.65727200000001,43.714771],"type":"Point"}
}