{
  "type": "Feature",
  "properties": {
    "addr:full":"1 Stoney Beach Rd Whites Lake NS B3T 2C3",
    "addr:housenumber":"1",
    "addr:postcode":"b3t 2c3",
    "addr:street":"Stoney Beach Rd",
    "iso:country":"CA",
    "sg:address":"1 Stoney Beach Rd",
    "sg:city":"Whites Lake",
    "sg:classifiers":[
        {
            "category":"Shopping",
            "subcategory":"Gifts & Souvenirs",
            "type":"Retail Goods"
        }
    ],
    "sg:phone":"+1 902 852 4436",
    "sg:postcode":"B3T 2C3",
    "sg:province":"NS",
    "sg:tags":[
        "pewter"
    ],
    "wof:name":"Ocean Art Pewter Canada Ltd",
    "wof:placetype":"venue"
},
  "geometry": {"coordinates":[-63.761627,44.528084],"type":"Point"}
}