{
  "type": "Feature",
  "properties": {
    "addr:full":"116 John St N Arnprior ON K7S 2N6",
    "addr:housenumber":"116",
    "addr:postcode":"k7s 2n6",
    "addr:street":"John St N",
    "iso:country":"CA",
    "sg:address":"116 John St N",
    "sg:city":"Arnprior",
    "sg:classifiers":[
        {
            "category":"Manufacturing",
            "subcategory":"Printing",
            "type":"Manufacturing & Wholesale Goods"
        }
    ],
    "sg:phone":"+1 613 623 6571",
    "sg:postcode":"K7S 2N6",
    "sg:province":"ON",
    "sg:tags":[
        "newspaper"
    ],
    "wof:name":"West Carleton Review",
    "wof:placetype":"venue"
},
  "geometry": {"coordinates":[-76.354309,45.433849],"type":"Point"}
}