{
  "type": "Feature",
  "properties": {
    "iso:country":"CA",
    "sg:city":"Moose Jaw",
    "sg:classifiers":[
        {
            "category":"Real Estate",
            "subcategory":"Real Estate Operator",
            "type":"Services"
        }
    ],
    "sg:phone":"+1 306 693 8880",
    "sg:postcode":"S6J 1B4",
    "sg:province":"SK",
    "sg:tags":[
        "apartment"
    ],
    "wof:name":"Woodlily Courts",
    "wof:placetype":"venue"
},
  "geometry": {"coordinates":[-105.53830719,50.4144592285],"type":"Point"}
}