{
  "type": "Feature",
  "properties": {
    "addr:full":"82 Balaclava St St Thomas ON N5P 3C5",
    "addr:housenumber":"82",
    "addr:postcode":"n5p 3c5",
    "addr:street":"Balaclava St",
    "iso:country":"CA",
    "sg:address":"82 Balaclava St",
    "sg:city":"St Thomas",
    "sg:classifiers":[
        {
            "category":"Shopping",
            "type":"Retail Goods"
        }
    ],
    "sg:phone":"+1 519 631 4469",
    "sg:postcode":"N5P 3C5",
    "sg:province":"ON",
    "sg:tags":[
        "trophy",
        "medal",
        "award"
    ],
    "wof:name":"Awards Unlimited",
    "wof:placetype":"venue"
},
  "geometry": {"coordinates":[-81.1828918457,42.7831001282],"type":"Point"}
}