{
  "type": "Feature",
  "properties": {
    "addr:full":"402 Main St Manning AB T0H 2M0",
    "addr:housenumber":"402",
    "addr:postcode":"t0h 2m0",
    "addr:street":"Main St",
    "iso:country":"CA",
    "sg:address":"402 Main St",
    "sg:city":"Manning",
    "sg:classifiers":[
        {
            "category":"Travel",
            "subcategory":"Hotels & Motels",
            "type":"Entertainment"
        }
    ],
    "sg:phone":"+1 780 836 3399",
    "sg:postcode":"T0H 2M0",
    "sg:province":"AB",
    "wof:name":"Garden Court Motel",
    "wof:placetype":"venue"
},
  "geometry": {"coordinates":[-117.625069,56.927868],"type":"Point"}
}