{
  "type": "Feature",
  "properties": {
    "addr:full":"404 13th Ave Cochrane ON P0L 1C0",
    "addr:housenumber":"404",
    "addr:postcode":"p0l 1c0",
    "addr:street":"13Th Ave",
    "iso:country":"CA",
    "sg:address":"404 13th Ave",
    "sg:city":"Cochrane",
    "sg:classifiers":[
        {
            "category":"Professional",
            "subcategory":"Accounting & Tax Preparation",
            "type":"Services"
        }
    ],
    "sg:phone":"+1 705 272 4397",
    "sg:postcode":"P0L 1C0",
    "sg:province":"ON",
    "sg:tags":[
        "return",
        "filing"
    ],
    "wof:name":"Computer Processing Unlimited",
    "wof:placetype":"venue"
},
  "geometry": {"coordinates":[-81.014732,49.069077],"type":"Point"}
}