{
  "type": "Feature",
  "properties": {
    "addr:full":"20020 Willowbrook Dr # 100 Langley BC V2Y 2T4",
    "addr:housenumber":"20020",
    "addr:postcode":"v2y 2t4",
    "addr:street":"Willowbrook Dr # 100",
    "iso:country":"CA",
    "sg:address":"20020 Willowbrook Dr # 100",
    "sg:city":"Langley",
    "sg:classifiers":[
        {
            "category":"Restaurant",
            "type":"Food & Drink"
        }
    ],
    "sg:phone":"+1 604 539 4620",
    "sg:postcode":"V2Y 2T4",
    "sg:province":"BC",
    "wof:name":"Mc Donald's",
    "wof:placetype":"venue"
},
  "geometry": {"coordinates":[-122.667175293,49.1163635254],"type":"Point"}
}