{
  "type": "Feature",
  "properties": {
    "addr:full":"Main St Manyberries AB T0K 1L0",
    "addr:postcode":"t0k 1l0",
    "addr:street":"Main St",
    "iso:country":"CA",
    "sg:address":"Main St",
    "sg:city":"Manyberries",
    "sg:classifiers":[
        {
            "category":"Professional",
            "subcategory":"Business Services",
            "type":"Services"
        }
    ],
    "sg:phone":"+1 403 868 3740",
    "sg:postcode":"T0K 1L0",
    "sg:province":"AB",
    "sg:tags":[
        "reservation",
        "motel",
        "hotel"
    ],
    "wof:name":"Southern Ranchmen's Inn",
    "wof:placetype":"venue"
},
  "geometry": {"coordinates":[-110.69833374,49.4024925232],"type":"Point"}
}