{
  "type": "Feature",
  "properties": {
    "addr:full":"360 St Laurent Ave Quesnel BC V2J 5A3",
    "addr:housenumber":"360",
    "addr:postcode":"v2j 5a3",
    "addr:street":"St Laurent Ave",
    "iso:country":"CA",
    "sg:address":"360 St Laurent Ave",
    "sg:city":"Quesnel",
    "sg:classifiers":[
        {
            "category":"Professional",
            "subcategory":"Accounting & Tax Preparation",
            "type":"Services"
        }
    ],
    "sg:phone":"+1 250 992 5411",
    "sg:postcode":"V2J 5A3",
    "sg:province":"BC",
    "sg:tags":[
        "accountant"
    ],
    "wof:name":"O'Dare & CO",
    "wof:placetype":"venue"
},
  "geometry": {"coordinates":[-122.49438499999999,52.979012],"type":"Point"}
}