{
  "type": "Feature",
  "properties": {
    "addr:full":"300 52 St Edson AB T7E 1X8",
    "addr:housenumber":"52",
    "addr:postcode":"t7e 1x8",
    "addr:street":"300;St",
    "iso:country":"CA",
    "sg:address":"300 52 St",
    "sg:city":"Edson",
    "sg:classifiers":[
        {
            "category":"Travel",
            "subcategory":"Hotels & Motels",
            "type":"Entertainment"
        }
    ],
    "sg:phone":"+1 780 712 2378",
    "sg:postcode":"T7E 1X8",
    "sg:province":"AB",
    "wof:name":"Best Western High Road Inn",
    "wof:placetype":"venue"
},
  "geometry": {"coordinates":[-116.435813904,53.580280304],"type":"Point"}
}