{
  "type": "Feature",
  "properties": {
    "addr:full":"9 Ch Du Manoir Messines QC J0X 2J0",
    "addr:housenumber":"9",
    "addr:postcode":"j0x 2j0",
    "addr:street":"Ch Du Manoir",
    "iso:country":"CA",
    "sg:address":"9 Ch Du Manoir",
    "sg:city":"Messines",
    "sg:classifiers":[
        {
            "category":"Travel",
            "subcategory":"Campground",
            "type":"Entertainment"
        }
    ],
    "sg:phone":"+1 819 465 5351",
    "sg:postcode":"J0X 2J0",
    "sg:province":"QC",
    "wof:name":"Camping Manoir Du Lac Blue",
    "wof:placetype":"venue"
},
  "geometry": {"coordinates":[-76.0652923584,46.2631797791],"type":"Point"}
}