{
  "type": "Feature",
  "properties": {
    "iso:country":"CA",
    "sg:address":"125 Rue Principale",
    "sg:city":"Granby",
    "sg:classifiers":[
        {
            "category":"Education",
            "subcategory":"School",
            "type":"Public Place"
        }
    ],
    "sg:phone":"+1 450 378 9788",
    "sg:postcode":"J2G 2T9",
    "sg:province":"QC",
    "sg:tags":[
        "academic",
        "special"
    ],
    "wof:name":"Centre Alpha",
    "wof:placetype":"venue"
},
  "geometry": {"coordinates":[-72.724319458,45.3990936279],"type":"Point"}
}