{
  "type": "Feature",
  "properties": {
    "addr:full":"766 St Clair Ave W Toronto ON M6C 1B5",
    "addr:housenumber":"766",
    "addr:postcode":"m6c 1b5",
    "addr:street":"St Clair Ave W",
    "iso:country":"CA",
    "sg:address":"766 St Clair Ave W",
    "sg:city":"Toronto",
    "sg:classifiers":[
        {
            "category":"Food & Beverages",
            "subcategory":"Groceries & Convenience Stores",
            "type":"Retail Goods"
        }
    ],
    "sg:phone":"+1 416 653 4707",
    "sg:postcode":"M6C 1B5",
    "sg:province":"ON",
    "wof:name":"Kamal's Discount Plus",
    "wof:placetype":"venue"
},
  "geometry": {"coordinates":[-79.42858099999999,43.681267],"type":"Point"}
}