{
  "type": "Feature",
  "properties": {
    "addr:full":"Saint-Eustache QC J7R 4L1",
    "addr:postcode":"j7r 4l1",
    "iso:country":"CA",
    "sg:city":"Saint-Eustache",
    "sg:classifiers":[
        {
            "category":"Social Services",
            "subcategory":"Job Training",
            "type":"Services"
        }
    ],
    "sg:phone":"+1 450 974 1635",
    "sg:postcode":"J7R 4L1",
    "sg:province":"QC",
    "sg:tags":[
        "employment"
    ],
    "wof:name":"Carrefour Jeunesse-Emploi DE",
    "wof:placetype":"venue"
},
  "geometry": {"coordinates":[-73.901939,45.561497],"type":"Point"}
}