{
  "type": "Feature",
  "properties": {
    "addr:full":"10830 96 St NW Edmonton AB T5H 2J9",
    "addr:housenumber":"10830",
    "addr:postcode":"t5h 2j9",
    "addr:street":"96 St Nw",
    "iso:country":"CA",
    "sg:address":"10830 96 St NW",
    "sg:city":"Edmonton",
    "sg:classifiers":[
        {
            "category":"Organizations",
            "subcategory":"Religious Organization",
            "type":"Services"
        }
    ],
    "sg:phone":"+1 780 423 5389",
    "sg:postcode":"T5H 2J9",
    "sg:province":"AB",
    "sg:tags":[
        "church"
    ],
    "wof:name":"Queen of Martyrs",
    "wof:placetype":"venue"
},
  "geometry": {"coordinates":[-113.487686,53.55484],"type":"Point"}
}