{
  "type": "Feature",
  "properties": {
    "iso:country":"CA",
    "sg:city":"Chatham",
    "sg:classifiers":[
        {
            "category":"Building & Trades",
            "subcategory":"Construction",
            "type":"Services"
        }
    ],
    "sg:phone":"+1 519 354 4799",
    "sg:postcode":"N7M 5J7",
    "sg:province":"ON",
    "sg:tags":[
        "general",
        "contractor"
    ],
    "wof:name":"Sluys, Harry",
    "wof:placetype":"venue"
},
  "geometry": {"coordinates":[-82.189583,42.404446],"type":"Point"}
}