{
  "type": "Feature",
  "properties": {
    "addr:full":"472 Devonian St Estevan SK S4A 2K9",
    "addr:housenumber":"472",
    "addr:postcode":"s4a 2k9",
    "addr:street":"Devonian St",
    "iso:country":"CA",
    "sg:address":"472 Devonian St",
    "sg:city":"Estevan",
    "sg:classifiers":[
        {
            "category":"Building & Trades",
            "subcategory":"Construction",
            "type":"Services"
        }
    ],
    "sg:phone":"+1 306 634 3255",
    "sg:postcode":"S4A 2K9",
    "sg:province":"SK",
    "sg:tags":[
        "general",
        "oil",
        "well",
        "contractor"
    ],
    "wof:name":"Tsb Oilfield Construction",
    "wof:placetype":"venue"
},
  "geometry": {"coordinates":[-102.946686,49.135849],"type":"Point"}
}