{
  "type": "Feature",
  "properties": {
    "addr:full":"40 Rue DE Lisieux Laval QC H7N 2A1",
    "addr:housenumber":"40",
    "addr:postcode":"h7n 2a1",
    "addr:street":"Rue De Lisieux",
    "iso:country":"CA",
    "sg:address":"40 Rue DE Lisieux",
    "sg:city":"Laval",
    "sg:classifiers":[
        {
            "category":"Building & Trades",
            "subcategory":"Plumbing",
            "type":"Services"
        }
    ],
    "sg:phone":"+1 450 663 4746",
    "sg:postcode":"H7N 2A1",
    "sg:province":"QC",
    "sg:tags":[
        "contractor"
    ],
    "wof:name":"Rossi Plomberie & Chauffage",
    "wof:placetype":"venue"
},
  "geometry": {"coordinates":[-73.685959,45.560059],"type":"Point"}
}