{
  "type": "Feature",
  "properties": {
    "addr:full":"20492 Lougheed Hwy Maple Ridge BC V2X 2P8",
    "addr:housenumber":"20492",
    "addr:postcode":"v2x 2p8",
    "addr:street":"Lougheed Hwy",
    "iso:country":"CA",
    "sg:address":"20492 Lougheed Hwy",
    "sg:city":"Maple Ridge",
    "sg:classifiers":[
        {
            "category":"Restaurant",
            "type":"Food & Drink"
        }
    ],
    "sg:phone":"+1 604 465 8600",
    "sg:postcode":"V2X 2P8",
    "sg:province":"BC",
    "sg:tags":[
        "parlor",
        "ice",
        "cream"
    ],
    "wof:name":"Dairy Queen",
    "wof:placetype":"venue"
},
  "geometry": {"coordinates":[-122.653533935,49.2185668945],"type":"Point"}
}