{
  "type": "Feature",
  "properties": {
    "addr:full":"6145 Boul Monk Montreal QC H4E 3H5",
    "addr:housenumber":"6145",
    "addr:postcode":"h4e 3h5",
    "addr:street":"Boul Monk",
    "iso:country":"CA",
    "sg:address":"6145 Boul Monk",
    "sg:city":"Montreal",
    "sg:classifiers":[
        {
            "category":"Cinema",
            "subcategory":"Movie Rental",
            "type":"Entertainment"
        }
    ],
    "sg:phone":"+1 514 769 6348",
    "sg:postcode":"H4E 3H5",
    "sg:province":"QC",
    "sg:tags":[
        "leasing",
        "video",
        "tape",
        "equipment"
    ],
    "wof:name":"Superclub Videotron",
    "wof:placetype":"venue"
},
  "geometry": {"coordinates":[-73.59580200000001,45.457417],"type":"Point"}
}