{
  "type": "Feature",
  "properties": {
    "iso:country":"CA",
    "sg:address":"6145 Boul Monk",
    "sg:city":"Montreal",
    "sg:classifiers":[
        {
            "category":"Cinema",
            "subcategory":"Movie Rental",
            "type":"Entertainment"
        }
    ],
    "sg:phone":"+1 514 769 6348",
    "sg:postcode":"H4E 3H5",
    "sg:province":"QC",
    "sg:tags":[
        "leasing",
        "video",
        "tape",
        "equipment"
    ],
    "wof:name":"Superclub Videotron",
    "wof:placetype":"venue"
},
  "geometry": {"coordinates":[-73.595802,45.457417],"type":"Point"}
}