{
  "type": "Feature",
  "properties": {
    "addr:full":"3189 Valmarie Ave Mississauga ON L5C 2A4",
    "addr:housenumber":"3189",
    "addr:postcode":"l5c 2a4",
    "addr:street":"Valmarie Ave",
    "iso:country":"CA",
    "sg:address":"3189 Valmarie Ave",
    "sg:city":"Mississauga",
    "sg:classifiers":[
        {
            "category":"Insurance",
            "subcategory":"Insurance Agent",
            "type":"Services"
        }
    ],
    "sg:phone":"+1 905 277 4158",
    "sg:postcode":"L5C 2A4",
    "sg:province":"ON",
    "wof:name":"Michael Kaspard & Son Ins Brkr",
    "wof:placetype":"venue"
},
  "geometry": {"coordinates":[-79.649101,43.559883],"type":"Point"}
}