{
  "type": "Feature",
  "properties": {
    "addr:full":"1861 Island Hwy Campbell River BC V9W 2E9",
    "addr:housenumber":"1861",
    "addr:postcode":"v9w 2e9",
    "addr:street":"Island Hwy",
    "iso:country":"CA",
    "sg:address":"1861 Island Hwy",
    "sg:city":"Campbell River",
    "sg:classifiers":[
        {
            "category":"Banks & Credit Unions",
            "subcategory":"Bank",
            "type":"Services"
        }
    ],
    "sg:phone":"+1 250 286 9779",
    "sg:postcode":"V9W 2E9",
    "sg:province":"BC",
    "sg:tags":[
        "cashing",
        "video",
        "disc",
        "tape",
        "check"
    ],
    "wof:name":"New Video Scene",
    "wof:placetype":"venue"
},
  "geometry": {"coordinates":[-125.269721985,50.0325317383],"type":"Point"}
}