{
  "type": "Feature",
  "properties": {
    "iso:country":"CA",
    "sg:city":"Windermere",
    "sg:classifiers":[
        {
            "category":"Government",
            "subcategory":"Office",
            "type":"Public Place"
        }
    ],
    "sg:phone":"+1 250 341 3388",
    "sg:postcode":"V0B 2L0",
    "sg:province":"BC",
    "sg:tags":[
        "village"
    ],
    "wof:name":"Columbia Valley Emergency",
    "wof:placetype":"venue"
},
  "geometry": {"coordinates":[-116.916816711,50.1659355164],"type":"Point"}
}