{
  "type": "Feature",
  "properties": {
    "iso:country":"CA",
    "sg:city":"Pointe-Claire",
    "sg:classifiers":[
        {
            "category":"Health Services",
            "subcategory":"Doctor",
            "type":"Services"
        }
    ],
    "sg:phone":"+1 514 695 6822",
    "sg:postcode":"H9R 4S3",
    "sg:province":"QC",
    "sg:tags":[
        "physician",
        "surgeon"
    ],
    "wof:name":"Bourdon, Gilles MD",
    "wof:placetype":"venue"
},
  "geometry": {"coordinates":[-73.833199,45.450356],"type":"Point"}
}