{
  "type": "Feature",
  "properties": {
    "iso:country":"CA",
    "sg:address":"90 Av Parkdale",
    "sg:city":"Pointe-Claire",
    "sg:classifiers":[
        {
            "category":"Building & Trades",
            "subcategory":"Electrical",
            "type":"Services"
        }
    ],
    "sg:phone":"+1 514 694 1616",
    "sg:postcode":"H9R 3Y7",
    "sg:province":"QC",
    "sg:tags":[
        "electric",
        "contractor"
    ],
    "wof:name":"Harder-Wessel",
    "wof:placetype":"venue"
},
  "geometry": {"coordinates":[-73.79998,45.456593],"type":"Point"}
}