{
  "type": "Feature",
  "properties": {
    "addr:full":"3915 Rue Saint-Denis Montreal QC H2W 2M4",
    "addr:housenumber":"3915",
    "addr:postcode":"h2w 2m4",
    "addr:street":"Rue Saint-Denis",
    "iso:country":"CA",
    "sg:address":"3915 Rue Saint-Denis",
    "sg:city":"Montreal",
    "sg:classifiers":[
        {
            "category":"Shopping",
            "subcategory":"Clothing, Apparel, & Fashions",
            "type":"Retail Goods"
        }
    ],
    "sg:phone":"+1 514 842 1222",
    "sg:postcode":"H2W 2M4",
    "sg:province":"QC",
    "wof:name":"Boutique Lolita Jaca Inc",
    "wof:placetype":"venue"
},
  "geometry": {"coordinates":[-73.573936,45.520065],"type":"Point"}
}