{
  "type": "Feature",
  "properties": {
    "addr:full":"8920 Rue Ravel Saint-Leonard QC H1P 3C9",
    "addr:housenumber":"8920",
    "addr:postcode":"h1p 3c9",
    "addr:street":"Rue Ravel",
    "iso:country":"CA",
    "sg:address":"8920 Rue Ravel",
    "sg:city":"Saint-Leonard",
    "sg:classifiers":[
        {
            "category":"Home & Garden",
            "subcategory":"Building Materials",
            "type":"Retail Goods"
        }
    ],
    "sg:phone":"+1 514 323 7572",
    "sg:postcode":"H1P 3C9",
    "sg:province":"QC",
    "sg:tags":[
        "door"
    ],
    "wof:name":"Gr Aluminium Renovations",
    "wof:placetype":"venue"
},
  "geometry": {"coordinates":[-73.5982055664,45.6009407043],"type":"Point"}
}