{
  "type": "Feature",
  "properties": {
    "addr:full":"North Vancouver BC V7P 1M6",
    "addr:postcode":"v7p 1m6",
    "iso:country":"CA",
    "sg:city":"North Vancouver",
    "sg:classifiers":[
        {
            "category":"Personal",
            "subcategory":"Beauty Salon",
            "type":"Services"
        }
    ],
    "sg:phone":"+1 604 984 0783",
    "sg:postcode":"V7P 1M6",
    "sg:province":"BC",
    "wof:name":"New Wave Beauty Salon",
    "wof:placetype":"venue"
},
  "geometry": {"coordinates":[-123.095169067,49.3224143982],"type":"Point"}
}