{
  "type": "Feature",
  "properties": {
    "iso:country":"CA",
    "sg:city":"L'Annonciation",
    "sg:classifiers":[
        {
            "category":"Shopping",
            "type":"Retail Goods"
        }
    ],
    "sg:phone":"+1 819 275 2211",
    "sg:postcode":"J0T 1T0",
    "sg:province":"QC",
    "sg:tags":[
        "hearing",
        "equipment",
        "supply",
        "impaired"
    ],
    "wof:name":"Leblanc, Vital",
    "wof:placetype":"venue"
},
  "geometry": {"coordinates":[-74.86842346189999,46.4100570679],"type":"Point"}
}