{
  "type": "Feature",
  "properties": {
    "addr:full":"Richmond BC V6V 1Z1",
    "addr:postcode":"v6v 1z1",
    "iso:country":"CA",
    "sg:city":"Richmond",
    "sg:classifiers":[
        {
            "category":"Professional",
            "subcategory":"Business Services",
            "type":"Services"
        }
    ],
    "sg:phone":"+1 604 207 1049",
    "sg:postcode":"V6V 1Z1",
    "sg:province":"BC",
    "sg:tags":[
        "embroidery"
    ],
    "wof:name":"Prestige Embroidery",
    "wof:placetype":"venue"
},
  "geometry": {"coordinates":[-123.06905399999999,49.172001],"type":"Point"}
}