{
  "type": "Feature",
  "properties": {
    "iso:country":"CA",
    "sg:address":"1284 Ch Saint-Louis",
    "sg:city":"Sillery",
    "sg:classifiers":[
        {
            "category":"Retail",
            "subcategory":"Auto Rental",
            "type":"Services"
        }
    ],
    "sg:phone":"+1 418 527 3061",
    "sg:postcode":"G1S 1E9",
    "sg:province":"QC",
    "sg:tags":[
        "renting",
        "automobile"
    ],
    "wof:name":"Avis Location DE Voitures",
    "wof:placetype":"venue"
},
  "geometry": {"coordinates":[-71.2466583252,46.7892990112],"type":"Point"}
}