{
  "type": "Feature",
  "properties": {
    "addr:full":"6 Dumbarton Blvd Winnipeg MB R3P 2C4",
    "addr:housenumber":"6",
    "addr:postcode":"r3p 2c4",
    "addr:street":"Dumbarton Blvd",
    "iso:country":"CA",
    "sg:address":"6 Dumbarton Blvd",
    "sg:city":"Winnipeg",
    "sg:classifiers":[
        {
            "category":"Organizations",
            "subcategory":"Religious Organization",
            "type":"Services"
        }
    ],
    "sg:phone":"+1 204 895 7544",
    "sg:postcode":"R3P 2C4",
    "sg:province":"MB",
    "wof:name":"Catholic Charismatic Renewal",
    "wof:placetype":"venue"
},
  "geometry": {"coordinates":[-97.223106,49.84977],"type":"Point"}
}