{
  "type": "Feature",
  "properties": {
    "iso:country":"CA",
    "sg:address":"33 Drummond St W # 227",
    "sg:city":"Perth",
    "sg:classifiers":[
        {
            "category":"Health Services",
            "subcategory":"Doctor",
            "type":"Services"
        }
    ],
    "sg:phone":"+1 613 267 7020",
    "sg:postcode":"K7H 2J9",
    "sg:province":"ON",
    "sg:tags":[
        "physician",
        "surgeon"
    ],
    "wof:name":"Anderson, Paul MD",
    "wof:placetype":"venue"
},
  "geometry": {"coordinates":[-76.253112793,44.9052238464],"type":"Point"}
}