{
  "type": "Feature",
  "properties": {
    "addr:full":"350 Marine Dr SE Vancouver BC V5X 2S5",
    "addr:housenumber":"350",
    "addr:postcode":"v5x 2s5",
    "addr:street":"Marine Dr Se",
    "iso:country":"CA",
    "sg:address":"350 Marine Dr SE",
    "sg:city":"Vancouver",
    "sg:classifiers":[
        {
            "category":"Insurance",
            "subcategory":"Insurance Agent",
            "type":"Services"
        }
    ],
    "sg:phone":"+1 604 322 6099",
    "sg:postcode":"V5X 2S5",
    "sg:province":"BC",
    "wof:name":"Sussex Insurance Inc",
    "wof:placetype":"venue"
},
  "geometry": {"coordinates":[-123.099220276,49.2106056213],"type":"Point"}
}