{
  "type": "Feature",
  "properties": {
    "addr:full":"60 Rutland St Warren ON P0H 2N0",
    "addr:housenumber":"60",
    "addr:postcode":"p0h 2n0",
    "addr:street":"Rutland St",
    "iso:country":"CA",
    "sg:address":"60 Rutland St",
    "sg:city":"Warren",
    "sg:classifiers":[
        {
            "category":"Banks & Credit Unions",
            "subcategory":"Bank",
            "type":"Services"
        }
    ],
    "sg:phone":"+1 705 967 2055",
    "sg:postcode":"P0H 2N0",
    "sg:province":"ON",
    "wof:name":"Caisse Populaire",
    "wof:placetype":"venue"
},
  "geometry": {"coordinates":[-80.311249,46.441933],"type":"Point"}
}