{
  "type": "Feature",
  "properties": {
    "addr:full":"1104 18E Rue Quebec QC G1J 1Z1",
    "addr:housenumber":"1104",
    "addr:postcode":"g1j 1z1",
    "addr:street":"18E Rue Quebec",
    "iso:country":"CA",
    "sg:address":"1104 18E Rue",
    "sg:city":"Quebec",
    "sg:classifiers":[
        {
            "category":"Restaurant",
            "type":"Food & Drink"
        }
    ],
    "sg:phone":"+1 418 523 2823",
    "sg:postcode":"G1J 1Z1",
    "sg:province":"QC",
    "wof:name":"Cube A Pizza",
    "wof:placetype":"venue"
},
  "geometry": {"coordinates":[-71.228607,46.834423],"type":"Point"}
}