{
  "type": "Feature",
  "properties": {
    "addr:full":"4495 Tomken Rd Mississauga ON L4W 1J9",
    "addr:housenumber":"4495",
    "addr:postcode":"l4w 1j9",
    "addr:street":"Tomken Rd",
    "iso:country":"CA",
    "sg:address":"4495 Tomken Rd",
    "sg:city":"Mississauga",
    "sg:classifiers":[
        {
            "category":"Arena",
            "subcategory":"Sports Club",
            "type":"Entertainment"
        }
    ],
    "sg:phone":"+1 905 625 1582",
    "sg:postcode":"L4W 1J9",
    "sg:province":"ON",
    "sg:tags":[
        "athletic",
        "fields",
        "stadium",
        "government"
    ],
    "wof:name":"Tomken Twin Arena",
    "wof:placetype":"venue"
},
  "geometry": {"coordinates":[-79.62415300000001,43.622673],"type":"Point"}
}