{
  "type": "Feature",
  "properties": {
    "addr:full":"751 King St W Kitchener ON N2G 1E5",
    "addr:housenumber":"751",
    "addr:postcode":"n2g 1e5",
    "addr:street":"King St W",
    "iso:country":"CA",
    "sg:address":"751 King St W",
    "sg:city":"Kitchener",
    "sg:classifiers":[
        {
            "category":"Shopping",
            "subcategory":"Pharmacy",
            "type":"Retail Goods"
        }
    ],
    "sg:phone":"+1 519 578 9991",
    "sg:postcode":"N2G 1E5",
    "sg:province":"ON",
    "wof:name":"Pharmacy on King",
    "wof:placetype":"venue"
},
  "geometry": {"coordinates":[-80.507294,43.455597],"type":"Point"}
}