{
  "type": "Feature",
  "properties": {
    "addr:full":"18 Rue Brunet Mont-Saint-Hilaire QC J3G 4S6",
    "addr:housenumber":"18",
    "addr:postcode":"j3g 4s6",
    "addr:street":"Rue Brunet",
    "iso:country":"CA",
    "sg:address":"18 Rue Brunet",
    "sg:city":"Mont-Saint-Hilaire",
    "sg:classifiers":[
        {
            "category":"Food & Beverages",
            "subcategory":"Groceries & Convenience Stores",
            "type":"Retail Goods"
        }
    ],
    "sg:phone":"+1 450 464 1117",
    "sg:postcode":"J3G 4S6",
    "sg:province":"QC",
    "wof:name":"Depanneur Du Golf",
    "wof:placetype":"venue"
},
  "geometry": {"coordinates":[-73.184235,45.592957],"type":"Point"}
}