{
  "type": "Feature",
  "properties": {
    "addr:full":"303 Av Dorval Dorval QC H9S 3H6",
    "addr:postcode":"h9s 3h6",
    "addr:street":"303 Av Dorval",
    "iso:country":"CA",
    "sg:address":"303 Av Dorval",
    "sg:city":"Dorval",
    "sg:classifiers":[
        {
            "category":"Insurance",
            "subcategory":"Insurance Agent",
            "type":"Services"
        }
    ],
    "sg:phone":"+1 514 636 6932",
    "sg:postcode":"H9S 3H6",
    "sg:province":"QC",
    "wof:name":"Stephen Bodi & CO",
    "wof:placetype":"venue"
},
  "geometry": {"coordinates":[-73.74057769780001,45.4439277649],"type":"Point"}
}