{
  "type": "Feature",
  "properties": {
    "addr:full":"1041 Great St Prince George BC V2N 2K8",
    "addr:housenumber":"1041",
    "addr:postcode":"v2n 2k8",
    "addr:street":"Great St",
    "iso:country":"CA",
    "sg:address":"1041 Great St",
    "sg:city":"Prince George",
    "sg:classifiers":[
        {
            "category":"Local Transit",
            "type":"Transportation"
        }
    ],
    "sg:phone":"+1 250 563 0011",
    "sg:postcode":"V2N 2K8",
    "sg:province":"BC",
    "sg:tags":[
        "bus",
        "line"
    ],
    "wof:name":"Prince George Transit & Chartr",
    "wof:placetype":"venue"
},
  "geometry": {"coordinates":[-122.740814,53.880894],"type":"Point"}
}