{
  "type": "Feature",
  "properties": {
    "addr:full":"1083 Garrett St Sharbot Lake ON K0H 2P0",
    "addr:housenumber":"1083",
    "addr:postcode":"k0h 2p0",
    "addr:street":"Garrett St",
    "iso:country":"CA",
    "sg:address":"1083 Garrett St",
    "sg:city":"Sharbot Lake",
    "sg:classifiers":[
        {
            "category":"Education",
            "subcategory":"School",
            "type":"Public Place"
        }
    ],
    "sg:phone":"+1 613 279 2103",
    "sg:postcode":"K0H 2P0",
    "sg:province":"ON",
    "wof:name":"Sharbot Lake Public School",
    "wof:placetype":"venue"
},
  "geometry": {"coordinates":[-76.68905639650001,44.7715301514],"type":"Point"}
}