{
  "type": "Feature",
  "properties": {
    "addr:full":"66 Third Ave N Yorkton SK S3N 1C3",
    "addr:housenumber":"66",
    "addr:postcode":"s3n 1c3",
    "addr:street":"Third Ave N",
    "iso:country":"CA",
    "sg:address":"66 Third Ave N",
    "sg:city":"Yorkton",
    "sg:classifiers":[
        {
            "category":"Recreation",
            "type":"Entertainment"
        }
    ],
    "sg:phone":"+1 306 783 5445",
    "sg:postcode":"S3N 1C3",
    "sg:province":"SK",
    "sg:tags":[
        "karate",
        "judo",
        "instr"
    ],
    "wof:name":"Yorkton Karate Club",
    "wof:placetype":"venue"
},
  "geometry": {"coordinates":[-102.46018219,51.2123832703],"type":"Point"}
}