{
  "type": "Feature",
  "properties": {
    "addr:full":"1384 Av Bourgogne Chambly QC J3L 1Y3",
    "addr:housenumber":"1384",
    "addr:postcode":"j3l 1y3",
    "addr:street":"Av Bourgogne",
    "iso:country":"CA",
    "sg:address":"1384 Av Bourgogne",
    "sg:city":"Chambly",
    "sg:classifiers":[
        {
            "category":"Personal",
            "subcategory":"Beauty Salon",
            "type":"Services"
        }
    ],
    "sg:phone":"+1 450 658 6497",
    "sg:postcode":"J3L 1Y3",
    "sg:province":"QC",
    "sg:tags":[
        "barber"
    ],
    "wof:name":"Coiffure Naja",
    "wof:placetype":"venue"
},
  "geometry": {"coordinates":[-73.2967376709,45.4510536194],"type":"Point"}
}