{
  "type": "Feature",
  "properties": {
    "addr:full":"109 Connaught Ave Revelstoke BC V0E 2S0",
    "addr:housenumber":"109",
    "addr:postcode":"v0e 2s0",
    "addr:street":"Connaught Ave",
    "iso:country":"CA",
    "sg:address":"109 Connaught Ave",
    "sg:city":"Revelstoke",
    "sg:classifiers":[
        {
            "category":"Professional",
            "subcategory":"Lawyer & Legal Services",
            "type":"Services"
        }
    ],
    "sg:phone":"+1 250 837 5168",
    "sg:postcode":"V0E 2S0",
    "sg:province":"BC",
    "sg:tags":[
        "attorney"
    ],
    "wof:name":"Lavallee, Bernard",
    "wof:placetype":"venue"
},
  "geometry": {"coordinates":[-118.195930481,50.9996795654],"type":"Point"}
}