{
  "type": "Feature",
  "properties": {
    "addr:full":"760 Lynx Lake Rd Huntsville ON P1H 2J3",
    "addr:housenumber":"760",
    "addr:postcode":"p1h 2j3",
    "addr:street":"Lynx Lake Rd",
    "iso:country":"CA",
    "sg:address":"760 Lynx Lake Rd",
    "sg:city":"Huntsville",
    "sg:classifiers":[
        {
            "category":"Wholesale",
            "subcategory":"Scrap",
            "type":"Manufacturing & Wholesale Goods"
        }
    ],
    "sg:phone":"+1 705 789 0816",
    "sg:postcode":"P1H 2J3",
    "sg:province":"ON",
    "sg:tags":[
        "recycling",
        "center",
        "lumber"
    ],
    "wof:name":"Muskoka Wood Recycling",
    "wof:placetype":"venue"
},
  "geometry": {"coordinates":[-79.204544,45.242199],"type":"Point"}
}