{
  "type": "Feature",
  "properties": {
    "addr:full":"1440 Queen St W Toronto ON M6K 1M2",
    "addr:housenumber":"1440",
    "addr:postcode":"m6k 1m2",
    "addr:street":"Queen St W",
    "iso:country":"CA",
    "sg:address":"1440 Queen St W",
    "sg:city":"Toronto",
    "sg:classifiers":[
        {
            "category":"Cinema",
            "subcategory":"Movie Rental",
            "type":"Entertainment"
        }
    ],
    "sg:phone":"+1 416 516 7871",
    "sg:postcode":"M6K 1M2",
    "sg:province":"ON",
    "sg:tags":[
        "leasing",
        "video",
        "disc",
        "tape"
    ],
    "wof:name":"Top Movies & Games",
    "wof:placetype":"venue"
},
  "geometry": {"coordinates":[-79.435738,43.64093],"type":"Point"}
}