{
  "type": "Feature",
  "properties": {
    "addr:full":"358 Isabey St Saint-Laurent QC H4T 1W1",
    "addr:housenumber":"358",
    "addr:postcode":"h4t 1w1",
    "addr:street":"Isabey St",
    "iso:country":"CA",
    "sg:address":"358 Isabey St",
    "sg:city":"Saint-Laurent",
    "sg:classifiers":[
        {
            "category":"Professional",
            "subcategory":"Business Services",
            "type":"Services"
        }
    ],
    "sg:phone":"+1 514 337 3755",
    "sg:postcode":"H4T 1W1",
    "sg:province":"QC",
    "sg:tags":[
        "mailing",
        "telemarketing",
        "shipping"
    ],
    "wof:name":"Poste Continentale Ltee",
    "wof:placetype":"venue"
},
  "geometry": {"coordinates":[-73.684219,45.492767],"type":"Point"}
}