{
  "type": "Feature",
  "properties": {
    "addr:full":"20383 Langley Bypass Langley BC V3A 5E8",
    "addr:housenumber":"20383",
    "addr:postcode":"v3a 5e8",
    "addr:street":"Langley Bypass",
    "iso:country":"CA",
    "sg:address":"20383 Langley Bypass",
    "sg:city":"Langley",
    "sg:classifiers":[
        {
            "category":"Building & Trades",
            "subcategory":"Equipment Rental",
            "type":"Services"
        }
    ],
    "sg:phone":"+1 604 533 9800",
    "sg:postcode":"V3A 5E8",
    "sg:province":"BC",
    "sg:tags":[
        "leasing"
    ],
    "wof:name":"Auto Canada Lease",
    "wof:placetype":"venue"
},
  "geometry": {"coordinates":[-122.659004211,49.1134147644],"type":"Point"}
}