{
  "type": "Feature",
  "properties": {
    "addr:full":"199 Queens Ave London ON N6A 1J1",
    "addr:housenumber":"199",
    "addr:postcode":"n6a 1j1",
    "addr:street":"Queens Ave",
    "iso:country":"CA",
    "sg:address":"199 Queens Ave",
    "sg:city":"London",
    "sg:classifiers":[
        {
            "category":"Personal",
            "subcategory":"Beauty Salon",
            "type":"Services"
        }
    ],
    "sg:phone":"+1 519 679 0082",
    "sg:postcode":"N6A 1J1",
    "sg:province":"ON",
    "wof:name":"Debut",
    "wof:placetype":"venue"
},
  "geometry": {"coordinates":[-81.2490234375,42.9852027893],"type":"Point"}
}