{
  "type": "Feature",
  "properties": {
    "addr:full":"142 1 St W Carrot River SK S0E 0L0",
    "addr:housenumber":"142 1",
    "addr:postcode":"s0e 0l0",
    "addr:street":"St W Carrot",
    "iso:country":"CA",
    "sg:address":"142 1 St W",
    "sg:city":"Carrot River",
    "sg:classifiers":[
        {
            "category":"Travel",
            "subcategory":"Travel Agent",
            "type":"Entertainment"
        }
    ],
    "sg:phone":"+1 306 768 2497",
    "sg:postcode":"S0E 0L0",
    "sg:province":"SK",
    "sg:tags":[
        "information",
        "tourist"
    ],
    "wof:name":"Visitor Information",
    "wof:placetype":"venue"
},
  "geometry": {"coordinates":[-103.587532,53.28336],"type":"Point"}
}