{
  "type": "Feature",
  "properties": {
    "addr:full":"1380 Rue Saint-Antoine Saint-Hyacinthe QC J2S 3K7",
    "addr:housenumber":"1380",
    "addr:postcode":"j2s 3k7",
    "addr:street":"Rue Saint-Antoine",
    "iso:country":"CA",
    "sg:address":"1380 Rue Saint-Antoine",
    "sg:city":"Saint-Hyacinthe",
    "sg:classifiers":[
        {
            "category":"Professional",
            "subcategory":"Business Services",
            "type":"Services"
        }
    ],
    "sg:phone":"+1 450 773 6631",
    "sg:postcode":"J2S 3K7",
    "sg:province":"QC",
    "sg:tags":[
        "packaging",
        "printer"
    ],
    "wof:name":"Imprimerie Dominion Printing",
    "wof:placetype":"venue"
},
  "geometry": {"coordinates":[-72.944107,45.624638],"type":"Point"}
}