{
  "type": "Feature",
  "properties": {
    "addr:full":"190 Pennywell Rd St. John's NL A1C 2L6",
    "addr:housenumber":"190",
    "addr:postcode":"a1c 2l6",
    "addr:street":"Pennywell Rd",
    "iso:country":"CA",
    "sg:address":"190 Pennywell Rd",
    "sg:city":"St. John's",
    "sg:classifiers":[
        {
            "category":"Education",
            "subcategory":"School",
            "type":"Public Place"
        }
    ],
    "sg:phone":"+1 709 579 4107",
    "sg:postcode":"A1C 2L6",
    "sg:province":"NL",
    "wof:name":"Bishops College",
    "wof:placetype":"venue"
},
  "geometry": {"coordinates":[-52.736504,47.557106],"type":"Point"}
}