{
  "type": "Feature",
  "properties": {
    "addr:full":"1320 Trans Canada Hwy W #40 Kamloops BC V1S 1J2",
    "addr:housenumber":"1320",
    "addr:postcode":"bc v1s 1j2",
    "addr:street":"Trans Canada Hwy W # 40",
    "iso:country":"CA",
    "sg:address":"1320 Trans Canada Hwy W #40",
    "sg:city":"Kamloops",
    "sg:classifiers":[
        {
            "category":"Shopping",
            "subcategory":"Department Store",
            "type":"Retail Goods"
        }
    ],
    "sg:phone":"+1 250 374 6611",
    "sg:postcode":"V1S 1J2",
    "sg:province":"BC",
    "wof:name":"Sears Canada Inc",
    "wof:placetype":"venue"
},
  "geometry": {"coordinates":[-120.36978149399999,50.6555862427],"type":"Point"}
}