{
  "type": "Feature",
  "properties": {
    "iso:country":"CA",
    "sg:address":"245 Av Victoria",
    "sg:city":"Westmount",
    "sg:classifiers":[
        {
            "category":"Professional",
            "subcategory":"Management & Consulting",
            "type":"Services"
        }
    ],
    "sg:phone":"+1 514 931 6399",
    "sg:postcode":"H3Z 2M6",
    "sg:province":"QC",
    "sg:tags":[
        "marketing",
        "consultant"
    ],
    "wof:name":"Greenleaf Group Inc",
    "wof:placetype":"venue"
},
  "geometry": {"coordinates":[-73.59940338129999,45.4772224426],"type":"Point"}
}