{
  "type": "Feature",
  "properties": {
    "addr:full":"178 Front St Trenton ON K8V 4N8",
    "addr:housenumber":"178",
    "addr:postcode":"k8v 4n8",
    "addr:street":"Front St",
    "iso:country":"CA",
    "sg:address":"178 Front St",
    "sg:city":"Trenton",
    "sg:classifiers":[
        {
            "category":"Restaurant",
            "type":"Food & Drink"
        }
    ],
    "sg:phone":"+1 613 392 7051",
    "sg:postcode":"K8V 4N8",
    "sg:province":"ON",
    "wof:name":"Kfc",
    "wof:placetype":"venue"
},
  "geometry": {"coordinates":[-77.5800857544,44.104473114],"type":"Point"}
}