{
  "type": "Feature",
  "properties": {
    "addr:full":"7899 50 Ave Drayton Valley AB T7A 1R9",
    "addr:housenumber":"7899",
    "addr:postcode":"t7a 1r9",
    "addr:street":"50 Ave",
    "iso:country":"CA",
    "sg:address":"7899 50 Ave",
    "sg:city":"Drayton Valley",
    "sg:classifiers":[
        {
            "category":"Restaurant",
            "type":"Food & Drink"
        }
    ],
    "sg:phone":"+1 780 621 1522",
    "sg:postcode":"T7A 1R9",
    "sg:province":"AB",
    "wof:name":"Mc Donald's",
    "wof:placetype":"venue"
},
  "geometry": {"coordinates":[-114.996749878,53.2213401794],"type":"Point"}
}