{
  "type": "Feature",
  "properties": {
    "addr:full":"Grenville QC J0V 1J0",
    "addr:postcode":"j0v 1j0",
    "iso:country":"CA",
    "sg:city":"Grenville",
    "sg:classifiers":[
        {
            "category":"Autos & Motor Vehicles",
            "subcategory":"Automobile Sales",
            "type":"Retail Goods"
        }
    ],
    "sg:phone":"+1 819 242 0115",
    "sg:postcode":"J0V 1J0",
    "sg:province":"QC",
    "sg:tags":[
        "car",
        "dealer"
    ],
    "wof:name":"Kia Grenville Inc",
    "wof:placetype":"venue"
},
  "geometry": {"coordinates":[-74.5913467407,45.6257362366],"type":"Point"}
}