{
  "type": "Feature",
  "properties": {
    "addr:full":"Montague PE C0A 1R0",
    "addr:postcode":"c0a 1r0",
    "iso:country":"CA",
    "sg:city":"Montague",
    "sg:classifiers":[
        {
            "category":"Building & Trades",
            "subcategory":"Electrical",
            "type":"Services"
        }
    ],
    "sg:phone":"+1 902 838 4299",
    "sg:postcode":"C0A 1R0",
    "sg:province":"PE",
    "sg:tags":[
        "electric",
        "contractor"
    ],
    "wof:name":"Fraser Electric",
    "wof:placetype":"venue"
},
  "geometry": {"coordinates":[-62.649719,46.167164],"type":"Point"}
}