{
  "type": "Feature",
  "properties": {
    "addr:full":"317 Kent St Charlottetown PE C1A 1P5",
    "addr:housenumber":"317",
    "addr:postcode":"c1a 1p5",
    "addr:street":"Kent St",
    "iso:country":"CA",
    "sg:address":"317 Kent St",
    "sg:city":"Charlottetown",
    "sg:classifiers":[
        {
            "category":"Farming",
            "subcategory":"Dairy Farm",
            "type":"Manufacturing & Wholesale Goods"
        }
    ],
    "sg:phone":"+1 902 894 7125",
    "sg:postcode":"C1A 1P5",
    "sg:province":"PE",
    "wof:name":"Purity Dairy Ltd",
    "wof:placetype":"venue"
},
  "geometry": {"coordinates":[-63.1208381653,46.2407226562],"type":"Point"}
}