{
  "type": "Feature",
  "properties": {
    "iso:country":"CA",
    "sg:address":"2266 Wilson Ave",
    "sg:city":"Port Coquitlam",
    "sg:classifiers":[
        {
            "category":"Government",
            "subcategory":"Office",
            "type":"Public Place"
        }
    ],
    "sg:phone":"+1 604 777 8700",
    "sg:postcode":"V3C 1Z5",
    "sg:province":"BC",
    "wof:name":"Simon Fraser Health Unit",
    "wof:placetype":"venue"
},
  "geometry": {"coordinates":[-122.781425476,49.2606925964],"type":"Point"}
}