{
  "type": "Feature",
  "properties": {
    "addr:full":"5000 Minoru Blvd Richmond BC V6X 2A9",
    "addr:housenumber":"5000",
    "addr:postcode":"v6x 2a9",
    "addr:street":"Minoru Blvd",
    "iso:country":"CA",
    "sg:address":"5000 Minoru Blvd",
    "sg:city":"Richmond",
    "sg:classifiers":[
        {
            "category":"Home & Garden",
            "subcategory":"Furniture",
            "type":"Retail Goods"
        }
    ],
    "sg:phone":"+1 604 270 4221",
    "sg:postcode":"V6X 2A9",
    "sg:province":"BC",
    "wof:name":"Westcoast's Furniture Ctr",
    "wof:placetype":"venue"
},
  "geometry": {"coordinates":[-123.140427,49.17622],"type":"Point"}
}