{
  "type": "Feature",
  "properties": {
    "addr:full":"1700 10 Ave SW Calgary AB T3C 0J8",
    "addr:housenumber":"1700",
    "addr:postcode":"t3c 0j8",
    "addr:street":"10 Ave Sw",
    "iso:country":"CA",
    "sg:address":"1700 10 Ave SW",
    "sg:city":"Calgary",
    "sg:classifiers":[
        {
            "category":"Retail",
            "subcategory":"Laundry & Dry Cleaning",
            "type":"Services"
        }
    ],
    "sg:phone":"+1 403 229 3323",
    "sg:postcode":"T3C 0J8",
    "sg:province":"AB",
    "sg:tags":[
        "cleaners",
        "rug",
        "carpet"
    ],
    "wof:name":"A Magiclean Cleaning Svc",
    "wof:placetype":"venue"
},
  "geometry": {"coordinates":[-114.09942627,51.0444717407],"type":"Point"}
}