{
  "type": "Feature",
  "properties": {
    "addr:full":"965 105E Av Drummondville QC J2B 4P7",
    "addr:housenumber":"965",
    "addr:postcode":"j2b 4p7",
    "addr:street":"105E Av",
    "iso:country":"CA",
    "sg:address":"965 105E Av",
    "sg:city":"Drummondville",
    "sg:classifiers":[
        {
            "category":"Building & Trades",
            "subcategory":"Electrical",
            "type":"Services"
        }
    ],
    "sg:phone":"+1 819 472 3659",
    "sg:postcode":"J2B 4P7",
    "sg:province":"QC",
    "sg:tags":[
        "electric",
        "contractor"
    ],
    "wof:name":"Proulx, Jacques",
    "wof:placetype":"venue"
},
  "geometry": {"coordinates":[-72.46929900000001,45.860413],"type":"Point"}
}