{
  "type": "Feature",
  "properties": {
    "addr:full":"Saint-Jude QC J0H 1P0",
    "addr:postcode":"j0h 1p0",
    "iso:country":"CA",
    "sg:city":"Saint-Jude",
    "sg:classifiers":[
        {
            "category":"Government",
            "subcategory":"Office",
            "type":"Public Place"
        }
    ],
    "sg:phone":"+1 450 792 3855",
    "sg:postcode":"J0H 1P0",
    "sg:province":"QC",
    "sg:tags":[
        "village"
    ],
    "wof:name":"St-Jude Corp Municipalite",
    "wof:placetype":"venue"
},
  "geometry": {"coordinates":[-73.02523040769999,45.7759132385],"type":"Point"}
}