{
  "type": "Feature",
  "properties": {
    "addr:full":"730 Clarke Rd Coquitlam BC V3J 3Y1",
    "addr:housenumber":"730",
    "addr:postcode":"v3j 3y1",
    "addr:street":"Clarke Rd",
    "iso:country":"CA",
    "sg:address":"730 Clarke Rd",
    "sg:city":"Coquitlam",
    "sg:classifiers":[
        {
            "category":"Travel",
            "subcategory":"Hotels & Motels",
            "type":"Entertainment"
        }
    ],
    "sg:phone":"+1 604 937 7737",
    "sg:postcode":"V3J 3Y1",
    "sg:province":"BC",
    "wof:name":"Coquitlam Sleepy Lodge",
    "wof:placetype":"venue"
},
  "geometry": {"coordinates":[-122.88227081300001,49.2675209045],"type":"Point"}
}