{
  "type": "Feature",
  "properties": {
    "addr:full":"36 Queen Elizabeth Blvd Etobicoke ON M8Z 1L8",
    "addr:housenumber":"36",
    "addr:postcode":"m8z 1l8",
    "addr:street":"Queen Elizabeth Blvd",
    "iso:country":"CA",
    "sg:address":"36 Queen Elizabeth Blvd",
    "sg:city":"Etobicoke",
    "sg:classifiers":[
        {
            "category":"Freight",
            "type":"Transportation"
        }
    ],
    "sg:phone":"+1 416 255 7936",
    "sg:postcode":"M8Z 1L8",
    "sg:province":"ON",
    "sg:tags":[
        "commercial",
        "storage"
    ],
    "wof:name":"Public Storage",
    "wof:placetype":"venue"
},
  "geometry": {"coordinates":[-79.505287,43.622559],"type":"Point"}
}