{
  "type": "Feature",
  "properties": {
    "addr:full":"73 Third Ave Sudbury ON P3B 3P7",
    "addr:housenumber":"73",
    "addr:postcode":"p3b 3p7",
    "addr:street":"Third Ave",
    "iso:country":"CA",
    "sg:address":"73 Third Ave",
    "sg:city":"Sudbury",
    "sg:classifiers":[
        {
            "category":"Organizations",
            "subcategory":"Religious Organization",
            "type":"Services"
        }
    ],
    "sg:phone":"+1 705 566 5405",
    "sg:postcode":"P3B 3P7",
    "sg:province":"ON",
    "sg:tags":[
        "church"
    ],
    "wof:name":"Hillside Presbyterian Church",
    "wof:placetype":"venue"
},
  "geometry": {"coordinates":[-80.93031311039999,46.4920387268],"type":"Point"}
}