{
  "type": "Feature",
  "properties": {
    "addr:full":"417 Main St Selkirk MB R1A 1V2",
    "addr:housenumber":"417",
    "addr:postcode":"r1a 1v2",
    "addr:street":"Main St",
    "iso:country":"CA",
    "sg:address":"417 Main St",
    "sg:city":"Selkirk",
    "sg:classifiers":[
        {
            "category":"Shopping",
            "subcategory":"Bicycles & Sporting Goods",
            "type":"Retail Goods"
        }
    ],
    "sg:phone":"+1 204 482 7552",
    "sg:postcode":"R1A 1V2",
    "sg:province":"MB",
    "wof:name":"Keystone Sporting Goods Ltd",
    "wof:placetype":"venue"
},
  "geometry": {"coordinates":[-96.872215271,50.1455345154],"type":"Point"}
}