{
  "type": "Feature",
  "properties": {
    "iso:country":"CA",
    "sg:address":"3804 50A St",
    "sg:city":"Red Deer",
    "sg:classifiers":[
        {
            "category":"Building & Trades",
            "subcategory":"Construction",
            "type":"Services"
        }
    ],
    "sg:phone":"+1 403 342 1086",
    "sg:postcode":"T4P 1G3",
    "sg:province":"AB",
    "sg:tags":[
        "repairing",
        "remodeling",
        "contractor"
    ],
    "wof:name":"Phil's Home Construction",
    "wof:placetype":"venue"
},
  "geometry": {"coordinates":[-113.785583,52.267941],"type":"Point"}
}