{
  "type": "Feature",
  "properties": {
    "addr:full":"2500 Rue Senkus Lasalle QC H8N 2X9",
    "addr:housenumber":"2500",
    "addr:postcode":"h8n 2x9",
    "addr:street":"Rue Senkus",
    "iso:country":"CA",
    "sg:address":"2500 Rue Senkus",
    "sg:city":"Lasalle",
    "sg:classifiers":[
        {
            "category":"Shopping",
            "type":"Retail Goods"
        }
    ],
    "sg:phone":"+1 514 366 9600",
    "sg:postcode":"H8N 2X9",
    "sg:province":"QC",
    "sg:tags":[
        "equipment",
        "telephone",
        "supply"
    ],
    "wof:name":"Groupe Communications Cds",
    "wof:placetype":"venue"
},
  "geometry": {"coordinates":[-73.621872,45.447319],"type":"Point"}
}