{
  "type": "Feature",
  "properties": {
    "addr:full":"237 Green St Flin Flon MB R8A 0G8",
    "addr:housenumber":"237",
    "addr:postcode":"r8a 0g8",
    "addr:street":"Green St",
    "iso:country":"CA",
    "sg:address":"237 Green St",
    "sg:city":"Flin Flon",
    "sg:classifiers":[
        {
            "category":"Organizations",
            "subcategory":"Religious Organization",
            "type":"Services"
        }
    ],
    "sg:phone":"+1 204 687 8498",
    "sg:postcode":"R8A 0G8",
    "sg:province":"MB",
    "sg:tags":[
        "church"
    ],
    "wof:name":"Alliance Church",
    "wof:placetype":"venue"
},
  "geometry": {"coordinates":[-101.850891,54.77129],"type":"Point"}
}