{
  "type": "Feature",
  "properties": {
    "iso:country":"CA",
    "sg:city":"Fort St James",
    "sg:classifiers":[
        {
            "category":"Manufacturing",
            "subcategory":"Lumber",
            "type":"Manufacturing & Wholesale Goods"
        }
    ],
    "sg:phone":"+1 250 996 8344",
    "sg:postcode":"V0J 1P0",
    "sg:province":"BC",
    "sg:tags":[
        "company",
        "logging"
    ],
    "wof:name":"Ubleis Logging Ltd",
    "wof:placetype":"venue"
},
  "geometry": {"coordinates":[-124.249412537,54.4417266846],"type":"Point"}
}