{
  "type": "Feature",
  "properties": {
    "addr:full":"6549 Monterey Rd Prince George BC V2K 4E1",
    "addr:housenumber":"6549",
    "addr:postcode":"v2k 4e1",
    "addr:street":"Monterey Rd",
    "iso:country":"CA",
    "sg:address":"6549 Monterey Rd",
    "sg:city":"Prince George",
    "sg:classifiers":[
        {
            "category":"Building & Trades",
            "subcategory":"Construction",
            "type":"Services"
        }
    ],
    "sg:phone":"+1 250 962 6437",
    "sg:postcode":"V2K 4E1",
    "sg:province":"BC",
    "sg:tags":[
        "general",
        "contractor"
    ],
    "wof:name":"Steve's Excavating",
    "wof:placetype":"venue"
},
  "geometry": {"coordinates":[-122.76226800000001,53.989292],"type":"Point"}
}