{
  "type": "Feature",
  "properties": {
    "iso:country":"CA",
    "sg:address":"4235 Gateway Blvd NW",
    "sg:city":"Edmonton",
    "sg:classifiers":[
        {
            "category":"Travel",
            "subcategory":"Hotels & Motels",
            "type":"Entertainment"
        }
    ],
    "sg:phone":"+1 780 438 1222",
    "sg:postcode":"T6J 5H2",
    "sg:province":"AB",
    "wof:name":"Holiday Inn",
    "wof:placetype":"venue"
},
  "geometry": {"coordinates":[-113.49190521200001,53.4780921936],"type":"Point"}
}