{
  "type": "Feature",
  "properties": {
    "addr:full":"80 London Rd W Guelph ON N1H 2B7",
    "addr:housenumber":"80",
    "addr:postcode":"n1h 2b7",
    "addr:street":"London Rd W",
    "iso:country":"CA",
    "sg:address":"80 London Rd W",
    "sg:city":"Guelph",
    "sg:classifiers":[
        {
            "category":"Travel",
            "subcategory":"Hotels & Motels",
            "type":"Entertainment"
        }
    ],
    "sg:phone":"+1 519 824 6874",
    "sg:postcode":"N1H 2B7",
    "sg:province":"ON",
    "sg:tags":[
        "breakfast",
        "accommodation",
        "bed"
    ],
    "wof:name":"London House Bed & Breakfast",
    "wof:placetype":"venue"
},
  "geometry": {"coordinates":[-80.259377,43.548145],"type":"Point"}
}