{
  "type": "Feature",
  "properties": {
    "iso:country":"CA",
    "sg:city":"Toronto",
    "sg:classifiers":[
        {
            "category":"Social Services",
            "subcategory":"Job Training",
            "type":"Services"
        }
    ],
    "sg:phone":"+1 416 921 1800",
    "sg:postcode":"M6G 1A5",
    "sg:province":"ON",
    "sg:tags":[
        "employment"
    ],
    "wof:name":"Acces",
    "wof:placetype":"venue"
},
  "geometry": {"coordinates":[-79.4093551636,43.656036377],"type":"Point"}
}