{
  "type": "Feature",
  "properties": {
    "iso:country":"CA",
    "sg:address":"4040 Boul Le Corbusier",
    "sg:city":"Laval",
    "sg:classifiers":[
        {
            "category":"Professional",
            "subcategory":"Lawyer & Legal Services",
            "type":"Services"
        }
    ],
    "sg:phone":"+1 450 963 4151",
    "sg:postcode":"H7L 5R2",
    "sg:province":"QC",
    "sg:tags":[
        "attorney"
    ],
    "wof:name":"Albert, Christian",
    "wof:placetype":"venue"
},
  "geometry": {"coordinates":[-73.76099395750001,45.5930557251],"type":"Point"}
}