{
  "type": "Feature",
  "properties": {
    "addr:full":"22628 Richmond St London ON N5X 4B2",
    "addr:housenumber":"22628",
    "addr:postcode":"n5x 4b2",
    "addr:street":"Richmond St",
    "iso:country":"CA",
    "sg:address":"22628 Richmond St",
    "sg:city":"London",
    "sg:classifiers":[
        {
            "category":"Building & Trades",
            "subcategory":"Construction",
            "type":"Services"
        }
    ],
    "sg:phone":"+1 519 666 0721",
    "sg:postcode":"N5X 4B2",
    "sg:province":"ON",
    "sg:tags":[
        "contractor"
    ],
    "wof:name":"Pittao Homes Inc",
    "wof:placetype":"venue"
},
  "geometry": {"coordinates":[-81.2918624878,43.0443916321],"type":"Point"}
}