{
  "type": "Feature",
  "properties": {
    "iso:country":"CA",
    "sg:address":"30 4E Av O",
    "sg:city":"LA Sarre",
    "sg:classifiers":[
        {
            "category":"Health Services",
            "subcategory":"Nursing And Care Facility",
            "type":"Services"
        }
    ],
    "sg:phone":"+1 819 333 6121",
    "sg:postcode":"J9Z 1J3",
    "sg:province":"QC",
    "sg:tags":[
        "home",
        "retirement",
        "community"
    ],
    "wof:name":"Residence Andrea",
    "wof:placetype":"venue"
},
  "geometry": {"coordinates":[-79.2038345337,48.8066177368],"type":"Point"}
}