{
  "type": "Feature",
  "properties": {
    "addr:full":"Schomberg ON L0G 1T0",
    "addr:postcode":"l0g 1t0",
    "iso:country":"CA",
    "sg:city":"Schomberg",
    "sg:classifiers":[
        {
            "category":"Wholesale",
            "subcategory":"Construction Materials",
            "type":"Manufacturing & Wholesale Goods"
        }
    ],
    "sg:phone":"+1 905 859 5892",
    "sg:postcode":"L0G 1T0",
    "sg:province":"ON",
    "sg:tags":[
        "fence"
    ],
    "wof:name":"Noble Fence",
    "wof:placetype":"venue"
},
  "geometry": {"coordinates":[-79.6841049194,44.0028152466],"type":"Point"}
}