{
  "type": "Feature",
  "properties": {
    "addr:full":"53 Sheffield St North York ON M6M 3E5",
    "addr:housenumber":"53",
    "addr:postcode":"m6m 3e5",
    "addr:street":"Sheffield St",
    "iso:country":"CA",
    "sg:address":"53 Sheffield St",
    "sg:city":"North York",
    "sg:classifiers":[
        {
            "category":"Wholesale",
            "subcategory":"Medical Equipment & Supplies",
            "type":"Manufacturing & Wholesale Goods"
        }
    ],
    "sg:phone":"+1 416 240 1950",
    "sg:postcode":"M6M 3E5",
    "sg:province":"ON",
    "sg:tags":[
        "microscope",
        "electronic"
    ],
    "wof:name":"Electronic Surplus Industries",
    "wof:placetype":"venue"
},
  "geometry": {"coordinates":[-79.470535,43.705505],"type":"Point"}
}