{
  "type": "Feature",
  "properties": {
    "iso:country":"CA",
    "sg:address":"265 Enfield Pl",
    "sg:city":"Mississauga",
    "sg:classifiers":[
        {
            "category":"Real Estate",
            "subcategory":"Real Estate Agent",
            "type":"Services"
        }
    ],
    "sg:phone":"+1 905 270 8852",
    "sg:postcode":"L5B 3Y7",
    "sg:province":"ON",
    "sg:tags":[
        "management"
    ],
    "wof:name":"Enfield Place Retail",
    "wof:placetype":"venue"
},
  "geometry": {"coordinates":[-79.6352386475,43.5916748047],"type":"Point"}
}