{
  "type": "Feature",
  "properties": {
    "addr:full":"28 Ch DE LA Peche Val-Des-Monts QC J8N 4A6",
    "addr:housenumber":"28",
    "addr:postcode":"j8n 4a6",
    "addr:street":"Ch De La Peche",
    "iso:country":"CA",
    "sg:address":"28 Ch DE LA Peche",
    "sg:city":"Val-Des-Monts",
    "sg:classifiers":[
        {
            "category":"Government",
            "subcategory":"Office",
            "type":"Public Place"
        }
    ],
    "sg:phone":"+1 819 457 4086",
    "sg:postcode":"J8N 4A6",
    "sg:province":"QC",
    "sg:tags":[
        "village"
    ],
    "wof:name":"Poste DE Transbordement",
    "wof:placetype":"venue"
},
  "geometry": {"coordinates":[-75.81442300000001,45.628819],"type":"Point"}
}