{
  "type": "Feature",
  "properties": {
    "iso:country":"CA",
    "sg:city":"Montreal-Nord",
    "sg:classifiers":[
        {
            "category":"Professional",
            "subcategory":"Lawyer & Legal Services",
            "type":"Services"
        }
    ],
    "sg:phone":"+1 514 955 0691",
    "sg:postcode":"H1G 2Z8",
    "sg:province":"QC",
    "sg:tags":[
        "attorney"
    ],
    "wof:name":"Bellan, Peter J",
    "wof:placetype":"venue"
},
  "geometry": {"coordinates":[-73.625275,45.599812],"type":"Point"}
}