{
  "type": "Feature",
  "properties": {
    "addr:full":"Toronto ON M5H 3L5",
    "addr:postcode":"m5h 3l5",
    "iso:country":"CA",
    "sg:city":"Toronto",
    "sg:classifiers":[
        {
            "category":"Professional",
            "subcategory":"Advertising",
            "type":"Services"
        }
    ],
    "sg:phone":"+1 416 703 4500",
    "sg:postcode":"M5H 3L5",
    "sg:province":"ON",
    "sg:tags":[
        "counselor"
    ],
    "wof:name":"Tmc North America Ltd",
    "wof:placetype":"venue"
},
  "geometry": {"coordinates":[-79.38427734379999,43.6489868164],"type":"Point"}
}