{
  "type": "Feature",
  "properties": {
    "addr:full":"542 Rue Pierre-Laviolette Nicolet QC J3T 1J3",
    "addr:housenumber":"542",
    "addr:postcode":"j3t 1j3",
    "addr:street":"Rue Pierre-Laviolette",
    "iso:country":"CA",
    "sg:address":"542 Rue Pierre-Laviolette",
    "sg:city":"Nicolet",
    "sg:classifiers":[
        {
            "category":"Building & Trades",
            "subcategory":"Construction",
            "type":"Services"
        }
    ],
    "sg:phone":"+1 819 293 2202",
    "sg:postcode":"J3T 1J3",
    "sg:province":"QC",
    "sg:tags":[
        "general",
        "contractor"
    ],
    "wof:name":"Contraction Leon Beliveau",
    "wof:placetype":"venue"
},
  "geometry": {"coordinates":[-72.60502624510001,46.2295265198],"type":"Point"}
}