{
  "type": "Feature",
  "properties": {
    "addr:full":"2754 32 St NE Calgary AB T1Y 6J7",
    "addr:housenumber":"2754",
    "addr:postcode":"t1y 6j7",
    "addr:street":"32 St Ne",
    "iso:country":"CA",
    "sg:address":"2754 32 St NE",
    "sg:city":"Calgary",
    "sg:classifiers":[
        {
            "category":"Professional",
            "subcategory":"Business Services",
            "type":"Services"
        }
    ],
    "sg:phone":"+1 403 291 9696",
    "sg:postcode":"T1Y 6J7",
    "sg:province":"AB",
    "sg:tags":[
        "license"
    ],
    "wof:name":"Registry Unlimited",
    "wof:placetype":"venue"
},
  "geometry": {"coordinates":[-113.98840300000001,51.078499],"type":"Point"}
}