{
  "type": "Feature",
  "properties": {
    "addr:full":"381 Dalhousie St Ottawa ON K1N 9L3",
    "addr:housenumber":"381",
    "addr:postcode":"k1n 9l3",
    "addr:street":"Dalhousie St",
    "iso:country":"CA",
    "sg:address":"381 Dalhousie St",
    "sg:city":"Ottawa",
    "sg:classifiers":[
        {
            "category":"Shopping",
            "subcategory":"Clothing, Apparel, & Fashions",
            "type":"Retail Goods"
        }
    ],
    "sg:phone":"+1 613 241 3333",
    "sg:postcode":"K1N 9L3",
    "sg:province":"ON",
    "sg:tags":[
        "hair",
        "supply"
    ],
    "wof:name":"Tropics Boutique",
    "wof:placetype":"venue"
},
  "geometry": {"coordinates":[-75.6898269653,45.4275054932],"type":"Point"}
}