{
  "type": "Feature",
  "properties": {
    "iso:country":"CA",
    "sg:address":"1301 Rue Gay-Lussac",
    "sg:city":"Boucherville",
    "sg:classifiers":[
        {
            "category":"Wholesale",
            "subcategory":"Groceries",
            "type":"Manufacturing & Wholesale Goods"
        }
    ],
    "sg:phone":"+1 450 449 4171",
    "sg:postcode":"J4B 7K1",
    "sg:province":"QC",
    "sg:tags":[
        "food",
        "broker"
    ],
    "wof:name":"Clark Drouin Lefebvre Inc",
    "wof:placetype":"venue"
},
  "geometry": {"coordinates":[-73.4297866821,45.5716247559],"type":"Point"}
}