{
  "type": "Feature",
  "properties": {
    "addr:full":"70 King William St # 73 Huntsville ON P1H 2A5",
    "addr:housenumber":"70",
    "addr:postcode":"p1h 2a5",
    "addr:street":"King William St # 73",
    "iso:country":"CA",
    "sg:address":"70 King William St # 73",
    "sg:city":"Huntsville",
    "sg:classifiers":[
        {
            "category":"Real Estate",
            "subcategory":"Real Estate Operator",
            "type":"Services"
        }
    ],
    "sg:phone":"+1 705 789 3889",
    "sg:postcode":"P1H 2A5",
    "sg:province":"ON",
    "sg:tags":[
        "mall",
        "shopping",
        "center"
    ],
    "wof:name":"Huntsville Place Mall",
    "wof:placetype":"venue"
},
  "geometry": {"coordinates":[-79.206161499,45.3339080811],"type":"Point"}
}