{
  "type": "Feature",
  "properties": {
    "iso:country":"CA",
    "sg:address":"244 Margaret Ave",
    "sg:city":"Kitchener",
    "sg:classifiers":[
        {
            "category":"Retail",
            "subcategory":"Auto Repair",
            "type":"Services"
        }
    ],
    "sg:phone":"+1 519 744 2831",
    "sg:postcode":"N2H 4J5",
    "sg:province":"ON",
    "sg:tags":[
        "repairing",
        "automobile"
    ],
    "wof:name":"Ron Snyder's Svc",
    "wof:placetype":"venue"
},
  "geometry": {"coordinates":[-80.4938735962,43.4629707336],"type":"Point"}
}