{
  "type": "Feature",
  "properties": {
    "addr:full":"6777 Cantelon Dr Windsor ON N8T 3C2",
    "addr:housenumber":"6777",
    "addr:postcode":"n8t 3c2",
    "addr:street":"Cantelon Dr",
    "iso:country":"CA",
    "sg:address":"6777 Cantelon Dr",
    "sg:city":"Windsor",
    "sg:classifiers":[
        {
            "category":"Wholesale",
            "subcategory":"Electrical",
            "type":"Manufacturing & Wholesale Goods"
        }
    ],
    "sg:phone":"+1 519 948 5595",
    "sg:postcode":"N8T 3C2",
    "sg:province":"ON",
    "sg:tags":[
        "control",
        "security",
        "burglar",
        "alarm",
        "system"
    ],
    "wof:name":"A Unique Communications Inc",
    "wof:placetype":"venue"
},
  "geometry": {"coordinates":[-82.9375,42.3022155762],"type":"Point"}
}