{
  "type": "Feature",
  "properties": {
    "iso:country":"CA",
    "sg:address":"1784 Mathers Ave",
    "sg:city":"Winnipeg",
    "sg:classifiers":[
        {
            "category":"Manufacturing",
            "subcategory":"Signs",
            "type":"Manufacturing & Wholesale Goods"
        }
    ],
    "sg:phone":"+1 204 489 9353",
    "sg:postcode":"R3N 0N6",
    "sg:province":"MB",
    "wof:name":"Grenville Services Ltd",
    "wof:placetype":"venue"
},
  "geometry": {"coordinates":[-97.20050048829999,49.853477478],"type":"Point"}
}