{
  "type": "Feature",
  "properties": {
    "iso:country":"CA",
    "sg:address":"71 Reeve Dr",
    "sg:city":"Markham",
    "sg:classifiers":[
        {
            "category":"Wholesale",
            "subcategory":"Furniture",
            "type":"Manufacturing & Wholesale Goods"
        }
    ],
    "sg:phone":"+1 905 781 7051",
    "sg:postcode":"L3P 6C4",
    "sg:province":"ON",
    "sg:tags":[
        "machine",
        "shredding",
        "paper"
    ],
    "wof:name":"David Laws & Assoc Ltd",
    "wof:placetype":"venue"
},
  "geometry": {"coordinates":[-79.255577,43.87236],"type":"Point"}
}