{
  "type": "Feature",
  "properties": {
    "iso:country":"CA",
    "sg:address":"291 Route 160",
    "sg:city":"Allardville",
    "sg:classifiers":[
        {
            "category":"Banks & Credit Unions",
            "subcategory":"Bank",
            "type":"Services"
        }
    ],
    "sg:phone":"+1 506 725 2959",
    "sg:postcode":"E8L 1J1",
    "sg:province":"NB",
    "wof:name":"Caisse Populaire Chaleur Ltee",
    "wof:placetype":"venue"
},
  "geometry": {"coordinates":[-65.49286651609999,47.474822998],"type":"Point"}
}