{
  "type": "Feature",
  "properties": {
    "addr:full":"186 Railway St Nipigon ON P0T 2J0",
    "addr:housenumber":"186",
    "addr:postcode":"p0t 2j0",
    "addr:street":"Railway St",
    "iso:country":"CA",
    "sg:address":"186 Railway St",
    "sg:city":"Nipigon",
    "sg:classifiers":[
        {
            "category":"Home & Garden",
            "subcategory":"Building Materials",
            "type":"Retail Goods"
        }
    ],
    "sg:phone":"+1 807 887 2339",
    "sg:postcode":"P0T 2J0",
    "sg:province":"ON",
    "sg:tags":[
        "glass",
        "window",
        "plate"
    ],
    "wof:name":"Gordie's Auto Glass",
    "wof:placetype":"venue"
},
  "geometry": {"coordinates":[-88.2589263916,49.0166358948],"type":"Point"}
}