{
  "type": "Feature",
  "properties": {
    "iso:country":"CA",
    "sg:address":"4820 49 St",
    "sg:city":"Rocky Mountain House",
    "sg:classifiers":[
        {
            "category":"Health Services",
            "subcategory":"Chiropractor",
            "type":"Services"
        }
    ],
    "sg:phone":"+1 403 845 3536",
    "sg:postcode":"T4T 1C2",
    "sg:province":"AB",
    "wof:name":"Gehrke & Gehrke",
    "wof:placetype":"venue"
},
  "geometry": {"coordinates":[-114.917945862,52.3716506958],"type":"Point"}
}