{
  "type": "Feature",
  "properties": {
    "iso:country":"CA",
    "sg:address":"1801 Walker Rd",
    "sg:city":"Windsor",
    "sg:classifiers":[
        {
            "category":"Shopping",
            "subcategory":"Musical Instruments",
            "type":"Retail Goods"
        }
    ],
    "sg:phone":"+1 519 252 3442",
    "sg:postcode":"N8W 3P3",
    "sg:province":"ON",
    "wof:name":"Long & Mc Quade",
    "wof:placetype":"venue"
},
  "geometry": {"coordinates":[-82.99604,42.304466],"type":"Point"}
}