{
  "type": "Feature",
  "properties": {
    "iso:country":"CA",
    "sg:address":"6851 West Coast Rd",
    "sg:city":"Sooke",
    "sg:classifiers":[
        {
            "category":"Organizations",
            "subcategory":"Religious Organization",
            "type":"Services"
        }
    ],
    "sg:phone":"+1 250 642 4822",
    "sg:postcode":"V0S 1N0",
    "sg:province":"BC",
    "sg:tags":[
        "church"
    ],
    "wof:name":"Sooke Pentecostal Church",
    "wof:placetype":"venue"
},
  "geometry": {"coordinates":[-123.728248596,48.370388031],"type":"Point"}
}