{
  "type": "Feature",
  "properties": {
    "addr:full":"767 Duke St Cambridge ON N3H 3T7",
    "addr:housenumber":"767",
    "addr:postcode":"n3h 3t7",
    "addr:street":"Duke St",
    "iso:country":"CA",
    "sg:address":"767 Duke St",
    "sg:city":"Cambridge",
    "sg:classifiers":[
        {
            "category":"Banks & Credit Unions",
            "subcategory":"Investment Brokerage",
            "type":"Services"
        }
    ],
    "sg:phone":"+1 519 653 6621",
    "sg:postcode":"N3H 3T7",
    "sg:province":"ON",
    "sg:tags":[
        "funds",
        "mutual"
    ],
    "wof:name":"Strome, Grant H",
    "wof:placetype":"venue"
},
  "geometry": {"coordinates":[-80.356583,43.396374],"type":"Point"}
}