{
  "type": "Feature",
  "properties": {
    "addr:full":"106 Main St Dysart SK S0G 1H0",
    "addr:housenumber":"106",
    "addr:postcode":"s0g 1h0",
    "addr:street":"Main St",
    "iso:country":"CA",
    "sg:address":"106 Main St",
    "sg:city":"Dysart",
    "sg:classifiers":[
        {
            "category":"Bars & Pubs",
            "type":"Food & Drink"
        }
    ],
    "sg:phone":"+1 306 432 2134",
    "sg:postcode":"S0G 1H0",
    "sg:province":"SK",
    "sg:tags":[
        "club",
        "night"
    ],
    "wof:name":"T-N-T Tavern",
    "wof:placetype":"venue"
},
  "geometry": {"coordinates":[-104.030846,50.944885],"type":"Point"}
}