{
  "type": "Feature",
  "properties": {
    "iso:country":"CA",
    "sg:address":"3833 Montague St",
    "sg:city":"Regina",
    "sg:classifiers":[
        {
            "category":"Organizations",
            "subcategory":"Religious Organization",
            "type":"Services"
        }
    ],
    "sg:phone":"+1 306 586 8718",
    "sg:postcode":"S4S 3J6",
    "sg:province":"SK",
    "sg:tags":[
        "church"
    ],
    "wof:name":"Peace Mennonite Church",
    "wof:placetype":"venue"
},
  "geometry": {"coordinates":[-104.629463196,50.4181289673],"type":"Point"}
}