{
  "type": "Feature",
  "properties": {
    "addr:full":"3122 Gibbins Rd Duncan BC V9L 1G2",
    "addr:housenumber":"3122",
    "addr:postcode":"v9l 1g2",
    "addr:street":"Gibbins Rd",
    "iso:country":"CA",
    "sg:address":"3122 Gibbins Rd",
    "sg:city":"Duncan",
    "sg:classifiers":[
        {
            "category":"Health Services",
            "subcategory":"Nursing And Care Facility",
            "type":"Services"
        }
    ],
    "sg:phone":"+1 250 701 4242",
    "sg:postcode":"V9L 1G2",
    "sg:province":"BC",
    "sg:tags":[
        "hospice"
    ],
    "wof:name":"Cowichan Valley Hospice",
    "wof:placetype":"venue"
},
  "geometry": {"coordinates":[-123.707382,48.779095],"type":"Point"}
}