{
  "type": "Feature",
  "properties": {
    "addr:full":"12 Rue Sainte-Therese Saint-Timothee QC J6S 4S1",
    "addr:housenumber":"12",
    "addr:postcode":"j6s 4s1",
    "addr:street":"Rue Sainte-Therese Saint-Timothee",
    "iso:country":"CA",
    "sg:address":"12 Rue Sainte-Therese",
    "sg:city":"Saint-Timothee",
    "sg:classifiers":[
        {
            "category":"Building & Trades",
            "subcategory":"Construction",
            "type":"Services"
        }
    ],
    "sg:phone":"+1 450 371 6063",
    "sg:postcode":"J6S 4S1",
    "sg:province":"QC",
    "sg:tags":[
        "builder",
        "stair",
        "railing"
    ],
    "wof:name":"L R Maheu Construction Inc",
    "wof:placetype":"venue"
},
  "geometry": {"coordinates":[-74.0804367065,45.2699050903],"type":"Point"}
}