{
  "type": "Feature",
  "properties": {
    "iso:country":"CA",
    "sg:address":"394 Front St",
    "sg:city":"Belleville",
    "sg:classifiers":[
        {
            "category":"Restaurant",
            "type":"Food & Drink"
        }
    ],
    "sg:phone":"+1 613 961 8507",
    "sg:postcode":"K8N 2Z8",
    "sg:province":"ON",
    "sg:tags":[
        "baker"
    ],
    "wof:name":"Bren's Bakeshop & Cafe",
    "wof:placetype":"venue"
},
  "geometry": {"coordinates":[-77.38600158689999,44.1676445007],"type":"Point"}
}