{
  "type": "Feature",
  "properties": {
    "addr:full":"67 Copper Lake Rd Goshen NS B0H 1M0",
    "addr:housenumber":"67",
    "addr:postcode":"b0h 1m0",
    "addr:street":"Copper Lake Rd",
    "iso:country":"CA",
    "sg:address":"67 Copper Lake Rd",
    "sg:city":"Goshen",
    "sg:classifiers":[
        {
            "category":"Organizations",
            "subcategory":"Religious Organization",
            "type":"Services"
        }
    ],
    "sg:phone":"+1 902 783 2320",
    "sg:postcode":"B0H 1M0",
    "sg:province":"NS",
    "sg:tags":[
        "church"
    ],
    "wof:name":"United Church Manse",
    "wof:placetype":"venue"
},
  "geometry": {"coordinates":[-61.973682,45.376469],"type":"Point"}
}