{
  "type": "Feature",
  "properties": {
    "addr:full":"Iqaluit NU X0A 0H0",
    "addr:postcode":"x0a 0h0",
    "iso:country":"CA",
    "sg:city":"Iqaluit",
    "sg:classifiers":[
        {
            "category":"Travel",
            "subcategory":"Travel Agent",
            "type":"Entertainment"
        }
    ],
    "sg:phone":"+1 867 979 8686",
    "sg:postcode":"X0A 0H0",
    "sg:province":"NU",
    "sg:tags":[
        "agency",
        "bureau"
    ],
    "wof:name":"Top of the World",
    "wof:placetype":"venue"
},
  "geometry": {"coordinates":[-68.51902,63.751469],"type":"Point"}
}