{
  "type": "Feature",
  "properties": {
    "addr:full":"725 Av Gagnon Sainte-Marie QC G6E 1R7",
    "addr:housenumber":"725",
    "addr:postcode":"g6e 1r7",
    "addr:street":"Av Gagnon",
    "iso:country":"CA",
    "sg:address":"725 Av Gagnon",
    "sg:city":"Sainte-Marie",
    "sg:classifiers":[
        {
            "category":"Utilities",
            "subcategory":"Fuel Oil & Lpg",
            "type":"Services"
        }
    ],
    "sg:phone":"+1 418 387 3675",
    "sg:postcode":"G6E 1R7",
    "sg:province":"QC",
    "wof:name":"J C Lagrange Distribution Inc",
    "wof:placetype":"venue"
},
  "geometry": {"coordinates":[-71.006218,46.435604],"type":"Point"}
}