{
  "type": "Feature",
  "properties": {
    "addr:full":"4430 Rue Beausejour Saint-Hubert QC J3Y 6H5",
    "addr:housenumber":"4430",
    "addr:postcode":"j3y 6h5",
    "addr:street":"Rue Beausejour",
    "iso:country":"CA",
    "sg:address":"4430 Rue Beausejour",
    "sg:city":"Saint-Hubert",
    "sg:classifiers":[
        {
            "category":"Building & Trades",
            "subcategory":"Construction",
            "type":"Services"
        }
    ],
    "sg:phone":"+1 450 445 2456",
    "sg:postcode":"J3Y 6H5",
    "sg:province":"QC",
    "sg:tags":[
        "resurfacing",
        "laying",
        "refinishing",
        "floor"
    ],
    "wof:name":"Plancher D Poulin",
    "wof:placetype":"venue"
},
  "geometry": {"coordinates":[-73.42132599999999,45.477001],"type":"Point"}
}