{
  "type": "Feature",
  "properties": {
    "addr:full":"1357 Rue Saint-Faustin Saint-Faustin-Lac-Carre QC J0T 1J3",
    "addr:housenumber":"1357",
    "addr:postcode":"j0t 1j3",
    "addr:street":"Rue Saint-Faustin",
    "iso:country":"CA",
    "sg:address":"1357 Rue Saint-Faustin",
    "sg:city":"Saint-Faustin-Lac-Carre",
    "sg:classifiers":[
        {
            "category":"Manufacturing",
            "subcategory":"Lumber",
            "type":"Manufacturing & Wholesale Goods"
        }
    ],
    "sg:phone":"+1 819 688 2101",
    "sg:postcode":"J0T 1J3",
    "sg:province":"QC",
    "sg:tags":[
        "syrup",
        "maple",
        "sugar"
    ],
    "wof:name":"Cabane A Sucre Millette",
    "wof:placetype":"venue"
},
  "geometry": {"coordinates":[-74.474548,46.115612],"type":"Point"}
}