{
  "type": "Feature",
  "properties": {
    "addr:full":"28 Munham Gate Scarborough ON M1P 2B4",
    "addr:housenumber":"28",
    "addr:postcode":"m1p 2b4",
    "addr:street":"Munham Gate",
    "iso:country":"CA",
    "sg:address":"28 Munham Gate",
    "sg:city":"Scarborough",
    "sg:classifiers":[
        {
            "category":"Building & Trades",
            "subcategory":"Plumbing",
            "type":"Services"
        }
    ],
    "sg:phone":"+1 416 752 0161",
    "sg:postcode":"M1P 2B4",
    "sg:province":"ON",
    "sg:tags":[
        "sheet",
        "work",
        "metal",
        "contractor"
    ],
    "wof:name":"Precision Sheet Metal",
    "wof:placetype":"venue"
},
  "geometry": {"coordinates":[-79.2777938843,43.7596664429],"type":"Point"}
}