{
  "type": "Feature",
  "properties": {
    "addr:full":"140 Midwest Rd #19 Scarborough ON M1P 3B3",
    "addr:housenumber":"140",
    "addr:postcode":"m1p 3b3",
    "addr:street":"Midwest Rd # 19",
    "iso:country":"CA",
    "sg:address":"140 Midwest Rd #19",
    "sg:city":"Scarborough",
    "sg:classifiers":[
        {
            "category":"Autos & Motor Vehicles",
            "subcategory":"Auto Supplies",
            "type":"Retail Goods"
        }
    ],
    "sg:phone":"+1 416 759 4471",
    "sg:postcode":"M1P 3B3",
    "sg:province":"ON",
    "sg:tags":[
        "automobile",
        "parts"
    ],
    "wof:name":"Track & Trend",
    "wof:placetype":"venue"
},
  "geometry": {"coordinates":[-79.269424,43.756439],"type":"Point"}
}