{
  "type": "Feature",
  "properties": {
    "addr:full":"310 Swain St Grandview MB R0L 0Y0",
    "addr:housenumber":"310",
    "addr:postcode":"r0l 0y0",
    "addr:street":"Swain St",
    "iso:country":"CA",
    "sg:address":"310 Swain St",
    "sg:city":"Grandview",
    "sg:classifiers":[
        {
            "category":"Arts & Performance",
            "subcategory":"Theater",
            "type":"Entertainment"
        }
    ],
    "sg:phone":"+1 204 546 2102",
    "sg:postcode":"R0L 0Y0",
    "sg:province":"MB",
    "sg:tags":[
        "dance",
        "music",
        "recorded"
    ],
    "wof:name":"Twilight Zone Music",
    "wof:placetype":"venue"
},
  "geometry": {"coordinates":[-100.69960021999999,51.1684112549],"type":"Point"}
}