{
  "type": "Feature",
  "properties": {
    "iso:country":"CA",
    "sg:city":"Monastery",
    "sg:classifiers":[
        {
            "category":"Education",
            "subcategory":"School",
            "type":"Public Place"
        }
    ],
    "sg:phone":"+1 902 232 2810",
    "sg:postcode":"B0H 1W0",
    "sg:province":"NS",
    "wof:name":"Antigonish East High School",
    "wof:placetype":"venue"
},
  "geometry": {"coordinates":[-61.6116676331,45.6081008911],"type":"Point"}
}