{
  "type": "Feature",
  "properties": {
    "addr:full":"PO Box 381 Gladstone MB R0J 0T0",
    "addr:housenumber":"po",
    "addr:postcode":"r0j 0t0",
    "addr:street":"Box 381",
    "iso:country":"CA",
    "sg:address":"PO Box 381",
    "sg:city":"Gladstone",
    "sg:classifiers":[
        {
            "category":"Shopping",
            "type":"Retail Goods"
        }
    ],
    "sg:phone":"+1 204 385 2095",
    "sg:postcode":"R0J 0T0",
    "sg:province":"MB",
    "sg:tags":[
        "monument"
    ],
    "wof:name":"Doug Stewart Concrete Memorial",
    "wof:placetype":"venue"
},
  "geometry": {"coordinates":[-98.95075199999999,50.225422],"type":"Point"}
}