{
  "type": "Feature",
  "properties": {
    "addr:full":"2967 Lough Rd South Mountain ON K0E 1W0",
    "addr:housenumber":"2967",
    "addr:postcode":"k0e 1w0",
    "addr:street":"Lough Rd",
    "iso:country":"CA",
    "sg:address":"2967 Lough Rd",
    "sg:city":"South Mountain",
    "sg:classifiers":[
        {
            "category":"Recreation",
            "type":"Entertainment"
        }
    ],
    "sg:phone":"+1 613 989 3815",
    "sg:postcode":"K0E 1W0",
    "sg:province":"ON",
    "sg:tags":[
        "hall",
        "auditorium"
    ],
    "wof:name":"Mountain Township Agricultural",
    "wof:placetype":"venue"
},
  "geometry": {"coordinates":[-75.450142,44.990841],"type":"Point"}
}