{
  "type": "Feature",
  "properties": {
    "addr:full":"Castlegar BC V1N 3K3",
    "addr:postcode":"v1n 3k3",
    "iso:country":"CA",
    "sg:city":"Castlegar",
    "sg:classifiers":[
        {
            "category":"Organizations",
            "subcategory":"Professional Association",
            "type":"Services"
        }
    ],
    "sg:phone":"+1 250 304 2246",
    "sg:postcode":"V1N 3K3",
    "sg:province":"BC",
    "wof:name":"Lower Columbia River All First",
    "wof:placetype":"venue"
},
  "geometry": {"coordinates":[-117.659477,49.307892],"type":"Point"}
}