{
  "type": "Feature",
  "properties": {
    "addr:full":"225 Parkdale Ave N Hamilton ON L8H 5X4",
    "addr:housenumber":"225",
    "addr:postcode":"l8h 5x4",
    "addr:street":"Parkdale Ave N",
    "iso:country":"CA",
    "sg:address":"225 Parkdale Ave N",
    "sg:city":"Hamilton",
    "sg:classifiers":[
        {
            "category":"Recreation",
            "type":"Entertainment"
        }
    ],
    "sg:phone":"+1 905 545 8816",
    "sg:postcode":"L8H 5X4",
    "sg:province":"ON",
    "sg:tags":[
        "parlor",
        "billiard"
    ],
    "wof:name":"M & J Billiards & Video",
    "wof:placetype":"venue"
},
  "geometry": {"coordinates":[-79.789390564,43.2429237366],"type":"Point"}
}