{
  "type": "Feature",
  "properties": {
    "addr:full":"3333 Rue Du Carrefour # 52A Beauport QC G1C 5R9",
    "addr:housenumber":"3333;# 52a",
    "addr:postcode":"qc g1c 5r9",
    "addr:street":"Rue Du Carrefour",
    "iso:country":"CA",
    "sg:address":"3333 Rue Du Carrefour # 52A",
    "sg:city":"Beauport",
    "sg:classifiers":[
        {
            "category":"Personal",
            "subcategory":"Beauty Salon",
            "type":"Services"
        }
    ],
    "sg:phone":"+1 418 661 0994",
    "sg:postcode":"G1C 5R9",
    "sg:province":"QC",
    "wof:name":"Institut DE Beaute M Simard",
    "wof:placetype":"venue"
},
  "geometry": {"coordinates":[-71.217178,46.858871],"type":"Point"}
}