{
  "type": "Feature",
  "properties": {
    "iso:country":"CA",
    "sg:address":"832 Av Bloomfield",
    "sg:city":"Outremont",
    "sg:classifiers":[
        {
            "category":"Health Services",
            "subcategory":"Health Practitioner",
            "type":"Services"
        }
    ],
    "sg:phone":"+1 514 277 6408",
    "sg:postcode":"H2V 3S6",
    "sg:province":"QC",
    "sg:tags":[
        "psychologist"
    ],
    "wof:name":"Lafortune Lamontagne",
    "wof:placetype":"venue"
},
  "geometry": {"coordinates":[-73.6138000488,45.5227928162],"type":"Point"}
}