{
  "type": "Feature",
  "properties": {
    "addr:full":"107 Jasper St Maple Creek SK S0N 1N0",
    "addr:housenumber":"107",
    "addr:postcode":"s0n 1n0",
    "addr:street":"Jasper St",
    "iso:country":"CA",
    "sg:address":"107 Jasper St",
    "sg:city":"Maple Creek",
    "sg:classifiers":[
        {
            "category":"Home & Garden",
            "subcategory":"Household Appliances",
            "type":"Retail Goods"
        }
    ],
    "sg:phone":"+1 306 662 2601",
    "sg:postcode":"S0N 1N0",
    "sg:province":"SK",
    "sg:tags":[
        "mail",
        "catalog",
        "shopping",
        "order"
    ],
    "wof:name":"Sears Canada Inc",
    "wof:placetype":"venue"
},
  "geometry": {"coordinates":[-109.478622,49.90921],"type":"Point"}
}