{
  "type": "Feature",
  "properties": {
    "addr:full":"550 Winnipeg Ave Thunder Bay ON P7B 3S7",
    "addr:housenumber":"550",
    "addr:postcode":"p7b 3s7",
    "addr:street":"Winnipeg Ave",
    "iso:country":"CA",
    "sg:address":"550 Winnipeg Ave",
    "sg:city":"Thunder Bay",
    "sg:classifiers":[
        {
            "category":"Retail",
            "subcategory":"Auto Repair",
            "type":"Services"
        }
    ],
    "sg:phone":"+1 807 345 7431",
    "sg:postcode":"P7B 3S7",
    "sg:province":"ON",
    "sg:tags":[
        "repairing",
        "automobile",
        "radiator"
    ],
    "wof:name":"Laine & Fairbairn",
    "wof:placetype":"venue"
},
  "geometry": {"coordinates":[-89.2410583496,48.4169960022],"type":"Point"}
}