{
  "type": "Feature",
  "properties": {
    "addr:full":"260 Av DE LA Falaise Sainte-Marie QC G6E 2A5",
    "addr:housenumber":"260",
    "addr:postcode":"g6e 2a5",
    "addr:street":"Av De La Falaise",
    "iso:country":"CA",
    "sg:address":"260 Av DE LA Falaise",
    "sg:city":"Sainte-Marie",
    "sg:classifiers":[
        {
            "category":"Building & Trades",
            "subcategory":"Electrical",
            "type":"Services"
        }
    ],
    "sg:phone":"+1 418 387 3039",
    "sg:postcode":"G6E 2A5",
    "sg:province":"QC",
    "sg:tags":[
        "electric",
        "contractor"
    ],
    "wof:name":"Electricite Pouliot & Parent",
    "wof:placetype":"venue"
},
  "geometry": {"coordinates":[-71.045311,46.458008],"type":"Point"}
}