{
  "type": "Feature",
  "properties": {
    "addr:full":"104 Rue Des Geants Saint-Raymond QC G3L 2X6",
    "addr:housenumber":"104",
    "addr:postcode":"g3l 2x6",
    "addr:street":"Rue Des Geants",
    "iso:country":"CA",
    "sg:address":"104 Rue Des Geants",
    "sg:city":"Saint-Raymond",
    "sg:classifiers":[
        {
            "category":"Freight",
            "type":"Transportation"
        }
    ],
    "sg:phone":"+1 418 337 7125",
    "sg:postcode":"G3L 2X6",
    "sg:province":"QC",
    "sg:tags":[
        "trucking"
    ],
    "wof:name":"Transport En Vrac Rdl Inc",
    "wof:placetype":"venue"
},
  "geometry": {"coordinates":[-71.815147,46.908634],"type":"Point"}
}