{
  "type": "Feature",
  "properties": {
    "addr:full":"4901 54th St Barrhead AB T7N 1A4",
    "addr:housenumber":"4901",
    "addr:postcode":"t7n 1a4",
    "addr:street":"54Th St",
    "iso:country":"CA",
    "sg:address":"4901 54th St",
    "sg:city":"Barrhead",
    "sg:classifiers":[
        {
            "category":"Farming",
            "subcategory":"Farm & Veterinary Services",
            "type":"Manufacturing & Wholesale Goods"
        }
    ],
    "sg:phone":"+1 780 674 2910",
    "sg:postcode":"T7N 1A4",
    "sg:province":"AB",
    "wof:name":"Champion Feed Svc Ltd",
    "wof:placetype":"venue"
},
  "geometry": {"coordinates":[-114.410622,54.120731],"type":"Point"}
}