{
  "type": "Feature",
  "properties": {
    "addr:full":"1042 Jefferson Ave Winnipeg MB R2P 0L1",
    "addr:housenumber":"1042",
    "addr:postcode":"r2p 0l1",
    "addr:street":"Jefferson Ave",
    "iso:country":"CA",
    "sg:address":"1042 Jefferson Ave",
    "sg:city":"Winnipeg",
    "sg:classifiers":[
        {
            "category":"Organizations",
            "subcategory":"Religious Organization",
            "type":"Services"
        }
    ],
    "sg:phone":"+1 204 694 6875",
    "sg:postcode":"R2P 0L1",
    "sg:province":"MB",
    "sg:tags":[
        "church"
    ],
    "wof:name":"Christian Life Assembly",
    "wof:placetype":"venue"
},
  "geometry": {"coordinates":[-97.161819458,49.9472236633],"type":"Point"}
}