{
  "type": "Feature",
  "properties": {
    "addr:full":"323 Montee Industrielle-Et-Com Rimouski QC G5M 1A7",
    "addr:housenumber":"323",
    "addr:postcode":"g5m 1a7",
    "addr:street":"Montee Industrielle-Et-Com",
    "iso:country":"CA",
    "sg:address":"323 Montee Industrielle-Et-Com",
    "sg:city":"Rimouski",
    "sg:classifiers":[
        {
            "category":"Manufacturing",
            "subcategory":"Electronics",
            "type":"Manufacturing & Wholesale Goods"
        }
    ],
    "sg:phone":"+1 418 722 2566",
    "sg:postcode":"G5M 1A7",
    "sg:province":"QC",
    "sg:tags":[
        "company",
        "broadcasting",
        "radio"
    ],
    "wof:name":"Ckmn-FM",
    "wof:placetype":"venue"
},
  "geometry": {"coordinates":[-68.500938,48.460239],"type":"Point"}
}