{
  "type": "Feature",
  "properties": {
    "addr:full":"1082 Highway 17 E Garden River ON P6A 6Z5",
    "addr:housenumber":"1082",
    "addr:postcode":"p6a 6z5",
    "addr:street":"Highway 17 E",
    "iso:country":"CA",
    "sg:address":"1082 Highway 17 E",
    "sg:city":"Garden River",
    "sg:classifiers":[
        {
            "category":"Organizations",
            "subcategory":"Religious Organization",
            "type":"Services"
        }
    ],
    "sg:phone":"+1 705 945 9046",
    "sg:postcode":"P6A 6Z5",
    "sg:province":"ON",
    "sg:tags":[
        "church"
    ],
    "wof:name":"Immaculate Heart of Mary Chrch",
    "wof:placetype":"venue"
},
  "geometry": {"coordinates":[-84.181496,46.552059],"type":"Point"}
}