{
  "type": "Feature",
  "properties": {
    "addr:full":"825 William St Cambridge ON N3H 3X2",
    "addr:housenumber":"825",
    "addr:postcode":"n3h 3x2",
    "addr:street":"William St",
    "iso:country":"CA",
    "sg:address":"825 William St",
    "sg:city":"Cambridge",
    "sg:classifiers":[
        {
            "category":"Arts & Performance",
            "subcategory":"Theater",
            "type":"Entertainment"
        }
    ],
    "sg:phone":"+1 519 653 3387",
    "sg:postcode":"N3H 3X2",
    "sg:province":"ON",
    "sg:tags":[
        "entertainer",
        "business"
    ],
    "wof:name":"Ragamuffins",
    "wof:placetype":"venue"
},
  "geometry": {"coordinates":[-80.354851,43.396778],"type":"Point"}
}