{
  "type": "Feature",
  "properties": {
    "addr:full":"439 North Rd Coquitlam BC V3K 3V9",
    "addr:housenumber":"439",
    "addr:postcode":"v3k 3v9",
    "addr:street":"North Rd",
    "iso:country":"CA",
    "sg:address":"439 North Rd",
    "sg:city":"Coquitlam",
    "sg:classifiers":[
        {
            "category":"Banks & Credit Unions",
            "subcategory":"Bank",
            "type":"Services"
        }
    ],
    "sg:phone":"+1 604 927 5653",
    "sg:postcode":"V3K 3V9",
    "sg:province":"BC",
    "wof:name":"Royal Bank Financial Group",
    "wof:placetype":"venue"
},
  "geometry": {"coordinates":[-122.89257000000001,49.247684],"type":"Point"}
}