{
  "type": "Feature",
  "properties": {
    "addr:full":"New Westminster BC V3M 6B9",
    "addr:postcode":"v3m 6b9",
    "iso:country":"CA",
    "sg:city":"New Westminster",
    "sg:classifiers":[
        {
            "category":"Manufacturing",
            "subcategory":"Food",
            "type":"Manufacturing & Wholesale Goods"
        }
    ],
    "sg:phone":"+1 604 540 9673",
    "sg:postcode":"V3M 6B9",
    "sg:province":"BC",
    "sg:tags":[
        "dry",
        "frozen",
        "dessert",
        "ice",
        "dairy",
        "prod",
        "cream"
    ],
    "wof:name":"Quayside Ice Cream",
    "wof:placetype":"venue"
},
  "geometry": {"coordinates":[-122.911827,49.200249],"type":"Point"}
}