{
  "type": "Feature",
  "properties": {
    "addr:full":"4700 County Rd 35 Comber ON N0P 1J0",
    "addr:housenumber":"4700;35",
    "addr:postcode":"n0p 1j0",
    "addr:street":"County Rd",
    "iso:country":"CA",
    "sg:address":"4700 County Rd 35",
    "sg:city":"Comber",
    "sg:classifiers":[
        {
            "category":"Freight",
            "type":"Transportation"
        }
    ],
    "sg:phone":"+1 519 687 2025",
    "sg:postcode":"N0P 1J0",
    "sg:province":"ON",
    "sg:tags":[
        "trucking"
    ],
    "wof:name":"Robert Transport Inc",
    "wof:placetype":"venue"
},
  "geometry": {"coordinates":[-82.552757,42.231224],"type":"Point"}
}