{
  "type": "Feature",
  "properties": {
    "iso:country":"CA",
    "sg:address":"2829 Rue King O",
    "sg:city":"Sherbrooke",
    "sg:classifiers":[
        {
            "category":"Organizations",
            "subcategory":"Non-profit Organization",
            "type":"Services"
        }
    ],
    "sg:phone":"+1 819 562 2555",
    "sg:postcode":"J1L 1C6",
    "sg:province":"QC",
    "sg:tags":[
        "handicapped"
    ],
    "wof:name":"Eureka Solutions",
    "wof:placetype":"venue"
},
  "geometry": {"coordinates":[-71.942116,45.397919],"type":"Point"}
}