{
  "type": "Feature",
  "properties": {
    "addr:full":"156 13th St E North Vancouver BC V7L 4W8",
    "addr:housenumber":"156",
    "addr:postcode":"v7l 4w8",
    "addr:street":"13Th St E",
    "iso:country":"CA",
    "sg:address":"156 13th St E",
    "sg:city":"North Vancouver",
    "sg:classifiers":[
        {
            "category":"Health Services",
            "subcategory":"Health Practitioner",
            "type":"Services"
        }
    ],
    "sg:phone":"+1 604 904 7447",
    "sg:postcode":"V7L 4W8",
    "sg:province":"BC",
    "sg:tags":[
        "acupuncture",
        "holistic"
    ],
    "wof:name":"Lion's Gate Health Ctr",
    "wof:placetype":"venue"
},
  "geometry": {"coordinates":[-123.07063293500001,49.3201179504],"type":"Point"}
}