{
  "type": "Feature",
  "properties": {
    "iso:country":"CA",
    "sg:address":"PO Box 157",
    "sg:city":"Czar",
    "sg:classifiers":[
        {
            "category":"Travel",
            "subcategory":"Campground",
            "type":"Entertainment"
        }
    ],
    "sg:phone":"+1 780 857 2435",
    "sg:postcode":"T0B 0Z0",
    "sg:province":"AB",
    "wof:name":"Shorncliffe Lake Park",
    "wof:placetype":"venue"
},
  "geometry": {"coordinates":[-110.828239,52.455479],"type":"Point"}
}