{
  "type": "Feature",
  "properties": {
    "iso:country":"CA",
    "sg:address":"393 Dundas St W",
    "sg:city":"Toronto",
    "sg:classifiers":[
        {
            "category":"Personal",
            "subcategory":"Beauty Salon",
            "type":"Services"
        }
    ],
    "sg:phone":"+1 416 977 8853",
    "sg:postcode":"M5T 1G6",
    "sg:province":"ON",
    "wof:name":"New Art Hair Design",
    "wof:placetype":"venue"
},
  "geometry": {"coordinates":[-79.39441680909999,43.6536407471],"type":"Point"}
}