{
  "type": "Feature",
  "properties": {
    "addr:full":"2790 3rd Ave W Vancouver BC V6K 1M5",
    "addr:housenumber":"2790",
    "addr:postcode":"v6k 1m5",
    "addr:street":"3Rd Ave W",
    "iso:country":"CA",
    "sg:address":"2790 3rd Ave W",
    "sg:city":"Vancouver",
    "sg:classifiers":[
        {
            "category":"Organizations",
            "subcategory":"Religious Organization",
            "type":"Services"
        }
    ],
    "sg:phone":"+1 604 736 6368",
    "sg:postcode":"V6K 1M5",
    "sg:province":"BC",
    "sg:tags":[
        "church"
    ],
    "wof:name":"Jehovah's Witnesses",
    "wof:placetype":"venue"
},
  "geometry": {"coordinates":[-123.167938232,49.269077301],"type":"Point"}
}