{
  "type": "Feature",
  "properties": {
    "addr:full":"PO Box 1599 Kahnawake QC J0L 1B0",
    "addr:housenumber":"po",
    "addr:postcode":"j0l 1b0",
    "addr:street":"Box 1599",
    "iso:country":"CA",
    "sg:address":"PO Box 1599",
    "sg:city":"Kahnawake",
    "sg:classifiers":[
        {
            "category":"Manufacturing",
            "subcategory":"Apparel",
            "type":"Manufacturing & Wholesale Goods"
        }
    ],
    "sg:phone":"+1 450 635 6757",
    "sg:postcode":"J0L 1B0",
    "sg:province":"QC",
    "sg:tags":[
        "clothing"
    ],
    "wof:name":"Tammy Beauvais Designs",
    "wof:placetype":"venue"
},
  "geometry": {"coordinates":[-73.68180084230001,45.410610199],"type":"Point"}
}