{
  "type": "Feature",
  "properties": {
    "iso:country":"CA",
    "sg:address":"3697 Rue Wellington",
    "sg:city":"Verdun",
    "sg:classifiers":[
        {
            "category":"Shopping",
            "subcategory":"Hobbies, Toys, & Games",
            "type":"Retail Goods"
        }
    ],
    "sg:phone":"+1 514 767 5389",
    "sg:postcode":"H4G 1V1",
    "sg:province":"QC",
    "sg:tags":[
        "video"
    ],
    "wof:name":"Game Zone",
    "wof:placetype":"venue"
},
  "geometry": {"coordinates":[-73.566849,45.466721],"type":"Point"}
}