{
  "type": "Feature",
  "properties": {
    "addr:full":"Montreal QC H1Y 3L1",
    "addr:postcode":"h1y 3l1",
    "iso:country":"CA",
    "sg:city":"Montreal",
    "sg:classifiers":[
        {
            "category":"Professional",
            "subcategory":"Business Services",
            "type":"Services"
        }
    ],
    "sg:phone":"+1 514 495 6500",
    "sg:postcode":"H1Y 3L1",
    "sg:province":"QC",
    "sg:tags":[
        "mapping"
    ],
    "wof:name":"Viasat Geo-Technologie Inc",
    "wof:placetype":"venue"
},
  "geometry": {"coordinates":[-73.56487300000001,45.541618],"type":"Point"}
}