{
  "type": "Feature",
  "properties": {
    "iso:country":"CA",
    "sg:address":"226 Rue Du Prince",
    "sg:city":"Sorel-Tracy",
    "sg:classifiers":[
        {
            "category":"Personal",
            "type":"Services"
        }
    ],
    "sg:phone":"+1 450 746 8540",
    "sg:postcode":"J3P 4L1",
    "sg:province":"QC",
    "sg:tags":[
        "psychotherapist",
        "therapist",
        "massage"
    ],
    "wof:name":"Dube, Ghislaine",
    "wof:placetype":"venue"
},
  "geometry": {"coordinates":[-73.1119766235,46.0381164551],"type":"Point"}
}