{
  "type": "Feature",
  "properties": {
    "addr:full":"Wynyard SK S0A 4T0",
    "addr:postcode":"s0a 4t0",
    "addr:street":"Wynyard",
    "iso:country":"CA",
    "sg:city":"Wynyard",
    "sg:classifiers":[
        {
            "category":"Government",
            "subcategory":"Office",
            "type":"Public Place"
        }
    ],
    "sg:phone":"+1 306 554 2123",
    "sg:postcode":"S0A 4T0",
    "sg:province":"SK",
    "sg:tags":[
        "village"
    ],
    "wof:name":"Wynyard Town Office",
    "wof:placetype":"venue"
},
  "geometry": {"coordinates":[-104.180092,51.765205],"type":"Point"}
}