{
  "type": "Feature",
  "properties": {
    "addr:full":"Saint-Alphonse-DE-Granby QC J0E 2A0",
    "addr:postcode":"j0e 2a0",
    "iso:country":"CA",
    "sg:city":"Saint-Alphonse-DE-Granby",
    "sg:classifiers":[
        {
            "category":"Retail",
            "subcategory":"Repair Shop",
            "type":"Services"
        }
    ],
    "sg:phone":"+1 450 378 2215",
    "sg:postcode":"J0E 2A0",
    "sg:province":"QC",
    "sg:tags":[
        "solder",
        "welding"
    ],
    "wof:name":"Equipements Industriels Fa-Mec",
    "wof:placetype":"venue"
},
  "geometry": {"coordinates":[-72.7217712402,45.3979949951],"type":"Point"}
}