{
  "type": "Feature",
  "properties": {
    "addr:full":"Cardinal ON K0E 1E0",
    "addr:postcode":"k0e 1e0",
    "iso:country":"CA",
    "sg:city":"Cardinal",
    "sg:classifiers":[
        {
            "category":"Government",
            "subcategory":"Fire Station",
            "type":"Public Place"
        }
    ],
    "sg:phone":"+1 613 657 3100",
    "sg:postcode":"K0E 1E0",
    "sg:province":"ON",
    "sg:tags":[
        "department"
    ],
    "wof:name":"Cardinal Fire Department",
    "wof:placetype":"venue"
},
  "geometry": {"coordinates":[-75.3848114014,44.7873153687],"type":"Point"}
}