{
  "type": "Feature",
  "properties": {
    "addr:full":"Mississauga ON L5L 3T5",
    "addr:postcode":"l5l 3t5",
    "iso:country":"CA",
    "sg:city":"Mississauga",
    "sg:classifiers":[
        {
            "category":"Professional",
            "subcategory":"Accounting & Tax Preparation",
            "type":"Services"
        }
    ],
    "sg:phone":"+1 905 607 1072",
    "sg:postcode":"L5L 3T5",
    "sg:province":"ON",
    "sg:tags":[
        "accountant"
    ],
    "wof:name":"Wormald, Robert CA",
    "wof:placetype":"venue"
},
  "geometry": {"coordinates":[-79.6821517944,43.5279541016],"type":"Point"}
}