{
  "type": "Feature",
  "properties": {
    "addr:full":"North York ON M9N 3K9",
    "addr:postcode":"m9n 3k9",
    "iso:country":"CA",
    "sg:city":"North York",
    "sg:classifiers":[
        {
            "category":"Retail",
            "subcategory":"Auto Repair",
            "type":"Services"
        }
    ],
    "sg:phone":"+1 416 244 3733",
    "sg:postcode":"M9N 3K9",
    "sg:province":"ON",
    "sg:tags":[
        "repairing",
        "automobile"
    ],
    "wof:name":"Cesario Auto Ctr Ltd",
    "wof:placetype":"venue"
},
  "geometry": {"coordinates":[-79.525688,43.713989],"type":"Point"}
}