{
  "type": "Feature",
  "properties": {
    "addr:full":"753 Dovercourt Rd Toronto ON M6H 2X1",
    "addr:housenumber":"753",
    "addr:postcode":"m6h 2x1",
    "addr:street":"Dovercourt Rd",
    "iso:country":"CA",
    "sg:address":"753 Dovercourt Rd",
    "sg:city":"Toronto",
    "sg:classifiers":[
        {
            "category":"Food & Beverages",
            "subcategory":"Groceries & Convenience Stores",
            "type":"Retail Goods"
        }
    ],
    "sg:phone":"+1 416 531 2616",
    "sg:postcode":"M6H 2X1",
    "sg:province":"ON",
    "sg:tags":[
        "grocer"
    ],
    "wof:name":"Wire's Variety & West Indian",
    "wof:placetype":"venue"
},
  "geometry": {"coordinates":[-79.42938232420001,43.6614952087],"type":"Point"}
}