{
  "type": "Feature",
  "properties": {
    "iso:country":"CA",
    "sg:city":"Langley",
    "sg:classifiers":[
        {
            "category":"Health Services",
            "subcategory":"Doctor",
            "type":"Services"
        }
    ],
    "sg:phone":"+1 604 534 5373",
    "sg:postcode":"V2Y 2M6",
    "sg:province":"BC",
    "sg:tags":[
        "physician",
        "surgeon"
    ],
    "wof:name":"Favero, Kenneth MD",
    "wof:placetype":"venue"
},
  "geometry": {"coordinates":[-122.61154174799999,49.0967941284],"type":"Point"}
}