{
  "type": "Feature",
  "properties": {
    "addr:full":"720 King Edward Ave E Vancouver BC V5V 2E2",
    "addr:housenumber":"720",
    "addr:postcode":"v5v 2e2",
    "addr:street":"King Edward Ave E",
    "iso:country":"CA",
    "sg:address":"720 King Edward Ave E",
    "sg:city":"Vancouver",
    "sg:classifiers":[
        {
            "category":"Social Services",
            "type":"Services"
        }
    ],
    "sg:phone":"+1 604 325 0576",
    "sg:postcode":"V5V 2E2",
    "sg:province":"BC",
    "sg:tags":[
        "organization",
        "welfare"
    ],
    "wof:name":"New Dawn Recovery Home-Women",
    "wof:placetype":"venue"
},
  "geometry": {"coordinates":[-123.089409,49.248486],"type":"Point"}
}