{
  "type": "Feature",
  "properties": {
    "addr:full":"215 Boul Rene-A.-Robert # 103 Sainte-Therese QC J7E 4L1",
    "addr:housenumber":"215",
    "addr:postcode":"j7e 4l1",
    "addr:street":"Boul Rene-A.-Robert # 103 Sainte-Therese",
    "iso:country":"CA",
    "sg:address":"215 Boul Rene-A.-Robert # 103",
    "sg:city":"Sainte-Therese",
    "sg:classifiers":[
        {
            "category":"Home & Garden",
            "subcategory":"Furniture",
            "type":"Retail Goods"
        }
    ],
    "sg:phone":"+1 450 434 1363",
    "sg:postcode":"J7E 4L1",
    "sg:province":"QC",
    "sg:tags":[
        "equipment",
        "kitchen",
        "cabinet"
    ],
    "wof:name":"Armoire DE Cuisine Ynolam",
    "wof:placetype":"venue"
},
  "geometry": {"coordinates":[-73.8184051514,45.6440048218],"type":"Point"}
}