{
  "type": "Feature",
  "properties": {
    "addr:full":"8416 Hwy 224 Upper Musquodoboit NS B0N 2M0",
    "addr:housenumber":"8416",
    "addr:postcode":"b0n 2m0",
    "addr:street":"Hwy 224",
    "iso:country":"CA",
    "sg:address":"8416 Hwy 224",
    "sg:city":"Upper Musquodoboit",
    "sg:classifiers":[
        {
            "category":"Education",
            "subcategory":"School",
            "type":"Public Place"
        }
    ],
    "sg:phone":"+1 902 568 2285",
    "sg:postcode":"B0N 2M0",
    "sg:province":"NS",
    "wof:name":"Upper Musquodoboit Cnsldtd",
    "wof:placetype":"venue"
},
  "geometry": {"coordinates":[-62.9511833191,45.1364173889],"type":"Point"}
}