{
  "type": "Feature",
  "properties": {
    "addr:full":"6236 Rue Saint-Hubert Montreal QC H2S 2M2",
    "addr:housenumber":"6236",
    "addr:postcode":"h2s 2m2",
    "addr:street":"Rue Saint-Hubert",
    "iso:country":"CA",
    "sg:address":"6236 Rue Saint-Hubert",
    "sg:city":"Montreal",
    "sg:classifiers":[
        {
            "category":"Home & Garden",
            "subcategory":"Carpets & Floor Coverings",
            "type":"Retail Goods"
        }
    ],
    "sg:phone":"+1 514 277 1138",
    "sg:postcode":"H2S 2M2",
    "sg:province":"QC",
    "sg:tags":[
        "dealer",
        "rug"
    ],
    "wof:name":"Tapis Haiks",
    "wof:placetype":"venue"
},
  "geometry": {"coordinates":[-73.600616,45.534889],"type":"Point"}
}