{
  "type": "Feature",
  "properties": {
    "addr:full":"5 Clearcrest Ave North York ON M2M 2T4",
    "addr:housenumber":"5",
    "addr:postcode":"m2m 2t4",
    "addr:street":"Clearcrest Ave",
    "iso:country":"CA",
    "sg:address":"5 Clearcrest Ave",
    "sg:city":"North York",
    "sg:classifiers":[
        {
            "category":"Professional",
            "subcategory":"Computer Services",
            "type":"Services"
        }
    ],
    "sg:phone":"+1 416 250 7325",
    "sg:postcode":"M2M 2T4",
    "sg:province":"ON",
    "wof:name":"Real Networks",
    "wof:placetype":"venue"
},
  "geometry": {"coordinates":[-79.3970794678,43.7994041443],"type":"Point"}
}