{
  "type": "Feature",
  "properties": {
    "iso:country":"CA",
    "sg:address":"5731 Av DE Monkland",
    "sg:city":"Montreal",
    "sg:classifiers":[
        {
            "category":"Shopping",
            "subcategory":"Gifts & Souvenirs",
            "type":"Retail Goods"
        }
    ],
    "sg:phone":"+1 514 485 9777",
    "sg:postcode":"H4A 1E7",
    "sg:province":"QC",
    "sg:tags":[
        "shop"
    ],
    "wof:name":"Boutique Mortimer Snodgrass",
    "wof:placetype":"venue"
},
  "geometry": {"coordinates":[-73.624306,45.474197],"type":"Point"}
}