{
  "type": "Feature",
  "properties": {
    "addr:full":"9802 104 St Fort Saskatchewan AB T8L 2E6",
    "addr:housenumber":"9802",
    "addr:postcode":"t8l 2e6",
    "addr:street":"104 St",
    "iso:country":"CA",
    "sg:address":"9802 104 St",
    "sg:city":"Fort Saskatchewan",
    "sg:classifiers":[
        {
            "category":"Organizations",
            "subcategory":"Religious Organization",
            "type":"Services"
        }
    ],
    "sg:phone":"+1 780 998 2451",
    "sg:postcode":"T8L 2E6",
    "sg:province":"AB",
    "sg:tags":[
        "church"
    ],
    "wof:name":"Church of the Nazarene",
    "wof:placetype":"venue"
},
  "geometry": {"coordinates":[-113.208702,53.710026],"type":"Point"}
}