{
  "type": "Feature",
  "properties": {
    "addr:full":"Unionville ON L3R 2E4",
    "addr:postcode":"l3r 2e4",
    "iso:country":"CA",
    "sg:city":"Unionville",
    "sg:classifiers":[
        {
            "category":"Retail",
            "subcategory":"Auto Repair",
            "type":"Services"
        }
    ],
    "sg:phone":"+1 905 947 0520",
    "sg:postcode":"L3R 2E4",
    "sg:province":"ON",
    "sg:tags":[
        "repairing",
        "automobile"
    ],
    "wof:name":"Main Auto Svc Ctr",
    "wof:placetype":"venue"
},
  "geometry": {"coordinates":[-79.29595947270001,43.8279075623],"type":"Point"}
}