{
  "type": "Feature",
  "properties": {
    "addr:full":"6 North St E Tillsonburg ON N4G 1B2",
    "addr:housenumber":"6",
    "addr:postcode":"n4g 1b2",
    "addr:street":"North St",
    "iso:country":"CA",
    "sg:address":"6 North St E",
    "sg:city":"Tillsonburg",
    "sg:classifiers":[
        {
            "category":"Organizations",
            "subcategory":"Religious Organization",
            "type":"Services"
        }
    ],
    "sg:phone":"+1 519 688 5959",
    "sg:postcode":"N4G 1B2",
    "sg:province":"ON",
    "sg:tags":[
        "church"
    ],
    "wof:name":"North Broadway Baptist Church",
    "wof:placetype":"venue"
},
  "geometry": {"coordinates":[-80.745689,42.878555],"type":"Point"}
}