{
  "type": "Feature",
  "properties": {
    "addr:full":"34 Rue Huot L'Ange Gardien QC G0A 2K0",
    "addr:housenumber":"34",
    "addr:postcode":"g0a 2k0",
    "addr:street":"Rue Huot",
    "iso:country":"CA",
    "sg:address":"34 Rue Huot",
    "sg:city":"L'Ange Gardien",
    "sg:classifiers":[
        {
            "category":"Retail",
            "subcategory":"Auto Repair",
            "type":"Services"
        }
    ],
    "sg:phone":"+1 418 822 0968",
    "sg:postcode":"G0A 2K0",
    "sg:province":"QC",
    "sg:tags":[
        "body",
        "automobile",
        "painting"
    ],
    "wof:name":"Garage Michel Fortier Inc",
    "wof:placetype":"venue"
},
  "geometry": {"coordinates":[-71.084694,46.920258],"type":"Point"}
}