{
  "type": "Feature",
  "properties": {
    "addr:full":"480 Range Lake Rd Yellowknife NT X1A 2P1",
    "addr:housenumber":"480",
    "addr:postcode":"x1a 2p1",
    "addr:street":"Range Lake Rd",
    "iso:country":"CA",
    "sg:address":"480 Range Lake Rd",
    "sg:city":"Yellowknife",
    "sg:classifiers":[
        {
            "category":"Organizations",
            "subcategory":"Religious Organization",
            "type":"Services"
        }
    ],
    "sg:phone":"+1 867 873 8449",
    "sg:postcode":"X1A 2P1",
    "sg:province":"NT",
    "sg:tags":[
        "church"
    ],
    "wof:name":"Glad Tidings Fellowship",
    "wof:placetype":"venue"
},
  "geometry": {"coordinates":[-114.41168999999999,62.445244],"type":"Point"}
}