{
  "type": "Feature",
  "properties": {
    "addr:full":"3456 Hope Mill Rd Indian River ON K0L 2B0",
    "addr:housenumber":"3456",
    "addr:postcode":"k0l 2b0",
    "addr:street":"Hope Mill Rd",
    "iso:country":"CA",
    "sg:address":"3456 Hope Mill Rd",
    "sg:city":"Indian River",
    "sg:classifiers":[
        {
            "category":"Museum",
            "type":"Entertainment"
        }
    ],
    "sg:phone":"+1 705 295 6250",
    "sg:postcode":"K0L 2B0",
    "sg:province":"ON",
    "sg:tags":[
        "campground"
    ],
    "wof:name":"Hope's Mill Conservation Area",
    "wof:placetype":"venue"
},
  "geometry": {"coordinates":[-78.141159,44.34341],"type":"Point"}
}