{
  "type": "Feature",
  "properties": {
    "addr:full":"3110 Rue Des Emeraudes Saint-Hubert QC J4T 3T5",
    "addr:housenumber":"3110",
    "addr:postcode":"j4t 3t5",
    "addr:street":"Rue Des Emeraudes",
    "iso:country":"CA",
    "sg:address":"3110 Rue Des Emeraudes",
    "sg:city":"Saint-Hubert",
    "sg:classifiers":[
        {
            "category":"Professional",
            "subcategory":"Business Services",
            "type":"Services"
        }
    ],
    "sg:phone":"+1 514 723 0616",
    "sg:postcode":"J4T 3T5",
    "sg:province":"QC",
    "sg:tags":[
        "inventory"
    ],
    "wof:name":"Inventaire Mcb Inc",
    "wof:placetype":"venue"
},
  "geometry": {"coordinates":[-73.4725189209,45.5032501221],"type":"Point"}
}