{
  "type": "Feature",
  "properties": {
    "iso:country":"CA",
    "sg:address":"112 John Cavanaugh Rd",
    "sg:city":"Carp",
    "sg:classifiers":[
        {
            "category":"Professional",
            "subcategory":"Management & Consulting",
            "type":"Services"
        }
    ],
    "sg:phone":"+1 613 839 3020",
    "sg:postcode":"K0A 1L0",
    "sg:province":"ON",
    "sg:tags":[
        "construction"
    ],
    "wof:name":"Pri Tec Intl Inc",
    "wof:placetype":"venue"
},
  "geometry": {"coordinates":[-75.99700164790001,45.3169136047],"type":"Point"}
}