{
  "type": "Feature",
  "properties": {
    "addr:full":"Calgary AB T2E 6V2",
    "addr:postcode":"t2e 6v2",
    "iso:country":"CA",
    "sg:city":"Calgary",
    "sg:classifiers":[
        {
            "category":"Retail",
            "subcategory":"Repair Shop",
            "type":"Services"
        }
    ],
    "sg:phone":"+1 403 291 2802",
    "sg:postcode":"T2E 6V2",
    "sg:province":"AB",
    "sg:tags":[
        "equipment",
        "video"
    ],
    "wof:name":"Vistec",
    "wof:placetype":"venue"
},
  "geometry": {"coordinates":[-114.011474609,51.0848274231],"type":"Point"}
}