{
  "type": "Feature",
  "properties": {
    "addr:full":"1017 Rue DE LA Visitation Saint-Charles-Borromee QC J6E 7Y8",
    "addr:housenumber":"1017",
    "addr:postcode":"j6e 7y8",
    "addr:street":"Rue De La Visitation Saint-Charles-Borromee",
    "iso:country":"CA",
    "sg:address":"1017 Rue DE LA Visitation",
    "sg:city":"Saint-Charles-Borromee",
    "sg:classifiers":[
        {
            "category":"Manufacturing",
            "subcategory":"Motor Vehicles & Parts",
            "type":"Manufacturing & Wholesale Goods"
        }
    ],
    "sg:phone":"+1 450 759 6808",
    "sg:postcode":"J6E 7Y8",
    "sg:province":"QC",
    "sg:tags":[
        "body",
        "automobile",
        "truck"
    ],
    "wof:name":"Garage Roger Garceau",
    "wof:placetype":"venue"
},
  "geometry": {"coordinates":[-73.482674,46.060406],"type":"Point"}
}