{
  "type": "Feature",
  "properties": {
    "addr:full":"Ascot QC J1H 4A3",
    "addr:postcode":"j1h 4a3",
    "iso:country":"CA",
    "sg:city":"Ascot",
    "sg:classifiers":[
        {
            "category":"Professional",
            "subcategory":"Computer Services",
            "type":"Services"
        }
    ],
    "sg:phone":"+1 819 565 5517",
    "sg:postcode":"J1H 4A3",
    "sg:province":"QC",
    "sg:tags":[
        "information",
        "system",
        "consultant"
    ],
    "wof:name":"Luc Allard Information",
    "wof:placetype":"venue"
},
  "geometry": {"coordinates":[-71.902939,45.379967],"type":"Point"}
}