{
  "type": "Feature",
  "properties": {
    "addr:full":"3035 Rue Sainte-Catherine E Montreal QC H1W 3X6",
    "addr:housenumber":"3035",
    "addr:postcode":"h1w 3x6",
    "addr:street":"Rue Sainte-Catherine E",
    "iso:country":"CA",
    "sg:address":"3035 Rue Sainte-Catherine E",
    "sg:city":"Montreal",
    "sg:classifiers":[
        {
            "category":"Manufacturing",
            "subcategory":"Printing",
            "type":"Manufacturing & Wholesale Goods"
        }
    ],
    "sg:phone":"+1 514 527 9111",
    "sg:postcode":"H1W 3X6",
    "sg:province":"QC",
    "sg:tags":[
        "printer"
    ],
    "wof:name":"Bcr Litho Ltd Ltee",
    "wof:placetype":"venue"
},
  "geometry": {"coordinates":[-73.542678833,45.5372276306],"type":"Point"}
}