{
  "type": "Feature",
  "properties": {
    "iso:country":"CA",
    "sg:address":"2355 Tedlo St",
    "sg:city":"Mississauga",
    "sg:classifiers":[
        {
            "category":"Wholesale",
            "subcategory":"Durable Goods & Equipment",
            "type":"Manufacturing & Wholesale Goods"
        }
    ],
    "sg:phone":"+1 905 277 9357",
    "sg:postcode":"L5A 3W7",
    "sg:province":"ON",
    "sg:tags":[
        "importer"
    ],
    "wof:name":"Monteiro Import Export Inc",
    "wof:placetype":"venue"
},
  "geometry": {"coordinates":[-79.5961685181,43.5869216919],"type":"Point"}
}