{
  "type": "Feature",
  "properties": {
    "addr:full":"875 Simpson Ave Winnipeg MB R2K 1S3",
    "addr:housenumber":"875",
    "addr:postcode":"r2k 1s3",
    "addr:street":"Simpson Ave",
    "iso:country":"CA",
    "sg:address":"875 Simpson Ave",
    "sg:city":"Winnipeg",
    "sg:classifiers":[
        {
            "category":"Retail",
            "subcategory":"Portrait Studio",
            "type":"Services"
        }
    ],
    "sg:phone":"+1 204 224 2424",
    "sg:postcode":"R2K 1S3",
    "sg:province":"MB",
    "sg:tags":[
        "photographer"
    ],
    "wof:name":"Impact Photographic Design",
    "wof:placetype":"venue"
},
  "geometry": {"coordinates":[-97.0750427246,49.9152450562],"type":"Point"}
}