{
  "type": "Feature",
  "properties": {
    "iso:country":"CA",
    "sg:address":"7930 Vantage Way",
    "sg:city":"Delta",
    "sg:classifiers":[
        {
            "category":"Wholesale",
            "subcategory":"Chemicals & Plastics",
            "type":"Manufacturing & Wholesale Goods"
        }
    ],
    "sg:phone":"+1 604 940 2313",
    "sg:postcode":"V4G 1A8",
    "sg:province":"BC",
    "wof:name":"Quadra Chemicals",
    "wof:placetype":"venue"
},
  "geometry": {"coordinates":[-123.004105,49.141769],"type":"Point"}
}