{
  "type": "Feature",
  "properties": {
    "addr:full":"7 Millwick Dr North York ON M9L 1Y4",
    "addr:housenumber":"7",
    "addr:postcode":"m9l 1y4",
    "addr:street":"Millwick Dr",
    "iso:country":"CA",
    "sg:address":"7 Millwick Dr",
    "sg:city":"North York",
    "sg:classifiers":[
        {
            "category":"Retail",
            "subcategory":"Auto Repair",
            "type":"Services"
        }
    ],
    "sg:phone":"+1 416 749 6101",
    "sg:postcode":"M9L 1Y4",
    "sg:province":"ON",
    "sg:tags":[
        "body",
        "automobile",
        "painting"
    ],
    "wof:name":"Mondial Fine Cars Inc",
    "wof:placetype":"venue"
},
  "geometry": {"coordinates":[-79.559837,43.756775],"type":"Point"}
}