{
  "type": "Feature",
  "properties": {
    "addr:full":"575 Richmond St London ON N6A 3G2",
    "addr:housenumber":"575",
    "addr:postcode":"n6a 3g2",
    "addr:street":"Richmond St",
    "iso:country":"CA",
    "sg:address":"575 Richmond St",
    "sg:city":"London",
    "sg:classifiers":[
        {
            "category":"Professional",
            "subcategory":"Employment Agencies",
            "type":"Services"
        }
    ],
    "sg:phone":"+1 519 432 1161",
    "sg:postcode":"N6A 3G2",
    "sg:province":"ON",
    "sg:tags":[
        "modeling"
    ],
    "wof:name":"Now Modelling & Acting Schl",
    "wof:placetype":"venue"
},
  "geometry": {"coordinates":[-81.25091552729999,42.9896659851],"type":"Point"}
}