{
  "type": "Feature",
  "properties": {
    "addr:full":"390 North Front St Belleville ON K8P 3E2",
    "addr:housenumber":"390",
    "addr:postcode":"k8p 3e2",
    "addr:street":"North Front St",
    "iso:country":"CA",
    "sg:address":"390 North Front St",
    "sg:city":"Belleville",
    "sg:classifiers":[
        {
            "category":"Shopping",
            "subcategory":"Music",
            "type":"Retail Goods"
        }
    ],
    "sg:phone":"+1 613 962 8933",
    "sg:postcode":"K8P 3E2",
    "sg:province":"ON",
    "sg:tags":[
        "compact",
        "record",
        "disc",
        "tape"
    ],
    "wof:name":"Music World",
    "wof:placetype":"venue"
},
  "geometry": {"coordinates":[-77.396591,44.1884],"type":"Point"}
}