{
  "type": "Feature",
  "properties": {
    "addr:full":"239 Water St St Andrews NB E5B 1B3",
    "addr:housenumber":"239",
    "addr:postcode":"e5b 1b3",
    "addr:street":"Water St",
    "iso:country":"CA",
    "sg:address":"239 Water St",
    "sg:city":"St Andrews",
    "sg:classifiers":[
        {
            "category":"Professional",
            "subcategory":"Lawyer & Legal Services",
            "type":"Services"
        }
    ],
    "sg:phone":"+1 506 529 9000",
    "sg:postcode":"E5B 1B3",
    "sg:province":"NB",
    "sg:tags":[
        "attorney"
    ],
    "wof:name":"Bartlett, David A",
    "wof:placetype":"venue"
},
  "geometry": {"coordinates":[-67.05135300000001,45.072842],"type":"Point"}
}