{
  "type": "Feature",
  "properties": {
    "addr:full":"671 Grand Ave W Chatham ON N7L 1C5",
    "addr:housenumber":"671",
    "addr:postcode":"n7l 1c5",
    "addr:street":"Grand Ave W",
    "iso:country":"CA",
    "sg:address":"671 Grand Ave W",
    "sg:city":"Chatham",
    "sg:classifiers":[
        {
            "category":"Shopping",
            "subcategory":"Department Store",
            "type":"Retail Goods"
        }
    ],
    "sg:phone":"+1 519 354 4000",
    "sg:postcode":"N7L 1C5",
    "sg:province":"ON",
    "wof:name":"Zellers",
    "wof:placetype":"venue"
},
  "geometry": {"coordinates":[-82.2105255127,42.3975906372],"type":"Point"}
}