{
  "type": "Feature",
  "properties": {
    "addr:full":"711 Woodstock Rd Fredericton NB E3B 5N8",
    "addr:housenumber":"711",
    "addr:postcode":"e3b 5n8",
    "addr:street":"Woodstock Rd",
    "iso:country":"CA",
    "sg:address":"711 Woodstock Rd",
    "sg:city":"Fredericton",
    "sg:classifiers":[
        {
            "category":"Professional",
            "subcategory":"Engineering",
            "type":"Services"
        }
    ],
    "sg:phone":"+1 506 457 3200",
    "sg:postcode":"E3B 5N8",
    "sg:province":"NB",
    "sg:tags":[
        "engineer"
    ],
    "wof:name":"Jacques Whitford",
    "wof:placetype":"venue"
},
  "geometry": {"coordinates":[-66.67671199999999,45.963516],"type":"Point"}
}