{
  "type": "Feature",
  "properties": {
    "addr:full":"468 Queen St W Toronto ON M5V 2B2",
    "addr:housenumber":"468",
    "addr:postcode":"m5v 2b2",
    "addr:street":"Queen St W",
    "iso:country":"CA",
    "sg:address":"468 Queen St W",
    "sg:city":"Toronto",
    "sg:classifiers":[
        {
            "category":"Recreation",
            "type":"Entertainment"
        }
    ],
    "sg:phone":"+1 416 504 9494",
    "sg:postcode":"M5V 2B2",
    "sg:province":"ON",
    "sg:tags":[
        "parlor",
        "billiard"
    ],
    "wof:name":"Central Billards",
    "wof:placetype":"venue"
},
  "geometry": {"coordinates":[-79.400009,43.648113],"type":"Point"}
}