{
  "type": "Feature",
  "properties": {
    "iso:country":"CA",
    "sg:address":"3484 Main St",
    "sg:city":"Vancouver",
    "sg:classifiers":[
        {
            "category":"Health Services",
            "subcategory":"Doctor",
            "type":"Services"
        }
    ],
    "sg:phone":"+1 604 877 2233",
    "sg:postcode":"V5V 3N2",
    "sg:province":"BC",
    "sg:tags":[
        "physician",
        "surgeon"
    ],
    "wof:name":"Thomas Mw Ho Inc",
    "wof:placetype":"venue"
},
  "geometry": {"coordinates":[-123.10068511999999,49.2540969849],"type":"Point"}
}