{
  "type": "Feature",
  "properties": {
    "addr:full":"Scarborough ON M1W 3Y3",
    "addr:postcode":"m1w 3y3",
    "iso:country":"CA",
    "sg:city":"Scarborough",
    "sg:classifiers":[
        {
            "category":"Shopping",
            "type":"Retail Goods"
        }
    ],
    "sg:phone":"+1 416 498 6899",
    "sg:postcode":"M1W 3Y3",
    "sg:province":"ON",
    "sg:tags":[
        "cosmetic",
        "perfume"
    ],
    "wof:name":"Ammei Cosmetics",
    "wof:placetype":"venue"
},
  "geometry": {"coordinates":[-79.335106,43.801819],"type":"Point"}
}