{
  "type": "Feature",
  "properties": {
    "addr:full":"3510 8th St E Saskatoon SK S7H 4Z8",
    "addr:housenumber":"3510",
    "addr:postcode":"s7h 4z8",
    "addr:street":"8Th St E",
    "iso:country":"CA",
    "sg:address":"3510 8th St E",
    "sg:city":"Saskatoon",
    "sg:classifiers":[
        {
            "category":"Shopping",
            "subcategory":"Jewelry",
            "type":"Retail Goods"
        }
    ],
    "sg:phone":"+1 306 955 2323",
    "sg:postcode":"S7H 4Z8",
    "sg:province":"SK",
    "sg:tags":[
        "beads"
    ],
    "wof:name":"Bead Hive",
    "wof:placetype":"venue"
},
  "geometry": {"coordinates":[-106.59704600000001,52.114491],"type":"Point"}
}