{
  "type": "Feature",
  "properties": {
    "addr:full":"5919 103A St NW Edmonton AB T6H 2J7",
    "addr:housenumber":"5919",
    "addr:postcode":"t6h 2j7",
    "addr:street":"103A St Nw",
    "iso:country":"CA",
    "sg:address":"5919 103A St NW",
    "sg:city":"Edmonton",
    "sg:classifiers":[
        {
            "category":"Wholesale",
            "subcategory":"Construction Materials",
            "type":"Manufacturing & Wholesale Goods"
        }
    ],
    "sg:phone":"+1 780 436 9530",
    "sg:postcode":"T6H 2J7",
    "sg:province":"AB",
    "sg:tags":[
        "fence"
    ],
    "wof:name":"Soldan Fence & Metals Ltd",
    "wof:placetype":"venue"
},
  "geometry": {"coordinates":[-113.494796753,53.4963188171],"type":"Point"}
}