{
  "type": "Feature",
  "properties": {
    "iso:country":"CA",
    "sg:city":"Markham",
    "sg:classifiers":[
        {
            "category":"Home & Garden",
            "subcategory":"Building Materials",
            "type":"Retail Goods"
        }
    ],
    "sg:phone":"+1 905 477 0401",
    "sg:postcode":"L3R 5J6",
    "sg:province":"ON",
    "sg:tags":[
        "glass",
        "window",
        "plate"
    ],
    "wof:name":"401 Glass & Window Hardware",
    "wof:placetype":"venue"
},
  "geometry": {"coordinates":[-79.3397979736,43.8327255249],"type":"Point"}
}