{
  "type": "Feature",
  "properties": {
    "addr:full":"4012 Boul DE LA Cote-Vertu Saint-Laurent QC H4R 1V4",
    "addr:housenumber":"4012",
    "addr:postcode":"h4r 1v4",
    "addr:street":"Boul De La Cote-Vertu",
    "iso:country":"CA",
    "sg:address":"4012 Boul DE LA Cote-Vertu",
    "sg:city":"Saint-Laurent",
    "sg:classifiers":[
        {
            "category":"Wholesale",
            "subcategory":"Apparel",
            "type":"Manufacturing & Wholesale Goods"
        }
    ],
    "sg:phone":"+1 514 333 4188",
    "sg:postcode":"H4R 1V4",
    "sg:province":"QC",
    "sg:tags":[
        "bar"
    ],
    "wof:name":"Distex Inc",
    "wof:placetype":"venue"
},
  "geometry": {"coordinates":[-73.7116775513,45.4909667969],"type":"Point"}
}