{
  "type": "Feature",
  "properties": {
    "addr:full":"PO Box 365 Moose Factory ON P0L 1W0",
    "addr:housenumber":"po",
    "addr:postcode":"p0l 1w0",
    "addr:street":"Box 365",
    "iso:country":"CA",
    "sg:address":"PO Box 365",
    "sg:city":"Moose Factory",
    "sg:classifiers":[
        {
            "category":"Shopping",
            "subcategory":"Gifts & Souvenirs",
            "type":"Retail Goods"
        }
    ],
    "sg:phone":"+1 705 658 4341",
    "sg:postcode":"P0L 1W0",
    "sg:province":"ON",
    "sg:tags":[
        "shop"
    ],
    "wof:name":"Gift Basket",
    "wof:placetype":"venue"
},
  "geometry": {"coordinates":[-80.59711456300001,51.2601966858],"type":"Point"}
}