{
  "type": "Feature",
  "properties": {
    "addr:full":"4258 Rue Jean-Talon E Saint-Leonard QC H1S 1J7",
    "addr:housenumber":"4258",
    "addr:postcode":"h1s 1j7",
    "addr:street":"Rue Jean-Talon E",
    "iso:country":"CA",
    "sg:address":"4258 Rue Jean-Talon E",
    "sg:city":"Saint-Leonard",
    "sg:classifiers":[
        {
            "category":"Restaurant",
            "type":"Food & Drink"
        }
    ],
    "sg:phone":"+1 514 722 1714",
    "sg:postcode":"H1S 1J7",
    "sg:province":"QC",
    "wof:name":"Berke Steak Bar & Luncheonnet",
    "wof:placetype":"venue"
},
  "geometry": {"coordinates":[-73.595856,45.586124],"type":"Point"}
}