{
  "type": "Feature",
  "properties": {
    "addr:full":"99 Craglea Corner Winnipeg MB R2C 4H8",
    "addr:housenumber":"99",
    "addr:postcode":"r2c 4h8",
    "addr:street":"Craglea Corner",
    "iso:country":"CA",
    "sg:address":"99 Craglea Corner",
    "sg:city":"Winnipeg",
    "sg:classifiers":[
        {
            "category":"Shopping",
            "subcategory":"Computers & Home Electronics",
            "type":"Retail Goods"
        }
    ],
    "sg:phone":"+1 204 958 4200",
    "sg:postcode":"R2C 4H8",
    "sg:province":"MB",
    "sg:tags":[
        "equipment",
        "dealer"
    ],
    "wof:name":"Profitable Business Systems",
    "wof:placetype":"venue"
},
  "geometry": {"coordinates":[-96.969925,49.906609],"type":"Point"}
}