{
  "type": "Feature",
  "properties": {
    "iso:country":"CA",
    "sg:address":"230 Main St",
    "sg:city":"Ferintosh",
    "sg:classifiers":[
        {
            "category":"Travel",
            "subcategory":"Hotels & Motels",
            "type":"Entertainment"
        }
    ],
    "sg:phone":"+1 780 877 2537",
    "sg:postcode":"T0B 1M0",
    "sg:province":"AB",
    "wof:name":"Ferintosh Hotel",
    "wof:placetype":"venue"
},
  "geometry": {"coordinates":[-112.974105835,52.7656364441],"type":"Point"}
}