{
  "type": "Feature",
  "properties": {
    "iso:country":"CA",
    "sg:address":"3131 Boul DE LA Cote-Vertu",
    "sg:city":"Saint-Laurent",
    "sg:classifiers":[
        {
            "category":"Restaurant",
            "type":"Food & Drink"
        }
    ],
    "sg:phone":"+1 514 331 7172",
    "sg:postcode":"H4R 1Y8",
    "sg:province":"QC",
    "wof:name":"East Side Mario's",
    "wof:placetype":"venue"
},
  "geometry": {"coordinates":[-73.70355987550001,45.4979896545],"type":"Point"}
}