{
  "type": "Feature",
  "properties": {
    "addr:full":"185 Thickson Rd N Whitby ON L1N 6T9",
    "addr:housenumber":"185",
    "addr:postcode":"l1n 6t9",
    "addr:street":"Thickson Rd N",
    "iso:country":"CA",
    "sg:address":"185 Thickson Rd N",
    "sg:city":"Whitby",
    "sg:classifiers":[
        {
            "category":"Retail",
            "subcategory":"Laundry & Dry Cleaning",
            "type":"Services"
        }
    ],
    "sg:phone":"+1 905 723 3021",
    "sg:postcode":"L1N 6T9",
    "sg:province":"ON",
    "sg:tags":[
        "cleaners"
    ],
    "wof:name":"Snow White Dry Cleaners",
    "wof:placetype":"venue"
},
  "geometry": {"coordinates":[-78.9177246094,43.8984947205],"type":"Point"}
}