{
  "type": "Feature",
  "properties": {
    "iso:country":"CA",
    "sg:address":"2876 Dundas St W",
    "sg:city":"Toronto",
    "sg:classifiers":[
        {
            "category":"Professional",
            "subcategory":"Business Services",
            "type":"Services"
        }
    ],
    "sg:phone":"+1 416 766 9084",
    "sg:postcode":"M6P 1Y8",
    "sg:province":"ON",
    "sg:tags":[
        "interior",
        "consultant",
        "design",
        "decorator"
    ],
    "wof:name":"Design Stream Ltd",
    "wof:placetype":"venue"
},
  "geometry": {"coordinates":[-79.4652557373,43.6655464172],"type":"Point"}
}