{
  "type": "Feature",
  "properties": {
    "iso:country":"CA",
    "sg:address":"PO Box 4438 STN Main",
    "sg:city":"Barrhead",
    "sg:classifiers":[
        {
            "category":"Organizations",
            "subcategory":"Religious Organization",
            "type":"Services"
        }
    ],
    "sg:phone":"+1 780 674 2173",
    "sg:postcode":"T7N 1A3",
    "sg:province":"AB",
    "sg:tags":[
        "church"
    ],
    "wof:name":"St Mary Abbots Anglican Church",
    "wof:placetype":"venue"
},
  "geometry": {"coordinates":[-114.406005859,54.1209907532],"type":"Point"}
}