{
  "type": "Feature",
  "properties": {
    "addr:full":"606 Main St Swan River MB R0L 1Z0",
    "addr:housenumber":"606",
    "addr:postcode":"r0l 1z0",
    "addr:street":"Main St",
    "iso:country":"CA",
    "sg:address":"606 Main St",
    "sg:city":"Swan River",
    "sg:classifiers":[
        {
            "category":"Shopping",
            "subcategory":"Jewelry",
            "type":"Retail Goods"
        }
    ],
    "sg:phone":"+1 204 734 2982",
    "sg:postcode":"R0L 1Z0",
    "sg:province":"MB",
    "sg:tags":[
        "jeweler"
    ],
    "wof:name":"Lloyd's Jewellers Ltd",
    "wof:placetype":"venue"
},
  "geometry": {"coordinates":[-101.267433166,52.1057548523],"type":"Point"}
}