{
  "type": "Feature",
  "properties": {
    "iso:country":"CA",
    "sg:city":"Toronto",
    "sg:classifiers":[
        {
            "category":"Banks & Credit Unions",
            "subcategory":"Investment Brokerage",
            "type":"Services"
        }
    ],
    "sg:phone":"+1 416 941 1560",
    "sg:postcode":"M5E 1J4",
    "sg:province":"ON",
    "sg:tags":[
        "stock",
        "broker",
        "bond"
    ],
    "wof:name":"Independent Trading Group",
    "wof:placetype":"venue"
},
  "geometry": {"coordinates":[-79.37729644780001,43.6482124329],"type":"Point"}
}