{
  "type": "Feature",
  "properties": {
    "addr:full":"532 Rue Saint-Antoine LA Tuque QC G9X 2Y4",
    "addr:housenumber":"532",
    "addr:postcode":"g9x 2y4",
    "addr:street":"Rue Saint-Antoine",
    "iso:country":"CA",
    "sg:address":"532 Rue Saint-Antoine",
    "sg:city":"LA Tuque",
    "sg:classifiers":[
        {
            "category":"Building & Trades",
            "subcategory":"Plumbing",
            "type":"Services"
        }
    ],
    "sg:phone":"+1 819 523 2590",
    "sg:postcode":"G9X 2Y4",
    "sg:province":"QC",
    "sg:tags":[
        "contractor"
    ],
    "wof:name":"Plomberie Roger Matte",
    "wof:placetype":"venue"
},
  "geometry": {"coordinates":[-72.783699,47.440121],"type":"Point"}
}