{
  "type": "Feature",
  "properties": {
    "iso:country":"CA",
    "sg:address":"17 Duke St",
    "sg:city":"Trenton",
    "sg:classifiers":[
        {
            "category":"Social Services",
            "subcategory":"Child Care",
            "type":"Services"
        }
    ],
    "sg:phone":"+1 902 752 0711",
    "sg:postcode":"B0K 1X0",
    "sg:province":"NS",
    "wof:name":"Children's Place",
    "wof:placetype":"venue"
},
  "geometry": {"coordinates":[-62.6262283325,45.6135902405],"type":"Point"}
}