{
  "type": "Feature",
  "properties": {
    "addr:full":"35 North River Rd Wallaceburg ON N8A 4R4",
    "addr:housenumber":"35",
    "addr:postcode":"n8a 4r4",
    "addr:street":"North River Rd",
    "iso:country":"CA",
    "sg:address":"35 North River Rd",
    "sg:city":"Wallaceburg",
    "sg:classifiers":[
        {
            "category":"Recreation",
            "type":"Entertainment"
        }
    ],
    "sg:phone":"+1 519 627 3623",
    "sg:postcode":"N8A 4R4",
    "sg:province":"ON",
    "sg:tags":[
        "center"
    ],
    "wof:name":"Sydenham Curling Club",
    "wof:placetype":"venue"
},
  "geometry": {"coordinates":[-82.358643,42.598358],"type":"Point"}
}