{
  "type": "Feature",
  "properties": {
    "addr:full":"659 Ouellette Ave Windsor ON N9A 4J4",
    "addr:housenumber":"659",
    "addr:postcode":"n9a 4j4",
    "addr:street":"Ouellette Ave",
    "iso:country":"CA",
    "sg:address":"659 Ouellette Ave",
    "sg:city":"Windsor",
    "sg:classifiers":[
        {
            "category":"Shopping",
            "subcategory":"Music",
            "type":"Retail Goods"
        }
    ],
    "sg:phone":"+1 519 253 9744",
    "sg:postcode":"N9A 4J4",
    "sg:province":"ON",
    "sg:tags":[
        "compact",
        "record",
        "disc",
        "tape"
    ],
    "wof:name":"Dr Disc",
    "wof:placetype":"venue"
},
  "geometry": {"coordinates":[-83.036545,42.313328],"type":"Point"}
}