{
  "type": "Feature",
  "properties": {
    "iso:country":"CA",
    "sg:address":"762 Springbank Dr",
    "sg:city":"London",
    "sg:classifiers":[
        {
            "category":"Building & Trades",
            "subcategory":"Construction",
            "type":"Services"
        }
    ],
    "sg:phone":"+1 519 657 3121",
    "sg:postcode":"N6K 1A3",
    "sg:province":"ON",
    "sg:tags":[
        "contractor"
    ],
    "wof:name":"Artisan Homes",
    "wof:placetype":"venue"
},
  "geometry": {"coordinates":[-81.301903,42.959301],"type":"Point"}
}