{
  "type": "Feature",
  "properties": {
    "addr:full":"Lourdes-DE-Joliette QC J0K 1K0",
    "addr:postcode":"j0k 1k0",
    "iso:country":"CA",
    "sg:city":"Lourdes-DE-Joliette",
    "sg:classifiers":[
        {
            "category":"Retail",
            "subcategory":"Auto Repair",
            "type":"Services"
        }
    ],
    "sg:phone":"+1 450 756 0699",
    "sg:postcode":"J0K 1K0",
    "sg:province":"QC",
    "sg:tags":[
        "repairing",
        "tire"
    ],
    "wof:name":"Pneus & Jantes Usages Michel",
    "wof:placetype":"venue"
},
  "geometry": {"coordinates":[-73.90818023680001,45.9096565247],"type":"Point"}
}