{
  "type": "Feature",
  "properties": {
    "iso:country":"CA",
    "sg:city":"Edmonton",
    "sg:classifiers":[
        {
            "category":"Professional",
            "subcategory":"Accounting & Tax Preparation",
            "type":"Services"
        }
    ],
    "sg:phone":"+1 780 426 6868",
    "sg:postcode":"T5E 5R8",
    "sg:province":"AB",
    "sg:tags":[
        "accountant"
    ],
    "wof:name":"Olyan & Assoc",
    "wof:placetype":"venue"
},
  "geometry": {"coordinates":[-113.487785339,53.5992660522],"type":"Point"}
}