{
  "type": "Feature",
  "properties": {
    "addr:full":"82 Victoria Ave S Hamilton ON L8N 2S7",
    "addr:housenumber":"82",
    "addr:postcode":"l8n 2s7",
    "addr:street":"Victoria Ave S",
    "iso:country":"CA",
    "sg:address":"82 Victoria Ave S",
    "sg:city":"Hamilton",
    "sg:classifiers":[
        {
            "category":"Social Services",
            "type":"Services"
        }
    ],
    "sg:phone":"+1 905 526 9529",
    "sg:postcode":"L8N 2S7",
    "sg:province":"ON",
    "sg:tags":[
        "organization",
        "welfare"
    ],
    "wof:name":"Dawn Patrol Child & Youth Svc",
    "wof:placetype":"venue"
},
  "geometry": {"coordinates":[-79.858192,43.250587],"type":"Point"}
}