{
  "type": "Feature",
  "properties": {
    "addr:full":"Saskatoon SK S7K 4Z6",
    "addr:postcode":"s7k 4z6",
    "iso:country":"CA",
    "sg:city":"Saskatoon",
    "sg:classifiers":[
        {
            "category":"Wholesale",
            "subcategory":"Machinery & Supplies",
            "type":"Manufacturing & Wholesale Goods"
        }
    ],
    "sg:phone":"+1 306 343 8408",
    "sg:postcode":"S7K 4Z6",
    "sg:province":"SK",
    "sg:tags":[
        "agricultural",
        "implement"
    ],
    "wof:name":"Wintersteiger",
    "wof:placetype":"venue"
},
  "geometry": {"coordinates":[-106.657402039,52.1756095886],"type":"Point"}
}