{
  "type": "Feature",
  "properties": {
    "addr:full":"333 Rue Chabanel O Montreal QC H2N 2E7",
    "addr:housenumber":"333",
    "addr:postcode":"h2n 2e7",
    "addr:street":"Rue Chabanel O",
    "iso:country":"CA",
    "sg:address":"333 Rue Chabanel O",
    "sg:city":"Montreal",
    "sg:classifiers":[
        {
            "category":"Banks & Credit Unions",
            "subcategory":"Investment Brokerage",
            "type":"Services"
        }
    ],
    "sg:phone":"+1 514 382 8822",
    "sg:postcode":"H2N 2E7",
    "sg:province":"QC",
    "sg:tags":[
        "advisory",
        "financial"
    ],
    "wof:name":"Ecgam Services",
    "wof:placetype":"venue"
},
  "geometry": {"coordinates":[-73.653968811,45.5399856567],"type":"Point"}
}