{
  "type": "Feature",
  "properties": {
    "addr:full":"Saint-Andre-Avellin QC J0V 1W0",
    "addr:postcode":"j0v 1w0",
    "iso:country":"CA",
    "sg:city":"Saint-Andre-Avellin",
    "sg:classifiers":[
        {
            "category":"Building & Trades",
            "subcategory":"Plumbing",
            "type":"Services"
        }
    ],
    "sg:phone":"+1 819 983 2747",
    "sg:postcode":"J0V 1W0",
    "sg:province":"QC",
    "sg:tags":[
        "contractor"
    ],
    "wof:name":"Plomberie Marc Boyer",
    "wof:placetype":"venue"
},
  "geometry": {"coordinates":[-75.06588000000001,45.722122],"type":"Point"}
}