{
  "type": "Feature",
  "properties": {
    "addr:full":"40 Bruce St Clarks Harbour NS B0W 1P0",
    "addr:housenumber":"40",
    "addr:postcode":"b0w 1p0",
    "addr:street":"Bruce St",
    "iso:country":"CA",
    "sg:address":"40 Bruce St",
    "sg:city":"Clarks Harbour",
    "sg:classifiers":[
        {
            "category":"Manufacturing",
            "subcategory":"Food",
            "type":"Manufacturing & Wholesale Goods"
        }
    ],
    "sg:phone":"+1 902 745 2801",
    "sg:postcode":"B0W 1P0",
    "sg:province":"NS",
    "sg:tags":[
        "product",
        "seafood",
        "fish",
        "prepared"
    ],
    "wof:name":"Island Fresh Seafood Inc",
    "wof:placetype":"venue"
},
  "geometry": {"coordinates":[-63.5308303833,44.6722717285],"type":"Point"}
}