{
  "type": "Feature",
  "properties": {
    "addr:full":"Parksville BC V9P 2E1",
    "addr:postcode":"v9p 2e1",
    "iso:country":"CA",
    "sg:city":"Parksville",
    "sg:classifiers":[
        {
            "category":"Professional",
            "subcategory":"Lawyer & Legal Services",
            "type":"Services"
        }
    ],
    "sg:phone":"+1 250 248 1150",
    "sg:postcode":"V9P 2E1",
    "sg:province":"BC",
    "sg:tags":[
        "attorney"
    ],
    "wof:name":"Russel Law Offices",
    "wof:placetype":"venue"
},
  "geometry": {"coordinates":[-124.31364440900001,49.3196907043],"type":"Point"}
}