{
  "type": "Feature",
  "properties": {
    "addr:full":"534 Boul Du Royaume O Chicoutimi QC G7H 5B1",
    "addr:housenumber":"534",
    "addr:postcode":"g7h 5b1",
    "addr:street":"Boul Du Royaume O",
    "iso:country":"CA",
    "sg:address":"534 Boul Du Royaume O",
    "sg:city":"Chicoutimi",
    "sg:classifiers":[
        {
            "category":"Home & Garden",
            "subcategory":"Building Materials",
            "type":"Retail Goods"
        }
    ],
    "sg:phone":"+1 418 549 7277",
    "sg:postcode":"G7H 5B1",
    "sg:province":"QC",
    "sg:tags":[
        "glass",
        "window",
        "plate"
    ],
    "wof:name":"Vitre D'Autos Saguenay",
    "wof:placetype":"venue"
},
  "geometry": {"coordinates":[-71.09375799999999,48.384171],"type":"Point"}
}