{
  "type": "Feature",
  "properties": {
    "addr:full":"8 Mitchell St Guelph ON N1E 4J1",
    "addr:housenumber":"8",
    "addr:postcode":"n1e 4j1",
    "addr:street":"Mitchell St",
    "iso:country":"CA",
    "sg:address":"8 Mitchell St",
    "sg:city":"Guelph",
    "sg:classifiers":[
        {
            "category":"Organizations",
            "subcategory":"Religious Organization",
            "type":"Services"
        }
    ],
    "sg:phone":"+1 519 836 1863",
    "sg:postcode":"N1E 4J1",
    "sg:province":"ON",
    "sg:tags":[
        "church"
    ],
    "wof:name":"Community of Christ Church",
    "wof:placetype":"venue"
},
  "geometry": {"coordinates":[-80.250687,43.550251],"type":"Point"}
}