{
  "type": "Feature",
  "properties": {
    "addr:full":"91 Martin Ross Ave North York ON M3J 2L9",
    "addr:housenumber":"91",
    "addr:postcode":"m3j 2l9",
    "addr:street":"Martin Ross Ave",
    "iso:country":"CA",
    "sg:address":"91 Martin Ross Ave",
    "sg:city":"North York",
    "sg:classifiers":[
        {
            "category":"Manufacturing",
            "subcategory":"Retail Goods",
            "type":"Manufacturing & Wholesale Goods"
        }
    ],
    "sg:phone":"+1 416 663 5570",
    "sg:postcode":"M3J 2L9",
    "sg:province":"ON",
    "sg:tags":[
        "marking",
        "devices"
    ],
    "wof:name":"Hambleton Enterprises Inc",
    "wof:placetype":"venue"
},
  "geometry": {"coordinates":[-79.476906,43.773327],"type":"Point"}
}