{
  "type": "Feature",
  "properties": {
    "addr:full":"683 Plains Rd E Burlington ON L7T 2E8",
    "addr:housenumber":"683",
    "addr:postcode":"l7t 2e8",
    "addr:street":"Plains Rd E",
    "iso:country":"CA",
    "sg:address":"683 Plains Rd E",
    "sg:city":"Burlington",
    "sg:classifiers":[
        {
            "category":"Shopping",
            "subcategory":"Computers & Home Electronics",
            "type":"Retail Goods"
        }
    ],
    "sg:phone":"+1 905 632 1110",
    "sg:postcode":"L7T 2E8",
    "sg:province":"ON",
    "sg:tags":[
        "television",
        "radio"
    ],
    "wof:name":"Hill's Tv & Audio",
    "wof:placetype":"venue"
},
  "geometry": {"coordinates":[-79.83007000000001,43.323875],"type":"Point"}
}