{
  "type": "Feature",
  "properties": {
    "addr:full":"325 Jubilee St Duncan BC V9L 1W9",
    "addr:housenumber":"325",
    "addr:postcode":"v9l 1w9",
    "addr:street":"Jubilee St",
    "iso:country":"CA",
    "sg:address":"325 Jubilee St",
    "sg:city":"Duncan",
    "sg:classifiers":[
        {
            "category":"Shopping",
            "subcategory":"Pharmacy",
            "type":"Retail Goods"
        }
    ],
    "sg:phone":"+1 250 746 7168",
    "sg:postcode":"V9L 1W9",
    "sg:province":"BC",
    "wof:name":"Mann's Prescription Pharmacy",
    "wof:placetype":"venue"
},
  "geometry": {"coordinates":[-123.71072387700001,48.7794342041],"type":"Point"}
}