{
  "type": "Feature",
  "properties": {
    "addr:full":"RR 5 Warkworth ON K0K 3K0",
    "addr:postcode":"k0k 3k0",
    "addr:street":"Rr 5",
    "iso:country":"CA",
    "sg:address":"RR 5",
    "sg:city":"Warkworth",
    "sg:classifiers":[
        {
            "category":"Professional",
            "subcategory":"Research",
            "type":"Services"
        }
    ],
    "sg:phone":"+1 705 924 1570",
    "sg:postcode":"K0K 3K0",
    "sg:province":"ON",
    "sg:tags":[
        "market",
        "analysis"
    ],
    "wof:name":"Envision Marketing Research",
    "wof:placetype":"venue"
},
  "geometry": {"coordinates":[-77.8898468018,44.2007331848],"type":"Point"}
}