{
  "type": "Feature",
  "properties": {
    "addr:full":"5008 50 St Red Deer AB T4N 1Y3",
    "addr:housenumber":"5008",
    "addr:postcode":"t4n 1y3",
    "addr:street":"50 St",
    "iso:country":"CA",
    "sg:address":"5008 50 St",
    "sg:city":"Red Deer",
    "sg:classifiers":[
        {
            "category":"Personal",
            "subcategory":"Beauty Salon",
            "type":"Services"
        }
    ],
    "sg:phone":"+1 403 342 1110",
    "sg:postcode":"T4N 1Y3",
    "sg:province":"AB",
    "wof:name":"Marvel College",
    "wof:placetype":"venue"
},
  "geometry": {"coordinates":[-113.816154,52.269016],"type":"Point"}
}