{
  "type": "Feature",
  "properties": {
    "addr:full":"1494 Erin St Winnipeg MB R3E 2S8",
    "addr:housenumber":"1494",
    "addr:postcode":"r3e 2s8",
    "addr:street":"Erin St",
    "iso:country":"CA",
    "sg:address":"1494 Erin St",
    "sg:city":"Winnipeg",
    "sg:classifiers":[
        {
            "category":"Retail",
            "subcategory":"Auto Repair",
            "type":"Services"
        }
    ],
    "sg:phone":"+1 204 775 6393",
    "sg:postcode":"R3E 2S8",
    "sg:province":"MB",
    "sg:tags":[
        "body",
        "automobile",
        "painting"
    ],
    "wof:name":"Arlington Auto Body Ltd",
    "wof:placetype":"venue"
},
  "geometry": {"coordinates":[-97.1838684082,49.9036331177],"type":"Point"}
}