{
  "type": "Feature",
  "properties": {
    "addr:full":"13652 Grosvenor Rd Surrey BC V3R 5C9",
    "addr:housenumber":"13652",
    "addr:postcode":"v3r 5c9",
    "addr:street":"Grosvenor Rd",
    "iso:country":"CA",
    "sg:address":"13652 Grosvenor Rd",
    "sg:city":"Surrey",
    "sg:classifiers":[
        {
            "category":"Personal",
            "subcategory":"Tattoo Parlor",
            "type":"Services"
        }
    ],
    "sg:phone":"+1 604 582 7222",
    "sg:postcode":"V3R 5C9",
    "sg:province":"BC",
    "sg:tags":[
        "tattooing"
    ],
    "wof:name":"Dragon Tattoo",
    "wof:placetype":"venue"
},
  "geometry": {"coordinates":[-122.843872,49.199749],"type":"Point"}
}