{
  "type": "Feature",
  "properties": {
    "addr:full":"94 Crescent Rd Toronto ON M4W 1T5",
    "addr:housenumber":"94",
    "addr:postcode":"m4w 1t5",
    "addr:street":"Crescent Rd",
    "iso:country":"CA",
    "sg:address":"94 Crescent Rd",
    "sg:city":"Toronto",
    "sg:classifiers":[
        {
            "category":"Professional",
            "subcategory":"Business Services",
            "type":"Services"
        }
    ],
    "sg:phone":"+1 416 944 9114",
    "sg:postcode":"M4W 1T5",
    "sg:province":"ON",
    "sg:tags":[
        "interior",
        "consultant",
        "design",
        "decorator"
    ],
    "wof:name":"Judith Pierce Interiors",
    "wof:placetype":"venue"
},
  "geometry": {"coordinates":[-79.38365899999999,43.678143],"type":"Point"}
}