{
  "type": "Feature",
  "properties": {
    "addr:full":"St Albert AB T8N 3K8",
    "addr:postcode":"t8n 3k8",
    "iso:country":"CA",
    "sg:city":"St Albert",
    "sg:classifiers":[
        {
            "category":"Shopping",
            "subcategory":"Clothing, Apparel, & Fashions",
            "type":"Retail Goods"
        }
    ],
    "sg:phone":"+1 780 458 0004",
    "sg:postcode":"T8N 3K8",
    "sg:province":"AB",
    "sg:tags":[
        "furnishing"
    ],
    "wof:name":"Tip Top Tailors",
    "wof:placetype":"venue"
},
  "geometry": {"coordinates":[-113.624825,53.640888],"type":"Point"}
}