{
  "type": "Feature",
  "properties": {
    "addr:full":"5011 50 St Stony Plain AB T7Z 1T3",
    "addr:housenumber":"5011",
    "addr:postcode":"t7z 1t3",
    "addr:street":"50 St",
    "iso:country":"CA",
    "sg:address":"5011 50 St",
    "sg:city":"Stony Plain",
    "sg:classifiers":[
        {
            "category":"Real Estate",
            "subcategory":"Real Estate Agent",
            "type":"Services"
        }
    ],
    "sg:phone":"+1 780 428 0841",
    "sg:postcode":"T7Z 1T3",
    "sg:province":"AB",
    "wof:name":"Decker Realty Inc",
    "wof:placetype":"venue"
},
  "geometry": {"coordinates":[-114.006958,53.529461],"type":"Point"}
}