{
  "type": "Feature",
  "properties": {
    "addr:full":"Saint-Hyacinthe QC J2T 3H1",
    "addr:postcode":"j2t 3h1",
    "iso:country":"CA",
    "sg:city":"Saint-Hyacinthe",
    "sg:classifiers":[
        {
            "category":"Health Services",
            "subcategory":"Health Practitioner",
            "type":"Services"
        }
    ],
    "sg:phone":"+1 450 774 8620",
    "sg:postcode":"J2T 3H1",
    "sg:province":"QC",
    "sg:tags":[
        "medicine",
        "orthopedic"
    ],
    "wof:name":"Clinique D'Orthotherapie Rm",
    "wof:placetype":"venue"
},
  "geometry": {"coordinates":[-72.925056,45.618412],"type":"Point"}
}