{
  "type": "Feature",
  "properties": {
    "addr:full":"6 Yule Ave Toronto ON M6S 1E8",
    "addr:housenumber":"6",
    "addr:postcode":"m6s 1e8",
    "addr:street":"Yule Ave",
    "iso:country":"CA",
    "sg:address":"6 Yule Ave",
    "sg:city":"Toronto",
    "sg:classifiers":[
        {
            "category":"Professional",
            "subcategory":"Art Services",
            "type":"Services"
        }
    ],
    "sg:phone":"+1 416 761 1737",
    "sg:postcode":"M6S 1E8",
    "sg:province":"ON",
    "sg:tags":[
        "graphic",
        "designer"
    ],
    "wof:name":"Malcolm Waddell Assoc Ltd",
    "wof:placetype":"venue"
},
  "geometry": {"coordinates":[-79.4791793823,43.6464729309],"type":"Point"}
}