{
  "type": "Feature",
  "properties": {
    "addr:full":"1001 Boul DE Montarville #51 Boucherville QC J4B 6P5",
    "addr:housenumber":"1001",
    "addr:postcode":"j4b 6p5",
    "addr:street":"Boul De Montarville # 51",
    "iso:country":"CA",
    "sg:address":"1001 Boul DE Montarville #51",
    "sg:city":"Boucherville",
    "sg:classifiers":[
        {
            "category":"Cinema",
            "subcategory":"Movie Rental",
            "type":"Entertainment"
        }
    ],
    "sg:phone":"+1 450 641 3550",
    "sg:postcode":"J4B 6P5",
    "sg:province":"QC",
    "sg:tags":[
        "leasing",
        "video",
        "disc",
        "tape"
    ],
    "wof:name":"Blockbuster Video",
    "wof:placetype":"venue"
},
  "geometry": {"coordinates":[-73.4341201782,45.5898475647],"type":"Point"}
}