{
  "type": "Feature",
  "properties": {
    "addr:full":"4292 John St Vancouver BC V5V 3W7",
    "addr:housenumber":"4292",
    "addr:postcode":"v5v 3w7",
    "addr:street":"John St",
    "iso:country":"CA",
    "sg:address":"4292 John St",
    "sg:city":"Vancouver",
    "sg:classifiers":[
        {
            "category":"Organizations",
            "subcategory":"Religious Organization",
            "type":"Services"
        }
    ],
    "sg:phone":"+1 604 874 2217",
    "sg:postcode":"V5V 3W7",
    "sg:province":"BC",
    "sg:tags":[
        "church"
    ],
    "wof:name":"Community Spiritualist Church",
    "wof:placetype":"venue"
},
  "geometry": {"coordinates":[-123.09703064,49.246837616],"type":"Point"}
}