{
  "type": "Feature",
  "properties": {
    "addr:full":"1948 Windsor Rd Kelowna BC V1Y 4R5",
    "addr:housenumber":"1948",
    "addr:postcode":"v1y 4r5",
    "addr:street":"Windsor Rd",
    "iso:country":"CA",
    "sg:address":"1948 Windsor Rd",
    "sg:city":"Kelowna",
    "sg:classifiers":[
        {
            "category":"Retail",
            "subcategory":"Auto Repair",
            "type":"Services"
        }
    ],
    "sg:phone":"+1 250 860 3925",
    "sg:postcode":"V1Y 4R5",
    "sg:province":"BC",
    "sg:tags":[
        "repairing",
        "automobile",
        "muffler",
        "system",
        "exhaust"
    ],
    "wof:name":"Jerry's Carline Mufflers",
    "wof:placetype":"venue"
},
  "geometry": {"coordinates":[-119.45271301299999,49.8805732727],"type":"Point"}
}