{
  "type": "Feature",
  "properties": {
    "iso:country":"CA",
    "sg:address":"1230 Rue Peel",
    "sg:city":"Montreal",
    "sg:classifiers":[
        {
            "category":"Banks & Credit Unions",
            "subcategory":"Bank",
            "type":"Services"
        }
    ],
    "sg:phone":"+1 514 397 9997",
    "sg:postcode":"H3B 2T6",
    "sg:province":"QC",
    "sg:tags":[
        "currency",
        "broker",
        "foreign",
        "dealer",
        "exchange"
    ],
    "wof:name":"Alpha Forex Inc",
    "wof:placetype":"venue"
},
  "geometry": {"coordinates":[-73.5723953247,45.4996299744],"type":"Point"}
}