{
  "type": "Feature",
  "properties": {
    "addr:full":"1581 Rue Royale Trois-Rivieres QC G9A 4J9",
    "addr:housenumber":"1581",
    "addr:postcode":"g9a 4j9",
    "addr:street":"Rue Royale",
    "iso:country":"CA",
    "sg:address":"1581 Rue Royale",
    "sg:city":"Trois-Rivieres",
    "sg:classifiers":[
        {
            "category":"Professional",
            "subcategory":"Engineering",
            "type":"Services"
        }
    ],
    "sg:phone":"+1 819 372 3366",
    "sg:postcode":"G9A 4J9",
    "sg:province":"QC",
    "sg:tags":[
        "town",
        "city",
        "regional",
        "planner",
        "engineer"
    ],
    "wof:name":"Bendwell & Assoc Inc",
    "wof:placetype":"venue"
},
  "geometry": {"coordinates":[-72.544464,46.341568],"type":"Point"}
}