{
  "type": "Feature",
  "properties": {
    "addr:full":"7033 Macpherson Ave Burnaby BC V5J 4N4",
    "addr:housenumber":"7033",
    "addr:postcode":"v5j 4n4",
    "addr:street":"Macpherson Ave",
    "iso:country":"CA",
    "sg:address":"7033 Macpherson Ave",
    "sg:city":"Burnaby",
    "sg:classifiers":[
        {
            "category":"Retail",
            "subcategory":"Car Wash",
            "type":"Services"
        }
    ],
    "sg:phone":"+1 604 439 8817",
    "sg:postcode":"V5J 4N4",
    "sg:province":"BC",
    "sg:tags":[
        "polishing",
        "automobile",
        "washing",
        "detail",
        "clean"
    ],
    "wof:name":"Ajs Auto Cosmetic Ctr",
    "wof:placetype":"venue"
},
  "geometry": {"coordinates":[-122.982941,49.221931],"type":"Point"}
}