{
  "type": "Feature",
  "properties": {
    "addr:full":"Burns Lake BC V0J 1E0",
    "addr:postcode":"bc v0j 1e0",
    "addr:street":"Burns Lake",
    "iso:country":"CA",
    "sg:city":"Burns Lake",
    "sg:classifiers":[
        {
            "category":"Recreation",
            "type":"Entertainment"
        }
    ],
    "sg:phone":"+1 250 695 6519",
    "sg:postcode":"V0J 1E0",
    "sg:province":"BC",
    "sg:tags":[
        "campground",
        "party",
        "fishing"
    ],
    "wof:name":"Beaver Point Resort",
    "wof:placetype":"venue"
},
  "geometry": {"coordinates":[-125.758537,54.2267],"type":"Point"}
}