{
  "type": "Feature",
  "properties": {
    "addr:full":"50 Duffy Pl St. John's NL A1B 4M5",
    "addr:housenumber":"50",
    "addr:postcode":"a1b 4m5",
    "addr:street":"Duffy Pl",
    "iso:country":"CA",
    "sg:address":"50 Duffy Pl",
    "sg:city":"St. John's",
    "sg:classifiers":[
        {
            "category":"Banks & Credit Unions",
            "subcategory":"Bank",
            "type":"Services"
        }
    ],
    "sg:phone":"+1 709 737 5624",
    "sg:postcode":"A1B 4M5",
    "sg:province":"NL",
    "wof:name":"Reddy Kilowatt Credit Union",
    "wof:placetype":"venue"
},
  "geometry": {"coordinates":[-52.776482,47.561096],"type":"Point"}
}