{
  "type": "Feature",
  "properties": {
    "addr:full":"Windsor ON N8Y 4V3",
    "addr:postcode":"n8y 4v3",
    "iso:country":"CA",
    "sg:city":"Windsor",
    "sg:classifiers":[
        {
            "category":"Real Estate",
            "subcategory":"Real Estate Operator",
            "type":"Services"
        }
    ],
    "sg:phone":"+1 519 944 6655",
    "sg:postcode":"N8Y 4V3",
    "sg:province":"ON",
    "sg:tags":[
        "condominium"
    ],
    "wof:name":"Essex Condominium Corp",
    "wof:placetype":"venue"
},
  "geometry": {"coordinates":[-82.99321,42.326656],"type":"Point"}
}