{
  "type": "Feature",
  "properties": {
    "addr:full":"1490 7th Ave Valemount BC V0E 2Z0",
    "addr:housenumber":"1490",
    "addr:postcode":"v0e 2z0",
    "addr:street":"7Th Ave",
    "iso:country":"CA",
    "sg:address":"1490 7th Ave",
    "sg:city":"Valemount",
    "sg:classifiers":[
        {
            "category":"Restaurant",
            "type":"Food & Drink"
        }
    ],
    "sg:phone":"+1 250 566 4345",
    "sg:postcode":"V0E 2Z0",
    "sg:province":"BC",
    "wof:name":"Sarak Restaurant",
    "wof:placetype":"venue"
},
  "geometry": {"coordinates":[-119.26284,52.83033],"type":"Point"}
}