{
  "type": "Feature",
  "properties": {
    "addr:full":"293 St George's Ave E Sault Ste Marie ON P6B 6E8",
    "addr:housenumber":"293",
    "addr:postcode":"p6b 6e8",
    "addr:street":"St George'S Ave E",
    "iso:country":"CA",
    "sg:address":"293 St George's Ave E",
    "sg:city":"Sault Ste Marie",
    "sg:classifiers":[
        {
            "category":"Organizations",
            "subcategory":"Religious Organization",
            "type":"Services"
        }
    ],
    "sg:phone":"+1 705 942 1377",
    "sg:postcode":"P6B 6E8",
    "sg:province":"ON",
    "sg:tags":[
        "church"
    ],
    "wof:name":"St Mary's Ukrainian Catholic",
    "wof:placetype":"venue"
},
  "geometry": {"coordinates":[-84.2667541504,46.5154533386],"type":"Point"}
}