{
  "type": "Feature",
  "properties": {
    "addr:full":"Mancebourg QC J0Z 2T0",
    "addr:postcode":"j0z 2t0",
    "iso:country":"CA",
    "sg:city":"Mancebourg",
    "sg:classifiers":[
        {
            "category":"Farming",
            "subcategory":"Livestock Farm",
            "type":"Manufacturing & Wholesale Goods"
        }
    ],
    "sg:phone":"+1 819 333 6004",
    "sg:postcode":"J0Z 2T0",
    "sg:province":"QC",
    "sg:tags":[
        "circus",
        "broker",
        "animal",
        "dealer"
    ],
    "wof:name":"Mario Pouliot Entreprises Inc",
    "wof:placetype":"venue"
},
  "geometry": {"coordinates":[-79.328812,48.750423],"type":"Point"}
}