{
  "type": "Feature",
  "properties": {
    "addr:full":"10 Canvarco Rd East York ON M4G 1L3",
    "addr:housenumber":"10",
    "addr:postcode":"m4g 1l3",
    "addr:street":"Canvarco Rd",
    "iso:country":"CA",
    "sg:address":"10 Canvarco Rd",
    "sg:city":"East York",
    "sg:classifiers":[
        {
            "category":"Building & Trades",
            "subcategory":"Construction",
            "type":"Services"
        }
    ],
    "sg:phone":"+1 416 429 2370",
    "sg:postcode":"M4G 1L3",
    "sg:province":"ON",
    "sg:tags":[
        "woodworker"
    ],
    "wof:name":"Barefoot Woodworks",
    "wof:placetype":"venue"
},
  "geometry": {"coordinates":[-79.3602142334,43.7040710449],"type":"Point"}
}