{
  "type": "Feature",
  "properties": {
    "addr:full":"1126 Ch Saint-Dominique Les Cedres QC J7T 1P4",
    "addr:housenumber":"1126",
    "addr:postcode":"j7t 1p4",
    "addr:street":"Ch Saint-Dominique",
    "iso:country":"CA",
    "sg:address":"1126 Ch Saint-Dominique",
    "sg:city":"Les Cedres",
    "sg:classifiers":[
        {
            "category":"Building & Trades",
            "subcategory":"Construction",
            "type":"Services"
        }
    ],
    "sg:phone":"+1 450 452 2442",
    "sg:postcode":"J7T 1P4",
    "sg:province":"QC",
    "sg:tags":[
        "excavating",
        "contractor"
    ],
    "wof:name":"Laventure Excavation Inc",
    "wof:placetype":"venue"
},
  "geometry": {"coordinates":[-74.14225,45.349678],"type":"Point"}
}