{
  "type": "Feature",
  "properties": {
    "addr:full":"2900 Norwell Dr Nanaimo BC V9T 1X3",
    "addr:postcode":"2900;v9t 1x3",
    "addr:street":"Norwell Dr",
    "iso:country":"CA",
    "sg:address":"2900 Norwell Dr",
    "sg:city":"Nanaimo",
    "sg:classifiers":[
        {
            "category":"Shopping",
            "subcategory":"Computers & Home Electronics",
            "type":"Retail Goods"
        }
    ],
    "sg:phone":"+1 250 758 8555",
    "sg:postcode":"V9T 1X3",
    "sg:province":"BC",
    "sg:tags":[
        "equipment",
        "dealer"
    ],
    "wof:name":"Amerl Computer Ctr",
    "wof:placetype":"venue"
},
  "geometry": {"coordinates":[-124.001617,49.205791],"type":"Point"}
}