{
  "type": "Feature",
  "properties": {
    "iso:country":"CA",
    "sg:address":"7751 Rue Saint-Hubert",
    "sg:city":"Montreal",
    "sg:classifiers":[
        {
            "category":"Restaurant",
            "type":"Food & Drink"
        }
    ],
    "sg:phone":"+1 514 277 3333",
    "sg:postcode":"H2R 2P1",
    "sg:province":"QC",
    "wof:name":"Monsieur Hotdog Plus",
    "wof:placetype":"venue"
},
  "geometry": {"coordinates":[-73.6217041016,45.544670105],"type":"Point"}
}