{
  "type": "Feature",
  "properties": {
    "addr:full":"700 Industrial Ave # 600 Ottawa ON K1G 0Y9",
    "addr:housenumber":"700",
    "addr:postcode":"k1g 0y9",
    "addr:street":"Industrial Ave # 600",
    "iso:country":"CA",
    "sg:address":"700 Industrial Ave # 600",
    "sg:city":"Ottawa",
    "sg:classifiers":[
        {
            "category":"Social Services",
            "subcategory":"Child Care",
            "type":"Services"
        }
    ],
    "sg:phone":"+1 613 736 5355",
    "sg:postcode":"K1G 0Y9",
    "sg:province":"ON",
    "wof:name":"Andrew Fleck Child Care Svc",
    "wof:placetype":"venue"
},
  "geometry": {"coordinates":[-75.638153,45.409935],"type":"Point"}
}