{
  "type": "Feature",
  "properties": {
    "addr:full":"11 Rue Des Camionneurs Degelis QC G5T 2G9",
    "addr:housenumber":"11",
    "addr:postcode":"g5t 2g9",
    "addr:street":"Rue Des Camionneurs Degelis",
    "iso:country":"CA",
    "sg:address":"11 Rue Des Camionneurs",
    "sg:city":"Degelis",
    "sg:classifiers":[
        {
            "category":"Manufacturing",
            "subcategory":"Tools & Machinery",
            "type":"Manufacturing & Wholesale Goods"
        }
    ],
    "sg:phone":"+1 418 853 3664",
    "sg:postcode":"G5T 2G9",
    "sg:province":"QC",
    "sg:tags":[
        "machine",
        "shop"
    ],
    "wof:name":"Usinages Industrielles Degelis",
    "wof:placetype":"venue"
},
  "geometry": {"coordinates":[-68.6268997192,47.5400810242],"type":"Point"}
}