{
  "type": "Feature",
  "properties": {
    "addr:full":"4804 46A Ave Athabasca AB T9S 1B6",
    "addr:housenumber":"4804",
    "addr:postcode":"t9s 1b6",
    "addr:street":"46A Ave",
    "iso:country":"CA",
    "sg:address":"4804 46A Ave",
    "sg:city":"Athabasca",
    "sg:classifiers":[
        {
            "category":"Travel",
            "subcategory":"Hotels & Motels",
            "type":"Entertainment"
        }
    ],
    "sg:phone":"+1 780 675 5111",
    "sg:postcode":"T9S 1B6",
    "sg:province":"AB",
    "wof:name":"Athabasca Hillside Motel",
    "wof:placetype":"venue"
},
  "geometry": {"coordinates":[-113.28295900000001,54.71492],"type":"Point"}
}