{
  "type": "Feature",
  "properties": {
    "addr:full":"4732 45A St Lacombe AB T4L 2C7",
    "addr:housenumber":"4732",
    "addr:postcode":"t4l 2c7",
    "addr:street":"45A St",
    "iso:country":"CA",
    "sg:address":"4732 45A St",
    "sg:city":"Lacombe",
    "sg:classifiers":[
        {
            "category":"Manufacturing",
            "subcategory":"Tools & Machinery",
            "type":"Manufacturing & Wholesale Goods"
        }
    ],
    "sg:phone":"+1 403 782 7330",
    "sg:postcode":"T4L 2C7",
    "sg:province":"AB",
    "sg:tags":[
        "machine",
        "shop"
    ],
    "wof:name":"Can-Rapid Ltd",
    "wof:placetype":"venue"
},
  "geometry": {"coordinates":[-113.728371,52.458744],"type":"Point"}
}