{
  "type": "Feature",
  "properties": {
    "addr:full":"5540 Kaye St Halifax NS B3K 1Y5",
    "addr:housenumber":"5540",
    "addr:postcode":"b3k 1y5",
    "addr:street":"Kaye St",
    "iso:country":"CA",
    "sg:address":"5540 Kaye St",
    "sg:city":"Halifax",
    "sg:classifiers":[
        {
            "category":"Building & Trades",
            "subcategory":"Construction",
            "type":"Services"
        }
    ],
    "sg:phone":"+1 902 455 7866",
    "sg:postcode":"B3K 1Y5",
    "sg:province":"NS",
    "sg:tags":[
        "solarium"
    ],
    "wof:name":"Four Seasons Sunrooms",
    "wof:placetype":"venue"
},
  "geometry": {"coordinates":[-63.5992164612,44.6616363525],"type":"Point"}
}