{
  "type": "Feature",
  "properties": {
    "addr:full":"1496 Cartwright St #23 Vancouver BC V6H 3Y5",
    "addr:housenumber":"1496",
    "addr:postcode":"v6h 3y5",
    "addr:street":"Cartwright St # 23",
    "iso:country":"CA",
    "sg:address":"1496 Cartwright St #23",
    "sg:city":"Vancouver",
    "sg:classifiers":[
        {
            "category":"Shopping",
            "subcategory":"Books",
            "type":"Retail Goods"
        }
    ],
    "sg:phone":"+1 604 683 7009",
    "sg:postcode":"V6H 3Y5",
    "sg:province":"BC",
    "sg:tags":[
        "dealer"
    ],
    "wof:name":"Humpty Dumpty Books & Music",
    "wof:placetype":"venue"
},
  "geometry": {"coordinates":[-123.135963,49.270515],"type":"Point"}
}