{
  "type": "Feature",
  "properties": {
    "addr:full":"London ON N5V 4A3",
    "addr:postcode":"n5v 4a3",
    "iso:country":"CA",
    "sg:city":"London",
    "sg:classifiers":[
        {
            "category":"Manufacturing",
            "subcategory":"Food",
            "type":"Manufacturing & Wholesale Goods"
        }
    ],
    "sg:phone":"+1 519 659 7758",
    "sg:postcode":"N5V 4A3",
    "sg:province":"ON",
    "sg:tags":[
        "grocer",
        "product",
        "manufacturer"
    ],
    "wof:name":"New Kampong Spei",
    "wof:placetype":"venue"
},
  "geometry": {"coordinates":[-81.18673699999999,43.02832],"type":"Point"}
}