{
  "type": "Feature",
  "properties": {
    "iso:country":"CA",
    "sg:address":"Main St",
    "sg:city":"Weekes",
    "sg:classifiers":[
        {
            "category":"Travel",
            "subcategory":"Hotels & Motels",
            "type":"Entertainment"
        }
    ],
    "sg:phone":"+1 306 278 3048",
    "sg:postcode":"S0E 1V0",
    "sg:province":"SK",
    "wof:name":"Weekes Hotel",
    "wof:placetype":"venue"
},
  "geometry": {"coordinates":[-102.87030792199999,52.5708961487],"type":"Point"}
}