{
  "type": "Feature",
  "properties": {
    "iso:country":"CA",
    "sg:address":"500 Av Du Mont-Royal E",
    "sg:city":"Montreal",
    "sg:classifiers":[
        {
            "category":"Organizations",
            "subcategory":"Religious Organization",
            "type":"Services"
        }
    ],
    "sg:phone":"+1 514 528 7033",
    "sg:postcode":"H2J 1W5",
    "sg:province":"QC",
    "sg:tags":[
        "church"
    ],
    "wof:name":"Relais Mont-Royal",
    "wof:placetype":"venue"
},
  "geometry": {"coordinates":[-73.5819244385,45.5249862671],"type":"Point"}
}