{
  "type": "Feature",
  "properties": {
    "addr:full":"239 Rue Seigneuriale Beauport QC G1E 4Y8",
    "addr:housenumber":"239",
    "addr:postcode":"qc g1e 4y8",
    "addr:street":"Rue Seigneuriale",
    "iso:country":"CA",
    "sg:address":"239 Rue Seigneuriale",
    "sg:city":"Beauport",
    "sg:classifiers":[
        {
            "category":"Restaurant",
            "type":"Food & Drink"
        }
    ],
    "sg:phone":"+1 418 661 7171",
    "sg:postcode":"G1E 4Y8",
    "sg:province":"QC",
    "wof:name":"Restaurant LA Belle Province",
    "wof:placetype":"venue"
},
  "geometry": {"coordinates":[-71.19548,46.872978],"type":"Point"}
}