{
  "type": "Feature",
  "properties": {
    "addr:full":"175 Bethridge Rd Etobicoke ON M9W 1N4",
    "addr:housenumber":"175",
    "addr:postcode":"m9w 1n4",
    "addr:street":"Bethridge Rd",
    "iso:country":"CA",
    "sg:address":"175 Bethridge Rd",
    "sg:city":"Etobicoke",
    "sg:classifiers":[
        {
            "category":"Building & Trades",
            "subcategory":"Construction",
            "type":"Services"
        }
    ],
    "sg:phone":"+1 416 743 3224",
    "sg:postcode":"M9W 1N4",
    "sg:province":"ON",
    "sg:tags":[
        "paving",
        "contractor"
    ],
    "wof:name":"Mso Construction Ltd",
    "wof:placetype":"venue"
},
  "geometry": {"coordinates":[-79.5851135254,43.708316803],"type":"Point"}
}