{
  "type": "Feature",
  "properties": {
    "addr:full":"3901 Rue DE Verdun Verdun QC H4G 1L1",
    "addr:housenumber":"3901",
    "addr:postcode":"h4g 1l1",
    "addr:street":"Rue De Verdun",
    "iso:country":"CA",
    "sg:address":"3901 Rue DE Verdun",
    "sg:city":"Verdun",
    "sg:classifiers":[
        {
            "category":"Cinema",
            "subcategory":"Movie Rental",
            "type":"Entertainment"
        }
    ],
    "sg:phone":"+1 514 762 5683",
    "sg:postcode":"H4G 1L1",
    "sg:province":"QC",
    "sg:tags":[
        "leasing",
        "video",
        "disc",
        "tape"
    ],
    "wof:name":"Video Ninja",
    "wof:placetype":"venue"
},
  "geometry": {"coordinates":[-73.5714187622,45.4648895264],"type":"Point"}
}