{
  "type": "Feature",
  "properties": {
    "addr:full":"102 2nd Ave E Shellbrook SK S0J 2E0",
    "addr:housenumber":"102",
    "addr:postcode":"s0j 2e0",
    "addr:street":"2Nd Ave E Shellbrook",
    "iso:country":"CA",
    "sg:address":"102 2nd Ave E",
    "sg:city":"Shellbrook",
    "sg:classifiers":[
        {
            "category":"Organizations",
            "subcategory":"Religious Organization",
            "type":"Services"
        }
    ],
    "sg:phone":"+1 306 747 2595",
    "sg:postcode":"S0J 2E0",
    "sg:province":"SK",
    "sg:tags":[
        "church"
    ],
    "wof:name":"Anglican Church",
    "wof:placetype":"venue"
},
  "geometry": {"coordinates":[-106.387123,53.220356],"type":"Point"}
}