{
  "type": "Feature",
  "properties": {
    "iso:country":"CA",
    "sg:city":"Vancouver",
    "sg:classifiers":[
        {
            "category":"Health Services",
            "subcategory":"Doctor",
            "type":"Services"
        }
    ],
    "sg:phone":"+1 604 739 8858",
    "sg:postcode":"V6K 4M1",
    "sg:province":"BC",
    "sg:tags":[
        "physician",
        "surgeon"
    ],
    "wof:name":"Pilar, Saul MD",
    "wof:placetype":"venue"
},
  "geometry": {"coordinates":[-123.167510986,49.2575187683],"type":"Point"}
}