{
  "type": "Feature",
  "properties": {
    "addr:full":"Highway 6 Pugwash NS B0K 1L0",
    "addr:postcode":"b0k 1l0",
    "addr:street":"Highway 6",
    "iso:country":"CA",
    "sg:address":"Highway 6",
    "sg:city":"Pugwash",
    "sg:classifiers":[
        {
            "category":"Wholesale",
            "subcategory":"Scrap",
            "type":"Manufacturing & Wholesale Goods"
        }
    ],
    "sg:phone":"+1 902 243 2665",
    "sg:postcode":"B0K 1L0",
    "sg:province":"NS",
    "sg:tags":[
        "recycling",
        "center"
    ],
    "wof:name":"Keep Garbage Benefical",
    "wof:placetype":"venue"
},
  "geometry": {"coordinates":[-63.6613349915,45.8495063782],"type":"Point"}
}