{
  "type": "Feature",
  "properties": {
    "addr:full":"8 Redwood Ave Halifax NS B3P 1Y4",
    "addr:housenumber":"8",
    "addr:postcode":"b3p 1y4",
    "addr:street":"Redwood Ave",
    "iso:country":"CA",
    "sg:address":"8 Redwood Ave",
    "sg:city":"Halifax",
    "sg:classifiers":[
        {
            "category":"Wholesale",
            "subcategory":"Durable Goods & Equipment",
            "type":"Manufacturing & Wholesale Goods"
        }
    ],
    "sg:phone":"+1 902 455 6665",
    "sg:postcode":"B3P 1Y4",
    "sg:province":"NS",
    "sg:tags":[
        "representative",
        "manufacturer"
    ],
    "wof:name":"Add-Tek Agencies Ltd",
    "wof:placetype":"venue"
},
  "geometry": {"coordinates":[-63.6098098755,44.6293296814],"type":"Point"}
}