{
  "type": "Feature",
  "properties": {
    "addr:full":"525 Head St Victoria BC V9A 5S1",
    "addr:housenumber":"525",
    "addr:postcode":"v9a 5s1",
    "addr:street":"Head St",
    "iso:country":"CA",
    "sg:address":"525 Head St",
    "sg:city":"Victoria",
    "sg:classifiers":[
        {
            "category":"Professional",
            "subcategory":"Research",
            "type":"Services"
        }
    ],
    "sg:phone":"+1 250 383 4535",
    "sg:postcode":"V9A 5S1",
    "sg:province":"BC",
    "sg:tags":[
        "environmental",
        "ecological"
    ],
    "wof:name":"Archipelago Marine Research",
    "wof:placetype":"venue"
},
  "geometry": {"coordinates":[-123.364517212,48.428314209],"type":"Point"}
}