{
  "type": "Feature",
  "properties": {
    "iso:country":"CA",
    "sg:address":"3315 Ch Queen-Mary",
    "sg:city":"Montreal",
    "sg:classifiers":[
        {
            "category":"Restaurant",
            "type":"Food & Drink"
        }
    ],
    "sg:phone":"+1 514 738 1887",
    "sg:postcode":"H3V 1A1",
    "sg:province":"QC",
    "sg:tags":[
        "shop",
        "coffee"
    ],
    "wof:name":"Second Cup",
    "wof:placetype":"venue"
},
  "geometry": {"coordinates":[-73.6178283691,45.4966201782],"type":"Point"}
}