{
  "type": "Feature",
  "properties": {
    "addr:full":"5982 Trans Canada Hwy Duncan BC V9L 6C8",
    "addr:housenumber":"5982",
    "addr:postcode":"v9l 6c8",
    "addr:street":"Trans Canada Hwy",
    "iso:country":"CA",
    "sg:address":"5982 Trans Canada Hwy",
    "sg:city":"Duncan",
    "sg:classifiers":[
        {
            "category":"Wholesale",
            "subcategory":"Hardware",
            "type":"Manufacturing & Wholesale Goods"
        }
    ],
    "sg:phone":"+1 250 746 2343",
    "sg:postcode":"V9L 6C8",
    "sg:province":"BC",
    "sg:tags":[
        "tool"
    ],
    "wof:name":"Ritchie Distributors",
    "wof:placetype":"venue"
},
  "geometry": {"coordinates":[-123.69882200000001,48.780491],"type":"Point"}
}