{
  "type": "Feature",
  "properties": {
    "addr:full":"11809 Cygnet Blvd Grande Prairie AB T8X 1J4",
    "addr:housenumber":"11809",
    "addr:postcode":"t8x 1j4",
    "addr:street":"Cygnet Blvd",
    "iso:country":"CA",
    "sg:address":"11809 Cygnet Blvd",
    "sg:city":"Grande Prairie",
    "sg:classifiers":[
        {
            "category":"Arts & Performance",
            "subcategory":"Theater",
            "type":"Entertainment"
        }
    ],
    "sg:phone":"+1 780 532 4735",
    "sg:postcode":"T8X 1J4",
    "sg:province":"AB",
    "sg:tags":[
        "live",
        "music"
    ],
    "wof:name":"Partie Sound Music & Video",
    "wof:placetype":"venue"
},
  "geometry": {"coordinates":[-118.763451,55.187172],"type":"Point"}
}