{
  "type": "Feature",
  "properties": {
    "addr:full":"175 Rue Desbiens Causapscal QC G0J 1J0",
    "addr:housenumber":"175",
    "addr:postcode":"g0j 1j0",
    "addr:street":"Rue Desbiens",
    "iso:country":"CA",
    "sg:address":"175 Rue Desbiens",
    "sg:city":"Causapscal",
    "sg:classifiers":[
        {
            "category":"Retail",
            "subcategory":"Funeral Services",
            "type":"Services"
        }
    ],
    "sg:phone":"+1 418 756 5858",
    "sg:postcode":"G0J 1J0",
    "sg:province":"QC",
    "sg:tags":[
        "director"
    ],
    "wof:name":"Georges Fournier & Fils Inc",
    "wof:placetype":"venue"
},
  "geometry": {"coordinates":[-67.228714,48.359695],"type":"Point"}
}