{
  "type": "Feature",
  "properties": {
    "iso:country":"CA",
    "sg:address":"80 Carlauren Rd",
    "sg:city":"Woodbridge",
    "sg:classifiers":[
        {
            "category":"Manufacturing",
            "subcategory":"Tools & Machinery",
            "type":"Manufacturing & Wholesale Goods"
        }
    ],
    "sg:phone":"+1 905 850 0300",
    "sg:postcode":"L4L 7Z5",
    "sg:province":"ON",
    "sg:tags":[
        "carpet",
        "cleaning",
        "rug"
    ],
    "wof:name":"Cleanmore Equipment & Supplies",
    "wof:placetype":"venue"
},
  "geometry": {"coordinates":[-79.546967,43.799152],"type":"Point"}
}