{
  "type": "Feature",
  "properties": {
    "iso:country":"CA",
    "sg:address":"200 Rue Berlioz",
    "sg:city":"Verdun",
    "sg:classifiers":[
        {
            "category":"Building & Trades",
            "subcategory":"Construction",
            "type":"Services"
        }
    ],
    "sg:phone":"+1 514 769 1077",
    "sg:postcode":"H3E 1L7",
    "sg:province":"QC",
    "sg:tags":[
        "marble",
        "dealer"
    ],
    "wof:name":"Ceramiques Du Sud-Est Inc",
    "wof:placetype":"venue"
},
  "geometry": {"coordinates":[-73.571762,45.459019],"type":"Point"}
}