{
  "type": "Feature",
  "properties": {
    "iso:country":"CA",
    "sg:address":"638 Norfolk St S",
    "sg:city":"Simcoe",
    "sg:classifiers":[
        {
            "category":"Building & Trades",
            "subcategory":"Construction",
            "type":"Services"
        }
    ],
    "sg:phone":"+1 519 426 6810",
    "sg:postcode":"N3Y 4K1",
    "sg:province":"ON",
    "sg:tags":[
        "excavating",
        "contractor"
    ],
    "wof:name":"Gerald B Livingston Excavating",
    "wof:placetype":"venue"
},
  "geometry": {"coordinates":[-80.29578399659999,42.8141021729],"type":"Point"}
}