{
  "type": "Feature",
  "properties": {
    "addr:full":"183 Kennedy St # 200 Winnipeg MB R3C 1S6",
    "addr:housenumber":"183",
    "addr:postcode":"r3c 1s6",
    "addr:street":"Kennedy St # 200",
    "iso:country":"CA",
    "sg:address":"183 Kennedy St # 200",
    "sg:city":"Winnipeg",
    "sg:classifiers":[
        {
            "category":"Organizations",
            "subcategory":"Non-profit Organization",
            "type":"Services"
        }
    ],
    "sg:phone":"+1 204 982 6210",
    "sg:postcode":"R3C 1S6",
    "sg:province":"MB",
    "sg:tags":[
        "bureau",
        "entertainment"
    ],
    "wof:name":"Faces",
    "wof:placetype":"venue"
},
  "geometry": {"coordinates":[-97.146591,49.888939],"type":"Point"}
}