{
  "type": "Feature",
  "properties": {
    "addr:full":"1128 Rue Principale Notre-Dame-DE-Stanbridge QC J0J 1M0",
    "addr:housenumber":"1128",
    "addr:postcode":"j0j 1m0",
    "addr:street":"Rue Principale",
    "iso:country":"CA",
    "sg:address":"1128 Rue Principale",
    "sg:city":"Notre-Dame-DE-Stanbridge",
    "sg:classifiers":[
        {
            "category":"Health Services",
            "subcategory":"Nursing And Care Facility",
            "type":"Services"
        }
    ],
    "sg:phone":"+1 450 296 4458",
    "sg:postcode":"J0J 1M0",
    "sg:province":"QC",
    "sg:tags":[
        "house",
        "retirement",
        "retreat",
        "community",
        "home"
    ],
    "wof:name":"Nid Joyeux Enr",
    "wof:placetype":"venue"
},
  "geometry": {"coordinates":[-73.02727508540001,45.1700286865],"type":"Point"}
}