{
  "type": "Feature",
  "properties": {
    "addr:full":"1244 Av DE LA Montagne E Val-Belair QC G3K 1S4",
    "addr:housenumber":"1244",
    "addr:postcode":"g3k 1s4",
    "addr:street":"Av De La Montagne E Val-Belair",
    "iso:country":"CA",
    "sg:address":"1244 Av DE LA Montagne E",
    "sg:city":"Val-Belair",
    "sg:classifiers":[
        {
            "category":"Building & Trades",
            "subcategory":"Construction",
            "type":"Services"
        }
    ],
    "sg:phone":"+1 418 843 6670",
    "sg:postcode":"G3K 1S4",
    "sg:province":"QC",
    "sg:tags":[
        "masonry",
        "contractor"
    ],
    "wof:name":"Maconneries Michel Ratte Inc",
    "wof:placetype":"venue"
},
  "geometry": {"coordinates":[-71.424744,46.846832],"type":"Point"}
}