{
  "type": "Feature",
  "properties": {
    "iso:country":"CA",
    "sg:city":"Stoney Creek",
    "sg:classifiers":[
        {
            "category":"Professional",
            "subcategory":"Business Services",
            "type":"Services"
        }
    ],
    "sg:phone":"+1 905 664 2221",
    "sg:postcode":"L8E 4P6",
    "sg:province":"ON",
    "sg:tags":[
        "embroidery"
    ],
    "wof:name":"Hamilton Monogram & Embroidery",
    "wof:placetype":"venue"
},
  "geometry": {"coordinates":[-79.7074127197,43.2286605835],"type":"Point"}
}