{
  "type": "Feature",
  "properties": {
    "addr:full":"3730 Fairwinds Dr Nanoose Bay BC V9P 9J6",
    "addr:postcode":"3730;v9p 9j6",
    "addr:street":"Fairwinds Dr",
    "iso:country":"CA",
    "sg:address":"3730 Fairwinds Dr",
    "sg:city":"Nanoose Bay",
    "sg:classifiers":[
        {
            "category":"Restaurant",
            "type":"Food & Drink"
        }
    ],
    "sg:phone":"+1 250 468 7666",
    "sg:postcode":"V9P 9J6",
    "sg:province":"BC",
    "sg:tags":[
        "course",
        "golf"
    ],
    "wof:name":"Fairwinds Golf & Country Club",
    "wof:placetype":"venue"
},
  "geometry": {"coordinates":[-124.131561279,49.277973175],"type":"Point"}
}