{
  "type": "Feature",
  "properties": {
    "addr:full":"9011 Leslie St # 205 Richmond Hill ON L4B 3B6",
    "addr:housenumber":"9011;205",
    "addr:postcode":"l4b 3b6",
    "addr:street":"Leslie St #",
    "iso:country":"CA",
    "sg:address":"9011 Leslie St # 205",
    "sg:city":"Richmond Hill",
    "sg:classifiers":[
        {
            "category":"Education",
            "subcategory":"Special Training",
            "type":"Public Place"
        }
    ],
    "sg:phone":"+1 905 764 9339",
    "sg:postcode":"L4B 3B6",
    "sg:province":"ON",
    "sg:tags":[
        "instruction",
        "music"
    ],
    "wof:name":"Creative Note",
    "wof:placetype":"venue"
},
  "geometry": {"coordinates":[-79.38260650629999,43.8463478088],"type":"Point"}
}