{
  "type": "Feature",
  "properties": {
    "addr:full":"Pictou NS B0K 1H0",
    "addr:postcode":"b0k 1h0",
    "iso:country":"CA",
    "sg:city":"Pictou",
    "sg:classifiers":[
        {
            "category":"Health Services",
            "subcategory":"Doctor",
            "type":"Services"
        }
    ],
    "sg:phone":"+1 902 485 6700",
    "sg:postcode":"B0K 1H0",
    "sg:province":"NS",
    "sg:tags":[
        "physician",
        "surgeon"
    ],
    "wof:name":"Young, Gordon MD",
    "wof:placetype":"venue"
},
  "geometry": {"coordinates":[-62.7070732117,45.6781806946],"type":"Point"}
}