{
  "type": "Feature",
  "properties": {
    "addr:full":"1218 45 Ave NE Calgary AB T2E 2P1",
    "addr:housenumber":"1218",
    "addr:postcode":"t2e 2p1",
    "addr:street":"45 Ave Ne",
    "iso:country":"CA",
    "sg:address":"1218 45 Ave NE",
    "sg:city":"Calgary",
    "sg:classifiers":[
        {
            "category":"Manufacturing",
            "subcategory":"Printing",
            "type":"Manufacturing & Wholesale Goods"
        }
    ],
    "sg:phone":"+1 403 250 9131",
    "sg:postcode":"T2E 2P1",
    "sg:province":"AB",
    "sg:tags":[
        "printer"
    ],
    "wof:name":"Ogilvie Printing Ltd",
    "wof:placetype":"venue"
},
  "geometry": {"coordinates":[-114.03589630099999,51.0934333801],"type":"Point"}
}