{
  "type": "Feature",
  "properties": {
    "addr:full":"7400 Boul Taschereau Brossard QC J4W 1M9",
    "addr:housenumber":"7400",
    "addr:postcode":"j4w 1m9",
    "addr:street":"Boul Taschereau",
    "iso:country":"CA",
    "sg:address":"7400 Boul Taschereau",
    "sg:city":"Brossard",
    "sg:classifiers":[
        {
            "category":"Professional",
            "subcategory":"Advertising",
            "type":"Services"
        }
    ],
    "sg:phone":"+1 514 598 1842",
    "sg:postcode":"J4W 1M9",
    "sg:province":"QC",
    "sg:tags":[
        "balloon"
    ],
    "wof:name":"Ballons Publicitaires Vision",
    "wof:placetype":"venue"
},
  "geometry": {"coordinates":[-73.4654006958,45.4588890076],"type":"Point"}
}