{
  "type": "Feature",
  "properties": {
    "addr:full":"397 Main St Thedford ON N0M 2N0",
    "addr:housenumber":"397",
    "addr:postcode":"n0m 2n0",
    "addr:street":"Main St",
    "iso:country":"CA",
    "sg:address":"397 Main St",
    "sg:city":"Thedford",
    "sg:classifiers":[
        {
            "category":"Shopping",
            "subcategory":"Computers & Home Electronics",
            "type":"Retail Goods"
        }
    ],
    "sg:phone":"+1 519 296 5565",
    "sg:postcode":"N0M 2N0",
    "sg:province":"ON",
    "sg:tags":[
        "equipment",
        "satellite",
        "system"
    ],
    "wof:name":"Allen Stubbs First in Entrtn",
    "wof:placetype":"venue"
},
  "geometry": {"coordinates":[-81.835846,43.162601],"type":"Point"}
}