{
  "type": "Feature",
  "properties": {
    "iso:country":"CA",
    "sg:city":"Grasmere",
    "sg:classifiers":[
        {
            "category":"Food & Beverages",
            "subcategory":"Groceries & Convenience Stores",
            "type":"Retail Goods"
        }
    ],
    "sg:phone":"+1 250 887 3244",
    "sg:postcode":"V0B 1R0",
    "sg:province":"BC",
    "sg:tags":[
        "grocer"
    ],
    "wof:name":"Grasmere General Store",
    "wof:placetype":"venue"
},
  "geometry": {"coordinates":[-115.10747528100001,49.1473312378],"type":"Point"}
}