{
  "type": "Feature",
  "properties": {
    "iso:country":"CA",
    "sg:address":"344 Church St",
    "sg:city":"Garson",
    "sg:classifiers":[
        {
            "category":"Retail",
            "subcategory":"Repair Shop",
            "type":"Services"
        }
    ],
    "sg:phone":"+1 705 693 2786",
    "sg:postcode":"P3L 1A4",
    "sg:province":"ON",
    "sg:tags":[
        "repairing",
        "equipment",
        "electric"
    ],
    "wof:name":"J & L Distributors",
    "wof:placetype":"venue"
},
  "geometry": {"coordinates":[-80.8614196777,46.5625343323],"type":"Point"}
}