{
  "type": "Feature",
  "properties": {
    "addr:full":"374 Rue Notre-Dame Saint-Francois-Du-Lac QC J0G 1M0",
    "addr:housenumber":"374",
    "addr:postcode":"j0g 1m0",
    "addr:street":"Rue Notre-Dame Saint-Francois-Du-Lac",
    "iso:country":"CA",
    "sg:address":"374 Rue Notre-Dame",
    "sg:city":"Saint-Francois-Du-Lac",
    "sg:classifiers":[
        {
            "category":"Retail",
            "subcategory":"Funeral Services",
            "type":"Services"
        }
    ],
    "sg:phone":"+1 450 568 3711",
    "sg:postcode":"J0G 1M0",
    "sg:province":"QC",
    "sg:tags":[
        "director"
    ],
    "wof:name":"Descoteaux & Frere Enr",
    "wof:placetype":"venue"
},
  "geometry": {"coordinates":[-72.8298110962,46.0680656433],"type":"Point"}
}