{
  "type": "Feature",
  "properties": {
    "iso:country":"CA",
    "sg:city":"Maple",
    "sg:classifiers":[
        {
            "category":"Health Services",
            "subcategory":"Doctor",
            "type":"Services"
        }
    ],
    "sg:phone":"+1 905 832 4886",
    "sg:postcode":"L6A 1P4",
    "sg:province":"ON",
    "sg:tags":[
        "dentist"
    ],
    "wof:name":"Bishai, Amy DDS",
    "wof:placetype":"venue"
},
  "geometry": {"coordinates":[-79.5086593628,43.8379402161],"type":"Point"}
}