{
  "type": "Feature",
  "properties": {
    "addr:full":"1550 Kingston Rd Pickering ON L1V 1C3",
    "addr:housenumber":"1550",
    "addr:postcode":"l1v 1c3",
    "addr:street":"Kingston Rd",
    "iso:country":"CA",
    "sg:address":"1550 Kingston Rd",
    "sg:city":"Pickering",
    "sg:classifiers":[
        {
            "category":"Personal",
            "subcategory":"Tanning Parlor",
            "type":"Services"
        }
    ],
    "sg:phone":"+1 905 831 1922",
    "sg:postcode":"L1V 1C3",
    "sg:province":"ON",
    "sg:tags":[
        "salon"
    ],
    "wof:name":"Palm Beach Mega Tan",
    "wof:placetype":"venue"
},
  "geometry": {"coordinates":[-79.0798568726,43.8442077637],"type":"Point"}
}