{
  "type": "Feature",
  "properties": {
    "addr:full":"Hwy 11 South Cochrane ON P0L 1C0",
    "addr:postcode":"p0l 1c0",
    "addr:street":"Hwy 11 South",
    "iso:country":"CA",
    "sg:address":"Hwy 11 South",
    "sg:city":"Cochrane",
    "sg:classifiers":[
        {
            "category":"Retail",
            "subcategory":"Auto Rental",
            "type":"Services"
        }
    ],
    "sg:phone":"+1 705 272 3380",
    "sg:postcode":"P0L 1C0",
    "sg:province":"ON",
    "sg:tags":[
        "renting",
        "automobile"
    ],
    "wof:name":"National Car Rental",
    "wof:placetype":"venue"
},
  "geometry": {"coordinates":[-81.095291,49.058411],"type":"Point"}
}