{
  "type": "Feature",
  "properties": {
    "iso:country":"CA",
    "sg:address":"214 Selkirk Ave",
    "sg:city":"Winnipeg",
    "sg:classifiers":[
        {
            "category":"Organizations",
            "subcategory":"Membership Organization",
            "type":"Services"
        }
    ],
    "sg:phone":"+1 204 586 4054",
    "sg:postcode":"R2W 2L6",
    "sg:province":"MB",
    "wof:name":"Independent Order of Mechanics",
    "wof:placetype":"venue"
},
  "geometry": {"coordinates":[-97.1333999634,49.9118156433],"type":"Point"}
}