{
  "type": "Feature",
  "properties": {
    "iso:country":"CA",
    "sg:city":"Brampton",
    "sg:classifiers":[
        {
            "category":"Retail",
            "subcategory":"Auto Repair",
            "type":"Services"
        }
    ],
    "sg:phone":"+1 905 457 2217",
    "sg:postcode":"L6W 3W6",
    "sg:province":"ON",
    "sg:tags":[
        "repairing",
        "automobile"
    ],
    "wof:name":"Gary's Automotive Repair",
    "wof:placetype":"venue"
},
  "geometry": {"coordinates":[-79.7345123291,43.6949958801],"type":"Point"}
}