{
  "type": "Feature",
  "properties": {
    "addr:full":"19 Charlotte St Toronto ON M5V 2H5",
    "addr:housenumber":"19",
    "addr:postcode":"m5v 2h5",
    "addr:street":"Charlotte St",
    "iso:country":"CA",
    "sg:address":"19 Charlotte St",
    "sg:city":"Toronto",
    "sg:classifiers":[
        {
            "category":"Recreation",
            "type":"Entertainment"
        }
    ],
    "sg:phone":"+1 416 598 2882",
    "sg:postcode":"M5V 2H5",
    "sg:province":"ON",
    "sg:tags":[
        "parlor",
        "billiard"
    ],
    "wof:name":"Charlotte Room",
    "wof:placetype":"venue"
},
  "geometry": {"coordinates":[-79.3938446045,43.646572113],"type":"Point"}
}