{
  "type": "Feature",
  "properties": {
    "addr:full":"Abbotsford BC V2S 3T2",
    "addr:postcode":"v2s 3t2",
    "iso:country":"CA",
    "sg:city":"Abbotsford",
    "sg:classifiers":[
        {
            "category":"Manufacturing",
            "subcategory":"Printing",
            "type":"Manufacturing & Wholesale Goods"
        }
    ],
    "sg:phone":"+1 604 870 3555",
    "sg:postcode":"V2S 3T2",
    "sg:province":"BC",
    "sg:tags":[
        "publication"
    ],
    "wof:name":"Campus Publications",
    "wof:placetype":"venue"
},
  "geometry": {"coordinates":[-122.290542602,49.0469551086],"type":"Point"}
}