{
  "type": "Feature",
  "properties": {
    "addr:full":"303 Old Hwy 17 Goulais River ON P0S 1E0",
    "addr:housenumber":"303",
    "addr:postcode":"p0s 1e0",
    "addr:street":"Old Hwy 17 Goulais",
    "iso:country":"CA",
    "sg:address":"303 Old Hwy 17",
    "sg:city":"Goulais River",
    "sg:classifiers":[
        {
            "category":"Organizations",
            "subcategory":"Religious Organization",
            "type":"Services"
        }
    ],
    "sg:phone":"+1 705 649 2087",
    "sg:postcode":"P0S 1E0",
    "sg:province":"ON",
    "sg:tags":[
        "church"
    ],
    "wof:name":"Mother of God Catholic Church",
    "wof:placetype":"venue"
},
  "geometry": {"coordinates":[-84.40471599999999,46.712547],"type":"Point"}
}