{
  "type": "Feature",
  "properties": {
    "addr:full":"3388 Findlay St Vancouver BC V5N 4E7",
    "addr:housenumber":"3388",
    "addr:postcode":"v5n 4e7",
    "addr:street":"Findlay St",
    "iso:country":"CA",
    "sg:address":"3388 Findlay St",
    "sg:city":"Vancouver",
    "sg:classifiers":[
        {
            "category":"Retail",
            "subcategory":"Self-service Laundry",
            "type":"Services"
        }
    ],
    "sg:phone":"+1 604 874 5178",
    "sg:postcode":"V5N 4E7",
    "sg:province":"BC",
    "wof:name":"D & D Coin Launbry",
    "wof:placetype":"venue"
},
  "geometry": {"coordinates":[-123.067657,49.254501],"type":"Point"}
}