{
  "type": "Feature",
  "properties": {
    "addr:full":"Dubreuilville ON P0S 1B0",
    "addr:postcode":"p0s 1b0",
    "iso:country":"CA",
    "sg:city":"Dubreuilville",
    "sg:classifiers":[
        {
            "category":"Government",
            "subcategory":"Office",
            "type":"Public Place"
        }
    ],
    "sg:phone":"+1 705 884 2670",
    "sg:postcode":"P0S 1B0",
    "sg:province":"ON",
    "sg:tags":[
        "village"
    ],
    "wof:name":"Dubreuilville Senior's Hall",
    "wof:placetype":"venue"
},
  "geometry": {"coordinates":[-84.553017,48.350536],"type":"Point"}
}