{
  "type": "Feature",
  "properties": {
    "iso:country":"CA",
    "sg:address":"120 Ninth Ave",
    "sg:city":"Brantford",
    "sg:classifiers":[
        {
            "category":"Education",
            "subcategory":"School",
            "type":"Public Place"
        }
    ],
    "sg:phone":"+1 519 753 5283",
    "sg:postcode":"N3S 1E7",
    "sg:province":"ON",
    "wof:name":"Our Lady of Fatima School",
    "wof:placetype":"venue"
},
  "geometry": {"coordinates":[-80.2506866455,43.1216087341],"type":"Point"}
}