{
  "type": "Feature",
  "properties": {
    "addr:full":"200 Burrard St # 600 Vancouver BC V6C 3L9",
    "addr:housenumber":"200",
    "addr:postcode":"v6c 3l9",
    "addr:street":"Burrard St # 600",
    "iso:country":"CA",
    "sg:address":"200 Burrard St # 600",
    "sg:city":"Vancouver",
    "sg:classifiers":[
        {
            "category":"Mining & Drilling",
            "type":"Manufacturing & Wholesale Goods"
        }
    ],
    "sg:phone":"+1 604 687 1117",
    "sg:postcode":"V6C 3L9",
    "sg:province":"BC",
    "sg:tags":[
        "company"
    ],
    "wof:name":"Teck-Hemlo Inc",
    "wof:placetype":"venue"
},
  "geometry": {"coordinates":[-123.115601,49.288116],"type":"Point"}
}