{
  "type": "Feature",
  "properties": {
    "addr:full":"2260 Ch Gascon Terrebonne QC J6X 3A5",
    "addr:postcode":"2260;j6x 3a5",
    "addr:street":"Ch Gascon",
    "iso:country":"CA",
    "sg:address":"2260 Ch Gascon",
    "sg:city":"Terrebonne",
    "sg:classifiers":[
        {
            "category":"Food & Beverages",
            "subcategory":"Groceries & Convenience Stores",
            "type":"Retail Goods"
        }
    ],
    "sg:phone":"+1 450 492 8718",
    "sg:postcode":"J6X 3A5",
    "sg:province":"QC",
    "sg:tags":[
        "grocer"
    ],
    "wof:name":"Maxi",
    "wof:placetype":"venue"
},
  "geometry": {"coordinates":[-73.663712,45.72282],"type":"Point"}
}