{
  "type": "Feature",
  "properties": {
    "addr:full":"502 1E Rue Chibougamau QC G8P 1K9",
    "addr:housenumber":"502",
    "addr:postcode":"g8p 1k9",
    "addr:street":"1E Rue",
    "iso:country":"CA",
    "sg:address":"502 1E Rue",
    "sg:city":"Chibougamau",
    "sg:classifiers":[
        {
            "category":"Food & Beverages",
            "subcategory":"Groceries & Convenience Stores",
            "type":"Retail Goods"
        }
    ],
    "sg:phone":"+1 418 748 4900",
    "sg:postcode":"G8P 1K9",
    "sg:province":"QC",
    "sg:tags":[
        "grocer"
    ],
    "wof:name":"Epicerie Du Coin",
    "wof:placetype":"venue"
},
  "geometry": {"coordinates":[-74.36328125,49.9151802063],"type":"Point"}
}