{
  "type": "Feature",
  "properties": {
    "iso:country":"CA",
    "sg:address":"2534 Maid Marian Pl",
    "sg:city":"Mississauga",
    "sg:classifiers":[
        {
            "category":"Wholesale",
            "subcategory":"Sporting Goods",
            "type":"Manufacturing & Wholesale Goods"
        }
    ],
    "sg:phone":"+1 905 823 8097",
    "sg:postcode":"L5K 2L9",
    "sg:province":"ON",
    "sg:tags":[
        "equipment",
        "pool",
        "swimming"
    ],
    "wof:name":"Ezee Pool & Spa Canada Inc",
    "wof:placetype":"venue"
},
  "geometry": {"coordinates":[-79.658386,43.537716],"type":"Point"}
}