{
  "type": "Feature",
  "properties": {
    "iso:country":"CA",
    "sg:address":"2865 Mccausland Rd",
    "sg:city":"Powell River",
    "sg:classifiers":[
        {
            "category":"Recreation",
            "type":"Entertainment"
        }
    ],
    "sg:phone":"+1 604 487 4537",
    "sg:postcode":"V8A 4Z2",
    "sg:province":"BC",
    "sg:tags":[
        "course",
        "golf"
    ],
    "wof:name":"Myrtle Point Golf Club",
    "wof:placetype":"venue"
},
  "geometry": {"coordinates":[-124.46224975600001,49.7923812866],"type":"Point"}
}