{
  "type": "Feature",
  "properties": {
    "addr:full":"53 Tycos Dr North York ON M6B 1W3",
    "addr:housenumber":"53",
    "addr:postcode":"m6b 1w3",
    "addr:street":"Tycos Dr",
    "iso:country":"CA",
    "sg:address":"53 Tycos Dr",
    "sg:city":"North York",
    "sg:classifiers":[
        {
            "category":"Wholesale",
            "subcategory":"Apparel",
            "type":"Manufacturing & Wholesale Goods"
        }
    ],
    "sg:phone":"+1 416 787 0750",
    "sg:postcode":"M6B 1W3",
    "sg:province":"ON",
    "sg:tags":[
        "bridal",
        "supply"
    ],
    "wof:name":"Party Time Fashions Ltd",
    "wof:placetype":"venue"
},
  "geometry": {"coordinates":[-79.4560852051,43.7049064636],"type":"Point"}
}