{
  "type": "Feature",
  "properties": {
    "addr:full":"1296 Laz See'l Hazelton BC V0J 1Y0",
    "addr:housenumber":"1296",
    "addr:postcode":"v0j 1y0",
    "addr:street":"Laz See'L",
    "iso:country":"CA",
    "sg:address":"1296 Laz See'l",
    "sg:city":"Hazelton",
    "sg:classifiers":[
        {
            "category":"Recreation",
            "type":"Entertainment"
        }
    ],
    "sg:phone":"+1 250 842 6532",
    "sg:postcode":"V0J 1Y0",
    "sg:province":"BC",
    "sg:tags":[
        "center"
    ],
    "wof:name":"Kispiox Community Ctr",
    "wof:placetype":"venue"
},
  "geometry": {"coordinates":[-127.643867493,55.2642593384],"type":"Point"}
}