{
  "type": "Feature",
  "properties": {
    "iso:country":"CA",
    "sg:address":"50 No 2 Rd",
    "sg:city":"Bell Island",
    "sg:classifiers":[
        {
            "category":"Cinema",
            "subcategory":"Movie Rental",
            "type":"Entertainment"
        }
    ],
    "sg:phone":"+1 709 488 3307",
    "sg:postcode":"A0A 4H0",
    "sg:province":"NL",
    "sg:tags":[
        "leasing",
        "video",
        "disc",
        "tape"
    ],
    "wof:name":"Mr Home Movie",
    "wof:placetype":"venue"
},
  "geometry": {"coordinates":[-52.9490699768,47.6229782104],"type":"Point"}
}