{
  "type": "Feature",
  "properties": {
    "addr:full":"Bracebridge ON P1L 1T3",
    "addr:postcode":"p1l 1t3",
    "iso:country":"CA",
    "sg:city":"Bracebridge",
    "sg:classifiers":[
        {
            "category":"Shopping",
            "type":"Retail Goods"
        }
    ],
    "sg:phone":"+1 705 645 3953",
    "sg:postcode":"P1L 1T3",
    "sg:province":"ON",
    "sg:tags":[
        "photo",
        "finishing",
        "picture"
    ],
    "wof:name":"Calvalcade Color Lab Foto",
    "wof:placetype":"venue"
},
  "geometry": {"coordinates":[-79.3299865723,45.0437393188],"type":"Point"}
}