{
  "type": "Feature",
  "properties": {
    "addr:full":"121 Guildwood Pky Scarborough ON M1E 1P1",
    "addr:housenumber":"121",
    "addr:postcode":"m1e 1p1",
    "addr:street":"Guildwood Pky",
    "iso:country":"CA",
    "sg:address":"121 Guildwood Pky",
    "sg:city":"Scarborough",
    "sg:classifiers":[
        {
            "category":"Shopping",
            "subcategory":"Pharmacy",
            "type":"Retail Goods"
        }
    ],
    "sg:phone":"+1 416 267 8248",
    "sg:postcode":"M1E 1P1",
    "sg:province":"ON",
    "wof:name":"Guildwood Drug Mart",
    "wof:placetype":"venue"
},
  "geometry": {"coordinates":[-79.1998825073,43.7472190857],"type":"Point"}
}