{
  "type": "Feature",
  "properties": {
    "iso:country":"CA",
    "sg:address":"1552 Rue Du Pont",
    "sg:city":"Saint-Lambert-DE-Lauzon",
    "sg:classifiers":[
        {
            "category":"Home & Garden",
            "subcategory":"Building Materials",
            "type":"Retail Goods"
        }
    ],
    "sg:phone":"+1 418 889 0712",
    "sg:postcode":"G0S 2W0",
    "sg:province":"QC",
    "sg:tags":[
        "door"
    ],
    "wof:name":"Gosselin & Boilard Inc",
    "wof:placetype":"venue"
},
  "geometry": {"coordinates":[-71.1800231934,46.6097412109],"type":"Point"}
}