{
  "type": "Feature",
  "properties": {
    "iso:country":"CA",
    "sg:address":"1277 Boul Desaulniers",
    "sg:city":"Longueuil",
    "sg:classifiers":[
        {
            "category":"Bars & Pubs",
            "type":"Food & Drink"
        }
    ],
    "sg:phone":"+1 450 674 3701",
    "sg:postcode":"J4K 1L1",
    "sg:province":"QC",
    "wof:name":"Brasserie Du Sud",
    "wof:placetype":"venue"
},
  "geometry": {"coordinates":[-73.5068740845,45.5172271729],"type":"Point"}
}