{
  "type": "Feature",
  "properties": {
    "iso:country":"CA",
    "sg:city":"Mississauga",
    "sg:classifiers":[
        {
            "category":"Manufacturing",
            "subcategory":"Metals",
            "type":"Manufacturing & Wholesale Goods"
        }
    ],
    "sg:phone":"+1 905 670 0749",
    "sg:postcode":"L4W 2V6",
    "sg:province":"ON",
    "sg:tags":[
        "production",
        "grinding"
    ],
    "wof:name":"Doon Machine & Knives CO",
    "wof:placetype":"venue"
},
  "geometry": {"coordinates":[-79.64599609379999,43.6569900513],"type":"Point"}
}