{
  "type": "Feature",
  "properties": {
    "addr:full":"7 Gimli Park Rd Gimli MB R0C 1B0",
    "addr:housenumber":"7",
    "addr:postcode":"r0c 1b0",
    "addr:street":"Gimli Park Rd",
    "iso:country":"CA",
    "sg:address":"7 Gimli Park Rd",
    "sg:city":"Gimli",
    "sg:classifiers":[
        {
            "category":"Home & Garden",
            "subcategory":"Building Materials",
            "type":"Retail Goods"
        }
    ],
    "sg:phone":"+1 204 942 4860",
    "sg:postcode":"R0C 1B0",
    "sg:province":"MB",
    "sg:tags":[
        "lumber"
    ],
    "wof:name":"K C Enterprises",
    "wof:placetype":"venue"
},
  "geometry": {"coordinates":[-97.01007799999999,50.625324],"type":"Point"}
}