{
  "type": "Feature",
  "properties": {
    "addr:full":"502 12th Ave Genelle BC V0G 1G0",
    "addr:housenumber":"502",
    "addr:postcode":"v0g 1g0",
    "addr:street":"12Th Ave",
    "iso:country":"CA",
    "sg:address":"502 12th Ave",
    "sg:city":"Genelle",
    "sg:classifiers":[
        {
            "category":"Food & Beverages",
            "subcategory":"Liquor & Beverages",
            "type":"Retail Goods"
        }
    ],
    "sg:phone":"+1 250 693 2382",
    "sg:postcode":"V0G 1G0",
    "sg:province":"BC",
    "sg:tags":[
        "scooter",
        "motorcycle",
        "motor"
    ],
    "wof:name":"Snow Trails Sales & Svc Ltd",
    "wof:placetype":"venue"
},
  "geometry": {"coordinates":[-117.690437,49.213921],"type":"Point"}
}