{
  "type": "Feature",
  "properties": {
    "addr:full":"2998 Tecumseh Rd E Windsor ON N8W 1G5",
    "addr:housenumber":"2998",
    "addr:postcode":"n8w 1g5",
    "addr:street":"Tecumseh Rd E",
    "iso:country":"CA",
    "sg:address":"2998 Tecumseh Rd E",
    "sg:city":"Windsor",
    "sg:classifiers":[
        {
            "category":"Bars & Pubs",
            "type":"Food & Drink"
        }
    ],
    "sg:phone":"+1 519 974 3109",
    "sg:postcode":"N8W 1G5",
    "sg:province":"ON",
    "wof:name":"Little Memphis Cabaret",
    "wof:placetype":"venue"
},
  "geometry": {"coordinates":[-82.9867324829,42.3038825989],"type":"Point"}
}