{
  "type": "Feature",
  "properties": {
    "addr:full":"1700 Rue Notre-Dame Centre Trois-Rivieres QC G9A 6G5",
    "addr:housenumber":"1700",
    "addr:postcode":"g9a 6g5",
    "addr:street":"Rue Notre-Dame Centre Trois-Rivieres",
    "iso:country":"CA",
    "sg:address":"1700 Rue Notre-Dame Centre",
    "sg:city":"Trois-Rivieres",
    "sg:classifiers":[
        {
            "category":"Health Services",
            "subcategory":"Nursing And Care Facility",
            "type":"Services"
        }
    ],
    "sg:phone":"+1 819 376 0352",
    "sg:postcode":"G9A 6G5",
    "sg:province":"QC",
    "sg:tags":[
        "home",
        "retirement",
        "community"
    ],
    "wof:name":"Residence LA Sittelle",
    "wof:placetype":"venue"
},
  "geometry": {"coordinates":[-72.4803619385,46.3845252991],"type":"Point"}
}