{
  "type": "Feature",
  "properties": {
    "addr:full":"Bombardier Rd Shilo MB R0K 2A0",
    "addr:postcode":"r0k 2a0",
    "addr:street":"Bombardier Rd",
    "iso:country":"CA",
    "sg:address":"Bombardier Rd",
    "sg:city":"Shilo",
    "sg:classifiers":[
        {
            "category":"Health Services",
            "subcategory":"Doctor",
            "type":"Services"
        }
    ],
    "sg:phone":"+1 204 765 2802",
    "sg:postcode":"R0K 2A0",
    "sg:province":"MB",
    "sg:tags":[
        "dentist"
    ],
    "wof:name":"Shilo Dental Ctr",
    "wof:placetype":"venue"
},
  "geometry": {"coordinates":[-99.640038,49.805996],"type":"Point"}
}