{
  "type": "Feature",
  "properties": {
    "addr:full":"2009 Lawrence Ave W # 1 York ON M9N 3V2",
    "addr:housenumber":"2009",
    "addr:postcode":"m9n 3v2",
    "addr:street":"Lawrence Ave W # 1",
    "iso:country":"CA",
    "sg:address":"2009 Lawrence Ave W # 1",
    "sg:city":"York",
    "sg:classifiers":[
        {
            "category":"Building & Trades",
            "subcategory":"Construction",
            "type":"Services"
        }
    ],
    "sg:phone":"+1 416 241 6923",
    "sg:postcode":"M9N 3V2",
    "sg:province":"ON",
    "sg:tags":[
        "general",
        "contractor"
    ],
    "wof:name":"Amari General Contractors",
    "wof:placetype":"venue"
},
  "geometry": {"coordinates":[-79.5114822388,43.7010879517],"type":"Point"}
}