{
  "type": "Feature",
  "properties": {
    "addr:full":"Newmarket ON L3Y 7B6",
    "addr:postcode":"l3y 7b6",
    "iso:country":"CA",
    "sg:city":"Newmarket",
    "sg:classifiers":[
        {
            "category":"Insurance",
            "subcategory":"Insurance Agent",
            "type":"Services"
        }
    ],
    "sg:phone":"+1 905 830 2992",
    "sg:postcode":"L3Y 7B6",
    "sg:province":"ON",
    "sg:tags":[
        "consultant"
    ],
    "wof:name":"Insurance Services Assoc",
    "wof:placetype":"venue"
},
  "geometry": {"coordinates":[-79.4295959473,44.0727958679],"type":"Point"}
}