{
  "type": "Feature",
  "properties": {
    "addr:full":"Dieppe NB E1A 6C8",
    "addr:postcode":"e1a 6c8",
    "iso:country":"CA",
    "sg:city":"Dieppe",
    "sg:classifiers":[
        {
            "category":"Professional",
            "subcategory":"Business Services",
            "type":"Services"
        }
    ],
    "sg:phone":"+1 506 859 5200",
    "sg:postcode":"E1A 6C8",
    "sg:province":"NB",
    "sg:tags":[
        "translator",
        "interpreter"
    ],
    "wof:name":"Lexi-Tech Intl",
    "wof:placetype":"venue"
},
  "geometry": {"coordinates":[-64.71659099999999,46.102299],"type":"Point"}
}