{
  "type": "Feature",
  "properties": {
    "addr:full":"Markham ON L3R 8X5",
    "addr:postcode":"l3r 8x5",
    "iso:country":"CA",
    "sg:city":"Markham",
    "sg:classifiers":[
        {
            "category":"Shopping",
            "subcategory":"Florist",
            "type":"Retail Goods"
        }
    ],
    "sg:phone":"+1 905 475 5525",
    "sg:postcode":"L3R 8X5",
    "sg:province":"ON",
    "wof:name":"Beaver Creek Florist",
    "wof:placetype":"venue"
},
  "geometry": {"coordinates":[-79.342880249,43.8711471558],"type":"Point"}
}