{
  "type": "Feature",
  "properties": {
    "addr:full":"1550 Chapais St North Bay ON P1B 6M4",
    "addr:housenumber":"1550",
    "addr:postcode":"p1b 6m4",
    "addr:street":"Chapais St",
    "iso:country":"CA",
    "sg:address":"1550 Chapais St",
    "sg:city":"North Bay",
    "sg:classifiers":[
        {
            "category":"Manufacturing",
            "subcategory":"Metals",
            "type":"Manufacturing & Wholesale Goods"
        }
    ],
    "sg:phone":"+1 705 474 5757",
    "sg:postcode":"P1B 6M4",
    "sg:province":"ON",
    "sg:tags":[
        "welding"
    ],
    "wof:name":"Weldtech",
    "wof:placetype":"venue"
},
  "geometry": {"coordinates":[-79.44491577150001,46.3340606689],"type":"Point"}
}