{
  "type": "Feature",
  "properties": {
    "addr:full":"Kingston ON K7K 6A9",
    "addr:postcode":"k7k 6a9",
    "iso:country":"CA",
    "sg:city":"Kingston",
    "sg:classifiers":[
        {
            "category":"Home & Garden",
            "subcategory":"Home Furnishings",
            "type":"Retail Goods"
        }
    ],
    "sg:phone":"+1 613 548 8397",
    "sg:postcode":"K7K 6A9",
    "sg:province":"ON",
    "sg:tags":[
        "lighting",
        "fixture"
    ],
    "wof:name":"Kingston Lighting",
    "wof:placetype":"venue"
},
  "geometry": {"coordinates":[-76.479332,44.231537],"type":"Point"}
}