{
  "type": "Feature",
  "properties": {
    "addr:full":"168 Bridgeland Ave North York ON M6A 1Z4",
    "addr:housenumber":"168",
    "addr:postcode":"m6a 1z4",
    "addr:street":"Bridgeland Ave",
    "iso:country":"CA",
    "sg:address":"168 Bridgeland Ave",
    "sg:city":"North York",
    "sg:classifiers":[
        {
            "category":"Professional",
            "subcategory":"Engineering",
            "type":"Services"
        }
    ],
    "sg:phone":"+1 416 787 0303",
    "sg:postcode":"M6A 1Z4",
    "sg:province":"ON",
    "sg:tags":[
        "surveyor"
    ],
    "wof:name":"Anton Kikas Ltd",
    "wof:placetype":"venue"
},
  "geometry": {"coordinates":[-79.4651107788,43.7253456116],"type":"Point"}
}