{
  "type": "Feature",
  "properties": {
    "addr:full":"1105 1st Ave E Owen Sound ON N4K 2E2",
    "addr:housenumber":"1105",
    "addr:postcode":"n4k 2e2",
    "addr:street":"1St Ave E",
    "iso:country":"CA",
    "sg:address":"1105 1st Ave E",
    "sg:city":"Owen Sound",
    "sg:classifiers":[
        {
            "category":"Utilities",
            "subcategory":"Telephone",
            "type":"Services"
        }
    ],
    "sg:phone":"+1 519 376 0001",
    "sg:postcode":"N4K 2E2",
    "sg:province":"ON",
    "sg:tags":[
        "distance",
        "long"
    ],
    "wof:name":"Canadian Long Distance",
    "wof:placetype":"venue"
},
  "geometry": {"coordinates":[-80.943108,44.57066],"type":"Point"}
}