{
  "type": "Feature",
  "properties": {
    "addr:full":"Sicamous BC V0E 2V0",
    "addr:postcode":"v0e 2v0",
    "iso:country":"CA",
    "sg:city":"Sicamous",
    "sg:classifiers":[
        {
            "category":"Personal",
            "subcategory":"Beauty Salon",
            "type":"Services"
        }
    ],
    "sg:phone":"+1 250 836 2737",
    "sg:postcode":"V0E 2V0",
    "sg:province":"BC",
    "wof:name":"Hair Affairs",
    "wof:placetype":"venue"
},
  "geometry": {"coordinates":[-118.97657775899999,50.8374633789],"type":"Point"}
}