{
  "type": "Feature",
  "properties": {
    "addr:full":"7905 Ch Mackle Cote Saint-Luc QC H4W 1A5",
    "addr:housenumber":"7905",
    "addr:postcode":"h4w 1a5",
    "addr:street":"Ch Mackle Cote",
    "iso:country":"CA",
    "sg:address":"7905 Ch Mackle",
    "sg:city":"Cote Saint-Luc",
    "sg:classifiers":[
        {
            "category":"Building & Trades",
            "subcategory":"Construction",
            "type":"Services"
        }
    ],
    "sg:phone":"+1 514 486 9638",
    "sg:postcode":"H4W 1A5",
    "sg:province":"QC",
    "sg:tags":[
        "masonry",
        "contractor"
    ],
    "wof:name":"Desjardins, C",
    "wof:placetype":"venue"
},
  "geometry": {"coordinates":[-73.671997,45.466244],"type":"Point"}
}