{
  "type": "Feature",
  "properties": {
    "iso:country":"CA",
    "sg:address":"2525 Route 132",
    "sg:city":"Greater Lakeburn",
    "sg:classifiers":[
        {
            "category":"Wholesale",
            "subcategory":"Medical Equipment & Supplies",
            "type":"Manufacturing & Wholesale Goods"
        }
    ],
    "sg:phone":"+1 506 857 1808",
    "sg:postcode":"E1H 1Z6",
    "sg:province":"NB",
    "sg:tags":[
        "wheel",
        "chair",
        "lift",
        "ramp"
    ],
    "wof:name":"Atlantic Coach Inc",
    "wof:placetype":"venue"
},
  "geometry": {"coordinates":[-64.6800003052,46.1034812927],"type":"Point"}
}