{
  "type": "Feature",
  "properties": {
    "addr:full":"261 Montee Des Saules Rimouski QC G5L 8Y9",
    "addr:housenumber":"261",
    "addr:postcode":"g5l 8y9",
    "addr:street":"Montee Des Saules",
    "iso:country":"CA",
    "sg:address":"261 Montee Des Saules",
    "sg:city":"Rimouski",
    "sg:classifiers":[
        {
            "category":"Sports & Exercise",
            "subcategory":"Golf",
            "type":"Entertainment"
        }
    ],
    "sg:phone":"+1 418 724 2295",
    "sg:postcode":"G5L 8Y9",
    "sg:province":"QC",
    "sg:tags":[
        "course"
    ],
    "wof:name":"Golf Des Saules Inc",
    "wof:placetype":"venue"
},
  "geometry": {"coordinates":[-68.5793228149,48.419719696],"type":"Point"}
}