{
  "type": "Feature",
  "properties": {
    "addr:full":"2800 Olafsen Ave Richmond BC V6X 2R3",
    "addr:housenumber":"2800",
    "addr:postcode":"v6x 2r3",
    "addr:street":"Olafsen Ave",
    "iso:country":"CA",
    "sg:address":"2800 Olafsen Ave",
    "sg:city":"Richmond",
    "sg:classifiers":[
        {
            "category":"Manufacturing",
            "subcategory":"Metals",
            "type":"Manufacturing & Wholesale Goods"
        }
    ],
    "sg:phone":"+1 604 273 9055",
    "sg:postcode":"V6X 2R3",
    "sg:province":"BC",
    "sg:tags":[
        "brass",
        "foundry",
        "bronze"
    ],
    "wof:name":"Obco",
    "wof:placetype":"venue"
},
  "geometry": {"coordinates":[-123.095589,49.193638],"type":"Point"}
}