{
  "type": "Feature",
  "properties": {
    "addr:full":"Sorel-Tracy QC J3R 1K7",
    "addr:postcode":"j3r 1k7",
    "iso:country":"CA",
    "sg:city":"Sorel-Tracy",
    "sg:classifiers":[
        {
            "category":"Health Services",
            "subcategory":"Doctor",
            "type":"Services"
        }
    ],
    "sg:phone":"+1 450 742 5638",
    "sg:postcode":"J3R 1K7",
    "sg:province":"QC",
    "sg:tags":[
        "physician",
        "surgeon"
    ],
    "wof:name":"Paradis, Jean MD",
    "wof:placetype":"venue"
},
  "geometry": {"coordinates":[-73.124039,46.039932],"type":"Point"}
}