{
  "type": "Feature",
  "properties": {
    "iso:country":"CA",
    "sg:address":"12840 109 Ave NW",
    "sg:city":"Edmonton",
    "sg:classifiers":[
        {
            "category":"Social Services",
            "subcategory":"Child Care",
            "type":"Services"
        }
    ],
    "sg:phone":"+1 780 452 1266",
    "sg:postcode":"T5M 2E8",
    "sg:province":"AB",
    "sg:tags":[
        "tennis",
        "court"
    ],
    "wof:name":"Ace Tennis Academy",
    "wof:placetype":"venue"
},
  "geometry": {"coordinates":[-113.543586731,53.554069519],"type":"Point"}
}