{
  "type": "Feature",
  "properties": {
    "addr:full":"Peterborough ON K9H 2H6",
    "addr:postcode":"k9h 2h6",
    "iso:country":"CA",
    "sg:city":"Peterborough",
    "sg:classifiers":[
        {
            "category":"Real Estate",
            "subcategory":"Real Estate Agent",
            "type":"Services"
        }
    ],
    "sg:phone":"+1 705 749 1602",
    "sg:postcode":"K9H 2H6",
    "sg:province":"ON",
    "wof:name":"Dns Real Estate Ltd",
    "wof:placetype":"venue"
},
  "geometry": {"coordinates":[-78.321434021,44.3044776917],"type":"Point"}
}