{
  "type": "Feature",
  "properties": {
    "iso:country":"CA",
    "sg:address":"610 Robson St",
    "sg:city":"Vancouver",
    "sg:classifiers":[
        {
            "category":"Travel",
            "subcategory":"Travel Agent",
            "type":"Entertainment"
        }
    ],
    "sg:phone":"+1 604 718 0800",
    "sg:postcode":"V6B 2B9",
    "sg:province":"BC",
    "sg:tags":[
        "agency",
        "bureau"
    ],
    "wof:name":"Flight Centre",
    "wof:placetype":"venue"
},
  "geometry": {"coordinates":[-123.119110107,49.2807312012],"type":"Point"}
}