{
  "type": "Feature",
  "properties": {
    "addr:full":"Sainte-Marthe-Du-Cap QC G8V 1W2",
    "addr:postcode":"g8v 1w2",
    "iso:country":"CA",
    "sg:city":"Sainte-Marthe-Du-Cap",
    "sg:classifiers":[
        {
            "category":"Wholesale",
            "subcategory":"Machinery & Supplies",
            "type":"Manufacturing & Wholesale Goods"
        }
    ],
    "sg:phone":"+1 819 375 0236",
    "sg:postcode":"G8V 1W2",
    "sg:province":"QC",
    "sg:tags":[
        "repairing",
        "equipment",
        "hydraulic"
    ],
    "wof:name":"Hymec Inc",
    "wof:placetype":"venue"
},
  "geometry": {"coordinates":[-72.5362701416,46.4011039734],"type":"Point"}
}