{
  "type": "Feature",
  "properties": {
    "addr:full":"Calgary AB T2C 4C7",
    "addr:postcode":"t2c 4c7",
    "iso:country":"CA",
    "sg:city":"Calgary",
    "sg:classifiers":[
        {
            "category":"Wholesale",
            "subcategory":"Machinery & Supplies",
            "type":"Manufacturing & Wholesale Goods"
        }
    ],
    "sg:phone":"+1 403 203 8112",
    "sg:postcode":"T2C 4C7",
    "sg:province":"AB",
    "sg:tags":[
        "concrete",
        "equipment"
    ],
    "wof:name":"Peri Formwork Systems Inc",
    "wof:placetype":"venue"
},
  "geometry": {"coordinates":[-113.964416504,50.9892044067],"type":"Point"}
}