{
  "type": "Feature",
  "properties": {
    "iso:country":"CA",
    "sg:city":"Morris",
    "sg:classifiers":[
        {
            "category":"Restaurant",
            "type":"Food & Drink"
        }
    ],
    "sg:phone":"+1 204 746 6229",
    "sg:postcode":"R0G 1K0",
    "sg:province":"MB",
    "wof:name":"Bill's Pizza",
    "wof:placetype":"venue"
},
  "geometry": {"coordinates":[-97.36604309080001,49.3546791077],"type":"Point"}
}