{
  "type": "Feature",
  "properties": {
    "addr:full":"2080 Trinity Church Rd Binbrook ON L0R 1C0",
    "addr:housenumber":"2080",
    "addr:postcode":"l0r 1c0",
    "addr:street":"Trinity Church Rd",
    "iso:country":"CA",
    "sg:address":"2080 Trinity Church Rd",
    "sg:city":"Binbrook",
    "sg:classifiers":[
        {
            "category":"Organizations",
            "subcategory":"Non-profit Organization",
            "type":"Services"
        }
    ],
    "sg:phone":"+1 905 692 4465",
    "sg:postcode":"L0R 1C0",
    "sg:province":"ON",
    "sg:tags":[
        "disability"
    ],
    "wof:name":"Participation House Hamilton",
    "wof:placetype":"venue"
},
  "geometry": {"coordinates":[-79.801697,43.127686],"type":"Point"}
}