{
  "type": "Feature",
  "properties": {
    "addr:full":"170 Stewart Ave Sussex NB E4E 2G2",
    "addr:housenumber":"170",
    "addr:postcode":"e4e 2g2",
    "addr:street":"Stewart Ave",
    "iso:country":"CA",
    "sg:address":"170 Stewart Ave",
    "sg:city":"Sussex",
    "sg:classifiers":[
        {
            "category":"Wholesale",
            "subcategory":"Farm Supplies",
            "type":"Manufacturing & Wholesale Goods"
        }
    ],
    "sg:phone":"+1 506 432 4200",
    "sg:postcode":"E4E 2G2",
    "sg:province":"NB",
    "sg:tags":[
        "feed"
    ],
    "wof:name":"Shur-Gain",
    "wof:placetype":"venue"
},
  "geometry": {"coordinates":[-65.508202,45.728603],"type":"Point"}
}