{
  "type": "Feature",
  "properties": {
    "addr:full":"Toronto ON M5R 2A5",
    "addr:postcode":"m5r 2a5",
    "iso:country":"CA",
    "sg:city":"Toronto",
    "sg:classifiers":[
        {
            "category":"Health Services",
            "subcategory":"Doctor",
            "type":"Services"
        }
    ],
    "sg:phone":"+1 416 920 9139",
    "sg:postcode":"M5R 2A5",
    "sg:province":"ON",
    "sg:tags":[
        "physician",
        "surgeon"
    ],
    "wof:name":"Banack, A MD",
    "wof:placetype":"venue"
},
  "geometry": {"coordinates":[-79.38962600000001,43.669739],"type":"Point"}
}