{
  "type": "Feature",
  "properties": {
    "addr:full":"145 Rue Saint-Laurent Saint-Eustache QC J7P 5H6",
    "addr:housenumber":"145",
    "addr:postcode":"j7p 5h6",
    "addr:street":"Rue Saint-Laurent",
    "iso:country":"CA",
    "sg:address":"145 Rue Saint-Laurent",
    "sg:city":"Saint-Eustache",
    "sg:classifiers":[
        {
            "category":"Restaurant",
            "type":"Food & Drink"
        }
    ],
    "sg:phone":"+1 450 472 1070",
    "sg:postcode":"J7P 5H6",
    "sg:province":"QC",
    "wof:name":"Restaurant Le Jardin St Lrnt",
    "wof:placetype":"venue"
},
  "geometry": {"coordinates":[-73.884995,45.568947],"type":"Point"}
}