{
  "type": "Feature",
  "properties": {
    "addr:full":"1900 Rue Sainte-Catherine E Montreal QC H2K 2H5",
    "addr:housenumber":"1900",
    "addr:postcode":"h2k 2h5",
    "addr:street":"Rue Sainte-Catherine E",
    "iso:country":"CA",
    "sg:address":"1900 Rue Sainte-Catherine E",
    "sg:city":"Montreal",
    "sg:classifiers":[
        {
            "category":"Restaurant",
            "type":"Food & Drink"
        }
    ],
    "sg:phone":"+1 514 931 0081",
    "sg:postcode":"H2K 2H5",
    "sg:province":"QC",
    "wof:name":"Restaurant U & Me",
    "wof:placetype":"venue"
},
  "geometry": {"coordinates":[-73.5514297485,45.5233688354],"type":"Point"}
}