{
  "type": "Feature",
  "properties": {
    "addr:full":"176 Rue Lemieux Granby QC J2G 9J6",
    "addr:housenumber":"176",
    "addr:postcode":"j2g 9j6",
    "addr:street":"Rue Lemieux",
    "iso:country":"CA",
    "sg:address":"176 Rue Lemieux",
    "sg:city":"Granby",
    "sg:classifiers":[
        {
            "category":"Manufacturing",
            "subcategory":"Signs",
            "type":"Manufacturing & Wholesale Goods"
        }
    ],
    "sg:phone":"+1 450 372 9696",
    "sg:postcode":"J2G 9J6",
    "sg:province":"QC",
    "sg:tags":[
        "painter"
    ],
    "wof:name":"Lettramatic Enr Serge Lussier",
    "wof:placetype":"venue"
},
  "geometry": {"coordinates":[-72.682846,45.393585],"type":"Point"}
}