{
  "type": "Feature",
  "properties": {
    "addr:full":"2025 222 Rte Saint-Denis-DE-Brompton QC J0B 2P0",
    "addr:housenumber":"2025",
    "addr:postcode":"j0b 2p0",
    "addr:street":"222 Rte Saint-Denis-De-Brompton",
    "iso:country":"CA",
    "sg:address":"2025 222 Rte",
    "sg:city":"Saint-Denis-DE-Brompton",
    "sg:classifiers":[
        {
            "category":"Food & Beverages",
            "subcategory":"Groceries & Convenience Stores",
            "type":"Retail Goods"
        }
    ],
    "sg:phone":"+1 819 846 0157",
    "sg:postcode":"J0B 2P0",
    "sg:province":"QC",
    "wof:name":"Depanneur 222 Enr",
    "wof:placetype":"venue"
},
  "geometry": {"coordinates":[-72.08098602290001,45.4581336975],"type":"Point"}
}