{
  "type": "Feature",
  "properties": {
    "iso:country":"CA",
    "sg:city":"Montreal",
    "sg:classifiers":[
        {
            "category":"Shopping",
            "subcategory":"Tobacco",
            "type":"Retail Goods"
        }
    ],
    "sg:phone":"+1 514 382 2659",
    "sg:postcode":"H2N 2K9",
    "sg:province":"QC",
    "sg:tags":[
        "cigarette",
        "cigar",
        "dealer"
    ],
    "wof:name":"Tabagie Frs Inc",
    "wof:placetype":"venue"
},
  "geometry": {"coordinates":[-73.648865,45.548431],"type":"Point"}
}