{
  "type": "Feature",
  "properties": {
    "addr:full":"611 Ch Du Pont-Tache N Alma QC G8B 6T4",
    "addr:housenumber":"611",
    "addr:postcode":"g8b 6t4",
    "addr:street":"Ch Du Pont-Tache N",
    "iso:country":"CA",
    "sg:address":"611 Ch Du Pont-Tache N",
    "sg:city":"Alma",
    "sg:classifiers":[
        {
            "category":"Retail",
            "subcategory":"Funeral Services",
            "type":"Services"
        }
    ],
    "sg:phone":"+1 418 668 8409",
    "sg:postcode":"G8B 6T4",
    "sg:province":"QC",
    "sg:tags":[
        "director"
    ],
    "wof:name":"Residence Funeraire Lac St-Jn",
    "wof:placetype":"venue"
},
  "geometry": {"coordinates":[-71.63771820069999,48.5585403442],"type":"Point"}
}