{
  "type": "Feature",
  "properties": {
    "addr:full":"424 18th Ave Hanover ON N4N 3P1",
    "addr:housenumber":"424",
    "addr:postcode":"n4n 3p1",
    "addr:street":"18Th Ave",
    "iso:country":"CA",
    "sg:address":"424 18th Ave",
    "sg:city":"Hanover",
    "sg:classifiers":[
        {
            "category":"Retail",
            "subcategory":"Portrait Studio",
            "type":"Services"
        }
    ],
    "sg:phone":"+1 519 364 9996",
    "sg:postcode":"N4N 3P1",
    "sg:province":"ON",
    "sg:tags":[
        "photographer"
    ],
    "wof:name":"A Natural Image",
    "wof:placetype":"venue"
},
  "geometry": {"coordinates":[-81.014511,44.153343],"type":"Point"}
}