{
  "type": "Feature",
  "properties": {
    "iso:country":"CA",
    "sg:city":"Montreal",
    "sg:classifiers":[
        {
            "category":"Ferry",
            "type":"Transportation"
        }
    ],
    "sg:phone":"+1 514 285 4400",
    "sg:postcode":"H2Y 2P5",
    "sg:province":"QC",
    "sg:tags":[
        "company",
        "steamship"
    ],
    "wof:name":"Cfr Confreight Maritime Line",
    "wof:placetype":"venue"
},
  "geometry": {"coordinates":[-73.5560531616,45.5020523071],"type":"Point"}
}