{
  "type": "Feature",
  "properties": {
    "addr:full":"602 South Railway St W Warman SK S0K 4S0",
    "addr:housenumber":"602",
    "addr:postcode":"s0k 4s0",
    "addr:street":"South Railway St W",
    "iso:country":"CA",
    "sg:address":"602 South Railway St W",
    "sg:city":"Warman",
    "sg:classifiers":[
        {
            "category":"Home & Garden",
            "subcategory":"Building Materials",
            "type":"Retail Goods"
        }
    ],
    "sg:phone":"+1 306 933 4950",
    "sg:postcode":"S0K 4S0",
    "sg:province":"SK",
    "sg:tags":[
        "lumber"
    ],
    "wof:name":"Warman Home Ctr",
    "wof:placetype":"venue"
},
  "geometry": {"coordinates":[-106.572525,52.318489],"type":"Point"}
}