{
  "type": "Feature",
  "properties": {
    "addr:full":"611 Archibald St Winnipeg MB R2J 0X8",
    "addr:housenumber":"611",
    "addr:postcode":"r2j 0x8",
    "addr:street":"Archibald St",
    "iso:country":"CA",
    "sg:address":"611 Archibald St",
    "sg:city":"Winnipeg",
    "sg:classifiers":[
        {
            "category":"Travel",
            "subcategory":"Hotels & Motels",
            "type":"Entertainment"
        }
    ],
    "sg:phone":"+1 204 237 8901",
    "sg:postcode":"R2J 0X8",
    "sg:province":"MB",
    "wof:name":"Chalet Hotel",
    "wof:placetype":"venue"
},
  "geometry": {"coordinates":[-97.0990829468,49.8820495605],"type":"Point"}
}