{
  "type": "Feature",
  "properties": {
    "addr:full":"6105 Yonge St North York ON M2M 3W2",
    "addr:housenumber":"6105",
    "addr:postcode":"m2m 3w2",
    "addr:street":"Yonge St",
    "iso:country":"CA",
    "sg:address":"6105 Yonge St",
    "sg:city":"North York",
    "sg:classifiers":[
        {
            "category":"Manufacturing",
            "subcategory":"Jewelry",
            "type":"Manufacturing & Wholesale Goods"
        }
    ],
    "sg:phone":"+1 416 225 4641",
    "sg:postcode":"M2M 3W2",
    "sg:province":"ON",
    "wof:name":"Some Jewellery",
    "wof:placetype":"venue"
},
  "geometry": {"coordinates":[-79.41821299999999,43.791412],"type":"Point"}
}