{
  "type": "Feature",
  "properties": {
    "addr:full":"196 Main St Dutton ON N0L 1J0",
    "addr:housenumber":"196",
    "addr:postcode":"n0l 1j0",
    "addr:street":"Main St",
    "iso:country":"CA",
    "sg:address":"196 Main St",
    "sg:city":"Dutton",
    "sg:classifiers":[
        {
            "category":"Real Estate",
            "subcategory":"Real Estate Agent",
            "type":"Services"
        }
    ],
    "sg:phone":"+1 519 762 0001",
    "sg:postcode":"N0L 1J0",
    "sg:province":"ON",
    "wof:name":"Land Office Inc",
    "wof:placetype":"venue"
},
  "geometry": {"coordinates":[-81.5026473999,42.663444519],"type":"Point"}
}