{
  "type": "Feature",
  "properties": {
    "addr:full":"4330 Sunshine Coast Hwy Sechelt BC V0N 3A1",
    "addr:housenumber":"4330",
    "addr:postcode":"v0n 3a1",
    "addr:street":"Sunshine Coast Hwy",
    "iso:country":"CA",
    "sg:address":"4330 Sunshine Coast Hwy",
    "sg:city":"Sechelt",
    "sg:classifiers":[
        {
            "category":"Shopping",
            "type":"Retail Goods"
        }
    ],
    "sg:phone":"+1 604 885 4225",
    "sg:postcode":"V0N 3A1",
    "sg:province":"BC",
    "sg:tags":[
        "equipment",
        "wine",
        "supply"
    ],
    "wof:name":"Wilson Creek Rent & Brew",
    "wof:placetype":"venue"
},
  "geometry": {"coordinates":[-123.70725299999999,49.440334],"type":"Point"}
}