{
  "type": "Feature",
  "properties": {
    "addr:full":"1908 21st Ave Nanton AB T0L 1R0",
    "addr:housenumber":"1908",
    "addr:postcode":"t0l 1r0",
    "addr:street":"21St Ave",
    "iso:country":"CA",
    "sg:address":"1908 21st Ave",
    "sg:city":"Nanton",
    "sg:classifiers":[
        {
            "category":"Manufacturing",
            "subcategory":"Printing",
            "type":"Manufacturing & Wholesale Goods"
        }
    ],
    "sg:phone":"+1 403 646 2833",
    "sg:postcode":"T0L 1R0",
    "sg:province":"AB",
    "sg:tags":[
        "printer"
    ],
    "wof:name":"Nanton Print Shop",
    "wof:placetype":"venue"
},
  "geometry": {"coordinates":[-113.773880005,50.3485946655],"type":"Point"}
}