{
  "type": "Feature",
  "properties": {
    "addr:full":"704 East Lake Rd NE Airdrie AB T4A 2J5",
    "addr:housenumber":"704",
    "addr:postcode":"t4a 2j5",
    "addr:street":"East Lake Rd Ne",
    "iso:country":"CA",
    "sg:address":"704 East Lake Rd NE",
    "sg:city":"Airdrie",
    "sg:classifiers":[
        {
            "category":"Mining & Drilling",
            "type":"Manufacturing & Wholesale Goods"
        }
    ],
    "sg:phone":"+1 403 948 6646",
    "sg:postcode":"T4A 2J5",
    "sg:province":"AB",
    "sg:tags":[
        "field",
        "oil"
    ],
    "wof:name":"Schlumberger of Canada",
    "wof:placetype":"venue"
},
  "geometry": {"coordinates":[-113.990326,51.288837],"type":"Point"}
}