{
  "type": "Feature",
  "properties": {
    "iso:country":"CA",
    "sg:city":"Saint-Lambert",
    "sg:classifiers":[
        {
            "category":"Food & Beverages",
            "subcategory":"Dairy",
            "type":"Retail Goods"
        }
    ],
    "sg:phone":"+1 450 672 9701",
    "sg:postcode":"J4P 1R3",
    "sg:province":"QC",
    "sg:tags":[
        "cheese"
    ],
    "wof:name":"Echoppe Des Fromages Inc",
    "wof:placetype":"venue"
},
  "geometry": {"coordinates":[-73.513077,45.501522],"type":"Point"}
}