{
  "type": "Feature",
  "properties": {
    "addr:full":"6403 123 St NW Edmonton AB T6H 3T3",
    "addr:housenumber":"6403",
    "addr:postcode":"t6h 3t3",
    "addr:street":"123 St Nw",
    "iso:country":"CA",
    "sg:address":"6403 123 St NW",
    "sg:city":"Edmonton",
    "sg:classifiers":[
        {
            "category":"Organizations",
            "subcategory":"Professional Association",
            "type":"Services"
        }
    ],
    "sg:phone":"+1 780 438 8314",
    "sg:postcode":"T6H 3T3",
    "sg:province":"AB",
    "wof:name":"Elder Advocates of Alberta",
    "wof:placetype":"venue"
},
  "geometry": {"coordinates":[-113.542007446,53.5008506775],"type":"Point"}
}