{
  "type": "Feature",
  "properties": {
    "addr:full":"901 Danforth Ave Toronto ON M4J 1L8",
    "addr:housenumber":"901",
    "addr:postcode":"m4j 1l8",
    "addr:street":"Danforth Ave",
    "iso:country":"CA",
    "sg:address":"901 Danforth Ave",
    "sg:city":"Toronto",
    "sg:classifiers":[
        {
            "category":"Retail",
            "subcategory":"Animal Services",
            "type":"Services"
        }
    ],
    "sg:phone":"+1 416 465 4655",
    "sg:postcode":"M4J 1L8",
    "sg:province":"ON",
    "sg:tags":[
        "pet",
        "grooming",
        "washing"
    ],
    "wof:name":"Adorable & Affordable Grooming",
    "wof:placetype":"venue"
},
  "geometry": {"coordinates":[-79.339035,43.679939],"type":"Point"}
}