{
  "type": "Feature",
  "properties": {
    "addr:full":"Orangeville ON L9W 3L2",
    "addr:postcode":"l9w 3l2",
    "iso:country":"CA",
    "sg:city":"Orangeville",
    "sg:classifiers":[
        {
            "category":"Professional",
            "subcategory":"Engineering",
            "type":"Services"
        }
    ],
    "sg:phone":"+1 519 941 0330",
    "sg:postcode":"L9W 3L2",
    "sg:province":"ON",
    "sg:tags":[
        "engineer"
    ],
    "wof:name":"Triton Engineering Svc Ltd",
    "wof:placetype":"venue"
},
  "geometry": {"coordinates":[-80.11102294920001,43.9063453674],"type":"Point"}
}