{
  "type": "Feature",
  "properties": {
    "addr:full":"Calgary AB T2H 0J3",
    "addr:postcode":"t2h 0j3",
    "iso:country":"CA",
    "sg:city":"Calgary",
    "sg:classifiers":[
        {
            "category":"Restaurant",
            "type":"Food & Drink"
        }
    ],
    "sg:phone":"+1 403 253 7575",
    "sg:postcode":"T2H 0J3",
    "sg:province":"AB",
    "wof:name":"Boyd's Seafood Restaurant",
    "wof:placetype":"venue"
},
  "geometry": {"coordinates":[-114.068763733,51.0077667236],"type":"Point"}
}