{
  "type": "Feature",
  "properties": {
    "addr:full":"409 Harmony Rd Ayr ON N0B 1E0",
    "addr:housenumber":"409",
    "addr:postcode":"n0b 1e0",
    "addr:street":"Harmony Rd",
    "iso:country":"CA",
    "sg:address":"409 Harmony Rd",
    "sg:city":"Ayr",
    "sg:classifiers":[
        {
            "category":"Building & Trades",
            "subcategory":"Electrical",
            "type":"Services"
        }
    ],
    "sg:phone":"+1 519 622 2238",
    "sg:postcode":"N0B 1E0",
    "sg:province":"ON",
    "sg:tags":[
        "electric",
        "contractor"
    ],
    "wof:name":"John Raepple Electric Ltd",
    "wof:placetype":"venue"
},
  "geometry": {"coordinates":[-80.4499969482,43.2856559753],"type":"Point"}
}