{
  "type": "Feature",
  "properties": {
    "addr:full":"1311 Rue Royale Malartic QC J0Y 1Z0",
    "addr:housenumber":"1311",
    "addr:postcode":"j0y 1z0",
    "addr:street":"Rue Royale",
    "iso:country":"CA",
    "sg:address":"1311 Rue Royale",
    "sg:city":"Malartic",
    "sg:classifiers":[
        {
            "category":"Travel",
            "subcategory":"Hotels & Motels",
            "type":"Entertainment"
        }
    ],
    "sg:phone":"+1 819 757 4377",
    "sg:postcode":"J0Y 1Z0",
    "sg:province":"QC",
    "wof:name":"Filon Dort",
    "wof:placetype":"venue"
},
  "geometry": {"coordinates":[-78.127335,48.143646],"type":"Point"}
}