{
  "type": "Feature",
  "properties": {
    "iso:country":"CA",
    "sg:address":"170 Joseph Zatzman Dr",
    "sg:city":"Dartmouth",
    "sg:classifiers":[
        {
            "category":"Building & Trades",
            "subcategory":"Construction",
            "type":"Services"
        }
    ],
    "sg:phone":"+1 902 468 9054",
    "sg:postcode":"B3B 1L9",
    "sg:province":"NS",
    "sg:tags":[
        "resurfacing",
        "floor",
        "laying",
        "refinishing",
        "dealer"
    ],
    "wof:name":"Floors Plus More Clearance Ctr",
    "wof:placetype":"venue"
},
  "geometry": {"coordinates":[-63.600063324,44.711933136],"type":"Point"}
}