{
  "type": "Feature",
  "properties": {
    "addr:full":"120 Sullivan Ave # 23 Nepean ON K2G 1V2",
    "addr:housenumber":"120;23",
    "addr:postcode":"k2g 1v2",
    "addr:street":"Sullivan Ave #",
    "iso:country":"CA",
    "sg:address":"120 Sullivan Ave # 23",
    "sg:city":"Nepean",
    "sg:classifiers":[
        {
            "category":"Building & Trades",
            "subcategory":"Cleaning & Sanitation",
            "type":"Services"
        }
    ],
    "sg:phone":"+1 613 727 8464",
    "sg:postcode":"K2G 1V2",
    "sg:province":"ON",
    "sg:tags":[
        "janitor"
    ],
    "wof:name":"J S Cleaning",
    "wof:placetype":"venue"
},
  "geometry": {"coordinates":[-75.744362,45.34087],"type":"Point"}
}