{
  "type": "Feature",
  "properties": {
    "iso:country":"CA",
    "sg:city":"Lachine",
    "sg:classifiers":[
        {
            "category":"Communications",
            "subcategory":"Film & Video Production",
            "type":"Services"
        }
    ],
    "sg:phone":"+1 514 639 8008",
    "sg:postcode":"H8S 3S2",
    "sg:province":"QC",
    "sg:tags":[
        "motion",
        "picture",
        "effects",
        "special"
    ],
    "wof:name":"Maestro Studio Fx",
    "wof:placetype":"venue"
},
  "geometry": {"coordinates":[-73.681099,45.436249],"type":"Point"}
}