{
  "type": "Feature",
  "properties": {
    "addr:full":"New Westminster BC V3M 1X4",
    "addr:postcode":"v3m 1x4",
    "iso:country":"CA",
    "sg:city":"New Westminster",
    "sg:classifiers":[
        {
            "category":"Shopping",
            "subcategory":"Pharmacy",
            "type":"Retail Goods"
        }
    ],
    "sg:phone":"+1 604 526 2233",
    "sg:postcode":"V3M 1X4",
    "sg:province":"BC",
    "wof:name":"Pharmasave",
    "wof:placetype":"venue"
},
  "geometry": {"coordinates":[-122.919113,49.211571],"type":"Point"}
}