{
  "type": "Feature",
  "properties": {
    "addr:full":"90 Avalon Dr Labrador City NL A2V 2L3",
    "addr:housenumber":"90",
    "addr:postcode":"a2v 2l3",
    "addr:street":"Avalon Dr",
    "iso:country":"CA",
    "sg:address":"90 Avalon Dr",
    "sg:city":"Labrador City",
    "sg:classifiers":[
        {
            "category":"Restaurant",
            "type":"Food & Drink"
        }
    ],
    "sg:phone":"+1 709 944 2901",
    "sg:postcode":"A2V 2L3",
    "sg:province":"NL",
    "wof:name":"Mc Donald's",
    "wof:placetype":"venue"
},
  "geometry": {"coordinates":[-66.90358000000001,52.944084],"type":"Point"}
}