{
  "type": "Feature",
  "properties": {
    "iso:country":"CA",
    "sg:address":"44 Hughson St S",
    "sg:city":"Hamilton",
    "sg:classifiers":[
        {
            "category":"Organizations",
            "subcategory":"Labor Organization",
            "type":"Services"
        }
    ],
    "sg:phone":"+1 905 522 7177",
    "sg:postcode":"L8N 2A7",
    "sg:province":"ON",
    "wof:name":"Labourers International Union",
    "wof:placetype":"venue"
},
  "geometry": {"coordinates":[-79.86866,43.254898],"type":"Point"}
}