{
  "type": "Feature",
  "properties": {
    "iso:country":"CA",
    "sg:address":"49 Collard Dr",
    "sg:city":"King City",
    "sg:classifiers":[
        {
            "category":"Manufacturing",
            "subcategory":"Tools & Machinery",
            "type":"Manufacturing & Wholesale Goods"
        }
    ],
    "sg:phone":"+1 905 833 2820",
    "sg:postcode":"L7B 1E4",
    "sg:province":"ON",
    "sg:tags":[
        "oven"
    ],
    "wof:name":"Griffon Enterprises Inc",
    "wof:placetype":"venue"
},
  "geometry": {"coordinates":[-79.548172,43.910618],"type":"Point"}
}