{
  "type": "Feature",
  "properties": {
    "addr:full":"Mississauga ON L4W 5A8",
    "addr:postcode":"l4w 5a8",
    "iso:country":"CA",
    "sg:city":"Mississauga",
    "sg:classifiers":[
        {
            "category":"Freight",
            "type":"Transportation"
        }
    ],
    "sg:phone":"+1 905 602 1890",
    "sg:postcode":"L4W 5A8",
    "sg:province":"ON",
    "wof:name":"Vinpac Lines Inc",
    "wof:placetype":"venue"
},
  "geometry": {"coordinates":[-79.601418,43.659748],"type":"Point"}
}