{
  "type": "Feature",
  "properties": {
    "iso:country":"CA",
    "sg:city":"Wingham",
    "sg:classifiers":[
        {
            "category":"Freight",
            "type":"Transportation"
        }
    ],
    "sg:phone":"+1 519 357 3346",
    "sg:postcode":"N0G 2W0",
    "sg:province":"ON",
    "sg:tags":[
        "trucking"
    ],
    "wof:name":"S & C Clark Transport",
    "wof:placetype":"venue"
},
  "geometry": {"coordinates":[-81.322052,43.89225],"type":"Point"}
}