{
  "type": "Feature",
  "properties": {
    "addr:full":"1920 Route 950 Petit-Cap NB E4N 2J2",
    "addr:housenumber":"1920",
    "addr:postcode":"e4n 2j2",
    "addr:street":"Route 950",
    "iso:country":"CA",
    "sg:address":"1920 Route 950",
    "sg:city":"Petit-Cap",
    "sg:classifiers":[
        {
            "category":"Food & Beverages",
            "subcategory":"Meat & Fish",
            "type":"Retail Goods"
        }
    ],
    "sg:phone":"+1 506 577 2750",
    "sg:postcode":"E4N 2J2",
    "sg:province":"NB",
    "sg:tags":[
        "seafood"
    ],
    "wof:name":"Boudreau Farm & Sea Products",
    "wof:placetype":"venue"
},
  "geometry": {"coordinates":[-64.17106628419999,46.1963577271],"type":"Point"}
}