{
  "type": "Feature",
  "properties": {
    "addr:full":"Nelson BC V1L 4H8",
    "addr:postcode":"bc v1l 4h8",
    "iso:country":"CA",
    "sg:city":"Nelson",
    "sg:classifiers":[
        {
            "category":"Real Estate",
            "subcategory":"Real Estate Agent",
            "type":"Services"
        }
    ],
    "sg:phone":"+1 250 352 7245",
    "sg:postcode":"V1L 4H8",
    "sg:province":"BC",
    "wof:name":"C W Appleyard & CO Ltd",
    "wof:placetype":"venue"
},
  "geometry": {"coordinates":[-117.29510498,49.4914474487],"type":"Point"}
}