{
  "type": "Feature",
  "properties": {
    "iso:country":"CA",
    "sg:address":"2018 Rue Saint-Denis",
    "sg:city":"Montreal",
    "sg:classifiers":[
        {
            "category":"Restaurant",
            "type":"Food & Drink"
        }
    ],
    "sg:phone":"+1 514 281 1402",
    "sg:postcode":"H2X 3K7",
    "sg:province":"QC",
    "wof:name":"Restaurant LA Lune Indienne",
    "wof:placetype":"venue"
},
  "geometry": {"coordinates":[-73.56575,45.515995],"type":"Point"}
}