{
  "type": "Feature",
  "properties": {
    "addr:full":"2018 Rue Saint-Denis Montreal QC H2X 3K7",
    "addr:housenumber":"2018",
    "addr:postcode":"h2x 3k7",
    "addr:street":"Rue Saint-Denis",
    "iso:country":"CA",
    "sg:address":"2018 Rue Saint-Denis",
    "sg:city":"Montreal",
    "sg:classifiers":[
        {
            "category":"Restaurant",
            "type":"Food & Drink"
        }
    ],
    "sg:phone":"+1 514 281 1402",
    "sg:postcode":"H2X 3K7",
    "sg:province":"QC",
    "wof:name":"Restaurant LA Lune Indienne",
    "wof:placetype":"venue"
},
  "geometry": {"coordinates":[-73.56574999999999,45.515995],"type":"Point"}
}