{
  "type": "Feature",
  "properties": {
    "addr:full":"Lloydminster SK S9V 0M8",
    "addr:postcode":"s9v 0m8",
    "iso:country":"CA",
    "sg:city":"Lloydminster",
    "sg:classifiers":[
        {
            "category":"Insurance",
            "subcategory":"Insurance Agent",
            "type":"Services"
        }
    ],
    "sg:phone":"+1 306 825 8200",
    "sg:postcode":"S9V 0M8",
    "sg:province":"SK",
    "sg:tags":[
        "government"
    ],
    "wof:name":"Saskatchewan Government Ins",
    "wof:placetype":"venue"
},
  "geometry": {"coordinates":[-110.000862,53.283344],"type":"Point"}
}