{
  "type": "Feature",
  "properties": {
    "addr:full":"5305 Rue Palmerston Montreal QC H1T 1J6",
    "addr:housenumber":"5305",
    "addr:postcode":"h1t 1j6",
    "addr:street":"Rue Palmerston",
    "iso:country":"CA",
    "sg:address":"5305 Rue Palmerston",
    "sg:city":"Montreal",
    "sg:classifiers":[
        {
            "category":"Building & Trades",
            "subcategory":"Electrical",
            "type":"Services"
        }
    ],
    "sg:phone":"+1 514 594 4884",
    "sg:postcode":"H1T 1J6",
    "sg:province":"QC",
    "sg:tags":[
        "electric",
        "contractor"
    ],
    "wof:name":"Pro Tech Electrique Inc",
    "wof:placetype":"venue"
},
  "geometry": {"coordinates":[-73.574371,45.575851],"type":"Point"}
}