{
  "type": "Feature",
  "properties": {
    "addr:full":"49 Stitt St Winnipeg Beach MB R0C 3G0",
    "addr:housenumber":"49",
    "addr:postcode":"r0c 3g0",
    "addr:street":"Stitt St",
    "iso:country":"CA",
    "sg:address":"49 Stitt St",
    "sg:city":"Winnipeg Beach",
    "sg:classifiers":[
        {
            "category":"Restaurant",
            "type":"Food & Drink"
        }
    ],
    "sg:phone":"+1 204 389 3673",
    "sg:postcode":"R0C 3G0",
    "sg:province":"MB",
    "wof:name":"Pizza Place",
    "wof:placetype":"venue"
},
  "geometry": {"coordinates":[-96.968628,50.497433],"type":"Point"}
}