{
  "type": "Feature",
  "properties": {
    "addr:full":"Sheros Island Barrington NS B0W 1E0",
    "addr:postcode":"b0w 1e0",
    "iso:country":"CA",
    "sg:address":"Sheros Island",
    "sg:city":"Barrington",
    "sg:classifiers":[
        {
            "category":"Government",
            "subcategory":"Office",
            "type":"Public Place"
        }
    ],
    "sg:phone":"+1 902 637 3432",
    "sg:postcode":"B0W 1E0",
    "sg:province":"NS",
    "sg:tags":[
        "village"
    ],
    "wof:name":"Barrington Public Works",
    "wof:placetype":"venue"
},
  "geometry": {"coordinates":[-65.60103599999999,43.534557],"type":"Point"}
}