{
  "type": "Feature",
  "properties": {
    "addr:full":"Kelowna BC V1Y 6H2",
    "addr:postcode":"v1y 6h2",
    "iso:country":"CA",
    "sg:city":"Kelowna",
    "sg:classifiers":[
        {
            "category":"Shopping",
            "subcategory":"Pharmacy",
            "type":"Retail Goods"
        }
    ],
    "sg:phone":"+1 250 860 3764",
    "sg:postcode":"V1Y 6H2",
    "sg:province":"BC",
    "sg:tags":[
        "post"
    ],
    "wof:name":"Shoppers Drug Mart",
    "wof:placetype":"venue"
},
  "geometry": {"coordinates":[-119.438515,49.881752],"type":"Point"}
}