{
  "type": "Feature",
  "properties": {
    "iso:country":"CA",
    "sg:address":"1882 Schoolhouse Rd",
    "sg:city":"Nanaimo",
    "sg:classifiers":[
        {
            "category":"Wholesale",
            "subcategory":"Construction Materials",
            "type":"Manufacturing & Wholesale Goods"
        }
    ],
    "sg:phone":"+1 250 741 1450",
    "sg:postcode":"V9X 1T4",
    "sg:province":"BC",
    "sg:tags":[
        "fence"
    ],
    "wof:name":"Mid-Island Fence Products Ltd",
    "wof:placetype":"venue"
},
  "geometry": {"coordinates":[-123.936157227,49.1642684937],"type":"Point"}
}