{
  "type": "Feature",
  "properties": {
    "addr:full":"480 Boul Harwood Vaudreuil-Dorion QC J7V 7H4",
    "addr:housenumber":"480",
    "addr:postcode":"j7v 7h4",
    "addr:street":"Boul Harwood",
    "iso:country":"CA",
    "sg:address":"480 Boul Harwood",
    "sg:city":"Vaudreuil-Dorion",
    "sg:classifiers":[
        {
            "category":"Shopping",
            "subcategory":"Books",
            "type":"Retail Goods"
        }
    ],
    "sg:phone":"+1 450 455 7974",
    "sg:postcode":"J7V 7H4",
    "sg:province":"QC",
    "sg:tags":[
        "dealer"
    ],
    "wof:name":"Editions Vaudreuil Inc",
    "wof:placetype":"venue"
},
  "geometry": {"coordinates":[-74.021866,45.377869],"type":"Point"}
}