{
  "type": "Feature",
  "properties": {
    "addr:full":"944 133 Rte Saint-Armand QC J0J 1T0",
    "addr:housenumber":"133",
    "addr:postcode":"j0j 1t0",
    "addr:street":"Rte Saint-Armand",
    "iso:country":"CA",
    "sg:address":"944 133 Rte",
    "sg:city":"Saint-Armand",
    "sg:classifiers":[
        {
            "category":"Restaurant",
            "type":"Food & Drink"
        }
    ],
    "sg:phone":"+1 450 248 4596",
    "sg:postcode":"J0J 1T0",
    "sg:province":"QC",
    "wof:name":"Routier Chez Bernadette",
    "wof:placetype":"venue"
},
  "geometry": {"coordinates":[-73.0670013428,45.0640487671],"type":"Point"}
}