{
  "type": "Feature",
  "properties": {
    "iso:country":"CA",
    "sg:address":"500 Michel-Houle Rue RR 3",
    "sg:city":"Saint-Charles-DE-Drummond",
    "sg:classifiers":[
        {
            "category":"Government",
            "subcategory":"Office",
            "type":"Public Place"
        }
    ],
    "sg:phone":"+1 819 478 7029",
    "sg:postcode":"J2B 7T5",
    "sg:province":"QC",
    "sg:tags":[
        "village"
    ],
    "wof:name":"St Charles DE Drummond Chalet",
    "wof:placetype":"venue"
},
  "geometry": {"coordinates":[-72.4251251221,45.8648948669],"type":"Point"}
}