{
  "type": "Feature",
  "properties": {
    "addr:full":"15 Wade Sq Courtice ON L1E 3E5",
    "addr:housenumber":"15",
    "addr:postcode":"l1e 3e5",
    "addr:street":"Wade Sq",
    "iso:country":"CA",
    "sg:address":"15 Wade Sq",
    "sg:city":"Courtice",
    "sg:classifiers":[
        {
            "category":"Professional",
            "subcategory":"Management & Consulting",
            "type":"Services"
        }
    ],
    "sg:phone":"+1 905 434 5338",
    "sg:postcode":"L1E 3E5",
    "sg:province":"ON",
    "sg:tags":[
        "consultant",
        "business"
    ],
    "wof:name":"S P Logistics Solutions",
    "wof:placetype":"venue"
},
  "geometry": {"coordinates":[-78.7861328125,43.9009819031],"type":"Point"}
}