{
  "type": "Feature",
  "properties": {
    "addr:full":"2021 Av Union Montreal QC H3A 2S9",
    "addr:housenumber":"2021",
    "addr:postcode":"h3a 2s9",
    "addr:street":"Av Union",
    "iso:country":"CA",
    "sg:address":"2021 Av Union",
    "sg:city":"Montreal",
    "sg:classifiers":[
        {
            "category":"Government",
            "subcategory":"Office",
            "type":"Public Place"
        }
    ],
    "sg:phone":"+1 514 873 2669",
    "sg:postcode":"H3A 2S9",
    "sg:province":"QC",
    "wof:name":"Quebec Conseil Quebecois DE LA",
    "wof:placetype":"venue"
},
  "geometry": {"coordinates":[-73.5713043213,45.504940033],"type":"Point"}
}