{
  "type": "Feature",
  "properties": {
    "addr:full":"102 Manitoba St E Moose Jaw SK S6H 0A3",
    "addr:housenumber":"102",
    "addr:postcode":"s6h 0a3",
    "addr:street":"Manitoba St E",
    "iso:country":"CA",
    "sg:address":"102 Manitoba St E",
    "sg:city":"Moose Jaw",
    "sg:classifiers":[
        {
            "category":"Retail",
            "subcategory":"Auto Repair",
            "type":"Services"
        }
    ],
    "sg:phone":"+1 306 692 5717",
    "sg:postcode":"S6H 0A3",
    "sg:province":"SK",
    "sg:tags":[
        "repairing",
        "automobile"
    ],
    "wof:name":"Constable Service",
    "wof:placetype":"venue"
},
  "geometry": {"coordinates":[-105.53185999999999,50.389481],"type":"Point"}
}