{
  "type": "Feature",
  "properties": {
    "iso:country":"CA",
    "sg:address":"533 Christina St N",
    "sg:city":"Sarnia",
    "sg:classifiers":[
        {
            "category":"Manufacturing",
            "subcategory":"Printing",
            "type":"Manufacturing & Wholesale Goods"
        }
    ],
    "sg:phone":"+1 519 337 5771",
    "sg:postcode":"N7T 5W5",
    "sg:province":"ON",
    "sg:tags":[
        "printer"
    ],
    "wof:name":"Ods Commercial Printing",
    "wof:placetype":"venue"
},
  "geometry": {"coordinates":[-82.40106964109999,42.9840126038],"type":"Point"}
}