{
  "type": "Feature",
  "properties": {
    "addr:full":"Uxbridge ON L9P 1R1",
    "addr:postcode":"l9p 1r1",
    "iso:country":"CA",
    "sg:city":"Uxbridge",
    "sg:classifiers":[
        {
            "category":"Building & Trades",
            "subcategory":"Construction",
            "type":"Services"
        }
    ],
    "sg:phone":"+1 905 852 4078",
    "sg:postcode":"L9P 1R1",
    "sg:province":"ON",
    "sg:tags":[
        "painter"
    ],
    "wof:name":"Decorcraft Painting",
    "wof:placetype":"venue"
},
  "geometry": {"coordinates":[-79.196465,44.100986],"type":"Point"}
}