{
  "type": "Feature",
  "properties": {
    "addr:full":"2440 Cliffe Ave Courtenay BC V9N 2L6",
    "addr:housenumber":"2440",
    "addr:postcode":"v9n 2l6",
    "addr:street":"Cliffe Ave",
    "iso:country":"CA",
    "sg:address":"2440 Cliffe Ave",
    "sg:city":"Courtenay",
    "sg:classifiers":[
        {
            "category":"Shopping",
            "type":"Retail Goods"
        }
    ],
    "sg:phone":"+1 250 334 3055",
    "sg:postcode":"V9N 2L6",
    "sg:province":"BC",
    "sg:tags":[
        "equipment",
        "beer",
        "supply"
    ],
    "wof:name":"Corks Caps & Fermentalia",
    "wof:placetype":"venue"
},
  "geometry": {"coordinates":[-124.98281900000001,49.676853],"type":"Point"}
}