{
  "type": "Feature",
  "properties": {
    "addr:full":"361 Applewood Cres Concord ON L4K 4J3",
    "addr:housenumber":"361",
    "addr:postcode":"l4k 4j3",
    "addr:street":"Applewood Cres",
    "iso:country":"CA",
    "sg:address":"361 Applewood Cres",
    "sg:city":"Concord",
    "sg:classifiers":[
        {
            "category":"Manufacturing",
            "subcategory":"Furniture",
            "type":"Manufacturing & Wholesale Goods"
        }
    ],
    "sg:phone":"+1 905 660 0433",
    "sg:postcode":"L4K 4J3",
    "sg:province":"ON",
    "wof:name":"Tricore Industries",
    "wof:placetype":"venue"
},
  "geometry": {"coordinates":[-79.53891,43.805668],"type":"Point"}
}