{
  "type": "Feature",
  "properties": {
    "addr:full":"Edmonton AB T5S 1K8",
    "addr:postcode":"t5s 1k8",
    "iso:country":"CA",
    "sg:city":"Edmonton",
    "sg:classifiers":[
        {
            "category":"Professional",
            "subcategory":"Engineering",
            "type":"Services"
        }
    ],
    "sg:phone":"+1 780 483 6558",
    "sg:postcode":"T5S 1K8",
    "sg:province":"AB",
    "sg:tags":[
        "engineer"
    ],
    "wof:name":"Rak Engineering Ltd",
    "wof:placetype":"venue"
},
  "geometry": {"coordinates":[-113.633460998,53.5537185669],"type":"Point"}
}