{
  "type": "Feature",
  "properties": {
    "addr:full":"5661 Av DE Monkland Montreal QC H4A 1E5",
    "addr:housenumber":"5661",
    "addr:postcode":"h4a 1e5",
    "addr:street":"Av De Monkland",
    "iso:country":"CA",
    "sg:address":"5661 Av DE Monkland",
    "sg:city":"Montreal",
    "sg:classifiers":[
        {
            "category":"Retail",
            "subcategory":"Photofinishing",
            "type":"Services"
        }
    ],
    "sg:phone":"+1 514 481 4910",
    "sg:postcode":"H4A 1E5",
    "sg:province":"QC",
    "sg:tags":[
        "photo",
        "finishing"
    ],
    "wof:name":"Photogenie One",
    "wof:placetype":"venue"
},
  "geometry": {"coordinates":[-73.62358856199999,45.4749755859],"type":"Point"}
}