{
  "type": "Feature",
  "properties": {
    "addr:full":"416 Thornhill Pl NW Calgary AB T2K 2S5",
    "addr:housenumber":"416",
    "addr:postcode":"t2k 2s5",
    "addr:street":"Thornhill Pl Nw",
    "iso:country":"CA",
    "sg:address":"416 Thornhill Pl NW",
    "sg:city":"Calgary",
    "sg:classifiers":[
        {
            "category":"Professional",
            "subcategory":"Management & Consulting",
            "type":"Services"
        }
    ],
    "sg:phone":"+1 403 275 8107",
    "sg:postcode":"T2K 2S5",
    "sg:province":"AB",
    "sg:tags":[
        "consultant",
        "business"
    ],
    "wof:name":"Stagg & Assoc Business",
    "wof:placetype":"venue"
},
  "geometry": {"coordinates":[-114.069435,51.096584],"type":"Point"}
}