{
  "type": "Feature",
  "properties": {
    "addr:full":"150 York St Toronto ON M5H 3S5",
    "addr:housenumber":"150",
    "addr:postcode":"m5h 3s5",
    "addr:street":"York St",
    "iso:country":"CA",
    "sg:address":"150 York St",
    "sg:city":"Toronto",
    "sg:classifiers":[
        {
            "category":"Professional",
            "type":"Services"
        }
    ],
    "sg:phone":"+1 416 360 0823",
    "sg:postcode":"M5H 3S5",
    "sg:province":"ON",
    "sg:tags":[
        "clinic",
        "establishment"
    ],
    "wof:name":"Medcan Health Management Inc",
    "wof:placetype":"venue"
},
  "geometry": {"coordinates":[-79.384331,43.649307],"type":"Point"}
}