{
  "type": "Feature",
  "properties": {
    "iso:country":"CA",
    "sg:city":"Terrebonne",
    "sg:classifiers":[
        {
            "category":"Manufacturing",
            "subcategory":"Metals",
            "type":"Manufacturing & Wholesale Goods"
        }
    ],
    "sg:phone":"+1 450 477 5497",
    "sg:postcode":"J6X 4J9",
    "sg:province":"QC",
    "sg:tags":[
        "solder"
    ],
    "wof:name":"Gervais St-Onge",
    "wof:placetype":"venue"
},
  "geometry": {"coordinates":[-73.6943511963,45.7243270874],"type":"Point"}
}