{
  "type": "Feature",
  "properties": {
    "iso:country":"CA",
    "sg:address":"6945 Meadowvale Town Centre Ci",
    "sg:city":"Mississauga",
    "sg:classifiers":[
        {
            "category":"Organizations",
            "subcategory":"Religious Organization",
            "type":"Services"
        }
    ],
    "sg:phone":"+1 905 821 2753",
    "sg:postcode":"L5N 2W7",
    "sg:province":"ON",
    "sg:tags":[
        "church"
    ],
    "wof:name":"White Oak Presbyterian Church",
    "wof:placetype":"venue"
},
  "geometry": {"coordinates":[-79.75709533689999,43.5827903748],"type":"Point"}
}