{
  "type": "Feature",
  "properties": {
    "addr:full":"1400 Av Du Pont S Alma QC G8B 2V8",
    "addr:housenumber":"1400",
    "addr:postcode":"g8b 2v8",
    "addr:street":"Av Du Pont S",
    "iso:country":"CA",
    "sg:address":"1400 Av Du Pont S",
    "sg:city":"Alma",
    "sg:classifiers":[
        {
            "category":"Retail",
            "subcategory":"Auto Repair",
            "type":"Services"
        }
    ],
    "sg:phone":"+1 418 668 7911",
    "sg:postcode":"G8B 2V8",
    "sg:province":"QC",
    "sg:tags":[
        "repairing",
        "automobile"
    ],
    "wof:name":"Specialite DE Freins Arthur",
    "wof:placetype":"venue"
},
  "geometry": {"coordinates":[-71.65057400000001,48.53014],"type":"Point"}
}