{
  "type": "Feature",
  "properties": {
    "addr:full":"Scarborough ON M1V 1S3",
    "addr:postcode":"m1v 1s3",
    "iso:country":"CA",
    "sg:city":"Scarborough",
    "sg:classifiers":[
        {
            "category":"Organizations",
            "subcategory":"Religious Organization",
            "type":"Services"
        }
    ],
    "sg:phone":"+1 416 291 8500",
    "sg:postcode":"M1V 1S3",
    "sg:province":"ON",
    "wof:name":"Sri Varasithi Vinayagar Hindu",
    "wof:placetype":"venue"
},
  "geometry": {"coordinates":[-79.2999038696,43.8081169128],"type":"Point"}
}