{
  "type": "Feature",
  "properties": {
    "iso:country":"CA",
    "sg:address":"22 Columbia St",
    "sg:city":"Melville",
    "sg:classifiers":[
        {
            "category":"Government",
            "subcategory":"Office",
            "type":"Public Place"
        }
    ],
    "sg:phone":"+1 306 728 2213",
    "sg:postcode":"S0A 2P0",
    "sg:province":"SK",
    "sg:tags":[
        "bus",
        "line"
    ],
    "wof:name":"Saskatchewan Transportation CO",
    "wof:placetype":"venue"
},
  "geometry": {"coordinates":[-102.81224822999999,50.9350090027],"type":"Point"}
}