{
  "type": "Feature",
  "properties": {
    "addr:full":"173 Main St Hwy 3 Courtland ON N0J 1E0",
    "addr:housenumber":"173",
    "addr:postcode":"n0j 1e0",
    "addr:street":"Main St Hwy 3",
    "iso:country":"CA",
    "sg:address":"173 Main St Hwy 3",
    "sg:city":"Courtland",
    "sg:classifiers":[
        {
            "category":"Wholesale",
            "subcategory":"Meat",
            "type":"Manufacturing & Wholesale Goods"
        }
    ],
    "sg:phone":"+1 519 688 2120",
    "sg:postcode":"N0J 1E0",
    "sg:province":"ON",
    "sg:tags":[
        "butchering"
    ],
    "wof:name":"People's Meat Market",
    "wof:placetype":"venue"
},
  "geometry": {"coordinates":[-80.635193,42.844494],"type":"Point"}
}