{
  "type": "Feature",
  "properties": {
    "addr:full":"891 220 Rte Bonsecours QC J0E 1H0",
    "addr:housenumber":"220",
    "addr:postcode":"j0e 1h0",
    "addr:street":"Rte Bonsecours",
    "iso:country":"CA",
    "sg:address":"891 220 Rte",
    "sg:city":"Bonsecours",
    "sg:classifiers":[
        {
            "category":"Wholesale",
            "subcategory":"Meat",
            "type":"Manufacturing & Wholesale Goods"
        }
    ],
    "sg:phone":"+1 450 532 4646",
    "sg:postcode":"J0E 1H0",
    "sg:province":"QC",
    "sg:tags":[
        "packer",
        "butchering"
    ],
    "wof:name":"Abattoir Tessier Enr 2001",
    "wof:placetype":"venue"
},
  "geometry": {"coordinates":[-72.27862500000001,45.403866],"type":"Point"}
}