{
  "type": "Feature",
  "properties": {
    "addr:full":"44 King St E Stoney Creek ON L8G 1K1",
    "addr:housenumber":"44",
    "addr:postcode":"l8g 1k1",
    "addr:street":"King St E",
    "iso:country":"CA",
    "sg:address":"44 King St E",
    "sg:city":"Stoney Creek",
    "sg:classifiers":[
        {
            "category":"Shopping",
            "subcategory":"Books",
            "type":"Retail Goods"
        }
    ],
    "sg:phone":"+1 905 664 3777",
    "sg:postcode":"L8G 1K1",
    "sg:province":"ON",
    "sg:tags":[
        "comic"
    ],
    "wof:name":"Comic 1 Books",
    "wof:placetype":"venue"
},
  "geometry": {"coordinates":[-79.755959,43.216366],"type":"Point"}
}