{
  "type": "Feature",
  "properties": {
    "iso:country":"CA",
    "sg:address":"3181 Wolfedale Rd",
    "sg:city":"Mississauga",
    "sg:classifiers":[
        {
            "category":"Retail",
            "subcategory":"Auto Repair",
            "type":"Services"
        }
    ],
    "sg:phone":"+1 905 306 8866",
    "sg:postcode":"L5C 1V8",
    "sg:province":"ON",
    "sg:tags":[
        "repairing",
        "automobile"
    ],
    "wof:name":"Royal Auto Ctr",
    "wof:placetype":"venue"
},
  "geometry": {"coordinates":[-79.6408,43.566486],"type":"Point"}
}