{
  "type": "Feature",
  "properties": {
    "addr:full":"9816 School Rd Coldstream BC V1B 3C7",
    "addr:housenumber":"9816",
    "addr:postcode":"bc v1b 3c7",
    "addr:street":"School Rd",
    "iso:country":"CA",
    "sg:address":"9816 School Rd",
    "sg:city":"Coldstream",
    "sg:classifiers":[
        {
            "category":"Social Services",
            "subcategory":"Adult Care",
            "type":"Services"
        }
    ],
    "sg:phone":"+1 250 542 8853",
    "sg:postcode":"V1B 3C7",
    "sg:province":"BC",
    "sg:tags":[
        "community",
        "facility"
    ],
    "wof:name":"Willowbrook Lodge",
    "wof:placetype":"venue"
},
  "geometry": {"coordinates":[-119.10753631599999,50.2321548462],"type":"Point"}
}