{
  "type": "Feature",
  "properties": {
    "addr:full":"147 John St N Arnprior ON K7S 2N8",
    "addr:housenumber":"147",
    "addr:postcode":"k7s 2n8",
    "addr:street":"John St N",
    "iso:country":"CA",
    "sg:address":"147 John St N",
    "sg:city":"Arnprior",
    "sg:classifiers":[
        {
            "category":"Cinema",
            "subcategory":"Movie Theater",
            "type":"Entertainment"
        }
    ],
    "sg:phone":"+1 613 623 4007",
    "sg:postcode":"K7S 2N8",
    "sg:province":"ON",
    "wof:name":"O'Brien Theatre",
    "wof:placetype":"venue"
},
  "geometry": {"coordinates":[-76.3533630371,45.4343223572],"type":"Point"}
}