{
  "type": "Feature",
  "properties": {
    "addr:full":"1852 Main St Bear River NS B0S 1B0",
    "addr:housenumber":"1852",
    "addr:postcode":"b0s 1b0",
    "addr:street":"Main St",
    "iso:country":"CA",
    "sg:address":"1852 Main St",
    "sg:city":"Bear River",
    "sg:classifiers":[
        {
            "category":"Food & Beverages",
            "subcategory":"Groceries & Convenience Stores",
            "type":"Retail Goods"
        }
    ],
    "sg:phone":"+1 902 467 3543",
    "sg:postcode":"B0S 1B0",
    "sg:province":"NS",
    "sg:tags":[
        "grocer"
    ],
    "wof:name":"Cherry Brook Grocery",
    "wof:placetype":"venue"
},
  "geometry": {"coordinates":[-65.65106964109999,44.5734100342],"type":"Point"}
}