{
  "type": "Feature",
  "properties": {
    "addr:full":"11 Donelda Crt Blackstock ON L0B 1B0",
    "addr:housenumber":"11",
    "addr:postcode":"l0b 1b0",
    "addr:street":"Donelda Crt",
    "iso:country":"CA",
    "sg:address":"11 Donelda Crt",
    "sg:city":"Blackstock",
    "sg:classifiers":[
        {
            "category":"Home & Garden",
            "subcategory":"Building Materials",
            "type":"Retail Goods"
        }
    ],
    "sg:phone":"+1 905 986 9627",
    "sg:postcode":"L0B 1B0",
    "sg:province":"ON",
    "sg:tags":[
        "glass",
        "leaded"
    ],
    "wof:name":"Looking Glass",
    "wof:placetype":"venue"
},
  "geometry": {"coordinates":[-78.81649,44.109634],"type":"Point"}
}