{
  "type": "Feature",
  "properties": {
    "addr:full":"3073 Ch Sainte-Foy Sainte-Foy QC G1X 1P7",
    "addr:postcode":"3073;g1x 1p7",
    "addr:street":"Ch Sainte-Foy",
    "iso:country":"CA",
    "sg:address":"3073 Ch Sainte-Foy",
    "sg:city":"Sainte-Foy",
    "sg:classifiers":[
        {
            "category":"Retail",
            "subcategory":"Auto Repair",
            "type":"Services"
        }
    ],
    "sg:phone":"+1 418 653 6262",
    "sg:postcode":"G1X 1P7",
    "sg:province":"QC",
    "sg:tags":[
        "repairing",
        "automobile"
    ],
    "wof:name":"Multifreins Inc",
    "wof:placetype":"venue"
},
  "geometry": {"coordinates":[-71.291763,46.769211],"type":"Point"}
}