{
  "type": "Feature",
  "properties": {
    "addr:full":"Markham ON L3R 9T9",
    "addr:postcode":"l3r 9t9",
    "iso:country":"CA",
    "sg:city":"Markham",
    "sg:classifiers":[
        {
            "category":"Professional",
            "subcategory":"Art Services",
            "type":"Services"
        }
    ],
    "sg:phone":"+1 905 477 9995",
    "sg:postcode":"L3R 9T9",
    "sg:province":"ON",
    "sg:tags":[
        "photographer"
    ],
    "wof:name":"Mc Crae Studios Inc",
    "wof:placetype":"venue"
},
  "geometry": {"coordinates":[-79.359734,43.832394],"type":"Point"}
}