{
  "type": "Feature",
  "properties": {
    "addr:full":"Kakabeka Falls ON P0T 1W0",
    "addr:postcode":"p0t 1w0",
    "addr:street":"Kakabeka Falls",
    "iso:country":"CA",
    "sg:city":"Kakabeka Falls",
    "sg:classifiers":[
        {
            "category":"Wholesale",
            "subcategory":"Construction Materials",
            "type":"Manufacturing & Wholesale Goods"
        }
    ],
    "sg:phone":"+1 807 475 4096",
    "sg:postcode":"P0T 1W0",
    "sg:province":"ON",
    "sg:tags":[
        "sand",
        "gravel",
        "general",
        "contractor"
    ],
    "wof:name":"Hacquoil Construction Ltd",
    "wof:placetype":"venue"
},
  "geometry": {"coordinates":[-89.614563,48.401741],"type":"Point"}
}