{
  "type": "Feature",
  "properties": {
    "addr:full":"360 Applewood Cres Concord ON L4K 4V2",
    "addr:housenumber":"360",
    "addr:postcode":"l4k 4v2",
    "addr:street":"Applewood Cres",
    "iso:country":"CA",
    "sg:address":"360 Applewood Cres",
    "sg:city":"Concord",
    "sg:classifiers":[
        {
            "category":"Home & Garden",
            "subcategory":"Building Materials",
            "type":"Retail Goods"
        }
    ],
    "sg:phone":"+1 905 669 7800",
    "sg:postcode":"L4K 4V2",
    "sg:province":"ON",
    "sg:tags":[
        "glass",
        "window",
        "plate"
    ],
    "wof:name":"Apple Auto Glass Ltd",
    "wof:placetype":"venue"
},
  "geometry": {"coordinates":[-79.53928399999999,43.805622],"type":"Point"}
}