{
  "type": "Feature",
  "properties": {
    "addr:full":"794 Mount Pleasant Rd Toronto ON M4P 2L2",
    "addr:housenumber":"794",
    "addr:postcode":"m4p 2l2",
    "addr:street":"Mount Pleasant Rd",
    "iso:country":"CA",
    "sg:address":"794 Mount Pleasant Rd",
    "sg:city":"Toronto",
    "sg:classifiers":[
        {
            "category":"Restaurant",
            "type":"Food & Drink"
        }
    ],
    "sg:phone":"+1 416 486 6911",
    "sg:postcode":"M4P 2L2",
    "sg:province":"ON",
    "sg:tags":[
        "shop",
        "coffee"
    ],
    "wof:name":"Second Cup",
    "wof:placetype":"venue"
},
  "geometry": {"coordinates":[-79.39052599999999,43.708847],"type":"Point"}
}