{
  "type": "Feature",
  "properties": {
    "addr:full":"Mississauga ON L4V 1R9",
    "addr:postcode":"l4v 1r9",
    "iso:country":"CA",
    "sg:city":"Mississauga",
    "sg:classifiers":[
        {
            "category":"Freight",
            "type":"Transportation"
        }
    ],
    "sg:phone":"+1 905 672 6255",
    "sg:postcode":"L4V 1R9",
    "sg:province":"ON",
    "sg:tags":[
        "broker",
        "customs"
    ],
    "wof:name":"Cole International Inc",
    "wof:placetype":"venue"
},
  "geometry": {"coordinates":[-79.608559,43.686085],"type":"Point"}
}