{
  "type": "Feature",
  "properties": {
    "addr:full":"248 Av Bethany Lachute QC J8H 2M8",
    "addr:postcode":"j8h 2m8",
    "addr:street":"248 Av Bethany",
    "iso:country":"CA",
    "sg:address":"248 Av Bethany",
    "sg:city":"Lachute",
    "sg:classifiers":[
        {
            "category":"Retail",
            "subcategory":"Auto Repair",
            "type":"Services"
        }
    ],
    "sg:phone":"+1 450 562 8228",
    "sg:postcode":"J8H 2M8",
    "sg:province":"QC",
    "sg:tags":[
        "repairing",
        "automobile"
    ],
    "wof:name":"Garage Brunet Yvon",
    "wof:placetype":"venue"
},
  "geometry": {"coordinates":[-74.3305969238,45.6508560181],"type":"Point"}
}