{
  "type": "Feature",
  "properties": {
    "addr:full":"14 Mackinnon Dr O'Leary PE C0B 1V0",
    "addr:housenumber":"14",
    "addr:postcode":"c0b 1v0",
    "addr:street":"Mackinnon Dr",
    "iso:country":"CA",
    "sg:address":"14 Mackinnon Dr",
    "sg:city":"O'Leary",
    "sg:classifiers":[
        {
            "category":"Health Services",
            "subcategory":"Hospital",
            "type":"Services"
        }
    ],
    "sg:phone":"+1 902 859 8700",
    "sg:postcode":"C0B 1V0",
    "sg:province":"PE",
    "wof:name":"Community Hospital",
    "wof:placetype":"venue"
},
  "geometry": {"coordinates":[-64.238243,46.705643],"type":"Point"}
}