{
  "type": "Feature",
  "properties": {
    "iso:country":"CA",
    "sg:address":"617 Rue Principale",
    "sg:city":"Lachute",
    "sg:classifiers":[
        {
            "category":"Health Services",
            "subcategory":"Doctor",
            "type":"Services"
        }
    ],
    "sg:phone":"+1 450 562 3101",
    "sg:postcode":"J8H 1Y8",
    "sg:province":"QC",
    "sg:tags":[
        "dentist"
    ],
    "wof:name":"Korzinstone, Ronald DDS",
    "wof:placetype":"venue"
},
  "geometry": {"coordinates":[-74.330704,45.657871],"type":"Point"}
}