{
  "type": "Feature",
  "properties": {
    "addr:full":"Westmount QC H3Z 2M9",
    "addr:postcode":"h3z 2m9",
    "iso:country":"CA",
    "sg:city":"Westmount",
    "sg:classifiers":[
        {
            "category":"Professional",
            "subcategory":"Art Services",
            "type":"Services"
        }
    ],
    "sg:phone":"+1 514 333 3922",
    "sg:postcode":"H3Z 2M9",
    "sg:province":"QC",
    "sg:tags":[
        "graphic",
        "designer"
    ],
    "wof:name":"William Marler Graphic Design",
    "wof:placetype":"venue"
},
  "geometry": {"coordinates":[-73.600784,45.477619],"type":"Point"}
}