{
  "type": "Feature",
  "properties": {
    "addr:full":"Breslau ON N0B 1M0",
    "addr:postcode":"n0b 1m0",
    "iso:country":"CA",
    "sg:city":"Breslau",
    "sg:classifiers":[
        {
            "category":"Retail",
            "subcategory":"Auto Repair",
            "type":"Services"
        }
    ],
    "sg:phone":"+1 519 648 2100",
    "sg:postcode":"N0B 1M0",
    "sg:province":"ON",
    "sg:tags":[
        "repairing",
        "automobile"
    ],
    "wof:name":"Dr Mechanic",
    "wof:placetype":"venue"
},
  "geometry": {"coordinates":[-80.40915679930001,43.4684410095],"type":"Point"}
}