{
  "type": "Feature",
  "properties": {
    "addr:full":"1 Crofton Rd Nepean ON K2G 0N1",
    "addr:housenumber":"1",
    "addr:postcode":"k2g 0n1",
    "addr:street":"Crofton Rd",
    "iso:country":"CA",
    "sg:address":"1 Crofton Rd",
    "sg:city":"Nepean",
    "sg:classifiers":[
        {
            "category":"Professional",
            "subcategory":"Detective & Security Services",
            "type":"Services"
        }
    ],
    "sg:phone":"+1 613 828 5288",
    "sg:postcode":"K2G 0N1",
    "sg:province":"ON",
    "sg:tags":[
        "investigator"
    ],
    "wof:name":"Loss Prevention Intl",
    "wof:placetype":"venue"
},
  "geometry": {"coordinates":[-75.77954864500001,45.3359222412],"type":"Point"}
}