{
  "type": "Feature",
  "properties": {
    "addr:full":"Montreal QC H2Z 1B1",
    "addr:postcode":"h2z 1b1",
    "iso:country":"CA",
    "sg:city":"Montreal",
    "sg:classifiers":[
        {
            "category":"Parking",
            "type":"Transportation"
        }
    ],
    "sg:phone":"+1 514 288 2727",
    "sg:postcode":"H2Z 1B1",
    "sg:province":"QC",
    "sg:tags":[
        "garage"
    ],
    "wof:name":"Stationnement Ideal Inc",
    "wof:placetype":"venue"
},
  "geometry": {"coordinates":[-73.557137,45.514172],"type":"Point"}
}