{
  "type": "Feature",
  "properties": {
    "addr:full":"46 Stanley Rd Lake Cowichan BC V0R 2G0",
    "addr:housenumber":"46",
    "addr:postcode":"v0r 2g0",
    "addr:street":"Stanley Rd",
    "iso:country":"CA",
    "sg:address":"46 Stanley Rd",
    "sg:city":"Lake Cowichan",
    "sg:classifiers":[
        {
            "category":"Health Services",
            "subcategory":"Doctor",
            "type":"Services"
        }
    ],
    "sg:phone":"+1 250 749 4114",
    "sg:postcode":"V0R 2G0",
    "sg:province":"BC",
    "sg:tags":[
        "physician",
        "surgeon"
    ],
    "wof:name":"Postuk, Peter MD",
    "wof:placetype":"venue"
},
  "geometry": {"coordinates":[-124.050308,48.826542],"type":"Point"}
}