{
  "type": "Feature",
  "properties": {
    "addr:full":"Burlington ON L7L 5Z4",
    "addr:postcode":"l7l 5z4",
    "iso:country":"CA",
    "sg:city":"Burlington",
    "sg:classifiers":[
        {
            "category":"Banks & Credit Unions",
            "subcategory":"Investment Brokerage",
            "type":"Services"
        }
    ],
    "sg:phone":"+1 905 336 9544",
    "sg:postcode":"L7L 5Z4",
    "sg:province":"ON",
    "sg:tags":[
        "consultant",
        "planning",
        "financial"
    ],
    "wof:name":"Burgeonvest Securities Ltd",
    "wof:placetype":"venue"
},
  "geometry": {"coordinates":[-79.784554,43.370312],"type":"Point"}
}