{
  "type": "Feature",
  "properties": {
    "iso:country":"CA",
    "sg:address":"2200 25th Ave",
    "sg:city":"Regina",
    "sg:classifiers":[
        {
            "category":"Organizations",
            "subcategory":"Religious Organization",
            "type":"Services"
        }
    ],
    "sg:phone":"+1 306 791 9576",
    "sg:postcode":"S4S 4E6",
    "sg:province":"SK",
    "sg:tags":[
        "church"
    ],
    "wof:name":"Regina Regional Tribunal",
    "wof:placetype":"venue"
},
  "geometry": {"coordinates":[-104.61214447,50.4189147949],"type":"Point"}
}