{
  "type": "Feature",
  "properties": {
    "addr:full":"2941 Forest Rd Stratford ON N5A 6S5",
    "addr:housenumber":"2941",
    "addr:postcode":"n5a 6s5",
    "addr:street":"Forest Rd",
    "iso:country":"CA",
    "sg:address":"2941 Forest Rd",
    "sg:city":"Stratford",
    "sg:classifiers":[
        {
            "category":"Travel",
            "subcategory":"Hotels & Motels",
            "type":"Entertainment"
        }
    ],
    "sg:phone":"+1 519 271 4573",
    "sg:postcode":"N5A 6S5",
    "sg:province":"ON",
    "wof:name":"Forest Motel",
    "wof:placetype":"venue"
},
  "geometry": {"coordinates":[-80.98192596440001,43.370136261],"type":"Point"}
}