{
  "type": "Feature",
  "properties": {
    "addr:full":"1160 Av Laurier E Montreal QC H2J 1G7",
    "addr:housenumber":"1160",
    "addr:postcode":"h2j 1g7",
    "addr:street":"Av Laurier E",
    "iso:country":"CA",
    "sg:address":"1160 Av Laurier E",
    "sg:city":"Montreal",
    "sg:classifiers":[
        {
            "category":"Personal",
            "type":"Services"
        }
    ],
    "sg:phone":"+1 514 270 1160",
    "sg:postcode":"H2J 1G7",
    "sg:province":"QC",
    "sg:tags":[
        "dating"
    ],
    "wof:name":"Rencontre Selecte Plus Inc",
    "wof:placetype":"venue"
},
  "geometry": {"coordinates":[-73.585358,45.531441],"type":"Point"}
}