{
  "type": "Feature",
  "properties": {
    "addr:full":"4152 Carlyon Line Orillia ON L3V 6H4",
    "addr:housenumber":"4152",
    "addr:postcode":"l3v 6h4",
    "addr:street":"Carlyon Line",
    "iso:country":"CA",
    "sg:address":"4152 Carlyon Line",
    "sg:city":"Orillia",
    "sg:classifiers":[
        {
            "category":"Wholesale",
            "subcategory":"Machinery & Supplies",
            "type":"Manufacturing & Wholesale Goods"
        }
    ],
    "sg:phone":"+1 705 325 3222",
    "sg:postcode":"L3V 6H4",
    "sg:province":"ON",
    "sg:tags":[
        "equipment",
        "mining"
    ],
    "wof:name":"Pajari Instruments Ltd",
    "wof:placetype":"venue"
},
  "geometry": {"coordinates":[-79.418228,44.60659],"type":"Point"}
}