{
  "type": "Feature",
  "properties": {
    "addr:full":"201 George St N Peterborough ON K9J 3G7",
    "addr:housenumber":"201",
    "addr:postcode":"k9j 3g7",
    "addr:street":"George St N",
    "iso:country":"CA",
    "sg:address":"201 George St N",
    "sg:city":"Peterborough",
    "sg:classifiers":[
        {
            "category":"Shopping",
            "subcategory":"Used Merchandise",
            "type":"Retail Goods"
        }
    ],
    "sg:phone":"+1 705 876 6409",
    "sg:postcode":"K9J 3G7",
    "sg:province":"ON",
    "sg:tags":[
        "antique"
    ],
    "wof:name":"Queen's Crown Antiques",
    "wof:placetype":"venue"
},
  "geometry": {"coordinates":[-78.319778,44.299709],"type":"Point"}
}