{
  "type": "Feature",
  "properties": {
    "addr:full":"60 Boul Des Bois-Francs S Victoriaville QC G6P 4S1",
    "addr:housenumber":"60",
    "addr:postcode":"g6p 4s1",
    "addr:street":"Boul Des Bois-Francs S",
    "iso:country":"CA",
    "sg:address":"60 Boul Des Bois-Francs S",
    "sg:city":"Victoriaville",
    "sg:classifiers":[
        {
            "category":"Professional",
            "subcategory":"Business Services",
            "type":"Services"
        }
    ],
    "sg:phone":"+1 819 752 6535",
    "sg:postcode":"G6P 4S1",
    "sg:province":"QC",
    "sg:tags":[
        "interior",
        "consultant",
        "design",
        "decorator"
    ],
    "wof:name":"Roger Gelinas Inc",
    "wof:placetype":"venue"
},
  "geometry": {"coordinates":[-71.9493637085,46.0580711365],"type":"Point"}
}