{
  "type": "Feature",
  "properties": {
    "addr:full":"46168 First Ave Chilliwack BC V2P 1W3",
    "addr:housenumber":"46168",
    "addr:postcode":"v2p 1w3",
    "addr:street":"First Ave",
    "iso:country":"CA",
    "sg:address":"46168 First Ave",
    "sg:city":"Chilliwack",
    "sg:classifiers":[
        {
            "category":"Retail",
            "subcategory":"Portrait Studio",
            "type":"Services"
        }
    ],
    "sg:phone":"+1 604 792 8313",
    "sg:postcode":"V2P 1W3",
    "sg:province":"BC",
    "sg:tags":[
        "photographer"
    ],
    "wof:name":"Don R Young Photography Ltd",
    "wof:placetype":"venue"
},
  "geometry": {"coordinates":[-121.94670105,49.1687355042],"type":"Point"}
}