{
  "type": "Feature",
  "properties": {
    "addr:full":"565 Sherbourne St Toronto ON M4X 1W7",
    "addr:housenumber":"565",
    "addr:postcode":"m4x 1w7",
    "addr:street":"Sherbourne St",
    "iso:country":"CA",
    "sg:address":"565 Sherbourne St",
    "sg:city":"Toronto",
    "sg:classifiers":[
        {
            "category":"Shopping",
            "subcategory":"Pharmacy",
            "type":"Retail Goods"
        }
    ],
    "sg:phone":"+1 416 972 0189",
    "sg:postcode":"M4X 1W7",
    "sg:province":"ON",
    "wof:name":"Sherbourne Pharmacy",
    "wof:placetype":"venue"
},
  "geometry": {"coordinates":[-79.3755950928,43.6695365906],"type":"Point"}
}