{
  "type": "Feature",
  "properties": {
    "addr:full":"1054 Rang 3 # A St-Nazaire-Du-Lac-St-Jean QC G0W 2V0",
    "addr:housenumber":"1054",
    "addr:postcode":"g0w 2v0",
    "addr:street":"Rang 3 # A St-Nazaire-Du-Lac-St-Jean",
    "iso:country":"CA",
    "sg:address":"1054 Rang 3 # A",
    "sg:city":"St-Nazaire-Du-Lac-St-Jean",
    "sg:classifiers":[
        {
            "category":"Building & Trades",
            "subcategory":"Construction",
            "type":"Services"
        }
    ],
    "sg:phone":"+1 418 662 4070",
    "sg:postcode":"G0W 2V0",
    "sg:province":"QC",
    "sg:tags":[
        "designer",
        "dealer",
        "pool",
        "swimming"
    ],
    "wof:name":"Piscines Escompte Plus",
    "wof:placetype":"venue"
},
  "geometry": {"coordinates":[-71.4869308472,48.5753669739],"type":"Point"}
}