{
  "type": "Feature",
  "properties": {
    "addr:full":"626 Second St New Westminster BC V3L 2M5",
    "addr:housenumber":"626",
    "addr:postcode":"v3l 2m5",
    "addr:street":"Second St",
    "iso:country":"CA",
    "sg:address":"626 Second St",
    "sg:city":"New Westminster",
    "sg:classifiers":[
        {
            "category":"Building & Trades",
            "subcategory":"Cleaning & Sanitation",
            "type":"Services"
        }
    ],
    "sg:phone":"+1 604 526 6402",
    "sg:postcode":"V3L 2M5",
    "sg:province":"BC",
    "sg:tags":[
        "window"
    ],
    "wof:name":"J R Window Cleaning",
    "wof:placetype":"venue"
},
  "geometry": {"coordinates":[-122.915245,49.217228],"type":"Point"}
}