{
  "type": "Feature",
  "properties": {
    "iso:country":"CA",
    "sg:address":"59 Wilson St W",
    "sg:city":"Ancaster",
    "sg:classifiers":[
        {
            "category":"Banks & Credit Unions",
            "subcategory":"Bank",
            "type":"Services"
        }
    ],
    "sg:phone":"+1 905 648 4411",
    "sg:postcode":"L9G 1N1",
    "sg:province":"ON",
    "wof:name":"Royal Bank Financial Group",
    "wof:placetype":"venue"
},
  "geometry": {"coordinates":[-79.9897232056,43.2164154053],"type":"Point"}
}