{
  "type": "Feature",
  "properties": {
    "addr:full":"501 Bryne Dr Barrie ON L4N 9P7",
    "addr:housenumber":"501",
    "addr:postcode":"l4n 9p7",
    "addr:street":"Bryne Dr",
    "iso:country":"CA",
    "sg:address":"501 Bryne Dr",
    "sg:city":"Barrie",
    "sg:classifiers":[
        {
            "category":"Restaurant",
            "type":"Food & Drink"
        }
    ],
    "sg:phone":"+1 705 726 8191",
    "sg:postcode":"L4N 9P7",
    "sg:province":"ON",
    "wof:name":"Williams Coffee Pub",
    "wof:placetype":"venue"
},
  "geometry": {"coordinates":[-79.6892089844,44.3320388794],"type":"Point"}
}