{
  "type": "Feature",
  "properties": {
    "iso:country":"CA",
    "sg:address":"3211 Grafton Ave",
    "sg:city":"Qualicum Beach",
    "sg:classifiers":[
        {
            "category":"Building & Trades",
            "subcategory":"Plumbing",
            "type":"Services"
        }
    ],
    "sg:phone":"+1 250 752 6847",
    "sg:postcode":"V9K 1W7",
    "sg:province":"BC",
    "sg:tags":[
        "contractor"
    ],
    "wof:name":"Sprinkling Dan-Plbg & Htg Ltd",
    "wof:placetype":"venue"
},
  "geometry": {"coordinates":[-124.441703796,49.3467063904],"type":"Point"}
}