{
  "type": "Feature",
  "properties": {
    "addr:full":"1619 29th St W Saskatoon SK S7L 0N6",
    "addr:housenumber":"1619",
    "addr:postcode":"s7l 0n6",
    "addr:street":"29Th St W",
    "iso:country":"CA",
    "sg:address":"1619 29th St W",
    "sg:city":"Saskatoon",
    "sg:classifiers":[
        {
            "category":"Retail",
            "subcategory":"Animal Services",
            "type":"Services"
        }
    ],
    "sg:phone":"+1 306 384 2111",
    "sg:postcode":"S7L 0N6",
    "sg:province":"SK",
    "sg:tags":[
        "pet",
        "grooming",
        "washing"
    ],
    "wof:name":"Bow Wow Boutique",
    "wof:placetype":"venue"
},
  "geometry": {"coordinates":[-106.694603,52.136822],"type":"Point"}
}