{
  "type": "Feature",
  "properties": {
    "addr:full":"335 Lacasse Ave Vanier ON K1L 7A8",
    "addr:housenumber":"335",
    "addr:postcode":"k1l 7a8",
    "addr:street":"Lacasse Ave",
    "iso:country":"CA",
    "sg:address":"335 Lacasse Ave",
    "sg:city":"Vanier",
    "sg:classifiers":[
        {
            "category":"Food & Beverages",
            "subcategory":"Groceries & Convenience Stores",
            "type":"Retail Goods"
        }
    ],
    "sg:phone":"+1 613 749 4758",
    "sg:postcode":"K1L 7A8",
    "sg:province":"ON",
    "sg:tags":[
        "grocer"
    ],
    "wof:name":"Thomas Food Market",
    "wof:placetype":"venue"
},
  "geometry": {"coordinates":[-75.6566162109,45.4344978333],"type":"Point"}
}