{
  "type": "Feature",
  "properties": {
    "addr:full":"150 Second St Tofino BC V0R 2Z0",
    "addr:housenumber":"150",
    "addr:postcode":"v0r 2z0",
    "addr:street":"Second St",
    "iso:country":"CA",
    "sg:address":"150 Second St",
    "sg:city":"Tofino",
    "sg:classifiers":[
        {
            "category":"Government",
            "subcategory":"Fire Station",
            "type":"Public Place"
        }
    ],
    "sg:phone":"+1 250 725 3365",
    "sg:postcode":"V0R 2Z0",
    "sg:province":"BC",
    "sg:tags":[
        "department"
    ],
    "wof:name":"Tofino Fire Dept",
    "wof:placetype":"venue"
},
  "geometry": {"coordinates":[-125.906547546,49.1526107788],"type":"Point"}
}