{
  "type": "Feature",
  "properties": {
    "addr:full":"Eckville AB T0M 0X0",
    "addr:postcode":"t0m 0x0",
    "iso:country":"CA",
    "sg:city":"Eckville",
    "sg:classifiers":[
        {
            "category":"Mining & Drilling",
            "type":"Manufacturing & Wholesale Goods"
        }
    ],
    "sg:phone":"+1 403 729 2381",
    "sg:postcode":"T0M 0X0",
    "sg:province":"AB",
    "sg:tags":[
        "field",
        "oil"
    ],
    "wof:name":"Tri-Don Oilfield Svc Ltd",
    "wof:placetype":"venue"
},
  "geometry": {"coordinates":[-114.361465454,52.3595733643],"type":"Point"}
}