{
  "type": "Feature",
  "properties": {
    "iso:country":"CA",
    "sg:city":"Kingston",
    "sg:classifiers":[
        {
            "category":"Health Services",
            "subcategory":"Chiropractor",
            "type":"Services"
        }
    ],
    "sg:phone":"+1 613 389 2125",
    "sg:postcode":"K7P 1T5",
    "sg:province":"ON",
    "wof:name":"Bayridge Chiropractic Ctr",
    "wof:placetype":"venue"
},
  "geometry": {"coordinates":[-76.5890579224,44.2521362305],"type":"Point"}
}