{
  "type": "Feature",
  "properties": {
    "addr:full":"522 1/2 Second St S Kenora ON P9N 1G8",
    "addr:housenumber":"522 1 / 2",
    "addr:postcode":"p9n 1g8",
    "addr:street":"Second St S",
    "iso:country":"CA",
    "sg:address":"522 1/2 Second St S",
    "sg:city":"Kenora",
    "sg:classifiers":[
        {
            "category":"Shopping",
            "subcategory":"Computers & Home Electronics",
            "type":"Retail Goods"
        }
    ],
    "sg:phone":"+1 807 468 5617",
    "sg:postcode":"P9N 1G8",
    "sg:province":"ON",
    "sg:tags":[
        "radio",
        "television",
        "video",
        "equipment"
    ],
    "wof:name":"Rolf's Tv & Electronic Svc",
    "wof:placetype":"venue"
},
  "geometry": {"coordinates":[-94.484161,49.765388],"type":"Point"}
}