{
  "type": "Feature",
  "properties": {
    "addr:full":"445 Rue Saint-Jean Drummondville QC J2B 5L7",
    "addr:housenumber":"445",
    "addr:postcode":"j2b 5l7",
    "addr:street":"Rue Saint-Jean",
    "iso:country":"CA",
    "sg:address":"445 Rue Saint-Jean",
    "sg:city":"Drummondville",
    "sg:classifiers":[
        {
            "category":"Food & Beverages",
            "subcategory":"Dairy",
            "type":"Retail Goods"
        }
    ],
    "sg:phone":"+1 819 477 4591",
    "sg:postcode":"J2B 5L7",
    "sg:province":"QC",
    "sg:tags":[
        "product"
    ],
    "wof:name":"Fromages D'Ernest",
    "wof:placetype":"venue"
},
  "geometry": {"coordinates":[-72.48577899999999,45.875725],"type":"Point"}
}