{
  "type": "Feature",
  "properties": {
    "addr:full":"851 Richmond Rd # 806 Ottawa ON K2A 3X2",
    "addr:housenumber":"851",
    "addr:postcode":"k2a 3x2",
    "addr:street":"Richmond Rd # 806",
    "iso:country":"CA",
    "sg:address":"851 Richmond Rd # 806",
    "sg:city":"Ottawa",
    "sg:classifiers":[
        {
            "category":"Health Services",
            "subcategory":"Health Practitioner",
            "type":"Services"
        }
    ],
    "sg:phone":"+1 613 860 1547",
    "sg:postcode":"K2A 3X2",
    "sg:province":"ON",
    "sg:tags":[
        "homeopath"
    ],
    "wof:name":"Marsat, Lyse",
    "wof:placetype":"venue"
},
  "geometry": {"coordinates":[-75.7727508545,45.3799743652],"type":"Point"}
}