{
  "type": "Feature",
  "properties": {
    "addr:full":"38 Birch Cres Morris MB R0G 1K0",
    "addr:housenumber":"38",
    "addr:postcode":"r0g 1k0",
    "addr:street":"Birch Cres",
    "iso:country":"CA",
    "sg:address":"38 Birch Cres",
    "sg:city":"Morris",
    "sg:classifiers":[
        {
            "category":"Professional",
            "subcategory":"Testing Lab",
            "type":"Services"
        }
    ],
    "sg:phone":"+1 204 746 8164",
    "sg:postcode":"R0G 1K0",
    "sg:province":"MB",
    "sg:tags":[
        "seed"
    ],
    "wof:name":"Valley Seed Laboratory Ltd",
    "wof:placetype":"venue"
},
  "geometry": {"coordinates":[-97.366043,49.354687],"type":"Point"}
}