{
  "type": "Feature",
  "properties": {
    "addr:full":"62 Rue Saint-Antoine S Granby QC J2G 6W5",
    "addr:housenumber":"62",
    "addr:postcode":"j2g 6w5",
    "addr:street":"Rue Saint-Antoine S Granby",
    "iso:country":"CA",
    "sg:address":"62 Rue Saint-Antoine S",
    "sg:city":"Granby",
    "sg:classifiers":[
        {
            "category":"Personal",
            "subcategory":"Tanning Parlor",
            "type":"Services"
        }
    ],
    "sg:phone":"+1 450 776 1063",
    "sg:postcode":"J2G 6W5",
    "sg:province":"QC",
    "sg:tags":[
        "salon"
    ],
    "wof:name":"Xtreme Seduction",
    "wof:placetype":"venue"
},
  "geometry": {"coordinates":[-72.731567,45.399574],"type":"Point"}
}