{
  "type": "Feature",
  "properties": {
    "addr:full":"Saint-Malachie QC G0R 3N0",
    "addr:postcode":"g0r 3n0",
    "iso:country":"CA",
    "sg:city":"Saint-Malachie",
    "sg:classifiers":[
        {
            "category":"Wholesale",
            "subcategory":"Meat",
            "type":"Manufacturing & Wholesale Goods"
        }
    ],
    "sg:phone":"+1 418 642 2066",
    "sg:postcode":"G0R 3N0",
    "sg:province":"QC",
    "sg:tags":[
        "butchering"
    ],
    "wof:name":"Boucherie Clement Guillemette",
    "wof:placetype":"venue"
},
  "geometry": {"coordinates":[-70.78318,46.534382],"type":"Point"}
}