{
  "type": "Feature",
  "properties": {
    "addr:full":"350 St George St Annapolis Royal NS B0S 1A0",
    "addr:housenumber":"350",
    "addr:postcode":"b0s 1a0",
    "addr:street":"St George St",
    "iso:country":"CA",
    "sg:address":"350 St George St",
    "sg:city":"Annapolis Royal",
    "sg:classifiers":[
        {
            "category":"Travel",
            "subcategory":"Hotels & Motels",
            "type":"Entertainment"
        }
    ],
    "sg:phone":"+1 902 532 5750",
    "sg:postcode":"B0S 1A0",
    "sg:province":"NS",
    "wof:name":"Garrison House Inn",
    "wof:placetype":"venue"
},
  "geometry": {"coordinates":[-65.516998,44.742249],"type":"Point"}
}