{
  "type": "Feature",
  "properties": {
    "addr:full":"Beaumont AB T4X 1E5",
    "addr:postcode":"t4x 1e5",
    "iso:country":"CA",
    "sg:city":"Beaumont",
    "sg:classifiers":[
        {
            "category":"Shopping",
            "subcategory":"Florist",
            "type":"Retail Goods"
        }
    ],
    "sg:phone":"+1 780 929 2989",
    "sg:postcode":"T4X 1E5",
    "sg:province":"AB",
    "wof:name":"Beau Villa Flowers & Gifts",
    "wof:placetype":"venue"
},
  "geometry": {"coordinates":[-113.416893,53.354515],"type":"Point"}
}