{
  "type": "Feature",
  "properties": {
    "addr:full":"1713 Av Dollard Lasalle QC H8N 1T7",
    "addr:housenumber":"1713",
    "addr:postcode":"h8n 1t7",
    "addr:street":"Av Dollard",
    "iso:country":"CA",
    "sg:address":"1713 Av Dollard",
    "sg:city":"Lasalle",
    "sg:classifiers":[
        {
            "category":"Restaurant",
            "type":"Food & Drink"
        }
    ],
    "sg:phone":"+1 514 595 3937",
    "sg:postcode":"H8N 1T7",
    "sg:province":"QC",
    "wof:name":"Quy Phi",
    "wof:placetype":"venue"
},
  "geometry": {"coordinates":[-73.630707,45.42873],"type":"Point"}
}