{
  "type": "Feature",
  "properties": {
    "addr:full":"150 Market St Brantford ON N3T 3A4",
    "addr:housenumber":"150",
    "addr:postcode":"n3t 3a4",
    "addr:street":"Market St",
    "iso:country":"CA",
    "sg:address":"150 Market St",
    "sg:city":"Brantford",
    "sg:classifiers":[
        {
            "category":"Home & Garden",
            "subcategory":"Hardware",
            "type":"Retail Goods"
        }
    ],
    "sg:phone":"+1 519 752 3213",
    "sg:postcode":"N3T 3A4",
    "sg:province":"ON",
    "sg:tags":[
        "lock",
        "locksmith"
    ],
    "wof:name":"Feely Hardware Ltd",
    "wof:placetype":"venue"
},
  "geometry": {"coordinates":[-80.2643127441,43.1434211731],"type":"Point"}
}