{
  "type": "Feature",
  "properties": {
    "iso:country":"CA",
    "sg:address":"352 Silvercreek Pky N",
    "sg:city":"Guelph",
    "sg:classifiers":[
        {
            "category":"Wholesale",
            "subcategory":"Machinery & Supplies",
            "type":"Manufacturing & Wholesale Goods"
        }
    ],
    "sg:phone":"+1 519 824 8020",
    "sg:postcode":"N1H 1E7",
    "sg:province":"ON",
    "sg:tags":[
        "director",
        "funeral"
    ],
    "wof:name":"H S Eckels & CO Ltd",
    "wof:placetype":"venue"
},
  "geometry": {"coordinates":[-80.290741,43.547222],"type":"Point"}
}