{
  "type": "Feature",
  "properties": {
    "addr:full":"Halifax NS B3S 1G4",
    "addr:postcode":"b3s 1g4",
    "iso:country":"CA",
    "sg:city":"Halifax",
    "sg:classifiers":[
        {
            "category":"Restaurant",
            "type":"Food & Drink"
        }
    ],
    "sg:phone":"+1 902 450 5643",
    "sg:postcode":"B3S 1G4",
    "sg:province":"NS",
    "wof:name":"Wendy's",
    "wof:placetype":"venue"
},
  "geometry": {"coordinates":[-63.6690292358,44.6363487244],"type":"Point"}
}