{
  "type": "Feature",
  "properties": {
    "addr:full":"1024 Benvenuto Ave Brentwood Bay BC V8M 1A1",
    "addr:housenumber":"1024",
    "addr:postcode":"v8m 1a1",
    "addr:street":"Benvenuto Ave",
    "iso:country":"CA",
    "sg:address":"1024 Benvenuto Ave",
    "sg:city":"Brentwood Bay",
    "sg:classifiers":[
        {
            "category":"Professional",
            "type":"Services"
        }
    ],
    "sg:phone":"+1 250 652 9254",
    "sg:postcode":"V8M 1A1",
    "sg:province":"BC",
    "sg:tags":[
        "consultant",
        "geological"
    ],
    "wof:name":"Monahan Petroleum Consulting",
    "wof:placetype":"venue"
},
  "geometry": {"coordinates":[-123.457191467,48.5629348755],"type":"Point"}
}