{
  "type": "Feature",
  "properties": {
    "addr:full":"351 West St S Orillia ON L3V 5H1",
    "addr:housenumber":"351",
    "addr:postcode":"l3v 5h1",
    "addr:street":"West St S",
    "iso:country":"CA",
    "sg:address":"351 West St S",
    "sg:city":"Orillia",
    "sg:classifiers":[
        {
            "category":"Wholesale",
            "subcategory":"Scrap",
            "type":"Manufacturing & Wholesale Goods"
        }
    ],
    "sg:phone":"+1 705 325 1301",
    "sg:postcode":"L3V 5H1",
    "sg:province":"ON",
    "sg:tags":[
        "metal",
        "iron"
    ],
    "wof:name":"Francoz Iron & Metal Inc",
    "wof:placetype":"venue"
},
  "geometry": {"coordinates":[-79.412659,44.599613],"type":"Point"}
}