{
  "type": "Feature",
  "properties": {
    "iso:country":"CA",
    "sg:address":"711 Finley Ave",
    "sg:city":"Ajax",
    "sg:classifiers":[
        {
            "category":"Professional",
            "subcategory":"Accounting & Tax Preparation",
            "type":"Services"
        }
    ],
    "sg:phone":"+1 905 686 0486",
    "sg:postcode":"L1S 3T1",
    "sg:province":"ON",
    "sg:tags":[
        "accountant",
        "return",
        "filing"
    ],
    "wof:name":"Accounting Tax & Computer Svc",
    "wof:placetype":"venue"
},
  "geometry": {"coordinates":[-79.026215,43.831249],"type":"Point"}
}