{
  "type": "Feature",
  "properties": {
    "addr:full":"711 Finley Ave Ajax ON L1S 3T1",
    "addr:housenumber":"711",
    "addr:postcode":"l1s 3t1",
    "addr:street":"Finley Ave",
    "iso:country":"CA",
    "sg:address":"711 Finley Ave",
    "sg:city":"Ajax",
    "sg:classifiers":[
        {
            "category":"Professional",
            "subcategory":"Accounting & Tax Preparation",
            "type":"Services"
        }
    ],
    "sg:phone":"+1 905 686 0486",
    "sg:postcode":"L1S 3T1",
    "sg:province":"ON",
    "sg:tags":[
        "accountant",
        "return",
        "filing"
    ],
    "wof:name":"Accounting Tax & Computer Svc",
    "wof:placetype":"venue"
},
  "geometry": {"coordinates":[-79.02621499999999,43.831249],"type":"Point"}
}