{
  "type": "Feature",
  "properties": {
    "addr:full":"709 Rue Labbe Thetford Mines QC G6G 2A6",
    "addr:housenumber":"709",
    "addr:postcode":"g6g 2a6",
    "addr:street":"Rue Labbe",
    "iso:country":"CA",
    "sg:address":"709 Rue Labbe",
    "sg:city":"Thetford Mines",
    "sg:classifiers":[
        {
            "category":"Food & Beverages",
            "subcategory":"Bakery",
            "type":"Retail Goods"
        }
    ],
    "sg:phone":"+1 418 338 5255",
    "sg:postcode":"G6G 2A6",
    "sg:province":"QC",
    "sg:tags":[
        "baker"
    ],
    "wof:name":"Patisserie St-Noel Enr",
    "wof:placetype":"venue"
},
  "geometry": {"coordinates":[-71.291573,46.101841],"type":"Point"}
}