{
  "type": "Feature",
  "properties": {
    "addr:full":"Saint-Jerome QC J7Z 5L3",
    "addr:postcode":"j7z 5l3",
    "iso:country":"CA",
    "sg:city":"Saint-Jerome",
    "sg:classifiers":[
        {
            "category":"Recreation",
            "type":"Entertainment"
        }
    ],
    "sg:phone":"+1 450 569 9963",
    "sg:postcode":"J7Z 5L3",
    "sg:province":"QC",
    "sg:tags":[
        "parlor",
        "billiard"
    ],
    "wof:name":"Boules & Drague",
    "wof:placetype":"venue"
},
  "geometry": {"coordinates":[-74.0044326782,45.7768135071],"type":"Point"}
}