{
  "type": "Feature",
  "properties": {
    "addr:full":"620 S 9th Ave Golden BC V0A 1H0",
    "addr:housenumber":"620",
    "addr:postcode":"v0a 1h0",
    "addr:street":"S 9Th Ave",
    "iso:country":"CA",
    "sg:address":"620 S 9th Ave",
    "sg:city":"Golden",
    "sg:classifiers":[
        {
            "category":"Education",
            "subcategory":"School",
            "type":"Public Place"
        }
    ],
    "sg:phone":"+1 250 344 6317",
    "sg:postcode":"V0A 1H0",
    "sg:province":"BC",
    "wof:name":"Lady Grey Elementary School",
    "wof:placetype":"venue"
},
  "geometry": {"coordinates":[-116.96790300000001,51.301807],"type":"Point"}
}