{
  "type": "Feature",
  "properties": {
    "addr:full":"Cap-Rouge QC G1Y 2A4",
    "addr:postcode":"g1y 2a4",
    "iso:country":"CA",
    "sg:city":"Cap-Rouge",
    "sg:classifiers":[
        {
            "category":"Professional",
            "subcategory":"Lawyer & Legal Services",
            "type":"Services"
        }
    ],
    "sg:phone":"+1 418 658 9966",
    "sg:postcode":"G1Y 2A4",
    "sg:province":"QC",
    "sg:tags":[
        "attorney"
    ],
    "wof:name":"Talbot, Richard",
    "wof:placetype":"venue"
},
  "geometry": {"coordinates":[-71.351151,46.755554],"type":"Point"}
}