{
  "type": "Feature",
  "properties": {
    "addr:full":"161 Bank St Ottawa ON K1P 5N7",
    "addr:housenumber":"161",
    "addr:postcode":"k1p 5n7",
    "addr:street":"Bank St",
    "iso:country":"CA",
    "sg:address":"161 Bank St",
    "sg:city":"Ottawa",
    "sg:classifiers":[
        {
            "category":"Shopping",
            "subcategory":"Pharmacy",
            "type":"Retail Goods"
        }
    ],
    "sg:phone":"+1 613 232 1919",
    "sg:postcode":"K1P 5N7",
    "sg:province":"ON",
    "sg:tags":[
        "grocer"
    ],
    "wof:name":"Shoppers Drug Mart",
    "wof:placetype":"venue"
},
  "geometry": {"coordinates":[-75.699074,45.41869],"type":"Point"}
}