{
  "type": "Feature",
  "properties": {
    "addr:full":"480 Mccarthy Blvd N Regina SK S4R 7M2",
    "addr:housenumber":"480",
    "addr:postcode":"s4r 7m2",
    "addr:street":"Mccarthy Blvd N",
    "iso:country":"CA",
    "sg:address":"480 Mccarthy Blvd N",
    "sg:city":"Regina",
    "sg:classifiers":[
        {
            "category":"Restaurant",
            "type":"Food & Drink"
        }
    ],
    "sg:phone":"+1 306 522 2739",
    "sg:postcode":"S4R 7M2",
    "sg:province":"SK",
    "sg:tags":[
        "brewer"
    ],
    "wof:name":"Brewsters Brewing CO & Rstrnt",
    "wof:placetype":"venue"
},
  "geometry": {"coordinates":[-104.664283752,50.4838981628],"type":"Point"}
}