{
  "type": "Feature",
  "properties": {
    "addr:full":"Courtenay BC V9N 1J8",
    "addr:postcode":"v9n 1j8",
    "iso:country":"CA",
    "sg:city":"Courtenay",
    "sg:classifiers":[
        {
            "category":"Restaurant",
            "type":"Food & Drink"
        }
    ],
    "sg:phone":"+1 250 338 9333",
    "sg:postcode":"V9N 1J8",
    "sg:province":"BC",
    "wof:name":"Golden Carriage Restaurant",
    "wof:placetype":"venue"
},
  "geometry": {"coordinates":[-125.00110599999999,49.689964],"type":"Point"}
}