{
  "type": "Feature",
  "properties": {
    "iso:country":"CA",
    "sg:address":"145 Rue DE Martigny O",
    "sg:city":"Saint-Jerome",
    "sg:classifiers":[
        {
            "category":"Professional",
            "subcategory":"Business Services",
            "type":"Services"
        }
    ],
    "sg:phone":"+1 450 436 5540",
    "sg:postcode":"J7Y 2G2",
    "sg:province":"QC",
    "sg:tags":[
        "fire",
        "protection"
    ],
    "wof:name":"Inspection Gamma Inc",
    "wof:placetype":"venue"
},
  "geometry": {"coordinates":[-74.0116119385,45.7797279358],"type":"Point"}
}