{
  "type": "Feature",
  "properties": {
    "addr:full":"344 N Rivermede Rd Concord ON L4K 3N2",
    "addr:housenumber":"344",
    "addr:postcode":"l4k 3n2",
    "addr:street":"N Rivermede Rd",
    "iso:country":"CA",
    "sg:address":"344 N Rivermede Rd",
    "sg:city":"Concord",
    "sg:classifiers":[
        {
            "category":"Building & Trades",
            "subcategory":"Construction",
            "type":"Services"
        }
    ],
    "sg:phone":"+1 905 660 7226",
    "sg:postcode":"L4K 3N2",
    "sg:province":"ON",
    "sg:tags":[
        "general",
        "contractor"
    ],
    "wof:name":"Anacond Contracting Inc",
    "wof:placetype":"venue"
},
  "geometry": {"coordinates":[-79.48347473139999,43.8132209778],"type":"Point"}
}