{
  "type": "Feature",
  "properties": {
    "iso:country":"CA",
    "sg:address":"502 Rue Lamontagne",
    "sg:city":"Repentigny",
    "sg:classifiers":[
        {
            "category":"Building & Trades",
            "subcategory":"Pest Control",
            "type":"Services"
        }
    ],
    "sg:phone":"+1 450 654 6424",
    "sg:postcode":"J6A 8C6",
    "sg:province":"QC",
    "wof:name":"A Advantage Extermination",
    "wof:placetype":"venue"
},
  "geometry": {"coordinates":[-73.449036,45.745003],"type":"Point"}
}