{
  "type": "Feature",
  "properties": {
    "addr:full":"2 Highland Ave Belleville ON K8P 3P9",
    "addr:housenumber":"2",
    "addr:postcode":"k8p 3p9",
    "addr:street":"Highland Ave",
    "iso:country":"CA",
    "sg:address":"2 Highland Ave",
    "sg:city":"Belleville",
    "sg:classifiers":[
        {
            "category":"Building & Trades",
            "subcategory":"Cleaning & Sanitation",
            "type":"Services"
        }
    ],
    "sg:phone":"+1 613 968 8000",
    "sg:postcode":"K8P 3P9",
    "sg:province":"ON",
    "sg:tags":[
        "pavement",
        "sealing",
        "maintenance"
    ],
    "wof:name":"Enviro Sweep Property Mntnc",
    "wof:placetype":"venue"
},
  "geometry": {"coordinates":[-77.39115099999999,44.157257],"type":"Point"}
}