{
  "type": "Feature",
  "properties": {
    "addr:full":"122 Av Saint-Gregoire Beauport QC G1C 2H5",
    "addr:postcode":"qc g1c 2h5",
    "addr:street":"122 Av Saint-Gregoire",
    "iso:country":"CA",
    "sg:address":"122 Av Saint-Gregoire",
    "sg:city":"Beauport",
    "sg:classifiers":[
        {
            "category":"Autos & Motor Vehicles",
            "subcategory":"Auto Supplies",
            "type":"Retail Goods"
        }
    ],
    "sg:phone":"+1 418 661 9072",
    "sg:postcode":"G1C 2H5",
    "sg:province":"QC",
    "sg:tags":[
        "automobile",
        "parts"
    ],
    "wof:name":"Pieces D'Auto Guill",
    "wof:placetype":"venue"
},
  "geometry": {"coordinates":[-71.156029,46.877136],"type":"Point"}
}