{
  "type": "Feature",
  "properties": {
    "addr:full":"1833 Main St E Swan River MB R0L 1Z0",
    "addr:housenumber":"1833",
    "addr:postcode":"r0l 1z0",
    "addr:street":"Main St E Swan",
    "iso:country":"CA",
    "sg:address":"1833 Main St E",
    "sg:city":"Swan River",
    "sg:classifiers":[
        {
            "category":"Autos & Motor Vehicles",
            "subcategory":"Motorcycle Sales",
            "type":"Retail Goods"
        }
    ],
    "sg:phone":"+1 204 734 3066",
    "sg:postcode":"R0L 1Z0",
    "sg:province":"MB",
    "sg:tags":[
        "all",
        "terrain",
        "snowmobile"
    ],
    "wof:name":"William's Auto Electric Svc",
    "wof:placetype":"venue"
},
  "geometry": {"coordinates":[-101.25145000000001,52.107151],"type":"Point"}
}