{
  "type": "Feature",
  "properties": {
    "addr:full":"Sainte-Henedine QC G0S 2R0",
    "addr:postcode":"g0s 2r0",
    "iso:country":"CA",
    "sg:city":"Sainte-Henedine",
    "sg:classifiers":[
        {
            "category":"Farming",
            "subcategory":"Farm",
            "type":"Manufacturing & Wholesale Goods"
        }
    ],
    "sg:phone":"+1 418 935 3738",
    "sg:postcode":"G0S 2R0",
    "sg:province":"QC",
    "wof:name":"Ferme Martin Fortier",
    "wof:placetype":"venue"
},
  "geometry": {"coordinates":[-70.93604999999999,46.56633],"type":"Point"}
}