{
  "type": "Feature",
  "properties": {
    "iso:country":"CA",
    "sg:address":"38 Main St W",
    "sg:city":"Markdale",
    "sg:classifiers":[
        {
            "category":"Shopping",
            "subcategory":"Gifts & Souvenirs",
            "type":"Retail Goods"
        }
    ],
    "sg:phone":"+1 519 986 2720",
    "sg:postcode":"N0C 1H0",
    "sg:province":"ON",
    "sg:tags":[
        "shop"
    ],
    "wof:name":"Mer Car Dept Store",
    "wof:placetype":"venue"
},
  "geometry": {"coordinates":[-80.648994,44.318001],"type":"Point"}
}