{
  "type": "Feature",
  "properties": {
    "addr:full":"4214 99 St NW Edmonton AB T6E 5B3",
    "addr:housenumber":"4214",
    "addr:postcode":"t6e 5b3",
    "addr:street":"99 St Nw",
    "iso:country":"CA",
    "sg:address":"4214 99 St NW",
    "sg:city":"Edmonton",
    "sg:classifiers":[
        {
            "category":"Social Services",
            "type":"Services"
        }
    ],
    "sg:phone":"+1 780 463 3232",
    "sg:postcode":"T6E 5B3",
    "sg:province":"AB",
    "sg:tags":[
        "recycling",
        "can",
        "bottle",
        "welfare",
        "organization",
        "depot"
    ],
    "wof:name":"Triple H South Side Bottle",
    "wof:placetype":"venue"
},
  "geometry": {"coordinates":[-113.48641204800001,53.4792137146],"type":"Point"}
}