{
  "type": "Feature",
  "properties": {
    "addr:full":"Port Carling ON P0B 1J0",
    "addr:postcode":"p0b 1j0",
    "iso:country":"CA",
    "sg:city":"Port Carling",
    "sg:classifiers":[
        {
            "category":"Building & Trades",
            "subcategory":"Plumbing",
            "type":"Services"
        }
    ],
    "sg:phone":"+1 705 765 6172",
    "sg:postcode":"P0B 1J0",
    "sg:province":"ON",
    "sg:tags":[
        "air",
        "conditioning",
        "contractor",
        "system",
        "mechanical"
    ],
    "wof:name":"Envirotech Heating & Air Cond",
    "wof:placetype":"venue"
},
  "geometry": {"coordinates":[-79.6234283447,45.093711853],"type":"Point"}
}