{
  "type": "Feature",
  "properties": {
    "addr:full":"546 Montrose St N Cambridge ON N3H 2P6",
    "addr:housenumber":"546",
    "addr:postcode":"n3h 2p6",
    "addr:street":"Montrose St N",
    "iso:country":"CA",
    "sg:address":"546 Montrose St N",
    "sg:city":"Cambridge",
    "sg:classifiers":[
        {
            "category":"Organizations",
            "subcategory":"Religious Organization",
            "type":"Services"
        }
    ],
    "sg:phone":"+1 519 653 7710",
    "sg:postcode":"N3H 2P6",
    "sg:province":"ON",
    "sg:tags":[
        "church"
    ],
    "wof:name":"St Andrew's United Church",
    "wof:placetype":"venue"
},
  "geometry": {"coordinates":[-80.34208700000001,43.395428],"type":"Point"}
}