{
  "type": "Feature",
  "properties": {
    "iso:country":"CA",
    "sg:address":"21 Colborne St S",
    "sg:city":"Simcoe",
    "sg:classifiers":[
        {
            "category":"Shopping",
            "subcategory":"Discount & Variety Stores",
            "type":"Retail Goods"
        }
    ],
    "sg:phone":"+1 519 426 8562",
    "sg:postcode":"N3Y 4H2",
    "sg:province":"ON",
    "wof:name":"Max Convenience",
    "wof:placetype":"venue"
},
  "geometry": {"coordinates":[-80.30587768549999,42.8364448547],"type":"Point"}
}