{
  "type": "Feature",
  "properties": {
    "iso:country":"CA",
    "sg:address":"2745 Rue Du Merle",
    "sg:city":"Laval",
    "sg:classifiers":[
        {
            "category":"Building & Trades",
            "subcategory":"Cleaning & Sanitation",
            "type":"Services"
        }
    ],
    "sg:phone":"+1 450 625 5686",
    "sg:postcode":"H7L 3R5",
    "sg:province":"QC",
    "sg:tags":[
        "janitor"
    ],
    "wof:name":"Services D'Entretiens Real",
    "wof:placetype":"venue"
},
  "geometry": {"coordinates":[-73.7824935913,45.5933265686],"type":"Point"}
}