{
  "type": "Feature",
  "properties": {
    "addr:full":"PO Box 213 Heron Bay ON P0T 1R0",
    "addr:housenumber":"po",
    "addr:postcode":"p0t 1r0",
    "addr:street":"Box 213 Heron",
    "iso:country":"CA",
    "sg:address":"PO Box 213",
    "sg:city":"Heron Bay",
    "sg:classifiers":[
        {
            "category":"Organizations",
            "subcategory":"Professional Association",
            "type":"Services"
        }
    ],
    "sg:phone":"+1 807 229 8543",
    "sg:postcode":"P0T 1R0",
    "sg:province":"ON",
    "sg:tags":[
        "government"
    ],
    "wof:name":"Pic River Wii Jii Waa Guneseg",
    "wof:placetype":"venue"
},
  "geometry": {"coordinates":[-86.26811218260001,48.6255989075],"type":"Point"}
}