{
  "type": "Feature",
  "properties": {
    "addr:full":"295 Colborne St Chatham ON N7M 3M3",
    "addr:housenumber":"295",
    "addr:postcode":"n7m 3m3",
    "addr:street":"Colborne St",
    "iso:country":"CA",
    "sg:address":"295 Colborne St",
    "sg:city":"Chatham",
    "sg:classifiers":[
        {
            "category":"Retail",
            "subcategory":"Repair Shop",
            "type":"Services"
        }
    ],
    "sg:phone":"+1 519 351 5644",
    "sg:postcode":"N7M 3M3",
    "sg:province":"ON",
    "sg:tags":[
        "refinishing",
        "upholsterer"
    ],
    "wof:name":"Furniture Medic",
    "wof:placetype":"venue"
},
  "geometry": {"coordinates":[-82.1692733765,42.4098243713],"type":"Point"}
}