{
  "type": "Feature",
  "properties": {
    "iso:country":"CA",
    "sg:city":"Calgary",
    "sg:classifiers":[
        {
            "category":"Personal",
            "subcategory":"Beauty Salon",
            "type":"Services"
        }
    ],
    "sg:phone":"+1 403 520 0128",
    "sg:postcode":"T2E 2P8",
    "sg:province":"AB",
    "wof:name":"Studio 9",
    "wof:placetype":"venue"
},
  "geometry": {"coordinates":[-114.06275177000001,51.0608825684],"type":"Point"}
}