{
  "type": "Feature",
  "properties": {
    "addr:full":"220 Regina Rd Woodbridge ON L4L 8L6",
    "addr:housenumber":"220",
    "addr:postcode":"l4l 8l6",
    "addr:street":"Regina Rd",
    "iso:country":"CA",
    "sg:address":"220 Regina Rd",
    "sg:city":"Woodbridge",
    "sg:classifiers":[
        {
            "category":"Building & Trades",
            "subcategory":"Construction",
            "type":"Services"
        }
    ],
    "sg:phone":"+1 905 264 9500",
    "sg:postcode":"L4L 8L6",
    "sg:province":"ON",
    "sg:tags":[
        "concrete",
        "restoration",
        "repair",
        "cleaning",
        "contractor"
    ],
    "wof:name":"Across Canada Construction Ltd",
    "wof:placetype":"venue"
},
  "geometry": {"coordinates":[-79.61151099999999,43.768669],"type":"Point"}
}