{
  "type": "Feature",
  "properties": {
    "addr:full":"1018 Indian Rd N Sarnia ON N7V 4C5",
    "addr:housenumber":"1018",
    "addr:postcode":"n7v 4c5",
    "addr:street":"Indian Rd N",
    "iso:country":"CA",
    "sg:address":"1018 Indian Rd N",
    "sg:city":"Sarnia",
    "sg:classifiers":[
        {
            "category":"Education",
            "subcategory":"School",
            "type":"Public Place"
        }
    ],
    "sg:phone":"+1 519 542 4552",
    "sg:postcode":"N7V 4C5",
    "sg:province":"ON",
    "wof:name":"Rosedale School",
    "wof:placetype":"venue"
},
  "geometry": {"coordinates":[-82.3751296997,42.9929885864],"type":"Point"}
}