{
  "type": "Feature",
  "properties": {
    "addr:full":"19 Broadway Redvers SK S0C 2H0",
    "addr:housenumber":"19",
    "addr:postcode":"s0c 2h0",
    "addr:street":"Broadway",
    "iso:country":"CA",
    "sg:address":"19 Broadway",
    "sg:city":"Redvers",
    "sg:classifiers":[
        {
            "category":"Organizations",
            "subcategory":"Religious Organization",
            "type":"Services"
        }
    ],
    "sg:phone":"+1 306 452 3210",
    "sg:postcode":"S0C 2H0",
    "sg:province":"SK",
    "sg:tags":[
        "church"
    ],
    "wof:name":"United Church Office",
    "wof:placetype":"venue"
},
  "geometry": {"coordinates":[-101.699142456,49.5762710571],"type":"Point"}
}