{
  "type": "Feature",
  "properties": {
    "addr:full":"2560 Gerrard St E #201 Scarborough ON M1N 1W8",
    "addr:housenumber":"2560",
    "addr:postcode":"m1n 1w8",
    "addr:street":"Gerrard St E # 201",
    "iso:country":"CA",
    "sg:address":"2560 Gerrard St E #201",
    "sg:city":"Scarborough",
    "sg:classifiers":[
        {
            "category":"Health Services",
            "subcategory":"Doctor",
            "type":"Services"
        }
    ],
    "sg:phone":"+1 416 694 4944",
    "sg:postcode":"M1N 1W8",
    "sg:province":"ON",
    "sg:tags":[
        "physician",
        "surgeon"
    ],
    "wof:name":"Cramer, Paul MD",
    "wof:placetype":"venue"
},
  "geometry": {"coordinates":[-79.2783508301,43.688747406],"type":"Point"}
}