{
  "type": "Feature",
  "properties": {
    "addr:full":"2391 Coleman Rd Courtenay BC V9J 1T8",
    "addr:housenumber":"2391",
    "addr:postcode":"v9j 1t8",
    "addr:street":"Coleman Rd",
    "iso:country":"CA",
    "sg:address":"2391 Coleman Rd",
    "sg:city":"Courtenay",
    "sg:classifiers":[
        {
            "category":"Recreation",
            "type":"Entertainment"
        }
    ],
    "sg:phone":"+1 250 334 3115",
    "sg:postcode":"V9J 1T8",
    "sg:province":"BC",
    "sg:tags":[
        "riding",
        "academy",
        "stable"
    ],
    "wof:name":"North Star Stables",
    "wof:placetype":"venue"
},
  "geometry": {"coordinates":[-124.99314099999999,49.686722],"type":"Point"}
}