{
  "type": "Feature",
  "properties": {
    "addr:full":"2066 Retallack St Regina SK S4T 7X5",
    "addr:housenumber":"2066",
    "addr:postcode":"s4t 7x5",
    "addr:street":"Retallack St",
    "iso:country":"CA",
    "sg:address":"2066 Retallack St",
    "sg:city":"Regina",
    "sg:classifiers":[
        {
            "category":"Health Services",
            "subcategory":"Health Practitioner",
            "type":"Services"
        }
    ],
    "sg:phone":"+1 306 359 4200",
    "sg:postcode":"S4T 7X5",
    "sg:province":"SK",
    "sg:tags":[
        "nurse",
        "registry",
        "association"
    ],
    "wof:name":"Sask Registerd Nurses Assoc",
    "wof:placetype":"venue"
},
  "geometry": {"coordinates":[-104.622688,50.446106],"type":"Point"}
}