{
  "type": "Feature",
  "properties": {
    "addr:full":"6 George St S Brampton ON L6Y 1P1",
    "addr:housenumber":"6",
    "addr:postcode":"l6y 1p1",
    "addr:street":"George St S",
    "iso:country":"CA",
    "sg:address":"6 George St S",
    "sg:city":"Brampton",
    "sg:classifiers":[
        {
            "category":"Shopping",
            "subcategory":"Musical Instruments",
            "type":"Retail Goods"
        }
    ],
    "sg:phone":"+1 905 457 2218",
    "sg:postcode":"L6Y 1P1",
    "sg:province":"ON",
    "sg:tags":[
        "instruction",
        "music"
    ],
    "wof:name":"Ontario Conservatory of Music",
    "wof:placetype":"venue"
},
  "geometry": {"coordinates":[-79.76049,43.684967],"type":"Point"}
}