{
  "type": "Feature",
  "properties": {
    "iso:country":"CA",
    "sg:address":"110 Queen St E",
    "sg:city":"Brampton",
    "sg:classifiers":[
        {
            "category":"Personal",
            "type":"Services"
        }
    ],
    "sg:phone":"+1 905 455 5870",
    "sg:postcode":"L6V 1B1",
    "sg:province":"ON",
    "sg:tags":[
        "physiotherapist",
        "therapist",
        "massage"
    ],
    "wof:name":"Life Mark Health Clinic",
    "wof:placetype":"venue"
},
  "geometry": {"coordinates":[-79.7558288574,43.6898765564],"type":"Point"}
}