{
  "type": "Feature",
  "properties": {
    "addr:full":"418 14A Cres Invermere BC V0A 1K0",
    "addr:postcode":"v0a 1k0",
    "addr:street":"418 14A Cres",
    "iso:country":"CA",
    "sg:address":"418 14A Cres",
    "sg:city":"Invermere",
    "sg:classifiers":[
        {
            "category":"Building & Trades",
            "subcategory":"Equipment Rental",
            "type":"Services"
        }
    ],
    "sg:phone":"+1 250 342 2283",
    "sg:postcode":"V0A 1K0",
    "sg:province":"BC",
    "sg:tags":[
        "crane"
    ],
    "wof:name":"Rocky Mountain Cranes",
    "wof:placetype":"venue"
},
  "geometry": {"coordinates":[-116.02343,50.50214],"type":"Point"}
}