{
  "type": "Feature",
  "properties": {
    "addr:full":"Midland ON L4R 4P4",
    "addr:postcode":"l4r 4p4",
    "iso:country":"CA",
    "sg:city":"Midland",
    "sg:classifiers":[
        {
            "category":"Health Services",
            "subcategory":"Medical Lab",
            "type":"Services"
        }
    ],
    "sg:phone":"+1 705 526 0118",
    "sg:postcode":"L4R 4P4",
    "sg:province":"ON",
    "sg:tags":[
        "laboratory"
    ],
    "wof:name":"Dynacare Laboratories",
    "wof:placetype":"venue"
},
  "geometry": {"coordinates":[-79.911095,44.742802],"type":"Point"}
}