{
  "type": "Feature",
  "properties": {
    "addr:full":"Calgary AB T2A 5L5",
    "addr:postcode":"t2a 5l5",
    "iso:country":"CA",
    "sg:city":"Calgary",
    "sg:classifiers":[
        {
            "category":"Food & Beverages",
            "subcategory":"Liquor & Beverages",
            "type":"Retail Goods"
        }
    ],
    "sg:phone":"+1 403 272 8881",
    "sg:postcode":"T2A 5L5",
    "sg:province":"AB",
    "sg:tags":[
        "store"
    ],
    "wof:name":"Canada Liquor Store",
    "wof:placetype":"venue"
},
  "geometry": {"coordinates":[-113.95926666299999,51.0602035522],"type":"Point"}
}