{
  "type": "Feature",
  "properties": {
    "addr:full":"291 Brant Ave # 110 Brantford ON N3T 5Y4",
    "addr:housenumber":"291",
    "addr:postcode":"n3t 5y4",
    "addr:street":"Brant Ave # 110",
    "iso:country":"CA",
    "sg:address":"291 Brant Ave # 110",
    "sg:city":"Brantford",
    "sg:classifiers":[
        {
            "category":"Real Estate",
            "subcategory":"Real Estate Operator",
            "type":"Services"
        }
    ],
    "sg:phone":"+1 519 754 0064",
    "sg:postcode":"N3T 5Y4",
    "sg:province":"ON",
    "sg:tags":[
        "apartment"
    ],
    "wof:name":"Brant Manor Apartments",
    "wof:placetype":"venue"
},
  "geometry": {"coordinates":[-80.27838897709999,43.1496315002],"type":"Point"}
}