{
  "type": "Feature",
  "properties": {
    "addr:full":"5401 Boul Des Galeries # 216 Quebec QC G2K 1N4",
    "addr:housenumber":"5401",
    "addr:postcode":"g2k 1n4",
    "addr:street":"Boul Des Galeries # 216",
    "iso:country":"CA",
    "sg:address":"5401 Boul Des Galeries # 216",
    "sg:city":"Quebec",
    "sg:classifiers":[
        {
            "category":"Shopping",
            "subcategory":"Jewelry",
            "type":"Retail Goods"
        }
    ],
    "sg:phone":"+1 418 623 4449",
    "sg:postcode":"G2K 1N4",
    "sg:province":"QC",
    "sg:tags":[
        "jeweler"
    ],
    "wof:name":"Bijouterie Bernard Ltee",
    "wof:placetype":"venue"
},
  "geometry": {"coordinates":[-71.295677,46.831238],"type":"Point"}
}