{
  "type": "Feature",
  "properties": {
    "addr:full":"318 Porters Lake Station Rd Porters Lake NS B3E 1J9",
    "addr:housenumber":"318",
    "addr:postcode":"b3e 1j9",
    "addr:street":"Porters Lake Station Rd",
    "iso:country":"CA",
    "sg:address":"318 Porters Lake Station Rd",
    "sg:city":"Porters Lake",
    "sg:classifiers":[
        {
            "category":"Retail",
            "subcategory":"Repair Shop",
            "type":"Services"
        }
    ],
    "sg:phone":"+1 902 827 7828",
    "sg:postcode":"B3E 1J9",
    "sg:province":"NS",
    "sg:tags":[
        "welding"
    ],
    "wof:name":"Stat Manufacturing Ltd",
    "wof:placetype":"venue"
},
  "geometry": {"coordinates":[-63.288536,44.741604],"type":"Point"}
}