{
  "type": "Feature",
  "properties": {
    "iso:country":"CA",
    "sg:address":"247 Boul Fiset",
    "sg:city":"Sorel-Tracy",
    "sg:classifiers":[
        {
            "category":"Home & Garden",
            "subcategory":"Carpets & Floor Coverings",
            "type":"Retail Goods"
        }
    ],
    "sg:phone":"+1 450 743 7144",
    "sg:postcode":"J3P 3P9",
    "sg:province":"QC",
    "sg:tags":[
        "dealer",
        "rug"
    ],
    "wof:name":"Lucien Handfield Enr",
    "wof:placetype":"venue"
},
  "geometry": {"coordinates":[-73.0985412598,46.0398216248],"type":"Point"}
}