{
  "type": "Feature",
  "properties": {
    "addr:full":"207 Railway Ave Weyburn SK S4H 0A4",
    "addr:housenumber":"207",
    "addr:postcode":"s4h 0a4",
    "addr:street":"Railway Ave",
    "iso:country":"CA",
    "sg:address":"207 Railway Ave",
    "sg:city":"Weyburn",
    "sg:classifiers":[
        {
            "category":"Travel",
            "subcategory":"Hotels & Motels",
            "type":"Entertainment"
        }
    ],
    "sg:phone":"+1 306 842 2653",
    "sg:postcode":"S4H 0A4",
    "sg:province":"SK",
    "wof:name":"Royal Hotel",
    "wof:placetype":"venue"
},
  "geometry": {"coordinates":[-103.855377,49.660492],"type":"Point"}
}