{
  "type": "Feature",
  "properties": {
    "addr:full":"Vancouver BC V6Z 1N9",
    "addr:postcode":"v6z 1n9",
    "iso:country":"CA",
    "sg:city":"Vancouver",
    "sg:classifiers":[
        {
            "category":"Professional",
            "subcategory":"Lawyer & Legal Services",
            "type":"Services"
        }
    ],
    "sg:phone":"+1 604 618 7994",
    "sg:postcode":"V6Z 1N9",
    "sg:province":"BC",
    "sg:tags":[
        "attorney"
    ],
    "wof:name":"Doust, Thomas B",
    "wof:placetype":"venue"
},
  "geometry": {"coordinates":[-123.12284099999999,49.280403],"type":"Point"}
}