{
  "type": "Feature",
  "properties": {
    "iso:country":"CA",
    "sg:address":"226 Queen St E",
    "sg:city":"Brampton",
    "sg:classifiers":[
        {
            "category":"Restaurant",
            "type":"Food & Drink"
        }
    ],
    "sg:phone":"+1 905 459 8610",
    "sg:postcode":"L6V 1B8",
    "sg:province":"ON",
    "wof:name":"Singapore Garden Chinese",
    "wof:placetype":"venue"
},
  "geometry": {"coordinates":[-79.749054,43.696232],"type":"Point"}
}