{
  "type": "Feature",
  "properties": {
    "addr:full":"223 5 St N Vauxhall AB T0K 2K0",
    "addr:housenumber":"223 5",
    "addr:postcode":"t0k 2k0",
    "addr:street":"St N",
    "iso:country":"CA",
    "sg:address":"223 5 St N",
    "sg:city":"Vauxhall",
    "sg:classifiers":[
        {
            "category":"Government",
            "subcategory":"Office",
            "type":"Public Place"
        }
    ],
    "sg:phone":"+1 403 654 2174",
    "sg:postcode":"T0K 2K0",
    "sg:province":"AB",
    "sg:tags":[
        "village"
    ],
    "wof:name":"Vauxhall Town Office",
    "wof:placetype":"venue"
},
  "geometry": {"coordinates":[-112.10588836700001,50.0683441162],"type":"Point"}
}