{
  "type": "Feature",
  "properties": {
    "addr:full":"Surrey BC V3S 6J9",
    "addr:postcode":"v3s 6j9",
    "iso:country":"CA",
    "sg:city":"Surrey",
    "sg:classifiers":[
        {
            "category":"Manufacturing",
            "subcategory":"Glass & Minerals",
            "type":"Manufacturing & Wholesale Goods"
        }
    ],
    "sg:phone":"+1 604 533 4111",
    "sg:postcode":"V3S 6J9",
    "sg:province":"BC",
    "wof:name":"Trimlite Canada Ltd",
    "wof:placetype":"venue"
},
  "geometry": {"coordinates":[-122.687004089,49.1087837219],"type":"Point"}
}