{
  "type": "Feature",
  "properties": {
    "addr:full":"298 Main St Wellington ON K0K 3L0",
    "addr:housenumber":"298",
    "addr:postcode":"k0k 3l0",
    "addr:street":"Main St",
    "iso:country":"CA",
    "sg:address":"298 Main St",
    "sg:city":"Wellington",
    "sg:classifiers":[
        {
            "category":"Real Estate",
            "subcategory":"Real Estate Agent",
            "type":"Services"
        }
    ],
    "sg:phone":"+1 613 399 2100",
    "sg:postcode":"K0K 3L0",
    "sg:province":"ON",
    "wof:name":"Century 21 Lanthorn Real Est",
    "wof:placetype":"venue"
},
  "geometry": {"coordinates":[-77.3506317139,43.9518203735],"type":"Point"}
}