{
  "type": "Feature",
  "properties": {
    "addr:full":"1062 Mainland St Vancouver BC V6B 2T4",
    "addr:housenumber":"1062",
    "addr:postcode":"bc v6b 2t4",
    "addr:street":"Mainland St",
    "iso:country":"CA",
    "sg:address":"1062 Mainland St",
    "sg:city":"Vancouver",
    "sg:classifiers":[
        {
            "category":"Shopping",
            "subcategory":"Tobacco",
            "type":"Retail Goods"
        }
    ],
    "sg:phone":"+1 604 662 4427",
    "sg:postcode":"V6B 2T4",
    "sg:province":"BC",
    "sg:tags":[
        "cigarette",
        "cigar",
        "dealer"
    ],
    "wof:name":"Churchill's Fine Cigars",
    "wof:placetype":"venue"
},
  "geometry": {"coordinates":[-123.11972045900001,49.2759208679],"type":"Point"}
}