{
  "type": "Feature",
  "properties": {
    "iso:country":"CA",
    "sg:address":"205 York St",
    "sg:city":"London",
    "sg:classifiers":[
        {
            "category":"Government",
            "subcategory":"Office",
            "type":"Public Place"
        }
    ],
    "sg:phone":"+1 519 661 1790",
    "sg:postcode":"N6A 1B1",
    "sg:province":"ON",
    "wof:name":"Ontario Emergency Health Svc",
    "wof:placetype":"venue"
},
  "geometry": {"coordinates":[-81.24732208250001,42.9814758301],"type":"Point"}
}