{
  "type": "Feature",
  "properties": {
    "addr:full":"167 Lisgar St Toronto ON M6J 3G4",
    "addr:housenumber":"167",
    "addr:postcode":"m6j 3g4",
    "addr:street":"Lisgar St",
    "iso:country":"CA",
    "sg:address":"167 Lisgar St",
    "sg:city":"Toronto",
    "sg:classifiers":[
        {
            "category":"Building & Trades",
            "subcategory":"Construction",
            "type":"Services"
        }
    ],
    "sg:phone":"+1 416 534 7375",
    "sg:postcode":"M6J 3G4",
    "sg:province":"ON",
    "sg:tags":[
        "general",
        "contractor"
    ],
    "wof:name":"Parkside Construction Ltd",
    "wof:placetype":"venue"
},
  "geometry": {"coordinates":[-79.424232,43.645267],"type":"Point"}
}