{
  "type": "Feature",
  "properties": {
    "addr:full":"5333 50 Ave Vegreville AB T9C 1M9",
    "addr:housenumber":"5333",
    "addr:postcode":"t9c 1m9",
    "addr:street":"50 Ave",
    "iso:country":"CA",
    "sg:address":"5333 50 Ave",
    "sg:city":"Vegreville",
    "sg:classifiers":[
        {
            "category":"Autos & Motor Vehicles",
            "subcategory":"Fuel & Gas Station",
            "type":"Retail Goods"
        }
    ],
    "sg:phone":"+1 780 632 2818",
    "sg:postcode":"T9C 1M9",
    "sg:province":"AB",
    "sg:tags":[
        "oil"
    ],
    "wof:name":"Vegreville Shell",
    "wof:placetype":"venue"
},
  "geometry": {"coordinates":[-112.061661,53.498142],"type":"Point"}
}