{
  "type": "Feature",
  "properties": {
    "addr:full":"2153 51st Ave W Vancouver BC V6P 1E4",
    "addr:housenumber":"2153",
    "addr:postcode":"v6p 1e4",
    "addr:street":"51St Ave W",
    "iso:country":"CA",
    "sg:address":"2153 51st Ave W",
    "sg:city":"Vancouver",
    "sg:classifiers":[
        {
            "category":"Health Services",
            "subcategory":"Clinic",
            "type":"Services"
        }
    ],
    "sg:phone":"+1 604 261 3730",
    "sg:postcode":"V6P 1E4",
    "sg:province":"BC",
    "sg:tags":[
        "agency",
        "welfare"
    ],
    "wof:name":"Pacific Otolaryngology Fndtn",
    "wof:placetype":"venue"
},
  "geometry": {"coordinates":[-123.157021,49.225067],"type":"Point"}
}