{
  "type": "Feature",
  "properties": {
    "addr:full":"Quebec QC G1J 4Z6",
    "addr:postcode":"g1j 4z6",
    "iso:country":"CA",
    "sg:city":"Quebec",
    "sg:classifiers":[
        {
            "category":"Health Services",
            "subcategory":"Doctor",
            "type":"Services"
        }
    ],
    "sg:phone":"+1 418 663 1838",
    "sg:postcode":"G1J 4Z6",
    "sg:province":"QC",
    "sg:tags":[
        "dentist"
    ],
    "wof:name":"Ferland, Jean-Pierre DDS",
    "wof:placetype":"venue"
},
  "geometry": {"coordinates":[-71.219177,46.841576],"type":"Point"}
}