{
  "type": "Feature",
  "properties": {
    "addr:full":"1095 Britannia Rd E Mississauga ON L4W 3X1",
    "addr:housenumber":"1095",
    "addr:postcode":"l4w 3x1",
    "addr:street":"Britannia Rd E",
    "iso:country":"CA",
    "sg:address":"1095 Britannia Rd E",
    "sg:city":"Mississauga",
    "sg:classifiers":[
        {
            "category":"Home & Garden",
            "subcategory":"Building Materials",
            "type":"Retail Goods"
        }
    ],
    "sg:phone":"+1 905 696 8655",
    "sg:postcode":"L4W 3X1",
    "sg:province":"ON",
    "sg:tags":[
        "glass",
        "window",
        "plate"
    ],
    "wof:name":"Brittania Autoglass Ltd",
    "wof:placetype":"venue"
},
  "geometry": {"coordinates":[-79.6570281982,43.6470527649],"type":"Point"}
}