{
  "type": "Feature",
  "properties": {
    "addr:full":"Vancouver BC V6C 2Z4",
    "addr:postcode":"v6c 2z4",
    "iso:country":"CA",
    "sg:city":"Vancouver",
    "sg:classifiers":[
        {
            "category":"Organizations",
            "subcategory":"Professional Association",
            "type":"Services"
        }
    ],
    "sg:phone":"+1 604 684 4493",
    "sg:postcode":"V6C 2Z4",
    "sg:province":"BC",
    "wof:name":"Fishing Vessel Owners Assn",
    "wof:placetype":"venue"
},
  "geometry": {"coordinates":[-123.116485596,49.2849884033],"type":"Point"}
}