{
  "type": "Feature",
  "properties": {
    "addr:full":"9805 Hwy 12 W Warminster ON L0K 2G0",
    "addr:housenumber":"9805",
    "addr:postcode":"l0k 2g0",
    "addr:street":"Hwy 12 W",
    "iso:country":"CA",
    "sg:address":"9805 Hwy 12 W",
    "sg:city":"Warminster",
    "sg:classifiers":[
        {
            "category":"Building & Trades",
            "subcategory":"Construction",
            "type":"Services"
        }
    ],
    "sg:phone":"+1 705 326 4103",
    "sg:postcode":"L0K 2G0",
    "sg:province":"ON",
    "sg:tags":[
        "woodworker"
    ],
    "wof:name":"Warminster Woodworks",
    "wof:placetype":"venue"
},
  "geometry": {"coordinates":[-79.5450744629,44.6400756836],"type":"Point"}
}