{
  "type": "Feature",
  "properties": {
    "iso:country":"CA",
    "sg:address":"50 Great Northern Rd",
    "sg:city":"Sault Ste Marie",
    "sg:classifiers":[
        {
            "category":"Manufacturing",
            "subcategory":"Food",
            "type":"Manufacturing & Wholesale Goods"
        }
    ],
    "sg:phone":"+1 705 254 4524",
    "sg:postcode":"P6B 4Y5",
    "sg:province":"ON",
    "sg:tags":[
        "winery"
    ],
    "wof:name":"Wine Rack",
    "wof:placetype":"venue"
},
  "geometry": {"coordinates":[-84.319283,46.525158],"type":"Point"}
}