{
  "type": "Feature",
  "properties": {
    "addr:full":"100 Rodney St Saint John NB E2M 1X1",
    "addr:housenumber":"100",
    "addr:postcode":"e2m 1x1",
    "addr:street":"Rodney St",
    "iso:country":"CA",
    "sg:address":"100 Rodney St",
    "sg:city":"Saint John",
    "sg:classifiers":[
        {
            "category":"Manufacturing",
            "subcategory":"Signs",
            "type":"Manufacturing & Wholesale Goods"
        }
    ],
    "sg:phone":"+1 506 648 1893",
    "sg:postcode":"E2M 1X1",
    "sg:province":"NB",
    "wof:name":"Design Art Signs",
    "wof:placetype":"venue"
},
  "geometry": {"coordinates":[-66.071938,45.258911],"type":"Point"}
}