{
  "type": "Feature",
  "properties": {
    "addr:full":"1218 Canopy Lane Haliburton ON K0M 1S0",
    "addr:housenumber":"1218",
    "addr:postcode":"k0m 1s0",
    "addr:street":"Canopy Lane",
    "iso:country":"CA",
    "sg:address":"1218 Canopy Lane",
    "sg:city":"Haliburton",
    "sg:classifiers":[
        {
            "category":"Building & Trades",
            "subcategory":"Construction",
            "type":"Services"
        }
    ],
    "sg:phone":"+1 705 754 4342",
    "sg:postcode":"K0M 1S0",
    "sg:province":"ON",
    "sg:tags":[
        "home",
        "contractor",
        "improvement"
    ],
    "wof:name":"Sws Svc",
    "wof:placetype":"venue"
},
  "geometry": {"coordinates":[-78.726242,44.531826],"type":"Point"}
}