{
  "type": "Feature",
  "properties": {
    "iso:country":"CA",
    "sg:city":"Montreal",
    "sg:classifiers":[
        {
            "category":"Organizations",
            "subcategory":"Religious Organization",
            "type":"Services"
        }
    ],
    "sg:phone":"+1 514 935 8628",
    "sg:postcode":"H3K 1H6",
    "sg:province":"QC",
    "sg:tags":[
        "church"
    ],
    "wof:name":"Holy Trinity Polish Eglise",
    "wof:placetype":"venue"
},
  "geometry": {"coordinates":[-73.560066,45.483986],"type":"Point"}
}