{
  "type": "Feature",
  "properties": {
    "addr:full":"Montreal QC H3K 1H6",
    "addr:postcode":"h3k 1h6",
    "iso:country":"CA",
    "sg:city":"Montreal",
    "sg:classifiers":[
        {
            "category":"Organizations",
            "subcategory":"Religious Organization",
            "type":"Services"
        }
    ],
    "sg:phone":"+1 514 935 8628",
    "sg:postcode":"H3K 1H6",
    "sg:province":"QC",
    "sg:tags":[
        "church"
    ],
    "wof:name":"Holy Trinity Polish Eglise",
    "wof:placetype":"venue"
},
  "geometry": {"coordinates":[-73.56006600000001,45.483986],"type":"Point"}
}