{
  "type": "Feature",
  "properties": {
    "addr:full":"5916 87A St NW Edmonton AB T6E 5Z1",
    "addr:housenumber":"5916",
    "addr:postcode":"t6e 5z1",
    "addr:street":"87A St Nw",
    "iso:country":"CA",
    "sg:address":"5916 87A St NW",
    "sg:city":"Edmonton",
    "sg:classifiers":[
        {
            "category":"Restaurant",
            "type":"Food & Drink"
        }
    ],
    "sg:phone":"+1 780 463 0297",
    "sg:postcode":"T6E 5Z1",
    "sg:province":"AB",
    "sg:tags":[
        "grocer"
    ],
    "wof:name":"Troika Foods Ltd",
    "wof:placetype":"venue"
},
  "geometry": {"coordinates":[-113.461189,53.495045],"type":"Point"}
}