{
  "type": "Feature",
  "properties": {
    "addr:full":"1805 Rang Saint-Mathieu E Shawinigan-Sud QC G9N 6T5",
    "addr:housenumber":"1805",
    "addr:postcode":"g9n 6t5",
    "addr:street":"Rang Saint-Mathieu E Shawinigan-Sud",
    "iso:country":"CA",
    "sg:address":"1805 Rang Saint-Mathieu E",
    "sg:city":"Shawinigan-Sud",
    "sg:classifiers":[
        {
            "category":"Education",
            "subcategory":"School",
            "type":"Public Place"
        }
    ],
    "sg:phone":"+1 819 536 2544",
    "sg:postcode":"G9N 6T5",
    "sg:province":"QC",
    "wof:name":"Institution Secondaire Montfrt",
    "wof:placetype":"venue"
},
  "geometry": {"coordinates":[-72.722939,46.532898],"type":"Point"}
}