{
  "type": "Feature",
  "properties": {
    "addr:full":"Almonte ON K0A 1A0",
    "addr:postcode":"k0a 1a0",
    "iso:country":"CA",
    "sg:city":"Almonte",
    "sg:classifiers":[
        {
            "category":"Farming",
            "subcategory":"Farm",
            "type":"Manufacturing & Wholesale Goods"
        }
    ],
    "sg:phone":"+1 613 257 2771",
    "sg:postcode":"K0A 1A0",
    "sg:province":"ON",
    "wof:name":"Countryside Petting Farm",
    "wof:placetype":"venue"
},
  "geometry": {"coordinates":[-76.19420599999999,45.228741],"type":"Point"}
}