{
  "type": "Feature",
  "properties": {
    "addr:full":"135 Henry St Miramichi NB E1V 2N5",
    "addr:housenumber":"135",
    "addr:postcode":"e1v 2n5",
    "addr:street":"Henry St",
    "iso:country":"CA",
    "sg:address":"135 Henry St",
    "sg:city":"Miramichi",
    "sg:classifiers":[
        {
            "category":"Professional",
            "subcategory":"Accounting & Tax Preparation",
            "type":"Services"
        }
    ],
    "sg:phone":"+1 506 622 0637",
    "sg:postcode":"E1V 2N5",
    "sg:province":"NB",
    "sg:tags":[
        "accountant"
    ],
    "wof:name":"Grant Thornton",
    "wof:placetype":"venue"
},
  "geometry": {"coordinates":[-65.566788,47.001846],"type":"Point"}
}