{
  "type": "Feature",
  "properties": {
    "addr:full":"49 Jupiter Cres Hanwell NB E3C 1M7",
    "addr:housenumber":"49",
    "addr:postcode":"e3c 1m7",
    "addr:street":"Jupiter Cres",
    "iso:country":"CA",
    "sg:address":"49 Jupiter Cres",
    "sg:city":"Hanwell",
    "sg:classifiers":[
        {
            "category":"Building & Trades",
            "subcategory":"Construction",
            "type":"Services"
        }
    ],
    "sg:phone":"+1 506 450 7144",
    "sg:postcode":"E3C 1M7",
    "sg:province":"NB",
    "sg:tags":[
        "painter"
    ],
    "wof:name":"Maritime Decorators Ltd",
    "wof:placetype":"venue"
},
  "geometry": {"coordinates":[-66.795441,45.868484],"type":"Point"}
}