{
  "type": "Feature",
  "properties": {
    "iso:country":"CA",
    "sg:address":"2655 Rue King O",
    "sg:city":"Sherbrooke",
    "sg:classifiers":[
        {
            "category":"Insurance",
            "subcategory":"Insurance Agent",
            "type":"Services"
        }
    ],
    "sg:phone":"+1 819 565 9202",
    "sg:postcode":"J1L 2G4",
    "sg:province":"QC",
    "wof:name":"Belair CO D'Assurances",
    "wof:placetype":"venue"
},
  "geometry": {"coordinates":[-71.9379272461,45.3983955383],"type":"Point"}
}