{
  "type": "Feature",
  "properties": {
    "addr:full":"2245 Warren Ave Kimberley BC V1A 1S8",
    "addr:housenumber":"2245",
    "addr:postcode":"v1a 1s8",
    "addr:street":"Warren Ave",
    "iso:country":"CA",
    "sg:address":"2245 Warren Ave",
    "sg:city":"Kimberley",
    "sg:classifiers":[
        {
            "category":"Wholesale",
            "subcategory":"Farm Supplies",
            "type":"Manufacturing & Wholesale Goods"
        }
    ],
    "sg:phone":"+1 250 427 7762",
    "sg:postcode":"V1A 1S8",
    "sg:province":"BC",
    "sg:tags":[
        "nurseryman"
    ],
    "wof:name":"Top Crops Nurseryland Feed-Pet",
    "wof:placetype":"venue"
},
  "geometry": {"coordinates":[-115.9765625,49.6688804626],"type":"Point"}
}