{
  "type": "Feature",
  "properties": {
    "addr:full":"Montreal QC H3W 1H2",
    "addr:postcode":"h3w 1h2",
    "iso:country":"CA",
    "sg:city":"Montreal",
    "sg:classifiers":[
        {
            "category":"Banks & Credit Unions",
            "subcategory":"Bank",
            "type":"Services"
        }
    ],
    "sg:phone":"+1 514 731 8585",
    "sg:postcode":"H3W 1H2",
    "sg:province":"QC",
    "sg:tags":[
        "financing"
    ],
    "wof:name":"Ace Mortgage Corp",
    "wof:placetype":"venue"
},
  "geometry": {"coordinates":[-73.63810700000001,45.495102],"type":"Point"}
}