{
  "type": "Feature",
  "properties": {
    "addr:full":"Vancouver BC V5W 3A4",
    "addr:postcode":"v5w 3a4",
    "iso:country":"CA",
    "sg:city":"Vancouver",
    "sg:classifiers":[
        {
            "category":"Professional",
            "subcategory":"Accounting & Tax Preparation",
            "type":"Services"
        }
    ],
    "sg:phone":"+1 604 324 3937",
    "sg:postcode":"V5W 3A4",
    "sg:province":"BC",
    "sg:tags":[
        "consultant"
    ],
    "wof:name":"H M Tax Svc",
    "wof:placetype":"venue"
},
  "geometry": {"coordinates":[-123.090469,49.227146],"type":"Point"}
}