{
  "type": "Feature",
  "properties": {
    "addr:full":"47 Government Rd E Kirkland Lake ON P2N 1A4",
    "addr:housenumber":"47",
    "addr:postcode":"p2n 1a4",
    "addr:street":"Government Rd E",
    "iso:country":"CA",
    "sg:address":"47 Government Rd E",
    "sg:city":"Kirkland Lake",
    "sg:classifiers":[
        {
            "category":"Food & Beverages",
            "subcategory":"Groceries & Convenience Stores",
            "type":"Retail Goods"
        }
    ],
    "sg:phone":"+1 705 567 7207",
    "sg:postcode":"P2N 1A4",
    "sg:province":"ON",
    "sg:tags":[
        "grocer"
    ],
    "wof:name":"Grocery Depot",
    "wof:placetype":"venue"
},
  "geometry": {"coordinates":[-80.028778,48.153759],"type":"Point"}
}