{
  "type": "Feature",
  "properties": {
    "addr:full":"1041 Av Royale Beauport QC G1E 2A7",
    "addr:housenumber":"1041",
    "addr:postcode":"qc g1e 2a7",
    "addr:street":"Av Royale",
    "iso:country":"CA",
    "sg:address":"1041 Av Royale",
    "sg:city":"Beauport",
    "sg:classifiers":[
        {
            "category":"Food & Beverages",
            "subcategory":"Groceries & Convenience Stores",
            "type":"Retail Goods"
        }
    ],
    "sg:phone":"+1 418 663 9331",
    "sg:postcode":"G1E 2A7",
    "sg:province":"QC",
    "sg:tags":[
        "grocer"
    ],
    "wof:name":"Accommodation L Careau",
    "wof:placetype":"venue"
},
  "geometry": {"coordinates":[-71.1778717041,46.8704338074],"type":"Point"}
}