{
  "type": "Feature",
  "properties": {
    "addr:full":"2165 Broadway W Vancouver BC V6K 4N5",
    "addr:housenumber":"2165",
    "addr:postcode":"v6k 4n5",
    "addr:street":"Broadway W",
    "iso:country":"CA",
    "sg:address":"2165 Broadway W",
    "sg:city":"Vancouver",
    "sg:classifiers":[
        {
            "category":"Insurance",
            "subcategory":"Insurance Agent",
            "type":"Services"
        }
    ],
    "sg:phone":"+1 604 734 1667",
    "sg:postcode":"V6K 4N5",
    "sg:province":"BC",
    "wof:name":"Industrial Alliance Pacific",
    "wof:placetype":"venue"
},
  "geometry": {"coordinates":[-123.154343,49.264004],"type":"Point"}
}