{
  "type": "Feature",
  "properties": {
    "addr:full":"1A Sir Winston Churchill Sq NW Edmonton AB T5J 0R2",
    "addr:housenumber":"1a",
    "addr:postcode":"t5j 0r2",
    "addr:street":"Sir Winston Churchill Sq Nw",
    "iso:country":"CA",
    "sg:address":"1A Sir Winston Churchill Sq NW",
    "sg:city":"Edmonton",
    "sg:classifiers":[
        {
            "category":"Government",
            "subcategory":"Office",
            "type":"Public Place"
        }
    ],
    "sg:phone":"+1 780 496 8110",
    "sg:postcode":"T5J 0R2",
    "sg:province":"AB",
    "sg:tags":[
        "village"
    ],
    "wof:name":"Edmonton's Aldermen's Office",
    "wof:placetype":"venue"
},
  "geometry": {"coordinates":[-113.490723,53.544552],"type":"Point"}
}