{
  "type": "Feature",
  "properties": {
    "addr:full":"1068 Kelly Dr Kelowna BC V1Z 2T2",
    "addr:housenumber":"1068",
    "addr:postcode":"v1z 2t2",
    "addr:street":"Kelly Dr",
    "iso:country":"CA",
    "sg:address":"1068 Kelly Dr",
    "sg:city":"Kelowna",
    "sg:classifiers":[
        {
            "category":"Building & Trades",
            "subcategory":"Construction",
            "type":"Services"
        }
    ],
    "sg:phone":"+1 250 707 0707",
    "sg:postcode":"V1Z 2T2",
    "sg:province":"BC",
    "sg:tags":[
        "excavating",
        "contractor"
    ],
    "wof:name":"Gil Barry Contractors",
    "wof:placetype":"venue"
},
  "geometry": {"coordinates":[-119.560379,49.843357],"type":"Point"}
}