{
  "type": "Feature",
  "properties": {
    "addr:full":"34 Napier St E Thornbury ON N0H 2P0",
    "addr:housenumber":"34",
    "addr:postcode":"n0h 2p0",
    "addr:street":"Napier St",
    "iso:country":"CA",
    "sg:address":"34 Napier St E",
    "sg:city":"Thornbury",
    "sg:classifiers":[
        {
            "category":"Building & Trades",
            "subcategory":"Construction",
            "type":"Services"
        }
    ],
    "sg:phone":"+1 519 599 3114",
    "sg:postcode":"N0H 2P0",
    "sg:province":"ON",
    "sg:tags":[
        "home",
        "general",
        "improvement",
        "contractor"
    ],
    "wof:name":"Dave's Handyman Svc",
    "wof:placetype":"venue"
},
  "geometry": {"coordinates":[-80.45903800000001,44.554142],"type":"Point"}
}