{
  "type": "Feature",
  "properties": {
    "iso:country":"CA",
    "sg:address":"38 Dogwood",
    "sg:city":"Valemount",
    "sg:classifiers":[
        {
            "category":"Government",
            "subcategory":"Office",
            "type":"Public Place"
        }
    ],
    "sg:phone":"+1 250 566 4652",
    "sg:postcode":"V0E 2Z0",
    "sg:province":"BC",
    "wof:name":"BC Provincial Court",
    "wof:placetype":"venue"
},
  "geometry": {"coordinates":[-119.267044067,52.8352203369],"type":"Point"}
}