{
  "type": "Feature",
  "properties": {
    "iso:country":"CA",
    "sg:city":"Winnipeg",
    "sg:classifiers":[
        {
            "category":"Real Estate",
            "subcategory":"Real Estate Operator",
            "type":"Services"
        }
    ],
    "sg:phone":"+1 204 275 7741",
    "sg:postcode":"R3T 2G6",
    "sg:province":"MB",
    "sg:tags":[
        "apartment"
    ],
    "wof:name":"Pembina Place",
    "wof:placetype":"venue"
},
  "geometry": {"coordinates":[-97.15297698969999,49.8253631592],"type":"Point"}
}