{
  "type": "Feature",
  "properties": {
    "addr:full":"279 St Philips Dr Arborg MB R0C 0A0",
    "addr:housenumber":"279",
    "addr:postcode":"r0c 0a0",
    "addr:street":"St Philips Dr Arborg",
    "iso:country":"CA",
    "sg:address":"279 St Philips Dr",
    "sg:city":"Arborg",
    "sg:classifiers":[
        {
            "category":"Organizations",
            "subcategory":"Religious Organization",
            "type":"Services"
        }
    ],
    "sg:phone":"+1 204 376 2637",
    "sg:postcode":"R0C 0A0",
    "sg:province":"MB",
    "sg:tags":[
        "church"
    ],
    "wof:name":"Jehovah's Witnesses Hall",
    "wof:placetype":"venue"
},
  "geometry": {"coordinates":[-97.22410600000001,50.905025],"type":"Point"}
}