{
  "type": "Feature",
  "properties": {
    "iso:country":"CA",
    "sg:address":"2951 Ch D'Oka",
    "sg:city":"Sainte-Marthe-Sur-Le-Lac",
    "sg:classifiers":[
        {
            "category":"Health Services",
            "subcategory":"Chiropractor",
            "type":"Services"
        }
    ],
    "sg:phone":"+1 450 491 5885",
    "sg:postcode":"J0N 1P0",
    "sg:province":"QC",
    "wof:name":"Clinique Chiropratique Ste",
    "wof:placetype":"venue"
},
  "geometry": {"coordinates":[-73.99458312989999,45.5016860962],"type":"Point"}
}