{
  "type": "Feature",
  "properties": {
    "addr:full":"25 Main St Lucky Lake SK S0L 1Z0",
    "addr:housenumber":"25",
    "addr:postcode":"s0l 1z0",
    "addr:street":"Main St",
    "iso:country":"CA",
    "sg:address":"25 Main St",
    "sg:city":"Lucky Lake",
    "sg:classifiers":[
        {
            "category":"Insurance",
            "subcategory":"Insurance Agent",
            "type":"Services"
        }
    ],
    "sg:phone":"+1 306 858 2622",
    "sg:postcode":"S0L 1Z0",
    "sg:province":"SK",
    "wof:name":"Tom Agencies",
    "wof:placetype":"venue"
},
  "geometry": {"coordinates":[-107.135559,50.979946],"type":"Point"}
}