{
  "type": "Feature",
  "properties": {
    "addr:full":"6895 Rue Saint-Hubert Montreal QC H2S 2M7",
    "addr:housenumber":"6895",
    "addr:postcode":"h2s 2m7",
    "addr:street":"Rue Saint-Hubert",
    "iso:country":"CA",
    "sg:address":"6895 Rue Saint-Hubert",
    "sg:city":"Montreal",
    "sg:classifiers":[
        {
            "category":"Shopping",
            "subcategory":"Discount & Variety Stores",
            "type":"Retail Goods"
        }
    ],
    "sg:phone":"+1 514 279 3135",
    "sg:postcode":"H2S 2M7",
    "sg:province":"QC",
    "wof:name":"Un Seul Prix 1 Dollard",
    "wof:placetype":"venue"
},
  "geometry": {"coordinates":[-73.6089019775,45.5389442444],"type":"Point"}
}