{
  "type": "Feature",
  "properties": {
    "iso:country":"CA",
    "sg:address":"6600 Av Du Parc",
    "sg:city":"Montreal",
    "sg:classifiers":[
        {
            "category":"Wholesale",
            "subcategory":"Electrical",
            "type":"Manufacturing & Wholesale Goods"
        }
    ],
    "sg:phone":"+1 514 253 5844",
    "sg:postcode":"H2V 4H9",
    "sg:province":"QC",
    "sg:tags":[
        "equipment",
        "electric",
        "supply"
    ],
    "wof:name":"Centre DE Distr Elec Cde",
    "wof:placetype":"venue"
},
  "geometry": {"coordinates":[-73.6141052246,45.5273284912],"type":"Point"}
}