{
  "type": "Feature",
  "properties": {
    "addr:full":"35 Av Cartier Pointe-Claire QC H9S 4R5",
    "addr:postcode":"h9s 4r5",
    "addr:street":"35 Av Cartier",
    "iso:country":"CA",
    "sg:address":"35 Av Cartier",
    "sg:city":"Pointe-Claire",
    "sg:classifiers":[
        {
            "category":"Professional",
            "subcategory":"Management & Consulting",
            "type":"Services"
        }
    ],
    "sg:phone":"+1 514 695 3666",
    "sg:postcode":"H9S 4R5",
    "sg:province":"QC",
    "sg:tags":[
        "consultant",
        "educational"
    ],
    "wof:name":"Light A Dream",
    "wof:placetype":"venue"
},
  "geometry": {"coordinates":[-73.8235626221,45.4307098389],"type":"Point"}
}