{
  "type": "Feature",
  "properties": {
    "addr:full":"223 Mary St Hamilton ON L8L 4W2",
    "addr:housenumber":"223",
    "addr:postcode":"l8l 4w2",
    "addr:street":"Mary St",
    "iso:country":"CA",
    "sg:address":"223 Mary St",
    "sg:city":"Hamilton",
    "sg:classifiers":[
        {
            "category":"Manufacturing",
            "subcategory":"Toys & Sporting Goods",
            "type":"Manufacturing & Wholesale Goods"
        }
    ],
    "sg:phone":"+1 905 528 6864",
    "sg:postcode":"L8L 4W2",
    "sg:province":"ON",
    "sg:tags":[
        "equipment",
        "pool",
        "swimming"
    ],
    "wof:name":"Stolar Automatic Pool Reel",
    "wof:placetype":"venue"
},
  "geometry": {"coordinates":[-79.861465,43.261566],"type":"Point"}
}