{
  "type": "Feature",
  "properties": {
    "iso:country":"CA",
    "sg:address":"630 Stevenson Rd N",
    "sg:city":"Oshawa",
    "sg:classifiers":[
        {
            "category":"Education",
            "subcategory":"School",
            "type":"Public Place"
        }
    ],
    "sg:phone":"+1 905 728 0521",
    "sg:postcode":"L1J 5P1",
    "sg:province":"ON",
    "wof:name":"Adelaide Mc Laughlin School",
    "wof:placetype":"venue"
},
  "geometry": {"coordinates":[-78.890778,43.909416],"type":"Point"}
}