{
  "type": "Feature",
  "properties": {
    "addr:full":"1764 Queensway Prince George BC V2L 1L8",
    "addr:housenumber":"1764",
    "addr:postcode":"v2l 1l8",
    "addr:street":"Queensway",
    "iso:country":"CA",
    "sg:address":"1764 Queensway",
    "sg:city":"Prince George",
    "sg:classifiers":[
        {
            "category":"Retail",
            "subcategory":"Auto Repair",
            "type":"Services"
        }
    ],
    "sg:phone":"+1 250 563 4440",
    "sg:postcode":"V2L 1L8",
    "sg:province":"BC",
    "sg:tags":[
        "repairing",
        "automobile"
    ],
    "wof:name":"Fort George Alignment",
    "wof:placetype":"venue"
},
  "geometry": {"coordinates":[-122.741989,53.907738],"type":"Point"}
}