{
  "type": "Feature",
  "properties": {
    "addr:full":"Rocky Mountain House AB T4T 1B5",
    "addr:postcode":"t4t 1b5",
    "iso:country":"CA",
    "sg:city":"Rocky Mountain House",
    "sg:classifiers":[
        {
            "category":"Mining & Drilling",
            "type":"Manufacturing & Wholesale Goods"
        }
    ],
    "sg:phone":"+1 403 844 2736",
    "sg:postcode":"T4T 1B5",
    "sg:province":"AB",
    "sg:tags":[
        "field",
        "oil"
    ],
    "wof:name":"Chevallier Geo-Con Ltd",
    "wof:placetype":"venue"
},
  "geometry": {"coordinates":[-114.904938,52.365711],"type":"Point"}
}