{
  "type": "Feature",
  "properties": {
    "addr:full":"24 Maple Ave Sydney NS B1S 1J6",
    "addr:housenumber":"24",
    "addr:postcode":"b1s 1j6",
    "addr:street":"Maple Ave",
    "iso:country":"CA",
    "sg:address":"24 Maple Ave",
    "sg:city":"Sydney",
    "sg:classifiers":[
        {
            "category":"Building & Trades",
            "subcategory":"Landscaping Services",
            "type":"Services"
        }
    ],
    "sg:phone":"+1 902 564 9910",
    "sg:postcode":"B1S 1J6",
    "sg:province":"NS",
    "sg:tags":[
        "landscape",
        "contractor"
    ],
    "wof:name":"Sydney Landscaping & Nurseries",
    "wof:placetype":"venue"
},
  "geometry": {"coordinates":[-60.226543,46.096771],"type":"Point"}
}