{
  "type": "Feature",
  "properties": {
    "addr:full":"151 Chapel Hill Cres Welland ON L3C 6G8",
    "addr:housenumber":"151",
    "addr:postcode":"l3c 6g8",
    "addr:street":"Chapel Hill Cres",
    "iso:country":"CA",
    "sg:address":"151 Chapel Hill Cres",
    "sg:city":"Welland",
    "sg:classifiers":[
        {
            "category":"Shopping",
            "type":"Retail Goods"
        }
    ],
    "sg:phone":"+1 905 734 7555",
    "sg:postcode":"L3C 6G8",
    "sg:province":"ON",
    "sg:tags":[
        "wood",
        "carving"
    ],
    "wof:name":"Casement Woodcarving & Supplie",
    "wof:placetype":"venue"
},
  "geometry": {"coordinates":[-79.276008606,43.0074501038],"type":"Point"}
}