{
  "type": "Feature",
  "properties": {
    "addr:full":"Quebec QC G1K 8W1",
    "addr:postcode":"g1k 8w1",
    "iso:country":"CA",
    "sg:city":"Quebec",
    "sg:classifiers":[
        {
            "category":"Health Services",
            "subcategory":"Optometrist",
            "type":"Services"
        }
    ],
    "sg:phone":"+1 418 529 9721",
    "sg:postcode":"G1K 8W1",
    "sg:province":"QC",
    "wof:name":"Deschenes, Pascal OD",
    "wof:placetype":"venue"
},
  "geometry": {"coordinates":[-71.2157211304,46.8179855347],"type":"Point"}
}