{
  "type": "Feature",
  "properties": {
    "iso:country":"CA",
    "sg:address":"2385 Guildford Town Ctr",
    "sg:city":"Surrey",
    "sg:classifiers":[
        {
            "category":"Utilities",
            "subcategory":"Mobile Phone",
            "type":"Services"
        }
    ],
    "sg:phone":"+1 604 584 0335",
    "sg:postcode":"V3R 7B9",
    "sg:province":"BC",
    "sg:tags":[
        "telephone",
        "cellular"
    ],
    "wof:name":"Glentel Wireless Wave",
    "wof:placetype":"venue"
},
  "geometry": {"coordinates":[-122.804023743,49.1879768372],"type":"Point"}
}