{
  "type": "Feature",
  "properties": {
    "addr:full":"Stettler AB T0C 2L2",
    "addr:postcode":"t0c 2l2",
    "iso:country":"CA",
    "sg:city":"Stettler",
    "sg:classifiers":[
        {
            "category":"Personal",
            "subcategory":"Beauty Salon",
            "type":"Services"
        }
    ],
    "sg:phone":"+1 403 742 0007",
    "sg:postcode":"T0C 2L2",
    "sg:province":"AB",
    "wof:name":"Cuttin' Corners",
    "wof:placetype":"venue"
},
  "geometry": {"coordinates":[-112.705299,52.32325],"type":"Point"}
}