{
  "type": "Feature",
  "properties": {
    "addr:full":"Victoria Harbour ON L0K 2A0",
    "addr:postcode":"l0k 2a0",
    "iso:country":"CA",
    "sg:city":"Victoria Harbour",
    "sg:classifiers":[
        {
            "category":"Building & Trades",
            "subcategory":"Landscaping Services",
            "type":"Services"
        }
    ],
    "sg:phone":"+1 705 529 6733",
    "sg:postcode":"L0K 2A0",
    "sg:province":"ON",
    "sg:tags":[
        "lawn",
        "maintenance",
        "grounds"
    ],
    "wof:name":"Bay Winds Property Maintenance",
    "wof:placetype":"venue"
},
  "geometry": {"coordinates":[-79.7744445801,44.7506942749],"type":"Point"}
}