{
  "type": "Feature",
  "properties": {
    "addr:full":"35 University Ave Charlottetown PE C1A 4K7",
    "addr:housenumber":"35",
    "addr:postcode":"c1a 4k7",
    "addr:street":"University Ave",
    "iso:country":"CA",
    "sg:address":"35 University Ave",
    "sg:city":"Charlottetown",
    "sg:classifiers":[
        {
            "category":"Personal",
            "subcategory":"Beauty Salon",
            "type":"Services"
        }
    ],
    "sg:phone":"+1 902 566 4686",
    "sg:postcode":"C1A 4K7",
    "sg:province":"PE",
    "wof:name":"Cleopatra Hair Design",
    "wof:placetype":"venue"
},
  "geometry": {"coordinates":[-63.127304,46.235729],"type":"Point"}
}