{
  "type": "Feature",
  "properties": {
    "iso:country":"CA",
    "sg:address":"1 Industrial Dr",
    "sg:city":"Campbellford",
    "sg:classifiers":[
        {
            "category":"Autos & Motor Vehicles",
            "subcategory":"Automobile Sales",
            "type":"Retail Goods"
        }
    ],
    "sg:phone":"+1 705 653 0066",
    "sg:postcode":"K0L 1L0",
    "sg:province":"ON",
    "sg:tags":[
        "car",
        "dealer"
    ],
    "wof:name":"Regional Auto Wholesalers Inc",
    "wof:placetype":"venue"
},
  "geometry": {"coordinates":[-77.80819702150001,44.2893714905],"type":"Point"}
}