{
  "type": "Feature",
  "properties": {
    "addr:full":"1 Transfer Pl Scarborough ON M1S 5H8",
    "addr:housenumber":"1",
    "addr:postcode":"m1s 5h8",
    "addr:street":"Transfer Pl",
    "iso:country":"CA",
    "sg:address":"1 Transfer Pl",
    "sg:city":"Scarborough",
    "sg:classifiers":[
        {
            "category":"Government",
            "subcategory":"Office",
            "type":"Public Place"
        }
    ],
    "sg:phone":"+1 416 397 1331",
    "sg:postcode":"M1S 5H8",
    "sg:province":"ON",
    "sg:tags":[
        "village"
    ],
    "wof:name":"Toronto Waste Transfer Station",
    "wof:placetype":"venue"
},
  "geometry": {"coordinates":[-79.24430847169999,43.7979431152],"type":"Point"}
}