{
  "type": "Feature",
  "properties": {
    "iso:country":"CA",
    "sg:city":"Neepawa",
    "sg:classifiers":[
        {
            "category":"Health Services",
            "subcategory":"Medical Lab",
            "type":"Services"
        }
    ],
    "sg:phone":"+1 204 476 3298",
    "sg:postcode":"R0J 1H0",
    "sg:province":"MB",
    "wof:name":"Swan Denture Clinic",
    "wof:placetype":"venue"
},
  "geometry": {"coordinates":[-99.4651184082,50.2277336121],"type":"Point"}
}