{
  "type": "Feature",
  "properties": {
    "addr:full":"SW 25 22 28 W Inglis MB R0J 0X0",
    "addr:housenumber":"22 28",
    "addr:postcode":"r0j 0x0",
    "addr:street":"Sw 25;W",
    "iso:country":"CA",
    "sg:address":"SW 25 22 28 W",
    "sg:city":"Inglis",
    "sg:classifiers":[
        {
            "category":"Farming",
            "subcategory":"Livestock Farm",
            "type":"Manufacturing & Wholesale Goods"
        }
    ],
    "sg:phone":"+1 204 564 2363",
    "sg:postcode":"R0J 0X0",
    "sg:province":"MB",
    "sg:tags":[
        "feeding"
    ],
    "wof:name":"Willow Hill Farms",
    "wof:placetype":"venue"
},
  "geometry": {"coordinates":[-101.25147247300001,50.9483566284],"type":"Point"}
}