{
  "type": "Feature",
  "properties": {
    "iso:country":"CA",
    "sg:address":"3490 Pinehurst Trunk 10",
    "sg:city":"New Germany",
    "sg:classifiers":[
        {
            "category":"Personal",
            "subcategory":"Beauty Salon",
            "type":"Services"
        }
    ],
    "sg:phone":"+1 902 543 8029",
    "sg:postcode":"B0R 1E0",
    "sg:province":"NS",
    "wof:name":"Betty Ann's Hair Fashions",
    "wof:placetype":"venue"
},
  "geometry": {"coordinates":[-64.716461,44.541767],"type":"Point"}
}