{
  "type": "Feature",
  "properties": {
    "addr:full":"47 Craighall Cir Ottawa ON K1T 4B5",
    "addr:housenumber":"47",
    "addr:postcode":"k1t 4b5",
    "addr:street":"Craighall Cir",
    "iso:country":"CA",
    "sg:address":"47 Craighall Cir",
    "sg:city":"Ottawa",
    "sg:classifiers":[
        {
            "category":"Building & Trades",
            "subcategory":"Construction",
            "type":"Services"
        }
    ],
    "sg:phone":"+1 613 731 2929",
    "sg:postcode":"K1T 4B5",
    "sg:province":"ON",
    "sg:tags":[
        "resurfacing",
        "laying",
        "refinishing",
        "floor"
    ],
    "wof:name":"European Hardwood Flooring",
    "wof:placetype":"venue"
},
  "geometry": {"coordinates":[-75.62865447999999,45.3674125671],"type":"Point"}
}