{
  "type": "Feature",
  "properties": {
    "addr:full":"600 Prospect St W Fredericton NB E3B 6G9",
    "addr:housenumber":"600",
    "addr:postcode":"e3b 6g9",
    "addr:street":"Prospect St W",
    "iso:country":"CA",
    "sg:address":"600 Prospect St W",
    "sg:city":"Fredericton",
    "sg:classifiers":[
        {
            "category":"Manufacturing",
            "subcategory":"Rubber & Plastics",
            "type":"Manufacturing & Wholesale Goods"
        }
    ],
    "sg:phone":"+1 506 458 9107",
    "sg:postcode":"E3B 6G9",
    "sg:province":"NB",
    "sg:tags":[
        "windows",
        "product"
    ],
    "wof:name":"Admiral Glass & Mirror",
    "wof:placetype":"venue"
},
  "geometry": {"coordinates":[-66.6840667725,45.9485092163],"type":"Point"}
}