{
  "type": "Feature",
  "properties": {
    "iso:country":"CA",
    "sg:address":"606 Victoria St",
    "sg:city":"Nelson",
    "sg:classifiers":[
        {
            "category":"Education",
            "subcategory":"Special Training",
            "type":"Public Place"
        }
    ],
    "sg:phone":"+1 250 352 2821",
    "sg:postcode":"V1L 4K9",
    "sg:province":"BC",
    "sg:tags":[
        "school",
        "instruction",
        "art"
    ],
    "wof:name":"Kootenay School of the Arts",
    "wof:placetype":"venue"
},
  "geometry": {"coordinates":[-117.291633606,49.4917106628],"type":"Point"}
}