{
  "type": "Feature",
  "properties": {
    "addr:full":"3410 Rue Principale Tracadie-Sheila NB E1X 1C8",
    "addr:housenumber":"3410",
    "addr:postcode":"e1x 1c8",
    "addr:street":"Rue Principale",
    "iso:country":"CA",
    "sg:address":"3410 Rue Principale",
    "sg:city":"Tracadie-Sheila",
    "sg:classifiers":[
        {
            "category":"Restaurant",
            "type":"Food & Drink"
        }
    ],
    "sg:phone":"+1 506 395 6555",
    "sg:postcode":"E1X 1C8",
    "sg:province":"NB",
    "sg:tags":[
        "pizza"
    ],
    "wof:name":"Pizza Delight",
    "wof:placetype":"venue"
},
  "geometry": {"coordinates":[-64.9176864624,47.4913406372],"type":"Point"}
}