{
  "type": "Feature",
  "properties": {
    "addr:full":"Gatineau QC J8T 8A4",
    "addr:postcode":"j8t 8a4",
    "iso:country":"CA",
    "sg:city":"Gatineau",
    "sg:classifiers":[
        {
            "category":"Shopping",
            "subcategory":"Clothing, Apparel, & Fashions",
            "type":"Retail Goods"
        }
    ],
    "sg:phone":"+1 819 243 4739",
    "sg:postcode":"J8T 8A4",
    "sg:province":"QC",
    "sg:tags":[
        "furnishing"
    ],
    "wof:name":"Moores Vetements Pour Hommes",
    "wof:placetype":"venue"
},
  "geometry": {"coordinates":[-75.7104873657,45.4278526306],"type":"Point"}
}