{
  "type": "Feature",
  "properties": {
    "addr:full":"39317 Fingal Line St Thomas ON N5P 3S5",
    "addr:housenumber":"39317",
    "addr:postcode":"n5p 3s5",
    "addr:street":"Fingal Line",
    "iso:country":"CA",
    "sg:address":"39317 Fingal Line",
    "sg:city":"St Thomas",
    "sg:classifiers":[
        {
            "category":"Manufacturing",
            "subcategory":"Metals",
            "type":"Manufacturing & Wholesale Goods"
        }
    ],
    "sg:phone":"+1 519 633 9452",
    "sg:postcode":"N5P 3S5",
    "sg:province":"ON",
    "sg:tags":[
        "windows"
    ],
    "wof:name":"Talbotville Windows",
    "wof:placetype":"venue"
},
  "geometry": {"coordinates":[-81.223518,42.773891],"type":"Point"}
}