{
  "type": "Feature",
  "properties": {
    "iso:country":"CA",
    "sg:address":"39317 Fingal Line",
    "sg:city":"St Thomas",
    "sg:classifiers":[
        {
            "category":"Manufacturing",
            "subcategory":"Metals",
            "type":"Manufacturing & Wholesale Goods"
        }
    ],
    "sg:phone":"+1 519 633 9452",
    "sg:postcode":"N5P 3S5",
    "sg:province":"ON",
    "sg:tags":[
        "windows"
    ],
    "wof:name":"Talbotville Windows",
    "wof:placetype":"venue"
},
  "geometry": {"coordinates":[-81.223518,42.773891],"type":"Point"}
}