{
  "type": "Feature",
  "properties": {
    "addr:full":"38 Wellington St W Bloomfield ON K0K 1G0",
    "addr:housenumber":"38",
    "addr:postcode":"k0k 1g0",
    "addr:street":"Wellington St W",
    "iso:country":"CA",
    "sg:address":"38 Wellington St W",
    "sg:city":"Bloomfield",
    "sg:classifiers":[
        {
            "category":"Food & Beverages",
            "subcategory":"Bakery",
            "type":"Retail Goods"
        }
    ],
    "sg:phone":"+1 613 393 5465",
    "sg:postcode":"K0K 1G0",
    "sg:province":"ON",
    "sg:tags":[
        "baker"
    ],
    "wof:name":"Patisserie Vienne",
    "wof:placetype":"venue"
},
  "geometry": {"coordinates":[-77.24380499999999,43.984699],"type":"Point"}
}