{
  "type": "Feature",
  "properties": {
    "iso:country":"CA",
    "sg:city":"Flowers Cove",
    "sg:classifiers":[
        {
            "category":"Government",
            "subcategory":"Office",
            "type":"Public Place"
        }
    ],
    "sg:phone":"+1 709 456 2431",
    "sg:postcode":"A0K 2N0",
    "sg:province":"NL",
    "wof:name":"Newfoundland Social Svc",
    "wof:placetype":"venue"
},
  "geometry": {"coordinates":[-56.7297592163,51.2975349426],"type":"Point"}
}