{
  "type": "Feature",
  "properties": {
    "addr:full":"345 Midwest Rd Scarborough ON M1P 3A6",
    "addr:housenumber":"345",
    "addr:postcode":"m1p 3a6",
    "addr:street":"Midwest Rd",
    "iso:country":"CA",
    "sg:address":"345 Midwest Rd",
    "sg:city":"Scarborough",
    "sg:classifiers":[
        {
            "category":"Building & Trades",
            "subcategory":"Plumbing",
            "type":"Services"
        }
    ],
    "sg:phone":"+1 416 285 4286",
    "sg:postcode":"M1P 3A6",
    "sg:province":"ON",
    "sg:tags":[
        "sheet",
        "work",
        "metal",
        "contractor"
    ],
    "wof:name":"Falcon Precision Ltd",
    "wof:placetype":"venue"
},
  "geometry": {"coordinates":[-79.27092,43.760532],"type":"Point"}
}