{
  "type": "Feature",
  "properties": {
    "addr:full":"Vancouver BC V6E 4H1",
    "addr:postcode":"v6e 4h1",
    "iso:country":"CA",
    "sg:city":"Vancouver",
    "sg:classifiers":[
        {
            "category":"Real Estate",
            "subcategory":"Real Estate Agent",
            "type":"Services"
        }
    ],
    "sg:phone":"+1 604 683 1141",
    "sg:postcode":"V6E 4H1",
    "sg:province":"BC",
    "wof:name":"Grosvenor Canada Ltd",
    "wof:placetype":"venue"
},
  "geometry": {"coordinates":[-123.122032166,49.2848739624],"type":"Point"}
}