{
  "type": "Feature",
  "properties": {
    "iso:country":"CA",
    "sg:address":"4410 Rue Garand",
    "sg:city":"Saint-Laurent",
    "sg:classifiers":[
        {
            "category":"Professional",
            "subcategory":"Art Services",
            "type":"Services"
        }
    ],
    "sg:phone":"+1 514 335 1010",
    "sg:postcode":"H4R 2A3",
    "sg:province":"QC",
    "sg:tags":[
        "photographer"
    ],
    "wof:name":"Studio Pettas Ltd",
    "wof:placetype":"venue"
},
  "geometry": {"coordinates":[-73.71853637700001,45.4909744263],"type":"Point"}
}