{
  "type": "Feature",
  "properties": {
    "addr:full":"30 Albert St Langton ON N0E 1G0",
    "addr:housenumber":"30",
    "addr:postcode":"n0e 1g0",
    "addr:street":"Albert St",
    "iso:country":"CA",
    "sg:address":"30 Albert St",
    "sg:city":"Langton",
    "sg:classifiers":[
        {
            "category":"Recreation",
            "type":"Entertainment"
        }
    ],
    "sg:phone":"+1 519 875 2761",
    "sg:postcode":"N0E 1G0",
    "sg:province":"ON",
    "sg:tags":[
        "center"
    ],
    "wof:name":"Langton & Area Minor Hockey",
    "wof:placetype":"venue"
},
  "geometry": {"coordinates":[-80.577011,42.742153],"type":"Point"}
}