{
  "type": "Feature",
  "properties": {
    "addr:full":"2750 River St W Moose Jaw SK S6H 4N9",
    "addr:housenumber":"2750",
    "addr:postcode":"s6h 4n9",
    "addr:street":"River St W",
    "iso:country":"CA",
    "sg:address":"2750 River St W",
    "sg:city":"Moose Jaw",
    "sg:classifiers":[
        {
            "category":"Wholesale",
            "subcategory":"Farm Supplies",
            "type":"Manufacturing & Wholesale Goods"
        }
    ],
    "sg:phone":"+1 306 694 5314",
    "sg:postcode":"S6H 4N9",
    "sg:province":"SK",
    "sg:tags":[
        "feeding",
        "livestock"
    ],
    "wof:name":"M & T Feed Lot Ltd",
    "wof:placetype":"venue"
},
  "geometry": {"coordinates":[-105.547050476,50.3906707764],"type":"Point"}
}