{
  "type": "Feature",
  "properties": {
    "addr:full":"56 Lorne Ave Dartmouth NS B2Y 3E7",
    "addr:housenumber":"56",
    "addr:postcode":"b2y 3e7",
    "addr:street":"Lorne Ave",
    "iso:country":"CA",
    "sg:address":"56 Lorne Ave",
    "sg:city":"Dartmouth",
    "sg:classifiers":[
        {
            "category":"Organizations",
            "subcategory":"Non-profit Organization",
            "type":"Services"
        }
    ],
    "sg:phone":"+1 902 466 8424",
    "sg:postcode":"B2Y 3E7",
    "sg:province":"NS",
    "sg:tags":[
        "charitable",
        "institution"
    ],
    "wof:name":"Nova Scotia Debating Society",
    "wof:placetype":"venue"
},
  "geometry": {"coordinates":[-63.551612854,44.6741600037],"type":"Point"}
}