{
  "type": "Feature",
  "properties": {
    "addr:full":"28 Gladiola Dr Carlisle ON L0R 1H1",
    "addr:housenumber":"28",
    "addr:postcode":"l0r 1h1",
    "addr:street":"Gladiola Dr",
    "iso:country":"CA",
    "sg:address":"28 Gladiola Dr",
    "sg:city":"Carlisle",
    "sg:classifiers":[
        {
            "category":"Wholesale",
            "subcategory":"Computers",
            "type":"Manufacturing & Wholesale Goods"
        }
    ],
    "sg:phone":"+1 905 689 2701",
    "sg:postcode":"L0R 1H1",
    "sg:province":"ON",
    "wof:name":"Re Soft Technology Brokers Inc",
    "wof:placetype":"venue"
},
  "geometry": {"coordinates":[-79.9733200073,43.3904876709],"type":"Point"}
}