{
  "type": "Feature",
  "properties": {
    "addr:full":"85 Nearys Pond Rd Portugal Cove-St Philips NL A1M 2Z8",
    "addr:housenumber":"85",
    "addr:postcode":"a1m 2z8",
    "addr:street":"Nearys Pond Rd",
    "iso:country":"CA",
    "sg:address":"85 Nearys Pond Rd",
    "sg:city":"Portugal Cove-St Philips",
    "sg:classifiers":[
        {
            "category":"Building & Trades",
            "subcategory":"Plumbing",
            "type":"Services"
        }
    ],
    "sg:phone":"+1 709 895 3795",
    "sg:postcode":"A1M 2Z8",
    "sg:province":"NL",
    "sg:tags":[
        "conditioning",
        "air",
        "system",
        "contractor"
    ],
    "wof:name":"Custom Sheet Metal Ltd",
    "wof:placetype":"venue"
},
  "geometry": {"coordinates":[-52.847229,47.613361],"type":"Point"}
}