{
  "type": "Feature",
  "properties": {
    "addr:full":"748 Arnold Rd Abbotsford BC V3G 1S4",
    "addr:housenumber":"748",
    "addr:postcode":"v3g 1s4",
    "addr:street":"Arnold Rd",
    "iso:country":"CA",
    "sg:address":"748 Arnold Rd",
    "sg:city":"Abbotsford",
    "sg:classifiers":[
        {
            "category":"Manufacturing",
            "subcategory":"Furniture",
            "type":"Manufacturing & Wholesale Goods"
        }
    ],
    "sg:phone":"+1 604 852 6467",
    "sg:postcode":"V3G 1S4",
    "sg:province":"BC",
    "sg:tags":[
        "woodworker"
    ],
    "wof:name":"R & R Woodcraft",
    "wof:placetype":"venue"
},
  "geometry": {"coordinates":[-122.15033699999999,49.015392],"type":"Point"}
}