{
  "type": "Feature",
  "properties": {
    "addr:full":"6000 Boul Metropolitain E Saint-Leonard QC H1S 1B1",
    "addr:housenumber":"6000",
    "addr:postcode":"h1s 1b1",
    "addr:street":"Boul Metropolitain E",
    "iso:country":"CA",
    "sg:address":"6000 Boul Metropolitain E",
    "sg:city":"Saint-Leonard",
    "sg:classifiers":[
        {
            "category":"Professional",
            "subcategory":"Credit Reporting & Collection",
            "type":"Services"
        }
    ],
    "sg:phone":"+1 514 259 7222",
    "sg:postcode":"H1S 1B1",
    "sg:province":"QC",
    "sg:tags":[
        "agency"
    ],
    "wof:name":"Agence DE Recouvrement Global",
    "wof:placetype":"venue"
},
  "geometry": {"coordinates":[-73.58260300000001,45.588764],"type":"Point"}
}