{
  "type": "Feature",
  "properties": {
    "addr:full":"47 Rue Aristide Canton-DE-Granby QC J2G 9R4",
    "addr:housenumber":"47",
    "addr:postcode":"j2g 9r4",
    "addr:street":"Rue Aristide Canton-De-Granby",
    "iso:country":"CA",
    "sg:address":"47 Rue Aristide",
    "sg:city":"Canton-DE-Granby",
    "sg:classifiers":[
        {
            "category":"Building & Trades",
            "subcategory":"Construction",
            "type":"Services"
        }
    ],
    "sg:phone":"+1 450 375 5054",
    "sg:postcode":"J2G 9R4",
    "sg:province":"QC",
    "sg:tags":[
        "railing",
        "maker",
        "cabinet"
    ],
    "wof:name":"Ebenisterie Des Cantons Enr",
    "wof:placetype":"venue"
},
  "geometry": {"coordinates":[-72.7217712402,45.3979949951],"type":"Point"}
}