{
  "type": "Feature",
  "properties": {
    "addr:full":"131 Lock St E Dunnville ON N1A 1J6",
    "addr:housenumber":"131",
    "addr:postcode":"n1a 1j6",
    "addr:street":"Lock St E",
    "iso:country":"CA",
    "sg:address":"131 Lock St E",
    "sg:city":"Dunnville",
    "sg:classifiers":[
        {
            "category":"Manufacturing",
            "subcategory":"Printing",
            "type":"Manufacturing & Wholesale Goods"
        }
    ],
    "sg:phone":"+1 905 774 7632",
    "sg:postcode":"N1A 1J6",
    "sg:province":"ON",
    "sg:tags":[
        "newspaper"
    ],
    "wof:name":"Dunnville Chronicle",
    "wof:placetype":"venue"
},
  "geometry": {"coordinates":[-79.618812561,42.9029312134],"type":"Point"}
}