{
  "type": "Feature",
  "properties": {
    "addr:full":"9225 Highway 93 Midland ON L4R 4K4",
    "addr:housenumber":"9225",
    "addr:postcode":"l4r 4k4",
    "addr:street":"Highway 93",
    "iso:country":"CA",
    "sg:address":"9225 Highway 93",
    "sg:city":"Midland",
    "sg:classifiers":[
        {
            "category":"Shopping",
            "subcategory":"Florist",
            "type":"Retail Goods"
        }
    ],
    "sg:phone":"+1 705 526 0612",
    "sg:postcode":"L4R 4K4",
    "sg:province":"ON",
    "wof:name":"Ivy Basket Flowers & Gifts",
    "wof:placetype":"venue"
},
  "geometry": {"coordinates":[-79.88851200000001,44.749905],"type":"Point"}
}