{
  "type": "Feature",
  "properties": {
    "addr:full":"Chilliwack BC V2R 4H3",
    "addr:postcode":"v2r 4h3",
    "iso:country":"CA",
    "sg:city":"Chilliwack",
    "sg:classifiers":[
        {
            "category":"Autos & Motor Vehicles",
            "subcategory":"Auto Supplies",
            "type":"Retail Goods"
        }
    ],
    "sg:phone":"+1 604 795 6126",
    "sg:postcode":"V2R 4H3",
    "sg:province":"BC",
    "sg:tags":[
        "battery",
        "gas"
    ],
    "wof:name":"Coast Battery Svc",
    "wof:placetype":"venue"
},
  "geometry": {"coordinates":[-121.981796,49.145069],"type":"Point"}
}