{
  "type": "Feature",
  "properties": {
    "addr:full":"2065 4th Ave W Vancouver BC V6J 1N3",
    "addr:housenumber":"2065",
    "addr:postcode":"v6j 1n3",
    "addr:street":"4Th Ave W",
    "iso:country":"CA",
    "sg:address":"2065 4th Ave W",
    "sg:city":"Vancouver",
    "sg:classifiers":[
        {
            "category":"Shopping",
            "subcategory":"Clothing, Apparel, & Fashions",
            "type":"Retail Goods"
        }
    ],
    "sg:phone":"+1 604 733 4448",
    "sg:postcode":"V6J 1N3",
    "sg:province":"BC",
    "wof:name":"Margareta",
    "wof:placetype":"venue"
},
  "geometry": {"coordinates":[-123.15181,49.268284],"type":"Point"}
}