{
  "type": "Feature",
  "properties": {
    "addr:full":"365 Portland St Dartmouth NS B2Y 1K7",
    "addr:housenumber":"365",
    "addr:postcode":"b2y 1k7",
    "addr:street":"Portland St",
    "iso:country":"CA",
    "sg:address":"365 Portland St",
    "sg:city":"Dartmouth",
    "sg:classifiers":[
        {
            "category":"Wholesale",
            "subcategory":"Scrap",
            "type":"Manufacturing & Wholesale Goods"
        }
    ],
    "sg:phone":"+1 902 469 8770",
    "sg:postcode":"B2Y 1K7",
    "sg:province":"NS",
    "sg:tags":[
        "recycling",
        "can",
        "bottle",
        "depot"
    ],
    "wof:name":"Canadian Recycling",
    "wof:placetype":"venue"
},
  "geometry": {"coordinates":[-63.5494804382,44.6676025391],"type":"Point"}
}