{
  "type": "Feature",
  "properties": {
    "addr:full":"Saint John NB E2J 3R9",
    "addr:postcode":"e2j 3r9",
    "iso:country":"CA",
    "sg:city":"Saint John",
    "sg:classifiers":[
        {
            "category":"Real Estate",
            "subcategory":"Real Estate Operator",
            "type":"Services"
        }
    ],
    "sg:phone":"+1 506 696 1212",
    "sg:postcode":"E2J 3R9",
    "sg:province":"NB",
    "sg:tags":[
        "apartment",
        "rental",
        "agency"
    ],
    "wof:name":"Regency Towers",
    "wof:placetype":"venue"
},
  "geometry": {"coordinates":[-65.98606100000001,45.299137],"type":"Point"}
}