{
  "type": "Feature",
  "properties": {
    "addr:full":"12 Rue Du Petit-Champlain Quebec QC G1K 4H4",
    "addr:housenumber":"12",
    "addr:postcode":"g1k 4h4",
    "addr:street":"Rue Du Petit-Champlain",
    "iso:country":"CA",
    "sg:address":"12 Rue Du Petit-Champlain",
    "sg:city":"Quebec",
    "sg:classifiers":[
        {
            "category":"Restaurant",
            "type":"Food & Drink"
        }
    ],
    "sg:phone":"+1 418 692 0857",
    "sg:postcode":"G1K 4H4",
    "sg:province":"QC",
    "wof:name":"Marie-Clarisse",
    "wof:placetype":"venue"
},
  "geometry": {"coordinates":[-71.203743,46.81234],"type":"Point"}
}