{
  "type": "Feature",
  "properties": {
    "addr:full":"144 Gibson St Fredericton NB E3A 4E2",
    "addr:housenumber":"144",
    "addr:postcode":"e3a 4e2",
    "addr:street":"Gibson St",
    "iso:country":"CA",
    "sg:address":"144 Gibson St",
    "sg:city":"Fredericton",
    "sg:classifiers":[
        {
            "category":"Personal",
            "subcategory":"Barber",
            "type":"Services"
        }
    ],
    "sg:phone":"+1 506 472 8099",
    "sg:postcode":"E3A 4E2",
    "sg:province":"NB",
    "sg:tags":[
        "salon",
        "beauty"
    ],
    "wof:name":"Modern Trend Hair Styling",
    "wof:placetype":"venue"
},
  "geometry": {"coordinates":[-66.623169,45.962231],"type":"Point"}
}