{
  "type": "Feature",
  "properties": {
    "addr:full":"6100 Indian Line Mississauga ON L4V 1G5",
    "addr:housenumber":"6100",
    "addr:postcode":"l4v 1g5",
    "addr:street":"Indian Line",
    "iso:country":"CA",
    "sg:address":"6100 Indian Line",
    "sg:city":"Mississauga",
    "sg:classifiers":[
        {
            "category":"Manufacturing",
            "subcategory":"Glass & Minerals",
            "type":"Manufacturing & Wholesale Goods"
        }
    ],
    "sg:phone":"+1 905 677 7600",
    "sg:postcode":"L4V 1G5",
    "sg:province":"ON",
    "sg:tags":[
        "tile"
    ],
    "wof:name":"Melmart Distributors Inc",
    "wof:placetype":"venue"
},
  "geometry": {"coordinates":[-79.606148,43.693745],"type":"Point"}
}