{
  "type": "Feature",
  "properties": {
    "addr:full":"719 Boul Decarie Saint-Laurent QC H4L 3L3",
    "addr:housenumber":"719",
    "addr:postcode":"h4l 3l3",
    "addr:street":"Boul Decarie",
    "iso:country":"CA",
    "sg:address":"719 Boul Decarie",
    "sg:city":"Saint-Laurent",
    "sg:classifiers":[
        {
            "category":"Restaurant",
            "type":"Food & Drink"
        }
    ],
    "sg:phone":"+1 514 748 8112",
    "sg:postcode":"H4L 3L3",
    "sg:province":"QC",
    "wof:name":"Rio Restaurant",
    "wof:placetype":"venue"
},
  "geometry": {"coordinates":[-73.67705535890001,45.5109176636],"type":"Point"}
}