{
  "type": "Feature",
  "properties": {
    "addr:full":"Montreal QC H2V 4L5",
    "addr:postcode":"h2v 4l5",
    "iso:country":"CA",
    "sg:city":"Montreal",
    "sg:classifiers":[
        {
            "category":"Manufacturing",
            "subcategory":"Rubber & Plastics",
            "type":"Manufacturing & Wholesale Goods"
        }
    ],
    "sg:phone":"+1 514 277 6766",
    "sg:postcode":"H2V 4L5",
    "sg:province":"QC",
    "sg:tags":[
        "belting",
        "supply"
    ],
    "wof:name":"Courroies 3R",
    "wof:placetype":"venue"
},
  "geometry": {"coordinates":[-73.6140136719,45.5291824341],"type":"Point"}
}