{
  "type": "Feature",
  "properties": {
    "addr:full":"Thunder Bay ON P7A 4T7",
    "addr:postcode":"p7a 4t7",
    "iso:country":"CA",
    "sg:city":"Thunder Bay",
    "sg:classifiers":[
        {
            "category":"Organizations",
            "subcategory":"Labor Organization",
            "type":"Services"
        }
    ],
    "sg:phone":"+1 807 345 1731",
    "sg:postcode":"P7A 4T7",
    "sg:province":"ON",
    "wof:name":"Canadian Union Public Emplys",
    "wof:placetype":"venue"
},
  "geometry": {"coordinates":[-89.21951293950001,48.4379081726],"type":"Point"}
}