{
  "type": "Feature",
  "properties": {
    "addr:full":"511 King St Winnipeg MB R2W 5L2",
    "addr:housenumber":"511",
    "addr:postcode":"r2w 5l2",
    "addr:street":"King St",
    "iso:country":"CA",
    "sg:address":"511 King St",
    "sg:city":"Winnipeg",
    "sg:classifiers":[
        {
            "category":"Social Services",
            "subcategory":"Child Care",
            "type":"Services"
        }
    ],
    "sg:phone":"+1 204 582 4636",
    "sg:postcode":"R2W 5L2",
    "sg:province":"MB",
    "wof:name":"Anne Ross Day Nursery",
    "wof:placetype":"venue"
},
  "geometry": {"coordinates":[-97.134956,49.910095],"type":"Point"}
}