{
  "type": "Feature",
  "properties": {
    "addr:full":"Sidney BC V8L 2X1",
    "addr:postcode":"v8l 2x1",
    "iso:country":"CA",
    "sg:city":"Sidney",
    "sg:classifiers":[
        {
            "category":"Insurance",
            "subcategory":"Insurance Agent",
            "type":"Services"
        }
    ],
    "sg:phone":"+1 250 656 9886",
    "sg:postcode":"V8L 2X1",
    "sg:province":"BC",
    "wof:name":"Sea First Insurance Brokers",
    "wof:placetype":"venue"
},
  "geometry": {"coordinates":[-123.400093079,48.6481742859],"type":"Point"}
}