{
  "type": "Feature",
  "properties": {
    "addr:full":"11 Coronation Dr Yellowknife NT X1A 2P7",
    "addr:housenumber":"11",
    "addr:postcode":"x1a 2p7",
    "addr:street":"Coronation Dr",
    "iso:country":"CA",
    "sg:address":"11 Coronation Dr",
    "sg:city":"Yellowknife",
    "sg:classifiers":[
        {
            "category":"Manufacturing",
            "subcategory":"Tools & Machinery",
            "type":"Manufacturing & Wholesale Goods"
        }
    ],
    "sg:phone":"+1 867 873 3953",
    "sg:postcode":"X1A 2P7",
    "sg:province":"NT",
    "sg:tags":[
        "machine",
        "shop"
    ],
    "wof:name":"Northern Machine Shop",
    "wof:placetype":"venue"
},
  "geometry": {"coordinates":[-114.410133362,62.4337997437],"type":"Point"}
}