{
  "type": "Feature",
  "properties": {
    "addr:full":"635 Shawcliffe Gate SW Calgary AB T2Y 1W1",
    "addr:housenumber":"635",
    "addr:postcode":"t2y 1w1",
    "addr:street":"Shawcliffe Gate Sw",
    "iso:country":"CA",
    "sg:address":"635 Shawcliffe Gate SW",
    "sg:city":"Calgary",
    "sg:classifiers":[
        {
            "category":"Education",
            "subcategory":"Dance Studio",
            "type":"Public Place"
        }
    ],
    "sg:phone":"+1 403 256 2808",
    "sg:postcode":"T2Y 1W1",
    "sg:province":"AB",
    "sg:tags":[
        "instruction",
        "dancing"
    ],
    "wof:name":"Drewitz Dance Productions Ltd",
    "wof:placetype":"venue"
},
  "geometry": {"coordinates":[-114.074821,50.911354],"type":"Point"}
}