{
  "type": "Feature",
  "properties": {
    "addr:full":"2530 Rue Dubose Jonquiere QC G7S 1B4",
    "addr:housenumber":"2530",
    "addr:postcode":"g7s 1b4",
    "addr:street":"Rue Dubose",
    "iso:country":"CA",
    "sg:address":"2530 Rue Dubose",
    "sg:city":"Jonquiere",
    "sg:classifiers":[
        {
            "category":"Building & Trades",
            "subcategory":"Equipment Rental",
            "type":"Services"
        }
    ],
    "sg:phone":"+1 418 548 3626",
    "sg:postcode":"G7S 1B4",
    "sg:province":"QC",
    "sg:tags":[
        "leasing"
    ],
    "wof:name":"Echafaudage Fortin Coop",
    "wof:placetype":"venue"
},
  "geometry": {"coordinates":[-71.1597976685,48.4026603699],"type":"Point"}
}