{
  "type": "Feature",
  "properties": {
    "iso:country":"CA",
    "sg:address":"333 Boul Saint-Joseph",
    "sg:city":"Hull",
    "sg:classifiers":[
        {
            "category":"Shopping",
            "subcategory":"Books",
            "type":"Retail Goods"
        }
    ],
    "sg:phone":"+1 819 778 0341",
    "sg:postcode":"J8Y 3Z2",
    "sg:province":"QC",
    "sg:tags":[
        "dealer"
    ],
    "wof:name":"Loisir Des Usagers",
    "wof:placetype":"venue"
},
  "geometry": {"coordinates":[-75.732979,45.441422],"type":"Point"}
}