{
  "type": "Feature",
  "properties": {
    "addr:full":"North York ON M2N 5N4",
    "addr:postcode":"m2n 5n4",
    "iso:country":"CA",
    "sg:city":"North York",
    "sg:classifiers":[
        {
            "category":"Education",
            "subcategory":"School",
            "type":"Public Place"
        }
    ],
    "sg:phone":"+1 416 221 2111",
    "sg:postcode":"M2N 5N4",
    "sg:province":"ON",
    "sg:tags":[
        "instruction",
        "art"
    ],
    "wof:name":"Sabouhi Fine Arts Studio",
    "wof:placetype":"venue"
},
  "geometry": {"coordinates":[-79.4114,43.764111],"type":"Point"}
}