{
  "type": "Feature",
  "properties": {
    "addr:full":"10528 Rue Principale Saint-Louis-DE-Kent NB E4X 1G7",
    "addr:housenumber":"10528",
    "addr:postcode":"e4x 1g7",
    "addr:street":"Rue Principale",
    "iso:country":"CA",
    "sg:address":"10528 Rue Principale",
    "sg:city":"Saint-Louis-DE-Kent",
    "sg:classifiers":[
        {
            "category":"Shopping",
            "subcategory":"Florist",
            "type":"Retail Goods"
        }
    ],
    "sg:phone":"+1 506 876 3828",
    "sg:postcode":"E4X 1G7",
    "sg:province":"NB",
    "wof:name":"Fleuriste Le Relais Fleuri",
    "wof:placetype":"venue"
},
  "geometry": {"coordinates":[-64.97275500000001,46.737202],"type":"Point"}
}