{
  "type": "Feature",
  "properties": {
    "addr:full":"431 Rue Du Bateau Passeur Tadoussac QC G0T 2A0",
    "addr:housenumber":"431",
    "addr:postcode":"g0t 2a0",
    "addr:street":"Rue Du Bateau Passeur",
    "iso:country":"CA",
    "sg:address":"431 Rue Du Bateau Passeur",
    "sg:city":"Tadoussac",
    "sg:classifiers":[
        {
            "category":"Recreation",
            "type":"Entertainment"
        }
    ],
    "sg:phone":"+1 418 235 4197",
    "sg:postcode":"G0T 2A0",
    "sg:province":"QC",
    "sg:tags":[
        "tours",
        "sightseeing"
    ],
    "wof:name":"Otis Excursions Inc",
    "wof:placetype":"venue"
},
  "geometry": {"coordinates":[-69.71350099999999,48.150555],"type":"Point"}
}