{
  "type": "Feature",
  "properties": {
    "addr:full":"146 Laird Dr East York ON M4G 3V7",
    "addr:housenumber":"146",
    "addr:postcode":"m4g 3v7",
    "addr:street":"Laird Dr",
    "iso:country":"CA",
    "sg:address":"146 Laird Dr",
    "sg:city":"East York",
    "sg:classifiers":[
        {
            "category":"Shopping",
            "subcategory":"Clothing, Apparel, & Fashions",
            "type":"Retail Goods"
        }
    ],
    "sg:phone":"+1 416 422 3032",
    "sg:postcode":"M4G 3V7",
    "sg:province":"ON",
    "sg:tags":[
        "riding",
        "equipment"
    ],
    "wof:name":"Marigold Enterprises",
    "wof:placetype":"venue"
},
  "geometry": {"coordinates":[-79.36288452150001,43.7084159851],"type":"Point"}
}