{
  "type": "Feature",
  "properties": {
    "addr:full":"1250 Rue DE LA Sapiniere Cap-Rouge QC G1Y 1A4",
    "addr:housenumber":"1250",
    "addr:postcode":"g1y 1a4",
    "addr:street":"Rue De La Sapiniere",
    "iso:country":"CA",
    "sg:address":"1250 Rue DE LA Sapiniere",
    "sg:city":"Cap-Rouge",
    "sg:classifiers":[
        {
            "category":"Building & Trades",
            "subcategory":"Construction",
            "type":"Services"
        }
    ],
    "sg:phone":"+1 418 657 5566",
    "sg:postcode":"G1Y 1A4",
    "sg:province":"QC",
    "sg:tags":[
        "masonry",
        "contractor"
    ],
    "wof:name":"Gaetan Julien & Marius Welsh",
    "wof:placetype":"venue"
},
  "geometry": {"coordinates":[-71.3442,46.759762],"type":"Point"}
}