{
  "type": "Feature",
  "properties": {
    "addr:full":"131 Caldari Rd Concord ON L4K 3Z9",
    "addr:housenumber":"131",
    "addr:postcode":"l4k 3z9",
    "addr:street":"Caldari Rd",
    "iso:country":"CA",
    "sg:address":"131 Caldari Rd",
    "sg:city":"Concord",
    "sg:classifiers":[
        {
            "category":"Wholesale",
            "subcategory":"Machinery & Supplies",
            "type":"Manufacturing & Wholesale Goods"
        }
    ],
    "sg:phone":"+1 416 665 8357",
    "sg:postcode":"L4K 3Z9",
    "sg:province":"ON",
    "sg:tags":[
        "packaging"
    ],
    "wof:name":"Pine Valley Packaging Ltd",
    "wof:placetype":"venue"
},
  "geometry": {"coordinates":[-79.52847300000001,43.820992],"type":"Point"}
}