{
  "type": "Feature",
  "properties": {
    "addr:full":"1510 36 St Vernon BC V1T 6C8",
    "addr:housenumber":"1510",
    "addr:postcode":"v1t 6c8",
    "addr:street":"36 St",
    "iso:country":"CA",
    "sg:address":"1510 36 St",
    "sg:city":"Vernon",
    "sg:classifiers":[
        {
            "category":"Education",
            "subcategory":"School",
            "type":"Public Place"
        }
    ],
    "sg:phone":"+1 250 545 0639",
    "sg:postcode":"V1T 6C8",
    "sg:province":"BC",
    "wof:name":"Mission Hill Elementary",
    "wof:placetype":"venue"
},
  "geometry": {"coordinates":[-119.281616211,50.2541694641],"type":"Point"}
}