{
  "type": "Feature",
  "properties": {
    "iso:country":"CA",
    "sg:city":"Vanier",
    "sg:classifiers":[
        {
            "category":"Personal",
            "subcategory":"Beauty Salon",
            "type":"Services"
        }
    ],
    "sg:phone":"+1 418 527 5727",
    "sg:postcode":"G1M 3L7",
    "sg:province":"QC",
    "wof:name":"Salon Noir Sur Blanc Enr",
    "wof:placetype":"venue"
},
  "geometry": {"coordinates":[-71.2638244629,46.8144416809],"type":"Point"}
}