{
  "type": "Feature",
  "properties": {
    "addr:full":"2751 132 Rte E Le Bic QC G0L 1B0",
    "addr:housenumber":"2751",
    "addr:postcode":"g0l 1b0",
    "addr:street":"132 Rte E Le Bic",
    "iso:country":"CA",
    "sg:address":"2751 132 Rte E",
    "sg:city":"Le Bic",
    "sg:classifiers":[
        {
            "category":"Utilities",
            "subcategory":"Fuel Oil & Lpg",
            "type":"Services"
        }
    ],
    "sg:phone":"+1 418 736 4445",
    "sg:postcode":"G0L 1B0",
    "sg:province":"QC",
    "wof:name":"Petroles Sonic",
    "wof:placetype":"venue"
},
  "geometry": {"coordinates":[-68.69478599999999,48.377186],"type":"Point"}
}