{
  "type": "Feature",
  "properties": {
    "addr:full":"Breslau ON N0B 1M0",
    "addr:postcode":"n0b 1m0",
    "iso:country":"CA",
    "sg:city":"Breslau",
    "sg:classifiers":[
        {
            "category":"Airport",
            "type":"Transportation"
        }
    ],
    "sg:phone":"+1 519 648 3537",
    "sg:postcode":"N0B 1M0",
    "sg:province":"ON",
    "sg:tags":[
        "aircraft",
        "maintenance"
    ],
    "wof:name":"Rotor Services Ltd",
    "wof:placetype":"venue"
},
  "geometry": {"coordinates":[-80.510437,43.539959],"type":"Point"}
}