{
  "type": "Feature",
  "properties": {
    "addr:full":"2716 Rena Rd Mississauga ON L4T 3J9",
    "addr:housenumber":"2716",
    "addr:postcode":"l4t 3j9",
    "addr:street":"Rena Rd",
    "iso:country":"CA",
    "sg:address":"2716 Rena Rd",
    "sg:city":"Mississauga",
    "sg:classifiers":[
        {
            "category":"Manufacturing",
            "subcategory":"Metals",
            "type":"Manufacturing & Wholesale Goods"
        }
    ],
    "sg:phone":"+1 905 678 0432",
    "sg:postcode":"L4T 3J9",
    "sg:province":"ON",
    "sg:tags":[
        "production",
        "grinding"
    ],
    "wof:name":"Midland Grinding CO Ltd",
    "wof:placetype":"venue"
},
  "geometry": {"coordinates":[-79.661942,43.710659],"type":"Point"}
}