{
  "type": "Feature",
  "properties": {
    "addr:full":"6280 Danville Rd Mississauga ON L5T 2H7",
    "addr:housenumber":"6280",
    "addr:postcode":"l5t 2h7",
    "addr:street":"Danville Rd",
    "iso:country":"CA",
    "sg:address":"6280 Danville Rd",
    "sg:city":"Mississauga",
    "sg:classifiers":[
        {
            "category":"Manufacturing",
            "subcategory":"Metals",
            "type":"Manufacturing & Wholesale Goods"
        }
    ],
    "sg:phone":"+1 905 564 0946",
    "sg:postcode":"L5T 2H7",
    "sg:province":"ON",
    "sg:tags":[
        "gas",
        "burner"
    ],
    "wof:name":"Weishaupt Corp",
    "wof:placetype":"venue"
},
  "geometry": {"coordinates":[-79.67520141599999,43.6434707642],"type":"Point"}
}