{
  "type": "Feature",
  "properties": {
    "iso:country":"CA",
    "sg:address":"128 Brock St S",
    "sg:city":"Whitby",
    "sg:classifiers":[
        {
            "category":"Organizations",
            "subcategory":"Professional Association",
            "type":"Services"
        }
    ],
    "sg:phone":"+1 905 668 4506",
    "sg:postcode":"L1N 4J8",
    "sg:province":"ON",
    "wof:name":"Whitby Chamber of Commerce",
    "wof:placetype":"venue"
},
  "geometry": {"coordinates":[-78.94226837159999,43.8794784546],"type":"Point"}
}