{
  "type": "Feature",
  "properties": {
    "addr:full":"198 1st Ave NE Swift Current SK S9H 2B2",
    "addr:housenumber":"198",
    "addr:postcode":"s9h 2b2",
    "addr:street":"1St Ave Ne",
    "iso:country":"CA",
    "sg:address":"198 1st Ave NE",
    "sg:city":"Swift Current",
    "sg:classifiers":[
        {
            "category":"Government",
            "subcategory":"Office",
            "type":"Public Place"
        }
    ],
    "sg:phone":"+1 306 778 2770",
    "sg:postcode":"S9H 2B2",
    "sg:province":"SK",
    "sg:tags":[
        "village"
    ],
    "wof:name":"Swift Current Light & Power",
    "wof:placetype":"venue"
},
  "geometry": {"coordinates":[-107.79888200000001,50.284904],"type":"Point"}
}