{
  "type": "Feature",
  "properties": {
    "addr:full":"1130 Fife St Winnipeg MB R2X 2Z6",
    "addr:housenumber":"1130",
    "addr:postcode":"r2x 2z6",
    "addr:street":"Fife St",
    "iso:country":"CA",
    "sg:address":"1130 Fife St",
    "sg:city":"Winnipeg",
    "sg:classifiers":[
        {
            "category":"Retail",
            "subcategory":"Auto Repair",
            "type":"Services"
        }
    ],
    "sg:phone":"+1 204 632 7712",
    "sg:postcode":"R2X 2Z6",
    "sg:province":"MB",
    "sg:tags":[
        "repairing",
        "automobile",
        "painting"
    ],
    "wof:name":"World Auto Svc Ctr Inc",
    "wof:placetype":"venue"
},
  "geometry": {"coordinates":[-97.17115020750001,49.9338569641],"type":"Point"}
}