{
  "type": "Feature",
  "properties": {
    "addr:full":"1594 Av Du Mont-Royal E Montreal QC H2J 1Z2",
    "addr:housenumber":"1594",
    "addr:postcode":"h2j 1z2",
    "addr:street":"Av Du Mont-Royal E",
    "iso:country":"CA",
    "sg:address":"1594 Av Du Mont-Royal E",
    "sg:city":"Montreal",
    "sg:classifiers":[
        {
            "category":"Personal",
            "subcategory":"Beauty Salon",
            "type":"Services"
        }
    ],
    "sg:phone":"+1 514 598 1548",
    "sg:postcode":"H2J 1Z2",
    "sg:province":"QC",
    "wof:name":"Boite A Coiffer",
    "wof:placetype":"venue"
},
  "geometry": {"coordinates":[-73.57521800000001,45.532036],"type":"Point"}
}