{
  "type": "Feature",
  "properties": {
    "addr:full":"9521 154 St NW Edmonton AB T5P 2E8",
    "addr:housenumber":"9521",
    "addr:postcode":"t5p 2e8",
    "addr:street":"154 St Nw",
    "iso:country":"CA",
    "sg:address":"9521 154 St NW",
    "sg:city":"Edmonton",
    "sg:classifiers":[
        {
            "category":"Wholesale",
            "subcategory":"Metals & Minerals",
            "type":"Manufacturing & Wholesale Goods"
        }
    ],
    "sg:phone":"+1 780 483 0091",
    "sg:postcode":"T5P 2E8",
    "sg:province":"AB",
    "sg:tags":[
        "piling"
    ],
    "wof:name":"Beamish Enterprises",
    "wof:placetype":"venue"
},
  "geometry": {"coordinates":[-113.58657836899999,53.5319519043],"type":"Point"}
}