{
  "type": "Feature",
  "properties": {
    "addr:full":"Drayton Valley AB T7A 1R8",
    "addr:postcode":"t7a 1r8",
    "addr:street":"Drayton",
    "iso:country":"CA",
    "sg:city":"Drayton Valley",
    "sg:classifiers":[
        {
            "category":"Building & Trades",
            "subcategory":"Plumbing",
            "type":"Services"
        }
    ],
    "sg:phone":"+1 780 542 6005",
    "sg:postcode":"T7A 1R8",
    "sg:province":"AB",
    "sg:tags":[
        "contractor"
    ],
    "wof:name":"Five Points Plumbing & Heating",
    "wof:placetype":"venue"
},
  "geometry": {"coordinates":[-114.982513428,53.2217674255],"type":"Point"}
}