{
  "type": "Feature",
  "properties": {
    "addr:full":"85 Ohio Rd Shelburne NS B0T 1W0",
    "addr:housenumber":"85",
    "addr:postcode":"b0t 1w0",
    "addr:street":"Ohio Rd",
    "iso:country":"CA",
    "sg:address":"85 Ohio Rd",
    "sg:city":"Shelburne",
    "sg:classifiers":[
        {
            "category":"Food & Beverages",
            "subcategory":"Bakery",
            "type":"Retail Goods"
        }
    ],
    "sg:phone":"+1 902 875 2513",
    "sg:postcode":"B0T 1W0",
    "sg:province":"NS",
    "sg:tags":[
        "doughnut"
    ],
    "wof:name":"Tim Horton's",
    "wof:placetype":"venue"
},
  "geometry": {"coordinates":[-65.31564331049999,43.7656593323],"type":"Point"}
}