{
  "type": "Feature",
  "properties": {
    "addr:full":"384 Shepherd St W Windsor ON N8X 1C3",
    "addr:housenumber":"384",
    "addr:postcode":"n8x 1c3",
    "addr:street":"Shepherd St W",
    "iso:country":"CA",
    "sg:address":"384 Shepherd St W",
    "sg:city":"Windsor",
    "sg:classifiers":[
        {
            "category":"Food & Beverages",
            "subcategory":"Groceries & Convenience Stores",
            "type":"Retail Goods"
        }
    ],
    "sg:phone":"+1 519 254 5722",
    "sg:postcode":"N8X 1C3",
    "sg:province":"ON",
    "sg:tags":[
        "variety"
    ],
    "wof:name":"Shepherd Variety",
    "wof:placetype":"venue"
},
  "geometry": {"coordinates":[-83.0318069458,42.2993354797],"type":"Point"}
}