{
  "type": "Feature",
  "properties": {
    "addr:full":"913 Tamarac St Dunnville ON N1A 2E5",
    "addr:housenumber":"913",
    "addr:postcode":"n1a 2e5",
    "addr:street":"Tamarac St",
    "iso:country":"CA",
    "sg:address":"913 Tamarac St",
    "sg:city":"Dunnville",
    "sg:classifiers":[
        {
            "category":"Taxi",
            "type":"Transportation"
        }
    ],
    "sg:phone":"+1 905 774 7161",
    "sg:postcode":"N1A 2E5",
    "sg:province":"ON",
    "sg:tags":[
        "taxicab"
    ],
    "wof:name":"Pat's Cab",
    "wof:placetype":"venue"
},
  "geometry": {"coordinates":[-79.60991668699999,42.9089851379],"type":"Point"}
}