{
  "type": "Feature",
  "properties": {
    "iso:country":"CA",
    "sg:address":"615 Ave DE LA Fabrique",
    "sg:city":"Girardville",
    "sg:classifiers":[
        {
            "category":"Health Services",
            "subcategory":"Doctor",
            "type":"Services"
        }
    ],
    "sg:phone":"+1 418 258 3208",
    "sg:postcode":"G0W 1R0",
    "sg:province":"QC",
    "sg:tags":[
        "clinic"
    ],
    "wof:name":"Clinique Medicale-Girardville",
    "wof:placetype":"venue"
},
  "geometry": {"coordinates":[-72.5446548462,49.0046463013],"type":"Point"}
}