{
  "type": "Feature",
  "properties": {
    "iso:country":"CA",
    "sg:address":"1924 Highway 236",
    "sg:city":"Truro",
    "sg:classifiers":[
        {
            "category":"Food & Beverages",
            "subcategory":"Fruits & Vegetables",
            "type":"Retail Goods"
        }
    ],
    "sg:phone":"+1 902 895 4817",
    "sg:postcode":"B2N 5A9",
    "sg:province":"NS",
    "sg:tags":[
        "produce"
    ],
    "wof:name":"P N Stokdijk Greenhouses",
    "wof:placetype":"venue"
},
  "geometry": {"coordinates":[-63.2890396118,45.3660202026],"type":"Point"}
}