{
  "type": "Feature",
  "properties": {
    "addr:full":"1700 Ch Du Fer-A-Cheval #114 Sainte-Julie QC J3E 1G2",
    "addr:housenumber":"1700",
    "addr:postcode":"j3e 1g2",
    "addr:street":"Ch Du Fer-A-Cheval # 114 Sainte-Julie",
    "iso:country":"CA",
    "sg:address":"1700 Ch Du Fer-A-Cheval #114",
    "sg:city":"Sainte-Julie",
    "sg:classifiers":[
        {
            "category":"Personal",
            "type":"Services"
        }
    ],
    "sg:phone":"+1 450 649 8588",
    "sg:postcode":"J3E 1G2",
    "sg:province":"QC",
    "sg:tags":[
        "electrolysis"
    ],
    "wof:name":"Electrolyse Drapeau Michelle",
    "wof:placetype":"venue"
},
  "geometry": {"coordinates":[-73.32659099999999,45.585289],"type":"Point"}
}