{
  "type": "Feature",
  "properties": {
    "addr:full":"1 Brookhaven Dr North York ON M6M 4N6",
    "addr:housenumber":"1",
    "addr:postcode":"m6m 4n6",
    "addr:street":"Brookhaven Dr",
    "iso:country":"CA",
    "sg:address":"1 Brookhaven Dr",
    "sg:city":"North York",
    "sg:classifiers":[
        {
            "category":"Organizations",
            "subcategory":"Religious Organization",
            "type":"Services"
        }
    ],
    "sg:phone":"+1 416 241 2470",
    "sg:postcode":"M6M 4N6",
    "sg:province":"ON",
    "sg:tags":[
        "church"
    ],
    "wof:name":"Greek Orthodox Church",
    "wof:placetype":"venue"
},
  "geometry": {"coordinates":[-79.493706,43.697018],"type":"Point"}
}