{
  "type": "Feature",
  "properties": {
    "addr:full":"1527 Upper Ottawa St #18 Hamilton ON L8W 3J4",
    "addr:housenumber":"1527",
    "addr:postcode":"l8w 3j4",
    "addr:street":"Upper Ottawa St # 18",
    "iso:country":"CA",
    "sg:address":"1527 Upper Ottawa St #18",
    "sg:city":"Hamilton",
    "sg:classifiers":[
        {
            "category":"Wholesale",
            "subcategory":"Home Furnishings",
            "type":"Manufacturing & Wholesale Goods"
        }
    ],
    "sg:phone":"+1 905 574 7563",
    "sg:postcode":"L8W 3J4",
    "sg:province":"ON",
    "sg:tags":[
        "housewares"
    ],
    "wof:name":"Phoenix Cash & Carry",
    "wof:placetype":"venue"
},
  "geometry": {"coordinates":[-79.842666626,43.1934623718],"type":"Point"}
}