{
  "type": "Feature",
  "properties": {
    "addr:full":"2404 Park Ave Brandon MB R7B 0S3",
    "addr:housenumber":"2404",
    "addr:postcode":"r7b 0s3",
    "addr:street":"Park Ave",
    "iso:country":"CA",
    "sg:address":"2404 Park Ave",
    "sg:city":"Brandon",
    "sg:classifiers":[
        {
            "category":"Building & Trades",
            "subcategory":"Construction",
            "type":"Services"
        }
    ],
    "sg:phone":"+1 204 728 2235",
    "sg:postcode":"R7B 0S3",
    "sg:province":"MB",
    "sg:tags":[
        "apartment",
        "general",
        "contractor"
    ],
    "wof:name":"Jacobson & Greiner",
    "wof:placetype":"venue"
},
  "geometry": {"coordinates":[-99.97040557859999,49.8359413147],"type":"Point"}
}