{
  "type": "Feature",
  "properties": {
    "iso:country":"CA",
    "sg:city":"Vancouver",
    "sg:classifiers":[
        {
            "category":"Professional",
            "subcategory":"Management & Consulting",
            "type":"Services"
        }
    ],
    "sg:phone":"+1 604 664 7660",
    "sg:postcode":"V6E 3C9",
    "sg:province":"BC",
    "sg:tags":[
        "counselor",
        "public",
        "relations"
    ],
    "wof:name":"Robertson Group",
    "wof:placetype":"venue"
},
  "geometry": {"coordinates":[-123.122421265,49.2854957581],"type":"Point"}
}