{
  "type": "Feature",
  "properties": {
    "addr:full":"5901 Av Papineau Montreal QC H2G 2W7",
    "addr:housenumber":"5901",
    "addr:postcode":"h2g 2w7",
    "addr:street":"Av Papineau",
    "iso:country":"CA",
    "sg:address":"5901 Av Papineau",
    "sg:city":"Montreal",
    "sg:classifiers":[
        {
            "category":"Shopping",
            "type":"Retail Goods"
        }
    ],
    "sg:phone":"+1 514 270 3666",
    "sg:postcode":"H2G 2W7",
    "sg:province":"QC",
    "sg:tags":[
        "art",
        "gallery",
        "dealer"
    ],
    "wof:name":"Unique Depanneur Enr",
    "wof:placetype":"venue"
},
  "geometry": {"coordinates":[-73.591393,45.540894],"type":"Point"}
}