{
  "type": "Feature",
  "properties": {
    "addr:full":"480 Rue Mccaffrey Saint-Laurent QC H4T 1N1",
    "addr:housenumber":"480",
    "addr:postcode":"h4t 1n1",
    "addr:street":"Rue Mccaffrey",
    "iso:country":"CA",
    "sg:address":"480 Rue Mccaffrey",
    "sg:city":"Saint-Laurent",
    "sg:classifiers":[
        {
            "category":"Recreation",
            "subcategory":"Arcade",
            "type":"Entertainment"
        }
    ],
    "sg:phone":"+1 514 731 2222",
    "sg:postcode":"H4T 1N1",
    "sg:province":"QC",
    "sg:tags":[
        "amusement",
        "devices"
    ],
    "wof:name":"Star Rides Ltd",
    "wof:placetype":"venue"
},
  "geometry": {"coordinates":[-73.70613899999999,45.484608],"type":"Point"}
}