{
  "type": "Feature",
  "properties": {
    "iso:country":"CA",
    "sg:address":"480 Rue Mccaffrey",
    "sg:city":"Saint-Laurent",
    "sg:classifiers":[
        {
            "category":"Recreation",
            "subcategory":"Arcade",
            "type":"Entertainment"
        }
    ],
    "sg:phone":"+1 514 731 2222",
    "sg:postcode":"H4T 1N1",
    "sg:province":"QC",
    "sg:tags":[
        "amusement",
        "devices"
    ],
    "wof:name":"Star Rides Ltd",
    "wof:placetype":"venue"
},
  "geometry": {"coordinates":[-73.706139,45.484608],"type":"Point"}
}