{
  "type": "Feature",
  "properties": {
    "addr:full":"Saint-Bernard QC G0S 2G0",
    "addr:postcode":"g0s 2g0",
    "iso:country":"CA",
    "sg:city":"Saint-Bernard",
    "sg:classifiers":[
        {
            "category":"Retail",
            "subcategory":"Auto Repair",
            "type":"Services"
        }
    ],
    "sg:phone":"+1 418 475 6670",
    "sg:postcode":"G0S 2G0",
    "sg:province":"QC",
    "sg:tags":[
        "repairing",
        "automobile"
    ],
    "wof:name":"Garage Raymond Breton Inc",
    "wof:placetype":"venue"
},
  "geometry": {"coordinates":[-71.14305899999999,46.494274],"type":"Point"}
}