{
  "type": "Feature",
  "properties": {
    "addr:full":"82 Hatton Cres Regina SK S4N 5K6",
    "addr:housenumber":"82",
    "addr:postcode":"s4n 5k6",
    "addr:street":"Hatton Cres",
    "iso:country":"CA",
    "sg:address":"82 Hatton Cres",
    "sg:city":"Regina",
    "sg:classifiers":[
        {
            "category":"Personal",
            "subcategory":"Beauty Salon",
            "type":"Services"
        }
    ],
    "sg:phone":"+1 306 789 7782",
    "sg:postcode":"S4N 5K6",
    "sg:province":"SK",
    "wof:name":"Hair Studio",
    "wof:placetype":"venue"
},
  "geometry": {"coordinates":[-104.538597,50.453156],"type":"Point"}
}