{
  "type": "Feature",
  "properties": {
    "addr:full":"Mississauga ON L4Y 4G6",
    "addr:postcode":"l4y 4g6",
    "iso:country":"CA",
    "sg:city":"Mississauga",
    "sg:classifiers":[
        {
            "category":"Restaurant",
            "type":"Food & Drink"
        }
    ],
    "sg:phone":"+1 905 848 4892",
    "sg:postcode":"L4Y 4G6",
    "sg:province":"ON",
    "wof:name":"Com Tam Dao Vien",
    "wof:placetype":"venue"
},
  "geometry": {"coordinates":[-79.59491,43.599037],"type":"Point"}
}