{
  "type": "Feature",
  "properties": {
    "addr:full":"460 Rue Metivier Vanier QC G1M 2T8",
    "addr:housenumber":"460",
    "addr:postcode":"g1m 2t8",
    "addr:street":"Rue Metivier",
    "iso:country":"CA",
    "sg:address":"460 Rue Metivier",
    "sg:city":"Vanier",
    "sg:classifiers":[
        {
            "category":"Building & Trades",
            "subcategory":"Construction",
            "type":"Services"
        }
    ],
    "sg:phone":"+1 418 681 8080",
    "sg:postcode":"G1M 2T8",
    "sg:province":"QC",
    "sg:tags":[
        "excavating",
        "contractor"
    ],
    "wof:name":"P E Pageau Inc",
    "wof:placetype":"venue"
},
  "geometry": {"coordinates":[-71.278137207,46.8234825134],"type":"Point"}
}