{
  "type": "Feature",
  "properties": {
    "addr:full":"Yorkton SK S3N 1B9",
    "addr:postcode":"s3n 1b9",
    "iso:country":"CA",
    "sg:city":"Yorkton",
    "sg:classifiers":[
        {
            "category":"Professional",
            "subcategory":"Lawyer & Legal Services",
            "type":"Services"
        }
    ],
    "sg:phone":"+1 306 782 2211",
    "sg:postcode":"S3N 1B9",
    "sg:province":"SK",
    "sg:tags":[
        "attorney"
    ],
    "wof:name":"Tourney Dellow",
    "wof:placetype":"venue"
},
  "geometry": {"coordinates":[-102.46018219,51.2107315063],"type":"Point"}
}