{
  "type": "Feature",
  "properties": {
    "addr:full":"Brampton ON L6S 5N4",
    "addr:postcode":"l6s 5n4",
    "iso:country":"CA",
    "sg:city":"Brampton",
    "sg:classifiers":[
        {
            "category":"Building & Trades",
            "subcategory":"Cleaning & Sanitation",
            "type":"Services"
        }
    ],
    "sg:phone":"+1 905 792 6888",
    "sg:postcode":"L6S 5N4",
    "sg:province":"ON",
    "sg:tags":[
        "ventilating",
        "contractor"
    ],
    "wof:name":"Commercial Ventilation Systems",
    "wof:placetype":"venue"
},
  "geometry": {"coordinates":[-79.709152,43.755619],"type":"Point"}
}