{
  "type": "Feature",
  "properties": {
    "iso:country":"CA",
    "sg:address":"10005 Av Du Bois-DE-Boulogne",
    "sg:city":"Montreal",
    "sg:classifiers":[
        {
            "category":"Health Services",
            "subcategory":"Nursing And Care Facility",
            "type":"Services"
        }
    ],
    "sg:phone":"+1 514 745 3414",
    "sg:postcode":"H4N 3B2",
    "sg:province":"QC",
    "sg:tags":[
        "home",
        "retirement",
        "community"
    ],
    "wof:name":"Manoir Bois-DE-Boulogne",
    "wof:placetype":"venue"
},
  "geometry": {"coordinates":[-73.668961,45.536556],"type":"Point"}
}