{
  "type": "Feature",
  "properties": {
    "iso:country":"CA",
    "sg:address":"113 Crantson Rd",
    "sg:city":"Providence Bay",
    "sg:classifiers":[
        {
            "category":"Manufacturing",
            "subcategory":"Building Materials",
            "type":"Manufacturing & Wholesale Goods"
        }
    ],
    "sg:phone":"+1 705 377 4816",
    "sg:postcode":"P0P 1T0",
    "sg:province":"ON",
    "sg:tags":[
        "truss"
    ],
    "wof:name":"Manitoulin Truss & Wall",
    "wof:placetype":"venue"
},
  "geometry": {"coordinates":[-82.26438903810001,45.6640815735],"type":"Point"}
}