{
  "type": "Feature",
  "properties": {
    "addr:full":"8570 Rue Chaminade Saint-Leonard QC H1P 2K7",
    "addr:housenumber":"8570",
    "addr:postcode":"h1p 2k7",
    "addr:street":"Rue Chaminade",
    "iso:country":"CA",
    "sg:address":"8570 Rue Chaminade",
    "sg:city":"Saint-Leonard",
    "sg:classifiers":[
        {
            "category":"Building & Trades",
            "subcategory":"Construction",
            "type":"Services"
        }
    ],
    "sg:phone":"+1 514 324 9401",
    "sg:postcode":"H1P 2K7",
    "sg:province":"QC",
    "sg:tags":[
        "masonry",
        "contractor"
    ],
    "wof:name":"Sirianni Briqueteur Inc",
    "wof:placetype":"venue"
},
  "geometry": {"coordinates":[-73.593521,45.594913],"type":"Point"}
}