{
  "type": "Feature",
  "properties": {
    "addr:full":"Trois-Rivieres QC G8Y 3C9",
    "addr:postcode":"g8y 3c9",
    "iso:country":"CA",
    "sg:city":"Trois-Rivieres",
    "sg:classifiers":[
        {
            "category":"Building & Trades",
            "subcategory":"Construction",
            "type":"Services"
        }
    ],
    "sg:phone":"+1 819 691 4243",
    "sg:postcode":"G8Y 3C9",
    "sg:province":"QC",
    "sg:tags":[
        "general",
        "contractor"
    ],
    "wof:name":"Construction Normand Couture",
    "wof:placetype":"venue"
},
  "geometry": {"coordinates":[-72.6010513306,46.3728675842],"type":"Point"}
}