{
  "type": "Feature",
  "properties": {
    "iso:country":"CA",
    "sg:address":"265 Av Saint-Alphonse",
    "sg:city":"Saint-Bruno-Lac-Saint-Jean",
    "sg:classifiers":[
        {
            "category":"Manufacturing",
            "subcategory":"Tools & Machinery",
            "type":"Manufacturing & Wholesale Goods"
        }
    ],
    "sg:phone":"+1 418 343 3603",
    "sg:postcode":"G0W 2L0",
    "sg:province":"QC",
    "sg:tags":[
        "machine",
        "shop",
        "welding"
    ],
    "wof:name":"Atelier Leo Bouchard Enr",
    "wof:placetype":"venue"
},
  "geometry": {"coordinates":[-71.6560668945,48.4651947021],"type":"Point"}
}