{
  "type": "Feature",
  "properties": {
    "addr:full":"2105 Rue Beaubien E Montreal QC H2G 1M5",
    "addr:housenumber":"2105",
    "addr:postcode":"h2g 1m5",
    "addr:street":"Rue Beaubien E",
    "iso:country":"CA",
    "sg:address":"2105 Rue Beaubien E",
    "sg:city":"Montreal",
    "sg:classifiers":[
        {
            "category":"Government",
            "subcategory":"Office",
            "type":"Public Place"
        }
    ],
    "sg:phone":"+1 514 729 5342",
    "sg:postcode":"H2G 1M5",
    "sg:province":"QC",
    "sg:tags":[
        "member",
        "legislative",
        "assembly"
    ],
    "wof:name":"Bigras, Bernard",
    "wof:placetype":"venue"
},
  "geometry": {"coordinates":[-73.594582,45.545666],"type":"Point"}
}