{
  "type": "Feature",
  "properties": {
    "addr:full":"3545 Montee Saint-Hubert Saint-Hubert QC J3Y 4J8",
    "addr:housenumber":"3545",
    "addr:postcode":"j3y 4j8",
    "addr:street":"Montee Saint-Hubert",
    "iso:country":"CA",
    "sg:address":"3545 Montee Saint-Hubert",
    "sg:city":"Saint-Hubert",
    "sg:classifiers":[
        {
            "category":"Food & Beverages",
            "subcategory":"Bakery",
            "type":"Retail Goods"
        }
    ],
    "sg:phone":"+1 450 445 4151",
    "sg:postcode":"J3Y 4J8",
    "sg:province":"QC",
    "sg:tags":[
        "baker"
    ],
    "wof:name":"Patisserie Toit Rouge",
    "wof:placetype":"venue"
},
  "geometry": {"coordinates":[-73.4283447266,45.4946403503],"type":"Point"}
}