{
  "type": "Feature",
  "properties": {
    "addr:full":"3219 Wells Ave Saskatoon SK S7K 5W4",
    "addr:housenumber":"3219",
    "addr:postcode":"s7k 5w4",
    "addr:street":"Wells Ave",
    "iso:country":"CA",
    "sg:address":"3219 Wells Ave",
    "sg:city":"Saskatoon",
    "sg:classifiers":[
        {
            "category":"Manufacturing",
            "subcategory":"Glass & Minerals",
            "type":"Manufacturing & Wholesale Goods"
        }
    ],
    "sg:phone":"+1 306 933 4948",
    "sg:postcode":"S7K 5W4",
    "sg:province":"SK",
    "sg:tags":[
        "fabricator",
        "excavating",
        "fiber",
        "contractor"
    ],
    "wof:name":"Saskcon Repair Svc Ltd",
    "wof:placetype":"venue"
},
  "geometry": {"coordinates":[-106.648849,52.182484],"type":"Point"}
}