{
  "type": "Feature",
  "properties": {
    "addr:full":"1 Paisley Crt Whitby ON L1N 9L2",
    "addr:housenumber":"1",
    "addr:postcode":"l1n 9l2",
    "addr:street":"Paisley Crt",
    "iso:country":"CA",
    "sg:address":"1 Paisley Crt",
    "sg:city":"Whitby",
    "sg:classifiers":[
        {
            "category":"Restaurant",
            "type":"Food & Drink"
        }
    ],
    "sg:phone":"+1 905 665 1217",
    "sg:postcode":"L1N 9L2",
    "sg:province":"ON",
    "wof:name":"Pioneer Food Courts Office",
    "wof:placetype":"venue"
},
  "geometry": {"coordinates":[-78.93536400000001,43.867683],"type":"Point"}
}