{
  "type": "Feature",
  "properties": {
    "addr:full":"1201 Aimco Blvd Mississauga ON L4W 1B3",
    "addr:housenumber":"1201",
    "addr:postcode":"l4w 1b3",
    "addr:street":"Aimco Blvd",
    "iso:country":"CA",
    "sg:address":"1201 Aimco Blvd",
    "sg:city":"Mississauga",
    "sg:classifiers":[
        {
            "category":"Wholesale",
            "subcategory":"Motor Vehicles",
            "type":"Manufacturing & Wholesale Goods"
        }
    ],
    "sg:phone":"+1 905 625 8441",
    "sg:postcode":"L4W 1B3",
    "sg:province":"ON",
    "sg:tags":[
        "trailer"
    ],
    "wof:name":"Glasvan Great Dane",
    "wof:placetype":"venue"
},
  "geometry": {"coordinates":[-79.63072200000001,43.633068],"type":"Point"}
}