{
  "type": "Feature",
  "properties": {
    "addr:full":"1406 Rue Jacques-Cartier S Saint-Jean-Sur-Richelieu QC J3B 6Y8",
    "addr:housenumber":"1406",
    "addr:postcode":"j3b 6y8",
    "addr:street":"Rue Jacques-Cartier S",
    "iso:country":"CA",
    "sg:address":"1406 Rue Jacques-Cartier S",
    "sg:city":"Saint-Jean-Sur-Richelieu",
    "sg:classifiers":[
        {
            "category":"Wholesale",
            "subcategory":"Machinery & Supplies",
            "type":"Manufacturing & Wholesale Goods"
        }
    ],
    "sg:phone":"+1 450 346 7948",
    "sg:postcode":"J3B 6Y8",
    "sg:province":"QC",
    "sg:tags":[
        "equipment",
        "dairy"
    ],
    "wof:name":"Depanneur Agricole St-Jean Inc",
    "wof:placetype":"venue"
},
  "geometry": {"coordinates":[-73.25602722169999,45.2351913452],"type":"Point"}
}