{
  "type": "Feature",
  "properties": {
    "addr:full":"4903 49 Ave Camrose AB T4V 0M9",
    "addr:housenumber":"4903",
    "addr:postcode":"t4v 0m9",
    "addr:street":"49 Ave",
    "iso:country":"CA",
    "sg:address":"4903 49 Ave",
    "sg:city":"Camrose",
    "sg:classifiers":[
        {
            "category":"Manufacturing",
            "subcategory":"Printing",
            "type":"Manufacturing & Wholesale Goods"
        }
    ],
    "sg:phone":"+1 780 672 4421",
    "sg:postcode":"T4V 0M9",
    "sg:province":"AB",
    "sg:tags":[
        "newspaper"
    ],
    "wof:name":"Camrose Canadian",
    "wof:placetype":"venue"
},
  "geometry": {"coordinates":[-112.82393646200001,53.020488739],"type":"Point"}
}