{
  "type": "Feature",
  "properties": {
    "addr:full":"81 Foster St Perth ON K7H 1R9",
    "addr:housenumber":"81",
    "addr:postcode":"k7h 1r9",
    "addr:street":"Foster St",
    "iso:country":"CA",
    "sg:address":"81 Foster St",
    "sg:city":"Perth",
    "sg:classifiers":[
        {
            "category":"Shopping",
            "subcategory":"Clothing, Apparel, & Fashions",
            "type":"Retail Goods"
        }
    ],
    "sg:phone":"+1 613 267 9678",
    "sg:postcode":"K7H 1R9",
    "sg:province":"ON",
    "sg:tags":[
        "shop",
        "bridal"
    ],
    "wof:name":"A Touch of Dlca Bridal Shop",
    "wof:placetype":"venue"
},
  "geometry": {"coordinates":[-76.2521362305,44.9008293152],"type":"Point"}
}