{
  "type": "Feature",
  "properties": {
    "addr:full":"147 Rue Des Cedres Stratford QC G0Y 1P0",
    "addr:housenumber":"147",
    "addr:postcode":"g0y 1p0",
    "addr:street":"Rue Des Cedres",
    "iso:country":"CA",
    "sg:address":"147 Rue Des Cedres",
    "sg:city":"Stratford",
    "sg:classifiers":[
        {
            "category":"Retail",
            "subcategory":"Veterinary Services",
            "type":"Services"
        }
    ],
    "sg:phone":"+1 418 443 2583",
    "sg:postcode":"G0Y 1P0",
    "sg:province":"QC",
    "sg:tags":[
        "veterinarian"
    ],
    "wof:name":"Boyer, Danielle DVM",
    "wof:placetype":"venue"
},
  "geometry": {"coordinates":[-71.283379,45.783535],"type":"Point"}
}