{
  "type": "Feature",
  "properties": {
    "iso:country":"CA",
    "sg:address":"182 Hwy 53",
    "sg:city":"Cathcart",
    "sg:classifiers":[
        {
            "category":"Retail",
            "subcategory":"Auto Repair",
            "type":"Services"
        }
    ],
    "sg:phone":"+1 519 458 4711",
    "sg:postcode":"N0E 1B0",
    "sg:province":"ON",
    "sg:tags":[
        "repairing",
        "automobile"
    ],
    "wof:name":"Randy's Garage",
    "wof:placetype":"venue"
},
  "geometry": {"coordinates":[-80.5222320557,43.1014060974],"type":"Point"}
}