{
  "type": "Feature",
  "properties": {
    "addr:full":"413 Souris Ave Weyburn SK S4H 0C9",
    "addr:housenumber":"413",
    "addr:postcode":"s4h 0c9",
    "addr:street":"Souris Ave",
    "iso:country":"CA",
    "sg:address":"413 Souris Ave",
    "sg:city":"Weyburn",
    "sg:classifiers":[
        {
            "category":"Shopping",
            "subcategory":"Used Merchandise",
            "type":"Retail Goods"
        }
    ],
    "sg:phone":"+1 306 842 1979",
    "sg:postcode":"S4H 0C9",
    "sg:province":"SK",
    "sg:tags":[
        "second",
        "store",
        "hand"
    ],
    "wof:name":"Rainbow Recyclers",
    "wof:placetype":"venue"
},
  "geometry": {"coordinates":[-103.851601,49.661522],"type":"Point"}
}