{
  "type": "Feature",
  "properties": {
    "addr:full":"1430 Boul Monseigneur-Langlois Salaberry-DE-Valleyfield QC J6S 1E3",
    "addr:housenumber":"1430",
    "addr:postcode":"j6s 1e3",
    "addr:street":"Boul Monseigneur-Langlois",
    "iso:country":"CA",
    "sg:address":"1430 Boul Monseigneur-Langlois",
    "sg:city":"Salaberry-DE-Valleyfield",
    "sg:classifiers":[
        {
            "category":"Shopping",
            "subcategory":"Clothing, Apparel, & Fashions",
            "type":"Retail Goods"
        }
    ],
    "sg:phone":"+1 450 371 6461",
    "sg:postcode":"J6S 1E3",
    "sg:province":"QC",
    "sg:tags":[
        "furnishing"
    ],
    "wof:name":"L'Equipeur",
    "wof:placetype":"venue"
},
  "geometry": {"coordinates":[-74.1318893433,45.2708053589],"type":"Point"}
}