{
  "type": "Feature",
  "properties": {
    "addr:full":"851 Golf Links Rd Ancaster ON L9K 1L5",
    "addr:housenumber":"851",
    "addr:postcode":"l9k 1l5",
    "addr:street":"Golf Links Rd",
    "iso:country":"CA",
    "sg:address":"851 Golf Links Rd",
    "sg:city":"Ancaster",
    "sg:classifiers":[
        {
            "category":"Banks & Credit Unions",
            "subcategory":"Bank",
            "type":"Services"
        }
    ],
    "sg:phone":"+1 905 304 4100",
    "sg:postcode":"L9K 1L5",
    "sg:province":"ON",
    "wof:name":"Scotiabank",
    "wof:placetype":"venue"
},
  "geometry": {"coordinates":[-79.94998168950001,43.2262077332],"type":"Point"}
}