{
  "type": "Feature",
  "properties": {
    "addr:full":"56 Broadway St N Kensington PE C0B 1M0",
    "addr:housenumber":"56",
    "addr:postcode":"c0b 1m0",
    "addr:street":"Broadway St N",
    "iso:country":"CA",
    "sg:address":"56 Broadway St N",
    "sg:city":"Kensington",
    "sg:classifiers":[
        {
            "category":"Shopping",
            "subcategory":"Pharmacy",
            "type":"Retail Goods"
        }
    ],
    "sg:phone":"+1 902 836 3316",
    "sg:postcode":"C0B 1M0",
    "sg:province":"PE",
    "wof:name":"Ramsay Pharmacy Ltd",
    "wof:placetype":"venue"
},
  "geometry": {"coordinates":[-63.6380691528,46.4376411438],"type":"Point"}
}