{
  "type": "Feature",
  "properties": {
    "addr:full":"945 Rue Saint-Jean Roberval QC G8H 2H3",
    "addr:housenumber":"945",
    "addr:postcode":"g8h 2h3",
    "addr:street":"Rue Saint-Jean",
    "iso:country":"CA",
    "sg:address":"945 Rue Saint-Jean",
    "sg:city":"Roberval",
    "sg:classifiers":[
        {
            "category":"Health Services",
            "subcategory":"Doctor",
            "type":"Services"
        }
    ],
    "sg:phone":"+1 418 275 3172",
    "sg:postcode":"G8H 2H3",
    "sg:province":"QC",
    "sg:tags":[
        "physician",
        "clinic",
        "surgeon"
    ],
    "wof:name":"2099-2533 Quebec Inc",
    "wof:placetype":"venue"
},
  "geometry": {"coordinates":[-72.224678,48.520672],"type":"Point"}
}