{
  "type": "Feature",
  "properties": {
    "addr:full":"935 St David St N Fergus ON N1M 2W3",
    "addr:housenumber":"935",
    "addr:postcode":"n1m 2w3",
    "addr:street":"St David St N",
    "iso:country":"CA",
    "sg:address":"935 St David St N",
    "sg:city":"Fergus",
    "sg:classifiers":[
        {
            "category":"Autos & Motor Vehicles",
            "subcategory":"Fuel & Gas Station",
            "type":"Retail Goods"
        }
    ],
    "sg:phone":"+1 519 843 7656",
    "sg:postcode":"N1M 2W3",
    "sg:province":"ON",
    "sg:tags":[
        "oil"
    ],
    "wof:name":"Blinkhorn's Corner Variety",
    "wof:placetype":"venue"
},
  "geometry": {"coordinates":[-80.393181,43.715454],"type":"Point"}
}