{
  "type": "Feature",
  "properties": {
    "addr:full":"321 St. George St Moncton NB E1C 1W8",
    "addr:housenumber":"321",
    "addr:postcode":"e1c 1w8",
    "addr:street":"St. George St",
    "iso:country":"CA",
    "sg:address":"321 St. George St",
    "sg:city":"Moncton",
    "sg:classifiers":[
        {
            "category":"Shopping",
            "subcategory":"Pharmacy",
            "type":"Retail Goods"
        }
    ],
    "sg:phone":"+1 506 857 4150",
    "sg:postcode":"E1C 1W8",
    "sg:province":"NB",
    "wof:name":"Staples Drugs",
    "wof:placetype":"venue"
},
  "geometry": {"coordinates":[-64.786697,46.090515],"type":"Point"}
}