{
  "type": "Feature",
  "properties": {
    "addr:full":"Vancouver BC V6B 2S2",
    "addr:postcode":"v6b 2s2",
    "iso:country":"CA",
    "sg:city":"Vancouver",
    "sg:classifiers":[
        {
            "category":"Health Services",
            "subcategory":"Health Practitioner",
            "type":"Services"
        }
    ],
    "sg:phone":"+1 604 682 4336",
    "sg:postcode":"V6B 2S2",
    "sg:province":"BC",
    "sg:tags":[
        "psychologist"
    ],
    "wof:name":"Kaushansky & Assoc",
    "wof:placetype":"venue"
},
  "geometry": {"coordinates":[-123.121979,49.275154],"type":"Point"}
}