{
  "type": "Feature",
  "properties": {
    "addr:full":"1062 Davie St Vancouver BC V6E 1M3",
    "addr:housenumber":"1062",
    "addr:postcode":"v6e 1m3",
    "addr:street":"Davie St",
    "iso:country":"CA",
    "sg:address":"1062 Davie St",
    "sg:city":"Vancouver",
    "sg:classifiers":[
        {
            "category":"Restaurant",
            "type":"Food & Drink"
        }
    ],
    "sg:phone":"+1 604 684 7848",
    "sg:postcode":"V6E 1M3",
    "sg:province":"BC",
    "wof:name":"Donair Pizza",
    "wof:placetype":"venue"
},
  "geometry": {"coordinates":[-123.130561829,49.2797775269],"type":"Point"}
}