{
  "type": "Feature",
  "properties": {
    "iso:country":"CA",
    "sg:address":"4 Av Saint-Augustin",
    "sg:city":"Sainte-Helene-DE-Breakeyville",
    "sg:classifiers":[
        {
            "category":"Autos & Motor Vehicles",
            "subcategory":"Motorcycle Sales",
            "type":"Retail Goods"
        }
    ],
    "sg:phone":"+1 418 832 6143",
    "sg:postcode":"G0S 1E1",
    "sg:province":"QC",
    "sg:tags":[
        "scooter"
    ],
    "wof:name":"Lavertu Equipement Inc",
    "wof:placetype":"venue"
},
  "geometry": {"coordinates":[-71.2401809692,46.691947937],"type":"Point"}
}