{
  "type": "Feature",
  "properties": {
    "addr:full":"892 Upper James St Hamilton ON L9C 3A5",
    "addr:housenumber":"892",
    "addr:postcode":"l9c 3a5",
    "addr:street":"Upper James St",
    "iso:country":"CA",
    "sg:address":"892 Upper James St",
    "sg:city":"Hamilton",
    "sg:classifiers":[
        {
            "category":"Shopping",
            "subcategory":"Musical Instruments",
            "type":"Retail Goods"
        }
    ],
    "sg:phone":"+1 905 318 9890",
    "sg:postcode":"L9C 3A5",
    "sg:province":"ON",
    "wof:name":"Pongetti Musical Instruments",
    "wof:placetype":"venue"
},
  "geometry": {"coordinates":[-79.8830032349,43.2260665894],"type":"Point"}
}