{
  "type": "Feature",
  "properties": {
    "addr:full":"Vancouver BC V6B 6H5",
    "addr:postcode":"v6b 6h5",
    "iso:country":"CA",
    "sg:city":"Vancouver",
    "sg:classifiers":[
        {
            "category":"Arts & Performance",
            "subcategory":"Theater",
            "type":"Entertainment"
        }
    ],
    "sg:phone":"+1 604 685 2218",
    "sg:postcode":"V6B 6H5",
    "sg:province":"BC",
    "sg:tags":[
        "talent",
        "agency",
        "casting"
    ],
    "wof:name":"Keystone Extras",
    "wof:placetype":"venue"
},
  "geometry": {"coordinates":[-123.112877,49.283596],"type":"Point"}
}