{
  "type": "Feature",
  "properties": {
    "addr:full":"100 Main St Dartmouth NS B2X 1R5",
    "addr:housenumber":"100",
    "addr:postcode":"b2x 1r5",
    "addr:street":"Main St",
    "iso:country":"CA",
    "sg:address":"100 Main St",
    "sg:city":"Dartmouth",
    "sg:classifiers":[
        {
            "category":"Food & Beverages",
            "subcategory":"Liquor & Beverages",
            "type":"Retail Goods"
        }
    ],
    "sg:phone":"+1 902 434 7410",
    "sg:postcode":"B2X 1R5",
    "sg:province":"NS",
    "sg:tags":[
        "store"
    ],
    "wof:name":"Nova Scotia Liquor Store",
    "wof:placetype":"venue"
},
  "geometry": {"coordinates":[-63.541168,44.681602],"type":"Point"}
}