{
  "type": "Feature",
  "properties": {
    "addr:full":"Frontier SK S0N 0W0",
    "addr:postcode":"s0n 0w0",
    "addr:street":"Frontier",
    "iso:country":"CA",
    "sg:city":"Frontier",
    "sg:classifiers":[
        {
            "category":"Wholesale",
            "subcategory":"Machinery & Supplies",
            "type":"Manufacturing & Wholesale Goods"
        }
    ],
    "sg:phone":"+1 306 296 2297",
    "sg:postcode":"S0N 0W0",
    "sg:province":"SK",
    "sg:tags":[
        "agricultural",
        "implement"
    ],
    "wof:name":"Honey Bee Mfg Ltd",
    "wof:placetype":"venue"
},
  "geometry": {"coordinates":[-108.561852,49.204166],"type":"Point"}
}