{
  "type": "Feature",
  "properties": {
    "iso:country":"CA",
    "sg:address":"1415 33 St N",
    "sg:city":"Lethbridge",
    "sg:classifiers":[
        {
            "category":"Freight",
            "type":"Transportation"
        }
    ],
    "sg:phone":"+1 403 328 4485",
    "sg:postcode":"T1H 5H2",
    "sg:province":"AB",
    "sg:tags":[
        "mover"
    ],
    "wof:name":"Pack & Ship",
    "wof:placetype":"venue"
},
  "geometry": {"coordinates":[-112.791618347,49.7182922363],"type":"Point"}
}