{
  "type": "Feature",
  "properties": {
    "addr:full":"300 Preston St Ottawa ON K1R 7R6",
    "addr:housenumber":"300",
    "addr:postcode":"k1r 7r6",
    "addr:street":"Preston St",
    "iso:country":"CA",
    "sg:address":"300 Preston St",
    "sg:city":"Ottawa",
    "sg:classifiers":[
        {
            "category":"Restaurant",
            "type":"Food & Drink"
        }
    ],
    "sg:phone":"+1 613 234 3030",
    "sg:postcode":"K1R 7R6",
    "sg:province":"ON",
    "wof:name":"Domino's Pizza",
    "wof:placetype":"venue"
},
  "geometry": {"coordinates":[-75.711128,45.403107],"type":"Point"}
}