{
  "type": "Feature",
  "properties": {
    "addr:full":"1068 Granville St Vancouver BC V6Z 1L5",
    "addr:housenumber":"1068",
    "addr:postcode":"v6z 1l5",
    "addr:street":"Granville St",
    "iso:country":"CA",
    "sg:address":"1068 Granville St",
    "sg:city":"Vancouver",
    "sg:classifiers":[
        {
            "category":"Personal",
            "subcategory":"Tattoo Parlor",
            "type":"Services"
        }
    ],
    "sg:phone":"+1 604 684 6398",
    "sg:postcode":"V6Z 1L5",
    "sg:province":"BC",
    "sg:tags":[
        "tattooing",
        "body",
        "piercing"
    ],
    "wof:name":"Next Body Piercing & Tattooing",
    "wof:placetype":"venue"
},
  "geometry": {"coordinates":[-123.123901367,49.2785186768],"type":"Point"}
}