{
  "type": "Feature",
  "properties": {
    "addr:full":"2222 Portland St SE Calgary AB T2G 4M6",
    "addr:housenumber":"2222",
    "addr:postcode":"t2g 4m6",
    "addr:street":"Portland St Se",
    "iso:country":"CA",
    "sg:address":"2222 Portland St SE",
    "sg:city":"Calgary",
    "sg:classifiers":[
        {
            "category":"Restaurant",
            "type":"Food & Drink"
        }
    ],
    "sg:phone":"+1 403 253 9214",
    "sg:postcode":"T2G 4M6",
    "sg:province":"AB",
    "sg:tags":[
        "popcorn",
        "parlor",
        "supply",
        "ice",
        "cream"
    ],
    "wof:name":"Harlan Fairbanks CO Ltd",
    "wof:placetype":"venue"
},
  "geometry": {"coordinates":[-114.035667,51.034019],"type":"Point"}
}