{
  "type": "Feature",
  "properties": {
    "iso:country":"CA",
    "sg:address":"70 Rankin St",
    "sg:city":"Waterloo",
    "sg:classifiers":[
        {
            "category":"Manufacturing",
            "subcategory":"Metals",
            "type":"Manufacturing & Wholesale Goods"
        }
    ],
    "sg:phone":"+1 519 885 1100",
    "sg:postcode":"N2V 1V9",
    "sg:province":"ON",
    "sg:tags":[
        "fastener",
        "bolt"
    ],
    "wof:name":"Eldorado Industrial Sales Inc",
    "wof:placetype":"venue"
},
  "geometry": {"coordinates":[-80.53686500000001,43.510567],"type":"Point"}
}