{
  "type": "Feature",
  "properties": {
    "addr:full":"5150 Boul DE L'Ormiere Quebec QC G1P 4B2",
    "addr:housenumber":"5150",
    "addr:postcode":"g1p 4b2",
    "addr:street":"Boul De L'Ormiere",
    "iso:country":"CA",
    "sg:address":"5150 Boul DE L'Ormiere",
    "sg:city":"Quebec",
    "sg:classifiers":[
        {
            "category":"Real Estate",
            "subcategory":"Real Estate Operator",
            "type":"Services"
        }
    ],
    "sg:phone":"+1 418 872 6660",
    "sg:postcode":"G1P 4B2",
    "sg:province":"QC",
    "sg:tags":[
        "mall",
        "shopping",
        "center"
    ],
    "wof:name":"Centre Commercial Carrefour",
    "wof:placetype":"venue"
},
  "geometry": {"coordinates":[-71.3399353027,46.8249206543],"type":"Point"}
}