{
  "type": "Feature",
  "properties": {
    "addr:full":"29 William St Bolton ON L7E 4V3",
    "addr:housenumber":"29",
    "addr:postcode":"l7e 4v3",
    "addr:street":"William St",
    "iso:country":"CA",
    "sg:address":"29 William St",
    "sg:city":"Bolton",
    "sg:classifiers":[
        {
            "category":"Shopping",
            "type":"Retail Goods"
        }
    ],
    "sg:phone":"+1 905 857 6047",
    "sg:postcode":"L7E 4V3",
    "sg:province":"ON",
    "sg:tags":[
        "tile",
        "mural"
    ],
    "wof:name":"Gabry Fine Art",
    "wof:placetype":"venue"
},
  "geometry": {"coordinates":[-79.73314666749999,43.8747406006],"type":"Point"}
}