{
  "type": "Feature",
  "properties": {
    "addr:full":"20 Rue Mercier Beauport QC G1C 3A2",
    "addr:housenumber":"20",
    "addr:postcode":"qc g1c 3a2",
    "addr:street":"Rue Mercier",
    "iso:country":"CA",
    "sg:address":"20 Rue Mercier",
    "sg:city":"Beauport",
    "sg:classifiers":[
        {
            "category":"Manufacturing",
            "subcategory":"Furniture",
            "type":"Manufacturing & Wholesale Goods"
        }
    ],
    "sg:phone":"+1 418 666 7642",
    "sg:postcode":"G1C 3A2",
    "sg:province":"QC",
    "wof:name":"Ebenisterie Routhier Enr",
    "wof:placetype":"venue"
},
  "geometry": {"coordinates":[-71.162102,46.882942],"type":"Point"}
}