{
  "type": "Feature",
  "properties": {
    "addr:full":"1302 Bloor St W Toronto ON M6H 1N9",
    "addr:housenumber":"1302",
    "addr:postcode":"m6h 1n9",
    "addr:street":"Bloor St W",
    "iso:country":"CA",
    "sg:address":"1302 Bloor St W",
    "sg:city":"Toronto",
    "sg:classifiers":[
        {
            "category":"Personal",
            "subcategory":"Beauty Salon",
            "type":"Services"
        }
    ],
    "sg:phone":"+1 416 534 9603",
    "sg:postcode":"M6H 1N9",
    "sg:province":"ON",
    "wof:name":"Pearl Unisex",
    "wof:placetype":"venue"
},
  "geometry": {"coordinates":[-79.442398,43.65855],"type":"Point"}
}