{
  "type": "Feature",
  "properties": {
    "addr:full":"967 Trunk Rd Sault Ste Marie ON P6A 5K9",
    "addr:housenumber":"967",
    "addr:postcode":"p6a 5k9",
    "addr:street":"Trunk Rd",
    "iso:country":"CA",
    "sg:address":"967 Trunk Rd",
    "sg:city":"Sault Ste Marie",
    "sg:classifiers":[
        {
            "category":"Autos & Motor Vehicles",
            "subcategory":"Automobile Sales",
            "type":"Retail Goods"
        }
    ],
    "sg:phone":"+1 705 759 1133",
    "sg:postcode":"P6A 5K9",
    "sg:province":"ON",
    "sg:tags":[
        "car",
        "dealer"
    ],
    "wof:name":"World Cars Complex",
    "wof:placetype":"venue"
},
  "geometry": {"coordinates":[-84.2604293823,46.5276069641],"type":"Point"}
}