{
  "type": "Feature",
  "properties": {
    "addr:full":"Hwy 330 S Oak Bluff MB R0G 1N0",
    "addr:postcode":"r0g 1n0",
    "addr:street":"Hwy 330 S Oak Bluff",
    "iso:country":"CA",
    "sg:address":"Hwy 330 S",
    "sg:city":"Oak Bluff",
    "sg:classifiers":[
        {
            "category":"Wholesale",
            "subcategory":"Farm Supplies",
            "type":"Manufacturing & Wholesale Goods"
        }
    ],
    "sg:phone":"+1 204 388 4224",
    "sg:postcode":"R0G 1N0",
    "sg:province":"MB",
    "sg:tags":[
        "fertilizer",
        "oil"
    ],
    "wof:name":"Terraco",
    "wof:placetype":"venue"
},
  "geometry": {"coordinates":[-97.32415,49.773743],"type":"Point"}
}