{
  "type": "Feature",
  "properties": {
    "addr:full":"290 Rue Saint-Joseph # A LA Tuque QC G9X 3Z8",
    "addr:housenumber":"290",
    "addr:postcode":"g9x 3z8",
    "addr:street":"Rue Saint-Joseph # A",
    "iso:country":"CA",
    "sg:address":"290 Rue Saint-Joseph # A",
    "sg:city":"LA Tuque",
    "sg:classifiers":[
        {
            "category":"Shopping",
            "subcategory":"Clothing, Apparel, & Fashions",
            "type":"Retail Goods"
        }
    ],
    "sg:phone":"+1 819 523 3333",
    "sg:postcode":"G9X 3Z8",
    "sg:province":"QC",
    "sg:tags":[
        "boutique"
    ],
    "wof:name":"Boutique Marie Soleil",
    "wof:placetype":"venue"
},
  "geometry": {"coordinates":[-72.7857513428,47.4410858154],"type":"Point"}
}