{
  "type": "Feature",
  "properties": {
    "addr:full":"1549 Jane St North York ON M9N 2R3",
    "addr:housenumber":"1549",
    "addr:postcode":"m9n 2r3",
    "addr:street":"Jane St",
    "iso:country":"CA",
    "sg:address":"1549 Jane St",
    "sg:city":"North York",
    "sg:classifiers":[
        {
            "category":"Cinema",
            "subcategory":"Movie Rental",
            "type":"Entertainment"
        }
    ],
    "sg:phone":"+1 416 248 0987",
    "sg:postcode":"M9N 2R3",
    "sg:province":"ON",
    "sg:tags":[
        "leasing",
        "video",
        "disc",
        "tape"
    ],
    "wof:name":"241 Videos & Games Inc",
    "wof:placetype":"venue"
},
  "geometry": {"coordinates":[-79.5024795532,43.69871521],"type":"Point"}
}