{
  "type": "Feature",
  "properties": {
    "addr:full":"Sainte-Foy QC G1X 4X7",
    "addr:postcode":"g1x 4x7",
    "iso:country":"CA",
    "sg:city":"Sainte-Foy",
    "sg:classifiers":[
        {
            "category":"Home & Garden",
            "subcategory":"Building Materials",
            "type":"Retail Goods"
        }
    ],
    "sg:phone":"+1 418 650 7889",
    "sg:postcode":"G1X 4X7",
    "sg:province":"QC",
    "sg:tags":[
        "screen",
        "window"
    ],
    "wof:name":"Moustiquaire Promax Inc",
    "wof:placetype":"venue"
},
  "geometry": {"coordinates":[-71.33034499999999,46.782215],"type":"Point"}
}