{
  "type": "Feature",
  "properties": {
    "addr:full":"202 Boul Brisebois Chateauguay QC J6K 5G7",
    "addr:housenumber":"202",
    "addr:postcode":"j6k 5g7",
    "addr:street":"Boul Brisebois",
    "iso:country":"CA",
    "sg:address":"202 Boul Brisebois",
    "sg:city":"Chateauguay",
    "sg:classifiers":[
        {
            "category":"Social Services",
            "subcategory":"Child Care",
            "type":"Services"
        }
    ],
    "sg:phone":"+1 450 699 2581",
    "sg:postcode":"J6K 5G7",
    "sg:province":"QC",
    "wof:name":"Centre DE LA Petite Enfance",
    "wof:placetype":"venue"
},
  "geometry": {"coordinates":[-73.7654037476,45.3457870483],"type":"Point"}
}