{
  "type": "Feature",
  "properties": {
    "addr:full":"4 Rue DE L'Eveche E Rimouski QC G5L 9C5",
    "addr:housenumber":"4",
    "addr:postcode":"g5l 9c5",
    "addr:street":"Rue De L'Eveche E",
    "iso:country":"CA",
    "sg:address":"4 Rue DE L'Eveche E",
    "sg:city":"Rimouski",
    "sg:classifiers":[
        {
            "category":"Professional",
            "subcategory":"Accounting & Tax Preparation",
            "type":"Services"
        }
    ],
    "sg:phone":"+1 418 722 8340",
    "sg:postcode":"G5L 9C5",
    "sg:province":"QC",
    "sg:tags":[
        "accountant",
        "management"
    ],
    "wof:name":"Theriault, Germain",
    "wof:placetype":"venue"
},
  "geometry": {"coordinates":[-68.52170599999999,48.450268],"type":"Point"}
}