{
  "type": "Feature",
  "properties": {
    "addr:full":"Port Coquitlam BC V3B 6J3",
    "addr:postcode":"v3b 6j3",
    "iso:country":"CA",
    "sg:city":"Port Coquitlam",
    "sg:classifiers":[
        {
            "category":"Professional",
            "subcategory":"Lawyer & Legal Services",
            "type":"Services"
        }
    ],
    "sg:phone":"+1 604 944 4115",
    "sg:postcode":"V3B 6J3",
    "sg:province":"BC",
    "sg:tags":[
        "attorney"
    ],
    "wof:name":"Payne & Assoc",
    "wof:placetype":"venue"
},
  "geometry": {"coordinates":[-122.755486,49.272507],"type":"Point"}
}