{
  "type": "Feature",
  "properties": {
    "addr:full":"Edmonton AB T5P 4P4",
    "addr:postcode":"t5p 4p4",
    "iso:country":"CA",
    "sg:city":"Edmonton",
    "sg:classifiers":[
        {
            "category":"Building & Trades",
            "subcategory":"Construction",
            "type":"Services"
        }
    ],
    "sg:phone":"+1 780 444 1560",
    "sg:postcode":"T5P 4P4",
    "sg:province":"AB",
    "sg:tags":[
        "pipe",
        "sewer",
        "culvert"
    ],
    "wof:name":"Armtec Limited",
    "wof:placetype":"venue"
},
  "geometry": {"coordinates":[-113.612457275,53.5477676392],"type":"Point"}
}