{
  "type": "Feature",
  "properties": {
    "iso:country":"CA",
    "sg:city":"Brandon",
    "sg:classifiers":[
        {
            "category":"Wholesale",
            "subcategory":"Farm Supplies",
            "type":"Manufacturing & Wholesale Goods"
        }
    ],
    "sg:phone":"+1 204 727 5021",
    "sg:postcode":"R7A 6Y9",
    "sg:province":"MB",
    "sg:tags":[
        "feeding",
        "livestock"
    ],
    "wof:name":"Roy Leitch Livestock CO Ltd",
    "wof:placetype":"venue"
},
  "geometry": {"coordinates":[-99.9619522095,49.8476982117],"type":"Point"}
}