{
  "type": "Feature",
  "properties": {
    "addr:full":"281 Durham St Kincardine ON N2Z 2X9",
    "addr:housenumber":"281",
    "addr:postcode":"n2z 2x9",
    "addr:street":"Durham St",
    "iso:country":"CA",
    "sg:address":"281 Durham St",
    "sg:city":"Kincardine",
    "sg:classifiers":[
        {
            "category":"Health Services",
            "subcategory":"Chiropractor",
            "type":"Services"
        }
    ],
    "sg:phone":"+1 519 396 6360",
    "sg:postcode":"N2Z 2X9",
    "sg:province":"ON",
    "wof:name":"Soloduka, Stanley DC",
    "wof:placetype":"venue"
},
  "geometry": {"coordinates":[-81.6344985962,44.1792869568],"type":"Point"}
}