{
  "type": "Feature",
  "properties": {
    "iso:country":"CA",
    "sg:city":"Pincher Creek",
    "sg:classifiers":[
        {
            "category":"Mining & Drilling",
            "type":"Manufacturing & Wholesale Goods"
        }
    ],
    "sg:phone":"+1 403 266 4744",
    "sg:postcode":"T0K 1W0",
    "sg:province":"AB",
    "sg:tags":[
        "field",
        "oil"
    ],
    "wof:name":"Chinook Pipe Lines",
    "wof:placetype":"venue"
},
  "geometry": {"coordinates":[-113.95009613000001,49.4856681824],"type":"Point"}
}