{
  "type": "Feature",
  "properties": {
    "addr:full":"60 Grand Marshall Dr Scarborough ON M1B 5N6",
    "addr:housenumber":"60",
    "addr:postcode":"m1b 5n6",
    "addr:street":"Grand Marshall Dr",
    "iso:country":"CA",
    "sg:address":"60 Grand Marshall Dr",
    "sg:city":"Scarborough",
    "sg:classifiers":[
        {
            "category":"Restaurant",
            "type":"Food & Drink"
        }
    ],
    "sg:phone":"+1 416 208 9136",
    "sg:postcode":"M1B 5N6",
    "sg:province":"ON",
    "wof:name":"Harvey's",
    "wof:placetype":"venue"
},
  "geometry": {"coordinates":[-79.194756,43.801498],"type":"Point"}
}