{
  "type": "Feature",
  "properties": {
    "addr:full":"709 Russell St Kincardine ON N2Z 1R1",
    "addr:housenumber":"709",
    "addr:postcode":"n2z 1r1",
    "addr:street":"Russell St",
    "iso:country":"CA",
    "sg:address":"709 Russell St",
    "sg:city":"Kincardine",
    "sg:classifiers":[
        {
            "category":"Education",
            "subcategory":"School",
            "type":"Public Place"
        }
    ],
    "sg:phone":"+1 519 396 4330",
    "sg:postcode":"N2Z 1R1",
    "sg:province":"ON",
    "wof:name":"St Anthony's School",
    "wof:placetype":"venue"
},
  "geometry": {"coordinates":[-81.622856,44.169716],"type":"Point"}
}