{
  "type": "Feature",
  "properties": {
    "iso:country":"CA",
    "sg:address":"605 Denison St",
    "sg:city":"Markham",
    "sg:classifiers":[
        {
            "category":"Professional",
            "subcategory":"Business Services",
            "type":"Services"
        }
    ],
    "sg:phone":"+1 905 944 9465",
    "sg:postcode":"L3R 1B8",
    "sg:province":"ON",
    "sg:tags":[
        "water",
        "treatment"
    ],
    "wof:name":"Water Quality Control Systems",
    "wof:placetype":"venue"
},
  "geometry": {"coordinates":[-79.341003,43.823971],"type":"Point"}
}