{
  "type": "Feature",
  "properties": {
    "addr:full":"95 East Beaver Creek Rd Richmond Hill ON L4B 1L4",
    "addr:housenumber":"95",
    "addr:postcode":"l4b 1l4",
    "addr:street":"East Beaver Creek Rd",
    "iso:country":"CA",
    "sg:address":"95 East Beaver Creek Rd",
    "sg:city":"Richmond Hill",
    "sg:classifiers":[
        {
            "category":"Shopping",
            "subcategory":"Clothing, Apparel, & Fashions",
            "type":"Retail Goods"
        }
    ],
    "sg:phone":"+1 905 707 8727",
    "sg:postcode":"L4B 1L4",
    "sg:province":"ON",
    "wof:name":"Firme",
    "wof:placetype":"venue"
},
  "geometry": {"coordinates":[-79.3785858154,43.8545875549],"type":"Point"}
}