{
  "type": "Feature",
  "properties": {
    "addr:full":"4625 Carl St Hanmer ON P3P 1X5",
    "addr:housenumber":"4625",
    "addr:postcode":"p3p 1x5",
    "addr:street":"Carl St",
    "iso:country":"CA",
    "sg:address":"4625 Carl St",
    "sg:city":"Hanmer",
    "sg:classifiers":[
        {
            "category":"Education",
            "subcategory":"School",
            "type":"Public Place"
        }
    ],
    "sg:phone":"+1 705 969 4435",
    "sg:postcode":"P3P 1X5",
    "sg:province":"ON",
    "wof:name":"Redwood Acres Public School",
    "wof:placetype":"venue"
},
  "geometry": {"coordinates":[-80.938599,46.654209],"type":"Point"}
}