{
  "type": "Feature",
  "properties": {
    "addr:full":"Pinawa MB R0E 1L0",
    "addr:postcode":"r0e 1l0",
    "iso:country":"CA",
    "sg:city":"Pinawa",
    "sg:classifiers":[
        {
            "category":"Retail",
            "subcategory":"Auto Repair",
            "type":"Services"
        }
    ],
    "sg:phone":"+1 204 753 8310",
    "sg:postcode":"R0E 1L0",
    "sg:province":"MB",
    "sg:tags":[
        "repairing",
        "automobile"
    ],
    "wof:name":"Pine Pro Automotive Ltd",
    "wof:placetype":"venue"
},
  "geometry": {"coordinates":[-95.880745,50.150822],"type":"Point"}
}