{
  "type": "Feature",
  "properties": {
    "addr:full":"699 Coxwell Ave Toronto ON M4C 3C1",
    "addr:housenumber":"699",
    "addr:postcode":"m4c 3c1",
    "addr:street":"Coxwell Ave",
    "iso:country":"CA",
    "sg:address":"699 Coxwell Ave",
    "sg:city":"Toronto",
    "sg:classifiers":[
        {
            "category":"Social Services",
            "type":"Services"
        }
    ],
    "sg:phone":"+1 416 463 1104",
    "sg:postcode":"M4C 3C1",
    "sg:province":"ON",
    "sg:tags":[
        "organization",
        "welfare"
    ],
    "wof:name":"Silent Voice Canada",
    "wof:placetype":"venue"
},
  "geometry": {"coordinates":[-79.32349395750001,43.6835517883],"type":"Point"}
}