{
  "type": "Feature",
  "properties": {
    "iso:country":"CA",
    "sg:address":"502 1st St E",
    "sg:city":"Saskatoon",
    "sg:classifiers":[
        {
            "category":"Retail",
            "subcategory":"Repair Shop",
            "type":"Services"
        }
    ],
    "sg:phone":"+1 306 653 2099",
    "sg:postcode":"S7H 1S6",
    "sg:province":"SK",
    "sg:tags":[
        "lock",
        "locksmith"
    ],
    "wof:name":"Precision Lock & Security",
    "wof:placetype":"venue"
},
  "geometry": {"coordinates":[-106.659157,52.108147],"type":"Point"}
}