{
  "type": "Feature",
  "properties": {
    "addr:full":"3997 Rue Overdale Rawdon QC J0K 1S0",
    "addr:housenumber":"3997",
    "addr:postcode":"j0k 1s0",
    "addr:street":"Rue Overdale",
    "iso:country":"CA",
    "sg:address":"3997 Rue Overdale",
    "sg:city":"Rawdon",
    "sg:classifiers":[
        {
            "category":"Building & Trades",
            "subcategory":"Plumbing",
            "type":"Services"
        }
    ],
    "sg:phone":"+1 450 834 3611",
    "sg:postcode":"J0K 1S0",
    "sg:province":"QC",
    "sg:tags":[
        "excavating",
        "tank",
        "septic",
        "contractor"
    ],
    "wof:name":"Excavation Glenn Stewart Enrg",
    "wof:placetype":"venue"
},
  "geometry": {"coordinates":[-73.75071,46.058968],"type":"Point"}
}