{
  "type": "Feature",
  "properties": {
    "addr:full":"Leaskdale ON L0C 1C0",
    "addr:postcode":"l0c 1c0",
    "iso:country":"CA",
    "sg:city":"Leaskdale",
    "sg:classifiers":[
        {
            "category":"Insurance",
            "subcategory":"Insurance Agent",
            "type":"Services"
        }
    ],
    "sg:phone":"+1 905 852 5691",
    "sg:postcode":"L0C 1C0",
    "sg:province":"ON",
    "wof:name":"D G Smith Insurance Broker Ltd",
    "wof:placetype":"venue"
},
  "geometry": {"coordinates":[-79.161041,44.203796],"type":"Point"}
}