{
  "type": "Feature",
  "properties": {
    "addr:full":"338 James St Pembroke ON K8A 4V2",
    "addr:housenumber":"338",
    "addr:postcode":"k8a 4v2",
    "addr:street":"James St",
    "iso:country":"CA",
    "sg:address":"338 James St",
    "sg:city":"Pembroke",
    "sg:classifiers":[
        {
            "category":"Retail",
            "subcategory":"Laundry & Dry Cleaning",
            "type":"Services"
        }
    ],
    "sg:phone":"+1 613 735 3276",
    "sg:postcode":"K8A 4V2",
    "sg:province":"ON",
    "sg:tags":[
        "cleaners",
        "rug",
        "carpet"
    ],
    "wof:name":"Abba Cleaning Svc",
    "wof:placetype":"venue"
},
  "geometry": {"coordinates":[-77.1265869141,45.8218040466],"type":"Point"}
}