{
  "type": "Feature",
  "properties": {
    "iso:country":"CA",
    "sg:address":"21 Amber St # 6",
    "sg:city":"Markham",
    "sg:classifiers":[
        {
            "category":"Professional",
            "subcategory":"Accounting & Tax Preparation",
            "type":"Services"
        }
    ],
    "sg:phone":"+1 905 474 3100",
    "sg:postcode":"L3R 4Z3",
    "sg:province":"ON",
    "sg:tags":[
        "accountant",
        "bookkeeping",
        "general"
    ],
    "wof:name":"R G Bookkeeping Svc",
    "wof:placetype":"venue"
},
  "geometry": {"coordinates":[-79.329849,43.828403],"type":"Point"}
}