{
  "type": "Feature",
  "properties": {
    "addr:full":"701 Broadway Ave N Melfort SK S0E 1A0",
    "addr:housenumber":"701",
    "addr:postcode":"s0e 1a0",
    "addr:street":"Broadway Ave N Melfort",
    "iso:country":"CA",
    "sg:address":"701 Broadway Ave N",
    "sg:city":"Melfort",
    "sg:classifiers":[
        {
            "category":"Wholesale",
            "subcategory":"Farm Supplies",
            "type":"Manufacturing & Wholesale Goods"
        }
    ],
    "sg:phone":"+1 306 752 2894",
    "sg:postcode":"S0E 1A0",
    "sg:province":"SK",
    "sg:tags":[
        "feed"
    ],
    "wof:name":"CO-OP Feeds",
    "wof:placetype":"venue"
},
  "geometry": {"coordinates":[-104.615982,52.86755],"type":"Point"}
}