{
  "type": "Feature",
  "properties": {
    "addr:full":"1490 Rue Sauve E Montreal QC H2C 2A5",
    "addr:housenumber":"1490",
    "addr:postcode":"h2c 2a5",
    "addr:street":"Rue Sauve E",
    "iso:country":"CA",
    "sg:address":"1490 Rue Sauve E",
    "sg:city":"Montreal",
    "sg:classifiers":[
        {
            "category":"Building & Trades",
            "subcategory":"Construction",
            "type":"Services"
        }
    ],
    "sg:phone":"+1 514 385 0875",
    "sg:postcode":"H2C 2A5",
    "sg:province":"QC",
    "sg:tags":[
        "insulation",
        "heat",
        "contractor"
    ],
    "wof:name":"Continental Isolation Inc",
    "wof:placetype":"venue"
},
  "geometry": {"coordinates":[-73.65032958979999,45.5605125427],"type":"Point"}
}