{
  "type": "Feature",
  "properties": {
    "addr:full":"73 Rue Saint-Antoine S Granby QC J2G 9K8",
    "addr:housenumber":"73",
    "addr:postcode":"j2g 9k8",
    "addr:street":"Rue Saint-Antoine S Granby",
    "iso:country":"CA",
    "sg:address":"73 Rue Saint-Antoine S",
    "sg:city":"Granby",
    "sg:classifiers":[
        {
            "category":"Manufacturing",
            "subcategory":"Chemicals & Compounds",
            "type":"Manufacturing & Wholesale Goods"
        }
    ],
    "sg:phone":"+1 450 777 0912",
    "sg:postcode":"J2G 9K8",
    "sg:province":"QC",
    "sg:tags":[
        "recycling",
        "center",
        "lithographing"
    ],
    "wof:name":"Recycnet",
    "wof:placetype":"venue"
},
  "geometry": {"coordinates":[-72.731651,45.398605],"type":"Point"}
}