{
  "type": "Feature",
  "properties": {
    "iso:country":"CA",
    "sg:address":"368 Kribs St",
    "sg:city":"Cambridge",
    "sg:classifiers":[
        {
            "category":"Building & Trades",
            "subcategory":"Cleaning & Sanitation",
            "type":"Services"
        }
    ],
    "sg:phone":"+1 519 658 5485",
    "sg:postcode":"N3C 3L6",
    "sg:province":"ON",
    "sg:tags":[
        "fireplace",
        "chimney"
    ],
    "wof:name":"Chimko Chimney Cleaning",
    "wof:placetype":"venue"
},
  "geometry": {"coordinates":[-80.298828125,43.4229812622],"type":"Point"}
}