{
  "type": "Feature",
  "properties": {
    "iso:country":"CA",
    "sg:address":"10 Rue DE L'Eveche E",
    "sg:city":"Rimouski",
    "sg:classifiers":[
        {
            "category":"Shopping",
            "type":"Retail Goods"
        }
    ],
    "sg:phone":"+1 418 722 4035",
    "sg:postcode":"G5L 1X4",
    "sg:province":"QC",
    "sg:tags":[
        "art",
        "gallery",
        "dealer"
    ],
    "wof:name":"Vu En Pointilles",
    "wof:placetype":"venue"
},
  "geometry": {"coordinates":[-68.5217056274,48.4502677917],"type":"Point"}
}