{
  "type": "Feature",
  "properties": {
    "addr:full":"Brockville ON K6V 2T3",
    "addr:postcode":"k6v 2t3",
    "iso:country":"CA",
    "sg:city":"Brockville",
    "sg:classifiers":[
        {
            "category":"Professional",
            "subcategory":"Management & Consulting",
            "type":"Services"
        }
    ],
    "sg:phone":"+1 613 345 1502",
    "sg:postcode":"K6V 2T3",
    "sg:province":"ON",
    "sg:tags":[
        "instrumentation",
        "indicating"
    ],
    "wof:name":"Isi Controls Inc",
    "wof:placetype":"venue"
},
  "geometry": {"coordinates":[-75.6849746704,44.6049537659],"type":"Point"}
}