{
  "type": "Feature",
  "properties": {
    "addr:full":"North York ON M6A 3A1",
    "addr:postcode":"m6a 3a1",
    "iso:country":"CA",
    "sg:city":"North York",
    "sg:classifiers":[
        {
            "category":"Professional",
            "subcategory":"Lawyer & Legal Services",
            "type":"Services"
        }
    ],
    "sg:phone":"+1 416 256 1555",
    "sg:postcode":"M6A 3A1",
    "sg:province":"ON",
    "sg:tags":[
        "attorney"
    ],
    "wof:name":"Graham & Tobe",
    "wof:placetype":"venue"
},
  "geometry": {"coordinates":[-79.453407,43.728207],"type":"Point"}
}