{
  "type": "Feature",
  "properties": {
    "iso:country":"CA",
    "sg:city":"Williams Lake",
    "sg:classifiers":[
        {
            "category":"Manufacturing",
            "subcategory":"Lumber",
            "type":"Manufacturing & Wholesale Goods"
        }
    ],
    "sg:phone":"+1 250 392 2001",
    "sg:postcode":"V2G 2V4",
    "sg:province":"BC",
    "sg:tags":[
        "company",
        "logging"
    ],
    "wof:name":"Clusko Logging Enterprises",
    "wof:placetype":"venue"
},
  "geometry": {"coordinates":[-122.141082764,52.1286506653],"type":"Point"}
}