{
  "type": "Feature",
  "properties": {
    "addr:full":"545 Boul Sir-Wilfrid-Laurier # 204 Beloeil QC J3G 4H8",
    "addr:housenumber":"545",
    "addr:postcode":"j3g 4h8",
    "addr:street":"Boul Sir-Wilfrid-Laurier # 204",
    "iso:country":"CA",
    "sg:address":"545 Boul Sir-Wilfrid-Laurier # 204",
    "sg:city":"Beloeil",
    "sg:classifiers":[
        {
            "category":"Health Services",
            "subcategory":"Health Practitioner",
            "type":"Services"
        }
    ],
    "sg:phone":"+1 450 464 9137",
    "sg:postcode":"J3G 4H8",
    "sg:province":"QC",
    "sg:tags":[
        "psychologist"
    ],
    "wof:name":"Darsigny, Noella",
    "wof:placetype":"venue"
},
  "geometry": {"coordinates":[-73.2073059082,45.5611839294],"type":"Point"}
}