{
  "type": "Feature",
  "properties": {
    "addr:full":"Calgary AB T2P 1Z2",
    "addr:postcode":"t2p 1z2",
    "iso:country":"CA",
    "sg:city":"Calgary",
    "sg:classifiers":[
        {
            "category":"Health Services",
            "subcategory":"Health Practitioner",
            "type":"Services"
        }
    ],
    "sg:phone":"+1 403 262 1606",
    "sg:postcode":"T2P 1Z2",
    "sg:province":"AB",
    "sg:tags":[
        "psychologist"
    ],
    "wof:name":"Luna, Sandra",
    "wof:placetype":"venue"
},
  "geometry": {"coordinates":[-114.07847599999999,51.04771],"type":"Point"}
}