{
  "type": "Feature",
  "properties": {
    "addr:full":"General Delivery Curve Lake ON K0L 1R0",
    "addr:postcode":"k0l 1r0",
    "iso:country":"CA",
    "sg:address":"General Delivery",
    "sg:city":"Curve Lake",
    "sg:classifiers":[
        {
            "category":"Recreation",
            "type":"Entertainment"
        }
    ],
    "sg:phone":"+1 705 657 3432",
    "sg:postcode":"K0L 1R0",
    "sg:province":"ON",
    "sg:tags":[
        "center"
    ],
    "wof:name":"Curve Lake Community Ctr",
    "wof:placetype":"venue"
},
  "geometry": {"coordinates":[-78.375671,44.458828],"type":"Point"}
}