{
  "type": "Feature",
  "properties": {
    "addr:full":"Rossland BC V0G 1Y0",
    "addr:postcode":"v0g 1y0",
    "iso:country":"CA",
    "sg:city":"Rossland",
    "sg:classifiers":[
        {
            "category":"Health Services",
            "subcategory":"Clinic",
            "type":"Services"
        }
    ],
    "sg:phone":"+1 250 362 7238",
    "sg:postcode":"V0G 1Y0",
    "sg:province":"BC",
    "sg:tags":[
        "therapist",
        "massage"
    ],
    "wof:name":"Essential Body Massage Therapy",
    "wof:placetype":"venue"
},
  "geometry": {"coordinates":[-117.798095703,49.0770111084],"type":"Point"}
}