{
  "type": "Feature",
  "properties": {
    "addr:full":"Delaware ON N0L 1E0",
    "addr:postcode":"n0l 1e0",
    "iso:country":"CA",
    "sg:city":"Delaware",
    "sg:classifiers":[
        {
            "category":"Shopping",
            "type":"Retail Goods"
        }
    ],
    "sg:phone":"+1 519 652 6956",
    "sg:postcode":"N0L 1E0",
    "sg:province":"ON",
    "sg:tags":[
        "art",
        "gallery",
        "dealer"
    ],
    "wof:name":"Radoff Studios",
    "wof:placetype":"venue"
},
  "geometry": {"coordinates":[-81.4204864502,42.9076843262],"type":"Point"}
}