{
  "type": "Feature",
  "properties": {
    "iso:country":"CA",
    "sg:address":"24 1E Av E # A",
    "sg:city":"Mont-Louis",
    "sg:classifiers":[
        {
            "category":"Travel",
            "subcategory":"Hotels & Motels",
            "type":"Entertainment"
        }
    ],
    "sg:phone":"+1 418 797 5000",
    "sg:postcode":"G0E 1T0",
    "sg:province":"QC",
    "wof:name":"Auberge Des Belles Soeurs",
    "wof:placetype":"venue"
},
  "geometry": {"coordinates":[-65.72611999510001,49.2300415039],"type":"Point"}
}