{
  "type": "Feature",
  "properties": {
    "addr:full":"Nisku AB T9E 7M9",
    "addr:postcode":"t9e 7m9",
    "iso:country":"CA",
    "sg:city":"Nisku",
    "sg:classifiers":[
        {
            "category":"Mining & Drilling",
            "type":"Manufacturing & Wholesale Goods"
        }
    ],
    "sg:phone":"+1 780 955 7788",
    "sg:postcode":"T9E 7M9",
    "sg:province":"AB",
    "sg:tags":[
        "pipe",
        "inspection"
    ],
    "wof:name":"Bison Energy Svc",
    "wof:placetype":"venue"
},
  "geometry": {"coordinates":[-113.532967,53.311241],"type":"Point"}
}