{
  "type": "Feature",
  "properties": {
    "addr:full":"415 Lake Dr S Keswick ON L4P 1P3",
    "addr:housenumber":"415",
    "addr:postcode":"l4p 1p3",
    "addr:street":"Lake Dr S",
    "iso:country":"CA",
    "sg:address":"415 Lake Dr S",
    "sg:city":"Keswick",
    "sg:classifiers":[
        {
            "category":"Building & Trades",
            "subcategory":"Construction",
            "type":"Services"
        }
    ],
    "sg:phone":"+1 905 989 2633",
    "sg:postcode":"L4P 1P3",
    "sg:province":"ON",
    "sg:tags":[
        "contractor"
    ],
    "wof:name":"First Rate Roofing",
    "wof:placetype":"venue"
},
  "geometry": {"coordinates":[-79.4722366333,44.2143173218],"type":"Point"}
}