{
  "type": "Feature",
  "properties": {
    "addr:full":"Timmins ON P4N 8A1",
    "addr:postcode":"p4n 8a1",
    "iso:country":"CA",
    "sg:city":"Timmins",
    "sg:classifiers":[
        {
            "category":"Mining & Drilling",
            "type":"Manufacturing & Wholesale Goods"
        }
    ],
    "sg:phone":"+1 705 267 3412",
    "sg:postcode":"P4N 8A1",
    "sg:province":"ON",
    "sg:tags":[
        "company",
        "mine"
    ],
    "wof:name":"Hussey Geophysics Inc",
    "wof:placetype":"venue"
},
  "geometry": {"coordinates":[-81.335396,48.490578],"type":"Point"}
}