{
  "type": "Feature",
  "properties": {
    "addr:full":"11507 160 St NW Edmonton AB T5M 3V9",
    "addr:housenumber":"11507",
    "addr:postcode":"t5m 3v9",
    "addr:street":"160 St Nw",
    "iso:country":"CA",
    "sg:address":"11507 160 St NW",
    "sg:city":"Edmonton",
    "sg:classifiers":[
        {
            "category":"Professional",
            "subcategory":"Engineering",
            "type":"Services"
        }
    ],
    "sg:phone":"+1 780 482 6263",
    "sg:postcode":"T5M 3V9",
    "sg:province":"AB",
    "sg:tags":[
        "fire",
        "consultant",
        "protection",
        "engineer"
    ],
    "wof:name":"Aps Engineering",
    "wof:placetype":"venue"
},
  "geometry": {"coordinates":[-113.597008,53.564873],"type":"Point"}
}