{
  "type": "Feature",
  "properties": {
    "addr:full":"RR 6 STN Main Saskatoon SK S7K 3J9",
    "addr:postcode":"s7k 3j9",
    "addr:street":"Rr 6 Stn",
    "iso:country":"CA",
    "sg:address":"RR 6 STN Main",
    "sg:city":"Saskatoon",
    "sg:classifiers":[
        {
            "category":"Freight",
            "type":"Transportation"
        }
    ],
    "sg:phone":"+1 306 249 3524",
    "sg:postcode":"S7K 3J9",
    "sg:province":"SK",
    "sg:tags":[
        "trucking"
    ],
    "wof:name":"U-Win Svc",
    "wof:placetype":"venue"
},
  "geometry": {"coordinates":[-106.65931701700001,52.1305046082],"type":"Point"}
}