{
  "type": "Feature",
  "properties": {
    "addr:full":"47 William St Ottawa ON K1N 6Z9",
    "addr:housenumber":"47",
    "addr:postcode":"k1n 6z9",
    "addr:street":"William St",
    "iso:country":"CA",
    "sg:address":"47 William St",
    "sg:city":"Ottawa",
    "sg:classifiers":[
        {
            "category":"Restaurant",
            "type":"Food & Drink"
        }
    ],
    "sg:phone":"+1 613 241 6314",
    "sg:postcode":"K1N 6Z9",
    "sg:province":"ON",
    "wof:name":"Mtl & CO",
    "wof:placetype":"venue"
},
  "geometry": {"coordinates":[-75.691986,45.42778],"type":"Point"}
}