{
  "type": "Feature",
  "properties": {
    "addr:full":"Nipawin SK S0E 1E0",
    "addr:postcode":"s0e 1e0",
    "iso:country":"CA",
    "sg:city":"Nipawin",
    "sg:classifiers":[
        {
            "category":"Personal",
            "subcategory":"Beauty Salon",
            "type":"Services"
        }
    ],
    "sg:phone":"+1 306 862 9466",
    "sg:postcode":"S0E 1E0",
    "sg:province":"SK",
    "wof:name":"Joell's Hair Design",
    "wof:placetype":"venue"
},
  "geometry": {"coordinates":[-104.018226623,53.3617210388],"type":"Point"}
}