{
  "type": "Feature",
  "properties": {
    "addr:full":"1232 Kingston Rd Scarborough ON M1N 1P3",
    "addr:housenumber":"1232",
    "addr:postcode":"m1n 1p3",
    "addr:street":"Kingston Rd",
    "iso:country":"CA",
    "sg:address":"1232 Kingston Rd",
    "sg:city":"Scarborough",
    "sg:classifiers":[
        {
            "category":"Building & Trades",
            "subcategory":"Electrical",
            "type":"Services"
        }
    ],
    "sg:phone":"+1 416 686 6577",
    "sg:postcode":"M1N 1P3",
    "sg:province":"ON",
    "sg:tags":[
        "equipment",
        "telecommunication"
    ],
    "wof:name":"Ditech Communications Corp",
    "wof:placetype":"venue"
},
  "geometry": {"coordinates":[-79.2783660889,43.682849884],"type":"Point"}
}