{
  "type": "Feature",
  "properties": {
    "addr:full":"Loreburn SK S0H 2S0",
    "addr:postcode":"s0h 2s0",
    "iso:country":"CA",
    "sg:city":"Loreburn",
    "sg:classifiers":[
        {
            "category":"Wholesale",
            "subcategory":"Petroleum",
            "type":"Manufacturing & Wholesale Goods"
        }
    ],
    "sg:phone":"+1 306 644 4987",
    "sg:postcode":"S0H 2S0",
    "sg:province":"SK",
    "sg:tags":[
        "pipe",
        "line",
        "company"
    ],
    "wof:name":"Alliance Pipeline Ltd",
    "wof:placetype":"venue"
},
  "geometry": {"coordinates":[-106.585968018,51.2286605835],"type":"Point"}
}