{
  "type": "Feature",
  "properties": {
    "addr:full":"6415 Fraser St Vancouver BC V5W 3A6",
    "addr:housenumber":"6415",
    "addr:postcode":"v5w 3a6",
    "addr:street":"Fraser St",
    "iso:country":"CA",
    "sg:address":"6415 Fraser St",
    "sg:city":"Vancouver",
    "sg:classifiers":[
        {
            "category":"Education",
            "subcategory":"Special Training",
            "type":"Public Place"
        }
    ],
    "sg:phone":"+1 604 322 5777",
    "sg:postcode":"V5W 3A6",
    "sg:province":"BC",
    "sg:tags":[
        "instruction",
        "driving"
    ],
    "wof:name":"All Season Driving School",
    "wof:placetype":"venue"
},
  "geometry": {"coordinates":[-123.090897,49.226353],"type":"Point"}
}