{
  "type": "Feature",
  "properties": {
    "addr:full":"21621 Lougheed Hwy Maple Ridge BC V2X 2S2",
    "addr:housenumber":"21621",
    "addr:postcode":"v2x 2s2",
    "addr:street":"Lougheed Hwy",
    "iso:country":"CA",
    "sg:address":"21621 Lougheed Hwy",
    "sg:city":"Maple Ridge",
    "sg:classifiers":[
        {
            "category":"Cinema",
            "subcategory":"Movie Rental",
            "type":"Entertainment"
        }
    ],
    "sg:phone":"+1 604 463 2993",
    "sg:postcode":"V2X 2S2",
    "sg:province":"BC",
    "sg:tags":[
        "leasing",
        "video",
        "disc",
        "tape"
    ],
    "wof:name":"Blockbuster Video",
    "wof:placetype":"venue"
},
  "geometry": {"coordinates":[-122.621933,49.217136],"type":"Point"}
}