{
  "type": "Feature",
  "properties": {
    "iso:country":"CA",
    "sg:city":"Montreal",
    "sg:classifiers":[
        {
            "category":"Museum",
            "type":"Entertainment"
        }
    ],
    "sg:phone":"+1 514 259 9201",
    "sg:postcode":"H1W 3W2",
    "sg:province":"QC",
    "wof:name":"Chateau Dufresne",
    "wof:placetype":"venue"
},
  "geometry": {"coordinates":[-73.553391,45.553429],"type":"Point"}
}