{
  "type": "Feature",
  "properties": {
    "addr:full":"4170 Rue Bonaventure Sherbrooke QC J1L 1Y6",
    "addr:housenumber":"4170",
    "addr:postcode":"j1l 1y6",
    "addr:street":"Rue Bonaventure",
    "iso:country":"CA",
    "sg:address":"4170 Rue Bonaventure",
    "sg:city":"Sherbrooke",
    "sg:classifiers":[
        {
            "category":"Professional",
            "subcategory":"Business Services",
            "type":"Services"
        }
    ],
    "sg:phone":"+1 819 821 2454",
    "sg:postcode":"J1L 1Y6",
    "sg:province":"QC",
    "sg:tags":[
        "repossessing",
        "appraiser"
    ],
    "wof:name":"Savary Paul & Assoc",
    "wof:placetype":"venue"
},
  "geometry": {"coordinates":[-71.96283,45.386936],"type":"Point"}
}