{
  "type": "Feature",
  "properties": {
    "addr:full":"45 Sylvan Way Winnipeg MB R2R 2B9",
    "addr:housenumber":"45",
    "addr:postcode":"r2r 2b9",
    "addr:street":"Sylvan Way",
    "iso:country":"CA",
    "sg:address":"45 Sylvan Way",
    "sg:city":"Winnipeg",
    "sg:classifiers":[
        {
            "category":"Manufacturing",
            "subcategory":"Tools & Machinery",
            "type":"Manufacturing & Wholesale Goods"
        }
    ],
    "sg:phone":"+1 204 697 2951",
    "sg:postcode":"R2R 2B9",
    "sg:province":"MB",
    "sg:tags":[
        "die",
        "maker"
    ],
    "wof:name":"K & S Tool & Die Ltd",
    "wof:placetype":"venue"
},
  "geometry": {"coordinates":[-97.224442,49.928017],"type":"Point"}
}