{
  "type": "Feature",
  "properties": {
    "addr:full":"3440 Bloomfield Rd Windsor ON N9C 1R5",
    "addr:housenumber":"3440",
    "addr:postcode":"n9c 1r5",
    "addr:street":"Bloomfield Rd",
    "iso:country":"CA",
    "sg:address":"3440 Bloomfield Rd",
    "sg:city":"Windsor",
    "sg:classifiers":[
        {
            "category":"Organizations",
            "subcategory":"Membership Organization",
            "type":"Services"
        }
    ],
    "sg:phone":"+1 519 977 7888",
    "sg:postcode":"N9C 1R5",
    "sg:province":"ON",
    "wof:name":"Windsor West Citizen's Orgnztn",
    "wof:placetype":"venue"
},
  "geometry": {"coordinates":[-83.07424899999999,42.294991],"type":"Point"}
}