{
  "type": "Feature",
  "properties": {
    "iso:country":"CA",
    "sg:city":"Burlington",
    "sg:classifiers":[
        {
            "category":"Building & Trades",
            "subcategory":"Cleaning & Sanitation",
            "type":"Services"
        }
    ],
    "sg:phone":"+1 905 631 6333",
    "sg:postcode":"L7L 5Y6",
    "sg:province":"ON",
    "sg:tags":[
        "tile",
        "maintenance"
    ],
    "wof:name":"Alternative Restoration Svc",
    "wof:placetype":"venue"
},
  "geometry": {"coordinates":[-79.776222,43.375465],"type":"Point"}
}