{
  "type": "Feature",
  "properties": {
    "addr:full":"180 Cote Blais Mont-Carmel QC G0L 1W0",
    "addr:housenumber":"180",
    "addr:postcode":"g0l 1w0",
    "addr:street":"Cote Blais",
    "iso:country":"CA",
    "sg:address":"180 Cote Blais",
    "sg:city":"Mont-Carmel",
    "sg:classifiers":[
        {
            "category":"Health Services",
            "subcategory":"Nursing And Care Facility",
            "type":"Services"
        }
    ],
    "sg:phone":"+1 418 498 3339",
    "sg:postcode":"G0L 1W0",
    "sg:province":"QC",
    "sg:tags":[
        "home",
        "retirement",
        "community"
    ],
    "wof:name":"Residence Pierrette Ouellet",
    "wof:placetype":"venue"
},
  "geometry": {"coordinates":[-69.859016,47.444386],"type":"Point"}
}