{
  "type": "Feature",
  "properties": {
    "addr:full":"5716 Ch Saint-Francois Saint-Laurent QC H4S 1B4",
    "addr:housenumber":"5716",
    "addr:postcode":"h4s 1b4",
    "addr:street":"Ch Saint-Francois",
    "iso:country":"CA",
    "sg:address":"5716 Ch Saint-Francois",
    "sg:city":"Saint-Laurent",
    "sg:classifiers":[
        {
            "category":"Wholesale",
            "subcategory":"Machinery & Supplies",
            "type":"Manufacturing & Wholesale Goods"
        }
    ],
    "sg:phone":"+1 514 956 1525",
    "sg:postcode":"H4S 1B4",
    "sg:province":"QC",
    "sg:tags":[
        "packaging"
    ],
    "wof:name":"Can am Packaging Systems Ltd",
    "wof:placetype":"venue"
},
  "geometry": {"coordinates":[-73.737709,45.487286],"type":"Point"}
}