{
  "type": "Feature",
  "properties": {
    "addr:full":"177 8th St E Owen Sound ON N4K 1K9",
    "addr:housenumber":"177",
    "addr:postcode":"n4k 1k9",
    "addr:street":"8Th St E",
    "iso:country":"CA",
    "sg:address":"177 8th St E",
    "sg:city":"Owen Sound",
    "sg:classifiers":[
        {
            "category":"Travel",
            "subcategory":"Travel Agent",
            "type":"Entertainment"
        }
    ],
    "sg:phone":"+1 519 371 0310",
    "sg:postcode":"N4K 1K9",
    "sg:province":"ON",
    "sg:tags":[
        "agency",
        "bureau"
    ],
    "wof:name":"Advantage Hanover Travel Svc",
    "wof:placetype":"venue"
},
  "geometry": {"coordinates":[-80.94274900000001,44.563732],"type":"Point"}
}