{
  "type": "Feature",
  "properties": {
    "addr:full":"188 Main St Antigonish NS B2G 2B9",
    "addr:housenumber":"188",
    "addr:postcode":"b2g 2b9",
    "addr:street":"Main St",
    "iso:country":"CA",
    "sg:address":"188 Main St",
    "sg:city":"Antigonish",
    "sg:classifiers":[
        {
            "category":"Organizations",
            "subcategory":"Non-profit Organization",
            "type":"Services"
        }
    ],
    "sg:phone":"+1 902 863 5062",
    "sg:postcode":"B2G 2B9",
    "sg:province":"NS",
    "sg:tags":[
        "charitable",
        "institution"
    ],
    "wof:name":"Canadian Cancer Society",
    "wof:placetype":"venue"
},
  "geometry": {"coordinates":[-61.9884033203,45.6229858398],"type":"Point"}
}