{
  "type": "Feature",
  "properties": {
    "addr:full":"8272 Rue Pascal-Gagnon Saint-Leonard QC H1P 1Y4",
    "addr:housenumber":"8272",
    "addr:postcode":"h1p 1y4",
    "addr:street":"Rue Pascal-Gagnon",
    "iso:country":"CA",
    "sg:address":"8272 Rue Pascal-Gagnon",
    "sg:city":"Saint-Leonard",
    "sg:classifiers":[
        {
            "category":"Wholesale",
            "subcategory":"Groceries",
            "type":"Manufacturing & Wholesale Goods"
        }
    ],
    "sg:phone":"+1 514 326 9890",
    "sg:postcode":"H1P 1Y4",
    "sg:province":"QC",
    "sg:tags":[
        "grocer"
    ],
    "wof:name":"Hershey Canada Inc",
    "wof:placetype":"venue"
},
  "geometry": {"coordinates":[-73.582375,45.599785],"type":"Point"}
}