{
  "type": "Feature",
  "properties": {
    "addr:full":"10815 76 Ave NW Edmonton AB T6E 1M1",
    "addr:housenumber":"10815",
    "addr:postcode":"t6e 1m1",
    "addr:street":"76 Ave Nw",
    "iso:country":"CA",
    "sg:address":"10815 76 Ave NW",
    "sg:city":"Edmonton",
    "sg:classifiers":[
        {
            "category":"Organizations",
            "subcategory":"Religious Organization",
            "type":"Services"
        }
    ],
    "sg:phone":"+1 780 433 7082",
    "sg:postcode":"T6E 1M1",
    "sg:province":"AB",
    "sg:tags":[
        "church"
    ],
    "wof:name":"Calvary Lutheran Church",
    "wof:placetype":"venue"
},
  "geometry": {"coordinates":[-113.509933,53.512066],"type":"Point"}
}