{
  "type": "Feature",
  "properties": {
    "addr:full":"83 Desgroseillers Rd Radisson QC J0Y 2X0",
    "addr:housenumber":"83",
    "addr:postcode":"j0y 2x0",
    "addr:street":"Desgroseillers Rd",
    "iso:country":"CA",
    "sg:address":"83 Desgroseillers Rd",
    "sg:city":"Radisson",
    "sg:classifiers":[
        {
            "category":"Local Transit",
            "type":"Transportation"
        }
    ],
    "sg:phone":"+1 819 638 8888",
    "sg:postcode":"J0Y 2X0",
    "sg:province":"QC",
    "sg:tags":[
        "airport"
    ],
    "wof:name":"Aviation Boreal Inc",
    "wof:placetype":"venue"
},
  "geometry": {"coordinates":[-77.66571044920001,53.7306251526],"type":"Point"}
}