{
  "type": "Feature",
  "properties": {
    "addr:full":"103 Redview Dr Winnipeg MB R2N 3C4",
    "addr:housenumber":"103",
    "addr:postcode":"r2n 3c4",
    "addr:street":"Redview Dr",
    "iso:country":"CA",
    "sg:address":"103 Redview Dr",
    "sg:city":"Winnipeg",
    "sg:classifiers":[
        {
            "category":"Banks & Credit Unions",
            "subcategory":"Bank",
            "type":"Services"
        }
    ],
    "sg:phone":"+1 204 256 5500",
    "sg:postcode":"R2N 3C4",
    "sg:province":"MB",
    "sg:tags":[
        "loan",
        "real estate"
    ],
    "wof:name":"J D Financial Consultants",
    "wof:placetype":"venue"
},
  "geometry": {"coordinates":[-97.119507,49.803413],"type":"Point"}
}