{
  "type": "Feature",
  "properties": {
    "addr:full":"5650 Av Du Parc Montreal QC H2V 4H1",
    "addr:housenumber":"5650",
    "addr:postcode":"h2v 4h1",
    "addr:street":"Av Du Parc",
    "iso:country":"CA",
    "sg:address":"5650 Av Du Parc",
    "sg:city":"Montreal",
    "sg:classifiers":[
        {
            "category":"Manufacturing",
            "subcategory":"Food",
            "type":"Manufacturing & Wholesale Goods"
        }
    ],
    "sg:phone":"+1 514 270 3141",
    "sg:postcode":"H2V 4H1",
    "sg:province":"QC",
    "sg:tags":[
        "grocer",
        "cookie",
        "bakery"
    ],
    "wof:name":"Boulangerie Napolitaine",
    "wof:placetype":"venue"
},
  "geometry": {"coordinates":[-73.603973,45.522831],"type":"Point"}
}