{
  "type": "Feature",
  "properties": {
    "addr:full":"5400 Portage Rd # 602 Niagara Falls ON L2G 5X7",
    "addr:housenumber":"5400",
    "addr:postcode":"l2g 5x7",
    "addr:street":"Portage Rd # 602",
    "iso:country":"CA",
    "sg:address":"5400 Portage Rd # 602",
    "sg:city":"Niagara Falls",
    "sg:classifiers":[
        {
            "category":"Health Services",
            "subcategory":"Doctor",
            "type":"Services"
        }
    ],
    "sg:phone":"+1 905 356 2228",
    "sg:postcode":"L2G 5X7",
    "sg:province":"ON",
    "sg:tags":[
        "physician",
        "surgeon"
    ],
    "wof:name":"Dec, David A MD",
    "wof:placetype":"venue"
},
  "geometry": {"coordinates":[-79.090805,43.095966],"type":"Point"}
}