{
  "type": "Feature",
  "properties": {
    "addr:full":"North York ON M2J 4G8",
    "addr:postcode":"m2j 4g8",
    "iso:country":"CA",
    "sg:city":"North York",
    "sg:classifiers":[
        {
            "category":"Organizations",
            "subcategory":"Professional Association",
            "type":"Services"
        }
    ],
    "sg:phone":"+1 416 495 1666",
    "sg:postcode":"M2J 4G8",
    "sg:province":"ON",
    "wof:name":"Barbados House Inc",
    "wof:placetype":"venue"
},
  "geometry": {"coordinates":[-79.331924,43.772156],"type":"Point"}
}