{
  "type": "Feature",
  "properties": {
    "iso:country":"CA",
    "sg:city":"Montreal",
    "sg:classifiers":[
        {
            "category":"Freight",
            "type":"Transportation"
        }
    ],
    "sg:phone":"+1 514 387 7111",
    "sg:postcode":"H2B 3A8",
    "sg:province":"QC",
    "sg:tags":[
        "trucking"
    ],
    "wof:name":"Transport Rtd Inc",
    "wof:placetype":"venue"
},
  "geometry": {"coordinates":[-73.6472702026,45.5658836365],"type":"Point"}
}