{
  "type": "Feature",
  "properties": {
    "addr:full":"53 Division St Bowmanville ON L1C 2Z8",
    "addr:housenumber":"53",
    "addr:postcode":"l1c 2z8",
    "addr:street":"Division St",
    "iso:country":"CA",
    "sg:address":"53 Division St",
    "sg:city":"Bowmanville",
    "sg:classifiers":[
        {
            "category":"Retail",
            "subcategory":"Funeral Services",
            "type":"Services"
        }
    ],
    "sg:phone":"+1 905 623 5668",
    "sg:postcode":"L1C 2Z8",
    "sg:province":"ON",
    "sg:tags":[
        "director"
    ],
    "wof:name":"Northcutt Elliott Funeral Home",
    "wof:placetype":"venue"
},
  "geometry": {"coordinates":[-78.68631000000001,43.914158],"type":"Point"}
}