{
  "type": "Feature",
  "properties": {
    "iso:country":"CA",
    "sg:address":"215 Wurtemburg St # 102",
    "sg:city":"Ottawa",
    "sg:classifiers":[
        {
            "category":"Social Services",
            "type":"Services"
        }
    ],
    "sg:phone":"+1 613 562 0011",
    "sg:postcode":"K1N 8T1",
    "sg:province":"ON",
    "sg:tags":[
        "organization",
        "welfare"
    ],
    "wof:name":"Options Bytown",
    "wof:placetype":"venue"
},
  "geometry": {"coordinates":[-75.674683,45.433083],"type":"Point"}
}