{
  "type": "Feature",
  "properties": {
    "iso:country":"CA",
    "sg:address":"167 Boul Laurier",
    "sg:city":"Laurier-Station",
    "sg:classifiers":[
        {
            "category":"Shopping",
            "subcategory":"Optical Goods",
            "type":"Retail Goods"
        }
    ],
    "sg:phone":"+1 418 728 5473",
    "sg:postcode":"G0S 1N0",
    "sg:province":"QC",
    "sg:tags":[
        "optician"
    ],
    "wof:name":"Guylaine Michaud Opticienne",
    "wof:placetype":"venue"
},
  "geometry": {"coordinates":[-71.6286697388,46.5424766541],"type":"Point"}
}