{
  "type": "Feature",
  "properties": {
    "iso:country":"CA",
    "sg:address":"240 Rue DE Beaujour",
    "sg:city":"Iberville",
    "sg:classifiers":[
        {
            "category":"Wholesale",
            "subcategory":"Durable Goods & Equipment",
            "type":"Manufacturing & Wholesale Goods"
        }
    ],
    "sg:phone":"+1 450 346 9624",
    "sg:postcode":"J2X 3W2",
    "sg:province":"QC",
    "sg:tags":[
        "sawdust",
        "shaving"
    ],
    "wof:name":"Exportations Iberville Inc",
    "wof:placetype":"venue"
},
  "geometry": {"coordinates":[-73.232201,45.315517],"type":"Point"}
}