{
  "type": "Feature",
  "properties": {
    "addr:full":"126 Rue Monseigneur-Blanche Sept-Iles QC G4R 3G8",
    "addr:housenumber":"126",
    "addr:postcode":"g4r 3g8",
    "addr:street":"Rue Monseigneur-Blanche Sept-Iles",
    "iso:country":"CA",
    "sg:address":"126 Rue Monseigneur-Blanche",
    "sg:city":"Sept-Iles",
    "sg:classifiers":[
        {
            "category":"Freight",
            "type":"Transportation"
        }
    ],
    "sg:phone":"+1 418 962 2126",
    "sg:postcode":"G4R 3G8",
    "sg:province":"QC",
    "sg:tags":[
        "bus",
        "line",
        "courier"
    ],
    "wof:name":"Terminus D'Autobus Intercar",
    "wof:placetype":"venue"
},
  "geometry": {"coordinates":[-66.367958,50.205936],"type":"Point"}
}