{
  "type": "Feature",
  "properties": {
    "addr:full":"Toronto ON M6H 1M3",
    "addr:postcode":"m6h 1m3",
    "iso:country":"CA",
    "sg:city":"Toronto",
    "sg:classifiers":[
        {
            "category":"Professional",
            "subcategory":"Lawyer & Legal Services",
            "type":"Services"
        }
    ],
    "sg:phone":"+1 416 532 2871",
    "sg:postcode":"M6H 1M3",
    "sg:province":"ON",
    "sg:tags":[
        "attorney"
    ],
    "wof:name":"Welman, Allen P",
    "wof:placetype":"venue"
},
  "geometry": {"coordinates":[-79.43180084230001,43.6606712341],"type":"Point"}
}