{
  "type": "Feature",
  "properties": {
    "addr:full":"1041 Kaiser William Ave E Langenburg SK S0A 2A0",
    "addr:housenumber":"1041",
    "addr:postcode":"s0a 2a0",
    "addr:street":"Kaiser William Ave E",
    "iso:country":"CA",
    "sg:address":"1041 Kaiser William Ave E",
    "sg:city":"Langenburg",
    "sg:classifiers":[
        {
            "category":"Travel",
            "subcategory":"Hotels & Motels",
            "type":"Entertainment"
        }
    ],
    "sg:phone":"+1 306 743 2638",
    "sg:postcode":"S0A 2A0",
    "sg:province":"SK",
    "wof:name":"Langenburg Country Inn Motel",
    "wof:placetype":"venue"
},
  "geometry": {"coordinates":[-101.685371,50.837391],"type":"Point"}
}