{
  "type": "Feature",
  "properties": {
    "addr:full":"781 Hwy 26 St Francois Xavier MB R4L 1A2",
    "addr:housenumber":"781",
    "addr:postcode":"r4l 1a2",
    "addr:street":"Hwy 26 St Francois Xavier",
    "iso:country":"CA",
    "sg:address":"781 Hwy 26",
    "sg:city":"St Francois Xavier",
    "sg:classifiers":[
        {
            "category":"Building & Trades",
            "subcategory":"Landscaping Services",
            "type":"Services"
        }
    ],
    "sg:phone":"+1 204 864 2753",
    "sg:postcode":"R4L 1A2",
    "sg:province":"MB",
    "sg:tags":[
        "underground",
        "trenching",
        "landscape",
        "contractor"
    ],
    "wof:name":"Whitehorse General Contracting",
    "wof:placetype":"venue"
},
  "geometry": {"coordinates":[-97.90888200000001,50.059078],"type":"Point"}
}