{
  "type": "Feature",
  "properties": {
    "addr:full":"817 1st St Edam SK S0M 0V0",
    "addr:housenumber":"817",
    "addr:postcode":"s0m 0v0",
    "addr:street":"1St St",
    "iso:country":"CA",
    "sg:address":"817 1st St",
    "sg:city":"Edam",
    "sg:classifiers":[
        {
            "category":"Mining & Drilling",
            "type":"Manufacturing & Wholesale Goods"
        }
    ],
    "sg:phone":"+1 306 397 2211",
    "sg:postcode":"S0M 0V0",
    "sg:province":"SK",
    "sg:tags":[
        "oil",
        "well"
    ],
    "wof:name":"Severs Oilfield Svc Inc",
    "wof:placetype":"venue"
},
  "geometry": {"coordinates":[-108.762641907,53.1887435913],"type":"Point"}
}