{
  "type": "Feature",
  "properties": {
    "addr:full":"5607 Riverbend Rd NW Edmonton AB T6H 5K4",
    "addr:housenumber":"5607",
    "addr:postcode":"t6h 5k4",
    "addr:street":"Riverbend Rd Nw",
    "iso:country":"CA",
    "sg:address":"5607 Riverbend Rd NW",
    "sg:city":"Edmonton",
    "sg:classifiers":[
        {
            "category":"Education",
            "subcategory":"School",
            "type":"Public Place"
        }
    ],
    "sg:phone":"+1 780 433 5182",
    "sg:postcode":"T6H 5K4",
    "sg:province":"AB",
    "wof:name":"Kumon Math & Reading Ctr",
    "wof:placetype":"venue"
},
  "geometry": {"coordinates":[-113.578064,53.493912],"type":"Point"}
}