{
  "type": "Feature",
  "properties": {
    "addr:full":"715 Rue Des Glacis Quebec QC G1R 3P8",
    "addr:housenumber":"715",
    "addr:postcode":"g1r 3p8",
    "addr:street":"Rue Des Glacis",
    "iso:country":"CA",
    "sg:address":"715 Rue Des Glacis",
    "sg:city":"Quebec",
    "sg:classifiers":[
        {
            "category":"Health Services",
            "subcategory":"Nursing And Care Facility",
            "type":"Services"
        }
    ],
    "sg:phone":"+1 418 694 0492",
    "sg:postcode":"G1R 3P8",
    "sg:province":"QC",
    "sg:tags":[
        "home",
        "rest"
    ],
    "wof:name":"Centre D'Acceuil Nazareth Inc",
    "wof:placetype":"venue"
},
  "geometry": {"coordinates":[-71.215515,46.814034],"type":"Point"}
}