{
  "type": "Feature",
  "properties": {
    "addr:full":"Beauport QC G1B 3A6",
    "addr:postcode":"g1b 3a6",
    "iso:country":"CA",
    "sg:city":"Beauport",
    "sg:classifiers":[
        {
            "category":"Food & Beverages",
            "subcategory":"Groceries & Convenience Stores",
            "type":"Retail Goods"
        }
    ],
    "sg:phone":"+1 418 661 6111",
    "sg:postcode":"G1B 3A6",
    "sg:province":"QC",
    "sg:tags":[
        "grocer"
    ],
    "wof:name":"Provigo",
    "wof:placetype":"venue"
},
  "geometry": {"coordinates":[-71.21275300000001,46.891842],"type":"Point"}
}