{
  "type": "Feature",
  "properties": {
    "iso:country":"CA",
    "sg:address":"55 York Blvd",
    "sg:city":"Hamilton",
    "sg:classifiers":[
        {
            "category":"Education",
            "subcategory":"Library",
            "type":"Public Place"
        }
    ],
    "sg:phone":"+1 905 546 3200",
    "sg:postcode":"L8R 3K1",
    "sg:province":"ON",
    "wof:name":"Hamilton Public Library",
    "wof:placetype":"venue"
},
  "geometry": {"coordinates":[-79.8704376221,43.2591896057],"type":"Point"}
}