{
  "type": "Feature",
  "properties": {
    "addr:full":"Guelph ON N1H 3X7",
    "addr:postcode":"n1h 3x7",
    "iso:country":"CA",
    "sg:city":"Guelph",
    "sg:classifiers":[
        {
            "category":"Professional",
            "subcategory":"Computer Services",
            "type":"Services"
        }
    ],
    "sg:phone":"+1 519 826 5222",
    "sg:postcode":"N1H 3X7",
    "sg:province":"ON",
    "sg:tags":[
        "internet"
    ],
    "wof:name":"Netsweeper Inc",
    "wof:placetype":"venue"
},
  "geometry": {"coordinates":[-80.2641220093,43.5551567078],"type":"Point"}
}