{
  "type": "Feature",
  "properties": {
    "iso:country":"CA",
    "sg:city":"Burnaby",
    "sg:classifiers":[
        {
            "category":"Health Services",
            "subcategory":"Doctor",
            "type":"Services"
        }
    ],
    "sg:phone":"+1 604 298 7343",
    "sg:postcode":"V5B 1S2",
    "sg:province":"BC",
    "sg:tags":[
        "dentist"
    ],
    "wof:name":"Wong, Tom L Q DDS",
    "wof:placetype":"venue"
},
  "geometry": {"coordinates":[-122.968353272,49.280128479],"type":"Point"}
}