{
  "type": "Feature",
  "properties": {
    "iso:country":"CA",
    "sg:address":"10 Lower Jarvis St",
    "sg:city":"Toronto",
    "sg:classifiers":[
        {
            "category":"Shopping",
            "subcategory":"Pharmacy",
            "type":"Retail Goods"
        }
    ],
    "sg:phone":"+1 416 304 0619",
    "sg:postcode":"M5E 1Z2",
    "sg:province":"ON",
    "wof:name":"Drug Store Pharmacy",
    "wof:placetype":"venue"
},
  "geometry": {"coordinates":[-79.3696899414,43.6447486877],"type":"Point"}
}