{
  "type": "Feature",
  "properties": {
    "addr:full":"6525 111 St NW Edmonton AB T6H 4R5",
    "addr:housenumber":"6525",
    "addr:postcode":"t6h 4r5",
    "addr:street":"111 St Nw",
    "iso:country":"CA",
    "sg:address":"6525 111 St NW",
    "sg:city":"Edmonton",
    "sg:classifiers":[
        {
            "category":"Restaurant",
            "type":"Food & Drink"
        }
    ],
    "sg:phone":"+1 780 435 7622",
    "sg:postcode":"T6H 4R5",
    "sg:province":"AB",
    "wof:name":"Happy Garden Restaurant",
    "wof:placetype":"venue"
},
  "geometry": {"coordinates":[-113.51616668699999,53.5025138855],"type":"Point"}
}