{
  "type": "Feature",
  "properties": {
    "addr:full":"Vancouver BC V6B 3E4",
    "addr:postcode":"v6b 3e4",
    "iso:country":"CA",
    "sg:city":"Vancouver",
    "sg:classifiers":[
        {
            "category":"Manufacturing",
            "subcategory":"Printing",
            "type":"Manufacturing & Wholesale Goods"
        }
    ],
    "sg:phone":"+1 604 696 9283",
    "sg:postcode":"V6B 3E4",
    "sg:province":"BC",
    "sg:tags":[
        "publisher"
    ],
    "wof:name":"Waves Magazine",
    "wof:placetype":"venue"
},
  "geometry": {"coordinates":[-123.12175000000001,49.27771],"type":"Point"}
}