{
  "type": "Feature",
  "properties": {
    "addr:full":"Hornepayne ON P0M 1Z0",
    "addr:postcode":"p0m 1z0",
    "iso:country":"CA",
    "sg:city":"Hornepayne",
    "sg:classifiers":[
        {
            "category":"Recreation",
            "type":"Entertainment"
        }
    ],
    "sg:phone":"+1 807 868 2774",
    "sg:postcode":"P0M 1Z0",
    "sg:province":"ON",
    "sg:tags":[
        "club",
        "curling",
        "government"
    ],
    "wof:name":"Hornepayne Curling Club",
    "wof:placetype":"venue"
},
  "geometry": {"coordinates":[-84.786766,49.217396],"type":"Point"}
}