{
  "type": "Feature",
  "properties": {
    "iso:country":"CA",
    "sg:address":"212 Bergey Crt",
    "sg:city":"New Hamburg",
    "sg:classifiers":[
        {
            "category":"Freight",
            "type":"Transportation"
        }
    ],
    "sg:phone":"+1 519 662 3640",
    "sg:postcode":"N3A 2J5",
    "sg:province":"ON",
    "sg:tags":[
        "trucking"
    ],
    "wof:name":"Grant Transport",
    "wof:placetype":"venue"
},
  "geometry": {"coordinates":[-80.69617462159999,43.3753662109],"type":"Point"}
}