{
  "type": "Feature",
  "properties": {
    "addr:full":"1145 Henderson Hwy Winnipeg MB R2G 1L5",
    "addr:housenumber":"1145",
    "addr:postcode":"r2g 1l5",
    "addr:street":"Henderson Hwy",
    "iso:country":"CA",
    "sg:address":"1145 Henderson Hwy",
    "sg:city":"Winnipeg",
    "sg:classifiers":[
        {
            "category":"Retail",
            "subcategory":"Laundry & Dry Cleaning",
            "type":"Services"
        }
    ],
    "sg:phone":"+1 204 338 2129",
    "sg:postcode":"R2G 1L5",
    "sg:province":"MB",
    "sg:tags":[
        "tailor"
    ],
    "wof:name":"Henderson Tailor & Alterations",
    "wof:placetype":"venue"
},
  "geometry": {"coordinates":[-97.091995,49.938541],"type":"Point"}
}