{
  "type": "Feature",
  "properties": {
    "addr:full":"Clearwater BC V0E 1N0",
    "addr:postcode":"v0e 1n0",
    "iso:country":"CA",
    "sg:city":"Clearwater",
    "sg:classifiers":[
        {
            "category":"Shopping",
            "subcategory":"Stationery & Office Supplies",
            "type":"Retail Goods"
        }
    ],
    "sg:phone":"+1 250 674 3232",
    "sg:postcode":"V0E 1N0",
    "sg:province":"BC",
    "sg:tags":[
        "stationer"
    ],
    "wof:name":"Valley Stationery",
    "wof:placetype":"venue"
},
  "geometry": {"coordinates":[-120.01159699999999,51.646591],"type":"Point"}
}