{
  "type": "Feature",
  "properties": {
    "addr:full":"3301 24 Ave # 201 Vernon BC V1T 9S8",
    "addr:housenumber":"3301",
    "addr:postcode":"v1t 9s8",
    "addr:street":"24 Ave # 201",
    "iso:country":"CA",
    "sg:address":"3301 24 Ave # 201",
    "sg:city":"Vernon",
    "sg:classifiers":[
        {
            "category":"Health Services",
            "subcategory":"Doctor",
            "type":"Services"
        }
    ],
    "sg:phone":"+1 250 542 8715",
    "sg:postcode":"V1T 9S8",
    "sg:province":"BC",
    "sg:tags":[
        "physician",
        "surgeon"
    ],
    "wof:name":"Lavoie, Dennis MD",
    "wof:placetype":"venue"
},
  "geometry": {"coordinates":[-119.275093079,50.2594909668],"type":"Point"}
}