{
  "type": "Feature",
  "properties": {
    "addr:full":"Cambridge ON N1R 6T6",
    "addr:postcode":"n1r 6t6",
    "iso:country":"CA",
    "sg:city":"Cambridge",
    "sg:classifiers":[
        {
            "category":"Manufacturing",
            "subcategory":"Printing",
            "type":"Manufacturing & Wholesale Goods"
        }
    ],
    "sg:phone":"+1 519 623 5551",
    "sg:postcode":"N1R 6T6",
    "sg:province":"ON",
    "sg:tags":[
        "printer"
    ],
    "wof:name":"Minuteman Press",
    "wof:placetype":"venue"
},
  "geometry": {"coordinates":[-80.31873299999999,43.402828],"type":"Point"}
}