{
  "type": "Feature",
  "properties": {
    "addr:full":"36 Bridge St E Belleville ON K8N 1L6",
    "addr:housenumber":"36",
    "addr:postcode":"k8n 1l6",
    "addr:street":"Bridge St E",
    "iso:country":"CA",
    "sg:address":"36 Bridge St E",
    "sg:city":"Belleville",
    "sg:classifiers":[
        {
            "category":"Museum",
            "type":"Entertainment"
        }
    ],
    "sg:phone":"+1 613 962 1232",
    "sg:postcode":"K8N 1L6",
    "sg:province":"ON",
    "sg:tags":[
        "organization",
        "arts",
        "information"
    ],
    "wof:name":"Quinte Arts Council",
    "wof:placetype":"venue"
},
  "geometry": {"coordinates":[-77.38369,44.163857],"type":"Point"}
}