{
  "type": "Feature",
  "properties": {
    "addr:full":"SW 15-5-11W Swan Lake MB R0G 2S0",
    "addr:postcode":"r0g 2s0",
    "addr:street":"Sw 15-5-11W",
    "iso:country":"CA",
    "sg:address":"SW 15-5-11W",
    "sg:city":"Swan Lake",
    "sg:classifiers":[
        {
            "category":"Government",
            "subcategory":"Office",
            "type":"Public Place"
        }
    ],
    "sg:phone":"+1 204 836 2424",
    "sg:postcode":"R0G 2S0",
    "sg:province":"MB",
    "sg:tags":[
        "association"
    ],
    "wof:name":"Canada Indian Health Svc",
    "wof:placetype":"venue"
},
  "geometry": {"coordinates":[-98.79357899999999,49.411362],"type":"Point"}
}