{
  "type": "Feature",
  "properties": {
    "iso:country":"CA",
    "sg:city":"Beulah",
    "sg:classifiers":[
        {
            "category":"Autos & Motor Vehicles",
            "subcategory":"Fuel & Gas Station",
            "type":"Retail Goods"
        }
    ],
    "sg:phone":"+1 204 568 4780",
    "sg:postcode":"R0M 0B0",
    "sg:province":"MB",
    "sg:tags":[
        "oil"
    ],
    "wof:name":"Birdtail Gas Bar & Convenience",
    "wof:placetype":"venue"
},
  "geometry": {"coordinates":[-101.038032532,50.259475708],"type":"Point"}
}