{
  "type": "Feature",
  "properties": {
    "addr:full":"465 Stone St S Gananoque ON K7G 2A7",
    "addr:housenumber":"465",
    "addr:postcode":"k7g 2a7",
    "addr:street":"Stone St S",
    "iso:country":"CA",
    "sg:address":"465 Stone St S",
    "sg:city":"Gananoque",
    "sg:classifiers":[
        {
            "category":"Travel",
            "subcategory":"Hotels & Motels",
            "type":"Entertainment"
        }
    ],
    "sg:phone":"+1 613 382 8642",
    "sg:postcode":"K7G 2A7",
    "sg:province":"ON",
    "sg:tags":[
        "breakfast",
        "accommodation",
        "bed"
    ],
    "wof:name":"Manse Lane Bed & Breakfast",
    "wof:placetype":"venue"
},
  "geometry": {"coordinates":[-76.1585235596,44.3265571594],"type":"Point"}
}