{
  "type": "Feature",
  "properties": {
    "addr:full":"30 Hemlo Dr Marathon ON P0T 2E0",
    "addr:housenumber":"30",
    "addr:postcode":"p0t 2e0",
    "addr:street":"Hemlo Dr",
    "iso:country":"CA",
    "sg:address":"30 Hemlo Dr",
    "sg:city":"Marathon",
    "sg:classifiers":[
        {
            "category":"Wholesale",
            "subcategory":"Apparel",
            "type":"Manufacturing & Wholesale Goods"
        }
    ],
    "sg:phone":"+1 807 229 1248",
    "sg:postcode":"P0T 2E0",
    "sg:province":"ON",
    "sg:tags":[
        "dressmaker",
        "supply"
    ],
    "wof:name":"Anne's Sewing",
    "wof:placetype":"venue"
},
  "geometry": {"coordinates":[-86.36883544920001,48.7135543823],"type":"Point"}
}