{
  "type": "Feature",
  "properties": {
    "addr:full":"Killarney MB R0K 1G0",
    "addr:postcode":"r0k 1g0",
    "iso:country":"CA",
    "sg:city":"Killarney",
    "sg:classifiers":[
        {
            "category":"Government",
            "subcategory":"Office",
            "type":"Public Place"
        }
    ],
    "sg:phone":"+1 204 523 3224",
    "sg:postcode":"R0K 1G0",
    "sg:province":"MB",
    "wof:name":"Manitoba District Office",
    "wof:placetype":"venue"
},
  "geometry": {"coordinates":[-99.65715,49.180435],"type":"Point"}
}