{
  "type": "Feature",
  "properties": {
    "iso:country":"CA",
    "sg:address":"RR 3 STN Main",
    "sg:city":"Innisfail",
    "sg:classifiers":[
        {
            "category":"Retail",
            "subcategory":"Auto Repair",
            "type":"Services"
        }
    ],
    "sg:phone":"+1 403 227 2873",
    "sg:postcode":"T4G 1T8",
    "sg:province":"AB",
    "sg:tags":[
        "truck"
    ],
    "wof:name":"3-D Diesel",
    "wof:placetype":"venue"
},
  "geometry": {"coordinates":[-113.948623657,52.0274085999],"type":"Point"}
}