{
  "type": "Feature",
  "properties": {
    "addr:full":"Vancouver BC V6Z 2T1",
    "addr:postcode":"v6z 2t1",
    "iso:country":"CA",
    "sg:city":"Vancouver",
    "sg:classifiers":[
        {
            "category":"Manufacturing",
            "subcategory":"Printing",
            "type":"Manufacturing & Wholesale Goods"
        }
    ],
    "sg:phone":"+1 604 606 4644",
    "sg:postcode":"V6Z 2T1",
    "sg:province":"BC",
    "sg:tags":[
        "publication"
    ],
    "wof:name":"O P Publishing",
    "wof:placetype":"venue"
},
  "geometry": {"coordinates":[-123.124961853,49.2789993286],"type":"Point"}
}