{
  "type": "Feature",
  "properties": {
    "addr:full":"1215 3 Ave S Lethbridge AB T1J 0J7",
    "addr:housenumber":"1215",
    "addr:postcode":"t1j 0j7",
    "addr:street":"3 Ave S",
    "iso:country":"CA",
    "sg:address":"1215 3 Ave S",
    "sg:city":"Lethbridge",
    "sg:classifiers":[
        {
            "category":"Wholesale",
            "subcategory":"Medical Equipment & Supplies",
            "type":"Manufacturing & Wholesale Goods"
        }
    ],
    "sg:phone":"+1 403 320 1488",
    "sg:postcode":"T1J 0J7",
    "sg:province":"AB",
    "sg:tags":[
        "physician",
        "surgeon"
    ],
    "wof:name":"Medichair Lethbridge",
    "wof:placetype":"venue"
},
  "geometry": {"coordinates":[-112.828728,49.69643],"type":"Point"}
}