{
  "type": "Feature",
  "properties": {
    "iso:country":"CA",
    "sg:address":"4025 Highway 1",
    "sg:city":"St George",
    "sg:classifiers":[
        {
            "category":"Wholesale",
            "subcategory":"Auto Parts",
            "type":"Manufacturing & Wholesale Goods"
        }
    ],
    "sg:phone":"+1 506 755 3065",
    "sg:postcode":"E5C 3S9",
    "sg:province":"NB",
    "sg:tags":[
        "automobile",
        "rebuilt"
    ],
    "wof:name":"Lee's Chevy Trucks & Parts",
    "wof:placetype":"venue"
},
  "geometry": {"coordinates":[-66.81961800000001,45.130531],"type":"Point"}
}