{
  "type": "Feature",
  "properties": {
    "addr:full":"Nipawin SK S0E 1E0",
    "addr:postcode":"s0e 1e0",
    "iso:country":"CA",
    "sg:city":"Nipawin",
    "sg:classifiers":[
        {
            "category":"Government",
            "subcategory":"Office",
            "type":"Public Place"
        }
    ],
    "sg:phone":"+1 306 862 4415",
    "sg:postcode":"S0E 1E0",
    "sg:province":"SK",
    "wof:name":"Canada Inspector Plant Health",
    "wof:placetype":"venue"
},
  "geometry": {"coordinates":[-104.026283264,53.3567428589],"type":"Point"}
}