{
  "type": "Feature",
  "properties": {
    "addr:full":"Halifax NS B3R 1W2",
    "addr:postcode":"b3r 1w2",
    "iso:country":"CA",
    "sg:city":"Halifax",
    "sg:classifiers":[
        {
            "category":"Restaurant",
            "type":"Food & Drink"
        }
    ],
    "sg:phone":"+1 902 477 4400",
    "sg:postcode":"B3R 1W2",
    "sg:province":"NS",
    "sg:tags":[
        "pizza"
    ],
    "wof:name":"Paul's Pizza",
    "wof:placetype":"venue"
},
  "geometry": {"coordinates":[-63.6170578003,44.6105957031],"type":"Point"}
}