{
  "type": "Feature",
  "properties": {
    "addr:full":"Waubaushene ON L0K 2C0",
    "addr:postcode":"l0k 2c0",
    "iso:country":"CA",
    "sg:city":"Waubaushene",
    "sg:classifiers":[
        {
            "category":"Shopping",
            "type":"Retail Goods"
        }
    ],
    "sg:phone":"+1 705 538 0110",
    "sg:postcode":"L0K 2C0",
    "sg:province":"ON",
    "sg:tags":[
        "spa",
        "hot",
        "tub"
    ],
    "wof:name":"Waubco Hot Tubs & Spas",
    "wof:placetype":"venue"
},
  "geometry": {"coordinates":[-79.71043396,44.7478942871],"type":"Point"}
}