{
  "type": "Feature",
  "properties": {
    "addr:full":"20 Boul DE LA Seigneurie E Blainville QC J7C 3V5",
    "addr:housenumber":"20",
    "addr:postcode":"j7c 3v5",
    "addr:street":"Boul De La Seigneurie E",
    "iso:country":"CA",
    "sg:address":"20 Boul DE LA Seigneurie E",
    "sg:city":"Blainville",
    "sg:classifiers":[
        {
            "category":"Real Estate",
            "subcategory":"Real Estate Agent",
            "type":"Services"
        }
    ],
    "sg:phone":"+1 450 433 7277",
    "sg:postcode":"J7C 3V5",
    "sg:province":"QC",
    "sg:tags":[
        "agency",
        "rental"
    ],
    "wof:name":"Location D'Outils Simplex",
    "wof:placetype":"venue"
},
  "geometry": {"coordinates":[-73.867439,45.669395],"type":"Point"}
}