{
  "type": "Feature",
  "properties": {
    "addr:full":"25 Dundas St E # 1 Dundas ON L9H 7H8",
    "addr:housenumber":"25",
    "addr:postcode":"l9h 7h8",
    "addr:street":"Dundas St E # 1",
    "iso:country":"CA",
    "sg:address":"25 Dundas St E # 1",
    "sg:city":"Dundas",
    "sg:classifiers":[
        {
            "category":"Retail",
            "subcategory":"Repair Shop",
            "type":"Services"
        }
    ],
    "sg:phone":"+1 905 689 5144",
    "sg:postcode":"L9H 7H8",
    "sg:province":"ON",
    "sg:tags":[
        "welding"
    ],
    "wof:name":"Parsons Welding Svc Ltd",
    "wof:placetype":"venue"
},
  "geometry": {"coordinates":[-79.9502944946,43.2638435364],"type":"Point"}
}