{
  "type": "Feature",
  "properties": {
    "addr:full":"5 Church St Lantz NS B2S 1P3",
    "addr:housenumber":"5",
    "addr:postcode":"b2s 1p3",
    "addr:street":"Church St",
    "iso:country":"CA",
    "sg:address":"5 Church St",
    "sg:city":"Lantz",
    "sg:classifiers":[
        {
            "category":"Government",
            "subcategory":"Fire Station",
            "type":"Public Place"
        }
    ],
    "sg:phone":"+1 902 883 9209",
    "sg:postcode":"B2S 1P3",
    "sg:province":"NS",
    "sg:tags":[
        "department"
    ],
    "wof:name":"Lantz Volunteer Fire Dept",
    "wof:placetype":"venue"
},
  "geometry": {"coordinates":[-63.482689,44.9865],"type":"Point"}
}