{
  "type": "Feature",
  "properties": {
    "addr:full":"Chicoutimi QC G7H 1S6",
    "addr:postcode":"g7h 1s6",
    "iso:country":"CA",
    "sg:city":"Chicoutimi",
    "sg:classifiers":[
        {
            "category":"Professional",
            "subcategory":"Lawyer & Legal Services",
            "type":"Services"
        }
    ],
    "sg:phone":"+1 418 690 3545",
    "sg:postcode":"G7H 1S6",
    "sg:province":"QC",
    "sg:tags":[
        "attorney"
    ],
    "wof:name":"Gauthier Bedard",
    "wof:placetype":"venue"
},
  "geometry": {"coordinates":[-71.0575714111,48.4274253845],"type":"Point"}
}