{
  "type": "Feature",
  "properties": {
    "addr:full":"Saint-Bernard QC G0S 2G0",
    "addr:postcode":"g0s 2g0",
    "iso:country":"CA",
    "sg:city":"Saint-Bernard",
    "sg:classifiers":[
        {
            "category":"Manufacturing",
            "subcategory":"Tools & Machinery",
            "type":"Manufacturing & Wholesale Goods"
        }
    ],
    "sg:phone":"+1 418 475 6566",
    "sg:postcode":"G0S 2G0",
    "sg:province":"QC",
    "sg:tags":[
        "farm",
        "equipment"
    ],
    "wof:name":"Conception Ro-Main Inc",
    "wof:placetype":"venue"
},
  "geometry": {"coordinates":[-71.136871,46.498371],"type":"Point"}
}