{
  "type": "Feature",
  "properties": {
    "addr:full":"204 Main St Burin Bay Arm NL A0E 1G0",
    "addr:housenumber":"204",
    "addr:postcode":"a0e 1g0",
    "addr:street":"Main St Burin Bay",
    "iso:country":"CA",
    "sg:address":"204 Main St",
    "sg:city":"Burin Bay Arm",
    "sg:classifiers":[
        {
            "category":"Travel",
            "subcategory":"Hotels & Motels",
            "type":"Entertainment"
        }
    ],
    "sg:phone":"+1 709 891 2000",
    "sg:postcode":"A0E 1G0",
    "sg:province":"NL",
    "sg:tags":[
        "breakfast",
        "accommodation",
        "bed"
    ],
    "wof:name":"Wheelhouse Inn",
    "wof:placetype":"venue"
},
  "geometry": {"coordinates":[-55.177979,47.068279],"type":"Point"}
}