{
  "type": "Feature",
  "properties": {
    "iso:country":"CA",
    "sg:address":"1157 Midland Ave",
    "sg:city":"Kingston",
    "sg:classifiers":[
        {
            "category":"Building & Trades",
            "subcategory":"Construction",
            "type":"Services"
        }
    ],
    "sg:phone":"+1 613 384 4910",
    "sg:postcode":"K7P 2X8",
    "sg:province":"ON",
    "sg:tags":[
        "designer",
        "marine",
        "contractor"
    ],
    "wof:name":"Moe Green & Assoc Inc",
    "wof:placetype":"venue"
},
  "geometry": {"coordinates":[-76.574364,44.264935],"type":"Point"}
}