{
  "type": "Feature",
  "properties": {
    "addr:full":"3329 Bloor St W Etobicoke ON M8X 1E7",
    "addr:housenumber":"3329",
    "addr:postcode":"m8x 1e7",
    "addr:street":"Bloor St W",
    "iso:country":"CA",
    "sg:address":"3329 Bloor St W",
    "sg:city":"Etobicoke",
    "sg:classifiers":[
        {
            "category":"Professional",
            "subcategory":"Lawyer & Legal Services",
            "type":"Services"
        }
    ],
    "sg:phone":"+1 416 231 7399",
    "sg:postcode":"M8X 1E7",
    "sg:province":"ON",
    "sg:tags":[
        "attorney"
    ],
    "wof:name":"Gerald Wise Law Office",
    "wof:placetype":"venue"
},
  "geometry": {"coordinates":[-79.5208740234,43.6451148987],"type":"Point"}
}