{
  "type": "Feature",
  "properties": {
    "addr:full":"2363 Taunton Rd Hampton ON L0B 1J0",
    "addr:housenumber":"2363",
    "addr:postcode":"l0b 1j0",
    "addr:street":"Taunton Rd",
    "iso:country":"CA",
    "sg:address":"2363 Taunton Rd",
    "sg:city":"Hampton",
    "sg:classifiers":[
        {
            "category":"Manufacturing",
            "subcategory":"Food",
            "type":"Manufacturing & Wholesale Goods"
        }
    ],
    "sg:phone":"+1 905 263 2872",
    "sg:postcode":"L0B 1J0",
    "sg:province":"ON",
    "sg:tags":[
        "chips"
    ],
    "wof:name":"Nofty's Home Fries",
    "wof:placetype":"venue"
},
  "geometry": {"coordinates":[-78.737244,43.965469],"type":"Point"}
}