{
  "type": "Feature",
  "properties": {
    "addr:full":"164 Boyne Ave W Morris MB R0G 1K0",
    "addr:housenumber":"164",
    "addr:postcode":"r0g 1k0",
    "addr:street":"Boyne Ave W",
    "iso:country":"CA",
    "sg:address":"164 Boyne Ave W",
    "sg:city":"Morris",
    "sg:classifiers":[
        {
            "category":"Professional",
            "subcategory":"Lawyer & Legal Services",
            "type":"Services"
        }
    ],
    "sg:phone":"+1 204 746 2179",
    "sg:postcode":"R0G 1K0",
    "sg:province":"MB",
    "sg:tags":[
        "attorney"
    ],
    "wof:name":"B D Gregory Law Office",
    "wof:placetype":"venue"
},
  "geometry": {"coordinates":[-97.36604309080001,49.3546867371],"type":"Point"}
}