{
  "type": "Feature",
  "properties": {
    "addr:full":"RR 3 STN Lcd 6 London ON N6A 4B7",
    "addr:housenumber":"6",
    "addr:postcode":"n6a 4b7",
    "addr:street":"Rr 3 Stn Lcd",
    "iso:country":"CA",
    "sg:address":"RR 3 STN Lcd 6",
    "sg:city":"London",
    "sg:classifiers":[
        {
            "category":"Education",
            "subcategory":"Special Training",
            "type":"Public Place"
        }
    ],
    "sg:phone":"+1 519 661 7844",
    "sg:postcode":"N6A 4B7",
    "sg:province":"ON",
    "sg:tags":[
        "aircraft",
        "school"
    ],
    "wof:name":"London Soaring Society",
    "wof:placetype":"venue"
},
  "geometry": {"coordinates":[-81.246216,42.986897],"type":"Point"}
}