{
  "type": "Feature",
  "properties": {
    "addr:full":"164 Edgehill Close NW Calgary AB T3A 2X1",
    "addr:housenumber":"164",
    "addr:postcode":"t3a 2x1",
    "addr:street":"Edgehill Close Nw",
    "iso:country":"CA",
    "sg:address":"164 Edgehill Close NW",
    "sg:city":"Calgary",
    "sg:classifiers":[
        {
            "category":"Building & Trades",
            "subcategory":"Electrical",
            "type":"Services"
        }
    ],
    "sg:phone":"+1 403 239 0829",
    "sg:postcode":"T3A 2X1",
    "sg:province":"AB",
    "sg:tags":[
        "electric",
        "contractor"
    ],
    "wof:name":"Parklane Electric Ltd",
    "wof:placetype":"venue"
},
  "geometry": {"coordinates":[-114.161903,51.123905],"type":"Point"}
}