{
  "type": "Feature",
  "properties": {
    "addr:full":"635551 Hwy 10 Shelburne ON L0N 1S5",
    "addr:housenumber":"635551",
    "addr:postcode":"l0n 1s5",
    "addr:street":"Hwy 10",
    "iso:country":"CA",
    "sg:address":"635551 Hwy 10",
    "sg:city":"Shelburne",
    "sg:classifiers":[
        {
            "category":"Shopping",
            "subcategory":"Gifts & Souvenirs",
            "type":"Retail Goods"
        }
    ],
    "sg:phone":"+1 519 925 3672",
    "sg:postcode":"L0N 1S5",
    "sg:province":"ON",
    "sg:tags":[
        "shop"
    ],
    "wof:name":"Fantasy Farm Gift Shop",
    "wof:placetype":"venue"
},
  "geometry": {"coordinates":[-80.181511,44.082958],"type":"Point"}
}