{
  "type": "Feature",
  "properties": {
    "iso:country":"CA",
    "sg:address":"4549 Buba Rd",
    "sg:city":"Prince George",
    "sg:classifiers":[
        {
            "category":"Building & Trades",
            "subcategory":"Construction",
            "type":"Services"
        }
    ],
    "sg:phone":"+1 250 962 7531",
    "sg:postcode":"V2K 1S5",
    "sg:province":"BC",
    "sg:tags":[
        "general",
        "contractor"
    ],
    "wof:name":"Knell Construction Ltd",
    "wof:placetype":"venue"
},
  "geometry": {"coordinates":[-122.764770508,53.9669265747],"type":"Point"}
}