{
  "type": "Feature",
  "properties": {
    "addr:full":"404 Cleveland Ave Riverview NB E1B 1Y2",
    "addr:housenumber":"404",
    "addr:postcode":"e1b 1y2",
    "addr:street":"Cleveland Ave",
    "iso:country":"CA",
    "sg:address":"404 Cleveland Ave",
    "sg:city":"Riverview",
    "sg:classifiers":[
        {
            "category":"Organizations",
            "subcategory":"Religious Organization",
            "type":"Services"
        }
    ],
    "sg:phone":"+1 506 386 3335",
    "sg:postcode":"E1B 1Y2",
    "sg:province":"NB",
    "sg:tags":[
        "church"
    ],
    "wof:name":"St Paul's United Church",
    "wof:placetype":"venue"
},
  "geometry": {"coordinates":[-64.79605865480001,46.0616111755],"type":"Point"}
}