{
  "type": "Feature",
  "properties": {
    "addr:full":"3430 Sheppard Ave E Scarborough ON M1T 3K4",
    "addr:housenumber":"3430",
    "addr:postcode":"m1t 3k4",
    "addr:street":"Sheppard Ave E",
    "iso:country":"CA",
    "sg:address":"3430 Sheppard Ave E",
    "sg:city":"Scarborough",
    "sg:classifiers":[
        {
            "category":"Restaurant",
            "type":"Food & Drink"
        }
    ],
    "sg:phone":"+1 416 293 5121",
    "sg:postcode":"M1T 3K4",
    "sg:province":"ON",
    "wof:name":"Mekeni Foods",
    "wof:placetype":"venue"
},
  "geometry": {"coordinates":[-79.30690002439999,43.7791061401],"type":"Point"}
}