{
  "type": "Feature",
  "properties": {
    "addr:full":"132 Dunn St Oakville ON L6J 3E2",
    "addr:housenumber":"132",
    "addr:postcode":"l6j 3e2",
    "addr:street":"Dunn St",
    "iso:country":"CA",
    "sg:address":"132 Dunn St",
    "sg:city":"Oakville",
    "sg:classifiers":[
        {
            "category":"Professional",
            "subcategory":"Lawyer & Legal Services",
            "type":"Services"
        }
    ],
    "sg:phone":"+1 905 845 1689",
    "sg:postcode":"L6J 3E2",
    "sg:province":"ON",
    "sg:tags":[
        "attorney"
    ],
    "wof:name":"Ford, John P H QC",
    "wof:placetype":"venue"
},
  "geometry": {"coordinates":[-79.66883087159999,43.4471931458],"type":"Point"}
}