{
  "type": "Feature",
  "properties": {
    "iso:country":"CA",
    "sg:address":"831 Legion Rd",
    "sg:city":"Burlington",
    "sg:classifiers":[
        {
            "category":"Organizations",
            "subcategory":"Religious Organization",
            "type":"Services"
        }
    ],
    "sg:phone":"+1 905 333 3373",
    "sg:postcode":"L7S 1T6",
    "sg:province":"ON",
    "sg:tags":[
        "church"
    ],
    "wof:name":"Living Waters Church Inc",
    "wof:placetype":"venue"
},
  "geometry": {"coordinates":[-79.8118515015,43.3336334229],"type":"Point"}
}