{
  "type": "Feature",
  "properties": {
    "addr:full":"Port Mcneill BC V0N 2R0",
    "addr:postcode":"v0n 2r0",
    "iso:country":"CA",
    "sg:city":"Port Mcneill",
    "sg:classifiers":[
        {
            "category":"Shopping",
            "subcategory":"Gifts & Souvenirs",
            "type":"Retail Goods"
        }
    ],
    "sg:phone":"+1 250 956 3484",
    "sg:postcode":"V0N 2R0",
    "sg:province":"BC",
    "sg:tags":[
        "shop"
    ],
    "wof:name":"East of Java",
    "wof:placetype":"venue"
},
  "geometry": {"coordinates":[-127.08678436300001,50.5895767212],"type":"Point"}
}