{
  "type": "Feature",
  "properties": {
    "iso:country":"CA",
    "sg:address":"12386 224 St",
    "sg:city":"Maple Ridge",
    "sg:classifiers":[
        {
            "category":"Retail",
            "subcategory":"Portrait Studio",
            "type":"Services"
        }
    ],
    "sg:phone":"+1 604 463 3292",
    "sg:postcode":"V2X 6B8",
    "sg:province":"BC",
    "sg:tags":[
        "photographer"
    ],
    "wof:name":"Leonard R Mc Gregor Photo",
    "wof:placetype":"venue"
},
  "geometry": {"coordinates":[-122.601089477,49.2271499634],"type":"Point"}
}