{
  "type": "Feature",
  "properties": {
    "addr:full":"615 Harold Cres Thunder Bay ON P7C 5H6",
    "addr:housenumber":"615",
    "addr:postcode":"p7c 5h6",
    "addr:street":"Harold Cres",
    "iso:country":"CA",
    "sg:address":"615 Harold Cres",
    "sg:city":"Thunder Bay",
    "sg:classifiers":[
        {
            "category":"Food & Beverages",
            "subcategory":"Liquor & Beverages",
            "type":"Retail Goods"
        }
    ],
    "sg:phone":"+1 807 622 9615",
    "sg:postcode":"P7C 5H6",
    "sg:province":"ON",
    "sg:tags":[
        "store"
    ],
    "wof:name":"Liquor Control Board of Ont",
    "wof:placetype":"venue"
},
  "geometry": {"coordinates":[-89.256767,48.392582],"type":"Point"}
}