{
  "type": "Feature",
  "properties": {
    "iso:country":"CA",
    "sg:address":"414 Sixth St",
    "sg:city":"New Westminster",
    "sg:classifiers":[
        {
            "category":"Restaurant",
            "type":"Food & Drink"
        }
    ],
    "sg:phone":"+1 604 521 9804",
    "sg:postcode":"V3L 3B2",
    "sg:province":"BC",
    "wof:name":"Matinee Grill",
    "wof:placetype":"venue"
},
  "geometry": {"coordinates":[-122.917358,49.210564],"type":"Point"}
}