{
  "type": "Feature",
  "properties": {
    "addr:full":"12 Nottinghill Cres London ON N6K 1R1",
    "addr:housenumber":"12",
    "addr:postcode":"n6k 1r1",
    "addr:street":"Nottinghill Cres",
    "iso:country":"CA",
    "sg:address":"12 Nottinghill Cres",
    "sg:city":"London",
    "sg:classifiers":[
        {
            "category":"Restaurant",
            "type":"Food & Drink"
        }
    ],
    "sg:phone":"+1 519 878 0364",
    "sg:postcode":"N6K 1R1",
    "sg:province":"ON",
    "sg:tags":[
        "caterer"
    ],
    "wof:name":"A Hand in the Kitchen",
    "wof:placetype":"venue"
},
  "geometry": {"coordinates":[-81.296379,42.952263],"type":"Point"}
}