{
  "type": "Feature",
  "properties": {
    "addr:full":"2108 10 St NW Calgary AB T2M 3M4",
    "addr:housenumber":"2108",
    "addr:postcode":"t2m 3m4",
    "addr:street":"10 St Nw",
    "iso:country":"CA",
    "sg:address":"2108 10 St NW",
    "sg:city":"Calgary",
    "sg:classifiers":[
        {
            "category":"Social Services",
            "subcategory":"Child Care",
            "type":"Services"
        }
    ],
    "sg:phone":"+1 403 289 8233",
    "sg:postcode":"T2M 3M4",
    "sg:province":"AB",
    "wof:name":"Pleasant Heights After School",
    "wof:placetype":"venue"
},
  "geometry": {"coordinates":[-114.084656,51.071053],"type":"Point"}
}