{
  "type": "Feature",
  "properties": {
    "iso:country":"CA",
    "sg:address":"37 Rte Du President-Kennedy",
    "sg:city":"Levis",
    "sg:classifiers":[
        {
            "category":"Building & Trades",
            "subcategory":"Cleaning & Sanitation",
            "type":"Services"
        }
    ],
    "sg:phone":"+1 418 838 4019",
    "sg:postcode":"G6V 6C3",
    "sg:province":"QC",
    "sg:tags":[
        "house",
        "health",
        "home"
    ],
    "wof:name":"Cooperative DE Svc Rive-Sud",
    "wof:placetype":"venue"
},
  "geometry": {"coordinates":[-71.178917,46.797161],"type":"Point"}
}