{
  "type": "Feature",
  "properties": {
    "addr:full":"5268 Memorial Dr NE Calgary AB T2A 2R1",
    "addr:housenumber":"5268",
    "addr:postcode":"t2a 2r1",
    "addr:street":"Memorial Dr Ne",
    "iso:country":"CA",
    "sg:address":"5268 Memorial Dr NE",
    "sg:city":"Calgary",
    "sg:classifiers":[
        {
            "category":"Restaurant",
            "type":"Food & Drink"
        }
    ],
    "sg:phone":"+1 403 273 9346",
    "sg:postcode":"T2A 2R1",
    "sg:province":"AB",
    "wof:name":"Dover Pizza Steak House & Lng",
    "wof:placetype":"venue"
},
  "geometry": {"coordinates":[-113.95682499999999,51.053364],"type":"Point"}
}