{
  "type": "Feature",
  "properties": {
    "addr:full":"1133 Queen St E Brampton ON L6T 4E2",
    "addr:housenumber":"1133",
    "addr:postcode":"l6t 4e2",
    "addr:street":"Queen St E",
    "iso:country":"CA",
    "sg:address":"1133 Queen St E",
    "sg:city":"Brampton",
    "sg:classifiers":[
        {
            "category":"Organizations",
            "subcategory":"Community Association",
            "type":"Services"
        }
    ],
    "sg:phone":"+1 905 453 1488",
    "sg:postcode":"L6T 4E2",
    "sg:province":"ON",
    "sg:tags":[
        "club"
    ],
    "wof:name":"Royal Canadian Legion Branch",
    "wof:placetype":"venue"
},
  "geometry": {"coordinates":[-79.733604,43.709469],"type":"Point"}
}