{
  "type": "Feature",
  "properties": {
    "addr:full":"1810 Main St W North Bay ON P1B 8G5",
    "addr:housenumber":"1810",
    "addr:postcode":"p1b 8g5",
    "addr:street":"Main St W",
    "iso:country":"CA",
    "sg:address":"1810 Main St W",
    "sg:city":"North Bay",
    "sg:classifiers":[
        {
            "category":"Manufacturing",
            "subcategory":"Metals",
            "type":"Manufacturing & Wholesale Goods"
        }
    ],
    "sg:phone":"+1 705 474 3630",
    "sg:postcode":"P1B 8G5",
    "sg:province":"ON",
    "sg:tags":[
        "plating"
    ],
    "wof:name":"Barrie Hard Chrome Plating",
    "wof:placetype":"venue"
},
  "geometry": {"coordinates":[-79.45993,46.306629],"type":"Point"}
}