{
  "type": "Feature",
  "properties": {
    "addr:full":"5375 Boul Maricourt Saint-Hubert QC J3Y 1S3",
    "addr:housenumber":"5375",
    "addr:postcode":"j3y 1s3",
    "addr:street":"Boul Maricourt",
    "iso:country":"CA",
    "sg:address":"5375 Boul Maricourt",
    "sg:city":"Saint-Hubert",
    "sg:classifiers":[
        {
            "category":"Building & Trades",
            "subcategory":"Construction",
            "type":"Services"
        }
    ],
    "sg:phone":"+1 450 678 1138",
    "sg:postcode":"J3Y 1S3",
    "sg:province":"QC",
    "sg:tags":[
        "concrete",
        "landscape",
        "contractor"
    ],
    "wof:name":"Agrebert Paysagiste Inc",
    "wof:placetype":"venue"
},
  "geometry": {"coordinates":[-73.431061,45.488441],"type":"Point"}
}