{
  "type": "Feature",
  "properties": {
    "addr:full":"900 Boul Cure-Labelle Laval QC H7V 2V5",
    "addr:housenumber":"900",
    "addr:postcode":"h7v 2v5",
    "addr:street":"Boul Cure-Labelle",
    "iso:country":"CA",
    "sg:address":"900 Boul Cure-Labelle",
    "sg:city":"Laval",
    "sg:classifiers":[
        {
            "category":"Recreation",
            "type":"Entertainment"
        }
    ],
    "sg:phone":"+1 450 686 1066",
    "sg:postcode":"H7V 2V5",
    "sg:province":"QC",
    "sg:tags":[
        "bingo",
        "game"
    ],
    "wof:name":"Bingo Recreatheque",
    "wof:placetype":"venue"
},
  "geometry": {"coordinates":[-73.74896240229999,45.5411529541],"type":"Point"}
}