{
  "type": "Feature",
  "properties": {
    "addr:full":"523 W 3rd St Revelstoke BC V0E 2S0",
    "addr:housenumber":"523",
    "addr:postcode":"v0e 2s0",
    "addr:street":"W 3Rd St",
    "iso:country":"CA",
    "sg:address":"523 W 3rd St",
    "sg:city":"Revelstoke",
    "sg:classifiers":[
        {
            "category":"Retail",
            "subcategory":"Repair Shop",
            "type":"Services"
        }
    ],
    "sg:phone":"+1 250 837 2944",
    "sg:postcode":"V0E 2S0",
    "sg:province":"BC",
    "sg:tags":[
        "cleaners",
        "parts",
        "vacuum"
    ],
    "wof:name":"Handyman Vacuum & Sewing Svc",
    "wof:placetype":"venue"
},
  "geometry": {"coordinates":[-118.20130899999999,51.000069],"type":"Point"}
}