{
  "type": "Feature",
  "properties": {
    "iso:country":"CA",
    "sg:address":"867 Rue Rochette",
    "sg:city":"Sainte-Foy",
    "sg:classifiers":[
        {
            "category":"Social Services",
            "type":"Services"
        }
    ],
    "sg:phone":"+1 418 527 3273",
    "sg:postcode":"G1V 2S6",
    "sg:province":"QC",
    "sg:tags":[
        "mission"
    ],
    "wof:name":"Missions Etrangeres",
    "wof:placetype":"venue"
},
  "geometry": {"coordinates":[-71.264511,46.787224],"type":"Point"}
}