{
  "type": "Feature",
  "properties": {
    "iso:country":"CA",
    "sg:address":"16 Rue Du Pere-Divet",
    "sg:city":"Sept-Iles",
    "sg:classifiers":[
        {
            "category":"Shopping",
            "subcategory":"Clothing, Apparel, & Fashions",
            "type":"Retail Goods"
        }
    ],
    "sg:phone":"+1 418 968 3000",
    "sg:postcode":"G4R 5G4",
    "sg:province":"QC",
    "wof:name":"Placard",
    "wof:placetype":"venue"
},
  "geometry": {"coordinates":[-66.387336731,50.2070655823],"type":"Point"}
}