{
  "type": "Feature",
  "properties": {
    "iso:country":"CA",
    "sg:city":"Pointe-Claire",
    "sg:classifiers":[
        {
            "category":"Wholesale",
            "subcategory":"Electrical",
            "type":"Manufacturing & Wholesale Goods"
        }
    ],
    "sg:phone":"+1 514 694 7373",
    "sg:postcode":"H9R 5N4",
    "sg:province":"QC",
    "sg:tags":[
        "equipment",
        "electronic",
        "supply"
    ],
    "wof:name":"Matrix Technologie Ltee",
    "wof:placetype":"venue"
},
  "geometry": {"coordinates":[-73.787895,45.46677],"type":"Point"}
}