{
  "type": "Feature",
  "properties": {
    "addr:full":"Winnipeg MB R3T 4R6",
    "addr:postcode":"r3t 4r6",
    "iso:country":"CA",
    "sg:city":"Winnipeg",
    "sg:classifiers":[
        {
            "category":"Building & Trades",
            "subcategory":"Landscaping Services",
            "type":"Services"
        }
    ],
    "sg:phone":"+1 204 261 4295",
    "sg:postcode":"R3T 4R6",
    "sg:province":"MB",
    "sg:tags":[
        "lawn",
        "contractor",
        "landscape",
        "maintenance",
        "grounds"
    ],
    "wof:name":"Great Plains Lawnscaping",
    "wof:placetype":"venue"
},
  "geometry": {"coordinates":[-97.157188,49.781193],"type":"Point"}
}