{
  "type": "Feature",
  "properties": {
    "addr:full":"Kamloops BC V2C 3J4",
    "addr:postcode":"bc v2c 3j4",
    "iso:country":"CA",
    "sg:city":"Kamloops",
    "sg:classifiers":[
        {
            "category":"Professional",
            "subcategory":"Accounting & Tax Preparation",
            "type":"Services"
        }
    ],
    "sg:phone":"+1 250 374 5577",
    "sg:postcode":"V2C 3J4",
    "sg:province":"BC",
    "sg:tags":[
        "accountant"
    ],
    "wof:name":"Mc Curdy, Maureen CA",
    "wof:placetype":"venue"
},
  "geometry": {"coordinates":[-120.338829041,50.6759910583],"type":"Point"}
}