{
  "type": "Feature",
  "properties": {
    "iso:country":"CA",
    "sg:address":"Farm",
    "sg:city":"Kamsack",
    "sg:classifiers":[
        {
            "category":"Professional",
            "subcategory":"Business Services",
            "type":"Services"
        }
    ],
    "sg:phone":"+1 306 542 3248",
    "sg:postcode":"S0A 1S0",
    "sg:province":"SK",
    "sg:tags":[
        "auctioneer"
    ],
    "wof:name":"Mike Kuzenko Auction Svc Ltd",
    "wof:placetype":"venue"
},
  "geometry": {"coordinates":[-101.903198242,51.5648117065],"type":"Point"}
}