{
  "type": "Feature",
  "properties": {
    "addr:full":"69 Rue DE LA Gauchetiere O Montreal QC H2Z 1C2",
    "addr:housenumber":"69",
    "addr:postcode":"h2z 1c2",
    "addr:street":"Rue De La Gauchetiere O",
    "iso:country":"CA",
    "sg:address":"69 Rue DE LA Gauchetiere O",
    "sg:city":"Montreal",
    "sg:classifiers":[
        {
            "category":"Shopping",
            "subcategory":"Gifts & Souvenirs",
            "type":"Retail Goods"
        }
    ],
    "sg:phone":"+1 514 866 3209",
    "sg:postcode":"H2Z 1C2",
    "sg:province":"QC",
    "sg:tags":[
        "shop"
    ],
    "wof:name":"Centre Du Cadeau Oriental",
    "wof:placetype":"venue"
},
  "geometry": {"coordinates":[-73.559532,45.509037],"type":"Point"}
}