{
  "type": "Feature",
  "properties": {
    "addr:full":"317 Niagara St St Catharines ON L2M 4V9",
    "addr:housenumber":"317",
    "addr:postcode":"l2m 4v9",
    "addr:street":"Niagara St",
    "iso:country":"CA",
    "sg:address":"317 Niagara St",
    "sg:city":"St Catharines",
    "sg:classifiers":[
        {
            "category":"Organizations",
            "subcategory":"Religious Organization",
            "type":"Services"
        }
    ],
    "sg:phone":"+1 905 646 1955",
    "sg:postcode":"L2M 4V9",
    "sg:province":"ON",
    "sg:tags":[
        "church"
    ],
    "wof:name":"Ukrainian Evangelical Baptist",
    "wof:placetype":"venue"
},
  "geometry": {"coordinates":[-79.22672271730001,43.181438446],"type":"Point"}
}