{
  "type": "Feature",
  "properties": {
    "addr:full":"11706 96 Ave Delta BC V4C 3W7",
    "addr:housenumber":"11706",
    "addr:postcode":"v4c 3w7",
    "addr:street":"96 Ave",
    "iso:country":"CA",
    "sg:address":"11706 96 Ave",
    "sg:city":"Delta",
    "sg:classifiers":[
        {
            "category":"Social Services",
            "subcategory":"Child Care",
            "type":"Services"
        }
    ],
    "sg:phone":"+1 604 589 2577",
    "sg:postcode":"V4C 3W7",
    "sg:province":"BC",
    "wof:name":"Small World Preschool",
    "wof:placetype":"venue"
},
  "geometry": {"coordinates":[-122.898285,49.17701],"type":"Point"}
}