{
  "type": "Feature",
  "properties": {
    "addr:full":"9E Rue Paspebiac QC G0C 2K0",
    "addr:postcode":"g0c 2k0",
    "addr:street":"9E Rue Paspebiac",
    "iso:country":"CA",
    "sg:address":"9E Rue",
    "sg:city":"Paspebiac",
    "sg:classifiers":[
        {
            "category":"Recreation",
            "type":"Entertainment"
        }
    ],
    "sg:phone":"+1 418 752 3261",
    "sg:postcode":"G0C 2K0",
    "sg:province":"QC",
    "sg:tags":[
        "center",
        "government"
    ],
    "wof:name":"Arena DE Paspebiac",
    "wof:placetype":"venue"
},
  "geometry": {"coordinates":[-65.262154,48.026878],"type":"Point"}
}