{
  "type": "Feature",
  "properties": {
    "addr:full":"7000 Mcleod Rd # 3 Niagara Falls ON L2G 7K3",
    "addr:housenumber":"7000",
    "addr:postcode":"l2g 7k3",
    "addr:street":"Mcleod Rd # 3",
    "iso:country":"CA",
    "sg:address":"7000 Mcleod Rd # 3",
    "sg:city":"Niagara Falls",
    "sg:classifiers":[
        {
            "category":"Restaurant",
            "type":"Food & Drink"
        }
    ],
    "sg:phone":"+1 905 371 0095",
    "sg:postcode":"L2G 7K3",
    "sg:province":"ON",
    "wof:name":"New Century Chinese Take Out",
    "wof:placetype":"venue"
},
  "geometry": {"coordinates":[-79.1118927002,43.0703125],"type":"Point"}
}