{
  "type": "Feature",
  "properties": {
    "addr:full":"1200 Boul Saint-Felicien # 4933 Saint-Felicien QC G8K 2N6",
    "addr:housenumber":"1200",
    "addr:postcode":"g8k 2n6",
    "addr:street":"Boul Saint-Felicien # 4933 Saint-Felicien",
    "iso:country":"CA",
    "sg:address":"1200 Boul Saint-Felicien # 4933",
    "sg:city":"Saint-Felicien",
    "sg:classifiers":[
        {
            "category":"Food & Beverages",
            "subcategory":"Groceries & Convenience Stores",
            "type":"Retail Goods"
        }
    ],
    "sg:phone":"+1 418 679 1431",
    "sg:postcode":"G8K 2N6",
    "sg:province":"QC",
    "sg:tags":[
        "grocer"
    ],
    "wof:name":"Marche Metro St-Felicien",
    "wof:placetype":"venue"
},
  "geometry": {"coordinates":[-72.4661865234,48.6507263184],"type":"Point"}
}