{
  "type": "Feature",
  "properties": {
    "addr:full":"Belwood ON N0B 1J0",
    "addr:postcode":"n0b 1j0",
    "iso:country":"CA",
    "sg:city":"Belwood",
    "sg:classifiers":[
        {
            "category":"Freight",
            "type":"Transportation"
        }
    ],
    "sg:phone":"+1 519 787 1330",
    "sg:postcode":"N0B 1J0",
    "sg:province":"ON",
    "sg:tags":[
        "trucking"
    ],
    "wof:name":"Compliance Carriers Inc",
    "wof:placetype":"venue"
},
  "geometry": {"coordinates":[-80.289513,43.771099],"type":"Point"}
}