{
  "type": "Feature",
  "properties": {
    "addr:full":"200 Boul Provencher Winnipeg MB R2H 0G3",
    "addr:housenumber":"200",
    "addr:postcode":"r2h 0g3",
    "addr:street":"Boul Provencher",
    "iso:country":"CA",
    "sg:address":"200 Boul Provencher",
    "sg:city":"Winnipeg",
    "sg:classifiers":[
        {
            "category":"Manufacturing",
            "subcategory":"Food",
            "type":"Manufacturing & Wholesale Goods"
        }
    ],
    "sg:phone":"+1 204 257 9681",
    "sg:postcode":"R2H 0G3",
    "sg:province":"MB",
    "sg:tags":[
        "cocoa",
        "chocolate"
    ],
    "wof:name":"Chocolate Affair",
    "wof:placetype":"venue"
},
  "geometry": {"coordinates":[-97.121315,49.892094],"type":"Point"}
}