{
  "type": "Feature",
  "properties": {
    "iso:country":"CA",
    "sg:address":"2304 Rang Saint-Pierre",
    "sg:city":"Chicoutimi",
    "sg:classifiers":[
        {
            "category":"Building & Trades",
            "subcategory":"Cleaning & Sanitation",
            "type":"Services"
        }
    ],
    "sg:phone":"+1 418 549 7606",
    "sg:postcode":"G7H 5B3",
    "sg:province":"QC",
    "sg:tags":[
        "snow",
        "removal"
    ],
    "wof:name":"Deneigement Robin Morin",
    "wof:placetype":"venue"
},
  "geometry": {"coordinates":[-71.1321258545,48.3862609863],"type":"Point"}
}