{
  "type": "Feature",
  "properties": {
    "addr:full":"1057 Merivale Rd Ottawa ON K1Z 6A9",
    "addr:housenumber":"1057",
    "addr:postcode":"k1z 6a9",
    "addr:street":"Merivale Rd",
    "iso:country":"CA",
    "sg:address":"1057 Merivale Rd",
    "sg:city":"Ottawa",
    "sg:classifiers":[
        {
            "category":"Travel",
            "subcategory":"Hotels & Motels",
            "type":"Entertainment"
        }
    ],
    "sg:phone":"+1 613 792 4949",
    "sg:postcode":"K1Z 6A9",
    "sg:province":"ON",
    "sg:tags":[
        "breakfast",
        "accommodation",
        "bed"
    ],
    "wof:name":"Cardinal Suites Inc",
    "wof:placetype":"venue"
},
  "geometry": {"coordinates":[-75.7332458496,45.3782958984],"type":"Point"}
}