{
  "type": "Feature",
  "properties": {
    "addr:full":"Bellis AB T0A 0J0",
    "addr:postcode":"t0a 0j0",
    "iso:country":"CA",
    "sg:city":"Bellis",
    "sg:classifiers":[
        {
            "category":"Shopping",
            "subcategory":"Used Merchandise",
            "type":"Retail Goods"
        }
    ],
    "sg:phone":"+1 780 636 3930",
    "sg:postcode":"T0A 0J0",
    "sg:province":"AB",
    "sg:tags":[
        "antique"
    ],
    "wof:name":"Heritage Corner Shoppe",
    "wof:placetype":"venue"
},
  "geometry": {"coordinates":[-112.151146,54.132633],"type":"Point"}
}