{
  "type": "Feature",
  "properties": {
    "addr:full":"2491 Lyons Brook Rd Rte 376 Pictou NS B0K 1H0",
    "addr:housenumber":"2491",
    "addr:postcode":"b0k 1h0",
    "addr:street":"Lyons Brook Rd Rte 376",
    "iso:country":"CA",
    "sg:address":"2491 Lyons Brook Rd Rte 376",
    "sg:city":"Pictou",
    "sg:classifiers":[
        {
            "category":"Personal",
            "subcategory":"Beauty Salon",
            "type":"Services"
        }
    ],
    "sg:phone":"+1 902 485 6040",
    "sg:postcode":"B0K 1H0",
    "sg:province":"NS",
    "wof:name":"Millie's Beauty Salon",
    "wof:placetype":"venue"
},
  "geometry": {"coordinates":[-62.7070732117,45.6781806946],"type":"Point"}
}