{
  "type": "Feature",
  "properties": {
    "addr:full":"2103 Boul Marcel-Laurin Saint-Laurent QC H4R 1K4",
    "addr:housenumber":"2103",
    "addr:postcode":"h4r 1k4",
    "addr:street":"Boul Marcel-Laurin",
    "iso:country":"CA",
    "sg:address":"2103 Boul Marcel-Laurin",
    "sg:city":"Saint-Laurent",
    "sg:classifiers":[
        {
            "category":"Real Estate",
            "subcategory":"Real Estate Operator",
            "type":"Services"
        }
    ],
    "sg:phone":"+1 514 336 9747",
    "sg:postcode":"H4R 1K4",
    "sg:province":"QC",
    "sg:tags":[
        "mall",
        "shopping",
        "center"
    ],
    "wof:name":"Galeries Saint Laurent",
    "wof:placetype":"venue"
},
  "geometry": {"coordinates":[-73.70219400000001,45.519073],"type":"Point"}
}