{
  "type": "Feature",
  "properties": {
    "addr:full":"2073 1st Ave Prince George BC V2L 2Z1",
    "addr:housenumber":"2073",
    "addr:postcode":"v2l 2z1",
    "addr:street":"1St Ave",
    "iso:country":"CA",
    "sg:address":"2073 1st Ave",
    "sg:city":"Prince George",
    "sg:classifiers":[
        {
            "category":"Building & Trades",
            "subcategory":"Equipment Rental",
            "type":"Services"
        }
    ],
    "sg:phone":"+1 250 564 3111",
    "sg:postcode":"V2L 2Z1",
    "sg:province":"BC",
    "wof:name":"United Rentals",
    "wof:placetype":"venue"
},
  "geometry": {"coordinates":[-122.761955,53.923771],"type":"Point"}
}