{
  "type": "Feature",
  "properties": {
    "iso:country":"CA",
    "sg:address":"700 the Queensway S",
    "sg:city":"Keswick",
    "sg:classifiers":[
        {
            "category":"Restaurant",
            "type":"Food & Drink"
        }
    ],
    "sg:phone":"+1 905 989 1900",
    "sg:postcode":"L4P 3G8",
    "sg:province":"ON",
    "wof:name":"Hero's",
    "wof:placetype":"venue"
},
  "geometry": {"coordinates":[-79.4657363892,44.1980361938],"type":"Point"}
}