{
  "type": "Feature",
  "properties": {
    "iso:country":"CA",
    "sg:address":"116 Boul Inter-Provinciale",
    "sg:city":"Pointe-A-LA-Croix",
    "sg:classifiers":[
        {
            "category":"Retail",
            "subcategory":"Auto Repair",
            "type":"Services"
        }
    ],
    "sg:phone":"+1 418 788 5000",
    "sg:postcode":"G0C 1L0",
    "sg:province":"QC",
    "sg:tags":[
        "repairing",
        "automobile"
    ],
    "wof:name":"Gareage Sdr Inc",
    "wof:placetype":"venue"
},
  "geometry": {"coordinates":[-66.6986236572,48.025302887],"type":"Point"}
}