{
  "type": "Feature",
  "properties": {
    "addr:full":"433 Main St Powassan ON P0H 1Z0",
    "addr:housenumber":"433",
    "addr:postcode":"p0h 1z0",
    "addr:street":"Main St",
    "iso:country":"CA",
    "sg:address":"433 Main St",
    "sg:city":"Powassan",
    "sg:classifiers":[
        {
            "category":"Government",
            "subcategory":"Office",
            "type":"Public Place"
        }
    ],
    "sg:phone":"+1 705 724 2537",
    "sg:postcode":"P0H 1Z0",
    "sg:province":"ON",
    "sg:tags":[
        "provincial",
        "parks",
        "village"
    ],
    "wof:name":"Powassan Sportsplex",
    "wof:placetype":"venue"
},
  "geometry": {"coordinates":[-79.36251799999999,46.083485],"type":"Point"}
}