{
  "type": "Feature",
  "properties": {
    "addr:full":"16 Rue Du Saint-Laurent Varennes QC J3X 2A3",
    "addr:housenumber":"16",
    "addr:postcode":"j3x 2a3",
    "addr:street":"Rue Du Saint-Laurent",
    "iso:country":"CA",
    "sg:address":"16 Rue Du Saint-Laurent",
    "sg:city":"Varennes",
    "sg:classifiers":[
        {
            "category":"Manufacturing",
            "subcategory":"Tools & Machinery",
            "type":"Manufacturing & Wholesale Goods"
        }
    ],
    "sg:phone":"+1 450 652 2981",
    "sg:postcode":"J3X 2A3",
    "sg:province":"QC",
    "sg:tags":[
        "machine",
        "shop"
    ],
    "wof:name":"Industries Varennes Inc",
    "wof:placetype":"venue"
},
  "geometry": {"coordinates":[-73.435867,45.670345],"type":"Point"}
}