{
  "type": "Feature",
  "properties": {
    "iso:country":"CA",
    "sg:address":"1777 Victoria Ave",
    "sg:city":"Regina",
    "sg:classifiers":[
        {
            "category":"Mining & Drilling",
            "type":"Manufacturing & Wholesale Goods"
        }
    ],
    "sg:phone":"+1 306 781 8200",
    "sg:postcode":"S4P 3C4",
    "sg:province":"SK",
    "sg:tags":[
        "development",
        "gas",
        "oil",
        "exploration"
    ],
    "wof:name":"Nexen Canada Ltd",
    "wof:placetype":"venue"
},
  "geometry": {"coordinates":[-104.605918884,50.4469718933],"type":"Point"}
}