{
  "type": "Feature",
  "properties": {
    "addr:full":"2324 Munroe Ave S Saskatoon SK S7J 1S5",
    "addr:housenumber":"2324",
    "addr:postcode":"s7j 1s5",
    "addr:street":"Munroe Ave S",
    "iso:country":"CA",
    "sg:address":"2324 Munroe Ave S",
    "sg:city":"Saskatoon",
    "sg:classifiers":[
        {
            "category":"Professional",
            "subcategory":"Engineering",
            "type":"Services"
        }
    ],
    "sg:phone":"+1 306 244 8805",
    "sg:postcode":"S7J 1S5",
    "sg:province":"SK",
    "sg:tags":[
        "engineer"
    ],
    "wof:name":"Indexel Engineering",
    "wof:placetype":"venue"
},
  "geometry": {"coordinates":[-106.641434,52.101418],"type":"Point"}
}