{
  "type": "Feature",
  "properties": {
    "addr:full":"6900 Airport Rd # 2 Mississauga ON L4V 1E8",
    "addr:housenumber":"6900",
    "addr:postcode":"l4v 1e8",
    "addr:street":"Airport Rd # 2",
    "iso:country":"CA",
    "sg:address":"6900 Airport Rd # 2",
    "sg:city":"Mississauga",
    "sg:classifiers":[
        {
            "category":"Professional",
            "subcategory":"Business Services",
            "type":"Services"
        }
    ],
    "sg:phone":"+1 905 676 1061",
    "sg:postcode":"L4V 1E8",
    "sg:province":"ON",
    "sg:tags":[
        "convention",
        "meeting",
        "facility"
    ],
    "wof:name":"Sodexho",
    "wof:placetype":"venue"
},
  "geometry": {"coordinates":[-79.63806200000001,43.700108],"type":"Point"}
}