{
  "type": "Feature",
  "properties": {
    "iso:country":"CA",
    "sg:address":"3104 30 Ave",
    "sg:city":"Vernon",
    "sg:classifiers":[
        {
            "category":"Wholesale",
            "subcategory":"Machinery & Supplies",
            "type":"Manufacturing & Wholesale Goods"
        }
    ],
    "sg:phone":"+1 250 549 7100",
    "sg:postcode":"V1T 9M9",
    "sg:province":"BC",
    "sg:tags":[
        "contractor"
    ],
    "wof:name":"Paragon Hawk Sales Ltd",
    "wof:placetype":"venue"
},
  "geometry": {"coordinates":[-119.272453308,50.2636451721],"type":"Point"}
}