{
  "type": "Feature",
  "properties": {
    "iso:country":"CA",
    "sg:address":"2101 Aldersbrook Rd",
    "sg:city":"London",
    "sg:classifiers":[
        {
            "category":"Restaurant",
            "type":"Food & Drink"
        }
    ],
    "sg:phone":"+1 519 473 4633",
    "sg:postcode":"N6G 3X1",
    "sg:province":"ON",
    "wof:name":"Wong's Garden",
    "wof:placetype":"venue"
},
  "geometry": {"coordinates":[-81.311874,43.015995],"type":"Point"}
}