{
  "type": "Feature",
  "properties": {
    "addr:full":"32 Rue Principale N Sutton QC J0E 2K0",
    "addr:housenumber":"32",
    "addr:postcode":"j0e 2k0",
    "addr:street":"Rue Principale N",
    "iso:country":"CA",
    "sg:address":"32 Rue Principale N",
    "sg:city":"Sutton",
    "sg:classifiers":[
        {
            "category":"Restaurant",
            "type":"Food & Drink"
        }
    ],
    "sg:phone":"+1 450 538 3311",
    "sg:postcode":"J0E 2K0",
    "sg:province":"QC",
    "wof:name":"Cantine Route 139",
    "wof:placetype":"venue"
},
  "geometry": {"coordinates":[-72.616409,45.108711],"type":"Point"}
}