{
  "type": "Feature",
  "properties": {
    "iso:country":"CA",
    "sg:address":"564 Bronson Ave",
    "sg:city":"Ottawa",
    "sg:classifiers":[
        {
            "category":"Restaurant",
            "type":"Food & Drink"
        }
    ],
    "sg:phone":"+1 613 230 6727",
    "sg:postcode":"K1R 6K3",
    "sg:province":"ON",
    "wof:name":"Harvey's",
    "wof:placetype":"venue"
},
  "geometry": {"coordinates":[-75.70259094239999,45.4056625366],"type":"Point"}
}