{
  "type": "Feature",
  "properties": {
    "addr:full":"3633 Dundas St W York ON M6S 2T2",
    "addr:housenumber":"3633",
    "addr:postcode":"m6s 2t2",
    "addr:street":"Dundas St W",
    "iso:country":"CA",
    "sg:address":"3633 Dundas St W",
    "sg:city":"York",
    "sg:classifiers":[
        {
            "category":"Personal",
            "subcategory":"Massage",
            "type":"Services"
        }
    ],
    "sg:phone":"+1 416 760 8555",
    "sg:postcode":"M6S 2T2",
    "sg:province":"ON",
    "wof:name":"A & R Massage Studio",
    "wof:placetype":"venue"
},
  "geometry": {"coordinates":[-79.505661,43.66275],"type":"Point"}
}