{
  "type": "Feature",
  "properties": {
    "addr:full":"Fort St James BC V0J 1P0",
    "addr:postcode":"v0j 1p0",
    "addr:street":"Fort St",
    "iso:country":"CA",
    "sg:city":"Fort St James",
    "sg:classifiers":[
        {
            "category":"Retail",
            "subcategory":"Auto Repair",
            "type":"Services"
        }
    ],
    "sg:phone":"+1 250 996 0108",
    "sg:postcode":"V0J 1P0",
    "sg:province":"BC",
    "sg:tags":[
        "repairing",
        "snowmobile"
    ],
    "wof:name":"Spatsizi Outdoor Specialists",
    "wof:placetype":"venue"
},
  "geometry": {"coordinates":[-124.250992,54.441624],"type":"Point"}
}