{
  "type": "Feature",
  "properties": {
    "iso:country":"CA",
    "sg:address":"3400 2E Rue",
    "sg:city":"Saint-Hubert",
    "sg:classifiers":[
        {
            "category":"Shopping",
            "type":"Retail Goods"
        }
    ],
    "sg:phone":"+1 450 676 0223",
    "sg:postcode":"J3Y 8Y7",
    "sg:province":"QC",
    "sg:tags":[
        "dry",
        "ice"
    ],
    "wof:name":"Praxair Canada Inc",
    "wof:placetype":"venue"
},
  "geometry": {"coordinates":[-73.388626,45.475731],"type":"Point"}
}