{
  "type": "Feature",
  "properties": {
    "addr:full":"8851 5E Croissant Anjou QC H1J 1A3",
    "addr:housenumber":"8851",
    "addr:postcode":"h1j 1a3",
    "addr:street":"5E Croissant",
    "iso:country":"CA",
    "sg:address":"8851 5E Croissant",
    "sg:city":"Anjou",
    "sg:classifiers":[
        {
            "category":"Retail",
            "subcategory":"Car Wash",
            "type":"Services"
        }
    ],
    "sg:phone":"+1 514 353 8265",
    "sg:postcode":"H1J 1A3",
    "sg:province":"QC",
    "sg:tags":[
        "polishing",
        "truck",
        "washing"
    ],
    "wof:name":"Lavage-Camion Citerne Unvrsl",
    "wof:placetype":"venue"
},
  "geometry": {"coordinates":[-73.55842590330001,45.6016464233],"type":"Point"}
}