{
  "type": "Feature",
  "properties": {
    "iso:country":"CA",
    "sg:address":"317 Roncesvalles Ave",
    "sg:city":"Toronto",
    "sg:classifiers":[
        {
            "category":"Restaurant",
            "type":"Food & Drink"
        }
    ],
    "sg:phone":"+1 416 530 0303",
    "sg:postcode":"M6R 2M6",
    "sg:province":"ON",
    "wof:name":"Zagloba Restaurant",
    "wof:placetype":"venue"
},
  "geometry": {"coordinates":[-79.44970703120001,43.6485328674],"type":"Point"}
}