{
  "type": "Feature",
  "properties": {
    "addr:full":"133 Matheson Ave E # 208 Winnipeg MB R2W 5M7",
    "addr:housenumber":"133",
    "addr:postcode":"r2w 5m7",
    "addr:street":"Matheson Ave E # 208",
    "iso:country":"CA",
    "sg:address":"133 Matheson Ave E # 208",
    "sg:city":"Winnipeg",
    "sg:classifiers":[
        {
            "category":"Real Estate",
            "subcategory":"Real Estate Agent",
            "type":"Services"
        }
    ],
    "sg:phone":"+1 204 586 6683",
    "sg:postcode":"R2W 5M7",
    "sg:province":"MB",
    "sg:tags":[
        "housing"
    ],
    "wof:name":"Rosh Piona Housing CO-OP",
    "wof:placetype":"venue"
},
  "geometry": {"coordinates":[-97.118439,49.927925],"type":"Point"}
}