{
  "type": "Feature",
  "properties": {
    "addr:full":"48075 Trans-Canada Hwy Boston Bar BC V0K 1C0",
    "addr:housenumber":"48075",
    "addr:postcode":"v0k 1c0",
    "addr:street":"Trans-Canada Hwy",
    "iso:country":"CA",
    "sg:address":"48075 Trans-Canada Hwy",
    "sg:city":"Boston Bar",
    "sg:classifiers":[
        {
            "category":"Retail",
            "subcategory":"Auto Repair",
            "type":"Services"
        }
    ],
    "sg:phone":"+1 604 867 9614",
    "sg:postcode":"V0K 1C0",
    "sg:province":"BC",
    "sg:tags":[
        "repairing",
        "automobile",
        "wrecker"
    ],
    "wof:name":"Boston Bar Svc Ltd",
    "wof:placetype":"venue"
},
  "geometry": {"coordinates":[-121.44194793699999,49.8657493591],"type":"Point"}
}