{
  "type": "Feature",
  "properties": {
    "addr:full":"3551 Granville Ave Richmond BC V7C 1C8",
    "addr:housenumber":"3551",
    "addr:postcode":"v7c 1c8",
    "addr:street":"Granville Ave",
    "iso:country":"CA",
    "sg:address":"3551 Granville Ave",
    "sg:city":"Richmond",
    "sg:classifiers":[
        {
            "category":"Recreation",
            "type":"Entertainment"
        }
    ],
    "sg:phone":"+1 604 277 1101",
    "sg:postcode":"V7C 1C8",
    "sg:province":"BC",
    "sg:tags":[
        "course",
        "golf"
    ],
    "wof:name":"Quilchena Golf & Country Club",
    "wof:placetype":"venue"
},
  "geometry": {"coordinates":[-123.187218,49.162949],"type":"Point"}
}