{
  "type": "Feature",
  "properties": {
    "iso:country":"CA",
    "sg:address":"85 Foxbend Cres N # 1",
    "sg:city":"Lethbridge",
    "sg:classifiers":[
        {
            "category":"Real Estate",
            "subcategory":"Real Estate Operator",
            "type":"Services"
        }
    ],
    "sg:phone":"+1 403 320 9410",
    "sg:postcode":"T1H 5T4",
    "sg:province":"AB",
    "sg:tags":[
        "apartment"
    ],
    "wof:name":"Uplands Manor",
    "wof:placetype":"venue"
},
  "geometry": {"coordinates":[-112.81387329099999,49.7276916504],"type":"Point"}
}