{
  "type": "Feature",
  "properties": {
    "addr:full":"7640 Boul Sainte-Anne E Chateau-Richer QC G0A 1N0",
    "addr:housenumber":"7640",
    "addr:postcode":"g0a 1n0",
    "addr:street":"Boul Sainte-Anne E Chateau-Richer",
    "iso:country":"CA",
    "sg:address":"7640 Boul Sainte-Anne E",
    "sg:city":"Chateau-Richer",
    "sg:classifiers":[
        {
            "category":"Manufacturing",
            "subcategory":"Metals",
            "type":"Manufacturing & Wholesale Goods"
        }
    ],
    "sg:phone":"+1 418 824 3342",
    "sg:postcode":"G0A 1N0",
    "sg:province":"QC",
    "sg:tags":[
        "solder"
    ],
    "wof:name":"Entreprises Marc St-Hilaire",
    "wof:placetype":"venue"
},
  "geometry": {"coordinates":[-71.03357699999999,46.959091],"type":"Point"}
}