{
  "type": "Feature",
  "properties": {
    "addr:full":"Surrey BC V4P 3K1",
    "addr:postcode":"v4p 3k1",
    "iso:country":"CA",
    "sg:city":"Surrey",
    "sg:classifiers":[
        {
            "category":"Shopping",
            "subcategory":"Jewelry",
            "type":"Retail Goods"
        }
    ],
    "sg:phone":"+1 604 536 4348",
    "sg:postcode":"V4P 3K1",
    "sg:province":"BC",
    "sg:tags":[
        "designer"
    ],
    "wof:name":"Murdoch Jewellers",
    "wof:placetype":"venue"
},
  "geometry": {"coordinates":[-122.801346,49.056671],"type":"Point"}
}