{
  "type": "Feature",
  "properties": {
    "addr:full":"SW 24 16 17W Minnedosa MB R0J 1E0",
    "addr:housenumber":"16 17w minnedosa",
    "addr:postcode":"r0j 1e0",
    "addr:street":"Sw 24",
    "iso:country":"CA",
    "sg:address":"SW 24 16 17W",
    "sg:city":"Minnedosa",
    "sg:classifiers":[
        {
            "category":"Manufacturing",
            "subcategory":"Metals",
            "type":"Manufacturing & Wholesale Goods"
        }
    ],
    "sg:phone":"+1 204 865 2373",
    "sg:postcode":"R0J 1E0",
    "sg:province":"MB",
    "sg:tags":[
        "steel"
    ],
    "wof:name":"Uplands Manufacturing",
    "wof:placetype":"venue"
},
  "geometry": {"coordinates":[-99.8386230469,50.2470207214],"type":"Point"}
}