{
  "type": "Feature",
  "properties": {
    "addr:full":"200 Cranbrook Dr Hamilton ON L9C 4S9",
    "addr:housenumber":"200",
    "addr:postcode":"l9c 4s9",
    "addr:street":"Cranbrook Dr",
    "iso:country":"CA",
    "sg:address":"200 Cranbrook Dr",
    "sg:city":"Hamilton",
    "sg:classifiers":[
        {
            "category":"Education",
            "subcategory":"School",
            "type":"Public Place"
        }
    ],
    "sg:phone":"+1 905 387 3350",
    "sg:postcode":"L9C 4S9",
    "sg:province":"ON",
    "wof:name":"R A Riddell School",
    "wof:placetype":"venue"
},
  "geometry": {"coordinates":[-79.909958,43.221462],"type":"Point"}
}