{
  "type": "Feature",
  "properties": {
    "iso:country":"CA",
    "sg:address":"430 Main St",
    "sg:city":"Creighton",
    "sg:classifiers":[
        {
            "category":"Professional",
            "subcategory":"Management & Consulting",
            "type":"Services"
        }
    ],
    "sg:phone":"+1 306 688 2122",
    "sg:postcode":"S0P 0A0",
    "sg:province":"SK",
    "sg:tags":[
        "consultant",
        "recreation",
        "program"
    ],
    "wof:name":"Neyanun Regional Rec Auth Inc",
    "wof:placetype":"venue"
},
  "geometry": {"coordinates":[-101.899665833,54.7572059631],"type":"Point"}
}