{
  "type": "Feature",
  "properties": {
    "addr:full":"1296 Barton St E Hamilton ON L8H 2W1",
    "addr:housenumber":"1296",
    "addr:postcode":"l8h 2w1",
    "addr:street":"Barton St E",
    "iso:country":"CA",
    "sg:address":"1296 Barton St E",
    "sg:city":"Hamilton",
    "sg:classifiers":[
        {
            "category":"Retail",
            "subcategory":"Auto Repair",
            "type":"Services"
        }
    ],
    "sg:phone":"+1 905 547 1948",
    "sg:postcode":"L8H 2W1",
    "sg:province":"ON",
    "sg:tags":[
        "repairing",
        "automobile"
    ],
    "wof:name":"Midas Auto Svc Experts",
    "wof:placetype":"venue"
},
  "geometry": {"coordinates":[-79.8074645996,43.2493438721],"type":"Point"}
}