{
  "type": "Feature",
  "properties": {
    "addr:full":"PO Box 131 Seven Persons AB T0K 1Z0",
    "addr:housenumber":"po;131",
    "addr:postcode":"t0k 1z0",
    "addr:street":"Box;Seven",
    "iso:country":"CA",
    "sg:address":"PO Box 131",
    "sg:city":"Seven Persons",
    "sg:classifiers":[
        {
            "category":"Professional",
            "subcategory":"Business Services",
            "type":"Services"
        }
    ],
    "sg:phone":"+1 403 832 2117",
    "sg:postcode":"T0K 1Z0",
    "sg:province":"AB",
    "sg:tags":[
        "water",
        "hauling"
    ],
    "wof:name":"Simon Hammel Water Hauling",
    "wof:placetype":"venue"
},
  "geometry": {"coordinates":[-110.91289520300001,49.8762054443],"type":"Point"}
}