{
  "type": "Feature",
  "properties": {
    "addr:full":"1588 Dundas St W Toronto ON M6K 1T8",
    "addr:housenumber":"1588",
    "addr:postcode":"m6k 1t8",
    "addr:street":"Dundas St W",
    "iso:country":"CA",
    "sg:address":"1588 Dundas St W",
    "sg:city":"Toronto",
    "sg:classifiers":[
        {
            "category":"Insurance",
            "subcategory":"Insurance Agent",
            "type":"Services"
        }
    ],
    "sg:phone":"+1 416 531 1146",
    "sg:postcode":"M6K 1T8",
    "sg:province":"ON",
    "wof:name":"Vieira Insurance",
    "wof:placetype":"venue"
},
  "geometry": {"coordinates":[-79.434753,43.649971],"type":"Point"}
}