{
  "type": "Feature",
  "properties": {
    "addr:full":"Saint-Pierre-DE-Lamy QC G0L 4B0",
    "addr:postcode":"g0l 4b0",
    "iso:country":"CA",
    "sg:city":"Saint-Pierre-DE-Lamy",
    "sg:classifiers":[
        {
            "category":"Manufacturing",
            "subcategory":"Lumber",
            "type":"Manufacturing & Wholesale Goods"
        }
    ],
    "sg:phone":"+1 418 497 1935",
    "sg:postcode":"G0L 4B0",
    "sg:province":"QC",
    "sg:tags":[
        "syrup",
        "maple",
        "sugar"
    ],
    "wof:name":"Erabliere LA Coulee Doree",
    "wof:placetype":"venue"
},
  "geometry": {"coordinates":[-69.0272979736,47.7902488708],"type":"Point"}
}