{
  "type": "Feature",
  "properties": {
    "addr:full":"1526 Fletcher Rd Saskatoon SK S7M 5M1",
    "addr:housenumber":"1526",
    "addr:postcode":"s7m 5m1",
    "addr:street":"Fletcher Rd",
    "iso:country":"CA",
    "sg:address":"1526 Fletcher Rd",
    "sg:city":"Saskatoon",
    "sg:classifiers":[
        {
            "category":"Organizations",
            "subcategory":"Labor Organization",
            "type":"Services"
        }
    ],
    "sg:phone":"+1 306 384 5787",
    "sg:postcode":"S7M 5M1",
    "sg:province":"SK",
    "wof:name":"United Food & Coml Workers Un",
    "wof:placetype":"venue"
},
  "geometry": {"coordinates":[-106.713859558,52.1083183289],"type":"Point"}
}