{
  "type": "Feature",
  "properties": {
    "addr:full":"6 Antares Dr #10B Nepean ON K2E 8A9",
    "addr:housenumber":"6;10b",
    "addr:postcode":"k2e 8a9",
    "addr:street":"Antares Dr #",
    "iso:country":"CA",
    "sg:address":"6 Antares Dr #10B",
    "sg:city":"Nepean",
    "sg:classifiers":[
        {
            "category":"Food & Beverages",
            "subcategory":"Specialty",
            "type":"Retail Goods"
        }
    ],
    "sg:phone":"+1 613 225 7873",
    "sg:postcode":"K2E 8A9",
    "sg:province":"ON",
    "sg:tags":[
        "water",
        "bulk",
        "company"
    ],
    "wof:name":"Bytown Pure Water CO",
    "wof:placetype":"venue"
},
  "geometry": {"coordinates":[-75.70594,45.335701],"type":"Point"}
}