{
  "type": "Feature",
  "properties": {
    "iso:country":"CA",
    "sg:address":"597 3rd Ave",
    "sg:city":"Prince George",
    "sg:classifiers":[
        {
            "category":"Manufacturing",
            "subcategory":"Furniture",
            "type":"Manufacturing & Wholesale Goods"
        }
    ],
    "sg:phone":"+1 250 561 1442",
    "sg:postcode":"V2L 3C2",
    "sg:province":"BC",
    "sg:tags":[
        "equipment",
        "work",
        "sheet",
        "metal",
        "contractor"
    ],
    "wof:name":"Desjardines Associates",
    "wof:placetype":"venue"
},
  "geometry": {"coordinates":[-122.73475646999999,53.9136962891],"type":"Point"}
}