{
  "type": "Feature",
  "properties": {
    "addr:full":"52 Wellington St Paris ON N3L 1T4",
    "addr:housenumber":"52",
    "addr:postcode":"n3l 1t4",
    "addr:street":"Wellington St",
    "iso:country":"CA",
    "sg:address":"52 Wellington St",
    "sg:city":"Paris",
    "sg:classifiers":[
        {
            "category":"Building & Trades",
            "subcategory":"Landscaping Services",
            "type":"Services"
        }
    ],
    "sg:phone":"+1 519 442 3662",
    "sg:postcode":"N3L 1T4",
    "sg:province":"ON",
    "sg:tags":[
        "tree"
    ],
    "wof:name":"Affordable Tree Removal",
    "wof:placetype":"venue"
},
  "geometry": {"coordinates":[-80.39999389650001,43.202545166],"type":"Point"}
}