{
  "type": "Feature",
  "properties": {
    "addr:full":"Brantford ON N3S 2A7",
    "addr:postcode":"n3s 2a7",
    "iso:country":"CA",
    "sg:city":"Brantford",
    "sg:classifiers":[
        {
            "category":"Social Services",
            "type":"Services"
        }
    ],
    "sg:phone":"+1 519 751 3915",
    "sg:postcode":"N3S 2A7",
    "sg:province":"ON",
    "sg:tags":[
        "organization",
        "welfare"
    ],
    "wof:name":"Stepping Stones Resource Ctr",
    "wof:placetype":"venue"
},
  "geometry": {"coordinates":[-80.261719,43.124699],"type":"Point"}
}