{
  "type": "Feature",
  "properties": {
    "addr:full":"425 Donlands Ave East York ON M4J 3S2",
    "addr:housenumber":"425",
    "addr:postcode":"m4j 3s2",
    "addr:street":"Donlands Ave",
    "iso:country":"CA",
    "sg:address":"425 Donlands Ave",
    "sg:city":"East York",
    "sg:classifiers":[
        {
            "category":"Building & Trades",
            "subcategory":"Construction",
            "type":"Services"
        }
    ],
    "sg:phone":"+1 416 425 4120",
    "sg:postcode":"M4J 3S2",
    "sg:province":"ON",
    "sg:tags":[
        "paint",
        "painter"
    ],
    "wof:name":"Continent Paint & Wallpaper",
    "wof:placetype":"venue"
},
  "geometry": {"coordinates":[-79.34281900000001,43.694489],"type":"Point"}
}