{
  "type": "Feature",
  "properties": {
    "addr:full":"99 Wellington Cres #101 Winnipeg MB R3M 0A2",
    "addr:housenumber":"99",
    "addr:postcode":"r3m 0a2",
    "addr:street":"Wellington Cres # 101",
    "iso:country":"CA",
    "sg:address":"99 Wellington Cres #101",
    "sg:city":"Winnipeg",
    "sg:classifiers":[
        {
            "category":"Real Estate",
            "subcategory":"Real Estate Operator",
            "type":"Services"
        }
    ],
    "sg:phone":"+1 204 474 1215",
    "sg:postcode":"R3M 0A2",
    "sg:province":"MB",
    "sg:tags":[
        "apartment"
    ],
    "wof:name":"Edinburgh House",
    "wof:placetype":"venue"
},
  "geometry": {"coordinates":[-97.1512374878,49.8765220642],"type":"Point"}
}