{
  "type": "Feature",
  "properties": {
    "addr:full":"Abbotsford BC V2T 3R5",
    "addr:postcode":"v2t 3r5",
    "iso:country":"CA",
    "sg:city":"Abbotsford",
    "sg:classifiers":[
        {
            "category":"Retail",
            "subcategory":"Auto Repair",
            "type":"Services"
        }
    ],
    "sg:phone":"+1 604 852 4667",
    "sg:postcode":"V2T 3R5",
    "sg:province":"BC",
    "sg:tags":[
        "repairing",
        "automobile",
        "wheel",
        "alignment"
    ],
    "wof:name":"Rpm Alignment & Repairs",
    "wof:placetype":"venue"
},
  "geometry": {"coordinates":[-122.321281433,49.0524902344],"type":"Point"}
}