{
  "type": "Feature",
  "properties": {
    "addr:full":"230 Manitoba St Bracebridge ON P1L 2E1",
    "addr:housenumber":"230",
    "addr:postcode":"p1l 2e1",
    "addr:street":"Manitoba St",
    "iso:country":"CA",
    "sg:address":"230 Manitoba St",
    "sg:city":"Bracebridge",
    "sg:classifiers":[
        {
            "category":"Health Services",
            "subcategory":"Doctor",
            "type":"Services"
        }
    ],
    "sg:phone":"+1 705 646 7634",
    "sg:postcode":"P1L 2E1",
    "sg:province":"ON",
    "sg:tags":[
        "physician",
        "surgeon"
    ],
    "wof:name":"South Muskoka Medical Ctr",
    "wof:placetype":"venue"
},
  "geometry": {"coordinates":[-79.31787109379999,45.044670105],"type":"Point"}
}