{
  "type": "Feature",
  "properties": {
    "addr:full":"118 Rue Saint-Laurent Saint-Eustache QC J7P 5G1",
    "addr:housenumber":"118",
    "addr:postcode":"j7p 5g1",
    "addr:street":"Rue Saint-Laurent",
    "iso:country":"CA",
    "sg:address":"118 Rue Saint-Laurent",
    "sg:city":"Saint-Eustache",
    "sg:classifiers":[
        {
            "category":"Shopping",
            "subcategory":"Computers & Home Electronics",
            "type":"Retail Goods"
        }
    ],
    "sg:phone":"+1 450 491 5928",
    "sg:postcode":"J7P 5G1",
    "sg:province":"QC",
    "sg:tags":[
        "equipment",
        "dealer"
    ],
    "wof:name":"C & E Informatique Inc",
    "wof:placetype":"venue"
},
  "geometry": {"coordinates":[-73.8857116699,45.5684280396],"type":"Point"}
}