{
  "type": "Feature",
  "properties": {
    "addr:full":"Wolfe Island ON K0H 2Y0",
    "addr:postcode":"k0h 2y0",
    "iso:country":"CA",
    "sg:city":"Wolfe Island",
    "sg:classifiers":[
        {
            "category":"Freight",
            "type":"Transportation"
        }
    ],
    "sg:phone":"+1 613 385 2370",
    "sg:postcode":"K0H 2Y0",
    "sg:province":"ON",
    "sg:tags":[
        "excavating",
        "contractor",
        "trucking"
    ],
    "wof:name":"Hulton Construction & Rentals",
    "wof:placetype":"venue"
},
  "geometry": {"coordinates":[-76.441689,44.19297],"type":"Point"}
}