{
  "type": "Feature",
  "properties": {
    "addr:full":"345 21st St W Owen Sound ON N4K 4E4",
    "addr:housenumber":"345",
    "addr:postcode":"n4k 4e4",
    "addr:street":"21St St W",
    "iso:country":"CA",
    "sg:address":"345 21st St W",
    "sg:city":"Owen Sound",
    "sg:classifiers":[
        {
            "category":"Building & Trades",
            "subcategory":"Construction",
            "type":"Services"
        }
    ],
    "sg:phone":"+1 519 371 1768",
    "sg:postcode":"N4K 4E4",
    "sg:province":"ON",
    "sg:tags":[
        "general",
        "contractor"
    ],
    "wof:name":"Mc Connell Construction",
    "wof:placetype":"venue"
},
  "geometry": {"coordinates":[-80.94863100000001,44.582424],"type":"Point"}
}