{
  "type": "Feature",
  "properties": {
    "addr:full":"1070 Kelly Lake Rd Sudbury ON P3E 5P4",
    "addr:housenumber":"1070",
    "addr:postcode":"p3e 5p4",
    "addr:street":"Kelly Lake Rd",
    "iso:country":"CA",
    "sg:address":"1070 Kelly Lake Rd",
    "sg:city":"Sudbury",
    "sg:classifiers":[
        {
            "category":"Professional",
            "subcategory":"Engineering",
            "type":"Services"
        }
    ],
    "sg:phone":"+1 705 677 0193",
    "sg:postcode":"P3E 5P4",
    "sg:province":"ON",
    "sg:tags":[
        "engineer"
    ],
    "wof:name":"Roy J Rupert & Assoc",
    "wof:placetype":"venue"
},
  "geometry": {"coordinates":[-81.0364,46.469402],"type":"Point"}
}