{
  "type": "Feature",
  "properties": {
    "addr:full":"201 Boul Cure-Poirier O Longueuil QC J4J 2G4",
    "addr:housenumber":"201",
    "addr:postcode":"j4j 2g4",
    "addr:street":"Boul Cure-Poirier O",
    "iso:country":"CA",
    "sg:address":"201 Boul Cure-Poirier O",
    "sg:city":"Longueuil",
    "sg:classifiers":[
        {
            "category":"Social Services",
            "type":"Services"
        }
    ],
    "sg:phone":"+1 450 651 9830",
    "sg:postcode":"J4J 2G4",
    "sg:province":"QC",
    "sg:tags":[
        "organization",
        "welfare"
    ],
    "wof:name":"Clsc",
    "wof:placetype":"venue"
},
  "geometry": {"coordinates":[-73.48062899999999,45.53162],"type":"Point"}
}