{
  "type": "Feature",
  "properties": {
    "addr:full":"1144 Chiefswood Rd Ohsweken ON N0A 1M0",
    "addr:housenumber":"1144",
    "addr:postcode":"n0a 1m0",
    "addr:street":"Chiefswood Rd",
    "iso:country":"CA",
    "sg:address":"1144 Chiefswood Rd",
    "sg:city":"Ohsweken",
    "sg:classifiers":[
        {
            "category":"Professional",
            "subcategory":"Computer Services",
            "type":"Services"
        }
    ],
    "sg:phone":"+1 519 445 0389",
    "sg:postcode":"N0A 1M0",
    "sg:province":"ON",
    "sg:tags":[
        "repair",
        "dealer",
        "equipment"
    ],
    "wof:name":"Rjm Computer Consultants",
    "wof:placetype":"venue"
},
  "geometry": {"coordinates":[-80.12715911870001,43.0546798706],"type":"Point"}
}