{
  "type": "Feature",
  "properties": {
    "addr:full":"838 Hamilton St Vancouver BC V6B 6A2",
    "addr:housenumber":"838",
    "addr:postcode":"bc v6b 6a2",
    "addr:street":"Hamilton St",
    "iso:country":"CA",
    "sg:address":"838 Hamilton St",
    "sg:city":"Vancouver",
    "sg:classifiers":[
        {
            "category":"Travel",
            "subcategory":"Hotels & Motels",
            "type":"Entertainment"
        }
    ],
    "sg:phone":"+1 604 689 8033",
    "sg:postcode":"V6B 6A2",
    "sg:province":"BC",
    "wof:name":"Rosedale on Robson Suite Hotel",
    "wof:placetype":"venue"
},
  "geometry": {"coordinates":[-123.11640930199999,49.278301239],"type":"Point"}
}