{
  "type": "Feature",
  "properties": {
    "iso:country":"CA",
    "sg:address":"43 Stafford St",
    "sg:city":"Barrys Bay",
    "sg:classifiers":[
        {
            "category":"Retail",
            "subcategory":"Funeral Services",
            "type":"Services"
        }
    ],
    "sg:phone":"+1 613 756 2003",
    "sg:postcode":"K0J 1B0",
    "sg:province":"ON",
    "sg:tags":[
        "director"
    ],
    "wof:name":"O'Reilly Funeral Home",
    "wof:placetype":"venue"
},
  "geometry": {"coordinates":[-77.6769485474,45.4864234924],"type":"Point"}
}