{
  "type": "Feature",
  "properties": {
    "iso:country":"CA",
    "sg:address":"67 Joseph St",
    "sg:city":"Port Carling",
    "sg:classifiers":[
        {
            "category":"Home & Garden",
            "subcategory":"Hardware",
            "type":"Retail Goods"
        }
    ],
    "sg:phone":"+1 705 765 3193",
    "sg:postcode":"P0B 1J0",
    "sg:province":"ON",
    "wof:name":"Fraser's Home Hardware & Bldg",
    "wof:placetype":"venue"
},
  "geometry": {"coordinates":[-79.575668335,45.1160736084],"type":"Point"}
}