{
  "type": "Feature",
  "properties": {
    "addr:full":"67 Yonge St Suite 1600 Toronto M5E 1J8",
    "addr:housenumber":"67",
    "addr:postcode":"m5e 1j8",
    "addr:street":"Yonge St Suite 1600",
    "iso:country":"CA",
    "sg:address":"67 Yonge St Suite 1600",
    "sg:city":"Toronto",
    "sg:classifiers":[
        {
            "category":"Professional",
            "subcategory":"Computer Services",
            "type":"Services"
        }
    ],
    "sg:postcode":"M5E 1J8",
    "sg:tags":[
        "ecards",
        "gifting",
        "social-networking",
        "user-generated-content",
        "greetings",
        "music",
        "photography",
        "creative-writing",
        "avatars",
        "personal-messages",
        "enterprise-marketing"
    ],
    "sg:website":"http://www.MashupArts.com",
    "wof:name":"Mashup Arts",
    "wof:placetype":"venue"
},
  "geometry": {"coordinates":[-79.3777473,43.648786],"type":"Point"}
}