{
  "type": "Feature",
  "properties": {
    "addr:full":"1484 Av Saint-Louis Plessisville QC G6L 2M8",
    "addr:housenumber":"1484",
    "addr:postcode":"g6l 2m8",
    "addr:street":"Av Saint-Louis",
    "iso:country":"CA",
    "sg:address":"1484 Av Saint-Louis",
    "sg:city":"Plessisville",
    "sg:classifiers":[
        {
            "category":"Health Services",
            "subcategory":"Optometrist",
            "type":"Services"
        }
    ],
    "sg:phone":"+1 819 362 8228",
    "sg:postcode":"G6L 2M8",
    "sg:province":"QC",
    "wof:name":"Demers, Denis OD",
    "wof:placetype":"venue"
},
  "geometry": {"coordinates":[-71.77039337159999,46.2188949585],"type":"Point"}
}