{
  "type": "Feature",
  "properties": {
    "addr:full":"1974 Quilchena Ave Merritt BC V1K 1B8",
    "addr:housenumber":"1974",
    "addr:postcode":"v1k 1b8",
    "addr:street":"Quilchena Ave",
    "iso:country":"CA",
    "sg:address":"1974 Quilchena Ave",
    "sg:city":"Merritt",
    "sg:classifiers":[
        {
            "category":"Shopping",
            "subcategory":"Stationery & Office Supplies",
            "type":"Retail Goods"
        }
    ],
    "sg:phone":"+1 250 378 9655",
    "sg:postcode":"V1K 1B8",
    "sg:province":"BC",
    "sg:tags":[
        "stationer"
    ],
    "wof:name":"Coldwater Office Ctr",
    "wof:placetype":"venue"
},
  "geometry": {"coordinates":[-120.79022979699999,50.110244751],"type":"Point"}
}