{
  "type": "Feature",
  "properties": {
    "iso:country":"CA",
    "sg:city":"Ryley",
    "sg:classifiers":[
        {
            "category":"Wholesale",
            "subcategory":"Machinery & Supplies",
            "type":"Manufacturing & Wholesale Goods"
        }
    ],
    "sg:phone":"+1 780 663 3759",
    "sg:postcode":"T0B 4A0",
    "sg:province":"AB",
    "sg:tags":[
        "farm",
        "equipment"
    ],
    "wof:name":"Ryalta Industries Ltd",
    "wof:placetype":"venue"
},
  "geometry": {"coordinates":[-112.431877136,53.2894554138],"type":"Point"}
}