{
  "type": "Feature",
  "properties": {
    "addr:full":"221 1st Ave Rockyford AB T0J 2R0",
    "addr:housenumber":"221",
    "addr:postcode":"t0j 2r0",
    "addr:street":"1St Ave",
    "iso:country":"CA",
    "sg:address":"221 1st Ave",
    "sg:city":"Rockyford",
    "sg:classifiers":[
        {
            "category":"Wholesale",
            "subcategory":"Farm Supplies",
            "type":"Manufacturing & Wholesale Goods"
        }
    ],
    "sg:phone":"+1 403 533 3811",
    "sg:postcode":"T0J 2R0",
    "sg:province":"AB",
    "sg:tags":[
        "feed",
        "poultry",
        "bedding"
    ],
    "wof:name":"Superior Feed & Supply Ltd",
    "wof:placetype":"venue"
},
  "geometry": {"coordinates":[-113.14379099999999,51.23241],"type":"Point"}
}