{
  "type": "Feature",
  "properties": {
    "addr:full":"General Delivery Harbour Round NL A0K 3A0",
    "addr:postcode":"a0k 3a0",
    "addr:street":"Harbour",
    "iso:country":"CA",
    "sg:address":"General Delivery",
    "sg:city":"Harbour Round",
    "sg:classifiers":[
        {
            "category":"Food & Beverages",
            "subcategory":"Groceries & Convenience Stores",
            "type":"Retail Goods"
        }
    ],
    "sg:phone":"+1 709 661 7300",
    "sg:postcode":"A0K 3A0",
    "sg:province":"NL",
    "sg:tags":[
        "grocer"
    ],
    "wof:name":"A & T Grocery",
    "wof:placetype":"venue"
},
  "geometry": {"coordinates":[-55.734909,49.920631],"type":"Point"}
}