{
  "type": "Feature",
  "properties": {
    "iso:country":"CA",
    "sg:address":"540 King's Hwy",
    "sg:city":"Fort Frances",
    "sg:classifiers":[
        {
            "category":"Real Estate",
            "subcategory":"Real Estate Agent",
            "type":"Services"
        }
    ],
    "sg:phone":"+1 807 274 8537",
    "sg:postcode":"P9A 2T1",
    "sg:province":"ON",
    "wof:name":"Zucchiatti, Anne",
    "wof:placetype":"venue"
},
  "geometry": {"coordinates":[-93.4144821167,48.6109542847],"type":"Point"}
}