{
  "type": "Feature",
  "properties": {
    "addr:full":"1329 Redpath Cres Montreal QC H3G 1A1",
    "addr:housenumber":"1329",
    "addr:postcode":"h3g 1a1",
    "addr:street":"Redpath Cres",
    "iso:country":"CA",
    "sg:address":"1329 Redpath Cres",
    "sg:city":"Montreal",
    "sg:classifiers":[
        {
            "category":"Health Services",
            "subcategory":"Doctor",
            "type":"Services"
        }
    ],
    "sg:phone":"+1 514 845 3809",
    "sg:postcode":"H3G 1A1",
    "sg:province":"QC",
    "sg:tags":[
        "physician",
        "surgeon"
    ],
    "wof:name":"Roper, P D L MD",
    "wof:placetype":"venue"
},
  "geometry": {"coordinates":[-73.5860290527,45.5022010803],"type":"Point"}
}