{
  "type": "Feature",
  "properties": {
    "addr:full":"75 Cecil Found Cres Courtice ON L1E 2W1",
    "addr:housenumber":"75",
    "addr:postcode":"l1e 2w1",
    "addr:street":"Cecil Found Cres Courtice",
    "iso:country":"CA",
    "sg:address":"75 Cecil Found Cres",
    "sg:city":"Courtice",
    "sg:classifiers":[
        {
            "category":"Personal",
            "subcategory":"Beauty Salon",
            "type":"Services"
        }
    ],
    "sg:phone":"+1 905 433 9742",
    "sg:postcode":"L1E 2W1",
    "sg:province":"ON",
    "wof:name":"Yorkville East Hair Studio",
    "wof:placetype":"venue"
},
  "geometry": {"coordinates":[-78.788223,43.918198],"type":"Point"}
}