{
  "type": "Feature",
  "properties": {
    "addr:full":"9812 92 Ave NW Edmonton AB T6E 2V5",
    "addr:housenumber":"9812",
    "addr:postcode":"t6e 2v5",
    "addr:street":"92 Ave Nw",
    "iso:country":"CA",
    "sg:address":"9812 92 Ave NW",
    "sg:city":"Edmonton",
    "sg:classifiers":[
        {
            "category":"Real Estate",
            "subcategory":"Architect",
            "type":"Services"
        }
    ],
    "sg:phone":"+1 780 439 9998",
    "sg:postcode":"T6E 2V5",
    "sg:province":"AB",
    "wof:name":"Terry Frost Designers Arch",
    "wof:placetype":"venue"
},
  "geometry": {"coordinates":[-113.48335299999999,53.527534],"type":"Point"}
}