{
  "type": "Feature",
  "properties": {
    "addr:full":"Nelson BC V1L 1G6",
    "addr:postcode":"bc v1l 1g6",
    "iso:country":"CA",
    "sg:city":"Nelson",
    "sg:classifiers":[
        {
            "category":"Travel",
            "subcategory":"Hotels & Motels",
            "type":"Entertainment"
        }
    ],
    "sg:phone":"+1 250 352 5501",
    "sg:postcode":"V1L 1G6",
    "sg:province":"BC",
    "wof:name":"Alpine Motel",
    "wof:placetype":"venue"
},
  "geometry": {"coordinates":[-117.293258667,49.4860229492],"type":"Point"}
}