{
  "type": "Feature",
  "properties": {
    "addr:full":"557 Cambridge St S Ottawa ON K1S 4J4",
    "addr:housenumber":"557",
    "addr:postcode":"k1s 4j4",
    "addr:street":"Cambridge St S",
    "iso:country":"CA",
    "sg:address":"557 Cambridge St S",
    "sg:city":"Ottawa",
    "sg:classifiers":[
        {
            "category":"Restaurant",
            "type":"Food & Drink"
        }
    ],
    "sg:phone":"+1 613 230 0803",
    "sg:postcode":"K1S 4J4",
    "sg:province":"ON",
    "wof:name":"Royal Oak",
    "wof:placetype":"venue"
},
  "geometry": {"coordinates":[-75.7004776001,45.399848938],"type":"Point"}
}