{
  "type": "Feature",
  "properties": {
    "addr:full":"203 Logy Bay Rd St. John's NL A1A 3T7",
    "addr:housenumber":"203",
    "addr:postcode":"a1a 3t7",
    "addr:street":"Logy Bay Rd",
    "iso:country":"CA",
    "sg:address":"203 Logy Bay Rd",
    "sg:city":"St. John's",
    "sg:classifiers":[
        {
            "category":"Organizations",
            "subcategory":"Religious Organization",
            "type":"Services"
        }
    ],
    "sg:phone":"+1 709 726 3213",
    "sg:postcode":"A1A 3T7",
    "sg:province":"NL",
    "sg:tags":[
        "church"
    ],
    "wof:name":"St Marks Church",
    "wof:placetype":"venue"
},
  "geometry": {"coordinates":[-52.679508,47.62904],"type":"Point"}
}