{
  "type": "Feature",
  "properties": {
    "addr:full":"6700 Rue Saint-Georges Levis QC G6V 4H3",
    "addr:housenumber":"6700",
    "addr:postcode":"g6v 4h3",
    "addr:street":"Rue Saint-Georges",
    "iso:country":"CA",
    "sg:address":"6700 Rue Saint-Georges",
    "sg:city":"Levis",
    "sg:classifiers":[
        {
            "category":"Food & Beverages",
            "subcategory":"Liquor & Beverages",
            "type":"Retail Goods"
        }
    ],
    "sg:phone":"+1 418 837 0602",
    "sg:postcode":"G6V 4H3",
    "sg:province":"QC",
    "sg:tags":[
        "store"
    ],
    "wof:name":"Saq",
    "wof:placetype":"venue"
},
  "geometry": {"coordinates":[-71.1731796265,46.8157577515],"type":"Point"}
}