{
  "type": "Feature",
  "properties": {
    "addr:full":"Burnaby BC V5C 5V1",
    "addr:postcode":"v5c 5v1",
    "iso:country":"CA",
    "sg:city":"Burnaby",
    "sg:classifiers":[
        {
            "category":"Building & Trades",
            "subcategory":"Electrical",
            "type":"Services"
        }
    ],
    "sg:phone":"+1 604 299 5454",
    "sg:postcode":"V5C 5V1",
    "sg:province":"BC",
    "sg:tags":[
        "electric",
        "contractor"
    ],
    "wof:name":"Deltec Electric",
    "wof:placetype":"venue"
},
  "geometry": {"coordinates":[-122.987762,49.260983],"type":"Point"}
}