{
  "type": "Feature",
  "properties": {
    "addr:full":"28 Burgoyne Rd Mill Village NS B0J 2H0",
    "addr:housenumber":"28",
    "addr:postcode":"b0j 2h0",
    "addr:street":"Burgoyne Rd",
    "iso:country":"CA",
    "sg:address":"28 Burgoyne Rd",
    "sg:city":"Mill Village",
    "sg:classifiers":[
        {
            "category":"Freight",
            "type":"Transportation"
        }
    ],
    "sg:phone":"+1 902 677 2567",
    "sg:postcode":"B0J 2H0",
    "sg:province":"NS",
    "sg:tags":[
        "tank",
        "septic",
        "trucking"
    ],
    "wof:name":"R & R Weagle Enterprises Ltd",
    "wof:placetype":"venue"
},
  "geometry": {"coordinates":[-64.64701843260001,44.144821167],"type":"Point"}
}