{
  "type": "Feature",
  "properties": {
    "addr:full":"Assiniboia SK S0H 0B0",
    "addr:postcode":"s0h 0b0",
    "iso:country":"CA",
    "sg:city":"Assiniboia",
    "sg:classifiers":[
        {
            "category":"Building & Trades",
            "subcategory":"Construction",
            "type":"Services"
        }
    ],
    "sg:phone":"+1 306 642 4060",
    "sg:postcode":"S0H 0B0",
    "sg:province":"SK",
    "sg:tags":[
        "general",
        "contractor"
    ],
    "wof:name":"L & C Hogg Construction Svc",
    "wof:placetype":"venue"
},
  "geometry": {"coordinates":[-105.992729,49.630028],"type":"Point"}
}