{
  "type": "Feature",
  "properties": {
    "addr:full":"1015 Golf Links Rd Ancaster ON L9K 1L6",
    "addr:housenumber":"1015",
    "addr:postcode":"l9k 1l6",
    "addr:street":"Golf Links Rd",
    "iso:country":"CA",
    "sg:address":"1015 Golf Links Rd",
    "sg:city":"Ancaster",
    "sg:classifiers":[
        {
            "category":"Shopping",
            "subcategory":"Stationery & Office Supplies",
            "type":"Retail Goods"
        }
    ],
    "sg:phone":"+1 905 648 6047",
    "sg:postcode":"L9K 1L6",
    "sg:province":"ON",
    "wof:name":"Business Depot",
    "wof:placetype":"venue"
},
  "geometry": {"coordinates":[-79.93896484379999,43.2281761169],"type":"Point"}
}