{
  "type": "Feature",
  "properties": {
    "addr:full":"124 Rue DE LA Forge Saint-Eustache QC J7R 2S2",
    "addr:housenumber":"124",
    "addr:postcode":"j7r 2s2",
    "addr:street":"Rue De La Forge",
    "iso:country":"CA",
    "sg:address":"124 Rue DE LA Forge",
    "sg:city":"Saint-Eustache",
    "sg:classifiers":[
        {
            "category":"Manufacturing",
            "subcategory":"Metals",
            "type":"Manufacturing & Wholesale Goods"
        }
    ],
    "sg:phone":"+1 450 473 2916",
    "sg:postcode":"J7R 2S2",
    "sg:province":"QC",
    "sg:tags":[
        "solder"
    ],
    "wof:name":"Sougetech Soudure Generale Inc",
    "wof:placetype":"venue"
},
  "geometry": {"coordinates":[-73.899635,45.558228],"type":"Point"}
}