{
  "type": "Feature",
  "properties": {
    "addr:full":"633 Turnberry St Brussels ON N0G 1H0",
    "addr:housenumber":"633",
    "addr:postcode":"n0g 1h0",
    "addr:street":"Turnberry St",
    "iso:country":"CA",
    "sg:address":"633 Turnberry St",
    "sg:city":"Brussels",
    "sg:classifiers":[
        {
            "category":"Organizations",
            "subcategory":"Religious Organization",
            "type":"Services"
        }
    ],
    "sg:phone":"+1 519 887 9273",
    "sg:postcode":"N0G 1H0",
    "sg:province":"ON",
    "sg:tags":[
        "church"
    ],
    "wof:name":"Anglican Church Rectory",
    "wof:placetype":"venue"
},
  "geometry": {"coordinates":[-81.2515945435,43.7416648865],"type":"Point"}
}