{
  "type": "Feature",
  "properties": {
    "addr:full":"45 Thorne St Cambridge ON N1R 8N1",
    "addr:housenumber":"45",
    "addr:postcode":"n1r 8n1",
    "addr:street":"Thorne St",
    "iso:country":"CA",
    "sg:address":"45 Thorne St",
    "sg:city":"Cambridge",
    "sg:classifiers":[
        {
            "category":"Government",
            "subcategory":"Office",
            "type":"Public Place"
        }
    ],
    "sg:phone":"+1 519 622 9676",
    "sg:postcode":"N1R 8N1",
    "sg:province":"ON",
    "sg:tags":[
        "village"
    ],
    "wof:name":"Cambridge Arts Culture",
    "wof:placetype":"venue"
},
  "geometry": {"coordinates":[-80.313248,43.360752],"type":"Point"}
}