{
  "type": "Feature",
  "properties": {
    "addr:full":"155 Rte 132 E Nouvelle QC G0C 2E0",
    "addr:housenumber":"155",
    "addr:postcode":"qc g0c 2e0",
    "addr:street":"Rte 132 E",
    "iso:country":"CA",
    "sg:address":"155 Rte 132 E",
    "sg:city":"Nouvelle",
    "sg:classifiers":[
        {
            "category":"Home & Garden",
            "subcategory":"Furniture",
            "type":"Retail Goods"
        }
    ],
    "sg:phone":"+1 418 794 2296",
    "sg:postcode":"G0C 2E0",
    "sg:province":"QC",
    "wof:name":"Innova-Meubles",
    "wof:placetype":"venue"
},
  "geometry": {"coordinates":[-66.30796813960001,48.1336326599],"type":"Point"}
}