{
  "type": "Feature",
  "properties": {
    "addr:full":"7059 Ch DE LA Cote-Saint-Luc Cote Saint-Luc QC H4V 1J2",
    "addr:postcode":"7059;h4v 1j2",
    "addr:street":"Ch De La Cote-Saint-Luc Cote",
    "iso:country":"CA",
    "sg:address":"7059 Ch DE LA Cote-Saint-Luc",
    "sg:city":"Cote Saint-Luc",
    "sg:classifiers":[
        {
            "category":"Personal",
            "subcategory":"Beauty Salon",
            "type":"Services"
        }
    ],
    "sg:phone":"+1 514 489 5351",
    "sg:postcode":"H4V 1J2",
    "sg:province":"QC",
    "wof:name":"Carisme Coiffure",
    "wof:placetype":"venue"
},
  "geometry": {"coordinates":[-73.653976,45.465347],"type":"Point"}
}