{
  "type": "Feature",
  "properties": {
    "addr:full":"1992 Yonge St Toronto ON M4S 1Z7",
    "addr:housenumber":"1992",
    "addr:postcode":"m4s 1z7",
    "addr:street":"Yonge St",
    "iso:country":"CA",
    "sg:address":"1992 Yonge St",
    "sg:city":"Toronto",
    "sg:classifiers":[
        {
            "category":"Recreation",
            "type":"Entertainment"
        }
    ],
    "sg:phone":"+1 416 485 5686",
    "sg:postcode":"M4S 1Z7",
    "sg:province":"ON",
    "sg:tags":[
        "instruction",
        "boxing",
        "program",
        "fitness",
        "exercise",
        "physical"
    ],
    "wof:name":"Centre Ring Ltd",
    "wof:placetype":"venue"
},
  "geometry": {"coordinates":[-79.3970947266,43.700214386],"type":"Point"}
}