{
  "type": "Feature",
  "properties": {
    "iso:country":"CA",
    "sg:address":"3875 Regent St",
    "sg:city":"Burnaby",
    "sg:classifiers":[
        {
            "category":"Shopping",
            "subcategory":"Computers & Home Electronics",
            "type":"Retail Goods"
        }
    ],
    "sg:phone":"+1 604 985 2223",
    "sg:postcode":"V5C 4G7",
    "sg:province":"BC",
    "sg:tags":[
        "software"
    ],
    "wof:name":"Microtests Computer Solutions",
    "wof:placetype":"venue"
},
  "geometry": {"coordinates":[-123.01838684099999,49.2592544556],"type":"Point"}
}