{
  "type": "Feature",
  "properties": {
    "addr:full":"12332 Boundary Dr N Surrey BC V3X 1Z6",
    "addr:housenumber":"12332",
    "addr:postcode":"v3x 1z6",
    "addr:street":"Boundary Dr N",
    "iso:country":"CA",
    "sg:address":"12332 Boundary Dr N",
    "sg:city":"Surrey",
    "sg:classifiers":[
        {
            "category":"Education",
            "subcategory":"School",
            "type":"Public Place"
        }
    ],
    "sg:phone":"+1 604 543 8158",
    "sg:postcode":"V3X 1Z6",
    "sg:province":"BC",
    "wof:name":"Boundary Park Elementary Schl",
    "wof:placetype":"venue"
},
  "geometry": {"coordinates":[-122.881446838,49.1173019409],"type":"Point"}
}