{
  "type": "Feature",
  "properties": {
    "addr:full":"705 Industrial Rd Shelburne ON L0N 1S4",
    "addr:housenumber":"705",
    "addr:postcode":"l0n 1s4",
    "addr:street":"Industrial Rd",
    "iso:country":"CA",
    "sg:address":"705 Industrial Rd",
    "sg:city":"Shelburne",
    "sg:classifiers":[
        {
            "category":"Wholesale",
            "subcategory":"Machinery & Supplies",
            "type":"Manufacturing & Wholesale Goods"
        }
    ],
    "sg:phone":"+1 519 925 6868",
    "sg:postcode":"L0N 1S4",
    "sg:province":"ON",
    "sg:tags":[
        "bearing"
    ],
    "wof:name":"Partsco",
    "wof:placetype":"venue"
},
  "geometry": {"coordinates":[-80.19090300000001,44.082993],"type":"Point"}
}