{
  "type": "Feature",
  "properties": {
    "addr:full":"292 Rue Saint-Pierre Saint-Constant QC J5A 2A7",
    "addr:housenumber":"292",
    "addr:postcode":"j5a 2a7",
    "addr:street":"Rue Saint-Pierre",
    "iso:country":"CA",
    "sg:address":"292 Rue Saint-Pierre",
    "sg:city":"Saint-Constant",
    "sg:classifiers":[
        {
            "category":"Wholesale",
            "subcategory":"Books, Periodicals, & Newspapers",
            "type":"Manufacturing & Wholesale Goods"
        }
    ],
    "sg:phone":"+1 450 632 5091",
    "sg:postcode":"J5A 2A7",
    "sg:province":"QC",
    "sg:tags":[
        "distributor"
    ],
    "wof:name":"Messagerie Erotique Enr",
    "wof:placetype":"venue"
},
  "geometry": {"coordinates":[-73.5730438232,45.3612442017],"type":"Point"}
}