{
  "type": "Feature",
  "properties": {
    "addr:full":"12 Cowan Ave Toronto ON M6K 2N2",
    "addr:housenumber":"12",
    "addr:postcode":"m6k 2n2",
    "addr:street":"Cowan Ave",
    "iso:country":"CA",
    "sg:address":"12 Cowan Ave",
    "sg:city":"Toronto",
    "sg:classifiers":[
        {
            "category":"Retail",
            "subcategory":"Repair Shop",
            "type":"Services"
        }
    ],
    "sg:phone":"+1 416 535 7505",
    "sg:postcode":"M6K 2N2",
    "sg:province":"ON",
    "sg:tags":[
        "ironwork",
        "work",
        "art",
        "metal"
    ],
    "wof:name":"Green Anvil",
    "wof:placetype":"venue"
},
  "geometry": {"coordinates":[-79.430412,43.633877],"type":"Point"}
}