{
  "type": "Feature",
  "properties": {
    "addr:full":"1544 7th St W Simcoe ON N3Y 4K5",
    "addr:housenumber":"1544",
    "addr:postcode":"n3y 4k5",
    "addr:street":"7Th St W",
    "iso:country":"CA",
    "sg:address":"1544 7th St W",
    "sg:city":"Simcoe",
    "sg:classifiers":[
        {
            "category":"Banks & Credit Unions",
            "subcategory":"Investment Brokerage",
            "type":"Services"
        }
    ],
    "sg:phone":"+1 519 428 9298",
    "sg:postcode":"N3Y 4K5",
    "sg:province":"ON",
    "sg:tags":[
        "insurance"
    ],
    "wof:name":"Clarica Life Insurance CO",
    "wof:placetype":"venue"
},
  "geometry": {"coordinates":[-80.32585899999999,42.80468],"type":"Point"}
}