{
  "type": "Feature",
  "properties": {
    "addr:full":"Calgary AB T2L 1V9",
    "addr:postcode":"t2l 1v9",
    "iso:country":"CA",
    "sg:city":"Calgary",
    "sg:classifiers":[
        {
            "category":"Restaurant",
            "type":"Food & Drink"
        }
    ],
    "sg:phone":"+1 403 282 5685",
    "sg:postcode":"T2L 1V9",
    "sg:province":"AB",
    "wof:name":"Subway Sandwiches & Salads",
    "wof:placetype":"venue"
},
  "geometry": {"coordinates":[-114.13921356199999,51.1010856628],"type":"Point"}
}