{
  "type": "Feature",
  "properties": {
    "addr:full":"111 West St Sydney NS B1N 1S2",
    "addr:housenumber":"111",
    "addr:postcode":"b1n 1s2",
    "addr:street":"West St",
    "iso:country":"CA",
    "sg:address":"111 West St",
    "sg:city":"Sydney",
    "sg:classifiers":[
        {
            "category":"Organizations",
            "subcategory":"Community Association",
            "type":"Services"
        }
    ],
    "sg:phone":"+1 902 567 0240",
    "sg:postcode":"B1N 1S2",
    "sg:province":"NS",
    "sg:tags":[
        "club"
    ],
    "wof:name":"Whitney Pier Youth Club",
    "wof:placetype":"venue"
},
  "geometry": {"coordinates":[-60.1814498901,46.1599998474],"type":"Point"}
}