{
  "type": "Feature",
  "properties": {
    "addr:full":"1145 Barton St Thunder Bay ON P7B 5N3",
    "addr:housenumber":"1145",
    "addr:postcode":"p7b 5n3",
    "addr:street":"Barton St",
    "iso:country":"CA",
    "sg:address":"1145 Barton St",
    "sg:city":"Thunder Bay",
    "sg:classifiers":[
        {
            "category":"Professional",
            "subcategory":"Advertising",
            "type":"Services"
        }
    ],
    "sg:phone":"+1 807 623 2348",
    "sg:postcode":"P7B 5N3",
    "sg:province":"ON",
    "wof:name":"North Superior Publishing Inc",
    "wof:placetype":"venue"
},
  "geometry": {"coordinates":[-89.26010100000001,48.403275],"type":"Point"}
}