{
  "type": "Feature",
  "properties": {
    "addr:full":"871 Ch DE Saint-Jean LA Prairie QC J5R 4S4",
    "addr:housenumber":"871",
    "addr:postcode":"j5r 4s4",
    "addr:street":"Ch De Saint-Jean",
    "iso:country":"CA",
    "sg:address":"871 Ch DE Saint-Jean",
    "sg:city":"LA Prairie",
    "sg:classifiers":[
        {
            "category":"Health Services",
            "subcategory":"Doctor",
            "type":"Services"
        }
    ],
    "sg:phone":"+1 450 659 0333",
    "sg:postcode":"J5R 4S4",
    "sg:province":"QC",
    "sg:tags":[
        "clinic",
        "dentist"
    ],
    "wof:name":"Clinique Dentaire Jy Conant",
    "wof:placetype":"venue"
},
  "geometry": {"coordinates":[-73.4810562134,45.4130172729],"type":"Point"}
}