{
  "type": "Feature",
  "properties": {
    "addr:full":"270 Parkdale Ave N Hamilton ON L8H 5X7",
    "addr:housenumber":"270",
    "addr:postcode":"l8h 5x7",
    "addr:street":"Parkdale Ave N",
    "iso:country":"CA",
    "sg:address":"270 Parkdale Ave N",
    "sg:city":"Hamilton",
    "sg:classifiers":[
        {
            "category":"Building & Trades",
            "subcategory":"Plumbing",
            "type":"Services"
        }
    ],
    "sg:phone":"+1 905 544 2606",
    "sg:postcode":"L8H 5X7",
    "sg:province":"ON",
    "sg:tags":[
        "sheet",
        "work",
        "metal",
        "contractor"
    ],
    "wof:name":"Steve's Sheet Metal CO",
    "wof:placetype":"venue"
},
  "geometry": {"coordinates":[-79.78848266599999,43.2442474365],"type":"Point"}
}