{
  "type": "Feature",
  "properties": {
    "addr:full":"34577 91st St Oliver BC V0H 1T0",
    "addr:housenumber":"34577",
    "addr:postcode":"bc v0h 1t0",
    "addr:street":"91St St",
    "iso:country":"CA",
    "sg:address":"34577 91st St",
    "sg:city":"Oliver",
    "sg:classifiers":[
        {
            "category":"Government",
            "subcategory":"Office",
            "type":"Public Place"
        }
    ],
    "sg:phone":"+1 250 498 5301",
    "sg:postcode":"V0H 1T0",
    "sg:province":"BC",
    "wof:name":"Canadian Food Inspection",
    "wof:placetype":"venue"
},
  "geometry": {"coordinates":[-119.54381600000001,49.174889],"type":"Point"}
}