{
  "type": "Feature",
  "properties": {
    "addr:full":"74 Broadway Orangeville ON L9W 1J9",
    "addr:housenumber":"74",
    "addr:postcode":"l9w 1j9",
    "addr:street":"Broadway",
    "iso:country":"CA",
    "sg:address":"74 Broadway",
    "sg:city":"Orangeville",
    "sg:classifiers":[
        {
            "category":"Government",
            "subcategory":"Office",
            "type":"Public Place"
        }
    ],
    "sg:phone":"+1 519 942 1430",
    "sg:postcode":"L9W 1J9",
    "sg:province":"ON",
    "wof:name":"Driver Vehicle License Office",
    "wof:placetype":"venue"
},
  "geometry": {"coordinates":[-80.093277,43.920017],"type":"Point"}
}