{
  "type": "Feature",
  "properties": {
    "addr:full":"345 Lansdowne Ave Callander ON P0H 1H0",
    "addr:housenumber":"345",
    "addr:postcode":"p0h 1h0",
    "addr:street":"Lansdowne Ave",
    "iso:country":"CA",
    "sg:address":"345 Lansdowne Ave",
    "sg:city":"Callander",
    "sg:classifiers":[
        {
            "category":"Restaurant",
            "type":"Food & Drink"
        }
    ],
    "sg:phone":"+1 705 752 3773",
    "sg:postcode":"P0H 1H0",
    "sg:province":"ON",
    "sg:tags":[
        "banquet",
        "rooms"
    ],
    "wof:name":"Royal Canadian Legion",
    "wof:placetype":"venue"
},
  "geometry": {"coordinates":[-79.3603515625,46.2237243652],"type":"Point"}
}