{
  "type": "Feature",
  "properties": {
    "addr:full":"Cp 218 Succ Bureau-Chef Vaudreuil-Dorion QC J7V 7J5",
    "addr:postcode":"j7v 7j5",
    "addr:street":"Bureau-Chef",
    "iso:country":"CA",
    "sg:address":"Cp 218 Succ Bureau-Chef",
    "sg:city":"Vaudreuil-Dorion",
    "sg:classifiers":[
        {
            "category":"Building & Trades",
            "subcategory":"Cleaning & Sanitation",
            "type":"Services"
        }
    ],
    "sg:phone":"+1 514 425 2055",
    "sg:postcode":"J7V 7J5",
    "sg:province":"QC",
    "sg:tags":[
        "janitor"
    ],
    "wof:name":"Ma Tante Matilda",
    "wof:placetype":"venue"
},
  "geometry": {"coordinates":[-74.0354,45.40493],"type":"Point"}
}