{
  "type": "Feature",
  "properties": {
    "addr:full":"322 Palmerston Blvd Toronto ON M6G 2N6",
    "addr:housenumber":"322",
    "addr:postcode":"m6g 2n6",
    "addr:street":"Palmerston Blvd",
    "iso:country":"CA",
    "sg:address":"322 Palmerston Blvd",
    "sg:city":"Toronto",
    "sg:classifiers":[
        {
            "category":"Travel",
            "subcategory":"Hotels & Motels",
            "type":"Entertainment"
        }
    ],
    "sg:phone":"+1 416 920 7842",
    "sg:postcode":"M6G 2N6",
    "sg:province":"ON",
    "sg:tags":[
        "breakfast",
        "accommodation",
        "bed"
    ],
    "wof:name":"Bed & Breakfast Palmerston Inn",
    "wof:placetype":"venue"
},
  "geometry": {"coordinates":[-79.41069793699999,43.6568908691],"type":"Point"}
}