{
  "type": "Feature",
  "properties": {
    "addr:full":"187 2nd Ave Cochrane ON P0L 1C0",
    "addr:housenumber":"187",
    "addr:postcode":"p0l 1c0",
    "addr:street":"2Nd Ave",
    "iso:country":"CA",
    "sg:address":"187 2nd Ave",
    "sg:city":"Cochrane",
    "sg:classifiers":[
        {
            "category":"Social Services",
            "type":"Services"
        }
    ],
    "sg:phone":"+1 705 272 5777",
    "sg:postcode":"P0L 1C0",
    "sg:province":"ON",
    "sg:tags":[
        "organization",
        "welfare"
    ],
    "wof:name":"Services Familiaux J Sauve",
    "wof:placetype":"venue"
},
  "geometry": {"coordinates":[-81.03128100000001,49.06522],"type":"Point"}
}