{
  "type": "Feature",
  "properties": {
    "addr:full":"Lower Sackville NS B4E 1J7",
    "addr:postcode":"b4e 1j7",
    "iso:country":"CA",
    "sg:city":"Lower Sackville",
    "sg:classifiers":[
        {
            "category":"Building & Trades",
            "subcategory":"Construction",
            "type":"Services"
        }
    ],
    "sg:phone":"+1 902 864 3011",
    "sg:postcode":"B4E 1J7",
    "sg:province":"NS",
    "sg:tags":[
        "insulation",
        "heat",
        "contractor"
    ],
    "wof:name":"Beaver Bank Insulators",
    "wof:placetype":"venue"
},
  "geometry": {"coordinates":[-63.692364,44.792568],"type":"Point"}
}