{
  "type": "Feature",
  "properties": {
    "addr:full":"3566 King George Hwy Surrey BC V4P 1B5",
    "addr:housenumber":"3566",
    "addr:postcode":"v4p 1b5",
    "addr:street":"King George Hwy",
    "iso:country":"CA",
    "sg:address":"3566 King George Hwy",
    "sg:city":"Surrey",
    "sg:classifiers":[
        {
            "category":"Health Services",
            "subcategory":"Health Practitioner",
            "type":"Services"
        }
    ],
    "sg:phone":"+1 604 538 8837",
    "sg:postcode":"V4P 1B5",
    "sg:province":"BC",
    "wof:name":"Mountainview Wellness Ctr",
    "wof:placetype":"venue"
},
  "geometry": {"coordinates":[-122.81997699999999,49.067043],"type":"Point"}
}