{
  "type": "Feature",
  "properties": {
    "addr:full":"1202 12 Ave SW Calgary AB T3C 0P3",
    "addr:housenumber":"1202",
    "addr:postcode":"t3c 0p3",
    "addr:street":"12 Ave Sw",
    "iso:country":"CA",
    "sg:address":"1202 12 Ave SW",
    "sg:city":"Calgary",
    "sg:classifiers":[
        {
            "category":"Recreation",
            "type":"Entertainment"
        }
    ],
    "sg:phone":"+1 403 228 7744",
    "sg:postcode":"T3C 0P3",
    "sg:province":"AB",
    "sg:tags":[
        "martial",
        "arts",
        "instruction"
    ],
    "wof:name":"Calgary Kickboxing Ctr",
    "wof:placetype":"venue"
},
  "geometry": {"coordinates":[-114.089195,51.042282],"type":"Point"}
}