{
  "type": "Feature",
  "properties": {
    "iso:country":"CA",
    "sg:address":"244 Stewart Green SW",
    "sg:city":"Calgary",
    "sg:classifiers":[
        {
            "category":"Utilities",
            "subcategory":"Mobile Phone",
            "type":"Services"
        }
    ],
    "sg:phone":"+1 403 291 5400",
    "sg:postcode":"T3H 3C8",
    "sg:province":"AB",
    "sg:tags":[
        "telephone",
        "cellular"
    ],
    "wof:name":"Pdl Call Ctr",
    "wof:placetype":"venue"
},
  "geometry": {"coordinates":[-114.16908264200001,51.0152740479],"type":"Point"}
}