{
  "type": "Feature",
  "properties": {
    "addr:full":"Victoriaville QC G6P 1H3",
    "addr:postcode":"g6p 1h3",
    "iso:country":"CA",
    "sg:city":"Victoriaville",
    "sg:classifiers":[
        {
            "category":"Sports & Exercise",
            "subcategory":"Bowling",
            "type":"Entertainment"
        }
    ],
    "sg:phone":"+1 819 758 8211",
    "sg:postcode":"G6P 1H3",
    "sg:province":"QC",
    "sg:tags":[
        "center"
    ],
    "wof:name":"Salon Futur-O-Quilles Inc",
    "wof:placetype":"venue"
},
  "geometry": {"coordinates":[-71.96717099999999,46.06749],"type":"Point"}
}