{
  "type": "Feature",
  "properties": {
    "addr:full":"600 Dixon Rd Etobicoke ON M9W 1J1",
    "addr:housenumber":"600",
    "addr:postcode":"m9w 1j1",
    "addr:street":"Dixon Rd",
    "iso:country":"CA",
    "sg:address":"600 Dixon Rd",
    "sg:city":"Etobicoke",
    "sg:classifiers":[
        {
            "category":"Restaurant",
            "type":"Food & Drink"
        }
    ],
    "sg:phone":"+1 416 240 9741",
    "sg:postcode":"M9W 1J1",
    "sg:province":"ON",
    "wof:name":"Perkins Family Restaurant",
    "wof:placetype":"venue"
},
  "geometry": {"coordinates":[-79.57279200000001,43.691418],"type":"Point"}
}