{
  "type": "Feature",
  "properties": {
    "addr:full":"10 Cochrane St Oak River MB R0K 1T0",
    "addr:housenumber":"10",
    "addr:postcode":"r0k 1t0",
    "addr:street":"Cochrane St Oak",
    "iso:country":"CA",
    "sg:address":"10 Cochrane St",
    "sg:city":"Oak River",
    "sg:classifiers":[
        {
            "category":"Government",
            "subcategory":"Office",
            "type":"Public Place"
        }
    ],
    "sg:phone":"+1 204 566 2493",
    "sg:postcode":"R0K 1T0",
    "sg:province":"MB",
    "sg:tags":[
        "village"
    ],
    "wof:name":"Blanshard Economic Development",
    "wof:placetype":"venue"
},
  "geometry": {"coordinates":[-100.42927551299999,50.1378059387],"type":"Point"}
}