{
  "type": "Feature",
  "properties": {
    "addr:full":"2372 Barton St E Hamilton ON L8E 2W7",
    "addr:housenumber":"2372",
    "addr:postcode":"l8e 2w7",
    "addr:street":"Barton St E",
    "iso:country":"CA",
    "sg:address":"2372 Barton St E",
    "sg:city":"Hamilton",
    "sg:classifiers":[
        {
            "category":"Home & Garden",
            "subcategory":"Building Materials",
            "type":"Retail Goods"
        }
    ],
    "sg:phone":"+1 905 984 8635",
    "sg:postcode":"L8E 2W7",
    "sg:province":"ON",
    "sg:tags":[
        "plumbing",
        "fixture",
        "supply"
    ],
    "wof:name":"Plumbing Centre",
    "wof:placetype":"venue"
},
  "geometry": {"coordinates":[-79.76494598390001,43.2377815247],"type":"Point"}
}