{
  "type": "Feature",
  "properties": {
    "addr:full":"2979 Bloor St W Etobicoke ON M8X 1C1",
    "addr:housenumber":"2979",
    "addr:postcode":"m8x 1c1",
    "addr:street":"Bloor St W",
    "iso:country":"CA",
    "sg:address":"2979 Bloor St W",
    "sg:city":"Etobicoke",
    "sg:classifiers":[
        {
            "category":"Shopping",
            "subcategory":"Shoes",
            "type":"Retail Goods"
        }
    ],
    "sg:phone":"+1 416 234 0481",
    "sg:postcode":"M8X 1C1",
    "sg:province":"ON",
    "wof:name":"Bio Ped Foot Care Ctr",
    "wof:placetype":"venue"
},
  "geometry": {"coordinates":[-79.509361,43.647678],"type":"Point"}
}