{
  "type": "Feature",
  "properties": {
    "addr:full":"64 Hartzell Rd St Catharines ON L2P 1M8",
    "addr:housenumber":"64",
    "addr:postcode":"l2p 1m8",
    "addr:street":"Hartzell Rd",
    "iso:country":"CA",
    "sg:address":"64 Hartzell Rd",
    "sg:city":"St Catharines",
    "sg:classifiers":[
        {
            "category":"Retail",
            "subcategory":"Animal Services",
            "type":"Services"
        }
    ],
    "sg:phone":"+1 905 682 4068",
    "sg:postcode":"L2P 1M8",
    "sg:province":"ON",
    "sg:tags":[
        "pet",
        "grooming",
        "washing"
    ],
    "wof:name":"A Bark Above",
    "wof:placetype":"venue"
},
  "geometry": {"coordinates":[-79.2142486572,43.1539306641],"type":"Point"}
}