{
  "type": "Feature",
  "properties": {
    "iso:country":"CA",
    "sg:address":"3243 5th Ave",
    "sg:city":"Rawdon",
    "sg:classifiers":[
        {
            "category":"Shopping",
            "subcategory":"Used Merchandise",
            "type":"Retail Goods"
        }
    ],
    "sg:phone":"+1 450 834 5678",
    "sg:postcode":"J0K 1S0",
    "sg:province":"QC",
    "sg:tags":[
        "antique"
    ],
    "wof:name":"Antiquites Rawdon Enr",
    "wof:placetype":"venue"
},
  "geometry": {"coordinates":[-73.709815979,46.0431556702],"type":"Point"}
}