{
  "type": "Feature",
  "properties": {
    "addr:full":"3549 Route 105 Bear Island NB E6L 1J6",
    "addr:housenumber":"3549",
    "addr:postcode":"e6l 1j6",
    "addr:street":"Route 105 Bear",
    "iso:country":"CA",
    "sg:address":"3549 Route 105",
    "sg:city":"Bear Island",
    "sg:classifiers":[
        {
            "category":"Travel",
            "subcategory":"Campground",
            "type":"Entertainment"
        }
    ],
    "sg:phone":"+1 506 575 8151",
    "sg:postcode":"E6L 1J6",
    "sg:province":"NB",
    "wof:name":"Great Bear Camping",
    "wof:placetype":"venue"
},
  "geometry": {"coordinates":[-67.01467132569999,45.9129981995],"type":"Point"}
}