{
  "type": "Feature",
  "properties": {
    "addr:full":"Elora ON N0B 1S0",
    "addr:postcode":"n0b 1s0",
    "iso:country":"CA",
    "sg:city":"Elora",
    "sg:classifiers":[
        {
            "category":"Personal",
            "type":"Services"
        }
    ],
    "sg:phone":"+1 519 846 2579",
    "sg:postcode":"N0B 1S0",
    "sg:province":"ON",
    "sg:tags":[
        "therapist",
        "massage"
    ],
    "wof:name":"Oasis Healing Arts Ctr & Day",
    "wof:placetype":"venue"
},
  "geometry": {"coordinates":[-80.42937499999999,43.678856],"type":"Point"}
}