{
  "type": "Feature",
  "properties": {
    "addr:full":"180 Ch Des Bains Saint-Irenee QC G0T 1V0",
    "addr:housenumber":"180",
    "addr:postcode":"g0t 1v0",
    "addr:street":"Ch Des Bains Saint-Irenee",
    "iso:country":"CA",
    "sg:address":"180 Ch Des Bains",
    "sg:city":"Saint-Irenee",
    "sg:classifiers":[
        {
            "category":"Travel",
            "subcategory":"Hotels & Motels",
            "type":"Entertainment"
        }
    ],
    "sg:phone":"+1 418 452 8148",
    "sg:postcode":"G0T 1V0",
    "sg:province":"QC",
    "sg:tags":[
        "bed",
        "convenience",
        "breakfast",
        "store",
        "accommodation"
    ],
    "wof:name":"Village Vacances St-Irenee",
    "wof:placetype":"venue"
},
  "geometry": {"coordinates":[-70.20532989500001,47.5635681152],"type":"Point"}
}