{
  "type": "Feature",
  "properties": {
    "addr:full":"Calgary AB T2Y 2Z7",
    "addr:postcode":"t2y 2z7",
    "iso:country":"CA",
    "sg:city":"Calgary",
    "sg:classifiers":[
        {
            "category":"Professional",
            "subcategory":"Printing & Photocopies",
            "type":"Services"
        }
    ],
    "sg:phone":"+1 403 201 1101",
    "sg:postcode":"T2Y 2Z7",
    "sg:province":"AB",
    "sg:tags":[
        "printer",
        "duplicating",
        "copying"
    ],
    "wof:name":"Digital Post",
    "wof:placetype":"venue"
},
  "geometry": {"coordinates":[-114.065102,50.903107],"type":"Point"}
}