{
  "type": "Feature",
  "properties": {
    "addr:full":"192 Boul DE L'Anse Roberval QC G8H 1Y9",
    "addr:housenumber":"192",
    "addr:postcode":"g8h 1y9",
    "addr:street":"Boul De L'Anse",
    "iso:country":"CA",
    "sg:address":"192 Boul DE L'Anse",
    "sg:city":"Roberval",
    "sg:classifiers":[
        {
            "category":"Retail",
            "subcategory":"Car Wash",
            "type":"Services"
        }
    ],
    "sg:phone":"+1 418 275 4525",
    "sg:postcode":"G8H 1Y9",
    "sg:province":"QC",
    "sg:tags":[
        "polishing",
        "glass",
        "washing"
    ],
    "wof:name":"Duro Vitres & Acces D'Autos",
    "wof:placetype":"venue"
},
  "geometry": {"coordinates":[-72.2184677124,48.4952735901],"type":"Point"}
}