{
  "type": "Feature",
  "properties": {
    "addr:full":"2490 37th Ave W Vancouver BC V6M 1P5",
    "addr:housenumber":"2490",
    "addr:postcode":"v6m 1p5",
    "addr:street":"37Th Ave W",
    "iso:country":"CA",
    "sg:address":"2490 37th Ave W",
    "sg:city":"Vancouver",
    "sg:classifiers":[
        {
            "category":"Organizations",
            "subcategory":"Religious Organization",
            "type":"Services"
        }
    ],
    "sg:phone":"+1 604 261 4228",
    "sg:postcode":"V6M 1P5",
    "sg:province":"BC",
    "sg:tags":[
        "church"
    ],
    "wof:name":"St Mary's Anglican Church",
    "wof:placetype":"venue"
},
  "geometry": {"coordinates":[-123.162338257,49.2383308411],"type":"Point"}
}