{
  "type": "Feature",
  "properties": {
    "addr:full":"1626 152 St Surrey BC V4A 4N2",
    "addr:housenumber":"1626",
    "addr:postcode":"v4a 4n2",
    "addr:street":"152 St",
    "iso:country":"CA",
    "sg:address":"1626 152 St",
    "sg:city":"Surrey",
    "sg:classifiers":[
        {
            "category":"Bars & Pubs",
            "type":"Food & Drink"
        }
    ],
    "sg:phone":"+1 604 536 6420",
    "sg:postcode":"V4A 4N2",
    "sg:province":"BC",
    "wof:name":"Sawbuck's Neighbourhood Pub",
    "wof:placetype":"venue"
},
  "geometry": {"coordinates":[-122.80096399999999,49.031761],"type":"Point"}
}