{
  "type": "Feature",
  "properties": {
    "addr:full":"3040 Crestwood Pl Nanaimo BC V9T 1P2",
    "addr:housenumber":"3040",
    "addr:postcode":"v9t 1p2",
    "addr:street":"Crestwood Pl",
    "iso:country":"CA",
    "sg:address":"3040 Crestwood Pl",
    "sg:city":"Nanaimo",
    "sg:classifiers":[
        {
            "category":"Building & Trades",
            "subcategory":"Construction",
            "type":"Services"
        }
    ],
    "sg:phone":"+1 250 758 3043",
    "sg:postcode":"V9T 1P2",
    "sg:province":"BC",
    "sg:tags":[
        "excavating",
        "contractor",
        "trucking"
    ],
    "wof:name":"Fred's Trucking",
    "wof:placetype":"venue"
},
  "geometry": {"coordinates":[-123.989196777,49.2076339722],"type":"Point"}
}