{
  "type": "Feature",
  "properties": {
    "iso:country":"CA",
    "sg:city":"Calgary",
    "sg:classifiers":[
        {
            "category":"Real Estate",
            "subcategory":"Developer",
            "type":"Services"
        }
    ],
    "sg:phone":"+1 403 283 3556",
    "sg:postcode":"T3G 5H6",
    "sg:province":"AB",
    "sg:tags":[
        "company",
        "land"
    ],
    "wof:name":"Melcor Developments Ltd",
    "wof:placetype":"venue"
},
  "geometry": {"coordinates":[-114.201080322,51.1291999817],"type":"Point"}
}