{
  "type": "Feature",
  "properties": {
    "addr:full":"2395 Av Watt Sainte-Foy QC G1P 3X2",
    "addr:housenumber":"2395",
    "addr:postcode":"g1p 3x2",
    "addr:street":"Av Watt",
    "iso:country":"CA",
    "sg:address":"2395 Av Watt",
    "sg:city":"Sainte-Foy",
    "sg:classifiers":[
        {
            "category":"Home & Garden",
            "subcategory":"Building Materials",
            "type":"Retail Goods"
        }
    ],
    "sg:phone":"+1 418 653 6655",
    "sg:postcode":"G1P 3X2",
    "sg:province":"QC",
    "sg:tags":[
        "siding"
    ],
    "wof:name":"Produits DE Batiment Rsdntl",
    "wof:placetype":"venue"
},
  "geometry": {"coordinates":[-71.2957229614,46.7904167175],"type":"Point"}
}