{
  "type": "Feature",
  "properties": {
    "addr:full":"1948 Ottawa St Windsor ON N8Y 1R7",
    "addr:housenumber":"1948",
    "addr:postcode":"n8y 1r7",
    "addr:street":"Ottawa St",
    "iso:country":"CA",
    "sg:address":"1948 Ottawa St",
    "sg:city":"Windsor",
    "sg:classifiers":[
        {
            "category":"Personal",
            "subcategory":"Barber",
            "type":"Services"
        }
    ],
    "sg:phone":"+1 519 254 6085",
    "sg:postcode":"N8Y 1R7",
    "sg:province":"ON",
    "wof:name":"Mario's Barber Salon",
    "wof:placetype":"venue"
},
  "geometry": {"coordinates":[-83.00572200000001,42.312309],"type":"Point"}
}