{
  "type": "Feature",
  "properties": {
    "addr:full":"3818 Sunset St Burnaby BC V5G 1T3",
    "addr:housenumber":"3818",
    "addr:postcode":"v5g 1t3",
    "addr:street":"Sunset St",
    "iso:country":"CA",
    "sg:address":"3818 Sunset St",
    "sg:city":"Burnaby",
    "sg:classifiers":[
        {
            "category":"Shopping",
            "subcategory":"Pharmacy",
            "type":"Retail Goods"
        }
    ],
    "sg:phone":"+1 604 435 3830",
    "sg:postcode":"V5G 1T3",
    "sg:province":"BC",
    "wof:name":"Sunset Pharmacy Ltd",
    "wof:placetype":"venue"
},
  "geometry": {"coordinates":[-123.019233704,49.2496185303],"type":"Point"}
}