{
  "type": "Feature",
  "properties": {
    "addr:full":"752 Bedford Hwy Halifax NS B3M 2L9",
    "addr:housenumber":"752",
    "addr:postcode":"b3m 2l9",
    "addr:street":"Bedford Hwy",
    "iso:country":"CA",
    "sg:address":"752 Bedford Hwy",
    "sg:city":"Halifax",
    "sg:classifiers":[
        {
            "category":"Professional",
            "subcategory":"Management & Consulting",
            "type":"Services"
        }
    ],
    "sg:phone":"+1 902 443 9170",
    "sg:postcode":"B3M 2L9",
    "sg:province":"NS",
    "sg:tags":[
        "consultant",
        "business"
    ],
    "wof:name":"Commodity House Inc",
    "wof:placetype":"venue"
},
  "geometry": {"coordinates":[-63.664967,44.706963],"type":"Point"}
}