{
  "type": "Feature",
  "properties": {
    "addr:full":"1084 Rue Saint-Jean Quebec QC G1R 1S4",
    "addr:housenumber":"1084",
    "addr:postcode":"g1r 1s4",
    "addr:street":"Rue Saint-Jean",
    "iso:country":"CA",
    "sg:address":"1084 Rue Saint-Jean",
    "sg:city":"Quebec",
    "sg:classifiers":[
        {
            "category":"Food & Beverages",
            "subcategory":"Specialty",
            "type":"Retail Goods"
        }
    ],
    "sg:phone":"+1 418 692 3900",
    "sg:postcode":"G1R 1S4",
    "sg:province":"QC",
    "sg:tags":[
        "tea",
        "coffee"
    ],
    "wof:name":"Brulerie Tatum Cafe",
    "wof:placetype":"venue"
},
  "geometry": {"coordinates":[-71.2111740112,46.8137626648],"type":"Point"}
}