{
  "type": "Feature",
  "properties": {
    "addr:full":"Kitchener ON N2B 2E2",
    "addr:postcode":"n2b 2e2",
    "iso:country":"CA",
    "sg:city":"Kitchener",
    "sg:classifiers":[
        {
            "category":"Professional",
            "subcategory":"Business Services",
            "type":"Services"
        }
    ],
    "sg:phone":"+1 519 578 7779",
    "sg:postcode":"N2B 2E2",
    "sg:province":"ON",
    "wof:name":"Brolain Distributors Ltd",
    "wof:placetype":"venue"
},
  "geometry": {"coordinates":[-80.46605700000001,43.465828],"type":"Point"}
}