{
  "type": "Feature",
  "properties": {
    "addr:full":"405 Rue Samuel-DE Champlain Boucherville QC J4B 1P7",
    "addr:housenumber":"405",
    "addr:postcode":"j4b 1p7",
    "addr:street":"Rue Samuel-De Champlain",
    "iso:country":"CA",
    "sg:address":"405 Rue Samuel-DE Champlain",
    "sg:city":"Boucherville",
    "sg:classifiers":[
        {
            "category":"Health Services",
            "subcategory":"Medical Lab",
            "type":"Services"
        }
    ],
    "sg:phone":"+1 450 449 3948",
    "sg:postcode":"J4B 1P7",
    "sg:province":"QC",
    "sg:tags":[
        "laboratory"
    ],
    "wof:name":"Laboratoire Dentaire Exacto",
    "wof:placetype":"venue"
},
  "geometry": {"coordinates":[-73.4489364624,45.5983886719],"type":"Point"}
}