{
  "type": "Feature",
  "properties": {
    "addr:full":"1426 Boul Industriel Magog QC J1X 4V9",
    "addr:housenumber":"1426",
    "addr:postcode":"j1x 4v9",
    "addr:street":"Boul Industriel",
    "iso:country":"CA",
    "sg:address":"1426 Boul Industriel",
    "sg:city":"Magog",
    "sg:classifiers":[
        {
            "category":"Wholesale",
            "subcategory":"Toys & Hobbies",
            "type":"Manufacturing & Wholesale Goods"
        }
    ],
    "sg:phone":"+1 819 843 2847",
    "sg:postcode":"J1X 4V9",
    "sg:province":"QC",
    "wof:name":"Just 4U",
    "wof:placetype":"venue"
},
  "geometry": {"coordinates":[-72.12989,45.272282],"type":"Point"}
}