{
  "type": "Feature",
  "properties": {
    "addr:full":"1945 Provincial Rd Windsor ON N8W 5V7",
    "addr:housenumber":"1945",
    "addr:postcode":"n8w 5v7",
    "addr:street":"Provincial Rd",
    "iso:country":"CA",
    "sg:address":"1945 Provincial Rd",
    "sg:city":"Windsor",
    "sg:classifiers":[
        {
            "category":"Wholesale",
            "subcategory":"Machinery & Supplies",
            "type":"Manufacturing & Wholesale Goods"
        }
    ],
    "sg:phone":"+1 519 969 1137",
    "sg:postcode":"N8W 5V7",
    "sg:province":"ON",
    "sg:tags":[
        "compressor"
    ],
    "wof:name":"Falcon Compressors Inc",
    "wof:placetype":"venue"
},
  "geometry": {"coordinates":[-82.96825408940001,42.2528877258],"type":"Point"}
}