{
  "type": "Feature",
  "properties": {
    "iso:country":"CA",
    "sg:address":"10 Howard St",
    "sg:city":"Miramichi",
    "sg:classifiers":[
        {
            "category":"Museum",
            "type":"Entertainment"
        }
    ],
    "sg:phone":"+1 506 778 5152",
    "sg:postcode":"E1N 1V2",
    "sg:province":"NB",
    "wof:name":"Saint Michael's Museum",
    "wof:placetype":"venue"
},
  "geometry": {"coordinates":[-65.465675354,47.0267372131],"type":"Point"}
}