{
  "type": "Feature",
  "properties": {
    "addr:full":"21 State Crown Blvd Scarborough ON M1V 4B1",
    "addr:housenumber":"21",
    "addr:postcode":"m1v 4b1",
    "addr:street":"State Crown Blvd",
    "iso:country":"CA",
    "sg:address":"21 State Crown Blvd",
    "sg:city":"Scarborough",
    "sg:classifiers":[
        {
            "category":"Manufacturing",
            "subcategory":"Tools & Machinery",
            "type":"Manufacturing & Wholesale Goods"
        }
    ],
    "sg:phone":"+1 416 297 5121",
    "sg:postcode":"M1V 4B1",
    "sg:province":"ON",
    "sg:tags":[
        "die",
        "maker"
    ],
    "wof:name":"Castool Tooling Solutions",
    "wof:placetype":"venue"
},
  "geometry": {"coordinates":[-79.258804,43.829601],"type":"Point"}
}