{
  "type": "Feature",
  "properties": {
    "addr:full":"Rycroft AB T0H 3A0",
    "addr:postcode":"t0h 3a0",
    "iso:country":"CA",
    "sg:city":"Rycroft",
    "sg:classifiers":[
        {
            "category":"Food & Beverages",
            "subcategory":"Groceries & Convenience Stores",
            "type":"Retail Goods"
        }
    ],
    "sg:phone":"+1 780 765 3900",
    "sg:postcode":"T0H 3A0",
    "sg:province":"AB",
    "sg:tags":[
        "market"
    ],
    "wof:name":"Golden Maple Gardens",
    "wof:placetype":"venue"
},
  "geometry": {"coordinates":[-118.704849,55.754356],"type":"Point"}
}