{
  "type": "Feature",
  "properties": {
    "addr:full":"8080 Rte Transcanadienne Saint-Laurent QC H4S 1M5",
    "addr:housenumber":"8080",
    "addr:postcode":"h4s 1m5",
    "addr:street":"Rte Transcanadienne",
    "iso:country":"CA",
    "sg:address":"8080 Rte Transcanadienne",
    "sg:city":"Saint-Laurent",
    "sg:classifiers":[
        {
            "category":"Manufacturing",
            "subcategory":"Tools & Machinery",
            "type":"Manufacturing & Wholesale Goods"
        }
    ],
    "sg:phone":"+1 514 331 9812",
    "sg:postcode":"H4S 1M5",
    "sg:province":"QC",
    "sg:tags":[
        "battery",
        "equipment",
        "charging"
    ],
    "wof:name":"Spectrodyne Systems Intl Inc",
    "wof:placetype":"venue"
},
  "geometry": {"coordinates":[-73.72125200000001,45.488922],"type":"Point"}
}