{
  "type": "Feature",
  "properties": {
    "iso:country":"CA",
    "sg:address":"10808 15 St",
    "sg:city":"Dawson Creek",
    "sg:classifiers":[
        {
            "category":"Education",
            "subcategory":"School",
            "type":"Public Place"
        }
    ],
    "sg:phone":"+1 250 782 5585",
    "sg:postcode":"V1G 3Z3",
    "sg:province":"BC",
    "wof:name":"South Peace Secondary School",
    "wof:placetype":"venue"
},
  "geometry": {"coordinates":[-120.24418640099999,55.7521286011],"type":"Point"}
}