{
  "type": "Feature",
  "properties": {
    "addr:full":"3464 Semenyk Crt Mississauga ON L5C 4P8",
    "addr:housenumber":"3464",
    "addr:postcode":"l5c 4p8",
    "addr:street":"Semenyk Crt",
    "iso:country":"CA",
    "sg:address":"3464 Semenyk Crt",
    "sg:city":"Mississauga",
    "sg:classifiers":[
        {
            "category":"Professional",
            "type":"Services"
        }
    ],
    "sg:phone":"+1 416 410 4292",
    "sg:postcode":"L5C 4P8",
    "sg:province":"ON",
    "sg:tags":[
        "establishment",
        "internet"
    ],
    "wof:name":"Echo Online",
    "wof:placetype":"venue"
},
  "geometry": {"coordinates":[-79.6532897949,43.5683898926],"type":"Point"}
}