{
  "type": "Feature",
  "properties": {
    "iso:country":"CA",
    "sg:address":"Hwy Rte 220",
    "sg:city":"Grand Bank",
    "sg:classifiers":[
        {
            "category":"Shopping",
            "subcategory":"Pharmacy",
            "type":"Retail Goods"
        }
    ],
    "sg:phone":"+1 709 832 2071",
    "sg:postcode":"A0E 1W0",
    "sg:province":"NL",
    "wof:name":"Sobeys Pharmacy",
    "wof:placetype":"venue"
},
  "geometry": {"coordinates":[-55.7579421997,47.0944137573],"type":"Point"}
}