{
  "type": "Feature",
  "properties": {
    "addr:full":"Kentville NS B4N 3V8",
    "addr:postcode":"b4n 3v8",
    "iso:country":"CA",
    "sg:city":"Kentville",
    "sg:classifiers":[
        {
            "category":"Restaurant",
            "type":"Food & Drink"
        }
    ],
    "sg:phone":"+1 902 678 8227",
    "sg:postcode":"B4N 3V8",
    "sg:province":"NS",
    "wof:name":"Mc Donald's",
    "wof:placetype":"venue"
},
  "geometry": {"coordinates":[-64.4925765991,45.0722236633],"type":"Point"}
}