{
  "type": "Feature",
  "properties": {
    "addr:full":"481 Rue Frontenac Berthierville QC J0K 1A0",
    "addr:housenumber":"481",
    "addr:postcode":"j0k 1a0",
    "addr:street":"Rue Frontenac",
    "iso:country":"CA",
    "sg:address":"481 Rue Frontenac",
    "sg:city":"Berthierville",
    "sg:classifiers":[
        {
            "category":"Bars & Pubs",
            "type":"Food & Drink"
        }
    ],
    "sg:phone":"+1 450 836 1938",
    "sg:postcode":"J0K 1A0",
    "sg:province":"QC",
    "sg:tags":[
        "lounge",
        "cocktail"
    ],
    "wof:name":"Pub 481",
    "wof:placetype":"venue"
},
  "geometry": {"coordinates":[-73.17175292970001,46.0836601257],"type":"Point"}
}