{
  "type": "Feature",
  "properties": {
    "addr:full":"46 Montreal Ave S Wawa ON P0S 1K0",
    "addr:housenumber":"46",
    "addr:postcode":"p0s 1k0",
    "addr:street":"Montreal Ave S",
    "iso:country":"CA",
    "sg:address":"46 Montreal Ave S",
    "sg:city":"Wawa",
    "sg:classifiers":[
        {
            "category":"Building & Trades",
            "subcategory":"Construction",
            "type":"Services"
        }
    ],
    "sg:phone":"+1 705 856 2846",
    "sg:postcode":"P0S 1K0",
    "sg:province":"ON",
    "sg:tags":[
        "home",
        "cabinet",
        "improvement",
        "kitchen",
        "equipment"
    ],
    "wof:name":"Shop",
    "wof:placetype":"venue"
},
  "geometry": {"coordinates":[-84.768539,47.989265],"type":"Point"}
}