{
  "type": "Feature",
  "properties": {
    "addr:full":"LA Loche Ave LA Loche SK S0M 1G0",
    "addr:postcode":"s0m 1g0",
    "addr:street":"Loche Ave",
    "iso:country":"CA",
    "sg:address":"LA Loche Ave",
    "sg:city":"LA Loche",
    "sg:classifiers":[
        {
            "category":"Government",
            "subcategory":"Office",
            "type":"Public Place"
        }
    ],
    "sg:phone":"+1 306 822 1711",
    "sg:postcode":"S0M 1G0",
    "sg:province":"SK",
    "wof:name":"Saskatchewan Child & Family",
    "wof:placetype":"venue"
},
  "geometry": {"coordinates":[-109.436096191,56.482334137],"type":"Point"}
}