{
  "type": "Feature",
  "properties": {
    "addr:full":"1193 Oxford St E London ON N5Y 3M2",
    "addr:housenumber":"1193",
    "addr:postcode":"n5y 3m2",
    "addr:street":"Oxford St E",
    "iso:country":"CA",
    "sg:address":"1193 Oxford St E",
    "sg:city":"London",
    "sg:classifiers":[
        {
            "category":"Home & Garden",
            "subcategory":"Furniture",
            "type":"Retail Goods"
        }
    ],
    "sg:phone":"+1 519 439 3241",
    "sg:postcode":"N5Y 3M2",
    "sg:province":"ON",
    "sg:tags":[
        "bedding"
    ],
    "wof:name":"Savannah Sheeting CO",
    "wof:placetype":"venue"
},
  "geometry": {"coordinates":[-81.21331000000001,43.007069],"type":"Point"}
}