{
  "type": "Feature",
  "properties": {
    "addr:full":"3005 Boul Matte # 101 Brossard QC J4Y 2P4",
    "addr:housenumber":"3005",
    "addr:postcode":"j4y 2p4",
    "addr:street":"Boul Matte # 101",
    "iso:country":"CA",
    "sg:address":"3005 Boul Matte # 101",
    "sg:city":"Brossard",
    "sg:classifiers":[
        {
            "category":"Retail",
            "subcategory":"Auto Repair",
            "type":"Services"
        }
    ],
    "sg:phone":"+1 450 659 8484",
    "sg:postcode":"J4Y 2P4",
    "sg:province":"QC",
    "sg:tags":[
        "body",
        "automobile",
        "painting"
    ],
    "wof:name":"Fix Auto Brossard",
    "wof:placetype":"venue"
},
  "geometry": {"coordinates":[-73.47068,45.43293],"type":"Point"}
}