{
  "type": "Feature",
  "properties": {
    "addr:full":"12345 84 Ave Surrey BC V3W 3G8",
    "addr:housenumber":"12345",
    "addr:postcode":"v3w 3g8",
    "addr:street":"84 Ave",
    "iso:country":"CA",
    "sg:address":"12345 84 Ave",
    "sg:city":"Surrey",
    "sg:classifiers":[
        {
            "category":"Freight",
            "type":"Transportation"
        }
    ],
    "sg:phone":"+1 604 543 1684",
    "sg:postcode":"V3W 3G8",
    "sg:province":"BC",
    "sg:tags":[
        "trucking"
    ],
    "wof:name":"Premier Freight Systems Inc",
    "wof:placetype":"venue"
},
  "geometry": {"coordinates":[-122.880821,49.155964],"type":"Point"}
}