{
  "type": "Feature",
  "properties": {
    "addr:full":"40 Rue Evangeline Granby QC J2G 8K1",
    "addr:housenumber":"40",
    "addr:postcode":"j2g 8k1",
    "addr:street":"Rue Evangeline",
    "iso:country":"CA",
    "sg:address":"40 Rue Evangeline",
    "sg:city":"Granby",
    "sg:classifiers":[
        {
            "category":"Restaurant",
            "type":"Food & Drink"
        }
    ],
    "sg:phone":"+1 450 375 8228",
    "sg:postcode":"J2G 8K1",
    "sg:province":"QC",
    "sg:tags":[
        "shop",
        "coffee"
    ],
    "wof:name":"Cafe Depot",
    "wof:placetype":"venue"
},
  "geometry": {"coordinates":[-72.7486190796,45.4135284424],"type":"Point"}
}