{
  "type": "Feature",
  "properties": {
    "iso:country":"CA",
    "sg:address":"921 Broad St",
    "sg:city":"Regina",
    "sg:classifiers":[
        {
            "category":"Building & Trades",
            "subcategory":"Plumbing",
            "type":"Services"
        }
    ],
    "sg:phone":"+1 306 525 4299",
    "sg:postcode":"S4R 8G9",
    "sg:province":"SK",
    "sg:tags":[
        "refrigeration",
        "contractor"
    ],
    "wof:name":"Display Fixtures Saskatchewan",
    "wof:placetype":"venue"
},
  "geometry": {"coordinates":[-104.60610961899999,50.4641914368],"type":"Point"}
}