{
  "type": "Feature",
  "properties": {
    "iso:country":"CA",
    "sg:city":"Ottawa",
    "sg:classifiers":[
        {
            "category":"Organizations",
            "subcategory":"Professional Association",
            "type":"Services"
        }
    ],
    "sg:phone":"+1 613 562 1202",
    "sg:postcode":"K1N 7E4",
    "sg:province":"ON",
    "wof:name":"Canadian Political Science",
    "wof:placetype":"venue"
},
  "geometry": {"coordinates":[-75.6927947998,45.4304542542],"type":"Point"}
}