{
  "type": "Feature",
  "properties": {
    "addr:full":"10112 24 St SE Calgary AB T2C 3X7",
    "addr:housenumber":"10112",
    "addr:postcode":"t2c 3x7",
    "addr:street":"24 St Se",
    "iso:country":"CA",
    "sg:address":"10112 24 St SE",
    "sg:city":"Calgary",
    "sg:classifiers":[
        {
            "category":"Freight",
            "type":"Transportation"
        }
    ],
    "sg:phone":"+1 403 279 7571",
    "sg:postcode":"T2C 3X7",
    "sg:province":"AB",
    "sg:tags":[
        "trucking"
    ],
    "wof:name":"Walton Enterprise Inc",
    "wof:placetype":"venue"
},
  "geometry": {"coordinates":[-114.00145000000001,50.962879],"type":"Point"}
}