{
  "type": "Feature",
  "properties": {
    "addr:full":"140 Av DE L'Eglise Dolbeau-Mistassini QC G8L 4W6",
    "addr:postcode":"g8l 4w6",
    "addr:street":"140 Av De L'Eglise",
    "iso:country":"CA",
    "sg:address":"140 Av DE L'Eglise",
    "sg:city":"Dolbeau-Mistassini",
    "sg:classifiers":[
        {
            "category":"Recreation",
            "type":"Entertainment"
        }
    ],
    "sg:phone":"+1 418 276 1241",
    "sg:postcode":"G8L 4W6",
    "sg:province":"QC",
    "sg:tags":[
        "event",
        "carnival"
    ],
    "wof:name":"Festival Du Bleuet",
    "wof:placetype":"venue"
},
  "geometry": {"coordinates":[-72.20044708250001,48.8933486938],"type":"Point"}
}