{
  "type": "Feature",
  "properties": {
    "addr:full":"197 Bond St E Oshawa ON L1G 1B4",
    "addr:housenumber":"197",
    "addr:postcode":"l1g 1b4",
    "addr:street":"Bond St E",
    "iso:country":"CA",
    "sg:address":"197 Bond St E",
    "sg:city":"Oshawa",
    "sg:classifiers":[
        {
            "category":"Professional",
            "subcategory":"Lawyer & Legal Services",
            "type":"Services"
        }
    ],
    "sg:phone":"+1 905 579 1121",
    "sg:postcode":"L1G 1B4",
    "sg:province":"ON",
    "sg:tags":[
        "attorney"
    ],
    "wof:name":"Kelly, William F",
    "wof:placetype":"venue"
},
  "geometry": {"coordinates":[-78.85684999999999,43.89996],"type":"Point"}
}