{
  "type": "Feature",
  "properties": {
    "iso:country":"CA",
    "sg:address":"197 Bond St E",
    "sg:city":"Oshawa",
    "sg:classifiers":[
        {
            "category":"Professional",
            "subcategory":"Lawyer & Legal Services",
            "type":"Services"
        }
    ],
    "sg:phone":"+1 905 579 1121",
    "sg:postcode":"L1G 1B4",
    "sg:province":"ON",
    "sg:tags":[
        "attorney"
    ],
    "wof:name":"Kelly, William F",
    "wof:placetype":"venue"
},
  "geometry": {"coordinates":[-78.85685,43.89996],"type":"Point"}
}