{
  "type": "Feature",
  "properties": {
    "addr:full":"98 Rue Notre-Dame E Victoriaville QC G6P 3Z6",
    "addr:housenumber":"98",
    "addr:postcode":"g6p 3z6",
    "addr:street":"Rue Notre-Dame E",
    "iso:country":"CA",
    "sg:address":"98 Rue Notre-Dame E",
    "sg:city":"Victoriaville",
    "sg:classifiers":[
        {
            "category":"Shopping",
            "subcategory":"Clothing, Apparel, & Fashions",
            "type":"Retail Goods"
        }
    ],
    "sg:phone":"+1 819 758 8336",
    "sg:postcode":"G6P 3Z6",
    "sg:province":"QC",
    "sg:tags":[
        "salon",
        "boutique",
        "beauty"
    ],
    "wof:name":"Boutique Du Cheveu",
    "wof:placetype":"venue"
},
  "geometry": {"coordinates":[-71.956451,46.056679],"type":"Point"}
}