{
  "type": "Feature",
  "properties": {
    "addr:full":"601 10 Ave SE Salmon Arm BC V1E 2C2",
    "addr:postcode":"v1e 2c2",
    "addr:street":"601 10 Ave Se",
    "iso:country":"CA",
    "sg:address":"601 10 Ave SE",
    "sg:city":"Salmon Arm",
    "sg:classifiers":[
        {
            "category":"Health Services",
            "subcategory":"Hospital",
            "type":"Services"
        }
    ],
    "sg:phone":"+1 250 833 3600",
    "sg:postcode":"V1E 2C2",
    "sg:province":"BC",
    "wof:name":"Shuswap Lake General Hospital",
    "wof:placetype":"venue"
},
  "geometry": {"coordinates":[-119.27340700000001,50.691067],"type":"Point"}
}