{
  "type": "Feature",
  "properties": {
    "iso:country":"CA",
    "sg:address":"595 Riddell Rd",
    "sg:city":"Orangeville",
    "sg:classifiers":[
        {
            "category":"Manufacturing",
            "subcategory":"Rubber & Plastics",
            "type":"Manufacturing & Wholesale Goods"
        }
    ],
    "sg:phone":"+1 416 626 1582",
    "sg:postcode":"L9W 4Z5",
    "sg:province":"ON",
    "sg:tags":[
        "tubing",
        "hose"
    ],
    "wof:name":"Plastiflex Canada Inc",
    "wof:placetype":"venue"
},
  "geometry": {"coordinates":[-80.1157913208,43.8989562988],"type":"Point"}
}