{
  "type": "Feature",
  "properties": {
    "addr:full":"14 Cameron W Cannington ON L0E 1E0",
    "addr:housenumber":"14",
    "addr:postcode":"l0e 1e0",
    "addr:street":"Cameron W",
    "iso:country":"CA",
    "sg:address":"14 Cameron W",
    "sg:city":"Cannington",
    "sg:classifiers":[
        {
            "category":"Restaurant",
            "type":"Food & Drink"
        }
    ],
    "sg:phone":"+1 705 432 3200",
    "sg:postcode":"L0E 1E0",
    "sg:province":"ON",
    "wof:name":"Locker",
    "wof:placetype":"venue"
},
  "geometry": {"coordinates":[-79.039131,44.349953],"type":"Point"}
}