{
  "type": "Feature",
  "properties": {
    "addr:full":"Victoria BC V8Z 6E3",
    "addr:postcode":"v8z 6e3",
    "iso:country":"CA",
    "sg:city":"Victoria",
    "sg:classifiers":[
        {
            "category":"Shopping",
            "subcategory":"Clothing, Apparel, & Fashions",
            "type":"Retail Goods"
        }
    ],
    "sg:phone":"+1 250 381 8878",
    "sg:postcode":"V8Z 6E3",
    "sg:province":"BC",
    "wof:name":"Garage Clothing CO",
    "wof:placetype":"venue"
},
  "geometry": {"coordinates":[-123.37140655499999,48.4463806152],"type":"Point"}
}