{
  "type": "Feature",
  "properties": {
    "addr:full":"2175 Tecumseh Rd W Windsor ON N9B 1V9",
    "addr:housenumber":"2175",
    "addr:postcode":"n9b 1v9",
    "addr:street":"Tecumseh Rd W",
    "iso:country":"CA",
    "sg:address":"2175 Tecumseh Rd W",
    "sg:city":"Windsor",
    "sg:classifiers":[
        {
            "category":"Autos & Motor Vehicles",
            "subcategory":"Automobile Sales",
            "type":"Retail Goods"
        }
    ],
    "sg:phone":"+1 519 977 6320",
    "sg:postcode":"N9B 1V9",
    "sg:province":"ON",
    "sg:tags":[
        "car",
        "dealer"
    ],
    "wof:name":"A & D Enterprise",
    "wof:placetype":"venue"
},
  "geometry": {"coordinates":[-83.052986,42.292694],"type":"Point"}
}