{
  "type": "Feature",
  "properties": {
    "addr:full":"Calgary AB T2P 3N4",
    "addr:postcode":"t2p 3n4",
    "iso:country":"CA",
    "sg:city":"Calgary",
    "sg:classifiers":[
        {
            "category":"Mining & Drilling",
            "type":"Manufacturing & Wholesale Goods"
        }
    ],
    "sg:phone":"+1 403 221 0800",
    "sg:postcode":"T2P 3N4",
    "sg:province":"AB",
    "sg:tags":[
        "company",
        "oil"
    ],
    "wof:name":"Rife Resources Ltd",
    "wof:placetype":"venue"
},
  "geometry": {"coordinates":[-114.063889,51.049454],"type":"Point"}
}