{
  "type": "Feature",
  "properties": {
    "iso:country":"CA",
    "sg:city":"Mississauga",
    "sg:classifiers":[
        {
            "category":"Airline",
            "type":"Transportation"
        }
    ],
    "sg:phone":"+1 905 672 5600",
    "sg:postcode":"L5P 1A2",
    "sg:province":"ON",
    "sg:tags":[
        "cargo",
        "air"
    ],
    "wof:name":"Cas Cargo & Travel",
    "wof:placetype":"venue"
},
  "geometry": {"coordinates":[-79.629913,43.692299],"type":"Point"}
}