{
  "type": "Feature",
  "properties": {
    "iso:country":"CA",
    "sg:address":"2520 Centre Ave NE",
    "sg:city":"Calgary",
    "sg:classifiers":[
        {
            "category":"Professional",
            "subcategory":"Advertising",
            "type":"Services"
        }
    ],
    "sg:phone":"+1 403 235 3214",
    "sg:postcode":"T2A 2L2",
    "sg:province":"AB",
    "sg:tags":[
        "counselor"
    ],
    "wof:name":"Touchstone Communications",
    "wof:placetype":"venue"
},
  "geometry": {"coordinates":[-114.000465393,51.0524978638],"type":"Point"}
}