{
  "type": "Feature",
  "properties": {
    "addr:full":"Terrebonne QC J6X 4J8",
    "addr:postcode":"j6x 4j8",
    "iso:country":"CA",
    "sg:city":"Terrebonne",
    "sg:classifiers":[
        {
            "category":"Professional",
            "subcategory":"Lawyer & Legal Services",
            "type":"Services"
        }
    ],
    "sg:phone":"+1 450 682 1090",
    "sg:postcode":"J6X 4J8",
    "sg:province":"QC",
    "sg:tags":[
        "attorney"
    ],
    "wof:name":"Picard Gauthier",
    "wof:placetype":"venue"
},
  "geometry": {"coordinates":[-73.689995,45.724689],"type":"Point"}
}