{
  "type": "Feature",
  "properties": {
    "addr:full":"86 Princess St Kingston ON K7L 1A5",
    "addr:housenumber":"86",
    "addr:postcode":"k7l 1a5",
    "addr:street":"Princess St",
    "iso:country":"CA",
    "sg:address":"86 Princess St",
    "sg:city":"Kingston",
    "sg:classifiers":[
        {
            "category":"Personal",
            "subcategory":"Adult",
            "type":"Services"
        }
    ],
    "sg:phone":"+1 613 536 5188",
    "sg:postcode":"K7L 1A5",
    "sg:province":"ON",
    "sg:tags":[
        "escort",
        "massage"
    ],
    "wof:name":"Touch of Class",
    "wof:placetype":"venue"
},
  "geometry": {"coordinates":[-76.481972,44.231323],"type":"Point"}
}