{
  "type": "Feature",
  "properties": {
    "addr:full":"Etobicoke ON M9W 6J3",
    "addr:postcode":"m9w 6j3",
    "iso:country":"CA",
    "sg:city":"Etobicoke",
    "sg:classifiers":[
        {
            "category":"Retail",
            "subcategory":"Auto Repair",
            "type":"Services"
        }
    ],
    "sg:phone":"+1 416 741 9640",
    "sg:postcode":"M9W 6J3",
    "sg:province":"ON",
    "sg:tags":[
        "repairing",
        "automobile"
    ],
    "wof:name":"Airview Motors Inc",
    "wof:placetype":"venue"
},
  "geometry": {"coordinates":[-79.57579,43.720367],"type":"Point"}
}