{
  "type": "Feature",
  "properties": {
    "addr:full":"2069 Lakeshore Rd Burlington ON L7R 1E2",
    "addr:housenumber":"2069",
    "addr:postcode":"l7r 1e2",
    "addr:street":"Lakeshore Rd",
    "iso:country":"CA",
    "sg:address":"2069 Lakeshore Rd",
    "sg:city":"Burlington",
    "sg:classifiers":[
        {
            "category":"Health Services",
            "subcategory":"Doctor",
            "type":"Services"
        }
    ],
    "sg:phone":"+1 905 681 1536",
    "sg:postcode":"L7R 1E2",
    "sg:province":"ON",
    "sg:tags":[
        "dentist"
    ],
    "wof:name":"Paszt, C C DDS",
    "wof:placetype":"venue"
},
  "geometry": {"coordinates":[-79.793404,43.326077],"type":"Point"}
}