{
  "type": "Feature",
  "properties": {
    "addr:full":"101 Bell Blvd Belleville ON K8P 4V2",
    "addr:housenumber":"101",
    "addr:postcode":"k8p 4v2",
    "addr:street":"Bell Blvd",
    "iso:country":"CA",
    "sg:address":"101 Bell Blvd",
    "sg:city":"Belleville",
    "sg:classifiers":[
        {
            "category":"Autos & Motor Vehicles",
            "subcategory":"Auto Supplies",
            "type":"Retail Goods"
        }
    ],
    "sg:phone":"+1 613 968 6701",
    "sg:postcode":"K8P 4V2",
    "sg:province":"ON",
    "sg:tags":[
        "automobile",
        "parts"
    ],
    "wof:name":"Canadian Tire",
    "wof:placetype":"venue"
},
  "geometry": {"coordinates":[-77.39771270750001,44.1878242493],"type":"Point"}
}