{
  "type": "Feature",
  "properties": {
    "addr:full":"5375 Rue Pare Mont-Royal QC H4P 1P7",
    "addr:housenumber":"5375",
    "addr:postcode":"h4p 1p7",
    "addr:street":"Rue Pare",
    "iso:country":"CA",
    "sg:address":"5375 Rue Pare",
    "sg:city":"Mont-Royal",
    "sg:classifiers":[
        {
            "category":"Personal",
            "type":"Services"
        }
    ],
    "sg:phone":"+1 514 343 9092",
    "sg:postcode":"H4P 1P7",
    "sg:province":"QC",
    "sg:tags":[
        "buyer"
    ],
    "wof:name":"Getel International Fashions",
    "wof:placetype":"venue"
},
  "geometry": {"coordinates":[-73.6576766968,45.4945755005],"type":"Point"}
}