{
  "type": "Feature",
  "properties": {
    "addr:full":"Coldbrook NS B4R 1B7",
    "addr:postcode":"b4r 1b7",
    "iso:country":"CA",
    "sg:city":"Coldbrook",
    "sg:classifiers":[
        {
            "category":"Shopping",
            "subcategory":"Pharmacy",
            "type":"Retail Goods"
        }
    ],
    "sg:phone":"+1 902 679 1251",
    "sg:postcode":"B4R 1B7",
    "sg:province":"NS",
    "wof:name":"Mader's Pharmachoice Pharmacy",
    "wof:placetype":"venue"
},
  "geometry": {"coordinates":[-64.59893798829999,45.0615615845],"type":"Point"}
}