{
  "type": "Feature",
  "properties": {
    "addr:full":"5357 Av Du Parc Montreal QC H2V 4G9",
    "addr:housenumber":"5357",
    "addr:postcode":"h2v 4g9",
    "addr:street":"Av Du Parc",
    "iso:country":"CA",
    "sg:address":"5357 Av Du Parc",
    "sg:city":"Montreal",
    "sg:classifiers":[
        {
            "category":"Restaurant",
            "type":"Food & Drink"
        }
    ],
    "sg:phone":"+1 514 272 3522",
    "sg:postcode":"H2V 4G9",
    "sg:province":"QC",
    "wof:name":"Milos Restaurant",
    "wof:placetype":"venue"
},
  "geometry": {"coordinates":[-73.59998299999999,45.521389],"type":"Point"}
}