{
  "type": "Feature",
  "properties": {
    "iso:country":"CA",
    "sg:address":"5357 Av Du Parc",
    "sg:city":"Montreal",
    "sg:classifiers":[
        {
            "category":"Restaurant",
            "type":"Food & Drink"
        }
    ],
    "sg:phone":"+1 514 272 3522",
    "sg:postcode":"H2V 4G9",
    "sg:province":"QC",
    "wof:name":"Milos Restaurant",
    "wof:placetype":"venue"
},
  "geometry": {"coordinates":[-73.599983,45.521389],"type":"Point"}
}