{
  "type": "Feature",
  "properties": {
    "addr:full":"North York ON M2K 1G4",
    "addr:postcode":"m2k 1g4",
    "iso:country":"CA",
    "sg:city":"North York",
    "sg:classifiers":[
        {
            "category":"Health Services",
            "subcategory":"Doctor",
            "type":"Services"
        }
    ],
    "sg:phone":"+1 416 221 0660",
    "sg:postcode":"M2K 1G4",
    "sg:province":"ON",
    "sg:tags":[
        "dentist"
    ],
    "wof:name":"Aynaciyan, Raffi DDS",
    "wof:placetype":"venue"
},
  "geometry": {"coordinates":[-79.393333,43.792019],"type":"Point"}
}