{
  "type": "Feature",
  "properties": {
    "addr:full":"315 Adelaide St W Toronto ON M5V 1P8",
    "addr:housenumber":"315",
    "addr:postcode":"m5v 1p8",
    "addr:street":"Adelaide St W",
    "iso:country":"CA",
    "sg:address":"315 Adelaide St W",
    "sg:city":"Toronto",
    "sg:classifiers":[
        {
            "category":"Wholesale",
            "subcategory":"Non-durable Goods",
            "type":"Manufacturing & Wholesale Goods"
        }
    ],
    "sg:phone":"+1 416 977 6849",
    "sg:postcode":"M5V 1P8",
    "sg:province":"ON",
    "sg:tags":[
        "leather",
        "tours",
        "sightseeing"
    ],
    "wof:name":"Showflex International Inc",
    "wof:placetype":"venue"
},
  "geometry": {"coordinates":[-79.392151,43.647308],"type":"Point"}
}