{
  "type": "Feature",
  "properties": {
    "addr:full":"3055 Boul Wilfrid-Hamel # 114 Quebec QC G1P 4C6",
    "addr:housenumber":"3055",
    "addr:postcode":"g1p 4c6",
    "addr:street":"Boul Wilfrid-Hamel # 114",
    "iso:country":"CA",
    "sg:address":"3055 Boul Wilfrid-Hamel # 114",
    "sg:city":"Quebec",
    "sg:classifiers":[
        {
            "category":"Building & Trades",
            "subcategory":"Construction",
            "type":"Services"
        }
    ],
    "sg:phone":"+1 418 871 9229",
    "sg:postcode":"G1P 4C6",
    "sg:province":"QC",
    "sg:tags":[
        "repairing",
        "cabinet",
        "equipment",
        "contractor",
        "remodeling",
        "kitchen"
    ],
    "wof:name":"Armoires G Baron Inc",
    "wof:placetype":"venue"
},
  "geometry": {"coordinates":[-71.305077,46.806343],"type":"Point"}
}