{
  "type": "Feature",
  "properties": {
    "addr:full":"1139 Austin Ave Coquitlam BC V3K 3P4",
    "addr:housenumber":"1139",
    "addr:postcode":"v3k 3p4",
    "addr:street":"Austin Ave",
    "iso:country":"CA",
    "sg:address":"1139 Austin Ave",
    "sg:city":"Coquitlam",
    "sg:classifiers":[
        {
            "category":"Restaurant",
            "type":"Food & Drink"
        }
    ],
    "sg:phone":"+1 604 939 8630",
    "sg:postcode":"V3K 3P4",
    "sg:province":"BC",
    "wof:name":"Lucky Gate Restaurant",
    "wof:placetype":"venue"
},
  "geometry": {"coordinates":[-122.860466,49.249111],"type":"Point"}
}