{
  "type": "Feature",
  "properties": {
    "addr:full":"40 Gerrard St E # 40 Toronto ON M5B 2E8",
    "addr:housenumber":"40",
    "addr:postcode":"m5b 2e8",
    "addr:street":"Gerrard St E # 40",
    "iso:country":"CA",
    "sg:address":"40 Gerrard St E # 40",
    "sg:city":"Toronto",
    "sg:classifiers":[
        {
            "category":"Real Estate",
            "subcategory":"Real Estate Operator",
            "type":"Services"
        }
    ],
    "sg:phone":"+1 416 977 2921",
    "sg:postcode":"M5B 2E8",
    "sg:province":"ON",
    "sg:tags":[
        "apartment"
    ],
    "wof:name":"Maple Leaf Properties",
    "wof:placetype":"venue"
},
  "geometry": {"coordinates":[-79.381226,43.659401],"type":"Point"}
}