{
  "type": "Feature",
  "properties": {
    "iso:country":"CA",
    "sg:address":"3599 LA Grande-Allee",
    "sg:city":"Saint-Hubert",
    "sg:classifiers":[
        {
            "category":"Home & Garden",
            "subcategory":"Household Appliances",
            "type":"Retail Goods"
        }
    ],
    "sg:phone":"+1 450 656 2865",
    "sg:postcode":"J4T 2V1",
    "sg:province":"QC",
    "sg:tags":[
        "machine",
        "sewing"
    ],
    "wof:name":"Sos Machines A Coudre",
    "wof:placetype":"venue"
},
  "geometry": {"coordinates":[-73.4702453613,45.4928741455],"type":"Point"}
}