{
  "type": "Feature",
  "properties": {
    "addr:full":"630 Boul DE LA Gappe Gatineau QC J8T 7S8",
    "addr:housenumber":"630",
    "addr:postcode":"j8t 7s8",
    "addr:street":"Boul De La Gappe",
    "iso:country":"CA",
    "sg:address":"630 Boul DE LA Gappe",
    "sg:city":"Gatineau",
    "sg:classifiers":[
        {
            "category":"Travel",
            "subcategory":"Hotels & Motels",
            "type":"Entertainment"
        }
    ],
    "sg:phone":"+1 819 243 6010",
    "sg:postcode":"J8T 7S8",
    "sg:province":"QC",
    "wof:name":"Comfort Inn Gatineau",
    "wof:placetype":"venue"
},
  "geometry": {"coordinates":[-75.69092559809999,45.4809455872],"type":"Point"}
}