{
  "type": "Feature",
  "properties": {
    "iso:country":"CA",
    "sg:address":"756 Boul Barrette",
    "sg:city":"Chicoutimi",
    "sg:classifiers":[
        {
            "category":"Retail",
            "subcategory":"Auto Repair",
            "type":"Services"
        }
    ],
    "sg:phone":"+1 418 549 5656",
    "sg:postcode":"G7J 3Z7",
    "sg:province":"QC",
    "sg:tags":[
        "repairing",
        "automobile"
    ],
    "wof:name":"Service DE Pneus Ruelland Inc",
    "wof:placetype":"venue"
},
  "geometry": {"coordinates":[-71.0954589844,48.4029846191],"type":"Point"}
}