{
  "type": "Feature",
  "properties": {
    "addr:full":"572 Talbot St E Aylmer ON N5H 2W2",
    "addr:housenumber":"572",
    "addr:postcode":"n5h 2w2",
    "addr:street":"Talbot St E",
    "iso:country":"CA",
    "sg:address":"572 Talbot St E",
    "sg:city":"Aylmer",
    "sg:classifiers":[
        {
            "category":"Wholesale",
            "subcategory":"Auto Parts",
            "type":"Manufacturing & Wholesale Goods"
        }
    ],
    "sg:phone":"+1 519 773 3141",
    "sg:postcode":"N5H 2W2",
    "sg:province":"ON",
    "sg:tags":[
        "tire"
    ],
    "wof:name":"Aylmer Tire",
    "wof:placetype":"venue"
},
  "geometry": {"coordinates":[-80.96904000000001,42.769737],"type":"Point"}
}