{
  "type": "Feature",
  "properties": {
    "iso:country":"CA",
    "sg:address":"5663 Burleigh Cres SE",
    "sg:city":"Calgary",
    "sg:classifiers":[
        {
            "category":"Organizations",
            "subcategory":"Labor Organization",
            "type":"Services"
        }
    ],
    "sg:phone":"+1 403 252 7843",
    "sg:postcode":"T2H 1Z7",
    "sg:province":"AB",
    "wof:name":"Teamsters Union Local 987",
    "wof:placetype":"venue"
},
  "geometry": {"coordinates":[-114.043579102,51.0046615601],"type":"Point"}
}