{
  "type": "Feature",
  "properties": {
    "addr:full":"225 Wicksteed Ave East York ON M4H 1G5",
    "addr:housenumber":"225",
    "addr:postcode":"m4h 1g5",
    "addr:street":"Wicksteed Ave",
    "iso:country":"CA",
    "sg:address":"225 Wicksteed Ave",
    "sg:city":"East York",
    "sg:classifiers":[
        {
            "category":"Manufacturing",
            "subcategory":"Chemicals & Compounds",
            "type":"Manufacturing & Wholesale Goods"
        }
    ],
    "sg:phone":"+1 416 424 4567",
    "sg:postcode":"M4H 1G5",
    "sg:province":"ON",
    "wof:name":"Siltech Corp",
    "wof:placetype":"venue"
},
  "geometry": {"coordinates":[-79.34684753419999,43.7131767273],"type":"Point"}
}