{
  "type": "Feature",
  "properties": {
    "addr:full":"6 Rue Proulx # 4 Amqui QC G5J 3G2",
    "addr:housenumber":"6",
    "addr:postcode":"g5j 3g2",
    "addr:street":"Rue Proulx # 4",
    "iso:country":"CA",
    "sg:address":"6 Rue Proulx # 4",
    "sg:city":"Amqui",
    "sg:classifiers":[
        {
            "category":"Banks & Credit Unions",
            "subcategory":"Bank",
            "type":"Services"
        }
    ],
    "sg:phone":"+1 418 629 2091",
    "sg:postcode":"G5J 3G2",
    "sg:province":"QC",
    "wof:name":"Caisse Des Mutuellistes",
    "wof:placetype":"venue"
},
  "geometry": {"coordinates":[-67.43380737299999,48.4641952515],"type":"Point"}
}