{
  "type": "Feature",
  "properties": {
    "addr:full":"20 Pearl St Smiths Falls ON K7A 5B5",
    "addr:housenumber":"20",
    "addr:postcode":"k7a 5b5",
    "addr:street":"Pearl St",
    "iso:country":"CA",
    "sg:address":"20 Pearl St",
    "sg:city":"Smiths Falls",
    "sg:classifiers":[
        {
            "category":"Organizations",
            "subcategory":"Religious Organization",
            "type":"Services"
        }
    ],
    "sg:phone":"+1 613 283 6036",
    "sg:postcode":"K7A 5B5",
    "sg:province":"ON",
    "wof:name":"Sisters of Providence",
    "wof:placetype":"venue"
},
  "geometry": {"coordinates":[-76.01332092289999,44.8846473694],"type":"Point"}
}