{
  "type": "Feature",
  "properties": {
    "iso:country":"CA",
    "sg:address":"1967 Oak Bay Ave",
    "sg:city":"Victoria",
    "sg:classifiers":[
        {
            "category":"Shopping",
            "subcategory":"Gifts & Souvenirs",
            "type":"Retail Goods"
        }
    ],
    "sg:phone":"+1 250 595 2966",
    "sg:postcode":"V8R 1E3",
    "sg:province":"BC",
    "sg:tags":[
        "collectible"
    ],
    "wof:name":"Country Comforts",
    "wof:placetype":"venue"
},
  "geometry": {"coordinates":[-123.323226929,48.4263076782],"type":"Point"}
}