{
  "type": "Feature",
  "properties": {
    "addr:full":"99 Weber St W Kitchener ON N2H 3Z6",
    "addr:housenumber":"99",
    "addr:postcode":"n2h 3z6",
    "addr:street":"Weber St W",
    "iso:country":"CA",
    "sg:address":"99 Weber St W",
    "sg:city":"Kitchener",
    "sg:classifiers":[
        {
            "category":"Food & Beverages",
            "subcategory":"Groceries & Convenience Stores",
            "type":"Retail Goods"
        }
    ],
    "sg:phone":"+1 519 570 4270",
    "sg:postcode":"N2H 3Z6",
    "sg:province":"ON",
    "wof:name":"Water Convenience",
    "wof:placetype":"venue"
},
  "geometry": {"coordinates":[-80.4931259155,43.4542312622],"type":"Point"}
}