{
  "type": "Feature",
  "properties": {
    "addr:full":"Waterloo ON N2L 5W6",
    "addr:postcode":"n2l 5w6",
    "iso:country":"CA",
    "sg:city":"Waterloo",
    "sg:classifiers":[
        {
            "category":"Shopping",
            "subcategory":"Clothing, Apparel, & Fashions",
            "type":"Retail Goods"
        }
    ],
    "sg:phone":"+1 519 885 3811",
    "sg:postcode":"N2L 5W6",
    "sg:province":"ON",
    "wof:name":"Cotton Ginny",
    "wof:placetype":"venue"
},
  "geometry": {"coordinates":[-80.5301361084,43.4990577698],"type":"Point"}
}