{
  "type": "Feature",
  "properties": {
    "addr:full":"Kelowna BC V1X 7S8",
    "addr:postcode":"v1x 7s8",
    "iso:country":"CA",
    "sg:city":"Kelowna",
    "sg:classifiers":[
        {
            "category":"Retail",
            "subcategory":"Auto Repair",
            "type":"Services"
        }
    ],
    "sg:phone":"+1 250 765 7466",
    "sg:postcode":"V1X 7S8",
    "sg:province":"BC",
    "sg:tags":[
        "repairing",
        "automobile"
    ],
    "wof:name":"Kiss Auto Repairs",
    "wof:placetype":"venue"
},
  "geometry": {"coordinates":[-119.402801514,49.9171943665],"type":"Point"}
}