{
  "type": "Feature",
  "properties": {
    "addr:full":"809 Blackburn Mews Kingston ON K7P 2N6",
    "addr:housenumber":"809",
    "addr:postcode":"k7p 2n6",
    "addr:street":"Blackburn Mews",
    "iso:country":"CA",
    "sg:address":"809 Blackburn Mews",
    "sg:city":"Kingston",
    "sg:classifiers":[
        {
            "category":"Organizations",
            "subcategory":"Professional Association",
            "type":"Services"
        }
    ],
    "sg:phone":"+1 613 384 6272",
    "sg:postcode":"K7P 2N6",
    "sg:province":"ON",
    "wof:name":"John Howard Society of Canada",
    "wof:placetype":"venue"
},
  "geometry": {"coordinates":[-76.571198,44.251087],"type":"Point"}
}