{
  "type": "Feature",
  "properties": {
    "addr:full":"46 Myrtle Ave Yorkton SK S3N 1P5",
    "addr:housenumber":"46",
    "addr:postcode":"s3n 1p5",
    "addr:street":"Myrtle Ave",
    "iso:country":"CA",
    "sg:address":"46 Myrtle Ave",
    "sg:city":"Yorkton",
    "sg:classifiers":[
        {
            "category":"Home & Garden",
            "subcategory":"Carpets & Floor Coverings",
            "type":"Retail Goods"
        }
    ],
    "sg:phone":"+1 306 783 8392",
    "sg:postcode":"S3N 1P5",
    "sg:province":"SK",
    "sg:tags":[
        "rug"
    ],
    "wof:name":"Wagner's Flooring Ltd",
    "wof:placetype":"venue"
},
  "geometry": {"coordinates":[-102.46569100000001,51.211506],"type":"Point"}
}