{
  "type": "Feature",
  "properties": {
    "addr:full":"Fort Mcmurray AB T9H 2K4",
    "addr:postcode":"t9h 2k4",
    "iso:country":"CA",
    "sg:city":"Fort Mcmurray",
    "sg:classifiers":[
        {
            "category":"Professional",
            "subcategory":"Lawyer & Legal Services",
            "type":"Services"
        }
    ],
    "sg:phone":"+1 780 743 7356",
    "sg:postcode":"T9H 2K4",
    "sg:province":"AB",
    "sg:tags":[
        "attorney"
    ],
    "wof:name":"Legal Aid Society of Alberta",
    "wof:placetype":"venue"
},
  "geometry": {"coordinates":[-111.37968444800001,56.726776123],"type":"Point"}
}