{
  "type": "Feature",
  "properties": {
    "addr:full":"870 DE Saint-Jean Ch LA Prairie QC J5R 2L5",
    "addr:housenumber":"870",
    "addr:postcode":"j5r 2l5",
    "addr:street":"De Saint-Jean Ch",
    "iso:country":"CA",
    "sg:address":"870 DE Saint-Jean Ch",
    "sg:city":"LA Prairie",
    "sg:classifiers":[
        {
            "category":"Education",
            "subcategory":"School",
            "type":"Public Place"
        }
    ],
    "sg:phone":"+1 450 659 7657",
    "sg:postcode":"J5R 2L5",
    "sg:province":"QC",
    "wof:name":"College Jean DE LA Mennais",
    "wof:placetype":"venue"
},
  "geometry": {"coordinates":[-73.482956,45.413651],"type":"Point"}
}