{
  "type": "Feature",
  "properties": {
    "iso:country":"CA",
    "sg:city":"Duncan",
    "sg:classifiers":[
        {
            "category":"Shopping",
            "subcategory":"Pharmacy",
            "type":"Retail Goods"
        }
    ],
    "sg:phone":"+1 250 746 5191",
    "sg:postcode":"V9L 1N8",
    "sg:province":"BC",
    "wof:name":"Ingram Pharmacy",
    "wof:placetype":"venue"
},
  "geometry": {"coordinates":[-123.709411621,48.7793998718],"type":"Point"}
}