{
  "type": "Feature",
  "properties": {
    "iso:country":"CA",
    "sg:address":"1 Germain St",
    "sg:city":"Saint John",
    "sg:classifiers":[
        {
            "category":"Retail",
            "subcategory":"Laundry & Dry Cleaning",
            "type":"Services"
        }
    ],
    "sg:phone":"+1 506 634 8879",
    "sg:postcode":"E2L 4V1",
    "sg:province":"NB",
    "sg:tags":[
        "cleaners"
    ],
    "wof:name":"City Laundry Ltd",
    "wof:placetype":"venue"
},
  "geometry": {"coordinates":[-66.06089782710001,45.2737922668],"type":"Point"}
}