{
  "type": "Feature",
  "properties": {
    "addr:full":"Brantford ON N3R 5L8",
    "addr:postcode":"n3r 5l8",
    "iso:country":"CA",
    "sg:city":"Brantford",
    "sg:classifiers":[
        {
            "category":"Shopping",
            "subcategory":"Jewelry",
            "type":"Retail Goods"
        }
    ],
    "sg:phone":"+1 519 770 4222",
    "sg:postcode":"N3R 5L8",
    "sg:province":"ON",
    "sg:tags":[
        "jeweler"
    ],
    "wof:name":"Gold & Ice",
    "wof:placetype":"venue"
},
  "geometry": {"coordinates":[-80.2811050415,43.181968689],"type":"Point"}
}