{
  "type": "Feature",
  "properties": {
    "addr:full":"1180 3rd Ave Prince George BC V2L 3E5",
    "addr:housenumber":"1180",
    "addr:postcode":"v2l 3e5",
    "addr:street":"3Rd Ave",
    "iso:country":"CA",
    "sg:address":"1180 3rd Ave",
    "sg:city":"Prince George",
    "sg:classifiers":[
        {
            "category":"Social Services",
            "type":"Services"
        }
    ],
    "sg:phone":"+1 250 562 5136",
    "sg:postcode":"V2L 3E5",
    "sg:province":"BC",
    "sg:tags":[
        "organization",
        "welfare"
    ],
    "wof:name":"St Vincent DE Paul Society",
    "wof:placetype":"venue"
},
  "geometry": {"coordinates":[-122.743942,53.916553],"type":"Point"}
}