{
  "type": "Feature",
  "properties": {
    "addr:full":"612 Main St Humboldt SK S0K 2A0",
    "addr:housenumber":"612",
    "addr:postcode":"s0k 2a0",
    "addr:street":"Main St",
    "iso:country":"CA",
    "sg:address":"612 Main St",
    "sg:city":"Humboldt",
    "sg:classifiers":[
        {
            "category":"Banks & Credit Unions",
            "subcategory":"Investment Brokerage",
            "type":"Services"
        }
    ],
    "sg:phone":"+1 306 682 1601",
    "sg:postcode":"S0K 2A0",
    "sg:province":"SK",
    "sg:tags":[
        "consultant",
        "planning",
        "financial"
    ],
    "wof:name":"Bwb Wealth Management",
    "wof:placetype":"venue"
},
  "geometry": {"coordinates":[-105.122711,52.199135],"type":"Point"}
}