{
  "type": "Feature",
  "properties": {
    "iso:country":"CA",
    "sg:address":"141 Adelaide St W #703",
    "sg:city":"Toronto",
    "sg:classifiers":[
        {
            "category":"Banks & Credit Unions",
            "subcategory":"Investment Brokerage",
            "type":"Services"
        }
    ],
    "sg:phone":"+1 416 366 9264",
    "sg:postcode":"M5H 3L5",
    "sg:province":"ON",
    "wof:name":"Rapport Investor Relations",
    "wof:placetype":"venue"
},
  "geometry": {"coordinates":[-79.38427734379999,43.6489868164],"type":"Point"}
}