{
  "type": "Feature",
  "properties": {
    "addr:full":"391 Highland Rd Peterborough ON K9H 5J6",
    "addr:housenumber":"391",
    "addr:postcode":"k9h 5j6",
    "addr:street":"Highland Rd",
    "iso:country":"CA",
    "sg:address":"391 Highland Rd",
    "sg:city":"Peterborough",
    "sg:classifiers":[
        {
            "category":"Retail",
            "subcategory":"Repair Shop",
            "type":"Services"
        }
    ],
    "sg:phone":"+1 705 748 5408",
    "sg:postcode":"K9H 5J6",
    "sg:province":"ON",
    "sg:tags":[
        "repairing",
        "piano",
        "refinishing"
    ],
    "wof:name":"Butler, Kent",
    "wof:placetype":"venue"
},
  "geometry": {"coordinates":[-78.3342590332,44.3185043335],"type":"Point"}
}