{
  "type": "Feature",
  "properties": {
    "addr:full":"Kingston ON K7K 6W6",
    "addr:postcode":"k7k 6w6",
    "iso:country":"CA",
    "sg:city":"Kingston",
    "sg:classifiers":[
        {
            "category":"Education",
            "subcategory":"College",
            "type":"Public Place"
        }
    ],
    "sg:phone":"+1 613 544 8973",
    "sg:postcode":"K7K 6W6",
    "sg:province":"ON",
    "sg:tags":[
        "academic",
        "training",
        "computer"
    ],
    "wof:name":"Academy of Learning",
    "wof:placetype":"venue"
},
  "geometry": {"coordinates":[-76.5071716309,44.2410202026],"type":"Point"}
}