{
  "type": "Feature",
  "properties": {
    "addr:full":"7201 Beechwood Rd Niagara Falls ON L2E 6S5",
    "addr:housenumber":"7201",
    "addr:postcode":"l2e 6s5",
    "addr:street":"Beechwood Rd",
    "iso:country":"CA",
    "sg:address":"7201 Beechwood Rd",
    "sg:city":"Niagara Falls",
    "sg:classifiers":[
        {
            "category":"Wholesale",
            "subcategory":"Fruits & Vegetables",
            "type":"Manufacturing & Wholesale Goods"
        }
    ],
    "sg:phone":"+1 905 356 1560",
    "sg:postcode":"L2E 6S5",
    "sg:province":"ON",
    "wof:name":"Dan's Produce Ltd",
    "wof:placetype":"venue"
},
  "geometry": {"coordinates":[-79.16132399999999,43.071148],"type":"Point"}
}