{
  "type": "Feature",
  "properties": {
    "addr:full":"668 Old Weston Rd Toronto ON M6N 3B3",
    "addr:housenumber":"668",
    "addr:postcode":"m6n 3b3",
    "addr:street":"Old Weston Rd",
    "iso:country":"CA",
    "sg:address":"668 Old Weston Rd",
    "sg:city":"Toronto",
    "sg:classifiers":[
        {
            "category":"Building & Trades",
            "subcategory":"Construction",
            "type":"Services"
        }
    ],
    "sg:phone":"+1 416 651 8997",
    "sg:postcode":"M6N 3B3",
    "sg:province":"ON",
    "sg:tags":[
        "home",
        "improvement"
    ],
    "wof:name":"P & P Home Pros",
    "wof:placetype":"venue"
},
  "geometry": {"coordinates":[-79.46601099999999,43.680099],"type":"Point"}
}