{
  "type": "Feature",
  "properties": {
    "addr:full":"205 Albion St S Amherst NS B4H 2X2",
    "addr:housenumber":"205",
    "addr:postcode":"b4h 2x2",
    "addr:street":"Albion St S",
    "iso:country":"CA",
    "sg:address":"205 Albion St S",
    "sg:city":"Amherst",
    "sg:classifiers":[
        {
            "category":"Autos & Motor Vehicles",
            "subcategory":"Fuel & Gas Station",
            "type":"Retail Goods"
        }
    ],
    "sg:phone":"+1 902 667 0123",
    "sg:postcode":"B4H 2X2",
    "sg:province":"NS",
    "sg:tags":[
        "oil"
    ],
    "wof:name":"Albion Street Shell",
    "wof:placetype":"venue"
},
  "geometry": {"coordinates":[-64.203354,45.813381],"type":"Point"}
}