{
  "type": "Feature",
  "properties": {
    "addr:full":"217 Rue Le Boise Riviere-Du-Loup QC G5R 5V3",
    "addr:housenumber":"217",
    "addr:postcode":"g5r 5v3",
    "addr:street":"Rue Le;Riviere-Du-Loup",
    "iso:country":"CA",
    "sg:address":"217 Rue Le Boise",
    "sg:city":"Riviere-Du-Loup",
    "sg:classifiers":[
        {
            "category":"Building & Trades",
            "subcategory":"Construction",
            "type":"Services"
        }
    ],
    "sg:phone":"+1 418 862 6179",
    "sg:postcode":"G5R 5V3",
    "sg:province":"QC",
    "sg:tags":[
        "general",
        "contractor"
    ],
    "wof:name":"Construction Jc Bosse Inc",
    "wof:placetype":"venue"
},
  "geometry": {"coordinates":[-69.50499000000001,47.847519],"type":"Point"}
}