{
  "type": "Feature",
  "properties": {
    "addr:full":"31 Leeson Dr Chatham ON N7M 5T9",
    "addr:housenumber":"31",
    "addr:postcode":"n7m 5t9",
    "addr:street":"Leeson Dr",
    "iso:country":"CA",
    "sg:address":"31 Leeson Dr",
    "sg:city":"Chatham",
    "sg:classifiers":[
        {
            "category":"Building & Trades",
            "subcategory":"Plumbing",
            "type":"Services"
        }
    ],
    "sg:phone":"+1 519 354 3380",
    "sg:postcode":"N7M 5T9",
    "sg:province":"ON",
    "sg:tags":[
        "conditioning",
        "air",
        "system",
        "contractor"
    ],
    "wof:name":"Gillanders Heating",
    "wof:placetype":"venue"
},
  "geometry": {"coordinates":[-82.1947250366,42.3926391602],"type":"Point"}
}