{
  "type": "Feature",
  "properties": {
    "addr:full":"245 Grand River St N Paris ON N3L 3V8",
    "addr:housenumber":"245",
    "addr:postcode":"n3l 3v8",
    "addr:street":"Grand River St N",
    "iso:country":"CA",
    "sg:address":"245 Grand River St N",
    "sg:city":"Paris",
    "sg:classifiers":[
        {
            "category":"Health Services",
            "subcategory":"Health Practitioner",
            "type":"Services"
        }
    ],
    "sg:phone":"+1 519 442 2234",
    "sg:postcode":"N3L 3V8",
    "sg:province":"ON",
    "sg:tags":[
        "physiotherapist"
    ],
    "wof:name":"Brantford Physiotherapy",
    "wof:placetype":"venue"
},
  "geometry": {"coordinates":[-80.3871,43.206627],"type":"Point"}
}