{
  "type": "Feature",
  "properties": {
    "addr:full":"4250 Village Stroll Whistler BC V0N 1B4",
    "addr:housenumber":"4250",
    "addr:postcode":"v0n 1b4",
    "addr:street":"Village Stroll",
    "iso:country":"CA",
    "sg:address":"4250 Village Stroll",
    "sg:city":"Whistler",
    "sg:classifiers":[
        {
            "category":"Travel",
            "subcategory":"Hotels & Motels",
            "type":"Entertainment"
        }
    ],
    "sg:phone":"+1 604 932 3200",
    "sg:postcode":"V0N 1B4",
    "sg:province":"BC",
    "sg:tags":[
        "resort"
    ],
    "wof:name":"Executive Inn At Whistler Vlg",
    "wof:placetype":"venue"
},
  "geometry": {"coordinates":[-122.955612,50.114265],"type":"Point"}
}