{
  "type": "Feature",
  "properties": {
    "addr:full":"3532 Rue Principale Tracadie-Sheila NB E1X 1C9",
    "addr:housenumber":"3532",
    "addr:postcode":"e1x 1c9",
    "addr:street":"Rue Principale",
    "iso:country":"CA",
    "sg:address":"3532 Rue Principale",
    "sg:city":"Tracadie-Sheila",
    "sg:classifiers":[
        {
            "category":"Shopping",
            "subcategory":"Shoes",
            "type":"Retail Goods"
        }
    ],
    "sg:phone":"+1 506 395 2280",
    "sg:postcode":"E1X 1C9",
    "sg:province":"NB",
    "wof:name":"Chaussures Ortheses Mc Graw",
    "wof:placetype":"venue"
},
  "geometry": {"coordinates":[-64.9176864624,47.4913406372],"type":"Point"}
}