{
  "type": "Feature",
  "properties": {
    "iso:country":"CA",
    "sg:city":"Richmond",
    "sg:classifiers":[
        {
            "category":"Health Services",
            "subcategory":"Optometrist",
            "type":"Services"
        }
    ],
    "sg:phone":"+1 604 273 2436",
    "sg:postcode":"V6X 1A4",
    "sg:province":"BC",
    "wof:name":"Mockler, Donna OD",
    "wof:placetype":"venue"
},
  "geometry": {"coordinates":[-123.136559,49.170254],"type":"Point"}
}