{
  "type": "Feature",
  "properties": {
    "addr:full":"110 St Andrew St Port Dover ON N0A 1N0",
    "addr:housenumber":"110",
    "addr:postcode":"n0a 1n0",
    "addr:street":"St Andrew St Port Dover",
    "iso:country":"CA",
    "sg:address":"110 St Andrew St",
    "sg:city":"Port Dover",
    "sg:classifiers":[
        {
            "category":"Professional",
            "subcategory":"Lawyer & Legal Services",
            "type":"Services"
        }
    ],
    "sg:phone":"+1 519 583 1411",
    "sg:postcode":"N0A 1N0",
    "sg:province":"ON",
    "sg:tags":[
        "attorney"
    ],
    "wof:name":"Driscoll & Gaunt",
    "wof:placetype":"venue"
},
  "geometry": {"coordinates":[-80.202423,42.787594],"type":"Point"}
}