{
  "type": "Feature",
  "properties": {
    "iso:country":"CA",
    "sg:address":"149 Lower Jarvis St",
    "sg:city":"Toronto",
    "sg:classifiers":[
        {
            "category":"Health Services",
            "subcategory":"Doctor",
            "type":"Services"
        }
    ],
    "sg:phone":"+1 416 363 4115",
    "sg:postcode":"M5E 1Z6",
    "sg:province":"ON",
    "sg:tags":[
        "dentist"
    ],
    "wof:name":"Koczerginski, Stephen DDS",
    "wof:placetype":"venue"
},
  "geometry": {"coordinates":[-79.371437,43.649441],"type":"Point"}
}