{
  "type": "Feature",
  "properties": {
    "addr:full":"Winnipeg MB R2M 5M3",
    "addr:postcode":"r2m 5m3",
    "iso:country":"CA",
    "sg:city":"Winnipeg",
    "sg:classifiers":[
        {
            "category":"Real Estate",
            "subcategory":"Real Estate Agent",
            "type":"Services"
        }
    ],
    "sg:phone":"+1 204 255 3377",
    "sg:postcode":"R2M 5M3",
    "sg:province":"MB",
    "wof:name":"Quest Real Estate Ltd",
    "wof:placetype":"venue"
},
  "geometry": {"coordinates":[-97.106552124,49.8302230835],"type":"Point"}
}