{
  "type": "Feature",
  "properties": {
    "addr:full":"Ajax ON L1S 2J1",
    "addr:postcode":"l1s 2j1",
    "iso:country":"CA",
    "sg:city":"Ajax",
    "sg:classifiers":[
        {
            "category":"Personal",
            "subcategory":"Shoe Repair & Shine",
            "type":"Services"
        }
    ],
    "sg:phone":"+1 905 686 1633",
    "sg:postcode":"L1S 2J1",
    "sg:province":"ON",
    "sg:tags":[
        "repairing",
        "boot"
    ],
    "wof:name":"Ajax Cleaners & Shoe Repair",
    "wof:placetype":"venue"
},
  "geometry": {"coordinates":[-79.01958500000001,43.846207],"type":"Point"}
}