{
  "type": "Feature",
  "properties": {
    "addr:full":"5900 Av Pierre-DE Coubertin Montreal QC H1N 1R8",
    "addr:housenumber":"5900",
    "addr:postcode":"h1n 1r8",
    "addr:street":"Av Pierre-De Coubertin",
    "iso:country":"CA",
    "sg:address":"5900 Av Pierre-DE Coubertin",
    "sg:city":"Montreal",
    "sg:classifiers":[
        {
            "category":"Government",
            "subcategory":"Office",
            "type":"Public Place"
        }
    ],
    "sg:phone":"+1 514 259 6221",
    "sg:postcode":"H1N 1R8",
    "sg:province":"QC",
    "sg:tags":[
        "village"
    ],
    "wof:name":"Tandem Montreal Mercier",
    "wof:placetype":"venue"
},
  "geometry": {"coordinates":[-73.53939800000001,45.573627],"type":"Point"}
}