{
  "type": "Feature",
  "properties": {
    "addr:full":"32 Commercial St Middleton NS B0S 1P0",
    "addr:housenumber":"32",
    "addr:postcode":"b0s 1p0",
    "addr:street":"Commercial St",
    "iso:country":"CA",
    "sg:address":"32 Commercial St",
    "sg:city":"Middleton",
    "sg:classifiers":[
        {
            "category":"Banks & Credit Unions",
            "subcategory":"Bank",
            "type":"Services"
        }
    ],
    "sg:phone":"+1 902 825 6876",
    "sg:postcode":"B0S 1P0",
    "sg:province":"NS",
    "wof:name":"Valley Credit Union Ltd",
    "wof:placetype":"venue"
},
  "geometry": {"coordinates":[-65.0684127808,44.9431800842],"type":"Point"}
}