{
  "type": "Feature",
  "properties": {
    "addr:full":"1888 Hwy 3 E Dunnville ON N1A 2W7",
    "addr:housenumber":"1888",
    "addr:postcode":"n1a 2w7",
    "addr:street":"Hwy 3 E",
    "iso:country":"CA",
    "sg:address":"1888 Hwy 3 E",
    "sg:city":"Dunnville",
    "sg:classifiers":[
        {
            "category":"Travel",
            "subcategory":"Travel Agent",
            "type":"Entertainment"
        }
    ],
    "sg:phone":"+1 905 774 7045",
    "sg:postcode":"N1A 2W7",
    "sg:province":"ON",
    "sg:tags":[
        "agency",
        "bureau"
    ],
    "wof:name":"Cardinal Tours",
    "wof:placetype":"venue"
},
  "geometry": {"coordinates":[-79.666252,42.977386],"type":"Point"}
}