{
  "type": "Feature",
  "properties": {
    "addr:full":"3100 Boul DE L'Assomption Montreal QC H1N 3S4",
    "addr:housenumber":"3100",
    "addr:postcode":"h1n 3s4",
    "addr:street":"Boul De L'Assomption",
    "iso:country":"CA",
    "sg:address":"3100 Boul DE L'Assomption",
    "sg:city":"Montreal",
    "sg:classifiers":[
        {
            "category":"Home & Garden",
            "subcategory":"Home Furnishings",
            "type":"Retail Goods"
        }
    ],
    "sg:phone":"+1 514 259 9955",
    "sg:postcode":"H1N 3S4",
    "sg:province":"QC",
    "sg:tags":[
        "venetian",
        "blind"
    ],
    "wof:name":"Blinds To Go",
    "wof:placetype":"venue"
},
  "geometry": {"coordinates":[-73.54810333250001,45.5695075989],"type":"Point"}
}