{
  "type": "Feature",
  "properties": {
    "addr:full":"Lethbridge AB T1K 7K8",
    "addr:postcode":"t1k 7k8",
    "iso:country":"CA",
    "sg:city":"Lethbridge",
    "sg:classifiers":[
        {
            "category":"Restaurant",
            "type":"Food & Drink"
        }
    ],
    "sg:phone":"+1 403 381 3339",
    "sg:postcode":"T1K 7K8",
    "sg:province":"AB",
    "wof:name":"A & W Family Restaurant",
    "wof:placetype":"venue"
},
  "geometry": {"coordinates":[-112.795883,49.663898],"type":"Point"}
}