{
  "type": "Feature",
  "properties": {
    "addr:full":"240 Scarlett Rd #1811 York ON M6N 4X4",
    "addr:housenumber":"240;1811",
    "addr:postcode":"m6n 4x4",
    "addr:street":"Scarlett Rd #",
    "iso:country":"CA",
    "sg:address":"240 Scarlett Rd #1811",
    "sg:city":"York",
    "sg:classifiers":[
        {
            "category":"Health Services",
            "subcategory":"Health Practitioner",
            "type":"Services"
        }
    ],
    "sg:phone":"+1 416 496 9885",
    "sg:postcode":"M6N 4X4",
    "sg:province":"ON",
    "sg:tags":[
        "psychologist"
    ],
    "wof:name":"Human Change Consultants",
    "wof:placetype":"venue"
},
  "geometry": {"coordinates":[-79.50607299799999,43.6759757996],"type":"Point"}
}