{
  "type": "Feature",
  "properties": {
    "iso:country":"CA",
    "sg:address":"1700 the Collegeway",
    "sg:city":"Mississauga",
    "sg:classifiers":[
        {
            "category":"Real Estate",
            "subcategory":"Real Estate Operator",
            "type":"Services"
        }
    ],
    "sg:phone":"+1 905 820 5818",
    "sg:postcode":"L5L 4M2",
    "sg:province":"ON",
    "sg:tags":[
        "condominium"
    ],
    "wof:name":"Peel Condominium",
    "wof:placetype":"venue"
},
  "geometry": {"coordinates":[-79.665787,43.543381],"type":"Point"}
}