{
  "type": "Feature",
  "properties": {
    "addr:full":"1700 the Collegeway Mississauga ON L5L 4M2",
    "addr:housenumber":"1700",
    "addr:postcode":"l5l 4m2",
    "addr:street":"The Collegeway",
    "iso:country":"CA",
    "sg:address":"1700 the Collegeway",
    "sg:city":"Mississauga",
    "sg:classifiers":[
        {
            "category":"Real Estate",
            "subcategory":"Real Estate Operator",
            "type":"Services"
        }
    ],
    "sg:phone":"+1 905 820 5818",
    "sg:postcode":"L5L 4M2",
    "sg:province":"ON",
    "sg:tags":[
        "condominium"
    ],
    "wof:name":"Peel Condominium",
    "wof:placetype":"venue"
},
  "geometry": {"coordinates":[-79.66578699999999,43.543381],"type":"Point"}
}