{
  "type": "Feature",
  "properties": {
    "addr:full":"853 Jane St York ON M6N 4C4",
    "addr:housenumber":"853",
    "addr:postcode":"m6n 4c4",
    "addr:street":"Jane St",
    "iso:country":"CA",
    "sg:address":"853 Jane St",
    "sg:city":"York",
    "sg:classifiers":[
        {
            "category":"Food & Beverages",
            "subcategory":"Groceries & Convenience Stores",
            "type":"Retail Goods"
        }
    ],
    "sg:phone":"+1 416 762 7975",
    "sg:postcode":"M6N 4C4",
    "sg:province":"ON",
    "sg:tags":[
        "grocer"
    ],
    "wof:name":"Food Basics",
    "wof:placetype":"venue"
},
  "geometry": {"coordinates":[-79.4956283569,43.6765441895],"type":"Point"}
}