{
  "type": "Feature",
  "properties": {
    "addr:full":"101 Main St E Trout Creek ON P0H 2L0",
    "addr:housenumber":"101",
    "addr:postcode":"p0h 2l0",
    "addr:street":"Main St E Trout",
    "iso:country":"CA",
    "sg:address":"101 Main St E",
    "sg:city":"Trout Creek",
    "sg:classifiers":[
        {
            "category":"Shopping",
            "subcategory":"Discount & Variety Stores",
            "type":"Retail Goods"
        }
    ],
    "sg:phone":"+1 705 723 1050",
    "sg:postcode":"P0H 2L0",
    "sg:province":"ON",
    "sg:tags":[
        "merchandise",
        "general"
    ],
    "wof:name":"Trout Creek General Store",
    "wof:placetype":"venue"
},
  "geometry": {"coordinates":[-79.35966500000001,45.986893],"type":"Point"}
}