{
  "type": "Feature",
  "properties": {
    "addr:full":"Mill Rd Terrace Bay ON P0T 2W0",
    "addr:postcode":"p0t 2w0",
    "addr:street":"Mill Rd",
    "iso:country":"CA",
    "sg:address":"Mill Rd",
    "sg:city":"Terrace Bay",
    "sg:classifiers":[
        {
            "category":"Home & Garden",
            "subcategory":"Garden Supply",
            "type":"Retail Goods"
        }
    ],
    "sg:phone":"+1 807 825 9050",
    "sg:postcode":"P0T 2W0",
    "sg:province":"ON",
    "sg:tags":[
        "lawn"
    ],
    "wof:name":"Jean Saw Sales",
    "wof:placetype":"venue"
},
  "geometry": {"coordinates":[-87.09462000000001,48.793484],"type":"Point"}
}