{
  "type": "Feature",
  "properties": {
    "addr:full":"16 Rue Paquette Saint-Liboire QC J0H 1R0",
    "addr:housenumber":"16",
    "addr:postcode":"j0h 1r0",
    "addr:street":"Rue Paquette",
    "iso:country":"CA",
    "sg:address":"16 Rue Paquette",
    "sg:city":"Saint-Liboire",
    "sg:classifiers":[
        {
            "category":"Personal",
            "subcategory":"Beauty Salon",
            "type":"Services"
        }
    ],
    "sg:phone":"+1 450 793 4704",
    "sg:postcode":"J0H 1R0",
    "sg:province":"QC",
    "wof:name":"Salon Nancy",
    "wof:placetype":"venue"
},
  "geometry": {"coordinates":[-72.7556762695,45.6525230408],"type":"Point"}
}