{
  "type": "Feature",
  "properties": {
    "addr:full":"Cp 68 Succ Pierrefonds Pierrefonds QC H9H 4K8",
    "addr:housenumber":"68",
    "addr:postcode":"h9h 4k8",
    "addr:street":"Cp;Succ Pierrefonds",
    "iso:country":"CA",
    "sg:address":"Cp 68 Succ Pierrefonds",
    "sg:city":"Pierrefonds",
    "sg:classifiers":[
        {
            "category":"Manufacturing",
            "subcategory":"Jewelry",
            "type":"Manufacturing & Wholesale Goods"
        }
    ],
    "sg:phone":"+1 514 630 4879",
    "sg:postcode":"H9H 4K8",
    "sg:province":"QC",
    "sg:tags":[
        "jeweler"
    ],
    "wof:name":"Ventes Paul Charky Ltee",
    "wof:placetype":"venue"
},
  "geometry": {"coordinates":[-73.847183,45.495155],"type":"Point"}
}