{
  "type": "Feature",
  "properties": {
    "addr:full":"Calgary AB T2E 6X8",
    "addr:postcode":"t2e 6x8",
    "iso:country":"CA",
    "sg:city":"Calgary",
    "sg:classifiers":[
        {
            "category":"Retail",
            "subcategory":"Auto Repair",
            "type":"Services"
        }
    ],
    "sg:phone":"+1 403 291 0072",
    "sg:postcode":"T2E 6X8",
    "sg:province":"AB",
    "sg:tags":[
        "repairing",
        "automobile"
    ],
    "wof:name":"One Stop Auto Repairs",
    "wof:placetype":"venue"
},
  "geometry": {"coordinates":[-114.011971,51.089146],"type":"Point"}
}