{
  "type": "Feature",
  "properties": {
    "addr:full":"20993 Dalton Rd Jacksons Point ON L0E 1L0",
    "addr:housenumber":"20993",
    "addr:postcode":"l0e 1l0",
    "addr:street":"Dalton Rd",
    "iso:country":"CA",
    "sg:address":"20993 Dalton Rd",
    "sg:city":"Jacksons Point",
    "sg:classifiers":[
        {
            "category":"Autos & Motor Vehicles",
            "subcategory":"Automobile Sales",
            "type":"Retail Goods"
        }
    ],
    "sg:phone":"+1 905 722 8129",
    "sg:postcode":"L0E 1L0",
    "sg:province":"ON",
    "sg:tags":[
        "car",
        "dealer"
    ],
    "wof:name":"Dean's Auto Sales",
    "wof:placetype":"venue"
},
  "geometry": {"coordinates":[-79.367661,44.315941],"type":"Point"}
}