{
  "type": "Feature",
  "properties": {
    "addr:full":"Lone Butte BC V0K 1X0",
    "addr:postcode":"v0k 1x0",
    "addr:street":"Lone",
    "iso:country":"CA",
    "sg:city":"Lone Butte",
    "sg:classifiers":[
        {
            "category":"Building & Trades",
            "subcategory":"Construction",
            "type":"Services"
        }
    ],
    "sg:phone":"+1 250 593 4048",
    "sg:postcode":"V0K 1X0",
    "sg:province":"BC",
    "sg:tags":[
        "disposal",
        "excavating",
        "system",
        "sewage",
        "contractor"
    ],
    "wof:name":"Windy Mountain Backhoe",
    "wof:placetype":"venue"
},
  "geometry": {"coordinates":[-121.19148300000001,51.553108],"type":"Point"}
}