{
  "type": "Feature",
  "properties": {
    "addr:full":"414 Palmerston Blvd Toronto ON M6G 2N8",
    "addr:housenumber":"414",
    "addr:postcode":"m6g 2n8",
    "addr:street":"Palmerston Blvd",
    "iso:country":"CA",
    "sg:address":"414 Palmerston Blvd",
    "sg:city":"Toronto",
    "sg:classifiers":[
        {
            "category":"Professional",
            "subcategory":"Management & Consulting",
            "type":"Services"
        }
    ],
    "sg:phone":"+1 416 535 6994",
    "sg:postcode":"M6G 2N8",
    "sg:province":"ON",
    "sg:tags":[
        "career",
        "consultant",
        "vocational",
        "business",
        "counseling"
    ],
    "wof:name":"Centre For Creative Change Inc",
    "wof:placetype":"venue"
},
  "geometry": {"coordinates":[-79.41188,43.659851],"type":"Point"}
}