{
  "type": "Feature",
  "properties": {
    "iso:country":"CA",
    "sg:address":"123 Montebello Dr",
    "sg:city":"London",
    "sg:classifiers":[
        {
            "category":"Social Services",
            "subcategory":"Child Care",
            "type":"Services"
        }
    ],
    "sg:phone":"+1 519 453 3220",
    "sg:postcode":"N5W 1S1",
    "sg:province":"ON",
    "wof:name":"Bright Beginnings Early Chldhd",
    "wof:placetype":"venue"
},
  "geometry": {"coordinates":[-81.178261,42.977268],"type":"Point"}
}