{
  "type": "Feature",
  "properties": {
    "addr:full":"123 Montebello Dr London ON N5W 1S1",
    "addr:housenumber":"123",
    "addr:postcode":"n5w 1s1",
    "addr:street":"Montebello Dr",
    "iso:country":"CA",
    "sg:address":"123 Montebello Dr",
    "sg:city":"London",
    "sg:classifiers":[
        {
            "category":"Social Services",
            "subcategory":"Child Care",
            "type":"Services"
        }
    ],
    "sg:phone":"+1 519 453 3220",
    "sg:postcode":"N5W 1S1",
    "sg:province":"ON",
    "wof:name":"Bright Beginnings Early Chldhd",
    "wof:placetype":"venue"
},
  "geometry": {"coordinates":[-81.17826100000001,42.977268],"type":"Point"}
}