{
  "type": "Feature",
  "properties": {
    "iso:country":"CA",
    "sg:address":"165 Werlich Dr",
    "sg:city":"Cambridge",
    "sg:classifiers":[
        {
            "category":"Manufacturing",
            "subcategory":"Tools & Machinery",
            "type":"Manufacturing & Wholesale Goods"
        }
    ],
    "sg:phone":"+1 519 624 5010",
    "sg:postcode":"N1T 1Y2",
    "sg:province":"ON",
    "sg:tags":[
        "machine",
        "shop"
    ],
    "wof:name":"Cantec Manufacturing Inc",
    "wof:placetype":"venue"
},
  "geometry": {"coordinates":[-80.298225,43.400997],"type":"Point"}
}