{
  "type": "Feature",
  "properties": {
    "addr:full":"Etobicoke ON M9W 6N6",
    "addr:postcode":"m9w 6n6",
    "iso:country":"CA",
    "sg:city":"Etobicoke",
    "sg:classifiers":[
        {
            "category":"Freight",
            "type":"Transportation"
        }
    ],
    "sg:phone":"+1 416 674 7111",
    "sg:postcode":"M9W 6N6",
    "sg:province":"ON",
    "sg:tags":[
        "shipping"
    ],
    "wof:name":"Currie Maritime Corp",
    "wof:placetype":"venue"
},
  "geometry": {"coordinates":[-79.583885,43.685242],"type":"Point"}
}