{
  "type": "Feature",
  "properties": {
    "addr:full":"375 Rue St-Laurent Saint-Simeon QC G0T 1X0",
    "addr:housenumber":"375",
    "addr:postcode":"g0t 1x0",
    "addr:street":"Rue St-Laurent",
    "iso:country":"CA",
    "sg:address":"375 Rue St-Laurent",
    "sg:city":"Saint-Simeon",
    "sg:classifiers":[
        {
            "category":"Freight",
            "type":"Transportation"
        }
    ],
    "sg:phone":"+1 418 638 5198",
    "sg:postcode":"G0T 1X0",
    "sg:province":"QC",
    "sg:tags":[
        "taxicab",
        "trucking"
    ],
    "wof:name":"Taxi St-Simeon",
    "wof:placetype":"venue"
},
  "geometry": {"coordinates":[-69.87958500000001,47.842472],"type":"Point"}
}