{
  "type": "Feature",
  "properties": {
    "addr:full":"32 Ontario St N Grand Bend ON N0M 1T0",
    "addr:housenumber":"32",
    "addr:postcode":"n0m 1t0",
    "addr:street":"Ontario St N",
    "iso:country":"CA",
    "sg:address":"32 Ontario St N",
    "sg:city":"Grand Bend",
    "sg:classifiers":[
        {
            "category":"Restaurant",
            "type":"Food & Drink"
        }
    ],
    "sg:phone":"+1 519 238 6771",
    "sg:postcode":"N0M 1T0",
    "sg:province":"ON",
    "sg:tags":[
        "sandwich"
    ],
    "wof:name":"Subway Sandwiches & Salads",
    "wof:placetype":"venue"
},
  "geometry": {"coordinates":[-81.755325,43.313698],"type":"Point"}
}