{
  "type": "Feature",
  "properties": {
    "addr:full":"9291 Route 3 Old Ridge NB E3L 4X2",
    "addr:housenumber":"9291",
    "addr:postcode":"e3l 4x2",
    "addr:street":"Route 3;Ridge",
    "iso:country":"CA",
    "sg:address":"9291 Route 3",
    "sg:city":"Old Ridge",
    "sg:classifiers":[
        {
            "category":"Real Estate",
            "subcategory":"Surveying",
            "type":"Services"
        }
    ],
    "sg:phone":"+1 506 466 1941",
    "sg:postcode":"E3L 4X2",
    "sg:province":"NB",
    "sg:tags":[
        "surveyor"
    ],
    "wof:name":"Murphy Surveys Ltd",
    "wof:placetype":"venue"
},
  "geometry": {"coordinates":[-67.2912597656,45.2627182007],"type":"Point"}
}