{
  "type": "Feature",
  "properties": {
    "addr:full":"21 Sylvan St Kenora ON P9N 3W7",
    "addr:housenumber":"21",
    "addr:postcode":"p9n 3w7",
    "addr:street":"Sylvan St",
    "iso:country":"CA",
    "sg:address":"21 Sylvan St",
    "sg:city":"Kenora",
    "sg:classifiers":[
        {
            "category":"Health Services",
            "subcategory":"Hospital",
            "type":"Services"
        }
    ],
    "sg:phone":"+1 807 468 9861",
    "sg:postcode":"P9N 3W7",
    "sg:province":"ON",
    "wof:name":"Lake of the Woods Hospital",
    "wof:placetype":"venue"
},
  "geometry": {"coordinates":[-94.4993362427,49.7675704956],"type":"Point"}
}