{
  "type": "Feature",
  "properties": {
    "addr:full":"Sechelt BC V0N 3A0",
    "addr:postcode":"v0n 3a0",
    "iso:country":"CA",
    "sg:city":"Sechelt",
    "sg:classifiers":[
        {
            "category":"Government",
            "subcategory":"Office",
            "type":"Public Place"
        }
    ],
    "sg:phone":"+1 604 885 8289",
    "sg:postcode":"V0N 3A0",
    "sg:province":"BC",
    "sg:tags":[
        "village"
    ],
    "wof:name":"Sunshine Dist Sechelt Landfill",
    "wof:placetype":"venue"
},
  "geometry": {"coordinates":[-123.754707,49.472565],"type":"Point"}
}