{
  "type": "Feature",
  "properties": {
    "addr:full":"11 Irwin Ave Toronto ON M4Y 1L1",
    "addr:housenumber":"11",
    "addr:postcode":"m4y 1l1",
    "addr:street":"Irwin Ave",
    "iso:country":"CA",
    "sg:address":"11 Irwin Ave",
    "sg:city":"Toronto",
    "sg:classifiers":[
        {
            "category":"Professional",
            "subcategory":"Management & Consulting",
            "type":"Services"
        }
    ],
    "sg:phone":"+1 416 925 3889",
    "sg:postcode":"M4Y 1L1",
    "sg:province":"ON",
    "sg:tags":[
        "consultant",
        "educational",
        "salon",
        "beauty"
    ],
    "wof:name":"Uscpa Success",
    "wof:placetype":"venue"
},
  "geometry": {"coordinates":[-79.385727,43.666454],"type":"Point"}
}