{
  "type": "Feature",
  "properties": {
    "addr:full":"8 Industrial Dr Caledonia ON N3W 1H8",
    "addr:housenumber":"8",
    "addr:postcode":"n3w 1h8",
    "addr:street":"Industrial Dr",
    "iso:country":"CA",
    "sg:address":"8 Industrial Dr",
    "sg:city":"Caledonia",
    "sg:classifiers":[
        {
            "category":"Retail",
            "subcategory":"Auto Repair",
            "type":"Services"
        }
    ],
    "sg:phone":"+1 905 765 8474",
    "sg:postcode":"N3W 1H8",
    "sg:province":"ON",
    "sg:tags":[
        "repairing",
        "automobile"
    ],
    "wof:name":"Tim's Tire & Alignment",
    "wof:placetype":"venue"
},
  "geometry": {"coordinates":[-79.94966125489999,43.0895347595],"type":"Point"}
}