{
  "type": "Feature",
  "properties": {
    "addr:full":"425 Rue Sainte-Angele Trois-Rivieres QC G9A 1M3",
    "addr:housenumber":"425",
    "addr:postcode":"g9a 1m3",
    "addr:street":"Rue Sainte-Angele Trois-Rivieres",
    "iso:country":"CA",
    "sg:address":"425 Rue Sainte-Angele",
    "sg:city":"Trois-Rivieres",
    "sg:classifiers":[
        {
            "category":"Organizations",
            "subcategory":"Religious Organization",
            "type":"Services"
        }
    ],
    "sg:phone":"+1 819 379 0502",
    "sg:postcode":"G9A 1M3",
    "sg:province":"QC",
    "wof:name":"Pauvres DE Saint Francois",
    "wof:placetype":"venue"
},
  "geometry": {"coordinates":[-72.5388870239,46.3469924927],"type":"Point"}
}