{
  "type": "Feature",
  "properties": {
    "addr:full":"507 Bernard Ave Kelowna BC V1Y 6N9",
    "addr:housenumber":"507",
    "addr:postcode":"v1y 6n9",
    "addr:street":"Bernard Ave",
    "iso:country":"CA",
    "sg:address":"507 Bernard Ave",
    "sg:city":"Kelowna",
    "sg:classifiers":[
        {
            "category":"Banks & Credit Unions",
            "subcategory":"Bank",
            "type":"Services"
        }
    ],
    "sg:phone":"+1 250 860 1900",
    "sg:postcode":"V1Y 6N9",
    "sg:province":"BC",
    "wof:name":"Valley First Credit Union",
    "wof:placetype":"venue"
},
  "geometry": {"coordinates":[-119.493195,49.886101],"type":"Point"}
}