{
  "type": "Feature",
  "properties": {
    "addr:full":"381 Water St Bay Roberts NL A0A 1G0",
    "addr:housenumber":"381",
    "addr:postcode":"a0a 1g0",
    "addr:street":"Water St",
    "iso:country":"CA",
    "sg:address":"381 Water St",
    "sg:city":"Bay Roberts",
    "sg:classifiers":[
        {
            "category":"Organizations",
            "subcategory":"Religious Organization",
            "type":"Services"
        }
    ],
    "sg:phone":"+1 709 786 9555",
    "sg:postcode":"A0A 1G0",
    "sg:province":"NL",
    "sg:tags":[
        "church"
    ],
    "wof:name":"Victory Christian Ctr",
    "wof:placetype":"venue"
},
  "geometry": {"coordinates":[-53.23584,47.601879],"type":"Point"}
}