{
  "type": "Feature",
  "properties": {
    "addr:full":"87 Rue Des Oblats E Chicoutimi QC G7H 2X9",
    "addr:housenumber":"87",
    "addr:postcode":"g7h 2x9",
    "addr:street":"Rue Des Oblats E",
    "iso:country":"CA",
    "sg:address":"87 Rue Des Oblats E",
    "sg:city":"Chicoutimi",
    "sg:classifiers":[
        {
            "category":"Personal",
            "subcategory":"Beauty Salon",
            "type":"Services"
        }
    ],
    "sg:phone":"+1 418 545 6780",
    "sg:postcode":"G7H 2X9",
    "sg:province":"QC",
    "wof:name":"Salon DE Coiffure Lindel",
    "wof:placetype":"venue"
},
  "geometry": {"coordinates":[-71.067688,48.413712],"type":"Point"}
}