{
  "type": "Feature",
  "properties": {
    "iso:country":"CA",
    "sg:address":"375 Bleecker St",
    "sg:city":"Toronto",
    "sg:classifiers":[
        {
            "category":"Building & Trades",
            "subcategory":"Cleaning & Sanitation",
            "type":"Services"
        }
    ],
    "sg:phone":"+1 416 964 6218",
    "sg:postcode":"M4X 1M3",
    "sg:province":"ON",
    "sg:tags":[
        "property",
        "maintenance"
    ],
    "wof:name":"Greenwin Property Management",
    "wof:placetype":"venue"
},
  "geometry": {"coordinates":[-79.37464904789999,43.6698684692],"type":"Point"}
}