{
  "type": "Feature",
  "properties": {
    "addr:full":"3106 Joseph Howe Dr Halifax NS B3L 4L7",
    "addr:housenumber":"3106",
    "addr:postcode":"b3l 4l7",
    "addr:street":"Joseph Howe Dr",
    "iso:country":"CA",
    "sg:address":"3106 Joseph Howe Dr",
    "sg:city":"Halifax",
    "sg:classifiers":[
        {
            "category":"Organizations",
            "subcategory":"Labor Organization",
            "type":"Services"
        }
    ],
    "sg:phone":"+1 902 477 5621",
    "sg:postcode":"B3L 4L7",
    "sg:province":"NS",
    "sg:tags":[
        "banks"
    ],
    "wof:name":"Nova Scotia Teachers Union",
    "wof:placetype":"venue"
},
  "geometry": {"coordinates":[-63.63007,44.648884],"type":"Point"}
}