{
  "type": "Feature",
  "properties": {
    "addr:full":"300 Rue Saint-Jean-Baptiste N Princeville QC G6L 5E2",
    "addr:housenumber":"300",
    "addr:postcode":"g6l 5e2",
    "addr:street":"Rue Saint-Jean-Baptiste N",
    "iso:country":"CA",
    "sg:address":"300 Rue Saint-Jean-Baptiste N",
    "sg:city":"Princeville",
    "sg:classifiers":[
        {
            "category":"Manufacturing",
            "subcategory":"Tools & Machinery",
            "type":"Manufacturing & Wholesale Goods"
        }
    ],
    "sg:phone":"+1 819 364 5120",
    "sg:postcode":"G6L 5E2",
    "sg:province":"QC",
    "sg:tags":[
        "control",
        "system",
        "automation"
    ],
    "wof:name":"Controles Inco",
    "wof:placetype":"venue"
},
  "geometry": {"coordinates":[-71.879036,46.175419],"type":"Point"}
}