{
  "type": "Feature",
  "properties": {
    "addr:full":"960 Rue Boulay Acton Vale QC J0H 1A0",
    "addr:housenumber":"960",
    "addr:postcode":"j0h 1a0",
    "addr:street":"Rue Boulay",
    "iso:country":"CA",
    "sg:address":"960 Rue Boulay",
    "sg:city":"Acton Vale",
    "sg:classifiers":[
        {
            "category":"Travel",
            "subcategory":"Travel Agent",
            "type":"Entertainment"
        }
    ],
    "sg:phone":"+1 450 546 7642",
    "sg:postcode":"J0H 1A0",
    "sg:province":"QC",
    "sg:tags":[
        "consultant"
    ],
    "wof:name":"Tourisme Acton",
    "wof:placetype":"venue"
},
  "geometry": {"coordinates":[-72.563461,45.648357],"type":"Point"}
}