{
  "type": "Feature",
  "properties": {
    "addr:full":"120 Rue Nicole Saint-Jerome QC J7Y 1J5",
    "addr:housenumber":"120",
    "addr:postcode":"j7y 1j5",
    "addr:street":"Rue Nicole Saint-Jerome",
    "iso:country":"CA",
    "sg:address":"120 Rue Nicole",
    "sg:city":"Saint-Jerome",
    "sg:classifiers":[
        {
            "category":"Wholesale",
            "subcategory":"Construction Materials",
            "type":"Manufacturing & Wholesale Goods"
        }
    ],
    "sg:phone":"+1 450 602 1482",
    "sg:postcode":"J7Y 1J5",
    "sg:province":"QC",
    "sg:tags":[
        "pole"
    ],
    "wof:name":"Michel Valois Excavation Inc",
    "wof:placetype":"venue"
},
  "geometry": {"coordinates":[-73.997711,45.796947],"type":"Point"}
}