{
  "type": "Feature",
  "properties": {
    "addr:full":"284 6th Ave NW Minnedosa MB R0J 1E0",
    "addr:housenumber":"284",
    "addr:postcode":"r0j 1e0",
    "addr:street":"6Th Ave Nw Minnedosa",
    "iso:country":"CA",
    "sg:address":"284 6th Ave NW",
    "sg:city":"Minnedosa",
    "sg:classifiers":[
        {
            "category":"Manufacturing",
            "subcategory":"Tools & Machinery",
            "type":"Manufacturing & Wholesale Goods"
        }
    ],
    "sg:phone":"+1 204 867 2713",
    "sg:postcode":"R0J 1E0",
    "sg:province":"MB",
    "sg:tags":[
        "farm",
        "equipment"
    ],
    "wof:name":"Morris Industries Ltd",
    "wof:placetype":"venue"
},
  "geometry": {"coordinates":[-99.8386230469,50.2470207214],"type":"Point"}
}