{
  "type": "Feature",
  "properties": {
    "addr:full":"Kamloops BC V2C 5Z3",
    "addr:postcode":"bc v2c 5z3",
    "iso:country":"CA",
    "sg:city":"Kamloops",
    "sg:classifiers":[
        {
            "category":"Manufacturing",
            "subcategory":"Metals",
            "type":"Manufacturing & Wholesale Goods"
        }
    ],
    "sg:phone":"+1 250 374 0880",
    "sg:postcode":"V2C 5Z3",
    "sg:province":"BC",
    "sg:tags":[
        "door"
    ],
    "wof:name":"Accurate Door & Hardware CO",
    "wof:placetype":"venue"
},
  "geometry": {"coordinates":[-120.368126,50.660652],"type":"Point"}
}