{
  "type": "Feature",
  "properties": {
    "addr:full":"283 Spadina Ave # 301 Toronto ON M5T 2E3",
    "addr:housenumber":"283",
    "addr:postcode":"m5t 2e3",
    "addr:street":"Spadina Ave # 301",
    "iso:country":"CA",
    "sg:address":"283 Spadina Ave # 301",
    "sg:city":"Toronto",
    "sg:classifiers":[
        {
            "category":"Wholesale",
            "subcategory":"Durable Goods & Equipment",
            "type":"Manufacturing & Wholesale Goods"
        }
    ],
    "sg:phone":"+1 416 977 8358",
    "sg:postcode":"M5T 2E3",
    "sg:province":"ON",
    "sg:tags":[
        "exporter"
    ],
    "wof:name":"Robinson International Trading",
    "wof:placetype":"venue"
},
  "geometry": {"coordinates":[-79.39778099999999,43.652878],"type":"Point"}
}