{
  "type": "Feature",
  "properties": {
    "addr:full":"2720 Centre St NE Calgary AB T2E 2V6",
    "addr:housenumber":"2720",
    "addr:postcode":"t2e 2v6",
    "addr:street":"Centre St Ne",
    "iso:country":"CA",
    "sg:address":"2720 Centre St NE",
    "sg:city":"Calgary",
    "sg:classifiers":[
        {
            "category":"Retail",
            "subcategory":"Funeral Services",
            "type":"Services"
        }
    ],
    "sg:phone":"+1 403 276 2999",
    "sg:postcode":"T2E 2V6",
    "sg:province":"AB",
    "sg:tags":[
        "director"
    ],
    "wof:name":"Centre Street Crematorium",
    "wof:placetype":"venue"
},
  "geometry": {"coordinates":[-114.062362671,51.0763244629],"type":"Point"}
}