{
  "type": "Feature",
  "properties": {
    "addr:full":"8 Rue Notre Dame Hebertville-Station QC G0W 1T0",
    "addr:housenumber":"8",
    "addr:postcode":"g0w 1t0",
    "addr:street":"Rue Notre Dame Hebertville-Station",
    "iso:country":"CA",
    "sg:address":"8 Rue Notre Dame",
    "sg:city":"Hebertville-Station",
    "sg:classifiers":[
        {
            "category":"Health Services",
            "subcategory":"Nursing And Care Facility",
            "type":"Services"
        }
    ],
    "sg:phone":"+1 418 343 3176",
    "sg:postcode":"G0W 1T0",
    "sg:province":"QC",
    "sg:tags":[
        "home",
        "retirement",
        "community",
        "rest"
    ],
    "wof:name":"Residence Patrick Trottier",
    "wof:placetype":"venue"
},
  "geometry": {"coordinates":[-71.663887,48.444187],"type":"Point"}
}