{
  "type": "Feature",
  "properties": {
    "iso:country":"CA",
    "sg:address":"10 Columbia Dr",
    "sg:city":"Marystown",
    "sg:classifiers":[
        {
            "category":"Banks & Credit Unions",
            "subcategory":"Bank",
            "type":"Services"
        }
    ],
    "sg:phone":"+1 709 279 1050",
    "sg:postcode":"A0E 2M0",
    "sg:province":"NL",
    "sg:tags":[
        "loan",
        "real estate"
    ],
    "wof:name":"Citifinancial",
    "wof:placetype":"venue"
},
  "geometry": {"coordinates":[-55.2424125671,47.1614303589],"type":"Point"}
}