{
  "type": "Feature",
  "properties": {
    "addr:full":"4859 Henderson Hwy Winnipeg MB R3C 2E7",
    "addr:housenumber":"4859",
    "addr:postcode":"r3c 2e7",
    "addr:street":"Henderson Hwy",
    "iso:country":"CA",
    "sg:address":"4859 Henderson Hwy",
    "sg:city":"Winnipeg",
    "sg:classifiers":[
        {
            "category":"Retail",
            "subcategory":"Auto Repair",
            "type":"Services"
        }
    ],
    "sg:phone":"+1 204 661 2093",
    "sg:postcode":"R3C 2E7",
    "sg:province":"MB",
    "sg:tags":[
        "body",
        "automobile",
        "painting"
    ],
    "wof:name":"Frey's Auto Body",
    "wof:placetype":"venue"
},
  "geometry": {"coordinates":[-97.066818,49.96109],"type":"Point"}
}