{
  "type": "Feature",
  "properties": {
    "addr:full":"75 Rue Hector Pierreville QC J0G 1J0",
    "addr:housenumber":"75",
    "addr:postcode":"j0g 1j0",
    "addr:street":"Rue Hector",
    "iso:country":"CA",
    "sg:address":"75 Rue Hector",
    "sg:city":"Pierreville",
    "sg:classifiers":[
        {
            "category":"Manufacturing",
            "subcategory":"Tools & Machinery",
            "type":"Manufacturing & Wholesale Goods"
        }
    ],
    "sg:phone":"+1 450 568 2719",
    "sg:postcode":"J0G 1J0",
    "sg:province":"QC",
    "sg:tags":[
        "fire",
        "equipment",
        "ladder",
        "protection"
    ],
    "wof:name":"Echelles Ce Thibault Inc",
    "wof:placetype":"venue"
},
  "geometry": {"coordinates":[-72.804596,46.070797],"type":"Point"}
}