{
  "type": "Feature",
  "properties": {
    "addr:full":"80 Rue Nicholson Salaberry-DE-Valleyfield QC J6T 4N2",
    "addr:housenumber":"80",
    "addr:postcode":"j6t 4n2",
    "addr:street":"Rue Nicholson",
    "iso:country":"CA",
    "sg:address":"80 Rue Nicholson",
    "sg:city":"Salaberry-DE-Valleyfield",
    "sg:classifiers":[
        {
            "category":"Insurance",
            "subcategory":"Insurance Agent",
            "type":"Services"
        }
    ],
    "sg:phone":"+1 450 373 1545",
    "sg:postcode":"J6T 4N2",
    "sg:province":"QC",
    "wof:name":"Assurance Rochefort Perron",
    "wof:placetype":"venue"
},
  "geometry": {"coordinates":[-74.1308517456,45.2539138794],"type":"Point"}
}