{
  "type": "Feature",
  "properties": {
    "addr:full":"48 Main St Springhill NS B0M 1X0",
    "addr:housenumber":"48",
    "addr:postcode":"b0m 1x0",
    "addr:street":"Main St",
    "iso:country":"CA",
    "sg:address":"48 Main St",
    "sg:city":"Springhill",
    "sg:classifiers":[
        {
            "category":"Shopping",
            "subcategory":"Florist",
            "type":"Retail Goods"
        }
    ],
    "sg:phone":"+1 902 597 3574",
    "sg:postcode":"B0M 1X0",
    "sg:province":"NS",
    "wof:name":"Marcat Flowers & Gifts",
    "wof:placetype":"venue"
},
  "geometry": {"coordinates":[-64.056938,45.65065],"type":"Point"}
}