{
  "type": "Feature",
  "properties": {
    "addr:full":"14 Church St Moncton NB E1C 4Y9",
    "addr:housenumber":"14",
    "addr:postcode":"e1c 4y9",
    "addr:street":"Church St",
    "iso:country":"CA",
    "sg:address":"14 Church St",
    "sg:city":"Moncton",
    "sg:classifiers":[
        {
            "category":"Restaurant",
            "type":"Food & Drink"
        }
    ],
    "sg:phone":"+1 506 388 4283",
    "sg:postcode":"E1C 4Y9",
    "sg:province":"NB",
    "wof:name":"St James Gate Ltd",
    "wof:placetype":"venue"
},
  "geometry": {"coordinates":[-64.77829699999999,46.088802],"type":"Point"}
}