{
  "type": "Feature",
  "properties": {
    "addr:full":"1124 Rue Saint-Calixte Plessisville QC G6L 1N8",
    "addr:housenumber":"1124",
    "addr:postcode":"g6l 1n8",
    "addr:street":"Rue Saint-Calixte",
    "iso:country":"CA",
    "sg:address":"1124 Rue Saint-Calixte",
    "sg:city":"Plessisville",
    "sg:classifiers":[
        {
            "category":"Wholesale",
            "subcategory":"Hardware",
            "type":"Manufacturing & Wholesale Goods"
        }
    ],
    "sg:phone":"+1 819 362 7345",
    "sg:postcode":"G6L 1N8",
    "sg:province":"QC",
    "sg:tags":[
        "tool"
    ],
    "wof:name":"Fournitures Industrielles",
    "wof:placetype":"venue"
},
  "geometry": {"coordinates":[-71.780418396,46.2134895325],"type":"Point"}
}