{
  "type": "Feature",
  "properties": {
    "addr:full":"410 Rue Saint-Germain E Rimouski QC G5L 1C7",
    "addr:housenumber":"410",
    "addr:postcode":"g5l 1c7",
    "addr:street":"Rue Saint-Germain E",
    "iso:country":"CA",
    "sg:address":"410 Rue Saint-Germain E",
    "sg:city":"Rimouski",
    "sg:classifiers":[
        {
            "category":"Travel",
            "subcategory":"Hotels & Motels",
            "type":"Entertainment"
        }
    ],
    "sg:phone":"+1 418 723 9219",
    "sg:postcode":"G5L 1C7",
    "sg:province":"QC",
    "wof:name":"Motel Rimouski Inc",
    "wof:placetype":"venue"
},
  "geometry": {"coordinates":[-68.51787567140001,48.4682540894],"type":"Point"}
}