{
  "type": "Feature",
  "properties": {
    "addr:full":"Pond Side Rd Carbonear NL A1Y 1B5",
    "addr:postcode":"a1y 1b5",
    "addr:street":"Pond Side Rd",
    "iso:country":"CA",
    "sg:address":"Pond Side Rd",
    "sg:city":"Carbonear",
    "sg:classifiers":[
        {
            "category":"Home & Garden",
            "subcategory":"Building Materials",
            "type":"Retail Goods"
        }
    ],
    "sg:phone":"+1 709 596 6073",
    "sg:postcode":"A1Y 1B5",
    "sg:province":"NL",
    "wof:name":"W G Garland Ltd",
    "wof:placetype":"venue"
},
  "geometry": {"coordinates":[-53.2295,47.736382],"type":"Point"}
}