{
  "type": "Feature",
  "properties": {
    "addr:full":"Dodge Rd Kingston NS B0P 1R0",
    "addr:postcode":"b0p 1r0",
    "addr:street":"Dodge Rd",
    "iso:country":"CA",
    "sg:address":"Dodge Rd",
    "sg:city":"Kingston",
    "sg:classifiers":[
        {
            "category":"Organizations",
            "subcategory":"Non-profit Organization",
            "type":"Services"
        }
    ],
    "sg:phone":"+1 902 765 4078",
    "sg:postcode":"B0P 1R0",
    "sg:province":"NS",
    "sg:tags":[
        "charitable",
        "institution"
    ],
    "wof:name":"Kinsmen Club",
    "wof:placetype":"venue"
},
  "geometry": {"coordinates":[-64.9493560791,44.9874382019],"type":"Point"}
}