{
  "type": "Feature",
  "properties": {
    "addr:full":"117 Ringwood Dr Stouffville ON L4A 8C1",
    "addr:housenumber":"117",
    "addr:postcode":"l4a 8c1",
    "addr:street":"Ringwood Dr",
    "iso:country":"CA",
    "sg:address":"117 Ringwood Dr",
    "sg:city":"Stouffville",
    "sg:classifiers":[
        {
            "category":"Manufacturing",
            "subcategory":"Tools & Machinery",
            "type":"Manufacturing & Wholesale Goods"
        }
    ],
    "sg:phone":"+1 905 640 6167",
    "sg:postcode":"L4A 8C1",
    "sg:province":"ON",
    "sg:tags":[
        "machine",
        "screw",
        "product",
        "equipment"
    ],
    "wof:name":"Jeymatic Precision Components",
    "wof:placetype":"venue"
},
  "geometry": {"coordinates":[-79.27411651609999,43.9631385803],"type":"Point"}
}