{
  "type": "Feature",
  "properties": {
    "iso:country":"CA",
    "sg:address":"PO Box 3148 STN Main",
    "sg:city":"Edmonton",
    "sg:classifiers":[
        {
            "category":"Education",
            "subcategory":"Special Training",
            "type":"Public Place"
        }
    ],
    "sg:phone":"+1 780 499 8050",
    "sg:postcode":"T5J 2G7",
    "sg:province":"AB",
    "sg:tags":[
        "tutoring"
    ],
    "wof:name":"Learning Assistants Instrctnl",
    "wof:placetype":"venue"
},
  "geometry": {"coordinates":[-113.490372,53.546219],"type":"Point"}
}