{
  "type": "Feature",
  "properties": {
    "addr:full":"140 Ch Sainte-Foy Quebec QC G1R 1T2",
    "addr:housenumber":"140",
    "addr:postcode":"g1r 1t2",
    "addr:street":"Ch Sainte-Foy",
    "iso:country":"CA",
    "sg:address":"140 Ch Sainte-Foy",
    "sg:city":"Quebec",
    "sg:classifiers":[
        {
            "category":"Education",
            "subcategory":"School",
            "type":"Public Place"
        }
    ],
    "sg:phone":"+1 418 525 8169",
    "sg:postcode":"G1R 1T2",
    "sg:province":"QC",
    "wof:name":"Ecole Joseph-Francois-Perrault",
    "wof:placetype":"venue"
},
  "geometry": {"coordinates":[-71.2286071777,46.8059883118],"type":"Point"}
}