{
  "type": "Feature",
  "properties": {
    "iso:country":"CA",
    "sg:city":"Mississauga",
    "sg:classifiers":[
        {
            "category":"Wholesale",
            "subcategory":"Electrical",
            "type":"Manufacturing & Wholesale Goods"
        }
    ],
    "sg:phone":"+1 905 608 2444",
    "sg:postcode":"L5L 5X9",
    "sg:province":"ON",
    "sg:tags":[
        "connector"
    ],
    "wof:name":"Steck Connections",
    "wof:placetype":"venue"
},
  "geometry": {"coordinates":[-79.7153930664,43.5284004211],"type":"Point"}
}