{
  "type": "Feature",
  "properties": {
    "iso:country":"CA",
    "sg:city":"Montreal",
    "sg:classifiers":[
        {
            "category":"Personal",
            "subcategory":"Beauty Salon",
            "type":"Services"
        }
    ],
    "sg:phone":"+1 514 256 8430",
    "sg:postcode":"H1W 1K4",
    "sg:province":"QC",
    "wof:name":"Coiffure Jm",
    "wof:placetype":"venue"
},
  "geometry": {"coordinates":[-73.5486755371,45.5521392822],"type":"Point"}
}