{
  "type": "Feature",
  "properties": {
    "addr:full":"Surrey BC V3W 3E9",
    "addr:postcode":"v3w 3e9",
    "iso:country":"CA",
    "sg:city":"Surrey",
    "sg:classifiers":[
        {
            "category":"Building & Trades",
            "subcategory":"Construction",
            "type":"Services"
        }
    ],
    "sg:phone":"+1 604 321 0012",
    "sg:postcode":"V3W 3E9",
    "sg:province":"BC",
    "sg:tags":[
        "general",
        "contractor"
    ],
    "wof:name":"Avante Raise Right Contracting",
    "wof:placetype":"venue"
},
  "geometry": {"coordinates":[-122.87576300000001,49.151924],"type":"Point"}
}