{
  "type": "Feature",
  "properties": {
    "addr:full":"2522 Bostock Rd Kamloops BC V2C 6B9",
    "addr:housenumber":"2522",
    "addr:postcode":"bc v2c 6b9",
    "addr:street":"Bostock Rd",
    "iso:country":"CA",
    "sg:address":"2522 Bostock Rd",
    "sg:city":"Kamloops",
    "sg:classifiers":[
        {
            "category":"Wholesale",
            "subcategory":"Machinery & Supplies",
            "type":"Manufacturing & Wholesale Goods"
        }
    ],
    "sg:phone":"+1 250 371 2610",
    "sg:postcode":"V2C 6B9",
    "sg:province":"BC",
    "sg:tags":[
        "contractor"
    ],
    "wof:name":"Deal Equipment",
    "wof:placetype":"venue"
},
  "geometry": {"coordinates":[-120.17965700000001,50.670891],"type":"Point"}
}