{
  "type": "Feature",
  "properties": {
    "addr:full":"Bowmanville ON L1C 3K2",
    "addr:postcode":"l1c 3k2",
    "iso:country":"CA",
    "sg:city":"Bowmanville",
    "sg:classifiers":[
        {
            "category":"Personal",
            "subcategory":"Beauty Salon",
            "type":"Services"
        }
    ],
    "sg:phone":"+1 905 432 8822",
    "sg:postcode":"L1C 3K2",
    "sg:province":"ON",
    "wof:name":"Beauty Supply Outlet",
    "wof:placetype":"venue"
},
  "geometry": {"coordinates":[-78.664497,43.912312],"type":"Point"}
}