{
  "type": "Feature",
  "properties": {
    "addr:full":"North York ON M3H 5Y4",
    "addr:postcode":"m3h 5y4",
    "iso:country":"CA",
    "sg:city":"North York",
    "sg:classifiers":[
        {
            "category":"Home & Garden",
            "subcategory":"Furniture",
            "type":"Retail Goods"
        }
    ],
    "sg:phone":"+1 416 661 0678",
    "sg:postcode":"M3H 5Y4",
    "sg:province":"ON",
    "sg:tags":[
        "second",
        "store",
        "hand"
    ],
    "wof:name":"Once Upon A Child",
    "wof:placetype":"venue"
},
  "geometry": {"coordinates":[-79.46820099999999,43.787506],"type":"Point"}
}