{
  "type": "Feature",
  "properties": {
    "addr:full":"111 Idylwyld Dr N Saskatoon SK S7L 0Y6",
    "addr:housenumber":"111",
    "addr:postcode":"s7l 0y6",
    "addr:street":"Idylwyld Dr N",
    "iso:country":"CA",
    "sg:address":"111 Idylwyld Dr N",
    "sg:city":"Saskatoon",
    "sg:classifiers":[
        {
            "category":"Retail",
            "subcategory":"Auto Repair",
            "type":"Services"
        }
    ],
    "sg:phone":"+1 306 242 5050",
    "sg:postcode":"S7L 0Y6",
    "sg:province":"SK",
    "sg:tags":[
        "tire"
    ],
    "wof:name":"Kal Tire",
    "wof:placetype":"venue"
},
  "geometry": {"coordinates":[-106.670563,52.129639],"type":"Point"}
}