{
  "type": "Feature",
  "properties": {
    "addr:full":"169 Mahonee Dr Winnipeg MB R2G 2Y9",
    "addr:housenumber":"169",
    "addr:postcode":"r2g 2y9",
    "addr:street":"Mahonee Dr",
    "iso:country":"CA",
    "sg:address":"169 Mahonee Dr",
    "sg:city":"Winnipeg",
    "sg:classifiers":[
        {
            "category":"Building & Trades",
            "subcategory":"Construction",
            "type":"Services"
        }
    ],
    "sg:phone":"+1 204 663 2626",
    "sg:postcode":"R2G 2Y9",
    "sg:province":"MB",
    "sg:tags":[
        "home",
        "builder",
        "general",
        "contractor"
    ],
    "wof:name":"Kelly Construction Ltd",
    "wof:placetype":"venue"
},
  "geometry": {"coordinates":[-97.05278800000001,49.928471],"type":"Point"}
}