{
  "type": "Feature",
  "properties": {
    "addr:full":"Calgary AB T2H 2V2",
    "addr:postcode":"t2h 2v2",
    "iso:country":"CA",
    "sg:city":"Calgary",
    "sg:classifiers":[
        {
            "category":"Home & Garden",
            "subcategory":"Garden Supply",
            "type":"Retail Goods"
        }
    ],
    "sg:phone":"+1 403 640 2632",
    "sg:postcode":"T2H 2V2",
    "sg:province":"AB",
    "sg:tags":[
        "house",
        "bird",
        "feeder"
    ],
    "wof:name":"Wild Bird Store",
    "wof:placetype":"venue"
},
  "geometry": {"coordinates":[-114.063186645,51.0450706482],"type":"Point"}
}