{
  "type": "Feature",
  "properties": {
    "iso:country":"CA",
    "sg:address":"120 Fry St",
    "sg:city":"Nanaimo",
    "sg:classifiers":[
        {
            "category":"Wholesale",
            "subcategory":"Metals & Minerals",
            "type":"Manufacturing & Wholesale Goods"
        }
    ],
    "sg:phone":"+1 250 753 0247",
    "sg:postcode":"V9R 4Y9",
    "sg:province":"BC",
    "sg:tags":[
        "rope",
        "wire"
    ],
    "wof:name":"Northwest Wire Rope Ltd",
    "wof:placetype":"venue"
},
  "geometry": {"coordinates":[-123.93019866900001,49.1593856812],"type":"Point"}
}