{
  "type": "Feature",
  "properties": {
    "addr:full":"555 Rue Notre-Dame LA Prairie QC J5R 5E5",
    "addr:housenumber":"555",
    "addr:postcode":"j5r 5e5",
    "addr:street":"Rue Notre-Dame",
    "iso:country":"CA",
    "sg:address":"555 Rue Notre-Dame",
    "sg:city":"LA Prairie",
    "sg:classifiers":[
        {
            "category":"Arena",
            "subcategory":"Sports Club",
            "type":"Entertainment"
        }
    ],
    "sg:phone":"+1 450 444 9005",
    "sg:postcode":"J5R 5E5",
    "sg:province":"QC",
    "sg:tags":[
        "athletic",
        "fields",
        "stadium"
    ],
    "wof:name":"Centre Sportif DE LA Prairie",
    "wof:placetype":"venue"
},
  "geometry": {"coordinates":[-73.495369,45.414722],"type":"Point"}
}