{
  "type": "Feature",
  "properties": {
    "iso:country":"CA",
    "sg:address":"9732 Third St",
    "sg:city":"Sidney",
    "sg:classifiers":[
        {
            "category":"Social Services",
            "type":"Services"
        }
    ],
    "sg:phone":"+1 250 656 5616",
    "sg:postcode":"V8L 3A2",
    "sg:province":"BC",
    "sg:tags":[
        "youth",
        "organization",
        "center"
    ],
    "wof:name":"Sidney Guide & Scout Hall",
    "wof:placetype":"venue"
},
  "geometry": {"coordinates":[-123.39793396,48.6473045349],"type":"Point"}
}