{
  "type": "Feature",
  "properties": {
    "iso:country":"CA",
    "sg:address":"370 Highland Rd W # 1",
    "sg:city":"Kitchener",
    "sg:classifiers":[
        {
            "category":"Food & Beverages",
            "subcategory":"Groceries & Convenience Stores",
            "type":"Retail Goods"
        }
    ],
    "sg:phone":"+1 519 744 4100",
    "sg:postcode":"N2M 5J9",
    "sg:province":"ON",
    "sg:tags":[
        "grocer"
    ],
    "wof:name":"Food Basics",
    "wof:placetype":"venue"
},
  "geometry": {"coordinates":[-80.5120544434,43.4372329712],"type":"Point"}
}