{
  "type": "Feature",
  "properties": {
    "iso:country":"CA",
    "sg:city":"Montreal",
    "sg:classifiers":[
        {
            "category":"Professional",
            "subcategory":"Research",
            "type":"Services"
        }
    ],
    "sg:phone":"+1 514 344 8786",
    "sg:postcode":"H3S 2C3",
    "sg:province":"QC",
    "sg:tags":[
        "assistance",
        "program",
        "technology"
    ],
    "wof:name":"Flogen Technologies",
    "wof:placetype":"venue"
},
  "geometry": {"coordinates":[-73.626274,45.501068],"type":"Point"}
}