{
  "type": "Feature",
  "properties": {
    "addr:full":"5501 Rue Saint-Jacques Montreal QC H4A 2E3",
    "addr:housenumber":"5501",
    "addr:postcode":"h4a 2e3",
    "addr:street":"Rue Saint-Jacques",
    "iso:country":"CA",
    "sg:address":"5501 Rue Saint-Jacques",
    "sg:city":"Montreal",
    "sg:classifiers":[
        {
            "category":"Food & Beverages",
            "subcategory":"Groceries & Convenience Stores",
            "type":"Retail Goods"
        }
    ],
    "sg:phone":"+1 514 489 8944",
    "sg:postcode":"H4A 2E3",
    "sg:province":"QC",
    "sg:tags":[
        "grocer"
    ],
    "wof:name":"Marche Merlin Market",
    "wof:placetype":"venue"
},
  "geometry": {"coordinates":[-73.6045227051,45.4691314697],"type":"Point"}
}