{
  "type": "Feature",
  "properties": {
    "addr:full":"261 Av Bloomfield Outremont QC H2V 3R6",
    "addr:postcode":"h2v 3r6",
    "addr:street":"261 Av Bloomfield",
    "iso:country":"CA",
    "sg:address":"261 Av Bloomfield",
    "sg:city":"Outremont",
    "sg:classifiers":[
        {
            "category":"Organizations",
            "subcategory":"Professional Association",
            "type":"Services"
        }
    ],
    "sg:phone":"+1 514 278 2232",
    "sg:postcode":"H2V 3R6",
    "sg:province":"QC",
    "sg:tags":[
        "publisher"
    ],
    "wof:name":"Institut D'Histoire DE L'Amer",
    "wof:placetype":"venue"
},
  "geometry": {"coordinates":[-73.6018981934,45.517906189],"type":"Point"}
}