{
  "type": "Feature",
  "properties": {
    "addr:full":"182 Townsend St Peterborough ON K9J 2K3",
    "addr:housenumber":"182",
    "addr:postcode":"k9j 2k3",
    "addr:street":"Townsend St",
    "iso:country":"CA",
    "sg:address":"182 Townsend St",
    "sg:city":"Peterborough",
    "sg:classifiers":[
        {
            "category":"Government",
            "subcategory":"Office",
            "type":"Public Place"
        }
    ],
    "sg:phone":"+1 705 745 1386",
    "sg:postcode":"K9J 2K3",
    "sg:province":"ON",
    "sg:tags":[
        "village"
    ],
    "wof:name":"Peterborough Public Works",
    "wof:placetype":"venue"
},
  "geometry": {"coordinates":[-78.321274,44.29715],"type":"Point"}
}