{
  "type": "Feature",
  "properties": {
    "addr:full":"415 Pth 5 Ste Rose Du Lac MB R0L 1S0",
    "addr:housenumber":"415;5 ste",
    "addr:postcode":"r0l 1s0",
    "addr:street":"Pth;Rose Du Lac",
    "iso:country":"CA",
    "sg:address":"415 Pth 5",
    "sg:city":"Ste Rose Du Lac",
    "sg:classifiers":[
        {
            "category":"Retail",
            "subcategory":"Auto Repair",
            "type":"Services"
        }
    ],
    "sg:phone":"+1 204 447 3138",
    "sg:postcode":"R0L 1S0",
    "sg:province":"MB",
    "sg:tags":[
        "body",
        "automobile",
        "painting"
    ],
    "wof:name":"Ste Rose Autobody",
    "wof:placetype":"venue"
},
  "geometry": {"coordinates":[-99.5232009888,51.0591850281],"type":"Point"}
}