{
  "type": "Feature",
  "properties": {
    "addr:full":"100 Galena Rd Whitehorse YT Y1A 2W6",
    "addr:housenumber":"100",
    "addr:postcode":"y1a 2w6",
    "addr:street":"Galena Rd",
    "iso:country":"CA",
    "sg:address":"100 Galena Rd",
    "sg:city":"Whitehorse",
    "sg:classifiers":[
        {
            "category":"Organizations",
            "subcategory":"Professional Association",
            "type":"Services"
        }
    ],
    "sg:phone":"+1 867 667 7269",
    "sg:postcode":"Y1A 2W6",
    "sg:province":"YT",
    "sg:tags":[
        "recycling",
        "center"
    ],
    "wof:name":"Raven Recycling Society",
    "wof:placetype":"venue"
},
  "geometry": {"coordinates":[-135.07237243599999,60.7403335571],"type":"Point"}
}