{
  "type": "Feature",
  "properties": {
    "addr:full":"685 Humboldt St Victoria BC V8W 1A6",
    "addr:housenumber":"685",
    "addr:postcode":"v8w 1a6",
    "addr:street":"Humboldt St",
    "iso:country":"CA",
    "sg:address":"685 Humboldt St",
    "sg:city":"Victoria",
    "sg:classifiers":[
        {
            "category":"Retail",
            "subcategory":"Photofinishing",
            "type":"Services"
        }
    ],
    "sg:phone":"+1 250 383 8086",
    "sg:postcode":"V8W 1A6",
    "sg:province":"BC",
    "sg:tags":[
        "photo",
        "finishing"
    ],
    "wof:name":"Snappy 1 Hour Foto",
    "wof:placetype":"venue"
},
  "geometry": {"coordinates":[-123.366394043,48.4221229553],"type":"Point"}
}