{
  "type": "Feature",
  "properties": {
    "iso:country":"CA",
    "sg:address":"871 Rue Melanie",
    "sg:city":"Laval",
    "sg:classifiers":[
        {
            "category":"Health Services",
            "subcategory":"Medical Lab",
            "type":"Services"
        }
    ],
    "sg:phone":"+1 450 969 0148",
    "sg:postcode":"H7X 3V3",
    "sg:province":"QC",
    "sg:tags":[
        "laboratory"
    ],
    "wof:name":"Dentoflex Inc",
    "wof:placetype":"venue"
},
  "geometry": {"coordinates":[-73.7962875366,45.5362625122],"type":"Point"}
}