{
  "type": "Feature",
  "properties": {
    "addr:full":"115 Vodden St E Brampton ON L6V 1M4",
    "addr:housenumber":"115",
    "addr:postcode":"l6v 1m4",
    "addr:street":"Vodden St E",
    "iso:country":"CA",
    "sg:address":"115 Vodden St E",
    "sg:city":"Brampton",
    "sg:classifiers":[
        {
            "category":"Organizations",
            "subcategory":"Religious Organization",
            "type":"Services"
        }
    ],
    "sg:phone":"+1 905 453 1303",
    "sg:postcode":"L6V 1M4",
    "sg:province":"ON",
    "sg:tags":[
        "church"
    ],
    "wof:name":"St Anne's Church",
    "wof:placetype":"venue"
},
  "geometry": {"coordinates":[-79.76308400000001,43.698627],"type":"Point"}
}