{
  "type": "Feature",
  "properties": {
    "addr:full":"7725 Jane St Concord ON L4K 1X4",
    "addr:housenumber":"7725",
    "addr:postcode":"l4k 1x4",
    "addr:street":"Jane St",
    "iso:country":"CA",
    "sg:address":"7725 Jane St",
    "sg:city":"Concord",
    "sg:classifiers":[
        {
            "category":"Shopping",
            "subcategory":"Computers & Home Electronics",
            "type":"Retail Goods"
        }
    ],
    "sg:phone":"+1 905 761 8800",
    "sg:postcode":"L4K 1X4",
    "sg:province":"ON",
    "sg:tags":[
        "software"
    ],
    "wof:name":"Accubid Systems",
    "wof:placetype":"venue"
},
  "geometry": {"coordinates":[-79.524063,43.793026],"type":"Point"}
}