{
  "type": "Feature",
  "properties": {
    "addr:full":"143 Rue DE LA Station Laval QC H7M 3W1",
    "addr:housenumber":"143",
    "addr:postcode":"h7m 3w1",
    "addr:street":"Rue De La Station",
    "iso:country":"CA",
    "sg:address":"143 Rue DE LA Station",
    "sg:city":"Laval",
    "sg:classifiers":[
        {
            "category":"Building & Trades",
            "subcategory":"Construction",
            "type":"Services"
        }
    ],
    "sg:phone":"+1 450 663 7155",
    "sg:postcode":"H7M 3W1",
    "sg:province":"QC",
    "sg:tags":[
        "general",
        "contractor"
    ],
    "wof:name":"Entreprises Jg Guimond Inc",
    "wof:placetype":"venue"
},
  "geometry": {"coordinates":[-73.722633,45.587593],"type":"Point"}
}