{
  "type": "Feature",
  "properties": {
    "addr:full":"2610 12th Ave Port Alberni BC V9Y 2T7",
    "addr:housenumber":"2610",
    "addr:postcode":"v9y 2t7",
    "addr:street":"12Th Ave",
    "iso:country":"CA",
    "sg:address":"2610 12th Ave",
    "sg:city":"Port Alberni",
    "sg:classifiers":[
        {
            "category":"Travel",
            "subcategory":"Hotels & Motels",
            "type":"Entertainment"
        }
    ],
    "sg:phone":"+1 250 723 5940",
    "sg:postcode":"V9Y 2T7",
    "sg:province":"BC",
    "sg:tags":[
        "breakfast",
        "accommodation",
        "bed"
    ],
    "wof:name":"Edelweiss Bed & Breakfast",
    "wof:placetype":"venue"
},
  "geometry": {"coordinates":[-124.795219421,49.2272338867],"type":"Point"}
}