{
  "type": "Feature",
  "properties": {
    "addr:full":"PO Box 68 Acadia Valley AB T0J 0A0",
    "addr:housenumber":"po box 68",
    "addr:postcode":"t0j 0a0",
    "addr:street":"Acadia Valley",
    "iso:country":"CA",
    "sg:address":"PO Box 68",
    "sg:city":"Acadia Valley",
    "sg:classifiers":[
        {
            "category":"Food & Beverages",
            "subcategory":"Groceries & Convenience Stores",
            "type":"Retail Goods"
        }
    ],
    "sg:phone":"+1 403 972 3861",
    "sg:postcode":"T0J 0A0",
    "sg:province":"AB",
    "sg:tags":[
        "grocer"
    ],
    "wof:name":"Brent's Family Foods",
    "wof:placetype":"venue"
},
  "geometry": {"coordinates":[-110.21421814,51.1582489014],"type":"Point"}
}