{
  "type": "Feature",
  "properties": {
    "addr:full":"7 Clarke St Grimsby ON L3M 1Y5",
    "addr:housenumber":"7",
    "addr:postcode":"l3m 1y5",
    "addr:street":"Clarke St",
    "iso:country":"CA",
    "sg:address":"7 Clarke St",
    "sg:city":"Grimsby",
    "sg:classifiers":[
        {
            "category":"Retail",
            "subcategory":"Auto Repair",
            "type":"Services"
        }
    ],
    "sg:phone":"+1 905 945 3824",
    "sg:postcode":"L3M 1Y5",
    "sg:province":"ON",
    "sg:tags":[
        "automobile",
        "top",
        "upholstery"
    ],
    "wof:name":"Auto Interiors By John",
    "wof:placetype":"venue"
},
  "geometry": {"coordinates":[-79.55584,43.196011],"type":"Point"}
}