{
  "type": "Feature",
  "properties": {
    "addr:full":"4209 32 St Vernon BC V1T 5P3",
    "addr:housenumber":"4209",
    "addr:postcode":"v1t 5p3",
    "addr:street":"32 St",
    "iso:country":"CA",
    "sg:address":"4209 32 St",
    "sg:city":"Vernon",
    "sg:classifiers":[
        {
            "category":"Restaurant",
            "type":"Food & Drink"
        }
    ],
    "sg:phone":"+1 250 542 7573",
    "sg:postcode":"V1T 5P3",
    "sg:province":"BC",
    "wof:name":"Dairy Queen Brazier",
    "wof:placetype":"venue"
},
  "geometry": {"coordinates":[-119.27355957,50.2733306885],"type":"Point"}
}