{
  "type": "Feature",
  "properties": {
    "addr:full":"358 Av Dionne Pointe-Au-Pere QC G5M 1N8",
    "addr:housenumber":"358",
    "addr:postcode":"g5m 1n8",
    "addr:street":"Av Dionne",
    "iso:country":"CA",
    "sg:address":"358 Av Dionne",
    "sg:city":"Pointe-Au-Pere",
    "sg:classifiers":[
        {
            "category":"Building & Trades",
            "subcategory":"Cleaning & Sanitation",
            "type":"Services"
        }
    ],
    "sg:phone":"+1 418 722 9715",
    "sg:postcode":"G5M 1N8",
    "sg:province":"QC",
    "sg:tags":[
        "janitor"
    ],
    "wof:name":"Jean N'Ettoie",
    "wof:placetype":"venue"
},
  "geometry": {"coordinates":[-68.4572067261,48.5094795227],"type":"Point"}
}