{
  "type": "Feature",
  "properties": {
    "addr:full":"1085 Rue DE Port-Royal O Montreal QC H4N 1G1",
    "addr:housenumber":"1085",
    "addr:postcode":"h4n 1g1",
    "addr:street":"Rue De Port-Royal O",
    "iso:country":"CA",
    "sg:address":"1085 Rue DE Port-Royal O",
    "sg:city":"Montreal",
    "sg:classifiers":[
        {
            "category":"Retail",
            "subcategory":"Auto Repair",
            "type":"Services"
        }
    ],
    "sg:phone":"+1 514 331 6055",
    "sg:postcode":"H4N 1G1",
    "sg:province":"QC",
    "sg:tags":[
        "repairing",
        "automobile"
    ],
    "wof:name":"Jmac Ctr D'Auto",
    "wof:placetype":"venue"
},
  "geometry": {"coordinates":[-73.6638717651,45.5355911255],"type":"Point"}
}