{
  "type": "Feature",
  "properties": {
    "iso:country":"CA",
    "sg:city":"North Vancouver",
    "sg:classifiers":[
        {
            "category":"Health Services",
            "subcategory":"Doctor",
            "type":"Services"
        }
    ],
    "sg:phone":"+1 604 988 7780",
    "sg:postcode":"V7M 1V5",
    "sg:province":"BC",
    "sg:tags":[
        "dentist"
    ],
    "wof:name":"Mohebiany, Mahmood DDS",
    "wof:placetype":"venue"
},
  "geometry": {"coordinates":[-123.073494,49.32402],"type":"Point"}
}