{
  "type": "Feature",
  "properties": {
    "addr:full":"360 8th St Brandon MB R7A 3X4",
    "addr:housenumber":"360",
    "addr:postcode":"r7a 3x4",
    "addr:street":"8Th St",
    "iso:country":"CA",
    "sg:address":"360 8th St",
    "sg:city":"Brandon",
    "sg:classifiers":[
        {
            "category":"Shopping",
            "subcategory":"Used Merchandise",
            "type":"Retail Goods"
        }
    ],
    "sg:phone":"+1 204 727 7117",
    "sg:postcode":"R7A 3X4",
    "sg:province":"MB",
    "sg:tags":[
        "salon",
        "beauty"
    ],
    "wof:name":"Finer Things in Life",
    "wof:placetype":"venue"
},
  "geometry": {"coordinates":[-99.948868,49.844421],"type":"Point"}
}