{
  "type": "Feature",
  "properties": {
    "addr:full":"928 Kingston Rd Toronto ON M4E 1S5",
    "addr:housenumber":"928",
    "addr:postcode":"m4e 1s5",
    "addr:street":"Kingston Rd",
    "iso:country":"CA",
    "sg:address":"928 Kingston Rd",
    "sg:city":"Toronto",
    "sg:classifiers":[
        {
            "category":"Cinema",
            "subcategory":"Movie Rental",
            "type":"Entertainment"
        }
    ],
    "sg:phone":"+1 416 690 0246",
    "sg:postcode":"M4E 1S5",
    "sg:province":"ON",
    "sg:tags":[
        "leasing",
        "video",
        "disc",
        "tape"
    ],
    "wof:name":"Movies 2 Go",
    "wof:placetype":"venue"
},
  "geometry": {"coordinates":[-79.2886581421,43.6805305481],"type":"Point"}
}