{
  "type": "Feature",
  "properties": {
    "addr:full":"3828 47 Ave Camrose AB T4V 3W8",
    "addr:housenumber":"3828",
    "addr:postcode":"t4v 3w8",
    "addr:street":"47 Ave",
    "iso:country":"CA",
    "sg:address":"3828 47 Ave",
    "sg:city":"Camrose",
    "sg:classifiers":[
        {
            "category":"Retail",
            "subcategory":"Auto Repair",
            "type":"Services"
        }
    ],
    "sg:phone":"+1 780 672 6369",
    "sg:postcode":"T4V 3W8",
    "sg:province":"AB",
    "sg:tags":[
        "farm",
        "equipment",
        "repairing",
        "automobile"
    ],
    "wof:name":"R & S Mechanical Repair",
    "wof:placetype":"venue"
},
  "geometry": {"coordinates":[-112.802803,53.014938],"type":"Point"}
}