{
  "type": "Feature",
  "properties": {
    "addr:full":"6670 Campobello Rd Mississauga ON L5N 2L8",
    "addr:housenumber":"6670",
    "addr:postcode":"l5n 2l8",
    "addr:street":"Campobello Rd",
    "iso:country":"CA",
    "sg:address":"6670 Campobello Rd",
    "sg:city":"Mississauga",
    "sg:classifiers":[
        {
            "category":"Wholesale",
            "subcategory":"Durable Goods & Equipment",
            "type":"Manufacturing & Wholesale Goods"
        }
    ],
    "sg:phone":"+1 905 826 5525",
    "sg:postcode":"L5N 2L8",
    "sg:province":"ON",
    "sg:tags":[
        "laboratory",
        "supply"
    ],
    "wof:name":"Brinkmann Instruments Ltd",
    "wof:placetype":"venue"
},
  "geometry": {"coordinates":[-79.7331314087,43.6080665588],"type":"Point"}
}