{
  "type": "Feature",
  "properties": {
    "iso:country":"CA",
    "sg:address":"984 Av Du Phare O",
    "sg:city":"Matane",
    "sg:classifiers":[
        {
            "category":"Professional",
            "subcategory":"Business Services",
            "type":"Services"
        }
    ],
    "sg:phone":"+1 418 562 6606",
    "sg:postcode":"G4W 3M6",
    "sg:province":"QC",
    "sg:tags":[
        "recording",
        "studio"
    ],
    "wof:name":"Passeport Audio",
    "wof:placetype":"venue"
},
  "geometry": {"coordinates":[-67.55132293699999,48.8491134644],"type":"Point"}
}