{
  "type": "Feature",
  "properties": {
    "iso:country":"CA",
    "sg:address":"5385 Lakeshore Rd",
    "sg:city":"Burlington",
    "sg:classifiers":[
        {
            "category":"Banks & Credit Unions",
            "subcategory":"Bank",
            "type":"Services"
        }
    ],
    "sg:phone":"+1 905 637 5231",
    "sg:postcode":"L7L 1C8",
    "sg:province":"ON",
    "wof:name":"Scotiabank",
    "wof:placetype":"venue"
},
  "geometry": {"coordinates":[-79.7306518555,43.3677711487],"type":"Point"}
}