{
  "type": "Feature",
  "properties": {
    "addr:full":"31 Henrietta Ave Sault Ste Marie ON P6C 1Z4",
    "addr:housenumber":"31",
    "addr:postcode":"p6c 1z4",
    "addr:street":"Henrietta Ave",
    "iso:country":"CA",
    "sg:address":"31 Henrietta Ave",
    "sg:city":"Sault Ste Marie",
    "sg:classifiers":[
        {
            "category":"Real Estate",
            "subcategory":"Real Estate Agent",
            "type":"Services"
        }
    ],
    "sg:phone":"+1 705 945 8899",
    "sg:postcode":"P6C 1Z4",
    "sg:province":"ON",
    "wof:name":"Bob Berto Real Estate & Appr",
    "wof:placetype":"venue"
},
  "geometry": {"coordinates":[-84.3518981934,46.5338439941],"type":"Point"}
}