{
  "type": "Feature",
  "properties": {
    "iso:country":"CA",
    "sg:city":"Saint-Sebastien",
    "sg:classifiers":[
        {
            "category":"Restaurant",
            "type":"Food & Drink"
        }
    ],
    "sg:phone":"+1 450 244 5479",
    "sg:postcode":"J0J 2C0",
    "sg:province":"QC",
    "wof:name":"Restaurant Alyce",
    "wof:placetype":"venue"
},
  "geometry": {"coordinates":[-70.9491882324,45.766456604],"type":"Point"}
}