{
  "type": "Feature",
  "properties": {
    "addr:full":"347 Rue Marie-DE-L'Incarnation Quebec QC G1N 3G9",
    "addr:housenumber":"347",
    "addr:postcode":"g1n 3g9",
    "addr:street":"Rue Marie-De-L'Incarnation",
    "iso:country":"CA",
    "sg:address":"347 Rue Marie-DE-L'Incarnation",
    "sg:city":"Quebec",
    "sg:classifiers":[
        {
            "category":"Professional",
            "subcategory":"Detective & Security Services",
            "type":"Services"
        }
    ],
    "sg:phone":"+1 418 687 3150",
    "sg:postcode":"G1N 3G9",
    "sg:province":"QC",
    "sg:tags":[
        "control",
        "burglary",
        "protective",
        "system",
        "robbery"
    ],
    "wof:name":"Panavideo Inc",
    "wof:placetype":"venue"
},
  "geometry": {"coordinates":[-71.4194717407,46.858581543],"type":"Point"}
}