{
  "type": "Feature",
  "properties": {
    "iso:country":"CA",
    "sg:address":"179 Valmont Crt",
    "sg:city":"Ancaster",
    "sg:classifiers":[
        {
            "category":"Real Estate",
            "subcategory":"Real Estate Agent",
            "type":"Services"
        }
    ],
    "sg:phone":"+1 905 637 7300",
    "sg:postcode":"L9G 5A1",
    "sg:province":"ON",
    "sg:tags":[
        "inspection"
    ],
    "wof:name":"Pillar To Post",
    "wof:placetype":"venue"
},
  "geometry": {"coordinates":[-80.015296936,43.2113075256],"type":"Point"}
}