{
  "type": "Feature",
  "properties": {
    "addr:full":"Almonte ON K0A 1A0",
    "addr:postcode":"k0a 1a0",
    "iso:country":"CA",
    "sg:city":"Almonte",
    "sg:classifiers":[
        {
            "category":"Recreation",
            "type":"Entertainment"
        }
    ],
    "sg:phone":"+1 613 256 5401",
    "sg:postcode":"K0A 1A0",
    "sg:province":"ON",
    "sg:tags":[
        "range",
        "practice",
        "golf"
    ],
    "wof:name":"Brown's Green Driving Range",
    "wof:placetype":"venue"
},
  "geometry": {"coordinates":[-76.212166,45.207691],"type":"Point"}
}