{
  "type": "Feature",
  "properties": {
    "addr:full":"559 Talbot St St Thomas ON N5P 1C5",
    "addr:housenumber":"559",
    "addr:postcode":"n5p 1c5",
    "addr:street":"Talbot St",
    "iso:country":"CA",
    "sg:address":"559 Talbot St",
    "sg:city":"St Thomas",
    "sg:classifiers":[
        {
            "category":"Shopping",
            "subcategory":"Jewelry",
            "type":"Retail Goods"
        }
    ],
    "sg:phone":"+1 519 631 9620",
    "sg:postcode":"N5P 1C5",
    "sg:province":"ON",
    "sg:tags":[
        "jeweler"
    ],
    "wof:name":"Toth Jewellers",
    "wof:placetype":"venue"
},
  "geometry": {"coordinates":[-81.192696,42.779064],"type":"Point"}
}