{
  "type": "Feature",
  "properties": {
    "addr:full":"1010 16 Ave NW Calgary AB T2M 0K5",
    "addr:housenumber":"1010",
    "addr:postcode":"t2m 0k5",
    "addr:street":"16 Ave Nw",
    "iso:country":"CA",
    "sg:address":"1010 16 Ave NW",
    "sg:city":"Calgary",
    "sg:classifiers":[
        {
            "category":"Shopping",
            "subcategory":"Books",
            "type":"Retail Goods"
        }
    ],
    "sg:phone":"+1 403 220 1399",
    "sg:postcode":"T2M 0K5",
    "sg:province":"AB",
    "sg:tags":[
        "comic"
    ],
    "wof:name":"Phoenix Comic Books",
    "wof:placetype":"venue"
},
  "geometry": {"coordinates":[-114.083511,51.067165],"type":"Point"}
}