{
  "type": "Feature",
  "properties": {
    "addr:full":"1360 Railway Ave Elbow SK S0H 1J0",
    "addr:housenumber":"1360",
    "addr:postcode":"s0h 1j0",
    "addr:street":"Railway Ave Elbow",
    "iso:country":"CA",
    "sg:address":"1360 Railway Ave",
    "sg:city":"Elbow",
    "sg:classifiers":[
        {
            "category":"Organizations",
            "subcategory":"Religious Organization",
            "type":"Services"
        }
    ],
    "sg:phone":"+1 306 854 2044",
    "sg:postcode":"S0H 1J0",
    "sg:province":"SK",
    "sg:tags":[
        "church"
    ],
    "wof:name":"Bethel Lutheran Church",
    "wof:placetype":"venue"
},
  "geometry": {"coordinates":[-106.59440600000001,51.121407],"type":"Point"}
}