{
  "type": "Feature",
  "properties": {
    "addr:full":"394 Av Saint-Jerome Matane QC G4W 3B5",
    "addr:postcode":"g4w 3b5",
    "addr:street":"394 Av Saint-Jerome",
    "iso:country":"CA",
    "sg:address":"394 Av Saint-Jerome",
    "sg:city":"Matane",
    "sg:classifiers":[
        {
            "category":"Taxi",
            "type":"Transportation"
        }
    ],
    "sg:phone":"+1 418 562 2030",
    "sg:postcode":"G4W 3B5",
    "sg:province":"QC",
    "sg:tags":[
        "taxicab"
    ],
    "wof:name":"Taxi Association 2030",
    "wof:placetype":"venue"
},
  "geometry": {"coordinates":[-67.529442,48.846954],"type":"Point"}
}