{
  "type": "Feature",
  "properties": {
    "addr:full":"4502 56 St # 101 Wetaskiwin AB T9A 3M5",
    "addr:housenumber":"4502",
    "addr:postcode":"t9a 3m5",
    "addr:street":"56 St # 101",
    "iso:country":"CA",
    "sg:address":"4502 56 St # 101",
    "sg:city":"Wetaskiwin",
    "sg:classifiers":[
        {
            "category":"Restaurant",
            "type":"Food & Drink"
        }
    ],
    "sg:phone":"+1 780 352 8895",
    "sg:postcode":"T9A 3M5",
    "sg:province":"AB",
    "wof:name":"2 For 1 Pizza & Pasta",
    "wof:placetype":"venue"
},
  "geometry": {"coordinates":[-113.390434,52.965508],"type":"Point"}
}