{
  "type": "Feature",
  "properties": {
    "addr:full":"4300 Steeles Ave W Woodbridge ON L4L 4C2",
    "addr:housenumber":"4300",
    "addr:postcode":"l4l 4c2",
    "addr:street":"Steeles Ave W",
    "iso:country":"CA",
    "sg:address":"4300 Steeles Ave W",
    "sg:city":"Woodbridge",
    "sg:classifiers":[
        {
            "category":"Organizations",
            "subcategory":"Professional Association",
            "type":"Services"
        }
    ],
    "sg:phone":"+1 905 851 8453",
    "sg:postcode":"L4L 4C2",
    "sg:province":"ON",
    "wof:name":"Delia Social Club",
    "wof:placetype":"venue"
},
  "geometry": {"coordinates":[-79.5611343384,43.7674293518],"type":"Point"}
}