{
  "type": "Feature",
  "properties": {
    "addr:full":"444 Starret Rd Hope BC V0X 1L2",
    "addr:housenumber":"444",
    "addr:postcode":"v0x 1l2",
    "addr:street":"Starret Rd",
    "iso:country":"CA",
    "sg:address":"444 Starret Rd",
    "sg:city":"Hope",
    "sg:classifiers":[
        {
            "category":"Education",
            "subcategory":"School",
            "type":"Public Place"
        }
    ],
    "sg:phone":"+1 604 869 5629",
    "sg:postcode":"V0X 1L2",
    "sg:province":"BC",
    "wof:name":"Career Education",
    "wof:placetype":"venue"
},
  "geometry": {"coordinates":[-121.480492,49.367401],"type":"Point"}
}