{
  "type": "Feature",
  "properties": {
    "addr:full":"899 Rue Vercheres Longueuil QC J4K 2Y8",
    "addr:housenumber":"899",
    "addr:postcode":"j4k 2y8",
    "addr:street":"Rue Vercheres",
    "iso:country":"CA",
    "sg:address":"899 Rue Vercheres",
    "sg:city":"Longueuil",
    "sg:classifiers":[
        {
            "category":"Real Estate",
            "subcategory":"Surveying",
            "type":"Services"
        }
    ],
    "sg:phone":"+1 450 677 5231",
    "sg:postcode":"J4K 2Y8",
    "sg:province":"QC",
    "sg:tags":[
        "surveyor"
    ],
    "wof:name":"Sice Arpenteurs Geometres",
    "wof:placetype":"venue"
},
  "geometry": {"coordinates":[-73.509102,45.516541],"type":"Point"}
}