{
  "type": "Feature",
  "properties": {
    "addr:full":"71 Evelyn Ave Toronto ON M6P 2Z2",
    "addr:housenumber":"71",
    "addr:postcode":"m6p 2z2",
    "addr:street":"Evelyn Ave",
    "iso:country":"CA",
    "sg:address":"71 Evelyn Ave",
    "sg:city":"Toronto",
    "sg:classifiers":[
        {
            "category":"Professional",
            "subcategory":"Management & Consulting",
            "type":"Services"
        }
    ],
    "sg:phone":"+1 416 769 1885",
    "sg:postcode":"M6P 2Z2",
    "sg:province":"ON",
    "sg:tags":[
        "consultant",
        "business"
    ],
    "wof:name":"Robert Fabian Assoc",
    "wof:placetype":"venue"
},
  "geometry": {"coordinates":[-79.472069,43.656918],"type":"Point"}
}