{
  "type": "Feature",
  "properties": {
    "addr:full":"4395 Fraser St Vancouver BC V5V 4G4",
    "addr:housenumber":"4395",
    "addr:postcode":"v5v 4g4",
    "addr:street":"Fraser St",
    "iso:country":"CA",
    "sg:address":"4395 Fraser St",
    "sg:city":"Vancouver",
    "sg:classifiers":[
        {
            "category":"Real Estate",
            "subcategory":"Real Estate Agent",
            "type":"Services"
        }
    ],
    "sg:phone":"+1 604 873 4811",
    "sg:postcode":"V5V 4G4",
    "sg:province":"BC",
    "wof:name":"Goodrich Realty Corp",
    "wof:placetype":"venue"
},
  "geometry": {"coordinates":[-123.090301514,49.2457427979],"type":"Point"}
}