{
  "type": "Feature",
  "properties": {
    "addr:full":"950 Boul Du Seminaire N Saint-Jean-Sur-Richelieu QC J3A 1L2",
    "addr:housenumber":"950",
    "addr:postcode":"j3a 1l2",
    "addr:street":"Boul Du Seminaire N",
    "iso:country":"CA",
    "sg:address":"950 Boul Du Seminaire N",
    "sg:city":"Saint-Jean-Sur-Richelieu",
    "sg:classifiers":[
        {
            "category":"Personal",
            "subcategory":"Beauty Salon",
            "type":"Services"
        }
    ],
    "sg:phone":"+1 450 359 7358",
    "sg:postcode":"J3A 1L2",
    "sg:province":"QC",
    "wof:name":"Griffe Coiffure Unisexe",
    "wof:placetype":"venue"
},
  "geometry": {"coordinates":[-73.26821099999999,45.334339],"type":"Point"}
}