{
  "type": "Feature",
  "properties": {
    "addr:full":"207 Burrrows Ave E Melfort SK S0E 1A0",
    "addr:housenumber":"207",
    "addr:postcode":"s0e 1a0",
    "addr:street":"Burrrows Ave E Melfort",
    "iso:country":"CA",
    "sg:address":"207 Burrrows Ave E",
    "sg:city":"Melfort",
    "sg:classifiers":[
        {
            "category":"Real Estate",
            "subcategory":"Surveying",
            "type":"Services"
        }
    ],
    "sg:phone":"+1 306 752 2252",
    "sg:postcode":"S0E 1A0",
    "sg:province":"SK",
    "sg:tags":[
        "surveyor"
    ],
    "wof:name":"Tri-City Surveys Ltd",
    "wof:placetype":"venue"
},
  "geometry": {"coordinates":[-104.60781900000001,52.859646],"type":"Point"}
}