{
  "type": "Feature",
  "properties": {
    "addr:full":"410 Fourth St Strathmore AB T1P 1B4",
    "addr:housenumber":"410",
    "addr:postcode":"t1p 1b4",
    "addr:street":"Fourth St",
    "iso:country":"CA",
    "sg:address":"410 Fourth St",
    "sg:city":"Strathmore",
    "sg:classifiers":[
        {
            "category":"Organizations",
            "subcategory":"Religious Organization",
            "type":"Services"
        }
    ],
    "sg:phone":"+1 403 934 3025",
    "sg:postcode":"T1P 1B4",
    "sg:province":"AB",
    "sg:tags":[
        "church"
    ],
    "wof:name":"United Church",
    "wof:placetype":"venue"
},
  "geometry": {"coordinates":[-113.399681,51.04063],"type":"Point"}
}