{
  "type": "Feature",
  "properties": {
    "iso:country":"CA",
    "sg:city":"Mississauga",
    "sg:classifiers":[
        {
            "category":"Travel",
            "subcategory":"Travel Agent",
            "type":"Entertainment"
        }
    ],
    "sg:phone":"+1 905 670 8710",
    "sg:postcode":"L4W 4P4",
    "sg:province":"ON",
    "sg:tags":[
        "agency",
        "bureau"
    ],
    "wof:name":"Kintetsu International Express",
    "wof:placetype":"venue"
},
  "geometry": {"coordinates":[-79.6407165527,43.6524772644],"type":"Point"}
}