{
  "type": "Feature",
  "properties": {
    "addr:full":"1 Airport Rd Hearst ON P0L 1N0",
    "addr:housenumber":"1",
    "addr:postcode":"p0l 1n0",
    "addr:street":"Airport Rd",
    "iso:country":"CA",
    "sg:address":"1 Airport Rd",
    "sg:city":"Hearst",
    "sg:classifiers":[
        {
            "category":"Building & Trades",
            "subcategory":"Equipment Rental",
            "type":"Services"
        }
    ],
    "sg:phone":"+1 705 362 8505",
    "sg:postcode":"P0L 1N0",
    "sg:province":"ON",
    "sg:tags":[
        "aircraft",
        "leasing",
        "charter"
    ],
    "wof:name":"Aviation Commercial Aviation",
    "wof:placetype":"venue"
},
  "geometry": {"coordinates":[-83.69137600000001,49.705467],"type":"Point"}
}