{
  "type": "Feature",
  "properties": {
    "addr:full":"1367 128 St Surrey BC V4A 3T5",
    "addr:housenumber":"1367",
    "addr:postcode":"v4a 3t5",
    "addr:street":"128 St",
    "iso:country":"CA",
    "sg:address":"1367 128 St",
    "sg:city":"Surrey",
    "sg:classifiers":[
        {
            "category":"Travel",
            "subcategory":"Campground",
            "type":"Entertainment"
        }
    ],
    "sg:phone":"+1 604 538 9216",
    "sg:postcode":"V4A 3T5",
    "sg:province":"BC",
    "sg:tags":[
        "camp"
    ],
    "wof:name":"Kwomais United Church Camp",
    "wof:placetype":"venue"
},
  "geometry": {"coordinates":[-122.86766799999999,49.027061],"type":"Point"}
}