{
  "type": "Feature",
  "properties": {
    "addr:full":"9383 222 St Langley BC V1M 3T7",
    "addr:housenumber":"9383",
    "addr:postcode":"v1m 3t7",
    "addr:street":"222 St",
    "iso:country":"CA",
    "sg:address":"9383 222 St",
    "sg:city":"Langley",
    "sg:classifiers":[
        {
            "category":"Organizations",
            "subcategory":"Religious Organization",
            "type":"Services"
        }
    ],
    "sg:phone":"+1 604 513 3665",
    "sg:postcode":"V1M 3T7",
    "sg:province":"BC",
    "sg:tags":[
        "church"
    ],
    "wof:name":"Queen of Peace Monastery",
    "wof:placetype":"venue"
},
  "geometry": {"coordinates":[-122.60697937,49.1732025146],"type":"Point"}
}