{
  "type": "Feature",
  "properties": {
    "addr:full":"22 Northumberland Ayr ON N0B 1E0",
    "addr:housenumber":"22",
    "addr:postcode":"n0b 1e0",
    "addr:street":"Northumberland",
    "iso:country":"CA",
    "sg:address":"22 Northumberland",
    "sg:city":"Ayr",
    "sg:classifiers":[
        {
            "category":"Restaurant",
            "type":"Food & Drink"
        }
    ],
    "sg:phone":"+1 519 632 9401",
    "sg:postcode":"N0B 1E0",
    "sg:province":"ON",
    "wof:name":"Ayr Village Pizza",
    "wof:placetype":"venue"
},
  "geometry": {"coordinates":[-80.45138549799999,43.2860946655],"type":"Point"}
}