{
  "type": "Feature",
  "properties": {
    "addr:full":"20 Rose St Barrie ON L4M 2T2",
    "addr:housenumber":"20",
    "addr:postcode":"l4m 2t2",
    "addr:street":"Rose St",
    "iso:country":"CA",
    "sg:address":"20 Rose St",
    "sg:city":"Barrie",
    "sg:classifiers":[
        {
            "category":"Government",
            "subcategory":"Police Station",
            "type":"Public Place"
        }
    ],
    "sg:phone":"+1 705 726 6484",
    "sg:postcode":"L4M 2T2",
    "sg:province":"ON",
    "sg:tags":[
        "department"
    ],
    "wof:name":"Ontario Provincial Police",
    "wof:placetype":"venue"
},
  "geometry": {"coordinates":[-79.695198,44.4007],"type":"Point"}
}