{
  "type": "Feature",
  "properties": {
    "addr:full":"674 College St Toronto ON M6G 1B8",
    "addr:housenumber":"674",
    "addr:postcode":"m6g 1b8",
    "addr:street":"College St",
    "iso:country":"CA",
    "sg:address":"674 College St",
    "sg:city":"Toronto",
    "sg:classifiers":[
        {
            "category":"Retail",
            "subcategory":"Laundry & Dry Cleaning",
            "type":"Services"
        }
    ],
    "sg:phone":"+1 416 532 7919",
    "sg:postcode":"M6G 1B8",
    "sg:province":"ON",
    "sg:tags":[
        "cleaners"
    ],
    "wof:name":"People's Dry Cleaners",
    "wof:placetype":"venue"
},
  "geometry": {"coordinates":[-79.416847,43.655216],"type":"Point"}
}