{
  "type": "Feature",
  "properties": {
    "iso:country":"CA",
    "sg:city":"Dieppe",
    "sg:classifiers":[
        {
            "category":"Organizations",
            "subcategory":"Religious Organization",
            "type":"Services"
        }
    ],
    "sg:phone":"+1 506 857 1094",
    "sg:postcode":"E1A 1T1",
    "sg:province":"NB",
    "sg:tags":[
        "church"
    ],
    "wof:name":"Paroisse Ste-Therese",
    "wof:placetype":"venue"
},
  "geometry": {"coordinates":[-64.7526092529,46.0963554382],"type":"Point"}
}