{
  "type": "Feature",
  "properties": {
    "addr:full":"Brampton ON L6W 3X4",
    "addr:postcode":"l6w 3x4",
    "iso:country":"CA",
    "sg:city":"Brampton",
    "sg:classifiers":[
        {
            "category":"Health Services",
            "subcategory":"Doctor",
            "type":"Services"
        }
    ],
    "sg:phone":"+1 905 457 7566",
    "sg:postcode":"L6W 3X4",
    "sg:province":"ON",
    "sg:tags":[
        "physician",
        "surgeon"
    ],
    "wof:name":"Queen Lynch Family Physicians",
    "wof:placetype":"venue"
},
  "geometry": {"coordinates":[-79.753258,43.692039],"type":"Point"}
}