{
  "type": "Feature",
  "properties": {
    "iso:country":"CA",
    "sg:address":"1326 Av Greene",
    "sg:city":"Westmount",
    "sg:classifiers":[
        {
            "category":"Banks & Credit Unions",
            "subcategory":"Bank",
            "type":"Services"
        }
    ],
    "sg:phone":"+1 514 499 5622",
    "sg:postcode":"H3Z 2B1",
    "sg:province":"QC",
    "wof:name":"Banquescotia",
    "wof:placetype":"venue"
},
  "geometry": {"coordinates":[-73.590332,45.487087],"type":"Point"}
}