{
  "type": "Feature",
  "properties": {
    "iso:country":"CA",
    "sg:city":"Glendon",
    "sg:classifiers":[
        {
            "category":"Organizations",
            "subcategory":"Religious Organization",
            "type":"Services"
        }
    ],
    "sg:phone":"+1 780 635 3848",
    "sg:postcode":"T0A 1P0",
    "sg:province":"AB",
    "sg:tags":[
        "church"
    ],
    "wof:name":"Glendon Community Church",
    "wof:placetype":"venue"
},
  "geometry": {"coordinates":[-111.153831482,54.2471961975],"type":"Point"}
}