{
  "type": "Feature",
  "properties": {
    "addr:full":"9353 Mary St Chilliwack BC V2P 4G9",
    "addr:housenumber":"9353",
    "addr:postcode":"v2p 4g9",
    "addr:street":"Mary St",
    "iso:country":"CA",
    "sg:address":"9353 Mary St",
    "sg:city":"Chilliwack",
    "sg:classifiers":[
        {
            "category":"Social Services",
            "type":"Services"
        }
    ],
    "sg:phone":"+1 604 792 7726",
    "sg:postcode":"V2P 4G9",
    "sg:province":"BC",
    "sg:tags":[
        "organization",
        "welfare"
    ],
    "wof:name":"Chilliwack Society Cmmnty Lvng",
    "wof:placetype":"venue"
},
  "geometry": {"coordinates":[-121.957672,49.171814],"type":"Point"}
}