{
  "type": "Feature",
  "properties": {
    "addr:full":"50 Invermarge Dr Scarborough ON M1C 3M4",
    "addr:housenumber":"50",
    "addr:postcode":"m1c 3m4",
    "addr:street":"Invermarge Dr",
    "iso:country":"CA",
    "sg:address":"50 Invermarge Dr",
    "sg:city":"Scarborough",
    "sg:classifiers":[
        {
            "category":"Building & Trades",
            "subcategory":"Construction",
            "type":"Services"
        }
    ],
    "sg:phone":"+1 416 281 1232",
    "sg:postcode":"M1C 3M4",
    "sg:province":"ON",
    "sg:tags":[
        "home",
        "improvement"
    ],
    "wof:name":"Killeen Developments",
    "wof:placetype":"venue"
},
  "geometry": {"coordinates":[-79.1540603638,43.7802047729],"type":"Point"}
}