{
  "type": "Feature",
  "properties": {
    "addr:full":"5029 50th Ave St Paul AB T0A 3A0",
    "addr:housenumber":"5029",
    "addr:postcode":"t0a 3a0",
    "addr:street":"50Th Ave",
    "iso:country":"CA",
    "sg:address":"5029 50th Ave",
    "sg:city":"St Paul",
    "sg:classifiers":[
        {
            "category":"Home & Garden",
            "subcategory":"Carpets & Floor Coverings",
            "type":"Retail Goods"
        }
    ],
    "sg:phone":"+1 780 645 5788",
    "sg:postcode":"T0A 3A0",
    "sg:province":"AB",
    "sg:tags":[
        "dealer",
        "rug"
    ],
    "wof:name":"Ideal Carpets & Interiors",
    "wof:placetype":"venue"
},
  "geometry": {"coordinates":[-111.297935486,53.9912528992],"type":"Point"}
}