{
  "type": "Feature",
  "properties": {
    "addr:full":"42 Boul Desjardins E Sainte-Therese QC J7E 1C1",
    "addr:housenumber":"42",
    "addr:postcode":"j7e 1c1",
    "addr:street":"Boul Desjardins E Sainte-Therese",
    "iso:country":"CA",
    "sg:address":"42 Boul Desjardins E",
    "sg:city":"Sainte-Therese",
    "sg:classifiers":[
        {
            "category":"Health Services",
            "subcategory":"Podiatrist",
            "type":"Services"
        }
    ],
    "sg:phone":"+1 450 435 1261",
    "sg:postcode":"J7E 1C1",
    "sg:province":"QC",
    "wof:name":"Gascon, Pierre DPM",
    "wof:placetype":"venue"
},
  "geometry": {"coordinates":[-73.831345,45.634029],"type":"Point"}
}