{
  "type": "Feature",
  "properties": {
    "addr:full":"301 Montee Outaouais Rockland ON K4K 1G2",
    "addr:housenumber":"301",
    "addr:postcode":"k4k 1g2",
    "addr:street":"Montee Outaouais",
    "iso:country":"CA",
    "sg:address":"301 Montee Outaouais",
    "sg:city":"Rockland",
    "sg:classifiers":[
        {
            "category":"Recreation",
            "type":"Entertainment"
        }
    ],
    "sg:phone":"+1 613 446 4490",
    "sg:postcode":"K4K 1G2",
    "sg:province":"ON",
    "sg:tags":[
        "course",
        "golf"
    ],
    "wof:name":"Club DE Golf Outaouais",
    "wof:placetype":"venue"
},
  "geometry": {"coordinates":[-75.262817,45.550816],"type":"Point"}
}