{
  "type": "Feature",
  "properties": {
    "addr:full":"262 Avenue Rd Toronto ON M4V 2G7",
    "addr:housenumber":"262",
    "addr:postcode":"m4v 2g7",
    "addr:street":"Avenue Rd",
    "iso:country":"CA",
    "sg:address":"262 Avenue Rd",
    "sg:city":"Toronto",
    "sg:classifiers":[
        {
            "category":"Professional",
            "subcategory":"Management & Consulting",
            "type":"Services"
        }
    ],
    "sg:phone":"+1 416 968 1750",
    "sg:postcode":"M4V 2G7",
    "sg:province":"ON",
    "sg:tags":[
        "project",
        "consultant",
        "interior",
        "design",
        "decorator"
    ],
    "wof:name":"Labyrinth Project Mgmt",
    "wof:placetype":"venue"
},
  "geometry": {"coordinates":[-79.3982391357,43.6782951355],"type":"Point"}
}