{
  "type": "Feature",
  "properties": {
    "addr:full":"392 Boul Lachapelle Saint-Jerome QC J7Z 3A1",
    "addr:housenumber":"392",
    "addr:postcode":"j7z 3a1",
    "addr:street":"Boul Lachapelle Saint-Jerome",
    "iso:country":"CA",
    "sg:address":"392 Boul Lachapelle",
    "sg:city":"Saint-Jerome",
    "sg:classifiers":[
        {
            "category":"Home & Garden",
            "subcategory":"Furniture",
            "type":"Retail Goods"
        }
    ],
    "sg:phone":"+1 450 432 2008",
    "sg:postcode":"J7Z 3A1",
    "sg:province":"QC",
    "sg:tags":[
        "mattress"
    ],
    "wof:name":"Matelas Depot",
    "wof:placetype":"venue"
},
  "geometry": {"coordinates":[-73.99382,45.759369],"type":"Point"}
}