{
  "type": "Feature",
  "properties": {
    "iso:country":"CA",
    "sg:address":"166 Brock St",
    "sg:city":"Kingston",
    "sg:classifiers":[
        {
            "category":"Health Services",
            "subcategory":"Doctor",
            "type":"Services"
        }
    ],
    "sg:phone":"+1 613 544 3400",
    "sg:postcode":"K7L 5G2",
    "sg:province":"ON",
    "sg:tags":[
        "physician",
        "surgeon"
    ],
    "wof:name":"Baird, M MD",
    "wof:placetype":"venue"
},
  "geometry": {"coordinates":[-76.4857254028,44.2309799194],"type":"Point"}
}