{
  "type": "Feature",
  "properties": {
    "addr:full":"2729 48 Ave SE Calgary AB T2B 0M4",
    "addr:housenumber":"2729",
    "addr:postcode":"t2b 0m4",
    "addr:street":"48 Ave Se",
    "iso:country":"CA",
    "sg:address":"2729 48 Ave SE",
    "sg:city":"Calgary",
    "sg:classifiers":[
        {
            "category":"Manufacturing",
            "subcategory":"Metals",
            "type":"Manufacturing & Wholesale Goods"
        }
    ],
    "sg:phone":"+1 403 248 5624",
    "sg:postcode":"T2B 0M4",
    "sg:province":"AB",
    "sg:tags":[
        "steel"
    ],
    "wof:name":"Namasco Limited",
    "wof:placetype":"venue"
},
  "geometry": {"coordinates":[-113.997375488,51.0106811523],"type":"Point"}
}