{
  "type": "Feature",
  "properties": {
    "addr:full":"68 Ch Auckland Saint-Isidore-DE-Clifton QC J0B 2X0",
    "addr:housenumber":"68",
    "addr:postcode":"j0b 2x0",
    "addr:street":"Ch Auckland",
    "iso:country":"CA",
    "sg:address":"68 Ch Auckland",
    "sg:city":"Saint-Isidore-DE-Clifton",
    "sg:classifiers":[
        {
            "category":"Banks & Credit Unions",
            "subcategory":"Bank",
            "type":"Services"
        }
    ],
    "sg:phone":"+1 819 658 3756",
    "sg:postcode":"J0B 2X0",
    "sg:province":"QC",
    "wof:name":"Caisses Desjardins",
    "wof:placetype":"venue"
},
  "geometry": {"coordinates":[-71.510971,45.264568],"type":"Point"}
}