{
  "type": "Feature",
  "properties": {
    "addr:full":"690 Queen St W Brampton ON L6V 1A1",
    "addr:housenumber":"690",
    "addr:postcode":"l6v 1a1",
    "addr:street":"Queen St W",
    "iso:country":"CA",
    "sg:address":"690 Queen St W",
    "sg:city":"Brampton",
    "sg:classifiers":[
        {
            "category":"Autos & Motor Vehicles",
            "subcategory":"Automobile Sales",
            "type":"Retail Goods"
        }
    ],
    "sg:phone":"+1 905 450 0009",
    "sg:postcode":"L6V 1A1",
    "sg:province":"ON",
    "sg:tags":[
        "car",
        "dealer"
    ],
    "wof:name":"Number 9 Auto Sales Ltd",
    "wof:placetype":"venue"
},
  "geometry": {"coordinates":[-79.77597045900001,43.6716384888],"type":"Point"}
}