{
  "type": "Feature",
  "properties": {
    "iso:country":"CA",
    "sg:address":"11810 Kingsway NW",
    "sg:city":"Edmonton",
    "sg:classifiers":[
        {
            "category":"Professional",
            "subcategory":"Research",
            "type":"Services"
        }
    ],
    "sg:phone":"+1 780 413 9031",
    "sg:postcode":"T5G 0X5",
    "sg:province":"AB",
    "sg:tags":[
        "development",
        "laboratory"
    ],
    "wof:name":"Fortinek Canada Corp",
    "wof:placetype":"venue"
},
  "geometry": {"coordinates":[-113.522675,53.567543],"type":"Point"}
}