{
  "type": "Feature",
  "properties": {
    "addr:full":"640 Denison St Markham ON L3R 1C1",
    "addr:housenumber":"640",
    "addr:postcode":"l3r 1c1",
    "addr:street":"Denison St",
    "iso:country":"CA",
    "sg:address":"640 Denison St",
    "sg:city":"Markham",
    "sg:classifiers":[
        {
            "category":"Building & Trades",
            "subcategory":"Construction",
            "type":"Services"
        }
    ],
    "sg:phone":"+1 905 474 3710",
    "sg:postcode":"L3R 1C1",
    "sg:province":"ON",
    "sg:tags":[
        "fire",
        "restoration",
        "damage"
    ],
    "wof:name":"Stay Kleen Svc & Contracting",
    "wof:placetype":"venue"
},
  "geometry": {"coordinates":[-79.34014892579999,43.8244476318],"type":"Point"}
}