{
  "type": "Feature",
  "properties": {
    "addr:full":"Sault Ste Marie ON P6A 1Z4",
    "addr:postcode":"p6a 1z4",
    "iso:country":"CA",
    "sg:city":"Sault Ste Marie",
    "sg:classifiers":[
        {
            "category":"Banks & Credit Unions",
            "subcategory":"Investment Brokerage",
            "type":"Services"
        }
    ],
    "sg:phone":"+1 705 253 5700",
    "sg:postcode":"P6A 1Z4",
    "sg:province":"ON",
    "wof:name":"Edward Jones",
    "wof:placetype":"venue"
},
  "geometry": {"coordinates":[-84.33457199999999,46.512611],"type":"Point"}
}