{
  "type": "Feature",
  "properties": {
    "addr:full":"1601 Eglinton Ave W Mississauga ON L5M 7C1",
    "addr:housenumber":"1601",
    "addr:postcode":"l5m 7c1",
    "addr:street":"Eglinton Ave W",
    "iso:country":"CA",
    "sg:address":"1601 Eglinton Ave W",
    "sg:city":"Mississauga",
    "sg:classifiers":[
        {
            "category":"Social Services",
            "subcategory":"Child Care",
            "type":"Services"
        }
    ],
    "sg:phone":"+1 905 858 7860",
    "sg:postcode":"L5M 7C1",
    "sg:province":"ON",
    "wof:name":"Creditview Child Care Ctr",
    "wof:placetype":"venue"
},
  "geometry": {"coordinates":[-79.6914978027,43.5727233887],"type":"Point"}
}