{
  "type": "Feature",
  "properties": {
    "addr:full":"4517 53 St Athabasca AB T9S 1K4",
    "addr:housenumber":"4517",
    "addr:postcode":"t9s 1k4",
    "addr:street":"53 St",
    "iso:country":"CA",
    "sg:address":"4517 53 St",
    "sg:city":"Athabasca",
    "sg:classifiers":[
        {
            "category":"Health Services",
            "subcategory":"Nursing And Care Facility",
            "type":"Services"
        }
    ],
    "sg:phone":"+1 780 675 2291",
    "sg:postcode":"T9S 1K4",
    "sg:province":"AB",
    "sg:tags":[
        "home",
        "convalescent"
    ],
    "wof:name":"Extendicare/Athabasca",
    "wof:placetype":"venue"
},
  "geometry": {"coordinates":[-113.29203,54.714306],"type":"Point"}
}