{
  "type": "Feature",
  "properties": {
    "addr:full":"11909 88 St NW Edmonton AB T5B 3S2",
    "addr:housenumber":"11909",
    "addr:postcode":"t5b 3s2",
    "addr:street":"88 St Nw",
    "iso:country":"CA",
    "sg:address":"11909 88 St NW",
    "sg:city":"Edmonton",
    "sg:classifiers":[
        {
            "category":"Social Services",
            "subcategory":"Adult Care",
            "type":"Services"
        }
    ],
    "sg:phone":"+1 780 479 6232",
    "sg:postcode":"T5B 3S2",
    "sg:province":"AB",
    "sg:tags":[
        "senior",
        "housing",
        "citizen"
    ],
    "wof:name":"Avenwood Corner Sr Citizens",
    "wof:placetype":"venue"
},
  "geometry": {"coordinates":[-113.47595200000001,53.572224],"type":"Point"}
}