{
  "type": "Feature",
  "properties": {
    "addr:full":"2655 Rue Le Pelletier Beauport QC G1C 3X7",
    "addr:housenumber":"2655",
    "addr:postcode":"qc g1c 3x7",
    "addr:street":"Rue Le Pelletier",
    "iso:country":"CA",
    "sg:address":"2655 Rue Le Pelletier",
    "sg:city":"Beauport",
    "sg:classifiers":[
        {
            "category":"Organizations",
            "subcategory":"Religious Organization",
            "type":"Services"
        }
    ],
    "sg:phone":"+1 418 628 8860",
    "sg:postcode":"G1C 3X7",
    "sg:province":"QC",
    "wof:name":"Soeurs DE LA Charite DE Quebec",
    "wof:placetype":"venue"
},
  "geometry": {"coordinates":[-71.23551940919999,46.8590507507],"type":"Point"}
}