{
  "type": "Feature",
  "properties": {
    "addr:full":"Calgary AB T2B 0S8",
    "addr:postcode":"t2b 0s8",
    "iso:country":"CA",
    "sg:city":"Calgary",
    "sg:classifiers":[
        {
            "category":"Wholesale",
            "subcategory":"Meat",
            "type":"Manufacturing & Wholesale Goods"
        }
    ],
    "sg:phone":"+1 403 273 0038",
    "sg:postcode":"T2B 0S8",
    "sg:province":"AB",
    "sg:tags":[
        "product"
    ],
    "wof:name":"Leung KY Meat & Seafood Ltd",
    "wof:placetype":"venue"
},
  "geometry": {"coordinates":[-113.9897,51.037266],"type":"Point"}
}