{
  "type": "Feature",
  "properties": {
    "addr:full":"6652 Parkway Rd Greely ON K4P 1E5",
    "addr:housenumber":"6652",
    "addr:postcode":"k4p 1e5",
    "addr:street":"Parkway Rd",
    "iso:country":"CA",
    "sg:address":"6652 Parkway Rd",
    "sg:city":"Greely",
    "sg:classifiers":[
        {
            "category":"Retail",
            "subcategory":"Auto Repair",
            "type":"Services"
        }
    ],
    "sg:phone":"+1 613 821 1783",
    "sg:postcode":"K4P 1E5",
    "sg:province":"ON",
    "sg:tags":[
        "body",
        "automobile",
        "painting"
    ],
    "wof:name":"Ed Zuger Auto Body",
    "wof:placetype":"venue"
},
  "geometry": {"coordinates":[-75.5862731934,45.2513504028],"type":"Point"}
}