{
  "type": "Feature",
  "properties": {
    "addr:full":"2126 Rama Rd Campbell River BC V9W 6B1",
    "addr:housenumber":"2126",
    "addr:postcode":"v9w 6b1",
    "addr:street":"Rama Rd",
    "iso:country":"CA",
    "sg:address":"2126 Rama Rd",
    "sg:city":"Campbell River",
    "sg:classifiers":[
        {
            "category":"Building & Trades",
            "subcategory":"Cleaning & Sanitation",
            "type":"Services"
        }
    ],
    "sg:phone":"+1 250 286 6621",
    "sg:postcode":"V9W 6B1",
    "sg:province":"BC",
    "sg:tags":[
        "janitor"
    ],
    "wof:name":"Ideal Janitorial Svc",
    "wof:placetype":"venue"
},
  "geometry": {"coordinates":[-125.2771,50.043312],"type":"Point"}
}