{
  "type": "Feature",
  "properties": {
    "addr:full":"1416 Route 101 Nasonworth NB E3C 2C9",
    "addr:housenumber":"1416",
    "addr:postcode":"e3c 2c9",
    "addr:street":"Route 101",
    "iso:country":"CA",
    "sg:address":"1416 Route 101",
    "sg:city":"Nasonworth",
    "sg:classifiers":[
        {
            "category":"Building & Trades",
            "subcategory":"Plumbing",
            "type":"Services"
        }
    ],
    "sg:phone":"+1 506 454 2028",
    "sg:postcode":"E3C 2C9",
    "sg:province":"NB",
    "sg:tags":[
        "contractor"
    ],
    "wof:name":"Flower's Plumbing",
    "wof:placetype":"venue"
},
  "geometry": {"coordinates":[-66.67807000000001,45.838051],"type":"Point"}
}