{
  "type": "Feature",
  "properties": {
    "addr:full":"5146 80 Ave SE Calgary AB T2C 2X3",
    "addr:housenumber":"5146",
    "addr:postcode":"t2c 2x3",
    "addr:street":"80 Ave Se",
    "iso:country":"CA",
    "sg:address":"5146 80 Ave SE",
    "sg:city":"Calgary",
    "sg:classifiers":[
        {
            "category":"Manufacturing",
            "subcategory":"Apparel",
            "type":"Manufacturing & Wholesale Goods"
        }
    ],
    "sg:phone":"+1 403 277 0100",
    "sg:postcode":"T2C 2X3",
    "sg:province":"AB",
    "sg:tags":[
        "tarpaulin"
    ],
    "wof:name":"Horizon Tarps & Repair",
    "wof:placetype":"venue"
},
  "geometry": {"coordinates":[-113.960166931,50.9805603027],"type":"Point"}
}