{
  "type": "Feature",
  "properties": {
    "addr:full":"4 Slemon Park Dr Slemon Park PE C0B 2A0",
    "addr:housenumber":"4",
    "addr:postcode":"c0b 2a0",
    "addr:street":"Slemon Park Dr",
    "iso:country":"CA",
    "sg:address":"4 Slemon Park Dr",
    "sg:city":"Slemon Park",
    "sg:classifiers":[
        {
            "category":"Manufacturing",
            "subcategory":"Food",
            "type":"Manufacturing & Wholesale Goods"
        }
    ],
    "sg:phone":"+1 902 888 5160",
    "sg:postcode":"C0B 2A0",
    "sg:province":"PE",
    "sg:tags":[
        "chips"
    ],
    "wof:name":"Humpty Dumpty Snack Foods Inc",
    "wof:placetype":"venue"
},
  "geometry": {"coordinates":[-63.82793,46.434826],"type":"Point"}
}