{
  "type": "Feature",
  "properties": {
    "iso:country":"CA",
    "sg:address":"3315 Boul Des Entreprises",
    "sg:city":"Terrebonne",
    "sg:classifiers":[
        {
            "category":"Manufacturing",
            "subcategory":"Tools & Machinery",
            "type":"Manufacturing & Wholesale Goods"
        }
    ],
    "sg:phone":"+1 450 968 2131",
    "sg:postcode":"J6X 4J9",
    "sg:province":"QC",
    "sg:tags":[
        "ventilating",
        "plate",
        "tin"
    ],
    "wof:name":"Ferblanterie Jgl Inc",
    "wof:placetype":"venue"
},
  "geometry": {"coordinates":[-73.6881942749,45.7252502441],"type":"Point"}
}