{
  "type": "Feature",
  "properties": {
    "addr:full":"2081 Rue DE LA Montagne Montreal QC H3G 1Z8",
    "addr:housenumber":"2081",
    "addr:postcode":"h3g 1z8",
    "addr:street":"Rue De La Montagne",
    "iso:country":"CA",
    "sg:address":"2081 Rue DE LA Montagne",
    "sg:city":"Montreal",
    "sg:classifiers":[
        {
            "category":"Shopping",
            "subcategory":"Clothing, Apparel, & Fashions",
            "type":"Retail Goods"
        }
    ],
    "sg:phone":"+1 514 281 5547",
    "sg:postcode":"H3G 1Z8",
    "sg:province":"QC",
    "wof:name":"Marie Saint Pierre Boutique",
    "wof:placetype":"venue"
},
  "geometry": {"coordinates":[-73.577324,45.499187],"type":"Point"}
}