{
  "type": "Feature",
  "properties": {
    "addr:full":"12278 Hwy 41 Northbrook ON K0H 2G0",
    "addr:housenumber":"12278",
    "addr:postcode":"k0h 2g0",
    "addr:street":"Hwy 41",
    "iso:country":"CA",
    "sg:address":"12278 Hwy 41",
    "sg:city":"Northbrook",
    "sg:classifiers":[
        {
            "category":"Building & Trades",
            "subcategory":"Construction",
            "type":"Services"
        }
    ],
    "sg:phone":"+1 613 336 2345",
    "sg:postcode":"K0H 2G0",
    "sg:province":"ON",
    "sg:tags":[
        "excavating",
        "contractor"
    ],
    "wof:name":"Kaladar Northern Construction",
    "wof:placetype":"venue"
},
  "geometry": {"coordinates":[-77.1590881348,44.7334365845],"type":"Point"}
}