{
  "type": "Feature",
  "properties": {
    "addr:full":"657 Lock St W Dunnville ON N1A 1V9",
    "addr:housenumber":"657",
    "addr:postcode":"n1a 1v9",
    "addr:street":"Lock St W",
    "iso:country":"CA",
    "sg:address":"657 Lock St W",
    "sg:city":"Dunnville",
    "sg:classifiers":[
        {
            "category":"Health Services",
            "subcategory":"Nursing And Care Facility",
            "type":"Services"
        }
    ],
    "sg:phone":"+1 905 774 7547",
    "sg:postcode":"N1A 1V9",
    "sg:province":"ON",
    "sg:tags":[
        "home",
        "convalescent",
        "government"
    ],
    "wof:name":"Grandview Lodge",
    "wof:placetype":"venue"
},
  "geometry": {"coordinates":[-79.63170599999999,42.907597],"type":"Point"}
}