{
  "type": "Feature",
  "properties": {
    "addr:full":"2201 4th Ave W Vancouver BC V6K 1N9",
    "addr:housenumber":"2201",
    "addr:postcode":"v6k 1n9",
    "addr:street":"4Th Ave W",
    "iso:country":"CA",
    "sg:address":"2201 4th Ave W",
    "sg:city":"Vancouver",
    "sg:classifiers":[
        {
            "category":"Shopping",
            "subcategory":"Bicycles & Sporting Goods",
            "type":"Retail Goods"
        }
    ],
    "sg:phone":"+1 604 731 6181",
    "sg:postcode":"V6K 1N9",
    "sg:province":"BC",
    "wof:name":"Coast Mountain Sports",
    "wof:placetype":"venue"
},
  "geometry": {"coordinates":[-123.155342,49.268368],"type":"Point"}
}