{
  "type": "Feature",
  "properties": {
    "addr:full":"262 Lorne St Kamloops BC V2C 1W1",
    "addr:housenumber":"262",
    "addr:postcode":"bc v2c 1w1",
    "addr:street":"Lorne St",
    "iso:country":"CA",
    "sg:address":"262 Lorne St",
    "sg:city":"Kamloops",
    "sg:classifiers":[
        {
            "category":"Museum",
            "type":"Entertainment"
        }
    ],
    "sg:phone":"+1 250 372 7323",
    "sg:postcode":"V2C 1W1",
    "sg:province":"BC",
    "sg:tags":[
        "organization",
        "arts",
        "information"
    ],
    "wof:name":"Community Art Council-Kamloops",
    "wof:placetype":"venue"
},
  "geometry": {"coordinates":[-120.335442,50.678116],"type":"Point"}
}