{
  "type": "Feature",
  "properties": {
    "addr:full":"119 Veats Ave Hinton AB T7V 1S8",
    "addr:housenumber":"119",
    "addr:postcode":"t7v 1s8",
    "addr:street":"Veats Ave",
    "iso:country":"CA",
    "sg:address":"119 Veats Ave",
    "sg:city":"Hinton",
    "sg:classifiers":[
        {
            "category":"Manufacturing",
            "subcategory":"Signs",
            "type":"Manufacturing & Wholesale Goods"
        }
    ],
    "sg:phone":"+1 780 865 7446",
    "sg:postcode":"T7V 1S8",
    "sg:province":"AB",
    "wof:name":"Rhythm Graphix & Signs",
    "wof:placetype":"venue"
},
  "geometry": {"coordinates":[-117.605171204,53.3954353333],"type":"Point"}
}