{
  "type": "Feature",
  "properties": {
    "addr:full":"Laval QC H7T 2P5",
    "addr:postcode":"h7t 2p5",
    "iso:country":"CA",
    "sg:city":"Laval",
    "sg:classifiers":[
        {
            "category":"Wholesale",
            "subcategory":"Drugs",
            "type":"Manufacturing & Wholesale Goods"
        }
    ],
    "sg:phone":"+1 450 687 1616",
    "sg:postcode":"H7T 2P5",
    "sg:province":"QC",
    "sg:tags":[
        "pharmaceutical",
        "product"
    ],
    "wof:name":"Glaxo Smith Kline",
    "wof:placetype":"venue"
},
  "geometry": {"coordinates":[-73.749191,45.568504],"type":"Point"}
}