{
  "type": "Feature",
  "properties": {
    "addr:full":"Calgary AB T2P 2V7",
    "addr:postcode":"t2p 2v7",
    "iso:country":"CA",
    "sg:city":"Calgary",
    "sg:classifiers":[
        {
            "category":"Shopping",
            "subcategory":"Jewelry",
            "type":"Retail Goods"
        }
    ],
    "sg:phone":"+1 403 234 0888",
    "sg:postcode":"T2P 2V7",
    "sg:province":"AB",
    "sg:tags":[
        "jeweler"
    ],
    "wof:name":"Bow Valley Jewellers",
    "wof:placetype":"venue"
},
  "geometry": {"coordinates":[-114.065575,51.048267],"type":"Point"}
}