{
  "type": "Feature",
  "properties": {
    "iso:country":"CA",
    "sg:city":"Salaberry-DE-Valleyfield",
    "sg:classifiers":[
        {
            "category":"Organizations",
            "subcategory":"Professional Association",
            "type":"Services"
        }
    ],
    "sg:phone":"+1 450 373 8789",
    "sg:postcode":"J6T 1M1",
    "sg:province":"QC",
    "wof:name":"Chambre DE Commerce Region",
    "wof:placetype":"venue"
},
  "geometry": {"coordinates":[-74.133232,45.255623],"type":"Point"}
}