{
  "type": "Feature",
  "properties": {
    "addr:full":"120 Larch St Sudbury ON P3E 1C2",
    "addr:housenumber":"120",
    "addr:postcode":"p3e 1c2",
    "addr:street":"Larch St",
    "iso:country":"CA",
    "sg:address":"120 Larch St",
    "sg:city":"Sudbury",
    "sg:classifiers":[
        {
            "category":"Insurance",
            "subcategory":"Insurance Agent",
            "type":"Services"
        }
    ],
    "sg:phone":"+1 705 675 2241",
    "sg:postcode":"P3E 1C2",
    "sg:province":"ON",
    "wof:name":"R L Gougeon Insurance",
    "wof:placetype":"venue"
},
  "geometry": {"coordinates":[-80.99221799999999,46.491554],"type":"Point"}
}