{
  "type": "Feature",
  "properties": {
    "addr:full":"4929 Malden Rd Windsor ON N9E 3T7",
    "addr:housenumber":"4929",
    "addr:postcode":"n9e 3t7",
    "addr:street":"Malden Rd",
    "iso:country":"CA",
    "sg:address":"4929 Malden Rd",
    "sg:city":"Windsor",
    "sg:classifiers":[
        {
            "category":"Education",
            "subcategory":"Special Training",
            "type":"Public Place"
        }
    ],
    "sg:phone":"+1 519 974 9797",
    "sg:postcode":"N9E 3T7",
    "sg:province":"ON",
    "sg:tags":[
        "instruction",
        "driving"
    ],
    "wof:name":"Windsor School of Motoring",
    "wof:placetype":"venue"
},
  "geometry": {"coordinates":[-83.05956999999999,42.265656],"type":"Point"}
}