{
  "type": "Feature",
  "properties": {
    "addr:full":"Cp 563 Succ Beaconsfield Beaconsfield QC H9W 5V2",
    "addr:postcode":"h9w 5v2",
    "addr:street":"Succ Beaconsfield",
    "iso:country":"CA",
    "sg:address":"Cp 563 Succ Beaconsfield",
    "sg:city":"Beaconsfield",
    "sg:classifiers":[
        {
            "category":"Professional",
            "subcategory":"Business Services",
            "type":"Services"
        }
    ],
    "sg:phone":"+1 514 694 9682",
    "sg:postcode":"H9W 5V2",
    "sg:province":"QC",
    "wof:name":"Disques Diva Inc",
    "wof:placetype":"venue"
},
  "geometry": {"coordinates":[-73.864616,45.424759],"type":"Point"}
}