{
  "type": "Feature",
  "properties": {
    "addr:full":"151 Boul Maloney E Gatineau QC J8P 1B9",
    "addr:housenumber":"151",
    "addr:postcode":"j8p 1b9",
    "addr:street":"Boul Maloney E",
    "iso:country":"CA",
    "sg:address":"151 Boul Maloney E",
    "sg:city":"Gatineau",
    "sg:classifiers":[
        {
            "category":"Food & Beverages",
            "subcategory":"Groceries & Convenience Stores",
            "type":"Retail Goods"
        }
    ],
    "sg:phone":"+1 819 663 9647",
    "sg:postcode":"J8P 1B9",
    "sg:province":"QC",
    "wof:name":"Quickie Convenience Stores",
    "wof:placetype":"venue"
},
  "geometry": {"coordinates":[-75.65013885499999,45.4839859009],"type":"Point"}
}