{
  "type": "Feature",
  "properties": {
    "addr:full":"PO Box 174 Weymouth NS B0W 3T0",
    "addr:housenumber":"po;174",
    "addr:postcode":"b0w 3t0",
    "addr:street":"Box",
    "iso:country":"CA",
    "sg:address":"PO Box 174",
    "sg:city":"Weymouth",
    "sg:classifiers":[
        {
            "category":"Social Services",
            "type":"Services"
        }
    ],
    "sg:phone":"+1 902 837 5592",
    "sg:postcode":"B0W 3T0",
    "sg:province":"NS",
    "sg:tags":[
        "organization",
        "welfare"
    ],
    "wof:name":"Weymouth New Horizons",
    "wof:placetype":"venue"
},
  "geometry": {"coordinates":[-66.00505065919999,44.4054450989],"type":"Point"}
}