{
  "type": "Feature",
  "properties": {
    "addr:full":"Saskatoon SK S7H 0T8",
    "addr:postcode":"s7h 0t8",
    "iso:country":"CA",
    "sg:city":"Saskatoon",
    "sg:classifiers":[
        {
            "category":"Sports & Exercise",
            "subcategory":"Gym",
            "type":"Entertainment"
        }
    ],
    "sg:phone":"+1 306 933 1959",
    "sg:postcode":"S7H 0T8",
    "sg:province":"SK",
    "sg:tags":[
        "club",
        "health",
        "studio",
        "gymnasium"
    ],
    "wof:name":"Iron Works Gym Inc",
    "wof:placetype":"venue"
},
  "geometry": {"coordinates":[-106.62412261999999,52.115032196],"type":"Point"}
}