{
  "type": "Feature",
  "properties": {
    "addr:full":"126 Bellamy Rd N Scarborough ON M1J 2L1",
    "addr:housenumber":"126",
    "addr:postcode":"m1j 2l1",
    "addr:street":"Bellamy Rd N",
    "iso:country":"CA",
    "sg:address":"126 Bellamy Rd N",
    "sg:city":"Scarborough",
    "sg:classifiers":[
        {
            "category":"Shopping",
            "subcategory":"Discount & Variety Stores",
            "type":"Retail Goods"
        }
    ],
    "sg:phone":"+1 416 439 9455",
    "sg:postcode":"M1J 2L1",
    "sg:province":"ON",
    "wof:name":"Kim's Tuck Shop",
    "wof:placetype":"venue"
},
  "geometry": {"coordinates":[-79.231964,43.741882],"type":"Point"}
}