{
  "type": "Feature",
  "properties": {
    "addr:full":"4103B Centre St NW # 100 Calgary AB T2E 2Y6",
    "addr:housenumber":"4103b",
    "addr:postcode":"t2e 2y6",
    "addr:street":"Centre St Nw # 100",
    "iso:country":"CA",
    "sg:address":"4103B Centre St NW # 100",
    "sg:city":"Calgary",
    "sg:classifiers":[
        {
            "category":"Professional",
            "subcategory":"Lawyer & Legal Services",
            "type":"Services"
        }
    ],
    "sg:phone":"+1 403 289 3131",
    "sg:postcode":"T2E 2Y6",
    "sg:province":"AB",
    "sg:tags":[
        "attorney"
    ],
    "wof:name":"Riccio & CO",
    "wof:placetype":"venue"
},
  "geometry": {"coordinates":[-114.06259900000001,51.088863],"type":"Point"}
}