{
  "type": "Feature",
  "properties": {
    "addr:full":"19 St Joseph St Gracefield QC J0X 1W0",
    "addr:housenumber":"19",
    "addr:postcode":"j0x 1w0",
    "addr:street":"St Joseph St",
    "iso:country":"CA",
    "sg:address":"19 St Joseph St",
    "sg:city":"Gracefield",
    "sg:classifiers":[
        {
            "category":"Restaurant",
            "type":"Food & Drink"
        }
    ],
    "sg:phone":"+1 819 463 3876",
    "sg:postcode":"J0X 1W0",
    "sg:province":"QC",
    "wof:name":"Casse-Croute Haute-Gatineau",
    "wof:placetype":"venue"
},
  "geometry": {"coordinates":[-76.05825042719999,46.083820343],"type":"Point"}
}