{
  "type": "Feature",
  "properties": {
    "iso:country":"CA",
    "sg:city":"Burnaby",
    "sg:classifiers":[
        {
            "category":"Manufacturing",
            "subcategory":"Printing",
            "type":"Manufacturing & Wholesale Goods"
        }
    ],
    "sg:phone":"+1 604 420 6034",
    "sg:postcode":"V3N 4R7",
    "sg:province":"BC",
    "sg:tags":[
        "newspaper"
    ],
    "wof:name":"Korea Central Daily",
    "wof:placetype":"venue"
},
  "geometry": {"coordinates":[-122.892814636,49.2442359924],"type":"Point"}
}