{
  "type": "Feature",
  "properties": {
    "addr:full":"Charlottetown PE C1A 4W8",
    "addr:postcode":"c1a 4w8",
    "iso:country":"CA",
    "sg:city":"Charlottetown",
    "sg:classifiers":[
        {
            "category":"Shopping",
            "subcategory":"Books",
            "type":"Retail Goods"
        }
    ],
    "sg:phone":"+1 902 566 5309",
    "sg:postcode":"C1A 4W8",
    "sg:province":"PE",
    "sg:tags":[
        "dealer"
    ],
    "wof:name":"Maritime Christian Bookstore",
    "wof:placetype":"venue"
},
  "geometry": {"coordinates":[-63.124825,46.238121],"type":"Point"}
}