{
  "type": "Feature",
  "properties": {
    "addr:full":"112 Boul Begin Sainte-Claire QC G0R 2V0",
    "addr:housenumber":"112",
    "addr:postcode":"g0r 2v0",
    "addr:street":"Boul Begin",
    "iso:country":"CA",
    "sg:address":"112 Boul Begin",
    "sg:city":"Sainte-Claire",
    "sg:classifiers":[
        {
            "category":"Food & Beverages",
            "subcategory":"Groceries & Convenience Stores",
            "type":"Retail Goods"
        }
    ],
    "sg:phone":"+1 418 883 3906",
    "sg:postcode":"G0R 2V0",
    "sg:province":"QC",
    "sg:tags":[
        "grocer"
    ],
    "wof:name":"Alimentation Roy",
    "wof:placetype":"venue"
},
  "geometry": {"coordinates":[-70.86449399999999,46.600952],"type":"Point"}
}