{
  "type": "Feature",
  "properties": {
    "addr:full":"St. John's NL A1A 4L6",
    "addr:postcode":"a1a 4l6",
    "iso:country":"CA",
    "sg:city":"St. John's",
    "sg:classifiers":[
        {
            "category":"Retail",
            "subcategory":"Veterinary Services",
            "type":"Services"
        }
    ],
    "sg:phone":"+1 709 753 0506",
    "sg:postcode":"A1A 4L6",
    "sg:province":"NL",
    "sg:tags":[
        "veterinarian"
    ],
    "wof:name":"Dezeeuw, H DVM",
    "wof:placetype":"venue"
},
  "geometry": {"coordinates":[-52.704967,47.581783],"type":"Point"}
}