{
  "type": "Feature",
  "properties": {
    "addr:full":"St Peters Canal St Peters NS B0E 3B0",
    "addr:postcode":"b0e 3b0",
    "addr:street":"Canal",
    "iso:country":"CA",
    "sg:address":"St Peters Canal",
    "sg:city":"St Peters",
    "sg:classifiers":[
        {
            "category":"Government",
            "subcategory":"Office",
            "type":"Public Place"
        }
    ],
    "sg:phone":"+1 902 535 2118",
    "sg:postcode":"B0E 3B0",
    "sg:province":"NS",
    "wof:name":"Canada Fortress of Louisbourg",
    "wof:placetype":"venue"
},
  "geometry": {"coordinates":[-63.587551,44.727379],"type":"Point"}
}