{
  "type": "Feature",
  "properties": {
    "addr:full":"5212 Rue Hurteau Contrecoeur QC J0L 1C0",
    "addr:housenumber":"5212",
    "addr:postcode":"j0l 1c0",
    "addr:street":"Rue Hurteau",
    "iso:country":"CA",
    "sg:address":"5212 Rue Hurteau",
    "sg:city":"Contrecoeur",
    "sg:classifiers":[
        {
            "category":"Health Services",
            "subcategory":"Doctor",
            "type":"Services"
        }
    ],
    "sg:phone":"+1 450 587 2744",
    "sg:postcode":"J0L 1C0",
    "sg:province":"QC",
    "sg:tags":[
        "dentist"
    ],
    "wof:name":"Clinique Dentaire Louise",
    "wof:placetype":"venue"
},
  "geometry": {"coordinates":[-73.232208,45.858551],"type":"Point"}
}