{
  "type": "Feature",
  "properties": {
    "addr:full":"Whitehorse YT Y1A 7A2",
    "addr:postcode":"y1a 7a2",
    "iso:country":"CA",
    "sg:city":"Whitehorse",
    "sg:classifiers":[
        {
            "category":"Retail",
            "subcategory":"Auto Repair",
            "type":"Services"
        }
    ],
    "sg:phone":"+1 867 393 3376",
    "sg:postcode":"Y1A 7A2",
    "sg:province":"YT",
    "sg:tags":[
        "repairing",
        "automobile"
    ],
    "wof:name":"Takhini Gas Ltd",
    "wof:placetype":"venue"
},
  "geometry": {"coordinates":[-135.05316162099999,60.7208709717],"type":"Point"}
}