{
  "type": "Feature",
  "properties": {
    "addr:full":"Lower Sackville NS B4C 4E9",
    "addr:postcode":"b4c 4e9",
    "iso:country":"CA",
    "sg:city":"Lower Sackville",
    "sg:classifiers":[
        {
            "category":"Home & Garden",
            "subcategory":"Furniture",
            "type":"Retail Goods"
        }
    ],
    "sg:phone":"+1 902 864 6088",
    "sg:postcode":"B4C 4E9",
    "sg:province":"NS",
    "sg:tags":[
        "equipment",
        "kitchen",
        "cabinet"
    ],
    "wof:name":"Traditional Cabinetry & Wood",
    "wof:placetype":"venue"
},
  "geometry": {"coordinates":[-63.648632,44.765377],"type":"Point"}
}