{
  "type": "Feature",
  "properties": {
    "addr:full":"2303 41st Ave W Vancouver BC V6M 2A3",
    "addr:housenumber":"2303",
    "addr:postcode":"v6m 2a3",
    "addr:street":"41St Ave W",
    "iso:country":"CA",
    "sg:address":"2303 41st Ave W",
    "sg:city":"Vancouver",
    "sg:classifiers":[
        {
            "category":"Mining & Drilling",
            "type":"Manufacturing & Wholesale Goods"
        }
    ],
    "sg:phone":"+1 604 688 0041",
    "sg:postcode":"V6M 2A3",
    "sg:province":"BC",
    "sg:tags":[
        "company"
    ],
    "wof:name":"Pacific North West Capital",
    "wof:placetype":"venue"
},
  "geometry": {"coordinates":[-123.159690857,49.2347068787],"type":"Point"}
}