{
  "type": "Feature",
  "properties": {
    "addr:full":"2666 Ulverston Ave Cumberland BC V0R 1S0",
    "addr:postcode":"2666;v0r 1s0",
    "addr:street":"Ulverston Ave",
    "iso:country":"CA",
    "sg:address":"2666 Ulverston Ave",
    "sg:city":"Cumberland",
    "sg:classifiers":[
        {
            "category":"Health Services",
            "subcategory":"Doctor",
            "type":"Services"
        }
    ],
    "sg:phone":"+1 250 336 2221",
    "sg:postcode":"V0R 1S0",
    "sg:province":"BC",
    "sg:tags":[
        "physician",
        "surgeon"
    ],
    "wof:name":"Mc Laughlin, Janice MD",
    "wof:placetype":"venue"
},
  "geometry": {"coordinates":[-125.03842163100001,49.6216583252],"type":"Point"}
}