{
  "type": "Feature",
  "properties": {
    "addr:full":"Castlegar BC V1N 3Z1",
    "addr:postcode":"v1n 3z1",
    "iso:country":"CA",
    "sg:city":"Castlegar",
    "sg:classifiers":[
        {
            "category":"Professional",
            "type":"Services"
        }
    ],
    "sg:phone":"+1 250 304 2251",
    "sg:postcode":"V1N 3Z1",
    "sg:province":"BC",
    "sg:tags":[
        "equipment",
        "hydroponics",
        "supply"
    ],
    "wof:name":"Light Years Garden Supply Ltd",
    "wof:placetype":"venue"
},
  "geometry": {"coordinates":[-117.65418243400001,49.2962493896],"type":"Point"}
}