{
  "type": "Feature",
  "properties": {
    "addr:full":"4497 Boul Westpark Pierrefonds QC H9A 2X8",
    "addr:housenumber":"4497",
    "addr:postcode":"h9a 2x8",
    "addr:street":"Boul Westpark",
    "iso:country":"CA",
    "sg:address":"4497 Boul Westpark",
    "sg:city":"Pierrefonds",
    "sg:classifiers":[
        {
            "category":"Social Services",
            "subcategory":"Child Care",
            "type":"Services"
        }
    ],
    "sg:phone":"+1 514 683 2811",
    "sg:postcode":"H9A 2X8",
    "sg:province":"QC",
    "sg:tags":[
        "kindergarten",
        "academic",
        "amusement"
    ],
    "wof:name":"Ethan's Playground",
    "wof:placetype":"venue"
},
  "geometry": {"coordinates":[-73.82814,45.502945],"type":"Point"}
}