{
  "type": "Feature",
  "properties": {
    "addr:full":"Sainte-Foy QC G1V 1Y4",
    "addr:postcode":"g1v 1y4",
    "iso:country":"CA",
    "sg:city":"Sainte-Foy",
    "sg:classifiers":[
        {
            "category":"Real Estate",
            "subcategory":"Architect",
            "type":"Services"
        }
    ],
    "sg:phone":"+1 418 651 0220",
    "sg:postcode":"G1V 1Y4",
    "sg:province":"QC",
    "sg:tags":[
        "general",
        "contractor"
    ],
    "wof:name":"Yvan Blouin Construction Inc",
    "wof:placetype":"venue"
},
  "geometry": {"coordinates":[-71.3011169434,46.7734260559],"type":"Point"}
}