{
  "type": "Feature",
  "properties": {
    "addr:full":"Montreal QC H2J 3J2",
    "addr:postcode":"h2j 3j2",
    "iso:country":"CA",
    "sg:city":"Montreal",
    "sg:classifiers":[
        {
            "category":"Shopping",
            "subcategory":"Books",
            "type":"Retail Goods"
        }
    ],
    "sg:phone":"+1 514 522 8848",
    "sg:postcode":"H2J 3J2",
    "sg:province":"QC",
    "sg:tags":[
        "dealer"
    ],
    "wof:name":"Librairie Bonheur D'Occasion",
    "wof:placetype":"venue"
},
  "geometry": {"coordinates":[-73.5779953003,45.5286750793],"type":"Point"}
}