{
  "type": "Feature",
  "properties": {
    "addr:full":"Scarborough ON M1P 4Z8",
    "addr:postcode":"m1p 4z8",
    "iso:country":"CA",
    "sg:city":"Scarborough",
    "sg:classifiers":[
        {
            "category":"Government",
            "subcategory":"Office",
            "type":"Public Place"
        }
    ],
    "sg:phone":"+1 416 752 2358",
    "sg:postcode":"M1P 4Z8",
    "sg:province":"ON",
    "wof:name":"Canada Members of Parliament",
    "wof:placetype":"venue"
},
  "geometry": {"coordinates":[-79.265625,43.7526664734],"type":"Point"}
}