{
  "type": "Feature",
  "properties": {
    "addr:full":"1130 Rue DE LA Gauchetiere E Montreal QC H2L 2N7",
    "addr:housenumber":"1130",
    "addr:postcode":"h2l 2n7",
    "addr:street":"Rue De La Gauchetiere E",
    "iso:country":"CA",
    "sg:address":"1130 Rue DE LA Gauchetiere E",
    "sg:city":"Montreal",
    "sg:classifiers":[
        {
            "category":"Bars & Pubs",
            "type":"Food & Drink"
        }
    ],
    "sg:phone":"+1 514 525 9038",
    "sg:postcode":"H2L 2N7",
    "sg:province":"QC",
    "wof:name":"Brasserie LA Mere Clavet",
    "wof:placetype":"venue"
},
  "geometry": {"coordinates":[-73.553101,45.515915],"type":"Point"}
}