{
  "type": "Feature",
  "properties": {
    "addr:full":"Braeside Rd Vanderhoof BC V0J 3A0",
    "addr:postcode":"v0j 3a0",
    "addr:street":"Braeside Rd",
    "iso:country":"CA",
    "sg:address":"Braeside Rd",
    "sg:city":"Vanderhoof",
    "sg:classifiers":[
        {
            "category":"Building & Trades",
            "subcategory":"Plumbing",
            "type":"Services"
        }
    ],
    "sg:phone":"+1 250 567 9604",
    "sg:postcode":"V0J 3A0",
    "sg:province":"BC",
    "sg:tags":[
        "toilet",
        "septic"
    ],
    "wof:name":"Chilco Creek Contracting",
    "wof:placetype":"venue"
},
  "geometry": {"coordinates":[-124.01409099999999,54.013081],"type":"Point"}
}