{
  "type": "Feature",
  "properties": {
    "addr:full":"202 Limit Ave Stockholm SK S0A 3Y0",
    "addr:housenumber":"202",
    "addr:postcode":"s0a 3y0",
    "addr:street":"Limit Ave",
    "iso:country":"CA",
    "sg:address":"202 Limit Ave",
    "sg:city":"Stockholm",
    "sg:classifiers":[
        {
            "category":"Government",
            "subcategory":"Office",
            "type":"Public Place"
        }
    ],
    "sg:phone":"+1 306 793 6250",
    "sg:postcode":"S0A 3Y0",
    "sg:province":"SK",
    "wof:name":"Saskatchewan Highways & Trnas",
    "wof:placetype":"venue"
},
  "geometry": {"coordinates":[-102.30262,50.6567],"type":"Point"}
}