{
  "type": "Feature",
  "properties": {
    "iso:country":"CA",
    "sg:address":"1601 Rue Albert",
    "sg:city":"Brossard",
    "sg:classifiers":[
        {
            "category":"Insurance",
            "subcategory":"Insurance Agent",
            "type":"Services"
        }
    ],
    "sg:phone":"+1 514 990 8285",
    "sg:postcode":"J4W 1Z6",
    "sg:province":"QC",
    "wof:name":"Assurance Pellerin Inc",
    "wof:placetype":"venue"
},
  "geometry": {"coordinates":[-73.47087097169999,45.4749488831],"type":"Point"}
}