{
  "type": "Feature",
  "properties": {
    "addr:full":"1073 Colborne St E Brantford ON N3T 5M1",
    "addr:housenumber":"1073",
    "addr:postcode":"n3t 5m1",
    "addr:street":"Colborne St E",
    "iso:country":"CA",
    "sg:address":"1073 Colborne St E",
    "sg:city":"Brantford",
    "sg:classifiers":[
        {
            "category":"Building & Trades",
            "subcategory":"Landscaping Services",
            "type":"Services"
        }
    ],
    "sg:phone":"+1 519 752 0400",
    "sg:postcode":"N3T 5M1",
    "sg:province":"ON",
    "sg:tags":[
        "landscape",
        "contractor"
    ],
    "wof:name":"Mclellan L Contracting CO Ltd",
    "wof:placetype":"venue"
},
  "geometry": {"coordinates":[-80.24224853520001,43.1401481628],"type":"Point"}
}