{
  "type": "Feature",
  "properties": {
    "iso:country":"CA",
    "sg:address":"24 Andover St",
    "sg:city":"Dartmouth",
    "sg:classifiers":[
        {
            "category":"Education",
            "subcategory":"School",
            "type":"Public Place"
        }
    ],
    "sg:phone":"+1 902 435 8357",
    "sg:postcode":"B2X 2L9",
    "sg:province":"NS",
    "wof:name":"Michael Wallace Elementary",
    "wof:placetype":"venue"
},
  "geometry": {"coordinates":[-63.5507278442,44.7026557922],"type":"Point"}
}