{
  "type": "Feature",
  "properties": {
    "iso:country":"CA",
    "sg:address":"219 Rue Commerciale # A",
    "sg:city":"Saint-Henri-DE-Levis",
    "sg:classifiers":[
        {
            "category":"Organizations",
            "subcategory":"Religious Organization",
            "type":"Services"
        }
    ],
    "sg:phone":"+1 418 882 2340",
    "sg:postcode":"G0R 3E0",
    "sg:province":"QC",
    "sg:tags":[
        "church"
    ],
    "wof:name":"Presbytere St-Henri",
    "wof:placetype":"venue"
},
  "geometry": {"coordinates":[-71.176940918,46.80286026],"type":"Point"}
}