{
  "type": "Feature",
  "properties": {
    "addr:full":"1255 Boul DE Perigny Chambly QC J3L 1W7",
    "addr:housenumber":"1255",
    "addr:postcode":"j3l 1w7",
    "addr:street":"Boul De Perigny",
    "iso:country":"CA",
    "sg:address":"1255 Boul DE Perigny",
    "sg:city":"Chambly",
    "sg:classifiers":[
        {
            "category":"Personal",
            "subcategory":"Barber",
            "type":"Services"
        }
    ],
    "sg:phone":"+1 450 658 0422",
    "sg:postcode":"J3L 1W7",
    "sg:province":"QC",
    "wof:name":"Salon Gaetan Denault Enrg",
    "wof:placetype":"venue"
},
  "geometry": {"coordinates":[-73.2890090942,45.4466438293],"type":"Point"}
}