{
  "type": "Feature",
  "properties": {
    "addr:full":"71 Orenda Rd Brampton ON L6W 1V8",
    "addr:housenumber":"71",
    "addr:postcode":"l6w 1v8",
    "addr:street":"Orenda Rd",
    "iso:country":"CA",
    "sg:address":"71 Orenda Rd",
    "sg:city":"Brampton",
    "sg:classifiers":[
        {
            "category":"Home & Garden",
            "subcategory":"Building Materials",
            "type":"Retail Goods"
        }
    ],
    "sg:phone":"+1 905 450 7071",
    "sg:postcode":"L6W 1V8",
    "sg:province":"ON",
    "sg:tags":[
        "roofing"
    ],
    "wof:name":"Iko Industries Ltd",
    "wof:placetype":"venue"
},
  "geometry": {"coordinates":[-79.740768,43.693417],"type":"Point"}
}