{
  "type": "Feature",
  "properties": {
    "addr:full":"47 Ontario St N # 9 Grand Bend ON N0M 1T0",
    "addr:housenumber":"47",
    "addr:postcode":"n0m 1t0",
    "addr:street":"Ontario St N # 9",
    "iso:country":"CA",
    "sg:address":"47 Ontario St N # 9",
    "sg:city":"Grand Bend",
    "sg:classifiers":[
        {
            "category":"Personal",
            "subcategory":"Beauty Salon",
            "type":"Services"
        }
    ],
    "sg:phone":"+1 519 238 1010",
    "sg:postcode":"N0M 1T0",
    "sg:province":"ON",
    "wof:name":"Accents Hair Studio",
    "wof:placetype":"venue"
},
  "geometry": {"coordinates":[-81.75483699999999,43.314831],"type":"Point"}
}