{
  "type": "Feature",
  "properties": {
    "addr:full":"357 Coxwell Ave Toronto ON M4L 3B8",
    "addr:housenumber":"357",
    "addr:postcode":"m4l 3b8",
    "addr:street":"Coxwell Ave",
    "iso:country":"CA",
    "sg:address":"357 Coxwell Ave",
    "sg:city":"Toronto",
    "sg:classifiers":[
        {
            "category":"Shopping",
            "subcategory":"Discount & Variety Stores",
            "type":"Retail Goods"
        }
    ],
    "sg:phone":"+1 416 463 3409",
    "sg:postcode":"M4L 3B8",
    "sg:province":"ON",
    "wof:name":"Coxwell Convenience",
    "wof:placetype":"venue"
},
  "geometry": {"coordinates":[-79.32017500000001,43.675537],"type":"Point"}
}