{
  "type": "Feature",
  "properties": {
    "iso:country":"CA",
    "sg:city":"North Gower",
    "sg:classifiers":[
        {
            "category":"Insurance",
            "subcategory":"Insurance Agent",
            "type":"Services"
        }
    ],
    "sg:phone":"+1 613 489 3800",
    "sg:postcode":"K0A 2T0",
    "sg:province":"ON",
    "wof:name":"S M Hill Insurance Brokers",
    "wof:placetype":"venue"
},
  "geometry": {"coordinates":[-75.715713501,45.1305427551],"type":"Point"}
}