{
  "type": "Feature",
  "properties": {
    "iso:country":"CA",
    "sg:city":"Dauphin",
    "sg:classifiers":[
        {
            "category":"Manufacturing",
            "subcategory":"Printing",
            "type":"Manufacturing & Wholesale Goods"
        }
    ],
    "sg:phone":"+1 204 638 6906",
    "sg:postcode":"R7N 1C3",
    "sg:province":"MB",
    "sg:tags":[
        "printer"
    ],
    "wof:name":"Burdeniuk's House of Printing",
    "wof:placetype":"venue"
},
  "geometry": {"coordinates":[-100.04894256599999,51.1506690979],"type":"Point"}
}