{
  "type": "Feature",
  "properties": {
    "addr:full":"1681 104th St Battleford SK S0M 0E0",
    "addr:housenumber":"1681",
    "addr:postcode":"s0m 0e0",
    "addr:street":"104Th St",
    "iso:country":"CA",
    "sg:address":"1681 104th St",
    "sg:city":"Battleford",
    "sg:classifiers":[
        {
            "category":"Building & Trades",
            "subcategory":"Construction",
            "type":"Services"
        }
    ],
    "sg:phone":"+1 306 937 2855",
    "sg:postcode":"S0M 0E0",
    "sg:province":"SK",
    "sg:tags":[
        "general",
        "contractor"
    ],
    "wof:name":"Weran Contracting",
    "wof:placetype":"venue"
},
  "geometry": {"coordinates":[-108.293282,52.782326],"type":"Point"}
}