{
  "type": "Feature",
  "properties": {
    "addr:full":"390 Rte 263 Saint-Sebastien-DE-Frontenac QC G0Y 1M0",
    "addr:housenumber":"390",
    "addr:postcode":"g0y 1m0",
    "addr:street":"Rte 263 Saint-Sebastien-De-Frontenac",
    "iso:country":"CA",
    "sg:address":"390 Rte 263",
    "sg:city":"Saint-Sebastien-DE-Frontenac",
    "sg:classifiers":[
        {
            "category":"Real Estate",
            "subcategory":"Real Estate Agent",
            "type":"Services"
        }
    ],
    "sg:phone":"+1 819 652 2266",
    "sg:postcode":"G0Y 1M0",
    "sg:province":"QC",
    "sg:tags":[
        "cooperative"
    ],
    "wof:name":"Centre Engrais Mineraux",
    "wof:placetype":"venue"
},
  "geometry": {"coordinates":[-70.8427200317,45.5727615356],"type":"Point"}
}