{
  "type": "Feature",
  "properties": {
    "addr:full":"17 White Lodge Cres Richmond Hill ON L4C 8Z8",
    "addr:housenumber":"17",
    "addr:postcode":"l4c 8z8",
    "addr:street":"White Lodge Cres",
    "iso:country":"CA",
    "sg:address":"17 White Lodge Cres",
    "sg:city":"Richmond Hill",
    "sg:classifiers":[
        {
            "category":"Professional",
            "subcategory":"Accounting & Tax Preparation",
            "type":"Services"
        }
    ],
    "sg:phone":"+1 905 884 9596",
    "sg:postcode":"L4C 8Z8",
    "sg:province":"ON",
    "sg:tags":[
        "accountant"
    ],
    "wof:name":"Bishop, David A CA",
    "wof:placetype":"venue"
},
  "geometry": {"coordinates":[-79.46328,43.875931],"type":"Point"}
}