{
  "type": "Feature",
  "properties": {
    "addr:full":"1495 Rue Des Tanneurs Quebec QC G1N 4S7",
    "addr:housenumber":"1495",
    "addr:postcode":"g1n 4s7",
    "addr:street":"Rue Des Tanneurs",
    "iso:country":"CA",
    "sg:address":"1495 Rue Des Tanneurs",
    "sg:city":"Quebec",
    "sg:classifiers":[
        {
            "category":"Building & Trades",
            "subcategory":"Construction",
            "type":"Services"
        }
    ],
    "sg:phone":"+1 418 683 1070",
    "sg:postcode":"G1N 4S7",
    "sg:province":"QC",
    "sg:tags":[
        "elevator"
    ],
    "wof:name":"Ascenseurs Maxi Inc",
    "wof:placetype":"venue"
},
  "geometry": {"coordinates":[-71.26773834230001,46.8003387451],"type":"Point"}
}