{
  "type": "Feature",
  "properties": {
    "addr:full":"210 Av Du Lac Rouyn-Noranda QC J9X 4N7",
    "addr:housenumber":"210",
    "addr:postcode":"j9x 4n7",
    "addr:street":"Av Du Lac",
    "iso:country":"CA",
    "sg:address":"210 Av Du Lac",
    "sg:city":"Rouyn-Noranda",
    "sg:classifiers":[
        {
            "category":"Health Services",
            "subcategory":"Doctor",
            "type":"Services"
        }
    ],
    "sg:phone":"+1 819 762 1535",
    "sg:postcode":"J9X 4N7",
    "sg:province":"QC",
    "sg:tags":[
        "clinic",
        "dentist"
    ],
    "wof:name":"Clinique Dentaire Busque/Girar",
    "wof:placetype":"venue"
},
  "geometry": {"coordinates":[-79.016243,48.238804],"type":"Point"}
}