{
  "type": "Feature",
  "properties": {
    "addr:full":"3155 Clairview Ave Val Caron ON P3N 1A5",
    "addr:housenumber":"3155",
    "addr:postcode":"p3n 1a5",
    "addr:street":"Clairview Ave",
    "iso:country":"CA",
    "sg:address":"3155 Clairview Ave",
    "sg:city":"Val Caron",
    "sg:classifiers":[
        {
            "category":"Home & Garden",
            "subcategory":"Household Appliances",
            "type":"Retail Goods"
        }
    ],
    "sg:phone":"+1 705 897 3048",
    "sg:postcode":"P3N 1A5",
    "sg:province":"ON",
    "wof:name":"Rudy's Appliance Svc",
    "wof:placetype":"venue"
},
  "geometry": {"coordinates":[-81.03340911870001,46.6133842468],"type":"Point"}
}