{
  "type": "Feature",
  "properties": {
    "addr:full":"Maple Ridge BC V2X 3K8",
    "addr:postcode":"v2x 3k8",
    "iso:country":"CA",
    "sg:city":"Maple Ridge",
    "sg:classifiers":[
        {
            "category":"Restaurant",
            "type":"Food & Drink"
        }
    ],
    "sg:phone":"+1 604 463 4535",
    "sg:postcode":"V2X 3K8",
    "sg:province":"BC",
    "sg:tags":[
        "pizza"
    ],
    "wof:name":"Super Mario's Pizza",
    "wof:placetype":"venue"
},
  "geometry": {"coordinates":[-122.587303162,49.2204971313],"type":"Point"}
}