{
  "type": "Feature",
  "properties": {
    "addr:full":"14151 Boul Du Cure-Labelle #979 Mirabel QC J7J 1M3",
    "addr:housenumber":"14151",
    "addr:postcode":"j7j 1m3",
    "addr:street":"Boul Du Cure-Labelle # 979",
    "iso:country":"CA",
    "sg:address":"14151 Boul Du Cure-Labelle #979",
    "sg:city":"Mirabel",
    "sg:classifiers":[
        {
            "category":"Manufacturing",
            "subcategory":"Tools & Machinery",
            "type":"Manufacturing & Wholesale Goods"
        }
    ],
    "sg:phone":"+1 450 979 5034",
    "sg:postcode":"J7J 1M3",
    "sg:province":"QC",
    "sg:tags":[
        "machine",
        "shop"
    ],
    "wof:name":"Guerette Outillages Inc",
    "wof:placetype":"venue"
},
  "geometry": {"coordinates":[-73.93454699999999,45.708996],"type":"Point"}
}