{
  "type": "Feature",
  "properties": {
    "addr:full":"1490 Rue Sherbrooke O # 200 Montreal QC H3G 1L3",
    "addr:housenumber":"1490",
    "addr:postcode":"h3g 1l3",
    "addr:street":"Rue Sherbrooke O # 200",
    "iso:country":"CA",
    "sg:address":"1490 Rue Sherbrooke O # 200",
    "sg:city":"Montreal",
    "sg:classifiers":[
        {
            "category":"Shopping",
            "type":"Retail Goods"
        }
    ],
    "sg:phone":"+1 514 939 0500",
    "sg:postcode":"H3G 1L3",
    "sg:province":"QC",
    "sg:tags":[
        "art",
        "gallery",
        "dealer"
    ],
    "wof:name":"Galerie Jean-Pierre Valentin",
    "wof:placetype":"venue"
},
  "geometry": {"coordinates":[-73.56429300000001,45.526203],"type":"Point"}
}