{
  "type": "Feature",
  "properties": {
    "addr:full":"Victoria BC V8X 1J8",
    "addr:postcode":"v8x 1j8",
    "iso:country":"CA",
    "sg:city":"Victoria",
    "sg:classifiers":[
        {
            "category":"Food & Beverages",
            "subcategory":"Groceries & Convenience Stores",
            "type":"Retail Goods"
        }
    ],
    "sg:phone":"+1 250 479 4430",
    "sg:postcode":"V8X 1J8",
    "sg:province":"BC",
    "sg:tags":[
        "organization",
        "social",
        "welfare"
    ],
    "wof:name":"Sendial",
    "wof:placetype":"venue"
},
  "geometry": {"coordinates":[-123.36200700000001,48.448891],"type":"Point"}
}