{
  "type": "Feature",
  "properties": {
    "addr:full":"118 1st Ave N Naicam SK S0K 2Z0",
    "addr:housenumber":"118",
    "addr:postcode":"s0k 2z0",
    "addr:street":"1St Ave N",
    "iso:country":"CA",
    "sg:address":"118 1st Ave N",
    "sg:city":"Naicam",
    "sg:classifiers":[
        {
            "category":"Autos & Motor Vehicles",
            "subcategory":"Fuel & Gas Station",
            "type":"Retail Goods"
        }
    ],
    "sg:phone":"+1 306 874 2333",
    "sg:postcode":"S0K 2Z0",
    "sg:province":"SK",
    "sg:tags":[
        "engine",
        "oil"
    ],
    "wof:name":"Naicam CO-OP Assoc Ltd Gas Bar",
    "wof:placetype":"venue"
},
  "geometry": {"coordinates":[-104.49769592299999,52.4200744629],"type":"Point"}
}