{
  "type": "Feature",
  "properties": {
    "addr:full":"8031 Dixie Rd Brampton ON L6T 3V1",
    "addr:housenumber":"8031",
    "addr:postcode":"l6t 3v1",
    "addr:street":"Dixie Rd",
    "iso:country":"CA",
    "sg:address":"8031 Dixie Rd",
    "sg:city":"Brampton",
    "sg:classifiers":[
        {
            "category":"Manufacturing",
            "subcategory":"Tools & Machinery",
            "type":"Manufacturing & Wholesale Goods"
        }
    ],
    "sg:phone":"+1 905 793 3000",
    "sg:postcode":"L6T 3V1",
    "sg:province":"ON",
    "sg:tags":[
        "plastic"
    ],
    "wof:name":"Brampton Engineering Inc",
    "wof:placetype":"venue"
},
  "geometry": {"coordinates":[-79.703568,43.696774],"type":"Point"}
}