{
  "type": "Feature",
  "properties": {
    "addr:full":"125 Sunnydale Dr Sydney NS B1R 1J4",
    "addr:housenumber":"125",
    "addr:postcode":"b1r 1j4",
    "addr:street":"Sunnydale Dr",
    "iso:country":"CA",
    "sg:address":"125 Sunnydale Dr",
    "sg:city":"Sydney",
    "sg:classifiers":[
        {
            "category":"Education",
            "subcategory":"School",
            "type":"Public Place"
        }
    ],
    "sg:phone":"+1 902 539 3031",
    "sg:postcode":"B1R 1J4",
    "sg:province":"NS",
    "wof:name":"Robin Foote Elementary School",
    "wof:placetype":"venue"
},
  "geometry": {"coordinates":[-60.1955680847,46.1373405457],"type":"Point"}
}