{
  "type": "Feature",
  "properties": {
    "addr:full":"341 Av Saint-Jacques Louiseville QC J5V 1C7",
    "addr:postcode":"j5v 1c7",
    "addr:street":"341 Av Saint-Jacques",
    "iso:country":"CA",
    "sg:address":"341 Av Saint-Jacques",
    "sg:city":"Louiseville",
    "sg:classifiers":[
        {
            "category":"Health Services",
            "subcategory":"Nursing And Care Facility",
            "type":"Services"
        }
    ],
    "sg:phone":"+1 819 228 0096",
    "sg:postcode":"J5V 1C7",
    "sg:province":"QC",
    "sg:tags":[
        "home",
        "retirement",
        "community"
    ],
    "wof:name":"Villa Harfang Des Neiges",
    "wof:placetype":"venue"
},
  "geometry": {"coordinates":[-72.9464874268,46.2572174072],"type":"Point"}
}