{
  "type": "Feature",
  "properties": {
    "addr:full":"750 Boul Monseigneur-DE Laval Baie-Saint-Paul QC G3Z 2V5",
    "addr:housenumber":"750",
    "addr:postcode":"g3z 2v5",
    "addr:street":"Boul Monseigneur-De Laval",
    "iso:country":"CA",
    "sg:address":"750 Boul Monseigneur-DE Laval",
    "sg:city":"Baie-Saint-Paul",
    "sg:classifiers":[
        {
            "category":"Travel",
            "subcategory":"Hotels & Motels",
            "type":"Entertainment"
        }
    ],
    "sg:phone":"+1 418 435 5505",
    "sg:postcode":"G3Z 2V5",
    "sg:province":"QC",
    "sg:tags":[
        "inn"
    ],
    "wof:name":"Auberge LA Pignoronde Inc",
    "wof:placetype":"venue"
},
  "geometry": {"coordinates":[-70.525627,47.423782],"type":"Point"}
}