{
  "type": "Feature",
  "properties": {
    "addr:full":"426 Talbot St St Thomas ON N5P 1B9",
    "addr:housenumber":"426",
    "addr:postcode":"n5p 1b9",
    "addr:street":"Talbot St",
    "iso:country":"CA",
    "sg:address":"426 Talbot St",
    "sg:city":"St Thomas",
    "sg:classifiers":[
        {
            "category":"Health Services",
            "subcategory":"Doctor",
            "type":"Services"
        }
    ],
    "sg:phone":"+1 519 633 4410",
    "sg:postcode":"N5P 1B9",
    "sg:province":"ON",
    "sg:tags":[
        "physician",
        "surgeon"
    ],
    "wof:name":"Jones, Robert A B MD",
    "wof:placetype":"venue"
},
  "geometry": {"coordinates":[-81.19657100000001,42.778858],"type":"Point"}
}