{
  "type": "Feature",
  "properties": {
    "iso:country":"CA",
    "sg:address":"1 Av Du Mont-Royal E",
    "sg:city":"Montreal",
    "sg:classifiers":[
        {
            "category":"Shopping",
            "subcategory":"Pharmacy",
            "type":"Retail Goods"
        }
    ],
    "sg:phone":"+1 514 284 1865",
    "sg:postcode":"H2T 1N4",
    "sg:province":"QC",
    "wof:name":"Pharmaprix",
    "wof:placetype":"venue"
},
  "geometry": {"coordinates":[-73.586357,45.520191],"type":"Point"}
}