{
  "type": "Feature",
  "properties": {
    "addr:full":"Corner Brook NL A2H 2Y6",
    "addr:postcode":"a2h 2y6",
    "iso:country":"CA",
    "sg:city":"Corner Brook",
    "sg:classifiers":[
        {
            "category":"Health Services",
            "subcategory":"Chiropractor",
            "type":"Services"
        }
    ],
    "sg:phone":"+1 709 639 2225",
    "sg:postcode":"A2H 2Y6",
    "sg:province":"NL",
    "wof:name":"Chiropractic Associates",
    "wof:placetype":"venue"
},
  "geometry": {"coordinates":[-57.9442367554,48.9526062012],"type":"Point"}
}