{
  "type": "Feature",
  "properties": {
    "addr:full":"5350 Imperial St Burnaby BC V5J 1E6",
    "addr:housenumber":"5350",
    "addr:postcode":"v5j 1e6",
    "addr:street":"Imperial St",
    "iso:country":"CA",
    "sg:address":"5350 Imperial St",
    "sg:city":"Burnaby",
    "sg:classifiers":[
        {
            "category":"Wholesale",
            "subcategory":"Electrical",
            "type":"Manufacturing & Wholesale Goods"
        }
    ],
    "sg:phone":"+1 604 433 5533",
    "sg:postcode":"V5J 1E6",
    "sg:province":"BC",
    "sg:tags":[
        "lighting",
        "fixture"
    ],
    "wof:name":"S & N Lighting Ltd",
    "wof:placetype":"venue"
},
  "geometry": {"coordinates":[-122.98626709,49.2217025757],"type":"Point"}
}