{
  "type": "Feature",
  "properties": {
    "addr:full":"Kipawa QC J0Z 2H0",
    "addr:postcode":"j0z 2h0",
    "iso:country":"CA",
    "sg:city":"Kipawa",
    "sg:classifiers":[
        {
            "category":"Building & Trades",
            "subcategory":"Equipment Rental",
            "type":"Services"
        }
    ],
    "sg:phone":"+1 819 627 3471",
    "sg:postcode":"J0Z 2H0",
    "sg:province":"QC",
    "sg:tags":[
        "aircraft",
        "leasing",
        "charter"
    ],
    "wof:name":"Air Kipawa Inc",
    "wof:placetype":"venue"
},
  "geometry": {"coordinates":[-79.025642,46.765965],"type":"Point"}
}