{
  "type": "Feature",
  "properties": {
    "addr:full":"1122 Dorval Dr Oakville ON L6M 3E4",
    "addr:housenumber":"1122",
    "addr:postcode":"l6m 3e4",
    "addr:street":"Dorval Dr",
    "iso:country":"CA",
    "sg:address":"1122 Dorval Dr",
    "sg:city":"Oakville",
    "sg:classifiers":[
        {
            "category":"Retail",
            "subcategory":"Laundry & Dry Cleaning",
            "type":"Services"
        }
    ],
    "sg:phone":"+1 905 844 6226",
    "sg:postcode":"L6M 3E4",
    "sg:province":"ON",
    "sg:tags":[
        "cleaners"
    ],
    "wof:name":"Caspian Cleaners",
    "wof:placetype":"venue"
},
  "geometry": {"coordinates":[-79.7054138184,43.4496116638],"type":"Point"}
}