{
  "type": "Feature",
  "properties": {
    "addr:full":"1600D Beach Ave Vancouver BC V6G 1Y8",
    "addr:housenumber":"1600d",
    "addr:postcode":"v6g 1y8",
    "addr:street":"Beach Ave",
    "iso:country":"CA",
    "sg:address":"1600D Beach Ave",
    "sg:city":"Vancouver",
    "sg:classifiers":[
        {
            "category":"Professional",
            "subcategory":"Accounting & Tax Preparation",
            "type":"Services"
        }
    ],
    "sg:phone":"+1 604 688 3043",
    "sg:postcode":"V6G 1Y8",
    "sg:province":"BC",
    "sg:tags":[
        "accountant"
    ],
    "wof:name":"Sharp & CO",
    "wof:placetype":"venue"
},
  "geometry": {"coordinates":[-123.14212000000001,49.283188],"type":"Point"}
}