{
  "type": "Feature",
  "properties": {
    "iso:country":"CA",
    "sg:address":"1600D Beach Ave",
    "sg:city":"Vancouver",
    "sg:classifiers":[
        {
            "category":"Professional",
            "subcategory":"Accounting & Tax Preparation",
            "type":"Services"
        }
    ],
    "sg:phone":"+1 604 688 3043",
    "sg:postcode":"V6G 1Y8",
    "sg:province":"BC",
    "sg:tags":[
        "accountant"
    ],
    "wof:name":"Sharp & CO",
    "wof:placetype":"venue"
},
  "geometry": {"coordinates":[-123.14212,49.283188],"type":"Point"}
}