{
  "type": "Feature",
  "properties": {
    "addr:full":"Saint-Hubert QC J3Y 4H8",
    "addr:postcode":"j3y 4h8",
    "iso:country":"CA",
    "sg:city":"Saint-Hubert",
    "sg:classifiers":[
        {
            "category":"Shopping",
            "subcategory":"Computers & Home Electronics",
            "type":"Retail Goods"
        }
    ],
    "sg:phone":"+1 450 445 8692",
    "sg:postcode":"J3Y 4H8",
    "sg:province":"QC",
    "sg:tags":[
        "software"
    ],
    "wof:name":"Troalen Technologie Inc",
    "wof:placetype":"venue"
},
  "geometry": {"coordinates":[-73.423241,45.502369],"type":"Point"}
}