{
  "type": "Feature",
  "properties": {
    "addr:full":"257 Rue Saint-Desire Black Lake QC G6H 1L2",
    "addr:housenumber":"257",
    "addr:postcode":"g6h 1l2",
    "addr:street":"Rue Saint-Desire Black Lake",
    "iso:country":"CA",
    "sg:address":"257 Rue Saint-Desire",
    "sg:city":"Black Lake",
    "sg:classifiers":[
        {
            "category":"Professional",
            "subcategory":"Accounting & Tax Preparation",
            "type":"Services"
        }
    ],
    "sg:phone":"+1 418 423 2701",
    "sg:postcode":"G6H 1L2",
    "sg:province":"QC",
    "sg:tags":[
        "accountant",
        "return",
        "filing"
    ],
    "wof:name":"Roy, Rene",
    "wof:placetype":"venue"
},
  "geometry": {"coordinates":[-71.36039700000001,46.043991],"type":"Point"}
}