{
  "type": "Feature",
  "properties": {
    "iso:country":"CA",
    "sg:address":"1126 Brydges St",
    "sg:city":"London",
    "sg:classifiers":[
        {
            "category":"Manufacturing",
            "subcategory":"Tools & Machinery",
            "type":"Manufacturing & Wholesale Goods"
        }
    ],
    "sg:phone":"+1 519 451 8169",
    "sg:postcode":"N5W 2B7",
    "sg:province":"ON",
    "sg:tags":[
        "machine",
        "shop"
    ],
    "wof:name":"Standard Machine Shop",
    "wof:placetype":"venue"
},
  "geometry": {"coordinates":[-81.209175,42.986897],"type":"Point"}
}