{
  "type": "Feature",
  "properties": {
    "addr:full":"11352 Yonge St Richmond Hill ON L4S 1K9",
    "addr:housenumber":"11352",
    "addr:postcode":"l4s 1k9",
    "addr:street":"Yonge St",
    "iso:country":"CA",
    "sg:address":"11352 Yonge St",
    "sg:city":"Richmond Hill",
    "sg:classifiers":[
        {
            "category":"Retail",
            "subcategory":"Auto Repair",
            "type":"Services"
        }
    ],
    "sg:phone":"+1 905 884 3777",
    "sg:postcode":"L4S 1K9",
    "sg:province":"ON",
    "sg:tags":[
        "repairing",
        "automobile"
    ],
    "wof:name":"Laser & Auto Svc",
    "wof:placetype":"venue"
},
  "geometry": {"coordinates":[-79.4451217651,43.9041824341],"type":"Point"}
}