{
  "type": "Feature",
  "properties": {
    "addr:full":"51A St & 40th Ave Red Deer AB T4N 6S6",
    "addr:housenumber":"51a",
    "addr:postcode":"t4n 6s6",
    "addr:street":"St & 40Th Ave",
    "iso:country":"CA",
    "sg:address":"51A St & 40th Ave",
    "sg:city":"Red Deer",
    "sg:classifiers":[
        {
            "category":"Recreation",
            "type":"Entertainment"
        }
    ],
    "sg:phone":"+1 403 346 0440",
    "sg:postcode":"T4N 6S6",
    "sg:province":"AB",
    "sg:tags":[
        "club",
        "curling"
    ],
    "wof:name":"Michener Hill Curling Assoc",
    "wof:placetype":"venue"
},
  "geometry": {"coordinates":[-113.79592895499999,52.26953125],"type":"Point"}
}