{
  "type": "Feature",
  "properties": {
    "addr:full":"57 Durand Rd Winnipeg MB R2J 3T1",
    "addr:housenumber":"57",
    "addr:postcode":"r2j 3t1",
    "addr:street":"Durand Rd",
    "iso:country":"CA",
    "sg:address":"57 Durand Rd",
    "sg:city":"Winnipeg",
    "sg:classifiers":[
        {
            "category":"Retail",
            "subcategory":"Auto Repair",
            "type":"Services"
        }
    ],
    "sg:phone":"+1 204 663 8362",
    "sg:postcode":"R2J 3T1",
    "sg:province":"MB",
    "sg:tags":[
        "body",
        "truck",
        "conversion",
        "van",
        "accessory"
    ],
    "wof:name":"Altec Industries Ltd",
    "wof:placetype":"venue"
},
  "geometry": {"coordinates":[-97.040779,49.884583],"type":"Point"}
}