{
  "type": "Feature",
  "properties": {
    "iso:country":"CA",
    "sg:city":"Montreal",
    "sg:classifiers":[
        {
            "category":"Wholesale",
            "subcategory":"Apparel",
            "type":"Manufacturing & Wholesale Goods"
        }
    ],
    "sg:phone":"+1 514 270 5854",
    "sg:postcode":"H2T 3B3",
    "sg:province":"QC",
    "sg:tags":[
        "shoes"
    ],
    "wof:name":"Zelo Chaussures Shoes Import",
    "wof:placetype":"venue"
},
  "geometry": {"coordinates":[-73.596329,45.527344],"type":"Point"}
}