{
  "type": "Feature",
  "properties": {
    "addr:full":"321 Mersea Rd 8 RR 5 Leamington ON N8H 3V8",
    "addr:housenumber":"321",
    "addr:postcode":"n8h 3v8",
    "addr:street":"Mersea Rd 8 Rr 5",
    "iso:country":"CA",
    "sg:address":"321 Mersea Rd 8 RR 5",
    "sg:city":"Leamington",
    "sg:classifiers":[
        {
            "category":"Farming",
            "subcategory":"Farm",
            "type":"Manufacturing & Wholesale Goods"
        }
    ],
    "sg:phone":"+1 519 326 1090",
    "sg:postcode":"N8H 3V8",
    "sg:province":"ON",
    "wof:name":"Tiessen Farms",
    "wof:placetype":"venue"
},
  "geometry": {"coordinates":[-82.6217346191,42.1230926514],"type":"Point"}
}