{
  "type": "Feature",
  "properties": {
    "iso:country":"CA",
    "sg:address":"363 Rue Principale",
    "sg:city":"Saint-Donat-DE-Montcalm",
    "sg:classifiers":[
        {
            "category":"Shopping",
            "subcategory":"Computers & Home Electronics",
            "type":"Retail Goods"
        }
    ],
    "sg:phone":"+1 819 424 4387",
    "sg:postcode":"J0T 2C0",
    "sg:province":"QC",
    "sg:tags":[
        "television",
        "radio"
    ],
    "wof:name":"Atelier Electronique St-Donat",
    "wof:placetype":"venue"
},
  "geometry": {"coordinates":[-74.2243728638,46.3205184937],"type":"Point"}
}