{
  "type": "Feature",
  "properties": {
    "addr:full":"500 Parkside Dr Waterloo ON N2L 5J4",
    "addr:housenumber":"500",
    "addr:postcode":"n2l 5j4",
    "addr:street":"Parkside Dr",
    "iso:country":"CA",
    "sg:address":"500 Parkside Dr",
    "sg:city":"Waterloo",
    "sg:classifiers":[
        {
            "category":"Organizations",
            "subcategory":"Professional Association",
            "type":"Services"
        }
    ],
    "sg:phone":"+1 519 747 0430",
    "sg:postcode":"N2L 5J4",
    "sg:province":"ON",
    "sg:tags":[
        "athletic"
    ],
    "wof:name":"Waterloo Minor Girls Softball",
    "wof:placetype":"venue"
},
  "geometry": {"coordinates":[-80.54529599999999,43.489372],"type":"Point"}
}