{
  "type": "Feature",
  "properties": {
    "addr:full":"806 Rue DE Saint-Jovite Mont-Tremblant QC J8E 3J8",
    "addr:housenumber":"806",
    "addr:postcode":"j8e 3j8",
    "addr:street":"Rue De Saint-Jovite",
    "iso:country":"CA",
    "sg:address":"806 Rue DE Saint-Jovite",
    "sg:city":"Mont-Tremblant",
    "sg:classifiers":[
        {
            "category":"Personal",
            "subcategory":"Beauty Salon",
            "type":"Services"
        }
    ],
    "sg:phone":"+1 819 425 9992",
    "sg:postcode":"J8E 3J8",
    "sg:province":"QC",
    "wof:name":"Salon DE Coiffure Le Doigte",
    "wof:placetype":"venue"
},
  "geometry": {"coordinates":[-74.59034699999999,46.118782],"type":"Point"}
}