{
  "type": "Feature",
  "properties": {
    "addr:full":"817 4 Ave SW Calgary AB T2P 0K5",
    "addr:housenumber":"817",
    "addr:postcode":"t2p 0k5",
    "addr:street":"4 Ave Sw",
    "iso:country":"CA",
    "sg:address":"817 4 Ave SW",
    "sg:city":"Calgary",
    "sg:classifiers":[
        {
            "category":"Food & Beverages",
            "subcategory":"Groceries & Convenience Stores",
            "type":"Retail Goods"
        }
    ],
    "sg:phone":"+1 403 237 0740",
    "sg:postcode":"T2P 0K5",
    "sg:province":"AB",
    "sg:tags":[
        "grocer"
    ],
    "wof:name":"Henry's Food Store",
    "wof:placetype":"venue"
},
  "geometry": {"coordinates":[-114.079109,51.049633],"type":"Point"}
}