{
  "type": "Feature",
  "properties": {
    "iso:country":"CA",
    "sg:city":"Provost",
    "sg:classifiers":[
        {
            "category":"Manufacturing",
            "subcategory":"Tools & Machinery",
            "type":"Manufacturing & Wholesale Goods"
        }
    ],
    "sg:phone":"+1 780 753 2914",
    "sg:postcode":"T0B 3S0",
    "sg:province":"AB",
    "sg:tags":[
        "machine",
        "shop"
    ],
    "wof:name":"Shawn's Mobile Welding",
    "wof:placetype":"venue"
},
  "geometry": {"coordinates":[-110.24916076700001,52.3562164307],"type":"Point"}
}