{
  "type": "Feature",
  "properties": {
    "iso:country":"CA",
    "sg:address":"54 Rue Fusey",
    "sg:city":"Cap-DE-LA-Madeleine",
    "sg:classifiers":[
        {
            "category":"Food & Beverages",
            "subcategory":"Bakery",
            "type":"Retail Goods"
        }
    ],
    "sg:phone":"+1 819 691 0767",
    "sg:postcode":"G8T 2T7",
    "sg:province":"QC",
    "sg:tags":[
        "baker"
    ],
    "wof:name":"Boulangerie Des Trois-Rivieres",
    "wof:placetype":"venue"
},
  "geometry": {"coordinates":[-72.5282363892,46.3645515442],"type":"Point"}
}