{
  "type": "Feature",
  "properties": {
    "iso:country":"CA",
    "sg:city":"Calgary",
    "sg:classifiers":[
        {
            "category":"Shopping",
            "subcategory":"Bicycles & Sporting Goods",
            "type":"Retail Goods"
        }
    ],
    "sg:phone":"+1 403 255 5761",
    "sg:postcode":"T2H 0K3",
    "sg:province":"AB",
    "sg:tags":[
        "sportswear"
    ],
    "wof:name":"Champs Sports",
    "wof:placetype":"venue"
},
  "geometry": {"coordinates":[-114.071831,50.996162],"type":"Point"}
}