{
  "type": "Feature",
  "properties": {
    "iso:country":"CA",
    "sg:address":"831 Queen St W",
    "sg:city":"Toronto",
    "sg:classifiers":[
        {
            "category":"Shopping",
            "subcategory":"Clothing, Apparel, & Fashions",
            "type":"Retail Goods"
        }
    ],
    "sg:phone":"+1 416 535 8618",
    "sg:postcode":"M6J 1G1",
    "sg:province":"ON",
    "wof:name":"Mothership",
    "wof:placetype":"venue"
},
  "geometry": {"coordinates":[-79.4096374512,43.6460151672],"type":"Point"}
}