{
  "type": "Feature",
  "properties": {
    "addr:full":"905 51st St E Saskatoon SK S7K 7E4",
    "addr:housenumber":"905",
    "addr:postcode":"s7k 7e4",
    "addr:street":"51St St E",
    "iso:country":"CA",
    "sg:address":"905 51st St E",
    "sg:city":"Saskatoon",
    "sg:classifiers":[
        {
            "category":"Restaurant",
            "type":"Food & Drink"
        }
    ],
    "sg:phone":"+1 306 955 8667",
    "sg:postcode":"S7K 7E4",
    "sg:province":"SK",
    "wof:name":"Mc Donald's",
    "wof:placetype":"venue"
},
  "geometry": {"coordinates":[-106.64592,52.172791],"type":"Point"}
}