{
  "type": "Feature",
  "properties": {
    "addr:full":"20 Government Rd W Kapuskasing ON P5N 2X8",
    "addr:housenumber":"20",
    "addr:postcode":"p5n 2x8",
    "addr:street":"Rd W",
    "iso:country":"CA",
    "sg:address":"20 Government Rd W",
    "sg:city":"Kapuskasing",
    "sg:classifiers":[
        {
            "category":"Restaurant",
            "type":"Food & Drink"
        }
    ],
    "sg:phone":"+1 705 337 5657",
    "sg:postcode":"P5N 2X8",
    "sg:province":"ON",
    "wof:name":"Sizzles",
    "wof:placetype":"venue"
},
  "geometry": {"coordinates":[-82.428436,49.412735],"type":"Point"}
}