{
  "type": "Feature",
  "properties": {
    "addr:full":"2911 Rue Du Meunier Vaudreuil-Dorion QC J7V 8P2",
    "addr:housenumber":"2911",
    "addr:postcode":"j7v 8p2",
    "addr:street":"Rue Du Meunier",
    "iso:country":"CA",
    "sg:address":"2911 Rue Du Meunier",
    "sg:city":"Vaudreuil-Dorion",
    "sg:classifiers":[
        {
            "category":"Real Estate",
            "subcategory":"Real Estate Agent",
            "type":"Services"
        }
    ],
    "sg:phone":"+1 450 424 5308",
    "sg:postcode":"J7V 8P2",
    "sg:province":"QC",
    "wof:name":"Service Immobilier Nordi Inc",
    "wof:placetype":"venue"
},
  "geometry": {"coordinates":[-74.035088,45.370461],"type":"Point"}
}