{
  "type": "Feature",
  "properties": {
    "addr:full":"197 Sheppard Ave E North York ON M2N 3A8",
    "addr:housenumber":"197",
    "addr:postcode":"m2n 3a8",
    "addr:street":"Sheppard Ave E",
    "iso:country":"CA",
    "sg:address":"197 Sheppard Ave E",
    "sg:city":"North York",
    "sg:classifiers":[
        {
            "category":"Retail",
            "subcategory":"Laundry & Dry Cleaning",
            "type":"Services"
        }
    ],
    "sg:phone":"+1 416 223 1858",
    "sg:postcode":"M2N 3A8",
    "sg:province":"ON",
    "sg:tags":[
        "cleaners"
    ],
    "wof:name":"Master Cleaner",
    "wof:placetype":"venue"
},
  "geometry": {"coordinates":[-79.399109,43.763992],"type":"Point"}
}