{
  "type": "Feature",
  "properties": {
    "addr:full":"Hamilton ON L8N 1V2",
    "addr:postcode":"l8n 1v2",
    "iso:country":"CA",
    "sg:city":"Hamilton",
    "sg:classifiers":[
        {
            "category":"Real Estate",
            "subcategory":"Real Estate Operator",
            "type":"Services"
        }
    ],
    "sg:phone":"+1 905 522 2542",
    "sg:postcode":"L8N 1V2",
    "sg:province":"ON",
    "sg:tags":[
        "apartment"
    ],
    "wof:name":"Villa Marie 2",
    "wof:placetype":"venue"
},
  "geometry": {"coordinates":[-79.869232,43.250645],"type":"Point"}
}