{
  "type": "Feature",
  "properties": {
    "addr:full":"5 Boul Henri-Bourassa O Montreal QC H3L 1M6",
    "addr:housenumber":"5",
    "addr:postcode":"h3l 1m6",
    "addr:street":"Boul Henri-Bourassa O",
    "iso:country":"CA",
    "sg:address":"5 Boul Henri-Bourassa O",
    "sg:city":"Montreal",
    "sg:classifiers":[
        {
            "category":"Restaurant",
            "type":"Food & Drink"
        }
    ],
    "sg:phone":"+1 514 331 2233",
    "sg:postcode":"H3L 1M6",
    "sg:province":"QC",
    "wof:name":"Restaurant Casa Vertoudos",
    "wof:placetype":"venue"
},
  "geometry": {"coordinates":[-73.6710739136,45.5505104065],"type":"Point"}
}