{
  "type": "Feature",
  "properties": {
    "addr:full":"1097 Rte DE LA Seigneurie Saint-Roch-Des-Aulnaies QC G0R 4E0",
    "addr:housenumber":"1097",
    "addr:postcode":"g0r 4e0",
    "addr:street":"Rte De La Seigneurie",
    "iso:country":"CA",
    "sg:address":"1097 Rte DE LA Seigneurie",
    "sg:city":"Saint-Roch-Des-Aulnaies",
    "sg:classifiers":[
        {
            "category":"Shopping",
            "type":"Retail Goods"
        }
    ],
    "sg:phone":"+1 418 354 2850",
    "sg:postcode":"G0R 4E0",
    "sg:province":"QC",
    "wof:name":"Michel Robitaille Objets-Bois",
    "wof:placetype":"venue"
},
  "geometry": {"coordinates":[-70.19285600000001,47.303825],"type":"Point"}
}