{
  "type": "Feature",
  "properties": {
    "addr:full":"960 Av Outremont Outremont QC H2V 4R1",
    "addr:housenumber":"960",
    "addr:postcode":"h2v 4r1",
    "addr:street":"Av Outremont",
    "iso:country":"CA",
    "sg:address":"960 Av Outremont",
    "sg:city":"Outremont",
    "sg:classifiers":[
        {
            "category":"Shopping",
            "subcategory":"Gifts & Souvenirs",
            "type":"Retail Goods"
        }
    ],
    "sg:phone":"+1 514 271 1101",
    "sg:postcode":"H2V 4R1",
    "sg:province":"QC",
    "sg:tags":[
        "shop"
    ],
    "wof:name":"Inter-Continental Mercantile",
    "wof:placetype":"venue"
},
  "geometry": {"coordinates":[-73.61706542970001,45.5225830078],"type":"Point"}
}