{
  "type": "Feature",
  "properties": {
    "addr:full":"1108 8th Ave W Vancouver BC V6H 3Z5",
    "addr:housenumber":"1108",
    "addr:postcode":"v6h 3z5",
    "addr:street":"8Th Ave W",
    "iso:country":"CA",
    "sg:address":"1108 8th Ave W",
    "sg:city":"Vancouver",
    "sg:classifiers":[
        {
            "category":"Insurance",
            "subcategory":"Insurance Agent",
            "type":"Services"
        }
    ],
    "sg:phone":"+1 604 731 5328",
    "sg:postcode":"V6H 3Z5",
    "sg:province":"BC",
    "wof:name":"Winram Insurance Ltd",
    "wof:placetype":"venue"
},
  "geometry": {"coordinates":[-123.12938699999999,49.264252],"type":"Point"}
}