{
  "type": "Feature",
  "properties": {
    "addr:full":"59 Connell Ave Virginiatown ON P0K 1X0",
    "addr:housenumber":"59",
    "addr:postcode":"p0k 1x0",
    "addr:street":"Connell Ave",
    "iso:country":"CA",
    "sg:address":"59 Connell Ave",
    "sg:city":"Virginiatown",
    "sg:classifiers":[
        {
            "category":"Shopping",
            "subcategory":"Discount & Variety Stores",
            "type":"Retail Goods"
        }
    ],
    "sg:phone":"+1 705 634 2228",
    "sg:postcode":"P0K 1X0",
    "sg:province":"ON",
    "wof:name":"Chez Lucie",
    "wof:placetype":"venue"
},
  "geometry": {"coordinates":[-79.58509100000001,48.131184],"type":"Point"}
}