{
  "type": "Feature",
  "properties": {
    "iso:country":"CA",
    "sg:address":"57 York St",
    "sg:city":"London",
    "sg:classifiers":[
        {
            "category":"Personal",
            "subcategory":"Beauty Salon",
            "type":"Services"
        }
    ],
    "sg:phone":"+1 519 672 2347",
    "sg:postcode":"N6A 1A6",
    "sg:province":"ON",
    "wof:name":"Ginger's Hair Studio",
    "wof:placetype":"venue"
},
  "geometry": {"coordinates":[-81.2524719238,42.9800796509],"type":"Point"}
}