{
  "type": "Feature",
  "properties": {
    "iso:country":"CA",
    "sg:city":"Gloucester",
    "sg:classifiers":[
        {
            "category":"Retail",
            "subcategory":"Car Wash",
            "type":"Services"
        }
    ],
    "sg:phone":"+1 613 748 7957",
    "sg:postcode":"K1J 9C7",
    "sg:province":"ON",
    "sg:tags":[
        "polishing",
        "automobile",
        "washing",
        "detail",
        "clean"
    ],
    "wof:name":"Road Star Auto Boutique Ctr",
    "wof:placetype":"venue"
},
  "geometry": {"coordinates":[-75.584815979,45.4538383484],"type":"Point"}
}