{
  "type": "Feature",
  "properties": {
    "iso:country":"CA",
    "sg:address":"4784 27 St",
    "sg:city":"Vernon",
    "sg:classifiers":[
        {
            "category":"Recreation",
            "subcategory":"Amusement Park",
            "type":"Entertainment"
        }
    ],
    "sg:phone":"+1 250 542 6800",
    "sg:postcode":"V1T 4Y6",
    "sg:province":"BC",
    "wof:name":"Ruckers",
    "wof:placetype":"venue"
},
  "geometry": {"coordinates":[-119.26679229699999,50.2816772461],"type":"Point"}
}