{
  "type": "Feature",
  "properties": {
    "iso:country":"CA",
    "sg:address":"762 Woolwich St",
    "sg:city":"Guelph",
    "sg:classifiers":[
        {
            "category":"Real Estate",
            "subcategory":"Developer",
            "type":"Services"
        }
    ],
    "sg:phone":"+1 519 822 1271",
    "sg:postcode":"N1H 3Z1",
    "sg:province":"ON",
    "sg:tags":[
        "cemetery",
        "monument"
    ],
    "wof:name":"Guelph Cemetery Commission",
    "wof:placetype":"venue"
},
  "geometry": {"coordinates":[-80.27611541749999,43.5639266968],"type":"Point"}
}