{
  "type": "Feature",
  "properties": {
    "iso:country":"CA",
    "sg:address":"2500 Rue Leon-Harmel",
    "sg:city":"Quebec",
    "sg:classifiers":[
        {
            "category":"Professional",
            "subcategory":"Advertising",
            "type":"Services"
        }
    ],
    "sg:phone":"+1 418 687 0562",
    "sg:postcode":"G1N 4L7",
    "sg:province":"QC",
    "wof:name":"Viacom Affichage",
    "wof:placetype":"venue"
},
  "geometry": {"coordinates":[-71.285263,46.798225],"type":"Point"}
}