{
  "type": "Feature",
  "properties": {
    "addr:full":"North York ON M2N 6K9",
    "addr:postcode":"m2n 6k9",
    "iso:country":"CA",
    "sg:city":"North York",
    "sg:classifiers":[
        {
            "category":"Real Estate",
            "subcategory":"Real Estate Agent",
            "type":"Services"
        }
    ],
    "sg:phone":"+1 416 223 2200",
    "sg:postcode":"M2N 6K9",
    "sg:province":"ON",
    "sg:tags":[
        "management"
    ],
    "wof:name":"I C Funds Management Inc",
    "wof:placetype":"venue"
},
  "geometry": {"coordinates":[-79.4129486084,43.7612495422],"type":"Point"}
}