{
  "type": "Feature",
  "properties": {
    "addr:full":"252 Rue Richelieu Saint-Jean-Sur-Richelieu QC J3B 6X8",
    "addr:housenumber":"252",
    "addr:postcode":"j3b 6x8",
    "addr:street":"Rue Richelieu",
    "iso:country":"CA",
    "sg:address":"252 Rue Richelieu",
    "sg:city":"Saint-Jean-Sur-Richelieu",
    "sg:classifiers":[
        {
            "category":"Shopping",
            "subcategory":"Shoes",
            "type":"Retail Goods"
        }
    ],
    "sg:phone":"+1 450 346 9849",
    "sg:postcode":"J3B 6X8",
    "sg:province":"QC",
    "wof:name":"Chaussures Pierre Roy Inc",
    "wof:placetype":"venue"
},
  "geometry": {"coordinates":[-73.250923,45.307232],"type":"Point"}
}