{
  "type": "Feature",
  "properties": {
    "addr:full":"Surrey BC V3R 8X8",
    "addr:postcode":"v3r 8x8",
    "iso:country":"CA",
    "sg:city":"Surrey",
    "sg:classifiers":[
        {
            "category":"Shopping",
            "subcategory":"Musical Instruments",
            "type":"Retail Goods"
        }
    ],
    "sg:phone":"+1 604 588 3200",
    "sg:postcode":"V3R 8X8",
    "sg:province":"BC",
    "wof:name":"Tom Lee Music CO Ltd",
    "wof:placetype":"venue"
},
  "geometry": {"coordinates":[-122.800720215,49.1858711243],"type":"Point"}
}