{
  "type": "Feature",
  "properties": {
    "iso:country":"CA",
    "sg:city":"Cap-DE-LA-Madeleine",
    "sg:classifiers":[
        {
            "category":"Retail",
            "subcategory":"Funeral Services",
            "type":"Services"
        }
    ],
    "sg:phone":"+1 819 375 2414",
    "sg:postcode":"G8T 7B1",
    "sg:province":"QC",
    "sg:tags":[
        "director"
    ],
    "wof:name":"Centre Funeraire Chateaudun",
    "wof:placetype":"venue"
},
  "geometry": {"coordinates":[-72.5544433594,46.3909263611],"type":"Point"}
}