{
  "type": "Feature",
  "properties": {
    "addr:full":"410 Ch Des Cedres Saint-Gerard-Des-Laurentides QC G9R 1P7",
    "addr:housenumber":"410",
    "addr:postcode":"g9r 1p7",
    "addr:street":"Ch Des Cedres Saint-Gerard-Des-Laurentides",
    "iso:country":"CA",
    "sg:address":"410 Ch Des Cedres",
    "sg:city":"Saint-Gerard-Des-Laurentides",
    "sg:classifiers":[
        {
            "category":"Building & Trades",
            "subcategory":"Construction",
            "type":"Services"
        }
    ],
    "sg:phone":"+1 819 539 8863",
    "sg:postcode":"G9R 1P7",
    "sg:province":"QC",
    "sg:tags":[
        "maker",
        "cabinet"
    ],
    "wof:name":"Ebenisterie Dbm Inc",
    "wof:placetype":"venue"
},
  "geometry": {"coordinates":[-72.81530761720001,46.6003684998],"type":"Point"}
}