{
  "type": "Feature",
  "properties": {
    "addr:full":"277 Riverside Dr W Windsor ON N9A 5K4",
    "addr:housenumber":"277",
    "addr:postcode":"n9a 5k4",
    "addr:street":"Riverside Dr W",
    "iso:country":"CA",
    "sg:address":"277 Riverside Dr W",
    "sg:city":"Windsor",
    "sg:classifiers":[
        {
            "category":"Shopping",
            "subcategory":"Gifts & Souvenirs",
            "type":"Retail Goods"
        }
    ],
    "sg:phone":"+1 519 252 1846",
    "sg:postcode":"N9A 5K4",
    "sg:province":"ON",
    "sg:tags":[
        "shop"
    ],
    "wof:name":"Yes Windsor Gift Shop",
    "wof:placetype":"venue"
},
  "geometry": {"coordinates":[-83.04303,42.319012],"type":"Point"}
}