{
  "type": "Feature",
  "properties": {
    "addr:full":"50 Bloor St W Toronto ON M4W 3L8",
    "addr:housenumber":"50",
    "addr:postcode":"m4w 3l8",
    "addr:street":"Bloor St W",
    "iso:country":"CA",
    "sg:address":"50 Bloor St W",
    "sg:city":"Toronto",
    "sg:classifiers":[
        {
            "category":"Shopping",
            "subcategory":"Optical Goods",
            "type":"Retail Goods"
        }
    ],
    "sg:phone":"+1 416 972 0814",
    "sg:postcode":"M4W 3L8",
    "sg:province":"ON",
    "sg:tags":[
        "sun",
        "goggles",
        "sunglasses"
    ],
    "wof:name":"Sunglass Hut",
    "wof:placetype":"venue"
},
  "geometry": {"coordinates":[-79.3891448975,43.6698684692],"type":"Point"}
}