{
  "type": "Feature",
  "properties": {
    "iso:country":"CA",
    "sg:address":"1930 Boul Lafleche",
    "sg:city":"Baie-Comeau",
    "sg:classifiers":[
        {
            "category":"Wholesale",
            "subcategory":"Machinery & Supplies",
            "type":"Manufacturing & Wholesale Goods"
        }
    ],
    "sg:phone":"+1 418 589 3354",
    "sg:postcode":"G5C 1C9",
    "sg:province":"QC",
    "sg:tags":[
        "repairing"
    ],
    "wof:name":"Location Gaetan Levesque Inc",
    "wof:placetype":"venue"
},
  "geometry": {"coordinates":[-68.2816314697,49.1948890686],"type":"Point"}
}