{
  "type": "Feature",
  "properties": {
    "addr:full":"1017 Pape Ave East York ON M4K 3V8",
    "addr:housenumber":"1017",
    "addr:postcode":"m4k 3v8",
    "addr:street":"Pape Ave",
    "iso:country":"CA",
    "sg:address":"1017 Pape Ave",
    "sg:city":"East York",
    "sg:classifiers":[
        {
            "category":"Food & Beverages",
            "subcategory":"Bakery",
            "type":"Retail Goods"
        }
    ],
    "sg:phone":"+1 416 425 8877",
    "sg:postcode":"M4K 3V8",
    "sg:province":"ON",
    "sg:tags":[
        "baker"
    ],
    "wof:name":"Danish Pastry Shop",
    "wof:placetype":"venue"
},
  "geometry": {"coordinates":[-79.34818300000001,43.688259],"type":"Point"}
}