{
  "type": "Feature",
  "properties": {
    "addr:full":"Winnipeg MB R3B 1G7",
    "addr:postcode":"r3b 1g7",
    "iso:country":"CA",
    "sg:city":"Winnipeg",
    "sg:classifiers":[
        {
            "category":"Professional",
            "subcategory":"Computer Services",
            "type":"Services"
        }
    ],
    "sg:phone":"+1 204 956 7086",
    "sg:postcode":"R3B 1G7",
    "sg:province":"MB",
    "sg:tags":[
        "consultant"
    ],
    "wof:name":"Lynx Graphics Ltd",
    "wof:placetype":"venue"
},
  "geometry": {"coordinates":[-97.14135,49.896976],"type":"Point"}
}