{
  "type": "Feature",
  "properties": {
    "iso:country":"CA",
    "sg:address":"1401 14 St SW # 1352",
    "sg:city":"Calgary",
    "sg:classifiers":[
        {
            "category":"Food & Beverages",
            "subcategory":"Groceries & Convenience Stores",
            "type":"Retail Goods"
        }
    ],
    "sg:phone":"+1 403 244 3468",
    "sg:postcode":"T3C 1C8",
    "sg:province":"AB",
    "sg:tags":[
        "grocer"
    ],
    "wof:name":"Tom's Food Store",
    "wof:placetype":"venue"
},
  "geometry": {"coordinates":[-114.094772339,51.0402641296],"type":"Point"}
}