{
  "type": "Feature",
  "properties": {
    "addr:full":"175 Rang 5 Saint-David-D'Yamaska QC J0G 1L0",
    "addr:housenumber":"175",
    "addr:postcode":"j0g 1l0",
    "addr:street":"Rang 5 Saint-David-D'Yamaska",
    "iso:country":"CA",
    "sg:address":"175 Rang 5",
    "sg:city":"Saint-David-D'Yamaska",
    "sg:classifiers":[
        {
            "category":"Building & Trades",
            "subcategory":"Electrical",
            "type":"Services"
        }
    ],
    "sg:phone":"+1 450 396 2775",
    "sg:postcode":"J0G 1L0",
    "sg:province":"QC",
    "sg:tags":[
        "electric",
        "contractor"
    ],
    "wof:name":"R Cournoyer Electricien Inc",
    "wof:placetype":"venue"
},
  "geometry": {"coordinates":[-72.91512299999999,46.004326],"type":"Point"}
}