{
  "type": "Feature",
  "properties": {
    "addr:full":"Barrie ON L4N 5J4",
    "addr:postcode":"l4n 5j4",
    "iso:country":"CA",
    "sg:city":"Barrie",
    "sg:classifiers":[
        {
            "category":"Health Services",
            "subcategory":"Chiropractor",
            "type":"Services"
        }
    ],
    "sg:phone":"+1 705 727 9200",
    "sg:postcode":"L4N 5J4",
    "sg:province":"ON",
    "wof:name":"Souter, Brent DC",
    "wof:placetype":"venue"
},
  "geometry": {"coordinates":[-79.6945343018,44.3876190186],"type":"Point"}
}