{
  "type": "Feature",
  "properties": {
    "addr:full":"50 Kennedy Rd S # 2 Brampton ON L6W 3R7",
    "addr:housenumber":"50",
    "addr:postcode":"l6w 3r7",
    "addr:street":"Kennedy Rd S # 2",
    "iso:country":"CA",
    "sg:address":"50 Kennedy Rd S # 2",
    "sg:city":"Brampton",
    "sg:classifiers":[
        {
            "category":"Retail",
            "subcategory":"Portrait Studio",
            "type":"Services"
        }
    ],
    "sg:phone":"+1 905 451 4658",
    "sg:postcode":"L6W 3R7",
    "sg:province":"ON",
    "sg:tags":[
        "key"
    ],
    "wof:name":"Casablanca Lottery Agency",
    "wof:placetype":"venue"
},
  "geometry": {"coordinates":[-79.741173,43.689617],"type":"Point"}
}