{
  "type": "Feature",
  "properties": {
    "addr:full":"353 Winnipeg St Penticton BC V2A 5M4",
    "addr:housenumber":"353",
    "addr:postcode":"v2a 5m4",
    "addr:street":"Winnipeg St",
    "iso:country":"CA",
    "sg:address":"353 Winnipeg St",
    "sg:city":"Penticton",
    "sg:classifiers":[
        {
            "category":"Health Services",
            "subcategory":"Health Practitioner",
            "type":"Services"
        }
    ],
    "sg:phone":"+1 250 493 7343",
    "sg:postcode":"V2A 5M4",
    "sg:province":"BC",
    "sg:tags":[
        "physiotherapist"
    ],
    "wof:name":"Dale Charles & Assoc",
    "wof:placetype":"venue"
},
  "geometry": {"coordinates":[-119.595085144,49.4973449707],"type":"Point"}
}