{
  "type": "Feature",
  "properties": {
    "addr:full":"176 1 Ave S St-Nazaire-Du-Lac-St-Jean QC G0W 2V0",
    "addr:housenumber":"176",
    "addr:postcode":"g0w 2v0",
    "addr:street":"1 Ave S St-Nazaire-Du-Lac-St-Jean",
    "iso:country":"CA",
    "sg:address":"176 1 Ave S",
    "sg:city":"St-Nazaire-Du-Lac-St-Jean",
    "sg:classifiers":[
        {
            "category":"Education",
            "subcategory":"Dance Studio",
            "type":"Public Place"
        }
    ],
    "sg:phone":"+1 418 668 8016",
    "sg:postcode":"G0W 2V0",
    "sg:province":"QC",
    "sg:tags":[
        "ballroom"
    ],
    "wof:name":"Salle Au Rondin",
    "wof:placetype":"venue"
},
  "geometry": {"coordinates":[-71.486931,48.575367],"type":"Point"}
}