{
  "type": "Feature",
  "properties": {
    "addr:full":"230 Logan Rd Bridgewater NS B4V 3J8",
    "addr:housenumber":"230",
    "addr:postcode":"b4v 3j8",
    "addr:street":"Logan Rd",
    "iso:country":"CA",
    "sg:address":"230 Logan Rd",
    "sg:city":"Bridgewater",
    "sg:classifiers":[
        {
            "category":"Retail",
            "subcategory":"Auto Rental",
            "type":"Services"
        }
    ],
    "sg:phone":"+1 902 543 4100",
    "sg:postcode":"B4V 3J8",
    "sg:province":"NS",
    "sg:tags":[
        "renting",
        "truck",
        "leasing"
    ],
    "wof:name":"U-Haul CO Ltd",
    "wof:placetype":"venue"
},
  "geometry": {"coordinates":[-64.54290008540001,44.386756897],"type":"Point"}
}