{
  "type": "Feature",
  "properties": {
    "addr:full":"1126 Central Ave Prince Albert SK S6V 4V6",
    "addr:housenumber":"1126",
    "addr:postcode":"s6v 4v6",
    "addr:street":"Central Ave",
    "iso:country":"CA",
    "sg:address":"1126 Central Ave",
    "sg:city":"Prince Albert",
    "sg:classifiers":[
        {
            "category":"Home & Garden",
            "subcategory":"Furniture",
            "type":"Retail Goods"
        }
    ],
    "sg:phone":"+1 306 922 6626",
    "sg:postcode":"S6V 4V6",
    "sg:province":"SK",
    "wof:name":"Partners Furniture",
    "wof:placetype":"venue"
},
  "geometry": {"coordinates":[-105.75403595,53.2027854919],"type":"Point"}
}