{
  "type": "Feature",
  "properties": {
    "iso:country":"CA",
    "sg:address":"127 Boul Renard O",
    "sg:city":"Gaspe",
    "sg:classifiers":[
        {
            "category":"Food & Beverages",
            "subcategory":"Groceries & Convenience Stores",
            "type":"Retail Goods"
        }
    ],
    "sg:phone":"+1 418 269 3138",
    "sg:postcode":"G4X 5B2",
    "sg:province":"QC",
    "sg:tags":[
        "grocer"
    ],
    "wof:name":"Depanneur Chez Marc",
    "wof:placetype":"venue"
},
  "geometry": {"coordinates":[-64.3769836426,48.990562439],"type":"Point"}
}