{
  "type": "Feature",
  "properties": {
    "addr:full":"Toronto ON M6E 1C2",
    "addr:postcode":"m6e 1c2",
    "iso:country":"CA",
    "sg:city":"Toronto",
    "sg:classifiers":[
        {
            "category":"Professional",
            "subcategory":"Lawyer & Legal Services",
            "type":"Services"
        }
    ],
    "sg:phone":"+1 416 652 0780",
    "sg:postcode":"M6E 1C2",
    "sg:province":"ON",
    "sg:tags":[
        "attorney"
    ],
    "wof:name":"Letterio, B J B QC",
    "wof:placetype":"venue"
},
  "geometry": {"coordinates":[-79.448212,43.676678],"type":"Point"}
}