{
  "type": "Feature",
  "properties": {
    "addr:full":"174 Rue Principale Les Coteaux QC J7X 1A1",
    "addr:housenumber":"174",
    "addr:postcode":"j7x 1a1",
    "addr:street":"Rue Principale",
    "iso:country":"CA",
    "sg:address":"174 Rue Principale",
    "sg:city":"Les Coteaux",
    "sg:classifiers":[
        {
            "category":"Professional",
            "subcategory":"Accounting & Tax Preparation",
            "type":"Services"
        }
    ],
    "sg:phone":"+1 450 267 4441",
    "sg:postcode":"J7X 1A1",
    "sg:province":"QC",
    "sg:tags":[
        "consultant",
        "notary"
    ],
    "wof:name":"Jeannotte & Jeannotte",
    "wof:placetype":"venue"
},
  "geometry": {"coordinates":[-74.208061,45.256721],"type":"Point"}
}