{
  "type": "Feature",
  "properties": {
    "addr:full":"Brampton ON L6V 1P8",
    "addr:postcode":"l6v 1p8",
    "iso:country":"CA",
    "sg:city":"Brampton",
    "sg:classifiers":[
        {
            "category":"Professional",
            "subcategory":"Computer Services",
            "type":"Services"
        }
    ],
    "sg:phone":"+1 905 796 5600",
    "sg:postcode":"L6V 1P8",
    "sg:province":"ON",
    "sg:tags":[
        "repair"
    ],
    "wof:name":"Microbase Systems Inc",
    "wof:placetype":"venue"
},
  "geometry": {"coordinates":[-79.769882,43.693516],"type":"Point"}
}