{
  "type": "Feature",
  "properties": {
    "iso:country":"CA",
    "sg:address":"621 Victoria Ave",
    "sg:city":"Regina",
    "sg:classifiers":[
        {
            "category":"Restaurant",
            "type":"Food & Drink"
        }
    ],
    "sg:phone":"+1 306 791 6400",
    "sg:postcode":"S4N 0R2",
    "sg:province":"SK",
    "wof:name":"Kfc",
    "wof:placetype":"venue"
},
  "geometry": {"coordinates":[-104.58979797400001,50.4469833374],"type":"Point"}
}