{
  "type": "Feature",
  "properties": {
    "addr:full":"Grand Falls-Windsor NL A2A 2K5",
    "addr:postcode":"a2a 2k5",
    "iso:country":"CA",
    "sg:city":"Grand Falls-Windsor",
    "sg:classifiers":[
        {
            "category":"Shopping",
            "subcategory":"Luggage & Leather Goods",
            "type":"Retail Goods"
        }
    ],
    "sg:phone":"+1 709 489 3999",
    "sg:postcode":"A2A 2K5",
    "sg:province":"NL",
    "wof:name":"Bentley Leathers",
    "wof:placetype":"venue"
},
  "geometry": {"coordinates":[-55.653919,48.947208],"type":"Point"}
}