{
  "type": "Feature",
  "properties": {
    "addr:full":"Maple Ridge BC V2X 2V5",
    "addr:postcode":"v2x 2v5",
    "iso:country":"CA",
    "sg:city":"Maple Ridge",
    "sg:classifiers":[
        {
            "category":"Shopping",
            "subcategory":"Gifts & Souvenirs",
            "type":"Retail Goods"
        }
    ],
    "sg:phone":"+1 604 476 0881",
    "sg:postcode":"V2X 2V5",
    "sg:province":"BC",
    "sg:tags":[
        "shop"
    ],
    "wof:name":"Favorite Finds Inc",
    "wof:placetype":"venue"
},
  "geometry": {"coordinates":[-122.593353272,49.217048645],"type":"Point"}
}