{
  "type": "Feature",
  "properties": {
    "addr:full":"1525 Rue Notre-Dame Lachine QC H8S 2E4",
    "addr:housenumber":"1525",
    "addr:postcode":"h8s 2e4",
    "addr:street":"Rue Notre-Dame",
    "iso:country":"CA",
    "sg:address":"1525 Rue Notre-Dame",
    "sg:city":"Lachine",
    "sg:classifiers":[
        {
            "category":"Health Services",
            "subcategory":"Doctor",
            "type":"Services"
        }
    ],
    "sg:phone":"+1 514 634 1911",
    "sg:postcode":"H8S 2E4",
    "sg:province":"QC",
    "sg:tags":[
        "dentist"
    ],
    "wof:name":"Macaluso, Maurice DDS",
    "wof:placetype":"venue"
},
  "geometry": {"coordinates":[-73.6777191162,45.4348373413],"type":"Point"}
}