{
  "type": "Feature",
  "properties": {
    "addr:full":"2447 Greenwood Rd Pembroke ON K8A 6W2",
    "addr:housenumber":"2447",
    "addr:postcode":"k8a 6w2",
    "addr:street":"Greenwood Rd",
    "iso:country":"CA",
    "sg:address":"2447 Greenwood Rd",
    "sg:city":"Pembroke",
    "sg:classifiers":[
        {
            "category":"Wholesale",
            "subcategory":"Machinery & Supplies",
            "type":"Manufacturing & Wholesale Goods"
        }
    ],
    "sg:phone":"+1 613 638 5372",
    "sg:postcode":"K8A 6W2",
    "sg:province":"ON",
    "sg:tags":[
        "farm",
        "equipment",
        "contractor"
    ],
    "wof:name":"Cecil C Elliott Farm Equipment",
    "wof:placetype":"venue"
},
  "geometry": {"coordinates":[-77.1122131348,45.8264808655],"type":"Point"}
}