{
  "type": "Feature",
  "properties": {
    "addr:full":"15 Sir Winston Churchill Sq NW Edmonton AB T5J 2E5",
    "addr:housenumber":"15",
    "addr:postcode":"t5j 2e5",
    "addr:street":"Sir Winston Churchill Sq Nw",
    "iso:country":"CA",
    "sg:address":"15 Sir Winston Churchill Sq NW",
    "sg:city":"Edmonton",
    "sg:classifiers":[
        {
            "category":"Social Services",
            "type":"Services"
        }
    ],
    "sg:phone":"+1 780 423 5510",
    "sg:postcode":"T5J 2E5",
    "sg:province":"AB",
    "sg:tags":[
        "organization",
        "welfare"
    ],
    "wof:name":"Senior Citizens Information",
    "wof:placetype":"venue"
},
  "geometry": {"coordinates":[-113.49054,53.544605],"type":"Point"}
}