{
  "type": "Feature",
  "properties": {
    "addr:full":"147 N Augusta Rd Brockville ON K6V 2Y1",
    "addr:housenumber":"147",
    "addr:postcode":"k6v 2y1",
    "addr:street":"N Augusta Rd",
    "iso:country":"CA",
    "sg:address":"147 N Augusta Rd",
    "sg:city":"Brockville",
    "sg:classifiers":[
        {
            "category":"Freight",
            "type":"Transportation"
        }
    ],
    "sg:phone":"+1 613 342 9028",
    "sg:postcode":"K6V 2Y1",
    "sg:province":"ON",
    "sg:tags":[
        "trucking"
    ],
    "wof:name":"Central Transport Ltd",
    "wof:placetype":"venue"
},
  "geometry": {"coordinates":[-75.6768569946,44.5999450684],"type":"Point"}
}