{
  "type": "Feature",
  "properties": {
    "addr:full":"199 338 Rte Coteau-Du-Lac QC J0P 1B0",
    "addr:housenumber":"338",
    "addr:postcode":"j0p 1b0",
    "addr:street":"Rte Coteau-Du-Lac",
    "iso:country":"CA",
    "sg:address":"199 338 Rte",
    "sg:city":"Coteau-Du-Lac",
    "sg:classifiers":[
        {
            "category":"Freight",
            "type":"Transportation"
        }
    ],
    "sg:phone":"+1 450 763 0612",
    "sg:postcode":"J0P 1B0",
    "sg:province":"QC",
    "sg:tags":[
        "trucking"
    ],
    "wof:name":"Quality Carrier Inc",
    "wof:placetype":"venue"
},
  "geometry": {"coordinates":[-74.17701,45.296982],"type":"Point"}
}