{
  "type": "Feature",
  "properties": {
    "iso:country":"CA",
    "sg:address":"7342 5th St",
    "sg:city":"Grand Forks",
    "sg:classifiers":[
        {
            "category":"Education",
            "subcategory":"Library",
            "type":"Public Place"
        }
    ],
    "sg:phone":"+1 250 442 3944",
    "sg:postcode":"V0H 1H0",
    "sg:province":"BC",
    "wof:name":"Grand Forks Public Library",
    "wof:placetype":"venue"
},
  "geometry": {"coordinates":[-118.440818787,49.0323867798],"type":"Point"}
}