{
  "type": "Feature",
  "properties": {
    "addr:full":"Surrey BC V3R 5C9",
    "addr:postcode":"v3r 5c9",
    "iso:country":"CA",
    "sg:city":"Surrey",
    "sg:classifiers":[
        {
            "category":"Professional",
            "subcategory":"Accounting & Tax Preparation",
            "type":"Services"
        }
    ],
    "sg:phone":"+1 604 930 3109",
    "sg:postcode":"V3R 5C9",
    "sg:province":"BC",
    "sg:tags":[
        "bookkeeping",
        "general"
    ],
    "wof:name":"Tom Peniuk Bookkeeping & Incme",
    "wof:placetype":"venue"
},
  "geometry": {"coordinates":[-122.843857,49.199787],"type":"Point"}
}