{
  "type": "Feature",
  "properties": {
    "iso:country":"CA",
    "sg:address":"47 Scott St",
    "sg:city":"Kitchener",
    "sg:classifiers":[
        {
            "category":"Restaurant",
            "type":"Food & Drink"
        }
    ],
    "sg:phone":"+1 519 749 0407",
    "sg:postcode":"N2H 2P9",
    "sg:province":"ON",
    "wof:name":"Casbah",
    "wof:placetype":"venue"
},
  "geometry": {"coordinates":[-80.484901,43.449844],"type":"Point"}
}