{
  "type": "Feature",
  "properties": {
    "addr:full":"47 Scott St Kitchener ON N2H 2P9",
    "addr:housenumber":"47",
    "addr:postcode":"n2h 2p9",
    "addr:street":"Scott St",
    "iso:country":"CA",
    "sg:address":"47 Scott St",
    "sg:city":"Kitchener",
    "sg:classifiers":[
        {
            "category":"Restaurant",
            "type":"Food & Drink"
        }
    ],
    "sg:phone":"+1 519 749 0407",
    "sg:postcode":"N2H 2P9",
    "sg:province":"ON",
    "wof:name":"Casbah",
    "wof:placetype":"venue"
},
  "geometry": {"coordinates":[-80.48490099999999,43.449844],"type":"Point"}
}