{
  "type": "Feature",
  "properties": {
    "addr:full":"1003 Av Rodolphe-Forget Sillery QC G1S 3Y3",
    "addr:housenumber":"1003",
    "addr:postcode":"g1s 3y3",
    "addr:street":"Av Rodolphe-Forget",
    "iso:country":"CA",
    "sg:address":"1003 Av Rodolphe-Forget",
    "sg:city":"Sillery",
    "sg:classifiers":[
        {
            "category":"Health Services",
            "subcategory":"Podiatrist",
            "type":"Services"
        }
    ],
    "sg:phone":"+1 418 681 3623",
    "sg:postcode":"G1S 3Y3",
    "sg:province":"QC",
    "wof:name":"Meiwes, Ferdinand DPM",
    "wof:placetype":"venue"
},
  "geometry": {"coordinates":[-71.2520599365,46.7895317078],"type":"Point"}
}