{
  "type": "Feature",
  "properties": {
    "addr:full":"28 Frederick St Saint John NB E2J 2A9",
    "addr:housenumber":"28",
    "addr:postcode":"e2j 2a9",
    "addr:street":"Frederick St",
    "iso:country":"CA",
    "sg:address":"28 Frederick St",
    "sg:city":"Saint John",
    "sg:classifiers":[
        {
            "category":"Wholesale",
            "subcategory":"Tobacco Products",
            "type":"Manufacturing & Wholesale Goods"
        }
    ],
    "sg:phone":"+1 506 642 6143",
    "sg:postcode":"E2J 2A9",
    "sg:province":"NB",
    "sg:tags":[
        "cigarette",
        "grocer",
        "cigar"
    ],
    "wof:name":"Tra Foods Ltd Cash & Carry",
    "wof:placetype":"venue"
},
  "geometry": {"coordinates":[-66.05072021479999,45.2848777771],"type":"Point"}
}