{
  "type": "Feature",
  "properties": {
    "addr:full":"Vancouver BC V6J 1T5",
    "addr:postcode":"v6j 1t5",
    "iso:country":"CA",
    "sg:city":"Vancouver",
    "sg:classifiers":[
        {
            "category":"Wholesale",
            "subcategory":"Durable Goods & Equipment",
            "type":"Manufacturing & Wholesale Goods"
        }
    ],
    "sg:phone":"+1 604 734 8885",
    "sg:postcode":"V6J 1T5",
    "sg:province":"BC",
    "sg:tags":[
        "room",
        "drafting"
    ],
    "wof:name":"Canadian Drafting & Eng Spls",
    "wof:placetype":"venue"
},
  "geometry": {"coordinates":[-123.139671326,49.2646713257],"type":"Point"}
}