{
  "type": "Feature",
  "properties": {
    "addr:full":"3437 Boul DE LA Grande-Allee Boisbriand QC J7H 1H5",
    "addr:housenumber":"3437",
    "addr:postcode":"j7h 1h5",
    "addr:street":"Boul De La Grande-Allee",
    "iso:country":"CA",
    "sg:address":"3437 Boul DE LA Grande-Allee",
    "sg:city":"Boisbriand",
    "sg:classifiers":[
        {
            "category":"Wholesale",
            "subcategory":"Hardware",
            "type":"Manufacturing & Wholesale Goods"
        }
    ],
    "sg:phone":"+1 450 434 1313",
    "sg:postcode":"J7H 1H5",
    "sg:province":"QC",
    "sg:tags":[
        "plumbing",
        "fixture",
        "supply"
    ],
    "wof:name":"Bmi Canada Inc",
    "wof:placetype":"venue"
},
  "geometry": {"coordinates":[-73.858322,45.628506],"type":"Point"}
}