{
  "type": "Feature",
  "properties": {
    "addr:full":"4040 Finch Ave E # 409 Scarborough ON M1S 4V5",
    "addr:housenumber":"4040",
    "addr:postcode":"m1s 4v5",
    "addr:street":"Finch Ave E # 409",
    "iso:country":"CA",
    "sg:address":"4040 Finch Ave E # 409",
    "sg:city":"Scarborough",
    "sg:classifiers":[
        {
            "category":"Health Services",
            "subcategory":"Doctor",
            "type":"Services"
        }
    ],
    "sg:phone":"+1 416 297 4807",
    "sg:postcode":"M1S 4V5",
    "sg:province":"ON",
    "sg:tags":[
        "physician",
        "surgeon"
    ],
    "wof:name":"Lo & Assoc",
    "wof:placetype":"venue"
},
  "geometry": {"coordinates":[-79.293976,43.802059],"type":"Point"}
}