{
  "type": "Feature",
  "properties": {
    "addr:full":"2915 54 Ave SE Calgary AB T2C 0A9",
    "addr:housenumber":"2915",
    "addr:postcode":"t2c 0a9",
    "addr:street":"54 Ave Se",
    "iso:country":"CA",
    "sg:address":"2915 54 Ave SE",
    "sg:city":"Calgary",
    "sg:classifiers":[
        {
            "category":"Manufacturing",
            "subcategory":"Metals",
            "type":"Manufacturing & Wholesale Goods"
        }
    ],
    "sg:phone":"+1 403 279 2622",
    "sg:postcode":"T2C 0A9",
    "sg:province":"AB",
    "sg:tags":[
        "steel"
    ],
    "wof:name":"Triangle Steel Ltd",
    "wof:placetype":"venue"
},
  "geometry": {"coordinates":[-113.99155399999999,51.005123],"type":"Point"}
}