{
  "type": "Feature",
  "properties": {
    "addr:full":"Surrey BC V3W 2V3",
    "addr:postcode":"v3w 2v3",
    "iso:country":"CA",
    "sg:city":"Surrey",
    "sg:classifiers":[
        {
            "category":"Retail",
            "subcategory":"Repair Shop",
            "type":"Services"
        }
    ],
    "sg:phone":"+1 604 572 0300",
    "sg:postcode":"V3W 2V3",
    "sg:province":"BC",
    "sg:tags":[
        "appliance"
    ],
    "wof:name":"D P Appliances",
    "wof:placetype":"venue"
},
  "geometry": {"coordinates":[-122.86792800000001,49.14106],"type":"Point"}
}