{
  "type": "Feature",
  "properties": {
    "addr:full":"1730 Steeles Ave E Brampton ON L6T 1A4",
    "addr:housenumber":"1730",
    "addr:postcode":"l6t 1a4",
    "addr:street":"Steeles Ave E",
    "iso:country":"CA",
    "sg:address":"1730 Steeles Ave E",
    "sg:city":"Brampton",
    "sg:classifiers":[
        {
            "category":"Manufacturing",
            "subcategory":"Furniture",
            "type":"Manufacturing & Wholesale Goods"
        }
    ],
    "sg:phone":"+1 905 790 6700",
    "sg:postcode":"L6T 1A4",
    "sg:province":"ON",
    "wof:name":"Noble Furniture Manufacturing",
    "wof:placetype":"venue"
},
  "geometry": {"coordinates":[-79.695061,43.700634],"type":"Point"}
}