{
  "type": "Feature",
  "properties": {
    "addr:full":"General Delivery St Lunaire-Griquet NL A0K 2X0",
    "iso:country":"CA",
    "sg:address":"General Delivery",
    "sg:city":"St Lunaire-Griquet",
    "sg:classifiers":[
        {
            "category":"Recreation",
            "type":"Entertainment"
        }
    ],
    "sg:phone":"+1 709 623 2357",
    "sg:postcode":"A0K 2X0",
    "sg:province":"NL",
    "sg:tags":[
        "youth",
        "information",
        "activity",
        "center",
        "organization"
    ],
    "wof:name":"Family Resource Ctr",
    "wof:placetype":"venue"
},
  "geometry": {"coordinates":[-55.483944,51.505058],"type":"Point"}
}