{
  "type": "Feature",
  "properties": {
    "iso:country":"CA",
    "sg:address":"149 Whiteacres Crt",
    "sg:city":"London",
    "sg:classifiers":[
        {
            "category":"Professional",
            "subcategory":"Business Services",
            "type":"Services"
        }
    ],
    "sg:phone":"+1 519 474 0911",
    "sg:postcode":"N6G 4N1",
    "sg:province":"ON",
    "sg:tags":[
        "arbitration"
    ],
    "wof:name":"Snow Arbitration & Mediation",
    "wof:placetype":"venue"
},
  "geometry": {"coordinates":[-81.3026428223,43.0104980469],"type":"Point"}
}