{
  "type": "Feature",
  "properties": {
    "addr:full":"General Delivery Pacquet NL A0K 3X0",
    "iso:country":"CA",
    "sg:address":"General Delivery",
    "sg:city":"Pacquet",
    "sg:classifiers":[
        {
            "category":"Food & Beverages",
            "subcategory":"Groceries & Convenience Stores",
            "type":"Retail Goods"
        }
    ],
    "sg:phone":"+1 709 251 3126",
    "sg:postcode":"A0K 3X0",
    "sg:province":"NL",
    "sg:tags":[
        "grocer"
    ],
    "wof:name":"H Norman & Sons",
    "wof:placetype":"venue"
},
  "geometry": {"coordinates":[-55.87746,49.987785],"type":"Point"}
}