{
  "type": "Feature",
  "properties": {
    "addr:full":"635 Mcdiarmid Dr Brandon MB R7B 2H6",
    "addr:housenumber":"635",
    "addr:postcode":"r7b 2h6",
    "addr:street":"Mcdiarmid Dr",
    "iso:country":"CA",
    "sg:address":"635 Mcdiarmid Dr",
    "sg:city":"Brandon",
    "sg:classifiers":[
        {
            "category":"Organizations",
            "subcategory":"Religious Organization",
            "type":"Services"
        }
    ],
    "sg:phone":"+1 204 728 2473",
    "sg:postcode":"R7B 2H6",
    "sg:province":"MB",
    "sg:tags":[
        "church"
    ],
    "wof:name":"Mc Diarmid Drive Alliance Chur",
    "wof:placetype":"venue"
},
  "geometry": {"coordinates":[-99.9762496948,49.8384742737],"type":"Point"}
}