{
  "type": "Feature",
  "properties": {
    "addr:full":"Red Deer AB T4R 2H2",
    "addr:postcode":"t4r 2h2",
    "iso:country":"CA",
    "sg:city":"Red Deer",
    "sg:classifiers":[
        {
            "category":"Food & Beverages",
            "subcategory":"Groceries & Convenience Stores",
            "type":"Retail Goods"
        }
    ],
    "sg:phone":"+1 403 343 6055",
    "sg:postcode":"T4R 2H2",
    "sg:province":"AB",
    "sg:tags":[
        "grocer"
    ],
    "wof:name":"Express 24 Foodmart",
    "wof:placetype":"venue"
},
  "geometry": {"coordinates":[-113.760002136,52.266040802],"type":"Point"}
}