{
  "type": "Feature",
  "properties": {
    "addr:full":"Winnipeg MB R2R 1T9",
    "addr:postcode":"r2r 1t9",
    "iso:country":"CA",
    "sg:city":"Winnipeg",
    "sg:classifiers":[
        {
            "category":"Retail",
            "subcategory":"Auto Repair",
            "type":"Services"
        }
    ],
    "sg:phone":"+1 204 633 2844",
    "sg:postcode":"R2R 1T9",
    "sg:province":"MB",
    "sg:tags":[
        "body",
        "automobile",
        "painting"
    ],
    "wof:name":"Weidmann Auto Body & Painting",
    "wof:placetype":"venue"
},
  "geometry": {"coordinates":[-97.218056,49.934582],"type":"Point"}
}