{
  "type": "Feature",
  "properties": {
    "iso:country":"CA",
    "sg:address":"161 Regal Rd",
    "sg:city":"Guelph",
    "sg:classifiers":[
        {
            "category":"Organizations",
            "subcategory":"Professional Association",
            "type":"Services"
        }
    ],
    "sg:phone":"+1 519 837 2934",
    "sg:postcode":"N1K 1E2",
    "sg:province":"ON",
    "wof:name":"Emergency Relief & Development",
    "wof:placetype":"venue"
},
  "geometry": {"coordinates":[-80.30471,43.552002],"type":"Point"}
}