{
  "type": "Feature",
  "properties": {
    "iso:country":"CA",
    "sg:address":"1701 Bloor St W",
    "sg:city":"Toronto",
    "sg:classifiers":[
        {
            "category":"Organizations",
            "subcategory":"Religious Organization",
            "type":"Services"
        }
    ],
    "sg:phone":"+1 416 762 1026",
    "sg:postcode":"M6P 1B1",
    "sg:province":"ON",
    "sg:tags":[
        "church"
    ],
    "wof:name":"St Joan of Arc Church",
    "wof:placetype":"venue"
},
  "geometry": {"coordinates":[-79.45840454099999,43.6549186707],"type":"Point"}
}