{
  "type": "Feature",
  "properties": {
    "iso:country":"CA",
    "sg:address":"1457 Main St S",
    "sg:city":"Dauphin",
    "sg:classifiers":[
        {
            "category":"Travel",
            "subcategory":"Hotels & Motels",
            "type":"Entertainment"
        }
    ],
    "sg:phone":"+1 204 638 0800",
    "sg:postcode":"R7N 3B3",
    "sg:province":"MB",
    "wof:name":"Super 8 Motel",
    "wof:placetype":"venue"
},
  "geometry": {"coordinates":[-100.06347700000001,51.134644],"type":"Point"}
}