{
  "type": "Feature",
  "properties": {
    "iso:country":"CA",
    "sg:address":"4160 Boul Thimens",
    "sg:city":"Saint-Laurent",
    "sg:classifiers":[
        {
            "category":"Wholesale",
            "subcategory":"Machinery & Supplies",
            "type":"Manufacturing & Wholesale Goods"
        }
    ],
    "sg:phone":"+1 514 331 0425",
    "sg:postcode":"H4R 2B9",
    "sg:province":"QC",
    "sg:tags":[
        "textile",
        "parts"
    ],
    "wof:name":"Vanguard Supreme Machine Corp",
    "wof:placetype":"venue"
},
  "geometry": {"coordinates":[-73.71701,45.493824],"type":"Point"}
}