{
  "type": "Feature",
  "properties": {
    "addr:full":"1295 Boul Saint-Joseph Drummondville QC J2C 2E2",
    "addr:housenumber":"1295",
    "addr:postcode":"j2c 2e2",
    "addr:street":"Boul Saint-Joseph",
    "iso:country":"CA",
    "sg:address":"1295 Boul Saint-Joseph",
    "sg:city":"Drummondville",
    "sg:classifiers":[
        {
            "category":"Autos & Motor Vehicles",
            "subcategory":"Automobile Sales",
            "type":"Retail Goods"
        }
    ],
    "sg:phone":"+1 819 477 5566",
    "sg:postcode":"J2C 2E2",
    "sg:province":"QC",
    "sg:tags":[
        "car",
        "dealer"
    ],
    "wof:name":"Mazda Drummondville",
    "wof:placetype":"venue"
},
  "geometry": {"coordinates":[-72.501732,45.885551],"type":"Point"}
}