{
  "type": "Feature",
  "properties": {
    "addr:full":"163 St. Paul St St Catharines ON L2R 3M5",
    "addr:housenumber":"163",
    "addr:postcode":"l2r 3m5",
    "addr:street":"St. Paul St",
    "iso:country":"CA",
    "sg:address":"163 St. Paul St",
    "sg:city":"St Catharines",
    "sg:classifiers":[
        {
            "category":"Shopping",
            "subcategory":"Tobacco",
            "type":"Retail Goods"
        }
    ],
    "sg:phone":"+1 905 684 7680",
    "sg:postcode":"L2R 3M5",
    "sg:province":"ON",
    "sg:tags":[
        "cigarette",
        "cigar",
        "dealer"
    ],
    "wof:name":"Spiritual Smoke",
    "wof:placetype":"venue"
},
  "geometry": {"coordinates":[-79.24464399999999,43.157692],"type":"Point"}
}