{
  "type": "Feature",
  "properties": {
    "addr:full":"PO Box 47 Cartwright NL A0K 1V0",
    "addr:housenumber":"po box 47",
    "addr:postcode":"a0k 1v0",
    "iso:country":"CA",
    "sg:address":"PO Box 47",
    "sg:city":"Cartwright",
    "sg:classifiers":[
        {
            "category":"Shopping",
            "subcategory":"Hobbies, Toys, & Games",
            "type":"Retail Goods"
        }
    ],
    "sg:phone":"+1 709 938 7518",
    "sg:postcode":"A0K 1V0",
    "sg:province":"NL",
    "sg:tags":[
        "craft",
        "supply"
    ],
    "wof:name":"Vicki's Craft Corner",
    "wof:placetype":"venue"
},
  "geometry": {"coordinates":[-57.017414,53.707478],"type":"Point"}
}