{
  "type": "Feature",
  "properties": {
    "addr:full":"390 Mcarthur Ave Vanier ON K1L 6N6",
    "addr:housenumber":"390",
    "addr:postcode":"k1l 6n6",
    "addr:street":"Mcarthur Ave",
    "iso:country":"CA",
    "sg:address":"390 Mcarthur Ave",
    "sg:city":"Vanier",
    "sg:classifiers":[
        {
            "category":"Shopping",
            "subcategory":"Pharmacy",
            "type":"Retail Goods"
        }
    ],
    "sg:phone":"+1 613 744 5800",
    "sg:postcode":"K1L 6N6",
    "sg:province":"ON",
    "wof:name":"Pharmacie LA Paix",
    "wof:placetype":"venue"
},
  "geometry": {"coordinates":[-75.6500244141,45.4319381714],"type":"Point"}
}