{
  "type": "Feature",
  "properties": {
    "iso:country":"CA",
    "sg:address":"3661 93 St NW",
    "sg:city":"Edmonton",
    "sg:classifiers":[
        {
            "category":"Wholesale",
            "subcategory":"Machinery & Supplies",
            "type":"Manufacturing & Wholesale Goods"
        }
    ],
    "sg:phone":"+1 780 436 4607",
    "sg:postcode":"T6E 6N6",
    "sg:province":"AB",
    "sg:tags":[
        "machine",
        "shop",
        "tool"
    ],
    "wof:name":"Martin Cutting Tools",
    "wof:placetype":"venue"
},
  "geometry": {"coordinates":[-113.473121643,53.4712142944],"type":"Point"}
}