{
  "type": "Feature",
  "properties": {
    "addr:full":"2633 Sweden Way Richmond BC V6V 2Z6",
    "addr:housenumber":"2633",
    "addr:postcode":"v6v 2z6",
    "addr:street":"Sweden Way",
    "iso:country":"CA",
    "sg:address":"2633 Sweden Way",
    "sg:city":"Richmond",
    "sg:classifiers":[
        {
            "category":"Home & Garden",
            "subcategory":"Furniture",
            "type":"Retail Goods"
        }
    ],
    "sg:phone":"+1 604 279 5532",
    "sg:postcode":"V6V 2Z6",
    "sg:province":"BC",
    "wof:name":"Sears Furniture Store",
    "wof:placetype":"venue"
},
  "geometry": {"coordinates":[-123.08252,49.194809],"type":"Point"}
}