{
  "type": "Feature",
  "properties": {
    "addr:full":"2175 Rue Saint-Patrick Montreal QC H3K 1B4",
    "addr:housenumber":"2175",
    "addr:postcode":"h3k 1b4",
    "addr:street":"Rue Saint-Patrick",
    "iso:country":"CA",
    "sg:address":"2175 Rue Saint-Patrick",
    "sg:city":"Montreal",
    "sg:classifiers":[
        {
            "category":"Government",
            "subcategory":"Office",
            "type":"Public Place"
        }
    ],
    "sg:phone":"+1 514 872 6426",
    "sg:postcode":"H3K 1B4",
    "sg:province":"QC",
    "wof:name":"Quebec Centre Local D'Emploi",
    "wof:placetype":"venue"
},
  "geometry": {"coordinates":[-73.5677719116,45.4827194214],"type":"Point"}
}