{
  "type": "Feature",
  "properties": {
    "addr:full":"Strathmore AB T1P 1M6",
    "addr:postcode":"t1p 1m6",
    "iso:country":"CA",
    "sg:city":"Strathmore",
    "sg:classifiers":[
        {
            "category":"Restaurant",
            "type":"Food & Drink"
        }
    ],
    "sg:phone":"+1 403 934 6469",
    "sg:postcode":"T1P 1M6",
    "sg:province":"AB",
    "wof:name":"Roadhouse Restaurant Ltd",
    "wof:placetype":"venue"
},
  "geometry": {"coordinates":[-113.400291443,51.0378913879],"type":"Point"}
}