{
  "type": "Feature",
  "properties": {
    "addr:full":"28 Talbot St Toronto ON M6N 1G4",
    "addr:housenumber":"28",
    "addr:postcode":"m6n 1g4",
    "addr:street":"Talbot St",
    "iso:country":"CA",
    "sg:address":"28 Talbot St",
    "sg:city":"Toronto",
    "sg:classifiers":[
        {
            "category":"Organizations",
            "subcategory":"Religious Organization",
            "type":"Services"
        }
    ],
    "sg:phone":"+1 416 733 8088",
    "sg:postcode":"M6N 1G4",
    "sg:province":"ON",
    "sg:tags":[
        "church"
    ],
    "wof:name":"North Toronto Chinese Baptist",
    "wof:placetype":"venue"
},
  "geometry": {"coordinates":[-79.456237793,43.6743087769],"type":"Point"}
}