{
  "type": "Feature",
  "properties": {
    "iso:country":"CA",
    "sg:address":"737 King St E",
    "sg:city":"Hamilton",
    "sg:classifiers":[
        {
            "category":"Travel",
            "subcategory":"Hotels & Motels",
            "type":"Entertainment"
        }
    ],
    "sg:phone":"+1 905 527 2708",
    "sg:postcode":"L8M 1A4",
    "sg:province":"ON",
    "wof:name":"Budget Motor Inn",
    "wof:placetype":"venue"
},
  "geometry": {"coordinates":[-79.846206665,43.25182724],"type":"Point"}
}