{
  "type": "Feature",
  "properties": {
    "iso:country":"CA",
    "sg:address":"1221 Rue Notre-Dame Est",
    "sg:city":"Sainte-Marthe-Du-Cap",
    "sg:classifiers":[
        {
            "category":"Retail",
            "subcategory":"Auto Repair",
            "type":"Services"
        }
    ],
    "sg:phone":"+1 819 374 6535",
    "sg:postcode":"G8T 4J8",
    "sg:province":"QC",
    "sg:tags":[
        "repairing",
        "automobile"
    ],
    "wof:name":"Multi-Mecanic Enr",
    "wof:placetype":"venue"
},
  "geometry": {"coordinates":[-72.488968,46.379292],"type":"Point"}
}