{
  "type": "Feature",
  "properties": {
    "addr:full":"Kingsville ON N9Y 2E5",
    "addr:postcode":"n9y 2e5",
    "iso:country":"CA",
    "sg:city":"Kingsville",
    "sg:classifiers":[
        {
            "category":"Museum",
            "type":"Entertainment"
        }
    ],
    "sg:phone":"+1 519 776 6909",
    "sg:postcode":"N9Y 2E5",
    "sg:province":"ON",
    "sg:tags":[
        "association"
    ],
    "wof:name":"Heritage Village",
    "wof:placetype":"venue"
},
  "geometry": {"coordinates":[-82.74031066889999,42.0378837585],"type":"Point"}
}