{
  "type": "Feature",
  "properties": {
    "addr:full":"Coteau-Du-Lac QC J0P 1B0",
    "addr:postcode":"j0p 1b0",
    "iso:country":"CA",
    "sg:city":"Coteau-Du-Lac",
    "sg:classifiers":[
        {
            "category":"Building & Trades",
            "subcategory":"Construction",
            "type":"Services"
        }
    ],
    "sg:phone":"+1 450 763 5517",
    "sg:postcode":"J0P 1B0",
    "sg:province":"QC",
    "sg:tags":[
        "contractor"
    ],
    "wof:name":"Construction Gilles Arsenault",
    "wof:placetype":"venue"
},
  "geometry": {"coordinates":[-74.180161,45.284531],"type":"Point"}
}