{
  "type": "Feature",
  "properties": {
    "addr:full":"18 Orchard View Blvd Oshawa ON L1G 3N7",
    "addr:housenumber":"18",
    "addr:postcode":"l1g 3n7",
    "addr:street":"Orchard View Blvd",
    "iso:country":"CA",
    "sg:address":"18 Orchard View Blvd",
    "sg:city":"Oshawa",
    "sg:classifiers":[
        {
            "category":"Building & Trades",
            "subcategory":"Landscaping Services",
            "type":"Services"
        }
    ],
    "sg:phone":"+1 905 571 4551",
    "sg:postcode":"L1G 3N7",
    "sg:province":"ON",
    "sg:tags":[
        "landscape",
        "contractor"
    ],
    "wof:name":"D & J Property Maintenance",
    "wof:placetype":"venue"
},
  "geometry": {"coordinates":[-78.878387,43.92902],"type":"Point"}
}