{
  "type": "Feature",
  "properties": {
    "iso:country":"CA",
    "sg:address":"2652 Danforth Ave",
    "sg:city":"Toronto",
    "sg:classifiers":[
        {
            "category":"Shopping",
            "type":"Retail Goods"
        }
    ],
    "sg:phone":"+1 416 691 3305",
    "sg:postcode":"M4C 1L7",
    "sg:province":"ON",
    "sg:tags":[
        "hearing",
        "equipment",
        "supply",
        "impaired"
    ],
    "wof:name":"Canada Hearing Ctr",
    "wof:placetype":"venue"
},
  "geometry": {"coordinates":[-79.299446106,43.6888122559],"type":"Point"}
}