{
  "type": "Feature",
  "properties": {
    "addr:full":"3498 Luxton Rd Victoria BC V9C 2Z5",
    "addr:housenumber":"3498",
    "addr:postcode":"bc v9c 2z5",
    "addr:street":"Luxton Rd",
    "iso:country":"CA",
    "sg:address":"3498 Luxton Rd",
    "sg:city":"Victoria",
    "sg:classifiers":[
        {
            "category":"Organizations",
            "subcategory":"Professional Association",
            "type":"Services"
        }
    ],
    "sg:phone":"+1 250 478 1369",
    "sg:postcode":"V9C 2Z5",
    "sg:province":"BC",
    "wof:name":"South Vancouver Island Rangers",
    "wof:placetype":"venue"
},
  "geometry": {"coordinates":[-123.377868652,48.4135093689],"type":"Point"}
}