{
  "type": "Feature",
  "properties": {
    "addr:full":"PO Box 149 Hines Creek AB T0H 2A0",
    "addr:housenumber":"po",
    "addr:postcode":"t0h 2a0",
    "addr:street":"Box 149 Hines",
    "iso:country":"CA",
    "sg:address":"PO Box 149",
    "sg:city":"Hines Creek",
    "sg:classifiers":[
        {
            "category":"Building & Trades",
            "subcategory":"Construction",
            "type":"Services"
        }
    ],
    "sg:phone":"+1 780 494 3838",
    "sg:postcode":"T0H 2A0",
    "sg:province":"AB",
    "sg:tags":[
        "general",
        "contractor"
    ],
    "wof:name":"Charles Dei Construction Ltd",
    "wof:placetype":"venue"
},
  "geometry": {"coordinates":[-118.60226400000001,56.247372],"type":"Point"}
}