{
  "type": "Feature",
  "properties": {
    "addr:full":"9 Chipstead Rd North York ON M3B 3E5",
    "addr:housenumber":"9",
    "addr:postcode":"m3b 3e5",
    "addr:street":"Chipstead Rd",
    "iso:country":"CA",
    "sg:address":"9 Chipstead Rd",
    "sg:city":"North York",
    "sg:classifiers":[
        {
            "category":"Building & Trades",
            "subcategory":"Construction",
            "type":"Services"
        }
    ],
    "sg:phone":"+1 416 449 5242",
    "sg:postcode":"M3B 3E5",
    "sg:province":"ON",
    "sg:tags":[
        "concrete"
    ],
    "wof:name":"Ontario Formwork CO",
    "wof:placetype":"venue"
},
  "geometry": {"coordinates":[-79.3718414307,43.7485618591],"type":"Point"}
}