{
  "type": "Feature",
  "properties": {
    "iso:country":"CA",
    "sg:city":"North York",
    "sg:classifiers":[
        {
            "category":"Home & Garden",
            "subcategory":"Building Materials",
            "type":"Retail Goods"
        }
    ],
    "sg:phone":"+1 416 650 5070",
    "sg:postcode":"M3J 3A8",
    "sg:province":"ON",
    "sg:tags":[
        "windows"
    ],
    "wof:name":"Euro Seal Windows",
    "wof:placetype":"venue"
},
  "geometry": {"coordinates":[-79.47979,43.784843],"type":"Point"}
}