{
  "type": "Feature",
  "properties": {
    "addr:full":"3516 Fulton Ave Smithers BC V0J 2N0",
    "addr:housenumber":"3516",
    "addr:postcode":"v0j 2n0",
    "addr:street":"Fulton Ave",
    "iso:country":"CA",
    "sg:address":"3516 Fulton Ave",
    "sg:city":"Smithers",
    "sg:classifiers":[
        {
            "category":"Manufacturing",
            "subcategory":"Building Materials",
            "type":"Manufacturing & Wholesale Goods"
        }
    ],
    "sg:phone":"+1 250 847 2117",
    "sg:postcode":"V0J 2N0",
    "sg:province":"BC",
    "sg:tags":[
        "truss"
    ],
    "wof:name":"Tricon",
    "wof:placetype":"venue"
},
  "geometry": {"coordinates":[-127.15888200000001,54.778481],"type":"Point"}
}