{
  "type": "Feature",
  "properties": {
    "addr:full":"607 Albert St Hudson Bay SK S0E 0Y0",
    "addr:housenumber":"607",
    "addr:postcode":"s0e 0y0",
    "addr:street":"Albert St",
    "iso:country":"CA",
    "sg:address":"607 Albert St",
    "sg:city":"Hudson Bay",
    "sg:classifiers":[
        {
            "category":"Health Services",
            "subcategory":"Doctor",
            "type":"Services"
        }
    ],
    "sg:phone":"+1 306 865 2238",
    "sg:postcode":"S0E 0Y0",
    "sg:province":"SK",
    "sg:tags":[
        "physician",
        "surgeon"
    ],
    "wof:name":"Hudson Bay Medical Group",
    "wof:placetype":"venue"
},
  "geometry": {"coordinates":[-102.386619568,52.8619194031],"type":"Point"}
}