{
  "type": "Feature",
  "properties": {
    "addr:full":"12002 Diamond View SE Calgary AB T2J 7B6",
    "addr:housenumber":"12002",
    "addr:postcode":"t2j 7b6",
    "addr:street":"Diamond;Se",
    "iso:country":"CA",
    "sg:address":"12002 Diamond View SE",
    "sg:city":"Calgary",
    "sg:classifiers":[
        {
            "category":"Building & Trades",
            "subcategory":"Construction",
            "type":"Services"
        }
    ],
    "sg:phone":"+1 403 271 6645",
    "sg:postcode":"T2J 7B6",
    "sg:province":"AB",
    "sg:tags":[
        "contractor"
    ],
    "wof:name":"Oak Manor Homes Ltd",
    "wof:placetype":"venue"
},
  "geometry": {"coordinates":[-114.024422,50.949425],"type":"Point"}
}