{
  "type": "Feature",
  "properties": {
    "addr:full":"180 Thompson Dr Thompson MB R8N 1Y8",
    "addr:housenumber":"180",
    "addr:postcode":"r8n 1y8",
    "addr:street":"Thompson Dr",
    "iso:country":"CA",
    "sg:address":"180 Thompson Dr",
    "sg:city":"Thompson",
    "sg:classifiers":[
        {
            "category":"Travel",
            "subcategory":"Hotels & Motels",
            "type":"Entertainment"
        }
    ],
    "sg:phone":"+1 204 778 5535",
    "sg:postcode":"R8N 1Y8",
    "sg:province":"MB",
    "wof:name":"Interior Inn",
    "wof:placetype":"venue"
},
  "geometry": {"coordinates":[-97.85994700000001,55.746094],"type":"Point"}
}