{
  "type": "Feature",
  "properties": {
    "iso:country":"CA",
    "sg:city":"Woodbridge",
    "sg:classifiers":[
        {
            "category":"Health Services",
            "subcategory":"Doctor",
            "type":"Services"
        }
    ],
    "sg:phone":"+1 905 851 1107",
    "sg:postcode":"L4L 2Z3",
    "sg:province":"ON",
    "sg:tags":[
        "dentist"
    ],
    "wof:name":"Woodbridge Dental Office",
    "wof:placetype":"venue"
},
  "geometry": {"coordinates":[-79.597244,43.779293],"type":"Point"}
}