{
  "type": "Feature",
  "properties": {
    "addr:full":"290 8E Av Dolbeau-Mistassini QC G8L 2W8",
    "addr:housenumber":"290",
    "addr:postcode":"g8l 2w8",
    "addr:street":"8E Av Dolbeau-Mistassini",
    "iso:country":"CA",
    "sg:address":"290 8E Av",
    "sg:city":"Dolbeau-Mistassini",
    "sg:classifiers":[
        {
            "category":"Real Estate",
            "subcategory":"Real Estate Agent",
            "type":"Services"
        }
    ],
    "sg:phone":"+1 418 276 6431",
    "sg:postcode":"G8L 2W8",
    "sg:province":"QC",
    "sg:tags":[
        "tool",
        "agency",
        "rental"
    ],
    "wof:name":"Location D'Outils Dolbeau Inc",
    "wof:placetype":"venue"
},
  "geometry": {"coordinates":[-72.234612,48.880569],"type":"Point"}
}