{
  "type": "Feature",
  "properties": {
    "addr:full":"Red Deer AB T4N 6H3",
    "addr:postcode":"t4n 6h3",
    "iso:country":"CA",
    "sg:city":"Red Deer",
    "sg:classifiers":[
        {
            "category":"Shopping",
            "subcategory":"Clothing, Apparel, & Fashions",
            "type":"Retail Goods"
        }
    ],
    "sg:phone":"+1 403 347 3192",
    "sg:postcode":"T4N 6H3",
    "sg:province":"AB",
    "wof:name":"Ricki's Bootlegger",
    "wof:placetype":"venue"
},
  "geometry": {"coordinates":[-113.801551819,52.2875099182],"type":"Point"}
}