{
  "type": "Feature",
  "properties": {
    "addr:full":"11411 Harris Rd Pitt Meadows BC V3Y 2M5",
    "addr:housenumber":"11411",
    "addr:postcode":"v3y 2m5",
    "addr:street":"Harris Rd",
    "iso:country":"CA",
    "sg:address":"11411 Harris Rd",
    "sg:city":"Pitt Meadows",
    "sg:classifiers":[
        {
            "category":"Manufacturing",
            "subcategory":"Building Materials",
            "type":"Manufacturing & Wholesale Goods"
        }
    ],
    "sg:phone":"+1 604 465 9106",
    "sg:postcode":"V3Y 2M5",
    "sg:province":"BC",
    "sg:tags":[
        "truss"
    ],
    "wof:name":"Maple Ridge Truss Ltd",
    "wof:placetype":"venue"
},
  "geometry": {"coordinates":[-122.689941406,49.2098999023],"type":"Point"}
}