{
  "type": "Feature",
  "properties": {
    "addr:full":"206 Wellington St Miramichi NB E1N 1M7",
    "addr:housenumber":"206",
    "addr:postcode":"e1n 1m7",
    "addr:street":"Wellington St",
    "iso:country":"CA",
    "sg:address":"206 Wellington St",
    "sg:city":"Miramichi",
    "sg:classifiers":[
        {
            "category":"Organizations",
            "subcategory":"Religious Organization",
            "type":"Services"
        }
    ],
    "sg:phone":"+1 506 773 7969",
    "sg:postcode":"E1N 1M7",
    "sg:province":"NB",
    "sg:tags":[
        "church"
    ],
    "wof:name":"Sunny Corner Presbyterian Ch",
    "wof:placetype":"venue"
},
  "geometry": {"coordinates":[-65.4644699097,47.0310783386],"type":"Point"}
}