{
  "type": "Feature",
  "properties": {
    "addr:full":"Landis SK S0K 2K0",
    "addr:postcode":"s0k 2k0",
    "iso:country":"CA",
    "sg:city":"Landis",
    "sg:classifiers":[
        {
            "category":"Manufacturing",
            "subcategory":"Chemicals & Compounds",
            "type":"Manufacturing & Wholesale Goods"
        }
    ],
    "sg:phone":"+1 306 658 2009",
    "sg:postcode":"S0K 2K0",
    "sg:province":"SK",
    "wof:name":"Millar Western Industries Ltd",
    "wof:placetype":"venue"
},
  "geometry": {"coordinates":[-108.455101013,52.1993103027],"type":"Point"}
}