{
  "type": "Feature",
  "properties": {
    "iso:country":"CA",
    "sg:address":"770 Barrydowne Rd",
    "sg:city":"Sudbury",
    "sg:classifiers":[
        {
            "category":"Autos & Motor Vehicles",
            "subcategory":"Auto Supplies",
            "type":"Retail Goods"
        }
    ],
    "sg:phone":"+1 705 566 0666",
    "sg:postcode":"P3A 3T7",
    "sg:province":"ON",
    "sg:tags":[
        "automobile",
        "dealer"
    ],
    "wof:name":"Duhamel & Dewar Tire Ctr",
    "wof:placetype":"venue"
},
  "geometry": {"coordinates":[-80.943962,46.513268],"type":"Point"}
}