{
  "type": "Feature",
  "properties": {
    "iso:country":"CA",
    "sg:city":"Longueuil",
    "sg:classifiers":[
        {
            "category":"Bars & Pubs",
            "type":"Food & Drink"
        }
    ],
    "sg:phone":"+1 450 670 6951",
    "sg:postcode":"J4K 2T4",
    "sg:province":"QC",
    "wof:name":"Brasserie Du Passant Inc",
    "wof:placetype":"venue"
},
  "geometry": {"coordinates":[-73.52253,45.525345],"type":"Point"}
}