{
  "type": "Feature",
  "properties": {
    "addr:full":"417 10 St NW Calgary AB T2N 1W1",
    "addr:housenumber":"10",
    "addr:postcode":"t2n 1w1",
    "addr:street":"417;St Nw",
    "iso:country":"CA",
    "sg:address":"417 10 St NW",
    "sg:city":"Calgary",
    "sg:classifiers":[
        {
            "category":"Banks & Credit Unions",
            "subcategory":"Bank",
            "type":"Services"
        }
    ],
    "sg:phone":"+1 403 292 2160",
    "sg:postcode":"T2N 1W1",
    "sg:province":"AB",
    "wof:name":"Royal Bank Financial Group",
    "wof:placetype":"venue"
},
  "geometry": {"coordinates":[-114.086181641,51.0562667847],"type":"Point"}
}