{
  "type": "Feature",
  "properties": {
    "addr:full":"Richmond BC V7C 1H8",
    "addr:postcode":"v7c 1h8",
    "iso:country":"CA",
    "sg:city":"Richmond",
    "sg:classifiers":[
        {
            "category":"Restaurant",
            "type":"Food & Drink"
        }
    ],
    "sg:phone":"+1 604 271 1117",
    "sg:postcode":"V7C 1H8",
    "sg:province":"BC",
    "wof:name":"Sushi Han",
    "wof:placetype":"venue"
},
  "geometry": {"coordinates":[-123.158401,49.155384],"type":"Point"}
}