{
  "type": "Feature",
  "properties": {
    "addr:full":"1680 Kildare Rd Windsor ON N8W 2W4",
    "addr:housenumber":"1680",
    "addr:postcode":"n8w 2w4",
    "addr:street":"Kildare Rd",
    "iso:country":"CA",
    "sg:address":"1680 Kildare Rd",
    "sg:city":"Windsor",
    "sg:classifiers":[
        {
            "category":"Manufacturing",
            "subcategory":"Tools & Machinery",
            "type":"Manufacturing & Wholesale Goods"
        }
    ],
    "sg:phone":"+1 519 258 2828",
    "sg:postcode":"N8W 2W4",
    "sg:province":"ON",
    "sg:tags":[
        "die",
        "maker"
    ],
    "wof:name":"Windsor Tool & Die",
    "wof:placetype":"venue"
},
  "geometry": {"coordinates":[-83.0015029907,42.3050231934],"type":"Point"}
}