{
  "type": "Feature",
  "properties": {
    "addr:full":"295 Wiltshire Pl Waterloo ON N2T 1R3",
    "addr:housenumber":"295",
    "addr:postcode":"n2t 1r3",
    "addr:street":"Wiltshire Pl",
    "iso:country":"CA",
    "sg:address":"295 Wiltshire Pl",
    "sg:city":"Waterloo",
    "sg:classifiers":[
        {
            "category":"Wholesale",
            "subcategory":"Office Equipment",
            "type":"Manufacturing & Wholesale Goods"
        }
    ],
    "sg:phone":"+1 519 746 4436",
    "sg:postcode":"N2T 1R3",
    "sg:province":"ON",
    "sg:tags":[
        "accounting",
        "bookkeeping",
        "system"
    ],
    "wof:name":"Jobanputra Financial Svc",
    "wof:placetype":"venue"
},
  "geometry": {"coordinates":[-80.564438,43.46352],"type":"Point"}
}