{
  "type": "Feature",
  "properties": {
    "addr:full":"6814 Harbour St Fitzroy Harbour ON K0A 1X0",
    "addr:housenumber":"6814",
    "addr:postcode":"k0a 1x0",
    "addr:street":"Harbour St",
    "iso:country":"CA",
    "sg:address":"6814 Harbour St",
    "sg:city":"Fitzroy Harbour",
    "sg:classifiers":[
        {
            "category":"Food & Beverages",
            "subcategory":"Candy",
            "type":"Retail Goods"
        }
    ],
    "sg:phone":"+1 613 623 7679",
    "sg:postcode":"K0A 1X0",
    "sg:province":"ON",
    "sg:tags":[
        "confectionery"
    ],
    "wof:name":"Penny's Fudge Factory",
    "wof:placetype":"venue"
},
  "geometry": {"coordinates":[-76.2124862671,45.4666481018],"type":"Point"}
}