{
  "type": "Feature",
  "properties": {
    "iso:country":"CA",
    "sg:address":"2675 Yukon St",
    "sg:city":"Vancouver",
    "sg:classifiers":[
        {
            "category":"Government",
            "subcategory":"Office",
            "type":"Public Place"
        }
    ],
    "sg:phone":"+1 604 873 7556",
    "sg:postcode":"V5Y 3P9",
    "sg:province":"BC",
    "sg:tags":[
        "village"
    ],
    "wof:name":"Vancouver Strata Title Inqrs",
    "wof:placetype":"venue"
},
  "geometry": {"coordinates":[-123.113204956,49.2616539001],"type":"Point"}
}