{
  "type": "Feature",
  "properties": {
    "iso:country":"CA",
    "sg:address":"12252 Industrial Rd",
    "sg:city":"Surrey",
    "sg:classifiers":[
        {
            "category":"Freight",
            "type":"Transportation"
        }
    ],
    "sg:phone":"+1 604 580 2215",
    "sg:postcode":"V3V 3S2",
    "sg:province":"BC",
    "sg:tags":[
        "crane",
        "trucking"
    ],
    "wof:name":"Metro Crane & Transfer Ltd",
    "wof:placetype":"venue"
},
  "geometry": {"coordinates":[-122.882507324,49.2086372375],"type":"Point"}
}