{
  "type": "Feature",
  "properties": {
    "addr:full":"North Vancouver BC V7L 1A4",
    "addr:postcode":"v7l 1a4",
    "iso:country":"CA",
    "sg:city":"North Vancouver",
    "sg:classifiers":[
        {
            "category":"Real Estate",
            "subcategory":"Architect",
            "type":"Services"
        }
    ],
    "sg:phone":"+1 604 983 3125",
    "sg:postcode":"V7L 1A4",
    "sg:province":"BC",
    "wof:name":"Ernest Collins Inc",
    "wof:placetype":"venue"
},
  "geometry": {"coordinates":[-123.072639,49.308277],"type":"Point"}
}