{
  "type": "Feature",
  "properties": {
    "addr:full":"2 Vanguard Crt St. John's NL A1B 3N9",
    "addr:housenumber":"2",
    "addr:postcode":"a1b 3n9",
    "addr:street":"Vanguard Crt",
    "iso:country":"CA",
    "sg:address":"2 Vanguard Crt",
    "sg:city":"St. John's",
    "sg:classifiers":[
        {
            "category":"Building & Trades",
            "subcategory":"Electrical",
            "type":"Services"
        }
    ],
    "sg:phone":"+1 709 754 0101",
    "sg:postcode":"A1B 3N9",
    "sg:province":"NL",
    "sg:tags":[
        "electric",
        "contractor"
    ],
    "wof:name":"Harvey Electric Ltd",
    "wof:placetype":"venue"
},
  "geometry": {"coordinates":[-52.739922,47.60693],"type":"Point"}
}