{
  "type": "Feature",
  "properties": {
    "addr:full":"Edmonton AB T5J 0B3",
    "addr:postcode":"t5j 0b3",
    "iso:country":"CA",
    "sg:city":"Edmonton",
    "sg:classifiers":[
        {
            "category":"Government",
            "subcategory":"Office",
            "type":"Public Place"
        }
    ],
    "sg:phone":"+1 780 427 3390",
    "sg:postcode":"T5J 0B3",
    "sg:province":"AB",
    "wof:name":"Alberta Emergency Social Svc",
    "wof:placetype":"venue"
},
  "geometry": {"coordinates":[-113.50341,53.538605],"type":"Point"}
}