{
  "type": "Feature",
  "properties": {
    "addr:full":"2817 Spring St Port Moody BC V3H 4C6",
    "addr:housenumber":"2817",
    "addr:postcode":"v3h 4c6",
    "addr:street":"Spring St",
    "iso:country":"CA",
    "sg:address":"2817 Spring St",
    "sg:city":"Port Moody",
    "sg:classifiers":[
        {
            "category":"Building & Trades",
            "subcategory":"Electrical",
            "type":"Services"
        }
    ],
    "sg:phone":"+1 604 931 8324",
    "sg:postcode":"V3H 4C6",
    "sg:province":"BC",
    "sg:tags":[
        "electric",
        "contractor"
    ],
    "wof:name":"Tri-Tech Electrical Svc",
    "wof:placetype":"venue"
},
  "geometry": {"coordinates":[-122.849632,49.277119],"type":"Point"}
}