{
  "type": "Feature",
  "properties": {
    "addr:full":"563 Av Des Oblats Quebec QC G1N 1V8",
    "addr:postcode":"g1n 1v8",
    "addr:street":"563 Av Des Oblats",
    "iso:country":"CA",
    "sg:address":"563 Av Des Oblats",
    "sg:city":"Quebec",
    "sg:classifiers":[
        {
            "category":"Retail",
            "subcategory":"Auto Repair",
            "type":"Services"
        }
    ],
    "sg:phone":"+1 418 641 1469",
    "sg:postcode":"G1N 1V8",
    "sg:province":"QC",
    "sg:tags":[
        "body",
        "automobile",
        "painting"
    ],
    "wof:name":"Carrossier Gmp Inc",
    "wof:placetype":"venue"
},
  "geometry": {"coordinates":[-71.24017333979999,46.8085823059],"type":"Point"}
}