{
  "type": "Feature",
  "properties": {
    "addr:full":"6001 Rue Saint-Hubert Montreal QC H2S 2L8",
    "addr:housenumber":"6001",
    "addr:postcode":"h2s 2l8",
    "addr:street":"Rue Saint-Hubert",
    "iso:country":"CA",
    "sg:address":"6001 Rue Saint-Hubert",
    "sg:city":"Montreal",
    "sg:classifiers":[
        {
            "category":"Home & Garden",
            "subcategory":"Home Furnishings",
            "type":"Retail Goods"
        }
    ],
    "sg:phone":"+1 514 278 2650",
    "sg:postcode":"H2S 2L8",
    "sg:province":"QC",
    "sg:tags":[
        "willow",
        "rattan",
        "reed"
    ],
    "wof:name":"Oriental Rattan Canada",
    "wof:placetype":"venue"
},
  "geometry": {"coordinates":[-73.5981292725,45.5340499878],"type":"Point"}
}