{
  "type": "Feature",
  "properties": {
    "addr:full":"88 South St W Aylmer ON N5H 1R4",
    "addr:housenumber":"88",
    "addr:postcode":"n5h 1r4",
    "addr:street":"South St W",
    "iso:country":"CA",
    "sg:address":"88 South St W",
    "sg:city":"Aylmer",
    "sg:classifiers":[
        {
            "category":"Building & Trades",
            "subcategory":"Construction",
            "type":"Services"
        }
    ],
    "sg:phone":"+1 519 773 9740",
    "sg:postcode":"N5H 1R4",
    "sg:province":"ON",
    "sg:tags":[
        "roofing",
        "contractor"
    ],
    "wof:name":"Milmine Painting & Roofing",
    "wof:placetype":"venue"
},
  "geometry": {"coordinates":[-80.98835,42.770161],"type":"Point"}
}