{
  "type": "Feature",
  "properties": {
    "iso:country":"CA",
    "sg:city":"Mississauga",
    "sg:classifiers":[
        {
            "category":"Building & Trades",
            "subcategory":"Construction",
            "type":"Services"
        }
    ],
    "sg:phone":"+1 905 405 9116",
    "sg:postcode":"L4V 1X1",
    "sg:province":"ON",
    "sg:tags":[
        "general",
        "contractor"
    ],
    "wof:name":"Laurin & CO",
    "wof:placetype":"venue"
},
  "geometry": {"coordinates":[-79.6193847656,43.7018318176],"type":"Point"}
}