{
  "type": "Feature",
  "properties": {
    "iso:country":"CA",
    "sg:address":"210 Stanley St",
    "sg:city":"Cupar",
    "sg:classifiers":[
        {
            "category":"Professional",
            "subcategory":"Lawyer & Legal Services",
            "type":"Services"
        }
    ],
    "sg:phone":"+1 306 723 4213",
    "sg:postcode":"S0G 0Y0",
    "sg:province":"SK",
    "sg:tags":[
        "attorney"
    ],
    "wof:name":"Pederson Norman Mc Leod & Todd",
    "wof:placetype":"venue"
},
  "geometry": {"coordinates":[-104.211624145,50.9502906799],"type":"Point"}
}