{
  "type": "Feature",
  "properties": {
    "addr:full":"222 Speedvale Ave E Guelph ON N1E 1M7",
    "addr:housenumber":"222",
    "addr:postcode":"n1e 1m7",
    "addr:street":"Speedvale Ave E",
    "iso:country":"CA",
    "sg:address":"222 Speedvale Ave E",
    "sg:city":"Guelph",
    "sg:classifiers":[
        {
            "category":"Insurance",
            "subcategory":"Insurance Agent",
            "type":"Services"
        }
    ],
    "sg:phone":"+1 519 824 4610",
    "sg:postcode":"N1E 1M7",
    "sg:province":"ON",
    "wof:name":"Carter Insurance Group",
    "wof:placetype":"venue"
},
  "geometry": {"coordinates":[-80.2627487183,43.5626182556],"type":"Point"}
}