{
  "type": "Feature",
  "properties": {
    "addr:full":"14380 Greencrest Dr Surrey BC V4P 1M1",
    "addr:housenumber":"14380",
    "addr:postcode":"v4p 1m1",
    "addr:street":"Greencrest Dr",
    "iso:country":"CA",
    "sg:address":"14380 Greencrest Dr",
    "sg:city":"Surrey",
    "sg:classifiers":[
        {
            "category":"Organizations",
            "subcategory":"Religious Organization",
            "type":"Services"
        }
    ],
    "sg:phone":"+1 604 535 3910",
    "sg:postcode":"V4P 1M1",
    "sg:province":"BC",
    "sg:tags":[
        "church"
    ],
    "wof:name":"White Rock Flshp Baptist Ch",
    "wof:placetype":"venue"
},
  "geometry": {"coordinates":[-122.824752808,49.0664215088],"type":"Point"}
}