{
  "type": "Feature",
  "properties": {
    "addr:full":"220 133 Rte Sabrevois QC J0J 2G0",
    "addr:housenumber":"133",
    "addr:postcode":"j0j 2g0",
    "addr:street":"Rte Sabrevois",
    "iso:country":"CA",
    "sg:address":"220 133 Rte",
    "sg:city":"Sabrevois",
    "sg:classifiers":[
        {
            "category":"Wholesale",
            "subcategory":"Home Furnishings",
            "type":"Manufacturing & Wholesale Goods"
        }
    ],
    "sg:phone":"+1 450 358 2780",
    "sg:postcode":"J0J 2G0",
    "sg:province":"QC",
    "sg:tags":[
        "carpet",
        "dealer",
        "rug"
    ],
    "wof:name":"Tapis Richelieu Linoleums Inc",
    "wof:placetype":"venue"
},
  "geometry": {"coordinates":[-73.2304992676,45.2063903809],"type":"Point"}
}