{
  "type": "Feature",
  "properties": {
    "addr:full":"81 Place Desjardins Victoriaville QC G6P 9C6",
    "addr:housenumber":"81",
    "addr:postcode":"g6p 9c6",
    "addr:street":"Place Desjardins",
    "iso:country":"CA",
    "sg:address":"81 Place Desjardins",
    "sg:city":"Victoriaville",
    "sg:classifiers":[
        {
            "category":"Education",
            "subcategory":"Special Training",
            "type":"Public Place"
        }
    ],
    "sg:phone":"+1 819 752 9317",
    "sg:postcode":"G6P 9C6",
    "sg:province":"QC",
    "sg:tags":[
        "dressmaker",
        "tutoring"
    ],
    "wof:name":"St-Cyr, Nicole",
    "wof:placetype":"venue"
},
  "geometry": {"coordinates":[-71.9521331787,46.0674133301],"type":"Point"}
}