{
  "type": "Feature",
  "properties": {
    "addr:full":"1357 Powell St Vancouver BC V5L 1G8",
    "addr:housenumber":"1357",
    "addr:postcode":"v5l 1g8",
    "addr:street":"Powell St",
    "iso:country":"CA",
    "sg:address":"1357 Powell St",
    "sg:city":"Vancouver",
    "sg:classifiers":[
        {
            "category":"Wholesale",
            "subcategory":"Apparel",
            "type":"Manufacturing & Wholesale Goods"
        }
    ],
    "sg:phone":"+1 604 253 1955",
    "sg:postcode":"V5L 1G8",
    "sg:province":"BC",
    "sg:tags":[
        "woolen",
        "worsted",
        "fabric"
    ],
    "wof:name":"Fraser & Kirkbright Weaving CO",
    "wof:placetype":"venue"
},
  "geometry": {"coordinates":[-123.075965881,49.2833213806],"type":"Point"}
}