{
  "type": "Feature",
  "properties": {
    "iso:country":"CA",
    "sg:address":"16628 Boul Pierrefonds",
    "sg:city":"Sainte-Genevieve",
    "sg:classifiers":[
        {
            "category":"Retail",
            "subcategory":"Veterinary Services",
            "type":"Services"
        }
    ],
    "sg:phone":"+1 514 626 9890",
    "sg:postcode":"H9H 1H1",
    "sg:province":"QC",
    "sg:tags":[
        "veterinarian"
    ],
    "wof:name":"Masse, A M DVM",
    "wof:placetype":"venue"
},
  "geometry": {"coordinates":[-73.872337,45.473133],"type":"Point"}
}