{
  "type": "Feature",
  "properties": {
    "iso:country":"CA",
    "sg:city":"Mont-Royal",
    "sg:classifiers":[
        {
            "category":"Building & Trades",
            "subcategory":"Plumbing",
            "type":"Services"
        }
    ],
    "sg:phone":"+1 514 739 1921",
    "sg:postcode":"H4N 2P7",
    "sg:province":"QC",
    "sg:tags":[
        "balancing",
        "air"
    ],
    "wof:name":"Hydrauliques R & O Svc",
    "wof:placetype":"venue"
},
  "geometry": {"coordinates":[-73.663696,45.505585],"type":"Point"}
}