{
  "type": "Feature",
  "properties": {
    "addr:full":"Saskatoon SK S7H 5H9",
    "addr:postcode":"s7h 5h9",
    "iso:country":"CA",
    "sg:city":"Saskatoon",
    "sg:classifiers":[
        {
            "category":"Banks & Credit Unions",
            "subcategory":"Investment Brokerage",
            "type":"Services"
        }
    ],
    "sg:phone":"+1 306 477 5770",
    "sg:postcode":"S7H 5H9",
    "sg:province":"SK",
    "sg:tags":[
        "consultant",
        "planning",
        "financial"
    ],
    "wof:name":"Targeted Strategies Ltd",
    "wof:placetype":"venue"
},
  "geometry": {"coordinates":[-106.59765625,52.104183197],"type":"Point"}
}