{
  "type": "Feature",
  "properties": {
    "iso:country":"CA",
    "sg:address":"35 Macdonell Ave",
    "sg:city":"Toronto",
    "sg:classifiers":[
        {
            "category":"Wholesale",
            "subcategory":"Construction Materials",
            "type":"Manufacturing & Wholesale Goods"
        }
    ],
    "sg:phone":"+1 416 588 1205",
    "sg:postcode":"M6R 2A3",
    "sg:province":"ON",
    "sg:tags":[
        "fence"
    ],
    "wof:name":"Mountain West Canada",
    "wof:placetype":"venue"
},
  "geometry": {"coordinates":[-79.4381484985,43.6414375305],"type":"Point"}
}