{
  "type": "Feature",
  "properties": {
    "addr:full":"314 Johnson St Kingston ON K7L 1Y7",
    "addr:housenumber":"314",
    "addr:postcode":"k7l 1y7",
    "addr:street":"Johnson St",
    "iso:country":"CA",
    "sg:address":"314 Johnson St",
    "sg:city":"Kingston",
    "sg:classifiers":[
        {
            "category":"Organizations",
            "subcategory":"Religious Organization",
            "type":"Services"
        }
    ],
    "sg:phone":"+1 613 542 2990",
    "sg:postcode":"K7L 1Y7",
    "sg:province":"ON",
    "sg:tags":[
        "church"
    ],
    "wof:name":"Bethel Church",
    "wof:placetype":"venue"
},
  "geometry": {"coordinates":[-76.4918136597,44.2309341431],"type":"Point"}
}