{
  "type": "Feature",
  "properties": {
    "addr:full":"7551 Westminster Hwy Richmond BC V6X 1A3",
    "addr:housenumber":"7551",
    "addr:postcode":"v6x 1a3",
    "addr:street":"Westminster Hwy",
    "iso:country":"CA",
    "sg:address":"7551 Westminster Hwy",
    "sg:city":"Richmond",
    "sg:classifiers":[
        {
            "category":"Bars & Pubs",
            "type":"Food & Drink"
        }
    ],
    "sg:phone":"+1 604 273 7878",
    "sg:postcode":"V6X 1A3",
    "sg:province":"BC",
    "wof:name":"Thirsty Turtle Bar & Grill",
    "wof:placetype":"venue"
},
  "geometry": {"coordinates":[-123.14144899999999,49.170349],"type":"Point"}
}