{
  "type": "Feature",
  "properties": {
    "addr:full":"1988 Boul Rosemont Montreal QC H2G 1S8",
    "addr:housenumber":"1988",
    "addr:postcode":"h2g 1s8",
    "addr:street":"Boul Rosemont",
    "iso:country":"CA",
    "sg:address":"1988 Boul Rosemont",
    "sg:city":"Montreal",
    "sg:classifiers":[
        {
            "category":"Food & Beverages",
            "subcategory":"Groceries & Convenience Stores",
            "type":"Retail Goods"
        }
    ],
    "sg:phone":"+1 514 270 4926",
    "sg:postcode":"H2G 1S8",
    "sg:province":"QC",
    "wof:name":"Depanneur Boni-Mag Enr",
    "wof:placetype":"venue"
},
  "geometry": {"coordinates":[-73.589752,45.542217],"type":"Point"}
}