{
  "type": "Feature",
  "properties": {
    "addr:full":"12 Byrnes Lane Torbay NL A1K 1H2",
    "addr:housenumber":"12",
    "addr:postcode":"a1k 1h2",
    "addr:street":"Byrnes Lane",
    "iso:country":"CA",
    "sg:address":"12 Byrnes Lane",
    "sg:city":"Torbay",
    "sg:classifiers":[
        {
            "category":"Home & Garden",
            "subcategory":"Garden Supply",
            "type":"Retail Goods"
        }
    ],
    "sg:phone":"+1 709 437 5539",
    "sg:postcode":"A1K 1H2",
    "sg:province":"NL",
    "sg:tags":[
        "nurseryman"
    ],
    "wof:name":"Traverse Gardens Plant Nursery",
    "wof:placetype":"venue"
},
  "geometry": {"coordinates":[-52.7304878235,47.6780776978],"type":"Point"}
}