{
  "type": "Feature",
  "properties": {
    "addr:full":"491 Rue Leonard Sainte-Agathe-Des-Monts QC J8C 2Y5",
    "addr:housenumber":"491",
    "addr:postcode":"j8c 2y5",
    "addr:street":"Rue Leonard",
    "iso:country":"CA",
    "sg:address":"491 Rue Leonard",
    "sg:city":"Sainte-Agathe-Des-Monts",
    "sg:classifiers":[
        {
            "category":"Retail",
            "subcategory":"Auto Repair",
            "type":"Services"
        }
    ],
    "sg:phone":"+1 819 326 5125",
    "sg:postcode":"J8C 2Y5",
    "sg:province":"QC",
    "sg:tags":[
        "transmission",
        "automobile",
        "repairing"
    ],
    "wof:name":"Transmission Ste-Agathe Inc",
    "wof:placetype":"venue"
},
  "geometry": {"coordinates":[-74.26996612550001,46.0428466797],"type":"Point"}
}