{
  "type": "Feature",
  "properties": {
    "iso:country":"CA",
    "sg:address":"3961 Boul Saint-Laurent",
    "sg:city":"Montreal",
    "sg:classifiers":[
        {
            "category":"Restaurant",
            "type":"Food & Drink"
        }
    ],
    "sg:phone":"+1 514 845 3509",
    "sg:postcode":"H2W 1Y4",
    "sg:province":"QC",
    "wof:name":"Moishe's Steak House",
    "wof:placetype":"venue"
},
  "geometry": {"coordinates":[-73.5782318115,45.516544342],"type":"Point"}
}