{
  "type": "Feature",
  "properties": {
    "addr:full":"8015 Wagner Rd NW Edmonton AB T6E 4N6",
    "addr:housenumber":"8015",
    "addr:postcode":"t6e 4n6",
    "addr:street":"Wagner Rd Nw",
    "iso:country":"CA",
    "sg:address":"8015 Wagner Rd NW",
    "sg:city":"Edmonton",
    "sg:classifiers":[
        {
            "category":"Restaurant",
            "type":"Food & Drink"
        }
    ],
    "sg:phone":"+1 780 466 1754",
    "sg:postcode":"T6E 4N6",
    "sg:province":"AB",
    "wof:name":"Sunrise Cafe",
    "wof:placetype":"venue"
},
  "geometry": {"coordinates":[-113.44995880099999,53.4987182617],"type":"Point"}
}