{
  "type": "Feature",
  "properties": {
    "addr:full":"260 Park Row Woodstock ON N4S 1W3",
    "addr:housenumber":"260",
    "addr:postcode":"n4s 1w3",
    "addr:street":"Park Row",
    "iso:country":"CA",
    "sg:address":"260 Park Row",
    "sg:city":"Woodstock",
    "sg:classifiers":[
        {
            "category":"Manufacturing",
            "subcategory":"Signs",
            "type":"Manufacturing & Wholesale Goods"
        }
    ],
    "sg:phone":"+1 519 539 8262",
    "sg:postcode":"N4S 1W3",
    "sg:province":"ON",
    "wof:name":"Horizon Signs",
    "wof:placetype":"venue"
},
  "geometry": {"coordinates":[-80.76532,43.124802],"type":"Point"}
}