{
  "type": "Feature",
  "properties": {
    "iso:country":"CA",
    "sg:address":"699 Old Black River Rd",
    "sg:city":"Saint John",
    "sg:classifiers":[
        {
            "category":"Manufacturing",
            "subcategory":"Tools & Machinery",
            "type":"Manufacturing & Wholesale Goods"
        }
    ],
    "sg:phone":"+1 506 633 6840",
    "sg:postcode":"E2J 4S8",
    "sg:province":"NB",
    "sg:tags":[
        "alternator",
        "automobile",
        "parts"
    ],
    "wof:name":"Wrecks Unlimited",
    "wof:placetype":"venue"
},
  "geometry": {"coordinates":[-65.9831237793,45.2700386047],"type":"Point"}
}