{
  "type": "Feature",
  "properties": {
    "addr:full":"Saint-Theodore-D'Acton QC J0H 1Z0",
    "addr:postcode":"j0h 1z0",
    "iso:country":"CA",
    "sg:city":"Saint-Theodore-D'Acton",
    "sg:classifiers":[
        {
            "category":"Manufacturing",
            "subcategory":"Toys & Sporting Goods",
            "type":"Manufacturing & Wholesale Goods"
        }
    ],
    "sg:phone":"+1 450 546 7148",
    "sg:postcode":"J0H 1Z0",
    "sg:province":"QC",
    "sg:tags":[
        "handicraft"
    ],
    "wof:name":"Atelier Es Arts Inc",
    "wof:placetype":"venue"
},
  "geometry": {"coordinates":[-72.5227508545,45.6212692261],"type":"Point"}
}