{
  "type": "Feature",
  "properties": {
    "addr:full":"19971 38A Ave Langley BC V3A 2V1",
    "addr:housenumber":"19971",
    "addr:postcode":"v3a 2v1",
    "addr:street":"38A Ave",
    "iso:country":"CA",
    "sg:address":"19971 38A Ave",
    "sg:city":"Langley",
    "sg:classifiers":[
        {
            "category":"Shopping",
            "subcategory":"Clothing, Apparel, & Fashions",
            "type":"Retail Goods"
        }
    ],
    "sg:phone":"+1 604 530 3886",
    "sg:postcode":"V3A 2V1",
    "sg:province":"BC",
    "sg:tags":[
        "shop",
        "bridal"
    ],
    "wof:name":"Angelic Visions",
    "wof:placetype":"venue"
},
  "geometry": {"coordinates":[-122.65657,49.104122],"type":"Point"}
}