{
  "type": "Feature",
  "properties": {
    "addr:full":"4914 Rue Sherbrooke O Westmount QC H3Z 1H3",
    "addr:housenumber":"4914",
    "addr:postcode":"h3z 1h3",
    "addr:street":"Rue Sherbrooke O",
    "iso:country":"CA",
    "sg:address":"4914 Rue Sherbrooke O",
    "sg:city":"Westmount",
    "sg:classifiers":[
        {
            "category":"Communications",
            "subcategory":"Film & Video Production",
            "type":"Services"
        }
    ],
    "sg:phone":"+1 514 484 4416",
    "sg:postcode":"H3Z 1H3",
    "sg:province":"QC",
    "sg:tags":[
        "consultant",
        "audio"
    ],
    "wof:name":"Environnement Electronique",
    "wof:placetype":"venue"
},
  "geometry": {"coordinates":[-73.604355,45.477966],"type":"Point"}
}