{
  "type": "Feature",
  "properties": {
    "addr:full":"5 Sulkara Crt North York ON M4A 2G8",
    "addr:housenumber":"5",
    "addr:postcode":"m4a 2g8",
    "addr:street":"Sulkara Crt",
    "iso:country":"CA",
    "sg:address":"5 Sulkara Crt",
    "sg:city":"North York",
    "sg:classifiers":[
        {
            "category":"Building & Trades",
            "subcategory":"Electrical",
            "type":"Services"
        }
    ],
    "sg:phone":"+1 416 466 9939",
    "sg:postcode":"M4A 2G8",
    "sg:province":"ON",
    "sg:tags":[
        "electric",
        "contractor"
    ],
    "wof:name":"Albright Electric CO Ltd",
    "wof:placetype":"venue"
},
  "geometry": {"coordinates":[-79.32316589360001,43.7323188782],"type":"Point"}
}