{
  "type": "Feature",
  "properties": {
    "addr:full":"136 2nd St Weyburn SK S4H 0T8",
    "addr:housenumber":"136",
    "addr:postcode":"s4h 0t8",
    "addr:street":"2Nd St",
    "iso:country":"CA",
    "sg:address":"136 2nd St",
    "sg:city":"Weyburn",
    "sg:classifiers":[
        {
            "category":"Organizations",
            "subcategory":"Religious Organization",
            "type":"Services"
        }
    ],
    "sg:phone":"+1 306 842 3544",
    "sg:postcode":"S4H 0T8",
    "sg:province":"SK",
    "sg:tags":[
        "church"
    ],
    "wof:name":"Presbyterian Church",
    "wof:placetype":"venue"
},
  "geometry": {"coordinates":[-103.854766846,49.6624031067],"type":"Point"}
}