{
  "type": "Feature",
  "properties": {
    "iso:country":"CA",
    "sg:city":"Trois-Rivieres",
    "sg:classifiers":[
        {
            "category":"Social Services",
            "type":"Services"
        }
    ],
    "sg:phone":"+1 819 373 2598",
    "sg:postcode":"G9A 3X6",
    "sg:province":"QC",
    "sg:tags":[
        "organization",
        "welfare"
    ],
    "wof:name":"Comite DE Solidarite Tiers",
    "wof:placetype":"venue"
},
  "geometry": {"coordinates":[-72.5450210571,46.3401603699],"type":"Point"}
}