{
  "type": "Feature",
  "properties": {
    "iso:country":"CA",
    "sg:address":"2081 Logan Ave",
    "sg:city":"Winnipeg",
    "sg:classifiers":[
        {
            "category":"Wholesale",
            "subcategory":"Metals & Minerals",
            "type":"Manufacturing & Wholesale Goods"
        }
    ],
    "sg:phone":"+1 204 633 3111",
    "sg:postcode":"R2R 0J1",
    "sg:province":"MB",
    "sg:tags":[
        "pipe",
        "drain"
    ],
    "wof:name":"Ipex Inc",
    "wof:placetype":"venue"
},
  "geometry": {"coordinates":[-97.210434,49.925781],"type":"Point"}
}