{
  "type": "Feature",
  "properties": {
    "addr:full":"2325 54th Ave E Vancouver BC V5S 1X1",
    "addr:housenumber":"2325",
    "addr:postcode":"v5s 1x1",
    "addr:street":"54Th Ave E",
    "iso:country":"CA",
    "sg:address":"2325 54th Ave E",
    "sg:city":"Vancouver",
    "sg:classifiers":[
        {
            "category":"Organizations",
            "subcategory":"Religious Organization",
            "type":"Services"
        }
    ],
    "sg:phone":"+1 604 325 9212",
    "sg:postcode":"V5S 1X1",
    "sg:province":"BC",
    "sg:tags":[
        "church"
    ],
    "wof:name":"Christian & Missionary Allnce",
    "wof:placetype":"venue"
},
  "geometry": {"coordinates":[-123.058846,49.220436],"type":"Point"}
}