{
  "type": "Feature",
  "properties": {
    "addr:full":"3315 Fairview St Burlington ON L7N 3N9",
    "addr:housenumber":"3315",
    "addr:postcode":"l7n 3n9",
    "addr:street":"Fairview St",
    "iso:country":"CA",
    "sg:address":"3315 Fairview St",
    "sg:city":"Burlington",
    "sg:classifiers":[
        {
            "category":"Home & Garden",
            "subcategory":"Household Appliances",
            "type":"Retail Goods"
        }
    ],
    "sg:phone":"+1 905 639 2326",
    "sg:postcode":"L7N 3N9",
    "sg:province":"ON",
    "sg:tags":[
        "cleaners",
        "vacuum"
    ],
    "wof:name":"Vac Connection",
    "wof:placetype":"venue"
},
  "geometry": {"coordinates":[-79.786621,43.353767],"type":"Point"}
}