{
  "type": "Feature",
  "properties": {
    "iso:country":"CA",
    "sg:address":"370 Rue DE L'Eglise",
    "sg:city":"Sullivan",
    "sg:classifiers":[
        {
            "category":"Education",
            "subcategory":"Library",
            "type":"Public Place"
        }
    ],
    "sg:phone":"+1 819 874 6251",
    "sg:postcode":"J0Y 2N0",
    "sg:province":"QC",
    "wof:name":"Sullivan Bibliotheque Mncpl",
    "wof:placetype":"venue"
},
  "geometry": {"coordinates":[-77.8282089233,48.1318778992],"type":"Point"}
}