{
  "type": "Feature",
  "properties": {
    "addr:full":"7210 Market St Port Hardy BC V0N 2P0",
    "addr:housenumber":"7210",
    "addr:postcode":"v0n 2p0",
    "addr:street":"Market St",
    "iso:country":"CA",
    "sg:address":"7210 Market St",
    "sg:city":"Port Hardy",
    "sg:classifiers":[
        {
            "category":"Sports & Exercise",
            "subcategory":"Bowling",
            "type":"Entertainment"
        }
    ],
    "sg:phone":"+1 250 949 6307",
    "sg:postcode":"V0N 2P0",
    "sg:province":"BC",
    "sg:tags":[
        "center"
    ],
    "wof:name":"North Island Lanes",
    "wof:placetype":"venue"
},
  "geometry": {"coordinates":[-127.492386,50.722618],"type":"Point"}
}