{
  "type": "Feature",
  "properties": {
    "addr:full":"Collingwood ON L9Y 3Z7",
    "addr:postcode":"l9y 3z7",
    "iso:country":"CA",
    "sg:city":"Collingwood",
    "sg:classifiers":[
        {
            "category":"Travel",
            "subcategory":"Hotels & Motels",
            "type":"Entertainment"
        }
    ],
    "sg:phone":"+1 705 445 4480",
    "sg:postcode":"L9Y 3Z7",
    "sg:province":"ON",
    "wof:name":"Pleasant Manor Motel",
    "wof:placetype":"venue"
},
  "geometry": {"coordinates":[-80.1641693115,44.487197876],"type":"Point"}
}