{
  "type": "Feature",
  "properties": {
    "addr:full":"631 David Manchester Rd Carp ON K0A 1L0",
    "addr:housenumber":"631",
    "addr:postcode":"k0a 1l0",
    "addr:street":"David Manchester Rd",
    "iso:country":"CA",
    "sg:address":"631 David Manchester Rd",
    "sg:city":"Carp",
    "sg:classifiers":[
        {
            "category":"Building & Trades",
            "subcategory":"Landscaping Services",
            "type":"Services"
        }
    ],
    "sg:phone":"+1 613 831 0303",
    "sg:postcode":"K0A 1L0",
    "sg:province":"ON",
    "sg:tags":[
        "landscape",
        "contractor"
    ],
    "wof:name":"Allan Mc Coy Contracting",
    "wof:placetype":"venue"
},
  "geometry": {"coordinates":[-76.0001754761,45.2782287598],"type":"Point"}
}