{
  "type": "Feature",
  "properties": {
    "addr:full":"Varennes QC J3X 2C7",
    "addr:postcode":"j3x 2c7",
    "iso:country":"CA",
    "sg:city":"Varennes",
    "sg:classifiers":[
        {
            "category":"Health Services",
            "subcategory":"Doctor",
            "type":"Services"
        }
    ],
    "sg:phone":"+1 450 652 2959",
    "sg:postcode":"J3X 2C7",
    "sg:province":"QC",
    "sg:tags":[
        "clinic"
    ],
    "wof:name":"Clinique Medicale DE Varennes",
    "wof:placetype":"venue"
},
  "geometry": {"coordinates":[-73.437927,45.678638],"type":"Point"}
}