{
  "type": "Feature",
  "properties": {
    "addr:full":"1500 Crois Rougemont Brossard QC J4X 2V1",
    "addr:housenumber":"1500",
    "addr:postcode":"j4x 2v1",
    "addr:street":"Crois Rougemont",
    "iso:country":"CA",
    "sg:address":"1500 Crois Rougemont",
    "sg:city":"Brossard",
    "sg:classifiers":[
        {
            "category":"Real Estate",
            "subcategory":"Real Estate Agent",
            "type":"Services"
        }
    ],
    "sg:phone":"+1 450 672 2455",
    "sg:postcode":"J4X 2V1",
    "sg:province":"QC",
    "sg:tags":[
        "management"
    ],
    "wof:name":"Gestion Immobiliere Progim Inc",
    "wof:placetype":"venue"
},
  "geometry": {"coordinates":[-73.47989699999999,45.43969],"type":"Point"}
}