{
  "type": "Feature",
  "properties": {
    "addr:full":"5160 Yonge St North York ON M2N 6L9",
    "addr:housenumber":"5160",
    "addr:postcode":"m2n 6l9",
    "addr:street":"Yonge St",
    "iso:country":"CA",
    "sg:address":"5160 Yonge St",
    "sg:city":"North York",
    "sg:classifiers":[
        {
            "category":"Government",
            "subcategory":"Office",
            "type":"Public Place"
        }
    ],
    "sg:phone":"+1 416 954 5786",
    "sg:postcode":"M2N 6L9",
    "sg:province":"ON",
    "wof:name":"Canada Consumer Products",
    "wof:placetype":"venue"
},
  "geometry": {"coordinates":[-79.412994,43.769146],"type":"Point"}
}