{
  "type": "Feature",
  "properties": {
    "iso:country":"CA",
    "sg:address":"6263 Rue Beaubien E",
    "sg:city":"Montreal",
    "sg:classifiers":[
        {
            "category":"Social Services",
            "subcategory":"Child Care",
            "type":"Services"
        }
    ],
    "sg:phone":"+1 514 254 6388",
    "sg:postcode":"H1M 3E6",
    "sg:province":"QC",
    "wof:name":"Garderie LA Maison Des Fon-Fon",
    "wof:placetype":"venue"
},
  "geometry": {"coordinates":[-73.5631942749,45.5841674805],"type":"Point"}
}