{
  "type": "Feature",
  "properties": {
    "iso:country":"CA",
    "sg:address":"236 2E Ave",
    "sg:city":"Lambton",
    "sg:classifiers":[
        {
            "category":"Building & Trades",
            "subcategory":"Construction",
            "type":"Services"
        }
    ],
    "sg:phone":"+1 418 486 2864",
    "sg:postcode":"G0M 1H0",
    "sg:province":"QC",
    "sg:tags":[
        "woodworker"
    ],
    "wof:name":"Lacroix, Michel",
    "wof:placetype":"venue"
},
  "geometry": {"coordinates":[-71.0845108032,45.8393135071],"type":"Point"}
}