{
  "type": "Feature",
  "properties": {
    "addr:full":"172 Rue Industrielle Saint-Apollinaire QC G0S 2E0",
    "addr:housenumber":"172",
    "addr:postcode":"g0s 2e0",
    "addr:street":"Rue Industrielle",
    "iso:country":"CA",
    "sg:address":"172 Rue Industrielle",
    "sg:city":"Saint-Apollinaire",
    "sg:classifiers":[
        {
            "category":"Manufacturing",
            "subcategory":"Building Materials",
            "type":"Manufacturing & Wholesale Goods"
        }
    ],
    "sg:phone":"+1 418 881 2988",
    "sg:postcode":"G0S 2E0",
    "sg:province":"QC",
    "wof:name":"Lam-Col Inc",
    "wof:placetype":"venue"
},
  "geometry": {"coordinates":[-71.4870681763,46.6264686584],"type":"Point"}
}