{
  "type": "Feature",
  "properties": {
    "addr:full":"168 Torrie Bay Fort Mcmurray AB T9K 1P2",
    "addr:housenumber":"168",
    "addr:postcode":"t9k 1p2",
    "addr:street":"Torrie Bay",
    "iso:country":"CA",
    "sg:address":"168 Torrie Bay",
    "sg:city":"Fort Mcmurray",
    "sg:classifiers":[
        {
            "category":"Building & Trades",
            "subcategory":"Construction",
            "type":"Services"
        }
    ],
    "sg:phone":"+1 780 743 3228",
    "sg:postcode":"T9K 1P2",
    "sg:province":"AB",
    "sg:tags":[
        "general",
        "contractor"
    ],
    "wof:name":"Mc Daniel Maintenance Ltd",
    "wof:placetype":"venue"
},
  "geometry": {"coordinates":[-111.458312988,56.7401313782],"type":"Point"}
}