{
  "type": "Feature",
  "properties": {
    "iso:country":"CA",
    "sg:city":"St Catharines",
    "sg:classifiers":[
        {
            "category":"Professional",
            "subcategory":"Lawyer & Legal Services",
            "type":"Services"
        }
    ],
    "sg:phone":"+1 905 688 4500",
    "sg:postcode":"L2R 7G1",
    "sg:province":"ON",
    "sg:tags":[
        "attorney"
    ],
    "wof:name":"Bauerle, Paul M",
    "wof:placetype":"venue"
},
  "geometry": {"coordinates":[-79.245979,43.158356],"type":"Point"}
}