{
  "type": "Feature",
  "properties": {
    "iso:country":"CA",
    "sg:address":"125 2nd St",
    "sg:city":"Weyburn",
    "sg:classifiers":[
        {
            "category":"Home & Garden",
            "subcategory":"Household Appliances",
            "type":"Retail Goods"
        }
    ],
    "sg:phone":"+1 306 842 7816",
    "sg:postcode":"S4H 0T7",
    "sg:province":"SK",
    "wof:name":"Stu's Repair",
    "wof:placetype":"venue"
},
  "geometry": {"coordinates":[-103.85518646200001,49.6624145508],"type":"Point"}
}