{
  "type": "Feature",
  "properties": {
    "addr:full":"2058 127A St Surrey BC V4A 5Z9",
    "addr:housenumber":"2058",
    "addr:postcode":"v4a 5z9",
    "addr:street":"127A St",
    "iso:country":"CA",
    "sg:address":"2058 127A St",
    "sg:city":"Surrey",
    "sg:classifiers":[
        {
            "category":"Real Estate",
            "subcategory":"Architect",
            "type":"Services"
        }
    ],
    "sg:phone":"+1 604 535 6000",
    "sg:postcode":"V4A 5Z9",
    "sg:province":"BC",
    "sg:tags":[
        "surveyor",
        "estimate",
        "construction"
    ],
    "wof:name":"Sanft & Assoc",
    "wof:placetype":"venue"
},
  "geometry": {"coordinates":[-122.830215454,49.105178833],"type":"Point"}
}