{
  "type": "Feature",
  "properties": {
    "addr:full":"163 Roncesvalles Ave Toronto ON M6R 2L3",
    "addr:housenumber":"163",
    "addr:postcode":"m6r 2l3",
    "addr:street":"Roncesvalles Ave",
    "iso:country":"CA",
    "sg:address":"163 Roncesvalles Ave",
    "sg:city":"Toronto",
    "sg:classifiers":[
        {
            "category":"Shopping",
            "subcategory":"Department Store",
            "type":"Retail Goods"
        }
    ],
    "sg:phone":"+1 416 531 8344",
    "sg:postcode":"M6R 2L3",
    "sg:province":"ON",
    "sg:tags":[
        "shop"
    ],
    "wof:name":"S K Dollar Plus",
    "wof:placetype":"venue"
},
  "geometry": {"coordinates":[-79.448013,43.64418],"type":"Point"}
}