{
  "type": "Feature",
  "properties": {
    "addr:full":"608 Weber St N #4 Waterloo ON N2V 1K4",
    "addr:housenumber":"608",
    "addr:postcode":"n2v 1k4",
    "addr:street":"Weber St N # 4",
    "iso:country":"CA",
    "sg:address":"608 Weber St N #4",
    "sg:city":"Waterloo",
    "sg:classifiers":[
        {
            "category":"Professional",
            "subcategory":"Research",
            "type":"Services"
        }
    ],
    "sg:phone":"+1 519 746 8483",
    "sg:postcode":"N2V 1K4",
    "sg:province":"ON",
    "sg:tags":[
        "development",
        "electronic"
    ],
    "wof:name":"Rdm Corp",
    "wof:placetype":"venue"
},
  "geometry": {"coordinates":[-80.552673,43.500687],"type":"Point"}
}