{
  "type": "Feature",
  "properties": {
    "iso:country":"CA",
    "sg:address":"1035 Belmont Ave",
    "sg:city":"Victoria",
    "sg:classifiers":[
        {
            "category":"Real Estate",
            "subcategory":"Real Estate Operator",
            "type":"Services"
        }
    ],
    "sg:phone":"+1 250 598 7542",
    "sg:postcode":"V8S 3T5",
    "sg:province":"BC",
    "sg:tags":[
        "apartment"
    ],
    "wof:name":"Camosack Manor",
    "wof:placetype":"venue"
},
  "geometry": {"coordinates":[-123.337882996,48.4252090454],"type":"Point"}
}