{
  "type": "Feature",
  "properties": {
    "addr:full":"281 Ch Sainte-Foy Quebec QC G1R 1T5",
    "addr:housenumber":"281",
    "addr:postcode":"g1r 1t5",
    "addr:street":"Ch Sainte-Foy",
    "iso:country":"CA",
    "sg:address":"281 Ch Sainte-Foy",
    "sg:city":"Quebec",
    "sg:classifiers":[
        {
            "category":"Social Services",
            "type":"Services"
        }
    ],
    "sg:phone":"+1 418 649 1720",
    "sg:postcode":"G1R 1T5",
    "sg:province":"QC",
    "sg:tags":[
        "organization",
        "welfare"
    ],
    "wof:name":"Mouvement D'Informations",
    "wof:placetype":"venue"
},
  "geometry": {"coordinates":[-71.2313613892,46.8042945862],"type":"Point"}
}