{
  "type": "Feature",
  "properties": {
    "addr:full":"770 Bradford St Winnipeg MB R3H 0N3",
    "addr:housenumber":"770",
    "addr:postcode":"r3h 0n3",
    "addr:street":"Bradford St",
    "iso:country":"CA",
    "sg:address":"770 Bradford St",
    "sg:city":"Winnipeg",
    "sg:classifiers":[
        {
            "category":"Professional",
            "subcategory":"Engineering",
            "type":"Services"
        }
    ],
    "sg:phone":"+1 204 775 0291",
    "sg:postcode":"R3H 0N3",
    "sg:province":"MB",
    "sg:tags":[
        "engineer"
    ],
    "wof:name":"Sms Engineering Ltd",
    "wof:placetype":"venue"
},
  "geometry": {"coordinates":[-97.204865,49.900448],"type":"Point"}
}