{
  "type": "Feature",
  "properties": {
    "addr:full":"101 Cedar St Tillsonburg ON N4G 5T7",
    "addr:housenumber":"101",
    "addr:postcode":"n4g 5t7",
    "addr:street":"Cedar St",
    "iso:country":"CA",
    "sg:address":"101 Cedar St",
    "sg:city":"Tillsonburg",
    "sg:classifiers":[
        {
            "category":"Wholesale",
            "subcategory":"Tobacco Products",
            "type":"Manufacturing & Wholesale Goods"
        }
    ],
    "sg:phone":"+1 519 842 6431",
    "sg:postcode":"N4G 5T7",
    "sg:province":"ON",
    "sg:tags":[
        "cigarette",
        "cigar",
        "dealer"
    ],
    "wof:name":"Rothmans Benson & Hedges Inc",
    "wof:placetype":"venue"
},
  "geometry": {"coordinates":[-80.715385,42.852577],"type":"Point"}
}