{
  "type": "Feature",
  "properties": {
    "addr:full":"1713 52 St SE Calgary AB T2A 1V1",
    "addr:housenumber":"1713",
    "addr:postcode":"t2a 1v1",
    "addr:street":"52 St Se",
    "iso:country":"CA",
    "sg:address":"1713 52 St SE",
    "sg:city":"Calgary",
    "sg:classifiers":[
        {
            "category":"Restaurant",
            "type":"Food & Drink"
        }
    ],
    "sg:phone":"+1 403 207 3388",
    "sg:postcode":"T2A 1V1",
    "sg:province":"AB",
    "sg:tags":[
        "out",
        "pizza"
    ],
    "wof:name":"Pizza 3000 Ltd",
    "wof:placetype":"venue"
},
  "geometry": {"coordinates":[-113.958641,51.03912],"type":"Point"}
}