{
  "type": "Feature",
  "properties": {
    "addr:full":"11482 149 St NW Edmonton AB T5M 1W7",
    "addr:housenumber":"11482",
    "addr:postcode":"t5m 1w7",
    "addr:street":"149 St Nw",
    "iso:country":"CA",
    "sg:address":"11482 149 St NW",
    "sg:city":"Edmonton",
    "sg:classifiers":[
        {
            "category":"Building & Trades",
            "subcategory":"Electrical",
            "type":"Services"
        }
    ],
    "sg:phone":"+1 780 454 8817",
    "sg:postcode":"T5M 1W7",
    "sg:province":"AB",
    "sg:tags":[
        "electric",
        "contractor"
    ],
    "wof:name":"Kamwin Electric Ltd",
    "wof:placetype":"venue"
},
  "geometry": {"coordinates":[-113.578193665,53.5649604797],"type":"Point"}
}