{
  "type": "Feature",
  "properties": {
    "addr:full":"50 Rue Des Visconti Blainville QC J7B 1P3",
    "addr:housenumber":"50",
    "addr:postcode":"j7b 1p3",
    "addr:street":"Rue Des Visconti",
    "iso:country":"CA",
    "sg:address":"50 Rue Des Visconti",
    "sg:city":"Blainville",
    "sg:classifiers":[
        {
            "category":"Professional",
            "subcategory":"Accounting & Tax Preparation",
            "type":"Services"
        }
    ],
    "sg:phone":"+1 450 979 5343",
    "sg:postcode":"J7B 1P3",
    "sg:province":"QC",
    "sg:tags":[
        "accountant"
    ],
    "wof:name":"Briard, Guy",
    "wof:placetype":"venue"
},
  "geometry": {"coordinates":[-73.80768585209999,45.6672210693],"type":"Point"}
}