{
  "type": "Feature",
  "properties": {
    "addr:full":"2208 Herchmer St Regina SK S4V 2N5",
    "addr:housenumber":"2208",
    "addr:postcode":"s4v 2n5",
    "addr:street":"Herchmer St",
    "iso:country":"CA",
    "sg:address":"2208 Herchmer St",
    "sg:city":"Regina",
    "sg:classifiers":[
        {
            "category":"Real Estate",
            "subcategory":"Real Estate Agent",
            "type":"Services"
        }
    ],
    "sg:phone":"+1 306 522 4663",
    "sg:postcode":"S4V 2N5",
    "sg:province":"SK",
    "sg:tags":[
        "inspection"
    ],
    "wof:name":"Calibre Home Inspection Svc",
    "wof:placetype":"venue"
},
  "geometry": {"coordinates":[-104.537406921,50.4421424866],"type":"Point"}
}