{
  "type": "Feature",
  "properties": {
    "addr:full":"6301 Mulligan Dr 100 Mile House BC V0K 2E3",
    "addr:housenumber":"6301;100",
    "addr:postcode":"v0k 2e3",
    "addr:street":"Mulligan Dr",
    "iso:country":"CA",
    "sg:address":"6301 Mulligan Dr",
    "sg:city":"100 Mile House",
    "sg:classifiers":[
        {
            "category":"Building & Trades",
            "subcategory":"Construction",
            "type":"Services"
        }
    ],
    "sg:phone":"+1 250 395 2077",
    "sg:postcode":"V0K 2E3",
    "sg:province":"BC",
    "sg:tags":[
        "general",
        "contractor"
    ],
    "wof:name":"Action Drilling Ltd",
    "wof:placetype":"venue"
},
  "geometry": {"coordinates":[-121.391159058,51.3140258789],"type":"Point"}
}