{
  "type": "Feature",
  "properties": {
    "iso:country":"CA",
    "sg:city":"Montreal",
    "sg:classifiers":[
        {
            "category":"Parking",
            "type":"Transportation"
        }
    ],
    "sg:phone":"+1 514 282 1700",
    "sg:postcode":"H3A 1M8",
    "sg:province":"QC",
    "sg:tags":[
        "garage"
    ],
    "wof:name":"Stationnement Populaire Inc",
    "wof:placetype":"venue"
},
  "geometry": {"coordinates":[-73.55806,45.51844],"type":"Point"}
}