{
  "type": "Feature",
  "properties": {
    "iso:country":"CA",
    "sg:address":"290 Carlingview Dr",
    "sg:city":"Etobicoke",
    "sg:classifiers":[
        {
            "category":"Manufacturing",
            "subcategory":"Metals",
            "type":"Manufacturing & Wholesale Goods"
        }
    ],
    "sg:phone":"+1 416 675 1860",
    "sg:postcode":"M9W 5G1",
    "sg:province":"ON",
    "sg:tags":[
        "refiner",
        "smelter"
    ],
    "wof:name":"Handy & Harman of Canada Ltd",
    "wof:placetype":"venue"
},
  "geometry": {"coordinates":[-79.59761,43.690914],"type":"Point"}
}