{
  "type": "Feature",
  "properties": {
    "iso:country":"CA",
    "sg:address":"585 Keele St",
    "sg:city":"Toronto",
    "sg:classifiers":[
        {
            "category":"Retail",
            "subcategory":"Auto Repair",
            "type":"Services"
        }
    ],
    "sg:phone":"+1 416 763 4101",
    "sg:postcode":"M6N 3E4",
    "sg:province":"ON",
    "sg:tags":[
        "transmission"
    ],
    "wof:name":"3 Way Transmissions",
    "wof:placetype":"venue"
},
  "geometry": {"coordinates":[-79.4668121338,43.6711616516],"type":"Point"}
}