{
  "type": "Feature",
  "properties": {
    "iso:country":"CA",
    "sg:address":"1125 Rue Franchere",
    "sg:city":"Longueuil",
    "sg:classifiers":[
        {
            "category":"Building & Trades",
            "subcategory":"Plumbing",
            "type":"Services"
        }
    ],
    "sg:phone":"+1 450 670 9779",
    "sg:postcode":"J4J 4T7",
    "sg:province":"QC",
    "sg:tags":[
        "contractor"
    ],
    "wof:name":"Plomberie & Chauffage R Moreau",
    "wof:placetype":"venue"
},
  "geometry": {"coordinates":[-73.478767,45.544331],"type":"Point"}
}