{
  "type": "Feature",
  "properties": {
    "addr:full":"305 12E Av Richelieu QC J3L 3T2",
    "addr:housenumber":"305",
    "addr:postcode":"j3l 3t2",
    "addr:street":"12E Av",
    "iso:country":"CA",
    "sg:address":"305 12E Av",
    "sg:city":"Richelieu",
    "sg:classifiers":[
        {
            "category":"Wholesale",
            "subcategory":"Metals & Minerals",
            "type":"Manufacturing & Wholesale Goods"
        }
    ],
    "sg:phone":"+1 450 658 8771",
    "sg:postcode":"J3L 3T2",
    "sg:province":"QC",
    "sg:tags":[
        "aluminum"
    ],
    "wof:name":"A & D Prevost Inc",
    "wof:placetype":"venue"
},
  "geometry": {"coordinates":[-73.247978,45.441631],"type":"Point"}
}