{
  "type": "Feature",
  "properties": {
    "addr:full":"155 John St Toronto ON M5T 1X3",
    "addr:housenumber":"155",
    "addr:postcode":"m5t 1x3",
    "addr:street":"John St",
    "iso:country":"CA",
    "sg:address":"155 John St",
    "sg:city":"Toronto",
    "sg:classifiers":[
        {
            "category":"Shopping",
            "subcategory":"Clothing, Apparel, & Fashions",
            "type":"Retail Goods"
        }
    ],
    "sg:phone":"+1 416 599 7945",
    "sg:postcode":"M5T 1X3",
    "sg:province":"ON",
    "sg:tags":[
        "sportswear"
    ],
    "wof:name":"Lounge Clothing",
    "wof:placetype":"venue"
},
  "geometry": {"coordinates":[-79.39104500000001,43.650032],"type":"Point"}
}