{
  "type": "Feature",
  "properties": {
    "addr:full":"44755 Yale Rd Chilliwack BC V2R 4H3",
    "addr:housenumber":"44755",
    "addr:postcode":"v2r 4h3",
    "addr:street":"Yale Rd",
    "iso:country":"CA",
    "sg:address":"44755 Yale Rd",
    "sg:city":"Chilliwack",
    "sg:classifiers":[
        {
            "category":"Wholesale",
            "subcategory":"Machinery & Supplies",
            "type":"Manufacturing & Wholesale Goods"
        }
    ],
    "sg:phone":"+1 604 793 2287",
    "sg:postcode":"V2R 4H3",
    "sg:province":"BC",
    "wof:name":"Pollard Equipment Ltd",
    "wof:placetype":"venue"
},
  "geometry": {"coordinates":[-121.984924316,49.1449546814],"type":"Point"}
}