{
  "type": "Feature",
  "properties": {
    "addr:full":"Saint-Bernard QC G0S 2G0",
    "addr:postcode":"g0s 2g0",
    "iso:country":"CA",
    "sg:city":"Saint-Bernard",
    "sg:classifiers":[
        {
            "category":"Home & Garden",
            "subcategory":"Building Materials",
            "type":"Retail Goods"
        }
    ],
    "sg:phone":"+1 418 475 6655",
    "sg:postcode":"G0S 2G0",
    "sg:province":"QC",
    "wof:name":"Emile Bilodeau & Fils Inc",
    "wof:placetype":"venue"
},
  "geometry": {"coordinates":[-71.1417922974,46.4951782227],"type":"Point"}
}