{
  "type": "Feature",
  "properties": {
    "iso:country":"CA",
    "sg:address":"1229 17A St NE",
    "sg:city":"Calgary",
    "sg:classifiers":[
        {
            "category":"Social Services",
            "subcategory":"Child Care",
            "type":"Services"
        }
    ],
    "sg:phone":"+1 403 277 3361",
    "sg:postcode":"T2E 4V4",
    "sg:province":"AB",
    "wof:name":"Belfast Child Care",
    "wof:placetype":"venue"
},
  "geometry": {"coordinates":[-114.017852783,51.0632171631],"type":"Point"}
}