{
  "type": "Feature",
  "properties": {
    "addr:full":"8293 Rue Saint-Denis Montreal QC H2P 2G7",
    "addr:housenumber":"8293",
    "addr:postcode":"h2p 2g7",
    "addr:street":"Rue Saint-Denis",
    "iso:country":"CA",
    "sg:address":"8293 Rue Saint-Denis",
    "sg:city":"Montreal",
    "sg:classifiers":[
        {
            "category":"Professional",
            "subcategory":"Accounting & Tax Preparation",
            "type":"Services"
        }
    ],
    "sg:phone":"+1 514 384 6797",
    "sg:postcode":"H2P 2G7",
    "sg:province":"QC",
    "sg:tags":[
        "return",
        "filing"
    ],
    "wof:name":"Gabriel Brouillette Inc",
    "wof:placetype":"venue"
},
  "geometry": {"coordinates":[-73.6318511963,45.5435066223],"type":"Point"}
}