{
  "type": "Feature",
  "properties": {
    "addr:full":"2025 Rue Parthenais # 241 Montreal QC H2K 3T2",
    "addr:housenumber":"2025",
    "addr:postcode":"h2k 3t2",
    "addr:street":"Rue Parthenais # 241",
    "iso:country":"CA",
    "sg:address":"2025 Rue Parthenais # 241",
    "sg:city":"Montreal",
    "sg:classifiers":[
        {
            "category":"Cinema",
            "subcategory":"Movie Theater",
            "type":"Entertainment"
        }
    ],
    "sg:phone":"+1 514 281 8942",
    "sg:postcode":"H2K 3T2",
    "sg:province":"QC",
    "wof:name":"L'Auguste Theatre",
    "wof:placetype":"venue"
},
  "geometry": {"coordinates":[-73.55652618409999,45.5298080444],"type":"Point"}
}