{
  "type": "Feature",
  "properties": {
    "addr:full":"226 3rd Ave W Canora SK S0A 0L0",
    "addr:housenumber":"226",
    "addr:postcode":"s0a 0l0",
    "addr:street":"3Rd Ave W Canora",
    "iso:country":"CA",
    "sg:address":"226 3rd Ave W",
    "sg:city":"Canora",
    "sg:classifiers":[
        {
            "category":"Home & Garden",
            "subcategory":"Garden Supply",
            "type":"Retail Goods"
        }
    ],
    "sg:phone":"+1 306 563 6061",
    "sg:postcode":"S0A 0L0",
    "sg:province":"SK",
    "sg:tags":[
        "center"
    ],
    "wof:name":"Diamond K Garden Ctr",
    "wof:placetype":"venue"
},
  "geometry": {"coordinates":[-102.432434,51.635456],"type":"Point"}
}