{
  "type": "Feature",
  "properties": {
    "addr:full":"1440 117 Rte Mont-Tremblant QC J8E 2X8",
    "addr:housenumber":"1440",
    "addr:postcode":"j8e 2x8",
    "addr:street":"117 Rte",
    "iso:country":"CA",
    "sg:address":"1440 117 Rte",
    "sg:city":"Mont-Tremblant",
    "sg:classifiers":[
        {
            "category":"Building & Trades",
            "subcategory":"Construction",
            "type":"Services"
        }
    ],
    "sg:phone":"+1 819 425 2414",
    "sg:postcode":"J8E 2X8",
    "sg:province":"QC",
    "sg:tags":[
        "home",
        "builder"
    ],
    "wof:name":"Maison Roco Viceroy",
    "wof:placetype":"venue"
},
  "geometry": {"coordinates":[-74.601685,46.11834],"type":"Point"}
}