{
  "type": "Feature",
  "properties": {
    "addr:full":"3450 Pembina Hwy Winnipeg MB R3V 1A1",
    "addr:housenumber":"3450",
    "addr:postcode":"r3v 1a1",
    "addr:street":"Pembina Hwy",
    "iso:country":"CA",
    "sg:address":"3450 Pembina Hwy",
    "sg:city":"Winnipeg",
    "sg:classifiers":[
        {
            "category":"Organizations",
            "subcategory":"Professional Association",
            "type":"Services"
        }
    ],
    "sg:phone":"+1 204 269 4120",
    "sg:postcode":"R3V 1A1",
    "sg:province":"MB",
    "sg:tags":[
        "hall",
        "auditorium"
    ],
    "wof:name":"St Norbert Community Ctr",
    "wof:placetype":"venue"
},
  "geometry": {"coordinates":[-97.1556472778,49.7678985596],"type":"Point"}
}