{
  "type": "Feature",
  "properties": {
    "addr:full":"Vernon BC V1T 8C1",
    "addr:postcode":"v1t 8c1",
    "iso:country":"CA",
    "sg:city":"Vernon",
    "sg:classifiers":[
        {
            "category":"Home & Garden",
            "subcategory":"Furniture",
            "type":"Retail Goods"
        }
    ],
    "sg:phone":"+1 250 549 1927",
    "sg:postcode":"V1T 8C1",
    "sg:province":"BC",
    "sg:tags":[
        "kitchen",
        "maker",
        "cabinet"
    ],
    "wof:name":"Kalwood Cabinets",
    "wof:placetype":"venue"
},
  "geometry": {"coordinates":[-119.263366699,50.2518005371],"type":"Point"}
}