{
  "type": "Feature",
  "properties": {
    "addr:full":"156 Kincade Rd Qualicum Beach BC V9K 2B7",
    "addr:housenumber":"156",
    "addr:postcode":"v9k 2b7",
    "addr:street":"Kincade Rd",
    "iso:country":"CA",
    "sg:address":"156 Kincade Rd",
    "sg:city":"Qualicum Beach",
    "sg:classifiers":[
        {
            "category":"Building & Trades",
            "subcategory":"Construction",
            "type":"Services"
        }
    ],
    "sg:phone":"+1 250 752 3744",
    "sg:postcode":"V9K 2B7",
    "sg:province":"BC",
    "sg:tags":[
        "general",
        "contractor"
    ],
    "wof:name":"Duncan Insulation Ltd",
    "wof:placetype":"venue"
},
  "geometry": {"coordinates":[-124.481323242,49.3599510193],"type":"Point"}
}