{
  "type": "Feature",
  "properties": {
    "addr:full":"25 Rue Des Forges Trois-Rivieres QC G9A 6A7",
    "addr:housenumber":"25",
    "addr:postcode":"g9a 6a7",
    "addr:street":"Rue Des Forges Trois-Rivieres",
    "iso:country":"CA",
    "sg:address":"25 Rue Des Forges",
    "sg:city":"Trois-Rivieres",
    "sg:classifiers":[
        {
            "category":"Government",
            "subcategory":"Office",
            "type":"Public Place"
        }
    ],
    "sg:phone":"+1 819 371 6009",
    "sg:postcode":"G9A 6A7",
    "sg:province":"QC",
    "wof:name":"Quebec Public Curateur",
    "wof:placetype":"venue"
},
  "geometry": {"coordinates":[-72.539108,46.341473],"type":"Point"}
}