{
  "type": "Feature",
  "properties": {
    "addr:full":"291 Mill St Port Elgin ON N0H 2C0",
    "addr:housenumber":"291",
    "addr:postcode":"n0h 2c0",
    "addr:street":"Mill St",
    "iso:country":"CA",
    "sg:address":"291 Mill St",
    "sg:city":"Port Elgin",
    "sg:classifiers":[
        {
            "category":"Travel",
            "subcategory":"Hotels & Motels",
            "type":"Entertainment"
        }
    ],
    "sg:phone":"+1 519 832 5584",
    "sg:postcode":"N0H 2C0",
    "sg:province":"ON",
    "sg:tags":[
        "cottage",
        "cabin"
    ],
    "wof:name":"Starlight Cottages",
    "wof:placetype":"venue"
},
  "geometry": {"coordinates":[-81.397903,44.441769],"type":"Point"}
}