{
  "type": "Feature",
  "properties": {
    "addr:full":"189 Regent St Sudbury ON P3C 4C4",
    "addr:housenumber":"189",
    "addr:postcode":"p3c 4c4",
    "addr:street":"Regent St",
    "iso:country":"CA",
    "sg:address":"189 Regent St",
    "sg:city":"Sudbury",
    "sg:classifiers":[
        {
            "category":"Organizations",
            "subcategory":"Religious Organization",
            "type":"Services"
        }
    ],
    "sg:phone":"+1 705 674 4834",
    "sg:postcode":"P3C 4C4",
    "sg:province":"ON",
    "sg:tags":[
        "church"
    ],
    "wof:name":"Trinity Evangelical Lutheran",
    "wof:placetype":"venue"
},
  "geometry": {"coordinates":[-81.00726299999999,46.488792],"type":"Point"}
}