{
  "type": "Feature",
  "properties": {
    "iso:country":"CA",
    "sg:address":"730 Mohawk Rd W",
    "sg:city":"Hamilton",
    "sg:classifiers":[
        {
            "category":"Real Estate",
            "subcategory":"Real Estate Operator",
            "type":"Services"
        }
    ],
    "sg:phone":"+1 905 383 1447",
    "sg:postcode":"L9C 1X9",
    "sg:province":"ON",
    "sg:tags":[
        "apartment"
    ],
    "wof:name":"Rice Townhouses",
    "wof:placetype":"venue"
},
  "geometry": {"coordinates":[-79.9183425903,43.2338027954],"type":"Point"}
}