{
  "type": "Feature",
  "properties": {
    "iso:country":"CA",
    "sg:address":"1814 Ch Du Village",
    "sg:city":"Amherst",
    "sg:classifiers":[
        {
            "category":"Education",
            "subcategory":"Library",
            "type":"Public Place"
        }
    ],
    "sg:phone":"+1 819 687 9775",
    "sg:postcode":"J0T 2T0",
    "sg:province":"QC",
    "wof:name":"Centre Communautaire",
    "wof:placetype":"venue"
},
  "geometry": {"coordinates":[-74.8315048218,46.0807113647],"type":"Point"}
}