{
  "type": "Feature",
  "properties": {
    "addr:full":"681 Bathurst St Toronto ON M5S 2R2",
    "addr:housenumber":"681",
    "addr:postcode":"m5s 2r2",
    "addr:street":"Bathurst St",
    "iso:country":"CA",
    "sg:address":"681 Bathurst St",
    "sg:city":"Toronto",
    "sg:classifiers":[
        {
            "category":"Food & Beverages",
            "subcategory":"Groceries & Convenience Stores",
            "type":"Retail Goods"
        }
    ],
    "sg:phone":"+1 416 531 8753",
    "sg:postcode":"M5S 2R2",
    "sg:province":"ON",
    "wof:name":"Stop N Go",
    "wof:placetype":"venue"
},
  "geometry": {"coordinates":[-79.40935500000001,43.661041],"type":"Point"}
}