{
  "type": "Feature",
  "properties": {
    "iso:country":"CA",
    "sg:address":"1091 Topsail Rd",
    "sg:city":"Mount Pearl",
    "sg:classifiers":[
        {
            "category":"Shopping",
            "subcategory":"Clothing, Apparel, & Fashions",
            "type":"Retail Goods"
        }
    ],
    "sg:phone":"+1 709 747 4661",
    "sg:postcode":"A1N 2M3",
    "sg:province":"NL",
    "sg:tags":[
        "salvage",
        "surplus",
        "merchandise"
    ],
    "wof:name":"Army Navy-Out Door Store",
    "wof:placetype":"venue"
},
  "geometry": {"coordinates":[-52.8169593811,47.526348114],"type":"Point"}
}