{
  "type": "Feature",
  "properties": {
    "addr:full":"547 Rue Paul-Eugene Baie-Comeau QC G5C 1E9",
    "addr:housenumber":"547",
    "addr:postcode":"g5c 1e9",
    "addr:street":"Rue Paul-Eugene",
    "iso:country":"CA",
    "sg:address":"547 Rue Paul-Eugene",
    "sg:city":"Baie-Comeau",
    "sg:classifiers":[
        {
            "category":"Professional",
            "subcategory":"Business Services",
            "type":"Services"
        }
    ],
    "sg:phone":"+1 418 295 3050",
    "sg:postcode":"G5C 1E9",
    "sg:province":"QC",
    "sg:tags":[
        "appraiser"
    ],
    "wof:name":"Bureau D'Evaluation Inc",
    "wof:placetype":"venue"
},
  "geometry": {"coordinates":[-68.25299835209999,49.1970443726],"type":"Point"}
}