{
  "type": "Feature",
  "properties": {
    "iso:country":"CA",
    "sg:address":"9 Car Grilli",
    "sg:city":"L'Ile-Bizard",
    "sg:classifiers":[
        {
            "category":"Building & Trades",
            "subcategory":"Construction",
            "type":"Services"
        }
    ],
    "sg:phone":"+1 514 620 4770",
    "sg:postcode":"H9E 1N8",
    "sg:province":"QC",
    "sg:tags":[
        "home",
        "builder",
        "contractor"
    ],
    "wof:name":"Habitations Luciano Grilli Inc",
    "wof:placetype":"venue"
},
  "geometry": {"coordinates":[-73.9225158691,45.476234436],"type":"Point"}
}