{
  "type": "Feature",
  "properties": {
    "addr:full":"419 Main St Wynyard SK S0A 4T0",
    "addr:housenumber":"419",
    "addr:postcode":"s0a 4t0",
    "addr:street":"Main St",
    "iso:country":"CA",
    "sg:address":"419 Main St",
    "sg:city":"Wynyard",
    "sg:classifiers":[
        {
            "category":"Autos & Motor Vehicles",
            "subcategory":"Auto Supplies",
            "type":"Retail Goods"
        }
    ],
    "sg:phone":"+1 306 554 3422",
    "sg:postcode":"S0A 4T0",
    "sg:province":"SK",
    "sg:tags":[
        "tire"
    ],
    "wof:name":"Wynyard Tire",
    "wof:placetype":"venue"
},
  "geometry": {"coordinates":[-104.180092,51.765205],"type":"Point"}
}