{
  "type": "Feature",
  "properties": {
    "iso:country":"CA",
    "sg:address":"2012 Columbia Ave",
    "sg:city":"Rossland",
    "sg:classifiers":[
        {
            "category":"Shopping",
            "type":"Retail Goods"
        }
    ],
    "sg:phone":"+1 250 362 9505",
    "sg:postcode":"V0G 1Y0",
    "sg:province":"BC",
    "sg:tags":[
        "art",
        "gallery",
        "dealer"
    ],
    "wof:name":"Main Stage Art Gallery",
    "wof:placetype":"venue"
},
  "geometry": {"coordinates":[-117.799888611,49.0770874023],"type":"Point"}
}