{
  "type": "Feature",
  "properties": {
    "addr:full":"1100 Burloak Dr # 601 Burlington ON L7L 6B2",
    "addr:housenumber":"1100;601",
    "addr:postcode":"l7l 6b2",
    "addr:street":"Burloak Dr #",
    "iso:country":"CA",
    "sg:address":"1100 Burloak Dr # 601",
    "sg:city":"Burlington",
    "sg:classifiers":[
        {
            "category":"Banks & Credit Unions",
            "subcategory":"Bank",
            "type":"Services"
        }
    ],
    "sg:phone":"+1 905 319 9956",
    "sg:postcode":"L7L 6B2",
    "sg:province":"ON",
    "sg:tags":[
        "consultant",
        "financing",
        "planning",
        "financial"
    ],
    "wof:name":"Site Finance Inc",
    "wof:placetype":"venue"
},
  "geometry": {"coordinates":[-79.7597503662,43.3974685669],"type":"Point"}
}