{
  "type": "Feature",
  "properties": {
    "addr:full":"7104 6E Av Montreal QC H2A 3E4",
    "addr:housenumber":"7104",
    "addr:postcode":"h2a 3e4",
    "addr:street":"6E Av",
    "iso:country":"CA",
    "sg:address":"7104 6E Av",
    "sg:city":"Montreal",
    "sg:classifiers":[
        {
            "category":"Shopping",
            "subcategory":"Bicycles & Sporting Goods",
            "type":"Retail Goods"
        }
    ],
    "sg:phone":"+1 514 722 9405",
    "sg:postcode":"H2A 3E4",
    "sg:province":"QC",
    "sg:tags":[
        "tackle",
        "fishing"
    ],
    "wof:name":"Ktl Canada Inc",
    "wof:placetype":"venue"
},
  "geometry": {"coordinates":[-73.6004486084,45.5562286377],"type":"Point"}
}