{
  "type": "Feature",
  "properties": {
    "addr:full":"1002 Bruce Rd 15 Cargill ON N0G 1J0",
    "addr:housenumber":"1002;15",
    "addr:postcode":"n0g 1j0",
    "addr:street":"Bruce Rd",
    "iso:country":"CA",
    "sg:address":"1002 Bruce Rd 15",
    "sg:city":"Cargill",
    "sg:classifiers":[
        {
            "category":"Manufacturing",
            "subcategory":"Lumber",
            "type":"Manufacturing & Wholesale Goods"
        }
    ],
    "sg:phone":"+1 519 366 1027",
    "sg:postcode":"N0G 1J0",
    "sg:province":"ON",
    "sg:tags":[
        "company",
        "logging"
    ],
    "wof:name":"Bruce County Sawing & Lumber",
    "wof:placetype":"venue"
},
  "geometry": {"coordinates":[-81.24530799999999,44.196098],"type":"Point"}
}