{
  "type": "Feature",
  "properties": {
    "addr:full":"389 Av Principale Degelis QC G5T 1L3",
    "addr:postcode":"g5t 1l3",
    "addr:street":"389 Av Principale",
    "iso:country":"CA",
    "sg:address":"389 Av Principale",
    "sg:city":"Degelis",
    "sg:classifiers":[
        {
            "category":"Banks & Credit Unions",
            "subcategory":"Bank",
            "type":"Services"
        }
    ],
    "sg:phone":"+1 418 853 2945",
    "sg:postcode":"G5T 1L3",
    "sg:province":"QC",
    "wof:name":"Banque Nationale Du Canada",
    "wof:placetype":"venue"
},
  "geometry": {"coordinates":[-68.644913,47.547516],"type":"Point"}
}