{
  "type": "Feature",
  "properties": {
    "addr:full":"Windsor ON N8T 1E9",
    "addr:postcode":"n8t 1e9",
    "iso:country":"CA",
    "sg:city":"Windsor",
    "sg:classifiers":[
        {
            "category":"Health Services",
            "subcategory":"Chiropractor",
            "type":"Services"
        }
    ],
    "sg:phone":"+1 519 974 1199",
    "sg:postcode":"N8T 1E9",
    "sg:province":"ON",
    "wof:name":"Lopez, Sergio DC",
    "wof:placetype":"venue"
},
  "geometry": {"coordinates":[-82.934746,42.313831],"type":"Point"}
}