{
  "type": "Feature",
  "properties": {
    "addr:full":"Qualicum Beach BC V9K 1J1",
    "addr:postcode":"v9k 1j1",
    "iso:country":"CA",
    "sg:city":"Qualicum Beach",
    "sg:classifiers":[
        {
            "category":"Building & Trades",
            "subcategory":"Construction",
            "type":"Services"
        }
    ],
    "sg:phone":"+1 250 752 4489",
    "sg:postcode":"V9K 1J1",
    "sg:province":"BC",
    "sg:tags":[
        "general",
        "contractor"
    ],
    "wof:name":"Don May Construction",
    "wof:placetype":"venue"
},
  "geometry": {"coordinates":[-124.453918457,49.3500671387],"type":"Point"}
}