{
  "type": "Feature",
  "properties": {
    "iso:country":"CA",
    "sg:address":"234 Weber St N",
    "sg:city":"Waterloo",
    "sg:classifiers":[
        {
            "category":"Recreation",
            "type":"Entertainment"
        }
    ],
    "sg:phone":"+1 519 880 9403",
    "sg:postcode":"N2J 3H4",
    "sg:province":"ON",
    "sg:tags":[
        "parlor",
        "billiard"
    ],
    "wof:name":"Sharp Shooters Billiards",
    "wof:placetype":"venue"
},
  "geometry": {"coordinates":[-80.519051,43.477451],"type":"Point"}
}