{
  "type": "Feature",
  "properties": {
    "addr:full":"48 Parker St Belleville ON K8P 1C8",
    "addr:housenumber":"48",
    "addr:postcode":"k8p 1c8",
    "addr:street":"Parker St",
    "iso:country":"CA",
    "sg:address":"48 Parker St",
    "sg:city":"Belleville",
    "sg:classifiers":[
        {
            "category":"Manufacturing",
            "subcategory":"Metals",
            "type":"Manufacturing & Wholesale Goods"
        }
    ],
    "sg:phone":"+1 613 962 5373",
    "sg:postcode":"K8P 1C8",
    "sg:province":"ON",
    "sg:tags":[
        "equipment",
        "heating",
        "system"
    ],
    "wof:name":"Southern Supplies",
    "wof:placetype":"venue"
},
  "geometry": {"coordinates":[-77.392731,44.157581],"type":"Point"}
}