{
  "type": "Feature",
  "properties": {
    "addr:full":"41 Grange St Guelph ON N1E 2T8",
    "addr:housenumber":"41",
    "addr:postcode":"n1e 2t8",
    "addr:street":"Grange St",
    "iso:country":"CA",
    "sg:address":"41 Grange St",
    "sg:city":"Guelph",
    "sg:classifiers":[
        {
            "category":"Health Services",
            "subcategory":"Health Practitioner",
            "type":"Services"
        }
    ],
    "sg:phone":"+1 519 824 5617",
    "sg:postcode":"N1E 2T8",
    "sg:province":"ON",
    "sg:tags":[
        "occupational",
        "safety"
    ],
    "wof:name":"Pan Tec Inc",
    "wof:placetype":"venue"
},
  "geometry": {"coordinates":[-80.242744,43.550922],"type":"Point"}
}