{
  "type": "Feature",
  "properties": {
    "addr:full":"540 Crescent Rd Innisfil ON L9S 2J6",
    "addr:housenumber":"540",
    "addr:postcode":"l9s 2j6",
    "addr:street":"Crescent Rd",
    "iso:country":"CA",
    "sg:address":"540 Crescent Rd",
    "sg:city":"Innisfil",
    "sg:classifiers":[
        {
            "category":"Building & Trades",
            "subcategory":"Construction",
            "type":"Services"
        }
    ],
    "sg:phone":"+1 705 436 6776",
    "sg:postcode":"L9S 2J6",
    "sg:province":"ON",
    "sg:tags":[
        "dealer",
        "landscape",
        "contractor"
    ],
    "wof:name":"Aztec Interlock",
    "wof:placetype":"venue"
},
  "geometry": {"coordinates":[-79.536613,44.355015],"type":"Point"}
}