{
  "type": "Feature",
  "properties": {
    "addr:full":"Digby NS B0V 1A0",
    "addr:postcode":"b0v 1a0",
    "iso:country":"CA",
    "sg:city":"Digby",
    "sg:classifiers":[
        {
            "category":"Government",
            "subcategory":"Office",
            "type":"Public Place"
        }
    ],
    "sg:phone":"+1 902 245 2540",
    "sg:postcode":"B0V 1A0",
    "sg:province":"NS",
    "sg:tags":[
        "village"
    ],
    "wof:name":"Digby Water Commission",
    "wof:placetype":"venue"
},
  "geometry": {"coordinates":[-65.7651062012,44.6172943115],"type":"Point"}
}