{
  "type": "Feature",
  "properties": {
    "addr:full":"2720 19th Ave Nanton AB T0L 1R0",
    "addr:housenumber":"2720",
    "addr:postcode":"t0l 1r0",
    "addr:street":"19Th Ave",
    "iso:country":"CA",
    "sg:address":"2720 19th Ave",
    "sg:city":"Nanton",
    "sg:classifiers":[
        {
            "category":"Freight",
            "type":"Transportation"
        }
    ],
    "sg:phone":"+1 403 646 2683",
    "sg:postcode":"T0L 1R0",
    "sg:province":"AB",
    "sg:tags":[
        "trucking"
    ],
    "wof:name":"Louie's Trucking Ltd",
    "wof:placetype":"venue"
},
  "geometry": {"coordinates":[-113.76445,50.343994],"type":"Point"}
}