{
  "type": "Feature",
  "properties": {
    "addr:full":"8 Keewatin St Winnipeg MB R3E 3B7",
    "addr:housenumber":"8",
    "addr:postcode":"r3e 3b7",
    "addr:street":"Keewatin St",
    "iso:country":"CA",
    "sg:address":"8 Keewatin St",
    "sg:city":"Winnipeg",
    "sg:classifiers":[
        {
            "category":"Travel",
            "subcategory":"Hotels & Motels",
            "type":"Entertainment"
        }
    ],
    "sg:phone":"+1 204 633 9707",
    "sg:postcode":"R3E 3B7",
    "sg:province":"MB",
    "wof:name":"Brooklands Inn",
    "wof:placetype":"venue"
},
  "geometry": {"coordinates":[-97.1954193115,49.9169502258],"type":"Point"}
}