{
  "type": "Feature",
  "properties": {
    "iso:country":"CA",
    "sg:city":"Nanisivik",
    "sg:classifiers":[
        {
            "category":"Government",
            "subcategory":"Office",
            "type":"Public Place"
        }
    ],
    "sg:phone":"+1 867 436 0554",
    "sg:postcode":"X0A 0X0",
    "sg:province":"NU",
    "sg:tags":[
        "village"
    ],
    "wof:name":"Arctic Bay Comm Aerodrome STN",
    "wof:placetype":"venue"
},
  "geometry": {"coordinates":[-84.5329208374,73.0354232788],"type":"Point"}
}