{
  "type": "Feature",
  "properties": {
    "iso:country":"CA",
    "sg:address":"1350 Boul Hymus",
    "sg:city":"Dorval",
    "sg:classifiers":[
        {
            "category":"Autos & Motor Vehicles",
            "subcategory":"Auto Supplies",
            "type":"Retail Goods"
        }
    ],
    "sg:phone":"+1 514 683 3112",
    "sg:postcode":"H9P 1J6",
    "sg:province":"QC",
    "sg:tags":[
        "automobile",
        "parts"
    ],
    "wof:name":"Rowland Hubcaps Enjoliveurs",
    "wof:placetype":"venue"
},
  "geometry": {"coordinates":[-73.76741,45.4869],"type":"Point"}
}