{
  "type": "Feature",
  "properties": {
    "addr:full":"3180 Isleville St Halifax NS B3K 3Y3",
    "addr:housenumber":"3180",
    "addr:postcode":"b3k 3y3",
    "addr:street":"Isleville St",
    "iso:country":"CA",
    "sg:address":"3180 Isleville St",
    "sg:city":"Halifax",
    "sg:classifiers":[
        {
            "category":"Wholesale",
            "subcategory":"Durable Goods & Equipment",
            "type":"Manufacturing & Wholesale Goods"
        }
    ],
    "sg:phone":"+1 902 453 6222",
    "sg:postcode":"B3K 3Y3",
    "sg:province":"NS",
    "sg:tags":[
        "representative",
        "manufacturer"
    ],
    "wof:name":"John Brown Agency",
    "wof:placetype":"venue"
},
  "geometry": {"coordinates":[-63.6015472412,44.6626167297],"type":"Point"}
}