{
  "type": "Feature",
  "properties": {
    "addr:full":"2729 Main St L'Anse Au Loup NL A0K 3L0",
    "addr:housenumber":"2729",
    "addr:postcode":"a0k 3l0",
    "addr:street":"Main St;Au Loup",
    "iso:country":"CA",
    "sg:address":"2729 Main St",
    "sg:city":"L'Anse Au Loup",
    "sg:classifiers":[
        {
            "category":"Food & Beverages",
            "subcategory":"Groceries & Convenience Stores",
            "type":"Retail Goods"
        }
    ],
    "sg:phone":"+1 709 927 5822",
    "sg:postcode":"A0K 3L0",
    "sg:province":"NL",
    "sg:tags":[
        "grocer"
    ],
    "wof:name":"Earle's Groceries Ltd",
    "wof:placetype":"venue"
},
  "geometry": {"coordinates":[-56.8312339783,51.5265731812],"type":"Point"}
}