{
  "type": "Feature",
  "properties": {
    "addr:full":"8444 Hwy 97B Salmon Arm BC V1E 2X6",
    "addr:housenumber":"8444",
    "addr:postcode":"v1e 2x6",
    "addr:street":"Hwy 97B",
    "iso:country":"CA",
    "sg:address":"8444 Hwy 97B",
    "sg:city":"Salmon Arm",
    "sg:classifiers":[
        {
            "category":"Manufacturing",
            "subcategory":"Lumber",
            "type":"Manufacturing & Wholesale Goods"
        }
    ],
    "sg:phone":"+1 250 832 9919",
    "sg:postcode":"V1E 2X6",
    "sg:province":"BC",
    "sg:tags":[
        "sawmill"
    ],
    "wof:name":"Egli's Sawmill",
    "wof:placetype":"venue"
},
  "geometry": {"coordinates":[-119.208359,50.663368],"type":"Point"}
}