{
  "type": "Feature",
  "properties": {
    "addr:full":"460 Whistler St Duncan BC V9L 3P6",
    "addr:housenumber":"460",
    "addr:postcode":"v9l 3p6",
    "addr:street":"Whistler St",
    "iso:country":"CA",
    "sg:address":"460 Whistler St",
    "sg:city":"Duncan",
    "sg:classifiers":[
        {
            "category":"Retail",
            "subcategory":"Repair Shop",
            "type":"Services"
        }
    ],
    "sg:phone":"+1 250 748 4368",
    "sg:postcode":"V9L 3P6",
    "sg:province":"BC",
    "sg:tags":[
        "appliance"
    ],
    "wof:name":"Ram Appliance Svc Ltd",
    "wof:placetype":"venue"
},
  "geometry": {"coordinates":[-123.697701,48.779766],"type":"Point"}
}