{
  "type": "Feature",
  "properties": {
    "iso:country":"CA",
    "sg:address":"5939 Wyandotte St E",
    "sg:city":"Windsor",
    "sg:classifiers":[
        {
            "category":"Wholesale",
            "subcategory":"Chemicals & Plastics",
            "type":"Manufacturing & Wholesale Goods"
        }
    ],
    "sg:phone":"+1 519 974 2682",
    "sg:postcode":"N8S 1M9",
    "sg:province":"ON",
    "wof:name":"Vichem Manufacturing",
    "wof:placetype":"venue"
},
  "geometry": {"coordinates":[-82.966003,42.329044],"type":"Point"}
}