{
  "type": "Feature",
  "properties": {
    "addr:full":"27 Wellington St E Alliston ON L9R 1G8",
    "addr:housenumber":"27",
    "addr:postcode":"l9r 1g8",
    "addr:street":"Wellington St E Alliston",
    "iso:country":"CA",
    "sg:address":"27 Wellington St E",
    "sg:city":"Alliston",
    "sg:classifiers":[
        {
            "category":"Social Services",
            "subcategory":"Child Care",
            "type":"Services"
        }
    ],
    "sg:phone":"+1 705 435 9661",
    "sg:postcode":"L9R 1G8",
    "sg:province":"ON",
    "wof:name":"Wellington Street Day Care",
    "wof:placetype":"venue"
},
  "geometry": {"coordinates":[-79.86758422849999,44.1530570984],"type":"Point"}
}