{
  "type": "Feature",
  "properties": {
    "addr:full":"Quebec QC G1P 3K3",
    "addr:postcode":"g1p 3k3",
    "iso:country":"CA",
    "sg:city":"Quebec",
    "sg:classifiers":[
        {
            "category":"Professional",
            "subcategory":"Detective & Security Services",
            "type":"Services"
        }
    ],
    "sg:phone":"+1 418 683 5703",
    "sg:postcode":"G1P 3K3",
    "sg:province":"QC",
    "sg:tags":[
        "burglary",
        "protective",
        "robbery"
    ],
    "wof:name":"Alarme R Cote Inc",
    "wof:placetype":"venue"
},
  "geometry": {"coordinates":[-71.2193527222,46.8127403259],"type":"Point"}
}