{
  "type": "Feature",
  "properties": {
    "addr:full":"1679 Kenworth St Thornhill BC V8G 3Y4",
    "addr:housenumber":"1679",
    "addr:postcode":"v8g 3y4",
    "addr:street":"Kenworth St",
    "iso:country":"CA",
    "sg:address":"1679 Kenworth St",
    "sg:city":"Thornhill",
    "sg:classifiers":[
        {
            "category":"Building & Trades",
            "subcategory":"Construction",
            "type":"Services"
        }
    ],
    "sg:phone":"+1 250 635 3496",
    "sg:postcode":"V8G 3Y4",
    "sg:province":"BC",
    "sg:tags":[
        "sandblasting",
        "truck"
    ],
    "wof:name":"Peg Rin Paint Shop",
    "wof:placetype":"venue"
},
  "geometry": {"coordinates":[-128.58009338400001,54.4941635132],"type":"Point"}
}