{
  "type": "Feature",
  "properties": {
    "addr:full":"989 Nelson St # 417 Vancouver BC V6Z 2S1",
    "addr:housenumber":"989",
    "addr:postcode":"v6z 2s1",
    "addr:street":"Nelson St # 417",
    "iso:country":"CA",
    "sg:address":"989 Nelson St # 417",
    "sg:city":"Vancouver",
    "sg:classifiers":[
        {
            "category":"Real Estate",
            "subcategory":"Real Estate Operator",
            "type":"Services"
        }
    ],
    "sg:phone":"+1 604 681 7822",
    "sg:postcode":"V6Z 2S1",
    "sg:province":"BC",
    "sg:tags":[
        "apartment"
    ],
    "wof:name":"Electra",
    "wof:placetype":"venue"
},
  "geometry": {"coordinates":[-123.12567900000001,49.281174],"type":"Point"}
}