{
  "type": "Feature",
  "properties": {
    "addr:full":"2305 Mcphillips St Winnipeg MB R2V 3E1",
    "addr:housenumber":"2305",
    "addr:postcode":"r2v 3e1",
    "addr:street":"Mcphillips St",
    "iso:country":"CA",
    "sg:address":"2305 Mcphillips St",
    "sg:city":"Winnipeg",
    "sg:classifiers":[
        {
            "category":"Shopping",
            "subcategory":"Jewelry",
            "type":"Retail Goods"
        }
    ],
    "sg:phone":"+1 204 339 2075",
    "sg:postcode":"R2V 3E1",
    "sg:province":"MB",
    "sg:tags":[
        "jeweler"
    ],
    "wof:name":"Peoples Jewellers",
    "wof:placetype":"venue"
},
  "geometry": {"coordinates":[-97.1476135254,49.9530601501],"type":"Point"}
}