{
  "type": "Feature",
  "properties": {
    "addr:full":"5 Rue Will Sainte-Anne-DE-Madawaska NB E7E 1J3",
    "addr:housenumber":"5",
    "addr:postcode":"e7e 1j3",
    "addr:street":"Rue Will",
    "iso:country":"CA",
    "sg:address":"5 Rue Will",
    "sg:city":"Sainte-Anne-DE-Madawaska",
    "sg:classifiers":[
        {
            "category":"Health Services",
            "subcategory":"Medical Lab",
            "type":"Services"
        }
    ],
    "sg:phone":"+1 506 445 2783",
    "sg:postcode":"E7E 1J3",
    "sg:province":"NB",
    "wof:name":"Daniel Thibodeau Denturist",
    "wof:placetype":"venue"
},
  "geometry": {"coordinates":[-68.020737,47.245541],"type":"Point"}
}