{
  "type": "Feature",
  "properties": {
    "addr:full":"855 Fredericton Station Rd Hunter River PE C0A 1N0",
    "addr:housenumber":"855",
    "addr:postcode":"c0a 1n0",
    "addr:street":"Fredericton Station Rd",
    "iso:country":"CA",
    "sg:address":"855 Fredericton Station Rd",
    "sg:city":"Hunter River",
    "sg:classifiers":[
        {
            "category":"Building & Trades",
            "subcategory":"Construction",
            "type":"Services"
        }
    ],
    "sg:phone":"+1 902 621 0841",
    "sg:postcode":"C0A 1N0",
    "sg:province":"PE",
    "sg:tags":[
        "paving",
        "contractor"
    ],
    "wof:name":"Central Roadways",
    "wof:placetype":"venue"
},
  "geometry": {"coordinates":[-63.343147,46.351761],"type":"Point"}
}