{
  "type": "Feature",
  "properties": {
    "addr:full":"325 Garrison Rd Fort Erie ON L2A 1M9",
    "addr:housenumber":"325",
    "addr:postcode":"l2a 1m9",
    "addr:street":"Garrison Rd",
    "iso:country":"CA",
    "sg:address":"325 Garrison Rd",
    "sg:city":"Fort Erie",
    "sg:classifiers":[
        {
            "category":"Restaurant",
            "type":"Food & Drink"
        }
    ],
    "sg:phone":"+1 905 871 4965",
    "sg:postcode":"L2A 1M9",
    "sg:province":"ON",
    "wof:name":"Mc Donald's",
    "wof:placetype":"venue"
},
  "geometry": {"coordinates":[-78.926651001,42.9056777954],"type":"Point"}
}