{
  "type": "Feature",
  "properties": {
    "addr:full":"116 King St Charlottetown PE C1A 1B5",
    "addr:housenumber":"116",
    "addr:postcode":"c1a 1b5",
    "addr:street":"King St",
    "iso:country":"CA",
    "sg:address":"116 King St",
    "sg:city":"Charlottetown",
    "sg:classifiers":[
        {
            "category":"Organizations",
            "subcategory":"Community Association",
            "type":"Services"
        }
    ],
    "sg:phone":"+1 902 894 3764",
    "sg:postcode":"C1A 1B5",
    "sg:province":"PE",
    "sg:tags":[
        "club"
    ],
    "wof:name":"Charlottetown Club",
    "wof:placetype":"venue"
},
  "geometry": {"coordinates":[-63.1242599487,46.233039856],"type":"Point"}
}