{
  "type": "Feature",
  "properties": {
    "addr:full":"2718 Fredericton Rd Salisbury NB E4J 3C7",
    "addr:housenumber":"2718",
    "addr:postcode":"e4j 3c7",
    "addr:street":"Fredericton Rd",
    "iso:country":"CA",
    "sg:address":"2718 Fredericton Rd",
    "sg:city":"Salisbury",
    "sg:classifiers":[
        {
            "category":"Bars & Pubs",
            "type":"Food & Drink"
        }
    ],
    "sg:phone":"+1 506 372 8008",
    "sg:postcode":"E4J 3C7",
    "sg:province":"NB",
    "sg:tags":[
        "lounge",
        "cocktail"
    ],
    "wof:name":"Big Dog Lounge",
    "wof:placetype":"venue"
},
  "geometry": {"coordinates":[-65.0407485962,46.0308761597],"type":"Point"}
}