{
  "type": "Feature",
  "properties": {
    "iso:country":"CA",
    "sg:address":"230 Martin Ave W",
    "sg:city":"Winnipeg",
    "sg:classifiers":[
        {
            "category":"Building & Trades",
            "subcategory":"Construction",
            "type":"Services"
        }
    ],
    "sg:phone":"+1 204 661 5118",
    "sg:postcode":"R2L 0B6",
    "sg:province":"MB",
    "sg:tags":[
        "maker",
        "cabinet"
    ],
    "wof:name":"Artec Design Kitchens",
    "wof:placetype":"venue"
},
  "geometry": {"coordinates":[-97.110466,49.915287],"type":"Point"}
}