{
  "type": "Feature",
  "properties": {
    "addr:full":"Calgary AB T2C 1R5",
    "addr:postcode":"t2c 1r5",
    "iso:country":"CA",
    "sg:city":"Calgary",
    "sg:classifiers":[
        {
            "category":"Manufacturing",
            "subcategory":"Metals",
            "type":"Manufacturing & Wholesale Goods"
        }
    ],
    "sg:phone":"+1 403 279 1983",
    "sg:postcode":"T2C 1R5",
    "sg:province":"AB",
    "sg:tags":[
        "work",
        "sheet",
        "contractor"
    ],
    "wof:name":"Asm Industries",
    "wof:placetype":"venue"
},
  "geometry": {"coordinates":[-113.994011,51.005096],"type":"Point"}
}