{
  "type": "Feature",
  "properties": {
    "addr:full":"433 St Paul Ave Brantford ON N3R 4N8",
    "addr:housenumber":"433",
    "addr:postcode":"n3r 4n8",
    "addr:street":"St Paul Ave",
    "iso:country":"CA",
    "sg:address":"433 St Paul Ave",
    "sg:city":"Brantford",
    "sg:classifiers":[
        {
            "category":"Cinema",
            "subcategory":"Movie Rental",
            "type":"Entertainment"
        }
    ],
    "sg:phone":"+1 519 750 0079",
    "sg:postcode":"N3R 4N8",
    "sg:province":"ON",
    "sg:tags":[
        "leasing",
        "video",
        "disc",
        "tape"
    ],
    "wof:name":"Adult Movie Emporium",
    "wof:placetype":"venue"
},
  "geometry": {"coordinates":[-80.2723770142,43.1588134766],"type":"Point"}
}