{
  "type": "Feature",
  "properties": {
    "addr:full":"2625B Weston Rd # 7 North York ON M9N 3W1",
    "addr:housenumber":"2625b",
    "addr:postcode":"m9n 3w1",
    "addr:street":"Weston Rd # 7",
    "iso:country":"CA",
    "sg:address":"2625B Weston Rd # 7",
    "sg:city":"North York",
    "sg:classifiers":[
        {
            "category":"Home & Garden",
            "subcategory":"Furniture",
            "type":"Retail Goods"
        }
    ],
    "sg:phone":"+1 416 249 1211",
    "sg:postcode":"M9N 3W1",
    "sg:province":"ON",
    "wof:name":"Brick",
    "wof:placetype":"venue"
},
  "geometry": {"coordinates":[-79.535194,43.711742],"type":"Point"}
}