{
  "type": "Feature",
  "properties": {
    "addr:full":"528 Av Ogilvy Montreal QC H3N 1M8",
    "addr:postcode":"h3n 1m8",
    "addr:street":"528 Av Ogilvy",
    "iso:country":"CA",
    "sg:address":"528 Av Ogilvy",
    "sg:city":"Montreal",
    "sg:classifiers":[
        {
            "category":"Education",
            "subcategory":"Special Training",
            "type":"Public Place"
        }
    ],
    "sg:phone":"+1 514 278 1824",
    "sg:postcode":"H3N 1M8",
    "sg:province":"QC",
    "sg:tags":[
        "instruction",
        "driving"
    ],
    "wof:name":"Abc Multi Visions",
    "wof:placetype":"venue"
},
  "geometry": {"coordinates":[-73.625191,45.528805],"type":"Point"}
}