{
  "type": "Feature",
  "properties": {
    "addr:full":"Huntingdon QC J0S 1H0",
    "addr:postcode":"j0s 1h0",
    "iso:country":"CA",
    "sg:city":"Huntingdon",
    "sg:classifiers":[
        {
            "category":"Government",
            "subcategory":"Office",
            "type":"Public Place"
        }
    ],
    "sg:phone":"+1 450 264 3027",
    "sg:postcode":"J0S 1H0",
    "sg:province":"QC",
    "sg:tags":[
        "village"
    ],
    "wof:name":"Haut-St-Laurent Svc D'Amen",
    "wof:placetype":"venue"
},
  "geometry": {"coordinates":[-74.172905,45.088146],"type":"Point"}
}