{
  "type": "Feature",
  "properties": {
    "addr:full":"5652 LA Grande-Allee Saint-Hubert QC J3Y 1B1",
    "addr:housenumber":"5652",
    "addr:postcode":"j3y 1b1",
    "addr:street":"La Grande-Allee",
    "iso:country":"CA",
    "sg:address":"5652 LA Grande-Allee",
    "sg:city":"Saint-Hubert",
    "sg:classifiers":[
        {
            "category":"Food & Beverages",
            "subcategory":"Groceries & Convenience Stores",
            "type":"Retail Goods"
        }
    ],
    "sg:phone":"+1 450 443 8638",
    "sg:postcode":"J3Y 1B1",
    "sg:province":"QC",
    "sg:tags":[
        "grocer"
    ],
    "wof:name":"Marche Antillais Grandes Allee",
    "wof:placetype":"venue"
},
  "geometry": {"coordinates":[-73.442329,45.474373],"type":"Point"}
}