{
  "type": "Feature",
  "properties": {
    "addr:full":"32 Factory Alley Waterford ON N0E 1Y0",
    "addr:housenumber":"32",
    "addr:postcode":"n0e 1y0",
    "addr:street":"Factory Alley",
    "iso:country":"CA",
    "sg:address":"32 Factory Alley",
    "sg:city":"Waterford",
    "sg:classifiers":[
        {
            "category":"Freight",
            "type":"Transportation"
        }
    ],
    "sg:phone":"+1 519 443 6193",
    "sg:postcode":"N0E 1Y0",
    "sg:province":"ON",
    "sg:tags":[
        "trucking"
    ],
    "wof:name":"C D Ace Transportation Inc",
    "wof:placetype":"venue"
},
  "geometry": {"coordinates":[-80.2972412109,42.9356689453],"type":"Point"}
}