{
  "type": "Feature",
  "properties": {
    "iso:country":"CA",
    "sg:address":"4244 Rue DE Salaberry",
    "sg:city":"Montreal",
    "sg:classifiers":[
        {
            "category":"Real Estate",
            "subcategory":"Surveying",
            "type":"Services"
        }
    ],
    "sg:phone":"+1 514 337 6141",
    "sg:postcode":"H4J 1H3",
    "sg:province":"QC",
    "sg:tags":[
        "surveyor"
    ],
    "wof:name":"Gascon, Yves",
    "wof:placetype":"venue"
},
  "geometry": {"coordinates":[-73.7043685913,45.534236908],"type":"Point"}
}