{
  "type": "Feature",
  "properties": {
    "addr:full":"272 Boul Saint-Joseph Hull QC J8Y 3Y3",
    "addr:housenumber":"272",
    "addr:postcode":"j8y 3y3",
    "addr:street":"Boul Saint-Joseph",
    "iso:country":"CA",
    "sg:address":"272 Boul Saint-Joseph",
    "sg:city":"Hull",
    "sg:classifiers":[
        {
            "category":"Health Services",
            "subcategory":"Medical Lab",
            "type":"Services"
        }
    ],
    "sg:phone":"+1 819 771 4565",
    "sg:postcode":"J8Y 3Y3",
    "sg:province":"QC",
    "sg:tags":[
        "laboratory"
    ],
    "wof:name":"Oraltech",
    "wof:placetype":"venue"
},
  "geometry": {"coordinates":[-75.732895,45.437958],"type":"Point"}
}