{
  "type": "Feature",
  "properties": {
    "addr:full":"32 Michigan St Blind River ON P0R 1B0",
    "addr:housenumber":"32",
    "addr:postcode":"p0r 1b0",
    "addr:street":"Michigan St",
    "iso:country":"CA",
    "sg:address":"32 Michigan St",
    "sg:city":"Blind River",
    "sg:classifiers":[
        {
            "category":"Organizations",
            "subcategory":"Religious Organization",
            "type":"Services"
        }
    ],
    "sg:phone":"+1 705 356 2502",
    "sg:postcode":"P0R 1B0",
    "sg:province":"ON",
    "sg:tags":[
        "church"
    ],
    "wof:name":"St Saviour's Anglican Parish",
    "wof:placetype":"venue"
},
  "geometry": {"coordinates":[-82.9595565796,46.184715271],"type":"Point"}
}