{
  "type": "Feature",
  "properties": {
    "addr:full":"267 Rue Notre-Dame Tring-Jonction QC G0N 1X0",
    "addr:housenumber":"267",
    "addr:postcode":"g0n 1x0",
    "addr:street":"Rue Notre-Dame",
    "iso:country":"CA",
    "sg:address":"267 Rue Notre-Dame",
    "sg:city":"Tring-Jonction",
    "sg:classifiers":[
        {
            "category":"Manufacturing",
            "subcategory":"Building Materials",
            "type":"Manufacturing & Wholesale Goods"
        }
    ],
    "sg:phone":"+1 418 426 3005",
    "sg:postcode":"G0N 1X0",
    "sg:province":"QC",
    "sg:tags":[
        "plywood",
        "veneer"
    ],
    "wof:name":"Placages Roy Inc",
    "wof:placetype":"venue"
},
  "geometry": {"coordinates":[-70.995659,46.270298],"type":"Point"}
}