{
  "type": "Feature",
  "properties": {
    "addr:full":"181 Woodstream Blvd Woodbridge ON L4L 8G9",
    "addr:housenumber":"181",
    "addr:postcode":"l4l 8g9",
    "addr:street":"Woodstream Blvd",
    "iso:country":"CA",
    "sg:address":"181 Woodstream Blvd",
    "sg:city":"Woodbridge",
    "sg:classifiers":[
        {
            "category":"Restaurant",
            "type":"Food & Drink"
        }
    ],
    "sg:phone":"+1 905 851 3283",
    "sg:postcode":"L4L 8G9",
    "sg:province":"ON",
    "sg:tags":[
        "cafe"
    ],
    "wof:name":"Number 7 Bar & Cafe",
    "wof:placetype":"venue"
},
  "geometry": {"coordinates":[-79.60656,43.773632],"type":"Point"}
}