{
  "type": "Feature",
  "properties": {
    "addr:full":"Wetaskiwin AB T9A 1W9",
    "addr:postcode":"t9a 1w9",
    "iso:country":"CA",
    "sg:city":"Wetaskiwin",
    "sg:classifiers":[
        {
            "category":"Building & Trades",
            "subcategory":"Landscaping Services",
            "type":"Services"
        }
    ],
    "sg:phone":"+1 780 352 6900",
    "sg:postcode":"T9A 1W9",
    "sg:province":"AB",
    "sg:tags":[
        "tree",
        "landscape",
        "contractor"
    ],
    "wof:name":"Forster Nurseries Ltd",
    "wof:placetype":"venue"
},
  "geometry": {"coordinates":[-113.377243042,52.969909668],"type":"Point"}
}