{
  "type": "Feature",
  "properties": {
    "addr:full":"Carrying Place ON K0K 1L0",
    "addr:postcode":"k0k 1l0",
    "addr:street":"Carrying Place",
    "iso:country":"CA",
    "sg:city":"Carrying Place",
    "sg:classifiers":[
        {
            "category":"Building & Trades",
            "subcategory":"Construction",
            "type":"Services"
        }
    ],
    "sg:phone":"+1 613 392 5039",
    "sg:postcode":"K0K 1L0",
    "sg:province":"ON",
    "sg:tags":[
        "general",
        "contractor"
    ],
    "wof:name":"Jmk Homes",
    "wof:placetype":"venue"
},
  "geometry": {"coordinates":[-77.58065795900001,44.0482940674],"type":"Point"}
}