{
  "type": "Feature",
  "properties": {
    "addr:full":"307 Argyle St S Caledonia ON N3W 1K7",
    "addr:housenumber":"307",
    "addr:postcode":"n3w 1k7",
    "addr:street":"Argyle St S",
    "iso:country":"CA",
    "sg:address":"307 Argyle St S",
    "sg:city":"Caledonia",
    "sg:classifiers":[
        {
            "category":"Restaurant",
            "type":"Food & Drink"
        }
    ],
    "sg:phone":"+1 905 765 7143",
    "sg:postcode":"N3W 1K7",
    "sg:province":"ON",
    "sg:tags":[
        "sandwich",
        "out"
    ],
    "wof:name":"Stan's Subs",
    "wof:placetype":"venue"
},
  "geometry": {"coordinates":[-79.95957199999999,43.06427],"type":"Point"}
}