{
  "type": "Feature",
  "properties": {
    "addr:full":"113 5th Ave E Kindersley SK S0L 1S0",
    "addr:housenumber":"113",
    "addr:postcode":"s0l 1s0",
    "addr:street":"5Th Ave E Kindersley",
    "iso:country":"CA",
    "sg:address":"113 5th Ave E",
    "sg:city":"Kindersley",
    "sg:classifiers":[
        {
            "category":"Building & Trades",
            "subcategory":"Electrical",
            "type":"Services"
        }
    ],
    "sg:phone":"+1 306 463 2588",
    "sg:postcode":"S0L 1S0",
    "sg:province":"SK",
    "sg:tags":[
        "electric",
        "contractor"
    ],
    "wof:name":"Pioneer Electric",
    "wof:placetype":"venue"
},
  "geometry": {"coordinates":[-109.15656280499999,51.4699897766],"type":"Point"}
}