{
  "type": "Feature",
  "properties": {
    "addr:full":"22521 Island Rd Port Perry ON L9L 1B6",
    "addr:housenumber":"22521",
    "addr:postcode":"l9l 1b6",
    "addr:street":"Island Rd",
    "iso:country":"CA",
    "sg:address":"22521 Island Rd",
    "sg:city":"Port Perry",
    "sg:classifiers":[
        {
            "category":"Organizations",
            "subcategory":"Community Association",
            "type":"Services"
        }
    ],
    "sg:phone":"+1 905 985 3337",
    "sg:postcode":"L9L 1B6",
    "sg:province":"ON",
    "sg:tags":[
        "native"
    ],
    "wof:name":"Mississaugas of Scugog Island",
    "wof:placetype":"venue"
},
  "geometry": {"coordinates":[-78.88273599999999,44.191406],"type":"Point"}
}