{
  "type": "Feature",
  "properties": {
    "addr:full":"Elsa St Margo SK S0A 2M0",
    "addr:postcode":"s0a 2m0",
    "addr:street":"Elsa St",
    "iso:country":"CA",
    "sg:address":"Elsa St",
    "sg:city":"Margo",
    "sg:classifiers":[
        {
            "category":"Professional",
            "subcategory":"Business Services",
            "type":"Services"
        }
    ],
    "sg:phone":"+1 306 324 2056",
    "sg:postcode":"S0A 2M0",
    "sg:province":"SK",
    "sg:tags":[
        "auctioneer"
    ],
    "wof:name":"Tim's Auction Svc",
    "wof:placetype":"venue"
},
  "geometry": {"coordinates":[-103.335472,51.827301],"type":"Point"}
}