{
  "type": "Feature",
  "properties": {
    "addr:full":"PO Box 480 Eckville AB T0M 0X0",
    "addr:housenumber":"po",
    "addr:postcode":"480;t0m 0x0",
    "addr:street":"Box",
    "iso:country":"CA",
    "sg:address":"PO Box 480",
    "sg:city":"Eckville",
    "sg:classifiers":[
        {
            "category":"Mining & Drilling",
            "type":"Manufacturing & Wholesale Goods"
        }
    ],
    "sg:phone":"+1 403 746 8300",
    "sg:postcode":"T0M 0X0",
    "sg:province":"AB",
    "sg:tags":[
        "company",
        "oil"
    ],
    "wof:name":"Petro-Canada",
    "wof:placetype":"venue"
},
  "geometry": {"coordinates":[-114.361465,52.359573],"type":"Point"}
}