{
  "type": "Feature",
  "properties": {
    "iso:country":"CA",
    "sg:city":"Toronto",
    "sg:classifiers":[
        {
            "category":"Real Estate",
            "subcategory":"Architect",
            "type":"Services"
        }
    ],
    "sg:phone":"+1 416 964 1902",
    "sg:postcode":"M4Y 1P9",
    "sg:province":"ON",
    "wof:name":"Loffler, Keith",
    "wof:placetype":"venue"
},
  "geometry": {"coordinates":[-79.3863372803,43.6680145264],"type":"Point"}
}