{
  "type": "Feature",
  "properties": {
    "iso:country":"CA",
    "sg:address":"15341 105 Ave NW",
    "sg:city":"Edmonton",
    "sg:classifiers":[
        {
            "category":"Autos & Motor Vehicles",
            "subcategory":"Auto Supplies",
            "type":"Retail Goods"
        }
    ],
    "sg:phone":"+1 780 413 1655",
    "sg:postcode":"T5P 0T6",
    "sg:province":"AB",
    "sg:tags":[
        "fireplace",
        "gas",
        "cleaning",
        "chimney"
    ],
    "wof:name":"Acclaimed Furnace Cleaning",
    "wof:placetype":"venue"
},
  "geometry": {"coordinates":[-113.58581543,53.5477256775],"type":"Point"}
}