{
  "type": "Feature",
  "properties": {
    "iso:country":"CA",
    "sg:address":"RR 2",
    "sg:city":"Tottenham",
    "sg:classifiers":[
        {
            "category":"Building & Trades",
            "subcategory":"Plumbing",
            "type":"Services"
        }
    ],
    "sg:phone":"+1 905 939 7078",
    "sg:postcode":"L0G 1W0",
    "sg:province":"ON",
    "sg:tags":[
        "control",
        "air",
        "pollution"
    ],
    "wof:name":"Northstream Industries Ltd",
    "wof:placetype":"venue"
},
  "geometry": {"coordinates":[-79.805786,44.022877],"type":"Point"}
}