{
  "type": "Feature",
  "properties": {
    "addr:full":"558 Mcdermot Ave Winnipeg MB R3A 0C1",
    "addr:housenumber":"558",
    "addr:postcode":"r3a 0c1",
    "addr:street":"Mcdermot Ave",
    "iso:country":"CA",
    "sg:address":"558 Mcdermot Ave",
    "sg:city":"Winnipeg",
    "sg:classifiers":[
        {
            "category":"Wholesale",
            "subcategory":"Apparel",
            "type":"Manufacturing & Wholesale Goods"
        }
    ],
    "sg:phone":"+1 204 772 4095",
    "sg:postcode":"R3A 0C1",
    "sg:province":"MB",
    "sg:tags":[
        "glove"
    ],
    "wof:name":"Utility Glove Ltd",
    "wof:placetype":"venue"
},
  "geometry": {"coordinates":[-97.15226,49.900745],"type":"Point"}
}