{
  "type": "Feature",
  "properties": {
    "addr:full":"Fenelon Falls ON K0M 1N0",
    "addr:postcode":"k0m 1n0",
    "iso:country":"CA",
    "sg:city":"Fenelon Falls",
    "sg:classifiers":[
        {
            "category":"Retail",
            "subcategory":"Repair Shop",
            "type":"Services"
        }
    ],
    "sg:phone":"+1 705 887 4050",
    "sg:postcode":"K0M 1N0",
    "sg:province":"ON",
    "sg:tags":[
        "lock",
        "locksmith"
    ],
    "wof:name":"Country Locksmith",
    "wof:placetype":"venue"
},
  "geometry": {"coordinates":[-78.738693,44.532677],"type":"Point"}
}