{
  "type": "Feature",
  "properties": {
    "addr:full":"548 Road 202 Pike River QC J0J 1P0",
    "addr:postcode":"j0j 1p0",
    "addr:street":"548 Road 202",
    "iso:country":"CA",
    "sg:address":"548 Road 202",
    "sg:city":"Pike River",
    "sg:classifiers":[
        {
            "category":"Government",
            "subcategory":"Office",
            "type":"Public Place"
        }
    ],
    "sg:phone":"+1 450 248 2716",
    "sg:postcode":"J0J 1P0",
    "sg:province":"QC",
    "sg:tags":[
        "municipality"
    ],
    "wof:name":"St-Pierre Inspecteur Municipal",
    "wof:placetype":"venue"
},
  "geometry": {"coordinates":[-73.0684051514,45.1209335327],"type":"Point"}
}