{
  "type": "Feature",
  "properties": {
    "addr:full":"Rigaud QC J0P 1P0",
    "addr:postcode":"j0p 1p0",
    "iso:country":"CA",
    "sg:city":"Rigaud",
    "sg:classifiers":[
        {
            "category":"Retail",
            "subcategory":"Funeral Services",
            "type":"Services"
        }
    ],
    "sg:phone":"+1 450 451 5363",
    "sg:postcode":"J0P 1P0",
    "sg:province":"QC",
    "sg:tags":[
        "director"
    ],
    "wof:name":"Residences Funeraire Roussin",
    "wof:placetype":"venue"
},
  "geometry": {"coordinates":[-74.296532,45.479488],"type":"Point"}
}