{
  "type": "Feature",
  "properties": {
    "addr:full":"202 Wolf St Banff AB T1L 1H1",
    "addr:housenumber":"202",
    "addr:postcode":"t1l 1h1",
    "addr:street":"Wolf St",
    "iso:country":"CA",
    "sg:address":"202 Wolf St",
    "sg:city":"Banff",
    "sg:classifiers":[
        {
            "category":"Food & Beverages",
            "subcategory":"Liquor & Beverages",
            "type":"Retail Goods"
        }
    ],
    "sg:phone":"+1 403 762 2518",
    "sg:postcode":"T1L 1H1",
    "sg:province":"AB",
    "sg:tags":[
        "store"
    ],
    "wof:name":"Cascade Liquor World",
    "wof:placetype":"venue"
},
  "geometry": {"coordinates":[-115.57268524200001,51.1785812378],"type":"Point"}
}