{
  "type": "Feature",
  "properties": {
    "addr:full":"8220 Bowridge Cres NW Calgary AB T3B 2V1",
    "addr:housenumber":"8220",
    "addr:postcode":"t3b 2v1",
    "addr:street":"Bowridge Cres Nw",
    "iso:country":"CA",
    "sg:address":"8220 Bowridge Cres NW",
    "sg:city":"Calgary",
    "sg:classifiers":[
        {
            "category":"Travel",
            "subcategory":"Hotels & Motels",
            "type":"Entertainment"
        }
    ],
    "sg:phone":"+1 403 288 4441",
    "sg:postcode":"T3B 2V1",
    "sg:province":"AB",
    "wof:name":"Four Points By Sheraton",
    "wof:placetype":"venue"
},
  "geometry": {"coordinates":[-114.206734,51.083538],"type":"Point"}
}