{
  "type": "Feature",
  "properties": {
    "addr:full":"Port Coquitlam BC V3B 1A7",
    "addr:postcode":"v3b 1a7",
    "iso:country":"CA",
    "sg:city":"Port Coquitlam",
    "sg:classifiers":[
        {
            "category":"Retail",
            "subcategory":"Auto Repair",
            "type":"Services"
        }
    ],
    "sg:phone":"+1 604 942 5544",
    "sg:postcode":"V3B 1A7",
    "sg:province":"BC",
    "sg:tags":[
        "body",
        "automobile",
        "painting"
    ],
    "wof:name":"Mark's Auto Body Ltd",
    "wof:placetype":"venue"
},
  "geometry": {"coordinates":[-122.771675,49.265701],"type":"Point"}
}