{
  "type": "Feature",
  "properties": {
    "addr:full":"304 Ch Du Bord-Du-Lac-Lakeshr # B Pointe-Claire QC H9S 4L5",
    "addr:housenumber":"304",
    "addr:postcode":"h9s 4l5",
    "addr:street":"Ch Du Bord-Du-Lac-Lakeshr # B",
    "iso:country":"CA",
    "sg:address":"304 Ch Du Bord-Du-Lac-Lakeshr # B",
    "sg:city":"Pointe-Claire",
    "sg:classifiers":[
        {
            "category":"Shopping",
            "subcategory":"Clothing, Apparel, & Fashions",
            "type":"Retail Goods"
        }
    ],
    "sg:phone":"+1 514 426 9049",
    "sg:postcode":"H9S 4L5",
    "sg:province":"QC",
    "sg:tags":[
        "shop",
        "bridal"
    ],
    "wof:name":"Gerrielle Bridal Shop & Btq",
    "wof:placetype":"venue"
},
  "geometry": {"coordinates":[-73.826469,45.428707],"type":"Point"}
}