{
  "type": "Feature",
  "properties": {
    "addr:full":"14630 107A Ave Surrey BC V3R 1V1",
    "addr:housenumber":"14630",
    "addr:postcode":"v3r 1v1",
    "addr:street":"107A Ave",
    "iso:country":"CA",
    "sg:address":"14630 107A Ave",
    "sg:city":"Surrey",
    "sg:classifiers":[
        {
            "category":"Organizations",
            "subcategory":"Religious Organization",
            "type":"Services"
        }
    ],
    "sg:phone":"+1 604 582 2650",
    "sg:postcode":"V3R 1V1",
    "sg:province":"BC",
    "sg:tags":[
        "church"
    ],
    "wof:name":"Hindi Punjabi Faserview Gospel",
    "wof:placetype":"venue"
},
  "geometry": {"coordinates":[-122.830215,49.105179],"type":"Point"}
}