{
  "type": "Feature",
  "properties": {
    "addr:full":"1 Eglinton Sq Scarborough ON M1L 2K1",
    "addr:housenumber":"1",
    "addr:postcode":"m1l 2k1",
    "addr:street":"Eglinton Sq",
    "iso:country":"CA",
    "sg:address":"1 Eglinton Sq",
    "sg:city":"Scarborough",
    "sg:classifiers":[
        {
            "category":"Recreation",
            "type":"Entertainment"
        }
    ],
    "sg:phone":"+1 416 285 8958",
    "sg:postcode":"M1L 2K1",
    "sg:province":"ON",
    "sg:tags":[
        "lottery",
        "agent"
    ],
    "wof:name":"Eglinton Sq Lotto Info Kiosk",
    "wof:placetype":"venue"
},
  "geometry": {"coordinates":[-79.30192599999999,43.723385],"type":"Point"}
}