{
  "type": "Feature",
  "properties": {
    "addr:full":"411 Bancroft St Ashcroft BC V0K 1A0",
    "addr:housenumber":"411",
    "addr:postcode":"v0k 1a0",
    "addr:street":"Bancroft St",
    "iso:country":"CA",
    "sg:address":"411 Bancroft St",
    "sg:city":"Ashcroft",
    "sg:classifiers":[
        {
            "category":"Manufacturing",
            "subcategory":"Metals",
            "type":"Manufacturing & Wholesale Goods"
        }
    ],
    "sg:phone":"+1 250 453 9655",
    "sg:postcode":"V0K 1A0",
    "sg:province":"BC",
    "sg:tags":[
        "joint",
        "expansion"
    ],
    "wof:name":"Johnson Elastomers",
    "wof:placetype":"venue"
},
  "geometry": {"coordinates":[-121.283172607,50.7211761475],"type":"Point"}
}