{
  "type": "Feature",
  "properties": {
    "addr:full":"92 Shaftesbury Ave Toronto ON M4T 1A5",
    "addr:housenumber":"92",
    "addr:postcode":"m4t 1a5",
    "addr:street":"Shaftesbury Ave",
    "iso:country":"CA",
    "sg:address":"92 Shaftesbury Ave",
    "sg:city":"Toronto",
    "sg:classifiers":[
        {
            "category":"Health Services",
            "subcategory":"Optometrist",
            "type":"Services"
        }
    ],
    "sg:phone":"+1 519 856 9921",
    "sg:postcode":"M4T 1A5",
    "sg:province":"ON",
    "sg:tags":[
        "attorney"
    ],
    "wof:name":"Gropp, John W OD",
    "wof:placetype":"venue"
},
  "geometry": {"coordinates":[-79.387878,43.682907],"type":"Point"}
}