{
  "type": "Feature",
  "properties": {
    "addr:full":"Stony Mountain MB R0C 3A0",
    "addr:postcode":"r0c 3a0",
    "iso:country":"CA",
    "sg:city":"Stony Mountain",
    "sg:classifiers":[
        {
            "category":"Government",
            "subcategory":"Office",
            "type":"Public Place"
        }
    ],
    "sg:phone":"+1 204 344 5111",
    "sg:postcode":"R0C 3A0",
    "sg:province":"MB",
    "wof:name":"Canada Penitentiaries Rockwood",
    "wof:placetype":"venue"
},
  "geometry": {"coordinates":[-97.2185058594,50.0859260559],"type":"Point"}
}