{
  "type": "Feature",
  "properties": {
    "addr:full":"6100 Boul Des Grandes-Prairies Saint-Leonard QC H1P 1A2",
    "addr:housenumber":"6100",
    "addr:postcode":"h1p 1a2",
    "addr:street":"Boul Des Grandes-Prairies",
    "iso:country":"CA",
    "sg:address":"6100 Boul Des Grandes-Prairies",
    "sg:city":"Saint-Leonard",
    "sg:classifiers":[
        {
            "category":"Professional",
            "subcategory":"Art Services",
            "type":"Services"
        }
    ],
    "sg:phone":"+1 514 327 4404",
    "sg:postcode":"H1P 1A2",
    "sg:province":"QC",
    "sg:tags":[
        "graphic",
        "designer"
    ],
    "wof:name":"Enterprises Cassi",
    "wof:placetype":"venue"
},
  "geometry": {"coordinates":[-73.6084365845,45.602306366],"type":"Point"}
}