{
  "type": "Feature",
  "properties": {
    "iso:country":"CA",
    "sg:address":"Dollard",
    "sg:city":"Bourget",
    "sg:classifiers":[
        {
            "category":"Organizations",
            "subcategory":"Professional Association",
            "type":"Services"
        }
    ],
    "sg:phone":"+1 613 487 3145",
    "sg:postcode":"K0A 1E0",
    "sg:province":"ON",
    "wof:name":"Chevaliers DE Colomb Bourget",
    "wof:placetype":"venue"
},
  "geometry": {"coordinates":[-75.1578140259,45.4366188049],"type":"Point"}
}