{
  "type": "Feature",
  "properties": {
    "addr:full":"56 Yonge St Toronto ON M5E 1G5",
    "addr:housenumber":"56",
    "addr:postcode":"m5e 1g5",
    "addr:street":"Yonge St",
    "iso:country":"CA",
    "sg:address":"56 Yonge St",
    "sg:city":"Toronto",
    "sg:classifiers":[
        {
            "category":"Travel",
            "subcategory":"Hotels & Motels",
            "type":"Entertainment"
        }
    ],
    "sg:phone":"+1 416 363 1666",
    "sg:postcode":"M5E 1G5",
    "sg:province":"ON",
    "wof:name":"Hotel Victoria",
    "wof:placetype":"venue"
},
  "geometry": {"coordinates":[-79.377686,43.648205],"type":"Point"}
}