{
  "type": "Feature",
  "properties": {
    "addr:full":"792 Main St Waterford ON N0E 1Y0",
    "addr:housenumber":"792",
    "addr:postcode":"n0e 1y0",
    "addr:street":"Main St",
    "iso:country":"CA",
    "sg:address":"792 Main St",
    "sg:city":"Waterford",
    "sg:classifiers":[
        {
            "category":"Restaurant",
            "type":"Food & Drink"
        }
    ],
    "sg:phone":"+1 519 443 4426",
    "sg:postcode":"N0E 1Y0",
    "sg:province":"ON",
    "sg:tags":[
        "pizza"
    ],
    "wof:name":"Godfathers Pizza",
    "wof:placetype":"venue"
},
  "geometry": {"coordinates":[-80.2931594849,42.9391937256],"type":"Point"}
}