{
  "type": "Feature",
  "properties": {
    "addr:full":"29 Main St N Markham ON L3P 1X3",
    "addr:housenumber":"29",
    "addr:postcode":"l3p 1x3",
    "addr:street":"Main St N",
    "iso:country":"CA",
    "sg:address":"29 Main St N",
    "sg:city":"Markham",
    "sg:classifiers":[
        {
            "category":"Shopping",
            "subcategory":"Bicycles & Sporting Goods",
            "type":"Retail Goods"
        }
    ],
    "sg:phone":"+1 905 294 8955",
    "sg:postcode":"L3P 1X3",
    "sg:province":"ON",
    "wof:name":"Cyclepath",
    "wof:placetype":"venue"
},
  "geometry": {"coordinates":[-79.259933,43.874905],"type":"Point"}
}