{
  "type": "Feature",
  "properties": {
    "iso:country":"CA",
    "sg:city":"Vancouver",
    "sg:classifiers":[
        {
            "category":"Health Services",
            "subcategory":"Doctor",
            "type":"Services"
        }
    ],
    "sg:phone":"+1 604 681 6699",
    "sg:postcode":"V6C 1N5",
    "sg:province":"BC",
    "sg:tags":[
        "dentist"
    ],
    "wof:name":"Jenkinson, Jan DDS",
    "wof:placetype":"venue"
},
  "geometry": {"coordinates":[-123.117881775,49.2848320007],"type":"Point"}
}