{
  "type": "Feature",
  "properties": {
    "addr:full":"1034 Toy Ave Pickering ON L1W 3P1",
    "addr:housenumber":"1034",
    "addr:postcode":"l1w 3p1",
    "addr:street":"Toy Ave",
    "iso:country":"CA",
    "sg:address":"1034 Toy Ave",
    "sg:city":"Pickering",
    "sg:classifiers":[
        {
            "category":"Wholesale",
            "subcategory":"Machinery & Supplies",
            "type":"Manufacturing & Wholesale Goods"
        }
    ],
    "sg:phone":"+1 905 619 9785",
    "sg:postcode":"L1W 3P1",
    "sg:province":"ON",
    "sg:tags":[
        "polishing",
        "buffing"
    ],
    "wof:name":"Superfinish Systems Ltd",
    "wof:placetype":"venue"
},
  "geometry": {"coordinates":[-79.0651550293,43.8354110718],"type":"Point"}
}