{
  "type": "Feature",
  "properties": {
    "addr:full":"210 Madawaska Blvd Arnprior ON K7S 1S8",
    "addr:housenumber":"210",
    "addr:postcode":"k7s 1s8",
    "addr:street":"Madawaska Blvd",
    "iso:country":"CA",
    "sg:address":"210 Madawaska Blvd",
    "sg:city":"Arnprior",
    "sg:classifiers":[
        {
            "category":"Home & Garden",
            "subcategory":"Building Materials",
            "type":"Retail Goods"
        }
    ],
    "sg:phone":"+1 613 623 2909",
    "sg:postcode":"K7S 1S8",
    "sg:province":"ON",
    "sg:tags":[
        "windows"
    ],
    "wof:name":"Scheel Window Ltd",
    "wof:placetype":"venue"
},
  "geometry": {"coordinates":[-76.3418121338,45.4322738647],"type":"Point"}
}