{
  "type": "Feature",
  "properties": {
    "addr:full":"52 Mohns Ave Petawawa ON K8H 2G9",
    "addr:housenumber":"52",
    "addr:postcode":"k8h 2g9",
    "addr:street":"Mohns Ave",
    "iso:country":"CA",
    "sg:address":"52 Mohns Ave",
    "sg:city":"Petawawa",
    "sg:classifiers":[
        {
            "category":"Building & Trades",
            "subcategory":"Construction",
            "type":"Services"
        }
    ],
    "sg:phone":"+1 613 687 4152",
    "sg:postcode":"K8H 2G9",
    "sg:province":"ON",
    "sg:tags":[
        "home",
        "improvement"
    ],
    "wof:name":"George P Ramsey Ltd",
    "wof:placetype":"venue"
},
  "geometry": {"coordinates":[-77.274918,45.898838],"type":"Point"}
}