{
  "type": "Feature",
  "properties": {
    "addr:full":"Victoria BC V8T 4G8",
    "addr:postcode":"v8t 4g8",
    "iso:country":"CA",
    "sg:city":"Victoria",
    "sg:classifiers":[
        {
            "category":"Real Estate",
            "subcategory":"Real Estate Operator",
            "type":"Services"
        }
    ],
    "sg:phone":"+1 250 383 6909",
    "sg:postcode":"V8T 4G8",
    "sg:province":"BC",
    "sg:tags":[
        "apartment"
    ],
    "wof:name":"April Manor",
    "wof:placetype":"venue"
},
  "geometry": {"coordinates":[-123.359909,48.43634],"type":"Point"}
}