{
  "type": "Feature",
  "properties": {
    "addr:full":"82 Miller St Toronto ON M6N 2Z9",
    "addr:housenumber":"82",
    "addr:postcode":"m6n 2z9",
    "addr:street":"Miller St",
    "iso:country":"CA",
    "sg:address":"82 Miller St",
    "sg:city":"Toronto",
    "sg:classifiers":[
        {
            "category":"Retail",
            "subcategory":"Auto Repair",
            "type":"Services"
        }
    ],
    "sg:phone":"+1 416 651 7598",
    "sg:postcode":"M6N 2Z9",
    "sg:province":"ON",
    "sg:tags":[
        "body",
        "automobile",
        "painting"
    ],
    "wof:name":"Arfil Auto Collision",
    "wof:placetype":"venue"
},
  "geometry": {"coordinates":[-79.4602966309,43.6690673828],"type":"Point"}
}