{
  "type": "Feature",
  "properties": {
    "addr:full":"24 Kensington Ave Toronto ON M5T 2J9",
    "addr:housenumber":"24",
    "addr:postcode":"m5t 2j9",
    "addr:street":"Kensington Ave",
    "iso:country":"CA",
    "sg:address":"24 Kensington Ave",
    "sg:city":"Toronto",
    "sg:classifiers":[
        {
            "category":"Shopping",
            "subcategory":"Used Merchandise",
            "type":"Retail Goods"
        }
    ],
    "sg:phone":"+1 416 593 9860",
    "sg:postcode":"M5T 2J9",
    "sg:province":"ON",
    "sg:tags":[
        "second",
        "store",
        "hand"
    ],
    "wof:name":"Astro",
    "wof:placetype":"venue"
},
  "geometry": {"coordinates":[-79.40026899999999,43.653454],"type":"Point"}
}