{
  "type": "Feature",
  "properties": {
    "iso:country":"CA",
    "sg:address":"PO Box 580",
    "sg:city":"Air Ronge",
    "sg:classifiers":[
        {
            "category":"Recreation",
            "type":"Entertainment"
        }
    ],
    "sg:phone":"+1 306 425 7337",
    "sg:postcode":"S0J 3G0",
    "sg:province":"SK",
    "sg:tags":[
        "party",
        "fishing"
    ],
    "wof:name":"Collin's Camp & Outfitting Inc",
    "wof:placetype":"venue"
},
  "geometry": {"coordinates":[-105.318794251,55.0824584961],"type":"Point"}
}