{
  "type": "Feature",
  "properties": {
    "iso:country":"CA",
    "sg:city":"Wikwemikong",
    "sg:classifiers":[
        {
            "category":"Professional",
            "subcategory":"Accounting & Tax Preparation",
            "type":"Services"
        }
    ],
    "sg:phone":"+1 705 859 2117",
    "sg:postcode":"P0P 2J0",
    "sg:province":"ON",
    "sg:tags":[
        "bookkeeping",
        "return",
        "filing",
        "general"
    ],
    "wof:name":"Maiangowi Bookkeeping Svc",
    "wof:placetype":"venue"
},
  "geometry": {"coordinates":[-81.7207183838,45.8031806946],"type":"Point"}
}