{
  "type": "Feature",
  "properties": {
    "iso:country":"CA",
    "sg:city":"Swift Current",
    "sg:classifiers":[
        {
            "category":"Restaurant",
            "type":"Food & Drink"
        }
    ],
    "sg:phone":"+1 306 773 9085",
    "sg:postcode":"S9H 4Z2",
    "sg:province":"SK",
    "wof:name":"Mom's Korner",
    "wof:placetype":"venue"
},
  "geometry": {"coordinates":[-107.796081543,50.3006286621],"type":"Point"}
}