{
  "type": "Feature",
  "properties": {
    "addr:full":"Hwy 16 W Yorkton SK S3N 2X1",
    "addr:postcode":"s3n 2x1",
    "addr:street":"Hwy 16 W",
    "iso:country":"CA",
    "sg:address":"Hwy 16 W",
    "sg:city":"Yorkton",
    "sg:classifiers":[
        {
            "category":"Retail",
            "subcategory":"Auto Repair",
            "type":"Services"
        }
    ],
    "sg:phone":"+1 306 786 6065",
    "sg:postcode":"S3N 2X1",
    "sg:province":"SK",
    "sg:tags":[
        "truck"
    ],
    "wof:name":"Truck Saver",
    "wof:placetype":"venue"
},
  "geometry": {"coordinates":[-102.447472,51.214134],"type":"Point"}
}