{
  "type": "Feature",
  "properties": {
    "addr:full":"218 2nd Ave W Frontier SK S0N 0W0",
    "addr:housenumber":"218",
    "addr:postcode":"s0n 0w0",
    "addr:street":"2Nd Ave W Frontier",
    "iso:country":"CA",
    "sg:address":"218 2nd Ave W",
    "sg:city":"Frontier",
    "sg:classifiers":[
        {
            "category":"Personal",
            "subcategory":"Beauty Salon",
            "type":"Services"
        }
    ],
    "sg:phone":"+1 306 296 2258",
    "sg:postcode":"S0N 0W0",
    "sg:province":"SK",
    "wof:name":"Marilyn's Beauty Salon",
    "wof:placetype":"venue"
},
  "geometry": {"coordinates":[-108.561851502,49.2041664124],"type":"Point"}
}