{
  "type": "Feature",
  "properties": {
    "addr:full":"694 Denison St Markham ON L3R 1C1",
    "addr:housenumber":"694",
    "addr:postcode":"l3r 1c1",
    "addr:street":"Denison St",
    "iso:country":"CA",
    "sg:address":"694 Denison St",
    "sg:city":"Markham",
    "sg:classifiers":[
        {
            "category":"Wholesale",
            "subcategory":"Groceries",
            "type":"Manufacturing & Wholesale Goods"
        }
    ],
    "sg:phone":"+1 905 470 7261",
    "sg:postcode":"L3R 1C1",
    "sg:province":"ON",
    "sg:tags":[
        "food",
        "grocer",
        "product"
    ],
    "wof:name":"Ermion Wholesale Food",
    "wof:placetype":"venue"
},
  "geometry": {"coordinates":[-79.33869934080001,43.8247718811],"type":"Point"}
}