{
  "type": "Feature",
  "properties": {
    "addr:full":"7825 Rue Saint-Denis Montreal QC H2R 2E9",
    "addr:housenumber":"7825",
    "addr:postcode":"h2r 2e9",
    "addr:street":"Rue Saint-Denis",
    "iso:country":"CA",
    "sg:address":"7825 Rue Saint-Denis",
    "sg:city":"Montreal",
    "sg:classifiers":[
        {
            "category":"Health Services",
            "subcategory":"Clinic",
            "type":"Services"
        }
    ],
    "sg:phone":"+1 514 948 5463",
    "sg:postcode":"H2R 2E9",
    "sg:province":"QC",
    "sg:tags":[
        "holistic",
        "practitioner"
    ],
    "wof:name":"Institut DE Kinesiologie Spec",
    "wof:placetype":"venue"
},
  "geometry": {"coordinates":[-73.6247787476,45.541469574],"type":"Point"}
}