{
  "type": "Feature",
  "properties": {
    "addr:full":"374 Main St S Russell MB R0J 1W0",
    "addr:housenumber":"374",
    "addr:postcode":"r0j 1w0",
    "addr:street":"Main St S",
    "iso:country":"CA",
    "sg:address":"374 Main St S",
    "sg:city":"Russell",
    "sg:classifiers":[
        {
            "category":"Utilities",
            "subcategory":"Mobile Phone",
            "type":"Services"
        }
    ],
    "sg:phone":"+1 204 773 3038",
    "sg:postcode":"R0J 1W0",
    "sg:province":"MB",
    "sg:tags":[
        "telephone",
        "cellular",
        "internet"
    ],
    "wof:name":"Ronald Mobile Communications",
    "wof:placetype":"venue"
},
  "geometry": {"coordinates":[-101.287872315,50.7778701782],"type":"Point"}
}