{
  "type": "Feature",
  "properties": {
    "addr:full":"Williams Lake BC V2G 3W1",
    "addr:postcode":"bc v2g 3w1",
    "iso:country":"CA",
    "sg:city":"Williams Lake",
    "sg:classifiers":[
        {
            "category":"Restaurant",
            "type":"Food & Drink"
        }
    ],
    "sg:phone":"+1 250 392 6068",
    "sg:postcode":"V2G 3W1",
    "sg:province":"BC",
    "wof:name":"A & W Family Restaurant",
    "wof:placetype":"venue"
},
  "geometry": {"coordinates":[-122.131927,52.12854],"type":"Point"}
}