{
  "type": "Feature",
  "properties": {
    "iso:country":"CA",
    "sg:city":"Vancouver",
    "sg:classifiers":[
        {
            "category":"Personal",
            "subcategory":"Beauty Salon",
            "type":"Services"
        }
    ],
    "sg:phone":"+1 604 683 9283",
    "sg:postcode":"V6Z 2N1",
    "sg:province":"BC",
    "wof:name":"Wave Hair Design",
    "wof:placetype":"venue"
},
  "geometry": {"coordinates":[-123.131798,49.274689],"type":"Point"}
}