{
  "type": "Feature",
  "properties": {
    "addr:full":"23 Church St Picton ON K0K 2T0",
    "addr:housenumber":"23",
    "addr:postcode":"k0k 2t0",
    "addr:street":"Church St",
    "iso:country":"CA",
    "sg:address":"23 Church St",
    "sg:city":"Picton",
    "sg:classifiers":[
        {
            "category":"Museum",
            "type":"Entertainment"
        }
    ],
    "sg:phone":"+1 613 476 3833",
    "sg:postcode":"K0K 2T0",
    "sg:province":"ON",
    "wof:name":"Mac Aulay Heritage Park",
    "wof:placetype":"venue"
},
  "geometry": {"coordinates":[-77.132301,44.005825],"type":"Point"}
}