{
  "type": "Feature",
  "properties": {
    "addr:full":"262 Rue Sainte-Catherine O Montreal QC H2X 2A1",
    "addr:housenumber":"262",
    "addr:postcode":"h2x 2a1",
    "addr:street":"Rue Sainte-Catherine O",
    "iso:country":"CA",
    "sg:address":"262 Rue Sainte-Catherine O",
    "sg:city":"Montreal",
    "sg:classifiers":[
        {
            "category":"Restaurant",
            "type":"Food & Drink"
        }
    ],
    "sg:phone":"+1 514 878 3923",
    "sg:postcode":"H2X 2A1",
    "sg:province":"QC",
    "sg:tags":[
        "shop",
        "coffee"
    ],
    "wof:name":"Second Cup",
    "wof:placetype":"venue"
},
  "geometry": {"coordinates":[-73.5614395142,45.5123062134],"type":"Point"}
}