{
  "type": "Feature",
  "properties": {
    "iso:country":"CA",
    "sg:city":"Kanata",
    "sg:classifiers":[
        {
            "category":"Restaurant",
            "type":"Food & Drink"
        }
    ],
    "sg:phone":"+1 613 271 0921",
    "sg:postcode":"K2T 1E6",
    "sg:province":"ON",
    "wof:name":"Graffiti's Italian Eatery",
    "wof:placetype":"venue"
},
  "geometry": {"coordinates":[-75.90538,45.311661],"type":"Point"}
}