{
  "type": "Feature",
  "properties": {
    "addr:full":"21628 Mull Rd Kent Bridge ON N0P 1V0",
    "addr:housenumber":"21628",
    "addr:postcode":"n0p 1v0",
    "addr:street":"Mull Rd",
    "iso:country":"CA",
    "sg:address":"21628 Mull Rd",
    "sg:city":"Kent Bridge",
    "sg:classifiers":[
        {
            "category":"Building & Trades",
            "subcategory":"Construction",
            "type":"Services"
        }
    ],
    "sg:phone":"+1 519 676 4965",
    "sg:postcode":"N0P 1V0",
    "sg:province":"ON",
    "sg:tags":[
        "concrete",
        "contractor"
    ],
    "wof:name":"Vantel Construction",
    "wof:placetype":"venue"
},
  "geometry": {"coordinates":[-82.07303619379999,42.5150604248],"type":"Point"}
}