{
  "type": "Feature",
  "properties": {
    "addr:full":"2787 Sheffield Rd Ottawa ON K1B 3V8",
    "addr:housenumber":"2787",
    "addr:postcode":"k1b 3v8",
    "addr:street":"Sheffield Rd",
    "iso:country":"CA",
    "sg:address":"2787 Sheffield Rd",
    "sg:city":"Ottawa",
    "sg:classifiers":[
        {
            "category":"Home & Garden",
            "subcategory":"Building Materials",
            "type":"Retail Goods"
        }
    ],
    "sg:phone":"+1 613 748 6650",
    "sg:postcode":"K1B 3V8",
    "sg:province":"ON",
    "sg:tags":[
        "mixed",
        "concrete"
    ],
    "wof:name":"Essroc Italcementi Group",
    "wof:placetype":"venue"
},
  "geometry": {"coordinates":[-75.60264599999999,45.39875],"type":"Point"}
}