{
  "type": "Feature",
  "properties": {
    "iso:country":"CA",
    "sg:address":"2021 West Mall # 101D",
    "sg:city":"Vancouver",
    "sg:classifiers":[
        {
            "category":"Education",
            "subcategory":"College",
            "type":"Public Place"
        }
    ],
    "sg:phone":"+1 604 822 0800",
    "sg:postcode":"V6T 1Z2",
    "sg:province":"BC",
    "sg:tags":[
        "academic",
        "school"
    ],
    "wof:name":"University of British Columbia",
    "wof:placetype":"venue"
},
  "geometry": {"coordinates":[-123.25614899999999,49.265041],"type":"Point"}
}