{
  "type": "Feature",
  "properties": {
    "addr:full":"1806 Rue Saint-Christophe Montreal QC H2L 3W8",
    "addr:housenumber":"1806",
    "addr:postcode":"h2l 3w8",
    "addr:street":"Rue Saint-Christophe",
    "iso:country":"CA",
    "sg:address":"1806 Rue Saint-Christophe",
    "sg:city":"Montreal",
    "sg:classifiers":[
        {
            "category":"Travel",
            "subcategory":"Hotels & Motels",
            "type":"Entertainment"
        }
    ],
    "sg:phone":"+1 514 523 4494",
    "sg:postcode":"H2L 3W8",
    "sg:province":"QC",
    "sg:tags":[
        "breakfast",
        "accommodation",
        "bed"
    ],
    "wof:name":"Au Git'Ann",
    "wof:placetype":"venue"
},
  "geometry": {"coordinates":[-73.5630874634,45.5178413391],"type":"Point"}
}