{
  "type": "Feature",
  "properties": {
    "addr:full":"3601 Joseph Howe Dr Halifax NS B3L 4H8",
    "addr:housenumber":"3601",
    "addr:postcode":"b3l 4h8",
    "addr:street":"Joseph Howe Dr",
    "iso:country":"CA",
    "sg:address":"3601 Joseph Howe Dr",
    "sg:city":"Halifax",
    "sg:classifiers":[
        {
            "category":"Shopping",
            "subcategory":"Clothing, Apparel, & Fashions",
            "type":"Retail Goods"
        }
    ],
    "sg:phone":"+1 902 455 0151",
    "sg:postcode":"B3L 4H8",
    "sg:province":"NS",
    "sg:tags":[
        "tailor"
    ],
    "wof:name":"Merry Bee Tailering Ltd",
    "wof:placetype":"venue"
},
  "geometry": {"coordinates":[-63.6291389465,44.6573524475],"type":"Point"}
}