{
  "type": "Feature",
  "properties": {
    "addr:full":"5216 54 St Wetaskiwin AB T9A 2X1",
    "addr:housenumber":"5216",
    "addr:postcode":"t9a 2x1",
    "addr:street":"54 St",
    "iso:country":"CA",
    "sg:address":"5216 54 St",
    "sg:city":"Wetaskiwin",
    "sg:classifiers":[
        {
            "category":"Organizations",
            "subcategory":"Community Association",
            "type":"Services"
        }
    ],
    "sg:phone":"+1 780 352 4646",
    "sg:postcode":"T9A 2X1",
    "sg:province":"AB",
    "sg:tags":[
        "club"
    ],
    "wof:name":"Wetaskiwin Seniors Drop-In Ctr",
    "wof:placetype":"venue"
},
  "geometry": {"coordinates":[-113.383041382,52.9725494385],"type":"Point"}
}