{
  "type": "Feature",
  "properties": {
    "addr:full":"4269 Rue Sainte-Catherine O Westmount QC H3Z 1P7",
    "addr:housenumber":"4269",
    "addr:postcode":"h3z 1p7",
    "addr:street":"Rue Sainte-Catherine O",
    "iso:country":"CA",
    "sg:address":"4269 Rue Sainte-Catherine O",
    "sg:city":"Westmount",
    "sg:classifiers":[
        {
            "category":"Banks & Credit Unions",
            "subcategory":"Investment Brokerage",
            "type":"Services"
        }
    ],
    "sg:phone":"+1 514 989 5508",
    "sg:postcode":"H3Z 1P7",
    "sg:province":"QC",
    "sg:tags":[
        "consultant",
        "financing"
    ],
    "wof:name":"Corporation Financiere Cafa",
    "wof:placetype":"venue"
},
  "geometry": {"coordinates":[-73.5889663696,45.4850997925],"type":"Point"}
}