{
  "type": "Feature",
  "properties": {
    "addr:full":"Berthierville QC J0K 1A0",
    "addr:postcode":"j0k 1a0",
    "iso:country":"CA",
    "sg:city":"Berthierville",
    "sg:phone":"+1 450 836 7285",
    "sg:postcode":"J0K 1A0",
    "sg:province":"QC",
    "sg:tags":[
        "product",
        "wire",
        "shelving"
    ],
    "wof:name":"Fils Metallique Berthier",
    "wof:placetype":"venue"
},
  "geometry": {"coordinates":[-73.1826095581,46.0829467773],"type":"Point"}
}