{
  "type": "Feature",
  "properties": {
    "addr:full":"SW 1 8 29 Sinclair MB R0M 2A0",
    "addr:housenumber":"8 29",
    "addr:postcode":"r0m 2a0",
    "addr:street":"Sw 1;Sinclair",
    "iso:country":"CA",
    "sg:address":"SW 1 8 29",
    "sg:city":"Sinclair",
    "sg:classifiers":[
        {
            "category":"Organizations",
            "subcategory":"Religious Organization",
            "type":"Services"
        }
    ],
    "sg:phone":"+1 204 662 4516",
    "sg:postcode":"R0M 2A0",
    "sg:province":"MB",
    "sg:tags":[
        "church"
    ],
    "wof:name":"Church of God in Christ Menn",
    "wof:placetype":"venue"
},
  "geometry": {"coordinates":[-101.292816,49.569382],"type":"Point"}
}