{
  "type": "Feature",
  "properties": {
    "addr:full":"8 Cromer Ave Grand Falls-Windsor NL A2A 1X2",
    "addr:housenumber":"8",
    "addr:postcode":"a2a 1x2",
    "addr:street":"Cromer Ave",
    "iso:country":"CA",
    "sg:address":"8 Cromer Ave",
    "sg:city":"Grand Falls-Windsor",
    "sg:classifiers":[
        {
            "category":"Autos & Motor Vehicles",
            "subcategory":"Auto Supplies",
            "type":"Retail Goods"
        }
    ],
    "sg:phone":"+1 709 489 2148",
    "sg:postcode":"A2A 1X2",
    "sg:province":"NL",
    "sg:tags":[
        "automobile",
        "parts"
    ],
    "wof:name":"Canadian Tire",
    "wof:placetype":"venue"
},
  "geometry": {"coordinates":[-55.6535,48.953869],"type":"Point"}
}