{
  "type": "Feature",
  "properties": {
    "addr:full":"305 Boul Iberville Repentigny QC J6A 2A6",
    "addr:housenumber":"305",
    "addr:postcode":"j6a 2a6",
    "addr:street":"Boul Iberville",
    "iso:country":"CA",
    "sg:address":"305 Boul Iberville",
    "sg:city":"Repentigny",
    "sg:classifiers":[
        {
            "category":"Food & Beverages",
            "subcategory":"Groceries & Convenience Stores",
            "type":"Retail Goods"
        }
    ],
    "sg:phone":"+1 450 581 2630",
    "sg:postcode":"J6A 2A6",
    "sg:province":"QC",
    "sg:tags":[
        "grocer"
    ],
    "wof:name":"Super Marche Iberville",
    "wof:placetype":"venue"
},
  "geometry": {"coordinates":[-73.460121,45.731655],"type":"Point"}
}