{
  "type": "Feature",
  "properties": {
    "iso:country":"CA",
    "sg:address":"2744 Rte Mcwatters",
    "sg:city":"Mcwatters",
    "sg:classifiers":[
        {
            "category":"Health Services",
            "subcategory":"Nursing And Care Facility",
            "type":"Services"
        }
    ],
    "sg:phone":"+1 819 762 3366",
    "sg:postcode":"J9X 5B7",
    "sg:province":"QC",
    "sg:tags":[
        "home",
        "rest"
    ],
    "wof:name":"Famille D'Acceuil Beaudry",
    "wof:placetype":"venue"
},
  "geometry": {"coordinates":[-78.9326171875,48.2142906189],"type":"Point"}
}