{
  "type": "Feature",
  "properties": {
    "addr:full":"Calgary AB T2P 2X6",
    "addr:postcode":"t2p 2x6",
    "iso:country":"CA",
    "sg:city":"Calgary",
    "sg:classifiers":[
        {
            "category":"Restaurant",
            "type":"Food & Drink"
        }
    ],
    "sg:phone":"+1 403 265 2206",
    "sg:postcode":"T2P 2X6",
    "sg:province":"AB",
    "wof:name":"Tower Cafe",
    "wof:placetype":"venue"
},
  "geometry": {"coordinates":[-114.07665252699999,51.0486335754],"type":"Point"}
}