{
  "type": "Feature",
  "properties": {
    "addr:full":"Victoria BC V9A 7C3",
    "addr:postcode":"v9a 7c3",
    "iso:country":"CA",
    "sg:city":"Victoria",
    "sg:classifiers":[
        {
            "category":"Real Estate",
            "subcategory":"Real Estate Operator",
            "type":"Services"
        }
    ],
    "sg:phone":"+1 250 385 2250",
    "sg:postcode":"V9A 7C3",
    "sg:province":"BC",
    "sg:tags":[
        "apartment"
    ],
    "wof:name":"Pacific Village II Ltd",
    "wof:placetype":"venue"
},
  "geometry": {"coordinates":[-123.393936,48.439781],"type":"Point"}
}