{
  "type": "Feature",
  "properties": {
    "addr:full":"25 Otter St Winnipeg MB R3T 0M7",
    "addr:housenumber":"25",
    "addr:postcode":"r3t 0m7",
    "addr:street":"Otter St",
    "iso:country":"CA",
    "sg:address":"25 Otter St",
    "sg:city":"Winnipeg",
    "sg:classifiers":[
        {
            "category":"Professional",
            "subcategory":"Advertising",
            "type":"Services"
        }
    ],
    "sg:phone":"+1 204 261 3537",
    "sg:postcode":"R3T 0M7",
    "sg:province":"MB",
    "sg:tags":[
        "counselor"
    ],
    "wof:name":"Killarney Printing Inc",
    "wof:placetype":"venue"
},
  "geometry": {"coordinates":[-97.1770706177,49.8410644531],"type":"Point"}
}