{
  "type": "Feature",
  "properties": {
    "addr:full":"Burnaby BC V5C 5T5",
    "addr:postcode":"v5c 5t5",
    "iso:country":"CA",
    "sg:city":"Burnaby",
    "sg:classifiers":[
        {
            "category":"Building & Trades",
            "subcategory":"Plumbing",
            "type":"Services"
        }
    ],
    "sg:phone":"+1 604 299 4641",
    "sg:postcode":"V5C 5T5",
    "sg:province":"BC",
    "sg:tags":[
        "sheet",
        "work",
        "metal",
        "contractor"
    ],
    "wof:name":"British Columbia Sheet Metal",
    "wof:placetype":"venue"
},
  "geometry": {"coordinates":[-122.99865699999999,49.266094],"type":"Point"}
}