{
  "type": "Feature",
  "properties": {
    "addr:full":"649 Upper James St Hamilton ON L9C 2Y9",
    "addr:housenumber":"649",
    "addr:postcode":"l9c 2y9",
    "addr:street":"Upper James St",
    "iso:country":"CA",
    "sg:address":"649 Upper James St",
    "sg:city":"Hamilton",
    "sg:classifiers":[
        {
            "category":"Food & Beverages",
            "subcategory":"Groceries & Convenience Stores",
            "type":"Retail Goods"
        }
    ],
    "sg:phone":"+1 905 389 9845",
    "sg:postcode":"L9C 2Y9",
    "sg:province":"ON",
    "wof:name":"Any Time Convenience",
    "wof:placetype":"venue"
},
  "geometry": {"coordinates":[-79.87744903559999,43.237991333],"type":"Point"}
}