{
  "type": "Feature",
  "properties": {
    "addr:full":"1360 Rue Notre-Dame O Victoriaville QC G6P 7L7",
    "addr:housenumber":"1360",
    "addr:postcode":"g6p 7l7",
    "addr:street":"Rue Notre-Dame O",
    "iso:country":"CA",
    "sg:address":"1360 Rue Notre-Dame O",
    "sg:city":"Victoriaville",
    "sg:classifiers":[
        {
            "category":"Home & Garden",
            "subcategory":"Building Materials",
            "type":"Retail Goods"
        }
    ],
    "sg:phone":"+1 819 758 4748",
    "sg:postcode":"G6P 7L7",
    "sg:province":"QC",
    "sg:tags":[
        "door"
    ],
    "wof:name":"Clau-RI-Van Inc",
    "wof:placetype":"venue"
},
  "geometry": {"coordinates":[-72.008049,46.049461],"type":"Point"}
}