{
  "type": "Feature",
  "properties": {
    "iso:country":"CA",
    "sg:city":"North Vancouver",
    "sg:classifiers":[
        {
            "category":"Building & Trades",
            "subcategory":"Construction",
            "type":"Services"
        }
    ],
    "sg:phone":"+1 604 980 7507",
    "sg:postcode":"V7L 1T9",
    "sg:province":"BC",
    "sg:tags":[
        "paving",
        "contractor"
    ],
    "wof:name":"Terry's Driveway Sealing & Rpr",
    "wof:placetype":"venue"
},
  "geometry": {"coordinates":[-123.072395325,49.3171577454],"type":"Point"}
}