{
  "type": "Feature",
  "properties": {
    "addr:full":"129 Humbercrest Blvd York ON M6S 4L4",
    "addr:housenumber":"129",
    "addr:postcode":"m6s 4l4",
    "addr:street":"Humbercrest Blvd",
    "iso:country":"CA",
    "sg:address":"129 Humbercrest Blvd",
    "sg:city":"York",
    "sg:classifiers":[
        {
            "category":"Banks & Credit Unions",
            "subcategory":"Investment Brokerage",
            "type":"Services"
        }
    ],
    "sg:phone":"+1 416 604 4204",
    "sg:postcode":"M6S 4L4",
    "sg:province":"ON",
    "sg:tags":[
        "advisory",
        "financial"
    ],
    "wof:name":"Hymas Investment Mgmt Inc",
    "wof:placetype":"venue"
},
  "geometry": {"coordinates":[-79.4928359985,43.6605644226],"type":"Point"}
}