{
  "type": "Feature",
  "properties": {
    "iso:country":"CA",
    "sg:address":"78 Martinet Pl",
    "sg:city":"London",
    "sg:classifiers":[
        {
            "category":"Retail",
            "subcategory":"Portrait Studio",
            "type":"Services"
        }
    ],
    "sg:phone":"+1 519 455 3214",
    "sg:postcode":"N5V 4B7",
    "sg:province":"ON",
    "sg:tags":[
        "photographer"
    ],
    "wof:name":"Fieldhouse Photography",
    "wof:placetype":"venue"
},
  "geometry": {"coordinates":[-81.155411,42.998512],"type":"Point"}
}