{
  "type": "Feature",
  "properties": {
    "addr:full":"163 Boul Saint-Sacrement Saint-Gabriel-DE-Valcartier QC G0A 4S0",
    "addr:housenumber":"163",
    "addr:postcode":"g0a 4s0",
    "addr:street":"Boul Saint-Sacrement",
    "iso:country":"CA",
    "sg:address":"163 Boul Saint-Sacrement",
    "sg:city":"Saint-Gabriel-DE-Valcartier",
    "sg:classifiers":[
        {
            "category":"Building & Trades",
            "subcategory":"Construction",
            "type":"Services"
        }
    ],
    "sg:phone":"+1 418 844 2427",
    "sg:postcode":"G0A 4S0",
    "sg:province":"QC",
    "sg:tags":[
        "contractor",
        "general"
    ],
    "wof:name":"Construction John Goodfellow",
    "wof:placetype":"venue"
},
  "geometry": {"coordinates":[-71.497574,46.970921],"type":"Point"}
}