{
  "type": "Feature",
  "properties": {
    "addr:full":"40 Courtwright St Fort Erie ON L2A 2R7",
    "addr:housenumber":"40",
    "addr:postcode":"l2a 2r7",
    "addr:street":"Courtwright St",
    "iso:country":"CA",
    "sg:address":"40 Courtwright St",
    "sg:city":"Fort Erie",
    "sg:classifiers":[
        {
            "category":"Shopping",
            "subcategory":"Used Merchandise",
            "type":"Retail Goods"
        }
    ],
    "sg:phone":"+1 905 871 0132",
    "sg:postcode":"L2A 2R7",
    "sg:province":"ON",
    "sg:tags":[
        "antique"
    ],
    "wof:name":"Bridgeburg Antique Village",
    "wof:placetype":"venue"
},
  "geometry": {"coordinates":[-78.916183,42.928989],"type":"Point"}
}