{
  "type": "Feature",
  "properties": {
    "addr:full":"4811 49 St Rocky Mountain House AB T4T 1C2",
    "addr:housenumber":"4811",
    "addr:postcode":"t4t 1c2",
    "addr:street":"49 St",
    "iso:country":"CA",
    "sg:address":"4811 49 St",
    "sg:city":"Rocky Mountain House",
    "sg:classifiers":[
        {
            "category":"Personal",
            "type":"Services"
        }
    ],
    "sg:phone":"+1 403 845 4060",
    "sg:postcode":"T4T 1C2",
    "sg:province":"AB",
    "sg:tags":[
        "therapist",
        "massage"
    ],
    "wof:name":"Mind Body Sole Therapy Clinic",
    "wof:placetype":"venue"
},
  "geometry": {"coordinates":[-114.917503357,52.3715667725],"type":"Point"}
}