{
  "type": "Feature",
  "properties": {
    "addr:full":"234 Shamrock St Sarnia ON N7T 2S6",
    "addr:housenumber":"234",
    "addr:postcode":"n7t 2s6",
    "addr:street":"Shamrock St",
    "iso:country":"CA",
    "sg:address":"234 Shamrock St",
    "sg:city":"Sarnia",
    "sg:classifiers":[
        {
            "category":"Manufacturing",
            "subcategory":"Metals",
            "type":"Manufacturing & Wholesale Goods"
        }
    ],
    "sg:phone":"+1 519 337 3300",
    "sg:postcode":"N7T 2S6",
    "sg:province":"ON",
    "sg:tags":[
        "coating"
    ],
    "wof:name":"Ics Technologies",
    "wof:placetype":"venue"
},
  "geometry": {"coordinates":[-82.4103088379,42.9561805725],"type":"Point"}
}