{
  "type": "Feature",
  "properties": {
    "addr:full":"109 Boul Saint-Francois S Lac-Des-Ecorces QC J0W 1H0",
    "addr:housenumber":"109",
    "addr:postcode":"j0w 1h0",
    "addr:street":"Boul Saint-Francois S Lac-Des-Ecorces",
    "iso:country":"CA",
    "sg:address":"109 Boul Saint-Francois S",
    "sg:city":"Lac-Des-Ecorces",
    "sg:classifiers":[
        {
            "category":"Government",
            "subcategory":"Office",
            "type":"Public Place"
        }
    ],
    "sg:phone":"+1 819 585 2189",
    "sg:postcode":"J0W 1H0",
    "sg:province":"QC",
    "sg:tags":[
        "village"
    ],
    "wof:name":"Clsc Lac-Des-Ecorces",
    "wof:placetype":"venue"
},
  "geometry": {"coordinates":[-75.364929,46.557083],"type":"Point"}
}