{
  "type": "Feature",
  "properties": {
    "iso:country":"CA",
    "sg:address":"592 1E Av",
    "sg:city":"Stoneham",
    "sg:classifiers":[
        {
            "category":"Food & Beverages",
            "subcategory":"Groceries & Convenience Stores",
            "type":"Retail Goods"
        }
    ],
    "sg:phone":"+1 418 848 3727",
    "sg:postcode":"G0A 4P0",
    "sg:province":"QC",
    "wof:name":"Depanneur Des Cantons Inc",
    "wof:placetype":"venue"
},
  "geometry": {"coordinates":[-71.3644561768,46.9972343445],"type":"Point"}
}