{
  "type": "Feature",
  "properties": {
    "addr:full":"RR 6 STN Main Cobourg ON K9A 4J9",
    "addr:postcode":"k9a 4j9",
    "addr:street":"Rr 6 Stn Main",
    "iso:country":"CA",
    "sg:address":"RR 6 STN Main",
    "sg:city":"Cobourg",
    "sg:classifiers":[
        {
            "category":"Professional",
            "subcategory":"Research",
            "type":"Services"
        }
    ],
    "sg:phone":"+1 905 342 2257",
    "sg:postcode":"K9A 4J9",
    "sg:province":"ON",
    "sg:tags":[
        "environmental",
        "ecological"
    ],
    "wof:name":"962121 Ontario Ltd",
    "wof:placetype":"venue"
},
  "geometry": {"coordinates":[-78.167778,43.959606],"type":"Point"}
}