{
  "type": "Feature",
  "properties": {
    "addr:full":"Coquitlam BC V3K 6Z8",
    "addr:postcode":"v3k 6z8",
    "iso:country":"CA",
    "sg:city":"Coquitlam",
    "sg:classifiers":[
        {
            "category":"Retail",
            "subcategory":"Animal Services",
            "type":"Services"
        }
    ],
    "sg:phone":"+1 604 836 6266",
    "sg:postcode":"V3K 6Z8",
    "sg:province":"BC",
    "sg:tags":[
        "pet"
    ],
    "wof:name":"Dreamdog Mobile Dog Training",
    "wof:placetype":"venue"
},
  "geometry": {"coordinates":[-122.892410278,49.2434387207],"type":"Point"}
}