{
  "type": "Feature",
  "properties": {
    "iso:country":"CA",
    "sg:address":"2630 Boul DE Portland",
    "sg:city":"Sherbrooke",
    "sg:classifiers":[
        {
            "category":"Organizations",
            "subcategory":"Religious Organization",
            "type":"Services"
        }
    ],
    "sg:phone":"+1 819 564 2862",
    "sg:postcode":"J1J 1V7",
    "sg:province":"QC",
    "sg:tags":[
        "house",
        "retreat"
    ],
    "wof:name":"Residence Portland",
    "wof:placetype":"venue"
},
  "geometry": {"coordinates":[-71.9384918213,45.4036521912],"type":"Point"}
}