{
  "type": "Feature",
  "properties": {
    "addr:full":"601 3rd St E Meadow Lake SK S9X 1G7",
    "addr:housenumber":"601",
    "addr:postcode":"s9x 1g7",
    "addr:street":"3Rd St E;Lake",
    "iso:country":"CA",
    "sg:address":"601 3rd St E",
    "sg:city":"Meadow Lake",
    "sg:classifiers":[
        {
            "category":"Food & Beverages",
            "subcategory":"Groceries & Convenience Stores",
            "type":"Retail Goods"
        }
    ],
    "sg:phone":"+1 306 236 6110",
    "sg:postcode":"S9X 1G7",
    "sg:province":"SK",
    "wof:name":"East Side Grocery",
    "wof:placetype":"venue"
},
  "geometry": {"coordinates":[-108.434708,54.110901],"type":"Point"}
}