{
  "type": "Feature",
  "properties": {
    "addr:full":"129 John St N Arnprior ON K7S 2N5",
    "addr:housenumber":"129",
    "addr:postcode":"k7s 2n5",
    "addr:street":"John St N",
    "iso:country":"CA",
    "sg:address":"129 John St N",
    "sg:city":"Arnprior",
    "sg:classifiers":[
        {
            "category":"Restaurant",
            "type":"Food & Drink"
        }
    ],
    "sg:phone":"+1 613 623 0344",
    "sg:postcode":"K7S 2N5",
    "sg:province":"ON",
    "wof:name":"Steve & Denis Restaurant",
    "wof:placetype":"venue"
},
  "geometry": {"coordinates":[-76.35377502439999,45.4339370728],"type":"Point"}
}