{
  "type": "Feature",
  "properties": {
    "addr:full":"Calgary AB T2H 2W9",
    "addr:postcode":"t2h 2w9",
    "iso:country":"CA",
    "sg:city":"Calgary",
    "sg:classifiers":[
        {
            "category":"Shopping",
            "subcategory":"Computers & Home Electronics",
            "type":"Retail Goods"
        }
    ],
    "sg:phone":"+1 403 252 9060",
    "sg:postcode":"T2H 2W9",
    "sg:province":"AB",
    "sg:tags":[
        "sound",
        "equipment",
        "video",
        "system",
        "consultant"
    ],
    "wof:name":"Pauer Electronics",
    "wof:placetype":"venue"
},
  "geometry": {"coordinates":[-114.062057,51.004681],"type":"Point"}
}