{
  "type": "Feature",
  "properties": {
    "iso:country":"CA",
    "sg:address":"965 Walker Rd",
    "sg:city":"Windsor",
    "sg:classifiers":[
        {
            "category":"Retail",
            "subcategory":"Auto Repair",
            "type":"Services"
        }
    ],
    "sg:phone":"+1 519 254 1487",
    "sg:postcode":"N8Y 2N6",
    "sg:province":"ON",
    "sg:tags":[
        "repairing",
        "automobile"
    ],
    "wof:name":"First Auto Svc",
    "wof:placetype":"venue"
},
  "geometry": {"coordinates":[-83.0059509277,42.3198204041],"type":"Point"}
}