{
  "type": "Feature",
  "properties": {
    "iso:country":"CA",
    "sg:address":"906 Camosun Cres",
    "sg:city":"Kamloops",
    "sg:classifiers":[
        {
            "category":"Building & Trades",
            "subcategory":"Construction",
            "type":"Services"
        }
    ],
    "sg:phone":"+1 250 374 1323",
    "sg:postcode":"V2C 6G2",
    "sg:province":"BC",
    "sg:tags":[
        "fire",
        "restoration",
        "general",
        "damage",
        "contractor"
    ],
    "wof:name":"N & H Contracting Ltd",
    "wof:placetype":"venue"
},
  "geometry": {"coordinates":[-120.365142822,50.664691925],"type":"Point"}
}