{
  "type": "Feature",
  "properties": {
    "addr:full":"Markham ON L3R 0B9",
    "addr:postcode":"l3r 0b9",
    "iso:country":"CA",
    "sg:city":"Markham",
    "sg:classifiers":[
        {
            "category":"Real Estate",
            "subcategory":"Real Estate Agent",
            "type":"Services"
        }
    ],
    "sg:phone":"+1 905 305 9669",
    "sg:postcode":"L3R 0B9",
    "sg:province":"ON",
    "wof:name":"Landpower Real Estate Ltd",
    "wof:placetype":"venue"
},
  "geometry": {"coordinates":[-79.35419464109999,43.8341445923],"type":"Point"}
}