{
  "type": "Feature",
  "properties": {
    "addr:full":"Mississauga ON L5B 2V2",
    "addr:postcode":"l5b 2v2",
    "iso:country":"CA",
    "sg:city":"Mississauga",
    "sg:classifiers":[
        {
            "category":"Health Services",
            "subcategory":"Doctor",
            "type":"Services"
        }
    ],
    "sg:phone":"+1 905 275 3361",
    "sg:postcode":"L5B 2V2",
    "sg:province":"ON",
    "sg:tags":[
        "dentist"
    ],
    "wof:name":"Hoang, Sophie DDS",
    "wof:placetype":"venue"
},
  "geometry": {"coordinates":[-79.61042022709999,43.5720481873],"type":"Point"}
}