{
  "type": "Feature",
  "properties": {
    "addr:full":"1215 Diane St Sudbury ON P3A 4H4",
    "addr:housenumber":"1215",
    "addr:postcode":"p3a 4h4",
    "addr:street":"Diane St",
    "iso:country":"CA",
    "sg:address":"1215 Diane St",
    "sg:city":"Sudbury",
    "sg:classifiers":[
        {
            "category":"Building & Trades",
            "subcategory":"Construction",
            "type":"Services"
        }
    ],
    "sg:phone":"+1 705 560 6671",
    "sg:postcode":"P3A 4H4",
    "sg:province":"ON",
    "sg:tags":[
        "dry wall",
        "contractor"
    ],
    "wof:name":"Beaudry Drywall & Plastering",
    "wof:placetype":"venue"
},
  "geometry": {"coordinates":[-80.92077636720001,46.5241279602],"type":"Point"}
}