{
  "type": "Feature",
  "properties": {
    "addr:full":"Oakville ON L6M 2W1",
    "addr:postcode":"l6m 2w1",
    "iso:country":"CA",
    "sg:city":"Oakville",
    "sg:classifiers":[
        {
            "category":"Professional",
            "subcategory":"Management & Consulting",
            "type":"Services"
        }
    ],
    "sg:phone":"+1 905 847 6800",
    "sg:postcode":"L6M 2W1",
    "sg:province":"ON",
    "sg:tags":[
        "consultant",
        "telecommunication"
    ],
    "wof:name":"Unis Lumin",
    "wof:placetype":"venue"
},
  "geometry": {"coordinates":[-79.71528625489999,43.4345169067],"type":"Point"}
}