{
  "type": "Feature",
  "properties": {
    "addr:full":"73 Russell St Dartmouth NS B3A 3N2",
    "addr:housenumber":"73",
    "addr:postcode":"b3a 3n2",
    "addr:street":"Russell St",
    "iso:country":"CA",
    "sg:address":"73 Russell St",
    "sg:city":"Dartmouth",
    "sg:classifiers":[
        {
            "category":"Real Estate",
            "subcategory":"Surveying",
            "type":"Services"
        }
    ],
    "sg:phone":"+1 902 469 3746",
    "sg:postcode":"B3A 3N2",
    "sg:province":"NS",
    "sg:tags":[
        "surveyor"
    ],
    "wof:name":"Mac Cullough, Allan C",
    "wof:placetype":"venue"
},
  "geometry": {"coordinates":[-63.5818023682,44.6792297363],"type":"Point"}
}