{
  "type": "Feature",
  "properties": {
    "iso:country":"CA",
    "sg:city":"Coldwater",
    "sg:classifiers":[
        {
            "category":"Building & Trades",
            "subcategory":"Construction",
            "type":"Services"
        }
    ],
    "sg:phone":"+1 705 835 2268",
    "sg:postcode":"L0K 1E0",
    "sg:province":"ON",
    "sg:tags":[
        "water",
        "well",
        "drilling"
    ],
    "wof:name":"Vinson's Well Drilling",
    "wof:placetype":"venue"
},
  "geometry": {"coordinates":[-79.64436340330001,44.7102241516],"type":"Point"}
}