{
  "type": "Feature",
  "properties": {
    "addr:full":"6922 King George Hwy Surrey BC V3W 4Z9",
    "addr:housenumber":"6922",
    "addr:postcode":"v3w 4z9",
    "addr:street":"King George Hwy",
    "iso:country":"CA",
    "sg:address":"6922 King George Hwy",
    "sg:city":"Surrey",
    "sg:classifiers":[
        {
            "category":"Freight",
            "type":"Transportation"
        }
    ],
    "sg:phone":"+1 604 594 4927",
    "sg:postcode":"V3W 4Z9",
    "sg:province":"BC",
    "sg:tags":[
        "courier"
    ],
    "wof:name":"Greyhound Lines of Canada Ltd",
    "wof:placetype":"venue"
},
  "geometry": {"coordinates":[-122.84558868400001,49.1262016296],"type":"Point"}
}