{
  "type": "Feature",
  "properties": {
    "addr:full":"107 Rue Oliver Cowansville QC J2K 1H7",
    "addr:housenumber":"107",
    "addr:postcode":"j2k 1h7",
    "addr:street":"Rue Oliver",
    "iso:country":"CA",
    "sg:address":"107 Rue Oliver",
    "sg:city":"Cowansville",
    "sg:classifiers":[
        {
            "category":"Taxi",
            "type":"Transportation"
        }
    ],
    "sg:phone":"+1 450 263 5050",
    "sg:postcode":"J2K 1H7",
    "sg:province":"QC",
    "sg:tags":[
        "taxicab"
    ],
    "wof:name":"Taxi Andre Gelineau",
    "wof:placetype":"venue"
},
  "geometry": {"coordinates":[-72.74999200000001,45.20863],"type":"Point"}
}