{
  "type": "Feature",
  "properties": {
    "addr:full":"21 Rue Dufferin Salaberry-DE-Valleyfield QC J6S 1Y1",
    "addr:housenumber":"21",
    "addr:postcode":"j6s 1y1",
    "addr:street":"Rue Dufferin",
    "iso:country":"CA",
    "sg:address":"21 Rue Dufferin",
    "sg:city":"Salaberry-DE-Valleyfield",
    "sg:classifiers":[
        {
            "category":"Organizations",
            "subcategory":"Religious Organization",
            "type":"Services"
        }
    ],
    "sg:phone":"+1 450 377 7610",
    "sg:postcode":"J6S 1Y1",
    "sg:province":"QC",
    "sg:tags":[
        "church"
    ],
    "wof:name":"Eglise Emmanuel Pentecote",
    "wof:placetype":"venue"
},
  "geometry": {"coordinates":[-74.1311416626,45.2613945007],"type":"Point"}
}