{
  "type": "Feature",
  "properties": {
    "addr:full":"4403 48 Ave Sylvan Lake AB T4S 1N8",
    "addr:housenumber":"4403",
    "addr:postcode":"t4s 1n8",
    "addr:street":"48 Ave",
    "iso:country":"CA",
    "sg:address":"4403 48 Ave",
    "sg:city":"Sylvan Lake",
    "sg:classifiers":[
        {
            "category":"Building & Trades",
            "subcategory":"Construction",
            "type":"Services"
        }
    ],
    "sg:phone":"+1 403 887 4229",
    "sg:postcode":"T4S 1N8",
    "sg:province":"AB",
    "sg:tags":[
        "painter"
    ],
    "wof:name":"Dennis J Wilde Painting",
    "wof:placetype":"venue"
},
  "geometry": {"coordinates":[-114.08702099999999,52.306507],"type":"Point"}
}