{
  "type": "Feature",
  "properties": {
    "addr:full":"1330 Pembroke St W Pembroke ON K8A 7A3",
    "addr:housenumber":"1330",
    "addr:postcode":"k8a 7a3",
    "addr:street":"Pembroke St W",
    "iso:country":"CA",
    "sg:address":"1330 Pembroke St W",
    "sg:city":"Pembroke",
    "sg:classifiers":[
        {
            "category":"Health Services",
            "subcategory":"Health Practitioner",
            "type":"Services"
        }
    ],
    "sg:phone":"+1 613 732 4713",
    "sg:postcode":"K8A 7A3",
    "sg:province":"ON",
    "sg:tags":[
        "home",
        "nurse",
        "registry"
    ],
    "wof:name":"Access Health Care Svc Inc",
    "wof:placetype":"venue"
},
  "geometry": {"coordinates":[-77.15371704099999,45.8348808289],"type":"Point"}
}