{
  "type": "Feature",
  "properties": {
    "addr:full":"951 Rowntree Dairy Rd Woodbridge ON L4L 8Z5",
    "addr:housenumber":"951",
    "addr:postcode":"l4l 8z5",
    "addr:street":"Rowntree Dairy Rd",
    "iso:country":"CA",
    "sg:address":"951 Rowntree Dairy Rd",
    "sg:city":"Woodbridge",
    "sg:classifiers":[
        {
            "category":"Wholesale",
            "subcategory":"Stationery",
            "type":"Manufacturing & Wholesale Goods"
        }
    ],
    "sg:phone":"+1 905 264 0655",
    "sg:postcode":"L4L 8Z5",
    "sg:province":"ON",
    "sg:tags":[
        "room",
        "shipping",
        "supply"
    ],
    "wof:name":"Canadian Industrial Distr Inc",
    "wof:placetype":"venue"
},
  "geometry": {"coordinates":[-79.5706253052,43.7829437256],"type":"Point"}
}