{
  "type": "Feature",
  "properties": {
    "addr:full":"250 Thatcher Dr E Moose Jaw SK S6J 1L7",
    "addr:housenumber":"250",
    "addr:postcode":"s6j 1l7",
    "addr:street":"Thatcher Dr E",
    "iso:country":"CA",
    "sg:address":"250 Thatcher Dr E",
    "sg:city":"Moose Jaw",
    "sg:classifiers":[
        {
            "category":"Restaurant",
            "type":"Food & Drink"
        }
    ],
    "sg:phone":"+1 306 692 2424",
    "sg:postcode":"S6J 1L7",
    "sg:province":"SK",
    "sg:tags":[
        "caterer"
    ],
    "wof:name":"Super Meats Catering",
    "wof:placetype":"venue"
},
  "geometry": {"coordinates":[-105.53463000000001,50.412586],"type":"Point"}
}