{
  "type": "Feature",
  "properties": {
    "iso:country":"CA",
    "sg:address":"8420 Boul Lacroix",
    "sg:city":"Saint-Georges",
    "sg:classifiers":[
        {
            "category":"Real Estate",
            "subcategory":"Real Estate Agent",
            "type":"Services"
        }
    ],
    "sg:phone":"+1 418 228 1991",
    "sg:postcode":"G5Y 2B5",
    "sg:province":"QC",
    "wof:name":"Permanent Beauce",
    "wof:placetype":"venue"
},
  "geometry": {"coordinates":[-70.70108,46.133663],"type":"Point"}
}