{
  "type": "Feature",
  "properties": {
    "addr:full":"124 Nassau St N Winnipeg MB R3L 2H1",
    "addr:housenumber":"124",
    "addr:postcode":"r3l 2h1",
    "addr:street":"Nassau St N",
    "iso:country":"CA",
    "sg:address":"124 Nassau St N",
    "sg:city":"Winnipeg",
    "sg:classifiers":[
        {
            "category":"Real Estate",
            "subcategory":"Architect",
            "type":"Services"
        }
    ],
    "sg:phone":"+1 204 453 6441",
    "sg:postcode":"R3L 2H1",
    "sg:province":"MB",
    "wof:name":"Calnitsky Associates Archs",
    "wof:placetype":"venue"
},
  "geometry": {"coordinates":[-97.14865899999999,49.877174],"type":"Point"}
}