{
  "type": "Feature",
  "properties": {
    "addr:full":"36 Rue Laforest Saint-Ignace-DE-Loyola QC J0K 2P0",
    "addr:housenumber":"36",
    "addr:postcode":"j0k 2p0",
    "addr:street":"Rue Laforest",
    "iso:country":"CA",
    "sg:address":"36 Rue Laforest",
    "sg:city":"Saint-Ignace-DE-Loyola",
    "sg:classifiers":[
        {
            "category":"Retail",
            "subcategory":"Auto Repair",
            "type":"Services"
        }
    ],
    "sg:phone":"+1 450 836 1010",
    "sg:postcode":"J0K 2P0",
    "sg:province":"QC",
    "sg:tags":[
        "repairing",
        "automobile"
    ],
    "wof:name":"Garage Mg Mecanique",
    "wof:placetype":"venue"
},
  "geometry": {"coordinates":[-73.131569,46.065887],"type":"Point"}
}