{
  "type": "Feature",
  "properties": {
    "iso:country":"CA",
    "sg:address":"510 Montee Des Trente",
    "sg:city":"Mont-Saint-Hilaire",
    "sg:classifiers":[
        {
            "category":"Museum",
            "type":"Entertainment"
        }
    ],
    "sg:phone":"+1 450 464 2500",
    "sg:postcode":"J3H 2R8",
    "sg:province":"QC",
    "wof:name":"Maison Des Cultures",
    "wof:placetype":"venue"
},
  "geometry": {"coordinates":[-73.18849945069999,45.5491905212],"type":"Point"}
}