{
  "type": "Feature",
  "properties": {
    "addr:full":"2925 Boul Du Cure-Labelle Prevost QC J0R 1T0",
    "addr:housenumber":"2925",
    "addr:postcode":"j0r 1t0",
    "addr:street":"Boul Du Cure-Labelle Prevost",
    "iso:country":"CA",
    "sg:address":"2925 Boul Du Cure-Labelle",
    "sg:city":"Prevost",
    "sg:classifiers":[
        {
            "category":"Restaurant",
            "type":"Food & Drink"
        }
    ],
    "sg:phone":"+1 450 224 2916",
    "sg:postcode":"J0R 1T0",
    "sg:province":"QC",
    "wof:name":"Restaurant Pizzeria L'Escale",
    "wof:placetype":"venue"
},
  "geometry": {"coordinates":[-74.07038116459999,45.8617897034],"type":"Point"}
}