{
  "type": "Feature",
  "properties": {
    "iso:country":"CA",
    "sg:city":"Clinton",
    "sg:classifiers":[
        {
            "category":"Recreation",
            "type":"Entertainment"
        }
    ],
    "sg:phone":"+1 250 459 7989",
    "sg:postcode":"V0K 1K0",
    "sg:province":"BC",
    "sg:tags":[
        "club",
        "curling"
    ],
    "wof:name":"Clinton Curling Club",
    "wof:placetype":"venue"
},
  "geometry": {"coordinates":[-121.58605194099999,51.0907516479],"type":"Point"}
}