{
  "type": "Feature",
  "properties": {
    "addr:full":"434 Keltic Dr Sydney NS B1L 1B8",
    "addr:housenumber":"434",
    "addr:postcode":"b1l 1b8",
    "addr:street":"Keltic Dr",
    "iso:country":"CA",
    "sg:address":"434 Keltic Dr",
    "sg:city":"Sydney",
    "sg:classifiers":[
        {
            "category":"Building & Trades",
            "subcategory":"Construction",
            "type":"Services"
        }
    ],
    "sg:phone":"+1 902 562 8008",
    "sg:postcode":"B1L 1B8",
    "sg:province":"NS",
    "sg:tags":[
        "roofing",
        "contractor"
    ],
    "wof:name":"Quentin's Roofing Ltd",
    "wof:placetype":"venue"
},
  "geometry": {"coordinates":[-60.241463,46.122303],"type":"Point"}
}