{
  "type": "Feature",
  "properties": {
    "addr:full":"2601 Granite Ave Merritt BC V1K 1A1",
    "addr:housenumber":"2601",
    "addr:postcode":"v1k 1a1",
    "addr:street":"Granite Ave",
    "iso:country":"CA",
    "sg:address":"2601 Granite Ave",
    "sg:city":"Merritt",
    "sg:classifiers":[
        {
            "category":"Retail",
            "subcategory":"Car Wash",
            "type":"Services"
        }
    ],
    "sg:phone":"+1 250 378 4944",
    "sg:postcode":"V1K 1A1",
    "sg:province":"BC",
    "sg:tags":[
        "polishing",
        "washing"
    ],
    "wof:name":"Clean Machine",
    "wof:placetype":"venue"
},
  "geometry": {"coordinates":[-120.775215,50.107628],"type":"Point"}
}