{
  "type": "Feature",
  "properties": {
    "iso:country":"CA",
    "sg:address":"9418 118 Ave NW",
    "sg:city":"Edmonton",
    "sg:classifiers":[
        {
            "category":"Insurance",
            "subcategory":"Insurance Agent",
            "type":"Services"
        }
    ],
    "sg:phone":"+1 780 474 8006",
    "sg:postcode":"T5G 0N6",
    "sg:province":"AB",
    "wof:name":"Allied Insurance Svc Ltd",
    "wof:placetype":"venue"
},
  "geometry": {"coordinates":[-113.486152649,53.5705413818],"type":"Point"}
}