{
  "type": "Feature",
  "properties": {
    "addr:full":"81 German CO Tract Breslau ON N0B 1M0",
    "addr:housenumber":"81",
    "addr:postcode":"n0b 1m0",
    "addr:street":"German",
    "iso:country":"CA",
    "sg:address":"81 German CO Tract",
    "sg:city":"Breslau",
    "sg:classifiers":[
        {
            "category":"Organizations",
            "subcategory":"Professional Association",
            "type":"Services"
        }
    ],
    "sg:phone":"+1 519 648 2311",
    "sg:postcode":"N0B 1M0",
    "sg:province":"ON",
    "sg:tags":[
        "club"
    ],
    "wof:name":"Polski Dom 2000",
    "wof:placetype":"venue"
},
  "geometry": {"coordinates":[-80.413971,43.475697],"type":"Point"}
}