{
  "type": "Feature",
  "properties": {
    "iso:country":"CA",
    "sg:city":"Pickering",
    "sg:classifiers":[
        {
            "category":"Banks & Credit Unions",
            "subcategory":"Bank",
            "type":"Services"
        }
    ],
    "sg:phone":"+1 905 428 8565",
    "sg:postcode":"L1V 6K5",
    "sg:province":"ON",
    "sg:tags":[
        "loan",
        "real estate"
    ],
    "wof:name":"Sgh Mortgages Inc",
    "wof:placetype":"venue"
},
  "geometry": {"coordinates":[-79.068962,43.843048],"type":"Point"}
}