{
  "type": "Feature",
  "properties": {
    "addr:full":"1403 7 St Nisku AB T9E 7P8",
    "addr:housenumber":"1403 7",
    "addr:postcode":"t9e 7p8",
    "addr:street":"St",
    "iso:country":"CA",
    "sg:address":"1403 7 St",
    "sg:city":"Nisku",
    "sg:classifiers":[
        {
            "category":"Manufacturing",
            "subcategory":"Metals",
            "type":"Manufacturing & Wholesale Goods"
        }
    ],
    "sg:phone":"+1 780 955 0501",
    "sg:postcode":"T9E 7P8",
    "sg:province":"AB",
    "sg:tags":[
        "pipe"
    ],
    "wof:name":"Pipe & Piling Supplies Ltd",
    "wof:placetype":"venue"
},
  "geometry": {"coordinates":[-113.521355,53.317856],"type":"Point"}
}