{
  "type": "Feature",
  "properties": {
    "addr:full":"49 Lakeshore Dr North Bay ON P1A 2A4",
    "addr:housenumber":"49",
    "addr:postcode":"p1a 2a4",
    "addr:street":"Lakeshore Dr",
    "iso:country":"CA",
    "sg:address":"49 Lakeshore Dr",
    "sg:city":"North Bay",
    "sg:classifiers":[
        {
            "category":"Autos & Motor Vehicles",
            "subcategory":"Auto Supplies",
            "type":"Retail Goods"
        }
    ],
    "sg:phone":"+1 705 474 9700",
    "sg:postcode":"P1A 2A4",
    "sg:province":"ON",
    "sg:tags":[
        "tire"
    ],
    "wof:name":"Brooks oK Tire",
    "wof:placetype":"venue"
},
  "geometry": {"coordinates":[-79.4544830322,46.2942695618],"type":"Point"}
}