{
  "type": "Feature",
  "properties": {
    "addr:full":"5402 50th St Grimshaw AB T0H 1W0",
    "addr:housenumber":"5402",
    "addr:postcode":"t0h 1w0",
    "addr:street":"50Th St",
    "iso:country":"CA",
    "sg:address":"5402 50th St",
    "sg:city":"Grimshaw",
    "sg:classifiers":[
        {
            "category":"Professional",
            "subcategory":"Lawyer & Legal Services",
            "type":"Services"
        }
    ],
    "sg:phone":"+1 780 332 4647",
    "sg:postcode":"T0H 1W0",
    "sg:province":"AB",
    "sg:tags":[
        "attorney"
    ],
    "wof:name":"Mathieu Hryniuk",
    "wof:placetype":"venue"
},
  "geometry": {"coordinates":[-117.607056,56.191166],"type":"Point"}
}