{
  "type": "Feature",
  "properties": {
    "addr:full":"7077 Duncan St Powell River BC V8A 1W1",
    "addr:housenumber":"7077",
    "addr:postcode":"v8a 1w1",
    "addr:street":"Duncan St",
    "iso:country":"CA",
    "sg:address":"7077 Duncan St",
    "sg:city":"Powell River",
    "sg:classifiers":[
        {
            "category":"Government",
            "subcategory":"Office",
            "type":"Public Place"
        }
    ],
    "sg:phone":"+1 604 485 0774",
    "sg:postcode":"V8A 1W1",
    "sg:province":"BC",
    "wof:name":"British Columbia Environment",
    "wof:placetype":"venue"
},
  "geometry": {"coordinates":[-124.517601013,49.8360481262],"type":"Point"}
}