{
  "type": "Feature",
  "properties": {
    "addr:full":"Sainte-Foy QC G1X 2L7",
    "addr:postcode":"g1x 2l7",
    "iso:country":"CA",
    "sg:city":"Sainte-Foy",
    "sg:classifiers":[
        {
            "category":"Government",
            "subcategory":"Office",
            "type":"Public Place"
        }
    ],
    "sg:phone":"+1 418 653 2155",
    "sg:postcode":"G1X 2L7",
    "sg:province":"QC",
    "sg:tags":[
        "village"
    ],
    "wof:name":"Office Municipal D'Habitation",
    "wof:placetype":"venue"
},
  "geometry": {"coordinates":[-71.316399,46.764767],"type":"Point"}
}