{
  "type": "Feature",
  "properties": {
    "addr:full":"36 Glenhill Cres Cochrane AB T4C 1G8",
    "addr:housenumber":"36",
    "addr:postcode":"t4c 1g8",
    "addr:street":"Glenhill Cres",
    "iso:country":"CA",
    "sg:address":"36 Glenhill Cres",
    "sg:city":"Cochrane",
    "sg:classifiers":[
        {
            "category":"Mining & Drilling",
            "type":"Manufacturing & Wholesale Goods"
        }
    ],
    "sg:phone":"+1 403 932 7771",
    "sg:postcode":"T4C 1G8",
    "sg:province":"AB",
    "sg:tags":[
        "field",
        "oil"
    ],
    "wof:name":"Wellpro Productions Svc Ltd",
    "wof:placetype":"venue"
},
  "geometry": {"coordinates":[-114.483009338,51.1878433228],"type":"Point"}
}