{
  "type": "Feature",
  "properties": {
    "addr:full":"5771 No. 3 Rd # 170 Richmond BC V6X 2C9",
    "addr:housenumber":"170",
    "addr:postcode":"5771;v6x 2c9",
    "addr:street":"3 Rd #",
    "iso:country":"CA",
    "sg:address":"5771 No. 3 Rd # 170",
    "sg:city":"Richmond",
    "sg:classifiers":[
        {
            "category":"Retail",
            "subcategory":"Auto Repair",
            "type":"Services"
        }
    ],
    "sg:phone":"+1 604 279 0388",
    "sg:postcode":"V6X 2C9",
    "sg:province":"BC",
    "sg:tags":[
        "repairing",
        "automobile"
    ],
    "wof:name":"Kaohsing Automobile Ltd",
    "wof:placetype":"venue"
},
  "geometry": {"coordinates":[-123.13696299999999,49.172642],"type":"Point"}
}