{
  "type": "Feature",
  "properties": {
    "iso:country":"CA",
    "sg:address":"316 Old Black River Rd",
    "sg:city":"Saint John",
    "sg:classifiers":[
        {
            "category":"Building & Trades",
            "subcategory":"Construction",
            "type":"Services"
        }
    ],
    "sg:phone":"+1 506 635 7663",
    "sg:postcode":"E2J 4Y1",
    "sg:province":"NB",
    "sg:tags":[
        "roofing",
        "contractor"
    ],
    "wof:name":"Atlantic Roofers Ltd",
    "wof:placetype":"venue"
},
  "geometry": {"coordinates":[-66.00188446040001,45.2727012634],"type":"Point"}
}