{
  "type": "Feature",
  "properties": {
    "iso:country":"CA",
    "sg:address":"1685 Ingleton Ave",
    "sg:city":"Burnaby",
    "sg:classifiers":[
        {
            "category":"Professional",
            "subcategory":"Management & Consulting",
            "type":"Services"
        }
    ],
    "sg:phone":"+1 604 294 3424",
    "sg:postcode":"V5C 4L8",
    "sg:province":"BC",
    "sg:tags":[
        "marketing",
        "consultant"
    ],
    "wof:name":"Jmp Marketing Svc Ltd",
    "wof:placetype":"venue"
},
  "geometry": {"coordinates":[-123.018913269,49.2695465088],"type":"Point"}
}