{
  "type": "Feature",
  "properties": {
    "addr:full":"Minden ON K0M 2K0",
    "addr:postcode":"k0m 2k0",
    "iso:country":"CA",
    "sg:city":"Minden",
    "sg:classifiers":[
        {
            "category":"Organizations",
            "subcategory":"Religious Organization",
            "type":"Services"
        }
    ],
    "sg:phone":"+1 705 286 1338",
    "sg:postcode":"K0M 2K0",
    "sg:province":"ON",
    "sg:tags":[
        "church"
    ],
    "wof:name":"Minden Bible Church",
    "wof:placetype":"venue"
},
  "geometry": {"coordinates":[-78.725899,44.926125],"type":"Point"}
}