{
  "type": "Feature",
  "properties": {
    "addr:full":"Boucherville QC J4B 6G4",
    "addr:postcode":"j4b 6g4",
    "iso:country":"CA",
    "sg:city":"Boucherville",
    "sg:classifiers":[
        {
            "category":"Insurance",
            "subcategory":"Insurance Agent",
            "type":"Services"
        }
    ],
    "sg:phone":"+1 450 449 4888",
    "sg:postcode":"J4B 6G4",
    "sg:province":"QC",
    "wof:name":"Assurance Caron & Menard Ltee",
    "wof:placetype":"venue"
},
  "geometry": {"coordinates":[-73.447014,45.577713],"type":"Point"}
}