{
  "type": "Feature",
  "properties": {
    "iso:country":"CA",
    "sg:city":"Toronto",
    "sg:classifiers":[
        {
            "category":"Communications",
            "subcategory":"Film & Video Production",
            "type":"Services"
        }
    ],
    "sg:phone":"+1 416 598 2232",
    "sg:postcode":"M5V 1G1",
    "sg:province":"ON",
    "sg:tags":[
        "motion",
        "picture",
        "studio",
        "producer"
    ],
    "wof:name":"Avion Film Productions Inc",
    "wof:placetype":"venue"
},
  "geometry": {"coordinates":[-79.3991470337,43.6429443359],"type":"Point"}
}