{
  "type": "Feature",
  "properties": {
    "addr:full":"2878 Lake Shore Blvd W Etobicoke ON M8V 1J2",
    "addr:housenumber":"2878",
    "addr:postcode":"m8v 1j2",
    "addr:street":"Lake Shore Blvd W",
    "iso:country":"CA",
    "sg:address":"2878 Lake Shore Blvd W",
    "sg:city":"Etobicoke",
    "sg:classifiers":[
        {
            "category":"Recreation",
            "type":"Entertainment"
        }
    ],
    "sg:phone":"+1 416 251 1376",
    "sg:postcode":"M8V 1J2",
    "sg:province":"ON",
    "sg:tags":[
        "parlor",
        "billiard"
    ],
    "wof:name":"New Toronto Billiards",
    "wof:placetype":"venue"
},
  "geometry": {"coordinates":[-79.5034866333,43.6013145447],"type":"Point"}
}