{
  "type": "Feature",
  "properties": {
    "iso:country":"CA",
    "sg:address":"3995 Sande Ave",
    "sg:city":"Thornhill",
    "sg:classifiers":[
        {
            "category":"Building & Trades",
            "subcategory":"Construction",
            "type":"Services"
        }
    ],
    "sg:phone":"+1 250 638 0086",
    "sg:postcode":"V8G 3V5",
    "sg:province":"BC",
    "sg:tags":[
        "excavating",
        "contractor",
        "general"
    ],
    "wof:name":"Mountain Shadow Excavating",
    "wof:placetype":"venue"
},
  "geometry": {"coordinates":[-128.54264831500001,54.5069313049],"type":"Point"}
}