{
  "type": "Feature",
  "properties": {
    "iso:country":"CA",
    "sg:address":"2266 Rue Marcotte",
    "sg:city":"Canton Magog",
    "sg:classifiers":[
        {
            "category":"Personal",
            "subcategory":"Beauty Salon",
            "type":"Services"
        }
    ],
    "sg:phone":"+1 819 868 6662",
    "sg:postcode":"J1X 5T7",
    "sg:province":"QC",
    "wof:name":"Esthetique Manon Benoit",
    "wof:placetype":"venue"
},
  "geometry": {"coordinates":[-72.1858596802,45.2715568542],"type":"Point"}
}