{
  "type": "Feature",
  "properties": {
    "addr:full":"42 Corinne Cres Scarborough ON M1K 2Y9",
    "addr:housenumber":"42",
    "addr:postcode":"m1k 2y9",
    "addr:street":"Corinne Cres",
    "iso:country":"CA",
    "sg:address":"42 Corinne Cres",
    "sg:city":"Scarborough",
    "sg:classifiers":[
        {
            "category":"Social Services",
            "type":"Services"
        }
    ],
    "sg:phone":"+1 416 755 7913",
    "sg:postcode":"M1K 2Y9",
    "sg:province":"ON",
    "sg:tags":[
        "organization",
        "welfare"
    ],
    "wof:name":"Surex Community Svc",
    "wof:placetype":"venue"
},
  "geometry": {"coordinates":[-79.2738265991,43.7344589233],"type":"Point"}
}