{
  "type": "Feature",
  "properties": {
    "iso:country":"CA",
    "sg:address":"1980 Ch Sainte-Angelique",
    "sg:city":"Saint-Lazare",
    "sg:classifiers":[
        {
            "category":"Organizations",
            "subcategory":"Religious Organization",
            "type":"Services"
        }
    ],
    "sg:phone":"+1 450 455 3523",
    "sg:postcode":"J7T 2Y7",
    "sg:province":"QC",
    "sg:tags":[
        "church"
    ],
    "wof:name":"Presbytere St Lazare",
    "wof:placetype":"venue"
},
  "geometry": {"coordinates":[-74.1420516968,45.4002037048],"type":"Point"}
}