{
  "type": "Feature",
  "properties": {
    "addr:full":"605 Newbold St London ON N6E 2T7",
    "addr:housenumber":"605",
    "addr:postcode":"n6e 2t7",
    "addr:street":"Newbold St",
    "iso:country":"CA",
    "sg:address":"605 Newbold St",
    "sg:city":"London",
    "sg:classifiers":[
        {
            "category":"Manufacturing",
            "subcategory":"Food",
            "type":"Manufacturing & Wholesale Goods"
        }
    ],
    "sg:phone":"+1 519 680 2715",
    "sg:postcode":"N6E 2T7",
    "sg:province":"ON",
    "sg:tags":[
        "confectionery",
        "candy"
    ],
    "wof:name":"Fudgery",
    "wof:placetype":"venue"
},
  "geometry": {"coordinates":[-81.203979,42.934822],"type":"Point"}
}