{
  "type": "Feature",
  "properties": {
    "addr:full":"89 Thames St S Ingersoll ON N5C 2T2",
    "addr:housenumber":"89",
    "addr:postcode":"n5c 2t2",
    "addr:street":"Thames St S",
    "iso:country":"CA",
    "sg:address":"89 Thames St S",
    "sg:city":"Ingersoll",
    "sg:classifiers":[
        {
            "category":"Restaurant",
            "type":"Food & Drink"
        }
    ],
    "sg:phone":"+1 519 485 1221",
    "sg:postcode":"N5C 2T2",
    "sg:province":"ON",
    "wof:name":"Freddie's Fish & Chips",
    "wof:placetype":"venue"
},
  "geometry": {"coordinates":[-80.88381200000001,43.039646],"type":"Point"}
}