{
  "type": "Feature",
  "properties": {
    "addr:full":"86 Driscoll Cres Moncton NB E1E 3R8",
    "addr:housenumber":"86",
    "addr:postcode":"e1e 3r8",
    "addr:street":"Driscoll Cres",
    "iso:country":"CA",
    "sg:address":"86 Driscoll Cres",
    "sg:city":"Moncton",
    "sg:classifiers":[
        {
            "category":"Wholesale",
            "subcategory":"Sporting Goods",
            "type":"Manufacturing & Wholesale Goods"
        }
    ],
    "sg:phone":"+1 506 853 4005",
    "sg:postcode":"E1E 3R8",
    "sg:province":"NB",
    "wof:name":"Conquest Sport",
    "wof:placetype":"venue"
},
  "geometry": {"coordinates":[-64.8357925415,46.0849266052],"type":"Point"}
}