{
  "type": "Feature",
  "properties": {
    "addr:full":"500 Edward Ave Richmond Hill ON L4C 4Y9",
    "addr:housenumber":"500",
    "addr:postcode":"l4c 4y9",
    "addr:street":"Edward Ave",
    "iso:country":"CA",
    "sg:address":"500 Edward Ave",
    "sg:city":"Richmond Hill",
    "sg:classifiers":[
        {
            "category":"Wholesale",
            "subcategory":"Machinery & Supplies",
            "type":"Manufacturing & Wholesale Goods"
        }
    ],
    "sg:phone":"+1 905 884 9161",
    "sg:postcode":"L4C 4Y9",
    "sg:province":"ON",
    "sg:tags":[
        "ladder"
    ],
    "wof:name":"Bon L Canada Inc",
    "wof:placetype":"venue"
},
  "geometry": {"coordinates":[-79.42906188960001,43.8968391418],"type":"Point"}
}