{
  "type": "Feature",
  "properties": {
    "iso:country":"CA",
    "sg:city":"Montreal",
    "sg:classifiers":[
        {
            "category":"Insurance",
            "subcategory":"Insurance Agent",
            "type":"Services"
        }
    ],
    "sg:phone":"+1 514 866 1841",
    "sg:postcode":"H3B 1S6",
    "sg:province":"QC",
    "wof:name":"Munich Reinsurance CO-Canada",
    "wof:placetype":"venue"
},
  "geometry": {"coordinates":[-73.56671142579999,45.5023345947],"type":"Point"}
}