{
  "type": "Feature",
  "properties": {
    "addr:full":"1384 Queen St W Toronto ON M6K 1L7",
    "addr:housenumber":"1384",
    "addr:postcode":"m6k 1l7",
    "addr:street":"Queen St W",
    "iso:country":"CA",
    "sg:address":"1384 Queen St W",
    "sg:city":"Toronto",
    "sg:classifiers":[
        {
            "category":"Restaurant",
            "type":"Food & Drink"
        }
    ],
    "sg:phone":"+1 416 532 9565",
    "sg:postcode":"M6K 1L7",
    "sg:province":"ON",
    "wof:name":"Happy Time Restaurant",
    "wof:placetype":"venue"
},
  "geometry": {"coordinates":[-79.4334640503,43.6413841248],"type":"Point"}
}