{
  "type": "Feature",
  "properties": {
    "addr:full":"795 Fort St Victoria BC V8W 1G9",
    "addr:housenumber":"795",
    "addr:postcode":"v8w 1g9",
    "addr:street":"Fort St",
    "iso:country":"CA",
    "sg:address":"795 Fort St",
    "sg:city":"Victoria",
    "sg:classifiers":[
        {
            "category":"Shopping",
            "subcategory":"Clothing, Apparel, & Fashions",
            "type":"Retail Goods"
        }
    ],
    "sg:phone":"+1 250 480 5183",
    "sg:postcode":"V8W 1G9",
    "sg:province":"BC",
    "wof:name":"Amos & Andes Imports",
    "wof:placetype":"venue"
},
  "geometry": {"coordinates":[-123.36292299999999,48.424129],"type":"Point"}
}