{
  "type": "Feature",
  "properties": {
    "addr:full":"224 Old Post Rd Crapaud PE C0A 1J0",
    "addr:housenumber":"224",
    "addr:postcode":"c0a 1j0",
    "addr:street":"Old Post Rd",
    "iso:country":"CA",
    "sg:address":"224 Old Post Rd",
    "sg:city":"Crapaud",
    "sg:classifiers":[
        {
            "category":"Wholesale",
            "subcategory":"Fruits & Vegetables",
            "type":"Manufacturing & Wholesale Goods"
        }
    ],
    "sg:phone":"+1 902 658 2924",
    "sg:postcode":"C0A 1J0",
    "sg:province":"PE",
    "wof:name":"Boyd Mac Donald Produce Ltd",
    "wof:placetype":"venue"
},
  "geometry": {"coordinates":[-63.4920082092,46.2350082397],"type":"Point"}
}