{
  "type": "Feature",
  "properties": {
    "addr:full":"1575 Steeles Ave E #102 North York ON M2M 3Y7",
    "addr:housenumber":"1575",
    "addr:postcode":"m2m 3y7",
    "addr:street":"Steeles Ave E # 102",
    "iso:country":"CA",
    "sg:address":"1575 Steeles Ave E #102",
    "sg:city":"North York",
    "sg:classifiers":[
        {
            "category":"Health Services",
            "subcategory":"Doctor",
            "type":"Services"
        }
    ],
    "sg:phone":"+1 416 226 4565",
    "sg:postcode":"M2M 3Y7",
    "sg:province":"ON",
    "sg:tags":[
        "physician",
        "surgeon"
    ],
    "wof:name":"Reingold, T MD",
    "wof:placetype":"venue"
},
  "geometry": {"coordinates":[-79.3835220337,43.805973053],"type":"Point"}
}