{
  "type": "Feature",
  "properties": {
    "addr:full":"446 Hansen Rd N Brampton ON L6V 3P8",
    "addr:housenumber":"446",
    "addr:postcode":"l6v 3p8",
    "addr:street":"Hansen Rd N",
    "iso:country":"CA",
    "sg:address":"446 Hansen Rd N",
    "sg:city":"Brampton",
    "sg:classifiers":[
        {
            "category":"Building & Trades",
            "subcategory":"Plumbing",
            "type":"Services"
        }
    ],
    "sg:phone":"+1 905 453 7221",
    "sg:postcode":"L6V 3P8",
    "sg:province":"ON",
    "sg:tags":[
        "ventilating",
        "contractor"
    ],
    "wof:name":"Kenyon Mechanical Design Inc",
    "wof:placetype":"venue"
},
  "geometry": {"coordinates":[-79.76155900000001,43.711727],"type":"Point"}
}