{
  "type": "Feature",
  "properties": {
    "addr:full":"Beauport QC G1C 1P5",
    "addr:postcode":"qc g1c 1p5",
    "iso:country":"CA",
    "sg:city":"Beauport",
    "sg:classifiers":[
        {
            "category":"Shopping",
            "subcategory":"Computers & Home Electronics",
            "type":"Retail Goods"
        }
    ],
    "sg:phone":"+1 418 661 5789",
    "sg:postcode":"G1C 1P5",
    "sg:province":"QC",
    "sg:tags":[
        "television",
        "radio"
    ],
    "wof:name":"Tv Moderne Enr",
    "wof:placetype":"venue"
},
  "geometry": {"coordinates":[-71.15926399999999,46.883774],"type":"Point"}
}