{
  "type": "Feature",
  "properties": {
    "iso:country":"CA",
    "sg:address":"231 13 St N",
    "sg:city":"Lethbridge",
    "sg:classifiers":[
        {
            "category":"Shopping",
            "type":"Retail Goods"
        }
    ],
    "sg:phone":"+1 403 381 4145",
    "sg:postcode":"T1H 2R6",
    "sg:province":"AB",
    "sg:tags":[
        "equipment",
        "wine",
        "supply"
    ],
    "wof:name":"Prairie Vintners & Brewers",
    "wof:placetype":"venue"
},
  "geometry": {"coordinates":[-112.824012756,49.7012825012],"type":"Point"}
}