{
  "type": "Feature",
  "properties": {
    "iso:country":"CA",
    "sg:address":"282 St Clair Ave W",
    "sg:city":"Toronto",
    "sg:classifiers":[
        {
            "category":"Health Services",
            "subcategory":"Nursing And Care Facility",
            "type":"Services"
        }
    ],
    "sg:phone":"+1 416 925 2283",
    "sg:postcode":"M4V 1S3",
    "sg:province":"ON",
    "sg:tags":[
        "home",
        "retirement",
        "community"
    ],
    "wof:name":"Village Park Retirement Rsdnc",
    "wof:placetype":"venue"
},
  "geometry": {"coordinates":[-79.4097366333,43.6850624084],"type":"Point"}
}