{
  "type": "Feature",
  "properties": {
    "addr:full":"Whistler BC V0N 1B4",
    "addr:postcode":"v0n 1b4",
    "iso:country":"CA",
    "sg:city":"Whistler",
    "sg:classifiers":[
        {
            "category":"Restaurant",
            "type":"Food & Drink"
        }
    ],
    "sg:phone":"+1 604 932 3244",
    "sg:postcode":"V0N 1B4",
    "sg:province":"BC",
    "sg:tags":[
        "sandwich"
    ],
    "wof:name":"Subway Sandwiches & Salads",
    "wof:placetype":"venue"
},
  "geometry": {"coordinates":[-122.958457947,50.1149978638],"type":"Point"}
}