{
  "type": "Feature",
  "properties": {
    "addr:full":"5309 Maingate Dr Mississauga ON L4W 1G6",
    "addr:housenumber":"5309",
    "addr:postcode":"l4w 1g6",
    "addr:street":"Maingate Dr",
    "iso:country":"CA",
    "sg:address":"5309 Maingate Dr",
    "sg:city":"Mississauga",
    "sg:classifiers":[
        {
            "category":"Manufacturing",
            "subcategory":"Textiles",
            "type":"Manufacturing & Wholesale Goods"
        }
    ],
    "sg:phone":"+1 905 629 2209",
    "sg:postcode":"L4W 1G6",
    "sg:province":"ON",
    "sg:tags":[
        "material",
        "waterproofing"
    ],
    "wof:name":"Ultraseal Waterproofing",
    "wof:placetype":"venue"
},
  "geometry": {"coordinates":[-79.6329498291,43.6344985962],"type":"Point"}
}