{
  "type": "Feature",
  "properties": {
    "addr:full":"1196 Rue D'Artigny Quebec QC G1R 3N8",
    "addr:housenumber":"1196",
    "addr:postcode":"g1r 3n8",
    "addr:street":"Rue D'Artigny",
    "iso:country":"CA",
    "sg:address":"1196 Rue D'Artigny",
    "sg:city":"Quebec",
    "sg:classifiers":[
        {
            "category":"Restaurant",
            "type":"Food & Drink"
        }
    ],
    "sg:phone":"+1 418 525 7075",
    "sg:postcode":"G1R 3N8",
    "sg:province":"QC",
    "wof:name":"Subway Sandwiches & Salads",
    "wof:placetype":"venue"
},
  "geometry": {"coordinates":[-71.2156829834,46.8072547913],"type":"Point"}
}