{
  "type": "Feature",
  "properties": {
    "addr:full":"Guelph ON N1H 4J4",
    "addr:postcode":"n1h 4j4",
    "iso:country":"CA",
    "sg:city":"Guelph",
    "sg:classifiers":[
        {
            "category":"Social Services",
            "type":"Services"
        }
    ],
    "sg:phone":"+1 519 767 2424",
    "sg:postcode":"N1H 4J4",
    "sg:province":"ON",
    "sg:tags":[
        "counselor",
        "marriage",
        "family"
    ],
    "wof:name":"Hodgson, Judy",
    "wof:placetype":"venue"
},
  "geometry": {"coordinates":[-80.251442,43.544857],"type":"Point"}
}