{
  "type": "Feature",
  "properties": {
    "iso:country":"CA",
    "sg:address":"48 Woodlawn Ave",
    "sg:city":"Winnipeg",
    "sg:classifiers":[
        {
            "category":"Professional",
            "subcategory":"Business Services",
            "type":"Services"
        }
    ],
    "sg:phone":"+1 204 257 1407",
    "sg:postcode":"R2M 2P2",
    "sg:province":"MB",
    "sg:tags":[
        "translator",
        "interpreter"
    ],
    "wof:name":"Freynet-Gagne Translation Svc",
    "wof:placetype":"venue"
},
  "geometry": {"coordinates":[-97.117607,49.822227],"type":"Point"}
}