{
  "type": "Feature",
  "properties": {
    "iso:country":"CA",
    "sg:address":"104 Avenue Rd",
    "sg:city":"Toronto",
    "sg:classifiers":[
        {
            "category":"Professional",
            "subcategory":"Business Services",
            "type":"Services"
        }
    ],
    "sg:phone":"+1 416 920 8162",
    "sg:postcode":"M5R 2H3",
    "sg:province":"ON",
    "sg:tags":[
        "interior",
        "consultant",
        "design",
        "decorator"
    ],
    "wof:name":"Babcock Zanner Inc",
    "wof:placetype":"venue"
},
  "geometry": {"coordinates":[-79.396065,43.672977],"type":"Point"}
}