{
  "type": "Feature",
  "properties": {
    "addr:full":"Moosomin SK S0G 3N0",
    "addr:postcode":"s0g 3n0",
    "iso:country":"CA",
    "sg:city":"Moosomin",
    "sg:classifiers":[
        {
            "category":"Retail",
            "subcategory":"Auto Repair",
            "type":"Services"
        }
    ],
    "sg:phone":"+1 306 435 4188",
    "sg:postcode":"S0G 3N0",
    "sg:province":"SK",
    "sg:tags":[
        "body",
        "automobile",
        "painting"
    ],
    "wof:name":"Easton's Autobody",
    "wof:placetype":"venue"
},
  "geometry": {"coordinates":[-101.663291931,50.1470336914],"type":"Point"}
}