{
  "type": "Feature",
  "properties": {
    "addr:full":"Vernon BC V1T 5G4",
    "addr:postcode":"v1t 5g4",
    "iso:country":"CA",
    "sg:city":"Vernon",
    "sg:classifiers":[
        {
            "category":"Restaurant",
            "type":"Food & Drink"
        }
    ],
    "sg:phone":"+1 250 542 7900",
    "sg:postcode":"V1T 5G4",
    "sg:province":"BC",
    "wof:name":"Polson Park Diner",
    "wof:placetype":"venue"
},
  "geometry": {"coordinates":[-119.268936,50.259502],"type":"Point"}
}