{
  "type": "Feature",
  "properties": {
    "addr:full":"Sundre AB T0M 1X0",
    "addr:postcode":"t0m 1x0",
    "iso:country":"CA",
    "sg:city":"Sundre",
    "sg:classifiers":[
        {
            "category":"Manufacturing",
            "subcategory":"Printing",
            "type":"Manufacturing & Wholesale Goods"
        }
    ],
    "sg:phone":"+1 403 638 3577",
    "sg:postcode":"T0M 1X0",
    "sg:province":"AB",
    "sg:tags":[
        "newspaper"
    ],
    "wof:name":"Sundre Round Up Publishing Ltd",
    "wof:placetype":"venue"
},
  "geometry": {"coordinates":[-114.641693,51.797276],"type":"Point"}
}