{
  "type": "Feature",
  "properties": {
    "addr:full":"201 Ontario St Collingwood ON L9Y 4M4",
    "addr:housenumber":"201",
    "addr:postcode":"l9y 4m4",
    "addr:street":"Ontario St",
    "iso:country":"CA",
    "sg:address":"201 Ontario St",
    "sg:city":"Collingwood",
    "sg:classifiers":[
        {
            "category":"Government",
            "subcategory":"Police Station",
            "type":"Public Place"
        }
    ],
    "sg:phone":"+1 705 445 4321",
    "sg:postcode":"L9Y 4M4",
    "sg:province":"ON",
    "sg:tags":[
        "department"
    ],
    "wof:name":"Collingwood Police Office",
    "wof:placetype":"venue"
},
  "geometry": {"coordinates":[-80.21157073969999,44.5007286072],"type":"Point"}
}