{
  "type": "Feature",
  "properties": {
    "addr:full":"Edmonton AB T5H 0V8",
    "addr:postcode":"t5h 0v8",
    "iso:country":"CA",
    "sg:city":"Edmonton",
    "sg:classifiers":[
        {
            "category":"Organizations",
            "subcategory":"Religious Organization",
            "type":"Services"
        }
    ],
    "sg:phone":"+1 780 448 1950",
    "sg:postcode":"T5H 0V8",
    "sg:province":"AB",
    "sg:tags":[
        "church"
    ],
    "wof:name":"Edmonton Vietnamese Mennonite",
    "wof:placetype":"venue"
},
  "geometry": {"coordinates":[-113.497955322,53.5516548157],"type":"Point"}
}