{
  "type": "Feature",
  "properties": {
    "iso:country":"CA",
    "sg:address":"644 Rue Principale",
    "sg:city":"Neguac",
    "sg:classifiers":[
        {
            "category":"Food & Beverages",
            "subcategory":"Meat & Fish",
            "type":"Retail Goods"
        }
    ],
    "sg:phone":"+1 506 776 8317",
    "sg:postcode":"E9G 1N3",
    "sg:province":"NB",
    "sg:tags":[
        "seafood"
    ],
    "wof:name":"Allain, Roger",
    "wof:placetype":"venue"
},
  "geometry": {"coordinates":[-65.0840911865,47.2438812256],"type":"Point"}
}