{
  "type": "Feature",
  "properties": {
    "addr:full":"1402 20 Ave Coaldale AB T1M 1A3",
    "addr:housenumber":"1402",
    "addr:postcode":"t1m 1a3",
    "addr:street":"20 Ave",
    "iso:country":"CA",
    "sg:address":"1402 20 Ave",
    "sg:city":"Coaldale",
    "sg:classifiers":[
        {
            "category":"Government",
            "subcategory":"Police Station",
            "type":"Public Place"
        }
    ],
    "sg:phone":"+1 403 345 4425",
    "sg:postcode":"T1M 1A3",
    "sg:province":"AB",
    "sg:tags":[
        "department"
    ],
    "wof:name":"Coaldale Police Dept",
    "wof:placetype":"venue"
},
  "geometry": {"coordinates":[-112.613479614,49.7276573181],"type":"Point"}
}