{
  "type": "Feature",
  "properties": {
    "addr:full":"16740 110 St NW Edmonton AB T5X 2V1",
    "addr:housenumber":"16740",
    "addr:postcode":"t5x 2v1",
    "addr:street":"110 St Nw",
    "iso:country":"CA",
    "sg:address":"16740 110 St NW",
    "sg:city":"Edmonton",
    "sg:classifiers":[
        {
            "category":"Wholesale",
            "subcategory":"Machinery & Supplies",
            "type":"Manufacturing & Wholesale Goods"
        }
    ],
    "sg:phone":"+1 780 457 0045",
    "sg:postcode":"T5X 2V1",
    "sg:province":"AB",
    "sg:tags":[
        "packaging"
    ],
    "wof:name":"Sparrow Packaging",
    "wof:placetype":"venue"
},
  "geometry": {"coordinates":[-113.514351,53.628147],"type":"Point"}
}