{
  "type": "Feature",
  "properties": {
    "addr:full":"8 Queen St Crysler ON K0A 1R0",
    "addr:housenumber":"8",
    "addr:postcode":"k0a 1r0",
    "addr:street":"Queen St",
    "iso:country":"CA",
    "sg:address":"8 Queen St",
    "sg:city":"Crysler",
    "sg:classifiers":[
        {
            "category":"Shopping",
            "subcategory":"Catalog Store",
            "type":"Retail Goods"
        }
    ],
    "sg:phone":"+1 613 987 5345",
    "sg:postcode":"K0A 1R0",
    "sg:province":"ON",
    "sg:tags":[
        "mail",
        "order",
        "internet"
    ],
    "wof:name":"Sears Canada Inc",
    "wof:placetype":"venue"
},
  "geometry": {"coordinates":[-75.1524734497,45.2185020447],"type":"Point"}
}