{
  "type": "Feature",
  "properties": {
    "addr:full":"2215 2 Ave N Lethbridge AB T1H 0C1",
    "addr:housenumber":"2215",
    "addr:postcode":"t1h 0c1",
    "addr:street":"2 Ave N",
    "iso:country":"CA",
    "sg:address":"2215 2 Ave N",
    "sg:city":"Lethbridge",
    "sg:classifiers":[
        {
            "category":"Manufacturing",
            "subcategory":"Metals",
            "type":"Manufacturing & Wholesale Goods"
        }
    ],
    "sg:phone":"+1 403 320 9661",
    "sg:postcode":"T1H 0C1",
    "sg:province":"AB",
    "sg:tags":[
        "work",
        "sheet",
        "contractor"
    ],
    "wof:name":"Boma Enterprises Ltd",
    "wof:placetype":"venue"
},
  "geometry": {"coordinates":[-112.80925000000001,49.700371],"type":"Point"}
}