{
  "type": "Feature",
  "properties": {
    "addr:full":"Dieppe NB E1A 4X5",
    "addr:postcode":"e1a 4x5",
    "iso:country":"CA",
    "sg:city":"Dieppe",
    "sg:classifiers":[
        {
            "category":"Shopping",
            "subcategory":"Clothing, Apparel, & Fashions",
            "type":"Retail Goods"
        }
    ],
    "sg:phone":"+1 506 857 9828",
    "sg:postcode":"E1A 4X5",
    "sg:province":"NB",
    "sg:tags":[
        "jean"
    ],
    "wof:name":"Bluenotes",
    "wof:placetype":"venue"
},
  "geometry": {"coordinates":[-64.76100158689999,46.0988845825],"type":"Point"}
}