{
  "type": "Feature",
  "properties": {
    "iso:country":"CA",
    "sg:address":"Hodgson Rd",
    "sg:city":"Williams Lake",
    "sg:classifiers":[
        {
            "category":"Building & Trades",
            "subcategory":"Construction",
            "type":"Services"
        }
    ],
    "sg:phone":"+1 250 398 8965",
    "sg:postcode":"V2G 2P1",
    "sg:province":"BC",
    "sg:tags":[
        "excavating",
        "contractor",
        "general"
    ],
    "wof:name":"George Giesbrecht Contracting",
    "wof:placetype":"venue"
},
  "geometry": {"coordinates":[-122.134766,52.11412],"type":"Point"}
}