{
  "type": "Feature",
  "properties": {
    "addr:full":"5016 47 Ave Bon Accord AB T0A 0K0",
    "addr:housenumber":"5016",
    "addr:postcode":"t0a 0k0",
    "addr:street":"47 Ave",
    "iso:country":"CA",
    "sg:address":"5016 47 Ave",
    "sg:city":"Bon Accord",
    "sg:classifiers":[
        {
            "category":"Retail",
            "subcategory":"Funeral Services",
            "type":"Services"
        }
    ],
    "sg:phone":"+1 780 915 1860",
    "sg:postcode":"T0A 0K0",
    "sg:province":"AB",
    "sg:tags":[
        "director"
    ],
    "wof:name":"Sturgeon Memorial Funeral Chpl",
    "wof:placetype":"venue"
},
  "geometry": {"coordinates":[-113.41368866000001,53.8330993652],"type":"Point"}
}