{
  "type": "Feature",
  "properties": {
    "addr:full":"476 Boul Montpellier Saint-Laurent QC H4N 2G7",
    "addr:housenumber":"476",
    "addr:postcode":"h4n 2g7",
    "addr:street":"Boul Montpellier",
    "iso:country":"CA",
    "sg:address":"476 Boul Montpellier",
    "sg:city":"Saint-Laurent",
    "sg:classifiers":[
        {
            "category":"Wholesale",
            "subcategory":"Metals & Minerals",
            "type":"Manufacturing & Wholesale Goods"
        }
    ],
    "sg:phone":"+1 514 744 4000",
    "sg:postcode":"H4N 2G7",
    "sg:province":"QC",
    "sg:tags":[
        "specialty"
    ],
    "wof:name":"Aramky Impex Inc",
    "wof:placetype":"venue"
},
  "geometry": {"coordinates":[-73.66461200000001,45.51878],"type":"Point"}
}