{
  "type": "Feature",
  "properties": {
    "addr:full":"11302 Imperial Rd Aylmer ON N5H 2R3",
    "addr:housenumber":"11302",
    "addr:postcode":"n5h 2r3",
    "addr:street":"Imperial Rd",
    "iso:country":"CA",
    "sg:address":"11302 Imperial Rd",
    "sg:city":"Aylmer",
    "sg:classifiers":[
        {
            "category":"Wholesale",
            "subcategory":"Groceries",
            "type":"Manufacturing & Wholesale Goods"
        }
    ],
    "sg:phone":"+1 519 773 5503",
    "sg:postcode":"N5H 2R3",
    "sg:province":"ON",
    "sg:tags":[
        "honey"
    ],
    "wof:name":"Clovermead Apiaries",
    "wof:placetype":"venue"
},
  "geometry": {"coordinates":[-80.982468,42.79171],"type":"Point"}
}