{
  "type": "Feature",
  "properties": {
    "addr:full":"112 9E Av Iberville QC J2X 1J5",
    "addr:housenumber":"112",
    "addr:postcode":"j2x 1j5",
    "addr:street":"9E Av",
    "iso:country":"CA",
    "sg:address":"112 9E Av",
    "sg:city":"Iberville",
    "sg:classifiers":[
        {
            "category":"Professional",
            "subcategory":"Accounting & Tax Preparation",
            "type":"Services"
        }
    ],
    "sg:phone":"+1 450 358 4108",
    "sg:postcode":"J2X 1J5",
    "sg:province":"QC",
    "sg:tags":[
        "accountant"
    ],
    "wof:name":"Bouchard, Anne",
    "wof:placetype":"venue"
},
  "geometry": {"coordinates":[-73.24318700000001,45.309578],"type":"Point"}
}