{
  "type": "Feature",
  "properties": {
    "addr:full":"Temiscaming QC J0Z 3R0",
    "addr:postcode":"j0z 3r0",
    "iso:country":"CA",
    "sg:city":"Temiscaming",
    "sg:classifiers":[
        {
            "category":"Building & Trades",
            "subcategory":"Construction",
            "type":"Services"
        }
    ],
    "sg:phone":"+1 819 627 3478",
    "sg:postcode":"J0Z 3R0",
    "sg:province":"QC",
    "sg:tags":[
        "excavating",
        "contractor"
    ],
    "wof:name":"Equipment Roland Champoux",
    "wof:placetype":"venue"
},
  "geometry": {"coordinates":[-79.06409499999999,46.737106],"type":"Point"}
}