{
  "type": "Feature",
  "properties": {
    "iso:country":"CA",
    "sg:address":"1920 Huron St",
    "sg:city":"London",
    "sg:classifiers":[
        {
            "category":"Organizations",
            "subcategory":"Religious Organization",
            "type":"Services"
        }
    ],
    "sg:phone":"+1 519 452 3480",
    "sg:postcode":"N5V 3A7",
    "sg:province":"ON",
    "sg:tags":[
        "church"
    ],
    "wof:name":"Faith Tabernacle",
    "wof:placetype":"venue"
},
  "geometry": {"coordinates":[-81.185928,43.028549],"type":"Point"}
}