{
  "type": "Feature",
  "properties": {
    "addr:full":"156 Boul Henri-Bourassa O Montreal QC H3L 1N3",
    "addr:housenumber":"156",
    "addr:postcode":"h3l 1n3",
    "addr:street":"Boul Henri-Bourassa O",
    "iso:country":"CA",
    "sg:address":"156 Boul Henri-Bourassa O",
    "sg:city":"Montreal",
    "sg:classifiers":[
        {
            "category":"Retail",
            "subcategory":"Laundry & Dry Cleaning",
            "type":"Services"
        }
    ],
    "sg:phone":"+1 514 336 4848",
    "sg:postcode":"H3L 1N3",
    "sg:province":"QC",
    "sg:tags":[
        "cleaners"
    ],
    "wof:name":"Nettoyeur Anthony",
    "wof:placetype":"venue"
},
  "geometry": {"coordinates":[-73.669853,45.551617],"type":"Point"}
}