{
  "type": "Feature",
  "properties": {
    "iso:country":"CA",
    "sg:city":"Sainte-Foy",
    "sg:classifiers":[
        {
            "category":"Sports & Exercise",
            "subcategory":"Bowling",
            "type":"Entertainment"
        }
    ],
    "sg:phone":"+1 418 656 0588",
    "sg:postcode":"G1V 4T3",
    "sg:province":"QC",
    "sg:tags":[
        "center"
    ],
    "wof:name":"Salon DE Quilles Entrain",
    "wof:placetype":"venue"
},
  "geometry": {"coordinates":[-71.281059,46.771248],"type":"Point"}
}