{
  "type": "Feature",
  "properties": {
    "addr:full":"1398 Nicholson Rd Estevan SK S4A 1T5",
    "addr:housenumber":"1398",
    "addr:postcode":"s4a 1t5",
    "addr:street":"Nicholson Rd",
    "iso:country":"CA",
    "sg:address":"1398 Nicholson Rd",
    "sg:city":"Estevan",
    "sg:classifiers":[
        {
            "category":"Utilities",
            "subcategory":"Refuse",
            "type":"Services"
        }
    ],
    "sg:phone":"+1 306 634 2391",
    "sg:postcode":"S4A 1T5",
    "sg:province":"SK",
    "sg:tags":[
        "garbage",
        "collection"
    ],
    "wof:name":"Estevan Sanitation Svc Ltd",
    "wof:placetype":"venue"
},
  "geometry": {"coordinates":[-103.00256299999999,49.148834],"type":"Point"}
}