{
  "type": "Feature",
  "properties": {
    "addr:full":"Ville-Marie QC J9V 2B7",
    "addr:postcode":"j9v 2b7",
    "iso:country":"CA",
    "sg:city":"Ville-Marie",
    "sg:classifiers":[
        {
            "category":"Insurance",
            "subcategory":"Insurance Agent",
            "type":"Services"
        }
    ],
    "sg:phone":"+1 819 622 0308",
    "sg:postcode":"J9V 2B7",
    "sg:province":"QC",
    "sg:tags":[
        "consultant",
        "planning",
        "financial"
    ],
    "wof:name":"Dion & Dostie Inc",
    "wof:placetype":"venue"
},
  "geometry": {"coordinates":[-79.439163208,47.3310661316],"type":"Point"}
}