{
  "type": "Feature",
  "properties": {
    "addr:full":"Scarborough ON M1J 2L1",
    "addr:postcode":"m1j 2l1",
    "iso:country":"CA",
    "sg:city":"Scarborough",
    "sg:classifiers":[
        {
            "category":"Real Estate",
            "subcategory":"Real Estate Operator",
            "type":"Services"
        }
    ],
    "sg:phone":"+1 416 431 9101",
    "sg:postcode":"M1J 2L1",
    "sg:province":"ON",
    "sg:tags":[
        "apartment"
    ],
    "wof:name":"Bell'Am Apartments Ltd",
    "wof:placetype":"venue"
},
  "geometry": {"coordinates":[-79.231964,43.741882],"type":"Point"}
}