{
  "type": "Feature",
  "properties": {
    "addr:full":"2 Ch DE Montreal O Masson-Angers QC J8M 2E1",
    "addr:housenumber":"2",
    "addr:postcode":"j8m 2e1",
    "addr:street":"Ch De Montreal O",
    "iso:country":"CA",
    "sg:address":"2 Ch DE Montreal O",
    "sg:city":"Masson-Angers",
    "sg:classifiers":[
        {
            "category":"Manufacturing",
            "subcategory":"Paper Products",
            "type":"Manufacturing & Wholesale Goods"
        }
    ],
    "sg:phone":"+1 819 986 4300",
    "sg:postcode":"J8M 2E1",
    "sg:province":"QC",
    "wof:name":"Papier Masson Ltee",
    "wof:placetype":"venue"
},
  "geometry": {"coordinates":[-75.4188,45.5434],"type":"Point"}
}