{
  "type": "Feature",
  "properties": {
    "addr:full":"311 Sherk St Leamington ON N8H 3L2",
    "addr:housenumber":"311",
    "addr:postcode":"n8h 3l2",
    "addr:street":"Sherk St",
    "iso:country":"CA",
    "sg:address":"311 Sherk St",
    "sg:city":"Leamington",
    "sg:classifiers":[
        {
            "category":"Organizations",
            "subcategory":"Religious Organization",
            "type":"Services"
        }
    ],
    "sg:phone":"+1 519 326 3966",
    "sg:postcode":"N8H 3L2",
    "sg:province":"ON",
    "sg:tags":[
        "church"
    ],
    "wof:name":"St Paul's Lutheran Church",
    "wof:placetype":"venue"
},
  "geometry": {"coordinates":[-82.60600280760001,42.0350494385],"type":"Point"}
}