{
  "type": "Feature",
  "properties": {
    "addr:full":"284 Foord St Stellarton NS B0K 1S0",
    "addr:housenumber":"284",
    "addr:postcode":"b0k 1s0",
    "addr:street":"Foord St",
    "iso:country":"CA",
    "sg:address":"284 Foord St",
    "sg:city":"Stellarton",
    "sg:classifiers":[
        {
            "category":"Shopping",
            "subcategory":"Clothing, Apparel, & Fashions",
            "type":"Retail Goods"
        }
    ],
    "sg:phone":"+1 902 752 7341",
    "sg:postcode":"B0K 1S0",
    "sg:province":"NS",
    "sg:tags":[
        "knit"
    ],
    "wof:name":"Rare Knits Ltd",
    "wof:placetype":"venue"
},
  "geometry": {"coordinates":[-62.6604232788,45.5573501587],"type":"Point"}
}