{
  "type": "Feature",
  "properties": {
    "addr:full":"4800 Rue DE Rouen Montreal QC H1V 3T4",
    "addr:housenumber":"4800",
    "addr:postcode":"h1v 3t4",
    "addr:street":"Rue De Rouen",
    "iso:country":"CA",
    "sg:address":"4800 Rue DE Rouen",
    "sg:city":"Montreal",
    "sg:classifiers":[
        {
            "category":"Manufacturing",
            "subcategory":"Furniture",
            "type":"Manufacturing & Wholesale Goods"
        }
    ],
    "sg:phone":"+1 514 256 5557",
    "sg:postcode":"H1V 3T4",
    "sg:province":"QC",
    "wof:name":"Bureaux D'Antoine",
    "wof:placetype":"venue"
},
  "geometry": {"coordinates":[-73.540207,45.558285],"type":"Point"}
}