{
  "type": "Feature",
  "properties": {
    "addr:full":"810 Kingsway Vancouver BC V5V 3C3",
    "addr:housenumber":"810",
    "addr:postcode":"v5v 3c3",
    "addr:street":"Kingsway",
    "iso:country":"CA",
    "sg:address":"810 Kingsway",
    "sg:city":"Vancouver",
    "sg:classifiers":[
        {
            "category":"Home & Garden",
            "subcategory":"Carpets & Floor Coverings",
            "type":"Retail Goods"
        }
    ],
    "sg:phone":"+1 604 879 5788",
    "sg:postcode":"V5V 3C3",
    "sg:province":"BC",
    "sg:tags":[
        "dealer",
        "rug"
    ],
    "wof:name":"Sammy's Carpets",
    "wof:placetype":"venue"
},
  "geometry": {"coordinates":[-123.087166,49.255302],"type":"Point"}
}