{
  "type": "Feature",
  "properties": {
    "addr:full":"6 Wicklow Dr Scarborough ON M1T 1R5",
    "addr:housenumber":"6",
    "addr:postcode":"m1t 1r5",
    "addr:street":"Wicklow Dr",
    "iso:country":"CA",
    "sg:address":"6 Wicklow Dr",
    "sg:city":"Scarborough",
    "sg:classifiers":[
        {
            "category":"Building & Trades",
            "subcategory":"Construction",
            "type":"Services"
        }
    ],
    "sg:phone":"+1 416 498 8882",
    "sg:postcode":"M1T 1R5",
    "sg:province":"ON",
    "sg:tags":[
        "general",
        "contractor"
    ],
    "wof:name":"Interior Plus Ltd",
    "wof:placetype":"venue"
},
  "geometry": {"coordinates":[-79.3151092529,43.7790985107],"type":"Point"}
}