{
  "type": "Feature",
  "properties": {
    "iso:country":"CA",
    "sg:address":"6 Wicklow Dr",
    "sg:city":"Scarborough",
    "sg:classifiers":[
        {
            "category":"Building & Trades",
            "subcategory":"Construction",
            "type":"Services"
        }
    ],
    "sg:phone":"+1 416 498 8882",
    "sg:postcode":"M1T 1R5",
    "sg:province":"ON",
    "sg:tags":[
        "general",
        "contractor"
    ],
    "wof:name":"Interior Plus Ltd",
    "wof:placetype":"venue"
},
  "geometry": {"coordinates":[-79.3151092529,43.7790985107],"type":"Point"}
}