{
  "type": "Feature",
  "properties": {
    "addr:full":"Barrie ON L4M 6H1",
    "addr:postcode":"l4m 6h1",
    "iso:country":"CA",
    "sg:city":"Barrie",
    "sg:classifiers":[
        {
            "category":"Professional",
            "subcategory":"Lawyer & Legal Services",
            "type":"Services"
        }
    ],
    "sg:phone":"+1 705 721 6642",
    "sg:postcode":"L4M 6H1",
    "sg:province":"ON",
    "sg:tags":[
        "attorney"
    ],
    "wof:name":"Wilcox, David A",
    "wof:placetype":"venue"
},
  "geometry": {"coordinates":[-79.683921814,44.3894729614],"type":"Point"}
}