{
  "type": "Feature",
  "properties": {
    "addr:full":"45 Blackmarsh Rd St. John's NL A1E 1S6",
    "addr:housenumber":"45",
    "addr:postcode":"a1e 1s6",
    "addr:street":"Blackmarsh Rd",
    "iso:country":"CA",
    "sg:address":"45 Blackmarsh Rd",
    "sg:city":"St. John's",
    "sg:classifiers":[
        {
            "category":"Manufacturing",
            "subcategory":"Printing",
            "type":"Manufacturing & Wholesale Goods"
        }
    ],
    "sg:phone":"+1 709 722 7720",
    "sg:postcode":"A1E 1S6",
    "sg:province":"NL",
    "sg:tags":[
        "newspaper"
    ],
    "wof:name":"Globe & Mail",
    "wof:placetype":"venue"
},
  "geometry": {"coordinates":[-52.7296867371,47.552028656],"type":"Point"}
}