{
  "type": "Feature",
  "properties": {
    "addr:full":"1201 Main Humboldt SK S0K 2A0",
    "addr:housenumber":"1201",
    "addr:postcode":"s0k 2a0",
    "addr:street":"Main Humboldt",
    "iso:country":"CA",
    "sg:address":"1201 Main",
    "sg:city":"Humboldt",
    "sg:classifiers":[
        {
            "category":"Government",
            "subcategory":"Office",
            "type":"Public Place"
        }
    ],
    "sg:phone":"+1 306 682 2565",
    "sg:postcode":"S0K 2A0",
    "sg:province":"SK",
    "sg:tags":[
        "village"
    ],
    "wof:name":"Humboldt Water Treatment Plant",
    "wof:placetype":"venue"
},
  "geometry": {"coordinates":[-105.12293243400001,52.2018890381],"type":"Point"}
}