{
  "type": "Feature",
  "properties": {
    "addr:full":"3354 Lake Shore Blvd W Etobicoke ON M8W 1M9",
    "addr:housenumber":"3354",
    "addr:postcode":"m8w 1m9",
    "addr:street":"Lake Shore Blvd W",
    "iso:country":"CA",
    "sg:address":"3354 Lake Shore Blvd W",
    "sg:city":"Etobicoke",
    "sg:classifiers":[
        {
            "category":"Shopping",
            "subcategory":"Discount & Variety Stores",
            "type":"Retail Goods"
        }
    ],
    "sg:phone":"+1 416 503 0761",
    "sg:postcode":"M8W 1M9",
    "sg:province":"ON",
    "wof:name":"Matadeen Trading Inc",
    "wof:placetype":"venue"
},
  "geometry": {"coordinates":[-79.526146,43.596287],"type":"Point"}
}