{
  "type": "Feature",
  "properties": {
    "addr:full":"7750 Yellowhead Trail NW Edmonton AB T5B 1G3",
    "addr:housenumber":"7750",
    "addr:postcode":"t5b 1g3",
    "addr:street":"Yellowhead Trail Nw",
    "iso:country":"CA",
    "sg:address":"7750 Yellowhead Trail NW",
    "sg:city":"Edmonton",
    "sg:classifiers":[
        {
            "category":"Retail",
            "subcategory":"Auto Repair",
            "type":"Services"
        }
    ],
    "sg:phone":"+1 780 471 2295",
    "sg:postcode":"T5B 1G3",
    "sg:province":"AB",
    "sg:tags":[
        "body",
        "automobile",
        "painting"
    ],
    "wof:name":"Stedelbauer Chevrolet Olds Ltd",
    "wof:placetype":"venue"
},
  "geometry": {"coordinates":[-113.460220337,53.5827522278],"type":"Point"}
}