{
  "type": "Feature",
  "properties": {
    "iso:country":"CA",
    "sg:address":"29 Toronto St S",
    "sg:city":"Uxbridge",
    "sg:classifiers":[
        {
            "category":"Health Services",
            "subcategory":"Doctor",
            "type":"Services"
        }
    ],
    "sg:phone":"+1 905 852 6101",
    "sg:postcode":"L9P 1V9",
    "sg:province":"ON",
    "sg:tags":[
        "physician",
        "surgeon"
    ],
    "wof:name":"Toronto Street Medical Ctr",
    "wof:placetype":"venue"
},
  "geometry": {"coordinates":[-79.122757,44.107738],"type":"Point"}
}