{
  "type": "Feature",
  "properties": {
    "addr:full":"Woodstock ON N4S 8X6",
    "addr:postcode":"n4s 8x6",
    "iso:country":"CA",
    "sg:city":"Woodstock",
    "sg:classifiers":[
        {
            "category":"Shopping",
            "subcategory":"Discount & Variety Stores",
            "type":"Retail Goods"
        }
    ],
    "sg:phone":"+1 519 536 9961",
    "sg:postcode":"N4S 8X6",
    "sg:province":"ON",
    "wof:name":"Ken's Mini Mart & Video",
    "wof:placetype":"venue"
},
  "geometry": {"coordinates":[-80.736046,43.132938],"type":"Point"}
}