{
  "type": "Feature",
  "properties": {
    "addr:full":"1381 Rang Saint-Philippe Saint-Polycarpe QC J0P 1X0",
    "addr:housenumber":"1381",
    "addr:postcode":"j0p 1x0",
    "addr:street":"Rang Saint-Philippe",
    "iso:country":"CA",
    "sg:address":"1381 Rang Saint-Philippe",
    "sg:city":"Saint-Polycarpe",
    "sg:classifiers":[
        {
            "category":"Retail",
            "subcategory":"Auto Repair",
            "type":"Services"
        }
    ],
    "sg:phone":"+1 450 265 3452",
    "sg:postcode":"J0P 1X0",
    "sg:province":"QC",
    "sg:tags":[
        "repairing",
        "automobile"
    ],
    "wof:name":"Garage Germain Leroux",
    "wof:placetype":"venue"
},
  "geometry": {"coordinates":[-74.33168000000001,45.259029],"type":"Point"}
}