{
  "type": "Feature",
  "properties": {
    "addr:full":"112 Rue Mcgill # 200 Montreal QC H2Y 2E5",
    "addr:housenumber":"112",
    "addr:postcode":"h2y 2e5",
    "addr:street":"Rue Mcgill # 200",
    "iso:country":"CA",
    "sg:address":"112 Rue Mcgill # 200",
    "sg:city":"Montreal",
    "sg:classifiers":[
        {
            "category":"Freight",
            "type":"Transportation"
        }
    ],
    "sg:phone":"+1 514 876 1704",
    "sg:postcode":"H2Y 2E5",
    "sg:province":"QC",
    "sg:tags":[
        "broker",
        "customs"
    ],
    "wof:name":"Courtiers En Douanes General",
    "wof:placetype":"venue"
},
  "geometry": {"coordinates":[-73.55522155760001,45.4993896484],"type":"Point"}
}