{
  "type": "Feature",
  "properties": {
    "addr:full":"997 Rue Panneton L'Ancienne-Lorette QC G2E 5G4",
    "addr:housenumber":"997",
    "addr:postcode":"g2e 5g4",
    "addr:street":"Rue Panneton",
    "iso:country":"CA",
    "sg:address":"997 Rue Panneton",
    "sg:city":"L'Ancienne-Lorette",
    "sg:classifiers":[
        {
            "category":"Professional",
            "subcategory":"Business Services",
            "type":"Services"
        }
    ],
    "sg:phone":"+1 418 872 2929",
    "sg:postcode":"G2E 5G4",
    "sg:province":"QC",
    "sg:tags":[
        "arbitration"
    ],
    "wof:name":"Nadeau, Ginette",
    "wof:placetype":"venue"
},
  "geometry": {"coordinates":[-71.3536605835,46.8129920959],"type":"Point"}
}