{
  "type": "Feature",
  "properties": {
    "addr:full":"Burnaby BC V5H 4J7",
    "addr:postcode":"v5h 4j7",
    "iso:country":"CA",
    "sg:city":"Burnaby",
    "sg:classifiers":[
        {
            "category":"Professional",
            "subcategory":"Lawyer & Legal Services",
            "type":"Services"
        }
    ],
    "sg:phone":"+1 604 431 8368",
    "sg:postcode":"V5H 4J7",
    "sg:province":"BC",
    "sg:tags":[
        "attorney"
    ],
    "wof:name":"Chee & Dusevic",
    "wof:placetype":"venue"
},
  "geometry": {"coordinates":[-123.007126,49.230106],"type":"Point"}
}