{
  "type": "Feature",
  "properties": {
    "addr:full":"341 Rue Charles-Gill Laval QC H7N 1C1",
    "addr:housenumber":"341",
    "addr:postcode":"h7n 1c1",
    "addr:street":"Rue Charles-Gill",
    "iso:country":"CA",
    "sg:address":"341 Rue Charles-Gill",
    "sg:city":"Laval",
    "sg:classifiers":[
        {
            "category":"Professional",
            "subcategory":"Secretarial Services",
            "type":"Services"
        }
    ],
    "sg:phone":"+1 450 669 8528",
    "sg:postcode":"H7N 1C1",
    "sg:province":"QC",
    "sg:tags":[
        "reporting",
        "court"
    ],
    "wof:name":"Bras Droit Svc Administratifs",
    "wof:placetype":"venue"
},
  "geometry": {"coordinates":[-73.71825408940001,45.5627593994],"type":"Point"}
}