{
  "type": "Feature",
  "properties": {
    "iso:country":"CA",
    "sg:address":"13506 127 St NW",
    "sg:city":"Edmonton",
    "sg:classifiers":[
        {
            "category":"Health Services",
            "subcategory":"Doctor",
            "type":"Services"
        }
    ],
    "sg:phone":"+1 780 454 0738",
    "sg:postcode":"T5L 1B9",
    "sg:province":"AB",
    "sg:tags":[
        "physician",
        "surgeon"
    ],
    "wof:name":"Princeton Medical Clinic",
    "wof:placetype":"venue"
},
  "geometry": {"coordinates":[-113.54126739500001,53.5967178345],"type":"Point"}
}