{
  "type": "Feature",
  "properties": {
    "addr:full":"2262 Rue Saint-Dominique Jonquiere QC G7X 6M3",
    "addr:housenumber":"2262",
    "addr:postcode":"g7x 6m3",
    "addr:street":"Rue Saint-Dominique",
    "iso:country":"CA",
    "sg:address":"2262 Rue Saint-Dominique",
    "sg:city":"Jonquiere",
    "sg:classifiers":[
        {
            "category":"Retail",
            "subcategory":"Auto Repair",
            "type":"Services"
        }
    ],
    "sg:phone":"+1 418 547 4143",
    "sg:postcode":"G7X 6M3",
    "sg:province":"QC",
    "sg:tags":[
        "repairing",
        "automobile"
    ],
    "wof:name":"Station DE Svc Gl Inc",
    "wof:placetype":"venue"
},
  "geometry": {"coordinates":[-71.2528915405,48.4162025452],"type":"Point"}
}