{
  "type": "Feature",
  "properties": {
    "addr:full":"157 Water St Shelburne NS B0T 1W0",
    "addr:housenumber":"157",
    "addr:postcode":"b0t 1w0",
    "addr:street":"Water St",
    "iso:country":"CA",
    "sg:address":"157 Water St",
    "sg:city":"Shelburne",
    "sg:classifiers":[
        {
            "category":"Professional",
            "subcategory":"Management & Consulting",
            "type":"Services"
        }
    ],
    "sg:phone":"+1 902 875 1133",
    "sg:postcode":"B0T 1W0",
    "sg:province":"NS",
    "sg:tags":[
        "consultant",
        "financing",
        "business"
    ],
    "wof:name":"Shelburne County Business Dev",
    "wof:placetype":"venue"
},
  "geometry": {"coordinates":[-65.3235321045,43.7632598877],"type":"Point"}
}