{
  "type": "Feature",
  "properties": {
    "addr:full":"73 Main Blvd Sherwood Park AB T8A 0R1",
    "addr:housenumber":"73",
    "addr:postcode":"t8a 0r1",
    "addr:street":"Main Blvd",
    "iso:country":"CA",
    "sg:address":"73 Main Blvd",
    "sg:city":"Sherwood Park",
    "sg:classifiers":[
        {
            "category":"Education",
            "subcategory":"School",
            "type":"Public Place"
        }
    ],
    "sg:phone":"+1 780 467 5556",
    "sg:postcode":"T8A 0R1",
    "sg:province":"AB",
    "wof:name":"Mills Haven School",
    "wof:placetype":"venue"
},
  "geometry": {"coordinates":[-113.306107,53.536808],"type":"Point"}
}