{
  "type": "Feature",
  "properties": {
    "addr:full":"4509 25 Ave Vernon BC V1T 1P5",
    "addr:housenumber":"4509",
    "addr:postcode":"v1t 1p5",
    "addr:street":"25 Ave",
    "iso:country":"CA",
    "sg:address":"4509 25 Ave",
    "sg:city":"Vernon",
    "sg:classifiers":[
        {
            "category":"Manufacturing",
            "subcategory":"Glass & Minerals",
            "type":"Manufacturing & Wholesale Goods"
        }
    ],
    "sg:phone":"+1 250 545 9108",
    "sg:postcode":"V1T 1P5",
    "sg:province":"BC",
    "sg:tags":[
        "concrete",
        "brick",
        "block",
        "contractor"
    ],
    "wof:name":"Farrer Enterprises Ltd",
    "wof:placetype":"venue"
},
  "geometry": {"coordinates":[-119.29953,50.258598],"type":"Point"}
}