{
  "type": "Feature",
  "properties": {
    "addr:full":"5444 6E Av Montreal QC H1Y 2P8",
    "addr:housenumber":"5444",
    "addr:postcode":"h1y 2p8",
    "addr:street":"6E Av",
    "iso:country":"CA",
    "sg:address":"5444 6E Av",
    "sg:city":"Montreal",
    "sg:classifiers":[
        {
            "category":"Organizations",
            "subcategory":"Professional Association",
            "type":"Services"
        }
    ],
    "sg:phone":"+1 514 725 2833",
    "sg:postcode":"H1Y 2P8",
    "sg:province":"QC",
    "wof:name":"Vestiaire St Esprit",
    "wof:placetype":"venue"
},
  "geometry": {"coordinates":[-73.575829,45.548264],"type":"Point"}
}