{
  "type": "Feature",
  "properties": {
    "addr:full":"Edmonton AB T6C 3C5",
    "addr:postcode":"t6c 3c5",
    "iso:country":"CA",
    "sg:city":"Edmonton",
    "sg:classifiers":[
        {
            "category":"Restaurant",
            "type":"Food & Drink"
        }
    ],
    "sg:phone":"+1 780 469 1819",
    "sg:postcode":"T6C 3C5",
    "sg:province":"AB",
    "wof:name":"China Kitchen",
    "wof:placetype":"venue"
},
  "geometry": {"coordinates":[-113.458023071,53.525604248],"type":"Point"}
}