{
  "type": "Feature",
  "properties": {
    "iso:country":"CA",
    "sg:address":"156 Rue Jean-Talon E",
    "sg:city":"Montreal",
    "sg:classifiers":[
        {
            "category":"Shopping",
            "subcategory":"Clothing, Apparel, & Fashions",
            "type":"Retail Goods"
        }
    ],
    "sg:phone":"+1 514 272 2637",
    "sg:postcode":"H2R 1S7",
    "sg:province":"QC",
    "sg:tags":[
        "tailor"
    ],
    "wof:name":"F Gerome & Fils Enrg",
    "wof:placetype":"venue"
},
  "geometry": {"coordinates":[-73.61655426030001,45.5358123779],"type":"Point"}
}