{
  "type": "Feature",
  "properties": {
    "addr:full":"Gaspe QC G4X 5M4",
    "addr:postcode":"g4x 5m4",
    "iso:country":"CA",
    "sg:city":"Gaspe",
    "sg:classifiers":[
        {
            "category":"Shopping",
            "subcategory":"Catalog Store",
            "type":"Retail Goods"
        }
    ],
    "sg:phone":"+1 418 269 3363",
    "sg:postcode":"G4X 5M4",
    "sg:province":"QC",
    "sg:tags":[
        "mail",
        "order",
        "internet"
    ],
    "wof:name":"Sears Canada Inc",
    "wof:placetype":"venue"
},
  "geometry": {"coordinates":[-64.40753173829999,48.9923019409],"type":"Point"}
}