{
  "type": "Feature",
  "properties": {
    "addr:full":"9330 Boul Saint-Laurent Montreal QC H2N 1N3",
    "addr:housenumber":"9330",
    "addr:postcode":"h2n 1n3",
    "addr:street":"Boul Saint-Laurent",
    "iso:country":"CA",
    "sg:address":"9330 Boul Saint-Laurent",
    "sg:city":"Montreal",
    "sg:classifiers":[
        {
            "category":"Shopping",
            "subcategory":"Clothing, Apparel, & Fashions",
            "type":"Retail Goods"
        }
    ],
    "sg:phone":"+1 514 382 7040",
    "sg:postcode":"H2N 1N3",
    "sg:province":"QC",
    "sg:tags":[
        "sportswear"
    ],
    "wof:name":"Fabuleux Fb Vetements DE Sprt",
    "wof:placetype":"venue"
},
  "geometry": {"coordinates":[-73.6518707275,45.5445213318],"type":"Point"}
}