{
  "type": "Feature",
  "properties": {
    "addr:full":"13964 Stoney Flats Buick BC V0C 2R0",
    "addr:housenumber":"13964",
    "addr:postcode":"bc v0c 2r0",
    "addr:street":"Stoney Flats",
    "iso:country":"CA",
    "sg:address":"13964 Stoney Flats",
    "sg:city":"Buick",
    "sg:classifiers":[
        {
            "category":"Education",
            "subcategory":"School",
            "type":"Public Place"
        }
    ],
    "sg:phone":"+1 250 630 2307",
    "sg:postcode":"V0C 2R0",
    "sg:province":"BC",
    "wof:name":"Blueberry Indian Band School",
    "wof:placetype":"venue"
},
  "geometry": {"coordinates":[-121.27456665,56.7601966858],"type":"Point"}
}