{
  "type": "Feature",
  "properties": {
    "addr:full":"PO Box 2082 STN Sardis Main Chilliwack BC V2R 1A5",
    "addr:housenumber":"po",
    "addr:postcode":"v2r 1a5",
    "addr:street":"Box 2082 Stn Sardis Main",
    "iso:country":"CA",
    "sg:address":"PO Box 2082 STN Sardis Main",
    "sg:city":"Chilliwack",
    "sg:classifiers":[
        {
            "category":"Building & Trades",
            "subcategory":"Landscaping Services",
            "type":"Services"
        }
    ],
    "sg:phone":"+1 604 858 9376",
    "sg:postcode":"V2R 1A5",
    "sg:province":"BC",
    "sg:tags":[
        "tree",
        "landscape",
        "contractor"
    ],
    "wof:name":"Joe Skillen Tree Topping",
    "wof:placetype":"venue"
},
  "geometry": {"coordinates":[-121.951499939,49.1563186646],"type":"Point"}
}