{
  "type": "Feature",
  "properties": {
    "addr:full":"1065 Roy Ave Cornwall ON K6H 4C2",
    "addr:housenumber":"1065",
    "addr:postcode":"k6h 4c2",
    "addr:street":"Roy Ave",
    "iso:country":"CA",
    "sg:address":"1065 Roy Ave",
    "sg:city":"Cornwall",
    "sg:classifiers":[
        {
            "category":"Wholesale",
            "subcategory":"Stationery",
            "type":"Manufacturing & Wholesale Goods"
        }
    ],
    "sg:phone":"+1 613 936 1852",
    "sg:postcode":"K6H 4C2",
    "sg:province":"ON",
    "sg:tags":[
        "business",
        "form",
        "system"
    ],
    "wof:name":"Versus Business Forms",
    "wof:placetype":"venue"
},
  "geometry": {"coordinates":[-74.728645,45.03299],"type":"Point"}
}