{
  "type": "Feature",
  "properties": {
    "addr:full":"4179 Fraser St Vancouver BC V5V 4E9",
    "addr:housenumber":"4179",
    "addr:postcode":"v5v 4e9",
    "addr:street":"Fraser St",
    "iso:country":"CA",
    "sg:address":"4179 Fraser St",
    "sg:city":"Vancouver",
    "sg:classifiers":[
        {
            "category":"Manufacturing",
            "subcategory":"Printing",
            "type":"Manufacturing & Wholesale Goods"
        }
    ],
    "sg:phone":"+1 604 873 4008",
    "sg:postcode":"V5V 4E9",
    "sg:province":"BC",
    "sg:tags":[
        "printer"
    ],
    "wof:name":"Century Printing Ltd",
    "wof:placetype":"venue"
},
  "geometry": {"coordinates":[-123.09028600000001,49.247902],"type":"Point"}
}