{
  "type": "Feature",
  "properties": {
    "addr:full":"6302 Main St Stouffville ON L4A 1G8",
    "addr:housenumber":"6302",
    "addr:postcode":"l4a 1g8",
    "addr:street":"Main St",
    "iso:country":"CA",
    "sg:address":"6302 Main St",
    "sg:city":"Stouffville",
    "sg:classifiers":[
        {
            "category":"Restaurant",
            "type":"Food & Drink"
        }
    ],
    "sg:phone":"+1 905 640 5707",
    "sg:postcode":"L4A 1G8",
    "sg:province":"ON",
    "wof:name":"Fickle Pickle Restaurants",
    "wof:placetype":"venue"
},
  "geometry": {"coordinates":[-79.245811,43.971661],"type":"Point"}
}