{
  "type": "Feature",
  "properties": {
    "iso:country":"CA",
    "sg:address":"347 Wharncliffe Rd S",
    "sg:city":"London",
    "sg:classifiers":[
        {
            "category":"Retail",
            "subcategory":"Auto Repair",
            "type":"Services"
        }
    ],
    "sg:phone":"+1 519 433 8331",
    "sg:postcode":"N6J 2L9",
    "sg:province":"ON",
    "sg:tags":[
        "brake"
    ],
    "wof:name":"Sure Stop Brake Ctr",
    "wof:placetype":"venue"
},
  "geometry": {"coordinates":[-81.261665,42.965607],"type":"Point"}
}