{
  "type": "Feature",
  "properties": {
    "addr:full":"347 Wharncliffe Rd S London ON N6J 2L9",
    "addr:housenumber":"347",
    "addr:postcode":"n6j 2l9",
    "addr:street":"Wharncliffe Rd",
    "iso:country":"CA",
    "sg:address":"347 Wharncliffe Rd S",
    "sg:city":"London",
    "sg:classifiers":[
        {
            "category":"Retail",
            "subcategory":"Auto Repair",
            "type":"Services"
        }
    ],
    "sg:phone":"+1 519 433 8331",
    "sg:postcode":"N6J 2L9",
    "sg:province":"ON",
    "sg:tags":[
        "brake"
    ],
    "wof:name":"Sure Stop Brake Ctr",
    "wof:placetype":"venue"
},
  "geometry": {"coordinates":[-81.26166499999999,42.965607],"type":"Point"}
}