{
  "type": "Feature",
  "properties": {
    "addr:full":"2901 Grandview St Windsor ON N8T 2L5",
    "addr:housenumber":"2901",
    "addr:postcode":"n8t 2l5",
    "addr:street":"Grandview St",
    "iso:country":"CA",
    "sg:address":"2901 Grandview St",
    "sg:city":"Windsor",
    "sg:classifiers":[
        {
            "category":"Shopping",
            "subcategory":"Pharmacy",
            "type":"Retail Goods"
        }
    ],
    "sg:phone":"+1 519 948 1422",
    "sg:postcode":"N8T 2L5",
    "sg:province":"ON",
    "wof:name":"Fontainebleu Pharmacy",
    "wof:placetype":"venue"
},
  "geometry": {"coordinates":[-82.95249200000001,42.297771],"type":"Point"}
}