{
  "type": "Feature",
  "properties": {
    "addr:full":"170 Main St Ailsa Craig ON N0M 1A0",
    "addr:housenumber":"170",
    "addr:postcode":"n0m 1a0",
    "addr:street":"Main St",
    "iso:country":"CA",
    "sg:address":"170 Main St",
    "sg:city":"Ailsa Craig",
    "sg:classifiers":[
        {
            "category":"Insurance",
            "subcategory":"Insurance Agent",
            "type":"Services"
        }
    ],
    "sg:phone":"+1 519 293 3295",
    "sg:postcode":"N0M 1A0",
    "sg:province":"ON",
    "wof:name":"Woods Hodgins Insurance Broker",
    "wof:placetype":"venue"
},
  "geometry": {"coordinates":[-81.534302,43.147285],"type":"Point"}
}