{
  "type": "Feature",
  "properties": {
    "addr:full":"279 Grosvenor Ave N Hamilton ON L8L 7T2",
    "addr:housenumber":"279",
    "addr:postcode":"l8l 7t2",
    "addr:street":"Grosvenor Ave N",
    "iso:country":"CA",
    "sg:address":"279 Grosvenor Ave N",
    "sg:city":"Hamilton",
    "sg:classifiers":[
        {
            "category":"Organizations",
            "subcategory":"Religious Organization",
            "type":"Services"
        }
    ],
    "sg:phone":"+1 905 547 1169",
    "sg:postcode":"L8L 7T2",
    "sg:province":"ON",
    "sg:tags":[
        "church"
    ],
    "wof:name":"Templo Neuva Vida",
    "wof:placetype":"venue"
},
  "geometry": {"coordinates":[-79.817993,43.250278],"type":"Point"}
}