{
  "type": "Feature",
  "properties": {
    "addr:full":"74 Railside Rd North York ON M3A 1A3",
    "addr:housenumber":"74",
    "addr:postcode":"m3a 1a3",
    "addr:street":"Railside Rd",
    "iso:country":"CA",
    "sg:address":"74 Railside Rd",
    "sg:city":"North York",
    "sg:classifiers":[
        {
            "category":"Recreation",
            "type":"Entertainment"
        }
    ],
    "sg:phone":"+1 416 446 0777",
    "sg:postcode":"M3A 1A3",
    "sg:province":"ON",
    "sg:tags":[
        "center"
    ],
    "wof:name":"North Beach Indoor Volleyball",
    "wof:placetype":"venue"
},
  "geometry": {"coordinates":[-79.3231582642,43.7373275757],"type":"Point"}
}