{
  "type": "Feature",
  "properties": {
    "addr:full":"Calgary AB T2P 3H3",
    "addr:postcode":"t2p 3h3",
    "iso:country":"CA",
    "sg:city":"Calgary",
    "sg:classifiers":[
        {
            "category":"Real Estate",
            "subcategory":"Real Estate Agent",
            "type":"Services"
        }
    ],
    "sg:phone":"+1 403 514 6000",
    "sg:postcode":"T2P 3H3",
    "sg:province":"AB",
    "sg:tags":[
        "management"
    ],
    "wof:name":"Bentall Real Estate Svc",
    "wof:placetype":"venue"
},
  "geometry": {"coordinates":[-114.068435669,51.0474433899],"type":"Point"}
}