{
  "type": "Feature",
  "properties": {
    "addr:full":"1657 Av Saint-Louis Plessisville QC G6L 2N1",
    "addr:housenumber":"1657",
    "addr:postcode":"g6l 2n1",
    "addr:street":"Av Saint-Louis",
    "iso:country":"CA",
    "sg:address":"1657 Av Saint-Louis",
    "sg:city":"Plessisville",
    "sg:classifiers":[
        {
            "category":"Organizations",
            "subcategory":"Professional Association",
            "type":"Services"
        }
    ],
    "sg:phone":"+1 819 362 0001",
    "sg:postcode":"G6L 2N1",
    "sg:province":"QC",
    "wof:name":"Organisme DE Recuperation Des",
    "wof:placetype":"venue"
},
  "geometry": {"coordinates":[-71.77295684809999,46.2205162048],"type":"Point"}
}