{
  "type": "Feature",
  "properties": {
    "addr:full":"PO Box 4 St Lina AB T0A 2Z0",
    "addr:housenumber":"po;4",
    "addr:postcode":"t0a 2z0",
    "addr:street":"Box",
    "iso:country":"CA",
    "sg:address":"PO Box 4",
    "sg:city":"St Lina",
    "sg:classifiers":[
        {
            "category":"Building & Trades",
            "subcategory":"Construction",
            "type":"Services"
        }
    ],
    "sg:phone":"+1 780 726 2125",
    "sg:postcode":"T0A 2Z0",
    "sg:province":"AB",
    "sg:tags":[
        "water",
        "boring",
        "well",
        "drilling",
        "contractor"
    ],
    "wof:name":"Chorney Water Well Drill Ltd",
    "wof:placetype":"venue"
},
  "geometry": {"coordinates":[-111.479675,54.267761],"type":"Point"}
}