{
  "type": "Feature",
  "properties": {
    "addr:full":"Victoria BC V8W 3B9",
    "addr:postcode":"v8w 3b9",
    "iso:country":"CA",
    "sg:city":"Victoria",
    "sg:classifiers":[
        {
            "category":"Professional",
            "subcategory":"Accounting & Tax Preparation",
            "type":"Services"
        }
    ],
    "sg:phone":"+1 250 386 1115",
    "sg:postcode":"V8W 3B9",
    "sg:province":"BC",
    "sg:tags":[
        "accountant"
    ],
    "wof:name":"Oye, Brandon CA",
    "wof:placetype":"venue"
},
  "geometry": {"coordinates":[-123.370255,48.426117],"type":"Point"}
}