{
  "type": "Feature",
  "properties": {
    "addr:full":"Trois-Lacs QC J1T 3M7",
    "addr:postcode":"j1t 3m7",
    "iso:country":"CA",
    "sg:city":"Trois-Lacs",
    "sg:classifiers":[
        {
            "category":"Recreation",
            "type":"Entertainment"
        }
    ],
    "sg:phone":"+1 819 879 2215",
    "sg:postcode":"J1T 3M7",
    "sg:province":"QC",
    "sg:tags":[
        "hall",
        "auditorium"
    ],
    "wof:name":"Buffet Trois Lacs",
    "wof:placetype":"venue"
},
  "geometry": {"coordinates":[-71.914185,45.801113],"type":"Point"}
}