{
  "type": "Feature",
  "properties": {
    "addr:full":"2801 Boul Des Promenades Sainte-Marthe-Sur-Le-Lac QC J0N 1P0",
    "addr:housenumber":"2801",
    "addr:postcode":"j0n 1p0",
    "addr:street":"Boul Des Promenades",
    "iso:country":"CA",
    "sg:address":"2801 Boul Des Promenades",
    "sg:city":"Sainte-Marthe-Sur-Le-Lac",
    "sg:classifiers":[
        {
            "category":"Shopping",
            "subcategory":"Pharmacy",
            "type":"Retail Goods"
        }
    ],
    "sg:phone":"+1 450 974 7777",
    "sg:postcode":"J0N 1P0",
    "sg:province":"QC",
    "wof:name":"Pharmacie Associee A Uniprix",
    "wof:placetype":"venue"
},
  "geometry": {"coordinates":[-73.932365,45.529251],"type":"Point"}
}