{
  "type": "Feature",
  "properties": {
    "addr:full":"30 Main St N Elm Creek MB R0G 0N0",
    "addr:housenumber":"30",
    "addr:postcode":"r0g 0n0",
    "addr:street":"Main St N",
    "iso:country":"CA",
    "sg:address":"30 Main St N",
    "sg:city":"Elm Creek",
    "sg:classifiers":[
        {
            "category":"Banks & Credit Unions",
            "subcategory":"Bank",
            "type":"Services"
        }
    ],
    "sg:phone":"+1 204 436 2246",
    "sg:postcode":"R0G 0N0",
    "sg:province":"MB",
    "wof:name":"Cibc",
    "wof:placetype":"venue"
},
  "geometry": {"coordinates":[-97.993042,49.675564],"type":"Point"}
}