{
  "type": "Feature",
  "properties": {
    "iso:country":"CA",
    "sg:address":"510 Park Ave",
    "sg:city":"Moosomin",
    "sg:classifiers":[
        {
            "category":"Home & Garden",
            "subcategory":"Furniture",
            "type":"Retail Goods"
        }
    ],
    "sg:phone":"+1 306 435 3020",
    "sg:postcode":"S0G 3N0",
    "sg:province":"SK",
    "wof:name":"Tilley's Auction & Furniture",
    "wof:placetype":"venue"
},
  "geometry": {"coordinates":[-101.667831421,50.1504745483],"type":"Point"}
}