{
  "type": "Feature",
  "properties": {
    "addr:full":"6745 Pacific Cir Mississauga ON L5T 1S6",
    "addr:housenumber":"6745",
    "addr:postcode":"l5t 1s6",
    "addr:street":"Pacific Cir",
    "iso:country":"CA",
    "sg:address":"6745 Pacific Cir",
    "sg:city":"Mississauga",
    "sg:classifiers":[
        {
            "category":"Wholesale",
            "subcategory":"Farm Supplies",
            "type":"Manufacturing & Wholesale Goods"
        }
    ],
    "sg:phone":"+1 905 670 2852",
    "sg:postcode":"L5T 1S6",
    "sg:province":"ON",
    "sg:tags":[
        "bulb",
        "seed"
    ],
    "wof:name":"Vanhof & Blokker Ltd",
    "wof:placetype":"venue"
},
  "geometry": {"coordinates":[-79.6797790527,43.6598243713],"type":"Point"}
}