{
  "type": "Feature",
  "properties": {
    "addr:full":"Mississauga ON L5M 2R8",
    "addr:postcode":"l5m 2r8",
    "iso:country":"CA",
    "sg:city":"Mississauga",
    "sg:classifiers":[
        {
            "category":"Food & Beverages",
            "subcategory":"Groceries & Convenience Stores",
            "type":"Retail Goods"
        }
    ],
    "sg:phone":"+1 905 826 1179",
    "sg:postcode":"L5M 2R8",
    "sg:province":"ON",
    "wof:name":"Simply Symon's Convenience",
    "wof:placetype":"venue"
},
  "geometry": {"coordinates":[-79.72687500000001,43.580406],"type":"Point"}
}