{
  "type": "Feature",
  "properties": {
    "addr:full":"Smoky Lake AB T0A 3C0",
    "addr:postcode":"t0a 3c0",
    "iso:country":"CA",
    "sg:city":"Smoky Lake",
    "sg:classifiers":[
        {
            "category":"Farming",
            "subcategory":"Aquatic Farm",
            "type":"Manufacturing & Wholesale Goods"
        }
    ],
    "sg:phone":"+1 780 656 4370",
    "sg:postcode":"T0A 3C0",
    "sg:province":"AB",
    "sg:tags":[
        "hatchery",
        "fish"
    ],
    "wof:name":"Shady Pines Trout Farm",
    "wof:placetype":"venue"
},
  "geometry": {"coordinates":[-112.475738525,54.1105041504],"type":"Point"}
}