{
  "type": "Feature",
  "properties": {
    "addr:full":"4 Silverwood Ave Toronto ON M5P 1W4",
    "addr:housenumber":"4",
    "addr:postcode":"m5p 1w4",
    "addr:street":"Silverwood Ave",
    "iso:country":"CA",
    "sg:address":"4 Silverwood Ave",
    "sg:city":"Toronto",
    "sg:classifiers":[
        {
            "category":"Travel",
            "subcategory":"Campground",
            "type":"Entertainment"
        }
    ],
    "sg:phone":"+1 416 486 1110",
    "sg:postcode":"M5P 1W4",
    "sg:province":"ON",
    "sg:tags":[
        "camp"
    ],
    "wof:name":"Camp Winnebagoe",
    "wof:placetype":"venue"
},
  "geometry": {"coordinates":[-79.4160614014,43.6960144043],"type":"Point"}
}