{
  "type": "Feature",
  "properties": {
    "addr:full":"10481 Dunlop Rd Delta BC V4C 2L1",
    "addr:housenumber":"10481",
    "addr:postcode":"v4c 2l1",
    "addr:street":"Dunlop Rd",
    "iso:country":"CA",
    "sg:address":"10481 Dunlop Rd",
    "sg:city":"Delta",
    "sg:classifiers":[
        {
            "category":"Building & Trades",
            "subcategory":"Construction",
            "type":"Services"
        }
    ],
    "sg:phone":"+1 604 583 1048",
    "sg:postcode":"V4C 2L1",
    "sg:province":"BC",
    "sg:tags":[
        "painter"
    ],
    "wof:name":"Poineer Painters",
    "wof:placetype":"venue"
},
  "geometry": {"coordinates":[-122.93229700000001,49.15641],"type":"Point"}
}