{
  "type": "Feature",
  "properties": {
    "iso:country":"CA",
    "sg:address":"6231 Piccolo Dr",
    "sg:city":"Whistler",
    "sg:classifiers":[
        {
            "category":"Travel",
            "subcategory":"Hotels & Motels",
            "type":"Entertainment"
        }
    ],
    "sg:phone":"+1 604 938 9722",
    "sg:postcode":"V0N 1B6",
    "sg:province":"BC",
    "sg:tags":[
        "breakfast",
        "accommodation",
        "bed"
    ],
    "wof:name":"Lorimer Ridge Pension",
    "wof:placetype":"venue"
},
  "geometry": {"coordinates":[-122.963218689,50.1259231567],"type":"Point"}
}