{
  "type": "Feature",
  "properties": {
    "addr:full":"2899 Plymouth Dr Oakville ON L6H 6G7",
    "addr:housenumber":"2899",
    "addr:postcode":"l6h 6g7",
    "addr:street":"Plymouth Dr",
    "iso:country":"CA",
    "sg:address":"2899 Plymouth Dr",
    "sg:city":"Oakville",
    "sg:classifiers":[
        {
            "category":"Wholesale",
            "subcategory":"Machinery & Supplies",
            "type":"Manufacturing & Wholesale Goods"
        }
    ],
    "sg:phone":"+1 905 823 5222",
    "sg:postcode":"L6H 6G7",
    "sg:province":"ON",
    "sg:tags":[
        "equipment",
        "material",
        "handling"
    ],
    "wof:name":"Master Lift Truck Svc Inc",
    "wof:placetype":"venue"
},
  "geometry": {"coordinates":[-79.67433200000001,43.512508],"type":"Point"}
}