{
  "type": "Feature",
  "properties": {
    "addr:full":"8 Main St Grand Bend ON N0M 1T0",
    "addr:housenumber":"8",
    "addr:postcode":"n0m 1t0",
    "addr:street":"Main St",
    "iso:country":"CA",
    "sg:address":"8 Main St",
    "sg:city":"Grand Bend",
    "sg:classifiers":[
        {
            "category":"Shopping",
            "subcategory":"Gifts & Souvenirs",
            "type":"Retail Goods"
        }
    ],
    "sg:phone":"+1 519 238 5474",
    "sg:postcode":"N0M 1T0",
    "sg:province":"ON",
    "sg:tags":[
        "shop"
    ],
    "wof:name":"Periwinkles Fine Gifts & Acces",
    "wof:placetype":"venue"
},
  "geometry": {"coordinates":[-81.753204,43.310501],"type":"Point"}
}