{
  "type": "Feature",
  "properties": {
    "iso:country":"CA",
    "sg:address":"586 Boul Saint-Jean-Baptiste",
    "sg:city":"Mercier",
    "sg:classifiers":[
        {
            "category":"Manufacturing",
            "subcategory":"Food",
            "type":"Manufacturing & Wholesale Goods"
        }
    ],
    "sg:phone":"+1 450 691 1515",
    "sg:postcode":"J6R 2A7",
    "sg:province":"QC",
    "sg:tags":[
        "winery"
    ],
    "wof:name":"Vignoble Cappabianca",
    "wof:placetype":"venue"
},
  "geometry": {"coordinates":[-73.7375869751,45.3229293823],"type":"Point"}
}