{
  "type": "Feature",
  "properties": {
    "addr:full":"145 Boul Saint-Joseph Saint-Jean-Sur-Richelieu QC J3B 1W5",
    "addr:housenumber":"145",
    "addr:postcode":"j3b 1w5",
    "addr:street":"Boul Saint-Joseph",
    "iso:country":"CA",
    "sg:address":"145 Boul Saint-Joseph",
    "sg:city":"Saint-Jean-Sur-Richelieu",
    "sg:classifiers":[
        {
            "category":"Bars & Pubs",
            "type":"Food & Drink"
        }
    ],
    "sg:phone":"+1 450 359 7040",
    "sg:postcode":"J3B 1W5",
    "sg:province":"QC",
    "sg:tags":[
        "lounge",
        "cocktail"
    ],
    "wof:name":"P'Tit Pub Enr",
    "wof:placetype":"venue"
},
  "geometry": {"coordinates":[-73.25927734379999,45.3145484924],"type":"Point"}
}