{
  "type": "Feature",
  "properties": {
    "addr:full":"144 Cornwallis St Kentville NS B4N 2E6",
    "addr:housenumber":"144",
    "addr:postcode":"b4n 2e6",
    "addr:street":"Cornwallis St",
    "iso:country":"CA",
    "sg:address":"144 Cornwallis St",
    "sg:city":"Kentville",
    "sg:classifiers":[
        {
            "category":"Autos & Motor Vehicles",
            "subcategory":"Auto Supplies",
            "type":"Retail Goods"
        }
    ],
    "sg:phone":"+1 902 678 2148",
    "sg:postcode":"B4N 2E6",
    "sg:province":"NS",
    "sg:tags":[
        "tire"
    ],
    "wof:name":"Goodyear",
    "wof:placetype":"venue"
},
  "geometry": {"coordinates":[-64.495148,45.085003],"type":"Point"}
}