{
  "type": "Feature",
  "properties": {
    "addr:full":"58 Rue Commerciale Cabano QC G0L 1E0",
    "addr:housenumber":"58",
    "addr:postcode":"g0l 1e0",
    "addr:street":"Rue Commerciale",
    "iso:country":"CA",
    "sg:address":"58 Rue Commerciale",
    "sg:city":"Cabano",
    "sg:classifiers":[
        {
            "category":"Social Services",
            "type":"Services"
        }
    ],
    "sg:phone":"+1 418 854 1580",
    "sg:postcode":"G0L 1E0",
    "sg:province":"QC",
    "sg:tags":[
        "youth",
        "organization",
        "center"
    ],
    "wof:name":"Maison Des Jeunes DE Cabano",
    "wof:placetype":"venue"
},
  "geometry": {"coordinates":[-68.88493347169999,47.6836357117],"type":"Point"}
}