{
  "type": "Feature",
  "properties": {
    "addr:full":"241 Chippawa Rd Port Colborne ON L3K 1T8",
    "addr:housenumber":"241",
    "addr:postcode":"l3k 1t8",
    "addr:street":"Chippawa Rd",
    "iso:country":"CA",
    "sg:address":"241 Chippawa Rd",
    "sg:city":"Port Colborne",
    "sg:classifiers":[
        {
            "category":"Personal",
            "subcategory":"Beauty Salon",
            "type":"Services"
        }
    ],
    "sg:phone":"+1 905 835 2671",
    "sg:postcode":"L3K 1T8",
    "sg:province":"ON",
    "wof:name":"Lea's Hairdressing",
    "wof:placetype":"venue"
},
  "geometry": {"coordinates":[-79.237213,42.906979],"type":"Point"}
}