{
  "type": "Feature",
  "properties": {
    "addr:full":"955 Rte 1 Hebron NS B0W 1X0",
    "addr:housenumber":"955",
    "addr:postcode":"b0w 1x0",
    "addr:street":"Rte 1",
    "iso:country":"CA",
    "sg:address":"955 Rte 1",
    "sg:city":"Hebron",
    "sg:classifiers":[
        {
            "category":"Health Services",
            "subcategory":"Chiropractor",
            "type":"Services"
        }
    ],
    "sg:phone":"+1 902 742 9419",
    "sg:postcode":"B0W 1X0",
    "sg:province":"NS",
    "wof:name":"Daniels, Charles DC",
    "wof:placetype":"venue"
},
  "geometry": {"coordinates":[-66.0930099487,43.8909225464],"type":"Point"}
}