{
  "type": "Feature",
  "properties": {
    "iso:country":"CA",
    "sg:address":"62 Wellesley Ave",
    "sg:city":"Saint John",
    "sg:classifiers":[
        {
            "category":"Building & Trades",
            "subcategory":"Cleaning & Sanitation",
            "type":"Services"
        }
    ],
    "sg:phone":"+1 506 652 9009",
    "sg:postcode":"E2K 2V6",
    "sg:province":"NB",
    "sg:tags":[
        "janitor"
    ],
    "wof:name":"Vern's Janitorial Svc Ltd",
    "wof:placetype":"venue"
},
  "geometry": {"coordinates":[-66.0725021362,45.2809638977],"type":"Point"}
}