{
  "type": "Feature",
  "properties": {
    "addr:full":"45 United Dr Orillia ON L3V 6H1",
    "addr:housenumber":"45",
    "addr:postcode":"l3v 6h1",
    "addr:street":"United Dr",
    "iso:country":"CA",
    "sg:address":"45 United Dr",
    "sg:city":"Orillia",
    "sg:classifiers":[
        {
            "category":"Manufacturing",
            "subcategory":"Tools & Machinery",
            "type":"Manufacturing & Wholesale Goods"
        }
    ],
    "sg:phone":"+1 705 327 2150",
    "sg:postcode":"L3V 6H1",
    "sg:province":"ON",
    "sg:tags":[
        "machine",
        "shop"
    ],
    "wof:name":"Huronia Machine Svc",
    "wof:placetype":"venue"
},
  "geometry": {"coordinates":[-79.4231872559,44.5873031616],"type":"Point"}
}