{
  "type": "Feature",
  "properties": {
    "addr:full":"1100 Dundas St London ON N5W 3A7",
    "addr:housenumber":"1100",
    "addr:postcode":"n5w 3a7",
    "addr:street":"Dundas St",
    "iso:country":"CA",
    "sg:address":"1100 Dundas St",
    "sg:city":"London",
    "sg:classifiers":[
        {
            "category":"Manufacturing",
            "subcategory":"Printing",
            "type":"Manufacturing & Wholesale Goods"
        }
    ],
    "sg:phone":"+1 519 453 9600",
    "sg:postcode":"N5W 3A7",
    "sg:province":"ON",
    "sg:tags":[
        "printer"
    ],
    "wof:name":"Document Source",
    "wof:placetype":"venue"
},
  "geometry": {"coordinates":[-81.213936,42.99408],"type":"Point"}
}