{
  "type": "Feature",
  "properties": {
    "addr:full":"4926 Delta St Delta BC V4K 2V2",
    "addr:housenumber":"4926",
    "addr:postcode":"v4k 2v2",
    "addr:street":"Delta St",
    "iso:country":"CA",
    "sg:address":"4926 Delta St",
    "sg:city":"Delta",
    "sg:classifiers":[
        {
            "category":"Home & Garden",
            "subcategory":"Building Materials",
            "type":"Retail Goods"
        }
    ],
    "sg:phone":"+1 604 952 4000",
    "sg:postcode":"V4K 2V2",
    "sg:province":"BC",
    "sg:tags":[
        "glass",
        "window",
        "plate"
    ],
    "wof:name":"Apex Glass & Security",
    "wof:placetype":"venue"
},
  "geometry": {"coordinates":[-123.086662292,49.0921478271],"type":"Point"}
}