{
  "type": "Feature",
  "properties": {
    "addr:full":"Calgary AB T1Y 7H7",
    "addr:postcode":"t1y 7h7",
    "iso:country":"CA",
    "sg:city":"Calgary",
    "sg:classifiers":[
        {
            "category":"Manufacturing",
            "subcategory":"Metals",
            "type":"Manufacturing & Wholesale Goods"
        }
    ],
    "sg:phone":"+1 403 273 7100",
    "sg:postcode":"T1Y 7H7",
    "sg:province":"AB",
    "sg:tags":[
        "fabricator",
        "sheet"
    ],
    "wof:name":"All New Mfg Inc",
    "wof:placetype":"venue"
},
  "geometry": {"coordinates":[-113.972908,51.078041],"type":"Point"}
}