{
  "type": "Feature",
  "properties": {
    "addr:full":"24 Rue Langevin Beauport QC G1E 5B9",
    "addr:housenumber":"24",
    "addr:postcode":"qc g1e 5b9",
    "addr:street":"Rue Langevin",
    "iso:country":"CA",
    "sg:address":"24 Rue Langevin",
    "sg:city":"Beauport",
    "sg:classifiers":[
        {
            "category":"Building & Trades",
            "subcategory":"Electrical",
            "type":"Services"
        }
    ],
    "sg:phone":"+1 418 661 9211",
    "sg:postcode":"G1E 5B9",
    "sg:province":"QC",
    "sg:tags":[
        "electric",
        "contractor"
    ],
    "wof:name":"Roger Guillot Inc",
    "wof:placetype":"venue"
},
  "geometry": {"coordinates":[-71.188828,46.86388],"type":"Point"}
}