{
  "type": "Feature",
  "properties": {
    "addr:full":"12301 Rue Colin Pierrefonds QC H9A 1C3",
    "addr:housenumber":"12301",
    "addr:postcode":"h9a 1c3",
    "addr:street":"Rue Colin",
    "iso:country":"CA",
    "sg:address":"12301 Rue Colin",
    "sg:city":"Pierrefonds",
    "sg:classifiers":[
        {
            "category":"Organizations",
            "subcategory":"Religious Organization",
            "type":"Services"
        }
    ],
    "sg:phone":"+1 514 684 4460",
    "sg:postcode":"H9A 1C3",
    "sg:province":"QC",
    "sg:tags":[
        "church"
    ],
    "wof:name":"St Barnabas Anglican Church",
    "wof:placetype":"venue"
},
  "geometry": {"coordinates":[-73.8273773193,45.5031929016],"type":"Point"}
}