{
  "type": "Feature",
  "properties": {
    "addr:full":"1860 Boul Valcartier Saint-Gabriel-DE-Valcartier QC G0A 4S0",
    "addr:housenumber":"1860",
    "addr:postcode":"g0a 4s0",
    "addr:street":"Boul Valcartier",
    "iso:country":"CA",
    "sg:address":"1860 Boul Valcartier",
    "sg:city":"Saint-Gabriel-DE-Valcartier",
    "sg:classifiers":[
        {
            "category":"Travel",
            "subcategory":"Campground",
            "type":"Entertainment"
        }
    ],
    "sg:phone":"+1 418 844 2200",
    "sg:postcode":"G0A 4S0",
    "sg:province":"QC",
    "wof:name":"Village Vacances Valcartier",
    "wof:placetype":"venue"
},
  "geometry": {"coordinates":[-71.476021,46.941807],"type":"Point"}
}