{
  "type": "Feature",
  "properties": {
    "addr:full":"208 Keefer St Vancouver BC V6A 1X5",
    "addr:housenumber":"208",
    "addr:postcode":"v6a 1x5",
    "addr:street":"Keefer St",
    "iso:country":"CA",
    "sg:address":"208 Keefer St",
    "sg:city":"Vancouver",
    "sg:classifiers":[
        {
            "category":"Utilities",
            "subcategory":"Mobile Phone",
            "type":"Services"
        }
    ],
    "sg:phone":"+1 604 688 3883",
    "sg:postcode":"V6A 1X5",
    "sg:province":"BC",
    "sg:tags":[
        "telephone",
        "cellular"
    ],
    "wof:name":"Rogers At & T Wireless",
    "wof:placetype":"venue"
},
  "geometry": {"coordinates":[-123.09928893999999,49.2793388367],"type":"Point"}
}