{
  "type": "Feature",
  "properties": {
    "addr:full":"1626 Cassells St North Bay ON P1B 4C5",
    "addr:housenumber":"1626",
    "addr:postcode":"p1b 4c5",
    "addr:street":"Cassells St",
    "iso:country":"CA",
    "sg:address":"1626 Cassells St",
    "sg:city":"North Bay",
    "sg:classifiers":[
        {
            "category":"Home & Garden",
            "subcategory":"Household Appliances",
            "type":"Retail Goods"
        }
    ],
    "sg:phone":"+1 705 476 3314",
    "sg:postcode":"P1B 4C5",
    "sg:province":"ON",
    "wof:name":"Bay Appliance Parts & Sales",
    "wof:placetype":"venue"
},
  "geometry": {"coordinates":[-79.4492492676,46.3182258606],"type":"Point"}
}