{
  "type": "Feature",
  "properties": {
    "addr:full":"Richmond BC V6V 1J8",
    "addr:postcode":"v6v 1j8",
    "iso:country":"CA",
    "sg:city":"Richmond",
    "sg:classifiers":[
        {
            "category":"Retail",
            "subcategory":"Auto Repair",
            "type":"Services"
        }
    ],
    "sg:phone":"+1 604 273 0041",
    "sg:postcode":"V6V 1J8",
    "sg:province":"BC",
    "sg:tags":[
        "repairing",
        "automobile"
    ],
    "wof:name":"K J Automotive",
    "wof:placetype":"venue"
},
  "geometry": {"coordinates":[-123.088447571,49.1937294006],"type":"Point"}
}