{
  "type": "Feature",
  "properties": {
    "addr:full":"3201 Greenbank Rd Nepean ON K2J 4H9",
    "addr:housenumber":"3201",
    "addr:postcode":"k2j 4h9",
    "addr:street":"Greenbank Rd",
    "iso:country":"CA",
    "sg:address":"3201 Greenbank Rd",
    "sg:city":"Nepean",
    "sg:classifiers":[
        {
            "category":"Shopping",
            "subcategory":"Pharmacy",
            "type":"Retail Goods"
        }
    ],
    "sg:phone":"+1 613 825 3748",
    "sg:postcode":"K2J 4H9",
    "sg:province":"ON",
    "wof:name":"Drug Store Pharmacy",
    "wof:placetype":"venue"
},
  "geometry": {"coordinates":[-75.744392,45.267437],"type":"Point"}
}