{
  "type": "Feature",
  "properties": {
    "addr:full":"567 Marion St Winnipeg MB R2J 0J9",
    "addr:housenumber":"567",
    "addr:postcode":"r2j 0j9",
    "addr:street":"Marion St",
    "iso:country":"CA",
    "sg:address":"567 Marion St",
    "sg:city":"Winnipeg",
    "sg:classifiers":[
        {
            "category":"Freight",
            "type":"Transportation"
        }
    ],
    "sg:phone":"+1 204 233 0850",
    "sg:postcode":"R2J 0J9",
    "sg:province":"MB",
    "sg:tags":[
        "trucking"
    ],
    "wof:name":"Crumb's Transfer",
    "wof:placetype":"venue"
},
  "geometry": {"coordinates":[-97.10004425050001,49.8821105957],"type":"Point"}
}