{
  "type": "Feature",
  "properties": {
    "addr:full":"1461 1st St E Cornwall ON K6H 1P8",
    "addr:housenumber":"1461",
    "addr:postcode":"k6h 1p8",
    "addr:street":"1St St E",
    "iso:country":"CA",
    "sg:address":"1461 1st St E",
    "sg:city":"Cornwall",
    "sg:classifiers":[
        {
            "category":"Home & Garden",
            "subcategory":"Building Materials",
            "type":"Retail Goods"
        }
    ],
    "sg:phone":"+1 613 936 9416",
    "sg:postcode":"K6H 1P8",
    "sg:province":"ON",
    "sg:tags":[
        "roofing"
    ],
    "wof:name":"Carlisle Syntec Corp",
    "wof:placetype":"venue"
},
  "geometry": {"coordinates":[-74.69548034669999,45.0281219482],"type":"Point"}
}