{
  "type": "Feature",
  "properties": {
    "addr:full":"4 Centennial Dr Penetanguishene ON L9M 1G8",
    "addr:housenumber":"4",
    "addr:postcode":"l9m 1g8",
    "addr:street":"Centennial Dr",
    "iso:country":"CA",
    "sg:address":"4 Centennial Dr",
    "sg:city":"Penetanguishene",
    "sg:classifiers":[
        {
            "category":"Building & Trades",
            "subcategory":"Plumbing",
            "type":"Services"
        }
    ],
    "sg:phone":"+1 705 549 2710",
    "sg:postcode":"L9M 1G8",
    "sg:province":"ON",
    "sg:tags":[
        "heating",
        "contractor"
    ],
    "wof:name":"Home & Cottage Ctr",
    "wof:placetype":"venue"
},
  "geometry": {"coordinates":[-79.91642,44.777241],"type":"Point"}
}