{
  "type": "Feature",
  "properties": {
    "iso:country":"CA",
    "sg:address":"1255 Prince Edward St",
    "sg:city":"Melville",
    "sg:classifiers":[
        {
            "category":"Education",
            "subcategory":"School",
            "type":"Public Place"
        }
    ],
    "sg:phone":"+1 306 728 3877",
    "sg:postcode":"S0A 2P0",
    "sg:province":"SK",
    "wof:name":"St Henry's Sr School",
    "wof:placetype":"venue"
},
  "geometry": {"coordinates":[-102.796257019,50.9308738708],"type":"Point"}
}