{
  "type": "Feature",
  "properties": {
    "addr:full":"1012 Notre-Dame St Embrun ON K0A 1W0",
    "addr:housenumber":"1012",
    "addr:postcode":"k0a 1w0",
    "addr:street":"Notre-Dame St",
    "iso:country":"CA",
    "sg:address":"1012 Notre-Dame St",
    "sg:city":"Embrun",
    "sg:classifiers":[
        {
            "category":"Wholesale",
            "subcategory":"Meat",
            "type":"Manufacturing & Wholesale Goods"
        }
    ],
    "sg:phone":"+1 613 443 2971",
    "sg:postcode":"K0A 1W0",
    "sg:province":"ON",
    "sg:tags":[
        "grocer",
        "butchering"
    ],
    "wof:name":"R Bourbonnais CO Ltd",
    "wof:placetype":"venue"
},
  "geometry": {"coordinates":[-75.2766876221,45.2733726501],"type":"Point"}
}