{
  "type": "Feature",
  "properties": {
    "addr:full":"Saint-Eustache QC J7R 1K5",
    "addr:postcode":"j7r 1k5",
    "iso:country":"CA",
    "sg:city":"Saint-Eustache",
    "sg:classifiers":[
        {
            "category":"Professional",
            "subcategory":"Business Services",
            "type":"Services"
        }
    ],
    "sg:phone":"+1 450 473 4567",
    "sg:postcode":"J7R 1K5",
    "sg:province":"QC",
    "sg:tags":[
        "consultant",
        "estate"
    ],
    "wof:name":"Bigras, Anne-Marie",
    "wof:placetype":"venue"
},
  "geometry": {"coordinates":[-73.96318817140001,45.5232391357],"type":"Point"}
}