{
  "type": "Feature",
  "properties": {
    "addr:full":"1010 Topsail Rd Mount Pearl NL A1N 5E5",
    "addr:housenumber":"1010",
    "addr:postcode":"a1n 5e5",
    "addr:street":"Topsail Rd",
    "iso:country":"CA",
    "sg:address":"1010 Topsail Rd",
    "sg:city":"Mount Pearl",
    "sg:classifiers":[
        {
            "category":"Social Services",
            "subcategory":"Child Care",
            "type":"Services"
        }
    ],
    "sg:phone":"+1 709 368 0496",
    "sg:postcode":"A1N 5E5",
    "sg:province":"NL",
    "wof:name":"Chatter Box Pre-School & Day",
    "wof:placetype":"venue"
},
  "geometry": {"coordinates":[-52.8078956604,47.5247993469],"type":"Point"}
}