{
  "type": "Feature",
  "properties": {
    "addr:full":"109 Railway St Milk River AB T0K 1M0",
    "addr:housenumber":"109",
    "addr:postcode":"t0k 1m0",
    "addr:street":"Railway St",
    "iso:country":"CA",
    "sg:address":"109 Railway St",
    "sg:city":"Milk River",
    "sg:classifiers":[
        {
            "category":"Wholesale",
            "subcategory":"Farm Supplies",
            "type":"Manufacturing & Wholesale Goods"
        }
    ],
    "sg:phone":"+1 403 647 3633",
    "sg:postcode":"T0K 1M0",
    "sg:province":"AB",
    "sg:tags":[
        "grain",
        "elevator"
    ],
    "wof:name":"Parrish & Heimbecker Ltd",
    "wof:placetype":"venue"
},
  "geometry": {"coordinates":[-112.090996,49.153141],"type":"Point"}
}