{
  "type": "Feature",
  "properties": {
    "addr:full":"215 Av Van Horne Montreal QC H2T 2J2",
    "addr:housenumber":"215",
    "addr:postcode":"h2t 2j2",
    "addr:street":"Av Van Horne",
    "iso:country":"CA",
    "sg:address":"215 Av Van Horne",
    "sg:city":"Montreal",
    "sg:classifiers":[
        {
            "category":"Retail",
            "subcategory":"Auto Repair",
            "type":"Services"
        }
    ],
    "sg:phone":"+1 514 272 3366",
    "sg:postcode":"H2T 2J2",
    "sg:province":"QC",
    "sg:tags":[
        "repairing",
        "automobile"
    ],
    "wof:name":"Outremont Auto Inc",
    "wof:placetype":"venue"
},
  "geometry": {"coordinates":[-73.6093444824,45.5268592834],"type":"Point"}
}