{
  "type": "Feature",
  "properties": {
    "addr:full":"776 Davis Dr Newmarket ON L3Y 2R4",
    "addr:housenumber":"776",
    "addr:postcode":"l3y 2r4",
    "addr:street":"Davis Dr",
    "iso:country":"CA",
    "sg:address":"776 Davis Dr",
    "sg:city":"Newmarket",
    "sg:classifiers":[
        {
            "category":"Manufacturing",
            "subcategory":"Motor Vehicles & Parts",
            "type":"Manufacturing & Wholesale Goods"
        }
    ],
    "sg:phone":"+1 416 798 7058",
    "sg:postcode":"L3Y 2R4",
    "sg:province":"ON",
    "sg:tags":[
        "automobile",
        "supply"
    ],
    "wof:name":"Tenatronics Limited",
    "wof:placetype":"venue"
},
  "geometry": {"coordinates":[-79.44533538819999,44.0625915527],"type":"Point"}
}