{
  "type": "Feature",
  "properties": {
    "iso:country":"CA",
    "sg:address":"353 South Mclean St",
    "sg:city":"Campbell River",
    "sg:classifiers":[
        {
            "category":"Professional",
            "subcategory":"Business Services",
            "type":"Services"
        }
    ],
    "sg:phone":"+1 250 286 1320",
    "sg:postcode":"V9W 2L7",
    "sg:province":"BC",
    "sg:tags":[
        "interior",
        "consultant",
        "design",
        "decorator"
    ],
    "wof:name":"Gail E Maier Interior Designs",
    "wof:placetype":"venue"
},
  "geometry": {"coordinates":[-125.237884522,50.0013313293],"type":"Point"}
}