{
  "type": "Feature",
  "properties": {
    "iso:country":"CA",
    "sg:city":"Markham",
    "sg:classifiers":[
        {
            "category":"Food & Beverages",
            "subcategory":"Groceries & Convenience Stores",
            "type":"Retail Goods"
        }
    ],
    "sg:phone":"+1 905 305 6688",
    "sg:postcode":"L3R 9V8",
    "sg:province":"ON",
    "sg:tags":[
        "grocer"
    ],
    "wof:name":"GA GA Luck Frozen Dim Sum Ltd",
    "wof:placetype":"venue"
},
  "geometry": {"coordinates":[-79.30394,43.824562],"type":"Point"}
}