{
  "type": "Feature",
  "properties": {
    "addr:full":"427 Ferguson St North Bay ON P1B 1X3",
    "addr:housenumber":"427",
    "addr:postcode":"p1b 1x3",
    "addr:street":"Ferguson St",
    "iso:country":"CA",
    "sg:address":"427 Ferguson St",
    "sg:city":"North Bay",
    "sg:classifiers":[
        {
            "category":"Health Services",
            "subcategory":"Doctor",
            "type":"Services"
        }
    ],
    "sg:phone":"+1 705 472 8707",
    "sg:postcode":"P1B 1X3",
    "sg:province":"ON",
    "sg:tags":[
        "dentist"
    ],
    "wof:name":"Mc Parland, David S DDS",
    "wof:placetype":"venue"
},
  "geometry": {"coordinates":[-79.461983,46.311298],"type":"Point"}
}