{
  "type": "Feature",
  "properties": {
    "addr:full":"Hinton AB T7V 1H1",
    "addr:postcode":"t7v 1h1",
    "iso:country":"CA",
    "sg:city":"Hinton",
    "sg:classifiers":[
        {
            "category":"Home & Garden",
            "subcategory":"Building Materials",
            "type":"Retail Goods"
        }
    ],
    "sg:phone":"+1 780 865 4900",
    "sg:postcode":"T7V 1H1",
    "sg:province":"AB",
    "sg:tags":[
        "glass",
        "window",
        "plate"
    ],
    "wof:name":"Tradewinds Glass Ltd",
    "wof:placetype":"venue"
},
  "geometry": {"coordinates":[-117.560081482,53.4159736633],"type":"Point"}
}