{
  "type": "Feature",
  "properties": {
    "iso:country":"CA",
    "sg:address":"330 Rue Marie-Anne E",
    "sg:city":"Montreal",
    "sg:classifiers":[
        {
            "category":"Restaurant",
            "type":"Food & Drink"
        }
    ],
    "sg:phone":"+1 514 282 6342",
    "sg:postcode":"H2W 1B1",
    "sg:province":"QC",
    "wof:name":"P'Tit Plateau",
    "wof:placetype":"venue"
},
  "geometry": {"coordinates":[-73.581123,45.522133],"type":"Point"}
}