{
  "type": "Feature",
  "properties": {
    "addr:full":"30 Intermodal Dr #50 Brampton ON L6T 5K1",
    "addr:housenumber":"30",
    "addr:postcode":"l6t 5k1",
    "addr:street":"Intermodal Dr # 50",
    "iso:country":"CA",
    "sg:address":"30 Intermodal Dr #50",
    "sg:city":"Brampton",
    "sg:classifiers":[
        {
            "category":"Building & Trades",
            "subcategory":"Plumbing",
            "type":"Services"
        }
    ],
    "sg:phone":"+1 905 792 7370",
    "sg:postcode":"L6T 5K1",
    "sg:province":"ON",
    "sg:tags":[
        "contractor"
    ],
    "wof:name":"Trademark Plumbing & Heating",
    "wof:placetype":"venue"
},
  "geometry": {"coordinates":[-79.6784744263,43.7310447693],"type":"Point"}
}