{
  "type": "Feature",
  "properties": {
    "addr:full":"413 Wingfield St Petrolia ON N0N 1R0",
    "addr:housenumber":"413",
    "addr:postcode":"n0n 1r0",
    "addr:street":"Wingfield St",
    "iso:country":"CA",
    "sg:address":"413 Wingfield St",
    "sg:city":"Petrolia",
    "sg:classifiers":[
        {
            "category":"Health Services",
            "subcategory":"Optometrist",
            "type":"Services"
        }
    ],
    "sg:phone":"+1 519 882 1316",
    "sg:postcode":"N0N 1R0",
    "sg:province":"ON",
    "wof:name":"St Pierre, Jessica OD",
    "wof:placetype":"venue"
},
  "geometry": {"coordinates":[-82.14746100000001,42.881077],"type":"Point"}
}