{
  "type": "Feature",
  "properties": {
    "iso:country":"CA",
    "sg:city":"Mississauga",
    "sg:classifiers":[
        {
            "category":"Professional",
            "subcategory":"Management & Consulting",
            "type":"Services"
        }
    ],
    "sg:phone":"+1 905 542 2890",
    "sg:postcode":"L5N 6J7",
    "sg:province":"ON",
    "sg:tags":[
        "consultant",
        "energy",
        "conservation"
    ],
    "wof:name":"Caneta Research Inc",
    "wof:placetype":"venue"
},
  "geometry": {"coordinates":[-79.7559967041,43.608707428],"type":"Point"}
}