{
  "type": "Feature",
  "properties": {
    "addr:full":"208 Eagle Ridge Dr SW Calgary AB T2V 2V7",
    "addr:housenumber":"208",
    "addr:postcode":"t2v 2v7",
    "addr:street":"Eagle Ridge Dr Sw",
    "iso:country":"CA",
    "sg:address":"208 Eagle Ridge Dr SW",
    "sg:city":"Calgary",
    "sg:classifiers":[
        {
            "category":"Real Estate",
            "subcategory":"Real Estate Agent",
            "type":"Services"
        }
    ],
    "sg:phone":"+1 403 258 3330",
    "sg:postcode":"T2V 2V7",
    "sg:province":"AB",
    "sg:tags":[
        "company",
        "management",
        "land"
    ],
    "wof:name":"Westland Investment CO Ltd",
    "wof:placetype":"venue"
},
  "geometry": {"coordinates":[-114.10018158,50.9862098694],"type":"Point"}
}