{
  "type": "Feature",
  "properties": {
    "addr:full":"1346 Three Bridges Rd St Jacobs ON N0B 2N0",
    "addr:housenumber":"1346",
    "addr:postcode":"n0b 2n0",
    "addr:street":"Three Bridges Rd St",
    "iso:country":"CA",
    "sg:address":"1346 Three Bridges Rd",
    "sg:city":"St Jacobs",
    "sg:classifiers":[
        {
            "category":"Retail",
            "subcategory":"Repair Shop",
            "type":"Services"
        }
    ],
    "sg:phone":"+1 519 664 2188",
    "sg:postcode":"N0B 2N0",
    "sg:province":"ON",
    "sg:tags":[
        "blacksmith"
    ],
    "wof:name":"Martin, Cleason B",
    "wof:placetype":"venue"
},
  "geometry": {"coordinates":[-80.568016,43.531563],"type":"Point"}
}