{
  "type": "Feature",
  "properties": {
    "addr:full":"8177 Av Christophe-Colomb Montreal QC H2P 2Z2",
    "addr:housenumber":"8177",
    "addr:postcode":"h2p 2z2",
    "addr:street":"Av Christophe-Colomb",
    "iso:country":"CA",
    "sg:address":"8177 Av Christophe-Colomb",
    "sg:city":"Montreal",
    "sg:classifiers":[
        {
            "category":"Professional",
            "subcategory":"Business Services",
            "type":"Services"
        }
    ],
    "sg:phone":"+1 514 374 7617",
    "sg:postcode":"H2P 2Z2",
    "sg:province":"QC",
    "sg:tags":[
        "interior",
        "consultant",
        "design",
        "decorator"
    ],
    "wof:name":"Suzanne Pitre Design D'Intr",
    "wof:placetype":"venue"
},
  "geometry": {"coordinates":[-73.62554900000001,45.548733],"type":"Point"}
}