{
  "type": "Feature",
  "properties": {
    "addr:full":"191 Drive-In-Theatre Rd New Liskeard ON P0J 1P0",
    "addr:housenumber":"191",
    "addr:postcode":"p0j 1p0",
    "addr:street":"Drive-In-Theatre Rd",
    "iso:country":"CA",
    "sg:address":"191 Drive-In-Theatre Rd",
    "sg:city":"New Liskeard",
    "sg:classifiers":[
        {
            "category":"Retail",
            "subcategory":"Veterinary Services",
            "type":"Services"
        }
    ],
    "sg:phone":"+1 705 647 7009",
    "sg:postcode":"P0J 1P0",
    "sg:province":"ON",
    "sg:tags":[
        "veterinarian"
    ],
    "wof:name":"Males, Lance DVM",
    "wof:placetype":"venue"
},
  "geometry": {"coordinates":[-79.67366800000001,47.508579],"type":"Point"}
}