{
  "type": "Feature",
  "properties": {
    "addr:full":"Gloucester ON K1J 9M1",
    "addr:postcode":"k1j 9m1",
    "iso:country":"CA",
    "sg:city":"Gloucester",
    "sg:classifiers":[
        {
            "category":"Health Services",
            "subcategory":"Medical Lab",
            "type":"Services"
        }
    ],
    "sg:phone":"+1 613 748 9797",
    "sg:postcode":"K1J 9M1",
    "sg:province":"ON",
    "sg:tags":[
        "x"
    ],
    "wof:name":"Diagnosti Care Beacon Hill Rad",
    "wof:placetype":"venue"
},
  "geometry": {"coordinates":[-75.58886699999999,45.4524],"type":"Point"}
}