{
  "type": "Feature",
  "properties": {
    "iso:country":"CA",
    "sg:address":"671 3E Rue",
    "sg:city":"LA Baie",
    "sg:classifiers":[
        {
            "category":"Food & Beverages",
            "subcategory":"Groceries & Convenience Stores",
            "type":"Retail Goods"
        }
    ],
    "sg:phone":"+1 418 544 4577",
    "sg:postcode":"G7B 2B6",
    "sg:province":"QC",
    "sg:tags":[
        "grocer"
    ],
    "wof:name":"Epicerie Bonichoix Eddy",
    "wof:placetype":"venue"
},
  "geometry": {"coordinates":[-70.8785018921,48.3283500671],"type":"Point"}
}