{
  "type": "Feature",
  "properties": {
    "addr:full":"Watson Lake YT Y0A 1C0",
    "addr:postcode":"y0a 1c0",
    "iso:country":"CA",
    "sg:city":"Watson Lake",
    "sg:classifiers":[
        {
            "category":"Government",
            "subcategory":"Office",
            "type":"Public Place"
        }
    ],
    "sg:phone":"+1 867 536 7494",
    "sg:postcode":"Y0A 1C0",
    "sg:province":"YT",
    "wof:name":"Yukon Building Maitenance",
    "wof:placetype":"venue"
},
  "geometry": {"coordinates":[-128.714157,60.062935],"type":"Point"}
}