{
  "type": "Feature",
  "properties": {
    "addr:full":"2072 Queen St E Toronto ON M4E 1E1",
    "addr:housenumber":"2072",
    "addr:postcode":"m4e 1e1",
    "addr:street":"Queen St E",
    "iso:country":"CA",
    "sg:address":"2072 Queen St E",
    "sg:city":"Toronto",
    "sg:classifiers":[
        {
            "category":"Retail",
            "subcategory":"Photofinishing",
            "type":"Services"
        }
    ],
    "sg:phone":"+1 416 686 5555",
    "sg:postcode":"M4E 1E1",
    "sg:province":"ON",
    "sg:tags":[
        "photo",
        "finishing"
    ],
    "wof:name":"Moto Photo",
    "wof:placetype":"venue"
},
  "geometry": {"coordinates":[-79.29681396479999,43.6707725525],"type":"Point"}
}