{
  "type": "Feature",
  "properties": {
    "addr:full":"59 Rue Sous-Le-Fort Quebec QC G1K 4G9",
    "addr:housenumber":"59",
    "addr:postcode":"g1k 4g9",
    "addr:street":"Rue Sous-Le-Fort",
    "iso:country":"CA",
    "sg:address":"59 Rue Sous-Le-Fort",
    "sg:city":"Quebec",
    "sg:classifiers":[
        {
            "category":"Shopping",
            "subcategory":"Tobacco",
            "type":"Retail Goods"
        }
    ],
    "sg:phone":"+1 418 692 4440",
    "sg:postcode":"G1K 4G9",
    "sg:province":"QC",
    "sg:tags":[
        "cigarette",
        "cigar",
        "dealer"
    ],
    "wof:name":"Tabagie Casse-Cou Enr",
    "wof:placetype":"venue"
},
  "geometry": {"coordinates":[-71.20311700000001,46.812469],"type":"Point"}
}