{
  "type": "Feature",
  "properties": {
    "addr:full":"53 Wolfrey Ave Toronto ON M4K 1K9",
    "addr:housenumber":"53",
    "addr:postcode":"m4k 1k9",
    "addr:street":"Wolfrey Ave",
    "iso:country":"CA",
    "sg:address":"53 Wolfrey Ave",
    "sg:city":"Toronto",
    "sg:classifiers":[
        {
            "category":"Building & Trades",
            "subcategory":"Construction",
            "type":"Services"
        }
    ],
    "sg:phone":"+1 416 406 4848",
    "sg:postcode":"M4K 1K9",
    "sg:province":"ON",
    "sg:tags":[
        "painter"
    ],
    "wof:name":"Russell Painting",
    "wof:placetype":"venue"
},
  "geometry": {"coordinates":[-79.35392,43.674713],"type":"Point"}
}