{
  "type": "Feature",
  "properties": {
    "addr:full":"7082 Mershon St Mission BC V2V 2Y7",
    "addr:postcode":"7082;v2v 2y7",
    "addr:street":"Mershon St",
    "iso:country":"CA",
    "sg:address":"7082 Mershon St",
    "sg:city":"Mission",
    "sg:classifiers":[
        {
            "category":"Retail",
            "subcategory":"Auto Repair",
            "type":"Services"
        }
    ],
    "sg:phone":"+1 604 826 3444",
    "sg:postcode":"V2V 2Y7",
    "sg:province":"BC",
    "sg:tags":[
        "repairing",
        "automobile"
    ],
    "wof:name":"Cedar Valley Alignment",
    "wof:placetype":"venue"
},
  "geometry": {"coordinates":[-122.300217,49.130302],"type":"Point"}
}