{
  "type": "Feature",
  "properties": {
    "iso:country":"CA",
    "sg:address":"949 Henderson Hwy",
    "sg:city":"Winnipeg",
    "sg:classifiers":[
        {
            "category":"Restaurant",
            "type":"Food & Drink"
        }
    ],
    "sg:phone":"+1 204 668 1062",
    "sg:postcode":"R2K 2M2",
    "sg:province":"MB",
    "sg:tags":[
        "parlor",
        "ice",
        "cream"
    ],
    "wof:name":"Sweet Tops Ice Cream",
    "wof:placetype":"venue"
},
  "geometry": {"coordinates":[-97.0982666016,49.9330940247],"type":"Point"}
}