{
  "type": "Feature",
  "properties": {
    "addr:full":"7 Oakland Ave North York ON M9M 2H9",
    "addr:housenumber":"7",
    "addr:postcode":"m9m 2h9",
    "addr:street":"Oakland Ave",
    "iso:country":"CA",
    "sg:address":"7 Oakland Ave",
    "sg:city":"North York",
    "sg:classifiers":[
        {
            "category":"Organizations",
            "subcategory":"Professional Association",
            "type":"Services"
        }
    ],
    "sg:phone":"+1 416 742 1333",
    "sg:postcode":"M9M 2H9",
    "sg:province":"ON",
    "sg:tags":[
        "club"
    ],
    "wof:name":"Delaware & Rutland Ltd",
    "wof:placetype":"venue"
},
  "geometry": {"coordinates":[-79.5265045166,43.7171897888],"type":"Point"}
}