{
  "type": "Feature",
  "properties": {
    "addr:full":"1215 15 Ave S Creston BC V0B 1G1",
    "addr:housenumber":"1215",
    "addr:postcode":"bc v0b 1g1",
    "addr:street":"15 Ave S",
    "iso:country":"CA",
    "sg:address":"1215 15 Ave S",
    "sg:city":"Creston",
    "sg:classifiers":[
        {
            "category":"Building & Trades",
            "subcategory":"Construction",
            "type":"Services"
        }
    ],
    "sg:phone":"+1 250 428 9868",
    "sg:postcode":"V0B 1G1",
    "sg:province":"BC",
    "sg:tags":[
        "excavating",
        "contractor"
    ],
    "wof:name":"Cull Brothers Contracting Ltd",
    "wof:placetype":"venue"
},
  "geometry": {"coordinates":[-116.508308411,49.0947608948],"type":"Point"}
}