{
  "type": "Feature",
  "properties": {
    "iso:country":"CA",
    "sg:address":"4396 King St E",
    "sg:city":"Kitchener",
    "sg:classifiers":[
        {
            "category":"Shopping",
            "subcategory":"Computers & Home Electronics",
            "type":"Retail Goods"
        }
    ],
    "sg:phone":"+1 519 650 2001",
    "sg:postcode":"N2P 2G4",
    "sg:province":"ON",
    "sg:tags":[
        "high",
        "television",
        "stereophonic",
        "fidelity"
    ],
    "wof:name":"2001 Audio Video",
    "wof:placetype":"venue"
},
  "geometry": {"coordinates":[-80.3942565918,43.4064826965],"type":"Point"}
}