{
  "type": "Feature",
  "properties": {
    "iso:country":"CA",
    "sg:address":"20 Rue Du Pont",
    "sg:city":"Yamaska-Est",
    "sg:classifiers":[
        {
            "category":"Taxi",
            "type":"Transportation"
        }
    ],
    "sg:phone":"+1 450 746 6666",
    "sg:postcode":"J0G 1X0",
    "sg:province":"QC",
    "sg:tags":[
        "taxicab"
    ],
    "wof:name":"Taxi Real Nadeau",
    "wof:placetype":"venue"
},
  "geometry": {"coordinates":[-72.90772247309999,46.0055999756],"type":"Point"}
}