{
  "type": "Feature",
  "properties": {
    "iso:country":"CA",
    "sg:address":"3417 17 Ave SW",
    "sg:city":"Calgary",
    "sg:classifiers":[
        {
            "category":"Retail",
            "subcategory":"Car Wash",
            "type":"Services"
        }
    ],
    "sg:phone":"+1 403 249 3779",
    "sg:postcode":"T3E 0B5",
    "sg:province":"AB",
    "sg:tags":[
        "polishing",
        "washing"
    ],
    "wof:name":"Mile-Wide Car Wash",
    "wof:placetype":"venue"
},
  "geometry": {"coordinates":[-114.135818481,51.0376548767],"type":"Point"}
}