{
  "type": "Feature",
  "properties": {
    "iso:country":"CA",
    "sg:city":"Whitby",
    "sg:classifiers":[
        {
            "category":"Health Services",
            "subcategory":"Optometrist",
            "type":"Services"
        }
    ],
    "sg:phone":"+1 905 668 4479",
    "sg:postcode":"L1N 2J2",
    "sg:province":"ON",
    "wof:name":"Ninacs, Edward F OD",
    "wof:placetype":"venue"
},
  "geometry": {"coordinates":[-78.93789672849999,43.8807067871],"type":"Point"}
}