{
  "type": "Feature",
  "properties": {
    "iso:country":"CA",
    "sg:address":"1065 Rue Saint-Alphonse O",
    "sg:city":"Thetford Mines",
    "sg:classifiers":[
        {
            "category":"Real Estate",
            "subcategory":"Real Estate Agent",
            "type":"Services"
        }
    ],
    "sg:phone":"+1 418 338 0340",
    "sg:postcode":"G6G 3X7",
    "sg:province":"QC",
    "wof:name":"Capitale Thetford Mines Inc",
    "wof:placetype":"venue"
},
  "geometry": {"coordinates":[-71.2857589722,46.0788536072],"type":"Point"}
}