{
  "type": "Feature",
  "properties": {
    "addr:full":"3046 Clearbrook Rd Abbotsford BC V2T 4T6",
    "addr:housenumber":"3046",
    "addr:postcode":"v2t 4t6",
    "addr:street":"Clearbrook Rd",
    "iso:country":"CA",
    "sg:address":"3046 Clearbrook Rd",
    "sg:city":"Abbotsford",
    "sg:classifiers":[
        {
            "category":"Real Estate",
            "subcategory":"Real Estate Operator",
            "type":"Services"
        }
    ],
    "sg:phone":"+1 604 852 4696",
    "sg:postcode":"V2T 4T6",
    "sg:province":"BC",
    "sg:tags":[
        "apartment"
    ],
    "wof:name":"Meadowood Manor",
    "wof:placetype":"venue"
},
  "geometry": {"coordinates":[-122.33775300000001,49.057438],"type":"Point"}
}