{
  "type": "Feature",
  "properties": {
    "addr:full":"557 Morrish Rd Scarborough ON M1C 1G2",
    "addr:housenumber":"557",
    "addr:postcode":"m1c 1g2",
    "addr:street":"Morrish Rd",
    "iso:country":"CA",
    "sg:address":"557 Morrish Rd",
    "sg:city":"Scarborough",
    "sg:classifiers":[
        {
            "category":"Freight",
            "type":"Transportation"
        }
    ],
    "sg:phone":"+1 416 282 6882",
    "sg:postcode":"M1C 1G2",
    "sg:province":"ON",
    "sg:tags":[
        "cartage"
    ],
    "wof:name":"Powell Transport",
    "wof:placetype":"venue"
},
  "geometry": {"coordinates":[-79.17394256590001,43.7921180725],"type":"Point"}
}