{
  "type": "Feature",
  "properties": {
    "addr:full":"214 Dunkirk Rd St Catharines ON L2R 7K6",
    "addr:housenumber":"214",
    "addr:postcode":"l2r 7k6",
    "addr:street":"Dunkirk Rd",
    "iso:country":"CA",
    "sg:address":"214 Dunkirk Rd",
    "sg:city":"St Catharines",
    "sg:classifiers":[
        {
            "category":"Manufacturing",
            "subcategory":"Tools & Machinery",
            "type":"Manufacturing & Wholesale Goods"
        }
    ],
    "sg:phone":"+1 905 687 4976",
    "sg:postcode":"L2R 7K6",
    "sg:province":"ON",
    "sg:tags":[
        "machine",
        "shop"
    ],
    "wof:name":"Willcock Machine",
    "wof:placetype":"venue"
},
  "geometry": {"coordinates":[-79.20599365229999,43.1666259766],"type":"Point"}
}