{
  "type": "Feature",
  "properties": {
    "addr:full":"1 Lakeside Ch Knowlton QC J0E 1V0",
    "addr:housenumber":"1",
    "addr:postcode":"j0e 1v0",
    "addr:street":"Lakeside Ch Knowlton",
    "iso:country":"CA",
    "sg:address":"1 Lakeside Ch",
    "sg:city":"Knowlton",
    "sg:classifiers":[
        {
            "category":"Home & Garden",
            "subcategory":"Furniture",
            "type":"Retail Goods"
        }
    ],
    "sg:phone":"+1 450 242 0222",
    "sg:postcode":"J0E 1V0",
    "sg:province":"QC",
    "wof:name":"Interieurs Bousada Interiors",
    "wof:placetype":"venue"
},
  "geometry": {"coordinates":[-72.51050600000001,45.216763],"type":"Point"}
}