{
  "type": "Feature",
  "properties": {
    "iso:country":"CA",
    "sg:address":"794 Av Myrand",
    "sg:city":"Sainte-Foy",
    "sg:classifiers":[
        {
            "category":"Organizations",
            "subcategory":"Religious Organization",
            "type":"Services"
        }
    ],
    "sg:phone":"+1 418 683 1329",
    "sg:postcode":"G1V 2V2",
    "sg:province":"QC",
    "wof:name":"Centre Culturel Islamique DE",
    "wof:placetype":"venue"
},
  "geometry": {"coordinates":[-71.270927,46.789234],"type":"Point"}
}