{
  "type": "Feature",
  "properties": {
    "addr:full":"62 Rue Prud'Homme Mercier QC J6R 2N1",
    "addr:housenumber":"62",
    "addr:postcode":"j6r 2n1",
    "addr:street":"Rue Prud'Homme",
    "iso:country":"CA",
    "sg:address":"62 Rue Prud'Homme",
    "sg:city":"Mercier",
    "sg:classifiers":[
        {
            "category":"Autos & Motor Vehicles",
            "subcategory":"Auto Supplies",
            "type":"Retail Goods"
        }
    ],
    "sg:phone":"+1 450 691 6919",
    "sg:postcode":"J6R 2N1",
    "sg:province":"QC",
    "sg:tags":[
        "tire"
    ],
    "wof:name":"Laurent Bergevin Pneus Inc",
    "wof:placetype":"venue"
},
  "geometry": {"coordinates":[-73.73693799999999,45.314182],"type":"Point"}
}