{
  "type": "Feature",
  "properties": {
    "iso:country":"CA",
    "sg:address":"5000 Dufferin St # 211",
    "sg:city":"North York",
    "sg:classifiers":[
        {
            "category":"Education",
            "subcategory":"Special Training",
            "type":"Public Place"
        }
    ],
    "sg:phone":"+1 416 663 7177",
    "sg:postcode":"M3H 5T5",
    "sg:province":"ON",
    "sg:tags":[
        "instruction",
        "driving"
    ],
    "wof:name":"Karat Driving School",
    "wof:placetype":"venue"
},
  "geometry": {"coordinates":[-79.4701309204,43.7813606262],"type":"Point"}
}