{
  "type": "Feature",
  "properties": {
    "addr:full":"477 Rue Simard Saint-Ambroise QC G7P 2S4",
    "addr:housenumber":"477",
    "addr:postcode":"g7p 2s4",
    "addr:street":"Rue Simard",
    "iso:country":"CA",
    "sg:address":"477 Rue Simard",
    "sg:city":"Saint-Ambroise",
    "sg:classifiers":[
        {
            "category":"Health Services",
            "subcategory":"Doctor",
            "type":"Services"
        }
    ],
    "sg:phone":"+1 418 672 4141",
    "sg:postcode":"G7P 2S4",
    "sg:province":"QC",
    "sg:tags":[
        "clinic",
        "dentist"
    ],
    "wof:name":"Clinique Dentaire Cauchon",
    "wof:placetype":"venue"
},
  "geometry": {"coordinates":[-71.3236312866,48.5565071106],"type":"Point"}
}