{
  "type": "Feature",
  "properties": {
    "addr:full":"4830 Rue Jean Notre-Dame-Du-Mont-Carmel QC G0X 3J0",
    "addr:housenumber":"4830",
    "addr:postcode":"g0x 3j0",
    "addr:street":"Rue Jean",
    "iso:country":"CA",
    "sg:address":"4830 Rue Jean",
    "sg:city":"Notre-Dame-Du-Mont-Carmel",
    "sg:classifiers":[
        {
            "category":"Building & Trades",
            "subcategory":"Electrical",
            "type":"Services"
        }
    ],
    "sg:phone":"+1 819 537 3553",
    "sg:postcode":"G0X 3J0",
    "sg:province":"QC",
    "sg:tags":[
        "electric",
        "contractor"
    ],
    "wof:name":"Contact Electrique 2000",
    "wof:placetype":"venue"
},
  "geometry": {"coordinates":[-69.8557052612,47.4413299561],"type":"Point"}
}