{
  "type": "Feature",
  "properties": {
    "addr:full":"Dawson Creek BC V1G 2B9",
    "addr:postcode":"v1g 2b9",
    "iso:country":"CA",
    "sg:city":"Dawson Creek",
    "sg:classifiers":[
        {
            "category":"Personal",
            "subcategory":"Beauty Salon",
            "type":"Services"
        }
    ],
    "sg:phone":"+1 250 782 2919",
    "sg:postcode":"V1G 2B9",
    "sg:province":"BC",
    "wof:name":"Vogue Hair Styling",
    "wof:placetype":"venue"
},
  "geometry": {"coordinates":[-120.2290802,55.7584266663],"type":"Point"}
}