{
  "type": "Feature",
  "properties": {
    "addr:full":"34600 Moffat Ave Mission BC V2V 6R6",
    "addr:housenumber":"34600",
    "addr:postcode":"v2v 6r6",
    "addr:street":"Moffat Ave",
    "iso:country":"CA",
    "sg:address":"34600 Moffat Ave",
    "sg:city":"Mission",
    "sg:classifiers":[
        {
            "category":"Building & Trades",
            "subcategory":"Construction",
            "type":"Services"
        }
    ],
    "sg:phone":"+1 604 826 5568",
    "sg:postcode":"V2V 6R6",
    "sg:province":"BC",
    "sg:tags":[
        "dry wall",
        "contractor"
    ],
    "wof:name":"Troika Drywall",
    "wof:placetype":"venue"
},
  "geometry": {"coordinates":[-122.26448822,49.1509246826],"type":"Point"}
}