{
  "type": "Feature",
  "properties": {
    "addr:full":"Hwy 2 N Prince Albert SK S6V 5R5",
    "addr:postcode":"s6v 5r5",
    "addr:street":"Hwy 2 N",
    "iso:country":"CA",
    "sg:address":"Hwy 2 N",
    "sg:city":"Prince Albert",
    "sg:classifiers":[
        {
            "category":"Home & Garden",
            "subcategory":"Building Materials",
            "type":"Retail Goods"
        }
    ],
    "sg:phone":"+1 306 763 4228",
    "sg:postcode":"S6V 5R5",
    "sg:province":"SK",
    "sg:tags":[
        "lumber"
    ],
    "wof:name":"M & M Building Supplies Ltd",
    "wof:placetype":"venue"
},
  "geometry": {"coordinates":[-105.760109,53.198093],"type":"Point"}
}