{
  "type": "Feature",
  "properties": {
    "addr:full":"1433 Main St E Swan River MB R0L 1Z0",
    "addr:housenumber":"1433",
    "addr:postcode":"r0l 1z0",
    "addr:street":"Main St E Swan",
    "iso:country":"CA",
    "sg:address":"1433 Main St E",
    "sg:city":"Swan River",
    "sg:classifiers":[
        {
            "category":"Travel",
            "subcategory":"Hotels & Motels",
            "type":"Entertainment"
        }
    ],
    "sg:phone":"+1 204 734 4104",
    "sg:postcode":"R0L 1Z0",
    "sg:province":"MB",
    "wof:name":"Thunderhill Motel",
    "wof:placetype":"venue"
},
  "geometry": {"coordinates":[-101.254616,52.10693],"type":"Point"}
}