{
  "type": "Feature",
  "properties": {
    "addr:full":"North York ON M3H 5Z3",
    "addr:postcode":"m3h 5z3",
    "iso:country":"CA",
    "sg:city":"North York",
    "sg:classifiers":[
        {
            "category":"Wholesale",
            "subcategory":"Durable Goods & Equipment",
            "type":"Manufacturing & Wholesale Goods"
        }
    ],
    "sg:phone":"+1 416 630 5931",
    "sg:postcode":"M3H 5Z3",
    "sg:province":"ON",
    "sg:tags":[
        "exporter"
    ],
    "wof:name":"Diproinduca Canada Ltd",
    "wof:placetype":"venue"
},
  "geometry": {"coordinates":[-79.43584442140001,43.7445411682],"type":"Point"}
}