{
  "type": "Feature",
  "properties": {
    "addr:full":"877 Hamilton St Vancouver BC V6B 2R7",
    "addr:housenumber":"877",
    "addr:postcode":"bc v6b 2r7",
    "addr:street":"Hamilton St",
    "iso:country":"CA",
    "sg:address":"877 Hamilton St",
    "sg:city":"Vancouver",
    "sg:classifiers":[
        {
            "category":"Travel",
            "subcategory":"Hotels & Motels",
            "type":"Entertainment"
        }
    ],
    "sg:phone":"+1 604 646 0090",
    "sg:postcode":"V6B 2R7",
    "sg:province":"BC",
    "sg:tags":[
        "resort",
        "real estate"
    ],
    "wof:name":"West Coast Timeshare Executive",
    "wof:placetype":"venue"
},
  "geometry": {"coordinates":[-123.11718,49.278137],"type":"Point"}
}