{
  "type": "Feature",
  "properties": {
    "addr:full":"2323 Smith St Regina SK S4P 2P7",
    "addr:housenumber":"2323",
    "addr:postcode":"s4p 2p7",
    "addr:street":"Smith St",
    "iso:country":"CA",
    "sg:address":"2323 Smith St",
    "sg:city":"Regina",
    "sg:classifiers":[
        {
            "category":"Personal",
            "subcategory":"Beauty Salon",
            "type":"Services"
        }
    ],
    "sg:phone":"+1 306 757 8889",
    "sg:postcode":"S4P 2P7",
    "sg:province":"SK",
    "sg:tags":[
        "treatment",
        "skin"
    ],
    "wof:name":"Jane's Skin Care & Day Spa",
    "wof:placetype":"venue"
},
  "geometry": {"coordinates":[-104.61507400000001,50.441994],"type":"Point"}
}