{
  "type": "Feature",
  "properties": {
    "addr:full":"Burks Falls ON P0A 1C0",
    "addr:postcode":"p0a 1c0",
    "addr:street":"Burks",
    "iso:country":"CA",
    "sg:city":"Burks Falls",
    "sg:classifiers":[
        {
            "category":"Social Services",
            "type":"Services"
        }
    ],
    "sg:phone":"+1 705 382 1657",
    "sg:postcode":"P0A 1C0",
    "sg:province":"ON",
    "sg:tags":[
        "organization",
        "welfare"
    ],
    "wof:name":"Haydon Youth Svc",
    "wof:placetype":"venue"
},
  "geometry": {"coordinates":[-78.48088799999999,45.033714],"type":"Point"}
}