{
  "type": "Feature",
  "properties": {
    "iso:country":"CA",
    "sg:address":"661 Sandford Rd",
    "sg:city":"Uxbridge",
    "sg:classifiers":[
        {
            "category":"Health Services",
            "subcategory":"Medical Lab",
            "type":"Services"
        }
    ],
    "sg:phone":"+1 905 852 4894",
    "sg:postcode":"L9P 1R2",
    "sg:province":"ON",
    "sg:tags":[
        "laboratory"
    ],
    "wof:name":"Implant Restorations Inc",
    "wof:placetype":"venue"
},
  "geometry": {"coordinates":[-79.1485290527,44.1489181519],"type":"Point"}
}