{
  "type": "Feature",
  "properties": {
    "addr:full":"Mainland Lourdes NL A0N 1R0",
    "addr:postcode":"a0n 1r0",
    "iso:country":"CA",
    "sg:address":"Mainland",
    "sg:city":"Lourdes",
    "sg:classifiers":[
        {
            "category":"Education",
            "subcategory":"School",
            "type":"Public Place"
        }
    ],
    "sg:phone":"+1 709 642 5771",
    "sg:postcode":"A0N 1R0",
    "sg:province":"NL",
    "wof:name":"St Anne's Elementary School",
    "wof:placetype":"venue"
},
  "geometry": {"coordinates":[-59.0033531189,48.6470603943],"type":"Point"}
}