{
  "type": "Feature",
  "properties": {
    "addr:full":"8260 13th Ave Burnaby BC V3N 2G5",
    "addr:housenumber":"8260",
    "addr:postcode":"v3n 2g5",
    "addr:street":"13Th Ave",
    "iso:country":"CA",
    "sg:address":"8260 13th Ave",
    "sg:city":"Burnaby",
    "sg:classifiers":[
        {
            "category":"Education",
            "subcategory":"School",
            "type":"Public Place"
        }
    ],
    "sg:phone":"+1 604 522 1410",
    "sg:postcode":"V3N 2G5",
    "sg:province":"BC",
    "wof:name":"John Knox Christian School",
    "wof:placetype":"venue"
},
  "geometry": {"coordinates":[-122.92070770300001,49.2263374329],"type":"Point"}
}