{
  "type": "Feature",
  "properties": {
    "addr:full":"8400 Woodbine Ave Markham ON L3R 4N7",
    "addr:housenumber":"8400",
    "addr:postcode":"l3r 4n7",
    "addr:street":"Woodbine Ave",
    "iso:country":"CA",
    "sg:address":"8400 Woodbine Ave",
    "sg:city":"Markham",
    "sg:classifiers":[
        {
            "category":"Shopping",
            "subcategory":"Computers & Home Electronics",
            "type":"Retail Goods"
        }
    ],
    "sg:phone":"+1 905 475 1728",
    "sg:postcode":"L3R 4N7",
    "sg:province":"ON",
    "sg:tags":[
        "software"
    ],
    "wof:name":"Design Kitchens",
    "wof:placetype":"venue"
},
  "geometry": {"coordinates":[-79.3576583862,43.8475608826],"type":"Point"}
}