{
  "type": "Feature",
  "properties": {
    "addr:full":"Montreal QC H2L 4G4",
    "addr:postcode":"h2l 4g4",
    "iso:country":"CA",
    "sg:city":"Montreal",
    "sg:classifiers":[
        {
            "category":"Professional",
            "subcategory":"Business Services",
            "type":"Services"
        }
    ],
    "sg:phone":"+1 514 985 2291",
    "sg:postcode":"H2L 4G4",
    "sg:province":"QC",
    "sg:tags":[
        "translator",
        "interpreter"
    ],
    "wof:name":"Traductions M Arseneault Ltee",
    "wof:placetype":"venue"
},
  "geometry": {"coordinates":[-73.568031311,45.5188217163],"type":"Point"}
}