{
  "type": "Feature",
  "properties": {
    "addr:full":"450 Evans Ave Etobicoke ON M8W 2T5",
    "addr:housenumber":"450",
    "addr:postcode":"m8w 2t5",
    "addr:street":"Evans Ave",
    "iso:country":"CA",
    "sg:address":"450 Evans Ave",
    "sg:city":"Etobicoke",
    "sg:classifiers":[
        {
            "category":"Manufacturing",
            "subcategory":"Paper Products",
            "type":"Manufacturing & Wholesale Goods"
        }
    ],
    "sg:phone":"+1 416 255 8541",
    "sg:postcode":"M8W 2T5",
    "sg:province":"ON",
    "sg:tags":[
        "corrugated",
        "solid",
        "fiber",
        "box"
    ],
    "wof:name":"Norampac Inc",
    "wof:placetype":"venue"
},
  "geometry": {"coordinates":[-79.532196,43.61459],"type":"Point"}
}