{
  "type": "Feature",
  "properties": {
    "addr:full":"PO Box 99 Riviere Qui Barre AB T0G 1Y0",
    "addr:housenumber":"po box 99",
    "addr:postcode":"t0g 1y0",
    "addr:street":"Riviere Qui Barre",
    "iso:country":"CA",
    "sg:address":"PO Box 99",
    "sg:city":"Riviere Qui Barre",
    "sg:classifiers":[
        {
            "category":"Building & Trades",
            "subcategory":"Construction",
            "type":"Services"
        }
    ],
    "sg:phone":"+1 780 939 2178",
    "sg:postcode":"T0G 1Y0",
    "sg:province":"AB",
    "sg:tags":[
        "excavating",
        "contractor"
    ],
    "wof:name":"Lionel's Gradall Svc Ltd",
    "wof:placetype":"venue"
},
  "geometry": {"coordinates":[-113.843307495,53.7753105164],"type":"Point"}
}