{
  "type": "Feature",
  "properties": {
    "addr:full":"1200 Av Mcgill College # 1100 Montreal QC H3B 4G7",
    "addr:housenumber":"1200;# 1100",
    "addr:postcode":"h3b 4g7",
    "addr:street":"Av Mcgill College",
    "iso:country":"CA",
    "sg:address":"1200 Av Mcgill College # 1100",
    "sg:city":"Montreal",
    "sg:classifiers":[
        {
            "category":"Shopping",
            "subcategory":"Computers & Home Electronics",
            "type":"Retail Goods"
        }
    ],
    "sg:phone":"+1 514 871 8881",
    "sg:postcode":"H3B 4G7",
    "sg:province":"QC",
    "sg:tags":[
        "software"
    ],
    "wof:name":"Witness Systems",
    "wof:placetype":"venue"
},
  "geometry": {"coordinates":[-73.5703964233,45.5014419556],"type":"Point"}
}