{
  "type": "Feature",
  "properties": {
    "addr:full":"Estevan SK S4A 2A7",
    "addr:postcode":"s4a 2a7",
    "iso:country":"CA",
    "sg:city":"Estevan",
    "sg:classifiers":[
        {
            "category":"Mining & Drilling",
            "type":"Manufacturing & Wholesale Goods"
        }
    ],
    "sg:phone":"+1 306 634 8737",
    "sg:postcode":"S4A 2A7",
    "sg:province":"SK",
    "sg:tags":[
        "oil",
        "well"
    ],
    "wof:name":"Mc Gillicky Oilfield Constr",
    "wof:placetype":"venue"
},
  "geometry": {"coordinates":[-102.94879899999999,49.131908],"type":"Point"}
}