{
  "type": "Feature",
  "properties": {
    "iso:country":"CA",
    "sg:city":"Tatamagouche",
    "sg:classifiers":[
        {
            "category":"Building & Trades",
            "subcategory":"Construction",
            "type":"Services"
        }
    ],
    "sg:phone":"+1 902 657 3300",
    "sg:postcode":"B0K 1V0",
    "sg:province":"NS",
    "sg:tags":[
        "masonry",
        "contractor"
    ],
    "wof:name":"Northumberland Masonry & Const",
    "wof:placetype":"venue"
},
  "geometry": {"coordinates":[-63.291798,45.71233],"type":"Point"}
}