{
  "type": "Feature",
  "properties": {
    "addr:full":"Long Lake Newbrook AB T0A 2P0",
    "addr:postcode":"t0a 2p0",
    "iso:country":"CA",
    "sg:address":"Long Lake",
    "sg:city":"Newbrook",
    "sg:classifiers":[
        {
            "category":"Recreation",
            "type":"Entertainment"
        }
    ],
    "sg:phone":"+1 780 576 3959",
    "sg:postcode":"T0A 2P0",
    "sg:province":"AB",
    "sg:tags":[
        "provincial",
        "parks"
    ],
    "wof:name":"Long Lake Provincial Park Camp",
    "wof:placetype":"venue"
},
  "geometry": {"coordinates":[-112.94393920900001,54.326084137],"type":"Point"}
}