{
  "type": "Feature",
  "properties": {
    "addr:full":"114 2nd St W Lashburn SK S0M 1H0",
    "addr:housenumber":"114",
    "addr:postcode":"s0m 1h0",
    "addr:street":"2Nd St W Lashburn",
    "iso:country":"CA",
    "sg:address":"114 2nd St W",
    "sg:city":"Lashburn",
    "sg:classifiers":[
        {
            "category":"Health Services",
            "subcategory":"Doctor",
            "type":"Services"
        }
    ],
    "sg:phone":"+1 306 285 3515",
    "sg:postcode":"S0M 1H0",
    "sg:province":"SK",
    "sg:tags":[
        "physician",
        "surgeon"
    ],
    "wof:name":"Lashburn Medical Clinic",
    "wof:placetype":"venue"
},
  "geometry": {"coordinates":[-109.613274,53.123459],"type":"Point"}
}