{
  "type": "Feature",
  "properties": {
    "iso:country":"CA",
    "sg:address":"10024 100 St",
    "sg:city":"Peace River",
    "sg:classifiers":[
        {
            "category":"Shopping",
            "subcategory":"Jewelry",
            "type":"Retail Goods"
        }
    ],
    "sg:phone":"+1 780 624 3188",
    "sg:postcode":"T8S 1S3",
    "sg:province":"AB",
    "sg:tags":[
        "jeweler"
    ],
    "wof:name":"B & C Jewellers",
    "wof:placetype":"venue"
},
  "geometry": {"coordinates":[-117.290626526,56.2334060669],"type":"Point"}
}