{
  "type": "Feature",
  "properties": {
    "addr:full":"2207 41st Ave W Vancouver BC V6M 2A3",
    "addr:housenumber":"2207",
    "addr:postcode":"v6m 2a3",
    "addr:street":"41St Ave W",
    "iso:country":"CA",
    "sg:address":"2207 41st Ave W",
    "sg:city":"Vancouver",
    "sg:classifiers":[
        {
            "category":"Banks & Credit Unions",
            "subcategory":"Bank",
            "type":"Services"
        }
    ],
    "sg:phone":"+1 604 668 3704",
    "sg:postcode":"V6M 2A3",
    "sg:province":"BC",
    "wof:name":"Scotiabank",
    "wof:placetype":"venue"
},
  "geometry": {"coordinates":[-123.15863,49.234718],"type":"Point"}
}