{
  "type": "Feature",
  "properties": {
    "addr:full":"Kingston ON K7M 4W9",
    "addr:postcode":"k7m 4w9",
    "iso:country":"CA",
    "sg:city":"Kingston",
    "sg:classifiers":[
        {
            "category":"Recreation",
            "type":"Entertainment"
        }
    ],
    "sg:phone":"+1 613 549 5564",
    "sg:postcode":"K7M 4W9",
    "sg:province":"ON",
    "sg:tags":[
        "instruction",
        "yoga"
    ],
    "wof:name":"Yoga To Go",
    "wof:placetype":"venue"
},
  "geometry": {"coordinates":[-76.570251,44.246708],"type":"Point"}
}