{
  "type": "Feature",
  "properties": {
    "addr:full":"3251 River St Alvinston ON N0N 1A0",
    "addr:housenumber":"3251",
    "addr:postcode":"n0n 1a0",
    "addr:street":"River St",
    "iso:country":"CA",
    "sg:address":"3251 River St",
    "sg:city":"Alvinston",
    "sg:classifiers":[
        {
            "category":"Education",
            "subcategory":"Library",
            "type":"Public Place"
        }
    ],
    "sg:phone":"+1 519 898 2921",
    "sg:postcode":"N0N 1A0",
    "sg:province":"ON",
    "sg:tags":[
        "government"
    ],
    "wof:name":"Alvinston Library",
    "wof:placetype":"venue"
},
  "geometry": {"coordinates":[-81.86232757569999,42.8209648132],"type":"Point"}
}