{
  "type": "Feature",
  "properties": {
    "iso:country":"CA",
    "sg:address":"841 Wellington St",
    "sg:city":"London",
    "sg:classifiers":[
        {
            "category":"Shopping",
            "subcategory":"Florist",
            "type":"Retail Goods"
        }
    ],
    "sg:phone":"+1 519 680 2529",
    "sg:postcode":"N6A 3S6",
    "sg:province":"ON",
    "wof:name":"Forest of Flowers",
    "wof:placetype":"venue"
},
  "geometry": {"coordinates":[-81.252892,42.999409],"type":"Point"}
}