{
  "type": "Feature",
  "properties": {
    "iso:country":"CA",
    "sg:address":"40 Noranda Dr",
    "sg:city":"North York",
    "sg:classifiers":[
        {
            "category":"Banks & Credit Unions",
            "subcategory":"Investment Brokerage",
            "type":"Services"
        }
    ],
    "sg:phone":"+1 416 240 1100",
    "sg:postcode":"M6M 2X9",
    "sg:province":"ON",
    "wof:name":"LA Mega Investments",
    "wof:placetype":"venue"
},
  "geometry": {"coordinates":[-79.491065979,43.7007637024],"type":"Point"}
}