{
  "type": "Feature",
  "properties": {
    "iso:country":"CA",
    "sg:address":"7891 Cambie Rd",
    "sg:city":"Richmond",
    "sg:classifiers":[
        {
            "category":"Organizations",
            "subcategory":"Professional Association",
            "type":"Services"
        }
    ],
    "sg:phone":"+1 604 278 2142",
    "sg:postcode":"V6X 1J7",
    "sg:province":"BC",
    "sg:tags":[
        "club"
    ],
    "wof:name":"Richmond Rod & Gun Club",
    "wof:placetype":"venue"
},
  "geometry": {"coordinates":[-123.136292,49.184631],"type":"Point"}
}