{
  "type": "Feature",
  "properties": {
    "addr:full":"Montreal QC H3B 4N4",
    "addr:postcode":"h3b 4n4",
    "iso:country":"CA",
    "sg:city":"Montreal",
    "sg:classifiers":[
        {
            "category":"Professional",
            "subcategory":"Lawyer & Legal Services",
            "type":"Services"
        }
    ],
    "sg:phone":"+1 514 879 6900",
    "sg:postcode":"H3B 4N4",
    "sg:province":"QC",
    "sg:tags":[
        "attorney"
    ],
    "wof:name":"Loranger Marcoux",
    "wof:placetype":"venue"
},
  "geometry": {"coordinates":[-73.554642,45.516445],"type":"Point"}
}