{
  "type": "Feature",
  "properties": {
    "addr:full":"5377 Elcho Rd Wellandport ON L0R 2J0",
    "addr:housenumber":"5377",
    "addr:postcode":"l0r 2j0",
    "addr:street":"Elcho Rd",
    "iso:country":"CA",
    "sg:address":"5377 Elcho Rd",
    "sg:city":"Wellandport",
    "sg:classifiers":[
        {
            "category":"Wholesale",
            "subcategory":"Machinery & Supplies",
            "type":"Manufacturing & Wholesale Goods"
        }
    ],
    "sg:phone":"+1 905 386 6231",
    "sg:postcode":"L0R 2J0",
    "sg:province":"ON",
    "sg:tags":[
        "farm",
        "equipment"
    ],
    "wof:name":"Peninsula Farm Supply",
    "wof:placetype":"venue"
},
  "geometry": {"coordinates":[-79.4921417236,43.0161399841],"type":"Point"}
}