{
  "type": "Feature",
  "properties": {
    "addr:full":"2160 Headon Rd Burlington ON L7M 3W7",
    "addr:housenumber":"2160",
    "addr:postcode":"l7m 3w7",
    "addr:street":"Headon Rd",
    "iso:country":"CA",
    "sg:address":"2160 Headon Rd",
    "sg:city":"Burlington",
    "sg:classifiers":[
        {
            "category":"Social Services",
            "subcategory":"Child Care",
            "type":"Services"
        }
    ],
    "sg:phone":"+1 905 335 9908",
    "sg:postcode":"L7M 3W7",
    "sg:province":"ON",
    "wof:name":"B J's Day Care & Nursery Schl",
    "wof:placetype":"venue"
},
  "geometry": {"coordinates":[-79.8166885376,43.3787918091],"type":"Point"}
}