{
  "type": "Feature",
  "properties": {
    "addr:full":"201 Boul Cure-Labelle Laval QC H7V 2R9",
    "addr:housenumber":"201",
    "addr:postcode":"h7v 2r9",
    "addr:street":"Boul Cure-Labelle",
    "iso:country":"CA",
    "sg:address":"201 Boul Cure-Labelle",
    "sg:city":"Laval",
    "sg:classifiers":[
        {
            "category":"Banks & Credit Unions",
            "subcategory":"Bank",
            "type":"Services"
        }
    ],
    "sg:phone":"+1 450 687 9980",
    "sg:postcode":"H7V 2R9",
    "sg:province":"QC",
    "wof:name":"Banque Nationale Du Canada",
    "wof:placetype":"venue"
},
  "geometry": {"coordinates":[-73.73175048829999,45.5370063782],"type":"Point"}
}