{
  "type": "Feature",
  "properties": {
    "iso:country":"CA",
    "sg:address":"125 Avenue X S",
    "sg:city":"Saskatoon",
    "sg:classifiers":[
        {
            "category":"Building & Trades",
            "subcategory":"Construction",
            "type":"Services"
        }
    ],
    "sg:phone":"+1 306 933 1912",
    "sg:postcode":"S7M 3H2",
    "sg:province":"SK",
    "sg:tags":[
        "painter"
    ],
    "wof:name":"Ward's Painting",
    "wof:placetype":"venue"
},
  "geometry": {"coordinates":[-106.70754241900001,52.1287994385],"type":"Point"}
}