{
  "type": "Feature",
  "properties": {
    "addr:full":"210 Main St Radville SK S0C 2G0",
    "addr:housenumber":"210",
    "addr:postcode":"s0c 2g0",
    "addr:street":"Main St",
    "iso:country":"CA",
    "sg:address":"210 Main St",
    "sg:city":"Radville",
    "sg:classifiers":[
        {
            "category":"Professional",
            "subcategory":"Accounting & Tax Preparation",
            "type":"Services"
        }
    ],
    "sg:phone":"+1 306 869 4140",
    "sg:postcode":"S0C 2G0",
    "sg:province":"SK",
    "sg:tags":[
        "accountant"
    ],
    "wof:name":"Meyers Norris & Penny",
    "wof:placetype":"venue"
},
  "geometry": {"coordinates":[-104.294662,49.460075],"type":"Point"}
}