{
  "type": "Feature",
  "properties": {
    "addr:full":"2228 Hwy 97 Okanagan Falls BC V0H 1R0",
    "addr:housenumber":"2228",
    "addr:postcode":"v0h 1r0",
    "addr:street":"Hwy 97",
    "iso:country":"CA",
    "sg:address":"2228 Hwy 97",
    "sg:city":"Okanagan Falls",
    "sg:classifiers":[
        {
            "category":"Retail",
            "subcategory":"Animal Services",
            "type":"Services"
        }
    ],
    "sg:phone":"+1 250 497 5787",
    "sg:postcode":"V0H 1R0",
    "sg:province":"BC",
    "sg:tags":[
        "pet",
        "boarding",
        "sitting"
    ],
    "wof:name":"Calimor Kennels",
    "wof:placetype":"venue"
},
  "geometry": {"coordinates":[-119.571236,49.338634],"type":"Point"}
}