{
  "type": "Feature",
  "properties": {
    "addr:full":"629 Marentette Ave Windsor ON N9A 1Z3",
    "addr:housenumber":"629",
    "addr:postcode":"n9a 1z3",
    "addr:street":"Marentette Ave",
    "iso:country":"CA",
    "sg:address":"629 Marentette Ave",
    "sg:city":"Windsor",
    "sg:classifiers":[
        {
            "category":"Home & Garden",
            "subcategory":"Building Materials",
            "type":"Retail Goods"
        }
    ],
    "sg:phone":"+1 519 252 3910",
    "sg:postcode":"N9A 1Z3",
    "sg:province":"ON",
    "sg:tags":[
        "glass",
        "window",
        "plate"
    ],
    "wof:name":"Pez Glass",
    "wof:placetype":"venue"
},
  "geometry": {"coordinates":[-83.025505,42.317749],"type":"Point"}
}