{
  "type": "Feature",
  "properties": {
    "addr:full":"9 Symonds Rd Bedford NS B4B 1J5",
    "addr:housenumber":"9",
    "addr:postcode":"b4b 1j5",
    "addr:street":"Symonds Rd",
    "iso:country":"CA",
    "sg:address":"9 Symonds Rd",
    "sg:city":"Bedford",
    "sg:classifiers":[
        {
            "category":"Shopping",
            "type":"Retail Goods"
        }
    ],
    "sg:phone":"+1 902 832 3203",
    "sg:postcode":"B4B 1J5",
    "sg:province":"NS",
    "sg:tags":[
        "spa",
        "hot",
        "tub",
        "furniture"
    ],
    "wof:name":"Patio Perfect Plus",
    "wof:placetype":"venue"
},
  "geometry": {"coordinates":[-63.7000427246,44.726234436],"type":"Point"}
}