{
  "type": "Feature",
  "properties": {
    "addr:full":"7557 Edmonds St Burnaby BC V3N 1B5",
    "addr:housenumber":"7557",
    "addr:postcode":"v3n 1b5",
    "addr:street":"Edmonds St",
    "iso:country":"CA",
    "sg:address":"7557 Edmonds St",
    "sg:city":"Burnaby",
    "sg:classifiers":[
        {
            "category":"Bars & Pubs",
            "type":"Food & Drink"
        }
    ],
    "sg:phone":"+1 604 524 1119",
    "sg:postcode":"V3N 1B5",
    "sg:province":"BC",
    "wof:name":"Oliver Twist Neighbourhood Pub",
    "wof:placetype":"venue"
},
  "geometry": {"coordinates":[-122.94395400000001,49.222641],"type":"Point"}
}