{
  "type": "Feature",
  "properties": {
    "addr:full":"255 Boul Saint-Laurent E Louiseville QC J5V 1H5",
    "addr:housenumber":"255",
    "addr:postcode":"j5v 1h5",
    "addr:street":"Boul Saint-Laurent E",
    "iso:country":"CA",
    "sg:address":"255 Boul Saint-Laurent E",
    "sg:city":"Louiseville",
    "sg:classifiers":[
        {
            "category":"Health Services",
            "subcategory":"Doctor",
            "type":"Services"
        }
    ],
    "sg:phone":"+1 819 228 5577",
    "sg:postcode":"J5V 1H5",
    "sg:province":"QC",
    "sg:tags":[
        "clinic",
        "dentist"
    ],
    "wof:name":"Clinique Dentaire Chaput",
    "wof:placetype":"venue"
},
  "geometry": {"coordinates":[-72.934387,46.256428],"type":"Point"}
}