{
  "type": "Feature",
  "properties": {
    "addr:full":"45 Bethridge Rd Etobicoke ON M9W 1M9",
    "addr:housenumber":"45",
    "addr:postcode":"m9w 1m9",
    "addr:street":"Bethridge Rd",
    "iso:country":"CA",
    "sg:address":"45 Bethridge Rd",
    "sg:city":"Etobicoke",
    "sg:classifiers":[
        {
            "category":"Home & Garden",
            "subcategory":"Building Materials",
            "type":"Retail Goods"
        }
    ],
    "sg:phone":"+1 416 743 5384",
    "sg:postcode":"M9W 1M9",
    "sg:province":"ON",
    "sg:tags":[
        "lumber"
    ],
    "wof:name":"Hanford Lumber Ltd",
    "wof:placetype":"venue"
},
  "geometry": {"coordinates":[-79.5707626343,43.7083015442],"type":"Point"}
}