{
  "type": "Feature",
  "properties": {
    "addr:full":"PO Box 685 High Level AB T0H 1Z0",
    "addr:housenumber":"po;685",
    "addr:postcode":"t0h 1z0",
    "addr:street":"Box",
    "iso:country":"CA",
    "sg:address":"PO Box 685",
    "sg:city":"High Level",
    "sg:classifiers":[
        {
            "category":"Retail",
            "subcategory":"Repair Shop",
            "type":"Services"
        }
    ],
    "sg:phone":"+1 780 683 2392",
    "sg:postcode":"T0H 1Z0",
    "sg:province":"AB",
    "sg:tags":[
        "welding"
    ],
    "wof:name":"Lawrence's Welding Ltd",
    "wof:placetype":"venue"
},
  "geometry": {"coordinates":[-117.126091,58.51672],"type":"Point"}
}