{
  "type": "Feature",
  "properties": {
    "addr:full":"7385 Meadow Ave Burnaby BC V5J 4Z2",
    "addr:housenumber":"7385",
    "addr:postcode":"v5j 4z2",
    "addr:street":"Meadow Ave",
    "iso:country":"CA",
    "sg:address":"7385 Meadow Ave",
    "sg:city":"Burnaby",
    "sg:classifiers":[
        {
            "category":"Farming",
            "subcategory":"Nursery",
            "type":"Manufacturing & Wholesale Goods"
        }
    ],
    "sg:phone":"+1 604 430 4601",
    "sg:postcode":"V5J 4Z2",
    "sg:province":"BC",
    "sg:tags":[
        "greenhouse"
    ],
    "wof:name":"Meadowlands Horticultural Inc",
    "wof:placetype":"venue"
},
  "geometry": {"coordinates":[-122.97608200000001,49.203098],"type":"Point"}
}