{
  "type": "Feature",
  "properties": {
    "iso:country":"CA",
    "sg:address":"345 Rue Saint-Jean",
    "sg:city":"Longueuil",
    "sg:classifiers":[
        {
            "category":"Shopping",
            "subcategory":"Jewelry",
            "type":"Retail Goods"
        }
    ],
    "sg:phone":"+1 450 670 6760",
    "sg:postcode":"J4H 2X7",
    "sg:province":"QC",
    "sg:tags":[
        "watch"
    ],
    "wof:name":"Bijouterie Veronneau",
    "wof:placetype":"venue"
},
  "geometry": {"coordinates":[-73.507957,45.535805],"type":"Point"}
}