{
  "type": "Feature",
  "properties": {
    "addr:full":"Sherwood Park AB T8H 2A8",
    "addr:postcode":"t8h 2a8",
    "iso:country":"CA",
    "sg:city":"Sherwood Park",
    "sg:classifiers":[
        {
            "category":"Health Services",
            "subcategory":"Doctor",
            "type":"Services"
        }
    ],
    "sg:phone":"+1 780 449 6597",
    "sg:postcode":"T8H 2A8",
    "sg:province":"AB",
    "sg:tags":[
        "dentist"
    ],
    "wof:name":"Align Orthodontics",
    "wof:placetype":"venue"
},
  "geometry": {"coordinates":[-113.30996704099999,53.5428733826],"type":"Point"}
}