{
  "type": "Feature",
  "properties": {
    "addr:full":"1576 Parent Ave Windsor ON N8X 4J7",
    "addr:housenumber":"1576",
    "addr:postcode":"n8x 4j7",
    "addr:street":"Parent Ave",
    "iso:country":"CA",
    "sg:address":"1576 Parent Ave",
    "sg:city":"Windsor",
    "sg:classifiers":[
        {
            "category":"Organizations",
            "subcategory":"Labor Organization",
            "type":"Services"
        }
    ],
    "sg:phone":"+1 519 254 3543",
    "sg:postcode":"N8X 4J7",
    "sg:province":"ON",
    "wof:name":"Canadian Union of Pblc Employs",
    "wof:placetype":"venue"
},
  "geometry": {"coordinates":[-83.013718,42.303238],"type":"Point"}
}