{
  "type": "Feature",
  "properties": {
    "iso:country":"CA",
    "sg:address":"26 Densley Ave",
    "sg:city":"North York",
    "sg:classifiers":[
        {
            "category":"Professional",
            "subcategory":"Lawyer & Legal Services",
            "type":"Services"
        }
    ],
    "sg:phone":"+1 416 248 2002",
    "sg:postcode":"M6M 2R1",
    "sg:province":"ON",
    "sg:tags":[
        "attorney"
    ],
    "wof:name":"Litman, Charles",
    "wof:placetype":"venue"
},
  "geometry": {"coordinates":[-79.47416699999999,43.703621],"type":"Point"}
}