{
  "type": "Feature",
  "properties": {
    "iso:country":"CA",
    "sg:address":"1260 Howe St",
    "sg:city":"Vancouver",
    "sg:classifiers":[
        {
            "category":"Organizations",
            "subcategory":"Professional Association",
            "type":"Services"
        }
    ],
    "sg:phone":"+1 604 682 3243",
    "sg:postcode":"V6Z 1R5",
    "sg:province":"BC",
    "wof:name":"B'Nai B'Rith Manor",
    "wof:placetype":"venue"
},
  "geometry": {"coordinates":[-123.127952576,49.2770576477],"type":"Point"}
}