{
  "type": "Feature",
  "properties": {
    "addr:full":"4234 Rue Belanger Montreal QC H1T 1A3",
    "addr:housenumber":"4234",
    "addr:postcode":"h1t 1a3",
    "addr:street":"Rue Belanger",
    "iso:country":"CA",
    "sg:address":"4234 Rue Belanger",
    "sg:city":"Montreal",
    "sg:classifiers":[
        {
            "category":"Food & Beverages",
            "subcategory":"Groceries & Convenience Stores",
            "type":"Retail Goods"
        }
    ],
    "sg:phone":"+1 514 722 3191",
    "sg:postcode":"H1T 1A3",
    "sg:province":"QC",
    "wof:name":"Depanneur Rodrigue",
    "wof:placetype":"venue"
},
  "geometry": {"coordinates":[-73.5862503052,45.5659217834],"type":"Point"}
}