{
  "type": "Feature",
  "properties": {
    "addr:full":"Edmonton AB T6E 4W3",
    "addr:postcode":"t6e 4w3",
    "iso:country":"CA",
    "sg:city":"Edmonton",
    "sg:classifiers":[
        {
            "category":"Social Services",
            "subcategory":"Child Care",
            "type":"Services"
        }
    ],
    "sg:phone":"+1 780 439 7991",
    "sg:postcode":"T6E 4W3",
    "sg:province":"AB",
    "wof:name":"Montessori Play & Learn Ctr",
    "wof:placetype":"venue"
},
  "geometry": {"coordinates":[-113.50372299999999,53.513618],"type":"Point"}
}