{
  "type": "Feature",
  "properties": {
    "addr:full":"Saint-Isidore-DE-Laprairie QC J0L 2A0",
    "addr:postcode":"j0l 2a0",
    "iso:country":"CA",
    "sg:city":"Saint-Isidore-DE-Laprairie",
    "sg:classifiers":[
        {
            "category":"Government",
            "subcategory":"Office",
            "type":"Public Place"
        }
    ],
    "sg:phone":"+1 450 454 3919",
    "sg:postcode":"J0L 2A0",
    "sg:province":"QC",
    "sg:tags":[
        "village"
    ],
    "wof:name":"St Isidore DE Laprairie Mun",
    "wof:placetype":"venue"
},
  "geometry": {"coordinates":[-73.48807525629999,45.4174537659],"type":"Point"}
}