{
  "type": "Feature",
  "properties": {
    "iso:country":"CA",
    "sg:address":"5527 4 Ave NE",
    "sg:city":"Calgary",
    "sg:classifiers":[
        {
            "category":"Food & Beverages",
            "subcategory":"Specialty",
            "type":"Retail Goods"
        }
    ],
    "sg:phone":"+1 403 248 5838",
    "sg:postcode":"T2A 3X9",
    "sg:province":"AB",
    "sg:tags":[
        "health",
        "diet"
    ],
    "wof:name":"Gnld Distr",
    "wof:placetype":"venue"
},
  "geometry": {"coordinates":[-113.953689575,51.0563430786],"type":"Point"}
}