{
  "type": "Feature",
  "properties": {
    "addr:full":"Digby NS B0V 1A0",
    "addr:postcode":"b0v 1a0",
    "iso:country":"CA",
    "sg:city":"Digby",
    "sg:classifiers":[
        {
            "category":"Government",
            "subcategory":"Office",
            "type":"Public Place"
        }
    ],
    "sg:phone":"+1 902 245 6571",
    "sg:postcode":"B0V 1A0",
    "sg:province":"NS",
    "wof:name":"Canada Food Inspection Agency",
    "wof:placetype":"venue"
},
  "geometry": {"coordinates":[-66.09781646730001,44.4806213379],"type":"Point"}
}