{
  "type": "Feature",
  "properties": {
    "iso:country":"CA",
    "sg:address":"369 Rockland Rd",
    "sg:city":"Saint John",
    "sg:classifiers":[
        {
            "category":"Building & Trades",
            "subcategory":"Electrical",
            "type":"Services"
        }
    ],
    "sg:phone":"+1 506 635 5780",
    "sg:postcode":"E2K 3W3",
    "sg:province":"NB",
    "sg:tags":[
        "electric",
        "contractor"
    ],
    "wof:name":"Security Electric Ltd",
    "wof:placetype":"venue"
},
  "geometry": {"coordinates":[-66.063232,45.280636],"type":"Point"}
}