{
  "type": "Feature",
  "properties": {
    "iso:country":"CA",
    "sg:city":"Mississauga",
    "sg:classifiers":[
        {
            "category":"Retail",
            "subcategory":"Auto Repair",
            "type":"Services"
        }
    ],
    "sg:phone":"+1 905 542 3360",
    "sg:postcode":"L5N 6A3",
    "sg:province":"ON",
    "sg:tags":[
        "repairing",
        "automobile"
    ],
    "wof:name":"Aquitaine Auto Ctr",
    "wof:placetype":"venue"
},
  "geometry": {"coordinates":[-79.757156,43.595512],"type":"Point"}
}