{
  "type": "Feature",
  "properties": {
    "addr:full":"1112 River Rd Bear River NS B0S 1B0",
    "addr:housenumber":"1112",
    "addr:postcode":"b0s 1b0",
    "addr:street":"River Rd",
    "iso:country":"CA",
    "sg:address":"1112 River Rd",
    "sg:city":"Bear River",
    "sg:classifiers":[
        {
            "category":"Health Services",
            "subcategory":"Doctor",
            "type":"Services"
        }
    ],
    "sg:phone":"+1 902 467 3611",
    "sg:postcode":"B0S 1B0",
    "sg:province":"NS",
    "sg:tags":[
        "clinic"
    ],
    "wof:name":"Bear River & Community Health",
    "wof:placetype":"venue"
},
  "geometry": {"coordinates":[-65.65107,44.57341],"type":"Point"}
}