{
  "type": "Feature",
  "properties": {
    "addr:full":"1056 St Mary's Rd Winnipeg MB R2M 3S9",
    "addr:housenumber":"1056",
    "addr:postcode":"r2m 3s9",
    "addr:street":"St Mary'S Rd",
    "iso:country":"CA",
    "sg:address":"1056 St Mary's Rd",
    "sg:city":"Winnipeg",
    "sg:classifiers":[
        {
            "category":"Health Services",
            "subcategory":"Chiropractor",
            "type":"Services"
        }
    ],
    "sg:phone":"+1 204 257 7685",
    "sg:postcode":"R2M 3S9",
    "sg:province":"MB",
    "wof:name":"Dakota Chiropractic Office",
    "wof:placetype":"venue"
},
  "geometry": {"coordinates":[-97.1126937866,49.8376846313],"type":"Point"}
}