{
  "type": "Feature",
  "properties": {
    "iso:country":"CA",
    "sg:address":"1401 S 9th St",
    "sg:city":"Golden",
    "sg:classifiers":[
        {
            "category":"Organizations",
            "subcategory":"Community Association",
            "type":"Services"
        }
    ],
    "sg:phone":"+1 250 344 5465",
    "sg:postcode":"V0A 1H0",
    "sg:province":"BC",
    "sg:tags":[
        "club"
    ],
    "wof:name":"Golden Senior's Club",
    "wof:placetype":"venue"
},
  "geometry": {"coordinates":[-116.95386505099999,51.2962226868],"type":"Point"}
}