{
  "type": "Feature",
  "properties": {
    "iso:country":"CA",
    "sg:address":"103 Bruce St",
    "sg:city":"South Porcupine",
    "sg:classifiers":[
        {
            "category":"Health Services",
            "subcategory":"Chiropractor",
            "type":"Services"
        }
    ],
    "sg:phone":"+1 705 235 3386",
    "sg:postcode":"P0N 1H0",
    "sg:province":"ON",
    "wof:name":"Jarvensivu, Richard DC",
    "wof:placetype":"venue"
},
  "geometry": {"coordinates":[-81.20970153810001,48.4778404236],"type":"Point"}
}