{
  "type": "Feature",
  "properties": {
    "addr:full":"2400 King Rd King City ON L7B 1J6",
    "addr:housenumber":"2400",
    "addr:postcode":"l7b 1j6",
    "addr:street":"King Rd",
    "iso:country":"CA",
    "sg:address":"2400 King Rd",
    "sg:city":"King City",
    "sg:classifiers":[
        {
            "category":"Building & Trades",
            "subcategory":"Construction",
            "type":"Services"
        }
    ],
    "sg:phone":"+1 905 833 5088",
    "sg:postcode":"L7B 1J6",
    "sg:province":"ON",
    "sg:tags":[
        "home",
        "improvement"
    ],
    "wof:name":"M Kirkby Contracting",
    "wof:placetype":"venue"
},
  "geometry": {"coordinates":[-79.53359985349999,43.9274177551],"type":"Point"}
}