{
  "type": "Feature",
  "properties": {
    "addr:full":"107 Birch Crest Lane Burks Falls ON P0A 1C0",
    "addr:housenumber":"107",
    "addr:postcode":"p0a 1c0",
    "addr:street":"Birch Crest Lane",
    "iso:country":"CA",
    "sg:address":"107 Birch Crest Lane",
    "sg:city":"Burks Falls",
    "sg:classifiers":[
        {
            "category":"Travel",
            "subcategory":"Hotels & Motels",
            "type":"Entertainment"
        }
    ],
    "sg:phone":"+1 705 382 3136",
    "sg:postcode":"P0A 1C0",
    "sg:province":"ON",
    "sg:tags":[
        "resort"
    ],
    "wof:name":"Birch Crest Resort",
    "wof:placetype":"venue"
},
  "geometry": {"coordinates":[-84.3328781128,46.5224113464],"type":"Point"}
}