{
  "type": "Feature",
  "properties": {
    "addr:full":"25 Downing Dr E Lanigan SK S0K 2M0",
    "addr:housenumber":"25",
    "addr:postcode":"s0k 2m0",
    "addr:street":"Downing Dr E Lanigan",
    "iso:country":"CA",
    "sg:address":"25 Downing Dr E",
    "sg:city":"Lanigan",
    "sg:classifiers":[
        {
            "category":"Government",
            "subcategory":"Fire Station",
            "type":"Public Place"
        }
    ],
    "sg:phone":"+1 ",
    "sg:postcode":"S0K 2M0",
    "sg:province":"SK",
    "sg:tags":[
        "department"
    ],
    "wof:name":"Lanigan Fire Dept",
    "wof:placetype":"venue"
},
  "geometry": {"coordinates":[-105.02722199999999,51.850819],"type":"Point"}
}