{
  "type": "Feature",
  "properties": {
    "addr:full":"574 Queen S Paisley ON N0G 2N0",
    "addr:housenumber":"574",
    "addr:postcode":"n0g 2n0",
    "addr:street":"Queen S",
    "iso:country":"CA",
    "sg:address":"574 Queen S",
    "sg:city":"Paisley",
    "sg:classifiers":[
        {
            "category":"Banks & Credit Unions",
            "subcategory":"Bank",
            "type":"Services"
        }
    ],
    "sg:phone":"+1 519 353 5693",
    "sg:postcode":"N0G 2N0",
    "sg:province":"ON",
    "wof:name":"Royal Bank Financial Group",
    "wof:placetype":"venue"
},
  "geometry": {"coordinates":[-81.272774,44.305931],"type":"Point"}
}