{
  "type": "Feature",
  "properties": {
    "iso:country":"CA",
    "sg:address":"20407 Leslie St",
    "sg:city":"Queensville",
    "sg:classifiers":[
        {
            "category":"Shopping",
            "subcategory":"Hobbies, Toys, & Games",
            "type":"Retail Goods"
        }
    ],
    "sg:phone":"+1 905 478 8555",
    "sg:postcode":"L0G 1R0",
    "sg:province":"ON",
    "sg:tags":[
        "craft",
        "supply"
    ],
    "wof:name":"Coach House Creations",
    "wof:placetype":"venue"
},
  "geometry": {"coordinates":[-79.4498062134,44.1365318298],"type":"Point"}
}