{
  "type": "Feature",
  "properties": {
    "addr:full":"411 Av Roslyn Westmount QC H3Y 2T6",
    "addr:postcode":"h3y 2t6",
    "addr:street":"411 Av Roslyn",
    "iso:country":"CA",
    "sg:address":"411 Av Roslyn",
    "sg:city":"Westmount",
    "sg:classifiers":[
        {
            "category":"Organizations",
            "subcategory":"Religious Organization",
            "type":"Services"
        }
    ],
    "sg:phone":"+1 514 937 1009",
    "sg:postcode":"H3Y 2T6",
    "sg:province":"QC",
    "sg:tags":[
        "church"
    ],
    "wof:name":"Westmount Baptist Church",
    "wof:placetype":"venue"
},
  "geometry": {"coordinates":[-73.602638,45.480694],"type":"Point"}
}