{
  "type": "Feature",
  "properties": {
    "iso:country":"CA",
    "sg:address":"16216 Old Hwy No 3",
    "sg:city":"Bridgewater",
    "sg:classifiers":[
        {
            "category":"Retail",
            "subcategory":"Veterinary Services",
            "type":"Services"
        }
    ],
    "sg:phone":"+1 902 543 7255",
    "sg:postcode":"B4V 2W3",
    "sg:province":"NS",
    "sg:tags":[
        "veterinarian"
    ],
    "wof:name":"Mac Donald, Bill DVM",
    "wof:placetype":"venue"
},
  "geometry": {"coordinates":[-64.523033,44.380497],"type":"Point"}
}