{
  "type": "Feature",
  "properties": {
    "addr:full":"130 Perkins St Estevan SK S4A 2K1",
    "addr:housenumber":"130",
    "addr:postcode":"s4a 2k1",
    "addr:street":"Perkins St",
    "iso:country":"CA",
    "sg:address":"130 Perkins St",
    "sg:city":"Estevan",
    "sg:classifiers":[
        {
            "category":"Manufacturing",
            "subcategory":"Tools & Machinery",
            "type":"Manufacturing & Wholesale Goods"
        }
    ],
    "sg:phone":"+1 306 634 7212",
    "sg:postcode":"S4A 2K1",
    "sg:province":"SK",
    "sg:tags":[
        "machine",
        "shop"
    ],
    "wof:name":"Waterflood Service & Sales Ltd",
    "wof:placetype":"venue"
},
  "geometry": {"coordinates":[-102.974739,49.131561],"type":"Point"}
}