{
  "type": "Feature",
  "properties": {
    "addr:full":"Mont-Royal QC H3P 3H5",
    "addr:postcode":"h3p 3h5",
    "iso:country":"CA",
    "sg:city":"Mont-Royal",
    "sg:classifiers":[
        {
            "category":"Professional",
            "subcategory":"Research",
            "type":"Services"
        }
    ],
    "sg:phone":"+1 514 345 9877",
    "sg:postcode":"H3P 3H5",
    "sg:province":"QC",
    "sg:tags":[
        "development",
        "laboratory"
    ],
    "wof:name":"Procrea Bio Sciences Inc",
    "wof:placetype":"venue"
},
  "geometry": {"coordinates":[-73.6235733032,45.5228157043],"type":"Point"}
}