{
  "type": "Feature",
  "properties": {
    "iso:country":"CA",
    "sg:city":"Calgary",
    "sg:classifiers":[
        {
            "category":"Restaurant",
            "type":"Food & Drink"
        }
    ],
    "sg:phone":"+1 403 252 5666",
    "sg:postcode":"T2H 2H9",
    "sg:province":"AB",
    "wof:name":"Chinook Snack Bar & Deli",
    "wof:placetype":"venue"
},
  "geometry": {"coordinates":[-114.054039002,50.9983940125],"type":"Point"}
}