{
  "type": "Feature",
  "properties": {
    "addr:full":"Miramichi NB E1V 3C4",
    "addr:postcode":"e1v 3c4",
    "iso:country":"CA",
    "sg:city":"Miramichi",
    "sg:classifiers":[
        {
            "category":"Wholesale",
            "subcategory":"Auto Parts",
            "type":"Manufacturing & Wholesale Goods"
        }
    ],
    "sg:phone":"+1 506 627 1088",
    "sg:postcode":"E1V 3C4",
    "sg:province":"NB",
    "sg:tags":[
        "equipment",
        "truck"
    ],
    "wof:name":"Target Truck Ctr Inc",
    "wof:placetype":"venue"
},
  "geometry": {"coordinates":[-65.57638549799999,46.9911804199],"type":"Point"}
}