{
  "type": "Feature",
  "properties": {
    "iso:country":"CA",
    "sg:address":"872 Rue Principale",
    "sg:city":"Saint-Etienne-DE-Lauzon",
    "sg:classifiers":[
        {
            "category":"Health Services",
            "subcategory":"Clinic",
            "type":"Services"
        }
    ],
    "sg:phone":"+1 418 563 9501",
    "sg:postcode":"G6J 1A8",
    "sg:province":"QC",
    "sg:tags":[
        "aid",
        "first"
    ],
    "wof:name":"Medic",
    "wof:placetype":"venue"
},
  "geometry": {"coordinates":[-71.33404541020001,46.6393165588],"type":"Point"}
}