{
  "type": "Feature",
  "properties": {
    "addr:full":"2540 Main St London ON N6P 1P9",
    "addr:housenumber":"2540",
    "addr:postcode":"n6p 1p9",
    "addr:street":"Main St",
    "iso:country":"CA",
    "sg:address":"2540 Main St",
    "sg:city":"London",
    "sg:classifiers":[
        {
            "category":"Manufacturing",
            "subcategory":"Signs",
            "type":"Manufacturing & Wholesale Goods"
        }
    ],
    "sg:phone":"+1 519 652 8713",
    "sg:postcode":"N6P 1P9",
    "sg:province":"ON",
    "wof:name":"Braveheart Signs",
    "wof:placetype":"venue"
},
  "geometry": {"coordinates":[-81.298805,42.909763],"type":"Point"}
}