{
  "type": "Feature",
  "properties": {
    "addr:full":"37415 Talbot Line Shedden ON N0L 2E0",
    "addr:housenumber":"37415",
    "addr:postcode":"n0l 2e0",
    "addr:street":"Talbot Line",
    "iso:country":"CA",
    "sg:address":"37415 Talbot Line",
    "sg:city":"Shedden",
    "sg:classifiers":[
        {
            "category":"Home & Garden",
            "subcategory":"Household Appliances",
            "type":"Retail Goods"
        }
    ],
    "sg:phone":"+1 519 764 2934",
    "sg:postcode":"N0L 2E0",
    "sg:province":"ON",
    "sg:tags":[
        "refrigerator"
    ],
    "wof:name":"Don Silcox Appliances",
    "wof:placetype":"venue"
},
  "geometry": {"coordinates":[-81.3181304932,42.7672424316],"type":"Point"}
}