{
  "type": "Feature",
  "properties": {
    "addr:full":"70 Wellington St Brantford ON N3T 2L9",
    "addr:housenumber":"70",
    "addr:postcode":"n3t 2l9",
    "addr:street":"Wellington St",
    "iso:country":"CA",
    "sg:address":"70 Wellington St",
    "sg:city":"Brantford",
    "sg:classifiers":[
        {
            "category":"Government",
            "subcategory":"Office",
            "type":"Public Place"
        }
    ],
    "sg:phone":"+1 519 752 7828",
    "sg:postcode":"N3T 2L9",
    "sg:province":"ON",
    "wof:name":"Ontario Small Claims Court",
    "wof:placetype":"venue"
},
  "geometry": {"coordinates":[-80.26411400000001,43.141338],"type":"Point"}
}