{
  "type": "Feature",
  "properties": {
    "addr:full":"10 George St Hamilton ON L8P 1C8",
    "addr:housenumber":"10",
    "addr:postcode":"l8p 1c8",
    "addr:street":"George St",
    "iso:country":"CA",
    "sg:address":"10 George St",
    "sg:city":"Hamilton",
    "sg:classifiers":[
        {
            "category":"Organizations",
            "subcategory":"Community Association",
            "type":"Services"
        }
    ],
    "sg:phone":"+1 905 540 4004",
    "sg:postcode":"L8P 1C8",
    "sg:province":"ON",
    "sg:tags":[
        "club"
    ],
    "wof:name":"Canadian Motoring Guild",
    "wof:placetype":"venue"
},
  "geometry": {"coordinates":[-79.87455,43.257355],"type":"Point"}
}