{
  "type": "Feature",
  "properties": {
    "iso:country":"CA",
    "sg:address":"134 Sherwood Ave",
    "sg:city":"London",
    "sg:classifiers":[
        {
            "category":"Professional",
            "subcategory":"Business Services",
            "type":"Services"
        }
    ],
    "sg:phone":"+1 519 432 1129",
    "sg:postcode":"N6A 2E5",
    "sg:province":"ON",
    "sg:tags":[
        "repossessing"
    ],
    "wof:name":"R W Hughwa & Assoc Inc",
    "wof:placetype":"venue"
},
  "geometry": {"coordinates":[-81.265106,43.002922],"type":"Point"}
}