{
  "type": "Feature",
  "properties": {
    "addr:full":"233 Wolf Ave Winnipeg MB R3C 2E6",
    "addr:housenumber":"233",
    "addr:postcode":"r3c 2e6",
    "addr:street":"Wolf Ave",
    "iso:country":"CA",
    "sg:address":"233 Wolf Ave",
    "sg:city":"Winnipeg",
    "sg:classifiers":[
        {
            "category":"Building & Trades",
            "subcategory":"Construction",
            "type":"Services"
        }
    ],
    "sg:phone":"+1 204 694 4506",
    "sg:postcode":"R3C 2E6",
    "sg:province":"MB",
    "sg:tags":[
        "sewer",
        "contractor"
    ],
    "wof:name":"Al-San Underground Ltd",
    "wof:placetype":"venue"
},
  "geometry": {"coordinates":[-97.140739,49.899426],"type":"Point"}
}