{
  "type": "Feature",
  "properties": {
    "addr:full":"16507 116 Ave NW Edmonton AB T5M 3V1",
    "addr:housenumber":"16507",
    "addr:postcode":"t5m 3v1",
    "addr:street":"116 Ave Nw",
    "iso:country":"CA",
    "sg:address":"16507 116 Ave NW",
    "sg:city":"Edmonton",
    "sg:classifiers":[
        {
            "category":"Wholesale",
            "subcategory":"Drugs",
            "type":"Manufacturing & Wholesale Goods"
        }
    ],
    "sg:phone":"+1 780 454 6099",
    "sg:postcode":"T5M 3V1",
    "sg:province":"AB",
    "sg:tags":[
        "pharmaceutical",
        "product"
    ],
    "wof:name":"Bercom Sales Ltd",
    "wof:placetype":"venue"
},
  "geometry": {"coordinates":[-113.60817,53.565273],"type":"Point"}
}