{
  "type": "Feature",
  "properties": {
    "addr:full":"73 Balsam St S Timmins ON P4N 2C9",
    "addr:housenumber":"73",
    "addr:postcode":"p4n 2c9",
    "addr:street":"Balsam St S",
    "iso:country":"CA",
    "sg:address":"73 Balsam St S",
    "sg:city":"Timmins",
    "sg:classifiers":[
        {
            "category":"Personal",
            "subcategory":"Beauty Salon",
            "type":"Services"
        }
    ],
    "sg:phone":"+1 705 267 3733",
    "sg:postcode":"P4N 2C9",
    "sg:province":"ON",
    "wof:name":"Classic Esthetics",
    "wof:placetype":"venue"
},
  "geometry": {"coordinates":[-81.331001,48.47456],"type":"Point"}
}