{
  "type": "Feature",
  "properties": {
    "addr:full":"3500 Dufferin St # 306 North York ON M3K 1N2",
    "addr:housenumber":"3500",
    "addr:postcode":"m3k 1n2",
    "addr:street":"Dufferin St # 306",
    "iso:country":"CA",
    "sg:address":"3500 Dufferin St # 306",
    "sg:city":"North York",
    "sg:classifiers":[
        {
            "category":"Personal",
            "type":"Services"
        }
    ],
    "sg:phone":"+1 416 783 7712",
    "sg:postcode":"M3K 1N2",
    "sg:province":"ON",
    "sg:tags":[
        "therapist",
        "massage"
    ],
    "wof:name":"Yorkdale Massage Therapy",
    "wof:placetype":"venue"
},
  "geometry": {"coordinates":[-79.45825958250001,43.7291717529],"type":"Point"}
}