{
  "type": "Feature",
  "properties": {
    "iso:country":"CA",
    "sg:city":"Cornwall",
    "sg:classifiers":[
        {
            "category":"Manufacturing",
            "subcategory":"Signs",
            "type":"Manufacturing & Wholesale Goods"
        }
    ],
    "sg:phone":"+1 613 938 2298",
    "sg:postcode":"K6H 5R5",
    "sg:province":"ON",
    "wof:name":"Dave's Reliable Signs",
    "wof:placetype":"venue"
},
  "geometry": {"coordinates":[-74.6926574707,45.065448761],"type":"Point"}
}