{
  "type": "Feature",
  "properties": {
    "addr:full":"436 Rue Lindsay Drummondville QC J2B 1G6",
    "addr:housenumber":"436",
    "addr:postcode":"j2b 1g6",
    "addr:street":"Rue Lindsay",
    "iso:country":"CA",
    "sg:address":"436 Rue Lindsay",
    "sg:city":"Drummondville",
    "sg:classifiers":[
        {
            "category":"Government",
            "subcategory":"Office",
            "type":"Public Place"
        }
    ],
    "sg:phone":"+1 819 477 2230",
    "sg:postcode":"J2B 1G6",
    "sg:province":"QC",
    "sg:tags":[
        "village"
    ],
    "wof:name":"Drummond Regionale DE Comte",
    "wof:placetype":"venue"
},
  "geometry": {"coordinates":[-72.48360443120001,45.8807029724],"type":"Point"}
}