{
  "type": "Feature",
  "properties": {
    "iso:country":"CA",
    "sg:address":"664 Yonge St",
    "sg:city":"Toronto",
    "sg:classifiers":[
        {
            "category":"Shopping",
            "subcategory":"Music",
            "type":"Retail Goods"
        }
    ],
    "sg:phone":"+1 416 975 1829",
    "sg:postcode":"M4Y 2A6",
    "sg:province":"ON",
    "sg:tags":[
        "compact",
        "record",
        "disc",
        "tape"
    ],
    "wof:name":"Monster Records",
    "wof:placetype":"venue"
},
  "geometry": {"coordinates":[-79.3856430054,43.6670684814],"type":"Point"}
}