{
  "type": "Feature",
  "properties": {
    "addr:full":"Mississauga ON L5T 1Y5",
    "addr:postcode":"l5t 1y5",
    "iso:country":"CA",
    "sg:city":"Mississauga",
    "sg:classifiers":[
        {
            "category":"Wholesale",
            "subcategory":"Drugs",
            "type":"Manufacturing & Wholesale Goods"
        }
    ],
    "sg:phone":"+1 905 670 1760",
    "sg:postcode":"L5T 1Y5",
    "sg:province":"ON",
    "sg:tags":[
        "pharmaceutical",
        "product"
    ],
    "wof:name":"Berna Products",
    "wof:placetype":"venue"
},
  "geometry": {"coordinates":[-79.6547622681,43.6629104614],"type":"Point"}
}