{
  "type": "Feature",
  "properties": {
    "addr:full":"Sainte-Julie QC J3E 1Y1",
    "addr:postcode":"j3e 1y1",
    "iso:country":"CA",
    "sg:city":"Sainte-Julie",
    "sg:classifiers":[
        {
            "category":"Manufacturing",
            "subcategory":"Printing",
            "type":"Manufacturing & Wholesale Goods"
        }
    ],
    "sg:phone":"+1 450 922 1243",
    "sg:postcode":"J3E 1Y1",
    "sg:province":"QC",
    "sg:tags":[
        "printer"
    ],
    "wof:name":"Imprimerie Couleur Expert",
    "wof:placetype":"venue"
},
  "geometry": {"coordinates":[-73.3210906982,45.6039085388],"type":"Point"}
}