{
  "type": "Feature",
  "properties": {
    "addr:full":"Calgary AB T2H 0R5",
    "addr:postcode":"t2h 0r5",
    "iso:country":"CA",
    "sg:city":"Calgary",
    "sg:classifiers":[
        {
            "category":"Restaurant",
            "type":"Food & Drink"
        }
    ],
    "sg:phone":"+1 403 253 6733",
    "sg:postcode":"T2H 0R5",
    "sg:province":"AB",
    "sg:tags":[
        "caterer"
    ],
    "wof:name":"Bow Catering",
    "wof:placetype":"venue"
},
  "geometry": {"coordinates":[-114.061584473,50.996383667],"type":"Point"}
}