{
  "type": "Feature",
  "properties": {
    "addr:full":"352 Martello Rd Saint John NB E2M 2A2",
    "addr:housenumber":"352",
    "addr:postcode":"e2m 2a2",
    "addr:street":"Martello Rd",
    "iso:country":"CA",
    "sg:address":"352 Martello Rd",
    "sg:city":"Saint John",
    "sg:classifiers":[
        {
            "category":"Building & Trades",
            "subcategory":"Construction",
            "type":"Services"
        }
    ],
    "sg:phone":"+1 506 847 4498",
    "sg:postcode":"E2M 2A2",
    "sg:province":"NB",
    "sg:tags":[
        "well",
        "drilling"
    ],
    "wof:name":"Short's Well Drilling Ltd",
    "wof:placetype":"venue"
},
  "geometry": {"coordinates":[-66.075050354,45.2536773682],"type":"Point"}
}