{
  "type": "Feature",
  "properties": {
    "addr:full":"Brossard QC J4Z 2K8",
    "addr:postcode":"j4z 2k8",
    "iso:country":"CA",
    "sg:city":"Brossard",
    "sg:classifiers":[
        {
            "category":"Social Services",
            "subcategory":"Child Care",
            "type":"Services"
        }
    ],
    "sg:phone":"+1 450 656 0330",
    "sg:postcode":"J4Z 2K8",
    "sg:province":"QC",
    "wof:name":"Centre DE Jour DE Brossard",
    "wof:placetype":"venue"
},
  "geometry": {"coordinates":[-73.46573600000001,45.470318],"type":"Point"}
}