{
  "type": "Feature",
  "properties": {
    "addr:full":"308 Canyon Close Canmore AB T1W 1H4",
    "addr:housenumber":"308",
    "addr:postcode":"t1w 1h4",
    "addr:street":"Canyon Close",
    "iso:country":"CA",
    "sg:address":"308 Canyon Close",
    "sg:city":"Canmore",
    "sg:classifiers":[
        {
            "category":"Retail",
            "subcategory":"Repair Shop",
            "type":"Services"
        }
    ],
    "sg:phone":"+1 403 678 6080",
    "sg:postcode":"T1W 1H4",
    "sg:province":"AB",
    "sg:tags":[
        "repairing",
        "piano",
        "refinishing"
    ],
    "wof:name":"Mountain Melodies",
    "wof:placetype":"venue"
},
  "geometry": {"coordinates":[-115.32616400000001,51.08292],"type":"Point"}
}