{
  "type": "Feature",
  "properties": {
    "addr:full":"Toronto ON M5C 1T4",
    "addr:postcode":"m5c 1t4",
    "iso:country":"CA",
    "sg:city":"Toronto",
    "sg:classifiers":[
        {
            "category":"Banks & Credit Unions",
            "subcategory":"Investment Brokerage",
            "type":"Services"
        }
    ],
    "sg:phone":"+1 416 366 2931",
    "sg:postcode":"M5C 1T4",
    "sg:province":"ON",
    "sg:tags":[
        "advisory",
        "financial"
    ],
    "wof:name":"Canadian General Investments",
    "wof:placetype":"venue"
},
  "geometry": {"coordinates":[-79.3785247803,43.6502113342],"type":"Point"}
}