{
  "type": "Feature",
  "properties": {
    "addr:full":"7 Keefer Crt Hamilton ON L8E 4V4",
    "addr:housenumber":"7",
    "addr:postcode":"l8e 4v4",
    "addr:street":"Keefer Crt",
    "iso:country":"CA",
    "sg:address":"7 Keefer Crt",
    "sg:city":"Hamilton",
    "sg:classifiers":[
        {
            "category":"Building & Trades",
            "subcategory":"Construction",
            "type":"Services"
        }
    ],
    "sg:phone":"+1 905 578 6277",
    "sg:postcode":"L8E 4V4",
    "sg:province":"ON",
    "sg:tags":[
        "elevator"
    ],
    "wof:name":"Otis Canada Inc",
    "wof:placetype":"venue"
},
  "geometry": {"coordinates":[-79.76169586180001,43.245967865],"type":"Point"}
}