{
  "type": "Feature",
  "properties": {
    "addr:full":"127 Broadway St Tillsonburg ON N4G 3P7",
    "addr:housenumber":"127",
    "addr:postcode":"n4g 3p7",
    "addr:street":"Broadway St",
    "iso:country":"CA",
    "sg:address":"127 Broadway St",
    "sg:city":"Tillsonburg",
    "sg:classifiers":[
        {
            "category":"Shopping",
            "subcategory":"Clothing, Apparel, & Fashions",
            "type":"Retail Goods"
        }
    ],
    "sg:phone":"+1 519 842 2121",
    "sg:postcode":"N4G 3P7",
    "sg:province":"ON",
    "sg:tags":[
        "furnishing"
    ],
    "wof:name":"Brian Bennett Men's Clothier",
    "wof:placetype":"venue"
},
  "geometry": {"coordinates":[-80.727768,42.860355],"type":"Point"}
}