{
  "type": "Feature",
  "properties": {
    "addr:full":"Les Eboulements QC G0A 2M0",
    "addr:postcode":"g0a 2m0",
    "iso:country":"CA",
    "sg:city":"Les Eboulements",
    "sg:classifiers":[
        {
            "category":"Wholesale",
            "subcategory":"Seafood",
            "type":"Manufacturing & Wholesale Goods"
        }
    ],
    "sg:phone":"+1 418 635 2394",
    "sg:postcode":"G0A 2M0",
    "sg:province":"QC",
    "sg:tags":[
        "hatchery",
        "fish"
    ],
    "wof:name":"Pisciculture Smith",
    "wof:placetype":"venue"
},
  "geometry": {"coordinates":[-70.35158538819999,47.4807739258],"type":"Point"}
}