{
  "type": "Feature",
  "properties": {
    "addr:full":"4135 Teakwood Dr Mississauga ON L5C 3L4",
    "addr:housenumber":"4135",
    "addr:postcode":"l5c 3l4",
    "addr:street":"Teakwood Dr",
    "iso:country":"CA",
    "sg:address":"4135 Teakwood Dr",
    "sg:city":"Mississauga",
    "sg:classifiers":[
        {
            "category":"Shopping",
            "subcategory":"Computers & Home Electronics",
            "type":"Retail Goods"
        }
    ],
    "sg:phone":"+1 905 897 3085",
    "sg:postcode":"L5C 3L4",
    "sg:province":"ON",
    "sg:tags":[
        "equipment",
        "television",
        "electronic",
        "supply"
    ],
    "wof:name":"Gwen Electronic Svc",
    "wof:placetype":"venue"
},
  "geometry": {"coordinates":[-79.66194915769999,43.5757789612],"type":"Point"}
}