{
  "type": "Feature",
  "properties": {
    "addr:full":"3115 Lenworth Dr Mississauga ON L4X 2G5",
    "addr:housenumber":"3115",
    "addr:postcode":"l4x 2g5",
    "addr:street":"Lenworth Dr",
    "iso:country":"CA",
    "sg:address":"3115 Lenworth Dr",
    "sg:city":"Mississauga",
    "sg:classifiers":[
        {
            "category":"Manufacturing",
            "subcategory":"Glass & Minerals",
            "type":"Manufacturing & Wholesale Goods"
        }
    ],
    "sg:phone":"+1 905 624 3391",
    "sg:postcode":"L4X 2G5",
    "sg:province":"ON",
    "sg:tags":[
        "bottle",
        "plastic"
    ],
    "wof:name":"Richards Packaging Inc",
    "wof:placetype":"venue"
},
  "geometry": {"coordinates":[-79.5749053955,43.6225090027],"type":"Point"}
}