{
  "type": "Feature",
  "properties": {
    "addr:full":"11811 Meridian St NE Edmonton AB T6S 1A3",
    "addr:housenumber":"11811",
    "addr:postcode":"t6s 1a3",
    "addr:street":"Meridian St Ne",
    "iso:country":"CA",
    "sg:address":"11811 Meridian St NE",
    "sg:city":"Edmonton",
    "sg:classifiers":[
        {
            "category":"Manufacturing",
            "subcategory":"Metals",
            "type":"Manufacturing & Wholesale Goods"
        }
    ],
    "sg:phone":"+1 780 472 6806",
    "sg:postcode":"T6S 1A3",
    "sg:province":"AB",
    "sg:tags":[
        "barrels",
        "drum"
    ],
    "wof:name":"Great Western Containers Inc",
    "wof:placetype":"venue"
},
  "geometry": {"coordinates":[-113.343895,53.571762],"type":"Point"}
}