{
  "type": "Feature",
  "properties": {
    "addr:full":"271 Jevlan Dr Woodbridge ON L4L 8A4",
    "addr:housenumber":"271",
    "addr:postcode":"l4l 8a4",
    "addr:street":"Jevlan Dr",
    "iso:country":"CA",
    "sg:address":"271 Jevlan Dr",
    "sg:city":"Woodbridge",
    "sg:classifiers":[
        {
            "category":"Building & Trades",
            "subcategory":"Construction",
            "type":"Services"
        }
    ],
    "sg:phone":"+1 905 851 5950",
    "sg:postcode":"L4L 8A4",
    "sg:province":"ON",
    "sg:tags":[
        "millwright"
    ],
    "wof:name":"Jevlan Industrial Mechanics",
    "wof:placetype":"venue"
},
  "geometry": {"coordinates":[-79.5478973389,43.800743103],"type":"Point"}
}