{
  "type": "Feature",
  "properties": {
    "addr:full":"48 Rue Girouard Victoriaville QC G6P 5S8",
    "addr:housenumber":"48",
    "addr:postcode":"g6p 5s8",
    "addr:street":"Rue Girouard",
    "iso:country":"CA",
    "sg:address":"48 Rue Girouard",
    "sg:city":"Victoriaville",
    "sg:classifiers":[
        {
            "category":"Food & Beverages",
            "subcategory":"Groceries & Convenience Stores",
            "type":"Retail Goods"
        }
    ],
    "sg:phone":"+1 819 357 2792",
    "sg:postcode":"G6P 5S8",
    "sg:province":"QC",
    "wof:name":"Depanneur Le Garde Manger Inc",
    "wof:placetype":"venue"
},
  "geometry": {"coordinates":[-71.93349499999999,46.050613],"type":"Point"}
}