{
  "type": "Feature",
  "properties": {
    "addr:full":"4870 51 St # 200 Camrose AB T4V 1S1",
    "addr:housenumber":"4870",
    "addr:postcode":"t4v 1s1",
    "addr:street":"51 St # 200",
    "iso:country":"CA",
    "sg:address":"4870 51 St # 200",
    "sg:city":"Camrose",
    "sg:classifiers":[
        {
            "category":"Professional",
            "subcategory":"Lawyer & Legal Services",
            "type":"Services"
        }
    ],
    "sg:phone":"+1 780 672 3181",
    "sg:postcode":"T4V 1S1",
    "sg:province":"AB",
    "sg:tags":[
        "attorney"
    ],
    "wof:name":"Andreassen Olson Borth",
    "wof:placetype":"venue"
},
  "geometry": {"coordinates":[-112.827179,53.020256],"type":"Point"}
}