{
  "type": "Feature",
  "properties": {
    "addr:full":"205 the Queensway S Keswick ON L4P 2A3",
    "addr:housenumber":"205",
    "addr:postcode":"l4p 2a3",
    "addr:street":"The Queensway S",
    "iso:country":"CA",
    "sg:address":"205 the Queensway S",
    "sg:city":"Keswick",
    "sg:classifiers":[
        {
            "category":"Food & Beverages",
            "subcategory":"Groceries & Convenience Stores",
            "type":"Retail Goods"
        }
    ],
    "sg:phone":"+1 905 989 9909",
    "sg:postcode":"L4P 2A3",
    "sg:province":"ON",
    "sg:tags":[
        "grocer"
    ],
    "wof:name":"Queensway Marketplace",
    "wof:placetype":"venue"
},
  "geometry": {"coordinates":[-79.4654312134,44.2304573059],"type":"Point"}
}