{
  "type": "Feature",
  "properties": {
    "addr:full":"4060 Lillian St Hanmer ON P3P 1A2",
    "addr:housenumber":"4060",
    "addr:postcode":"p3p 1a2",
    "addr:street":"Lillian St",
    "iso:country":"CA",
    "sg:address":"4060 Lillian St",
    "sg:city":"Hanmer",
    "sg:classifiers":[
        {
            "category":"Freight",
            "type":"Transportation"
        }
    ],
    "sg:phone":"+1 705 969 2214",
    "sg:postcode":"P3P 1A2",
    "sg:province":"ON",
    "sg:tags":[
        "trucking"
    ],
    "wof:name":"Fern Jutras & Sons Trucking",
    "wof:placetype":"venue"
},
  "geometry": {"coordinates":[-81.00934599999999,46.639637],"type":"Point"}
}