{
  "type": "Feature",
  "properties": {
    "iso:country":"CA",
    "sg:address":"PO Box 1150",
    "sg:city":"Vulcan",
    "sg:classifiers":[
        {
            "category":"Farming",
            "subcategory":"Nursery",
            "type":"Manufacturing & Wholesale Goods"
        }
    ],
    "sg:phone":"+1 403 485 6708",
    "sg:postcode":"T0L 2B0",
    "sg:province":"AB",
    "sg:tags":[
        "greenhouse"
    ],
    "wof:name":"Markert Seeds Ltd",
    "wof:placetype":"venue"
},
  "geometry": {"coordinates":[-113.258178711,50.3973388672],"type":"Point"}
}