{
  "type": "Feature",
  "properties": {
    "addr:full":"2070 Peninsula Ucluelet BC V0R 3A0",
    "addr:housenumber":"2070",
    "addr:postcode":"bc v0r 3a0",
    "addr:street":"Peninsula",
    "iso:country":"CA",
    "sg:address":"2070 Peninsula",
    "sg:city":"Ucluelet",
    "sg:classifiers":[
        {
            "category":"Government",
            "subcategory":"Office",
            "type":"Public Place"
        }
    ],
    "sg:phone":"+1 250 726 7133",
    "sg:postcode":"V0R 3A0",
    "sg:province":"BC",
    "sg:tags":[
        "village"
    ],
    "wof:name":"Ucluelet Works Dept",
    "wof:placetype":"venue"
},
  "geometry": {"coordinates":[-125.542610169,48.9380264282],"type":"Point"}
}