{
  "type": "Feature",
  "properties": {
    "addr:full":"533 Rte 315 Montpellier QC J0V 1M0",
    "addr:housenumber":"533",
    "addr:postcode":"j0v 1m0",
    "addr:street":"Rte 315",
    "iso:country":"CA",
    "sg:address":"533 Rte 315",
    "sg:city":"Montpellier",
    "sg:classifiers":[
        {
            "category":"Travel",
            "subcategory":"Hotels & Motels",
            "type":"Entertainment"
        }
    ],
    "sg:phone":"+1 819 428 2827",
    "sg:postcode":"J0V 1M0",
    "sg:province":"QC",
    "wof:name":"Auberge Viceroy",
    "wof:placetype":"venue"
},
  "geometry": {"coordinates":[-75.137726,45.860512],"type":"Point"}
}