{
  "type": "Feature",
  "properties": {
    "addr:full":"28 Evenwood Ave Scarborough ON M1C 4T8",
    "addr:housenumber":"28",
    "addr:postcode":"m1c 4t8",
    "addr:street":"Evenwood Ave",
    "iso:country":"CA",
    "sg:address":"28 Evenwood Ave",
    "sg:city":"Scarborough",
    "sg:classifiers":[
        {
            "category":"Building & Trades",
            "subcategory":"Construction",
            "type":"Services"
        }
    ],
    "sg:phone":"+1 416 282 6377",
    "sg:postcode":"M1C 4T8",
    "sg:province":"ON",
    "sg:tags":[
        "painter"
    ],
    "wof:name":"Brumwell Contracting Inc",
    "wof:placetype":"venue"
},
  "geometry": {"coordinates":[-79.15361,43.790455],"type":"Point"}
}