{
  "type": "Feature",
  "properties": {
    "addr:full":"458 Wetmore Rd # B Fredericton NB E3B 5V1",
    "addr:housenumber":"458",
    "addr:postcode":"e3b 5v1",
    "addr:street":"Wetmore Rd # B",
    "iso:country":"CA",
    "sg:address":"458 Wetmore Rd # B",
    "sg:city":"Fredericton",
    "sg:classifiers":[
        {
            "category":"Home & Garden",
            "subcategory":"Household Appliances",
            "type":"Retail Goods"
        }
    ],
    "sg:phone":"+1 506 454 3018",
    "sg:postcode":"E3B 5V1",
    "sg:province":"NB",
    "wof:name":"Bill's Refrigeration Svc Ltd",
    "wof:placetype":"venue"
},
  "geometry": {"coordinates":[-66.631477,45.92244],"type":"Point"}
}