{
  "type": "Feature",
  "properties": {
    "iso:country":"CA",
    "sg:address":"214 5th St",
    "sg:city":"Courtenay",
    "sg:classifiers":[
        {
            "category":"Personal",
            "subcategory":"Beauty Salon",
            "type":"Services"
        }
    ],
    "sg:phone":"+1 250 338 5712",
    "sg:postcode":"V9N 1J6",
    "sg:province":"BC",
    "wof:name":"Salon Bridges",
    "wof:placetype":"venue"
},
  "geometry": {"coordinates":[-124.997459412,49.6912231445],"type":"Point"}
}