{
  "type": "Feature",
  "properties": {
    "addr:full":"2078 Rue Bombardier Marieville QC J3M 1E6",
    "addr:housenumber":"2078",
    "addr:postcode":"j3m 1e6",
    "addr:street":"Rue Bombardier",
    "iso:country":"CA",
    "sg:address":"2078 Rue Bombardier",
    "sg:city":"Marieville",
    "sg:classifiers":[
        {
            "category":"Utilities",
            "subcategory":"Fuel Oil & Lpg",
            "type":"Services"
        }
    ],
    "sg:phone":"+1 450 460 7128",
    "sg:postcode":"J3M 1E6",
    "sg:province":"QC",
    "wof:name":"Darsigny, Jean-Guy",
    "wof:placetype":"venue"
},
  "geometry": {"coordinates":[-73.1548690796,45.4311294556],"type":"Point"}
}