{
  "type": "Feature",
  "properties": {
    "addr:full":"Coquitlam BC V3K 6Z8",
    "addr:postcode":"v3k 6z8",
    "iso:country":"CA",
    "sg:city":"Coquitlam",
    "sg:classifiers":[
        {
            "category":"Education",
            "subcategory":"Special Training",
            "type":"Public Place"
        }
    ],
    "sg:phone":"+1 604 420 5450",
    "sg:postcode":"V3K 6Z8",
    "sg:province":"BC",
    "sg:tags":[
        "tutoring"
    ],
    "wof:name":"Canada Spanish Language Inst",
    "wof:placetype":"venue"
},
  "geometry": {"coordinates":[-122.89241,49.243439],"type":"Point"}
}