{
  "type": "Feature",
  "properties": {
    "addr:full":"1095 Queen St E Toronto ON M4M 1K7",
    "addr:housenumber":"1095",
    "addr:postcode":"m4m 1k7",
    "addr:street":"Queen St E",
    "iso:country":"CA",
    "sg:address":"1095 Queen St E",
    "sg:city":"Toronto",
    "sg:classifiers":[
        {
            "category":"Food & Beverages",
            "subcategory":"Meat & Fish",
            "type":"Retail Goods"
        }
    ],
    "sg:phone":"+1 416 466 5152",
    "sg:postcode":"M4M 1K7",
    "sg:province":"ON",
    "sg:tags":[
        "seafood"
    ],
    "wof:name":"Kristapsons Inc",
    "wof:placetype":"venue"
},
  "geometry": {"coordinates":[-79.33596,43.661915],"type":"Point"}
}