{
  "type": "Feature",
  "properties": {
    "addr:full":"10185 199B St Langley BC V1M 3W9",
    "addr:housenumber":"10185",
    "addr:postcode":"v1m 3w9",
    "addr:street":"199B St",
    "iso:country":"CA",
    "sg:address":"10185 199B St",
    "sg:city":"Langley",
    "sg:classifiers":[
        {
            "category":"Retail",
            "subcategory":"Auto Repair",
            "type":"Services"
        }
    ],
    "sg:phone":"+1 604 513 1818",
    "sg:postcode":"V1M 3W9",
    "sg:province":"BC",
    "sg:tags":[
        "wrecker"
    ],
    "wof:name":"A-Active Towing & Recovery Ltd",
    "wof:placetype":"venue"
},
  "geometry": {"coordinates":[-122.65657,49.104122],"type":"Point"}
}