{
  "type": "Feature",
  "properties": {
    "addr:full":"160 John St S Hamilton ON L8N 2C4",
    "addr:housenumber":"160",
    "addr:postcode":"l8n 2c4",
    "addr:street":"John St S",
    "iso:country":"CA",
    "sg:address":"160 John St S",
    "sg:city":"Hamilton",
    "sg:classifiers":[
        {
            "category":"Taxi",
            "type":"Transportation"
        }
    ],
    "sg:phone":"+1 905 304 8294",
    "sg:postcode":"L8N 2C4",
    "sg:province":"ON",
    "sg:tags":[
        "delivery",
        "taxicab"
    ],
    "wof:name":"Ancaster Taxi Inc",
    "wof:placetype":"venue"
},
  "geometry": {"coordinates":[-79.868431,43.251823],"type":"Point"}
}