{
  "type": "Feature",
  "properties": {
    "addr:full":"4046 Highway 43 Elkford BC V0B 1H0",
    "addr:housenumber":"4046",
    "addr:postcode":"bc v0b 1h0",
    "addr:street":"Highway 43",
    "iso:country":"CA",
    "sg:address":"4046 Highway 43",
    "sg:city":"Elkford",
    "sg:classifiers":[
        {
            "category":"Professional",
            "subcategory":"Business Services",
            "type":"Services"
        }
    ],
    "sg:phone":"+1 250 865 7553",
    "sg:postcode":"V0B 1H0",
    "sg:province":"BC",
    "sg:tags":[
        "water",
        "treatment",
        "ice"
    ],
    "wof:name":"Mountain Manna",
    "wof:placetype":"venue"
},
  "geometry": {"coordinates":[-114.916702,50.020916],"type":"Point"}
}