{
  "type": "Feature",
  "properties": {
    "iso:country":"CA",
    "sg:address":"389 Ontario St",
    "sg:city":"St Catharines",
    "sg:classifiers":[
        {
            "category":"Autos & Motor Vehicles",
            "subcategory":"Fuel & Gas Station",
            "type":"Retail Goods"
        }
    ],
    "sg:phone":"+1 905 688 2562",
    "sg:postcode":"L2R 5L3",
    "sg:province":"ON",
    "sg:tags":[
        "oil"
    ],
    "wof:name":"Shell Gas Bar",
    "wof:placetype":"venue"
},
  "geometry": {"coordinates":[-79.2667999268,43.1775817871],"type":"Point"}
}