{
  "type": "Feature",
  "properties": {
    "addr:full":"Brandon MB R7A 5C5",
    "addr:postcode":"r7a 5c5",
    "iso:country":"CA",
    "sg:city":"Brandon",
    "sg:classifiers":[
        {
            "category":"Food & Beverages",
            "subcategory":"Specialty",
            "type":"Retail Goods"
        }
    ],
    "sg:phone":"+1 204 728 9413",
    "sg:postcode":"R7A 5C5",
    "sg:province":"MB",
    "sg:tags":[
        "health",
        "diet"
    ],
    "wof:name":"General Nutrition Ctr",
    "wof:placetype":"venue"
},
  "geometry": {"coordinates":[-99.96209,49.826466],"type":"Point"}
}