{
  "type": "Feature",
  "properties": {
    "addr:full":"South Porcupine ON P0N 1H0",
    "addr:postcode":"p0n 1h0",
    "addr:street":"South",
    "iso:country":"CA",
    "sg:city":"South Porcupine",
    "sg:classifiers":[
        {
            "category":"Government",
            "subcategory":"Office",
            "type":"Public Place"
        }
    ],
    "sg:phone":"+1 705 235 1300",
    "sg:postcode":"P0N 1H0",
    "sg:province":"ON",
    "wof:name":"Ontario Richesses Naturelles",
    "wof:placetype":"venue"
},
  "geometry": {"coordinates":[-81.1603927612,48.4942779541],"type":"Point"}
}