{
  "type": "Feature",
  "properties": {
    "addr:full":"Castlegar BC V1N 1Z6",
    "addr:postcode":"v1n 1z6",
    "iso:country":"CA",
    "sg:city":"Castlegar",
    "sg:classifiers":[
        {
            "category":"Travel",
            "subcategory":"Travel Agent",
            "type":"Entertainment"
        }
    ],
    "sg:phone":"+1 250 365 7782",
    "sg:postcode":"V1N 1Z6",
    "sg:province":"BC",
    "sg:tags":[
        "agency",
        "bureau"
    ],
    "wof:name":"West's Travel Agency",
    "wof:placetype":"venue"
},
  "geometry": {"coordinates":[-117.665786743,49.3266105652],"type":"Point"}
}