{
  "type": "Feature",
  "properties": {
    "addr:full":"506 Main St N Brampton ON L6V 1P9",
    "addr:housenumber":"506",
    "addr:postcode":"l6v 1p9",
    "addr:street":"Main St N",
    "iso:country":"CA",
    "sg:address":"506 Main St N",
    "sg:city":"Brampton",
    "sg:classifiers":[
        {
            "category":"Autos & Motor Vehicles",
            "subcategory":"Auto Supplies",
            "type":"Retail Goods"
        }
    ],
    "sg:phone":"+1 905 453 5565",
    "sg:postcode":"L6V 1P9",
    "sg:province":"ON",
    "sg:tags":[
        "tire"
    ],
    "wof:name":"Tiresmart Auto Svc",
    "wof:placetype":"venue"
},
  "geometry": {"coordinates":[-79.778198,43.699665],"type":"Point"}
}