{
  "type": "Feature",
  "properties": {
    "addr:full":"621 Manouane Ch Saint-Michel-Des-Saints QC J0K 3B0",
    "addr:housenumber":"621",
    "addr:postcode":"j0k 3b0",
    "addr:street":"Manouane Ch",
    "iso:country":"CA",
    "sg:address":"621 Manouane Ch",
    "sg:city":"Saint-Michel-Des-Saints",
    "sg:classifiers":[
        {
            "category":"Government",
            "subcategory":"Office",
            "type":"Public Place"
        }
    ],
    "sg:phone":"+1 450 833 6034",
    "sg:postcode":"J0K 3B0",
    "sg:province":"QC",
    "sg:tags":[
        "village"
    ],
    "wof:name":"St-Michel-Des-Saints STN Eau",
    "wof:placetype":"venue"
},
  "geometry": {"coordinates":[-73.916573,46.68063],"type":"Point"}
}