{
  "type": "Feature",
  "properties": {
    "addr:full":"77 Maple St S Timmins ON P4N 1Y6",
    "addr:housenumber":"77",
    "addr:postcode":"p4n 1y6",
    "addr:street":"Maple St S",
    "iso:country":"CA",
    "sg:address":"77 Maple St S",
    "sg:city":"Timmins",
    "sg:classifiers":[
        {
            "category":"Professional",
            "subcategory":"Business Services",
            "type":"Services"
        }
    ],
    "sg:phone":"+1 705 267 6209",
    "sg:postcode":"P4N 1Y6",
    "sg:province":"ON",
    "sg:tags":[
        "appraiser"
    ],
    "wof:name":"Art Appraisal Svc",
    "wof:placetype":"venue"
},
  "geometry": {"coordinates":[-81.33354187010001,48.4744567871],"type":"Point"}
}