{
  "type": "Feature",
  "properties": {
    "addr:full":"St Denis SK S0K 3W0",
    "addr:postcode":"s0k 3w0",
    "addr:street":"St Denis",
    "iso:country":"CA",
    "sg:city":"St Denis",
    "sg:classifiers":[
        {
            "category":"Recreation",
            "type":"Entertainment"
        }
    ],
    "sg:phone":"+1 306 258 4635",
    "sg:postcode":"S0K 3W0",
    "sg:province":"SK",
    "sg:tags":[
        "hall",
        "auditorium"
    ],
    "wof:name":"Champetre County",
    "wof:placetype":"venue"
},
  "geometry": {"coordinates":[-106.073532,52.158375],"type":"Point"}
}