{
  "type": "Feature",
  "properties": {
    "addr:full":"426 5 Ave SE High River AB T1V 1H8",
    "addr:housenumber":"426",
    "addr:postcode":"t1v 1h8",
    "addr:street":"5 Ave Se",
    "iso:country":"CA",
    "sg:address":"426 5 Ave SE",
    "sg:city":"High River",
    "sg:classifiers":[
        {
            "category":"Home & Garden",
            "subcategory":"Home Furnishings",
            "type":"Retail Goods"
        }
    ],
    "sg:phone":"+1 403 652 1788",
    "sg:postcode":"T1V 1H8",
    "sg:province":"AB",
    "sg:tags":[
        "curtain",
        "made",
        "drapery"
    ],
    "wof:name":"Carla's Draperies",
    "wof:placetype":"venue"
},
  "geometry": {"coordinates":[-113.86041299999999,50.578583],"type":"Point"}
}