{
  "type": "Feature",
  "properties": {
    "iso:country":"CA",
    "sg:address":"819 Rue Honore-Mercier",
    "sg:city":"Iberville",
    "sg:classifiers":[
        {
            "category":"Manufacturing",
            "subcategory":"Apparel",
            "type":"Manufacturing & Wholesale Goods"
        }
    ],
    "sg:phone":"+1 450 358 4196",
    "sg:postcode":"J2X 3S4",
    "sg:province":"QC",
    "sg:tags":[
        "cap",
        "hat",
        "t",
        "millinery"
    ],
    "wof:name":"Serigraphie Jdj Inc",
    "wof:placetype":"venue"
},
  "geometry": {"coordinates":[-73.2365722656,45.3040351868],"type":"Point"}
}