{
  "type": "Feature",
  "properties": {
    "addr:full":"885 Buttercup Rd Gabriola BC V0R 1X5",
    "addr:housenumber":"885",
    "addr:postcode":"v0r 1x5",
    "addr:street":"Buttercup Rd",
    "iso:country":"CA",
    "sg:address":"885 Buttercup Rd",
    "sg:city":"Gabriola",
    "sg:classifiers":[
        {
            "category":"Retail",
            "subcategory":"Veterinary Services",
            "type":"Services"
        }
    ],
    "sg:phone":"+1 250 247 9185",
    "sg:postcode":"V0R 1X5",
    "sg:province":"BC",
    "sg:tags":[
        "veterinarian"
    ],
    "wof:name":"Twin Cedars Veterinary Svc",
    "wof:placetype":"venue"
},
  "geometry": {"coordinates":[-123.799843,49.171589],"type":"Point"}
}