{
  "type": "Feature",
  "properties": {
    "iso:country":"CA",
    "sg:address":"25 Boul Don-Quichotte",
    "sg:city":"L'Ile-Perrot",
    "sg:classifiers":[
        {
            "category":"Restaurant",
            "type":"Food & Drink"
        }
    ],
    "sg:phone":"+1 514 425 6666",
    "sg:postcode":"J7V 7X4",
    "sg:province":"QC",
    "wof:name":"Domino's Pizza",
    "wof:placetype":"venue"
},
  "geometry": {"coordinates":[-73.964111,45.38966],"type":"Point"}
}