{
  "type": "Feature",
  "properties": {
    "addr:full":"4920 Rue Sherbrooke O Westmount QC H3Z 1H3",
    "addr:housenumber":"4920",
    "addr:postcode":"h3z 1h3",
    "addr:street":"Rue Sherbrooke O",
    "iso:country":"CA",
    "sg:address":"4920 Rue Sherbrooke O",
    "sg:city":"Westmount",
    "sg:classifiers":[
        {
            "category":"Shopping",
            "subcategory":"Clothing, Apparel, & Fashions",
            "type":"Retail Goods"
        }
    ],
    "sg:phone":"+1 514 482 4702",
    "sg:postcode":"H3Z 1H3",
    "sg:province":"QC",
    "sg:tags":[
        "dancing",
        "supply"
    ],
    "wof:name":"Boutique Bodywares",
    "wof:placetype":"venue"
},
  "geometry": {"coordinates":[-73.6044082642,45.4779205322],"type":"Point"}
}