{
  "type": "Feature",
  "properties": {
    "addr:full":"32 Cootes Dr Dundas ON L9H 1B3",
    "addr:housenumber":"32",
    "addr:postcode":"l9h 1b3",
    "addr:street":"Cootes Dr",
    "iso:country":"CA",
    "sg:address":"32 Cootes Dr",
    "sg:city":"Dundas",
    "sg:classifiers":[
        {
            "category":"Autos & Motor Vehicles",
            "subcategory":"Fuel & Gas Station",
            "type":"Retail Goods"
        }
    ],
    "sg:phone":"+1 905 627 5966",
    "sg:postcode":"L9H 1B3",
    "sg:province":"ON",
    "sg:tags":[
        "oil"
    ],
    "wof:name":"Sunoco",
    "wof:placetype":"venue"
},
  "geometry": {"coordinates":[-79.947845,43.265148],"type":"Point"}
}