{
  "type": "Feature",
  "properties": {
    "addr:full":"31 Housers Lane Woodstock ON N4S 7V9",
    "addr:housenumber":"31",
    "addr:postcode":"n4s 7v9",
    "addr:street":"Housers Lane",
    "iso:country":"CA",
    "sg:address":"31 Housers Lane",
    "sg:city":"Woodstock",
    "sg:classifiers":[
        {
            "category":"Building & Trades",
            "subcategory":"Construction",
            "type":"Services"
        }
    ],
    "sg:phone":"+1 519 421 3879",
    "sg:postcode":"N4S 7V9",
    "sg:province":"ON",
    "sg:tags":[
        "sandblasting"
    ],
    "wof:name":"M & S Thermal Cleaning & Rbldg",
    "wof:placetype":"venue"
},
  "geometry": {"coordinates":[-80.71500396730001,43.1370124817],"type":"Point"}
}