{
  "type": "Feature",
  "properties": {
    "addr:full":"5395 East Vernon Rd Vernon BC V1B 3J7",
    "addr:housenumber":"5395",
    "addr:postcode":"bc v1b 3j7",
    "addr:street":"East Vernon Rd",
    "iso:country":"CA",
    "sg:address":"5395 East Vernon Rd",
    "sg:city":"Vernon",
    "sg:classifiers":[
        {
            "category":"Building & Trades",
            "subcategory":"Construction",
            "type":"Services"
        }
    ],
    "sg:phone":"+1 250 558 1007",
    "sg:postcode":"V1B 3J7",
    "sg:province":"BC",
    "sg:tags":[
        "painter"
    ],
    "wof:name":"Okanagan Coating & Painting",
    "wof:placetype":"venue"
},
  "geometry": {"coordinates":[-119.273804,50.265686],"type":"Point"}
}