{
  "type": "Feature",
  "properties": {
    "addr:full":"363 St Vincent St S Stratford ON N5A 2Y2",
    "addr:housenumber":"363",
    "addr:postcode":"n5a 2y2",
    "addr:street":"St Vincent St S",
    "iso:country":"CA",
    "sg:address":"363 St Vincent St S",
    "sg:city":"Stratford",
    "sg:classifiers":[
        {
            "category":"Education",
            "subcategory":"School",
            "type":"Public Place"
        }
    ],
    "sg:phone":"+1 519 271 3574",
    "sg:postcode":"N5A 2Y2",
    "sg:province":"ON",
    "wof:name":"St Joseph's School",
    "wof:placetype":"venue"
},
  "geometry": {"coordinates":[-80.997856,43.362564],"type":"Point"}
}