{
  "type": "Feature",
  "properties": {
    "addr:full":"105 7th Rang Saint-Leonard-D'Aston QC J0C 1M0",
    "addr:housenumber":"105",
    "addr:postcode":"j0c 1m0",
    "addr:street":"7Th Rang Saint-Leonard-D'Aston",
    "iso:country":"CA",
    "sg:address":"105 7th Rang",
    "sg:city":"Saint-Leonard-D'Aston",
    "sg:classifiers":[
        {
            "category":"Farming",
            "subcategory":"Farm",
            "type":"Manufacturing & Wholesale Goods"
        }
    ],
    "sg:phone":"+1 819 399 2205",
    "sg:postcode":"J0C 1M0",
    "sg:province":"QC",
    "wof:name":"Ferme Aston Inc",
    "wof:placetype":"venue"
},
  "geometry": {"coordinates":[-71.320038,48.54493],"type":"Point"}
}