{
  "type": "Feature",
  "properties": {
    "addr:full":"818 Gilbert Dr Barriere BC V0E 1E0",
    "addr:housenumber":"818",
    "addr:postcode":"bc v0e 1e0",
    "addr:street":"Gilbert Dr",
    "iso:country":"CA",
    "sg:address":"818 Gilbert Dr",
    "sg:city":"Barriere",
    "sg:classifiers":[
        {
            "category":"Building & Trades",
            "subcategory":"Construction",
            "type":"Services"
        }
    ],
    "sg:phone":"+1 250 672 5599",
    "sg:postcode":"V0E 1E0",
    "sg:province":"BC",
    "sg:tags":[
        "general",
        "contractor"
    ],
    "wof:name":"Argo Road Maintenance Ltd",
    "wof:placetype":"venue"
},
  "geometry": {"coordinates":[-120.134964,51.179424],"type":"Point"}
}