{
  "type": "Feature",
  "properties": {
    "addr:full":"1079 Bloor St W Toronto ON M6H 1M5",
    "addr:housenumber":"1079",
    "addr:postcode":"m6h 1m5",
    "addr:street":"Bloor St W",
    "iso:country":"CA",
    "sg:address":"1079 Bloor St W",
    "sg:city":"Toronto",
    "sg:classifiers":[
        {
            "category":"Retail",
            "subcategory":"Veterinary Services",
            "type":"Services"
        }
    ],
    "sg:phone":"+1 416 537 9677",
    "sg:postcode":"M6H 1M5",
    "sg:province":"ON",
    "sg:tags":[
        "veterinarian"
    ],
    "wof:name":"Parente, Maria DVM",
    "wof:placetype":"venue"
},
  "geometry": {"coordinates":[-79.4331436157,43.6601867676],"type":"Point"}
}