{
  "type": "Feature",
  "properties": {
    "addr:full":"Edmonton AB T6C 4E3",
    "addr:postcode":"t6c 4e3",
    "iso:country":"CA",
    "sg:city":"Edmonton",
    "sg:classifiers":[
        {
            "category":"Shopping",
            "subcategory":"Optical Goods",
            "type":"Retail Goods"
        }
    ],
    "sg:phone":"+1 780 466 5332",
    "sg:postcode":"T6C 4E3",
    "sg:province":"AB",
    "sg:tags":[
        "optician"
    ],
    "wof:name":"Bonnie Doon Optical",
    "wof:placetype":"venue"
},
  "geometry": {"coordinates":[-113.490371704,53.5462188721],"type":"Point"}
}