{
  "type": "Feature",
  "properties": {
    "addr:full":"222 2nd Ave S Saskatoon SK S7K 1K9",
    "addr:housenumber":"222",
    "addr:postcode":"s7k 1k9",
    "addr:street":"2Nd Ave S",
    "iso:country":"CA",
    "sg:address":"222 2nd Ave S",
    "sg:city":"Saskatoon",
    "sg:classifiers":[
        {
            "category":"Manufacturing",
            "subcategory":"Food",
            "type":"Manufacturing & Wholesale Goods"
        }
    ],
    "sg:phone":"+1 306 384 7444",
    "sg:postcode":"S7K 1K9",
    "sg:province":"SK",
    "sg:tags":[
        "brewer"
    ],
    "wof:name":"O'Shea's Irish Pub",
    "wof:placetype":"venue"
},
  "geometry": {"coordinates":[-106.664619446,52.1267166138],"type":"Point"}
}