{
  "type": "Feature",
  "properties": {
    "addr:full":"750 1Re Rue Richelieu QC J3L 3W4",
    "addr:housenumber":"750",
    "addr:postcode":"j3l 3w4",
    "addr:street":"1Re Rue Richelieu",
    "iso:country":"CA",
    "sg:address":"750 1Re Rue",
    "sg:city":"Richelieu",
    "sg:classifiers":[
        {
            "category":"Organizations",
            "subcategory":"Religious Organization",
            "type":"Services"
        }
    ],
    "sg:phone":"+1 450 658 1151",
    "sg:postcode":"J3L 3W4",
    "sg:province":"QC",
    "sg:tags":[
        "church"
    ],
    "wof:name":"Presbytere Richelieu",
    "wof:placetype":"venue"
},
  "geometry": {"coordinates":[-73.256905,45.445515],"type":"Point"}
}