{
  "type": "Feature",
  "properties": {
    "addr:full":"3504 1Re Rue Saint-Hubert QC J3Y 8Y5",
    "addr:postcode":"3504;j3y 8y5",
    "addr:street":"1Re Rue Saint-Hubert",
    "iso:country":"CA",
    "sg:address":"3504 1Re Rue",
    "sg:city":"Saint-Hubert",
    "sg:classifiers":[
        {
            "category":"Professional",
            "subcategory":"Engineering",
            "type":"Services"
        }
    ],
    "sg:phone":"+1 450 926 1325",
    "sg:postcode":"J3Y 8Y5",
    "sg:province":"QC",
    "sg:tags":[
        "engineer"
    ],
    "wof:name":"Coprodev",
    "wof:placetype":"venue"
},
  "geometry": {"coordinates":[-73.3931274414,45.4752922058],"type":"Point"}
}