{
  "type": "Feature",
  "properties": {
    "addr:full":"Eastman QC J0E 1P0",
    "addr:postcode":"j0e 1p0",
    "iso:country":"CA",
    "sg:city":"Eastman",
    "sg:classifiers":[
        {
            "category":"Travel",
            "subcategory":"Hotels & Motels",
            "type":"Entertainment"
        }
    ],
    "sg:phone":"+1 450 297 0770",
    "sg:postcode":"J0E 1P0",
    "sg:province":"QC",
    "sg:tags":[
        "cottage",
        "cabin"
    ],
    "wof:name":"Entre Cimes & Racines",
    "wof:placetype":"venue"
},
  "geometry": {"coordinates":[-72.305595,45.286442],"type":"Point"}
}