{
  "type": "Feature",
  "properties": {
    "addr:full":"32 Rue Sous-Le-Fort Quebec QC G1K 4G7",
    "addr:housenumber":"32",
    "addr:postcode":"g1k 4g7",
    "addr:street":"Rue Sous-Le-Fort",
    "iso:country":"CA",
    "sg:address":"32 Rue Sous-Le-Fort",
    "sg:city":"Quebec",
    "sg:classifiers":[
        {
            "category":"Organizations",
            "subcategory":"Religious Organization",
            "type":"Services"
        }
    ],
    "sg:phone":"+1 418 692 1650",
    "sg:postcode":"G1K 4G7",
    "sg:province":"QC",
    "sg:tags":[
        "church"
    ],
    "wof:name":"Presbytere N-D-Des-Victoires",
    "wof:placetype":"venue"
},
  "geometry": {"coordinates":[-71.20265999999999,46.812691],"type":"Point"}
}