{
  "type": "Feature",
  "properties": {
    "addr:full":"Saskatoon SK S7N 2G5",
    "addr:postcode":"s7n 2g5",
    "iso:country":"CA",
    "sg:city":"Saskatoon",
    "sg:classifiers":[
        {
            "category":"Restaurant",
            "type":"Food & Drink"
        }
    ],
    "sg:phone":"+1 306 665 8376",
    "sg:postcode":"S7N 2G5",
    "sg:province":"SK",
    "sg:tags":[
        "pizza"
    ],
    "wof:name":"Vern's Pizza",
    "wof:placetype":"venue"
},
  "geometry": {"coordinates":[-106.59918999999999,52.136192],"type":"Point"}
}