{
  "type": "Feature",
  "properties": {
    "iso:country":"CA",
    "sg:city":"Kingston",
    "sg:classifiers":[
        {
            "category":"Wholesale",
            "subcategory":"Electrical",
            "type":"Manufacturing & Wholesale Goods"
        }
    ],
    "sg:phone":"+1 613 384 9888",
    "sg:postcode":"K7M 3Y4",
    "sg:province":"ON",
    "sg:tags":[
        "equipment",
        "electric",
        "supply"
    ],
    "wof:name":"Torbram Electric Supply",
    "wof:placetype":"venue"
},
  "geometry": {"coordinates":[-76.5680007935,44.2426834106],"type":"Point"}
}