{
  "type": "Feature",
  "properties": {
    "addr:full":"10 Ashwarren Rd North York ON M3J 1Z5",
    "addr:housenumber":"10",
    "addr:postcode":"m3j 1z5",
    "addr:street":"Ashwarren Rd",
    "iso:country":"CA",
    "sg:address":"10 Ashwarren Rd",
    "sg:city":"North York",
    "sg:classifiers":[
        {
            "category":"Building & Trades",
            "subcategory":"Plumbing",
            "type":"Services"
        }
    ],
    "sg:phone":"+1 416 635 6161",
    "sg:postcode":"M3J 1Z5",
    "sg:province":"ON",
    "sg:tags":[
        "sheet",
        "work",
        "metal",
        "contractor"
    ],
    "wof:name":"Icon Sheet Metal",
    "wof:placetype":"venue"
},
  "geometry": {"coordinates":[-79.481758,43.75811],"type":"Point"}
}