{
  "type": "Feature",
  "properties": {
    "iso:country":"CA",
    "sg:address":"3174 Rue Ontario E",
    "sg:city":"Montreal",
    "sg:classifiers":[
        {
            "category":"Personal",
            "subcategory":"Beauty Salon",
            "type":"Services"
        }
    ],
    "sg:phone":"+1 514 527 7112",
    "sg:postcode":"H1W 1P2",
    "sg:province":"QC",
    "wof:name":"Coiffure Flash Pointe Assoc",
    "wof:placetype":"venue"
},
  "geometry": {"coordinates":[-73.547417,45.540634],"type":"Point"}
}