{
  "type": "Feature",
  "properties": {
    "addr:full":"205 Miner St Cowansville QC J2K 3Y5",
    "addr:housenumber":"205",
    "addr:postcode":"j2k 3y5",
    "addr:street":"Miner St",
    "iso:country":"CA",
    "sg:address":"205 Miner St",
    "sg:city":"Cowansville",
    "sg:classifiers":[
        {
            "category":"Professional",
            "subcategory":"Management & Consulting",
            "type":"Services"
        }
    ],
    "sg:phone":"+1 450 263 0001",
    "sg:postcode":"J2K 3Y5",
    "sg:province":"QC",
    "sg:tags":[
        "agricultural",
        "consultant"
    ],
    "wof:name":"Green Farmline Ltd",
    "wof:placetype":"venue"
},
  "geometry": {"coordinates":[-72.755295,45.197857],"type":"Point"}
}