{
  "type": "Feature",
  "properties": {
    "addr:full":"185 Water St Summerside PE C1N 1B2",
    "addr:housenumber":"185",
    "addr:postcode":"c1n 1b2",
    "addr:street":"Water St",
    "iso:country":"CA",
    "sg:address":"185 Water St",
    "sg:city":"Summerside",
    "sg:classifiers":[
        {
            "category":"Retail",
            "subcategory":"Laundry & Dry Cleaning",
            "type":"Services"
        }
    ],
    "sg:phone":"+1 902 436 8687",
    "sg:postcode":"C1N 1B2",
    "sg:province":"PE",
    "sg:tags":[
        "cleaners"
    ],
    "wof:name":"B J's Fabric-Care",
    "wof:placetype":"venue"
},
  "geometry": {"coordinates":[-63.787647,46.391087],"type":"Point"}
}