{
  "type": "Feature",
  "properties": {
    "iso:country":"CA",
    "sg:address":"840 Notre Dame",
    "sg:city":"St-Barnabe-Nord",
    "sg:classifiers":[
        {
            "category":"Restaurant",
            "type":"Food & Drink"
        }
    ],
    "sg:phone":"+1 819 264 5614",
    "sg:postcode":"G0X 2K0",
    "sg:province":"QC",
    "wof:name":"Casse-Croute St-Barnabe",
    "wof:placetype":"venue"
},
  "geometry": {"coordinates":[-72.8800201416,46.393901825],"type":"Point"}
}