{
  "type": "Feature",
  "properties": {
    "addr:full":"123 Ellice St Rocanville SK S0A 3L0",
    "addr:housenumber":"123",
    "addr:postcode":"s0a 3l0",
    "addr:street":"Ellice St",
    "iso:country":"CA",
    "sg:address":"123 Ellice St",
    "sg:city":"Rocanville",
    "sg:classifiers":[
        {
            "category":"Banks & Credit Unions",
            "subcategory":"Bank",
            "type":"Services"
        }
    ],
    "sg:phone":"+1 306 645 2177",
    "sg:postcode":"S0A 3L0",
    "sg:province":"SK",
    "wof:name":"Moosomin Credit Union",
    "wof:placetype":"venue"
},
  "geometry": {"coordinates":[-101.699921,50.382442],"type":"Point"}
}