{
  "type": "Feature",
  "properties": {
    "addr:full":"1400 Boul Edouard Saint-Hubert QC J4T 3T2",
    "addr:housenumber":"1400",
    "addr:postcode":"j4t 3t2",
    "addr:street":"Boul Edouard",
    "iso:country":"CA",
    "sg:address":"1400 Boul Edouard",
    "sg:city":"Saint-Hubert",
    "sg:classifiers":[
        {
            "category":"Food & Beverages",
            "subcategory":"Groceries & Convenience Stores",
            "type":"Retail Goods"
        }
    ],
    "sg:phone":"+1 450 443 2932",
    "sg:postcode":"J4T 3T2",
    "sg:province":"QC",
    "wof:name":"Depan-Escompte Couche-Tard",
    "wof:placetype":"venue"
},
  "geometry": {"coordinates":[-73.46961212159999,45.5032310486],"type":"Point"}
}