{
  "type": "Feature",
  "properties": {
    "iso:country":"CA",
    "sg:city":"Toronto",
    "sg:classifiers":[
        {
            "category":"Health Services",
            "subcategory":"Doctor",
            "type":"Services"
        }
    ],
    "sg:phone":"+1 416 480 4436",
    "sg:postcode":"M4N 3M5",
    "sg:province":"ON",
    "sg:tags":[
        "dentist"
    ],
    "wof:name":"Dover, D G DDS",
    "wof:placetype":"venue"
},
  "geometry": {"coordinates":[-79.3787689209,43.7211761475],"type":"Point"}
}