{
  "type": "Feature",
  "properties": {
    "addr:full":"620 Main St Wolfville NS B4P 1E8",
    "addr:housenumber":"620",
    "addr:postcode":"b4p 1e8",
    "addr:street":"Main St",
    "iso:country":"CA",
    "sg:address":"620 Main St",
    "sg:city":"Wolfville",
    "sg:classifiers":[
        {
            "category":"Travel",
            "subcategory":"Hotels & Motels",
            "type":"Entertainment"
        }
    ],
    "sg:phone":"+1 902 542 7696",
    "sg:postcode":"B4P 1E8",
    "sg:province":"NS",
    "sg:tags":[
        "breakfast",
        "accommodation",
        "bed"
    ],
    "wof:name":"Tattingstone Inn",
    "wof:placetype":"venue"
},
  "geometry": {"coordinates":[-64.37445831300001,45.0894889832],"type":"Point"}
}