{
  "type": "Feature",
  "properties": {
    "addr:full":"1262 Stone Church Rd E Hamilton ON L8W 2C8",
    "addr:housenumber":"1262",
    "addr:postcode":"l8w 2c8",
    "addr:street":"Stone Church Rd E",
    "iso:country":"CA",
    "sg:address":"1262 Stone Church Rd E",
    "sg:city":"Hamilton",
    "sg:classifiers":[
        {
            "category":"Home & Garden",
            "subcategory":"Building Materials",
            "type":"Retail Goods"
        }
    ],
    "sg:phone":"+1 905 575 4440",
    "sg:postcode":"L8W 2C8",
    "sg:province":"ON",
    "sg:tags":[
        "concrete"
    ],
    "wof:name":"Hess Machinery Ltd",
    "wof:placetype":"venue"
},
  "geometry": {"coordinates":[-79.83326700000001,43.197342],"type":"Point"}
}