{
  "type": "Feature",
  "properties": {
    "addr:full":"145 Guildwood Pky Scarborough ON M1E 1P5",
    "addr:housenumber":"145",
    "addr:postcode":"m1e 1p5",
    "addr:street":"Guildwood Pky",
    "iso:country":"CA",
    "sg:address":"145 Guildwood Pky",
    "sg:city":"Scarborough",
    "sg:classifiers":[
        {
            "category":"Social Services",
            "subcategory":"Child Care",
            "type":"Services"
        }
    ],
    "sg:phone":"+1 416 261 5153",
    "sg:postcode":"M1E 1P5",
    "sg:province":"ON",
    "wof:name":"Nyad Community Inc",
    "wof:placetype":"venue"
},
  "geometry": {"coordinates":[-79.19807434080001,43.7476654053],"type":"Point"}
}