{
  "type": "Feature",
  "properties": {
    "iso:country":"CA",
    "sg:address":"1509 Eastern Ave",
    "sg:city":"North Vancouver",
    "sg:classifiers":[
        {
            "category":"Health Services",
            "subcategory":"Doctor",
            "type":"Services"
        }
    ],
    "sg:phone":"+1 604 987 7188",
    "sg:postcode":"V7L 3G2",
    "sg:province":"BC",
    "sg:tags":[
        "dentist"
    ],
    "wof:name":"Larjava, Kirsi DDS",
    "wof:placetype":"venue"
},
  "geometry": {"coordinates":[-123.07089233400001,49.3223495483],"type":"Point"}
}