{
  "type": "Feature",
  "properties": {
    "addr:full":"9307 48 St SE Calgary AB T2C 2R1",
    "addr:housenumber":"9307",
    "addr:postcode":"t2c 2r1",
    "addr:street":"48 St Se",
    "iso:country":"CA",
    "sg:address":"9307 48 St SE",
    "sg:city":"Calgary",
    "sg:classifiers":[
        {
            "category":"Wholesale",
            "subcategory":"Metals & Minerals",
            "type":"Manufacturing & Wholesale Goods"
        }
    ],
    "sg:phone":"+1 403 203 0766",
    "sg:postcode":"T2C 2R1",
    "sg:province":"AB",
    "sg:tags":[
        "valve"
    ],
    "wof:name":"Comco Pipe & Supply CO",
    "wof:placetype":"venue"
},
  "geometry": {"coordinates":[-113.964386,50.970036],"type":"Point"}
}