{
  "type": "Feature",
  "properties": {
    "addr:full":"373 Av Sainte-Croix Saint-Laurent QC H4N 2L3",
    "addr:postcode":"h4n 2l3",
    "addr:street":"373 Av Sainte-Croix",
    "iso:country":"CA",
    "sg:address":"373 Av Sainte-Croix",
    "sg:city":"Saint-Laurent",
    "sg:classifiers":[
        {
            "category":"Wholesale",
            "subcategory":"Durable Goods & Equipment",
            "type":"Manufacturing & Wholesale Goods"
        }
    ],
    "sg:phone":"+1 514 855 8940",
    "sg:postcode":"H4N 2L3",
    "sg:province":"QC",
    "sg:tags":[
        "importer"
    ],
    "wof:name":"Importations Fdr Inc",
    "wof:placetype":"venue"
},
  "geometry": {"coordinates":[-73.668419,45.510189],"type":"Point"}
}