{
  "type": "Feature",
  "properties": {
    "addr:full":"797 Drake St Vancouver BC V6Z 2N7",
    "addr:housenumber":"797",
    "addr:postcode":"v6z 2n7",
    "addr:street":"Drake St",
    "iso:country":"CA",
    "sg:address":"797 Drake St",
    "sg:city":"Vancouver",
    "sg:classifiers":[
        {
            "category":"Food & Beverages",
            "subcategory":"Groceries & Convenience Stores",
            "type":"Retail Goods"
        }
    ],
    "sg:phone":"+1 604 681 2595",
    "sg:postcode":"V6Z 2N7",
    "sg:province":"BC",
    "sg:tags":[
        "grocer"
    ],
    "wof:name":"Monikaz Market",
    "wof:placetype":"venue"
},
  "geometry": {"coordinates":[-123.12867,49.276714],"type":"Point"}
}