{
  "type": "Feature",
  "properties": {
    "addr:full":"Montreal QC H3G 1R8",
    "addr:postcode":"h3g 1r8",
    "iso:country":"CA",
    "sg:city":"Montreal",
    "sg:classifiers":[
        {
            "category":"Health Services",
            "subcategory":"Health Practitioner",
            "type":"Services"
        }
    ],
    "sg:phone":"+1 514 954 1848",
    "sg:postcode":"H3G 1R8",
    "sg:province":"QC",
    "sg:tags":[
        "psychologist"
    ],
    "wof:name":"Institut Victoria",
    "wof:placetype":"venue"
},
  "geometry": {"coordinates":[-73.553909,45.52063],"type":"Point"}
}