{
  "type": "Feature",
  "properties": {
    "iso:country":"CA",
    "sg:city":"Mississauga",
    "sg:classifiers":[
        {
            "category":"Manufacturing",
            "subcategory":"Furniture",
            "type":"Manufacturing & Wholesale Goods"
        }
    ],
    "sg:phone":"+1 905 671 4664",
    "sg:postcode":"L4V 1E8",
    "sg:province":"ON",
    "wof:name":"Artage International Showroom",
    "wof:placetype":"venue"
},
  "geometry": {"coordinates":[-79.638062,43.700108],"type":"Point"}
}