{
  "type": "Feature",
  "properties": {
    "addr:full":"Calgary AB T2P 3E6",
    "addr:postcode":"t2p 3e6",
    "iso:country":"CA",
    "sg:city":"Calgary",
    "sg:classifiers":[
        {
            "category":"Mining & Drilling",
            "type":"Manufacturing & Wholesale Goods"
        }
    ],
    "sg:phone":"+1 403 237 9900",
    "sg:postcode":"T2P 3E6",
    "sg:province":"AB",
    "sg:tags":[
        "field",
        "oil"
    ],
    "wof:name":"Alliance Tubulars & Supply Ltd",
    "wof:placetype":"venue"
},
  "geometry": {"coordinates":[-114.07032775899999,51.0484352112],"type":"Point"}
}