{
  "type": "Feature",
  "properties": {
    "addr:full":"1991 Brunswick St #1006 Halifax NS B3J 2G9",
    "addr:housenumber":"1991",
    "addr:postcode":"ns b3j 2g9",
    "addr:street":"Brunswick St # 1006",
    "iso:country":"CA",
    "sg:address":"1991 Brunswick St #1006",
    "sg:city":"Halifax",
    "sg:classifiers":[
        {
            "category":"Professional",
            "type":"Services"
        }
    ],
    "sg:phone":"+1 902 423 2172",
    "sg:postcode":"B3J 2G9",
    "sg:province":"NS",
    "sg:tags":[
        "arts",
        "artist"
    ],
    "wof:name":"Jsm Fine Arts",
    "wof:placetype":"venue"
},
  "geometry": {"coordinates":[-63.578453064,44.6504135132],"type":"Point"}
}