{
  "type": "Feature",
  "properties": {
    "addr:full":"1996 Highway 15 Kingston ON K7L 4V3",
    "addr:housenumber":"1996",
    "addr:postcode":"k7l 4v3",
    "addr:street":"Highway 15",
    "iso:country":"CA",
    "sg:address":"1996 Highway 15",
    "sg:city":"Kingston",
    "sg:classifiers":[
        {
            "category":"Insurance",
            "subcategory":"Insurance Agent",
            "type":"Services"
        }
    ],
    "sg:phone":"+1 613 542 4440",
    "sg:postcode":"K7L 4V3",
    "sg:province":"ON",
    "wof:name":"Thousand Islands Insurance Ltd",
    "wof:placetype":"venue"
},
  "geometry": {"coordinates":[-76.479332,44.231537],"type":"Point"}
}