{
  "type": "Feature",
  "properties": {
    "iso:country":"CA",
    "sg:address":"8 Boul Des Iles",
    "sg:city":"Port-Cartier",
    "sg:classifiers":[
        {
            "category":"Shopping",
            "subcategory":"Pharmacy",
            "type":"Retail Goods"
        }
    ],
    "sg:phone":"+1 418 766 4424",
    "sg:postcode":"G5B 2J4",
    "sg:province":"QC",
    "wof:name":"Brunet Pharmacie Affiliee",
    "wof:placetype":"venue"
},
  "geometry": {"coordinates":[-66.8775024414,50.0208892822],"type":"Point"}
}