{
  "type": "Feature",
  "properties": {
    "addr:full":"LA Pocatiere QC G0R 1Z0",
    "addr:postcode":"g0r 1z0",
    "iso:country":"CA",
    "sg:city":"LA Pocatiere",
    "sg:classifiers":[
        {
            "category":"Autos & Motor Vehicles",
            "subcategory":"Auto Supplies",
            "type":"Retail Goods"
        }
    ],
    "sg:phone":"+1 418 856 6210",
    "sg:postcode":"G0R 1Z0",
    "sg:province":"QC",
    "sg:tags":[
        "automobile",
        "parts",
        "electric"
    ],
    "wof:name":"Alternateurs & Demarreurs Roma",
    "wof:placetype":"venue"
},
  "geometry": {"coordinates":[-70.05558000000001,47.363422],"type":"Point"}
}