{
  "type": "Feature",
  "properties": {
    "addr:full":"1 Unity Crt Lower Sackville NS B4E 2R9",
    "addr:housenumber":"1",
    "addr:postcode":"b4e 2r9",
    "addr:street":"Unity Crt",
    "iso:country":"CA",
    "sg:address":"1 Unity Crt",
    "sg:city":"Lower Sackville",
    "sg:classifiers":[
        {
            "category":"Real Estate",
            "subcategory":"Real Estate Agent",
            "type":"Services"
        }
    ],
    "sg:phone":"+1 902 864 4648",
    "sg:postcode":"B4E 2R9",
    "sg:province":"NS",
    "wof:name":"Crossroad Housing CO-OP",
    "wof:placetype":"venue"
},
  "geometry": {"coordinates":[-63.6997070312,44.7896118164],"type":"Point"}
}