{
  "type": "Feature",
  "properties": {
    "iso:country":"CA",
    "sg:address":"103 Bayfield St",
    "sg:city":"Meaford",
    "sg:classifiers":[
        {
            "category":"Recreation",
            "subcategory":"Marina",
            "type":"Entertainment"
        }
    ],
    "sg:phone":"+1 519 538 1940",
    "sg:postcode":"N4L 1N4",
    "sg:province":"ON",
    "sg:tags":[
        "repairing",
        "boat"
    ],
    "wof:name":"Cliff Richardson Boats Ltd",
    "wof:placetype":"venue"
},
  "geometry": {"coordinates":[-80.5903015137,44.6101379395],"type":"Point"}
}