{
  "type": "Feature",
  "properties": {
    "addr:full":"Richmond BC V6V 2L3",
    "addr:postcode":"v6v 2l3",
    "iso:country":"CA",
    "sg:city":"Richmond",
    "sg:classifiers":[
        {
            "category":"Wholesale",
            "subcategory":"Apparel",
            "type":"Manufacturing & Wholesale Goods"
        }
    ],
    "sg:phone":"+1 604 279 2333",
    "sg:postcode":"V6V 2L3",
    "sg:province":"BC",
    "sg:tags":[
        "clothing"
    ],
    "wof:name":"Two Systems Enterprises CO Ltd",
    "wof:placetype":"venue"
},
  "geometry": {"coordinates":[-123.069397,49.180519],"type":"Point"}
}