{
  "type": "Feature",
  "properties": {
    "iso:country":"CA",
    "sg:address":"305 Rue Saint-Jean",
    "sg:city":"Drummondville",
    "sg:classifiers":[
        {
            "category":"Health Services",
            "subcategory":"Medical Lab",
            "type":"Services"
        }
    ],
    "sg:phone":"+1 819 474 4050",
    "sg:postcode":"J2B 5L5",
    "sg:province":"QC",
    "sg:tags":[
        "laboratory"
    ],
    "wof:name":"Clinique A Votre Sourire",
    "wof:placetype":"venue"
},
  "geometry": {"coordinates":[-72.4839172363,45.8771324158],"type":"Point"}
}