{
  "type": "Feature",
  "properties": {
    "addr:full":"101 Rue DE L'Ecole Shippagan NB E8S 1V5",
    "addr:housenumber":"101",
    "addr:postcode":"e8s 1v5",
    "addr:street":"Rue De L'Ecole Shippagan",
    "iso:country":"CA",
    "sg:address":"101 Rue DE L'Ecole",
    "sg:city":"Shippagan",
    "sg:classifiers":[
        {
            "category":"Manufacturing",
            "subcategory":"Paper Products",
            "type":"Manufacturing & Wholesale Goods"
        }
    ],
    "sg:phone":"+1 506 336 1313",
    "sg:postcode":"E8S 1V5",
    "sg:province":"NB",
    "sg:tags":[
        "corrugated",
        "solid",
        "fiber",
        "box"
    ],
    "wof:name":"Multi-Carton Inc",
    "wof:placetype":"venue"
},
  "geometry": {"coordinates":[-64.7087631226,47.7438392639],"type":"Point"}
}