{
  "type": "Feature",
  "properties": {
    "addr:full":"12451 82 Ave # 223 Surrey BC V3W 3E8",
    "addr:housenumber":"12451",
    "addr:postcode":"v3w 3e8",
    "addr:street":"82 Ave # 223",
    "iso:country":"CA",
    "sg:address":"12451 82 Ave # 223",
    "sg:city":"Surrey",
    "sg:classifiers":[
        {
            "category":"Retail",
            "subcategory":"Auto Repair",
            "type":"Services"
        }
    ],
    "sg:phone":"+1 604 596 0643",
    "sg:postcode":"V3W 3E8",
    "sg:province":"BC",
    "sg:tags":[
        "body",
        "automobile",
        "painting"
    ],
    "wof:name":"Wasyl Auto Body Shop",
    "wof:placetype":"venue"
},
  "geometry": {"coordinates":[-122.87657900000001,49.152206],"type":"Point"}
}