{
  "type": "Feature",
  "properties": {
    "addr:full":"403 Rue Lafontaine Riviere-Du-Loup QC G5R 3B6",
    "addr:housenumber":"403",
    "addr:postcode":"g5r 3b6",
    "addr:street":"Rue Lafontaine",
    "iso:country":"CA",
    "sg:address":"403 Rue Lafontaine",
    "sg:city":"Riviere-Du-Loup",
    "sg:classifiers":[
        {
            "category":"Bars & Pubs",
            "type":"Food & Drink"
        }
    ],
    "sg:phone":"+1 418 862 1101",
    "sg:postcode":"G5R 3B6",
    "sg:province":"QC",
    "sg:tags":[
        "club",
        "night"
    ],
    "wof:name":"Discotheque Chez Kojak",
    "wof:placetype":"venue"
},
  "geometry": {"coordinates":[-69.532707,47.829315],"type":"Point"}
}