{
  "type": "Feature",
  "properties": {
    "addr:full":"1997 Dundas St E London ON N5V 1P6",
    "addr:housenumber":"1997",
    "addr:postcode":"n5v 1p6",
    "addr:street":"Dundas St E",
    "iso:country":"CA",
    "sg:address":"1997 Dundas St E",
    "sg:city":"London",
    "sg:classifiers":[
        {
            "category":"Retail",
            "subcategory":"Funeral Services",
            "type":"Services"
        }
    ],
    "sg:phone":"+1 519 455 9343",
    "sg:postcode":"N5V 1P6",
    "sg:province":"ON",
    "sg:tags":[
        "plan"
    ],
    "wof:name":"Forest Lawn Memorial Chapel",
    "wof:placetype":"venue"
},
  "geometry": {"coordinates":[-81.168999,43.006512],"type":"Point"}
}