{
  "type": "Feature",
  "properties": {
    "addr:full":"483 Ch Knowlton Knowlton QC J0E 1V0",
    "addr:housenumber":"483",
    "addr:postcode":"j0e 1v0",
    "addr:street":"Ch Knowlton",
    "iso:country":"CA",
    "sg:address":"483 Ch Knowlton",
    "sg:city":"Knowlton",
    "sg:classifiers":[
        {
            "category":"Restaurant",
            "type":"Food & Drink"
        }
    ],
    "sg:phone":"+1 450 243 6398",
    "sg:postcode":"J0E 1V0",
    "sg:province":"QC",
    "sg:tags":[
        "baker"
    ],
    "wof:name":"Patisserie Lac Brome Enr",
    "wof:placetype":"venue"
},
  "geometry": {"coordinates":[-72.5317230225,45.2135925293],"type":"Point"}
}