{
  "type": "Feature",
  "properties": {
    "addr:full":"100 Ontario Rd Mitchell ON N0K 1N0",
    "addr:housenumber":"100",
    "addr:postcode":"n0k 1n0",
    "addr:street":"Ontario Rd",
    "iso:country":"CA",
    "sg:address":"100 Ontario Rd",
    "sg:city":"Mitchell",
    "sg:classifiers":[
        {
            "category":"Personal",
            "subcategory":"Beauty Salon",
            "type":"Services"
        }
    ],
    "sg:phone":"+1 519 348 4497",
    "sg:postcode":"N0K 1N0",
    "sg:province":"ON",
    "wof:name":"Hair By Maxine & the Image Ctr",
    "wof:placetype":"venue"
},
  "geometry": {"coordinates":[-81.19566345210001,43.46692276],"type":"Point"}
}