{
  "type": "Feature",
  "properties": {
    "iso:country":"CA",
    "sg:address":"4517 Lions Ave",
    "sg:city":"North Vancouver",
    "sg:classifiers":[
        {
            "category":"Professional",
            "subcategory":"Lawyer & Legal Services",
            "type":"Services"
        }
    ],
    "sg:phone":"+1 604 980 4014",
    "sg:postcode":"V7R 3S7",
    "sg:province":"BC",
    "sg:tags":[
        "attorney"
    ],
    "wof:name":"Clark, Richard",
    "wof:placetype":"venue"
},
  "geometry": {"coordinates":[-123.09833526600001,49.352771759],"type":"Point"}
}