{
  "type": "Feature",
  "properties": {
    "addr:full":"113 Fourth St Rainy River ON P0W 1L0",
    "addr:housenumber":"113",
    "addr:postcode":"p0w 1l0",
    "addr:street":"Fourth St",
    "iso:country":"CA",
    "sg:address":"113 Fourth St",
    "sg:city":"Rainy River",
    "sg:classifiers":[
        {
            "category":"Health Services",
            "subcategory":"Hospital",
            "type":"Services"
        }
    ],
    "sg:phone":"+1 807 852 3232",
    "sg:postcode":"P0W 1L0",
    "sg:province":"ON",
    "wof:name":"Rainy River Health Ctr",
    "wof:placetype":"venue"
},
  "geometry": {"coordinates":[-94.568192,48.717613],"type":"Point"}
}