{
  "type": "Feature",
  "properties": {
    "addr:full":"Sorel-Tracy QC J3R 4L8",
    "addr:postcode":"j3r 4l8",
    "iso:country":"CA",
    "sg:city":"Sorel-Tracy",
    "sg:classifiers":[
        {
            "category":"Cinema",
            "subcategory":"Movie Rental",
            "type":"Entertainment"
        }
    ],
    "sg:phone":"+1 450 746 3808",
    "sg:postcode":"J3R 4L8",
    "sg:province":"QC",
    "sg:tags":[
        "leasing",
        "video",
        "disc",
        "tape"
    ],
    "wof:name":"Superclub Videotron",
    "wof:placetype":"venue"
},
  "geometry": {"coordinates":[-73.15372499999999,46.018894],"type":"Point"}
}