{
  "type": "Feature",
  "properties": {
    "iso:country":"CA",
    "sg:address":"642 13 St N",
    "sg:city":"Lethbridge",
    "sg:classifiers":[
        {
            "category":"Food & Beverages",
            "subcategory":"Groceries & Convenience Stores",
            "type":"Retail Goods"
        }
    ],
    "sg:phone":"+1 403 320 8867",
    "sg:postcode":"T1H 2S8",
    "sg:province":"AB",
    "sg:tags":[
        "grocer"
    ],
    "wof:name":"Asian Supermarket",
    "wof:placetype":"venue"
},
  "geometry": {"coordinates":[-112.82426452599999,49.70860672],"type":"Point"}
}