{
  "type": "Feature",
  "properties": {
    "addr:full":"Oakville ON L6L 5G8",
    "addr:postcode":"l6l 5g8",
    "iso:country":"CA",
    "sg:city":"Oakville",
    "sg:classifiers":[
        {
            "category":"Manufacturing",
            "subcategory":"Tools & Machinery",
            "type":"Manufacturing & Wholesale Goods"
        }
    ],
    "sg:phone":"+1 905 847 9946",
    "sg:postcode":"L6L 5G8",
    "sg:province":"ON",
    "sg:tags":[
        "hobby",
        "model",
        "maker",
        "supply"
    ],
    "wof:name":"Oakville Hobby",
    "wof:placetype":"venue"
},
  "geometry": {"coordinates":[-79.705521,43.411427],"type":"Point"}
}