{
  "type": "Feature",
  "properties": {
    "iso:country":"CA",
    "sg:address":"3235 Klondike Rd W",
    "sg:city":"North Gower",
    "sg:classifiers":[
        {
            "category":"Building & Trades",
            "subcategory":"Construction",
            "type":"Services"
        }
    ],
    "sg:phone":"+1 613 489 2916",
    "sg:postcode":"K0A 2T0",
    "sg:province":"ON",
    "sg:tags":[
        "roofing",
        "contractor"
    ],
    "wof:name":"Teck Roofing Svc",
    "wof:placetype":"venue"
},
  "geometry": {"coordinates":[-75.7071151733,45.1352081299],"type":"Point"}
}