{
  "type": "Feature",
  "properties": {
    "addr:full":"105 Rue Commerciale Saint-Lazare-DE-Bellechasse QC G0R 3J0",
    "addr:housenumber":"105",
    "addr:postcode":"g0r 3j0",
    "addr:street":"Rue Commerciale",
    "iso:country":"CA",
    "sg:address":"105 Rue Commerciale",
    "sg:city":"Saint-Lazare-DE-Bellechasse",
    "sg:classifiers":[
        {
            "category":"Retail",
            "subcategory":"Auto Repair",
            "type":"Services"
        }
    ],
    "sg:phone":"+1 418 883 3868",
    "sg:postcode":"G0R 3J0",
    "sg:province":"QC",
    "sg:tags":[
        "repairing",
        "automobile",
        "electric"
    ],
    "wof:name":"A Chabot & Fils Auto Elect Enr",
    "wof:placetype":"venue"
},
  "geometry": {"coordinates":[-70.80744934080001,46.6549491882],"type":"Point"}
}