{
  "type": "Feature",
  "properties": {
    "iso:country":"CA",
    "sg:city":"Delta",
    "sg:classifiers":[
        {
            "category":"Health Services",
            "subcategory":"Doctor",
            "type":"Services"
        }
    ],
    "sg:phone":"+1 604 592 2244",
    "sg:postcode":"V4C 6R4",
    "sg:province":"BC",
    "sg:tags":[
        "dentist"
    ],
    "wof:name":"Scott Road Dental Ctr",
    "wof:placetype":"venue"
},
  "geometry": {"coordinates":[-123.09877014200001,49.0872612],"type":"Point"}
}