{
  "type": "Feature",
  "properties": {
    "iso:country":"CA",
    "sg:address":"1610 1st Ave W",
    "sg:city":"Prince Albert",
    "sg:classifiers":[
        {
            "category":"Retail",
            "subcategory":"Auto Repair",
            "type":"Services"
        }
    ],
    "sg:phone":"+1 306 763 4999",
    "sg:postcode":"S6V 4Z3",
    "sg:province":"SK",
    "sg:tags":[
        "repairing",
        "automobile"
    ],
    "wof:name":"Tirecraft Auto Ctr",
    "wof:placetype":"venue"
},
  "geometry": {"coordinates":[-105.757004,53.198383],"type":"Point"}
}