{
  "type": "Feature",
  "properties": {
    "addr:full":"1042 Alberni St Vancouver BC V6E 1A3",
    "addr:housenumber":"1042",
    "addr:postcode":"v6e 1a3",
    "addr:street":"Alberni St",
    "iso:country":"CA",
    "sg:address":"1042 Alberni St",
    "sg:city":"Vancouver",
    "sg:classifiers":[
        {
            "category":"Restaurant",
            "type":"Food & Drink"
        }
    ],
    "sg:phone":"+1 604 684 2451",
    "sg:postcode":"V6E 1A3",
    "sg:province":"BC",
    "wof:name":"Kobe Japanese Steak House",
    "wof:placetype":"venue"
},
  "geometry": {"coordinates":[-123.122833,49.284515],"type":"Point"}
}