{
  "type": "Feature",
  "properties": {
    "addr:full":"2045 St. Peter Ave Bathurst NB E2A 7J5",
    "addr:housenumber":"2045",
    "addr:postcode":"e2a 7j5",
    "addr:street":"St. Peter Ave",
    "iso:country":"CA",
    "sg:address":"2045 St. Peter Ave",
    "sg:city":"Bathurst",
    "sg:classifiers":[
        {
            "category":"Manufacturing",
            "subcategory":"Electronics",
            "type":"Manufacturing & Wholesale Goods"
        }
    ],
    "sg:phone":"+1 506 546 9591",
    "sg:postcode":"E2A 7J5",
    "sg:province":"NB",
    "sg:tags":[
        "sound",
        "equipment",
        "alarm",
        "burglar",
        "system"
    ],
    "wof:name":"Northcoast Electronics Alarm",
    "wof:placetype":"venue"
},
  "geometry": {"coordinates":[-65.67939,47.653618],"type":"Point"}
}