{
  "type": "Feature",
  "properties": {
    "addr:full":"RR 1 Italy Cross NS B0J 1V0",
    "addr:postcode":"b0j 1v0",
    "addr:street":"Rr 1",
    "iso:country":"CA",
    "sg:address":"RR 1",
    "sg:city":"Italy Cross",
    "sg:classifiers":[
        {
            "category":"Wholesale",
            "subcategory":"Electrical",
            "type":"Manufacturing & Wholesale Goods"
        }
    ],
    "sg:phone":"+1 902 543 8705",
    "sg:postcode":"B0J 1V0",
    "sg:province":"NS",
    "sg:tags":[
        "control",
        "alarm",
        "burglar",
        "security",
        "system"
    ],
    "wof:name":"South Sure Security Svc Ltd",
    "wof:placetype":"venue"
},
  "geometry": {"coordinates":[-64.5493774414,44.2610435486],"type":"Point"}
}