{
  "type": "Feature",
  "properties": {
    "addr:full":"Abbotsford BC V2S 8G9",
    "addr:postcode":"v2s 8g9",
    "iso:country":"CA",
    "sg:city":"Abbotsford",
    "sg:classifiers":[
        {
            "category":"Health Services",
            "subcategory":"Health Practitioner",
            "type":"Services"
        }
    ],
    "sg:phone":"+1 604 557 0198",
    "sg:postcode":"V2S 8G9",
    "sg:province":"BC",
    "sg:tags":[
        "physiotherapist"
    ],
    "wof:name":"Glenn Mountain Orthopaedic",
    "wof:placetype":"venue"
},
  "geometry": {"coordinates":[-122.26796,49.047718],"type":"Point"}
}