{
  "type": "Feature",
  "properties": {
    "addr:full":"517 Hardisty St N Thunder Bay ON P7C 5S6",
    "addr:housenumber":"517",
    "addr:postcode":"p7c 5s6",
    "addr:street":"Hardisty St N",
    "iso:country":"CA",
    "sg:address":"517 Hardisty St N",
    "sg:city":"Thunder Bay",
    "sg:classifiers":[
        {
            "category":"Building & Trades",
            "subcategory":"Construction",
            "type":"Services"
        }
    ],
    "sg:phone":"+1 807 623 4540",
    "sg:postcode":"P7C 5S6",
    "sg:province":"ON",
    "sg:tags":[
        "general",
        "contractor"
    ],
    "wof:name":"Drd Construction Svc",
    "wof:placetype":"venue"
},
  "geometry": {"coordinates":[-89.235878,48.391182],"type":"Point"}
}