{
  "type": "Feature",
  "properties": {
    "addr:full":"Deep River ON K0J 1P0",
    "addr:postcode":"k0j 1p0",
    "iso:country":"CA",
    "sg:city":"Deep River",
    "sg:classifiers":[
        {
            "category":"Health Services",
            "subcategory":"Doctor",
            "type":"Services"
        }
    ],
    "sg:phone":"+1 613 584 4700",
    "sg:postcode":"K0J 1P0",
    "sg:province":"ON",
    "sg:tags":[
        "dentist"
    ],
    "wof:name":"Delta Dental Ctr",
    "wof:placetype":"venue"
},
  "geometry": {"coordinates":[-77.5047,46.102413],"type":"Point"}
}