{
  "type": "Feature",
  "properties": {
    "iso:country":"CA",
    "sg:address":"547 13th St",
    "sg:city":"Brandon",
    "sg:classifiers":[
        {
            "category":"Shopping",
            "subcategory":"Florist",
            "type":"Retail Goods"
        }
    ],
    "sg:phone":"+1 204 726 0256",
    "sg:postcode":"R7A 4R3",
    "sg:province":"MB",
    "sg:tags":[
        "plant"
    ],
    "wof:name":"Brandon Tropicare",
    "wof:placetype":"venue"
},
  "geometry": {"coordinates":[-99.9554138184,49.8414421082],"type":"Point"}
}