{
  "type": "Feature",
  "properties": {
    "addr:full":"195 Westney Rd S Ajax ON L1S 2C9",
    "addr:housenumber":"195",
    "addr:postcode":"l1s 2c9",
    "addr:street":"Westney Rd",
    "iso:country":"CA",
    "sg:address":"195 Westney Rd S",
    "sg:city":"Ajax",
    "sg:classifiers":[
        {
            "category":"Retail",
            "subcategory":"Auto Repair",
            "type":"Services"
        }
    ],
    "sg:phone":"+1 905 427 6796",
    "sg:postcode":"L1S 2C9",
    "sg:province":"ON",
    "sg:tags":[
        "repairing",
        "automobile",
        "lubrication"
    ],
    "wof:name":"Pennzoil 10 Minute Oil Change",
    "wof:placetype":"venue"
},
  "geometry": {"coordinates":[-79.0365905762,43.8439369202],"type":"Point"}
}