{
  "type": "Feature",
  "properties": {
    "addr:full":"520 Bemister E Melfort SK S0E 1A0",
    "addr:housenumber":"520",
    "addr:postcode":"s0e 1a0",
    "addr:street":"Bemister E Melfort",
    "iso:country":"CA",
    "sg:address":"520 Bemister E",
    "sg:city":"Melfort",
    "sg:classifiers":[
        {
            "category":"Organizations",
            "subcategory":"Religious Organization",
            "type":"Services"
        }
    ],
    "sg:phone":"+1 306 752 4550",
    "sg:postcode":"S0E 1A0",
    "sg:province":"SK",
    "sg:tags":[
        "church"
    ],
    "wof:name":"Free Methodist Church",
    "wof:placetype":"venue"
},
  "geometry": {"coordinates":[-104.607056,52.863625],"type":"Point"}
}