{
  "type": "Feature",
  "properties": {
    "addr:full":"Saint-Clet QC J0P 1S0",
    "addr:postcode":"j0p 1s0",
    "iso:country":"CA",
    "sg:city":"Saint-Clet",
    "sg:classifiers":[
        {
            "category":"Restaurant",
            "type":"Food & Drink"
        }
    ],
    "sg:phone":"+1 450 456 3336",
    "sg:postcode":"J0P 1S0",
    "sg:province":"QC",
    "wof:name":"Casse-Croute DE Saint-Clet",
    "wof:placetype":"venue"
},
  "geometry": {"coordinates":[-74.21734600000001,45.356091],"type":"Point"}
}