{
  "type": "Feature",
  "properties": {
    "addr:full":"515 Saint Marys St # 7 Fredericton NB E3A 8H4",
    "addr:housenumber":"515",
    "addr:postcode":"e3a 8h4",
    "addr:street":"Saint Marys St # 7",
    "iso:country":"CA",
    "sg:address":"515 Saint Marys St # 7",
    "sg:city":"Fredericton",
    "sg:classifiers":[
        {
            "category":"Insurance",
            "subcategory":"Insurance Agent",
            "type":"Services"
        }
    ],
    "sg:phone":"+1 506 458 0102",
    "sg:postcode":"E3A 8H4",
    "sg:province":"NB",
    "wof:name":"Corey Insurance Ltd",
    "wof:placetype":"venue"
},
  "geometry": {"coordinates":[-66.6391220093,45.9606399536],"type":"Point"}
}