{
  "type": "Feature",
  "properties": {
    "iso:country":"CA",
    "sg:address":"837 Rue Commerciale",
    "sg:city":"Saint-Jean-Chrysostome",
    "sg:classifiers":[
        {
            "category":"Shopping",
            "subcategory":"Jewelry",
            "type":"Retail Goods"
        }
    ],
    "sg:phone":"+1 418 834 1977",
    "sg:postcode":"G6Z 2E1",
    "sg:province":"QC",
    "sg:tags":[
        "jeweler"
    ],
    "wof:name":"Joaillerie Mercier Enr",
    "wof:placetype":"venue"
},
  "geometry": {"coordinates":[-71.20513916020001,46.7285995483],"type":"Point"}
}