{
  "type": "Feature",
  "properties": {
    "addr:full":"91 Kaska Rd Sherwood Park AB T8A 4E7",
    "addr:housenumber":"91",
    "addr:postcode":"t8a 4e7",
    "addr:street":"Kaska Rd",
    "iso:country":"CA",
    "sg:address":"91 Kaska Rd",
    "sg:city":"Sherwood Park",
    "sg:classifiers":[
        {
            "category":"Home & Garden",
            "subcategory":"Building Materials",
            "type":"Retail Goods"
        }
    ],
    "sg:phone":"+1 780 464 1552",
    "sg:postcode":"T8A 4E7",
    "sg:province":"AB",
    "sg:tags":[
        "glass",
        "window",
        "plate"
    ],
    "wof:name":"Hartwell's Glass & Mirror CO",
    "wof:placetype":"venue"
},
  "geometry": {"coordinates":[-113.321929932,53.539264679],"type":"Point"}
}