{
  "type": "Feature",
  "properties": {
    "addr:full":"4660 Av DE Gaulle Charlesbourg QC G1H 4J2",
    "addr:housenumber":"4660",
    "addr:postcode":"g1h 4j2",
    "addr:street":"Av De Gaulle",
    "iso:country":"CA",
    "sg:address":"4660 Av DE Gaulle",
    "sg:city":"Charlesbourg",
    "sg:classifiers":[
        {
            "category":"Food & Beverages",
            "subcategory":"Groceries & Convenience Stores",
            "type":"Retail Goods"
        }
    ],
    "sg:phone":"+1 418 626 1929",
    "sg:postcode":"G1H 4J2",
    "sg:province":"QC",
    "wof:name":"Couche-Tard",
    "wof:placetype":"venue"
},
  "geometry": {"coordinates":[-71.23878499999999,46.852036],"type":"Point"}
}