{
  "type": "Feature",
  "properties": {
    "addr:full":"Thunder Bay ON P7C 3V6",
    "addr:postcode":"p7c 3v6",
    "iso:country":"CA",
    "sg:city":"Thunder Bay",
    "sg:classifiers":[
        {
            "category":"Shopping",
            "type":"Retail Goods"
        }
    ],
    "sg:phone":"+1 807 623 1646",
    "sg:postcode":"P7C 3V6",
    "sg:province":"ON",
    "sg:tags":[
        "hearing",
        "equipment",
        "supply",
        "association",
        "impaired"
    ],
    "wof:name":"Canadian Hearing Society",
    "wof:placetype":"venue"
},
  "geometry": {"coordinates":[-89.24784088129999,48.385433197],"type":"Point"}
}