{
  "type": "Feature",
  "properties": {
    "addr:full":"144 Simcoe St Exeter ON N0M 1S1",
    "addr:housenumber":"144",
    "addr:postcode":"n0m 1s1",
    "addr:street":"Simcoe St",
    "iso:country":"CA",
    "sg:address":"144 Simcoe St",
    "sg:city":"Exeter",
    "sg:classifiers":[
        {
            "category":"Shopping",
            "subcategory":"Clothing, Apparel, & Fashions",
            "type":"Retail Goods"
        }
    ],
    "sg:phone":"+1 519 667 8771",
    "sg:postcode":"N0M 1S1",
    "sg:province":"ON",
    "sg:tags":[
        "salvage",
        "surplus",
        "merchandise"
    ],
    "wof:name":"Hope Salvage & Haulage",
    "wof:placetype":"venue"
},
  "geometry": {"coordinates":[-81.47472399999999,43.34301],"type":"Point"}
}