{
  "type": "Feature",
  "properties": {
    "iso:country":"CA",
    "sg:city":"Salaberry-DE-Valleyfield",
    "sg:classifiers":[
        {
            "category":"Building & Trades",
            "subcategory":"Construction",
            "type":"Services"
        }
    ],
    "sg:phone":"+1 450 371 3354",
    "sg:postcode":"J6T 4L8",
    "sg:province":"QC",
    "sg:tags":[
        "general",
        "contractor"
    ],
    "wof:name":"Construction Lecompte Inc",
    "wof:placetype":"venue"
},
  "geometry": {"coordinates":[-74.125229,45.246311],"type":"Point"}
}