{
  "type": "Feature",
  "properties": {
    "addr:full":"510 Cliff St Enderby BC V0E 1V0",
    "addr:housenumber":"510",
    "addr:postcode":"v0e 1v0",
    "addr:street":"Cliff St",
    "iso:country":"CA",
    "sg:address":"510 Cliff St",
    "sg:city":"Enderby",
    "sg:classifiers":[
        {
            "category":"Banks & Credit Unions",
            "subcategory":"Bank",
            "type":"Services"
        }
    ],
    "sg:phone":"+1 250 838 6421",
    "sg:postcode":"V0E 1V0",
    "sg:province":"BC",
    "wof:name":"Bank of Montreal",
    "wof:placetype":"venue"
},
  "geometry": {"coordinates":[-119.138000488,50.5502319336],"type":"Point"}
}