{
  "type": "Feature",
  "properties": {
    "addr:full":"2 Campbell Dr Uxbridge ON L9P 1H6",
    "addr:housenumber":"2",
    "addr:postcode":"l9p 1h6",
    "addr:street":"Campbell Dr",
    "iso:country":"CA",
    "sg:address":"2 Campbell Dr",
    "sg:city":"Uxbridge",
    "sg:classifiers":[
        {
            "category":"Government",
            "subcategory":"Office",
            "type":"Public Place"
        }
    ],
    "sg:phone":"+1 905 852 4566",
    "sg:postcode":"L9P 1H6",
    "sg:province":"ON",
    "sg:tags":[
        "village"
    ],
    "wof:name":"Durham Social Svc",
    "wof:placetype":"venue"
},
  "geometry": {"coordinates":[-79.1262054443,44.1023521423],"type":"Point"}
}