{
  "type": "Feature",
  "properties": {
    "addr:full":"3172 Dundas St W Toronto ON M6P 2A1",
    "addr:housenumber":"3172",
    "addr:postcode":"m6p 2a1",
    "addr:street":"Dundas St W",
    "iso:country":"CA",
    "sg:address":"3172 Dundas St W",
    "sg:city":"Toronto",
    "sg:classifiers":[
        {
            "category":"Health Services",
            "subcategory":"Doctor",
            "type":"Services"
        }
    ],
    "sg:phone":"+1 416 763 1907",
    "sg:postcode":"M6P 2A1",
    "sg:province":"ON",
    "sg:tags":[
        "physician",
        "surgeon"
    ],
    "wof:name":"Yeh, William S L MD",
    "wof:placetype":"venue"
},
  "geometry": {"coordinates":[-79.475533,43.665672],"type":"Point"}
}