{
  "type": "Feature",
  "properties": {
    "addr:full":"69 281 Rte N # A Saint-Magloire QC G0R 3M0",
    "addr:housenumber":"281",
    "addr:postcode":"g0r 3m0",
    "addr:street":"69;Rte N # A Saint-Magloire",
    "iso:country":"CA",
    "sg:address":"69 281 Rte N # A",
    "sg:city":"Saint-Magloire",
    "sg:classifiers":[
        {
            "category":"Wholesale",
            "subcategory":"Machinery & Supplies",
            "type":"Manufacturing & Wholesale Goods"
        }
    ],
    "sg:phone":"+1 418 257 2665",
    "sg:postcode":"G0R 3M0",
    "sg:province":"QC",
    "sg:tags":[
        "forestry",
        "timber"
    ],
    "wof:name":"Groupement Forestier DE Belle",
    "wof:placetype":"venue"
},
  "geometry": {"coordinates":[-70.288422,46.575642],"type":"Point"}
}