{
  "type": "Feature",
  "properties": {
    "addr:full":"1395 Main St North Vancouver BC V7J 1C4",
    "addr:housenumber":"1395",
    "addr:postcode":"v7j 1c4",
    "addr:street":"Main St",
    "iso:country":"CA",
    "sg:address":"1395 Main St",
    "sg:city":"North Vancouver",
    "sg:classifiers":[
        {
            "category":"Autos & Motor Vehicles",
            "subcategory":"Motorcycle Sales",
            "type":"Retail Goods"
        }
    ],
    "sg:phone":"+1 604 986 1581",
    "sg:postcode":"V7J 1C4",
    "sg:province":"BC",
    "sg:tags":[
        "scooter"
    ],
    "wof:name":"North Shore Suzuki Motorcycles",
    "wof:placetype":"venue"
},
  "geometry": {"coordinates":[-123.100082,49.272892],"type":"Point"}
}