{
  "type": "Feature",
  "properties": {
    "addr:full":"Kamloops BC V2C 3K8",
    "addr:postcode":"bc v2c 3k8",
    "iso:country":"CA",
    "sg:city":"Kamloops",
    "sg:classifiers":[
        {
            "category":"Professional",
            "subcategory":"Lawyer & Legal Services",
            "type":"Services"
        }
    ],
    "sg:phone":"+1 250 374 4463",
    "sg:postcode":"V2C 3K8",
    "sg:province":"BC",
    "sg:tags":[
        "attorney"
    ],
    "wof:name":"Gillespie Renkema Barnett",
    "wof:placetype":"venue"
},
  "geometry": {"coordinates":[-120.33840942400001,50.6742668152],"type":"Point"}
}