{
  "type": "Feature",
  "properties": {
    "iso:country":"CA",
    "sg:address":"7025 Tomken Rd #29",
    "sg:city":"Mississauga",
    "sg:classifiers":[
        {
            "category":"Wholesale",
            "subcategory":"Office Equipment",
            "type":"Manufacturing & Wholesale Goods"
        }
    ],
    "sg:phone":"+1 905 565 6560",
    "sg:postcode":"L5S 1R6",
    "sg:province":"ON",
    "sg:tags":[
        "scanning",
        "code",
        "bar"
    ],
    "wof:name":"Automation Associates Inc",
    "wof:placetype":"venue"
},
  "geometry": {"coordinates":[-79.68457,43.665428],"type":"Point"}
}