{
  "type": "Feature",
  "properties": {
    "iso:country":"CA",
    "sg:address":"1150 Flint Rd",
    "sg:city":"North York",
    "sg:classifiers":[
        {
            "category":"Manufacturing",
            "subcategory":"Tools & Machinery",
            "type":"Manufacturing & Wholesale Goods"
        }
    ],
    "sg:phone":"+1 416 661 1577",
    "sg:postcode":"M3J 2J5",
    "sg:province":"ON",
    "sg:tags":[
        "furniture"
    ],
    "wof:name":"Teknion Corp",
    "wof:placetype":"venue"
},
  "geometry": {"coordinates":[-79.481705,43.778046],"type":"Point"}
}