{
  "type": "Feature",
  "properties": {
    "addr:full":"1150 Flint Rd North York ON M3J 2J5",
    "addr:housenumber":"1150",
    "addr:postcode":"m3j 2j5",
    "addr:street":"Flint Rd",
    "iso:country":"CA",
    "sg:address":"1150 Flint Rd",
    "sg:city":"North York",
    "sg:classifiers":[
        {
            "category":"Manufacturing",
            "subcategory":"Tools & Machinery",
            "type":"Manufacturing & Wholesale Goods"
        }
    ],
    "sg:phone":"+1 416 661 1577",
    "sg:postcode":"M3J 2J5",
    "sg:province":"ON",
    "sg:tags":[
        "furniture"
    ],
    "wof:name":"Teknion Corp",
    "wof:placetype":"venue"
},
  "geometry": {"coordinates":[-79.48170500000001,43.778046],"type":"Point"}
}