{
  "type": "Feature",
  "properties": {
    "addr:full":"Saskatoon SK S7K 2Y1",
    "addr:postcode":"s7k 2y1",
    "iso:country":"CA",
    "sg:city":"Saskatoon",
    "sg:classifiers":[
        {
            "category":"Manufacturing",
            "subcategory":"Tools & Machinery",
            "type":"Manufacturing & Wholesale Goods"
        }
    ],
    "sg:phone":"+1 306 242 4046",
    "sg:postcode":"S7K 2Y1",
    "sg:province":"SK",
    "sg:tags":[
        "equipment",
        "electric"
    ],
    "wof:name":"Schneider Electric",
    "wof:placetype":"venue"
},
  "geometry": {"coordinates":[-106.64901733400001,52.1619682312],"type":"Point"}
}