{
  "type": "Feature",
  "properties": {
    "addr:full":"405 Pelissier St Windsor ON N9A 4L2",
    "addr:housenumber":"405",
    "addr:postcode":"n9a 4l2",
    "addr:street":"Pelissier St",
    "iso:country":"CA",
    "sg:address":"405 Pelissier St",
    "sg:city":"Windsor",
    "sg:classifiers":[
        {
            "category":"Shopping",
            "subcategory":"Gifts & Souvenirs",
            "type":"Retail Goods"
        }
    ],
    "sg:phone":"+1 519 254 6865",
    "sg:postcode":"N9A 4L2",
    "sg:province":"ON",
    "sg:tags":[
        "shop"
    ],
    "wof:name":"Casa Chavela",
    "wof:placetype":"venue"
},
  "geometry": {"coordinates":[-83.039322,42.315899],"type":"Point"}
}