{
  "type": "Feature",
  "properties": {
    "iso:country":"CA",
    "sg:address":"300 Charlotte St",
    "sg:city":"Sydney",
    "sg:classifiers":[
        {
            "category":"Shopping",
            "subcategory":"Clothing, Apparel, & Fashions",
            "type":"Retail Goods"
        }
    ],
    "sg:phone":"+1 902 564 4464",
    "sg:postcode":"B1P 1C7",
    "sg:province":"NS",
    "sg:tags":[
        "infant",
        "wear"
    ],
    "wof:name":"Rascalz Kids Clothing",
    "wof:placetype":"venue"
},
  "geometry": {"coordinates":[-60.1948699951,46.1382064819],"type":"Point"}
}