{
  "type": "Feature",
  "properties": {
    "addr:full":"Calgary AB T2E 7N6",
    "addr:postcode":"t2e 7n6",
    "iso:country":"CA",
    "sg:city":"Calgary",
    "sg:classifiers":[
        {
            "category":"Health Services",
            "subcategory":"Clinic",
            "type":"Services"
        }
    ],
    "sg:phone":"+1 403 297 9744",
    "sg:postcode":"T2E 7N6",
    "sg:province":"AB",
    "sg:tags":[
        "home"
    ],
    "wof:name":"We Care Home Health Svc",
    "wof:placetype":"venue"
},
  "geometry": {"coordinates":[-114.01767700000001,51.055511],"type":"Point"}
}