{
  "type": "Feature",
  "properties": {
    "addr:full":"1450 Tecumseh Rd E Windsor ON N8W 1C1",
    "addr:housenumber":"1450",
    "addr:postcode":"n8w 1c1",
    "addr:street":"Tecumseh Rd E",
    "iso:country":"CA",
    "sg:address":"1450 Tecumseh Rd E",
    "sg:city":"Windsor",
    "sg:classifiers":[
        {
            "category":"Shopping",
            "subcategory":"Used Merchandise",
            "type":"Retail Goods"
        }
    ],
    "sg:phone":"+1 519 258 2603",
    "sg:postcode":"N8W 1C1",
    "sg:province":"ON",
    "sg:tags":[
        "second",
        "store",
        "hand"
    ],
    "wof:name":"Christian Community Store",
    "wof:placetype":"venue"
},
  "geometry": {"coordinates":[-83.00419599999999,42.300587],"type":"Point"}
}