{
  "type": "Feature",
  "properties": {
    "addr:full":"786 Rue Principale Roxton Pond QC J0E 1Z0",
    "addr:housenumber":"786",
    "addr:postcode":"j0e 1z0",
    "addr:street":"Rue Principale",
    "iso:country":"CA",
    "sg:address":"786 Rue Principale",
    "sg:city":"Roxton Pond",
    "sg:classifiers":[
        {
            "category":"Home & Garden",
            "subcategory":"Garden Supply",
            "type":"Retail Goods"
        }
    ],
    "sg:phone":"+1 450 372 6932",
    "sg:postcode":"J0E 1Z0",
    "sg:province":"QC",
    "sg:tags":[
        "nurseryman"
    ],
    "wof:name":"Pepiniere Larose Enr",
    "wof:placetype":"venue"
},
  "geometry": {"coordinates":[-72.66487884519999,45.4704818726],"type":"Point"}
}