{
  "type": "Feature",
  "properties": {
    "iso:country":"CA",
    "sg:address":"2425 Boul Cure-Labelle",
    "sg:city":"Laval",
    "sg:classifiers":[
        {
            "category":"Food & Beverages",
            "subcategory":"Groceries & Convenience Stores",
            "type":"Retail Goods"
        }
    ],
    "sg:phone":"+1 450 687 1375",
    "sg:postcode":"H7T 1R3",
    "sg:province":"QC",
    "sg:tags":[
        "grocer"
    ],
    "wof:name":"Super C",
    "wof:placetype":"venue"
},
  "geometry": {"coordinates":[-73.770058,45.560295],"type":"Point"}
}