{
  "type": "Feature",
  "properties": {
    "addr:full":"Fort St James BC V0J 1P0",
    "addr:postcode":"v0j 1p0",
    "addr:street":"Fort St",
    "iso:country":"CA",
    "sg:city":"Fort St James",
    "sg:classifiers":[
        {
            "category":"Food & Beverages",
            "subcategory":"Groceries & Convenience Stores",
            "type":"Retail Goods"
        }
    ],
    "sg:phone":"+1 250 996 7305",
    "sg:postcode":"V0J 1P0",
    "sg:province":"BC",
    "sg:tags":[
        "grocer"
    ],
    "wof:name":"Mr G",
    "wof:placetype":"venue"
},
  "geometry": {"coordinates":[-124.264282227,54.4468955994],"type":"Point"}
}