{
  "type": "Feature",
  "properties": {
    "addr:full":"1771 Hungerford Dr Houston BC V0J 1Z0",
    "addr:housenumber":"1771",
    "addr:postcode":"v0j 1z0",
    "addr:street":"Hungerford Dr",
    "iso:country":"CA",
    "sg:address":"1771 Hungerford Dr",
    "sg:city":"Houston",
    "sg:classifiers":[
        {
            "category":"Education",
            "subcategory":"School",
            "type":"Public Place"
        }
    ],
    "sg:phone":"+1 250 845 7217",
    "sg:postcode":"V0J 1Z0",
    "sg:province":"BC",
    "wof:name":"Houston Secondary School",
    "wof:placetype":"venue"
},
  "geometry": {"coordinates":[-126.651054,54.389706],"type":"Point"}
}