{
  "type": "Feature",
  "properties": {
    "addr:full":"506 Lonergan Blvd Timmins ON P4P 1C9",
    "addr:housenumber":"506",
    "addr:postcode":"p4p 1c9",
    "addr:street":"Lonergan Blvd",
    "iso:country":"CA",
    "sg:address":"506 Lonergan Blvd",
    "sg:city":"Timmins",
    "sg:classifiers":[
        {
            "category":"Social Services",
            "type":"Services"
        }
    ],
    "sg:phone":"+1 705 268 2230",
    "sg:postcode":"P4P 1C9",
    "sg:province":"ON",
    "sg:tags":[
        "housing",
        "assistance"
    ],
    "wof:name":"Access Better Living Inc",
    "wof:placetype":"venue"
},
  "geometry": {"coordinates":[-81.350853,48.498749],"type":"Point"}
}