{
  "type": "Feature",
  "properties": {
    "addr:full":"577 Rue Victoria Edmundston NB E3V 3M9",
    "addr:housenumber":"577",
    "addr:postcode":"e3v 3m9",
    "addr:street":"Rue Victoria",
    "iso:country":"CA",
    "sg:address":"577 Rue Victoria",
    "sg:city":"Edmundston",
    "sg:classifiers":[
        {
            "category":"Food & Beverages",
            "subcategory":"Groceries & Convenience Stores",
            "type":"Retail Goods"
        }
    ],
    "sg:phone":"+1 506 739 9670",
    "sg:postcode":"E3V 3M9",
    "sg:province":"NB",
    "sg:tags":[
        "grocer"
    ],
    "wof:name":"Atlantic Superstore",
    "wof:placetype":"venue"
},
  "geometry": {"coordinates":[-68.336296,47.381966],"type":"Point"}
}