{
  "type": "Feature",
  "properties": {
    "iso:country":"CA",
    "sg:address":"1819 4 St SW",
    "sg:city":"Calgary",
    "sg:classifiers":[
        {
            "category":"Personal",
            "subcategory":"Beauty Salon",
            "type":"Services"
        }
    ],
    "sg:phone":"+1 403 228 0179",
    "sg:postcode":"T2S 1W2",
    "sg:province":"AB",
    "wof:name":"Izobizo Hair Salon",
    "wof:placetype":"venue"
},
  "geometry": {"coordinates":[-114.071540833,51.0362434387],"type":"Point"}
}