{
  "type": "Feature",
  "properties": {
    "addr:full":"5667 King Rd Nobleton ON L0G 1N0",
    "addr:housenumber":"5667",
    "addr:postcode":"l0g 1n0",
    "addr:street":"King Rd",
    "iso:country":"CA",
    "sg:address":"5667 King Rd",
    "sg:city":"Nobleton",
    "sg:classifiers":[
        {
            "category":"Professional",
            "subcategory":"Engineering",
            "type":"Services"
        }
    ],
    "sg:phone":"+1 905 859 1945",
    "sg:postcode":"L0G 1N0",
    "sg:province":"ON",
    "sg:tags":[
        "engineer"
    ],
    "wof:name":"Good Vibrations Engineering",
    "wof:placetype":"venue"
},
  "geometry": {"coordinates":[-79.65409088129999,43.9074783325],"type":"Point"}
}