{
  "type": "Feature",
  "properties": {
    "addr:full":"Dunrobin ON K0A 1T0",
    "addr:postcode":"k0a 1t0",
    "iso:country":"CA",
    "sg:city":"Dunrobin",
    "sg:classifiers":[
        {
            "category":"Building & Trades",
            "subcategory":"Construction",
            "type":"Services"
        }
    ],
    "sg:phone":"+1 613 832 2901",
    "sg:postcode":"K0A 1T0",
    "sg:province":"ON",
    "sg:tags":[
        "tile",
        "dealer"
    ],
    "wof:name":"Tilex Inc",
    "wof:placetype":"venue"
},
  "geometry": {"coordinates":[-76.02285766599999,45.423992157],"type":"Point"}
}