{
  "type": "Feature",
  "properties": {
    "addr:full":"1 Rue Fleury Saint-Raphael QC G0R 4C0",
    "addr:housenumber":"1",
    "addr:postcode":"g0r 4c0",
    "addr:street":"Rue Fleury",
    "iso:country":"CA",
    "sg:address":"1 Rue Fleury",
    "sg:city":"Saint-Raphael",
    "sg:classifiers":[
        {
            "category":"Social Services",
            "subcategory":"Child Care",
            "type":"Services"
        }
    ],
    "sg:phone":"+1 418 243 3545",
    "sg:postcode":"G0R 4C0",
    "sg:province":"QC",
    "wof:name":"Centre DE LA Petite Enfance",
    "wof:placetype":"venue"
},
  "geometry": {"coordinates":[-70.7519836426,46.7942008972],"type":"Point"}
}