{
  "type": "Feature",
  "properties": {
    "addr:full":"615 Yonge St Toronto ON M4Y 1Z5",
    "addr:housenumber":"615",
    "addr:postcode":"m4y 1z5",
    "addr:street":"Yonge St",
    "iso:country":"CA",
    "sg:address":"615 Yonge St",
    "sg:city":"Toronto",
    "sg:classifiers":[
        {
            "category":"Arts & Performance",
            "subcategory":"Theater",
            "type":"Entertainment"
        }
    ],
    "sg:phone":"+1 416 515 2028",
    "sg:postcode":"M4Y 1Z5",
    "sg:province":"ON",
    "sg:tags":[
        "talent",
        "agency",
        "casting"
    ],
    "wof:name":"Jordan & Assoc Talent Mgmt Ltd",
    "wof:placetype":"venue"
},
  "geometry": {"coordinates":[-79.38526899999999,43.667088],"type":"Point"}
}