{
  "type": "Feature",
  "properties": {
    "iso:country":"CA",
    "sg:city":"Courtenay",
    "sg:classifiers":[
        {
            "category":"Professional",
            "subcategory":"Business Services",
            "type":"Services"
        }
    ],
    "sg:phone":"+1 250 338 0262",
    "sg:postcode":"V9N 2J6",
    "sg:province":"BC",
    "sg:tags":[
        "interior",
        "consultant",
        "design",
        "decorator"
    ],
    "wof:name":"Judith Moore Interiors",
    "wof:placetype":"venue"
},
  "geometry": {"coordinates":[-124.99671936,49.6904067993],"type":"Point"}
}