{
  "type": "Feature",
  "properties": {
    "addr:full":"6855 16E Av Montreal QC H1X 2T5",
    "addr:housenumber":"6855",
    "addr:postcode":"h1x 2t5",
    "addr:street":"16E Av",
    "iso:country":"CA",
    "sg:address":"6855 16E Av",
    "sg:city":"Montreal",
    "sg:classifiers":[
        {
            "category":"Education",
            "subcategory":"School",
            "type":"Public Place"
        }
    ],
    "sg:phone":"+1 514 596 4166",
    "sg:postcode":"H1X 2T5",
    "sg:province":"QC",
    "wof:name":"Ste-Bernadette-Soubirous Ecole",
    "wof:placetype":"venue"
},
  "geometry": {"coordinates":[-73.58934021,45.5604133606],"type":"Point"}
}