{
  "type": "Feature",
  "properties": {
    "addr:full":"102 Mckendry Ave W Melfort SK S0E 1A0",
    "addr:housenumber":"102",
    "addr:postcode":"s0e 1a0",
    "addr:street":"Mckendry Ave W Melfort",
    "iso:country":"CA",
    "sg:address":"102 Mckendry Ave W",
    "sg:city":"Melfort",
    "sg:classifiers":[
        {
            "category":"Food & Beverages",
            "subcategory":"Groceries & Convenience Stores",
            "type":"Retail Goods"
        }
    ],
    "sg:phone":"+1 306 752 1900",
    "sg:postcode":"S0E 1A0",
    "sg:province":"SK",
    "sg:tags":[
        "product",
        "health",
        "diet"
    ],
    "wof:name":"Nutter's Bulk & Natural Foods",
    "wof:placetype":"venue"
},
  "geometry": {"coordinates":[-104.60826873800001,52.8679046631],"type":"Point"}
}