{
  "type": "Feature",
  "properties": {
    "addr:full":"7762 Progress Way Delta BC V4G 1A4",
    "addr:housenumber":"7762",
    "addr:postcode":"v4g 1a4",
    "addr:street":"Progress Way",
    "iso:country":"CA",
    "sg:address":"7762 Progress Way",
    "sg:city":"Delta",
    "sg:classifiers":[
        {
            "category":"Wholesale",
            "subcategory":"Groceries",
            "type":"Manufacturing & Wholesale Goods"
        }
    ],
    "sg:phone":"+1 604 946 7625",
    "sg:postcode":"V4G 1A4",
    "sg:province":"BC",
    "sg:tags":[
        "chips",
        "potato"
    ],
    "wof:name":"Hostess Frito-Lay",
    "wof:placetype":"venue"
},
  "geometry": {"coordinates":[-123.008217,49.137245],"type":"Point"}
}