{
  "type": "Feature",
  "properties": {
    "addr:full":"Vancouver BC V6A 1A4",
    "addr:postcode":"v6a 1a4",
    "iso:country":"CA",
    "sg:city":"Vancouver",
    "sg:classifiers":[
        {
            "category":"Professional",
            "subcategory":"Computer Services",
            "type":"Services"
        }
    ],
    "sg:phone":"+1 604 685 4310",
    "sg:postcode":"V6A 1A4",
    "sg:province":"BC",
    "sg:tags":[
        "internet"
    ],
    "wof:name":"Blue Zone Entertainment Inc",
    "wof:placetype":"venue"
},
  "geometry": {"coordinates":[-123.097008,49.284649],"type":"Point"}
}