{
  "type": "Feature",
  "properties": {
    "addr:full":"Russell MB R0J 1W0",
    "addr:postcode":"r0j 1w0",
    "iso:country":"CA",
    "sg:city":"Russell",
    "sg:classifiers":[
        {
            "category":"Social Services",
            "type":"Services"
        }
    ],
    "sg:phone":"+1 204 773 3852",
    "sg:postcode":"R0J 1W0",
    "sg:province":"MB",
    "sg:tags":[
        "organization",
        "welfare"
    ],
    "wof:name":"Parkland Regional Community",
    "wof:placetype":"venue"
},
  "geometry": {"coordinates":[-101.288269,50.773129],"type":"Point"}
}