{
  "type": "Feature",
  "properties": {
    "addr:full":"235 Main St W Hamilton ON L8P 1J5",
    "addr:housenumber":"235",
    "addr:postcode":"l8p 1j5",
    "addr:street":"Main St W",
    "iso:country":"CA",
    "sg:address":"235 Main St W",
    "sg:city":"Hamilton",
    "sg:classifiers":[
        {
            "category":"Autos & Motor Vehicles",
            "subcategory":"Auto Supplies",
            "type":"Retail Goods"
        }
    ],
    "sg:phone":"+1 905 527 5255",
    "sg:postcode":"L8P 1J5",
    "sg:province":"ON",
    "sg:tags":[
        "equipment",
        "air",
        "conditioning",
        "automobile"
    ],
    "wof:name":"Forbes Service Ctr Ltd",
    "wof:placetype":"venue"
},
  "geometry": {"coordinates":[-79.8797531128,43.2575950623],"type":"Point"}
}