{
  "type": "Feature",
  "properties": {
    "iso:country":"CA",
    "sg:city":"Kelowna",
    "sg:classifiers":[
        {
            "category":"Shopping",
            "subcategory":"Clothing, Apparel, & Fashions",
            "type":"Retail Goods"
        }
    ],
    "sg:phone":"+1 250 762 4741",
    "sg:postcode":"V1Y 8J8",
    "sg:province":"BC",
    "sg:tags":[
        "jean"
    ],
    "wof:name":"Warehouse One the Jeans Store",
    "wof:placetype":"venue"
},
  "geometry": {"coordinates":[-119.452095032,49.8820953369],"type":"Point"}
}