{
  "type": "Feature",
  "properties": {
    "addr:full":"8118 Beddington Blvd NW Calgary AB T3K 2R6",
    "addr:housenumber":"8118",
    "addr:postcode":"t3k 2r6",
    "addr:street":"Beddington Blvd Nw",
    "iso:country":"CA",
    "sg:address":"8118 Beddington Blvd NW",
    "sg:city":"Calgary",
    "sg:classifiers":[
        {
            "category":"Banks & Credit Unions",
            "subcategory":"Bank",
            "type":"Services"
        }
    ],
    "sg:phone":"+1 403 275 4033",
    "sg:postcode":"T3K 2R6",
    "sg:province":"AB",
    "wof:name":"Td Canada Trust",
    "wof:placetype":"venue"
},
  "geometry": {"coordinates":[-114.072884,51.125404],"type":"Point"}
}