{
  "type": "Feature",
  "properties": {
    "addr:full":"109 Vaughan Rd York ON M6C 2L9",
    "addr:housenumber":"109",
    "addr:postcode":"m6c 2l9",
    "addr:street":"Vaughan Rd",
    "iso:country":"CA",
    "sg:address":"109 Vaughan Rd",
    "sg:city":"York",
    "sg:classifiers":[
        {
            "category":"Shopping",
            "subcategory":"Books",
            "type":"Retail Goods"
        }
    ],
    "sg:phone":"+1 416 656 6564",
    "sg:postcode":"M6C 2L9",
    "sg:province":"ON",
    "sg:tags":[
        "dealer"
    ],
    "wof:name":"Occult Shop",
    "wof:placetype":"venue"
},
  "geometry": {"coordinates":[-79.421066,43.684067],"type":"Point"}
}