{
  "type": "Feature",
  "properties": {
    "addr:full":"203 Main St S Eston SK S0L 1A0",
    "addr:housenumber":"203",
    "addr:postcode":"s0l 1a0",
    "addr:street":"Main St S Eston",
    "iso:country":"CA",
    "sg:address":"203 Main St S",
    "sg:city":"Eston",
    "sg:classifiers":[
        {
            "category":"Real Estate",
            "subcategory":"Real Estate Agent",
            "type":"Services"
        }
    ],
    "sg:phone":"+1 306 962 3645",
    "sg:postcode":"S0L 1A0",
    "sg:province":"SK",
    "sg:tags":[
        "cooperative"
    ],
    "wof:name":"Eston CO-Operative Assn Ltd",
    "wof:placetype":"venue"
},
  "geometry": {"coordinates":[-108.75290699999999,51.152874],"type":"Point"}
}