{
  "type": "Feature",
  "properties": {
    "addr:full":"119 Marina Blvd Peterborough ON K9H 6M7",
    "addr:housenumber":"119",
    "addr:postcode":"k9h 6m7",
    "addr:street":"Marina Blvd",
    "iso:country":"CA",
    "sg:address":"119 Marina Blvd",
    "sg:city":"Peterborough",
    "sg:classifiers":[
        {
            "category":"Building & Trades",
            "subcategory":"Construction",
            "type":"Services"
        }
    ],
    "sg:phone":"+1 705 743 3250",
    "sg:postcode":"K9H 6M7",
    "sg:province":"ON",
    "sg:tags":[
        "home",
        "general",
        "improvement",
        "contractor"
    ],
    "wof:name":"Contrast Home Renovations Plus",
    "wof:placetype":"venue"
},
  "geometry": {"coordinates":[-78.31755099999999,44.33498],"type":"Point"}
}