{
  "type": "Feature",
  "properties": {
    "addr:full":"163 Baseline Rd E Bowmanville ON L1C 3L4",
    "addr:housenumber":"163",
    "addr:postcode":"l1c 3l4",
    "addr:street":"Baseline Rd E",
    "iso:country":"CA",
    "sg:address":"163 Baseline Rd E",
    "sg:city":"Bowmanville",
    "sg:classifiers":[
        {
            "category":"Retail",
            "subcategory":"Auto Repair",
            "type":"Services"
        }
    ],
    "sg:phone":"+1 905 623 6353",
    "sg:postcode":"L1C 3L4",
    "sg:province":"ON",
    "sg:tags":[
        "body",
        "automobile",
        "painting"
    ],
    "wof:name":"Fred's Auto Body",
    "wof:placetype":"venue"
},
  "geometry": {"coordinates":[-78.668251,43.90276],"type":"Point"}
}