{
  "type": "Feature",
  "properties": {
    "addr:full":"12103 64 St NW Edmonton AB T5W 4J8",
    "addr:housenumber":"12103",
    "addr:postcode":"t5w 4j8",
    "addr:street":"64 St Nw",
    "iso:country":"CA",
    "sg:address":"12103 64 St NW",
    "sg:city":"Edmonton",
    "sg:classifiers":[
        {
            "category":"Personal",
            "subcategory":"Beauty Salon",
            "type":"Services"
        }
    ],
    "sg:phone":"+1 780 471 2420",
    "sg:postcode":"T5W 4J8",
    "sg:province":"AB",
    "wof:name":"Mary Cholak Hairdressing",
    "wof:placetype":"venue"
},
  "geometry": {"coordinates":[-113.439629,53.575314],"type":"Point"}
}