{
  "type": "Feature",
  "properties": {
    "addr:full":"36 Main St N Gilbert Plains MB R0L 0X0",
    "addr:housenumber":"36",
    "addr:postcode":"r0l 0x0",
    "addr:street":"Main St N Gilbert",
    "iso:country":"CA",
    "sg:address":"36 Main St N",
    "sg:city":"Gilbert Plains",
    "sg:classifiers":[
        {
            "category":"Professional",
            "subcategory":"Lawyer & Legal Services",
            "type":"Services"
        }
    ],
    "sg:phone":"+1 204 548 2572",
    "sg:postcode":"R0L 0X0",
    "sg:province":"MB",
    "sg:tags":[
        "attorney"
    ],
    "wof:name":"Johnston & CO",
    "wof:placetype":"venue"
},
  "geometry": {"coordinates":[-100.485572815,51.1472663879],"type":"Point"}
}