{
  "type": "Feature",
  "properties": {
    "addr:full":"1122 Boul DE Sainte-Adele Sainte-Adele QC J8B 2N5",
    "addr:housenumber":"1122",
    "addr:postcode":"j8b 2n5",
    "addr:street":"Boul De Sainte-Adele Sainte-Adele",
    "iso:country":"CA",
    "sg:address":"1122 Boul DE Sainte-Adele",
    "sg:city":"Sainte-Adele",
    "sg:classifiers":[
        {
            "category":"Travel",
            "subcategory":"Hotels & Motels",
            "type":"Entertainment"
        }
    ],
    "sg:phone":"+1 450 229 5555",
    "sg:postcode":"J8B 2N5",
    "sg:province":"QC",
    "wof:name":"Joes Restaurant",
    "wof:placetype":"venue"
},
  "geometry": {"coordinates":[-74.120407,45.986362],"type":"Point"}
}