{
  "type": "Feature",
  "properties": {
    "iso:country":"CA",
    "sg:city":"Oakville",
    "sg:classifiers":[
        {
            "category":"Manufacturing",
            "subcategory":"Printing",
            "type":"Manufacturing & Wholesale Goods"
        }
    ],
    "sg:phone":"+1 905 847 2424",
    "sg:postcode":"L6L 6M5",
    "sg:province":"ON",
    "sg:tags":[
        "foil",
        "metal",
        "label"
    ],
    "wof:name":"Vecc Industries Inc",
    "wof:placetype":"venue"
},
  "geometry": {"coordinates":[-79.7347488403,43.4127502441],"type":"Point"}
}