{
  "type": "Feature",
  "properties": {
    "iso:country":"CA",
    "sg:address":"271 Old Kingston Rd",
    "sg:city":"Scarborough",
    "sg:classifiers":[
        {
            "category":"Personal",
            "subcategory":"Barber",
            "type":"Services"
        }
    ],
    "sg:phone":"+1 416 286 9573",
    "sg:postcode":"M1C 1B4",
    "sg:province":"ON",
    "wof:name":"Barber Shop",
    "wof:placetype":"venue"
},
  "geometry": {"coordinates":[-79.172492981,43.7820091248],"type":"Point"}
}