{
  "type": "Feature",
  "properties": {
    "addr:full":"1297 Marlborough Crt Oakville ON L6H 2S1",
    "addr:housenumber":"1297",
    "addr:postcode":"l6h 2s1",
    "addr:street":"Marlborough Crt",
    "iso:country":"CA",
    "sg:address":"1297 Marlborough Crt",
    "sg:city":"Oakville",
    "sg:classifiers":[
        {
            "category":"Building & Trades",
            "subcategory":"Construction",
            "type":"Services"
        }
    ],
    "sg:phone":"+1 905 338 8032",
    "sg:postcode":"L6H 2S1",
    "sg:province":"ON",
    "sg:tags":[
        "painter"
    ],
    "wof:name":"Mister Paint",
    "wof:placetype":"venue"
},
  "geometry": {"coordinates":[-79.693512,43.469559],"type":"Point"}
}