{
  "type": "Feature",
  "properties": {
    "addr:full":"181 Rue Du Pont Vallee-Jonction QC G0S 3J0",
    "addr:housenumber":"181",
    "addr:postcode":"g0s 3j0",
    "addr:street":"Rue Du Pont Vallee-Jonction",
    "iso:country":"CA",
    "sg:address":"181 Rue Du Pont",
    "sg:city":"Vallee-Jonction",
    "sg:classifiers":[
        {
            "category":"Personal",
            "subcategory":"Beauty Salon",
            "type":"Services"
        }
    ],
    "sg:phone":"+1 418 253 6243",
    "sg:postcode":"G0S 3J0",
    "sg:province":"QC",
    "wof:name":"Salon Denise",
    "wof:placetype":"venue"
},
  "geometry": {"coordinates":[-70.926292,46.376053],"type":"Point"}
}