{
  "type": "Feature",
  "properties": {
    "addr:full":"10020 115 St NW Edmonton AB T5K 1T2",
    "addr:housenumber":"10020",
    "addr:postcode":"t5k 1t2",
    "addr:street":"115 St Nw",
    "iso:country":"CA",
    "sg:address":"10020 115 St NW",
    "sg:city":"Edmonton",
    "sg:classifiers":[
        {
            "category":"Real Estate",
            "subcategory":"Real Estate Operator",
            "type":"Services"
        }
    ],
    "sg:phone":"+1 780 413 1985",
    "sg:postcode":"T5K 1T2",
    "sg:province":"AB",
    "sg:tags":[
        "apartment"
    ],
    "wof:name":"Deville Apartments",
    "wof:placetype":"venue"
},
  "geometry": {"coordinates":[-113.519676,53.539402],"type":"Point"}
}