{
  "type": "Feature",
  "properties": {
    "addr:full":"8405 Boul Raoul-Duchesne Becancour QC G9H 2V5",
    "addr:housenumber":"8405",
    "addr:postcode":"g9h 2v5",
    "addr:street":"Boul Raoul-Duchesne Becancour",
    "iso:country":"CA",
    "sg:address":"8405 Boul Raoul-Duchesne",
    "sg:city":"Becancour",
    "sg:classifiers":[
        {
            "category":"Building & Trades",
            "subcategory":"Construction",
            "type":"Services"
        }
    ],
    "sg:phone":"+1 819 294 6646",
    "sg:postcode":"G9H 2V5",
    "sg:province":"QC",
    "sg:tags":[
        "excavating",
        "contractor",
        "trucking"
    ],
    "wof:name":"Excavation 2000",
    "wof:placetype":"venue"
},
  "geometry": {"coordinates":[-72.420326,46.361],"type":"Point"}
}