{
  "type": "Feature",
  "properties": {
    "addr:full":"17 Lynndale Dr Dundas ON L9H 3L4",
    "addr:housenumber":"17",
    "addr:postcode":"l9h 3l4",
    "addr:street":"Lynndale Dr",
    "iso:country":"CA",
    "sg:address":"17 Lynndale Dr",
    "sg:city":"Dundas",
    "sg:classifiers":[
        {
            "category":"Professional",
            "subcategory":"Engineering",
            "type":"Services"
        }
    ],
    "sg:phone":"+1 905 628 4682",
    "sg:postcode":"L9H 3L4",
    "sg:province":"ON",
    "sg:tags":[
        "engineer"
    ],
    "wof:name":"Alan A Smith Inc",
    "wof:placetype":"venue"
},
  "geometry": {"coordinates":[-79.970375061,43.258556366],"type":"Point"}
}