{
  "type": "Feature",
  "properties": {
    "addr:full":"66 Wellington St W Barrie ON L4N 1K4",
    "addr:housenumber":"66",
    "addr:postcode":"l4n 1k4",
    "addr:street":"Wellington St W",
    "iso:country":"CA",
    "sg:address":"66 Wellington St W",
    "sg:city":"Barrie",
    "sg:classifiers":[
        {
            "category":"Health Services",
            "subcategory":"Doctor",
            "type":"Services"
        }
    ],
    "sg:phone":"+1 705 728 0912",
    "sg:postcode":"L4N 1K4",
    "sg:province":"ON",
    "sg:tags":[
        "clinic"
    ],
    "wof:name":"Dialysis Clinic",
    "wof:placetype":"venue"
},
  "geometry": {"coordinates":[-79.6996841431,44.3918838501],"type":"Point"}
}