{
  "type": "Feature",
  "properties": {
    "addr:full":"403 Main St Hwy 35 Manning AB T0H 2M0",
    "addr:housenumber":"403",
    "addr:postcode":"t0h 2m0",
    "addr:street":"Main St Hwy 35",
    "iso:country":"CA",
    "sg:address":"403 Main St Hwy 35",
    "sg:city":"Manning",
    "sg:classifiers":[
        {
            "category":"Shopping",
            "subcategory":"Pharmacy",
            "type":"Retail Goods"
        }
    ],
    "sg:phone":"+1 780 836 3043",
    "sg:postcode":"T0H 2M0",
    "sg:province":"AB",
    "wof:name":"Manning Value Drug Mart",
    "wof:placetype":"venue"
},
  "geometry": {"coordinates":[-117.629928589,56.9220504761],"type":"Point"}
}