{
  "type": "Feature",
  "properties": {
    "addr:full":"1320 2nd Ave Prince George BC V2L 3B5",
    "addr:housenumber":"1320",
    "addr:postcode":"v2l 3b5",
    "addr:street":"2Nd Ave",
    "iso:country":"CA",
    "sg:address":"1320 2nd Ave",
    "sg:city":"Prince George",
    "sg:classifiers":[
        {
            "category":"Home & Garden",
            "subcategory":"Building Materials",
            "type":"Retail Goods"
        }
    ],
    "sg:phone":"+1 250 562 9899",
    "sg:postcode":"V2L 3B5",
    "sg:province":"BC",
    "sg:tags":[
        "glass",
        "window",
        "plate"
    ],
    "wof:name":"Glass Express",
    "wof:placetype":"venue"
},
  "geometry": {"coordinates":[-122.74567413299999,53.9180297852],"type":"Point"}
}