{
  "type": "Feature",
  "properties": {
    "iso:country":"CA",
    "sg:address":"2701 25E Rue",
    "sg:city":"Grand-Mere",
    "sg:classifiers":[
        {
            "category":"Freight",
            "type":"Transportation"
        }
    ],
    "sg:phone":"+1 819 538 2225",
    "sg:postcode":"G9T 3R8",
    "sg:province":"QC",
    "sg:tags":[
        "trucking"
    ],
    "wof:name":"Mario Briere Transport Inc",
    "wof:placetype":"venue"
},
  "geometry": {"coordinates":[-72.695274353,46.6131134033],"type":"Point"}
}