{
  "type": "Feature",
  "properties": {
    "addr:full":"474 Rue DE L'Hotel-DE-Ville Farnham QC J2N 2H2",
    "addr:housenumber":"474",
    "addr:postcode":"j2n 2h2",
    "addr:street":"Rue De L'Hotel-De-Ville",
    "iso:country":"CA",
    "sg:address":"474 Rue DE L'Hotel-DE-Ville",
    "sg:city":"Farnham",
    "sg:classifiers":[
        {
            "category":"Professional",
            "subcategory":"Business Services",
            "type":"Services"
        }
    ],
    "sg:phone":"+1 450 293 8645",
    "sg:postcode":"J2N 2H2",
    "sg:province":"QC",
    "sg:tags":[
        "notary"
    ],
    "wof:name":"Landry, Maryse",
    "wof:placetype":"venue"
},
  "geometry": {"coordinates":[-72.978172,45.282303],"type":"Point"}
}