{
  "type": "Feature",
  "properties": {
    "addr:full":"22 Princess St Cayuga ON N0A 1E0",
    "addr:housenumber":"22",
    "addr:postcode":"n0a 1e0",
    "addr:street":"Princess St",
    "iso:country":"CA",
    "sg:address":"22 Princess St",
    "sg:city":"Cayuga",
    "sg:classifiers":[
        {
            "category":"Personal",
            "subcategory":"Beauty Salon",
            "type":"Services"
        }
    ],
    "sg:phone":"+1 905 772 5431",
    "sg:postcode":"N0A 1E0",
    "sg:province":"ON",
    "wof:name":"Alma's Hairstyling",
    "wof:placetype":"venue"
},
  "geometry": {"coordinates":[-79.84864,42.946213],"type":"Point"}
}