{
  "type": "Feature",
  "properties": {
    "addr:full":"844 Wonderland Rd S London ON N6K 2V8",
    "addr:housenumber":"844",
    "addr:postcode":"n6k 2v8",
    "addr:street":"Wonderland Rd",
    "iso:country":"CA",
    "sg:address":"844 Wonderland Rd S",
    "sg:city":"London",
    "sg:classifiers":[
        {
            "category":"Personal",
            "subcategory":"Beauty Salon",
            "type":"Services"
        }
    ],
    "sg:phone":"+1 519 474 7204",
    "sg:postcode":"N6K 2V8",
    "sg:province":"ON",
    "wof:name":"Hair Gallery",
    "wof:placetype":"venue"
},
  "geometry": {"coordinates":[-81.28840599999999,42.945461],"type":"Point"}
}