{
  "type": "Feature",
  "properties": {
    "addr:full":"12535 133 St NW Edmonton AB T5L 1S5",
    "addr:housenumber":"12535",
    "addr:postcode":"t5l 1s5",
    "addr:street":"133 St Nw",
    "iso:country":"CA",
    "sg:address":"12535 133 St NW",
    "sg:city":"Edmonton",
    "sg:classifiers":[
        {
            "category":"Wholesale",
            "subcategory":"Scrap",
            "type":"Manufacturing & Wholesale Goods"
        }
    ],
    "sg:phone":"+1 780 455 8363",
    "sg:postcode":"T5L 1S5",
    "sg:province":"AB",
    "sg:tags":[
        "recycling",
        "can",
        "bottle",
        "depot"
    ],
    "wof:name":"Bottle King",
    "wof:placetype":"venue"
},
  "geometry": {"coordinates":[-113.555503845,53.5822525024],"type":"Point"}
}