{
  "type": "Feature",
  "properties": {
    "addr:full":"210 Main St E Hawkesbury ON K6A 1A5",
    "addr:housenumber":"210",
    "addr:postcode":"k6a 1a5",
    "addr:street":"Main St E",
    "iso:country":"CA",
    "sg:address":"210 Main St E",
    "sg:city":"Hawkesbury",
    "sg:classifiers":[
        {
            "category":"Health Services",
            "subcategory":"Optometrist",
            "type":"Services"
        }
    ],
    "sg:phone":"+1 613 632 3937",
    "sg:postcode":"K6A 1A5",
    "sg:province":"ON",
    "wof:name":"Hawkesbury Optometric Clinic",
    "wof:placetype":"venue"
},
  "geometry": {"coordinates":[-74.6089630127,45.6097106934],"type":"Point"}
}