{
  "type": "Feature",
  "properties": {
    "iso:country":"CA",
    "sg:address":"198 Boul DE Gaspe",
    "sg:city":"Gaspe",
    "sg:classifiers":[
        {
            "category":"Professional",
            "subcategory":"Research",
            "type":"Services"
        }
    ],
    "sg:phone":"+1 418 368 5597",
    "sg:postcode":"G4X 1B1",
    "sg:province":"QC",
    "sg:tags":[
        "environmental",
        "ecological",
        "association"
    ],
    "wof:name":"Biorex Inc",
    "wof:placetype":"venue"
},
  "geometry": {"coordinates":[-64.4875411987,48.8411521912],"type":"Point"}
}