{
  "type": "Feature",
  "properties": {
    "addr:full":"7218 Progress Way Delta BC V4G 1H2",
    "addr:housenumber":"7218",
    "addr:postcode":"v4g 1h2",
    "addr:street":"Progress Way",
    "iso:country":"CA",
    "sg:address":"7218 Progress Way",
    "sg:city":"Delta",
    "sg:classifiers":[
        {
            "category":"Wholesale",
            "subcategory":"Machinery & Supplies",
            "type":"Manufacturing & Wholesale Goods"
        }
    ],
    "sg:phone":"+1 604 940 4266",
    "sg:postcode":"V4G 1H2",
    "sg:province":"BC",
    "sg:tags":[
        "heat",
        "exchanger"
    ],
    "wof:name":"Bay Industrial Instruments Ltd",
    "wof:placetype":"venue"
},
  "geometry": {"coordinates":[-123.02282700000001,49.133282],"type":"Point"}
}