{
  "type": "Feature",
  "properties": {
    "addr:full":"333 Rue Notre-Dame E Montreal QC H2Y 3Z2",
    "addr:housenumber":"333",
    "addr:postcode":"h2y 3z2",
    "addr:street":"Rue Notre-Dame E",
    "iso:country":"CA",
    "sg:address":"333 Rue Notre-Dame E",
    "sg:city":"Montreal",
    "sg:classifiers":[
        {
            "category":"Manufacturing",
            "subcategory":"Printing",
            "type":"Manufacturing & Wholesale Goods"
        }
    ],
    "sg:phone":"+1 514 876 1770",
    "sg:postcode":"H2Y 3Z2",
    "sg:province":"QC",
    "sg:tags":[
        "multimedia"
    ],
    "wof:name":"Archi Data Inc",
    "wof:placetype":"venue"
},
  "geometry": {"coordinates":[-73.55322265620001,45.5095367432],"type":"Point"}
}