{
  "type": "Feature",
  "properties": {
    "addr:full":"Peterborough ON K9J 2J4",
    "addr:postcode":"k9j 2j4",
    "iso:country":"CA",
    "sg:city":"Peterborough",
    "sg:classifiers":[
        {
            "category":"Recreation",
            "type":"Entertainment"
        }
    ],
    "sg:phone":"+1 705 745 2333",
    "sg:postcode":"K9J 2J4",
    "sg:province":"ON",
    "sg:tags":[
        "amusement"
    ],
    "wof:name":"Rock & Rope Climbing Ctr",
    "wof:placetype":"venue"
},
  "geometry": {"coordinates":[-78.322731,44.294647],"type":"Point"}
}