{
  "type": "Feature",
  "properties": {
    "addr:full":"469 Powell St Vancouver BC V6A 1G7",
    "addr:housenumber":"469",
    "addr:postcode":"v6a 1g7",
    "addr:street":"Powell St",
    "iso:country":"CA",
    "sg:address":"469 Powell St",
    "sg:city":"Vancouver",
    "sg:classifiers":[
        {
            "category":"Food & Beverages",
            "subcategory":"Meat & Fish",
            "type":"Retail Goods"
        }
    ],
    "sg:phone":"+1 604 254 2620",
    "sg:postcode":"V6A 1G7",
    "sg:province":"BC",
    "wof:name":"Pay-Less Meats",
    "wof:placetype":"venue"
},
  "geometry": {"coordinates":[-123.093948,49.283237],"type":"Point"}
}