{
  "type": "Feature",
  "properties": {
    "addr:full":"235 Indian Rd S Sarnia ON N7T 3W5",
    "addr:housenumber":"235",
    "addr:postcode":"n7t 3w5",
    "addr:street":"Indian Rd S",
    "iso:country":"CA",
    "sg:address":"235 Indian Rd S",
    "sg:city":"Sarnia",
    "sg:classifiers":[
        {
            "category":"Autos & Motor Vehicles",
            "subcategory":"Automobile Sales",
            "type":"Retail Goods"
        }
    ],
    "sg:phone":"+1 519 337 4550",
    "sg:postcode":"N7T 3W5",
    "sg:province":"ON",
    "sg:tags":[
        "car",
        "dealer"
    ],
    "wof:name":"Payless Auto Mart",
    "wof:placetype":"venue"
},
  "geometry": {"coordinates":[-82.37646484379999,42.9629936218],"type":"Point"}
}