{
  "type": "Feature",
  "properties": {
    "addr:full":"9881 Seaport Pl Sidney BC V8L 4X3",
    "addr:housenumber":"9881",
    "addr:postcode":"v8l 4x3",
    "addr:street":"Seaport Pl",
    "iso:country":"CA",
    "sg:address":"9881 Seaport Pl",
    "sg:city":"Sidney",
    "sg:classifiers":[
        {
            "category":"Restaurant",
            "type":"Food & Drink"
        }
    ],
    "sg:phone":"+1 250 656 5643",
    "sg:postcode":"V8L 4X3",
    "sg:province":"BC",
    "sg:tags":[
        "pub"
    ],
    "wof:name":"Rumrunner Pub",
    "wof:placetype":"venue"
},
  "geometry": {"coordinates":[-123.39484405499999,48.6500816345],"type":"Point"}
}