{
  "type": "Feature",
  "properties": {
    "iso:country":"CA",
    "sg:address":"192 St David St",
    "sg:city":"Lindsay",
    "sg:classifiers":[
        {
            "category":"Professional",
            "subcategory":"Computer Services",
            "type":"Services"
        }
    ],
    "sg:phone":"+1 705 878 1888",
    "sg:postcode":"K9V 4Z4",
    "sg:province":"ON",
    "sg:tags":[
        "internet"
    ],
    "wof:name":"Cyber Av Solutions",
    "wof:placetype":"venue"
},
  "geometry": {"coordinates":[-78.7316360474,44.3719100952],"type":"Point"}
}