{
  "type": "Feature",
  "properties": {
    "addr:full":"1140 Albert St Regina SK S4R 2R1",
    "addr:housenumber":"1140",
    "addr:postcode":"s4r 2r1",
    "addr:street":"Albert St",
    "iso:country":"CA",
    "sg:address":"1140 Albert St",
    "sg:city":"Regina",
    "sg:classifiers":[
        {
            "category":"Professional",
            "subcategory":"Business Services",
            "type":"Services"
        }
    ],
    "sg:phone":"+1 306 757 0033",
    "sg:postcode":"S4R 2R1",
    "sg:province":"SK",
    "sg:tags":[
        "consultant",
        "trademark",
        "agent"
    ],
    "wof:name":"Edge Manufacturing Corp",
    "wof:placetype":"venue"
},
  "geometry": {"coordinates":[-104.61843109100001,50.4607391357],"type":"Point"}
}