{
  "type": "Feature",
  "properties": {
    "iso:country":"CA",
    "sg:address":"554 Rue Jean-Talon O",
    "sg:city":"Montreal",
    "sg:classifiers":[
        {
            "category":"Shopping",
            "subcategory":"Used Merchandise",
            "type":"Retail Goods"
        }
    ],
    "sg:phone":"+1 514 948 1999",
    "sg:postcode":"H3N 1R5",
    "sg:province":"QC",
    "sg:tags":[
        "pawnbroker"
    ],
    "wof:name":"Preteur Du Parc",
    "wof:placetype":"venue"
},
  "geometry": {"coordinates":[-73.61363220210001,45.5395736694],"type":"Point"}
}