{
  "type": "Feature",
  "properties": {
    "addr:full":"Winnipeg MB R3H 1B5",
    "addr:postcode":"r3h 1b5",
    "iso:country":"CA",
    "sg:city":"Winnipeg",
    "sg:classifiers":[
        {
            "category":"Government",
            "subcategory":"Office",
            "type":"Public Place"
        }
    ],
    "sg:phone":"+1 204 784 4350",
    "sg:postcode":"R3H 1B5",
    "sg:province":"MB",
    "sg:tags":[
        "environmental",
        "org"
    ],
    "wof:name":"Manitoba Habitat Heritage Corp",
    "wof:placetype":"venue"
},
  "geometry": {"coordinates":[-97.19911999999999,49.910049],"type":"Point"}
}