{
  "type": "Feature",
  "properties": {
    "iso:country":"CA",
    "sg:address":"5170 Ninth Line Rr2",
    "sg:city":"Hornby",
    "sg:classifiers":[
        {
            "category":"Retail",
            "subcategory":"Veterinary Services",
            "type":"Services"
        }
    ],
    "sg:phone":"+1 905 608 2494",
    "sg:postcode":"L0P 1E0",
    "sg:province":"ON",
    "sg:tags":[
        "veterinarian"
    ],
    "wof:name":"Churchill Meadows Animal Hosp",
    "wof:placetype":"venue"
},
  "geometry": {"coordinates":[-79.83795166020001,43.5715789795],"type":"Point"}
}