{
  "type": "Feature",
  "properties": {
    "addr:full":"52 Samor Rd North York ON M6A 1J6",
    "addr:housenumber":"52",
    "addr:postcode":"m6a 1j6",
    "addr:street":"Samor Rd",
    "iso:country":"CA",
    "sg:address":"52 Samor Rd",
    "sg:city":"North York",
    "sg:classifiers":[
        {
            "category":"Wholesale",
            "subcategory":"Groceries",
            "type":"Manufacturing & Wholesale Goods"
        }
    ],
    "sg:phone":"+1 416 789 7539",
    "sg:postcode":"M6A 1J6",
    "sg:province":"ON",
    "sg:tags":[
        "confectionery",
        "candy"
    ],
    "wof:name":"Bemco Wholesale Confectionery",
    "wof:placetype":"venue"
},
  "geometry": {"coordinates":[-79.4593505859,43.7178268433],"type":"Point"}
}