{
  "type": "Feature",
  "properties": {
    "iso:country":"CA",
    "sg:address":"181 Belmont Ave",
    "sg:city":"Hamilton",
    "sg:classifiers":[
        {
            "category":"Education",
            "subcategory":"School",
            "type":"Public Place"
        }
    ],
    "sg:phone":"+1 905 549 6767",
    "sg:postcode":"L8L 7M5",
    "sg:province":"ON",
    "wof:name":"Holy Name of Jesus School",
    "wof:placetype":"venue"
},
  "geometry": {"coordinates":[-79.822678,43.249477],"type":"Point"}
}