{
  "type": "Feature",
  "properties": {
    "addr:full":"1st Ave O Saint-Eugene-DE-Guigues QC J0Z 3L0",
    "addr:postcode":"j0z 3l0",
    "addr:street":"1St Ave O Saint-Eugene-De-Guigues",
    "iso:country":"CA",
    "sg:address":"1st Ave O",
    "sg:city":"Saint-Eugene-DE-Guigues",
    "sg:classifiers":[
        {
            "category":"Government",
            "subcategory":"Office",
            "type":"Public Place"
        }
    ],
    "sg:phone":"+1 819 785 4441",
    "sg:postcode":"J0Z 3L0",
    "sg:province":"QC",
    "sg:tags":[
        "village"
    ],
    "wof:name":"St-Eugene-DE-Guiges Centre",
    "wof:placetype":"venue"
},
  "geometry": {"coordinates":[-79.35219600000001,47.510361],"type":"Point"}
}