{
  "type": "Feature",
  "properties": {
    "addr:full":"513 Boul L'Assomption Repentigny QC J6A 6Y5",
    "addr:housenumber":"513",
    "addr:postcode":"j6a 6y5",
    "addr:street":"Boul L'Assomption",
    "iso:country":"CA",
    "sg:address":"513 Boul L'Assomption",
    "sg:city":"Repentigny",
    "sg:classifiers":[
        {
            "category":"Health Services",
            "subcategory":"Chiropractor",
            "type":"Services"
        }
    ],
    "sg:phone":"+1 450 654 9506",
    "sg:postcode":"J6A 6Y5",
    "sg:province":"QC",
    "wof:name":"Tremblay, Jacques DC",
    "wof:placetype":"venue"
},
  "geometry": {"coordinates":[-73.4440612793,45.7554397583],"type":"Point"}
}