{
  "type": "Feature",
  "properties": {
    "addr:full":"Sudbury ON P3E 2K8",
    "addr:postcode":"p3e 2k8",
    "iso:country":"CA",
    "sg:city":"Sudbury",
    "sg:classifiers":[
        {
            "category":"Banks & Credit Unions",
            "subcategory":"Investment Brokerage",
            "type":"Services"
        }
    ],
    "sg:phone":"+1 705 523 6565",
    "sg:postcode":"P3E 2K8",
    "sg:province":"ON",
    "wof:name":"Thomas Young Financial Svc",
    "wof:placetype":"venue"
},
  "geometry": {"coordinates":[-81.0115280151,46.460811615],"type":"Point"}
}