{
  "type": "Feature",
  "properties": {
    "addr:full":"70 Ward Rd Brampton ON L6S 4L5",
    "addr:housenumber":"70",
    "addr:postcode":"l6s 4l5",
    "addr:street":"Ward Rd",
    "iso:country":"CA",
    "sg:address":"70 Ward Rd",
    "sg:city":"Brampton",
    "sg:classifiers":[
        {
            "category":"Freight",
            "type":"Transportation"
        }
    ],
    "sg:phone":"+1 905 789 1901",
    "sg:postcode":"L6S 4L5",
    "sg:province":"ON",
    "sg:tags":[
        "trucking"
    ],
    "wof:name":"Able Trucking",
    "wof:placetype":"venue"
},
  "geometry": {"coordinates":[-79.6987075806,43.7562103271],"type":"Point"}
}