{
  "type": "Feature",
  "properties": {
    "addr:full":"21 Woodlawn Rd Dartmouth NS B2W 2R7",
    "addr:housenumber":"21",
    "addr:postcode":"b2w 2r7",
    "addr:street":"Woodlawn Rd",
    "iso:country":"CA",
    "sg:address":"21 Woodlawn Rd",
    "sg:city":"Dartmouth",
    "sg:classifiers":[
        {
            "category":"Social Services",
            "type":"Services"
        }
    ],
    "sg:phone":"+1 902 469 9622",
    "sg:postcode":"B2W 2R7",
    "sg:province":"NS",
    "sg:tags":[
        "center",
        "club",
        "gymnasium",
        "youth",
        "health",
        "studio",
        "organization"
    ],
    "wof:name":"Ym-Ywca Dartmouth",
    "wof:placetype":"venue"
},
  "geometry": {"coordinates":[-63.5281944275,44.6826896667],"type":"Point"}
}