{
  "type": "Feature",
  "properties": {
    "addr:full":"Laval QC H7S 2B2",
    "addr:postcode":"h7s 2b2",
    "iso:country":"CA",
    "sg:city":"Laval",
    "sg:classifiers":[
        {
            "category":"Building & Trades",
            "subcategory":"Construction",
            "type":"Services"
        }
    ],
    "sg:phone":"+1 514 331 9365",
    "sg:postcode":"H7S 2B2",
    "sg:province":"QC",
    "sg:tags":[
        "insulation",
        "heat",
        "contractor"
    ],
    "wof:name":"Urethene Superieure DE Quebec",
    "wof:placetype":"venue"
},
  "geometry": {"coordinates":[-73.738693,45.578106],"type":"Point"}
}