{
  "type": "Feature",
  "properties": {
    "iso:country":"CA",
    "sg:address":"250 Shields Crt #12",
    "sg:city":"Markham",
    "sg:classifiers":[
        {
            "category":"Professional",
            "subcategory":"Computer Services",
            "type":"Services"
        }
    ],
    "sg:phone":"+1 416 441 9878",
    "sg:postcode":"L3R 9W7",
    "sg:province":"ON",
    "sg:tags":[
        "consultant"
    ],
    "wof:name":"Quasimodo Consulting Svc Ltd",
    "wof:placetype":"venue"
},
  "geometry": {"coordinates":[-79.36319,43.832451],"type":"Point"}
}