{
  "type": "Feature",
  "properties": {
    "addr:full":"168 Rue Rolland Sainte-Anne-Des-Plaines QC J0N 1H0",
    "addr:housenumber":"168",
    "addr:postcode":"j0n 1h0",
    "addr:street":"Rue Rolland",
    "iso:country":"CA",
    "sg:address":"168 Rue Rolland",
    "sg:city":"Sainte-Anne-Des-Plaines",
    "sg:classifiers":[
        {
            "category":"Wholesale",
            "subcategory":"Auto Parts",
            "type":"Manufacturing & Wholesale Goods"
        }
    ],
    "sg:phone":"+1 450 478 1934",
    "sg:postcode":"J0N 1H0",
    "sg:province":"QC",
    "sg:tags":[
        "equipment",
        "truck"
    ],
    "wof:name":"Pieces DE Camions Remi Lauzon",
    "wof:placetype":"venue"
},
  "geometry": {"coordinates":[-73.810806,45.760838],"type":"Point"}
}