{
  "type": "Feature",
  "properties": {
    "iso:country":"CA",
    "sg:city":"Salaberry-DE-Valleyfield",
    "sg:classifiers":[
        {
            "category":"Shopping",
            "subcategory":"Used Merchandise",
            "type":"Retail Goods"
        }
    ],
    "sg:phone":"+1 450 377 9408",
    "sg:postcode":"J6T 1P7",
    "sg:province":"QC",
    "sg:tags":[
        "second",
        "store",
        "hand"
    ],
    "wof:name":"Bon Marche",
    "wof:placetype":"venue"
},
  "geometry": {"coordinates":[-74.136131,45.253605],"type":"Point"}
}