{
  "type": "Feature",
  "properties": {
    "addr:full":"331 7th Ave W Vancouver BC V5Y 1M2",
    "addr:housenumber":"331",
    "addr:postcode":"v5y 1m2",
    "addr:street":"7Th Ave W",
    "iso:country":"CA",
    "sg:address":"331 7th Ave W",
    "sg:city":"Vancouver",
    "sg:classifiers":[
        {
            "category":"Manufacturing",
            "subcategory":"Furniture",
            "type":"Manufacturing & Wholesale Goods"
        }
    ],
    "sg:phone":"+1 604 874 1121",
    "sg:postcode":"V5Y 1M2",
    "sg:province":"BC",
    "sg:tags":[
        "venetian",
        "blind"
    ],
    "wof:name":"Venetian Blind Svc Ctr",
    "wof:placetype":"venue"
},
  "geometry": {"coordinates":[-123.111587524,49.2649383545],"type":"Point"}
}