{
  "type": "Feature",
  "properties": {
    "addr:full":"Vancouver BC V6M 2A3",
    "addr:postcode":"v6m 2a3",
    "iso:country":"CA",
    "sg:city":"Vancouver",
    "sg:classifiers":[
        {
            "category":"Education",
            "subcategory":"Special Training",
            "type":"Public Place"
        }
    ],
    "sg:phone":"+1 604 738 9344",
    "sg:postcode":"V6M 2A3",
    "sg:province":"BC",
    "sg:tags":[
        "tutoring"
    ],
    "wof:name":"Spanish Teaching Svc",
    "wof:placetype":"venue"
},
  "geometry": {"coordinates":[-123.159271,49.234753],"type":"Point"}
}