{
  "type": "Feature",
  "properties": {
    "addr:full":"116 Guestville Ave York ON M6N 4N6",
    "addr:housenumber":"116",
    "addr:postcode":"m6n 4n6",
    "addr:street":"Guestville Ave",
    "iso:country":"CA",
    "sg:address":"116 Guestville Ave",
    "sg:city":"York",
    "sg:classifiers":[
        {
            "category":"Building & Trades",
            "subcategory":"Landscaping Services",
            "type":"Services"
        }
    ],
    "sg:phone":"+1 416 760 0133",
    "sg:postcode":"M6N 4N6",
    "sg:province":"ON",
    "sg:tags":[
        "landscape",
        "contractor"
    ],
    "wof:name":"Select Landscape Systems Ltd",
    "wof:placetype":"venue"
},
  "geometry": {"coordinates":[-79.49045599999999,43.685913],"type":"Point"}
}