{
  "type": "Feature",
  "properties": {
    "iso:country":"CA",
    "sg:address":"460 Torbay Rd",
    "sg:city":"St. John's",
    "sg:classifiers":[
        {
            "category":"Organizations",
            "subcategory":"Professional Association",
            "type":"Services"
        }
    ],
    "sg:phone":"+1 709 726 6405",
    "sg:postcode":"A1A 5J3",
    "sg:province":"NL",
    "wof:name":"Nlama-Assn of Mun Admin",
    "wof:placetype":"venue"
},
  "geometry": {"coordinates":[-52.7204284668,47.607383728],"type":"Point"}
}