{
  "type": "Feature",
  "properties": {
    "iso:country":"CA",
    "sg:address":"256 Jarvis St # 256",
    "sg:city":"Toronto",
    "sg:classifiers":[
        {
            "category":"Food & Beverages",
            "subcategory":"Groceries & Convenience Stores",
            "type":"Retail Goods"
        }
    ],
    "sg:phone":"+1 416 595 9679",
    "sg:postcode":"M5B 2J4",
    "sg:province":"ON",
    "sg:tags":[
        "grocer"
    ],
    "wof:name":"Rabba Fine Foods",
    "wof:placetype":"venue"
},
  "geometry": {"coordinates":[-79.3756942749,43.6595344543],"type":"Point"}
}