{
  "type": "Feature",
  "properties": {
    "addr:full":"1025 Pape Ave East York ON M4K 3W1",
    "addr:housenumber":"1025",
    "addr:postcode":"m4k 3w1",
    "addr:street":"Pape Ave",
    "iso:country":"CA",
    "sg:address":"1025 Pape Ave",
    "sg:city":"East York",
    "sg:classifiers":[
        {
            "category":"Wholesale",
            "subcategory":"Durable Goods & Equipment",
            "type":"Manufacturing & Wholesale Goods"
        }
    ],
    "sg:phone":"+1 416 425 9852",
    "sg:postcode":"M4K 3W1",
    "sg:province":"ON",
    "sg:tags":[
        "importer"
    ],
    "wof:name":"Everywhere International Imprt",
    "wof:placetype":"venue"
},
  "geometry": {"coordinates":[-79.3483428955,43.6886978149],"type":"Point"}
}