{
  "type": "Feature",
  "properties": {
    "addr:full":"1550 Rue Du Perigord Charlesbourg QC G1G 5T8",
    "addr:housenumber":"1550",
    "addr:postcode":"g1g 5t8",
    "addr:street":"Rue Du Perigord",
    "iso:country":"CA",
    "sg:address":"1550 Rue Du Perigord",
    "sg:city":"Charlesbourg",
    "sg:classifiers":[
        {
            "category":"Education",
            "subcategory":"School",
            "type":"Public Place"
        }
    ],
    "sg:phone":"+1 418 624 3755",
    "sg:postcode":"G1G 5T8",
    "sg:province":"QC",
    "wof:name":"Ecole L'Oasis",
    "wof:placetype":"venue"
},
  "geometry": {"coordinates":[-71.2888183594,46.8699645996],"type":"Point"}
}