{
  "type": "Feature",
  "properties": {
    "addr:full":"Vancouver BC V6J 1B7",
    "addr:postcode":"v6j 1b7",
    "iso:country":"CA",
    "sg:city":"Vancouver",
    "sg:classifiers":[
        {
            "category":"Retail",
            "subcategory":"Portrait Studio",
            "type":"Services"
        }
    ],
    "sg:phone":"+1 604 733 3301",
    "sg:postcode":"V6J 1B7",
    "sg:province":"BC",
    "sg:tags":[
        "photographer"
    ],
    "wof:name":"Michael D O'Shea Photography",
    "wof:placetype":"venue"
},
  "geometry": {"coordinates":[-123.14690400000001,49.27457],"type":"Point"}
}