{
  "type": "Feature",
  "properties": {
    "addr:full":"2257 Kingsway Vancouver BC V5N 2T6",
    "addr:housenumber":"2257",
    "addr:postcode":"v5n 2t6",
    "addr:street":"Kingsway",
    "iso:country":"CA",
    "sg:address":"2257 Kingsway",
    "sg:city":"Vancouver",
    "sg:classifiers":[
        {
            "category":"Restaurant",
            "type":"Food & Drink"
        }
    ],
    "sg:phone":"+1 604 432 6022",
    "sg:postcode":"V5N 2T6",
    "sg:province":"BC",
    "wof:name":"Pho Hoa Restaurant",
    "wof:placetype":"venue"
},
  "geometry": {"coordinates":[-123.059516907,49.2426681519],"type":"Point"}
}