{
  "type": "Feature",
  "properties": {
    "addr:full":"Vernon BC V1T 2G9",
    "addr:postcode":"v1t 2g9",
    "iso:country":"CA",
    "sg:city":"Vernon",
    "sg:classifiers":[
        {
            "category":"Professional",
            "subcategory":"Engineering",
            "type":"Services"
        }
    ],
    "sg:phone":"+1 250 503 1023",
    "sg:postcode":"V1T 2G9",
    "sg:province":"BC",
    "sg:tags":[
        "engineer"
    ],
    "wof:name":"Quantum Consulting Svc",
    "wof:placetype":"venue"
},
  "geometry": {"coordinates":[-119.273804,50.265678],"type":"Point"}
}