{
  "type": "Feature",
  "properties": {
    "addr:full":"121 Kootenay St N Cranbrook BC V1C 3T5",
    "addr:housenumber":"121",
    "addr:postcode":"v1c 3t5",
    "addr:street":"Kootenay St N",
    "iso:country":"CA",
    "sg:address":"121 Kootenay St N",
    "sg:city":"Cranbrook",
    "sg:classifiers":[
        {
            "category":"Home & Garden",
            "subcategory":"Carpets & Floor Coverings",
            "type":"Retail Goods"
        }
    ],
    "sg:phone":"+1 250 426 8471",
    "sg:postcode":"V1C 3T5",
    "sg:province":"BC",
    "sg:tags":[
        "rug"
    ],
    "wof:name":"Cranbrook Flooring Ltd",
    "wof:placetype":"venue"
},
  "geometry": {"coordinates":[-115.765289,49.513706],"type":"Point"}
}