{
  "type": "Feature",
  "properties": {
    "addr:full":"Calgary AB T2N 3P7",
    "addr:postcode":"t2n 3p7",
    "iso:country":"CA",
    "sg:city":"Calgary",
    "sg:classifiers":[
        {
            "category":"Professional",
            "subcategory":"Lawyer & Legal Services",
            "type":"Services"
        }
    ],
    "sg:phone":"+1 403 221 9801",
    "sg:postcode":"T2N 3P7",
    "sg:province":"AB",
    "sg:tags":[
        "attorney"
    ],
    "wof:name":"Clark, Robert J",
    "wof:placetype":"venue"
},
  "geometry": {"coordinates":[-114.09065200000001,51.05262],"type":"Point"}
}