{
  "type": "Feature",
  "properties": {
    "addr:full":"Levis QC G6V 6C9",
    "addr:postcode":"g6v 6c9",
    "iso:country":"CA",
    "sg:city":"Levis",
    "sg:classifiers":[
        {
            "category":"Home & Garden",
            "subcategory":"Furniture",
            "type":"Retail Goods"
        }
    ],
    "sg:phone":"+1 418 835 0218",
    "sg:postcode":"G6V 6C9",
    "sg:province":"QC",
    "sg:tags":[
        "mattress"
    ],
    "wof:name":"Matelas Dauphin Inc",
    "wof:placetype":"venue"
},
  "geometry": {"coordinates":[-71.1683807373,46.7895202637],"type":"Point"}
}