{
  "type": "Feature",
  "properties": {
    "iso:country":"CA",
    "sg:city":"Woodbridge",
    "sg:classifiers":[
        {
            "category":"Travel",
            "subcategory":"Travel Agent",
            "type":"Entertainment"
        }
    ],
    "sg:phone":"+1 905 850 7900",
    "sg:postcode":"L4L 9G7",
    "sg:province":"ON",
    "sg:tags":[
        "agency",
        "bureau"
    ],
    "wof:name":"Cruise Ship Ctr",
    "wof:placetype":"venue"
},
  "geometry": {"coordinates":[-79.5495834351,43.8063850403],"type":"Point"}
}