{
  "type": "Feature",
  "properties": {
    "addr:full":"1681 Sugar Lake Rd Lumby BC V0E 2G2",
    "addr:housenumber":"1681",
    "addr:postcode":"v0e 2g2",
    "addr:street":"Sugar Lake Rd",
    "iso:country":"CA",
    "sg:address":"1681 Sugar Lake Rd",
    "sg:city":"Lumby",
    "sg:classifiers":[
        {
            "category":"Travel",
            "subcategory":"Hotels & Motels",
            "type":"Entertainment"
        }
    ],
    "sg:phone":"+1 250 547 6517",
    "sg:postcode":"V0E 2G2",
    "sg:province":"BC",
    "sg:tags":[
        "resort"
    ],
    "wof:name":"Kokanee Lodge & Resort",
    "wof:placetype":"venue"
},
  "geometry": {"coordinates":[-118.966888428,50.2472686768],"type":"Point"}
}