{
  "type": "Feature",
  "properties": {
    "addr:full":"143 Rue Victoria Salaberry-DE-Valleyfield QC J6T 1A4",
    "addr:housenumber":"143",
    "addr:postcode":"j6t 1a4",
    "addr:street":"Rue Victoria",
    "iso:country":"CA",
    "sg:address":"143 Rue Victoria",
    "sg:city":"Salaberry-DE-Valleyfield",
    "sg:classifiers":[
        {
            "category":"Restaurant",
            "type":"Food & Drink"
        }
    ],
    "sg:phone":"+1 450 371 2535",
    "sg:postcode":"J6T 1A4",
    "sg:province":"QC",
    "wof:name":"Restaurant Pacifique Inc",
    "wof:placetype":"venue"
},
  "geometry": {"coordinates":[-74.126701,45.256714],"type":"Point"}
}