{
  "type": "Feature",
  "properties": {
    "addr:full":"2 Sheppard Ave E North York ON M2N 5Y7",
    "addr:housenumber":"2",
    "addr:postcode":"m2n 5y7",
    "addr:street":"Sheppard Ave E",
    "iso:country":"CA",
    "sg:address":"2 Sheppard Ave E",
    "sg:city":"North York",
    "sg:classifiers":[
        {
            "category":"Restaurant",
            "type":"Food & Drink"
        }
    ],
    "sg:phone":"+1 416 224 5160",
    "sg:postcode":"M2N 5Y7",
    "sg:province":"ON",
    "sg:tags":[
        "shop",
        "tea",
        "coffee"
    ],
    "wof:name":"Second Cup",
    "wof:placetype":"venue"
},
  "geometry": {"coordinates":[-79.41065216059999,43.761756897],"type":"Point"}
}