{
  "type": "Feature",
  "properties": {
    "addr:full":"50 Venture Cres North Bay ON P1B 8G4",
    "addr:housenumber":"50",
    "addr:postcode":"p1b 8g4",
    "addr:street":"Venture Cres",
    "iso:country":"CA",
    "sg:address":"50 Venture Cres",
    "sg:city":"North Bay",
    "sg:classifiers":[
        {
            "category":"Freight",
            "type":"Transportation"
        }
    ],
    "sg:phone":"+1 705 476 4223",
    "sg:postcode":"P1B 8G4",
    "sg:province":"ON",
    "sg:tags":[
        "mover"
    ],
    "wof:name":"Walker's Van & Storage",
    "wof:placetype":"venue"
},
  "geometry": {"coordinates":[-79.42916099999999,46.309483],"type":"Point"}
}