{
  "type": "Feature",
  "properties": {
    "addr:full":"49 Craig St Brantford ON N3R 7H8",
    "addr:housenumber":"49",
    "addr:postcode":"n3r 7h8",
    "addr:street":"Craig St",
    "iso:country":"CA",
    "sg:address":"49 Craig St",
    "sg:city":"Brantford",
    "sg:classifiers":[
        {
            "category":"Wholesale",
            "subcategory":"Machinery & Supplies",
            "type":"Manufacturing & Wholesale Goods"
        }
    ],
    "sg:phone":"+1 519 756 0990",
    "sg:postcode":"N3R 7H8",
    "sg:province":"ON",
    "sg:tags":[
        "equipment",
        "baker"
    ],
    "wof:name":"Offenhammer Bakery Equipment",
    "wof:placetype":"venue"
},
  "geometry": {"coordinates":[-80.2510223389,43.1620788574],"type":"Point"}
}