{
  "type": "Feature",
  "properties": {
    "addr:full":"1649 Ch Sullivan Sullivan QC J0Y 2N0",
    "addr:housenumber":"1649",
    "addr:postcode":"j0y 2n0",
    "addr:street":"Ch Sullivan",
    "iso:country":"CA",
    "sg:address":"1649 Ch Sullivan",
    "sg:city":"Sullivan",
    "sg:classifiers":[
        {
            "category":"Building & Trades",
            "subcategory":"Cleaning & Sanitation",
            "type":"Services"
        }
    ],
    "sg:phone":"+1 819 874 2711",
    "sg:postcode":"J0Y 2N0",
    "sg:province":"QC",
    "sg:tags":[
        "sweeping",
        "snow",
        "removal"
    ],
    "wof:name":"Avalanche Secours Enr",
    "wof:placetype":"venue"
},
  "geometry": {"coordinates":[-77.828209,48.131878],"type":"Point"}
}