{
  "type": "Feature",
  "properties": {
    "iso:country":"CA",
    "sg:address":"939 Danforth Ave",
    "sg:city":"Toronto",
    "sg:classifiers":[
        {
            "category":"Food & Beverages",
            "subcategory":"Groceries & Convenience Stores",
            "type":"Retail Goods"
        }
    ],
    "sg:phone":"+1 416 466 6121",
    "sg:postcode":"M4J 1L8",
    "sg:province":"ON",
    "sg:tags":[
        "variety"
    ],
    "wof:name":"Danforth Milk Store",
    "wof:placetype":"venue"
},
  "geometry": {"coordinates":[-79.3384170532,43.6800498962],"type":"Point"}
}