{
  "type": "Feature",
  "properties": {
    "addr:full":"Richmond BC V6V 2H6",
    "addr:postcode":"v6v 2h6",
    "iso:country":"CA",
    "sg:city":"Richmond",
    "sg:classifiers":[
        {
            "category":"Professional",
            "subcategory":"Business Services",
            "type":"Services"
        }
    ],
    "sg:phone":"+1 604 231 0910",
    "sg:postcode":"V6V 2H6",
    "sg:province":"BC",
    "sg:tags":[
        "embroidery"
    ],
    "wof:name":"Classic Image Embroidery",
    "wof:placetype":"venue"
},
  "geometry": {"coordinates":[-123.082038879,49.1854438782],"type":"Point"}
}