{
  "type": "Feature",
  "properties": {
    "addr:full":"Sainte-Marthe QC J0P 1W0",
    "addr:postcode":"j0p 1w0",
    "iso:country":"CA",
    "sg:city":"Sainte-Marthe",
    "sg:classifiers":[
        {
            "category":"Home & Garden",
            "subcategory":"Hardware",
            "type":"Retail Goods"
        }
    ],
    "sg:phone":"+1 450 459 4231",
    "sg:postcode":"J0P 1W0",
    "sg:province":"QC",
    "sg:tags":[
        "feed"
    ],
    "wof:name":"Societe Cooperative Agricole",
    "wof:placetype":"venue"
},
  "geometry": {"coordinates":[-74.30359649659999,45.407623291],"type":"Point"}
}