{
  "type": "Feature",
  "properties": {
    "addr:full":"Bonnyville AB T9N 2H4",
    "addr:postcode":"t9n 2h4",
    "iso:country":"CA",
    "sg:city":"Bonnyville",
    "sg:classifiers":[
        {
            "category":"Mining & Drilling",
            "type":"Manufacturing & Wholesale Goods"
        }
    ],
    "sg:phone":"+1 780 826 4447",
    "sg:postcode":"T9N 2H4",
    "sg:province":"AB",
    "sg:tags":[
        "development",
        "gas",
        "company",
        "oil",
        "exploration"
    ],
    "wof:name":"Canadian Natural Resources Ltd",
    "wof:placetype":"venue"
},
  "geometry": {"coordinates":[-110.725280762,54.2706108093],"type":"Point"}
}