{
  "type": "Feature",
  "properties": {
    "addr:full":"1700 Elm St Port Colborne ON L3K 5V4",
    "addr:housenumber":"1700",
    "addr:postcode":"l3k 5v4",
    "addr:street":"Elm St",
    "iso:country":"CA",
    "sg:address":"1700 Elm St",
    "sg:city":"Port Colborne",
    "sg:classifiers":[
        {
            "category":"Government",
            "subcategory":"Office",
            "type":"Public Place"
        }
    ],
    "sg:phone":"+1 905 835 2788",
    "sg:postcode":"L3K 5V4",
    "sg:province":"ON",
    "sg:tags":[
        "village"
    ],
    "wof:name":"Port Colborne Landfill Site",
    "wof:placetype":"venue"
},
  "geometry": {"coordinates":[-79.255501,42.926205],"type":"Point"}
}