{
  "type": "Feature",
  "properties": {
    "iso:country":"CA",
    "sg:city":"North Vancouver",
    "sg:classifiers":[
        {
            "category":"Restaurant",
            "type":"Food & Drink"
        }
    ],
    "sg:phone":"+1 604 924 1111",
    "sg:postcode":"V7H 1T6",
    "sg:province":"BC",
    "wof:name":"Old Fashion Sandwich Shoppe",
    "wof:placetype":"venue"
},
  "geometry": {"coordinates":[-123.014442,49.306007],"type":"Point"}
}