{
  "type": "Feature",
  "properties": {
    "addr:full":"1269 Rue Principale Saint-Agapit QC G0S 1Z0",
    "addr:housenumber":"1269",
    "addr:postcode":"g0s 1z0",
    "addr:street":"Rue Principale",
    "iso:country":"CA",
    "sg:address":"1269 Rue Principale",
    "sg:city":"Saint-Agapit",
    "sg:classifiers":[
        {
            "category":"Home & Garden",
            "subcategory":"Furniture",
            "type":"Retail Goods"
        }
    ],
    "sg:phone":"+1 418 888 4142",
    "sg:postcode":"G0S 1Z0",
    "sg:province":"QC",
    "sg:tags":[
        "kitchen",
        "door",
        "cabinet"
    ],
    "wof:name":"Produits DE Bois St-Agapit",
    "wof:placetype":"venue"
},
  "geometry": {"coordinates":[-71.4459991455,46.5570335388],"type":"Point"}
}