{
  "type": "Feature",
  "properties": {
    "iso:country":"CA",
    "sg:address":"5505 Rang Du Bas-Saint-Francoi",
    "sg:city":"Laval",
    "sg:classifiers":[
        {
            "category":"Real Estate",
            "subcategory":"Developer",
            "type":"Services"
        }
    ],
    "sg:phone":"+1 450 661 7016",
    "sg:postcode":"H7E 4P2",
    "sg:province":"QC",
    "sg:tags":[
        "cemetery"
    ],
    "wof:name":"Beth Israel Memorial Park",
    "wof:placetype":"venue"
},
  "geometry": {"coordinates":[-73.6617050171,45.6428184509],"type":"Point"}
}