{
  "type": "Feature",
  "properties": {
    "addr:full":"Mississauga ON L5V 1N3",
    "addr:postcode":"l5v 1n3",
    "iso:country":"CA",
    "sg:city":"Mississauga",
    "sg:classifiers":[
        {
            "category":"Health Services",
            "subcategory":"Doctor",
            "type":"Services"
        }
    ],
    "sg:phone":"+1 905 567 1231",
    "sg:postcode":"L5V 1N3",
    "sg:province":"ON",
    "sg:tags":[
        "clinic"
    ],
    "wof:name":"Roseborough Dental Office",
    "wof:placetype":"venue"
},
  "geometry": {"coordinates":[-79.6833190918,43.579460144],"type":"Point"}
}