{
  "type": "Feature",
  "properties": {
    "iso:country":"CA",
    "sg:address":"4170 Rue Saint-Urbain",
    "sg:city":"Montreal",
    "sg:classifiers":[
        {
            "category":"Arts & Performance",
            "subcategory":"Theater",
            "type":"Entertainment"
        }
    ],
    "sg:phone":"+1 514 844 1774",
    "sg:postcode":"H2W 1V3",
    "sg:province":"QC",
    "sg:tags":[
        "music"
    ],
    "wof:name":"Filamonica Divino Espirito",
    "wof:placetype":"venue"
},
  "geometry": {"coordinates":[-73.582344,45.516445],"type":"Point"}
}