{
  "type": "Feature",
  "properties": {
    "iso:country":"CA",
    "sg:address":"253 St George St",
    "sg:city":"Annapolis Royal",
    "sg:classifiers":[
        {
            "category":"Professional",
            "subcategory":"Lawyer & Legal Services",
            "type":"Services"
        }
    ],
    "sg:phone":"+1 902 532 2311",
    "sg:postcode":"B0S 1A0",
    "sg:province":"NS",
    "sg:tags":[
        "attorney"
    ],
    "wof:name":"Nova Scotia Legal Aid",
    "wof:placetype":"venue"
},
  "geometry": {"coordinates":[-65.5193939209,44.744140625],"type":"Point"}
}