{
  "type": "Feature",
  "properties": {
    "addr:full":"935 Boul Decarie Saint-Laurent QC H4L 3M3",
    "addr:housenumber":"935",
    "addr:postcode":"h4l 3m3",
    "addr:street":"Boul Decarie",
    "iso:country":"CA",
    "sg:address":"935 Boul Decarie",
    "sg:city":"Saint-Laurent",
    "sg:classifiers":[
        {
            "category":"Insurance",
            "subcategory":"Insurance Agent",
            "type":"Services"
        }
    ],
    "sg:phone":"+1 514 336 9500",
    "sg:postcode":"H4L 3M3",
    "sg:province":"QC",
    "wof:name":"Assurance Generale",
    "wof:placetype":"venue"
},
  "geometry": {"coordinates":[-73.681084,45.513439],"type":"Point"}
}