{
  "type": "Feature",
  "properties": {
    "addr:full":"11315 75 Ave Delta BC V4C 1H4",
    "addr:housenumber":"11315",
    "addr:postcode":"v4c 1h4",
    "addr:street":"75 Ave",
    "iso:country":"CA",
    "sg:address":"11315 75 Ave",
    "sg:city":"Delta",
    "sg:classifiers":[
        {
            "category":"Education",
            "subcategory":"School",
            "type":"Public Place"
        }
    ],
    "sg:phone":"+1 604 594 5437",
    "sg:postcode":"V4C 1H4",
    "sg:province":"BC",
    "wof:name":"Chalmers Elementary School",
    "wof:placetype":"venue"
},
  "geometry": {"coordinates":[-122.90802002,49.1395683289],"type":"Point"}
}