{
  "type": "Feature",
  "properties": {
    "addr:full":"Toronto ON M4K 1N6",
    "addr:postcode":"m4k 1n6",
    "iso:country":"CA",
    "sg:city":"Toronto",
    "sg:classifiers":[
        {
            "category":"Personal",
            "subcategory":"Beauty Salon",
            "type":"Services"
        }
    ],
    "sg:phone":"+1 416 778 9094",
    "sg:postcode":"M4K 1N6",
    "sg:province":"ON",
    "wof:name":"Allazo Skin Care",
    "wof:placetype":"venue"
},
  "geometry": {"coordinates":[-79.353729,43.677311],"type":"Point"}
}