{
  "type": "Feature",
  "properties": {
    "addr:full":"1931 Ogilvie St S Prince George BC V2N 1X2",
    "addr:housenumber":"1931",
    "addr:postcode":"v2n 1x2",
    "addr:street":"Ogilvie St S",
    "iso:country":"CA",
    "sg:address":"1931 Ogilvie St S",
    "sg:city":"Prince George",
    "sg:classifiers":[
        {
            "category":"Building & Trades",
            "subcategory":"Electrical",
            "type":"Services"
        }
    ],
    "sg:phone":"+1 250 564 7685",
    "sg:postcode":"V2N 1X2",
    "sg:province":"BC",
    "sg:tags":[
        "electric",
        "contractor"
    ],
    "wof:name":"Bryant Electric Ltd",
    "wof:placetype":"venue"
},
  "geometry": {"coordinates":[-122.789451599,53.9059753418],"type":"Point"}
}