{
  "type": "Feature",
  "properties": {
    "addr:full":"480 Steeles Ave W Thornhill ON L4J 6X6",
    "addr:housenumber":"480",
    "addr:postcode":"l4j 6x6",
    "addr:street":"Steeles Ave W",
    "iso:country":"CA",
    "sg:address":"480 Steeles Ave W",
    "sg:city":"Thornhill",
    "sg:classifiers":[
        {
            "category":"Autos & Motor Vehicles",
            "subcategory":"Automobile Sales",
            "type":"Retail Goods"
        }
    ],
    "sg:phone":"+1 905 886 3380",
    "sg:postcode":"L4J 6X6",
    "sg:province":"ON",
    "sg:tags":[
        "car",
        "dealer"
    ],
    "wof:name":"Bmw Autohaus",
    "wof:placetype":"venue"
},
  "geometry": {"coordinates":[-79.435844,43.794716],"type":"Point"}
}