{
  "type": "Feature",
  "properties": {
    "iso:country":"CA",
    "sg:address":"705 Consortium Crt",
    "sg:city":"London",
    "sg:classifiers":[
        {
            "category":"Organizations",
            "subcategory":"Membership Organization",
            "type":"Services"
        }
    ],
    "sg:phone":"+1 519 672 3499",
    "sg:postcode":"N6E 2S8",
    "sg:province":"ON",
    "wof:name":"Elgin Middlesex Oxford Local",
    "wof:placetype":"venue"
},
  "geometry": {"coordinates":[-81.204208,42.933979],"type":"Point"}
}