{
  "type": "Feature",
  "properties": {
    "addr:full":"351 13th Ave E Prince Albert SK S6V 2N3",
    "addr:housenumber":"351",
    "addr:postcode":"s6v 2n3",
    "addr:street":"13Th Ave E",
    "iso:country":"CA",
    "sg:address":"351 13th Ave E",
    "sg:city":"Prince Albert",
    "sg:classifiers":[
        {
            "category":"Education",
            "subcategory":"School",
            "type":"Public Place"
        }
    ],
    "sg:phone":"+1 306 763 5217",
    "sg:postcode":"S6V 2N3",
    "sg:province":"SK",
    "wof:name":"Princess Margaret School",
    "wof:placetype":"venue"
},
  "geometry": {"coordinates":[-105.712463,53.207119],"type":"Point"}
}