{
  "type": "Feature",
  "properties": {
    "addr:full":"Bobcaygeon ON K0M 1A0",
    "addr:postcode":"k0m 1a0",
    "iso:country":"CA",
    "sg:city":"Bobcaygeon",
    "sg:classifiers":[
        {
            "category":"Organizations",
            "subcategory":"Professional Association",
            "type":"Services"
        }
    ],
    "sg:phone":"+1 705 738 2710",
    "sg:postcode":"K0M 1A0",
    "sg:province":"ON",
    "sg:tags":[
        "club"
    ],
    "wof:name":"Royal Candn Legion Branch 239",
    "wof:placetype":"venue"
},
  "geometry": {"coordinates":[-78.538231,44.537022],"type":"Point"}
}