{
  "type": "Feature",
  "properties": {
    "addr:full":"1644 Hillside Ave # 8 Victoria BC V8T 2C5",
    "addr:housenumber":"1644",
    "addr:postcode":"v8t 2c5",
    "addr:street":"Hillside Ave # 8",
    "iso:country":"CA",
    "sg:address":"1644 Hillside Ave # 8",
    "sg:city":"Victoria",
    "sg:classifiers":[
        {
            "category":"Shopping",
            "subcategory":"Shoes",
            "type":"Retail Goods"
        }
    ],
    "sg:phone":"+1 250 595 4143",
    "sg:postcode":"V8T 2C5",
    "sg:province":"BC",
    "sg:tags":[
        "sportswear"
    ],
    "wof:name":"Foot Locker",
    "wof:placetype":"venue"
},
  "geometry": {"coordinates":[-123.33448,48.445351],"type":"Point"}
}