{
  "type": "Feature",
  "properties": {
    "addr:full":"11121 Av Salk Montreal-Nord QC H1G 4Y3",
    "addr:postcode":"h1g 4y3",
    "addr:street":"Av Salk",
    "iso:country":"CA",
    "sg:address":"11121 Av Salk",
    "sg:city":"Montreal-Nord",
    "sg:classifiers":[
        {
            "category":"Social Services",
            "type":"Services"
        }
    ],
    "sg:phone":"+1 514 329 5044",
    "sg:postcode":"H1G 4Y3",
    "sg:province":"QC",
    "sg:tags":[
        "organization",
        "welfare"
    ],
    "wof:name":"Centre Communautaire Multi",
    "wof:placetype":"venue"
},
  "geometry": {"coordinates":[-73.62325286870001,45.6014480591],"type":"Point"}
}