{
  "type": "Feature",
  "properties": {
    "addr:full":"5770 Rue DE LA Montagne Trois-Rivieres-Ouest QC G8Y 3S1",
    "addr:housenumber":"5770",
    "addr:postcode":"g8y 3s1",
    "addr:street":"Rue De La Montagne Trois-Rivieres-Ouest",
    "iso:country":"CA",
    "sg:address":"5770 Rue DE LA Montagne",
    "sg:city":"Trois-Rivieres-Ouest",
    "sg:classifiers":[
        {
            "category":"Personal",
            "subcategory":"Beauty Salon",
            "type":"Services"
        }
    ],
    "sg:phone":"+1 819 374 7234",
    "sg:postcode":"G8Y 3S1",
    "sg:province":"QC",
    "wof:name":"Salon Avant-Garde Coiffure",
    "wof:placetype":"venue"
},
  "geometry": {"coordinates":[-72.59326900000001,46.332253],"type":"Point"}
}