{
  "type": "Feature",
  "properties": {
    "addr:full":"325 Twiddy Rd Madoc ON K0K 2K0",
    "addr:housenumber":"325",
    "addr:postcode":"k0k 2k0",
    "addr:street":"Twiddy Rd",
    "iso:country":"CA",
    "sg:address":"325 Twiddy Rd",
    "sg:city":"Madoc",
    "sg:classifiers":[
        {
            "category":"Social Services",
            "type":"Services"
        }
    ],
    "sg:phone":"+1 613 473 2597",
    "sg:postcode":"K0K 2K0",
    "sg:province":"ON",
    "sg:tags":[
        "organization",
        "welfare"
    ],
    "wof:name":"Ivanhoe Residence",
    "wof:placetype":"venue"
},
  "geometry": {"coordinates":[-77.47504425050001,44.5046463013],"type":"Point"}
}