{
  "type": "Feature",
  "properties": {
    "addr:full":"Milton ON L9T 3J2",
    "addr:postcode":"l9t 3j2",
    "iso:country":"CA",
    "sg:city":"Milton",
    "sg:classifiers":[
        {
            "category":"Autos & Motor Vehicles",
            "subcategory":"Auto Supplies",
            "type":"Retail Goods"
        }
    ],
    "sg:phone":"+1 905 876 4788",
    "sg:postcode":"L9T 3J2",
    "sg:province":"ON",
    "sg:tags":[
        "tire"
    ],
    "wof:name":"J & D Tire Sales & Svc",
    "wof:placetype":"venue"
},
  "geometry": {"coordinates":[-79.874664,43.52124],"type":"Point"}
}