{
  "type": "Feature",
  "properties": {
    "addr:full":"193 Woolwich St Guelph ON N1H 3V4",
    "addr:housenumber":"193",
    "addr:postcode":"n1h 3v4",
    "addr:street":"Woolwich St",
    "iso:country":"CA",
    "sg:address":"193 Woolwich St",
    "sg:city":"Guelph",
    "sg:classifiers":[
        {
            "category":"Professional",
            "subcategory":"Business Services",
            "type":"Services"
        }
    ],
    "sg:phone":"+1 519 822 2890",
    "sg:postcode":"N1H 3V4",
    "sg:province":"ON",
    "sg:tags":[
        "trade",
        "exposition",
        "fair",
        "show"
    ],
    "wof:name":"Canada's Outdoor Farm Show",
    "wof:placetype":"venue"
},
  "geometry": {"coordinates":[-80.25347137449999,43.5485420227],"type":"Point"}
}