{
  "type": "Feature",
  "properties": {
    "addr:full":"Toronto ON M6K 1T9",
    "addr:postcode":"m6k 1t9",
    "iso:country":"CA",
    "sg:city":"Toronto",
    "sg:classifiers":[
        {
            "category":"Restaurant",
            "type":"Food & Drink"
        }
    ],
    "sg:phone":"+1 416 536 5142",
    "sg:postcode":"M6K 1T9",
    "sg:province":"ON",
    "wof:name":"Atlantic Restaurant",
    "wof:placetype":"venue"
},
  "geometry": {"coordinates":[-79.4350204468,43.6497573853],"type":"Point"}
}