{
  "type": "Feature",
  "properties": {
    "addr:full":"107 Rue Saint-Charles Chicoutimi QC G7J 1T9",
    "addr:housenumber":"107",
    "addr:postcode":"g7j 1t9",
    "addr:street":"Rue Saint-Charles",
    "iso:country":"CA",
    "sg:address":"107 Rue Saint-Charles",
    "sg:city":"Chicoutimi",
    "sg:classifiers":[
        {
            "category":"Building & Trades",
            "subcategory":"Electrical",
            "type":"Services"
        }
    ],
    "sg:phone":"+1 418 543 9518",
    "sg:postcode":"G7J 1T9",
    "sg:province":"QC",
    "sg:tags":[
        "electric",
        "contractor"
    ],
    "wof:name":"Entreprises Belanger Tremblay",
    "wof:placetype":"venue"
},
  "geometry": {"coordinates":[-71.072357,48.421204],"type":"Point"}
}