{
  "type": "Feature",
  "properties": {
    "addr:full":"754 Rte Begin Saint-Anselme QC G0R 2N0",
    "addr:housenumber":"754",
    "addr:postcode":"g0r 2n0",
    "addr:street":"Rte Begin",
    "iso:country":"CA",
    "sg:address":"754 Rte Begin",
    "sg:city":"Saint-Anselme",
    "sg:classifiers":[
        {
            "category":"Shopping",
            "subcategory":"Computers & Home Electronics",
            "type":"Retail Goods"
        }
    ],
    "sg:phone":"+1 418 885 9858",
    "sg:postcode":"G0R 2N0",
    "sg:province":"QC",
    "sg:tags":[
        "television",
        "radio"
    ],
    "wof:name":"Marceau Radio Tv Enr",
    "wof:placetype":"venue"
},
  "geometry": {"coordinates":[-70.97155761720001,46.6305885315],"type":"Point"}
}