{
  "type": "Feature",
  "properties": {
    "addr:full":"211 Archibald St S Thunder Bay ON P7E 1G4",
    "addr:housenumber":"211",
    "addr:postcode":"p7e 1g4",
    "addr:street":"Archibald St S",
    "iso:country":"CA",
    "sg:address":"211 Archibald St S",
    "sg:city":"Thunder Bay",
    "sg:classifiers":[
        {
            "category":"Organizations",
            "subcategory":"Religious Organization",
            "type":"Services"
        }
    ],
    "sg:phone":"+1 807 622 5389",
    "sg:postcode":"P7E 1G4",
    "sg:province":"ON",
    "sg:tags":[
        "church"
    ],
    "wof:name":"St Patrick's Cathedral",
    "wof:placetype":"venue"
},
  "geometry": {"coordinates":[-89.24904632569999,48.3821983337],"type":"Point"}
}