{
  "type": "Feature",
  "properties": {
    "iso:country":"CA",
    "sg:address":"4898 Rutherford Rd",
    "sg:city":"Nanaimo",
    "sg:classifiers":[
        {
            "category":"Travel",
            "subcategory":"Hotels & Motels",
            "type":"Entertainment"
        }
    ],
    "sg:phone":"+1 250 758 3000",
    "sg:postcode":"V9T 4Z4",
    "sg:province":"BC",
    "wof:name":"Grand Hotel Nanaimo",
    "wof:placetype":"venue"
},
  "geometry": {"coordinates":[-124.022804,49.21756],"type":"Point"}
}