{
  "type": "Feature",
  "properties": {
    "addr:full":"4898 Rutherford Rd Nanaimo BC V9T 4Z4",
    "addr:housenumber":"4898",
    "addr:postcode":"v9t 4z4",
    "addr:street":"Rutherford Rd",
    "iso:country":"CA",
    "sg:address":"4898 Rutherford Rd",
    "sg:city":"Nanaimo",
    "sg:classifiers":[
        {
            "category":"Travel",
            "subcategory":"Hotels & Motels",
            "type":"Entertainment"
        }
    ],
    "sg:phone":"+1 250 758 3000",
    "sg:postcode":"V9T 4Z4",
    "sg:province":"BC",
    "wof:name":"Grand Hotel Nanaimo",
    "wof:placetype":"venue"
},
  "geometry": {"coordinates":[-124.02280399999999,49.21756],"type":"Point"}
}