{
  "type": "Feature",
  "properties": {
    "addr:full":"North York ON M2M 4G3",
    "addr:postcode":"m2m 4g3",
    "iso:country":"CA",
    "sg:city":"North York",
    "sg:classifiers":[
        {
            "category":"Professional",
            "subcategory":"Lawyer & Legal Services",
            "type":"Services"
        }
    ],
    "sg:phone":"+1 416 250 1313",
    "sg:postcode":"M2M 4G3",
    "sg:province":"ON",
    "sg:tags":[
        "attorney"
    ],
    "wof:name":"Abrahams, Peter",
    "wof:placetype":"venue"
},
  "geometry": {"coordinates":[-79.4157943726,43.7799530029],"type":"Point"}
}