{
  "type": "Feature",
  "properties": {
    "iso:country":"CA",
    "sg:address":"92 Glencairn Ave",
    "sg:city":"Toronto",
    "sg:classifiers":[
        {
            "category":"Professional",
            "subcategory":"Advertising",
            "type":"Services"
        }
    ],
    "sg:phone":"+1 416 483 6354",
    "sg:postcode":"M4R 1M8",
    "sg:province":"ON",
    "sg:tags":[
        "counselor"
    ],
    "wof:name":"M E Butorac Advertising Inc",
    "wof:placetype":"venue"
},
  "geometry": {"coordinates":[-79.405663,43.717522],"type":"Point"}
}