{
  "type": "Feature",
  "properties": {
    "addr:full":"PO Box 175 Plum Point NL A0K 4A0",
    "addr:housenumber":"po",
    "addr:postcode":"a0k 4a0",
    "addr:street":"Box 175",
    "iso:country":"CA",
    "sg:address":"PO Box 175",
    "sg:city":"Plum Point",
    "sg:classifiers":[
        {
            "category":"Manufacturing",
            "subcategory":"Food",
            "type":"Manufacturing & Wholesale Goods"
        }
    ],
    "sg:phone":"+1 709 247 2323",
    "sg:postcode":"A0K 4A0",
    "sg:province":"NL",
    "sg:tags":[
        "packer",
        "equipment",
        "fish"
    ],
    "wof:name":"Harvester Enterprises",
    "wof:placetype":"venue"
},
  "geometry": {"coordinates":[-56.8771934509,51.0777702332],"type":"Point"}
}