{
  "type": "Feature",
  "properties": {
    "iso:country":"CA",
    "sg:city":"Fort St John",
    "sg:classifiers":[
        {
            "category":"Shopping",
            "subcategory":"Pharmacy",
            "type":"Retail Goods"
        }
    ],
    "sg:phone":"+1 250 785 9563",
    "sg:postcode":"V1J 5Z2",
    "sg:province":"BC",
    "wof:name":"Zellers",
    "wof:placetype":"venue"
},
  "geometry": {"coordinates":[-120.839118958,56.2392234802],"type":"Point"}
}