{
  "type": "Feature",
  "properties": {
    "iso:country":"CA",
    "sg:address":"1215 Bayly St",
    "sg:city":"Pickering",
    "sg:classifiers":[
        {
            "category":"Restaurant",
            "type":"Food & Drink"
        }
    ],
    "sg:phone":"+1 905 831 0030",
    "sg:postcode":"L1W 1L7",
    "sg:province":"ON",
    "sg:tags":[
        "pizza"
    ],
    "wof:name":"Domino's Pizza",
    "wof:placetype":"venue"
},
  "geometry": {"coordinates":[-79.089874,43.828335],"type":"Point"}
}