{
  "type": "Feature",
  "properties": {
    "addr:full":"1215 Bayly St Pickering ON L1W 1L7",
    "addr:housenumber":"1215",
    "addr:postcode":"l1w 1l7",
    "addr:street":"Bayly St",
    "iso:country":"CA",
    "sg:address":"1215 Bayly St",
    "sg:city":"Pickering",
    "sg:classifiers":[
        {
            "category":"Restaurant",
            "type":"Food & Drink"
        }
    ],
    "sg:phone":"+1 905 831 0030",
    "sg:postcode":"L1W 1L7",
    "sg:province":"ON",
    "sg:tags":[
        "pizza"
    ],
    "wof:name":"Domino's Pizza",
    "wof:placetype":"venue"
},
  "geometry": {"coordinates":[-79.08987399999999,43.828335],"type":"Point"}
}