{
  "type": "Feature",
  "properties": {
    "addr:full":"6715 County Rd 46 Maidstone ON N0R 1K0",
    "addr:housenumber":"6715;46",
    "addr:postcode":"n0r 1k0",
    "addr:street":"County Rd",
    "iso:country":"CA",
    "sg:address":"6715 County Rd 46",
    "sg:city":"Maidstone",
    "sg:classifiers":[
        {
            "category":"Retail",
            "subcategory":"Auto Repair",
            "type":"Services"
        }
    ],
    "sg:phone":"+1 519 737 6224",
    "sg:postcode":"N0R 1K0",
    "sg:province":"ON",
    "sg:tags":[
        "body",
        "automobile",
        "painting"
    ],
    "wof:name":"Lafreniere Auto Body",
    "wof:placetype":"venue"
},
  "geometry": {"coordinates":[-82.890511,42.210068],"type":"Point"}
}