{
  "type": "Feature",
  "properties": {
    "addr:full":"Ohsweken ON N0A 1M0",
    "addr:postcode":"n0a 1m0",
    "iso:country":"CA",
    "sg:city":"Ohsweken",
    "sg:classifiers":[
        {
            "category":"Social Services",
            "type":"Services"
        }
    ],
    "sg:phone":"+1 519 445 0216",
    "sg:postcode":"N0A 1M0",
    "sg:province":"ON",
    "sg:tags":[
        "organization",
        "welfare"
    ],
    "wof:name":"My Home on Turtle Island",
    "wof:placetype":"venue"
},
  "geometry": {"coordinates":[-80.1143417358,43.0709228516],"type":"Point"}
}