{
  "type": "Feature",
  "properties": {
    "addr:full":"4532 6 St NE Calgary AB T2E 3Z7",
    "addr:housenumber":"4532 6",
    "addr:postcode":"t2e 3z7",
    "addr:street":"St Ne",
    "iso:country":"CA",
    "sg:address":"4532 6 St NE",
    "sg:city":"Calgary",
    "sg:classifiers":[
        {
            "category":"Manufacturing",
            "subcategory":"Tools & Machinery",
            "type":"Manufacturing & Wholesale Goods"
        }
    ],
    "sg:phone":"+1 403 276 9292",
    "sg:postcode":"T2E 3Z7",
    "sg:province":"AB",
    "sg:tags":[
        "machine",
        "shop"
    ],
    "wof:name":"Canadian High Tech Machining",
    "wof:placetype":"venue"
},
  "geometry": {"coordinates":[-114.047943,51.092079],"type":"Point"}
}