{
  "type": "Feature",
  "properties": {
    "addr:full":"300 Place D'Youville Montreal QC H2Y 2B6",
    "addr:housenumber":"300",
    "addr:postcode":"h2y 2b6",
    "addr:street":"Place D'Youville",
    "iso:country":"CA",
    "sg:address":"300 Place D'Youville",
    "sg:city":"Montreal",
    "sg:classifiers":[
        {
            "category":"Professional",
            "subcategory":"Advertising",
            "type":"Services"
        }
    ],
    "sg:phone":"+1 514 282 0980",
    "sg:postcode":"H2Y 2B6",
    "sg:province":"QC",
    "wof:name":"Productions Les Mercenaires",
    "wof:placetype":"venue"
},
  "geometry": {"coordinates":[-73.6438674927,45.5474205017],"type":"Point"}
}