{
  "type": "Feature",
  "properties": {
    "addr:full":"RR 4 STN Main Box 20 Orillia ON L3V 6H4",
    "addr:housenumber":"box 20",
    "addr:postcode":"l3v 6h4",
    "addr:street":"Rr 4 Stn Main",
    "iso:country":"CA",
    "sg:address":"RR 4 STN Main Box 20",
    "sg:city":"Orillia",
    "sg:classifiers":[
        {
            "category":"Shopping",
            "subcategory":"Clothing, Apparel, & Fashions",
            "type":"Retail Goods"
        }
    ],
    "sg:phone":"+1 705 325 4934",
    "sg:postcode":"L3V 6H4",
    "sg:province":"ON",
    "wof:name":"Alia",
    "wof:placetype":"venue"
},
  "geometry": {"coordinates":[-79.418228,44.60659],"type":"Point"}
}