{
  "type": "Feature",
  "properties": {
    "addr:full":"Dorval QC H9S 3H7",
    "addr:postcode":"h9s 3h7",
    "iso:country":"CA",
    "sg:city":"Dorval",
    "sg:classifiers":[
        {
            "category":"Restaurant",
            "type":"Food & Drink"
        }
    ],
    "sg:phone":"+1 514 631 5413",
    "sg:postcode":"H9S 3H7",
    "sg:province":"QC",
    "wof:name":"Tiki Wok",
    "wof:placetype":"venue"
},
  "geometry": {"coordinates":[-73.741287,45.444874],"type":"Point"}
}