{
  "type": "Feature",
  "properties": {
    "addr:full":"41 Mill St W Tottenham ON L0G 1W0",
    "addr:housenumber":"41",
    "addr:postcode":"l0g 1w0",
    "addr:street":"Mill St W Tottenham",
    "iso:country":"CA",
    "sg:address":"41 Mill St W",
    "sg:city":"Tottenham",
    "sg:classifiers":[
        {
            "category":"Wholesale",
            "subcategory":"Farm Supplies",
            "type":"Manufacturing & Wholesale Goods"
        }
    ],
    "sg:phone":"+1 905 936 4163",
    "sg:postcode":"L0G 1W0",
    "sg:province":"ON",
    "sg:tags":[
        "feed"
    ],
    "wof:name":"Tottenham Feed Svc Ltd",
    "wof:placetype":"venue"
},
  "geometry": {"coordinates":[-79.809059,44.021564],"type":"Point"}
}