{
  "type": "Feature",
  "properties": {
    "addr:full":"92 Rue Saint-Joseph Sainte-Therese QC J7E 3L9",
    "addr:housenumber":"92",
    "addr:postcode":"j7e 3l9",
    "addr:street":"Rue Saint-Joseph Sainte-Therese",
    "iso:country":"CA",
    "sg:address":"92 Rue Saint-Joseph",
    "sg:city":"Sainte-Therese",
    "sg:classifiers":[
        {
            "category":"Personal",
            "type":"Services"
        }
    ],
    "sg:phone":"+1 450 435 9344",
    "sg:postcode":"J7E 3L9",
    "sg:province":"QC",
    "sg:tags":[
        "control",
        "weight"
    ],
    "wof:name":"Clinique DE Cellulite Option",
    "wof:placetype":"venue"
},
  "geometry": {"coordinates":[-73.8407669067,45.636882782],"type":"Point"}
}