{
  "type": "Feature",
  "properties": {
    "addr:full":"650 Kingston Rd Pickering ON L1V 1A6",
    "addr:housenumber":"650",
    "addr:postcode":"l1v 1a6",
    "addr:street":"Kingston Rd",
    "iso:country":"CA",
    "sg:address":"650 Kingston Rd",
    "sg:city":"Pickering",
    "sg:classifiers":[
        {
            "category":"Shopping",
            "subcategory":"Music",
            "type":"Retail Goods"
        }
    ],
    "sg:phone":"+1 905 837 9449",
    "sg:postcode":"L1V 1A6",
    "sg:province":"ON",
    "sg:tags":[
        "compact",
        "record",
        "disc",
        "tape"
    ],
    "wof:name":"Deja Vu Discs",
    "wof:placetype":"venue"
},
  "geometry": {"coordinates":[-79.117317,43.817837],"type":"Point"}
}