{
  "type": "Feature",
  "properties": {
    "addr:full":"Calgary AB T2P 2W3",
    "addr:postcode":"t2p 2w3",
    "iso:country":"CA",
    "sg:city":"Calgary",
    "sg:classifiers":[
        {
            "category":"Shopping",
            "subcategory":"Clothing, Apparel, & Fashions",
            "type":"Retail Goods"
        }
    ],
    "sg:phone":"+1 403 265 2081",
    "sg:postcode":"T2P 2W3",
    "sg:province":"AB",
    "wof:name":"Thomas Jeffery Men's Wear",
    "wof:placetype":"venue"
},
  "geometry": {"coordinates":[-114.066146851,51.0464057922],"type":"Point"}
}