{
  "type": "Feature",
  "properties": {
    "addr:full":"32012 Joyce Ave Abbotsford BC V2T 1B7",
    "addr:housenumber":"32012",
    "addr:postcode":"v2t 1b7",
    "addr:street":"Joyce Ave",
    "iso:country":"CA",
    "sg:address":"32012 Joyce Ave",
    "sg:city":"Abbotsford",
    "sg:classifiers":[
        {
            "category":"Autos & Motor Vehicles",
            "subcategory":"Automobile Sales",
            "type":"Retail Goods"
        }
    ],
    "sg:phone":"+1 604 857 1471",
    "sg:postcode":"V2T 1B7",
    "sg:province":"BC",
    "sg:tags":[
        "car",
        "dealer"
    ],
    "wof:name":"Abbotsford Auto World Ltd",
    "wof:placetype":"venue"
},
  "geometry": {"coordinates":[-122.33669281,49.0397109985],"type":"Point"}
}