{
  "type": "Feature",
  "properties": {
    "addr:full":"3038 Exton Way 150 Mile House BC V0K 2G0",
    "addr:housenumber":"3038",
    "addr:postcode":"v0k 2g0",
    "addr:street":"Exton Way",
    "iso:country":"CA",
    "sg:address":"3038 Exton Way",
    "sg:city":"150 Mile House",
    "sg:classifiers":[
        {
            "category":"Building & Trades",
            "subcategory":"Construction",
            "type":"Services"
        }
    ],
    "sg:phone":"+1 250 296 4779",
    "sg:postcode":"V0K 2G0",
    "sg:province":"BC",
    "sg:tags":[
        "railroad",
        "contractor"
    ],
    "wof:name":"Cariboo Central Rail CO",
    "wof:placetype":"venue"
},
  "geometry": {"coordinates":[-121.920097,52.102425],"type":"Point"}
}