{
  "type": "Feature",
  "properties": {
    "addr:full":"598 7E Av Grand-Mere QC G9T 2B2",
    "addr:housenumber":"598",
    "addr:postcode":"g9t 2b2",
    "addr:street":"7E Av Grand-Mere",
    "iso:country":"CA",
    "sg:address":"598 7E Av",
    "sg:city":"Grand-Mere",
    "sg:classifiers":[
        {
            "category":"Building & Trades",
            "subcategory":"Electrical",
            "type":"Services"
        }
    ],
    "sg:phone":"+1 819 538 3379",
    "sg:postcode":"G9T 2B2",
    "sg:province":"QC",
    "sg:tags":[
        "electric",
        "contractor"
    ],
    "wof:name":"Bernard Gauthier Inc",
    "wof:placetype":"venue"
},
  "geometry": {"coordinates":[-72.6923904419,46.6157798767],"type":"Point"}
}