{
  "type": "Feature",
  "properties": {
    "addr:full":"Calgary AB T2G 2R7",
    "addr:postcode":"t2g 2r7",
    "iso:country":"CA",
    "sg:city":"Calgary",
    "sg:classifiers":[
        {
            "category":"Education",
            "subcategory":"Special Training",
            "type":"Public Place"
        }
    ],
    "sg:phone":"+1 403 220 9300",
    "sg:postcode":"T2G 2R7",
    "sg:province":"AB",
    "sg:tags":[
        "management"
    ],
    "wof:name":"Joyce Group Inc",
    "wof:placetype":"venue"
},
  "geometry": {"coordinates":[-114.062645,51.018215],"type":"Point"}
}