{
  "type": "Feature",
  "properties": {
    "addr:full":"1475 Esquimalt Ave # 205 West Vancouver BC V7T 1L2",
    "addr:housenumber":"1475",
    "addr:postcode":"v7t 1l2",
    "addr:street":"Esquimalt Ave # 205",
    "iso:country":"CA",
    "sg:address":"1475 Esquimalt Ave # 205",
    "sg:city":"West Vancouver",
    "sg:classifiers":[
        {
            "category":"Real Estate",
            "subcategory":"Real Estate Agent",
            "type":"Services"
        }
    ],
    "sg:phone":"+1 604 922 5220",
    "sg:postcode":"V7T 1L2",
    "sg:province":"BC",
    "sg:tags":[
        "authorities",
        "housing"
    ],
    "wof:name":"Capilano Tower",
    "wof:placetype":"venue"
},
  "geometry": {"coordinates":[-123.156074524,49.3307266235],"type":"Point"}
}