{
  "type": "Feature",
  "properties": {
    "addr:full":"Nakusp BC V0G 1R0",
    "addr:postcode":"v0g 1r0",
    "iso:country":"CA",
    "sg:city":"Nakusp",
    "sg:classifiers":[
        {
            "category":"Building & Trades",
            "subcategory":"Plumbing",
            "type":"Services"
        }
    ],
    "sg:phone":"+1 250 265 4901",
    "sg:postcode":"V0G 1R0",
    "sg:province":"BC",
    "sg:tags":[
        "contractor"
    ],
    "wof:name":"Witwicki's Mechanical Cntrctng",
    "wof:placetype":"venue"
},
  "geometry": {"coordinates":[-117.798561096,50.2397117615],"type":"Point"}
}