{
  "type": "Feature",
  "properties": {
    "addr:full":"Montreal QC H3B 4G5",
    "addr:postcode":"h3b 4g5",
    "iso:country":"CA",
    "sg:city":"Montreal",
    "sg:classifiers":[
        {
            "category":"Shopping",
            "subcategory":"Jewelry",
            "type":"Retail Goods"
        }
    ],
    "sg:phone":"+1 514 847 7562",
    "sg:postcode":"H3B 4G5",
    "sg:province":"QC",
    "sg:tags":[
        "jeweler"
    ],
    "wof:name":"Bijouterie Safadi",
    "wof:placetype":"venue"
},
  "geometry": {"coordinates":[-73.559196,45.515362],"type":"Point"}
}