{
  "type": "Feature",
  "properties": {
    "addr:full":"PO Box 174 Tomslake BC V0C 2L0",
    "addr:housenumber":"po",
    "addr:postcode":"bc v0c 2l0",
    "addr:street":"Box 174",
    "iso:country":"CA",
    "sg:address":"PO Box 174",
    "sg:city":"Tomslake",
    "sg:classifiers":[
        {
            "category":"Health Services",
            "subcategory":"Clinic",
            "type":"Services"
        }
    ],
    "sg:phone":"+1 250 784 5322",
    "sg:postcode":"V0C 2L0",
    "sg:province":"BC",
    "sg:tags":[
        "aid",
        "first"
    ],
    "wof:name":"Koala-T First Aid Svc",
    "wof:placetype":"venue"
},
  "geometry": {"coordinates":[-120.078948975,55.5601196289],"type":"Point"}
}