{
  "type": "Feature",
  "properties": {
    "addr:full":"Port Hawkesbury NS B9A 2R7",
    "addr:postcode":"b9a 2r7",
    "iso:country":"CA",
    "sg:city":"Port Hawkesbury",
    "sg:classifiers":[
        {
            "category":"Food & Beverages",
            "subcategory":"Liquor & Beverages",
            "type":"Retail Goods"
        }
    ],
    "sg:phone":"+1 902 625 2010",
    "sg:postcode":"B9A 2R7",
    "sg:province":"NS",
    "sg:tags":[
        "store"
    ],
    "wof:name":"Nova Scotia Liquor Commission",
    "wof:placetype":"venue"
},
  "geometry": {"coordinates":[-61.352978,45.615425],"type":"Point"}
}