{
  "type": "Feature",
  "properties": {
    "iso:country":"CA",
    "sg:address":"51 Grant Blvd",
    "sg:city":"Dundas",
    "sg:classifiers":[
        {
            "category":"Freight",
            "type":"Transportation"
        }
    ],
    "sg:phone":"+1 905 628 0127",
    "sg:postcode":"L9H 4L9",
    "sg:province":"ON",
    "sg:tags":[
        "mover"
    ],
    "wof:name":"Alan's Moving",
    "wof:placetype":"venue"
},
  "geometry": {"coordinates":[-79.93664550779999,43.2601203918],"type":"Point"}
}