{
  "type": "Feature",
  "properties": {
    "addr:full":"5720 4 St SE Calgary AB T2H 1K7",
    "addr:housenumber":"5720 4",
    "addr:postcode":"t2h 1k7",
    "addr:street":"St Se",
    "iso:country":"CA",
    "sg:address":"5720 4 St SE",
    "sg:city":"Calgary",
    "sg:classifiers":[
        {
            "category":"Building & Trades",
            "subcategory":"Construction",
            "type":"Services"
        }
    ],
    "sg:phone":"+1 403 255 5521",
    "sg:postcode":"T2H 1K7",
    "sg:province":"AB",
    "sg:tags":[
        "line",
        "general",
        "telephone",
        "power",
        "contractor"
    ],
    "wof:name":"Ace Construction CO Ltd",
    "wof:placetype":"venue"
},
  "geometry": {"coordinates":[-114.053619385,51.003452301],"type":"Point"}
}