{
  "type": "Feature",
  "properties": {
    "addr:full":"Blainville QC J7C 2K6",
    "addr:postcode":"j7c 2k6",
    "iso:country":"CA",
    "sg:city":"Blainville",
    "sg:classifiers":[
        {
            "category":"Retail",
            "subcategory":"Auto Rental",
            "type":"Services"
        }
    ],
    "sg:phone":"+1 450 437 3979",
    "sg:postcode":"J7C 2K6",
    "sg:province":"QC",
    "sg:tags":[
        "renting",
        "automobile"
    ],
    "wof:name":"Discount Location D'Autos",
    "wof:placetype":"venue"
},
  "geometry": {"coordinates":[-73.87344360349999,45.6694412231],"type":"Point"}
}