{
  "type": "Feature",
  "properties": {
    "addr:full":"720 Park Royal N West Vancouver BC V7T 1H9",
    "addr:housenumber":"720",
    "addr:postcode":"v7t 1h9",
    "addr:street":"Park Royal N",
    "iso:country":"CA",
    "sg:address":"720 Park Royal N",
    "sg:city":"West Vancouver",
    "sg:classifiers":[
        {
            "category":"Food & Beverages",
            "subcategory":"Specialty",
            "type":"Retail Goods"
        }
    ],
    "sg:phone":"+1 604 921 1928",
    "sg:postcode":"V7T 1H9",
    "sg:province":"BC",
    "sg:tags":[
        "health",
        "diet"
    ],
    "wof:name":"Alive Health Ctr Ltd",
    "wof:placetype":"venue"
},
  "geometry": {"coordinates":[-123.137184,49.327618],"type":"Point"}
}