{
  "type": "Feature",
  "properties": {
    "addr:full":"5100 Boul Cousineau # 102 Saint-Hubert QC J3Y 7G5",
    "addr:housenumber":"5100",
    "addr:postcode":"j3y 7g5",
    "addr:street":"Boul Cousineau # 102",
    "iso:country":"CA",
    "sg:address":"5100 Boul Cousineau # 102",
    "sg:city":"Saint-Hubert",
    "sg:classifiers":[
        {
            "category":"Health Services",
            "subcategory":"Chiropractor",
            "type":"Services"
        }
    ],
    "sg:phone":"+1 450 445 5454",
    "sg:postcode":"J3Y 7G5",
    "sg:province":"QC",
    "wof:name":"Clinique Chiro-Sante Rive-Sud",
    "wof:placetype":"venue"
},
  "geometry": {"coordinates":[-73.42915344239999,45.5040664673],"type":"Point"}
}