{
  "type": "Feature",
  "properties": {
    "addr:full":"Calgary AB T2R 0H7",
    "addr:postcode":"t2r 0h7",
    "iso:country":"CA",
    "sg:city":"Calgary",
    "sg:classifiers":[
        {
            "category":"Professional",
            "subcategory":"Research",
            "type":"Services"
        }
    ],
    "sg:phone":"+1 403 699 8802",
    "sg:postcode":"T2R 0H7",
    "sg:province":"AB",
    "sg:tags":[
        "development",
        "laboratory"
    ],
    "wof:name":"Canadian Outcomes Institute",
    "wof:placetype":"venue"
},
  "geometry": {"coordinates":[-114.077194214,51.0419311523],"type":"Point"}
}