{
  "type": "Feature",
  "properties": {
    "addr:full":"300 Rue Richelieu Saint-Jean-Sur-Richelieu QC J3B 6Y4",
    "addr:housenumber":"300",
    "addr:postcode":"j3b 6y4",
    "addr:street":"Rue Richelieu",
    "iso:country":"CA",
    "sg:address":"300 Rue Richelieu",
    "sg:city":"Saint-Jean-Sur-Richelieu",
    "sg:classifiers":[
        {
            "category":"Restaurant",
            "type":"Food & Drink"
        }
    ],
    "sg:phone":"+1 450 347 1872",
    "sg:postcode":"J3B 6Y4",
    "sg:province":"QC",
    "wof:name":"Capitaine Pouf",
    "wof:placetype":"venue"
},
  "geometry": {"coordinates":[-73.25118999999999,45.308643],"type":"Point"}
}