{
  "type": "Feature",
  "properties": {
    "addr:full":"1400 Ch DE L'Avenir Deux-Montagnes QC J7R 6A6",
    "addr:housenumber":"1400",
    "addr:postcode":"j7r 6a6",
    "addr:street":"Ch De L'Avenir",
    "iso:country":"CA",
    "sg:address":"1400 Ch DE L'Avenir",
    "sg:city":"Deux-Montagnes",
    "sg:classifiers":[
        {
            "category":"Education",
            "subcategory":"School",
            "type":"Public Place"
        }
    ],
    "sg:phone":"+1 450 472 2670",
    "sg:postcode":"J7R 6A6",
    "sg:province":"QC",
    "wof:name":"Pavillon Des Erables Ecole",
    "wof:placetype":"venue"
},
  "geometry": {"coordinates":[-73.9049530029,45.5462188721],"type":"Point"}
}