{
  "type": "Feature",
  "properties": {
    "addr:full":"Surrey BC V3S 3C3",
    "addr:postcode":"v3s 3c3",
    "iso:country":"CA",
    "sg:city":"Surrey",
    "sg:classifiers":[
        {
            "category":"Wholesale",
            "subcategory":"Construction Materials",
            "type":"Manufacturing & Wholesale Goods"
        }
    ],
    "sg:phone":"+1 604 599 0322",
    "sg:postcode":"V3S 3C3",
    "sg:province":"BC",
    "sg:tags":[
        "frame",
        "door"
    ],
    "wof:name":"Richwood Distribution Inc",
    "wof:placetype":"venue"
},
  "geometry": {"coordinates":[-122.812408,49.117435],"type":"Point"}
}