{
  "type": "Feature",
  "properties": {
    "addr:full":"375 Route 8 Nashwaak Village NB E6C 1M5",
    "addr:housenumber":"375",
    "addr:postcode":"e6c 1m5",
    "addr:street":"Route 8",
    "iso:country":"CA",
    "sg:address":"375 Route 8",
    "sg:city":"Nashwaak Village",
    "sg:classifiers":[
        {
            "category":"Restaurant",
            "type":"Food & Drink"
        }
    ],
    "sg:phone":"+1 506 472 3940",
    "sg:postcode":"E6C 1M5",
    "sg:province":"NB",
    "wof:name":"Ben's Pizza",
    "wof:placetype":"venue"
},
  "geometry": {"coordinates":[-66.605705,46.105015],"type":"Point"}
}