{
  "type": "Feature",
  "properties": {
    "addr:full":"511 Rue Saint-Francois-Xavier Terrebonne QC J6W 1G1",
    "addr:housenumber":"511",
    "addr:postcode":"j6w 1g1",
    "addr:street":"Rue Saint-Francois-Xavier",
    "iso:country":"CA",
    "sg:address":"511 Rue Saint-Francois-Xavier",
    "sg:city":"Terrebonne",
    "sg:classifiers":[
        {
            "category":"Autos & Motor Vehicles",
            "subcategory":"Auto Supplies",
            "type":"Retail Goods"
        }
    ],
    "sg:phone":"+1 450 471 8679",
    "sg:postcode":"J6W 1G1",
    "sg:province":"QC",
    "sg:tags":[
        "alternator",
        "automobile",
        "parts",
        "generator"
    ],
    "wof:name":"Atelier Dynamo Enr",
    "wof:placetype":"venue"
},
  "geometry": {"coordinates":[-73.6299743652,45.6943626404],"type":"Point"}
}