{
  "type": "Feature",
  "properties": {
    "addr:full":"248 Manitoba St # 3 Bracebridge ON P1L 2E1",
    "addr:housenumber":"248",
    "addr:postcode":"p1l 2e1",
    "addr:street":"Manitoba St # 3",
    "iso:country":"CA",
    "sg:address":"248 Manitoba St # 3",
    "sg:city":"Bracebridge",
    "sg:classifiers":[
        {
            "category":"Shopping",
            "type":"Retail Goods"
        }
    ],
    "sg:phone":"+1 705 645 3470",
    "sg:postcode":"P1L 2E1",
    "sg:province":"ON",
    "sg:tags":[
        "pet",
        "food",
        "shop",
        "supply"
    ],
    "wof:name":"Paulmac's Pet Food",
    "wof:placetype":"venue"
},
  "geometry": {"coordinates":[-79.31847381590001,45.0449447632],"type":"Point"}
}