{
  "type": "Feature",
  "properties": {
    "iso:country":"CA",
    "sg:city":"Surrey",
    "sg:classifiers":[
        {
            "category":"Manufacturing",
            "subcategory":"Glass & Minerals",
            "type":"Manufacturing & Wholesale Goods"
        }
    ],
    "sg:phone":"+1 604 594 6311",
    "sg:postcode":"V3W 0A8",
    "sg:province":"BC",
    "wof:name":"Sunlight Art Glass",
    "wof:placetype":"venue"
},
  "geometry": {"coordinates":[-122.849914551,49.1447372437],"type":"Point"}
}