{
  "type": "Feature",
  "properties": {
    "addr:full":"550 Rue Stanislas Koska Wendake QC G0A 4V0",
    "addr:housenumber":"550",
    "addr:postcode":"g0a 4v0",
    "addr:street":"Rue Stanislas Koska",
    "iso:country":"CA",
    "sg:address":"550 Rue Stanislas Koska",
    "sg:city":"Wendake",
    "sg:classifiers":[
        {
            "category":"Professional",
            "type":"Services"
        }
    ],
    "sg:phone":"+1 418 847 0883",
    "sg:postcode":"G0A 4V0",
    "sg:province":"QC",
    "sg:tags":[
        "sculptor"
    ],
    "wof:name":"Mastersculptures Inc",
    "wof:placetype":"venue"
},
  "geometry": {"coordinates":[-73.69668579099999,45.9864578247],"type":"Point"}
}