{
  "type": "Feature",
  "properties": {
    "addr:full":"Chambord QC G0W 1G0",
    "addr:postcode":"g0w 1g0",
    "iso:country":"CA",
    "sg:city":"Chambord",
    "sg:classifiers":[
        {
            "category":"Government",
            "subcategory":"Office",
            "type":"Public Place"
        }
    ],
    "sg:phone":"+1 418 275 3132",
    "sg:postcode":"G0W 1G0",
    "sg:province":"QC",
    "wof:name":"Quebec Village Historique",
    "wof:placetype":"venue"
},
  "geometry": {"coordinates":[-71.97265625,48.4182052612],"type":"Point"}
}