{
  "type": "Feature",
  "properties": {
    "addr:full":"157 Whitewood Ave New Liskeard ON P0J 1P0",
    "addr:housenumber":"157",
    "addr:postcode":"p0j 1p0",
    "addr:street":"Whitewood Ave",
    "iso:country":"CA",
    "sg:address":"157 Whitewood Ave",
    "sg:city":"New Liskeard",
    "sg:classifiers":[
        {
            "category":"Organizations",
            "subcategory":"Professional Association",
            "type":"Services"
        }
    ],
    "sg:phone":"+1 705 647 1200",
    "sg:postcode":"P0J 1P0",
    "sg:province":"ON",
    "sg:tags":[
        "social",
        "welfare"
    ],
    "wof:name":"Timiskaming Child & Family Svc",
    "wof:placetype":"venue"
},
  "geometry": {"coordinates":[-79.67789459230001,47.5087890625],"type":"Point"}
}