{
  "type": "Feature",
  "properties": {
    "iso:country":"CA",
    "sg:address":"64 Mill St",
    "sg:city":"Almonte",
    "sg:classifiers":[
        {
            "category":"Real Estate",
            "subcategory":"Developer",
            "type":"Services"
        }
    ],
    "sg:phone":"+1 613 256 5717",
    "sg:postcode":"K0A 1A0",
    "sg:province":"ON",
    "sg:tags":[
        "company",
        "land"
    ],
    "wof:name":"Almonte Land Management",
    "wof:placetype":"venue"
},
  "geometry": {"coordinates":[-76.195679,45.225399],"type":"Point"}
}