{
  "type": "Feature",
  "properties": {
    "addr:full":"7405 127 Ave NW Edmonton AB T5C 1R9",
    "addr:housenumber":"7405",
    "addr:postcode":"t5c 1r9",
    "addr:street":"127 Ave Nw",
    "iso:country":"CA",
    "sg:address":"7405 127 Ave NW",
    "sg:city":"Edmonton",
    "sg:classifiers":[
        {
            "category":"Freight",
            "type":"Transportation"
        }
    ],
    "sg:phone":"+1 780 478 8561",
    "sg:postcode":"T5C 1R9",
    "sg:province":"AB",
    "sg:tags":[
        "warehouse",
        "storage"
    ],
    "wof:name":"Versacold Group",
    "wof:placetype":"venue"
},
  "geometry": {"coordinates":[-113.45575714100001,53.5848083496],"type":"Point"}
}