{
  "type": "Feature",
  "properties": {
    "addr:full":"128 Green Rd Sydney NS B1P 3E5",
    "addr:housenumber":"128",
    "addr:postcode":"b1p 3e5",
    "addr:street":"Green Rd",
    "iso:country":"CA",
    "sg:address":"128 Green Rd",
    "sg:city":"Sydney",
    "sg:classifiers":[
        {
            "category":"Restaurant",
            "type":"Food & Drink"
        }
    ],
    "sg:phone":"+1 902 562 4688",
    "sg:postcode":"B1P 3E5",
    "sg:province":"NS",
    "sg:tags":[
        "caterer"
    ],
    "wof:name":"Sydney Party Rentals Catering",
    "wof:placetype":"venue"
},
  "geometry": {"coordinates":[-60.1495628357,46.1449012756],"type":"Point"}
}