{
  "type": "Feature",
  "properties": {
    "addr:full":"Harbour Breton NL A0H 1P0",
    "addr:postcode":"a0h 1p0",
    "iso:country":"CA",
    "sg:city":"Harbour Breton",
    "sg:classifiers":[
        {
            "category":"Organizations",
            "subcategory":"Religious Organization",
            "type":"Services"
        }
    ],
    "sg:phone":"+1 709 885 2225",
    "sg:postcode":"A0H 1P0",
    "sg:province":"NL",
    "sg:tags":[
        "church"
    ],
    "wof:name":"St Bartholomew Anglican Church",
    "wof:placetype":"venue"
},
  "geometry": {"coordinates":[-55.821507,47.469494],"type":"Point"}
}