{
  "type": "Feature",
  "properties": {
    "addr:full":"115 Brentwood Rd N Etobicoke ON M8X 2C7",
    "addr:housenumber":"115",
    "addr:postcode":"m8x 2c7",
    "addr:street":"Brentwood Rd N",
    "iso:country":"CA",
    "sg:address":"115 Brentwood Rd N",
    "sg:city":"Etobicoke",
    "sg:classifiers":[
        {
            "category":"Professional",
            "subcategory":"Management & Consulting",
            "type":"Services"
        }
    ],
    "sg:phone":"+1 416 239 7779",
    "sg:postcode":"M8X 2C7",
    "sg:province":"ON",
    "sg:tags":[
        "consultant",
        "business"
    ],
    "wof:name":"Vertex Intellectual Property",
    "wof:placetype":"venue"
},
  "geometry": {"coordinates":[-79.515381,43.651325],"type":"Point"}
}