{
  "type": "Feature",
  "properties": {
    "addr:full":"Swift Current SK S9H 2B4",
    "addr:postcode":"s9h 2b4",
    "iso:country":"CA",
    "sg:city":"Swift Current",
    "sg:classifiers":[
        {
            "category":"Professional",
            "subcategory":"Lawyer & Legal Services",
            "type":"Services"
        }
    ],
    "sg:phone":"+1 306 773 7205",
    "sg:postcode":"S9H 2B4",
    "sg:province":"SK",
    "sg:tags":[
        "attorney"
    ],
    "wof:name":"Mc Laughlin Forrester Heinrich",
    "wof:placetype":"venue"
},
  "geometry": {"coordinates":[-107.79892,50.285931],"type":"Point"}
}