{
  "type": "Feature",
  "properties": {
    "addr:full":"325 Rue Joliette Longueuil QC J4H 2G6",
    "addr:housenumber":"325",
    "addr:postcode":"j4h 2g6",
    "addr:street":"Rue Joliette",
    "iso:country":"CA",
    "sg:address":"325 Rue Joliette",
    "sg:city":"Longueuil",
    "sg:classifiers":[
        {
            "category":"Real Estate",
            "subcategory":"Real Estate Operator",
            "type":"Services"
        }
    ],
    "sg:phone":"+1 450 651 1400",
    "sg:postcode":"J4H 2G6",
    "sg:province":"QC",
    "sg:tags":[
        "apartment"
    ],
    "wof:name":"Domaine D'Iberville Ltee",
    "wof:placetype":"venue"
},
  "geometry": {"coordinates":[-73.51863098139999,45.531539917],"type":"Point"}
}