{
  "type": "Feature",
  "properties": {
    "addr:full":"374 Principale Saint-Cyprien QC G0L 2P0",
    "addr:housenumber":"374",
    "addr:postcode":"g0l 2p0",
    "addr:street":"Principale",
    "iso:country":"CA",
    "sg:address":"374 Principale",
    "sg:city":"Saint-Cyprien",
    "sg:classifiers":[
        {
            "category":"Building & Trades",
            "subcategory":"Landscaping Services",
            "type":"Services"
        }
    ],
    "sg:phone":"+1 418 383 5123",
    "sg:postcode":"G0L 2P0",
    "sg:province":"QC",
    "sg:tags":[
        "landscape",
        "contractor"
    ],
    "wof:name":"Morisette, Dany",
    "wof:placetype":"venue"
},
  "geometry": {"coordinates":[-70.2620773315,46.354309082],"type":"Point"}
}