{
  "type": "Feature",
  "properties": {
    "addr:full":"Edmonton AB T5H 4J1",
    "addr:postcode":"t5h 4j1",
    "iso:country":"CA",
    "sg:city":"Edmonton",
    "sg:classifiers":[
        {
            "category":"Personal",
            "subcategory":"Beauty Salon",
            "type":"Services"
        }
    ],
    "sg:phone":"+1 780 425 3424",
    "sg:postcode":"T5H 4J1",
    "sg:province":"AB",
    "wof:name":"Coral Salon",
    "wof:placetype":"venue"
},
  "geometry": {"coordinates":[-113.48831199999999,53.548801],"type":"Point"}
}