{
  "type": "Feature",
  "properties": {
    "iso:country":"CA",
    "sg:address":"4545 Jane St",
    "sg:city":"North York",
    "sg:classifiers":[
        {
            "category":"Organizations",
            "subcategory":"Religious Organization",
            "type":"Services"
        }
    ],
    "sg:phone":"+1 416 736 1322",
    "sg:postcode":"M3N 2K7",
    "sg:province":"ON",
    "sg:tags":[
        "church"
    ],
    "wof:name":"Faithful Remnant Spanish Chr",
    "wof:placetype":"venue"
},
  "geometry": {"coordinates":[-79.519745,43.766953],"type":"Point"}
}