{
  "type": "Feature",
  "properties": {
    "addr:full":"3915 Boul Des Fondateurs Saint-Isidore NB E8M 1C1",
    "addr:housenumber":"3915",
    "addr:postcode":"e8m 1c1",
    "addr:street":"Boul Des Fondateurs",
    "iso:country":"CA",
    "sg:address":"3915 Boul Des Fondateurs",
    "sg:city":"Saint-Isidore",
    "sg:classifiers":[
        {
            "category":"Organizations",
            "subcategory":"Religious Organization",
            "type":"Services"
        }
    ],
    "sg:phone":"+1 506 358 2371",
    "sg:postcode":"E8M 1C1",
    "sg:province":"NB",
    "sg:tags":[
        "church"
    ],
    "wof:name":"St Isidore Catholic Church",
    "wof:placetype":"venue"
},
  "geometry": {"coordinates":[-65.05635100000001,47.552952],"type":"Point"}
}