{
  "type": "Feature",
  "properties": {
    "addr:full":"Teulon MB R0C 3B0",
    "addr:postcode":"r0c 3b0",
    "iso:country":"CA",
    "sg:city":"Teulon",
    "sg:classifiers":[
        {
            "category":"Wholesale",
            "subcategory":"Farm Supplies",
            "type":"Manufacturing & Wholesale Goods"
        }
    ],
    "sg:phone":"+1 204 886 3100",
    "sg:postcode":"R0C 3B0",
    "sg:province":"MB",
    "wof:name":"Rockwood Farm Supplies",
    "wof:placetype":"venue"
},
  "geometry": {"coordinates":[-97.252617,50.389114],"type":"Point"}
}