{
  "type": "Feature",
  "properties": {
    "addr:full":"Rockland ON K4K 1K4",
    "addr:postcode":"k4k 1k4",
    "addr:street":"Rockland",
    "iso:country":"CA",
    "sg:city":"Rockland",
    "sg:classifiers":[
        {
            "category":"Insurance",
            "subcategory":"Insurance Agent",
            "type":"Services"
        }
    ],
    "sg:phone":"+1 613 446 2045",
    "sg:postcode":"K4K 1K4",
    "sg:province":"ON",
    "wof:name":"Budget Concept Financial Inc",
    "wof:placetype":"venue"
},
  "geometry": {"coordinates":[-75.287964,45.551758],"type":"Point"}
}