{
  "type": "Feature",
  "properties": {
    "addr:full":"Lloydminster AB T9V 2S8",
    "addr:postcode":"t9v 2s8",
    "iso:country":"CA",
    "sg:city":"Lloydminster",
    "sg:classifiers":[
        {
            "category":"Building & Trades",
            "subcategory":"Construction",
            "type":"Services"
        }
    ],
    "sg:phone":"+1 780 875 1659",
    "sg:postcode":"T9V 2S8",
    "sg:province":"AB",
    "sg:tags":[
        "general",
        "road",
        "contractor"
    ],
    "wof:name":"Valley C Construction Ltd",
    "wof:placetype":"venue"
},
  "geometry": {"coordinates":[-110.01279449499999,53.2967338562],"type":"Point"}
}