{
  "type": "Feature",
  "properties": {
    "iso:country":"CA",
    "sg:address":"17304 Stony Plain Rd NW",
    "sg:city":"Edmonton",
    "sg:classifiers":[
        {
            "category":"Retail",
            "subcategory":"Auto Repair",
            "type":"Services"
        }
    ],
    "sg:phone":"+1 780 423 7902",
    "sg:postcode":"T5S 1K6",
    "sg:province":"AB",
    "sg:tags":[
        "repairing",
        "automobile"
    ],
    "wof:name":"Karmac-German Autohaus",
    "wof:placetype":"venue"
},
  "geometry": {"coordinates":[-113.619041443,53.542427063],"type":"Point"}
}