{
  "type": "Feature",
  "properties": {
    "addr:full":"630 Rue Trudel Saint-Jerome QC J7Z 1H7",
    "addr:housenumber":"630",
    "addr:postcode":"j7z 1h7",
    "addr:street":"Rue Trudel Saint-Jerome",
    "iso:country":"CA",
    "sg:address":"630 Rue Trudel",
    "sg:city":"Saint-Jerome",
    "sg:classifiers":[
        {
            "category":"Education",
            "subcategory":"School",
            "type":"Public Place"
        }
    ],
    "sg:phone":"+1 450 438 6078",
    "sg:postcode":"J7Z 1H7",
    "sg:province":"QC",
    "wof:name":"Laurentia Elementary School",
    "wof:placetype":"venue"
},
  "geometry": {"coordinates":[-74.00351000000001,45.775009],"type":"Point"}
}