{
  "type": "Feature",
  "properties": {
    "addr:full":"5029 49th Ave Ponoka AB T4J 1S8",
    "addr:housenumber":"5029",
    "addr:postcode":"t4j 1s8",
    "addr:street":"49Th Ave",
    "iso:country":"CA",
    "sg:address":"5029 49th Ave",
    "sg:city":"Ponoka",
    "sg:classifiers":[
        {
            "category":"Shopping",
            "subcategory":"Stationery & Office Supplies",
            "type":"Retail Goods"
        }
    ],
    "sg:phone":"+1 403 783 3777",
    "sg:postcode":"T4J 1S8",
    "sg:province":"AB",
    "sg:tags":[
        "educational",
        "material"
    ],
    "wof:name":"Advance School Equipment Ltd",
    "wof:placetype":"venue"
},
  "geometry": {"coordinates":[-113.57755299999999,52.675285],"type":"Point"}
}