{
  "type": "Feature",
  "properties": {
    "addr:full":"49 Boul St-Pierre O #A Caraquet NB E1W 1B6",
    "addr:housenumber":"49",
    "addr:postcode":"e1w 1b6",
    "addr:street":"Boul St-Pierre O # A Caraquet",
    "iso:country":"CA",
    "sg:address":"49 Boul St-Pierre O #A",
    "sg:city":"Caraquet",
    "sg:classifiers":[
        {
            "category":"Bars & Pubs",
            "type":"Food & Drink"
        }
    ],
    "sg:phone":"+1 506 727 5553",
    "sg:postcode":"E1W 1B6",
    "sg:province":"NB",
    "sg:tags":[
        "club",
        "night"
    ],
    "wof:name":"Bar Sportif Chez Bebe",
    "wof:placetype":"venue"
},
  "geometry": {"coordinates":[-64.95227050779999,47.7910690308],"type":"Point"}
}