{
  "type": "Feature",
  "properties": {
    "addr:full":"Lachine QC H8T 1C3",
    "addr:postcode":"h8t 1c3",
    "iso:country":"CA",
    "sg:city":"Lachine",
    "sg:classifiers":[
        {
            "category":"Wholesale",
            "subcategory":"Metals & Minerals",
            "type":"Manufacturing & Wholesale Goods"
        }
    ],
    "sg:phone":"+1 514 828 0057",
    "sg:postcode":"H8T 1C3",
    "sg:province":"QC",
    "sg:tags":[
        "rope",
        "wire"
    ],
    "wof:name":"Helix Uniforme Ltee",
    "wof:placetype":"venue"
},
  "geometry": {"coordinates":[-73.702225,45.465149],"type":"Point"}
}