{
  "type": "Feature",
  "properties": {
    "addr:full":"4646 37 St SW Calgary AB T3E 3C9",
    "addr:housenumber":"4646",
    "addr:postcode":"t3e 3c9",
    "addr:street":"37 St Sw",
    "iso:country":"CA",
    "sg:address":"4646 37 St SW",
    "sg:city":"Calgary",
    "sg:classifiers":[
        {
            "category":"Autos & Motor Vehicles",
            "subcategory":"Fuel & Gas Station",
            "type":"Retail Goods"
        }
    ],
    "sg:phone":"+1 403 246 0406",
    "sg:postcode":"T3E 3C9",
    "sg:province":"AB",
    "sg:tags":[
        "oil"
    ],
    "wof:name":"Petro-Canada",
    "wof:placetype":"venue"
},
  "geometry": {"coordinates":[-114.14106,51.012699],"type":"Point"}
}