{
  "type": "Feature",
  "properties": {
    "addr:full":"274 Lake St St Catharines ON L2N 4H1",
    "addr:housenumber":"274",
    "addr:postcode":"l2n 4h1",
    "addr:street":"Lake St",
    "iso:country":"CA",
    "sg:address":"274 Lake St",
    "sg:city":"St Catharines",
    "sg:classifiers":[
        {
            "category":"Restaurant",
            "type":"Food & Drink"
        }
    ],
    "sg:phone":"+1 905 646 7827",
    "sg:postcode":"L2N 4H1",
    "sg:province":"ON",
    "wof:name":"Subway Sandwiches & Salads",
    "wof:placetype":"venue"
},
  "geometry": {"coordinates":[-79.2513046265,43.1803627014],"type":"Point"}
}