{
  "type": "Feature",
  "properties": {
    "addr:full":"103 2 Ave W Foremost AB T0K 0X0",
    "addr:housenumber":"103",
    "addr:postcode":"t0k 0x0",
    "addr:street":"2 Ave W Foremost",
    "iso:country":"CA",
    "sg:address":"103 2 Ave W",
    "sg:city":"Foremost",
    "sg:classifiers":[
        {
            "category":"Home & Garden",
            "subcategory":"Building Materials",
            "type":"Retail Goods"
        }
    ],
    "sg:phone":"+1 403 867 3573",
    "sg:postcode":"T0K 0X0",
    "sg:province":"AB",
    "wof:name":"Foremost Building Supplies Ltd",
    "wof:placetype":"venue"
},
  "geometry": {"coordinates":[-111.441711,49.478008],"type":"Point"}
}