{
  "type": "Feature",
  "properties": {
    "addr:full":"Levis QC G6V 6C1",
    "addr:postcode":"g6v 6c1",
    "iso:country":"CA",
    "sg:city":"Levis",
    "sg:classifiers":[
        {
            "category":"Restaurant",
            "type":"Food & Drink"
        }
    ],
    "sg:phone":"+1 418 833 6001",
    "sg:postcode":"G6V 6C1",
    "sg:province":"QC",
    "sg:tags":[
        "parlor",
        "ice",
        "cream"
    ],
    "wof:name":"Bar Laitier Le Bidon Inc",
    "wof:placetype":"venue"
},
  "geometry": {"coordinates":[-71.181915,46.799187],"type":"Point"}
}