{
  "type": "Feature",
  "properties": {
    "addr:full":"2105 Portage Ave Winnipeg MB R3J 0L2",
    "addr:housenumber":"2105",
    "addr:postcode":"r3j 0l2",
    "addr:street":"Portage Ave",
    "iso:country":"CA",
    "sg:address":"2105 Portage Ave",
    "sg:city":"Winnipeg",
    "sg:classifiers":[
        {
            "category":"Restaurant",
            "type":"Food & Drink"
        }
    ],
    "sg:phone":"+1 204 888 5912",
    "sg:postcode":"R3J 0L2",
    "sg:province":"MB",
    "wof:name":"Rainbow Chinese Vietnamese",
    "wof:placetype":"venue"
},
  "geometry": {"coordinates":[-97.234138,49.87748],"type":"Point"}
}