{
  "type": "Feature",
  "properties": {
    "addr:full":"5001 50th Ave St Paul AB T0A 3A0",
    "addr:housenumber":"5001",
    "addr:postcode":"t0a 3a0",
    "addr:street":"50Th Ave",
    "iso:country":"CA",
    "sg:address":"5001 50th Ave",
    "sg:city":"St Paul",
    "sg:classifiers":[
        {
            "category":"Banks & Credit Unions",
            "subcategory":"Bank",
            "type":"Services"
        }
    ],
    "sg:phone":"+1 780 645 3371",
    "sg:postcode":"T0A 3A0",
    "sg:province":"AB",
    "wof:name":"Cibc",
    "wof:placetype":"venue"
},
  "geometry": {"coordinates":[-111.29734000000001,53.991261],"type":"Point"}
}