{
  "type": "Feature",
  "properties": {
    "iso:country":"CA",
    "sg:address":"92 2E Rue O",
    "sg:city":"Rimouski",
    "sg:classifiers":[
        {
            "category":"Food & Beverages",
            "subcategory":"Groceries & Convenience Stores",
            "type":"Retail Goods"
        }
    ],
    "sg:phone":"+1 418 723 6941",
    "sg:postcode":"G5L 8B3",
    "sg:province":"QC",
    "sg:tags":[
        "grocer"
    ],
    "wof:name":"Supermarches Gp Inc",
    "wof:placetype":"venue"
},
  "geometry": {"coordinates":[-68.5120544434,48.441734314],"type":"Point"}
}