{
  "type": "Feature",
  "properties": {
    "iso:country":"CA",
    "sg:address":"155 Rue Saint-Antoine",
    "sg:city":"Loretteville",
    "sg:classifiers":[
        {
            "category":"Organizations",
            "subcategory":"Religious Organization",
            "type":"Services"
        }
    ],
    "sg:phone":"+1 418 843 1499",
    "sg:postcode":"G2A 1V6",
    "sg:province":"QC",
    "sg:tags":[
        "house",
        "retreat"
    ],
    "wof:name":"Tourelle DE L'Amitie",
    "wof:placetype":"venue"
},
  "geometry": {"coordinates":[-71.34326900000001,46.856773],"type":"Point"}
}