{
  "type": "Feature",
  "properties": {
    "addr:full":"15 Concession 12 W Tara ON N0H 2N0",
    "addr:housenumber":"15",
    "addr:postcode":"n0h 2n0",
    "addr:street":"Concession 12 W Tara",
    "iso:country":"CA",
    "sg:address":"15 Concession 12 W",
    "sg:city":"Tara",
    "sg:classifiers":[
        {
            "category":"Travel",
            "subcategory":"Hotels & Motels",
            "type":"Entertainment"
        }
    ],
    "sg:phone":"+1 519 934 2719",
    "sg:postcode":"N0H 2N0",
    "sg:province":"ON",
    "sg:tags":[
        "resort"
    ],
    "wof:name":"Loch Arran Cottage & Campsite",
    "wof:placetype":"venue"
},
  "geometry": {"coordinates":[-81.145248,44.476524],"type":"Point"}
}