{
  "type": "Feature",
  "properties": {
    "iso:country":"CA",
    "sg:address":"1034 Av Du Mont-Royal E",
    "sg:city":"Montreal",
    "sg:classifiers":[
        {
            "category":"Food & Beverages",
            "subcategory":"Liquor & Beverages",
            "type":"Retail Goods"
        }
    ],
    "sg:phone":"+1 514 523 6117",
    "sg:postcode":"H2J 1X6",
    "sg:province":"QC",
    "sg:tags":[
        "store"
    ],
    "wof:name":"Saq",
    "wof:placetype":"venue"
},
  "geometry": {"coordinates":[-73.5793914795,45.5275497437],"type":"Point"}
}