{
  "type": "Feature",
  "properties": {
    "addr:full":"1716 Fairview Rd Cambridge ON N3H 4M7",
    "addr:housenumber":"1716",
    "addr:postcode":"n3h 4m7",
    "addr:street":"Fairview Rd",
    "iso:country":"CA",
    "sg:address":"1716 Fairview Rd",
    "sg:city":"Cambridge",
    "sg:classifiers":[
        {
            "category":"Building & Trades",
            "subcategory":"Electrical",
            "type":"Services"
        }
    ],
    "sg:phone":"+1 519 653 6555",
    "sg:postcode":"N3H 4M7",
    "sg:province":"ON",
    "sg:tags":[
        "electric",
        "contractor"
    ],
    "wof:name":"Clark Electric",
    "wof:placetype":"venue"
},
  "geometry": {"coordinates":[-80.34131600000001,43.389549],"type":"Point"}
}