{
  "type": "Feature",
  "properties": {
    "addr:full":"470 Island Hwy Campbell River BC V9W 2B7",
    "addr:housenumber":"470",
    "addr:postcode":"v9w 2b7",
    "addr:street":"Island Hwy",
    "iso:country":"CA",
    "sg:address":"470 Island Hwy",
    "sg:city":"Campbell River",
    "sg:classifiers":[
        {
            "category":"Museum",
            "type":"Entertainment"
        }
    ],
    "sg:phone":"+1 250 287 3103",
    "sg:postcode":"V9W 2B7",
    "sg:province":"BC",
    "wof:name":"Campbell River Museum Shop",
    "wof:placetype":"venue"
},
  "geometry": {"coordinates":[-125.23556499999999,50.015514],"type":"Point"}
}