{
  "type": "Feature",
  "properties": {
    "addr:full":"4916 50 Ave Wetaskiwin AB T9A 3P8",
    "addr:housenumber":"4916",
    "addr:postcode":"t9a 3p8",
    "addr:street":"50 Ave",
    "iso:country":"CA",
    "sg:address":"4916 50 Ave",
    "sg:city":"Wetaskiwin",
    "sg:classifiers":[
        {
            "category":"Banks & Credit Unions",
            "subcategory":"Bank",
            "type":"Services"
        }
    ],
    "sg:phone":"+1 780 352 6011",
    "sg:postcode":"T9A 3P8",
    "sg:province":"AB",
    "wof:name":"Royal Bank Financial Group",
    "wof:placetype":"venue"
},
  "geometry": {"coordinates":[-113.373306274,52.9696731567],"type":"Point"}
}