{
  "type": "Feature",
  "properties": {
    "addr:full":"1091 Rue Bouchard Saint-Felicien QC G8K 2G6",
    "addr:housenumber":"1091",
    "addr:postcode":"g8k 2g6",
    "addr:street":"Rue Bouchard Saint-Felicien",
    "iso:country":"CA",
    "sg:address":"1091 Rue Bouchard",
    "sg:city":"Saint-Felicien",
    "sg:classifiers":[
        {
            "category":"Home & Garden",
            "subcategory":"Building Materials",
            "type":"Retail Goods"
        }
    ],
    "sg:phone":"+1 418 679 5605",
    "sg:postcode":"G8K 2G6",
    "sg:province":"QC",
    "sg:tags":[
        "door"
    ],
    "wof:name":"Enterprises Da Enr",
    "wof:placetype":"venue"
},
  "geometry": {"coordinates":[-72.451897,48.646919],"type":"Point"}
}