{
  "type": "Feature",
  "properties": {
    "addr:full":"Vancouver BC V7X 1M3",
    "addr:postcode":"v7x 1m3",
    "iso:country":"CA",
    "sg:city":"Vancouver",
    "sg:classifiers":[
        {
            "category":"Insurance",
            "subcategory":"Insurance Agent",
            "type":"Services"
        }
    ],
    "sg:phone":"+1 604 682 6115",
    "sg:postcode":"V7X 1M3",
    "sg:province":"BC",
    "wof:name":"Westland Insurance",
    "wof:placetype":"venue"
},
  "geometry": {"coordinates":[-123.11797332800001,49.2866172791],"type":"Point"}
}