{
  "type": "Feature",
  "properties": {
    "addr:full":"Red Deer AB T4N 6T3",
    "addr:postcode":"t4n 6t3",
    "iso:country":"CA",
    "sg:city":"Red Deer",
    "sg:classifiers":[
        {
            "category":"Building & Trades",
            "subcategory":"Plumbing",
            "type":"Services"
        }
    ],
    "sg:phone":"+1 403 346 4769",
    "sg:postcode":"T4N 6T3",
    "sg:province":"AB",
    "sg:tags":[
        "contractor"
    ],
    "wof:name":"Ken's Plumbing Svc Ltd",
    "wof:placetype":"venue"
},
  "geometry": {"coordinates":[-113.803337,52.285458],"type":"Point"}
}