{
  "type": "Feature",
  "properties": {
    "addr:full":"3222 Weston Rd North York ON M9M 2T7",
    "addr:housenumber":"3222",
    "addr:postcode":"m9m 2t7",
    "addr:street":"Weston Rd",
    "iso:country":"CA",
    "sg:address":"3222 Weston Rd",
    "sg:city":"North York",
    "sg:classifiers":[
        {
            "category":"Food & Beverages",
            "subcategory":"Groceries & Convenience Stores",
            "type":"Retail Goods"
        }
    ],
    "sg:phone":"+1 416 743 3336",
    "sg:postcode":"M9M 2T7",
    "sg:province":"ON",
    "wof:name":"Weston Gifts & Variety",
    "wof:placetype":"venue"
},
  "geometry": {"coordinates":[-79.5395889282,43.7386627197],"type":"Point"}
}