{
  "type": "Feature",
  "properties": {
    "addr:full":"New Westminster BC V3L 2B8",
    "addr:postcode":"v3l 2b8",
    "iso:country":"CA",
    "sg:city":"New Westminster",
    "sg:classifiers":[
        {
            "category":"Retail",
            "subcategory":"Laundry & Dry Cleaning",
            "type":"Services"
        }
    ],
    "sg:phone":"+1 604 526 6081",
    "sg:postcode":"V3L 2B8",
    "sg:province":"BC",
    "sg:tags":[
        "cleaners"
    ],
    "wof:name":"Royal City Cleaners",
    "wof:placetype":"venue"
},
  "geometry": {"coordinates":[-122.912254334,49.222442627],"type":"Point"}
}