{
  "type": "Feature",
  "properties": {
    "addr:full":"60 Coronet Rd Etobicoke ON M8Z 2M1",
    "addr:housenumber":"60",
    "addr:postcode":"m8z 2m1",
    "addr:street":"Coronet Rd",
    "iso:country":"CA",
    "sg:address":"60 Coronet Rd",
    "sg:city":"Etobicoke",
    "sg:classifiers":[
        {
            "category":"Manufacturing",
            "subcategory":"Metals",
            "type":"Manufacturing & Wholesale Goods"
        }
    ],
    "sg:phone":"+1 416 231 9000",
    "sg:postcode":"M8Z 2M1",
    "sg:province":"ON",
    "sg:tags":[
        "spring"
    ],
    "wof:name":"Bohne Spring Industries Ltd",
    "wof:placetype":"venue"
},
  "geometry": {"coordinates":[-79.5478439331,43.6232872009],"type":"Point"}
}