{
  "type": "Feature",
  "properties": {
    "addr:full":"1405 Rue Bishop Montreal QC H3G 2E4",
    "addr:housenumber":"1405",
    "addr:postcode":"h3g 2e4",
    "addr:street":"Rue Bishop",
    "iso:country":"CA",
    "sg:address":"1405 Rue Bishop",
    "sg:city":"Montreal",
    "sg:classifiers":[
        {
            "category":"Professional",
            "subcategory":"Research",
            "type":"Services"
        }
    ],
    "sg:phone":"+1 514 847 0085",
    "sg:postcode":"H3G 2E4",
    "sg:province":"QC",
    "sg:tags":[
        "market",
        "analysis"
    ],
    "wof:name":"Megatab Recherche Inc",
    "wof:placetype":"venue"
},
  "geometry": {"coordinates":[-73.5764007568,45.4967803955],"type":"Point"}
}