{
  "type": "Feature",
  "properties": {
    "addr:full":"10330 120 St NW # K20 Edmonton AB T5K 2A6",
    "addr:housenumber":"10330",
    "addr:postcode":"t5k 2a6",
    "addr:street":"120 St Nw # K20",
    "iso:country":"CA",
    "sg:address":"10330 120 St NW # K20",
    "sg:city":"Edmonton",
    "sg:classifiers":[
        {
            "category":"Social Services",
            "subcategory":"Adult Care",
            "type":"Services"
        }
    ],
    "sg:phone":"+1 780 488 4205",
    "sg:postcode":"T5K 2A6",
    "sg:province":"AB",
    "sg:tags":[
        "senior",
        "housing",
        "citizen"
    ],
    "wof:name":"Kiwanis Place",
    "wof:placetype":"venue"
},
  "geometry": {"coordinates":[-113.52887,53.545158],"type":"Point"}
}