{
  "type": "Feature",
  "properties": {
    "iso:country":"CA",
    "sg:city":"Chicoutimi",
    "sg:classifiers":[
        {
            "category":"Shopping",
            "subcategory":"Jewelry",
            "type":"Retail Goods"
        }
    ],
    "sg:phone":"+1 418 690 5023",
    "sg:postcode":"G7H 4B8",
    "sg:province":"QC",
    "sg:tags":[
        "jeweler"
    ],
    "wof:name":"Robin Le Bijoutier",
    "wof:placetype":"venue"
},
  "geometry": {"coordinates":[-71.057037,48.406109],"type":"Point"}
}