{
  "type": "Feature",
  "properties": {
    "addr:full":"145 John St S Hamilton ON L8N 2C3",
    "addr:housenumber":"145",
    "addr:postcode":"l8n 2c3",
    "addr:street":"John St S",
    "iso:country":"CA",
    "sg:address":"145 John St S",
    "sg:city":"Hamilton",
    "sg:classifiers":[
        {
            "category":"Insurance",
            "subcategory":"Insurance Agent",
            "type":"Services"
        }
    ],
    "sg:phone":"+1 905 529 8154",
    "sg:postcode":"L8N 2C3",
    "sg:province":"ON",
    "wof:name":"J A Mc Edwards Ins Brokers Ltd",
    "wof:placetype":"venue"
},
  "geometry": {"coordinates":[-79.86799621580001,43.2519874573],"type":"Point"}
}