{
  "type": "Feature",
  "properties": {
    "addr:full":"390 Rue Notre-Dame Saint-Tite QC G0X 3H0",
    "addr:housenumber":"390",
    "addr:postcode":"g0x 3h0",
    "addr:street":"Rue Notre-Dame",
    "iso:country":"CA",
    "sg:address":"390 Rue Notre-Dame",
    "sg:city":"Saint-Tite",
    "sg:classifiers":[
        {
            "category":"Bars & Pubs",
            "type":"Food & Drink"
        }
    ],
    "sg:phone":"+1 418 365 6866",
    "sg:postcode":"G0X 3H0",
    "sg:province":"QC",
    "sg:tags":[
        "lounge",
        "cocktail"
    ],
    "wof:name":"Bar Du Moulin DE St-Tite Inc",
    "wof:placetype":"venue"
},
  "geometry": {"coordinates":[-72.566185,46.729069],"type":"Point"}
}