{
  "type": "Feature",
  "properties": {
    "addr:full":"Saint-Cesaire QC J0L 1T0",
    "addr:postcode":"j0l 1t0",
    "iso:country":"CA",
    "sg:city":"Saint-Cesaire",
    "sg:classifiers":[
        {
            "category":"Health Services",
            "subcategory":"Health Practitioner",
            "type":"Services"
        }
    ],
    "sg:phone":"+1 450 469 5725",
    "sg:postcode":"J0L 1T0",
    "sg:province":"QC",
    "sg:tags":[
        "physiotherapist",
        "therapist",
        "physical"
    ],
    "wof:name":"Physiotherapie Danielle Baril",
    "wof:placetype":"venue"
},
  "geometry": {"coordinates":[-73.0078048706,45.414150238],"type":"Point"}
}