{
  "type": "Feature",
  "properties": {
    "addr:full":"2457 Coho Rd Campbell River BC V9W 4W3",
    "addr:housenumber":"2457",
    "addr:postcode":"v9w 4w3",
    "addr:street":"Coho Rd",
    "iso:country":"CA",
    "sg:address":"2457 Coho Rd",
    "sg:city":"Campbell River",
    "sg:classifiers":[
        {
            "category":"Manufacturing",
            "subcategory":"Lumber",
            "type":"Manufacturing & Wholesale Goods"
        }
    ],
    "sg:phone":"+1 250 286 1796",
    "sg:postcode":"V9W 4W3",
    "sg:province":"BC",
    "sg:tags":[
        "company",
        "logging"
    ],
    "wof:name":"Stuno Enterprises",
    "wof:placetype":"venue"
},
  "geometry": {"coordinates":[-125.28239440900001,50.0401229858],"type":"Point"}
}