{
  "type": "Feature",
  "properties": {
    "addr:full":"1 Coventry Rd Brampton ON L6T 4B1",
    "addr:housenumber":"1",
    "addr:postcode":"l6t 4b1",
    "addr:street":"Coventry Rd",
    "iso:country":"CA",
    "sg:address":"1 Coventry Rd",
    "sg:city":"Brampton",
    "sg:classifiers":[
        {
            "category":"Wholesale",
            "subcategory":"Machinery & Supplies",
            "type":"Manufacturing & Wholesale Goods"
        }
    ],
    "sg:phone":"+1 905 791 9811",
    "sg:postcode":"L6T 4B1",
    "sg:province":"ON",
    "sg:tags":[
        "die",
        "tool",
        "maker"
    ],
    "wof:name":"Tipco Inc",
    "wof:placetype":"venue"
},
  "geometry": {"coordinates":[-79.69515228269999,43.7387237549],"type":"Point"}
}