{
  "type": "Feature",
  "properties": {
    "addr:full":"3296 Lake Shore Blvd W Etobicoke ON M8V 1M4",
    "addr:housenumber":"3296",
    "addr:postcode":"m8v 1m4",
    "addr:street":"Lake Shore Blvd W",
    "iso:country":"CA",
    "sg:address":"3296 Lake Shore Blvd W",
    "sg:city":"Etobicoke",
    "sg:classifiers":[
        {
            "category":"Personal",
            "subcategory":"Beauty Salon",
            "type":"Services"
        }
    ],
    "sg:phone":"+1 416 259 1659",
    "sg:postcode":"M8V 1M4",
    "sg:province":"ON",
    "wof:name":"New Elegance",
    "wof:placetype":"venue"
},
  "geometry": {"coordinates":[-79.523781,43.596752],"type":"Point"}
}