{
  "type": "Feature",
  "properties": {
    "addr:full":"829 Murray St Wallaceburg ON N8A 1W5",
    "addr:housenumber":"829",
    "addr:postcode":"n8a 1w5",
    "addr:street":"Murray St",
    "iso:country":"CA",
    "sg:address":"829 Murray St",
    "sg:city":"Wallaceburg",
    "sg:classifiers":[
        {
            "category":"Home & Garden",
            "subcategory":"Building Materials",
            "type":"Retail Goods"
        }
    ],
    "sg:phone":"+1 519 628 5753",
    "sg:postcode":"N8A 1W5",
    "sg:province":"ON",
    "sg:tags":[
        "glass",
        "window",
        "plate"
    ],
    "wof:name":"Gus's Glass",
    "wof:placetype":"venue"
},
  "geometry": {"coordinates":[-82.380318,42.577297],"type":"Point"}
}