{
  "type": "Feature",
  "properties": {
    "addr:full":"4420 Rue Jean-Talon E Saint-Leonard QC H1S 1J7",
    "addr:housenumber":"4420",
    "addr:postcode":"h1s 1j7",
    "addr:street":"Rue Jean-Talon E",
    "iso:country":"CA",
    "sg:address":"4420 Rue Jean-Talon E",
    "sg:city":"Saint-Leonard",
    "sg:classifiers":[
        {
            "category":"Shopping",
            "subcategory":"Pharmacy",
            "type":"Retail Goods"
        }
    ],
    "sg:phone":"+1 514 723 1000",
    "sg:postcode":"H1S 1J7",
    "sg:province":"QC",
    "wof:name":"Pharmaprix",
    "wof:placetype":"venue"
},
  "geometry": {"coordinates":[-73.58912658689999,45.5688438416],"type":"Point"}
}