{
  "type": "Feature",
  "properties": {
    "addr:full":"286 Venture Cres Saskatoon SK S7K 6M1",
    "addr:housenumber":"286",
    "addr:postcode":"s7k 6m1",
    "addr:street":"Venture Cres",
    "iso:country":"CA",
    "sg:address":"286 Venture Cres",
    "sg:city":"Saskatoon",
    "sg:classifiers":[
        {
            "category":"Home & Garden",
            "subcategory":"Building Materials",
            "type":"Retail Goods"
        }
    ],
    "sg:phone":"+1 306 933 1903",
    "sg:postcode":"S7K 6M1",
    "sg:province":"SK",
    "sg:tags":[
        "lumber"
    ],
    "wof:name":"Rona Revelstoke Home Ctr Ltd",
    "wof:placetype":"venue"
},
  "geometry": {"coordinates":[-106.64952099999999,52.157543],"type":"Point"}
}