{
  "type": "Feature",
  "properties": {
    "addr:full":"3 Crabtree Ave London ON N6G 2H6",
    "addr:housenumber":"3",
    "addr:postcode":"n6g 2h6",
    "addr:street":"Crabtree Ave",
    "iso:country":"CA",
    "sg:address":"3 Crabtree Ave",
    "sg:city":"London",
    "sg:classifiers":[
        {
            "category":"Professional",
            "subcategory":"Art Services",
            "type":"Services"
        }
    ],
    "sg:phone":"+1 519 473 4810",
    "sg:postcode":"N6G 2H6",
    "sg:province":"ON",
    "sg:tags":[
        "graphic",
        "designer"
    ],
    "wof:name":"Vortex Visual Concepts",
    "wof:placetype":"venue"
},
  "geometry": {"coordinates":[-81.30742600000001,43.010368],"type":"Point"}
}