{
  "type": "Feature",
  "properties": {
    "iso:country":"CA",
    "sg:address":"3 Crabtree Ave",
    "sg:city":"London",
    "sg:classifiers":[
        {
            "category":"Professional",
            "subcategory":"Art Services",
            "type":"Services"
        }
    ],
    "sg:phone":"+1 519 473 4810",
    "sg:postcode":"N6G 2H6",
    "sg:province":"ON",
    "sg:tags":[
        "graphic",
        "designer"
    ],
    "wof:name":"Vortex Visual Concepts",
    "wof:placetype":"venue"
},
  "geometry": {"coordinates":[-81.307426,43.010368],"type":"Point"}
}