{
  "type": "Feature",
  "properties": {
    "iso:country":"CA",
    "sg:address":"201 Rue Beaubien E",
    "sg:city":"Montreal",
    "sg:classifiers":[
        {
            "category":"Food & Beverages",
            "subcategory":"Bakery",
            "type":"Retail Goods"
        }
    ],
    "sg:phone":"+1 514 273 8540",
    "sg:postcode":"H2S 1R5",
    "sg:province":"QC",
    "sg:tags":[
        "baker"
    ],
    "wof:name":"Samos Boulangerie Depanneur",
    "wof:placetype":"venue"
},
  "geometry": {"coordinates":[-73.606918,45.532009],"type":"Point"}
}