{
  "type": "Feature",
  "properties": {
    "addr:full":"Mascouche QC J7L 2J6",
    "addr:postcode":"j7l 2j6",
    "iso:country":"CA",
    "sg:city":"Mascouche",
    "sg:classifiers":[
        {
            "category":"Real Estate",
            "subcategory":"Real Estate Agent",
            "type":"Services"
        }
    ],
    "sg:phone":"+1 450 477 9333",
    "sg:postcode":"J7L 2J6",
    "sg:province":"QC",
    "wof:name":"Au Carrefour Inc",
    "wof:placetype":"venue"
},
  "geometry": {"coordinates":[-73.654831,45.729542],"type":"Point"}
}