{
  "type": "Feature",
  "properties": {
    "iso:country":"CA",
    "sg:city":"Grand Bay-Westfield",
    "sg:classifiers":[
        {
            "category":"Health Services",
            "subcategory":"Doctor",
            "type":"Services"
        }
    ],
    "sg:phone":"+1 506 738 8462",
    "sg:postcode":"E5K 4V3",
    "sg:province":"NB",
    "sg:tags":[
        "physician",
        "surgeon"
    ],
    "wof:name":"Webb, G Robert MD",
    "wof:placetype":"venue"
},
  "geometry": {"coordinates":[-66.1951751709,45.3033370972],"type":"Point"}
}