{
  "type": "Feature",
  "properties": {
    "iso:country":"CA",
    "sg:address":"356 Main St # A",
    "sg:city":"Shediac",
    "sg:classifiers":[
        {
            "category":"Shopping",
            "subcategory":"Florist",
            "type":"Retail Goods"
        }
    ],
    "sg:phone":"+1 506 532 1084",
    "sg:postcode":"E4P 2E8",
    "sg:province":"NB",
    "wof:name":"Fleurs Lighthouse Lane Flowers",
    "wof:placetype":"venue"
},
  "geometry": {"coordinates":[-64.54262542719999,46.2195358276],"type":"Point"}
}