{
  "type": "Feature",
  "properties": {
    "addr:full":"1575 Rue Dudemaine Montreal QC H3M 1R2",
    "addr:housenumber":"1575",
    "addr:postcode":"h3m 1r2",
    "addr:street":"Rue Dudemaine",
    "iso:country":"CA",
    "sg:address":"1575 Rue Dudemaine",
    "sg:city":"Montreal",
    "sg:classifiers":[
        {
            "category":"Restaurant",
            "type":"Food & Drink"
        }
    ],
    "sg:phone":"+1 514 334 3876",
    "sg:postcode":"H3M 1R2",
    "sg:province":"QC",
    "wof:name":"Restaurant Dima",
    "wof:placetype":"venue"
},
  "geometry": {"coordinates":[-73.687515,45.540146],"type":"Point"}
}