{
  "type": "Feature",
  "properties": {
    "addr:full":"8 Colborne St Fenelon Falls ON K0M 1N0",
    "addr:housenumber":"8",
    "addr:postcode":"k0m 1n0",
    "addr:street":"Colborne St",
    "iso:country":"CA",
    "sg:address":"8 Colborne St",
    "sg:city":"Fenelon Falls",
    "sg:classifiers":[
        {
            "category":"Shopping",
            "subcategory":"Jewelry",
            "type":"Retail Goods"
        }
    ],
    "sg:phone":"+1 705 887 2930",
    "sg:postcode":"K0M 1N0",
    "sg:province":"ON",
    "sg:tags":[
        "jeweler"
    ],
    "wof:name":"Stokes on Trent",
    "wof:placetype":"venue"
},
  "geometry": {"coordinates":[-78.736626,44.536236],"type":"Point"}
}