{
  "type": "Feature",
  "properties": {
    "iso:country":"CA",
    "sg:address":"180 Morden Rd",
    "sg:city":"Oakville",
    "sg:classifiers":[
        {
            "category":"Education",
            "subcategory":"School",
            "type":"Public Place"
        }
    ],
    "sg:phone":"+1 905 844 9612",
    "sg:postcode":"L6K 2S3",
    "sg:province":"ON",
    "wof:name":"W H Morden Elementary School",
    "wof:placetype":"venue"
},
  "geometry": {"coordinates":[-79.685486,43.434093],"type":"Point"}
}