{
  "type": "Feature",
  "properties": {
    "addr:full":"1211 1st Ave W Prince Albert SK S6V 4Y8",
    "addr:housenumber":"1211",
    "addr:postcode":"s6v 4y8",
    "addr:street":"1St Ave W",
    "iso:country":"CA",
    "sg:address":"1211 1st Ave W",
    "sg:city":"Prince Albert",
    "sg:classifiers":[
        {
            "category":"Recreation",
            "type":"Entertainment"
        }
    ],
    "sg:phone":"+1 306 764 0806",
    "sg:postcode":"S6V 4Y8",
    "sg:province":"SK",
    "sg:tags":[
        "club",
        "sport"
    ],
    "wof:name":"Rhythmic Gymnastics Club",
    "wof:placetype":"venue"
},
  "geometry": {"coordinates":[-105.75739288299999,53.2020111084],"type":"Point"}
}