{
  "type": "Feature",
  "properties": {
    "iso:country":"CA",
    "sg:address":"806 Boul Cure-Labelle",
    "sg:city":"Laval",
    "sg:classifiers":[
        {
            "category":"Restaurant",
            "type":"Food & Drink"
        }
    ],
    "sg:phone":"+1 450 681 9551",
    "sg:postcode":"H7V 2V3",
    "sg:province":"QC",
    "sg:tags":[
        "delicatessen"
    ],
    "wof:name":"Charcuterie Transilvania",
    "wof:placetype":"venue"
},
  "geometry": {"coordinates":[-73.7475280762,45.539806366],"type":"Point"}
}