{
  "type": "Feature",
  "properties": {
    "addr:full":"Racine QC J0E 1Y0",
    "addr:postcode":"j0e 1y0",
    "iso:country":"CA",
    "sg:city":"Racine",
    "sg:classifiers":[
        {
            "category":"Travel",
            "subcategory":"Hotels & Motels",
            "type":"Entertainment"
        }
    ],
    "sg:phone":"+1 450 532 3177",
    "sg:postcode":"J0E 1Y0",
    "sg:province":"QC",
    "sg:tags":[
        "inn"
    ],
    "wof:name":"Auberge DE LA Grande Ligne",
    "wof:placetype":"venue"
},
  "geometry": {"coordinates":[-72.2374572754,45.4816513062],"type":"Point"}
}