{
  "type": "Feature",
  "properties": {
    "addr:full":"300 Laplanche St Amherst NS B4H 4A1",
    "addr:housenumber":"300",
    "addr:postcode":"b4h 4a1",
    "addr:street":"Laplanche St",
    "iso:country":"CA",
    "sg:address":"300 Laplanche St",
    "sg:city":"Amherst",
    "sg:classifiers":[
        {
            "category":"Shopping",
            "subcategory":"Used Merchandise",
            "type":"Retail Goods"
        }
    ],
    "sg:phone":"+1 902 667 5556",
    "sg:postcode":"B4H 4A1",
    "sg:province":"NS",
    "sg:tags":[
        "clothing"
    ],
    "wof:name":"Frenchy's Guy's",
    "wof:placetype":"venue"
},
  "geometry": {"coordinates":[-64.217659,45.835999],"type":"Point"}
}