{
  "type": "Feature",
  "properties": {
    "addr:full":"11374 Nassagaweya-Esquesing Acton ON L7J 2L7",
    "addr:housenumber":"11374",
    "addr:postcode":"l7j 2l7",
    "addr:street":"Nassagaweya-Esquesing Acton",
    "iso:country":"CA",
    "sg:address":"11374 Nassagaweya-Esquesing",
    "sg:city":"Acton",
    "sg:classifiers":[
        {
            "category":"Building & Trades",
            "subcategory":"Landscaping Services",
            "type":"Services"
        }
    ],
    "sg:phone":"+1 519 853 1248",
    "sg:postcode":"L7J 2L7",
    "sg:province":"ON",
    "sg:tags":[
        "landscape",
        "contractor"
    ],
    "wof:name":"White Oak Landscaping Ltd",
    "wof:placetype":"venue"
},
  "geometry": {"coordinates":[-80.047127,43.60199],"type":"Point"}
}