{
  "type": "Feature",
  "properties": {
    "addr:full":"Louiseville QC J5V 1A6",
    "addr:postcode":"j5v 1a6",
    "iso:country":"CA",
    "sg:city":"Louiseville",
    "sg:classifiers":[
        {
            "category":"Building & Trades",
            "subcategory":"Plumbing",
            "type":"Services"
        }
    ],
    "sg:phone":"+1 819 228 8004",
    "sg:postcode":"J5V 1A6",
    "sg:province":"QC",
    "sg:tags":[
        "septic"
    ],
    "wof:name":"Pompage Mauricie Inc",
    "wof:placetype":"venue"
},
  "geometry": {"coordinates":[-72.940361,46.261654],"type":"Point"}
}