{
  "type": "Feature",
  "properties": {
    "addr:full":"1035 Centre St SE High River AB T1V 1Y1",
    "addr:housenumber":"1035",
    "addr:postcode":"t1v 1y1",
    "addr:street":"Centre St Se",
    "iso:country":"CA",
    "sg:address":"1035 Centre St SE",
    "sg:city":"High River",
    "sg:classifiers":[
        {
            "category":"Shopping",
            "subcategory":"Bicycles & Sporting Goods",
            "type":"Retail Goods"
        }
    ],
    "sg:phone":"+1 403 652 2614",
    "sg:postcode":"T1V 1Y1",
    "sg:province":"AB",
    "sg:tags":[
        "saddlery",
        "harness"
    ],
    "wof:name":"Eamor's Saddlery Ltd",
    "wof:placetype":"venue"
},
  "geometry": {"coordinates":[-113.872276306,50.573551178],"type":"Point"}
}