{
  "type": "Feature",
  "properties": {
    "addr:full":"Shelburne NS B0T 1W0",
    "addr:postcode":"b0t 1w0",
    "iso:country":"CA",
    "sg:city":"Shelburne",
    "sg:classifiers":[
        {
            "category":"Health Services",
            "subcategory":"Clinic",
            "type":"Services"
        }
    ],
    "sg:phone":"+1 902 875 2623",
    "sg:postcode":"B0T 1W0",
    "sg:province":"NS",
    "wof:name":"Nova Scotia Public Health Nrs",
    "wof:placetype":"venue"
},
  "geometry": {"coordinates":[-65.31564299999999,43.765659],"type":"Point"}
}