{
  "type": "Feature",
  "properties": {
    "addr:full":"6355 Richmond Ave E Brandon MB R7A 7M5",
    "addr:housenumber":"6355",
    "addr:postcode":"r7a 7m5",
    "addr:street":"Richmond Ave E",
    "iso:country":"CA",
    "sg:address":"6355 Richmond Ave E",
    "sg:city":"Brandon",
    "sg:classifiers":[
        {
            "category":"Wholesale",
            "subcategory":"Meat",
            "type":"Manufacturing & Wholesale Goods"
        }
    ],
    "sg:phone":"+1 204 571 2500",
    "sg:postcode":"R7A 7M5",
    "sg:province":"MB",
    "sg:tags":[
        "product"
    ],
    "wof:name":"Maple Leaf Pork",
    "wof:placetype":"venue"
},
  "geometry": {"coordinates":[-99.858994,49.827908],"type":"Point"}
}