{
  "type": "Feature",
  "properties": {
    "addr:full":"91 Ch Giard Canton-DE-Granby QC J2G 9H8",
    "addr:housenumber":"91",
    "addr:postcode":"j2g 9h8",
    "addr:street":"Ch Giard Canton-De-Granby",
    "iso:country":"CA",
    "sg:address":"91 Ch Giard",
    "sg:city":"Canton-DE-Granby",
    "sg:classifiers":[
        {
            "category":"Farming",
            "subcategory":"Farm",
            "type":"Manufacturing & Wholesale Goods"
        }
    ],
    "sg:phone":"+1 450 777 1300",
    "sg:postcode":"J2G 9H8",
    "sg:province":"QC",
    "wof:name":"Ferme Alain Lallier",
    "wof:placetype":"venue"
},
  "geometry": {"coordinates":[-72.7217712402,45.3979949951],"type":"Point"}
}