{
  "type": "Feature",
  "properties": {
    "addr:full":"25 Webster St Kentville NS B4N 1H4",
    "addr:housenumber":"25",
    "addr:postcode":"b4n 1h4",
    "addr:street":"Webster St",
    "iso:country":"CA",
    "sg:address":"25 Webster St",
    "sg:city":"Kentville",
    "sg:classifiers":[
        {
            "category":"Shopping",
            "subcategory":"Stationery & Office Supplies",
            "type":"Retail Goods"
        }
    ],
    "sg:phone":"+1 902 678 4661",
    "sg:postcode":"B4N 1H4",
    "sg:province":"NS",
    "wof:name":"R D Chisholm Stationery-Books",
    "wof:placetype":"venue"
},
  "geometry": {"coordinates":[-64.495071,45.078274],"type":"Point"}
}