{
  "type": "Feature",
  "properties": {
    "addr:full":"210 Centre Ave Coutts AB T0K 0N0",
    "addr:housenumber":"210",
    "addr:postcode":"t0k 0n0",
    "addr:street":"Centre Ave",
    "iso:country":"CA",
    "sg:address":"210 Centre Ave",
    "sg:city":"Coutts",
    "sg:classifiers":[
        {
            "category":"Organizations",
            "subcategory":"Religious Organization",
            "type":"Services"
        }
    ],
    "sg:phone":"+1 403 344 3938",
    "sg:postcode":"T0K 0N0",
    "sg:province":"AB",
    "sg:tags":[
        "church"
    ],
    "wof:name":"Church of Jesus Christ of Lds",
    "wof:placetype":"venue"
},
  "geometry": {"coordinates":[-111.963485718,49.0012207031],"type":"Point"}
}