{
  "type": "Feature",
  "properties": {
    "addr:full":"310 Ross Ave # 200 Winnipeg MB R3A 0L4",
    "addr:housenumber":"310",
    "addr:postcode":"r3a 0l4",
    "addr:street":"Ross Ave # 200",
    "iso:country":"CA",
    "sg:address":"310 Ross Ave # 200",
    "sg:city":"Winnipeg",
    "sg:classifiers":[
        {
            "category":"Manufacturing",
            "subcategory":"Apparel",
            "type":"Manufacturing & Wholesale Goods"
        }
    ],
    "sg:phone":"+1 204 943 4725",
    "sg:postcode":"R3A 0L4",
    "sg:province":"MB",
    "sg:tags":[
        "clothing"
    ],
    "wof:name":"Central Sportswear Mfg CO",
    "wof:placetype":"venue"
},
  "geometry": {"coordinates":[-97.141167,49.901451],"type":"Point"}
}