{
  "type": "Feature",
  "properties": {
    "iso:country":"CA",
    "sg:address":"48 Rexdale Blvd",
    "sg:city":"Etobicoke",
    "sg:classifiers":[
        {
            "category":"Insurance",
            "subcategory":"Insurance Agent",
            "type":"Services"
        }
    ],
    "sg:phone":"+1 416 748 8808",
    "sg:postcode":"M9W 5Z3",
    "sg:province":"ON",
    "wof:name":"Ace Insurance Ltd",
    "wof:placetype":"venue"
},
  "geometry": {"coordinates":[-79.55926513670001,43.7136688232],"type":"Point"}
}