{
  "type": "Feature",
  "properties": {
    "addr:full":"Mount Pearl NL A1N 3J6",
    "addr:postcode":"a1n 3j6",
    "iso:country":"CA",
    "sg:city":"Mount Pearl",
    "sg:classifiers":[
        {
            "category":"Professional",
            "subcategory":"Credit Reporting & Collection",
            "type":"Services"
        }
    ],
    "sg:phone":"+1 709 368 8300",
    "sg:postcode":"A1N 3J6",
    "sg:province":"NL",
    "sg:tags":[
        "agency"
    ],
    "wof:name":"Credit Control Svc",
    "wof:placetype":"venue"
},
  "geometry": {"coordinates":[-52.791447,47.524052],"type":"Point"}
}