{
  "type": "Feature",
  "properties": {
    "addr:full":"5030 50 St Sylvan Lake AB T4S 1P3",
    "addr:housenumber":"5030",
    "addr:postcode":"t4s 1p3",
    "addr:street":"50 St",
    "iso:country":"CA",
    "sg:address":"5030 50 St",
    "sg:city":"Sylvan Lake",
    "sg:classifiers":[
        {
            "category":"Organizations",
            "subcategory":"Religious Organization",
            "type":"Services"
        }
    ],
    "sg:phone":"+1 403 887 3313",
    "sg:postcode":"T4S 1P3",
    "sg:province":"AB",
    "sg:tags":[
        "church"
    ],
    "wof:name":"Frontline Worship Ctr",
    "wof:placetype":"venue"
},
  "geometry": {"coordinates":[-114.09750366199999,52.3089904785],"type":"Point"}
}