{
  "type": "Feature",
  "properties": {
    "addr:full":"3350 Dufferin St North York ON M6A 3A4",
    "addr:housenumber":"3350",
    "addr:postcode":"m6a 3a4",
    "addr:street":"Dufferin St",
    "iso:country":"CA",
    "sg:address":"3350 Dufferin St",
    "sg:city":"North York",
    "sg:classifiers":[
        {
            "category":"Shopping",
            "type":"Retail Goods"
        }
    ],
    "sg:phone":"+1 416 787 4581",
    "sg:postcode":"M6A 3A4",
    "sg:province":"ON",
    "sg:tags":[
        "binoculars",
        "telescope"
    ],
    "wof:name":"Efstonscience Inc",
    "wof:placetype":"venue"
},
  "geometry": {"coordinates":[-79.45713000000001,43.724072],"type":"Point"}
}