{
  "type": "Feature",
  "properties": {
    "addr:full":"210 West Rd Leroy SK S0K 2P0",
    "addr:housenumber":"210",
    "addr:postcode":"s0k 2p0",
    "addr:street":"West Rd",
    "iso:country":"CA",
    "sg:address":"210 West Rd",
    "sg:city":"Leroy",
    "sg:classifiers":[
        {
            "category":"Shopping",
            "subcategory":"Computers & Home Electronics",
            "type":"Retail Goods"
        }
    ],
    "sg:phone":"+1 306 286 3242",
    "sg:postcode":"S0K 2P0",
    "sg:province":"SK",
    "sg:tags":[
        "television",
        "radio"
    ],
    "wof:name":"Cross Country Television",
    "wof:placetype":"venue"
},
  "geometry": {"coordinates":[-104.744072,52.003365],"type":"Point"}
}