{
  "type": "Feature",
  "properties": {
    "addr:full":"Mississauga ON L5C 1T8",
    "addr:postcode":"l5c 1t8",
    "iso:country":"CA",
    "sg:city":"Mississauga",
    "sg:classifiers":[
        {
            "category":"Retail",
            "subcategory":"Auto Repair",
            "type":"Services"
        }
    ],
    "sg:phone":"+1 905 897 0526",
    "sg:postcode":"L5C 1T8",
    "sg:province":"ON",
    "sg:tags":[
        "repairing",
        "automobile"
    ],
    "wof:name":"Nihan Automotive",
    "wof:placetype":"venue"
},
  "geometry": {"coordinates":[-79.643173,43.57299],"type":"Point"}
}