{
  "type": "Feature",
  "properties": {
    "iso:country":"CA",
    "sg:address":"185 Broadway St",
    "sg:city":"Tillsonburg",
    "sg:classifiers":[
        {
            "category":"Shopping",
            "subcategory":"Shoes",
            "type":"Retail Goods"
        }
    ],
    "sg:phone":"+1 519 842 8666",
    "sg:postcode":"N4G 3P9",
    "sg:province":"ON",
    "wof:name":"Mugford Shoes",
    "wof:placetype":"venue"
},
  "geometry": {"coordinates":[-80.72914123539999,42.8616600037],"type":"Point"}
}