{
  "type": "Feature",
  "properties": {
    "addr:full":"Edmonton AB T5S 2E3",
    "addr:postcode":"t5s 2e3",
    "iso:country":"CA",
    "sg:city":"Edmonton",
    "sg:classifiers":[
        {
            "category":"Insurance",
            "subcategory":"Insurance Agent",
            "type":"Services"
        }
    ],
    "sg:phone":"+1 780 486 4488",
    "sg:postcode":"T5S 2E3",
    "sg:province":"AB",
    "wof:name":"Trans West Insurance Brokers",
    "wof:placetype":"venue"
},
  "geometry": {"coordinates":[-113.627594,53.550735],"type":"Point"}
}