{
  "type": "Feature",
  "properties": {
    "addr:full":"North York ON M3J 2V8",
    "addr:postcode":"m3j 2v8",
    "iso:country":"CA",
    "sg:city":"North York",
    "sg:classifiers":[
        {
            "category":"Manufacturing",
            "subcategory":"Printing",
            "type":"Manufacturing & Wholesale Goods"
        }
    ],
    "sg:phone":"+1 416 663 6916",
    "sg:postcode":"M3J 2V8",
    "sg:province":"ON",
    "sg:tags":[
        "printer"
    ],
    "wof:name":"Digital Data Corp",
    "wof:placetype":"venue"
},
  "geometry": {"coordinates":[-79.4816894531,43.7654037476],"type":"Point"}
}