{
  "type": "Feature",
  "properties": {
    "addr:full":"Orangeville ON L9W 2E1",
    "addr:postcode":"l9w 2e1",
    "iso:country":"CA",
    "sg:city":"Orangeville",
    "sg:classifiers":[
        {
            "category":"Health Services",
            "subcategory":"Doctor",
            "type":"Services"
        }
    ],
    "sg:phone":"+1 519 938 9500",
    "sg:postcode":"L9W 2E1",
    "sg:province":"ON",
    "sg:tags":[
        "dentist"
    ],
    "wof:name":"Abouzgia, M DDS",
    "wof:placetype":"venue"
},
  "geometry": {"coordinates":[-80.09839599999999,43.922382],"type":"Point"}
}