{
  "type": "Feature",
  "properties": {
    "addr:full":"Prince George BC V2L 2K9",
    "addr:postcode":"v2l 2k9",
    "iso:country":"CA",
    "sg:city":"Prince George",
    "sg:classifiers":[
        {
            "category":"Health Services",
            "subcategory":"Doctor",
            "type":"Services"
        }
    ],
    "sg:phone":"+1 250 563 4939",
    "sg:postcode":"V2L 2K9",
    "sg:province":"BC",
    "sg:tags":[
        "dentist"
    ],
    "wof:name":"Legault, Lonny DDS",
    "wof:placetype":"venue"
},
  "geometry": {"coordinates":[-122.753281,53.913139],"type":"Point"}
}