{
  "type": "Feature",
  "properties": {
    "iso:country":"CA",
    "sg:address":"14 Frederick St",
    "sg:city":"Barrie",
    "sg:classifiers":[
        {
            "category":"Building & Trades",
            "subcategory":"Cleaning & Sanitation",
            "type":"Services"
        }
    ],
    "sg:phone":"+1 705 725 9013",
    "sg:postcode":"L4N 2L5",
    "sg:province":"ON",
    "sg:tags":[
        "window"
    ],
    "wof:name":"Bayview Window Cleaning",
    "wof:placetype":"venue"
},
  "geometry": {"coordinates":[-79.69767,44.378654],"type":"Point"}
}