{
  "type": "Feature",
  "properties": {
    "iso:country":"CA",
    "sg:address":"175 Rue Merizzi",
    "sg:city":"Saint-Laurent",
    "sg:classifiers":[
        {
            "category":"Wholesale",
            "subcategory":"Plants",
            "type":"Manufacturing & Wholesale Goods"
        }
    ],
    "sg:phone":"+1 514 739 4567",
    "sg:postcode":"H4T 1Y3",
    "sg:province":"QC",
    "sg:tags":[
        "florist"
    ],
    "wof:name":"Cambrian Distribution Florale",
    "wof:placetype":"venue"
},
  "geometry": {"coordinates":[-73.695816,45.479565],"type":"Point"}
}