{
  "type": "Feature",
  "properties": {
    "addr:full":"175 Rue Merizzi Saint-Laurent QC H4T 1Y3",
    "addr:housenumber":"175",
    "addr:postcode":"h4t 1y3",
    "addr:street":"Rue Merizzi",
    "iso:country":"CA",
    "sg:address":"175 Rue Merizzi",
    "sg:city":"Saint-Laurent",
    "sg:classifiers":[
        {
            "category":"Wholesale",
            "subcategory":"Plants",
            "type":"Manufacturing & Wholesale Goods"
        }
    ],
    "sg:phone":"+1 514 739 4567",
    "sg:postcode":"H4T 1Y3",
    "sg:province":"QC",
    "sg:tags":[
        "florist"
    ],
    "wof:name":"Cambrian Distribution Florale",
    "wof:placetype":"venue"
},
  "geometry": {"coordinates":[-73.69581599999999,45.479565],"type":"Point"}
}