{
  "type": "Feature",
  "properties": {
    "iso:country":"CA",
    "sg:city":"Ottawa",
    "sg:classifiers":[
        {
            "category":"Professional",
            "subcategory":"Computer Services",
            "type":"Services"
        }
    ],
    "sg:phone":"+1 613 747 2148",
    "sg:postcode":"K1B 3V7",
    "sg:province":"ON",
    "sg:tags":[
        "equipment",
        "supply",
        "electronic",
        "repair"
    ],
    "wof:name":"Adept Technical Svc",
    "wof:placetype":"venue"
},
  "geometry": {"coordinates":[-75.6075668335,45.4061317444],"type":"Point"}
}