{
  "type": "Feature",
  "properties": {
    "addr:full":"2114 Boul Des Laurentides Vimont QC H7M 2R5",
    "addr:housenumber":"2114",
    "addr:postcode":"h7m 2r5",
    "addr:street":"Boul Des Laurentides",
    "iso:country":"CA",
    "sg:address":"2114 Boul Des Laurentides",
    "sg:city":"Vimont",
    "sg:classifiers":[
        {
            "category":"Food & Beverages",
            "subcategory":"Liquor & Beverages",
            "type":"Retail Goods"
        }
    ],
    "sg:phone":"+1 450 669 1911",
    "sg:postcode":"H7M 2R5",
    "sg:province":"QC",
    "sg:tags":[
        "store"
    ],
    "wof:name":"Saq",
    "wof:placetype":"venue"
},
  "geometry": {"coordinates":[-73.7343826294,45.6083488464],"type":"Point"}
}