{
  "type": "Feature",
  "properties": {
    "iso:country":"CA",
    "sg:address":"6 Central St",
    "sg:city":"Yarmouth",
    "sg:classifiers":[
        {
            "category":"Wholesale",
            "subcategory":"Vending Machines",
            "type":"Manufacturing & Wholesale Goods"
        }
    ],
    "sg:phone":"+1 902 742 5242",
    "sg:postcode":"B5A 3H1",
    "sg:province":"NS",
    "wof:name":"Acadian Vending",
    "wof:placetype":"venue"
},
  "geometry": {"coordinates":[-66.1206665039,43.8359451294],"type":"Point"}
}