{
  "type": "Feature",
  "properties": {
    "iso:country":"CA",
    "sg:address":"50 Reeves St",
    "sg:city":"Sydney",
    "sg:classifiers":[
        {
            "category":"Restaurant",
            "type":"Food & Drink"
        }
    ],
    "sg:phone":"+1 902 539 9884",
    "sg:postcode":"B1P 3C5",
    "sg:province":"NS",
    "sg:tags":[
        "lounge",
        "cocktail"
    ],
    "wof:name":"Flora's Grill",
    "wof:placetype":"venue"
},
  "geometry": {"coordinates":[-60.1603622437,46.1437034607],"type":"Point"}
}