{
  "type": "Feature",
  "properties": {
    "addr:full":"Haliburton ON K0M 1S0",
    "addr:postcode":"k0m 1s0",
    "iso:country":"CA",
    "sg:city":"Haliburton",
    "sg:classifiers":[
        {
            "category":"Education",
            "subcategory":"School",
            "type":"Public Place"
        }
    ],
    "sg:phone":"+1 705 457 2950",
    "sg:postcode":"K0M 1S0",
    "sg:province":"ON",
    "wof:name":"Haliburton Highlands Secondary",
    "wof:placetype":"venue"
},
  "geometry": {"coordinates":[-78.5088043213,45.0466995239],"type":"Point"}
}