{
  "type": "Feature",
  "properties": {
    "addr:full":"Verdun QC H4G 3E7",
    "addr:postcode":"h4g 3e7",
    "iso:country":"CA",
    "sg:city":"Verdun",
    "sg:classifiers":[
        {
            "category":"Health Services",
            "subcategory":"Doctor",
            "type":"Services"
        }
    ],
    "sg:phone":"+1 514 768 1652",
    "sg:postcode":"H4G 3E7",
    "sg:province":"QC",
    "sg:tags":[
        "clinic"
    ],
    "wof:name":"Clinique Medico Chirurgicale",
    "wof:placetype":"venue"
},
  "geometry": {"coordinates":[-73.563828,45.456539],"type":"Point"}
}