{
  "type": "Feature",
  "properties": {
    "addr:full":"Watrous SK S0K 4T0",
    "addr:postcode":"s0k 4t0",
    "addr:street":"Watrous",
    "iso:country":"CA",
    "sg:city":"Watrous",
    "sg:classifiers":[
        {
            "category":"Shopping",
            "subcategory":"Department Store",
            "type":"Retail Goods"
        }
    ],
    "sg:phone":"+1 306 946 3666",
    "sg:postcode":"S0K 4T0",
    "sg:province":"SK",
    "wof:name":"Bargain Shop",
    "wof:placetype":"venue"
},
  "geometry": {"coordinates":[-105.46781900000001,51.672966],"type":"Point"}
}