{
  "type": "Feature",
  "properties": {
    "addr:full":"Quebec QC G1N 2E7",
    "addr:postcode":"g1n 2e7",
    "iso:country":"CA",
    "sg:city":"Quebec",
    "sg:classifiers":[
        {
            "category":"Professional",
            "subcategory":"Computer Services",
            "type":"Services"
        }
    ],
    "sg:phone":"+1 418 686 0437",
    "sg:postcode":"G1N 2E7",
    "sg:province":"QC",
    "sg:tags":[
        "repair"
    ],
    "wof:name":"Monitec Informatique Inc",
    "wof:placetype":"venue"
},
  "geometry": {"coordinates":[-71.25934599999999,46.797825],"type":"Point"}
}