{
  "type": "Feature",
  "properties": {
    "iso:country":"CA",
    "sg:address":"1536 Patchett Rd",
    "sg:city":"Quesnel",
    "sg:classifiers":[
        {
            "category":"Building & Trades",
            "subcategory":"Landscaping Services",
            "type":"Services"
        }
    ],
    "sg:phone":"+1 250 249 0100",
    "sg:postcode":"V2J 7A6",
    "sg:province":"BC",
    "sg:tags":[
        "landscape",
        "contractor"
    ],
    "wof:name":"We Rock",
    "wof:placetype":"venue"
},
  "geometry": {"coordinates":[-122.52494812,52.9809417725],"type":"Point"}
}