{
  "type": "Feature",
  "properties": {
    "addr:full":"32 Stafford Dr Brampton ON L6W 1L4",
    "addr:housenumber":"32",
    "addr:postcode":"l6w 1l4",
    "addr:street":"Stafford Dr",
    "iso:country":"CA",
    "sg:address":"32 Stafford Dr",
    "sg:city":"Brampton",
    "sg:classifiers":[
        {
            "category":"Home & Garden",
            "subcategory":"Furniture",
            "type":"Retail Goods"
        }
    ],
    "sg:phone":"+1 905 452 8330",
    "sg:postcode":"L6W 1L4",
    "sg:province":"ON",
    "sg:tags":[
        "top",
        "counter",
        "kitchen",
        "cabinet"
    ],
    "wof:name":"Magnaplas Limited",
    "wof:placetype":"venue"
},
  "geometry": {"coordinates":[-79.73516100000001,43.686848],"type":"Point"}
}