{
  "type": "Feature",
  "properties": {
    "addr:full":"9635 76 Ave Grande Prairie AB T8V 5B3",
    "addr:housenumber":"9635",
    "addr:postcode":"t8v 5b3",
    "addr:street":"76 Ave",
    "iso:country":"CA",
    "sg:address":"9635 76 Ave",
    "sg:city":"Grande Prairie",
    "sg:classifiers":[
        {
            "category":"Organizations",
            "subcategory":"Religious Organization",
            "type":"Services"
        }
    ],
    "sg:phone":"+1 780 539 5125",
    "sg:postcode":"T8V 5B3",
    "sg:province":"AB",
    "sg:tags":[
        "church"
    ],
    "wof:name":"Forbes Presbyterian Church",
    "wof:placetype":"venue"
},
  "geometry": {"coordinates":[-118.784294,55.148823],"type":"Point"}
}