{
  "type": "Feature",
  "properties": {
    "addr:full":"Essex ON N8M 1A7",
    "addr:postcode":"n8m 1a7",
    "iso:country":"CA",
    "sg:city":"Essex",
    "sg:classifiers":[
        {
            "category":"Food & Beverages",
            "subcategory":"Groceries & Convenience Stores",
            "type":"Retail Goods"
        }
    ],
    "sg:phone":"+1 519 776 9060",
    "sg:postcode":"N8M 1A7",
    "sg:province":"ON",
    "sg:tags":[
        "frozen"
    ],
    "wof:name":"M & M Meat Shops",
    "wof:placetype":"venue"
},
  "geometry": {"coordinates":[-82.819923,42.172829],"type":"Point"}
}