{
  "type": "Feature",
  "properties": {
    "iso:country":"CA",
    "sg:city":"Burlington",
    "sg:classifiers":[
        {
            "category":"Professional",
            "subcategory":"Accounting & Tax Preparation",
            "type":"Services"
        }
    ],
    "sg:phone":"+1 905 333 4711",
    "sg:postcode":"L7N 3M6",
    "sg:province":"ON",
    "sg:tags":[
        "bookkeeping",
        "general"
    ],
    "wof:name":"Hancock Gardner & Assoc",
    "wof:placetype":"venue"
},
  "geometry": {"coordinates":[-79.794365,43.359943],"type":"Point"}
}