{
  "type": "Feature",
  "properties": {
    "iso:country":"CA",
    "sg:address":"3234 Station Rd",
    "sg:city":"Bonavista",
    "sg:classifiers":[
        {
            "category":"Shopping",
            "subcategory":"Optical Goods",
            "type":"Retail Goods"
        }
    ],
    "sg:phone":"+1 709 468 7595",
    "sg:postcode":"A0C 1B0",
    "sg:province":"NL",
    "sg:tags":[
        "optician"
    ],
    "wof:name":"M J Optical",
    "wof:placetype":"venue"
},
  "geometry": {"coordinates":[-53.0991287231,48.6561279297],"type":"Point"}
}