{
  "type": "Feature",
  "properties": {
    "addr:full":"469 Jarvis St Toronto ON M4Y 2G8",
    "addr:housenumber":"469",
    "addr:postcode":"m4y 2g8",
    "addr:street":"Jarvis St",
    "iso:country":"CA",
    "sg:address":"469 Jarvis St",
    "sg:city":"Toronto",
    "sg:classifiers":[
        {
            "category":"Professional",
            "subcategory":"Accounting & Tax Preparation",
            "type":"Services"
        }
    ],
    "sg:phone":"+1 416 920 3434",
    "sg:postcode":"M4Y 2G8",
    "sg:province":"ON",
    "sg:tags":[
        "accountant"
    ],
    "wof:name":"Weisdorf, David CA",
    "wof:placetype":"venue"
},
  "geometry": {"coordinates":[-79.3775024414,43.6647758484],"type":"Point"}
}