{
  "type": "Feature",
  "properties": {
    "iso:country":"CA",
    "sg:address":"31 Everest St",
    "sg:city":"Hamilton",
    "sg:classifiers":[
        {
            "category":"Professional",
            "subcategory":"Computer Services",
            "type":"Services"
        }
    ],
    "sg:phone":"+1 905 318 2682",
    "sg:postcode":"L8W 2J5",
    "sg:province":"ON",
    "sg:tags":[
        "repair"
    ],
    "wof:name":"Acr Computers",
    "wof:placetype":"venue"
},
  "geometry": {"coordinates":[-79.844856,43.192059],"type":"Point"}
}