{
  "type": "Feature",
  "properties": {
    "addr:full":"1184 Lands End Rd North Saanich BC V8L 5K2",
    "addr:housenumber":"1184",
    "addr:postcode":"v8l 5k2",
    "addr:street":"Lands End Rd",
    "iso:country":"CA",
    "sg:address":"1184 Lands End Rd",
    "sg:city":"North Saanich",
    "sg:classifiers":[
        {
            "category":"Building & Trades",
            "subcategory":"Construction",
            "type":"Services"
        }
    ],
    "sg:phone":"+1 250 656 0918",
    "sg:postcode":"V8L 5K2",
    "sg:province":"BC",
    "sg:tags":[
        "concrete",
        "contractor"
    ],
    "wof:name":"Square B Construction Ltd",
    "wof:placetype":"venue"
},
  "geometry": {"coordinates":[-123.44973754900001,48.6962890625],"type":"Point"}
}