{
  "type": "Feature",
  "properties": {
    "addr:full":"43 Church St S Richmond Hill ON L4C 1W1",
    "addr:housenumber":"43",
    "addr:postcode":"l4c 1w1",
    "addr:street":"Church St S Richmond",
    "iso:country":"CA",
    "sg:address":"43 Church St S",
    "sg:city":"Richmond Hill",
    "sg:classifiers":[
        {
            "category":"Arena",
            "subcategory":"Sports Club",
            "type":"Entertainment"
        }
    ],
    "sg:phone":"+1 905 884 1368",
    "sg:postcode":"L4C 1W1",
    "sg:province":"ON",
    "sg:tags":[
        "athletic",
        "fields",
        "stadium",
        "government"
    ],
    "wof:name":"Elgin Barrow Arena",
    "wof:placetype":"venue"
},
  "geometry": {"coordinates":[-79.436333,43.874992],"type":"Point"}
}