{
  "type": "Feature",
  "properties": {
    "addr:full":"203 Main St Whitehorse YT Y1A 2B2",
    "addr:housenumber":"203",
    "addr:postcode":"y1a 2b2",
    "addr:street":"Main St",
    "iso:country":"CA",
    "sg:address":"203 Main St",
    "sg:city":"Whitehorse",
    "sg:classifiers":[
        {
            "category":"Shopping",
            "subcategory":"Books",
            "type":"Retail Goods"
        }
    ],
    "sg:phone":"+1 867 668 2434",
    "sg:postcode":"Y1A 2B2",
    "sg:province":"YT",
    "sg:tags":[
        "dealer"
    ],
    "wof:name":"Mac's Fireweed Books",
    "wof:placetype":"venue"
},
  "geometry": {"coordinates":[-135.05246,60.719547],"type":"Point"}
}