{
  "type": "Feature",
  "properties": {
    "addr:full":"30 Dorchester Ave Etobicoke ON M8Z 4W3",
    "addr:housenumber":"30",
    "addr:postcode":"m8z 4w3",
    "addr:street":"Dorchester Ave",
    "iso:country":"CA",
    "sg:address":"30 Dorchester Ave",
    "sg:city":"Etobicoke",
    "sg:classifiers":[
        {
            "category":"Shopping",
            "subcategory":"Pharmacy",
            "type":"Retail Goods"
        }
    ],
    "sg:phone":"+1 905 281 3463",
    "sg:postcode":"M8Z 4W3",
    "sg:province":"ON",
    "wof:name":"Better Buy Discount Stores",
    "wof:placetype":"venue"
},
  "geometry": {"coordinates":[-79.51736450200001,43.6212005615],"type":"Point"}
}