{
  "type": "Feature",
  "properties": {
    "addr:full":"Springfield MB R2C 2Z2",
    "addr:postcode":"r2c 2z2",
    "iso:country":"CA",
    "sg:city":"Springfield",
    "sg:classifiers":[
        {
            "category":"Wholesale",
            "subcategory":"Scrap",
            "type":"Manufacturing & Wholesale Goods"
        }
    ],
    "sg:phone":"+1 204 224 4010",
    "sg:postcode":"R2C 2Z2",
    "sg:province":"MB",
    "sg:tags":[
        "waste",
        "garbage",
        "collection"
    ],
    "wof:name":"Harbour View Recycling",
    "wof:placetype":"venue"
},
  "geometry": {"coordinates":[-97.0128707886,49.9304084778],"type":"Point"}
}