{
  "type": "Feature",
  "properties": {
    "iso:country":"CA",
    "sg:address":"45 Burney Rd",
    "sg:city":"Bragg Creek",
    "sg:classifiers":[
        {
            "category":"Manufacturing",
            "subcategory":"Printing",
            "type":"Manufacturing & Wholesale Goods"
        }
    ],
    "sg:phone":"+1 403 949 2299",
    "sg:postcode":"T0L 0K0",
    "sg:province":"AB",
    "sg:tags":[
        "printer"
    ],
    "wof:name":"Roper Graphics & Printing",
    "wof:placetype":"venue"
},
  "geometry": {"coordinates":[-114.56471999999999,50.946758],"type":"Point"}
}