{
  "type": "Feature",
  "properties": {
    "iso:country":"CA",
    "sg:address":"556 Belyea Pl",
    "sg:city":"Qualicum Beach",
    "sg:classifiers":[
        {
            "category":"Building & Trades",
            "subcategory":"Construction",
            "type":"Services"
        }
    ],
    "sg:phone":"+1 250 248 0875",
    "sg:postcode":"V9K 1H3",
    "sg:province":"BC",
    "sg:tags":[
        "general",
        "contractor"
    ],
    "wof:name":"Beachwood Homes Inc",
    "wof:placetype":"venue"
},
  "geometry": {"coordinates":[-124.47028350799999,49.3564910889],"type":"Point"}
}