{
  "type": "Feature",
  "properties": {
    "addr:full":"Third St # 372 Elk Lake ON P0J 1G0",
    "addr:postcode":"p0j 1g0",
    "addr:street":"Third St # 372 Elk",
    "iso:country":"CA",
    "sg:address":"Third St # 372",
    "sg:city":"Elk Lake",
    "sg:classifiers":[
        {
            "category":"Manufacturing",
            "subcategory":"Lumber",
            "type":"Manufacturing & Wholesale Goods"
        }
    ],
    "sg:phone":"+1 705 678 2477",
    "sg:postcode":"P0J 1G0",
    "sg:province":"ON",
    "sg:tags":[
        "forester"
    ],
    "wof:name":"Elk Lake Community Forest",
    "wof:placetype":"venue"
},
  "geometry": {"coordinates":[-80.329712,47.727921],"type":"Point"}
}