{
  "type": "Feature",
  "properties": {
    "addr:full":"4735 39 Ave Wetaskiwin AB T9A 2J4",
    "addr:housenumber":"4735",
    "addr:postcode":"t9a 2j4",
    "addr:street":"39 Ave",
    "iso:country":"CA",
    "sg:address":"4735 39 Ave",
    "sg:city":"Wetaskiwin",
    "sg:classifiers":[
        {
            "category":"Retail",
            "subcategory":"Veterinary Services",
            "type":"Services"
        }
    ],
    "sg:phone":"+1 780 352 7006",
    "sg:postcode":"T9A 2J4",
    "sg:province":"AB",
    "sg:tags":[
        "veterinarian"
    ],
    "wof:name":"Wetaskiwin Animal Clinic",
    "wof:placetype":"venue"
},
  "geometry": {"coordinates":[-113.37125399999999,52.957668],"type":"Point"}
}