{
  "type": "Feature",
  "properties": {
    "addr:full":"3555 Bainbridge Ave Burnaby BC V5A 2T3",
    "addr:housenumber":"3555",
    "addr:postcode":"v5a 2t3",
    "addr:street":"Bainbridge Ave",
    "iso:country":"CA",
    "sg:address":"3555 Bainbridge Ave",
    "sg:city":"Burnaby",
    "sg:classifiers":[
        {
            "category":"Wholesale",
            "subcategory":"Machinery & Supplies",
            "type":"Manufacturing & Wholesale Goods"
        }
    ],
    "sg:phone":"+1 604 253 4121",
    "sg:postcode":"V5A 2T3",
    "sg:province":"BC",
    "sg:tags":[
        "dry wall",
        "contractor"
    ],
    "wof:name":"Dryco",
    "wof:placetype":"venue"
},
  "geometry": {"coordinates":[-122.956176758,49.2524604797],"type":"Point"}
}