{
  "type": "Feature",
  "properties": {
    "addr:full":"2039 Idlemore Rd Sooke BC V0S 1N0",
    "addr:housenumber":"2039",
    "addr:postcode":"v0s 1n0",
    "addr:street":"Idlemore Rd",
    "iso:country":"CA",
    "sg:address":"2039 Idlemore Rd",
    "sg:city":"Sooke",
    "sg:classifiers":[
        {
            "category":"Manufacturing",
            "subcategory":"Lumber",
            "type":"Manufacturing & Wholesale Goods"
        }
    ],
    "sg:phone":"+1 250 642 7141",
    "sg:postcode":"V0S 1N0",
    "sg:province":"BC",
    "sg:tags":[
        "company",
        "logging",
        "log",
        "hauling"
    ],
    "wof:name":"Dale Arden Log Hauling Ltd",
    "wof:placetype":"venue"
},
  "geometry": {"coordinates":[-123.69169599999999,48.383736],"type":"Point"}
}