{
  "type": "Feature",
  "properties": {
    "iso:country":"CA",
    "sg:address":"53 Wellington St S",
    "sg:city":"Mitchell",
    "sg:classifiers":[
        {
            "category":"Manufacturing",
            "subcategory":"Tools & Machinery",
            "type":"Manufacturing & Wholesale Goods"
        }
    ],
    "sg:phone":"+1 519 348 8475",
    "sg:postcode":"N0K 1N0",
    "sg:province":"ON",
    "sg:tags":[
        "poultry",
        "equipment",
        "supply"
    ],
    "wof:name":"Ford Dickison 2000 Inc",
    "wof:placetype":"venue"
},
  "geometry": {"coordinates":[-81.19580078120001,43.4609909058],"type":"Point"}
}