{
  "type": "Feature",
  "properties": {
    "addr:full":"6038 Kingsway Burnaby BC V5J 1H3",
    "addr:housenumber":"6038",
    "addr:postcode":"v5j 1h3",
    "addr:street":"Kingsway",
    "iso:country":"CA",
    "sg:address":"6038 Kingsway",
    "sg:city":"Burnaby",
    "sg:classifiers":[
        {
            "category":"Restaurant",
            "type":"Food & Drink"
        }
    ],
    "sg:phone":"+1 604 435 7799",
    "sg:postcode":"V5J 1H3",
    "sg:province":"BC",
    "wof:name":"Arby's",
    "wof:placetype":"venue"
},
  "geometry": {"coordinates":[-122.975533,49.220631],"type":"Point"}
}