{
  "type": "Feature",
  "properties": {
    "iso:country":"CA",
    "sg:address":"2600 Victoria Ave",
    "sg:city":"Regina",
    "sg:classifiers":[
        {
            "category":"Professional",
            "subcategory":"Lawyer & Legal Services",
            "type":"Services"
        }
    ],
    "sg:phone":"+1 306 761 6200",
    "sg:postcode":"S4T 1K2",
    "sg:province":"SK",
    "sg:tags":[
        "attorney"
    ],
    "wof:name":"Karwandy, Kenneth J",
    "wof:placetype":"venue"
},
  "geometry": {"coordinates":[-104.618347168,50.4473648071],"type":"Point"}
}