{
  "type": "Feature",
  "properties": {
    "addr:full":"158 281 Rte N Saint-Magloire QC G0R 3M0",
    "addr:housenumber":"281",
    "addr:postcode":"g0r 3m0",
    "addr:street":"Rte N",
    "iso:country":"CA",
    "sg:address":"158 281 Rte N",
    "sg:city":"Saint-Magloire",
    "sg:classifiers":[
        {
            "category":"Manufacturing",
            "subcategory":"Lumber",
            "type":"Manufacturing & Wholesale Goods"
        }
    ],
    "sg:phone":"+1 418 257 2138",
    "sg:postcode":"G0R 3M0",
    "sg:province":"QC",
    "sg:tags":[
        "sawmill"
    ],
    "wof:name":"Scierie Bel Ache Ltee",
    "wof:placetype":"venue"
},
  "geometry": {"coordinates":[-70.2884216309,46.5756416321],"type":"Point"}
}