{
  "type": "Feature",
  "properties": {
    "addr:full":"20585 Fraser Hwy Langley BC V3A 4G4",
    "addr:housenumber":"20585",
    "addr:postcode":"v3a 4g4",
    "addr:street":"Fraser Hwy",
    "iso:country":"CA",
    "sg:address":"20585 Fraser Hwy",
    "sg:city":"Langley",
    "sg:classifiers":[
        {
            "category":"Real Estate",
            "subcategory":"Real Estate Agent",
            "type":"Services"
        }
    ],
    "sg:phone":"+1 604 533 3231",
    "sg:postcode":"V3A 4G4",
    "sg:province":"BC",
    "wof:name":"Prudential Power Play Realty",
    "wof:placetype":"venue"
},
  "geometry": {"coordinates":[-122.652283,49.103947],"type":"Point"}
}