{
  "type": "Feature",
  "properties": {
    "addr:full":"1120 Ironwood St Campbell River BC V9W 5P7",
    "addr:housenumber":"1120",
    "addr:postcode":"v9w 5p7",
    "addr:street":"Ironwood St",
    "iso:country":"CA",
    "sg:address":"1120 Ironwood St",
    "sg:city":"Campbell River",
    "sg:classifiers":[
        {
            "category":"Restaurant",
            "type":"Food & Drink"
        }
    ],
    "sg:phone":"+1 250 286 4828",
    "sg:postcode":"V9W 5P7",
    "sg:province":"BC",
    "wof:name":"Popsey's Restaurant",
    "wof:placetype":"venue"
},
  "geometry": {"coordinates":[-125.255210877,50.0261421204],"type":"Point"}
}