{
  "type": "Feature",
  "properties": {
    "iso:country":"CA",
    "sg:address":"4450 Albert St",
    "sg:city":"Regina",
    "sg:classifiers":[
        {
            "category":"Restaurant",
            "type":"Food & Drink"
        }
    ],
    "sg:phone":"+1 306 586 7427",
    "sg:postcode":"S4S 6B4",
    "sg:province":"SK",
    "wof:name":"Tony Roma's",
    "wof:placetype":"venue"
},
  "geometry": {"coordinates":[-104.618438721,50.4087333679],"type":"Point"}
}