{
  "type": "Feature",
  "properties": {
    "addr:full":"Whitbourne NL A0B 3K0",
    "addr:postcode":"a0b 3k0",
    "iso:country":"CA",
    "sg:city":"Whitbourne",
    "sg:classifiers":[
        {
            "category":"Local Transit",
            "type":"Transportation"
        }
    ],
    "sg:phone":"+1 709 759 2691",
    "sg:postcode":"A0B 3K0",
    "sg:province":"NL",
    "sg:tags":[
        "ambulance"
    ],
    "wof:name":"Smith's Ambulance Svc",
    "wof:placetype":"venue"
},
  "geometry": {"coordinates":[-53.535805,47.420006],"type":"Point"}
}