{
  "type": "Feature",
  "properties": {
    "addr:full":"1040 Rang DE LA Riviere-Bayonn Berthierville QC J0K 1A0",
    "addr:housenumber":"1040",
    "addr:postcode":"j0k 1a0",
    "addr:street":"Rang De La Riviere-Bayonn",
    "iso:country":"CA",
    "sg:address":"1040 Rang DE LA Riviere-Bayonn",
    "sg:city":"Berthierville",
    "sg:classifiers":[
        {
            "category":"Professional",
            "subcategory":"Advertising",
            "type":"Services"
        }
    ],
    "sg:phone":"+1 450 836 0826",
    "sg:postcode":"J0K 1A0",
    "sg:province":"QC",
    "wof:name":"Contact Publicite",
    "wof:placetype":"venue"
},
  "geometry": {"coordinates":[-73.1784667969,46.0809059143],"type":"Point"}
}