{
  "type": "Feature",
  "properties": {
    "addr:full":"Estlin Riceton SK S0G 4E0",
    "addr:postcode":"s0g 4e0",
    "addr:street":"Riceton",
    "iso:country":"CA",
    "sg:address":"Estlin",
    "sg:city":"Riceton",
    "sg:classifiers":[
        {
            "category":"Wholesale",
            "subcategory":"Petroleum",
            "type":"Manufacturing & Wholesale Goods"
        }
    ],
    "sg:phone":"+1 306 738 2044",
    "sg:postcode":"S0G 4E0",
    "sg:province":"SK",
    "sg:tags":[
        "pipe",
        "line",
        "company"
    ],
    "wof:name":"Bp Canada Energy CO",
    "wof:placetype":"venue"
},
  "geometry": {"coordinates":[-104.323891,50.111855],"type":"Point"}
}