{
  "type": "Feature",
  "properties": {
    "addr:full":"57 Church St Bonavista NL A0C 1B0",
    "addr:housenumber":"57",
    "addr:postcode":"a0c 1b0",
    "addr:street":"Church St",
    "iso:country":"CA",
    "sg:address":"57 Church St",
    "sg:city":"Bonavista",
    "sg:classifiers":[
        {
            "category":"Home & Garden",
            "subcategory":"Carpets & Floor Coverings",
            "type":"Retail Goods"
        }
    ],
    "sg:phone":"+1 709 468 2383",
    "sg:postcode":"A0C 1B0",
    "sg:province":"NL",
    "sg:tags":[
        "paint",
        "rug"
    ],
    "wof:name":"Paint Shop",
    "wof:placetype":"venue"
},
  "geometry": {"coordinates":[-53.099129,48.656128],"type":"Point"}
}