{
  "type": "Feature",
  "properties": {
    "addr:full":"227 Wilkinson Rd Brampton ON L6T 4M2",
    "addr:housenumber":"227",
    "addr:postcode":"l6t 4m2",
    "addr:street":"Wilkinson Rd",
    "iso:country":"CA",
    "sg:address":"227 Wilkinson Rd",
    "sg:city":"Brampton",
    "sg:classifiers":[
        {
            "category":"Manufacturing",
            "subcategory":"Tools & Machinery",
            "type":"Manufacturing & Wholesale Goods"
        }
    ],
    "sg:phone":"+1 905 457 4777",
    "sg:postcode":"L6T 4M2",
    "sg:province":"ON",
    "sg:tags":[
        "lighting",
        "fixture"
    ],
    "wof:name":"Solera Corp",
    "wof:placetype":"venue"
},
  "geometry": {"coordinates":[-79.6962738037,43.6860733032],"type":"Point"}
}