{
  "type": "Feature",
  "properties": {
    "addr:full":"880 Boul DE Perigny Chambly QC J3L 1W3",
    "addr:housenumber":"880",
    "addr:postcode":"j3l 1w3",
    "addr:street":"Boul De Perigny",
    "iso:country":"CA",
    "sg:address":"880 Boul DE Perigny",
    "sg:city":"Chambly",
    "sg:classifiers":[
        {
            "category":"Autos & Motor Vehicles",
            "subcategory":"Fuel & Gas Station",
            "type":"Retail Goods"
        }
    ],
    "sg:phone":"+1 450 658 9215",
    "sg:postcode":"J3L 1W3",
    "sg:province":"QC",
    "sg:tags":[
        "oil"
    ],
    "wof:name":"Olco",
    "wof:placetype":"venue"
},
  "geometry": {"coordinates":[-73.302032,45.453922],"type":"Point"}
}