{
  "type": "Feature",
  "properties": {
    "addr:full":"2479 Main St London ON N6P 1R2",
    "addr:housenumber":"2479",
    "addr:postcode":"n6p 1r2",
    "addr:street":"Main St",
    "iso:country":"CA",
    "sg:address":"2479 Main St",
    "sg:city":"London",
    "sg:classifiers":[
        {
            "category":"Building & Trades",
            "subcategory":"Construction",
            "type":"Services"
        }
    ],
    "sg:phone":"+1 519 264 3300",
    "sg:postcode":"N6P 1R2",
    "sg:province":"ON",
    "sg:tags":[
        "general",
        "contractor"
    ],
    "wof:name":"Patrick Construction Ltd",
    "wof:placetype":"venue"
},
  "geometry": {"coordinates":[-81.2973403931,42.9104232788],"type":"Point"}
}