{
  "type": "Feature",
  "properties": {
    "addr:full":"83 Rue Principale Boisbriand QC J7G 1R1",
    "addr:housenumber":"83",
    "addr:postcode":"j7g 1r1",
    "addr:street":"Rue Principale",
    "iso:country":"CA",
    "sg:address":"83 Rue Principale",
    "sg:city":"Boisbriand",
    "sg:classifiers":[
        {
            "category":"Building & Trades",
            "subcategory":"Construction",
            "type":"Services"
        }
    ],
    "sg:phone":"+1 450 430 2202",
    "sg:postcode":"J7G 1R1",
    "sg:province":"QC",
    "sg:tags":[
        "contractor"
    ],
    "wof:name":"Construction Dany Rivard Inc",
    "wof:placetype":"venue"
},
  "geometry": {"coordinates":[-73.834778,45.603508],"type":"Point"}
}