{
  "type": "Feature",
  "properties": {
    "addr:full":"952 Dock Rd Rte 150 Elmsdale PE C0B 1K0",
    "addr:housenumber":"952",
    "addr:postcode":"c0b 1k0",
    "addr:street":"Dock Rd Rte 150",
    "iso:country":"CA",
    "sg:address":"952 Dock Rd Rte 150",
    "sg:city":"Elmsdale",
    "sg:classifiers":[
        {
            "category":"Organizations",
            "subcategory":"Religious Organization",
            "type":"Services"
        }
    ],
    "sg:phone":"+1 902 853 3260",
    "sg:postcode":"C0B 1K0",
    "sg:province":"PE",
    "sg:tags":[
        "church"
    ],
    "wof:name":"Elmsdale Church-the Nazarene",
    "wof:placetype":"venue"
},
  "geometry": {"coordinates":[-64.13790130620001,46.8207168579],"type":"Point"}
}