{
  "type": "Feature",
  "properties": {
    "addr:full":"Orillia ON L3V 4Y7",
    "addr:postcode":"l3v 4y7",
    "iso:country":"CA",
    "sg:city":"Orillia",
    "sg:classifiers":[
        {
            "category":"Banks & Credit Unions",
            "subcategory":"Bank",
            "type":"Services"
        }
    ],
    "sg:phone":"+1 705 323 9191",
    "sg:postcode":"L3V 4Y7",
    "sg:province":"ON",
    "sg:tags":[
        "cashing",
        "loan",
        "check"
    ],
    "wof:name":"Payday Plus",
    "wof:placetype":"venue"
},
  "geometry": {"coordinates":[-79.417725,44.60944],"type":"Point"}
}