{
  "type": "Feature",
  "properties": {
    "addr:full":"Sainte-Marthe-Sur-Le-Lac QC J0N 1P0",
    "addr:postcode":"j0n 1p0",
    "iso:country":"CA",
    "sg:city":"Sainte-Marthe-Sur-Le-Lac",
    "sg:classifiers":[
        {
            "category":"Shopping",
            "subcategory":"Department Store",
            "type":"Retail Goods"
        }
    ],
    "sg:phone":"+1 450 491 5000",
    "sg:postcode":"J0N 1P0",
    "sg:province":"QC",
    "wof:name":"Sears Canada Inc",
    "wof:placetype":"venue"
},
  "geometry": {"coordinates":[-73.92266100000001,45.540596],"type":"Point"}
}