{
  "type": "Feature",
  "properties": {
    "addr:full":"4712 Herald St Macklin SK S0L 2C0",
    "addr:housenumber":"4712",
    "addr:postcode":"s0l 2c0",
    "addr:street":"Herald St",
    "iso:country":"CA",
    "sg:address":"4712 Herald St",
    "sg:city":"Macklin",
    "sg:classifiers":[
        {
            "category":"Shopping",
            "subcategory":"Florist",
            "type":"Retail Goods"
        }
    ],
    "sg:phone":"+1 306 753 2399",
    "sg:postcode":"S0L 2C0",
    "sg:province":"SK",
    "wof:name":"Flowers & More",
    "wof:placetype":"venue"
},
  "geometry": {"coordinates":[-109.93589,52.332813],"type":"Point"}
}