{
  "type": "Feature",
  "properties": {
    "addr:full":"Ponteix SK S0N 1Z0",
    "addr:postcode":"s0n 1z0",
    "addr:street":"Ponteix",
    "iso:country":"CA",
    "sg:city":"Ponteix",
    "sg:classifiers":[
        {
            "category":"Manufacturing",
            "subcategory":"Retail Goods",
            "type":"Manufacturing & Wholesale Goods"
        }
    ],
    "sg:phone":"+1 306 625 3551",
    "sg:postcode":"S0N 1Z0",
    "sg:province":"SK",
    "sg:tags":[
        "manufacturer"
    ],
    "wof:name":"Jade Manufacturing & Welding",
    "wof:placetype":"venue"
},
  "geometry": {"coordinates":[-107.493972778,49.7460632324],"type":"Point"}
}