{
  "type": "Feature",
  "properties": {
    "iso:country":"CA",
    "sg:address":"222 Avenue Rd",
    "sg:city":"Toronto",
    "sg:classifiers":[
        {
            "category":"Shopping",
            "subcategory":"Gifts & Souvenirs",
            "type":"Retail Goods"
        }
    ],
    "sg:phone":"+1 416 975 0500",
    "sg:postcode":"M5R 2J4",
    "sg:province":"ON",
    "sg:tags":[
        "party",
        "balloon",
        "artist",
        "supply"
    ],
    "wof:name":"Balloonagram",
    "wof:placetype":"venue"
},
  "geometry": {"coordinates":[-79.3974456787,43.6765861511],"type":"Point"}
}