{
  "type": "Feature",
  "properties": {
    "addr:full":"237 Churchill Ave New Westminster BC V3L 4N9",
    "addr:housenumber":"237",
    "addr:postcode":"v3l 4n9",
    "addr:street":"Churchill Ave",
    "iso:country":"CA",
    "sg:address":"237 Churchill Ave",
    "sg:city":"New Westminster",
    "sg:classifiers":[
        {
            "category":"Professional",
            "subcategory":"Art Services",
            "type":"Services"
        }
    ],
    "sg:phone":"+1 604 524 3727",
    "sg:postcode":"V3L 4N9",
    "sg:province":"BC",
    "sg:tags":[
        "graphic",
        "designer"
    ],
    "wof:name":"Artegraphica Design CO",
    "wof:placetype":"venue"
},
  "geometry": {"coordinates":[-122.905334,49.228615],"type":"Point"}
}