{
  "type": "Feature",
  "properties": {
    "addr:full":"80 Select Ave Scarborough ON M1V 4A9",
    "addr:housenumber":"80",
    "addr:postcode":"m1v 4a9",
    "addr:street":"Select Ave",
    "iso:country":"CA",
    "sg:address":"80 Select Ave",
    "sg:city":"Scarborough",
    "sg:classifiers":[
        {
            "category":"Wholesale",
            "subcategory":"Auto Parts",
            "type":"Manufacturing & Wholesale Goods"
        }
    ],
    "sg:phone":"+1 416 292 0699",
    "sg:postcode":"M1V 4A9",
    "sg:province":"ON",
    "sg:tags":[
        "garage",
        "equipment"
    ],
    "wof:name":"Newton's Apple",
    "wof:placetype":"venue"
},
  "geometry": {"coordinates":[-79.260368,43.831085],"type":"Point"}
}