{
  "type": "Feature",
  "properties": {
    "addr:full":"875 Av Royale Beauport QC G1E 1Z9",
    "addr:postcode":"qc g1e 1z9",
    "addr:street":"875 Av Royale",
    "iso:country":"CA",
    "sg:address":"875 Av Royale",
    "sg:city":"Beauport",
    "sg:classifiers":[
        {
            "category":"Restaurant",
            "type":"Food & Drink"
        }
    ],
    "sg:phone":"+1 418 663 1722",
    "sg:postcode":"G1E 1Z9",
    "sg:province":"QC",
    "wof:name":"Restaurant Normandin",
    "wof:placetype":"venue"
},
  "geometry": {"coordinates":[-71.183998,46.865772],"type":"Point"}
}