{
  "type": "Feature",
  "properties": {
    "addr:full":"Toronto ON M4J 5B9",
    "addr:postcode":"m4j 5b9",
    "iso:country":"CA",
    "sg:city":"Toronto",
    "sg:classifiers":[
        {
            "category":"Health Services",
            "subcategory":"Doctor",
            "type":"Services"
        }
    ],
    "sg:phone":"+1 416 406 2634",
    "sg:postcode":"M4J 5B9",
    "sg:province":"ON",
    "sg:tags":[
        "physician",
        "surgeon"
    ],
    "wof:name":"Dyment, Stuart Z MD",
    "wof:placetype":"venue"
},
  "geometry": {"coordinates":[-79.3445358276,43.6790771484],"type":"Point"}
}