{
  "type": "Feature",
  "properties": {
    "addr:full":"328 Passmore Ave #52 Scarborough ON M1V 5J5",
    "addr:housenumber":"328",
    "addr:postcode":"m1v 5j5",
    "addr:street":"Passmore Ave # 52",
    "iso:country":"CA",
    "sg:address":"328 Passmore Ave #52",
    "sg:city":"Scarborough",
    "sg:classifiers":[
        {
            "category":"Manufacturing",
            "subcategory":"Food",
            "type":"Manufacturing & Wholesale Goods"
        }
    ],
    "sg:phone":"+1 416 321 0038",
    "sg:postcode":"M1V 5J5",
    "sg:province":"ON",
    "sg:tags":[
        "grocer",
        "product",
        "manufacturer"
    ],
    "wof:name":"Ah Fong Products",
    "wof:placetype":"venue"
},
  "geometry": {"coordinates":[-79.26263427729999,43.8280677795],"type":"Point"}
}