{
  "type": "Feature",
  "properties": {
    "addr:full":"North York ON M2J 1L8",
    "addr:postcode":"m2j 1l8",
    "iso:country":"CA",
    "sg:city":"North York",
    "sg:classifiers":[
        {
            "category":"Health Services",
            "subcategory":"Doctor",
            "type":"Services"
        }
    ],
    "sg:phone":"+1 416 491 4040",
    "sg:postcode":"M2J 1L8",
    "sg:province":"ON",
    "sg:tags":[
        "physician",
        "clinic",
        "surgeon"
    ],
    "wof:name":"Parkway Forest Medical Walk in",
    "wof:placetype":"venue"
},
  "geometry": {"coordinates":[-79.341072,43.773319],"type":"Point"}
}