{
  "type": "Feature",
  "properties": {
    "addr:full":"20 Estates Rd Dartmouth NS B2Y 4K7",
    "addr:housenumber":"20",
    "addr:postcode":"b2y 4k7",
    "addr:street":"Estates Rd",
    "iso:country":"CA",
    "sg:address":"20 Estates Rd",
    "sg:city":"Dartmouth",
    "sg:classifiers":[
        {
            "category":"Building & Trades",
            "subcategory":"Construction",
            "type":"Services"
        }
    ],
    "sg:phone":"+1 902 465 1171",
    "sg:postcode":"B2Y 4K7",
    "sg:province":"NS",
    "sg:tags":[
        "designer",
        "marine",
        "contractor"
    ],
    "wof:name":"Pro-Dive Marine Svc",
    "wof:placetype":"venue"
},
  "geometry": {"coordinates":[-63.5423622131,44.6552200317],"type":"Point"}
}