{
  "type": "Feature",
  "properties": {
    "addr:full":"Toronto ON M4J 1L1",
    "addr:postcode":"m4j 1l1",
    "iso:country":"CA",
    "sg:city":"Toronto",
    "sg:classifiers":[
        {
            "category":"Restaurant",
            "type":"Food & Drink"
        }
    ],
    "sg:phone":"+1 416 466 9791",
    "sg:postcode":"M4J 1L1",
    "sg:province":"ON",
    "wof:name":"Neon Coffee Shop",
    "wof:placetype":"venue"
},
  "geometry": {"coordinates":[-79.3434829712,43.6793251038],"type":"Point"}
}