{
  "type": "Feature",
  "properties": {
    "addr:full":"Montreal QC H3W 1X7",
    "addr:postcode":"h3w 1x7",
    "iso:country":"CA",
    "sg:city":"Montreal",
    "sg:classifiers":[
        {
            "category":"Health Services",
            "subcategory":"Doctor",
            "type":"Services"
        }
    ],
    "sg:phone":"+1 514 484 1252",
    "sg:postcode":"H3W 1X7",
    "sg:province":"QC",
    "sg:tags":[
        "dentist"
    ],
    "wof:name":"Blanshay, Sidney DDS",
    "wof:placetype":"venue"
},
  "geometry": {"coordinates":[-73.62809799999999,45.485191],"type":"Point"}
}