{
  "type": "Feature",
  "properties": {
    "addr:full":"147 Cove Rd Bowmanville ON L1C 3K3",
    "addr:housenumber":"147",
    "addr:postcode":"l1c 3k3",
    "addr:street":"Cove Rd",
    "iso:country":"CA",
    "sg:address":"147 Cove Rd",
    "sg:city":"Bowmanville",
    "sg:classifiers":[
        {
            "category":"Building & Trades",
            "subcategory":"Electrical",
            "type":"Services"
        }
    ],
    "sg:phone":"+1 905 623 6756",
    "sg:postcode":"L1C 3K3",
    "sg:province":"ON",
    "sg:tags":[
        "electric",
        "contractor"
    ],
    "wof:name":"Defosse Custom Renovating",
    "wof:placetype":"venue"
},
  "geometry": {"coordinates":[-78.67375199999999,43.887291],"type":"Point"}
}