{
  "type": "Feature",
  "properties": {
    "addr:full":"90 Av Des Jardins Orford QC J1X 6M6",
    "addr:postcode":"j1x 6m6",
    "addr:street":"90 Av Des Jardins",
    "iso:country":"CA",
    "sg:address":"90 Av Des Jardins",
    "sg:city":"Orford",
    "sg:classifiers":[
        {
            "category":"Sports & Exercise",
            "subcategory":"Golf",
            "type":"Entertainment"
        }
    ],
    "sg:phone":"+1 819 847 4299",
    "sg:postcode":"J1X 6M6",
    "sg:province":"QC",
    "sg:tags":[
        "course",
        "motel",
        "hotel"
    ],
    "wof:name":"Golf Manoir Des Sables",
    "wof:placetype":"venue"
},
  "geometry": {"coordinates":[-72.1647720337,45.3148727417],"type":"Point"}
}