{
  "type": "Feature",
  "properties": {
    "addr:full":"11 Rue Laurier E Victoriaville QC G6P 6P6",
    "addr:housenumber":"11",
    "addr:postcode":"g6p 6p6",
    "addr:street":"Rue Laurier E",
    "iso:country":"CA",
    "sg:address":"11 Rue Laurier E",
    "sg:city":"Victoriaville",
    "sg:classifiers":[
        {
            "category":"Retail",
            "subcategory":"Auto Repair",
            "type":"Services"
        }
    ],
    "sg:phone":"+1 819 357 2308",
    "sg:postcode":"G6P 6P6",
    "sg:province":"QC",
    "sg:tags":[
        "repairing",
        "automobile"
    ],
    "wof:name":"Garage Chez Ti-Claude",
    "wof:placetype":"venue"
},
  "geometry": {"coordinates":[-71.914528,46.039108],"type":"Point"}
}