{
  "type": "Feature",
  "properties": {
    "addr:full":"Valemount BC V0E 2Z0",
    "addr:postcode":"v0e 2z0",
    "iso:country":"CA",
    "sg:city":"Valemount",
    "sg:classifiers":[
        {
            "category":"Restaurant",
            "type":"Food & Drink"
        }
    ],
    "sg:phone":"+1 250 566 4220",
    "sg:postcode":"V0E 2Z0",
    "sg:province":"BC",
    "wof:name":"L W Pizza House",
    "wof:placetype":"venue"
},
  "geometry": {"coordinates":[-119.26284,52.83033],"type":"Point"}
}