{
  "type": "Feature",
  "properties": {
    "addr:full":"12415 Av Pierre-Baillargeon Montreal QC H1E 6H4",
    "addr:housenumber":"12415",
    "addr:postcode":"h1e 6h4",
    "addr:street":"Av Pierre-Baillargeon",
    "iso:country":"CA",
    "sg:address":"12415 Av Pierre-Baillargeon",
    "sg:city":"Montreal",
    "sg:classifiers":[
        {
            "category":"Building & Trades",
            "subcategory":"Construction",
            "type":"Services"
        }
    ],
    "sg:phone":"+1 514 648 3950",
    "sg:postcode":"H1E 6H4",
    "sg:province":"QC",
    "sg:tags":[
        "contractor"
    ],
    "wof:name":"Construction Rubbo Ltee",
    "wof:placetype":"venue"
},
  "geometry": {"coordinates":[-73.5814285278,45.6462020874],"type":"Point"}
}