{
  "type": "Feature",
  "properties": {
    "addr:full":"22710 117 Ave Maple Ridge BC V2X 3E6",
    "addr:housenumber":"22710",
    "addr:postcode":"v2x 3e6",
    "addr:street":"117 Ave",
    "iso:country":"CA",
    "sg:address":"22710 117 Ave",
    "sg:city":"Maple Ridge",
    "sg:classifiers":[
        {
            "category":"Health Services",
            "subcategory":"Nursing And Care Facility",
            "type":"Services"
        }
    ],
    "sg:phone":"+1 604 467 8831",
    "sg:postcode":"V2X 3E6",
    "sg:province":"BC",
    "sg:tags":[
        "home",
        "hospital",
        "convalescent"
    ],
    "wof:name":"Holyrood Manor",
    "wof:placetype":"venue"
},
  "geometry": {"coordinates":[-122.588417053,49.2151489258],"type":"Point"}
}