{
  "type": "Feature",
  "properties": {
    "iso:country":"CA",
    "sg:address":"1129 Derry Rd E",
    "sg:city":"Mississauga",
    "sg:classifiers":[
        {
            "category":"Personal",
            "subcategory":"Beauty Salon",
            "type":"Services"
        }
    ],
    "sg:phone":"+1 905 564 5468",
    "sg:postcode":"L5T 1P3",
    "sg:province":"ON",
    "wof:name":"Russo Hair Studio",
    "wof:placetype":"venue"
},
  "geometry": {"coordinates":[-79.6822357178,43.6680831909],"type":"Point"}
}