{
  "type": "Feature",
  "properties": {
    "addr:full":"4558 Dawson St Burnaby BC V5C 4C1",
    "addr:housenumber":"4558",
    "addr:postcode":"v5c 4c1",
    "addr:street":"Dawson St",
    "iso:country":"CA",
    "sg:address":"4558 Dawson St",
    "sg:city":"Burnaby",
    "sg:classifiers":[
        {
            "category":"Wholesale",
            "subcategory":"Construction Materials",
            "type":"Manufacturing & Wholesale Goods"
        }
    ],
    "sg:phone":"+1 604 298 1188",
    "sg:postcode":"V5C 4C1",
    "sg:province":"BC",
    "sg:tags":[
        "tile"
    ],
    "wof:name":"Italpro Tile & Marble",
    "wof:placetype":"venue"
},
  "geometry": {"coordinates":[-123.001625061,49.2643585205],"type":"Point"}
}