{
  "type": "Feature",
  "properties": {
    "addr:full":"25 Tapiola Cres #200 Ottawa ON K1T 2J7",
    "addr:housenumber":"25",
    "addr:postcode":"k1t 2j7",
    "addr:street":"Tapiola Cres # 200",
    "iso:country":"CA",
    "sg:address":"25 Tapiola Cres #200",
    "sg:city":"Ottawa",
    "sg:classifiers":[
        {
            "category":"Health Services",
            "subcategory":"Doctor",
            "type":"Services"
        }
    ],
    "sg:phone":"+1 613 738 0303",
    "sg:postcode":"K1T 2J7",
    "sg:province":"ON",
    "sg:tags":[
        "physician",
        "surgeon"
    ],
    "wof:name":"Greenboro Family Medicine Ctr",
    "wof:placetype":"venue"
},
  "geometry": {"coordinates":[-75.64679,45.363407],"type":"Point"}
}