{
  "type": "Feature",
  "properties": {
    "addr:full":"1299 Gordon St The Pas MB R9A 1K2",
    "addr:housenumber":"1299",
    "addr:postcode":"r9a 1k2",
    "addr:street":"Gordon St",
    "iso:country":"CA",
    "sg:address":"1299 Gordon St",
    "sg:city":"The Pas",
    "sg:classifiers":[
        {
            "category":"Retail",
            "subcategory":"Car Wash",
            "type":"Services"
        }
    ],
    "sg:phone":"+1 204 623 6640",
    "sg:postcode":"R9A 1K2",
    "sg:province":"MB",
    "sg:tags":[
        "polishing",
        "washing"
    ],
    "wof:name":"Don's Car Wash",
    "wof:placetype":"venue"
},
  "geometry": {"coordinates":[-101.250877,53.809578],"type":"Point"}
}