{
  "type": "Feature",
  "properties": {
    "addr:full":"Kelowna BC V1W 4M3",
    "addr:postcode":"v1w 4m3",
    "iso:country":"CA",
    "sg:city":"Kelowna",
    "sg:classifiers":[
        {
            "category":"Manufacturing",
            "subcategory":"Food",
            "type":"Manufacturing & Wholesale Goods"
        }
    ],
    "sg:phone":"+1 250 764 8000",
    "sg:postcode":"V1W 4M3",
    "sg:province":"BC",
    "sg:tags":[
        "winery"
    ],
    "wof:name":"Summerhill Pyramid Winery",
    "wof:placetype":"venue"
},
  "geometry": {"coordinates":[-119.499893,49.80761],"type":"Point"}
}