{
  "type": "Feature",
  "properties": {
    "addr:full":"464 Hargrave St Winnipeg MB R3A 0X5",
    "addr:housenumber":"464",
    "addr:postcode":"r3a 0x5",
    "addr:street":"Hargrave St",
    "iso:country":"CA",
    "sg:address":"464 Hargrave St",
    "sg:city":"Winnipeg",
    "sg:classifiers":[
        {
            "category":"Professional",
            "subcategory":"Art Services",
            "type":"Services"
        }
    ],
    "sg:phone":"+1 204 942 0708",
    "sg:postcode":"R3A 0X5",
    "sg:province":"MB",
    "sg:tags":[
        "graphic",
        "designer"
    ],
    "wof:name":"Tetro Design",
    "wof:placetype":"venue"
},
  "geometry": {"coordinates":[-97.14529418950001,49.8979263306],"type":"Point"}
}