{
  "type": "Feature",
  "properties": {
    "addr:full":"Hamilton ON L8P 3H3",
    "addr:postcode":"l8p 3h3",
    "iso:country":"CA",
    "sg:city":"Hamilton",
    "sg:classifiers":[
        {
            "category":"Real Estate",
            "subcategory":"Real Estate Operator",
            "type":"Services"
        }
    ],
    "sg:phone":"+1 905 525 0845",
    "sg:postcode":"L8P 3H3",
    "sg:province":"ON",
    "sg:tags":[
        "apartment"
    ],
    "wof:name":"Bay South Apartments",
    "wof:placetype":"venue"
},
  "geometry": {"coordinates":[-79.8750305176,43.2555427551],"type":"Point"}
}