{
  "type": "Feature",
  "properties": {
    "addr:full":"35 Duke St Hamilton ON L8P 1X2",
    "addr:housenumber":"35",
    "addr:postcode":"l8p 1x2",
    "addr:street":"Duke St",
    "iso:country":"CA",
    "sg:address":"35 Duke St",
    "sg:city":"Hamilton",
    "sg:classifiers":[
        {
            "category":"Banks & Credit Unions",
            "subcategory":"Investment Brokerage",
            "type":"Services"
        }
    ],
    "sg:phone":"+1 905 546 0404",
    "sg:postcode":"L8P 1X2",
    "sg:province":"ON",
    "sg:tags":[
        "consultant",
        "planning",
        "financial"
    ],
    "wof:name":"Adelaide Financial Inc",
    "wof:placetype":"venue"
},
  "geometry": {"coordinates":[-79.87329864500001,43.251991272],"type":"Point"}
}