{
  "type": "Feature",
  "properties": {
    "iso:country":"CA",
    "sg:address":"548 1Re Rue",
    "sg:city":"Iberville",
    "sg:classifiers":[
        {
            "category":"Education",
            "subcategory":"Vocational School",
            "type":"Public Place"
        }
    ],
    "sg:phone":"+1 450 346 2324",
    "sg:postcode":"J2X 3B4",
    "sg:province":"QC",
    "sg:tags":[
        "technical",
        "trade"
    ],
    "wof:name":"Ecole DE Couture Danielle Dube",
    "wof:placetype":"venue"
},
  "geometry": {"coordinates":[-73.228424,45.303219],"type":"Point"}
}