{
  "type": "Feature",
  "properties": {
    "addr:full":"Halifax NS B3J 1M5",
    "addr:postcode":"ns b3j 1m5",
    "iso:country":"CA",
    "sg:city":"Halifax",
    "sg:classifiers":[
        {
            "category":"Restaurant",
            "type":"Food & Drink"
        }
    ],
    "sg:phone":"+1 902 425 5900",
    "sg:postcode":"B3J 1M5",
    "sg:province":"NS",
    "wof:name":"Montreal Grill & Diner",
    "wof:placetype":"venue"
},
  "geometry": {"coordinates":[-63.572906,44.648796],"type":"Point"}
}