{
  "type": "Feature",
  "properties": {
    "iso:country":"CA",
    "sg:address":"650 Rue DE LA Madone",
    "sg:city":"Mont-Laurier",
    "sg:classifiers":[
        {
            "category":"Shopping",
            "subcategory":"Florist",
            "type":"Retail Goods"
        }
    ],
    "sg:phone":"+1 819 623 7673",
    "sg:postcode":"J9L 1S9",
    "sg:province":"QC",
    "wof:name":"Adora Fleuriste Snc",
    "wof:placetype":"venue"
},
  "geometry": {"coordinates":[-75.49520099999999,46.554165],"type":"Point"}
}