{
  "type": "Feature",
  "properties": {
    "addr:full":"102 1st Ave W Delia AB T0J 0W0",
    "addr:housenumber":"102",
    "addr:postcode":"t0j 0w0",
    "addr:street":"1St Ave W Delia",
    "iso:country":"CA",
    "sg:address":"102 1st Ave W",
    "sg:city":"Delia",
    "sg:classifiers":[
        {
            "category":"Restaurant",
            "type":"Food & Drink"
        }
    ],
    "sg:phone":"+1 403 364 2057",
    "sg:postcode":"T0J 0W0",
    "sg:province":"AB",
    "sg:tags":[
        "tea",
        "rooms"
    ],
    "wof:name":"Mother Mountain Teahouse",
    "wof:placetype":"venue"
},
  "geometry": {"coordinates":[-112.37294,51.631512],"type":"Point"}
}