{
  "type": "Feature",
  "properties": {
    "iso:country":"CA",
    "sg:address":"75 Albert St",
    "sg:city":"Ottawa",
    "sg:classifiers":[
        {
            "category":"Professional",
            "subcategory":"Management & Consulting",
            "type":"Services"
        }
    ],
    "sg:phone":"+1 613 239 0612",
    "sg:postcode":"K1P 5E7",
    "sg:province":"ON",
    "sg:tags":[
        "consultant",
        "government"
    ],
    "wof:name":"Canadian Aquaculture Industry",
    "wof:placetype":"venue"
},
  "geometry": {"coordinates":[-75.695625,45.422123],"type":"Point"}
}