{
  "type": "Feature",
  "properties": {
    "iso:country":"CA",
    "sg:address":"RR 2",
    "sg:city":"Puslinch",
    "sg:classifiers":[
        {
            "category":"Retail",
            "subcategory":"Veterinary Services",
            "type":"Services"
        }
    ],
    "sg:phone":"+1 519 823 1777",
    "sg:postcode":"N0B 2J0",
    "sg:province":"ON",
    "sg:tags":[
        "veterinarian"
    ],
    "wof:name":"Mannington Equine Svc",
    "wof:placetype":"venue"
},
  "geometry": {"coordinates":[-80.162613,43.467278],"type":"Point"}
}