{
  "type": "Feature",
  "properties": {
    "addr:full":"1818 Eglinton Ave W York ON M6E 2H6",
    "addr:housenumber":"1818",
    "addr:postcode":"m6e 2h6",
    "addr:street":"Eglinton Ave W",
    "iso:country":"CA",
    "sg:address":"1818 Eglinton Ave W",
    "sg:city":"York",
    "sg:classifiers":[
        {
            "category":"Professional",
            "subcategory":"Accounting & Tax Preparation",
            "type":"Services"
        }
    ],
    "sg:phone":"+1 416 781 8220",
    "sg:postcode":"M6E 2H6",
    "sg:province":"ON",
    "sg:tags":[
        "consultant",
        "accountant"
    ],
    "wof:name":"Constancio & Assoc Ltd",
    "wof:placetype":"venue"
},
  "geometry": {"coordinates":[-79.4497833252,43.6959266663],"type":"Point"}
}