{
  "type": "Feature",
  "properties": {
    "addr:full":"755 5 Ave SW Calgary AB T2P 0N2",
    "addr:housenumber":"755",
    "addr:postcode":"t2p 0n2",
    "addr:street":"5 Ave Sw",
    "iso:country":"CA",
    "sg:address":"755 5 Ave SW",
    "sg:city":"Calgary",
    "sg:classifiers":[
        {
            "category":"Professional",
            "subcategory":"Business Services",
            "type":"Services"
        }
    ],
    "sg:phone":"+1 403 261 8886",
    "sg:postcode":"T2P 0N2",
    "sg:province":"AB",
    "sg:tags":[
        "advertising",
        "embroidery"
    ],
    "wof:name":"Sport-Stitch Ltd",
    "wof:placetype":"venue"
},
  "geometry": {"coordinates":[-114.077454,51.04866],"type":"Point"}
}