{
  "type": "Feature",
  "properties": {
    "addr:full":"8946 Shook Rd Mission BC V2V 7M9",
    "addr:housenumber":"8946",
    "addr:postcode":"v2v 7m9",
    "addr:street":"Shook Rd",
    "iso:country":"CA",
    "sg:address":"8946 Shook Rd",
    "sg:city":"Mission",
    "sg:classifiers":[
        {
            "category":"Wholesale",
            "subcategory":"Groceries",
            "type":"Manufacturing & Wholesale Goods"
        }
    ],
    "sg:phone":"+1 604 826 1547",
    "sg:postcode":"V2V 7M9",
    "sg:province":"BC",
    "sg:tags":[
        "tea",
        "coffee"
    ],
    "wof:name":"Lindquist Marketing",
    "wof:placetype":"venue"
},
  "geometry": {"coordinates":[-122.23780059800001,49.1653404236],"type":"Point"}
}