{
  "type": "Feature",
  "properties": {
    "addr:full":"10647 99 St NW Edmonton AB T5H 4M2",
    "addr:housenumber":"10647",
    "addr:postcode":"t5h 4m2",
    "addr:street":"99 St Nw",
    "iso:country":"CA",
    "sg:address":"10647 99 St NW",
    "sg:city":"Edmonton",
    "sg:classifiers":[
        {
            "category":"Personal",
            "subcategory":"Beauty Salon",
            "type":"Services"
        }
    ],
    "sg:phone":"+1 780 413 9809",
    "sg:postcode":"T5H 4M2",
    "sg:province":"AB",
    "wof:name":"Regina Professional Skin Care",
    "wof:placetype":"venue"
},
  "geometry": {"coordinates":[-113.49121100000001,53.551151],"type":"Point"}
}