{
  "type": "Feature",
  "properties": {
    "addr:full":"Westport ON K0G 1X0",
    "addr:postcode":"k0g 1x0",
    "iso:country":"CA",
    "sg:city":"Westport",
    "sg:classifiers":[
        {
            "category":"Personal",
            "subcategory":"Beauty Salon",
            "type":"Services"
        }
    ],
    "sg:phone":"+1 613 273 9300",
    "sg:postcode":"K0G 1X0",
    "sg:province":"ON",
    "wof:name":"Salon 93",
    "wof:placetype":"venue"
},
  "geometry": {"coordinates":[-76.39641571040001,44.6786499023],"type":"Point"}
}