{
  "type": "Feature",
  "properties": {
    "addr:full":"Etobicoke ON M9C 5K8",
    "addr:postcode":"m9c 5k8",
    "iso:country":"CA",
    "sg:city":"Etobicoke",
    "sg:classifiers":[
        {
            "category":"Wholesale",
            "subcategory":"Non-durable Goods",
            "type":"Manufacturing & Wholesale Goods"
        }
    ],
    "sg:phone":"+1 416 626 7035",
    "sg:postcode":"M9C 5K8",
    "sg:province":"ON",
    "sg:tags":[
        "advertising"
    ],
    "wof:name":"Sunstar Marketing",
    "wof:placetype":"venue"
},
  "geometry": {"coordinates":[-79.5588760376,43.6261978149],"type":"Point"}
}