{
  "type": "Feature",
  "properties": {
    "addr:full":"39 Norfolk St N Simcoe ON N3Y 3N6",
    "addr:housenumber":"39",
    "addr:postcode":"n3y 3n6",
    "addr:street":"Norfolk St N",
    "iso:country":"CA",
    "sg:address":"39 Norfolk St N",
    "sg:city":"Simcoe",
    "sg:classifiers":[
        {
            "category":"Government",
            "subcategory":"Office",
            "type":"Public Place"
        }
    ],
    "sg:phone":"+1 519 428 0446",
    "sg:postcode":"N3Y 3N6",
    "sg:province":"ON",
    "wof:name":"Ontario Members of Parliament",
    "wof:placetype":"venue"
},
  "geometry": {"coordinates":[-80.30399300000001,42.837948],"type":"Point"}
}