{
  "type": "Feature",
  "properties": {
    "addr:full":"Terrebonne QC J6Y 1E6",
    "addr:postcode":"j6y 1e6",
    "iso:country":"CA",
    "sg:city":"Terrebonne",
    "sg:classifiers":[
        {
            "category":"Professional",
            "subcategory":"Accounting & Tax Preparation",
            "type":"Services"
        }
    ],
    "sg:phone":"+1 450 492 4941",
    "sg:postcode":"J6Y 1E6",
    "sg:province":"QC",
    "sg:tags":[
        "accountant"
    ],
    "wof:name":"Drouin, Nathalie CA",
    "wof:placetype":"venue"
},
  "geometry": {"coordinates":[-73.6701202393,45.696849823],"type":"Point"}
}