{
  "type": "Feature",
  "properties": {
    "addr:full":"PO Box 173 Blackie AB T0L 0J0",
    "addr:housenumber":"po",
    "addr:postcode":"t0l 0j0",
    "addr:street":"Box 173 Blackie",
    "iso:country":"CA",
    "sg:address":"PO Box 173",
    "sg:city":"Blackie",
    "sg:classifiers":[
        {
            "category":"Building & Trades",
            "subcategory":"Construction",
            "type":"Services"
        }
    ],
    "sg:phone":"+1 403 684 3724",
    "sg:postcode":"T0L 0J0",
    "sg:province":"AB",
    "sg:tags":[
        "general",
        "contractor"
    ],
    "wof:name":"Alberta Foundation & Concrete",
    "wof:placetype":"venue"
},
  "geometry": {"coordinates":[-113.622573852,50.6062660217],"type":"Point"}
}