{
  "type": "Feature",
  "properties": {
    "addr:full":"1450 Castlefield Ave York ON M6M 1Y6",
    "addr:housenumber":"1450",
    "addr:postcode":"m6m 1y6",
    "addr:street":"Castlefield Ave",
    "iso:country":"CA",
    "sg:address":"1450 Castlefield Ave",
    "sg:city":"York",
    "sg:classifiers":[
        {
            "category":"Wholesale",
            "subcategory":"Apparel",
            "type":"Manufacturing & Wholesale Goods"
        }
    ],
    "sg:phone":"+1 416 658 2222",
    "sg:postcode":"M6M 1Y6",
    "sg:province":"ON",
    "sg:tags":[
        "textile"
    ],
    "wof:name":"Rose E Dee Intl Ltd",
    "wof:placetype":"venue"
},
  "geometry": {"coordinates":[-79.46682,43.697842],"type":"Point"}
}