{
  "type": "Feature",
  "properties": {
    "iso:country":"CA",
    "sg:address":"15 Victoria Ave",
    "sg:city":"Belleville",
    "sg:classifiers":[
        {
            "category":"Government",
            "subcategory":"Office",
            "type":"Public Place"
        }
    ],
    "sg:phone":"+1 613 968 4597",
    "sg:postcode":"K8N 1Z5",
    "sg:province":"ON",
    "wof:name":"Ontario Land Registry Office",
    "wof:placetype":"venue"
},
  "geometry": {"coordinates":[-77.3847503662,44.1662902832],"type":"Point"}
}