{
  "type": "Feature",
  "properties": {
    "iso:country":"CA",
    "sg:city":"Barrie",
    "sg:classifiers":[
        {
            "category":"Health Services",
            "subcategory":"Doctor",
            "type":"Services"
        }
    ],
    "sg:phone":"+1 705 739 7856",
    "sg:postcode":"L4N 4E1",
    "sg:province":"ON",
    "sg:tags":[
        "dentist"
    ],
    "wof:name":"Mac Pherson, Scott DDS",
    "wof:placetype":"venue"
},
  "geometry": {"coordinates":[-79.6567077637,44.3619651794],"type":"Point"}
}