{
  "type": "Feature",
  "properties": {
    "addr:full":"2718 Rue Notre-Dame O Montreal QC H3J 1P1",
    "addr:housenumber":"2718",
    "addr:postcode":"h3j 1p1",
    "addr:street":"Rue Notre-Dame O",
    "iso:country":"CA",
    "sg:address":"2718 Rue Notre-Dame O",
    "sg:city":"Montreal",
    "sg:classifiers":[
        {
            "category":"Home & Garden",
            "subcategory":"Building Materials",
            "type":"Retail Goods"
        }
    ],
    "sg:phone":"+1 514 931 9322",
    "sg:postcode":"H3J 1P1",
    "sg:province":"QC",
    "sg:tags":[
        "paint"
    ],
    "wof:name":"Betonel",
    "wof:placetype":"venue"
},
  "geometry": {"coordinates":[-73.5426330566,45.5328636169],"type":"Point"}
}