{
  "type": "Feature",
  "properties": {
    "iso:country":"CA",
    "sg:address":"Broadway",
    "sg:city":"Carievale",
    "sg:classifiers":[
        {
            "category":"Organizations",
            "subcategory":"Religious Organization",
            "type":"Services"
        }
    ],
    "sg:phone":"+1 306 928 2178",
    "sg:postcode":"S0C 0P0",
    "sg:province":"SK",
    "sg:tags":[
        "church"
    ],
    "wof:name":"Carievale United Church",
    "wof:placetype":"venue"
},
  "geometry": {"coordinates":[-101.630783081,49.1774139404],"type":"Point"}
}