{
  "type": "Feature",
  "properties": {
    "addr:full":"2595 Mccullough Rd # B Nanaimo BC V9S 4M9",
    "addr:housenumber":"2595",
    "addr:postcode":"v9s 4m9",
    "addr:street":"Mccullough Rd # B",
    "iso:country":"CA",
    "sg:address":"2595 Mccullough Rd # B",
    "sg:city":"Nanaimo",
    "sg:classifiers":[
        {
            "category":"Building & Trades",
            "subcategory":"Construction",
            "type":"Services"
        }
    ],
    "sg:phone":"+1 250 729 0197",
    "sg:postcode":"V9S 4M9",
    "sg:province":"BC",
    "sg:tags":[
        "general",
        "contractor"
    ],
    "wof:name":"Saywell Contracting Ltd",
    "wof:placetype":"venue"
},
  "geometry": {"coordinates":[-123.98432200000001,49.197456],"type":"Point"}
}