{
  "type": "Feature",
  "properties": {
    "iso:country":"CA",
    "sg:address":"30 Mill Brook Rd",
    "sg:city":"Mill Brook",
    "sg:classifiers":[
        {
            "category":"Freight",
            "type":"Transportation"
        }
    ],
    "sg:phone":"+1 506 433 0740",
    "sg:postcode":"E4E 3V3",
    "sg:province":"NB",
    "sg:tags":[
        "trucking"
    ],
    "wof:name":"L D Adair Ltd",
    "wof:placetype":"venue"
},
  "geometry": {"coordinates":[-65.8815,45.77206],"type":"Point"}
}