{
  "type": "Feature",
  "properties": {
    "addr:full":"2155 Lawrence Ave E Scarborough ON M1R 5G9",
    "addr:housenumber":"2155",
    "addr:postcode":"m1r 5g9",
    "addr:street":"Lawrence Ave E",
    "iso:country":"CA",
    "sg:address":"2155 Lawrence Ave E",
    "sg:city":"Scarborough",
    "sg:classifiers":[
        {
            "category":"Personal",
            "subcategory":"Beauty Salon",
            "type":"Services"
        }
    ],
    "sg:phone":"+1 416 751 7221",
    "sg:postcode":"M1R 5G9",
    "sg:province":"ON",
    "wof:name":"Unisex Hair Cuts By Margaret",
    "wof:placetype":"venue"
},
  "geometry": {"coordinates":[-79.28518699999999,43.747288],"type":"Point"}
}