{
  "type": "Feature",
  "properties": {
    "addr:full":"Toronto ON M5J 2S7",
    "addr:postcode":"m5j 2s7",
    "iso:country":"CA",
    "sg:city":"Toronto",
    "sg:classifiers":[
        {
            "category":"Restaurant",
            "type":"Food & Drink"
        }
    ],
    "sg:phone":"+1 416 364 3474",
    "sg:postcode":"M5J 2S7",
    "sg:province":"ON",
    "sg:tags":[
        "sandwich"
    ],
    "wof:name":"Subway Sandwiches & Salads",
    "wof:placetype":"venue"
},
  "geometry": {"coordinates":[-79.383781,43.646057],"type":"Point"}
}