{
  "type": "Feature",
  "properties": {
    "addr:full":"43 Bridge St E Campbellford ON K0L 1L0",
    "addr:housenumber":"43",
    "addr:postcode":"k0l 1l0",
    "addr:street":"Bridge St E Campbellford",
    "iso:country":"CA",
    "sg:address":"43 Bridge St E",
    "sg:city":"Campbellford",
    "sg:classifiers":[
        {
            "category":"Shopping",
            "subcategory":"Jewelry",
            "type":"Retail Goods"
        }
    ],
    "sg:phone":"+1 705 653 2540",
    "sg:postcode":"K0L 1L0",
    "sg:province":"ON",
    "sg:tags":[
        "jeweler"
    ],
    "wof:name":"Rabethge's Jewellery",
    "wof:placetype":"venue"
},
  "geometry": {"coordinates":[-77.7969741821,44.3080024719],"type":"Point"}
}