{
  "type": "Feature",
  "properties": {
    "addr:full":"Muskeg River Mine Site Fort Mcmurray AB T9H 4W1",
    "addr:postcode":"t9h 4w1",
    "iso:country":"CA",
    "sg:address":"Muskeg River Mine Site",
    "sg:city":"Fort Mcmurray",
    "sg:classifiers":[
        {
            "category":"Mining & Drilling",
            "type":"Manufacturing & Wholesale Goods"
        }
    ],
    "sg:phone":"+1 780 713 4400",
    "sg:postcode":"T9H 4W1",
    "sg:province":"AB",
    "sg:tags":[
        "company",
        "oil"
    ],
    "wof:name":"Albian Sands Energy Inc",
    "wof:placetype":"venue"
},
  "geometry": {"coordinates":[-111.380302429,56.7271881104],"type":"Point"}
}