{
  "type": "Feature",
  "properties": {
    "addr:full":"637 Boul Talbot Chicoutimi QC G7H 6A4",
    "addr:housenumber":"637",
    "addr:postcode":"g7h 6a4",
    "addr:street":"Boul Talbot",
    "iso:country":"CA",
    "sg:address":"637 Boul Talbot",
    "sg:city":"Chicoutimi",
    "sg:classifiers":[
        {
            "category":"Education",
            "subcategory":"College",
            "type":"Public Place"
        }
    ],
    "sg:phone":"+1 418 545 5035",
    "sg:postcode":"G7H 6A4",
    "sg:province":"QC",
    "sg:tags":[
        "academic",
        "school"
    ],
    "wof:name":"Ecole Nationale D'Admin Pub",
    "wof:placetype":"venue"
},
  "geometry": {"coordinates":[-71.04369354249999,48.4197883606],"type":"Point"}
}