{
  "type": "Feature",
  "properties": {
    "addr:full":"1507 Acadia Dr SE Calgary AB T2J 5C4",
    "addr:housenumber":"1507",
    "addr:postcode":"t2j 5c4",
    "addr:street":"Acadia Dr Se",
    "iso:country":"CA",
    "sg:address":"1507 Acadia Dr SE",
    "sg:city":"Calgary",
    "sg:classifiers":[
        {
            "category":"Organizations",
            "subcategory":"Religious Organization",
            "type":"Services"
        }
    ],
    "sg:phone":"+1 403 271 6969",
    "sg:postcode":"T2J 5C4",
    "sg:province":"AB",
    "sg:tags":[
        "church"
    ],
    "wof:name":"Bonavista Baptist Church",
    "wof:placetype":"venue"
},
  "geometry": {"coordinates":[-114.048553467,50.9314994812],"type":"Point"}
}