{
  "type": "Feature",
  "properties": {
    "addr:full":"Timmins ON P4N 3K5",
    "addr:postcode":"p4n 3k5",
    "iso:country":"CA",
    "sg:city":"Timmins",
    "sg:classifiers":[
        {
            "category":"Education",
            "subcategory":"School",
            "type":"Public Place"
        }
    ],
    "sg:phone":"+1 705 264 0998",
    "sg:postcode":"P4N 3K5",
    "sg:province":"ON",
    "wof:name":"Coronation Public School",
    "wof:placetype":"venue"
},
  "geometry": {"coordinates":[-81.2098617554,48.4773864746],"type":"Point"}
}