{
  "type": "Feature",
  "properties": {
    "addr:full":"306 Kenora Ave Hamilton ON L8E 2W2",
    "addr:housenumber":"306",
    "addr:postcode":"l8e 2w2",
    "addr:street":"Kenora Ave",
    "iso:country":"CA",
    "sg:address":"306 Kenora Ave",
    "sg:city":"Hamilton",
    "sg:classifiers":[
        {
            "category":"Shopping",
            "subcategory":"Computers & Home Electronics",
            "type":"Retail Goods"
        }
    ],
    "sg:phone":"+1 905 561 5506",
    "sg:postcode":"L8E 2W2",
    "sg:province":"ON",
    "sg:tags":[
        "equipment",
        "television",
        "video"
    ],
    "wof:name":"Coltech Electronics Inc",
    "wof:placetype":"venue"
},
  "geometry": {"coordinates":[-79.76505299999999,43.238701],"type":"Point"}
}