{
  "type": "Feature",
  "properties": {
    "addr:full":"Sainte-Sophie QC J5J 2V3",
    "addr:postcode":"j5j 2v3",
    "iso:country":"CA",
    "sg:city":"Sainte-Sophie",
    "sg:classifiers":[
        {
            "category":"Manufacturing",
            "subcategory":"Metals",
            "type":"Manufacturing & Wholesale Goods"
        }
    ],
    "sg:phone":"+1 450 530 7878",
    "sg:postcode":"J5J 2V3",
    "sg:province":"QC",
    "sg:tags":[
        "finisher",
        "painter"
    ],
    "wof:name":"Entreprises Techno Statique",
    "wof:placetype":"venue"
},
  "geometry": {"coordinates":[-73.89659899999999,45.819359],"type":"Point"}
}