{
  "type": "Feature",
  "properties": {
    "addr:full":"162 Provost St New Glasgow NS B2H 2R1",
    "addr:housenumber":"162",
    "addr:postcode":"b2h 2r1",
    "addr:street":"Provost St",
    "iso:country":"CA",
    "sg:address":"162 Provost St",
    "sg:city":"New Glasgow",
    "sg:classifiers":[
        {
            "category":"Banks & Credit Unions",
            "subcategory":"Bank",
            "type":"Services"
        }
    ],
    "sg:phone":"+1 902 752 2573",
    "sg:postcode":"B2H 2R1",
    "sg:province":"NS",
    "wof:name":"Cibc",
    "wof:placetype":"venue"
},
  "geometry": {"coordinates":[-62.645088,45.587067],"type":"Point"}
}