{
  "type": "Feature",
  "properties": {
    "addr:full":"Richmond BC V6X 3K2",
    "addr:postcode":"v6x 3k2",
    "iso:country":"CA",
    "sg:city":"Richmond",
    "sg:classifiers":[
        {
            "category":"Personal",
            "subcategory":"Beauty Salon",
            "type":"Services"
        }
    ],
    "sg:phone":"+1 604 273 4445",
    "sg:postcode":"V6X 3K2",
    "sg:province":"BC",
    "wof:name":"Richard S Ego & CO",
    "wof:placetype":"venue"
},
  "geometry": {"coordinates":[-123.135032654,49.1719169617],"type":"Point"}
}