{
  "type": "Feature",
  "properties": {
    "addr:full":"2301 Brimley Rd #120 Scarborough ON M1S 5B8",
    "addr:housenumber":"2301",
    "addr:postcode":"m1s 5b8",
    "addr:street":"Brimley Rd # 120",
    "iso:country":"CA",
    "sg:address":"2301 Brimley Rd #120",
    "sg:city":"Scarborough",
    "sg:classifiers":[
        {
            "category":"Shopping",
            "subcategory":"Clothing, Apparel, & Fashions",
            "type":"Retail Goods"
        }
    ],
    "sg:phone":"+1 416 299 4512",
    "sg:postcode":"M1S 5B8",
    "sg:province":"ON",
    "wof:name":"Pink House Fashions",
    "wof:placetype":"venue"
},
  "geometry": {"coordinates":[-79.271103,43.793739],"type":"Point"}
}