{
  "type": "Feature",
  "properties": {
    "addr:full":"1937 Quilchena Ave Merritt BC V1K 1B8",
    "addr:housenumber":"1937",
    "addr:postcode":"v1k 1b8",
    "addr:street":"Quilchena Ave",
    "iso:country":"CA",
    "sg:address":"1937 Quilchena Ave",
    "sg:city":"Merritt",
    "sg:classifiers":[
        {
            "category":"Personal",
            "subcategory":"Beauty Salon",
            "type":"Services"
        }
    ],
    "sg:phone":"+1 250 378 6664",
    "sg:postcode":"V1K 1B8",
    "sg:province":"BC",
    "wof:name":"Kruse N' Style",
    "wof:placetype":"venue"
},
  "geometry": {"coordinates":[-120.790756,50.110664],"type":"Point"}
}