{
  "type": "Feature",
  "properties": {
    "addr:full":"15 Rue Monday Saint-Gabriel-DE-Brandon QC J0K 2N0",
    "addr:housenumber":"15",
    "addr:postcode":"j0k 2n0",
    "addr:street":"Rue Monday",
    "iso:country":"CA",
    "sg:address":"15 Rue Monday",
    "sg:city":"Saint-Gabriel-DE-Brandon",
    "sg:classifiers":[
        {
            "category":"Social Services",
            "type":"Services"
        }
    ],
    "sg:phone":"+1 450 835 0900",
    "sg:postcode":"J0K 2N0",
    "sg:province":"QC",
    "sg:tags":[
        "organization",
        "welfare"
    ],
    "wof:name":"Espace Lanaudiere",
    "wof:placetype":"venue"
},
  "geometry": {"coordinates":[-73.38246154789999,46.2945518494],"type":"Point"}
}