{
  "type": "Feature",
  "properties": {
    "addr:full":"Edmonton AB T6E 5J3",
    "addr:postcode":"t6e 5j3",
    "iso:country":"CA",
    "sg:city":"Edmonton",
    "sg:classifiers":[
        {
            "category":"Wholesale",
            "subcategory":"Medical Equipment & Supplies",
            "type":"Manufacturing & Wholesale Goods"
        }
    ],
    "sg:phone":"+1 780 466 7008",
    "sg:postcode":"T6E 5J3",
    "sg:province":"AB",
    "sg:tags":[
        "dental"
    ],
    "wof:name":"Gold Dental Management Systems",
    "wof:placetype":"venue"
},
  "geometry": {"coordinates":[-113.464516,53.487919],"type":"Point"}
}