{
  "type": "Feature",
  "properties": {
    "addr:full":"4317 47 Ave Olds AB T4H 1A2",
    "addr:housenumber":"4317",
    "addr:postcode":"t4h 1a2",
    "addr:street":"47 Ave",
    "iso:country":"CA",
    "sg:address":"4317 47 Ave",
    "sg:city":"Olds",
    "sg:classifiers":[
        {
            "category":"Home & Garden",
            "subcategory":"Building Materials",
            "type":"Retail Goods"
        }
    ],
    "sg:phone":"+1 403 556 8878",
    "sg:postcode":"T4H 1A2",
    "sg:province":"AB",
    "sg:tags":[
        "mixed",
        "concrete"
    ],
    "wof:name":"Inland Concrete Ltd",
    "wof:placetype":"venue"
},
  "geometry": {"coordinates":[-114.098144531,51.8002281189],"type":"Point"}
}