{
  "type": "Feature",
  "properties": {
    "addr:full":"3285 Mainway Burlington ON L7M 1A6",
    "addr:housenumber":"3285",
    "addr:postcode":"l7m 1a6",
    "addr:street":"Mainway",
    "iso:country":"CA",
    "sg:address":"3285 Mainway",
    "sg:city":"Burlington",
    "sg:classifiers":[
        {
            "category":"Manufacturing",
            "subcategory":"Printing",
            "type":"Manufacturing & Wholesale Goods"
        }
    ],
    "sg:phone":"+1 905 331 5845",
    "sg:postcode":"L7M 1A6",
    "sg:province":"ON",
    "sg:tags":[
        "screen"
    ],
    "wof:name":"Precision Print",
    "wof:placetype":"venue"
},
  "geometry": {"coordinates":[-79.8025970459,43.3651313782],"type":"Point"}
}