{
  "type": "Feature",
  "properties": {
    "addr:full":"9800 Rue Berri Montreal QC H3L 2G4",
    "addr:housenumber":"9800",
    "addr:postcode":"h3l 2g4",
    "addr:street":"Rue Berri",
    "iso:country":"CA",
    "sg:address":"9800 Rue Berri",
    "sg:city":"Montreal",
    "sg:classifiers":[
        {
            "category":"Shopping",
            "subcategory":"Tobacco",
            "type":"Retail Goods"
        }
    ],
    "sg:phone":"+1 514 389 6285",
    "sg:postcode":"H3L 2G4",
    "sg:province":"QC",
    "sg:tags":[
        "cigarette",
        "cigar",
        "dealer"
    ],
    "wof:name":"Tabagie Metro Sauve",
    "wof:placetype":"venue"
},
  "geometry": {"coordinates":[-73.6537857056,45.5502700806],"type":"Point"}
}