{
  "type": "Feature",
  "properties": {
    "iso:country":"CA",
    "sg:address":"15 Morenz Dr",
    "sg:city":"Stratford",
    "sg:classifiers":[
        {
            "category":"Organizations",
            "subcategory":"Professional Association",
            "type":"Services"
        }
    ],
    "sg:phone":"+1 519 271 4010",
    "sg:postcode":"N5A 4B7",
    "sg:province":"ON",
    "sg:tags":[
        "club"
    ],
    "wof:name":"Kinsmen Club of Stratford Inc",
    "wof:placetype":"venue"
},
  "geometry": {"coordinates":[-80.9764709473,43.3740882874],"type":"Point"}
}