{
  "type": "Feature",
  "properties": {
    "addr:full":"9366 120 St Surrey BC V3V 4B9",
    "addr:housenumber":"9366",
    "addr:postcode":"v3v 4b9",
    "addr:street":"120 St",
    "iso:country":"CA",
    "sg:address":"9366 120 St",
    "sg:city":"Surrey",
    "sg:classifiers":[
        {
            "category":"Personal",
            "subcategory":"Beauty Salon",
            "type":"Services"
        }
    ],
    "sg:phone":"+1 604 582 4082",
    "sg:postcode":"V3V 4B9",
    "sg:province":"BC",
    "wof:name":"Happy Haircuts",
    "wof:placetype":"venue"
},
  "geometry": {"coordinates":[-122.89003,49.173336],"type":"Point"}
}