{
  "type": "Feature",
  "properties": {
    "iso:country":"CA",
    "sg:address":"30 Crescent Ave",
    "sg:city":"Kentville",
    "sg:classifiers":[
        {
            "category":"Building & Trades",
            "subcategory":"Plumbing",
            "type":"Services"
        }
    ],
    "sg:phone":"+1 902 681 2505",
    "sg:postcode":"B4N 1R2",
    "sg:province":"NS",
    "sg:tags":[
        "sheet",
        "work",
        "metal",
        "contractor"
    ],
    "wof:name":"New Minas Sheet Metal",
    "wof:placetype":"venue"
},
  "geometry": {"coordinates":[-64.48992919920001,45.0764350891],"type":"Point"}
}