{
  "type": "Feature",
  "properties": {
    "addr:full":"880 Taylor Creek Dr Orleans ON K1C 1T1",
    "addr:housenumber":"880",
    "addr:postcode":"k1c 1t1",
    "addr:street":"Taylor Creek Dr",
    "iso:country":"CA",
    "sg:address":"880 Taylor Creek Dr",
    "sg:city":"Orleans",
    "sg:classifiers":[
        {
            "category":"Recreation",
            "type":"Entertainment"
        }
    ],
    "sg:phone":"+1 613 824 2255",
    "sg:postcode":"K1C 1T1",
    "sg:province":"ON",
    "sg:tags":[
        "club",
        "baseball"
    ],
    "wof:name":"Orleans Little League Baseball",
    "wof:placetype":"venue"
},
  "geometry": {"coordinates":[-75.4825286865,45.4920959473],"type":"Point"}
}