{
  "type": "Feature",
  "properties": {
    "addr:full":"4567 Dixie Rd Mississauga ON L4W 1S2",
    "addr:housenumber":"4567",
    "addr:postcode":"l4w 1s2",
    "addr:street":"Dixie Rd",
    "iso:country":"CA",
    "sg:address":"4567 Dixie Rd",
    "sg:city":"Mississauga",
    "sg:classifiers":[
        {
            "category":"Real Estate",
            "subcategory":"Real Estate Agent",
            "type":"Services"
        }
    ],
    "sg:phone":"+1 905 625 3399",
    "sg:postcode":"L4W 1S2",
    "sg:province":"ON",
    "sg:tags":[
        "management"
    ],
    "wof:name":"Profac Management Group",
    "wof:placetype":"venue"
},
  "geometry": {"coordinates":[-79.618179,43.634148],"type":"Point"}
}