{
  "type": "Feature",
  "properties": {
    "addr:full":"1920 99 St NW Edmonton AB T6N 1K9",
    "addr:housenumber":"1920",
    "addr:postcode":"t6n 1k9",
    "addr:street":"99 St Nw",
    "iso:country":"CA",
    "sg:address":"1920 99 St NW",
    "sg:city":"Edmonton",
    "sg:classifiers":[
        {
            "category":"Home & Garden",
            "subcategory":"Furniture",
            "type":"Retail Goods"
        }
    ],
    "sg:phone":"+1 780 430 5151",
    "sg:postcode":"T6N 1K9",
    "sg:province":"AB",
    "wof:name":"Brick",
    "wof:placetype":"venue"
},
  "geometry": {"coordinates":[-113.48571,53.448231],"type":"Point"}
}