{
  "type": "Feature",
  "properties": {
    "iso:country":"CA",
    "sg:address":"1 Roslyn Dr",
    "sg:city":"Dartmouth",
    "sg:classifiers":[
        {
            "category":"Education",
            "subcategory":"Special Training",
            "type":"Public Place"
        }
    ],
    "sg:phone":"+1 902 435 7916",
    "sg:postcode":"B2W 2M2",
    "sg:province":"NS",
    "sg:tags":[
        "instruction",
        "driving"
    ],
    "wof:name":"Mc Kenna's Defensive Driving",
    "wof:placetype":"venue"
},
  "geometry": {"coordinates":[-63.4971466064,44.6844673157],"type":"Point"}
}