{
  "type": "Feature",
  "properties": {
    "addr:full":"333 Rue Perroteau Beauport QC G1C 5Z4",
    "addr:housenumber":"333",
    "addr:postcode":"qc g1c 5z4",
    "addr:street":"Rue Perroteau",
    "iso:country":"CA",
    "sg:address":"333 Rue Perroteau",
    "sg:city":"Beauport",
    "sg:classifiers":[
        {
            "category":"Recreation",
            "type":"Entertainment"
        }
    ],
    "sg:phone":"+1 418 666 3745",
    "sg:postcode":"G1C 5Z4",
    "sg:province":"QC",
    "sg:tags":[
        "center"
    ],
    "wof:name":"Gestions Inter-Ados Beauport",
    "wof:placetype":"venue"
},
  "geometry": {"coordinates":[-71.19813499999999,46.890045],"type":"Point"}
}