{
  "type": "Feature",
  "properties": {
    "addr:full":"Highway 3 Rock Creek BC V0H 1Y0",
    "addr:postcode":"v0h 1y0",
    "addr:street":"Highway 3",
    "iso:country":"CA",
    "sg:address":"Highway 3",
    "sg:city":"Rock Creek",
    "sg:classifiers":[
        {
            "category":"Government",
            "subcategory":"Office",
            "type":"Public Place"
        }
    ],
    "sg:phone":"+1 250 446 2212",
    "sg:postcode":"V0H 1Y0",
    "sg:province":"BC",
    "wof:name":"BC Forests",
    "wof:placetype":"venue"
},
  "geometry": {"coordinates":[-118.99773407000001,49.0561141968],"type":"Point"}
}