{
  "type": "Feature",
  "properties": {
    "addr:full":"23 Mandeville Dr Yellowknife NT X1A 3N2",
    "addr:housenumber":"23",
    "addr:postcode":"x1a 3n2",
    "addr:street":"Mandeville Dr",
    "iso:country":"CA",
    "sg:address":"23 Mandeville Dr",
    "sg:city":"Yellowknife",
    "sg:classifiers":[
        {
            "category":"Wholesale",
            "subcategory":"Electrical",
            "type":"Manufacturing & Wholesale Goods"
        }
    ],
    "sg:phone":"+1 867 873 3964",
    "sg:postcode":"X1A 3N2",
    "sg:province":"NT",
    "sg:tags":[
        "equipment",
        "electric",
        "supply"
    ],
    "wof:name":"Eecol Electric Ltd",
    "wof:placetype":"venue"
},
  "geometry": {"coordinates":[-114.427658081,62.4400177002],"type":"Point"}
}