{
  "type": "Feature",
  "properties": {
    "addr:full":"815 Brenda Cres Windsor ON N8N 2G5",
    "addr:housenumber":"815",
    "addr:postcode":"n8n 2g5",
    "addr:street":"Brenda Cres",
    "iso:country":"CA",
    "sg:address":"815 Brenda Cres",
    "sg:city":"Windsor",
    "sg:classifiers":[
        {
            "category":"Education",
            "subcategory":"School",
            "type":"Public Place"
        }
    ],
    "sg:phone":"+1 519 735 6260",
    "sg:postcode":"N8N 2G5",
    "sg:province":"ON",
    "wof:name":"A V Graham",
    "wof:placetype":"venue"
},
  "geometry": {"coordinates":[-83.0339126587,42.3178215027],"type":"Point"}
}