{
  "type": "Feature",
  "properties": {
    "addr:full":"65 Woodstream Blvd # 17 Woodbridge ON L4L 7X6",
    "addr:housenumber":"65",
    "addr:postcode":"l4l 7x6",
    "addr:street":"Woodstream Blvd # 17",
    "iso:country":"CA",
    "sg:address":"65 Woodstream Blvd # 17",
    "sg:city":"Woodbridge",
    "sg:classifiers":[
        {
            "category":"Building & Trades",
            "subcategory":"Plumbing",
            "type":"Services"
        }
    ],
    "sg:phone":"+1 905 851 2253",
    "sg:postcode":"L4L 7X6",
    "sg:province":"ON",
    "sg:tags":[
        "conditioning",
        "air",
        "system",
        "contractor"
    ],
    "wof:name":"General Air Systems",
    "wof:placetype":"venue"
},
  "geometry": {"coordinates":[-79.6042175293,43.7752342224],"type":"Point"}
}