{
  "type": "Feature",
  "properties": {
    "iso:country":"CA",
    "sg:city":"Mississauga",
    "sg:classifiers":[
        {
            "category":"Building & Trades",
            "subcategory":"Construction",
            "type":"Services"
        }
    ],
    "sg:phone":"+1 905 795 9399",
    "sg:postcode":"L4W 4L8",
    "sg:province":"ON",
    "sg:tags":[
        "skylight"
    ],
    "wof:name":"Columbia Skylights",
    "wof:placetype":"venue"
},
  "geometry": {"coordinates":[-79.655685,43.644119],"type":"Point"}
}