{
  "type": "Feature",
  "properties": {
    "addr:full":"Kelowna BC V1Y 7X1",
    "addr:postcode":"v1y 7x1",
    "iso:country":"CA",
    "sg:city":"Kelowna",
    "sg:classifiers":[
        {
            "category":"Home & Garden",
            "subcategory":"Household Appliances",
            "type":"Retail Goods"
        }
    ],
    "sg:phone":"+1 250 762 9902",
    "sg:postcode":"V1Y 7X1",
    "sg:province":"BC",
    "sg:tags":[
        "cleaners",
        "vacuum"
    ],
    "wof:name":"Your Vacuum Superstore",
    "wof:placetype":"venue"
},
  "geometry": {"coordinates":[-119.442321777,49.8771209717],"type":"Point"}
}