{
  "type": "Feature",
  "properties": {
    "addr:full":"Halifax NS B3J 3K1",
    "addr:postcode":"ns b3j 3k1",
    "iso:country":"CA",
    "sg:city":"Halifax",
    "sg:classifiers":[
        {
            "category":"Shopping",
            "subcategory":"Computers & Home Electronics",
            "type":"Retail Goods"
        }
    ],
    "sg:phone":"+1 902 482 1600",
    "sg:postcode":"B3J 3K1",
    "sg:province":"NS",
    "sg:tags":[
        "equipment",
        "dealer"
    ],
    "wof:name":"Imp Solutions",
    "wof:placetype":"venue"
},
  "geometry": {"coordinates":[-63.575733,44.650124],"type":"Point"}
}