{
  "type": "Feature",
  "properties": {
    "addr:full":"Cambridge ON N3H 4R7",
    "addr:postcode":"n3h 4r7",
    "iso:country":"CA",
    "sg:city":"Cambridge",
    "sg:classifiers":[
        {
            "category":"Wholesale",
            "subcategory":"Machinery & Supplies",
            "type":"Manufacturing & Wholesale Goods"
        }
    ],
    "sg:phone":"+1 519 653 6282",
    "sg:postcode":"N3H 4R7",
    "sg:province":"ON",
    "sg:tags":[
        "abrasive"
    ],
    "wof:name":"Abrasive Supply & Svc Inc",
    "wof:placetype":"venue"
},
  "geometry": {"coordinates":[-80.332092,43.407188],"type":"Point"}
}