{
  "type": "Feature",
  "properties": {
    "iso:country":"CA",
    "sg:address":"798 Concession St",
    "sg:city":"Hamilton",
    "sg:classifiers":[
        {
            "category":"Restaurant",
            "type":"Food & Drink"
        }
    ],
    "sg:phone":"+1 905 383 3860",
    "sg:postcode":"L8V 1C9",
    "sg:province":"ON",
    "wof:name":"Jack's Roadhouse",
    "wof:placetype":"venue"
},
  "geometry": {"coordinates":[-79.841873,43.23835],"type":"Point"}
}