{
  "type": "Feature",
  "properties": {
    "addr:full":"798 Concession St Hamilton ON L8V 1C9",
    "addr:housenumber":"798",
    "addr:postcode":"l8v 1c9",
    "addr:street":"Concession St",
    "iso:country":"CA",
    "sg:address":"798 Concession St",
    "sg:city":"Hamilton",
    "sg:classifiers":[
        {
            "category":"Restaurant",
            "type":"Food & Drink"
        }
    ],
    "sg:phone":"+1 905 383 3860",
    "sg:postcode":"L8V 1C9",
    "sg:province":"ON",
    "wof:name":"Jack's Roadhouse",
    "wof:placetype":"venue"
},
  "geometry": {"coordinates":[-79.84187300000001,43.23835],"type":"Point"}
}