{
  "type": "Feature",
  "properties": {
    "addr:full":"4866 Victoria Dr Vancouver BC V5N 4P5",
    "addr:housenumber":"4866",
    "addr:postcode":"v5n 4p5",
    "addr:street":"Victoria Dr",
    "iso:country":"CA",
    "sg:address":"4866 Victoria Dr",
    "sg:city":"Vancouver",
    "sg:classifiers":[
        {
            "category":"Retail",
            "subcategory":"Laundry & Dry Cleaning",
            "type":"Services"
        }
    ],
    "sg:phone":"+1 604 435 9147",
    "sg:postcode":"V5N 4P5",
    "sg:province":"BC",
    "wof:name":"Sampan Laundry & Laundromat",
    "wof:placetype":"venue"
},
  "geometry": {"coordinates":[-123.065079,49.240398],"type":"Point"}
}