{
  "type": "Feature",
  "properties": {
    "iso:country":"CA",
    "sg:address":"1220 St. George Blvd",
    "sg:city":"Moncton",
    "sg:classifiers":[
        {
            "category":"Manufacturing",
            "subcategory":"Food",
            "type":"Manufacturing & Wholesale Goods"
        }
    ],
    "sg:phone":"+1 506 853 7299",
    "sg:postcode":"E1E 4K7",
    "sg:province":"NB",
    "sg:tags":[
        "baker",
        "cookie",
        "bakery"
    ],
    "wof:name":"Fancy Pocket Corp",
    "wof:placetype":"venue"
},
  "geometry": {"coordinates":[-64.8328170776,46.080406189],"type":"Point"}
}