{
  "type": "Feature",
  "properties": {
    "addr:full":"PO Box 269 Markstay ON P0M 2G0",
    "addr:housenumber":"po",
    "addr:postcode":"p0m 2g0",
    "addr:street":"Box 269",
    "iso:country":"CA",
    "sg:address":"PO Box 269",
    "sg:city":"Markstay",
    "sg:classifiers":[
        {
            "category":"Education",
            "subcategory":"Library",
            "type":"Public Place"
        }
    ],
    "sg:phone":"+1 705 853 0635",
    "sg:postcode":"P0M 2G0",
    "sg:province":"ON",
    "wof:name":"Markstay Warren Library",
    "wof:placetype":"venue"
},
  "geometry": {"coordinates":[-80.5423660278,46.4920196533],"type":"Point"}
}