{
  "type": "Feature",
  "properties": {
    "iso:country":"CA",
    "sg:city":"Vancouver",
    "sg:classifiers":[
        {
            "category":"Shopping",
            "subcategory":"Optical Goods",
            "type":"Retail Goods"
        }
    ],
    "sg:phone":"+1 604 683 9382",
    "sg:postcode":"V6B 6N9",
    "sg:province":"BC",
    "sg:tags":[
        "optician"
    ],
    "wof:name":"Galaxy Eyewear",
    "wof:placetype":"venue"
},
  "geometry": {"coordinates":[-123.107299805,49.2809028625],"type":"Point"}
}