{
  "type": "Feature",
  "properties": {
    "iso:country":"CA",
    "sg:address":"166 Bunting Rd",
    "sg:city":"St Catharines",
    "sg:classifiers":[
        {
            "category":"Retail",
            "subcategory":"Auto Repair",
            "type":"Services"
        }
    ],
    "sg:phone":"+1 905 685 0022",
    "sg:postcode":"L2M 3Y1",
    "sg:province":"ON",
    "sg:tags":[
        "automobile",
        "painting",
        "truck"
    ],
    "wof:name":"Metro Collision Svc Inc",
    "wof:placetype":"venue"
},
  "geometry": {"coordinates":[-79.2096405029,43.1694221497],"type":"Point"}
}