{
  "type": "Feature",
  "properties": {
    "addr:full":"19 Bird Lane Bracebridge ON P1L 1J1",
    "addr:housenumber":"19",
    "addr:postcode":"p1l 1j1",
    "addr:street":"Bird Lane",
    "iso:country":"CA",
    "sg:address":"19 Bird Lane",
    "sg:city":"Bracebridge",
    "sg:classifiers":[
        {
            "category":"Real Estate",
            "subcategory":"Architect",
            "type":"Services"
        }
    ],
    "sg:phone":"+1 705 645 2291",
    "sg:postcode":"P1L 1J1",
    "sg:province":"ON",
    "wof:name":"Bird Architect & Engineer",
    "wof:placetype":"venue"
},
  "geometry": {"coordinates":[-79.304924,45.041626],"type":"Point"}
}