{
  "type": "Feature",
  "properties": {
    "addr:full":"250 Stuart Dr # 121 Fort St James BC V0J 1P0",
    "addr:housenumber":"250",
    "addr:postcode":"v0j 1p0",
    "addr:street":"Stuart Dr # 121 Fort St",
    "iso:country":"CA",
    "sg:address":"250 Stuart Dr # 121",
    "sg:city":"Fort St James",
    "sg:classifiers":[
        {
            "category":"Government",
            "subcategory":"Office",
            "type":"Public Place"
        }
    ],
    "sg:phone":"+1 250 996 7178",
    "sg:postcode":"V0J 1P0",
    "sg:province":"BC",
    "wof:name":"BC Health Unit",
    "wof:placetype":"venue"
},
  "geometry": {"coordinates":[-124.26428199999999,54.446896],"type":"Point"}
}