{
  "type": "Feature",
  "properties": {
    "addr:full":"5008 48 St Wetaskiwin AB T9A 1G2",
    "addr:housenumber":"5008",
    "addr:postcode":"t9a 1g2",
    "addr:street":"48 St",
    "iso:country":"CA",
    "sg:address":"5008 48 St",
    "sg:city":"Wetaskiwin",
    "sg:classifiers":[
        {
            "category":"Social Services",
            "subcategory":"Job Training",
            "type":"Services"
        }
    ],
    "sg:phone":"+1 780 352 0774",
    "sg:postcode":"T9A 1G2",
    "sg:province":"AB",
    "sg:tags":[
        "rehabilitation"
    ],
    "wof:name":"Spinal Posture Rehab Ctr",
    "wof:placetype":"venue"
},
  "geometry": {"coordinates":[-113.370079,52.969364],"type":"Point"}
}