{
  "type": "Feature",
  "properties": {
    "addr:full":"New Westminster BC V3L 5P5",
    "addr:postcode":"v3l 5p5",
    "iso:country":"CA",
    "sg:city":"New Westminster",
    "sg:classifiers":[
        {
            "category":"Health Services",
            "subcategory":"Doctor",
            "type":"Services"
        }
    ],
    "sg:phone":"+1 604 526 7466",
    "sg:postcode":"V3L 5P5",
    "sg:province":"BC",
    "sg:tags":[
        "physician",
        "surgeon"
    ],
    "wof:name":"Shearer, Carl MD",
    "wof:placetype":"venue"
},
  "geometry": {"coordinates":[-122.896606445,49.2181816101],"type":"Point"}
}