{
  "type": "Feature",
  "properties": {
    "addr:full":"606 Rue Lanaudiere Repentigny QC J6A 7M9",
    "addr:housenumber":"606",
    "addr:postcode":"j6a 7m9",
    "addr:street":"Rue Lanaudiere",
    "iso:country":"CA",
    "sg:address":"606 Rue Lanaudiere",
    "sg:city":"Repentigny",
    "sg:classifiers":[
        {
            "category":"Wholesale",
            "subcategory":"Machinery & Supplies",
            "type":"Manufacturing & Wholesale Goods"
        }
    ],
    "sg:phone":"+1 450 654 9671",
    "sg:postcode":"J6A 7M9",
    "sg:province":"QC",
    "sg:tags":[
        "equipment",
        "welding"
    ],
    "wof:name":"Oxygene Rive Nord Inc",
    "wof:placetype":"venue"
},
  "geometry": {"coordinates":[-73.45062299999999,45.752678],"type":"Point"}
}