{
  "type": "Feature",
  "properties": {
    "iso:country":"CA",
    "sg:address":"606 Rue Lanaudiere",
    "sg:city":"Repentigny",
    "sg:classifiers":[
        {
            "category":"Wholesale",
            "subcategory":"Machinery & Supplies",
            "type":"Manufacturing & Wholesale Goods"
        }
    ],
    "sg:phone":"+1 450 654 9671",
    "sg:postcode":"J6A 7M9",
    "sg:province":"QC",
    "sg:tags":[
        "equipment",
        "welding"
    ],
    "wof:name":"Oxygene Rive Nord Inc",
    "wof:placetype":"venue"
},
  "geometry": {"coordinates":[-73.450623,45.752678],"type":"Point"}
}