{
  "type": "Feature",
  "properties": {
    "addr:full":"Lake George Rd Aylesford NS B0P 1C0",
    "addr:postcode":"b0p 1c0",
    "addr:street":"Lake George Rd",
    "iso:country":"CA",
    "sg:address":"Lake George Rd",
    "sg:city":"Aylesford",
    "sg:classifiers":[
        {
            "category":"Organizations",
            "subcategory":"Non-profit Organization",
            "type":"Services"
        }
    ],
    "sg:phone":"+1 902 847 9161",
    "sg:postcode":"B0P 1C0",
    "sg:province":"NS",
    "sg:tags":[
        "charitable",
        "institution"
    ],
    "wof:name":"Kingswood Camp",
    "wof:placetype":"venue"
},
  "geometry": {"coordinates":[-64.837524,45.027794],"type":"Point"}
}