{
  "type": "Feature",
  "properties": {
    "addr:full":"1020 Ranckwicha Ave Lac-Simon QC J0Y 3M0",
    "addr:housenumber":"1020",
    "addr:postcode":"j0y 3m0",
    "addr:street":"Ranckwicha Ave",
    "iso:country":"CA",
    "sg:address":"1020 Ranckwicha Ave",
    "sg:city":"Lac-Simon",
    "sg:classifiers":[
        {
            "category":"Organizations",
            "subcategory":"Professional Association",
            "type":"Services"
        }
    ],
    "sg:phone":"+1 819 736 2161",
    "sg:postcode":"J0Y 3M0",
    "sg:province":"QC",
    "wof:name":"Gouvernements",
    "wof:placetype":"venue"
},
  "geometry": {"coordinates":[-75.09307099999999,45.905376],"type":"Point"}
}