{
  "type": "Feature",
  "properties": {
    "addr:full":"560 Duke St Bathurst NB E2A 2X5",
    "addr:housenumber":"560",
    "addr:postcode":"e2a 2x5",
    "addr:street":"Duke St",
    "iso:country":"CA",
    "sg:address":"560 Duke St",
    "sg:city":"Bathurst",
    "sg:classifiers":[
        {
            "category":"Education",
            "subcategory":"School",
            "type":"Public Place"
        }
    ],
    "sg:phone":"+1 506 547 2750",
    "sg:postcode":"E2A 2X5",
    "sg:province":"NB",
    "wof:name":"Superior Middle",
    "wof:placetype":"venue"
},
  "geometry": {"coordinates":[-65.669594,47.621643],"type":"Point"}
}