{
  "type": "Feature",
  "properties": {
    "addr:full":"45 Connors Lane Bayside NB E5B 2Y3",
    "addr:housenumber":"45",
    "addr:postcode":"e5b 2y3",
    "addr:street":"Connors Lane",
    "iso:country":"CA",
    "sg:address":"45 Connors Lane",
    "sg:city":"Bayside",
    "sg:classifiers":[
        {
            "category":"Freight",
            "type":"Transportation"
        }
    ],
    "sg:phone":"+1 506 529 4591",
    "sg:postcode":"E5B 2Y3",
    "sg:province":"NB",
    "sg:tags":[
        "cargo",
        "containerized",
        "trucking"
    ],
    "wof:name":"Sea Shuttle Inc",
    "wof:placetype":"venue"
},
  "geometry": {"coordinates":[-67.12211600000001,45.143124],"type":"Point"}
}