{
  "type": "Feature",
  "properties": {
    "addr:full":"2420 Homelands Dr Mississauga ON L5K 1H2",
    "addr:housenumber":"2420",
    "addr:postcode":"l5k 1h2",
    "addr:street":"Homelands Dr",
    "iso:country":"CA",
    "sg:address":"2420 Homelands Dr",
    "sg:city":"Mississauga",
    "sg:classifiers":[
        {
            "category":"Education",
            "subcategory":"School",
            "type":"Public Place"
        }
    ],
    "sg:phone":"+1 905 822 2031",
    "sg:postcode":"L5K 1H2",
    "sg:province":"ON",
    "wof:name":"Homelands Senior School",
    "wof:placetype":"venue"
},
  "geometry": {"coordinates":[-79.667946,43.523914],"type":"Point"}
}