{
  "type": "Feature",
  "properties": {
    "addr:full":"1180 Main St Smithers BC V0J 2N0",
    "addr:housenumber":"1180",
    "addr:postcode":"v0j 2n0",
    "addr:street":"Main St",
    "iso:country":"CA",
    "sg:address":"1180 Main St",
    "sg:city":"Smithers",
    "sg:classifiers":[
        {
            "category":"Personal",
            "subcategory":"Beauty Salon",
            "type":"Services"
        }
    ],
    "sg:phone":"+1 250 847 4441",
    "sg:postcode":"V0J 2N0",
    "sg:province":"BC",
    "wof:name":"Salon 1180",
    "wof:placetype":"venue"
},
  "geometry": {"coordinates":[-127.17115800000001,54.779797],"type":"Point"}
}