{
  "type": "Feature",
  "properties": {
    "addr:full":"Granby QC J2G 5B7",
    "addr:postcode":"j2g 5b7",
    "iso:country":"CA",
    "sg:city":"Granby",
    "sg:classifiers":[
        {
            "category":"Manufacturing",
            "subcategory":"Printing",
            "type":"Manufacturing & Wholesale Goods"
        }
    ],
    "sg:phone":"+1 450 372 2985",
    "sg:postcode":"J2G 5B7",
    "sg:province":"QC",
    "sg:tags":[
        "plate",
        "printer"
    ],
    "wof:name":"Novaflex",
    "wof:placetype":"venue"
},
  "geometry": {"coordinates":[-72.725281,45.402645],"type":"Point"}
}