{
  "type": "Feature",
  "properties": {
    "addr:full":"Saskatoon SK S7K 0B8",
    "addr:postcode":"s7k 0b8",
    "iso:country":"CA",
    "sg:city":"Saskatoon",
    "sg:classifiers":[
        {
            "category":"Shopping",
            "subcategory":"Clothing, Apparel, & Fashions",
            "type":"Retail Goods"
        }
    ],
    "sg:phone":"+1 306 934 8206",
    "sg:postcode":"S7K 0B8",
    "sg:province":"SK",
    "wof:name":"Jocks Sportswear",
    "wof:placetype":"venue"
},
  "geometry": {"coordinates":[-106.664474,52.127064],"type":"Point"}
}