{
  "type": "Feature",
  "properties": {
    "iso:country":"CA",
    "sg:address":"2898 Pinnacles Rd",
    "sg:city":"Quesnel",
    "sg:classifiers":[
        {
            "category":"Home & Garden",
            "subcategory":"Building Materials",
            "type":"Retail Goods"
        }
    ],
    "sg:phone":"+1 250 249 5629",
    "sg:postcode":"V2J 7G9",
    "sg:province":"BC",
    "sg:tags":[
        "glass",
        "window",
        "plate"
    ],
    "wof:name":"Northern Interior Windows",
    "wof:placetype":"venue"
},
  "geometry": {"coordinates":[-122.498245239,52.9781188965],"type":"Point"}
}