{
  "type": "Feature",
  "properties": {
    "addr:full":"1225 Prince George St Prince Rupert BC V8J 4K6",
    "addr:housenumber":"1225",
    "addr:postcode":"v8j 4k6",
    "addr:street":"Prince George St",
    "iso:country":"CA",
    "sg:address":"1225 Prince George St",
    "sg:city":"Prince Rupert",
    "sg:classifiers":[
        {
            "category":"Organizations",
            "subcategory":"Religious Organization",
            "type":"Services"
        }
    ],
    "sg:phone":"+1 250 624 2354",
    "sg:postcode":"V8J 4K6",
    "sg:province":"BC",
    "sg:tags":[
        "church"
    ],
    "wof:name":"Church of Jesus Christ-Lds",
    "wof:placetype":"venue"
},
  "geometry": {"coordinates":[-130.29975899999999,54.311771],"type":"Point"}
}