{
  "type": "Feature",
  "properties": {
    "addr:full":"Brampton ON L6Z 4R3",
    "addr:postcode":"l6z 4r3",
    "iso:country":"CA",
    "sg:city":"Brampton",
    "sg:classifiers":[
        {
            "category":"Professional",
            "subcategory":"Business Services",
            "type":"Services"
        }
    ],
    "sg:phone":"+1 905 840 5813",
    "sg:postcode":"L6Z 4R3",
    "sg:province":"ON",
    "sg:tags":[
        "interior",
        "consultant",
        "design",
        "decorator"
    ],
    "wof:name":"Design Center",
    "wof:placetype":"venue"
},
  "geometry": {"coordinates":[-79.81326300000001,43.72628],"type":"Point"}
}