{
  "type": "Feature",
  "properties": {
    "addr:full":"Kenora ON P9N 1S8",
    "addr:postcode":"p9n 1s8",
    "iso:country":"CA",
    "sg:city":"Kenora",
    "sg:classifiers":[
        {
            "category":"Education",
            "subcategory":"School",
            "type":"Public Place"
        }
    ],
    "sg:phone":"+1 807 468 3394",
    "sg:postcode":"P9N 1S8",
    "sg:province":"ON",
    "wof:name":"Community Learning Ctr",
    "wof:placetype":"venue"
},
  "geometry": {"coordinates":[-94.4895706177,49.7681503296],"type":"Point"}
}