{
  "type": "Feature",
  "properties": {
    "addr:full":"1236 Rue Jean-Talon E Montreal QC H2R 1W2",
    "addr:housenumber":"1236",
    "addr:postcode":"h2r 1w2",
    "addr:street":"Rue Jean-Talon E",
    "iso:country":"CA",
    "sg:address":"1236 Rue Jean-Talon E",
    "sg:city":"Montreal",
    "sg:classifiers":[
        {
            "category":"Personal",
            "subcategory":"Barber",
            "type":"Services"
        }
    ],
    "sg:phone":"+1 514 277 7222",
    "sg:postcode":"H2R 1W2",
    "sg:province":"QC",
    "wof:name":"Salon Louis T",
    "wof:placetype":"venue"
},
  "geometry": {"coordinates":[-73.610741,45.543655],"type":"Point"}
}