{
  "type": "Feature",
  "properties": {
    "iso:country":"CA",
    "sg:address":"6296 Donway Dr",
    "sg:city":"Mississauga",
    "sg:classifiers":[
        {
            "category":"Building & Trades",
            "subcategory":"Construction",
            "type":"Services"
        }
    ],
    "sg:phone":"+1 905 821 2451",
    "sg:postcode":"L5V 1J6",
    "sg:province":"ON",
    "sg:tags":[
        "home",
        "improvement"
    ],
    "wof:name":"Winston Construction & Rnvtn",
    "wof:placetype":"venue"
},
  "geometry": {"coordinates":[-79.7097854614,43.6123542786],"type":"Point"}
}