{
  "type": "Feature",
  "properties": {
    "addr:full":"Smiths Falls ON K7A 5B8",
    "addr:postcode":"k7a 5b8",
    "iso:country":"CA",
    "sg:city":"Smiths Falls",
    "sg:classifiers":[
        {
            "category":"Shopping",
            "subcategory":"Used Merchandise",
            "type":"Retail Goods"
        }
    ],
    "sg:phone":"+1 613 283 7032",
    "sg:postcode":"K7A 5B8",
    "sg:province":"ON",
    "sg:tags":[
        "second",
        "hand",
        "store",
        "furniture"
    ],
    "wof:name":"Bernie's Nearly New Shoppe",
    "wof:placetype":"venue"
},
  "geometry": {"coordinates":[-76.02151499999999,44.902584],"type":"Point"}
}