{
  "type": "Feature",
  "properties": {
    "addr:full":"167 Rue DE LA Reine Gaspe QC G4X 2W6",
    "addr:housenumber":"167",
    "addr:postcode":"g4x 2w6",
    "addr:street":"Rue De La Reine Gaspe",
    "iso:country":"CA",
    "sg:address":"167 Rue DE LA Reine",
    "sg:city":"Gaspe",
    "sg:classifiers":[
        {
            "category":"Shopping",
            "subcategory":"Department Store",
            "type":"Retail Goods"
        }
    ],
    "sg:phone":"+1 418 368 8020",
    "sg:postcode":"G4X 2W6",
    "sg:province":"QC",
    "wof:name":"Aubainerie Croteau",
    "wof:placetype":"venue"
},
  "geometry": {"coordinates":[-64.4849243164,48.8287162781],"type":"Point"}
}