{
  "type": "Feature",
  "properties": {
    "addr:full":"5291 General Rd Mississauga ON L4W 2K4",
    "addr:housenumber":"5291",
    "addr:postcode":"l4w 2k4",
    "addr:street":"General Rd",
    "iso:country":"CA",
    "sg:address":"5291 General Rd",
    "sg:city":"Mississauga",
    "sg:classifiers":[
        {
            "category":"Wholesale",
            "subcategory":"Construction Materials",
            "type":"Manufacturing & Wholesale Goods"
        }
    ],
    "sg:phone":"+1 905 629 0242",
    "sg:postcode":"L4W 2K4",
    "sg:province":"ON",
    "sg:tags":[
        "concrete",
        "form"
    ],
    "wof:name":"Form & Build Supply Inc",
    "wof:placetype":"venue"
},
  "geometry": {"coordinates":[-79.62999000000001,43.639088],"type":"Point"}
}