{
  "type": "Feature",
  "properties": {
    "addr:full":"29 Airport Rd Sioux Lookout ON P8T 1B3",
    "addr:housenumber":"29",
    "addr:postcode":"p8t 1b3",
    "addr:street":"Airport Rd",
    "iso:country":"CA",
    "sg:address":"29 Airport Rd",
    "sg:city":"Sioux Lookout",
    "sg:classifiers":[
        {
            "category":"Building & Trades",
            "subcategory":"Equipment Rental",
            "type":"Services"
        }
    ],
    "sg:phone":"+1 807 737 4445",
    "sg:postcode":"P8T 1B3",
    "sg:province":"ON",
    "sg:tags":[
        "aircraft",
        "leasing",
        "charter"
    ],
    "wof:name":"Lockhart Air Svc Ltd",
    "wof:placetype":"venue"
},
  "geometry": {"coordinates":[-91.90171813960001,50.1154747009],"type":"Point"}
}