{
  "type": "Feature",
  "properties": {
    "addr:full":"Toronto ON M5V 2H8",
    "addr:postcode":"m5v 2h8",
    "iso:country":"CA",
    "sg:city":"Toronto",
    "sg:classifiers":[
        {
            "category":"Wholesale",
            "subcategory":"Books, Periodicals, & Newspapers",
            "type":"Manufacturing & Wholesale Goods"
        }
    ],
    "sg:phone":"+1 416 408 3805",
    "sg:postcode":"M5V 2H8",
    "sg:province":"ON",
    "sg:tags":[
        "distributor"
    ],
    "wof:name":"R M Distribution",
    "wof:placetype":"venue"
},
  "geometry": {"coordinates":[-79.394859314,43.6444969177],"type":"Point"}
}