{
  "type": "Feature",
  "properties": {
    "addr:full":"248 Rue Des Palominos Gatineau QC J8R 3P7",
    "addr:housenumber":"248",
    "addr:postcode":"j8r 3p7",
    "addr:street":"Rue Des Palominos",
    "iso:country":"CA",
    "sg:address":"248 Rue Des Palominos",
    "sg:city":"Gatineau",
    "sg:classifiers":[
        {
            "category":"Wholesale",
            "subcategory":"Electrical",
            "type":"Manufacturing & Wholesale Goods"
        }
    ],
    "sg:phone":"+1 819 669 9209",
    "sg:postcode":"J8R 3P7",
    "sg:province":"QC",
    "sg:tags":[
        "control",
        "alarm",
        "burglar",
        "security",
        "system"
    ],
    "wof:name":"Prevention Outaouais Inc",
    "wof:placetype":"venue"
},
  "geometry": {"coordinates":[-75.577896,45.51078],"type":"Point"}
}