{
  "type": "Feature",
  "properties": {
    "iso:country":"CA",
    "sg:address":"1562 Blair Rd",
    "sg:city":"Gloucester",
    "sg:classifiers":[
        {
            "category":"Building & Trades",
            "subcategory":"Construction",
            "type":"Services"
        }
    ],
    "sg:phone":"+1 613 744 0610",
    "sg:postcode":"K1B 3K7",
    "sg:province":"ON",
    "sg:tags":[
        "home",
        "improvement"
    ],
    "wof:name":"F & R Alvarez Carpentry",
    "wof:placetype":"venue"
},
  "geometry": {"coordinates":[-75.599571228,45.4259986877],"type":"Point"}
}