{
  "type": "Feature",
  "properties": {
    "addr:full":"340 Rue Joseph-Carrier Vaudreuil-Dorion QC J7V 5V5",
    "addr:housenumber":"340",
    "addr:postcode":"j7v 5v5",
    "addr:street":"Rue Joseph-Carrier",
    "iso:country":"CA",
    "sg:address":"340 Rue Joseph-Carrier",
    "sg:city":"Vaudreuil-Dorion",
    "sg:classifiers":[
        {
            "category":"Professional",
            "type":"Services"
        }
    ],
    "sg:phone":"+1 450 424 7008",
    "sg:postcode":"J7V 5V5",
    "sg:province":"QC",
    "sg:tags":[
        "equipment",
        "printing",
        "establishment"
    ],
    "wof:name":"Rocom Equipment Ltd",
    "wof:placetype":"venue"
},
  "geometry": {"coordinates":[-74.05334499999999,45.405041],"type":"Point"}
}