{
  "type": "Feature",
  "properties": {
    "addr:full":"Windsor ON N8X 5A6",
    "addr:postcode":"n8x 5a6",
    "iso:country":"CA",
    "sg:city":"Windsor",
    "sg:classifiers":[
        {
            "category":"Personal",
            "type":"Services"
        }
    ],
    "sg:phone":"+1 519 258 9833",
    "sg:postcode":"N8X 5A6",
    "sg:province":"ON",
    "sg:tags":[
        "therapist",
        "massage"
    ],
    "wof:name":"Windsor Therapeutic Massage",
    "wof:placetype":"venue"
},
  "geometry": {"coordinates":[-83.0175857544,42.2991447449],"type":"Point"}
}