{
  "type": "Feature",
  "properties": {
    "iso:country":"CA",
    "sg:address":"250 Rue Saint-Francois N",
    "sg:city":"Sherbrooke",
    "sg:classifiers":[
        {
            "category":"Shopping",
            "subcategory":"Books",
            "type":"Retail Goods"
        }
    ],
    "sg:phone":"+1 819 569 5535",
    "sg:postcode":"J1E 2B9",
    "sg:province":"QC",
    "sg:tags":[
        "religious"
    ],
    "wof:name":"Librairie Mediaspaul",
    "wof:placetype":"venue"
},
  "geometry": {"coordinates":[-71.88902282710001,45.4073753357],"type":"Point"}
}