{
  "type": "Feature",
  "properties": {
    "addr:full":"1230 381 Rte S Ferland-Et-Boilleau QC G0V 1H0",
    "addr:housenumber":"1230",
    "addr:postcode":"g0v 1h0",
    "addr:street":"381 Rte S",
    "iso:country":"CA",
    "sg:address":"1230 381 Rte S",
    "sg:city":"Ferland-Et-Boilleau",
    "sg:classifiers":[
        {
            "category":"Building & Trades",
            "subcategory":"Construction",
            "type":"Services"
        }
    ],
    "sg:phone":"+1 418 676 2575",
    "sg:postcode":"G0V 1H0",
    "sg:province":"QC",
    "sg:tags":[
        "excavating",
        "contractor",
        "general"
    ],
    "wof:name":"Entreprises Forestieres Michel",
    "wof:placetype":"venue"
},
  "geometry": {"coordinates":[-70.87565600000001,48.129974],"type":"Point"}
}