{
  "type": "Feature",
  "properties": {
    "iso:country":"CA",
    "sg:address":"2 Ch Masson",
    "sg:city":"Sainte-Marguerite-Esterel",
    "sg:classifiers":[
        {
            "category":"Social Services",
            "type":"Services"
        }
    ],
    "sg:phone":"+1 450 228 8606",
    "sg:postcode":"J0T 1L0",
    "sg:province":"QC",
    "sg:tags":[
        "organization",
        "welfare"
    ],
    "wof:name":"Rencontre",
    "wof:placetype":"venue"
},
  "geometry": {"coordinates":[-74.0189590454,46.0425453186],"type":"Point"}
}