{
  "type": "Feature",
  "properties": {
    "addr:full":"2250 Boul Jean-DE Brebeuf Drummondville QC J2B 8A1",
    "addr:housenumber":"2250",
    "addr:postcode":"j2b 8a1",
    "addr:street":"Boul Jean-De Brebeuf",
    "iso:country":"CA",
    "sg:address":"2250 Boul Jean-DE Brebeuf",
    "sg:city":"Drummondville",
    "sg:classifiers":[
        {
            "category":"Organizations",
            "subcategory":"Religious Organization",
            "type":"Services"
        }
    ],
    "sg:phone":"+1 819 478 5333",
    "sg:postcode":"J2B 8A1",
    "sg:province":"QC",
    "sg:tags":[
        "church"
    ],
    "wof:name":"Eglise Baptiste DE LA Foi",
    "wof:placetype":"venue"
},
  "geometry": {"coordinates":[-72.4869689941,45.8518066406],"type":"Point"}
}