{
  "type": "Feature",
  "properties": {
    "addr:full":"743 Queen St Kincardine ON N2Z 1Z9",
    "addr:housenumber":"743",
    "addr:postcode":"n2z 1z9",
    "addr:street":"Queen St",
    "iso:country":"CA",
    "sg:address":"743 Queen St",
    "sg:city":"Kincardine",
    "sg:classifiers":[
        {
            "category":"Shopping",
            "subcategory":"Jewelry",
            "type":"Retail Goods"
        }
    ],
    "sg:phone":"+1 519 396 2672",
    "sg:postcode":"N2Z 1Z9",
    "sg:province":"ON",
    "sg:tags":[
        "jeweler"
    ],
    "wof:name":"Gilbert's Jewellery",
    "wof:placetype":"venue"
},
  "geometry": {"coordinates":[-81.635902,44.175869],"type":"Point"}
}