{
  "type": "Feature",
  "properties": {
    "addr:full":"2847 Garland Rd Cobourg ON K9A 4J7",
    "addr:housenumber":"2847",
    "addr:postcode":"k9a 4j7",
    "addr:street":"Garland Rd",
    "iso:country":"CA",
    "sg:address":"2847 Garland Rd",
    "sg:city":"Cobourg",
    "sg:classifiers":[
        {
            "category":"Building & Trades",
            "subcategory":"Plumbing",
            "type":"Services"
        }
    ],
    "sg:phone":"+1 905 885 7572",
    "sg:postcode":"K9A 4J7",
    "sg:province":"ON",
    "sg:tags":[
        "contractor"
    ],
    "wof:name":"Barney Mills Plumbing Svc",
    "wof:placetype":"venue"
},
  "geometry": {"coordinates":[-78.1677780151,43.9596061707],"type":"Point"}
}