{
  "type": "Feature",
  "properties": {
    "addr:full":"338 Goldie St Paisley ON N0G 2N0",
    "addr:housenumber":"338",
    "addr:postcode":"n0g 2n0",
    "addr:street":"Goldie St",
    "iso:country":"CA",
    "sg:address":"338 Goldie St",
    "sg:city":"Paisley",
    "sg:classifiers":[
        {
            "category":"Organizations",
            "subcategory":"Professional Association",
            "type":"Services"
        }
    ],
    "sg:phone":"+1 519 353 5444",
    "sg:postcode":"N0G 2N0",
    "sg:province":"ON",
    "wof:name":"Royal Canadian Legion",
    "wof:placetype":"venue"
},
  "geometry": {"coordinates":[-81.272606,44.306213],"type":"Point"}
}