{
  "type": "Feature",
  "properties": {
    "addr:full":"170 Glenmorris St Cambridge ON N1S 2Z7",
    "addr:housenumber":"170",
    "addr:postcode":"n1s 2z7",
    "addr:street":"Glenmorris St",
    "iso:country":"CA",
    "sg:address":"170 Glenmorris St",
    "sg:city":"Cambridge",
    "sg:classifiers":[
        {
            "category":"Personal",
            "subcategory":"Beauty Salon",
            "type":"Services"
        }
    ],
    "sg:phone":"+1 519 621 5442",
    "sg:postcode":"N1S 2Z7",
    "sg:province":"ON",
    "wof:name":"Designers 84 Inc",
    "wof:placetype":"venue"
},
  "geometry": {"coordinates":[-80.321762085,43.3425140381],"type":"Point"}
}