{
  "type": "Feature",
  "properties": {
    "iso:country":"CA",
    "sg:address":"14 Rue Comtois",
    "sg:city":"Notre-Dame-Des-Prairies",
    "sg:classifiers":[
        {
            "category":"Professional",
            "subcategory":"Business Services",
            "type":"Services"
        }
    ],
    "sg:phone":"+1 514 591 7655",
    "sg:postcode":"J6E 6Y3",
    "sg:province":"QC",
    "sg:tags":[
        "repairing",
        "sign"
    ],
    "wof:name":"Installations",
    "wof:placetype":"venue"
},
  "geometry": {"coordinates":[-73.42412567140001,46.0418968201],"type":"Point"}
}