{
  "type": "Feature",
  "properties": {
    "addr:full":"8108 Mckendry Dr Metcalfe ON K0A 2P0",
    "addr:housenumber":"8108",
    "addr:postcode":"k0a 2p0",
    "addr:street":"Mckendry Dr",
    "iso:country":"CA",
    "sg:address":"8108 Mckendry Dr",
    "sg:city":"Metcalfe",
    "sg:classifiers":[
        {
            "category":"Personal",
            "subcategory":"Beauty Salon",
            "type":"Services"
        }
    ],
    "sg:phone":"+1 613 821 4095",
    "sg:postcode":"K0A 2P0",
    "sg:province":"ON",
    "wof:name":"Valley Salon",
    "wof:placetype":"venue"
},
  "geometry": {"coordinates":[-75.48281860349999,45.2353057861],"type":"Point"}
}