{
  "type": "Feature",
  "properties": {
    "addr:full":"160 Rue St Laurent Cookshire QC J0B 1M0",
    "addr:housenumber":"160",
    "addr:postcode":"j0b 1m0",
    "addr:street":"Rue St Laurent Cookshire",
    "iso:country":"CA",
    "sg:address":"160 Rue St Laurent",
    "sg:city":"Cookshire",
    "sg:classifiers":[
        {
            "category":"Manufacturing",
            "subcategory":"Printing",
            "type":"Manufacturing & Wholesale Goods"
        }
    ],
    "sg:phone":"+1 819 875 3163",
    "sg:postcode":"J0B 1M0",
    "sg:province":"QC",
    "sg:tags":[
        "printer"
    ],
    "wof:name":"Imprimerie Ml",
    "wof:placetype":"venue"
},
  "geometry": {"coordinates":[-71.63072200000001,45.414555],"type":"Point"}
}