{
  "type": "Feature",
  "properties": {
    "addr:full":"64 Dartford Pl Hamilton ON L8V 4M4",
    "addr:housenumber":"64",
    "addr:postcode":"l8v 4m4",
    "addr:street":"Dartford Pl",
    "iso:country":"CA",
    "sg:address":"64 Dartford Pl",
    "sg:city":"Hamilton",
    "sg:classifiers":[
        {
            "category":"Wholesale",
            "subcategory":"Auto Parts",
            "type":"Manufacturing & Wholesale Goods"
        }
    ],
    "sg:phone":"+1 905 575 5300",
    "sg:postcode":"L8V 4M4",
    "sg:province":"ON",
    "sg:tags":[
        "equipment",
        "truck"
    ],
    "wof:name":"Petrie Truck & Auto",
    "wof:placetype":"venue"
},
  "geometry": {"coordinates":[-79.85069300000001,43.217075],"type":"Point"}
}