{
  "type": "Feature",
  "properties": {
    "addr:full":"719 LA Ronge Ave LA Ronge SK S0J 1L0",
    "addr:housenumber":"719",
    "addr:postcode":"s0j 1l0",
    "addr:street":"La Ronge Ave",
    "iso:country":"CA",
    "sg:address":"719 LA Ronge Ave",
    "sg:city":"LA Ronge",
    "sg:classifiers":[
        {
            "category":"Food & Beverages",
            "subcategory":"Bakery",
            "type":"Retail Goods"
        }
    ],
    "sg:phone":"+1 306 425 3866",
    "sg:postcode":"S0J 1L0",
    "sg:province":"SK",
    "sg:tags":[
        "baker"
    ],
    "wof:name":"LA Ronge Bakery",
    "wof:placetype":"venue"
},
  "geometry": {"coordinates":[-105.295326,55.112495],"type":"Point"}
}