{
  "type": "Feature",
  "properties": {
    "addr:full":"639 Broadway Winnipeg MB R3C 0X2",
    "addr:housenumber":"639",
    "addr:postcode":"r3c 0x2",
    "addr:street":"Broadway",
    "iso:country":"CA",
    "sg:address":"639 Broadway",
    "sg:city":"Winnipeg",
    "sg:classifiers":[
        {
            "category":"Restaurant",
            "type":"Food & Drink"
        }
    ],
    "sg:phone":"+1 204 772 6969",
    "sg:postcode":"R3C 0X2",
    "sg:province":"MB",
    "wof:name":"Wanabees Diner",
    "wof:placetype":"venue"
},
  "geometry": {"coordinates":[-97.1566085815,49.8857803345],"type":"Point"}
}