{
  "type": "Feature",
  "properties": {
    "addr:full":"5055 Boul Metropolitain E Saint-Leonard QC H1R 1Z7",
    "addr:housenumber":"5055",
    "addr:postcode":"h1r 1z7",
    "addr:street":"Boul Metropolitain E",
    "iso:country":"CA",
    "sg:address":"5055 Boul Metropolitain E",
    "sg:city":"Saint-Leonard",
    "sg:classifiers":[
        {
            "category":"Insurance",
            "subcategory":"Insurance Agent",
            "type":"Services"
        }
    ],
    "sg:phone":"+1 514 327 8472",
    "sg:postcode":"H1R 1Z7",
    "sg:province":"QC",
    "wof:name":"L'Excellence CO D'Assurance",
    "wof:placetype":"venue"
},
  "geometry": {"coordinates":[-73.59148399999999,45.580189],"type":"Point"}
}