{
  "type": "Feature",
  "properties": {
    "iso:country":"CA",
    "sg:address":"5055 Boul Metropolitain E",
    "sg:city":"Saint-Leonard",
    "sg:classifiers":[
        {
            "category":"Insurance",
            "subcategory":"Insurance Agent",
            "type":"Services"
        }
    ],
    "sg:phone":"+1 514 327 8472",
    "sg:postcode":"H1R 1Z7",
    "sg:province":"QC",
    "wof:name":"L'Excellence CO D'Assurance",
    "wof:placetype":"venue"
},
  "geometry": {"coordinates":[-73.591484,45.580189],"type":"Point"}
}