{
  "type": "Feature",
  "properties": {
    "addr:full":"745 Boul Saint-Joseph Hull QC J8Y 4B7",
    "addr:housenumber":"745",
    "addr:postcode":"j8y 4b7",
    "addr:street":"Boul Saint-Joseph",
    "iso:country":"CA",
    "sg:address":"745 Boul Saint-Joseph",
    "sg:city":"Hull",
    "sg:classifiers":[
        {
            "category":"Insurance",
            "subcategory":"Insurance Agent",
            "type":"Services"
        }
    ],
    "sg:phone":"+1 819 778 7787",
    "sg:postcode":"J8Y 4B7",
    "sg:province":"QC",
    "wof:name":"Dale Parizeau Lm Inc",
    "wof:placetype":"venue"
},
  "geometry": {"coordinates":[-75.74243927000001,45.4580993652],"type":"Point"}
}