{
  "type": "Feature",
  "properties": {
    "addr:full":"Wing Rd RR 5 Thunder Bay ON P7C 5M9",
    "addr:postcode":"p7c 5m9",
    "addr:street":"Wing Rd;5",
    "iso:country":"CA",
    "sg:address":"Wing Rd RR 5",
    "sg:city":"Thunder Bay",
    "sg:classifiers":[
        {
            "category":"Building & Trades",
            "subcategory":"Construction",
            "type":"Services"
        }
    ],
    "sg:phone":"+1 807 939 2533",
    "sg:postcode":"P7C 5M9",
    "sg:province":"ON",
    "sg:tags":[
        "general",
        "contractor"
    ],
    "wof:name":"B J Halow & Son Constructors",
    "wof:placetype":"venue"
},
  "geometry": {"coordinates":[-89.245476,48.381699],"type":"Point"}
}