{
  "type": "Feature",
  "properties": {
    "addr:full":"205 Main St Biggar SK S0K 0M0",
    "addr:housenumber":"205",
    "addr:postcode":"s0k 0m0",
    "addr:street":"Main St",
    "iso:country":"CA",
    "sg:address":"205 Main St",
    "sg:city":"Biggar",
    "sg:classifiers":[
        {
            "category":"Shopping",
            "subcategory":"Pharmacy",
            "type":"Retail Goods"
        }
    ],
    "sg:phone":"+1 306 948 3397",
    "sg:postcode":"S0K 0M0",
    "sg:province":"SK",
    "wof:name":"Leslie's Drug Store",
    "wof:placetype":"venue"
},
  "geometry": {"coordinates":[-107.985924,52.055092],"type":"Point"}
}