{
  "type": "Feature",
  "properties": {
    "addr:full":"534 George St N Peterborough ON K9H 3S2",
    "addr:housenumber":"534",
    "addr:postcode":"k9h 3s2",
    "addr:street":"George St N",
    "iso:country":"CA",
    "sg:address":"534 George St N",
    "sg:city":"Peterborough",
    "sg:classifiers":[
        {
            "category":"Organizations",
            "subcategory":"Religious Organization",
            "type":"Services"
        }
    ],
    "sg:phone":"+1 705 876 7850",
    "sg:postcode":"K9H 3S2",
    "sg:province":"ON",
    "sg:tags":[
        "church"
    ],
    "wof:name":"Peterborough Presbytery United",
    "wof:placetype":"venue"
},
  "geometry": {"coordinates":[-78.32010650629999,44.3093147278],"type":"Point"}
}