{
  "type": "Feature",
  "properties": {
    "addr:full":"7080 River Rd # 208 Richmond BC V6X 1X5",
    "addr:housenumber":"7080;208",
    "addr:postcode":"v6x 1x5",
    "addr:street":"River Rd #",
    "iso:country":"CA",
    "sg:address":"7080 River Rd # 208",
    "sg:city":"Richmond",
    "sg:classifiers":[
        {
            "category":"Real Estate",
            "subcategory":"Real Estate Agent",
            "type":"Services"
        }
    ],
    "sg:phone":"+1 604 273 5200",
    "sg:postcode":"V6X 1X5",
    "sg:province":"BC",
    "wof:name":"Legend Real Estate Group Ltd",
    "wof:placetype":"venue"
},
  "geometry": {"coordinates":[-123.147880554,49.177318573],"type":"Point"}
}