{
  "type": "Feature",
  "properties": {
    "addr:full":"Calgary AB T2C 4E8",
    "addr:postcode":"t2c 4e8",
    "iso:country":"CA",
    "sg:city":"Calgary",
    "sg:classifiers":[
        {
            "category":"Shopping",
            "subcategory":"Stationery & Office Supplies",
            "type":"Retail Goods"
        }
    ],
    "sg:phone":"+1 403 236 3211",
    "sg:postcode":"T2C 4E8",
    "sg:province":"AB",
    "wof:name":"Lyreco Office Products",
    "wof:placetype":"venue"
},
  "geometry": {"coordinates":[-113.970275879,50.9918899536],"type":"Point"}
}