{
  "type": "Feature",
  "properties": {
    "iso:country":"CA",
    "sg:address":"5670 Boul Bourque",
    "sg:city":"Rock Forest",
    "sg:classifiers":[
        {
            "category":"Retail",
            "subcategory":"Auto Repair",
            "type":"Services"
        }
    ],
    "sg:phone":"+1 819 864 7925",
    "sg:postcode":"J1N 1H3",
    "sg:province":"QC",
    "sg:tags":[
        "repairing",
        "automobile"
    ],
    "wof:name":"J F Mecanique Plus",
    "wof:placetype":"venue"
},
  "geometry": {"coordinates":[-72.0051498413,45.3615455627],"type":"Point"}
}