{
  "type": "Feature",
  "properties": {
    "addr:full":"1346 Main St Winnipeg MB R2W 3T6",
    "addr:housenumber":"1346",
    "addr:postcode":"r2w 3t6",
    "addr:street":"Main St",
    "iso:country":"CA",
    "sg:address":"1346 Main St",
    "sg:city":"Winnipeg",
    "sg:classifiers":[
        {
            "category":"Building & Trades",
            "subcategory":"Plumbing",
            "type":"Services"
        }
    ],
    "sg:phone":"+1 204 582 3056",
    "sg:postcode":"R2W 3T6",
    "sg:province":"MB",
    "sg:tags":[
        "air",
        "conditioning",
        "furnace",
        "system",
        "contractor"
    ],
    "wof:name":"Tri-Star Hvac Ltd",
    "wof:placetype":"venue"
},
  "geometry": {"coordinates":[-97.1265258789,49.9237442017],"type":"Point"}
}