{
  "type": "Feature",
  "properties": {
    "addr:full":"Montreal QC H3H 2M6",
    "addr:postcode":"h3h 2m6",
    "iso:country":"CA",
    "sg:city":"Montreal",
    "sg:classifiers":[
        {
            "category":"Professional",
            "subcategory":"Secretarial Services",
            "type":"Services"
        }
    ],
    "sg:phone":"+1 514 933 8665",
    "sg:postcode":"H3H 2M6",
    "sg:province":"QC",
    "sg:tags":[
        "resume"
    ],
    "wof:name":"Profil Cv",
    "wof:placetype":"venue"
},
  "geometry": {"coordinates":[-73.584343,45.496315],"type":"Point"}
}