{
  "type": "Feature",
  "properties": {
    "addr:full":"2981 Dundas St W Toronto ON M6P 1Z4",
    "addr:housenumber":"2981",
    "addr:postcode":"m6p 1z4",
    "addr:street":"Dundas St W",
    "iso:country":"CA",
    "sg:address":"2981 Dundas St W",
    "sg:city":"Toronto",
    "sg:classifiers":[
        {
            "category":"Health Services",
            "subcategory":"Doctor",
            "type":"Services"
        }
    ],
    "sg:phone":"+1 416 769 5664",
    "sg:postcode":"M6P 1Z4",
    "sg:province":"ON",
    "sg:tags":[
        "dentist"
    ],
    "wof:name":"Miller, D DDS",
    "wof:placetype":"venue"
},
  "geometry": {"coordinates":[-79.4688034058,43.6653442383],"type":"Point"}
}