{
  "type": "Feature",
  "properties": {
    "iso:country":"CA",
    "sg:address":"19 Princess St",
    "sg:city":"Leamington",
    "sg:classifiers":[
        {
            "category":"Personal",
            "subcategory":"Beauty Salon",
            "type":"Services"
        }
    ],
    "sg:phone":"+1 519 326 9820",
    "sg:postcode":"N8H 2X8",
    "sg:province":"ON",
    "wof:name":"Coiffures By Salvatore",
    "wof:placetype":"venue"
},
  "geometry": {"coordinates":[-82.59851837159999,42.0526046753],"type":"Point"}
}