{
  "type": "Feature",
  "properties": {
    "addr:full":"26 William Kitchen Rd Scarborough ON M1P 5B7",
    "addr:housenumber":"26",
    "addr:postcode":"m1p 5b7",
    "addr:street":"William Kitchen Rd",
    "iso:country":"CA",
    "sg:address":"26 William Kitchen Rd",
    "sg:city":"Scarborough",
    "sg:classifiers":[
        {
            "category":"Shopping",
            "subcategory":"Music",
            "type":"Retail Goods"
        }
    ],
    "sg:phone":"+1 416 332 1722",
    "sg:postcode":"M1P 5B7",
    "sg:province":"ON",
    "sg:tags":[
        "compact",
        "record",
        "disc",
        "tape"
    ],
    "wof:name":"Deja Vu Discs",
    "wof:placetype":"venue"
},
  "geometry": {"coordinates":[-79.2794265747,43.7717475891],"type":"Point"}
}