{
  "type": "Feature",
  "properties": {
    "iso:country":"CA",
    "sg:address":"205 2nd St",
    "sg:city":"St Louis",
    "sg:classifiers":[
        {
            "category":"Education",
            "subcategory":"School",
            "type":"Public Place"
        }
    ],
    "sg:phone":"+1 306 422 8511",
    "sg:postcode":"S0J 2C0",
    "sg:province":"SK",
    "wof:name":"St Louis High School",
    "wof:placetype":"venue"
},
  "geometry": {"coordinates":[-105.811576843,52.920211792],"type":"Point"}
}