{
  "type": "Feature",
  "properties": {
    "addr:full":"Surrey BC V3W 8J9",
    "addr:postcode":"v3w 8j9",
    "iso:country":"CA",
    "sg:city":"Surrey",
    "sg:classifiers":[
        {
            "category":"Wholesale",
            "subcategory":"Machinery & Supplies",
            "type":"Manufacturing & Wholesale Goods"
        }
    ],
    "sg:phone":"+1 604 501 7756",
    "sg:postcode":"V3W 8J9",
    "sg:province":"BC",
    "sg:tags":[
        "salon",
        "beauty"
    ],
    "wof:name":"Fine Edge Salon Essentials",
    "wof:placetype":"venue"
},
  "geometry": {"coordinates":[-122.861961365,49.1540527344],"type":"Point"}
}