{
  "type": "Feature",
  "properties": {
    "addr:full":"2325 Hurontario St # 19 Mississauga ON L5A 4C7",
    "addr:housenumber":"2325",
    "addr:postcode":"l5a 4c7",
    "addr:street":"Hurontario St # 19",
    "iso:country":"CA",
    "sg:address":"2325 Hurontario St # 19",
    "sg:city":"Mississauga",
    "sg:classifiers":[
        {
            "category":"Wholesale",
            "subcategory":"Sporting Goods",
            "type":"Manufacturing & Wholesale Goods"
        }
    ],
    "sg:phone":"+1 905 281 9844",
    "sg:postcode":"L5A 4C7",
    "sg:province":"ON",
    "sg:tags":[
        "salon",
        "tanning"
    ],
    "wof:name":"Club Tan Premier Tanning Ctr",
    "wof:placetype":"venue"
},
  "geometry": {"coordinates":[-79.608521,43.574886],"type":"Point"}
}