{
  "type": "Feature",
  "properties": {
    "addr:full":"Paspebiac QC G0C 2K0",
    "addr:postcode":"g0c 2k0",
    "iso:country":"CA",
    "sg:city":"Paspebiac",
    "sg:classifiers":[
        {
            "category":"Shopping",
            "subcategory":"Clothing, Apparel, & Fashions",
            "type":"Retail Goods"
        }
    ],
    "sg:phone":"+1 418 752 5322",
    "sg:postcode":"G0C 2K0",
    "sg:province":"QC",
    "sg:tags":[
        "item",
        "boutique"
    ],
    "wof:name":"Boutique Signal Inc",
    "wof:placetype":"venue"
},
  "geometry": {"coordinates":[-65.237159729,48.0306053162],"type":"Point"}
}