{
  "type": "Feature",
  "properties": {
    "addr:full":"955 Edward St Prescott ON K0E 1T0",
    "addr:housenumber":"955",
    "addr:postcode":"k0e 1t0",
    "addr:street":"Edward St",
    "iso:country":"CA",
    "sg:address":"955 Edward St",
    "sg:city":"Prescott",
    "sg:classifiers":[
        {
            "category":"Restaurant",
            "type":"Food & Drink"
        }
    ],
    "sg:phone":"+1 613 925 1323",
    "sg:postcode":"K0E 1T0",
    "sg:province":"ON",
    "wof:name":"Burger King",
    "wof:placetype":"venue"
},
  "geometry": {"coordinates":[-75.52076721189999,44.7173652649],"type":"Point"}
}