{
  "type": "Feature",
  "properties": {
    "iso:country":"CA",
    "sg:address":"1392 Main St",
    "sg:city":"North Vancouver",
    "sg:classifiers":[
        {
            "category":"Utilities",
            "subcategory":"Mobile Phone",
            "type":"Services"
        }
    ],
    "sg:phone":"+1 604 990 8200",
    "sg:postcode":"V7J 1C6",
    "sg:province":"BC",
    "sg:tags":[
        "telephone",
        "cellular"
    ],
    "wof:name":"Innovative Telecom",
    "wof:placetype":"venue"
},
  "geometry": {"coordinates":[-123.099945068,49.272895813],"type":"Point"}
}