{
  "type": "Feature",
  "properties": {
    "addr:full":"198 Rue Saint-Joseph Levis QC G6V 1C9",
    "addr:housenumber":"198",
    "addr:postcode":"g6v 1c9",
    "addr:street":"Rue Saint-Joseph",
    "iso:country":"CA",
    "sg:address":"198 Rue Saint-Joseph",
    "sg:city":"Levis",
    "sg:classifiers":[
        {
            "category":"Social Services",
            "subcategory":"Child Care",
            "type":"Services"
        }
    ],
    "sg:phone":"+1 418 837 5111",
    "sg:postcode":"G6V 1C9",
    "sg:province":"QC",
    "wof:name":"Cpe LA Petite Grenouille",
    "wof:placetype":"venue"
},
  "geometry": {"coordinates":[-71.1690444946,46.823261261],"type":"Point"}
}