{
  "type": "Feature",
  "properties": {
    "iso:country":"CA",
    "sg:address":"3805 Hillbank Rd",
    "sg:city":"Duncan",
    "sg:classifiers":[
        {
            "category":"Wholesale",
            "subcategory":"Hardware",
            "type":"Manufacturing & Wholesale Goods"
        }
    ],
    "sg:phone":"+1 250 743 9050",
    "sg:postcode":"V9L 6M1",
    "sg:province":"BC",
    "sg:tags":[
        "beverage",
        "dispensing"
    ],
    "wof:name":"B C Artesian Springs Water",
    "wof:placetype":"venue"
},
  "geometry": {"coordinates":[-123.707382,48.779095],"type":"Point"}
}