{
  "type": "Feature",
  "properties": {
    "iso:country":"CA",
    "sg:address":"88 John St S",
    "sg:city":"Hamilton",
    "sg:classifiers":[
        {
            "category":"Real Estate",
            "subcategory":"Real Estate Agent",
            "type":"Services"
        }
    ],
    "sg:phone":"+1 905 527 8282",
    "sg:postcode":"L8N 2C1",
    "sg:province":"ON",
    "wof:name":"Catania Realty Ltd",
    "wof:placetype":"venue"
},
  "geometry": {"coordinates":[-79.86781311039999,43.2535362244],"type":"Point"}
}