{
  "type": "Feature",
  "properties": {
    "addr:full":"1200 Cedar Village Close North Vancouver BC V7J 3P3",
    "addr:housenumber":"1200",
    "addr:postcode":"v7j 3p3",
    "addr:street":"Cedar Village Close",
    "iso:country":"CA",
    "sg:address":"1200 Cedar Village Close",
    "sg:city":"North Vancouver",
    "sg:classifiers":[
        {
            "category":"Government",
            "subcategory":"Office",
            "type":"Public Place"
        }
    ],
    "sg:phone":"+1 604 904 6400",
    "sg:postcode":"V7J 3P3",
    "sg:province":"BC",
    "wof:name":"Residential Care Svc",
    "wof:placetype":"venue"
},
  "geometry": {"coordinates":[-123.04216003400001,49.3262329102],"type":"Point"}
}