{
  "type": "Feature",
  "properties": {
    "addr:full":"Surrey BC V3W 3E9",
    "addr:postcode":"v3w 3e9",
    "iso:country":"CA",
    "sg:city":"Surrey",
    "sg:classifiers":[
        {
            "category":"Building & Trades",
            "subcategory":"Plumbing",
            "type":"Services"
        }
    ],
    "sg:phone":"+1 604 590 8888",
    "sg:postcode":"V3W 3E9",
    "sg:province":"BC",
    "sg:tags":[
        "sheet",
        "work",
        "metal",
        "contractor"
    ],
    "wof:name":"J R Vent Ltd",
    "wof:placetype":"venue"
},
  "geometry": {"coordinates":[-122.87663999999999,49.151939],"type":"Point"}
}