{
  "type": "Feature",
  "properties": {
    "addr:full":"547 Eglinton Ave E Toronto ON M4P 1N7",
    "addr:housenumber":"547",
    "addr:postcode":"m4p 1n7",
    "addr:street":"Eglinton Ave E",
    "iso:country":"CA",
    "sg:address":"547 Eglinton Ave E",
    "sg:city":"Toronto",
    "sg:classifiers":[
        {
            "category":"Health Services",
            "subcategory":"Podiatrist",
            "type":"Services"
        }
    ],
    "sg:phone":"+1 416 488 7020",
    "sg:postcode":"M4P 1N7",
    "sg:province":"ON",
    "wof:name":"Walpole, Peter DPM",
    "wof:placetype":"venue"
},
  "geometry": {"coordinates":[-79.37911200000001,43.710518],"type":"Point"}
}