{
  "type": "Feature",
  "properties": {
    "addr:full":"Winnipeg MB R2H 2N9",
    "addr:postcode":"r2h 2n9",
    "iso:country":"CA",
    "sg:city":"Winnipeg",
    "sg:classifiers":[
        {
            "category":"Professional",
            "type":"Services"
        }
    ],
    "sg:phone":"+1 204 231 2142",
    "sg:postcode":"R2H 2N9",
    "sg:province":"MB",
    "sg:tags":[
        "arts",
        "artist"
    ],
    "wof:name":"Giffin Art Works",
    "wof:placetype":"venue"
},
  "geometry": {"coordinates":[-97.11116790769999,49.885597229],"type":"Point"}
}