{
  "type": "Feature",
  "properties": {
    "iso:country":"CA",
    "sg:address":"4 Henry St",
    "sg:city":"Dominion",
    "sg:classifiers":[
        {
            "category":"Building & Trades",
            "subcategory":"Construction",
            "type":"Services"
        }
    ],
    "sg:phone":"+1 902 849 9123",
    "sg:postcode":"B1G 1G5",
    "sg:province":"NS",
    "sg:tags":[
        "foundation",
        "concrete",
        "contractor"
    ],
    "wof:name":"DE Meyere's Cbj Construction",
    "wof:placetype":"venue"
},
  "geometry": {"coordinates":[-60.0238723755,46.208190918],"type":"Point"}
}