{
  "type": "Feature",
  "properties": {
    "addr:full":"904 Rue Du Belvedere Saint-Nicolas QC G7A 3V3",
    "addr:housenumber":"904",
    "addr:postcode":"g7a 3v3",
    "addr:street":"Rue Du Belvedere",
    "iso:country":"CA",
    "sg:address":"904 Rue Du Belvedere",
    "sg:city":"Saint-Nicolas",
    "sg:classifiers":[
        {
            "category":"Professional",
            "type":"Services"
        }
    ],
    "sg:phone":"+1 418 831 8987",
    "sg:postcode":"G7A 3V3",
    "sg:province":"QC",
    "sg:tags":[
        "consultant"
    ],
    "wof:name":"Envir'Eau Puits Inc",
    "wof:placetype":"venue"
},
  "geometry": {"coordinates":[-71.3548583984,46.7149772644],"type":"Point"}
}