{
  "type": "Feature",
  "properties": {
    "addr:full":"Saint-Louis-DE-France QC G8T 1G2",
    "addr:postcode":"g8t 1g2",
    "iso:country":"CA",
    "sg:city":"Saint-Louis-DE-France",
    "sg:classifiers":[
        {
            "category":"Autos & Motor Vehicles",
            "subcategory":"Boat Sales",
            "type":"Retail Goods"
        }
    ],
    "sg:phone":"+1 819 375 4385",
    "sg:postcode":"G8T 1G2",
    "sg:province":"QC",
    "sg:tags":[
        "canoe"
    ],
    "wof:name":"Canots Pasquinel Enr",
    "wof:placetype":"venue"
},
  "geometry": {"coordinates":[-72.581024,46.41383],"type":"Point"}
}