{
  "type": "Feature",
  "properties": {
    "addr:full":"Windsor NS B0N 2T0",
    "addr:postcode":"b0n 2t0",
    "iso:country":"CA",
    "sg:city":"Windsor",
    "sg:classifiers":[
        {
            "category":"Government",
            "subcategory":"Office",
            "type":"Public Place"
        }
    ],
    "sg:phone":"+1 902 798 2914",
    "sg:postcode":"B0N 2T0",
    "sg:province":"NS",
    "wof:name":"Canada West N S Regiment",
    "wof:placetype":"venue"
},
  "geometry": {"coordinates":[-64.1306762695,44.98985672],"type":"Point"}
}