{
  "type": "Feature",
  "properties": {
    "addr:full":"Edmonton AB T6A 0A1",
    "addr:postcode":"t6a 0a1",
    "iso:country":"CA",
    "sg:city":"Edmonton",
    "sg:classifiers":[
        {
            "category":"Shopping",
            "subcategory":"Clothing, Apparel, & Fashions",
            "type":"Retail Goods"
        }
    ],
    "sg:phone":"+1 780 490 4760",
    "sg:postcode":"T6A 0A1",
    "sg:province":"AB",
    "wof:name":"Kids R Special",
    "wof:placetype":"venue"
},
  "geometry": {"coordinates":[-113.42030334499999,53.538143158],"type":"Point"}
}