{
  "type": "Feature",
  "properties": {
    "addr:full":"Burnaby BC V5J 5B6",
    "addr:postcode":"v5j 5b6",
    "iso:country":"CA",
    "sg:city":"Burnaby",
    "sg:classifiers":[
        {
            "category":"Manufacturing",
            "subcategory":"Tools & Machinery",
            "type":"Manufacturing & Wholesale Goods"
        }
    ],
    "sg:phone":"+1 604 451 9166",
    "sg:postcode":"V5J 5B6",
    "sg:province":"BC",
    "sg:tags":[
        "machine",
        "shop",
        "plastic"
    ],
    "wof:name":"Pathway Design & Mfg",
    "wof:placetype":"venue"
},
  "geometry": {"coordinates":[-122.982506,49.21653],"type":"Point"}
}