{
  "type": "Feature",
  "properties": {
    "iso:country":"CA",
    "sg:city":"Montreal",
    "sg:classifiers":[
        {
            "category":"Professional",
            "subcategory":"Management & Consulting",
            "type":"Services"
        }
    ],
    "sg:phone":"+1 514 286 1021",
    "sg:postcode":"H2X 2V4",
    "sg:province":"QC",
    "sg:tags":[
        "consultant",
        "business"
    ],
    "wof:name":"Bernstein DE Lambre",
    "wof:placetype":"venue"
},
  "geometry": {"coordinates":[-73.57405853269999,45.5144691467],"type":"Point"}
}