{
  "type": "Feature",
  "properties": {
    "iso:country":"CA",
    "sg:address":"3649 Lake Shore Blvd W",
    "sg:city":"Etobicoke",
    "sg:classifiers":[
        {
            "category":"Personal",
            "subcategory":"Beauty Salon",
            "type":"Services"
        }
    ],
    "sg:phone":"+1 416 251 5123",
    "sg:postcode":"M8W 1P6",
    "sg:province":"ON",
    "wof:name":"Lee's Hair Stylist",
    "wof:placetype":"venue"
},
  "geometry": {"coordinates":[-79.53656768800001,43.5936470032],"type":"Point"}
}