{
  "type": "Feature",
  "properties": {
    "addr:full":"Cacouna QC G0L 1G0",
    "addr:postcode":"g0l 1g0",
    "iso:country":"CA",
    "sg:city":"Cacouna",
    "sg:classifiers":[
        {
            "category":"Wholesale",
            "subcategory":"Scrap",
            "type":"Manufacturing & Wholesale Goods"
        }
    ],
    "sg:phone":"+1 418 868 1515",
    "sg:postcode":"G0L 1G0",
    "sg:province":"QC",
    "sg:tags":[
        "metal",
        "iron"
    ],
    "wof:name":"Snf Cacouna Metal Inc",
    "wof:placetype":"venue"
},
  "geometry": {"coordinates":[-69.507698,47.909615],"type":"Point"}
}