{
  "type": "Feature",
  "properties": {
    "addr:full":"263 Rue Arsene Longueuil QC J4G 1N4",
    "addr:housenumber":"263",
    "addr:postcode":"j4g 1n4",
    "addr:street":"Rue Arsene",
    "iso:country":"CA",
    "sg:address":"263 Rue Arsene",
    "sg:city":"Longueuil",
    "sg:classifiers":[
        {
            "category":"Building & Trades",
            "subcategory":"Construction",
            "type":"Services"
        }
    ],
    "sg:phone":"+1 450 677 7772",
    "sg:postcode":"J4G 1N4",
    "sg:province":"QC",
    "sg:tags":[
        "general",
        "contractor"
    ],
    "wof:name":"Gendreau & Desjardins Inc",
    "wof:placetype":"venue"
},
  "geometry": {"coordinates":[-73.4739456177,45.5752830505],"type":"Point"}
}