{
  "type": "Feature",
  "properties": {
    "addr:full":"32 Elliot St New Westminster BC V3L 2K1",
    "addr:housenumber":"32",
    "addr:postcode":"v3l 2k1",
    "addr:street":"Elliot St",
    "iso:country":"CA",
    "sg:address":"32 Elliot St",
    "sg:city":"New Westminster",
    "sg:classifiers":[
        {
            "category":"Social Services",
            "type":"Services"
        }
    ],
    "sg:phone":"+1 604 526 4783",
    "sg:postcode":"V3L 2K1",
    "sg:province":"BC",
    "sg:tags":[
        "organization",
        "welfare"
    ],
    "wof:name":"Salvation Army",
    "wof:placetype":"venue"
},
  "geometry": {"coordinates":[-122.902275085,49.2070121765],"type":"Point"}
}