{
  "type": "Feature",
  "properties": {
    "iso:country":"CA",
    "sg:address":"340 Greenstone Dr",
    "sg:city":"Kamloops",
    "sg:classifiers":[
        {
            "category":"Manufacturing",
            "subcategory":"Lumber",
            "type":"Manufacturing & Wholesale Goods"
        }
    ],
    "sg:phone":"+1 250 851 9222",
    "sg:postcode":"V2C 1N7",
    "sg:province":"BC",
    "sg:tags":[
        "forester"
    ],
    "wof:name":"Thomas & Norwell Forestry",
    "wof:placetype":"venue"
},
  "geometry": {"coordinates":[-120.347686768,50.6692581177],"type":"Point"}
}