{
  "type": "Feature",
  "properties": {
    "addr:full":"Saint-Hubert QC J3Y 7G5",
    "addr:postcode":"j3y 7g5",
    "iso:country":"CA",
    "sg:city":"Saint-Hubert",
    "sg:classifiers":[
        {
            "category":"Organizations",
            "subcategory":"Professional Association",
            "type":"Services"
        }
    ],
    "sg:phone":"+1 450 462 4363",
    "sg:postcode":"J3Y 7G5",
    "sg:province":"QC",
    "wof:name":"Groupe D'Entraide Geme",
    "wof:placetype":"venue"
},
  "geometry": {"coordinates":[-73.42892456049999,45.5039482117],"type":"Point"}
}