{
  "type": "Feature",
  "properties": {
    "iso:country":"CA",
    "sg:address":"3377 Bathurst St",
    "sg:city":"North York",
    "sg:classifiers":[
        {
            "category":"Shopping",
            "subcategory":"Shoes",
            "type":"Retail Goods"
        }
    ],
    "sg:phone":"+1 416 398 4676",
    "sg:postcode":"M6A 2B8",
    "sg:province":"ON",
    "wof:name":"Kids Club Toronto",
    "wof:placetype":"venue"
},
  "geometry": {"coordinates":[-79.43110656739999,43.7260398865],"type":"Point"}
}