{
  "type": "Feature",
  "properties": {
    "addr:full":"St Catharines ON L2R 5J5",
    "addr:postcode":"l2r 5j5",
    "iso:country":"CA",
    "sg:city":"St Catharines",
    "sg:classifiers":[
        {
            "category":"Wholesale",
            "subcategory":"Machinery & Supplies",
            "type":"Manufacturing & Wholesale Goods"
        }
    ],
    "sg:phone":"+1 905 641 2818",
    "sg:postcode":"L2R 5J5",
    "sg:province":"ON",
    "sg:tags":[
        "equipment",
        "window",
        "cleaning"
    ],
    "wof:name":"Niagara Roof Anchors Inc",
    "wof:placetype":"venue"
},
  "geometry": {"coordinates":[-79.24797821040001,43.1559104919],"type":"Point"}
}