{
  "type": "Feature",
  "properties": {
    "addr:full":"Wainfleet ON L0S 1V0",
    "addr:postcode":"l0s 1v0",
    "iso:country":"CA",
    "sg:city":"Wainfleet",
    "sg:classifiers":[
        {
            "category":"Shopping",
            "subcategory":"Discount & Variety Stores",
            "type":"Retail Goods"
        }
    ],
    "sg:phone":"+1 905 899 1555",
    "sg:postcode":"L0S 1V0",
    "sg:province":"ON",
    "sg:tags":[
        "merchandise",
        "general"
    ],
    "wof:name":"Winger General Store",
    "wof:placetype":"venue"
},
  "geometry": {"coordinates":[-79.34906768800001,42.8909683228],"type":"Point"}
}