{
  "type": "Feature",
  "properties": {
    "iso:country":"CA",
    "sg:address":"193 Boul DE Quen N",
    "sg:city":"Alma",
    "sg:classifiers":[
        {
            "category":"Health Services",
            "subcategory":"Doctor",
            "type":"Services"
        }
    ],
    "sg:phone":"+1 418 668 3008",
    "sg:postcode":"G8B 5N4",
    "sg:province":"QC",
    "sg:tags":[
        "physician",
        "surgeon"
    ],
    "wof:name":"Poulin, Renald MD",
    "wof:placetype":"venue"
},
  "geometry": {"coordinates":[-71.6492156982,48.5555877686],"type":"Point"}
}