{
  "type": "Feature",
  "properties": {
    "addr:full":"14 Dunlop St W Barrie ON L4N 1A2",
    "addr:housenumber":"14",
    "addr:postcode":"l4n 1a2",
    "addr:street":"Dunlop St W",
    "iso:country":"CA",
    "sg:address":"14 Dunlop St W",
    "sg:city":"Barrie",
    "sg:classifiers":[
        {
            "category":"Shopping",
            "subcategory":"Clothing, Apparel, & Fashions",
            "type":"Retail Goods"
        }
    ],
    "sg:phone":"+1 705 737 2661",
    "sg:postcode":"L4N 1A2",
    "sg:province":"ON",
    "sg:tags":[
        "lingerie"
    ],
    "wof:name":"Sinfully Fun",
    "wof:placetype":"venue"
},
  "geometry": {"coordinates":[-79.6906051636,44.3891830444],"type":"Point"}
}