{
  "type": "Feature",
  "properties": {
    "addr:full":"476 Berford Lake Rd Wiarton ON N0H 2T0",
    "addr:housenumber":"476",
    "addr:postcode":"n0h 2t0",
    "addr:street":"Berford Lake Rd",
    "iso:country":"CA",
    "sg:address":"476 Berford Lake Rd",
    "sg:city":"Wiarton",
    "sg:classifiers":[
        {
            "category":"Building & Trades",
            "subcategory":"Cleaning & Sanitation",
            "type":"Services"
        }
    ],
    "sg:phone":"+1 519 534 5293",
    "sg:postcode":"N0H 2T0",
    "sg:province":"ON",
    "sg:tags":[
        "window",
        "janitor"
    ],
    "wof:name":"Professional Window Cleaning",
    "wof:placetype":"venue"
},
  "geometry": {"coordinates":[-81.139786,44.740135],"type":"Point"}
}