{
  "type": "Feature",
  "properties": {
    "addr:full":"239 Rang Sainte-Julie Notre-Dame-Des-Prairies QC J6E 7Y8",
    "addr:housenumber":"239",
    "addr:postcode":"j6e 7y8",
    "addr:street":"Rang Sainte-Julie",
    "iso:country":"CA",
    "sg:address":"239 Rang Sainte-Julie",
    "sg:city":"Notre-Dame-Des-Prairies",
    "sg:classifiers":[
        {
            "category":"Organizations",
            "subcategory":"Religious Organization",
            "type":"Services"
        }
    ],
    "sg:phone":"+1 450 759 3881",
    "sg:postcode":"J6E 7Y8",
    "sg:province":"QC",
    "sg:tags":[
        "house",
        "retreat"
    ],
    "wof:name":"Residence L'Oasis Sous Les Pin",
    "wof:placetype":"venue"
},
  "geometry": {"coordinates":[-73.448204,46.058376],"type":"Point"}
}