{
  "type": "Feature",
  "properties": {
    "addr:full":"Morinville AB T8R 1R3",
    "addr:postcode":"t8r 1r3",
    "iso:country":"CA",
    "sg:city":"Morinville",
    "sg:classifiers":[
        {
            "category":"Health Services",
            "subcategory":"Doctor",
            "type":"Services"
        }
    ],
    "sg:phone":"+1 780 939 5224",
    "sg:postcode":"T8R 1R3",
    "sg:province":"AB",
    "sg:tags":[
        "dentist"
    ],
    "wof:name":"Horricks, R D DDS",
    "wof:placetype":"venue"
},
  "geometry": {"coordinates":[-113.64463000000001,53.798264],"type":"Point"}
}