{
  "type": "Feature",
  "properties": {
    "addr:full":"108 Rue Mariette Saint-Alphonse-DE-Granby QC J0E 2A0",
    "addr:housenumber":"108",
    "addr:postcode":"j0e 2a0",
    "addr:street":"Rue Mariette",
    "iso:country":"CA",
    "sg:address":"108 Rue Mariette",
    "sg:city":"Saint-Alphonse-DE-Granby",
    "sg:classifiers":[
        {
            "category":"Professional",
            "subcategory":"Advertising",
            "type":"Services"
        }
    ],
    "sg:phone":"+1 450 372 3995",
    "sg:postcode":"J0E 2A0",
    "sg:province":"QC",
    "sg:tags":[
        "distribution",
        "importer"
    ],
    "wof:name":"Valliglobe Canada",
    "wof:placetype":"venue"
},
  "geometry": {"coordinates":[-72.7217712402,45.3979949951],"type":"Point"}
}