{
  "type": "Feature",
  "properties": {
    "addr:full":"161 Main St Wolfville NS B4P 1C2",
    "addr:housenumber":"161",
    "addr:postcode":"b4p 1c2",
    "addr:street":"Main St",
    "iso:country":"CA",
    "sg:address":"161 Main St",
    "sg:city":"Wolfville",
    "sg:classifiers":[
        {
            "category":"Real Estate",
            "subcategory":"Developer",
            "type":"Services"
        }
    ],
    "sg:phone":"+1 902 542 1400",
    "sg:postcode":"B4P 1C2",
    "sg:province":"NS",
    "sg:tags":[
        "management"
    ],
    "wof:name":"Chambers Developments Inc",
    "wof:placetype":"venue"
},
  "geometry": {"coordinates":[-64.3728256226,45.0900688171],"type":"Point"}
}