{
  "type": "Feature",
  "properties": {
    "addr:full":"58 Hampstead Rise NW Calgary AB T3A 6B5",
    "addr:housenumber":"58",
    "addr:postcode":"t3a 6b5",
    "addr:street":"Hampstead Rise Nw",
    "iso:country":"CA",
    "sg:address":"58 Hampstead Rise NW",
    "sg:city":"Calgary",
    "sg:classifiers":[
        {
            "category":"Building & Trades",
            "subcategory":"Construction",
            "type":"Services"
        }
    ],
    "sg:phone":"+1 403 226 7117",
    "sg:postcode":"T3A 6B5",
    "sg:province":"AB",
    "sg:tags":[
        "contractor"
    ],
    "wof:name":"Stanford Homes",
    "wof:placetype":"venue"
},
  "geometry": {"coordinates":[-114.135627747,51.1461868286],"type":"Point"}
}