{
  "type": "Feature",
  "properties": {
    "iso:country":"CA",
    "sg:city":"Charlesbourg",
    "sg:classifiers":[
        {
            "category":"Wholesale",
            "subcategory":"Meat",
            "type":"Manufacturing & Wholesale Goods"
        }
    ],
    "sg:phone":"+1 418 626 1511",
    "sg:postcode":"G1G 3Z4",
    "sg:province":"QC",
    "sg:tags":[
        "butchering"
    ],
    "wof:name":"Boucherie Robert Trudeau",
    "wof:placetype":"venue"
},
  "geometry": {"coordinates":[-71.2901763916,46.8843574524],"type":"Point"}
}