{
  "type": "Feature",
  "properties": {
    "addr:full":"421 Crois Du Colibri Rosemere QC J7A 4T8",
    "addr:housenumber":"421",
    "addr:postcode":"j7a 4t8",
    "addr:street":"Crois Du Colibri Rosemere",
    "iso:country":"CA",
    "sg:address":"421 Crois Du Colibri",
    "sg:city":"Rosemere",
    "sg:classifiers":[
        {
            "category":"Professional",
            "subcategory":"Detective & Security Services",
            "type":"Services"
        }
    ],
    "sg:phone":"+1 450 621 5259",
    "sg:postcode":"J7A 4T8",
    "sg:province":"QC",
    "sg:tags":[
        "burglary",
        "protective",
        "robbery"
    ],
    "wof:name":"Alarme Jl",
    "wof:placetype":"venue"
},
  "geometry": {"coordinates":[-73.799561,45.648121],"type":"Point"}
}