{
  "type": "Feature",
  "properties": {
    "addr:full":"67 Rue Audubon Port-Cartier QC G5B 1M7",
    "addr:housenumber":"67",
    "addr:postcode":"g5b 1m7",
    "addr:street":"Rue Audubon",
    "iso:country":"CA",
    "sg:address":"67 Rue Audubon",
    "sg:city":"Port-Cartier",
    "sg:classifiers":[
        {
            "category":"Education",
            "subcategory":"School",
            "type":"Public Place"
        }
    ],
    "sg:phone":"+1 418 766 2665",
    "sg:postcode":"G5B 1M7",
    "sg:province":"QC",
    "wof:name":"Riverview School",
    "wof:placetype":"venue"
},
  "geometry": {"coordinates":[-66.8611984253,50.0245857239],"type":"Point"}
}