{
  "type": "Feature",
  "properties": {
    "iso:country":"CA",
    "sg:address":"20255 64 Ave",
    "sg:city":"Langley",
    "sg:classifiers":[
        {
            "category":"Food & Beverages",
            "subcategory":"Groceries & Convenience Stores",
            "type":"Retail Goods"
        }
    ],
    "sg:phone":"+1 604 532 5988",
    "sg:postcode":"V2Y 1M9",
    "sg:province":"BC",
    "sg:tags":[
        "grocer"
    ],
    "wof:name":"Save-On-Foods & Drugs",
    "wof:placetype":"venue"
},
  "geometry": {"coordinates":[-122.661774,49.119099],"type":"Point"}
}