{
  "type": "Feature",
  "properties": {
    "addr:full":"278 Av Des Pecheurs Shippagan NB E8S 1J6",
    "addr:postcode":"e8s 1j6",
    "addr:street":"278 Av Des Pecheurs Shippagan",
    "iso:country":"CA",
    "sg:address":"278 Av Des Pecheurs",
    "sg:city":"Shippagan",
    "sg:classifiers":[
        {
            "category":"Organizations",
            "subcategory":"Professional Association",
            "type":"Services"
        }
    ],
    "sg:phone":"+1 506 336 1414",
    "sg:postcode":"E8S 1J6",
    "sg:province":"NB",
    "wof:name":"Frapp",
    "wof:placetype":"venue"
},
  "geometry": {"coordinates":[-64.70358299999999,47.742458],"type":"Point"}
}