{
  "type": "Feature",
  "properties": {
    "addr:full":"405 Parr St Winnipeg MB R2W 5G1",
    "addr:housenumber":"405",
    "addr:postcode":"r2w 5g1",
    "addr:street":"Parr St",
    "iso:country":"CA",
    "sg:address":"405 Parr St",
    "sg:city":"Winnipeg",
    "sg:classifiers":[
        {
            "category":"Organizations",
            "subcategory":"Membership Organization",
            "type":"Services"
        }
    ],
    "sg:phone":"+1 204 586 6367",
    "sg:postcode":"R2W 5G1",
    "sg:province":"MB",
    "wof:name":"Faraday School Parent Council",
    "wof:placetype":"venue"
},
  "geometry": {"coordinates":[-97.148552,49.925995],"type":"Point"}
}