{
  "type": "Feature",
  "properties": {
    "addr:full":"526 Rue Guilbault Mascouche QC J7L 3K9",
    "addr:housenumber":"526",
    "addr:postcode":"j7l 3k9",
    "addr:street":"Rue Guilbault",
    "iso:country":"CA",
    "sg:address":"526 Rue Guilbault",
    "sg:city":"Mascouche",
    "sg:classifiers":[
        {
            "category":"Retail",
            "subcategory":"Repair Shop",
            "type":"Services"
        }
    ],
    "sg:phone":"+1 450 477 8851",
    "sg:postcode":"J7L 3K9",
    "sg:province":"QC",
    "sg:tags":[
        "real estate",
        "welding"
    ],
    "wof:name":"Concept Inuk Inc",
    "wof:placetype":"venue"
},
  "geometry": {"coordinates":[-73.65211499999999,45.738369],"type":"Point"}
}