{
  "type": "Feature",
  "properties": {
    "iso:country":"CA",
    "sg:address":"4203 17A St SE",
    "sg:city":"Calgary",
    "sg:classifiers":[
        {
            "category":"Freight",
            "type":"Transportation"
        }
    ],
    "sg:phone":"+1 403 569 1615",
    "sg:postcode":"T2G 3X1",
    "sg:province":"AB",
    "sg:tags":[
        "mover"
    ],
    "wof:name":"P & W Moving",
    "wof:placetype":"venue"
},
  "geometry": {"coordinates":[-114.017936706,51.0173416138],"type":"Point"}
}