{
  "type": "Feature",
  "properties": {
    "addr:full":"11913 20th Ave Blairmore AB T0K 0E0",
    "addr:housenumber":"11913",
    "addr:postcode":"t0k 0e0",
    "addr:street":"20Th Ave",
    "iso:country":"CA",
    "sg:address":"11913 20th Ave",
    "sg:city":"Blairmore",
    "sg:classifiers":[
        {
            "category":"Restaurant",
            "type":"Food & Drink"
        }
    ],
    "sg:phone":"+1 403 562 2666",
    "sg:postcode":"T0K 0E0",
    "sg:province":"AB",
    "wof:name":"Kfc",
    "wof:placetype":"venue"
},
  "geometry": {"coordinates":[-114.450684,49.610291],"type":"Point"}
}