{
  "type": "Feature",
  "properties": {
    "addr:full":"49 Skagway Ave Scarborough ON M1M 3T9",
    "addr:housenumber":"49",
    "addr:postcode":"m1m 3t9",
    "addr:street":"Skagway Ave",
    "iso:country":"CA",
    "sg:address":"49 Skagway Ave",
    "sg:city":"Scarborough",
    "sg:classifiers":[
        {
            "category":"Manufacturing",
            "subcategory":"Rubber & Plastics",
            "type":"Manufacturing & Wholesale Goods"
        }
    ],
    "sg:phone":"+1 416 261 6118",
    "sg:postcode":"M1M 3T9",
    "sg:province":"ON",
    "sg:tags":[
        "mold",
        "maker"
    ],
    "wof:name":"Art Mould Plastics Ltd",
    "wof:placetype":"venue"
},
  "geometry": {"coordinates":[-79.24192810060001,43.7299957275],"type":"Point"}
}