{
  "type": "Feature",
  "properties": {
    "addr:full":"10809 97 Ave Grande Prairie AB T8V 4Y9",
    "addr:housenumber":"10809",
    "addr:postcode":"t8v 4y9",
    "addr:street":"97 Ave",
    "iso:country":"CA",
    "sg:address":"10809 97 Ave",
    "sg:city":"Grande Prairie",
    "sg:classifiers":[
        {
            "category":"Autos & Motor Vehicles",
            "subcategory":"Auto Supplies",
            "type":"Retail Goods"
        }
    ],
    "sg:phone":"+1 780 539 1733",
    "sg:postcode":"T8V 4Y9",
    "sg:province":"AB",
    "sg:tags":[
        "filter",
        "gas"
    ],
    "wof:name":"Globe Fire Extinguisher Shop",
    "wof:placetype":"venue"
},
  "geometry": {"coordinates":[-118.82321899999999,55.168411],"type":"Point"}
}