{
  "type": "Feature",
  "properties": {
    "addr:full":"100 Mile House BC V0K 2E0",
    "addr:postcode":"v0k 2e0",
    "iso:country":"CA",
    "sg:city":"100 Mile House",
    "sg:classifiers":[
        {
            "category":"Restaurant",
            "type":"Food & Drink"
        }
    ],
    "sg:phone":"+1 250 395 4026",
    "sg:postcode":"V0K 2E0",
    "sg:province":"BC",
    "wof:name":"Yummers",
    "wof:placetype":"venue"
},
  "geometry": {"coordinates":[-121.29737900000001,51.642132],"type":"Point"}
}