{
  "type": "Feature",
  "properties": {
    "addr:full":"181 March St Sault Ste Marie ON P6A 2Z6",
    "addr:housenumber":"181",
    "addr:postcode":"p6a 2z6",
    "addr:street":"March St",
    "iso:country":"CA",
    "sg:address":"181 March St",
    "sg:city":"Sault Ste Marie",
    "sg:classifiers":[
        {
            "category":"Professional",
            "subcategory":"Lawyer & Legal Services",
            "type":"Services"
        }
    ],
    "sg:phone":"+1 705 942 2580",
    "sg:postcode":"P6A 2Z6",
    "sg:province":"ON",
    "sg:tags":[
        "attorney"
    ],
    "wof:name":"Shamess, Carol A",
    "wof:placetype":"venue"
},
  "geometry": {"coordinates":[-84.33015441889999,46.5122795105],"type":"Point"}
}