{
  "type": "Feature",
  "properties": {
    "iso:country":"CA",
    "sg:address":"362 Bloor St W",
    "sg:city":"Toronto",
    "sg:classifiers":[
        {
            "category":"Retail",
            "subcategory":"Laundry & Dry Cleaning",
            "type":"Services"
        }
    ],
    "sg:phone":"+1 416 963 8743",
    "sg:postcode":"M5S 1X2",
    "sg:province":"ON",
    "sg:tags":[
        "cleaners"
    ],
    "wof:name":"Warmer Dry Cleaner",
    "wof:placetype":"venue"
},
  "geometry": {"coordinates":[-79.405487,43.666389],"type":"Point"}
}