{
  "type": "Feature",
  "properties": {
    "addr:full":"384 Richmond Rd Ottawa ON K2A 0E8",
    "addr:housenumber":"384",
    "addr:postcode":"k2a 0e8",
    "addr:street":"Richmond Rd",
    "iso:country":"CA",
    "sg:address":"384 Richmond Rd",
    "sg:city":"Ottawa",
    "sg:classifiers":[
        {
            "category":"Shopping",
            "subcategory":"Hobbies, Toys, & Games",
            "type":"Retail Goods"
        }
    ],
    "sg:phone":"+1 613 729 4998",
    "sg:postcode":"K2A 0E8",
    "sg:province":"ON",
    "sg:tags":[
        "craft",
        "supply"
    ],
    "wof:name":"Crafts Treasures",
    "wof:placetype":"venue"
},
  "geometry": {"coordinates":[-75.7557144165,45.3910751343],"type":"Point"}
}