{
  "type": "Feature",
  "properties": {
    "addr:full":"5925 Av DE Monkland # 104 Montreal QC H4A 1G7",
    "addr:housenumber":"5925",
    "addr:postcode":"h4a 1g7",
    "addr:street":"Av De Monkland # 104",
    "iso:country":"CA",
    "sg:address":"5925 Av DE Monkland # 104",
    "sg:city":"Montreal",
    "sg:classifiers":[
        {
            "category":"Professional",
            "subcategory":"Management & Consulting",
            "type":"Services"
        }
    ],
    "sg:phone":"+1 514 489 9800",
    "sg:postcode":"H4A 1G7",
    "sg:province":"QC",
    "sg:tags":[
        "consultant",
        "hospital"
    ],
    "wof:name":"Elder Dayle Inc",
    "wof:placetype":"venue"
},
  "geometry": {"coordinates":[-73.62610599999999,45.472206],"type":"Point"}
}