{
  "type": "Feature",
  "properties": {
    "iso:country":"CA",
    "sg:address":"411 Huronia Rd #5",
    "sg:city":"Barrie",
    "sg:classifiers":[
        {
            "category":"Shopping",
            "subcategory":"Bicycles & Sporting Goods",
            "type":"Retail Goods"
        }
    ],
    "sg:phone":"+1 705 721 5138",
    "sg:postcode":"L4N 9B3",
    "sg:province":"ON",
    "wof:name":"Trainers Choice Sports Med",
    "wof:placetype":"venue"
},
  "geometry": {"coordinates":[-79.664612,44.352036],"type":"Point"}
}