{
  "type": "Feature",
  "properties": {
    "addr:full":"RR 3 Campbellville ON L0P 1B0",
    "addr:postcode":"l0p 1b0",
    "addr:street":"Rr 3",
    "iso:country":"CA",
    "sg:address":"RR 3",
    "sg:city":"Campbellville",
    "sg:classifiers":[
        {
            "category":"Building & Trades",
            "subcategory":"Construction",
            "type":"Services"
        }
    ],
    "sg:phone":"+1 905 854 0401",
    "sg:postcode":"L0P 1B0",
    "sg:province":"ON",
    "sg:tags":[
        "excavating",
        "contractor"
    ],
    "wof:name":"Watson Excavating",
    "wof:placetype":"venue"
},
  "geometry": {"coordinates":[-79.983047,43.48774],"type":"Point"}
}