{
  "type": "Feature",
  "properties": {
    "addr:full":"190 Liberty Street InCentre Toronto M6K3L5",
    "addr:housenumber":"190",
    "addr:postcode":"m6k3l5",
    "addr:street":"Liberty Street",
    "iso:country":"CA",
    "sg:address":"190 Liberty Street InCentre",
    "sg:city":"Toronto",
    "sg:classifiers":[
        {
            "category":"Professional",
            "subcategory":"Computer Services",
            "type":"Services"
        }
    ],
    "sg:postcode":"M6K3L5",
    "sg:tags":[
        "incentives",
        "rewards",
        "employee-motivation"
    ],
    "sg:website":"http://www.iloverewards.com",
    "wof:name":"I Love Rewards",
    "wof:placetype":"venue"
},
  "geometry": {"coordinates":[-79.425455,43.637296],"type":"Point"}
}