{
  "type": "Feature",
  "properties": {
    "addr:full":"3422 Hill Ave Regina SK S4S 0W9",
    "addr:housenumber":"3422",
    "addr:postcode":"s4s 0w9",
    "addr:street":"Hill Ave",
    "iso:country":"CA",
    "sg:address":"3422 Hill Ave",
    "sg:city":"Regina",
    "sg:classifiers":[
        {
            "category":"Personal",
            "subcategory":"Beauty Salon",
            "type":"Services"
        }
    ],
    "sg:phone":"+1 306 584 3499",
    "sg:postcode":"S4S 0W9",
    "sg:province":"SK",
    "sg:tags":[
        "therapist",
        "massage"
    ],
    "wof:name":"Body Fixx Health Massage",
    "wof:placetype":"venue"
},
  "geometry": {"coordinates":[-104.630027771,50.4284210205],"type":"Point"}
}