{
  "type": "Feature",
  "properties": {
    "iso:country":"CA",
    "sg:address":"56 Regent St",
    "sg:city":"Fredericton",
    "sg:classifiers":[
        {
            "category":"Personal",
            "subcategory":"Barber",
            "type":"Services"
        }
    ],
    "sg:phone":"+1 506 457 6266",
    "sg:postcode":"E3B 3W4",
    "sg:province":"NB",
    "wof:name":"Clipperman Barber Shop",
    "wof:placetype":"venue"
},
  "geometry": {"coordinates":[-66.638939,45.960594],"type":"Point"}
}