{
  "type": "Feature",
  "properties": {
    "addr:full":"10740 181 St NW Edmonton AB T5S 1K8",
    "addr:housenumber":"10740",
    "addr:postcode":"t5s 1k8",
    "addr:street":"181 St Nw",
    "iso:country":"CA",
    "sg:address":"10740 181 St NW",
    "sg:city":"Edmonton",
    "sg:classifiers":[
        {
            "category":"Manufacturing",
            "subcategory":"Tools & Machinery",
            "type":"Manufacturing & Wholesale Goods"
        }
    ],
    "sg:phone":"+1 780 483 3132",
    "sg:postcode":"T5S 1K8",
    "sg:province":"AB",
    "sg:tags":[
        "coating"
    ],
    "wof:name":"Boundary Equipment CO Ltd",
    "wof:placetype":"venue"
},
  "geometry": {"coordinates":[-113.633460998,53.5539779663],"type":"Point"}
}