{
  "type": "Feature",
  "properties": {
    "iso:country":"CA",
    "sg:address":"222 Blake St",
    "sg:city":"Barrie",
    "sg:classifiers":[
        {
            "category":"Retail",
            "subcategory":"Auto Repair",
            "type":"Services"
        }
    ],
    "sg:phone":"+1 705 728 7411",
    "sg:postcode":"L4M 1K3",
    "sg:province":"ON",
    "sg:tags":[
        "repairing",
        "automobile"
    ],
    "wof:name":"Morrison Auto Svc",
    "wof:placetype":"venue"
},
  "geometry": {"coordinates":[-79.663651,44.395275],"type":"Point"}
}