{
  "type": "Feature",
  "properties": {
    "addr:full":"Richmond BC V6Y 1T8",
    "addr:postcode":"v6y 1t8",
    "iso:country":"CA",
    "sg:city":"Richmond",
    "sg:classifiers":[
        {
            "category":"Professional",
            "subcategory":"Employment Agencies",
            "type":"Services"
        }
    ],
    "sg:phone":"+1 604 270 7721",
    "sg:postcode":"V6Y 1T8",
    "sg:province":"BC",
    "sg:tags":[
        "opportunity"
    ],
    "wof:name":"Drs Vocational Svc",
    "wof:placetype":"venue"
},
  "geometry": {"coordinates":[-123.134407,49.166405],"type":"Point"}
}