{
  "type": "Feature",
  "properties": {
    "addr:full":"8496 Rue Lajeunesse Montreal QC H2P 2E6",
    "addr:housenumber":"8496",
    "addr:postcode":"h2p 2e6",
    "addr:street":"Rue Lajeunesse",
    "iso:country":"CA",
    "sg:address":"8496 Rue Lajeunesse",
    "sg:city":"Montreal",
    "sg:classifiers":[
        {
            "category":"Food & Beverages",
            "subcategory":"Groceries & Convenience Stores",
            "type":"Retail Goods"
        }
    ],
    "sg:phone":"+1 514 381 0202",
    "sg:postcode":"H2P 2E6",
    "sg:province":"QC",
    "wof:name":"Depanneur Pat-So",
    "wof:placetype":"venue"
},
  "geometry": {"coordinates":[-73.63446044920001,45.5453071594],"type":"Point"}
}