{
  "type": "Feature",
  "properties": {
    "addr:full":"355 Purves St North Sydney NS B2A 3V2",
    "addr:housenumber":"355",
    "addr:postcode":"b2a 3v2",
    "addr:street":"Purves St",
    "iso:country":"CA",
    "sg:address":"355 Purves St",
    "sg:city":"North Sydney",
    "sg:classifiers":[
        {
            "category":"Ferry",
            "type":"Transportation"
        }
    ],
    "sg:phone":"+1 902 794 5200",
    "sg:postcode":"B2A 3V2",
    "sg:province":"NS",
    "wof:name":"Marine Atlantic",
    "wof:placetype":"venue"
},
  "geometry": {"coordinates":[-60.242199,46.212688],"type":"Point"}
}