{
  "type": "Feature",
  "properties": {
    "addr:full":"289 Boul Saint-Francois S Lac-Des-Ecorces QC J0W 1H0",
    "addr:housenumber":"289",
    "addr:postcode":"j0w 1h0",
    "addr:street":"Boul Saint-Francois S Lac-Des-Ecorces",
    "iso:country":"CA",
    "sg:address":"289 Boul Saint-Francois S",
    "sg:city":"Lac-Des-Ecorces",
    "sg:classifiers":[
        {
            "category":"Food & Beverages",
            "subcategory":"Groceries & Convenience Stores",
            "type":"Retail Goods"
        }
    ],
    "sg:phone":"+1 819 585 3860",
    "sg:postcode":"J0W 1H0",
    "sg:province":"QC",
    "wof:name":"Depanneur Andre Enr",
    "wof:placetype":"venue"
},
  "geometry": {"coordinates":[-75.357643,46.555462],"type":"Point"}
}