{
  "type": "Feature",
  "properties": {
    "iso:country":"CA",
    "sg:address":"654 Mckay St",
    "sg:city":"Kingston",
    "sg:classifiers":[
        {
            "category":"Retail",
            "subcategory":"Auto Repair",
            "type":"Services"
        }
    ],
    "sg:phone":"+1 613 389 6585",
    "sg:postcode":"K7M 5V9",
    "sg:province":"ON",
    "sg:tags":[
        "repairing",
        "automobile"
    ],
    "wof:name":"Vic's Automotive Ltd",
    "wof:placetype":"venue"
},
  "geometry": {"coordinates":[-76.57680511469999,44.2445678711],"type":"Point"}
}