{
  "type": "Feature",
  "properties": {
    "iso:country":"CA",
    "sg:address":"230 21st St W",
    "sg:city":"North Vancouver",
    "sg:classifiers":[
        {
            "category":"Social Services",
            "subcategory":"Child Care",
            "type":"Services"
        }
    ],
    "sg:phone":"+1 604 988 0114",
    "sg:postcode":"V7M 1Z4",
    "sg:province":"BC",
    "wof:name":"Lonsdale Creek Day Care Ctr",
    "wof:placetype":"venue"
},
  "geometry": {"coordinates":[-123.077515,49.328491],"type":"Point"}
}