{
  "type": "Feature",
  "properties": {
    "addr:full":"230 21st St W North Vancouver BC V7M 1Z4",
    "addr:housenumber":"230",
    "addr:postcode":"v7m 1z4",
    "addr:street":"21St St W",
    "iso:country":"CA",
    "sg:address":"230 21st St W",
    "sg:city":"North Vancouver",
    "sg:classifiers":[
        {
            "category":"Social Services",
            "subcategory":"Child Care",
            "type":"Services"
        }
    ],
    "sg:phone":"+1 604 988 0114",
    "sg:postcode":"V7M 1Z4",
    "sg:province":"BC",
    "wof:name":"Lonsdale Creek Day Care Ctr",
    "wof:placetype":"venue"
},
  "geometry": {"coordinates":[-123.07751500000001,49.328491],"type":"Point"}
}