{
  "type": "Feature",
  "properties": {
    "addr:full":"Edmonton AB T5J 2C3",
    "addr:postcode":"t5j 2c3",
    "iso:country":"CA",
    "sg:city":"Edmonton",
    "sg:classifiers":[
        {
            "category":"Government",
            "subcategory":"Office",
            "type":"Public Place"
        }
    ],
    "sg:phone":"+1 780 496 5244",
    "sg:postcode":"T5J 2C3",
    "sg:province":"AB",
    "sg:tags":[
        "village"
    ],
    "wof:name":"Edmonton Taxi Cab Commission",
    "wof:placetype":"venue"
},
  "geometry": {"coordinates":[-113.4907,53.544563],"type":"Point"}
}