{
  "type": "Feature",
  "properties": {
    "iso:country":"CA",
    "sg:address":"880 Rue Longpre",
    "sg:city":"Sherbrooke",
    "sg:classifiers":[
        {
            "category":"Manufacturing",
            "subcategory":"Apparel",
            "type":"Manufacturing & Wholesale Goods"
        }
    ],
    "sg:phone":"+1 819 562 7772",
    "sg:postcode":"J1G 5B9",
    "sg:province":"QC",
    "sg:tags":[
        "sewing",
        "contractor"
    ],
    "wof:name":"Troisieme Division Inc",
    "wof:placetype":"venue"
},
  "geometry": {"coordinates":[-71.8585510254,45.394569397],"type":"Point"}
}