{
  "type": "Feature",
  "properties": {
    "addr:full":"Bowden AB T0M 0K0",
    "addr:postcode":"t0m 0k0",
    "iso:country":"CA",
    "sg:city":"Bowden",
    "sg:classifiers":[
        {
            "category":"Personal",
            "subcategory":"Beauty Salon",
            "type":"Services"
        }
    ],
    "sg:phone":"+1 403 224 2005",
    "sg:postcode":"T0M 0K0",
    "sg:province":"AB",
    "wof:name":"Snippers",
    "wof:placetype":"venue"
},
  "geometry": {"coordinates":[-114.034386,51.932636],"type":"Point"}
}