{
  "type": "Feature",
  "properties": {
    "addr:full":"Patricia AB T0J 2K0",
    "addr:postcode":"t0j 2k0",
    "iso:country":"CA",
    "sg:city":"Patricia",
    "sg:classifiers":[
        {
            "category":"Travel",
            "subcategory":"Hotels & Motels",
            "type":"Entertainment"
        }
    ],
    "sg:phone":"+1 403 378 4647",
    "sg:postcode":"T0J 2K0",
    "sg:province":"AB",
    "wof:name":"Patricia Hotel",
    "wof:placetype":"venue"
},
  "geometry": {"coordinates":[-111.67698669400001,50.7011108398],"type":"Point"}
}