{
  "type": "Feature",
  "properties": {
    "addr:full":"4333 Spinningdale Crt Mississauga ON L5M 3J9",
    "addr:housenumber":"4333",
    "addr:postcode":"l5m 3j9",
    "addr:street":"Spinningdale Crt",
    "iso:country":"CA",
    "sg:address":"4333 Spinningdale Crt",
    "sg:city":"Mississauga",
    "sg:classifiers":[
        {
            "category":"Building & Trades",
            "subcategory":"Cleaning & Sanitation",
            "type":"Services"
        }
    ],
    "sg:phone":"+1 905 826 0034",
    "sg:postcode":"L5M 3J9",
    "sg:province":"ON",
    "sg:tags":[
        "janitor"
    ],
    "wof:name":"O K Soji",
    "wof:placetype":"venue"
},
  "geometry": {"coordinates":[-79.68013000000001,43.570091],"type":"Point"}
}