{
  "type": "Feature",
  "properties": {
    "addr:full":"444 Campbell St Tofino BC V0R 2Z0",
    "addr:housenumber":"444",
    "addr:postcode":"v0r 2z0",
    "addr:street":"Campbell St",
    "iso:country":"CA",
    "sg:address":"444 Campbell St",
    "sg:city":"Tofino",
    "sg:classifiers":[
        {
            "category":"Shopping",
            "subcategory":"Bicycles & Sporting Goods",
            "type":"Retail Goods"
        }
    ],
    "sg:phone":"+1 250 725 3344",
    "sg:postcode":"V0R 2Z0",
    "sg:province":"BC",
    "sg:tags":[
        "surfboard"
    ],
    "wof:name":"Storm the Tofino Surf Shop",
    "wof:placetype":"venue"
},
  "geometry": {"coordinates":[-125.903587,49.152691],"type":"Point"}
}