{
  "type": "Feature",
  "properties": {
    "addr:full":"Farm Bengough SK S0C 0K0",
    "addr:postcode":"s0c 0k0",
    "iso:country":"CA",
    "sg:address":"Farm",
    "sg:city":"Bengough",
    "sg:classifiers":[
        {
            "category":"Freight",
            "type":"Transportation"
        }
    ],
    "sg:phone":"+1 306 268 4375",
    "sg:postcode":"S0C 0K0",
    "sg:province":"SK",
    "sg:tags":[
        "trucking"
    ],
    "wof:name":"Tuffy's Transport",
    "wof:placetype":"venue"
},
  "geometry": {"coordinates":[-105.12273407000001,49.3972854614],"type":"Point"}
}