{
  "type": "Feature",
  "properties": {
    "addr:full":"6164 9th Line Egbert ON L0L 1N0",
    "addr:housenumber":"6164",
    "addr:postcode":"l0l 1n0",
    "addr:street":"9Th Line",
    "iso:country":"CA",
    "sg:address":"6164 9th Line",
    "sg:city":"Egbert",
    "sg:classifiers":[
        {
            "category":"Building & Trades",
            "subcategory":"Construction",
            "type":"Services"
        }
    ],
    "sg:phone":"+1 705 458 4090",
    "sg:postcode":"L0L 1N0",
    "sg:province":"ON",
    "sg:tags":[
        "marking",
        "parking",
        "lawn",
        "maintenance",
        "grounds"
    ],
    "wof:name":"S J Landscape",
    "wof:placetype":"venue"
},
  "geometry": {"coordinates":[-79.75973500000001,44.228436],"type":"Point"}
}