{
  "type": "Feature",
  "properties": {
    "iso:country":"CA",
    "sg:address":"293 Rayette Rd",
    "sg:city":"Concord",
    "sg:classifiers":[
        {
            "category":"Organizations",
            "subcategory":"Membership Organization",
            "type":"Services"
        }
    ],
    "sg:phone":"+1 905 761 2139",
    "sg:postcode":"L4K 2G1",
    "sg:province":"ON",
    "wof:name":"Vaughan in Action",
    "wof:placetype":"venue"
},
  "geometry": {"coordinates":[-79.49806976319999,43.8117790222],"type":"Point"}
}