{
  "type": "Feature",
  "properties": {
    "iso:country":"CA",
    "sg:address":"42285 Yarrow Central Rd",
    "sg:city":"Chilliwack",
    "sg:classifiers":[
        {
            "category":"Organizations",
            "subcategory":"Religious Organization",
            "type":"Services"
        }
    ],
    "sg:phone":"+1 604 823 7340",
    "sg:postcode":"V2R 5E3",
    "sg:province":"BC",
    "sg:tags":[
        "church"
    ],
    "wof:name":"Canadian Reformed Churches",
    "wof:placetype":"venue"
},
  "geometry": {"coordinates":[-122.054130554,49.0822219849],"type":"Point"}
}