{
  "type": "Feature",
  "properties": {
    "addr:full":"160 10th Ave Campbell River BC V9W 4E3",
    "addr:housenumber":"160",
    "addr:postcode":"v9w 4e3",
    "addr:street":"10Th Ave",
    "iso:country":"CA",
    "sg:address":"160 10th Ave",
    "sg:city":"Campbell River",
    "sg:classifiers":[
        {
            "category":"Professional",
            "subcategory":"Computer Services",
            "type":"Services"
        }
    ],
    "sg:phone":"+1 250 337 2064",
    "sg:postcode":"V9W 4E3",
    "sg:province":"BC",
    "sg:tags":[
        "repair",
        "dealer",
        "equipment"
    ],
    "wof:name":"Island Micro Systems",
    "wof:placetype":"venue"
},
  "geometry": {"coordinates":[-125.24514000000001,50.025497],"type":"Point"}
}