{
  "type": "Feature",
  "properties": {
    "addr:full":"4270 Ponderosa Cres Victoria BC V8Z 7H3",
    "addr:housenumber":"4270",
    "addr:postcode":"v8z 7h3",
    "addr:street":"Ponderosa Cres",
    "iso:country":"CA",
    "sg:address":"4270 Ponderosa Cres",
    "sg:city":"Victoria",
    "sg:classifiers":[
        {
            "category":"Real Estate",
            "subcategory":"Real Estate Agent",
            "type":"Services"
        }
    ],
    "sg:phone":"+1 250 727 7219",
    "sg:postcode":"V8Z 7H3",
    "sg:province":"BC",
    "sg:tags":[
        "cooperative"
    ],
    "wof:name":"Krisineleos CO-OP Housing Assn",
    "wof:placetype":"venue"
},
  "geometry": {"coordinates":[-123.364517212,48.428314209],"type":"Point"}
}