{
  "type": "Feature",
  "properties": {
    "addr:full":"72521 Airport Line Hensall ON N0M 1X0",
    "addr:housenumber":"72521",
    "addr:postcode":"n0m 1x0",
    "addr:street":"Airport Line",
    "iso:country":"CA",
    "sg:address":"72521 Airport Line",
    "sg:city":"Hensall",
    "sg:classifiers":[
        {
            "category":"Autos & Motor Vehicles",
            "subcategory":"Automobile Sales",
            "type":"Retail Goods"
        }
    ],
    "sg:phone":"+1 519 263 6142",
    "sg:postcode":"N0M 1X0",
    "sg:province":"ON",
    "sg:tags":[
        "parts",
        "snowmobile",
        "accessory"
    ],
    "wof:name":"Elder Enterprises",
    "wof:placetype":"venue"
},
  "geometry": {"coordinates":[-81.502083,43.434174],"type":"Point"}
}