{
  "type": "Feature",
  "properties": {
    "addr:full":"Edmonton AB T5X 3Y7",
    "addr:postcode":"t5x 3y7",
    "iso:country":"CA",
    "sg:city":"Edmonton",
    "sg:classifiers":[
        {
            "category":"Retail",
            "subcategory":"Laundry & Dry Cleaning",
            "type":"Services"
        }
    ],
    "sg:phone":"+1 780 456 7146",
    "sg:postcode":"T5X 3Y7",
    "sg:province":"AB",
    "sg:tags":[
        "cleaners"
    ],
    "wof:name":"Castledowns Cleanitizing",
    "wof:placetype":"venue"
},
  "geometry": {"coordinates":[-113.516540527,53.6157569885],"type":"Point"}
}