{
  "type": "Feature",
  "properties": {
    "addr:full":"Mississauga ON L5A 3K6",
    "addr:postcode":"l5a 3k6",
    "iso:country":"CA",
    "sg:city":"Mississauga",
    "sg:classifiers":[
        {
            "category":"Building & Trades",
            "subcategory":"Electrical",
            "type":"Services"
        }
    ],
    "sg:phone":"+1 905 896 3401",
    "sg:postcode":"L5A 3K6",
    "sg:province":"ON",
    "sg:tags":[
        "electric",
        "contractor"
    ],
    "wof:name":"Bryant Electric Inc",
    "wof:placetype":"venue"
},
  "geometry": {"coordinates":[-79.59586299999999,43.591621],"type":"Point"}
}