{
  "type": "Feature",
  "properties": {
    "addr:full":"18 Cromer Ave Grand Falls-Windsor NL A2A 1X2",
    "addr:housenumber":"18",
    "addr:postcode":"a2a 1x2",
    "addr:street":"Cromer Ave",
    "iso:country":"CA",
    "sg:address":"18 Cromer Ave",
    "sg:city":"Grand Falls-Windsor",
    "sg:classifiers":[
        {
            "category":"Retail",
            "subcategory":"Auto Repair",
            "type":"Services"
        }
    ],
    "sg:phone":"+1 709 489 5628",
    "sg:postcode":"A2A 1X2",
    "sg:province":"NL",
    "sg:tags":[
        "repairing",
        "automobile",
        "tire"
    ],
    "wof:name":"City Tire & Automotive",
    "wof:placetype":"venue"
},
  "geometry": {"coordinates":[-55.6538467407,48.9539527893],"type":"Point"}
}