{
  "type": "Feature",
  "properties": {
    "iso:country":"CA",
    "sg:address":"20 Waapstan",
    "sg:city":"Mistissini",
    "sg:classifiers":[
        {
            "category":"Taxi",
            "type":"Transportation"
        }
    ],
    "sg:phone":"+1 418 923 3777",
    "sg:postcode":"G0W 1C0",
    "sg:province":"QC",
    "sg:tags":[
        "taxicab"
    ],
    "wof:name":"Meeyobin Taxi",
    "wof:placetype":"venue"
},
  "geometry": {"coordinates":[-73.8604812622,50.4130210876],"type":"Point"}
}