{
  "type": "Feature",
  "properties": {
    "iso:country":"CA",
    "sg:city":"Calgary",
    "sg:classifiers":[
        {
            "category":"Shopping",
            "subcategory":"News",
            "type":"Retail Goods"
        }
    ],
    "sg:phone":"+1 403 241 6066",
    "sg:postcode":"T3G 3T2",
    "sg:province":"AB",
    "sg:tags":[
        "magazine"
    ],
    "wof:name":"Calgary's Child Magazine",
    "wof:placetype":"venue"
},
  "geometry": {"coordinates":[-114.197608948,51.1270446777],"type":"Point"}
}