{
  "type": "Feature",
  "properties": {
    "addr:full":"10 Rue Jean-Talon Saint-Luc QC J2W 1P2",
    "addr:housenumber":"10",
    "addr:postcode":"j2w 1p2",
    "addr:street":"Rue Jean-Talon",
    "iso:country":"CA",
    "sg:address":"10 Rue Jean-Talon",
    "sg:city":"Saint-Luc",
    "sg:classifiers":[
        {
            "category":"Bus Charters",
            "type":"Transportation"
        }
    ],
    "sg:phone":"+1 450 348 3535",
    "sg:postcode":"J2W 1P2",
    "sg:province":"QC",
    "sg:tags":[
        "line",
        "rental"
    ],
    "wof:name":"Guy Dolbec & Fils Inc",
    "wof:placetype":"venue"
},
  "geometry": {"coordinates":[-73.266853,45.341408],"type":"Point"}
}