{
  "type": "Feature",
  "properties": {
    "addr:full":"53 Commercial Pl Thompson MB R8N 1T1",
    "addr:housenumber":"53",
    "addr:postcode":"r8n 1t1",
    "addr:street":"Commercial Pl",
    "iso:country":"CA",
    "sg:address":"53 Commercial Pl",
    "sg:city":"Thompson",
    "sg:classifiers":[
        {
            "category":"Insurance",
            "subcategory":"Insurance Agent",
            "type":"Services"
        }
    ],
    "sg:phone":"+1 204 677 1400",
    "sg:postcode":"R8N 1T1",
    "sg:province":"MB",
    "wof:name":"Manitoba Public Insurance Corp",
    "wof:placetype":"venue"
},
  "geometry": {"coordinates":[-97.8446731567,55.7462005615],"type":"Point"}
}