{
  "type": "Feature",
  "properties": {
    "iso:country":"CA",
    "sg:address":"1360 Pembina Hwy",
    "sg:city":"Winnipeg",
    "sg:classifiers":[
        {
            "category":"Education",
            "subcategory":"Library",
            "type":"Public Place"
        }
    ],
    "sg:phone":"+1 204 986 4918",
    "sg:postcode":"R3T 2B4",
    "sg:province":"MB",
    "wof:name":"Fort Garry Branch Library",
    "wof:placetype":"venue"
},
  "geometry": {"coordinates":[-97.151604,49.839478],"type":"Point"}
}