{
  "type": "Feature",
  "properties": {
    "addr:full":"Cedar Point ON L0K 1C0",
    "addr:postcode":"l0k 1c0",
    "iso:country":"CA",
    "sg:city":"Cedar Point",
    "sg:classifiers":[
        {
            "category":"Social Services",
            "type":"Services"
        }
    ],
    "sg:phone":"+1 705 247 2128",
    "sg:postcode":"L0K 1C0",
    "sg:province":"ON",
    "sg:tags":[
        "senior",
        "citizen"
    ],
    "wof:name":"Seniors Rec Ctr",
    "wof:placetype":"venue"
},
  "geometry": {"coordinates":[-80.114403,44.809227],"type":"Point"}
}