{
  "type": "Feature",
  "properties": {
    "iso:country":"CA",
    "sg:address":"325 Renfrew Dr",
    "sg:city":"Markham",
    "sg:classifiers":[
        {
            "category":"Professional",
            "subcategory":"Accounting & Tax Preparation",
            "type":"Services"
        }
    ],
    "sg:phone":"+1 905 475 1895",
    "sg:postcode":"L3R 9S8",
    "sg:province":"ON",
    "sg:tags":[
        "accountant"
    ],
    "wof:name":"Gedir, Earl C CA",
    "wof:placetype":"venue"
},
  "geometry": {"coordinates":[-79.3658294678,43.8622589111],"type":"Point"}
}