{
  "type": "Feature",
  "properties": {
    "addr:full":"735 Wonderland Rd N # 22 London ON N6H 4L1",
    "addr:housenumber":"735",
    "addr:postcode":"n6h 4l1",
    "addr:street":"Wonderland Rd N # 22",
    "iso:country":"CA",
    "sg:address":"735 Wonderland Rd N # 22",
    "sg:city":"London",
    "sg:classifiers":[
        {
            "category":"Food & Beverages",
            "subcategory":"Meat & Fish",
            "type":"Retail Goods"
        }
    ],
    "sg:phone":"+1 519 473 0999",
    "sg:postcode":"N6H 4L1",
    "sg:province":"ON",
    "sg:tags":[
        "frozen"
    ],
    "wof:name":"M & M Meat Shops",
    "wof:placetype":"venue"
},
  "geometry": {"coordinates":[-81.295013,42.988838],"type":"Point"}
}