{
  "type": "Feature",
  "properties": {
    "addr:full":"1362 4E Rang Saint-Gabriel-DE-Brandon QC J0K 2N0",
    "addr:housenumber":"1362",
    "addr:postcode":"j0k 2n0",
    "addr:street":"4E Rang",
    "iso:country":"CA",
    "sg:address":"1362 4E Rang",
    "sg:city":"Saint-Gabriel-DE-Brandon",
    "sg:classifiers":[
        {
            "category":"Shopping",
            "subcategory":"Bicycles & Sporting Goods",
            "type":"Retail Goods"
        }
    ],
    "sg:phone":"+1 450 835 7345",
    "sg:postcode":"J0K 2N0",
    "sg:province":"QC",
    "sg:tags":[
        "bait",
        "fishing"
    ],
    "wof:name":"Appats St-Gabriel",
    "wof:placetype":"venue"
},
  "geometry": {"coordinates":[-73.381607,46.29126],"type":"Point"}
}