{
  "type": "Feature",
  "properties": {
    "addr:full":"80 Ewen Rd Hamilton ON L8S 3C5",
    "addr:housenumber":"80",
    "addr:postcode":"l8s 3c5",
    "addr:street":"Ewen Rd",
    "iso:country":"CA",
    "sg:address":"80 Ewen Rd",
    "sg:city":"Hamilton",
    "sg:classifiers":[
        {
            "category":"Organizations",
            "subcategory":"Religious Organization",
            "type":"Services"
        }
    ],
    "sg:phone":"+1 905 528 2275",
    "sg:postcode":"L8S 3C5",
    "sg:province":"ON",
    "sg:tags":[
        "church"
    ],
    "wof:name":"Christadelphian's Church",
    "wof:placetype":"venue"
},
  "geometry": {"coordinates":[-79.9313049316,43.2539405823],"type":"Point"}
}