{
  "type": "Feature",
  "properties": {
    "addr:full":"RR 1 STN A Kingston ON K7P 2Y7",
    "addr:postcode":"k7p 2y7",
    "addr:street":"Rr 1 Stn A",
    "iso:country":"CA",
    "sg:address":"RR 1 STN A",
    "sg:city":"Kingston",
    "sg:classifiers":[
        {
            "category":"Building & Trades",
            "subcategory":"Landscaping Services",
            "type":"Services"
        }
    ],
    "sg:phone":"+1 613 384 1196",
    "sg:postcode":"K7P 2Y7",
    "sg:province":"ON",
    "sg:tags":[
        "landscape",
        "contractor"
    ],
    "wof:name":"Zomer & Sons Landscaping Ltd",
    "wof:placetype":"venue"
},
  "geometry": {"coordinates":[-76.479332,44.231537],"type":"Point"}
}