{
  "type": "Feature",
  "properties": {
    "iso:country":"CA",
    "sg:address":"114 Nelson St W",
    "sg:city":"Virden",
    "sg:classifiers":[
        {
            "category":"Travel",
            "subcategory":"Hotels & Motels",
            "type":"Entertainment"
        }
    ],
    "sg:phone":"+1 204 748 2677",
    "sg:postcode":"R0M 2C0",
    "sg:province":"MB",
    "wof:name":"Alexandra Hotel",
    "wof:placetype":"venue"
},
  "geometry": {"coordinates":[-100.919715881,49.8560256958],"type":"Point"}
}