{
  "type": "Feature",
  "properties": {
    "addr:full":"6835 Rue Bombardier Saint-Leonard QC H1P 3A1",
    "addr:housenumber":"6835",
    "addr:postcode":"h1p 3a1",
    "addr:street":"Rue Bombardier",
    "iso:country":"CA",
    "sg:address":"6835 Rue Bombardier",
    "sg:city":"Saint-Leonard",
    "sg:classifiers":[
        {
            "category":"Real Estate",
            "subcategory":"Real Estate Agent",
            "type":"Services"
        }
    ],
    "sg:phone":"+1 514 955 0000",
    "sg:postcode":"H1P 3A1",
    "sg:province":"QC",
    "wof:name":"Services Immobiliers Terrex",
    "wof:placetype":"venue"
},
  "geometry": {"coordinates":[-73.5904159546,45.6036758423],"type":"Point"}
}