{
  "type": "Feature",
  "properties": {
    "addr:full":"4736 Sheppard Ave E # 3 Scarborough ON M1S 3V6",
    "addr:housenumber":"4736",
    "addr:postcode":"m1s 3v6",
    "addr:street":"Sheppard Ave E # 3",
    "iso:country":"CA",
    "sg:address":"4736 Sheppard Ave E # 3",
    "sg:city":"Scarborough",
    "sg:classifiers":[
        {
            "category":"Retail",
            "subcategory":"Car Wash",
            "type":"Services"
        }
    ],
    "sg:phone":"+1 416 299 1383",
    "sg:postcode":"M1S 3V6",
    "sg:province":"ON",
    "sg:tags":[
        "polishing",
        "automobile",
        "washing",
        "detail",
        "clean"
    ],
    "wof:name":"Fine Details",
    "wof:placetype":"venue"
},
  "geometry": {"coordinates":[-79.255943,43.790367],"type":"Point"}
}