{
  "type": "Feature",
  "properties": {
    "addr:full":"105 Northland Rd Waterloo ON N2V 1Y8",
    "addr:housenumber":"105",
    "addr:postcode":"n2v 1y8",
    "addr:street":"Northland Rd",
    "iso:country":"CA",
    "sg:address":"105 Northland Rd",
    "sg:city":"Waterloo",
    "sg:classifiers":[
        {
            "category":"Manufacturing",
            "subcategory":"Rubber & Plastics",
            "type":"Manufacturing & Wholesale Goods"
        }
    ],
    "sg:phone":"+1 519 746 7093",
    "sg:postcode":"N2V 1Y8",
    "sg:province":"ON",
    "sg:tags":[
        "mold",
        "maker"
    ],
    "wof:name":"Northland Manufacturing",
    "wof:placetype":"venue"
},
  "geometry": {"coordinates":[-80.53182200000001,43.507656],"type":"Point"}
}