{
  "type": "Feature",
  "properties": {
    "addr:full":"426 Bank St Ottawa ON K2P 1Y8",
    "addr:housenumber":"426",
    "addr:postcode":"k2p 1y8",
    "addr:street":"Bank St",
    "iso:country":"CA",
    "sg:address":"426 Bank St",
    "sg:city":"Ottawa",
    "sg:classifiers":[
        {
            "category":"Shopping",
            "subcategory":"Gifts & Souvenirs",
            "type":"Retail Goods"
        }
    ],
    "sg:phone":"+1 613 235 8378",
    "sg:postcode":"K2P 1Y8",
    "sg:province":"ON",
    "sg:tags":[
        "shop",
        "craft"
    ],
    "wof:name":"Beaded Dreams",
    "wof:placetype":"venue"
},
  "geometry": {"coordinates":[-75.693977356,45.4123344421],"type":"Point"}
}