{
  "type": "Feature",
  "properties": {
    "addr:full":"Neepawa MB R0J 1H0",
    "addr:postcode":"r0j 1h0",
    "iso:country":"CA",
    "sg:city":"Neepawa",
    "sg:classifiers":[
        {
            "category":"Government",
            "subcategory":"Office",
            "type":"Public Place"
        }
    ],
    "sg:phone":"+1 204 476 7024",
    "sg:postcode":"R0J 1H0",
    "sg:province":"MB",
    "wof:name":"Manitoba Agricultural Crown",
    "wof:placetype":"venue"
},
  "geometry": {"coordinates":[-99.4651794434,50.2262382507],"type":"Point"}
}