{
  "type": "Feature",
  "properties": {
    "addr:full":"Saint-Felix-D'Otis QC G0V 1M0",
    "addr:postcode":"g0v 1m0",
    "iso:country":"CA",
    "sg:city":"Saint-Felix-D'Otis",
    "sg:classifiers":[
        {
            "category":"Building & Trades",
            "subcategory":"Construction",
            "type":"Services"
        }
    ],
    "sg:phone":"+1 418 544 9254",
    "sg:postcode":"G0V 1M0",
    "sg:province":"QC",
    "sg:tags":[
        "general",
        "contractor"
    ],
    "wof:name":"Immeubles Econo Inc",
    "wof:placetype":"venue"
},
  "geometry": {"coordinates":[-68.172974,48.423107],"type":"Point"}
}