{
  "type": "Feature",
  "properties": {
    "addr:full":"850 Barnet Hwy Port Moody BC V3H 1V6",
    "addr:housenumber":"850",
    "addr:postcode":"v3h 1v6",
    "addr:street":"Barnet Hwy",
    "iso:country":"CA",
    "sg:address":"850 Barnet Hwy",
    "sg:city":"Port Moody",
    "sg:classifiers":[
        {
            "category":"Recreation",
            "subcategory":"Marina",
            "type":"Entertainment"
        }
    ],
    "sg:phone":"+1 604 936 4602",
    "sg:postcode":"V3H 1V6",
    "sg:province":"BC",
    "sg:tags":[
        "repair",
        "marine"
    ],
    "wof:name":"Inlet Marine",
    "wof:placetype":"venue"
},
  "geometry": {"coordinates":[-122.885704,49.290077],"type":"Point"}
}