{
  "type": "Feature",
  "properties": {
    "addr:full":"Pefferlaw ON L0E 1N0",
    "addr:postcode":"l0e 1n0",
    "iso:country":"CA",
    "sg:city":"Pefferlaw",
    "sg:classifiers":[
        {
            "category":"Education",
            "subcategory":"School",
            "type":"Public Place"
        }
    ],
    "sg:phone":"+1 705 437 1537",
    "sg:postcode":"L0E 1N0",
    "sg:province":"ON",
    "wof:name":"Morning Glory Public School",
    "wof:placetype":"venue"
},
  "geometry": {"coordinates":[-79.24413300000001,44.324532],"type":"Point"}
}