{
  "type": "Feature",
  "properties": {
    "addr:full":"5543 Rte 112 Ascot Corner QC J0B 1A0",
    "addr:housenumber":"5543",
    "addr:postcode":"j0b 1a0",
    "addr:street":"Rte 112",
    "iso:country":"CA",
    "sg:address":"5543 Rte 112",
    "sg:city":"Ascot Corner",
    "sg:classifiers":[
        {
            "category":"Home & Garden",
            "subcategory":"Furniture",
            "type":"Retail Goods"
        }
    ],
    "sg:phone":"+1 819 822 1642",
    "sg:postcode":"J0B 1A0",
    "sg:province":"QC",
    "sg:tags":[
        "infant",
        "wear"
    ],
    "wof:name":"Boutique Bebe Maude",
    "wof:placetype":"venue"
},
  "geometry": {"coordinates":[-71.7696228027,45.4464950562],"type":"Point"}
}