{
  "type": "Feature",
  "properties": {
    "addr:full":"3550 Boul Levesque O Laval QC H7V 1E8",
    "addr:housenumber":"3550",
    "addr:postcode":"h7v 1e8",
    "addr:street":"Boul Levesque O",
    "iso:country":"CA",
    "sg:address":"3550 Boul Levesque O",
    "sg:city":"Laval",
    "sg:classifiers":[
        {
            "category":"Organizations",
            "subcategory":"Religious Organization",
            "type":"Services"
        }
    ],
    "sg:phone":"+1 450 681 9206",
    "sg:postcode":"H7V 1E8",
    "sg:province":"QC",
    "wof:name":"Freres DE Sainte Croix",
    "wof:placetype":"venue"
},
  "geometry": {"coordinates":[-73.733429,45.536407],"type":"Point"}
}