{
  "type": "Feature",
  "properties": {
    "iso:country":"CA",
    "sg:address":"982 St Mary's Blvd",
    "sg:city":"Windsor",
    "sg:classifiers":[
        {
            "category":"Building & Trades",
            "subcategory":"Construction",
            "type":"Services"
        }
    ],
    "sg:phone":"+1 519 948 5949",
    "sg:postcode":"N8S 2V2",
    "sg:province":"ON",
    "sg:tags":[
        "painter"
    ],
    "wof:name":"Master Painting & Decorating",
    "wof:placetype":"venue"
},
  "geometry": {"coordinates":[-83.0694274902,42.2917861938],"type":"Point"}
}