{
  "type": "Feature",
  "properties": {
    "addr:full":"Vancouver BC V6E 1R2",
    "addr:postcode":"v6e 1r2",
    "iso:country":"CA",
    "sg:city":"Vancouver",
    "sg:classifiers":[
        {
            "category":"Communications",
            "subcategory":"Film & Video Production",
            "type":"Services"
        }
    ],
    "sg:phone":"+1 604 688 9838",
    "sg:postcode":"V6E 1R2",
    "sg:province":"BC",
    "sg:tags":[
        "taping"
    ],
    "wof:name":"Front Runner Productions",
    "wof:placetype":"venue"
},
  "geometry": {"coordinates":[-123.136528,49.282619],"type":"Point"}
}