{
  "type": "Feature",
  "properties": {
    "addr:full":"130 E 12th Ave Regina SK S4N 6L6",
    "addr:housenumber":"130",
    "addr:postcode":"s4n 6l6",
    "addr:street":"E 12Th Ave",
    "iso:country":"CA",
    "sg:address":"130 E 12th Ave",
    "sg:city":"Regina",
    "sg:classifiers":[
        {
            "category":"Manufacturing",
            "subcategory":"Signs",
            "type":"Manufacturing & Wholesale Goods"
        }
    ],
    "sg:phone":"+1 306 949 3232",
    "sg:postcode":"S4N 6L6",
    "sg:province":"SK",
    "wof:name":"National Signs Ltd",
    "wof:placetype":"venue"
},
  "geometry": {"coordinates":[-104.581695557,50.4489593506],"type":"Point"}
}