{
  "type": "Feature",
  "properties": {
    "addr:full":"76 Rue Saint-Georges Saint-Charles-Borromee QC J6E 2B2",
    "addr:housenumber":"76",
    "addr:postcode":"j6e 2b2",
    "addr:street":"Rue Saint-Georges Saint-Charles-Borromee",
    "iso:country":"CA",
    "sg:address":"76 Rue Saint-Georges",
    "sg:city":"Saint-Charles-Borromee",
    "sg:classifiers":[
        {
            "category":"Personal",
            "subcategory":"Beauty Salon",
            "type":"Services"
        }
    ],
    "sg:phone":"+1 450 753 9720",
    "sg:postcode":"J6E 2B2",
    "sg:province":"QC",
    "wof:name":"Salon DE Coiffure Odette",
    "wof:placetype":"venue"
},
  "geometry": {"coordinates":[-73.45824399999999,46.043499],"type":"Point"}
}