{
  "type": "Feature",
  "properties": {
    "addr:full":"1 Boulder Blvd Stony Plain AB T7Z 1V6",
    "addr:housenumber":"1",
    "addr:postcode":"t7z 1v6",
    "addr:street":"Boulder Blvd",
    "iso:country":"CA",
    "sg:address":"1 Boulder Blvd",
    "sg:city":"Stony Plain",
    "sg:classifiers":[
        {
            "category":"Autos & Motor Vehicles",
            "subcategory":"Auto Supplies",
            "type":"Retail Goods"
        }
    ],
    "sg:phone":"+1 780 963 7334",
    "sg:postcode":"T7Z 1V6",
    "sg:province":"AB",
    "sg:tags":[
        "automobile",
        "parts"
    ],
    "wof:name":"George Moir Antique Auto Parts",
    "wof:placetype":"venue"
},
  "geometry": {"coordinates":[-113.993843,53.547703],"type":"Point"}
}