{
  "type": "Feature",
  "properties": {
    "addr:full":"9139 Rue Lutgarde Saint-Leonard QC H1P 2N5",
    "addr:housenumber":"9139",
    "addr:postcode":"h1p 2n5",
    "addr:street":"Rue Lutgarde",
    "iso:country":"CA",
    "sg:address":"9139 Rue Lutgarde",
    "sg:city":"Saint-Leonard",
    "sg:classifiers":[
        {
            "category":"Building & Trades",
            "subcategory":"Plumbing",
            "type":"Services"
        }
    ],
    "sg:phone":"+1 514 325 4943",
    "sg:postcode":"H1P 2N5",
    "sg:province":"QC",
    "sg:tags":[
        "contractor"
    ],
    "wof:name":"Plomberie Chauffage Super Td",
    "wof:placetype":"venue"
},
  "geometry": {"coordinates":[-73.606201,45.597336],"type":"Point"}
}