{
  "type": "Feature",
  "properties": {
    "iso:country":"CA",
    "sg:city":"North York",
    "sg:classifiers":[
        {
            "category":"Personal",
            "subcategory":"Beauty Salon",
            "type":"Services"
        }
    ],
    "sg:phone":"+1 416 494 3431",
    "sg:postcode":"M2J 4K3",
    "sg:province":"ON",
    "wof:name":"Velvet Touch Beauty Salon",
    "wof:placetype":"venue"
},
  "geometry": {"coordinates":[-79.33674621580001,43.7778015137],"type":"Point"}
}