{
  "type": "Feature",
  "properties": {
    "addr:full":"49 N Industrial Dr Prince Albert SK S6V 5T2",
    "addr:housenumber":"49",
    "addr:postcode":"s6v 5t2",
    "addr:street":"N Industrial Dr",
    "iso:country":"CA",
    "sg:address":"49 N Industrial Dr",
    "sg:city":"Prince Albert",
    "sg:classifiers":[
        {
            "category":"Wholesale",
            "subcategory":"Groceries",
            "type":"Manufacturing & Wholesale Goods"
        }
    ],
    "sg:phone":"+1 306 764 3330",
    "sg:postcode":"S6V 5T2",
    "sg:province":"SK",
    "sg:tags":[
        "grocer"
    ],
    "wof:name":"Northern Grocers Inc",
    "wof:placetype":"venue"
},
  "geometry": {"coordinates":[-105.752121,53.216507],"type":"Point"}
}