{
  "type": "Feature",
  "properties": {
    "addr:full":"18 Gloucester Lane Toronto ON M4Y 1L5",
    "addr:housenumber":"18",
    "addr:postcode":"m4y 1l5",
    "addr:street":"Gloucester Lane",
    "iso:country":"CA",
    "sg:address":"18 Gloucester Lane",
    "sg:city":"Toronto",
    "sg:classifiers":[
        {
            "category":"Arts & Performance",
            "subcategory":"Theater",
            "type":"Entertainment"
        }
    ],
    "sg:phone":"+1 416 972 1046",
    "sg:postcode":"M4Y 1L5",
    "sg:province":"ON",
    "sg:tags":[
        "talent",
        "agency",
        "casting"
    ],
    "wof:name":"Steve Young & Assoc Inc",
    "wof:placetype":"venue"
},
  "geometry": {"coordinates":[-79.384834,43.666885],"type":"Point"}
}