{
  "type": "Feature",
  "properties": {
    "addr:full":"18 Foymount Rd Eganville ON K0J 1T0",
    "addr:housenumber":"18",
    "addr:postcode":"k0j 1t0",
    "addr:street":"Foymount Rd",
    "iso:country":"CA",
    "sg:address":"18 Foymount Rd",
    "sg:city":"Eganville",
    "sg:classifiers":[
        {
            "category":"Building & Trades",
            "subcategory":"Construction",
            "type":"Services"
        }
    ],
    "sg:phone":"+1 613 628 2212",
    "sg:postcode":"K0J 1T0",
    "sg:province":"ON",
    "sg:tags":[
        "contractor",
        "general"
    ],
    "wof:name":"William G Verheyen & Sons Ltd",
    "wof:placetype":"venue"
},
  "geometry": {"coordinates":[-77.10090599999999,45.540077],"type":"Point"}
}