{
  "type": "Feature",
  "properties": {
    "addr:full":"Alliston ON L9R 1J3",
    "addr:postcode":"l9r 1j3",
    "addr:street":"Alliston",
    "iso:country":"CA",
    "sg:city":"Alliston",
    "sg:classifiers":[
        {
            "category":"Recreation",
            "type":"Entertainment"
        }
    ],
    "sg:phone":"+1 705 435 5734",
    "sg:postcode":"L9R 1J3",
    "sg:province":"ON",
    "sg:tags":[
        "youth",
        "information",
        "activity",
        "center",
        "organization"
    ],
    "wof:name":"Community Action Program",
    "wof:placetype":"venue"
},
  "geometry": {"coordinates":[-79.869430542,44.1526603699],"type":"Point"}
}