{
  "type": "Feature",
  "properties": {
    "addr:full":"730 Garth St Hamilton ON L9C 4K3",
    "addr:housenumber":"730",
    "addr:postcode":"l9c 4k3",
    "addr:street":"Garth St",
    "iso:country":"CA",
    "sg:address":"730 Garth St",
    "sg:city":"Hamilton",
    "sg:classifiers":[
        {
            "category":"Personal",
            "subcategory":"Beauty Salon",
            "type":"Services"
        }
    ],
    "sg:phone":"+1 905 385 1350",
    "sg:postcode":"L9C 4K3",
    "sg:province":"ON",
    "wof:name":"Kathy's Hair Styling",
    "wof:placetype":"venue"
},
  "geometry": {"coordinates":[-79.897514,43.240971],"type":"Point"}
}