{
  "type": "Feature",
  "properties": {
    "addr:full":"901 Rte Principale Val-Des-Monts QC J8N 4H7",
    "addr:housenumber":"901",
    "addr:postcode":"j8n 4h7",
    "addr:street":"Rte Principale",
    "iso:country":"CA",
    "sg:address":"901 Rte Principale",
    "sg:city":"Val-Des-Monts",
    "sg:classifiers":[
        {
            "category":"Restaurant",
            "type":"Food & Drink"
        }
    ],
    "sg:phone":"+1 819 457 4077",
    "sg:postcode":"J8N 4H7",
    "sg:province":"QC",
    "wof:name":"Restaurants Le Nouveau 27",
    "wof:placetype":"venue"
},
  "geometry": {"coordinates":[-75.729721,45.674919],"type":"Point"}
}