{
  "type": "Feature",
  "properties": {
    "addr:full":"2959 Boul Saint-Charles Kirkland QC H9H 3B5",
    "addr:housenumber":"2959",
    "addr:postcode":"h9h 3b5",
    "addr:street":"Boul Saint-Charles",
    "iso:country":"CA",
    "sg:address":"2959 Boul Saint-Charles",
    "sg:city":"Kirkland",
    "sg:classifiers":[
        {
            "category":"Banks & Credit Unions",
            "subcategory":"Bank",
            "type":"Services"
        }
    ],
    "sg:phone":"+1 514 694 3026",
    "sg:postcode":"H9H 3B5",
    "sg:province":"QC",
    "wof:name":"Cibc",
    "wof:placetype":"venue"
},
  "geometry": {"coordinates":[-73.85417200000001,45.448193],"type":"Point"}
}