{
  "type": "Feature",
  "properties": {
    "addr:full":"Montreal QC H3C 1A9",
    "addr:postcode":"h3c 1a9",
    "iso:country":"CA",
    "sg:city":"Montreal",
    "sg:classifiers":[
        {
            "category":"Recreation",
            "type":"Entertainment"
        }
    ],
    "sg:phone":"+1 514 879 1027",
    "sg:postcode":"H3C 1A9",
    "sg:province":"QC",
    "sg:tags":[
        "organization",
        "carnival"
    ],
    "wof:name":"Festival DE LA Sante",
    "wof:placetype":"venue"
},
  "geometry": {"coordinates":[-73.5556793213,45.5062522888],"type":"Point"}
}