{
  "type": "Feature",
  "properties": {
    "iso:country":"CA",
    "sg:city":"Hamilton",
    "sg:classifiers":[
        {
            "category":"Personal",
            "type":"Services"
        }
    ],
    "sg:phone":"+1 905 667 0667",
    "sg:postcode":"L8N 1T8",
    "sg:province":"ON",
    "sg:tags":[
        "therapist",
        "massage"
    ],
    "wof:name":"Arruda Massage Therapy",
    "wof:placetype":"venue"
},
  "geometry": {"coordinates":[-79.87117004389999,43.2514076233],"type":"Point"}
}