{
  "type": "Feature",
  "properties": {
    "addr:full":"Halifax NS B3M 2K6",
    "addr:postcode":"b3m 2k6",
    "iso:country":"CA",
    "sg:city":"Halifax",
    "sg:classifiers":[
        {
            "category":"Professional",
            "subcategory":"Accounting & Tax Preparation",
            "type":"Services"
        }
    ],
    "sg:phone":"+1 902 457 1666",
    "sg:postcode":"B3M 2K6",
    "sg:province":"NS",
    "sg:tags":[
        "bookkeeping",
        "general"
    ],
    "wof:name":"Bardsley, Art G",
    "wof:placetype":"venue"
},
  "geometry": {"coordinates":[-63.6500587463,44.6780548096],"type":"Point"}
}