{
  "type": "Feature",
  "properties": {
    "iso:country":"CA",
    "sg:address":"898 Monaghan Rd",
    "sg:city":"Peterborough",
    "sg:classifiers":[
        {
            "category":"Home & Garden",
            "subcategory":"Building Materials",
            "type":"Retail Goods"
        }
    ],
    "sg:phone":"+1 705 743 9723",
    "sg:postcode":"K9J 5K4",
    "sg:province":"ON",
    "sg:tags":[
        "equipment",
        "kitchen",
        "cabinet"
    ],
    "wof:name":"Rona Cashway Building Ctr",
    "wof:placetype":"venue"
},
  "geometry": {"coordinates":[-78.32944488530001,44.2857627869],"type":"Point"}
}