{
  "type": "Feature",
  "properties": {
    "addr:full":"7149 50 Ave Red Deer AB T4N 4E4",
    "addr:housenumber":"7149",
    "addr:postcode":"t4n 4e4",
    "addr:street":"50 Ave",
    "iso:country":"CA",
    "sg:address":"7149 50 Ave",
    "sg:city":"Red Deer",
    "sg:classifiers":[
        {
            "category":"Restaurant",
            "type":"Food & Drink"
        }
    ],
    "sg:phone":"+1 403 342 2226",
    "sg:postcode":"T4N 4E4",
    "sg:province":"AB",
    "wof:name":"Mc Donald's",
    "wof:placetype":"venue"
},
  "geometry": {"coordinates":[-113.813255,52.297707],"type":"Point"}
}