{
  "type": "Feature",
  "properties": {
    "iso:country":"CA",
    "sg:city":"Westmount",
    "sg:classifiers":[
        {
            "category":"Shopping",
            "subcategory":"Clothing, Apparel, & Fashions",
            "type":"Retail Goods"
        }
    ],
    "sg:phone":"+1 514 939 4141",
    "sg:postcode":"H3Z 2P9",
    "sg:province":"QC",
    "wof:name":"Davicci",
    "wof:placetype":"venue"
},
  "geometry": {"coordinates":[-73.5875091553,45.4867591858],"type":"Point"}
}