{
  "type": "Feature",
  "properties": {
    "addr:full":"9361 Rue Lajeunesse Montreal QC H2M 1S5",
    "addr:housenumber":"9361",
    "addr:postcode":"h2m 1s5",
    "addr:street":"Rue Lajeunesse",
    "iso:country":"CA",
    "sg:address":"9361 Rue Lajeunesse",
    "sg:city":"Montreal",
    "sg:classifiers":[
        {
            "category":"Shopping",
            "subcategory":"Florist",
            "type":"Retail Goods"
        }
    ],
    "sg:phone":"+1 514 388 3378",
    "sg:postcode":"H2M 1S5",
    "sg:province":"QC",
    "wof:name":"A LA Fleuristerie",
    "wof:placetype":"venue"
},
  "geometry": {"coordinates":[-73.64907100000001,45.549835],"type":"Point"}
}