{
  "type": "Feature",
  "properties": {
    "addr:full":"1710 Rue Rigaud Brossard QC J4X 2J2",
    "addr:housenumber":"1710",
    "addr:postcode":"j4x 2j2",
    "addr:street":"Rue Rigaud",
    "iso:country":"CA",
    "sg:address":"1710 Rue Rigaud",
    "sg:city":"Brossard",
    "sg:classifiers":[
        {
            "category":"Professional",
            "subcategory":"Management & Consulting",
            "type":"Services"
        }
    ],
    "sg:phone":"+1 450 923 3156",
    "sg:postcode":"J4X 2J2",
    "sg:province":"QC",
    "sg:tags":[
        "consultant",
        "printing"
    ],
    "wof:name":"Webco Management Inc",
    "wof:placetype":"venue"
},
  "geometry": {"coordinates":[-73.489746,45.440697],"type":"Point"}
}