{
  "type": "Feature",
  "properties": {
    "addr:full":"4027 7 St SE Calgary AB T2G 2Y9",
    "addr:housenumber":"4027 7",
    "addr:postcode":"t2g 2y9",
    "addr:street":"St Se",
    "iso:country":"CA",
    "sg:address":"4027 7 St SE",
    "sg:city":"Calgary",
    "sg:classifiers":[
        {
            "category":"Shopping",
            "subcategory":"Musical Instruments",
            "type":"Retail Goods"
        }
    ],
    "sg:phone":"+1 403 243 4099",
    "sg:postcode":"T2G 2Y9",
    "sg:province":"AB",
    "sg:tags":[
        "music",
        "dealer"
    ],
    "wof:name":"Calton Cases of Canada",
    "wof:placetype":"venue"
},
  "geometry": {"coordinates":[-114.045951843,51.0186271667],"type":"Point"}
}