{
  "type": "Feature",
  "properties": {
    "addr:full":"44 Head St Dundas ON L9H 3H3",
    "addr:housenumber":"44",
    "addr:postcode":"l9h 3h3",
    "addr:street":"Head St",
    "iso:country":"CA",
    "sg:address":"44 Head St",
    "sg:city":"Dundas",
    "sg:classifiers":[
        {
            "category":"Professional",
            "subcategory":"Business Services",
            "type":"Services"
        }
    ],
    "sg:phone":"+1 905 627 9233",
    "sg:postcode":"L9H 3H3",
    "sg:province":"ON",
    "sg:tags":[
        "water",
        "treatment"
    ],
    "wof:name":"Anderson Water Systems",
    "wof:placetype":"venue"
},
  "geometry": {"coordinates":[-79.974442,43.269352],"type":"Point"}
}