{
  "type": "Feature",
  "properties": {
    "addr:full":"5005 Main St Donalda AB T0B 1H0",
    "addr:housenumber":"5005",
    "addr:postcode":"t0b 1h0",
    "addr:street":"Main St",
    "iso:country":"CA",
    "sg:address":"5005 Main St",
    "sg:city":"Donalda",
    "sg:classifiers":[
        {
            "category":"Shopping",
            "subcategory":"Used Merchandise",
            "type":"Retail Goods"
        }
    ],
    "sg:phone":"+1 403 883 2888",
    "sg:postcode":"T0B 1H0",
    "sg:province":"AB",
    "sg:tags":[
        "antique"
    ],
    "wof:name":"Nutcracker Sweet",
    "wof:placetype":"venue"
},
  "geometry": {"coordinates":[-112.573768616,52.5849990845],"type":"Point"}
}