{
  "type": "Feature",
  "properties": {
    "addr:full":"4988 Dundas St W Etobicoke ON M9A 1B8",
    "addr:housenumber":"4988",
    "addr:postcode":"m9a 1b8",
    "addr:street":"Dundas St W",
    "iso:country":"CA",
    "sg:address":"4988 Dundas St W",
    "sg:city":"Etobicoke",
    "sg:classifiers":[
        {
            "category":"Retail",
            "subcategory":"Repair Shop",
            "type":"Services"
        }
    ],
    "sg:phone":"+1 416 231 3325",
    "sg:postcode":"M9A 1B8",
    "sg:province":"ON",
    "sg:tags":[
        "lock",
        "locksmith"
    ],
    "wof:name":"Edwards Builders Hardware Ltd",
    "wof:placetype":"venue"
},
  "geometry": {"coordinates":[-79.5305557251,43.6469345093],"type":"Point"}
}