{
  "type": "Feature",
  "properties": {
    "addr:full":"1073 Topsail Rd Mount Pearl NL A1N 5E9",
    "addr:housenumber":"1073",
    "addr:postcode":"a1n 5e9",
    "addr:street":"Topsail Rd",
    "iso:country":"CA",
    "sg:address":"1073 Topsail Rd",
    "sg:city":"Mount Pearl",
    "sg:classifiers":[
        {
            "category":"Autos & Motor Vehicles",
            "subcategory":"Motorcycle Sales",
            "type":"Retail Goods"
        }
    ],
    "sg:phone":"+1 709 364 9051",
    "sg:postcode":"A1N 5E9",
    "sg:province":"NL",
    "sg:tags":[
        "scooter"
    ],
    "wof:name":"Cycle City & Recreation Ltd",
    "wof:placetype":"venue"
},
  "geometry": {"coordinates":[-52.8147125244,47.5259552002],"type":"Point"}
}