{
  "type": "Feature",
  "properties": {
    "addr:full":"Port Alberni BC V9Y 4E1",
    "addr:postcode":"v9y 4e1",
    "iso:country":"CA",
    "sg:city":"Port Alberni",
    "sg:classifiers":[
        {
            "category":"Shopping",
            "subcategory":"Crafts & Fabrics",
            "type":"Retail Goods"
        }
    ],
    "sg:phone":"+1 250 723 8831",
    "sg:postcode":"V9Y 4E1",
    "sg:province":"BC",
    "sg:tags":[
        "shop"
    ],
    "wof:name":"Pincushion",
    "wof:placetype":"venue"
},
  "geometry": {"coordinates":[-124.807785,49.236301],"type":"Point"}
}