{
  "type": "Feature",
  "properties": {
    "addr:full":"555 Finch Ave W North York ON M2R 1N5",
    "addr:housenumber":"555",
    "addr:postcode":"m2r 1n5",
    "addr:street":"Finch Ave W",
    "iso:country":"CA",
    "sg:address":"555 Finch Ave W",
    "sg:city":"North York",
    "sg:classifiers":[
        {
            "category":"Organizations",
            "subcategory":"Religious Organization",
            "type":"Services"
        }
    ],
    "sg:phone":"+1 416 638 6072",
    "sg:postcode":"M2R 1N5",
    "sg:province":"ON",
    "wof:name":"It Is Written",
    "wof:placetype":"venue"
},
  "geometry": {"coordinates":[-79.448654,43.772629],"type":"Point"}
}