{
  "type": "Feature",
  "properties": {
    "addr:full":"3 Niash Picard Betsiamites QC G0H 1B0",
    "addr:housenumber":"3",
    "addr:postcode":"g0h 1b0",
    "addr:street":"Niash Picard",
    "iso:country":"CA",
    "sg:address":"3 Niash Picard",
    "sg:city":"Betsiamites",
    "sg:classifiers":[
        {
            "category":"Professional",
            "subcategory":"Business Services",
            "type":"Services"
        }
    ],
    "sg:phone":"+1 418 567 2814",
    "sg:postcode":"G0H 1B0",
    "sg:province":"QC",
    "sg:tags":[
        "youth",
        "organization",
        "referral",
        "center",
        "information"
    ],
    "wof:name":"Maison Des Jeunes",
    "wof:placetype":"venue"
},
  "geometry": {"coordinates":[-68.6533355713,48.9492797852],"type":"Point"}
}