{
  "type": "Feature",
  "properties": {
    "addr:full":"234 Century Rd Spruce Grove AB T7X 3X7",
    "addr:housenumber":"234",
    "addr:postcode":"t7x 3x7",
    "addr:street":"Century Rd",
    "iso:country":"CA",
    "sg:address":"234 Century Rd",
    "sg:city":"Spruce Grove",
    "sg:classifiers":[
        {
            "category":"Food & Beverages",
            "subcategory":"Groceries & Convenience Stores",
            "type":"Retail Goods"
        }
    ],
    "sg:phone":"+1 780 960 3287",
    "sg:postcode":"T7X 3X7",
    "sg:province":"AB",
    "sg:tags":[
        "grocer"
    ],
    "wof:name":"Century Convenience",
    "wof:placetype":"venue"
},
  "geometry": {"coordinates":[-113.885124206,53.551448822],"type":"Point"}
}