{
  "type": "Feature",
  "properties": {
    "addr:full":"8403 142 St NW Edmonton AB T5R 4L3",
    "addr:housenumber":"8403",
    "addr:postcode":"t5r 4l3",
    "addr:street":"142 St Nw",
    "iso:country":"CA",
    "sg:address":"8403 142 St NW",
    "sg:city":"Edmonton",
    "sg:classifiers":[
        {
            "category":"Personal",
            "subcategory":"Beauty Salon",
            "type":"Services"
        }
    ],
    "sg:phone":"+1 780 444 0483",
    "sg:postcode":"T5R 4L3",
    "sg:province":"AB",
    "wof:name":"Canterbury Court Beauty Salon",
    "wof:placetype":"venue"
},
  "geometry": {"coordinates":[-113.56546,53.516651],"type":"Point"}
}