{
  "type": "Feature",
  "properties": {
    "addr:full":"Prince George BC V2L 5B8",
    "addr:postcode":"v2l 5b8",
    "iso:country":"CA",
    "sg:city":"Prince George",
    "sg:classifiers":[
        {
            "category":"Organizations",
            "subcategory":"Professional Association",
            "type":"Services"
        }
    ],
    "sg:phone":"+1 250 564 5166",
    "sg:postcode":"V2L 5B8",
    "sg:province":"BC",
    "wof:name":"Council-Northern Interior Frst",
    "wof:placetype":"venue"
},
  "geometry": {"coordinates":[-122.749191,53.918034],"type":"Point"}
}