{
  "type": "Feature",
  "properties": {
    "addr:full":"7007 Islington Ave Woodbridge ON L4L 4T5",
    "addr:housenumber":"7007",
    "addr:postcode":"l4l 4t5",
    "addr:street":"Islington Ave",
    "iso:country":"CA",
    "sg:address":"7007 Islington Ave",
    "sg:city":"Woodbridge",
    "sg:classifiers":[
        {
            "category":"Shopping",
            "subcategory":"Hobbies, Toys, & Games",
            "type":"Retail Goods"
        }
    ],
    "sg:phone":"+1 905 856 5518",
    "sg:postcode":"L4L 4T5",
    "sg:province":"ON",
    "sg:tags":[
        "equipment",
        "ceramic",
        "supply"
    ],
    "wof:name":"M & M Ceramic Tile",
    "wof:placetype":"venue"
},
  "geometry": {"coordinates":[-79.574806,43.764633],"type":"Point"}
}