{
  "type": "Feature",
  "properties": {
    "addr:full":"3220 5 Ave NE #11 Calgary AB T2A 5N1",
    "addr:housenumber":"3220",
    "addr:postcode":"t2a 5n1",
    "addr:street":"5 Ave Ne # 11",
    "iso:country":"CA",
    "sg:address":"3220 5 Ave NE #11",
    "sg:city":"Calgary",
    "sg:classifiers":[
        {
            "category":"Manufacturing",
            "subcategory":"Apparel",
            "type":"Manufacturing & Wholesale Goods"
        }
    ],
    "sg:phone":"+1 403 235 2005",
    "sg:postcode":"T2A 5N1",
    "sg:province":"AB",
    "sg:tags":[
        "closet",
        "accessory"
    ],
    "wof:name":"Kordick Enterprises",
    "wof:placetype":"venue"
},
  "geometry": {"coordinates":[-113.987220764,51.0571784973],"type":"Point"}
}