{
  "type": "Feature",
  "properties": {
    "addr:full":"16 Estate Dr Scarborough ON M1H 2Z1",
    "addr:housenumber":"16",
    "addr:postcode":"m1h 2z1",
    "addr:street":"Estate Dr",
    "iso:country":"CA",
    "sg:address":"16 Estate Dr",
    "sg:city":"Scarborough",
    "sg:classifiers":[
        {
            "category":"Wholesale",
            "subcategory":"Auto Parts",
            "type":"Manufacturing & Wholesale Goods"
        }
    ],
    "sg:phone":"+1 416 439 4994",
    "sg:postcode":"M1H 2Z1",
    "sg:province":"ON",
    "sg:tags":[
        "equipment",
        "truck"
    ],
    "wof:name":"Drivetec Manufacturing Ltd",
    "wof:placetype":"venue"
},
  "geometry": {"coordinates":[-79.2384109497,43.7817306519],"type":"Point"}
}