{
  "type": "Feature",
  "properties": {
    "addr:full":"262 Rue Camirand Asbestos QC J1T 3R7",
    "addr:housenumber":"262",
    "addr:postcode":"j1t 3r7",
    "addr:street":"Rue Camirand",
    "iso:country":"CA",
    "sg:address":"262 Rue Camirand",
    "sg:city":"Asbestos",
    "sg:classifiers":[
        {
            "category":"Personal",
            "subcategory":"Beauty Salon",
            "type":"Services"
        }
    ],
    "sg:phone":"+1 819 879 2959",
    "sg:postcode":"J1T 3R7",
    "sg:province":"QC",
    "wof:name":"Salon Denise C Mayette Enr",
    "wof:placetype":"venue"
},
  "geometry": {"coordinates":[-71.927223,45.778332],"type":"Point"}
}