{
  "type": "Feature",
  "properties": {
    "iso:country":"CA",
    "sg:address":"326 Main St W",
    "sg:city":"Berwick",
    "sg:classifiers":[
        {
            "category":"Wholesale",
            "subcategory":"Meat",
            "type":"Manufacturing & Wholesale Goods"
        }
    ],
    "sg:phone":"+1 902 538 8060",
    "sg:postcode":"B0P 1E0",
    "sg:province":"NS",
    "sg:tags":[
        "packer"
    ],
    "wof:name":"Larsen Packers Ltd",
    "wof:placetype":"venue"
},
  "geometry": {"coordinates":[-64.74969482420001,45.0509605408],"type":"Point"}
}