{
  "type": "Feature",
  "properties": {
    "addr:full":"68 Rue DE LA Gauchetiere O Montreal QC H2Z 1C1",
    "addr:housenumber":"68",
    "addr:postcode":"h2z 1c1",
    "addr:street":"Rue De La Gauchetiere O",
    "iso:country":"CA",
    "sg:address":"68 Rue DE LA Gauchetiere O",
    "sg:city":"Montreal",
    "sg:classifiers":[
        {
            "category":"Restaurant",
            "type":"Food & Drink"
        }
    ],
    "sg:phone":"+1 514 866 1628",
    "sg:postcode":"H2Z 1C1",
    "sg:province":"QC",
    "wof:name":"M & M Legent Inc",
    "wof:placetype":"venue"
},
  "geometry": {"coordinates":[-73.5591964722,45.5089035034],"type":"Point"}
}