{
  "type": "Feature",
  "properties": {
    "addr:full":"1474 Pickwick Dr Mississauga ON L5V 2G2",
    "addr:housenumber":"1474",
    "addr:postcode":"l5v 2g2",
    "addr:street":"Pickwick Dr",
    "iso:country":"CA",
    "sg:address":"1474 Pickwick Dr",
    "sg:city":"Mississauga",
    "sg:classifiers":[
        {
            "category":"Wholesale",
            "subcategory":"Office Equipment",
            "type":"Manufacturing & Wholesale Goods"
        }
    ],
    "sg:phone":"+1 905 858 2700",
    "sg:postcode":"L5V 2G2",
    "sg:province":"ON",
    "sg:tags":[
        "bank",
        "supply"
    ],
    "wof:name":"Narinder Khasria",
    "wof:placetype":"venue"
},
  "geometry": {"coordinates":[-79.70388793950001,43.5926933289],"type":"Point"}
}