{
  "type": "Feature",
  "properties": {
    "addr:full":"4825 Luxor Station Rd Radium Hot Springs BC V0A 1M0",
    "addr:housenumber":"4825",
    "addr:postcode":"v0a 1m0",
    "addr:street":"Luxor Station Rd",
    "iso:country":"CA",
    "sg:address":"4825 Luxor Station Rd",
    "sg:city":"Radium Hot Springs",
    "sg:classifiers":[
        {
            "category":"Sports & Exercise",
            "subcategory":"Golf",
            "type":"Entertainment"
        }
    ],
    "sg:phone":"+1 250 347 6500",
    "sg:postcode":"V0A 1M0",
    "sg:province":"BC",
    "sg:tags":[
        "course"
    ],
    "wof:name":"Spur Valley Greens",
    "wof:placetype":"venue"
},
  "geometry": {"coordinates":[-116.071266174,50.6213645935],"type":"Point"}
}