{
  "type": "Feature",
  "properties": {
    "addr:full":"Montreal QC H3M 3E2",
    "addr:postcode":"h3m 3e2",
    "iso:country":"CA",
    "sg:city":"Montreal",
    "sg:classifiers":[
        {
            "category":"Social Services",
            "type":"Services"
        }
    ],
    "sg:phone":"+1 514 332 6332",
    "sg:postcode":"H3M 3E2",
    "sg:province":"QC",
    "sg:tags":[
        "agency",
        "adoption"
    ],
    "wof:name":"Adoption Enfants Du Monde Inc",
    "wof:placetype":"venue"
},
  "geometry": {"coordinates":[-73.678719,45.5368],"type":"Point"}
}