{
  "type": "Feature",
  "properties": {
    "addr:full":"Sudbury ON P3E 3M9",
    "addr:postcode":"p3e 3m9",
    "iso:country":"CA",
    "sg:city":"Sudbury",
    "sg:classifiers":[
        {
            "category":"Professional",
            "subcategory":"Lawyer & Legal Services",
            "type":"Services"
        }
    ],
    "sg:phone":"+1 705 674 9292",
    "sg:postcode":"P3E 3M9",
    "sg:province":"ON",
    "sg:tags":[
        "attorney"
    ],
    "wof:name":"Peter D Best Law Office",
    "wof:placetype":"venue"
},
  "geometry": {"coordinates":[-80.995239,46.490791],"type":"Point"}
}