{
  "type": "Feature",
  "properties": {
    "addr:full":"7380 Mccowan Rd # 1 Markham ON L3S 3H8",
    "addr:housenumber":"7380",
    "addr:postcode":"l3s 3h8",
    "addr:street":"Mccowan Rd # 1",
    "iso:country":"CA",
    "sg:address":"7380 Mccowan Rd # 1",
    "sg:city":"Markham",
    "sg:classifiers":[
        {
            "category":"Health Services",
            "subcategory":"Doctor",
            "type":"Services"
        }
    ],
    "sg:phone":"+1 905 479 7443",
    "sg:postcode":"L3S 3H8",
    "sg:province":"ON",
    "sg:tags":[
        "dentist"
    ],
    "wof:name":"Kerbel, Darren DDS",
    "wof:placetype":"venue"
},
  "geometry": {"coordinates":[-79.277687,43.839817],"type":"Point"}
}