{
  "type": "Feature",
  "properties": {
    "addr:full":"643 20 St Fort Macleod AB T0L 0Z0",
    "addr:housenumber":"643 20",
    "addr:postcode":"t0l 0z0",
    "addr:street":"St",
    "iso:country":"CA",
    "sg:address":"643 20 St",
    "sg:city":"Fort Macleod",
    "sg:classifiers":[
        {
            "category":"Organizations",
            "subcategory":"Religious Organization",
            "type":"Services"
        }
    ],
    "sg:phone":"+1 403 553 3777",
    "sg:postcode":"T0L 0Z0",
    "sg:province":"AB",
    "sg:tags":[
        "church"
    ],
    "wof:name":"Church of Jesus Christ of Lds",
    "wof:placetype":"venue"
},
  "geometry": {"coordinates":[-113.396347046,49.7225761414],"type":"Point"}
}