{
  "type": "Feature",
  "properties": {
    "addr:full":"8092 Little Falls Rd Washago ON L0K 2B0",
    "addr:housenumber":"8092",
    "addr:postcode":"l0k 2b0",
    "addr:street":"Little Falls Rd",
    "iso:country":"CA",
    "sg:address":"8092 Little Falls Rd",
    "sg:city":"Washago",
    "sg:classifiers":[
        {
            "category":"Travel",
            "subcategory":"Hotels & Motels",
            "type":"Entertainment"
        }
    ],
    "sg:phone":"+1 705 689 2043",
    "sg:postcode":"L0K 2B0",
    "sg:province":"ON",
    "sg:tags":[
        "cottage",
        "cabin"
    ],
    "wof:name":"Little Fall's Cottages",
    "wof:placetype":"venue"
},
  "geometry": {"coordinates":[-79.324112,44.74593],"type":"Point"}
}