{
  "type": "Feature",
  "properties": {
    "addr:full":"Beaverton ON L0K 1A0",
    "addr:postcode":"l0k 1a0",
    "iso:country":"CA",
    "sg:city":"Beaverton",
    "sg:classifiers":[
        {
            "category":"Retail",
            "subcategory":"Veterinary Services",
            "type":"Services"
        }
    ],
    "sg:phone":"+1 705 426 5206",
    "sg:postcode":"L0K 1A0",
    "sg:province":"ON",
    "sg:tags":[
        "veterinarian"
    ],
    "wof:name":"Sadoch, L DVM",
    "wof:placetype":"venue"
},
  "geometry": {"coordinates":[-79.04666137700001,44.4355010986],"type":"Point"}
}