{
  "type": "Feature",
  "properties": {
    "addr:full":"1513 Second St W Brooks AB T1R 1C4",
    "addr:housenumber":"1513",
    "addr:postcode":"ab t1r 1c4",
    "addr:street":"Second St W Brooks",
    "iso:country":"CA",
    "sg:address":"1513 Second St W",
    "sg:city":"Brooks",
    "sg:classifiers":[
        {
            "category":"Building & Trades",
            "subcategory":"Landscaping Services",
            "type":"Services"
        }
    ],
    "sg:phone":"+1 403 362 7426",
    "sg:postcode":"T1R 1C4",
    "sg:province":"AB",
    "sg:tags":[
        "lawn",
        "sprinkler",
        "maintenance",
        "grounds"
    ],
    "wof:name":"Cactus Sprinkler System",
    "wof:placetype":"venue"
},
  "geometry": {"coordinates":[-111.89717899999999,50.586609],"type":"Point"}
}