{
  "type": "Feature",
  "properties": {
    "addr:full":"Quebec QC G2K 2E3",
    "addr:postcode":"g2k 2e3",
    "iso:country":"CA",
    "sg:city":"Quebec",
    "sg:classifiers":[
        {
            "category":"Health Services",
            "subcategory":"Doctor",
            "type":"Services"
        }
    ],
    "sg:phone":"+1 418 628 0707",
    "sg:postcode":"G2K 2E3",
    "sg:province":"QC",
    "sg:tags":[
        "dentist"
    ],
    "wof:name":"Clinique Dentaire Dallaire",
    "wof:placetype":"venue"
},
  "geometry": {"coordinates":[-71.29394499999999,46.836075],"type":"Point"}
}