{
  "type": "Feature",
  "properties": {
    "addr:full":"139 Joseph St Kingston ON K7K 2H8",
    "addr:housenumber":"139",
    "addr:postcode":"k7k 2h8",
    "addr:street":"Joseph St",
    "iso:country":"CA",
    "sg:address":"139 Joseph St",
    "sg:city":"Kingston",
    "sg:classifiers":[
        {
            "category":"Home & Garden",
            "subcategory":"Household Appliances",
            "type":"Retail Goods"
        }
    ],
    "sg:phone":"+1 613 542 4525",
    "sg:postcode":"K7K 2H8",
    "sg:province":"ON",
    "wof:name":"Fridge Doctor",
    "wof:placetype":"venue"
},
  "geometry": {"coordinates":[-76.493195,44.245052],"type":"Point"}
}