{
  "type": "Feature",
  "properties": {
    "addr:full":"3500 30 St Vernon BC V1T 5E8",
    "addr:housenumber":"3500",
    "addr:postcode":"v1t 5e8",
    "addr:street":"30 St",
    "iso:country":"CA",
    "sg:address":"3500 30 St",
    "sg:city":"Vernon",
    "sg:classifiers":[
        {
            "category":"Real Estate",
            "subcategory":"Architect",
            "type":"Services"
        }
    ],
    "sg:phone":"+1 250 545 0784",
    "sg:postcode":"V1T 5E8",
    "sg:province":"BC",
    "wof:name":"T R Thorburn Architects",
    "wof:placetype":"venue"
},
  "geometry": {"coordinates":[-119.27092,50.26759],"type":"Point"}
}