{
  "type": "Feature",
  "properties": {
    "iso:country":"CA",
    "sg:address":"1610 Garfield St",
    "sg:city":"Saskatoon",
    "sg:classifiers":[
        {
            "category":"Building & Trades",
            "subcategory":"Construction",
            "type":"Services"
        }
    ],
    "sg:phone":"+1 306 955 0212",
    "sg:postcode":"S7M 1G3",
    "sg:province":"SK",
    "sg:tags":[
        "sandblasting"
    ],
    "wof:name":"Sandrich Maintenance Ltd",
    "wof:placetype":"venue"
},
  "geometry": {"coordinates":[-106.69455719,52.1157264709],"type":"Point"}
}