{
  "type": "Feature",
  "properties": {
    "addr:full":"839 Sutherland Ave Kelowna BC V1Y 5X4",
    "addr:housenumber":"839",
    "addr:postcode":"v1y 5x4",
    "addr:street":"Sutherland Ave",
    "iso:country":"CA",
    "sg:address":"839 Sutherland Ave",
    "sg:city":"Kelowna",
    "sg:classifiers":[
        {
            "category":"Recreation",
            "type":"Entertainment"
        }
    ],
    "sg:phone":"+1 250 762 3328",
    "sg:postcode":"V1Y 5X4",
    "sg:province":"BC",
    "sg:tags":[
        "center"
    ],
    "wof:name":"Seton Centre",
    "wof:placetype":"venue"
},
  "geometry": {"coordinates":[-119.484741,49.879704],"type":"Point"}
}