{
  "type": "Feature",
  "properties": {
    "addr:full":"Beaverdell BC V0H 1A0",
    "addr:postcode":"v0h 1a0",
    "iso:country":"CA",
    "sg:city":"Beaverdell",
    "sg:classifiers":[
        {
            "category":"Travel",
            "subcategory":"Hotels & Motels",
            "type":"Entertainment"
        }
    ],
    "sg:phone":"+1 250 484 5513",
    "sg:postcode":"V0H 1A0",
    "sg:province":"BC",
    "wof:name":"Beaverdell Hotel",
    "wof:placetype":"venue"
},
  "geometry": {"coordinates":[-119.087631,49.435806],"type":"Point"}
}