{
  "type": "Feature",
  "properties": {
    "addr:full":"7 Litchfield Cres Halifax NS B3P 2N5",
    "addr:housenumber":"7",
    "addr:postcode":"b3p 2n5",
    "addr:street":"Litchfield Cres",
    "iso:country":"CA",
    "sg:address":"7 Litchfield Cres",
    "sg:city":"Halifax",
    "sg:classifiers":[
        {
            "category":"Building & Trades",
            "subcategory":"Construction",
            "type":"Services"
        }
    ],
    "sg:phone":"+1 902 497 8272",
    "sg:postcode":"B3P 2N5",
    "sg:province":"NS",
    "sg:tags":[
        "general",
        "contractor"
    ],
    "wof:name":"Don Longuard Renovations",
    "wof:placetype":"venue"
},
  "geometry": {"coordinates":[-63.598248,44.621819],"type":"Point"}
}