{
  "type": "Feature",
  "properties": {
    "addr:full":"Burnaby BC V5H 4K9",
    "addr:postcode":"v5h 4k9",
    "iso:country":"CA",
    "sg:city":"Burnaby",
    "sg:classifiers":[
        {
            "category":"Retail",
            "subcategory":"Photofinishing",
            "type":"Services"
        }
    ],
    "sg:phone":"+1 604 439 1288",
    "sg:postcode":"V5H 4K9",
    "sg:province":"BC",
    "sg:tags":[
        "photographer"
    ],
    "wof:name":"Gunter Marx-Stock Photos",
    "wof:placetype":"venue"
},
  "geometry": {"coordinates":[-123.006729126,49.2265701294],"type":"Point"}
}