{
  "type": "Feature",
  "properties": {
    "addr:full":"6493 Hwy 115/35 Orono ON L0B 1M0",
    "addr:housenumber":"6493;/ 35",
    "addr:postcode":"l0b 1m0",
    "addr:street":"Hwy 115",
    "iso:country":"CA",
    "sg:address":"6493 Hwy 115/35",
    "sg:city":"Orono",
    "sg:classifiers":[
        {
            "category":"Professional",
            "subcategory":"Accounting & Tax Preparation",
            "type":"Services"
        }
    ],
    "sg:phone":"+1 905 983 5538",
    "sg:postcode":"L0B 1M0",
    "sg:province":"ON",
    "sg:tags":[
        "consultant"
    ],
    "wof:name":"Irwin Tax",
    "wof:placetype":"venue"
},
  "geometry": {"coordinates":[-78.60524700000001,44.003387],"type":"Point"}
}