{
  "type": "Feature",
  "properties": {
    "addr:full":"780 Rue Principale Saint-Ambroise-DE-Kildare QC J0K 1C0",
    "addr:housenumber":"780",
    "addr:postcode":"j0k 1c0",
    "addr:street":"Rue Principale",
    "iso:country":"CA",
    "sg:address":"780 Rue Principale",
    "sg:city":"Saint-Ambroise-DE-Kildare",
    "sg:classifiers":[
        {
            "category":"Organizations",
            "subcategory":"Religious Organization",
            "type":"Services"
        }
    ],
    "sg:phone":"+1 514 753 3055",
    "sg:postcode":"J0K 1C0",
    "sg:province":"QC",
    "sg:tags":[
        "church"
    ],
    "wof:name":"St Ambroise Catholic Church",
    "wof:placetype":"venue"
},
  "geometry": {"coordinates":[-73.55594600000001,46.075932],"type":"Point"}
}