{
  "type": "Feature",
  "properties": {
    "addr:full":"9500 Boul Parkway Anjou QC H1J 1N9",
    "addr:housenumber":"9500",
    "addr:postcode":"h1j 1n9",
    "addr:street":"Boul Parkway",
    "iso:country":"CA",
    "sg:address":"9500 Boul Parkway",
    "sg:city":"Anjou",
    "sg:classifiers":[
        {
            "category":"Freight",
            "type":"Transportation"
        }
    ],
    "sg:phone":"+1 514 352 5700",
    "sg:postcode":"H1J 1N9",
    "sg:province":"QC",
    "sg:tags":[
        "trucking"
    ],
    "wof:name":"Entreprises Real Caron Ltee",
    "wof:placetype":"venue"
},
  "geometry": {"coordinates":[-73.5695724487,45.6160316467],"type":"Point"}
}