{
  "type": "Feature",
  "properties": {
    "addr:full":"32 Fourth Ave Kingston ON K7K 2K2",
    "addr:housenumber":"32",
    "addr:postcode":"k7k 2k2",
    "addr:street":"Fourth Ave",
    "iso:country":"CA",
    "sg:address":"32 Fourth Ave",
    "sg:city":"Kingston",
    "sg:classifiers":[
        {
            "category":"Wholesale",
            "subcategory":"Furniture",
            "type":"Manufacturing & Wholesale Goods"
        }
    ],
    "sg:phone":"+1 613 531 6230",
    "sg:postcode":"K7K 2K2",
    "sg:province":"ON",
    "sg:tags":[
        "furnishing",
        "church"
    ],
    "wof:name":"Ncs Church Envelope CO",
    "wof:placetype":"venue"
},
  "geometry": {"coordinates":[-76.49928300000001,44.24538],"type":"Point"}
}