{
  "type": "Feature",
  "properties": {
    "addr:full":"10827 Boul Pie-Ix Montreal-Nord QC H1H 4A9",
    "addr:housenumber":"10827",
    "addr:postcode":"h1h 4a9",
    "addr:street":"Boul Pie-Ix",
    "iso:country":"CA",
    "sg:address":"10827 Boul Pie-Ix",
    "sg:city":"Montreal-Nord",
    "sg:classifiers":[
        {
            "category":"Restaurant",
            "type":"Food & Drink"
        }
    ],
    "sg:phone":"+1 514 324 9792",
    "sg:postcode":"H1H 4A9",
    "sg:province":"QC",
    "wof:name":"Restaurant Chez Toto",
    "wof:placetype":"venue"
},
  "geometry": {"coordinates":[-73.636826,45.590744],"type":"Point"}
}