{
  "type": "Feature",
  "properties": {
    "addr:full":"207 6th Ave W Vancouver BC V5Y 1K7",
    "addr:housenumber":"207",
    "addr:postcode":"v5y 1k7",
    "addr:street":"6Th Ave W",
    "iso:country":"CA",
    "sg:address":"207 6th Ave W",
    "sg:city":"Vancouver",
    "sg:classifiers":[
        {
            "category":"Wholesale",
            "subcategory":"Groceries",
            "type":"Manufacturing & Wholesale Goods"
        }
    ],
    "sg:phone":"+1 604 681 9953",
    "sg:postcode":"V5Y 1K7",
    "sg:province":"BC",
    "sg:tags":[
        "grocer"
    ],
    "wof:name":"Lunapads International",
    "wof:placetype":"venue"
},
  "geometry": {"coordinates":[-123.109672546,49.265789032],"type":"Point"}
}