{
  "type": "Feature",
  "properties": {
    "addr:full":"2 George St N Cambridge ON N1S 2M7",
    "addr:housenumber":"2",
    "addr:postcode":"n1s 2m7",
    "addr:street":"George St N",
    "iso:country":"CA",
    "sg:address":"2 George St N",
    "sg:city":"Cambridge",
    "sg:classifiers":[
        {
            "category":"Shopping",
            "subcategory":"Pharmacy",
            "type":"Retail Goods"
        }
    ],
    "sg:phone":"+1 519 623 3900",
    "sg:postcode":"N1S 2M7",
    "sg:province":"ON",
    "wof:name":"Prescription Shoppe",
    "wof:placetype":"venue"
},
  "geometry": {"coordinates":[-80.318825,43.358269],"type":"Point"}
}