{
  "type": "Feature",
  "properties": {
    "addr:full":"North Vancouver BC V7M 2J5",
    "addr:postcode":"v7m 2j5",
    "iso:country":"CA",
    "sg:city":"North Vancouver",
    "sg:classifiers":[
        {
            "category":"Shopping",
            "type":"Retail Goods"
        }
    ],
    "sg:phone":"+1 604 980 5770",
    "sg:postcode":"V7M 2J5",
    "sg:province":"BC",
    "sg:tags":[
        "equipment",
        "wine",
        "supply"
    ],
    "wof:name":"B C Hobby Brewers & Vintners",
    "wof:placetype":"venue"
},
  "geometry": {"coordinates":[-123.07244900000001,49.323528],"type":"Point"}
}