{
  "type": "Feature",
  "properties": {
    "iso:country":"CA",
    "sg:address":"1450 Robertson St",
    "sg:city":"Trail",
    "sg:classifiers":[
        {
            "category":"Retail",
            "subcategory":"Car Wash",
            "type":"Services"
        }
    ],
    "sg:phone":"+1 250 368 9100",
    "sg:postcode":"V1R 4P5",
    "sg:province":"BC",
    "sg:tags":[
        "polishing",
        "washing"
    ],
    "wof:name":"Challenger Auto Detailing",
    "wof:placetype":"venue"
},
  "geometry": {"coordinates":[-117.70178199999999,49.098701],"type":"Point"}
}