{
  "type": "Feature",
  "properties": {
    "iso:country":"CA",
    "sg:city":"Repentigny",
    "sg:classifiers":[
        {
            "category":"Personal",
            "subcategory":"Beauty Salon",
            "type":"Services"
        }
    ],
    "sg:phone":"+1 450 657 1807",
    "sg:postcode":"J6A 2W5",
    "sg:province":"QC",
    "wof:name":"Visagerie",
    "wof:placetype":"venue"
},
  "geometry": {"coordinates":[-73.4308624268,45.753578186],"type":"Point"}
}