{
  "type": "Feature",
  "properties": {
    "addr:full":"12053 Boul Laurentien Montreal QC H4K 1N3",
    "addr:housenumber":"12053",
    "addr:postcode":"h4k 1n3",
    "addr:street":"Boul Laurentien",
    "iso:country":"CA",
    "sg:address":"12053 Boul Laurentien",
    "sg:city":"Montreal",
    "sg:classifiers":[
        {
            "category":"Autos & Motor Vehicles",
            "subcategory":"Boat Sales",
            "type":"Retail Goods"
        }
    ],
    "sg:phone":"+1 514 337 4141",
    "sg:postcode":"H4K 1N3",
    "sg:province":"QC",
    "sg:tags":[
        "dealer"
    ],
    "wof:name":"Ampco Marine",
    "wof:placetype":"venue"
},
  "geometry": {"coordinates":[-73.716927,45.526878],"type":"Point"}
}