{
  "type": "Feature",
  "properties": {
    "addr:full":"Burlington ON L7S 1T5",
    "addr:postcode":"l7s 1t5",
    "iso:country":"CA",
    "sg:city":"Burlington",
    "sg:classifiers":[
        {
            "category":"Building & Trades",
            "subcategory":"Construction",
            "type":"Services"
        }
    ],
    "sg:phone":"+1 905 333 0079",
    "sg:postcode":"L7S 1T5",
    "sg:province":"ON",
    "sg:tags":[
        "equipment",
        "kitchen",
        "maker",
        "cabinet"
    ],
    "wof:name":"Artisan Design",
    "wof:placetype":"venue"
},
  "geometry": {"coordinates":[-79.81234000000001,43.333599],"type":"Point"}
}