{
  "type": "Feature",
  "properties": {
    "addr:full":"156 3E Av Sainte-Anne-Des-Plaines QC J0N 1H0",
    "addr:housenumber":"156",
    "addr:postcode":"j0n 1h0",
    "addr:street":"3E Av",
    "iso:country":"CA",
    "sg:address":"156 3E Av",
    "sg:city":"Sainte-Anne-Des-Plaines",
    "sg:classifiers":[
        {
            "category":"Museum",
            "type":"Entertainment"
        }
    ],
    "sg:phone":"+1 450 478 4045",
    "sg:postcode":"J0N 1H0",
    "sg:province":"QC",
    "sg:tags":[
        "cultural",
        "government"
    ],
    "wof:name":"Ste Anne Plaine Ctr Culturl",
    "wof:placetype":"venue"
},
  "geometry": {"coordinates":[-73.8144454956,45.7602043152],"type":"Point"}
}