{
  "type": "Feature",
  "properties": {
    "addr:full":"88 Huron St New Hamburg ON N3A 1J3",
    "addr:housenumber":"88",
    "addr:postcode":"n3a 1j3",
    "addr:street":"Huron St",
    "iso:country":"CA",
    "sg:address":"88 Huron St",
    "sg:city":"New Hamburg",
    "sg:classifiers":[
        {
            "category":"Home & Garden",
            "subcategory":"Garden Supply",
            "type":"Retail Goods"
        }
    ],
    "sg:phone":"+1 519 662 3684",
    "sg:postcode":"N3A 1J3",
    "sg:province":"ON",
    "sg:tags":[
        "pet",
        "house",
        "bird",
        "food",
        "feeder"
    ],
    "wof:name":"Heritage Pet & Garden Counter",
    "wof:placetype":"venue"
},
  "geometry": {"coordinates":[-80.7113418579,43.3784446716],"type":"Point"}
}