{
  "type": "Feature",
  "properties": {
    "iso:country":"CA",
    "sg:city":"Calgary",
    "sg:classifiers":[
        {
            "category":"Building & Trades",
            "subcategory":"Plumbing",
            "type":"Services"
        }
    ],
    "sg:phone":"+1 403 288 4769",
    "sg:postcode":"T3B 2G6",
    "sg:province":"AB",
    "sg:tags":[
        "contractor"
    ],
    "wof:name":"W & R Plumbing & Heating Ltd",
    "wof:placetype":"venue"
},
  "geometry": {"coordinates":[-114.181396484,51.0853462219],"type":"Point"}
}