{
  "type": "Feature",
  "properties": {
    "addr:full":"149 Rue Saint-Eustache Saint-Eustache QC J7R 2L6",
    "addr:housenumber":"149",
    "addr:postcode":"j7r 2l6",
    "addr:street":"Rue Saint-Eustache",
    "iso:country":"CA",
    "sg:address":"149 Rue Saint-Eustache",
    "sg:city":"Saint-Eustache",
    "sg:classifiers":[
        {
            "category":"Professional",
            "subcategory":"Business Services",
            "type":"Services"
        }
    ],
    "sg:phone":"+1 450 473 2122",
    "sg:postcode":"J7R 2L6",
    "sg:province":"QC",
    "sg:tags":[
        "notary"
    ],
    "wof:name":"Danis, Janique A",
    "wof:placetype":"venue"
},
  "geometry": {"coordinates":[-73.893021,45.558731],"type":"Point"}
}