{
  "type": "Feature",
  "properties": {
    "addr:full":"30 Main St E #3 Markdale ON N0C 1H0",
    "addr:housenumber":"30",
    "addr:postcode":"n0c 1h0",
    "addr:street":"Main St E # 3",
    "iso:country":"CA",
    "sg:address":"30 Main St E #3",
    "sg:city":"Markdale",
    "sg:classifiers":[
        {
            "category":"Personal",
            "subcategory":"Beauty Salon",
            "type":"Services"
        }
    ],
    "sg:phone":"+1 519 986 2804",
    "sg:postcode":"N0C 1H0",
    "sg:province":"ON",
    "wof:name":"Tracy's Hair Boutique",
    "wof:placetype":"venue"
},
  "geometry": {"coordinates":[-80.647575,44.319279],"type":"Point"}
}