{
  "type": "Feature",
  "properties": {
    "addr:full":"Nanaimo BC V9R 2S5",
    "addr:postcode":"v9r 2s5",
    "iso:country":"CA",
    "sg:city":"Nanaimo",
    "sg:classifiers":[
        {
            "category":"Manufacturing",
            "subcategory":"Building Materials",
            "type":"Manufacturing & Wholesale Goods"
        }
    ],
    "sg:phone":"+1 250 754 1962",
    "sg:postcode":"V9R 2S5",
    "sg:province":"BC",
    "sg:tags":[
        "plywood",
        "veneer"
    ],
    "wof:name":"Coastland Wood Industries Ltd",
    "wof:placetype":"venue"
},
  "geometry": {"coordinates":[-123.93549346899999,49.1616439819],"type":"Point"}
}