{
  "type": "Feature",
  "properties": {
    "addr:full":"2715 Jane St North York ON M3L 1S3",
    "addr:housenumber":"2715",
    "addr:postcode":"m3l 1s3",
    "addr:street":"Jane St",
    "iso:country":"CA",
    "sg:address":"2715 Jane St",
    "sg:city":"North York",
    "sg:classifiers":[
        {
            "category":"Health Services",
            "subcategory":"Doctor",
            "type":"Services"
        }
    ],
    "sg:phone":"+1 416 742 5111",
    "sg:postcode":"M3L 1S3",
    "sg:province":"ON",
    "sg:tags":[
        "dentist"
    ],
    "wof:name":"Sheppard Jane Dental Clinic",
    "wof:placetype":"venue"
},
  "geometry": {"coordinates":[-79.51325199999999,43.740341],"type":"Point"}
}