{
  "type": "Feature",
  "properties": {
    "addr:full":"1414 Rue Drummond # 1024 Montreal QC H3G 1W1",
    "addr:housenumber":"1414",
    "addr:postcode":"h3g 1w1",
    "addr:street":"Rue Drummond # 1024",
    "iso:country":"CA",
    "sg:address":"1414 Rue Drummond # 1024",
    "sg:city":"Montreal",
    "sg:classifiers":[
        {
            "category":"Health Services",
            "subcategory":"Doctor",
            "type":"Services"
        }
    ],
    "sg:phone":"+1 514 844 3470",
    "sg:postcode":"H3G 1W1",
    "sg:province":"QC",
    "sg:tags":[
        "dentist"
    ],
    "wof:name":"Owen, Peter DDS",
    "wof:placetype":"venue"
},
  "geometry": {"coordinates":[-73.5749053955,45.4988136292],"type":"Point"}
}