{
  "type": "Feature",
  "properties": {
    "addr:full":"2236 80 Ave NW Edmonton AB T6P 1N2",
    "addr:housenumber":"2236",
    "addr:postcode":"t6p 1n2",
    "addr:street":"80 Ave Nw",
    "iso:country":"CA",
    "sg:address":"2236 80 Ave NW",
    "sg:city":"Edmonton",
    "sg:classifiers":[
        {
            "category":"Manufacturing",
            "subcategory":"Tools & Machinery",
            "type":"Manufacturing & Wholesale Goods"
        }
    ],
    "sg:phone":"+1 780 440 1942",
    "sg:postcode":"T6P 1N2",
    "sg:province":"AB",
    "sg:tags":[
        "instrument",
        "radioactivity"
    ],
    "wof:name":"Enviropac Inc",
    "wof:placetype":"venue"
},
  "geometry": {"coordinates":[-113.377815,53.516376],"type":"Point"}
}