{
  "type": "Feature",
  "properties": {
    "iso:country":"CA",
    "sg:address":"7050 Duncan St",
    "sg:city":"Powell River",
    "sg:classifiers":[
        {
            "category":"Home & Garden",
            "subcategory":"Garden Supply",
            "type":"Retail Goods"
        }
    ],
    "sg:phone":"+1 604 485 9878",
    "sg:postcode":"V8A 1V9",
    "sg:province":"BC",
    "sg:tags":[
        "nurseryman",
        "center"
    ],
    "wof:name":"Mother Nature Garden Farm",
    "wof:placetype":"venue"
},
  "geometry": {"coordinates":[-124.518562317,49.8356895447],"type":"Point"}
}