{
  "type": "Feature",
  "properties": {
    "addr:full":"40 High St SE Calgary AB T2Z 3T8",
    "addr:housenumber":"40",
    "addr:postcode":"t2z 3t8",
    "addr:street":"High St Se",
    "iso:country":"CA",
    "sg:address":"40 High St SE",
    "sg:city":"Calgary",
    "sg:classifiers":[
        {
            "category":"Retail",
            "subcategory":"Veterinary Services",
            "type":"Services"
        }
    ],
    "sg:phone":"+1 403 257 6105",
    "sg:postcode":"T2Z 3T8",
    "sg:province":"AB",
    "sg:tags":[
        "veterinarian"
    ],
    "wof:name":"Mc Kenzie Towne Animal Clinic",
    "wof:placetype":"venue"
},
  "geometry": {"coordinates":[-113.960266,50.9156],"type":"Point"}
}