{
  "type": "Feature",
  "properties": {
    "addr:full":"7860 Rue Fleuricourt Saint-Leonard QC H1R 2L3",
    "addr:housenumber":"7860",
    "addr:postcode":"h1r 2l3",
    "addr:street":"Rue Fleuricourt",
    "iso:country":"CA",
    "sg:address":"7860 Rue Fleuricourt",
    "sg:city":"Saint-Leonard",
    "sg:classifiers":[
        {
            "category":"Manufacturing",
            "subcategory":"Food",
            "type":"Manufacturing & Wholesale Goods"
        }
    ],
    "sg:phone":"+1 514 327 6727",
    "sg:postcode":"H1R 2L3",
    "sg:province":"QC",
    "sg:tags":[
        "tea",
        "coffee",
        "product"
    ],
    "wof:name":"Ropar Inc",
    "wof:placetype":"venue"
},
  "geometry": {"coordinates":[-73.59129299999999,45.581993],"type":"Point"}
}