{
  "type": "Feature",
  "properties": {
    "addr:full":"1405 Boul Henri-Bourassa E Montreal QC H2C 1H1",
    "addr:housenumber":"1405",
    "addr:postcode":"h2c 1h1",
    "addr:street":"Boul Henri-Bourassa E",
    "iso:country":"CA",
    "sg:address":"1405 Boul Henri-Bourassa E",
    "sg:city":"Montreal",
    "sg:classifiers":[
        {
            "category":"Shopping",
            "subcategory":"Computers & Home Electronics",
            "type":"Retail Goods"
        }
    ],
    "sg:phone":"+1 514 335 0405",
    "sg:postcode":"H2C 1H1",
    "sg:province":"QC",
    "sg:tags":[
        "repair",
        "dealer",
        "equipment"
    ],
    "wof:name":"Calgah Systemes Informatiques",
    "wof:placetype":"venue"
},
  "geometry": {"coordinates":[-73.66260528559999,45.5628051758],"type":"Point"}
}