{
  "type": "Feature",
  "properties": {
    "addr:full":"Altona MB R0G 0B0",
    "addr:postcode":"r0g 0b0",
    "iso:country":"CA",
    "sg:city":"Altona",
    "sg:classifiers":[
        {
            "category":"Farming",
            "subcategory":"Nursery",
            "type":"Manufacturing & Wholesale Goods"
        }
    ],
    "sg:phone":"+1 204 324 6658",
    "sg:postcode":"R0G 0B0",
    "sg:province":"MB",
    "sg:tags":[
        "greenhouse"
    ],
    "wof:name":"Altona Greenhouse",
    "wof:placetype":"venue"
},
  "geometry": {"coordinates":[-97.557014,49.110916],"type":"Point"}
}