{
  "type": "Feature",
  "properties": {
    "iso:country":"CA",
    "sg:address":"2120 Queen St E",
    "sg:city":"Toronto",
    "sg:classifiers":[
        {
            "category":"Restaurant",
            "type":"Food & Drink"
        }
    ],
    "sg:phone":"+1 416 699 9444",
    "sg:postcode":"M4E 1E2",
    "sg:province":"ON",
    "wof:name":"Mersini",
    "wof:placetype":"venue"
},
  "geometry": {"coordinates":[-79.2946853638,43.6712989807],"type":"Point"}
}