{
  "type": "Feature",
  "properties": {
    "addr:full":"Calgary AB T2A 0V1",
    "addr:postcode":"t2a 0v1",
    "iso:country":"CA",
    "sg:city":"Calgary",
    "sg:classifiers":[
        {
            "category":"Restaurant",
            "type":"Food & Drink"
        }
    ],
    "sg:phone":"+1 403 248 7000",
    "sg:postcode":"T2A 0V1",
    "sg:province":"AB",
    "sg:tags":[
        "out",
        "pizza"
    ],
    "wof:name":"Sambouca's",
    "wof:placetype":"venue"
},
  "geometry": {"coordinates":[-113.96704099999999,51.037987],"type":"Point"}
}