{
  "type": "Feature",
  "properties": {
    "addr:full":"2146 Rue DE LA Province Longueuil QC J4G 1R7",
    "addr:housenumber":"2146",
    "addr:postcode":"j4g 1r7",
    "addr:street":"Rue De La Province",
    "iso:country":"CA",
    "sg:address":"2146 Rue DE LA Province",
    "sg:city":"Longueuil",
    "sg:classifiers":[
        {
            "category":"Manufacturing",
            "subcategory":"Apparel",
            "type":"Manufacturing & Wholesale Goods"
        }
    ],
    "sg:phone":"+1 450 679 1275",
    "sg:postcode":"J4G 1R7",
    "sg:province":"QC",
    "sg:tags":[
        "embroidery"
    ],
    "wof:name":"Broderie Distinction",
    "wof:placetype":"venue"
},
  "geometry": {"coordinates":[-73.47139,45.564781],"type":"Point"}
}