{
  "type": "Feature",
  "properties": {
    "addr:full":"1693 Rue Principale Pohenegamook QC G0L 1J0",
    "addr:housenumber":"1693",
    "addr:postcode":"g0l 1j0",
    "addr:street":"Rue Principale",
    "iso:country":"CA",
    "sg:address":"1693 Rue Principale",
    "sg:city":"Pohenegamook",
    "sg:classifiers":[
        {
            "category":"Freight",
            "type":"Transportation"
        }
    ],
    "sg:phone":"+1 418 859 2215",
    "sg:postcode":"G0L 1J0",
    "sg:province":"QC",
    "sg:tags":[
        "trucking"
    ],
    "wof:name":"Transport Laurier St-Pierre",
    "wof:placetype":"venue"
},
  "geometry": {"coordinates":[-69.2618637085,47.4765777588],"type":"Point"}
}