{
  "type": "Feature",
  "properties": {
    "addr:full":"239 Main St W Markdale ON N0C 1H0",
    "addr:housenumber":"239",
    "addr:postcode":"n0c 1h0",
    "addr:street":"Main St W",
    "iso:country":"CA",
    "sg:address":"239 Main St W",
    "sg:city":"Markdale",
    "sg:classifiers":[
        {
            "category":"Building & Trades",
            "subcategory":"Equipment Rental",
            "type":"Services"
        }
    ],
    "sg:phone":"+1 519 372 1334",
    "sg:postcode":"N0C 1H0",
    "sg:province":"ON",
    "sg:tags":[
        "party"
    ],
    "wof:name":"Four Seasons Party Rentals Ltd",
    "wof:placetype":"venue"
},
  "geometry": {"coordinates":[-80.65373200000001,44.313705],"type":"Point"}
}