{
  "type": "Feature",
  "properties": {
    "iso:country":"CA",
    "sg:address":"PO Box 216 STN Main",
    "sg:city":"Port Coquitlam",
    "sg:classifiers":[
        {
            "category":"Building & Trades",
            "subcategory":"Equipment Rental",
            "type":"Services"
        }
    ],
    "sg:phone":"+1 604 990 0350",
    "sg:postcode":"V3C 3V7",
    "sg:province":"BC",
    "sg:tags":[
        "toilet"
    ],
    "wof:name":"Jiffy John Rentals Ltd",
    "wof:placetype":"venue"
},
  "geometry": {"coordinates":[-122.793952942,49.2848854065],"type":"Point"}
}