{
  "type": "Feature",
  "properties": {
    "iso:country":"CA",
    "sg:address":"900 Rue Des Cascades O",
    "sg:city":"Saint-Hyacinthe",
    "sg:classifiers":[
        {
            "category":"Personal",
            "subcategory":"Beauty Salon",
            "type":"Services"
        }
    ],
    "sg:phone":"+1 450 773 2999",
    "sg:postcode":"J2S 3G4",
    "sg:province":"QC",
    "wof:name":"Evolution Coiffure",
    "wof:placetype":"venue"
},
  "geometry": {"coordinates":[-72.94231414790001,45.626991272],"type":"Point"}
}