{
  "type": "Feature",
  "properties": {
    "addr:full":"Delta BC V4K 4L1",
    "addr:postcode":"v4k 4l1",
    "iso:country":"CA",
    "sg:city":"Delta",
    "sg:classifiers":[
        {
            "category":"Health Services",
            "subcategory":"Medical Lab",
            "type":"Services"
        }
    ],
    "sg:phone":"+1 604 946 1855",
    "sg:postcode":"V4K 4L1",
    "sg:province":"BC",
    "wof:name":"Connolly, James R",
    "wof:placetype":"venue"
},
  "geometry": {"coordinates":[-123.06443,49.085064],"type":"Point"}
}