{
  "type": "Feature",
  "properties": {
    "addr:full":"4 Ridley St W Belleville ON K8P 1Y6",
    "addr:housenumber":"4",
    "addr:postcode":"k8p 1y6",
    "addr:street":"Ridley St W",
    "iso:country":"CA",
    "sg:address":"4 Ridley St W",
    "sg:city":"Belleville",
    "sg:classifiers":[
        {
            "category":"Building & Trades",
            "subcategory":"Landscaping Services",
            "type":"Services"
        }
    ],
    "sg:phone":"+1 613 968 9673",
    "sg:postcode":"K8P 1Y6",
    "sg:province":"ON",
    "sg:tags":[
        "landscape",
        "contractor"
    ],
    "wof:name":"M Dales Tree Svc",
    "wof:placetype":"venue"
},
  "geometry": {"coordinates":[-77.38954200000001,44.173496],"type":"Point"}
}