{
  "type": "Feature",
  "properties": {
    "iso:country":"CA",
    "sg:address":"308 Black Point Rd",
    "sg:city":"Barrington",
    "sg:classifiers":[
        {
            "category":"Travel",
            "subcategory":"Hotels & Motels",
            "type":"Entertainment"
        }
    ],
    "sg:phone":"+1 902 637 3535",
    "sg:postcode":"B0W 1E0",
    "sg:province":"NS",
    "sg:tags":[
        "cottage",
        "cabin"
    ],
    "wof:name":"Whispering Waves",
    "wof:placetype":"venue"
},
  "geometry": {"coordinates":[-65.6209030151,43.4204063416],"type":"Point"}
}