{
  "type": "Feature",
  "properties": {
    "addr:full":"Stayner ON L0M 1S0",
    "addr:postcode":"l0m 1s0",
    "iso:country":"CA",
    "sg:city":"Stayner",
    "sg:classifiers":[
        {
            "category":"Real Estate",
            "subcategory":"Real Estate Agent",
            "type":"Services"
        }
    ],
    "sg:phone":"+1 705 428 2900",
    "sg:postcode":"L0M 1S0",
    "sg:province":"ON",
    "wof:name":"One Stop Realty",
    "wof:placetype":"venue"
},
  "geometry": {"coordinates":[-80.0783081055,44.4221992493],"type":"Point"}
}