{
  "type": "Feature",
  "properties": {
    "addr:full":"1261 3E Av Val-D'Or QC J9P 1V4",
    "addr:housenumber":"1261",
    "addr:postcode":"j9p 1v4",
    "addr:street":"3E Av Val-D'Or",
    "iso:country":"CA",
    "sg:address":"1261 3E Av",
    "sg:city":"Val-D'Or",
    "sg:classifiers":[
        {
            "category":"Shopping",
            "type":"Retail Goods"
        }
    ],
    "sg:phone":"+1 819 825 6575",
    "sg:postcode":"J9P 1V4",
    "sg:province":"QC",
    "sg:tags":[
        "miscellaneous",
        "store"
    ],
    "wof:name":"Tabagie Du Gadget",
    "wof:placetype":"venue"
},
  "geometry": {"coordinates":[-70.87930297849999,48.3280334473],"type":"Point"}
}