{
  "type": "Feature",
  "properties": {
    "addr:full":"239 Main St E North Bay ON P1B 1B2",
    "addr:housenumber":"239",
    "addr:postcode":"p1b 1b2",
    "addr:street":"Main St E",
    "iso:country":"CA",
    "sg:address":"239 Main St E",
    "sg:city":"North Bay",
    "sg:classifiers":[
        {
            "category":"Professional",
            "subcategory":"Accounting & Tax Preparation",
            "type":"Services"
        }
    ],
    "sg:phone":"+1 705 494 8940",
    "sg:postcode":"P1B 1B2",
    "sg:province":"ON",
    "sg:tags":[
        "bookkeeping",
        "return",
        "filing",
        "general"
    ],
    "wof:name":"Fowler's Computerized Bookkeep",
    "wof:placetype":"venue"
},
  "geometry": {"coordinates":[-79.462486,46.308357],"type":"Point"}
}