{
  "type": "Feature",
  "properties": {
    "addr:full":"114 River Valley Dr Grand Bay-Westfield NB E5K 1A2",
    "addr:housenumber":"114",
    "addr:postcode":"e5k 1a2",
    "addr:street":"River Valley Dr",
    "iso:country":"CA",
    "sg:address":"114 River Valley Dr",
    "sg:city":"Grand Bay-Westfield",
    "sg:classifiers":[
        {
            "category":"Shopping",
            "subcategory":"Pharmacy",
            "type":"Retail Goods"
        }
    ],
    "sg:phone":"+1 506 738 8406",
    "sg:postcode":"E5K 1A2",
    "sg:province":"NB",
    "wof:name":"Grand Bay Guardian Drug Store",
    "wof:placetype":"venue"
},
  "geometry": {"coordinates":[-66.19516,45.299911],"type":"Point"}
}