{
  "type": "Feature",
  "properties": {
    "addr:full":"2457 Mount Forest Dr Burlington ON L7P 1J7",
    "addr:housenumber":"2457",
    "addr:postcode":"l7p 1j7",
    "addr:street":"Mount Forest Dr",
    "iso:country":"CA",
    "sg:address":"2457 Mount Forest Dr",
    "sg:city":"Burlington",
    "sg:classifiers":[
        {
            "category":"Insurance",
            "subcategory":"Insurance Agent",
            "type":"Services"
        }
    ],
    "sg:phone":"+1 905 335 4884",
    "sg:postcode":"L7P 1J7",
    "sg:province":"ON",
    "wof:name":"Rose Monachino Insurance Ltd",
    "wof:placetype":"venue"
},
  "geometry": {"coordinates":[-79.815872,43.359348],"type":"Point"}
}