{
  "type": "Feature",
  "properties": {
    "iso:country":"CA",
    "sg:address":"7230 Main St",
    "sg:city":"North Rustico",
    "sg:classifiers":[
        {
            "category":"Restaurant",
            "type":"Food & Drink"
        }
    ],
    "sg:phone":"+1 902 963 2669",
    "sg:postcode":"C0A 1X0",
    "sg:province":"PE",
    "wof:name":"Fisherman's Wharf Lobster",
    "wof:placetype":"venue"
},
  "geometry": {"coordinates":[-63.313206,46.458141],"type":"Point"}
}