{
  "type": "Feature",
  "properties": {
    "iso:country":"CA",
    "sg:address":"120 Rue Du Barry",
    "sg:city":"Kirkland",
    "sg:classifiers":[
        {
            "category":"Restaurant",
            "type":"Food & Drink"
        }
    ],
    "sg:phone":"+1 514 426 3888",
    "sg:postcode":"H9H 4P8",
    "sg:province":"QC",
    "wof:name":"Imperial Palace Restaurant",
    "wof:placetype":"venue"
},
  "geometry": {"coordinates":[-73.8632354736,45.4579048157],"type":"Point"}
}