{
  "type": "Feature",
  "properties": {
    "addr:full":"1965 Boul Perrot Notre-Dame-DE-L'Ile-Perrot QC J7V 8P4",
    "addr:housenumber":"1965",
    "addr:postcode":"j7v 8p4",
    "addr:street":"Boul Perrot Notre-Dame-De-L'Ile-Perrot",
    "iso:country":"CA",
    "sg:address":"1965 Boul Perrot",
    "sg:city":"Notre-Dame-DE-L'Ile-Perrot",
    "sg:classifiers":[
        {
            "category":"Government",
            "subcategory":"Office",
            "type":"Public Place"
        }
    ],
    "sg:phone":"+1 514 453 7239",
    "sg:postcode":"J7V 8P4",
    "sg:province":"QC",
    "sg:tags":[
        "village"
    ],
    "wof:name":"N-D-L'Ile Perrot Garage Mncpl",
    "wof:placetype":"venue"
},
  "geometry": {"coordinates":[-73.955368042,45.3937644958],"type":"Point"}
}