{
  "type": "Feature",
  "properties": {
    "addr:full":"5840 Boul Des Laurentides Laval QC H7H 1N1",
    "addr:housenumber":"5840",
    "addr:postcode":"h7h 1n1",
    "addr:street":"Boul Des Laurentides",
    "iso:country":"CA",
    "sg:address":"5840 Boul Des Laurentides",
    "sg:city":"Laval",
    "sg:classifiers":[
        {
            "category":"Wholesale",
            "subcategory":"Medical Equipment & Supplies",
            "type":"Manufacturing & Wholesale Goods"
        }
    ],
    "sg:phone":"+1 450 624 0390",
    "sg:postcode":"H7H 1N1",
    "sg:province":"QC",
    "wof:name":"Esthetique & Electrolyse",
    "wof:placetype":"venue"
},
  "geometry": {"coordinates":[-73.7529449463,45.6312980652],"type":"Point"}
}