{
  "type": "Feature",
  "properties": {
    "iso:country":"CA",
    "sg:address":"5565 Rue Pare",
    "sg:city":"Mont-Royal",
    "sg:classifiers":[
        {
            "category":"Real Estate",
            "subcategory":"Real Estate Agent",
            "type":"Services"
        }
    ],
    "sg:phone":"+1 514 344 3453",
    "sg:postcode":"H4P 1P7",
    "sg:province":"QC",
    "sg:tags":[
        "consultant",
        "management"
    ],
    "wof:name":"Fard Investment Ltee",
    "wof:placetype":"venue"
},
  "geometry": {"coordinates":[-73.661194,45.491783],"type":"Point"}
}