{
  "type": "Feature",
  "properties": {
    "addr:full":"5565 Rue Pare Mont-Royal QC H4P 1P7",
    "addr:housenumber":"5565",
    "addr:postcode":"h4p 1p7",
    "addr:street":"Rue Pare",
    "iso:country":"CA",
    "sg:address":"5565 Rue Pare",
    "sg:city":"Mont-Royal",
    "sg:classifiers":[
        {
            "category":"Real Estate",
            "subcategory":"Real Estate Agent",
            "type":"Services"
        }
    ],
    "sg:phone":"+1 514 344 3453",
    "sg:postcode":"H4P 1P7",
    "sg:province":"QC",
    "sg:tags":[
        "consultant",
        "management"
    ],
    "wof:name":"Fard Investment Ltee",
    "wof:placetype":"venue"
},
  "geometry": {"coordinates":[-73.66119399999999,45.491783],"type":"Point"}
}