{
  "type": "Feature",
  "properties": {
    "addr:full":"239 Saskatchewan Ave E Portage LA Prairie MB R1N 0L7",
    "addr:housenumber":"239",
    "addr:postcode":"r1n 0l7",
    "addr:street":"Saskatchewan Ave E",
    "iso:country":"CA",
    "sg:address":"239 Saskatchewan Ave E",
    "sg:city":"Portage LA Prairie",
    "sg:classifiers":[
        {
            "category":"Retail",
            "subcategory":"Auto Repair",
            "type":"Services"
        }
    ],
    "sg:phone":"+1 204 857 7811",
    "sg:postcode":"R1N 0L7",
    "sg:province":"MB",
    "sg:tags":[
        "repairing",
        "tire"
    ],
    "wof:name":"Fountain Tire",
    "wof:placetype":"venue"
},
  "geometry": {"coordinates":[-98.287003,49.972763],"type":"Point"}
}