{
  "type": "Feature",
  "properties": {
    "addr:full":"340 Av LA Sarre Malartic QC J0Y 1Z0",
    "addr:postcode":"j0y 1z0",
    "addr:street":"340 Av La Sarre",
    "iso:country":"CA",
    "sg:address":"340 Av LA Sarre",
    "sg:city":"Malartic",
    "sg:classifiers":[
        {
            "category":"Social Services",
            "subcategory":"Child Care",
            "type":"Services"
        }
    ],
    "sg:phone":"+1 819 757 2838",
    "sg:postcode":"J0Y 1Z0",
    "sg:province":"QC",
    "wof:name":"Centre DE LA Petite Enfance",
    "wof:placetype":"venue"
},
  "geometry": {"coordinates":[-78.12194100000001,48.132111],"type":"Point"}
}