{
  "type": "Feature",
  "properties": {
    "addr:full":"3746 Napier St Burnaby BC V5C 3E5",
    "addr:housenumber":"3746",
    "addr:postcode":"v5c 3e5",
    "addr:street":"Napier St",
    "iso:country":"CA",
    "sg:address":"3746 Napier St",
    "sg:city":"Burnaby",
    "sg:classifiers":[
        {
            "category":"Building & Trades",
            "subcategory":"Plumbing",
            "type":"Services"
        }
    ],
    "sg:phone":"+1 604 291 1471",
    "sg:postcode":"V5C 3E5",
    "sg:province":"BC",
    "sg:tags":[
        "mechanical",
        "contractor"
    ],
    "wof:name":"Lake Mechanical Ltd",
    "wof:placetype":"venue"
},
  "geometry": {"coordinates":[-123.022369,49.274727],"type":"Point"}
}