{
  "type": "Feature",
  "properties": {
    "addr:full":"650 King St E Oshawa ON L1H 1G5",
    "addr:housenumber":"650",
    "addr:postcode":"l1h 1g5",
    "addr:street":"King St E",
    "iso:country":"CA",
    "sg:address":"650 King St E",
    "sg:city":"Oshawa",
    "sg:classifiers":[
        {
            "category":"Personal",
            "subcategory":"Beauty Salon",
            "type":"Services"
        }
    ],
    "sg:phone":"+1 905 720 2052",
    "sg:postcode":"L1H 1G5",
    "sg:province":"ON",
    "sg:tags":[
        "manicuring"
    ],
    "wof:name":"Beauty Nails",
    "wof:placetype":"venue"
},
  "geometry": {"coordinates":[-78.840515,43.903072],"type":"Point"}
}