{
  "type": "Feature",
  "properties": {
    "addr:full":"135 St Clair Ave W Toronto ON M4V 1P4",
    "addr:housenumber":"135",
    "addr:postcode":"m4v 1p4",
    "addr:street":"St Clair Ave W",
    "iso:country":"CA",
    "sg:address":"135 St Clair Ave W",
    "sg:city":"Toronto",
    "sg:classifiers":[
        {
            "category":"Government",
            "subcategory":"Office",
            "type":"Public Place"
        }
    ],
    "sg:phone":"+1 416 325 4000",
    "sg:postcode":"M4V 1P4",
    "sg:province":"ON",
    "wof:name":"Ontario Environment Ministry",
    "wof:placetype":"venue"
},
  "geometry": {"coordinates":[-79.4009170532,43.6865959167],"type":"Point"}
}