{
  "type": "Feature",
  "properties": {
    "addr:full":"247 Hemlock St Ucluelet BC V0R 3A0",
    "addr:housenumber":"247",
    "addr:postcode":"bc v0r 3a0",
    "addr:street":"Hemlock St",
    "iso:country":"CA",
    "sg:address":"247 Hemlock St",
    "sg:city":"Ucluelet",
    "sg:classifiers":[
        {
            "category":"Travel",
            "subcategory":"Hotels & Motels",
            "type":"Entertainment"
        }
    ],
    "sg:phone":"+1 250 726 7732",
    "sg:postcode":"V0R 3A0",
    "sg:province":"BC",
    "wof:name":"West Coast Motel",
    "wof:placetype":"venue"
},
  "geometry": {"coordinates":[-125.55178832999999,48.9454994202],"type":"Point"}
}