{
  "type": "Feature",
  "properties": {
    "addr:full":"586 Grosvenor St London ON N5Y 3T3",
    "addr:housenumber":"586",
    "addr:postcode":"n5y 3t3",
    "addr:street":"Grosvenor St",
    "iso:country":"CA",
    "sg:address":"586 Grosvenor St",
    "sg:city":"London",
    "sg:classifiers":[
        {
            "category":"Organizations",
            "subcategory":"Religious Organization",
            "type":"Services"
        }
    ],
    "sg:phone":"+1 519 439 2581",
    "sg:postcode":"N5Y 3T3",
    "sg:province":"ON",
    "sg:tags":[
        "church"
    ],
    "wof:name":"Anglican Church",
    "wof:placetype":"venue"
},
  "geometry": {"coordinates":[-81.2400054932,43.004032135],"type":"Point"}
}