{
  "type": "Feature",
  "properties": {
    "addr:full":"Waterford ON N0E 1Y0",
    "addr:postcode":"n0e 1y0",
    "iso:country":"CA",
    "sg:city":"Waterford",
    "sg:classifiers":[
        {
            "category":"Arts & Performance",
            "subcategory":"Theater",
            "type":"Entertainment"
        }
    ],
    "sg:phone":"+1 519 443 4351",
    "sg:postcode":"N0E 1Y0",
    "sg:province":"ON",
    "sg:tags":[
        "bureau"
    ],
    "wof:name":"Platinum Enterprises",
    "wof:placetype":"venue"
},
  "geometry": {"coordinates":[-80.241058,42.944675],"type":"Point"}
}