{
  "type": "Feature",
  "properties": {
    "addr:full":"597 Sheraton Rd Burlington ON L7L 4B3",
    "addr:housenumber":"597",
    "addr:postcode":"l7l 4b3",
    "addr:street":"Sheraton Rd",
    "iso:country":"CA",
    "sg:address":"597 Sheraton Rd",
    "sg:city":"Burlington",
    "sg:classifiers":[
        {
            "category":"Professional",
            "subcategory":"Management & Consulting",
            "type":"Services"
        }
    ],
    "sg:phone":"+1 905 681 7532",
    "sg:postcode":"L7L 4B3",
    "sg:province":"ON",
    "sg:tags":[
        "marketing",
        "consultant"
    ],
    "wof:name":"Rejenmor",
    "wof:placetype":"venue"
},
  "geometry": {"coordinates":[-79.755882,43.373669],"type":"Point"}
}