{
  "type": "Feature",
  "properties": {
    "addr:full":"4380 No. 3 Rd # 1275 Richmond BC V6X 3V7",
    "addr:postcode":"4380;v6x 3v7",
    "addr:street":"3 Rd # 1275",
    "iso:country":"CA",
    "sg:address":"4380 No. 3 Rd # 1275",
    "sg:city":"Richmond",
    "sg:classifiers":[
        {
            "category":"Shopping",
            "subcategory":"Used Merchandise",
            "type":"Retail Goods"
        }
    ],
    "sg:phone":"+1 604 231 0308",
    "sg:postcode":"V6X 3V7",
    "sg:province":"BC",
    "sg:tags":[
        "antique"
    ],
    "wof:name":"Albert's Antique Ctr",
    "wof:placetype":"venue"
},
  "geometry": {"coordinates":[-123.136260986,49.181854248],"type":"Point"}
}