{
  "type": "Feature",
  "properties": {
    "addr:full":"612 Squier St Thunder Bay ON P7B 4A8",
    "addr:housenumber":"612",
    "addr:postcode":"p7b 4a8",
    "addr:street":"Squier St",
    "iso:country":"CA",
    "sg:address":"612 Squier St",
    "sg:city":"Thunder Bay",
    "sg:classifiers":[
        {
            "category":"Shopping",
            "subcategory":"Hobbies, Toys, & Games",
            "type":"Retail Goods"
        }
    ],
    "sg:phone":"+1 807 345 3784",
    "sg:postcode":"P7B 4A8",
    "sg:province":"ON",
    "sg:tags":[
        "bingo",
        "supply"
    ],
    "wof:name":"Bazaar & Novelty",
    "wof:placetype":"venue"
},
  "geometry": {"coordinates":[-89.2469863892,48.4161224365],"type":"Point"}
}