{
  "type": "Feature",
  "properties": {
    "addr:full":"Burlington ON L7N 2H4",
    "addr:postcode":"l7n 2h4",
    "iso:country":"CA",
    "sg:city":"Burlington",
    "sg:classifiers":[
        {
            "category":"Real Estate",
            "subcategory":"Real Estate Operator",
            "type":"Services"
        }
    ],
    "sg:phone":"+1 905 637 2225",
    "sg:postcode":"L7N 2H4",
    "sg:province":"ON",
    "sg:tags":[
        "apartment"
    ],
    "wof:name":"Kaf Development Ltd",
    "wof:placetype":"venue"
},
  "geometry": {"coordinates":[-79.786896,43.341682],"type":"Point"}
}