{
  "type": "Feature",
  "properties": {
    "addr:full":"570 63E Rue E Charlesbourg QC G1H 1Y8",
    "addr:housenumber":"570",
    "addr:postcode":"g1h 1y8",
    "addr:street":"63E Rue E",
    "iso:country":"CA",
    "sg:address":"570 63E Rue E",
    "sg:city":"Charlesbourg",
    "sg:classifiers":[
        {
            "category":"Food & Beverages",
            "subcategory":"Groceries & Convenience Stores",
            "type":"Retail Goods"
        }
    ],
    "sg:phone":"+1 418 626 0527",
    "sg:postcode":"G1H 1Y8",
    "sg:province":"QC",
    "sg:tags":[
        "grocer"
    ],
    "wof:name":"Accommodation St-Jerome Enr",
    "wof:placetype":"venue"
},
  "geometry": {"coordinates":[-71.2515335083,46.8458786011],"type":"Point"}
}