{
  "type": "Feature",
  "properties": {
    "addr:full":"118 Av DE L'Eglise Dolbeau-Mistassini QC G8L 4W4",
    "addr:postcode":"g8l 4w4",
    "addr:street":"118 Av De L'Eglise",
    "iso:country":"CA",
    "sg:address":"118 Av DE L'Eglise",
    "sg:city":"Dolbeau-Mistassini",
    "sg:classifiers":[
        {
            "category":"Shopping",
            "subcategory":"Books",
            "type":"Retail Goods"
        }
    ],
    "sg:phone":"+1 418 276 4187",
    "sg:postcode":"G8L 4W4",
    "sg:province":"QC",
    "sg:tags":[
        "dealer"
    ],
    "wof:name":"Librairie Myrtille Ltee",
    "wof:placetype":"venue"
},
  "geometry": {"coordinates":[-72.20044708250001,48.8933486938],"type":"Point"}
}