{
  "type": "Feature",
  "properties": {
    "addr:full":"1201 2nd St Estevan SK S4A 0M1",
    "addr:housenumber":"1201",
    "addr:postcode":"s4a 0m1",
    "addr:street":"2Nd St",
    "iso:country":"CA",
    "sg:address":"1201 2nd St",
    "sg:city":"Estevan",
    "sg:classifiers":[
        {
            "category":"Social Services",
            "type":"Services"
        }
    ],
    "sg:phone":"+1 306 634 6428",
    "sg:postcode":"S4A 0M1",
    "sg:province":"SK",
    "sg:tags":[
        "organization",
        "welfare"
    ],
    "wof:name":"Smile Svc Inc",
    "wof:placetype":"venue"
},
  "geometry": {"coordinates":[-102.99646799999999,49.139004],"type":"Point"}
}