{
  "type": "Feature",
  "properties": {
    "addr:full":"8 London St # 75 Happy Valley-Goose Bay NL A0P 1E0",
    "addr:housenumber":"8",
    "addr:postcode":"a0p 1e0",
    "addr:street":"London St # 75",
    "iso:country":"CA",
    "sg:address":"8 London St # 75",
    "sg:city":"Happy Valley-Goose Bay",
    "sg:classifiers":[
        {
            "category":"Wholesale",
            "subcategory":"Groceries",
            "type":"Manufacturing & Wholesale Goods"
        }
    ],
    "sg:phone":"+1 709 896 3795",
    "sg:postcode":"A0P 1E0",
    "sg:province":"NL",
    "sg:tags":[
        "beverage"
    ],
    "wof:name":"Nor-Lab Ltd",
    "wof:placetype":"venue"
},
  "geometry": {"coordinates":[-60.4039955139,53.32604599],"type":"Point"}
}