{
  "type": "Feature",
  "properties": {
    "addr:full":"Scarborough ON M1P 4R9",
    "addr:postcode":"m1p 4r9",
    "iso:country":"CA",
    "sg:city":"Scarborough",
    "sg:classifiers":[
        {
            "category":"Wholesale",
            "subcategory":"Machinery & Supplies",
            "type":"Manufacturing & Wholesale Goods"
        }
    ],
    "sg:phone":"+1 416 755 3351",
    "sg:postcode":"M1P 4R9",
    "sg:province":"ON",
    "sg:tags":[
        "equipment",
        "drying"
    ],
    "wof:name":"Process Drying & Filtration CO",
    "wof:placetype":"venue"
},
  "geometry": {"coordinates":[-79.274033,43.774963],"type":"Point"}
}