{
  "type": "Feature",
  "properties": {
    "addr:full":"1169 Parisien St Gloucester ON K1B 4W4",
    "addr:housenumber":"1169",
    "addr:postcode":"k1b 4w4",
    "addr:street":"Parisien St",
    "iso:country":"CA",
    "sg:address":"1169 Parisien St",
    "sg:city":"Gloucester",
    "sg:classifiers":[
        {
            "category":"Wholesale",
            "subcategory":"Books, Periodicals, & Newspapers",
            "type":"Manufacturing & Wholesale Goods"
        }
    ],
    "sg:phone":"+1 613 745 3098",
    "sg:postcode":"K1B 4W4",
    "sg:province":"ON",
    "sg:tags":[
        "dealer"
    ],
    "wof:name":"A M Productions",
    "wof:placetype":"venue"
},
  "geometry": {"coordinates":[-75.62758636469999,45.4193725586],"type":"Point"}
}