{
  "type": "Feature",
  "properties": {
    "addr:full":"4910 Yonge St North York ON M2N 5N5",
    "addr:housenumber":"4910",
    "addr:postcode":"m2n 5n5",
    "addr:street":"Yonge St",
    "iso:country":"CA",
    "sg:address":"4910 Yonge St",
    "sg:city":"North York",
    "sg:classifiers":[
        {
            "category":"Wholesale",
            "subcategory":"Books, Periodicals, & Newspapers",
            "type":"Manufacturing & Wholesale Goods"
        }
    ],
    "sg:phone":"+1 416 224 5300",
    "sg:postcode":"M2N 5N5",
    "sg:province":"ON",
    "sg:tags":[
        "dealer"
    ],
    "wof:name":"Academic Book Svc",
    "wof:placetype":"venue"
},
  "geometry": {"coordinates":[-79.41175800000001,43.764114],"type":"Point"}
}