{
  "type": "Feature",
  "properties": {
    "addr:full":"12229 38 St NW Edmonton AB T5W 2J2",
    "addr:housenumber":"12229",
    "addr:postcode":"t5w 2j2",
    "addr:street":"38 St Nw",
    "iso:country":"CA",
    "sg:address":"12229 38 St NW",
    "sg:city":"Edmonton",
    "sg:classifiers":[
        {
            "category":"Organizations",
            "subcategory":"Religious Organization",
            "type":"Services"
        }
    ],
    "sg:phone":"+1 780 479 0746",
    "sg:postcode":"T5W 2J2",
    "sg:province":"AB",
    "sg:tags":[
        "church"
    ],
    "wof:name":"Bible Presbyterian Church",
    "wof:placetype":"venue"
},
  "geometry": {"coordinates":[-113.399673462,53.5773200989],"type":"Point"}
}