{
  "type": "Feature",
  "properties": {
    "addr:full":"Saskatoon SK S7H 0V7",
    "addr:postcode":"s7h 0v7",
    "iso:country":"CA",
    "sg:city":"Saskatoon",
    "sg:classifiers":[
        {
            "category":"Professional",
            "subcategory":"Accounting & Tax Preparation",
            "type":"Services"
        }
    ],
    "sg:phone":"+1 306 374 6322",
    "sg:postcode":"S7H 0V7",
    "sg:province":"SK",
    "sg:tags":[
        "accountant",
        "return",
        "filing"
    ],
    "wof:name":"B Jolly Accounting Ltd",
    "wof:placetype":"venue"
},
  "geometry": {"coordinates":[-106.616631,52.11462],"type":"Point"}
}