{
  "type": "Feature",
  "properties": {
    "iso:country":"CA",
    "sg:city":"Sheet Harbour",
    "sg:classifiers":[
        {
            "category":"Health Services",
            "subcategory":"Doctor",
            "type":"Services"
        }
    ],
    "sg:phone":"+1 902 885 2298",
    "sg:postcode":"B0J 3B0",
    "sg:province":"NS",
    "sg:tags":[
        "physician",
        "surgeon"
    ],
    "wof:name":"Atkinson, Brad MD",
    "wof:placetype":"venue"
},
  "geometry": {"coordinates":[-62.5352134705,44.9217758179],"type":"Point"}
}