{
  "type": "Feature",
  "properties": {
    "addr:full":"10 Armagh Way Nepean ON K2J 4C3",
    "addr:housenumber":"10",
    "addr:postcode":"k2j 4c3",
    "addr:street":"Armagh Way",
    "iso:country":"CA",
    "sg:address":"10 Armagh Way",
    "sg:city":"Nepean",
    "sg:classifiers":[
        {
            "category":"Professional",
            "subcategory":"Employment Agencies",
            "type":"Services"
        }
    ],
    "sg:phone":"+1 613 823 0513",
    "sg:postcode":"K2J 4C3",
    "sg:province":"ON",
    "sg:tags":[
        "consultant",
        "search",
        "executive"
    ],
    "wof:name":"Smith Gunther Assoc Ltd",
    "wof:placetype":"venue"
},
  "geometry": {"coordinates":[-75.73159800000001,45.293304],"type":"Point"}
}