{
  "type": "Feature",
  "properties": {
    "addr:full":"Westlock AB T7P 1H4",
    "addr:postcode":"t7p 1h4",
    "iso:country":"CA",
    "sg:city":"Westlock",
    "sg:classifiers":[
        {
            "category":"Real Estate",
            "subcategory":"Real Estate Operator",
            "type":"Services"
        }
    ],
    "sg:phone":"+1 780 349 4371",
    "sg:postcode":"T7P 1H4",
    "sg:province":"AB",
    "sg:tags":[
        "mobile",
        "home",
        "community"
    ],
    "wof:name":"Westlock Trailer Inn Village",
    "wof:placetype":"venue"
},
  "geometry": {"coordinates":[-113.837020874,54.1535263062],"type":"Point"}
}