{
  "type": "Feature",
  "properties": {
    "iso:country":"CA",
    "sg:address":"1595 Bedford Hwy # 195",
    "sg:city":"Bedford",
    "sg:classifiers":[
        {
            "category":"Shopping",
            "subcategory":"News",
            "type":"Retail Goods"
        }
    ],
    "sg:phone":"+1 902 835 7955",
    "sg:postcode":"B4A 3Y4",
    "sg:province":"NS",
    "sg:tags":[
        "magazine"
    ],
    "wof:name":"Great Canadian News CO",
    "wof:placetype":"venue"
},
  "geometry": {"coordinates":[-63.655972,44.73278],"type":"Point"}
}