{
  "type": "Feature",
  "properties": {
    "addr:full":"11301 98 Ave Grande Prairie AB T8V 5A5",
    "addr:housenumber":"11301",
    "addr:postcode":"t8v 5a5",
    "addr:street":"98 Ave",
    "iso:country":"CA",
    "sg:address":"11301 98 Ave",
    "sg:city":"Grande Prairie",
    "sg:classifiers":[
        {
            "category":"Building & Trades",
            "subcategory":"Plumbing",
            "type":"Services"
        }
    ],
    "sg:phone":"+1 780 518 1114",
    "sg:postcode":"T8V 5A5",
    "sg:province":"AB",
    "sg:tags":[
        "contractor"
    ],
    "wof:name":"Holmes Plumbing & Heating",
    "wof:placetype":"venue"
},
  "geometry": {"coordinates":[-118.83529663100001,55.1687965393],"type":"Point"}
}