{
  "type": "Feature",
  "properties": {
    "addr:full":"218 Yonge St Toronto ON M5B 2H6",
    "addr:housenumber":"218",
    "addr:postcode":"m5b 2h6",
    "addr:street":"Yonge St",
    "iso:country":"CA",
    "sg:address":"218 Yonge St",
    "sg:city":"Toronto",
    "sg:classifiers":[
        {
            "category":"Restaurant",
            "type":"Food & Drink"
        }
    ],
    "sg:phone":"+1 416 408 3501",
    "sg:postcode":"M5B 2H6",
    "sg:province":"ON",
    "wof:name":"New York Fries",
    "wof:placetype":"venue"
},
  "geometry": {"coordinates":[-79.379784,43.653156],"type":"Point"}
}