{
  "type": "Feature",
  "properties": {
    "addr:full":"22 Ottawa St S Kitchener ON N2G 3S5",
    "addr:housenumber":"22",
    "addr:postcode":"n2g 3s5",
    "addr:street":"Ottawa St S",
    "iso:country":"CA",
    "sg:address":"22 Ottawa St S",
    "sg:city":"Kitchener",
    "sg:classifiers":[
        {
            "category":"Restaurant",
            "type":"Food & Drink"
        }
    ],
    "sg:phone":"+1 519 745 7682",
    "sg:postcode":"N2G 3S5",
    "sg:province":"ON",
    "wof:name":"Shanghai Restaurant",
    "wof:placetype":"venue"
},
  "geometry": {"coordinates":[-80.47219800000001,43.441601],"type":"Point"}
}