{
  "type": "Feature",
  "properties": {
    "addr:full":"5387 Bethesda Rd Stouffville ON L4A 7X3",
    "addr:housenumber":"5387",
    "addr:postcode":"l4a 7x3",
    "addr:street":"Bethesda Rd",
    "iso:country":"CA",
    "sg:address":"5387 Bethesda Rd",
    "sg:city":"Stouffville",
    "sg:classifiers":[
        {
            "category":"Manufacturing",
            "subcategory":"Glass & Minerals",
            "type":"Manufacturing & Wholesale Goods"
        }
    ],
    "sg:phone":"+1 905 640 5151",
    "sg:postcode":"L4A 7X3",
    "sg:province":"ON",
    "sg:tags":[
        "pipe",
        "drain"
    ],
    "wof:name":"Hyprescon Inc",
    "wof:placetype":"venue"
},
  "geometry": {"coordinates":[-79.277596,43.980064],"type":"Point"}
}