{
  "type": "Feature",
  "properties": {
    "addr:full":"4165 Ch Saint-Pierre Laterriere QC G7N 1X8",
    "addr:housenumber":"4165",
    "addr:postcode":"g7n 1x8",
    "addr:street":"Ch Saint-Pierre Laterriere",
    "iso:country":"CA",
    "sg:address":"4165 Ch Saint-Pierre",
    "sg:city":"Laterriere",
    "sg:classifiers":[
        {
            "category":"Farming",
            "subcategory":"Nursery",
            "type":"Manufacturing & Wholesale Goods"
        }
    ],
    "sg:phone":"+1 418 690 2358",
    "sg:postcode":"G7N 1X8",
    "sg:province":"QC",
    "sg:tags":[
        "glass",
        "greenhouse"
    ],
    "wof:name":"Verrieres Saguenay Lac St-Jean",
    "wof:placetype":"venue"
},
  "geometry": {"coordinates":[-71.1597824097,48.3524742126],"type":"Point"}
}