{
  "type": "Feature",
  "properties": {
    "addr:full":"Etobicoke ON M9V 5G5",
    "addr:postcode":"m9v 5g5",
    "iso:country":"CA",
    "sg:city":"Etobicoke",
    "sg:classifiers":[
        {
            "category":"Health Services",
            "subcategory":"Doctor",
            "type":"Services"
        }
    ],
    "sg:phone":"+1 416 743 4267",
    "sg:postcode":"M9V 5G5",
    "sg:province":"ON",
    "sg:tags":[
        "physician",
        "surgeon"
    ],
    "wof:name":"Wasserman, Gary MD",
    "wof:placetype":"venue"
},
  "geometry": {"coordinates":[-79.584373,43.740227],"type":"Point"}
}