{
  "type": "Feature",
  "properties": {
    "iso:country":"CA",
    "sg:address":"PO Box 39",
    "sg:city":"Clyde",
    "sg:classifiers":[
        {
            "category":"Building & Trades",
            "subcategory":"Construction",
            "type":"Services"
        }
    ],
    "sg:phone":"+1 780 348 5220",
    "sg:postcode":"T0G 0P0",
    "sg:province":"AB",
    "sg:tags":[
        "repairing",
        "remodeling",
        "contractor"
    ],
    "wof:name":"Original Renovations",
    "wof:placetype":"venue"
},
  "geometry": {"coordinates":[-113.636520386,54.1469955444],"type":"Point"}
}