{
  "type": "Feature",
  "properties": {
    "addr:full":"273 Rue Tache N Saint-Pascal QC G0L 3Y0",
    "addr:housenumber":"273",
    "addr:postcode":"g0l 3y0",
    "addr:street":"Rue Tache N",
    "iso:country":"CA",
    "sg:address":"273 Rue Tache N",
    "sg:city":"Saint-Pascal",
    "sg:classifiers":[
        {
            "category":"Autos & Motor Vehicles",
            "subcategory":"Fuel & Gas Station",
            "type":"Retail Goods"
        }
    ],
    "sg:phone":"+1 418 492 2406",
    "sg:postcode":"G0L 3Y0",
    "sg:province":"QC",
    "sg:tags":[
        "oil"
    ],
    "wof:name":"Libre Service DE L'Amitie Inc",
    "wof:placetype":"venue"
},
  "geometry": {"coordinates":[-69.81146200000001,47.530437],"type":"Point"}
}