{
  "type": "Feature",
  "properties": {
    "iso:country":"CA",
    "sg:address":"450 Rang Berthier N",
    "sg:city":"Berthierville",
    "sg:classifiers":[
        {
            "category":"Autos & Motor Vehicles",
            "subcategory":"Auto Supplies",
            "type":"Retail Goods"
        }
    ],
    "sg:phone":"+1 450 836 3586",
    "sg:postcode":"J0K 1A0",
    "sg:province":"QC",
    "sg:tags":[
        "hitch",
        "trailer",
        "welding"
    ],
    "wof:name":"Mirandette, Yvon",
    "wof:placetype":"venue"
},
  "geometry": {"coordinates":[-73.1784667969,46.0809059143],"type":"Point"}
}