{
  "type": "Feature",
  "properties": {
    "addr:full":"2030 Pilon St Chelmsford ON P0M 1L0",
    "addr:housenumber":"2030",
    "addr:postcode":"p0m 1l0",
    "addr:street":"Pilon St",
    "iso:country":"CA",
    "sg:address":"2030 Pilon St",
    "sg:city":"Chelmsford",
    "sg:classifiers":[
        {
            "category":"Professional",
            "subcategory":"Management & Consulting",
            "type":"Services"
        }
    ],
    "sg:phone":"+1 705 983 0005",
    "sg:postcode":"P0M 1L0",
    "sg:province":"ON",
    "sg:tags":[
        "consultant",
        "safety"
    ],
    "wof:name":"Safety Systems Training",
    "wof:placetype":"venue"
},
  "geometry": {"coordinates":[-81.175652,46.56509],"type":"Point"}
}