{
  "type": "Feature",
  "properties": {
    "addr:full":"1038 Austin Ave Coquitlam BC V3K 3P3",
    "addr:housenumber":"1038",
    "addr:postcode":"v3k 3p3",
    "addr:street":"Austin Ave",
    "iso:country":"CA",
    "sg:address":"1038 Austin Ave",
    "sg:city":"Coquitlam",
    "sg:classifiers":[
        {
            "category":"Shopping",
            "subcategory":"Used Merchandise",
            "type":"Retail Goods"
        }
    ],
    "sg:phone":"+1 604 939 0933",
    "sg:postcode":"V3K 3P3",
    "sg:province":"BC",
    "sg:tags":[
        "shop",
        "consignment"
    ],
    "wof:name":"Consign-It",
    "wof:placetype":"venue"
},
  "geometry": {"coordinates":[-122.864646912,49.2487754822],"type":"Point"}
}