{
  "type": "Feature",
  "properties": {
    "addr:full":"2441 Av Du Viaduc Charny QC G6X 2V1",
    "addr:housenumber":"2441",
    "addr:postcode":"g6x 2v1",
    "addr:street":"Av Du Viaduc",
    "iso:country":"CA",
    "sg:address":"2441 Av Du Viaduc",
    "sg:city":"Charny",
    "sg:classifiers":[
        {
            "category":"Health Services",
            "subcategory":"Nursing And Care Facility",
            "type":"Services"
        }
    ],
    "sg:phone":"+1 418 832 5143",
    "sg:postcode":"G6X 2V1",
    "sg:province":"QC",
    "sg:tags":[
        "home",
        "retirement",
        "community"
    ],
    "wof:name":"Residence Le Charnycois Enr",
    "wof:placetype":"venue"
},
  "geometry": {"coordinates":[-71.269936,46.712032],"type":"Point"}
}