{
  "type": "Feature",
  "properties": {
    "addr:full":"1045 St James St Winnipeg MB R3H 0K6",
    "addr:housenumber":"1045",
    "addr:postcode":"r3h 0k6",
    "addr:street":"St James St",
    "iso:country":"CA",
    "sg:address":"1045 St James St",
    "sg:city":"Winnipeg",
    "sg:classifiers":[
        {
            "category":"Shopping",
            "subcategory":"Luggage & Leather Goods",
            "type":"Retail Goods"
        }
    ],
    "sg:phone":"+1 204 774 9235",
    "sg:postcode":"R3H 0K6",
    "sg:province":"MB",
    "wof:name":"Danier Leather",
    "wof:placetype":"venue"
},
  "geometry": {"coordinates":[-97.20031,49.895378],"type":"Point"}
}