{
  "type": "Feature",
  "properties": {
    "addr:full":"3908 69 Ave NW Edmonton AB T6B 2V2",
    "addr:housenumber":"3908",
    "addr:postcode":"t6b 2v2",
    "addr:street":"69 Ave Nw",
    "iso:country":"CA",
    "sg:address":"3908 69 Ave NW",
    "sg:city":"Edmonton",
    "sg:classifiers":[
        {
            "category":"Manufacturing",
            "subcategory":"Tools & Machinery",
            "type":"Manufacturing & Wholesale Goods"
        }
    ],
    "sg:phone":"+1 780 468 2165",
    "sg:postcode":"T6B 2V2",
    "sg:province":"AB",
    "sg:tags":[
        "food",
        "equipment",
        "conveyor",
        "processing",
        "conveying"
    ],
    "wof:name":"Stanfos Inc",
    "wof:placetype":"venue"
},
  "geometry": {"coordinates":[-113.40164900000001,53.506035],"type":"Point"}
}