{
  "type": "Feature",
  "properties": {
    "addr:full":"Vancouver BC V6B 3H7",
    "addr:postcode":"v6b 3h7",
    "iso:country":"CA",
    "sg:city":"Vancouver",
    "sg:classifiers":[
        {
            "category":"Professional",
            "subcategory":"Lawyer & Legal Services",
            "type":"Services"
        }
    ],
    "sg:phone":"+1 604 688 7211",
    "sg:postcode":"V6B 3H7",
    "sg:province":"BC",
    "sg:tags":[
        "attorney"
    ],
    "wof:name":"Street Morrison",
    "wof:placetype":"venue"
},
  "geometry": {"coordinates":[-123.114403,49.283783],"type":"Point"}
}