{
  "type": "Feature",
  "properties": {
    "addr:full":"4975 Rue DE Sorel Montreal QC H4P 1G3",
    "addr:housenumber":"4975",
    "addr:postcode":"h4p 1g3",
    "addr:street":"Rue De Sorel",
    "iso:country":"CA",
    "sg:address":"4975 Rue DE Sorel",
    "sg:city":"Montreal",
    "sg:classifiers":[
        {
            "category":"Retail",
            "subcategory":"Car Wash",
            "type":"Services"
        }
    ],
    "sg:phone":"+1 514 736 4975",
    "sg:postcode":"H4P 1G3",
    "sg:province":"QC",
    "sg:tags":[
        "polishing",
        "washing"
    ],
    "wof:name":"Detaillants Show Car",
    "wof:placetype":"venue"
},
  "geometry": {"coordinates":[-73.6589889526,45.5011177063],"type":"Point"}
}