{
  "type": "Feature",
  "properties": {
    "addr:full":"172 Main St W Listowel ON N4W 1A1",
    "addr:housenumber":"172",
    "addr:postcode":"n4w 1a1",
    "addr:street":"Main St W",
    "iso:country":"CA",
    "sg:address":"172 Main St W",
    "sg:city":"Listowel",
    "sg:classifiers":[
        {
            "category":"Personal",
            "type":"Services"
        }
    ],
    "sg:phone":"+1 519 291 3129",
    "sg:postcode":"N4W 1A1",
    "sg:province":"ON",
    "sg:tags":[
        "wear",
        "formal"
    ],
    "wof:name":"B K's Bridal & Tuxedo Ctr",
    "wof:placetype":"venue"
},
  "geometry": {"coordinates":[-80.95407867430001,43.7317848206],"type":"Point"}
}