{
  "type": "Feature",
  "properties": {
    "addr:full":"New Westminster BC V3L 3B1",
    "addr:postcode":"v3l 3b1",
    "iso:country":"CA",
    "sg:city":"New Westminster",
    "sg:classifiers":[
        {
            "category":"Professional",
            "subcategory":"Accounting & Tax Preparation",
            "type":"Services"
        }
    ],
    "sg:phone":"+1 604 525 9295",
    "sg:postcode":"V3L 3B1",
    "sg:province":"BC",
    "sg:tags":[
        "accountant"
    ],
    "wof:name":"Olson & CO",
    "wof:placetype":"venue"
},
  "geometry": {"coordinates":[-122.91791499999999,49.211414],"type":"Point"}
}