{
  "type": "Feature",
  "properties": {
    "iso:country":"CA",
    "sg:city":"New Westminster",
    "sg:classifiers":[
        {
            "category":"Professional",
            "subcategory":"Accounting & Tax Preparation",
            "type":"Services"
        }
    ],
    "sg:phone":"+1 604 525 9295",
    "sg:postcode":"V3L 3B1",
    "sg:province":"BC",
    "sg:tags":[
        "accountant"
    ],
    "wof:name":"Olson & CO",
    "wof:placetype":"venue"
},
  "geometry": {"coordinates":[-122.917915,49.211414],"type":"Point"}
}