{
  "type": "Feature",
  "properties": {
    "addr:full":"4850 St. Catherines St Vancouver BC V5V 4M7",
    "addr:housenumber":"4850",
    "addr:postcode":"v5v 4m7",
    "addr:street":"St. Catherines St",
    "iso:country":"CA",
    "sg:address":"4850 St. Catherines St",
    "sg:city":"Vancouver",
    "sg:classifiers":[
        {
            "category":"Recreation",
            "type":"Entertainment"
        }
    ],
    "sg:phone":"+1 604 874 3038",
    "sg:postcode":"V5V 4M7",
    "sg:province":"BC",
    "sg:tags":[
        "amusement"
    ],
    "wof:name":"Vancouver South Lawn Bowling",
    "wof:placetype":"venue"
},
  "geometry": {"coordinates":[-123.085724,49.241062],"type":"Point"}
}