{
  "type": "Feature",
  "properties": {
    "addr:full":"431 Concession 2 Alfred ON K0B 1A0",
    "addr:housenumber":"431",
    "addr:postcode":"k0b 1a0",
    "addr:street":"Concession 2 Alfred",
    "iso:country":"CA",
    "sg:address":"431 Concession 2",
    "sg:city":"Alfred",
    "sg:classifiers":[
        {
            "category":"Retail",
            "subcategory":"Auto Repair",
            "type":"Services"
        }
    ],
    "sg:phone":"+1 613 678 5501",
    "sg:postcode":"K0B 1A0",
    "sg:province":"ON",
    "sg:tags":[
        "truck"
    ],
    "wof:name":"Serge Cadieux Mecanique Inc",
    "wof:placetype":"venue"
},
  "geometry": {"coordinates":[-74.88402600000001,45.557522],"type":"Point"}
}