{
  "type": "Feature",
  "properties": {
    "addr:full":"1350 Rue Sherbrooke O Montreal QC H3G 1J1",
    "addr:housenumber":"1350",
    "addr:postcode":"h3g 1j1",
    "addr:street":"Rue Sherbrooke O",
    "iso:country":"CA",
    "sg:address":"1350 Rue Sherbrooke O",
    "sg:city":"Montreal",
    "sg:classifiers":[
        {
            "category":"Manufacturing",
            "subcategory":"Paper Products",
            "type":"Manufacturing & Wholesale Goods"
        }
    ],
    "sg:phone":"+1 514 286 6124",
    "sg:postcode":"H3G 1J1",
    "sg:province":"QC",
    "sg:tags":[
        "pulp"
    ],
    "wof:name":"Travers Forest Products",
    "wof:placetype":"venue"
},
  "geometry": {"coordinates":[-73.5648574829,45.5247383118],"type":"Point"}
}