{
  "type": "Feature",
  "properties": {
    "addr:full":"Pickering ON L1W 3V4",
    "addr:postcode":"l1w 3v4",
    "iso:country":"CA",
    "sg:city":"Pickering",
    "sg:classifiers":[
        {
            "category":"Building & Trades",
            "subcategory":"Electrical",
            "type":"Services"
        }
    ],
    "sg:phone":"+1 905 619 6527",
    "sg:postcode":"L1W 3V4",
    "sg:province":"ON",
    "sg:tags":[
        "electric",
        "contractor"
    ],
    "wof:name":"Alltech Electrical Systems Inc",
    "wof:placetype":"venue"
},
  "geometry": {"coordinates":[-79.05626700000001,43.826466],"type":"Point"}
}