{
  "type": "Feature",
  "properties": {
    "addr:full":"1025 Pigeon Lake Lindsay ON K9V 4R5",
    "addr:housenumber":"1025",
    "addr:postcode":"k9v 4r5",
    "addr:street":"Pigeon Lake",
    "iso:country":"CA",
    "sg:address":"1025 Pigeon Lake",
    "sg:city":"Lindsay",
    "sg:classifiers":[
        {
            "category":"Shopping",
            "subcategory":"Computers & Home Electronics",
            "type":"Retail Goods"
        }
    ],
    "sg:phone":"+1 705 799 7340",
    "sg:postcode":"K9V 4R5",
    "sg:province":"ON",
    "sg:tags":[
        "equipment",
        "satellite",
        "system"
    ],
    "wof:name":"Lna Sales",
    "wof:placetype":"venue"
},
  "geometry": {"coordinates":[-78.59838104249999,44.3845481873],"type":"Point"}
}