{
  "type": "Feature",
  "properties": {
    "iso:country":"CA",
    "sg:address":"4630 Rue Belair",
    "sg:city":"Val-Morin",
    "sg:classifiers":[
        {
            "category":"Professional",
            "subcategory":"Accounting & Tax Preparation",
            "type":"Services"
        }
    ],
    "sg:phone":"+1 819 322 2525",
    "sg:postcode":"J0T 2R0",
    "sg:province":"QC",
    "sg:tags":[
        "accountant"
    ],
    "wof:name":"St-Laurent, Jean-Claude",
    "wof:placetype":"venue"
},
  "geometry": {"coordinates":[-74.16557312010001,45.9947471619],"type":"Point"}
}