{
  "type": "Feature",
  "properties": {
    "iso:country":"CA",
    "sg:city":"Elma",
    "sg:classifiers":[
        {
            "category":"Education",
            "subcategory":"School",
            "type":"Public Place"
        }
    ],
    "sg:phone":"+1 204 348 2686",
    "sg:postcode":"R0E 0Z0",
    "sg:province":"MB",
    "wof:name":"Riverside School",
    "wof:placetype":"venue"
},
  "geometry": {"coordinates":[-95.9072113037,49.8675689697],"type":"Point"}
}