{
  "type": "Feature",
  "properties": {
    "addr:full":"Campbell River BC V9W 3A4",
    "addr:postcode":"v9w 3a4",
    "iso:country":"CA",
    "sg:city":"Campbell River",
    "sg:classifiers":[
        {
            "category":"Food & Beverages",
            "subcategory":"Specialty",
            "type":"Retail Goods"
        }
    ],
    "sg:phone":"+1 250 286 6011",
    "sg:postcode":"V9W 3A4",
    "sg:province":"BC",
    "sg:tags":[
        "health",
        "vitamin",
        "diet"
    ],
    "wof:name":"Healthyway Vitamins Plus",
    "wof:placetype":"venue"
},
  "geometry": {"coordinates":[-125.24823000000001,49.993488],"type":"Point"}
}