{
  "type": "Feature",
  "properties": {
    "addr:full":"1889 Rue Saint-Clement Montreal QC H1V 3E5",
    "addr:housenumber":"1889",
    "addr:postcode":"h1v 3e5",
    "addr:street":"Rue Saint-Clement",
    "iso:country":"CA",
    "sg:address":"1889 Rue Saint-Clement",
    "sg:city":"Montreal",
    "sg:classifiers":[
        {
            "category":"Organizations",
            "subcategory":"Religious Organization",
            "type":"Services"
        }
    ],
    "sg:phone":"+1 514 254 4596",
    "sg:postcode":"H1V 3E5",
    "sg:province":"QC",
    "wof:name":"Soeurs Maristes",
    "wof:placetype":"venue"
},
  "geometry": {"coordinates":[-73.534683,45.558247],"type":"Point"}
}