{
  "type": "Feature",
  "properties": {
    "addr:full":"10 Dempsey Ave Regina SK S4T 7H9",
    "addr:housenumber":"10",
    "addr:postcode":"s4t 7h9",
    "addr:street":"Dempsey Ave",
    "iso:country":"CA",
    "sg:address":"10 Dempsey Ave",
    "sg:city":"Regina",
    "sg:classifiers":[
        {
            "category":"Education",
            "subcategory":"School",
            "type":"Public Place"
        }
    ],
    "sg:phone":"+1 306 791 7350",
    "sg:postcode":"S4T 7H9",
    "sg:province":"SK",
    "wof:name":"St Joan of Arc Elem School",
    "wof:placetype":"venue"
},
  "geometry": {"coordinates":[-104.66964,50.476063],"type":"Point"}
}