{
  "type": "Feature",
  "properties": {
    "addr:full":"112 Main St Prelate SK S0N 2B0",
    "addr:housenumber":"112",
    "addr:postcode":"s0n 2b0",
    "addr:street":"Main St",
    "iso:country":"CA",
    "sg:address":"112 Main St",
    "sg:city":"Prelate",
    "sg:classifiers":[
        {
            "category":"Banks & Credit Unions",
            "subcategory":"Bank",
            "type":"Services"
        }
    ],
    "sg:phone":"+1 306 673 2311",
    "sg:postcode":"S0N 2B0",
    "sg:province":"SK",
    "sg:tags":[
        "investment"
    ],
    "wof:name":"Sandhills Credit Union Prelate",
    "wof:placetype":"venue"
},
  "geometry": {"coordinates":[-109.39801,50.851967],"type":"Point"}
}