{
  "type": "Feature",
  "properties": {
    "iso:country":"CA",
    "sg:address":"215 Durrance Rd",
    "sg:city":"Victoria",
    "sg:classifiers":[
        {
            "category":"Building & Trades",
            "subcategory":"Construction",
            "type":"Services"
        }
    ],
    "sg:phone":"+1 250 652 1345",
    "sg:postcode":"V9E 2G6",
    "sg:province":"BC",
    "sg:tags":[
        "general",
        "contractor"
    ],
    "wof:name":"Robin Curtis General Contr Ltd",
    "wof:placetype":"venue"
},
  "geometry": {"coordinates":[-123.364517,48.428314],"type":"Point"}
}