{
  "type": "Feature",
  "properties": {
    "addr:full":"65 Angeline St N #9 Lindsay ON K9V 5N7",
    "addr:housenumber":"65;9",
    "addr:postcode":"k9v 5n7",
    "addr:street":"Angeline St N #",
    "iso:country":"CA",
    "sg:address":"65 Angeline St N #9",
    "sg:city":"Lindsay",
    "sg:classifiers":[
        {
            "category":"Health Services",
            "subcategory":"Doctor",
            "type":"Services"
        }
    ],
    "sg:phone":"+1 705 324 8212",
    "sg:postcode":"K9V 5N7",
    "sg:province":"ON",
    "sg:tags":[
        "physician",
        "surgeon"
    ],
    "wof:name":"Petrosoniak, Peter MD",
    "wof:placetype":"venue"
},
  "geometry": {"coordinates":[-78.753029,44.354942],"type":"Point"}
}