{
  "type": "Feature",
  "properties": {
    "addr:full":"1845 Hwy 613 N Devlin ON P0W 1C0",
    "addr:housenumber":"1845",
    "addr:postcode":"p0w 1c0",
    "addr:street":"Hwy 613 N Devlin",
    "iso:country":"CA",
    "sg:address":"1845 Hwy 613 N",
    "sg:city":"Devlin",
    "sg:classifiers":[
        {
            "category":"Home & Garden",
            "subcategory":"Garden Supply",
            "type":"Retail Goods"
        }
    ],
    "sg:phone":"+1 807 486 3428",
    "sg:postcode":"P0W 1C0",
    "sg:province":"ON",
    "sg:tags":[
        "nurseryman"
    ],
    "wof:name":"Northwest Nursery",
    "wof:placetype":"venue"
},
  "geometry": {"coordinates":[-93.67073059080001,48.6637191772],"type":"Point"}
}