{
  "type": "Feature",
  "properties": {
    "addr:full":"Ottawa ON K2C 3N6",
    "addr:postcode":"k2c 3n6",
    "iso:country":"CA",
    "sg:city":"Ottawa",
    "sg:classifiers":[
        {
            "category":"Social Services",
            "type":"Services"
        }
    ],
    "sg:phone":"+1 613 748 7162",
    "sg:postcode":"K2C 3N6",
    "sg:province":"ON",
    "sg:tags":[
        "organization",
        "welfare"
    ],
    "wof:name":"Lifetime Networks Ottawa",
    "wof:placetype":"venue"
},
  "geometry": {"coordinates":[-75.7026596069,45.3698425293],"type":"Point"}
}