{
  "type": "Feature",
  "properties": {
    "addr:full":"640 Rue Saint-Vallier O Quebec QC G1N 1C5",
    "addr:housenumber":"640",
    "addr:postcode":"g1n 1c5",
    "addr:street":"Rue Saint-Vallier O",
    "iso:country":"CA",
    "sg:address":"640 Rue Saint-Vallier O",
    "sg:city":"Quebec",
    "sg:classifiers":[
        {
            "category":"Travel",
            "subcategory":"Hotels & Motels",
            "type":"Entertainment"
        }
    ],
    "sg:phone":"+1 418 522 1554",
    "sg:postcode":"G1N 1C5",
    "sg:province":"QC",
    "wof:name":"Hotel Du Nord Enr",
    "wof:placetype":"venue"
},
  "geometry": {"coordinates":[-71.2200927734,46.8133964539],"type":"Point"}
}