{
  "type": "Feature",
  "properties": {
    "addr:full":"455 Borden St Invermere BC V0A 1K0",
    "addr:housenumber":"455",
    "addr:postcode":"v0a 1k0",
    "addr:street":"Borden St",
    "iso:country":"CA",
    "sg:address":"455 Borden St",
    "sg:city":"Invermere",
    "sg:classifiers":[
        {
            "category":"Retail",
            "subcategory":"Repair Shop",
            "type":"Services"
        }
    ],
    "sg:phone":"+1 250 342 0355",
    "sg:postcode":"V0A 1K0",
    "sg:province":"BC",
    "sg:tags":[
        "upholsterer"
    ],
    "wof:name":"Moms Upholstery & Industries",
    "wof:placetype":"venue"
},
  "geometry": {"coordinates":[-116.02945699999999,50.517345],"type":"Point"}
}