{
  "type": "Feature",
  "properties": {
    "addr:full":"291 Milltown Blvd St Stephen NB E3L 1H8",
    "addr:housenumber":"291",
    "addr:postcode":"e3l 1h8",
    "addr:street":"Milltown Blvd",
    "iso:country":"CA",
    "sg:address":"291 Milltown Blvd",
    "sg:city":"St Stephen",
    "sg:classifiers":[
        {
            "category":"Shopping",
            "subcategory":"Computers & Home Electronics",
            "type":"Retail Goods"
        }
    ],
    "sg:phone":"+1 506 465 0900",
    "sg:postcode":"E3L 1H8",
    "sg:province":"NB",
    "sg:tags":[
        "equipment",
        "dealer"
    ],
    "wof:name":"Easy Computer Svc",
    "wof:placetype":"venue"
},
  "geometry": {"coordinates":[-67.2899475098,45.1898193359],"type":"Point"}
}