{
  "type": "Feature",
  "properties": {
    "addr:full":"29 Young St Truro NS B2N 3W3",
    "addr:housenumber":"29",
    "addr:postcode":"b2n 3w3",
    "addr:street":"Young St",
    "iso:country":"CA",
    "sg:address":"29 Young St",
    "sg:city":"Truro",
    "sg:classifiers":[
        {
            "category":"Museum",
            "type":"Entertainment"
        }
    ],
    "sg:phone":"+1 902 895 6284",
    "sg:postcode":"B2N 3W3",
    "sg:province":"NS",
    "wof:name":"Colchester Historical Society",
    "wof:placetype":"venue"
},
  "geometry": {"coordinates":[-63.279297,45.363991],"type":"Point"}
}