{
  "type": "Feature",
  "properties": {
    "addr:full":"Berthierville QC J0K 1A0",
    "addr:postcode":"j0k 1a0",
    "iso:country":"CA",
    "sg:city":"Berthierville",
    "sg:classifiers":[
        {
            "category":"Utilities",
            "subcategory":"Fuel Oil & Lpg",
            "type":"Services"
        }
    ],
    "sg:phone":"+1 450 836 3401",
    "sg:postcode":"J0K 1A0",
    "sg:province":"QC",
    "wof:name":"Huile A Chauffage Berthier Inc",
    "wof:placetype":"venue"
},
  "geometry": {"coordinates":[-73.189156,46.08456],"type":"Point"}
}