{
  "type": "Feature",
  "properties": {
    "addr:full":"100 Elgin St Brantford ON N3S 5A2",
    "addr:housenumber":"100",
    "addr:postcode":"n3s 5a2",
    "addr:street":"Elgin St",
    "iso:country":"CA",
    "sg:address":"100 Elgin St",
    "sg:city":"Brantford",
    "sg:classifiers":[
        {
            "category":"Manufacturing",
            "subcategory":"Printing",
            "type":"Manufacturing & Wholesale Goods"
        }
    ],
    "sg:phone":"+1 519 756 6185",
    "sg:postcode":"N3S 5A2",
    "sg:province":"ON",
    "sg:tags":[
        "screen"
    ],
    "wof:name":"Storeimage Programs Inc",
    "wof:placetype":"venue"
},
  "geometry": {"coordinates":[-80.25448608400001,43.1492767334],"type":"Point"}
}