{
  "type": "Feature",
  "properties": {
    "iso:country":"CA",
    "sg:address":"1380 Clyde Ave",
    "sg:city":"Nepean",
    "sg:classifiers":[
        {
            "category":"Restaurant",
            "type":"Food & Drink"
        }
    ],
    "sg:phone":"+1 613 226 9277",
    "sg:postcode":"K2G 3H9",
    "sg:province":"ON",
    "wof:name":"Denny's Family Restaurant",
    "wof:placetype":"venue"
},
  "geometry": {"coordinates":[-75.739075,45.359997],"type":"Point"}
}