{
  "type": "Feature",
  "properties": {
    "addr:full":"136 North Mayor Magrath Dr Lethbridge AB T1H 3P5",
    "addr:housenumber":"136",
    "addr:postcode":"t1h 3p5",
    "addr:street":"North Mayor Magrath Dr",
    "iso:country":"CA",
    "sg:address":"136 North Mayor Magrath Dr",
    "sg:city":"Lethbridge",
    "sg:classifiers":[
        {
            "category":"Retail",
            "subcategory":"Auto Repair",
            "type":"Services"
        }
    ],
    "sg:phone":"+1 403 320 2500",
    "sg:postcode":"T1H 3P5",
    "sg:province":"AB",
    "sg:tags":[
        "repairing",
        "automobile"
    ],
    "wof:name":"Subway Automotive Svc Ltd",
    "wof:placetype":"venue"
},
  "geometry": {"coordinates":[-112.811707,49.69997],"type":"Point"}
}