{
  "type": "Feature",
  "properties": {
    "addr:full":"1201 Brookdale Ave Cornwall ON K6J 4P7",
    "addr:housenumber":"1201",
    "addr:postcode":"k6j 4p7",
    "addr:street":"Brookdale Ave",
    "iso:country":"CA",
    "sg:address":"1201 Brookdale Ave",
    "sg:city":"Cornwall",
    "sg:phone":"+1 613 932 8974",
    "sg:postcode":"K6J 4P7",
    "sg:province":"ON",
    "sg:tags":[
        "oil"
    ],
    "wof:name":"Upi Inc",
    "wof:placetype":"venue"
},
  "geometry": {"coordinates":[-74.751625,45.027149],"type":"Point"}
}