{
  "type": "Feature",
  "properties": {
    "addr:full":"80 Aberdeen Street Ottawa K1S 5R5",
    "addr:housenumber":"80",
    "addr:postcode":"k1s 5r5",
    "addr:street":"Aberdeen Street",
    "iso:country":"CA",
    "sg:address":"80 Aberdeen Street",
    "sg:city":"Ottawa",
    "sg:classifiers":[
        {
            "category":"Professional",
            "subcategory":"Computer Services",
            "type":"Services"
        }
    ],
    "sg:postcode":"K1S 5R5",
    "sg:website":"http://www.overlay.tv/",
    "wof:name":"Overlay.tv",
    "wof:placetype":"venue"
},
  "geometry": {"coordinates":[-75.71080000000001,45.401005],"type":"Point"}
}