{
  "type": "Feature",
  "properties": {
    "iso:country":"CA",
    "sg:address":"3 Kellys Dr",
    "sg:city":"Fredericton",
    "sg:classifiers":[
        {
            "category":"Real Estate",
            "subcategory":"Real Estate Operator",
            "type":"Services"
        }
    ],
    "sg:phone":"+1 506 458 8119",
    "sg:postcode":"E3B 7R1",
    "sg:province":"NB",
    "sg:tags":[
        "mobile",
        "home",
        "community"
    ],
    "wof:name":"Kelly's Homes",
    "wof:placetype":"venue"
},
  "geometry": {"coordinates":[-66.6870269775,45.9598197937],"type":"Point"}
}