{
  "type": "Feature",
  "properties": {
    "addr:full":"844 Rye St Peterborough ON K9J 6W9",
    "addr:housenumber":"844",
    "addr:postcode":"k9j 6w9",
    "addr:street":"Rye St",
    "iso:country":"CA",
    "sg:address":"844 Rye St",
    "sg:city":"Peterborough",
    "sg:classifiers":[
        {
            "category":"Professional",
            "subcategory":"Business Services",
            "type":"Services"
        }
    ],
    "sg:phone":"+1 705 749 1136",
    "sg:postcode":"K9J 6W9",
    "sg:province":"ON",
    "sg:tags":[
        "embroidery"
    ],
    "wof:name":"Imprinted Apparel Store",
    "wof:placetype":"venue"
},
  "geometry": {"coordinates":[-78.34474899999999,44.280258],"type":"Point"}
}