{
  "type": "Feature",
  "properties": {
    "iso:country":"CA",
    "sg:address":"253 Stratford Rd",
    "sg:city":"Stratford",
    "sg:classifiers":[
        {
            "category":"Building & Trades",
            "subcategory":"Construction",
            "type":"Services"
        }
    ],
    "sg:phone":"+1 902 569 5779",
    "sg:postcode":"C1B 1H3",
    "sg:province":"PE",
    "sg:tags":[
        "general",
        "contractor"
    ],
    "wof:name":"Brumac Construction Ltd",
    "wof:placetype":"venue"
},
  "geometry": {"coordinates":[-63.0811424255,46.2164115906],"type":"Point"}
}