{
  "type": "Feature",
  "properties": {
    "addr:full":"359 Rue Sainte-Claire Saint-Urbain-DE-Charlevoix QC G0A 4K0",
    "addr:housenumber":"359",
    "addr:postcode":"g0a 4k0",
    "addr:street":"Rue Sainte-Claire Saint-Urbain-De-Charlevoix",
    "iso:country":"CA",
    "sg:address":"359 Rue Sainte-Claire",
    "sg:city":"Saint-Urbain-DE-Charlevoix",
    "sg:classifiers":[
        {
            "category":"Government",
            "subcategory":"Office",
            "type":"Public Place"
        }
    ],
    "sg:phone":"+1 418 639 2200",
    "sg:postcode":"G0A 4K0",
    "sg:province":"QC",
    "sg:tags":[
        "village"
    ],
    "wof:name":"St-Urbain Ctr Communautaire",
    "wof:placetype":"venue"
},
  "geometry": {"coordinates":[-70.5461425781,47.5606842041],"type":"Point"}
}