{
  "type": "Feature",
  "properties": {
    "addr:full":"609 Rue Principale Eastman QC J0E 1P0",
    "addr:housenumber":"609",
    "addr:postcode":"j0e 1p0",
    "addr:street":"Rue Principale",
    "iso:country":"CA",
    "sg:address":"609 Rue Principale",
    "sg:city":"Eastman",
    "sg:classifiers":[
        {
            "category":"Retail",
            "subcategory":"Auto Repair",
            "type":"Services"
        }
    ],
    "sg:phone":"+1 450 297 2579",
    "sg:postcode":"J0E 1P0",
    "sg:province":"QC",
    "sg:tags":[
        "repairing",
        "automobile"
    ],
    "wof:name":"Garage Alain Boisvert Enr",
    "wof:placetype":"venue"
},
  "geometry": {"coordinates":[-72.29924800000001,45.299923],"type":"Point"}
}