{
  "type": "Feature",
  "properties": {
    "addr:full":"16203 114 Ave NW Edmonton AB T5M 2Z3",
    "addr:housenumber":"16203",
    "addr:postcode":"t5m 2z3",
    "addr:street":"114 Ave Nw",
    "iso:country":"CA",
    "sg:address":"16203 114 Ave NW",
    "sg:city":"Edmonton",
    "sg:classifiers":[
        {
            "category":"Utilities",
            "subcategory":"Fuel Oil & Lpg",
            "type":"Services"
        }
    ],
    "sg:phone":"+1 780 451 4454",
    "sg:postcode":"T5M 2Z3",
    "sg:province":"AB",
    "sg:tags":[
        "propane",
        "gas",
        "business"
    ],
    "wof:name":"Mutual Propane Ltd",
    "wof:placetype":"venue"
},
  "geometry": {"coordinates":[-113.600769,53.562782],"type":"Point"}
}