{
  "type": "Feature",
  "properties": {
    "addr:full":"421 Apple Tree Lane Ottawa ON K1K 2R4",
    "addr:housenumber":"421",
    "addr:postcode":"k1k 2r4",
    "addr:street":"Apple Tree Lane",
    "iso:country":"CA",
    "sg:address":"421 Apple Tree Lane",
    "sg:city":"Ottawa",
    "sg:classifiers":[
        {
            "category":"Health Services",
            "subcategory":"Health Practitioner",
            "type":"Services"
        }
    ],
    "sg:phone":"+1 613 741 5998",
    "sg:postcode":"K1K 2R4",
    "sg:province":"ON",
    "sg:tags":[
        "acupuncture"
    ],
    "wof:name":"Jing Jin Acupuncture",
    "wof:placetype":"venue"
},
  "geometry": {"coordinates":[-75.648346,45.447517],"type":"Point"}
}