{
  "type": "Feature",
  "properties": {
    "addr:full":"90 Kingston Rd E Ajax ON L1Z 1G1",
    "addr:housenumber":"90",
    "addr:postcode":"l1z 1g1",
    "addr:street":"Kingston Rd E",
    "iso:country":"CA",
    "sg:address":"90 Kingston Rd E",
    "sg:city":"Ajax",
    "sg:classifiers":[
        {
            "category":"Shopping",
            "subcategory":"Books",
            "type":"Retail Goods"
        }
    ],
    "sg:phone":"+1 905 426 4431",
    "sg:postcode":"L1Z 1G1",
    "sg:province":"ON",
    "sg:tags":[
        "dealer"
    ],
    "wof:name":"Chapters",
    "wof:placetype":"venue"
},
  "geometry": {"coordinates":[-79.02113300000001,43.862492],"type":"Point"}
}