{
  "type": "Feature",
  "properties": {
    "iso:country":"CA",
    "sg:address":"90 Kingston Rd E",
    "sg:city":"Ajax",
    "sg:classifiers":[
        {
            "category":"Shopping",
            "subcategory":"Books",
            "type":"Retail Goods"
        }
    ],
    "sg:phone":"+1 905 426 4431",
    "sg:postcode":"L1Z 1G1",
    "sg:province":"ON",
    "sg:tags":[
        "dealer"
    ],
    "wof:name":"Chapters",
    "wof:placetype":"venue"
},
  "geometry": {"coordinates":[-79.021133,43.862492],"type":"Point"}
}