{
  "type": "Feature",
  "properties": {
    "addr:full":"75 the Donway W #1110 North York ON M3C 2E9",
    "addr:housenumber":"75",
    "addr:postcode":"m3c 2e9",
    "addr:street":"The Donway W # 1110",
    "iso:country":"CA",
    "sg:address":"75 the Donway W #1110",
    "sg:city":"North York",
    "sg:classifiers":[
        {
            "category":"Travel",
            "subcategory":"Travel Agent",
            "type":"Entertainment"
        }
    ],
    "sg:phone":"+1 416 510 8677",
    "sg:postcode":"M3C 2E9",
    "sg:province":"ON",
    "sg:tags":[
        "agency",
        "bureau"
    ],
    "wof:name":"Travel Scene",
    "wof:placetype":"venue"
},
  "geometry": {"coordinates":[-79.34575700000001,43.732414],"type":"Point"}
}