{
  "type": "Feature",
  "properties": {
    "addr:full":"14 Gertrude St W North Bay ON P1A 1J3",
    "addr:housenumber":"14",
    "addr:postcode":"p1a 1j3",
    "addr:street":"Gertrude St W",
    "iso:country":"CA",
    "sg:address":"14 Gertrude St W",
    "sg:city":"North Bay",
    "sg:classifiers":[
        {
            "category":"Retail",
            "subcategory":"Veterinary Services",
            "type":"Services"
        }
    ],
    "sg:phone":"+1 705 472 1570",
    "sg:postcode":"P1A 1J3",
    "sg:province":"ON",
    "sg:tags":[
        "veterinarian"
    ],
    "wof:name":"Blue Sky Animal Hospital",
    "wof:placetype":"venue"
},
  "geometry": {"coordinates":[-79.451576,46.287964],"type":"Point"}
}