{
  "type": "Feature",
  "properties": {
    "addr:full":"425 Banks Rd Kelowna BC V1X 6A2",
    "addr:housenumber":"425",
    "addr:postcode":"v1x 6a2",
    "addr:street":"Banks Rd",
    "iso:country":"CA",
    "sg:address":"425 Banks Rd",
    "sg:city":"Kelowna",
    "sg:classifiers":[
        {
            "category":"Home & Garden",
            "subcategory":"Household Appliances",
            "type":"Retail Goods"
        }
    ],
    "sg:phone":"+1 250 861 1566",
    "sg:postcode":"V1X 6A2",
    "sg:province":"BC",
    "sg:tags":[
        "cleaners",
        "vacuum"
    ],
    "wof:name":"O K Vacuums",
    "wof:placetype":"venue"
},
  "geometry": {"coordinates":[-119.422783,49.884827],"type":"Point"}
}