{
  "type": "Feature",
  "properties": {
    "iso:country":"CA",
    "sg:city":"North York",
    "sg:classifiers":[
        {
            "category":"Health Services",
            "subcategory":"Doctor",
            "type":"Services"
        }
    ],
    "sg:phone":"+1 416 750 8400",
    "sg:postcode":"M4A 2S8",
    "sg:province":"ON",
    "sg:tags":[
        "physician",
        "surgeon"
    ],
    "wof:name":"Ung, Chantelle MD",
    "wof:placetype":"venue"
},
  "geometry": {"coordinates":[-79.313248,43.741722],"type":"Point"}
}