{
  "type": "Feature",
  "properties": {
    "iso:country":"CA",
    "sg:address":"45288 Ferguson Line",
    "sg:city":"Belmont",
    "sg:classifiers":[
        {
            "category":"Building & Trades",
            "subcategory":"Plumbing",
            "type":"Services"
        }
    ],
    "sg:phone":"+1 519 455 9460",
    "sg:postcode":"N0L 1B0",
    "sg:province":"ON",
    "sg:tags":[
        "mechanical",
        "contractor"
    ],
    "wof:name":"Westminster Mechanical",
    "wof:placetype":"venue"
},
  "geometry": {"coordinates":[-81.1088104248,42.8347396851],"type":"Point"}
}