{
  "type": "Feature",
  "properties": {
    "addr:full":"425 Queen St W Toronto ON M5V 2A5",
    "addr:housenumber":"425",
    "addr:postcode":"m5v 2a5",
    "addr:street":"Queen St W",
    "iso:country":"CA",
    "sg:address":"425 Queen St W",
    "sg:city":"Toronto",
    "sg:classifiers":[
        {
            "category":"Shopping",
            "subcategory":"Clothing, Apparel, & Fashions",
            "type":"Retail Goods"
        }
    ],
    "sg:phone":"+1 416 977 4709",
    "sg:postcode":"M5V 2A5",
    "sg:province":"ON",
    "sg:tags":[
        "accessory"
    ],
    "wof:name":"Change Room",
    "wof:placetype":"venue"
},
  "geometry": {"coordinates":[-79.395409,43.6488],"type":"Point"}
}