{
  "type": "Feature",
  "properties": {
    "addr:full":"Grande Prairie AB T8V 0V2",
    "addr:postcode":"t8v 0v2",
    "iso:country":"CA",
    "sg:city":"Grande Prairie",
    "sg:classifiers":[
        {
            "category":"Shopping",
            "type":"Retail Goods"
        }
    ],
    "sg:phone":"+1 780 538 1355",
    "sg:postcode":"T8V 0V2",
    "sg:province":"AB",
    "sg:tags":[
        "trophy",
        "medal",
        "award"
    ],
    "wof:name":"Trophy Gallery",
    "wof:placetype":"venue"
},
  "geometry": {"coordinates":[-118.795547,55.170605],"type":"Point"}
}