{
  "type": "Feature",
  "properties": {
    "addr:full":"47 Superior St Devon AB T9G 1K8",
    "addr:housenumber":"47",
    "addr:postcode":"t9g 1k8",
    "addr:street":"Superior St",
    "iso:country":"CA",
    "sg:address":"47 Superior St",
    "sg:city":"Devon",
    "sg:classifiers":[
        {
            "category":"Food & Beverages",
            "subcategory":"Liquor & Beverages",
            "type":"Retail Goods"
        }
    ],
    "sg:phone":"+1 780 987 2744",
    "sg:postcode":"T9G 1K8",
    "sg:province":"AB",
    "sg:tags":[
        "store"
    ],
    "wof:name":"Superior Liquor Mart",
    "wof:placetype":"venue"
},
  "geometry": {"coordinates":[-113.732384,53.363277],"type":"Point"}
}