{
  "type": "Feature",
  "properties": {
    "addr:full":"Coaticook QC J1A 2B2",
    "addr:postcode":"j1a 2b2",
    "iso:country":"CA",
    "sg:city":"Coaticook",
    "sg:classifiers":[
        {
            "category":"Personal",
            "subcategory":"Beauty Salon",
            "type":"Services"
        }
    ],
    "sg:phone":"+1 819 849 2691",
    "sg:postcode":"J1A 2B2",
    "sg:province":"QC",
    "wof:name":"Mikel-Ange Coiffure",
    "wof:placetype":"venue"
},
  "geometry": {"coordinates":[-71.80513000489999,45.1327590942],"type":"Point"}
}