{
  "type": "Feature",
  "properties": {
    "addr:full":"Saint-Joseph-Du-Lac QC J0N 1M0",
    "addr:postcode":"j0n 1m0",
    "iso:country":"CA",
    "sg:city":"Saint-Joseph-Du-Lac",
    "sg:classifiers":[
        {
            "category":"Retail",
            "subcategory":"Auto Repair",
            "type":"Services"
        }
    ],
    "sg:phone":"+1 450 491 6967",
    "sg:postcode":"J0N 1M0",
    "sg:province":"QC",
    "sg:tags":[
        "truck"
    ],
    "wof:name":"Centre Du Camion Sg Inc",
    "wof:placetype":"venue"
},
  "geometry": {"coordinates":[-73.996963501,45.5016822815],"type":"Point"}
}