{
  "type": "Feature",
  "properties": {
    "addr:full":"341 Olsen St Tofino BC V0R 2Z0",
    "addr:housenumber":"341",
    "addr:postcode":"v0r 2z0",
    "addr:street":"Olsen St",
    "iso:country":"CA",
    "sg:address":"341 Olsen St",
    "sg:city":"Tofino",
    "sg:classifiers":[
        {
            "category":"Travel",
            "subcategory":"Hotels & Motels",
            "type":"Entertainment"
        }
    ],
    "sg:phone":"+1 250 725 3274",
    "sg:postcode":"V0R 2Z0",
    "sg:province":"BC",
    "wof:name":"Tofino Swell Lodge",
    "wof:placetype":"venue"
},
  "geometry": {"coordinates":[-125.892654419,49.1494636536],"type":"Point"}
}