{
  "type": "Feature",
  "properties": {
    "addr:full":"74 Mill Rd Cornwall PE C0A 1H0",
    "addr:housenumber":"74",
    "addr:postcode":"c0a 1h0",
    "addr:street":"Mill Rd",
    "iso:country":"CA",
    "sg:address":"74 Mill Rd",
    "sg:city":"Cornwall",
    "sg:classifiers":[
        {
            "category":"Home & Garden",
            "subcategory":"Garden Supply",
            "type":"Retail Goods"
        }
    ],
    "sg:phone":"+1 902 566 2921",
    "sg:postcode":"C0A 1H0",
    "sg:province":"PE",
    "sg:tags":[
        "lawn",
        "snowmobile",
        "mower"
    ],
    "wof:name":"Dave's Snowmobile Repair",
    "wof:placetype":"venue"
},
  "geometry": {"coordinates":[-63.218075,46.22768],"type":"Point"}
}