{
  "type": "Feature",
  "properties": {
    "addr:full":"Scarborough ON M1N 1W8",
    "addr:postcode":"m1n 1w8",
    "iso:country":"CA",
    "sg:city":"Scarborough",
    "sg:classifiers":[
        {
            "category":"Restaurant",
            "type":"Food & Drink"
        }
    ],
    "sg:phone":"+1 416 690 2098",
    "sg:postcode":"M1N 1W8",
    "sg:province":"ON",
    "wof:name":"Quarry Cafe",
    "wof:placetype":"venue"
},
  "geometry": {"coordinates":[-79.2783508301,43.688747406],"type":"Point"}
}