{
  "type": "Feature",
  "properties": {
    "iso:country":"CA",
    "sg:address":"111 Manville Rd",
    "sg:city":"Scarborough",
    "sg:classifiers":[
        {
            "category":"Wholesale",
            "subcategory":"Stationery",
            "type":"Manufacturing & Wholesale Goods"
        }
    ],
    "sg:phone":"+1 416 757 2737",
    "sg:postcode":"M1L 4J2",
    "sg:province":"ON",
    "sg:tags":[
        "product",
        "paper"
    ],
    "wof:name":"Metro Paper Industries Inc",
    "wof:placetype":"venue"
},
  "geometry": {"coordinates":[-79.2819595337,43.7233657837],"type":"Point"}
}