{
  "type": "Feature",
  "properties": {
    "addr:full":"71 Braid St New Westminster BC V3L 3P2",
    "addr:housenumber":"71",
    "addr:postcode":"v3l 3p2",
    "addr:street":"Braid St",
    "iso:country":"CA",
    "sg:address":"71 Braid St",
    "sg:city":"New Westminster",
    "sg:classifiers":[
        {
            "category":"Home & Garden",
            "subcategory":"Building Materials",
            "type":"Retail Goods"
        }
    ],
    "sg:phone":"+1 604 525 6677",
    "sg:postcode":"V3L 3P2",
    "sg:province":"BC",
    "wof:name":"Teamwood Traders Ltd",
    "wof:placetype":"venue"
},
  "geometry": {"coordinates":[-122.88133999999999,49.230965],"type":"Point"}
}