{
  "type": "Feature",
  "properties": {
    "iso:country":"CA",
    "sg:address":"496 Av Birch",
    "sg:city":"Saint-Lambert",
    "sg:classifiers":[
        {
            "category":"Organizations",
            "subcategory":"Religious Organization",
            "type":"Services"
        }
    ],
    "sg:phone":"+1 450 671 1862",
    "sg:postcode":"J4P 2M8",
    "sg:province":"QC",
    "sg:tags":[
        "church"
    ],
    "wof:name":"St Andrew's Presbyterian Ch",
    "wof:placetype":"venue"
},
  "geometry": {"coordinates":[-73.510017,45.503754],"type":"Point"}
}