{
  "type": "Feature",
  "properties": {
    "addr:full":"1025 Wellington Rd London ON N6E 1W4",
    "addr:housenumber":"1025",
    "addr:postcode":"n6e 1w4",
    "addr:street":"Wellington Rd",
    "iso:country":"CA",
    "sg:address":"1025 Wellington Rd",
    "sg:city":"London",
    "sg:classifiers":[
        {
            "category":"Shopping",
            "subcategory":"Music",
            "type":"Retail Goods"
        }
    ],
    "sg:phone":"+1 519 649 2722",
    "sg:postcode":"N6E 1W4",
    "sg:province":"ON",
    "sg:tags":[
        "compact",
        "record",
        "disc",
        "tape"
    ],
    "wof:name":"C D Plus",
    "wof:placetype":"venue"
},
  "geometry": {"coordinates":[-81.22448730470001,42.9372940063],"type":"Point"}
}