{
  "type": "Feature",
  "properties": {
    "addr:full":"Beauport QC G1B 1L3",
    "addr:postcode":"g1b 1l3",
    "iso:country":"CA",
    "sg:city":"Beauport",
    "sg:classifiers":[
        {
            "category":"Building & Trades",
            "subcategory":"Construction",
            "type":"Services"
        }
    ],
    "sg:phone":"+1 418 666 7449",
    "sg:postcode":"G1B 1L3",
    "sg:province":"QC",
    "sg:tags":[
        "plastering",
        "contractor"
    ],
    "wof:name":"Laurent Paquet & Fils Inc",
    "wof:placetype":"venue"
},
  "geometry": {"coordinates":[-71.193443,46.903461],"type":"Point"}
}