{
  "type": "Feature",
  "properties": {
    "addr:full":"10 Kenwood Dr Kitchener ON N2B 3G9",
    "addr:housenumber":"10",
    "addr:postcode":"n2b 3g9",
    "addr:street":"Kenwood Dr",
    "iso:country":"CA",
    "sg:address":"10 Kenwood Dr",
    "sg:city":"Kitchener",
    "sg:classifiers":[
        {
            "category":"Arts & Performance",
            "subcategory":"Theater",
            "type":"Entertainment"
        }
    ],
    "sg:phone":"+1 519 744 8201",
    "sg:postcode":"N2B 3G9",
    "sg:province":"ON",
    "sg:tags":[
        "live",
        "music"
    ],
    "wof:name":"Sounds of Our Time Dj Svc",
    "wof:placetype":"venue"
},
  "geometry": {"coordinates":[-80.45951843260001,43.4524154663],"type":"Point"}
}