{
  "type": "Feature",
  "properties": {
    "addr:full":"L'Ancienne-Lorette QC G2G 2P4",
    "addr:postcode":"g2g 2p4",
    "iso:country":"CA",
    "sg:city":"L'Ancienne-Lorette",
    "sg:classifiers":[
        {
            "category":"Retail",
            "subcategory":"Auto Repair",
            "type":"Services"
        }
    ],
    "sg:phone":"+1 418 872 9601",
    "sg:postcode":"G2G 2P4",
    "sg:province":"QC",
    "sg:tags":[
        "transmission"
    ],
    "wof:name":"Specialites Servo-Trans Enr",
    "wof:placetype":"venue"
},
  "geometry": {"coordinates":[-71.36563099999999,46.796211],"type":"Point"}
}