{
  "type": "Feature",
  "properties": {
    "iso:country":"CA",
    "sg:address":"326 Hwy 72",
    "sg:city":"Sioux Lookout",
    "sg:classifiers":[
        {
            "category":"Travel",
            "subcategory":"Hotels & Motels",
            "type":"Entertainment"
        }
    ],
    "sg:phone":"+1 807 737 1014",
    "sg:postcode":"P8T 1A8",
    "sg:province":"ON",
    "wof:name":"Lamplighter Motel",
    "wof:placetype":"venue"
},
  "geometry": {"coordinates":[-91.9727935791,50.0577087402],"type":"Point"}
}