{
  "type": "Feature",
  "properties": {
    "addr:full":"32 Av Babin Baie-Comeau QC G4Z 3A6",
    "addr:postcode":"g4z 3a6",
    "addr:street":"32 Av Babin",
    "iso:country":"CA",
    "sg:address":"32 Av Babin",
    "sg:city":"Baie-Comeau",
    "sg:classifiers":[
        {
            "category":"Building & Trades",
            "subcategory":"Construction",
            "type":"Services"
        }
    ],
    "sg:phone":"+1 418 296 1444",
    "sg:postcode":"G4Z 3A6",
    "sg:province":"QC",
    "sg:tags":[
        "general",
        "contractor"
    ],
    "wof:name":"Fransi Construction Inc",
    "wof:placetype":"venue"
},
  "geometry": {"coordinates":[-68.1904449463,49.2223930359],"type":"Point"}
}