{
  "type": "Feature",
  "properties": {
    "addr:full":"7006 3rd Ave E Waldheim SK S0K 4R0",
    "addr:housenumber":"7006",
    "addr:postcode":"s0k 4r0",
    "addr:street":"3Rd Ave E",
    "iso:country":"CA",
    "sg:address":"7006 3rd Ave E",
    "sg:city":"Waldheim",
    "sg:classifiers":[
        {
            "category":"Freight",
            "type":"Transportation"
        }
    ],
    "sg:phone":"+1 306 945 2150",
    "sg:postcode":"S0K 4R0",
    "sg:province":"SK",
    "sg:tags":[
        "grain",
        "hauling",
        "trucking"
    ],
    "wof:name":"L P Schmidt Trucking Ltd",
    "wof:placetype":"venue"
},
  "geometry": {"coordinates":[-106.647575,52.613106],"type":"Point"}
}