{
  "type": "Feature",
  "properties": {
    "addr:full":"407 Royal York Rd Etobicoke ON M8Y 2R8",
    "addr:housenumber":"407",
    "addr:postcode":"m8y 2r8",
    "addr:street":"Royal York Rd",
    "iso:country":"CA",
    "sg:address":"407 Royal York Rd",
    "sg:city":"Etobicoke",
    "sg:classifiers":[
        {
            "category":"Food & Beverages",
            "subcategory":"Groceries & Convenience Stores",
            "type":"Retail Goods"
        }
    ],
    "sg:phone":"+1 416 255 4214",
    "sg:postcode":"M8Y 2R8",
    "sg:province":"ON",
    "sg:tags":[
        "grocer"
    ],
    "wof:name":"Royal York Convenience Store",
    "wof:placetype":"venue"
},
  "geometry": {"coordinates":[-79.49988555909999,43.6199455261],"type":"Point"}
}