{
  "type": "Feature",
  "properties": {
    "addr:full":"Richmond BC V6X 1R5",
    "addr:postcode":"v6x 1r5",
    "iso:country":"CA",
    "sg:city":"Richmond",
    "sg:classifiers":[
        {
            "category":"Retail",
            "subcategory":"Auto Repair",
            "type":"Services"
        }
    ],
    "sg:phone":"+1 604 241 2848",
    "sg:postcode":"V6X 1R5",
    "sg:province":"BC",
    "sg:tags":[
        "repairing",
        "automobile"
    ],
    "wof:name":"Juan's Auto Svc",
    "wof:placetype":"venue"
},
  "geometry": {"coordinates":[-123.13439178500001,49.1888542175],"type":"Point"}
}