{
  "type": "Feature",
  "properties": {
    "iso:country":"CA",
    "sg:address":"922 Broadview Ave",
    "sg:city":"Toronto",
    "sg:classifiers":[
        {
            "category":"Personal",
            "subcategory":"Beauty Salon",
            "type":"Services"
        }
    ],
    "sg:phone":"+1 416 462 0500",
    "sg:postcode":"M4K 2R1",
    "sg:province":"ON",
    "wof:name":"Samantha Hair Design",
    "wof:placetype":"venue"
},
  "geometry": {"coordinates":[-79.3580245972,43.6806411743],"type":"Point"}
}