{
  "type": "Feature",
  "properties": {
    "addr:full":"120 Hunt St Ajax ON L1S 1P5",
    "addr:housenumber":"120",
    "addr:postcode":"l1s 1p5",
    "addr:street":"Hunt St",
    "iso:country":"CA",
    "sg:address":"120 Hunt St",
    "sg:city":"Ajax",
    "sg:classifiers":[
        {
            "category":"Home & Garden",
            "subcategory":"Carpets & Floor Coverings",
            "type":"Retail Goods"
        }
    ],
    "sg:phone":"+1 905 683 6126",
    "sg:postcode":"L1S 1P5",
    "sg:province":"ON",
    "sg:tags":[
        "material"
    ],
    "wof:name":"Midway Carpet",
    "wof:placetype":"venue"
},
  "geometry": {"coordinates":[-79.024033,43.846661],"type":"Point"}
}