{
  "type": "Feature",
  "properties": {
    "addr:full":"1778 Av Saint-Marc Shawinigan QC G9N 2H7",
    "addr:housenumber":"1778",
    "addr:postcode":"g9n 2h7",
    "addr:street":"Av Saint-Marc",
    "iso:country":"CA",
    "sg:address":"1778 Av Saint-Marc",
    "sg:city":"Shawinigan",
    "sg:classifiers":[
        {
            "category":"Shopping",
            "subcategory":"Florist",
            "type":"Retail Goods"
        }
    ],
    "sg:phone":"+1 819 537 7225",
    "sg:postcode":"G9N 2H7",
    "sg:province":"QC",
    "wof:name":"Aux Mille Fleurs Enrg",
    "wof:placetype":"venue"
},
  "geometry": {"coordinates":[-72.74430099999999,46.552212],"type":"Point"}
}