{
  "type": "Feature",
  "properties": {
    "addr:full":"1911 Dundas St E Mississauga ON L4X 1M1",
    "addr:housenumber":"1911",
    "addr:postcode":"l4x 1m1",
    "addr:street":"Dundas St E",
    "iso:country":"CA",
    "sg:address":"1911 Dundas St E",
    "sg:city":"Mississauga",
    "sg:classifiers":[
        {
            "category":"Home & Garden",
            "subcategory":"Furniture",
            "type":"Retail Goods"
        }
    ],
    "sg:phone":"+1 416 621 9483",
    "sg:postcode":"L4X 1M1",
    "sg:province":"ON",
    "wof:name":"Kiddies World of Mississauga",
    "wof:placetype":"venue"
},
  "geometry": {"coordinates":[-79.5716094971,43.6209335327],"type":"Point"}
}