{
  "type": "Feature",
  "properties": {
    "iso:country":"CA",
    "sg:address":"67 Westmore Dr",
    "sg:city":"Etobicoke",
    "sg:classifiers":[
        {
            "category":"Wholesale",
            "subcategory":"Groceries",
            "type":"Manufacturing & Wholesale Goods"
        }
    ],
    "sg:phone":"+1 416 744 2127",
    "sg:postcode":"M9V 3Y6",
    "sg:province":"ON",
    "sg:tags":[
        "grocer"
    ],
    "wof:name":"California Orange Juice",
    "wof:placetype":"venue"
},
  "geometry": {"coordinates":[-79.603188,43.740105],"type":"Point"}
}