{
  "type": "Feature",
  "properties": {
    "addr:full":"527 Clarke Rd London ON N5V 2C9",
    "addr:housenumber":"527",
    "addr:postcode":"n5v 2c9",
    "addr:street":"Clarke Rd",
    "iso:country":"CA",
    "sg:address":"527 Clarke Rd",
    "sg:city":"London",
    "sg:classifiers":[
        {
            "category":"Insurance",
            "subcategory":"Insurance Agent",
            "type":"Services"
        }
    ],
    "sg:phone":"+1 519 451 3540",
    "sg:postcode":"N5V 2C9",
    "sg:province":"ON",
    "wof:name":"State Farm Insurance CO",
    "wof:placetype":"venue"
},
  "geometry": {"coordinates":[-81.178619,43.009964],"type":"Point"}
}