{
  "type": "Feature",
  "properties": {
    "addr:full":"4309C Boul Saint-Jean Dollard-Des-Ormeaux QC H9H 2A4",
    "addr:housenumber":"4309c",
    "addr:postcode":"h9h 2a4",
    "addr:street":"Boul Saint-Jean",
    "iso:country":"CA",
    "sg:address":"4309C Boul Saint-Jean",
    "sg:city":"Dollard-Des-Ormeaux",
    "sg:classifiers":[
        {
            "category":"Health Services",
            "subcategory":"Doctor",
            "type":"Services"
        }
    ],
    "sg:phone":"+1 514 696 1111",
    "sg:postcode":"H9H 2A4",
    "sg:province":"QC",
    "sg:tags":[
        "physician",
        "surgeon"
    ],
    "wof:name":"Blain, Jean Gilles MD",
    "wof:placetype":"venue"
},
  "geometry": {"coordinates":[-73.84227752690001,45.4808883667],"type":"Point"}
}