{
  "type": "Feature",
  "properties": {
    "addr:full":"6337 Laurel St Burnaby BC V5B 3B3",
    "addr:housenumber":"6337",
    "addr:postcode":"bc v5b 3b3",
    "addr:street":"Laurel St",
    "iso:country":"CA",
    "sg:address":"6337 Laurel St",
    "sg:city":"Burnaby",
    "sg:classifiers":[
        {
            "category":"Manufacturing",
            "subcategory":"Tools & Machinery",
            "type":"Manufacturing & Wholesale Goods"
        }
    ],
    "sg:phone":"+1 604 436 0431",
    "sg:postcode":"V5B 3B3",
    "sg:province":"BC",
    "sg:tags":[
        "elevator"
    ],
    "wof:name":"Argo Electronics Micro-Control",
    "wof:placetype":"venue"
},
  "geometry": {"coordinates":[-122.972007752,49.2537155151],"type":"Point"}
}