{
  "type": "Feature",
  "properties": {
    "addr:full":"29 Pageant Dr Sault Ste Marie ON P6B 5J7",
    "addr:housenumber":"29",
    "addr:postcode":"p6b 5j7",
    "addr:street":"Pageant Dr",
    "iso:country":"CA",
    "sg:address":"29 Pageant Dr",
    "sg:city":"Sault Ste Marie",
    "sg:classifiers":[
        {
            "category":"Government",
            "subcategory":"Office",
            "type":"Public Place"
        }
    ],
    "sg:phone":"+1 705 942 6196",
    "sg:postcode":"P6B 5J7",
    "sg:province":"ON",
    "sg:tags":[
        "federal",
        "affairs"
    ],
    "wof:name":"Consulate of Finland",
    "wof:placetype":"venue"
},
  "geometry": {"coordinates":[-84.300369,46.523258],"type":"Point"}
}