{
  "type": "Feature",
  "properties": {
    "iso:country":"CA",
    "sg:address":"296 Cote Ave",
    "sg:city":"Chelmsford",
    "sg:classifiers":[
        {
            "category":"Real Estate",
            "subcategory":"Real Estate Operator",
            "type":"Services"
        }
    ],
    "sg:phone":"+1 705 855 1685",
    "sg:postcode":"P0M 1L0",
    "sg:province":"ON",
    "sg:tags":[
        "apartment"
    ],
    "wof:name":"Friendship Place D'Amitie",
    "wof:placetype":"venue"
},
  "geometry": {"coordinates":[-81.1953201294,46.5726203918],"type":"Point"}
}