{
  "type": "Feature",
  "properties": {
    "addr:full":"333 Margueretta St Toronto ON M6H 3S4",
    "addr:housenumber":"333",
    "addr:postcode":"m6h 3s4",
    "addr:street":"Margueretta St",
    "iso:country":"CA",
    "sg:address":"333 Margueretta St",
    "sg:city":"Toronto",
    "sg:classifiers":[
        {
            "category":"Building & Trades",
            "subcategory":"Construction",
            "type":"Services"
        }
    ],
    "sg:phone":"+1 416 535 3333",
    "sg:postcode":"M6H 3S4",
    "sg:province":"ON",
    "sg:tags":[
        "ironwork",
        "railing"
    ],
    "wof:name":"Abc Iron Railings & Welding",
    "wof:placetype":"venue"
},
  "geometry": {"coordinates":[-79.43982699999999,43.657818],"type":"Point"}
}