{
  "type": "Feature",
  "properties": {
    "iso:country":"CA",
    "sg:address":"5001 51 Ave",
    "sg:city":"Athabasca",
    "sg:classifiers":[
        {
            "category":"Home & Garden",
            "subcategory":"Building Materials",
            "type":"Retail Goods"
        }
    ],
    "sg:phone":"+1 780 675 2355",
    "sg:postcode":"T9S 1E8",
    "sg:province":"AB",
    "sg:tags":[
        "lumber"
    ],
    "wof:name":"Athabasca Home Hardware Bldg",
    "wof:placetype":"venue"
},
  "geometry": {"coordinates":[-113.298156738,54.7218093872],"type":"Point"}
}