{
  "type": "Feature",
  "properties": {
    "addr:full":"216 Signal Rd Fort Mcmurray AB T9H 3S3",
    "addr:housenumber":"216",
    "addr:postcode":"t9h 3s3",
    "addr:street":"Signal Rd",
    "iso:country":"CA",
    "sg:address":"216 Signal Rd",
    "sg:city":"Fort Mcmurray",
    "sg:classifiers":[
        {
            "category":"Retail",
            "subcategory":"Portrait Studio",
            "type":"Services"
        }
    ],
    "sg:phone":"+1 780 799 1838",
    "sg:postcode":"T9H 3S3",
    "sg:province":"AB",
    "sg:tags":[
        "photographer"
    ],
    "wof:name":"Sky Wonder",
    "wof:placetype":"venue"
},
  "geometry": {"coordinates":[-111.426109,56.728104],"type":"Point"}
}