{
  "type": "Feature",
  "properties": {
    "addr:full":"11 William St W Smiths Falls ON K7A 1M8",
    "addr:housenumber":"11",
    "addr:postcode":"k7a 1m8",
    "addr:street":"William St W",
    "iso:country":"CA",
    "sg:address":"11 William St W",
    "sg:city":"Smiths Falls",
    "sg:classifiers":[
        {
            "category":"Personal",
            "subcategory":"Barber",
            "type":"Services"
        }
    ],
    "sg:phone":"+1 613 283 4374",
    "sg:postcode":"K7A 1M8",
    "sg:province":"ON",
    "wof:name":"Moustache Hair Styling For Men",
    "wof:placetype":"venue"
},
  "geometry": {"coordinates":[-76.022026,44.900311],"type":"Point"}
}