{
  "type": "Feature",
  "properties": {
    "addr:full":"1549 Rte 122 Bon-Conseil QC J0C 1A0",
    "addr:housenumber":"1549",
    "addr:postcode":"j0c 1a0",
    "addr:street":"Rte 122 Bon-Conseil",
    "iso:country":"CA",
    "sg:address":"1549 Rte 122",
    "sg:city":"Bon-Conseil",
    "sg:classifiers":[
        {
            "category":"Recreation",
            "type":"Entertainment"
        }
    ],
    "sg:phone":"+1 819 336 5273",
    "sg:postcode":"J0C 1A0",
    "sg:province":"QC",
    "sg:tags":[
        "sugar",
        "syrup",
        "hall",
        "maple",
        "auditorium"
    ],
    "wof:name":"Erabliere LA Pente Douce",
    "wof:placetype":"venue"
},
  "geometry": {"coordinates":[-72.345375,45.9991],"type":"Point"}
}