{
  "type": "Feature",
  "properties": {
    "addr:full":"1206 10 St Wainwright AB T9W 1E3",
    "addr:housenumber":"1206",
    "addr:postcode":"t9w 1e3",
    "addr:street":"10 St",
    "iso:country":"CA",
    "sg:address":"1206 10 St",
    "sg:city":"Wainwright",
    "sg:classifiers":[
        {
            "category":"Food & Beverages",
            "subcategory":"Liquor & Beverages",
            "type":"Retail Goods"
        }
    ],
    "sg:phone":"+1 780 842 5752",
    "sg:postcode":"T9W 1E3",
    "sg:province":"AB",
    "sg:tags":[
        "store"
    ],
    "wof:name":"Wainwright Liquor & Cold Beer",
    "wof:placetype":"venue"
},
  "geometry": {"coordinates":[-110.852394,52.841503],"type":"Point"}
}