{
  "type": "Feature",
  "properties": {
    "addr:full":"172 Boul Perron O New Richmond QC G0C 2B0",
    "addr:housenumber":"172",
    "addr:postcode":"g0c 2b0",
    "addr:street":"Boul Perron",
    "iso:country":"CA",
    "sg:address":"172 Boul Perron O",
    "sg:city":"New Richmond",
    "sg:classifiers":[
        {
            "category":"Home & Garden",
            "subcategory":"Furniture",
            "type":"Retail Goods"
        }
    ],
    "sg:phone":"+1 418 392 5300",
    "sg:postcode":"G0C 2B0",
    "sg:province":"QC",
    "wof:name":"Meubles Gustave Leblanc Inc",
    "wof:placetype":"venue"
},
  "geometry": {"coordinates":[-65.84639,48.153618],"type":"Point"}
}