{
  "type": "Feature",
  "properties": {
    "addr:full":"1694 Upper James St Hamilton ON L9B 1K6",
    "addr:housenumber":"1694",
    "addr:postcode":"l9b 1k6",
    "addr:street":"Upper James St",
    "iso:country":"CA",
    "sg:address":"1694 Upper James St",
    "sg:city":"Hamilton",
    "sg:classifiers":[
        {
            "category":"Organizations",
            "subcategory":"Religious Organization",
            "type":"Services"
        }
    ],
    "sg:phone":"+1 905 389 2472",
    "sg:postcode":"L9B 1K6",
    "sg:province":"ON",
    "sg:tags":[
        "church"
    ],
    "wof:name":"Corpus Christi Rectory",
    "wof:placetype":"venue"
},
  "geometry": {"coordinates":[-79.894882,43.199703],"type":"Point"}
}