{
  "type": "Feature",
  "properties": {
    "addr:full":"6917 93 St Grande Prairie AB T8V 6T4",
    "addr:housenumber":"6917",
    "addr:postcode":"t8v 6t4",
    "addr:street":"93 St",
    "iso:country":"CA",
    "sg:address":"6917 93 St",
    "sg:city":"Grande Prairie",
    "sg:classifiers":[
        {
            "category":"Building & Trades",
            "subcategory":"Construction",
            "type":"Services"
        }
    ],
    "sg:phone":"+1 780 532 9908",
    "sg:postcode":"T8V 6T4",
    "sg:province":"AB",
    "sg:tags":[
        "painter"
    ],
    "wof:name":"Hector's Painting & Decorating",
    "wof:placetype":"venue"
},
  "geometry": {"coordinates":[-118.77005800000001,55.142937],"type":"Point"}
}