{
  "type": "Feature",
  "properties": {
    "iso:country":"CA",
    "sg:address":"275 Rue DE L'Ile",
    "sg:city":"Caraquet",
    "sg:classifiers":[
        {
            "category":"Personal",
            "subcategory":"Beauty Salon",
            "type":"Services"
        }
    ],
    "sg:phone":"+1 506 727 6106",
    "sg:postcode":"E1W 1B5",
    "sg:province":"NB",
    "wof:name":"Salon Esthetique LA Joconde",
    "wof:placetype":"venue"
},
  "geometry": {"coordinates":[-64.95227050779999,47.7910690308],"type":"Point"}
}