{
  "type": "Feature",
  "properties": {
    "addr:full":"5865 Rue Jarry E Saint-Leonard QC H1P 1V7",
    "addr:housenumber":"5865",
    "addr:postcode":"h1p 1v7",
    "addr:street":"Rue Jarry E",
    "iso:country":"CA",
    "sg:address":"5865 Rue Jarry E",
    "sg:city":"Saint-Leonard",
    "sg:classifiers":[
        {
            "category":"Banks & Credit Unions",
            "subcategory":"Investment Brokerage",
            "type":"Services"
        }
    ],
    "sg:phone":"+1 514 322 3989",
    "sg:postcode":"H1P 1V7",
    "sg:province":"QC",
    "sg:tags":[
        "consultant",
        "planning",
        "financial"
    ],
    "wof:name":"Services Financiers Capitale",
    "wof:placetype":"venue"
},
  "geometry": {"coordinates":[-73.587502,45.588711],"type":"Point"}
}