{
  "type": "Feature",
  "properties": {
    "addr:full":"Surrey BC V3W 0N2",
    "addr:postcode":"v3w 0n2",
    "iso:country":"CA",
    "sg:city":"Surrey",
    "sg:classifiers":[
        {
            "category":"Autos & Motor Vehicles",
            "subcategory":"Auto Supplies",
            "type":"Retail Goods"
        }
    ],
    "sg:phone":"+1 604 572 3735",
    "sg:postcode":"V3W 0N2",
    "sg:province":"BC",
    "sg:tags":[
        "shaft",
        "parts",
        "drive",
        "automobile"
    ],
    "wof:name":"Driveline Services",
    "wof:placetype":"venue"
},
  "geometry": {"coordinates":[-122.8815,49.155701],"type":"Point"}
}