{
  "type": "Feature",
  "properties": {
    "addr:full":"833 King St Midland ON L4R 4L1",
    "addr:housenumber":"833",
    "addr:postcode":"l4r 4l1",
    "addr:street":"King St",
    "iso:country":"CA",
    "sg:address":"833 King St",
    "sg:city":"Midland",
    "sg:classifiers":[
        {
            "category":"Real Estate",
            "subcategory":"Real Estate Agent",
            "type":"Services"
        }
    ],
    "sg:phone":"+1 705 526 9366",
    "sg:postcode":"L4R 4L1",
    "sg:province":"ON",
    "wof:name":"Re/Max Georgian Bay Realty Ltd",
    "wof:placetype":"venue"
},
  "geometry": {"coordinates":[-79.87194824220001,44.7344360352],"type":"Point"}
}