{
  "type": "Feature",
  "properties": {
    "addr:full":"1285 Rue Aubuchon Trois-Rivieres QC G8Y 5K4",
    "addr:housenumber":"1285",
    "addr:postcode":"g8y 5k4",
    "addr:street":"Rue Aubuchon Trois-Rivieres",
    "iso:country":"CA",
    "sg:address":"1285 Rue Aubuchon",
    "sg:city":"Trois-Rivieres",
    "sg:classifiers":[
        {
            "category":"Restaurant",
            "type":"Food & Drink"
        }
    ],
    "sg:phone":"+1 819 693 2421",
    "sg:postcode":"G8Y 5K4",
    "sg:province":"QC",
    "wof:name":"Casa Grecque Trois-Rivieres",
    "wof:placetype":"venue"
},
  "geometry": {"coordinates":[-72.579819,46.354439],"type":"Point"}
}