{
  "type": "Feature",
  "properties": {
    "addr:full":"SE 5-12-5 E Dugald MB R0E 0K0",
    "addr:housenumber":"5-12-5",
    "addr:postcode":"r0e 0k0",
    "addr:street":"E Dugald",
    "iso:country":"CA",
    "sg:address":"SE 5-12-5 E",
    "sg:city":"Dugald",
    "sg:classifiers":[
        {
            "category":"Building & Trades",
            "subcategory":"Landscaping Services",
            "type":"Services"
        }
    ],
    "sg:phone":"+1 204 444 3594",
    "sg:postcode":"R0E 0K0",
    "sg:province":"MB",
    "sg:tags":[
        "landscape",
        "contractor"
    ],
    "wof:name":"Oakbank Small Acreage Svc",
    "wof:placetype":"venue"
},
  "geometry": {"coordinates":[-96.8401184082,49.8859062195],"type":"Point"}
}