{
  "type": "Feature",
  "properties": {
    "iso:country":"CA",
    "sg:address":"55 Metcalfe St #420",
    "sg:city":"Ottawa",
    "sg:classifiers":[
        {
            "category":"Wholesale",
            "subcategory":"Furniture",
            "type":"Manufacturing & Wholesale Goods"
        }
    ],
    "sg:phone":"+1 613 230 8187",
    "sg:postcode":"K1P 6L5",
    "sg:province":"ON",
    "wof:name":"Teknion Furniture Systems",
    "wof:placetype":"venue"
},
  "geometry": {"coordinates":[-75.696671,45.422134],"type":"Point"}
}