{
  "type": "Feature",
  "properties": {
    "addr:full":"55 Metcalfe St #420 Ottawa ON K1P 6L5",
    "addr:housenumber":"55",
    "addr:postcode":"k1p 6l5",
    "addr:street":"Metcalfe St # 420",
    "iso:country":"CA",
    "sg:address":"55 Metcalfe St #420",
    "sg:city":"Ottawa",
    "sg:classifiers":[
        {
            "category":"Wholesale",
            "subcategory":"Furniture",
            "type":"Manufacturing & Wholesale Goods"
        }
    ],
    "sg:phone":"+1 613 230 8187",
    "sg:postcode":"K1P 6L5",
    "sg:province":"ON",
    "wof:name":"Teknion Furniture Systems",
    "wof:placetype":"venue"
},
  "geometry": {"coordinates":[-75.69667099999999,45.422134],"type":"Point"}
}