{
  "type": "Feature",
  "properties": {
    "iso:country":"CA",
    "sg:city":"Calgary",
    "sg:classifiers":[
        {
            "category":"Wholesale",
            "subcategory":"Durable Goods & Equipment",
            "type":"Manufacturing & Wholesale Goods"
        }
    ],
    "sg:phone":"+1 403 291 3711",
    "sg:postcode":"T2E 6L6",
    "sg:province":"AB",
    "sg:tags":[
        "geophysical",
        "apparatus"
    ],
    "wof:name":"Lamont Bit Svc Ltd",
    "wof:placetype":"venue"
},
  "geometry": {"coordinates":[-114.032836914,51.0918922424],"type":"Point"}
}