{
  "type": "Feature",
  "properties": {
    "addr:full":"8469 Boul Newman Lasalle QC H8N 2Y7",
    "addr:housenumber":"8469",
    "addr:postcode":"h8n 2y7",
    "addr:street":"Boul Newman",
    "iso:country":"CA",
    "sg:address":"8469 Boul Newman",
    "sg:city":"Lasalle",
    "sg:classifiers":[
        {
            "category":"Home & Garden",
            "subcategory":"Home Furnishings",
            "type":"Retail Goods"
        }
    ],
    "sg:phone":"+1 514 365 8045",
    "sg:postcode":"H8N 2Y7",
    "sg:province":"QC",
    "sg:tags":[
        "curtain",
        "made",
        "drapery"
    ],
    "wof:name":"Fabricville",
    "wof:placetype":"venue"
},
  "geometry": {"coordinates":[-73.6327133179,45.4315643311],"type":"Point"}
}