{
  "type": "Feature",
  "properties": {
    "addr:full":"100 Newbold Crt London ON N6E 1Z7",
    "addr:housenumber":"100",
    "addr:postcode":"n6e 1z7",
    "addr:street":"Newbold Crt",
    "iso:country":"CA",
    "sg:address":"100 Newbold Crt",
    "sg:city":"London",
    "sg:classifiers":[
        {
            "category":"Home & Garden",
            "subcategory":"Building Materials",
            "type":"Retail Goods"
        }
    ],
    "sg:phone":"+1 519 649 2777",
    "sg:postcode":"N6E 1Z7",
    "sg:province":"ON",
    "sg:tags":[
        "glass",
        "window",
        "plate"
    ],
    "wof:name":"Vanfax",
    "wof:placetype":"venue"
},
  "geometry": {"coordinates":[-81.2129364014,42.9348716736],"type":"Point"}
}