{
  "type": "Feature",
  "properties": {
    "addr:full":"7136 Abbot St Mission BC V2V 5J6",
    "addr:housenumber":"7136",
    "addr:postcode":"v2v 5j6",
    "addr:street":"Abbot St",
    "iso:country":"CA",
    "sg:address":"7136 Abbot St",
    "sg:city":"Mission",
    "sg:classifiers":[
        {
            "category":"Manufacturing",
            "subcategory":"Tools & Machinery",
            "type":"Manufacturing & Wholesale Goods"
        }
    ],
    "sg:phone":"+1 604 820 1828",
    "sg:postcode":"V2V 5J6",
    "sg:province":"BC",
    "sg:tags":[
        "machine",
        "shop"
    ],
    "wof:name":"South Pacific Machine Ind Ltd",
    "wof:placetype":"venue"
},
  "geometry": {"coordinates":[-122.304947,49.131302],"type":"Point"}
}