{
  "type": "Feature",
  "properties": {
    "addr:full":"32915 South Fraser Way Abbotsford BC V2S 2A6",
    "addr:housenumber":"32915",
    "addr:postcode":"v2s 2a6",
    "addr:street":"South Fraser Way",
    "iso:country":"CA",
    "sg:address":"32915 South Fraser Way",
    "sg:city":"Abbotsford",
    "sg:classifiers":[
        {
            "category":"Banks & Credit Unions",
            "subcategory":"Bank",
            "type":"Services"
        }
    ],
    "sg:phone":"+1 604 852 2004",
    "sg:postcode":"V2S 2A6",
    "sg:province":"BC",
    "sg:tags":[
        "loan",
        "real estate"
    ],
    "wof:name":"Citifinancial Canada",
    "wof:placetype":"venue"
},
  "geometry": {"coordinates":[-122.311645508,49.0510482788],"type":"Point"}
}