{
  "type": "Feature",
  "properties": {
    "addr:full":"1 Bayard Dr Saint John NB E2L 3L5",
    "addr:housenumber":"1",
    "addr:postcode":"e2l 3l5",
    "addr:street":"Bayard Dr",
    "iso:country":"CA",
    "sg:address":"1 Bayard Dr",
    "sg:city":"Saint John",
    "sg:classifiers":[
        {
            "category":"Organizations",
            "subcategory":"Religious Organization",
            "type":"Services"
        }
    ],
    "sg:phone":"+1 506 653 6800",
    "sg:postcode":"E2L 3L5",
    "sg:province":"NB",
    "sg:tags":[
        "church"
    ],
    "wof:name":"Diocese of Saint John",
    "wof:placetype":"venue"
},
  "geometry": {"coordinates":[-66.058403,45.279011],"type":"Point"}
}