{
  "type": "Feature",
  "properties": {
    "addr:full":"38 Adelaide St N London ON N6B 3N5",
    "addr:housenumber":"38",
    "addr:postcode":"n6b 3n5",
    "addr:street":"Adelaide St N",
    "iso:country":"CA",
    "sg:address":"38 Adelaide St N",
    "sg:city":"London",
    "sg:classifiers":[
        {
            "category":"Restaurant",
            "type":"Food & Drink"
        }
    ],
    "sg:phone":"+1 519 439 9292",
    "sg:postcode":"N6B 3N5",
    "sg:province":"ON",
    "wof:name":"Paradise Cafe",
    "wof:placetype":"venue"
},
  "geometry": {"coordinates":[-81.22640228269999,42.9773139954],"type":"Point"}
}