{
  "type": "Feature",
  "properties": {
    "addr:full":"437 Main St W Grimsby ON L3M 1T1",
    "addr:housenumber":"437",
    "addr:postcode":"l3m 1t1",
    "addr:street":"Main St W",
    "iso:country":"CA",
    "sg:address":"437 Main St W",
    "sg:city":"Grimsby",
    "sg:classifiers":[
        {
            "category":"Autos & Motor Vehicles",
            "subcategory":"Automobile Sales",
            "type":"Retail Goods"
        }
    ],
    "sg:phone":"+1 905 309 9300",
    "sg:postcode":"L3M 1T1",
    "sg:province":"ON",
    "sg:tags":[
        "car",
        "dealer"
    ],
    "wof:name":"Milan's Auto Sales",
    "wof:placetype":"venue"
},
  "geometry": {"coordinates":[-79.60614,43.197578],"type":"Point"}
}