{
  "type": "Feature",
  "properties": {
    "addr:full":"2165 Parkcrest Ave Kamloops BC V2B 4X9",
    "addr:housenumber":"2165",
    "addr:postcode":"bc v2b 4x9",
    "addr:street":"Parkcrest Ave",
    "iso:country":"CA",
    "sg:address":"2165 Parkcrest Ave",
    "sg:city":"Kamloops",
    "sg:classifiers":[
        {
            "category":"Organizations",
            "subcategory":"Religious Organization",
            "type":"Services"
        }
    ],
    "sg:phone":"+1 250 376 2515",
    "sg:postcode":"V2B 4X9",
    "sg:province":"BC",
    "sg:tags":[
        "church"
    ],
    "wof:name":"Church of Jesus Christ-Lds",
    "wof:placetype":"venue"
},
  "geometry": {"coordinates":[-120.406334,50.707607],"type":"Point"}
}