{
  "type": "Feature",
  "properties": {
    "iso:country":"CA",
    "sg:city":"Montreal",
    "sg:classifiers":[
        {
            "category":"Social Services",
            "subcategory":"Child Care",
            "type":"Services"
        }
    ],
    "sg:phone":"+1 514 890 1168",
    "sg:postcode":"H2J 3J5",
    "sg:province":"QC",
    "wof:name":"Halte-Garderie Du Soleil",
    "wof:placetype":"venue"
},
  "geometry": {"coordinates":[-73.581116,45.530098],"type":"Point"}
}