{
  "type": "Feature",
  "properties": {
    "addr:full":"Penhold AB T0M 1R0",
    "addr:postcode":"t0m 1r0",
    "iso:country":"CA",
    "sg:city":"Penhold",
    "sg:classifiers":[
        {
            "category":"Professional",
            "subcategory":"Printing & Photocopies",
            "type":"Services"
        }
    ],
    "sg:phone":"+1 403 886 2720",
    "sg:postcode":"T0M 1R0",
    "sg:province":"AB",
    "sg:tags":[
        "duplicating",
        "copying"
    ],
    "wof:name":"Aviation Publications",
    "wof:placetype":"venue"
},
  "geometry": {"coordinates":[-113.88269805900001,52.1786499023],"type":"Point"}
}