{
  "type": "Feature",
  "properties": {
    "addr:full":"866 Wellingsboro Rd London ON N6E 1Y5",
    "addr:housenumber":"866",
    "addr:postcode":"n6e 1y5",
    "addr:street":"Wellingsboro Rd",
    "iso:country":"CA",
    "sg:address":"866 Wellingsboro Rd",
    "sg:city":"London",
    "sg:classifiers":[
        {
            "category":"Organizations",
            "subcategory":"Religious Organization",
            "type":"Services"
        }
    ],
    "sg:phone":"+1 519 681 3561",
    "sg:postcode":"N6E 1Y5",
    "sg:province":"ON",
    "sg:tags":[
        "church"
    ],
    "wof:name":"Jehovah's Witnesses",
    "wof:placetype":"venue"
},
  "geometry": {"coordinates":[-81.224037,42.942223],"type":"Point"}
}