{
  "type": "Feature",
  "properties": {
    "addr:full":"686 Queenston Rd Hamilton ON L8G 1A3",
    "addr:housenumber":"686",
    "addr:postcode":"l8g 1a3",
    "addr:street":"Queenston Rd",
    "iso:country":"CA",
    "sg:address":"686 Queenston Rd",
    "sg:city":"Hamilton",
    "sg:classifiers":[
        {
            "category":"Banks & Credit Unions",
            "subcategory":"Bank",
            "type":"Services"
        }
    ],
    "sg:phone":"+1 905 560 2200",
    "sg:postcode":"L8G 1A3",
    "sg:province":"ON",
    "wof:name":"Scotiabank",
    "wof:placetype":"venue"
},
  "geometry": {"coordinates":[-79.772141,43.229515],"type":"Point"}
}