{
  "type": "Feature",
  "properties": {
    "addr:full":"737 Rue Tardif E Rouyn-Noranda QC J9X 5R5",
    "addr:housenumber":"737",
    "addr:postcode":"j9x 5r5",
    "addr:street":"Rue Tardif E",
    "iso:country":"CA",
    "sg:address":"737 Rue Tardif E",
    "sg:city":"Rouyn-Noranda",
    "sg:classifiers":[
        {
            "category":"Education",
            "subcategory":"College",
            "type":"Public Place"
        }
    ],
    "sg:phone":"+1 819 764 5551",
    "sg:postcode":"J9X 5R5",
    "sg:province":"QC",
    "sg:tags":[
        "academic",
        "school"
    ],
    "wof:name":"Cegep DE L'Abitibi",
    "wof:placetype":"venue"
},
  "geometry": {"coordinates":[-79.005065918,48.2275085449],"type":"Point"}
}