{
  "type": "Feature",
  "properties": {
    "addr:full":"613 Columbia St New Westminster BC V3M 1A7",
    "addr:housenumber":"613",
    "addr:postcode":"v3m 1a7",
    "addr:street":"Columbia",
    "iso:country":"CA",
    "sg:address":"613 Columbia St",
    "sg:city":"New Westminster",
    "sg:classifiers":[
        {
            "category":"Education",
            "subcategory":"College",
            "type":"Public Place"
        }
    ],
    "sg:phone":"+1 604 520 1844",
    "sg:postcode":"V3M 1A7",
    "sg:province":"BC",
    "sg:tags":[
        "academic",
        "school"
    ],
    "wof:name":"West Coast College of Massage",
    "wof:placetype":"venue"
},
  "geometry": {"coordinates":[-122.908302307,49.2031135559],"type":"Point"}
}