{
  "type": "Feature",
  "properties": {
    "addr:full":"9801 Boul Parkway Anjou QC H1J 1P3",
    "addr:housenumber":"9801",
    "addr:postcode":"h1j 1p3",
    "addr:street":"Boul Parkway",
    "iso:country":"CA",
    "sg:address":"9801 Boul Parkway",
    "sg:city":"Anjou",
    "sg:classifiers":[
        {
            "category":"Professional",
            "subcategory":"Business Services",
            "type":"Services"
        }
    ],
    "sg:phone":"+1 514 351 5300",
    "sg:postcode":"H1J 1P3",
    "sg:province":"QC",
    "sg:tags":[
        "plate",
        "lithographic",
        "negative"
    ],
    "wof:name":"Luxolith Inc",
    "wof:placetype":"venue"
},
  "geometry": {"coordinates":[-73.57209,45.617447],"type":"Point"}
}