{
  "type": "Feature",
  "properties": {
    "addr:full":"Huntsville ON P1H 2J4",
    "addr:postcode":"p1h 2j4",
    "iso:country":"CA",
    "sg:city":"Huntsville",
    "sg:classifiers":[
        {
            "category":"Travel",
            "subcategory":"Hotels & Motels",
            "type":"Entertainment"
        }
    ],
    "sg:phone":"+1 705 789 5383",
    "sg:postcode":"P1H 2J4",
    "sg:province":"ON",
    "sg:tags":[
        "tourist",
        "accommodation"
    ],
    "wof:name":"Silver Sands Tent & Trailer",
    "wof:placetype":"venue"
},
  "geometry": {"coordinates":[-79.23346710209999,45.3777580261],"type":"Point"}
}