{
  "type": "Feature",
  "properties": {
    "addr:full":"5290 Rue Jacques-Cartier Saint-Hyacinthe QC J2S 3Z3",
    "addr:housenumber":"5290",
    "addr:postcode":"j2s 3z3",
    "addr:street":"Rue Jacques-Cartier",
    "iso:country":"CA",
    "sg:address":"5290 Rue Jacques-Cartier",
    "sg:city":"Saint-Hyacinthe",
    "sg:classifiers":[
        {
            "category":"Building & Trades",
            "subcategory":"Cleaning & Sanitation",
            "type":"Services"
        }
    ],
    "sg:phone":"+1 450 773 2294",
    "sg:postcode":"J2S 3Z3",
    "sg:province":"QC",
    "sg:tags":[
        "house",
        "janitor"
    ],
    "wof:name":"Services Menagers Aurele",
    "wof:placetype":"venue"
},
  "geometry": {"coordinates":[-72.97430419920001,45.6031951904],"type":"Point"}
}