{
  "type": "Feature",
  "properties": {
    "addr:full":"1394 Pembroke St W Pembroke ON K8A 7M3",
    "addr:housenumber":"1394",
    "addr:postcode":"k8a 7m3",
    "addr:street":"Pembroke St W",
    "iso:country":"CA",
    "sg:address":"1394 Pembroke St W",
    "sg:city":"Pembroke",
    "sg:classifiers":[
        {
            "category":"Manufacturing",
            "subcategory":"Signs",
            "type":"Manufacturing & Wholesale Goods"
        }
    ],
    "sg:phone":"+1 613 735 4464",
    "sg:postcode":"K8A 7M3",
    "sg:province":"ON",
    "wof:name":"Sunsign Graphics Inc",
    "wof:placetype":"venue"
},
  "geometry": {"coordinates":[-77.15371704099999,45.8348808289],"type":"Point"}
}