{
  "type": "Feature",
  "properties": {
    "addr:full":"919 Rue Beaubien E Montreal QC H2S 1T2",
    "addr:housenumber":"919",
    "addr:postcode":"h2s 1t2",
    "addr:street":"Rue Beaubien E",
    "iso:country":"CA",
    "sg:address":"919 Rue Beaubien E",
    "sg:city":"Montreal",
    "sg:classifiers":[
        {
            "category":"Shopping",
            "type":"Retail Goods"
        }
    ],
    "sg:phone":"+1 514 277 8429",
    "sg:postcode":"H2S 1T2",
    "sg:province":"QC",
    "sg:tags":[
        "pet",
        "food",
        "supply"
    ],
    "wof:name":"Nutranimo-Bouffe Animale Dlc",
    "wof:placetype":"venue"
},
  "geometry": {"coordinates":[-73.60251617430001,45.5368309021],"type":"Point"}
}