{
  "type": "Feature",
  "properties": {
    "iso:country":"CA",
    "sg:city":"Sherwood Park",
    "sg:classifiers":[
        {
            "category":"Building & Trades",
            "subcategory":"Plumbing",
            "type":"Services"
        }
    ],
    "sg:phone":"+1 780 922 5200",
    "sg:postcode":"T8G 1B8",
    "sg:province":"AB",
    "sg:tags":[
        "contractor"
    ],
    "wof:name":"Mainline Mechanical Ltd",
    "wof:placetype":"venue"
},
  "geometry": {"coordinates":[-113.29573822,53.5264015198],"type":"Point"}
}