{
  "type": "Feature",
  "properties": {
    "iso:country":"CA",
    "sg:address":"177 Rue Victoria",
    "sg:city":"Edmundston",
    "sg:classifiers":[
        {
            "category":"Autos & Motor Vehicles",
            "subcategory":"Recreational Vehicle Sales",
            "type":"Retail Goods"
        }
    ],
    "sg:phone":"+1 506 739 5247",
    "sg:postcode":"E3V 2H7",
    "sg:province":"NB",
    "wof:name":"Martin Rv Trailer Parts",
    "wof:placetype":"venue"
},
  "geometry": {"coordinates":[-68.3231124878,47.3687286377],"type":"Point"}
}