{
  "type": "Feature",
  "properties": {
    "addr:full":"42nd St & Hwy 3 Prince Albert SK S6V 8A4",
    "addr:postcode":"s6v 8a4",
    "addr:street":"42Nd St & Hwy 3",
    "iso:country":"CA",
    "sg:address":"42nd St & Hwy 3",
    "sg:city":"Prince Albert",
    "sg:classifiers":[
        {
            "category":"Manufacturing",
            "subcategory":"Metals",
            "type":"Manufacturing & Wholesale Goods"
        }
    ],
    "sg:phone":"+1 306 764 9333",
    "sg:postcode":"S6V 8A4",
    "sg:province":"SK",
    "sg:tags":[
        "steel"
    ],
    "wof:name":"Mc Donald Metals Ltd",
    "wof:placetype":"venue"
},
  "geometry": {"coordinates":[-105.757301,53.174927],"type":"Point"}
}