{
  "type": "Feature",
  "properties": {
    "addr:full":"Hull QC J8Z 2B4",
    "addr:postcode":"j8z 2b4",
    "iso:country":"CA",
    "sg:city":"Hull",
    "sg:classifiers":[
        {
            "category":"Shopping",
            "subcategory":"Clothing, Apparel, & Fashions",
            "type":"Retail Goods"
        }
    ],
    "sg:phone":"+1 819 771 8458",
    "sg:postcode":"J8Z 2B4",
    "sg:province":"QC",
    "sg:tags":[
        "salvage",
        "surplus",
        "merchandise"
    ],
    "wof:name":"G Brunette & Fils Enrg",
    "wof:placetype":"venue"
},
  "geometry": {"coordinates":[-75.74346923829999,45.4728546143],"type":"Point"}
}