{
  "type": "Feature",
  "properties": {
    "iso:country":"CA",
    "sg:city":"Charlesbourg",
    "sg:classifiers":[
        {
            "category":"Health Services",
            "subcategory":"Doctor",
            "type":"Services"
        }
    ],
    "sg:phone":"+1 418 622 1330",
    "sg:postcode":"G1G 5X1",
    "sg:province":"QC",
    "sg:tags":[
        "clinic"
    ],
    "wof:name":"Societe Medico Administrative",
    "wof:placetype":"venue"
},
  "geometry": {"coordinates":[-71.2707748413,46.8651123047],"type":"Point"}
}