{
  "type": "Feature",
  "properties": {
    "addr:full":"616 Av Saint-Redempteur Matane QC G4W 1L1",
    "addr:postcode":"g4w 1l1",
    "addr:street":"616 Av Saint-Redempteur",
    "iso:country":"CA",
    "sg:address":"616 Av Saint-Redempteur",
    "sg:city":"Matane",
    "sg:classifiers":[
        {
            "category":"Education",
            "subcategory":"College",
            "type":"Public Place"
        }
    ],
    "sg:phone":"+1 418 562 1240",
    "sg:postcode":"G4W 1L1",
    "sg:province":"QC",
    "sg:tags":[
        "academic",
        "school"
    ],
    "wof:name":"Cegep DE Matane",
    "wof:placetype":"venue"
},
  "geometry": {"coordinates":[-67.50258636469999,48.8404655457],"type":"Point"}
}