{
  "type": "Feature",
  "properties": {
    "addr:full":"6126 Wadge St Regina SK S4X 4A3",
    "addr:housenumber":"6126",
    "addr:postcode":"s4x 4a3",
    "addr:street":"Wadge St",
    "iso:country":"CA",
    "sg:address":"6126 Wadge St",
    "sg:city":"Regina",
    "sg:classifiers":[
        {
            "category":"Wholesale",
            "subcategory":"Machinery & Supplies",
            "type":"Manufacturing & Wholesale Goods"
        }
    ],
    "sg:phone":"+1 306 949 1564",
    "sg:postcode":"S4X 4A3",
    "sg:province":"SK",
    "wof:name":"Reliance Industrial Svc",
    "wof:placetype":"venue"
},
  "geometry": {"coordinates":[-104.668678,50.502197],"type":"Point"}
}