{
  "type": "Feature",
  "properties": {
    "addr:full":"190 Springbank Ave Woodstock ON N4S 7R1",
    "addr:housenumber":"190",
    "addr:postcode":"n4s 7r1",
    "addr:street":"Springbank Ave",
    "iso:country":"CA",
    "sg:address":"190 Springbank Ave",
    "sg:city":"Woodstock",
    "sg:classifiers":[
        {
            "category":"Organizations",
            "subcategory":"Religious Organization",
            "type":"Services"
        }
    ],
    "sg:phone":"+1 519 539 3161",
    "sg:postcode":"N4S 7R1",
    "sg:province":"ON",
    "sg:tags":[
        "church"
    ],
    "wof:name":"St David's United Church",
    "wof:placetype":"venue"
},
  "geometry": {"coordinates":[-80.73189499999999,43.140957],"type":"Point"}
}