{
  "type": "Feature",
  "properties": {
    "addr:full":"20353 1st St Green Valley ON K0C 1L0",
    "addr:housenumber":"20353",
    "addr:postcode":"k0c 1l0",
    "addr:street":"1St St",
    "iso:country":"CA",
    "sg:address":"20353 1st St",
    "sg:city":"Green Valley",
    "sg:classifiers":[
        {
            "category":"Manufacturing",
            "subcategory":"Printing",
            "type":"Manufacturing & Wholesale Goods"
        }
    ],
    "sg:phone":"+1 613 525 5070",
    "sg:postcode":"K0C 1L0",
    "sg:province":"ON",
    "sg:tags":[
        "printer"
    ],
    "wof:name":"Imprimerie C'a Presse Printing",
    "wof:placetype":"venue"
},
  "geometry": {"coordinates":[-74.59627500000001,45.258953],"type":"Point"}
}