{
  "type": "Feature",
  "properties": {
    "addr:full":"1090 18E Rue Quebec QC G1J 1Y9",
    "addr:housenumber":"1090",
    "addr:postcode":"g1j 1y9",
    "addr:street":"18E Rue Quebec",
    "iso:country":"CA",
    "sg:address":"1090 18E Rue",
    "sg:city":"Quebec",
    "sg:classifiers":[
        {
            "category":"Manufacturing",
            "subcategory":"Building Materials",
            "type":"Manufacturing & Wholesale Goods"
        }
    ],
    "sg:phone":"+1 418 524 5317",
    "sg:postcode":"G1J 1Y9",
    "sg:province":"QC",
    "sg:tags":[
        "woodworker"
    ],
    "wof:name":"Menuiserie Delisle Inc",
    "wof:placetype":"venue"
},
  "geometry": {"coordinates":[-71.2287979126,46.8342628479],"type":"Point"}
}