{
  "type": "Feature",
  "properties": {
    "iso:country":"CA",
    "sg:city":"Brampton",
    "sg:classifiers":[
        {
            "category":"Building & Trades",
            "subcategory":"Construction",
            "type":"Services"
        }
    ],
    "sg:phone":"+1 905 458 5271",
    "sg:postcode":"L6S 5N9",
    "sg:province":"ON",
    "sg:tags":[
        "paving",
        "contractor"
    ],
    "wof:name":"Girone Concrete & Paving Inc",
    "wof:placetype":"venue"
},
  "geometry": {"coordinates":[-79.711334,43.758102],"type":"Point"}
}