{
  "type": "Feature",
  "properties": {
    "addr:full":"339 Boul Henri-Bourassa O Montreal QC H3L 1N9",
    "addr:housenumber":"339",
    "addr:postcode":"h3l 1n9",
    "addr:street":"Boul Henri-Bourassa O",
    "iso:country":"CA",
    "sg:address":"339 Boul Henri-Bourassa O",
    "sg:city":"Montreal",
    "sg:classifiers":[
        {
            "category":"Food & Beverages",
            "subcategory":"Groceries & Convenience Stores",
            "type":"Retail Goods"
        }
    ],
    "sg:phone":"+1 514 334 1929",
    "sg:postcode":"H3L 1N9",
    "sg:province":"QC",
    "sg:tags":[
        "grocer"
    ],
    "wof:name":"Marche Delorme",
    "wof:placetype":"venue"
},
  "geometry": {"coordinates":[-73.669533,45.553349],"type":"Point"}
}