{
  "type": "Feature",
  "properties": {
    "addr:full":"475 Mary St Hamilton ON L8L 4X3",
    "addr:housenumber":"475",
    "addr:postcode":"l8l 4x3",
    "addr:street":"Mary St",
    "iso:country":"CA",
    "sg:address":"475 Mary St",
    "sg:city":"Hamilton",
    "sg:classifiers":[
        {
            "category":"Organizations",
            "subcategory":"Religious Organization",
            "type":"Services"
        }
    ],
    "sg:phone":"+1 905 522 6012",
    "sg:postcode":"L8L 4X3",
    "sg:province":"ON",
    "sg:tags":[
        "church"
    ],
    "wof:name":"Saint Lawrence's Rectory",
    "wof:placetype":"venue"
},
  "geometry": {"coordinates":[-79.85824599999999,43.269127],"type":"Point"}
}