{
  "type": "Feature",
  "properties": {
    "addr:full":"534 Barton St E Hamilton ON L8L 2Z1",
    "addr:housenumber":"534",
    "addr:postcode":"l8l 2z1",
    "addr:street":"Barton St E",
    "iso:country":"CA",
    "sg:address":"534 Barton St E",
    "sg:city":"Hamilton",
    "sg:classifiers":[
        {
            "category":"Professional",
            "subcategory":"Art Services",
            "type":"Services"
        }
    ],
    "sg:phone":"+1 905 522 3800",
    "sg:postcode":"L8L 2Z1",
    "sg:province":"ON",
    "sg:tags":[
        "graphic",
        "designer"
    ],
    "wof:name":"Palmese Photodesign Group Inc",
    "wof:placetype":"venue"
},
  "geometry": {"coordinates":[-79.84332999999999,43.258297],"type":"Point"}
}