{
  "type": "Feature",
  "properties": {
    "addr:full":"3183 Gershaw Dr SW Medicine Hat AB T1B 3N1",
    "addr:housenumber":"3183",
    "addr:postcode":"t1b 3n1",
    "addr:street":"Gershaw Dr Sw",
    "iso:country":"CA",
    "sg:address":"3183 Gershaw Dr SW",
    "sg:city":"Medicine Hat",
    "sg:classifiers":[
        {
            "category":"Freight",
            "type":"Transportation"
        }
    ],
    "sg:phone":"+1 403 529 2646",
    "sg:postcode":"T1B 3N1",
    "sg:province":"AB",
    "sg:tags":[
        "commercial",
        "storage"
    ],
    "wof:name":"Medicine Hat Mini Storage Ltd",
    "wof:placetype":"venue"
},
  "geometry": {"coordinates":[-110.732193,50.009735],"type":"Point"}
}