{
  "type": "Feature",
  "properties": {
    "addr:full":"Terrace BC V8G 1T2",
    "addr:postcode":"v8g 1t2",
    "iso:country":"CA",
    "sg:city":"Terrace",
    "sg:classifiers":[
        {
            "category":"Professional",
            "subcategory":"Computer Services",
            "type":"Services"
        }
    ],
    "sg:phone":"+1 250 635 3362",
    "sg:postcode":"V8G 1T2",
    "sg:province":"BC",
    "sg:tags":[
        "repair",
        "dealer",
        "equipment"
    ],
    "wof:name":"Pendragon Computers",
    "wof:placetype":"venue"
},
  "geometry": {"coordinates":[-128.59425400000001,54.517868],"type":"Point"}
}