{
  "type": "Feature",
  "properties": {
    "addr:full":"45465 Bernard Ave Chilliwack BC V2P 1H6",
    "addr:housenumber":"45465",
    "addr:postcode":"v2p 1h6",
    "addr:street":"Bernard Ave",
    "iso:country":"CA",
    "sg:address":"45465 Bernard Ave",
    "sg:city":"Chilliwack",
    "sg:classifiers":[
        {
            "category":"Education",
            "subcategory":"School",
            "type":"Public Place"
        }
    ],
    "sg:phone":"+1 604 795 7840",
    "sg:postcode":"V2P 1H6",
    "sg:province":"BC",
    "wof:name":"Bernard Elementary",
    "wof:placetype":"venue"
},
  "geometry": {"coordinates":[-121.966072,49.163605],"type":"Point"}
}