{
  "type": "Feature",
  "properties": {
    "addr:full":"774 Colborne St Brantford ON N3S 3S1",
    "addr:housenumber":"774",
    "addr:postcode":"n3s 3s1",
    "addr:street":"Colborne St",
    "iso:country":"CA",
    "sg:address":"774 Colborne St",
    "sg:city":"Brantford",
    "sg:classifiers":[
        {
            "category":"Building & Trades",
            "subcategory":"Construction",
            "type":"Services"
        }
    ],
    "sg:phone":"+1 519 752 1851",
    "sg:postcode":"N3S 3S1",
    "sg:province":"ON",
    "sg:tags":[
        "tile",
        "dealer"
    ],
    "wof:name":"Brantford Ceramic Tile Ctr",
    "wof:placetype":"venue"
},
  "geometry": {"coordinates":[-80.22801200000001,43.143658],"type":"Point"}
}