{
  "type": "Feature",
  "properties": {
    "addr:full":"Everett ON L0M 1J0",
    "addr:postcode":"l0m 1j0",
    "iso:country":"CA",
    "sg:city":"Everett",
    "sg:classifiers":[
        {
            "category":"Professional",
            "subcategory":"Computer Services",
            "type":"Services"
        }
    ],
    "sg:phone":"+1 705 435 0500",
    "sg:postcode":"L0M 1J0",
    "sg:province":"ON",
    "sg:tags":[
        "telephone"
    ],
    "wof:name":"Voiceline Communications",
    "wof:placetype":"venue"
},
  "geometry": {"coordinates":[-79.933975,44.194599],"type":"Point"}
}