{
  "type": "Feature",
  "properties": {
    "iso:country":"CA",
    "sg:city":"Markham",
    "sg:classifiers":[
        {
            "category":"Shopping",
            "subcategory":"Florist",
            "type":"Retail Goods"
        }
    ],
    "sg:phone":"+1 905 940 6682",
    "sg:postcode":"L3R 5H4",
    "sg:province":"ON",
    "wof:name":"Beyond Flowers",
    "wof:placetype":"venue"
},
  "geometry": {"coordinates":[-79.33358,43.83477],"type":"Point"}
}