{
  "type": "Feature",
  "properties": {
    "iso:country":"CA",
    "sg:city":"Richmond Hill",
    "sg:classifiers":[
        {
            "category":"Retail",
            "subcategory":"Repair Shop",
            "type":"Services"
        }
    ],
    "sg:phone":"+1 905 731 1624",
    "sg:postcode":"L4C 3C7",
    "sg:province":"ON",
    "sg:tags":[
        "lock",
        "locksmith"
    ],
    "wof:name":"Lock Master Security Svc",
    "wof:placetype":"venue"
},
  "geometry": {"coordinates":[-79.440369,43.883972],"type":"Point"}
}