{
  "type": "Feature",
  "properties": {
    "addr:full":"Calgary AB T2P 3G9",
    "addr:postcode":"t2p 3g9",
    "iso:country":"CA",
    "sg:city":"Calgary",
    "sg:classifiers":[
        {
            "category":"Professional",
            "subcategory":"Management & Consulting",
            "type":"Services"
        }
    ],
    "sg:phone":"+1 403 233 7448",
    "sg:postcode":"T2P 3G9",
    "sg:province":"AB",
    "sg:tags":[
        "consultant",
        "training"
    ],
    "wof:name":"Priority Management",
    "wof:placetype":"venue"
},
  "geometry": {"coordinates":[-114.08466339100001,51.0472679138],"type":"Point"}
}