{
  "type": "Feature",
  "properties": {
    "addr:full":"1971 Rue Saint-Cesaire Marieville QC J3M 1J5",
    "addr:housenumber":"1971",
    "addr:postcode":"j3m 1j5",
    "addr:street":"Rue Saint-Cesaire",
    "iso:country":"CA",
    "sg:address":"1971 Rue Saint-Cesaire",
    "sg:city":"Marieville",
    "sg:classifiers":[
        {
            "category":"Professional",
            "subcategory":"Business Services",
            "type":"Services"
        }
    ],
    "sg:phone":"+1 450 460 7678",
    "sg:postcode":"J3M 1J5",
    "sg:province":"QC",
    "sg:tags":[
        "event"
    ],
    "wof:name":"Festival International-Chanson",
    "wof:placetype":"venue"
},
  "geometry": {"coordinates":[-73.15763099999999,45.435299],"type":"Point"}
}