{
  "type": "Feature",
  "properties": {
    "addr:full":"1744 Main St N Moose Jaw SK S6J 1L4",
    "addr:housenumber":"1744",
    "addr:postcode":"s6j 1l4",
    "addr:street":"Main St N",
    "iso:country":"CA",
    "sg:address":"1744 Main St N",
    "sg:city":"Moose Jaw",
    "sg:classifiers":[
        {
            "category":"Retail",
            "subcategory":"Auto Repair",
            "type":"Services"
        }
    ],
    "sg:phone":"+1 306 694 0700",
    "sg:postcode":"S6J 1L4",
    "sg:province":"SK",
    "sg:tags":[
        "repairing",
        "automobile"
    ],
    "wof:name":"Centennial Tire Ctr Ltd",
    "wof:placetype":"venue"
},
  "geometry": {"coordinates":[-105.53511047400001,50.4161224365],"type":"Point"}
}