{
  "type": "Feature",
  "properties": {
    "iso:country":"CA",
    "sg:address":"303 Av Mozart E",
    "sg:city":"Montreal",
    "sg:classifiers":[
        {
            "category":"Restaurant",
            "type":"Food & Drink"
        }
    ],
    "sg:phone":"+1 514 270 5952",
    "sg:postcode":"H2S 1B8",
    "sg:province":"QC",
    "sg:tags":[
        "baker"
    ],
    "wof:name":"Boulangerie & Patisserie Motta",
    "wof:placetype":"venue"
},
  "geometry": {"coordinates":[-73.613243103,45.536239624],"type":"Point"}
}