{
  "type": "Feature",
  "properties": {
    "addr:full":"Mississauga ON L5E 1V4",
    "addr:postcode":"l5e 1v4",
    "iso:country":"CA",
    "sg:city":"Mississauga",
    "sg:classifiers":[
        {
            "category":"Shopping",
            "subcategory":"Shoes",
            "type":"Retail Goods"
        }
    ],
    "sg:phone":"+1 905 271 7077",
    "sg:postcode":"L5E 1V4",
    "sg:province":"ON",
    "wof:name":"Payless Shoe Source",
    "wof:placetype":"venue"
},
  "geometry": {"coordinates":[-79.567795,43.594978],"type":"Point"}
}