{
  "type": "Feature",
  "properties": {
    "addr:full":"405 Stevenson Rd 2 W Utterson ON P0B 1M0",
    "addr:housenumber":"405",
    "addr:postcode":"p0b 1m0",
    "addr:street":"Stevenson Rd 2 W Utterson",
    "iso:country":"CA",
    "sg:address":"405 Stevenson Rd 2 W",
    "sg:city":"Utterson",
    "sg:classifiers":[
        {
            "category":"Organizations",
            "subcategory":"Membership Organization",
            "type":"Services"
        }
    ],
    "sg:phone":"+1 705 385 1488",
    "sg:postcode":"P0B 1M0",
    "sg:province":"ON",
    "sg:tags":[
        "society",
        "humane"
    ],
    "wof:name":"Wing & A Prayer Bird Rehab",
    "wof:placetype":"venue"
},
  "geometry": {"coordinates":[-79.327866,45.21104],"type":"Point"}
}