{
  "type": "Feature",
  "properties": {
    "iso:country":"CA",
    "sg:address":"2184 Bader Cres",
    "sg:city":"Burlington",
    "sg:classifiers":[
        {
            "category":"Real Estate",
            "subcategory":"Architect",
            "type":"Services"
        }
    ],
    "sg:phone":"+1 905 332 8533",
    "sg:postcode":"L7P 4N5",
    "sg:province":"ON",
    "wof:name":"Clarridge, Ana",
    "wof:placetype":"venue"
},
  "geometry": {"coordinates":[-79.845734,43.359116],"type":"Point"}
}