{
  "type": "Feature",
  "properties": {
    "addr:full":"RR 1 Carstairs AB T0M 0N0",
    "addr:postcode":"t0m 0n0",
    "addr:street":"Rr 1",
    "iso:country":"CA",
    "sg:address":"RR 1",
    "sg:city":"Carstairs",
    "sg:classifiers":[
        {
            "category":"Shopping",
            "subcategory":"Crafts & Fabrics",
            "type":"Retail Goods"
        }
    ],
    "sg:phone":"+1 403 337 2221",
    "sg:postcode":"T0M 0N0",
    "sg:province":"AB",
    "sg:tags":[
        "woolen"
    ],
    "wof:name":"Custom Woollen Mills Ltd",
    "wof:placetype":"venue"
},
  "geometry": {"coordinates":[-114.095428467,51.5625953674],"type":"Point"}
}