{
  "type": "Feature",
  "properties": {
    "addr:full":"RR 4 Hunter River PE C0A 1N0",
    "addr:postcode":"c0a 1n0",
    "addr:street":"Rr 4",
    "iso:country":"CA",
    "sg:address":"RR 4",
    "sg:city":"Hunter River",
    "sg:classifiers":[
        {
            "category":"Shopping",
            "type":"Retail Goods"
        }
    ],
    "sg:phone":"+1 902 964 3494",
    "sg:postcode":"C0A 1N0",
    "sg:province":"PE",
    "sg:tags":[
        "monument"
    ],
    "wof:name":"Tingley Monuments Ltd",
    "wof:placetype":"venue"
},
  "geometry": {"coordinates":[-63.3431472778,46.3517608643],"type":"Point"}
}