{
  "type": "Feature",
  "properties": {
    "addr:full":"115 Main St Rosetown SK S0L 2V0",
    "addr:housenumber":"115",
    "addr:postcode":"s0l 2v0",
    "addr:street":"Main St",
    "iso:country":"CA",
    "sg:address":"115 Main St",
    "sg:city":"Rosetown",
    "sg:classifiers":[
        {
            "category":"Shopping",
            "type":"Retail Goods"
        }
    ],
    "sg:phone":"+1 306 882 4522",
    "sg:postcode":"S0L 2V0",
    "sg:province":"SK",
    "sg:tags":[
        "equipment",
        "care",
        "health",
        "home"
    ],
    "wof:name":"Niccolls Mobility Plus",
    "wof:placetype":"venue"
},
  "geometry": {"coordinates":[-107.991432,51.550991],"type":"Point"}
}