{
  "type": "Feature",
  "properties": {
    "iso:country":"CA",
    "sg:address":"530 Adelaide St W",
    "sg:city":"Toronto",
    "sg:classifiers":[
        {
            "category":"Manufacturing",
            "subcategory":"Apparel",
            "type":"Manufacturing & Wholesale Goods"
        }
    ],
    "sg:phone":"+1 416 504 0762",
    "sg:postcode":"M5V 1T5",
    "sg:province":"ON",
    "sg:tags":[
        "clothing"
    ],
    "wof:name":"Bingtex",
    "wof:placetype":"venue"
},
  "geometry": {"coordinates":[-79.4014968872,43.6456832886],"type":"Point"}
}