{
  "type": "Feature",
  "properties": {
    "addr:full":"1950 Barton St E Hamilton ON L8H 2Y6",
    "addr:housenumber":"1950",
    "addr:postcode":"l8h 2y6",
    "addr:street":"Barton St E",
    "iso:country":"CA",
    "sg:address":"1950 Barton St E",
    "sg:city":"Hamilton",
    "sg:classifiers":[
        {
            "category":"Building & Trades",
            "subcategory":"Construction",
            "type":"Services"
        }
    ],
    "sg:phone":"+1 905 544 0707",
    "sg:postcode":"L8H 2Y6",
    "sg:province":"ON",
    "sg:tags":[
        "roofing",
        "material",
        "contractor"
    ],
    "wof:name":"Herman's Building Ctr",
    "wof:placetype":"venue"
},
  "geometry": {"coordinates":[-79.7817764282,43.2432975769],"type":"Point"}
}