{
  "type": "Feature",
  "properties": {
    "addr:full":"3295 14th Ave Markham ON L3R 0H3",
    "addr:housenumber":"3295",
    "addr:postcode":"l3r 0h3",
    "addr:street":"14Th Ave",
    "iso:country":"CA",
    "sg:address":"3295 14th Ave",
    "sg:city":"Markham",
    "sg:classifiers":[
        {
            "category":"Autos & Motor Vehicles",
            "subcategory":"Auto Supplies",
            "type":"Retail Goods"
        }
    ],
    "sg:phone":"+1 905 479 1313",
    "sg:postcode":"L3R 0H3",
    "sg:province":"ON",
    "sg:tags":[
        "tire"
    ],
    "wof:name":"Consumers Tire Sales & Svc",
    "wof:placetype":"venue"
},
  "geometry": {"coordinates":[-79.3433685303,43.8338470459],"type":"Point"}
}