{
  "type": "Feature",
  "properties": {
    "addr:full":"Toronto ON M5S 1T9",
    "addr:postcode":"m5s 1t9",
    "iso:country":"CA",
    "sg:city":"Toronto",
    "sg:classifiers":[
        {
            "category":"Professional",
            "subcategory":"Research",
            "type":"Services"
        }
    ],
    "sg:phone":"+1 416 944 2627",
    "sg:postcode":"M5S 1T9",
    "sg:province":"ON",
    "sg:tags":[
        "foundation",
        "philanthropic"
    ],
    "wof:name":"Maytree Foundation",
    "wof:placetype":"venue"
},
  "geometry": {"coordinates":[-79.39469909669999,43.6687278748],"type":"Point"}
}