{
  "type": "Feature",
  "properties": {
    "addr:full":"Gatineau QC J8V 1T7",
    "addr:postcode":"j8v 1t7",
    "iso:country":"CA",
    "sg:city":"Gatineau",
    "sg:classifiers":[
        {
            "category":"Health Services",
            "subcategory":"Doctor",
            "type":"Services"
        }
    ],
    "sg:phone":"+1 819 568 1209",
    "sg:postcode":"J8V 1T7",
    "sg:province":"QC",
    "sg:tags":[
        "physiotherapist",
        "clinic"
    ],
    "wof:name":"Physio-Action",
    "wof:placetype":"venue"
},
  "geometry": {"coordinates":[-75.71050262449999,45.4278488159],"type":"Point"}
}