{
  "type": "Feature",
  "properties": {
    "addr:full":"Calgary AB T3E 6V2",
    "addr:postcode":"t3e 6v2",
    "iso:country":"CA",
    "sg:city":"Calgary",
    "sg:classifiers":[
        {
            "category":"Bars & Pubs",
            "type":"Food & Drink"
        }
    ],
    "sg:phone":"+1 403 686 1404",
    "sg:postcode":"T3E 6V2",
    "sg:province":"AB",
    "wof:name":"Buffalo Bob's",
    "wof:placetype":"venue"
},
  "geometry": {"coordinates":[-114.16132399999999,51.021431],"type":"Point"}
}