{
  "type": "Feature",
  "properties": {
    "addr:full":"9707 100 St Morinville AB T8R 1R3",
    "addr:housenumber":"9707",
    "addr:postcode":"t8r 1r3",
    "addr:street":"100 St",
    "iso:country":"CA",
    "sg:address":"9707 100 St",
    "sg:city":"Morinville",
    "sg:classifiers":[
        {
            "category":"Health Services",
            "subcategory":"Chiropractor",
            "type":"Services"
        }
    ],
    "sg:phone":"+1 780 939 3399",
    "sg:postcode":"T8R 1R3",
    "sg:province":"AB",
    "wof:name":"Morinville Chiropractic Clinic",
    "wof:placetype":"venue"
},
  "geometry": {"coordinates":[-113.644790649,53.7982788086],"type":"Point"}
}