{
  "type": "Feature",
  "properties": {
    "addr:full":"Surrey BC V3R 1M7",
    "addr:postcode":"v3r 1m7",
    "iso:country":"CA",
    "sg:city":"Surrey",
    "sg:classifiers":[
        {
            "category":"Cinema",
            "subcategory":"Movie Rental",
            "type":"Entertainment"
        }
    ],
    "sg:phone":"+1 604 583 7588",
    "sg:postcode":"V3R 1M7",
    "sg:province":"BC",
    "sg:tags":[
        "leasing",
        "video",
        "disc",
        "tape"
    ],
    "wof:name":"Ocean Video",
    "wof:placetype":"venue"
},
  "geometry": {"coordinates":[-122.808860779,49.1913642883],"type":"Point"}
}