{
  "type": "Feature",
  "properties": {
    "addr:full":"Trail BC V1R 1T1",
    "addr:postcode":"bc v1r 1t1",
    "addr:street":"Trail",
    "iso:country":"CA",
    "sg:city":"Trail",
    "sg:classifiers":[
        {
            "category":"Personal",
            "subcategory":"Beauty Salon",
            "type":"Services"
        }
    ],
    "sg:phone":"+1 250 368 4665",
    "sg:postcode":"V1R 1T1",
    "sg:province":"BC",
    "sg:tags":[
        "manicuring"
    ],
    "wof:name":"Penny's From Heaven Day Spa",
    "wof:placetype":"venue"
},
  "geometry": {"coordinates":[-117.697304,49.097694],"type":"Point"}
}