{
  "type": "Feature",
  "properties": {
    "addr:full":"315 Traders Blvd E Mississauga ON L4Z 3E4",
    "addr:housenumber":"315",
    "addr:postcode":"l4z 3e4",
    "addr:street":"Traders Blvd E",
    "iso:country":"CA",
    "sg:address":"315 Traders Blvd E",
    "sg:city":"Mississauga",
    "sg:classifiers":[
        {
            "category":"Wholesale",
            "subcategory":"Durable Goods & Equipment",
            "type":"Manufacturing & Wholesale Goods"
        }
    ],
    "sg:phone":"+1 905 568 2023",
    "sg:postcode":"L4Z 3E4",
    "sg:province":"ON",
    "sg:tags":[
        "representative",
        "manufacturer"
    ],
    "wof:name":"Roney Marketing Inc",
    "wof:placetype":"venue"
},
  "geometry": {"coordinates":[-79.6675796509,43.6286354065],"type":"Point"}
}