{
  "type": "Feature",
  "properties": {
    "iso:country":"CA",
    "sg:city":"Calgary",
    "sg:classifiers":[
        {
            "category":"Building & Trades",
            "subcategory":"Equipment Rental",
            "type":"Services"
        }
    ],
    "sg:phone":"+1 403 250 8225",
    "sg:postcode":"T1Y 5S5",
    "sg:province":"AB",
    "sg:tags":[
        "player",
        "recorder",
        "video"
    ],
    "wof:name":"Source Adult Video",
    "wof:placetype":"venue"
},
  "geometry": {"coordinates":[-113.99597930900001,51.0816879272],"type":"Point"}
}