{
  "type": "Feature",
  "properties": {
    "addr:full":"5308 Highway 7 Woodbridge ON L4L 1T3",
    "addr:housenumber":"5308",
    "addr:postcode":"l4l 1t3",
    "addr:street":"Highway 7",
    "iso:country":"CA",
    "sg:address":"5308 Highway 7",
    "sg:city":"Woodbridge",
    "sg:classifiers":[
        {
            "category":"Home & Garden",
            "subcategory":"Household Appliances",
            "type":"Retail Goods"
        }
    ],
    "sg:phone":"+1 905 851 2600",
    "sg:postcode":"L4L 1T3",
    "sg:province":"ON",
    "sg:tags":[
        "cleaners",
        "vacuum"
    ],
    "wof:name":"AAA Vacuum Ctr",
    "wof:placetype":"venue"
},
  "geometry": {"coordinates":[-79.5921554565,43.7850646973],"type":"Point"}
}