{
  "type": "Feature",
  "properties": {
    "iso:country":"CA",
    "sg:address":"272 Highbury Ave N",
    "sg:city":"London",
    "sg:classifiers":[
        {
            "category":"Organizations",
            "subcategory":"Religious Organization",
            "type":"Services"
        }
    ],
    "sg:phone":"+1 519 269 3221",
    "sg:postcode":"N5Z 2W9",
    "sg:province":"ON",
    "sg:tags":[
        "church"
    ],
    "wof:name":"Hope Congregational Fellowship",
    "wof:placetype":"venue"
},
  "geometry": {"coordinates":[-81.197441,42.983662],"type":"Point"}
}