{
  "type": "Feature",
  "properties": {
    "addr:full":"5990 Fraser St Vancouver BC V5W 2Z7",
    "addr:housenumber":"5990",
    "addr:postcode":"v5w 2z7",
    "addr:street":"Fraser St",
    "iso:country":"CA",
    "sg:address":"5990 Fraser St",
    "sg:city":"Vancouver",
    "sg:classifiers":[
        {
            "category":"Health Services",
            "subcategory":"Health Practitioner",
            "type":"Services"
        }
    ],
    "sg:phone":"+1 604 321 8343",
    "sg:postcode":"V5W 2Z7",
    "sg:province":"BC",
    "sg:tags":[
        "physiotherapist"
    ],
    "wof:name":"South Van Massage & Physio",
    "wof:placetype":"venue"
},
  "geometry": {"coordinates":[-123.090363,49.230339],"type":"Point"}
}