{
  "type": "Feature",
  "properties": {
    "addr:full":"235 Patteson Ave Chatham ON N7M 5M8",
    "addr:housenumber":"235",
    "addr:postcode":"n7m 5m8",
    "addr:street":"Patteson Ave",
    "iso:country":"CA",
    "sg:address":"235 Patteson Ave",
    "sg:city":"Chatham",
    "sg:classifiers":[
        {
            "category":"Freight",
            "type":"Transportation"
        }
    ],
    "sg:phone":"+1 519 352 7300",
    "sg:postcode":"N7M 5M8",
    "sg:province":"ON",
    "sg:tags":[
        "warehouse",
        "commercial"
    ],
    "wof:name":"Chatham Commercial Warehousing",
    "wof:placetype":"venue"
},
  "geometry": {"coordinates":[-82.18831634519999,42.393913269],"type":"Point"}
}