{
  "type": "Feature",
  "properties": {
    "iso:country":"CA",
    "sg:address":"619 Sackville Dr",
    "sg:city":"Lower Sackville",
    "sg:classifiers":[
        {
            "category":"Personal",
            "subcategory":"Beauty Salon",
            "type":"Services"
        }
    ],
    "sg:phone":"+1 902 865 7775",
    "sg:postcode":"B4C 2S4",
    "sg:province":"NS",
    "wof:name":"3's CO Hair Design Ltd",
    "wof:placetype":"venue"
},
  "geometry": {"coordinates":[-63.6869773865,44.7689323425],"type":"Point"}
}