{
  "type": "Feature",
  "properties": {
    "addr:full":"390 King St W Virden MB R0M 2C0",
    "addr:housenumber":"390",
    "addr:postcode":"r0m 2c0",
    "addr:street":"King St W Virden",
    "iso:country":"CA",
    "sg:address":"390 King St W",
    "sg:city":"Virden",
    "sg:classifiers":[
        {
            "category":"Museum",
            "type":"Entertainment"
        }
    ],
    "sg:phone":"+1 204 748 1659",
    "sg:postcode":"R0M 2C0",
    "sg:province":"MB",
    "wof:name":"Virden Pioneer Home Museum Inc",
    "wof:placetype":"venue"
},
  "geometry": {"coordinates":[-100.939964,49.849709],"type":"Point"}
}