{
  "type": "Feature",
  "properties": {
    "addr:full":"2268 Wyandotte St W Windsor ON N9B 1K2",
    "addr:housenumber":"2268",
    "addr:postcode":"n9b 1k2",
    "addr:street":"Wyandotte St W",
    "iso:country":"CA",
    "sg:address":"2268 Wyandotte St W",
    "sg:city":"Windsor",
    "sg:classifiers":[
        {
            "category":"Food & Beverages",
            "subcategory":"Groceries & Convenience Stores",
            "type":"Retail Goods"
        }
    ],
    "sg:phone":"+1 519 254 1949",
    "sg:postcode":"N9B 1K2",
    "sg:province":"ON",
    "sg:tags":[
        "grocer"
    ],
    "wof:name":"Giglio's Market",
    "wof:placetype":"venue"
},
  "geometry": {"coordinates":[-83.061882019,42.3055801392],"type":"Point"}
}