{
  "type": "Feature",
  "properties": {
    "addr:full":"Bassano AB T0J 0B0",
    "addr:postcode":"t0j 0b0",
    "iso:country":"CA",
    "sg:city":"Bassano",
    "sg:classifiers":[
        {
            "category":"Freight",
            "type":"Transportation"
        }
    ],
    "sg:phone":"+1 403 641 3844",
    "sg:postcode":"T0J 0B0",
    "sg:province":"AB",
    "sg:tags":[
        "trucking"
    ],
    "wof:name":"Bernard Moss Truck Svc Ltd",
    "wof:placetype":"venue"
},
  "geometry": {"coordinates":[-112.45423889200001,50.7870903015],"type":"Point"}
}