{
  "type": "Feature",
  "properties": {
    "addr:full":"531 Manitou Rd SE Calgary AB T2G 4C2",
    "addr:housenumber":"531",
    "addr:postcode":"t2g 4c2",
    "addr:street":"Manitou Rd Se",
    "iso:country":"CA",
    "sg:address":"531 Manitou Rd SE",
    "sg:city":"Calgary",
    "sg:classifiers":[
        {
            "category":"Shopping",
            "subcategory":"Hobbies, Toys, & Games",
            "type":"Retail Goods"
        }
    ],
    "sg:phone":"+1 403 287 7448",
    "sg:postcode":"T2G 4C2",
    "sg:province":"AB",
    "sg:tags":[
        "craft",
        "supply"
    ],
    "wof:name":"Cactus Arts & Crafts Wholesale",
    "wof:placetype":"venue"
},
  "geometry": {"coordinates":[-114.053749,51.010544],"type":"Point"}
}