{
  "type": "Feature",
  "properties": {
    "addr:full":"5929 Yonge St North York ON M2M 3V7",
    "addr:housenumber":"5929",
    "addr:postcode":"m2m 3v7",
    "addr:street":"Yonge St",
    "iso:country":"CA",
    "sg:address":"5929 Yonge St",
    "sg:city":"North York",
    "sg:classifiers":[
        {
            "category":"Shopping",
            "subcategory":"Discount & Variety Stores",
            "type":"Retail Goods"
        }
    ],
    "sg:phone":"+1 416 223 2339",
    "sg:postcode":"M2M 3V7",
    "sg:province":"ON",
    "wof:name":"North York Books & Gifts",
    "wof:placetype":"venue"
},
  "geometry": {"coordinates":[-79.417198,43.787296],"type":"Point"}
}