{
  "type": "Feature",
  "properties": {
    "addr:full":"42 Brookmount Rd Toronto ON M4L 3N2",
    "addr:housenumber":"42",
    "addr:postcode":"m4l 3n2",
    "addr:street":"Brookmount Rd",
    "iso:country":"CA",
    "sg:address":"42 Brookmount Rd",
    "sg:city":"Toronto",
    "sg:classifiers":[
        {
            "category":"Health Services",
            "subcategory":"Health Practitioner",
            "type":"Services"
        }
    ],
    "sg:phone":"+1 416 690 3722",
    "sg:postcode":"M4L 3N2",
    "sg:province":"ON",
    "sg:tags":[
        "psychotherapist"
    ],
    "wof:name":"Institute For the Advancement",
    "wof:placetype":"venue"
},
  "geometry": {"coordinates":[-79.30901299999999,43.67012],"type":"Point"}
}