{
  "type": "Feature",
  "properties": {
    "addr:full":"7965 Rue Saint-Denis Montreal QC H2R 2G2",
    "addr:housenumber":"7965",
    "addr:postcode":"h2r 2g2",
    "addr:street":"Rue Saint-Denis",
    "iso:country":"CA",
    "sg:address":"7965 Rue Saint-Denis",
    "sg:city":"Montreal",
    "sg:classifiers":[
        {
            "category":"Health Services",
            "subcategory":"Chiropractor",
            "type":"Services"
        }
    ],
    "sg:phone":"+1 514 387 4189",
    "sg:postcode":"H2R 2G2",
    "sg:province":"QC",
    "wof:name":"Abc Chiropratique",
    "wof:placetype":"venue"
},
  "geometry": {"coordinates":[-73.6271438599,45.5421524048],"type":"Point"}
}