{
  "type": "Feature",
  "properties": {
    "addr:full":"550 Rue Saint-Charles-Borromee Joliette QC J6E 4S6",
    "addr:housenumber":"550",
    "addr:postcode":"j6e 4s6",
    "addr:street":"Rue Saint-Charles-Borromee",
    "iso:country":"CA",
    "sg:address":"550 Rue Saint-Charles-Borromee",
    "sg:city":"Joliette",
    "sg:classifiers":[
        {
            "category":"Home & Garden",
            "subcategory":"Building Materials",
            "type":"Retail Goods"
        }
    ],
    "sg:phone":"+1 450 753 7451",
    "sg:postcode":"J6E 4S6",
    "sg:province":"QC",
    "sg:tags":[
        "glass",
        "window",
        "plate"
    ],
    "wof:name":"Lebeau Vitres D'Autos",
    "wof:placetype":"venue"
},
  "geometry": {"coordinates":[-73.44212341310001,46.0367088318],"type":"Point"}
}