{
  "type": "Feature",
  "properties": {
    "addr:full":"203 Harbison Ave W Winnipeg MB R2L 0A3",
    "addr:housenumber":"203",
    "addr:postcode":"r2l 0a3",
    "addr:street":"Harbison Ave W",
    "iso:country":"CA",
    "sg:address":"203 Harbison Ave W",
    "sg:city":"Winnipeg",
    "sg:classifiers":[
        {
            "category":"Bus Charters",
            "type":"Transportation"
        }
    ],
    "sg:phone":"+1 204 663 9811",
    "sg:postcode":"R2L 0A3",
    "sg:province":"MB",
    "sg:tags":[
        "rental"
    ],
    "wof:name":"Crocus Transport",
    "wof:placetype":"venue"
},
  "geometry": {"coordinates":[-97.11039700000001,49.91629],"type":"Point"}
}