{
  "type": "Feature",
  "properties": {
    "iso:country":"CA",
    "sg:address":"200 Rue Macdonald # 401",
    "sg:city":"Saint-Jean-Sur-Richelieu",
    "sg:classifiers":[
        {
            "category":"Real Estate",
            "subcategory":"Surveying",
            "type":"Services"
        }
    ],
    "sg:phone":"+1 450 359 1660",
    "sg:postcode":"J3B 8J6",
    "sg:province":"QC",
    "sg:tags":[
        "surveyor"
    ],
    "wof:name":"Tremblay, Berard",
    "wof:placetype":"venue"
},
  "geometry": {"coordinates":[-73.263557,45.32515],"type":"Point"}
}