{
  "type": "Feature",
  "properties": {
    "addr:full":"200 Rue Macdonald # 401 Saint-Jean-Sur-Richelieu QC J3B 8J6",
    "addr:housenumber":"200",
    "addr:postcode":"j3b 8j6",
    "addr:street":"Rue Macdonald # 401",
    "iso:country":"CA",
    "sg:address":"200 Rue Macdonald # 401",
    "sg:city":"Saint-Jean-Sur-Richelieu",
    "sg:classifiers":[
        {
            "category":"Real Estate",
            "subcategory":"Surveying",
            "type":"Services"
        }
    ],
    "sg:phone":"+1 450 359 1660",
    "sg:postcode":"J3B 8J6",
    "sg:province":"QC",
    "sg:tags":[
        "surveyor"
    ],
    "wof:name":"Tremblay, Berard",
    "wof:placetype":"venue"
},
  "geometry": {"coordinates":[-73.26355700000001,45.32515],"type":"Point"}
}