{
  "type": "Feature",
  "properties": {
    "addr:full":"Vancouver BC V6J 1X6",
    "addr:postcode":"v6j 1x6",
    "iso:country":"CA",
    "sg:city":"Vancouver",
    "sg:classifiers":[
        {
            "category":"Shopping",
            "subcategory":"Florist",
            "type":"Retail Goods"
        }
    ],
    "sg:phone":"+1 604 734 1557",
    "sg:postcode":"V6J 1X6",
    "sg:province":"BC",
    "wof:name":"Thai Orchard Flowers",
    "wof:placetype":"venue"
},
  "geometry": {"coordinates":[-123.142616,49.26355],"type":"Point"}
}