{
  "type": "Feature",
  "properties": {
    "addr:full":"Calgary AB T2H 0W3",
    "addr:postcode":"t2h 0w3",
    "iso:country":"CA",
    "sg:city":"Calgary",
    "sg:classifiers":[
        {
            "category":"Professional",
            "subcategory":"Research",
            "type":"Services"
        }
    ],
    "sg:phone":"+1 403 261 5000",
    "sg:postcode":"T2H 0W3",
    "sg:province":"AB",
    "sg:tags":[
        "market",
        "analysis"
    ],
    "wof:name":"Service Intelligence",
    "wof:placetype":"venue"
},
  "geometry": {"coordinates":[-114.068283081,50.9927902222],"type":"Point"}
}