{
  "type": "Feature",
  "properties": {
    "iso:country":"CA",
    "sg:city":"Alder Flats",
    "sg:classifiers":[
        {
            "category":"Mining & Drilling",
            "type":"Manufacturing & Wholesale Goods"
        }
    ],
    "sg:phone":"+1 780 388 3886",
    "sg:postcode":"T0C 0A0",
    "sg:province":"AB",
    "sg:tags":[
        "field",
        "oil",
        "transportation"
    ],
    "wof:name":"Hayduk Trucking",
    "wof:placetype":"venue"
},
  "geometry": {"coordinates":[-114.96631600000001,52.93137],"type":"Point"}
}