{
  "type": "Feature",
  "properties": {
    "addr:full":"3675 Rue Saint-Joseph Trois-Rivieres QC G8Z 4J4",
    "addr:housenumber":"3675",
    "addr:postcode":"g8z 4j4",
    "addr:street":"Rue Saint-Joseph Trois-Rivieres",
    "iso:country":"CA",
    "sg:address":"3675 Rue Saint-Joseph",
    "sg:city":"Trois-Rivieres",
    "sg:classifiers":[
        {
            "category":"Professional",
            "subcategory":"Engineering",
            "type":"Services"
        }
    ],
    "sg:phone":"+1 819 693 2903",
    "sg:postcode":"G8Z 4J4",
    "sg:province":"QC",
    "sg:tags":[
        "engineer"
    ],
    "wof:name":"Synergetik Inc",
    "wof:placetype":"venue"
},
  "geometry": {"coordinates":[-72.5709762573,46.3389587402],"type":"Point"}
}