{
  "type": "Feature",
  "properties": {
    "iso:country":"CA",
    "sg:address":"1790 Dundas St",
    "sg:city":"London",
    "sg:classifiers":[
        {
            "category":"Retail",
            "subcategory":"Auto Repair",
            "type":"Services"
        }
    ],
    "sg:phone":"+1 519 453 8064",
    "sg:postcode":"N5W 3E5",
    "sg:province":"ON",
    "sg:tags":[
        "repairing",
        "automobile"
    ],
    "wof:name":"Donny Martin Automotive Inc",
    "wof:placetype":"venue"
},
  "geometry": {"coordinates":[-81.182205,43.003117],"type":"Point"}
}