{
  "type": "Feature",
  "properties": {
    "iso:country":"CA",
    "sg:address":"150 Wyndham St N",
    "sg:city":"Guelph",
    "sg:classifiers":[
        {
            "category":"Social Services",
            "type":"Services"
        }
    ],
    "sg:phone":"+1 519 822 2887",
    "sg:postcode":"N1H 4E8",
    "sg:province":"ON",
    "sg:tags":[
        "organization",
        "welfare"
    ],
    "wof:name":"Fresh Start Housing Ctr",
    "wof:placetype":"venue"
},
  "geometry": {"coordinates":[-80.2504043579,43.5470237732],"type":"Point"}
}