{
  "type": "Feature",
  "properties": {
    "iso:country":"CA",
    "sg:city":"Ottawa",
    "sg:classifiers":[
        {
            "category":"Organizations",
            "subcategory":"Professional Association",
            "type":"Services"
        }
    ],
    "sg:phone":"+1 613 241 3500",
    "sg:postcode":"K1N 5Z4",
    "sg:province":"ON",
    "wof:name":"Federation Nationale Des Femme",
    "wof:placetype":"venue"
},
  "geometry": {"coordinates":[-75.6807098389,45.4307441711],"type":"Point"}
}