{
  "type": "Feature",
  "properties": {
    "addr:full":"Grand Bend ON N0M 1T0",
    "addr:postcode":"n0m 1t0",
    "iso:country":"CA",
    "sg:city":"Grand Bend",
    "sg:classifiers":[
        {
            "category":"Food & Beverages",
            "subcategory":"Liquor & Beverages",
            "type":"Retail Goods"
        }
    ],
    "sg:phone":"+1 519 238 2356",
    "sg:postcode":"N0M 1T0",
    "sg:province":"ON",
    "sg:tags":[
        "beer",
        "ale"
    ],
    "wof:name":"Beer Store",
    "wof:placetype":"venue"
},
  "geometry": {"coordinates":[-81.760178,43.308067],"type":"Point"}
}