{
  "type": "Feature",
  "properties": {
    "addr:full":"55 Rue Saint-Paul O Montreal QC H2Y 1Z1",
    "addr:housenumber":"55",
    "addr:postcode":"h2y 1z1",
    "addr:street":"Rue Saint-Paul O",
    "iso:country":"CA",
    "sg:address":"55 Rue Saint-Paul O",
    "sg:city":"Montreal",
    "sg:classifiers":[
        {
            "category":"Ferry",
            "type":"Transportation"
        }
    ],
    "sg:phone":"+1 514 849 9952",
    "sg:postcode":"H2Y 1Z1",
    "sg:province":"QC",
    "sg:tags":[
        "boat"
    ],
    "wof:name":"Bateau-Mouche Au Vieux",
    "wof:placetype":"venue"
},
  "geometry": {"coordinates":[-73.553375,45.50639],"type":"Point"}
}