{
  "type": "Feature",
  "properties": {
    "addr:full":"179 Rue Saint-Jean-Baptiste L'Isle-Verte QC G0L 1K0",
    "addr:housenumber":"179",
    "addr:postcode":"g0l 1k0",
    "addr:street":"Rue Saint-Jean-Baptiste",
    "iso:country":"CA",
    "sg:address":"179 Rue Saint-Jean-Baptiste",
    "sg:city":"L'Isle-Verte",
    "sg:classifiers":[
        {
            "category":"Home & Garden",
            "subcategory":"Household Appliances",
            "type":"Retail Goods"
        }
    ],
    "sg:phone":"+1 418 898 2642",
    "sg:postcode":"G0L 1K0",
    "sg:province":"QC",
    "wof:name":"Service Daniel Levesque Enr",
    "wof:placetype":"venue"
},
  "geometry": {"coordinates":[-69.337914,48.0131],"type":"Point"}
}