{
  "type": "Feature",
  "properties": {
    "addr:full":"Hwy 17 E Spragge ON P0R 1K0",
    "addr:postcode":"p0r 1k0",
    "addr:street":"Hwy 17 E Spragge",
    "iso:country":"CA",
    "sg:address":"Hwy 17 E",
    "sg:city":"Spragge",
    "sg:classifiers":[
        {
            "category":"Personal",
            "subcategory":"Shoe Repair & Shine",
            "type":"Services"
        }
    ],
    "sg:phone":"+1 705 849 2287",
    "sg:postcode":"P0R 1K0",
    "sg:province":"ON",
    "sg:tags":[
        "repairing",
        "boot"
    ],
    "wof:name":"Rob's Leather & Canvas Ctr",
    "wof:placetype":"venue"
},
  "geometry": {"coordinates":[-82.65589900000001,46.208714],"type":"Point"}
}