{
  "type": "Feature",
  "properties": {
    "addr:full":"181 Church St Oakville ON L6J 1N3",
    "addr:housenumber":"181",
    "addr:postcode":"l6j 1n3",
    "addr:street":"Church St",
    "iso:country":"CA",
    "sg:address":"181 Church St",
    "sg:city":"Oakville",
    "sg:classifiers":[
        {
            "category":"Personal",
            "subcategory":"Beauty Salon",
            "type":"Services"
        }
    ],
    "sg:phone":"+1 905 842 1095",
    "sg:postcode":"L6J 1N3",
    "sg:province":"ON",
    "wof:name":"Studio 238",
    "wof:placetype":"venue"
},
  "geometry": {"coordinates":[-79.669685,43.445896],"type":"Point"}
}