{
  "type": "Feature",
  "properties": {
    "addr:full":"509 1st St S Waldheim SK S0K 4R0",
    "addr:housenumber":"509",
    "addr:postcode":"s0k 4r0",
    "addr:street":"1St St S",
    "iso:country":"CA",
    "sg:address":"509 1st St S",
    "sg:city":"Waldheim",
    "sg:classifiers":[
        {
            "category":"Organizations",
            "subcategory":"Religious Organization",
            "type":"Services"
        }
    ],
    "sg:phone":"+1 306 945 2040",
    "sg:postcode":"S0K 4R0",
    "sg:province":"SK",
    "sg:tags":[
        "church"
    ],
    "wof:name":"Salem Church",
    "wof:placetype":"venue"
},
  "geometry": {"coordinates":[-106.647575,52.613106],"type":"Point"}
}