{
  "type": "Feature",
  "properties": {
    "iso:country":"CA",
    "sg:address":"1601 Telesat Crt",
    "sg:city":"Gloucester",
    "sg:classifiers":[
        {
            "category":"Professional",
            "subcategory":"Management & Consulting",
            "type":"Services"
        }
    ],
    "sg:phone":"+1 613 748 0123",
    "sg:postcode":"K1B 5P4",
    "sg:province":"ON",
    "sg:tags":[
        "consultant",
        "telecommunication"
    ],
    "wof:name":"Telesat Canada",
    "wof:placetype":"venue"
},
  "geometry": {"coordinates":[-75.604553,45.427982],"type":"Point"}
}