{
  "type": "Feature",
  "properties": {
    "iso:country":"CA",
    "sg:address":"919 Baker St",
    "sg:city":"Cranbrook",
    "sg:classifiers":[
        {
            "category":"Banks & Credit Unions",
            "subcategory":"Bank",
            "type":"Services"
        }
    ],
    "sg:phone":"+1 250 489 4501",
    "sg:postcode":"V1C 1A4",
    "sg:province":"BC",
    "wof:name":"Cibc",
    "wof:placetype":"venue"
},
  "geometry": {"coordinates":[-115.76821899399999,49.5119972229],"type":"Point"}
}