{
  "type": "Feature",
  "properties": {
    "iso:country":"CA",
    "sg:city":"Pickering",
    "sg:classifiers":[
        {
            "category":"Wholesale",
            "subcategory":"Electrical",
            "type":"Manufacturing & Wholesale Goods"
        }
    ],
    "sg:phone":"+1 905 420 3878",
    "sg:postcode":"L1W 2Y6",
    "sg:province":"ON",
    "sg:tags":[
        "control",
        "security",
        "system"
    ],
    "wof:name":"Parr Security Products",
    "wof:placetype":"venue"
},
  "geometry": {"coordinates":[-79.067565918,43.8261489868],"type":"Point"}
}