{
  "type": "Feature",
  "properties": {
    "iso:country":"CA",
    "sg:city":"Saskatoon",
    "sg:classifiers":[
        {
            "category":"Insurance",
            "subcategory":"Insurance Agent",
            "type":"Services"
        }
    ],
    "sg:phone":"+1 306 934 1999",
    "sg:postcode":"S7K 7Y1",
    "sg:province":"SK",
    "wof:name":"Knibbs, Darryn",
    "wof:placetype":"venue"
},
  "geometry": {"coordinates":[-106.637542725,52.1728782654],"type":"Point"}
}