{
  "type": "Feature",
  "properties": {
    "addr:full":"Kelowna BC V1Y 9R3",
    "addr:postcode":"v1y 9r3",
    "iso:country":"CA",
    "sg:city":"Kelowna",
    "sg:classifiers":[
        {
            "category":"Government",
            "subcategory":"Office",
            "type":"Public Place"
        }
    ],
    "sg:phone":"+1 250 470 6978",
    "sg:postcode":"V1Y 9R3",
    "sg:province":"BC",
    "wof:name":"British Columbia Interior",
    "wof:placetype":"venue"
},
  "geometry": {"coordinates":[-119.496391296,49.8894042969],"type":"Point"}
}