{
  "type": "Feature",
  "properties": {
    "addr:full":"45 Keltic Dr Sydney NS B1S 1P4",
    "addr:housenumber":"45",
    "addr:postcode":"b1s 1p4",
    "addr:street":"Keltic Dr",
    "iso:country":"CA",
    "sg:address":"45 Keltic Dr",
    "sg:city":"Sydney",
    "sg:classifiers":[
        {
            "category":"Real Estate",
            "subcategory":"Real Estate Operator",
            "type":"Services"
        }
    ],
    "sg:phone":"+1 902 564 5777",
    "sg:postcode":"B1S 1P4",
    "sg:province":"NS",
    "sg:tags":[
        "mall",
        "shopping",
        "center"
    ],
    "wof:name":"Cape Breton Shopping Plaza Ltd",
    "wof:placetype":"venue"
},
  "geometry": {"coordinates":[-60.2237892151,46.1100654602],"type":"Point"}
}