{
  "type": "Feature",
  "properties": {
    "addr:full":"147 Vesuvius Bay Rd Salt Spring Island BC V8K 1K3",
    "addr:housenumber":"147",
    "addr:postcode":"v8k 1k3",
    "addr:street":"Vesuvius Bay Rd",
    "iso:country":"CA",
    "sg:address":"147 Vesuvius Bay Rd",
    "sg:city":"Salt Spring Island",
    "sg:classifiers":[
        {
            "category":"Organizations",
            "subcategory":"Religious Organization",
            "type":"Services"
        }
    ],
    "sg:phone":"+1 250 537 2622",
    "sg:postcode":"V8K 1K3",
    "sg:province":"BC",
    "sg:tags":[
        "church"
    ],
    "wof:name":"Community Gospel Chapel",
    "wof:placetype":"venue"
},
  "geometry": {"coordinates":[-123.53276099999999,48.873955],"type":"Point"}
}