{
  "type": "Feature",
  "properties": {
    "addr:full":"Toronto ON M5J 2P1",
    "addr:postcode":"m5j 2p1",
    "iso:country":"CA",
    "sg:city":"Toronto",
    "sg:classifiers":[
        {
            "category":"Insurance",
            "subcategory":"Insurance Agent",
            "type":"Services"
        }
    ],
    "sg:phone":"+1 416 366 8771",
    "sg:postcode":"M5J 2P1",
    "sg:province":"ON",
    "wof:name":"Clarica Life Insurance CO",
    "wof:placetype":"venue"
},
  "geometry": {"coordinates":[-79.383682251,43.6457481384],"type":"Point"}
}