{
  "type": "Feature",
  "properties": {
    "iso:country":"CA",
    "sg:address":"5225 55 St",
    "sg:city":"Cold Lake",
    "sg:classifiers":[
        {
            "category":"Health Services",
            "subcategory":"Doctor",
            "type":"Services"
        }
    ],
    "sg:phone":"+1 780 594 5056",
    "sg:postcode":"T9M 1P4",
    "sg:province":"AB",
    "sg:tags":[
        "dentist"
    ],
    "wof:name":"Tri-Town Dental Ctr",
    "wof:placetype":"venue"
},
  "geometry": {"coordinates":[-110.215103149,54.4161529541],"type":"Point"}
}