{
  "type": "Feature",
  "properties": {
    "iso:country":"CA",
    "sg:address":"2437 Rue King O",
    "sg:city":"Sherbrooke",
    "sg:classifiers":[
        {
            "category":"Bars & Pubs",
            "type":"Food & Drink"
        }
    ],
    "sg:phone":"+1 819 346 7279",
    "sg:postcode":"J1J 2G7",
    "sg:province":"QC",
    "sg:tags":[
        "lounge",
        "cocktail"
    ],
    "wof:name":"Pub Du Nord",
    "wof:placetype":"venue"
},
  "geometry": {"coordinates":[-71.9321136475,45.3985557556],"type":"Point"}
}