{
  "type": "Feature",
  "properties": {
    "iso:country":"CA",
    "sg:city":"Mission",
    "sg:classifiers":[
        {
            "category":"Organizations",
            "subcategory":"Professional Association",
            "type":"Services"
        }
    ],
    "sg:phone":"+1 604 826 0112",
    "sg:postcode":"V2V 1K3",
    "sg:province":"BC",
    "wof:name":"Mission Teachers' Union",
    "wof:placetype":"venue"
},
  "geometry": {"coordinates":[-122.30115508999999,49.1351242065],"type":"Point"}
}