{
  "type": "Feature",
  "properties": {
    "addr:full":"21 Avenue Rd Toronto ON M5R 2G1",
    "addr:housenumber":"21",
    "addr:postcode":"m5r 2g1",
    "addr:street":"Avenue Rd",
    "iso:country":"CA",
    "sg:address":"21 Avenue Rd",
    "sg:city":"Toronto",
    "sg:classifiers":[
        {
            "category":"Shopping",
            "subcategory":"Gifts & Souvenirs",
            "type":"Retail Goods"
        }
    ],
    "sg:phone":"+1 416 323 1699",
    "sg:postcode":"M5R 2G1",
    "sg:province":"ON",
    "sg:tags":[
        "shop"
    ],
    "wof:name":"Selection",
    "wof:placetype":"venue"
},
  "geometry": {"coordinates":[-79.39440917970001,43.6697158813],"type":"Point"}
}