{
  "type": "Feature",
  "properties": {
    "addr:full":"414 Mcarthur Ave Ottawa ON K1K 1G6",
    "addr:housenumber":"414",
    "addr:postcode":"k1k 1g6",
    "addr:street":"Mcarthur Ave",
    "iso:country":"CA",
    "sg:address":"414 Mcarthur Ave",
    "sg:city":"Ottawa",
    "sg:classifiers":[
        {
            "category":"Autos & Motor Vehicles",
            "subcategory":"Fuel & Gas Station",
            "type":"Retail Goods"
        }
    ],
    "sg:phone":"+1 613 747 7101",
    "sg:postcode":"K1K 1G6",
    "sg:province":"ON",
    "sg:tags":[
        "oil"
    ],
    "wof:name":"Econo Gas Bar",
    "wof:placetype":"venue"
},
  "geometry": {"coordinates":[-75.64791099999999,45.432053],"type":"Point"}
}