{
  "type": "Feature",
  "properties": {
    "addr:full":"Toronto ON M5H 1X6",
    "addr:postcode":"m5h 1x6",
    "iso:country":"CA",
    "sg:city":"Toronto",
    "sg:classifiers":[
        {
            "category":"Freight",
            "type":"Transportation"
        }
    ],
    "sg:phone":"+1 416 977 9683",
    "sg:postcode":"M5H 1X6",
    "sg:province":"ON",
    "sg:tags":[
        "delivery",
        "courier"
    ],
    "wof:name":"Kid Gloves Delivery Ltd",
    "wof:placetype":"venue"
},
  "geometry": {"coordinates":[-79.389954,43.64806],"type":"Point"}
}