{
  "type": "Feature",
  "properties": {
    "iso:country":"CA",
    "sg:address":"120 Chatham St",
    "sg:city":"Hamilton",
    "sg:classifiers":[
        {
            "category":"Building & Trades",
            "subcategory":"Construction",
            "type":"Services"
        }
    ],
    "sg:phone":"+1 905 574 2427",
    "sg:postcode":"L8P 2B5",
    "sg:province":"ON",
    "sg:tags":[
        "pavement",
        "material",
        "paving",
        "marking"
    ],
    "wof:name":"Petroleum Distributors",
    "wof:placetype":"venue"
},
  "geometry": {"coordinates":[-79.8911437988,43.2555541992],"type":"Point"}
}