{
  "type": "Feature",
  "properties": {
    "iso:country":"CA",
    "sg:address":"1333 Ch Sullivan",
    "sg:city":"Val-D'Or",
    "sg:classifiers":[
        {
            "category":"Autos & Motor Vehicles",
            "subcategory":"Auto Supplies",
            "type":"Retail Goods"
        }
    ],
    "sg:phone":"+1 819 825 6211",
    "sg:postcode":"J9P 6Z8",
    "sg:province":"QC",
    "sg:tags":[
        "automobile",
        "parts"
    ],
    "wof:name":"Uap Napa Pieces D'Auto",
    "wof:placetype":"venue"
},
  "geometry": {"coordinates":[-71.0033187866,45.3835067749],"type":"Point"}
}