{
  "type": "Feature",
  "properties": {
    "addr:full":"Abbotsford BC V2S 2B4",
    "addr:postcode":"v2s 2b4",
    "iso:country":"CA",
    "sg:city":"Abbotsford",
    "sg:classifiers":[
        {
            "category":"Manufacturing",
            "subcategory":"Motor Vehicles & Parts",
            "type":"Manufacturing & Wholesale Goods"
        }
    ],
    "sg:phone":"+1 604 850 1446",
    "sg:postcode":"V2S 2B4",
    "sg:province":"BC",
    "sg:tags":[
        "automobile",
        "supply"
    ],
    "wof:name":"Lordco Auto Parts Ltd",
    "wof:placetype":"venue"
},
  "geometry": {"coordinates":[-122.30101000000001,49.049854],"type":"Point"}
}