{
  "type": "Feature",
  "properties": {
    "addr:full":"80 Galaxy Blvd #4 Etobicoke ON M9W 4Y8",
    "addr:housenumber":"80",
    "addr:postcode":"m9w 4y8",
    "addr:street":"Galaxy Blvd # 4",
    "iso:country":"CA",
    "sg:address":"80 Galaxy Blvd #4",
    "sg:city":"Etobicoke",
    "sg:classifiers":[
        {
            "category":"Wholesale",
            "subcategory":"Drugs",
            "type":"Manufacturing & Wholesale Goods"
        }
    ],
    "sg:phone":"+1 416 675 3333",
    "sg:postcode":"M9W 4Y8",
    "sg:province":"ON",
    "sg:tags":[
        "pharmaceutical",
        "product"
    ],
    "wof:name":"Pharmax Limited",
    "wof:placetype":"venue"
},
  "geometry": {"coordinates":[-79.587219,43.680325],"type":"Point"}
}