{
  "type": "Feature",
  "properties": {
    "addr:full":"60C Highway 105 Red Lake ON P0V 2M0",
    "addr:housenumber":"60c",
    "addr:postcode":"p0v 2m0",
    "addr:street":"Highway 105;Lake",
    "iso:country":"CA",
    "sg:address":"60C Highway 105",
    "sg:city":"Red Lake",
    "sg:classifiers":[
        {
            "category":"Education",
            "subcategory":"School",
            "type":"Public Place"
        }
    ],
    "sg:phone":"+1 807 727 2092",
    "sg:postcode":"P0V 2M0",
    "sg:province":"ON",
    "wof:name":"Red Lake District High School",
    "wof:placetype":"venue"
},
  "geometry": {"coordinates":[-93.8221664429,51.0190124512],"type":"Point"}
}