{
  "type": "Feature",
  "properties": {
    "addr:full":"Mississauga ON L4W 1P5",
    "addr:postcode":"l4w 1p5",
    "iso:country":"CA",
    "sg:city":"Mississauga",
    "sg:classifiers":[
        {
            "category":"Personal",
            "subcategory":"Massage",
            "type":"Services"
        }
    ],
    "sg:phone":"+1 905 602 1422",
    "sg:postcode":"L4W 1P5",
    "sg:province":"ON",
    "wof:name":"Tomken Bohemian Club",
    "wof:placetype":"venue"
},
  "geometry": {"coordinates":[-79.639831543,43.6323471069],"type":"Point"}
}