{
  "type": "Feature",
  "properties": {
    "addr:full":"175 St Andrews Mitchell ON N0K 1N0",
    "addr:housenumber":"175",
    "addr:postcode":"n0k 1n0",
    "addr:street":"St",
    "iso:country":"CA",
    "sg:address":"175 St Andrews",
    "sg:city":"Mitchell",
    "sg:classifiers":[
        {
            "category":"Recreation",
            "type":"Entertainment"
        }
    ],
    "sg:phone":"+1 519 348 9064",
    "sg:postcode":"N0K 1N0",
    "sg:province":"ON",
    "sg:tags":[
        "hall",
        "auditorium"
    ],
    "wof:name":"Canadian Legion",
    "wof:placetype":"venue"
},
  "geometry": {"coordinates":[-81.193039,43.470619],"type":"Point"}
}