{
  "type": "Feature",
  "properties": {
    "addr:full":"10011 167 St NW Edmonton AB T5P 3W3",
    "addr:housenumber":"10011",
    "addr:postcode":"t5p 3w3",
    "addr:street":"167 St Nw",
    "iso:country":"CA",
    "sg:address":"10011 167 St NW",
    "sg:city":"Edmonton",
    "sg:classifiers":[
        {
            "category":"Building & Trades",
            "subcategory":"Construction",
            "type":"Services"
        }
    ],
    "sg:phone":"+1 780 489 1872",
    "sg:postcode":"T5P 3W3",
    "sg:province":"AB",
    "sg:tags":[
        "cabinet",
        "maker",
        "woodworker"
    ],
    "wof:name":"Pohling Woodworking Ltd",
    "wof:placetype":"venue"
},
  "geometry": {"coordinates":[-113.609093,53.539616],"type":"Point"}
}