{
  "type": "Feature",
  "properties": {
    "addr:full":"Saskatoon SK S7J 2G2",
    "addr:postcode":"s7j 2g2",
    "iso:country":"CA",
    "sg:city":"Saskatoon",
    "sg:classifiers":[
        {
            "category":"Shopping",
            "subcategory":"Catalog Store",
            "type":"Retail Goods"
        }
    ],
    "sg:phone":"+1 306 373 3537",
    "sg:postcode":"S7J 2G2",
    "sg:province":"SK",
    "sg:tags":[
        "mail",
        "order",
        "internet"
    ],
    "wof:name":"Sears Canada Inc",
    "wof:placetype":"venue"
},
  "geometry": {"coordinates":[-106.62247499999999,52.101315],"type":"Point"}
}