{
  "type": "Feature",
  "properties": {
    "addr:full":"399 Main St # 105 Penticton BC V2A 5B7",
    "addr:housenumber":"399",
    "addr:postcode":"v2a 5b7",
    "addr:street":"Main St # 105",
    "iso:country":"CA",
    "sg:address":"399 Main St # 105",
    "sg:city":"Penticton",
    "sg:classifiers":[
        {
            "category":"Banks & Credit Unions",
            "subcategory":"Investment Brokerage",
            "type":"Services"
        }
    ],
    "sg:phone":"+1 250 492 0212",
    "sg:postcode":"V2A 5B7",
    "sg:province":"BC",
    "wof:name":"Cibc Wood Gundy Inc",
    "wof:placetype":"venue"
},
  "geometry": {"coordinates":[-119.591919,49.497303],"type":"Point"}
}