{
  "type": "Feature",
  "properties": {
    "addr:full":"6 Southampton Pky Sauble Beach ON N0H 2G0",
    "addr:housenumber":"6",
    "addr:postcode":"n0h 2g0",
    "addr:street":"Southampton Pky",
    "iso:country":"CA",
    "sg:address":"6 Southampton Pky",
    "sg:city":"Sauble Beach",
    "sg:classifiers":[
        {
            "category":"Restaurant",
            "type":"Food & Drink"
        }
    ],
    "sg:phone":"+1 519 422 1624",
    "sg:postcode":"N0H 2G0",
    "sg:province":"ON",
    "wof:name":"Chalet Shoppe",
    "wof:placetype":"venue"
},
  "geometry": {"coordinates":[-81.2649230957,44.6291999817],"type":"Point"}
}