{
  "type": "Feature",
  "properties": {
    "addr:full":"Winnipeg MB R3J 0K8",
    "addr:postcode":"r3j 0k8",
    "iso:country":"CA",
    "sg:city":"Winnipeg",
    "sg:classifiers":[
        {
            "category":"Real Estate",
            "subcategory":"Architect",
            "type":"Services"
        }
    ],
    "sg:phone":"+1 204 885 9323",
    "sg:postcode":"R3J 0K8",
    "sg:province":"MB",
    "wof:name":"Peters, Jerald D",
    "wof:placetype":"venue"
},
  "geometry": {"coordinates":[-97.2299423218,49.877696991],"type":"Point"}
}