{
  "type": "Feature",
  "properties": {
    "iso:country":"CA",
    "sg:city":"Campbell River",
    "sg:classifiers":[
        {
            "category":"Real Estate",
            "subcategory":"Real Estate Operator",
            "type":"Services"
        }
    ],
    "sg:phone":"+1 250 286 6513",
    "sg:postcode":"V9W 2P5",
    "sg:province":"BC",
    "sg:tags":[
        "apartment"
    ],
    "wof:name":"Seaview Manor",
    "wof:placetype":"venue"
},
  "geometry": {"coordinates":[-125.242797852,50.0219917297],"type":"Point"}
}