{
  "type": "Feature",
  "properties": {
    "addr:full":"Coquitlam BC V3B 6S2",
    "addr:postcode":"v3b 6s2",
    "iso:country":"CA",
    "sg:city":"Coquitlam",
    "sg:classifiers":[
        {
            "category":"Home & Garden",
            "subcategory":"Furniture",
            "type":"Retail Goods"
        }
    ],
    "sg:phone":"+1 604 945 5975",
    "sg:postcode":"V3B 6S2",
    "sg:province":"BC",
    "wof:name":"Jysk Linen 'N Furniture Inc",
    "wof:placetype":"venue"
},
  "geometry": {"coordinates":[-122.792244,49.274433],"type":"Point"}
}