{
  "type": "Feature",
  "properties": {
    "addr:full":"2525 Speakman Dr Mississauga ON L5K 1B1",
    "addr:housenumber":"2525",
    "addr:postcode":"l5k 1b1",
    "addr:street":"Speakman Dr",
    "iso:country":"CA",
    "sg:address":"2525 Speakman Dr",
    "sg:city":"Mississauga",
    "sg:classifiers":[
        {
            "category":"Communications",
            "subcategory":"Film & Video Production",
            "type":"Services"
        }
    ],
    "sg:phone":"+1 905 403 6500",
    "sg:postcode":"L5K 1B1",
    "sg:province":"ON",
    "sg:tags":[
        "motion",
        "picture"
    ],
    "wof:name":"Imax Corp",
    "wof:placetype":"venue"
},
  "geometry": {"coordinates":[-79.6633682251,43.5154914856],"type":"Point"}
}