{
  "type": "Feature",
  "properties": {
    "addr:full":"215 Park Ave W Chatham ON N7M 1W3",
    "addr:housenumber":"215",
    "addr:postcode":"n7m 1w3",
    "addr:street":"Park Ave W",
    "iso:country":"CA",
    "sg:address":"215 Park Ave W",
    "sg:city":"Chatham",
    "sg:classifiers":[
        {
            "category":"Food & Beverages",
            "subcategory":"Groceries & Convenience Stores",
            "type":"Retail Goods"
        }
    ],
    "sg:phone":"+1 519 380 0550",
    "sg:postcode":"N7M 1W3",
    "sg:province":"ON",
    "sg:tags":[
        "grocer"
    ],
    "wof:name":"Sobeys",
    "wof:placetype":"venue"
},
  "geometry": {"coordinates":[-82.183303833,42.3926582336],"type":"Point"}
}