{
  "type": "Feature",
  "properties": {
    "addr:full":"390 Edgeley Blvd Concord ON L4K 3Z6",
    "addr:housenumber":"390",
    "addr:postcode":"l4k 3z6",
    "addr:street":"Edgeley Blvd",
    "iso:country":"CA",
    "sg:address":"390 Edgeley Blvd",
    "sg:city":"Concord",
    "sg:classifiers":[
        {
            "category":"Building & Trades",
            "subcategory":"Construction",
            "type":"Services"
        }
    ],
    "sg:phone":"+1 905 669 3519",
    "sg:postcode":"L4K 3Z6",
    "sg:province":"ON",
    "sg:tags":[
        "general",
        "contractor"
    ],
    "wof:name":"Palmark Construction Ltd",
    "wof:placetype":"venue"
},
  "geometry": {"coordinates":[-79.5352096558,43.8025894165],"type":"Point"}
}