{
  "type": "Feature",
  "properties": {
    "iso:country":"CA",
    "sg:address":"1319 Logan Ave",
    "sg:city":"Winnipeg",
    "sg:classifiers":[
        {
            "category":"Retail",
            "subcategory":"Repair Shop",
            "type":"Services"
        }
    ],
    "sg:phone":"+1 204 783 8579",
    "sg:postcode":"R3E 1R5",
    "sg:province":"MB",
    "sg:tags":[
        "lock",
        "locksmith"
    ],
    "wof:name":"Daly Locksmith CO",
    "wof:placetype":"venue"
},
  "geometry": {"coordinates":[-97.1787567139,49.9164619446],"type":"Point"}
}