{
  "type": "Feature",
  "properties": {
    "addr:full":"19 Main St Fisher Branch MB R0C 0Z0",
    "addr:housenumber":"19",
    "addr:postcode":"r0c 0z0",
    "addr:street":"Main St",
    "iso:country":"CA",
    "sg:address":"19 Main St",
    "sg:city":"Fisher Branch",
    "sg:classifiers":[
        {
            "category":"Retail",
            "subcategory":"Auto Repair",
            "type":"Services"
        }
    ],
    "sg:phone":"+1 204 372 8585",
    "sg:postcode":"R0C 0Z0",
    "sg:province":"MB",
    "sg:tags":[
        "repairing",
        "automobile"
    ],
    "wof:name":"Smith's Auto Tech",
    "wof:placetype":"venue"
},
  "geometry": {"coordinates":[-97.6184539795,51.0826034546],"type":"Point"}
}