{
  "type": "Feature",
  "properties": {
    "addr:full":"10616 82 Ave NW Edmonton AB T6E 2A7",
    "addr:housenumber":"10616",
    "addr:postcode":"t6e 2a7",
    "addr:street":"82 Ave Nw",
    "iso:country":"CA",
    "sg:address":"10616 82 Ave NW",
    "sg:city":"Edmonton",
    "sg:classifiers":[
        {
            "category":"Bars & Pubs",
            "type":"Food & Drink"
        }
    ],
    "sg:phone":"+1 780 414 6766",
    "sg:postcode":"T6E 2A7",
    "sg:province":"AB",
    "wof:name":"O'Byrne's Irish Pub",
    "wof:placetype":"venue"
},
  "geometry": {"coordinates":[-113.504143,53.518215],"type":"Point"}
}