{
  "type": "Feature",
  "properties": {
    "addr:full":"2136 Rue Tillemont Montreal QC H2E 1E3",
    "addr:housenumber":"2136",
    "addr:postcode":"h2e 1e3",
    "addr:street":"Rue Tillemont",
    "iso:country":"CA",
    "sg:address":"2136 Rue Tillemont",
    "sg:city":"Montreal",
    "sg:classifiers":[
        {
            "category":"Personal",
            "subcategory":"Beauty Salon",
            "type":"Services"
        }
    ],
    "sg:phone":"+1 514 729 9156",
    "sg:postcode":"H2E 1E3",
    "sg:province":"QC",
    "wof:name":"Studio D'Esthetique Luminanc",
    "wof:placetype":"venue"
},
  "geometry": {"coordinates":[-73.613716,45.554668],"type":"Point"}
}