{
  "type": "Feature",
  "properties": {
    "addr:full":"Etobicoke ON M9B 1B3",
    "addr:postcode":"m9b 1b3",
    "iso:country":"CA",
    "sg:city":"Etobicoke",
    "sg:classifiers":[
        {
            "category":"Cinema",
            "subcategory":"Movie Rental",
            "type":"Entertainment"
        }
    ],
    "sg:phone":"+1 416 234 1620",
    "sg:postcode":"M9B 1B3",
    "sg:province":"ON",
    "sg:tags":[
        "leasing",
        "video",
        "disc",
        "tape"
    ],
    "wof:name":"Adult Video World",
    "wof:placetype":"venue"
},
  "geometry": {"coordinates":[-79.54048156739999,43.6359024048],"type":"Point"}
}