{
  "type": "Feature",
  "properties": {
    "iso:country":"CA",
    "sg:address":"8 Turner Crt",
    "sg:city":"Sussex",
    "sg:classifiers":[
        {
            "category":"Autos & Motor Vehicles",
            "subcategory":"Auto Supplies",
            "type":"Retail Goods"
        }
    ],
    "sg:phone":"+1 506 433 6150",
    "sg:postcode":"E4E 2S1",
    "sg:province":"NB",
    "sg:tags":[
        "automobile",
        "parts"
    ],
    "wof:name":"Shur-Fit Automotive",
    "wof:placetype":"venue"
},
  "geometry": {"coordinates":[-65.5124740601,45.7236404419],"type":"Point"}
}