{
  "type": "Feature",
  "properties": {
    "addr:full":"Scarborough ON M1X 1E2",
    "addr:postcode":"m1x 1e2",
    "iso:country":"CA",
    "sg:city":"Scarborough",
    "sg:classifiers":[
        {
            "category":"Freight",
            "type":"Transportation"
        }
    ],
    "sg:phone":"+1 416 293 1234",
    "sg:postcode":"M1X 1E2",
    "sg:province":"ON",
    "sg:tags":[
        "mover"
    ],
    "wof:name":"Jim Clifford Moving Svc",
    "wof:placetype":"venue"
},
  "geometry": {"coordinates":[-79.23672500000001,43.817883],"type":"Point"}
}