{
  "type": "Feature",
  "properties": {
    "addr:full":"Souris PE C0A 2B0",
    "addr:postcode":"c0a 2b0",
    "iso:country":"CA",
    "sg:city":"Souris",
    "sg:classifiers":[
        {
            "category":"Travel",
            "subcategory":"Hotels & Motels",
            "type":"Entertainment"
        }
    ],
    "sg:phone":"+1 902 687 1725",
    "sg:postcode":"C0A 2B0",
    "sg:province":"PE",
    "sg:tags":[
        "cottage",
        "cabin"
    ],
    "wof:name":"Kee-Way-Din Cottage",
    "wof:placetype":"venue"
},
  "geometry": {"coordinates":[-62.253033,46.354488],"type":"Point"}
}