{
  "type": "Feature",
  "properties": {
    "addr:full":"415 4th Ave Stewart BC V0T 1W0",
    "addr:housenumber":"415",
    "addr:postcode":"v0t 1w0",
    "addr:street":"4Th Ave",
    "iso:country":"CA",
    "sg:address":"415 4th Ave",
    "sg:city":"Stewart",
    "sg:classifiers":[
        {
            "category":"Food & Beverages",
            "subcategory":"Liquor & Beverages",
            "type":"Retail Goods"
        }
    ],
    "sg:phone":"+1 250 636 2524",
    "sg:postcode":"V0T 1W0",
    "sg:province":"BC",
    "sg:tags":[
        "store"
    ],
    "wof:name":"Liquor Stores-Government",
    "wof:placetype":"venue"
},
  "geometry": {"coordinates":[-129.993972778,55.9352111816],"type":"Point"}
}