{
  "type": "Feature",
  "properties": {
    "addr:full":"Gatineau QC J8P 2V5",
    "addr:postcode":"j8p 2v5",
    "iso:country":"CA",
    "sg:city":"Gatineau",
    "sg:classifiers":[
        {
            "category":"Personal",
            "subcategory":"Beauty Salon",
            "type":"Services"
        }
    ],
    "sg:phone":"+1 819 643 3408",
    "sg:postcode":"J8P 2V5",
    "sg:province":"QC",
    "wof:name":"Coiffure D'Aujuourd'Hui",
    "wof:placetype":"venue"
},
  "geometry": {"coordinates":[-75.65631103520001,45.4919967651],"type":"Point"}
}