{
  "type": "Feature",
  "properties": {
    "addr:full":"630 1st Ave E Assiniboia SK S0H 0B0",
    "addr:housenumber":"630",
    "addr:postcode":"s0h 0b0",
    "addr:street":"1St Ave E Assiniboia",
    "iso:country":"CA",
    "sg:address":"630 1st Ave E",
    "sg:city":"Assiniboia",
    "sg:classifiers":[
        {
            "category":"Government",
            "subcategory":"Office",
            "type":"Public Place"
        }
    ],
    "sg:phone":"+1 306 642 7221",
    "sg:postcode":"S0H 0B0",
    "sg:province":"SK",
    "wof:name":"Saskatchewan Highway Mntnc",
    "wof:placetype":"venue"
},
  "geometry": {"coordinates":[-105.983772,49.632622],"type":"Point"}
}