{
  "type": "Feature",
  "properties": {
    "addr:full":"59 Camelot Dr Nepean ON K2G 5W6",
    "addr:housenumber":"59",
    "addr:postcode":"k2g 5w6",
    "addr:street":"Camelot Dr",
    "iso:country":"CA",
    "sg:address":"59 Camelot Dr",
    "sg:city":"Nepean",
    "sg:classifiers":[
        {
            "category":"Government",
            "subcategory":"Office",
            "type":"Public Place"
        }
    ],
    "sg:phone":"+1 613 225 2342",
    "sg:postcode":"K2G 5W6",
    "sg:province":"ON",
    "wof:name":"Canadian Food Inspection Agcy",
    "wof:placetype":"venue"
},
  "geometry": {"coordinates":[-75.72498299999999,45.330242],"type":"Point"}
}