{
  "type": "Feature",
  "properties": {
    "addr:full":"140 Muskoka Rd S Gravenhurst ON P1P 1X2",
    "addr:housenumber":"140",
    "addr:postcode":"p1p 1x2",
    "addr:street":"Muskoka Rd S",
    "iso:country":"CA",
    "sg:address":"140 Muskoka Rd S",
    "sg:city":"Gravenhurst",
    "sg:classifiers":[
        {
            "category":"Manufacturing",
            "subcategory":"Printing",
            "type":"Manufacturing & Wholesale Goods"
        }
    ],
    "sg:phone":"+1 705 687 6674",
    "sg:postcode":"P1P 1X2",
    "sg:province":"ON",
    "sg:tags":[
        "newspaper"
    ],
    "wof:name":"Weekender",
    "wof:placetype":"venue"
},
  "geometry": {"coordinates":[-79.373688,44.919483],"type":"Point"}
}