{
  "type": "Feature",
  "properties": {
    "iso:country":"CA",
    "sg:address":"40 Ch Bates # 224",
    "sg:city":"Outremont",
    "sg:classifiers":[
        {
            "category":"Health Services",
            "subcategory":"Health Practitioner",
            "type":"Services"
        }
    ],
    "sg:phone":"+1 514 272 3966",
    "sg:postcode":"H2V 4T5",
    "sg:province":"QC",
    "sg:tags":[
        "psychologist"
    ],
    "wof:name":"Poupard, Danielle PhD",
    "wof:placetype":"venue"
},
  "geometry": {"coordinates":[-73.624634,45.517979],"type":"Point"}
}