{
  "type": "Feature",
  "properties": {
    "addr:full":"185 Golf Course Rd Janetville ON L0B 1K0",
    "addr:housenumber":"185",
    "addr:postcode":"l0b 1k0",
    "addr:street":"Golf Course Rd",
    "iso:country":"CA",
    "sg:address":"185 Golf Course Rd",
    "sg:city":"Janetville",
    "sg:classifiers":[
        {
            "category":"Building & Trades",
            "subcategory":"Construction",
            "type":"Services"
        }
    ],
    "sg:phone":"+1 705 324 9544",
    "sg:postcode":"L0B 1K0",
    "sg:province":"ON",
    "sg:tags":[
        "excavating",
        "contractor"
    ],
    "wof:name":"R D Sutcliffe Contracting Inc",
    "wof:placetype":"venue"
},
  "geometry": {"coordinates":[-78.746323,44.22245],"type":"Point"}
}