{
  "type": "Feature",
  "properties": {
    "addr:full":"Brampton ON L6T 5R5",
    "addr:postcode":"l6t 5r5",
    "iso:country":"CA",
    "sg:city":"Brampton",
    "sg:classifiers":[
        {
            "category":"Wholesale",
            "subcategory":"Home Furnishings",
            "type":"Manufacturing & Wholesale Goods"
        }
    ],
    "sg:phone":"+1 905 458 1772",
    "sg:postcode":"L6T 5R5",
    "sg:province":"ON",
    "sg:tags":[
        "housewares"
    ],
    "wof:name":"Modern Housewares",
    "wof:placetype":"venue"
},
  "geometry": {"coordinates":[-79.691986,43.731316],"type":"Point"}
}