{
  "type": "Feature",
  "properties": {
    "addr:full":"8434 Sullivan Pl Delta BC V4C 4E4",
    "addr:housenumber":"8434",
    "addr:postcode":"v4c 4e4",
    "addr:street":"Sullivan Pl",
    "iso:country":"CA",
    "sg:address":"8434 Sullivan Pl",
    "sg:city":"Delta",
    "sg:classifiers":[
        {
            "category":"Autos & Motor Vehicles",
            "subcategory":"Auto Supplies",
            "type":"Retail Goods"
        }
    ],
    "sg:phone":"+1 604 572 4490",
    "sg:postcode":"V4C 4E4",
    "sg:province":"BC",
    "sg:tags":[
        "equipment",
        "air",
        "conditioning",
        "automobile"
    ],
    "wof:name":"Aireco Enterprises",
    "wof:placetype":"venue"
},
  "geometry": {"coordinates":[-122.92208100000001,49.157425],"type":"Point"}
}