{
  "type": "Feature",
  "properties": {
    "iso:country":"CA",
    "sg:address":"1703 Line 33 Peth E",
    "sg:city":"Shakespeare",
    "sg:classifiers":[
        {
            "category":"Manufacturing",
            "subcategory":"Motor Vehicles & Parts",
            "type":"Manufacturing & Wholesale Goods"
        }
    ],
    "sg:phone":"+1 519 655 2748",
    "sg:postcode":"N0B 2P0",
    "sg:province":"ON",
    "sg:tags":[
        "automobile"
    ],
    "wof:name":"Benny's Auto Parts",
    "wof:placetype":"venue"
},
  "geometry": {"coordinates":[-80.81127166749999,43.3507995605],"type":"Point"}
}