{
  "type": "Feature",
  "properties": {
    "addr:full":"Enderby BC V0E 1V0",
    "addr:postcode":"v0e 1v0",
    "iso:country":"CA",
    "sg:city":"Enderby",
    "sg:classifiers":[
        {
            "category":"Personal",
            "subcategory":"Beauty Salon",
            "type":"Services"
        }
    ],
    "sg:phone":"+1 250 838 7966",
    "sg:postcode":"V0E 1V0",
    "sg:province":"BC",
    "wof:name":"Lookers",
    "wof:placetype":"venue"
},
  "geometry": {"coordinates":[-119.138412,50.550377],"type":"Point"}
}