{
  "type": "Feature",
  "properties": {
    "iso:country":"CA",
    "sg:city":"Saint-Felicien",
    "sg:classifiers":[
        {
            "category":"Education",
            "subcategory":"School",
            "type":"Public Place"
        }
    ],
    "sg:phone":"+1 418 679 5737",
    "sg:postcode":"G8K 2R2",
    "sg:province":"QC",
    "wof:name":"Centre D'Alphabetisation",
    "wof:placetype":"venue"
},
  "geometry": {"coordinates":[-72.44956970210001,48.6566238403],"type":"Point"}
}