{
  "type": "Feature",
  "properties": {
    "iso:country":"CA",
    "sg:city":"Toronto",
    "sg:classifiers":[
        {
            "category":"Professional",
            "subcategory":"Lawyer & Legal Services",
            "type":"Services"
        }
    ],
    "sg:phone":"+1 416 532 2833",
    "sg:postcode":"M6H 1M5",
    "sg:province":"ON",
    "sg:tags":[
        "attorney"
    ],
    "wof:name":"Menzies & Von Bogen",
    "wof:placetype":"venue"
},
  "geometry": {"coordinates":[-79.432976,43.660294],"type":"Point"}
}