{
  "type": "Feature",
  "properties": {
    "addr:full":"668 Government Rd Allowance Melita MB R0M 1L0",
    "addr:housenumber":"668",
    "addr:postcode":"r0m 1l0",
    "addr:street":"Government Rd",
    "iso:country":"CA",
    "sg:address":"668 Government Rd Allowance",
    "sg:city":"Melita",
    "sg:classifiers":[
        {
            "category":"Home & Garden",
            "subcategory":"Garden Supply",
            "type":"Retail Goods"
        }
    ],
    "sg:phone":"+1 204 522 3341",
    "sg:postcode":"R0M 1L0",
    "sg:province":"MB",
    "sg:tags":[
        "farm",
        "equipment",
        "lawn"
    ],
    "wof:name":"D B Murray Ltd",
    "wof:placetype":"venue"
},
  "geometry": {"coordinates":[-100.985801697,49.2723083496],"type":"Point"}
}