{
  "type": "Feature",
  "properties": {
    "addr:full":"250 River Rd Arnprior ON K7S 1G8",
    "addr:housenumber":"250",
    "addr:postcode":"k7s 1g8",
    "addr:street":"River Rd",
    "iso:country":"CA",
    "sg:address":"250 River Rd",
    "sg:city":"Arnprior",
    "sg:classifiers":[
        {
            "category":"Freight",
            "type":"Transportation"
        }
    ],
    "sg:phone":"+1 613 623 3045",
    "sg:postcode":"K7S 1G8",
    "sg:province":"ON",
    "sg:tags":[
        "excavating",
        "contractor",
        "trucking"
    ],
    "wof:name":"Robillard & Sons Trucking",
    "wof:placetype":"venue"
},
  "geometry": {"coordinates":[-76.3583679199,45.435634613],"type":"Point"}
}