{
  "type": "Feature",
  "properties": {
    "addr:full":"47 Boul Saint-Joseph Hull QC J8Y 3V9",
    "addr:housenumber":"47",
    "addr:postcode":"j8y 3v9",
    "addr:street":"Boul Saint-Joseph",
    "iso:country":"CA",
    "sg:address":"47 Boul Saint-Joseph",
    "sg:city":"Hull",
    "sg:classifiers":[
        {
            "category":"Personal",
            "subcategory":"Beauty Salon",
            "type":"Services"
        }
    ],
    "sg:phone":"+1 819 772 4415",
    "sg:postcode":"J8Y 3V9",
    "sg:province":"QC",
    "wof:name":"Coiffure Millenaire",
    "wof:placetype":"venue"
},
  "geometry": {"coordinates":[-75.733665,45.426384],"type":"Point"}
}