{
  "type": "Feature",
  "properties": {
    "addr:full":"6975 Creditview Rd # 1 Mississauga ON L5N 8E9",
    "addr:housenumber":"6975",
    "addr:postcode":"l5n 8e9",
    "addr:street":"Creditview Rd # 1",
    "iso:country":"CA",
    "sg:address":"6975 Creditview Rd # 1",
    "sg:city":"Mississauga",
    "sg:classifiers":[
        {
            "category":"Wholesale",
            "subcategory":"Electrical",
            "type":"Manufacturing & Wholesale Goods"
        }
    ],
    "sg:phone":"+1 905 286 9666",
    "sg:postcode":"L5N 8E9",
    "sg:province":"ON",
    "sg:tags":[
        "equipment",
        "electronic",
        "supply"
    ],
    "wof:name":"Fujitsu Canada Inc",
    "wof:placetype":"venue"
},
  "geometry": {"coordinates":[-79.7431945801,43.6133880615],"type":"Point"}
}