{
  "type": "Feature",
  "properties": {
    "addr:full":"2101 S Highway Dr Redcliff AB T0J 2P0",
    "addr:housenumber":"2101",
    "addr:postcode":"t0j 2p0",
    "addr:street":"S Highway Dr",
    "iso:country":"CA",
    "sg:address":"2101 S Highway Dr",
    "sg:city":"Redcliff",
    "sg:classifiers":[
        {
            "category":"Retail",
            "subcategory":"Auto Repair",
            "type":"Services"
        }
    ],
    "sg:phone":"+1 403 548 6262",
    "sg:postcode":"T0J 2P0",
    "sg:province":"AB",
    "sg:tags":[
        "truck"
    ],
    "wof:name":"Ken Hauck Truck Repair Towing",
    "wof:placetype":"venue"
},
  "geometry": {"coordinates":[-110.776596,50.07716],"type":"Point"}
}