{
  "type": "Feature",
  "properties": {
    "addr:full":"6477 Jeanne D'Arc Blvd N Orleans ON K1C 2R1",
    "addr:housenumber":"6477",
    "addr:postcode":"k1c 2r1",
    "addr:street":"Jeanne D'Arc Blvd N",
    "iso:country":"CA",
    "sg:address":"6477 Jeanne D'Arc Blvd N",
    "sg:city":"Orleans",
    "sg:classifiers":[
        {
            "category":"Retail",
            "subcategory":"Laundry & Dry Cleaning",
            "type":"Services"
        }
    ],
    "sg:phone":"+1 613 824 1051",
    "sg:postcode":"K1C 2R1",
    "sg:province":"ON",
    "sg:tags":[
        "cleaners"
    ],
    "wof:name":"Parker Clean",
    "wof:placetype":"venue"
},
  "geometry": {"coordinates":[-75.5380859375,45.4788513184],"type":"Point"}
}