{
  "type": "Feature",
  "properties": {
    "addr:full":"950 Ch Herron Dorval QC H9S 1B3",
    "addr:housenumber":"950",
    "addr:postcode":"h9s 1b3",
    "addr:street":"Ch Herron",
    "iso:country":"CA",
    "sg:address":"950 Ch Herron",
    "sg:city":"Dorval",
    "sg:classifiers":[
        {
            "category":"Shopping",
            "subcategory":"Computers & Home Electronics",
            "type":"Retail Goods"
        }
    ],
    "sg:phone":"+1 514 636 5127",
    "sg:postcode":"H9S 1B3",
    "sg:province":"QC",
    "sg:tags":[
        "equipment",
        "dealer"
    ],
    "wof:name":"Microserv",
    "wof:placetype":"venue"
},
  "geometry": {"coordinates":[-73.746078,45.447319],"type":"Point"}
}