{
  "type": "Feature",
  "properties": {
    "addr:full":"Edmonton AB T5N 0Z2",
    "addr:postcode":"t5n 0z2",
    "iso:country":"CA",
    "sg:city":"Edmonton",
    "sg:phone":"+1 780 414 1862",
    "sg:postcode":"T5N 0Z2",
    "sg:province":"AB",
    "sg:tags":[
        "product",
        "petroleum"
    ],
    "wof:name":"Bakken Petroleum Ltd",
    "wof:placetype":"venue"
},
  "geometry": {"coordinates":[-113.531342,53.549515],"type":"Point"}
}