{
  "type": "Feature",
  "properties": {
    "addr:full":"195 Wyse Rd Dartmouth NS B3A 1N1",
    "addr:housenumber":"195",
    "addr:postcode":"b3a 1n1",
    "addr:street":"Wyse Rd",
    "iso:country":"CA",
    "sg:address":"195 Wyse Rd",
    "sg:city":"Dartmouth",
    "sg:classifiers":[
        {
            "category":"Shopping",
            "subcategory":"Used Merchandise",
            "type":"Retail Goods"
        }
    ],
    "sg:phone":"+1 902 464 0010",
    "sg:postcode":"B3A 1N1",
    "sg:province":"NS",
    "sg:tags":[
        "furniture"
    ],
    "wof:name":"Wyse Buys Trading Inc",
    "wof:placetype":"venue"
},
  "geometry": {"coordinates":[-63.583065033,44.6730651855],"type":"Point"}
}