{
  "type": "Feature",
  "properties": {
    "iso:country":"CA",
    "sg:address":"839 Ottawa St",
    "sg:city":"Windsor",
    "sg:classifiers":[
        {
            "category":"Home & Garden",
            "subcategory":"Household Appliances",
            "type":"Retail Goods"
        }
    ],
    "sg:phone":"+1 519 253 5022",
    "sg:postcode":"N8X 2C7",
    "sg:province":"ON",
    "sg:tags":[
        "machine",
        "sewing",
        "vacuum"
    ],
    "wof:name":"D & R Vacuum Sales & Svc",
    "wof:placetype":"venue"
},
  "geometry": {"coordinates":[-83.018448,42.307491],"type":"Point"}
}