{
  "type": "Feature",
  "properties": {
    "iso:country":"CA",
    "sg:address":"630 8 Ave SW # 102",
    "sg:city":"Calgary",
    "sg:classifiers":[
        {
            "category":"Bars & Pubs",
            "type":"Food & Drink"
        }
    ],
    "sg:phone":"+1 403 263 6555",
    "sg:postcode":"T2P 1G6",
    "sg:province":"AB",
    "wof:name":"Murph's Pub & Eatery",
    "wof:placetype":"venue"
},
  "geometry": {"coordinates":[-114.074692,51.046021],"type":"Point"}
}