{
  "type": "Feature",
  "properties": {
    "addr:full":"17 Stover St S Norwich ON N0J 1P0",
    "addr:housenumber":"17",
    "addr:postcode":"n0j 1p0",
    "addr:street":"Stover St S",
    "iso:country":"CA",
    "sg:address":"17 Stover St S",
    "sg:city":"Norwich",
    "sg:classifiers":[
        {
            "category":"Home & Garden",
            "subcategory":"Hardware",
            "type":"Retail Goods"
        }
    ],
    "sg:phone":"+1 519 863 2055",
    "sg:postcode":"N0J 1P0",
    "sg:province":"ON",
    "wof:name":"Home Hardware Stores",
    "wof:placetype":"venue"
},
  "geometry": {"coordinates":[-80.596756,42.985901],"type":"Point"}
}