{
  "type": "Feature",
  "properties": {
    "addr:full":"759 Boul DE Pointe-Jaune Gaspe QC G4X 4B5",
    "addr:housenumber":"759",
    "addr:postcode":"g4x 4b5",
    "addr:street":"Boul De Pointe-Jaune",
    "iso:country":"CA",
    "sg:address":"759 Boul DE Pointe-Jaune",
    "sg:city":"Gaspe",
    "sg:classifiers":[
        {
            "category":"Retail",
            "subcategory":"Repair Shop",
            "type":"Services"
        }
    ],
    "sg:phone":"+1 418 269 3165",
    "sg:postcode":"G4X 4B5",
    "sg:province":"QC",
    "sg:tags":[
        "equipment",
        "electronic",
        "supply"
    ],
    "wof:name":"Joncas, Yves",
    "wof:placetype":"venue"
},
  "geometry": {"coordinates":[-64.504532,49.065018],"type":"Point"}
}