{
  "type": "Feature",
  "properties": {
    "addr:full":"Cloridorme QC G0E 1G0",
    "addr:postcode":"g0e 1g0",
    "iso:country":"CA",
    "sg:city":"Cloridorme",
    "sg:classifiers":[
        {
            "category":"Shopping",
            "subcategory":"Catalog Store",
            "type":"Retail Goods"
        }
    ],
    "sg:phone":"+1 418 395 2525",
    "sg:postcode":"G0E 1G0",
    "sg:province":"QC",
    "sg:tags":[
        "mail",
        "order",
        "internet"
    ],
    "wof:name":"Sears Canada Inc",
    "wof:placetype":"venue"
},
  "geometry": {"coordinates":[-64.85288199999999,49.185135],"type":"Point"}
}