{
  "type": "Feature",
  "properties": {
    "addr:full":"2130 Shirley Rd Port Perry ON L9L 1B3",
    "addr:housenumber":"2130",
    "addr:postcode":"l9l 1b3",
    "addr:street":"Shirley Rd",
    "iso:country":"CA",
    "sg:address":"2130 Shirley Rd",
    "sg:city":"Port Perry",
    "sg:classifiers":[
        {
            "category":"Recreation",
            "type":"Entertainment"
        }
    ],
    "sg:phone":"+1 905 985 1599",
    "sg:postcode":"L9L 1B3",
    "sg:province":"ON",
    "sg:tags":[
        "riding",
        "horse",
        "dealer",
        "academy"
    ],
    "wof:name":"Dreamcrest Equestrian Svc",
    "wof:placetype":"venue"
},
  "geometry": {"coordinates":[-78.900475,44.055168],"type":"Point"}
}