{
  "type": "Feature",
  "properties": {
    "iso:country":"CA",
    "sg:city":"Calgary",
    "sg:classifiers":[
        {
            "category":"Wholesale",
            "subcategory":"Chemicals & Plastics",
            "type":"Manufacturing & Wholesale Goods"
        }
    ],
    "sg:phone":"+1 403 720 2688",
    "sg:postcode":"T2C 2P7",
    "sg:province":"AB",
    "sg:tags":[
        "concrete",
        "additive"
    ],
    "wof:name":"Interstar Materials Inc",
    "wof:placetype":"venue"
},
  "geometry": {"coordinates":[-113.97019195599999,50.9711494446],"type":"Point"}
}