{
  "type": "Feature",
  "properties": {
    "addr:full":"60 Elgin St Tobermory ON N0H 2R0",
    "addr:housenumber":"60",
    "addr:postcode":"n0h 2r0",
    "addr:street":"Elgin St",
    "iso:country":"CA",
    "sg:address":"60 Elgin St",
    "sg:city":"Tobermory",
    "sg:classifiers":[
        {
            "category":"Travel",
            "subcategory":"Hotels & Motels",
            "type":"Entertainment"
        }
    ],
    "sg:phone":"+1 519 596 2249",
    "sg:postcode":"N0H 2R0",
    "sg:province":"ON",
    "sg:tags":[
        "resort"
    ],
    "wof:name":"Trails End Lodge",
    "wof:placetype":"venue"
},
  "geometry": {"coordinates":[-81.6623535156,45.2629928589],"type":"Point"}
}