{
  "type": "Feature",
  "properties": {
    "addr:full":"Concord ON L4K 4C8",
    "addr:postcode":"l4k 4c8",
    "iso:country":"CA",
    "sg:city":"Concord",
    "sg:classifiers":[
        {
            "category":"Manufacturing",
            "subcategory":"Apparel",
            "type":"Manufacturing & Wholesale Goods"
        }
    ],
    "sg:phone":"+1 905 660 7879",
    "sg:postcode":"L4K 4C8",
    "sg:province":"ON",
    "sg:tags":[
        "clothing"
    ],
    "wof:name":"Ma Belle Fashions",
    "wof:placetype":"venue"
},
  "geometry": {"coordinates":[-79.52538300000001,43.774776],"type":"Point"}
}