{
  "type": "Feature",
  "properties": {
    "addr:full":"310 Boul Industriel Cacouna QC G0L 1G0",
    "addr:housenumber":"310",
    "addr:postcode":"g0l 1g0",
    "addr:street":"Boul Industriel",
    "iso:country":"CA",
    "sg:address":"310 Boul Industriel",
    "sg:city":"Cacouna",
    "sg:classifiers":[
        {
            "category":"Manufacturing",
            "subcategory":"Glass & Minerals",
            "type":"Manufacturing & Wholesale Goods"
        }
    ],
    "sg:phone":"+1 418 862 8876",
    "sg:postcode":"G0L 1G0",
    "sg:province":"QC",
    "sg:tags":[
        "concrete"
    ],
    "wof:name":"Betonieres Du Golf Inc",
    "wof:placetype":"venue"
},
  "geometry": {"coordinates":[-69.507698,47.909615],"type":"Point"}
}