{
  "type": "Feature",
  "properties": {
    "addr:full":"17045 Highway 27 Schomberg ON L0G 1T0",
    "addr:housenumber":"17045",
    "addr:postcode":"l0g 1t0",
    "addr:street":"Highway 27",
    "iso:country":"CA",
    "sg:address":"17045 Highway 27",
    "sg:city":"Schomberg",
    "sg:classifiers":[
        {
            "category":"Building & Trades",
            "subcategory":"Plumbing",
            "type":"Services"
        }
    ],
    "sg:phone":"+1 905 939 2350",
    "sg:postcode":"L0G 1T0",
    "sg:province":"ON",
    "sg:tags":[
        "conditioning",
        "air",
        "fireplace",
        "system",
        "contractor"
    ],
    "wof:name":"Schomberg Sheet Metal Contr",
    "wof:placetype":"venue"
},
  "geometry": {"coordinates":[-79.684105,44.002815],"type":"Point"}
}