{
  "type": "Feature",
  "properties": {
    "addr:full":"Outremont QC H2V 1V5",
    "addr:postcode":"h2v 1v5",
    "iso:country":"CA",
    "sg:city":"Outremont",
    "sg:classifiers":[
        {
            "category":"Wholesale",
            "subcategory":"Durable Goods & Equipment",
            "type":"Manufacturing & Wholesale Goods"
        }
    ],
    "sg:phone":"+1 514 737 7708",
    "sg:postcode":"H2V 1V5",
    "sg:province":"QC",
    "sg:tags":[
        "exporter"
    ],
    "wof:name":"Simcan Inc",
    "wof:placetype":"venue"
},
  "geometry": {"coordinates":[-73.608238,45.520916],"type":"Point"}
}