{
  "type": "Feature",
  "properties": {
    "iso:country":"CA",
    "sg:address":"5739 Av Du Parc",
    "sg:city":"Montreal",
    "sg:classifiers":[
        {
            "category":"Wholesale",
            "subcategory":"Meat",
            "type":"Manufacturing & Wholesale Goods"
        }
    ],
    "sg:phone":"+1 514 272 1828",
    "sg:postcode":"H2V 4H2",
    "sg:province":"QC",
    "wof:name":"Boucherie Buymore Inc",
    "wof:placetype":"venue"
},
  "geometry": {"coordinates":[-73.604546,45.523399],"type":"Point"}
}