{
  "type": "Feature",
  "properties": {
    "addr:full":"27 John St S Hamilton ON L8N 2B8",
    "addr:housenumber":"27",
    "addr:postcode":"l8n 2b8",
    "addr:street":"John St S",
    "iso:country":"CA",
    "sg:address":"27 John St S",
    "sg:city":"Hamilton",
    "sg:classifiers":[
        {
            "category":"Education",
            "subcategory":"School",
            "type":"Public Place"
        }
    ],
    "sg:phone":"+1 905 308 9333",
    "sg:postcode":"L8N 2B8",
    "sg:province":"ON",
    "wof:name":"Liaison College",
    "wof:placetype":"venue"
},
  "geometry": {"coordinates":[-79.8666610718,43.2552337646],"type":"Point"}
}