{
  "type": "Feature",
  "properties": {
    "addr:full":"6068 Netherhart Rd # 12 Mississauga ON L5T 1N3",
    "addr:housenumber":"6068",
    "addr:postcode":"l5t 1n3",
    "addr:street":"Netherhart Rd # 12",
    "iso:country":"CA",
    "sg:address":"6068 Netherhart Rd # 12",
    "sg:city":"Mississauga",
    "sg:classifiers":[
        {
            "category":"Manufacturing",
            "subcategory":"Tools & Machinery",
            "type":"Manufacturing & Wholesale Goods"
        }
    ],
    "sg:phone":"+1 905 564 6942",
    "sg:postcode":"L5T 1N3",
    "sg:province":"ON",
    "sg:tags":[
        "machine",
        "shop"
    ],
    "wof:name":"Ram Components Ltd",
    "wof:placetype":"venue"
},
  "geometry": {"coordinates":[-79.64302062989999,43.6630859375],"type":"Point"}
}