{
  "type": "Feature",
  "properties": {
    "addr:full":"Oakville ON L6M 2Y1",
    "addr:postcode":"l6m 2y1",
    "iso:country":"CA",
    "sg:city":"Oakville",
    "sg:classifiers":[
        {
            "category":"Health Services",
            "subcategory":"Doctor",
            "type":"Services"
        }
    ],
    "sg:phone":"+1 905 815 8888",
    "sg:postcode":"L6M 2Y1",
    "sg:province":"ON",
    "sg:tags":[
        "dentist"
    ],
    "wof:name":"Dentistry in the Abbey",
    "wof:placetype":"venue"
},
  "geometry": {"coordinates":[-79.702034,43.450554],"type":"Point"}
}