{
  "type": "Feature",
  "properties": {
    "addr:full":"430 Route 450 Lavillette NB E9G 2R8",
    "addr:housenumber":"430",
    "addr:postcode":"e9g 2r8",
    "addr:street":"Route 450",
    "iso:country":"CA",
    "sg:address":"430 Route 450",
    "sg:city":"Lavillette",
    "sg:classifiers":[
        {
            "category":"Home & Garden",
            "subcategory":"Building Materials",
            "type":"Retail Goods"
        }
    ],
    "sg:phone":"+1 506 776 8744",
    "sg:postcode":"E9G 2R8",
    "sg:province":"NB",
    "sg:tags":[
        "grocer"
    ],
    "wof:name":"Normand Doiron Grocery & Bldg",
    "wof:placetype":"venue"
},
  "geometry": {"coordinates":[-65.31255299999999,47.26392],"type":"Point"}
}