{
  "type": "Feature",
  "properties": {
    "iso:country":"CA",
    "sg:address":"2736 Lower Glenrosa Rd",
    "sg:city":"Westbank",
    "sg:classifiers":[
        {
            "category":"Museum",
            "type":"Entertainment"
        }
    ],
    "sg:phone":"+1 250 768 0110",
    "sg:postcode":"V4T 1L7",
    "sg:province":"BC",
    "wof:name":"Westbank Museum",
    "wof:placetype":"venue"
},
  "geometry": {"coordinates":[-119.64685821499999,49.8266143799],"type":"Point"}
}