{
  "type": "Feature",
  "properties": {
    "iso:country":"CA",
    "sg:address":"2936 Broadway W",
    "sg:city":"Vancouver",
    "sg:classifiers":[
        {
            "category":"Shopping",
            "subcategory":"Jewelry",
            "type":"Retail Goods"
        }
    ],
    "sg:phone":"+1 604 736 5956",
    "sg:postcode":"V6K 2G8",
    "sg:province":"BC",
    "sg:tags":[
        "jeweler"
    ],
    "wof:name":"Gurvin's on Broadway Ltd",
    "wof:placetype":"venue"
},
  "geometry": {"coordinates":[-123.1707,49.263943],"type":"Point"}
}