{
  "type": "Feature",
  "properties": {
    "addr:full":"Duhamel-Ouest QC J9V 1L5",
    "addr:postcode":"j9v 1l5",
    "iso:country":"CA",
    "sg:city":"Duhamel-Ouest",
    "sg:classifiers":[
        {
            "category":"Food & Beverages",
            "subcategory":"Groceries & Convenience Stores",
            "type":"Retail Goods"
        }
    ],
    "sg:phone":"+1 819 622 2138",
    "sg:postcode":"J9V 1L5",
    "sg:province":"QC",
    "sg:tags":[
        "grocer"
    ],
    "wof:name":"Depanneur Le Vrac A Mon Onche",
    "wof:placetype":"venue"
},
  "geometry": {"coordinates":[-79.45388,47.344242],"type":"Point"}
}