{
  "type": "Feature",
  "properties": {
    "addr:full":"660 Rue Leduc Saint-Laurent QC H4L 2S2",
    "addr:housenumber":"660",
    "addr:postcode":"h4l 2s2",
    "addr:street":"Rue Leduc",
    "iso:country":"CA",
    "sg:address":"660 Rue Leduc",
    "sg:city":"Saint-Laurent",
    "sg:classifiers":[
        {
            "category":"Health Services",
            "subcategory":"Doctor",
            "type":"Services"
        }
    ],
    "sg:phone":"+1 514 748 2255",
    "sg:postcode":"H4L 2S2",
    "sg:province":"QC",
    "sg:tags":[
        "dentist"
    ],
    "wof:name":"Clinique Dentaire Lepojka",
    "wof:placetype":"venue"
},
  "geometry": {"coordinates":[-73.679962,45.507015],"type":"Point"}
}