{
  "type": "Feature",
  "properties": {
    "addr:full":"6611 88 St NW Edmonton AB T6E 2Z2",
    "addr:housenumber":"6611",
    "addr:postcode":"t6e 2z2",
    "addr:street":"88 St Nw",
    "iso:country":"CA",
    "sg:address":"6611 88 St NW",
    "sg:city":"Edmonton",
    "sg:classifiers":[
        {
            "category":"Building & Trades",
            "subcategory":"Construction",
            "type":"Services"
        }
    ],
    "sg:phone":"+1 780 466 2818",
    "sg:postcode":"T6E 2Z2",
    "sg:province":"AB",
    "sg:tags":[
        "plastering",
        "contractor"
    ],
    "wof:name":"Riehl Bros Plastering Ltd",
    "wof:placetype":"venue"
},
  "geometry": {"coordinates":[-113.465675,53.502911],"type":"Point"}
}