{
  "type": "Feature",
  "properties": {
    "addr:full":"16 Queen St Campbellford ON K0L 1L0",
    "addr:housenumber":"16",
    "addr:postcode":"k0l 1l0",
    "addr:street":"Queen St",
    "iso:country":"CA",
    "sg:address":"16 Queen St",
    "sg:city":"Campbellford",
    "sg:classifiers":[
        {
            "category":"Retail",
            "subcategory":"Photofinishing",
            "type":"Services"
        }
    ],
    "sg:phone":"+1 705 653 0388",
    "sg:postcode":"K0L 1L0",
    "sg:province":"ON",
    "sg:tags":[
        "photo",
        "finishing"
    ],
    "wof:name":"Snapshots One Hour Photo",
    "wof:placetype":"venue"
},
  "geometry": {"coordinates":[-77.800331,44.309166],"type":"Point"}
}