{
  "type": "Feature",
  "properties": {
    "addr:full":"3740 Boul Du Royaume Jonquiere QC G7X 1Y5",
    "addr:housenumber":"3740",
    "addr:postcode":"g7x 1y5",
    "addr:street":"Boul Du Royaume",
    "iso:country":"CA",
    "sg:address":"3740 Boul Du Royaume",
    "sg:city":"Jonquiere",
    "sg:classifiers":[
        {
            "category":"Home & Garden",
            "subcategory":"Furniture",
            "type":"Retail Goods"
        }
    ],
    "sg:phone":"+1 418 547 3560",
    "sg:postcode":"G7X 1Y5",
    "sg:province":"QC",
    "wof:name":"Specialites Matelas & Futons",
    "wof:placetype":"venue"
},
  "geometry": {"coordinates":[-71.24073028559999,48.4223861694],"type":"Point"}
}