{
  "type": "Feature",
  "properties": {
    "addr:full":"Winnipeg MB R3B 2Y5",
    "addr:postcode":"r3b 2y5",
    "iso:country":"CA",
    "sg:city":"Winnipeg",
    "sg:classifiers":[
        {
            "category":"Health Services",
            "subcategory":"Doctor",
            "type":"Services"
        }
    ],
    "sg:phone":"+1 204 783 6551",
    "sg:postcode":"R3B 2Y5",
    "sg:province":"MB",
    "sg:tags":[
        "dentist"
    ],
    "wof:name":"Wong, Henry DDS",
    "wof:placetype":"venue"
},
  "geometry": {"coordinates":[-97.14975699999999,49.89394],"type":"Point"}
}