{
  "type": "Feature",
  "properties": {
    "addr:full":"1 Mcphillips St Winnipeg MB R3E 2J4",
    "addr:housenumber":"1",
    "addr:postcode":"r3e 2j4",
    "addr:street":"Mcphillips St",
    "iso:country":"CA",
    "sg:address":"1 Mcphillips St",
    "sg:city":"Winnipeg",
    "sg:classifiers":[
        {
            "category":"Retail",
            "subcategory":"Auto Repair",
            "type":"Services"
        }
    ],
    "sg:phone":"+1 204 775 1700",
    "sg:postcode":"R3E 2J4",
    "sg:province":"MB",
    "sg:tags":[
        "repairing",
        "automobile",
        "lubrication"
    ],
    "wof:name":"Super Lube Auto Ctr",
    "wof:placetype":"venue"
},
  "geometry": {"coordinates":[-97.171181,49.90546],"type":"Point"}
}