{
  "type": "Feature",
  "properties": {
    "iso:country":"CA",
    "sg:address":"1010 Rue Sherbrooke O",
    "sg:city":"Montreal",
    "sg:classifiers":[
        {
            "category":"Banks & Credit Unions",
            "subcategory":"Investment Brokerage",
            "type":"Services"
        }
    ],
    "sg:phone":"+1 514 842 8473",
    "sg:postcode":"H3A 2R7",
    "sg:province":"QC",
    "sg:tags":[
        "advisory",
        "financial"
    ],
    "wof:name":"Pandion Investments Ltd",
    "wof:placetype":"venue"
},
  "geometry": {"coordinates":[-73.565544,45.520882],"type":"Point"}
}