{
  "type": "Feature",
  "properties": {
    "addr:full":"Grasshead St Wabasca AB T0G 2K0",
    "addr:postcode":"t0g 2k0",
    "addr:street":"St",
    "iso:country":"CA",
    "sg:address":"Grasshead St",
    "sg:city":"Wabasca",
    "sg:classifiers":[
        {
            "category":"Building & Trades",
            "subcategory":"Construction",
            "type":"Services"
        }
    ],
    "sg:phone":"+1 780 891 3125",
    "sg:postcode":"T0G 2K0",
    "sg:province":"AB",
    "sg:tags":[
        "general",
        "contractor"
    ],
    "wof:name":"Laforce Construction Ltd",
    "wof:placetype":"venue"
},
  "geometry": {"coordinates":[-113.865623,55.98365],"type":"Point"}
}