{
  "type": "Feature",
  "properties": {
    "addr:full":"49 Progress Dr St Stephen NB E3L 5Y8",
    "addr:housenumber":"49",
    "addr:postcode":"e3l 5y8",
    "addr:street":"Progress Dr",
    "iso:country":"CA",
    "sg:address":"49 Progress Dr",
    "sg:city":"St Stephen",
    "sg:classifiers":[
        {
            "category":"Manufacturing",
            "subcategory":"Tools & Machinery",
            "type":"Manufacturing & Wholesale Goods"
        }
    ],
    "sg:phone":"+1 506 466 5566",
    "sg:postcode":"E3L 5Y8",
    "sg:province":"NB",
    "sg:tags":[
        "machine",
        "shop"
    ],
    "wof:name":"Milltown Machine & Fab Ltd",
    "wof:placetype":"venue"
},
  "geometry": {"coordinates":[-67.3066940308,45.1763267517],"type":"Point"}
}