{
  "type": "Feature",
  "properties": {
    "addr:full":"31201 Old Yale Rd Abbotsford BC V2T 5E5",
    "addr:housenumber":"31201",
    "addr:postcode":"v2t 5e5",
    "addr:street":"Old Yale Rd",
    "iso:country":"CA",
    "sg:address":"31201 Old Yale Rd",
    "sg:city":"Abbotsford",
    "sg:classifiers":[
        {
            "category":"Autos & Motor Vehicles",
            "subcategory":"Fuel & Gas Station",
            "type":"Retail Goods"
        }
    ],
    "sg:phone":"+1 604 850 5533",
    "sg:postcode":"V2T 5E5",
    "sg:province":"BC",
    "sg:tags":[
        "oil"
    ],
    "wof:name":"Petro-Canada Neighbours",
    "wof:placetype":"venue"
},
  "geometry": {"coordinates":[-122.359467,49.054314],"type":"Point"}
}