{
  "type": "Feature",
  "properties": {
    "addr:full":"214 Thurlby Rd Winnipeg MB R2G 2V4",
    "addr:housenumber":"214",
    "addr:postcode":"r2g 2v4",
    "addr:street":"Thurlby Rd",
    "iso:country":"CA",
    "sg:address":"214 Thurlby Rd",
    "sg:city":"Winnipeg",
    "sg:classifiers":[
        {
            "category":"Wholesale",
            "subcategory":"Durable Goods & Equipment",
            "type":"Manufacturing & Wholesale Goods"
        }
    ],
    "sg:phone":"+1 204 668 7901",
    "sg:postcode":"R2G 2V4",
    "sg:province":"MB",
    "sg:tags":[
        "importer"
    ],
    "wof:name":"Milne-Mac Kay Assoc",
    "wof:placetype":"venue"
},
  "geometry": {"coordinates":[-97.045143,49.938488],"type":"Point"}
}