{
  "type": "Feature",
  "properties": {
    "iso:country":"CA",
    "sg:address":"5008 50 Ave",
    "sg:city":"Cold Lake",
    "sg:classifiers":[
        {
            "category":"Personal",
            "subcategory":"Beauty Salon",
            "type":"Services"
        }
    ],
    "sg:phone":"+1 780 594 5703",
    "sg:postcode":"T9M 1P1",
    "sg:province":"AB",
    "wof:name":"Jay's Hair Team",
    "wof:placetype":"venue"
},
  "geometry": {"coordinates":[-110.20564299999999,54.41357],"type":"Point"}
}