{
  "type": "Feature",
  "properties": {
    "addr:full":"850 Barrydowne Rd Sudbury ON P3A 3T7",
    "addr:housenumber":"850",
    "addr:postcode":"p3a 3t7",
    "addr:street":"Barrydowne Rd",
    "iso:country":"CA",
    "sg:address":"850 Barrydowne Rd",
    "sg:city":"Sudbury",
    "sg:classifiers":[
        {
            "category":"Professional",
            "subcategory":"Printing & Photocopies",
            "type":"Services"
        }
    ],
    "sg:phone":"+1 705 524 2114",
    "sg:postcode":"P3A 3T7",
    "sg:province":"ON",
    "sg:tags":[
        "duplicating",
        "copying"
    ],
    "wof:name":"Copy Copy",
    "wof:placetype":"venue"
},
  "geometry": {"coordinates":[-80.94396999999999,46.514778],"type":"Point"}
}