{
  "type": "Feature",
  "properties": {
    "iso:country":"CA",
    "sg:address":"58 Albert St",
    "sg:city":"Chesterville",
    "sg:classifiers":[
        {
            "category":"Wholesale",
            "subcategory":"Scrap",
            "type":"Manufacturing & Wholesale Goods"
        }
    ],
    "sg:phone":"+1 613 448 2383",
    "sg:postcode":"K0C 1H0",
    "sg:province":"ON",
    "sg:tags":[
        "recycling",
        "center"
    ],
    "wof:name":"Recycling Data Assoc",
    "wof:placetype":"venue"
},
  "geometry": {"coordinates":[-75.2284164429,45.1044654846],"type":"Point"}
}