{
  "type": "Feature",
  "properties": {
    "iso:country":"CA",
    "sg:address":"43 Rue Beaubien E",
    "sg:city":"Montreal",
    "sg:classifiers":[
        {
            "category":"Personal",
            "subcategory":"Beauty Salon",
            "type":"Services"
        }
    ],
    "sg:phone":"+1 514 276 1416",
    "sg:postcode":"H2S 1P7",
    "sg:province":"QC",
    "wof:name":"Coiffure Mayra",
    "wof:placetype":"venue"
},
  "geometry": {"coordinates":[-73.608093,45.53083],"type":"Point"}
}