{
  "type": "Feature",
  "properties": {
    "iso:country":"CA",
    "sg:address":"294 Commercial St",
    "sg:city":"North Sydney",
    "sg:classifiers":[
        {
            "category":"Restaurant",
            "type":"Food & Drink"
        }
    ],
    "sg:phone":"+1 902 794 4587",
    "sg:postcode":"B2A 1C1",
    "sg:province":"NS",
    "wof:name":"Canton Restaurant",
    "wof:placetype":"venue"
},
  "geometry": {"coordinates":[-60.2482643127,46.2097969055],"type":"Point"}
}