{
  "type": "Feature",
  "properties": {
    "addr:full":"525 Av Sainte-Croix Saint-Laurent QC H4L 3X6",
    "addr:postcode":"h4l 3x6",
    "addr:street":"525 Av Sainte-Croix",
    "iso:country":"CA",
    "sg:address":"525 Av Sainte-Croix",
    "sg:city":"Saint-Laurent",
    "sg:classifiers":[
        {
            "category":"Recreation",
            "type":"Entertainment"
        }
    ],
    "sg:phone":"+1 514 744 8374",
    "sg:postcode":"H4L 3X6",
    "sg:province":"QC",
    "sg:tags":[
        "club",
        "hockey"
    ],
    "wof:name":"Ligue DE Hockey Depression Inc",
    "wof:placetype":"venue"
},
  "geometry": {"coordinates":[-73.67038700000001,45.510685],"type":"Point"}
}