{
  "type": "Feature",
  "properties": {
    "addr:full":"3270 Hwy 313 Lac Du Bonnet MB R0E 1A0",
    "addr:housenumber":"3270",
    "addr:postcode":"r0e 1a0",
    "addr:street":"Hwy 313 Lac Du Bonnet",
    "iso:country":"CA",
    "sg:address":"3270 Hwy 313",
    "sg:city":"Lac Du Bonnet",
    "sg:classifiers":[
        {
            "category":"Travel",
            "subcategory":"Hotels & Motels",
            "type":"Entertainment"
        }
    ],
    "sg:phone":"+1 204 345 2346",
    "sg:postcode":"R0E 1A0",
    "sg:province":"MB",
    "sg:tags":[
        "resort",
        "tourist",
        "accommodation"
    ],
    "wof:name":"Riverdale Tourist Camp",
    "wof:placetype":"venue"
},
  "geometry": {"coordinates":[-95.8573760986,50.2825965881],"type":"Point"}
}