{
  "type": "Feature",
  "properties": {
    "addr:full":"147 Rue Principale Chateauguay QC J6K 1G2",
    "addr:housenumber":"147",
    "addr:postcode":"j6k 1g2",
    "addr:street":"Rue Principale",
    "iso:country":"CA",
    "sg:address":"147 Rue Principale",
    "sg:city":"Chateauguay",
    "sg:classifiers":[
        {
            "category":"Bus Charters",
            "type":"Transportation"
        }
    ],
    "sg:phone":"+1 450 691 1654",
    "sg:postcode":"J6K 1G2",
    "sg:province":"QC",
    "sg:tags":[
        "rental"
    ],
    "wof:name":"Autobus Auger Metropolitan Inc",
    "wof:placetype":"venue"
},
  "geometry": {"coordinates":[-73.760796,45.357105],"type":"Point"}
}