{
  "type": "Feature",
  "properties": {
    "addr:full":"50 Boul Couillard-Despres Sorel-Tracy QC J3P 5B7",
    "addr:housenumber":"50",
    "addr:postcode":"j3p 5b7",
    "addr:street":"Boul Couillard-Despres",
    "iso:country":"CA",
    "sg:address":"50 Boul Couillard-Despres",
    "sg:city":"Sorel-Tracy",
    "sg:classifiers":[
        {
            "category":"Professional",
            "subcategory":"Management & Consulting",
            "type":"Services"
        }
    ],
    "sg:phone":"+1 450 743 7677",
    "sg:postcode":"J3P 5B7",
    "sg:province":"QC",
    "sg:tags":[
        "consultant",
        "educational"
    ],
    "wof:name":"Foucault Inc",
    "wof:placetype":"venue"
},
  "geometry": {"coordinates":[-73.1203460693,46.0221366882],"type":"Point"}
}