{
  "type": "Feature",
  "properties": {
    "addr:full":"6420 Boul Wilfrid-Hamel L'Ancienne-Lorette QC G2E 5M3",
    "addr:housenumber":"6420",
    "addr:postcode":"g2e 5m3",
    "addr:street":"Boul Wilfrid-Hamel",
    "iso:country":"CA",
    "sg:address":"6420 Boul Wilfrid-Hamel",
    "sg:city":"L'Ancienne-Lorette",
    "sg:classifiers":[
        {
            "category":"Retail",
            "subcategory":"Auto Rental",
            "type":"Services"
        }
    ],
    "sg:phone":"+1 418 877 1717",
    "sg:postcode":"G2E 5M3",
    "sg:province":"QC",
    "sg:tags":[
        "renting",
        "automobile"
    ],
    "wof:name":"Discount Location D'Autos",
    "wof:placetype":"venue"
},
  "geometry": {"coordinates":[-71.352119,46.793678],"type":"Point"}
}