{
  "type": "Feature",
  "properties": {
    "addr:full":"516 Rte Begin N Sainte-Claire QC G0R 2V0",
    "addr:housenumber":"516",
    "addr:postcode":"g0r 2v0",
    "addr:street":"Rte Begin N",
    "iso:country":"CA",
    "sg:address":"516 Rte Begin N",
    "sg:city":"Sainte-Claire",
    "sg:classifiers":[
        {
            "category":"Manufacturing",
            "subcategory":"Lumber",
            "type":"Manufacturing & Wholesale Goods"
        }
    ],
    "sg:phone":"+1 418 883 3770",
    "sg:postcode":"G0R 2V0",
    "sg:province":"QC",
    "sg:tags":[
        "sawmill"
    ],
    "wof:name":"Couture, Gilles",
    "wof:placetype":"venue"
},
  "geometry": {"coordinates":[-70.928185,46.602417],"type":"Point"}
}