{
  "type": "Feature",
  "properties": {
    "addr:full":"Breadalbane PE C0A 1E0",
    "addr:postcode":"c0a 1e0",
    "iso:country":"CA",
    "sg:city":"Breadalbane",
    "sg:classifiers":[
        {
            "category":"Manufacturing",
            "subcategory":"Food",
            "type":"Manufacturing & Wholesale Goods"
        }
    ],
    "sg:phone":"+1 902 621 0300",
    "sg:postcode":"C0A 1E0",
    "sg:province":"PE",
    "sg:tags":[
        "carcass",
        "animal",
        "removal"
    ],
    "wof:name":"Maritime Pet Foods",
    "wof:placetype":"venue"
},
  "geometry": {"coordinates":[-63.503227,46.352989],"type":"Point"}
}