{
  "type": "Feature",
  "properties": {
    "iso:country":"CA",
    "sg:address":"405 Rue Boivin O",
    "sg:city":"Alma",
    "sg:classifiers":[
        {
            "category":"Health Services",
            "subcategory":"Doctor",
            "type":"Services"
        }
    ],
    "sg:phone":"+1 418 481 4922",
    "sg:postcode":"G8B 1Y5",
    "sg:province":"QC",
    "sg:tags":[
        "clinic"
    ],
    "wof:name":"Clinique DE Massotherapie",
    "wof:placetype":"venue"
},
  "geometry": {"coordinates":[-71.65180969239999,48.5453186035],"type":"Point"}
}