{
  "type": "Feature",
  "properties": {
    "iso:country":"CA",
    "sg:address":"21 Rue Renaud",
    "sg:city":"Brownsburg-Chatham",
    "sg:classifiers":[
        {
            "category":"Health Services",
            "subcategory":"Nursing And Care Facility",
            "type":"Services"
        }
    ],
    "sg:phone":"+1 450 562 0582",
    "sg:postcode":"J8G 2E7",
    "sg:province":"QC",
    "sg:tags":[
        "home",
        "retirement",
        "community"
    ],
    "wof:name":"Seigneurie D'Argenteiul",
    "wof:placetype":"venue"
},
  "geometry": {"coordinates":[-74.42584228520001,45.6268501282],"type":"Point"}
}