{
  "type": "Feature",
  "properties": {
    "addr:full":"1981 Logan Ave Winnipeg MB R2R 0H8",
    "addr:housenumber":"1981",
    "addr:postcode":"r2r 0h8",
    "addr:street":"Logan Ave",
    "iso:country":"CA",
    "sg:address":"1981 Logan Ave",
    "sg:city":"Winnipeg",
    "sg:classifiers":[
        {
            "category":"Autos & Motor Vehicles",
            "subcategory":"Motorcycle Sales",
            "type":"Retail Goods"
        }
    ],
    "sg:phone":"+1 204 697 0335",
    "sg:postcode":"R2R 0H8",
    "sg:province":"MB",
    "sg:tags":[
        "wrecker"
    ],
    "wof:name":"Best Performance Towing",
    "wof:placetype":"venue"
},
  "geometry": {"coordinates":[-97.2037200928,49.9244880676],"type":"Point"}
}