{
  "type": "Feature",
  "properties": {
    "addr:full":"13 Ajax Pl Victoria Beach MB R0E 2C0",
    "addr:housenumber":"13",
    "addr:postcode":"r0e 2c0",
    "addr:street":"Ajax Pl",
    "iso:country":"CA",
    "sg:address":"13 Ajax Pl",
    "sg:city":"Victoria Beach",
    "sg:classifiers":[
        {
            "category":"Building & Trades",
            "subcategory":"Plumbing",
            "type":"Services"
        }
    ],
    "sg:phone":"+1 204 756 2722",
    "sg:postcode":"R0E 2C0",
    "sg:province":"MB",
    "sg:tags":[
        "contractor"
    ],
    "wof:name":"Ray's Plumbing",
    "wof:placetype":"venue"
},
  "geometry": {"coordinates":[-96.530128,50.698463],"type":"Point"}
}