{
  "type": "Feature",
  "properties": {
    "addr:full":"4270 Rang Du Cordon Saint-Jacques QC J0K 2R0",
    "addr:housenumber":"4270",
    "addr:postcode":"j0k 2r0",
    "addr:street":"Rang Du Cordon",
    "iso:country":"CA",
    "sg:address":"4270 Rang Du Cordon",
    "sg:city":"Saint-Jacques",
    "sg:classifiers":[
        {
            "category":"Manufacturing",
            "subcategory":"Lumber",
            "type":"Manufacturing & Wholesale Goods"
        }
    ],
    "sg:phone":"+1 450 839 3044",
    "sg:postcode":"J0K 2R0",
    "sg:province":"QC",
    "sg:tags":[
        "syrup",
        "maple",
        "sugar"
    ],
    "wof:name":"Beaudoin Claude & Robert",
    "wof:placetype":"venue"
},
  "geometry": {"coordinates":[-73.6593093872,45.989200592],"type":"Point"}
}