{
  "type": "Feature",
  "properties": {
    "addr:full":"Burnaby BC V5B 1S2",
    "addr:postcode":"v5b 1s2",
    "iso:country":"CA",
    "sg:city":"Burnaby",
    "sg:classifiers":[
        {
            "category":"Retail",
            "subcategory":"Photofinishing",
            "type":"Services"
        }
    ],
    "sg:phone":"+1 604 293 1899",
    "sg:postcode":"V5B 1S2",
    "sg:province":"BC",
    "sg:tags":[
        "photo",
        "finishing"
    ],
    "wof:name":"Scenic Photo",
    "wof:placetype":"venue"
},
  "geometry": {"coordinates":[-122.96939086899999,49.2801132202],"type":"Point"}
}