{
  "type": "Feature",
  "properties": {
    "addr:full":"1490 Venables St Vancouver BC V5L 4X6",
    "addr:housenumber":"1490",
    "addr:postcode":"v5l 4x6",
    "addr:street":"Venables St",
    "iso:country":"CA",
    "sg:address":"1490 Venables St",
    "sg:city":"Vancouver",
    "sg:classifiers":[
        {
            "category":"Retail",
            "subcategory":"Repair Shop",
            "type":"Services"
        }
    ],
    "sg:phone":"+1 604 255 2461",
    "sg:postcode":"V5L 4X6",
    "sg:province":"BC",
    "sg:tags":[
        "conditioning",
        "air",
        "system",
        "refrigerating",
        "contractor"
    ],
    "wof:name":"Broadway Refrigeration & Ac",
    "wof:placetype":"venue"
},
  "geometry": {"coordinates":[-123.07359314,49.2765769958],"type":"Point"}
}