{
  "type": "Feature",
  "properties": {
    "iso:country":"CA",
    "sg:address":"72 Wilson Rd N",
    "sg:city":"Oshawa",
    "sg:classifiers":[
        {
            "category":"Building & Trades",
            "subcategory":"Pest Control",
            "type":"Services"
        }
    ],
    "sg:phone":"+1 905 404 9933",
    "sg:postcode":"L1G 6E2",
    "sg:province":"ON",
    "wof:name":"Sky Pest Control Ltd",
    "wof:placetype":"venue"
},
  "geometry": {"coordinates":[-78.8450164795,43.9041442871],"type":"Point"}
}