{
  "type": "Feature",
  "properties": {
    "addr:full":"Oakville ON L6L 3B7",
    "addr:postcode":"l6l 3b7",
    "iso:country":"CA",
    "sg:city":"Oakville",
    "sg:classifiers":[
        {
            "category":"Banks & Credit Unions",
            "subcategory":"Investment Brokerage",
            "type":"Services"
        }
    ],
    "sg:phone":"+1 905 465 3460",
    "sg:postcode":"L6L 3B7",
    "sg:province":"ON",
    "sg:tags":[
        "stock",
        "broker",
        "bond"
    ],
    "wof:name":"Edward Jones",
    "wof:placetype":"venue"
},
  "geometry": {"coordinates":[-79.711189,43.394157],"type":"Point"}
}