{
  "type": "Feature",
  "properties": {
    "addr:full":"879 10th St W Owen Sound ON N4K 6S1",
    "addr:housenumber":"879",
    "addr:postcode":"n4k 6s1",
    "addr:street":"10Th St W",
    "iso:country":"CA",
    "sg:address":"879 10th St W",
    "sg:city":"Owen Sound",
    "sg:classifiers":[
        {
            "category":"Sports & Exercise",
            "subcategory":"Gym",
            "type":"Entertainment"
        }
    ],
    "sg:phone":"+1 519 371 7760",
    "sg:postcode":"N4K 6S1",
    "sg:province":"ON",
    "sg:tags":[
        "club",
        "gymnasium",
        "program",
        "health",
        "fitness",
        "studio",
        "physical"
    ],
    "wof:name":"Curves For Women",
    "wof:placetype":"venue"
},
  "geometry": {"coordinates":[-80.961494,44.566006],"type":"Point"}
}