{
  "type": "Feature",
  "properties": {
    "addr:full":"1000 Stewart Ave Nanaimo BC V9S 4C9",
    "addr:housenumber":"1000",
    "addr:postcode":"v9s 4c9",
    "addr:street":"Stewart Ave",
    "iso:country":"CA",
    "sg:address":"1000 Stewart Ave",
    "sg:city":"Nanaimo",
    "sg:classifiers":[
        {
            "category":"Travel",
            "subcategory":"Hotels & Motels",
            "type":"Entertainment"
        }
    ],
    "sg:phone":"+1 250 753 7111",
    "sg:postcode":"V9S 4C9",
    "sg:province":"BC",
    "wof:name":"Moby Dick Oceanfront Lodge",
    "wof:placetype":"venue"
},
  "geometry": {"coordinates":[-123.94555699999999,49.181206],"type":"Point"}
}