{
  "type": "Feature",
  "properties": {
    "addr:full":"361 O'Brien Rd Renfrew ON K7V 2S1",
    "addr:housenumber":"361",
    "addr:postcode":"k7v 2s1",
    "addr:street":"O'Brien Rd",
    "iso:country":"CA",
    "sg:address":"361 O'Brien Rd",
    "sg:city":"Renfrew",
    "sg:classifiers":[
        {
            "category":"Shopping",
            "subcategory":"Discount & Variety Stores",
            "type":"Retail Goods"
        }
    ],
    "sg:phone":"+1 613 432 4150",
    "sg:postcode":"K7V 2S1",
    "sg:province":"ON",
    "wof:name":"O'Brien Road Variety",
    "wof:placetype":"venue"
},
  "geometry": {"coordinates":[-77.354973,45.696079],"type":"Point"}
}