{
  "type": "Feature",
  "properties": {
    "addr:full":"305 Mackenzie Blvd Mackenzie BC V0J 2C0",
    "addr:housenumber":"305",
    "addr:postcode":"v0j 2c0",
    "addr:street":"Mackenzie Blvd",
    "iso:country":"CA",
    "sg:address":"305 Mackenzie Blvd",
    "sg:city":"Mackenzie",
    "sg:classifiers":[
        {
            "category":"Travel",
            "subcategory":"Hotels & Motels",
            "type":"Entertainment"
        }
    ],
    "sg:phone":"+1 250 997 3131",
    "sg:postcode":"V0J 2C0",
    "sg:province":"BC",
    "wof:name":"Williston Lake Lodge",
    "wof:placetype":"venue"
},
  "geometry": {"coordinates":[-123.09421500000001,55.336308],"type":"Point"}
}