{
  "type": "Feature",
  "properties": {
    "addr:full":"37 Parkside Dr Barrie ON L4N 1W8",
    "addr:housenumber":"37",
    "addr:postcode":"l4n 1w8",
    "addr:street":"Parkside Dr",
    "iso:country":"CA",
    "sg:address":"37 Parkside Dr",
    "sg:city":"Barrie",
    "sg:classifiers":[
        {
            "category":"Government",
            "subcategory":"Office",
            "type":"Public Place"
        }
    ],
    "sg:phone":"+1 705 728 3761",
    "sg:postcode":"L4N 1W8",
    "sg:province":"ON",
    "wof:name":"Canada Defense Nationale",
    "wof:placetype":"venue"
},
  "geometry": {"coordinates":[-79.6968383789,44.3886375427],"type":"Point"}
}