{
  "type": "Feature",
  "properties": {
    "iso:country":"CA",
    "sg:address":"1778 Rue Saint-Calixte",
    "sg:city":"Plessisville",
    "sg:classifiers":[
        {
            "category":"Organizations",
            "subcategory":"Professional Association",
            "type":"Services"
        }
    ],
    "sg:phone":"+1 819 980 8044",
    "sg:postcode":"G6L 1R5",
    "sg:province":"QC",
    "wof:name":"Sdc",
    "wof:placetype":"venue"
},
  "geometry": {"coordinates":[-71.770988,46.219498],"type":"Point"}
}