{
  "type": "Feature",
  "properties": {
    "addr:full":"19531 Fraser Hwy Surrey BC V3S 6K7",
    "addr:housenumber":"19531",
    "addr:postcode":"v3s 6k7",
    "addr:street":"Fraser Hwy",
    "iso:country":"CA",
    "sg:address":"19531 Fraser Hwy",
    "sg:city":"Surrey",
    "sg:classifiers":[
        {
            "category":"Retail",
            "subcategory":"Laundry & Dry Cleaning",
            "type":"Services"
        }
    ],
    "sg:phone":"+1 604 534 6422",
    "sg:postcode":"V3S 6K7",
    "sg:province":"BC",
    "sg:tags":[
        "cleaners"
    ],
    "wof:name":"DE Elegance Cleaners & Drapery",
    "wof:placetype":"venue"
},
  "geometry": {"coordinates":[-122.68112182599999,49.1146621704],"type":"Point"}
}