{
  "type": "Feature",
  "properties": {
    "iso:country":"CA",
    "sg:address":"185 Talon Lake Rd",
    "sg:city":"Rutherglen",
    "sg:classifiers":[
        {
            "category":"Travel",
            "subcategory":"Campground",
            "type":"Entertainment"
        }
    ],
    "sg:phone":"+1 705 776 2832",
    "sg:postcode":"P0H 2E0",
    "sg:province":"ON",
    "sg:tags":[
        "cottage",
        "cabin"
    ],
    "wof:name":"Talon Lake Campground",
    "wof:placetype":"venue"
},
  "geometry": {"coordinates":[-79.0396270752,46.2705154419],"type":"Point"}
}