{
  "type": "Feature",
  "properties": {
    "iso:country":"CA",
    "sg:city":"Winnipeg",
    "sg:classifiers":[
        {
            "category":"Real Estate",
            "subcategory":"Real Estate Operator",
            "type":"Services"
        }
    ],
    "sg:phone":"+1 204 694 4497",
    "sg:postcode":"R2P 2C8",
    "sg:province":"MB",
    "sg:tags":[
        "apartment"
    ],
    "wof:name":"Seven Oaks Village Hsng CO-OP",
    "wof:placetype":"venue"
},
  "geometry": {"coordinates":[-97.18351745610001,49.95911026],"type":"Point"}
}