{
  "type": "Feature",
  "properties": {
    "addr:full":"Vancouver BC V5Z 1J8",
    "addr:postcode":"v5z 1j8",
    "iso:country":"CA",
    "sg:city":"Vancouver",
    "sg:classifiers":[
        {
            "category":"Personal",
            "subcategory":"Beauty Salon",
            "type":"Services"
        }
    ],
    "sg:phone":"+1 604 708 3566",
    "sg:postcode":"V5Z 1J8",
    "sg:province":"BC",
    "wof:name":"Broadway's Just For Hair",
    "wof:placetype":"venue"
},
  "geometry": {"coordinates":[-123.12247499999999,49.263226],"type":"Point"}
}