{
  "type": "Feature",
  "properties": {
    "addr:full":"4272 Slocan River Rd Winlaw BC V0G 2J0",
    "addr:housenumber":"4272",
    "addr:postcode":"v0g 2j0",
    "addr:street":"Slocan River Rd",
    "iso:country":"CA",
    "sg:address":"4272 Slocan River Rd",
    "sg:city":"Winlaw",
    "sg:classifiers":[
        {
            "category":"Manufacturing",
            "subcategory":"Lumber",
            "type":"Manufacturing & Wholesale Goods"
        }
    ],
    "sg:phone":"+1 250 226 7222",
    "sg:postcode":"V0G 2J0",
    "sg:province":"BC",
    "sg:tags":[
        "forester"
    ],
    "wof:name":"Silva Ecosystems Consultants",
    "wof:placetype":"venue"
},
  "geometry": {"coordinates":[-117.498512268,49.6750488281],"type":"Point"}
}