{
  "type": "Feature",
  "properties": {
    "addr:full":"Penticton BC V2A 5L2",
    "addr:postcode":"v2a 5l2",
    "iso:country":"CA",
    "sg:city":"Penticton",
    "sg:classifiers":[
        {
            "category":"Health Services",
            "subcategory":"Doctor",
            "type":"Services"
        }
    ],
    "sg:phone":"+1 250 493 1117",
    "sg:postcode":"V2A 5L2",
    "sg:province":"BC",
    "sg:tags":[
        "physician",
        "surgeon"
    ],
    "wof:name":"Terrence M Maguire Medical Svc",
    "wof:placetype":"venue"
},
  "geometry": {"coordinates":[-119.592140198,49.4952812195],"type":"Point"}
}