{
  "type": "Feature",
  "properties": {
    "iso:country":"CA",
    "sg:address":"5598 Rue Hochelaga",
    "sg:city":"Montreal",
    "sg:classifiers":[
        {
            "category":"Manufacturing",
            "subcategory":"Metals",
            "type":"Manufacturing & Wholesale Goods"
        }
    ],
    "sg:phone":"+1 514 526 0894",
    "sg:postcode":"H1N 3L7",
    "sg:province":"QC",
    "sg:tags":[
        "shelter",
        "garage",
        "canopy",
        "temporary",
        "awning"
    ],
    "wof:name":"Bellon Industries Inc",
    "wof:placetype":"venue"
},
  "geometry": {"coordinates":[-73.538727,45.568253],"type":"Point"}
}