{
  "type": "Feature",
  "properties": {
    "addr:full":"5598 Rue Hochelaga Montreal QC H1N 3L7",
    "addr:housenumber":"5598",
    "addr:postcode":"h1n 3l7",
    "addr:street":"Rue Hochelaga",
    "iso:country":"CA",
    "sg:address":"5598 Rue Hochelaga",
    "sg:city":"Montreal",
    "sg:classifiers":[
        {
            "category":"Manufacturing",
            "subcategory":"Metals",
            "type":"Manufacturing & Wholesale Goods"
        }
    ],
    "sg:phone":"+1 514 526 0894",
    "sg:postcode":"H1N 3L7",
    "sg:province":"QC",
    "sg:tags":[
        "shelter",
        "garage",
        "canopy",
        "temporary",
        "awning"
    ],
    "wof:name":"Bellon Industries Inc",
    "wof:placetype":"venue"
},
  "geometry": {"coordinates":[-73.53872699999999,45.568253],"type":"Point"}
}