{
  "type": "Feature",
  "properties": {
    "addr:full":"60 Aberdeen Ave Sarnia ON N7S 2N8",
    "addr:housenumber":"60",
    "addr:postcode":"n7s 2n8",
    "addr:street":"Aberdeen Ave",
    "iso:country":"CA",
    "sg:address":"60 Aberdeen Ave",
    "sg:city":"Sarnia",
    "sg:classifiers":[
        {
            "category":"Education",
            "subcategory":"School",
            "type":"Public Place"
        }
    ],
    "sg:phone":"+1 519 344 0801",
    "sg:postcode":"N7S 2N8",
    "sg:province":"ON",
    "wof:name":"Queen Elizabeth II School",
    "wof:placetype":"venue"
},
  "geometry": {"coordinates":[-82.373604,42.971252],"type":"Point"}
}