{
  "type": "Feature",
  "properties": {
    "addr:full":"2900 Boul Le Corbusier # 100 Laval QC H7L 3M2",
    "addr:housenumber":"2900",
    "addr:postcode":"h7l 3m2",
    "addr:street":"Boul Le Corbusier # 100",
    "iso:country":"CA",
    "sg:address":"2900 Boul Le Corbusier # 100",
    "sg:city":"Laval",
    "sg:classifiers":[
        {
            "category":"Home & Garden",
            "subcategory":"Building Materials",
            "type":"Retail Goods"
        }
    ],
    "sg:phone":"+1 450 681 2900",
    "sg:postcode":"H7L 3M2",
    "sg:province":"QC",
    "sg:tags":[
        "glass",
        "window",
        "plate"
    ],
    "wof:name":"Lehoux Vitres D'Autos & Access",
    "wof:placetype":"venue"
},
  "geometry": {"coordinates":[-73.748672,45.582134],"type":"Point"}
}