{
  "type": "Feature",
  "properties": {
    "addr:full":"2504 Rue King O Sherbrooke QC J1J 2E8",
    "addr:housenumber":"2504",
    "addr:postcode":"j1j 2e8",
    "addr:street":"Rue King O",
    "iso:country":"CA",
    "sg:address":"2504 Rue King O",
    "sg:city":"Sherbrooke",
    "sg:classifiers":[
        {
            "category":"Shopping",
            "subcategory":"Clothing, Apparel, & Fashions",
            "type":"Retail Goods"
        }
    ],
    "sg:phone":"+1 819 564 3993",
    "sg:postcode":"J1J 2E8",
    "sg:province":"QC",
    "sg:tags":[
        "work",
        "shoes"
    ],
    "wof:name":"Entrepot Du Travailleur",
    "wof:placetype":"venue"
},
  "geometry": {"coordinates":[-71.93338799999999,45.398125],"type":"Point"}
}