{
  "type": "Feature",
  "properties": {
    "addr:full":"1068 Davie St Vancouver BC V6E 1M3",
    "addr:housenumber":"1068",
    "addr:postcode":"v6e 1m3",
    "addr:street":"Davie St",
    "iso:country":"CA",
    "sg:address":"1068 Davie St",
    "sg:city":"Vancouver",
    "sg:classifiers":[
        {
            "category":"Restaurant",
            "type":"Food & Drink"
        }
    ],
    "sg:phone":"+1 604 689 0208",
    "sg:postcode":"V6E 1M3",
    "sg:province":"BC",
    "wof:name":"Dish",
    "wof:placetype":"venue"
},
  "geometry": {"coordinates":[-123.130653,49.279842],"type":"Point"}
}