{
  "type": "Feature",
  "properties": {
    "addr:full":"15 Pigeon Lake Rd Lindsay ON K9V 4R6",
    "addr:housenumber":"15",
    "addr:postcode":"k9v 4r6",
    "addr:street":"Pigeon Lake Rd",
    "iso:country":"CA",
    "sg:address":"15 Pigeon Lake Rd",
    "sg:city":"Lindsay",
    "sg:classifiers":[
        {
            "category":"Freight",
            "type":"Transportation"
        }
    ],
    "sg:phone":"+1 705 324 5431",
    "sg:postcode":"K9V 4R6",
    "sg:province":"ON",
    "sg:tags":[
        "mover"
    ],
    "wof:name":"Lindsay Movers & Storage",
    "wof:placetype":"venue"
},
  "geometry": {"coordinates":[-78.7169036865,44.3622245789],"type":"Point"}
}