{
  "type": "Feature",
  "properties": {
    "addr:full":"9319 60 Ave NW Edmonton AB T6E 0C2",
    "addr:housenumber":"9319",
    "addr:postcode":"t6e 0c2",
    "addr:street":"60 Ave Nw",
    "iso:country":"CA",
    "sg:address":"9319 60 Ave NW",
    "sg:city":"Edmonton",
    "sg:classifiers":[
        {
            "category":"Freight",
            "type":"Transportation"
        }
    ],
    "sg:phone":"+1 780 433 2076",
    "sg:postcode":"T6E 0C2",
    "sg:province":"AB",
    "sg:tags":[
        "trucking"
    ],
    "wof:name":"Jpt Trucking Inc",
    "wof:placetype":"venue"
},
  "geometry": {"coordinates":[-113.47154235799999,53.4956436157],"type":"Point"}
}