{
  "type": "Feature",
  "properties": {
    "addr:full":"101 Fairview Dr Moncton NB E1E 3C9",
    "addr:housenumber":"101",
    "addr:postcode":"e1e 3c9",
    "addr:street":"Fairview Dr",
    "iso:country":"CA",
    "sg:address":"101 Fairview Dr",
    "sg:city":"Moncton",
    "sg:classifiers":[
        {
            "category":"Organizations",
            "subcategory":"Religious Organization",
            "type":"Services"
        }
    ],
    "sg:phone":"+1 506 382 7725",
    "sg:postcode":"E1E 3C9",
    "sg:province":"NB",
    "sg:tags":[
        "church"
    ],
    "wof:name":"St James Anglican Church",
    "wof:placetype":"venue"
},
  "geometry": {"coordinates":[-64.8013000488,46.0857124329],"type":"Point"}
}