{
  "type": "Feature",
  "properties": {
    "addr:full":"4326 Smith Rd St-Louis PE C0B 1Z0",
    "addr:housenumber":"4326",
    "addr:postcode":"c0b 1z0",
    "addr:street":"Smith Rd",
    "iso:country":"CA",
    "sg:address":"4326 Smith Rd",
    "sg:city":"St-Louis",
    "sg:classifiers":[
        {
            "category":"Retail",
            "subcategory":"Repair Shop",
            "type":"Services"
        }
    ],
    "sg:phone":"+1 902 882 3454",
    "sg:postcode":"C0B 1Z0",
    "sg:province":"PE",
    "sg:tags":[
        "upholsterer"
    ],
    "wof:name":"Doucette Upholstery",
    "wof:placetype":"venue"
},
  "geometry": {"coordinates":[-64.1410903931,46.8868141174],"type":"Point"}
}