{
  "type": "Feature",
  "properties": {
    "addr:full":"805 Kraft Creek Rd Timmins ON P4N 7C3",
    "addr:housenumber":"805",
    "addr:postcode":"p4n 7c3",
    "addr:street":"Kraft Creek Rd",
    "iso:country":"CA",
    "sg:address":"805 Kraft Creek Rd",
    "sg:city":"Timmins",
    "sg:classifiers":[
        {
            "category":"Building & Trades",
            "subcategory":"Construction",
            "type":"Services"
        }
    ],
    "sg:phone":"+1 705 267 1742",
    "sg:postcode":"P4N 7C3",
    "sg:province":"ON",
    "sg:tags":[
        "pole",
        "line",
        "contractor"
    ],
    "wof:name":"High Line Power Inc",
    "wof:placetype":"venue"
},
  "geometry": {"coordinates":[-81.4022369385,48.5303153992],"type":"Point"}
}