{
  "type": "Feature",
  "properties": {
    "addr:full":"Westlock AB T7P 2K4",
    "addr:postcode":"t7p 2k4",
    "iso:country":"CA",
    "sg:city":"Westlock",
    "sg:classifiers":[
        {
            "category":"Health Services",
            "subcategory":"Doctor",
            "type":"Services"
        }
    ],
    "sg:phone":"+1 780 349 3341",
    "sg:postcode":"T7P 2K4",
    "sg:province":"AB",
    "sg:tags":[
        "physician",
        "clinic",
        "surgeon"
    ],
    "wof:name":"Associate Medical Clinic",
    "wof:placetype":"venue"
},
  "geometry": {"coordinates":[-113.860626,54.155376],"type":"Point"}
}