{
  "type": "Feature",
  "properties": {
    "iso:country":"CA",
    "sg:address":"494 Maple Leaf Dr",
    "sg:city":"North York",
    "sg:classifiers":[
        {
            "category":"Retail",
            "subcategory":"Laundry & Dry Cleaning",
            "type":"Services"
        }
    ],
    "sg:phone":"+1 416 241 9441",
    "sg:postcode":"M6L 1R4",
    "sg:province":"ON",
    "sg:tags":[
        "cleaners",
        "rug",
        "carpet"
    ],
    "wof:name":"Aqua Dry Mississauga",
    "wof:placetype":"venue"
},
  "geometry": {"coordinates":[-79.4767379761,43.7155838013],"type":"Point"}
}