{
  "type": "Feature",
  "properties": {
    "addr:full":"9501 Boul Gouin O Pierrefonds QC H8Y 1T7",
    "addr:housenumber":"9501",
    "addr:postcode":"h8y 1t7",
    "addr:street":"Boul Gouin O",
    "iso:country":"CA",
    "sg:address":"9501 Boul Gouin O",
    "sg:city":"Pierrefonds",
    "sg:classifiers":[
        {
            "category":"Organizations",
            "subcategory":"Religious Organization",
            "type":"Services"
        }
    ],
    "sg:phone":"+1 514 684 0951",
    "sg:postcode":"H8Y 1T7",
    "sg:province":"QC",
    "sg:tags":[
        "church"
    ],
    "wof:name":"Ste Suzanne Paroisses",
    "wof:placetype":"venue"
},
  "geometry": {"coordinates":[-73.7751235962,45.5061225891],"type":"Point"}
}