{
  "type": "Feature",
  "properties": {
    "addr:full":"Red Deer AB T4N 5G6",
    "addr:postcode":"t4n 5g6",
    "iso:country":"CA",
    "sg:city":"Red Deer",
    "sg:classifiers":[
        {
            "category":"Mining & Drilling",
            "type":"Manufacturing & Wholesale Goods"
        }
    ],
    "sg:phone":"+1 403 347 2122",
    "sg:postcode":"T4N 5G6",
    "sg:province":"AB",
    "sg:tags":[
        "field",
        "oil"
    ],
    "wof:name":"Lariat Trucking & Hot Shot Svc",
    "wof:placetype":"venue"
},
  "geometry": {"coordinates":[-113.817436218,52.2623023987],"type":"Point"}
}