{
  "type": "Feature",
  "properties": {
    "iso:country":"CA",
    "sg:address":"565 Second Line E",
    "sg:city":"Sault Ste Marie",
    "sg:classifiers":[
        {
            "category":"Building & Trades",
            "subcategory":"Construction",
            "type":"Services"
        }
    ],
    "sg:phone":"+1 705 254 3661",
    "sg:postcode":"P6B 4K2",
    "sg:province":"ON",
    "sg:tags":[
        "excavating",
        "contractor"
    ],
    "wof:name":"Phillips Haulage",
    "wof:placetype":"venue"
},
  "geometry": {"coordinates":[-84.3243255615,46.5381164551],"type":"Point"}
}