{
  "type": "Feature",
  "properties": {
    "addr:full":"2535 7 Ave NE Calgary AB T2A 7R2",
    "addr:postcode":"2535;t2a 7r2",
    "addr:street":"7 Ave Ne",
    "iso:country":"CA",
    "sg:address":"2535 7 Ave NE",
    "sg:city":"Calgary",
    "sg:classifiers":[
        {
            "category":"Health Services",
            "subcategory":"Chiropractor",
            "type":"Services"
        }
    ],
    "sg:phone":"+1 403 248 7775",
    "sg:postcode":"T2A 7R2",
    "sg:province":"AB",
    "wof:name":"Barlow Chiropractic Ctr",
    "wof:placetype":"venue"
},
  "geometry": {"coordinates":[-114.000229,51.058388],"type":"Point"}
}