{
  "type": "Feature",
  "properties": {
    "iso:country":"CA",
    "sg:address":"371 Rue Montcalm",
    "sg:city":"Chicoutimi",
    "sg:classifiers":[
        {
            "category":"Home & Garden",
            "subcategory":"Household Appliances",
            "type":"Retail Goods"
        }
    ],
    "sg:phone":"+1 418 696 3537",
    "sg:postcode":"G7J 2V2",
    "sg:province":"QC",
    "wof:name":"Mp-Refrigeration Enr",
    "wof:placetype":"venue"
},
  "geometry": {"coordinates":[-71.07122039790001,48.4276695251],"type":"Point"}
}