{
  "type": "Feature",
  "properties": {
    "addr:full":"Sydney NS B1P 5K6",
    "addr:postcode":"b1p 5k6",
    "iso:country":"CA",
    "sg:city":"Sydney",
    "sg:classifiers":[
        {
            "category":"Shopping",
            "subcategory":"Clothing, Apparel, & Fashions",
            "type":"Retail Goods"
        }
    ],
    "sg:phone":"+1 902 539 6282",
    "sg:postcode":"B1P 5K6",
    "sg:province":"NS",
    "wof:name":"Eclipse",
    "wof:placetype":"venue"
},
  "geometry": {"coordinates":[-60.18642,46.139217],"type":"Point"}
}