{
  "type": "Feature",
  "properties": {
    "addr:full":"Montreal QC H3H 2R9",
    "addr:postcode":"h3h 2r9",
    "iso:country":"CA",
    "sg:city":"Montreal",
    "sg:classifiers":[
        {
            "category":"Banks & Credit Unions",
            "subcategory":"Investment Brokerage",
            "type":"Services"
        }
    ],
    "sg:phone":"+1 514 932 2332",
    "sg:postcode":"H3H 2R9",
    "sg:province":"QC",
    "sg:tags":[
        "consultant",
        "planning",
        "financial"
    ],
    "wof:name":"Financiere Nashtone",
    "wof:placetype":"venue"
},
  "geometry": {"coordinates":[-73.58013916020001,45.4960975647],"type":"Point"}
}