{
  "type": "Feature",
  "properties": {
    "addr:full":"990 3E Rue Chibougamau QC G8P 1R7",
    "addr:housenumber":"990",
    "addr:postcode":"g8p 1r7",
    "addr:street":"3E Rue",
    "iso:country":"CA",
    "sg:address":"990 3E Rue",
    "sg:city":"Chibougamau",
    "sg:classifiers":[
        {
            "category":"Restaurant",
            "type":"Food & Drink"
        }
    ],
    "sg:phone":"+1 418 748 2114",
    "sg:postcode":"G8P 1R7",
    "sg:province":"QC",
    "wof:name":"Restaurant Le Rustique",
    "wof:placetype":"venue"
},
  "geometry": {"coordinates":[-74.3858795166,49.9054718018],"type":"Point"}
}