{
  "type": "Feature",
  "properties": {
    "addr:full":"5302 Dundas St W Etobicoke ON M9B 1B2",
    "addr:housenumber":"5302",
    "addr:postcode":"m9b 1b2",
    "addr:street":"Dundas St W",
    "iso:country":"CA",
    "sg:address":"5302 Dundas St W",
    "sg:city":"Etobicoke",
    "sg:classifiers":[
        {
            "category":"Communications",
            "subcategory":"Radio Station",
            "type":"Services"
        }
    ],
    "sg:phone":"+1 905 751 0761",
    "sg:postcode":"M9B 1B2",
    "sg:province":"ON",
    "sg:tags":[
        "company",
        "broadcasting"
    ],
    "wof:name":"Ckdx",
    "wof:placetype":"venue"
},
  "geometry": {"coordinates":[-79.540047,43.636425],"type":"Point"}
}