{
  "type": "Feature",
  "properties": {
    "addr:full":"Scarborough ON M1S 3L2",
    "addr:postcode":"m1s 3l2",
    "iso:country":"CA",
    "sg:city":"Scarborough",
    "sg:classifiers":[
        {
            "category":"Professional",
            "subcategory":"Business Services",
            "type":"Services"
        }
    ],
    "sg:phone":"+1 416 292 7471",
    "sg:postcode":"M1S 3L2",
    "sg:province":"ON",
    "sg:tags":[
        "embroidery"
    ],
    "wof:name":"King's Embroidery Ltd",
    "wof:placetype":"venue"
},
  "geometry": {"coordinates":[-79.253258,43.794765],"type":"Point"}
}