{
  "type": "Feature",
  "properties": {
    "addr:full":"985 Dundas St E Mississauga ON L4Y 2B9",
    "addr:housenumber":"985",
    "addr:postcode":"l4y 2b9",
    "addr:street":"Dundas St E",
    "iso:country":"CA",
    "sg:address":"985 Dundas St E",
    "sg:city":"Mississauga",
    "sg:classifiers":[
        {
            "category":"Banks & Credit Unions",
            "subcategory":"Bank",
            "type":"Services"
        }
    ],
    "sg:phone":"+1 905 279 6530",
    "sg:postcode":"L4Y 2B9",
    "sg:province":"ON",
    "wof:name":"Bank of Montreal",
    "wof:placetype":"venue"
},
  "geometry": {"coordinates":[-79.5930938721,43.6011734009],"type":"Point"}
}