{
  "type": "Feature",
  "properties": {
    "addr:full":"1209 8th St W Nipawin SK S0E 1E0",
    "addr:housenumber":"1209",
    "addr:postcode":"s0e 1e0",
    "addr:street":"8Th St W Nipawin",
    "iso:country":"CA",
    "sg:address":"1209 8th St W",
    "sg:city":"Nipawin",
    "sg:classifiers":[
        {
            "category":"Retail",
            "subcategory":"Self-service Laundry",
            "type":"Services"
        }
    ],
    "sg:phone":"+1 306 862 3155",
    "sg:postcode":"S0E 1E0",
    "sg:province":"SK",
    "sg:tags":[
        "polishing",
        "car",
        "washing"
    ],
    "wof:name":"Double L Car Wash",
    "wof:placetype":"venue"
},
  "geometry": {"coordinates":[-104.026611328,53.3531494141],"type":"Point"}
}