{
  "type": "Feature",
  "properties": {
    "addr:full":"1621 Barton St E Hamilton ON L8H 7R7",
    "addr:housenumber":"1621",
    "addr:postcode":"l8h 7r7",
    "addr:street":"Barton St E",
    "iso:country":"CA",
    "sg:address":"1621 Barton St E",
    "sg:city":"Hamilton",
    "sg:classifiers":[
        {
            "category":"Organizations",
            "subcategory":"Professional Association",
            "type":"Services"
        }
    ],
    "sg:phone":"+1 905 549 1722",
    "sg:postcode":"L8H 7R7",
    "sg:province":"ON",
    "sg:tags":[
        "boxing",
        "instruction"
    ],
    "wof:name":"Mc Grory's Boxing Club",
    "wof:placetype":"venue"
},
  "geometry": {"coordinates":[-79.793465,43.246174],"type":"Point"}
}