{
  "type": "Feature",
  "properties": {
    "addr:full":"100 Sidney Belsey Cres North York ON M6M 5H6",
    "addr:housenumber":"100",
    "addr:postcode":"m6m 5h6",
    "addr:street":"Sidney Belsey Cres",
    "iso:country":"CA",
    "sg:address":"100 Sidney Belsey Cres",
    "sg:city":"North York",
    "sg:classifiers":[
        {
            "category":"Education",
            "subcategory":"School",
            "type":"Public Place"
        }
    ],
    "sg:phone":"+1 416 394 4333",
    "sg:postcode":"M6M 5H6",
    "sg:province":"ON",
    "wof:name":"Portage Trail Jcs",
    "wof:placetype":"venue"
},
  "geometry": {"coordinates":[-79.50950622560001,43.6919517517],"type":"Point"}
}