{
  "type": "Feature",
  "properties": {
    "iso:country":"CA",
    "sg:address":"10643 123 St NW",
    "sg:city":"Edmonton",
    "sg:classifiers":[
        {
            "category":"Restaurant",
            "type":"Food & Drink"
        }
    ],
    "sg:phone":"+1 780 482 7178",
    "sg:postcode":"T5N 1P3",
    "sg:province":"AB",
    "wof:name":"Blue Pear Restaurant",
    "wof:placetype":"venue"
},
  "geometry": {"coordinates":[-113.533905029,53.550075531],"type":"Point"}
}