{
  "type": "Feature",
  "properties": {
    "addr:full":"150 Main St Cambridge ON N1R 6P9",
    "addr:housenumber":"150",
    "addr:postcode":"n1r 6p9",
    "addr:street":"Main St",
    "iso:country":"CA",
    "sg:address":"150 Main St",
    "sg:city":"Cambridge",
    "sg:classifiers":[
        {
            "category":"Professional",
            "subcategory":"Business Services",
            "type":"Services"
        }
    ],
    "sg:phone":"+1 519 624 9718",
    "sg:postcode":"N1R 6P9",
    "sg:province":"ON",
    "sg:tags":[
        "paralegal"
    ],
    "wof:name":"Ticket Defense",
    "wof:placetype":"venue"
},
  "geometry": {"coordinates":[-80.3104476929,43.3589782715],"type":"Point"}
}