{
  "type": "Feature",
  "properties": {
    "addr:full":"260 Main St Parkhill ON N0M 2K0",
    "addr:housenumber":"260",
    "addr:postcode":"n0m 2k0",
    "addr:street":"Main St",
    "iso:country":"CA",
    "sg:address":"260 Main St",
    "sg:city":"Parkhill",
    "sg:classifiers":[
        {
            "category":"Shopping",
            "subcategory":"Discount & Variety Stores",
            "type":"Retail Goods"
        }
    ],
    "sg:phone":"+1 519 294 0600",
    "sg:postcode":"N0M 2K0",
    "sg:province":"ON",
    "wof:name":"Parkhill Variety & Video",
    "wof:placetype":"venue"
},
  "geometry": {"coordinates":[-81.6833267212,43.1645507812],"type":"Point"}
}