{
  "type": "Feature",
  "properties": {
    "addr:full":"Alban ON P0M 1A0",
    "addr:postcode":"p0m 1a0",
    "iso:country":"CA",
    "sg:city":"Alban",
    "sg:classifiers":[
        {
            "category":"Wholesale",
            "subcategory":"Auto Parts",
            "type":"Manufacturing & Wholesale Goods"
        }
    ],
    "sg:phone":"+1 705 857 2626",
    "sg:postcode":"P0M 1A0",
    "sg:province":"ON",
    "sg:tags":[
        "automobile",
        "wrecking"
    ],
    "wof:name":"Andy's Towing & Wrecking",
    "wof:placetype":"venue"
},
  "geometry": {"coordinates":[-80.6227111816,46.1047058105],"type":"Point"}
}