{
  "type": "Feature",
  "properties": {
    "addr:full":"2225 Chapman St Merritt BC V1K 1B8",
    "addr:housenumber":"2225",
    "addr:postcode":"v1k 1b8",
    "addr:street":"Chapman St",
    "iso:country":"CA",
    "sg:address":"2225 Chapman St",
    "sg:city":"Merritt",
    "sg:classifiers":[
        {
            "category":"Building & Trades",
            "subcategory":"Construction",
            "type":"Services"
        }
    ],
    "sg:phone":"+1 250 378 5988",
    "sg:postcode":"V1K 1B8",
    "sg:province":"BC",
    "sg:tags":[
        "contractor"
    ],
    "wof:name":"Ken Nicholls Construction Ltd",
    "wof:placetype":"venue"
},
  "geometry": {"coordinates":[-120.79023742699999,50.1135444641],"type":"Point"}
}