{
  "type": "Feature",
  "properties": {
    "iso:country":"CA",
    "sg:address":"7632 17th Ave",
    "sg:city":"Coleman",
    "sg:classifiers":[
        {
            "category":"Retail",
            "subcategory":"Veterinary Services",
            "type":"Services"
        }
    ],
    "sg:phone":"+1 403 562 8380",
    "sg:postcode":"T0K 0M0",
    "sg:province":"AB",
    "sg:tags":[
        "veterinarian"
    ],
    "wof:name":"Crowsnest Pass Veterinary Clnc",
    "wof:placetype":"venue"
},
  "geometry": {"coordinates":[-114.50386047400001,49.6336555481],"type":"Point"}
}