{
  "type": "Feature",
  "properties": {
    "addr:full":"6004 53 St Taber AB T1G 1K4",
    "addr:housenumber":"6004",
    "addr:postcode":"t1g 1k4",
    "addr:street":"53 St",
    "iso:country":"CA",
    "sg:address":"6004 53 St",
    "sg:city":"Taber",
    "sg:classifiers":[
        {
            "category":"Professional",
            "subcategory":"Business Services",
            "type":"Services"
        }
    ],
    "sg:phone":"+1 403 382 9440",
    "sg:postcode":"T1G 1K4",
    "sg:province":"AB",
    "sg:tags":[
        "water",
        "hauling"
    ],
    "wof:name":"Greg's Fresh Water Hauling",
    "wof:placetype":"venue"
},
  "geometry": {"coordinates":[-112.144768,49.796631],"type":"Point"}
}