{
  "type": "Feature",
  "properties": {
    "addr:full":"2940 Patterson St Armstrong BC V0E 1B1",
    "addr:housenumber":"2940",
    "addr:postcode":"v0e 1b1",
    "addr:street":"Patterson St",
    "iso:country":"CA",
    "sg:address":"2940 Patterson St",
    "sg:city":"Armstrong",
    "sg:classifiers":[
        {
            "category":"Government",
            "subcategory":"Office",
            "type":"Public Place"
        }
    ],
    "sg:phone":"+1 250 546 9586",
    "sg:postcode":"V0E 1B1",
    "sg:province":"BC",
    "sg:tags":[
        "village"
    ],
    "wof:name":"Armstrong Public Works",
    "wof:placetype":"venue"
},
  "geometry": {"coordinates":[-119.196990967,50.4466285706],"type":"Point"}
}