{
  "type": "Feature",
  "properties": {
    "addr:full":"Calgary AB T2E 6V2",
    "addr:postcode":"t2e 6v2",
    "iso:country":"CA",
    "sg:city":"Calgary",
    "sg:classifiers":[
        {
            "category":"Wholesale",
            "subcategory":"Furniture",
            "type":"Manufacturing & Wholesale Goods"
        }
    ],
    "sg:phone":"+1 403 291 3166",
    "sg:postcode":"T2E 6V2",
    "sg:province":"AB",
    "sg:tags":[
        "gymnasium",
        "equipment",
        "seating",
        "company",
        "supply"
    ],
    "wof:name":"Kilroe & Associates Ltd",
    "wof:placetype":"venue"
},
  "geometry": {"coordinates":[-114.011497498,51.0852661133],"type":"Point"}
}