{
  "type": "Feature",
  "properties": {
    "addr:full":"Saint-Jean-Sur-Richelieu QC J3B 1W5",
    "addr:postcode":"j3b 1w5",
    "iso:country":"CA",
    "sg:city":"Saint-Jean-Sur-Richelieu",
    "sg:classifiers":[
        {
            "category":"Real Estate",
            "subcategory":"Real Estate Operator",
            "type":"Services"
        }
    ],
    "sg:phone":"+1 450 348 0935",
    "sg:postcode":"J3B 1W5",
    "sg:province":"QC",
    "sg:tags":[
        "mall",
        "shopping",
        "center"
    ],
    "wof:name":"Halles St-Jean",
    "wof:placetype":"venue"
},
  "geometry": {"coordinates":[-73.259277,45.314548],"type":"Point"}
}