{
  "type": "Feature",
  "properties": {
    "addr:full":"1681 Lake Shore Blvd E Toronto ON M4L 3W6",
    "addr:housenumber":"1681",
    "addr:postcode":"m4l 3w6",
    "addr:street":"Lake Shore Blvd E",
    "iso:country":"CA",
    "sg:address":"1681 Lake Shore Blvd E",
    "sg:city":"Toronto",
    "sg:classifiers":[
        {
            "category":"Restaurant",
            "type":"Food & Drink"
        }
    ],
    "sg:phone":"+1 416 694 8844",
    "sg:postcode":"M4L 3W6",
    "sg:province":"ON",
    "wof:name":"Boardwalk Cafe",
    "wof:placetype":"venue"
},
  "geometry": {"coordinates":[-79.3089752197,43.6634025574],"type":"Point"}
}