{
  "type": "Feature",
  "properties": {
    "addr:full":"260 Rue Du Parc Saint-Joseph-DE-Beauce QC G0S 2V0",
    "addr:housenumber":"260",
    "addr:postcode":"g0s 2v0",
    "addr:street":"Rue Du Parc",
    "iso:country":"CA",
    "sg:address":"260 Rue Du Parc",
    "sg:city":"Saint-Joseph-DE-Beauce",
    "sg:classifiers":[
        {
            "category":"Manufacturing",
            "subcategory":"Furniture",
            "type":"Manufacturing & Wholesale Goods"
        }
    ],
    "sg:phone":"+1 418 397 6851",
    "sg:postcode":"G0S 2V0",
    "sg:province":"QC",
    "wof:name":"Industries Sitraco Inc",
    "wof:placetype":"venue"
},
  "geometry": {"coordinates":[-70.86177062989999,46.2975234985],"type":"Point"}
}