{
  "type": "Feature",
  "properties": {
    "addr:full":"1084 Central Ave Prince Albert SK S6V 7P3",
    "addr:housenumber":"1084",
    "addr:postcode":"s6v 7p3",
    "addr:street":"Central Ave",
    "iso:country":"CA",
    "sg:address":"1084 Central Ave",
    "sg:city":"Prince Albert",
    "sg:classifiers":[
        {
            "category":"Government",
            "subcategory":"Office",
            "type":"Public Place"
        }
    ],
    "sg:phone":"+1 306 953 4300",
    "sg:postcode":"S6V 7P3",
    "sg:province":"SK",
    "sg:tags":[
        "village"
    ],
    "wof:name":"Prince Albert Mayor's Office",
    "wof:placetype":"venue"
},
  "geometry": {"coordinates":[-105.754043579,53.2032699585],"type":"Point"}
}