{
  "type": "Feature",
  "properties": {
    "addr:full":"130 Keedian Dr East St Paul MB R2E 0K3",
    "addr:housenumber":"130",
    "addr:postcode":"r2e 0k3",
    "addr:street":"Keedian Dr",
    "iso:country":"CA",
    "sg:address":"130 Keedian Dr",
    "sg:city":"East St Paul",
    "sg:classifiers":[
        {
            "category":"Wholesale",
            "subcategory":"Electrical",
            "type":"Manufacturing & Wholesale Goods"
        }
    ],
    "sg:phone":"+1 204 668 2783",
    "sg:postcode":"R2E 0K3",
    "sg:province":"MB",
    "sg:tags":[
        "battery"
    ],
    "wof:name":"Tony Pawlowski Ventures Ltd",
    "wof:placetype":"venue"
},
  "geometry": {"coordinates":[-97.00224300000001,49.968422],"type":"Point"}
}