{
  "type": "Feature",
  "properties": {
    "addr:full":"2555 Pleasant Valley Rd Armstrong BC V0E 1B2",
    "addr:housenumber":"2555",
    "addr:postcode":"v0e 1b2",
    "addr:street":"Pleasant Valley Rd",
    "iso:country":"CA",
    "sg:address":"2555 Pleasant Valley Rd",
    "sg:city":"Armstrong",
    "sg:classifiers":[
        {
            "category":"Real Estate",
            "subcategory":"Real Estate Agent",
            "type":"Services"
        }
    ],
    "sg:phone":"+1 250 546 3119",
    "sg:postcode":"V0E 1B2",
    "sg:province":"BC",
    "wof:name":"Re/Max Armstrong",
    "wof:placetype":"venue"
},
  "geometry": {"coordinates":[-119.20592499999999,50.439835],"type":"Point"}
}