{
  "type": "Feature",
  "properties": {
    "addr:full":"1305 Boul Pie-Xi S Val-Belair QC G3K 1H3",
    "addr:housenumber":"1305",
    "addr:postcode":"g3k 1h3",
    "addr:street":"Boul Pie-Xi S Val-Belair",
    "iso:country":"CA",
    "sg:address":"1305 Boul Pie-Xi S",
    "sg:city":"Val-Belair",
    "sg:classifiers":[
        {
            "category":"Building & Trades",
            "subcategory":"Construction",
            "type":"Services"
        }
    ],
    "sg:phone":"+1 418 842 7642",
    "sg:postcode":"G3K 1H3",
    "sg:province":"QC",
    "sg:tags":[
        "designer",
        "dealer",
        "pool",
        "swimming"
    ],
    "wof:name":"Concept Piscine Design Enr",
    "wof:placetype":"venue"
},
  "geometry": {"coordinates":[-71.40089399999999,46.847599],"type":"Point"}
}