{
  "type": "Feature",
  "properties": {
    "addr:full":"13025 112 St NW Edmonton AB T5E 6E4",
    "addr:housenumber":"13025",
    "addr:postcode":"t5e 6e4",
    "addr:street":"112 St Nw",
    "iso:country":"CA",
    "sg:address":"13025 112 St NW",
    "sg:city":"Edmonton",
    "sg:classifiers":[
        {
            "category":"Personal",
            "type":"Services"
        }
    ],
    "sg:phone":"+1 780 451 9171",
    "sg:postcode":"T5E 6E4",
    "sg:province":"AB",
    "sg:tags":[
        "therapist",
        "massage"
    ],
    "wof:name":"Bodywise Massage Therapy",
    "wof:placetype":"venue"
},
  "geometry": {"coordinates":[-113.513351,53.590416],"type":"Point"}
}