{
  "type": "Feature",
  "properties": {
    "addr:full":"3331 Robinson Rd North Vancouver BC V7J 3P7",
    "addr:housenumber":"3331",
    "addr:postcode":"v7j 3p7",
    "addr:street":"Robinson Rd",
    "iso:country":"CA",
    "sg:address":"3331 Robinson Rd",
    "sg:city":"North Vancouver",
    "sg:classifiers":[
        {
            "category":"Building & Trades",
            "subcategory":"Construction",
            "type":"Services"
        }
    ],
    "sg:phone":"+1 604 980 3080",
    "sg:postcode":"V7J 3P7",
    "sg:province":"BC",
    "sg:tags":[
        "general",
        "contractor"
    ],
    "wof:name":"Best Boarding & Taping CO Ltd",
    "wof:placetype":"venue"
},
  "geometry": {"coordinates":[-123.02110290500001,49.3402481079],"type":"Point"}
}