{
  "type": "Feature",
  "properties": {
    "addr:full":"1771 Boul Cure-Labelle Laval QC H7T 1L1",
    "addr:housenumber":"1771",
    "addr:postcode":"h7t 1l1",
    "addr:street":"Boul Cure-Labelle",
    "iso:country":"CA",
    "sg:address":"1771 Boul Cure-Labelle",
    "sg:city":"Laval",
    "sg:classifiers":[
        {
            "category":"Retail",
            "subcategory":"Auto Repair",
            "type":"Services"
        }
    ],
    "sg:phone":"+1 450 681 2216",
    "sg:postcode":"H7T 1L1",
    "sg:province":"QC",
    "sg:tags":[
        "lettering",
        "truck"
    ],
    "wof:name":"Peintures Eurotek Inc",
    "wof:placetype":"venue"
},
  "geometry": {"coordinates":[-73.760925,45.553131],"type":"Point"}
}