{
  "type": "Feature",
  "properties": {
    "addr:full":"1130 Boul Saint-Joseph Roberval QC G8H 2L9",
    "addr:housenumber":"1130",
    "addr:postcode":"g8h 2l9",
    "addr:street":"Boul Saint-Joseph",
    "iso:country":"CA",
    "sg:address":"1130 Boul Saint-Joseph",
    "sg:city":"Roberval",
    "sg:classifiers":[
        {
            "category":"Organizations",
            "subcategory":"Professional Association",
            "type":"Services"
        }
    ],
    "sg:phone":"+1 418 275 4723",
    "sg:postcode":"G8H 2L9",
    "sg:province":"QC",
    "wof:name":"Club DE L'Age D'Or Les Aines",
    "wof:placetype":"venue"
},
  "geometry": {"coordinates":[-72.22229799999999,48.525436],"type":"Point"}
}