{
  "type": "Feature",
  "properties": {
    "addr:full":"Waterloo ON N2J 4N3",
    "addr:postcode":"n2j 4n3",
    "iso:country":"CA",
    "sg:city":"Waterloo",
    "sg:classifiers":[
        {
            "category":"Real Estate",
            "subcategory":"Real Estate Operator",
            "type":"Services"
        }
    ],
    "sg:phone":"+1 519 746 6888",
    "sg:postcode":"N2J 4N3",
    "sg:province":"ON",
    "sg:tags":[
        "apartment"
    ],
    "wof:name":"Lincoln Towers",
    "wof:placetype":"venue"
},
  "geometry": {"coordinates":[-80.51232899999999,43.472],"type":"Point"}
}