{
  "type": "Feature",
  "properties": {
    "addr:full":"318 King St E Kingston ON K7L 3B4",
    "addr:housenumber":"318",
    "addr:postcode":"k7l 3b4",
    "addr:street":"King St E",
    "iso:country":"CA",
    "sg:address":"318 King St E",
    "sg:city":"Kingston",
    "sg:classifiers":[
        {
            "category":"Restaurant",
            "type":"Food & Drink"
        }
    ],
    "sg:phone":"+1 613 542 9483",
    "sg:postcode":"K7L 3B4",
    "sg:province":"ON",
    "wof:name":"Morrison's Restaurant",
    "wof:placetype":"venue"
},
  "geometry": {"coordinates":[-76.481613,44.230171],"type":"Point"}
}