{
  "type": "Feature",
  "properties": {
    "iso:country":"CA",
    "sg:address":"2390 Boul Rosemont",
    "sg:city":"Montreal",
    "sg:classifiers":[
        {
            "category":"Personal",
            "subcategory":"Beauty Salon",
            "type":"Services"
        }
    ],
    "sg:phone":"+1 514 271 8028",
    "sg:postcode":"H2G 1V1",
    "sg:province":"QC",
    "wof:name":"Coiffure Francine & Paul Inc",
    "wof:placetype":"venue"
},
  "geometry": {"coordinates":[-73.586777,45.545616],"type":"Point"}
}