{
  "type": "Feature",
  "properties": {
    "addr:full":"2390 Boul Rosemont Montreal QC H2G 1V1",
    "addr:housenumber":"2390",
    "addr:postcode":"h2g 1v1",
    "addr:street":"Boul Rosemont",
    "iso:country":"CA",
    "sg:address":"2390 Boul Rosemont",
    "sg:city":"Montreal",
    "sg:classifiers":[
        {
            "category":"Personal",
            "subcategory":"Beauty Salon",
            "type":"Services"
        }
    ],
    "sg:phone":"+1 514 271 8028",
    "sg:postcode":"H2G 1V1",
    "sg:province":"QC",
    "wof:name":"Coiffure Francine & Paul Inc",
    "wof:placetype":"venue"
},
  "geometry": {"coordinates":[-73.586777,45.545616],"type":"Point"}
}