{
  "type": "Feature",
  "properties": {
    "addr:full":"Lindsay ON K9V 4R1",
    "addr:postcode":"k9v 4r1",
    "iso:country":"CA",
    "sg:city":"Lindsay",
    "sg:classifiers":[
        {
            "category":"Restaurant",
            "type":"Food & Drink"
        }
    ],
    "sg:phone":"+1 705 324 6545",
    "sg:postcode":"K9V 4R1",
    "sg:province":"ON",
    "wof:name":"Airport View Restaurant",
    "wof:placetype":"venue"
},
  "geometry": {"coordinates":[-78.7753829956,44.3641090393],"type":"Point"}
}