{
  "type": "Feature",
  "properties": {
    "addr:full":"2 Wilby Cres York ON M9N 1E5",
    "addr:housenumber":"2",
    "addr:postcode":"m9n 1e5",
    "addr:street":"Wilby Cres",
    "iso:country":"CA",
    "sg:address":"2 Wilby Cres",
    "sg:city":"York",
    "sg:classifiers":[
        {
            "category":"Manufacturing",
            "subcategory":"Tools & Machinery",
            "type":"Manufacturing & Wholesale Goods"
        }
    ],
    "sg:phone":"+1 416 235 1211",
    "sg:postcode":"M9N 1E5",
    "sg:province":"ON",
    "sg:tags":[
        "lighting",
        "fixture"
    ],
    "wof:name":"Lights of Canada Inc",
    "wof:placetype":"venue"
},
  "geometry": {"coordinates":[-79.51149700000001,43.698269],"type":"Point"}
}