{
  "type": "Feature",
  "properties": {
    "addr:full":"503 42 Ave SE Calgary AB T2G 1Y7",
    "addr:housenumber":"503",
    "addr:postcode":"t2g 1y7",
    "addr:street":"42 Ave Se",
    "iso:country":"CA",
    "sg:address":"503 42 Ave SE",
    "sg:city":"Calgary",
    "sg:classifiers":[
        {
            "category":"Wholesale",
            "subcategory":"Machinery & Supplies",
            "type":"Manufacturing & Wholesale Goods"
        }
    ],
    "sg:phone":"+1 403 243 3261",
    "sg:postcode":"T2G 1Y7",
    "sg:province":"AB",
    "sg:tags":[
        "transmission",
        "equipment",
        "power",
        "bearing"
    ],
    "wof:name":"Transmission Supplies Ltd",
    "wof:placetype":"venue"
},
  "geometry": {"coordinates":[-114.05281829800001,51.0157241821],"type":"Point"}
}