{
  "type": "Feature",
  "properties": {
    "addr:full":"629 Alexander Ave Winnipeg MB R3A 0P3",
    "addr:housenumber":"629",
    "addr:postcode":"r3a 0p3",
    "addr:street":"Alexander Ave",
    "iso:country":"CA",
    "sg:address":"629 Alexander Ave",
    "sg:city":"Winnipeg",
    "sg:classifiers":[
        {
            "category":"Wholesale",
            "subcategory":"Hardware",
            "type":"Manufacturing & Wholesale Goods"
        }
    ],
    "sg:phone":"+1 204 774 8388",
    "sg:postcode":"R3A 0P3",
    "sg:province":"MB",
    "sg:tags":[
        "equipment",
        "furnace",
        "heating",
        "system"
    ],
    "wof:name":"Recon Controls Ltd",
    "wof:placetype":"venue"
},
  "geometry": {"coordinates":[-97.152512,49.906895],"type":"Point"}
}