{
  "type": "Feature",
  "properties": {
    "iso:country":"CA",
    "sg:city":"Abbotsford",
    "sg:classifiers":[
        {
            "category":"Health Services",
            "subcategory":"Doctor",
            "type":"Services"
        }
    ],
    "sg:phone":"+1 604 853 3314",
    "sg:postcode":"V2S 3N9",
    "sg:province":"BC",
    "sg:tags":[
        "physician",
        "surgeon"
    ],
    "wof:name":"Scaman, Donald L MD",
    "wof:placetype":"venue"
},
  "geometry": {"coordinates":[-122.293434,49.040859],"type":"Point"}
}