{
  "type": "Feature",
  "properties": {
    "iso:country":"CA",
    "sg:address":"107 Judson St",
    "sg:city":"Etobicoke",
    "sg:classifiers":[
        {
            "category":"Building & Trades",
            "subcategory":"Construction",
            "type":"Services"
        }
    ],
    "sg:phone":"+1 416 503 1887",
    "sg:postcode":"M8Z 1A4",
    "sg:province":"ON",
    "sg:tags":[
        "roofing",
        "contractor"
    ],
    "wof:name":"Sproule Specialty Roofing Ltd",
    "wof:placetype":"venue"
},
  "geometry": {"coordinates":[-79.5050582886,43.6142845154],"type":"Point"}
}