{
  "type": "Feature",
  "properties": {
    "addr:full":"37 Greystone Cres Brampton ON L6Y 2B2",
    "addr:housenumber":"37",
    "addr:postcode":"l6y 2b2",
    "addr:street":"Greystone Cres",
    "iso:country":"CA",
    "sg:address":"37 Greystone Cres",
    "sg:city":"Brampton",
    "sg:classifiers":[
        {
            "category":"Building & Trades",
            "subcategory":"Construction",
            "type":"Services"
        }
    ],
    "sg:phone":"+1 905 459 5010",
    "sg:postcode":"L6Y 2B2",
    "sg:province":"ON",
    "sg:tags":[
        "concrete",
        "contractor"
    ],
    "wof:name":"Bav Contracting",
    "wof:placetype":"venue"
},
  "geometry": {"coordinates":[-79.7518463135,43.6695747375],"type":"Point"}
}