{
  "type": "Feature",
  "properties": {
    "addr:full":"50 Featherstone Ave Markham ON L3S 2H4",
    "addr:housenumber":"50",
    "addr:postcode":"l3s 2h4",
    "addr:street":"Featherstone Ave",
    "iso:country":"CA",
    "sg:address":"50 Featherstone Ave",
    "sg:city":"Markham",
    "sg:classifiers":[
        {
            "category":"Education",
            "subcategory":"School",
            "type":"Public Place"
        }
    ],
    "sg:phone":"+1 905 472 2420",
    "sg:postcode":"L3S 2H4",
    "sg:province":"ON",
    "wof:name":"St Vincent DE Paul Catholic",
    "wof:placetype":"venue"
},
  "geometry": {"coordinates":[-79.26899,43.840023],"type":"Point"}
}