{
  "type": "Feature",
  "properties": {
    "addr:full":"186 Rue Champlain Saint-Jean-Sur-Richelieu QC J3B 6V6",
    "addr:housenumber":"186",
    "addr:postcode":"j3b 6v6",
    "addr:street":"Rue Champlain",
    "iso:country":"CA",
    "sg:address":"186 Rue Champlain",
    "sg:city":"Saint-Jean-Sur-Richelieu",
    "sg:classifiers":[
        {
            "category":"Retail",
            "subcategory":"Repair Shop",
            "type":"Services"
        }
    ],
    "sg:phone":"+1 450 346 7249",
    "sg:postcode":"J3B 6V6",
    "sg:province":"QC",
    "sg:tags":[
        "upholsterer"
    ],
    "wof:name":"Atelier Albert",
    "wof:placetype":"venue"
},
  "geometry": {"coordinates":[-73.252281,45.305653],"type":"Point"}
}