{
  "type": "Feature",
  "properties": {
    "iso:country":"CA",
    "sg:address":"21 Surrey St W",
    "sg:city":"Guelph",
    "sg:classifiers":[
        {
            "category":"Health Services",
            "subcategory":"Medical Lab",
            "type":"Services"
        }
    ],
    "sg:phone":"+1 519 767 2165",
    "sg:postcode":"N1H 3R3",
    "sg:province":"ON",
    "sg:tags":[
        "laboratory"
    ],
    "wof:name":"Canadian Medical Laboratories",
    "wof:placetype":"venue"
},
  "geometry": {"coordinates":[-80.246201,43.540398],"type":"Point"}
}