{
  "type": "Feature",
  "properties": {
    "addr:full":"57 Rue Lacharite Saint-Francois-Du-Lac QC J0G 1M0",
    "addr:housenumber":"57",
    "addr:postcode":"j0g 1m0",
    "addr:street":"Rue Lacharite Saint-Francois-Du-Lac",
    "iso:country":"CA",
    "sg:address":"57 Rue Lacharite",
    "sg:city":"Saint-Francois-Du-Lac",
    "sg:classifiers":[
        {
            "category":"Manufacturing",
            "subcategory":"Tools & Machinery",
            "type":"Manufacturing & Wholesale Goods"
        }
    ],
    "sg:phone":"+1 450 568 1047",
    "sg:postcode":"J0G 1M0",
    "sg:province":"QC",
    "sg:tags":[
        "machine",
        "shop"
    ],
    "wof:name":"Usinage Game",
    "wof:placetype":"venue"
},
  "geometry": {"coordinates":[-72.823471,46.060673],"type":"Point"}
}