{
  "type": "Feature",
  "properties": {
    "addr:full":"4239 Petrolia Line Petrolia ON N0N 1R0",
    "addr:housenumber":"4239",
    "addr:postcode":"n0n 1r0",
    "addr:street":"Petrolia Line",
    "iso:country":"CA",
    "sg:address":"4239 Petrolia Line",
    "sg:city":"Petrolia",
    "sg:classifiers":[
        {
            "category":"Health Services",
            "subcategory":"Podiatrist",
            "type":"Services"
        }
    ],
    "sg:phone":"+1 519 882 0019",
    "sg:postcode":"N0N 1R0",
    "sg:province":"ON",
    "wof:name":"Petrolia Foot Clinic",
    "wof:placetype":"venue"
},
  "geometry": {"coordinates":[-82.14432499999999,42.881802],"type":"Point"}
}