{
  "type": "Feature",
  "properties": {
    "addr:full":"1025 York Rd Niagara on the Lake ON L0S 1J0",
    "addr:housenumber":"1025",
    "addr:postcode":"l0s 1j0",
    "addr:street":"York Rd;On",
    "iso:country":"CA",
    "sg:address":"1025 York Rd",
    "sg:city":"Niagara on the Lake",
    "sg:classifiers":[
        {
            "category":"Manufacturing",
            "subcategory":"Food",
            "type":"Manufacturing & Wholesale Goods"
        }
    ],
    "sg:phone":"+1 905 262 4219",
    "sg:postcode":"L0S 1J0",
    "sg:province":"ON",
    "sg:tags":[
        "winery"
    ],
    "wof:name":"Chateau Des Charmes Wines Ltd",
    "wof:placetype":"venue"
},
  "geometry": {"coordinates":[-79.127701,43.157455],"type":"Point"}
}