{
  "type": "Feature",
  "properties": {
    "addr:full":"10501 20th Ave Blairmore AB T0K 0E0",
    "addr:housenumber":"10501",
    "addr:postcode":"t0k 0e0",
    "addr:street":"20Th Ave",
    "iso:country":"CA",
    "sg:address":"10501 20th Ave",
    "sg:city":"Blairmore",
    "sg:classifiers":[
        {
            "category":"Education",
            "subcategory":"College",
            "type":"Public Place"
        }
    ],
    "sg:phone":"+1 403 562 2853",
    "sg:postcode":"T0K 0E0",
    "sg:province":"AB",
    "sg:tags":[
        "academic",
        "school"
    ],
    "wof:name":"Chinook Educational Consortium",
    "wof:placetype":"venue"
},
  "geometry": {"coordinates":[-114.463684,49.619884],"type":"Point"}
}