{
  "type": "Feature",
  "properties": {
    "iso:country":"CA",
    "sg:address":"18 Industrial St",
    "sg:city":"Guelph",
    "sg:classifiers":[
        {
            "category":"Manufacturing",
            "subcategory":"Printing",
            "type":"Manufacturing & Wholesale Goods"
        }
    ],
    "sg:phone":"+1 519 823 2411",
    "sg:postcode":"N1E 6B8",
    "sg:province":"ON",
    "sg:tags":[
        "designer",
        "graphic",
        "printer"
    ],
    "wof:name":"Infinite Images Graphics Ctr",
    "wof:placetype":"venue"
},
  "geometry": {"coordinates":[-80.2212677002,43.5545196533],"type":"Point"}
}