{
  "type": "Feature",
  "properties": {
    "iso:country":"CA",
    "sg:address":"13560 106 Ave",
    "sg:city":"Surrey",
    "sg:classifiers":[
        {
            "category":"Building & Trades",
            "subcategory":"Plumbing",
            "type":"Services"
        }
    ],
    "sg:phone":"+1 604 581 2717",
    "sg:postcode":"V3T 2C5",
    "sg:province":"BC",
    "sg:tags":[
        "sheet",
        "work",
        "metal",
        "heating",
        "contractor"
    ],
    "wof:name":"Nicolson Heating & Metal Works",
    "wof:placetype":"venue"
},
  "geometry": {"coordinates":[-122.834152222,49.1951789856],"type":"Point"}
}