{
  "type": "Feature",
  "properties": {
    "addr:full":"218 7E Av Dolbeau-Mistassini QC G8L 2Z2",
    "addr:housenumber":"218",
    "addr:postcode":"g8l 2z2",
    "addr:street":"7E Av Dolbeau-Mistassini",
    "iso:country":"CA",
    "sg:address":"218 7E Av",
    "sg:city":"Dolbeau-Mistassini",
    "sg:classifiers":[
        {
            "category":"Travel",
            "subcategory":"Hotels & Motels",
            "type":"Entertainment"
        }
    ],
    "sg:phone":"+1 418 276 0797",
    "sg:postcode":"G8L 2Z2",
    "sg:province":"QC",
    "wof:name":"Hotel Motel Maison Blanche",
    "wof:placetype":"venue"
},
  "geometry": {"coordinates":[-72.230949,48.880016],"type":"Point"}
}