{
  "type": "Feature",
  "properties": {
    "addr:full":"8170 120 St Surrey BC V3W 3N3",
    "addr:housenumber":"8170",
    "addr:postcode":"v3w 3n3",
    "addr:street":"120 St",
    "iso:country":"CA",
    "sg:address":"8170 120 St",
    "sg:city":"Surrey",
    "sg:classifiers":[
        {
            "category":"Restaurant",
            "type":"Food & Drink"
        }
    ],
    "sg:phone":"+1 604 596 4994",
    "sg:postcode":"V3W 3N3",
    "sg:province":"BC",
    "wof:name":"International House-Pancakes",
    "wof:placetype":"venue"
},
  "geometry": {"coordinates":[-122.89016700000001,49.151775],"type":"Point"}
}