{
  "type": "Feature",
  "properties": {
    "addr:full":"3365 Fairview St Burlington ON L7N 3N9",
    "addr:housenumber":"3365",
    "addr:postcode":"l7n 3n9",
    "addr:street":"Fairview St",
    "iso:country":"CA",
    "sg:address":"3365 Fairview St",
    "sg:city":"Burlington",
    "sg:classifiers":[
        {
            "category":"Banks & Credit Unions",
            "subcategory":"Bank",
            "type":"Services"
        }
    ],
    "sg:phone":"+1 905 634 2900",
    "sg:postcode":"L7N 3N9",
    "sg:province":"ON",
    "wof:name":"Bank of Montreal",
    "wof:placetype":"venue"
},
  "geometry": {"coordinates":[-79.7851867676,43.3546524048],"type":"Point"}
}