{
  "type": "Feature",
  "properties": {
    "iso:country":"CA",
    "sg:address":"165 Simcoe St S",
    "sg:city":"Oshawa",
    "sg:classifiers":[
        {
            "category":"Restaurant",
            "type":"Food & Drink"
        }
    ],
    "sg:phone":"+1 905 571 1010",
    "sg:postcode":"L1H 4G8",
    "sg:province":"ON",
    "wof:name":"Free Topping Pizza",
    "wof:placetype":"venue"
},
  "geometry": {"coordinates":[-78.8615722656,43.893196106],"type":"Point"}
}