{
  "type": "Feature",
  "properties": {
    "addr:full":"165 Simcoe St S Oshawa ON L1H 4G8",
    "addr:housenumber":"165",
    "addr:postcode":"l1h 4g8",
    "addr:street":"Simcoe St S",
    "iso:country":"CA",
    "sg:address":"165 Simcoe St S",
    "sg:city":"Oshawa",
    "sg:classifiers":[
        {
            "category":"Restaurant",
            "type":"Food & Drink"
        }
    ],
    "sg:phone":"+1 905 571 1010",
    "sg:postcode":"L1H 4G8",
    "sg:province":"ON",
    "wof:name":"Free Topping Pizza",
    "wof:placetype":"venue"
},
  "geometry": {"coordinates":[-78.8615722656,43.893196106],"type":"Point"}
}