{
  "type": "Feature",
  "properties": {
    "addr:full":"1328 Topsail Rd Paradise NL A1L 1P2",
    "addr:housenumber":"1328",
    "addr:postcode":"a1l 1p2",
    "addr:street":"Topsail Rd",
    "iso:country":"CA",
    "sg:address":"1328 Topsail Rd",
    "sg:city":"Paradise",
    "sg:classifiers":[
        {
            "category":"Building & Trades",
            "subcategory":"Construction",
            "type":"Services"
        }
    ],
    "sg:phone":"+1 709 782 1711",
    "sg:postcode":"A1L 1P2",
    "sg:province":"NL",
    "sg:tags":[
        "maker",
        "cabinet"
    ],
    "wof:name":"NU-Way Kitchens Ltd",
    "wof:placetype":"venue"
},
  "geometry": {"coordinates":[-52.8470611572,47.5350189209],"type":"Point"}
}