{
  "type": "Feature",
  "properties": {
    "addr:full":"1715 Woodstock Rd Fredericton NB E3C 1L4",
    "addr:housenumber":"1715",
    "addr:postcode":"e3c 1l4",
    "addr:street":"Woodstock Rd",
    "iso:country":"CA",
    "sg:address":"1715 Woodstock Rd",
    "sg:city":"Fredericton",
    "sg:classifiers":[
        {
            "category":"Autos & Motor Vehicles",
            "subcategory":"Fuel & Gas Station",
            "type":"Retail Goods"
        }
    ],
    "sg:phone":"+1 506 450 9915",
    "sg:postcode":"E3C 1L4",
    "sg:province":"NB",
    "sg:tags":[
        "oil"
    ],
    "wof:name":"By Pass Esso",
    "wof:placetype":"venue"
},
  "geometry": {"coordinates":[-66.72235107420001,45.9674301147],"type":"Point"}
}