{
  "type": "Feature",
  "properties": {
    "addr:full":"4205 Roy St Saint-Antoine-Abbe QC J0S 1N0",
    "addr:housenumber":"4205",
    "addr:postcode":"j0s 1n0",
    "addr:street":"Roy St",
    "iso:country":"CA",
    "sg:address":"4205 Roy St",
    "sg:city":"Saint-Antoine-Abbe",
    "sg:classifiers":[
        {
            "category":"Wholesale",
            "subcategory":"Fruits & Vegetables",
            "type":"Manufacturing & Wholesale Goods"
        }
    ],
    "sg:phone":"+1 450 827 2589",
    "sg:postcode":"J0S 1N0",
    "sg:province":"QC",
    "sg:tags":[
        "shipper"
    ],
    "wof:name":"Pommes Phillip Cassidy Inc",
    "wof:placetype":"venue"
},
  "geometry": {"coordinates":[-73.88910675050001,45.0512542725],"type":"Point"}
}