{
  "type": "Feature",
  "properties": {
    "addr:full":"671 Regent St E Mount Brydges ON N0L 1W0",
    "addr:housenumber":"671",
    "addr:postcode":"n0l 1w0",
    "addr:street":"Regent St E",
    "iso:country":"CA",
    "sg:address":"671 Regent St E",
    "sg:city":"Mount Brydges",
    "sg:classifiers":[
        {
            "category":"Home & Garden",
            "subcategory":"Household Appliances",
            "type":"Retail Goods"
        }
    ],
    "sg:phone":"+1 519 264 1102",
    "sg:postcode":"N0L 1W0",
    "sg:province":"ON",
    "wof:name":"Mount Brydges Appliance Svc",
    "wof:placetype":"venue"
},
  "geometry": {"coordinates":[-81.4965667725,42.9105567932],"type":"Point"}
}