{
  "type": "Feature",
  "properties": {
    "addr:full":"7188 King George Hwy Surrey BC V3W 5A3",
    "addr:housenumber":"7188",
    "addr:postcode":"v3w 5a3",
    "addr:street":"King George Hwy",
    "iso:country":"CA",
    "sg:address":"7188 King George Hwy",
    "sg:city":"Surrey",
    "sg:classifiers":[
        {
            "category":"Banks & Credit Unions",
            "subcategory":"Bank",
            "type":"Services"
        }
    ],
    "sg:phone":"+1 604 501 7075",
    "sg:postcode":"V3W 5A3",
    "sg:province":"BC",
    "wof:name":"Cibc",
    "wof:placetype":"venue"
},
  "geometry": {"coordinates":[-122.845505,49.133186],"type":"Point"}
}