{
  "type": "Feature",
  "properties": {
    "addr:full":"41 Breynat St Fort Smith NT X0E 0P0",
    "addr:housenumber":"41",
    "addr:postcode":"x0e 0p0",
    "addr:street":"Breynat St",
    "iso:country":"CA",
    "sg:address":"41 Breynat St",
    "sg:city":"Fort Smith",
    "sg:classifiers":[
        {
            "category":"Health Services",
            "subcategory":"Hospital",
            "type":"Services"
        }
    ],
    "sg:phone":"+1 867 872 6200",
    "sg:postcode":"X0E 0P0",
    "sg:province":"NT",
    "wof:name":"Fort Smith Health & Social Svc",
    "wof:placetype":"venue"
},
  "geometry": {"coordinates":[-111.90263400000001,60.000095],"type":"Point"}
}