{
  "type": "Feature",
  "properties": {
    "addr:full":"21 Steelwell Rd Brampton ON L6T 5P7",
    "addr:housenumber":"21",
    "addr:postcode":"l6t 5p7",
    "addr:street":"Steelwell Rd",
    "iso:country":"CA",
    "sg:address":"21 Steelwell Rd",
    "sg:city":"Brampton",
    "sg:classifiers":[
        {
            "category":"Manufacturing",
            "subcategory":"Wood Products",
            "type":"Manufacturing & Wholesale Goods"
        }
    ],
    "sg:phone":"+1 905 459 0775",
    "sg:postcode":"L6T 5P7",
    "sg:province":"ON",
    "sg:tags":[
        "pallet",
        "skid"
    ],
    "wof:name":"Bernie's Box & Pallet Ltd",
    "wof:placetype":"venue"
},
  "geometry": {"coordinates":[-79.704994,43.683861],"type":"Point"}
}