{
  "type": "Feature",
  "properties": {
    "iso:country":"CA",
    "sg:city":"Quebec",
    "sg:classifiers":[
        {
            "category":"Organizations",
            "subcategory":"Professional Association",
            "type":"Services"
        }
    ],
    "sg:phone":"+1 418 648 0246",
    "sg:postcode":"G1R 2L3",
    "sg:province":"QC",
    "wof:name":"Legion Royale Canadienne 260",
    "wof:placetype":"venue"
},
  "geometry": {"coordinates":[-71.214058,46.806404],"type":"Point"}
}