{
  "type": "Feature",
  "properties": {
    "iso:country":"CA",
    "sg:address":"1155 Rue Decarie",
    "sg:city":"Saint-Laurent",
    "sg:classifiers":[
        {
            "category":"Personal",
            "subcategory":"Shoe Repair & Shine",
            "type":"Services"
        }
    ],
    "sg:phone":"+1 514 747 6103",
    "sg:postcode":"H4L 3M8",
    "sg:province":"QC",
    "sg:tags":[
        "repairing",
        "boot"
    ],
    "wof:name":"Abba Cordonnerie",
    "wof:placetype":"venue"
},
  "geometry": {"coordinates":[-73.684372,45.515549],"type":"Point"}
}