{
  "type": "Feature",
  "properties": {
    "addr:full":"280 132 Rte W Saint-Andre-DE-Kamouraska QC G0L 2H0",
    "addr:housenumber":"132",
    "addr:postcode":"g0l 2h0",
    "addr:street":"Rte W Saint-Andre-De-Kamouraska",
    "iso:country":"CA",
    "sg:address":"280 132 Rte W",
    "sg:city":"Saint-Andre-DE-Kamouraska",
    "sg:classifiers":[
        {
            "category":"Travel",
            "subcategory":"Hotels & Motels",
            "type":"Entertainment"
        }
    ],
    "sg:phone":"+1 418 493 2495",
    "sg:postcode":"G0L 2H0",
    "sg:province":"QC",
    "sg:tags":[
        "inn"
    ],
    "wof:name":"Auberge Des Aboiteaux",
    "wof:placetype":"venue"
},
  "geometry": {"coordinates":[-69.7337341309,47.6705665588],"type":"Point"}
}