{
  "type": "Feature",
  "properties": {
    "addr:full":"Rosser MB R0H 1E0",
    "addr:postcode":"r0h 1e0",
    "iso:country":"CA",
    "sg:city":"Rosser",
    "sg:classifiers":[
        {
            "category":"Freight",
            "type":"Transportation"
        }
    ],
    "sg:phone":"+1 204 322 5575",
    "sg:postcode":"R0H 1E0",
    "sg:province":"MB",
    "sg:tags":[
        "trucking"
    ],
    "wof:name":"B & B Dueck Transport Svc Ltd",
    "wof:placetype":"venue"
},
  "geometry": {"coordinates":[-97.3417663574,49.9909629822],"type":"Point"}
}