{
  "type": "Feature",
  "properties": {
    "iso:country":"CA",
    "sg:address":"111 Lake Louise Dr # 1",
    "sg:city":"Lake Louise",
    "sg:classifiers":[
        {
            "category":"Shopping",
            "subcategory":"Bicycles & Sporting Goods",
            "type":"Retail Goods"
        }
    ],
    "sg:phone":"+1 403 522 3837",
    "sg:postcode":"T0L 1E0",
    "sg:province":"AB",
    "wof:name":"Monod Sports Ltd",
    "wof:placetype":"venue"
},
  "geometry": {"coordinates":[-116.212554932,51.4170303345],"type":"Point"}
}