{
  "type": "Feature",
  "properties": {
    "addr:full":"PO Box 97 Hagen SK S0J 1B0",
    "addr:housenumber":"po box 97",
    "addr:postcode":"s0j 1b0",
    "iso:country":"CA",
    "sg:address":"PO Box 97",
    "sg:city":"Hagen",
    "sg:classifiers":[
        {
            "category":"Organizations",
            "subcategory":"Religious Organization",
            "type":"Services"
        }
    ],
    "sg:phone":"+1 306 749 2487",
    "sg:postcode":"S0J 1B0",
    "sg:province":"SK",
    "sg:tags":[
        "church"
    ],
    "wof:name":"Saron Lutheran Church",
    "wof:placetype":"venue"
},
  "geometry": {"coordinates":[-105.558395386,52.9380683899],"type":"Point"}
}