{
  "type": "Feature",
  "properties": {
    "iso:country":"CA",
    "sg:address":"8897 Rue Lajeunesse",
    "sg:city":"Montreal",
    "sg:classifiers":[
        {
            "category":"Shopping",
            "subcategory":"Pharmacy",
            "type":"Retail Goods"
        }
    ],
    "sg:phone":"+1 514 382 5921",
    "sg:postcode":"H2M 1R8",
    "sg:province":"QC",
    "wof:name":"Paylan Yetvart Pharmaciens",
    "wof:placetype":"venue"
},
  "geometry": {"coordinates":[-73.641594,45.547649],"type":"Point"}
}