{
  "type": "Feature",
  "properties": {
    "addr:full":"130 Payne Rd Saturna BC V0N 2Y0",
    "addr:housenumber":"130",
    "addr:postcode":"v0n 2y0",
    "addr:street":"Payne Rd",
    "iso:country":"CA",
    "sg:address":"130 Payne Rd",
    "sg:city":"Saturna",
    "sg:classifiers":[
        {
            "category":"Travel",
            "subcategory":"Hotels & Motels",
            "type":"Entertainment"
        }
    ],
    "sg:phone":"+1 250 539 2254",
    "sg:postcode":"V0N 2Y0",
    "sg:province":"BC",
    "sg:tags":[
        "breakfast",
        "accommodation",
        "bed"
    ],
    "wof:name":"Saturna Lodge & Restaurant",
    "wof:placetype":"venue"
},
  "geometry": {"coordinates":[-123.198921204,48.786781311],"type":"Point"}
}