{
  "type": "Feature",
  "properties": {
    "addr:full":"97 Dufferin St Orillia ON L3V 5S9",
    "addr:housenumber":"97",
    "addr:postcode":"l3v 5s9",
    "addr:street":"Dufferin St",
    "iso:country":"CA",
    "sg:address":"97 Dufferin St",
    "sg:city":"Orillia",
    "sg:classifiers":[
        {
            "category":"Autos & Motor Vehicles",
            "subcategory":"Auto Supplies",
            "type":"Retail Goods"
        }
    ],
    "sg:phone":"+1 705 325 2771",
    "sg:postcode":"L3V 5S9",
    "sg:province":"ON",
    "sg:tags":[
        "body",
        "automobile",
        "parts",
        "shop"
    ],
    "wof:name":"Garage Supply Ltd",
    "wof:placetype":"venue"
},
  "geometry": {"coordinates":[-79.423553,44.60265],"type":"Point"}
}