{
  "type": "Feature",
  "properties": {
    "iso:country":"CA",
    "sg:address":"RR 3",
    "sg:city":"Princeton",
    "sg:classifiers":[
        {
            "category":"Building & Trades",
            "subcategory":"Electrical",
            "type":"Services"
        }
    ],
    "sg:phone":"+1 519 467 5329",
    "sg:postcode":"N0J 1V0",
    "sg:province":"ON",
    "sg:tags":[
        "electric",
        "contractor"
    ],
    "wof:name":"Ken Reading Electrical Contr",
    "wof:placetype":"venue"
},
  "geometry": {"coordinates":[-80.5275268555,43.1720085144],"type":"Point"}
}