{
  "type": "Feature",
  "properties": {
    "addr:full":"554 Rue King E Sherbrooke QC J1G 1B5",
    "addr:housenumber":"554",
    "addr:postcode":"j1g 1b5",
    "addr:street":"Rue King E",
    "iso:country":"CA",
    "sg:address":"554 Rue King E",
    "sg:city":"Sherbrooke",
    "sg:classifiers":[
        {
            "category":"Personal",
            "subcategory":"Beauty Salon",
            "type":"Services"
        }
    ],
    "sg:phone":"+1 819 346 5243",
    "sg:postcode":"J1G 1B5",
    "sg:province":"QC",
    "wof:name":"Salon DE Coiffure Vanessa",
    "wof:placetype":"venue"
},
  "geometry": {"coordinates":[-71.8768539429,45.4079475403],"type":"Point"}
}