{
  "type": "Feature",
  "properties": {
    "iso:country":"CA",
    "sg:address":"521 West 5th St",
    "sg:city":"Hamilton",
    "sg:classifiers":[
        {
            "category":"Recreation",
            "type":"Entertainment"
        }
    ],
    "sg:phone":"+1 905 389 6689",
    "sg:postcode":"L9C 3P7",
    "sg:province":"ON",
    "sg:tags":[
        "hall",
        "auditorium"
    ],
    "wof:name":"St Michel's Hungarian Greek",
    "wof:placetype":"venue"
},
  "geometry": {"coordinates":[-79.8869094849,43.2283096313],"type":"Point"}
}