{
  "type": "Feature",
  "properties": {
    "iso:country":"CA",
    "sg:address":"41 Rue Des Pilotes",
    "sg:city":"Les Escoumins",
    "sg:classifiers":[
        {
            "category":"Shopping",
            "subcategory":"Bicycles & Sporting Goods",
            "type":"Retail Goods"
        }
    ],
    "sg:phone":"+1 418 233 4242",
    "sg:postcode":"G0T 1K0",
    "sg:province":"QC",
    "wof:name":"Atlan Productions Inc",
    "wof:placetype":"venue"
},
  "geometry": {"coordinates":[-69.4152832031,48.3205909729],"type":"Point"}
}