{
  "type": "Feature",
  "properties": {
    "addr:full":"5032A 50th St Barrhead AB T7N 1A2",
    "addr:housenumber":"5032a",
    "addr:postcode":"t7n 1a2",
    "addr:street":"50Th St",
    "iso:country":"CA",
    "sg:address":"5032A 50th St",
    "sg:city":"Barrhead",
    "sg:classifiers":[
        {
            "category":"Shopping",
            "subcategory":"Jewelry",
            "type":"Retail Goods"
        }
    ],
    "sg:phone":"+1 780 674 5055",
    "sg:postcode":"T7N 1A2",
    "sg:province":"AB",
    "sg:tags":[
        "jeweler"
    ],
    "wof:name":"J S Jewellery Ltd",
    "wof:placetype":"venue"
},
  "geometry": {"coordinates":[-114.40630299999999,54.119537],"type":"Point"}
}