{
  "type": "Feature",
  "properties": {
    "addr:full":"Kelowna BC V1X 3H9",
    "addr:postcode":"v1x 3h9",
    "iso:country":"CA",
    "sg:city":"Kelowna",
    "sg:classifiers":[
        {
            "category":"Building & Trades",
            "subcategory":"Construction",
            "type":"Services"
        }
    ],
    "sg:phone":"+1 250 765 2978",
    "sg:postcode":"V1X 3H9",
    "sg:province":"BC",
    "sg:tags":[
        "repairing",
        "remodeling",
        "contractor"
    ],
    "wof:name":"Geralyn's Tub Enclosures",
    "wof:placetype":"venue"
},
  "geometry": {"coordinates":[-119.391235352,49.8870735168],"type":"Point"}
}