{
  "type": "Feature",
  "properties": {
    "iso:country":"CA",
    "sg:address":"561 6E Rue O",
    "sg:city":"Amos",
    "sg:classifiers":[
        {
            "category":"Wholesale",
            "subcategory":"Meat",
            "type":"Manufacturing & Wholesale Goods"
        }
    ],
    "sg:phone":"+1 819 732 2939",
    "sg:postcode":"J9T 2V3",
    "sg:province":"QC",
    "sg:tags":[
        "butchering"
    ],
    "wof:name":"Boucherie Julien Inc",
    "wof:placetype":"venue"
},
  "geometry": {"coordinates":[-78.11102294920001,48.5624465942],"type":"Point"}
}