{
  "type": "Feature",
  "properties": {
    "iso:country":"CA",
    "sg:city":"Dugald",
    "sg:classifiers":[
        {
            "category":"Retail",
            "subcategory":"Animal Services",
            "type":"Services"
        }
    ],
    "sg:phone":"+1 204 444 2566",
    "sg:postcode":"R0E 0K0",
    "sg:province":"MB",
    "sg:tags":[
        "horse",
        "training"
    ],
    "wof:name":"Don Rudko Training Stables",
    "wof:placetype":"venue"
},
  "geometry": {"coordinates":[-96.8401184082,49.8859062195],"type":"Point"}
}