{
  "type": "Feature",
  "properties": {
    "addr:full":"York ON M6N 4Z9",
    "addr:postcode":"m6n 4z9",
    "iso:country":"CA",
    "sg:city":"York",
    "sg:classifiers":[
        {
            "category":"Home & Garden",
            "subcategory":"Building Materials",
            "type":"Retail Goods"
        }
    ],
    "sg:phone":"+1 416 604 9450",
    "sg:postcode":"M6N 4Z9",
    "sg:province":"ON",
    "sg:tags":[
        "windows"
    ],
    "wof:name":"Terra Aluminum Products",
    "wof:placetype":"venue"
},
  "geometry": {"coordinates":[-79.47439575200001,43.6792106628],"type":"Point"}
}