{
  "type": "Feature",
  "properties": {
    "addr:full":"445 Kaleva Rd Sointula BC V0N 3E0",
    "addr:housenumber":"445",
    "addr:postcode":"v0n 3e0",
    "addr:street":"Kaleva Rd",
    "iso:country":"CA",
    "sg:address":"445 Kaleva Rd",
    "sg:city":"Sointula",
    "sg:classifiers":[
        {
            "category":"Travel",
            "subcategory":"Hotels & Motels",
            "type":"Entertainment"
        }
    ],
    "sg:phone":"+1 250 973 6381",
    "sg:postcode":"V0N 3E0",
    "sg:province":"BC",
    "sg:tags":[
        "resort"
    ],
    "wof:name":"Sund's Lodge",
    "wof:placetype":"venue"
},
  "geometry": {"coordinates":[-127.01764679,50.6280441284],"type":"Point"}
}