{
  "type": "Feature",
  "properties": {
    "addr:full":"360 Rue Saint-Jacques #1805 Montreal QC H2Y 1P5",
    "addr:housenumber":"360",
    "addr:postcode":"h2y 1p5",
    "addr:street":"Rue Saint-Jacques # 1805",
    "iso:country":"CA",
    "sg:address":"360 Rue Saint-Jacques #1805",
    "sg:city":"Montreal",
    "sg:classifiers":[
        {
            "category":"Travel",
            "subcategory":"Travel Agent",
            "type":"Entertainment"
        }
    ],
    "sg:phone":"+1 514 286 7559",
    "sg:postcode":"H2Y 1P5",
    "sg:province":"QC",
    "sg:tags":[
        "agency",
        "bureau"
    ],
    "wof:name":"Voyages Malavoy Inc",
    "wof:placetype":"venue"
},
  "geometry": {"coordinates":[-73.559425354,45.5022315979],"type":"Point"}
}