{
  "type": "Feature",
  "properties": {
    "addr:full":"2605 Kaslo St Vancouver BC V5M 3G9",
    "addr:housenumber":"2605",
    "addr:postcode":"v5m 3g9",
    "addr:street":"Kaslo St",
    "iso:country":"CA",
    "sg:address":"2605 Kaslo St",
    "sg:city":"Vancouver",
    "sg:classifiers":[
        {
            "category":"Wholesale",
            "subcategory":"Scrap",
            "type":"Manufacturing & Wholesale Goods"
        }
    ],
    "sg:phone":"+1 604 255 4243",
    "sg:postcode":"V5M 3G9",
    "sg:province":"BC",
    "sg:tags":[
        "recycling",
        "center"
    ],
    "wof:name":"East Vancouver Bottle Depot",
    "wof:placetype":"venue"
},
  "geometry": {"coordinates":[-123.047234,49.261169],"type":"Point"}
}