{
  "type": "Feature",
  "properties": {
    "addr:full":"1167 Victoria Park Ave Scarborough ON M4B 2K5",
    "addr:housenumber":"1167",
    "addr:postcode":"m4b 2k5",
    "addr:street":"Victoria Park Ave",
    "iso:country":"CA",
    "sg:address":"1167 Victoria Park Ave",
    "sg:city":"Scarborough",
    "sg:classifiers":[
        {
            "category":"Restaurant",
            "type":"Food & Drink"
        }
    ],
    "sg:phone":"+1 416 755 5766",
    "sg:postcode":"M4B 2K5",
    "sg:province":"ON",
    "wof:name":"Golden King Chinese Food",
    "wof:placetype":"venue"
},
  "geometry": {"coordinates":[-79.296364,43.710217],"type":"Point"}
}