{
  "type": "Feature",
  "properties": {
    "iso:country":"CA",
    "sg:address":"1705 Rue Denault",
    "sg:city":"Sherbrooke",
    "sg:classifiers":[
        {
            "category":"Retail",
            "subcategory":"Auto Repair",
            "type":"Services"
        }
    ],
    "sg:phone":"+1 819 822 4212",
    "sg:postcode":"J1K 1E9",
    "sg:province":"QC",
    "sg:tags":[
        "repairing",
        "automobile",
        "brake"
    ],
    "wof:name":"Uni Pro Denault",
    "wof:placetype":"venue"
},
  "geometry": {"coordinates":[-71.916786,45.388687],"type":"Point"}
}