{
  "type": "Feature",
  "properties": {
    "addr:full":"2341 Av DE LA Rotonde Charny QC G6X 2M2",
    "addr:housenumber":"2341",
    "addr:postcode":"g6x 2m2",
    "addr:street":"Av De La Rotonde",
    "iso:country":"CA",
    "sg:address":"2341 Av DE LA Rotonde",
    "sg:city":"Charny",
    "sg:classifiers":[
        {
            "category":"Home & Garden",
            "subcategory":"Hardware",
            "type":"Retail Goods"
        }
    ],
    "sg:phone":"+1 418 832 2918",
    "sg:postcode":"G6X 2M2",
    "sg:province":"QC",
    "sg:tags":[
        "saw",
        "machinery"
    ],
    "wof:name":"Scies Bgr Inc",
    "wof:placetype":"venue"
},
  "geometry": {"coordinates":[-71.263428,46.709381],"type":"Point"}
}