{
  "type": "Feature",
  "properties": {
    "iso:country":"CA",
    "sg:city":"Woodstock",
    "sg:classifiers":[
        {
            "category":"Health Services",
            "subcategory":"Doctor",
            "type":"Services"
        }
    ],
    "sg:phone":"+1 519 537 5052",
    "sg:postcode":"N4S 8W7",
    "sg:province":"ON",
    "sg:tags":[
        "physician",
        "surgeon"
    ],
    "wof:name":"Johnson, David MD",
    "wof:placetype":"venue"
},
  "geometry": {"coordinates":[-80.7484054565,43.1347236633],"type":"Point"}
}