{
  "type": "Feature",
  "properties": {
    "addr:full":"422 3rd St Estevan SK S4A 0P2",
    "addr:housenumber":"422",
    "addr:postcode":"s4a 0p2",
    "addr:street":"3Rd St",
    "iso:country":"CA",
    "sg:address":"422 3rd St",
    "sg:city":"Estevan",
    "sg:classifiers":[
        {
            "category":"Manufacturing",
            "subcategory":"Glass & Minerals",
            "type":"Manufacturing & Wholesale Goods"
        }
    ],
    "sg:phone":"+1 306 634 8210",
    "sg:postcode":"S4A 0P2",
    "sg:province":"SK",
    "sg:tags":[
        "refractory"
    ],
    "wof:name":"Max Refractory Svc",
    "wof:placetype":"venue"
},
  "geometry": {"coordinates":[-102.979912,49.133499],"type":"Point"}
}