{
  "type": "Feature",
  "properties": {
    "addr:full":"964 Kingston Rd Toronto ON M4E 1S7",
    "addr:housenumber":"964",
    "addr:postcode":"m4e 1s7",
    "addr:street":"Kingston Rd",
    "iso:country":"CA",
    "sg:address":"964 Kingston Rd",
    "sg:city":"Toronto",
    "sg:classifiers":[
        {
            "category":"Shopping",
            "subcategory":"Stationery & Office Supplies",
            "type":"Retail Goods"
        }
    ],
    "sg:phone":"+1 416 691 0924",
    "sg:postcode":"M4E 1S7",
    "sg:province":"ON",
    "sg:tags":[
        "stationer"
    ],
    "wof:name":"Randall S Stationery",
    "wof:placetype":"venue"
},
  "geometry": {"coordinates":[-79.2872924805,43.6806335449],"type":"Point"}
}