{
  "type": "Feature",
  "properties": {
    "addr:full":"782 Island Park Dr Ottawa ON K1Y 0C2",
    "addr:housenumber":"782",
    "addr:postcode":"k1y 0c2",
    "addr:street":"Island Park Dr",
    "iso:country":"CA",
    "sg:address":"782 Island Park Dr",
    "sg:city":"Ottawa",
    "sg:classifiers":[
        {
            "category":"Professional",
            "subcategory":"Business Services",
            "type":"Services"
        }
    ],
    "sg:phone":"+1 613 224 9662",
    "sg:postcode":"K1Y 0C2",
    "sg:province":"ON",
    "sg:tags":[
        "interior",
        "consultant",
        "design",
        "decorator"
    ],
    "wof:name":"Julia Brady Design",
    "wof:placetype":"venue"
},
  "geometry": {"coordinates":[-75.72717299999999,45.389534],"type":"Point"}
}