{
  "type": "Feature",
  "properties": {
    "addr:full":"Hearst ON P0L 1N0",
    "addr:postcode":"p0l 1n0",
    "iso:country":"CA",
    "sg:city":"Hearst",
    "sg:classifiers":[
        {
            "category":"Restaurant",
            "type":"Food & Drink"
        }
    ],
    "sg:phone":"+1 705 362 7362",
    "sg:postcode":"P0L 1N0",
    "sg:province":"ON",
    "wof:name":"Cafe Duo",
    "wof:placetype":"venue"
},
  "geometry": {"coordinates":[-83.685806,49.691494],"type":"Point"}
}