{
  "type": "Feature",
  "properties": {
    "addr:full":"7776 Boul Sainte-Anne E Chateau-Richer QC G0A 1N0",
    "addr:housenumber":"7776",
    "addr:postcode":"g0a 1n0",
    "addr:street":"Boul Sainte-Anne E Chateau-Richer",
    "iso:country":"CA",
    "sg:address":"7776 Boul Sainte-Anne E",
    "sg:city":"Chateau-Richer",
    "sg:classifiers":[
        {
            "category":"Personal",
            "subcategory":"Beauty Salon",
            "type":"Services"
        }
    ],
    "sg:phone":"+1 418 824 9597",
    "sg:postcode":"G0A 1N0",
    "sg:province":"QC",
    "wof:name":"Coiffure & Bronzage-St-Laurent",
    "wof:placetype":"venue"
},
  "geometry": {"coordinates":[-71.026245,46.964203],"type":"Point"}
}