{
  "type": "Feature",
  "properties": {
    "addr:full":"109 Boul D'Anjou Chateauguay QC J6J 2R2",
    "addr:housenumber":"109",
    "addr:postcode":"j6j 2r2",
    "addr:street":"Boul D'Anjou",
    "iso:country":"CA",
    "sg:address":"109 Boul D'Anjou",
    "sg:city":"Chateauguay",
    "sg:classifiers":[
        {
            "category":"Autos & Motor Vehicles",
            "subcategory":"Fuel & Gas Station",
            "type":"Retail Goods"
        }
    ],
    "sg:phone":"+1 450 691 1160",
    "sg:postcode":"J6J 2R2",
    "sg:province":"QC",
    "sg:tags":[
        "oil"
    ],
    "wof:name":"Car Wash Shell",
    "wof:placetype":"venue"
},
  "geometry": {"coordinates":[-73.74011230470001,45.3614845276],"type":"Point"}
}