{
  "type": "Feature",
  "properties": {
    "addr:full":"721 Woolwich St Guelph ON N1H 3Z2",
    "addr:housenumber":"721",
    "addr:postcode":"n1h 3z2",
    "addr:street":"Woolwich St",
    "iso:country":"CA",
    "sg:address":"721 Woolwich St",
    "sg:city":"Guelph",
    "sg:classifiers":[
        {
            "category":"Travel",
            "subcategory":"Hotels & Motels",
            "type":"Entertainment"
        }
    ],
    "sg:phone":"+1 519 836 1410",
    "sg:postcode":"N1H 3Z2",
    "sg:province":"ON",
    "wof:name":"Parkview Motel",
    "wof:placetype":"venue"
},
  "geometry": {"coordinates":[-80.273804,43.562618],"type":"Point"}
}