{
  "type": "Feature",
  "properties": {
    "addr:full":"1125 Derry Rd E Mississauga ON L5T 1P3",
    "addr:housenumber":"1125",
    "addr:postcode":"l5t 1p3",
    "addr:street":"Derry Rd E",
    "iso:country":"CA",
    "sg:address":"1125 Derry Rd E",
    "sg:city":"Mississauga",
    "sg:classifiers":[
        {
            "category":"Professional",
            "subcategory":"Business Services",
            "type":"Services"
        }
    ],
    "sg:phone":"+1 905 565 8363",
    "sg:postcode":"L5T 1P3",
    "sg:province":"ON",
    "sg:tags":[
        "packaging"
    ],
    "wof:name":"Footworks Distribution",
    "wof:placetype":"venue"
},
  "geometry": {"coordinates":[-79.68229700000001,43.668026],"type":"Point"}
}