{
  "type": "Feature",
  "properties": {
    "addr:full":"876 Montreal Rd #P Ottawa ON K1K 4L3",
    "addr:housenumber":"876",
    "addr:postcode":"k1k 4l3",
    "addr:street":"Montreal Rd # P",
    "iso:country":"CA",
    "sg:address":"876 Montreal Rd #P",
    "sg:city":"Ottawa",
    "sg:classifiers":[
        {
            "category":"Restaurant",
            "type":"Food & Drink"
        }
    ],
    "sg:phone":"+1 613 741 4657",
    "sg:postcode":"K1K 4L3",
    "sg:province":"ON",
    "wof:name":"Pilos Restaurant",
    "wof:placetype":"venue"
},
  "geometry": {"coordinates":[-75.630577,45.446167],"type":"Point"}
}