{
  "type": "Feature",
  "properties": {
    "addr:full":"896 Lanoie Upton QC J0H 2E0",
    "addr:housenumber":"896",
    "addr:postcode":"j0h 2e0",
    "addr:street":"Lanoie",
    "iso:country":"CA",
    "sg:address":"896 Lanoie",
    "sg:city":"Upton",
    "sg:classifiers":[
        {
            "category":"Shopping",
            "subcategory":"Discount & Variety Stores",
            "type":"Retail Goods"
        }
    ],
    "sg:phone":"+1 450 549 4676",
    "sg:postcode":"J0H 2E0",
    "sg:province":"QC",
    "sg:tags":[
        "merchandise",
        "general"
    ],
    "wof:name":"Blanchard, Gerard",
    "wof:placetype":"venue"
},
  "geometry": {"coordinates":[-72.69444300000001,45.649448],"type":"Point"}
}