{
  "type": "Feature",
  "properties": {
    "addr:full":"Abbotsford BC V2T 5T4",
    "addr:postcode":"v2t 5t4",
    "iso:country":"CA",
    "sg:city":"Abbotsford",
    "sg:classifiers":[
        {
            "category":"Professional",
            "subcategory":"Accounting & Tax Preparation",
            "type":"Services"
        }
    ],
    "sg:phone":"+1 604 853 2264",
    "sg:postcode":"V2T 5T4",
    "sg:province":"BC",
    "sg:tags":[
        "accountant"
    ],
    "wof:name":"Verigan, John D CA",
    "wof:placetype":"venue"
},
  "geometry": {"coordinates":[-122.31546,49.055634],"type":"Point"}
}