{
  "type": "Feature",
  "properties": {
    "addr:full":"127 Raleigh Ave Scarborough ON M1K 1A1",
    "addr:housenumber":"127",
    "addr:postcode":"m1k 1a1",
    "addr:street":"Raleigh Ave",
    "iso:country":"CA",
    "sg:address":"127 Raleigh Ave",
    "sg:city":"Scarborough",
    "sg:classifiers":[
        {
            "category":"Retail",
            "subcategory":"Auto Repair",
            "type":"Services"
        }
    ],
    "sg:phone":"+1 416 267 9577",
    "sg:postcode":"M1K 1A1",
    "sg:province":"ON",
    "sg:tags":[
        "body",
        "automobile",
        "painting"
    ],
    "wof:name":"Raleigh Auto Svc Ctr",
    "wof:placetype":"venue"
},
  "geometry": {"coordinates":[-79.26398500000001,43.704617],"type":"Point"}
}