{
  "type": "Feature",
  "properties": {
    "addr:full":"2871 Rte Bellevue Plessisville QC G6L 2Y4",
    "addr:housenumber":"2871",
    "addr:postcode":"g6l 2y4",
    "addr:street":"Rte Bellevue",
    "iso:country":"CA",
    "sg:address":"2871 Rte Bellevue",
    "sg:city":"Plessisville",
    "sg:classifiers":[
        {
            "category":"Farming",
            "subcategory":"Farm",
            "type":"Manufacturing & Wholesale Goods"
        }
    ],
    "sg:phone":"+1 819 362 9370",
    "sg:postcode":"G6L 2Y4",
    "sg:province":"QC",
    "wof:name":"Sylvain Vigneault Inc",
    "wof:placetype":"venue"
},
  "geometry": {"coordinates":[-71.792152,46.233349],"type":"Point"}
}