{
  "type": "Feature",
  "properties": {
    "iso:country":"CA",
    "sg:address":"617 3rd St W",
    "sg:city":"Stonewall",
    "sg:classifiers":[
        {
            "category":"Building & Trades",
            "subcategory":"Construction",
            "type":"Services"
        }
    ],
    "sg:phone":"+1 204 467 9321",
    "sg:postcode":"R0C 2Z0",
    "sg:province":"MB",
    "sg:tags":[
        "general",
        "contractor"
    ],
    "wof:name":"Murray Graydon Construction",
    "wof:placetype":"venue"
},
  "geometry": {"coordinates":[-97.330581665,50.1354255676],"type":"Point"}
}