{
  "type": "Feature",
  "properties": {
    "addr:full":"2710 Vigar Rd Campbell River BC V9W 6A3",
    "addr:housenumber":"2710",
    "addr:postcode":"v9w 6a3",
    "addr:street":"Vigar Rd",
    "iso:country":"CA",
    "sg:address":"2710 Vigar Rd",
    "sg:city":"Campbell River",
    "sg:classifiers":[
        {
            "category":"Wholesale",
            "subcategory":"Metals & Minerals",
            "type":"Manufacturing & Wholesale Goods"
        }
    ],
    "sg:phone":"+1 250 287 8841",
    "sg:postcode":"V9W 6A3",
    "sg:province":"BC",
    "sg:tags":[
        "steel",
        "warehouse"
    ],
    "wof:name":"A J Forsyth & CO Ltd",
    "wof:placetype":"venue"
},
  "geometry": {"coordinates":[-125.273453,50.043499],"type":"Point"}
}