{
  "type": "Feature",
  "properties": {
    "addr:full":"PO Box 67039 Rpo Northland Vlg Calgary AB T2L 2L2",
    "addr:housenumber":"po box",
    "addr:postcode":"67039;t2l 2l2",
    "iso:country":"CA",
    "sg:address":"PO Box 67039 Rpo Northland Vlg",
    "sg:city":"Calgary",
    "sg:classifiers":[
        {
            "category":"Real Estate",
            "subcategory":"Surveying",
            "type":"Services"
        }
    ],
    "sg:phone":"+1 403 297 0033",
    "sg:postcode":"T2L 2L2",
    "sg:province":"AB",
    "sg:tags":[
        "surveyor"
    ],
    "wof:name":"Hunter Survey Systems Ltd",
    "wof:placetype":"venue"
},
  "geometry": {"coordinates":[-114.063194,51.045074],"type":"Point"}
}