{
  "type": "Feature",
  "properties": {
    "iso:country":"CA",
    "sg:city":"Calgary",
    "sg:classifiers":[
        {
            "category":"Professional",
            "subcategory":"Business Services",
            "type":"Services"
        }
    ],
    "sg:phone":"+1 403 291 4115",
    "sg:postcode":"T2E 2P6",
    "sg:province":"AB",
    "sg:tags":[
        "appraiser"
    ],
    "wof:name":"Wernick Omura Ltd",
    "wof:placetype":"venue"
},
  "geometry": {"coordinates":[-114.062645,51.059875],"type":"Point"}
}