{
  "type": "Feature",
  "properties": {
    "addr:full":"630 Place Barriere Richelieu QC J3L 5P7",
    "addr:housenumber":"630",
    "addr:postcode":"j3l 5p7",
    "addr:street":"Place Barriere",
    "iso:country":"CA",
    "sg:address":"630 Place Barriere",
    "sg:city":"Richelieu",
    "sg:classifiers":[
        {
            "category":"Building & Trades",
            "subcategory":"Plumbing",
            "type":"Services"
        }
    ],
    "sg:phone":"+1 450 658 0237",
    "sg:postcode":"J3L 5P7",
    "sg:province":"QC",
    "sg:tags":[
        "contractor"
    ],
    "wof:name":"Plomberie Denis Vincelette",
    "wof:placetype":"venue"
},
  "geometry": {"coordinates":[-73.243904,45.439037],"type":"Point"}
}