{
  "type": "Feature",
  "properties": {
    "addr:full":"10351 Rue Renaude-Lapointe Anjou QC H1J 2T4",
    "addr:housenumber":"10351",
    "addr:postcode":"h1j 2t4",
    "addr:street":"Rue Renaude-Lapointe",
    "iso:country":"CA",
    "sg:address":"10351 Rue Renaude-Lapointe",
    "sg:city":"Anjou",
    "sg:classifiers":[
        {
            "category":"Wholesale",
            "subcategory":"Non-durable Goods",
            "type":"Manufacturing & Wholesale Goods"
        }
    ],
    "sg:phone":"+1 514 353 2689",
    "sg:postcode":"H1J 2T4",
    "sg:province":"QC",
    "sg:tags":[
        "yarn"
    ],
    "wof:name":"Titan Textile Canada Inc",
    "wof:placetype":"venue"
},
  "geometry": {"coordinates":[-73.58970600000001,45.611736],"type":"Point"}
}