{
  "type": "Feature",
  "properties": {
    "addr:full":"1040 Georgia St W #G3 Vancouver BC V6E 4H1",
    "addr:housenumber":"1040",
    "addr:postcode":"v6e 4h1",
    "addr:street":"Georgia St W # G3",
    "iso:country":"CA",
    "sg:address":"1040 Georgia St W #G3",
    "sg:city":"Vancouver",
    "sg:classifiers":[
        {
            "category":"Shopping",
            "subcategory":"Tobacco",
            "type":"Retail Goods"
        }
    ],
    "sg:phone":"+1 604 669 0453",
    "sg:postcode":"V6E 4H1",
    "sg:province":"BC",
    "sg:tags":[
        "cigarette",
        "cigar",
        "dealer"
    ],
    "wof:name":"Shefield & Sons Tobacconists",
    "wof:placetype":"venue"
},
  "geometry": {"coordinates":[-123.121971,49.284916],"type":"Point"}
}