{
  "type": "Feature",
  "properties": {
    "addr:full":"1999 Rue Sainte-Famille Jonquiere QC G7X 4X5",
    "addr:housenumber":"1999",
    "addr:postcode":"g7x 4x5",
    "addr:street":"Rue Sainte-Famille",
    "iso:country":"CA",
    "sg:address":"1999 Rue Sainte-Famille",
    "sg:city":"Jonquiere",
    "sg:classifiers":[
        {
            "category":"Bars & Pubs",
            "type":"Food & Drink"
        }
    ],
    "sg:phone":"+1 418 542 3642",
    "sg:postcode":"G7X 4X5",
    "sg:province":"QC",
    "sg:tags":[
        "lounge",
        "cocktail"
    ],
    "wof:name":"Bar Chez Pappy",
    "wof:placetype":"venue"
},
  "geometry": {"coordinates":[-71.237701,48.426537],"type":"Point"}
}