{
  "type": "Feature",
  "properties": {
    "addr:full":"Vancouver BC V6R 2H7",
    "addr:postcode":"v6r 2h7",
    "iso:country":"CA",
    "sg:city":"Vancouver",
    "sg:classifiers":[
        {
            "category":"Real Estate",
            "subcategory":"Real Estate Agent",
            "type":"Services"
        }
    ],
    "sg:phone":"+1 604 222 2218",
    "sg:postcode":"V6R 2H7",
    "sg:province":"BC",
    "wof:name":"Sawmac Realty Inc",
    "wof:placetype":"venue"
},
  "geometry": {"coordinates":[-123.205474853,49.263633728],"type":"Point"}
}