{
  "type": "Feature",
  "properties": {
    "addr:full":"1060 Britannia Rd E Mississauga ON L4W 4T1",
    "addr:housenumber":"1060",
    "addr:postcode":"l4w 4t1",
    "addr:street":"Britannia Rd E",
    "iso:country":"CA",
    "sg:address":"1060 Britannia Rd E",
    "sg:city":"Mississauga",
    "sg:classifiers":[
        {
            "category":"Real Estate",
            "subcategory":"Real Estate Agent",
            "type":"Services"
        }
    ],
    "sg:phone":"+1 905 565 2400",
    "sg:postcode":"L4W 4T1",
    "sg:province":"ON",
    "wof:name":"Preferred Choice Realty Inc",
    "wof:placetype":"venue"
},
  "geometry": {"coordinates":[-79.657119751,43.6465301514],"type":"Point"}
}