{
  "type": "Feature",
  "properties": {
    "iso:country":"CA",
    "sg:city":"Saint-Felicien",
    "sg:classifiers":[
        {
            "category":"Autos & Motor Vehicles",
            "subcategory":"Automobile Sales",
            "type":"Retail Goods"
        }
    ],
    "sg:phone":"+1 418 679 3770",
    "sg:postcode":"G8K 1S9",
    "sg:province":"QC",
    "sg:tags":[
        "car",
        "dealer"
    ],
    "wof:name":"St-Felicien Nissan Inc",
    "wof:placetype":"venue"
},
  "geometry": {"coordinates":[-72.42008972169999,48.6423187256],"type":"Point"}
}