{
  "type": "Feature",
  "properties": {
    "addr:full":"331 Spadina Ave Toronto ON M5T 2E9",
    "addr:housenumber":"331",
    "addr:postcode":"m5t 2e9",
    "addr:street":"Spadina Ave",
    "iso:country":"CA",
    "sg:address":"331 Spadina Ave",
    "sg:city":"Toronto",
    "sg:classifiers":[
        {
            "category":"Restaurant",
            "type":"Food & Drink"
        }
    ],
    "sg:phone":"+1 416 593 9524",
    "sg:postcode":"M5T 2E9",
    "sg:province":"ON",
    "wof:name":"Lee Garden Restaurant",
    "wof:placetype":"venue"
},
  "geometry": {"coordinates":[-79.398475647,43.6547737122],"type":"Point"}
}