{
  "type": "Feature",
  "properties": {
    "addr:full":"3552 Hwy 206 Petit DE Grat NS B0E 2L0",
    "addr:housenumber":"3552",
    "addr:postcode":"ns b0e 2l0",
    "addr:street":"Hwy 206 Petit De Grat",
    "iso:country":"CA",
    "sg:address":"3552 Hwy 206",
    "sg:city":"Petit DE Grat",
    "sg:classifiers":[
        {
            "category":"Banks & Credit Unions",
            "subcategory":"Bank",
            "type":"Services"
        }
    ],
    "sg:phone":"+1 902 226 2288",
    "sg:postcode":"B0E 2L0",
    "sg:province":"NS",
    "wof:name":"St Joseph's Credit Union",
    "wof:placetype":"venue"
},
  "geometry": {"coordinates":[-60.957039,45.505089],"type":"Point"}
}