{
  "type": "Feature",
  "properties": {
    "addr:full":"2660 Warren Ave Kimberley BC V1A 1T5",
    "addr:housenumber":"2660",
    "addr:postcode":"v1a 1t5",
    "addr:street":"Warren Ave",
    "iso:country":"CA",
    "sg:address":"2660 Warren Ave",
    "sg:city":"Kimberley",
    "sg:classifiers":[
        {
            "category":"Travel",
            "subcategory":"Hotels & Motels",
            "type":"Entertainment"
        }
    ],
    "sg:phone":"+1 250 427 2252",
    "sg:postcode":"V1A 1T5",
    "sg:province":"BC",
    "wof:name":"Travellaire Motel",
    "wof:placetype":"venue"
},
  "geometry": {"coordinates":[-115.973602,49.666859],"type":"Point"}
}