{
  "type": "Feature",
  "properties": {
    "addr:full":"2050 Boul Rene-Laennec Laval QC H7M 4J8",
    "addr:housenumber":"2050",
    "addr:postcode":"h7m 4j8",
    "addr:street":"Boul Rene-Laennec",
    "iso:country":"CA",
    "sg:address":"2050 Boul Rene-Laennec",
    "sg:city":"Laval",
    "sg:classifiers":[
        {
            "category":"Restaurant",
            "type":"Food & Drink"
        }
    ],
    "sg:phone":"+1 450 629 3843",
    "sg:postcode":"H7M 4J8",
    "sg:province":"QC",
    "sg:tags":[
        "pizza"
    ],
    "wof:name":"Bob Le Roi Des Sous-Marins",
    "wof:placetype":"venue"
},
  "geometry": {"coordinates":[-73.720207,45.609386],"type":"Point"}
}