{
  "type": "Feature",
  "properties": {
    "iso:country":"CA",
    "sg:address":"20 Falls Point Rd",
    "sg:city":"Lower Woods Harbour",
    "sg:phone":"+1 902 723 2455",
    "sg:postcode":"B0W 2E0",
    "sg:province":"NS",
    "sg:tags":[
        "oil"
    ],
    "wof:name":"West Nova Fuels Ltd",
    "wof:placetype":"venue"
},
  "geometry": {"coordinates":[-65.7338256836,43.5277328491],"type":"Point"}
}