{
  "type": "Feature",
  "properties": {
    "addr:full":"14 Gore St W Perth ON K7H 2L6",
    "addr:housenumber":"14",
    "addr:postcode":"k7h 2l6",
    "addr:street":"Gore St W",
    "iso:country":"CA",
    "sg:address":"14 Gore St W",
    "sg:city":"Perth",
    "sg:classifiers":[
        {
            "category":"Health Services",
            "subcategory":"Doctor",
            "type":"Services"
        }
    ],
    "sg:phone":"+1 613 264 0700",
    "sg:postcode":"K7H 2L6",
    "sg:province":"ON",
    "sg:tags":[
        "dentist"
    ],
    "wof:name":"Hall, William E DDS",
    "wof:placetype":"venue"
},
  "geometry": {"coordinates":[-76.25253295900001,44.902256012],"type":"Point"}
}