{
  "type": "Feature",
  "properties": {
    "addr:full":"Mont-Saint-Hilaire QC J3H 3N9",
    "addr:postcode":"j3h 3n9",
    "iso:country":"CA",
    "sg:city":"Mont-Saint-Hilaire",
    "sg:classifiers":[
        {
            "category":"Home & Garden",
            "subcategory":"Building Materials",
            "type":"Retail Goods"
        }
    ],
    "sg:phone":"+1 450 464 1183",
    "sg:postcode":"J3H 3N9",
    "sg:province":"QC",
    "sg:tags":[
        "windows",
        "door"
    ],
    "wof:name":"Fenetres Hp Lamoureaux Inc",
    "wof:placetype":"venue"
},
  "geometry": {"coordinates":[-73.18421936039999,45.5648155212],"type":"Point"}
}