{
  "type": "Feature",
  "properties": {
    "addr:full":"484 Danforth Ave Toronto ON M4K 1P6",
    "addr:housenumber":"484",
    "addr:postcode":"m4k 1p6",
    "addr:street":"Danforth Ave",
    "iso:country":"CA",
    "sg:address":"484 Danforth Ave",
    "sg:city":"Toronto",
    "sg:classifiers":[
        {
            "category":"Travel",
            "subcategory":"Travel Agent",
            "type":"Entertainment"
        }
    ],
    "sg:phone":"+1 416 469 5101",
    "sg:postcode":"M4K 1P6",
    "sg:province":"ON",
    "sg:tags":[
        "agency",
        "bureau"
    ],
    "wof:name":"Skyway Tours Ltd",
    "wof:placetype":"venue"
},
  "geometry": {"coordinates":[-79.34944900000001,43.678123],"type":"Point"}
}