{
  "type": "Feature",
  "properties": {
    "iso:country":"CA",
    "sg:address":"480 Central Ave",
    "sg:city":"Ste Rose Du Lac",
    "sg:classifiers":[
        {
            "category":"Education",
            "subcategory":"School",
            "type":"Public Place"
        }
    ],
    "sg:phone":"+1 204 447 2088",
    "sg:postcode":"R0L 1S0",
    "sg:province":"MB",
    "wof:name":"Ste Rose Schools",
    "wof:placetype":"venue"
},
  "geometry": {"coordinates":[-99.52394104,51.064289093],"type":"Point"}
}