{
  "type": "Feature",
  "properties": {
    "addr:full":"General Delivery Wekweti NT X0E 1W0",
    "addr:postcode":"x0e 1w0",
    "iso:country":"CA",
    "sg:address":"General Delivery",
    "sg:city":"Wekweti",
    "sg:classifiers":[
        {
            "category":"Travel",
            "subcategory":"Hotels & Motels",
            "type":"Entertainment"
        }
    ],
    "sg:phone":"+1 867 713 2700",
    "sg:postcode":"X0E 1W0",
    "sg:province":"NT",
    "wof:name":"Wekweti Hotel",
    "wof:placetype":"venue"
},
  "geometry": {"coordinates":[-114.18284606900001,64.1904296875],"type":"Point"}
}