{
  "type": "Feature",
  "properties": {
    "addr:full":"Sainte-Foy QC G1V 1Y4",
    "addr:postcode":"g1v 1y4",
    "iso:country":"CA",
    "sg:city":"Sainte-Foy",
    "sg:classifiers":[
        {
            "category":"Health Services",
            "subcategory":"Clinic",
            "type":"Services"
        }
    ],
    "sg:phone":"+1 418 650 2228",
    "sg:postcode":"G1V 1Y4",
    "sg:province":"QC",
    "sg:tags":[
        "holistic",
        "practitioner"
    ],
    "wof:name":"Martin, Nicole",
    "wof:placetype":"venue"
},
  "geometry": {"coordinates":[-71.301117,46.773426],"type":"Point"}
}