{
  "type": "Feature",
  "properties": {
    "addr:full":"Toronto ON M5S 2V1",
    "addr:postcode":"m5s 2v1",
    "iso:country":"CA",
    "sg:city":"Toronto",
    "sg:classifiers":[
        {
            "category":"Professional",
            "subcategory":"Employment Agencies",
            "type":"Services"
        }
    ],
    "sg:phone":"+1 416 926 8820",
    "sg:postcode":"M5S 2V1",
    "sg:province":"ON",
    "sg:tags":[
        "opportunity"
    ],
    "wof:name":"Options Personnel Inc",
    "wof:placetype":"venue"
},
  "geometry": {"coordinates":[-79.390404,43.669609],"type":"Point"}
}