{
  "type": "Feature",
  "properties": {
    "addr:full":"82931 Glendale Rd Goderich ON N7A 3X9",
    "addr:housenumber":"82931",
    "addr:postcode":"n7a 3x9",
    "addr:street":"Glendale Rd",
    "iso:country":"CA",
    "sg:address":"82931 Glendale Rd",
    "sg:city":"Goderich",
    "sg:classifiers":[
        {
            "category":"Travel",
            "subcategory":"Campground",
            "type":"Entertainment"
        }
    ],
    "sg:phone":"+1 519 524 7009",
    "sg:postcode":"N7A 3X9",
    "sg:province":"ON",
    "sg:tags":[
        "organization",
        "camp",
        "religious"
    ],
    "wof:name":"Baptists Church Camp Hermosa",
    "wof:placetype":"venue"
},
  "geometry": {"coordinates":[-81.707764,43.742641],"type":"Point"}
}