{
  "type": "Feature",
  "properties": {
    "addr:full":"8901 Boul Saint-Michel Montreal QC H1Z 3G3",
    "addr:housenumber":"8901",
    "addr:postcode":"h1z 3g3",
    "addr:street":"Boul Saint-Michel",
    "iso:country":"CA",
    "sg:address":"8901 Boul Saint-Michel",
    "sg:city":"Montreal",
    "sg:classifiers":[
        {
            "category":"Education",
            "subcategory":"School",
            "type":"Public Place"
        }
    ],
    "sg:phone":"+1 514 596 5550",
    "sg:postcode":"H1Z 3G3",
    "sg:province":"QC",
    "wof:name":"Ecole Ste-Lucie",
    "wof:placetype":"venue"
},
  "geometry": {"coordinates":[-73.6253356934,45.5709762573],"type":"Point"}
}