{
  "type": "Feature",
  "properties": {
    "addr:full":"55 University Ave Toronto ON M5J 2H7",
    "addr:housenumber":"55",
    "addr:postcode":"m5j 2h7",
    "addr:street":"University Ave",
    "iso:country":"CA",
    "sg:address":"55 University Ave",
    "sg:city":"Toronto",
    "sg:classifiers":[
        {
            "category":"Restaurant",
            "type":"Food & Drink"
        }
    ],
    "sg:phone":"+1 416 861 0790",
    "sg:postcode":"M5J 2H7",
    "sg:province":"ON",
    "wof:name":"Made in Japan",
    "wof:placetype":"venue"
},
  "geometry": {"coordinates":[-79.3840103149,43.6465759277],"type":"Point"}
}