{
  "type": "Feature",
  "properties": {
    "addr:full":"1208 Boul Du Lac Deux-Montagnes QC J7R 1C2",
    "addr:housenumber":"1208",
    "addr:postcode":"j7r 1c2",
    "addr:street":"Boul Du Lac",
    "iso:country":"CA",
    "sg:address":"1208 Boul Du Lac",
    "sg:city":"Deux-Montagnes",
    "sg:classifiers":[
        {
            "category":"Building & Trades",
            "subcategory":"Electrical",
            "type":"Services"
        }
    ],
    "sg:phone":"+1 450 491 1920",
    "sg:postcode":"J7R 1C2",
    "sg:province":"QC",
    "sg:tags":[
        "electric",
        "contractor"
    ],
    "wof:name":"Lavaltec Electrique",
    "wof:placetype":"venue"
},
  "geometry": {"coordinates":[-73.8893661499,45.5348052979],"type":"Point"}
}