{
  "type": "Feature",
  "properties": {
    "addr:full":"Lloydminster AB T9V 0P4",
    "addr:postcode":"t9v 0p4",
    "iso:country":"CA",
    "sg:city":"Lloydminster",
    "sg:classifiers":[
        {
            "category":"Manufacturing",
            "subcategory":"Printing",
            "type":"Manufacturing & Wholesale Goods"
        }
    ],
    "sg:phone":"+1 780 875 3222",
    "sg:postcode":"T9V 0P4",
    "sg:province":"AB",
    "sg:tags":[
        "printer"
    ],
    "wof:name":"Image Press",
    "wof:placetype":"venue"
},
  "geometry": {"coordinates":[-110.011154,53.284595],"type":"Point"}
}