{
  "type": "Feature",
  "properties": {
    "iso:country":"CA",
    "sg:address":"10100 Southport Rd SW",
    "sg:city":"Calgary",
    "sg:classifiers":[
        {
            "category":"Banks & Credit Unions",
            "subcategory":"Bank",
            "type":"Services"
        }
    ],
    "sg:phone":"+1 403 974 6356",
    "sg:postcode":"T2W 3X4",
    "sg:province":"AB",
    "wof:name":"Cibc",
    "wof:placetype":"venue"
},
  "geometry": {"coordinates":[-114.074241638,50.9647331238],"type":"Point"}
}