{
  "type": "Feature",
  "properties": {
    "addr:full":"Mississauga ON L4W 2P5",
    "addr:postcode":"l4w 2p5",
    "iso:country":"CA",
    "sg:city":"Mississauga",
    "sg:classifiers":[
        {
            "category":"Home & Garden",
            "subcategory":"Furniture",
            "type":"Retail Goods"
        }
    ],
    "sg:phone":"+1 905 602 1482",
    "sg:postcode":"L4W 2P5",
    "sg:province":"ON",
    "wof:name":"Giliberti Furniture",
    "wof:placetype":"venue"
},
  "geometry": {"coordinates":[-79.6295928955,43.6432342529],"type":"Point"}
}