{
  "type": "Feature",
  "properties": {
    "iso:country":"CA",
    "sg:address":"3683 Boul Saint-Jean",
    "sg:city":"Dollard-Des-Ormeaux",
    "sg:classifiers":[
        {
            "category":"Education",
            "subcategory":"Special Training",
            "type":"Public Place"
        }
    ],
    "sg:phone":"+1 514 696 0606",
    "sg:postcode":"H9G 1X2",
    "sg:province":"QC",
    "sg:tags":[
        "school",
        "tutoring"
    ],
    "wof:name":"Oxford Learning Ctr",
    "wof:placetype":"venue"
},
  "geometry": {"coordinates":[-73.8333282471,45.472026825],"type":"Point"}
}