{
  "type": "Feature",
  "properties": {
    "iso:country":"CA",
    "sg:city":"Rodney",
    "sg:classifiers":[
        {
            "category":"Travel",
            "subcategory":"Campground",
            "type":"Entertainment"
        }
    ],
    "sg:phone":"+1 519 785 0008",
    "sg:postcode":"N0L 2C0",
    "sg:province":"ON",
    "wof:name":"Hickory Grove Fmly Campground",
    "wof:placetype":"venue"
},
  "geometry": {"coordinates":[-81.68309021,42.5680351257],"type":"Point"}
}