{
  "type": "Feature",
  "properties": {
    "iso:country":"CA",
    "sg:address":"11291 Stave Lake St",
    "sg:city":"Mission",
    "sg:classifiers":[
        {
            "category":"Manufacturing",
            "subcategory":"Tools & Machinery",
            "type":"Manufacturing & Wholesale Goods"
        }
    ],
    "sg:phone":"+1 604 826 6816",
    "sg:postcode":"V2V 4J1",
    "sg:province":"BC",
    "sg:tags":[
        "machine",
        "shop"
    ],
    "wof:name":"Marksman Machining & Fab",
    "wof:placetype":"venue"
},
  "geometry": {"coordinates":[-122.26560974100001,49.1982803345],"type":"Point"}
}