{
  "type": "Feature",
  "properties": {
    "iso:country":"CA",
    "sg:address":"1500 Av Atwater",
    "sg:city":"Montreal",
    "sg:classifiers":[
        {
            "category":"Restaurant",
            "type":"Food & Drink"
        }
    ],
    "sg:phone":"+1 514 935 5519",
    "sg:postcode":"H3Z 1X5",
    "sg:province":"QC",
    "sg:tags":[
        "cocoa",
        "parlor",
        "chocolate",
        "ice",
        "cream"
    ],
    "wof:name":"Laura Secord",
    "wof:placetype":"venue"
},
  "geometry": {"coordinates":[-73.585319519,45.4897117615],"type":"Point"}
}