{
  "type": "Feature",
  "properties": {
    "addr:full":"81 7E Av Drummondville QC J2B 2R1",
    "addr:housenumber":"81",
    "addr:postcode":"j2b 2r1",
    "addr:street":"7E Av",
    "iso:country":"CA",
    "sg:address":"81 7E Av",
    "sg:city":"Drummondville",
    "sg:classifiers":[
        {
            "category":"Professional",
            "subcategory":"Business Services",
            "type":"Services"
        }
    ],
    "sg:phone":"+1 819 474 3931",
    "sg:postcode":"J2B 2R1",
    "sg:province":"QC",
    "wof:name":"Vestiaire St Jean Baptiste",
    "wof:placetype":"venue"
},
  "geometry": {"coordinates":[-72.4906387329,45.8736038208],"type":"Point"}
}