{
  "type": "Feature",
  "properties": {
    "addr:full":"North Vancouver BC V7M 1T3",
    "addr:postcode":"v7m 1t3",
    "iso:country":"CA",
    "sg:city":"North Vancouver",
    "sg:classifiers":[
        {
            "category":"Professional",
            "subcategory":"Lawyer & Legal Services",
            "type":"Services"
        }
    ],
    "sg:phone":"+1 604 986 0544",
    "sg:postcode":"V7M 1T3",
    "sg:province":"BC",
    "sg:tags":[
        "attorney"
    ],
    "wof:name":"Weir, Paul C",
    "wof:placetype":"venue"
},
  "geometry": {"coordinates":[-123.073783874,49.3229675293],"type":"Point"}
}