{
  "type": "Feature",
  "properties": {
    "addr:full":"75 Centennial Pky S Stoney Creek ON L8G 2C7",
    "addr:housenumber":"75",
    "addr:postcode":"l8g 2c7",
    "addr:street":"Centennial Pky S Stoney",
    "iso:country":"CA",
    "sg:address":"75 Centennial Pky S",
    "sg:city":"Stoney Creek",
    "sg:classifiers":[
        {
            "category":"Shopping",
            "subcategory":"Jewelry",
            "type":"Retail Goods"
        }
    ],
    "sg:phone":"+1 905 561 5792",
    "sg:postcode":"L8G 2C7",
    "sg:province":"ON",
    "sg:tags":[
        "jeweler"
    ],
    "wof:name":"Ardene",
    "wof:placetype":"venue"
},
  "geometry": {"coordinates":[-79.76573944090001,43.2246551514],"type":"Point"}
}