{
  "type": "Feature",
  "properties": {
    "addr:full":"242 James St S #200 Hamilton ON L8P 3B3",
    "addr:housenumber":"242;200",
    "addr:postcode":"l8p 3b3",
    "addr:street":"James St S #",
    "iso:country":"CA",
    "sg:address":"242 James St S #200",
    "sg:city":"Hamilton",
    "sg:classifiers":[
        {
            "category":"Professional",
            "subcategory":"Lawyer & Legal Services",
            "type":"Services"
        }
    ],
    "sg:phone":"+1 905 525 9636",
    "sg:postcode":"L8P 3B3",
    "sg:province":"ON",
    "sg:tags":[
        "attorney"
    ],
    "wof:name":"Rubenstein, Michael N",
    "wof:placetype":"venue"
},
  "geometry": {"coordinates":[-79.8725280762,43.2492103577],"type":"Point"}
}