{
  "type": "Feature",
  "properties": {
    "addr:full":"34 Prospect St Doaktown NB E9C 1C5",
    "addr:housenumber":"34",
    "addr:postcode":"e9c 1c5",
    "addr:street":"Prospect St",
    "iso:country":"CA",
    "sg:address":"34 Prospect St",
    "sg:city":"Doaktown",
    "sg:phone":"+1 506 365 2222",
    "sg:postcode":"E9C 1C5",
    "sg:province":"NB",
    "sg:tags":[
        "oil"
    ],
    "wof:name":"Kenneth Robinson Fuel Ltd",
    "wof:placetype":"venue"
},
  "geometry": {"coordinates":[-66.137047,46.552082],"type":"Point"}
}