{
  "type": "Feature",
  "properties": {
    "addr:full":"3053 Av DE LA Montagne Shawinigan QC G9N 6K5",
    "addr:housenumber":"3053",
    "addr:postcode":"g9n 6k5",
    "addr:street":"Av De La Montagne",
    "iso:country":"CA",
    "sg:address":"3053 Av DE LA Montagne",
    "sg:city":"Shawinigan",
    "sg:classifiers":[
        {
            "category":"Building & Trades",
            "subcategory":"Plumbing",
            "type":"Services"
        }
    ],
    "sg:phone":"+1 819 539 2989",
    "sg:postcode":"G9N 6K5",
    "sg:province":"QC",
    "sg:tags":[
        "conditioning",
        "air",
        "system",
        "refrigerating",
        "contractor"
    ],
    "wof:name":"Pierre Lavergne Inc",
    "wof:placetype":"venue"
},
  "geometry": {"coordinates":[-72.75908699999999,46.576721],"type":"Point"}
}