{
  "type": "Feature",
  "properties": {
    "addr:full":"6404 Wellington Ave West Vancouver BC V7W 2H6",
    "addr:housenumber":"6404",
    "addr:postcode":"v7w 2h6",
    "addr:street":"Wellington Ave",
    "iso:country":"CA",
    "sg:address":"6404 Wellington Ave",
    "sg:city":"West Vancouver",
    "sg:classifiers":[
        {
            "category":"Organizations",
            "subcategory":"Religious Organization",
            "type":"Services"
        }
    ],
    "sg:phone":"+1 604 921 9112",
    "sg:postcode":"V7W 2H6",
    "sg:province":"BC",
    "sg:tags":[
        "church"
    ],
    "wof:name":"St Monica's Church",
    "wof:placetype":"venue"
},
  "geometry": {"coordinates":[-123.280312,49.371059],"type":"Point"}
}