{
  "type": "Feature",
  "properties": {
    "iso:country":"CA",
    "sg:address":"4435 Av Thibault",
    "sg:city":"Saint-Hubert",
    "sg:classifiers":[
        {
            "category":"Building & Trades",
            "subcategory":"Landscaping Services",
            "type":"Services"
        }
    ],
    "sg:phone":"+1 450 678 9712",
    "sg:postcode":"J3Y 7N1",
    "sg:province":"QC",
    "sg:tags":[
        "lawn",
        "maintenance",
        "grounds"
    ],
    "wof:name":"Vertdure Rive-Sud",
    "wof:placetype":"venue"
},
  "geometry": {"coordinates":[-73.443115,45.504299],"type":"Point"}
}