{
  "type": "Feature",
  "properties": {
    "addr:full":"109 Bridgeport Rd E Waterloo ON N2J 2K3",
    "addr:housenumber":"109",
    "addr:postcode":"n2j 2k3",
    "addr:street":"Bridgeport Rd E",
    "iso:country":"CA",
    "sg:address":"109 Bridgeport Rd E",
    "sg:city":"Waterloo",
    "sg:classifiers":[
        {
            "category":"Retail",
            "subcategory":"Auto Repair",
            "type":"Services"
        }
    ],
    "sg:phone":"+1 519 885 5950",
    "sg:postcode":"N2J 2K3",
    "sg:province":"ON",
    "sg:tags":[
        "repairing",
        "automobile"
    ],
    "wof:name":"Mike's Auto Svc & Sale",
    "wof:placetype":"venue"
},
  "geometry": {"coordinates":[-80.51316799999999,43.469795],"type":"Point"}
}