{
  "type": "Feature",
  "properties": {
    "addr:full":"12375 132 St NW Edmonton AB T5L 1P9",
    "addr:housenumber":"12375",
    "addr:postcode":"t5l 1p9",
    "addr:street":"132 St Nw",
    "iso:country":"CA",
    "sg:address":"12375 132 St NW",
    "sg:city":"Edmonton",
    "sg:classifiers":[
        {
            "category":"Airport",
            "type":"Transportation"
        }
    ],
    "sg:phone":"+1 780 459 3332",
    "sg:postcode":"T5L 1P9",
    "sg:province":"AB",
    "sg:tags":[
        "aircraft",
        "maintenance"
    ],
    "wof:name":"Nason Aviation Inc",
    "wof:placetype":"venue"
},
  "geometry": {"coordinates":[-113.55341300000001,53.57972],"type":"Point"}
}