{
  "type": "Feature",
  "properties": {
    "addr:full":"19 Boul Des Hauteurs Saint-Jerome QC J7Y 1R1",
    "addr:housenumber":"19",
    "addr:postcode":"j7y 1r1",
    "addr:street":"Boul Des Hauteurs",
    "iso:country":"CA",
    "sg:address":"19 Boul Des Hauteurs",
    "sg:city":"Saint-Jerome",
    "sg:classifiers":[
        {
            "category":"Manufacturing",
            "subcategory":"Metals",
            "type":"Manufacturing & Wholesale Goods"
        }
    ],
    "sg:phone":"+1 450 438 2653",
    "sg:postcode":"J7Y 1R1",
    "sg:province":"QC",
    "sg:tags":[
        "ironwork",
        "solder"
    ],
    "wof:name":"Fer Ornemental G Dumoulin Inc",
    "wof:placetype":"venue"
},
  "geometry": {"coordinates":[-74.0127487183,45.8076820374],"type":"Point"}
}