{
  "type": "Feature",
  "properties": {
    "addr:full":"141 Fifth St Smooth Rock Falls ON P0L 2B0",
    "addr:housenumber":"141",
    "addr:postcode":"p0l 2b0",
    "addr:street":"Fifth St",
    "iso:country":"CA",
    "sg:address":"141 Fifth St",
    "sg:city":"Smooth Rock Falls",
    "sg:classifiers":[
        {
            "category":"Social Services",
            "type":"Services"
        }
    ],
    "sg:phone":"+1 705 338 2654",
    "sg:postcode":"P0L 2B0",
    "sg:province":"ON",
    "sg:tags":[
        "organization",
        "welfare"
    ],
    "wof:name":"Bureau DE Sante Porcupine",
    "wof:placetype":"venue"
},
  "geometry": {"coordinates":[-81.6300582886,49.2786560059],"type":"Point"}
}