{
  "type": "Feature",
  "properties": {
    "addr:full":"10 Wellington St W Chatham ON N7M 1H8",
    "addr:housenumber":"10",
    "addr:postcode":"n7m 1h8",
    "addr:street":"Wellington St W",
    "iso:country":"CA",
    "sg:address":"10 Wellington St W",
    "sg:city":"Chatham",
    "sg:classifiers":[
        {
            "category":"Home & Garden",
            "subcategory":"Household Appliances",
            "type":"Retail Goods"
        }
    ],
    "sg:phone":"+1 519 351 1488",
    "sg:postcode":"N7M 1H8",
    "sg:province":"ON",
    "wof:name":"Ace Used Appliance Ctr",
    "wof:placetype":"venue"
},
  "geometry": {"coordinates":[-82.18104599999999,42.403137],"type":"Point"}
}