{
  "type": "Feature",
  "properties": {
    "addr:full":"675 Ch Du Sablon Laval QC H7W 4H5",
    "addr:housenumber":"675",
    "addr:postcode":"h7w 4h5",
    "addr:street":"Ch Du Sablon",
    "iso:country":"CA",
    "sg:address":"675 Ch Du Sablon",
    "sg:city":"Laval",
    "sg:classifiers":[
        {
            "category":"Organizations",
            "subcategory":"Religious Organization",
            "type":"Services"
        }
    ],
    "sg:phone":"+1 450 978 1770",
    "sg:postcode":"H7W 4H5",
    "sg:province":"QC",
    "sg:tags":[
        "synagogue"
    ],
    "wof:name":"Centre Sepharade DE Torah",
    "wof:placetype":"venue"
},
  "geometry": {"coordinates":[-73.770325,45.531174],"type":"Point"}
}