{
  "type": "Feature",
  "properties": {
    "addr:full":"Lac-Simon QC J0Y 3M0",
    "addr:postcode":"j0y 3m0",
    "iso:country":"CA",
    "sg:city":"Lac-Simon",
    "sg:classifiers":[
        {
            "category":"Government",
            "subcategory":"Office",
            "type":"Public Place"
        }
    ],
    "sg:phone":"+1 819 428 4477",
    "sg:postcode":"J0Y 3M0",
    "sg:province":"QC",
    "sg:tags":[
        "village"
    ],
    "wof:name":"Lac Simon Securite",
    "wof:placetype":"venue"
},
  "geometry": {"coordinates":[-75.09307098390001,45.9053764343],"type":"Point"}
}