{
  "type": "Feature",
  "properties": {
    "addr:full":"938 the Queensway Etobicoke ON M8Z 1P4",
    "addr:housenumber":"938",
    "addr:postcode":"m8z 1p4",
    "addr:street":"The Queensway",
    "iso:country":"CA",
    "sg:address":"938 the Queensway",
    "sg:city":"Etobicoke",
    "sg:classifiers":[
        {
            "category":"Health Services",
            "subcategory":"Chiropractor",
            "type":"Services"
        }
    ],
    "sg:phone":"+1 416 259 0941",
    "sg:postcode":"M8Z 1P4",
    "sg:province":"ON",
    "wof:name":"Queensway Chiropractic Ctr",
    "wof:placetype":"venue"
},
  "geometry": {"coordinates":[-79.512238,43.624344],"type":"Point"}
}