{
  "type": "Feature",
  "properties": {
    "iso:country":"CA",
    "sg:address":"299 Orenda Rd",
    "sg:city":"Brampton",
    "sg:classifiers":[
        {
            "category":"Manufacturing",
            "subcategory":"Metals",
            "type":"Manufacturing & Wholesale Goods"
        }
    ],
    "sg:phone":"+1 905 457 3014",
    "sg:postcode":"L6T 1E8",
    "sg:province":"ON",
    "sg:tags":[
        "tool"
    ],
    "wof:name":"Gray Hand Tool Sales Ltd",
    "wof:placetype":"venue"
},
  "geometry": {"coordinates":[-79.711845,43.700497],"type":"Point"}
}