{
  "type": "Feature",
  "properties": {
    "addr:full":"2211 Rue Saint-Dominique Jonquiere QC G7X 6M6",
    "addr:housenumber":"2211",
    "addr:postcode":"g7x 6m6",
    "addr:street":"Rue Saint-Dominique",
    "iso:country":"CA",
    "sg:address":"2211 Rue Saint-Dominique",
    "sg:city":"Jonquiere",
    "sg:classifiers":[
        {
            "category":"Insurance",
            "subcategory":"Life Insurance",
            "type":"Services"
        }
    ],
    "sg:phone":"+1 418 695 3588",
    "sg:postcode":"G7X 6M6",
    "sg:province":"QC",
    "wof:name":"Services Financiers Plani-Vie",
    "wof:placetype":"venue"
},
  "geometry": {"coordinates":[-71.250404,48.417767],"type":"Point"}
}