{
  "type": "Feature",
  "properties": {
    "addr:full":"501 Wilkins St # 402 London ON N6C 5G2",
    "addr:housenumber":"501",
    "addr:postcode":"n6c 5g2",
    "addr:street":"Wilkins St # 402",
    "iso:country":"CA",
    "sg:address":"501 Wilkins St # 402",
    "sg:city":"London",
    "sg:classifiers":[
        {
            "category":"Real Estate",
            "subcategory":"Real Estate Operator",
            "type":"Services"
        }
    ],
    "sg:phone":"+1 519 685 0821",
    "sg:postcode":"N6C 5G2",
    "sg:province":"ON",
    "sg:tags":[
        "apartment"
    ],
    "wof:name":"Settlement Apartments",
    "wof:placetype":"venue"
},
  "geometry": {"coordinates":[-81.2344055176,42.9507255554],"type":"Point"}
}