{
  "type": "Feature",
  "properties": {
    "addr:full":"3607 LA Grande-Allee Saint-Hubert QC J4T 2V1",
    "addr:housenumber":"3607",
    "addr:postcode":"j4t 2v1",
    "addr:street":"La Grande-Allee",
    "iso:country":"CA",
    "sg:address":"3607 LA Grande-Allee",
    "sg:city":"Saint-Hubert",
    "sg:classifiers":[
        {
            "category":"Shopping",
            "subcategory":"Computers & Home Electronics",
            "type":"Retail Goods"
        }
    ],
    "sg:phone":"+1 450 445 4333",
    "sg:postcode":"J4T 2V1",
    "sg:province":"QC",
    "sg:tags":[
        "radio",
        "television",
        "video",
        "equipment"
    ],
    "wof:name":"Grande Allee Electronics Regd",
    "wof:placetype":"venue"
},
  "geometry": {"coordinates":[-73.47012329099999,45.4928436279],"type":"Point"}
}