{
  "type": "Feature",
  "properties": {
    "addr:full":"1919 25E Rue Grand-Mere QC G9T 3R8",
    "addr:housenumber":"1919",
    "addr:postcode":"g9t 3r8",
    "addr:street":"25E Rue Grand-Mere",
    "iso:country":"CA",
    "sg:address":"1919 25E Rue",
    "sg:city":"Grand-Mere",
    "sg:classifiers":[
        {
            "category":"Insurance",
            "subcategory":"Insurance Agent",
            "type":"Services"
        }
    ],
    "sg:phone":"+1 819 538 8283",
    "sg:postcode":"G9T 3R8",
    "sg:province":"QC",
    "sg:tags":[
        "consultant",
        "planning",
        "financial"
    ],
    "wof:name":"Jacques, Francis P",
    "wof:placetype":"venue"
},
  "geometry": {"coordinates":[-72.695274353,46.6131134033],"type":"Point"}
}