{
  "type": "Feature",
  "properties": {
    "addr:full":"189 Killaly St E Port Colborne ON L3K 1N7",
    "addr:housenumber":"189",
    "addr:postcode":"l3k 1n7",
    "addr:street":"Killaly St E",
    "iso:country":"CA",
    "sg:address":"189 Killaly St E",
    "sg:city":"Port Colborne",
    "sg:classifiers":[
        {
            "category":"Food & Beverages",
            "subcategory":"Groceries & Convenience Stores",
            "type":"Retail Goods"
        }
    ],
    "sg:phone":"+1 905 835 1925",
    "sg:postcode":"L3K 1N7",
    "sg:province":"ON",
    "wof:name":"Avondale Stores Ltd",
    "wof:placetype":"venue"
},
  "geometry": {"coordinates":[-79.2428894043,42.8915786743],"type":"Point"}
}