{
  "type": "Feature",
  "properties": {
    "addr:full":"10 Con Kendall Hearst ON P0L 1N0",
    "addr:housenumber":"10",
    "addr:postcode":"p0l 1n0",
    "addr:street":"Con Kendall",
    "iso:country":"CA",
    "sg:address":"10 Con Kendall",
    "sg:city":"Hearst",
    "sg:classifiers":[
        {
            "category":"Retail",
            "subcategory":"Auto Repair",
            "type":"Services"
        }
    ],
    "sg:phone":"+1 705 362 5633",
    "sg:postcode":"P0L 1N0",
    "sg:province":"ON",
    "sg:tags":[
        "repairing",
        "automobile"
    ],
    "wof:name":"G & D Serge Repair Inc",
    "wof:placetype":"venue"
},
  "geometry": {"coordinates":[-83.664948,49.689316],"type":"Point"}
}