{
  "type": "Feature",
  "properties": {
    "addr:full":"Red Deer AB T4N 6V4",
    "addr:postcode":"t4n 6v4",
    "iso:country":"CA",
    "sg:city":"Red Deer",
    "sg:classifiers":[
        {
            "category":"Professional",
            "subcategory":"Accounting & Tax Preparation",
            "type":"Services"
        }
    ],
    "sg:phone":"+1 403 347 2226",
    "sg:postcode":"T4N 6V4",
    "sg:province":"AB",
    "sg:tags":[
        "accountant"
    ],
    "wof:name":"Wellbrock, Lori CA",
    "wof:placetype":"venue"
},
  "geometry": {"coordinates":[-113.812904358,52.269821167],"type":"Point"}
}