{
  "type": "Feature",
  "properties": {
    "iso:country":"CA",
    "sg:address":"3024 Kennedy Rd",
    "sg:city":"Scarborough",
    "sg:classifiers":[
        {
            "category":"Home & Garden",
            "subcategory":"Garden Supply",
            "type":"Retail Goods"
        }
    ],
    "sg:phone":"+1 416 299 1775",
    "sg:postcode":"M1V 4Y2",
    "sg:province":"ON",
    "sg:tags":[
        "center",
        "landscape",
        "contractor"
    ],
    "wof:name":"Colangelo Brothers Nurseries",
    "wof:placetype":"venue"
},
  "geometry": {"coordinates":[-79.299621582,43.8066291809],"type":"Point"}
}