{
  "type": "Feature",
  "properties": {
    "addr:full":"448 Frontenac Bay Thunder Bay ON P7C 1M6",
    "addr:housenumber":"448",
    "addr:postcode":"p7c 1m6",
    "addr:street":"Frontenac Bay",
    "iso:country":"CA",
    "sg:address":"448 Frontenac Bay",
    "sg:city":"Thunder Bay",
    "sg:classifiers":[
        {
            "category":"Building & Trades",
            "subcategory":"Plumbing",
            "type":"Services"
        }
    ],
    "sg:phone":"+1 807 475 3626",
    "sg:postcode":"P7C 1M6",
    "sg:province":"ON",
    "sg:tags":[
        "conditioning",
        "air",
        "system",
        "contractor"
    ],
    "wof:name":"Allied Air Systems",
    "wof:placetype":"venue"
},
  "geometry": {"coordinates":[-89.28621699999999,48.385822],"type":"Point"}
}