{
  "type": "Feature",
  "properties": {
    "iso:country":"CA",
    "sg:address":"448 Frontenac Bay",
    "sg:city":"Thunder Bay",
    "sg:classifiers":[
        {
            "category":"Building & Trades",
            "subcategory":"Plumbing",
            "type":"Services"
        }
    ],
    "sg:phone":"+1 807 475 3626",
    "sg:postcode":"P7C 1M6",
    "sg:province":"ON",
    "sg:tags":[
        "conditioning",
        "air",
        "system",
        "contractor"
    ],
    "wof:name":"Allied Air Systems",
    "wof:placetype":"venue"
},
  "geometry": {"coordinates":[-89.286217,48.385822],"type":"Point"}
}