{
  "type": "Feature",
  "properties": {
    "addr:full":"8242 Ontario St Vancouver BC V5X 3E3",
    "addr:housenumber":"8242",
    "addr:postcode":"v5x 3e3",
    "addr:street":"Ontario St",
    "iso:country":"CA",
    "sg:address":"8242 Ontario St",
    "sg:city":"Vancouver",
    "sg:classifiers":[
        {
            "category":"Wholesale",
            "subcategory":"Toys & Hobbies",
            "type":"Manufacturing & Wholesale Goods"
        }
    ],
    "sg:phone":"+1 604 327 8391",
    "sg:postcode":"V5X 3E3",
    "sg:province":"BC",
    "wof:name":"Jackson Agencies CO Ltd",
    "wof:placetype":"venue"
},
  "geometry": {"coordinates":[-123.10641479500001,49.2101516724],"type":"Point"}
}