{
  "type": "Feature",
  "properties": {
    "addr:full":"PO Box 7081 STN Main Peace River AB T8S 1S8",
    "addr:housenumber":"po",
    "addr:postcode":"7081;t8s 1s8",
    "addr:street":"Box;Stn Main",
    "iso:country":"CA",
    "sg:address":"PO Box 7081 STN Main",
    "sg:city":"Peace River",
    "sg:classifiers":[
        {
            "category":"Professional",
            "subcategory":"Detective & Security Services",
            "type":"Services"
        }
    ],
    "sg:phone":"+1 780 618 6930",
    "sg:postcode":"T8S 1S8",
    "sg:province":"AB",
    "sg:tags":[
        "guard",
        "patrol"
    ],
    "wof:name":"Sgs Protection",
    "wof:placetype":"venue"
},
  "geometry": {"coordinates":[-117.290382385,56.2329711914],"type":"Point"}
}