{
  "type": "Feature",
  "properties": {
    "addr:full":"PO Box 22316 Rpo Bankers Hall Calgary AB T2P 4J1",
    "addr:housenumber":"po box",
    "addr:postcode":"t2p 4j1",
    "addr:street":"22316",
    "iso:country":"CA",
    "sg:address":"PO Box 22316 Rpo Bankers Hall",
    "sg:city":"Calgary",
    "sg:classifiers":[
        {
            "category":"Professional",
            "subcategory":"Business Services",
            "type":"Services"
        }
    ],
    "sg:phone":"+1 403 870 6019",
    "sg:postcode":"T2P 4J1",
    "sg:province":"AB",
    "sg:tags":[
        "process",
        "server"
    ],
    "wof:name":"Effective Process Svc",
    "wof:placetype":"venue"
},
  "geometry": {"coordinates":[-114.063194,51.045074],"type":"Point"}
}