{
  "type": "Feature",
  "properties": {
    "addr:full":"465 Edison Ave Winnipeg MB R2G 0M2",
    "addr:housenumber":"465",
    "addr:postcode":"r2g 0m2",
    "addr:street":"Edison Ave",
    "iso:country":"CA",
    "sg:address":"465 Edison Ave",
    "sg:city":"Winnipeg",
    "sg:classifiers":[
        {
            "category":"Building & Trades",
            "subcategory":"Construction",
            "type":"Services"
        }
    ],
    "sg:phone":"+1 204 663 5022",
    "sg:postcode":"R2G 0M2",
    "sg:province":"MB",
    "sg:tags":[
        "maker",
        "cabinet"
    ],
    "wof:name":"Hawthorne Woodworks Ltd",
    "wof:placetype":"venue"
},
  "geometry": {"coordinates":[-97.076134,49.937111],"type":"Point"}
}