{
  "type": "Feature",
  "properties": {
    "addr:full":"6490 Av Somerled Montreal QC H4V 1S5",
    "addr:housenumber":"6490",
    "addr:postcode":"h4v 1s5",
    "addr:street":"Av Somerled",
    "iso:country":"CA",
    "sg:address":"6490 Av Somerled",
    "sg:city":"Montreal",
    "sg:classifiers":[
        {
            "category":"Autos & Motor Vehicles",
            "subcategory":"Fuel & Gas Station",
            "type":"Retail Goods"
        }
    ],
    "sg:phone":"+1 514 484 8945",
    "sg:postcode":"H4V 1S5",
    "sg:province":"QC",
    "sg:tags":[
        "oil"
    ],
    "wof:name":"Shell Canada Ltd",
    "wof:placetype":"venue"
},
  "geometry": {"coordinates":[-73.637924,45.467957],"type":"Point"}
}