{
  "type": "Feature",
  "properties": {
    "iso:country":"CA",
    "sg:address":"19 Pettipas Dr",
    "sg:city":"Dartmouth",
    "sg:classifiers":[
        {
            "category":"Retail",
            "subcategory":"Auto Repair",
            "type":"Services"
        }
    ],
    "sg:phone":"+1 902 468 5409",
    "sg:postcode":"B3B 1K1",
    "sg:province":"NS",
    "sg:tags":[
        "body",
        "automobile",
        "painting"
    ],
    "wof:name":"Boutilier's Auto Body",
    "wof:placetype":"venue"
},
  "geometry": {"coordinates":[-63.6122932434,44.71043396],"type":"Point"}
}