{
  "type": "Feature",
  "properties": {
    "addr:full":"1191 Parker St Vancouver BC V6A 2H3",
    "addr:housenumber":"1191",
    "addr:postcode":"v6a 2h3",
    "addr:street":"Parker St",
    "iso:country":"CA",
    "sg:address":"1191 Parker St",
    "sg:city":"Vancouver",
    "sg:classifiers":[
        {
            "category":"Manufacturing",
            "subcategory":"Pottery",
            "type":"Manufacturing & Wholesale Goods"
        }
    ],
    "sg:phone":"+1 604 215 2569",
    "sg:postcode":"V6A 2H3",
    "sg:province":"BC",
    "sg:tags":[
        "glass"
    ],
    "wof:name":"Joe Blow Glassworks",
    "wof:placetype":"venue"
},
  "geometry": {"coordinates":[-123.078842163,49.2760314941],"type":"Point"}
}