{
  "type": "Feature",
  "properties": {
    "addr:full":"5307 Main St Montague PE C0A 1R0",
    "addr:housenumber":"5307",
    "addr:postcode":"c0a 1r0",
    "addr:street":"Main St",
    "iso:country":"CA",
    "sg:address":"5307 Main St",
    "sg:city":"Montague",
    "sg:classifiers":[
        {
            "category":"Building & Trades",
            "subcategory":"Construction",
            "type":"Services"
        }
    ],
    "sg:phone":"+1 902 838 2639",
    "sg:postcode":"C0A 1R0",
    "sg:province":"PE",
    "sg:tags":[
        "excavating",
        "contractor"
    ],
    "wof:name":"Kenny's Backhoeing Ltd",
    "wof:placetype":"venue"
},
  "geometry": {"coordinates":[-62.642429,46.162933],"type":"Point"}
}