{
  "type": "Feature",
  "properties": {
    "addr:full":"11835 Boul Laurentien Montreal QC H4J 2M1",
    "addr:housenumber":"11835",
    "addr:postcode":"h4j 2m1",
    "addr:street":"Boul Laurentien",
    "iso:country":"CA",
    "sg:address":"11835 Boul Laurentien",
    "sg:city":"Montreal",
    "sg:classifiers":[
        {
            "category":"Food & Beverages",
            "subcategory":"Meat & Fish",
            "type":"Retail Goods"
        }
    ],
    "sg:phone":"+1 514 856 0450",
    "sg:postcode":"H4J 2M1",
    "sg:province":"QC",
    "sg:tags":[
        "seafood"
    ],
    "wof:name":"Poissonnerie Cartierville Enr",
    "wof:placetype":"venue"
},
  "geometry": {"coordinates":[-73.71318100000001,45.525269],"type":"Point"}
}