{
  "type": "Feature",
  "properties": {
    "addr:full":"16 Rue Saint-Joseph Levis QC G6V 1A6",
    "addr:housenumber":"16",
    "addr:postcode":"g6v 1a6",
    "addr:street":"Rue Saint-Joseph",
    "iso:country":"CA",
    "sg:address":"16 Rue Saint-Joseph",
    "sg:city":"Levis",
    "sg:classifiers":[
        {
            "category":"Home & Garden",
            "subcategory":"Hardware",
            "type":"Retail Goods"
        }
    ],
    "sg:phone":"+1 418 837 2441",
    "sg:postcode":"G6V 1A6",
    "sg:province":"QC",
    "wof:name":"Quincaillerie Dgr Inc",
    "wof:placetype":"venue"
},
  "geometry": {"coordinates":[-71.17987100000001,46.819691],"type":"Point"}
}