{
  "type": "Feature",
  "properties": {
    "addr:full":"1993 Finch Ave W North York ON M3N 2V3",
    "addr:housenumber":"1993",
    "addr:postcode":"m3n 2v3",
    "addr:street":"Finch Ave W",
    "iso:country":"CA",
    "sg:address":"1993 Finch Ave W",
    "sg:city":"North York",
    "sg:classifiers":[
        {
            "category":"Health Services",
            "subcategory":"Doctor",
            "type":"Services"
        }
    ],
    "sg:phone":"+1 416 745 4949",
    "sg:postcode":"M3N 2V3",
    "sg:province":"ON",
    "sg:tags":[
        "physician",
        "surgeon"
    ],
    "wof:name":"Samuel, O MD",
    "wof:placetype":"venue"
},
  "geometry": {"coordinates":[-79.519707,43.756824],"type":"Point"}
}