{
  "type": "Feature",
  "properties": {
    "addr:full":"5338 Rue Sherbrooke O Montreal QC H4A 1V5",
    "addr:housenumber":"5338",
    "addr:postcode":"h4a 1v5",
    "addr:street":"Rue Sherbrooke O",
    "iso:country":"CA",
    "sg:address":"5338 Rue Sherbrooke O",
    "sg:city":"Montreal",
    "sg:classifiers":[
        {
            "category":"Home & Garden",
            "subcategory":"Furniture",
            "type":"Retail Goods"
        }
    ],
    "sg:phone":"+1 514 483 0040",
    "sg:postcode":"H4A 1V5",
    "sg:province":"QC",
    "sg:tags":[
        "mattress"
    ],
    "wof:name":"Au Monde Du Matelas",
    "wof:placetype":"venue"
},
  "geometry": {"coordinates":[-73.55165100000001,45.56905],"type":"Point"}
}