{
  "type": "Feature",
  "properties": {
    "iso:country":"CA",
    "sg:address":"5338 Rue Sherbrooke O",
    "sg:city":"Montreal",
    "sg:classifiers":[
        {
            "category":"Home & Garden",
            "subcategory":"Furniture",
            "type":"Retail Goods"
        }
    ],
    "sg:phone":"+1 514 483 0040",
    "sg:postcode":"H4A 1V5",
    "sg:province":"QC",
    "sg:tags":[
        "mattress"
    ],
    "wof:name":"Au Monde Du Matelas",
    "wof:placetype":"venue"
},
  "geometry": {"coordinates":[-73.551651,45.56905],"type":"Point"}
}