{
  "type": "Feature",
  "properties": {
    "addr:full":"1197 Fraser Ave Port Coquitlam BC V3B 1M1",
    "addr:housenumber":"1197",
    "addr:postcode":"v3b 1m1",
    "addr:street":"Fraser Ave",
    "iso:country":"CA",
    "sg:address":"1197 Fraser Ave",
    "sg:city":"Port Coquitlam",
    "sg:classifiers":[
        {
            "category":"Building & Trades",
            "subcategory":"Construction",
            "type":"Services"
        }
    ],
    "sg:phone":"+1 604 942 4383",
    "sg:postcode":"V3B 1M1",
    "sg:province":"BC",
    "sg:tags":[
        "painter"
    ],
    "wof:name":"Pro-Acc Painting Svc",
    "wof:placetype":"venue"
},
  "geometry": {"coordinates":[-122.747192,49.269073],"type":"Point"}
}