{
  "type": "Feature",
  "properties": {
    "addr:full":"163 Janette Ave Windsor ON N9A 4Y9",
    "addr:housenumber":"163",
    "addr:postcode":"n9a 4y9",
    "addr:street":"Janette Ave",
    "iso:country":"CA",
    "sg:address":"163 Janette Ave",
    "sg:city":"Windsor",
    "sg:classifiers":[
        {
            "category":"Personal",
            "subcategory":"Beauty Salon",
            "type":"Services"
        }
    ],
    "sg:phone":"+1 519 977 6636",
    "sg:postcode":"N9A 4Y9",
    "sg:province":"ON",
    "wof:name":"Luxe Salon",
    "wof:placetype":"venue"
},
  "geometry": {"coordinates":[-83.046959,42.316891],"type":"Point"}
}