{
  "type": "Feature",
  "properties": {
    "addr:full":"17855 66 Ave Surrey BC V3S 7X1",
    "addr:housenumber":"17855",
    "addr:postcode":"v3s 7x1",
    "addr:street":"66 Ave",
    "iso:country":"CA",
    "sg:address":"17855 66 Ave",
    "sg:city":"Surrey",
    "sg:classifiers":[
        {
            "category":"Wholesale",
            "subcategory":"Electrical",
            "type":"Manufacturing & Wholesale Goods"
        }
    ],
    "sg:phone":"+1 604 576 9916",
    "sg:postcode":"V3S 7X1",
    "sg:province":"BC",
    "sg:tags":[
        "equipment",
        "electric",
        "supply"
    ],
    "wof:name":"E B Horsman & Son Ltd",
    "wof:placetype":"venue"
},
  "geometry": {"coordinates":[-122.72931699999999,49.122562],"type":"Point"}
}