{
  "type": "Feature",
  "properties": {
    "addr:full":"50 O'Connor St Ottawa ON K1P 6L2",
    "addr:housenumber":"50",
    "addr:postcode":"k1p 6l2",
    "addr:street":"O'Connor St",
    "iso:country":"CA",
    "sg:address":"50 O'Connor St",
    "sg:city":"Ottawa",
    "sg:classifiers":[
        {
            "category":"Professional",
            "subcategory":"Printing & Photocopies",
            "type":"Services"
        }
    ],
    "sg:phone":"+1 613 239 3834",
    "sg:postcode":"K1P 6L2",
    "sg:province":"ON",
    "sg:tags":[
        "printer",
        "duplicating",
        "copying"
    ],
    "wof:name":"Tph the Printing House Ltd",
    "wof:placetype":"venue"
},
  "geometry": {"coordinates":[-75.698898,45.421761],"type":"Point"}
}