{
  "type": "Feature",
  "properties": {
    "addr:full":"5927 148 St Surrey BC V3S 3B9",
    "addr:housenumber":"5927",
    "addr:postcode":"v3s 3b9",
    "addr:street":"148 St",
    "iso:country":"CA",
    "sg:address":"5927 148 St",
    "sg:city":"Surrey",
    "sg:classifiers":[
        {
            "category":"Building & Trades",
            "subcategory":"Construction",
            "type":"Services"
        }
    ],
    "sg:phone":"+1 604 599 6875",
    "sg:postcode":"V3S 3B9",
    "sg:province":"BC",
    "sg:tags":[
        "masonry",
        "contractor"
    ],
    "wof:name":"Kiener's A Masonry",
    "wof:placetype":"venue"
},
  "geometry": {"coordinates":[-122.812462,49.110416],"type":"Point"}
}