{
  "type": "Feature",
  "properties": {
    "addr:full":"Regina SK S4P 3C6",
    "addr:postcode":"s4p 3c6",
    "iso:country":"CA",
    "sg:city":"Regina",
    "sg:classifiers":[
        {
            "category":"Sports & Exercise",
            "subcategory":"Golf",
            "type":"Entertainment"
        }
    ],
    "sg:phone":"+1 306 777 7739",
    "sg:postcode":"S4P 3C6",
    "sg:province":"SK",
    "sg:tags":[
        "course"
    ],
    "wof:name":"Murray Golf Course",
    "wof:placetype":"venue"
},
  "geometry": {"coordinates":[-104.63130188,50.4247093201],"type":"Point"}
}