{
  "type": "Feature",
  "properties": {
    "addr:full":"51 Boul DE LA Seigneurie E Blainville QC J7C 4G6",
    "addr:housenumber":"51",
    "addr:postcode":"j7c 4g6",
    "addr:street":"Boul De La Seigneurie E",
    "iso:country":"CA",
    "sg:address":"51 Boul DE LA Seigneurie E",
    "sg:city":"Blainville",
    "sg:classifiers":[
        {
            "category":"Building & Trades",
            "subcategory":"Construction",
            "type":"Services"
        }
    ],
    "sg:phone":"+1 450 430 7888",
    "sg:postcode":"J7C 4G6",
    "sg:province":"QC",
    "sg:tags":[
        "masonry",
        "contractor"
    ],
    "wof:name":"Maconnerie Asp Inc",
    "wof:placetype":"venue"
},
  "geometry": {"coordinates":[-73.86328125,45.6720199585],"type":"Point"}
}