{
  "type": "Feature",
  "properties": {
    "addr:full":"Woodstock NB E7M 1L2",
    "addr:postcode":"e7m 1l2",
    "iso:country":"CA",
    "sg:city":"Woodstock",
    "sg:classifiers":[
        {
            "category":"Insurance",
            "subcategory":"Insurance Agent",
            "type":"Services"
        }
    ],
    "sg:phone":"+1 506 328 9328",
    "sg:postcode":"E7M 1L2",
    "sg:province":"NB",
    "wof:name":"CO-Operators General Insurance",
    "wof:placetype":"venue"
},
  "geometry": {"coordinates":[-67.590805,46.158695],"type":"Point"}
}