{
  "type": "Feature",
  "properties": {
    "addr:full":"188 Main St E Hawkesbury ON K6A 1A5",
    "addr:housenumber":"188",
    "addr:postcode":"k6a 1a5",
    "addr:street":"Main St E",
    "iso:country":"CA",
    "sg:address":"188 Main St E",
    "sg:city":"Hawkesbury",
    "sg:classifiers":[
        {
            "category":"Shopping",
            "type":"Retail Goods"
        }
    ],
    "sg:phone":"+1 613 632 2382",
    "sg:postcode":"K6A 1A5",
    "sg:province":"ON",
    "sg:tags":[
        "picture",
        "photographic",
        "supply"
    ],
    "wof:name":"Bogue Photo Hawkesbury Ltd",
    "wof:placetype":"venue"
},
  "geometry": {"coordinates":[-74.609306,45.609653],"type":"Point"}
}