{
  "type": "Feature",
  "properties": {
    "addr:full":"Gloucester ON K1J 7T2",
    "addr:postcode":"k1j 7t2",
    "iso:country":"CA",
    "sg:city":"Gloucester",
    "sg:classifiers":[
        {
            "category":"Banks & Credit Unions",
            "subcategory":"Investment Brokerage",
            "type":"Services"
        }
    ],
    "sg:phone":"+1 613 748 3455",
    "sg:postcode":"K1J 7T2",
    "sg:province":"ON",
    "sg:tags":[
        "consultant",
        "planning",
        "financial"
    ],
    "wof:name":"Financiere Liberte 55 Une Div",
    "wof:placetype":"venue"
},
  "geometry": {"coordinates":[-75.6319198608,45.421962738],"type":"Point"}
}