{
  "type": "Feature",
  "properties": {
    "iso:country":"CA",
    "sg:address":"54 1st St",
    "sg:city":"Souris",
    "sg:classifiers":[
        {
            "category":"Personal",
            "subcategory":"Beauty Salon",
            "type":"Services"
        }
    ],
    "sg:phone":"+1 204 483 2180",
    "sg:postcode":"R0K 2C0",
    "sg:province":"MB",
    "wof:name":"Souris Hair Unique",
    "wof:placetype":"venue"
},
  "geometry": {"coordinates":[-100.258865,49.620834],"type":"Point"}
}