{
  "type": "Feature",
  "properties": {
    "addr:full":"1402 Fletcher Rd Saskatoon SK S7M 5J4",
    "addr:housenumber":"1402",
    "addr:postcode":"s7m 5j4",
    "addr:street":"Fletcher Rd",
    "iso:country":"CA",
    "sg:address":"1402 Fletcher Rd",
    "sg:city":"Saskatoon",
    "sg:classifiers":[
        {
            "category":"Wholesale",
            "subcategory":"Farm Supplies",
            "type":"Manufacturing & Wholesale Goods"
        }
    ],
    "sg:phone":"+1 306 384 6116",
    "sg:postcode":"S7M 5J4",
    "sg:province":"SK",
    "sg:tags":[
        "feed"
    ],
    "wof:name":"Finer Feeds Ltd",
    "wof:placetype":"venue"
},
  "geometry": {"coordinates":[-106.707787,52.108326],"type":"Point"}
}