{
  "type": "Feature",
  "properties": {
    "addr:full":"2799 Main St Hillsborough NB E4H 2X4",
    "addr:housenumber":"2799",
    "addr:postcode":"e4h 2x4",
    "addr:street":"Main St",
    "iso:country":"CA",
    "sg:address":"2799 Main St",
    "sg:city":"Hillsborough",
    "sg:classifiers":[
        {
            "category":"Food & Beverages",
            "subcategory":"Groceries & Convenience Stores",
            "type":"Retail Goods"
        }
    ],
    "sg:phone":"+1 506 734 2650",
    "sg:postcode":"E4H 2X4",
    "sg:province":"NB",
    "wof:name":"Hillsborough Irving Cnvnc",
    "wof:placetype":"venue"
},
  "geometry": {"coordinates":[-64.6483078003,45.9270095825],"type":"Point"}
}