{
  "type": "Feature",
  "properties": {
    "iso:country":"CA",
    "sg:city":"Mississauga",
    "sg:classifiers":[
        {
            "category":"Health Services",
            "subcategory":"Doctor",
            "type":"Services"
        }
    ],
    "sg:phone":"+1 905 277 9882",
    "sg:postcode":"L4Y 4G4",
    "sg:province":"ON",
    "sg:tags":[
        "physician",
        "surgeon"
    ],
    "wof:name":"Mississauga Sleep Disorders",
    "wof:placetype":"venue"
},
  "geometry": {"coordinates":[-79.584724,43.608334],"type":"Point"}
}