{
  "type": "Feature",
  "properties": {
    "addr:full":"2500 Ch Des Quatre-Bourgeois Sainte-Foy QC G1V 4P9",
    "addr:postcode":"2500;g1v 4p9",
    "addr:street":"Ch Des Quatre-Bourgeois",
    "iso:country":"CA",
    "sg:address":"2500 Ch Des Quatre-Bourgeois",
    "sg:city":"Sainte-Foy",
    "sg:classifiers":[
        {
            "category":"Retail",
            "subcategory":"Laundry & Dry Cleaning",
            "type":"Services"
        }
    ],
    "sg:phone":"+1 418 657 7070",
    "sg:postcode":"G1V 4P9",
    "sg:province":"QC",
    "sg:tags":[
        "cleaners"
    ],
    "wof:name":"Coordonerie Nettoyeur",
    "wof:placetype":"venue"
},
  "geometry": {"coordinates":[-71.287178,46.782433],"type":"Point"}
}