{
  "type": "Feature",
  "properties": {
    "addr:full":"12 William St Paris ON N3L 1K7",
    "addr:housenumber":"12",
    "addr:postcode":"n3l 1k7",
    "addr:street":"William St",
    "iso:country":"CA",
    "sg:address":"12 William St",
    "sg:city":"Paris",
    "sg:classifiers":[
        {
            "category":"Education",
            "subcategory":"Library",
            "type":"Public Place"
        }
    ],
    "sg:phone":"+1 519 442 2433",
    "sg:postcode":"N3L 1K7",
    "sg:province":"ON",
    "wof:name":"County of Brant Public Library",
    "wof:placetype":"venue"
},
  "geometry": {"coordinates":[-80.386391,43.19355],"type":"Point"}
}