{
  "type": "Feature",
  "properties": {
    "addr:full":"142 Basinview Dr Bedford NS B4A 3J8",
    "addr:housenumber":"142",
    "addr:postcode":"b4a 3j8",
    "addr:street":"Basinview Dr",
    "iso:country":"CA",
    "sg:address":"142 Basinview Dr",
    "sg:city":"Bedford",
    "sg:classifiers":[
        {
            "category":"Wholesale",
            "subcategory":"Electrical",
            "type":"Manufacturing & Wholesale Goods"
        }
    ],
    "sg:phone":"+1 902 835 1910",
    "sg:postcode":"B4A 3J8",
    "sg:province":"NS",
    "sg:tags":[
        "supply",
        "sign"
    ],
    "wof:name":"Sign Equipment Canada Ltd",
    "wof:placetype":"venue"
},
  "geometry": {"coordinates":[-63.679695,44.720188],"type":"Point"}
}