{
  "type": "Feature",
  "properties": {
    "addr:full":"163 Dundas St London ON N6A 1G4",
    "addr:housenumber":"163",
    "addr:postcode":"n6a 1g4",
    "addr:street":"Dundas St",
    "iso:country":"CA",
    "sg:address":"163 Dundas St",
    "sg:city":"London",
    "sg:classifiers":[
        {
            "category":"Shopping",
            "subcategory":"Discount & Variety Stores",
            "type":"Retail Goods"
        }
    ],
    "sg:phone":"+1 519 438 0883",
    "sg:postcode":"N6A 1G4",
    "sg:province":"ON",
    "wof:name":"Smoke Shop",
    "wof:placetype":"venue"
},
  "geometry": {"coordinates":[-81.24936700000001,42.983662],"type":"Point"}
}