{
  "type": "Feature",
  "properties": {
    "iso:country":"CA",
    "sg:address":"518 Rue Sara",
    "sg:city":"Ascot",
    "sg:classifiers":[
        {
            "category":"Retail",
            "subcategory":"Animal Services",
            "type":"Services"
        }
    ],
    "sg:phone":"+1 819 565 2434",
    "sg:postcode":"J1H 5V8",
    "sg:province":"QC",
    "sg:tags":[
        "pet",
        "grooming",
        "washing"
    ],
    "wof:name":"Toilettage CA-Line",
    "wof:placetype":"venue"
},
  "geometry": {"coordinates":[-71.8920211792,45.3783416748],"type":"Point"}
}