{
  "type": "Feature",
  "properties": {
    "addr:full":"1118 King St E Cambridge ON N3H 3P6",
    "addr:housenumber":"1118",
    "addr:postcode":"n3h 3p6",
    "addr:street":"King St E",
    "iso:country":"CA",
    "sg:address":"1118 King St E",
    "sg:city":"Cambridge",
    "sg:classifiers":[
        {
            "category":"Education",
            "subcategory":"Special Training",
            "type":"Public Place"
        }
    ],
    "sg:phone":"+1 519 650 1659",
    "sg:postcode":"N3H 3P6",
    "sg:province":"ON",
    "sg:tags":[
        "instruction",
        "music"
    ],
    "wof:name":"Preston Music Studios",
    "wof:placetype":"venue"
},
  "geometry": {"coordinates":[-80.352737,43.392765],"type":"Point"}
}