{
  "type": "Feature",
  "properties": {
    "addr:full":"555 4 Ave SW Calgary AB T2P 3E7",
    "addr:housenumber":"555",
    "addr:postcode":"t2p 3e7",
    "addr:street":"4 Ave Sw",
    "iso:country":"CA",
    "sg:address":"555 4 Ave SW",
    "sg:city":"Calgary",
    "sg:classifiers":[
        {
            "category":"Mining & Drilling",
            "type":"Manufacturing & Wholesale Goods"
        }
    ],
    "sg:phone":"+1 403 262 9077",
    "sg:postcode":"T2P 3E7",
    "sg:province":"AB",
    "sg:tags":[
        "development",
        "gas",
        "oil",
        "exploration"
    ],
    "wof:name":"Real Resources Inc",
    "wof:placetype":"venue"
},
  "geometry": {"coordinates":[-114.07257799999999,51.049435],"type":"Point"}
}