{
  "type": "Feature",
  "properties": {
    "iso:country":"CA",
    "sg:address":"3335 Ch Queen-Mary",
    "sg:city":"Montreal",
    "sg:classifiers":[
        {
            "category":"Retail",
            "subcategory":"Laundry & Dry Cleaning",
            "type":"Services"
        }
    ],
    "sg:phone":"+1 514 342 4534",
    "sg:postcode":"H3V 1A1",
    "sg:province":"QC",
    "sg:tags":[
        "cleaners"
    ],
    "wof:name":"Florida Dry Cleaners Inc",
    "wof:placetype":"venue"
},
  "geometry": {"coordinates":[-73.618019104,45.4964332581],"type":"Point"}
}