{
  "type": "Feature",
  "properties": {
    "addr:full":"Mississauga ON L4Z 3K6",
    "addr:postcode":"l4z 3k6",
    "iso:country":"CA",
    "sg:city":"Mississauga",
    "sg:classifiers":[
        {
            "category":"Banks & Credit Unions",
            "subcategory":"Bank",
            "type":"Services"
        }
    ],
    "sg:phone":"+1 905 568 1476",
    "sg:postcode":"L4Z 3K6",
    "sg:province":"ON",
    "wof:name":"National Bank of Canada",
    "wof:placetype":"venue"
},
  "geometry": {"coordinates":[-79.6454772949,43.6136665344],"type":"Point"}
}