{
  "type": "Feature",
  "properties": {
    "iso:country":"CA",
    "sg:address":"18 King St E",
    "sg:city":"Bolton",
    "sg:classifiers":[
        {
            "category":"Building & Trades",
            "subcategory":"Electrical",
            "type":"Services"
        }
    ],
    "sg:phone":"+1 905 857 3827",
    "sg:postcode":"L7E 1E8",
    "sg:province":"ON",
    "sg:tags":[
        "electric",
        "contractor"
    ],
    "wof:name":"Budge Electric",
    "wof:placetype":"venue"
},
  "geometry": {"coordinates":[-79.7377700806,43.8799209595],"type":"Point"}
}