{
  "type": "Feature",
  "properties": {
    "addr:full":"4054 Rue Jean-Talon O Montreal QC H4P 1V5",
    "addr:housenumber":"4054",
    "addr:postcode":"h4p 1v5",
    "addr:street":"Rue Jean-Talon O",
    "iso:country":"CA",
    "sg:address":"4054 Rue Jean-Talon O",
    "sg:city":"Montreal",
    "sg:classifiers":[
        {
            "category":"Shopping",
            "subcategory":"Bicycles & Sporting Goods",
            "type":"Retail Goods"
        }
    ],
    "sg:phone":"+1 514 727 9700",
    "sg:postcode":"H4P 1V5",
    "sg:province":"QC",
    "wof:name":"Sacs Sports Inc",
    "wof:placetype":"venue"
},
  "geometry": {"coordinates":[-73.645081,45.5019],"type":"Point"}
}