{
  "type": "Feature",
  "properties": {
    "addr:full":"311 Mountain View Rd Arnprior ON K7S 3H6",
    "addr:housenumber":"311",
    "addr:postcode":"k7s 3h6",
    "addr:street":"Mountain View Rd",
    "iso:country":"CA",
    "sg:address":"311 Mountain View Rd",
    "sg:city":"Arnprior",
    "sg:classifiers":[
        {
            "category":"Recreation",
            "type":"Entertainment"
        }
    ],
    "sg:phone":"+1 613 623 8919",
    "sg:postcode":"K7S 3H6",
    "sg:province":"ON",
    "sg:tags":[
        "course",
        "golf"
    ],
    "wof:name":"Mountain Creek Golf Course",
    "wof:placetype":"venue"
},
  "geometry": {"coordinates":[-76.358368,45.435635],"type":"Point"}
}