{
  "type": "Feature",
  "properties": {
    "addr:full":"2224 Departure Bay Rd Nanaimo BC V9S 3V8",
    "addr:postcode":"2224;v9s 3v8",
    "addr:street":"Departure Bay Rd",
    "iso:country":"CA",
    "sg:address":"2224 Departure Bay Rd",
    "sg:city":"Nanaimo",
    "sg:classifiers":[
        {
            "category":"Health Services",
            "subcategory":"Chiropractor",
            "type":"Services"
        }
    ],
    "sg:phone":"+1 250 758 6121",
    "sg:postcode":"V9S 3V8",
    "sg:province":"BC",
    "wof:name":"Lindsay, W Rod DC",
    "wof:placetype":"venue"
},
  "geometry": {"coordinates":[-123.96904000000001,49.193691],"type":"Point"}
}