{
  "type": "Feature",
  "properties": {
    "addr:full":"110 Main St E Vankleek Hill ON K0B 1R0",
    "addr:housenumber":"110",
    "addr:postcode":"k0b 1r0",
    "addr:street":"Main St E Vankleek Hill",
    "iso:country":"CA",
    "sg:address":"110 Main St E",
    "sg:city":"Vankleek Hill",
    "sg:classifiers":[
        {
            "category":"Shopping",
            "subcategory":"Clothing, Apparel, & Fashions",
            "type":"Retail Goods"
        }
    ],
    "sg:phone":"+1 613 678 2120",
    "sg:postcode":"K0B 1R0",
    "sg:province":"ON",
    "wof:name":"White Palace Store",
    "wof:placetype":"venue"
},
  "geometry": {"coordinates":[-74.6490478516,45.5186538696],"type":"Point"}
}