{
  "type": "Feature",
  "properties": {
    "addr:full":"171 Broadway Orangeville ON L9W 1K2",
    "addr:housenumber":"171",
    "addr:postcode":"l9w 1k2",
    "addr:street":"Broadway",
    "iso:country":"CA",
    "sg:address":"171 Broadway",
    "sg:city":"Orangeville",
    "sg:classifiers":[
        {
            "category":"Restaurant",
            "type":"Food & Drink"
        }
    ],
    "sg:phone":"+1 519 941 9533",
    "sg:postcode":"L9W 1K2",
    "sg:province":"ON",
    "wof:name":"Winchester Arms Orangeville",
    "wof:placetype":"venue"
},
  "geometry": {"coordinates":[-80.0968704224,43.9195213318],"type":"Point"}
}