{
  "type": "Feature",
  "properties": {
    "addr:full":"8255 Av Mountain Sights # 515 Montreal QC H4P 2B5",
    "addr:housenumber":"8255",
    "addr:postcode":"h4p 2b5",
    "addr:street":"Av Mountain Sights # 515",
    "iso:country":"CA",
    "sg:address":"8255 Av Mountain Sights # 515",
    "sg:city":"Montreal",
    "sg:classifiers":[
        {
            "category":"Personal",
            "type":"Services"
        }
    ],
    "sg:phone":"+1 514 737 3280",
    "sg:postcode":"H4P 2B5",
    "sg:province":"QC",
    "sg:tags":[
        "consultant",
        "fashion"
    ],
    "wof:name":"Mad-Mag Fashion Inc",
    "wof:placetype":"venue"
},
  "geometry": {"coordinates":[-73.65795135499999,45.5006599426],"type":"Point"}
}