{
  "type": "Feature",
  "properties": {
    "iso:country":"CA",
    "sg:address":"1199 Rue DE Bleury",
    "sg:city":"Montreal",
    "sg:classifiers":[
        {
            "category":"Education",
            "subcategory":"School",
            "type":"Public Place"
        }
    ],
    "sg:phone":"+1 514 395 2359",
    "sg:postcode":"H3B 3J1",
    "sg:province":"QC",
    "wof:name":"Notre Theatre",
    "wof:placetype":"venue"
},
  "geometry": {"coordinates":[-73.565369,45.505733],"type":"Point"}
}