{
  "type": "Feature",
  "properties": {
    "addr:full":"120 Silver Star Blvd # A Scarborough ON M1V 4V8",
    "addr:housenumber":"120",
    "addr:postcode":"m1v 4v8",
    "addr:street":"Silver Star Blvd # A",
    "iso:country":"CA",
    "sg:address":"120 Silver Star Blvd # A",
    "sg:city":"Scarborough",
    "sg:classifiers":[
        {
            "category":"Wholesale",
            "subcategory":"Auto Parts",
            "type":"Manufacturing & Wholesale Goods"
        }
    ],
    "sg:phone":"+1 416 293 4420",
    "sg:postcode":"M1V 4V8",
    "sg:province":"ON",
    "sg:tags":[
        "automobile",
        "supply"
    ],
    "wof:name":"Fishman Engineering",
    "wof:placetype":"venue"
},
  "geometry": {"coordinates":[-79.292259,43.807007],"type":"Point"}
}