{
  "type": "Feature",
  "properties": {
    "addr:full":"3620 32 St NE Calgary AB T1Y 6G7",
    "addr:housenumber":"3620",
    "addr:postcode":"t1y 6g7",
    "addr:street":"32 St Ne",
    "iso:country":"CA",
    "sg:address":"3620 32 St NE",
    "sg:city":"Calgary",
    "sg:classifiers":[
        {
            "category":"Manufacturing",
            "subcategory":"Chemicals & Compounds",
            "type":"Manufacturing & Wholesale Goods"
        }
    ],
    "sg:phone":"+1 403 291 8444",
    "sg:postcode":"T1Y 6G7",
    "sg:province":"AB",
    "wof:name":"Nova Chemicals Technical Ctr",
    "wof:placetype":"venue"
},
  "geometry": {"coordinates":[-113.98839599999999,51.084915],"type":"Point"}
}