{
  "type": "Feature",
  "properties": {
    "iso:country":"CA",
    "sg:address":"1235 26 Ave SE",
    "sg:city":"Calgary",
    "sg:classifiers":[
        {
            "category":"Shopping",
            "subcategory":"Used Merchandise",
            "type":"Retail Goods"
        }
    ],
    "sg:phone":"+1 403 291 5208",
    "sg:postcode":"T2G 1R7",
    "sg:province":"AB",
    "sg:tags":[
        "flea",
        "food",
        "market"
    ],
    "wof:name":"Crossroads Markets",
    "wof:placetype":"venue"
},
  "geometry": {"coordinates":[-114.035888672,51.0304641724],"type":"Point"}
}