{
  "type": "Feature",
  "properties": {
    "addr:full":"1049 4th Ave W Owen Sound ON N4K 4W1",
    "addr:housenumber":"1049",
    "addr:postcode":"n4k 4w1",
    "addr:street":"4Th Ave W",
    "iso:country":"CA",
    "sg:address":"1049 4th Ave W",
    "sg:city":"Owen Sound",
    "sg:classifiers":[
        {
            "category":"Organizations",
            "subcategory":"Religious Organization",
            "type":"Services"
        }
    ],
    "sg:phone":"+1 519 376 9710",
    "sg:postcode":"N4K 4W1",
    "sg:province":"ON",
    "sg:tags":[
        "church"
    ],
    "wof:name":"Lutheran Church of Our Savior",
    "wof:placetype":"venue"
},
  "geometry": {"coordinates":[-80.949501,44.567913],"type":"Point"}
}