{
  "type": "Feature",
  "properties": {
    "iso:country":"CA",
    "sg:address":"55 Collier St",
    "sg:city":"Barrie",
    "sg:classifiers":[
        {
            "category":"Utilities",
            "subcategory":"Mobile Phone",
            "type":"Services"
        }
    ],
    "sg:phone":"+1 705 726 9922",
    "sg:postcode":"L4M 1G7",
    "sg:province":"ON",
    "sg:tags":[
        "equipment",
        "paging",
        "signaling",
        "system"
    ],
    "wof:name":"Wise Advantage",
    "wof:placetype":"venue"
},
  "geometry": {"coordinates":[-79.6871109009,44.3902702332],"type":"Point"}
}