{
  "type": "Feature",
  "properties": {
    "addr:full":"80 Rue Principale E Sainte-Agathe-Des-Monts QC J8C 1J7",
    "addr:housenumber":"80",
    "addr:postcode":"j8c 1j7",
    "addr:street":"Rue Principale E Sainte-Agathe-Des-Monts",
    "iso:country":"CA",
    "sg:address":"80 Rue Principale E",
    "sg:city":"Sainte-Agathe-Des-Monts",
    "sg:classifiers":[
        {
            "category":"Shopping",
            "subcategory":"Pharmacy",
            "type":"Retail Goods"
        }
    ],
    "sg:phone":"+1 819 326 5444",
    "sg:postcode":"J8C 1J7",
    "sg:province":"QC",
    "wof:name":"Jean Coutu",
    "wof:placetype":"venue"
},
  "geometry": {"coordinates":[-74.28454600000001,46.046646],"type":"Point"}
}