{
  "type": "Feature",
  "properties": {
    "addr:full":"53 Easton Dr Selkirk MB R1A 2B3",
    "addr:housenumber":"53",
    "addr:postcode":"r1a 2b3",
    "addr:street":"Easton Dr",
    "iso:country":"CA",
    "sg:address":"53 Easton Dr",
    "sg:city":"Selkirk",
    "sg:classifiers":[
        {
            "category":"Wholesale",
            "subcategory":"Construction Materials",
            "type":"Manufacturing & Wholesale Goods"
        }
    ],
    "sg:phone":"+1 204 482 5544",
    "sg:postcode":"R1A 2B3",
    "sg:province":"MB",
    "sg:tags":[
        "sand",
        "gravel"
    ],
    "wof:name":"Fort Garry Bldg Products Ltd",
    "wof:placetype":"venue"
},
  "geometry": {"coordinates":[-96.882133,50.155731],"type":"Point"}
}