{
  "type": "Feature",
  "properties": {
    "iso:country":"CA",
    "sg:address":"200 Av Du Pont S # 7",
    "sg:city":"Alma",
    "sg:classifiers":[
        {
            "category":"Professional",
            "subcategory":"Engineering",
            "type":"Services"
        }
    ],
    "sg:phone":"+1 418 668 5236",
    "sg:postcode":"G8B 2T6",
    "sg:province":"QC",
    "sg:tags":[
        "engineer"
    ],
    "wof:name":"Cegertec Inc",
    "wof:placetype":"venue"
},
  "geometry": {"coordinates":[-71.6445159912,48.5436172485],"type":"Point"}
}