{
  "type": "Feature",
  "properties": {
    "addr:full":"6065 Paddle Rd Mississauga ON L5N 1X8",
    "addr:housenumber":"6065",
    "addr:postcode":"l5n 1x8",
    "addr:street":"Paddle Rd",
    "iso:country":"CA",
    "sg:address":"6065 Paddle Rd",
    "sg:city":"Mississauga",
    "sg:classifiers":[
        {
            "category":"Freight",
            "type":"Transportation"
        }
    ],
    "sg:phone":"+1 905 542 1811",
    "sg:postcode":"L5N 1X8",
    "sg:province":"ON",
    "sg:tags":[
        "consultant"
    ],
    "wof:name":"Ralen Transportation Mgmt Ltd",
    "wof:placetype":"venue"
},
  "geometry": {"coordinates":[-79.74335499999999,43.571491],"type":"Point"}
}