{
  "type": "Feature",
  "properties": {
    "addr:full":"2131 Washington St Rossland BC V0G 1Y0",
    "addr:housenumber":"2131",
    "addr:postcode":"v0g 1y0",
    "addr:street":"Washington St",
    "iso:country":"CA",
    "sg:address":"2131 Washington St",
    "sg:city":"Rossland",
    "sg:classifiers":[
        {
            "category":"Building & Trades",
            "subcategory":"Landscaping Services",
            "type":"Services"
        }
    ],
    "sg:phone":"+1 250 362 3391",
    "sg:postcode":"V0G 1Y0",
    "sg:province":"BC",
    "sg:tags":[
        "sprinkler",
        "landscape",
        "contractor"
    ],
    "wof:name":"LA Face Contracting",
    "wof:placetype":"venue"
},
  "geometry": {"coordinates":[-117.80027008099999,49.0786018372],"type":"Point"}
}