{
  "type": "Feature",
  "properties": {
    "addr:full":"Thetford Mines QC G6G 1J7",
    "addr:postcode":"g6g 1j7",
    "iso:country":"CA",
    "sg:city":"Thetford Mines",
    "sg:classifiers":[
        {
            "category":"Professional",
            "subcategory":"Accounting & Tax Preparation",
            "type":"Services"
        }
    ],
    "sg:phone":"+1 418 335 7511",
    "sg:postcode":"G6G 1J7",
    "sg:province":"QC",
    "sg:tags":[
        "accountant"
    ],
    "wof:name":"Raymond Chabot Grant Thornton",
    "wof:placetype":"venue"
},
  "geometry": {"coordinates":[-71.303703,46.087502],"type":"Point"}
}