{
  "type": "Feature",
  "properties": {
    "addr:full":"5404 Dalton Dr NW Calgary AB T3A 2C3",
    "addr:housenumber":"5404",
    "addr:postcode":"t3a 2c3",
    "addr:street":"Dalton Dr Nw",
    "iso:country":"CA",
    "sg:address":"5404 Dalton Dr NW",
    "sg:city":"Calgary",
    "sg:classifiers":[
        {
            "category":"Autos & Motor Vehicles",
            "subcategory":"Auto Supplies",
            "type":"Retail Goods"
        }
    ],
    "sg:phone":"+1 403 286 2620",
    "sg:postcode":"T3A 2C3",
    "sg:province":"AB",
    "sg:tags":[
        "automobile",
        "parts"
    ],
    "wof:name":"Canadian Tire Gas Bar",
    "wof:placetype":"venue"
},
  "geometry": {"coordinates":[-114.150527954,51.1009483337],"type":"Point"}
}