{
  "type": "Feature",
  "properties": {
    "addr:full":"723 Av Bergeron Roberval QC G8H 3L5",
    "addr:postcode":"g8h 3l5",
    "addr:street":"723 Av Bergeron",
    "iso:country":"CA",
    "sg:address":"723 Av Bergeron",
    "sg:city":"Roberval",
    "sg:classifiers":[
        {
            "category":"Personal",
            "subcategory":"Beauty Salon",
            "type":"Services"
        }
    ],
    "sg:phone":"+1 418 275 7214",
    "sg:postcode":"G8H 3L5",
    "sg:province":"QC",
    "wof:name":"Centre Sante-Beaute Madonnova",
    "wof:placetype":"venue"
},
  "geometry": {"coordinates":[-72.233459,48.513958],"type":"Point"}
}