{
  "type": "Feature",
  "properties": {
    "iso:country":"CA",
    "sg:city":"Vanderhoof",
    "sg:classifiers":[
        {
            "category":"Professional",
            "subcategory":"Research",
            "type":"Services"
        }
    ],
    "sg:phone":"+1 250 567 9496",
    "sg:postcode":"V0J 3A0",
    "sg:province":"BC",
    "sg:tags":[
        "archaeologist"
    ],
    "wof:name":"Traces Archaeological Research",
    "wof:placetype":"venue"
},
  "geometry": {"coordinates":[-124.012901306,54.0139770508],"type":"Point"}
}