{
  "type": "Feature",
  "properties": {
    "addr:full":"6800 Av Du Parc Montreal QC H3N 1W7",
    "addr:housenumber":"6800",
    "addr:postcode":"h3n 1w7",
    "addr:street":"Av Du Parc",
    "iso:country":"CA",
    "sg:address":"6800 Av Du Parc",
    "sg:city":"Montreal",
    "sg:classifiers":[
        {
            "category":"Building & Trades",
            "subcategory":"Construction",
            "type":"Services"
        }
    ],
    "sg:phone":"+1 514 274 4263",
    "sg:postcode":"H3N 1W7",
    "sg:province":"QC",
    "sg:tags":[
        "maker",
        "cabinet"
    ],
    "wof:name":"Ebenisterie Yves Charland Enrg",
    "wof:placetype":"venue"
},
  "geometry": {"coordinates":[-73.616524,45.5284],"type":"Point"}
}