{
  "type": "Feature",
  "properties": {
    "addr:full":"10500 Av Du Bois-DE-Boulogne Montreal QC H4N 1L3",
    "addr:housenumber":"10500",
    "addr:postcode":"h4n 1l3",
    "addr:street":"Av Du Bois-De-Boulogne",
    "iso:country":"CA",
    "sg:address":"10500 Av Du Bois-DE-Boulogne",
    "sg:city":"Montreal",
    "sg:classifiers":[
        {
            "category":"Organizations",
            "subcategory":"Labor Organization",
            "type":"Services"
        }
    ],
    "sg:phone":"+1 514 335 1936",
    "sg:postcode":"H4N 1L3",
    "sg:province":"QC",
    "wof:name":"Syndicat-Professeurs-Bois",
    "wof:placetype":"venue"
},
  "geometry": {"coordinates":[-73.6747894287,45.5368804932],"type":"Point"}
}