{
  "type": "Feature",
  "properties": {
    "addr:full":"2251 Pembina Hwy Winnipeg MB R3T 2H1",
    "addr:housenumber":"2251",
    "addr:postcode":"r3t 2h1",
    "addr:street":"Pembina Hwy",
    "iso:country":"CA",
    "sg:address":"2251 Pembina Hwy",
    "sg:city":"Winnipeg",
    "sg:classifiers":[
        {
            "category":"Banks & Credit Unions",
            "subcategory":"Bank",
            "type":"Services"
        }
    ],
    "sg:phone":"+1 204 925 2660",
    "sg:postcode":"R3T 2H1",
    "sg:province":"MB",
    "wof:name":"Cambrian Credit Union",
    "wof:placetype":"venue"
},
  "geometry": {"coordinates":[-97.1536407471,49.809928894],"type":"Point"}
}