{
  "type": "Feature",
  "properties": {
    "iso:country":"CA",
    "sg:address":"11552 Av Bossuet",
    "sg:city":"Montreal-Nord",
    "sg:classifiers":[
        {
            "category":"Professional",
            "subcategory":"Computer Services",
            "type":"Services"
        }
    ],
    "sg:phone":"+1 514 323 3523",
    "sg:postcode":"H1G 4G9",
    "sg:province":"QC",
    "sg:tags":[
        "information",
        "system",
        "consultant"
    ],
    "wof:name":"Rotech Technologies",
    "wof:placetype":"venue"
},
  "geometry": {"coordinates":[-73.621094,45.608856],"type":"Point"}
}