{
  "type": "Feature",
  "properties": {
    "iso:country":"CA",
    "sg:city":"Cap-DE-LA-Madeleine",
    "sg:classifiers":[
        {
            "category":"Building & Trades",
            "subcategory":"Electrical",
            "type":"Services"
        }
    ],
    "sg:phone":"+1 819 376 5325",
    "sg:postcode":"G8T 6K7",
    "sg:province":"QC",
    "sg:tags":[
        "electric",
        "contractor"
    ],
    "wof:name":"Leclerc Electrique Inc",
    "wof:placetype":"venue"
},
  "geometry": {"coordinates":[-72.5255813599,46.3706436157],"type":"Point"}
}