{
  "type": "Feature",
  "properties": {
    "addr:full":"51 Av Talon Baie-Comeau QC G4Z 1J7",
    "addr:postcode":"g4z 1j7",
    "addr:street":"51 Av Talon",
    "iso:country":"CA",
    "sg:address":"51 Av Talon",
    "sg:city":"Baie-Comeau",
    "sg:classifiers":[
        {
            "category":"Shopping",
            "subcategory":"Florist",
            "type":"Retail Goods"
        }
    ],
    "sg:phone":"+1 418 296 9111",
    "sg:postcode":"G4Z 1J7",
    "sg:province":"QC",
    "wof:name":"Fleuriste Au Tournesol Ltee",
    "wof:placetype":"venue"
},
  "geometry": {"coordinates":[-68.1614532471,49.2183609009],"type":"Point"}
}