{
  "type": "Feature",
  "properties": {
    "addr:full":"2180 South Wellington Rd Nanaimo BC V9X 1V8",
    "addr:housenumber":"2180",
    "addr:postcode":"v9x 1v8",
    "addr:street":"South Wellington Rd",
    "iso:country":"CA",
    "sg:address":"2180 South Wellington Rd",
    "sg:city":"Nanaimo",
    "sg:classifiers":[
        {
            "category":"Retail",
            "subcategory":"Auto Rental",
            "type":"Services"
        }
    ],
    "sg:phone":"+1 250 741 0067",
    "sg:postcode":"V9X 1V8",
    "sg:province":"BC",
    "sg:tags":[
        "renting",
        "leasing",
        "supply",
        "equipment",
        "moving",
        "truck"
    ],
    "wof:name":"U-Haul CO Ltd",
    "wof:placetype":"venue"
},
  "geometry": {"coordinates":[-123.977966,49.18058],"type":"Point"}
}