{
  "type": "Feature",
  "properties": {
    "addr:full":"1606 Queen St E Toronto ON M4L 1G2",
    "addr:housenumber":"1606",
    "addr:postcode":"m4l 1g2",
    "addr:street":"Queen St E",
    "iso:country":"CA",
    "sg:address":"1606 Queen St E",
    "sg:city":"Toronto",
    "sg:classifiers":[
        {
            "category":"Restaurant",
            "type":"Food & Drink"
        }
    ],
    "sg:phone":"+1 416 469 5797",
    "sg:postcode":"M4L 1G2",
    "sg:province":"ON",
    "wof:name":"Tulip",
    "wof:placetype":"venue"
},
  "geometry": {"coordinates":[-79.31703186039999,43.6663703918],"type":"Point"}
}