{
  "type": "Feature",
  "properties": {
    "addr:full":"Chilliwack BC V2R 1C8",
    "addr:postcode":"v2r 1c8",
    "iso:country":"CA",
    "sg:city":"Chilliwack",
    "sg:classifiers":[
        {
            "category":"Restaurant",
            "type":"Food & Drink"
        }
    ],
    "sg:phone":"+1 604 824 9996",
    "sg:postcode":"V2R 1C8",
    "sg:province":"BC",
    "wof:name":"Planet Earth Expresso Deli",
    "wof:placetype":"venue"
},
  "geometry": {"coordinates":[-121.957290649,49.1141052246],"type":"Point"}
}