{
  "type": "Feature",
  "properties": {
    "addr:full":"155 Carillon St Vanier ON K1L 5X9",
    "addr:housenumber":"155",
    "addr:postcode":"k1l 5x9",
    "addr:street":"Carillon St",
    "iso:country":"CA",
    "sg:address":"155 Carillon St",
    "sg:city":"Vanier",
    "sg:classifiers":[
        {
            "category":"Organizations",
            "subcategory":"Religious Organization",
            "type":"Services"
        }
    ],
    "sg:phone":"+1 613 740 0607",
    "sg:postcode":"K1L 5X9",
    "sg:province":"ON",
    "sg:tags":[
        "church"
    ],
    "wof:name":"City Church",
    "wof:placetype":"venue"
},
  "geometry": {"coordinates":[-75.666679,45.437332],"type":"Point"}
}