{
  "type": "Feature",
  "properties": {
    "addr:full":"47915 Homestead Rd Berry Mills NB E1G 3S5",
    "addr:housenumber":"47915",
    "addr:postcode":"e1g 3s5",
    "addr:street":"Homestead Rd",
    "iso:country":"CA",
    "sg:address":"47915 Homestead Rd",
    "sg:city":"Berry Mills",
    "sg:classifiers":[
        {
            "category":"Sports & Exercise",
            "subcategory":"Golf",
            "type":"Entertainment"
        }
    ],
    "sg:phone":"+1 506 852 4162",
    "sg:postcode":"E1G 3S5",
    "sg:province":"NB",
    "sg:tags":[
        "course"
    ],
    "wof:name":"Stonehurst Golf Course & Park",
    "wof:placetype":"venue"
},
  "geometry": {"coordinates":[-64.935318,46.113686],"type":"Point"}
}