{
  "type": "Feature",
  "properties": {
    "addr:full":"39 Talbot St W Blenheim ON N0P 1A0",
    "addr:housenumber":"39",
    "addr:postcode":"n0p 1a0",
    "addr:street":"Talbot St W",
    "iso:country":"CA",
    "sg:address":"39 Talbot St W",
    "sg:city":"Blenheim",
    "sg:classifiers":[
        {
            "category":"Banks & Credit Unions",
            "subcategory":"Bank",
            "type":"Services"
        }
    ],
    "sg:phone":"+1 519 676 5454",
    "sg:postcode":"N0P 1A0",
    "sg:province":"ON",
    "wof:name":"Bank of Montreal",
    "wof:placetype":"venue"
},
  "geometry": {"coordinates":[-81.998550415,42.3344612122],"type":"Point"}
}