{
  "type": "Feature",
  "properties": {
    "addr:full":"2355 Trafalgar Rd Oakville ON L6H 6N9",
    "addr:housenumber":"2355",
    "addr:postcode":"l6h 6n9",
    "addr:street":"Trafalgar Rd",
    "iso:country":"CA",
    "sg:address":"2355 Trafalgar Rd",
    "sg:city":"Oakville",
    "sg:classifiers":[
        {
            "category":"Restaurant",
            "type":"Food & Drink"
        }
    ],
    "sg:phone":"+1 905 257 0071",
    "sg:postcode":"L6H 6N9",
    "sg:province":"ON",
    "wof:name":"Wendy's",
    "wof:placetype":"venue"
},
  "geometry": {"coordinates":[-79.713707,43.483738],"type":"Point"}
}