{
  "type": "Feature",
  "properties": {
    "addr:full":"5948 200 St Langley BC V3A 1N3",
    "addr:housenumber":"5948",
    "addr:postcode":"v3a 1n3",
    "addr:street":"200 St",
    "iso:country":"CA",
    "sg:address":"5948 200 St",
    "sg:city":"Langley",
    "sg:classifiers":[
        {
            "category":"Retail",
            "subcategory":"Auto Repair",
            "type":"Services"
        }
    ],
    "sg:phone":"+1 604 534 2886",
    "sg:postcode":"V3A 1N3",
    "sg:province":"BC",
    "sg:tags":[
        "repairing",
        "automobile"
    ],
    "wof:name":"Bostek Auto Inc",
    "wof:placetype":"venue"
},
  "geometry": {"coordinates":[-122.668503,49.110611],"type":"Point"}
}