{
  "type": "Feature",
  "properties": {
    "addr:full":"2429 Boul Du Cure-Labelle Prevost QC J0R 1T0",
    "addr:housenumber":"2429",
    "addr:postcode":"j0r 1t0",
    "addr:street":"Boul Du Cure-Labelle Prevost",
    "iso:country":"CA",
    "sg:address":"2429 Boul Du Cure-Labelle",
    "sg:city":"Prevost",
    "sg:classifiers":[
        {
            "category":"Manufacturing",
            "subcategory":"Building Materials",
            "type":"Manufacturing & Wholesale Goods"
        }
    ],
    "sg:phone":"+1 450 565 2552",
    "sg:postcode":"J0R 1T0",
    "sg:province":"QC",
    "wof:name":"Bois Dalpe & Fils Inc",
    "wof:placetype":"venue"
},
  "geometry": {"coordinates":[-74.04437299999999,45.819515],"type":"Point"}
}