{
  "type": "Feature",
  "properties": {
    "addr:full":"3154 Harmony Rd N Oshawa ON L1H 8L7",
    "addr:housenumber":"3154",
    "addr:postcode":"l1h 8l7",
    "addr:street":"Harmony Rd N",
    "iso:country":"CA",
    "sg:address":"3154 Harmony Rd N",
    "sg:city":"Oshawa",
    "sg:classifiers":[
        {
            "category":"Building & Trades",
            "subcategory":"Construction",
            "type":"Services"
        }
    ],
    "sg:phone":"+1 905 655 4683",
    "sg:postcode":"L1H 8L7",
    "sg:province":"ON",
    "sg:tags":[
        "general",
        "contractor"
    ],
    "wof:name":"Thomas Wieland Construction",
    "wof:placetype":"venue"
},
  "geometry": {"coordinates":[-78.870079,43.985989],"type":"Point"}
}