{
  "type": "Feature",
  "properties": {
    "addr:full":"160 Rue Principale Saint-Andre-Avellin QC J0V 1W0",
    "addr:housenumber":"160",
    "addr:postcode":"j0v 1w0",
    "addr:street":"Rue Principale",
    "iso:country":"CA",
    "sg:address":"160 Rue Principale",
    "sg:city":"Saint-Andre-Avellin",
    "sg:classifiers":[
        {
            "category":"Bars & Pubs",
            "type":"Food & Drink"
        }
    ],
    "sg:phone":"+1 819 428 3044",
    "sg:postcode":"J0V 1W0",
    "sg:province":"QC",
    "sg:tags":[
        "lounge",
        "cocktail"
    ],
    "wof:name":"Piano Bar Chez Pierre",
    "wof:placetype":"venue"
},
  "geometry": {"coordinates":[-75.052734,45.727501],"type":"Point"}
}