{
  "type": "Feature",
  "properties": {
    "addr:full":"333 Av DE LA Cathedrale Rimouski QC G5L 5J5",
    "addr:postcode":"g5l 5j5",
    "addr:street":"333 Av De La Cathedrale",
    "iso:country":"CA",
    "sg:address":"333 Av DE LA Cathedrale",
    "sg:city":"Rimouski",
    "sg:classifiers":[
        {
            "category":"Autos & Motor Vehicles",
            "subcategory":"Motorcycle Sales",
            "type":"Retail Goods"
        }
    ],
    "sg:phone":"+1 418 725 4545",
    "sg:postcode":"G5L 5J5",
    "sg:province":"QC",
    "sg:tags":[
        "snowmobile"
    ],
    "wof:name":"Labonte Scies A Chaine",
    "wof:placetype":"venue"
},
  "geometry": {"coordinates":[-68.518867,48.44548],"type":"Point"}
}