{
  "type": "Feature",
  "properties": {
    "addr:full":"628 Main St Broadview SK S0G 0K0",
    "addr:housenumber":"628",
    "addr:postcode":"s0g 0k0",
    "addr:street":"Main St",
    "iso:country":"CA",
    "sg:address":"628 Main St",
    "sg:city":"Broadview",
    "sg:classifiers":[
        {
            "category":"Food & Beverages",
            "subcategory":"Groceries & Convenience Stores",
            "type":"Retail Goods"
        }
    ],
    "sg:phone":"+1 306 696 2447",
    "sg:postcode":"S0G 0K0",
    "sg:province":"SK",
    "sg:tags":[
        "grocer"
    ],
    "wof:name":"Broadview CO-OP Ltd",
    "wof:placetype":"venue"
},
  "geometry": {"coordinates":[-102.579078674,50.378490448],"type":"Point"}
}