{
  "type": "Feature",
  "properties": {
    "addr:full":"125 Blake St Toronto ON M4J 3E2",
    "addr:housenumber":"125",
    "addr:postcode":"m4j 3e2",
    "addr:street":"Blake St",
    "iso:country":"CA",
    "sg:address":"125 Blake St",
    "sg:city":"Toronto",
    "sg:classifiers":[
        {
            "category":"Retail",
            "subcategory":"Repair Shop",
            "type":"Services"
        }
    ],
    "sg:phone":"+1 416 778 6757",
    "sg:postcode":"M4J 3E2",
    "sg:province":"ON",
    "sg:tags":[
        "refinishing",
        "furniture"
    ],
    "wof:name":"Ross Furniture Refinishing",
    "wof:placetype":"venue"
},
  "geometry": {"coordinates":[-79.339172,43.675228],"type":"Point"}
}