{
  "type": "Feature",
  "properties": {
    "iso:country":"CA",
    "sg:city":"Vancouver",
    "sg:classifiers":[
        {
            "category":"Utilities",
            "subcategory":"Mobile Phone",
            "type":"Services"
        }
    ],
    "sg:phone":"+1 604 708 1918",
    "sg:postcode":"V5V 3N9",
    "sg:province":"BC",
    "sg:tags":[
        "telephone",
        "cellular"
    ],
    "wof:name":"Skynet Communication Svc",
    "wof:placetype":"venue"
},
  "geometry": {"coordinates":[-123.100746155,49.250579834],"type":"Point"}
}