{
  "type": "Feature",
  "properties": {
    "addr:full":"Eagle Lake ON K0M 1M0",
    "addr:postcode":"k0m 1m0",
    "addr:street":"Eagle Lake",
    "iso:country":"CA",
    "sg:city":"Eagle Lake",
    "sg:classifiers":[
        {
            "category":"Travel",
            "subcategory":"Hotels & Motels",
            "type":"Entertainment"
        }
    ],
    "sg:phone":"+1 705 754 2188",
    "sg:postcode":"K0M 1M0",
    "sg:province":"ON",
    "sg:tags":[
        "resort"
    ],
    "wof:name":"Sir Sam's Inn",
    "wof:placetype":"venue"
},
  "geometry": {"coordinates":[-78.50960499999999,45.128593],"type":"Point"}
}