{
  "type": "Feature",
  "properties": {
    "addr:full":"Iron Bridge ON P0R 1H0",
    "addr:postcode":"p0r 1h0",
    "addr:street":"Iron",
    "iso:country":"CA",
    "sg:city":"Iron Bridge",
    "sg:classifiers":[
        {
            "category":"Retail",
            "subcategory":"Auto Repair",
            "type":"Services"
        }
    ],
    "sg:phone":"+1 705 843 2285",
    "sg:postcode":"P0R 1H0",
    "sg:province":"ON",
    "sg:tags":[
        "wrecker"
    ],
    "wof:name":"Randy's Towing",
    "wof:placetype":"venue"
},
  "geometry": {"coordinates":[-83.215851,46.278111],"type":"Point"}
}