{
  "type": "Feature",
  "properties": {
    "addr:full":"246 James St N Hamilton ON L8R 2L3",
    "addr:housenumber":"246",
    "addr:postcode":"l8r 2l3",
    "addr:street":"James St N",
    "iso:country":"CA",
    "sg:address":"246 James St N",
    "sg:city":"Hamilton",
    "sg:classifiers":[
        {
            "category":"Restaurant",
            "type":"Food & Drink"
        }
    ],
    "sg:phone":"+1 905 527 5269",
    "sg:postcode":"L8R 2L3",
    "sg:province":"ON",
    "sg:tags":[
        "shop",
        "coffee"
    ],
    "wof:name":"Bar Michelangelo",
    "wof:placetype":"venue"
},
  "geometry": {"coordinates":[-79.866219,43.262733],"type":"Point"}
}