{
  "type": "Feature",
  "properties": {
    "iso:country":"CA",
    "sg:address":"324 8th Ave",
    "sg:city":"New Denver",
    "sg:classifiers":[
        {
            "category":"Manufacturing",
            "subcategory":"Lumber",
            "type":"Manufacturing & Wholesale Goods"
        }
    ],
    "sg:phone":"+1 250 358 2423",
    "sg:postcode":"V0G 1S0",
    "sg:province":"BC",
    "sg:tags":[
        "company",
        "logging"
    ],
    "wof:name":"Ted Reitmeier Logging",
    "wof:placetype":"venue"
},
  "geometry": {"coordinates":[-117.372840881,49.9935264587],"type":"Point"}
}