{
  "type": "Feature",
  "properties": {
    "addr:full":"182 1st Ave W Battleford SK S0M 0E0",
    "addr:housenumber":"182",
    "addr:postcode":"s0m 0e0",
    "addr:street":"1St Ave W",
    "iso:country":"CA",
    "sg:address":"182 1st Ave W",
    "sg:city":"Battleford",
    "sg:classifiers":[
        {
            "category":"Building & Trades",
            "subcategory":"Electrical",
            "type":"Services"
        }
    ],
    "sg:phone":"+1 306 937 2633",
    "sg:postcode":"S0M 0E0",
    "sg:province":"SK",
    "sg:tags":[
        "electric",
        "contractor"
    ],
    "wof:name":"Gardiner Electric",
    "wof:placetype":"venue"
},
  "geometry": {"coordinates":[-108.305222,52.737545],"type":"Point"}
}