{
  "type": "Feature",
  "properties": {
    "addr:full":"20 Owen St Barrie ON L4M 3G7",
    "addr:housenumber":"20",
    "addr:postcode":"l4m 3g7",
    "addr:street":"Owen St",
    "iso:country":"CA",
    "sg:address":"20 Owen St",
    "sg:city":"Barrie",
    "sg:classifiers":[
        {
            "category":"Organizations",
            "subcategory":"Non-profit Organization",
            "type":"Services"
        }
    ],
    "sg:phone":"+1 705 730 0286",
    "sg:postcode":"L4M 3G7",
    "sg:province":"ON",
    "sg:tags":[
        "addiction",
        "treatment",
        "center"
    ],
    "wof:name":"Barrie Addiction Treatment",
    "wof:placetype":"venue"
},
  "geometry": {"coordinates":[-79.68800400000001,44.389908],"type":"Point"}
}