{
  "type": "Feature",
  "properties": {
    "iso:country":"CA",
    "sg:address":"20 Owen St",
    "sg:city":"Barrie",
    "sg:classifiers":[
        {
            "category":"Organizations",
            "subcategory":"Non-profit Organization",
            "type":"Services"
        }
    ],
    "sg:phone":"+1 705 730 0286",
    "sg:postcode":"L4M 3G7",
    "sg:province":"ON",
    "sg:tags":[
        "addiction",
        "treatment",
        "center"
    ],
    "wof:name":"Barrie Addiction Treatment",
    "wof:placetype":"venue"
},
  "geometry": {"coordinates":[-79.688004,44.389908],"type":"Point"}
}