{
  "type": "Feature",
  "properties": {
    "addr:full":"Antonio St Bissett MB R0E 0J0",
    "addr:postcode":"r0e 0j0",
    "addr:street":"Antonio St",
    "iso:country":"CA",
    "sg:address":"Antonio St",
    "sg:city":"Bissett",
    "sg:classifiers":[
        {
            "category":"Education",
            "subcategory":"School",
            "type":"Public Place"
        }
    ],
    "sg:phone":"+1 204 277 5277",
    "sg:postcode":"R0E 0J0",
    "sg:province":"MB",
    "wof:name":"San Antonio School",
    "wof:placetype":"venue"
},
  "geometry": {"coordinates":[-95.651718,51.026501],"type":"Point"}
}