{
  "type": "Feature",
  "properties": {
    "addr:full":"70 Exhibition St Kentville NS B4N 4K9",
    "addr:housenumber":"70",
    "addr:postcode":"b4n 4k9",
    "addr:street":"Exhibition St",
    "iso:country":"CA",
    "sg:address":"70 Exhibition St",
    "sg:city":"Kentville",
    "sg:classifiers":[
        {
            "category":"Health Services",
            "subcategory":"Doctor",
            "type":"Services"
        }
    ],
    "sg:phone":"+1 902 678 8797",
    "sg:postcode":"B4N 4K9",
    "sg:province":"NS",
    "sg:tags":[
        "dentist"
    ],
    "wof:name":"David E Mac Leod Orthodontics",
    "wof:placetype":"venue"
},
  "geometry": {"coordinates":[-64.492836,45.08379],"type":"Point"}
}