{
  "type": "Feature",
  "properties": {
    "iso:country":"CA",
    "sg:address":"1829 Main St W",
    "sg:city":"Hamilton",
    "sg:classifiers":[
        {
            "category":"Personal",
            "subcategory":"Beauty Salon",
            "type":"Services"
        }
    ],
    "sg:phone":"+1 905 522 4707",
    "sg:postcode":"L8S 1H6",
    "sg:province":"ON",
    "sg:tags":[
        "manicuring"
    ],
    "wof:name":"Fancy Nails",
    "wof:placetype":"venue"
},
  "geometry": {"coordinates":[-79.93887329099999,43.2527732849],"type":"Point"}
}