{
  "type": "Feature",
  "properties": {
    "addr:full":"1038 Manchester Cres Oakville ON L6M 1G2",
    "addr:housenumber":"1038",
    "addr:postcode":"l6m 1g2",
    "addr:street":"Manchester Cres",
    "iso:country":"CA",
    "sg:address":"1038 Manchester Cres",
    "sg:city":"Oakville",
    "sg:classifiers":[
        {
            "category":"Freight",
            "type":"Transportation"
        }
    ],
    "sg:phone":"+1 905 469 0054",
    "sg:postcode":"L6M 1G2",
    "sg:province":"ON",
    "wof:name":"Transmaster Freight Svc",
    "wof:placetype":"venue"
},
  "geometry": {"coordinates":[-79.7130355835,43.4389533997],"type":"Point"}
}