{
  "type": "Feature",
  "properties": {
    "iso:country":"CA",
    "sg:address":"976 Car DE Tracy E",
    "sg:city":"Charlesbourg",
    "sg:classifiers":[
        {
            "category":"Travel",
            "subcategory":"Campground",
            "type":"Entertainment"
        }
    ],
    "sg:phone":"+1 418 622 1289",
    "sg:postcode":"G2L 1K9",
    "sg:province":"QC",
    "sg:tags":[
        "camp"
    ],
    "wof:name":"Camp Bourg-Royal",
    "wof:placetype":"venue"
},
  "geometry": {"coordinates":[-71.249542,46.884903],"type":"Point"}
}