{
  "type": "Feature",
  "properties": {
    "addr:full":"4631 12 St NE Calgary AB T2E 4R3",
    "addr:housenumber":"4631",
    "addr:postcode":"t2e 4r3",
    "addr:street":"12 St Ne",
    "iso:country":"CA",
    "sg:address":"4631 12 St NE",
    "sg:city":"Calgary",
    "sg:classifiers":[
        {
            "category":"Retail",
            "subcategory":"Auto Repair",
            "type":"Services"
        }
    ],
    "sg:phone":"+1 403 250 6915",
    "sg:postcode":"T2E 4R3",
    "sg:province":"AB",
    "sg:tags":[
        "repairing",
        "automobile",
        "radiator"
    ],
    "wof:name":"All Seasons Radiators",
    "wof:placetype":"venue"
},
  "geometry": {"coordinates":[-114.03362274200001,51.0937271118],"type":"Point"}
}