{
  "type": "Feature",
  "properties": {
    "iso:country":"CA",
    "sg:address":"318 Rue Verreault",
    "sg:city":"Saint-Jean-Port-Joli",
    "sg:classifiers":[
        {
            "category":"Manufacturing",
            "subcategory":"Printing",
            "type":"Manufacturing & Wholesale Goods"
        }
    ],
    "sg:phone":"+1 418 598 9590",
    "sg:postcode":"G0R 3G0",
    "sg:province":"QC",
    "sg:tags":[
        "newspaper"
    ],
    "wof:name":"Journal Attisee",
    "wof:placetype":"venue"
},
  "geometry": {"coordinates":[-70.265083,47.213718],"type":"Point"}
}