{
  "type": "Feature",
  "properties": {
    "addr:full":"304 Calahoo Rd Spruce Grove AB T7X 2H6",
    "addr:housenumber":"304",
    "addr:postcode":"t7x 2h6",
    "addr:street":"Calahoo Rd",
    "iso:country":"CA",
    "sg:address":"304 Calahoo Rd",
    "sg:city":"Spruce Grove",
    "sg:classifiers":[
        {
            "category":"Personal",
            "subcategory":"Beauty Salon",
            "type":"Services"
        }
    ],
    "sg:phone":"+1 780 962 9526",
    "sg:postcode":"T7X 2H6",
    "sg:province":"AB",
    "wof:name":"Sahaira's",
    "wof:placetype":"venue"
},
  "geometry": {"coordinates":[-113.90977478000001,53.5432815552],"type":"Point"}
}