{
  "type": "Feature",
  "properties": {
    "addr:full":"2600 Viking Way Richmond BC V6V 1N2",
    "addr:housenumber":"2600",
    "addr:postcode":"v6v 1n2",
    "addr:street":"Viking Way",
    "iso:country":"CA",
    "sg:address":"2600 Viking Way",
    "sg:city":"Richmond",
    "sg:classifiers":[
        {
            "category":"Manufacturing",
            "subcategory":"Building Materials",
            "type":"Manufacturing & Wholesale Goods"
        }
    ],
    "sg:phone":"+1 604 273 3108",
    "sg:postcode":"V6V 1N2",
    "sg:province":"BC",
    "sg:tags":[
        "door"
    ],
    "wof:name":"Richelieu Panel Products",
    "wof:placetype":"venue"
},
  "geometry": {"coordinates":[-123.07311199999999,49.194847],"type":"Point"}
}