{
  "type": "Feature",
  "properties": {
    "addr:full":"822 Danforth Ave Toronto ON M4J 1L6",
    "addr:housenumber":"822",
    "addr:postcode":"m4j 1l6",
    "addr:street":"Danforth Ave",
    "iso:country":"CA",
    "sg:address":"822 Danforth Ave",
    "sg:city":"Toronto",
    "sg:classifiers":[
        {
            "category":"Education",
            "subcategory":"Special Training",
            "type":"Public Place"
        }
    ],
    "sg:phone":"+1 416 406 5355",
    "sg:postcode":"M4J 1L6",
    "sg:province":"ON",
    "sg:tags":[
        "instruction",
        "music"
    ],
    "wof:name":"Elite Music Academy",
    "wof:placetype":"venue"
},
  "geometry": {"coordinates":[-79.34101099999999,43.679836],"type":"Point"}
}