{
  "type": "Feature",
  "properties": {
    "addr:full":"302 3rd St E Meadow Lake SK S9X 1R5",
    "addr:housenumber":"302",
    "addr:postcode":"s9x 1r5",
    "addr:street":"3Rd St E;Lake",
    "iso:country":"CA",
    "sg:address":"302 3rd St E",
    "sg:city":"Meadow Lake",
    "sg:classifiers":[
        {
            "category":"Autos & Motor Vehicles",
            "subcategory":"Automobile Sales",
            "type":"Retail Goods"
        }
    ],
    "sg:phone":"+1 306 236 4411",
    "sg:postcode":"S9X 1R5",
    "sg:province":"SK",
    "sg:tags":[
        "car",
        "dealer"
    ],
    "wof:name":"Northland Plymouth Chrysler",
    "wof:placetype":"venue"
},
  "geometry": {"coordinates":[-108.42787199999999,54.130131],"type":"Point"}
}