{
  "type": "Feature",
  "properties": {
    "iso:country":"CA",
    "sg:address":"3 Arnie's Chance",
    "sg:city":"Stouffville",
    "sg:classifiers":[
        {
            "category":"Building & Trades",
            "subcategory":"Construction",
            "type":"Services"
        }
    ],
    "sg:phone":"+1 905 640 0611",
    "sg:postcode":"L4A 1M1",
    "sg:province":"ON",
    "sg:tags":[
        "general",
        "contractor"
    ],
    "wof:name":"Schickendanz Bros Ltd",
    "wof:placetype":"venue"
},
  "geometry": {"coordinates":[-79.270042,43.964458],"type":"Point"}
}