{
  "type": "Feature",
  "properties": {
    "addr:full":"147 Howey St Red Lake ON P0V 2M0",
    "addr:housenumber":"147",
    "addr:postcode":"p0v 2m0",
    "addr:street":"Howey St",
    "iso:country":"CA",
    "sg:address":"147 Howey St",
    "sg:city":"Red Lake",
    "sg:classifiers":[
        {
            "category":"Manufacturing",
            "subcategory":"Lumber",
            "type":"Manufacturing & Wholesale Goods"
        }
    ],
    "sg:phone":"+1 807 727 1132",
    "sg:postcode":"P0V 2M0",
    "sg:province":"ON",
    "sg:tags":[
        "company",
        "logging"
    ],
    "wof:name":"Red Lake Forest Mgmt CO",
    "wof:placetype":"venue"
},
  "geometry": {"coordinates":[-93.8229064941,51.0216674805],"type":"Point"}
}