{
  "type": "Feature",
  "properties": {
    "iso:country":"CA",
    "sg:address":"109 Greer Ave W",
    "sg:city":"Geraldton",
    "sg:classifiers":[
        {
            "category":"Professional",
            "subcategory":"Computer Services",
            "type":"Services"
        }
    ],
    "sg:phone":"+1 807 854 1569",
    "sg:postcode":"P0T 1M0",
    "sg:province":"ON",
    "sg:tags":[
        "internet"
    ],
    "wof:name":"Astrocom Cable Vision Inc",
    "wof:placetype":"venue"
},
  "geometry": {"coordinates":[-86.94971466059999,49.7073173523],"type":"Point"}
}