{
  "type": "Feature",
  "properties": {
    "addr:full":"2608 Burrard Ave Vanderhoof BC V0J 3A0",
    "addr:housenumber":"2608",
    "addr:postcode":"v0j 3a0",
    "addr:street":"Burrard Ave",
    "iso:country":"CA",
    "sg:address":"2608 Burrard Ave",
    "sg:city":"Vanderhoof",
    "sg:classifiers":[
        {
            "category":"Professional",
            "subcategory":"Lawyer & Legal Services",
            "type":"Services"
        }
    ],
    "sg:phone":"+1 250 567 9277",
    "sg:postcode":"V0J 3A0",
    "sg:province":"BC",
    "sg:tags":[
        "attorney"
    ],
    "wof:name":"Peleshok, Steven F",
    "wof:placetype":"venue"
},
  "geometry": {"coordinates":[-124.00918579099999,54.0254898071],"type":"Point"}
}