{
  "type": "Feature",
  "properties": {
    "iso:country":"CA",
    "sg:address":"1059 Plains Rd E",
    "sg:city":"Burlington",
    "sg:classifiers":[
        {
            "category":"Retail",
            "subcategory":"Animal Services",
            "type":"Services"
        }
    ],
    "sg:phone":"+1 905 634 9999",
    "sg:postcode":"L7T 4K1",
    "sg:province":"ON",
    "sg:tags":[
        "pet",
        "shop",
        "grooming",
        "washing"
    ],
    "wof:name":"Super Pet",
    "wof:placetype":"venue"
},
  "geometry": {"coordinates":[-79.827774,43.326241],"type":"Point"}
}