{
  "type": "Feature",
  "properties": {
    "addr:full":"45 Queensway St Essex ON N8M 3C3",
    "addr:housenumber":"45",
    "addr:postcode":"n8m 3c3",
    "addr:street":"Queensway St",
    "iso:country":"CA",
    "sg:address":"45 Queensway St",
    "sg:city":"Essex",
    "sg:classifiers":[
        {
            "category":"Wholesale",
            "subcategory":"Groceries",
            "type":"Manufacturing & Wholesale Goods"
        }
    ],
    "sg:phone":"+1 519 776 8032",
    "sg:postcode":"N8M 3C3",
    "sg:province":"ON",
    "sg:tags":[
        "food",
        "broker"
    ],
    "wof:name":"Confed Brokers Intl",
    "wof:placetype":"venue"
},
  "geometry": {"coordinates":[-82.819672,42.172825],"type":"Point"}
}