{
  "type": "Feature",
  "properties": {
    "addr:full":"35 Arena St St Isidore ON K0C 2B0",
    "addr:housenumber":"35",
    "addr:postcode":"k0c 2b0",
    "addr:street":"Arena St St",
    "iso:country":"CA",
    "sg:address":"35 Arena St",
    "sg:city":"St Isidore",
    "sg:classifiers":[
        {
            "category":"Government",
            "subcategory":"Office",
            "type":"Public Place"
        }
    ],
    "sg:phone":"+1 613 524 3157",
    "sg:postcode":"K0C 2B0",
    "sg:province":"ON",
    "sg:tags":[
        "apartment",
        "village"
    ],
    "wof:name":"L'Escale",
    "wof:placetype":"venue"
},
  "geometry": {"coordinates":[-74.90582999999999,45.385731],"type":"Point"}
}