{
  "type": "Feature",
  "properties": {
    "iso:country":"CA",
    "sg:city":"Quebec",
    "sg:classifiers":[
        {
            "category":"Food & Beverages",
            "subcategory":"Specialty",
            "type":"Retail Goods"
        }
    ],
    "sg:phone":"+1 418 623 8322",
    "sg:postcode":"G2J 1C2",
    "sg:province":"QC",
    "wof:name":"Phyto-Med",
    "wof:placetype":"venue"
},
  "geometry": {"coordinates":[-71.273109,46.834042],"type":"Point"}
}