{
  "type": "Feature",
  "properties": {
    "addr:full":"5327 Brendan Lane Oldcastle ON N0R 1L0",
    "addr:housenumber":"5327",
    "addr:postcode":"n0r 1l0",
    "addr:street":"Brendan Lane",
    "iso:country":"CA",
    "sg:address":"5327 Brendan Lane",
    "sg:city":"Oldcastle",
    "sg:classifiers":[
        {
            "category":"Manufacturing",
            "subcategory":"Tools & Machinery",
            "type":"Manufacturing & Wholesale Goods"
        }
    ],
    "sg:phone":"+1 519 737 1535",
    "sg:postcode":"N0R 1L0",
    "sg:province":"ON",
    "sg:tags":[
        "mold"
    ],
    "wof:name":"Majestic Tool & Mold",
    "wof:placetype":"venue"
},
  "geometry": {"coordinates":[-82.96123504640001,42.2354278564],"type":"Point"}
}