{
  "type": "Feature",
  "properties": {
    "addr:full":"5915 104 St NW Edmonton AB T6H 2K5",
    "addr:housenumber":"5915",
    "addr:postcode":"t6h 2k5",
    "addr:street":"104 St Nw",
    "iso:country":"CA",
    "sg:address":"5915 104 St NW",
    "sg:city":"Edmonton",
    "sg:classifiers":[
        {
            "category":"Retail",
            "subcategory":"Repair Shop",
            "type":"Services"
        }
    ],
    "sg:phone":"+1 780 436 4091",
    "sg:postcode":"T6H 2K5",
    "sg:province":"AB",
    "sg:tags":[
        "antique",
        "parts"
    ],
    "wof:name":"Old Woodworks",
    "wof:placetype":"venue"
},
  "geometry": {"coordinates":[-113.497451782,53.4962844849],"type":"Point"}
}