{
  "type": "Feature",
  "properties": {
    "addr:full":"273 King St E Kingston ON K7L 3B1",
    "addr:housenumber":"273",
    "addr:postcode":"k7l 3b1",
    "addr:street":"King St E",
    "iso:country":"CA",
    "sg:address":"273 King St E",
    "sg:city":"Kingston",
    "sg:classifiers":[
        {
            "category":"Professional",
            "subcategory":"Lawyer & Legal Services",
            "type":"Services"
        }
    ],
    "sg:phone":"+1 613 549 1225",
    "sg:postcode":"K7L 3B1",
    "sg:province":"ON",
    "sg:tags":[
        "attorney"
    ],
    "wof:name":"O'Neill, Wendy A",
    "wof:placetype":"venue"
},
  "geometry": {"coordinates":[-76.482185,44.229023],"type":"Point"}
}