{
  "type": "Feature",
  "properties": {
    "addr:full":"39 King St Saint John NB E2L 4W3",
    "addr:housenumber":"39",
    "addr:postcode":"nb e2l 4w3",
    "addr:street":"King St",
    "iso:country":"CA",
    "sg:address":"39 King St",
    "sg:city":"Saint John",
    "sg:classifiers":[
        {
            "category":"Professional",
            "subcategory":"Business Services",
            "type":"Services"
        }
    ],
    "sg:phone":"+1 506 693 8004",
    "sg:postcode":"E2L 4W3",
    "sg:province":"NB",
    "sg:tags":[
        "shop",
        "gift",
        "consultant",
        "design",
        "interior",
        "decorator"
    ],
    "wof:name":"English Butler",
    "wof:placetype":"venue"
},
  "geometry": {"coordinates":[-66.060875,45.273251],"type":"Point"}
}