{
  "type": "Feature",
  "properties": {
    "addr:full":"Vancouver BC V6R 2G5",
    "addr:postcode":"v6r 2g5",
    "iso:country":"CA",
    "sg:city":"Vancouver",
    "sg:classifiers":[
        {
            "category":"Personal",
            "subcategory":"Beauty Salon",
            "type":"Services"
        }
    ],
    "sg:phone":"+1 604 222 1082",
    "sg:postcode":"V6R 2G5",
    "sg:province":"BC",
    "wof:name":"Montan's Hair Studio",
    "wof:placetype":"venue"
},
  "geometry": {"coordinates":[-123.186843872,49.2636413574],"type":"Point"}
}