{
  "type": "Feature",
  "properties": {
    "addr:full":"12 Milvan Dr North York ON M9L 1Z2",
    "addr:housenumber":"12",
    "addr:postcode":"m9l 1z2",
    "addr:street":"Milvan Dr",
    "iso:country":"CA",
    "sg:address":"12 Milvan Dr",
    "sg:city":"North York",
    "sg:classifiers":[
        {
            "category":"Building & Trades",
            "subcategory":"Construction",
            "type":"Services"
        }
    ],
    "sg:phone":"+1 416 748 6666",
    "sg:postcode":"M9L 1Z2",
    "sg:province":"ON",
    "sg:tags":[
        "paving",
        "contractor"
    ],
    "wof:name":"Best Nationwide Paving",
    "wof:placetype":"venue"
},
  "geometry": {"coordinates":[-79.55289459230001,43.7508735657],"type":"Point"}
}