{
  "type": "Feature",
  "properties": {
    "addr:full":"103 Ernest Ave North York ON M2J 3T7",
    "addr:housenumber":"103",
    "addr:postcode":"m2j 3t7",
    "addr:street":"Ernest Ave",
    "iso:country":"CA",
    "sg:address":"103 Ernest Ave",
    "sg:city":"North York",
    "sg:classifiers":[
        {
            "category":"Real Estate",
            "subcategory":"Surveying",
            "type":"Services"
        }
    ],
    "sg:phone":"+1 416 491 7101",
    "sg:postcode":"M2J 3T7",
    "sg:province":"ON",
    "sg:tags":[
        "surveyor"
    ],
    "wof:name":"Clarke Morton Wilkinson Ltd",
    "wof:placetype":"venue"
},
  "geometry": {"coordinates":[-79.3347854614,43.7907180786],"type":"Point"}
}