{
  "type": "Feature",
  "properties": {
    "iso:country":"CA",
    "sg:address":"80 Dufferin Ave",
    "sg:city":"London",
    "sg:classifiers":[
        {
            "category":"Professional",
            "subcategory":"Lawyer & Legal Services",
            "type":"Services"
        }
    ],
    "sg:phone":"+1 519 672 4131",
    "sg:postcode":"N6A 1K4",
    "sg:province":"ON",
    "sg:tags":[
        "attorney"
    ],
    "wof:name":"Bent, Maia L QC",
    "wof:placetype":"venue"
},
  "geometry": {"coordinates":[-81.253944397,42.9860038757],"type":"Point"}
}