{
  "type": "Feature",
  "properties": {
    "addr:full":"Thunder Bay ON P7E 6E7",
    "addr:postcode":"p7e 6e7",
    "iso:country":"CA",
    "sg:city":"Thunder Bay",
    "sg:classifiers":[
        {
            "category":"Insurance",
            "subcategory":"Insurance Agent",
            "type":"Services"
        }
    ],
    "sg:phone":"+1 807 624 5670",
    "sg:postcode":"P7E 6E7",
    "sg:province":"ON",
    "wof:name":"Wawanesa Mutual Insurance CO",
    "wof:placetype":"venue"
},
  "geometry": {"coordinates":[-89.25476074220001,48.381061554],"type":"Point"}
}