{
  "type": "Feature",
  "properties": {
    "addr:full":"100 Blair Ave Tatamagouche NS B0K 1V0",
    "addr:housenumber":"100",
    "addr:postcode":"b0k 1v0",
    "addr:street":"Blair Ave",
    "iso:country":"CA",
    "sg:address":"100 Blair Ave",
    "sg:city":"Tatamagouche",
    "sg:classifiers":[
        {
            "category":"Health Services",
            "subcategory":"Nursing And Care Facility",
            "type":"Services"
        }
    ],
    "sg:phone":"+1 902 657 3101",
    "sg:postcode":"B0K 1V0",
    "sg:province":"NS",
    "sg:tags":[
        "home",
        "convalescent"
    ],
    "wof:name":"Willow Lodge Home-Spec Care",
    "wof:placetype":"venue"
},
  "geometry": {"coordinates":[-63.297009,45.712292],"type":"Point"}
}