{
  "type": "Feature",
  "properties": {
    "iso:country":"CA",
    "sg:city":"Shediac",
    "sg:classifiers":[
        {
            "category":"Health Services",
            "subcategory":"Chiropractor",
            "type":"Services"
        }
    ],
    "sg:phone":"+1 506 532 1114",
    "sg:postcode":"E4P 2E7",
    "sg:province":"NB",
    "wof:name":"Clinique Chiropratique Shediac",
    "wof:placetype":"venue"
},
  "geometry": {"coordinates":[-64.54373168950001,46.2195549011],"type":"Point"}
}