{
  "type": "Feature",
  "properties": {
    "addr:full":"4995 Monck Rd Kinmount ON K0M 2A0",
    "addr:housenumber":"4995",
    "addr:postcode":"k0m 2a0",
    "addr:street":"Monck Rd",
    "iso:country":"CA",
    "sg:address":"4995 Monck Rd",
    "sg:city":"Kinmount",
    "sg:classifiers":[
        {
            "category":"Shopping",
            "subcategory":"Gifts & Souvenirs",
            "type":"Retail Goods"
        }
    ],
    "sg:phone":"+1 705 488 1414",
    "sg:postcode":"K0M 2A0",
    "sg:province":"ON",
    "sg:tags":[
        "shop"
    ],
    "wof:name":"Kinmount Artisan's Market Pl",
    "wof:placetype":"venue"
},
  "geometry": {"coordinates":[-78.65316799999999,44.783222],"type":"Point"}
}