{
  "type": "Feature",
  "properties": {
    "iso:country":"CA",
    "sg:address":"5550 Rang Ste-Marguerite",
    "sg:city":"Saint-Narcisse",
    "sg:classifiers":[
        {
            "category":"Wholesale",
            "subcategory":"Machinery & Supplies",
            "type":"Manufacturing & Wholesale Goods"
        }
    ],
    "sg:phone":"+1 418 328 3547",
    "sg:postcode":"G0X 2Y0",
    "sg:province":"QC",
    "sg:tags":[
        "farm",
        "equipment"
    ],
    "wof:name":"Agro Service Imhof Inc",
    "wof:placetype":"venue"
},
  "geometry": {"coordinates":[-72.49295043950001,46.5283432007],"type":"Point"}
}