{
  "type": "Feature",
  "properties": {
    "addr:full":"Scarborough ON M1P 3B4",
    "addr:postcode":"m1p 3b4",
    "iso:country":"CA",
    "sg:city":"Scarborough",
    "sg:classifiers":[
        {
            "category":"Retail",
            "subcategory":"Auto Repair",
            "type":"Services"
        }
    ],
    "sg:phone":"+1 416 759 5810",
    "sg:postcode":"M1P 3B4",
    "sg:province":"ON",
    "sg:tags":[
        "body",
        "automobile",
        "painting"
    ],
    "wof:name":"M & D Auto Body Repair",
    "wof:placetype":"venue"
},
  "geometry": {"coordinates":[-79.27063800000001,43.758755],"type":"Point"}
}