{
  "type": "Feature",
  "properties": {
    "addr:full":"6199 Cypress St Vancouver BC V6M 3S3",
    "addr:housenumber":"6199",
    "addr:postcode":"v6m 3s3",
    "addr:street":"Cypress St",
    "iso:country":"CA",
    "sg:address":"6199 Cypress St",
    "sg:city":"Vancouver",
    "sg:classifiers":[
        {
            "category":"Education",
            "subcategory":"School",
            "type":"Public Place"
        }
    ],
    "sg:phone":"+1 604 713 5356",
    "sg:postcode":"V6M 3S3",
    "sg:province":"BC",
    "wof:name":"Maple Grove Elementary",
    "wof:placetype":"venue"
},
  "geometry": {"coordinates":[-123.14949799999999,49.229832],"type":"Point"}
}