{
  "type": "Feature",
  "properties": {
    "addr:full":"87 Bentley Ave Nepean ON K2E 6T7",
    "addr:housenumber":"87",
    "addr:postcode":"k2e 6t7",
    "addr:street":"Bentley Ave",
    "iso:country":"CA",
    "sg:address":"87 Bentley Ave",
    "sg:city":"Nepean",
    "sg:classifiers":[
        {
            "category":"Wholesale",
            "subcategory":"Machinery & Supplies",
            "type":"Manufacturing & Wholesale Goods"
        }
    ],
    "sg:phone":"+1 613 224 5555",
    "sg:postcode":"K2E 6T7",
    "sg:province":"ON",
    "sg:tags":[
        "equipment",
        "pneumatic",
        "hydraulic"
    ],
    "wof:name":"Schooner Industrial Ltd",
    "wof:placetype":"venue"
},
  "geometry": {"coordinates":[-75.71466100000001,45.335087],"type":"Point"}
}