{
  "type": "Feature",
  "properties": {
    "addr:full":"Coquitlam BC V3K 3V9",
    "addr:postcode":"v3k 3v9",
    "iso:country":"CA",
    "sg:city":"Coquitlam",
    "sg:classifiers":[
        {
            "category":"Banks & Credit Unions",
            "subcategory":"Bank",
            "type":"Services"
        }
    ],
    "sg:phone":"+1 604 936 5058",
    "sg:postcode":"V3K 3V9",
    "sg:province":"BC",
    "wof:name":"Sharons Credit Union",
    "wof:placetype":"venue"
},
  "geometry": {"coordinates":[-122.89249420199999,49.2460861206],"type":"Point"}
}