{
  "type": "Feature",
  "properties": {
    "iso:country":"CA",
    "sg:address":"1232 Howe St",
    "sg:city":"Vancouver",
    "sg:classifiers":[
        {
            "category":"Restaurant",
            "type":"Food & Drink"
        }
    ],
    "sg:phone":"+1 604 682 6666",
    "sg:postcode":"V6Z 1R5",
    "sg:province":"BC",
    "sg:tags":[
        "pizza"
    ],
    "wof:name":"Pizza Guys",
    "wof:placetype":"venue"
},
  "geometry": {"coordinates":[-123.127586,49.27729],"type":"Point"}
}