{
  "type": "Feature",
  "properties": {
    "addr:full":"Stewart BC V0T 1W0",
    "addr:postcode":"v0t 1w0",
    "iso:country":"CA",
    "sg:city":"Stewart",
    "sg:classifiers":[
        {
            "category":"Education",
            "subcategory":"College",
            "type":"Public Place"
        }
    ],
    "sg:phone":"+1 250 636 9184",
    "sg:postcode":"V0T 1W0",
    "sg:province":"BC",
    "sg:tags":[
        "academic",
        "school"
    ],
    "wof:name":"Northwest Community College",
    "wof:placetype":"venue"
},
  "geometry": {"coordinates":[-130.316315,54.315582],"type":"Point"}
}