{
  "type": "Feature",
  "properties": {
    "iso:country":"CA",
    "sg:city":"Scarborough",
    "sg:classifiers":[
        {
            "category":"Manufacturing",
            "subcategory":"Rubber & Plastics",
            "type":"Manufacturing & Wholesale Goods"
        }
    ],
    "sg:phone":"+1 416 292 4039",
    "sg:postcode":"M1B 5R2",
    "sg:province":"ON",
    "sg:tags":[
        "producer"
    ],
    "wof:name":"L & K Industries",
    "wof:placetype":"venue"
},
  "geometry": {"coordinates":[-79.233253479,43.8152313232],"type":"Point"}
}