{
  "type": "Feature",
  "properties": {
    "addr:full":"Saint-Laurent QC H4T 1N3",
    "addr:postcode":"h4t 1n3",
    "iso:country":"CA",
    "sg:city":"Saint-Laurent",
    "sg:classifiers":[
        {
            "category":"Manufacturing",
            "subcategory":"Tools & Machinery",
            "type":"Manufacturing & Wholesale Goods"
        }
    ],
    "sg:phone":"+1 514 733 1992",
    "sg:postcode":"H4T 1N3",
    "sg:province":"QC",
    "sg:tags":[
        "equipment",
        "welding",
        "supply"
    ],
    "wof:name":"Sodel Limitee",
    "wof:placetype":"venue"
},
  "geometry": {"coordinates":[-73.7114105225,45.4871025085],"type":"Point"}
}