{
  "type": "Feature",
  "properties": {
    "addr:full":"265 Boul DE Quen N Alma QC G8B 5N8",
    "addr:housenumber":"265",
    "addr:postcode":"g8b 5n8",
    "addr:street":"Boul De Quen N",
    "iso:country":"CA",
    "sg:address":"265 Boul DE Quen N",
    "sg:city":"Alma",
    "sg:classifiers":[
        {
            "category":"Social Services",
            "type":"Services"
        }
    ],
    "sg:phone":"+1 418 480 4999",
    "sg:postcode":"G8B 5N8",
    "sg:province":"QC",
    "sg:tags":[
        "organization",
        "welfare"
    ],
    "wof:name":"Moisson D'Alma",
    "wof:placetype":"venue"
},
  "geometry": {"coordinates":[-71.64819300000001,48.556404],"type":"Point"}
}