{
  "type": "Feature",
  "properties": {
    "addr:full":"2021 Av Union # 1200 Montreal QC H3A 2S9",
    "addr:housenumber":"2021",
    "addr:postcode":"h3a 2s9",
    "addr:street":"Av Union # 1200",
    "iso:country":"CA",
    "sg:address":"2021 Av Union # 1200",
    "sg:city":"Montreal",
    "sg:classifiers":[
        {
            "category":"Professional",
            "subcategory":"Management & Consulting",
            "type":"Services"
        }
    ],
    "sg:phone":"+1 514 848 9899",
    "sg:postcode":"H3A 2S9",
    "sg:province":"QC",
    "sg:tags":[
        "consultant",
        "resource",
        "business",
        "human"
    ],
    "wof:name":"Groupe Ast Inc",
    "wof:placetype":"venue"
},
  "geometry": {"coordinates":[-73.571304,45.50494],"type":"Point"}
}