{
  "type": "Feature",
  "properties": {
    "addr:full":"129 Shannon Rd Sault Ste Marie ON P6A 4J8",
    "addr:housenumber":"129",
    "addr:postcode":"p6a 4j8",
    "addr:street":"Shannon Rd",
    "iso:country":"CA",
    "sg:address":"129 Shannon Rd",
    "sg:city":"Sault Ste Marie",
    "sg:classifiers":[
        {
            "category":"Health Services",
            "subcategory":"Health Practitioner",
            "type":"Services"
        }
    ],
    "sg:phone":"+1 705 253 8735",
    "sg:postcode":"P6A 4J8",
    "sg:province":"ON",
    "sg:tags":[
        "psychologist"
    ],
    "wof:name":"Fick, Carol",
    "wof:placetype":"venue"
},
  "geometry": {"coordinates":[-84.283554,46.499241],"type":"Point"}
}