{
  "type": "Feature",
  "properties": {
    "addr:full":"480 Avalon Pl Ottawa ON K1G 0W4",
    "addr:housenumber":"480",
    "addr:postcode":"k1g 0w4",
    "addr:street":"Avalon Pl",
    "iso:country":"CA",
    "sg:address":"480 Avalon Pl",
    "sg:city":"Ottawa",
    "sg:classifiers":[
        {
            "category":"Organizations",
            "subcategory":"Religious Organization",
            "type":"Services"
        }
    ],
    "sg:phone":"+1 613 731 8926",
    "sg:postcode":"K1G 0W4",
    "sg:province":"ON",
    "sg:tags":[
        "church"
    ],
    "wof:name":"Trinity Church of Nazarene",
    "wof:placetype":"venue"
},
  "geometry": {"coordinates":[-75.64939099999999,45.406124],"type":"Point"}
}