{
  "type": "Feature",
  "properties": {
    "iso:country":"CA",
    "sg:address":"5020 Rue Fairway # 226",
    "sg:city":"Lachine",
    "sg:classifiers":[
        {
            "category":"Professional",
            "subcategory":"Management & Consulting",
            "type":"Services"
        }
    ],
    "sg:phone":"+1 514 631 8242",
    "sg:postcode":"H8T 1B8",
    "sg:province":"QC",
    "sg:tags":[
        "employee",
        "consultant",
        "benefit"
    ],
    "wof:name":"Agence En Avantages Sociaux",
    "wof:placetype":"venue"
},
  "geometry": {"coordinates":[-73.716263,45.452988],"type":"Point"}
}