{
  "type": "Feature",
  "properties": {
    "iso:country":"CA",
    "sg:address":"1890 Barton St E",
    "sg:city":"Hamilton",
    "sg:classifiers":[
        {
            "category":"Autos & Motor Vehicles",
            "subcategory":"Auto Supplies",
            "type":"Retail Goods"
        }
    ],
    "sg:phone":"+1 905 547 6751",
    "sg:postcode":"L8H 2Y6",
    "sg:province":"ON",
    "sg:tags":[
        "tire"
    ],
    "wof:name":"Frank's Tire Svc of Hamilton",
    "wof:placetype":"venue"
},
  "geometry": {"coordinates":[-79.784065,43.243793],"type":"Point"}
}