{
  "type": "Feature",
  "properties": {
    "addr:full":"153 Boul DE Gaspe Gaspe QC G4X 1A4",
    "addr:housenumber":"153",
    "addr:postcode":"g4x 1a4",
    "addr:street":"Boul De Gaspe",
    "iso:country":"CA",
    "sg:address":"153 Boul DE Gaspe",
    "sg:city":"Gaspe",
    "sg:classifiers":[
        {
            "category":"Insurance",
            "subcategory":"Insurance Agent",
            "type":"Services"
        }
    ],
    "sg:phone":"+1 418 368 2696",
    "sg:postcode":"G4X 1A4",
    "sg:province":"QC",
    "wof:name":"Assurexperts Clovis Morris Inc",
    "wof:placetype":"venue"
},
  "geometry": {"coordinates":[-64.48361206049999,48.8397254944],"type":"Point"}
}