{
  "type": "Feature",
  "properties": {
    "iso:country":"CA",
    "sg:address":"301 Rideau St",
    "sg:city":"Kemptville",
    "sg:classifiers":[
        {
            "category":"Food & Beverages",
            "subcategory":"Groceries & Convenience Stores",
            "type":"Retail Goods"
        }
    ],
    "sg:phone":"+1 613 258 3014",
    "sg:postcode":"K0G 1J0",
    "sg:province":"ON",
    "sg:tags":[
        "grocer"
    ],
    "wof:name":"B & H Foodliner Iga",
    "wof:placetype":"venue"
},
  "geometry": {"coordinates":[-75.649323,45.017986],"type":"Point"}
}