{
  "type": "Feature",
  "properties": {
    "addr:full":"86 Old Haliburton Rd Pictou NS B0K 1H0",
    "addr:housenumber":"86",
    "addr:postcode":"b0k 1h0",
    "addr:street":"Old Haliburton Rd",
    "iso:country":"CA",
    "sg:address":"86 Old Haliburton Rd",
    "sg:city":"Pictou",
    "sg:classifiers":[
        {
            "category":"Organizations",
            "subcategory":"Non-profit Organization",
            "type":"Services"
        }
    ],
    "sg:phone":"+1 902 485 4563",
    "sg:postcode":"B0K 1H0",
    "sg:province":"NS",
    "sg:tags":[
        "charitable",
        "institution"
    ],
    "wof:name":"Pictour County Geneaology",
    "wof:placetype":"venue"
},
  "geometry": {"coordinates":[-62.728714,45.675426],"type":"Point"}
}