{
  "type": "Feature",
  "properties": {
    "addr:full":"443 St Clair St Chatham ON N7L 3K6",
    "addr:housenumber":"443",
    "addr:postcode":"n7l 3k6",
    "addr:street":"St Clair St",
    "iso:country":"CA",
    "sg:address":"443 St Clair St",
    "sg:city":"Chatham",
    "sg:classifiers":[
        {
            "category":"Restaurant",
            "type":"Food & Drink"
        }
    ],
    "sg:phone":"+1 519 351 2121",
    "sg:postcode":"N7L 3K6",
    "sg:province":"ON",
    "wof:name":"Lil Juli Fish & Chips",
    "wof:placetype":"venue"
},
  "geometry": {"coordinates":[-82.20224,42.417061],"type":"Point"}
}