{
  "type": "Feature",
  "properties": {
    "addr:full":"108 Chestnut St Toronto ON M5G 1R3",
    "addr:housenumber":"108",
    "addr:postcode":"m5g 1r3",
    "addr:street":"Chestnut St",
    "iso:country":"CA",
    "sg:address":"108 Chestnut St",
    "sg:city":"Toronto",
    "sg:classifiers":[
        {
            "category":"Travel",
            "subcategory":"Hotels & Motels",
            "type":"Entertainment"
        }
    ],
    "sg:phone":"+1 416 977 5000",
    "sg:postcode":"M5G 1R3",
    "sg:province":"ON",
    "wof:name":"Metropolitan Hotel",
    "wof:placetype":"venue"
},
  "geometry": {"coordinates":[-79.38604736329999,43.6548805237],"type":"Point"}
}