{
  "type": "Feature",
  "properties": {
    "addr:full":"90 Rue Saint-Paul Victoriaville QC G6P 9C8",
    "addr:housenumber":"90",
    "addr:postcode":"g6p 9c8",
    "addr:street":"Rue Saint-Paul",
    "iso:country":"CA",
    "sg:address":"90 Rue Saint-Paul",
    "sg:city":"Victoriaville",
    "sg:classifiers":[
        {
            "category":"Organizations",
            "subcategory":"Religious Organization",
            "type":"Services"
        }
    ],
    "sg:phone":"+1 819 758 1911",
    "sg:postcode":"G6P 9C8",
    "sg:province":"QC",
    "wof:name":"Communaute Du Desert",
    "wof:placetype":"venue"
},
  "geometry": {"coordinates":[-71.9640884399,46.0620994568],"type":"Point"}
}