{
  "type": "Feature",
  "properties": {
    "iso:country":"CA",
    "sg:address":"5514 Richards Rd",
    "sg:city":"Celista",
    "sg:classifiers":[
        {
            "category":"Manufacturing",
            "subcategory":"Lumber",
            "type":"Manufacturing & Wholesale Goods"
        }
    ],
    "sg:phone":"+1 250 955 2924",
    "sg:postcode":"V0E 1L0",
    "sg:province":"BC",
    "sg:tags":[
        "company",
        "logging"
    ],
    "wof:name":"Bvr Contractors Ltd",
    "wof:placetype":"venue"
},
  "geometry": {"coordinates":[-119.22883606000001,50.9617538452],"type":"Point"}
}