{
  "type": "Feature",
  "properties": {
    "iso:country":"CA",
    "sg:city":"Nanaimo",
    "sg:classifiers":[
        {
            "category":"Home & Garden",
            "subcategory":"Furniture",
            "type":"Retail Goods"
        }
    ],
    "sg:phone":"+1 250 758 5132",
    "sg:postcode":"V9T 6A6",
    "sg:province":"BC",
    "sg:tags":[
        "top",
        "counter"
    ],
    "wof:name":"Colonial Countertops Ltd",
    "wof:placetype":"venue"
},
  "geometry": {"coordinates":[-124.03511047400001,49.2065544128],"type":"Point"}
}