{
  "type": "Feature",
  "properties": {
    "addr:full":"492 Bronson Ave #A Ottawa ON K1R 6J9",
    "addr:housenumber":"492",
    "addr:postcode":"k1r 6j9",
    "addr:street":"Bronson Ave # A",
    "iso:country":"CA",
    "sg:address":"492 Bronson Ave #A",
    "sg:city":"Ottawa",
    "sg:classifiers":[
        {
            "category":"Real Estate",
            "subcategory":"Real Estate Agent",
            "type":"Services"
        }
    ],
    "sg:phone":"+1 613 724 0310",
    "sg:postcode":"K1R 6J9",
    "sg:province":"ON",
    "wof:name":"Mtn Realty Ltd",
    "wof:placetype":"venue"
},
  "geometry": {"coordinates":[-75.703423,45.407185],"type":"Point"}
}