{
  "type": "Feature",
  "properties": {
    "addr:full":"Grande Prairie AB T8V 7X9",
    "addr:postcode":"t8v 7x9",
    "iso:country":"CA",
    "sg:city":"Grande Prairie",
    "sg:classifiers":[
        {
            "category":"Organizations",
            "subcategory":"Professional Association",
            "type":"Services"
        }
    ],
    "sg:phone":"+1 780 532 5340",
    "sg:postcode":"T8V 7X9",
    "sg:province":"AB",
    "sg:tags":[
        "chambers",
        "commerce"
    ],
    "wof:name":"Grande Prairie Chamber-Cmmrc",
    "wof:placetype":"venue"
},
  "geometry": {"coordinates":[-118.815201,55.187462],"type":"Point"}
}