{
  "type": "Feature",
  "properties": {
    "addr:full":"906 Rue Principale Ile-Aux-Noix QC J0J 1G0",
    "addr:housenumber":"906",
    "addr:postcode":"j0j 1g0",
    "addr:street":"Rue Principale",
    "iso:country":"CA",
    "sg:address":"906 Rue Principale",
    "sg:city":"Ile-Aux-Noix",
    "sg:classifiers":[
        {
            "category":"Restaurant",
            "type":"Food & Drink"
        }
    ],
    "sg:phone":"+1 450 291 5708",
    "sg:postcode":"J0J 1G0",
    "sg:province":"QC",
    "wof:name":"Casse Croute Chez Dede",
    "wof:placetype":"venue"
},
  "geometry": {"coordinates":[-73.282143,45.125744],"type":"Point"}
}