{
  "type": "Feature",
  "properties": {
    "addr:full":"915 Rue Notre-Dame Lanoraie QC J0K 1E0",
    "addr:housenumber":"915",
    "addr:postcode":"j0k 1e0",
    "addr:street":"Rue Notre-Dame",
    "iso:country":"CA",
    "sg:address":"915 Rue Notre-Dame",
    "sg:city":"Lanoraie",
    "sg:classifiers":[
        {
            "category":"Freight",
            "type":"Transportation"
        }
    ],
    "sg:phone":"+1 450 887 2327",
    "sg:postcode":"J0K 1E0",
    "sg:province":"QC",
    "sg:tags":[
        "trucking"
    ],
    "wof:name":"Transport R Mondor Inc",
    "wof:placetype":"venue"
},
  "geometry": {"coordinates":[-73.212761,45.963829],"type":"Point"}
}