{
  "type": "Feature",
  "properties": {
    "iso:country":"CA",
    "sg:address":"1760 Regent St",
    "sg:city":"Sudbury",
    "sg:classifiers":[
        {
            "category":"Professional",
            "subcategory":"Management & Consulting",
            "type":"Services"
        }
    ],
    "sg:phone":"+1 705 522 0158",
    "sg:postcode":"P3E 3Z8",
    "sg:province":"ON",
    "sg:tags":[
        "marketing",
        "consultant"
    ],
    "wof:name":"More Comm Consultants",
    "wof:placetype":"venue"
},
  "geometry": {"coordinates":[-81.0056,46.45454],"type":"Point"}
}