{
  "type": "Feature",
  "properties": {
    "addr:full":"1525 Alaska Ave Dawson Creek BC V1G 1Z8",
    "addr:housenumber":"1525",
    "addr:postcode":"v1g 1z8",
    "addr:street":"Alaska Ave",
    "iso:country":"CA",
    "sg:address":"1525 Alaska Ave",
    "sg:city":"Dawson Creek",
    "sg:classifiers":[
        {
            "category":"Restaurant",
            "type":"Food & Drink"
        }
    ],
    "sg:phone":"+1 250 782 8585",
    "sg:postcode":"V1G 1Z8",
    "sg:province":"BC",
    "wof:name":"Boston Pizza",
    "wof:placetype":"venue"
},
  "geometry": {"coordinates":[-120.245041,55.763737],"type":"Point"}
}