{
  "type": "Feature",
  "properties": {
    "addr:full":"387 Rue Bernard O Montreal QC H2V 1T6",
    "addr:housenumber":"387",
    "addr:postcode":"h2v 1t6",
    "addr:street":"Rue Bernard O",
    "iso:country":"CA",
    "sg:address":"387 Rue Bernard O",
    "sg:city":"Montreal",
    "sg:classifiers":[
        {
            "category":"Restaurant",
            "type":"Food & Drink"
        }
    ],
    "sg:phone":"+1 514 490 1225",
    "sg:postcode":"H2V 1T6",
    "sg:province":"QC",
    "wof:name":"Sushi Maiko",
    "wof:placetype":"venue"
},
  "geometry": {"coordinates":[-73.606163,45.523205],"type":"Point"}
}