{
  "type": "Feature",
  "properties": {
    "addr:full":"813 Victoria St Prince George BC V2L 2K7",
    "addr:housenumber":"813",
    "addr:postcode":"v2l 2k7",
    "addr:street":"Victoria St",
    "iso:country":"CA",
    "sg:address":"813 Victoria St",
    "sg:city":"Prince George",
    "sg:classifiers":[
        {
            "category":"Real Estate",
            "subcategory":"Developer",
            "type":"Services"
        }
    ],
    "sg:phone":"+1 250 563 0611",
    "sg:postcode":"V2L 2K7",
    "sg:province":"BC",
    "sg:tags":[
        "company",
        "land"
    ],
    "wof:name":"Matte Brothers & Sons Constr",
    "wof:placetype":"venue"
},
  "geometry": {"coordinates":[-122.752647,53.913937],"type":"Point"}
}