{
  "type": "Feature",
  "properties": {
    "addr:full":"1361 Ch Saint-Henri Mascouche QC J7K 2N5",
    "addr:housenumber":"1361",
    "addr:postcode":"j7k 2n5",
    "addr:street":"Ch Saint-Henri",
    "iso:country":"CA",
    "sg:address":"1361 Ch Saint-Henri",
    "sg:city":"Mascouche",
    "sg:classifiers":[
        {
            "category":"Personal",
            "subcategory":"Beauty Salon",
            "type":"Services"
        }
    ],
    "sg:phone":"+1 450 474 2171",
    "sg:postcode":"J7K 2N5",
    "sg:province":"QC",
    "wof:name":"Salon Huguette",
    "wof:placetype":"venue"
},
  "geometry": {"coordinates":[-73.596786499,45.7554321289],"type":"Point"}
}