{
  "type": "Feature",
  "properties": {
    "addr:full":"7941 Boul Industriel Chambly QC J3L 5G8",
    "addr:housenumber":"7941",
    "addr:postcode":"j3l 5g8",
    "addr:street":"Boul Industriel",
    "iso:country":"CA",
    "sg:address":"7941 Boul Industriel",
    "sg:city":"Chambly",
    "sg:classifiers":[
        {
            "category":"Autos & Motor Vehicles",
            "subcategory":"Boat Sales",
            "type":"Retail Goods"
        }
    ],
    "sg:phone":"+1 450 658 6061",
    "sg:postcode":"J3L 5G8",
    "sg:province":"QC",
    "sg:tags":[
        "propeller"
    ],
    "wof:name":"Atelier D'Usinage Real Proulx",
    "wof:placetype":"venue"
},
  "geometry": {"coordinates":[-73.280289,45.416092],"type":"Point"}
}