{
  "type": "Feature",
  "properties": {
    "addr:full":"5 Lewer St Gloucester ON K1V 1G9",
    "addr:housenumber":"5",
    "addr:postcode":"k1v 1g9",
    "addr:street":"Lewer St",
    "iso:country":"CA",
    "sg:address":"5 Lewer St",
    "sg:city":"Gloucester",
    "sg:classifiers":[
        {
            "category":"Building & Trades",
            "subcategory":"Landscaping Services",
            "type":"Services"
        }
    ],
    "sg:phone":"+1 613 738 3331",
    "sg:postcode":"K1V 1G9",
    "sg:province":"ON",
    "sg:tags":[
        "tree"
    ],
    "wof:name":"Alfred Roger's Fireplace Wood",
    "wof:placetype":"venue"
},
  "geometry": {"coordinates":[-75.6908569336,45.3208961487],"type":"Point"}
}