{
  "type": "Feature",
  "properties": {
    "addr:full":"Zephyr ON L0E 1T0",
    "addr:postcode":"l0e 1t0",
    "iso:country":"CA",
    "sg:city":"Zephyr",
    "sg:classifiers":[
        {
            "category":"Building & Trades",
            "subcategory":"Cleaning & Sanitation",
            "type":"Services"
        }
    ],
    "sg:phone":"+1 905 473 5934",
    "sg:postcode":"L0E 1T0",
    "sg:province":"ON",
    "sg:tags":[
        "butler",
        "maid"
    ],
    "wof:name":"A Better Clean Home Cleaning",
    "wof:placetype":"venue"
},
  "geometry": {"coordinates":[-79.264786,44.200161],"type":"Point"}
}