{
  "type": "Feature",
  "properties": {
    "iso:country":"CA",
    "sg:address":"8500 Boul Henri-Bourassa",
    "sg:city":"Charlesbourg",
    "sg:classifiers":[
        {
            "category":"Shopping",
            "subcategory":"Music",
            "type":"Retail Goods"
        }
    ],
    "sg:phone":"+1 418 626 6262",
    "sg:postcode":"G1G 5X1",
    "sg:province":"QC",
    "sg:tags":[
        "compact",
        "record",
        "disc",
        "tape"
    ],
    "wof:name":"Fortification Muzzik",
    "wof:placetype":"venue"
},
  "geometry": {"coordinates":[-71.270775,46.865112],"type":"Point"}
}