{
  "type": "Feature",
  "properties": {
    "addr:full":"6376 Yonge St North York ON M2M 3X4",
    "addr:housenumber":"6376",
    "addr:postcode":"m2m 3x4",
    "addr:street":"Yonge St",
    "iso:country":"CA",
    "sg:address":"6376 Yonge St",
    "sg:city":"North York",
    "sg:classifiers":[
        {
            "category":"Personal",
            "subcategory":"Beauty Salon",
            "type":"Services"
        }
    ],
    "sg:phone":"+1 416 226 6375",
    "sg:postcode":"M2M 3X4",
    "sg:province":"ON",
    "wof:name":"Hair Care Stylists",
    "wof:placetype":"venue"
},
  "geometry": {"coordinates":[-79.4196548462,43.7957038879],"type":"Point"}
}