{
  "type": "Feature",
  "properties": {
    "addr:full":"319 Mountain St Strasbourg SK S0G 4V0",
    "addr:housenumber":"319",
    "addr:postcode":"s0g 4v0",
    "addr:street":"Mountain St",
    "iso:country":"CA",
    "sg:address":"319 Mountain St",
    "sg:city":"Strasbourg",
    "sg:classifiers":[
        {
            "category":"Organizations",
            "subcategory":"Religious Organization",
            "type":"Services"
        }
    ],
    "sg:phone":"+1 306 725 3113",
    "sg:postcode":"S0G 4V0",
    "sg:province":"SK",
    "sg:tags":[
        "church"
    ],
    "wof:name":"St John Lutheran Church",
    "wof:placetype":"venue"
},
  "geometry": {"coordinates":[-104.958099365,51.0692176819],"type":"Point"}
}