{
  "type": "Feature",
  "properties": {
    "addr:full":"25 Steeles Ave E Milton ON L9T 1X9",
    "addr:housenumber":"25",
    "addr:postcode":"l9t 1x9",
    "addr:street":"Steeles Ave E",
    "iso:country":"CA",
    "sg:address":"25 Steeles Ave E",
    "sg:city":"Milton",
    "sg:classifiers":[
        {
            "category":"Autos & Motor Vehicles",
            "subcategory":"Auto Supplies",
            "type":"Retail Goods"
        }
    ],
    "sg:phone":"+1 905 878 2859",
    "sg:postcode":"L9T 1X9",
    "sg:province":"ON",
    "sg:tags":[
        "tire"
    ],
    "wof:name":"Bargain Tire Auto Ctr",
    "wof:placetype":"venue"
},
  "geometry": {"coordinates":[-79.89874267579999,43.5175361633],"type":"Point"}
}