{
  "type": "Feature",
  "properties": {
    "addr:full":"255 Industrial Pky S # 2 Aurora ON L4G 3V5",
    "addr:housenumber":"255",
    "addr:postcode":"l4g 3v5",
    "addr:street":"Industrial Pky S # 2",
    "iso:country":"CA",
    "sg:address":"255 Industrial Pky S # 2",
    "sg:city":"Aurora",
    "sg:classifiers":[
        {
            "category":"Shopping",
            "subcategory":"Musical Instruments",
            "type":"Retail Goods"
        }
    ],
    "sg:phone":"+1 905 727 5582",
    "sg:postcode":"L4G 3V5",
    "sg:province":"ON",
    "sg:tags":[
        "piano",
        "music",
        "dealer"
    ],
    "wof:name":"Piano Studio",
    "wof:placetype":"venue"
},
  "geometry": {"coordinates":[-79.453812,43.990845],"type":"Point"}
}