{
  "type": "Feature",
  "properties": {
    "addr:full":"8825 126 Ave NW Edmonton AB T5B 1G8",
    "addr:housenumber":"8825",
    "addr:postcode":"t5b 1g8",
    "addr:street":"126 Ave Nw",
    "iso:country":"CA",
    "sg:address":"8825 126 Ave NW",
    "sg:city":"Edmonton",
    "sg:classifiers":[
        {
            "category":"Manufacturing",
            "subcategory":"Motor Vehicles & Parts",
            "type":"Manufacturing & Wholesale Goods"
        }
    ],
    "sg:phone":"+1 780 474 6411",
    "sg:postcode":"T5B 1G8",
    "sg:province":"AB",
    "sg:tags":[
        "body",
        "equipment",
        "truck"
    ],
    "wof:name":"Deluxe Van & Body Ltd",
    "wof:placetype":"venue"
},
  "geometry": {"coordinates":[-113.476646,53.582539],"type":"Point"}
}