{
  "type": "Feature",
  "properties": {
    "addr:full":"33 Kent Rd Stewiacke NS B0N 2J0",
    "addr:housenumber":"33",
    "addr:postcode":"b0n 2j0",
    "addr:street":"Kent Rd",
    "iso:country":"CA",
    "sg:address":"33 Kent Rd",
    "sg:city":"Stewiacke",
    "sg:classifiers":[
        {
            "category":"Government",
            "subcategory":"Office",
            "type":"Public Place"
        }
    ],
    "sg:phone":"+1 902 639 2125",
    "sg:postcode":"B0N 2J0",
    "sg:province":"NS",
    "sg:tags":[
        "village"
    ],
    "wof:name":"Stewiacke Public Works Garage",
    "wof:placetype":"venue"
},
  "geometry": {"coordinates":[-63.356918,45.138763],"type":"Point"}
}