{
  "type": "Feature",
  "properties": {
    "iso:country":"CA",
    "sg:address":"410 Main Rd",
    "sg:city":"Pouch Cove",
    "sg:classifiers":[
        {
            "category":"Food & Beverages",
            "subcategory":"Groceries & Convenience Stores",
            "type":"Retail Goods"
        }
    ],
    "sg:phone":"+1 709 335 2471",
    "sg:postcode":"A0A 3L0",
    "sg:province":"NL",
    "wof:name":"D & L Convenience",
    "wof:placetype":"venue"
},
  "geometry": {"coordinates":[-52.7464637756,47.7564468384],"type":"Point"}
}