{
  "type": "Feature",
  "properties": {
    "addr:full":"133 Davidson Cres Regina SK S4S 4T2",
    "addr:housenumber":"133",
    "addr:postcode":"s4s 4t2",
    "addr:street":"Davidson Cres",
    "iso:country":"CA",
    "sg:address":"133 Davidson Cres",
    "sg:city":"Regina",
    "sg:classifiers":[
        {
            "category":"Real Estate",
            "subcategory":"Real Estate Operator",
            "type":"Services"
        }
    ],
    "sg:phone":"+1 306 584 1499",
    "sg:postcode":"S4S 4T2",
    "sg:province":"SK",
    "sg:tags":[
        "apartment"
    ],
    "wof:name":"Casavilla Apartments",
    "wof:placetype":"venue"
},
  "geometry": {"coordinates":[-104.59992217999999,50.4093933105],"type":"Point"}
}