{
  "type": "Feature",
  "properties": {
    "iso:country":"CA",
    "sg:city":"York",
    "sg:classifiers":[
        {
            "category":"Retail",
            "subcategory":"Auto Repair",
            "type":"Services"
        }
    ],
    "sg:phone":"+1 416 767 4303",
    "sg:postcode":"M6N 1L3",
    "sg:province":"ON",
    "sg:tags":[
        "transmission"
    ],
    "wof:name":"Mekong Transmission Auto Svc",
    "wof:placetype":"venue"
},
  "geometry": {"coordinates":[-79.48462677000001,43.6688652039],"type":"Point"}
}