{
  "type": "Feature",
  "properties": {
    "addr:full":"27314 Fraser Hwy Aldergrove BC V4W 3P8",
    "addr:housenumber":"27314",
    "addr:postcode":"v4w 3p8",
    "addr:street":"Fraser Hwy",
    "iso:country":"CA",
    "sg:address":"27314 Fraser Hwy",
    "sg:city":"Aldergrove",
    "sg:classifiers":[
        {
            "category":"Health Services",
            "subcategory":"Medical Lab",
            "type":"Services"
        }
    ],
    "sg:phone":"+1 604 856 5155",
    "sg:postcode":"V4W 3P8",
    "sg:province":"BC",
    "wof:name":"Aldergrove Denture Clinic",
    "wof:placetype":"venue"
},
  "geometry": {"coordinates":[-122.46784210200001,49.0577659607],"type":"Point"}
}