{
  "type": "Feature",
  "properties": {
    "addr:full":"4938 Dunbar St Port Alberni BC V9Y 3G6",
    "addr:housenumber":"4938",
    "addr:postcode":"v9y 3g6",
    "addr:street":"Dunbar St",
    "iso:country":"CA",
    "sg:address":"4938 Dunbar St",
    "sg:city":"Port Alberni",
    "sg:classifiers":[
        {
            "category":"Retail",
            "subcategory":"Auto Repair",
            "type":"Services"
        }
    ],
    "sg:phone":"+1 250 724 4465",
    "sg:postcode":"V9Y 3G6",
    "sg:province":"BC",
    "sg:tags":[
        "repairing",
        "automobile",
        "tire"
    ],
    "wof:name":"Pearson-Kal Tire Ltd",
    "wof:placetype":"venue"
},
  "geometry": {"coordinates":[-124.806664,49.238361],"type":"Point"}
}