{
  "type": "Feature",
  "properties": {
    "addr:full":"29 - 20159 68th ave Langley V2Y3H9",
    "addr:housenumber":"29 20159",
    "addr:postcode":"v2y3h9",
    "addr:street":"68Th Ave",
    "iso:country":"CA",
    "sg:address":"29 - 20159 68th ave",
    "sg:city":"Langley",
    "sg:classifiers":[
        {
            "category":"Professional",
            "subcategory":"Computer Services",
            "type":"Services"
        }
    ],
    "sg:postcode":"V2Y3H9",
    "sg:tags":[
        "goal-setting",
        "goal-tracking",
        "time-management"
    ],
    "sg:website":"http://www.goalsontrack.com",
    "wof:name":"GoalsOnTrack",
    "wof:placetype":"venue"
},
  "geometry": {"coordinates":[-122.66437019999999,49.1261967],"type":"Point"}
}