{
  "type": "Feature",
  "properties": {
    "addr:full":"1290 70 St SE Salmon Arm BC V1E 1X8",
    "addr:housenumber":"1290",
    "addr:postcode":"v1e 1x8",
    "addr:street":"70 St Se",
    "iso:country":"CA",
    "sg:address":"1290 70 St SE",
    "sg:city":"Salmon Arm",
    "sg:classifiers":[
        {
            "category":"Building & Trades",
            "subcategory":"Construction",
            "type":"Services"
        }
    ],
    "sg:phone":"+1 250 832 8739",
    "sg:postcode":"V1E 1X8",
    "sg:province":"BC",
    "sg:tags":[
        "sand",
        "gravel",
        "excavating",
        "contractor"
    ],
    "wof:name":"Rizzi Enterprises",
    "wof:placetype":"venue"
},
  "geometry": {"coordinates":[-119.20439148,50.6890258789],"type":"Point"}
}