{
  "type": "Feature",
  "properties": {
    "addr:full":"4511 Boul Arthur-Sauve Laval QC H7R 5P8",
    "addr:housenumber":"4511",
    "addr:postcode":"h7r 5p8",
    "addr:street":"Boul Arthur-Sauve",
    "iso:country":"CA",
    "sg:address":"4511 Boul Arthur-Sauve",
    "sg:city":"Laval",
    "sg:classifiers":[
        {
            "category":"Shopping",
            "subcategory":"Computers & Home Electronics",
            "type":"Retail Goods"
        }
    ],
    "sg:phone":"+1 450 627 7882",
    "sg:postcode":"H7R 5P8",
    "sg:province":"QC",
    "sg:tags":[
        "equipment",
        "video"
    ],
    "wof:name":"Club International Video Film",
    "wof:placetype":"venue"
},
  "geometry": {"coordinates":[-73.869591,45.552849],"type":"Point"}
}