{
  "type": "Feature",
  "properties": {
    "addr:full":"39 Dundas St E Mississauga ON L5A 1V9",
    "addr:housenumber":"39",
    "addr:postcode":"l5a 1v9",
    "addr:street":"Dundas St E",
    "iso:country":"CA",
    "sg:address":"39 Dundas St E",
    "sg:city":"Mississauga",
    "sg:classifiers":[
        {
            "category":"Travel",
            "subcategory":"Travel Agent",
            "type":"Entertainment"
        }
    ],
    "sg:phone":"+1 905 897 2115",
    "sg:postcode":"L5A 1V9",
    "sg:province":"ON",
    "sg:tags":[
        "agency",
        "bureau"
    ],
    "wof:name":"Mississauga Travel",
    "wof:placetype":"venue"
},
  "geometry": {"coordinates":[-79.6151046753,43.5815582275],"type":"Point"}
}