{
  "type": "Feature",
  "properties": {
    "iso:country":"CA",
    "sg:city":"Winnipeg",
    "sg:classifiers":[
        {
            "category":"Restaurant",
            "type":"Food & Drink"
        }
    ],
    "sg:phone":"+1 204 255 0665",
    "sg:postcode":"R2M 4K4",
    "sg:province":"MB",
    "wof:name":"Victoria Seafood Restaurant",
    "wof:placetype":"venue"
},
  "geometry": {"coordinates":[-97.136482,49.891891],"type":"Point"}
}