{
  "type": "Feature",
  "properties": {
    "addr:full":"2435 Kingston Rd Scarborough ON M1N 1V4",
    "addr:housenumber":"2435",
    "addr:postcode":"m1n 1v4",
    "addr:street":"Kingston Rd",
    "iso:country":"CA",
    "sg:address":"2435 Kingston Rd",
    "sg:city":"Scarborough",
    "sg:classifiers":[
        {
            "category":"Building & Trades",
            "subcategory":"Construction",
            "type":"Services"
        }
    ],
    "sg:phone":"+1 416 261 4303",
    "sg:postcode":"M1N 1V4",
    "sg:province":"ON",
    "sg:tags":[
        "general",
        "contractor"
    ],
    "wof:name":"Adanac General Contracting",
    "wof:placetype":"venue"
},
  "geometry": {"coordinates":[-79.249138,43.709312],"type":"Point"}
}