{
  "type": "Feature",
  "properties": {
    "addr:full":"440 Wyld St North Bay ON P1B 1Z5",
    "addr:housenumber":"440",
    "addr:postcode":"p1b 1z5",
    "addr:street":"Wyld St",
    "iso:country":"CA",
    "sg:address":"440 Wyld St",
    "sg:city":"North Bay",
    "sg:classifiers":[
        {
            "category":"Wholesale",
            "subcategory":"Non-durable Goods",
            "type":"Manufacturing & Wholesale Goods"
        }
    ],
    "sg:phone":"+1 705 472 6940",
    "sg:postcode":"P1B 1Z5",
    "sg:province":"ON",
    "sg:tags":[
        "shop",
        "broker",
        "gift"
    ],
    "wof:name":"North West CO",
    "wof:placetype":"venue"
},
  "geometry": {"coordinates":[-79.461288,46.309757],"type":"Point"}
}