{
  "type": "Feature",
  "properties": {
    "iso:country":"CA",
    "sg:address":"17 Thetis Pl",
    "sg:city":"Nanaimo",
    "sg:classifiers":[
        {
            "category":"Personal",
            "subcategory":"Beauty Salon",
            "type":"Services"
        }
    ],
    "sg:phone":"+1 250 753 5011",
    "sg:postcode":"V9S 3A5",
    "sg:province":"BC",
    "wof:name":"Head Above Hair & Skin Care",
    "wof:placetype":"venue"
},
  "geometry": {"coordinates":[-123.96453094500001,49.1907463074],"type":"Point"}
}