{
  "type": "Feature",
  "properties": {
    "addr:full":"15 Fair St Sioux Lookout ON P8T 1A9",
    "addr:housenumber":"15",
    "addr:postcode":"p8t 1a9",
    "addr:street":"Fair St",
    "iso:country":"CA",
    "sg:address":"15 Fair St",
    "sg:city":"Sioux Lookout",
    "sg:classifiers":[
        {
            "category":"Education",
            "subcategory":"School",
            "type":"Public Place"
        }
    ],
    "sg:phone":"+1 807 737 3500",
    "sg:postcode":"P8T 1A9",
    "sg:province":"ON",
    "wof:name":"Queen Elizabeth High School",
    "wof:placetype":"venue"
},
  "geometry": {"coordinates":[-91.910973,50.10339],"type":"Point"}
}