{
  "type": "Feature",
  "properties": {
    "addr:full":"Lloydminster AB T9V 0Y7",
    "addr:postcode":"t9v 0y7",
    "iso:country":"CA",
    "sg:city":"Lloydminster",
    "sg:classifiers":[
        {
            "category":"Education",
            "subcategory":"School",
            "type":"Public Place"
        }
    ],
    "sg:phone":"+1 780 875 5090",
    "sg:postcode":"T9V 0Y7",
    "sg:province":"AB",
    "wof:name":"Queen Elizabeth School",
    "wof:placetype":"venue"
},
  "geometry": {"coordinates":[-110.01834100000001,53.284603],"type":"Point"}
}