{
  "type": "Feature",
  "properties": {
    "addr:full":"12 St Etienne Beaumont QC G0R 1C0",
    "addr:housenumber":"12",
    "addr:postcode":"g0r 1c0",
    "addr:street":"St Etienne",
    "iso:country":"CA",
    "sg:address":"12 St Etienne",
    "sg:city":"Beaumont",
    "sg:classifiers":[
        {
            "category":"Government",
            "subcategory":"Office",
            "type":"Public Place"
        }
    ],
    "sg:phone":"+1 418 835 5530",
    "sg:postcode":"G0R 1C0",
    "sg:province":"QC",
    "sg:tags":[
        "village"
    ],
    "wof:name":"Beaumont Caserne",
    "wof:placetype":"venue"
},
  "geometry": {"coordinates":[-71.012008667,46.8281364441],"type":"Point"}
}