{
  "type": "Feature",
  "properties": {
    "addr:full":"1959 Weston Rd York ON M9N 1W8",
    "addr:housenumber":"1959",
    "addr:postcode":"m9n 1w8",
    "addr:street":"Weston Rd",
    "iso:country":"CA",
    "sg:address":"1959 Weston Rd",
    "sg:city":"York",
    "sg:classifiers":[
        {
            "category":"Shopping",
            "subcategory":"Used Merchandise",
            "type":"Retail Goods"
        }
    ],
    "sg:phone":"+1 416 243 0777",
    "sg:postcode":"M9N 1W8",
    "sg:province":"ON",
    "sg:tags":[
        "second",
        "store",
        "hand"
    ],
    "wof:name":"Cash Inverters",
    "wof:placetype":"venue"
},
  "geometry": {"coordinates":[-79.5185394287,43.7009468079],"type":"Point"}
}