{
  "type": "Feature",
  "properties": {
    "addr:full":"Kamloops BC V1S 1J2",
    "addr:postcode":"bc v1s 1j2",
    "iso:country":"CA",
    "sg:city":"Kamloops",
    "sg:classifiers":[
        {
            "category":"Shopping",
            "type":"Retail Goods"
        }
    ],
    "sg:phone":"+1 250 372 5560",
    "sg:postcode":"V1S 1J2",
    "sg:province":"BC",
    "sg:tags":[
        "cosmetic",
        "perfume"
    ],
    "wof:name":"Body Shop",
    "wof:placetype":"venue"
},
  "geometry": {"coordinates":[-120.36978149399999,50.6555862427],"type":"Point"}
}