{
  "type": "Feature",
  "properties": {
    "addr:full":"Rockland ON K4K 1L6",
    "addr:postcode":"k4k 1l6",
    "addr:street":"Rockland",
    "iso:country":"CA",
    "sg:city":"Rockland",
    "sg:classifiers":[
        {
            "category":"Retail",
            "subcategory":"Repair Shop",
            "type":"Services"
        }
    ],
    "sg:phone":"+1 613 446 4988",
    "sg:postcode":"K4K 1L6",
    "sg:province":"ON",
    "sg:tags":[
        "equipment",
        "dental",
        "refinishing"
    ],
    "wof:name":"Handpiece Clinic",
    "wof:placetype":"venue"
},
  "geometry": {"coordinates":[-75.29442596440001,45.5464553833],"type":"Point"}
}