{
  "type": "Feature",
  "properties": {
    "addr:full":"3309 Bayview Ave North York ON M2K 1G4",
    "addr:housenumber":"3309",
    "addr:postcode":"m2k 1g4",
    "addr:street":"Bayview Ave",
    "iso:country":"CA",
    "sg:address":"3309 Bayview Ave",
    "sg:city":"North York",
    "sg:classifiers":[
        {
            "category":"Personal",
            "subcategory":"Beauty Salon",
            "type":"Services"
        }
    ],
    "sg:phone":"+1 416 225 2339",
    "sg:postcode":"M2K 1G4",
    "sg:province":"ON",
    "wof:name":"Haute Coiffure Beauty Studio",
    "wof:placetype":"venue"
},
  "geometry": {"coordinates":[-79.393288,43.79179],"type":"Point"}
}