{
  "type": "Feature",
  "properties": {
    "iso:country":"CA",
    "sg:address":"7215 Rte Transcanadienne",
    "sg:city":"Saint-Laurent",
    "sg:classifiers":[
        {
            "category":"Wholesale",
            "subcategory":"Drugs",
            "type":"Manufacturing & Wholesale Goods"
        }
    ],
    "sg:phone":"+1 514 335 8146",
    "sg:postcode":"H4T 1A2",
    "sg:province":"QC",
    "sg:tags":[
        "preparation",
        "toilet",
        "salon",
        "beauty"
    ],
    "wof:name":"L'Oreal Professionnel",
    "wof:placetype":"venue"
},
  "geometry": {"coordinates":[-73.7040710449,45.4908981323],"type":"Point"}
}