{
  "type": "Feature",
  "properties": {
    "addr:full":"2 Beverly St W St George Brant ON N0E 1N0",
    "addr:housenumber":"2",
    "addr:postcode":"n0e 1n0",
    "addr:street":"Beverly St W",
    "iso:country":"CA",
    "sg:address":"2 Beverly St W",
    "sg:city":"St George Brant",
    "sg:classifiers":[
        {
            "category":"Retail",
            "subcategory":"Auto Repair",
            "type":"Services"
        }
    ],
    "sg:phone":"+1 519 448 1791",
    "sg:postcode":"N0E 1N0",
    "sg:province":"ON",
    "sg:tags":[
        "repairing",
        "automobile"
    ],
    "wof:name":"Jack Kay's Garage Ltd",
    "wof:placetype":"venue"
},
  "geometry": {"coordinates":[-80.25360107420001,43.2451248169],"type":"Point"}
}