{
  "type": "Feature",
  "properties": {
    "addr:full":"5842 Highway 2A Lacombe AB T4L 2G5",
    "addr:housenumber":"5842",
    "addr:postcode":"t4l 2g5",
    "addr:street":"Highway 2A",
    "iso:country":"CA",
    "sg:address":"5842 Highway 2A",
    "sg:city":"Lacombe",
    "sg:classifiers":[
        {
            "category":"Food & Beverages",
            "subcategory":"Groceries & Convenience Stores",
            "type":"Retail Goods"
        }
    ],
    "sg:phone":"+1 403 782 6200",
    "sg:postcode":"T4L 2G5",
    "sg:province":"AB",
    "sg:tags":[
        "department"
    ],
    "wof:name":"CO-OP Centre",
    "wof:placetype":"venue"
},
  "geometry": {"coordinates":[-113.718903,52.472675],"type":"Point"}
}