{
  "type": "Feature",
  "properties": {
    "addr:full":"459 Fenmar Dr North York ON M9L 2R6",
    "addr:housenumber":"459",
    "addr:postcode":"m9l 2r6",
    "addr:street":"Fenmar Dr",
    "iso:country":"CA",
    "sg:address":"459 Fenmar Dr",
    "sg:city":"North York",
    "sg:classifiers":[
        {
            "category":"Manufacturing",
            "subcategory":"Tools & Machinery",
            "type":"Manufacturing & Wholesale Goods"
        }
    ],
    "sg:phone":"+1 416 749 3322",
    "sg:postcode":"M9L 2R6",
    "sg:province":"ON",
    "sg:tags":[
        "die",
        "rule"
    ],
    "wof:name":"Container Graphics Ltd",
    "wof:placetype":"venue"
},
  "geometry": {"coordinates":[-79.5567855835,43.762676239],"type":"Point"}
}