{
  "type": "Feature",
  "properties": {
    "iso:country":"CA",
    "sg:address":"150 Churchill Blvd",
    "sg:city":"Sault Ste Marie",
    "sg:classifiers":[
        {
            "category":"Cinema",
            "subcategory":"Movie Rental",
            "type":"Entertainment"
        }
    ],
    "sg:phone":"+1 705 942 1788",
    "sg:postcode":"P6A 3Z9",
    "sg:province":"ON",
    "sg:tags":[
        "leasing",
        "video",
        "disc",
        "tape"
    ],
    "wof:name":"Rogers Video",
    "wof:placetype":"venue"
},
  "geometry": {"coordinates":[-84.29834700000001,46.509586],"type":"Point"}
}