{
  "type": "Feature",
  "properties": {
    "iso:country":"CA",
    "sg:address":"287 Speedvale Ave W",
    "sg:city":"Guelph",
    "sg:classifiers":[
        {
            "category":"Manufacturing",
            "subcategory":"Tools & Machinery",
            "type":"Manufacturing & Wholesale Goods"
        }
    ],
    "sg:phone":"+1 519 836 7550",
    "sg:postcode":"N1H 1C5",
    "sg:province":"ON",
    "sg:tags":[
        "machine",
        "shop"
    ],
    "wof:name":"Linamar Corp",
    "wof:placetype":"venue"
},
  "geometry": {"coordinates":[-80.2857131958,43.5459251404],"type":"Point"}
}