{
  "type": "Feature",
  "properties": {
    "addr:full":"265 W Stewart St Vanderhoof BC V0J 3A0",
    "addr:housenumber":"265",
    "addr:postcode":"v0j 3a0",
    "addr:street":"W Stewart St",
    "iso:country":"CA",
    "sg:address":"265 W Stewart St",
    "sg:city":"Vanderhoof",
    "sg:classifiers":[
        {
            "category":"Retail",
            "subcategory":"Repair Shop",
            "type":"Services"
        }
    ],
    "sg:phone":"+1 250 567 5120",
    "sg:postcode":"V0J 3A0",
    "sg:province":"BC",
    "sg:tags":[
        "appliance"
    ],
    "wof:name":"Doug's Appliance Svc",
    "wof:placetype":"venue"
},
  "geometry": {"coordinates":[-124.010345,54.016014],"type":"Point"}
}