{
  "type": "Feature",
  "properties": {
    "addr:full":"1346 Rue Des Voltigeurs Saint-Bruno QC J3V 2Y8",
    "addr:housenumber":"1346",
    "addr:postcode":"j3v 2y8",
    "addr:street":"Rue Des Voltigeurs",
    "iso:country":"CA",
    "sg:address":"1346 Rue Des Voltigeurs",
    "sg:city":"Saint-Bruno",
    "sg:classifiers":[
        {
            "category":"Building & Trades",
            "subcategory":"Electrical",
            "type":"Services"
        }
    ],
    "sg:phone":"+1 450 653 5166",
    "sg:postcode":"J3V 2Y8",
    "sg:province":"QC",
    "sg:tags":[
        "electric",
        "contractor"
    ],
    "wof:name":"Entreprises En Electricite",
    "wof:placetype":"venue"
},
  "geometry": {"coordinates":[-71.675522,48.471771],"type":"Point"}
}