{
  "type": "Feature",
  "properties": {
    "addr:full":"780 Rue DE Liege E Montreal QC H2P 1K9",
    "addr:housenumber":"780",
    "addr:postcode":"h2p 1k9",
    "addr:street":"Rue De Liege E",
    "iso:country":"CA",
    "sg:address":"780 Rue DE Liege E",
    "sg:city":"Montreal",
    "sg:classifiers":[
        {
            "category":"Utilities",
            "subcategory":"Fuel Oil & Lpg",
            "type":"Services"
        }
    ],
    "sg:phone":"+1 514 325 6446",
    "sg:postcode":"H2P 1K9",
    "sg:province":"QC",
    "sg:tags":[
        "firewood",
        "snow",
        "removal"
    ],
    "wof:name":"Dube N Deneigement Inc",
    "wof:placetype":"venue"
},
  "geometry": {"coordinates":[-73.63273620610001,45.548122406],"type":"Point"}
}