{
  "type": "Feature",
  "properties": {
    "addr:full":"5 Rue Fafard Cap-DE-LA-Madeleine QC G8V 1A9",
    "addr:housenumber":"5",
    "addr:postcode":"g8v 1a9",
    "addr:street":"Rue Fafard",
    "iso:country":"CA",
    "sg:address":"5 Rue Fafard",
    "sg:city":"Cap-DE-LA-Madeleine",
    "sg:classifiers":[
        {
            "category":"Shopping",
            "type":"Retail Goods"
        }
    ],
    "sg:phone":"+1 819 375 4110",
    "sg:postcode":"G8V 1A9",
    "sg:province":"QC",
    "sg:tags":[
        "equipment",
        "supply",
        "system",
        "telephone"
    ],
    "wof:name":"Santel Trois-Rivieres",
    "wof:placetype":"venue"
},
  "geometry": {"coordinates":[-72.561348,46.395695],"type":"Point"}
}