{
  "type": "Feature",
  "properties": {
    "addr:full":"31 Toro Rd North York ON M3J 2A4",
    "addr:housenumber":"31",
    "addr:postcode":"m3j 2a4",
    "addr:street":"Toro Rd",
    "iso:country":"CA",
    "sg:address":"31 Toro Rd",
    "sg:city":"North York",
    "sg:classifiers":[
        {
            "category":"Retail",
            "subcategory":"Auto Repair",
            "type":"Services"
        }
    ],
    "sg:phone":"+1 416 633 5800",
    "sg:postcode":"M3J 2A4",
    "sg:province":"ON",
    "sg:tags":[
        "repairing",
        "automobile"
    ],
    "wof:name":"D'Aversa Automotive Repairs",
    "wof:placetype":"venue"
},
  "geometry": {"coordinates":[-79.48802947999999,43.7601051331],"type":"Point"}
}