{
  "type": "Feature",
  "properties": {
    "iso:country":"CA",
    "sg:address":"PO Box 2168",
    "sg:city":"Lac LA Biche",
    "sg:classifiers":[
        {
            "category":"Social Services",
            "type":"Services"
        }
    ],
    "sg:phone":"+1 780 623 3100",
    "sg:postcode":"T0A 2C0",
    "sg:province":"AB",
    "sg:tags":[
        "crisis",
        "center"
    ],
    "wof:name":"Hope Haven Women's Shelter",
    "wof:placetype":"venue"
},
  "geometry": {"coordinates":[-111.97445678699999,54.77110672],"type":"Point"}
}