{
  "type": "Feature",
  "properties": {
    "addr:full":"50 Steeles Ave E Milton ON L9T 4W9",
    "addr:housenumber":"50",
    "addr:postcode":"l9t 4w9",
    "addr:street":"Steeles Ave E",
    "iso:country":"CA",
    "sg:address":"50 Steeles Ave E",
    "sg:city":"Milton",
    "sg:classifiers":[
        {
            "category":"Professional",
            "subcategory":"Research",
            "type":"Services"
        }
    ],
    "sg:phone":"+1 905 693 0227",
    "sg:postcode":"L9T 4W9",
    "sg:province":"ON",
    "sg:tags":[
        "development",
        "laboratory"
    ],
    "wof:name":"For Con Svc Ltd",
    "wof:placetype":"venue"
},
  "geometry": {"coordinates":[-79.8980178833,43.5177612305],"type":"Point"}
}