{
  "type": "Feature",
  "properties": {
    "addr:full":"458 Rue Seigneuriale Beauport QC G1C 3P9",
    "addr:housenumber":"458",
    "addr:postcode":"qc g1c 3p9",
    "addr:street":"Rue Seigneuriale",
    "iso:country":"CA",
    "sg:address":"458 Rue Seigneuriale",
    "sg:city":"Beauport",
    "sg:classifiers":[
        {
            "category":"Health Services",
            "subcategory":"Nursing And Care Facility",
            "type":"Services"
        }
    ],
    "sg:phone":"+1 418 666 7707",
    "sg:postcode":"G1C 3P9",
    "sg:province":"QC",
    "sg:tags":[
        "home",
        "retirement",
        "community",
        "rest"
    ],
    "wof:name":"Residences Aux 3 Pignons Inc",
    "wof:placetype":"venue"
},
  "geometry": {"coordinates":[-71.21019,46.889515],"type":"Point"}
}