{
  "type": "Feature",
  "properties": {
    "iso:country":"CA",
    "sg:address":"3459 Av Gaspard",
    "sg:city":"Beauport",
    "sg:classifiers":[
        {
            "category":"Shopping",
            "subcategory":"Clothing, Apparel, & Fashions",
            "type":"Retail Goods"
        }
    ],
    "sg:phone":"+1 418 626 4175",
    "sg:postcode":"G1C 3W6",
    "sg:province":"QC",
    "sg:tags":[
        "tailor"
    ],
    "wof:name":"Hermann Touzin Inc",
    "wof:placetype":"venue"
},
  "geometry": {"coordinates":[-71.2409820557,46.8610801697],"type":"Point"}
}