{
  "type": "Feature",
  "properties": {
    "iso:country":"CA",
    "sg:address":"NE 10 83 23 W 0F 5th",
    "sg:city":"Grimshaw",
    "sg:classifiers":[
        {
            "category":"Building & Trades",
            "subcategory":"Equipment Rental",
            "type":"Services"
        }
    ],
    "sg:phone":"+1 780 332 2995",
    "sg:postcode":"T0H 1W0",
    "sg:province":"AB",
    "sg:tags":[
        "helicopter",
        "aircraft",
        "leasing",
        "charter"
    ],
    "wof:name":"Ultra Helicopters Ltd",
    "wof:placetype":"venue"
},
  "geometry": {"coordinates":[-117.610466003,56.1913795471],"type":"Point"}
}