{
  "type": "Feature",
  "properties": {
    "addr:full":"PO Box 2290 STN Main Salmon Arm BC V1E 4R3",
    "addr:housenumber":"po",
    "addr:postcode":"v1e 4r3",
    "addr:street":"Box 2290 Stn Main",
    "iso:country":"CA",
    "sg:address":"PO Box 2290 STN Main",
    "sg:city":"Salmon Arm",
    "sg:classifiers":[
        {
            "category":"Wholesale",
            "subcategory":"Jewelry",
            "type":"Manufacturing & Wholesale Goods"
        }
    ],
    "sg:phone":"+1 250 804 0006",
    "sg:postcode":"V1E 4R3",
    "sg:province":"BC",
    "sg:tags":[
        "jeweler"
    ],
    "wof:name":"Adams & Son Importers Ltd",
    "wof:placetype":"venue"
},
  "geometry": {"coordinates":[-119.27188099999999,50.702221],"type":"Point"}
}