{
  "type": "Feature",
  "properties": {
    "addr:full":"755 Gilmore Rd Fort Erie ON L2A 5M4",
    "addr:housenumber":"755",
    "addr:postcode":"l2a 5m4",
    "addr:street":"Gilmore Rd",
    "iso:country":"CA",
    "sg:address":"755 Gilmore Rd",
    "sg:city":"Fort Erie",
    "sg:classifiers":[
        {
            "category":"Building & Trades",
            "subcategory":"Construction",
            "type":"Services"
        }
    ],
    "sg:phone":"+1 905 871 5069",
    "sg:postcode":"L2A 5M4",
    "sg:province":"ON",
    "sg:tags":[
        "concrete",
        "masonry",
        "contractor"
    ],
    "wof:name":"R A Pontello Construction",
    "wof:placetype":"venue"
},
  "geometry": {"coordinates":[-78.94461800000001,42.919876],"type":"Point"}
}