{
  "type": "Feature",
  "properties": {
    "addr:full":"752 Central Ave Greenwood NS B0P 1N0",
    "addr:housenumber":"752",
    "addr:postcode":"b0p 1n0",
    "addr:street":"Central Ave",
    "iso:country":"CA",
    "sg:address":"752 Central Ave",
    "sg:city":"Greenwood",
    "sg:classifiers":[
        {
            "category":"Real Estate",
            "subcategory":"Real Estate Agent",
            "type":"Services"
        }
    ],
    "sg:phone":"+1 902 765 6393",
    "sg:postcode":"B0P 1N0",
    "sg:province":"NS",
    "wof:name":"Acclaim Realty Ltd",
    "wof:placetype":"venue"
},
  "geometry": {"coordinates":[-64.934319,44.971573],"type":"Point"}
}