{
  "type": "Feature",
  "properties": {
    "addr:full":"SE 25 4 30 W 4 Pincher Creek AB T0K 1W0",
    "addr:housenumber":"25;30;4",
    "addr:postcode":"t0k 1w0",
    "addr:street":"Se;4;W",
    "iso:country":"CA",
    "sg:address":"SE 25 4 30 W 4",
    "sg:city":"Pincher Creek",
    "sg:classifiers":[
        {
            "category":"Farming",
            "subcategory":"Farm",
            "type":"Manufacturing & Wholesale Goods"
        }
    ],
    "sg:phone":"+1 403 627 2239",
    "sg:postcode":"T0K 1W0",
    "sg:province":"AB",
    "wof:name":"Wind Valley Ranch",
    "wof:placetype":"venue"
},
  "geometry": {"coordinates":[-113.950096,49.485668],"type":"Point"}
}