{
  "type": "Feature",
  "properties": {
    "iso:country":"CA",
    "sg:address":"197 Rue Young",
    "sg:city":"Montreal",
    "sg:classifiers":[
        {
            "category":"Professional",
            "subcategory":"Art Services",
            "type":"Services"
        }
    ],
    "sg:phone":"+1 514 939 9777",
    "sg:postcode":"H3C 2E9",
    "sg:province":"QC",
    "sg:tags":[
        "photographer"
    ],
    "wof:name":"Aventure Studio Enr",
    "wof:placetype":"venue"
},
  "geometry": {"coordinates":[-73.557579,45.492828],"type":"Point"}
}