{
  "type": "Feature",
  "properties": {
    "addr:full":"1110 Davie St Vancouver BC V6E 1N1",
    "addr:housenumber":"1110",
    "addr:postcode":"v6e 1n1",
    "addr:street":"Davie St",
    "iso:country":"CA",
    "sg:address":"1110 Davie St",
    "sg:city":"Vancouver",
    "sg:classifiers":[
        {
            "category":"Real Estate",
            "subcategory":"Real Estate Agent",
            "type":"Services"
        }
    ],
    "sg:phone":"+1 604 684 8613",
    "sg:postcode":"V6E 1N1",
    "sg:province":"BC",
    "wof:name":"Schuster Land Corp",
    "wof:placetype":"venue"
},
  "geometry": {"coordinates":[-123.131767,49.280567],"type":"Point"}
}