{
  "type": "Feature",
  "properties": {
    "addr:full":"352 Rue Brown LA Tuque QC G9X 2W4",
    "addr:housenumber":"352",
    "addr:postcode":"g9x 2w4",
    "addr:street":"Rue Brown",
    "iso:country":"CA",
    "sg:address":"352 Rue Brown",
    "sg:city":"LA Tuque",
    "sg:classifiers":[
        {
            "category":"Travel",
            "subcategory":"Hotels & Motels",
            "type":"Entertainment"
        }
    ],
    "sg:phone":"+1 819 523 9267",
    "sg:postcode":"G9X 2W4",
    "sg:province":"QC",
    "sg:tags":[
        "inn"
    ],
    "wof:name":"Auberge LA Residence",
    "wof:placetype":"venue"
},
  "geometry": {"coordinates":[-72.781654,47.445084],"type":"Point"}
}