{
  "type": "Feature",
  "properties": {
    "iso:country":"CA",
    "sg:city":"Wakefield",
    "sg:classifiers":[
        {
            "category":"Insurance",
            "subcategory":"Insurance Agent",
            "type":"Services"
        }
    ],
    "sg:phone":"+1 819 459 2361",
    "sg:postcode":"J0X 3G0",
    "sg:province":"QC",
    "wof:name":"Mallette-Mc Lennan Assurances",
    "wof:placetype":"venue"
},
  "geometry": {"coordinates":[-75.9282989502,45.6447868347],"type":"Point"}
}