{
  "type": "Feature",
  "properties": {
    "addr:full":"351 Speedvale Ave W Guelph ON N1H 1C6",
    "addr:housenumber":"351",
    "addr:postcode":"n1h 1c6",
    "addr:street":"Speedvale Ave W",
    "iso:country":"CA",
    "sg:address":"351 Speedvale Ave W",
    "sg:city":"Guelph",
    "sg:classifiers":[
        {
            "category":"Real Estate",
            "subcategory":"Surveying",
            "type":"Services"
        }
    ],
    "sg:phone":"+1 519 822 4031",
    "sg:postcode":"N1H 1C6",
    "sg:province":"ON",
    "sg:tags":[
        "surveyor"
    ],
    "wof:name":"Black Shoemaker Robinson Ltd",
    "wof:placetype":"venue"
},
  "geometry": {"coordinates":[-80.2895202637,43.5430526733],"type":"Point"}
}