{
  "type": "Feature",
  "properties": {
    "iso:country":"CA",
    "sg:address":"2670 Rue Paulus",
    "sg:city":"Saint-Laurent",
    "sg:classifiers":[
        {
            "category":"Wholesale",
            "subcategory":"Machinery & Supplies",
            "type":"Manufacturing & Wholesale Goods"
        }
    ],
    "sg:phone":"+1 514 337 4547",
    "sg:postcode":"H4S 1G1",
    "sg:province":"QC",
    "sg:tags":[
        "die",
        "tool",
        "maker"
    ],
    "wof:name":"Robot Machinerie Outils Ind",
    "wof:placetype":"venue"
},
  "geometry": {"coordinates":[-73.7462005615,45.4948730469],"type":"Point"}
}