{
  "type": "Feature",
  "properties": {
    "iso:country":"CA",
    "sg:address":"1365 Boul Cure-Labelle",
    "sg:city":"Laval",
    "sg:classifiers":[
        {
            "category":"Restaurant",
            "type":"Food & Drink"
        }
    ],
    "sg:phone":"+1 450 686 8669",
    "sg:postcode":"H7V 2V9",
    "sg:province":"QC",
    "wof:name":"Restaurant Saverio",
    "wof:placetype":"venue"
},
  "geometry": {"coordinates":[-73.755249,45.547466],"type":"Point"}
}