{
  "type": "Feature",
  "properties": {
    "addr:full":"1365 Boul Cure-Labelle Laval QC H7V 2V9",
    "addr:housenumber":"1365",
    "addr:postcode":"h7v 2v9",
    "addr:street":"Boul Cure-Labelle",
    "iso:country":"CA",
    "sg:address":"1365 Boul Cure-Labelle",
    "sg:city":"Laval",
    "sg:classifiers":[
        {
            "category":"Restaurant",
            "type":"Food & Drink"
        }
    ],
    "sg:phone":"+1 450 686 8669",
    "sg:postcode":"H7V 2V9",
    "sg:province":"QC",
    "wof:name":"Restaurant Saverio",
    "wof:placetype":"venue"
},
  "geometry": {"coordinates":[-73.75524900000001,45.547466],"type":"Point"}
}