{
  "type": "Feature",
  "properties": {
    "iso:country":"CA",
    "sg:address":"610 Ontario Rd",
    "sg:city":"Welland",
    "sg:classifiers":[
        {
            "category":"Organizations",
            "subcategory":"Religious Organization",
            "type":"Services"
        }
    ],
    "sg:phone":"+1 905 788 3943",
    "sg:postcode":"L3B 5C8",
    "sg:province":"ON",
    "sg:tags":[
        "church"
    ],
    "wof:name":"Apolistic Lighthouse Upc",
    "wof:placetype":"venue"
},
  "geometry": {"coordinates":[-79.2427520752,42.9744873047],"type":"Point"}
}