{
  "type": "Feature",
  "properties": {
    "iso:country":"CA",
    "sg:city":"Winnipeg",
    "sg:classifiers":[
        {
            "category":"Health Services",
            "subcategory":"Optometrist",
            "type":"Services"
        }
    ],
    "sg:phone":"+1 204 582 2308",
    "sg:postcode":"R2G 1P1",
    "sg:province":"MB",
    "wof:name":"Henderson Vision Ctr",
    "wof:placetype":"venue"
},
  "geometry": {"coordinates":[-97.07963599999999,49.950871],"type":"Point"}
}