{
  "type": "Feature",
  "properties": {
    "addr:full":"9318 Townsend Line Arkona ON N0M 1B0",
    "addr:housenumber":"9318",
    "addr:postcode":"n0m 1b0",
    "addr:street":"Townsend Line",
    "iso:country":"CA",
    "sg:address":"9318 Townsend Line",
    "sg:city":"Arkona",
    "sg:classifiers":[
        {
            "category":"Building & Trades",
            "subcategory":"Construction",
            "type":"Services"
        }
    ],
    "sg:phone":"+1 519 828 3210",
    "sg:postcode":"N0M 1B0",
    "sg:province":"ON",
    "sg:tags":[
        "excavating",
        "contractor"
    ],
    "wof:name":"Ernie Herrington Excavating",
    "wof:placetype":"venue"
},
  "geometry": {"coordinates":[-81.8341369629,43.0743637085],"type":"Point"}
}