{
  "type": "Feature",
  "properties": {
    "addr:full":"565 Boul Saint-Joseph Drummondville QC J2C 2B6",
    "addr:housenumber":"565",
    "addr:postcode":"j2c 2b6",
    "addr:street":"Boul Saint-Joseph",
    "iso:country":"CA",
    "sg:address":"565 Boul Saint-Joseph",
    "sg:city":"Drummondville",
    "sg:classifiers":[
        {
            "category":"Shopping",
            "subcategory":"Department Store",
            "type":"Retail Goods"
        }
    ],
    "sg:phone":"+1 819 472 8496",
    "sg:postcode":"J2C 2B6",
    "sg:province":"QC",
    "wof:name":"Dollar Station",
    "wof:placetype":"venue"
},
  "geometry": {"coordinates":[-72.51490800000001,45.893169],"type":"Point"}
}