{
  "type": "Feature",
  "properties": {
    "addr:full":"9214 Mary St Chilliwack BC V2P 4H6",
    "addr:housenumber":"9214",
    "addr:postcode":"v2p 4h6",
    "addr:street":"Mary St",
    "iso:country":"CA",
    "sg:address":"9214 Mary St",
    "sg:city":"Chilliwack",
    "sg:classifiers":[
        {
            "category":"Health Services",
            "subcategory":"Doctor",
            "type":"Services"
        }
    ],
    "sg:phone":"+1 604 795 7228",
    "sg:postcode":"V2P 4H6",
    "sg:province":"BC",
    "sg:tags":[
        "physician",
        "surgeon"
    ],
    "wof:name":"Kerr, C MD",
    "wof:placetype":"venue"
},
  "geometry": {"coordinates":[-121.959114,49.169411],"type":"Point"}
}