{
  "type": "Feature",
  "properties": {
    "addr:full":"Mount Pearl NL A1N 4R9",
    "addr:postcode":"a1n 4r9",
    "iso:country":"CA",
    "sg:city":"Mount Pearl",
    "sg:classifiers":[
        {
            "category":"Autos & Motor Vehicles",
            "subcategory":"Auto Supplies",
            "type":"Retail Goods"
        }
    ],
    "sg:phone":"+1 709 745 6464",
    "sg:postcode":"A1N 4R9",
    "sg:province":"NL",
    "sg:tags":[
        "equipment",
        "industrial",
        "gas"
    ],
    "wof:name":"Techcon Enterprises Ltd",
    "wof:placetype":"venue"
},
  "geometry": {"coordinates":[-52.836929,47.523598],"type":"Point"}
}