{
  "type": "Feature",
  "properties": {
    "addr:full":"620 Rue Du Filtre Victoriaville QC G6P 6R9",
    "addr:housenumber":"620",
    "addr:postcode":"g6p 6r9",
    "addr:street":"Rue Du Filtre",
    "iso:country":"CA",
    "sg:address":"620 Rue Du Filtre",
    "sg:city":"Victoriaville",
    "sg:classifiers":[
        {
            "category":"Food & Beverages",
            "subcategory":"Fruits & Vegetables",
            "type":"Retail Goods"
        }
    ],
    "sg:phone":"+1 819 752 9351",
    "sg:postcode":"G6P 6R9",
    "sg:province":"QC",
    "sg:tags":[
        "produce"
    ],
    "wof:name":"Fraisiere, Gagne",
    "wof:placetype":"venue"
},
  "geometry": {"coordinates":[-71.936699,46.0905],"type":"Point"}
}