{
  "type": "Feature",
  "properties": {
    "addr:full":"462 Topsail Rd St. John's NL A1E 2C2",
    "addr:housenumber":"462",
    "addr:postcode":"a1e 2c2",
    "addr:street":"Topsail Rd",
    "iso:country":"CA",
    "sg:address":"462 Topsail Rd",
    "sg:city":"St. John's",
    "sg:classifiers":[
        {
            "category":"Restaurant",
            "type":"Food & Drink"
        }
    ],
    "sg:phone":"+1 709 747 2582",
    "sg:postcode":"A1E 2C2",
    "sg:province":"NL",
    "wof:name":"Subway Sandwiches & Salads",
    "wof:placetype":"venue"
},
  "geometry": {"coordinates":[-52.7544937134,47.5316772461],"type":"Point"}
}