{
  "type": "Feature",
  "properties": {
    "addr:full":"8711 66 Ave NW Edmonton AB T6E 0L4",
    "addr:housenumber":"8711",
    "addr:postcode":"t6e 0l4",
    "addr:street":"66 Ave Nw",
    "iso:country":"CA",
    "sg:address":"8711 66 Ave NW",
    "sg:city":"Edmonton",
    "sg:classifiers":[
        {
            "category":"Building & Trades",
            "subcategory":"Electrical",
            "type":"Services"
        }
    ],
    "sg:phone":"+1 780 446 1474",
    "sg:postcode":"T6E 0L4",
    "sg:province":"AB",
    "sg:tags":[
        "electric",
        "contractor"
    ],
    "wof:name":"Wajan Electrical Svc Ltd",
    "wof:placetype":"venue"
},
  "geometry": {"coordinates":[-113.463127,53.501724],"type":"Point"}
}