{
  "type": "Feature",
  "properties": {
    "addr:full":"33 Pender St E Vancouver BC V6A 1S9",
    "addr:housenumber":"33",
    "addr:postcode":"v6a 1s9",
    "addr:street":"Pender St E",
    "iso:country":"CA",
    "sg:address":"33 Pender St E",
    "sg:city":"Vancouver",
    "sg:classifiers":[
        {
            "category":"Personal",
            "subcategory":"Beauty Salon",
            "type":"Services"
        }
    ],
    "sg:phone":"+1 604 688 8226",
    "sg:postcode":"V6A 1S9",
    "sg:province":"BC",
    "wof:name":"Sue's Beauty Salon",
    "wof:placetype":"venue"
},
  "geometry": {"coordinates":[-123.10359200000001,49.280575],"type":"Point"}
}