{
  "type": "Feature",
  "properties": {
    "addr:full":"595 West St Brantford ON N3R 7C5",
    "addr:housenumber":"595",
    "addr:postcode":"n3r 7c5",
    "addr:street":"West St",
    "iso:country":"CA",
    "sg:address":"595 West St",
    "sg:city":"Brantford",
    "sg:classifiers":[
        {
            "category":"Food & Beverages",
            "subcategory":"Meat & Fish",
            "type":"Retail Goods"
        }
    ],
    "sg:phone":"+1 519 750 1107",
    "sg:postcode":"N3R 7C5",
    "sg:province":"ON",
    "sg:tags":[
        "frozen"
    ],
    "wof:name":"M & M Meat Shops",
    "wof:placetype":"venue"
},
  "geometry": {"coordinates":[-80.248001,43.169327],"type":"Point"}
}