{
  "type": "Feature",
  "properties": {
    "addr:full":"917 East Chestermere Dr Chestermere AB T1X 1A8",
    "addr:housenumber":"917",
    "addr:postcode":"t1x 1a8",
    "addr:street":"East Chestermere Dr",
    "iso:country":"CA",
    "sg:address":"917 East Chestermere Dr",
    "sg:city":"Chestermere",
    "sg:classifiers":[
        {
            "category":"Building & Trades",
            "subcategory":"Electrical",
            "type":"Services"
        }
    ],
    "sg:phone":"+1 403 934 3373",
    "sg:postcode":"T1X 1A8",
    "sg:province":"AB",
    "sg:tags":[
        "electric",
        "contractor"
    ],
    "wof:name":"Spruce Park Electric",
    "wof:placetype":"venue"
},
  "geometry": {"coordinates":[-113.815086365,51.0260848999],"type":"Point"}
}