{
  "type": "Feature",
  "properties": {
    "addr:full":"9002 20 St NW Edmonton AB T6P 1K8",
    "addr:housenumber":"9002",
    "addr:postcode":"t6p 1k8",
    "addr:street":"20 St Nw",
    "iso:country":"CA",
    "sg:address":"9002 20 St NW",
    "sg:city":"Edmonton",
    "sg:classifiers":[
        {
            "category":"Freight",
            "type":"Transportation"
        }
    ],
    "sg:phone":"+1 780 464 7174",
    "sg:postcode":"T6P 1K8",
    "sg:province":"AB",
    "sg:tags":[
        "warehouse",
        "storage"
    ],
    "wof:name":"Versacold Canada Corp",
    "wof:placetype":"venue"
},
  "geometry": {"coordinates":[-113.375701904,53.502948761],"type":"Point"}
}