{
  "type": "Feature",
  "properties": {
    "addr:full":"1203 Boul Saint-Laurent Montreal QC H2X 2S6",
    "addr:housenumber":"1203",
    "addr:postcode":"h2x 2s6",
    "addr:street":"Boul Saint-Laurent",
    "iso:country":"CA",
    "sg:address":"1203 Boul Saint-Laurent",
    "sg:city":"Montreal",
    "sg:classifiers":[
        {
            "category":"Shopping",
            "type":"Retail Goods"
        }
    ],
    "sg:phone":"+1 514 861 6051",
    "sg:postcode":"H2X 2S6",
    "sg:province":"QC",
    "sg:tags":[
        "telephone",
        "cellular"
    ],
    "wof:name":"Entrepot Cellulaire Inc",
    "wof:placetype":"venue"
},
  "geometry": {"coordinates":[-73.5626907349,45.5095024109],"type":"Point"}
}