{
  "type": "Feature",
  "properties": {
    "iso:country":"CA",
    "sg:address":"7385 Boul DE LA Rive-Sud",
    "sg:city":"Levis",
    "sg:classifiers":[
        {
            "category":"Retail",
            "subcategory":"Auto Repair",
            "type":"Services"
        }
    ],
    "sg:phone":"+1 418 837 4685",
    "sg:postcode":"G6V 7A3",
    "sg:province":"QC",
    "sg:tags":[
        "repairing",
        "automobile"
    ],
    "wof:name":"Garage Pierre Bernier Enr",
    "wof:placetype":"venue"
},
  "geometry": {"coordinates":[-71.152633667,46.8141021729],"type":"Point"}
}