{
  "type": "Feature",
  "properties": {
    "addr:full":"43 Rue Child Coaticook QC J1A 2B2",
    "addr:housenumber":"43",
    "addr:postcode":"j1a 2b2",
    "addr:street":"Rue Child",
    "iso:country":"CA",
    "sg:address":"43 Rue Child",
    "sg:city":"Coaticook",
    "sg:classifiers":[
        {
            "category":"Professional",
            "subcategory":"Accounting & Tax Preparation",
            "type":"Services"
        }
    ],
    "sg:phone":"+1 819 849 4894",
    "sg:postcode":"J1A 2B2",
    "sg:province":"QC",
    "sg:tags":[
        "accountant"
    ],
    "wof:name":"Dumont, Bernard",
    "wof:placetype":"venue"
},
  "geometry": {"coordinates":[-71.80510700000001,45.133049],"type":"Point"}
}