{
  "type": "Feature",
  "properties": {
    "addr:full":"8 Rue Saint-Jean-Baptiste Saint-Louis-Du-Ha-Ha QC G0L 3S0",
    "addr:housenumber":"8",
    "addr:postcode":"g0l 3s0",
    "addr:street":"Rue Saint-Jean-Baptiste",
    "iso:country":"CA",
    "sg:address":"8 Rue Saint-Jean-Baptiste",
    "sg:city":"Saint-Louis-Du-Ha-Ha",
    "sg:classifiers":[
        {
            "category":"Insurance",
            "subcategory":"Insurance Agent",
            "type":"Services"
        }
    ],
    "sg:phone":"+1 418 854 9121",
    "sg:postcode":"G0L 3S0",
    "sg:province":"QC",
    "wof:name":"Morin, Ghislain",
    "wof:placetype":"venue"
},
  "geometry": {"coordinates":[-68.97788199999999,47.670971],"type":"Point"}
}