{
  "type": "Feature",
  "properties": {
    "addr:full":"660 Atherley Rd Orillia ON L3V 1P2",
    "addr:housenumber":"660",
    "addr:postcode":"l3v 1p2",
    "addr:street":"Atherley Rd",
    "iso:country":"CA",
    "sg:address":"660 Atherley Rd",
    "sg:city":"Orillia",
    "sg:classifiers":[
        {
            "category":"Shopping",
            "subcategory":"Bicycles & Sporting Goods",
            "type":"Retail Goods"
        }
    ],
    "sg:phone":"+1 705 325 5873",
    "sg:postcode":"L3V 1P2",
    "sg:province":"ON",
    "wof:name":"Hook & Bow",
    "wof:placetype":"venue"
},
  "geometry": {"coordinates":[-79.373665,44.604958],"type":"Point"}
}