{
  "type": "Feature",
  "properties": {
    "iso:country":"CA",
    "sg:address":"3104 Edgemont Blvd",
    "sg:city":"North Vancouver",
    "sg:classifiers":[
        {
            "category":"Shopping",
            "subcategory":"Optical Goods",
            "type":"Retail Goods"
        }
    ],
    "sg:phone":"+1 604 988 8919",
    "sg:postcode":"V7R 2N6",
    "sg:province":"BC",
    "sg:tags":[
        "sun",
        "goggles",
        "sunglasses"
    ],
    "wof:name":"Highland Optical",
    "wof:placetype":"venue"
},
  "geometry": {"coordinates":[-123.101890564,49.3376846313],"type":"Point"}
}