{
  "type": "Feature",
  "properties": {
    "addr:full":"1978 Weston Rd York ON M9N 1W2",
    "addr:housenumber":"1978",
    "addr:postcode":"m9n 1w2",
    "addr:street":"Weston Rd",
    "iso:country":"CA",
    "sg:address":"1978 Weston Rd",
    "sg:city":"York",
    "sg:classifiers":[
        {
            "category":"Shopping",
            "subcategory":"Discount & Variety Stores",
            "type":"Retail Goods"
        }
    ],
    "sg:phone":"+1 416 242 8508",
    "sg:postcode":"M9N 1W2",
    "sg:province":"ON",
    "wof:name":"Bumper Discount & Smoke Corner",
    "wof:placetype":"venue"
},
  "geometry": {"coordinates":[-79.51907300000001,43.700794],"type":"Point"}
}