{
  "type": "Feature",
  "properties": {
    "addr:full":"1152 Ch DE Chambly Longueuil QC J4J 3W6",
    "addr:housenumber":"1152",
    "addr:postcode":"j4j 3w6",
    "addr:street":"Ch De Chambly",
    "iso:country":"CA",
    "sg:address":"1152 Ch DE Chambly",
    "sg:city":"Longueuil",
    "sg:classifiers":[
        {
            "category":"Shopping",
            "subcategory":"Clothing, Apparel, & Fashions",
            "type":"Retail Goods"
        }
    ],
    "sg:phone":"+1 450 677 0950",
    "sg:postcode":"J4J 3W6",
    "sg:province":"QC",
    "sg:tags":[
        "uniform"
    ],
    "wof:name":"Uniformes & Accessoires Mode",
    "wof:placetype":"venue"
},
  "geometry": {"coordinates":[-73.48979199999999,45.532631],"type":"Point"}
}