{
  "type": "Feature",
  "properties": {
    "addr:full":"521 Deering St Nanaimo BC V9R 6Y2",
    "addr:housenumber":"521",
    "addr:postcode":"v9r 6y2",
    "addr:street":"Deering St",
    "iso:country":"CA",
    "sg:address":"521 Deering St",
    "sg:city":"Nanaimo",
    "sg:classifiers":[
        {
            "category":"Health Services",
            "subcategory":"Doctor",
            "type":"Services"
        }
    ],
    "sg:phone":"+1 250 754 1949",
    "sg:postcode":"V9R 6Y2",
    "sg:province":"BC",
    "sg:tags":[
        "dentist"
    ],
    "wof:name":"Lueke, Lynn DDS",
    "wof:placetype":"venue"
},
  "geometry": {"coordinates":[-123.950012207,49.1455535889],"type":"Point"}
}