{
  "type": "Feature",
  "properties": {
    "addr:full":"1580 Pipeline Rd Coquitlam BC V3E 3P6",
    "addr:housenumber":"1580",
    "addr:postcode":"v3e 3p6",
    "addr:street":"Pipeline Rd",
    "iso:country":"CA",
    "sg:address":"1580 Pipeline Rd",
    "sg:city":"Coquitlam",
    "sg:classifiers":[
        {
            "category":"Wholesale",
            "subcategory":"Construction Materials",
            "type":"Manufacturing & Wholesale Goods"
        }
    ],
    "sg:phone":"+1 604 944 1448",
    "sg:postcode":"V3E 3P6",
    "sg:province":"BC",
    "sg:tags":[
        "sand",
        "gravel"
    ],
    "wof:name":"Allard Contractors Ltd",
    "wof:placetype":"venue"
},
  "geometry": {"coordinates":[-122.772423,49.311501],"type":"Point"}
}