{
  "type": "Feature",
  "properties": {
    "addr:full":"190 Highway 33 W Kelowna BC V1X 1X7",
    "addr:housenumber":"190",
    "addr:postcode":"v1x 1x7",
    "addr:street":"Highway 33 W",
    "iso:country":"CA",
    "sg:address":"190 Highway 33 W",
    "sg:city":"Kelowna",
    "sg:classifiers":[
        {
            "category":"Banks & Credit Unions",
            "subcategory":"Bank",
            "type":"Services"
        }
    ],
    "sg:phone":"+1 250 491 7000",
    "sg:postcode":"V1X 1X7",
    "sg:province":"BC",
    "wof:name":"Scotiabank",
    "wof:placetype":"venue"
},
  "geometry": {"coordinates":[-119.49659729,49.8868141174],"type":"Point"}
}