{
  "type": "Feature",
  "properties": {
    "addr:full":"864 Rue Des Ursulines # 3 Trois-Rivieres QC G9A 5C1",
    "addr:housenumber":"864;# 3",
    "addr:postcode":"g9a 5c1",
    "addr:street":"Rue Des Ursulines;Trois-Rivieres",
    "iso:country":"CA",
    "sg:address":"864 Rue Des Ursulines # 3",
    "sg:city":"Trois-Rivieres",
    "sg:classifiers":[
        {
            "category":"Museum",
            "type":"Entertainment"
        }
    ],
    "sg:phone":"+1 819 691 0829",
    "sg:postcode":"G9A 5C1",
    "sg:province":"QC",
    "sg:tags":[
        "organization",
        "arts",
        "information"
    ],
    "wof:name":"Biennale Nationale DE Ceramiqu",
    "wof:placetype":"venue"
},
  "geometry": {"coordinates":[-72.53829956049999,46.3430862427],"type":"Point"}
}