{
  "type": "Feature",
  "properties": {
    "addr:full":"RR 1 Bedeque PE C0B 1C0",
    "addr:postcode":"c0b 1c0",
    "addr:street":"Rr 1",
    "iso:country":"CA",
    "sg:address":"RR 1",
    "sg:city":"Bedeque",
    "sg:classifiers":[
        {
            "category":"Autos & Motor Vehicles",
            "subcategory":"Automobile Sales",
            "type":"Retail Goods"
        }
    ],
    "sg:phone":"+1 902 887 2556",
    "sg:postcode":"C0B 1C0",
    "sg:province":"PE",
    "sg:tags":[
        "car",
        "truck"
    ],
    "wof:name":"Barter Centre Used Vehicles",
    "wof:placetype":"venue"
},
  "geometry": {"coordinates":[-63.725075,46.337898],"type":"Point"}
}