{
  "type": "Feature",
  "properties": {
    "addr:full":"1976 Boul Des Laurentides Vimont QC H7M 2R4",
    "addr:housenumber":"1976",
    "addr:postcode":"h7m 2r4",
    "addr:street":"Boul Des Laurentides",
    "iso:country":"CA",
    "sg:address":"1976 Boul Des Laurentides",
    "sg:city":"Vimont",
    "sg:classifiers":[
        {
            "category":"Building & Trades",
            "subcategory":"Electrical",
            "type":"Services"
        }
    ],
    "sg:phone":"+1 450 668 9900",
    "sg:postcode":"H7M 2R4",
    "sg:province":"QC",
    "sg:tags":[
        "electric",
        "contractor"
    ],
    "wof:name":"Dube & Dube Electrique Inc",
    "wof:placetype":"venue"
},
  "geometry": {"coordinates":[-73.73067500000001,45.604805],"type":"Point"}
}