{
  "type": "Feature",
  "properties": {
    "addr:full":"Trans Canada Hwy E Brandon MB R7A 5Y5",
    "addr:postcode":"r7a 5y5",
    "addr:street":"Trans Canada Hwy E",
    "iso:country":"CA",
    "sg:address":"Trans Canada Hwy E",
    "sg:city":"Brandon",
    "sg:classifiers":[
        {
            "category":"Shopping",
            "subcategory":"Hobbies, Toys, & Games",
            "type":"Retail Goods"
        }
    ],
    "sg:phone":"+1 204 728 1245",
    "sg:postcode":"R7A 5Y5",
    "sg:province":"MB",
    "sg:tags":[
        "doll"
    ],
    "wof:name":"Carrousels & Dolls",
    "wof:placetype":"venue"
},
  "geometry": {"coordinates":[-99.95296478269999,49.8867912292],"type":"Point"}
}