{
  "type": "Feature",
  "properties": {
    "addr:full":"7961 Pemberton Meadows Rd Pemberton BC V0N 2L0",
    "addr:housenumber":"7961",
    "addr:postcode":"v0n 2l0",
    "addr:street":"Pemberton Meadows Rd",
    "iso:country":"CA",
    "sg:address":"7961 Pemberton Meadows Rd",
    "sg:city":"Pemberton",
    "sg:classifiers":[
        {
            "category":"Recreation",
            "type":"Entertainment"
        }
    ],
    "sg:phone":"+1 604 894 6615",
    "sg:postcode":"V0N 2L0",
    "sg:province":"BC",
    "sg:tags":[
        "amusement",
        "stable"
    ],
    "wof:name":"Pemberton Stables",
    "wof:placetype":"venue"
},
  "geometry": {"coordinates":[-122.81117999999999,50.326477],"type":"Point"}
}