{
  "type": "Feature",
  "properties": {
    "addr:full":"3625 Dufferin St North York ON M3K 1Z2",
    "addr:housenumber":"3625",
    "addr:postcode":"m3k 1z2",
    "addr:street":"Dufferin St",
    "iso:country":"CA",
    "sg:address":"3625 Dufferin St",
    "sg:city":"North York",
    "sg:classifiers":[
        {
            "category":"Real Estate",
            "subcategory":"Real Estate Operator",
            "type":"Services"
        }
    ],
    "sg:phone":"+1 416 635 8323",
    "sg:postcode":"M3K 1Z2",
    "sg:province":"ON",
    "sg:tags":[
        "apartment"
    ],
    "wof:name":"Parkway Realty Ltd",
    "wof:placetype":"venue"
},
  "geometry": {"coordinates":[-79.458534,43.7314],"type":"Point"}
}