{
  "type": "Feature",
  "properties": {
    "addr:full":"Saint-Clet QC J0P 1S0",
    "addr:postcode":"j0p 1s0",
    "iso:country":"CA",
    "sg:city":"Saint-Clet",
    "sg:classifiers":[
        {
            "category":"Building & Trades",
            "subcategory":"Landscaping Services",
            "type":"Services"
        }
    ],
    "sg:phone":"+1 450 456 3744",
    "sg:postcode":"J0P 1S0",
    "sg:province":"QC",
    "sg:tags":[
        "landscape",
        "contractor"
    ],
    "wof:name":"Pelouse-Tec",
    "wof:placetype":"venue"
},
  "geometry": {"coordinates":[-74.21803300000001,45.355499],"type":"Point"}
}