{
  "type": "Feature",
  "properties": {
    "addr:full":"29 Arrowflight Dr Markham ON L3P 1R9",
    "addr:housenumber":"29",
    "addr:postcode":"l3p 1r9",
    "addr:street":"Arrowflight Dr",
    "iso:country":"CA",
    "sg:address":"29 Arrowflight Dr",
    "sg:city":"Markham",
    "sg:classifiers":[
        {
            "category":"Freight",
            "type":"Transportation"
        }
    ],
    "sg:phone":"+1 905 294 4413",
    "sg:postcode":"L3P 1R9",
    "sg:province":"ON",
    "sg:tags":[
        "trucking"
    ],
    "wof:name":"Bendell Haulage Ltd",
    "wof:placetype":"venue"
},
  "geometry": {"coordinates":[-79.27155303959999,43.8721237183],"type":"Point"}
}