{
  "type": "Feature",
  "properties": {
    "addr:full":"177 Atkinson Rd Madoc ON K0K 2K0",
    "addr:housenumber":"177",
    "addr:postcode":"k0k 2k0",
    "addr:street":"Atkinson Rd",
    "iso:country":"CA",
    "sg:address":"177 Atkinson Rd",
    "sg:city":"Madoc",
    "sg:classifiers":[
        {
            "category":"Sports & Exercise",
            "subcategory":"Golf",
            "type":"Entertainment"
        }
    ],
    "sg:phone":"+1 613 473 3880",
    "sg:postcode":"K0K 2K0",
    "sg:province":"ON",
    "sg:tags":[
        "course"
    ],
    "wof:name":"West Highland Golf Course",
    "wof:placetype":"venue"
},
  "geometry": {"coordinates":[-77.49329400000001,44.501625],"type":"Point"}
}