{
  "type": "Feature",
  "properties": {
    "iso:country":"CA",
    "sg:address":"735 6E Rang N",
    "sg:city":"Saint-Bruno-Lac-Saint-Jean",
    "sg:classifiers":[
        {
            "category":"Food & Beverages",
            "subcategory":"Dairy",
            "type":"Retail Goods"
        }
    ],
    "sg:phone":"+1 418 343 3655",
    "sg:postcode":"G0W 2L0",
    "sg:province":"QC",
    "sg:tags":[
        "cheese"
    ],
    "wof:name":"Fromagerie Maurice St-Laurent",
    "wof:placetype":"venue"
},
  "geometry": {"coordinates":[-70.8897018433,46.9212303162],"type":"Point"}
}