{
  "type": "Feature",
  "properties": {
    "addr:full":"Montreal QC H2Y 2W8",
    "addr:postcode":"h2y 2w8",
    "iso:country":"CA",
    "sg:city":"Montreal",
    "sg:classifiers":[
        {
            "category":"Professional",
            "subcategory":"Research",
            "type":"Services"
        }
    ],
    "sg:phone":"+1 514 982 2464",
    "sg:postcode":"H2Y 2W8",
    "sg:province":"QC",
    "sg:tags":[
        "market",
        "analysis"
    ],
    "wof:name":"Leger Marketing",
    "wof:placetype":"venue"
},
  "geometry": {"coordinates":[-73.554359436,45.5123100281],"type":"Point"}
}