{
  "type": "Feature",
  "properties": {
    "addr:full":"108 Centre St St Thomas ON N5R 2Z7",
    "addr:housenumber":"108",
    "addr:postcode":"n5r 2z7",
    "addr:street":"Centre St",
    "iso:country":"CA",
    "sg:address":"108 Centre St",
    "sg:city":"St Thomas",
    "sg:classifiers":[
        {
            "category":"Professional",
            "subcategory":"Secretarial Services",
            "type":"Services"
        }
    ],
    "sg:phone":"+1 519 637 1708",
    "sg:postcode":"N5R 2Z7",
    "sg:province":"ON",
    "sg:tags":[
        "convention",
        "court",
        "reporter"
    ],
    "wof:name":"Djs Reporting Svc",
    "wof:placetype":"venue"
},
  "geometry": {"coordinates":[-81.2007598877,42.7778091431],"type":"Point"}
}