{
  "type": "Feature",
  "properties": {
    "addr:full":"530 Rue Chasse Asbestos QC J1T 3X7",
    "addr:housenumber":"530",
    "addr:postcode":"j1t 3x7",
    "addr:street":"Rue Chasse",
    "iso:country":"CA",
    "sg:address":"530 Rue Chasse",
    "sg:city":"Asbestos",
    "sg:classifiers":[
        {
            "category":"Government",
            "subcategory":"Office",
            "type":"Public Place"
        }
    ],
    "sg:phone":"+1 819 879 4554",
    "sg:postcode":"J1T 3X7",
    "sg:province":"QC",
    "wof:name":"Quebec Mandataires",
    "wof:placetype":"venue"
},
  "geometry": {"coordinates":[-71.9295043945,45.7682876587],"type":"Point"}
}