{
  "type": "Feature",
  "properties": {
    "addr:full":"Chatham ON N7M 6B3",
    "addr:postcode":"n7m 6b3",
    "iso:country":"CA",
    "sg:city":"Chatham",
    "sg:classifiers":[
        {
            "category":"Professional",
            "subcategory":"Lawyer & Legal Services",
            "type":"Services"
        }
    ],
    "sg:phone":"+1 519 352 4700",
    "sg:postcode":"N7M 6B3",
    "sg:province":"ON",
    "sg:tags":[
        "attorney"
    ],
    "wof:name":"Rhodes Law Firm",
    "wof:placetype":"venue"
},
  "geometry": {"coordinates":[-82.181152,42.404606],"type":"Point"}
}