{
  "type": "Feature",
  "properties": {
    "addr:full":"133 Mcintosh St Scarborough ON M1N 3Y8",
    "addr:housenumber":"133",
    "addr:postcode":"m1n 3y8",
    "addr:street":"Mcintosh St",
    "iso:country":"CA",
    "sg:address":"133 Mcintosh St",
    "sg:city":"Scarborough",
    "sg:classifiers":[
        {
            "category":"Manufacturing",
            "subcategory":"Paper Products",
            "type":"Manufacturing & Wholesale Goods"
        }
    ],
    "sg:phone":"+1 416 267 4482",
    "sg:postcode":"M1N 3Y8",
    "sg:province":"ON",
    "sg:tags":[
        "label"
    ],
    "wof:name":"H Moore Printing Svc Ltd",
    "wof:placetype":"venue"
},
  "geometry": {"coordinates":[-79.25202899999999,43.707287],"type":"Point"}
}