{
  "type": "Feature",
  "properties": {
    "iso:country":"CA",
    "sg:address":"1145 Alaska Ave",
    "sg:city":"Dawson Creek",
    "sg:classifiers":[
        {
            "category":"Autos & Motor Vehicles",
            "subcategory":"Auto Supplies",
            "type":"Retail Goods"
        }
    ],
    "sg:phone":"+1 250 782 1777",
    "sg:postcode":"V1G 1Y8",
    "sg:province":"BC",
    "sg:tags":[
        "tire"
    ],
    "wof:name":"Tirecraft",
    "wof:placetype":"venue"
},
  "geometry": {"coordinates":[-120.231452942,55.7601242065],"type":"Point"}
}