{
  "type": "Feature",
  "properties": {
    "addr:full":"1145 Alaska Ave Dawson Creek BC V1G 1Y8",
    "addr:housenumber":"1145",
    "addr:postcode":"v1g 1y8",
    "addr:street":"Alaska Ave",
    "iso:country":"CA",
    "sg:address":"1145 Alaska Ave",
    "sg:city":"Dawson Creek",
    "sg:classifiers":[
        {
            "category":"Autos & Motor Vehicles",
            "subcategory":"Auto Supplies",
            "type":"Retail Goods"
        }
    ],
    "sg:phone":"+1 250 782 1777",
    "sg:postcode":"V1G 1Y8",
    "sg:province":"BC",
    "sg:tags":[
        "tire"
    ],
    "wof:name":"Tirecraft",
    "wof:placetype":"venue"
},
  "geometry": {"coordinates":[-120.231452942,55.7601242065],"type":"Point"}
}