{
  "type": "Feature",
  "properties": {
    "addr:full":"RR 7 STN Main Simcoe ON N3Y 4K6",
    "addr:postcode":"n3y 4k6",
    "addr:street":"Rr 7 Stn Main",
    "iso:country":"CA",
    "sg:address":"RR 7 STN Main",
    "sg:city":"Simcoe",
    "sg:classifiers":[
        {
            "category":"Organizations",
            "subcategory":"Religious Organization",
            "type":"Services"
        }
    ],
    "sg:phone":"+1 519 428 1853",
    "sg:postcode":"N3Y 4K6",
    "sg:province":"ON",
    "sg:tags":[
        "church"
    ],
    "wof:name":"Faith Bible Church",
    "wof:placetype":"venue"
},
  "geometry": {"coordinates":[-80.30529,42.835903],"type":"Point"}
}