{
  "type": "Feature",
  "properties": {
    "iso:country":"CA",
    "sg:address":"3 Rue DE L'Eglise Nord",
    "sg:city":"Lacolle",
    "sg:classifiers":[
        {
            "category":"Banks & Credit Unions",
            "subcategory":"Bank",
            "type":"Services"
        }
    ],
    "sg:phone":"+1 450 246 3891",
    "sg:postcode":"J0J 1J0",
    "sg:province":"QC",
    "wof:name":"Caisse Populaire DE Beaujeu",
    "wof:placetype":"venue"
},
  "geometry": {"coordinates":[-73.3729095459,45.0812911987],"type":"Point"}
}