{
  "type": "Feature",
  "properties": {
    "addr:full":"33621 Best Ave Mission BC V2V 5Z3",
    "addr:housenumber":"33621",
    "addr:postcode":"v2v 5z3",
    "addr:street":"Best Ave",
    "iso:country":"CA",
    "sg:address":"33621 Best Ave",
    "sg:city":"Mission",
    "sg:classifiers":[
        {
            "category":"Education",
            "subcategory":"School",
            "type":"Public Place"
        }
    ],
    "sg:phone":"+1 604 826 4187",
    "sg:postcode":"V2V 5Z3",
    "sg:province":"BC",
    "wof:name":"Hillside Elementary School",
    "wof:placetype":"venue"
},
  "geometry": {"coordinates":[-122.293128967,49.151096344],"type":"Point"}
}