{
  "type": "Feature",
  "properties": {
    "addr:full":"90 Concession St E Tillsonburg ON N4G 4Z8",
    "addr:housenumber":"90",
    "addr:postcode":"n4g 4z8",
    "addr:street":"Concession St",
    "iso:country":"CA",
    "sg:address":"90 Concession St E",
    "sg:city":"Tillsonburg",
    "sg:classifiers":[
        {
            "category":"Government",
            "subcategory":"Police Station",
            "type":"Public Place"
        }
    ],
    "sg:phone":"+1 519 688 6541",
    "sg:postcode":"N4G 4Z8",
    "sg:province":"ON",
    "sg:tags":[
        "department"
    ],
    "wof:name":"Tillsonburg Police Station",
    "wof:placetype":"venue"
},
  "geometry": {"coordinates":[-80.725578,42.867138],"type":"Point"}
}