{
  "type": "Feature",
  "properties": {
    "addr:full":"1145 Prince St Truro NS B2N 1J3",
    "addr:housenumber":"1145",
    "addr:postcode":"b2n 1j3",
    "addr:street":"Prince St",
    "iso:country":"CA",
    "sg:address":"1145 Prince St",
    "sg:city":"Truro",
    "sg:classifiers":[
        {
            "category":"Freight",
            "type":"Transportation"
        }
    ],
    "sg:phone":"+1 902 893 4753",
    "sg:postcode":"B2N 1J3",
    "sg:province":"NS",
    "sg:tags":[
        "commercial",
        "storage"
    ],
    "wof:name":"Unlimited Self Storage",
    "wof:placetype":"venue"
},
  "geometry": {"coordinates":[-63.28904,45.36602],"type":"Point"}
}