{
  "type": "Feature",
  "properties": {
    "addr:full":"915 Boul Saint-Joseph Roberval QC G8H 2M1",
    "addr:housenumber":"915",
    "addr:postcode":"g8h 2m1",
    "addr:street":"Boul Saint-Joseph",
    "iso:country":"CA",
    "sg:address":"915 Boul Saint-Joseph",
    "sg:city":"Roberval",
    "sg:classifiers":[
        {
            "category":"Professional",
            "subcategory":"Art Services",
            "type":"Services"
        }
    ],
    "sg:phone":"+1 418 275 3791",
    "sg:postcode":"G8H 2M1",
    "sg:province":"QC",
    "sg:tags":[
        "project",
        "management",
        "graphic",
        "designer"
    ],
    "wof:name":"Groupe Proconcept Inc",
    "wof:placetype":"venue"
},
  "geometry": {"coordinates":[-72.22156524659999,48.520160675],"type":"Point"}
}