{
  "type": "Feature",
  "properties": {
    "addr:full":"Thorsby AB T0C 2P0",
    "addr:postcode":"t0c 2p0",
    "iso:country":"CA",
    "sg:city":"Thorsby",
    "sg:classifiers":[
        {
            "category":"Organizations",
            "subcategory":"Professional Association",
            "type":"Services"
        }
    ],
    "sg:phone":"+1 780 789 3829",
    "sg:postcode":"T0C 2P0",
    "sg:province":"AB",
    "wof:name":"Thorsby Agricultural Society",
    "wof:placetype":"venue"
},
  "geometry": {"coordinates":[-114.050598145,53.2280654907],"type":"Point"}
}