{
  "type": "Feature",
  "properties": {
    "addr:full":"Waterloo ON N2L 4E7",
    "addr:postcode":"n2l 4e7",
    "iso:country":"CA",
    "sg:city":"Waterloo",
    "sg:classifiers":[
        {
            "category":"Travel",
            "subcategory":"Travel Agent",
            "type":"Entertainment"
        }
    ],
    "sg:phone":"+1 519 886 7700",
    "sg:postcode":"N2L 4E7",
    "sg:province":"ON",
    "sg:tags":[
        "agency",
        "bureau"
    ],
    "wof:name":"Worldwide Central Travel Inc",
    "wof:placetype":"venue"
},
  "geometry": {"coordinates":[-80.52855700000001,43.485222],"type":"Point"}
}