{
  "type": "Feature",
  "properties": {
    "addr:full":"Saskatoon SK S7L 5X5",
    "addr:postcode":"s7l 5x5",
    "iso:country":"CA",
    "sg:city":"Saskatoon",
    "sg:classifiers":[
        {
            "category":"Professional",
            "subcategory":"Employment Agencies",
            "type":"Services"
        }
    ],
    "sg:phone":"+1 306 244 2141",
    "sg:postcode":"S7L 5X5",
    "sg:province":"SK",
    "sg:tags":[
        "help",
        "contractor"
    ],
    "wof:name":"Saskatoon Labour Savers Inc",
    "wof:placetype":"venue"
},
  "geometry": {"coordinates":[-106.67403400000001,52.163017],"type":"Point"}
}