{
  "type": "Feature",
  "properties": {
    "iso:country":"CA",
    "sg:city":"Saskatoon",
    "sg:classifiers":[
        {
            "category":"Professional",
            "subcategory":"Employment Agencies",
            "type":"Services"
        }
    ],
    "sg:phone":"+1 306 244 2141",
    "sg:postcode":"S7L 5X5",
    "sg:province":"SK",
    "sg:tags":[
        "help",
        "contractor"
    ],
    "wof:name":"Saskatoon Labour Savers Inc",
    "wof:placetype":"venue"
},
  "geometry": {"coordinates":[-106.674034,52.163017],"type":"Point"}
}