{
  "type": "Feature",
  "properties": {
    "addr:full":"Arborg MB R0C 0A0",
    "addr:postcode":"r0c 0a0",
    "iso:country":"CA",
    "sg:city":"Arborg",
    "sg:classifiers":[
        {
            "category":"Health Services",
            "subcategory":"Optometrist",
            "type":"Services"
        }
    ],
    "sg:phone":"+1 204 376 5566",
    "sg:postcode":"R0C 0A0",
    "sg:province":"MB",
    "wof:name":"Oakley Vision Ctr",
    "wof:placetype":"venue"
},
  "geometry": {"coordinates":[-97.2188796997,50.9064788818],"type":"Point"}
}