{
  "type": "Feature",
  "properties": {
    "addr:full":"167 Chaffey Township Rd Huntsville ON P1H 1C8",
    "addr:housenumber":"167",
    "addr:postcode":"p1h 1c8",
    "addr:street":"Chaffey Township Rd",
    "iso:country":"CA",
    "sg:address":"167 Chaffey Township Rd",
    "sg:city":"Huntsville",
    "sg:classifiers":[
        {
            "category":"Building & Trades",
            "subcategory":"Landscaping Services",
            "type":"Services"
        }
    ],
    "sg:phone":"+1 705 788 1283",
    "sg:postcode":"P1H 1C8",
    "sg:province":"ON",
    "sg:tags":[
        "landscape",
        "contractor"
    ],
    "wof:name":"D B Maw Landscaping",
    "wof:placetype":"venue"
},
  "geometry": {"coordinates":[-79.19467899999999,45.346142],"type":"Point"}
}