{
  "type": "Feature",
  "properties": {
    "addr:full":"1740 Boul Des Forges Trois-Rivieres QC G9A 5H3",
    "addr:housenumber":"1740",
    "addr:postcode":"g9a 5h3",
    "addr:street":"Boul Des Forges Trois-Rivieres",
    "iso:country":"CA",
    "sg:address":"1740 Boul Des Forges",
    "sg:city":"Trois-Rivieres",
    "sg:classifiers":[
        {
            "category":"Organizations",
            "subcategory":"Professional Association",
            "type":"Services"
        }
    ],
    "sg:phone":"+1 819 376 2464",
    "sg:postcode":"G9A 5H3",
    "sg:province":"QC",
    "wof:name":"Club DE Natation Megophias",
    "wof:placetype":"venue"
},
  "geometry": {"coordinates":[-72.5613479614,46.3454284668],"type":"Point"}
}