{
  "type": "Feature",
  "properties": {
    "addr:full":"6172 Rue Villeneuve Montreal-Nord QC H1G 1M3",
    "addr:housenumber":"6172",
    "addr:postcode":"h1g 1m3",
    "addr:street":"Rue Villeneuve",
    "iso:country":"CA",
    "sg:address":"6172 Rue Villeneuve",
    "sg:city":"Montreal-Nord",
    "sg:classifiers":[
        {
            "category":"Banks & Credit Unions",
            "subcategory":"Investment Brokerage",
            "type":"Services"
        }
    ],
    "sg:phone":"+1 514 721 5599",
    "sg:postcode":"H1G 1M3",
    "sg:province":"QC",
    "sg:tags":[
        "consultant",
        "financing"
    ],
    "wof:name":"Quoi Faire",
    "wof:placetype":"venue"
},
  "geometry": {"coordinates":[-73.625107,45.619789],"type":"Point"}
}