{
  "type": "Feature",
  "properties": {
    "addr:full":"St Catharines ON L2R 3H5",
    "addr:postcode":"l2r 3h5",
    "iso:country":"CA",
    "sg:city":"St Catharines",
    "sg:classifiers":[
        {
            "category":"Professional",
            "subcategory":"Lawyer & Legal Services",
            "type":"Services"
        }
    ],
    "sg:phone":"+1 905 641 1900",
    "sg:postcode":"L2R 3H5",
    "sg:province":"ON",
    "sg:tags":[
        "attorney"
    ],
    "wof:name":"Stewart, Mark",
    "wof:placetype":"venue"
},
  "geometry": {"coordinates":[-79.2467803955,43.1578445435],"type":"Point"}
}