{
  "type": "Feature",
  "properties": {
    "addr:full":"Red Deer AB T4P 1X6",
    "addr:postcode":"t4p 1x6",
    "iso:country":"CA",
    "sg:city":"Red Deer",
    "sg:classifiers":[
        {
            "category":"Retail",
            "subcategory":"Auto Repair",
            "type":"Services"
        }
    ],
    "sg:phone":"+1 403 343 0092",
    "sg:postcode":"T4P 1X6",
    "sg:province":"AB",
    "sg:tags":[
        "body",
        "automobile",
        "painting"
    ],
    "wof:name":"First Choice Collision & Frame",
    "wof:placetype":"venue"
},
  "geometry": {"coordinates":[-113.80935669,52.3033103943],"type":"Point"}
}