{
  "type": "Feature",
  "properties": {
    "addr:full":"17028 90 Ave NW Edmonton AB T5T 1L6",
    "addr:housenumber":"17028",
    "addr:postcode":"t5t 1l6",
    "addr:street":"90 Ave Nw",
    "iso:country":"CA",
    "sg:address":"17028 90 Ave NW",
    "sg:city":"Edmonton",
    "sg:classifiers":[
        {
            "category":"Health Services",
            "subcategory":"Doctor",
            "type":"Services"
        }
    ],
    "sg:phone":"+1 780 444 6484",
    "sg:postcode":"T5T 1L6",
    "sg:province":"AB",
    "sg:tags":[
        "dentist"
    ],
    "wof:name":"Westgate Dental Clinic",
    "wof:placetype":"venue"
},
  "geometry": {"coordinates":[-113.61599,53.524986],"type":"Point"}
}