{
  "type": "Feature",
  "properties": {
    "iso:country":"CA",
    "sg:address":"841 Ouellette Ave",
    "sg:city":"Windsor",
    "sg:classifiers":[
        {
            "category":"Restaurant",
            "type":"Food & Drink"
        }
    ],
    "sg:phone":"+1 519 258 2804",
    "sg:postcode":"N9A 4J5",
    "sg:province":"ON",
    "wof:name":"Himalaya Dining Room",
    "wof:placetype":"venue"
},
  "geometry": {"coordinates":[-83.0350189209,42.3109588623],"type":"Point"}
}