{
  "type": "Feature",
  "properties": {
    "addr:full":"Calgary AB T2P 1N3",
    "addr:postcode":"t2p 1n3",
    "iso:country":"CA",
    "sg:city":"Calgary",
    "sg:classifiers":[
        {
            "category":"Professional",
            "subcategory":"Research",
            "type":"Services"
        }
    ],
    "sg:phone":"+1 403 263 6600",
    "sg:postcode":"T2P 1N3",
    "sg:province":"AB",
    "sg:tags":[
        "environmental",
        "ecological",
        "oil",
        "gas",
        "consultant"
    ],
    "wof:name":"Dyad Engineering Inc",
    "wof:placetype":"venue"
},
  "geometry": {"coordinates":[-114.065712,51.045399],"type":"Point"}
}