{
  "type": "Feature",
  "properties": {
    "addr:full":"6602 Hwy 35 Coboconk ON K0M 1K0",
    "addr:housenumber":"6602",
    "addr:postcode":"k0m 1k0",
    "addr:street":"Hwy 35",
    "iso:country":"CA",
    "sg:address":"6602 Hwy 35",
    "sg:city":"Coboconk",
    "sg:classifiers":[
        {
            "category":"Retail",
            "subcategory":"Auto Repair",
            "type":"Services"
        }
    ],
    "sg:phone":"+1 705 454 3962",
    "sg:postcode":"K0M 1K0",
    "sg:province":"ON",
    "sg:tags":[
        "repairing",
        "automobile"
    ],
    "wof:name":"Kawartha Garage Ltd",
    "wof:placetype":"venue"
},
  "geometry": {"coordinates":[-78.795502,44.653667],"type":"Point"}
}