{
  "type": "Feature",
  "properties": {
    "addr:full":"25 Taber Rd Etobicoke ON M9W 3A7",
    "addr:housenumber":"25",
    "addr:postcode":"m9w 3a7",
    "addr:street":"Taber Rd",
    "iso:country":"CA",
    "sg:address":"25 Taber Rd",
    "sg:city":"Etobicoke",
    "sg:classifiers":[
        {
            "category":"Building & Trades",
            "subcategory":"Construction",
            "type":"Services"
        }
    ],
    "sg:phone":"+1 416 743 3162",
    "sg:postcode":"M9W 3A7",
    "sg:province":"ON",
    "sg:tags":[
        "excavating",
        "contractor"
    ],
    "wof:name":"Regina Construction Ltd",
    "wof:placetype":"venue"
},
  "geometry": {"coordinates":[-79.574883,43.718678],"type":"Point"}
}