{
  "type": "Feature",
  "properties": {
    "addr:full":"Saint-Louis-DE-France QC G8T 1G1",
    "addr:postcode":"g8t 1g1",
    "iso:country":"CA",
    "sg:city":"Saint-Louis-DE-France",
    "sg:classifiers":[
        {
            "category":"Bars & Pubs",
            "type":"Food & Drink"
        }
    ],
    "sg:phone":"+1 819 373 1789",
    "sg:postcode":"G8T 1G1",
    "sg:province":"QC",
    "sg:tags":[
        "lounge",
        "cocktail"
    ],
    "wof:name":"Chalet Du Sportif",
    "wof:placetype":"venue"
},
  "geometry": {"coordinates":[-72.58796700000001,46.418964],"type":"Point"}
}