{
  "type": "Feature",
  "properties": {
    "addr:full":"Repentigny QC J6A 2P7",
    "addr:postcode":"j6a 2p7",
    "iso:country":"CA",
    "sg:city":"Repentigny",
    "sg:classifiers":[
        {
            "category":"Shopping",
            "subcategory":"Clothing, Apparel, & Fashions",
            "type":"Retail Goods"
        }
    ],
    "sg:phone":"+1 450 657 0092",
    "sg:postcode":"J6A 2P7",
    "sg:province":"QC",
    "wof:name":"Boutique Erotique Fantasme",
    "wof:placetype":"venue"
},
  "geometry": {"coordinates":[-73.46849060060001,45.7182121277],"type":"Point"}
}