{
  "type": "Feature",
  "properties": {
    "addr:full":"89 Newkirk Rd Richmond Hill ON L4C 2C6",
    "addr:housenumber":"89",
    "addr:postcode":"l4c 2c6",
    "addr:street":"Newkirk Rd",
    "iso:country":"CA",
    "sg:address":"89 Newkirk Rd",
    "sg:city":"Richmond Hill",
    "sg:classifiers":[
        {
            "category":"Retail",
            "subcategory":"Auto Repair",
            "type":"Services"
        }
    ],
    "sg:phone":"+1 905 780 9254",
    "sg:postcode":"L4C 2C6",
    "sg:province":"ON",
    "sg:tags":[
        "body",
        "automobile",
        "painting"
    ],
    "wof:name":"Forest Hill North Auto Cllsn",
    "wof:placetype":"venue"
},
  "geometry": {"coordinates":[-79.427757,43.881046],"type":"Point"}
}