{
  "type": "Feature",
  "properties": {
    "addr:full":"7037 Randolph Ave Burnaby BC V5J 4W5",
    "addr:housenumber":"7037",
    "addr:postcode":"v5j 4w5",
    "addr:street":"Randolph Ave",
    "iso:country":"CA",
    "sg:address":"7037 Randolph Ave",
    "sg:city":"Burnaby",
    "sg:classifiers":[
        {
            "category":"Retail",
            "subcategory":"Auto Repair",
            "type":"Services"
        }
    ],
    "sg:phone":"+1 604 435 9797",
    "sg:postcode":"V5J 4W5",
    "sg:province":"BC",
    "sg:tags":[
        "body",
        "automobile",
        "painting"
    ],
    "wof:name":"Eddy's Auto Body Repair",
    "wof:placetype":"venue"
},
  "geometry": {"coordinates":[-122.973618,49.219723],"type":"Point"}
}