{
  "type": "Feature",
  "properties": {
    "iso:country":"CA",
    "sg:address":"1916 Ch Gascon",
    "sg:city":"Terrebonne",
    "sg:classifiers":[
        {
            "category":"Autos & Motor Vehicles",
            "subcategory":"Auto Supplies",
            "type":"Retail Goods"
        }
    ],
    "sg:phone":"+1 450 492 0141",
    "sg:postcode":"J6X 2E4",
    "sg:province":"QC",
    "sg:tags":[
        "equipment",
        "racing",
        "car",
        "automobile"
    ],
    "wof:name":"Para Performance",
    "wof:placetype":"venue"
},
  "geometry": {"coordinates":[-73.658195,45.719128],"type":"Point"}
}