{
  "type": "Feature",
  "properties": {
    "addr:full":"Mount Hope ON L0R 1W0",
    "addr:postcode":"l0r 1w0",
    "iso:country":"CA",
    "sg:city":"Mount Hope",
    "sg:classifiers":[
        {
            "category":"Retail",
            "subcategory":"Auto Rental",
            "type":"Services"
        }
    ],
    "sg:phone":"+1 905 679 3290",
    "sg:postcode":"L0R 1W0",
    "sg:province":"ON",
    "sg:tags":[
        "renting",
        "automobile"
    ],
    "wof:name":"Hertz Rent A Car",
    "wof:placetype":"venue"
},
  "geometry": {"coordinates":[-79.92841339109999,43.1596755981],"type":"Point"}
}