{
  "type": "Feature",
  "properties": {
    "iso:country":"CA",
    "sg:address":"2953 Olinda Side Rd",
    "sg:city":"Ruthven",
    "sg:classifiers":[
        {
            "category":"Organizations",
            "subcategory":"Religious Organization",
            "type":"Services"
        }
    ],
    "sg:phone":"+1 519 326 4352",
    "sg:postcode":"N0P 2G0",
    "sg:province":"ON",
    "sg:tags":[
        "church"
    ],
    "wof:name":"Unitarian Universalist Church",
    "wof:placetype":"venue"
},
  "geometry": {"coordinates":[-82.6720199585,42.0519142151],"type":"Point"}
}