{
  "type": "Feature",
  "properties": {
    "addr:full":"55 Torbay Rd Markham ON L3R 1G7",
    "addr:housenumber":"55",
    "addr:postcode":"l3r 1g7",
    "addr:street":"Torbay Rd",
    "iso:country":"CA",
    "sg:address":"55 Torbay Rd",
    "sg:city":"Markham",
    "sg:classifiers":[
        {
            "category":"Professional",
            "subcategory":"Management & Consulting",
            "type":"Services"
        }
    ],
    "sg:phone":"+1 905 477 7767",
    "sg:postcode":"L3R 1G7",
    "sg:province":"ON",
    "sg:tags":[
        "promotion",
        "sales"
    ],
    "wof:name":"Sales Solutions Group Inc",
    "wof:placetype":"venue"
},
  "geometry": {"coordinates":[-79.3464355469,43.8190917969],"type":"Point"}
}