{
  "type": "Feature",
  "properties": {
    "addr:full":"406 Gastle St Strasbourg SK S0G 4V0",
    "addr:housenumber":"406",
    "addr:postcode":"s0g 4v0",
    "addr:street":"Gastle St",
    "iso:country":"CA",
    "sg:address":"406 Gastle St",
    "sg:city":"Strasbourg",
    "sg:classifiers":[
        {
            "category":"Retail",
            "subcategory":"Funeral Services",
            "type":"Services"
        }
    ],
    "sg:phone":"+1 306 725 3633",
    "sg:postcode":"S0G 4V0",
    "sg:province":"SK",
    "sg:tags":[
        "director",
        "ambulance"
    ],
    "wof:name":"Hansen's Funeral Home",
    "wof:placetype":"venue"
},
  "geometry": {"coordinates":[-104.959869385,51.070980072],"type":"Point"}
}