{
  "type": "Feature",
  "properties": {
    "addr:full":"131 Main St Milo AB T0L 1L0",
    "addr:housenumber":"131",
    "addr:postcode":"t0l 1l0",
    "addr:street":"Main St",
    "iso:country":"CA",
    "sg:address":"131 Main St",
    "sg:city":"Milo",
    "sg:classifiers":[
        {
            "category":"Travel",
            "subcategory":"Hotels & Motels",
            "type":"Entertainment"
        }
    ],
    "sg:phone":"+1 403 599 3853",
    "sg:postcode":"T0L 1L0",
    "sg:province":"AB",
    "wof:name":"Milo Hotel",
    "wof:placetype":"venue"
},
  "geometry": {"coordinates":[-112.884040833,50.5721702576],"type":"Point"}
}