{
  "type": "Feature",
  "properties": {
    "iso:country":"CA",
    "sg:address":"600 Av Belvedere",
    "sg:city":"Quebec",
    "sg:classifiers":[
        {
            "category":"Manufacturing",
            "subcategory":"Printing",
            "type":"Manufacturing & Wholesale Goods"
        }
    ],
    "sg:phone":"+1 418 688 0455",
    "sg:postcode":"G1S 3E5",
    "sg:province":"QC",
    "sg:tags":[
        "engraver"
    ],
    "wof:name":"Girafe & Assoc",
    "wof:placetype":"venue"
},
  "geometry": {"coordinates":[-71.244484,46.801285],"type":"Point"}
}