{
  "type": "Feature",
  "properties": {
    "addr:full":"Didsbury AB T0M 0W0",
    "addr:postcode":"t0m 0w0",
    "iso:country":"CA",
    "sg:city":"Didsbury",
    "sg:classifiers":[
        {
            "category":"Professional",
            "subcategory":"Lawyer & Legal Services",
            "type":"Services"
        }
    ],
    "sg:phone":"+1 403 335 3347",
    "sg:postcode":"T0M 0W0",
    "sg:province":"AB",
    "sg:tags":[
        "attorney"
    ],
    "wof:name":"Good, Vernon E",
    "wof:placetype":"venue"
},
  "geometry": {"coordinates":[-114.138397217,51.66015625],"type":"Point"}
}