{
  "type": "Feature",
  "properties": {
    "addr:full":"Kent Bridge ON N0P 1V0",
    "addr:postcode":"n0p 1v0",
    "iso:country":"CA",
    "sg:city":"Kent Bridge",
    "sg:classifiers":[
        {
            "category":"Shopping",
            "subcategory":"Crafts & Fabrics",
            "type":"Retail Goods"
        }
    ],
    "sg:phone":"+1 519 674 5733",
    "sg:postcode":"N0P 1V0",
    "sg:province":"ON",
    "sg:tags":[
        "shop"
    ],
    "wof:name":"Mc Kays Corners Surplus Ctr",
    "wof:placetype":"venue"
},
  "geometry": {"coordinates":[-82.07303619379999,42.5150604248],"type":"Point"}
}