{
  "type": "Feature",
  "properties": {
    "addr:full":"8902 168 St NW Edmonton AB T5R 2V5",
    "addr:housenumber":"8902",
    "addr:postcode":"t5r 2v5",
    "addr:street":"168 St Nw",
    "iso:country":"CA",
    "sg:address":"8902 168 St NW",
    "sg:city":"Edmonton",
    "sg:classifiers":[
        {
            "category":"Organizations",
            "subcategory":"Religious Organization",
            "type":"Services"
        }
    ],
    "sg:phone":"+1 780 489 7218",
    "sg:postcode":"T5R 2V5",
    "sg:province":"AB",
    "sg:tags":[
        "church"
    ],
    "wof:name":"Edmonton Ev Mennonite Church",
    "wof:placetype":"venue"
},
  "geometry": {"coordinates":[-113.61273199999999,53.524548],"type":"Point"}
}