{
  "type": "Feature",
  "properties": {
    "addr:full":"145 1st Ave NE Swift Current SK S9H 2B1",
    "addr:housenumber":"145",
    "addr:postcode":"s9h 2b1",
    "addr:street":"1St Ave Ne",
    "iso:country":"CA",
    "sg:address":"145 1st Ave NE",
    "sg:city":"Swift Current",
    "sg:classifiers":[
        {
            "category":"Professional",
            "subcategory":"Accounting & Tax Preparation",
            "type":"Services"
        }
    ],
    "sg:phone":"+1 306 773 7285",
    "sg:postcode":"S9H 2B1",
    "sg:province":"SK",
    "sg:tags":[
        "accountant"
    ],
    "wof:name":"Stark & Marsh",
    "wof:placetype":"venue"
},
  "geometry": {"coordinates":[-107.79843099999999,50.284229],"type":"Point"}
}