{
  "type": "Feature",
  "properties": {
    "addr:full":"296 Rue Guertin Disraeli QC G0N 1E0",
    "addr:housenumber":"296",
    "addr:postcode":"g0n 1e0",
    "addr:street":"Rue Guertin Disraeli",
    "iso:country":"CA",
    "sg:address":"296 Rue Guertin",
    "sg:city":"Disraeli",
    "sg:classifiers":[
        {
            "category":"Organizations",
            "subcategory":"Professional Association",
            "type":"Services"
        }
    ],
    "sg:phone":"+1 418 449 2849",
    "sg:postcode":"G0N 1E0",
    "sg:province":"QC",
    "wof:name":"Chevaliers DE Colomb",
    "wof:placetype":"venue"
},
  "geometry": {"coordinates":[-71.357338,45.898399],"type":"Point"}
}