{
  "type": "Feature",
  "properties": {
    "addr:full":"1123 4th St Estevan SK S4A 0W6",
    "addr:housenumber":"1123",
    "addr:postcode":"s4a 0w6",
    "addr:street":"4Th St",
    "iso:country":"CA",
    "sg:address":"1123 4th St",
    "sg:city":"Estevan",
    "sg:classifiers":[
        {
            "category":"Shopping",
            "subcategory":"Florist",
            "type":"Retail Goods"
        }
    ],
    "sg:phone":"+1 306 634 4701",
    "sg:postcode":"S4A 0W6",
    "sg:province":"SK",
    "wof:name":"Estevan Florist-Gift Shoppe",
    "wof:placetype":"venue"
},
  "geometry": {"coordinates":[-102.993347,49.139999],"type":"Point"}
}