{
  "type": "Feature",
  "properties": {
    "addr:full":"511 Highway 3 Cayuga ON N0A 1E0",
    "addr:housenumber":"511",
    "addr:postcode":"n0a 1e0",
    "addr:street":"Highway 3",
    "iso:country":"CA",
    "sg:address":"511 Highway 3",
    "sg:city":"Cayuga",
    "sg:classifiers":[
        {
            "category":"Building & Trades",
            "subcategory":"Construction",
            "type":"Services"
        }
    ],
    "sg:phone":"+1 905 772 3331",
    "sg:postcode":"N0A 1E0",
    "sg:province":"ON",
    "sg:tags":[
        "product",
        "stone",
        "asphalt"
    ],
    "wof:name":"Cayuga Materials & Constr CO",
    "wof:placetype":"venue"
},
  "geometry": {"coordinates":[-79.85507200000001,42.9505],"type":"Point"}
}