{
  "type": "Feature",
  "properties": {
    "addr:full":"166 Rue DE Notre-Dame-Des-Vict Sainte-Foy QC G2G 1J2",
    "addr:housenumber":"166",
    "addr:postcode":"g2g 1j2",
    "addr:street":"Rue De Notre-Dame-Des-Vict",
    "iso:country":"CA",
    "sg:address":"166 Rue DE Notre-Dame-Des-Vict",
    "sg:city":"Sainte-Foy",
    "sg:classifiers":[
        {
            "category":"Professional",
            "subcategory":"Business Services",
            "type":"Services"
        }
    ],
    "sg:phone":"+1 418 872 3689",
    "sg:postcode":"G2G 1J2",
    "sg:province":"QC",
    "sg:tags":[
        "notary"
    ],
    "wof:name":"Aid Marketing",
    "wof:placetype":"venue"
},
  "geometry": {"coordinates":[-71.38249999999999,46.767056],"type":"Point"}
}