{
  "type": "Feature",
  "properties": {
    "iso:country":"CA",
    "sg:address":"14839 108 Ave",
    "sg:city":"Surrey",
    "sg:classifiers":[
        {
            "category":"Restaurant",
            "type":"Food & Drink"
        }
    ],
    "sg:phone":"+1 604 930 2949",
    "sg:postcode":"V3R 1W2",
    "sg:province":"BC",
    "sg:tags":[
        "shop",
        "coffee"
    ],
    "wof:name":"Expresso Shack",
    "wof:placetype":"venue"
},
  "geometry": {"coordinates":[-122.811309815,49.1988754272],"type":"Point"}
}