{
  "type": "Feature",
  "properties": {
    "addr:full":"731 Goldstream Ave Victoria BC V9B 2X4",
    "addr:housenumber":"731",
    "addr:postcode":"v9b 2x4",
    "addr:street":"Goldstream Ave",
    "iso:country":"CA",
    "sg:address":"731 Goldstream Ave",
    "sg:city":"Victoria",
    "sg:classifiers":[
        {
            "category":"Restaurant",
            "type":"Food & Drink"
        }
    ],
    "sg:phone":"+1 250 478 1533",
    "sg:postcode":"V9B 2X4",
    "sg:province":"BC",
    "wof:name":"Kfc",
    "wof:placetype":"venue"
},
  "geometry": {"coordinates":[-123.364517212,48.428314209],"type":"Point"}
}