{
  "type": "Feature",
  "properties": {
    "addr:full":"650 Rue Loyola Saint-Jean-Sur-Richelieu QC J3B 6A1",
    "addr:housenumber":"650",
    "addr:postcode":"j3b 6a1",
    "addr:street":"Rue Loyola",
    "iso:country":"CA",
    "sg:address":"650 Rue Loyola",
    "sg:city":"Saint-Jean-Sur-Richelieu",
    "sg:classifiers":[
        {
            "category":"Wholesale",
            "subcategory":"Electrical",
            "type":"Manufacturing & Wholesale Goods"
        }
    ],
    "sg:phone":"+1 450 348 3126",
    "sg:postcode":"J3B 6A1",
    "sg:province":"QC",
    "sg:tags":[
        "equipment",
        "electric",
        "supply"
    ],
    "wof:name":"Pirelli Cables Inc",
    "wof:placetype":"venue"
},
  "geometry": {"coordinates":[-73.263245,45.319626],"type":"Point"}
}