{
  "type": "Feature",
  "properties": {
    "addr:full":"Vancouver BC V6C 1Z7",
    "addr:postcode":"v6c 1z7",
    "iso:country":"CA",
    "sg:city":"Vancouver",
    "sg:classifiers":[
        {
            "category":"Freight",
            "type":"Transportation"
        }
    ],
    "sg:phone":"+1 604 899 5447",
    "sg:postcode":"V6C 1Z7",
    "sg:province":"BC",
    "sg:tags":[
        "courier"
    ],
    "wof:name":"Phantom Couriers",
    "wof:placetype":"venue"
},
  "geometry": {"coordinates":[-123.11416626,49.2865257263],"type":"Point"}
}