{
  "type": "Feature",
  "properties": {
    "addr:full":"1225 Franklin Blvd Cambridge ON N1R 7E5",
    "addr:housenumber":"1225",
    "addr:postcode":"n1r 7e5",
    "addr:street":"Franklin Blvd",
    "iso:country":"CA",
    "sg:address":"1225 Franklin Blvd",
    "sg:city":"Cambridge",
    "sg:classifiers":[
        {
            "category":"Utilities",
            "subcategory":"Refuse",
            "type":"Services"
        }
    ],
    "sg:phone":"+1 519 740 6801",
    "sg:postcode":"N1R 7E5",
    "sg:province":"ON",
    "sg:tags":[
        "equipment",
        "recycling",
        "system"
    ],
    "wof:name":"Recovery Technologies Inc",
    "wof:placetype":"venue"
},
  "geometry": {"coordinates":[-80.307106,43.407406],"type":"Point"}
}