{
  "type": "Feature",
  "properties": {
    "addr:full":"11120 100 78 St Edmonton AB T5S 1P2",
    "addr:housenumber":"11120;78",
    "addr:postcode":"t5s 1p2",
    "addr:street":"100",
    "iso:country":"CA",
    "sg:address":"11120 100 78 St",
    "sg:city":"Edmonton",
    "sg:classifiers":[
        {
            "category":"Insurance",
            "subcategory":"Insurance Agent",
            "type":"Services"
        }
    ],
    "sg:phone":"+1 403 262 4141",
    "sg:postcode":"T5S 1P2",
    "sg:province":"AB",
    "wof:name":"Morgex Insurance Group",
    "wof:placetype":"venue"
},
  "geometry": {"coordinates":[-113.46157836899999,53.5602111816],"type":"Point"}
}