{
  "type": "Feature",
  "properties": {
    "addr:full":"264 Adelaide St E Toronto ON M5A 1N1",
    "addr:housenumber":"264",
    "addr:postcode":"m5a 1n1",
    "addr:street":"Adelaide St E",
    "iso:country":"CA",
    "sg:address":"264 Adelaide St E",
    "sg:city":"Toronto",
    "sg:classifiers":[
        {
            "category":"Professional",
            "subcategory":"Management & Consulting",
            "type":"Services"
        }
    ],
    "sg:phone":"+1 416 861 9880",
    "sg:postcode":"M5A 1N1",
    "sg:province":"ON",
    "sg:tags":[
        "marketing",
        "consultant",
        "market",
        "analysis",
        "research"
    ],
    "wof:name":"Longwoods International",
    "wof:placetype":"venue"
},
  "geometry": {"coordinates":[-79.370728,43.651802],"type":"Point"}
}