{
  "type": "Feature",
  "properties": {
    "addr:full":"160 Talbot St E Leamington ON N8H 1M2",
    "addr:housenumber":"160",
    "addr:postcode":"n8h 1m2",
    "addr:street":"Talbot St E",
    "iso:country":"CA",
    "sg:address":"160 Talbot St E",
    "sg:city":"Leamington",
    "sg:classifiers":[
        {
            "category":"Social Services",
            "type":"Services"
        }
    ],
    "sg:phone":"+1 519 326 2521",
    "sg:postcode":"N8H 1M2",
    "sg:province":"ON",
    "sg:tags":[
        "club",
        "senior",
        "citizen"
    ],
    "wof:name":"Half Century Club",
    "wof:placetype":"venue"
},
  "geometry": {"coordinates":[-82.59189600000001,42.054886],"type":"Point"}
}