{
  "type": "Feature",
  "properties": {
    "addr:full":"1959 Tecumseh Rd W Windsor ON N9B 1V7",
    "addr:housenumber":"1959",
    "addr:postcode":"n9b 1v7",
    "addr:street":"Tecumseh Rd W",
    "iso:country":"CA",
    "sg:address":"1959 Tecumseh Rd W",
    "sg:city":"Windsor",
    "sg:classifiers":[
        {
            "category":"Restaurant",
            "type":"Food & Drink"
        }
    ],
    "sg:phone":"+1 519 252 5669",
    "sg:postcode":"N9B 1V7",
    "sg:province":"ON",
    "wof:name":"Hong Chow Restaurant",
    "wof:placetype":"venue"
},
  "geometry": {"coordinates":[-83.05080413819999,42.2938156128],"type":"Point"}
}