{
  "type": "Feature",
  "properties": {
    "addr:full":"Mississauga ON L4T 3W4",
    "addr:postcode":"l4t 3w4",
    "iso:country":"CA",
    "sg:city":"Mississauga",
    "sg:classifiers":[
        {
            "category":"Manufacturing",
            "subcategory":"Furniture",
            "type":"Manufacturing & Wholesale Goods"
        }
    ],
    "sg:phone":"+1 905 677 5603",
    "sg:postcode":"L4T 3W4",
    "sg:province":"ON",
    "sg:tags":[
        "fixture",
        "store"
    ],
    "wof:name":"Ital Store Fixtures Ltd",
    "wof:placetype":"venue"
},
  "geometry": {"coordinates":[-79.65776824949999,43.6981048584],"type":"Point"}
}