{
  "type": "Feature",
  "properties": {
    "iso:country":"CA",
    "sg:address":"SW 22 7 14E",
    "sg:city":"East Braintree",
    "sg:classifiers":[
        {
            "category":"Freight",
            "type":"Transportation"
        }
    ],
    "sg:phone":"+1 204 426 2156",
    "sg:postcode":"R0E 0L0",
    "sg:province":"MB",
    "sg:tags":[
        "car",
        "pilot"
    ],
    "wof:name":"R Karalash Enterprises",
    "wof:placetype":"venue"
},
  "geometry": {"coordinates":[-95.6244812012,49.6283454895],"type":"Point"}
}