{
  "type": "Feature",
  "properties": {
    "addr:full":"426 Queen St W Toronto ON M5V 2A7",
    "addr:housenumber":"426",
    "addr:postcode":"m5v 2a7",
    "addr:street":"Queen St W",
    "iso:country":"CA",
    "sg:address":"426 Queen St W",
    "sg:city":"Toronto",
    "sg:classifiers":[
        {
            "category":"Personal",
            "subcategory":"Beauty Salon",
            "type":"Services"
        }
    ],
    "sg:phone":"+1 416 703 0240",
    "sg:postcode":"M5V 2A7",
    "sg:province":"ON",
    "wof:name":"Image Make Over",
    "wof:placetype":"venue"
},
  "geometry": {"coordinates":[-79.398048,43.648441],"type":"Point"}
}