{
  "type": "Feature",
  "properties": {
    "addr:full":"291 Selkirk Ave Winnipeg MB R2W 2L8",
    "addr:housenumber":"291",
    "addr:postcode":"r2w 2l8",
    "addr:street":"Selkirk Ave",
    "iso:country":"CA",
    "sg:address":"291 Selkirk Ave",
    "sg:city":"Winnipeg",
    "sg:classifiers":[
        {
            "category":"Food & Beverages",
            "subcategory":"Groceries & Convenience Stores",
            "type":"Retail Goods"
        }
    ],
    "sg:phone":"+1 204 582 2249",
    "sg:postcode":"R2W 2L8",
    "sg:province":"MB",
    "sg:tags":[
        "grocer"
    ],
    "wof:name":"Charles Lucky Dollar Food",
    "wof:placetype":"venue"
},
  "geometry": {"coordinates":[-97.136421,49.913036],"type":"Point"}
}