{
  "type": "Feature",
  "properties": {
    "iso:country":"CA",
    "sg:address":"7600 Boul Henri-Bourassa O",
    "sg:city":"Saint-Laurent",
    "sg:classifiers":[
        {
            "category":"Shopping",
            "type":"Retail Goods"
        }
    ],
    "sg:phone":"+1 514 745 0200",
    "sg:postcode":"H4S 1W3",
    "sg:province":"QC",
    "sg:tags":[
        "chemical"
    ],
    "wof:name":"Protech Chemicals Ltd",
    "wof:placetype":"venue"
},
  "geometry": {"coordinates":[-73.73877,45.506374],"type":"Point"}
}