{
  "type": "Feature",
  "properties": {
    "addr:full":"1740 Boul Lionel-Bertrand Boisbriand QC J7H 1N7",
    "addr:housenumber":"1740",
    "addr:postcode":"j7h 1n7",
    "addr:street":"Boul Lionel-Bertrand",
    "iso:country":"CA",
    "sg:address":"1740 Boul Lionel-Bertrand",
    "sg:city":"Boisbriand",
    "sg:classifiers":[
        {
            "category":"Manufacturing",
            "subcategory":"Tools & Machinery",
            "type":"Manufacturing & Wholesale Goods"
        }
    ],
    "sg:phone":"+1 450 435 6899",
    "sg:postcode":"J7H 1N7",
    "sg:province":"QC",
    "sg:tags":[
        "equipment",
        "system",
        "vacuum"
    ],
    "wof:name":"Busch Vacuum Technics Inc",
    "wof:placetype":"venue"
},
  "geometry": {"coordinates":[-73.85264599999999,45.616009],"type":"Point"}
}