{
  "type": "Feature",
  "properties": {
    "addr:full":"Calgary AB T2S 2S4",
    "addr:postcode":"t2s 2s4",
    "iso:country":"CA",
    "sg:city":"Calgary",
    "sg:classifiers":[
        {
            "category":"Health Services",
            "subcategory":"Chiropractor",
            "type":"Services"
        }
    ],
    "sg:phone":"+1 403 209 2225",
    "sg:postcode":"T2S 2S4",
    "sg:province":"AB",
    "wof:name":"Back & Body Health",
    "wof:placetype":"venue"
},
  "geometry": {"coordinates":[-114.071411,51.036865],"type":"Point"}
}