{
  "type": "Feature",
  "properties": {
    "addr:full":"259 Queen St W Toronto ON M5V 1Z4",
    "addr:housenumber":"259",
    "addr:postcode":"m5v 1z4",
    "addr:street":"Queen St W",
    "iso:country":"CA",
    "sg:address":"259 Queen St W",
    "sg:city":"Toronto",
    "sg:classifiers":[
        {
            "category":"Shopping",
            "subcategory":"Computers & Home Electronics",
            "type":"Retail Goods"
        }
    ],
    "sg:phone":"+1 416 597 1097",
    "sg:postcode":"M5V 1Z4",
    "sg:province":"ON",
    "sg:tags":[
        "television",
        "radio"
    ],
    "wof:name":"Global Electronic CO",
    "wof:placetype":"venue"
},
  "geometry": {"coordinates":[-79.389053,43.650169],"type":"Point"}
}