{
  "type": "Feature",
  "properties": {
    "addr:full":"1955 Lasalle Blvd Sudbury ON P3A 2A3",
    "addr:housenumber":"1955",
    "addr:postcode":"p3a 2a3",
    "addr:street":"Lasalle Blvd",
    "iso:country":"CA",
    "sg:address":"1955 Lasalle Blvd",
    "sg:city":"Sudbury",
    "sg:classifiers":[
        {
            "category":"Restaurant",
            "type":"Food & Drink"
        }
    ],
    "sg:phone":"+1 705 566 6969",
    "sg:postcode":"P3A 2A3",
    "sg:province":"ON",
    "sg:tags":[
        "pizza"
    ],
    "wof:name":"Great Lakes Pizza CO",
    "wof:placetype":"venue"
},
  "geometry": {"coordinates":[-80.92617797849999,46.5219116211],"type":"Point"}
}