{
  "type": "Feature",
  "properties": {
    "addr:full":"East Broughton QC G0N 1G0",
    "addr:postcode":"g0n 1g0",
    "iso:country":"CA",
    "sg:city":"East Broughton",
    "sg:classifiers":[
        {
            "category":"Professional",
            "subcategory":"Employment Agencies",
            "type":"Services"
        }
    ],
    "sg:phone":"+1 418 427 5594",
    "sg:postcode":"G0N 1G0",
    "sg:province":"QC",
    "sg:tags":[
        "opportunity"
    ],
    "wof:name":"Classe 1 Inc",
    "wof:placetype":"venue"
},
  "geometry": {"coordinates":[-71.0785522461,46.2201576233],"type":"Point"}
}