{
  "type": "Feature",
  "properties": {
    "iso:country":"CA",
    "sg:city":"Morden",
    "sg:classifiers":[
        {
            "category":"Government",
            "subcategory":"Office",
            "type":"Public Place"
        }
    ],
    "sg:phone":"+1 204 822 7273",
    "sg:postcode":"R6M 1Y5",
    "sg:province":"MB",
    "wof:name":"Canada Rehabilitation Adm",
    "wof:placetype":"venue"
},
  "geometry": {"coordinates":[-98.11302185060001,49.1922836304],"type":"Point"}
}