{
  "type": "Feature",
  "properties": {
    "addr:full":"310 103rd St E Saskatoon SK S7N 1Z1",
    "addr:housenumber":"310",
    "addr:postcode":"s7n 1z1",
    "addr:street":"103Rd St E",
    "iso:country":"CA",
    "sg:address":"310 103rd St E",
    "sg:city":"Saskatoon",
    "sg:classifiers":[
        {
            "category":"Building & Trades",
            "subcategory":"Equipment Rental",
            "type":"Services"
        }
    ],
    "sg:phone":"+1 306 374 6548",
    "sg:postcode":"S7N 1Z1",
    "sg:province":"SK",
    "sg:tags":[
        "scaffolding"
    ],
    "wof:name":"Skyhigh Scaffold Construction",
    "wof:placetype":"venue"
},
  "geometry": {"coordinates":[-106.592407227,52.1293563843],"type":"Point"}
}