{
  "type": "Feature",
  "properties": {
    "addr:full":"215 Westcroft Rd Beaconsfield QC H9W 2M2",
    "addr:housenumber":"215",
    "addr:postcode":"h9w 2m2",
    "addr:street":"Westcroft Rd",
    "iso:country":"CA",
    "sg:address":"215 Westcroft Rd",
    "sg:city":"Beaconsfield",
    "sg:classifiers":[
        {
            "category":"Travel",
            "subcategory":"Travel Agent",
            "type":"Entertainment"
        }
    ],
    "sg:phone":"+1 514 694 3707",
    "sg:postcode":"H9W 2M2",
    "sg:province":"QC",
    "sg:tags":[
        "agency",
        "steamship"
    ],
    "wof:name":"Mca Marine & Cargo Agencies",
    "wof:placetype":"venue"
},
  "geometry": {"coordinates":[-73.864243,45.435284],"type":"Point"}
}