{
  "type": "Feature",
  "properties": {
    "addr:full":"449 Hodder Ave Thunder Bay ON P7A 1V2",
    "addr:housenumber":"449",
    "addr:postcode":"p7a 1v2",
    "addr:street":"Hodder Ave",
    "iso:country":"CA",
    "sg:address":"449 Hodder Ave",
    "sg:city":"Thunder Bay",
    "sg:classifiers":[
        {
            "category":"Health Services",
            "subcategory":"Doctor",
            "type":"Services"
        }
    ],
    "sg:phone":"+1 807 683 3771",
    "sg:postcode":"P7A 1V2",
    "sg:province":"ON",
    "sg:tags":[
        "dentist"
    ],
    "wof:name":"Sare, Robert DDS",
    "wof:placetype":"venue"
},
  "geometry": {"coordinates":[-89.1824188232,48.467464447],"type":"Point"}
}