{
  "type": "Feature",
  "properties": {
    "addr:full":"200 Boul D'Anjou Chateauguay QC J6K 1C5",
    "addr:housenumber":"200",
    "addr:postcode":"j6k 1c5",
    "addr:street":"Boul D'Anjou",
    "iso:country":"CA",
    "sg:address":"200 Boul D'Anjou",
    "sg:city":"Chateauguay",
    "sg:classifiers":[
        {
            "category":"Shopping",
            "subcategory":"Clothing, Apparel, & Fashions",
            "type":"Retail Goods"
        }
    ],
    "sg:phone":"+1 450 698 0938",
    "sg:postcode":"J6K 1C5",
    "sg:province":"QC",
    "sg:tags":[
        "item",
        "boutique"
    ],
    "wof:name":"Cohoes Fashions Inc",
    "wof:placetype":"venue"
},
  "geometry": {"coordinates":[-73.740112,45.361485],"type":"Point"}
}