{
  "type": "Feature",
  "properties": {
    "addr:full":"314 138 Rte Saint-Augustin-DE-Desmaures QC G3A 1G8",
    "addr:housenumber":"138",
    "addr:postcode":"g3a 1g8",
    "addr:street":"Rte Saint-Augustin-De-Desmaures",
    "iso:country":"CA",
    "sg:address":"314 138 Rte",
    "sg:city":"Saint-Augustin-DE-Desmaures",
    "sg:classifiers":[
        {
            "category":"Health Services",
            "subcategory":"Doctor",
            "type":"Services"
        }
    ],
    "sg:phone":"+1 418 878 3737",
    "sg:postcode":"G3A 1G8",
    "sg:province":"QC",
    "sg:tags":[
        "dentist"
    ],
    "wof:name":"Clinique Dentaire S Lamarre",
    "wof:placetype":"venue"
},
  "geometry": {"coordinates":[-71.457733,46.743736],"type":"Point"}
}