{
  "type": "Feature",
  "properties": {
    "iso:country":"CA",
    "sg:address":"4128 Midland Ave",
    "sg:city":"Scarborough",
    "sg:classifiers":[
        {
            "category":"Building & Trades",
            "subcategory":"Landscaping Services",
            "type":"Services"
        }
    ],
    "sg:phone":"+1 416 299 7361",
    "sg:postcode":"M1V 1S8",
    "sg:province":"ON",
    "sg:tags":[
        "lawn",
        "maintenance",
        "grounds"
    ],
    "wof:name":"Phoenix Grounds Maintenance",
    "wof:placetype":"venue"
},
  "geometry": {"coordinates":[-79.296089,43.822895],"type":"Point"}
}