{
  "type": "Feature",
  "properties": {
    "addr:full":"Mississauga ON L5G 1G2",
    "addr:postcode":"l5g 1g2",
    "iso:country":"CA",
    "sg:city":"Mississauga",
    "sg:classifiers":[
        {
            "category":"Education",
            "subcategory":"Special Training",
            "type":"Public Place"
        }
    ],
    "sg:phone":"+1 905 278 9751",
    "sg:postcode":"L5G 1G2",
    "sg:province":"ON",
    "sg:tags":[
        "instruction",
        "driving"
    ],
    "wof:name":"Cosmo & Mississauga School",
    "wof:placetype":"venue"
},
  "geometry": {"coordinates":[-79.578918457,43.5577468872],"type":"Point"}
}