{
  "type": "Feature",
  "properties": {
    "iso:country":"CA",
    "sg:address":"Rl 5 Fisher Bay",
    "sg:city":"Fisher Branch",
    "sg:classifiers":[
        {
            "category":"Travel",
            "subcategory":"Campground",
            "type":"Entertainment"
        }
    ],
    "sg:phone":"+1 204 645 2531",
    "sg:postcode":"R0C 0Z0",
    "sg:province":"MB",
    "sg:tags":[
        "camp"
    ],
    "wof:name":"Fisher Bay Bible Camp",
    "wof:placetype":"venue"
},
  "geometry": {"coordinates":[-97.6184539795,51.0826034546],"type":"Point"}
}