{
  "type": "Feature",
  "properties": {
    "iso:country":"CA",
    "sg:address":"220 Maccrae Dr",
    "sg:city":"Caledonia",
    "sg:classifiers":[
        {
            "category":"Building & Trades",
            "subcategory":"Landscaping Services",
            "type":"Services"
        }
    ],
    "sg:phone":"+1 905 765 3082",
    "sg:postcode":"N3W 1K6",
    "sg:province":"ON",
    "sg:tags":[
        "landscape",
        "contractor"
    ],
    "wof:name":"Outlooks Landscape & Design",
    "wof:placetype":"venue"
},
  "geometry": {"coordinates":[-79.9659729004,43.067024231],"type":"Point"}
}