{
  "type": "Feature",
  "properties": {
    "addr:full":"2625 County Rd 8 Campbellford ON K0L 1L0",
    "addr:housenumber":"2625",
    "addr:postcode":"k0l 1l0",
    "addr:street":"County Rd 8 Campbellford",
    "iso:country":"CA",
    "sg:address":"2625 County Rd 8",
    "sg:city":"Campbellford",
    "sg:classifiers":[
        {
            "category":"Wholesale",
            "subcategory":"Machinery & Supplies",
            "type":"Manufacturing & Wholesale Goods"
        }
    ],
    "sg:phone":"+1 705 653 3094",
    "sg:postcode":"K0L 1L0",
    "sg:province":"ON",
    "sg:tags":[
        "farm",
        "equipment"
    ],
    "wof:name":"Foote Farm Equipment Ltd",
    "wof:placetype":"venue"
},
  "geometry": {"coordinates":[-77.797492981,44.309211731],"type":"Point"}
}