{
  "type": "Feature",
  "properties": {
    "addr:full":"11219 103 St Fort St John BC V1J 4W7",
    "addr:housenumber":"11219",
    "addr:postcode":"v1j 4w7",
    "addr:street":"103 St",
    "iso:country":"CA",
    "sg:address":"11219 103 St",
    "sg:city":"Fort St John",
    "sg:classifiers":[
        {
            "category":"Wholesale",
            "subcategory":"Electrical",
            "type":"Manufacturing & Wholesale Goods"
        }
    ],
    "sg:phone":"+1 250 787 8721",
    "sg:postcode":"V1J 4W7",
    "sg:province":"BC",
    "sg:tags":[
        "telephone",
        "equipment",
        "system",
        "telecommunication"
    ],
    "wof:name":"Myles Communications",
    "wof:placetype":"venue"
},
  "geometry": {"coordinates":[-120.852287292,56.2578468323],"type":"Point"}
}