{
  "type": "Feature",
  "properties": {
    "addr:full":"40 Secord Dr St Catharines ON L2N 1K8",
    "addr:housenumber":"40",
    "addr:postcode":"l2n 1k8",
    "addr:street":"Secord Dr",
    "iso:country":"CA",
    "sg:address":"40 Secord Dr",
    "sg:city":"St Catharines",
    "sg:classifiers":[
        {
            "category":"Insurance",
            "subcategory":"Insurance Agent",
            "type":"Services"
        }
    ],
    "sg:phone":"+1 905 935 0396",
    "sg:postcode":"L2N 1K8",
    "sg:province":"ON",
    "wof:name":"Sneath, Peter",
    "wof:placetype":"venue"
},
  "geometry": {"coordinates":[-79.2487564087,43.1840133667],"type":"Point"}
}