{
  "type": "Feature",
  "properties": {
    "iso:country":"CA",
    "sg:city":"Waterloo",
    "sg:classifiers":[
        {
            "category":"Manufacturing",
            "subcategory":"Lumber",
            "type":"Manufacturing & Wholesale Goods"
        }
    ],
    "sg:phone":"+1 450 539 4822",
    "sg:postcode":"J0E 2N0",
    "sg:province":"QC",
    "sg:tags":[
        "syrup",
        "maple",
        "sugar"
    ],
    "wof:name":"Turkey Hill Sugarbush Ltd",
    "wof:placetype":"venue"
},
  "geometry": {"coordinates":[-72.5268173218,45.3393707275],"type":"Point"}
}