{
  "type": "Feature",
  "properties": {
    "addr:full":"3113 Rue Masson Montreal QC H1Y 1X9",
    "addr:housenumber":"3113",
    "addr:postcode":"h1y 1x9",
    "addr:street":"Rue Masson",
    "iso:country":"CA",
    "sg:address":"3113 Rue Masson",
    "sg:city":"Montreal",
    "sg:classifiers":[
        {
            "category":"Home & Garden",
            "subcategory":"Hardware",
            "type":"Retail Goods"
        }
    ],
    "sg:phone":"+1 514 728 3637",
    "sg:postcode":"H1Y 1X9",
    "sg:province":"QC",
    "wof:name":"Quincaillerie A Lalonde Ltee",
    "wof:placetype":"venue"
},
  "geometry": {"coordinates":[-73.574242,45.549484],"type":"Point"}
}