{
  "type": "Feature",
  "properties": {
    "addr:full":"Fort Simpson NT X0E 0N0",
    "addr:postcode":"x0e 0n0",
    "addr:street":"Fort",
    "iso:country":"CA",
    "sg:city":"Fort Simpson",
    "sg:classifiers":[
        {
            "category":"Social Services",
            "subcategory":"Child Care",
            "type":"Services"
        }
    ],
    "sg:phone":"+1 867 695 7335",
    "sg:postcode":"X0E 0N0",
    "sg:province":"NT",
    "sg:tags":[
        "government"
    ],
    "wof:name":"N T Education Culture & Emply",
    "wof:placetype":"venue"
},
  "geometry": {"coordinates":[-121.24024963399999,61.7775421143],"type":"Point"}
}