{
  "type": "Feature",
  "properties": {
    "addr:full":"Box 5628 Fort Mcmurray AB T9H 3G6",
    "addr:housenumber":"5628",
    "addr:postcode":"t9h 3g6",
    "iso:country":"CA",
    "sg:address":"Box 5628",
    "sg:city":"Fort Mcmurray",
    "sg:classifiers":[
        {
            "category":"Professional",
            "subcategory":"Computer Services",
            "type":"Services"
        }
    ],
    "sg:phone":"+1 780 743 4638",
    "sg:postcode":"T9H 3G6",
    "sg:province":"AB",
    "sg:tags":[
        "consultant"
    ],
    "wof:name":"Tnc North",
    "wof:placetype":"venue"
},
  "geometry": {"coordinates":[-111.380302,56.727188],"type":"Point"}
}