{
  "type": "Feature",
  "properties": {
    "iso:country":"CA",
    "sg:address":"1153 Queen St W",
    "sg:city":"Toronto",
    "sg:classifiers":[
        {
            "category":"Shopping",
            "type":"Retail Goods"
        }
    ],
    "sg:phone":"+1 416 536 7878",
    "sg:postcode":"M6J 1J4",
    "sg:province":"ON",
    "sg:tags":[
        "material",
        "craft",
        "artist",
        "supply"
    ],
    "wof:name":"Woolfitt's Art Enterprises Inc",
    "wof:placetype":"venue"
},
  "geometry": {"coordinates":[-79.424911499,43.6428642273],"type":"Point"}
}