{
  "type": "Feature",
  "properties": {
    "addr:full":"596 Rue Principale Saint-Amable QC J0L 1N0",
    "addr:housenumber":"596",
    "addr:postcode":"j0l 1n0",
    "addr:street":"Rue Principale",
    "iso:country":"CA",
    "sg:address":"596 Rue Principale",
    "sg:city":"Saint-Amable",
    "sg:classifiers":[
        {
            "category":"Restaurant",
            "type":"Food & Drink"
        }
    ],
    "sg:phone":"+1 450 649 0381",
    "sg:postcode":"J0L 1N0",
    "sg:province":"QC",
    "wof:name":"Restaurant Chez T-Yvon Patates",
    "wof:placetype":"venue"
},
  "geometry": {"coordinates":[-73.304199,45.643787],"type":"Point"}
}