{
  "type": "Feature",
  "properties": {
    "addr:full":"975 Crowley Ave Kelowna BC V1Y 9R6",
    "addr:housenumber":"975",
    "addr:postcode":"v1y 9r6",
    "addr:street":"Crowley Ave",
    "iso:country":"CA",
    "sg:address":"975 Crowley Ave",
    "sg:city":"Kelowna",
    "sg:classifiers":[
        {
            "category":"Manufacturing",
            "subcategory":"Tools & Machinery",
            "type":"Manufacturing & Wholesale Goods"
        }
    ],
    "sg:phone":"+1 250 860 6969",
    "sg:postcode":"V1Y 9R6",
    "sg:province":"BC",
    "sg:tags":[
        "machine",
        "shop"
    ],
    "wof:name":"Multi-Power Products Ltd",
    "wof:placetype":"venue"
},
  "geometry": {"coordinates":[-119.480430603,49.8980255127],"type":"Point"}
}