{
  "type": "Feature",
  "properties": {
    "addr:full":"100 Rue Du Terminus O Rouyn-Noranda QC J9X 6H7",
    "addr:housenumber":"100",
    "addr:postcode":"j9x 6h7",
    "addr:street":"Rue Du Terminus O",
    "iso:country":"CA",
    "sg:address":"100 Rue Du Terminus O",
    "sg:city":"Rouyn-Noranda",
    "sg:classifiers":[
        {
            "category":"Shopping",
            "subcategory":"Clothing, Apparel, & Fashions",
            "type":"Retail Goods"
        }
    ],
    "sg:phone":"+1 819 762 8373",
    "sg:postcode":"J9X 6H7",
    "sg:province":"QC",
    "sg:tags":[
        "item",
        "boutique"
    ],
    "wof:name":"Accessoirie",
    "wof:placetype":"venue"
},
  "geometry": {"coordinates":[-79.025375,48.241879],"type":"Point"}
}