{
  "type": "Feature",
  "properties": {
    "addr:full":"Ottawa ON K1V 8A1",
    "addr:postcode":"k1v 8a1",
    "iso:country":"CA",
    "sg:city":"Ottawa",
    "sg:classifiers":[
        {
            "category":"Health Services",
            "subcategory":"Optometrist",
            "type":"Services"
        }
    ],
    "sg:phone":"+1 613 526 2701",
    "sg:postcode":"K1V 8A1",
    "sg:province":"ON",
    "wof:name":"Mc Dade, W D",
    "wof:placetype":"venue"
},
  "geometry": {"coordinates":[-75.6624298096,45.3689956665],"type":"Point"}
}