{
  "type": "Feature",
  "properties": {
    "addr:full":"735 Lorne St Sudbury ON P3C 4R5",
    "addr:housenumber":"735",
    "addr:postcode":"p3c 4r5",
    "addr:street":"Lorne St",
    "iso:country":"CA",
    "sg:address":"735 Lorne St",
    "sg:city":"Sudbury",
    "sg:classifiers":[
        {
            "category":"Shopping",
            "subcategory":"Computers & Home Electronics",
            "type":"Retail Goods"
        }
    ],
    "sg:phone":"+1 705 673 5555",
    "sg:postcode":"P3C 4R5",
    "sg:province":"ON",
    "sg:tags":[
        "television",
        "radio"
    ],
    "wof:name":"Lorne Electronics",
    "wof:placetype":"venue"
},
  "geometry": {"coordinates":[-81.0155715942,46.4786720276],"type":"Point"}
}