{
  "type": "Feature",
  "properties": {
    "addr:full":"135 Vermilion St Princeton BC V0X 1W0",
    "addr:housenumber":"135",
    "addr:postcode":"v0x 1w0",
    "addr:street":"Vermilion St",
    "iso:country":"CA",
    "sg:address":"135 Vermilion St",
    "sg:city":"Princeton",
    "sg:classifiers":[
        {
            "category":"Cinema",
            "subcategory":"Movie Rental",
            "type":"Entertainment"
        }
    ],
    "sg:phone":"+1 250 295 7602",
    "sg:postcode":"V0X 1W0",
    "sg:province":"BC",
    "sg:tags":[
        "leasing",
        "video",
        "disc",
        "tape"
    ],
    "wof:name":"No 1 Video",
    "wof:placetype":"venue"
},
  "geometry": {"coordinates":[-120.50859069800001,49.4596595764],"type":"Point"}
}