{
  "type": "Feature",
  "properties": {
    "addr:full":"3615 9 Ave N Lethbridge AB T1H 6G8",
    "addr:housenumber":"3615",
    "addr:postcode":"t1h 6g8",
    "addr:street":"9 Ave N",
    "iso:country":"CA",
    "sg:address":"3615 9 Ave N",
    "sg:city":"Lethbridge",
    "sg:classifiers":[
        {
            "category":"Home & Garden",
            "subcategory":"Building Materials",
            "type":"Retail Goods"
        }
    ],
    "sg:phone":"+1 403 328 5400",
    "sg:postcode":"T1H 6G8",
    "sg:province":"AB",
    "sg:tags":[
        "glass",
        "window",
        "plate"
    ],
    "wof:name":"Can-am Auto Glass & Supplies",
    "wof:placetype":"venue"
},
  "geometry": {"coordinates":[-112.788551,49.712849],"type":"Point"}
}