{
  "type": "Feature",
  "properties": {
    "iso:country":"CA",
    "sg:city":"Laval",
    "sg:classifiers":[
        {
            "category":"Insurance",
            "subcategory":"Insurance Agent",
            "type":"Services"
        }
    ],
    "sg:phone":"+1 450 682 7772",
    "sg:postcode":"H7T 2S3",
    "sg:province":"QC",
    "wof:name":"Groupe Vigilis Inc",
    "wof:placetype":"venue"
},
  "geometry": {"coordinates":[-73.75518035890001,45.5666160583],"type":"Point"}
}