{
  "type": "Feature",
  "properties": {
    "addr:full":"2020 Rue University #1090 Montreal QC H3A 2A5",
    "addr:housenumber":"2020;#",
    "addr:postcode":"h3a 2a5",
    "addr:street":"Rue University",
    "iso:country":"CA",
    "sg:address":"2020 Rue University #1090",
    "sg:city":"Montreal",
    "sg:classifiers":[
        {
            "category":"Professional",
            "subcategory":"Employment Agencies",
            "type":"Services"
        }
    ],
    "sg:phone":"+1 514 840 1090",
    "sg:postcode":"H3A 2A5",
    "sg:province":"QC",
    "sg:tags":[
        "opportunity"
    ],
    "wof:name":"Prud'Homme Groupe-Conseil",
    "wof:placetype":"venue"
},
  "geometry": {"coordinates":[-73.57186889650001,45.504070282],"type":"Point"}
}