{
  "type": "Feature",
  "properties": {
    "addr:full":"425 Main St Exeter ON N0M 1S6",
    "addr:housenumber":"425",
    "addr:postcode":"n0m 1s6",
    "addr:street":"Main St",
    "iso:country":"CA",
    "sg:address":"425 Main St",
    "sg:city":"Exeter",
    "sg:classifiers":[
        {
            "category":"Insurance",
            "subcategory":"Insurance Agent",
            "type":"Services"
        }
    ],
    "sg:phone":"+1 519 235 2740",
    "sg:postcode":"N0M 1S6",
    "sg:province":"ON",
    "wof:name":"Godbolt Ciufo Ins & Financial",
    "wof:placetype":"venue"
},
  "geometry": {"coordinates":[-81.48034667970001,43.3451805115],"type":"Point"}
}