{
  "type": "Feature",
  "properties": {
    "addr:full":"Palmerston ON N0G 2P0",
    "addr:postcode":"n0g 2p0",
    "iso:country":"CA",
    "sg:city":"Palmerston",
    "sg:classifiers":[
        {
            "category":"Wholesale",
            "subcategory":"Machinery & Supplies",
            "type":"Manufacturing & Wholesale Goods"
        }
    ],
    "sg:phone":"+1 519 343 2840",
    "sg:postcode":"N0G 2P0",
    "sg:province":"ON",
    "sg:tags":[
        "janitor"
    ],
    "wof:name":"Eric Cox Sanitation Equipment",
    "wof:placetype":"venue"
},
  "geometry": {"coordinates":[-80.84841900000001,43.835464],"type":"Point"}
}