{
  "type": "Feature",
  "properties": {
    "addr:full":"Halmo St & Railway Ave Kuroki SK S0A 1Y0",
    "addr:postcode":"s0a 1y0",
    "addr:street":"St & Railway Ave",
    "iso:country":"CA",
    "sg:address":"Halmo St & Railway Ave",
    "sg:city":"Kuroki",
    "sg:classifiers":[
        {
            "category":"Organizations",
            "subcategory":"Religious Organization",
            "type":"Services"
        }
    ],
    "sg:phone":"+1 306 338 3321",
    "sg:postcode":"S0A 1Y0",
    "sg:province":"SK",
    "sg:tags":[
        "church"
    ],
    "wof:name":"Kuroki New Life Community Chr",
    "wof:placetype":"venue"
},
  "geometry": {"coordinates":[-103.799278259,51.9428634644],"type":"Point"}
}