{
  "type": "Feature",
  "properties": {
    "iso:country":"CA",
    "sg:address":"417 Rue Saint-Pierre",
    "sg:city":"Montreal",
    "sg:classifiers":[
        {
            "category":"Professional",
            "subcategory":"Lawyer & Legal Services",
            "type":"Services"
        }
    ],
    "sg:phone":"+1 514 844 0300",
    "sg:postcode":"H2Y 2M4",
    "sg:province":"QC",
    "sg:tags":[
        "attorney"
    ],
    "wof:name":"Giannetti St-Pierre Desrochers",
    "wof:placetype":"venue"
},
  "geometry": {"coordinates":[-73.556702,45.501583],"type":"Point"}
}