{
  "type": "Feature",
  "properties": {
    "addr:full":"625 Rue Belmont Montreal QC H3B 2M1",
    "addr:housenumber":"625",
    "addr:postcode":"h3b 2m1",
    "addr:street":"Rue Belmont",
    "iso:country":"CA",
    "sg:address":"625 Rue Belmont",
    "sg:city":"Montreal",
    "sg:classifiers":[
        {
            "category":"Wholesale",
            "subcategory":"Metals & Minerals",
            "type":"Manufacturing & Wholesale Goods"
        }
    ],
    "sg:phone":"+1 514 861 6905",
    "sg:postcode":"H3B 2M1",
    "sg:province":"QC",
    "sg:tags":[
        "steel",
        "warehouse"
    ],
    "wof:name":"Fagen & Fils",
    "wof:placetype":"venue"
},
  "geometry": {"coordinates":[-73.56562,45.501831],"type":"Point"}
}