{
  "type": "Feature",
  "properties": {
    "addr:full":"1210 31 St N Lethbridge AB T1H 5J8",
    "addr:housenumber":"1210",
    "addr:postcode":"t1h 5j8",
    "addr:street":"31 St N",
    "iso:country":"CA",
    "sg:address":"1210 31 St N",
    "sg:city":"Lethbridge",
    "sg:classifiers":[
        {
            "category":"Professional",
            "subcategory":"Research",
            "type":"Services"
        }
    ],
    "sg:phone":"+1 403 328 1346",
    "sg:postcode":"T1H 5J8",
    "sg:province":"AB",
    "sg:tags":[
        "environmental",
        "ecological",
        "excavating",
        "contractor"
    ],
    "wof:name":"G W Cox Construction Ltd",
    "wof:placetype":"venue"
},
  "geometry": {"coordinates":[-112.79473900000001,49.716312],"type":"Point"}
}