{
  "type": "Feature",
  "properties": {
    "iso:country":"CA",
    "sg:city":"Montreal",
    "sg:classifiers":[
        {
            "category":"Wholesale",
            "subcategory":"Apparel",
            "type":"Manufacturing & Wholesale Goods"
        }
    ],
    "sg:phone":"+1 514 384 4439",
    "sg:postcode":"H2N 1E4",
    "sg:province":"QC",
    "sg:tags":[
        "clothing"
    ],
    "wof:name":"Items By Design",
    "wof:placetype":"venue"
},
  "geometry": {"coordinates":[-73.65274,45.541733],"type":"Point"}
}