{
  "type": "Feature",
  "properties": {
    "addr:full":"4150 Boul Saint-Martin O Laval QC H7T 1C1",
    "addr:housenumber":"4150",
    "addr:postcode":"h7t 1c1",
    "addr:street":"Boul Saint-Martin O",
    "iso:country":"CA",
    "sg:address":"4150 Boul Saint-Martin O",
    "sg:city":"Laval",
    "sg:classifiers":[
        {
            "category":"Professional",
            "subcategory":"Accounting & Tax Preparation",
            "type":"Services"
        }
    ],
    "sg:phone":"+1 450 686 7555",
    "sg:postcode":"H7T 1C1",
    "sg:province":"QC",
    "sg:tags":[
        "accountant"
    ],
    "wof:name":"Taillefer Lussier",
    "wof:placetype":"venue"
},
  "geometry": {"coordinates":[-73.764923,45.549614],"type":"Point"}
}