{
  "type": "Feature",
  "properties": {
    "addr:full":"12512 39A Ave NW Edmonton AB T6J 0P5",
    "addr:housenumber":"12512",
    "addr:postcode":"t6j 0p5",
    "addr:street":"39A Ave Nw",
    "iso:country":"CA",
    "sg:address":"12512 39A Ave NW",
    "sg:city":"Edmonton",
    "sg:classifiers":[
        {
            "category":"Professional",
            "subcategory":"Advertising",
            "type":"Services"
        }
    ],
    "sg:phone":"+1 780 468 6962",
    "sg:postcode":"T6J 0P5",
    "sg:province":"AB",
    "sg:tags":[
        "distributing",
        "sample"
    ],
    "wof:name":"Main Staple Poster Distr",
    "wof:placetype":"venue"
},
  "geometry": {"coordinates":[-113.548225,53.475262],"type":"Point"}
}