{
  "type": "Feature",
  "properties": {
    "addr:full":"Vanderhoof BC V0J 3A0",
    "addr:postcode":"v0j 3a0",
    "iso:country":"CA",
    "sg:city":"Vanderhoof",
    "sg:classifiers":[
        {
            "category":"Manufacturing",
            "subcategory":"Lumber",
            "type":"Manufacturing & Wholesale Goods"
        }
    ],
    "sg:phone":"+1 250 567 2775",
    "sg:postcode":"V0J 3A0",
    "sg:province":"BC",
    "sg:tags":[
        "forester"
    ],
    "wof:name":"Van Dolah Enterprises Inc",
    "wof:placetype":"venue"
},
  "geometry": {"coordinates":[-124.00918579099999,54.0254898071],"type":"Point"}
}