{
  "type": "Feature",
  "properties": {
    "addr:full":"6840 Boul Saint-Laurent Montreal QC H2S 3C7",
    "addr:housenumber":6840,
    "addr:postcode":"h2s 3c7",
    "addr:street":"Boul Saint-Laurent",
    "iso:country":"CA",
    "sg:address":"6840 Boul Saint-Laurent",
    "sg:city":"Montreal",
    "sg:classifiers":[
        {
            "category":"Restaurant",
            "type":"Food & Drink"
        }
    ],
    "sg:phone":"+1 514 495 0059",
    "sg:postcode":"H2S 3C7",
    "sg:province":"QC",
    "wof:name":"Cafe Italia",
    "wof:placetype":"venue"
},
  "geometry": {"coordinates":[-73.614349,45.532726],"type":"Point"}
}