{
  "type": "Feature",
  "properties": {
    "addr:full":"1480 Huron St London ON N5V 2E5",
    "addr:housenumber":"1480",
    "addr:postcode":"n5v 2e5",
    "addr:street":"Huron St",
    "iso:country":"CA",
    "sg:address":"1480 Huron St",
    "sg:city":"London",
    "sg:classifiers":[
        {
            "category":"Health Services",
            "subcategory":"Doctor",
            "type":"Services"
        }
    ],
    "sg:phone":"+1 519 455 7650",
    "sg:postcode":"N5V 2E5",
    "sg:province":"ON",
    "sg:tags":[
        "dentist"
    ],
    "wof:name":"Lafferty, John DDS",
    "wof:placetype":"venue"
},
  "geometry": {"coordinates":[-81.2043838501,43.0232582092],"type":"Point"}
}