{
  "type": "Feature",
  "properties": {
    "addr:full":"355 Dundas St E Mississauga ON L5A 1X3",
    "addr:housenumber":"355",
    "addr:postcode":"l5a 1x3",
    "addr:street":"Dundas St E",
    "iso:country":"CA",
    "sg:address":"355 Dundas St E",
    "sg:city":"Mississauga",
    "sg:classifiers":[
        {
            "category":"Home & Garden",
            "subcategory":"Building Materials",
            "type":"Retail Goods"
        }
    ],
    "sg:phone":"+1 905 276 2344",
    "sg:postcode":"L5A 1X3",
    "sg:province":"ON",
    "sg:tags":[
        "paint"
    ],
    "wof:name":"Color Your World",
    "wof:placetype":"venue"
},
  "geometry": {"coordinates":[-79.60771200000001,43.588028],"type":"Point"}
}