{
  "type": "Feature",
  "properties": {
    "iso:country":"CA",
    "sg:address":"300 Tecumseh Rd E # 310",
    "sg:city":"Windsor",
    "sg:classifiers":[
        {
            "category":"Shopping",
            "subcategory":"Department Store",
            "type":"Retail Goods"
        }
    ],
    "sg:phone":"+1 519 973 9158",
    "sg:postcode":"N8X 5E8",
    "sg:province":"ON",
    "sg:tags":[
        "shop"
    ],
    "wof:name":"Dollarama",
    "wof:placetype":"venue"
},
  "geometry": {"coordinates":[-83.0207061768,42.2974128723],"type":"Point"}
}