{
  "type": "Feature",
  "properties": {
    "addr:full":"109 Carberry Cres Winnipeg MB R2Y 0K3",
    "addr:housenumber":"109",
    "addr:postcode":"r2y 0k3",
    "addr:street":"Carberry Cres",
    "iso:country":"CA",
    "sg:address":"109 Carberry Cres",
    "sg:city":"Winnipeg",
    "sg:classifiers":[
        {
            "category":"Manufacturing",
            "subcategory":"Printing",
            "type":"Manufacturing & Wholesale Goods"
        }
    ],
    "sg:phone":"+1 204 831 5131",
    "sg:postcode":"R2Y 0K3",
    "sg:province":"MB",
    "sg:tags":[
        "broker",
        "publishing"
    ],
    "wof:name":"Sales Write Marketing",
    "wof:placetype":"venue"
},
  "geometry": {"coordinates":[-97.2995605469,49.8995780945],"type":"Point"}
}