{
  "type": "Feature",
  "properties": {
    "addr:full":"1189 Confederation St Sarnia ON N7S 4M7",
    "addr:housenumber":"1189",
    "addr:postcode":"n7s 4m7",
    "addr:street":"Confederation St",
    "iso:country":"CA",
    "sg:address":"1189 Confederation St",
    "sg:city":"Sarnia",
    "sg:classifiers":[
        {
            "category":"Home & Garden",
            "subcategory":"Building Materials",
            "type":"Retail Goods"
        }
    ],
    "sg:phone":"+1 519 337 2334",
    "sg:postcode":"N7S 4M7",
    "sg:province":"ON",
    "wof:name":"Patene Building Supplies Ltd",
    "wof:placetype":"venue"
},
  "geometry": {"coordinates":[-82.366692,42.960278],"type":"Point"}
}