{
  "type": "Feature",
  "properties": {
    "addr:full":"4794 Boul Saint-Charles Pierrefonds QC H9H 3C9",
    "addr:housenumber":"4794",
    "addr:postcode":"h9h 3c9",
    "addr:street":"Boul Saint-Charles",
    "iso:country":"CA",
    "sg:address":"4794 Boul Saint-Charles",
    "sg:city":"Pierrefonds",
    "sg:classifiers":[
        {
            "category":"Restaurant",
            "type":"Food & Drink"
        }
    ],
    "sg:phone":"+1 514 626 8366",
    "sg:postcode":"H9H 3C9",
    "sg:province":"QC",
    "wof:name":"Valentine Restaurant",
    "wof:placetype":"venue"
},
  "geometry": {"coordinates":[-73.87261199949999,45.4643554688],"type":"Point"}
}