{
  "type": "Feature",
  "properties": {
    "addr:full":"101 Boul Cardinal-Leger Pincourt QC J7V 3Y3",
    "addr:housenumber":"101",
    "addr:postcode":"j7v 3y3",
    "addr:street":"Boul Cardinal-Leger",
    "iso:country":"CA",
    "sg:address":"101 Boul Cardinal-Leger",
    "sg:city":"Pincourt",
    "sg:classifiers":[
        {
            "category":"Cinema",
            "subcategory":"Movie Rental",
            "type":"Entertainment"
        }
    ],
    "sg:phone":"+1 514 453 4554",
    "sg:postcode":"J7V 3Y3",
    "sg:province":"QC",
    "sg:tags":[
        "leasing",
        "video",
        "disc",
        "tape"
    ],
    "wof:name":"Blockbuster Video",
    "wof:placetype":"venue"
},
  "geometry": {"coordinates":[-73.992805481,45.3839836121],"type":"Point"}
}