{
  "type": "Feature",
  "properties": {
    "addr:full":"357 Trunk Rd Sault Ste Marie ON P6A 3S9",
    "addr:housenumber":"357",
    "addr:postcode":"p6a 3s9",
    "addr:street":"Trunk Rd",
    "iso:country":"CA",
    "sg:address":"357 Trunk Rd",
    "sg:city":"Sault Ste Marie",
    "sg:classifiers":[
        {
            "category":"Food & Beverages",
            "subcategory":"Bakery",
            "type":"Retail Goods"
        }
    ],
    "sg:phone":"+1 705 942 3380",
    "sg:postcode":"P6A 3S9",
    "sg:province":"ON",
    "sg:tags":[
        "doughnut"
    ],
    "wof:name":"Country Style Donuts",
    "wof:placetype":"venue"
},
  "geometry": {"coordinates":[-84.28545379640001,46.5165214539],"type":"Point"}
}