{
  "type": "Feature",
  "properties": {
    "addr:full":"275 Rue DE L'Eglise Charlesbourg QC G2N 1E3",
    "addr:housenumber":"275",
    "addr:postcode":"g2n 1e3",
    "addr:street":"Rue De L'Eglise",
    "iso:country":"CA",
    "sg:address":"275 Rue DE L'Eglise",
    "sg:city":"Charlesbourg",
    "sg:classifiers":[
        {
            "category":"Building & Trades",
            "subcategory":"Construction",
            "type":"Services"
        }
    ],
    "sg:phone":"+1 418 849 3469",
    "sg:postcode":"G2N 1E3",
    "sg:province":"QC",
    "sg:tags":[
        "roofing",
        "contractor"
    ],
    "wof:name":"Robert Labbe & Fils Inc",
    "wof:placetype":"venue"
},
  "geometry": {"coordinates":[-71.3413925171,46.9114990234],"type":"Point"}
}