{
  "type": "Feature",
  "properties": {
    "addr:full":"2 Rue Elie-Rochefort # 2 Port-Cartier QC G5B 2N2",
    "addr:housenumber":"2",
    "addr:postcode":"g5b 2n2",
    "addr:street":"Rue Elie-Rochefort # 2 Port-Cartier",
    "iso:country":"CA",
    "sg:address":"2 Rue Elie-Rochefort # 2",
    "sg:city":"Port-Cartier",
    "sg:classifiers":[
        {
            "category":"Insurance",
            "subcategory":"Insurance Agent",
            "type":"Services"
        }
    ],
    "sg:phone":"+1 418 766 6511",
    "sg:postcode":"G5B 2N2",
    "sg:province":"QC",
    "sg:tags":[
        "consultant"
    ],
    "wof:name":"Boisse, Claude",
    "wof:placetype":"venue"
},
  "geometry": {"coordinates":[-66.880943,50.029186],"type":"Point"}
}