{
  "type": "Feature",
  "properties": {
    "addr:full":"500 Rue Du Pont Quebec QC G1K 6N4",
    "addr:housenumber":"500",
    "addr:postcode":"g1k 6n4",
    "addr:street":"Rue Du Pont",
    "iso:country":"CA",
    "sg:address":"500 Rue Du Pont",
    "sg:city":"Quebec",
    "sg:classifiers":[
        {
            "category":"Cinema",
            "subcategory":"Movie Theater",
            "type":"Entertainment"
        }
    ],
    "sg:phone":"+1 418 529 9745",
    "sg:postcode":"G1K 6N4",
    "sg:province":"QC",
    "wof:name":"Cinema Place Charest",
    "wof:placetype":"venue"
},
  "geometry": {"coordinates":[-71.2198791504,46.8140830994],"type":"Point"}
}