{
  "type": "Feature",
  "properties": {
    "iso:country":"CA",
    "sg:address":"230 Marconi Blvd",
    "sg:city":"London",
    "sg:classifiers":[
        {
            "category":"Real Estate",
            "subcategory":"Real Estate Operator",
            "type":"Services"
        }
    ],
    "sg:phone":"+1 519 455 3844",
    "sg:postcode":"N5V 1A7",
    "sg:province":"ON",
    "sg:tags":[
        "apartment"
    ],
    "wof:name":"Noel Meadows",
    "wof:placetype":"venue"
},
  "geometry": {"coordinates":[-81.1641082764,42.9897651672],"type":"Point"}
}