{
  "type": "Feature",
  "properties": {
    "addr:full":"214 Kelley Rd Hinton AB T7V 1H2",
    "addr:housenumber":"214",
    "addr:postcode":"t7v 1h2",
    "addr:street":"Kelley Rd",
    "iso:country":"CA",
    "sg:address":"214 Kelley Rd",
    "sg:city":"Hinton",
    "sg:classifiers":[
        {
            "category":"Wholesale",
            "subcategory":"Machinery & Supplies",
            "type":"Manufacturing & Wholesale Goods"
        }
    ],
    "sg:phone":"+1 780 865 2246",
    "sg:postcode":"T7V 1H2",
    "sg:province":"AB",
    "sg:tags":[
        "equipment",
        "industrial"
    ],
    "wof:name":"Acklands-Grainger Inc",
    "wof:placetype":"venue"
},
  "geometry": {"coordinates":[-117.58032989500001,53.4057579041],"type":"Point"}
}