{
  "type": "Feature",
  "properties": {
    "addr:full":"2840 49th Ave E Vancouver BC V5S 1K5",
    "addr:housenumber":"2840",
    "addr:postcode":"v5s 1k5",
    "addr:street":"49Th Ave E",
    "iso:country":"CA",
    "sg:address":"2840 49th Ave E",
    "sg:city":"Vancouver",
    "sg:classifiers":[
        {
            "category":"Real Estate",
            "subcategory":"Real Estate Agent",
            "type":"Services"
        }
    ],
    "sg:phone":"+1 604 451 5189",
    "sg:postcode":"V5S 1K5",
    "sg:province":"BC",
    "wof:name":"Sunrise Realty",
    "wof:placetype":"venue"
},
  "geometry": {"coordinates":[-123.047462,49.224648],"type":"Point"}
}