{
  "type": "Feature",
  "properties": {
    "addr:full":"547 Peace Rd Omemee ON K0L 2W0",
    "addr:housenumber":"547",
    "addr:postcode":"k0l 2w0",
    "addr:street":"Peace Rd",
    "iso:country":"CA",
    "sg:address":"547 Peace Rd",
    "sg:city":"Omemee",
    "sg:classifiers":[
        {
            "category":"Building & Trades",
            "subcategory":"Construction",
            "type":"Services"
        }
    ],
    "sg:phone":"+1 705 799 7558",
    "sg:postcode":"K0L 2W0",
    "sg:province":"ON",
    "sg:tags":[
        "resurfacing",
        "laying",
        "refinishing",
        "floor"
    ],
    "wof:name":"Resline Limited",
    "wof:placetype":"venue"
},
  "geometry": {"coordinates":[-78.57637786870001,44.3359413147],"type":"Point"}
}