{
  "type": "Feature",
  "properties": {
    "iso:country":"CA",
    "sg:city":"Peterborough",
    "sg:classifiers":[
        {
            "category":"Professional",
            "subcategory":"Employment Agencies",
            "type":"Services"
        }
    ],
    "sg:phone":"+1 705 743 5871",
    "sg:postcode":"K9H 7E8",
    "sg:province":"ON",
    "sg:tags":[
        "opportunity",
        "contractor"
    ],
    "wof:name":"Manpower Temporary Svc",
    "wof:placetype":"venue"
},
  "geometry": {"coordinates":[-78.3197021484,44.3036155701],"type":"Point"}
}