{
  "type": "Feature",
  "properties": {
    "addr:full":"174 Boul Greber # 100 Gatineau QC J8T 6Z5",
    "addr:housenumber":"174",
    "addr:postcode":"j8t 6z5",
    "addr:street":"Boul Greber # 100",
    "iso:country":"CA",
    "sg:address":"174 Boul Greber # 100",
    "sg:city":"Gatineau",
    "sg:classifiers":[
        {
            "category":"Shopping",
            "subcategory":"Gifts & Souvenirs",
            "type":"Retail Goods"
        }
    ],
    "sg:phone":"+1 819 243 2255",
    "sg:postcode":"J8T 6Z5",
    "sg:province":"QC",
    "sg:tags":[
        "party",
        "supply"
    ],
    "wof:name":"Au Centre Du Party",
    "wof:placetype":"venue"
},
  "geometry": {"coordinates":[-75.701263,45.471699],"type":"Point"}
}