{
  "type": "Feature",
  "properties": {
    "addr:full":"3943 Boul Leman Laval QC H7E 4V7",
    "addr:housenumber":"3943",
    "addr:postcode":"h7e 4v7",
    "addr:street":"Boul Leman",
    "iso:country":"CA",
    "sg:address":"3943 Boul Leman",
    "sg:city":"Laval",
    "sg:classifiers":[
        {
            "category":"Retail",
            "subcategory":"Repair Shop",
            "type":"Services"
        }
    ],
    "sg:phone":"+1 450 664 0920",
    "sg:postcode":"H7E 4V7",
    "sg:province":"QC",
    "sg:tags":[
        "sharpening"
    ],
    "wof:name":"Grindex International",
    "wof:placetype":"venue"
},
  "geometry": {"coordinates":[-73.67130299999999,45.613186],"type":"Point"}
}