{
  "type": "Feature",
  "properties": {
    "addr:full":"1975 Lonsdale Ave # 102 North Vancouver BC V7M 2K3",
    "addr:housenumber":"1975",
    "addr:postcode":"v7m 2k3",
    "addr:street":"Lonsdale Ave # 102",
    "iso:country":"CA",
    "sg:address":"1975 Lonsdale Ave # 102",
    "sg:city":"North Vancouver",
    "sg:classifiers":[
        {
            "category":"Professional",
            "subcategory":"Accounting & Tax Preparation",
            "type":"Services"
        }
    ],
    "sg:phone":"+1 604 987 8101",
    "sg:postcode":"V7M 2K3",
    "sg:province":"BC",
    "sg:tags":[
        "accountant"
    ],
    "wof:name":"Evancic Perrault Robertson",
    "wof:placetype":"venue"
},
  "geometry": {"coordinates":[-123.072395,49.32695],"type":"Point"}
}