{
  "type": "Feature",
  "properties": {
    "addr:full":"4297 Wyandotte St E Windsor ON N8Y 1G8",
    "addr:housenumber":"4297",
    "addr:postcode":"n8y 1g8",
    "addr:street":"Wyandotte St E",
    "iso:country":"CA",
    "sg:address":"4297 Wyandotte St E",
    "sg:city":"Windsor",
    "sg:classifiers":[
        {
            "category":"Shopping",
            "subcategory":"Discount & Variety Stores",
            "type":"Retail Goods"
        }
    ],
    "sg:phone":"+1 519 948 8983",
    "sg:postcode":"N8Y 1G8",
    "sg:province":"ON",
    "wof:name":"A & F Corner Store",
    "wof:placetype":"venue"
},
  "geometry": {"coordinates":[-82.98468017579999,42.325378418],"type":"Point"}
}