{
  "type": "Feature",
  "properties": {
    "iso:country":"CA",
    "sg:address":"29 Dysart Rd",
    "sg:city":"Winnipeg",
    "sg:classifiers":[
        {
            "category":"Education",
            "subcategory":"School",
            "type":"Public Place"
        }
    ],
    "sg:phone":"+1 204 474 8895",
    "sg:postcode":"R3T 2M7",
    "sg:province":"MB",
    "wof:name":"St Andrew's College",
    "wof:placetype":"venue"
},
  "geometry": {"coordinates":[-97.140289,49.810364],"type":"Point"}
}