{
  "type": "Feature",
  "properties": {
    "addr:full":"Sudbury ON P3E 5S1",
    "addr:postcode":"p3e 5s1",
    "iso:country":"CA",
    "sg:city":"Sudbury",
    "sg:classifiers":[
        {
            "category":"Banks & Credit Unions",
            "subcategory":"Bank",
            "type":"Services"
        }
    ],
    "sg:phone":"+1 705 523 1321",
    "sg:postcode":"P3E 5S1",
    "sg:province":"ON",
    "sg:tags":[
        "cashing",
        "loan",
        "check"
    ],
    "wof:name":"Instaloans Financial Solution",
    "wof:placetype":"venue"
},
  "geometry": {"coordinates":[-81.0011520386,46.4510765076],"type":"Point"}
}