{
  "type": "Feature",
  "properties": {
    "addr:full":"24 Drummond St Newboro ON K0G 1P0",
    "addr:housenumber":"24",
    "addr:postcode":"k0g 1p0",
    "addr:street":"Drummond St",
    "iso:country":"CA",
    "sg:address":"24 Drummond St",
    "sg:city":"Newboro",
    "sg:classifiers":[
        {
            "category":"Banks & Credit Unions",
            "subcategory":"Bank",
            "type":"Services"
        }
    ],
    "sg:phone":"+1 613 272 2600",
    "sg:postcode":"K0G 1P0",
    "sg:province":"ON",
    "wof:name":"Royal Bank Financial Group",
    "wof:placetype":"venue"
},
  "geometry": {"coordinates":[-76.317024231,44.6521072388],"type":"Point"}
}