{
  "type": "Feature",
  "properties": {
    "addr:full":"Lloydminster AB T9V 1N7",
    "addr:postcode":"t9v 1n7",
    "iso:country":"CA",
    "sg:city":"Lloydminster",
    "sg:classifiers":[
        {
            "category":"Health Services",
            "subcategory":"Clinic",
            "type":"Services"
        }
    ],
    "sg:phone":"+1 780 871 2895",
    "sg:postcode":"T9V 1N7",
    "sg:province":"AB",
    "sg:tags":[
        "herbalist"
    ],
    "wof:name":"Shen Herbals Inc",
    "wof:placetype":"venue"
},
  "geometry": {"coordinates":[-110.017082,53.26429],"type":"Point"}
}