{
  "type": "Feature",
  "properties": {
    "iso:country":"CA",
    "sg:city":"Bowen Island",
    "sg:classifiers":[
        {
            "category":"Shopping",
            "subcategory":"Pharmacy",
            "type":"Retail Goods"
        }
    ],
    "sg:phone":"+1 604 947 0766",
    "sg:postcode":"V0N 1G0",
    "sg:province":"BC",
    "wof:name":"Cates Pharmacy",
    "wof:placetype":"venue"
},
  "geometry": {"coordinates":[-123.337989807,49.3796691895],"type":"Point"}
}