{
  "type": "Feature",
  "properties": {
    "addr:full":"Port Coquitlam BC V3C 5W9",
    "addr:postcode":"v3c 5w9",
    "iso:country":"CA",
    "sg:city":"Port Coquitlam",
    "sg:classifiers":[
        {
            "category":"Manufacturing",
            "subcategory":"Food",
            "type":"Manufacturing & Wholesale Goods"
        }
    ],
    "sg:phone":"+1 604 945 4600",
    "sg:postcode":"V3C 5W9",
    "sg:province":"BC",
    "sg:tags":[
        "grocer",
        "product",
        "manufacturer"
    ],
    "wof:name":"Pacific Blends Ltd",
    "wof:placetype":"venue"
},
  "geometry": {"coordinates":[-122.761002,49.238811],"type":"Point"}
}