{
  "type": "Feature",
  "properties": {
    "addr:full":"Sudbury ON P3E 2L5",
    "addr:postcode":"p3e 2l5",
    "iso:country":"CA",
    "sg:city":"Sudbury",
    "sg:classifiers":[
        {
            "category":"Social Services",
            "type":"Services"
        }
    ],
    "sg:phone":"+1 705 522 4679",
    "sg:postcode":"P3E 2L5",
    "sg:province":"ON",
    "sg:tags":[
        "counselor",
        "marriage",
        "family"
    ],
    "wof:name":"Dan Keaney & Assoc",
    "wof:placetype":"venue"
},
  "geometry": {"coordinates":[-81.01263400000001,46.460346],"type":"Point"}
}