{
  "type": "Feature",
  "properties": {
    "iso:country":"CA",
    "sg:address":"9721 West Saanich Rd",
    "sg:city":"North Saanich",
    "sg:classifiers":[
        {
            "category":"Wholesale",
            "subcategory":"Plants",
            "type":"Manufacturing & Wholesale Goods"
        }
    ],
    "sg:phone":"+1 250 656 4162",
    "sg:postcode":"V8L 5T5",
    "sg:province":"BC",
    "sg:tags":[
        "nursery",
        "tree"
    ],
    "wof:name":"Arbutus Grove Nursery",
    "wof:placetype":"venue"
},
  "geometry": {"coordinates":[-123.45595550500001,48.6461906433],"type":"Point"}
}