{
  "type": "Feature",
  "properties": {
    "addr:full":"201 Main St Melfort SK S0E 1A0",
    "addr:housenumber":"201",
    "addr:postcode":"s0e 1a0",
    "addr:street":"Main St",
    "iso:country":"CA",
    "sg:address":"201 Main St",
    "sg:city":"Melfort",
    "sg:classifiers":[
        {
            "category":"Banks & Credit Unions",
            "subcategory":"Bank",
            "type":"Services"
        }
    ],
    "sg:phone":"+1 306 752 2863",
    "sg:postcode":"S0E 1A0",
    "sg:province":"SK",
    "wof:name":"Royal Bank Financial Group",
    "wof:placetype":"venue"
},
  "geometry": {"coordinates":[-104.61084,52.860657],"type":"Point"}
}