{
  "type": "Feature",
  "properties": {
    "addr:full":"46 Ferguson Ave S Hamilton ON L8N 2M5",
    "addr:housenumber":"46",
    "addr:postcode":"l8n 2m5",
    "addr:street":"Ferguson Ave S",
    "iso:country":"CA",
    "sg:address":"46 Ferguson Ave S",
    "sg:city":"Hamilton",
    "sg:classifiers":[
        {
            "category":"Wholesale",
            "subcategory":"Machinery & Supplies",
            "type":"Manufacturing & Wholesale Goods"
        }
    ],
    "sg:phone":"+1 905 527 4533",
    "sg:postcode":"L8N 2M5",
    "sg:province":"ON",
    "sg:tags":[
        "janitor"
    ],
    "wof:name":"Radigan Brothers Ltd",
    "wof:placetype":"venue"
},
  "geometry": {"coordinates":[-79.86278533940001,43.2530784607],"type":"Point"}
}