{
  "type": "Feature",
  "properties": {
    "addr:full":"Prescott ON K0E 1T0",
    "addr:postcode":"k0e 1t0",
    "iso:country":"CA",
    "sg:city":"Prescott",
    "sg:classifiers":[
        {
            "category":"Freight",
            "type":"Transportation"
        }
    ],
    "sg:phone":"+1 613 925 0606",
    "sg:postcode":"K0E 1T0",
    "sg:province":"ON",
    "sg:tags":[
        "cartage"
    ],
    "wof:name":"Champagne Cartage",
    "wof:placetype":"venue"
},
  "geometry": {"coordinates":[-75.5184173584,44.7094192505],"type":"Point"}
}