{
  "type": "Feature",
  "properties": {
    "iso:country":"CA",
    "sg:address":"131 Rue Saint-Ephrem",
    "sg:city":"Chicoutimi",
    "sg:classifiers":[
        {
            "category":"Home & Garden",
            "subcategory":"Garden Supply",
            "type":"Retail Goods"
        }
    ],
    "sg:phone":"+1 418 549 8887",
    "sg:postcode":"G7G 2W2",
    "sg:province":"QC",
    "sg:tags":[
        "pump"
    ],
    "wof:name":"Centre DE Svc Gdl Inc",
    "wof:placetype":"venue"
},
  "geometry": {"coordinates":[-71.0637130737,48.4374046326],"type":"Point"}
}