{
  "type": "Feature",
  "properties": {
    "addr:full":"296 Welland Ave St Catharines ON L2R 7L9",
    "addr:housenumber":"296",
    "addr:postcode":"l2r 7l9",
    "addr:street":"Welland Ave",
    "iso:country":"CA",
    "sg:address":"296 Welland Ave",
    "sg:city":"St Catharines",
    "sg:classifiers":[
        {
            "category":"Health Services",
            "subcategory":"Health Practitioner",
            "type":"Services"
        }
    ],
    "sg:phone":"+1 905 684 4934",
    "sg:postcode":"L2R 7L9",
    "sg:province":"ON",
    "sg:tags":[
        "physician"
    ],
    "wof:name":"Naturomediccom",
    "wof:placetype":"venue"
},
  "geometry": {"coordinates":[-79.2296218872,43.1693611145],"type":"Point"}
}