{
  "type": "Feature",
  "properties": {
    "addr:full":"5145 Rue Rideau Quebec QC G2E 5H5",
    "addr:housenumber":"5145",
    "addr:postcode":"g2e 5h5",
    "addr:street":"Rue Rideau",
    "iso:country":"CA",
    "sg:address":"5145 Rue Rideau",
    "sg:city":"Quebec",
    "sg:classifiers":[
        {
            "category":"Wholesale",
            "subcategory":"Electrical",
            "type":"Manufacturing & Wholesale Goods"
        }
    ],
    "sg:phone":"+1 418 872 1000",
    "sg:postcode":"G2E 5H5",
    "sg:province":"QC",
    "sg:tags":[
        "fire",
        "control",
        "alarm",
        "security",
        "system"
    ],
    "wof:name":"Sidelco Inc",
    "wof:placetype":"venue"
},
  "geometry": {"coordinates":[-71.3268356323,46.7973899841],"type":"Point"}
}