{
  "type": "Feature",
  "properties": {
    "addr:full":"Vancouver BC V6A 3G3",
    "addr:postcode":"v6a 3g3",
    "iso:country":"CA",
    "sg:city":"Vancouver",
    "sg:classifiers":[
        {
            "category":"Government",
            "subcategory":"Office",
            "type":"Public Place"
        }
    ],
    "sg:phone":"+1 604 253 4401",
    "sg:postcode":"V6A 3G3",
    "sg:province":"BC",
    "wof:name":"B C Mental Health Svc",
    "wof:placetype":"venue"
},
  "geometry": {"coordinates":[-123.08925600000001,49.281761],"type":"Point"}
}