{
  "type": "Feature",
  "properties": {
    "addr:full":"520 Route 1 Oak Bay NB E3L 3Y6",
    "addr:housenumber":"520",
    "addr:postcode":"e3l 3y6",
    "addr:street":"Route 1",
    "iso:country":"CA",
    "sg:address":"520 Route 1",
    "sg:city":"Oak Bay",
    "sg:classifiers":[
        {
            "category":"Freight",
            "type":"Transportation"
        }
    ],
    "sg:phone":"+1 506 466 3449",
    "sg:postcode":"E3L 3Y6",
    "sg:province":"NB",
    "sg:tags":[
        "trucking"
    ],
    "wof:name":"Milltown Trucking CO Ltd",
    "wof:placetype":"venue"
},
  "geometry": {"coordinates":[-67.1998672485,45.2187309265],"type":"Point"}
}