{
  "type": "Feature",
  "properties": {
    "addr:full":"10003 110 Ave Fort St John BC V1J 6M7",
    "addr:housenumber":"10003",
    "addr:postcode":"v1j 6m7",
    "addr:street":"110 Ave",
    "iso:country":"CA",
    "sg:address":"10003 110 Ave",
    "sg:city":"Fort St John",
    "sg:classifiers":[
        {
            "category":"Government",
            "subcategory":"Office",
            "type":"Public Place"
        }
    ],
    "sg:phone":"+1 250 787 3225",
    "sg:postcode":"V1J 6M7",
    "sg:province":"BC",
    "wof:name":"B C Conservation Officer Svc",
    "wof:placetype":"venue"
},
  "geometry": {"coordinates":[-120.84786200000001,56.255116],"type":"Point"}
}