{
  "type": "Feature",
  "properties": {
    "addr:full":"Quebec QC G1N 3N8",
    "addr:postcode":"g1n 3n8",
    "iso:country":"CA",
    "sg:city":"Quebec",
    "sg:classifiers":[
        {
            "category":"Organizations",
            "subcategory":"Professional Association",
            "type":"Services"
        }
    ],
    "sg:phone":"+1 418 687 4121",
    "sg:postcode":"G1N 3N8",
    "sg:province":"QC",
    "wof:name":"Acq Region DE Quebec",
    "wof:placetype":"venue"
},
  "geometry": {"coordinates":[-71.24603271479999,46.8046417236],"type":"Point"}
}