{
  "type": "Feature",
  "properties": {
    "addr:full":"2050 Rue Gardenvale Saint-Bruno QC J3V 2X1",
    "addr:housenumber":"2050",
    "addr:postcode":"j3v 2x1",
    "addr:street":"Rue Gardenvale",
    "iso:country":"CA",
    "sg:address":"2050 Rue Gardenvale",
    "sg:city":"Saint-Bruno",
    "sg:classifiers":[
        {
            "category":"Wholesale",
            "subcategory":"Toys & Hobbies",
            "type":"Manufacturing & Wholesale Goods"
        }
    ],
    "sg:phone":"+1 450 653 7555",
    "sg:postcode":"J3V 2X1",
    "sg:province":"QC",
    "sg:tags":[
        "firework"
    ],
    "wof:name":"Artificiers Daigneault Marcel",
    "wof:placetype":"venue"
},
  "geometry": {"coordinates":[-71.675522,48.471771],"type":"Point"}
}