{
  "type": "Feature",
  "properties": {
    "addr:full":"Regina SK S4N 6H4",
    "addr:postcode":"s4n 6h4",
    "iso:country":"CA",
    "sg:city":"Regina",
    "sg:classifiers":[
        {
            "category":"Building & Trades",
            "subcategory":"Construction",
            "type":"Services"
        }
    ],
    "sg:phone":"+1 306 585 1967",
    "sg:postcode":"S4N 6H4",
    "sg:province":"SK",
    "sg:tags":[
        "general",
        "contractor"
    ],
    "wof:name":"Ccr Construction Ltd",
    "wof:placetype":"venue"
},
  "geometry": {"coordinates":[-104.58197784399999,50.4532661438],"type":"Point"}
}