{
  "type": "Feature",
  "properties": {
    "addr:full":"194 Lakeshore Rd E Oakville ON L6J 1H6",
    "addr:housenumber":"194",
    "addr:postcode":"l6j 1h6",
    "addr:street":"Lakeshore Rd E",
    "iso:country":"CA",
    "sg:address":"194 Lakeshore Rd E",
    "sg:city":"Oakville",
    "sg:classifiers":[
        {
            "category":"Food & Beverages",
            "subcategory":"Candy",
            "type":"Retail Goods"
        }
    ],
    "sg:phone":"+1 905 339 2100",
    "sg:postcode":"L6J 1H6",
    "sg:province":"ON",
    "sg:tags":[
        "confectionery"
    ],
    "wof:name":"Bernard Callebaut Chocolaterie",
    "wof:placetype":"venue"
},
  "geometry": {"coordinates":[-79.668296814,43.4454727173],"type":"Point"}
}