{
  "type": "Feature",
  "properties": {
    "addr:full":"9943 170 St NW Edmonton AB T5P 4S2",
    "addr:housenumber":"9943",
    "addr:postcode":"t5p 4s2",
    "addr:street":"170 St Nw",
    "iso:country":"CA",
    "sg:address":"9943 170 St NW",
    "sg:city":"Edmonton",
    "sg:classifiers":[
        {
            "category":"Health Services",
            "subcategory":"Doctor",
            "type":"Services"
        }
    ],
    "sg:phone":"+1 780 444 8925",
    "sg:postcode":"T5P 4S2",
    "sg:province":"AB",
    "sg:tags":[
        "dentist"
    ],
    "wof:name":"West Edmonton Dental Care",
    "wof:placetype":"venue"
},
  "geometry": {"coordinates":[-113.614807129,53.5368423462],"type":"Point"}
}