{
  "type": "Feature",
  "properties": {
    "addr:full":"494 Rue Commerciale O Chandler QC G0C 1K0",
    "addr:housenumber":"494",
    "addr:postcode":"g0c 1k0",
    "addr:street":"Rue Commerciale O",
    "iso:country":"CA",
    "sg:address":"494 Rue Commerciale O",
    "sg:city":"Chandler",
    "sg:classifiers":[
        {
            "category":"Education",
            "subcategory":"Special Training",
            "type":"Public Place"
        }
    ],
    "sg:phone":"+1 418 689 6888",
    "sg:postcode":"G0C 1K0",
    "sg:province":"QC",
    "sg:tags":[
        "instruction",
        "driving"
    ],
    "wof:name":"Ecole DE Conduite Pabok",
    "wof:placetype":"venue"
},
  "geometry": {"coordinates":[-64.7005767822,48.3457527161],"type":"Point"}
}