{
  "type": "Feature",
  "properties": {
    "addr:full":"RR 1 Bluevale ON N0G 1G0",
    "addr:postcode":"n0g 1g0",
    "addr:street":"Rr 1 Bluevale",
    "iso:country":"CA",
    "sg:address":"RR 1",
    "sg:city":"Bluevale",
    "sg:classifiers":[
        {
            "category":"Wholesale",
            "subcategory":"Machinery & Supplies",
            "type":"Manufacturing & Wholesale Goods"
        }
    ],
    "sg:phone":"+1 519 335 6770",
    "sg:postcode":"N0G 1G0",
    "sg:province":"ON",
    "sg:tags":[
        "repairing"
    ],
    "wof:name":"Wroxeter Rigging & Fabrication",
    "wof:placetype":"venue"
},
  "geometry": {"coordinates":[-81.25165557859999,43.8579368591],"type":"Point"}
}