{
  "type": "Feature",
  "properties": {
    "addr:full":"850 Lakeshore Rd Niagara on the Lake ON L0S 1J0",
    "addr:housenumber":"850",
    "addr:postcode":"l0s 1j0",
    "addr:street":"Lakeshore Rd;On",
    "iso:country":"CA",
    "sg:address":"850 Lakeshore Rd",
    "sg:city":"Niagara on the Lake",
    "sg:classifiers":[
        {
            "category":"Home & Garden",
            "subcategory":"Garden Supply",
            "type":"Retail Goods"
        }
    ],
    "sg:phone":"+1 905 934 1376",
    "sg:postcode":"L0S 1J0",
    "sg:province":"ON",
    "sg:tags":[
        "nurseryman"
    ],
    "wof:name":"Niagara Holland Nurseries",
    "wof:placetype":"venue"
},
  "geometry": {"coordinates":[-79.15537999999999,43.244083],"type":"Point"}
}