{
  "type": "Feature",
  "properties": {
    "addr:full":"1367 Osprey Dr Ancaster ON L9G 4V5",
    "addr:housenumber":"1367",
    "addr:postcode":"l9g 4v5",
    "addr:street":"Osprey Dr",
    "iso:country":"CA",
    "sg:address":"1367 Osprey Dr",
    "sg:city":"Ancaster",
    "sg:classifiers":[
        {
            "category":"Shopping",
            "subcategory":"Gifts & Souvenirs",
            "type":"Retail Goods"
        }
    ],
    "sg:phone":"+1 905 304 9155",
    "sg:postcode":"L9G 4V5",
    "sg:province":"ON",
    "sg:tags":[
        "equipment",
        "racing",
        "automobile",
        "car",
        "collectible"
    ],
    "wof:name":"Everest Wholesale Sports Cards",
    "wof:placetype":"venue"
},
  "geometry": {"coordinates":[-80.02739699999999,43.189438],"type":"Point"}
}