{
  "type": "Feature",
  "properties": {
    "addr:full":"2658 Gunter Rd Merville BC V0R 2M0",
    "addr:postcode":"2658;v0r 2m0",
    "addr:street":"Gunter Rd",
    "iso:country":"CA",
    "sg:address":"2658 Gunter Rd",
    "sg:city":"Merville",
    "sg:classifiers":[
        {
            "category":"Shopping",
            "subcategory":"Hobbies, Toys, & Games",
            "type":"Retail Goods"
        }
    ],
    "sg:phone":"+1 250 337 5320",
    "sg:postcode":"V0R 2M0",
    "sg:province":"BC",
    "sg:tags":[
        "model",
        "supply"
    ],
    "wof:name":"Flite Supply",
    "wof:placetype":"venue"
},
  "geometry": {"coordinates":[-125.052230835,49.7814064026],"type":"Point"}
}