{
  "type": "Feature",
  "properties": {
    "addr:full":"1408 Highway 8 Stoney Creek ON L8E 5K7",
    "addr:housenumber":"1408",
    "addr:postcode":"l8e 5k7",
    "addr:street":"Highway 8",
    "iso:country":"CA",
    "sg:address":"1408 Highway 8",
    "sg:city":"Stoney Creek",
    "sg:classifiers":[
        {
            "category":"Professional",
            "subcategory":"Management & Consulting",
            "type":"Services"
        }
    ],
    "sg:phone":"+1 905 643 9736",
    "sg:postcode":"L8E 5K7",
    "sg:province":"ON",
    "sg:tags":[
        "consultant",
        "lighting"
    ],
    "wof:name":"Getty Associates",
    "wof:placetype":"venue"
},
  "geometry": {"coordinates":[-79.6898803711,43.2120666504],"type":"Point"}
}