{
  "type": "Feature",
  "properties": {
    "addr:full":"1B Hwy 21 Bayfield ON N0M 1G0",
    "addr:housenumber":"1b",
    "addr:postcode":"n0m 1g0",
    "addr:street":"Hwy 21",
    "iso:country":"CA",
    "sg:address":"1B Hwy 21",
    "sg:city":"Bayfield",
    "sg:classifiers":[
        {
            "category":"Shopping",
            "subcategory":"Discount & Variety Stores",
            "type":"Retail Goods"
        }
    ],
    "sg:phone":"+1 519 565 2688",
    "sg:postcode":"N0M 1G0",
    "sg:province":"ON",
    "wof:name":"Nip & Tuck Variety",
    "wof:placetype":"venue"
},
  "geometry": {"coordinates":[-81.705376,43.575764],"type":"Point"}
}