{
  "type": "Feature",
  "properties": {
    "addr:full":"78 Rue Saint-Pierre Saint-Constant QC J5A 1G3",
    "addr:housenumber":"78",
    "addr:postcode":"j5a 1g3",
    "addr:street":"Rue Saint-Pierre",
    "iso:country":"CA",
    "sg:address":"78 Rue Saint-Pierre",
    "sg:city":"Saint-Constant",
    "sg:classifiers":[
        {
            "category":"Recreation",
            "type":"Entertainment"
        }
    ],
    "sg:phone":"+1 450 638 0908",
    "sg:postcode":"J5A 1G3",
    "sg:province":"QC",
    "sg:tags":[
        "martial",
        "arts",
        "instruction"
    ],
    "wof:name":"Centre DE Karate St Constant",
    "wof:placetype":"venue"
},
  "geometry": {"coordinates":[-73.56424,45.378868],"type":"Point"}
}