{
  "type": "Feature",
  "properties": {
    "addr:full":"14 Rue Montplaisir Victoriaville QC G6T 1N1",
    "addr:housenumber":"14",
    "addr:postcode":"g6t 1n1",
    "addr:street":"Rue Montplaisir",
    "iso:country":"CA",
    "sg:address":"14 Rue Montplaisir",
    "sg:city":"Victoriaville",
    "sg:classifiers":[
        {
            "category":"Building & Trades",
            "subcategory":"Construction",
            "type":"Services"
        }
    ],
    "sg:phone":"+1 819 758 1808",
    "sg:postcode":"G6T 1N1",
    "sg:province":"QC",
    "sg:tags":[
        "excavating",
        "contractor"
    ],
    "wof:name":"Excavation P-P Dusseault",
    "wof:placetype":"venue"
},
  "geometry": {"coordinates":[-72.0203094482,46.0581016541],"type":"Point"}
}