{
  "type": "Feature",
  "properties": {
    "iso:country":"CA",
    "sg:address":"3005 Woodstock Rd",
    "sg:city":"Fredericton",
    "sg:classifiers":[
        {
            "category":"Food & Beverages",
            "subcategory":"Groceries & Convenience Stores",
            "type":"Retail Goods"
        }
    ],
    "sg:phone":"+1 506 450 2080",
    "sg:postcode":"E3C 1R2",
    "sg:province":"NB",
    "sg:tags":[
        "motel",
        "hotel"
    ],
    "wof:name":"Roadside Motel",
    "wof:placetype":"venue"
},
  "geometry": {"coordinates":[-66.757973,45.965103],"type":"Point"}
}