{
  "type": "Feature",
  "properties": {
    "iso:country":"CA",
    "sg:address":"67 Patrick Blvd",
    "sg:city":"North York",
    "sg:classifiers":[
        {
            "category":"Shopping",
            "subcategory":"Bicycles & Sporting Goods",
            "type":"Retail Goods"
        }
    ],
    "sg:phone":"+1 416 493 1896",
    "sg:postcode":"M2J 3K7",
    "sg:province":"ON",
    "wof:name":"Cricket Equipment Supply CO",
    "wof:placetype":"venue"
},
  "geometry": {"coordinates":[-79.32531738279999,43.7773551941],"type":"Point"}
}