{
  "type": "Feature",
  "properties": {
    "addr:full":"5913 Imperial Way Olds AB T4H 1M5",
    "addr:housenumber":"5913",
    "addr:postcode":"t4h 1m5",
    "addr:street":"Imperial Way",
    "iso:country":"CA",
    "sg:address":"5913 Imperial Way",
    "sg:city":"Olds",
    "sg:classifiers":[
        {
            "category":"Professional",
            "subcategory":"Management & Consulting",
            "type":"Services"
        }
    ],
    "sg:phone":"+1 403 507 2444",
    "sg:postcode":"T4H 1M5",
    "sg:province":"AB",
    "sg:tags":[
        "fire",
        "consultant",
        "safety",
        "extinguisher"
    ],
    "wof:name":"Ultimate Safety Alberta",
    "wof:placetype":"venue"
},
  "geometry": {"coordinates":[-114.124275208,51.7960929871],"type":"Point"}
}