{
  "type": "Feature",
  "properties": {
    "iso:country":"CA",
    "sg:address":"960 Rue Saint-Georges",
    "sg:city":"Drummondville",
    "sg:classifiers":[
        {
            "category":"Education",
            "subcategory":"College",
            "type":"Public Place"
        }
    ],
    "sg:phone":"+1 819 478 4671",
    "sg:postcode":"J2C 6A2",
    "sg:province":"QC",
    "sg:tags":[
        "academic",
        "school"
    ],
    "wof:name":"Cegep DE Drummondville",
    "wof:placetype":"venue"
},
  "geometry": {"coordinates":[-72.506798,45.874321],"type":"Point"}
}