{
  "type": "Feature",
  "properties": {
    "iso:country":"CA",
    "sg:address":"3426 Mainway",
    "sg:city":"Burlington",
    "sg:classifiers":[
        {
            "category":"Wholesale",
            "subcategory":"Machinery & Supplies",
            "type":"Manufacturing & Wholesale Goods"
        }
    ],
    "sg:phone":"+1 905 335 5511",
    "sg:postcode":"L7M 1A8",
    "sg:province":"ON",
    "sg:tags":[
        "equipment",
        "hydraulic"
    ],
    "wof:name":"Bosch Rexroth Canada",
    "wof:placetype":"venue"
},
  "geometry": {"coordinates":[-79.798592,43.368683],"type":"Point"}
}