{
  "type": "Feature",
  "properties": {
    "addr:full":"900 the East Mall Etobicoke ON M9B 6K2",
    "addr:housenumber":"900",
    "addr:postcode":"m9b 6k2",
    "addr:street":"The East Mall",
    "iso:country":"CA",
    "sg:address":"900 the East Mall",
    "sg:city":"Etobicoke",
    "sg:classifiers":[
        {
            "category":"Insurance",
            "subcategory":"Insurance Agent",
            "type":"Services"
        }
    ],
    "sg:phone":"+1 416 622 9523",
    "sg:postcode":"M9B 6K2",
    "sg:province":"ON",
    "wof:name":"Marketing Concepts Group Inc",
    "wof:placetype":"venue"
},
  "geometry": {"coordinates":[-79.57266199999999,43.667252],"type":"Point"}
}