{
  "type": "Feature",
  "properties": {
    "iso:country":"CA",
    "sg:address":"6509 Chebucto Rd",
    "sg:city":"Halifax",
    "sg:classifiers":[
        {
            "category":"Personal",
            "subcategory":"Beauty Salon",
            "type":"Services"
        }
    ],
    "sg:phone":"+1 902 454 9222",
    "sg:postcode":"B3L 1L6",
    "sg:province":"NS",
    "wof:name":"Lifestyles Hair Studio Inc",
    "wof:placetype":"venue"
},
  "geometry": {"coordinates":[-63.6054458618,44.6481056213],"type":"Point"}
}