{
  "type": "Feature",
  "properties": {
    "iso:country":"CA",
    "sg:address":"500 Rue DE LA Riviere-Aux-Pins",
    "sg:city":"Boucherville",
    "sg:classifiers":[
        {
            "category":"Recreation",
            "type":"Entertainment"
        }
    ],
    "sg:phone":"+1 450 655 3246",
    "sg:postcode":"J4B 2Z7",
    "sg:province":"QC",
    "sg:tags":[
        "skating",
        "instruction"
    ],
    "wof:name":"Club-Patinage Artistique",
    "wof:placetype":"venue"
},
  "geometry": {"coordinates":[-73.4526596069,45.6038322449],"type":"Point"}
}