{
  "type": "Feature",
  "properties": {
    "addr:full":"5 Water St Parry Sound ON P2A 3A3",
    "addr:housenumber":"5",
    "addr:postcode":"p2a 3a3",
    "addr:street":"Water St",
    "iso:country":"CA",
    "sg:address":"5 Water St",
    "sg:city":"Parry Sound",
    "sg:classifiers":[
        {
            "category":"Retail",
            "subcategory":"Repair Shop",
            "type":"Services"
        }
    ],
    "sg:phone":"+1 705 746 5232",
    "sg:postcode":"P2A 3A3",
    "sg:province":"ON",
    "sg:tags":[
        "automobile",
        "electric"
    ],
    "wof:name":"O'Rourke Auto Electric",
    "wof:placetype":"venue"
},
  "geometry": {"coordinates":[-80.02562,45.351036],"type":"Point"}
}