{
  "type": "Feature",
  "properties": {
    "addr:full":"37829 Highway 41 Pembroke ON K8A 6W4",
    "addr:housenumber":"37829",
    "addr:postcode":"k8a 6w4",
    "addr:street":"Highway 41",
    "iso:country":"CA",
    "sg:address":"37829 Highway 41",
    "sg:city":"Pembroke",
    "sg:classifiers":[
        {
            "category":"Shopping",
            "type":"Retail Goods"
        }
    ],
    "sg:phone":"+1 613 735 2726",
    "sg:postcode":"K8A 6W4",
    "sg:province":"ON",
    "sg:tags":[
        "pet",
        "food",
        "supply"
    ],
    "wof:name":"Van's Pet Food",
    "wof:placetype":"venue"
},
  "geometry": {"coordinates":[-77.112213,45.826481],"type":"Point"}
}