{
  "type": "Feature",
  "properties": {
    "addr:full":"1460 Rue Mazurette Montreal QC H4N 1H2",
    "addr:housenumber":"1460",
    "addr:postcode":"h4n 1h2",
    "addr:street":"Rue Mazurette",
    "iso:country":"CA",
    "sg:address":"1460 Rue Mazurette",
    "sg:city":"Montreal",
    "sg:classifiers":[
        {
            "category":"Professional",
            "subcategory":"Engineering",
            "type":"Services"
        }
    ],
    "sg:phone":"+1 514 385 9962",
    "sg:postcode":"H4N 1H2",
    "sg:province":"QC",
    "sg:tags":[
        "engineer"
    ],
    "wof:name":"Gesco Norex Inc",
    "wof:placetype":"venue"
},
  "geometry": {"coordinates":[-73.6597442627,45.5321388245],"type":"Point"}
}