{
  "type": "Feature",
  "properties": {
    "addr:full":"907 N 10th St Golden BC V0A 1H0",
    "addr:housenumber":"907",
    "addr:postcode":"v0a 1h0",
    "addr:street":"N 10Th St",
    "iso:country":"CA",
    "sg:address":"907 N 10th St",
    "sg:city":"Golden",
    "sg:classifiers":[
        {
            "category":"Building & Trades",
            "subcategory":"Construction",
            "type":"Services"
        }
    ],
    "sg:phone":"+1 250 344 5661",
    "sg:postcode":"V0A 1H0",
    "sg:province":"BC",
    "sg:tags":[
        "general",
        "contractor"
    ],
    "wof:name":"Mertex Construction",
    "wof:placetype":"venue"
},
  "geometry": {"coordinates":[-116.975159,51.307571],"type":"Point"}
}