{
  "type": "Feature",
  "properties": {
    "addr:full":"Kitchener ON N2H 6R2",
    "addr:postcode":"n2h 6r2",
    "iso:country":"CA",
    "sg:city":"Kitchener",
    "sg:classifiers":[
        {
            "category":"Banks & Credit Unions",
            "subcategory":"Bank",
            "type":"Services"
        }
    ],
    "sg:phone":"+1 519 571 6427",
    "sg:postcode":"N2H 6R2",
    "sg:province":"ON",
    "wof:name":"Scotiabank",
    "wof:placetype":"venue"
},
  "geometry": {"coordinates":[-80.485992,43.45134],"type":"Point"}
}