{
  "type": "Feature",
  "properties": {
    "iso:country":"CA",
    "sg:city":"Guelph",
    "sg:classifiers":[
        {
            "category":"Building & Trades",
            "subcategory":"Construction",
            "type":"Services"
        }
    ],
    "sg:phone":"+1 519 824 1418",
    "sg:postcode":"N1H 6H8",
    "sg:province":"ON",
    "sg:tags":[
        "home",
        "improvement"
    ],
    "wof:name":"Royal City Renovations Ltd",
    "wof:placetype":"venue"
},
  "geometry": {"coordinates":[-80.247871,43.544563],"type":"Point"}
}