{
  "type": "Feature",
  "properties": {
    "addr:full":"Sooke BC V0S 1N0",
    "addr:postcode":"v0s 1n0",
    "iso:country":"CA",
    "sg:city":"Sooke",
    "sg:classifiers":[
        {
            "category":"Manufacturing",
            "subcategory":"Printing",
            "type":"Manufacturing & Wholesale Goods"
        }
    ],
    "sg:phone":"+1 250 642 5752",
    "sg:postcode":"V0S 1N0",
    "sg:province":"BC",
    "sg:tags":[
        "newspaper"
    ],
    "wof:name":"Sooke News Mirror",
    "wof:placetype":"venue"
},
  "geometry": {"coordinates":[-123.72468600000001,48.37759],"type":"Point"}
}