{
  "type": "Feature",
  "properties": {
    "iso:country":"CA",
    "sg:address":"2340 Pembina Hwy",
    "sg:city":"Winnipeg",
    "sg:classifiers":[
        {
            "category":"Wholesale",
            "subcategory":"Medical Equipment & Supplies",
            "type":"Manufacturing & Wholesale Goods"
        }
    ],
    "sg:phone":"+1 204 956 6777",
    "sg:postcode":"R3T 2E8",
    "sg:province":"MB",
    "sg:tags":[
        "alarm"
    ],
    "wof:name":"Victoria Lifeline",
    "wof:placetype":"venue"
},
  "geometry": {"coordinates":[-97.1544494629,49.8071556091],"type":"Point"}
}