{
  "type": "Feature",
  "properties": {
    "addr:full":"Vancouver BC V6C 3A8",
    "addr:postcode":"v6c 3a8",
    "iso:country":"CA",
    "sg:city":"Vancouver",
    "sg:classifiers":[
        {
            "category":"Mining & Drilling",
            "type":"Manufacturing & Wholesale Goods"
        }
    ],
    "sg:phone":"+1 604 687 6600",
    "sg:postcode":"V6C 3A8",
    "sg:province":"BC",
    "sg:tags":[
        "company"
    ],
    "wof:name":"Aurizon Mines Ltd",
    "wof:placetype":"venue"
},
  "geometry": {"coordinates":[-123.11779,49.286404],"type":"Point"}
}