{
  "type": "Feature",
  "properties": {
    "iso:country":"CA",
    "sg:address":"204 Third Ave",
    "sg:city":"Gleichen",
    "sg:classifiers":[
        {
            "category":"Recreation",
            "type":"Entertainment"
        }
    ],
    "sg:phone":"+1 403 734 2224",
    "sg:postcode":"T0J 1N0",
    "sg:province":"AB",
    "sg:tags":[
        "center"
    ],
    "wof:name":"Gleichen & District Community",
    "wof:placetype":"venue"
},
  "geometry": {"coordinates":[-113.05510700000001,50.866627],"type":"Point"}
}