{
  "type": "Feature",
  "properties": {
    "addr:full":"3005 Ch Miletta Canton Magog QC J1X 5R9",
    "addr:postcode":"3005;j1x 5r9",
    "addr:street":"Ch Miletta Canton",
    "iso:country":"CA",
    "sg:address":"3005 Ch Miletta",
    "sg:city":"Canton Magog",
    "sg:classifiers":[
        {
            "category":"Restaurant",
            "type":"Food & Drink"
        }
    ],
    "sg:phone":"+1 819 847 4091",
    "sg:postcode":"J1X 5R9",
    "sg:province":"QC",
    "wof:name":"Ranch Du Spaghetti & Plus",
    "wof:placetype":"venue"
},
  "geometry": {"coordinates":[-72.21594238279999,45.2905807495],"type":"Point"}
}