{
  "type": "Feature",
  "properties": {
    "addr:full":"2273 Dundas St W Toronto ON M6R 1X6",
    "addr:housenumber":"2273",
    "addr:postcode":"m6r 1x6",
    "addr:street":"Dundas St W",
    "iso:country":"CA",
    "sg:address":"2273 Dundas St W",
    "sg:city":"Toronto",
    "sg:classifiers":[
        {
            "category":"Real Estate",
            "subcategory":"Real Estate Agent",
            "type":"Services"
        }
    ],
    "sg:phone":"+1 416 534 3511",
    "sg:postcode":"M6R 1X6",
    "sg:province":"ON",
    "wof:name":"Go West Realty Ltd",
    "wof:placetype":"venue"
},
  "geometry": {"coordinates":[-79.45230100000001,43.655067],"type":"Point"}
}