{
  "type": "Feature",
  "properties": {
    "addr:full":"905 Queen St W Toronto ON M6J 1G5",
    "addr:housenumber":"905",
    "addr:postcode":"m6j 1g5",
    "addr:street":"Queen St W",
    "iso:country":"CA",
    "sg:address":"905 Queen St W",
    "sg:city":"Toronto",
    "sg:classifiers":[
        {
            "category":"Real Estate",
            "subcategory":"Developer",
            "type":"Services"
        }
    ],
    "sg:phone":"+1 416 703 5025",
    "sg:postcode":"M6J 1G5",
    "sg:province":"ON",
    "wof:name":"Trinity Park Lofts",
    "wof:placetype":"venue"
},
  "geometry": {"coordinates":[-79.412216,43.645393],"type":"Point"}
}