{
  "type": "Feature",
  "properties": {
    "addr:full":"Burnaby BC V5J 4R6",
    "addr:postcode":"v5j 4r6",
    "iso:country":"CA",
    "sg:city":"Burnaby",
    "sg:classifiers":[
        {
            "category":"Retail",
            "subcategory":"Auto Repair",
            "type":"Services"
        }
    ],
    "sg:phone":"+1 604 438 1001",
    "sg:postcode":"V5J 4R6",
    "sg:province":"BC",
    "sg:tags":[
        "repairing",
        "automobile"
    ],
    "wof:name":"Auto Experts Svc Inc",
    "wof:placetype":"venue"
},
  "geometry": {"coordinates":[-122.98004899999999,49.220539],"type":"Point"}
}