{
  "type": "Feature",
  "properties": {
    "addr:full":"3131 Bayview Ave North York ON M2K 1G2",
    "addr:housenumber":"3131",
    "addr:postcode":"m2k 1g2",
    "addr:street":"Bayview Ave",
    "iso:country":"CA",
    "sg:address":"3131 Bayview Ave",
    "sg:city":"North York",
    "sg:classifiers":[
        {
            "category":"Freight",
            "type":"Transportation"
        }
    ],
    "sg:phone":"+1 416 221 1879",
    "sg:postcode":"M2K 1G2",
    "sg:province":"ON",
    "wof:name":"Mego Holdings Ltd",
    "wof:placetype":"venue"
},
  "geometry": {"coordinates":[-79.39130401609999,43.7818260193],"type":"Point"}
}