{
  "type": "Feature",
  "properties": {
    "addr:full":"Sherwood Park AB T8A 4E3",
    "addr:postcode":"t8a 4e3",
    "iso:country":"CA",
    "sg:city":"Sherwood Park",
    "sg:classifiers":[
        {
            "category":"Professional",
            "subcategory":"Management & Consulting",
            "type":"Services"
        }
    ],
    "sg:phone":"+1 780 467 5511",
    "sg:postcode":"T8A 4E3",
    "sg:province":"AB",
    "sg:tags":[
        "consultant",
        "educational"
    ],
    "wof:name":"Home Education Exchange",
    "wof:placetype":"venue"
},
  "geometry": {"coordinates":[-113.320564,53.53656],"type":"Point"}
}