{
  "type": "Feature",
  "properties": {
    "addr:full":"133 Redcoat Dr Eastend SK S0N 0T0",
    "addr:housenumber":"133",
    "addr:postcode":"s0n 0t0",
    "addr:street":"Redcoat Dr",
    "iso:country":"CA",
    "sg:address":"133 Redcoat Dr",
    "sg:city":"Eastend",
    "sg:classifiers":[
        {
            "category":"Organizations",
            "subcategory":"Religious Organization",
            "type":"Services"
        }
    ],
    "sg:phone":"+1 306 295 3668",
    "sg:postcode":"S0N 0T0",
    "sg:province":"SK",
    "sg:tags":[
        "church"
    ],
    "wof:name":"Faith Christian Fellowship",
    "wof:placetype":"venue"
},
  "geometry": {"coordinates":[-108.82870483400001,49.5136566162],"type":"Point"}
}