{
  "type": "Feature",
  "properties": {
    "addr:full":"Pincher Creek AB T0K 1W0",
    "addr:postcode":"t0k 1w0",
    "iso:country":"CA",
    "sg:city":"Pincher Creek",
    "sg:classifiers":[
        {
            "category":"Travel",
            "subcategory":"Campground",
            "type":"Entertainment"
        }
    ],
    "sg:phone":"+1 403 627 2033",
    "sg:postcode":"T0K 1W0",
    "sg:province":"AB",
    "wof:name":"Sleepy Hollow Campground",
    "wof:placetype":"venue"
},
  "geometry": {"coordinates":[-113.936637878,49.4843711853],"type":"Point"}
}