{
  "type": "Feature",
  "properties": {
    "addr:full":"185 Principale Sainte-Sabine QC J0J 2B0",
    "addr:housenumber":"185",
    "addr:postcode":"j0j 2b0",
    "addr:street":"Principale",
    "iso:country":"CA",
    "sg:address":"185 Principale",
    "sg:city":"Sainte-Sabine",
    "sg:classifiers":[
        {
            "category":"Government",
            "subcategory":"Office",
            "type":"Public Place"
        }
    ],
    "sg:phone":"+1 450 293 7686",
    "sg:postcode":"J0J 2B0",
    "sg:province":"QC",
    "sg:tags":[
        "village"
    ],
    "wof:name":"Ste-Sabine Municipalite Ofc",
    "wof:placetype":"venue"
},
  "geometry": {"coordinates":[-73.02010300000001,45.229172],"type":"Point"}
}