{
  "type": "Feature",
  "properties": {
    "addr:full":"9 Freeman St Middleton NS B0S 1P0",
    "addr:housenumber":"9",
    "addr:postcode":"b0s 1p0",
    "addr:street":"Freeman St",
    "iso:country":"CA",
    "sg:address":"9 Freeman St",
    "sg:city":"Middleton",
    "sg:classifiers":[
        {
            "category":"Retail",
            "subcategory":"Car Wash",
            "type":"Services"
        }
    ],
    "sg:phone":"+1 902 825 1695",
    "sg:postcode":"B0S 1P0",
    "sg:province":"NS",
    "sg:tags":[
        "polishing",
        "washing"
    ],
    "wof:name":"Middleton Car Wash",
    "wof:placetype":"venue"
},
  "geometry": {"coordinates":[-65.08414500000001,44.941582],"type":"Point"}
}