{
  "type": "Feature",
  "properties": {
    "addr:full":"3501 35 St Whitecourt AB T7S 1P2",
    "addr:housenumber":"3501",
    "addr:postcode":"t7s 1p2",
    "addr:street":"35 St",
    "iso:country":"CA",
    "sg:address":"3501 35 St",
    "sg:city":"Whitecourt",
    "sg:classifiers":[
        {
            "category":"Home & Garden",
            "subcategory":"Building Materials",
            "type":"Retail Goods"
        }
    ],
    "sg:phone":"+1 780 778 4404",
    "sg:postcode":"T7S 1P2",
    "sg:province":"AB",
    "sg:tags":[
        "hardware"
    ],
    "wof:name":"Whitecourt Home Building Ctr",
    "wof:placetype":"venue"
},
  "geometry": {"coordinates":[-115.651641846,54.1216278076],"type":"Point"}
}