{
  "type": "Feature",
  "properties": {
    "addr:full":"57 Craigleigh Cres Brampton ON L6T 2E3",
    "addr:housenumber":"57",
    "addr:postcode":"l6t 2e3",
    "addr:street":"Craigleigh Cres",
    "iso:country":"CA",
    "sg:address":"57 Craigleigh Cres",
    "sg:city":"Brampton",
    "sg:classifiers":[
        {
            "category":"Professional",
            "subcategory":"Art Services",
            "type":"Services"
        }
    ],
    "sg:phone":"+1 905 789 1213",
    "sg:postcode":"L6T 2E3",
    "sg:province":"ON",
    "sg:tags":[
        "graphic",
        "designer"
    ],
    "wof:name":"Archon Design & Communication",
    "wof:placetype":"venue"
},
  "geometry": {"coordinates":[-79.711868,43.718338],"type":"Point"}
}