{
  "type": "Feature",
  "properties": {
    "addr:full":"112 Duke St Miramichi NB E1N 1H2",
    "addr:housenumber":"112",
    "addr:postcode":"e1n 1h2",
    "addr:street":"Duke St",
    "iso:country":"CA",
    "sg:address":"112 Duke St",
    "sg:city":"Miramichi",
    "sg:classifiers":[
        {
            "category":"Personal",
            "subcategory":"Beauty Salon",
            "type":"Services"
        }
    ],
    "sg:phone":"+1 506 778 8117",
    "sg:postcode":"E1N 1H2",
    "sg:province":"NB",
    "wof:name":"Brenda's Creative Hair Design",
    "wof:placetype":"venue"
},
  "geometry": {"coordinates":[-65.46985599999999,47.028828],"type":"Point"}
}