{
  "type": "Feature",
  "properties": {
    "addr:full":"3144 Gregoire Rd Russell ON K4R 1E5",
    "addr:housenumber":"3144",
    "addr:postcode":"k4r 1e5",
    "addr:street":"Gregoire Rd",
    "iso:country":"CA",
    "sg:address":"3144 Gregoire Rd",
    "sg:city":"Russell",
    "sg:classifiers":[
        {
            "category":"Wholesale",
            "subcategory":"Scrap",
            "type":"Manufacturing & Wholesale Goods"
        }
    ],
    "sg:phone":"+1 613 445 3610",
    "sg:postcode":"K4R 1E5",
    "sg:province":"ON",
    "sg:tags":[
        "recycling",
        "center"
    ],
    "wof:name":"Haycore Canada Inc",
    "wof:placetype":"venue"
},
  "geometry": {"coordinates":[-75.396477,45.25478],"type":"Point"}
}