{
  "type": "Feature",
  "properties": {
    "iso:country":"CA",
    "sg:address":"71 1E Av O",
    "sg:city":"Amos",
    "sg:classifiers":[
        {
            "category":"Personal",
            "subcategory":"Beauty Salon",
            "type":"Services"
        }
    ],
    "sg:phone":"+1 819 732 0022",
    "sg:postcode":"J9T 1T7",
    "sg:province":"QC",
    "wof:name":"Centre Multi-Beaute",
    "wof:placetype":"venue"
},
  "geometry": {"coordinates":[-78.11419677729999,48.572052002],"type":"Point"}
}