{
  "type": "Feature",
  "properties": {
    "addr:full":"15895 Mckenzie Lake Way SE Calgary AB T2Z 2H5",
    "addr:housenumber":"15895",
    "addr:postcode":"t2z 2h5",
    "addr:street":"Mckenzie Lake Way Se",
    "iso:country":"CA",
    "sg:address":"15895 Mckenzie Lake Way SE",
    "sg:city":"Calgary",
    "sg:classifiers":[
        {
            "category":"Wholesale",
            "subcategory":"Durable Goods & Equipment",
            "type":"Manufacturing & Wholesale Goods"
        }
    ],
    "sg:phone":"+1 403 279 7298",
    "sg:postcode":"T2Z 2H5",
    "sg:province":"AB",
    "sg:tags":[
        "representative",
        "manufacturer"
    ],
    "wof:name":"Maaxam Group Inc",
    "wof:placetype":"venue"
},
  "geometry": {"coordinates":[-113.97854599999999,50.911346],"type":"Point"}
}