{
  "type": "Feature",
  "properties": {
    "addr:full":"970 Paramount Dr Stoney Creek ON L8J 1Y2",
    "addr:housenumber":"970",
    "addr:postcode":"l8j 1y2",
    "addr:street":"Paramount Dr",
    "iso:country":"CA",
    "sg:address":"970 Paramount Dr",
    "sg:city":"Stoney Creek",
    "sg:classifiers":[
        {
            "category":"Arena",
            "subcategory":"Sports Club",
            "type":"Entertainment"
        }
    ],
    "sg:phone":"+1 905 573 3600",
    "sg:postcode":"L8J 1Y2",
    "sg:province":"ON",
    "sg:tags":[
        "athletic",
        "fields",
        "stadium",
        "government"
    ],
    "wof:name":"Stoney Creek Valley Park Arena",
    "wof:placetype":"venue"
},
  "geometry": {"coordinates":[-79.79631000000001,43.194698],"type":"Point"}
}