{
  "type": "Feature",
  "properties": {
    "addr:full":"3793 Rue Sainte-Cecile Jonquiere QC G7X 2V3",
    "addr:housenumber":"3793",
    "addr:postcode":"g7x 2v3",
    "addr:street":"Rue Sainte-Cecile",
    "iso:country":"CA",
    "sg:address":"3793 Rue Sainte-Cecile",
    "sg:city":"Jonquiere",
    "sg:classifiers":[
        {
            "category":"Professional",
            "subcategory":"Accounting & Tax Preparation",
            "type":"Services"
        }
    ],
    "sg:phone":"+1 418 695 0078",
    "sg:postcode":"G7X 2V3",
    "sg:province":"QC",
    "sg:tags":[
        "bookkeeping",
        "general"
    ],
    "wof:name":"Arseneault, Alain",
    "wof:placetype":"venue"
},
  "geometry": {"coordinates":[-71.245789,48.415901],"type":"Point"}
}