{
  "type": "Feature",
  "properties": {
    "addr:full":"50 Baywood Rd Etobicoke ON M9V 3Z3",
    "addr:housenumber":"50",
    "addr:postcode":"m9v 3z3",
    "addr:street":"Baywood Rd",
    "iso:country":"CA",
    "sg:address":"50 Baywood Rd",
    "sg:city":"Etobicoke",
    "sg:classifiers":[
        {
            "category":"Real Estate",
            "subcategory":"Real Estate Agent",
            "type":"Services"
        }
    ],
    "sg:phone":"+1 416 741 1319",
    "sg:postcode":"M9V 3Z3",
    "sg:province":"ON",
    "sg:tags":[
        "management"
    ],
    "wof:name":"Dalco Holding Corp",
    "wof:placetype":"venue"
},
  "geometry": {"coordinates":[-79.60656738279999,43.7474021912],"type":"Point"}
}