{
  "type": "Feature",
  "properties": {
    "iso:country":"CA",
    "sg:address":"28 Esplanade St",
    "sg:city":"Truro",
    "sg:classifiers":[
        {
            "category":"Government",
            "subcategory":"Office",
            "type":"Public Place"
        }
    ],
    "sg:phone":"+1 902 893 2455",
    "sg:postcode":"B2N 2K3",
    "sg:province":"NS",
    "wof:name":"Casey, Bill",
    "wof:placetype":"venue"
},
  "geometry": {"coordinates":[-63.2777557373,45.3623466492],"type":"Point"}
}