{
  "type": "Feature",
  "properties": {
    "addr:full":"Scarborough ON M1K 5J1",
    "addr:postcode":"m1k 5j1",
    "iso:country":"CA",
    "sg:city":"Scarborough",
    "sg:classifiers":[
        {
            "category":"Personal",
            "subcategory":"Beauty Salon",
            "type":"Services"
        }
    ],
    "sg:phone":"+1 416 266 1789",
    "sg:postcode":"M1K 5J1",
    "sg:province":"ON",
    "wof:name":"Nails Express",
    "wof:placetype":"venue"
},
  "geometry": {"coordinates":[-79.256935,43.73473],"type":"Point"}
}