{
  "type": "Feature",
  "properties": {
    "addr:full":"310 Mcnaughton Ave W Chatham ON N7L 1R9",
    "addr:housenumber":"310",
    "addr:postcode":"n7l 1r9",
    "addr:street":"Mcnaughton Ave W",
    "iso:country":"CA",
    "sg:address":"310 Mcnaughton Ave W",
    "sg:city":"Chatham",
    "sg:classifiers":[
        {
            "category":"Organizations",
            "subcategory":"Religious Organization",
            "type":"Services"
        }
    ],
    "sg:phone":"+1 519 352 1240",
    "sg:postcode":"N7L 1R9",
    "sg:province":"ON",
    "sg:tags":[
        "church"
    ],
    "wof:name":"St James Presbyterian Church",
    "wof:placetype":"venue"
},
  "geometry": {"coordinates":[-82.21038799999999,42.407692],"type":"Point"}
}