{
  "type": "Feature",
  "properties": {
    "iso:country":"CA",
    "sg:address":"555 Pratt Rd",
    "sg:city":"Gibsons",
    "sg:classifiers":[
        {
            "category":"Freight",
            "type":"Transportation"
        }
    ],
    "sg:phone":"+1 604 886 7212",
    "sg:postcode":"V0N 1V4",
    "sg:province":"BC",
    "sg:tags":[
        "trucking"
    ],
    "wof:name":"Youdell Trucking",
    "wof:placetype":"venue"
},
  "geometry": {"coordinates":[-123.503440857,49.4034538269],"type":"Point"}
}