{
  "type": "Feature",
  "properties": {
    "addr:full":"600 113E Rue Shawinigan-Sud QC G9P 2W7",
    "addr:housenumber":"600",
    "addr:postcode":"g9p 2w7",
    "addr:street":"113E Rue Shawinigan-Sud",
    "iso:country":"CA",
    "sg:address":"600 113E Rue",
    "sg:city":"Shawinigan-Sud",
    "sg:classifiers":[
        {
            "category":"Organizations",
            "subcategory":"Professional Association",
            "type":"Services"
        }
    ],
    "sg:phone":"+1 819 536 4785",
    "sg:postcode":"G9P 2W7",
    "sg:province":"QC",
    "wof:name":"Club DE L'Age D'Or-Ste-Jeanne",
    "wof:placetype":"venue"
},
  "geometry": {"coordinates":[-72.75188446040001,46.5231742859],"type":"Point"}
}