{
  "type": "Feature",
  "properties": {
    "iso:country":"CA",
    "sg:address":"50 Anchor Way",
    "sg:city":"Nanaimo",
    "sg:classifiers":[
        {
            "category":"Bars & Pubs",
            "type":"Food & Drink"
        }
    ],
    "sg:phone":"+1 250 754 3212",
    "sg:postcode":"V9R 7B5",
    "sg:province":"BC",
    "wof:name":"Lighthouse Bistro & Pub",
    "wof:placetype":"venue"
},
  "geometry": {"coordinates":[-123.936012268,49.1677780151],"type":"Point"}
}