{
  "type": "Feature",
  "properties": {
    "iso:country":"CA",
    "sg:address":"154 John St N",
    "sg:city":"Arnprior",
    "sg:classifiers":[
        {
            "category":"Shopping",
            "subcategory":"Gifts & Souvenirs",
            "type":"Retail Goods"
        }
    ],
    "sg:phone":"+1 613 623 7399",
    "sg:postcode":"K7S 2N7",
    "sg:province":"ON",
    "sg:tags":[
        "shop"
    ],
    "wof:name":"Gallery Gift Shop",
    "wof:placetype":"venue"
},
  "geometry": {"coordinates":[-76.353485,45.43462],"type":"Point"}
}