{
  "type": "Feature",
  "properties": {
    "addr:full":"Burton School Rd Burton BC V0G 1E0",
    "addr:postcode":"v0g 1e0",
    "addr:street":"School Rd",
    "iso:country":"CA",
    "sg:address":"Burton School Rd",
    "sg:city":"Burton",
    "sg:classifiers":[
        {
            "category":"Organizations",
            "subcategory":"Religious Organization",
            "type":"Services"
        }
    ],
    "sg:phone":"+1 250 265 3629",
    "sg:postcode":"V0G 1E0",
    "sg:province":"BC",
    "sg:tags":[
        "church"
    ],
    "wof:name":"Burton Full Gospel Church",
    "wof:placetype":"venue"
},
  "geometry": {"coordinates":[-117.877174,49.991631],"type":"Point"}
}