{
  "type": "Feature",
  "properties": {
    "addr:full":"87 Esplanade Sydney NS B1P 1A3",
    "addr:housenumber":"87",
    "addr:postcode":"b1p 1a3",
    "addr:street":"Esplanade",
    "iso:country":"CA",
    "sg:address":"87 Esplanade",
    "sg:city":"Sydney",
    "sg:classifiers":[
        {
            "category":"Museum",
            "type":"Entertainment"
        }
    ],
    "sg:phone":"+1 902 562 8237",
    "sg:postcode":"B1P 1A3",
    "sg:province":"NS",
    "wof:name":"St Patrick's Museum",
    "wof:placetype":"venue"
},
  "geometry": {"coordinates":[-60.1987686157,46.1428756714],"type":"Point"}
}