{
  "type": "Feature",
  "properties": {
    "addr:full":"2430 Royal Windsor Dr Oakville ON L6J 7Y2",
    "addr:housenumber":"2430",
    "addr:postcode":"l6j 7y2",
    "addr:street":"Royal Windsor Dr",
    "iso:country":"CA",
    "sg:address":"2430 Royal Windsor Dr",
    "sg:city":"Oakville",
    "sg:classifiers":[
        {
            "category":"Retail",
            "subcategory":"Auto Repair",
            "type":"Services"
        }
    ],
    "sg:phone":"+1 905 337 8547",
    "sg:postcode":"L6J 7Y2",
    "sg:province":"ON",
    "sg:tags":[
        "truck"
    ],
    "wof:name":"Bsj Equipment Inc",
    "wof:placetype":"venue"
},
  "geometry": {"coordinates":[-79.648483,43.493679],"type":"Point"}
}