{
  "type": "Feature",
  "properties": {
    "iso:country":"CA",
    "sg:address":"20 Sunmount Gdns SE",
    "sg:city":"Calgary",
    "sg:classifiers":[
        {
            "category":"Building & Trades",
            "subcategory":"Construction",
            "type":"Services"
        }
    ],
    "sg:phone":"+1 403 254 9617",
    "sg:postcode":"T2X 2B1",
    "sg:province":"AB",
    "sg:tags":[
        "insulation",
        "heat",
        "contractor"
    ],
    "wof:name":"Hanson Insulation Ltd",
    "wof:placetype":"venue"
},
  "geometry": {"coordinates":[-114.044288635,50.9084892273],"type":"Point"}
}