{
  "type": "Feature",
  "properties": {
    "addr:full":"Saint-Lambert-DE-Lauzon QC G0S 2W0",
    "addr:postcode":"g0s 2w0",
    "iso:country":"CA",
    "sg:city":"Saint-Lambert-DE-Lauzon",
    "sg:classifiers":[
        {
            "category":"Building & Trades",
            "subcategory":"Construction",
            "type":"Services"
        }
    ],
    "sg:phone":"+1 418 889 0670",
    "sg:postcode":"G0S 2W0",
    "sg:province":"QC",
    "sg:tags":[
        "contractor"
    ],
    "wof:name":"L'Equipe Construct'Elle",
    "wof:placetype":"venue"
},
  "geometry": {"coordinates":[-71.2111587524,46.5876846313],"type":"Point"}
}