{
  "type": "Feature",
  "properties": {
    "addr:full":"4921 Wellington Rd Nanaimo BC V9T 2H5",
    "addr:housenumber":"4921",
    "addr:postcode":"v9t 2h5",
    "addr:street":"Wellington Rd",
    "iso:country":"CA",
    "sg:address":"4921 Wellington Rd",
    "sg:city":"Nanaimo",
    "sg:classifiers":[
        {
            "category":"Autos & Motor Vehicles",
            "subcategory":"Automobile Sales",
            "type":"Retail Goods"
        }
    ],
    "sg:phone":"+1 250 751 1221",
    "sg:postcode":"V9T 2H5",
    "sg:province":"BC",
    "sg:tags":[
        "car",
        "dealer"
    ],
    "wof:name":"Harbourview Autohaus Ltd",
    "wof:placetype":"venue"
},
  "geometry": {"coordinates":[-124.029518127,49.2116889954],"type":"Point"}
}