{
  "type": "Feature",
  "properties": {
    "addr:full":"1661 Island Hwy Campbell River BC V9W 2E6",
    "addr:housenumber":"1661",
    "addr:postcode":"v9w 2e6",
    "addr:street":"Island Hwy",
    "iso:country":"CA",
    "sg:address":"1661 Island Hwy",
    "sg:city":"Campbell River",
    "sg:classifiers":[
        {
            "category":"Building & Trades",
            "subcategory":"Plumbing",
            "type":"Services"
        }
    ],
    "sg:phone":"+1 250 286 6424",
    "sg:postcode":"V9W 2E6",
    "sg:province":"BC",
    "sg:tags":[
        "contractor"
    ],
    "wof:name":"Vanisle Plumbing & Heating Ltd",
    "wof:placetype":"venue"
},
  "geometry": {"coordinates":[-125.265785217,50.032409668],"type":"Point"}
}