{
  "type": "Feature",
  "properties": {
    "addr:full":"275 Ontario St Kingston ON K7K 2X5",
    "addr:housenumber":"275",
    "addr:postcode":"k7k 2x5",
    "addr:street":"Ontario St",
    "iso:country":"CA",
    "sg:address":"275 Ontario St",
    "sg:city":"Kingston",
    "sg:classifiers":[
        {
            "category":"Professional",
            "subcategory":"Lawyer & Legal Services",
            "type":"Services"
        }
    ],
    "sg:phone":"+1 613 547 8686",
    "sg:postcode":"K7K 2X5",
    "sg:province":"ON",
    "sg:tags":[
        "attorney"
    ],
    "wof:name":"Smith, Linda L",
    "wof:placetype":"venue"
},
  "geometry": {"coordinates":[-76.47909545900001,44.2317314148],"type":"Point"}
}