{
  "type": "Feature",
  "properties": {
    "addr:full":"1170 Burnhamthorpe Rd W # 1 Mississauga ON L5C 4E6",
    "addr:housenumber":"1170",
    "addr:postcode":"l5c 4e6",
    "addr:street":"Burnhamthorpe Rd W # 1",
    "iso:country":"CA",
    "sg:address":"1170 Burnhamthorpe Rd W # 1",
    "sg:city":"Mississauga",
    "sg:classifiers":[
        {
            "category":"Home & Garden",
            "subcategory":"Carpets & Floor Coverings",
            "type":"Retail Goods"
        }
    ],
    "sg:phone":"+1 905 275 6999",
    "sg:postcode":"L5C 4E6",
    "sg:province":"ON",
    "sg:tags":[
        "dealer",
        "rug"
    ],
    "wof:name":"Super Choice Carpet",
    "wof:placetype":"venue"
},
  "geometry": {"coordinates":[-79.6631698608,43.5690078735],"type":"Point"}
}