{
  "type": "Feature",
  "properties": {
    "iso:country":"CA",
    "sg:address":"1540 Dundas St E",
    "sg:city":"Whitby",
    "sg:classifiers":[
        {
            "category":"Home & Garden",
            "subcategory":"Home Furnishings",
            "type":"Retail Goods"
        }
    ],
    "sg:phone":"+1 905 430 6727",
    "sg:postcode":"L1N 2K7",
    "sg:province":"ON",
    "sg:tags":[
        "venetian",
        "blind"
    ],
    "wof:name":"Blinds To Go",
    "wof:placetype":"venue"
},
  "geometry": {"coordinates":[-78.9152297974,43.8861045837],"type":"Point"}
}