{
  "type": "Feature",
  "properties": {
    "addr:full":"6977 Rue Saint-Hubert Montreal QC H2S 2N1",
    "addr:housenumber":"6977",
    "addr:postcode":"h2s 2n1",
    "addr:street":"Rue Saint-Hubert",
    "iso:country":"CA",
    "sg:address":"6977 Rue Saint-Hubert",
    "sg:city":"Montreal",
    "sg:classifiers":[
        {
            "category":"Shopping",
            "subcategory":"Luggage & Leather Goods",
            "type":"Retail Goods"
        }
    ],
    "sg:phone":"+1 514 271 8080",
    "sg:postcode":"H2S 2N1",
    "sg:province":"QC",
    "sg:tags":[
        "ice",
        "cream"
    ],
    "wof:name":"Assayag, Jean",
    "wof:placetype":"venue"
},
  "geometry": {"coordinates":[-73.610527,45.539677],"type":"Point"}
}