{
  "type": "Feature",
  "properties": {
    "addr:full":"1300 Fennell Ave E Hamilton ON L8T 1T6",
    "addr:housenumber":"1300",
    "addr:postcode":"l8t 1t6",
    "addr:street":"Fennell Ave E",
    "iso:country":"CA",
    "sg:address":"1300 Fennell Ave E",
    "sg:city":"Hamilton",
    "sg:classifiers":[
        {
            "category":"Organizations",
            "subcategory":"Religious Organization",
            "type":"Services"
        }
    ],
    "sg:phone":"+1 905 575 8303",
    "sg:postcode":"L8T 1T6",
    "sg:province":"ON",
    "sg:tags":[
        "church"
    ],
    "wof:name":"Elliott Heights Baptist Church",
    "wof:placetype":"venue"
},
  "geometry": {"coordinates":[-79.8190078735,43.2230796814],"type":"Point"}
}