{
  "type": "Feature",
  "properties": {
    "addr:full":"2057 Rue Bonin Saint-Laurent QC H4M 1A1",
    "addr:housenumber":"2057",
    "addr:postcode":"h4m 1a1",
    "addr:street":"Rue Bonin",
    "iso:country":"CA",
    "sg:address":"2057 Rue Bonin",
    "sg:city":"Saint-Laurent",
    "sg:classifiers":[
        {
            "category":"Local Transit",
            "type":"Transportation"
        }
    ],
    "sg:phone":"+1 514 951 6989",
    "sg:postcode":"H4M 1A1",
    "sg:province":"QC",
    "sg:tags":[
        "limousine"
    ],
    "wof:name":"Limousines Renaissance",
    "wof:placetype":"venue"
},
  "geometry": {"coordinates":[-73.69010900000001,45.507301],"type":"Point"}
}