{
  "type": "Feature",
  "properties": {
    "addr:full":"Richmond BC V6Y 2V9",
    "addr:postcode":"v6y 2v9",
    "iso:country":"CA",
    "sg:city":"Richmond",
    "sg:classifiers":[
        {
            "category":"Restaurant",
            "type":"Food & Drink"
        }
    ],
    "sg:phone":"+1 604 273 9756",
    "sg:postcode":"V6Y 2V9",
    "sg:province":"BC",
    "wof:name":"Tai Yau Yick Restaurant",
    "wof:placetype":"venue"
},
  "geometry": {"coordinates":[-123.134552,49.163734],"type":"Point"}
}