{
  "type": "Feature",
  "properties": {
    "iso:country":"CA",
    "sg:address":"332 Central Ave",
    "sg:city":"London",
    "sg:classifiers":[
        {
            "category":"Banks & Credit Unions",
            "subcategory":"Investment Brokerage",
            "type":"Services"
        }
    ],
    "sg:phone":"+1 519 679 2580",
    "sg:postcode":"N6B 2C8",
    "sg:province":"ON",
    "sg:tags":[
        "consultant",
        "planning",
        "financial"
    ],
    "wof:name":"Dufferin Financial Group",
    "wof:placetype":"venue"
},
  "geometry": {"coordinates":[-81.24617,42.991711],"type":"Point"}
}