{
  "type": "Feature",
  "properties": {
    "addr:full":"Lloydminster AB T9V 2C9",
    "addr:postcode":"t9v 2c9",
    "iso:country":"CA",
    "sg:city":"Lloydminster",
    "sg:classifiers":[
        {
            "category":"Building & Trades",
            "subcategory":"Electrical",
            "type":"Services"
        }
    ],
    "sg:phone":"+1 780 875 6226",
    "sg:postcode":"T9V 2C9",
    "sg:province":"AB",
    "sg:tags":[
        "electric",
        "contractor"
    ],
    "wof:name":"Kondro Electric Ltd",
    "wof:placetype":"venue"
},
  "geometry": {"coordinates":[-110.005661011,53.3002243042],"type":"Point"}
}