{
  "type": "Feature",
  "properties": {
    "addr:full":"1200 Boul Saint-Felicien # 418 Saint-Felicien QC G8K 2N6",
    "addr:housenumber":"1200",
    "addr:postcode":"g8k 2n6",
    "addr:street":"Boul Saint-Felicien # 418 Saint-Felicien",
    "iso:country":"CA",
    "sg:address":"1200 Boul Saint-Felicien # 418",
    "sg:city":"Saint-Felicien",
    "sg:classifiers":[
        {
            "category":"Shopping",
            "type":"Retail Goods"
        }
    ],
    "sg:phone":"+1 418 679 8987",
    "sg:postcode":"G8K 2N6",
    "sg:province":"QC",
    "sg:tags":[
        "pet",
        "shop"
    ],
    "wof:name":"Animalerie Aqua-Plume",
    "wof:placetype":"venue"
},
  "geometry": {"coordinates":[-72.46618700000001,48.650726],"type":"Point"}
}