{
  "type": "Feature",
  "properties": {
    "iso:country":"CA",
    "sg:address":"37 John St",
    "sg:city":"Sturgeon Falls",
    "sg:classifiers":[
        {
            "category":"Food & Beverages",
            "subcategory":"Groceries & Convenience Stores",
            "type":"Retail Goods"
        }
    ],
    "sg:phone":"+1 705 753 1042",
    "sg:postcode":"P2B 1Y2",
    "sg:province":"ON",
    "wof:name":"4 Seasons Variety Store",
    "wof:placetype":"venue"
},
  "geometry": {"coordinates":[-79.9306716919,46.3694725037],"type":"Point"}
}