{
  "type": "Feature",
  "properties": {
    "iso:country":"CA",
    "sg:address":"57 Pembroke St W",
    "sg:city":"Pembroke",
    "sg:classifiers":[
        {
            "category":"Manufacturing",
            "subcategory":"Tools & Machinery",
            "type":"Manufacturing & Wholesale Goods"
        }
    ],
    "sg:phone":"+1 613 735 3859",
    "sg:postcode":"K8A 5M5",
    "sg:province":"ON",
    "sg:tags":[
        "optical"
    ],
    "wof:name":"Valley Optical",
    "wof:placetype":"venue"
},
  "geometry": {"coordinates":[-77.11408996580001,45.8260612488],"type":"Point"}
}