{
  "type": "Feature",
  "properties": {
    "addr:full":"690 Sir John A Macdonald Blvd Kingston ON K7M 1A2",
    "addr:housenumber":"690",
    "addr:postcode":"k7m 1a2",
    "addr:street":"Sir John A Macdonald Blvd",
    "iso:country":"CA",
    "sg:address":"690 Sir John A Macdonald Blvd",
    "sg:city":"Kingston",
    "sg:classifiers":[
        {
            "category":"Organizations",
            "subcategory":"Religious Organization",
            "type":"Services"
        }
    ],
    "sg:phone":"+1 613 542 9305",
    "sg:postcode":"K7M 1A2",
    "sg:province":"ON",
    "sg:tags":[
        "church"
    ],
    "wof:name":"St Margaret's United Church",
    "wof:placetype":"venue"
},
  "geometry": {"coordinates":[-76.519707,44.243073],"type":"Point"}
}