{
  "type": "Feature",
  "properties": {
    "addr:full":"967 Ch Du Rivage Saint-Antoine-Sur-Richelieu QC J0L 1R0",
    "addr:housenumber":"967",
    "addr:postcode":"j0l 1r0",
    "addr:street":"Ch Du Rivage",
    "iso:country":"CA",
    "sg:address":"967 Ch Du Rivage",
    "sg:city":"Saint-Antoine-Sur-Richelieu",
    "sg:classifiers":[
        {
            "category":"Restaurant",
            "type":"Food & Drink"
        }
    ],
    "sg:phone":"+1 450 787 4098",
    "sg:postcode":"J0L 1R0",
    "sg:province":"QC",
    "wof:name":"Cantine Marie-L'Eau",
    "wof:placetype":"venue"
},
  "geometry": {"coordinates":[-73.174408,45.776058],"type":"Point"}
}