{
  "type": "Feature",
  "properties": {
    "addr:full":"239 Menzies St Victoria BC V8V 2G6",
    "addr:housenumber":"239",
    "addr:postcode":"v8v 2g6",
    "addr:street":"Menzies St",
    "iso:country":"CA",
    "sg:address":"239 Menzies St",
    "sg:city":"Victoria",
    "sg:classifiers":[
        {
            "category":"Restaurant",
            "type":"Food & Drink"
        }
    ],
    "sg:phone":"+1 250 480 7724",
    "sg:postcode":"V8V 2G6",
    "sg:province":"BC",
    "wof:name":"Subway Sandwiches & Salads",
    "wof:placetype":"venue"
},
  "geometry": {"coordinates":[-123.373215,48.416348],"type":"Point"}
}