{
  "type": "Feature",
  "properties": {
    "addr:full":"1200 Boul Casavant O Saint-Hyacinthe QC J2S 8B9",
    "addr:housenumber":"1200",
    "addr:postcode":"j2s 8b9",
    "addr:street":"Boul Casavant O",
    "iso:country":"CA",
    "sg:address":"1200 Boul Casavant O",
    "sg:city":"Saint-Hyacinthe",
    "sg:classifiers":[
        {
            "category":"Government",
            "subcategory":"Office",
            "type":"Public Place"
        }
    ],
    "sg:phone":"+1 450 778 6616",
    "sg:postcode":"J2S 8B9",
    "sg:province":"QC",
    "wof:name":"Quebec Permis DE Conduire",
    "wof:placetype":"venue"
},
  "geometry": {"coordinates":[-72.95380401609999,45.6459732056],"type":"Point"}
}