{
  "type": "Feature",
  "properties": {
    "addr:full":"2303 Rue Belanger Richelieu QC J3L 6P7",
    "addr:housenumber":"2303",
    "addr:postcode":"j3l 6p7",
    "addr:street":"Rue Belanger",
    "iso:country":"CA",
    "sg:address":"2303 Rue Belanger",
    "sg:city":"Richelieu",
    "sg:classifiers":[
        {
            "category":"Building & Trades",
            "subcategory":"Construction",
            "type":"Services"
        }
    ],
    "sg:phone":"+1 450 658 1845",
    "sg:postcode":"J3L 6P7",
    "sg:province":"QC",
    "sg:tags":[
        "excavating",
        "contractor"
    ],
    "wof:name":"Lewis Belanger Excavation Inc",
    "wof:placetype":"venue"
},
  "geometry": {"coordinates":[-73.21668200000001,45.419437],"type":"Point"}
}