{
  "type": "Feature",
  "properties": {
    "addr:full":"2669 Route 104 Middle Hainesville NB E6E 1G8",
    "addr:housenumber":"2669",
    "addr:postcode":"e6e 1g8",
    "addr:street":"Route 104 Middle",
    "iso:country":"CA",
    "sg:address":"2669 Route 104",
    "sg:city":"Middle Hainesville",
    "sg:classifiers":[
        {
            "category":"Food & Beverages",
            "subcategory":"Groceries & Convenience Stores",
            "type":"Retail Goods"
        }
    ],
    "sg:phone":"+1 506 463 8278",
    "sg:postcode":"E6E 1G8",
    "sg:province":"NB",
    "wof:name":"Hainesville Stop & Shop",
    "wof:placetype":"venue"
},
  "geometry": {"coordinates":[-67.06521606450001,46.0709457397],"type":"Point"}
}