{
  "type": "Feature",
  "properties": {
    "addr:full":"SW 19 7 28 Sinclair MB R0M 2A0",
    "addr:housenumber":"28",
    "addr:postcode":"r0m 2a0",
    "addr:street":"Sw 19 7;Sinclair",
    "iso:country":"CA",
    "sg:address":"SW 19 7 28",
    "sg:city":"Sinclair",
    "sg:classifiers":[
        {
            "category":"Retail",
            "subcategory":"Auto Repair",
            "type":"Services"
        }
    ],
    "sg:phone":"+1 204 662 4524",
    "sg:postcode":"R0M 2A0",
    "sg:province":"MB",
    "sg:tags":[
        "repairing",
        "automobile"
    ],
    "wof:name":"Irwin Automotive Ltd",
    "wof:placetype":"venue"
},
  "geometry": {"coordinates":[-101.292816,49.569382],"type":"Point"}
}