{
  "type": "Feature",
  "properties": {
    "iso:country":"CA",
    "sg:address":"357 Southdale Rd E",
    "sg:city":"London",
    "sg:classifiers":[
        {
            "category":"Health Services",
            "subcategory":"Doctor",
            "type":"Services"
        }
    ],
    "sg:phone":"+1 519 685 9743",
    "sg:postcode":"N6E 1A2",
    "sg:province":"ON",
    "sg:tags":[
        "physician",
        "surgeon"
    ],
    "wof:name":"Melville, Rhona D MD",
    "wof:placetype":"venue"
},
  "geometry": {"coordinates":[-81.24630737299999,42.9415931702],"type":"Point"}
}