{
  "type": "Feature",
  "properties": {
    "addr:full":"92 Keats Walk Waterloo ON N2L 5H1",
    "addr:housenumber":"92",
    "addr:postcode":"n2l 5h1",
    "addr:street":"Keats Walk",
    "iso:country":"CA",
    "sg:address":"92 Keats Walk",
    "sg:city":"Waterloo",
    "sg:classifiers":[
        {
            "category":"Manufacturing",
            "subcategory":"Printing",
            "type":"Manufacturing & Wholesale Goods"
        }
    ],
    "sg:phone":"+1 519 746 5796",
    "sg:postcode":"N2L 5H1",
    "sg:province":"ON",
    "sg:tags":[
        "publisher"
    ],
    "wof:name":"Canada & the World",
    "wof:placetype":"venue"
},
  "geometry": {"coordinates":[-80.54827899999999,43.460419],"type":"Point"}
}