{
  "type": "Feature",
  "properties": {
    "addr:full":"2176 Madison Ave Sudbury ON P3A 2R2",
    "addr:housenumber":"2176",
    "addr:postcode":"p3a 2r2",
    "addr:street":"Madison Ave",
    "iso:country":"CA",
    "sg:address":"2176 Madison Ave",
    "sg:city":"Sudbury",
    "sg:classifiers":[
        {
            "category":"Food & Beverages",
            "subcategory":"Groceries & Convenience Stores",
            "type":"Retail Goods"
        }
    ],
    "sg:phone":"+1 705 566 8807",
    "sg:postcode":"P3A 2R2",
    "sg:province":"ON",
    "wof:name":"Madison Confectionery",
    "wof:placetype":"venue"
},
  "geometry": {"coordinates":[-80.9192810059,46.5304527283],"type":"Point"}
}