{
  "type": "Feature",
  "properties": {
    "addr:full":"Nanaimo BC V9S 5H6",
    "addr:postcode":"v9s 5h6",
    "iso:country":"CA",
    "sg:city":"Nanaimo",
    "sg:classifiers":[
        {
            "category":"Health Services",
            "subcategory":"Doctor",
            "type":"Services"
        }
    ],
    "sg:phone":"+1 250 754 1258",
    "sg:postcode":"V9S 5H6",
    "sg:province":"BC",
    "sg:tags":[
        "physician",
        "surgeon"
    ],
    "wof:name":"Mitchell, Patrick J MD",
    "wof:placetype":"venue"
},
  "geometry": {"coordinates":[-123.971626282,49.1830711365],"type":"Point"}
}