{
  "type": "Feature",
  "properties": {
    "addr:full":"14 Wiarton Crt Thornhill ON L3T 2P4",
    "addr:housenumber":"14",
    "addr:postcode":"l3t 2p4",
    "addr:street":"Wiarton Crt",
    "iso:country":"CA",
    "sg:address":"14 Wiarton Crt",
    "sg:city":"Thornhill",
    "sg:classifiers":[
        {
            "category":"Building & Trades",
            "subcategory":"Construction",
            "type":"Services"
        }
    ],
    "sg:phone":"+1 905 889 0153",
    "sg:postcode":"L3T 2P4",
    "sg:province":"ON",
    "sg:tags":[
        "dry wall",
        "dealer",
        "contractor"
    ],
    "wof:name":"Flegar Plastering & Ceramics",
    "wof:placetype":"venue"
},
  "geometry": {"coordinates":[-79.40599822999999,43.8128242493],"type":"Point"}
}