{
  "type": "Feature",
  "properties": {
    "iso:country":"CA",
    "sg:address":"12225 Boul Laurentien",
    "sg:city":"Montreal",
    "sg:classifiers":[
        {
            "category":"Autos & Motor Vehicles",
            "subcategory":"Auto Supplies",
            "type":"Retail Goods"
        }
    ],
    "sg:phone":"+1 514 334 7442",
    "sg:postcode":"H4K 1N4",
    "sg:province":"QC",
    "sg:tags":[
        "trailer",
        "hitch"
    ],
    "wof:name":"A Mailhot & Fils Inc",
    "wof:placetype":"venue"
},
  "geometry": {"coordinates":[-73.721039,45.528503],"type":"Point"}
}