{
  "type": "Feature",
  "properties": {
    "addr:full":"Vernon BC V1T 5G4",
    "addr:postcode":"v1t 5g4",
    "iso:country":"CA",
    "sg:city":"Vernon",
    "sg:classifiers":[
        {
            "category":"Banks & Credit Unions",
            "subcategory":"Bank",
            "type":"Services"
        }
    ],
    "sg:phone":"+1 250 545 0704",
    "sg:postcode":"V1T 5G4",
    "sg:province":"BC",
    "sg:tags":[
        "loan",
        "real estate"
    ],
    "wof:name":"Citifinancial",
    "wof:placetype":"venue"
},
  "geometry": {"coordinates":[-119.269989,50.260696],"type":"Point"}
}