{
  "type": "Feature",
  "properties": {
    "iso:country":"CA",
    "sg:address":"111 Rue DE L'Hotel-DE-Ville",
    "sg:city":"Riviere-Du-Loup",
    "sg:classifiers":[
        {
            "category":"Retail",
            "subcategory":"Auto Repair",
            "type":"Services"
        }
    ],
    "sg:phone":"+1 418 868 7000",
    "sg:postcode":"G5R 1M1",
    "sg:province":"QC",
    "sg:tags":[
        "lettering",
        "painter",
        "sign"
    ],
    "wof:name":"Lettrage Michel Labonte Inc",
    "wof:placetype":"venue"
},
  "geometry": {"coordinates":[-69.5353088379,47.8369369507],"type":"Point"}
}