{
  "type": "Feature",
  "properties": {
    "addr:full":"RR 1 Spirit River AB T0H 3G0",
    "addr:postcode":"t0h 3g0",
    "addr:street":"Rr 1 Spirit",
    "iso:country":"CA",
    "sg:address":"RR 1",
    "sg:city":"Spirit River",
    "sg:classifiers":[
        {
            "category":"Mining & Drilling",
            "type":"Manufacturing & Wholesale Goods"
        }
    ],
    "sg:phone":"+1 780 864 2396",
    "sg:postcode":"T0H 3G0",
    "sg:province":"AB",
    "sg:tags":[
        "field",
        "oil"
    ],
    "wof:name":"D & D Well Svc",
    "wof:placetype":"venue"
},
  "geometry": {"coordinates":[-118.84854126,55.7812995911],"type":"Point"}
}