{
  "type": "Feature",
  "properties": {
    "addr:full":"Burlington ON L7M 1A4",
    "addr:postcode":"l7m 1a4",
    "iso:country":"CA",
    "sg:city":"Burlington",
    "sg:classifiers":[
        {
            "category":"Recreation",
            "subcategory":"Amusement Park",
            "type":"Entertainment"
        }
    ],
    "sg:phone":"+1 905 335 8520",
    "sg:postcode":"L7M 1A4",
    "sg:province":"ON",
    "wof:name":"Mainway Sports & Game Ctr",
    "wof:placetype":"venue"
},
  "geometry": {"coordinates":[-79.80688499999999,43.360886],"type":"Point"}
}