{
  "type": "Feature",
  "properties": {
    "addr:full":"154 St. Peters Rd Charlottetown PE C1A 5P8",
    "addr:housenumber":"154",
    "addr:postcode":"c1a 5p8",
    "addr:street":"St. Peters Rd",
    "iso:country":"CA",
    "sg:address":"154 St. Peters Rd",
    "sg:city":"Charlottetown",
    "sg:classifiers":[
        {
            "category":"Food & Beverages",
            "subcategory":"Groceries & Convenience Stores",
            "type":"Retail Goods"
        }
    ],
    "sg:phone":"+1 902 892 2651",
    "sg:postcode":"C1A 5P8",
    "sg:province":"PE",
    "sg:tags":[
        "grocer"
    ],
    "wof:name":"Ultramar Corner Store",
    "wof:placetype":"venue"
},
  "geometry": {"coordinates":[-63.118477,46.260746],"type":"Point"}
}