{
  "type": "Feature",
  "properties": {
    "addr:full":"3310 8th St E # 94 Saskatoon SK S7H 5M3",
    "addr:housenumber":"3310",
    "addr:postcode":"s7h 5m3",
    "addr:street":"8Th St E # 94",
    "iso:country":"CA",
    "sg:address":"3310 8th St E # 94",
    "sg:city":"Saskatoon",
    "sg:classifiers":[
        {
            "category":"Shopping",
            "subcategory":"Clothing, Apparel, & Fashions",
            "type":"Retail Goods"
        }
    ],
    "sg:phone":"+1 306 955 2919",
    "sg:postcode":"S7H 5M3",
    "sg:province":"SK",
    "wof:name":"Mariposa-Savannah",
    "wof:placetype":"venue"
},
  "geometry": {"coordinates":[-106.602676,52.114422],"type":"Point"}
}