{
  "type": "Feature",
  "properties": {
    "addr:full":"1220 Islington Ave Etobicoke ON M8Z 4T1",
    "addr:housenumber":"1220",
    "addr:postcode":"m8z 4t1",
    "addr:street":"Islington Ave",
    "iso:country":"CA",
    "sg:address":"1220 Islington Ave",
    "sg:city":"Etobicoke",
    "sg:classifiers":[
        {
            "category":"Health Services",
            "subcategory":"Medical Lab",
            "type":"Services"
        }
    ],
    "sg:phone":"+1 416 767 1464",
    "sg:postcode":"M8Z 4T1",
    "sg:province":"ON",
    "wof:name":"Dentures on Wheels",
    "wof:placetype":"venue"
},
  "geometry": {"coordinates":[-79.523453,43.64426],"type":"Point"}
}