{
  "type": "Feature",
  "properties": {
    "addr:full":"1314 Elphinstone St Regina SK S4T 3M4",
    "addr:housenumber":"1314",
    "addr:postcode":"s4t 3m4",
    "addr:street":"Elphinstone St",
    "iso:country":"CA",
    "sg:address":"1314 Elphinstone St",
    "sg:city":"Regina",
    "sg:classifiers":[
        {
            "category":"Education",
            "subcategory":"School",
            "type":"Public Place"
        }
    ],
    "sg:phone":"+1 306 791 7290",
    "sg:postcode":"S4T 3M4",
    "sg:province":"SK",
    "wof:name":"Sacred Heart Elementary School",
    "wof:placetype":"venue"
},
  "geometry": {"coordinates":[-104.631294,50.457935],"type":"Point"}
}