{
  "type": "Feature",
  "properties": {
    "addr:full":"76 Howie St Charlton ON P0J 1B0",
    "addr:housenumber":"76",
    "addr:postcode":"p0j 1b0",
    "addr:street":"Howie St",
    "iso:country":"CA",
    "sg:address":"76 Howie St",
    "sg:city":"Charlton",
    "sg:classifiers":[
        {
            "category":"Shopping",
            "subcategory":"Discount & Variety Stores",
            "type":"Retail Goods"
        }
    ],
    "sg:phone":"+1 705 544 2333",
    "sg:postcode":"P0J 1B0",
    "sg:province":"ON",
    "wof:name":"Marie's Market",
    "wof:placetype":"venue"
},
  "geometry": {"coordinates":[-79.9932022095,47.8104972839],"type":"Point"}
}