{
  "type": "Feature",
  "properties": {
    "addr:full":"56 Bond St Wabush NL A0R 1B0",
    "addr:housenumber":"56",
    "addr:postcode":"a0r 1b0",
    "addr:street":"Bond St",
    "iso:country":"CA",
    "sg:address":"56 Bond St",
    "sg:city":"Wabush",
    "sg:classifiers":[
        {
            "category":"Organizations",
            "subcategory":"Professional Association",
            "type":"Services"
        }
    ],
    "sg:phone":"+1 709 282 6815",
    "sg:postcode":"A0R 1B0",
    "sg:province":"NL",
    "wof:name":"Royal Canadian Legion Brnch 57",
    "wof:placetype":"venue"
},
  "geometry": {"coordinates":[-66.868637085,52.8973655701],"type":"Point"}
}