{
  "type": "Feature",
  "properties": {
    "addr:full":"Edmonton AB T5B 2C9",
    "addr:postcode":"t5b 2c9",
    "iso:country":"CA",
    "sg:city":"Edmonton",
    "sg:classifiers":[
        {
            "category":"Wholesale",
            "subcategory":"Construction Materials",
            "type":"Manufacturing & Wholesale Goods"
        }
    ],
    "sg:phone":"+1 780 471 2770",
    "sg:postcode":"T5B 2C9",
    "sg:province":"AB",
    "sg:tags":[
        "lumber"
    ],
    "wof:name":"Peter Rebus Lumber Sales Ltd",
    "wof:placetype":"venue"
},
  "geometry": {"coordinates":[-113.457885742,53.5738945007],"type":"Point"}
}