{
  "type": "Feature",
  "properties": {
    "iso:country":"CA",
    "sg:address":"2099 Ch DE LA Canardiere",
    "sg:city":"Quebec",
    "sg:classifiers":[
        {
            "category":"Education",
            "subcategory":"Special Training",
            "type":"Public Place"
        }
    ],
    "sg:phone":"+1 418 667 0129",
    "sg:postcode":"G1J 2E7",
    "sg:province":"QC",
    "sg:tags":[
        "instruction",
        "driving"
    ],
    "wof:name":"Ecole DE Conduite Lauzon",
    "wof:placetype":"venue"
},
  "geometry": {"coordinates":[-71.2210159302,46.8404426575],"type":"Point"}
}