{
  "type": "Feature",
  "properties": {
    "addr:full":"702 Boul DE Perigny Chambly QC J3L 1W3",
    "addr:housenumber":"702",
    "addr:postcode":"j3l 1w3",
    "addr:street":"Boul De Perigny",
    "iso:country":"CA",
    "sg:address":"702 Boul DE Perigny",
    "sg:city":"Chambly",
    "sg:classifiers":[
        {
            "category":"Bus Charters",
            "type":"Transportation"
        }
    ],
    "sg:phone":"+1 450 658 0202",
    "sg:postcode":"J3L 1W3",
    "sg:province":"QC",
    "sg:tags":[
        "rental"
    ],
    "wof:name":"Autobus Chambly Inc",
    "wof:placetype":"venue"
},
  "geometry": {"coordinates":[-73.303185,45.457146],"type":"Point"}
}