{
  "type": "Feature",
  "properties": {
    "addr:full":"1911 Jerseyville Rd W Jerseyville ON L0R 1R0",
    "addr:housenumber":"1911",
    "addr:postcode":"l0r 1r0",
    "addr:street":"Jerseyville Rd W",
    "iso:country":"CA",
    "sg:address":"1911 Jerseyville Rd W",
    "sg:city":"Jerseyville",
    "sg:classifiers":[
        {
            "category":"Building & Trades",
            "subcategory":"Landscaping Services",
            "type":"Services"
        }
    ],
    "sg:phone":"+1 905 648 8598",
    "sg:postcode":"L0R 1R0",
    "sg:province":"ON",
    "sg:tags":[
        "landscape",
        "contractor"
    ],
    "wof:name":"Scott's Landscaping",
    "wof:placetype":"venue"
},
  "geometry": {"coordinates":[-80.104179,43.200432],"type":"Point"}
}