{
  "type": "Feature",
  "properties": {
    "addr:full":"PO Box 71 Cowley AB T0K 0P0",
    "addr:housenumber":"po box 71",
    "addr:postcode":"t0k 0p0",
    "iso:country":"CA",
    "sg:address":"PO Box 71",
    "sg:city":"Cowley",
    "sg:classifiers":[
        {
            "category":"Building & Trades",
            "subcategory":"Construction",
            "type":"Services"
        }
    ],
    "sg:phone":"+1 403 628 2030",
    "sg:postcode":"T0K 0P0",
    "sg:province":"AB",
    "sg:tags":[
        "maker",
        "cabinet"
    ],
    "wof:name":"Thibert's Cabinetry & Fine",
    "wof:placetype":"venue"
},
  "geometry": {"coordinates":[-114.074783,49.568714],"type":"Point"}
}