{
  "type": "Feature",
  "properties": {
    "iso:country":"CA",
    "sg:city":"Montreal",
    "sg:classifiers":[
        {
            "category":"Building & Trades",
            "subcategory":"Cleaning & Sanitation",
            "type":"Services"
        }
    ],
    "sg:phone":"+1 514 875 4242",
    "sg:postcode":"H2Z 1B1",
    "sg:province":"QC",
    "sg:tags":[
        "energy",
        "company",
        "steam"
    ],
    "wof:name":"Corporation DE Chauffage Urbn",
    "wof:placetype":"venue"
},
  "geometry": {"coordinates":[-73.557137,45.514172],"type":"Point"}
}