{
  "type": "Feature",
  "properties": {
    "iso:country":"CA",
    "sg:address":"1400 12 Ave SW",
    "sg:city":"Calgary",
    "sg:classifiers":[
        {
            "category":"Shopping",
            "subcategory":"Optical Goods",
            "type":"Retail Goods"
        }
    ],
    "sg:phone":"+1 403 245 1525",
    "sg:postcode":"T3C 0P7",
    "sg:province":"AB",
    "sg:tags":[
        "optician"
    ],
    "wof:name":"Mercury Optical Ltd",
    "wof:placetype":"venue"
},
  "geometry": {"coordinates":[-114.093910217,51.0423316956],"type":"Point"}
}