{
  "type": "Feature",
  "properties": {
    "addr:full":"2805 Princess St Kingston ON K7P 2X1",
    "addr:housenumber":"2805",
    "addr:postcode":"k7p 2x1",
    "addr:street":"Princess St",
    "iso:country":"CA",
    "sg:address":"2805 Princess St",
    "sg:city":"Kingston",
    "sg:classifiers":[
        {
            "category":"Shopping",
            "subcategory":"Florist",
            "type":"Retail Goods"
        }
    ],
    "sg:phone":"+1 613 384 7673",
    "sg:postcode":"K7P 2X1",
    "sg:province":"ON",
    "wof:name":"Flower Market",
    "wof:placetype":"venue"
},
  "geometry": {"coordinates":[-76.58233642579999,44.259349823],"type":"Point"}
}