{
  "type": "Feature",
  "properties": {
    "addr:full":"1571 Rue Pierre-Corneille Sainte-Foy QC G2E 4W9",
    "addr:housenumber":"1571",
    "addr:postcode":"g2e 4w9",
    "addr:street":"Rue Pierre-Corneille",
    "iso:country":"CA",
    "sg:address":"1571 Rue Pierre-Corneille",
    "sg:city":"Sainte-Foy",
    "sg:classifiers":[
        {
            "category":"Retail",
            "subcategory":"Repair Shop",
            "type":"Services"
        }
    ],
    "sg:phone":"+1 418 877 6067",
    "sg:postcode":"G2E 4W9",
    "sg:province":"QC",
    "sg:tags":[
        "upholsterer"
    ],
    "wof:name":"Sofa Et Cetera",
    "wof:placetype":"venue"
},
  "geometry": {"coordinates":[-71.36553955079999,46.820274353],"type":"Point"}
}