{
  "type": "Feature",
  "properties": {
    "addr:full":"Sydney Mines NS B1V 2S6",
    "addr:postcode":"b1v 2s6",
    "iso:country":"CA",
    "sg:city":"Sydney Mines",
    "sg:classifiers":[
        {
            "category":"Restaurant",
            "type":"Food & Drink"
        }
    ],
    "sg:phone":"+1 902 736 9424",
    "sg:postcode":"B1V 2S6",
    "sg:province":"NS",
    "wof:name":"Princess Pizzeria",
    "wof:placetype":"venue"
},
  "geometry": {"coordinates":[-60.233437,46.245483],"type":"Point"}
}