{
  "type": "Feature",
  "properties": {
    "iso:country":"CA",
    "sg:address":"115 Av Saint-Denis",
    "sg:city":"Saint-Lambert",
    "sg:classifiers":[
        {
            "category":"Manufacturing",
            "subcategory":"Rubber & Plastics",
            "type":"Manufacturing & Wholesale Goods"
        }
    ],
    "sg:phone":"+1 450 466 7969",
    "sg:postcode":"J4P 2G1",
    "sg:province":"QC",
    "sg:tags":[
        "belting",
        "supply"
    ],
    "wof:name":"Covimex 2000 Ltee",
    "wof:placetype":"venue"
},
  "geometry": {"coordinates":[-73.513,45.499218],"type":"Point"}
}