{
  "type": "Feature",
  "properties": {
    "addr:full":"435 Lagimodiere Blvd Winnipeg MB R2J 4J4",
    "addr:housenumber":"435",
    "addr:postcode":"r2j 4j4",
    "addr:street":"Lagimodiere Blvd",
    "iso:country":"CA",
    "sg:address":"435 Lagimodiere Blvd",
    "sg:city":"Winnipeg",
    "sg:classifiers":[
        {
            "category":"Building & Trades",
            "subcategory":"Landscaping Services",
            "type":"Services"
        }
    ],
    "sg:phone":"+1 204 257 3575",
    "sg:postcode":"R2J 4J4",
    "sg:province":"MB",
    "sg:tags":[
        "contractor",
        "landscape",
        "topsoil"
    ],
    "wof:name":"T & T Soils",
    "wof:placetype":"venue"
},
  "geometry": {"coordinates":[-97.0493850708,49.8450927734],"type":"Point"}
}