{
  "type": "Feature",
  "properties": {
    "addr:full":"Lloydminster AB T9V 2Y7",
    "addr:postcode":"t9v 2y7",
    "iso:country":"CA",
    "sg:city":"Lloydminster",
    "sg:classifiers":[
        {
            "category":"Professional",
            "subcategory":"Engineering",
            "type":"Services"
        }
    ],
    "sg:phone":"+1 780 875 8847",
    "sg:postcode":"T9V 2Y7",
    "sg:province":"AB",
    "sg:tags":[
        "engineer"
    ],
    "wof:name":"Integra Energy Consulting Ltd",
    "wof:placetype":"venue"
},
  "geometry": {"coordinates":[-110.040031433,53.2769012451],"type":"Point"}
}