{
  "type": "Feature",
  "properties": {
    "addr:full":"630 Rue Jarry E Montreal QC H2P 1V7",
    "addr:housenumber":"630",
    "addr:postcode":"h2p 1v7",
    "addr:street":"Rue Jarry E",
    "iso:country":"CA",
    "sg:address":"630 Rue Jarry E",
    "sg:city":"Montreal",
    "sg:classifiers":[
        {
            "category":"Personal",
            "subcategory":"Barber",
            "type":"Services"
        }
    ],
    "sg:phone":"+1 514 274 2322",
    "sg:postcode":"H2P 1V7",
    "sg:province":"QC",
    "wof:name":"Hans Coiffure Enr",
    "wof:placetype":"venue"
},
  "geometry": {"coordinates":[-73.6276931763,45.5445976257],"type":"Point"}
}