{
  "type": "Feature",
  "properties": {
    "addr:full":"2977 Dahlstrom Pl Abbotsford BC V2T 4Y3",
    "addr:postcode":"2977;v2t 4y3",
    "addr:street":"Dahlstrom Pl",
    "iso:country":"CA",
    "sg:address":"2977 Dahlstrom Pl",
    "sg:city":"Abbotsford",
    "sg:classifiers":[
        {
            "category":"Real Estate",
            "subcategory":"Real Estate Operator",
            "type":"Services"
        }
    ],
    "sg:phone":"+1 604 850 2355",
    "sg:postcode":"V2T 4Y3",
    "sg:province":"BC",
    "sg:tags":[
        "apartment"
    ],
    "wof:name":"Chelsea Manor",
    "wof:placetype":"venue"
},
  "geometry": {"coordinates":[-122.316734314,49.056098938],"type":"Point"}
}