{
  "type": "Feature",
  "properties": {
    "addr:full":"Port Mcneill BC V0N 2R0",
    "addr:postcode":"v0n 2r0",
    "iso:country":"CA",
    "sg:city":"Port Mcneill",
    "sg:classifiers":[
        {
            "category":"Manufacturing",
            "subcategory":"Tools & Machinery",
            "type":"Manufacturing & Wholesale Goods"
        }
    ],
    "sg:phone":"+1 250 956 2700",
    "sg:postcode":"V0N 2R0",
    "sg:province":"BC",
    "sg:tags":[
        "engine"
    ],
    "wof:name":"Progressive Diesel",
    "wof:placetype":"venue"
},
  "geometry": {"coordinates":[-127.074707,50.579647],"type":"Point"}
}