{
  "type": "Feature",
  "properties": {
    "iso:country":"CA",
    "sg:address":"68 Young St",
    "sg:city":"Red Lake",
    "sg:classifiers":[
        {
            "category":"Building & Trades",
            "subcategory":"Cleaning & Sanitation",
            "type":"Services"
        }
    ],
    "sg:phone":"+1 807 727 2681",
    "sg:postcode":"P0V 2M0",
    "sg:province":"ON",
    "sg:tags":[
        "janitor"
    ],
    "wof:name":"Rogowsky's Cleaning",
    "wof:placetype":"venue"
},
  "geometry": {"coordinates":[-93.81186676030001,51.0170402527],"type":"Point"}
}