{
  "type": "Feature",
  "properties": {
    "addr:full":"16060 128 Ave NW Edmonton AB T5V 1B6",
    "addr:housenumber":"16060",
    "addr:postcode":"t5v 1b6",
    "addr:street":"128 Ave Nw",
    "iso:country":"CA",
    "sg:address":"16060 128 Ave NW",
    "sg:city":"Edmonton",
    "sg:classifiers":[
        {
            "category":"Freight",
            "type":"Transportation"
        }
    ],
    "sg:phone":"+1 780 447 2525",
    "sg:postcode":"T5V 1B6",
    "sg:province":"AB",
    "sg:tags":[
        "trucking"
    ],
    "wof:name":"Reimer Express Lines",
    "wof:placetype":"venue"
},
  "geometry": {"coordinates":[-113.599335,53.585079],"type":"Point"}
}