{
  "type": "Feature",
  "properties": {
    "addr:full":"RR 1 Denbigh ON K0H 1L0",
    "addr:postcode":"k0h 1l0",
    "addr:street":"Rr 1",
    "iso:country":"CA",
    "sg:address":"RR 1",
    "sg:city":"Denbigh",
    "sg:classifiers":[
        {
            "category":"Mining & Drilling",
            "type":"Manufacturing & Wholesale Goods"
        }
    ],
    "sg:phone":"+1 613 333 5228",
    "sg:postcode":"K0H 1L0",
    "sg:province":"ON",
    "sg:tags":[
        "mine"
    ],
    "wof:name":"Wagg Mineral Exploration Inc",
    "wof:placetype":"venue"
},
  "geometry": {"coordinates":[-77.2655410767,45.1427879333],"type":"Point"}
}