{
  "type": "Feature",
  "properties": {
    "addr:full":"2809 Eglinton Ave E Scarborough ON M1J 2E1",
    "addr:housenumber":"2809",
    "addr:postcode":"m1j 2e1",
    "addr:street":"Eglinton Ave E",
    "iso:country":"CA",
    "sg:address":"2809 Eglinton Ave E",
    "sg:city":"Scarborough",
    "sg:classifiers":[
        {
            "category":"Health Services",
            "subcategory":"Doctor",
            "type":"Services"
        }
    ],
    "sg:phone":"+1 416 261 2212",
    "sg:postcode":"M1J 2E1",
    "sg:province":"ON",
    "sg:tags":[
        "physician",
        "surgeon"
    ],
    "wof:name":"Yee, I C MD",
    "wof:placetype":"venue"
},
  "geometry": {"coordinates":[-79.244614,43.737347],"type":"Point"}
}