{
  "type": "Feature",
  "properties": {
    "addr:full":"Toronto ON M5R 3P8",
    "addr:postcode":"m5r 3p8",
    "iso:country":"CA",
    "sg:city":"Toronto",
    "sg:classifiers":[
        {
            "category":"Home & Garden",
            "subcategory":"Carpets & Floor Coverings",
            "type":"Retail Goods"
        }
    ],
    "sg:phone":"+1 416 923 2147",
    "sg:postcode":"M5R 3P8",
    "sg:province":"ON",
    "sg:tags":[
        "dealer",
        "rug"
    ],
    "wof:name":"Templeton Fine Carpets",
    "wof:placetype":"venue"
},
  "geometry": {"coordinates":[-79.39849853520001,43.6753730774],"type":"Point"}
}