{
  "type": "Feature",
  "properties": {
    "addr:full":"3280 Electricity Dr Windsor ON N8W 5J1",
    "addr:housenumber":"3280",
    "addr:postcode":"n8w 5j1",
    "addr:street":"Electricity Dr",
    "iso:country":"CA",
    "sg:address":"3280 Electricity Dr",
    "sg:city":"Windsor",
    "sg:classifiers":[
        {
            "category":"Professional",
            "subcategory":"Computer Services",
            "type":"Services"
        }
    ],
    "sg:phone":"+1 519 974 6789",
    "sg:postcode":"N8W 5J1",
    "sg:province":"ON",
    "sg:tags":[
        "internet"
    ],
    "wof:name":"Jet 2 Net",
    "wof:placetype":"venue"
},
  "geometry": {"coordinates":[-82.96537780760001,42.2831726074],"type":"Point"}
}