{
  "type": "Feature",
  "properties": {
    "iso:country":"CA",
    "sg:address":"304 Huntbourne Way NE",
    "sg:city":"Calgary",
    "sg:classifiers":[
        {
            "category":"Mining & Drilling",
            "type":"Manufacturing & Wholesale Goods"
        }
    ],
    "sg:phone":"+1 403 275 2343",
    "sg:postcode":"T2K 3Y1",
    "sg:province":"AB",
    "sg:tags":[
        "insulation",
        "field",
        "oil",
        "contractor"
    ],
    "wof:name":"Art's Maintenance Svc Ltd",
    "wof:placetype":"venue"
},
  "geometry": {"coordinates":[-114.062927246,51.1156387329],"type":"Point"}
}