{
  "type": "Feature",
  "properties": {
    "iso:country":"CA",
    "sg:address":"2685 Iris St",
    "sg:city":"Ottawa",
    "sg:classifiers":[
        {
            "category":"Home & Garden",
            "subcategory":"Furniture",
            "type":"Retail Goods"
        }
    ],
    "sg:phone":"+1 613 829 4530",
    "sg:postcode":"K2C 3S4",
    "sg:province":"ON",
    "wof:name":"Ikea",
    "wof:placetype":"venue"
},
  "geometry": {"coordinates":[-75.7851486206,45.3486938477],"type":"Point"}
}