{
  "type": "Feature",
  "properties": {
    "addr:full":"145 Stewart Cres Kindersley SK S0L 1S1",
    "addr:housenumber":"145",
    "addr:postcode":"s0l 1s1",
    "addr:street":"Stewart Cres Kindersley",
    "iso:country":"CA",
    "sg:address":"145 Stewart Cres",
    "sg:city":"Kindersley",
    "sg:classifiers":[
        {
            "category":"Mining & Drilling",
            "type":"Manufacturing & Wholesale Goods"
        }
    ],
    "sg:phone":"+1 306 463 6454",
    "sg:postcode":"S0L 1S1",
    "sg:province":"SK",
    "sg:tags":[
        "oil",
        "well"
    ],
    "wof:name":"Wielgosz Resources Ltd",
    "wof:placetype":"venue"
},
  "geometry": {"coordinates":[-109.14110599999999,51.46352],"type":"Point"}
}