{
  "type": "Feature",
  "properties": {
    "addr:full":"593 Broadway St Tillsonburg ON N4G 3S8",
    "addr:housenumber":"593",
    "addr:postcode":"n4g 3s8",
    "addr:street":"Broadway St",
    "iso:country":"CA",
    "sg:address":"593 Broadway St",
    "sg:city":"Tillsonburg",
    "sg:classifiers":[
        {
            "category":"Autos & Motor Vehicles",
            "subcategory":"Fuel & Gas Station",
            "type":"Retail Goods"
        }
    ],
    "sg:phone":"+1 519 842 7740",
    "sg:postcode":"N4G 3S8",
    "sg:province":"ON",
    "sg:tags":[
        "oil"
    ],
    "wof:name":"North Broadway Shell",
    "wof:placetype":"venue"
},
  "geometry": {"coordinates":[-80.7461929321,42.8780822754],"type":"Point"}
}