{
  "type": "Feature",
  "properties": {
    "addr:full":"5665 Boul Saint-Laurent Montreal QC H2T 1S9",
    "addr:housenumber":"5665",
    "addr:postcode":"h2t 1s9",
    "addr:street":"Boul Saint-Laurent",
    "iso:country":"CA",
    "sg:address":"5665 Boul Saint-Laurent",
    "sg:city":"Montreal",
    "sg:classifiers":[
        {
            "category":"Shopping",
            "subcategory":"Shoes",
            "type":"Retail Goods"
        }
    ],
    "sg:phone":"+1 514 273 0424",
    "sg:postcode":"H2T 1S9",
    "sg:province":"QC",
    "wof:name":"Groupe Yellow Inc",
    "wof:placetype":"venue"
},
  "geometry": {"coordinates":[-73.60037994379999,45.5266723633],"type":"Point"}
}