{
  "type": "Feature",
  "properties": {
    "addr:full":"Ripley ON N0G 2R0",
    "addr:postcode":"n0g 2r0",
    "iso:country":"CA",
    "sg:city":"Ripley",
    "sg:classifiers":[
        {
            "category":"Building & Trades",
            "subcategory":"Construction",
            "type":"Services"
        }
    ],
    "sg:phone":"+1 519 395 5077",
    "sg:postcode":"N0G 2R0",
    "sg:province":"ON",
    "sg:tags":[
        "contractor"
    ],
    "wof:name":"Joe Van Rooy Construction",
    "wof:placetype":"venue"
},
  "geometry": {"coordinates":[-81.5777893066,44.0711288452],"type":"Point"}
}