{
  "type": "Feature",
  "properties": {
    "addr:full":"2200 Yonge St Toronto ON M4S 2C6",
    "addr:housenumber":"2200",
    "addr:postcode":"m4s 2c6",
    "addr:street":"Yonge St",
    "iso:country":"CA",
    "sg:address":"2200 Yonge St",
    "sg:city":"Toronto",
    "sg:classifiers":[
        {
            "category":"Restaurant",
            "type":"Food & Drink"
        }
    ],
    "sg:phone":"+1 416 489 3989",
    "sg:postcode":"M4S 2C6",
    "sg:province":"ON",
    "wof:name":"Tessorro Pizza & Submarine",
    "wof:placetype":"venue"
},
  "geometry": {"coordinates":[-79.398201,43.705006],"type":"Point"}
}