{
  "type": "Feature",
  "properties": {
    "addr:full":"8627 Haldi Lake Rd Prince George BC V2N 6K1",
    "addr:postcode":"8627;v2n 6k1",
    "addr:street":"Haldi Lake Rd",
    "iso:country":"CA",
    "sg:address":"8627 Haldi Lake Rd",
    "sg:city":"Prince George",
    "sg:classifiers":[
        {
            "category":"Building & Trades",
            "subcategory":"Construction",
            "type":"Services"
        }
    ],
    "sg:phone":"+1 250 964 6144",
    "sg:postcode":"V2N 6K1",
    "sg:province":"BC",
    "sg:tags":[
        "excavating",
        "contractor"
    ],
    "wof:name":"Cmh Underground Utilities",
    "wof:placetype":"venue"
},
  "geometry": {"coordinates":[-122.833038,53.839939],"type":"Point"}
}