{
  "type": "Feature",
  "properties": {
    "addr:full":"Main St #2 Callander ON P0H 1H0",
    "addr:postcode":"p0h 1h0",
    "addr:street":"Main St # 2",
    "iso:country":"CA",
    "sg:address":"Main St #2",
    "sg:city":"Callander",
    "sg:classifiers":[
        {
            "category":"Restaurant",
            "type":"Food & Drink"
        }
    ],
    "sg:phone":"+1 705 752 3399",
    "sg:postcode":"P0H 1H0",
    "sg:province":"ON",
    "sg:tags":[
        "out",
        "pizza"
    ],
    "wof:name":"LA Piaza Pizza",
    "wof:placetype":"venue"
},
  "geometry": {"coordinates":[-79.36560799999999,46.102699],"type":"Point"}
}