{
  "type": "Feature",
  "properties": {
    "addr:full":"149 West Dr Brampton ON L6T 2J6",
    "addr:housenumber":"149",
    "addr:postcode":"l6t 2j6",
    "addr:street":"West Dr",
    "iso:country":"CA",
    "sg:address":"149 West Dr",
    "sg:city":"Brampton",
    "sg:classifiers":[
        {
            "category":"Autos & Motor Vehicles",
            "subcategory":"Fuel & Gas Station",
            "type":"Retail Goods"
        }
    ],
    "sg:phone":"+1 905 451 8263",
    "sg:postcode":"L6T 2J6",
    "sg:province":"ON",
    "sg:tags":[
        "oil"
    ],
    "wof:name":"Sunoco",
    "wof:placetype":"venue"
},
  "geometry": {"coordinates":[-79.73142199999999,43.707111],"type":"Point"}
}