{
  "type": "Feature",
  "properties": {
    "addr:full":"486 Rue Comeau Saint-Nicephore QC J2A 2J1",
    "addr:housenumber":"486",
    "addr:postcode":"j2a 2j1",
    "addr:street":"Rue Comeau Saint-Nicephore",
    "iso:country":"CA",
    "sg:address":"486 Rue Comeau",
    "sg:city":"Saint-Nicephore",
    "sg:classifiers":[
        {
            "category":"Personal",
            "subcategory":"Beauty Salon",
            "type":"Services"
        }
    ],
    "sg:phone":"+1 819 472 5518",
    "sg:postcode":"J2A 2J1",
    "sg:province":"QC",
    "wof:name":"Esthetique Guylene Niquette",
    "wof:placetype":"venue"
},
  "geometry": {"coordinates":[-72.444031,45.841137],"type":"Point"}
}