{
  "type": "Feature",
  "properties": {
    "iso:country":"CA",
    "sg:city":"Milton",
    "sg:classifiers":[
        {
            "category":"Health Services",
            "subcategory":"Doctor",
            "type":"Services"
        }
    ],
    "sg:phone":"+1 905 878 4556",
    "sg:postcode":"L9T 5B5",
    "sg:province":"ON",
    "sg:tags":[
        "physician",
        "surgeon"
    ],
    "wof:name":"Marchetti, Paul MD",
    "wof:placetype":"venue"
},
  "geometry": {"coordinates":[-79.872246,43.496281],"type":"Point"}
}