{
  "type": "Feature",
  "properties": {
    "addr:full":"New Westminster BC V3M 6R2",
    "addr:postcode":"v3m 6r2",
    "iso:country":"CA",
    "sg:city":"New Westminster",
    "sg:classifiers":[
        {
            "category":"Education",
            "subcategory":"Special Training",
            "type":"Public Place"
        }
    ],
    "sg:phone":"+1 604 521 4418",
    "sg:postcode":"V3M 6R2",
    "sg:province":"BC",
    "sg:tags":[
        "instruction",
        "driving"
    ],
    "wof:name":"Luzon Driving School Ltd",
    "wof:placetype":"venue"
},
  "geometry": {"coordinates":[-122.927627563,49.2051010132],"type":"Point"}
}