{
  "type": "Feature",
  "properties": {
    "addr:full":"Sydney NS B1R 1V7",
    "addr:postcode":"b1r 1v7",
    "iso:country":"CA",
    "sg:city":"Sydney",
    "sg:classifiers":[
        {
            "category":"Professional",
            "subcategory":"Management & Consulting",
            "type":"Services"
        }
    ],
    "sg:phone":"+1 902 564 0440",
    "sg:postcode":"B1R 1V7",
    "sg:province":"NS",
    "sg:tags":[
        "break",
        "coffee",
        "supply"
    ],
    "wof:name":"Maritime Coffee Svc",
    "wof:placetype":"venue"
},
  "geometry": {"coordinates":[-60.2338981628,46.1182098389],"type":"Point"}
}