{
  "type": "Feature",
  "properties": {
    "iso:country":"CA",
    "sg:address":"303 Rue Canada",
    "sg:city":"Saint-Quentin",
    "sg:classifiers":[
        {
            "category":"Restaurant",
            "type":"Food & Drink"
        }
    ],
    "sg:phone":"+1 506 235 3029",
    "sg:postcode":"E8A 1K3",
    "sg:province":"NB",
    "sg:tags":[
        "convenience",
        "store"
    ],
    "wof:name":"Depanneur Marche CA-Ro",
    "wof:placetype":"venue"
},
  "geometry": {"coordinates":[-67.3921966553,47.5181884766],"type":"Point"}
}