{
  "type": "Feature",
  "properties": {
    "addr:full":"6049 3rd Line Tottenham ON L0G 1W0",
    "addr:housenumber":"6049",
    "addr:postcode":"l0g 1w0",
    "addr:street":"3Rd Line",
    "iso:country":"CA",
    "sg:address":"6049 3rd Line",
    "sg:city":"Tottenham",
    "sg:classifiers":[
        {
            "category":"Manufacturing",
            "subcategory":"Tools & Machinery",
            "type":"Manufacturing & Wholesale Goods"
        }
    ],
    "sg:phone":"+1 905 936 2917",
    "sg:postcode":"L0G 1W0",
    "sg:province":"ON",
    "sg:tags":[
        "scale"
    ],
    "wof:name":"Arrow Scale CO Ltd",
    "wof:placetype":"venue"
},
  "geometry": {"coordinates":[-79.76596832280001,44.0179481506],"type":"Point"}
}