{
  "type": "Feature",
  "properties": {
    "addr:full":"6325 Boul Des Grandes-Prairies Saint-Leonard QC H1P 1A5",
    "addr:housenumber":"6325",
    "addr:postcode":"h1p 1a5",
    "addr:street":"Boul Des Grandes-Prairies",
    "iso:country":"CA",
    "sg:address":"6325 Boul Des Grandes-Prairies",
    "sg:city":"Saint-Leonard",
    "sg:classifiers":[
        {
            "category":"Wholesale",
            "subcategory":"Groceries",
            "type":"Manufacturing & Wholesale Goods"
        }
    ],
    "sg:phone":"+1 514 323 1880",
    "sg:postcode":"H1P 1A5",
    "sg:province":"QC",
    "sg:tags":[
        "baker"
    ],
    "wof:name":"Boulangerie Comas Inc",
    "wof:placetype":"venue"
},
  "geometry": {"coordinates":[-73.6068344116,45.6042976379],"type":"Point"}
}