{
  "type": "Feature",
  "properties": {
    "addr:full":"3311 26 St NE Calgary AB T1Y 6K9",
    "addr:housenumber":"3311",
    "addr:postcode":"t1y 6k9",
    "addr:street":"26 St Ne",
    "iso:country":"CA",
    "sg:address":"3311 26 St NE",
    "sg:city":"Calgary",
    "sg:classifiers":[
        {
            "category":"Restaurant",
            "type":"Food & Drink"
        }
    ],
    "sg:phone":"+1 403 250 6698",
    "sg:postcode":"T1Y 6K9",
    "sg:province":"AB",
    "wof:name":"Wendy's",
    "wof:placetype":"venue"
},
  "geometry": {"coordinates":[-113.998459,51.081841],"type":"Point"}
}