{
  "type": "Feature",
  "properties": {
    "addr:full":"3469 Rue Queen Rawdon QC J0K 1S0",
    "addr:housenumber":"3469",
    "addr:postcode":"j0k 1s0",
    "addr:street":"Rue Queen",
    "iso:country":"CA",
    "sg:address":"3469 Rue Queen",
    "sg:city":"Rawdon",
    "sg:classifiers":[
        {
            "category":"Restaurant",
            "type":"Food & Drink"
        }
    ],
    "sg:phone":"+1 450 834 2525",
    "sg:postcode":"J0K 1S0",
    "sg:province":"QC",
    "wof:name":"Restaurant Ming Wong Inc",
    "wof:placetype":"venue"
},
  "geometry": {"coordinates":[-73.70159099999999,46.038441],"type":"Point"}
}