{
  "type": "Feature",
  "properties": {
    "addr:full":"330 Burford St Newmarket ON L3Y 6L1",
    "addr:housenumber":"330",
    "addr:postcode":"l3y 6l1",
    "addr:street":"Burford St",
    "iso:country":"CA",
    "sg:address":"330 Burford St",
    "sg:city":"Newmarket",
    "sg:classifiers":[
        {
            "category":"Government",
            "subcategory":"Office",
            "type":"Public Place"
        }
    ],
    "sg:phone":"+1 905 953 5309",
    "sg:postcode":"L3Y 6L1",
    "sg:province":"ON",
    "sg:tags":[
        "village"
    ],
    "wof:name":"Newmarket Shared Use Facility",
    "wof:placetype":"venue"
},
  "geometry": {"coordinates":[-79.46217300000001,44.070866],"type":"Point"}
}