{
  "type": "Feature",
  "properties": {
    "iso:country":"CA",
    "sg:address":"851 Field St",
    "sg:city":"Thunder Bay",
    "sg:classifiers":[
        {
            "category":"Mining & Drilling",
            "type":"Manufacturing & Wholesale Goods"
        }
    ],
    "sg:phone":"+1 807 346 0777",
    "sg:postcode":"P7B 6B6",
    "sg:province":"ON",
    "sg:tags":[
        "mine"
    ],
    "wof:name":"Freewest Resources Canada Inc",
    "wof:placetype":"venue"
},
  "geometry": {"coordinates":[-89.2417602539,48.4102554321],"type":"Point"}
}