{
  "type": "Feature",
  "properties": {
    "addr:full":"42 Glen Elm Ave Toronto ON M4T 1T7",
    "addr:housenumber":"42",
    "addr:postcode":"m4t 1t7",
    "addr:street":"Glen Elm Ave",
    "iso:country":"CA",
    "sg:address":"42 Glen Elm Ave",
    "sg:city":"Toronto",
    "sg:classifiers":[
        {
            "category":"Wholesale",
            "subcategory":"Furniture",
            "type":"Manufacturing & Wholesale Goods"
        }
    ],
    "sg:phone":"+1 416 488 6146",
    "sg:postcode":"M4T 1T7",
    "sg:province":"ON",
    "sg:tags":[
        "chair"
    ],
    "wof:name":"Care Products CO",
    "wof:placetype":"venue"
},
  "geometry": {"coordinates":[-79.3933563232,43.6917419434],"type":"Point"}
}