{
  "type": "Feature",
  "properties": {
    "addr:full":"1875 Pembina Hwy Winnipeg MB R3T 2G7",
    "addr:housenumber":"1875",
    "addr:postcode":"r3t 2g7",
    "addr:street":"Pembina Hwy",
    "iso:country":"CA",
    "sg:address":"1875 Pembina Hwy",
    "sg:city":"Winnipeg",
    "sg:classifiers":[
        {
            "category":"Health Services",
            "subcategory":"Doctor",
            "type":"Services"
        }
    ],
    "sg:phone":"+1 204 261 1762",
    "sg:postcode":"R3T 2G7",
    "sg:province":"MB",
    "sg:tags":[
        "dentist"
    ],
    "wof:name":"Slainte Management",
    "wof:placetype":"venue"
},
  "geometry": {"coordinates":[-97.15315200000001,49.822456],"type":"Point"}
}