{
  "type": "Feature",
  "properties": {
    "addr:full":"Saint-Pamphile QC G0R 3X0",
    "addr:postcode":"g0r 3x0",
    "iso:country":"CA",
    "sg:city":"Saint-Pamphile",
    "sg:classifiers":[
        {
            "category":"Food & Beverages",
            "subcategory":"Groceries & Convenience Stores",
            "type":"Retail Goods"
        }
    ],
    "sg:phone":"+1 418 356 2933",
    "sg:postcode":"G0R 3X0",
    "sg:province":"QC",
    "wof:name":"Depanneur Le 550 Halte",
    "wof:placetype":"venue"
},
  "geometry": {"coordinates":[-69.79145800000001,46.969284],"type":"Point"}
}