{
  "type": "Feature",
  "properties": {
    "addr:full":"221 Boul Clairevue E Saint-Bruno QC J3V 5J3",
    "addr:housenumber":"221",
    "addr:postcode":"j3v 5j3",
    "addr:street":"Boul Clairevue E Saint-Bruno",
    "iso:country":"CA",
    "sg:address":"221 Boul Clairevue E",
    "sg:city":"Saint-Bruno",
    "sg:classifiers":[
        {
            "category":"Education",
            "subcategory":"School",
            "type":"Public Place"
        }
    ],
    "sg:phone":"+1 450 653 1541",
    "sg:postcode":"J3V 5J3",
    "sg:province":"QC",
    "wof:name":"Ecole Du Mont Bruno",
    "wof:placetype":"venue"
},
  "geometry": {"coordinates":[-71.675522,48.471771],"type":"Point"}
}