{
  "type": "Feature",
  "properties": {
    "addr:full":"236 Saskatchewan Ave E Portage LA Prairie MB R1N 0K9",
    "addr:housenumber":"236",
    "addr:postcode":"r1n 0k9",
    "addr:street":"Saskatchewan Ave E",
    "iso:country":"CA",
    "sg:address":"236 Saskatchewan Ave E",
    "sg:city":"Portage LA Prairie",
    "sg:classifiers":[
        {
            "category":"Social Services",
            "type":"Services"
        }
    ],
    "sg:phone":"+1 204 239 6590",
    "sg:postcode":"R1N 0K9",
    "sg:province":"MB",
    "sg:tags":[
        "organization",
        "welfare"
    ],
    "wof:name":"Cmha-Central Region",
    "wof:placetype":"venue"
},
  "geometry": {"coordinates":[-98.2870025635,49.973033905],"type":"Point"}
}