{
  "type": "Feature",
  "properties": {
    "addr:full":"1400 Rue Beauharnois Longueuil QC J4M 1C2",
    "addr:housenumber":"1400",
    "addr:postcode":"j4m 1c2",
    "addr:street":"Rue Beauharnois",
    "iso:country":"CA",
    "sg:address":"1400 Rue Beauharnois",
    "sg:city":"Longueuil",
    "sg:classifiers":[
        {
            "category":"Personal",
            "subcategory":"Beauty Salon",
            "type":"Services"
        }
    ],
    "sg:phone":"+1 450 468 3467",
    "sg:postcode":"J4M 1C2",
    "sg:province":"QC",
    "wof:name":"Salon DE Coiffure Sandra",
    "wof:placetype":"venue"
},
  "geometry": {"coordinates":[-73.454758,45.535355],"type":"Point"}
}