{
  "type": "Feature",
  "properties": {
    "iso:country":"CA",
    "sg:address":"1566 Pembina Hwy",
    "sg:city":"Winnipeg",
    "sg:classifiers":[
        {
            "category":"Autos & Motor Vehicles",
            "subcategory":"Auto Supplies",
            "type":"Retail Goods"
        }
    ],
    "sg:phone":"+1 204 987 9550",
    "sg:postcode":"R3T 2E9",
    "sg:province":"MB",
    "sg:tags":[
        "tire"
    ],
    "wof:name":"Sturgeon Tire",
    "wof:placetype":"venue"
},
  "geometry": {"coordinates":[-97.150475,49.832371],"type":"Point"}
}