{
  "type": "Feature",
  "properties": {
    "addr:full":"237 Boul DE L'Hotel-DE-Ville Riviere-Du-Loup QC G5R 4E5",
    "addr:housenumber":"237",
    "addr:postcode":"g5r 4e5",
    "addr:street":"Boul De L'Hotel-De-Ville Riviere-Du-Loup",
    "iso:country":"CA",
    "sg:address":"237 Boul DE L'Hotel-DE-Ville",
    "sg:city":"Riviere-Du-Loup",
    "sg:classifiers":[
        {
            "category":"Autos & Motor Vehicles",
            "subcategory":"Auto Supplies",
            "type":"Retail Goods"
        }
    ],
    "sg:phone":"+1 418 862 0106",
    "sg:postcode":"G5R 4E5",
    "sg:province":"QC",
    "sg:tags":[
        "repairing",
        "automobile",
        "parts"
    ],
    "wof:name":"Canadian Tire",
    "wof:placetype":"venue"
},
  "geometry": {"coordinates":[-69.535309,47.836937],"type":"Point"}
}