{
  "type": "Feature",
  "properties": {
    "addr:full":"197 Main St Parkhill ON N0M 2K0",
    "addr:housenumber":"197",
    "addr:postcode":"n0m 2k0",
    "addr:street":"Main St",
    "iso:country":"CA",
    "sg:address":"197 Main St",
    "sg:city":"Parkhill",
    "sg:classifiers":[
        {
            "category":"Professional",
            "subcategory":"Accounting & Tax Preparation",
            "type":"Services"
        }
    ],
    "sg:phone":"+1 519 294 0340",
    "sg:postcode":"N0M 2K0",
    "sg:province":"ON",
    "sg:tags":[
        "accountant"
    ],
    "wof:name":"Fisher Corp",
    "wof:placetype":"venue"
},
  "geometry": {"coordinates":[-81.68454742430001,43.1615867615],"type":"Point"}
}