{
  "type": "Feature",
  "properties": {
    "addr:full":"134 Portugal Cove Rd St. John's NL A1B 2N2",
    "addr:housenumber":"134",
    "addr:postcode":"a1b 2n2",
    "addr:street":"Portugal Cove Rd",
    "iso:country":"CA",
    "sg:address":"134 Portugal Cove Rd",
    "sg:city":"St. John's",
    "sg:classifiers":[
        {
            "category":"Real Estate",
            "subcategory":"Real Estate Operator",
            "type":"Services"
        }
    ],
    "sg:phone":"+1 709 753 1531",
    "sg:postcode":"A1B 2N2",
    "sg:province":"NL",
    "sg:tags":[
        "condominium"
    ],
    "wof:name":"Highgate",
    "wof:placetype":"venue"
},
  "geometry": {"coordinates":[-52.7153930664,47.5874786377],"type":"Point"}
}