{
  "type": "Feature",
  "properties": {
    "addr:full":"455 Boul Renault Beauceville QC G5X 1N5",
    "addr:housenumber":"455",
    "addr:postcode":"g5x 1n5",
    "addr:street":"Boul Renault",
    "iso:country":"CA",
    "sg:address":"455 Boul Renault",
    "sg:city":"Beauceville",
    "sg:classifiers":[
        {
            "category":"Building & Trades",
            "subcategory":"Electrical",
            "type":"Services"
        }
    ],
    "sg:phone":"+1 418 774 5302",
    "sg:postcode":"G5X 1N5",
    "sg:province":"QC",
    "sg:tags":[
        "electric",
        "contractor"
    ],
    "wof:name":"Gingras Electrique Inc",
    "wof:placetype":"venue"
},
  "geometry": {"coordinates":[-70.791183,46.220551],"type":"Point"}
}