{
  "type": "Feature",
  "properties": {
    "addr:full":"465 Baskin Dr Arnprior ON K7S 3G8",
    "addr:housenumber":"465",
    "addr:postcode":"k7s 3g8",
    "addr:street":"Baskin Dr",
    "iso:country":"CA",
    "sg:address":"465 Baskin Dr",
    "sg:city":"Arnprior",
    "sg:classifiers":[
        {
            "category":"Building & Trades",
            "subcategory":"Construction",
            "type":"Services"
        }
    ],
    "sg:phone":"+1 613 623 6999",
    "sg:postcode":"K7S 3G8",
    "sg:province":"ON",
    "sg:tags":[
        "pipe",
        "line",
        "contractor"
    ],
    "wof:name":"Coolsaet Pipeline CO",
    "wof:placetype":"venue"
},
  "geometry": {"coordinates":[-76.354958,45.410172],"type":"Point"}
}