{
  "type": "Feature",
  "properties": {
    "addr:full":"909 Bloor St W Toronto ON M6H 1L2",
    "addr:housenumber":"909",
    "addr:postcode":"m6h 1l2",
    "addr:street":"Bloor St W",
    "iso:country":"CA",
    "sg:address":"909 Bloor St W",
    "sg:city":"Toronto",
    "sg:classifiers":[
        {
            "category":"Real Estate",
            "subcategory":"Real Estate Agent",
            "type":"Services"
        }
    ],
    "sg:phone":"+1 416 531 3115",
    "sg:postcode":"M6H 1L2",
    "sg:province":"ON",
    "sg:tags":[
        "consultant"
    ],
    "wof:name":"Cardosa, George",
    "wof:placetype":"venue"
},
  "geometry": {"coordinates":[-79.426323,43.661694],"type":"Point"}
}