{
  "type": "Feature",
  "properties": {
    "iso:country":"CA",
    "sg:address":"2660 Hastings St E",
    "sg:city":"Vancouver",
    "sg:classifiers":[
        {
            "category":"Health Services",
            "subcategory":"Doctor",
            "type":"Services"
        }
    ],
    "sg:phone":"+1 604 254 1600",
    "sg:postcode":"V5K 1Z6",
    "sg:province":"BC",
    "sg:tags":[
        "physician",
        "surgeon"
    ],
    "wof:name":"L Salvino & Assoc",
    "wof:placetype":"venue"
},
  "geometry": {"coordinates":[-123.050346,49.28101],"type":"Point"}
}