{
  "type": "Feature",
  "properties": {
    "addr:full":"445 Main St Grandview MB R0L 0Y0",
    "addr:housenumber":"445",
    "addr:postcode":"r0l 0y0",
    "addr:street":"Main St",
    "iso:country":"CA",
    "sg:address":"445 Main St",
    "sg:city":"Grandview",
    "sg:classifiers":[
        {
            "category":"Social Services",
            "type":"Services"
        }
    ],
    "sg:phone":"+1 204 546 2085",
    "sg:postcode":"R0L 0Y0",
    "sg:province":"MB",
    "sg:tags":[
        "senior",
        "citizen"
    ],
    "wof:name":"Grandview Community Resource",
    "wof:placetype":"venue"
},
  "geometry": {"coordinates":[-100.69960021999999,51.1684112549],"type":"Point"}
}