{
  "type": "Feature",
  "properties": {
    "addr:full":"7770 40 Ave Red Deer AB T4P 2H9",
    "addr:housenumber":"7770",
    "addr:postcode":"t4p 2h9",
    "addr:street":"40 Ave",
    "iso:country":"CA",
    "sg:address":"7770 40 Ave",
    "sg:city":"Red Deer",
    "sg:classifiers":[
        {
            "category":"Retail",
            "subcategory":"Auto Repair",
            "type":"Services"
        }
    ],
    "sg:phone":"+1 403 346 7278",
    "sg:postcode":"T4P 2H9",
    "sg:province":"AB",
    "sg:tags":[
        "repairing",
        "automobile"
    ],
    "wof:name":"A-1 Willy's Parts Place Inc",
    "wof:placetype":"venue"
},
  "geometry": {"coordinates":[-113.79022979699999,52.3078994751],"type":"Point"}
}