{
  "type": "Feature",
  "properties": {
    "iso:country":"CA",
    "sg:city":"Mossbank",
    "sg:classifiers":[
        {
            "category":"Travel",
            "subcategory":"Hotels & Motels",
            "type":"Entertainment"
        }
    ],
    "sg:phone":"+1 306 354 2471",
    "sg:postcode":"S0H 3G0",
    "sg:province":"SK",
    "wof:name":"Empress Hotel",
    "wof:placetype":"venue"
},
  "geometry": {"coordinates":[-105.964393616,49.9402542114],"type":"Point"}
}