{
  "type": "Feature",
  "properties": {
    "addr:full":"5213 47 Ave Taber AB T1G 1R5",
    "addr:housenumber":"5213",
    "addr:postcode":"t1g 1r5",
    "addr:street":"47 Ave",
    "iso:country":"CA",
    "sg:address":"5213 47 Ave",
    "sg:city":"Taber",
    "sg:classifiers":[
        {
            "category":"Home & Garden",
            "subcategory":"Building Materials",
            "type":"Retail Goods"
        }
    ],
    "sg:phone":"+1 403 223 4014",
    "sg:postcode":"T1G 1R5",
    "sg:province":"AB",
    "sg:tags":[
        "glass",
        "window",
        "plate"
    ],
    "wof:name":"D & D Glass",
    "wof:placetype":"venue"
},
  "geometry": {"coordinates":[-112.146011,49.783577],"type":"Point"}
}