{
  "type": "Feature",
  "properties": {
    "addr:full":"Chute-Aux-Outardes QC G0H 1C0",
    "addr:postcode":"g0h 1c0",
    "iso:country":"CA",
    "sg:city":"Chute-Aux-Outardes",
    "sg:classifiers":[
        {
            "category":"Personal",
            "subcategory":"Beauty Salon",
            "type":"Services"
        }
    ],
    "sg:phone":"+1 418 567 2550",
    "sg:postcode":"G0H 1C0",
    "sg:province":"QC",
    "wof:name":"Salon Suzie Enr",
    "wof:placetype":"venue"
},
  "geometry": {"coordinates":[-68.393845,49.129738],"type":"Point"}
}