{
  "type": "Feature",
  "properties": {
    "iso:country":"CA",
    "sg:address":"5300 Boul Hebert",
    "sg:city":"Saint-Timothee",
    "sg:classifiers":[
        {
            "category":"Retail",
            "subcategory":"Auto Repair",
            "type":"Services"
        }
    ],
    "sg:phone":"+1 450 373 0221",
    "sg:postcode":"J6S 6H6",
    "sg:province":"QC",
    "sg:tags":[
        "body",
        "automobile",
        "painting"
    ],
    "wof:name":"Urgence Carrosserie Enr",
    "wof:placetype":"venue"
},
  "geometry": {"coordinates":[-74.04039001460001,45.2893829346],"type":"Point"}
}