{
  "type": "Feature",
  "properties": {
    "iso:country":"CA",
    "sg:address":"735 Fourth Line",
    "sg:city":"Oakville",
    "sg:classifiers":[
        {
            "category":"Manufacturing",
            "subcategory":"Building Materials",
            "type":"Manufacturing & Wholesale Goods"
        }
    ],
    "sg:phone":"+1 905 337 5000",
    "sg:postcode":"L6L 5B7",
    "sg:province":"ON",
    "wof:name":"Cgc Inc",
    "wof:placetype":"venue"
},
  "geometry": {"coordinates":[-79.704338,43.435322],"type":"Point"}
}