{
  "type": "Feature",
  "properties": {
    "iso:country":"CA",
    "sg:address":"7 Rue Dumas",
    "sg:city":"Hull",
    "sg:classifiers":[
        {
            "category":"Travel",
            "subcategory":"Campground",
            "type":"Entertainment"
        }
    ],
    "sg:phone":"+1 819 777 6164",
    "sg:postcode":"J8Y 2M4",
    "sg:province":"QC",
    "sg:tags":[
        "camp"
    ],
    "wof:name":"Camp Gatineau",
    "wof:placetype":"venue"
},
  "geometry": {"coordinates":[-75.730507,45.437355],"type":"Point"}
}