{
  "type": "Feature",
  "properties": {
    "iso:country":"CA",
    "sg:address":"30 Elliott Ave",
    "sg:city":"Barrie",
    "sg:classifiers":[
        {
            "category":"Organizations",
            "subcategory":"Religious Organization",
            "type":"Services"
        }
    ],
    "sg:phone":"+1 705 726 7902",
    "sg:postcode":"L4N 4V7",
    "sg:province":"ON",
    "sg:tags":[
        "church"
    ],
    "wof:name":"Barrie Alliance Church",
    "wof:placetype":"venue"
},
  "geometry": {"coordinates":[-79.7164077759,44.375213623],"type":"Point"}
}