{
  "type": "Feature",
  "properties": {
    "addr:full":"58 Wellington St E Toronto ON M5E 1C7",
    "addr:housenumber":"58",
    "addr:postcode":"m5e 1c7",
    "addr:street":"Wellington St E",
    "iso:country":"CA",
    "sg:address":"58 Wellington St E",
    "sg:city":"Toronto",
    "sg:classifiers":[
        {
            "category":"Restaurant",
            "type":"Food & Drink"
        }
    ],
    "sg:phone":"+1 416 862 9191",
    "sg:postcode":"M5E 1C7",
    "sg:province":"ON",
    "wof:name":"Ichiban Sushi",
    "wof:placetype":"venue"
},
  "geometry": {"coordinates":[-79.37453499999999,43.648598],"type":"Point"}
}