{
  "type": "Feature",
  "properties": {
    "addr:full":"Victoria BC V9B 1X1",
    "addr:postcode":"v9b 1x1",
    "iso:country":"CA",
    "sg:city":"Victoria",
    "sg:classifiers":[
        {
            "category":"Professional",
            "subcategory":"Lawyer & Legal Services",
            "type":"Services"
        }
    ],
    "sg:phone":"+1 250 474 1321",
    "sg:postcode":"V9B 1X1",
    "sg:province":"BC",
    "sg:tags":[
        "attorney"
    ],
    "wof:name":"Loster, Gerald J",
    "wof:placetype":"venue"
},
  "geometry": {"coordinates":[-123.364517212,48.428314209],"type":"Point"}
}