{
  "type": "Feature",
  "properties": {
    "addr:full":"13 Canada St Fredericton NB E3A 3Z1",
    "addr:housenumber":"13",
    "addr:postcode":"e3a 3z1",
    "addr:street":"Canada St",
    "iso:country":"CA",
    "sg:address":"13 Canada St",
    "sg:city":"Fredericton",
    "sg:classifiers":[
        {
            "category":"Food & Beverages",
            "subcategory":"Groceries & Convenience Stores",
            "type":"Retail Goods"
        }
    ],
    "sg:phone":"+1 506 460 0000",
    "sg:postcode":"E3A 3Z1",
    "sg:province":"NB",
    "wof:name":"Canada St Variety",
    "wof:placetype":"venue"
},
  "geometry": {"coordinates":[-66.6036453247,45.9661827087],"type":"Point"}
}