{
  "type": "Feature",
  "properties": {
    "addr:full":"Vancouver BC V6Z 2R9",
    "addr:postcode":"v6z 2r9",
    "iso:country":"CA",
    "sg:city":"Vancouver",
    "sg:classifiers":[
        {
            "category":"Real Estate",
            "subcategory":"Real Estate Agent",
            "type":"Services"
        }
    ],
    "sg:phone":"+1 604 893 7131",
    "sg:postcode":"V6Z 2R9",
    "sg:province":"BC",
    "wof:name":"Wall Financial Corp",
    "wof:placetype":"venue"
},
  "geometry": {"coordinates":[-123.12715900000001,49.280205],"type":"Point"}
}