{
  "type": "Feature",
  "properties": {
    "addr:full":"7923 54 St SE Calgary AB T2C 4R7",
    "addr:housenumber":"7923",
    "addr:postcode":"t2c 4r7",
    "addr:street":"54 St Se",
    "iso:country":"CA",
    "sg:address":"7923 54 St SE",
    "sg:city":"Calgary",
    "sg:classifiers":[
        {
            "category":"Manufacturing",
            "subcategory":"Tools & Machinery",
            "type":"Manufacturing & Wholesale Goods"
        }
    ],
    "sg:phone":"+1 403 216 1010",
    "sg:postcode":"T2C 4R7",
    "sg:province":"AB",
    "sg:tags":[
        "equipment",
        "excavating"
    ],
    "wof:name":"Strongco Equipment",
    "wof:placetype":"venue"
},
  "geometry": {"coordinates":[-113.956551,50.982441],"type":"Point"}
}