{
  "type": "Feature",
  "properties": {
    "addr:full":"228 Bradford St Ottawa ON K2B 5Z6",
    "addr:housenumber":"228",
    "addr:postcode":"k2b 5z6",
    "addr:street":"Bradford St",
    "iso:country":"CA",
    "sg:address":"228 Bradford St",
    "sg:city":"Ottawa",
    "sg:classifiers":[
        {
            "category":"Professional",
            "subcategory":"Management & Consulting",
            "type":"Services"
        }
    ],
    "sg:phone":"+1 613 829 2780",
    "sg:postcode":"K2B 5Z6",
    "sg:province":"ON",
    "sg:tags":[
        "consultant",
        "business"
    ],
    "wof:name":"Bridges Agt Consulting",
    "wof:placetype":"venue"
},
  "geometry": {"coordinates":[-75.7986068726,45.366317749],"type":"Point"}
}