{
  "type": "Feature",
  "properties": {
    "addr:full":"56 Ellen St Winnipeg MB R3A 0Z7",
    "addr:housenumber":"56",
    "addr:postcode":"r3a 0z7",
    "addr:street":"Ellen St",
    "iso:country":"CA",
    "sg:address":"56 Ellen St",
    "sg:city":"Winnipeg",
    "sg:classifiers":[
        {
            "category":"Building & Trades",
            "subcategory":"Pest Control",
            "type":"Services"
        }
    ],
    "sg:phone":"+1 204 942 3511",
    "sg:postcode":"R3A 0Z7",
    "sg:province":"MB",
    "sg:tags":[
        "fire",
        "deodorizing",
        "restoration",
        "damage",
        "disinfecting"
    ],
    "wof:name":"Winnipeg Furniture Svc Ltd",
    "wof:placetype":"venue"
},
  "geometry": {"coordinates":[-97.1471328735,49.8988227844],"type":"Point"}
}