{
  "type": "Feature",
  "properties": {
    "addr:full":"715 Southesk St Whitewood SK S0G 5C0",
    "addr:housenumber":"715",
    "addr:postcode":"s0g 5c0",
    "addr:street":"Southesk St",
    "iso:country":"CA",
    "sg:address":"715 Southesk St",
    "sg:city":"Whitewood",
    "sg:classifiers":[
        {
            "category":"Retail",
            "subcategory":"Funeral Services",
            "type":"Services"
        }
    ],
    "sg:phone":"+1 306 735 2335",
    "sg:postcode":"S0G 5C0",
    "sg:province":"SK",
    "sg:tags":[
        "director"
    ],
    "wof:name":"Matthews Funeral Home",
    "wof:placetype":"venue"
},
  "geometry": {"coordinates":[-102.26391599999999,50.329475],"type":"Point"}
}