{
  "type": "Feature",
  "properties": {
    "iso:country":"CA",
    "sg:address":"107 Rue Principale",
    "sg:city":"Lac-Des-Aigles",
    "sg:classifiers":[
        {
            "category":"Freight",
            "type":"Transportation"
        }
    ],
    "sg:phone":"+1 418 779 2133",
    "sg:postcode":"G0K 1V0",
    "sg:province":"QC",
    "sg:tags":[
        "mover"
    ],
    "wof:name":"90076563 Quebec Inc",
    "wof:placetype":"venue"
},
  "geometry": {"coordinates":[-68.67572021479999,47.9930686951],"type":"Point"}
}