{
  "type": "Feature",
  "properties": {
    "addr:full":"314 Main St N Vita MB R0A 2K0",
    "addr:housenumber":"314",
    "addr:postcode":"r0a 2k0",
    "addr:street":"Main St N Vita",
    "iso:country":"CA",
    "sg:address":"314 Main St N",
    "sg:city":"Vita",
    "sg:classifiers":[
        {
            "category":"Organizations",
            "subcategory":"Religious Organization",
            "type":"Services"
        }
    ],
    "sg:phone":"+1 204 425 3896",
    "sg:postcode":"R0A 2K0",
    "sg:province":"MB",
    "sg:tags":[
        "church"
    ],
    "wof:name":"Ukrainian Catholic Parish Ctr",
    "wof:placetype":"venue"
},
  "geometry": {"coordinates":[-96.562881,49.133385],"type":"Point"}
}