{
  "type": "Feature",
  "properties": {
    "addr:full":"3639 Lobsinger Line St Clements ON N0B 2M0",
    "addr:housenumber":"3639",
    "addr:postcode":"n0b 2m0",
    "addr:street":"Lobsinger Line St Clements",
    "iso:country":"CA",
    "sg:address":"3639 Lobsinger Line",
    "sg:city":"St Clements",
    "sg:classifiers":[
        {
            "category":"Education",
            "subcategory":"School",
            "type":"Public Place"
        }
    ],
    "sg:phone":"+1 519 699 5271",
    "sg:postcode":"N0B 2M0",
    "sg:province":"ON",
    "wof:name":"St Clements School",
    "wof:placetype":"venue"
},
  "geometry": {"coordinates":[-80.6539154053,43.5233688354],"type":"Point"}
}