{
  "type": "Feature",
  "properties": {
    "iso:country":"CA",
    "sg:city":"Komoka",
    "sg:classifiers":[
        {
            "category":"Shopping",
            "subcategory":"Discount & Variety Stores",
            "type":"Retail Goods"
        }
    ],
    "sg:phone":"+1 519 641 3480",
    "sg:postcode":"N0L 1R0",
    "sg:province":"ON",
    "wof:name":"Kilworth Variety",
    "wof:placetype":"venue"
},
  "geometry": {"coordinates":[-81.3988494873,42.9614562988],"type":"Point"}
}