{
  "type": "Feature",
  "properties": {
    "addr:full":"333 Boul Pierre-Boursier Chateauguay QC J6J 4Z2",
    "addr:housenumber":"333",
    "addr:postcode":"j6j 4z2",
    "addr:street":"Boul Pierre-Boursier",
    "iso:country":"CA",
    "sg:address":"333 Boul Pierre-Boursier",
    "sg:city":"Chateauguay",
    "sg:classifiers":[
        {
            "category":"Building & Trades",
            "subcategory":"Electrical",
            "type":"Services"
        }
    ],
    "sg:phone":"+1 450 692 9883",
    "sg:postcode":"J6J 4Z2",
    "sg:province":"QC",
    "sg:tags":[
        "electric",
        "contractor"
    ],
    "wof:name":"Ratte Electrique Inc",
    "wof:placetype":"venue"
},
  "geometry": {"coordinates":[-73.700897,45.348976],"type":"Point"}
}