{
  "type": "Feature",
  "properties": {
    "addr:full":"1049 Mccurdy Rd Kelowna BC V1X 2P9",
    "addr:housenumber":"1049",
    "addr:postcode":"v1x 2p9",
    "addr:street":"Mccurdy Rd",
    "iso:country":"CA",
    "sg:address":"1049 Mccurdy Rd",
    "sg:city":"Kelowna",
    "sg:classifiers":[
        {
            "category":"Building & Trades",
            "subcategory":"Construction",
            "type":"Services"
        }
    ],
    "sg:phone":"+1 250 765 1050",
    "sg:postcode":"V1X 2P9",
    "sg:province":"BC",
    "sg:tags":[
        "siding",
        "contractor"
    ],
    "wof:name":"Gentek Building Products Ltd",
    "wof:placetype":"venue"
},
  "geometry": {"coordinates":[-119.407539368,49.9010467529],"type":"Point"}
}