{
  "type": "Feature",
  "properties": {
    "addr:full":"9906 98th Ave Fort Simpson NT X0E 0N0",
    "addr:housenumber":"9906",
    "addr:postcode":"x0e 0n0",
    "addr:street":"98Th Ave Fort Simpson",
    "iso:country":"CA",
    "sg:address":"9906 98th Ave",
    "sg:city":"Fort Simpson",
    "sg:classifiers":[
        {
            "category":"Education",
            "subcategory":"School",
            "type":"Public Place"
        }
    ],
    "sg:phone":"+1 867 695 7326",
    "sg:postcode":"X0E 0N0",
    "sg:province":"NT",
    "wof:name":"Bompas Elementary School",
    "wof:placetype":"venue"
},
  "geometry": {"coordinates":[-121.24025,61.777542],"type":"Point"}
}