{
  "type": "Feature",
  "properties": {
    "addr:full":"4546 Boul Saint-Joseph Saint-Nicephore QC J2A 1B5",
    "addr:housenumber":"4546",
    "addr:postcode":"j2a 1b5",
    "addr:street":"Boul Saint-Joseph Saint-Nicephore",
    "iso:country":"CA",
    "sg:address":"4546 Boul Saint-Joseph",
    "sg:city":"Saint-Nicephore",
    "sg:classifiers":[
        {
            "category":"Sports & Exercise",
            "subcategory":"Bowling",
            "type":"Entertainment"
        }
    ],
    "sg:phone":"+1 819 475 1441",
    "sg:postcode":"J2A 1B5",
    "sg:province":"QC",
    "sg:tags":[
        "center"
    ],
    "wof:name":"Salon DE Quilles L'Impact",
    "wof:placetype":"venue"
},
  "geometry": {"coordinates":[-72.434647,45.840004],"type":"Point"}
}